{
  "type": "Feature",
  "properties": {
    "gn:admin1_code":"15.0",
    "gn:asciiname":"Xinquan",
    "gn:country_code":"CN",
    "gn:dem":2177,
    "gn:feature_class":"P",
    "gn:feature_code":"PPL",
    "gn:name":"Xinquan",
    "gn:population":0,
    "gn:timezone":"Asia/Shanghai",
    "iso:country":"CN",
    "name:zho_x_preferred":[
        "\u65b0\u5708"
    ],
    "wof:name":"Xinquan",
    "wof:placetype":"locality"
},
  "geometry": {"coordinates":[101.515,38.6221],"type":"Point"}
}