{
  "type": "Feature",
  "properties": {
    "gn:admin1_code":"8.0",
    "gn:asciiname":"Ashihe",
    "gn:country_code":"CN",
    "gn:dem":153,
    "gn:feature_class":"P",
    "gn:feature_code":"PPLA4",
    "gn:name":"Ashihe",
    "gn:population":0,
    "gn:timezone":"Asia/Shanghai",
    "iso:country":"CN",
    "name:und_x_variant":[
        "Ashihe Jiedao"
    ],
    "name:zho_x_preferred":[
        "\u963f\u4ec0\u6cb3"
    ],
    "name:zho_x_variant":[
        "\u963f\u4ec0\u6cb3\u8857\u9053"
    ],
    "wof:name":"Ashihe",
    "wof:placetype":"locality"
},
  "geometry": {"coordinates":[126.97369999999999,45.5358],"type":"Point"}
}