{
  "type": "Feature",
  "properties": {
    "gn:admin1_code":"1.0",
    "gn:asciiname":"Dengyingcun",
    "gn:country_code":"CN",
    "gn:dem":32,
    "gn:feature_class":"P",
    "gn:feature_code":"PPL",
    "gn:name":"Dengyingcun",
    "gn:population":0,
    "gn:timezone":"Asia/Shanghai",
    "iso:country":"CN",
    "name:zho_x_preferred":[
        "\u9093\u90e2\u6751"
    ],
    "wof:name":"Dengyingcun",
    "wof:placetype":"locality"
},
  "geometry": {"coordinates":[115.77272000000001,32.64651],"type":"Point"}
}