{
  "type": "Feature",
  "properties": {
    "gn:admin1_code":"18",
    "gn:asciiname":"Dashan",
    "gn:country_code":"CN",
    "gn:dem":1406,
    "gn:feature_class":"P",
    "gn:feature_code":"PPL",
    "gn:name":"Dashan",
    "gn:population":0,
    "gn:timezone":"Asia/Shanghai",
    "iso:country":"CN",
    "name:zho_x_preferred":[
        "\u5927\u5c71"
    ],
    "wof:name":"Dashan",
    "wof:placetype":"locality"
},
  "geometry": {"coordinates":[105.071,25.2239],"type":"Point"}
}