{
  "type": "Feature",
  "properties": {
    "gn:admin1_code":"4.0",
    "gn:asciiname":"Houchongying",
    "gn:country_code":"CN",
    "gn:dem":41,
    "gn:feature_class":"P",
    "gn:feature_code":"PPL",
    "gn:name":"Houchongying",
    "gn:population":0,
    "gn:timezone":"Asia/Shanghai",
    "iso:country":"CN",
    "name:zho_x_preferred":[
        "\u540e\u51b2\u8425"
    ],
    "wof:name":"Houchongying",
    "wof:placetype":"locality"
},
  "geometry": {"coordinates":[118.66262999999999,32.76524000000001],"type":"Point"}
}