{
  "type": "Feature",
  "properties": {
    "gn:admin1_code":"32.0",
    "gn:asciiname":"Midi",
    "gn:country_code":"CN",
    "gn:dem":3564,
    "gn:feature_class":"P",
    "gn:feature_code":"PPL",
    "gn:name":"Midi",
    "gn:population":0,
    "gn:timezone":"Asia/Shanghai",
    "iso:country":"CN",
    "name:zho_x_preferred":[
        "\u7c73\u8fea"
    ],
    "wof:name":"Midi",
    "wof:placetype":"locality"
},
  "geometry": {"coordinates":[100.446,28.7909],"type":"Point"}
}