{
  "type": "Feature",
  "properties": {
    "gn:admin1_code":"26.0",
    "gn:asciiname":"Niutiwo",
    "gn:country_code":"CN",
    "gn:dem":1075,
    "gn:feature_class":"P",
    "gn:feature_code":"PPL",
    "gn:name":"Niutiwo",
    "gn:population":0,
    "gn:timezone":"Asia/Shanghai",
    "iso:country":"CN",
    "name:zho_x_preferred":[
        "\u725b\u8e44\u7a9d"
    ],
    "wof:name":"Niutiwo",
    "wof:placetype":"locality"
},
  "geometry": {"coordinates":[108.79478,35.08023],"type":"Point"}
}