{
  "type": "Feature",
  "properties": {
    "gn:admin1_code":"32.0",
    "gn:asciiname":"Zirancun",
    "gn:country_code":"CN",
    "gn:dem":836,
    "gn:feature_class":"P",
    "gn:feature_code":"PPL",
    "gn:name":"Zirancun",
    "gn:population":0,
    "gn:timezone":"Asia/Shanghai",
    "iso:country":"CN",
    "name:zho_x_preferred":[
        "\u81ea\u7136\u6751"
    ],
    "wof:name":"Zirancun",
    "wof:placetype":"locality"
},
  "geometry": {"coordinates":[105.873,32.7595],"type":"Point"}
}