{
  "type": "Feature",
  "properties": {
    "gn:admin1_code":"32.0",
    "gn:asciiname":"Hongfu",
    "gn:country_code":"CN",
    "gn:dem":337,
    "gn:feature_class":"P",
    "gn:feature_code":"PPL",
    "gn:name":"Hongfu",
    "gn:population":0,
    "gn:timezone":"Asia/Shanghai",
    "iso:country":"CN",
    "name:zho_x_preferred":[
        "\u6d2a\u798f"
    ],
    "wof:name":"Hongfu",
    "wof:placetype":"locality"
},
  "geometry": {"coordinates":[107.29900000000001,30.9202],"type":"Point"}
}