{
  "type": "Feature",
  "properties": {
    "gn:admin1_code":"30.0",
    "gn:asciiname":"Cancheng",
    "gn:country_code":"CN",
    "gn:dem":38,
    "gn:feature_class":"P",
    "gn:feature_code":"PPL",
    "gn:name":"Cancheng",
    "gn:population":0,
    "gn:timezone":"Asia/Shanghai",
    "iso:country":"CN",
    "name:zho_x_preferred":[
        "\u53c2\u57ce"
    ],
    "wof:name":"Cancheng",
    "wof:placetype":"locality"
},
  "geometry": {"coordinates":[115.54243999999998,23.20283],"type":"Point"}
}