{
  "type": "Feature",
  "properties": {
    "gn:admin1_code":"25",
    "gn:asciiname":"Nanchahe",
    "gn:country_code":"CN",
    "gn:dem":8,
    "gn:feature_class":"P",
    "gn:feature_code":"PPL",
    "gn:name":"Nanchahe",
    "gn:population":0,
    "gn:timezone":"Asia/Shanghai",
    "iso:country":"CN",
    "name:zho_x_preferred":[
        "\u5357\u5c94\u6cb3"
    ],
    "wof:name":"Nanchahe",
    "wof:placetype":"locality"
},
  "geometry": {"coordinates":[118.854,37.0504],"type":"Point"}
}