{
  "type": "Feature",
  "properties": {
    "gn:admin1_code":"04",
    "gn:asciiname":"Nancheng",
    "gn:country_code":"CN",
    "gn:dem":6,
    "gn:feature_class":"P",
    "gn:feature_code":"PPLA4",
    "gn:name":"Nancheng",
    "gn:population":0,
    "gn:timezone":"Asia/Shanghai",
    "iso:country":"CN",
    "name:ceb_x_preferred":[
        "Nancheng"
    ],
    "name:deu_x_preferred":[
        "Nancheng"
    ],
    "name:fra_x_preferred":[
        "Nancheng"
    ],
    "name:nld_x_preferred":[
        "Nancheng"
    ],
    "name:und_x_variant":[
        "\u5357\u57ce",
        "Nancheng Zhen",
        "\u5357\u57ce\u9547"
    ],
    "wof:name":"Nancheng",
    "wof:placetype":"locality"
},
  "geometry": {"coordinates":[119.22417,34.56167],"type":"Point"}
}