{
  "type": "Feature",
  "properties": {
    "gn:admin1_code":"9.0",
    "gn:asciiname":"Ranfanggou",
    "gn:country_code":"CN",
    "gn:dem":817,
    "gn:feature_class":"P",
    "gn:feature_code":"PPL",
    "gn:name":"Ranfanggou",
    "gn:population":0,
    "gn:timezone":"Asia/Shanghai",
    "iso:country":"CN",
    "name:zho_x_preferred":[
        "\u67d3\u574a\u6c9f"
    ],
    "wof:name":"Ranfanggou",
    "wof:placetype":"locality"
},
  "geometry": {"coordinates":[111.71075,34.05367],"type":"Point"}
}