{
  "type": "Feature",
  "properties": {
    "gn:admin1_code":"26.0",
    "gn:asciiname":"Xinmiao",
    "gn:cc2":"CN",
    "gn:country_code":"CN",
    "gn:dem":619,
    "gn:feature_class":"P",
    "gn:feature_code":"PPL",
    "gn:name":"Xinmiao",
    "gn:population":0,
    "gn:timezone":"Asia/Shanghai",
    "iso:country":"CN",
    "name:und_x_variant":[
        "Hsin-miao",
        "Xinmiao"
    ],
    "wof:name":"Xinmiao",
    "wof:placetype":"locality"
},
  "geometry": {"coordinates":[111.00111,33.37972],"type":"Point"}
}