{
  "type": "Feature",
  "properties": {
    "gn:admin1_code":"1.0",
    "gn:asciiname":"Zhifengshancun",
    "gn:country_code":"CN",
    "gn:dem":371,
    "gn:feature_class":"P",
    "gn:feature_code":"PPL",
    "gn:name":"Zhifengshancun",
    "gn:population":0,
    "gn:timezone":"Asia/Shanghai",
    "iso:country":"CN",
    "name:zho_x_preferred":[
        "\u6307\u5c01\u5c71\u6751"
    ],
    "wof:name":"Zhifengshancun",
    "wof:placetype":"locality"
},
  "geometry": {"coordinates":[116.47192,31.36543],"type":"Point"}
}