{
  "type": "Feature",
  "properties": {
    "gn:admin1_code":"11.0",
    "gn:asciiname":"Huang'en",
    "gn:country_code":"CN",
    "gn:dem":555,
    "gn:feature_class":"P",
    "gn:feature_code":"PPL",
    "gn:name":"Huang\u2019en",
    "gn:population":0,
    "gn:timezone":"Asia/Shanghai",
    "iso:country":"CN",
    "name:und_x_variant":[
        "Huang\u2019en"
    ],
    "name:zho_x_preferred":[
        "\u7687\u6069"
    ],
    "wof:name":"Huang'en",
    "wof:placetype":"locality"
},
  "geometry": {"coordinates":[110.50609,27.59545],"type":"Point"}
}