{
  "type": "Feature",
  "properties": {
    "gn:admin1_code":"2.0",
    "gn:asciiname":"Zhaqiao",
    "gn:country_code":"CN",
    "gn:dem":169,
    "gn:feature_class":"P",
    "gn:feature_code":"PPL",
    "gn:name":"Zhaqiao",
    "gn:population":0,
    "gn:timezone":"Asia/Shanghai",
    "iso:country":"CN",
    "name:zho_x_preferred":[
        "\u6805\u6865"
    ],
    "wof:name":"Zhaqiao",
    "wof:placetype":"locality"
},
  "geometry": {"coordinates":[120.51694000000001,27.41365],"type":"Point"}
}