{
  "type": "Feature",
  "properties": {
    "gn:admin1_code":"29.0",
    "gn:asciiname":"Duoyishu",
    "gn:country_code":"CN",
    "gn:dem":1973,
    "gn:feature_class":"P",
    "gn:feature_code":"PPL",
    "gn:name":"Duoyishu",
    "gn:population":0,
    "gn:timezone":"Asia/Shanghai",
    "iso:country":"CN",
    "name:zho_x_preferred":[
        "\u591a\u8863\u6811"
    ],
    "wof:name":"Duoyishu",
    "wof:placetype":"locality"
},
  "geometry": {"coordinates":[103.98699999999999,23.331],"type":"Point"}
}