{
  "type": "Feature",
  "properties": {
    "gn:admin1_code":"21.0",
    "gn:asciiname":"Zhanghugou",
    "gn:country_code":"CN",
    "gn:dem":1605,
    "gn:feature_class":"P",
    "gn:feature_code":"PPL",
    "gn:name":"Zhanghugou",
    "gn:population":0,
    "gn:timezone":"Asia/Shanghai",
    "iso:country":"CN",
    "name:zho_x_preferred":[
        "\u5f20\u864e\u6c9f"
    ],
    "wof:name":"Zhanghugou",
    "wof:placetype":"locality"
},
  "geometry": {"coordinates":[106.83,35.8911],"type":"Point"}
}