{
  "type": "Feature",
  "properties": {
    "gn:admin1_code":"22",
    "gn:asciiname":"Yangshudi",
    "gn:country_code":"CN",
    "gn:dem":677,
    "gn:feature_class":"P",
    "gn:feature_code":"PPL",
    "gn:name":"Yangshudi",
    "gn:population":0,
    "gn:timezone":"Asia/Shanghai",
    "iso:country":"CN",
    "name:zho_x_preferred":[
        "\u6768\u6811\u5e95"
    ],
    "wof:name":"Yangshudi",
    "wof:placetype":"locality"
},
  "geometry": {"coordinates":[116.51559,40.54021],"type":"Point"}
}