{
  "type": "Feature",
  "properties": {
    "gn:admin1_code":"30",
    "gn:asciiname":"Pinggangxu",
    "gn:country_code":"CN",
    "gn:dem":49,
    "gn:feature_class":"P",
    "gn:feature_code":"PPL",
    "gn:name":"Pinggangxu",
    "gn:population":0,
    "gn:timezone":"Asia/Shanghai",
    "iso:country":"CN",
    "name:und_x_variant":[
        "P\u2019ing-kang-hs\u00fc",
        "Pinggangxu"
    ],
    "name:zho_x_preferred":[
        "\u5e73\u5c97\u5729"
    ],
    "wof:name":"Pinggangxu",
    "wof:placetype":"locality"
},
  "geometry": {"coordinates":[111.43633,23.32366],"type":"Point"}
}