{
  "type": "Feature",
  "properties": {
    "gn:admin1_code":"15.0",
    "gn:asciiname":"Huangchang",
    "gn:country_code":"CN",
    "gn:dem":1066,
    "gn:feature_class":"P",
    "gn:feature_code":"PPL",
    "gn:name":"Huangchang",
    "gn:population":0,
    "gn:timezone":"Asia/Shanghai",
    "iso:country":"CN",
    "name:zho_x_preferred":[
        "\u8352\u573a"
    ],
    "wof:name":"Huangchang",
    "wof:placetype":"locality"
},
  "geometry": {"coordinates":[107.33499999999999,35.217],"type":"Point"}
}