{
  "type": "Feature",
  "properties": {
    "gn:admin1_code":"15.0",
    "gn:asciiname":"Erbandi",
    "gn:country_code":"CN",
    "gn:dem":1836,
    "gn:feature_class":"P",
    "gn:feature_code":"PPL",
    "gn:name":"Erbandi",
    "gn:population":0,
    "gn:timezone":"Asia/Shanghai",
    "iso:country":"CN",
    "name:zho_x_preferred":[
        "\u4e8c\u73ed\u5730"
    ],
    "wof:name":"Erbandi",
    "wof:placetype":"locality"
},
  "geometry": {"coordinates":[99.12949999999999,39.2793],"type":"Point"}
}