{
  "type": "Feature",
  "properties": {
    "gn:admin1_code":"32.0",
    "gn:asciiname":"Xiao'anzhen",
    "gn:country_code":"CN",
    "gn:dem":284,
    "gn:feature_class":"P",
    "gn:feature_code":"PPL",
    "gn:name":"Xiao\u2019anzhen",
    "gn:population":0,
    "gn:timezone":"Asia/Shanghai",
    "iso:country":"CN",
    "name:und_x_variant":[
        "Xiao\u2019anzhen"
    ],
    "name:zho_x_preferred":[
        "\u5c0f\u5b89\u9547"
    ],
    "wof:name":"Xiao'anzhen",
    "wof:placetype":"locality"
},
  "geometry": {"coordinates":[105.426,30.1707],"type":"Point"}
}