{
  "type": "Feature",
  "properties": {
    "gn:admin1_code":"15.0",
    "gn:asciiname":"Huangjiadaping",
    "gn:country_code":"CN",
    "gn:dem":2326,
    "gn:feature_class":"P",
    "gn:feature_code":"PPL",
    "gn:name":"Huangjiadaping",
    "gn:population":0,
    "gn:timezone":"Asia/Shanghai",
    "iso:country":"CN",
    "name:und_x_variant":[
        "\u9ec4\u5bb6\u5927\u576a"
    ],
    "wof:name":"Huangjiadaping",
    "wof:placetype":"locality"
},
  "geometry": {"coordinates":[104.77623,34.54373],"type":"Point"}
}