{
  "type": "Feature",
  "properties": {
    "gn:admin1_code":"10",
    "gn:asciiname":"Fanzhuang",
    "gn:cc2":"CN",
    "gn:country_code":"CN",
    "gn:dem":25,
    "gn:feature_class":"P",
    "gn:feature_code":"PPL",
    "gn:name":"Fanzhuang",
    "gn:population":0,
    "gn:timezone":"Asia/Shanghai",
    "iso:country":"CN",
    "name:und_x_variant":[
        "Fanjiazhuang",
        "Fan-chia-chuang",
        "Fanzhuang"
    ],
    "wof:name":"Fanzhuang",
    "wof:placetype":"locality"
},
  "geometry": {"coordinates":[115.44194,37.65222],"type":"Point"}
}