{
  "type": "Feature",
  "properties": {
    "gn:admin1_code":"16",
    "gn:asciiname":"Maozhu'an",
    "gn:country_code":"CN",
    "gn:dem":811,
    "gn:feature_class":"P",
    "gn:feature_code":"PPL",
    "gn:name":"Maozhu\u2019an",
    "gn:population":0,
    "gn:timezone":"Asia/Shanghai",
    "iso:country":"CN",
    "name:und_x_variant":[
        "Maozhu\u2019an"
    ],
    "name:zho_x_preferred":[
        "\u6bdb\u7af9\u5b89"
    ],
    "wof:name":"Maozhu'an",
    "wof:placetype":"locality"
},
  "geometry": {"coordinates":[110.70099999999999,26.0338],"type":"Point"}
}