{
  "type": "Feature",
  "properties": {
    "gn:admin1_code":"26",
    "gn:asciiname":"Moziqiao",
    "gn:country_code":"CN",
    "gn:dem":410,
    "gn:feature_class":"P",
    "gn:feature_code":"PPL",
    "gn:name":"Moziqiao",
    "gn:population":0,
    "gn:timezone":"Asia/Shanghai",
    "iso:country":"CN",
    "name:und_x_variant":[
        "\u6469\u5b50\u6865"
    ],
    "name:zho_x_preferred":[
        "\u6469\u5b50\u6865"
    ],
    "wof:name":"Moziqiao",
    "wof:placetype":"locality"
},
  "geometry": {"coordinates":[108.96583,34.54028],"type":"Point"}
}