{
  "type": "Feature",
  "properties": {
    "gn:admin1_code":"8.0",
    "gn:asciiname":"Hou Wopeng",
    "gn:country_code":"CN",
    "gn:dem":308,
    "gn:feature_class":"P",
    "gn:feature_code":"PPL",
    "gn:name":"Hou Wopeng",
    "gn:population":0,
    "gn:timezone":"Asia/Shanghai",
    "iso:country":"CN",
    "name:zho_x_preferred":[
        "\u540e\u7a9d\u68da"
    ],
    "wof:name":"Hou Wopeng",
    "wof:placetype":"locality"
},
  "geometry": {"coordinates":[126.20123999999998,47.92645],"type":"Point"}
}