{
  "type": "Feature",
  "properties": {
    "gn:admin1_code":"19.0",
    "gn:asciiname":"Mantougou",
    "gn:country_code":"CN",
    "gn:dem":329,
    "gn:feature_class":"P",
    "gn:feature_code":"PPL",
    "gn:name":"Mantougou",
    "gn:population":0,
    "gn:timezone":"Asia/Shanghai",
    "iso:country":"CN",
    "name:und_x_variant":[
        "\u9992\u5934\u6c9f"
    ],
    "name:zho_x_preferred":[
        "\u9992\u5934\u6c9f"
    ],
    "wof:name":"Mantougou",
    "wof:placetype":"locality"
},
  "geometry": {"coordinates":[120.58922,41.8967],"type":"Point"}
}