{
  "type": "Feature",
  "properties": {
    "gn:admin1_code":"29",
    "gn:asciiname":"Yuetingzhai",
    "gn:country_code":"CN",
    "gn:dem":1467,
    "gn:feature_class":"P",
    "gn:feature_code":"PPL",
    "gn:name":"Yuetingzhai",
    "gn:population":0,
    "gn:timezone":"Asia/Shanghai",
    "iso:country":"CN",
    "name:zho_x_preferred":[
        "\u6708\u4ead\u5be8"
    ],
    "wof:name":"Yuetingzhai",
    "wof:placetype":"locality"
},
  "geometry": {"coordinates":[103.306,24.1223],"type":"Point"}
}