{
  "type": "Feature",
  "properties": {
    "gn:admin1_code":"15.0",
    "gn:asciiname":"Maolakeng",
    "gn:country_code":"CN",
    "gn:dem":2183,
    "gn:feature_class":"P",
    "gn:feature_code":"PPL",
    "gn:name":"Maolakeng",
    "gn:population":0,
    "gn:timezone":"Asia/Shanghai",
    "iso:country":"CN",
    "name:zho_x_preferred":[
        "\u6bdb\u8721\u5751"
    ],
    "wof:name":"Maolakeng",
    "wof:placetype":"locality"
},
  "geometry": {"coordinates":[104.435,35.0095],"type":"Point"}
}