{
  "type": "Feature",
  "properties": {
    "gn:admin1_code":"31.0",
    "gn:asciiname":"Xinsidui",
    "gn:country_code":"CN",
    "gn:dem":249,
    "gn:feature_class":"P",
    "gn:feature_code":"PPLF",
    "gn:name":"Xinsidui",
    "gn:population":0,
    "gn:timezone":"Asia/Shanghai",
    "iso:country":"CN",
    "name:und_x_variant":[
        "\u65b0\u56db\u961f"
    ],
    "wof:name":"Xinsidui",
    "wof:placetype":"locality"
},
  "geometry": {"coordinates":[110.05794,18.74543],"type":"Point"}
}