{
  "type": "Feature",
  "properties": {
    "gn:admin1_code":"16.0",
    "gn:asciiname":"Lidao",
    "gn:country_code":"CN",
    "gn:dem":70,
    "gn:feature_class":"P",
    "gn:feature_code":"PPL",
    "gn:name":"Lidao",
    "gn:population":0,
    "gn:timezone":"Asia/Shanghai",
    "iso:country":"CN",
    "name:zho_x_preferred":[
        "\u5229\u9053"
    ],
    "name:zho_x_variant":[
        "\u4fda\u5c9b\u9547"
    ],
    "wof:name":"Lidao",
    "wof:placetype":"locality"
},
  "geometry": {"coordinates":[110.479,23.7973],"type":"Point"}
}