{
  "type": "Feature",
  "properties": {
    "gn:admin1_code":"32.0",
    "gn:asciiname":"Luxiangzi",
    "gn:country_code":"CN",
    "gn:dem":475,
    "gn:feature_class":"P",
    "gn:feature_code":"PPL",
    "gn:name":"Luxiangzi",
    "gn:population":0,
    "gn:timezone":"Asia/Shanghai",
    "iso:country":"CN",
    "name:zho_x_preferred":[
        "\u9c81\u5df7\u5b50"
    ],
    "wof:name":"Luxiangzi",
    "wof:placetype":"locality"
},
  "geometry": {"coordinates":[103.697,30.4186],"type":"Point"}
}