{
  "type": "Feature",
  "properties": {
    "gn:admin1_code":"1.0",
    "gn:asciiname":"Chezhuangcun",
    "gn:country_code":"CN",
    "gn:dem":46,
    "gn:feature_class":"P",
    "gn:feature_code":"PPL",
    "gn:name":"Chezhuangcun",
    "gn:population":0,
    "gn:timezone":"Asia/Shanghai",
    "iso:country":"CN",
    "name:zho_x_preferred":[
        "\u8f66\u5e84\u6751"
    ],
    "wof:name":"Chezhuangcun",
    "wof:placetype":"locality"
},
  "geometry": {"coordinates":[117.77512,32.87495],"type":"Point"}
}