{
  "type": "Feature",
  "properties": {
    "gn:admin1_code":"4.0",
    "gn:asciiname":"Qigoucun",
    "gn:country_code":"CN",
    "gn:dem":30,
    "gn:feature_class":"P",
    "gn:feature_code":"PPL",
    "gn:name":"Qigoucun",
    "gn:population":0,
    "gn:timezone":"Asia/Shanghai",
    "iso:country":"CN",
    "name:zho_x_preferred":[
        "\u621a\u6c9f\u6751"
    ],
    "wof:name":"Qigoucun",
    "wof:placetype":"locality"
},
  "geometry": {"coordinates":[118.24048000000001,34.19232],"type":"Point"}
}