{
  "type": "Feature",
  "properties": {
    "gn:admin1_code":"25",
    "gn:asciiname":"Dawujia",
    "gn:country_code":"CN",
    "gn:dem":159,
    "gn:feature_class":"P",
    "gn:feature_code":"PPL",
    "gn:name":"Dawujia",
    "gn:population":0,
    "gn:timezone":"Asia/Shanghai",
    "iso:country":"CN",
    "name:zho_x_preferred":[
        "\u5927\u5434\u5bb6"
    ],
    "wof:name":"Dawujia",
    "wof:placetype":"locality"
},
  "geometry": {"coordinates":[120.419,37.2407],"type":"Point"}
}