{
  "type": "Feature",
  "properties": {
    "gn:admin1_code":"10.0",
    "gn:asciiname":"Jing'ergou",
    "gn:country_code":"CN",
    "gn:dem":403,
    "gn:feature_class":"P",
    "gn:feature_code":"PPL",
    "gn:name":"Jing\u2019ergou",
    "gn:population":0,
    "gn:timezone":"Asia/Shanghai",
    "iso:country":"CN",
    "name:und_x_variant":[
        "Jing\u2019ergou",
        "\u4e95\u5c14\u6c9f"
    ],
    "wof:name":"Jing'ergou",
    "wof:placetype":"locality"
},
  "geometry": {"coordinates":[114.47631,38.93591],"type":"Point"}
}