{
  "type": "Feature",
  "properties": {
    "gn:admin1_code":"32.0",
    "gn:asciiname":"Xiling",
    "gn:country_code":"CN",
    "gn:dem":1068,
    "gn:feature_class":"P",
    "gn:feature_code":"PPL",
    "gn:name":"Xiling",
    "gn:population":0,
    "gn:timezone":"Asia/Shanghai",
    "iso:country":"CN",
    "name:und_x_variant":[
        "\u897f\u9675"
    ],
    "wof:name":"Xiling",
    "wof:placetype":"locality"
},
  "geometry": {"coordinates":[106.32505,32.61574],"type":"Point"}
}