{
  "type": "Feature",
  "properties": {
    "gn:admin1_code":"11",
    "gn:asciiname":"Shibanchong",
    "gn:country_code":"CN",
    "gn:dem":144,
    "gn:feature_class":"P",
    "gn:feature_code":"PPL",
    "gn:name":"Shibanchong",
    "gn:population":0,
    "gn:timezone":"Asia/Shanghai",
    "iso:country":"CN",
    "name:zho_x_preferred":[
        "\u77f3\u677f\u51b2"
    ],
    "wof:name":"Shibanchong",
    "wof:placetype":"locality"
},
  "geometry": {"coordinates":[112.23529000000001,27.42678],"type":"Point"}
}