{
  "type": "Feature",
  "properties": {
    "gn:admin1_code":"18",
    "gn:asciiname":"Tianjia Wuji",
    "gn:country_code":"CN",
    "gn:dem":1047,
    "gn:feature_class":"P",
    "gn:feature_code":"PPL",
    "gn:name":"Tianjia Wuji",
    "gn:population":0,
    "gn:timezone":"Asia/Shanghai",
    "iso:country":"CN",
    "name:zho_x_preferred":[
        "\u7530\u5bb6\u5c4b\u57fa"
    ],
    "wof:name":"Tianjia Wuji",
    "wof:placetype":"locality"
},
  "geometry": {"coordinates":[107.295,27.794],"type":"Point"}
}