{
  "type": "Feature",
  "properties": {
    "gn:admin1_code":"1.0",
    "gn:asciiname":"Zhifengcun",
    "gn:country_code":"CN",
    "gn:dem":75,
    "gn:feature_class":"P",
    "gn:feature_code":"PPL",
    "gn:name":"Zhifengcun",
    "gn:population":0,
    "gn:timezone":"Asia/Shanghai",
    "iso:country":"CN",
    "name:zho_x_preferred":[
        "\u8dbe\u51e4\u6751"
    ],
    "wof:name":"Zhifengcun",
    "wof:placetype":"locality"
},
  "geometry": {"coordinates":[116.15271,30.35712],"type":"Point"}
}