{
  "type": "Feature",
  "properties": {
    "gn:admin1_code":"15.0",
    "gn:asciiname":"Qiujiashan",
    "gn:country_code":"CN",
    "gn:dem":1861,
    "gn:feature_class":"P",
    "gn:feature_code":"PPL",
    "gn:name":"Qiujiashan",
    "gn:population":0,
    "gn:timezone":"Asia/Shanghai",
    "iso:country":"CN",
    "name:zho_x_preferred":[
        "\u4e18\u5bb6\u5c71"
    ],
    "wof:name":"Qiujiashan",
    "wof:placetype":"locality"
},
  "geometry": {"coordinates":[104.599,37.0909],"type":"Point"}
}