{
  "type": "Feature",
  "properties": {
    "gn:admin1_code":"26.0",
    "gn:asciiname":"Mifengyucun",
    "gn:country_code":"CN",
    "gn:dem":1055,
    "gn:feature_class":"P",
    "gn:feature_code":"PPL",
    "gn:name":"Mifengyucun",
    "gn:population":0,
    "gn:timezone":"Asia/Shanghai",
    "iso:country":"CN",
    "name:zho_x_preferred":[
        "\u871c\u8702\u5cea\u6751"
    ],
    "wof:name":"Mifengyucun",
    "wof:placetype":"locality"
},
  "geometry": {"coordinates":[109.76925,37.19673],"type":"Point"}
}