{
  "type": "Feature",
  "properties": {
    "gn:admin1_code":"14.0",
    "gn:asciiname":"Daqiongda",
    "gn:country_code":"CN",
    "gn:dem":4141,
    "gn:feature_class":"P",
    "gn:feature_code":"PPL",
    "gn:name":"Daqiongda",
    "gn:population":0,
    "gn:timezone":"Asia/Urumqi",
    "iso:country":"CN",
    "name:zho_x_preferred":[
        "\u8fbe\u743c\u8fbe"
    ],
    "wof:name":"Daqiongda",
    "wof:placetype":"locality"
},
  "geometry": {"coordinates":[97.62151,32.00492],"type":"Point"}
}