{
  "type": "Feature",
  "properties": {
    "gn:admin1_code":"16.0",
    "gn:asciiname":"Nabatun",
    "gn:country_code":"CN",
    "gn:dem":722,
    "gn:feature_class":"P",
    "gn:feature_code":"PPL",
    "gn:name":"Nabatun",
    "gn:population":0,
    "gn:timezone":"Asia/Shanghai",
    "iso:country":"CN",
    "name:zho_x_preferred":[
        "\u7eb3\u5df4\u5c6f"
    ],
    "wof:name":"Nabatun",
    "wof:placetype":"locality"
},
  "geometry": {"coordinates":[107.527,24.5441],"type":"Point"}
}