{
  "type": "Feature",
  "properties": {
    "gn:admin1_code":"30",
    "gn:asciiname":"Aoxia",
    "gn:country_code":"CN",
    "gn:dem":137,
    "gn:feature_class":"P",
    "gn:feature_code":"PPL",
    "gn:name":"Aoxia",
    "gn:population":0,
    "gn:timezone":"Asia/Shanghai",
    "iso:country":"CN",
    "name:zho_x_preferred":[
        "\u51f9\u4e0b"
    ],
    "wof:name":"Aoxia",
    "wof:placetype":"locality"
},
  "geometry": {"coordinates":[116.27717,24.53191],"type":"Point"}
}