{
  "type": "Feature",
  "properties": {
    "gn:admin1_code":"11",
    "gn:asciiname":"Cuiping",
    "gn:country_code":"CN",
    "gn:dem":267,
    "gn:feature_class":"P",
    "gn:feature_code":"PPLA4",
    "gn:name":"Cuiping",
    "gn:population":0,
    "gn:timezone":"Asia/Shanghai",
    "iso:country":"CN",
    "name:und_x_variant":[
        "Xiatang",
        "Cuiping Xiang"
    ],
    "name:zho_x_preferred":[
        "\u5d14\u576a"
    ],
    "name:zho_x_variant":[
        "\u5d14\u576a\u4e61"
    ],
    "wof:name":"Cuiping",
    "wof:placetype":"locality"
},
  "geometry": {"coordinates":[112.09975,28.24086],"type":"Point"}
}