{
  "type": "Feature",
  "properties": {
    "gn:admin1_code":"2.0",
    "gn:asciiname":"Fangjiadun",
    "gn:country_code":"CN",
    "gn:dem":8,
    "gn:feature_class":"P",
    "gn:feature_code":"PPL",
    "gn:name":"Fangjiadun",
    "gn:population":0,
    "gn:timezone":"Asia/Shanghai",
    "iso:country":"CN",
    "name:und_x_variant":[
        "\u65b9\u5bb6\u58a9"
    ],
    "wof:name":"Fangjiadun",
    "wof:placetype":"locality"
},
  "geometry": {"coordinates":[120.03287,30.57445],"type":"Point"}
}