{
  "type": "Feature",
  "properties": {
    "gn:admin1_code":"26.0",
    "gn:asciiname":"Houhuitou",
    "gn:country_code":"CN",
    "gn:dem":1498,
    "gn:feature_class":"P",
    "gn:feature_code":"PPL",
    "gn:name":"Houhuitou",
    "gn:population":0,
    "gn:timezone":"Asia/Shanghai",
    "iso:country":"CN",
    "name:zho_x_preferred":[
        "\u540e\u56de\u5934"
    ],
    "wof:name":"Houhuitou",
    "wof:placetype":"locality"
},
  "geometry": {"coordinates":[108.45715,35.08692],"type":"Point"}
}