{
  "type": "Feature",
  "properties": {
    "gn:admin1_code":"16.0",
    "gn:asciiname":"Jiaji",
    "gn:country_code":"CN",
    "gn:dem":404,
    "gn:feature_class":"P",
    "gn:feature_code":"PPL",
    "gn:name":"Jiaji",
    "gn:population":0,
    "gn:timezone":"Asia/Shanghai",
    "iso:country":"CN",
    "name:zho_x_preferred":[
        "\u52a0\u5409"
    ],
    "wof:name":"Jiaji",
    "wof:placetype":"locality"
},
  "geometry": {"coordinates":[108.413,23.9493],"type":"Point"}
}