{
  "type": "Feature",
  "properties": {
    "gn:admin1_code":"8.0",
    "gn:asciiname":"Chunguangcun",
    "gn:country_code":"CN",
    "gn:dem":220,
    "gn:feature_class":"P",
    "gn:feature_code":"PPL",
    "gn:name":"Chunguangcun",
    "gn:population":0,
    "gn:timezone":"Asia/Shanghai",
    "iso:country":"CN",
    "name:zho_x_preferred":[
        "\u6625\u5149\u6751"
    ],
    "wof:name":"Chunguangcun",
    "wof:placetype":"locality"
},
  "geometry": {"coordinates":[127.88343999999999,46.85914],"type":"Point"}
}