{
  "type": "Feature",
  "properties": {
    "gn:admin1_code":"4.0",
    "gn:asciiname":"Louloucun",
    "gn:country_code":"CN",
    "gn:dem":28,
    "gn:feature_class":"P",
    "gn:feature_code":"PPL",
    "gn:name":"Louloucun",
    "gn:population":0,
    "gn:timezone":"Asia/Shanghai",
    "iso:country":"CN",
    "name:zho_x_preferred":[
        "\u5a04\u697c\u6751"
    ],
    "wof:name":"Louloucun",
    "wof:placetype":"locality"
},
  "geometry": {"coordinates":[117.76849,34.22229],"type":"Point"}
}