{
  "type": "Feature",
  "properties": {
    "gn:admin1_code":"19.0",
    "gn:asciiname":"Chenwushitun",
    "gn:country_code":"CN",
    "gn:dem":78,
    "gn:feature_class":"P",
    "gn:feature_code":"PPL",
    "gn:name":"Chenwushitun",
    "gn:population":0,
    "gn:timezone":"Asia/Shanghai",
    "iso:country":"CN",
    "name:und_x_variant":[
        "\u9648\u4e94\u5341\u5c6f"
    ],
    "name:zho_x_preferred":[
        "\u9648\u4e94\u5341\u5c6f"
    ],
    "wof:name":"Chenwushitun",
    "wof:placetype":"locality"
},
  "geometry": {"coordinates":[123.14899,42.5147],"type":"Point"}
}