{
  "type": "Feature",
  "properties": {
    "gn:admin1_code":"5.0",
    "gn:asciiname":"Hanconggoucun",
    "gn:country_code":"CN",
    "gn:dem":567,
    "gn:feature_class":"P",
    "gn:feature_code":"PPL",
    "gn:name":"Hanconggoucun",
    "gn:population":0,
    "gn:timezone":"Asia/Shanghai",
    "iso:country":"CN",
    "name:zho_x_preferred":[
        "\u5bd2\u8471\u6c9f\u6751"
    ],
    "wof:name":"Hanconggoucun",
    "wof:placetype":"locality"
},
  "geometry": {"coordinates":[128.01871,43.12539],"type":"Point"}
}