{
  "type": "Feature",
  "properties": {
    "gn:admin1_code":"9.0",
    "gn:asciiname":"Waxuezi",
    "gn:country_code":"CN",
    "gn:dem":1126,
    "gn:feature_class":"P",
    "gn:feature_code":"PPL",
    "gn:name":"Waxuezi",
    "gn:population":0,
    "gn:timezone":"Asia/Shanghai",
    "iso:country":"CN",
    "name:zho_x_preferred":[
        "\u74e6\u7a74\u5b50"
    ],
    "wof:name":"Waxuezi",
    "wof:placetype":"locality"
},
  "geometry": {"coordinates":[111.02196000000001,33.85528],"type":"Point"}
}