{
  "type": "Feature",
  "properties": {
    "gn:admin1_code":"20",
    "gn:asciiname":"Qianda Labin",
    "gn:country_code":"CN",
    "gn:dem":309,
    "gn:feature_class":"P",
    "gn:feature_code":"PPL",
    "gn:name":"Qianda Labin",
    "gn:population":0,
    "gn:timezone":"Asia/Shanghai",
    "iso:country":"CN",
    "name:und_x_variant":[
        "Ch\u2019en-ta-la-pin",
        "Qianda Labin"
    ],
    "name:zho_x_preferred":[
        "\u524d\u8fbe\u62c9\u6ee8"
    ],
    "wof:name":"Qianda Labin",
    "wof:placetype":"locality"
},
  "geometry": {"coordinates":[124.86018,49.62488],"type":"Point"}
}