{
  "type": "Feature",
  "properties": {
    "gn:admin1_code":"20.0",
    "gn:asciiname":"Kangshengzhuang",
    "gn:country_code":"CN",
    "gn:dem":1145,
    "gn:feature_class":"P",
    "gn:feature_code":"PPL",
    "gn:name":"Kangshengzhuang",
    "gn:population":0,
    "gn:timezone":"Asia/Shanghai",
    "iso:country":"CN",
    "name:und_x_variant":[
        "\u5eb7\u5723\u5e84"
    ],
    "wof:name":"Kangshengzhuang",
    "wof:placetype":"locality"
},
  "geometry": {"coordinates":[111.7234,40.07075],"type":"Point"}
}