{
  "type": "Feature",
  "properties": {
    "gn:admin1_code":"15.0",
    "gn:asciiname":"Xiangziba",
    "gn:country_code":"CN",
    "gn:dem":1300,
    "gn:feature_class":"P",
    "gn:feature_code":"PPL",
    "gn:name":"Xiangziba",
    "gn:population":0,
    "gn:timezone":"Asia/Shanghai",
    "iso:country":"CN",
    "name:und_x_variant":[
        "\u9999\u5b50\u575d"
    ],
    "wof:name":"Xiangziba",
    "wof:placetype":"locality"
},
  "geometry": {"coordinates":[105.57469,33.35513],"type":"Point"}
}