{
  "type": "Feature",
  "properties": {
    "gn:admin1_code":"25",
    "gn:asciiname":"Niuzhuang",
    "gn:cc2":"CN",
    "gn:country_code":"CN",
    "gn:dem":4,
    "gn:feature_class":"P",
    "gn:feature_code":"PPL",
    "gn:name":"Niuzhuang",
    "gn:population":0,
    "gn:timezone":"Asia/Shanghai",
    "iso:country":"CN",
    "name:und_x_variant":[
        "Niu-chuang",
        "Niuzhuang"
    ],
    "wof:name":"Niuzhuang",
    "wof:placetype":"locality"
},
  "geometry": {"coordinates":[118.4575,37.34472],"type":"Point"}
}