{
  "type": "Feature",
  "properties": {
    "gn:admin1_code":"16",
    "gn:asciiname":"Chalongkou",
    "gn:country_code":"CN",
    "gn:dem":286,
    "gn:feature_class":"P",
    "gn:feature_code":"PPL",
    "gn:name":"Chalongkou",
    "gn:population":0,
    "gn:timezone":"Asia/Shanghai",
    "iso:country":"CN",
    "name:zho_x_preferred":[
        "\u8336\u9f99\u53e3"
    ],
    "wof:name":"Chalongkou",
    "wof:placetype":"locality"
},
  "geometry": {"coordinates":[110.56999999999999,25.4325],"type":"Point"}
}