{
  "type": "Feature",
  "properties": {
    "gn:admin1_code":"14.0",
    "gn:asciiname":"Gongxiding",
    "gn:country_code":"CN",
    "gn:dem":4422,
    "gn:feature_class":"P",
    "gn:feature_code":"PPL",
    "gn:name":"Gongxiding",
    "gn:population":0,
    "gn:timezone":"Asia/Urumqi",
    "iso:country":"CN",
    "name:bod_x_preferred":[
        "Goinxigd\u00eang"
    ],
    "name:zho_x_preferred":[
        "Gongxiding"
    ],
    "name:zho_x_variant":[
        "\u8d21\u7ec6\u4e01"
    ],
    "wof:name":"Gongxiding",
    "wof:placetype":"locality"
},
  "geometry": {"coordinates":[93.401,30.801],"type":"Point"}
}