{
  "type": "Feature",
  "properties": {
    "gn:admin1_code":"26.0",
    "gn:asciiname":"Simao",
    "gn:country_code":"CN",
    "gn:dem":1181,
    "gn:feature_class":"P",
    "gn:feature_code":"PPL",
    "gn:name":"Simao",
    "gn:population":0,
    "gn:timezone":"Asia/Shanghai",
    "iso:country":"CN",
    "name:deu_x_preferred":[
        "Simao"
    ],
    "name:fra_x_preferred":[
        "Simao"
    ],
    "name:ita_x_preferred":[
        "Simao"
    ],
    "name:por_x_preferred":[
        "Sim\u00e3o"
    ],
    "name:ukr_x_preferred":[
        "\u0421\u0456\u043c\u0430\u0443"
    ],
    "name:zho_x_preferred":[
        "\u5bfa\u5cc1"
    ],
    "wof:name":"Simao",
    "wof:placetype":"locality"
},
  "geometry": {"coordinates":[109.44643000000001,37.42623],"type":"Point"}
}