{
  "type": "Feature",
  "properties": {
    "gn:admin1_code":"4.0",
    "gn:asciiname":"Linshengxu",
    "gn:country_code":"CN",
    "gn:dem":4,
    "gn:feature_class":"P",
    "gn:feature_code":"PPL",
    "gn:name":"Linshengxu",
    "gn:population":0,
    "gn:timezone":"Asia/Shanghai",
    "iso:country":"CN",
    "name:zho_x_preferred":[
        "\u6797\u76db\u5729"
    ],
    "wof:name":"Linshengxu",
    "wof:placetype":"locality"
},
  "geometry": {"coordinates":[120.21502,31.99084],"type":"Point"}
}