{
  "type": "Feature",
  "properties": {
    "gn:admin1_code":"26.0",
    "gn:asciiname":"Yihe",
    "gn:cc2":"CN",
    "gn:country_code":"CN",
    "gn:dem":676,
    "gn:feature_class":"P",
    "gn:feature_code":"PPL",
    "gn:name":"Yihe",
    "gn:population":0,
    "gn:timezone":"Asia/Shanghai",
    "iso:country":"CN",
    "name:und_x_variant":[
        "Chao-ho-pa",
        "I-ho",
        "I-ho-ya",
        "I-ho-pa",
        "Yihe"
    ],
    "wof:name":"Yihe",
    "wof:placetype":"locality"
},
  "geometry": {"coordinates":[108.9575,32.28194000000001],"type":"Point"}
}