{
  "type": "Feature",
  "properties": {
    "gn:admin1_code":"19.0",
    "gn:asciiname":"Baoshantang",
    "gn:country_code":"CN",
    "gn:dem":268,
    "gn:feature_class":"P",
    "gn:feature_code":"PPL",
    "gn:name":"Baoshantang",
    "gn:population":0,
    "gn:timezone":"Asia/Shanghai",
    "iso:country":"CN",
    "name:und_x_variant":[
        "\u5b9d\u5584\u5802"
    ],
    "name:zho_x_preferred":[
        "\u5b9d\u5584\u5802"
    ],
    "wof:name":"Baoshantang",
    "wof:placetype":"locality"
},
  "geometry": {"coordinates":[121.00828,42.17733],"type":"Point"}
}