{
  "type": "Feature",
  "properties": {
    "gn:admin1_code":"13.0",
    "gn:asciiname":"Tuofuqia",
    "gn:country_code":"CN",
    "gn:dem":1353,
    "gn:feature_class":"P",
    "gn:feature_code":"PPL",
    "gn:name":"Tuofuqia",
    "gn:population":0,
    "gn:timezone":"Asia/Shanghai",
    "iso:country":"CN",
    "name:zho_x_preferred":[
        "\u6258\u752b\u6070"
    ],
    "wof:name":"Tuofuqia",
    "wof:placetype":"locality"
},
  "geometry": {"coordinates":[79.91169000000002,37.13193],"type":"Point"}
}