{
  "type": "Feature",
  "properties": {
    "gn:admin1_code":"15.0",
    "gn:asciiname":"Chuyana",
    "gn:country_code":"CN",
    "gn:dem":2805,
    "gn:feature_class":"P",
    "gn:feature_code":"PPL",
    "gn:name":"Chuyana",
    "gn:population":0,
    "gn:timezone":"Asia/Shanghai",
    "iso:country":"CN",
    "name:und_x_variant":[
        "\u51fa\u7259\u7eb3"
    ],
    "wof:name":"Chuyana",
    "wof:placetype":"locality"
},
  "geometry": {"coordinates":[103.50362,34.64872],"type":"Point"}
}