{
  "type": "Feature",
  "properties": {
    "gn:admin1_code":"26.0",
    "gn:asciiname":"Jingtangmiao",
    "gn:country_code":"CN",
    "gn:dem":1458,
    "gn:feature_class":"P",
    "gn:feature_code":"PPL",
    "gn:name":"Jingtangmiao",
    "gn:population":0,
    "gn:timezone":"Asia/Shanghai",
    "iso:country":"CN",
    "name:zho_x_preferred":[
        "\u7ecf\u5802\u5e99"
    ],
    "wof:name":"Jingtangmiao",
    "wof:placetype":"locality"
},
  "geometry": {"coordinates":[110.223,33.26657],"type":"Point"}
}