{
  "type": "Feature",
  "properties": {
    "gn:admin1_code":"15.0",
    "gn:asciiname":"Hawu",
    "gn:country_code":"CN",
    "gn:dem":2167,
    "gn:feature_class":"P",
    "gn:feature_code":"PPL",
    "gn:name":"Hawu",
    "gn:population":0,
    "gn:timezone":"Asia/Shanghai",
    "iso:country":"CN",
    "name:zho_x_preferred":[
        "\u54c8\u543e"
    ],
    "wof:name":"Hawu",
    "wof:placetype":"locality"
},
  "geometry": {"coordinates":[104.6397,33.45544],"type":"Point"}
}