{
  "type": "Feature",
  "properties": {
    "gn:admin1_code":"29.0",
    "gn:asciiname":"Ayanji",
    "gn:country_code":"CN",
    "gn:dem":1826,
    "gn:feature_class":"P",
    "gn:feature_code":"PPL",
    "gn:name":"Ayanji",
    "gn:population":0,
    "gn:timezone":"Asia/Shanghai",
    "iso:country":"CN",
    "name:zho_x_preferred":[
        "\u963f\u5ca9\u57fa"
    ],
    "wof:name":"Ayanji",
    "wof:placetype":"locality"
},
  "geometry": {"coordinates":[98.914,26.1427],"type":"Point"}
}