{
  "type": "Feature",
  "properties": {
    "gn:admin1_code":"14.0",
    "gn:asciiname":"Qiemokou",
    "gn:country_code":"CN",
    "gn:dem":4281,
    "gn:feature_class":"P",
    "gn:feature_code":"PPL",
    "gn:name":"Qiemokou",
    "gn:population":0,
    "gn:timezone":"Asia/Urumqi",
    "iso:country":"CN",
    "name:zho_x_preferred":[
        "\u5207\u83ab\u6263"
    ],
    "wof:name":"Qiemokou",
    "wof:placetype":"locality"
},
  "geometry": {"coordinates":[94.15331999999999,31.99191],"type":"Point"}
}