{
  "type": "Feature",
  "properties": {
    "gn:admin1_code":"16.0",
    "gn:asciiname":"Nagui",
    "gn:country_code":"CN",
    "gn:dem":398,
    "gn:feature_class":"P",
    "gn:feature_code":"PPL",
    "gn:name":"Nagui",
    "gn:population":0,
    "gn:timezone":"Asia/Shanghai",
    "iso:country":"CN",
    "name:ara_x_preferred":[
        "\u0646\u0627\u062c\u064a \u0641\u0627\u0645"
    ],
    "name:arz_x_preferred":[
        "\u0646\u0627\u062c\u0649 \u0641\u0627\u0645"
    ],
    "name:cat_x_preferred":[
        "Nagui"
    ],
    "name:epo_x_preferred":[
        "Nagui"
    ],
    "name:eus_x_preferred":[
        "Nagui"
    ],
    "name:fra_x_preferred":[
        "Nagui"
    ],
    "name:ita_x_preferred":[
        "Nagui"
    ],
    "name:spa_x_preferred":[
        "Nagui"
    ],
    "name:zho_x_preferred":[
        "\u90a3\u89c4"
    ],
    "wof:name":"Nagui",
    "wof:placetype":"locality"
},
  "geometry": {"coordinates":[106.367,23.8658],"type":"Point"}
}