{
  "type": "Feature",
  "properties": {
    "gn:admin1_code":"29",
    "gn:asciiname":"Yen-t'ou-chai",
    "gn:country_code":"CN",
    "gn:dem":930,
    "gn:feature_class":"P",
    "gn:feature_code":"PPL",
    "gn:name":"Yen-t\u2019ou-chai",
    "gn:population":0,
    "gn:timezone":"Asia/Shanghai",
    "iso:country":"CN",
    "wof:name":"Yen-t'ou-chai",
    "wof:placetype":"locality"
},
  "geometry": {"coordinates":[103.82306,22.77389],"type":"Point"}
}