{
  "type": "Feature",
  "properties": {
    "gn:admin1_code":"3.0",
    "gn:asciiname":"Chengjialing",
    "gn:country_code":"CN",
    "gn:dem":30,
    "gn:feature_class":"P",
    "gn:feature_code":"PPL",
    "gn:name":"Chengjialing",
    "gn:population":0,
    "gn:timezone":"Asia/Shanghai",
    "iso:country":"CN",
    "name:und_x_variant":[
        "\u7a0b\u5bb6\u5cad"
    ],
    "wof:name":"Chengjialing",
    "wof:placetype":"locality"
},
  "geometry": {"coordinates":[116.68810000000001,29.4907],"type":"Point"}
}