{
  "type": "Feature",
  "properties": {
    "gn:admin1_code":"3.0",
    "gn:asciiname":"Pantian",
    "gn:country_code":"CN",
    "gn:dem":130,
    "gn:feature_class":"P",
    "gn:feature_code":"PPL",
    "gn:name":"Pantian",
    "gn:population":0,
    "gn:timezone":"Asia/Shanghai",
    "iso:country":"CN",
    "name:und_x_variant":[
        "\u76d8\u7530"
    ],
    "name:zho_x_preferred":[
        "\u6f58\u7530\u9547"
    ],
    "wof:name":"Pantian",
    "wof:placetype":"locality"
},
  "geometry": {"coordinates":[114.14332,27.96155],"type":"Point"}
}