{
  "type": "Feature",
  "properties": {
    "gn:admin1_code":"02",
    "gn:asciiname":"Yaxicun",
    "gn:country_code":"CN",
    "gn:dem":260,
    "gn:feature_class":"P",
    "gn:feature_code":"PPL",
    "gn:name":"Yaxicun",
    "gn:population":0,
    "gn:timezone":"Asia/Shanghai",
    "iso:country":"CN",
    "name:und_x_variant":[
        "Hsia-ch\u2019i-ts\u2019un",
        "Yaxi",
        "Yaxicun"
    ],
    "name:zho_x_preferred":[
        "\u96c5\u6eaa"
    ],
    "name:zho_x_variant":[
        "\u96c5\u6eaa\u6751"
    ],
    "wof:name":"Yaxicun",
    "wof:placetype":"locality"
},
  "geometry": {"coordinates":[120.33235999999999,28.69632],"type":"Point"}
}