{
  "type": "Feature",
  "properties": {
    "gn:admin1_code":"16.0",
    "gn:asciiname":"Tanrao",
    "gn:country_code":"CN",
    "gn:dem":328,
    "gn:feature_class":"P",
    "gn:feature_code":"PPL",
    "gn:name":"Tanrao",
    "gn:population":0,
    "gn:timezone":"Asia/Shanghai",
    "iso:country":"CN",
    "name:zho_x_preferred":[
        "\u6f6d\u7ed5"
    ],
    "wof:name":"Tanrao",
    "wof:placetype":"locality"
},
  "geometry": {"coordinates":[107.789,23.4499],"type":"Point"}
}