{
  "type": "Feature",
  "properties": {
    "gn:admin1_code":"29.0",
    "gn:asciiname":"Hedixia",
    "gn:country_code":"CN",
    "gn:dem":1310,
    "gn:feature_class":"P",
    "gn:feature_code":"PPL",
    "gn:name":"Hedixia",
    "gn:population":0,
    "gn:timezone":"Asia/Shanghai",
    "iso:country":"CN",
    "name:zho_x_preferred":[
        "\u6cb3\u5e95\u4e0b"
    ],
    "wof:name":"Hedixia",
    "wof:placetype":"locality"
},
  "geometry": {"coordinates":[104.902,27.7882],"type":"Point"}
}