{
  "type": "Feature",
  "properties": {
    "gn:admin1_code":"2.0",
    "gn:asciiname":"Dingqingliao",
    "gn:country_code":"CN",
    "gn:dem":159,
    "gn:feature_class":"P",
    "gn:feature_code":"PPL",
    "gn:name":"Dingqingliao",
    "gn:population":0,
    "gn:timezone":"Asia/Shanghai",
    "iso:country":"CN",
    "name:zho_x_preferred":[
        "\u952d\u9752\u5bee"
    ],
    "wof:name":"Dingqingliao",
    "wof:placetype":"locality"
},
  "geometry": {"coordinates":[119.90984,27.97425],"type":"Point"}
}