{
  "type": "Feature",
  "properties": {
    "gn:admin1_code":"3.0",
    "gn:asciiname":"Guojiashan",
    "gn:country_code":"CN",
    "gn:dem":49,
    "gn:feature_class":"P",
    "gn:feature_code":"PPL",
    "gn:name":"Guojiashan",
    "gn:population":0,
    "gn:timezone":"Asia/Shanghai",
    "iso:country":"CN",
    "name:und_x_variant":[
        "\u90ed\u5bb6\u5c71"
    ],
    "wof:name":"Guojiashan",
    "wof:placetype":"locality"
},
  "geometry": {"coordinates":[116.46682,29.45334],"type":"Point"}
}