{
  "type": "Feature",
  "properties": {
    "gn:admin1_code":"26.0",
    "gn:asciiname":"Jinjiwancun",
    "gn:country_code":"CN",
    "gn:dem":1338,
    "gn:feature_class":"P",
    "gn:feature_code":"PPL",
    "gn:name":"Jinjiwancun",
    "gn:population":0,
    "gn:timezone":"Asia/Shanghai",
    "iso:country":"CN",
    "name:und_x_variant":[
        "Chin-chi-wan",
        "Jinjiwan",
        "Jinjiwancun"
    ],
    "name:zho_x_preferred":[
        "\u91d1\u9e21\u6e7e\u6751"
    ],
    "wof:name":"Jinjiwancun",
    "wof:placetype":"locality"
},
  "geometry": {"coordinates":[107.682,37.8001],"type":"Point"}
}