{
  "type": "Feature",
  "properties": {
    "gn:country":"CN",
    "gn:fcode":"PPL",
    "gn:population":625040,
    "iso:country":"CN",
    "name:ceb_x_preferred":[
        "Panshan"
    ],
    "name:und_x_variant":[
        "Shuang-t\u2019ai-tzu"
    ],
    "qs:name":"Panshan",
    "qs:photos_9r":0,
    "qs:photos_sr":0,
    "qs:pop_sr":"11",
    "wd:wordcount":17,
    "wof:name":"Panshan",
    "wof:placetype":"locality",
    "wof:population":625040
},
  "geometry": {"coordinates":[122.04944,41.18806],"type":"Point"}
}