{
  "type": "Feature",
  "properties": {
    "gn:admin1_code":"7",
    "gn:asciiname":"Yedi",
    "gn:country_code":"CN",
    "gn:dem":751,
    "gn:feature_class":"P",
    "gn:feature_code":"PPL",
    "gn:name":"Yedi",
    "gn:population":0,
    "gn:timezone":"Asia/Shanghai",
    "iso:country":"CN",
    "name:azb_x_preferred":[
        "\u06cc\u062f\u06cc"
    ],
    "name:fas_x_preferred":[
        "\u06cc\u062f\u06cc"
    ],
    "name:und_x_variant":[
        "\u53f6\u5730"
    ],
    "name:zho_x_preferred":[
        "\u53f6\u5730"
    ],
    "wof:name":"Yedi",
    "wof:placetype":"locality"
},
  "geometry": {"coordinates":[117.50941,26.54716],"type":"Point"}
}