{
  "type": "Feature",
  "properties": {
    "gn:admin1_code":"7.0",
    "gn:asciiname":"Yanfeng",
    "gn:country_code":"CN",
    "gn:dem":21,
    "gn:feature_class":"P",
    "gn:feature_code":"PPL",
    "gn:name":"Yanfeng",
    "gn:population":0,
    "gn:timezone":"Asia/Shanghai",
    "iso:country":"CN",
    "name:zho_x_preferred":[
        "\u5ca9\u5cf0"
    ],
    "wof:name":"Yanfeng",
    "wof:placetype":"locality"
},
  "geometry": {"coordinates":[118.85744,24.96183],"type":"Point"}
}