{
  "type": "Feature",
  "properties": {
    "gn:admin1_code":"32.0",
    "gn:asciiname":"Dongyuemiao",
    "gn:country_code":"CN",
    "gn:dem":686,
    "gn:feature_class":"P",
    "gn:feature_code":"PPL",
    "gn:name":"Dongyuemiao",
    "gn:population":0,
    "gn:timezone":"Asia/Shanghai",
    "iso:country":"CN",
    "name:zho_x_preferred":[
        "\u4e1c\u5cb3\u5e99"
    ],
    "wof:name":"Dongyuemiao",
    "wof:placetype":"locality"
},
  "geometry": {"coordinates":[104.47989,30.7504],"type":"Point"}
}