{
  "type": "Feature",
  "properties": {
    "gn:admin1_code":"16.0",
    "gn:asciiname":"Jinfeng",
    "gn:country_code":"CN",
    "gn:dem":222,
    "gn:feature_class":"P",
    "gn:feature_code":"PPL",
    "gn:name":"Jinfeng",
    "gn:population":0,
    "gn:timezone":"Asia/Shanghai",
    "iso:country":"CN",
    "name:ceb_x_preferred":[
        "Jinfeng"
    ],
    "name:zho_x_preferred":[
        "\u91d1\u950b"
    ],
    "wof:name":"Jinfeng",
    "wof:placetype":"locality"
},
  "geometry": {"coordinates":[111.328,24.7223],"type":"Point"}
}