{
  "type": "Feature",
  "properties": {
    "gn:admin1_code":"1.0",
    "gn:asciiname":"Jiuqucun",
    "gn:country_code":"CN",
    "gn:dem":418,
    "gn:feature_class":"P",
    "gn:feature_code":"PPL",
    "gn:name":"Jiuqucun",
    "gn:population":0,
    "gn:timezone":"Asia/Shanghai",
    "iso:country":"CN",
    "name:zho_x_preferred":[
        "\u4e5d\u66f2\u6751"
    ],
    "wof:name":"Jiuqucun",
    "wof:placetype":"locality"
},
  "geometry": {"coordinates":[116.12524999999999,31.57675],"type":"Point"}
}