{
  "type": "Feature",
  "properties": {
    "gn:admin1_code":"12.0",
    "gn:asciiname":"Fanchong",
    "gn:country_code":"CN",
    "gn:dem":101,
    "gn:feature_class":"P",
    "gn:feature_code":"PPL",
    "gn:name":"Fanchong",
    "gn:population":0,
    "gn:timezone":"Asia/Shanghai",
    "iso:country":"CN",
    "name:zho_x_preferred":[
        "Fanchong"
    ],
    "name:zho_x_variant":[
        "\u51e1\u51b2"
    ],
    "wof:name":"Fanchong",
    "wof:placetype":"locality"
},
  "geometry": {"coordinates":[114.47410000000001,29.80317],"type":"Point"}
}