{
  "type": "Feature",
  "properties": {
    "gn:admin1_code":"30",
    "gn:asciiname":"Guanlu",
    "gn:country_code":"CN",
    "gn:dem":39,
    "gn:feature_class":"P",
    "gn:feature_code":"PPL",
    "gn:name":"Guanlu",
    "gn:population":0,
    "gn:timezone":"Asia/Urumqi",
    "iso:country":"CN",
    "name:zho_x_preferred":[
        "\u5b98\u8def"
    ],
    "wof:name":"Guanlu",
    "wof:placetype":"locality"
},
  "geometry": {"coordinates":[111.02925999999999,21.72947000000001],"type":"Point"}
}