{
  "type": "Feature",
  "properties": {
    "gn:admin1_code":"15.0",
    "gn:asciiname":"Tanyaogou",
    "gn:country_code":"CN",
    "gn:dem":2367,
    "gn:feature_class":"P",
    "gn:feature_code":"PPL",
    "gn:name":"Tanyaogou",
    "gn:population":0,
    "gn:timezone":"Asia/Shanghai",
    "iso:country":"CN",
    "name:zho_x_preferred":[
        "\u70ad\u7a91\u6c9f"
    ],
    "wof:name":"Tanyaogou",
    "wof:placetype":"locality"
},
  "geometry": {"coordinates":[103.676,37.4336],"type":"Point"}
}