{
  "type": "Feature",
  "properties": {
    "gn:admin1_code":"29.0",
    "gn:asciiname":"Longquan",
    "gn:country_code":"CN",
    "gn:dem":2059,
    "gn:feature_class":"P",
    "gn:feature_code":"PPL",
    "gn:name":"Longquan",
    "gn:population":0,
    "gn:timezone":"Asia/Shanghai",
    "iso:country":"CN",
    "name:und_x_variant":[
        "\u9f99\u6cc9"
    ],
    "wof:name":"Longquan",
    "wof:placetype":"locality"
},
  "geometry": {"coordinates":[104.41766,26.412],"type":"Point"}
}