{
  "type": "Feature",
  "properties": {
    "gn:admin1_code":"26",
    "gn:asciiname":"Tangfangpo",
    "gn:country_code":"CN",
    "gn:dem":793,
    "gn:feature_class":"P",
    "gn:feature_code":"PPL",
    "gn:name":"Tangfangpo",
    "gn:population":0,
    "gn:timezone":"Asia/Shanghai",
    "iso:country":"CN",
    "name:zho_x_preferred":[
        "\u6c64\u623f\u5761"
    ],
    "wof:name":"Tangfangpo",
    "wof:placetype":"locality"
},
  "geometry": {"coordinates":[108.41278,34.59528],"type":"Point"}
}