{
  "type": "Feature",
  "properties": {
    "gn:admin1_code":"30",
    "gn:asciiname":"Shezhuhe",
    "gn:country_code":"CN",
    "gn:dem":751,
    "gn:feature_class":"P",
    "gn:feature_code":"PPL",
    "gn:name":"Shezhuhe",
    "gn:population":0,
    "gn:timezone":"Asia/Urumqi",
    "iso:country":"CN",
    "name:zho_x_preferred":[
        "\u6444\u7af9\u6cb3"
    ],
    "wof:name":"Shezhuhe",
    "wof:placetype":"locality"
},
  "geometry": {"coordinates":[111.19926,22.22093],"type":"Point"}
}