{
  "type": "Feature",
  "properties": {
    "gn:admin1_code":"11",
    "gn:asciiname":"Gualuping",
    "gn:country_code":"CN",
    "gn:dem":608,
    "gn:feature_class":"P",
    "gn:feature_code":"PPL",
    "gn:name":"Gualuping",
    "gn:population":0,
    "gn:timezone":"Asia/Shanghai",
    "iso:country":"CN",
    "name:zho_x_preferred":[
        "\u74dc\u8def\u576a"
    ],
    "wof:name":"Gualuping",
    "wof:placetype":"locality"
},
  "geometry": {"coordinates":[111.02567999999999,27.86106],"type":"Point"}
}