{
  "type": "Feature",
  "properties": {
    "gn:admin1_code":"5.0",
    "gn:asciiname":"Hala Gantu",
    "gn:country_code":"CN",
    "gn:dem":148,
    "gn:feature_class":"P",
    "gn:feature_code":"PPL",
    "gn:name":"Hala Gantu",
    "gn:population":0,
    "gn:timezone":"Asia/Shanghai",
    "iso:country":"CN",
    "name:zho_x_preferred":[
        "\u54c8\u62c9\u5e72\u571f"
    ],
    "wof:name":"Hala Gantu",
    "wof:placetype":"locality"
},
  "geometry": {"coordinates":[123.20004,44.85406],"type":"Point"}
}