{
  "type": "Feature",
  "properties": {
    "gn:admin1_code":"14.0",
    "gn:asciiname":"Ninggong",
    "gn:country_code":"CN",
    "gn:dem":4036,
    "gn:feature_class":"P",
    "gn:feature_code":"PPL",
    "gn:name":"Ninggong",
    "gn:population":0,
    "gn:timezone":"Asia/Shanghai",
    "iso:country":"CN",
    "name:zho_x_preferred":[
        "\u5b81\u9f9a"
    ],
    "wof:name":"Ninggong",
    "wof:placetype":"locality"
},
  "geometry": {"coordinates":[79.5038,31.7696],"type":"Point"}
}