{
  "type": "Feature",
  "properties": {
    "gn:admin1_code":"26.0",
    "gn:asciiname":"Nongwudui",
    "gn:country_code":"CN",
    "gn:dem":372,
    "gn:feature_class":"P",
    "gn:feature_code":"PPLF",
    "gn:name":"Nongwudui",
    "gn:population":0,
    "gn:timezone":"Asia/Shanghai",
    "iso:country":"CN",
    "name:zho_x_preferred":[
        "\u519c\u4e94\u961f"
    ],
    "wof:name":"Nongwudui",
    "wof:placetype":"locality"
},
  "geometry": {"coordinates":[108.89775,34.37715],"type":"Point"}
}