{
  "type": "Feature",
  "properties": {
    "gn:admin1_code":"30.0",
    "gn:asciiname":"Jiangzui",
    "gn:country_code":"CN",
    "gn:dem":317,
    "gn:feature_class":"P",
    "gn:feature_code":"PPL",
    "gn:name":"Jiangzui",
    "gn:population":0,
    "gn:timezone":"Asia/Shanghai",
    "iso:country":"CN",
    "name:zho_x_preferred":[
        "Jiangzui"
    ],
    "name:zho_x_variant":[
        "\u6c5f\u5480"
    ],
    "wof:name":"Jiangzui",
    "wof:placetype":"locality"
},
  "geometry": {"coordinates":[112.48833,24.21028],"type":"Point"}
}