{
  "type": "Feature",
  "properties": {
    "gn:admin1_code":"30.0",
    "gn:asciiname":"Shiheping",
    "gn:country_code":"CN",
    "gn:dem":230,
    "gn:feature_class":"P",
    "gn:feature_code":"PPL",
    "gn:name":"Shiheping",
    "gn:population":0,
    "gn:timezone":"Asia/Shanghai",
    "iso:country":"CN",
    "name:zho_x_preferred":[
        "\u77f3\u79be\u576a"
    ],
    "wof:name":"Shiheping",
    "wof:placetype":"locality"
},
  "geometry": {"coordinates":[115.78058,24.29774],"type":"Point"}
}