{
  "type": "Feature",
  "properties": {
    "gn:admin1_code":"19.0",
    "gn:asciiname":"Jiukouyucun",
    "gn:country_code":"CN",
    "gn:dem":120,
    "gn:feature_class":"P",
    "gn:feature_code":"PPL",
    "gn:name":"Jiukouyucun",
    "gn:population":0,
    "gn:timezone":"Asia/Shanghai",
    "iso:country":"CN",
    "name:zho_x_preferred":[
        "\u4e5d\u53e3\u5cea\u6751"
    ],
    "wof:name":"Jiukouyucun",
    "wof:placetype":"locality"
},
  "geometry": {"coordinates":[123.57393,41.16189],"type":"Point"}
}