{
  "type": "Feature",
  "properties": {
    "gn:admin1_code":"11",
    "gn:asciiname":"Menlouxia",
    "gn:country_code":"CN",
    "gn:dem":646,
    "gn:feature_class":"P",
    "gn:feature_code":"PPLA4",
    "gn:name":"Menlouxia",
    "gn:population":0,
    "gn:timezone":"Asia/Shanghai",
    "iso:country":"CN",
    "name:und_x_variant":[
        "Menlouxia Yaozuxiang",
        "\u95e8\u697c\u4e0b\u7476\u65cf\u4e61",
        "Menlouxia"
    ],
    "name:zho_x_preferred":[
        "\u95e8\u697c\u4e0b"
    ],
    "wof:name":"Menlouxia",
    "wof:placetype":"locality"
},
  "geometry": {"coordinates":[112.20722000000001,26.01444],"type":"Point"}
}