{
  "type": "Feature",
  "properties": {
    "gn:admin1_code":"26.0",
    "gn:asciiname":"Lulingcun",
    "gn:country_code":"CN",
    "gn:dem":439,
    "gn:feature_class":"P",
    "gn:feature_code":"PPL",
    "gn:name":"Lulingcun",
    "gn:population":0,
    "gn:timezone":"Asia/Shanghai",
    "iso:country":"CN",
    "name:und_x_variant":[
        "\u9e7f\u9f84\u6751"
    ],
    "wof:name":"Lulingcun",
    "wof:placetype":"locality"
},
  "geometry": {"coordinates":[107.74517,32.98415],"type":"Point"}
}