{
  "type": "Feature",
  "properties": {
    "gn:admin1_code":"16.0",
    "gn:asciiname":"Fenghuangwei",
    "gn:country_code":"CN",
    "gn:dem":291,
    "gn:feature_class":"P",
    "gn:feature_code":"PPL",
    "gn:name":"Fenghuangwei",
    "gn:population":0,
    "gn:timezone":"Asia/Shanghai",
    "iso:country":"CN",
    "name:zho_x_preferred":[
        "\u51e4\u51f0\u5c3e"
    ],
    "wof:name":"Fenghuangwei",
    "wof:placetype":"locality"
},
  "geometry": {"coordinates":[110.964,22.7623],"type":"Point"}
}