{
  "type": "Feature",
  "properties": {
    "gn:admin1_code":"13.0",
    "gn:asciiname":"Erliugong",
    "gn:country_code":"CN",
    "gn:dem":577,
    "gn:feature_class":"P",
    "gn:feature_code":"PPLA4",
    "gn:name":"Erliugong",
    "gn:population":0,
    "gn:timezone":"Asia/Urumqi",
    "iso:country":"CN",
    "name:und_x_variant":[
        "Erliugong Zhen"
    ],
    "name:zho_x_preferred":[
        "\u4e8c\u516d\u5de5"
    ],
    "name:zho_x_variant":[
        "\u4e8c\u516d\u5de5\u9547"
    ],
    "wof:name":"Erliugong",
    "wof:placetype":"locality"
},
  "geometry": {"coordinates":[87.17036,44.05286],"type":"Point"}
}