{
  "type": "Feature",
  "properties": {
    "gn:admin1_code":"10",
    "gn:asciiname":"Pangcun",
    "gn:country_code":"CN",
    "gn:dem":66,
    "gn:feature_class":"P",
    "gn:feature_code":"PPLA4",
    "gn:name":"Pangcun",
    "gn:population":0,
    "gn:timezone":"Asia/Shanghai",
    "iso:country":"CN",
    "name:und_x_variant":[
        "\u5e9e\u6751",
        "Pangcun Zhen",
        "\u5e9e\u6751\u9547"
    ],
    "wof:name":"Pangcun",
    "wof:placetype":"locality"
},
  "geometry": {"coordinates":[114.96716000000001,38.6149],"type":"Point"}
}