{
  "type": "Feature",
  "properties": {
    "iso:country":"CN",
    "name:ceb_x_preferred":[
        "Shuangliu Xian"
    ],
    "name:cym_x_preferred":[
        "Ardal Shuangliu"
    ],
    "name:deu_x_preferred":[
        "Shuangliu"
    ],
    "name:eng_x_preferred":[
        "Shuangliu District"
    ],
    "name:eus_x_preferred":[
        "Shuangliu konderria"
    ],
    "name:fas_x_preferred":[
        "\u0634\u0648\u0627\u0646\u06af\u0644\u06cc\u0648"
    ],
    "name:gan_x_preferred":[
        "\u53cc\u6d41\u533a"
    ],
    "name:hak_x_preferred":[
        "S\u00fbng-li\u00f9-yen"
    ],
    "name:jpn_x_preferred":[
        "\u53cc\u6d41\u533a"
    ],
    "name:kor_x_preferred":[
        "\uc1bd\ub958 \ud604"
    ],
    "name:nan_x_preferred":[
        "Siang-li\u00fb-khu"
    ],
    "name:nld_x_preferred":[
        "Shuangliu District"
    ],
    "name:nob_x_preferred":[
        "Shuangliu"
    ],
    "name:rus_x_preferred":[
        "\u0428\u0443\u0430\u043d\u043b\u044e"
    ],
    "name:spa_x_preferred":[
        "Shuangliu"
    ],
    "name:swe_x_preferred":[
        "Shuangliu"
    ],
    "name:vie_x_preferred":[
        "Song L\u01b0u"
    ],
    "name:wuu_x_preferred":[
        "\u53cc\u6d41\u533a"
    ],
    "name:zho_x_preferred":[
        "\u53cc\u6d41\u533a"
    ],
    "qs:name":"\u53cc\u6d41\u53bf",
    "qs:name_adm0":"\u4e2d\u570b",
    "qs:name_adm1":"\u56db\u5ddd\u7701",
    "qs:photos":12,
    "qs:photos_1k":2,
    "qs:photos_9k":1,
    "qs:photos_9r":4,
    "qs:photos_all":239,
    "qs:photos_sr":1,
    "qs:placetype":"LocalAdmin",
    "qs:pop_sr":"0",
    "wd:wordcount":305,
    "wof:name":"\u53cc\u6d41\u53bf",
    "wof:placetype":"localadmin"
},
  "geometry": {"coordinates":[103.95866599999999,30.5764345],"type":"Point"}
}