{
  "type": "Feature",
  "properties": {
    "iso:country":"CN",
    "qs:name":"\u53cc\u6d41\u53bf",
    "qs:name_adm0":"\u4e2d\u570b",
    "qs:name_adm1":"\u56db\u5ddd\u7701",
    "qs:photos":12,
    "qs:photos_1k":2,
    "qs:photos_9k":1,
    "qs:photos_9r":4,
    "qs:photos_all":239,
    "qs:photos_sr":1,
    "qs:placetype":"LocalAdmin",
    "qs:pop_sr":"0",
    "wd:wordcount":305,
    "wof:name":"\u53cc\u6d41\u53bf",
    "wof:placetype":"localadmin"
},
  "geometry": {"coordinates":[103.95866599999999,30.5764345],"type":"Point"}
}