{
  "type": "Feature",
  "properties": {
    "gn:admin1_code":"12.0",
    "gn:asciiname":"Fancitangwan",
    "gn:country_code":"CN",
    "gn:dem":58,
    "gn:feature_class":"P",
    "gn:feature_code":"PPL",
    "gn:name":"Fancitangwan",
    "gn:population":0,
    "gn:timezone":"Asia/Shanghai",
    "iso:country":"CN",
    "name:zho_x_preferred":[
        "\u8303\u7960\u5802\u6e7e"
    ],
    "wof:name":"Fancitangwan",
    "wof:placetype":"locality"
},
  "geometry": {"coordinates":[112.4395,30.65309],"type":"Point"}
}