{
  "type": "Feature",
  "properties": {
    "gn:admin1_code":"9.0",
    "gn:asciiname":"Yangmuqiao",
    "gn:country_code":"CN",
    "gn:dem":1084,
    "gn:feature_class":"P",
    "gn:feature_code":"PPL",
    "gn:name":"Yangmuqiao",
    "gn:population":0,
    "gn:timezone":"Asia/Shanghai",
    "iso:country":"CN",
    "name:zho_x_preferred":[
        "\u6768\u6728\u6865"
    ],
    "wof:name":"Yangmuqiao",
    "wof:placetype":"locality"
},
  "geometry": {"coordinates":[111.50266999999999,34.08503],"type":"Point"}
}