{
  "type": "Feature",
  "properties": {
    "gn:admin1_code":"02",
    "gn:asciiname":"Taimen",
    "gn:country_code":"CN",
    "gn:dem":35,
    "gn:feature_class":"P",
    "gn:feature_code":"PPL",
    "gn:name":"Taimen",
    "gn:population":0,
    "gn:timezone":"Asia/Shanghai",
    "iso:country":"CN",
    "name:und_x_variant":[
        "\u53f0\u95e8",
        "Taimenzhen",
        "\u53f0\u95e8\u9547"
    ],
    "wof:name":"Taimen",
    "wof:placetype":"locality"
},
  "geometry": {"coordinates":[122.15791000000002,29.6998],"type":"Point"}
}