{
  "type": "Feature",
  "properties": {
    "gn:admin1_code":"26.0",
    "gn:asciiname":"Wangchi Goumen",
    "gn:country_code":"CN",
    "gn:dem":1811,
    "gn:feature_class":"P",
    "gn:feature_code":"PPL",
    "gn:name":"Wangchi Goumen",
    "gn:population":0,
    "gn:timezone":"Asia/Shanghai",
    "iso:country":"CN",
    "name:zho_x_preferred":[
        "\u738b\u6c60\u6c9f\u95e8"
    ],
    "wof:name":"Wangchi Goumen",
    "wof:placetype":"locality"
},
  "geometry": {"coordinates":[106.61883,34.59967],"type":"Point"}
}