{
  "type": "Feature",
  "properties": {
    "gn:admin1_code":"4.0",
    "gn:asciiname":"Nanjizhuang",
    "gn:country_code":"CN",
    "gn:dem":2,
    "gn:feature_class":"P",
    "gn:feature_code":"PPL",
    "gn:name":"Nanjizhuang",
    "gn:population":0,
    "gn:timezone":"Asia/Shanghai",
    "iso:country":"CN",
    "name:zho_x_preferred":[
        "\u5357\u96c6\u5e84"
    ],
    "wof:name":"Nanjizhuang",
    "wof:placetype":"locality"
},
  "geometry": {"coordinates":[120.13684000000001,31.99886],"type":"Point"}
}