{
  "type": "Feature",
  "properties": {
    "gn:admin1_code":"13",
    "gn:asciiname":"Shanggule Bage",
    "gn:country_code":"CN",
    "gn:dem":1237,
    "gn:feature_class":"P",
    "gn:feature_code":"PPL",
    "gn:name":"Shanggule Bage",
    "gn:population":0,
    "gn:timezone":"Asia/Shanghai",
    "iso:country":"CN",
    "name:und_x_variant":[
        "\u4e0a\u53e4\u52d2\u5df4\u683c"
    ],
    "wof:name":"Shanggule Bage",
    "wof:placetype":"locality"
},
  "geometry": {"coordinates":[77.40015,38.21715],"type":"Point"}
}