{
  "type": "Feature",
  "properties": {
    "gn:admin1_code":"32.0",
    "gn:asciiname":"Malianggou",
    "gn:country_code":"CN",
    "gn:dem":334,
    "gn:feature_class":"P",
    "gn:feature_code":"PPL",
    "gn:name":"Malianggou",
    "gn:population":0,
    "gn:timezone":"Asia/Shanghai",
    "iso:country":"CN",
    "name:zho_x_preferred":[
        "\u9a6c\u826f\u6c9f"
    ],
    "wof:name":"Malianggou",
    "wof:placetype":"locality"
},
  "geometry": {"coordinates":[105.318,30.3356],"type":"Point"}
}