{
  "type": "Feature",
  "properties": {
    "gn:admin1_code":"18",
    "gn:asciiname":"Balongzhai",
    "gn:country_code":"CN",
    "gn:dem":1051,
    "gn:feature_class":"P",
    "gn:feature_code":"PPL",
    "gn:name":"Balongzhai",
    "gn:population":0,
    "gn:timezone":"Asia/Shanghai",
    "iso:country":"CN",
    "name:zho_x_preferred":[
        "\u82ad\u7b3c\u5be8"
    ],
    "wof:name":"Balongzhai",
    "wof:placetype":"locality"
},
  "geometry": {"coordinates":[106.373,25.559],"type":"Point"}
}