{
  "type": "Feature",
  "properties": {
    "gn:admin1_code":"12.0",
    "gn:asciiname":"Jianggeda",
    "gn:country_code":"CN",
    "gn:dem":554,
    "gn:feature_class":"P",
    "gn:feature_code":"PPL",
    "gn:name":"Jianggeda",
    "gn:population":0,
    "gn:timezone":"Asia/Shanghai",
    "iso:country":"CN",
    "name:zho_x_preferred":[
        "\u59dc\u7599\u7629"
    ],
    "wof:name":"Jianggeda",
    "wof:placetype":"locality"
},
  "geometry": {"coordinates":[110.64458,32.91696],"type":"Point"}
}