{
  "type": "Feature",
  "properties": {
    "gn:admin1_code":"26.0",
    "gn:asciiname":"Shenjiayuancun",
    "gn:country_code":"CN",
    "gn:dem":1273,
    "gn:feature_class":"P",
    "gn:feature_code":"PPL",
    "gn:name":"Shenjiayuancun",
    "gn:population":0,
    "gn:timezone":"Asia/Shanghai",
    "iso:country":"CN",
    "name:zho_x_preferred":[
        "\u7533\u5bb6\u586c\u6751"
    ],
    "wof:name":"Shenjiayuancun",
    "wof:placetype":"locality"
},
  "geometry": {"coordinates":[109.74066999999999,35.57834000000001],"type":"Point"}
}