{
  "type": "Feature",
  "properties": {
    "gn:admin1_code":"30",
    "gn:asciiname":"Laoyachong",
    "gn:country_code":"CN",
    "gn:dem":272,
    "gn:feature_class":"P",
    "gn:feature_code":"PPL",
    "gn:name":"Laoyachong",
    "gn:population":0,
    "gn:timezone":"Asia/Shanghai",
    "iso:country":"CN",
    "name:und_x_variant":[
        "\u8001\u9e26\u51b2"
    ],
    "wof:name":"Laoyachong",
    "wof:placetype":"locality"
},
  "geometry": {"coordinates":[112.42278,24.98833],"type":"Point"}
}