{
  "type": "Feature",
  "properties": {
    "gn:admin1_code":"11.0",
    "gn:asciiname":"Manxi",
    "gn:country_code":"CN",
    "gn:dem":252,
    "gn:feature_class":"P",
    "gn:feature_code":"PPL",
    "gn:name":"Manxi",
    "gn:population":0,
    "gn:timezone":"Asia/Shanghai",
    "iso:country":"CN",
    "name:zho_x_preferred":[
        "\u86ee\u6eaa"
    ],
    "wof:name":"Manxi",
    "wof:placetype":"locality"
},
  "geometry": {"coordinates":[110.93492999999999,28.74648],"type":"Point"}
}