{
  "type": "Feature",
  "properties": {
    "gn:admin1_code":"1.0",
    "gn:asciiname":"Yanjia Xiaoxu",
    "gn:country_code":"CN",
    "gn:dem":5,
    "gn:feature_class":"P",
    "gn:feature_code":"PPL",
    "gn:name":"Yanjia Xiaoxu",
    "gn:population":0,
    "gn:timezone":"Asia/Shanghai",
    "iso:country":"CN",
    "name:zho_x_preferred":[
        "\u6bb7\u5bb6\u5c0f\u5729"
    ],
    "wof:name":"Yanjia Xiaoxu",
    "wof:placetype":"locality"
},
  "geometry": {"coordinates":[118.18397,31.17306],"type":"Point"}
}