{
  "type": "Feature",
  "properties": {
    "gn:admin1_code":"32.0",
    "gn:asciiname":"Dexueda",
    "gn:country_code":"CN",
    "gn:dem":3368,
    "gn:feature_class":"P",
    "gn:feature_code":"PPL",
    "gn:name":"Dexueda",
    "gn:population":0,
    "gn:timezone":"Asia/Shanghai",
    "iso:country":"CN",
    "name:zho_x_preferred":[
        "\u5fb7\u5b66\u8fbe"
    ],
    "wof:name":"Dexueda",
    "wof:placetype":"locality"
},
  "geometry": {"coordinates":[98.58329000000001,31.86719],"type":"Point"}
}