{
  "type": "Feature",
  "properties": {
    "gn:admin1_code":"8.0",
    "gn:asciiname":"Dongduibaocun",
    "gn:country_code":"CN",
    "gn:dem":189,
    "gn:feature_class":"P",
    "gn:feature_code":"PPL",
    "gn:name":"Dongduibaocun",
    "gn:population":0,
    "gn:timezone":"Asia/Shanghai",
    "iso:country":"CN",
    "name:zho_x_preferred":[
        "\u4e1c\u5bf9\u5b9d\u6751"
    ],
    "wof:name":"Dongduibaocun",
    "wof:placetype":"locality"
},
  "geometry": {"coordinates":[123.08387999999999,47.23277],"type":"Point"}
}