{
  "type": "Feature",
  "properties": {
    "gn:admin1_code":"29.0",
    "gn:asciiname":"Qiada",
    "gn:cc2":"CN",
    "gn:country_code":"CN",
    "gn:dem":1361,
    "gn:feature_class":"P",
    "gn:feature_code":"PPL",
    "gn:name":"Qiada",
    "gn:population":0,
    "gn:timezone":"Asia/Shanghai",
    "iso:country":"CN",
    "name:und_x_variant":[
        "Chia-ta",
        "Qiada"
    ],
    "wof:name":"Qiada",
    "wof:placetype":"locality"
},
  "geometry": {"coordinates":[98.90000000000001,26.61667000000001],"type":"Point"}
}