{
  "type": "Feature",
  "properties": {
    "gn:admin1_code":"3",
    "gn:asciiname":"Fangli",
    "gn:country_code":"CN",
    "gn:dem":77,
    "gn:feature_class":"P",
    "gn:feature_code":"PPL",
    "gn:name":"Fangli",
    "gn:population":0,
    "gn:timezone":"Asia/Shanghai",
    "iso:country":"CN",
    "name:und_x_variant":[
        "\u82b3\u91cc"
    ],
    "wof:name":"Fangli",
    "wof:placetype":"locality"
},
  "geometry": {"coordinates":[115.0498,28.48501],"type":"Point"}
}