{
  "type": "Feature",
  "properties": {
    "gn:admin1_code":"12",
    "gn:asciiname":"Liushui",
    "gn:country_code":"CN",
    "gn:dem":55,
    "gn:feature_class":"P",
    "gn:feature_code":"PPLA4",
    "gn:name":"Liushui",
    "gn:population":0,
    "gn:timezone":"Asia/Shanghai",
    "iso:country":"CN",
    "name:und_x_variant":[
        "Liushuigou",
        "Liu-shui-kou",
        "Liushui",
        "\u6d41\u6c34",
        "Liushui Zhen",
        "\u6d41\u6c34\u9547"
    ],
    "wof:name":"Liushui",
    "wof:placetype":"locality"
},
  "geometry": {"coordinates":[112.44798,31.56707],"type":"Point"}
}