{
  "type": "Feature",
  "properties": {
    "gn:admin1_code":"12.0",
    "gn:asciiname":"Tianchiya",
    "gn:country_code":"CN",
    "gn:dem":501,
    "gn:feature_class":"P",
    "gn:feature_code":"PPL",
    "gn:name":"Tianchiya",
    "gn:population":0,
    "gn:timezone":"Asia/Shanghai",
    "iso:country":"CN",
    "name:zho_x_preferred":[
        "\u5929\u6c60\u57ad"
    ],
    "wof:name":"Tianchiya",
    "wof:placetype":"locality"
},
  "geometry": {"coordinates":[110.36409999999999,32.29335],"type":"Point"}
}