{
  "type": "Feature",
  "properties": {
    "gn:admin1_code":"11.0",
    "gn:asciiname":"Pipayuan",
    "gn:country_code":"CN",
    "gn:dem":639,
    "gn:feature_class":"P",
    "gn:feature_code":"PPL",
    "gn:name":"Pipayuan",
    "gn:population":0,
    "gn:timezone":"Asia/Shanghai",
    "iso:country":"CN",
    "name:zho_x_preferred":[
        "\u6787\u6777\u56ed"
    ],
    "wof:name":"Pipayuan",
    "wof:placetype":"locality"
},
  "geometry": {"coordinates":[110.76365,27.60907000000001],"type":"Point"}
}