{
  "type": "Feature",
  "properties": {
    "gn:admin1_code":"5.0",
    "gn:asciiname":"Shuili",
    "gn:country_code":"CN",
    "gn:dem":109,
    "gn:feature_class":"P",
    "gn:feature_code":"PPL",
    "gn:name":"Shuili",
    "gn:population":0,
    "gn:timezone":"Asia/Shanghai",
    "iso:country":"CN",
    "name:deu_x_preferred":[
        "Shuili"
    ],
    "name:hak_x_preferred":[
        "S\u00fai-l\u00ee-hi\u00f4ng"
    ],
    "name:jpn_x_preferred":[
        "\u6c34\u91cc\u90f7"
    ],
    "name:kor_x_preferred":[
        "\uc218\uc774\ub9ac\ud5a5"
    ],
    "name:pol_x_preferred":[
        "Shuili"
    ],
    "name:und_x_variant":[
        "\u6c34\u793c"
    ],
    "name:vie_x_preferred":[
        "Th\u1ee7y L\u00fd"
    ],
    "name:zho_x_preferred":[
        "\u6c34\u91cc\u9109"
    ],
    "wof:name":"Shuili",
    "wof:placetype":"locality"
},
  "geometry": {"coordinates":[129.73391999999998,43.01214],"type":"Point"}
}