{
  "type": "Feature",
  "properties": {
    "gn:admin1_code":"10",
    "gn:asciiname":"Donglongmen",
    "gn:country_code":"CN",
    "gn:dem":120,
    "gn:feature_class":"P",
    "gn:feature_code":"PPL",
    "gn:name":"Donglongmen",
    "gn:population":0,
    "gn:timezone":"Asia/Shanghai",
    "iso:country":"CN",
    "name:zho_x_preferred":[
        "\u4e1c\u9f99\u95e8"
    ],
    "wof:name":"Donglongmen",
    "wof:placetype":"locality"
},
  "geometry": {"coordinates":[115.27642,39.10772],"type":"Point"}
}