{
  "type": "Feature",
  "properties": {
    "gn:admin1_code":"25.0",
    "gn:asciiname":"Zhengcheng",
    "gn:cc2":"CN",
    "gn:country_code":"CN",
    "gn:dem":235,
    "gn:feature_class":"P",
    "gn:feature_code":"PPL",
    "gn:name":"Zhengcheng",
    "gn:population":0,
    "gn:timezone":"Asia/Shanghai",
    "iso:country":"CN",
    "name:und_x_variant":[
        "Cheng-ch\u2019eng",
        "Zhengcheng"
    ],
    "wof:name":"Zhengcheng",
    "wof:placetype":"locality"
},
  "geometry": {"coordinates":[117.66667,35.26667],"type":"Point"}
}