{
  "type": "Feature",
  "properties": {
    "gn:admin1_code":"16.0",
    "gn:asciiname":"Jiaohuai",
    "gn:country_code":"CN",
    "gn:dem":847,
    "gn:feature_class":"P",
    "gn:feature_code":"PPL",
    "gn:name":"Jiaohuai",
    "gn:population":0,
    "gn:timezone":"Asia/Shanghai",
    "iso:country":"CN",
    "name:zho_x_preferred":[
        "\u4ea4\u6000"
    ],
    "wof:name":"Jiaohuai",
    "wof:placetype":"locality"
},
  "geometry": {"coordinates":[106.101,23.3078],"type":"Point"}
}