{
  "type": "Feature",
  "properties": {
    "gn:admin1_code":"11.0",
    "gn:asciiname":"Toudushui",
    "gn:country_code":"CN",
    "gn:dem":128,
    "gn:feature_class":"P",
    "gn:feature_code":"PPL",
    "gn:name":"Toudushui",
    "gn:population":0,
    "gn:timezone":"Asia/Shanghai",
    "iso:country":"CN",
    "name:zho_x_preferred":[
        "\u5934\u6e21\u6c34"
    ],
    "wof:name":"Toudushui",
    "wof:placetype":"locality"
},
  "geometry": {"coordinates":[112.0979,28.18476],"type":"Point"}
}