{
  "type": "Feature",
  "properties": {
    "gn:admin1_code":"15.0",
    "gn:asciiname":"Kutanyu",
    "gn:country_code":"CN",
    "gn:dem":1721,
    "gn:feature_class":"P",
    "gn:feature_code":"PPL",
    "gn:name":"Kutanyu",
    "gn:population":0,
    "gn:timezone":"Asia/Shanghai",
    "iso:country":"CN",
    "name:und_x_variant":[
        "\u5e93\u6f6d\u5cea"
    ],
    "name:zho_x_preferred":[
        "\u5e93\u6f6d\u5cea"
    ],
    "wof:name":"Kutanyu",
    "wof:placetype":"locality"
},
  "geometry": {"coordinates":[105.00532,33.64659],"type":"Point"}
}