{
  "type": "Feature",
  "properties": {
    "gn:admin1_code":"15.0",
    "gn:asciiname":"Jianzang",
    "gn:country_code":"CN",
    "gn:dem":2070,
    "gn:feature_class":"P",
    "gn:feature_code":"PPL",
    "gn:name":"Jianzang",
    "gn:population":0,
    "gn:timezone":"Asia/Shanghai",
    "iso:country":"CN",
    "name:zho_x_preferred":[
        "\u5c16\u85cf"
    ],
    "wof:name":"Jianzang",
    "wof:placetype":"locality"
},
  "geometry": {"coordinates":[103.92701,34.00987],"type":"Point"}
}