{
  "type": "Feature",
  "properties": {
    "gn:admin1_code":"3.0",
    "gn:asciiname":"Pingjiayuan",
    "gn:country_code":"CN",
    "gn:dem":921,
    "gn:feature_class":"P",
    "gn:feature_code":"PPL",
    "gn:name":"Pingjiayuan",
    "gn:population":0,
    "gn:timezone":"Asia/Shanghai",
    "iso:country":"CN",
    "name:zho_x_preferred":[
        "\u5e73\u5bb6\u6e90"
    ],
    "wof:name":"Pingjiayuan",
    "wof:placetype":"locality"
},
  "geometry": {"coordinates":[118.09052,28.98483],"type":"Point"}
}