{
  "type": "Feature",
  "properties": {
    "gn:admin1_code":"26.0",
    "gn:asciiname":"Caizhangjian",
    "gn:country_code":"CN",
    "gn:dem":1639,
    "gn:feature_class":"P",
    "gn:feature_code":"PPL",
    "gn:name":"Caizhangjian",
    "gn:population":0,
    "gn:timezone":"Asia/Shanghai",
    "iso:country":"CN",
    "name:und_x_variant":[
        "\u83dc\u638c\u6da7"
    ],
    "wof:name":"Caizhangjian",
    "wof:placetype":"locality"
},
  "geometry": {"coordinates":[107.64409999999999,36.90869],"type":"Point"}
}