{
  "type": "Feature",
  "properties": {
    "gn:admin1_code":"11.0",
    "gn:asciiname":"Zhengjiachong",
    "gn:country_code":"CN",
    "gn:dem":71,
    "gn:feature_class":"P",
    "gn:feature_code":"PPL",
    "gn:name":"Zhengjiachong",
    "gn:population":0,
    "gn:timezone":"Asia/Shanghai",
    "iso:country":"CN",
    "name:zho_x_preferred":[
        "Zhengjiachong"
    ],
    "name:zho_x_variant":[
        "\u90d1\u5bb6\u51b2"
    ],
    "wof:name":"Zhengjiachong",
    "wof:placetype":"locality"
},
  "geometry": {"coordinates":[111.38336,28.90855],"type":"Point"}
}