{
  "type": "Feature",
  "properties": {
    "gn:admin1_code":"32.0",
    "gn:asciiname":"Xiangqin",
    "gn:country_code":"CN",
    "gn:dem":4072,
    "gn:feature_class":"P",
    "gn:feature_code":"PPL",
    "gn:name":"Xiangqin",
    "gn:population":0,
    "gn:timezone":"Asia/Shanghai",
    "iso:country":"CN",
    "name:zho_x_preferred":[
        "\u9999\u94a6"
    ],
    "wof:name":"Xiangqin",
    "wof:placetype":"locality"
},
  "geometry": {"coordinates":[98.8242,32.6082],"type":"Point"}
}