{
  "type": "Feature",
  "properties": {
    "gn:admin1_code":"1.0",
    "gn:asciiname":"Yucun",
    "gn:country_code":"CN",
    "gn:dem":160,
    "gn:feature_class":"P",
    "gn:feature_code":"PPL",
    "gn:name":"Yucun",
    "gn:population":0,
    "gn:timezone":"Asia/Shanghai",
    "iso:country":"CN",
    "name:und_x_variant":[
        "Y\u00fc-ts\u2019un",
        "Yucun",
        "Yucun Xiang",
        "\u6986\u6751\u4e61"
    ],
    "name:zho_x_preferred":[
        "\u6986\u6751"
    ],
    "wof:name":"Yucun",
    "wof:placetype":"locality"
},
  "geometry": {"coordinates":[118.35657999999999,29.66054],"type":"Point"}
}