{
  "type": "Feature",
  "properties": {
    "gn:admin1_code":"26.0",
    "gn:asciiname":"Lazhushancun",
    "gn:country_code":"CN",
    "gn:dem":1139,
    "gn:feature_class":"P",
    "gn:feature_code":"PPL",
    "gn:name":"Lazhushancun",
    "gn:population":0,
    "gn:timezone":"Asia/Shanghai",
    "iso:country":"CN",
    "name:zho_x_preferred":[
        "\u8721\u70db\u5c71\u6751"
    ],
    "wof:name":"Lazhushancun",
    "wof:placetype":"locality"
},
  "geometry": {"coordinates":[110.27467,33.34650999999999],"type":"Point"}
}