{
  "type": "Feature",
  "properties": {
    "gn:admin1_code":"19.0",
    "gn:asciiname":"Piankanzicun",
    "gn:country_code":"CN",
    "gn:dem":123,
    "gn:feature_class":"P",
    "gn:feature_code":"PPL",
    "gn:name":"Piankanzicun",
    "gn:population":0,
    "gn:timezone":"Asia/Shanghai",
    "iso:country":"CN",
    "name:zho_x_preferred":[
        "\u504f\u574e\u5b50\u6751"
    ],
    "wof:name":"Piankanzicun",
    "wof:placetype":"locality"
},
  "geometry": {"coordinates":[123.944,41.7902],"type":"Point"}
}