{
  "type": "Feature",
  "properties": {
    "gn:admin1_code":"32.0",
    "gn:asciiname":"Xie'erga",
    "gn:country_code":"CN",
    "gn:dem":3040,
    "gn:feature_class":"P",
    "gn:feature_code":"PPL",
    "gn:name":"Xie\u2019erga",
    "gn:population":0,
    "gn:timezone":"Asia/Shanghai",
    "iso:country":"CN",
    "name:und_x_variant":[
        "Xie\u2019erga"
    ],
    "name:zho_x_preferred":[
        "\u659c\u5c14\u5c15"
    ],
    "wof:name":"Xie'erga",
    "wof:placetype":"locality"
},
  "geometry": {"coordinates":[101.53700000000001,32.4463],"type":"Point"}
}