{
  "type": "Feature",
  "properties": {
    "gn:admin1_code":"19.0",
    "gn:asciiname":"Xiaocuitun",
    "gn:country_code":"CN",
    "gn:dem":29,
    "gn:feature_class":"P",
    "gn:feature_code":"PPL",
    "gn:name":"Xiaocuitun",
    "gn:population":0,
    "gn:timezone":"Asia/Shanghai",
    "iso:country":"CN",
    "name:zho_x_preferred":[
        "\u5c0f\u5d14\u5c6f"
    ],
    "wof:name":"Xiaocuitun",
    "wof:placetype":"locality"
},
  "geometry": {"coordinates":[122.256,41.8546],"type":"Point"}
}