{
  "type": "Feature",
  "properties": {
    "gn:admin1_code":"4.0",
    "gn:asciiname":"Sihao",
    "gn:country_code":"CN",
    "gn:dem":4,
    "gn:feature_class":"P",
    "gn:feature_code":"PPL",
    "gn:name":"Sihao",
    "gn:population":0,
    "gn:timezone":"Asia/Shanghai",
    "iso:country":"CN",
    "name:und_x_variant":[
        "\u56db\u53f7"
    ],
    "name:zho_x_preferred":[
        "\u56db\u53f7"
    ],
    "wof:name":"Sihao",
    "wof:placetype":"locality"
},
  "geometry": {"coordinates":[120.45363,32.12716],"type":"Point"}
}