{
  "type": "Feature",
  "properties": {
    "gn:admin1_code":"29.0",
    "gn:asciiname":"Guanwengzhai",
    "gn:country_code":"CN",
    "gn:dem":1376,
    "gn:feature_class":"P",
    "gn:feature_code":"PPL",
    "gn:name":"Guanwengzhai",
    "gn:population":0,
    "gn:timezone":"Asia/Shanghai",
    "iso:country":"CN",
    "name:zho_x_preferred":[
        "\u7ba1\u7fc1\u5be8"
    ],
    "wof:name":"Guanwengzhai",
    "wof:placetype":"locality"
},
  "geometry": {"coordinates":[99.0081,25.0371],"type":"Point"}
}