{
  "type": "Feature",
  "properties": {
    "gn:admin1_code":"26.0",
    "gn:asciiname":"Zhaishangou",
    "gn:country_code":"CN",
    "gn:dem":1001,
    "gn:feature_class":"P",
    "gn:feature_code":"PPL",
    "gn:name":"Zhaishangou",
    "gn:population":0,
    "gn:timezone":"Asia/Shanghai",
    "iso:country":"CN",
    "name:zho_x_preferred":[
        "\u5be8\u5c71\u6c9f"
    ],
    "wof:name":"Zhaishangou",
    "wof:placetype":"locality"
},
  "geometry": {"coordinates":[110.03422999999999,37.84562],"type":"Point"}
}