{
  "type": "Feature",
  "properties": {
    "gn:admin1_code":"26.0",
    "gn:asciiname":"Erdaohe",
    "gn:country_code":"CN",
    "gn:dem":734,
    "gn:feature_class":"P",
    "gn:feature_code":"PPL",
    "gn:name":"Erdaohe",
    "gn:population":0,
    "gn:timezone":"Asia/Shanghai",
    "iso:country":"CN",
    "name:zho_x_preferred":[
        "\u4e8c\u9053\u6cb3"
    ],
    "wof:name":"Erdaohe",
    "wof:placetype":"locality"
},
  "geometry": {"coordinates":[109.72377,33.4596],"type":"Point"}
}