{
  "type": "Feature",
  "properties": {
    "gn:admin1_code":"16.0",
    "gn:asciiname":"Malu",
    "gn:country_code":"CN",
    "gn:dem":158,
    "gn:feature_class":"P",
    "gn:feature_code":"PPL",
    "gn:name":"Malu",
    "gn:population":0,
    "gn:timezone":"Asia/Shanghai",
    "iso:country":"CN",
    "name:cat_x_preferred":[
        "Malu"
    ],
    "name:ell_x_preferred":[
        "\u039c\u03b1\u03bb\u03bf\u03cd"
    ],
    "name:fra_x_preferred":[
        "Malu"
    ],
    "name:hrv_x_preferred":[
        "Malu"
    ],
    "name:new_x_preferred":[
        "\u092e\u093e\u0932\u0941"
    ],
    "name:zho_x_preferred":[
        "\u9a6c\u9e7f"
    ],
    "wof:name":"Malu",
    "wof:placetype":"locality"
},
  "geometry": {"coordinates":[108.157,23.774],"type":"Point"}
}