{
  "type": "Feature",
  "properties": {
    "gn:admin1_code":"12.0",
    "gn:asciiname":"Tonghu",
    "gn:country_code":"CN",
    "gn:dem":58,
    "gn:feature_class":"P",
    "gn:feature_code":"PPL",
    "gn:name":"Tonghu",
    "gn:population":0,
    "gn:timezone":"Asia/Shanghai",
    "iso:country":"CN",
    "name:zho_x_preferred":[
        "Tonghu"
    ],
    "name:zho_x_variant":[
        "\u4f5f\u6e56"
    ],
    "wof:name":"Tonghu",
    "wof:placetype":"locality"
},
  "geometry": {"coordinates":[111.91519,30.9235],"type":"Point"}
}