{
  "type": "Feature",
  "properties": {
    "gn:admin1_code":"6.0",
    "gn:asciiname":"Dayu",
    "gn:country_code":"CN",
    "gn:dem":2741,
    "gn:feature_class":"P",
    "gn:feature_code":"PPL",
    "gn:name":"Dayu",
    "gn:population":0,
    "gn:timezone":"Asia/Shanghai",
    "iso:country":"CN",
    "name:und_x_variant":[
        "\u8fbe\u7389"
    ],
    "wof:name":"Dayu",
    "wof:placetype":"locality"
},
  "geometry": {"coordinates":[100.72926,35.96400999999999],"type":"Point"}
}