{
  "type": "Feature",
  "properties": {
    "gn:admin1_code":"5.0",
    "gn:asciiname":"Renjia Buzii",
    "gn:country_code":"CN",
    "gn:dem":191,
    "gn:feature_class":"P",
    "gn:feature_code":"PPL",
    "gn:name":"Renjia Buzii",
    "gn:population":0,
    "gn:timezone":"Asia/Shanghai",
    "iso:country":"CN",
    "name:zho_x_preferred":[
        "\u4efb\u5bb6\u5821\u5b50"
    ],
    "wof:name":"Renjia Buzii",
    "wof:placetype":"locality"
},
  "geometry": {"coordinates":[124.44168999999999,43.48784000000001],"type":"Point"}
}