{
  "type": "Feature",
  "properties": {
    "gn:admin1_code":"9.0",
    "gn:asciiname":"Balipo",
    "gn:country_code":"CN",
    "gn:dem":681,
    "gn:feature_class":"P",
    "gn:feature_code":"PPL",
    "gn:name":"Balipo",
    "gn:population":0,
    "gn:timezone":"Asia/Shanghai",
    "iso:country":"CN",
    "name:und_x_variant":[
        "\u516b\u91cc\u5761",
        "Balipo"
    ],
    "wof:name":"Balipo",
    "wof:placetype":"locality"
},
  "geometry": {"coordinates":[112.03628999999999,33.56055],"type":"Point"}
}