{
  "type": "Feature",
  "properties": {
    "gn:admin1_code":"29.0",
    "gn:asciiname":"Mansao",
    "gn:country_code":"CN",
    "gn:dem":1175,
    "gn:feature_class":"P",
    "gn:feature_code":"PPL",
    "gn:name":"Mansao",
    "gn:population":0,
    "gn:timezone":"Asia/Shanghai",
    "iso:country":"CN",
    "name:zho_x_preferred":[
        "\u66fc\u626b"
    ],
    "wof:name":"Mansao",
    "wof:placetype":"locality"
},
  "geometry": {"coordinates":[100.428,21.9644],"type":"Point"}
}