{
  "type": "Feature",
  "properties": {
    "gn:admin1_code":"29.0",
    "gn:asciiname":"Maidishan",
    "gn:country_code":"CN",
    "gn:dem":1917,
    "gn:feature_class":"P",
    "gn:feature_code":"PPL",
    "gn:name":"Maidishan",
    "gn:population":0,
    "gn:timezone":"Asia/Shanghai",
    "iso:country":"CN",
    "name:zho_x_preferred":[
        "\u9ea6\u5730\u5c71"
    ],
    "wof:name":"Maidishan",
    "wof:placetype":"locality"
},
  "geometry": {"coordinates":[101.18300000000001,25.2411],"type":"Point"}
}