{
  "type": "Feature",
  "properties": {
    "gn:admin1_code":"29.0",
    "gn:asciiname":"Yiludi",
    "gn:country_code":"CN",
    "gn:dem":1609,
    "gn:feature_class":"P",
    "gn:feature_code":"PPL",
    "gn:name":"Yiludi",
    "gn:population":0,
    "gn:timezone":"Asia/Shanghai",
    "iso:country":"CN",
    "name:zho_x_preferred":[
        "\u4f9d\u6cf8\u5e95"
    ],
    "wof:name":"Yiludi",
    "wof:placetype":"locality"
},
  "geometry": {"coordinates":[98.89830000000001,27.2566],"type":"Point"}
}