{
  "type": "Feature",
  "properties": {
    "gn:admin1_code":"18",
    "gn:asciiname":"Baimuyuan",
    "gn:country_code":"CN",
    "gn:dem":822,
    "gn:feature_class":"P",
    "gn:feature_code":"PPL",
    "gn:name":"Baimuyuan",
    "gn:population":0,
    "gn:timezone":"Asia/Shanghai",
    "iso:country":"CN",
    "name:zho_x_preferred":[
        "\u67cf\u6728\u56ed"
    ],
    "wof:name":"Baimuyuan",
    "wof:placetype":"locality"
},
  "geometry": {"coordinates":[108.01600000000001,28.6343],"type":"Point"}
}