{
  "type": "Feature",
  "properties": {
    "gn:admin1_code":"32.0",
    "gn:asciiname":"Hetaoshu",
    "gn:country_code":"CN",
    "gn:dem":2641,
    "gn:feature_class":"P",
    "gn:feature_code":"PPL",
    "gn:name":"Hetaoshu",
    "gn:population":0,
    "gn:timezone":"Asia/Shanghai",
    "iso:country":"CN",
    "name:zho_x_preferred":[
        "\u6838\u6843\u6811"
    ],
    "wof:name":"Hetaoshu",
    "wof:placetype":"locality"
},
  "geometry": {"coordinates":[102.414,31.0909],"type":"Point"}
}