{
  "type": "Feature",
  "properties": {
    "gn:admin1_code":"32.0",
    "gn:asciiname":"Dachun",
    "gn:country_code":"CN",
    "gn:dem":1937,
    "gn:feature_class":"P",
    "gn:feature_code":"PPL",
    "gn:name":"Dachun",
    "gn:population":0,
    "gn:timezone":"Asia/Shanghai",
    "iso:country":"CN",
    "name:zho_x_preferred":[
        "\u5927\u6625"
    ],
    "wof:name":"Dachun",
    "wof:placetype":"locality"
},
  "geometry": {"coordinates":[102.215,28.2682],"type":"Point"}
}