{
  "type": "Feature",
  "properties": {
    "gn:admin1_code":"15.0",
    "gn:asciiname":"Shangdaoyugou",
    "gn:country_code":"CN",
    "gn:dem":2397,
    "gn:feature_class":"P",
    "gn:feature_code":"PPL",
    "gn:name":"Shangdaoyugou",
    "gn:population":0,
    "gn:timezone":"Asia/Shanghai",
    "iso:country":"CN",
    "name:zho_x_preferred":[
        "\u4e0a\u9053\u5cea\u6c9f"
    ],
    "wof:name":"Shangdaoyugou",
    "wof:placetype":"locality"
},
  "geometry": {"coordinates":[104.21259000000001,33.66152],"type":"Point"}
}