{
  "type": "Feature",
  "properties": {
    "gn:admin1_code":"15.0",
    "gn:asciiname":"Shiyanggou",
    "gn:country_code":"CN",
    "gn:dem":2169,
    "gn:feature_class":"P",
    "gn:feature_code":"PPL",
    "gn:name":"Shiyanggou",
    "gn:population":0,
    "gn:timezone":"Asia/Shanghai",
    "iso:country":"CN",
    "name:zho_x_preferred":[
        "\u77f3\u7f8a\u6c9f"
    ],
    "wof:name":"Shiyanggou",
    "wof:placetype":"locality"
},
  "geometry": {"coordinates":[103.893,37.0019],"type":"Point"}
}