{
  "type": "Feature",
  "properties": {
    "gn:admin1_code":"15",
    "gn:asciiname":"Changzheng",
    "gn:cc2":"CN",
    "gn:country_code":"CN",
    "gn:dem":1806,
    "gn:feature_class":"P",
    "gn:feature_code":"PPL",
    "gn:name":"Changzheng",
    "gn:population":0,
    "gn:timezone":"Asia/Shanghai",
    "iso:country":"CN",
    "name:und_x_variant":[
        "Changzhengzhan",
        "Changzheng"
    ],
    "wof:name":"Changzheng",
    "wof:placetype":"locality"
},
  "geometry": {"coordinates":[105.03167000000001,36.66278],"type":"Point"}
}