{
  "type": "Feature",
  "properties": {
    "gn:admin1_code":"05",
    "gn:asciiname":"Yanjiang",
    "gn:country_code":"CN",
    "gn:dem":566,
    "gn:feature_class":"P",
    "gn:feature_code":"PPL",
    "gn:name":"Yanjiang",
    "gn:population":0,
    "gn:timezone":"Asia/Shanghai",
    "iso:country":"CN",
    "wof:name":"Yanjiang",
    "wof:placetype":"locality"
},
  "geometry": {"coordinates":[127.81806,42.72],"type":"Point"}
}