{
  "type": "Feature",
  "properties": {
    "gn:admin1_code":"29.0",
    "gn:asciiname":"Dafengyan",
    "gn:country_code":"CN",
    "gn:dem":1458,
    "gn:feature_class":"P",
    "gn:feature_code":"PPL",
    "gn:name":"Dafengyan",
    "gn:population":0,
    "gn:timezone":"Asia/Shanghai",
    "iso:country":"CN",
    "name:zho_x_preferred":[
        "\u5927\u98ce\u5ca9"
    ],
    "wof:name":"Dafengyan",
    "wof:placetype":"locality"
},
  "geometry": {"coordinates":[103.952,28.0809],"type":"Point"}
}