{
  "type": "Feature",
  "properties": {
    "gn:admin1_code":"19.0",
    "gn:asciiname":"Daxi Goumencun",
    "gn:country_code":"CN",
    "gn:dem":309,
    "gn:feature_class":"P",
    "gn:feature_code":"PPL",
    "gn:name":"Daxi Goumencun",
    "gn:population":0,
    "gn:timezone":"Asia/Shanghai",
    "iso:country":"CN",
    "name:zho_x_preferred":[
        "\u5927\u897f\u6c9f\u95e8\u6751"
    ],
    "wof:name":"Daxi Goumencun",
    "wof:placetype":"locality"
},
  "geometry": {"coordinates":[120.021,41.2522],"type":"Point"}
}