{
  "type": "Feature",
  "properties": {
    "gn:admin1_code":"7.0",
    "gn:asciiname":"Xinglin",
    "gn:country_code":"CN",
    "gn:dem":16,
    "gn:feature_class":"P",
    "gn:feature_code":"PPLA4",
    "gn:name":"Xinglin",
    "gn:population":0,
    "gn:timezone":"Asia/Shanghai",
    "iso:country":"CN",
    "name:und_x_variant":[
        "Hsing-lin",
        "\u674f\u6797",
        "Xinglin",
        "Xinglin Jiedao",
        "\u674f\u6797\u8857\u9053"
    ],
    "wof:name":"Xinglin",
    "wof:placetype":"locality"
},
  "geometry": {"coordinates":[118.03758999999999,24.56609],"type":"Point"}
}