{
  "type": "Feature",
  "properties": {
    "gn:admin1_code":"26.0",
    "gn:asciiname":"Gaobianzi",
    "gn:country_code":"CN",
    "gn:dem":1393,
    "gn:feature_class":"P",
    "gn:feature_code":"PPL",
    "gn:name":"Gaobianzi",
    "gn:population":0,
    "gn:timezone":"Asia/Shanghai",
    "iso:country":"CN",
    "name:zho_x_preferred":[
        "\u9ad8\u78a5\u5b50"
    ],
    "wof:name":"Gaobianzi",
    "wof:placetype":"locality"
},
  "geometry": {"coordinates":[109.06303,33.87473],"type":"Point"}
}