{
  "type": "Feature",
  "properties": {
    "gn:admin1_code":"29",
    "gn:asciiname":"Gantianbu",
    "gn:country_code":"CN",
    "gn:dem":1404,
    "gn:feature_class":"P",
    "gn:feature_code":"PPL",
    "gn:name":"Gantianbu",
    "gn:population":0,
    "gn:timezone":"Asia/Shanghai",
    "iso:country":"CN",
    "name:zho_x_preferred":[
        "\u5e72\u7530\u5821"
    ],
    "wof:name":"Gantianbu",
    "wof:placetype":"locality"
},
  "geometry": {"coordinates":[105.315,23.5147],"type":"Point"}
}