{
  "type": "Feature",
  "properties": {
    "gn:admin1_code":"19.0",
    "gn:asciiname":"Baimiaozicun",
    "gn:country_code":"CN",
    "gn:dem":31,
    "gn:feature_class":"P",
    "gn:feature_code":"PPL",
    "gn:name":"Baimiaozicun",
    "gn:population":0,
    "gn:timezone":"Asia/Shanghai",
    "iso:country":"CN",
    "name:zho_x_preferred":[
        "\u767d\u5e99\u5b50\u6751"
    ],
    "wof:name":"Baimiaozicun",
    "wof:placetype":"locality"
},
  "geometry": {"coordinates":[121.88200000000001,41.5944],"type":"Point"}
}