{
  "type": "Feature",
  "properties": {
    "gn:admin1_code":"11.0",
    "gn:asciiname":"Songyaling",
    "gn:country_code":"CN",
    "gn:dem":88,
    "gn:feature_class":"P",
    "gn:feature_code":"PPL",
    "gn:name":"Songyaling",
    "gn:population":0,
    "gn:timezone":"Asia/Shanghai",
    "iso:country":"CN",
    "name:zho_x_preferred":[
        "\u9882\u96c5\u5cad"
    ],
    "wof:name":"Songyaling",
    "wof:placetype":"locality"
},
  "geometry": {"coordinates":[113.35486000000002,27.88556],"type":"Point"}
}