{
  "type": "Feature",
  "properties": {
    "gn:admin1_code":"30.0",
    "gn:asciiname":"Hongshan",
    "gn:country_code":"CN",
    "gn:dem":11,
    "gn:feature_class":"P",
    "gn:feature_code":"PPLA4",
    "gn:name":"Hongshan",
    "gn:population":0,
    "gn:timezone":"Asia/Shanghai",
    "iso:country":"CN",
    "name:ceb_x_preferred":[
        "Hongshan"
    ],
    "name:deu_x_preferred":[
        "Hongshan"
    ],
    "name:fra_x_preferred":[
        "Hongshan"
    ],
    "name:kor_x_preferred":[
        "\ud6d9\uc0b0\uad6c"
    ],
    "name:nor_x_preferred":[
        "Hongshan"
    ],
    "name:swe_x_preferred":[
        "Hongshan"
    ],
    "name:und_x_variant":[
        "Hongshan Jiedao"
    ],
    "name:zho_x_preferred":[
        "\u7ea2\u5c71"
    ],
    "name:zho_x_variant":[
        "\u7ea2\u5c71\u8857\u9053"
    ],
    "wof:name":"Hongshan",
    "wof:placetype":"locality"
},
  "geometry": {"coordinates":[113.46581,23.10253],"type":"Point"}
}