{
  "type": "Feature",
  "properties": {
    "gn:admin1_code":"25.0",
    "gn:asciiname":"Xiaodongjia",
    "gn:country_code":"CN",
    "gn:dem":49,
    "gn:feature_class":"P",
    "gn:feature_code":"PPL",
    "gn:name":"Xiaodongjia",
    "gn:population":0,
    "gn:timezone":"Asia/Shanghai",
    "iso:country":"CN",
    "name:zho_x_preferred":[
        "\u5c0f\u8463\u5bb6"
    ],
    "wof:name":"Xiaodongjia",
    "wof:placetype":"locality"
},
  "geometry": {"coordinates":[120.23972999999999,37.46386],"type":"Point"}
}