{
  "type": "Feature",
  "properties": {
    "gn:admin1_code":"9.0",
    "gn:asciiname":"Xiping",
    "gn:country_code":"CN",
    "gn:dem":208,
    "gn:feature_class":"P",
    "gn:feature_code":"PPL",
    "gn:name":"Xiping",
    "gn:population":0,
    "gn:timezone":"Asia/Shanghai",
    "iso:country":"CN",
    "name:ceb_x_preferred":[
        "Xiping"
    ],
    "name:deu_x_preferred":[
        "Xiping"
    ],
    "name:nor_x_preferred":[
        "Xiping"
    ],
    "name:und_x_variant":[
        "\u897f\u576a"
    ],
    "wof:name":"Xiping",
    "wof:placetype":"locality"
},
  "geometry": {"coordinates":[112.69461,33.46511],"type":"Point"}
}