{
  "type": "Feature",
  "properties": {
    "gn:admin1_code":"8.0",
    "gn:asciiname":"Minzhong",
    "gn:country_code":"CN",
    "gn:dem":167,
    "gn:feature_class":"P",
    "gn:feature_code":"PPL",
    "gn:name":"Minzhong",
    "gn:population":0,
    "gn:timezone":"Asia/Shanghai",
    "iso:country":"CN",
    "name:zho_x_preferred":[
        "\u6c11\u4f17"
    ],
    "wof:name":"Minzhong",
    "wof:placetype":"locality"
},
  "geometry": {"coordinates":[124.16098999999998,47.95967],"type":"Point"}
}