{
  "type": "Feature",
  "properties": {
    "gn:admin1_code":"30",
    "gn:asciiname":"Fuxing'an",
    "gn:country_code":"CN",
    "gn:dem":175,
    "gn:feature_class":"P",
    "gn:feature_code":"PPL",
    "gn:name":"Fuxing\u2019an",
    "gn:population":0,
    "gn:timezone":"Asia/Shanghai",
    "iso:country":"CN",
    "name:zho_x_preferred":[
        "\u798f\u5174\u5eb5"
    ],
    "name:zho_x_variant":[
        "Fuxing\u2019an"
    ],
    "wof:name":"Fuxing'an",
    "wof:placetype":"locality"
},
  "geometry": {"coordinates":[116.33450999999999,24.52486],"type":"Point"}
}