{
  "type": "Feature",
  "properties": {
    "gn:admin1_code":"3",
    "gn:asciiname":"Fengkeng",
    "gn:country_code":"CN",
    "gn:dem":171,
    "gn:feature_class":"P",
    "gn:feature_code":"PPL",
    "gn:name":"Fengkeng",
    "gn:population":0,
    "gn:timezone":"Asia/Shanghai",
    "iso:country":"CN",
    "name:zho_x_preferred":[
        "\u67ab\u5751"
    ],
    "wof:name":"Fengkeng",
    "wof:placetype":"locality"
},
  "geometry": {"coordinates":[114.861,25.1635],"type":"Point"}
}