{
  "type": "Feature",
  "properties": {
    "gn:admin1_code":"4.0",
    "gn:asciiname":"Suxiang",
    "gn:country_code":"CN",
    "gn:dem":3,
    "gn:feature_class":"P",
    "gn:feature_code":"PPL",
    "gn:name":"Suxiang",
    "gn:population":0,
    "gn:timezone":"Asia/Shanghai",
    "iso:country":"CN",
    "name:zho_x_preferred":[
        "Suxiang"
    ],
    "name:zho_x_variant":[
        "\u82cf\u5df7"
    ],
    "wof:name":"Suxiang",
    "wof:placetype":"locality"
},
  "geometry": {"coordinates":[121.79179000000001,31.94112],"type":"Point"}
}