{
  "type": "Feature",
  "properties": {
    "gn:admin1_code":"21",
    "gn:asciiname":"Guoyangwa",
    "gn:country_code":"CN",
    "gn:dem":1706,
    "gn:feature_class":"P",
    "gn:feature_code":"PPL",
    "gn:name":"Guoyangwa",
    "gn:population":0,
    "gn:timezone":"Asia/Shanghai",
    "iso:country":"CN",
    "name:und_x_variant":[
        "\u90ed\u9633\u6d3c",
        "Guojiayangwa"
    ],
    "wof:name":"Guoyangwa",
    "wof:placetype":"locality"
},
  "geometry": {"coordinates":[106.26353,36.92021],"type":"Point"}
}