{
  "type": "Feature",
  "properties": {
    "gn:admin1_code":"13",
    "gn:asciiname":"Wulasi Tanhasa",
    "gn:country_code":"CN",
    "gn:dem":2508,
    "gn:feature_class":"P",
    "gn:feature_code":"PPL",
    "gn:name":"Wulasi Tanhasa",
    "gn:population":0,
    "gn:timezone":"Asia/Urumqi",
    "iso:country":"CN",
    "name:und_x_variant":[
        "\u4e4c\u62c9\u65af\u5766\u54c8\u8428"
    ],
    "wof:name":"Wulasi Tanhasa",
    "wof:placetype":"locality"
},
  "geometry": {"coordinates":[85.76048,43.37668],"type":"Point"}
}