{
  "type": "Feature",
  "properties": {
    "gn:admin1_code":"07",
    "gn:asciiname":"Shuijiao",
    "gn:country_code":"CN",
    "gn:dem":914,
    "gn:feature_class":"P",
    "gn:feature_code":"PPL",
    "gn:name":"Shuijiao",
    "gn:population":0,
    "gn:timezone":"Asia/Shanghai",
    "iso:country":"CN",
    "name:zho_x_preferred":[
        "\u6c34\u90ca"
    ],
    "wof:name":"Shuijiao",
    "wof:placetype":"locality"
},
  "geometry": {"coordinates":[117.91916999999999,25.60333],"type":"Point"}
}