{
  "type": "Feature",
  "properties": {
    "gn:admin1_code":"26.0",
    "gn:asciiname":"Luze Goucun",
    "gn:country_code":"CN",
    "gn:dem":1058,
    "gn:feature_class":"P",
    "gn:feature_code":"PPL",
    "gn:name":"Luze Goucun",
    "gn:population":0,
    "gn:timezone":"Asia/Shanghai",
    "iso:country":"CN",
    "name:zho_x_preferred":[
        "\u82a6\u5219\u6c9f\u6751"
    ],
    "wof:name":"Luze Goucun",
    "wof:placetype":"locality"
},
  "geometry": {"coordinates":[109.827,37.8163],"type":"Point"}
}