{
  "type": "Feature",
  "properties": {
    "gn:admin1_code":"10",
    "gn:asciiname":"Daliu",
    "gn:country_code":"CN",
    "gn:dem":65,
    "gn:feature_class":"P",
    "gn:feature_code":"PPL",
    "gn:name":"Daliu",
    "gn:population":0,
    "gn:timezone":"Asia/Shanghai",
    "iso:country":"CN",
    "name:und_x_variant":[
        "\u5927\u6d41"
    ],
    "wof:name":"Daliu",
    "wof:placetype":"locality"
},
  "geometry": {"coordinates":[114.78360000000001,38.32592],"type":"Point"}
}