{
  "type": "Feature",
  "properties": {
    "gn:admin1_code":"14.0",
    "gn:asciiname":"Ninong",
    "gn:country_code":"CN",
    "gn:dem":4859,
    "gn:feature_class":"P",
    "gn:feature_code":"PPL",
    "gn:name":"Ninong",
    "gn:population":0,
    "gn:timezone":"Asia/Urumqi",
    "iso:country":"CN",
    "name:zho_x_preferred":[
        "\u6ce5\u5f04"
    ],
    "wof:name":"Ninong",
    "wof:placetype":"locality"
},
  "geometry": {"coordinates":[91.17085,31.00565],"type":"Point"}
}