{
  "type": "Feature",
  "properties": {
    "gn:admin1_code":"15.0",
    "gn:asciiname":"Sandaozhuang",
    "gn:country_code":"CN",
    "gn:dem":1367,
    "gn:feature_class":"P",
    "gn:feature_code":"PPL",
    "gn:name":"Sandaozhuang",
    "gn:population":0,
    "gn:timezone":"Asia/Shanghai",
    "iso:country":"CN",
    "name:zho_x_preferred":[
        "\u4e09\u9053\u5e84"
    ],
    "wof:name":"Sandaozhuang",
    "wof:placetype":"locality"
},
  "geometry": {"coordinates":[108.36,36.2813],"type":"Point"}
}