{
  "type": "Feature",
  "properties": {
    "gn:admin1_code":"12.0",
    "gn:asciiname":"Weijiahu",
    "gn:country_code":"CN",
    "gn:dem":355,
    "gn:feature_class":"P",
    "gn:feature_code":"PPL",
    "gn:name":"Weijiahu",
    "gn:population":0,
    "gn:timezone":"Asia/Shanghai",
    "iso:country":"CN",
    "name:zho_x_preferred":[
        "Weijiahu"
    ],
    "name:zho_x_variant":[
        "\u536b\u5bb6\u6e56"
    ],
    "wof:name":"Weijiahu",
    "wof:placetype":"locality"
},
  "geometry": {"coordinates":[114.92973000000001,29.91012000000001],"type":"Point"}
}