{
  "type": "Feature",
  "properties": {
    "gn:admin1_code":"8.0",
    "gn:asciiname":"Quanhaocun",
    "gn:country_code":"CN",
    "gn:dem":162,
    "gn:feature_class":"P",
    "gn:feature_code":"PPL",
    "gn:name":"Quanhaocun",
    "gn:population":0,
    "gn:timezone":"Asia/Shanghai",
    "iso:country":"CN",
    "name:zho_x_preferred":[
        "\u5168\u597d\u6751"
    ],
    "wof:name":"Quanhaocun",
    "wof:placetype":"locality"
},
  "geometry": {"coordinates":[124.94103,47.53184],"type":"Point"}
}