{
  "type": "Feature",
  "properties": {
    "gn:admin1_code":"1.0",
    "gn:asciiname":"Hunanocun",
    "gn:country_code":"CN",
    "gn:dem":6,
    "gn:feature_class":"P",
    "gn:feature_code":"PPL",
    "gn:name":"Hunanocun",
    "gn:population":0,
    "gn:timezone":"Asia/Shanghai",
    "iso:country":"CN",
    "name:zho_x_preferred":[
        "\u80e1\u57b4\u6751"
    ],
    "wof:name":"Hunanocun",
    "wof:placetype":"locality"
},
  "geometry": {"coordinates":[118.17836,31.38437],"type":"Point"}
}