{
  "type": "Feature",
  "properties": {
    "gn:admin1_code":"14.0",
    "gn:asciiname":"Ridigang",
    "gn:country_code":"CN",
    "gn:dem":4482,
    "gn:feature_class":"P",
    "gn:feature_code":"PPL",
    "gn:name":"Ridigang",
    "gn:population":0,
    "gn:timezone":"Asia/Shanghai",
    "iso:country":"CN",
    "name:zho_x_preferred":[
        "\u65e5\u5e95\u5c97"
    ],
    "wof:name":"Ridigang",
    "wof:placetype":"locality"
},
  "geometry": {"coordinates":[79.2281,31.5315],"type":"Point"}
}