{
  "type": "Feature",
  "properties": {
    "gn:admin1_code":"29.0",
    "gn:asciiname":"Shizhupo",
    "gn:country_code":"CN",
    "gn:dem":2200,
    "gn:feature_class":"P",
    "gn:feature_code":"PPL",
    "gn:name":"Shizhupo",
    "gn:population":0,
    "gn:timezone":"Asia/Shanghai",
    "iso:country":"CN",
    "name:zho_x_preferred":[
        "\u77f3\u7af9\u5761"
    ],
    "wof:name":"Shizhupo",
    "wof:placetype":"locality"
},
  "geometry": {"coordinates":[99.77330000000001,25.6979],"type":"Point"}
}