{
  "type": "Feature",
  "properties": {
    "gn:admin1_code":"1.0",
    "gn:asciiname":"Renxinghe",
    "gn:country_code":"CN",
    "gn:dem":35,
    "gn:feature_class":"P",
    "gn:feature_code":"PPL",
    "gn:name":"Renxinghe",
    "gn:population":0,
    "gn:timezone":"Asia/Shanghai",
    "iso:country":"CN",
    "name:zho_x_preferred":[
        "\u4eba\u5f62\u6cb3"
    ],
    "wof:name":"Renxinghe",
    "wof:placetype":"locality"
},
  "geometry": {"coordinates":[116.86266999999999,30.8017],"type":"Point"}
}