{
  "type": "Feature",
  "properties": {
    "gn:admin1_code":"15.0",
    "gn:asciiname":"Shimen",
    "gn:country_code":"CN",
    "gn:dem":2460,
    "gn:feature_class":"P",
    "gn:feature_code":"PPLA4",
    "gn:name":"Shimen",
    "gn:population":0,
    "gn:timezone":"Asia/Shanghai",
    "iso:country":"CN",
    "name:und_x_variant":[
        "\u77f3\u95e8"
    ],
    "wof:name":"Shimen",
    "wof:placetype":"locality"
},
  "geometry": {"coordinates":[103.70148,34.73602],"type":"Point"}
}