{
  "type": "Feature",
  "properties": {
    "gn:admin1_code":"19.0",
    "gn:asciiname":"Chijiatun",
    "gn:country_code":"CN",
    "gn:dem":275,
    "gn:feature_class":"P",
    "gn:feature_code":"PPL",
    "gn:name":"Chijiatun",
    "gn:population":0,
    "gn:timezone":"Asia/Shanghai",
    "iso:country":"CN",
    "name:und_x_variant":[
        "\u8fdf\u5bb6\u5c6f"
    ],
    "wof:name":"Chijiatun",
    "wof:placetype":"locality"
},
  "geometry": {"coordinates":[122.40300000000001,40.0155],"type":"Point"}
}