{
  "type": "Feature",
  "properties": {
    "gn:admin1_code":"29.0",
    "gn:asciiname":"Duokuan",
    "gn:country_code":"CN",
    "gn:dem":2012,
    "gn:feature_class":"P",
    "gn:feature_code":"PPL",
    "gn:name":"Duokuan",
    "gn:population":0,
    "gn:timezone":"Asia/Shanghai",
    "iso:country":"CN",
    "name:zho_x_preferred":[
        "\u591a\u5bbd"
    ],
    "wof:name":"Duokuan",
    "wof:placetype":"locality"
},
  "geometry": {"coordinates":[102.866,25.8757],"type":"Point"}
}