{
  "type": "Feature",
  "properties": {
    "gn:admin1_code":"26.0",
    "gn:asciiname":"Daluwan",
    "gn:country_code":"CN",
    "gn:dem":1517,
    "gn:feature_class":"P",
    "gn:feature_code":"PPL",
    "gn:name":"Daluwan",
    "gn:population":0,
    "gn:timezone":"Asia/Shanghai",
    "iso:country":"CN",
    "name:zho_x_preferred":[
        "\u5927\u8def\u6e7e"
    ],
    "wof:name":"Daluwan",
    "wof:placetype":"locality"
},
  "geometry": {"coordinates":[107.24715,32.71077],"type":"Point"}
}