{
  "type": "Feature",
  "properties": {
    "gn:admin1_code":"15.0",
    "gn:asciiname":"Wujiamo",
    "gn:country_code":"CN",
    "gn:dem":1549,
    "gn:feature_class":"P",
    "gn:feature_code":"PPL",
    "gn:name":"Wujiamo",
    "gn:population":0,
    "gn:timezone":"Asia/Shanghai",
    "iso:country":"CN",
    "name:und_x_variant":[
        "\u5434\u5bb6\u78e8"
    ],
    "wof:name":"Wujiamo",
    "wof:placetype":"locality"
},
  "geometry": {"coordinates":[105.81108999999999,34.0585],"type":"Point"}
}