{
  "type": "Feature",
  "properties": {
    "gn:admin1_code":"31.0",
    "gn:asciiname":"Shimubi",
    "gn:country_code":"CN",
    "gn:dem":117,
    "gn:feature_class":"P",
    "gn:feature_code":"PPL",
    "gn:name":"Shimubi",
    "gn:population":0,
    "gn:timezone":"Asia/Shanghai",
    "iso:country":"CN",
    "name:zho_x_preferred":[
        "\u77f3\u59c6\u58c1"
    ],
    "wof:name":"Shimubi",
    "wof:placetype":"locality"
},
  "geometry": {"coordinates":[110.38443999999998,19.04248],"type":"Point"}
}