{
  "type": "Feature",
  "properties": {
    "gn:admin1_code":"15.0",
    "gn:asciiname":"Fenglapai",
    "gn:country_code":"CN",
    "gn:dem":2008,
    "gn:feature_class":"P",
    "gn:feature_code":"PPL",
    "gn:name":"Fenglapai",
    "gn:population":0,
    "gn:timezone":"Asia/Shanghai",
    "iso:country":"CN",
    "name:zho_x_preferred":[
        "\u98ce\u62c9\u724c"
    ],
    "wof:name":"Fenglapai",
    "wof:placetype":"locality"
},
  "geometry": {"coordinates":[103.99299999999999,36.6232],"type":"Point"}
}