{
  "type": "Feature",
  "properties": {
    "gn:admin1_code":"02",
    "gn:asciiname":"Longbi'ao",
    "gn:country_code":"CN",
    "gn:dem":27,
    "gn:feature_class":"P",
    "gn:feature_code":"PPL",
    "gn:name":"Longbi\u2019ao",
    "gn:population":0,
    "gn:timezone":"Asia/Shanghai",
    "iso:country":"CN",
    "name:und_x_variant":[
        "Longbi\u2019ao"
    ],
    "name:zho_x_preferred":[
        "\u9f99\u907f\u5c99"
    ],
    "wof:name":"Longbi'ao",
    "wof:placetype":"locality"
},
  "geometry": {"coordinates":[121.12025,28.42119000000001],"type":"Point"}
}