{
  "type": "Feature",
  "properties": {
    "gn:admin1_code":"18",
    "gn:asciiname":"Dalongchangcun",
    "gn:country_code":"CN",
    "gn:dem":1376,
    "gn:feature_class":"P",
    "gn:feature_code":"PPL",
    "gn:name":"Dalongchangcun",
    "gn:population":0,
    "gn:timezone":"Asia/Shanghai",
    "iso:country":"CN",
    "name:zho_x_preferred":[
        "\u5927\u9f99\u573a\u6751"
    ],
    "wof:name":"Dalongchangcun",
    "wof:placetype":"locality"
},
  "geometry": {"coordinates":[105.563,26.7969],"type":"Point"}
}