{
  "type": "Feature",
  "properties": {
    "gn:admin1_code":"24.0",
    "gn:asciiname":"Getacun",
    "gn:country_code":"CN",
    "gn:dem":1424,
    "gn:feature_class":"P",
    "gn:feature_code":"PPL",
    "gn:name":"Getacun",
    "gn:population":0,
    "gn:timezone":"Asia/Shanghai",
    "iso:country":"CN",
    "name:zho_x_preferred":[
        "\u572a\u5854\u6751"
    ],
    "wof:name":"Getacun",
    "wof:placetype":"locality"
},
  "geometry": {"coordinates":[111.82894,38.3738],"type":"Point"}
}