{
  "type": "Feature",
  "properties": {
    "gn:admin1_code":"32.0",
    "gn:asciiname":"Guanshangchang",
    "gn:country_code":"CN",
    "gn:dem":518,
    "gn:feature_class":"P",
    "gn:feature_code":"PPL",
    "gn:name":"Guanshangchang",
    "gn:population":0,
    "gn:timezone":"Asia/Shanghai",
    "iso:country":"CN",
    "name:zho_x_preferred":[
        "\u5173\u4e0a\u573a"
    ],
    "wof:name":"Guanshangchang",
    "wof:placetype":"locality"
},
  "geometry": {"coordinates":[103.73961,29.02227],"type":"Point"}
}