{
  "type": "Feature",
  "properties": {
    "gn:admin1_code":"1.0",
    "gn:asciiname":"Yuanping",
    "gn:country_code":"CN",
    "gn:dem":237,
    "gn:feature_class":"P",
    "gn:feature_code":"PPL",
    "gn:name":"Yuanping",
    "gn:population":0,
    "gn:timezone":"Asia/Shanghai",
    "iso:country":"CN",
    "name:ara_x_preferred":[
        "\u0645\u062f\u064a\u0646\u0629 \u064a\u0648\u0627\u0646\u0628\u064a\u0646\u062c"
    ],
    "name:ceb_x_preferred":[
        "Yuanping"
    ],
    "name:deu_x_preferred":[
        "Yuanping"
    ],
    "name:fra_x_preferred":[
        "Yuanping"
    ],
    "name:ita_x_preferred":[
        "Yuanping"
    ],
    "name:jpn_x_preferred":[
        "\u539f\u5e73\u5e02"
    ],
    "name:kik_x_preferred":[
        "Yuanping City"
    ],
    "name:kor_x_preferred":[
        "\uc704\uc548\ud551\uc2dc"
    ],
    "name:nld_x_preferred":[
        "Yuanping"
    ],
    "name:nor_x_preferred":[
        "Yuanping"
    ],
    "name:rus_x_preferred":[
        "\u042e\u0430\u043d\u044c\u043f\u0438\u043d"
    ],
    "name:swe_x_preferred":[
        "Yuanping"
    ],
    "name:urd_x_preferred":[
        "\u06cc\u0648\u0622\u0646\u067e\u0646\u06af \u0633\u0679\u06cc"
    ],
    "name:vie_x_preferred":[
        "Nguy\u00ean B\u00ecnh"
    ],
    "name:zho_x_preferred":[
        "\u539f\u576a"
    ],
    "name:zho_x_variant":[
        "\u539f\u5e73\u5e02"
    ],
    "wof:name":"Yuanping",
    "wof:placetype":"locality"
},
  "geometry": {"coordinates":[118.83326,30.60962],"type":"Point"}
}