{
  "type": "Feature",
  "properties": {
    "gn:admin1_code":"32",
    "gn:asciiname":"Liangshiping",
    "gn:country_code":"CN",
    "gn:dem":302,
    "gn:feature_class":"P",
    "gn:feature_code":"PPL",
    "gn:name":"Liangshiping",
    "gn:population":0,
    "gn:timezone":"Asia/Shanghai",
    "iso:country":"CN",
    "wof:name":"Liangshiping",
    "wof:placetype":"locality"
},
  "geometry": {"coordinates":[105.74666999999999,28.96889],"type":"Point"}
}