{
  "type": "Feature",
  "properties": {
    "gn:admin1_code":"3.0",
    "gn:asciiname":"Louqian",
    "gn:country_code":"CN",
    "gn:dem":129,
    "gn:feature_class":"P",
    "gn:feature_code":"PPL",
    "gn:name":"Louqian",
    "gn:population":0,
    "gn:timezone":"Asia/Shanghai",
    "iso:country":"CN",
    "name:und_x_variant":[
        "\u697c\u524d"
    ],
    "wof:name":"Louqian",
    "wof:placetype":"locality"
},
  "geometry": {"coordinates":[116.97726000000002,27.98012],"type":"Point"}
}