{
  "type": "Feature",
  "properties": {
    "gn:admin1_code":"29",
    "gn:asciiname":"Longli",
    "gn:country_code":"CN",
    "gn:dem":1029,
    "gn:feature_class":"P",
    "gn:feature_code":"PPL",
    "gn:name":"Longli",
    "gn:population":0,
    "gn:timezone":"Asia/Shanghai",
    "iso:country":"CN",
    "name:zho_x_preferred":[
        "\u9f99\u91cc"
    ],
    "wof:name":"Longli",
    "wof:placetype":"locality"
},
  "geometry": {"coordinates":[105.127,24.1672],"type":"Point"}
}