{
  "type": "Feature",
  "properties": {
    "gn:admin1_code":"14.0",
    "gn:asciiname":"Gugong",
    "gn:country_code":"CN",
    "gn:dem":3990,
    "gn:feature_class":"P",
    "gn:feature_code":"PPL",
    "gn:name":"Gugong",
    "gn:population":0,
    "gn:timezone":"Asia/Urumqi",
    "iso:country":"CN",
    "name:zho_x_preferred":[
        "\u987e\u5de5"
    ],
    "wof:name":"Gugong",
    "wof:placetype":"locality"
},
  "geometry": {"coordinates":[94.78707,30.85784],"type":"Point"}
}