{
  "type": "Feature",
  "properties": {
    "gn:admin1_code":"15.0",
    "gn:asciiname":"Dongsi Shilipu",
    "gn:country_code":"CN",
    "gn:dem":2004,
    "gn:feature_class":"P",
    "gn:feature_code":"PPL",
    "gn:name":"Dongsi Shilipu",
    "gn:population":0,
    "gn:timezone":"Asia/Shanghai",
    "iso:country":"CN",
    "name:zho_x_preferred":[
        "\u4e1c\u56db\u5341\u91cc\u94fa"
    ],
    "wof:name":"Dongsi Shilipu",
    "wof:placetype":"locality"
},
  "geometry": {"coordinates":[104.015,35.3344],"type":"Point"}
}