{
  "type": "Feature",
  "properties": {
    "gn:admin1_code":"30",
    "gn:asciiname":"Danshuitang",
    "gn:country_code":"CN",
    "gn:dem":173,
    "gn:feature_class":"P",
    "gn:feature_code":"PPL",
    "gn:name":"Danshuitang",
    "gn:population":0,
    "gn:timezone":"Asia/Shanghai",
    "iso:country":"CN",
    "name:zho_x_preferred":[
        "\u65e6\u6c34\u5858"
    ],
    "wof:name":"Danshuitang",
    "wof:placetype":"locality"
},
  "geometry": {"coordinates":[115.5107,23.64157],"type":"Point"}
}