{
  "type": "Feature",
  "properties": {
    "gn:admin1_code":"18.0",
    "gn:asciiname":"Kongkeng",
    "gn:country_code":"CN",
    "gn:dem":731,
    "gn:feature_class":"P",
    "gn:feature_code":"PPL",
    "gn:name":"Kongkeng",
    "gn:population":0,
    "gn:timezone":"Asia/Shanghai",
    "iso:country":"CN",
    "name:zho_x_preferred":[
        "\u63a7\u5751"
    ],
    "wof:name":"Kongkeng",
    "wof:placetype":"locality"
},
  "geometry": {"coordinates":[108.121,25.9057],"type":"Point"}
}