{
  "type": "Feature",
  "properties": {
    "gn:admin1_code":"15.0",
    "gn:asciiname":"Wutonggou",
    "gn:country_code":"CN",
    "gn:dem":1597,
    "gn:feature_class":"P",
    "gn:feature_code":"PPL",
    "gn:name":"Wutonggou",
    "gn:population":0,
    "gn:timezone":"Asia/Shanghai",
    "iso:country":"CN",
    "name:und_x_variant":[
        "Utungou Well",
        "Khuduk Utungou",
        "Wu-t\u2019ung-kou",
        "Wutonggou"
    ],
    "name:zho_x_preferred":[
        "\u68a7\u6850\u6c9f"
    ],
    "wof:name":"Wutonggou",
    "wof:placetype":"locality"
},
  "geometry": {"coordinates":[98.6114,40.7189],"type":"Point"}
}