{
  "type": "Feature",
  "properties": {
    "gn:admin1_code":"25",
    "gn:asciiname":"Dayang",
    "gn:cc2":"CN",
    "gn:country_code":"CN",
    "gn:dem":69,
    "gn:feature_class":"P",
    "gn:feature_code":"PPL",
    "gn:name":"Dayang",
    "gn:population":0,
    "gn:timezone":"Asia/Shanghai",
    "iso:country":"CN",
    "name:und_x_variant":[
        "Tayang",
        "Ta-yang-chi",
        "Ta-yang-chen",
        "Dayang"
    ],
    "wof:name":"Dayang",
    "wof:placetype":"locality"
},
  "geometry": {"coordinates":[116.48027999999999,36.04833],"type":"Point"}
}