{
  "type": "Feature",
  "properties": {
    "gn:admin1_code":"14.0",
    "gn:asciiname":"Sibta",
    "gn:country_code":"CN",
    "gn:dem":3853,
    "gn:feature_class":"P",
    "gn:feature_code":"PPLF",
    "gn:name":"Sibta",
    "gn:population":0,
    "gn:timezone":"Asia/Urumqi",
    "iso:country":"CN",
    "name:bod_x_preferred":[
        "Sibta"
    ],
    "name:zho_x_preferred":[
        "Seda"
    ],
    "name:zho_x_variant":[
        "\u8272\u8fbe",
        "Sangduo",
        "\u6851\u591a"
    ],
    "wof:name":"Sibta",
    "wof:placetype":"locality"
},
  "geometry": {"coordinates":[96.602,31.202],"type":"Point"}
}