{
  "type": "Feature",
  "properties": {
    "gn:admin1_code":"26.0",
    "gn:asciiname":"Xiaoyang",
    "gn:cc2":"CN",
    "gn:country_code":"CN",
    "gn:dem":887,
    "gn:feature_class":"P",
    "gn:feature_code":"PPL",
    "gn:name":"Xiaoyang",
    "gn:population":0,
    "gn:timezone":"Asia/Shanghai",
    "iso:country":"CN",
    "name:und_x_variant":[
        "Hsiao-yang-pa",
        "Xiaoyangba",
        "Xiaoyang"
    ],
    "wof:name":"Xiaoyang",
    "wof:placetype":"locality"
},
  "geometry": {"coordinates":[107.9375,32.47639],"type":"Point"}
}