{
  "type": "Feature",
  "properties": {
    "gn:admin1_code":"11.0",
    "gn:asciiname":"Ludiping",
    "gn:country_code":"CN",
    "gn:dem":197,
    "gn:feature_class":"P",
    "gn:feature_code":"PPL",
    "gn:name":"Ludiping",
    "gn:population":0,
    "gn:timezone":"Asia/Shanghai",
    "iso:country":"CN",
    "name:zho_x_preferred":[
        "\u82a6\u837b\u576a"
    ],
    "wof:name":"Ludiping",
    "wof:placetype":"locality"
},
  "geometry": {"coordinates":[109.74308000000001,27.22694000000001],"type":"Point"}
}