{
  "type": "Feature",
  "properties": {
    "gn:admin1_code":"7",
    "gn:asciiname":"Huku",
    "gn:country_code":"CN",
    "gn:dem":212,
    "gn:feature_class":"P",
    "gn:feature_code":"PPL",
    "gn:name":"Huku",
    "gn:population":0,
    "gn:timezone":"Asia/Shanghai",
    "iso:country":"CN",
    "name:und_x_variant":[
        "\u547c\u5800"
    ],
    "wof:name":"Huku",
    "wof:placetype":"locality"
},
  "geometry": {"coordinates":[118.82778,27.57667],"type":"Point"}
}