{
  "type": "Feature",
  "properties": {
    "gn:admin1_code":"10.0",
    "gn:asciiname":"Shi'erhu",
    "gn:country_code":"CN",
    "gn:dem":13,
    "gn:feature_class":"P",
    "gn:feature_code":"PPL",
    "gn:name":"Shi\u2019erhu",
    "gn:population":0,
    "gn:timezone":"Asia/Shanghai",
    "iso:country":"CN",
    "name:und_x_variant":[
        "Shi\u2019erhu"
    ],
    "name:zho_x_preferred":[
        "\u5341\u4e8c\u6237"
    ],
    "wof:name":"Shi'erhu",
    "wof:placetype":"locality"
},
  "geometry": {"coordinates":[116.789,38.2837],"type":"Point"}
}