{
  "type": "Feature",
  "properties": {
    "gn:admin1_code":"2",
    "gn:asciiname":"Baimufan",
    "gn:country_code":"CN",
    "gn:dem":113,
    "gn:feature_class":"P",
    "gn:feature_code":"PPL",
    "gn:name":"Baimufan",
    "gn:population":0,
    "gn:timezone":"Asia/Shanghai",
    "iso:country":"CN",
    "name:und_x_variant":[
        "\u767e\u4ea9\u7548"
    ],
    "name:zho_x_preferred":[
        "\u767e\u4ea9\u7548"
    ],
    "wof:name":"Baimufan",
    "wof:placetype":"locality"
},
  "geometry": {"coordinates":[118.61972,29.4325],"type":"Point"}
}