{
  "type": "Feature",
  "properties": {
    "gn:admin1_code":"3.0",
    "gn:asciiname":"Qiufang",
    "gn:country_code":"CN",
    "gn:dem":65,
    "gn:feature_class":"P",
    "gn:feature_code":"PPL",
    "gn:name":"Qiufang",
    "gn:population":0,
    "gn:timezone":"Asia/Shanghai",
    "iso:country":"CN",
    "name:und_x_variant":[
        "\u90b1\u574a"
    ],
    "wof:name":"Qiufang",
    "wof:placetype":"locality"
},
  "geometry": {"coordinates":[116.28404999999999,27.83027],"type":"Point"}
}