{
  "type": "Feature",
  "properties": {
    "gn:admin1_code":"29.0",
    "gn:asciiname":"Shangbangbie",
    "gn:country_code":"CN",
    "gn:dem":1776,
    "gn:feature_class":"P",
    "gn:feature_code":"PPL",
    "gn:name":"Shangbangbie",
    "gn:population":0,
    "gn:timezone":"Asia/Shanghai",
    "iso:country":"CN",
    "name:zho_x_preferred":[
        "\u4e0a\u5e2e\u522b"
    ],
    "wof:name":"Shangbangbie",
    "wof:placetype":"locality"
},
  "geometry": {"coordinates":[99.8779,24.22300000000001],"type":"Point"}
}