{
  "type": "Feature",
  "properties": {
    "gn:admin1_code":"32.0",
    "gn:asciiname":"Daozishang",
    "gn:country_code":"CN",
    "gn:dem":1050,
    "gn:feature_class":"P",
    "gn:feature_code":"PPL",
    "gn:name":"Daozishang",
    "gn:population":0,
    "gn:timezone":"Asia/Shanghai",
    "iso:country":"CN",
    "name:zho_x_preferred":[
        "\u9053\u5b50\u4e0a"
    ],
    "wof:name":"Daozishang",
    "wof:placetype":"locality"
},
  "geometry": {"coordinates":[102.99988999999999,30.13466],"type":"Point"}
}