{
  "type": "Feature",
  "properties": {
    "gn:admin1_code":"31.0",
    "gn:asciiname":"Jiamiao",
    "gn:country_code":"CN",
    "gn:dem":110,
    "gn:feature_class":"P",
    "gn:feature_code":"PPL",
    "gn:name":"Jiamiao",
    "gn:population":0,
    "gn:timezone":"Asia/Shanghai",
    "iso:country":"CN",
    "name:und_x_variant":[
        "\u52a0\u82d7"
    ],
    "wof:name":"Jiamiao",
    "wof:placetype":"locality"
},
  "geometry": {"coordinates":[110.13575,18.92625],"type":"Point"}
}