{
  "type": "Feature",
  "properties": {
    "gn:admin1_code":"26.0",
    "gn:asciiname":"Baishuping",
    "gn:country_code":"CN",
    "gn:dem":1248,
    "gn:feature_class":"P",
    "gn:feature_code":"PPL",
    "gn:name":"Baishuping",
    "gn:population":0,
    "gn:timezone":"Asia/Shanghai",
    "iso:country":"CN",
    "name:und_x_variant":[
        "\u67cf\u6811\u576a"
    ],
    "wof:name":"Baishuping",
    "wof:placetype":"locality"
},
  "geometry": {"coordinates":[106.97238,33.84942],"type":"Point"}
}