{
  "type": "Feature",
  "properties": {
    "gn:admin1_code":"12.0",
    "gn:asciiname":"Zhaoqipo",
    "gn:country_code":"CN",
    "gn:dem":57,
    "gn:feature_class":"P",
    "gn:feature_code":"PPL",
    "gn:name":"Zhaoqipo",
    "gn:population":0,
    "gn:timezone":"Asia/Shanghai",
    "iso:country":"CN",
    "name:zho_x_preferred":[
        "Zhaoqipo"
    ],
    "name:zho_x_variant":[
        "\u62db\u59bb\u5761"
    ],
    "wof:name":"Zhaoqipo",
    "wof:placetype":"locality"
},
  "geometry": {"coordinates":[111.863,29.89908],"type":"Point"}
}