{
  "type": "Feature",
  "properties": {
    "gn:admin1_code":"24.0",
    "gn:asciiname":"Wangjia'ao",
    "gn:country_code":"CN",
    "gn:dem":1082,
    "gn:feature_class":"P",
    "gn:feature_code":"PPL",
    "gn:name":"Wangjia\u2019ao",
    "gn:population":0,
    "gn:timezone":"Asia/Shanghai",
    "iso:country":"CN",
    "name:und_x_variant":[
        "Wangjia\u2019ao",
        "\u738b\u5bb6\u51f9"
    ],
    "wof:name":"Wangjia'ao",
    "wof:placetype":"locality"
},
  "geometry": {"coordinates":[111.51783,35.2818],"type":"Point"}
}