{
  "type": "Feature",
  "properties": {
    "gn:admin1_code":"25",
    "gn:asciiname":"Gejia",
    "gn:country_code":"CN",
    "gn:dem":22,
    "gn:feature_class":"P",
    "gn:feature_code":"PPL",
    "gn:name":"Gejia",
    "gn:population":0,
    "gn:timezone":"Asia/Shanghai",
    "iso:country":"CN",
    "name:zho_x_preferred":[
        "\u845b\u5bb6"
    ],
    "wof:name":"Gejia",
    "wof:placetype":"locality"
},
  "geometry": {"coordinates":[117.14700000000001,36.9371],"type":"Point"}
}