{
  "type": "Feature",
  "properties": {
    "gn:admin1_code":"29.0",
    "gn:asciiname":"Chaganshan",
    "gn:country_code":"CN",
    "gn:dem":894,
    "gn:feature_class":"P",
    "gn:feature_code":"PPL",
    "gn:name":"Chaganshan",
    "gn:population":0,
    "gn:timezone":"Asia/Shanghai",
    "iso:country":"CN",
    "name:zho_x_preferred":[
        "\u5c94\u5e72\u5c71"
    ],
    "wof:name":"Chaganshan",
    "wof:placetype":"locality"
},
  "geometry": {"coordinates":[100.33799999999999,22.8002],"type":"Point"}
}