{
  "type": "Feature",
  "properties": {
    "gn:admin1_code":"18",
    "gn:asciiname":"Huolangchong",
    "gn:country_code":"CN",
    "gn:dem":1772,
    "gn:feature_class":"P",
    "gn:feature_code":"PPL",
    "gn:name":"Huolangchong",
    "gn:population":0,
    "gn:timezone":"Asia/Shanghai",
    "iso:country":"CN",
    "name:zho_x_preferred":[
        "\u8d27\u90ce\u51b2"
    ],
    "wof:name":"Huolangchong",
    "wof:placetype":"locality"
},
  "geometry": {"coordinates":[104.605,25.6176],"type":"Point"}
}