{
  "type": "Feature",
  "properties": {
    "gn:admin1_code":"22.0",
    "gn:asciiname":"Houtaowacun",
    "gn:country_code":"CN",
    "gn:dem":109,
    "gn:feature_class":"P",
    "gn:feature_code":"PPL",
    "gn:name":"Houtaowacun",
    "gn:population":0,
    "gn:timezone":"Asia/Shanghai",
    "iso:country":"CN",
    "name:zho_x_preferred":[
        "\u540e\u6843\u6d3c\u6751"
    ],
    "wof:name":"Houtaowacun",
    "wof:placetype":"locality"
},
  "geometry": {"coordinates":[116.07876,40.23193],"type":"Point"}
}