{
  "type": "Feature",
  "properties": {
    "gn:admin1_code":"5.0",
    "gn:asciiname":"Gonglamacun",
    "gn:country_code":"CN",
    "gn:dem":179,
    "gn:feature_class":"P",
    "gn:feature_code":"PPL",
    "gn:name":"Gonglamacun",
    "gn:population":0,
    "gn:timezone":"Asia/Shanghai",
    "iso:country":"CN",
    "name:zho_x_preferred":[
        "\u516c\u62c9\u739b\u6751"
    ],
    "wof:name":"Gonglamacun",
    "wof:placetype":"locality"
},
  "geometry": {"coordinates":[126.46648,44.07337],"type":"Point"}
}