{
  "type": "Feature",
  "properties": {
    "gn:admin1_code":"2",
    "gn:asciiname":"Longyuan",
    "gn:country_code":"CN",
    "gn:dem":118,
    "gn:feature_class":"P",
    "gn:feature_code":"PPLA4",
    "gn:name":"Longyuan",
    "gn:population":0,
    "gn:timezone":"Asia/Shanghai",
    "iso:country":"CN",
    "name:ceb_x_preferred":[
        "Longyuan"
    ],
    "name:deu_x_preferred":[
        "Longyuan"
    ],
    "name:swe_x_preferred":[
        "Longyuan"
    ],
    "name:und_x_variant":[
        "Longyuan Xiang"
    ],
    "name:zho_x_preferred":[
        "\u9f99\u6e90"
    ],
    "name:zho_x_variant":[
        "\u9f99\u6e90\u4e61"
    ],
    "wof:name":"Longyuan",
    "wof:placetype":"locality"
},
  "geometry": {"coordinates":[118.58687,29.40206],"type":"Point"}
}