{
  "type": "Feature",
  "properties": {
    "gn:admin1_code":"7",
    "gn:asciiname":"Qianxue",
    "gn:country_code":"CN",
    "gn:dem":14,
    "gn:feature_class":"P",
    "gn:feature_code":"PPL",
    "gn:name":"Qianxue",
    "gn:population":0,
    "gn:timezone":"Asia/Shanghai",
    "iso:country":"CN",
    "name:und_x_variant":[
        "Ch\u2019ien-hsieh",
        "Qianxue"
    ],
    "name:zho_x_preferred":[
        "\u524d\u859b"
    ],
    "wof:name":"Qianxue",
    "wof:placetype":"locality"
},
  "geometry": {"coordinates":[119.44897,25.46119],"type":"Point"}
}