{
  "type": "Feature",
  "properties": {
    "gn:admin1_code":"16.0",
    "gn:asciiname":"Shilongbao",
    "gn:country_code":"CN",
    "gn:dem":1018,
    "gn:feature_class":"P",
    "gn:feature_code":"PPL",
    "gn:name":"Shilongbao",
    "gn:population":0,
    "gn:timezone":"Asia/Shanghai",
    "iso:country":"CN",
    "name:zho_x_preferred":[
        "\u5341\u9f99\u4fdd"
    ],
    "wof:name":"Shilongbao",
    "wof:placetype":"locality"
},
  "geometry": {"coordinates":[105.381,24.2128],"type":"Point"}
}