{
  "type": "Feature",
  "properties": {
    "gn:admin1_code":"4.0",
    "gn:asciiname":"Jiangtuncun",
    "gn:country_code":"CN",
    "gn:dem":46,
    "gn:feature_class":"P",
    "gn:feature_code":"PPL",
    "gn:name":"Jiangtuncun",
    "gn:population":0,
    "gn:timezone":"Asia/Shanghai",
    "iso:country":"CN",
    "name:zho_x_preferred":[
        "\u848b\u5c6f\u6751"
    ],
    "wof:name":"Jiangtuncun",
    "wof:placetype":"locality"
},
  "geometry": {"coordinates":[116.50208000000001,34.6499],"type":"Point"}
}