{
  "type": "Feature",
  "properties": {
    "gn:admin1_code":"1.0",
    "gn:asciiname":"Damacun",
    "gn:country_code":"CN",
    "gn:dem":358,
    "gn:feature_class":"P",
    "gn:feature_code":"PPL",
    "gn:name":"Damacun",
    "gn:population":0,
    "gn:timezone":"Asia/Shanghai",
    "iso:country":"CN",
    "name:zho_x_preferred":[
        "\u5927\u9a6c\u6751"
    ],
    "wof:name":"Damacun",
    "wof:placetype":"locality"
},
  "geometry": {"coordinates":[116.48998,31.15729],"type":"Point"}
}