{
  "type": "Feature",
  "properties": {
    "gn:admin1_code":"12.0",
    "gn:asciiname":"Xuwuchang",
    "gn:country_code":"CN",
    "gn:dem":189,
    "gn:feature_class":"P",
    "gn:feature_code":"PPL",
    "gn:name":"Xuwuchang",
    "gn:population":0,
    "gn:timezone":"Asia/Shanghai",
    "iso:country":"CN",
    "name:zho_x_preferred":[
        "\u5f90\u5c4b\u573a"
    ],
    "wof:name":"Xuwuchang",
    "wof:placetype":"locality"
},
  "geometry": {"coordinates":[111.99393999999999,31.42641],"type":"Point"}
}