{
  "type": "Feature",
  "properties": {
    "gn:admin1_code":"15.0",
    "gn:asciiname":"Huilong'ang",
    "gn:country_code":"CN",
    "gn:dem":3020,
    "gn:feature_class":"P",
    "gn:feature_code":"PPL",
    "gn:name":"Huilong\u2019ang",
    "gn:population":0,
    "gn:timezone":"Asia/Shanghai",
    "iso:country":"CN",
    "name:und_x_variant":[
        "Huilong\u2019ang",
        "\u7070\u9686\u6602"
    ],
    "wof:name":"Huilong'ang",
    "wof:placetype":"locality"
},
  "geometry": {"coordinates":[102.80800000000001,35.1196],"type":"Point"}
}