{
  "type": "Feature",
  "properties": {
    "gn:admin1_code":"14.0",
    "gn:asciiname":"Qingdu",
    "gn:country_code":"CN",
    "gn:dem":4844,
    "gn:feature_class":"P",
    "gn:feature_code":"PPLF",
    "gn:name":"Qingdu",
    "gn:population":0,
    "gn:timezone":"Asia/Urumqi",
    "iso:country":"CN",
    "name:bod_x_preferred":[
        "Qingt\u00fc"
    ],
    "name:msa_x_preferred":[
        "Qingt\u00fc"
    ],
    "name:zho_x_preferred":[
        "Qingdu"
    ],
    "name:zho_x_variant":[
        "\u9752\u90fd",
        "Naqiang",
        "\u90a3\u5f3a",
        "\u9752\u90fd\u4e61"
    ],
    "wof:name":"Qingdu",
    "wof:placetype":"locality"
},
  "geometry": {"coordinates":[88.38333,30.03333],"type":"Point"}
}