{
  "type": "Feature",
  "properties": {
    "gn:admin1_code":"04",
    "gn:asciiname":"Tianfen",
    "gn:country_code":"CN",
    "gn:dem":4,
    "gn:feature_class":"P",
    "gn:feature_code":"PPLA4",
    "gn:name":"Tianfen",
    "gn:population":0,
    "gn:timezone":"Asia/Shanghai",
    "iso:country":"CN",
    "name:und_x_variant":[
        "\u5929\u6c7e",
        "Tianfen Zhen",
        "\u5929\u6c7e\u9547"
    ],
    "wof:name":"Tianfen",
    "wof:placetype":"locality"
},
  "geometry": {"coordinates":[121.54158,32.06308],"type":"Point"}
}