{
  "type": "Feature",
  "properties": {
    "gn:admin1_code":"29.0",
    "gn:asciiname":"Aiguo",
    "gn:country_code":"CN",
    "gn:dem":1521,
    "gn:feature_class":"P",
    "gn:feature_code":"PPL",
    "gn:name":"Aiguo",
    "gn:population":0,
    "gn:timezone":"Asia/Shanghai",
    "iso:country":"CN",
    "name:zho_x_preferred":[
        "\u7231\u56fd"
    ],
    "wof:name":"Aiguo",
    "wof:placetype":"locality"
},
  "geometry": {"coordinates":[100.06999999999999,24.9885],"type":"Point"}
}