{
  "type": "Feature",
  "properties": {
    "gn:admin1_code":"26.0",
    "gn:asciiname":"Xiaoqiangcun",
    "gn:country_code":"CN",
    "gn:dem":728,
    "gn:feature_class":"P",
    "gn:feature_code":"PPL",
    "gn:name":"Xiaoqiangcun",
    "gn:population":0,
    "gn:timezone":"Asia/Shanghai",
    "iso:country":"CN",
    "name:zho_x_preferred":[
        "\u5c0f\u5f3a\u6751"
    ],
    "wof:name":"Xiaoqiangcun",
    "wof:placetype":"locality"
},
  "geometry": {"coordinates":[107.77491000000001,34.46066],"type":"Point"}
}