{
  "type": "Feature",
  "properties": {
    "gn:admin1_code":"24",
    "gn:asciiname":"Aogeta",
    "gn:country_code":"CN",
    "gn:dem":1186,
    "gn:feature_class":"P",
    "gn:feature_code":"PPL",
    "gn:name":"Aogeta",
    "gn:population":0,
    "gn:timezone":"Asia/Shanghai",
    "iso:country":"CN",
    "name:und_x_variant":[
        "Ao-ko-t\u2019a",
        "Aogeta"
    ],
    "name:zho_x_preferred":[
        "\u9ccc\u7599\u5854"
    ],
    "wof:name":"Aogeta",
    "wof:placetype":"locality"
},
  "geometry": {"coordinates":[111.94441999999999,35.90627999999999],"type":"Point"}
}