{
  "type": "Feature",
  "properties": {
    "gn:admin1_code":"4.0",
    "gn:asciiname":"Xizou",
    "gn:country_code":"CN",
    "gn:dem":4,
    "gn:feature_class":"P",
    "gn:feature_code":"PPL",
    "gn:name":"Xizou",
    "gn:population":0,
    "gn:timezone":"Asia/Shanghai",
    "iso:country":"CN",
    "name:und_x_variant":[
        "\u897f\u90b9"
    ],
    "name:zho_x_preferred":[
        "\u897f\u90b9"
    ],
    "wof:name":"Xizou",
    "wof:placetype":"locality"
},
  "geometry": {"coordinates":[120.83799999999999,32.72126],"type":"Point"}
}