{
  "type": "Feature",
  "properties": {
    "gn:admin1_code":"26.0",
    "gn:asciiname":"Hequancun",
    "gn:country_code":"CN",
    "gn:dem":1439,
    "gn:feature_class":"P",
    "gn:feature_code":"PPL",
    "gn:name":"Hequancun",
    "gn:population":0,
    "gn:timezone":"Asia/Shanghai",
    "iso:country":"CN",
    "name:zho_x_preferred":[
        "\u8d3a\u5708\u6751"
    ],
    "wof:name":"Hequancun",
    "wof:placetype":"locality"
},
  "geometry": {"coordinates":[107.34535,37.42704000000001],"type":"Point"}
}