{
  "type": "Feature",
  "properties": {
    "gn:admin1_code":"11.0",
    "gn:asciiname":"Gengshuling",
    "gn:country_code":"CN",
    "gn:dem":1279,
    "gn:feature_class":"P",
    "gn:feature_code":"PPL",
    "gn:name":"Gengshuling",
    "gn:population":0,
    "gn:timezone":"Asia/Shanghai",
    "iso:country":"CN",
    "name:zho_x_preferred":[
        "\u8015\u719f\u5cad"
    ],
    "wof:name":"Gengshuling",
    "wof:placetype":"locality"
},
  "geometry": {"coordinates":[113.8475,26.12782],"type":"Point"}
}