{
  "type": "Feature",
  "properties": {
    "gn:admin1_code":"10",
    "gn:asciiname":"Halagang",
    "gn:country_code":"CN",
    "gn:dem":19,
    "gn:feature_class":"P",
    "gn:feature_code":"PPL",
    "gn:name":"Halagang",
    "gn:population":0,
    "gn:timezone":"Asia/Shanghai",
    "iso:country":"CN",
    "name:und_x_variant":[
        "Ha-la-kang",
        "Halagang"
    ],
    "name:zho_x_preferred":[
        "\u54c8\u5587\u6e2f"
    ],
    "wof:name":"Halagang",
    "wof:placetype":"locality"
},
  "geometry": {"coordinates":[116.70289,39.23953],"type":"Point"}
}