{
  "type": "Feature",
  "properties": {
    "gn:admin1_code":"11",
    "gn:asciiname":"Laowuyuan",
    "gn:country_code":"CN",
    "gn:dem":161,
    "gn:feature_class":"P",
    "gn:feature_code":"PPL",
    "gn:name":"Laowuyuan",
    "gn:population":0,
    "gn:timezone":"Asia/Shanghai",
    "iso:country":"CN",
    "wof:name":"Laowuyuan",
    "wof:placetype":"locality"
},
  "geometry": {"coordinates":[111.70667,26.76306],"type":"Point"}
}