{
  "type": "Feature",
  "properties": {
    "gn:admin1_code":"4.0",
    "gn:asciiname":"Shaolin",
    "gn:country_code":"CN",
    "gn:dem":-1,
    "gn:feature_class":"P",
    "gn:feature_code":"PPL",
    "gn:name":"Shaolin",
    "gn:population":0,
    "gn:timezone":"Asia/Shanghai",
    "iso:country":"CN",
    "name:zho_x_preferred":[
        "\u7ecd\u6797"
    ],
    "wof:name":"Shaolin",
    "wof:placetype":"locality"
},
  "geometry": {"coordinates":[120.25691999999999,33.42429],"type":"Point"}
}