{
  "type": "Feature",
  "properties": {
    "gn:admin1_code":"4.0",
    "gn:asciiname":"Shaolin",
    "gn:country_code":"CN",
    "gn:dem":-1,
    "gn:feature_class":"P",
    "gn:feature_code":"PPL",
    "gn:name":"Shaolin",
    "gn:population":0,
    "gn:timezone":"Asia/Shanghai",
    "iso:country":"CN",
    "name:fra_x_preferred":[
        "Shaolin"
    ],
    "name:hun_x_preferred":[
        "Saolin"
    ],
    "name:ind_x_preferred":[
        "Shaolin"
    ],
    "name:ita_x_preferred":[
        "Shaolin"
    ],
    "name:jpn_x_preferred":[
        "\u5c11\u6797\u5bfa"
    ],
    "name:lit_x_preferred":[
        "\u0160aolinas"
    ],
    "name:pol_x_preferred":[
        "Shaolin"
    ],
    "name:por_x_preferred":[
        "Shaolin"
    ],
    "name:rus_x_preferred":[
        "\u0428\u0430\u043e\u043b\u0438\u043d\u044c"
    ],
    "name:srp_x_preferred":[
        "\u0428\u0430\u043e\u043b\u0438\u043d"
    ],
    "name:swe_x_preferred":[
        "Shaolin"
    ],
    "name:tha_x_preferred":[
        "\u0e40\u0e2a\u0e49\u0e32\u0e2b\u0e25\u0e34\u0e19"
    ],
    "name:zho_x_preferred":[
        "\u7ecd\u6797"
    ],
    "name:zho_x_variant":[
        "\u5c11\u6797"
    ],
    "wof:name":"Shaolin",
    "wof:placetype":"locality"
},
  "geometry": {"coordinates":[120.25691999999999,33.42429],"type":"Point"}
}