{
  "type": "Feature",
  "properties": {
    "gn:admin1_code":"3.0",
    "gn:asciiname":"Wanshacun",
    "gn:country_code":"CN",
    "gn:dem":22,
    "gn:feature_class":"P",
    "gn:feature_code":"PPL",
    "gn:name":"Wanshacun",
    "gn:population":0,
    "gn:timezone":"Asia/Shanghai",
    "iso:country":"CN",
    "name:und_x_variant":[
        "\u4e07\u6c99\u6751"
    ],
    "wof:name":"Wanshacun",
    "wof:placetype":"locality"
},
  "geometry": {"coordinates":[115.90043,28.29065],"type":"Point"}
}