{
  "type": "Feature",
  "properties": {
    "gn:admin1_code":"3",
    "gn:asciiname":"Zhangxi",
    "gn:country_code":"CN",
    "gn:dem":159,
    "gn:feature_class":"P",
    "gn:feature_code":"PPL",
    "gn:name":"Zhangxi",
    "gn:population":0,
    "gn:timezone":"Asia/Shanghai",
    "iso:country":"CN",
    "name:und_x_variant":[
        "\u6a1f\u6eaa",
        "Zhangxixiang",
        "\u6a1f\u6eaa\u4e61"
    ],
    "wof:name":"Zhangxi",
    "wof:placetype":"locality"
},
  "geometry": {"coordinates":[116.85621,27.0803],"type":"Point"}
}