{
  "type": "Feature",
  "properties": {
    "gn:admin1_code":"3.0",
    "gn:asciiname":"Zhangwuchang",
    "gn:country_code":"CN",
    "gn:dem":118,
    "gn:feature_class":"P",
    "gn:feature_code":"PPL",
    "gn:name":"Zhangwuchang",
    "gn:population":0,
    "gn:timezone":"Asia/Shanghai",
    "iso:country":"CN",
    "name:und_x_variant":[
        "\u5f20\u5c4b\u573a"
    ],
    "wof:name":"Zhangwuchang",
    "wof:placetype":"locality"
},
  "geometry": {"coordinates":[117.08323,29.57361],"type":"Point"}
}