{
  "type": "Feature",
  "properties": {
    "gn:admin1_code":"1.0",
    "gn:asciiname":"Yilian",
    "gn:country_code":"CN",
    "gn:dem":11,
    "gn:feature_class":"P",
    "gn:feature_code":"PPL",
    "gn:name":"Yilian",
    "gn:population":0,
    "gn:timezone":"Asia/Shanghai",
    "iso:country":"CN",
    "name:zho_x_preferred":[
        "\u4e00\u8054"
    ],
    "wof:name":"Yilian",
    "wof:placetype":"locality"
},
  "geometry": {"coordinates":[118.44584,31.79631],"type":"Point"}
}