{
  "type": "Feature",
  "properties": {
    "gn:admin1_code":"16.0",
    "gn:asciiname":"Tunyao",
    "gn:country_code":"CN",
    "gn:dem":227,
    "gn:feature_class":"P",
    "gn:feature_code":"PPL",
    "gn:name":"Tunyao",
    "gn:population":0,
    "gn:timezone":"Asia/Shanghai",
    "iso:country":"CN",
    "name:und_x_variant":[
        "Tunme",
        "Tunyao"
    ],
    "name:zho_x_preferred":[
        "\u541e\u4e48"
    ],
    "wof:name":"Tunyao",
    "wof:placetype":"locality"
},
  "geometry": {"coordinates":[107.979,23.979],"type":"Point"}
}