{
  "type": "Feature",
  "properties": {
    "gn:admin1_code":"29.0",
    "gn:asciiname":"Tonghong",
    "gn:country_code":"CN",
    "gn:dem":1354,
    "gn:feature_class":"P",
    "gn:feature_code":"PPL",
    "gn:name":"Tonghong",
    "gn:population":0,
    "gn:timezone":"Asia/Shanghai",
    "iso:country":"CN",
    "name:zho_x_preferred":[
        "\u540c\u8f70"
    ],
    "wof:name":"Tonghong",
    "wof:placetype":"locality"
},
  "geometry": {"coordinates":[104.41,23.9473],"type":"Point"}
}