{
  "type": "Feature",
  "properties": {
    "gn:admin1_code":"20.0",
    "gn:asciiname":"Shitou Gouzi",
    "gn:country_code":"CN",
    "gn:dem":356,
    "gn:feature_class":"P",
    "gn:feature_code":"PPL",
    "gn:name":"Shitou Gouzi",
    "gn:population":0,
    "gn:timezone":"Asia/Shanghai",
    "iso:country":"CN",
    "name:zho_x_preferred":[
        "\u77f3\u5934\u6c9f\u5b50"
    ],
    "wof:name":"Shitou Gouzi",
    "wof:placetype":"locality"
},
  "geometry": {"coordinates":[123.92243999999999,49.76531],"type":"Point"}
}