{
  "type": "Feature",
  "properties": {
    "gn:admin1_code":"32.0",
    "gn:asciiname":"Beijiao",
    "gn:country_code":"CN",
    "gn:dem":583,
    "gn:feature_class":"P",
    "gn:feature_code":"PPL",
    "gn:name":"Beijiao",
    "gn:population":0,
    "gn:timezone":"Asia/Shanghai",
    "iso:country":"CN",
    "name:ceb_x_preferred":[
        "Beijiao"
    ],
    "name:deu_x_preferred":[
        "Beijiao"
    ],
    "name:swe_x_preferred":[
        "Beijiao"
    ],
    "name:zho_x_preferred":[
        "\u5317\u90ca"
    ],
    "wof:name":"Beijiao",
    "wof:placetype":"locality"
},
  "geometry": {"coordinates":[103.00941,30.00733],"type":"Point"}
}