{
  "type": "Feature",
  "properties": {
    "gn:admin1_code":"26.0",
    "gn:asciiname":"Shiyaocun",
    "gn:country_code":"CN",
    "gn:dem":918,
    "gn:feature_class":"P",
    "gn:feature_code":"PPL",
    "gn:name":"Shiyaocun",
    "gn:population":0,
    "gn:timezone":"Asia/Shanghai",
    "iso:country":"CN",
    "name:zho_x_preferred":[
        "\u77f3\u78d8\u6751"
    ],
    "wof:name":"Shiyaocun",
    "wof:placetype":"locality"
},
  "geometry": {"coordinates":[109.95189000000001,37.02199],"type":"Point"}
}