{
  "type": "Feature",
  "properties": {
    "gn:admin1_code":"11.0",
    "gn:asciiname":"Jiuquping",
    "gn:country_code":"CN",
    "gn:dem":133,
    "gn:feature_class":"P",
    "gn:feature_code":"PPL",
    "gn:name":"Jiuquping",
    "gn:population":0,
    "gn:timezone":"Asia/Shanghai",
    "iso:country":"CN",
    "name:zho_x_preferred":[
        "\u4e5d\u66f2\u576a"
    ],
    "wof:name":"Jiuquping",
    "wof:placetype":"locality"
},
  "geometry": {"coordinates":[111.46278,28.42828],"type":"Point"}
}