{
  "type": "Feature",
  "properties": {
    "gn:admin1_code":"29.0",
    "gn:asciiname":"Yutu",
    "gn:country_code":"CN",
    "gn:dem":1026,
    "gn:feature_class":"P",
    "gn:feature_code":"PPL",
    "gn:name":"Yutu",
    "gn:population":0,
    "gn:timezone":"Asia/Shanghai",
    "iso:country":"CN",
    "name:deu_x_preferred":[
        "Yutu"
    ],
    "name:ind_x_preferred":[
        "Yutu"
    ],
    "name:por_x_preferred":[
        "Yutu"
    ],
    "name:swe_x_preferred":[
        "Yutu"
    ],
    "name:zho_x_preferred":[
        "\u96e8\u571f"
    ],
    "name:zho_x_variant":[
        "\u7389\u5154"
    ],
    "wof:name":"Yutu",
    "wof:placetype":"locality"
},
  "geometry": {"coordinates":[104.126,24.386],"type":"Point"}
}