{
  "type": "Feature",
  "properties": {
    "gn:admin1_code":"29.0",
    "gn:asciiname":"Baojia Pingzi",
    "gn:country_code":"CN",
    "gn:dem":1385,
    "gn:feature_class":"P",
    "gn:feature_code":"PPL",
    "gn:name":"Baojia Pingzi",
    "gn:population":0,
    "gn:timezone":"Asia/Shanghai",
    "iso:country":"CN",
    "name:zho_x_preferred":[
        "\u5305\u5bb6\u576a\u5b50"
    ],
    "wof:name":"Baojia Pingzi",
    "wof:placetype":"locality"
},
  "geometry": {"coordinates":[102.988,26.8749],"type":"Point"}
}