{
  "type": "Feature",
  "properties": {
    "gn:admin1_code":"19.0",
    "gn:asciiname":"Dashan",
    "gn:country_code":"CN",
    "gn:dem":699,
    "gn:feature_class":"P",
    "gn:feature_code":"PPL",
    "gn:name":"Dashan",
    "gn:population":0,
    "gn:timezone":"Asia/Shanghai",
    "iso:country":"CN",
    "name:fra_x_preferred":[
        "Dashan"
    ],
    "name:ita_x_preferred":[
        "Dashan"
    ],
    "name:jpn_x_preferred":[
        "\u5927\u5c71"
    ],
    "name:kor_x_preferred":[
        "\ub2e4\uc0b0"
    ],
    "name:nor_x_preferred":[
        "Dashan"
    ],
    "name:swe_x_preferred":[
        "Dashan"
    ],
    "name:ukr_x_preferred":[
        "\u0414\u0430\u0448\u0430\u043d"
    ],
    "name:zho_x_preferred":[
        "\u5927\u5c71"
    ],
    "wof:name":"Dashan",
    "wof:placetype":"locality"
},
  "geometry": {"coordinates":[119.82953999999999,42.15127],"type":"Point"}
}