{
  "type": "Feature",
  "properties": {
    "gn:admin1_code":"24.0",
    "gn:asciiname":"Hujiawa",
    "gn:country_code":"CN",
    "gn:dem":1541,
    "gn:feature_class":"P",
    "gn:feature_code":"PPL",
    "gn:name":"Hujiawa",
    "gn:population":0,
    "gn:timezone":"Asia/Shanghai",
    "iso:country":"CN",
    "name:zho_x_preferred":[
        "\u80e1\u5bb6\u6d3c"
    ],
    "wof:name":"Hujiawa",
    "wof:placetype":"locality"
},
  "geometry": {"coordinates":[111.41566,38.90036],"type":"Point"}
}