{
  "type": "Feature",
  "properties": {
    "gn:admin1_code":"12.0",
    "gn:asciiname":"Hulingye",
    "gn:country_code":"CN",
    "gn:dem":28,
    "gn:feature_class":"P",
    "gn:feature_code":"PPL",
    "gn:name":"Hulingye",
    "gn:population":0,
    "gn:timezone":"Asia/Shanghai",
    "iso:country":"CN",
    "name:und_x_variant":[
        "\u6e56\u5cad\u53f6"
    ],
    "wof:name":"Hulingye",
    "wof:placetype":"locality"
},
  "geometry": {"coordinates":[114.38093000000001,30.09841],"type":"Point"}
}