{
  "type": "Feature",
  "properties": {
    "gn:admin1_code":"15.0",
    "gn:asciiname":"Dayu",
    "gn:country_code":"CN",
    "gn:dem":2112,
    "gn:feature_class":"P",
    "gn:feature_code":"PPLA4",
    "gn:name":"Dayu",
    "gn:population":0,
    "gn:timezone":"Asia/Shanghai",
    "iso:country":"CN",
    "name:ceb_x_preferred":[
        "Dayu"
    ],
    "name:deu_x_preferred":[
        "Dayu"
    ],
    "name:ind_x_preferred":[
        "Dayu"
    ],
    "name:nld_x_preferred":[
        "Dayu"
    ],
    "name:swe_x_preferred":[
        "Dayu"
    ],
    "name:und_x_variant":[
        "\u5927\u5cea"
    ],
    "name:zho_x_preferred":[
        "\u5927\u5cea"
    ],
    "wof:name":"Dayu",
    "wof:placetype":"locality"
},
  "geometry": {"coordinates":[104.03957,33.83125],"type":"Point"}
}