{
  "type": "Feature",
  "properties": {
    "gn:admin1_code":"25",
    "gn:asciiname":"Luwangzhuang",
    "gn:country_code":"CN",
    "gn:dem":20,
    "gn:feature_class":"P",
    "gn:feature_code":"PPL",
    "gn:name":"L\u00fcwangzhuang",
    "gn:population":0,
    "gn:timezone":"Asia/Shanghai",
    "iso:country":"CN",
    "name:und_x_variant":[
        "L\u00fcwangzhuang"
    ],
    "name:zho_x_preferred":[
        "\u5415\u738b\u5e84"
    ],
    "wof:name":"Luwangzhuang",
    "wof:placetype":"locality"
},
  "geometry": {"coordinates":[117.652,37.2864],"type":"Point"}
}