{
  "type": "Feature",
  "properties": {
    "gn:admin1_code":"32.0",
    "gn:asciiname":"Ailang",
    "gn:country_code":"CN",
    "gn:dem":1982,
    "gn:feature_class":"P",
    "gn:feature_code":"PPL",
    "gn:name":"Ailang",
    "gn:population":0,
    "gn:timezone":"Asia/Shanghai",
    "iso:country":"CN",
    "name:zho_x_preferred":[
        "\u77ee\u90ce"
    ],
    "wof:name":"Ailang",
    "wof:placetype":"locality"
},
  "geometry": {"coordinates":[102.06905999999999,26.61567],"type":"Point"}
}