{
  "type": "Feature",
  "properties": {
    "gn:admin1_code":"11.0",
    "gn:asciiname":"Niubeiyan",
    "gn:country_code":"CN",
    "gn:dem":503,
    "gn:feature_class":"P",
    "gn:feature_code":"PPL",
    "gn:name":"Niubeiyan",
    "gn:population":0,
    "gn:timezone":"Asia/Shanghai",
    "iso:country":"CN",
    "name:zho_x_preferred":[
        "\u725b\u80cc\u5ca9"
    ],
    "wof:name":"Niubeiyan",
    "wof:placetype":"locality"
},
  "geometry": {"coordinates":[110.19135,28.41609],"type":"Point"}
}