{
  "type": "Feature",
  "properties": {
    "gn:admin1_code":"7",
    "gn:asciiname":"Shangdun",
    "gn:country_code":"CN",
    "gn:dem":310,
    "gn:feature_class":"P",
    "gn:feature_code":"PPL",
    "gn:name":"Shangdun",
    "gn:population":0,
    "gn:timezone":"Asia/Shanghai",
    "iso:country":"CN",
    "name:und_x_variant":[
        "Shangfang",
        "Shangdun"
    ],
    "name:zho_x_preferred":[
        "\u4e0a\u58a9"
    ],
    "wof:name":"Shangdun",
    "wof:placetype":"locality"
},
  "geometry": {"coordinates":[116.24944000000001,24.90778],"type":"Point"}
}