{
  "type": "Feature",
  "properties": {
    "gn:admin1_code":"14.0",
    "gn:asciiname":"Dacang",
    "gn:country_code":"CN",
    "gn:dem":4050,
    "gn:feature_class":"P",
    "gn:feature_code":"PPL",
    "gn:name":"Dacang",
    "gn:population":0,
    "gn:timezone":"Asia/Urumqi",
    "iso:country":"CN",
    "name:zho_x_preferred":[
        "\u8fbe\u4ed3"
    ],
    "wof:name":"Dacang",
    "wof:placetype":"locality"
},
  "geometry": {"coordinates":[86.42200000000003,28.145],"type":"Point"}
}