{
  "type": "Feature",
  "properties": {
    "gn:admin1_code":"11.0",
    "gn:asciiname":"Zhuzichong",
    "gn:country_code":"CN",
    "gn:dem":73,
    "gn:feature_class":"P",
    "gn:feature_code":"PPL",
    "gn:name":"Zhuzichong",
    "gn:population":0,
    "gn:timezone":"Asia/Shanghai",
    "iso:country":"CN",
    "name:zho_x_preferred":[
        "\u7af9\u5b50\u51b2"
    ],
    "wof:name":"Zhuzichong",
    "wof:placetype":"locality"
},
  "geometry": {"coordinates":[112.86439,28.27559],"type":"Point"}
}