{
  "type": "Feature",
  "properties": {
    "gn:admin1_code":"15.0",
    "gn:asciiname":"Shuangping",
    "gn:country_code":"CN",
    "gn:dem":1690,
    "gn:feature_class":"P",
    "gn:feature_code":"PPL",
    "gn:name":"Shuangping",
    "gn:population":0,
    "gn:timezone":"Asia/Shanghai",
    "iso:country":"CN",
    "name:und_x_variant":[
        "\u53cc\u576a"
    ],
    "name:zho_x_preferred":[
        "\u53cc\u576a"
    ],
    "wof:name":"Shuangping",
    "wof:placetype":"locality"
},
  "geometry": {"coordinates":[105.01354000000001,33.72239],"type":"Point"}
}