{
  "type": "Feature",
  "properties": {
    "gn:admin1_code":"4.0",
    "gn:asciiname":"Lianbiancun",
    "gn:country_code":"CN",
    "gn:dem":4,
    "gn:feature_class":"P",
    "gn:feature_code":"PPL",
    "gn:name":"Lianbiancun",
    "gn:population":0,
    "gn:timezone":"Asia/Shanghai",
    "iso:country":"CN",
    "name:zho_x_preferred":[
        "\u8054\u8fb9\u6751"
    ],
    "wof:name":"Lianbiancun",
    "wof:placetype":"locality"
},
  "geometry": {"coordinates":[120.8031,32.7337],"type":"Point"}
}