{
  "type": "Feature",
  "properties": {
    "gn:admin1_code":"11",
    "gn:asciiname":"Shoulan",
    "gn:country_code":"CN",
    "gn:dem":165,
    "gn:feature_class":"P",
    "gn:feature_code":"PPL",
    "gn:name":"Shoulan",
    "gn:population":0,
    "gn:timezone":"Asia/Shanghai",
    "iso:country":"CN",
    "name:zho_x_preferred":[
        "\u5bff\u5170"
    ],
    "wof:name":"Shoulan",
    "wof:placetype":"locality"
},
  "geometry": {"coordinates":[111.81698,27.84102],"type":"Point"}
}