{
  "type": "Feature",
  "properties": {
    "gn:admin1_code":"26.0",
    "gn:asciiname":"Putuocun",
    "gn:country_code":"CN",
    "gn:dem":855,
    "gn:feature_class":"P",
    "gn:feature_code":"PPL",
    "gn:name":"Putuocun",
    "gn:population":0,
    "gn:timezone":"Asia/Shanghai",
    "iso:country":"CN",
    "name:zho_x_preferred":[
        "\u666e\u9640\u6751"
    ],
    "wof:name":"Putuocun",
    "wof:placetype":"locality"
},
  "geometry": {"coordinates":[109.88175,34.02407],"type":"Point"}
}