{
  "type": "Feature",
  "properties": {
    "gn:admin1_code":"32.0",
    "gn:asciiname":"Mu'er",
    "gn:country_code":"CN",
    "gn:dem":1743,
    "gn:feature_class":"P",
    "gn:feature_code":"PPL",
    "gn:name":"Mu\u2019er",
    "gn:population":0,
    "gn:timezone":"Asia/Shanghai",
    "iso:country":"CN",
    "name:und_x_variant":[
        "Mu\u2019er"
    ],
    "name:zho_x_preferred":[
        "\u6728\u8033"
    ],
    "wof:name":"Mu'er",
    "wof:placetype":"locality"
},
  "geometry": {"coordinates":[102.182,29.2324],"type":"Point"}
}