{
  "type": "Feature",
  "properties": {
    "gn:admin1_code":"11",
    "gn:asciiname":"Dahetang",
    "gn:country_code":"CN",
    "gn:dem":302,
    "gn:feature_class":"P",
    "gn:feature_code":"PPL",
    "gn:name":"Dahetang",
    "gn:population":0,
    "gn:timezone":"Asia/Shanghai",
    "iso:country":"CN",
    "name:zho_x_preferred":[
        "\u5927\u548c\u5858"
    ],
    "name:zho_x_variant":[
        "\u5927\u79be\u5858\u8857\u9053"
    ],
    "wof:name":"Dahetang",
    "wof:placetype":"locality"
},
  "geometry": {"coordinates":[111.34925,27.00888],"type":"Point"}
}