{
  "type": "Feature",
  "properties": {
    "gn:admin1_code":"3.0",
    "gn:asciiname":"Muniuguo",
    "gn:country_code":"CN",
    "gn:dem":290,
    "gn:feature_class":"P",
    "gn:feature_code":"PPL",
    "gn:name":"Muniuguo",
    "gn:population":0,
    "gn:timezone":"Asia/Shanghai",
    "iso:country":"CN",
    "name:und_x_variant":[
        "\u7267\u725b\u57da"
    ],
    "wof:name":"Muniuguo",
    "wof:placetype":"locality"
},
  "geometry": {"coordinates":[114.09096,28.84447],"type":"Point"}
}