{
  "type": "Feature",
  "properties": {
    "gn:admin1_code":"4.0",
    "gn:asciiname":"Jiangangcun",
    "gn:country_code":"CN",
    "gn:dem":-3,
    "gn:feature_class":"P",
    "gn:feature_code":"PPL",
    "gn:name":"Jiangangcun",
    "gn:population":0,
    "gn:timezone":"Asia/Shanghai",
    "iso:country":"CN",
    "name:zho_x_preferred":[
        "\u5efa\u6e2f\u6751"
    ],
    "wof:name":"Jiangangcun",
    "wof:placetype":"locality"
},
  "geometry": {"coordinates":[120.02649,33.93408],"type":"Point"}
}