{
  "type": "Feature",
  "properties": {
    "gn:admin1_code":"11.0",
    "gn:asciiname":"Xia'aohe",
    "gn:country_code":"CN",
    "gn:dem":328,
    "gn:feature_class":"P",
    "gn:feature_code":"PPL",
    "gn:name":"Xia\u2019aohe",
    "gn:population":0,
    "gn:timezone":"Asia/Shanghai",
    "iso:country":"CN",
    "name:und_x_variant":[
        "Xia\u2019aohe"
    ],
    "name:zho_x_preferred":[
        "\u4e0b\u5773\u6cb3"
    ],
    "wof:name":"Xia'aohe",
    "wof:placetype":"locality"
},
  "geometry": {"coordinates":[109.72035,25.96984],"type":"Point"}
}