{
  "type": "Feature",
  "properties": {
    "gn:admin1_code":"14.0",
    "gn:asciiname":"Chongguo",
    "gn:country_code":"CN",
    "gn:dem":3720,
    "gn:feature_class":"P",
    "gn:feature_code":"PPL",
    "gn:name":"Chongguo",
    "gn:population":0,
    "gn:timezone":"Asia/Urumqi",
    "iso:country":"CN",
    "name:zho_x_preferred":[
        "\u51b2\u679c"
    ],
    "wof:name":"Chongguo",
    "wof:placetype":"locality"
},
  "geometry": {"coordinates":[97.52535,29.41922000000001],"type":"Point"}
}