{
  "type": "Feature",
  "properties": {
    "gn:admin1_code":"8.0",
    "gn:asciiname":"Zheng'ancun",
    "gn:country_code":"CN",
    "gn:dem":154,
    "gn:feature_class":"P",
    "gn:feature_code":"PPL",
    "gn:name":"Zheng\u2019ancun",
    "gn:population":0,
    "gn:timezone":"Asia/Shanghai",
    "iso:country":"CN",
    "name:und_x_variant":[
        "Zheng\u2019ancun"
    ],
    "name:zho_x_preferred":[
        "\u653f\u5b89\u6751"
    ],
    "wof:name":"Zheng'ancun",
    "wof:placetype":"locality"
},
  "geometry": {"coordinates":[126.39752,45.25532000000001],"type":"Point"}
}