{
  "type": "Feature",
  "properties": {
    "gn:admin1_code":"25.0",
    "gn:asciiname":"Yangzhuangpucun",
    "gn:country_code":"CN",
    "gn:dem":19,
    "gn:feature_class":"P",
    "gn:feature_code":"PPL",
    "gn:name":"Yangzhuangpucun",
    "gn:population":0,
    "gn:timezone":"Asia/Shanghai",
    "iso:country":"CN",
    "name:zho_x_preferred":[
        "\u6768\u5e84\u94fa\u6751"
    ],
    "wof:name":"Yangzhuangpucun",
    "wof:placetype":"locality"
},
  "geometry": {"coordinates":[117.18262,37.18693],"type":"Point"}
}