{
  "type": "Feature",
  "properties": {
    "gn:admin1_code":"4.0",
    "gn:asciiname":"Jiagou Yuyecun",
    "gn:country_code":"CN",
    "gn:dem":9,
    "gn:feature_class":"P",
    "gn:feature_code":"PPLF",
    "gn:name":"Jiagou Yuyecun",
    "gn:population":0,
    "gn:timezone":"Asia/Shanghai",
    "iso:country":"CN",
    "name:zho_x_preferred":[
        "\u5939\u6c9f\u6e14\u4e1a\u6751"
    ],
    "wof:name":"Jiagou Yuyecun",
    "wof:placetype":"locality"
},
  "geometry": {"coordinates":[119.22684,32.97126],"type":"Point"}
}