{
  "type": "Feature",
  "properties": {
    "gn:admin1_code":"14.0",
    "gn:asciiname":"Naishai",
    "gn:country_code":"CN",
    "gn:dem":4498,
    "gn:feature_class":"P",
    "gn:feature_code":"PPL",
    "gn:name":"Naishai",
    "gn:population":0,
    "gn:timezone":"Asia/Urumqi",
    "iso:country":"CN",
    "name:zho_x_preferred":[
        "\u5976\u6652"
    ],
    "wof:name":"Naishai",
    "wof:placetype":"locality"
},
  "geometry": {"coordinates":[90.85773,28.90078],"type":"Point"}
}