{
  "type": "Feature",
  "properties": {
    "gn:admin1_code":"15.0",
    "gn:asciiname":"Dongtangba",
    "gn:country_code":"CN",
    "gn:dem":2468,
    "gn:feature_class":"P",
    "gn:feature_code":"PPL",
    "gn:name":"Dongtangba",
    "gn:population":0,
    "gn:timezone":"Asia/Shanghai",
    "iso:country":"CN",
    "name:zho_x_preferred":[
        "\u4e1c\u5858\u575d"
    ],
    "wof:name":"Dongtangba",
    "wof:placetype":"locality"
},
  "geometry": {"coordinates":[99.3383,39.092],"type":"Point"}
}