{
  "type": "Feature",
  "properties": {
    "gn:admin1_code":"3.0",
    "gn:asciiname":"Sanqiao",
    "gn:country_code":"CN",
    "gn:dem":48,
    "gn:feature_class":"P",
    "gn:feature_code":"PPL",
    "gn:name":"Sanqiao",
    "gn:population":0,
    "gn:timezone":"Asia/Shanghai",
    "iso:country":"CN",
    "name:und_x_variant":[
        "\u4e09\u6865"
    ],
    "wof:name":"Sanqiao",
    "wof:placetype":"locality"
},
  "geometry": {"coordinates":[115.84404000000001,29.58282],"type":"Point"}
}