{
  "type": "Feature",
  "properties": {
    "gn:admin1_code":"19.0",
    "gn:asciiname":"Beimaizigou",
    "gn:country_code":"CN",
    "gn:dem":81,
    "gn:feature_class":"P",
    "gn:feature_code":"PPL",
    "gn:name":"Beimaizigou",
    "gn:population":0,
    "gn:timezone":"Asia/Shanghai",
    "iso:country":"CN",
    "name:zho_x_preferred":[
        "\u5317\u9ea6\u5b50\u6c9f"
    ],
    "wof:name":"Beimaizigou",
    "wof:placetype":"locality"
},
  "geometry": {"coordinates":[120.497,40.6482],"type":"Point"}
}