{
  "type": "Feature",
  "properties": {
    "gn:admin1_code":"24.0",
    "gn:asciiname":"Gaoyashang",
    "gn:country_code":"CN",
    "gn:dem":1039,
    "gn:feature_class":"P",
    "gn:feature_code":"PPL",
    "gn:name":"Gaoyashang",
    "gn:population":0,
    "gn:timezone":"Asia/Shanghai",
    "iso:country":"CN",
    "name:zho_x_preferred":[
        "\u9ad8\u5d16\u4e0a"
    ],
    "wof:name":"Gaoyashang",
    "wof:placetype":"locality"
},
  "geometry": {"coordinates":[113.19232,35.54538],"type":"Point"}
}