{
  "type": "Feature",
  "properties": {
    "gn:admin1_code":"8.0",
    "gn:asciiname":"Huandonggang",
    "gn:country_code":"CN",
    "gn:dem":143,
    "gn:feature_class":"P",
    "gn:feature_code":"PPL",
    "gn:name":"Huandonggang",
    "gn:population":0,
    "gn:timezone":"Asia/Shanghai",
    "iso:country":"CN",
    "name:zho_x_preferred":[
        "\u737e\u6d1e\u5c97"
    ],
    "wof:name":"Huandonggang",
    "wof:placetype":"locality"
},
  "geometry": {"coordinates":[124.04889,47.0753],"type":"Point"}
}