{
  "type": "Feature",
  "properties": {
    "gn:admin1_code":"10.0",
    "gn:asciiname":"Dongyingjie",
    "gn:country_code":"CN",
    "gn:dem":31,
    "gn:feature_class":"P",
    "gn:feature_code":"PPL",
    "gn:name":"Dongyingjie",
    "gn:population":0,
    "gn:timezone":"Asia/Shanghai",
    "iso:country":"CN",
    "name:zho_x_preferred":[
        "\u4e1c\u8425\u8857"
    ],
    "wof:name":"Dongyingjie",
    "wof:placetype":"locality"
},
  "geometry": {"coordinates":[116.02077,39.55072],"type":"Point"}
}