{
  "type": "Feature",
  "properties": {
    "gn:admin1_code":"24.0",
    "gn:asciiname":"Duzhuang",
    "gn:country_code":"CN",
    "gn:dem":1000,
    "gn:feature_class":"P",
    "gn:feature_code":"PPL",
    "gn:name":"Duzhuang",
    "gn:population":0,
    "gn:timezone":"Asia/Shanghai",
    "iso:country":"CN",
    "name:und_x_variant":[
        "\u675c\u5e84"
    ],
    "wof:name":"Duzhuang",
    "wof:placetype":"locality"
},
  "geometry": {"coordinates":[113.37081999999999,39.85688],"type":"Point"}
}