{
  "type": "Feature",
  "properties": {
    "gn:admin1_code":"11.0",
    "gn:asciiname":"Shebeichong",
    "gn:country_code":"CN",
    "gn:dem":205,
    "gn:feature_class":"P",
    "gn:feature_code":"PPL",
    "gn:name":"Shebeichong",
    "gn:population":0,
    "gn:timezone":"Asia/Shanghai",
    "iso:country":"CN",
    "name:zho_x_preferred":[
        "\u793e\u80cc\u51b2"
    ],
    "wof:name":"Shebeichong",
    "wof:placetype":"locality"
},
  "geometry": {"coordinates":[113.08114999999999,26.79176],"type":"Point"}
}