{
  "type": "Feature",
  "properties": {
    "gn:admin1_code":"12.0",
    "gn:asciiname":"Yanzoujia",
    "gn:country_code":"CN",
    "gn:dem":115,
    "gn:feature_class":"P",
    "gn:feature_code":"PPL",
    "gn:name":"Yanzoujia",
    "gn:population":0,
    "gn:timezone":"Asia/Shanghai",
    "iso:country":"CN",
    "name:zho_x_preferred":[
        "\u989c\u90b9\u5bb6"
    ],
    "wof:name":"Yanzoujia",
    "wof:placetype":"locality"
},
  "geometry": {"coordinates":[114.59641000000001,31.44697],"type":"Point"}
}