{
  "type": "Feature",
  "properties": {
    "gn:admin1_code":"33.0",
    "gn:asciiname":"Yangjun",
    "gn:country_code":"CN",
    "gn:dem":768,
    "gn:feature_class":"P",
    "gn:feature_code":"PPL",
    "gn:name":"Yangjun",
    "gn:population":0,
    "gn:timezone":"Asia/Shanghai",
    "iso:country":"CN",
    "name:urd_x_preferred":[
        "\u06cc\u0646\u06af\u062c\u0646"
    ],
    "name:zho_x_preferred":[
        "\u517b\u519b"
    ],
    "name:zho_x_variant":[
        "\u7f8a\u90e1\u9547"
    ],
    "wof:name":"Yangjun",
    "wof:placetype":"locality"
},
  "geometry": {"coordinates":[109.15579,31.08741],"type":"Point"}
}