{
  "type": "Feature",
  "properties": {
    "gn:admin1_code":"03",
    "gn:asciiname":"Keshuling",
    "gn:country_code":"CN",
    "gn:dem":369,
    "gn:feature_class":"P",
    "gn:feature_code":"PPL",
    "gn:name":"Keshuling",
    "gn:population":0,
    "gn:timezone":"Asia/Shanghai",
    "iso:country":"CN",
    "name:und_x_variant":[
        "K\u2019o-shu-ling",
        "Keshuling"
    ],
    "name:zho_x_preferred":[
        "\u67ef\u6811\u5cad"
    ],
    "wof:name":"Keshuling",
    "wof:placetype":"locality"
},
  "geometry": {"coordinates":[114.182,25.6254],"type":"Point"}
}