{
  "type": "Feature",
  "properties": {
    "gn:admin1_code":"4.0",
    "gn:asciiname":"Sanbacun",
    "gn:country_code":"CN",
    "gn:dem":15,
    "gn:feature_class":"P",
    "gn:feature_code":"PPL",
    "gn:name":"Sanbacun",
    "gn:population":0,
    "gn:timezone":"Asia/Shanghai",
    "iso:country":"CN",
    "name:zho_x_preferred":[
        "\u4e09\u575d\u6751"
    ],
    "wof:name":"Sanbacun",
    "wof:placetype":"locality"
},
  "geometry": {"coordinates":[118.77428999999999,33.62653],"type":"Point"}
}