{
  "type": "Feature",
  "properties": {
    "gn:admin1_code":"14.0",
    "gn:asciiname":"Yamagele",
    "gn:country_code":"CN",
    "gn:dem":4486,
    "gn:feature_class":"P",
    "gn:feature_code":"PPL",
    "gn:name":"Yamagele",
    "gn:population":0,
    "gn:timezone":"Asia/Urumqi",
    "iso:country":"CN",
    "name:zho_x_preferred":[
        "\u96c5\u9ebb\u683c\u52d2"
    ],
    "wof:name":"Yamagele",
    "wof:placetype":"locality"
},
  "geometry": {"coordinates":[97.10782,30.48437],"type":"Point"}
}