{
  "type": "Feature",
  "properties": {
    "gn:admin1_code":"8.0",
    "gn:asciiname":"Wuyinghe Guanliqu",
    "gn:country_code":"CN",
    "gn:dem":316,
    "gn:feature_class":"P",
    "gn:feature_code":"PPL",
    "gn:name":"Wuyinghe Guanliqu",
    "gn:population":0,
    "gn:timezone":"Asia/Shanghai",
    "iso:country":"CN",
    "name:zho_x_preferred":[
        "\u4e94\u8425\u6cb3\u7ba1\u7406\u533a"
    ],
    "wof:name":"Wuyinghe Guanliqu",
    "wof:placetype":"locality"
},
  "geometry": {"coordinates":[129.25836000000001,48.07607],"type":"Point"}
}