{
  "type": "Feature",
  "properties": {
    "gn:admin1_code":"10",
    "gn:asciiname":"Guoguoshan",
    "gn:country_code":"CN",
    "gn:dem":1434,
    "gn:feature_class":"P",
    "gn:feature_code":"PPL",
    "gn:name":"Guoguoshan",
    "gn:population":0,
    "gn:timezone":"Asia/Shanghai",
    "iso:country":"CN",
    "name:zho_x_preferred":[
        "\u8748\u8748\u5c71"
    ],
    "wof:name":"Guoguoshan",
    "wof:placetype":"locality"
},
  "geometry": {"coordinates":[115.81403,41.68855],"type":"Point"}
}