{
  "type": "Feature",
  "properties": {
    "gn:admin1_code":"26.0",
    "gn:asciiname":"Yonghongcun",
    "gn:country_code":"CN",
    "gn:dem":1017,
    "gn:feature_class":"P",
    "gn:feature_code":"PPL",
    "gn:name":"Yonghongcun",
    "gn:population":0,
    "gn:timezone":"Asia/Shanghai",
    "iso:country":"CN",
    "name:zho_x_preferred":[
        "\u6c38\u7ea2\u6751"
    ],
    "wof:name":"Yonghongcun",
    "wof:placetype":"locality"
},
  "geometry": {"coordinates":[108.72005,32.44204000000001],"type":"Point"}
}