{
  "type": "Feature",
  "properties": {
    "gn:admin1_code":"4.0",
    "gn:asciiname":"Dongdang",
    "gn:country_code":"CN",
    "gn:dem":4,
    "gn:feature_class":"P",
    "gn:feature_code":"PPL",
    "gn:name":"Dongdang",
    "gn:population":0,
    "gn:timezone":"Asia/Shanghai",
    "iso:country":"CN",
    "name:zho_x_preferred":[
        "Dongdang"
    ],
    "name:zho_x_variant":[
        "\u4e1c\u8361"
    ],
    "wof:name":"Dongdang",
    "wof:placetype":"locality"
},
  "geometry": {"coordinates":[119.67382000000001,33.03582],"type":"Point"}
}