{
  "type": "Feature",
  "properties": {
    "gn:admin1_code":"14.0",
    "gn:asciiname":"Gongzudagu",
    "gn:country_code":"CN",
    "gn:dem":4394,
    "gn:feature_class":"P",
    "gn:feature_code":"PPL",
    "gn:name":"Gongzudagu",
    "gn:population":0,
    "gn:timezone":"Asia/Urumqi",
    "iso:country":"CN",
    "name:zho_x_preferred":[
        "\u5171\u8db3\u6253\u8c37"
    ],
    "wof:name":"Gongzudagu",
    "wof:placetype":"locality"
},
  "geometry": {"coordinates":[83.6066,32.012],"type":"Point"}
}