{
  "type": "Feature",
  "properties": {
    "gn:admin1_code":"8.0",
    "gn:asciiname":"Yongqiancun",
    "gn:country_code":"CN",
    "gn:dem":68,
    "gn:feature_class":"P",
    "gn:feature_code":"PPL",
    "gn:name":"Yongqiancun",
    "gn:population":0,
    "gn:timezone":"Asia/Shanghai",
    "iso:country":"CN",
    "name:zho_x_preferred":[
        "\u6c38\u524d\u6751"
    ],
    "wof:name":"Yongqiancun",
    "wof:placetype":"locality"
},
  "geometry": {"coordinates":[133.49424999999999,47.16352],"type":"Point"}
}