{
  "type": "Feature",
  "properties": {
    "gn:admin1_code":"32.0",
    "gn:asciiname":"Guanling",
    "gn:country_code":"CN",
    "gn:dem":1414,
    "gn:feature_class":"P",
    "gn:feature_code":"PPL",
    "gn:name":"Guanling",
    "gn:population":0,
    "gn:timezone":"Asia/Shanghai",
    "iso:country":"CN",
    "name:zho_x_preferred":[
        "\u8d2f\u5cad"
    ],
    "wof:name":"Guanling",
    "wof:placetype":"locality"
},
  "geometry": {"coordinates":[104.55159999999999,32.03084],"type":"Point"}
}