{
  "type": "Feature",
  "properties": {
    "gn:admin1_code":"4.0",
    "gn:asciiname":"Longtian",
    "gn:country_code":"CN",
    "gn:dem":5,
    "gn:feature_class":"P",
    "gn:feature_code":"PPL",
    "gn:name":"Longtian",
    "gn:population":0,
    "gn:timezone":"Asia/Shanghai",
    "iso:country":"CN",
    "name:ceb_x_preferred":[
        "Longtian"
    ],
    "name:swe_x_preferred":[
        "Longtian"
    ],
    "name:und_x_variant":[
        "\u9f99\u7530"
    ],
    "wof:name":"Longtian",
    "wof:placetype":"locality"
},
  "geometry": {"coordinates":[120.98284,31.91046],"type":"Point"}
}