{
  "type": "Feature",
  "properties": {
    "gn:admin1_code":"11.0",
    "gn:asciiname":"Huangtianli",
    "gn:country_code":"CN",
    "gn:dem":97,
    "gn:feature_class":"P",
    "gn:feature_code":"PPL",
    "gn:name":"Huangtianli",
    "gn:population":0,
    "gn:timezone":"Asia/Shanghai",
    "iso:country":"CN",
    "name:zho_x_preferred":[
        "\u9ec4\u7530\u91cc"
    ],
    "wof:name":"Huangtianli",
    "wof:placetype":"locality"
},
  "geometry": {"coordinates":[113.18783999999999,28.50865],"type":"Point"}
}