{
  "type": "Feature",
  "properties": {
    "gn:admin1_code":"14.0",
    "gn:asciiname":"Galegong",
    "gn:country_code":"CN",
    "gn:dem":4329,
    "gn:feature_class":"P",
    "gn:feature_code":"PPL",
    "gn:name":"Galegong",
    "gn:population":0,
    "gn:timezone":"Asia/Urumqi",
    "iso:country":"CN",
    "name:zho_x_preferred":[
        "\u560e\u52d2\u5171"
    ],
    "wof:name":"Galegong",
    "wof:placetype":"locality"
},
  "geometry": {"coordinates":[95.86774,31.39475],"type":"Point"}
}