{
  "type": "Feature",
  "properties": {
    "gn:admin1_code":"30",
    "gn:asciiname":"Beishi",
    "gn:country_code":"CN",
    "gn:dem":240,
    "gn:feature_class":"P",
    "gn:feature_code":"PPLA4",
    "gn:name":"Beishi",
    "gn:population":0,
    "gn:timezone":"Asia/Shanghai",
    "iso:country":"CN",
    "name:ceb_x_preferred":[
        "Beishi"
    ],
    "name:deu_x_preferred":[
        "Beishi"
    ],
    "name:swe_x_preferred":[
        "Beishi"
    ],
    "name:und_x_variant":[
        "Pei-shih",
        "Beishi Zhen",
        "\u5317\u5e02\u9547"
    ],
    "name:zho_x_preferred":[
        "\u5317\u5e02"
    ],
    "wof:name":"Beishi",
    "wof:placetype":"locality"
},
  "geometry": {"coordinates":[112.57125000000001,23.83947],"type":"Point"}
}