{
  "type": "Feature",
  "properties": {
    "gn:admin1_code":"1.0",
    "gn:asciiname":"Lutangcun",
    "gn:country_code":"CN",
    "gn:dem":49,
    "gn:feature_class":"P",
    "gn:feature_code":"PPL",
    "gn:name":"Lutangcun",
    "gn:population":0,
    "gn:timezone":"Asia/Shanghai",
    "iso:country":"CN",
    "name:zho_x_preferred":[
        "\u9e7f\u5858\u6751"
    ],
    "wof:name":"Lutangcun",
    "wof:placetype":"locality"
},
  "geometry": {"coordinates":[117.62829000000001,32.79069],"type":"Point"}
}