{
  "type": "Feature",
  "properties": {
    "gn:admin1_code":"25",
    "gn:asciiname":"Xiaoshao",
    "gn:country_code":"CN",
    "gn:dem":42,
    "gn:feature_class":"P",
    "gn:feature_code":"PPL",
    "gn:name":"Xiaoshao",
    "gn:population":0,
    "gn:timezone":"Asia/Shanghai",
    "iso:country":"CN",
    "name:zho_x_preferred":[
        "\u5c0f\u90b5"
    ],
    "wof:name":"Xiaoshao",
    "wof:placetype":"locality"
},
  "geometry": {"coordinates":[116.45999999999999,35.5794],"type":"Point"}
}