{
  "type": "Feature",
  "properties": {
    "gn:admin1_code":"9.0",
    "gn:asciiname":"Taipingbu",
    "gn:country_code":"CN",
    "gn:dem":204,
    "gn:feature_class":"P",
    "gn:feature_code":"PPL",
    "gn:name":"Taipingbu",
    "gn:population":0,
    "gn:timezone":"Asia/Shanghai",
    "iso:country":"CN",
    "name:und_x_variant":[
        "\u592a\u5e73\u5821",
        "Taipingbu"
    ],
    "wof:name":"Taipingbu",
    "wof:placetype":"locality"
},
  "geometry": {"coordinates":[112.73971,33.84305],"type":"Point"}
}