{
  "type": "Feature",
  "properties": {
    "gn:admin1_code":"8.0",
    "gn:asciiname":"Wangjijiang",
    "gn:country_code":"CN",
    "gn:dem":196,
    "gn:feature_class":"P",
    "gn:feature_code":"PPL",
    "gn:name":"Wangjijiang",
    "gn:population":0,
    "gn:timezone":"Asia/Shanghai",
    "iso:country":"CN",
    "name:zho_x_preferred":[
        "\u738b\u673a\u5320"
    ],
    "wof:name":"Wangjijiang",
    "wof:placetype":"locality"
},
  "geometry": {"coordinates":[127.71042,46.9033],"type":"Point"}
}