{
  "type": "Feature",
  "properties": {
    "gn:admin1_code":"25",
    "gn:asciiname":"Dongshuang Wuzi",
    "gn:country_code":"CN",
    "gn:dem":4,
    "gn:feature_class":"P",
    "gn:feature_code":"PPL",
    "gn:name":"Dongshuang Wuzi",
    "gn:population":0,
    "gn:timezone":"Asia/Shanghai",
    "iso:country":"CN",
    "name:zho_x_preferred":[
        "\u4e1c\u53cc\u5c4b\u5b50"
    ],
    "wof:name":"Dongshuang Wuzi",
    "wof:placetype":"locality"
},
  "geometry": {"coordinates":[118.622,38.0031],"type":"Point"}
}