{
  "type": "Feature",
  "properties": {
    "gn:admin1_code":"14.0",
    "gn:asciiname":"Sangmaduocun",
    "gn:country_code":"CN",
    "gn:dem":4469,
    "gn:feature_class":"P",
    "gn:feature_code":"PPL",
    "gn:name":"Sangmaduocun",
    "gn:population":0,
    "gn:timezone":"Asia/Urumqi",
    "iso:country":"CN",
    "name:zho_x_preferred":[
        "\u6851\u739b\u6735\u6751"
    ],
    "wof:name":"Sangmaduocun",
    "wof:placetype":"locality"
},
  "geometry": {"coordinates":[92.97057,31.43935],"type":"Point"}
}