{
  "type": "Feature",
  "properties": {
    "gn:admin1_code":"11.0",
    "gn:asciiname":"Mojiazhou",
    "gn:country_code":"CN",
    "gn:dem":261,
    "gn:feature_class":"P",
    "gn:feature_code":"PPL",
    "gn:name":"Mojiazhou",
    "gn:population":0,
    "gn:timezone":"Asia/Shanghai",
    "iso:country":"CN",
    "name:zho_x_preferred":[
        "\u83ab\u5bb6\u6d32"
    ],
    "wof:name":"Mojiazhou",
    "wof:placetype":"locality"
},
  "geometry": {"coordinates":[110.92272,27.13408],"type":"Point"}
}