{
  "type": "Feature",
  "properties": {
    "gn:admin1_code":"15.0",
    "gn:asciiname":"Zhenwudian",
    "gn:country_code":"CN",
    "gn:dem":1620,
    "gn:feature_class":"P",
    "gn:feature_code":"PPL",
    "gn:name":"Zhenwudian",
    "gn:population":0,
    "gn:timezone":"Asia/Shanghai",
    "iso:country":"CN",
    "name:und_x_variant":[
        "\u771f\u6b66\u6bbf"
    ],
    "wof:name":"Zhenwudian",
    "wof:placetype":"locality"
},
  "geometry": {"coordinates":[105.33156,33.81531],"type":"Point"}
}