{
  "type": "Feature",
  "properties": {
    "gn:admin1_code":"3.0",
    "gn:asciiname":"Yifang",
    "gn:country_code":"CN",
    "gn:dem":319,
    "gn:feature_class":"P",
    "gn:feature_code":"PPL",
    "gn:name":"Yifang",
    "gn:population":0,
    "gn:timezone":"Asia/Shanghai",
    "iso:country":"CN",
    "name:zho_x_preferred":[
        "\u8d3b\u574a"
    ],
    "wof:name":"Yifang",
    "wof:placetype":"locality"
},
  "geometry": {"coordinates":[116.97199999999999,27.6275],"type":"Point"}
}