{
  "type": "Feature",
  "properties": {
    "gn:admin1_code":"25",
    "gn:asciiname":"Jisibu",
    "gn:country_code":"CN",
    "gn:dem":182,
    "gn:feature_class":"P",
    "gn:feature_code":"PPL",
    "gn:name":"Jisibu",
    "gn:population":0,
    "gn:timezone":"Asia/Shanghai",
    "iso:country":"CN",
    "name:zho_x_preferred":[
        "\u5409\u5bfa\u57e0"
    ],
    "wof:name":"Jisibu",
    "wof:placetype":"locality"
},
  "geometry": {"coordinates":[118.602,36.4312],"type":"Point"}
}