{
  "type": "Feature",
  "properties": {
    "gn:admin1_code":"1.0",
    "gn:asciiname":"Wangchongcun",
    "gn:country_code":"CN",
    "gn:dem":331,
    "gn:feature_class":"P",
    "gn:feature_code":"PPL",
    "gn:name":"Wangchongcun",
    "gn:population":0,
    "gn:timezone":"Asia/Shanghai",
    "iso:country":"CN",
    "name:zho_x_preferred":[
        "\u6c6a\u51b2\u6751"
    ],
    "wof:name":"Wangchongcun",
    "wof:placetype":"locality"
},
  "geometry": {"coordinates":[116.5907,31.12988],"type":"Point"}
}