{
  "type": "Feature",
  "properties": {
    "gn:admin1_code":"15.0",
    "gn:asciiname":"Wanzi",
    "gn:country_code":"CN",
    "gn:dem":2054,
    "gn:feature_class":"P",
    "gn:feature_code":"PPL",
    "gn:name":"Wanzi",
    "gn:population":0,
    "gn:timezone":"Asia/Shanghai",
    "iso:country":"CN",
    "name:zho_x_preferred":[
        "\u6e7e\u5b50"
    ],
    "wof:name":"Wanzi",
    "wof:placetype":"locality"
},
  "geometry": {"coordinates":[103.551,35.7596],"type":"Point"}
}