{
  "type": "Feature",
  "properties": {
    "gn:admin1_code":"33.0",
    "gn:asciiname":"Liziyuan",
    "gn:country_code":"CN",
    "gn:dem":435,
    "gn:feature_class":"P",
    "gn:feature_code":"PPL",
    "gn:name":"Liziyuan",
    "gn:population":0,
    "gn:timezone":"Asia/Shanghai",
    "iso:country":"CN",
    "name:zho_x_preferred":[
        "\u68a8\u5b50\u56ed"
    ],
    "wof:name":"Liziyuan",
    "wof:placetype":"locality"
},
  "geometry": {"coordinates":[107.48812,30.48063],"type":"Point"}
}