{
  "type": "Feature",
  "properties": {
    "gn:admin1_code":"8.0",
    "gn:asciiname":"Zhenxingcun",
    "gn:country_code":"CN",
    "gn:dem":161,
    "gn:feature_class":"P",
    "gn:feature_code":"PPL",
    "gn:name":"Zhenxingcun",
    "gn:population":0,
    "gn:timezone":"Asia/Shanghai",
    "iso:country":"CN",
    "name:zho_x_preferred":[
        "\u632f\u5174\u6751"
    ],
    "wof:name":"Zhenxingcun",
    "wof:placetype":"locality"
},
  "geometry": {"coordinates":[129.93496999999999,46.05793],"type":"Point"}
}