{
  "type": "Feature",
  "properties": {
    "gn:admin1_code":"15.0",
    "gn:asciiname":"Doujiaping",
    "gn:country_code":"CN",
    "gn:dem":1018,
    "gn:feature_class":"P",
    "gn:feature_code":"PPL",
    "gn:name":"Doujiaping",
    "gn:population":0,
    "gn:timezone":"Asia/Shanghai",
    "iso:country":"CN",
    "name:und_x_variant":[
        "\u8c46\u5bb6\u576a"
    ],
    "wof:name":"Doujiaping",
    "wof:placetype":"locality"
},
  "geometry": {"coordinates":[106.40525,33.9504],"type":"Point"}
}