{
  "type": "Feature",
  "properties": {
    "gn:admin1_code":"1.0",
    "gn:asciiname":"Xiheshan",
    "gn:country_code":"CN",
    "gn:dem":17,
    "gn:feature_class":"P",
    "gn:feature_code":"PPLA4",
    "gn:name":"Xiheshan",
    "gn:population":0,
    "gn:timezone":"Asia/Shanghai",
    "iso:country":"CN",
    "name:und_x_variant":[
        "Xiheshan Jiedao",
        "\u897f\u8910\u5c71\u8857\u9053",
        "Xiheshan"
    ],
    "name:zho_x_preferred":[
        "\u897f\u8910\u5c71"
    ],
    "wof:name":"Xiheshan",
    "wof:placetype":"locality"
},
  "geometry": {"coordinates":[118.34893,31.44302],"type":"Point"}
}