{
  "type": "Feature",
  "properties": {
    "gn:admin1_code":"01",
    "gn:asciiname":"Qutingcun",
    "gn:country_code":"CN",
    "gn:dem":63,
    "gn:feature_class":"P",
    "gn:feature_code":"PPL",
    "gn:name":"Qutingcun",
    "gn:population":0,
    "gn:timezone":"Asia/Shanghai",
    "iso:country":"CN",
    "name:und_x_variant":[
        "Ch\u2019\u00fc-t\u2019ing-chi",
        "Ch\u2019u-t\u2019ing-tien",
        "Ch\u2019\u00fc-t\u2019ing",
        "Quting",
        "Qutingcun"
    ],
    "name:zho_x_preferred":[
        "\u66f2\u4ead\u6751"
    ],
    "wof:name":"Qutingcun",
    "wof:placetype":"locality"
},
  "geometry": {"coordinates":[118.04386,32.37035],"type":"Point"}
}