{
  "type": "Feature",
  "properties": {
    "gn:admin1_code":"30.0",
    "gn:asciiname":"Tiandongcun",
    "gn:country_code":"CN",
    "gn:dem":102,
    "gn:feature_class":"P",
    "gn:feature_code":"PPL",
    "gn:name":"Tiandongcun",
    "gn:population":0,
    "gn:timezone":"Asia/Shanghai",
    "iso:country":"CN",
    "name:zho_x_preferred":[
        "\u7530\u4e1c\u6751"
    ],
    "wof:name":"Tiandongcun",
    "wof:placetype":"locality"
},
  "geometry": {"coordinates":[116.31623999999999,24.0633],"type":"Point"}
}