{
  "type": "Feature",
  "properties": {
    "gn:admin1_code":"19.0",
    "gn:asciiname":"Nantaizi",
    "gn:country_code":"CN",
    "gn:dem":294,
    "gn:feature_class":"P",
    "gn:feature_code":"PPL",
    "gn:name":"Nantaizi",
    "gn:population":0,
    "gn:timezone":"Asia/Shanghai",
    "iso:country":"CN",
    "name:und_x_variant":[
        "\u5357\u53f0\u5b50"
    ],
    "wof:name":"Nantaizi",
    "wof:placetype":"locality"
},
  "geometry": {"coordinates":[122.87076,40.14521],"type":"Point"}
}