{
  "type": "Feature",
  "properties": {
    "gn:admin1_code":"29.0",
    "gn:asciiname":"Guanbachong",
    "gn:country_code":"CN",
    "gn:dem":2039,
    "gn:feature_class":"P",
    "gn:feature_code":"PPL",
    "gn:name":"Guanbachong",
    "gn:population":0,
    "gn:timezone":"Asia/Shanghai",
    "iso:country":"CN",
    "name:zho_x_preferred":[
        "\u5b98\u575d\u51b2"
    ],
    "wof:name":"Guanbachong",
    "wof:placetype":"locality"
},
  "geometry": {"coordinates":[103.557,27.3954],"type":"Point"}
}