{
  "type": "Feature",
  "properties": {
    "gn:admin1_code":"26.0",
    "gn:asciiname":"Yin'ancun",
    "gn:country_code":"CN",
    "gn:dem":892,
    "gn:feature_class":"P",
    "gn:feature_code":"PPL",
    "gn:name":"Yin\u2019ancun",
    "gn:population":0,
    "gn:timezone":"Asia/Shanghai",
    "iso:country":"CN",
    "name:und_x_variant":[
        "Yin\u2019ancun"
    ],
    "name:zho_x_preferred":[
        "\u5f15\u5b89\u6751"
    ],
    "wof:name":"Yin'ancun",
    "wof:placetype":"locality"
},
  "geometry": {"coordinates":[108.65757000000001,34.78943],"type":"Point"}
}