{
  "type": "Feature",
  "properties": {
    "gn:admin1_code":"10",
    "gn:asciiname":"Maliankou",
    "gn:country_code":"CN",
    "gn:dem":1282,
    "gn:feature_class":"P",
    "gn:feature_code":"PPL",
    "gn:name":"Maliankou",
    "gn:population":0,
    "gn:timezone":"Asia/Shanghai",
    "iso:country":"CN",
    "name:zho_x_preferred":[
        "\u9a6c\u8fde\u53e3"
    ],
    "wof:name":"Maliankou",
    "wof:placetype":"locality"
},
  "geometry": {"coordinates":[115.55901,41.24843],"type":"Point"}
}