{
  "type": "Feature",
  "properties": {
    "gn:admin1_code":"3",
    "gn:asciiname":"Beimen",
    "gn:country_code":"CN",
    "gn:dem":63,
    "gn:feature_class":"P",
    "gn:feature_code":"PPL",
    "gn:name":"Beimen",
    "gn:population":0,
    "gn:timezone":"Asia/Shanghai",
    "iso:country":"CN",
    "name:zho_x_preferred":[
        "\u5317\u95e8"
    ],
    "wof:name":"Beimen",
    "wof:placetype":"locality"
},
  "geometry": {"coordinates":[114.90407999999999,26.80007],"type":"Point"}
}