{
  "type": "Feature",
  "properties": {
    "gn:admin1_code":"12.0",
    "gn:asciiname":"Wuwahe",
    "gn:country_code":"CN",
    "gn:dem":30,
    "gn:feature_class":"P",
    "gn:feature_code":"PPL",
    "gn:name":"Wuwahe",
    "gn:population":0,
    "gn:timezone":"Asia/Shanghai",
    "iso:country":"CN",
    "name:zho_x_preferred":[
        "\u5434\u74e6\u6cb3"
    ],
    "wof:name":"Wuwahe",
    "wof:placetype":"locality"
},
  "geometry": {"coordinates":[112.36075,30.3546],"type":"Point"}
}