{
  "type": "Feature",
  "properties": {
    "gn:admin1_code":"18",
    "gn:asciiname":"Tianping",
    "gn:country_code":"CN",
    "gn:dem":745,
    "gn:feature_class":"P",
    "gn:feature_code":"PPL",
    "gn:name":"Tianping",
    "gn:population":0,
    "gn:timezone":"Asia/Shanghai",
    "iso:country":"CN",
    "name:zho_x_preferred":[
        "\u7530\u5e73"
    ],
    "wof:name":"Tianping",
    "wof:placetype":"locality"
},
  "geometry": {"coordinates":[105.797,24.9811],"type":"Point"}
}