{
  "type": "Feature",
  "properties": {
    "gn:admin1_code":"13.0",
    "gn:asciiname":"Qiate",
    "gn:country_code":"CN",
    "gn:dem":3293,
    "gn:feature_class":"P",
    "gn:feature_code":"PPL",
    "gn:name":"Qiate",
    "gn:population":0,
    "gn:timezone":"Asia/Shanghai",
    "iso:country":"CN",
    "name:und_x_variant":[
        "\u6070\u7279"
    ],
    "wof:name":"Qiate",
    "wof:placetype":"locality"
},
  "geometry": {"coordinates":[76.34387,38.18373],"type":"Point"}
}