{
  "type": "Feature",
  "properties": {
    "gn:admin1_code":"3.0",
    "gn:asciiname":"Fenghuangping",
    "gn:country_code":"CN",
    "gn:dem":182,
    "gn:feature_class":"P",
    "gn:feature_code":"PPL",
    "gn:name":"Fenghuangping",
    "gn:population":0,
    "gn:timezone":"Asia/Shanghai",
    "iso:country":"CN",
    "name:und_x_variant":[
        "\u51e4\u51f0\u576a"
    ],
    "wof:name":"Fenghuangping",
    "wof:placetype":"locality"
},
  "geometry": {"coordinates":[114.33396999999999,28.89646],"type":"Point"}
}