{
  "type": "Feature",
  "properties": {
    "gn:admin1_code":"32.0",
    "gn:asciiname":"Moziqiao",
    "gn:country_code":"CN",
    "gn:dem":470,
    "gn:feature_class":"P",
    "gn:feature_code":"PPL",
    "gn:name":"Moziqiao",
    "gn:population":0,
    "gn:timezone":"Asia/Shanghai",
    "iso:country":"CN",
    "name:zho_x_preferred":[
        "\u78e8\u5b50\u6865"
    ],
    "wof:name":"Moziqiao",
    "wof:placetype":"locality"
},
  "geometry": {"coordinates":[104.64933000000001,30.88105],"type":"Point"}
}