{
  "type": "Feature",
  "properties": {
    "gn:admin1_code":"26.0",
    "gn:asciiname":"Fujiaping",
    "gn:country_code":"CN",
    "gn:dem":1168,
    "gn:feature_class":"P",
    "gn:feature_code":"PPL",
    "gn:name":"Fujiaping",
    "gn:population":0,
    "gn:timezone":"Asia/Shanghai",
    "iso:country":"CN",
    "name:und_x_variant":[
        "\u4ed8\u5bb6\u576a"
    ],
    "wof:name":"Fujiaping",
    "wof:placetype":"locality"
},
  "geometry": {"coordinates":[107.22492,33.55583],"type":"Point"}
}