{
  "type": "Feature",
  "properties": {
    "gn:admin1_code":"5.0",
    "gn:asciiname":"Qianshantun",
    "gn:country_code":"CN",
    "gn:dem":209,
    "gn:feature_class":"P",
    "gn:feature_code":"PPL",
    "gn:name":"Qianshantun",
    "gn:population":0,
    "gn:timezone":"Asia/Shanghai",
    "iso:country":"CN",
    "name:zho_x_preferred":[
        "\u524d\u5c71\u5c6f"
    ],
    "wof:name":"Qianshantun",
    "wof:placetype":"locality"
},
  "geometry": {"coordinates":[125.36433999999998,44.37409],"type":"Point"}
}