{
  "type": "Feature",
  "properties": {
    "gn:admin1_code":"11.0",
    "gn:asciiname":"Baizhutang",
    "gn:country_code":"CN",
    "gn:dem":467,
    "gn:feature_class":"P",
    "gn:feature_code":"PPL",
    "gn:name":"Baizhutang",
    "gn:population":0,
    "gn:timezone":"Asia/Shanghai",
    "iso:country":"CN",
    "name:zho_x_preferred":[
        "\u767d\u7af9\u5858"
    ],
    "wof:name":"Baizhutang",
    "wof:placetype":"locality"
},
  "geometry": {"coordinates":[109.92932999999999,27.07183],"type":"Point"}
}