{
  "type": "Feature",
  "properties": {
    "gn:admin1_code":"12.0",
    "gn:asciiname":"Wujiazha",
    "gn:country_code":"CN",
    "gn:dem":85,
    "gn:feature_class":"P",
    "gn:feature_code":"PPL",
    "gn:name":"Wujiazha",
    "gn:population":0,
    "gn:timezone":"Asia/Shanghai",
    "iso:country":"CN",
    "name:zho_x_preferred":[
        "\u6b66\u5bb6\u69a8"
    ],
    "wof:name":"Wujiazha",
    "wof:placetype":"locality"
},
  "geometry": {"coordinates":[114.15118,31.7348],"type":"Point"}
}