{
  "type": "Feature",
  "properties": {
    "gn:admin1_code":"24",
    "gn:asciiname":"Donggeta",
    "gn:cc2":"CN",
    "gn:country_code":"CN",
    "gn:dem":1184,
    "gn:feature_class":"P",
    "gn:feature_code":"PPL",
    "gn:name":"Donggeta",
    "gn:population":0,
    "gn:timezone":"Asia/Shanghai",
    "iso:country":"CN",
    "name:und_x_variant":[
        "Tung-ko-t\u2019a",
        "Donggeta"
    ],
    "wof:name":"Donggeta",
    "wof:placetype":"locality"
},
  "geometry": {"coordinates":[111.40000000000001,36.35],"type":"Point"}
}