{
  "type": "Feature",
  "properties": {
    "gn:admin1_code":"5.0",
    "gn:asciiname":"Qingfengcun",
    "gn:country_code":"CN",
    "gn:dem":183,
    "gn:feature_class":"P",
    "gn:feature_code":"PPL",
    "gn:name":"Qingfengcun",
    "gn:population":0,
    "gn:timezone":"Asia/Shanghai",
    "iso:country":"CN",
    "name:zho_x_preferred":[
        "\u5e86\u4e30\u6751"
    ],
    "wof:name":"Qingfengcun",
    "wof:placetype":"locality"
},
  "geometry": {"coordinates":[125.61561,44.62316],"type":"Point"}
}