{
  "type": "Feature",
  "properties": {
    "gn:admin1_code":"19.0",
    "gn:asciiname":"Dongbeicun",
    "gn:country_code":"CN",
    "gn:dem":168,
    "gn:feature_class":"P",
    "gn:feature_code":"PPL",
    "gn:name":"Dongbeicun",
    "gn:population":0,
    "gn:timezone":"Asia/Shanghai",
    "iso:country":"CN",
    "name:und_x_variant":[
        "Dongbei"
    ],
    "name:zho_x_preferred":[
        "\u4e1c\u5317\u6751"
    ],
    "name:zho_x_variant":[
        "\u4e1c\u5317"
    ],
    "wof:name":"Dongbeicun",
    "wof:placetype":"locality"
},
  "geometry": {"coordinates":[124.39667,42.84354],"type":"Point"}
}