{
  "type": "Feature",
  "properties": {
    "gn:admin1_code":"29.0",
    "gn:asciiname":"Shuicaochong",
    "gn:country_code":"CN",
    "gn:dem":1752,
    "gn:feature_class":"P",
    "gn:feature_code":"PPL",
    "gn:name":"Shuicaochong",
    "gn:population":0,
    "gn:timezone":"Asia/Shanghai",
    "iso:country":"CN",
    "name:zho_x_preferred":[
        "\u6c34\u8349\u51b2"
    ],
    "wof:name":"Shuicaochong",
    "wof:placetype":"locality"
},
  "geometry": {"coordinates":[102.95099999999999,23.5451],"type":"Point"}
}