{
  "type": "Feature",
  "properties": {
    "gn:admin1_code":"5.0",
    "gn:asciiname":"Jianchanggou",
    "gn:country_code":"CN",
    "gn:dem":337,
    "gn:feature_class":"P",
    "gn:feature_code":"PPL",
    "gn:name":"Jianchanggou",
    "gn:population":0,
    "gn:timezone":"Asia/Shanghai",
    "iso:country":"CN",
    "name:und_x_variant":[
        "Jianchang",
        "\u8327\u573a",
        "Jianchanggou"
    ],
    "name:zho_x_preferred":[
        "\u8327\u573a\u6c9f"
    ],
    "wof:name":"Jianchanggou",
    "wof:placetype":"locality"
},
  "geometry": {"coordinates":[125.60186000000002,41.40051],"type":"Point"}
}