{
  "type": "Feature",
  "properties": {
    "gn:admin1_code":"20.0",
    "gn:asciiname":"Bulanwa",
    "gn:country_code":"CN",
    "gn:dem":1292,
    "gn:feature_class":"P",
    "gn:feature_code":"PPL",
    "gn:name":"Bulanwa",
    "gn:population":0,
    "gn:timezone":"Asia/Shanghai",
    "iso:country":"CN",
    "name:und_x_variant":[
        "\u4e0d\u70c2\u6d3c"
    ],
    "wof:name":"Bulanwa",
    "wof:placetype":"locality"
},
  "geometry": {"coordinates":[111.52137999999999,39.88499],"type":"Point"}
}