{
  "type": "Feature",
  "properties": {
    "gn:admin1_code":"9.0",
    "gn:asciiname":"Liucungang",
    "gn:country_code":"CN",
    "gn:dem":65,
    "gn:feature_class":"P",
    "gn:feature_code":"PPL",
    "gn:name":"Liucungang",
    "gn:population":0,
    "gn:timezone":"Asia/Shanghai",
    "iso:country":"CN",
    "name:zho_x_preferred":[
        "\u5218\u5bf8\u5c97"
    ],
    "wof:name":"Liucungang",
    "wof:placetype":"locality"
},
  "geometry": {"coordinates":[114.4157,34.35005],"type":"Point"}
}