{
  "type": "Feature",
  "properties": {
    "gn:admin1_code":"3.0",
    "gn:asciiname":"Zhougongling",
    "gn:country_code":"CN",
    "gn:dem":504,
    "gn:feature_class":"P",
    "gn:feature_code":"PPL",
    "gn:name":"Zhougongling",
    "gn:population":0,
    "gn:timezone":"Asia/Shanghai",
    "iso:country":"CN",
    "name:zho_x_preferred":[
        "\u5468\u516c\u5cad"
    ],
    "wof:name":"Zhougongling",
    "wof:placetype":"locality"
},
  "geometry": {"coordinates":[113.693,27.7194],"type":"Point"}
}