{
  "type": "Feature",
  "properties": {
    "gn:admin1_code":"7.0",
    "gn:asciiname":"Xiayangkeng",
    "gn:country_code":"CN",
    "gn:dem":655,
    "gn:feature_class":"P",
    "gn:feature_code":"PPL",
    "gn:name":"Xiayangkeng",
    "gn:population":0,
    "gn:timezone":"Asia/Shanghai",
    "iso:country":"CN",
    "name:zho_x_preferred":[
        "\u4e0b\u6d0b\u5751"
    ],
    "wof:name":"Xiayangkeng",
    "wof:placetype":"locality"
},
  "geometry": {"coordinates":[119.30198,26.95042],"type":"Point"}
}