{
  "type": "Feature",
  "properties": {
    "gn:admin1_code":"9.0",
    "gn:asciiname":"Lihecun",
    "gn:country_code":"CN",
    "gn:dem":114,
    "gn:feature_class":"P",
    "gn:feature_code":"PPL",
    "gn:name":"Lihecun",
    "gn:population":0,
    "gn:timezone":"Asia/Shanghai",
    "iso:country":"CN",
    "name:zho_x_preferred":[
        "\u68a8\u6cb3\u6751"
    ],
    "wof:name":"Lihecun",
    "wof:placetype":"locality"
},
  "geometry": {"coordinates":[113.72677,34.33998],"type":"Point"}
}