{
  "type": "Feature",
  "properties": {
    "gn:admin1_code":"32.0",
    "gn:asciiname":"Hanlingang",
    "gn:country_code":"CN",
    "gn:dem":2132,
    "gn:feature_class":"P",
    "gn:feature_code":"PPL",
    "gn:name":"Hanlingang",
    "gn:population":0,
    "gn:timezone":"Asia/Shanghai",
    "iso:country":"CN",
    "name:zho_x_preferred":[
        "\u5bd2\u6797\u6760"
    ],
    "wof:name":"Hanlingang",
    "wof:placetype":"locality"
},
  "geometry": {"coordinates":[102.614,28.4927],"type":"Point"}
}