{
  "type": "Feature",
  "properties": {
    "gn:admin1_code":"1.0",
    "gn:asciiname":"Yufengcun",
    "gn:country_code":"CN",
    "gn:dem":16,
    "gn:feature_class":"P",
    "gn:feature_code":"PPL",
    "gn:name":"Yufengcun",
    "gn:population":0,
    "gn:timezone":"Asia/Shanghai",
    "iso:country":"CN",
    "name:zho_x_preferred":[
        "\u88d5\u4e30\u6751"
    ],
    "wof:name":"Yufengcun",
    "wof:placetype":"locality"
},
  "geometry": {"coordinates":[117.15936000000001,30.47117],"type":"Point"}
}