{
  "type": "Feature",
  "properties": {
    "gn:admin1_code":"32.0",
    "gn:asciiname":"Erku",
    "gn:country_code":"CN",
    "gn:dem":2211,
    "gn:feature_class":"P",
    "gn:feature_code":"PPL",
    "gn:name":"Erku",
    "gn:population":0,
    "gn:timezone":"Asia/Shanghai",
    "iso:country":"CN",
    "name:zho_x_preferred":[
        "\u5c14\u5e93"
    ],
    "wof:name":"Erku",
    "wof:placetype":"locality"
},
  "geometry": {"coordinates":[103.0077,28.22447],"type":"Point"}
}