{
  "type": "Feature",
  "properties": {
    "gn:admin1_code":"32.0",
    "gn:asciiname":"Luji",
    "gn:country_code":"CN",
    "gn:dem":2145,
    "gn:feature_class":"P",
    "gn:feature_code":"PPL",
    "gn:name":"Luji",
    "gn:population":0,
    "gn:timezone":"Asia/Shanghai",
    "iso:country":"CN",
    "name:zho_x_preferred":[
        "\u5362\u57fa"
    ],
    "wof:name":"Luji",
    "wof:placetype":"locality"
},
  "geometry": {"coordinates":[102.02500000000001,28.0184],"type":"Point"}
}