{
  "type": "Feature",
  "properties": {
    "gn:admin1_code":"14.0",
    "gn:asciiname":"Rumei",
    "gn:country_code":"CN",
    "gn:dem":2767,
    "gn:feature_class":"P",
    "gn:feature_code":"PPLF",
    "gn:name":"Rumei",
    "gn:population":0,
    "gn:timezone":"Asia/Urumqi",
    "iso:country":"CN",
    "name:bod_x_preferred":[
        "Rongm\u00ea"
    ],
    "name:zho_x_preferred":[
        "Rumei"
    ],
    "name:zho_x_variant":[
        "\u5982\u7f8e"
    ],
    "wof:name":"Rumei",
    "wof:placetype":"locality"
},
  "geometry": {"coordinates":[98.36667,29.63333],"type":"Point"}
}