{
  "type": "Feature",
  "properties": {
    "gn:admin1_code":"12.0",
    "gn:asciiname":"Jianjiakou",
    "gn:country_code":"CN",
    "gn:dem":24,
    "gn:feature_class":"P",
    "gn:feature_code":"PPL",
    "gn:name":"Jianjiakou",
    "gn:population":0,
    "gn:timezone":"Asia/Shanghai",
    "iso:country":"CN",
    "name:zho_x_preferred":[
        "\u7b80\u5bb6\u53e3"
    ],
    "wof:name":"Jianjiakou",
    "wof:placetype":"locality"
},
  "geometry": {"coordinates":[113.37163,30.05724],"type":"Point"}
}