{
  "type": "Feature",
  "properties": {
    "gn:admin1_code":"26.0",
    "gn:asciiname":"Liangwanlu",
    "gn:country_code":"CN",
    "gn:dem":2334,
    "gn:feature_class":"P",
    "gn:feature_code":"PPL",
    "gn:name":"Liangwanlu",
    "gn:population":0,
    "gn:timezone":"Asia/Shanghai",
    "iso:country":"CN",
    "name:und_x_variant":[
        "\u4e24\u6e7e\u8def"
    ],
    "wof:name":"Liangwanlu",
    "wof:placetype":"locality"
},
  "geometry": {"coordinates":[107.06928000000001,34.09104],"type":"Point"}
}