{
  "type": "Feature",
  "properties": {
    "gn:admin1_code":"9.0",
    "gn:asciiname":"Hedi Xiacun",
    "gn:country_code":"CN",
    "gn:dem":74,
    "gn:feature_class":"P",
    "gn:feature_code":"PPL",
    "gn:name":"Hedi Xiacun",
    "gn:population":0,
    "gn:timezone":"Asia/Shanghai",
    "iso:country":"CN",
    "name:zho_x_preferred":[
        "\u6cb3\u5e95\u4e0b\u6751"
    ],
    "wof:name":"Hedi Xiacun",
    "wof:placetype":"locality"
},
  "geometry": {"coordinates":[114.82523,31.81233],"type":"Point"}
}