{
  "type": "Feature",
  "properties": {
    "gn:admin1_code":"8.0",
    "gn:asciiname":"Dagangzi",
    "gn:country_code":"CN",
    "gn:dem":161,
    "gn:feature_class":"P",
    "gn:feature_code":"PPL",
    "gn:name":"Dagangzi",
    "gn:population":0,
    "gn:timezone":"Asia/Shanghai",
    "iso:country":"CN",
    "name:zho_x_preferred":[
        "\u5927\u5c97\u5b50"
    ],
    "wof:name":"Dagangzi",
    "wof:placetype":"locality"
},
  "geometry": {"coordinates":[124.70551,47.58902],"type":"Point"}
}