{
  "type": "Feature",
  "properties": {
    "gn:admin1_code":"3.0",
    "gn:asciiname":"Mushantang",
    "gn:country_code":"CN",
    "gn:dem":73,
    "gn:feature_class":"P",
    "gn:feature_code":"PPL",
    "gn:name":"Mushantang",
    "gn:population":0,
    "gn:timezone":"Asia/Shanghai",
    "iso:country":"CN",
    "name:und_x_variant":[
        "\u6728\u5c71\u5858"
    ],
    "wof:name":"Mushantang",
    "wof:placetype":"locality"
},
  "geometry": {"coordinates":[115.05874,26.93193],"type":"Point"}
}