{
  "type": "Feature",
  "properties": {
    "gn:admin1_code":"25",
    "gn:asciiname":"Liupowu",
    "gn:cc2":"CN",
    "gn:country_code":"CN",
    "gn:dem":11,
    "gn:feature_class":"P",
    "gn:feature_code":"PPL",
    "gn:name":"Liupowu",
    "gn:population":0,
    "gn:timezone":"Asia/Shanghai",
    "iso:country":"CN",
    "name:und_x_variant":[
        "Liu-po",
        "Liu-po-chen",
        "Liubowu",
        "Liupowu"
    ],
    "wof:name":"Liupowu",
    "wof:placetype":"locality"
},
  "geometry": {"coordinates":[117.41667,37.63333],"type":"Point"}
}