{
  "type": "Feature",
  "properties": {
    "gn:admin1_code":"21.0",
    "gn:asciiname":"Hejiacha",
    "gn:country_code":"CN",
    "gn:dem":1946,
    "gn:feature_class":"P",
    "gn:feature_code":"PPL",
    "gn:name":"Hejiacha",
    "gn:population":0,
    "gn:timezone":"Asia/Shanghai",
    "iso:country":"CN",
    "name:und_x_variant":[
        "\u4f55\u5bb6\u5c94"
    ],
    "name:zho_x_preferred":[
        "\u4f55\u5bb6\u5c94"
    ],
    "wof:name":"Hejiacha",
    "wof:placetype":"locality"
},
  "geometry": {"coordinates":[105.51927999999999,35.91876],"type":"Point"}
}