{
  "type": "Feature",
  "properties": {
    "gn:admin1_code":"7.0",
    "gn:asciiname":"Yaoshan",
    "gn:country_code":"CN",
    "gn:dem":400,
    "gn:feature_class":"P",
    "gn:feature_code":"PPL",
    "gn:name":"Yaoshan",
    "gn:population":0,
    "gn:timezone":"Asia/Shanghai",
    "iso:country":"CN",
    "name:ceb_x_preferred":[
        "Yaoshan"
    ],
    "name:swe_x_preferred":[
        "Yaoshan"
    ],
    "name:und_x_variant":[
        "\u5c27\u5c71"
    ],
    "wof:name":"Yaoshan",
    "wof:placetype":"locality"
},
  "geometry": {"coordinates":[116.21666999999999,25.45],"type":"Point"}
}