{
  "type": "Feature",
  "properties": {
    "gn:admin1_code":"2.0",
    "gn:asciiname":"Zhuandaishan",
    "gn:country_code":"CN",
    "gn:dem":714,
    "gn:feature_class":"P",
    "gn:feature_code":"PPL",
    "gn:name":"Zhuandaishan",
    "gn:population":0,
    "gn:timezone":"Asia/Shanghai",
    "iso:country":"CN",
    "name:zho_x_preferred":[
        "\u7bc6\u5cb1\u5c71"
    ],
    "wof:name":"Zhuandaishan",
    "wof:placetype":"locality"
},
  "geometry": {"coordinates":[119.40715,28.77493],"type":"Point"}
}