{
  "type": "Feature",
  "properties": {
    "gn:admin1_code":"10",
    "gn:asciiname":"Mashenmiao",
    "gn:country_code":"CN",
    "gn:dem":1533,
    "gn:feature_class":"P",
    "gn:feature_code":"PPL",
    "gn:name":"Mashenmiao",
    "gn:population":0,
    "gn:timezone":"Asia/Shanghai",
    "iso:country":"CN",
    "name:zho_x_preferred":[
        "\u9a6c\u795e\u5e99"
    ],
    "wof:name":"Mashenmiao",
    "wof:placetype":"locality"
},
  "geometry": {"coordinates":[115.8377,41.38672],"type":"Point"}
}