{
  "type": "Feature",
  "properties": {
    "gn:admin1_code":"9",
    "gn:asciiname":"Congzhuang",
    "gn:country_code":"CN",
    "gn:dem":45,
    "gn:feature_class":"P",
    "gn:feature_code":"PPL",
    "gn:name":"Congzhuang",
    "gn:population":0,
    "gn:timezone":"Asia/Shanghai",
    "iso:country":"CN",
    "name:zho_x_preferred":[
        "\u4ece\u5e84"
    ],
    "wof:name":"Congzhuang",
    "wof:placetype":"locality"
},
  "geometry": {"coordinates":[114.92100000000001,33.74],"type":"Point"}
}