{
  "type": "Feature",
  "properties": {
    "gn:admin1_code":"19.0",
    "gn:asciiname":"Mengke",
    "gn:country_code":"CN",
    "gn:dem":170,
    "gn:feature_class":"P",
    "gn:feature_code":"PPL",
    "gn:name":"Mengke",
    "gn:population":0,
    "gn:timezone":"Asia/Shanghai",
    "iso:country":"CN",
    "name:und_x_variant":[
        "\u5b5f\u514b"
    ],
    "name:zho_x_preferred":[
        "\u5b5f\u514b"
    ],
    "wof:name":"Mengke",
    "wof:placetype":"locality"
},
  "geometry": {"coordinates":[120.46708,41.60505],"type":"Point"}
}