{
  "type": "Feature",
  "properties": {
    "gn:admin1_code":"29.0",
    "gn:asciiname":"Dalishu",
    "gn:country_code":"CN",
    "gn:dem":1990,
    "gn:feature_class":"P",
    "gn:feature_code":"PPL",
    "gn:name":"Dalishu",
    "gn:population":0,
    "gn:timezone":"Asia/Shanghai",
    "iso:country":"CN",
    "name:zho_x_preferred":[
        "\u5927\u68a8\u6811"
    ],
    "wof:name":"Dalishu",
    "wof:placetype":"locality"
},
  "geometry": {"coordinates":[99.73009999999999,24.8429],"type":"Point"}
}