{
  "type": "Feature",
  "properties": {
    "gn:admin1_code":"8.0",
    "gn:asciiname":"Yongchangcun",
    "gn:country_code":"CN",
    "gn:dem":119,
    "gn:feature_class":"P",
    "gn:feature_code":"PPL",
    "gn:name":"Yongchangcun",
    "gn:population":0,
    "gn:timezone":"Asia/Shanghai",
    "iso:country":"CN",
    "name:zho_x_preferred":[
        "\u6c38\u660c\u6751"
    ],
    "wof:name":"Yongchangcun",
    "wof:placetype":"locality"
},
  "geometry": {"coordinates":[130.23883999999998,47.1339],"type":"Point"}
}