{
  "type": "Feature",
  "properties": {
    "gn:admin1_code":"18",
    "gn:asciiname":"Shizitai",
    "gn:country_code":"CN",
    "gn:dem":1279,
    "gn:feature_class":"P",
    "gn:feature_code":"PPL",
    "gn:name":"Shizitai",
    "gn:population":0,
    "gn:timezone":"Asia/Shanghai",
    "iso:country":"CN",
    "name:zho_x_preferred":[
        "\u72ee\u5b50\u53f0"
    ],
    "wof:name":"Shizitai",
    "wof:placetype":"locality"
},
  "geometry": {"coordinates":[107.124,28.8815],"type":"Point"}
}