{
  "type": "Feature",
  "properties": {
    "gn:admin1_code":"24.0",
    "gn:asciiname":"Yadixia",
    "gn:country_code":"CN",
    "gn:dem":362,
    "gn:feature_class":"P",
    "gn:feature_code":"PPL",
    "gn:name":"Yadixia",
    "gn:population":0,
    "gn:timezone":"Asia/Shanghai",
    "iso:country":"CN",
    "name:zho_x_preferred":[
        "\u5d16\u5e95\u4e0b"
    ],
    "wof:name":"Yadixia",
    "wof:placetype":"locality"
},
  "geometry": {"coordinates":[111.45422000000001,34.83784],"type":"Point"}
}