{
  "type": "Feature",
  "properties": {
    "gn:admin1_code":"19.0",
    "gn:asciiname":"Langjiachang",
    "gn:country_code":"CN",
    "gn:dem":19,
    "gn:feature_class":"P",
    "gn:feature_code":"PPL",
    "gn:name":"Langjiachang",
    "gn:population":0,
    "gn:timezone":"Asia/Shanghai",
    "iso:country":"CN",
    "name:und_x_variant":[
        "\u90ce\u5bb6\u5382"
    ],
    "name:zho_x_preferred":[
        "\u90ce\u5bb6\u5382"
    ],
    "wof:name":"Langjiachang",
    "wof:placetype":"locality"
},
  "geometry": {"coordinates":[122.94087,41.1853],"type":"Point"}
}