{
  "type": "Feature",
  "properties": {
    "gn:admin1_code":"26.0",
    "gn:asciiname":"Yulong",
    "gn:country_code":"CN",
    "gn:dem":677,
    "gn:feature_class":"P",
    "gn:feature_code":"PPL",
    "gn:name":"Yulong",
    "gn:population":0,
    "gn:timezone":"Asia/Shanghai",
    "iso:country":"CN",
    "name:und_x_variant":[
        "\u9c7c\u9f99"
    ],
    "wof:name":"Yulong",
    "wof:placetype":"locality"
},
  "geometry": {"coordinates":[107.56601999999999,34.23777],"type":"Point"}
}