{
  "type": "Feature",
  "properties": {
    "gn:admin1_code":"2.0",
    "gn:asciiname":"Tongling",
    "gn:country_code":"CN",
    "gn:dem":83,
    "gn:feature_class":"P",
    "gn:feature_code":"PPL",
    "gn:name":"Tongling",
    "gn:population":0,
    "gn:timezone":"Asia/Shanghai",
    "iso:country":"CN",
    "name:und_x_variant":[
        "\u94dc\u5cad"
    ],
    "wof:name":"Tongling",
    "wof:placetype":"locality"
},
  "geometry": {"coordinates":[121.3108,30.05156],"type":"Point"}
}