{
  "type": "Feature",
  "properties": {
    "gn:admin1_code":"3.0",
    "gn:asciiname":"Jinzhuwo",
    "gn:country_code":"CN",
    "gn:dem":205,
    "gn:feature_class":"P",
    "gn:feature_code":"PPL",
    "gn:name":"Jinzhuwo",
    "gn:population":0,
    "gn:timezone":"Asia/Shanghai",
    "iso:country":"CN",
    "name:und_x_variant":[
        "\u91d1\u7af9\u7a9d"
    ],
    "wof:name":"Jinzhuwo",
    "wof:placetype":"locality"
},
  "geometry": {"coordinates":[115.88784,25.84215],"type":"Point"}
}