{
  "type": "Feature",
  "properties": {
    "gn:admin1_code":"2.0",
    "gn:asciiname":"Aokou",
    "gn:country_code":"CN",
    "gn:dem":19,
    "gn:feature_class":"P",
    "gn:feature_code":"PPL",
    "gn:name":"Aokou",
    "gn:population":0,
    "gn:timezone":"Asia/Shanghai",
    "iso:country":"CN",
    "name:zho_x_preferred":[
        "\u5c99\u53e3"
    ],
    "wof:name":"Aokou",
    "wof:placetype":"locality"
},
  "geometry": {"coordinates":[122.24323,29.77281],"type":"Point"}
}