{
  "type": "Feature",
  "properties": {
    "gn:admin1_code":"9.0",
    "gn:asciiname":"Zhujialou",
    "gn:country_code":"CN",
    "gn:dem":47,
    "gn:feature_class":"P",
    "gn:feature_code":"PPL",
    "gn:name":"Zhujialou",
    "gn:population":0,
    "gn:timezone":"Asia/Shanghai",
    "iso:country":"CN",
    "name:zho_x_preferred":[
        "\u795d\u5bb6\u697c"
    ],
    "wof:name":"Zhujialou",
    "wof:placetype":"locality"
},
  "geometry": {"coordinates":[115.81031000000002,32.00178],"type":"Point"}
}