{
  "type": "Feature",
  "properties": {
    "gn:admin1_code":"26.0",
    "gn:asciiname":"Tongmugoucun",
    "gn:country_code":"CN",
    "gn:dem":817,
    "gn:feature_class":"P",
    "gn:feature_code":"PPL",
    "gn:name":"Tongmugoucun",
    "gn:population":0,
    "gn:timezone":"Asia/Shanghai",
    "iso:country":"CN",
    "name:zho_x_preferred":[
        "\u6850\u6728\u6c9f\u6751"
    ],
    "wof:name":"Tongmugoucun",
    "wof:placetype":"locality"
},
  "geometry": {"coordinates":[110.0093,33.79],"type":"Point"}
}