{
  "type": "Feature",
  "properties": {
    "gn:admin1_code":"8.0",
    "gn:asciiname":"Yangfuqiang",
    "gn:country_code":"CN",
    "gn:dem":120,
    "gn:feature_class":"P",
    "gn:feature_code":"PPL",
    "gn:name":"Yangfuqiang",
    "gn:population":0,
    "gn:timezone":"Asia/Shanghai",
    "iso:country":"CN",
    "name:zho_x_preferred":[
        "\u6d0b\u8179\u8154"
    ],
    "wof:name":"Yangfuqiang",
    "wof:placetype":"locality"
},
  "geometry": {"coordinates":[126.32904000000001,45.74047],"type":"Point"}
}