{
  "type": "Feature",
  "properties": {
    "gn:admin1_code":"19.0",
    "gn:asciiname":"Daizigou",
    "gn:country_code":"CN",
    "gn:dem":75,
    "gn:feature_class":"P",
    "gn:feature_code":"PPL",
    "gn:name":"Daizigou",
    "gn:population":0,
    "gn:timezone":"Asia/Shanghai",
    "iso:country":"CN",
    "name:zho_x_preferred":[
        "\u5e26\u5b50\u6c9f"
    ],
    "wof:name":"Daizigou",
    "wof:placetype":"locality"
},
  "geometry": {"coordinates":[121.681,39.7483],"type":"Point"}
}