{
  "type": "Feature",
  "properties": {
    "gn:admin1_code":"7.0",
    "gn:asciiname":"Chaoshan",
    "gn:country_code":"CN",
    "gn:dem":611,
    "gn:feature_class":"P",
    "gn:feature_code":"PPL",
    "gn:name":"Chaoshan",
    "gn:population":0,
    "gn:timezone":"Asia/Shanghai",
    "iso:country":"CN",
    "name:fra_x_preferred":[
        "Chaoshan"
    ],
    "name:ind_x_preferred":[
        "Chaoshan"
    ],
    "name:ita_x_preferred":[
        "Chaoshan"
    ],
    "name:nld_x_preferred":[
        "Chaoshan"
    ],
    "name:nor_x_preferred":[
        "Chaoshan"
    ],
    "name:pol_x_preferred":[
        "Chaoshan"
    ],
    "name:zho_x_preferred":[
        "\u671d\u5c71"
    ],
    "name:zho_x_variant":[
        "\u6f6e\u6c55\u5730\u5340"
    ],
    "wof:name":"Chaoshan",
    "wof:placetype":"locality"
},
  "geometry": {"coordinates":[116.1778,25.26205],"type":"Point"}
}