{
  "type": "Feature",
  "properties": {
    "gn:country":"CN",
    "gn:fcode":"PPL",
    "gn:pop":1295,
    "iso:country":"CN",
    "name:cym_x_preferred":[
        "Ardal Baodi"
    ],
    "name:deu_x_preferred":[
        "Baodi"
    ],
    "name:eng_x_preferred":[
        "Baodi District"
    ],
    "name:eus_x_preferred":[
        "Baodi Barrutia"
    ],
    "name:gan_x_preferred":[
        "\u5b9d\u577b\u533a"
    ],
    "name:jpn_x_preferred":[
        "\u5b9d\u30c6\u30a4\u533a"
    ],
    "name:kor_x_preferred":[
        "\ubc14\uc624\ub514\uad6c"
    ],
    "name:nan_x_preferred":[
        "P\u00f3-t\u00ee-khu"
    ],
    "name:nld_x_preferred":[
        "Baodi District"
    ],
    "name:nob_x_preferred":[
        "Baodi"
    ],
    "name:rus_x_preferred":[
        "\u0411\u0430\u043e\u0434\u0438"
    ],
    "name:swe_x_preferred":[
        "Baodi"
    ],
    "name:unk_x_variant":[
        "Ta-pai-chuang"
    ],
    "name:urd_x_preferred":[
        "\u0628\u0627\u0648\u062f\u06cc \u0636\u0644\u0639"
    ],
    "name:vie_x_preferred":[
        "B\u1ea3o Tr\u00ec"
    ],
    "name:wuu_x_preferred":[
        "\u5b9d\u577b\u533a"
    ],
    "name:zho_x_preferred":[
        "\u5b9d\u577b\u533a"
    ],
    "qs:name":"Dabaizhuang",
    "qs:photos_9r":0,
    "qs:photos_sr":0,
    "qs:pop_sr":"3",
    "wd:wordcount":192,
    "wof:name":"Dabaizhuang",
    "wof:placetype":"locality",
    "wof:population":1295
},
  "geometry": {"coordinates":[117.38028,39.44472],"type":"Point"}
}