{
  "type": "Feature",
  "properties": {
    "gn:country":"CN",
    "gn:fcode":"PPL",
    "gn:pop":1295,
    "iso:country":"CN",
    "name:unk_x_variant":[
        "Ta-pai-chuang"
    ],
    "qs:name":"Dabaizhuang",
    "qs:photos_9r":0,
    "qs:photos_sr":0,
    "qs:pop_sr":"3",
    "wd:wordcount":192,
    "wof:name":"Dabaizhuang",
    "wof:placetype":"locality",
    "wof:population":1295
},
  "geometry": {"coordinates":[117.38028,39.44472],"type":"Point"}
}