{
  "type": "Feature",
  "properties": {
    "gn:admin1_code":"20.0",
    "gn:asciiname":"Shijing Sidui",
    "gn:country_code":"CN",
    "gn:dem":341,
    "gn:feature_class":"P",
    "gn:feature_code":"PPLF",
    "gn:name":"Shijing Sidui",
    "gn:population":0,
    "gn:timezone":"Asia/Shanghai",
    "iso:country":"CN",
    "name:zho_x_preferred":[
        "\u77f3\u4e95\u56db\u961f"
    ],
    "wof:name":"Shijing Sidui",
    "wof:placetype":"locality"
},
  "geometry": {"coordinates":[123.35303999999999,48.67115],"type":"Point"}
}