{
  "type": "Feature",
  "properties": {
    "gn:admin1_code":"12.0",
    "gn:asciiname":"Renjiagou",
    "gn:country_code":"CN",
    "gn:dem":362,
    "gn:feature_class":"P",
    "gn:feature_code":"PPL",
    "gn:name":"Renjiagou",
    "gn:population":0,
    "gn:timezone":"Asia/Shanghai",
    "iso:country":"CN",
    "name:zho_x_preferred":[
        "\u4efb\u5bb6\u6c9f"
    ],
    "wof:name":"Renjiagou",
    "wof:placetype":"locality"
},
  "geometry": {"coordinates":[110.41759,32.8914],"type":"Point"}
}