{
  "type": "Feature",
  "properties": {
    "gn:admin1_code":"6.0",
    "gn:asciiname":"Qiecha",
    "gn:country_code":"CN",
    "gn:dem":3208,
    "gn:feature_class":"P",
    "gn:feature_code":"PPLA4",
    "gn:name":"Qiecha",
    "gn:population":0,
    "gn:timezone":"Asia/Shanghai",
    "iso:country":"CN",
    "name:und_x_variant":[
        "\u5207\u67e5",
        "Shinaihai Xiang",
        "\u77f3\u4e43\u4ea5\u4e61"
    ],
    "wof:name":"Qiecha",
    "wof:placetype":"locality"
},
  "geometry": {"coordinates":[99.59859,36.99512],"type":"Point"}
}