{
  "type": "Feature",
  "properties": {
    "gn:admin1_code":"14.0",
    "gn:asciiname":"Geqingka",
    "gn:country_code":"CN",
    "gn:dem":4140,
    "gn:feature_class":"P",
    "gn:feature_code":"PPL",
    "gn:name":"Geqingka",
    "gn:population":0,
    "gn:timezone":"Asia/Urumqi",
    "iso:country":"CN",
    "name:zho_x_preferred":[
        "\u683c\u9752\u5361"
    ],
    "wof:name":"Geqingka",
    "wof:placetype":"locality"
},
  "geometry": {"coordinates":[95.60380000000001,31.50807],"type":"Point"}
}