{
  "type": "Feature",
  "properties": {
    "gn:admin1_code":"14.0",
    "gn:asciiname":"Damoge",
    "gn:country_code":"CN",
    "gn:dem":3955,
    "gn:feature_class":"P",
    "gn:feature_code":"PPL",
    "gn:name":"Damoge",
    "gn:population":0,
    "gn:timezone":"Asia/Urumqi",
    "iso:country":"CN",
    "name:zho_x_preferred":[
        "\u8fbe\u78e8\u54e5"
    ],
    "wof:name":"Damoge",
    "wof:placetype":"locality"
},
  "geometry": {"coordinates":[93.93000000000001,30.19495],"type":"Point"}
}