{
  "type": "Feature",
  "properties": {
    "gn:admin1_code":"29.0",
    "gn:asciiname":"Dacaoba",
    "gn:country_code":"CN",
    "gn:dem":1238,
    "gn:feature_class":"P",
    "gn:feature_code":"PPL",
    "gn:name":"Dacaoba",
    "gn:population":0,
    "gn:timezone":"Asia/Shanghai",
    "iso:country":"CN",
    "name:zho_x_preferred":[
        "\u5927\u8349\u575d"
    ],
    "wof:name":"Dacaoba",
    "wof:placetype":"locality"
},
  "geometry": {"coordinates":[101.161,23.6459],"type":"Point"}
}