{
  "type": "Feature",
  "properties": {
    "gn:admin1_code":"3.0",
    "gn:asciiname":"Jiantou",
    "gn:country_code":"CN",
    "gn:dem":101,
    "gn:feature_class":"P",
    "gn:feature_code":"PPL",
    "gn:name":"Jiantou",
    "gn:population":0,
    "gn:timezone":"Asia/Shanghai",
    "iso:country":"CN",
    "name:und_x_variant":[
        "\u67a7\u5934"
    ],
    "wof:name":"Jiantou",
    "wof:placetype":"locality"
},
  "geometry": {"coordinates":[114.61084,28.10227],"type":"Point"}
}