{
  "type": "Feature",
  "properties": {
    "gn:admin1_code":"6.0",
    "gn:asciiname":"Chahan Taolegai",
    "gn:country_code":"CN",
    "gn:dem":3204,
    "gn:feature_class":"P",
    "gn:feature_code":"PPL",
    "gn:name":"Chahan Taolegai",
    "gn:population":0,
    "gn:timezone":"Asia/Urumqi",
    "iso:country":"CN",
    "name:zho_x_preferred":[
        "\u5bdf\u6c57\u9676\u52d2\u76d6"
    ],
    "wof:name":"Chahan Taolegai",
    "wof:placetype":"locality"
},
  "geometry": {"coordinates":[98.00922,36.04985],"type":"Point"}
}