{
  "type": "Feature",
  "properties": {
    "gn:admin1_code":"29.0",
    "gn:asciiname":"Nuogutian",
    "gn:country_code":"CN",
    "gn:dem":1569,
    "gn:feature_class":"P",
    "gn:feature_code":"PPL",
    "gn:name":"Nuogutian",
    "gn:population":0,
    "gn:timezone":"Asia/Shanghai",
    "iso:country":"CN",
    "name:zho_x_preferred":[
        "\u7cef\u8c37\u7530"
    ],
    "wof:name":"Nuogutian",
    "wof:placetype":"locality"
},
  "geometry": {"coordinates":[101.173,26.6455],"type":"Point"}
}