{
  "type": "Feature",
  "properties": {
    "gn:admin1_code":"29.0",
    "gn:asciiname":"Dashui",
    "gn:country_code":"CN",
    "gn:dem":2693,
    "gn:feature_class":"P",
    "gn:feature_code":"PPL",
    "gn:name":"Dashui",
    "gn:population":0,
    "gn:timezone":"Asia/Shanghai",
    "iso:country":"CN",
    "name:und_x_variant":[
        "\u5927\u6c34"
    ],
    "wof:name":"Dashui",
    "wof:placetype":"locality"
},
  "geometry": {"coordinates":[103.36450000000001,26.04803],"type":"Point"}
}