{
  "type": "Feature",
  "properties": {
    "gn:admin1_code":"9.0",
    "gn:asciiname":"Dongshima",
    "gn:country_code":"CN",
    "gn:dem":108,
    "gn:feature_class":"P",
    "gn:feature_code":"PPL",
    "gn:name":"Dongshima",
    "gn:population":0,
    "gn:timezone":"Asia/Shanghai",
    "iso:country":"CN",
    "name:zho_x_preferred":[
        "\u4e1c\u53f2\u9a6c"
    ],
    "wof:name":"Dongshima",
    "wof:placetype":"locality"
},
  "geometry": {"coordinates":[113.55412,34.83127],"type":"Point"}
}