{
  "type": "Feature",
  "properties": {
    "gn:admin1_code":"14.0",
    "gn:asciiname":"Jiangdun",
    "gn:country_code":"CN",
    "gn:dem":3787,
    "gn:feature_class":"P",
    "gn:feature_code":"PPL",
    "gn:name":"Jiangdun",
    "gn:population":0,
    "gn:timezone":"Asia/Urumqi",
    "iso:country":"CN",
    "name:zho_x_preferred":[
        "\u6c5f\u6566"
    ],
    "wof:name":"Jiangdun",
    "wof:placetype":"locality"
},
  "geometry": {"coordinates":[98.95959000000001,29.00621],"type":"Point"}
}