{
  "type": "Feature",
  "properties": {
    "gn:country":"CN",
    "gn:fcode":"ADM3",
    "gn:pop":0,
    "iso:country":"CN",
    "name:unk_x_variant":[
        "T\u2019eng-ch\u2019ung Hsien"
    ],
    "name:zho_x_preferred":[
        "\u817e\u51b2\u53bf"
    ],
    "name:zho_x_variant":[
        "\u817e\u51b2"
    ],
    "qs:name":"Tengchong Xian",
    "qs:photos_9r":0,
    "qs:photos_sr":0,
    "qs:pop_sr":"0",
    "wof:name":"Tengchong Xian",
    "wof:placetype":"localadmin",
    "wof:population":0
},
  "geometry": {"coordinates":[98.46133,25.32508],"type":"Point"}
}