{
  "type": "Feature",
  "properties": {
    "gn:admin1_code":"10",
    "gn:asciiname":"Langkou",
    "gn:country_code":"CN",
    "gn:dem":37,
    "gn:feature_class":"P",
    "gn:feature_code":"PPL",
    "gn:name":"Langkou",
    "gn:population":0,
    "gn:timezone":"Asia/Shanghai",
    "iso:country":"CN",
    "name:zho_x_preferred":[
        "\u6717\u53e3"
    ],
    "wof:name":"Langkou",
    "wof:placetype":"locality"
},
  "geometry": {"coordinates":[115.155,37.7701],"type":"Point"}
}