{
  "type": "Feature",
  "properties": {
    "gn:admin1_code":"7",
    "gn:asciiname":"Pingkeng",
    "gn:country_code":"CN",
    "gn:dem":533,
    "gn:feature_class":"P",
    "gn:feature_code":"PPL",
    "gn:name":"Pingkeng",
    "gn:population":0,
    "gn:timezone":"Asia/Shanghai",
    "iso:country":"CN",
    "name:und_x_variant":[
        "\u576a\u5751",
        "Pingkeng"
    ],
    "wof:name":"Pingkeng",
    "wof:placetype":"locality"
},
  "geometry": {"coordinates":[119.87124,27.14623],"type":"Point"}
}