{
  "type": "Feature",
  "properties": {
    "gn:admin1_code":"11.0",
    "gn:asciiname":"Xiageng",
    "gn:country_code":"CN",
    "gn:dem":1154,
    "gn:feature_class":"P",
    "gn:feature_code":"PPL",
    "gn:name":"Xiageng",
    "gn:population":0,
    "gn:timezone":"Asia/Shanghai",
    "iso:country":"CN",
    "name:zho_x_preferred":[
        "\u4e0b\u57c2"
    ],
    "wof:name":"Xiageng",
    "wof:placetype":"locality"
},
  "geometry": {"coordinates":[114.00091999999999,26.17326],"type":"Point"}
}