{
  "type": "Feature",
  "properties": {
    "gn:admin1_code":"12.0",
    "gn:asciiname":"Liushen",
    "gn:country_code":"CN",
    "gn:dem":23,
    "gn:feature_class":"P",
    "gn:feature_code":"PPL",
    "gn:name":"Liushen",
    "gn:population":0,
    "gn:timezone":"Asia/Shanghai",
    "iso:country":"CN",
    "name:zho_x_preferred":[
        "Liushen"
    ],
    "name:zho_x_variant":[
        "\u516d\u795e"
    ],
    "wof:name":"Liushen",
    "wof:placetype":"locality"
},
  "geometry": {"coordinates":[115.20068000000001,30.39022000000001],"type":"Point"}
}