{
  "type": "Feature",
  "properties": {
    "gn:admin1_code":"26.0",
    "gn:asciiname":"Shatangshu",
    "gn:country_code":"CN",
    "gn:dem":784,
    "gn:feature_class":"P",
    "gn:feature_code":"PPL",
    "gn:name":"Shatangshu",
    "gn:population":0,
    "gn:timezone":"Asia/Shanghai",
    "iso:country":"CN",
    "name:und_x_variant":[
        "\u6c99\u68e0\u6811"
    ],
    "wof:name":"Shatangshu",
    "wof:placetype":"locality"
},
  "geometry": {"coordinates":[106.34692,33.0821],"type":"Point"}
}