{
  "type": "Feature",
  "properties": {
    "gn:admin1_code":"30.0",
    "gn:asciiname":"Lingbian",
    "gn:country_code":"CN",
    "gn:dem":64,
    "gn:feature_class":"P",
    "gn:feature_code":"PPL",
    "gn:name":"Lingbian",
    "gn:population":0,
    "gn:timezone":"Asia/Shanghai",
    "iso:country":"CN",
    "name:zho_x_preferred":[
        "\u5cad\u8fb9"
    ],
    "wof:name":"Lingbian",
    "wof:placetype":"locality"
},
  "geometry": {"coordinates":[113.10167,24.23694],"type":"Point"}
}