{
  "type": "Feature",
  "properties": {
    "gn:admin1_code":"13.0",
    "gn:asciiname":"Dunmaili",
    "gn:country_code":"CN",
    "gn:dem":922,
    "gn:feature_class":"P",
    "gn:feature_code":"PPL",
    "gn:name":"Dunmaili",
    "gn:population":0,
    "gn:timezone":"Asia/Urumqi",
    "iso:country":"CN",
    "name:zho_x_preferred":[
        "\u58a9\u4e70\u91cc"
    ],
    "wof:name":"Dunmaili",
    "wof:placetype":"locality"
},
  "geometry": {"coordinates":[84.69125,41.16818],"type":"Point"}
}