{
  "type": "Feature",
  "properties": {
    "gn:admin1_code":"30.0",
    "gn:asciiname":"Xianrenzhang",
    "gn:country_code":"CN",
    "gn:dem":478,
    "gn:feature_class":"P",
    "gn:feature_code":"PPL",
    "gn:name":"Xianrenzhang",
    "gn:population":0,
    "gn:timezone":"Asia/Shanghai",
    "iso:country":"CN",
    "name:zho_x_preferred":[
        "Xianrenzhang"
    ],
    "name:zho_x_variant":[
        "\u4ed9\u4eba\u969c"
    ],
    "wof:name":"Xianrenzhang",
    "wof:placetype":"locality"
},
  "geometry": {"coordinates":[114.25679,24.53922],"type":"Point"}
}