{
  "type": "Feature",
  "properties": {
    "gn:admin1_code":"15.0",
    "gn:asciiname":"Bojiwan",
    "gn:country_code":"CN",
    "gn:dem":2437,
    "gn:feature_class":"P",
    "gn:feature_code":"PPL",
    "gn:name":"Bojiwan",
    "gn:population":0,
    "gn:timezone":"Asia/Shanghai",
    "iso:country":"CN",
    "name:zho_x_preferred":[
        "\u7c38\u7b95\u6e7e"
    ],
    "wof:name":"Bojiwan",
    "wof:placetype":"locality"
},
  "geometry": {"coordinates":[104.13500000000001,35.3758],"type":"Point"}
}