{
  "type": "Feature",
  "properties": {
    "gn:admin1_code":"01",
    "gn:asciiname":"Sanchahe",
    "gn:cc2":"CN",
    "gn:country_code":"CN",
    "gn:dem":7,
    "gn:feature_class":"P",
    "gn:feature_code":"PPL",
    "gn:name":"Sanchahe",
    "gn:population":0,
    "gn:timezone":"Asia/Shanghai",
    "iso:country":"CN",
    "name:und_x_variant":[
        "San-ch\u2019a-ho",
        "Sanchahe"
    ],
    "wof:name":"Sanchahe",
    "wof:placetype":"locality"
},
  "geometry": {"coordinates":[117.21917000000001,31.48056],"type":"Point"}
}