{
  "type": "Feature",
  "properties": {
    "gn:admin1_code":"29.0",
    "gn:asciiname":"Xiaogoujiao",
    "gn:country_code":"CN",
    "gn:dem":1268,
    "gn:feature_class":"P",
    "gn:feature_code":"PPL",
    "gn:name":"Xiaogoujiao",
    "gn:population":0,
    "gn:timezone":"Asia/Shanghai",
    "iso:country":"CN",
    "name:zho_x_preferred":[
        "\u5c0f\u6c9f\u7ede"
    ],
    "wof:name":"Xiaogoujiao",
    "wof:placetype":"locality"
},
  "geometry": {"coordinates":[104.279,23.3118],"type":"Point"}
}