{
  "type": "Feature",
  "properties": {
    "gn:admin1_code":"22.0",
    "gn:asciiname":"Beitaizicun",
    "gn:country_code":"CN",
    "gn:dem":755,
    "gn:feature_class":"P",
    "gn:feature_code":"PPL",
    "gn:name":"Beitaizicun",
    "gn:population":0,
    "gn:timezone":"Asia/Shanghai",
    "iso:country":"CN",
    "name:zho_x_preferred":[
        "\u5317\u53f0\u5b50\u6751"
    ],
    "wof:name":"Beitaizicun",
    "wof:placetype":"locality"
},
  "geometry": {"coordinates":[116.56822,40.53413],"type":"Point"}
}