{
  "type": "Feature",
  "properties": {
    "gn:admin1_code":"08",
    "gn:asciiname":"Ma-chan-yuan",
    "gn:country_code":"CN",
    "gn:dem":152,
    "gn:feature_class":"P",
    "gn:feature_code":"PPL",
    "gn:name":"Ma-chan-y\u00fcan",
    "gn:population":0,
    "gn:timezone":"Asia/Shanghai",
    "iso:country":"CN",
    "wof:name":"Ma-chan-yuan",
    "wof:placetype":"locality"
},
  "geometry": {"coordinates":[124.66943999999999,47.27778],"type":"Point"}
}