{
  "type": "Feature",
  "properties": {
    "gn:admin1_code":"15",
    "gn:asciiname":"Wangge'ertang",
    "gn:country_code":"CN",
    "gn:dem":2704,
    "gn:feature_class":"P",
    "gn:feature_code":"PPLA4",
    "gn:name":"Wangge\u2019ertang",
    "gn:population":0,
    "gn:timezone":"Asia/Shanghai",
    "iso:country":"CN",
    "name:bod_x_preferred":[
        "\u0f56\u0f44\u0f0b\u0f42\u0f74\u0f62\u0f0b\u0f50\u0f44"
    ],
    "name:und_x_variant":[
        "Y\u00fcan-ka-t\u2019an",
        "Panggurtang",
        "Wangge\u2019ertang",
        "Ponggartang",
        "Wangge\u2019ertang Xiang",
        "\u738b\u683c\u5c14\u5858\u4e61"
    ],
    "name:zho_x_preferred":[
        "\u738b\u683c\u5c14\u5858"
    ],
    "wof:name":"Wangge'ertang",
    "wof:placetype":"locality"
},
  "geometry": {"coordinates":[102.83307000000001,35.24172],"type":"Point"}
}