{
  "type": "Feature",
  "properties": {
    "gn:admin1_code":"1.0",
    "gn:asciiname":"Liyoufangcun",
    "gn:country_code":"CN",
    "gn:dem":30,
    "gn:feature_class":"P",
    "gn:feature_code":"PPL",
    "gn:name":"Liyoufangcun",
    "gn:population":0,
    "gn:timezone":"Asia/Shanghai",
    "iso:country":"CN",
    "name:zho_x_preferred":[
        "\u674e\u6cb9\u574a\u6751"
    ],
    "wof:name":"Liyoufangcun",
    "wof:placetype":"locality"
},
  "geometry": {"coordinates":[116.45117,33.28971],"type":"Point"}
}