{
  "type": "Feature",
  "properties": {
    "gn:admin1_code":"18.0",
    "gn:asciiname":"Jiufeng",
    "gn:country_code":"CN",
    "gn:dem":1532,
    "gn:feature_class":"P",
    "gn:feature_code":"PPL",
    "gn:name":"Jiufeng",
    "gn:population":0,
    "gn:timezone":"Asia/Shanghai",
    "iso:country":"CN",
    "wof:name":"Jiufeng",
    "wof:placetype":"locality"
},
  "geometry": {"coordinates":[104.90000000000001,25.775],"type":"Point"}
}