{
  "type": "Feature",
  "properties": {
    "gn:admin1_code":"11.0",
    "gn:asciiname":"Gongjiatai",
    "gn:country_code":"CN",
    "gn:dem":35,
    "gn:feature_class":"P",
    "gn:feature_code":"PPL",
    "gn:name":"Gongjiatai",
    "gn:population":0,
    "gn:timezone":"Asia/Shanghai",
    "iso:country":"CN",
    "name:zho_x_preferred":[
        "Gongjiatai"
    ],
    "name:zho_x_variant":[
        "\u9f9a\u5bb6\u53f0"
    ],
    "wof:name":"Gongjiatai",
    "wof:placetype":"locality"
},
  "geometry": {"coordinates":[111.82598,29.70434],"type":"Point"}
}