{
  "type": "Feature",
  "properties": {
    "gn:admin1_code":"31",
    "gn:asciiname":"Gutiao",
    "gn:cc2":"CN",
    "gn:country_code":"CN",
    "gn:dem":7,
    "gn:feature_class":"P",
    "gn:feature_code":"PPL",
    "gn:name":"Gutiao",
    "gn:population":0,
    "gn:timezone":"Asia/Shanghai",
    "iso:country":"CN",
    "name:und_x_variant":[
        "Ku-t\u2019iao-ts\u2019un",
        "Gutiao"
    ],
    "wof:name":"Gutiao",
    "wof:placetype":"locality"
},
  "geometry": {"coordinates":[110.495,19.18222],"type":"Point"}
}