{
  "type": "Feature",
  "properties": {
    "gn:admin1_code":"15.0",
    "gn:asciiname":"Mananzhuang",
    "gn:country_code":"CN",
    "gn:dem":1356,
    "gn:feature_class":"P",
    "gn:feature_code":"PPL",
    "gn:name":"Mananzhuang",
    "gn:population":0,
    "gn:timezone":"Asia/Shanghai",
    "iso:country":"CN",
    "name:zho_x_preferred":[
        "\u9a6c\u5357\u5e84"
    ],
    "wof:name":"Mananzhuang",
    "wof:placetype":"locality"
},
  "geometry": {"coordinates":[107.411,35.6922],"type":"Point"}
}