{
  "type": "Feature",
  "properties": {
    "gn:admin1_code":"32.0",
    "gn:asciiname":"Zhonglaofen",
    "gn:country_code":"CN",
    "gn:dem":892,
    "gn:feature_class":"P",
    "gn:feature_code":"PPL",
    "gn:name":"Zhonglaofen",
    "gn:population":0,
    "gn:timezone":"Asia/Shanghai",
    "iso:country":"CN",
    "name:zho_x_preferred":[
        "\u949f\u8001\u575f"
    ],
    "wof:name":"Zhonglaofen",
    "wof:placetype":"locality"
},
  "geometry": {"coordinates":[107.76300000000001,31.7388],"type":"Point"}
}