{
  "type": "Feature",
  "properties": {
    "gn:admin1_code":"3.0",
    "gn:asciiname":"Banshan",
    "gn:country_code":"CN",
    "gn:dem":471,
    "gn:feature_class":"P",
    "gn:feature_code":"PPL",
    "gn:name":"Banshan",
    "gn:population":0,
    "gn:timezone":"Asia/Shanghai",
    "iso:country":"CN",
    "name:deu_x_preferred":[
        "Banshan-Machang-Kultur"
    ],
    "name:swe_x_preferred":[
        "Banshankulturen"
    ],
    "name:ukr_x_preferred":[
        "\u0411\u0430\u043d\u044c\u0448\u0430\u043d\u044c"
    ],
    "name:und_x_variant":[
        "\u534a\u5c71"
    ],
    "name:zho_x_preferred":[
        "\u534a\u5c71\u907a\u5740"
    ],
    "wof:name":"Banshan",
    "wof:placetype":"locality"
},
  "geometry": {"coordinates":[115.81673000000001,26.55938],"type":"Point"}
}