{
  "type": "Feature",
  "properties": {
    "gn:admin1_code":"8.0",
    "gn:asciiname":"Jiefangtun",
    "gn:country_code":"CN",
    "gn:dem":229,
    "gn:feature_class":"P",
    "gn:feature_code":"PPL",
    "gn:name":"Jiefangtun",
    "gn:population":0,
    "gn:timezone":"Asia/Shanghai",
    "iso:country":"CN",
    "name:zho_x_preferred":[
        "\u89e3\u653e\u5c6f"
    ],
    "wof:name":"Jiefangtun",
    "wof:placetype":"locality"
},
  "geometry": {"coordinates":[127.90549,45.41751],"type":"Point"}
}