{
  "type": "Feature",
  "properties": {
    "gn:admin1_code":"3.0",
    "gn:asciiname":"Dutou Shujia",
    "gn:country_code":"CN",
    "gn:dem":22,
    "gn:feature_class":"P",
    "gn:feature_code":"PPL",
    "gn:name":"Dutou Shujia",
    "gn:population":0,
    "gn:timezone":"Asia/Shanghai",
    "iso:country":"CN",
    "name:und_x_variant":[
        "\u6e21\u5934\u8212\u5bb6"
    ],
    "wof:name":"Dutou Shujia",
    "wof:placetype":"locality"
},
  "geometry": {"coordinates":[116.42406,28.73193],"type":"Point"}
}