{
  "type": "Feature",
  "properties": {
    "gn:admin1_code":"03",
    "gn:asciiname":"Shangluokeng",
    "gn:country_code":"CN",
    "gn:dem":333,
    "gn:feature_class":"P",
    "gn:feature_code":"PPL",
    "gn:name":"Shangluokeng",
    "gn:population":0,
    "gn:timezone":"Asia/Shanghai",
    "iso:country":"CN",
    "name:zho_x_preferred":[
        "\u4e0a\u7f57\u5751"
    ],
    "wof:name":"Shangluokeng",
    "wof:placetype":"locality"
},
  "geometry": {"coordinates":[115.61507,24.95973],"type":"Point"}
}