{
  "type": "Feature",
  "properties": {
    "gn:admin1_code":"24",
    "gn:asciiname":"Xuanjiata",
    "gn:cc2":"CN",
    "gn:country_code":"CN",
    "gn:dem":999,
    "gn:feature_class":"P",
    "gn:feature_code":"PPL",
    "gn:name":"Xuanjiata",
    "gn:population":0,
    "gn:timezone":"Asia/Shanghai",
    "iso:country":"CN",
    "name:und_x_variant":[
        "I-chia-ko-t\u2019a",
        "Hs\u00fcan-chia-ko-t\u2019a",
        "Hs\u00fcan-chia-t\u2019a",
        "Xuanjiata"
    ],
    "wof:name":"Xuanjiata",
    "wof:placetype":"locality"
},
  "geometry": {"coordinates":[114.10417,40.4825],"type":"Point"}
}