{
  "type": "Feature",
  "properties": {
    "gn:admin1_code":"7",
    "gn:asciiname":"Shanhou",
    "gn:country_code":"CN",
    "gn:dem":779,
    "gn:feature_class":"P",
    "gn:feature_code":"PPL",
    "gn:name":"Shanhou",
    "gn:population":0,
    "gn:timezone":"Asia/Shanghai",
    "iso:country":"CN",
    "name:und_x_variant":[
        "\u5c71\u540e",
        "Shanhou"
    ],
    "wof:name":"Shanhou",
    "wof:placetype":"locality"
},
  "geometry": {"coordinates":[119.91343000000001,27.28084],"type":"Point"}
}