{
  "type": "Feature",
  "properties": {
    "gn:admin1_code":"30.0",
    "gn:asciiname":"Hege",
    "gn:country_code":"CN",
    "gn:dem":289,
    "gn:feature_class":"P",
    "gn:feature_code":"PPL",
    "gn:name":"Hege",
    "gn:population":0,
    "gn:timezone":"Asia/Shanghai",
    "iso:country":"CN",
    "name:zho_x_preferred":[
        "Hege"
    ],
    "name:zho_x_variant":[
        "\u6cb3\u9694"
    ],
    "wof:name":"Hege",
    "wof:placetype":"locality"
},
  "geometry": {"coordinates":[114.55001,24.35066],"type":"Point"}
}