{
  "type": "Feature",
  "properties": {
    "gn:admin1_code":"31",
    "gn:asciiname":"Xiandong",
    "gn:country_code":"CN",
    "gn:dem":66,
    "gn:feature_class":"P",
    "gn:feature_code":"PPL",
    "gn:name":"Xiandong",
    "gn:population":0,
    "gn:timezone":"Asia/Shanghai",
    "iso:country":"CN",
    "name:und_x_variant":[
        "\u54b8\u4e1c"
    ],
    "wof:name":"Xiandong",
    "wof:placetype":"locality"
},
  "geometry": {"coordinates":[110.30200000000001,19.8509],"type":"Point"}
}