{
  "type": "Feature",
  "properties": {
    "gn:admin1_code":"02",
    "gn:asciiname":"Shiqiao",
    "gn:cc2":"CN",
    "gn:country_code":"CN",
    "gn:dem":5,
    "gn:feature_class":"P",
    "gn:feature_code":"PPL",
    "gn:name":"Shiqiao",
    "gn:population":0,
    "gn:timezone":"Asia/Shanghai",
    "iso:country":"CN",
    "name:ceb_x_preferred":[
        "Shiqiao"
    ],
    "name:deu_x_preferred":[
        "Shiqiao"
    ],
    "name:swe_x_preferred":[
        "Shiqiao"
    ],
    "name:und_x_variant":[
        "Shih-ch\u2019iao",
        "Shiqiao"
    ],
    "wof:name":"Shiqiao",
    "wof:placetype":"locality"
},
  "geometry": {"coordinates":[121.68000000000001,29.915],"type":"Point"}
}