{
  "type": "Feature",
  "properties": {
    "gn:admin1_code":"32",
    "gn:asciiname":"Qingfu",
    "gn:country_code":"CN",
    "gn:dem":339,
    "gn:feature_class":"P",
    "gn:feature_code":"PPLA3",
    "gn:name":"Qingfu",
    "gn:population":0,
    "gn:timezone":"Asia/Shanghai",
    "iso:country":"CN",
    "name:und_x_variant":[
        "Ch\u2019ing-fu",
        "Kingfu-hsien",
        "Ch\u2019ing-fu-hsien",
        "Qingfu"
    ],
    "name:zho_x_preferred":[
        "\u5e86\u7b26"
    ],
    "wof:name":"Qingfu",
    "wof:placetype":"locality"
},
  "geometry": {"coordinates":[104.51622,28.43701],"type":"Point"}
}