{
  "type": "Feature",
  "properties": {
    "gn:admin1_code":"16.0",
    "gn:asciiname":"Danzhuchong",
    "gn:country_code":"CN",
    "gn:dem":229,
    "gn:feature_class":"P",
    "gn:feature_code":"PPL",
    "gn:name":"Danzhuchong",
    "gn:population":0,
    "gn:timezone":"Asia/Shanghai",
    "iso:country":"CN",
    "name:zho_x_preferred":[
        "\u4e39\u7af9\u51b2"
    ],
    "wof:name":"Danzhuchong",
    "wof:placetype":"locality"
},
  "geometry": {"coordinates":[111.15300000000001,24.0919],"type":"Point"}
}