{
  "type": "Feature",
  "properties": {
    "gn:admin1_code":"2.0",
    "gn:asciiname":"Shangyuanxin",
    "gn:country_code":"CN",
    "gn:dem":190,
    "gn:feature_class":"P",
    "gn:feature_code":"PPL",
    "gn:name":"Shangyuanxin",
    "gn:population":0,
    "gn:timezone":"Asia/Shanghai",
    "iso:country":"CN",
    "name:und_x_variant":[
        "\u4e0a\u6e90\u5fc3",
        "Shangyuanxin"
    ],
    "wof:name":"Shangyuanxin",
    "wof:placetype":"locality"
},
  "geometry": {"coordinates":[119.36131,29.40899000000001],"type":"Point"}
}