{
  "type": "Feature",
  "properties": {
    "gn:admin1_code":"19.0",
    "gn:asciiname":"Changgangzicun",
    "gn:country_code":"CN",
    "gn:dem":17,
    "gn:feature_class":"P",
    "gn:feature_code":"PPL",
    "gn:name":"Changgangzicun",
    "gn:population":0,
    "gn:timezone":"Asia/Shanghai",
    "iso:country":"CN",
    "name:zho_x_preferred":[
        "\u957f\u5c97\u5b50\u6751"
    ],
    "wof:name":"Changgangzicun",
    "wof:placetype":"locality"
},
  "geometry": {"coordinates":[122.38598,41.67485],"type":"Point"}
}