{
  "type": "Feature",
  "properties": {
    "gn:admin1_code":"16.0",
    "gn:asciiname":"Changmo",
    "gn:country_code":"CN",
    "gn:dem":103,
    "gn:feature_class":"P",
    "gn:feature_code":"PPL",
    "gn:name":"Changmo",
    "gn:population":0,
    "gn:timezone":"Asia/Shanghai",
    "iso:country":"CN",
    "name:zho_x_preferred":[
        "\u957f\u6a21"
    ],
    "name:zho_x_variant":[
        "Changmo"
    ],
    "wof:name":"Changmo",
    "wof:placetype":"locality"
},
  "geometry": {"coordinates":[108.932,23.7099],"type":"Point"}
}