{
  "type": "Feature",
  "properties": {
    "gn:admin1_code":"14.0",
    "gn:asciiname":"Erjizhan",
    "gn:country_code":"CN",
    "gn:dem":3672,
    "gn:feature_class":"P",
    "gn:feature_code":"PPL",
    "gn:name":"Erjizhan",
    "gn:population":0,
    "gn:timezone":"Asia/Urumqi",
    "iso:country":"CN",
    "name:zho_x_preferred":[
        "\u4e8c\u7ea7\u7ad9"
    ],
    "wof:name":"Erjizhan",
    "wof:placetype":"locality"
},
  "geometry": {"coordinates":[91.15647,29.67813],"type":"Point"}
}