{
  "type": "Feature",
  "properties": {
    "gn:admin1_code":"30.0",
    "gn:asciiname":"Langxia",
    "gn:country_code":"CN",
    "gn:dem":11,
    "gn:feature_class":"P",
    "gn:feature_code":"PPL",
    "gn:name":"Langxia",
    "gn:population":0,
    "gn:timezone":"Asia/Shanghai",
    "iso:country":"CN",
    "name:zho_x_preferred":[
        "\u6717\u53a6"
    ],
    "wof:name":"Langxia",
    "wof:placetype":"locality"
},
  "geometry": {"coordinates":[114.08360999999999,23.03886],"type":"Point"}
}