{
  "type": "Feature",
  "properties": {
    "gn:admin1_code":"11.0",
    "gn:asciiname":"Michehu",
    "gn:country_code":"CN",
    "gn:dem":815,
    "gn:feature_class":"P",
    "gn:feature_code":"PPL",
    "gn:name":"Michehu",
    "gn:population":0,
    "gn:timezone":"Asia/Shanghai",
    "iso:country":"CN",
    "name:zho_x_preferred":[
        "\u7c73\u8f66\u6e56"
    ],
    "wof:name":"Michehu",
    "wof:placetype":"locality"
},
  "geometry": {"coordinates":[109.52285999999999,29.29253],"type":"Point"}
}