{
  "type": "Feature",
  "properties": {
    "gn:admin1_code":"19",
    "gn:asciiname":"Chung-yang-mu-hsia",
    "gn:country_code":"CN",
    "gn:dem":351,
    "gn:feature_class":"P",
    "gn:feature_code":"PPL",
    "gn:name":"Chung-yang-mu-hsia",
    "gn:population":0,
    "gn:timezone":"Asia/Shanghai",
    "iso:country":"CN",
    "wof:name":"Chung-yang-mu-hsia",
    "wof:placetype":"locality"
},
  "geometry": {"coordinates":[125.38861,41.49028],"type":"Point"}
}