{
  "type": "Feature",
  "properties": {
    "gn:admin1_code":"11",
    "gn:asciiname":"Taigushan",
    "gn:country_code":"CN",
    "gn:dem":71,
    "gn:feature_class":"P",
    "gn:feature_code":"PPL",
    "gn:name":"Taigushan",
    "gn:population":0,
    "gn:timezone":"Asia/Shanghai",
    "iso:country":"CN",
    "name:zho_x_preferred":[
        "\u592a\u53e4\u5c71"
    ],
    "wof:name":"Taigushan",
    "wof:placetype":"locality"
},
  "geometry": {"coordinates":[112.45089,26.85291],"type":"Point"}
}