{
  "type": "Feature",
  "properties": {
    "gn:admin1_code":"32.0",
    "gn:asciiname":"Zegai",
    "gn:country_code":"CN",
    "gn:dem":2429,
    "gn:feature_class":"P",
    "gn:feature_code":"PPL",
    "gn:name":"Zegai",
    "gn:population":0,
    "gn:timezone":"Asia/Shanghai",
    "iso:country":"CN",
    "name:zho_x_preferred":[
        "\u6cfd\u76d6"
    ],
    "wof:name":"Zegai",
    "wof:placetype":"locality"
},
  "geometry": {"coordinates":[102.973,32.0951],"type":"Point"}
}