{
  "type": "Feature",
  "properties": {
    "gn:admin1_code":"16.0",
    "gn:asciiname":"Huangling",
    "gn:country_code":"CN",
    "gn:dem":72,
    "gn:feature_class":"P",
    "gn:feature_code":"PPL",
    "gn:name":"Huangling",
    "gn:population":0,
    "gn:timezone":"Asia/Shanghai",
    "iso:country":"CN",
    "name:zho_x_preferred":[
        "\u968d\u5cad"
    ],
    "wof:name":"Huangling",
    "wof:placetype":"locality"
},
  "geometry": {"coordinates":[109.211,22.3307],"type":"Point"}
}