{
  "type": "Feature",
  "properties": {
    "gn:admin1_code":"29.0",
    "gn:asciiname":"Bulahe",
    "gn:country_code":"CN",
    "gn:dem":1118,
    "gn:feature_class":"P",
    "gn:feature_code":"PPL",
    "gn:name":"Bulahe",
    "gn:population":0,
    "gn:timezone":"Asia/Shanghai",
    "iso:country":"CN",
    "name:zho_x_preferred":[
        "\u5e03\u62c9\u6cb3"
    ],
    "wof:name":"Bulahe",
    "wof:placetype":"locality"
},
  "geometry": {"coordinates":[101.26300000000001,23.1335],"type":"Point"}
}