{
  "type": "Feature",
  "properties": {
    "gn:admin1_code":"30.0",
    "gn:asciiname":"Gangling Ercun",
    "gn:country_code":"CN",
    "gn:dem":4,
    "gn:feature_class":"P",
    "gn:feature_code":"PPL",
    "gn:name":"Gangling Ercun",
    "gn:population":0,
    "gn:timezone":"Asia/Shanghai",
    "iso:country":"CN",
    "name:zho_x_preferred":[
        "\u5ca1\u9675\u4e8c\u6751"
    ],
    "wof:name":"Gangling Ercun",
    "wof:placetype":"locality"
},
  "geometry": {"coordinates":[112.54509,22.40619],"type":"Point"}
}