{
  "type": "Feature",
  "properties": {
    "gn:admin1_code":"16.0",
    "gn:asciiname":"Yonglong",
    "gn:country_code":"CN",
    "gn:dem":49,
    "gn:feature_class":"P",
    "gn:feature_code":"PPL",
    "gn:name":"Yonglong",
    "gn:population":0,
    "gn:timezone":"Asia/Shanghai",
    "iso:country":"CN",
    "name:swe_x_preferred":[
        "Yonglong"
    ],
    "name:zho_x_preferred":[
        "\u6c38\u9686"
    ],
    "wof:name":"Yonglong",
    "wof:placetype":"locality"
},
  "geometry": {"coordinates":[110.90900000000001,23.4618],"type":"Point"}
}