{
  "type": "Feature",
  "properties": {
    "gn:admin1_code":"26.0",
    "gn:asciiname":"Luoyaocun",
    "gn:country_code":"CN",
    "gn:dem":945,
    "gn:feature_class":"P",
    "gn:feature_code":"PPL",
    "gn:name":"Luoyaocun",
    "gn:population":0,
    "gn:timezone":"Asia/Shanghai",
    "iso:country":"CN",
    "name:zho_x_preferred":[
        "\u7f57\u7a91\u6751"
    ],
    "wof:name":"Luoyaocun",
    "wof:placetype":"locality"
},
  "geometry": {"coordinates":[110.27494,34.23495],"type":"Point"}
}