{
  "type": "Feature",
  "properties": {
    "gn:admin1_code":"16.0",
    "gn:asciiname":"Ouwu",
    "gn:country_code":"CN",
    "gn:dem":50,
    "gn:feature_class":"P",
    "gn:feature_code":"PPL",
    "gn:name":"Ouwu",
    "gn:population":0,
    "gn:timezone":"Asia/Shanghai",
    "iso:country":"CN",
    "name:zho_x_preferred":[
        "\u6b27\u5c4b"
    ],
    "wof:name":"Ouwu",
    "wof:placetype":"locality"
},
  "geometry": {"coordinates":[109.361,21.6888],"type":"Point"}
}