{
  "type": "Feature",
  "properties": {
    "gn:admin1_code":"2.0",
    "gn:asciiname":"Xiehetou",
    "gn:country_code":"CN",
    "gn:dem":8,
    "gn:feature_class":"P",
    "gn:feature_code":"PPL",
    "gn:name":"Xiehetou",
    "gn:population":0,
    "gn:timezone":"Asia/Shanghai",
    "iso:country":"CN",
    "name:und_x_variant":[
        "\u659c\u6cb3\u5934"
    ],
    "wof:name":"Xiehetou",
    "wof:placetype":"locality"
},
  "geometry": {"coordinates":[120.59399999999999,30.40728],"type":"Point"}
}