{
  "type": "Feature",
  "properties": {
    "gn:admin1_code":"30",
    "gn:asciiname":"Huangshakeng",
    "gn:country_code":"CN",
    "gn:dem":369,
    "gn:feature_class":"P",
    "gn:feature_code":"PPL",
    "gn:name":"Huangshakeng",
    "gn:population":0,
    "gn:timezone":"Asia/Shanghai",
    "iso:country":"CN",
    "name:zho_x_preferred":[
        "\u9ec4\u6c99\u5751"
    ],
    "wof:name":"Huangshakeng",
    "wof:placetype":"locality"
},
  "geometry": {"coordinates":[116.16555,23.9935],"type":"Point"}
}