{
  "type": "Feature",
  "properties": {
    "gn:admin1_code":"26.0",
    "gn:asciiname":"Nianjicun",
    "gn:country_code":"CN",
    "gn:dem":904,
    "gn:feature_class":"P",
    "gn:feature_code":"PPL",
    "gn:name":"Nianjicun",
    "gn:population":0,
    "gn:timezone":"Asia/Shanghai",
    "iso:country":"CN",
    "name:zho_x_preferred":[
        "\u5ff5\u5409\u6751"
    ],
    "wof:name":"Nianjicun",
    "wof:placetype":"locality"
},
  "geometry": {"coordinates":[110.03126,35.35992],"type":"Point"}
}