{
  "type": "Feature",
  "properties": {
    "gn:admin1_code":"24.0",
    "gn:asciiname":"An'ergou",
    "gn:country_code":"CN",
    "gn:dem":1501,
    "gn:feature_class":"P",
    "gn:feature_code":"PPL",
    "gn:name":"An\u2019ergou",
    "gn:population":0,
    "gn:timezone":"Asia/Shanghai",
    "iso:country":"CN",
    "name:zho_x_preferred":[
        "An\u2019ergou"
    ],
    "name:zho_x_variant":[
        "\u5b89\u513f\u6c9f"
    ],
    "wof:name":"An'ergou",
    "wof:placetype":"locality"
},
  "geometry": {"coordinates":[112.71718,39.80049],"type":"Point"}
}