{
  "type": "Feature",
  "properties": {
    "gn:admin1_code":"16",
    "gn:asciiname":"Pantian",
    "gn:country_code":"CN",
    "gn:dem":669,
    "gn:feature_class":"P",
    "gn:feature_code":"PPL",
    "gn:name":"Pantian",
    "gn:population":0,
    "gn:timezone":"Asia/Shanghai",
    "iso:country":"CN",
    "name:zho_x_preferred":[
        "\u7554\u7530"
    ],
    "name:zho_x_variant":[
        "\u6f58\u7530\u9547"
    ],
    "wof:name":"Pantian",
    "wof:placetype":"locality"
},
  "geometry": {"coordinates":[110.705,25.1863],"type":"Point"}
}