{
  "type": "Feature",
  "properties": {
    "gn:admin1_code":"30.0",
    "gn:asciiname":"Longxingwei",
    "gn:country_code":"CN",
    "gn:dem":2,
    "gn:feature_class":"P",
    "gn:feature_code":"PPL",
    "gn:name":"Longxingwei",
    "gn:population":0,
    "gn:timezone":"Asia/Shanghai",
    "iso:country":"CN",
    "name:zho_x_preferred":[
        "\u9686\u5174\u56f4"
    ],
    "wof:name":"Longxingwei",
    "wof:placetype":"locality"
},
  "geometry": {"coordinates":[113.52024,22.6852],"type":"Point"}
}