{
  "type": "Feature",
  "properties": {
    "gn:admin1_code":"26.0",
    "gn:asciiname":"Laodaibacun",
    "gn:country_code":"CN",
    "gn:dem":692,
    "gn:feature_class":"P",
    "gn:feature_code":"PPL",
    "gn:name":"Laodaibacun",
    "gn:population":0,
    "gn:timezone":"Asia/Shanghai",
    "iso:country":"CN",
    "name:zho_x_preferred":[
        "\u8001\u4ee3\u575d\u6751"
    ],
    "wof:name":"Laodaibacun",
    "wof:placetype":"locality"
},
  "geometry": {"coordinates":[106.52412,32.98719000000001],"type":"Point"}
}