{
  "type": "Feature",
  "properties": {
    "gn:admin1_code":"2",
    "gn:asciiname":"Dashe",
    "gn:country_code":"CN",
    "gn:dem":628,
    "gn:feature_class":"P",
    "gn:feature_code":"PPLA4",
    "gn:name":"Dashe",
    "gn:population":0,
    "gn:timezone":"Asia/Shanghai",
    "iso:country":"CN",
    "name:und_x_variant":[
        "Yanjia",
        "Dashe"
    ],
    "name:zho_x_preferred":[
        "\u5927\u793e"
    ],
    "name:zho_x_variant":[
        "\u4e25\u5bb6"
    ],
    "wof:name":"Dashe",
    "wof:placetype":"locality"
},
  "geometry": {"coordinates":[118.9074,29.9079],"type":"Point"}
}