{
  "type": "Feature",
  "properties": {
    "gn:admin1_code":"15.0",
    "gn:asciiname":"Xiabaijiazui",
    "gn:country_code":"CN",
    "gn:dem":2225,
    "gn:feature_class":"P",
    "gn:feature_code":"PPL",
    "gn:name":"Xiabaijiazui",
    "gn:population":0,
    "gn:timezone":"Asia/Shanghai",
    "iso:country":"CN",
    "name:zho_x_preferred":[
        "\u4e0b\u767d\u5bb6\u5634"
    ],
    "wof:name":"Xiabaijiazui",
    "wof:placetype":"locality"
},
  "geometry": {"coordinates":[103.98699999999999,35.504],"type":"Point"}
}