{
  "type": "Feature",
  "properties": {
    "gn:admin1_code":"4.0",
    "gn:asciiname":"Jingdazhuang",
    "gn:country_code":"CN",
    "gn:dem":7,
    "gn:feature_class":"P",
    "gn:feature_code":"PPL",
    "gn:name":"Jingdazhuang",
    "gn:population":0,
    "gn:timezone":"Asia/Shanghai",
    "iso:country":"CN",
    "name:zho_x_preferred":[
        "Jingdazhuang"
    ],
    "name:zho_x_variant":[
        "\u9756\u5927\u5e84"
    ],
    "wof:name":"Jingdazhuang",
    "wof:placetype":"locality"
},
  "geometry": {"coordinates":[119.22308,33.46612],"type":"Point"}
}