{
  "type": "Feature",
  "properties": {
    "gn:admin1_code":"19.0",
    "gn:asciiname":"Nansidaogou",
    "gn:country_code":"CN",
    "gn:dem":294,
    "gn:feature_class":"P",
    "gn:feature_code":"PPL",
    "gn:name":"Nansidaogou",
    "gn:population":0,
    "gn:timezone":"Asia/Shanghai",
    "iso:country":"CN",
    "name:zho_x_preferred":[
        "\u5357\u56db\u9053\u6c9f"
    ],
    "wof:name":"Nansidaogou",
    "wof:placetype":"locality"
},
  "geometry": {"coordinates":[120.551,40.9781],"type":"Point"}
}