{
  "type": "Feature",
  "properties": {
    "gn:admin1_code":"12.0",
    "gn:asciiname":"Yaohe",
    "gn:country_code":"CN",
    "gn:dem":28,
    "gn:feature_class":"P",
    "gn:feature_code":"PPL",
    "gn:name":"Yaohe",
    "gn:population":0,
    "gn:timezone":"Asia/Shanghai",
    "iso:country":"CN",
    "name:zho_x_preferred":[
        "\u8170\u6cb3"
    ],
    "wof:name":"Yaohe",
    "wof:placetype":"locality"
},
  "geometry": {"coordinates":[112.7191,30.2978],"type":"Point"}
}