{
  "type": "Feature",
  "properties": {
    "gn:admin1_code":"32.0",
    "gn:asciiname":"Mozhi",
    "gn:country_code":"CN",
    "gn:dem":2123,
    "gn:feature_class":"P",
    "gn:feature_code":"PPL",
    "gn:name":"Mozhi",
    "gn:population":0,
    "gn:timezone":"Asia/Shanghai",
    "iso:country":"CN",
    "name:zho_x_preferred":[
        "\u83ab\u6cbb"
    ],
    "wof:name":"Mozhi",
    "wof:placetype":"locality"
},
  "geometry": {"coordinates":[102.56793999999999,27.58633],"type":"Point"}
}