{
  "type": "Feature",
  "properties": {
    "gn:admin1_code":"6.0",
    "gn:asciiname":"Ri'ala Riwa",
    "gn:country_code":"CN",
    "gn:dem":4094,
    "gn:feature_class":"P",
    "gn:feature_code":"PPL",
    "gn:name":"Ri\u2019ala Riwa",
    "gn:population":0,
    "gn:timezone":"Asia/Urumqi",
    "iso:country":"CN",
    "name:und_x_variant":[
        "Ri\u2019ala Riwa"
    ],
    "name:zho_x_preferred":[
        "\u65e5\u963f\u62c9\u65e5\u74e6"
    ],
    "wof:name":"Ri'ala Riwa",
    "wof:placetype":"locality"
},
  "geometry": {"coordinates":[96.9284,32.32013],"type":"Point"}
}