{
  "type": "Feature",
  "properties": {
    "gn:admin1_code":"18.0",
    "gn:asciiname":"Huanglagou",
    "gn:country_code":"CN",
    "gn:dem":643,
    "gn:feature_class":"P",
    "gn:feature_code":"PPL",
    "gn:name":"Huanglagou",
    "gn:population":0,
    "gn:timezone":"Asia/Shanghai",
    "iso:country":"CN",
    "name:zho_x_preferred":[
        "\u9ec4\u814a\u6c9f"
    ],
    "wof:name":"Huanglagou",
    "wof:placetype":"locality"
},
  "geometry": {"coordinates":[109.131,28.3047],"type":"Point"}
}