{
  "type": "Feature",
  "properties": {
    "gn:admin1_code":"08",
    "gn:asciiname":"Tuanjie",
    "gn:country_code":"CN",
    "gn:dem":76,
    "gn:feature_class":"P",
    "gn:feature_code":"PPLA4",
    "gn:name":"Tuanjie",
    "gn:population":0,
    "gn:timezone":"Asia/Shanghai",
    "iso:country":"CN",
    "name:und_x_variant":[
        "Tuanjie Zhen"
    ],
    "name:zho_x_preferred":[
        "\u56e2\u7ed3"
    ],
    "name:zho_x_variant":[
        "\u56e2\u7ed3\u9547"
    ],
    "wof:name":"Tuanjie",
    "wof:placetype":"locality"
},
  "geometry": {"coordinates":[130.87133,47.48446],"type":"Point"}
}