{
  "type": "Feature",
  "properties": {
    "gn:admin1_code":"24.0",
    "gn:asciiname":"Shangcaohuaping",
    "gn:country_code":"CN",
    "gn:dem":1239,
    "gn:feature_class":"P",
    "gn:feature_code":"PPL",
    "gn:name":"Shangcaohuaping",
    "gn:population":0,
    "gn:timezone":"Asia/Shanghai",
    "iso:country":"CN",
    "name:zho_x_preferred":[
        "\u4e0a\u66f9\u82b1\u576a"
    ],
    "wof:name":"Shangcaohuaping",
    "wof:placetype":"locality"
},
  "geometry": {"coordinates":[110.60945,36.24683],"type":"Point"}
}