{
  "type": "Feature",
  "properties": {
    "gn:admin1_code":"24.0",
    "gn:asciiname":"Wangkeng",
    "gn:cc2":"CN",
    "gn:country_code":"CN",
    "gn:dem":387,
    "gn:feature_class":"P",
    "gn:feature_code":"PPL",
    "gn:name":"Wangkeng",
    "gn:population":0,
    "gn:timezone":"Asia/Shanghai",
    "iso:country":"CN",
    "name:und_x_variant":[
        "Wang-chien-ts\u2019un",
        "Wangkeng"
    ],
    "wof:name":"Wangkeng",
    "wof:placetype":"locality"
},
  "geometry": {"coordinates":[110.85222,35.07611],"type":"Point"}
}