{
  "type": "Feature",
  "properties": {
    "gn:admin1_code":"3.0",
    "gn:asciiname":"Guanshan",
    "gn:country_code":"CN",
    "gn:dem":29,
    "gn:feature_class":"P",
    "gn:feature_code":"PPL",
    "gn:name":"Guanshan",
    "gn:population":0,
    "gn:timezone":"Asia/Shanghai",
    "iso:country":"CN",
    "name:und_x_variant":[
        "\u704c\u5c71"
    ],
    "wof:name":"Guanshan",
    "wof:placetype":"locality"
},
  "geometry": {"coordinates":[116.92827,28.69541],"type":"Point"}
}