{
  "type": "Feature",
  "properties": {
    "gn:admin1_code":"25.0",
    "gn:asciiname":"Wangxiaozhuangcun",
    "gn:country_code":"CN",
    "gn:dem":45,
    "gn:feature_class":"P",
    "gn:feature_code":"PPL",
    "gn:name":"Wangxiaozhuangcun",
    "gn:population":0,
    "gn:timezone":"Asia/Shanghai",
    "iso:country":"CN",
    "name:zho_x_preferred":[
        "\u738b\u5c0f\u5e84\u6751"
    ],
    "wof:name":"Wangxiaozhuangcun",
    "wof:placetype":"locality"
},
  "geometry": {"coordinates":[116.29734999999999,34.70441],"type":"Point"}
}