{
  "type": "Feature",
  "properties": {
    "gn:admin1_code":"16.0",
    "gn:asciiname":"Dongxin",
    "gn:country_code":"CN",
    "gn:dem":12,
    "gn:feature_class":"P",
    "gn:feature_code":"PPL",
    "gn:name":"Dongxin",
    "gn:population":0,
    "gn:timezone":"Asia/Shanghai",
    "iso:country":"CN",
    "name:zho_x_preferred":[
        "\u578c\u5fc3"
    ],
    "wof:name":"Dongxin",
    "wof:placetype":"locality"
},
  "geometry": {"coordinates":[109.25,21.7357],"type":"Point"}
}