{
  "type": "Feature",
  "properties": {
    "gn:admin1_code":"26.0",
    "gn:asciiname":"Shuangliushu",
    "gn:country_code":"CN",
    "gn:dem":1327,
    "gn:feature_class":"P",
    "gn:feature_code":"PPL",
    "gn:name":"Shuangliushu",
    "gn:population":0,
    "gn:timezone":"Asia/Shanghai",
    "iso:country":"CN",
    "name:zho_x_preferred":[
        "\u53cc\u67f3\u6811"
    ],
    "wof:name":"Shuangliushu",
    "wof:placetype":"locality"
},
  "geometry": {"coordinates":[109.85527,35.90752],"type":"Point"}
}