{
  "type": "Feature",
  "properties": {
    "gn:admin1_code":"16.0",
    "gn:asciiname":"Tuocong",
    "gn:country_code":"CN",
    "gn:dem":142,
    "gn:feature_class":"P",
    "gn:feature_code":"PPL",
    "gn:name":"Tuocong",
    "gn:population":0,
    "gn:timezone":"Asia/Shanghai",
    "iso:country":"CN",
    "name:zho_x_preferred":[
        "\u9a6e\u4ece"
    ],
    "wof:name":"Tuocong",
    "wof:placetype":"locality"
},
  "geometry": {"coordinates":[107.673,22.1117],"type":"Point"}
}