{
  "type": "Feature",
  "properties": {
    "gn:admin1_code":"30.0",
    "gn:asciiname":"Kengkou",
    "gn:country_code":"CN",
    "gn:dem":4,
    "gn:feature_class":"P",
    "gn:feature_code":"PPLA4",
    "gn:name":"Kengkou",
    "gn:population":0,
    "gn:timezone":"Asia/Shanghai",
    "iso:country":"CN",
    "name:und_x_variant":[
        "Kengkou Jiedao"
    ],
    "name:zho_x_preferred":[
        "\u5751\u53e3"
    ],
    "name:zho_x_variant":[
        "\u5751\u53e3\u8857\u9053"
    ],
    "wof:name":"Kengkou",
    "wof:placetype":"locality"
},
  "geometry": {"coordinates":[112.55831999999999,23.15357],"type":"Point"}
}