{
  "type": "Feature",
  "properties": {
    "gn:admin1_code":"32.0",
    "gn:asciiname":"Qie'amu",
    "gn:country_code":"CN",
    "gn:dem":2842,
    "gn:feature_class":"P",
    "gn:feature_code":"PPL",
    "gn:name":"Qie\u2019amu",
    "gn:population":0,
    "gn:timezone":"Asia/Shanghai",
    "iso:country":"CN",
    "name:und_x_variant":[
        "Qie\u2019amu"
    ],
    "name:zho_x_preferred":[
        "\u5207\u554a\u6728"
    ],
    "wof:name":"Qie'amu",
    "wof:placetype":"locality"
},
  "geometry": {"coordinates":[103.06,27.9458],"type":"Point"}
}