{
  "type": "Feature",
  "properties": {
    "gn:admin1_code":"15.0",
    "gn:asciiname":"Houjiawan",
    "gn:country_code":"CN",
    "gn:dem":2106,
    "gn:feature_class":"P",
    "gn:feature_code":"PPL",
    "gn:name":"Houjiawan",
    "gn:population":0,
    "gn:timezone":"Asia/Shanghai",
    "iso:country":"CN",
    "name:zho_x_preferred":[
        "\u4faf\u5bb6\u6e7e"
    ],
    "wof:name":"Houjiawan",
    "wof:placetype":"locality"
},
  "geometry": {"coordinates":[103.803,35.9645],"type":"Point"}
}