{
  "type": "Feature",
  "properties": {
    "gn:admin1_code":"14.0",
    "gn:asciiname":"Daide",
    "gn:country_code":"CN",
    "gn:dem":2802,
    "gn:feature_class":"P",
    "gn:feature_code":"PPL",
    "gn:name":"Daide",
    "gn:population":0,
    "gn:timezone":"Asia/Urumqi",
    "iso:country":"CN",
    "name:zho_x_preferred":[
        "\u4ee3\u5f97"
    ],
    "wof:name":"Daide",
    "wof:placetype":"locality"
},
  "geometry": {"coordinates":[98.1246,29.86912],"type":"Point"}
}