{
  "type": "Feature",
  "properties": {
    "gn:admin1_code":"32.0",
    "gn:asciiname":"Dagutan",
    "gn:country_code":"CN",
    "gn:dem":412,
    "gn:feature_class":"P",
    "gn:feature_code":"PPL",
    "gn:name":"Dagutan",
    "gn:population":0,
    "gn:timezone":"Asia/Shanghai",
    "iso:country":"CN",
    "name:zho_x_preferred":[
        "\u6253\u9f13\u6ee9"
    ],
    "wof:name":"Dagutan",
    "wof:placetype":"locality"
},
  "geometry": {"coordinates":[104.15733,29.65089],"type":"Point"}
}