{
  "type": "Feature",
  "properties": {
    "gn:admin1_code":"15.0",
    "gn:asciiname":"Hanjiawan",
    "gn:country_code":"CN",
    "gn:dem":2276,
    "gn:feature_class":"P",
    "gn:feature_code":"PPL",
    "gn:name":"Hanjiawan",
    "gn:population":0,
    "gn:timezone":"Asia/Shanghai",
    "iso:country":"CN",
    "name:zho_x_preferred":[
        "\u97e9\u5bb6\u6e7e"
    ],
    "wof:name":"Hanjiawan",
    "wof:placetype":"locality"
},
  "geometry": {"coordinates":[104.23,36.2279],"type":"Point"}
}