{
  "type": "Feature",
  "properties": {
    "gn:admin1_code":"12.0",
    "gn:asciiname":"Caofangwan",
    "gn:country_code":"CN",
    "gn:dem":30,
    "gn:feature_class":"P",
    "gn:feature_code":"PPL",
    "gn:name":"Caofangwan",
    "gn:population":0,
    "gn:timezone":"Asia/Shanghai",
    "iso:country":"CN",
    "name:zho_x_preferred":[
        "\u69fd\u574a\u6e7e"
    ],
    "wof:name":"Caofangwan",
    "wof:placetype":"locality"
},
  "geometry": {"coordinates":[112.98560999999999,30.47293],"type":"Point"}
}