{
  "type": "Feature",
  "properties": {
    "gn:admin1_code":"25.0",
    "gn:asciiname":"Xilichabu",
    "gn:country_code":"CN",
    "gn:dem":22,
    "gn:feature_class":"P",
    "gn:feature_code":"PPL",
    "gn:name":"Xilichabu",
    "gn:population":0,
    "gn:timezone":"Asia/Shanghai",
    "iso:country":"CN",
    "name:zho_x_preferred":[
        "\u897f\u5229\u67e5\u57e0"
    ],
    "wof:name":"Xilichabu",
    "wof:placetype":"locality"
},
  "geometry": {"coordinates":[122.52902,37.26363],"type":"Point"}
}