{
  "type": "Feature",
  "properties": {
    "gn:admin1_code":"20.0",
    "gn:asciiname":"Tanggongliang",
    "gn:country_code":"CN",
    "gn:dem":1485,
    "gn:feature_class":"P",
    "gn:feature_code":"PPL",
    "gn:name":"Tanggongliang",
    "gn:population":0,
    "gn:timezone":"Asia/Shanghai",
    "iso:country":"CN",
    "name:und_x_variant":[
        "\u5510\u8d21\u6881"
    ],
    "wof:name":"Tanggongliang",
    "wof:placetype":"locality"
},
  "geometry": {"coordinates":[113.12421999999999,41.89249],"type":"Point"}
}