{
  "type": "Feature",
  "properties": {
    "gn:admin1_code":"9.0",
    "gn:asciiname":"Taoyuan",
    "gn:country_code":"CN",
    "gn:dem":41,
    "gn:feature_class":"P",
    "gn:feature_code":"PPL",
    "gn:name":"Taoyuan",
    "gn:population":0,
    "gn:timezone":"Asia/Shanghai",
    "iso:country":"CN",
    "name:ceb_x_preferred":[
        "Taoyuan"
    ],
    "name:deu_x_preferred":[
        "Taoyuan"
    ],
    "name:fra_x_preferred":[
        "Taoyuan"
    ],
    "name:kor_x_preferred":[
        "\ud0c0\uc624\uc704\uc548"
    ],
    "name:lit_x_preferred":[
        "Taojuanas"
    ],
    "name:nld_x_preferred":[
        "Taoyuan"
    ],
    "name:nor_x_preferred":[
        "Taoyuan"
    ],
    "name:por_x_preferred":[
        "Taoyuan"
    ],
    "name:vie_x_preferred":[
        "\u0110\u00e0o Vi\u00ean"
    ],
    "name:zho_x_preferred":[
        "\u6843\u56ed"
    ],
    "name:zho_x_variant":[
        "\u6843\u5712"
    ],
    "wof:name":"Taoyuan",
    "wof:placetype":"locality"
},
  "geometry": {"coordinates":[115.69580000000001,32.14472],"type":"Point"}
}