{
  "type": "Feature",
  "properties": {
    "gn:admin1_code":"10.0",
    "gn:asciiname":"Wuguanzhai",
    "gn:cc2":"CN",
    "gn:country_code":"CN",
    "gn:dem":34,
    "gn:feature_class":"P",
    "gn:feature_code":"PPL",
    "gn:name":"Wuguanzhai",
    "gn:population":0,
    "gn:timezone":"Asia/Shanghai",
    "iso:country":"CN",
    "name:und_x_variant":[
        "Wu-kuan-chai",
        "Wuguanzhai"
    ],
    "wof:name":"Wuguanzhai",
    "wof:placetype":"locality"
},
  "geometry": {"coordinates":[115.86556000000002,37.2525],"type":"Point"}
}