{
  "type": "Feature",
  "properties": {
    "gn:admin1_code":"4.0",
    "gn:asciiname":"Xuri",
    "gn:country_code":"CN",
    "gn:dem":8,
    "gn:feature_class":"P",
    "gn:feature_code":"PPL",
    "gn:name":"Xuri",
    "gn:population":0,
    "gn:timezone":"Asia/Shanghai",
    "iso:country":"CN",
    "name:und_x_variant":[
        "\u65ed\u65e5"
    ],
    "wof:name":"Xuri",
    "wof:placetype":"locality"
},
  "geometry": {"coordinates":[118.90624,34.6996],"type":"Point"}
}