{
  "type": "Feature",
  "properties": {
    "gn:admin1_code":"06",
    "gn:asciiname":"Ganglong",
    "gn:country_code":"CN",
    "gn:dem":3834,
    "gn:feature_class":"P",
    "gn:feature_code":"PPLA4",
    "gn:name":"Ganglong",
    "gn:population":0,
    "gn:timezone":"Asia/Shanghai",
    "iso:country":"CN",
    "name:und_x_variant":[
        "Kanglung",
        "Ganglong Xiang",
        "Saixi Duoka"
    ],
    "name:zho_x_preferred":[
        "\u5c97\u9f99"
    ],
    "name:zho_x_variant":[
        "\u5c97\u9f99\u4e61",
        "\u8d5b\u897f\u591a\u5361"
    ],
    "wof:name":"Ganglong",
    "wof:placetype":"locality"
},
  "geometry": {"coordinates":[100.25645,33.76228],"type":"Point"}
}