{
  "type": "Feature",
  "properties": {
    "gn:admin1_code":"20.0",
    "gn:asciiname":"Yangpanwa",
    "gn:country_code":"CN",
    "gn:dem":1504,
    "gn:feature_class":"P",
    "gn:feature_code":"PPL",
    "gn:name":"Yangpanwa",
    "gn:population":0,
    "gn:timezone":"Asia/Shanghai",
    "iso:country":"CN",
    "name:und_x_variant":[
        "\u7f8a\u76d8\u6d3c"
    ],
    "wof:name":"Yangpanwa",
    "wof:placetype":"locality"
},
  "geometry": {"coordinates":[113.31274000000001,41.19137],"type":"Point"}
}