{
  "type": "Feature",
  "properties": {
    "gn:admin1_code":"3.0",
    "gn:asciiname":"Shangda Chenggang",
    "gn:country_code":"CN",
    "gn:dem":27,
    "gn:feature_class":"P",
    "gn:feature_code":"PPL",
    "gn:name":"Shangda Chenggang",
    "gn:population":0,
    "gn:timezone":"Asia/Shanghai",
    "iso:country":"CN",
    "name:und_x_variant":[
        "\u4e0a\u5927\u57ce\u5c97"
    ],
    "wof:name":"Shangda Chenggang",
    "wof:placetype":"locality"
},
  "geometry": {"coordinates":[116.23636,28.48095],"type":"Point"}
}