{
  "type": "Feature",
  "properties": {
    "gn:admin1_code":"13.0",
    "gn:asciiname":"Ganhezi",
    "gn:country_code":"CN",
    "gn:dem":935,
    "gn:feature_class":"P",
    "gn:feature_code":"PPL",
    "gn:name":"Ganhezi",
    "gn:population":0,
    "gn:timezone":"Asia/Urumqi",
    "iso:country":"CN",
    "name:und_x_variant":[
        "Kan-ho-tzu",
        "Ganhezi"
    ],
    "wof:name":"Ganhezi",
    "wof:placetype":"locality"
},
  "geometry": {"coordinates":[88.35193000000002,44.09209],"type":"Point"}
}