{
  "type": "Feature",
  "properties": {
    "gn:admin1_code":"12.0",
    "gn:asciiname":"Guanyinping",
    "gn:country_code":"CN",
    "gn:dem":378,
    "gn:feature_class":"P",
    "gn:feature_code":"PPL",
    "gn:name":"Guanyinping",
    "gn:population":0,
    "gn:timezone":"Asia/Shanghai",
    "iso:country":"CN",
    "name:zho_x_preferred":[
        "Guanyinping"
    ],
    "name:zho_x_variant":[
        "\u89c2\u97f3\u576a"
    ],
    "wof:name":"Guanyinping",
    "wof:placetype":"locality"
},
  "geometry": {"coordinates":[109.2141,29.20127],"type":"Point"}
}