{
  "type": "Feature",
  "properties": {
    "gn:admin1_code":"1.0",
    "gn:asciiname":"Xiacun",
    "gn:country_code":"CN",
    "gn:dem":68,
    "gn:feature_class":"P",
    "gn:feature_code":"PPL",
    "gn:name":"Xiacun",
    "gn:population":0,
    "gn:timezone":"Asia/Shanghai",
    "iso:country":"CN",
    "name:zho_x_preferred":[
        "\u590f\u6751"
    ],
    "wof:name":"Xiacun",
    "wof:placetype":"locality"
},
  "geometry": {"coordinates":[117.06947,29.93269],"type":"Point"}
}