{
  "type": "Feature",
  "properties": {
    "gn:admin1_code":"29.0",
    "gn:asciiname":"Yanhejie",
    "gn:country_code":"CN",
    "gn:dem":1536,
    "gn:feature_class":"P",
    "gn:feature_code":"PPL",
    "gn:name":"Yanhejie",
    "gn:population":0,
    "gn:timezone":"Asia/Shanghai",
    "iso:country":"CN",
    "wof:name":"Yanhejie",
    "wof:placetype":"locality"
},
  "geometry": {"coordinates":[102.41667,24.16667],"type":"Point"}
}