{
  "type": "Feature",
  "properties": {
    "gn:admin1_code":"8.0",
    "gn:asciiname":"Guangshengcun",
    "gn:country_code":"CN",
    "gn:dem":259,
    "gn:feature_class":"P",
    "gn:feature_code":"PPL",
    "gn:name":"Guangshengcun",
    "gn:population":0,
    "gn:timezone":"Asia/Shanghai",
    "iso:country":"CN",
    "name:zho_x_preferred":[
        "\u5e7f\u80dc\u6751"
    ],
    "wof:name":"Guangshengcun",
    "wof:placetype":"locality"
},
  "geometry": {"coordinates":[125.45593999999998,49.327],"type":"Point"}
}