{
  "type": "Feature",
  "properties": {
    "gn:admin1_code":"4.0",
    "gn:asciiname":"Shenshicun",
    "gn:country_code":"CN",
    "gn:dem":6,
    "gn:feature_class":"P",
    "gn:feature_code":"PPL",
    "gn:name":"Shenshicun",
    "gn:population":0,
    "gn:timezone":"Asia/Shanghai",
    "iso:country":"CN",
    "name:und_x_variant":[
        "Shenshi",
        "\u6c88\u5e02"
    ],
    "name:zho_x_preferred":[
        "\u6c88\u5e02\u6751"
    ],
    "wof:name":"Shenshicun",
    "wof:placetype":"locality"
},
  "geometry": {"coordinates":[120.9057,31.66229],"type":"Point"}
}