{
  "type": "Feature",
  "properties": {
    "gn:admin1_code":"15.0",
    "gn:asciiname":"Daquan",
    "gn:country_code":"CN",
    "gn:dem":1982,
    "gn:feature_class":"P",
    "gn:feature_code":"PPL",
    "gn:name":"Daquan",
    "gn:population":0,
    "gn:timezone":"Asia/Shanghai",
    "iso:country":"CN",
    "name:zho_x_preferred":[
        "\u5927\u6cc9"
    ],
    "wof:name":"Daquan",
    "wof:placetype":"locality"
},
  "geometry": {"coordinates":[100.80500000000001,39.1341],"type":"Point"}
}