{
  "type": "Feature",
  "properties": {
    "gn:admin1_code":"9.0",
    "gn:asciiname":"Shilihe",
    "gn:country_code":"CN",
    "gn:dem":113,
    "gn:feature_class":"P",
    "gn:feature_code":"PPL",
    "gn:name":"Shilihe",
    "gn:population":0,
    "gn:timezone":"Asia/Shanghai",
    "iso:country":"CN",
    "name:zho_x_preferred":[
        "\u5341\u91cc\u6cb3"
    ],
    "wof:name":"Shilihe",
    "wof:placetype":"locality"
},
  "geometry": {"coordinates":[114.05175,32.16332],"type":"Point"}
}