{
  "type": "Feature",
  "properties": {
    "gn:admin1_code":"14.0",
    "gn:asciiname":"Songgucun",
    "gn:country_code":"CN",
    "gn:dem":2796,
    "gn:feature_class":"P",
    "gn:feature_code":"PPL",
    "gn:name":"Songgucun",
    "gn:population":0,
    "gn:timezone":"Asia/Urumqi",
    "iso:country":"CN",
    "name:zho_x_preferred":[
        "\u677e\u53e4\u6751"
    ],
    "wof:name":"Songgucun",
    "wof:placetype":"locality"
},
  "geometry": {"coordinates":[97.73849,29.42355],"type":"Point"}
}