{
  "type": "Feature",
  "properties": {
    "gn:admin1_code":"12.0",
    "gn:asciiname":"Gangounao",
    "gn:country_code":"CN",
    "gn:dem":704,
    "gn:feature_class":"P",
    "gn:feature_code":"PPL",
    "gn:name":"Gangounao",
    "gn:population":0,
    "gn:timezone":"Asia/Shanghai",
    "iso:country":"CN",
    "name:zho_x_preferred":[
        "\u5e72\u6c9f\u8111"
    ],
    "wof:name":"Gangounao",
    "wof:placetype":"locality"
},
  "geometry": {"coordinates":[110.04615,33.1084],"type":"Point"}
}