{
  "type": "Feature",
  "properties": {
    "gn:admin1_code":"8.0",
    "gn:asciiname":"Erdaolinzi",
    "gn:country_code":"CN",
    "gn:dem":187,
    "gn:feature_class":"P",
    "gn:feature_code":"PPL",
    "gn:name":"Erdaolinzi",
    "gn:population":0,
    "gn:timezone":"Asia/Shanghai",
    "iso:country":"CN",
    "name:zho_x_preferred":[
        "\u4e8c\u9053\u6797\u5b50"
    ],
    "wof:name":"Erdaolinzi",
    "wof:placetype":"locality"
},
  "geometry": {"coordinates":[126.95401,45.31886],"type":"Point"}
}