{
  "type": "Feature",
  "properties": {
    "gn:country":"CN",
    "gn:fcode":"PPL",
    "gn:pop":1450,
    "iso:country":"CN",
    "name:ceb_x_preferred":[
        "Qianshan Qu"
    ],
    "name:deu_x_preferred":[
        "Qianshan"
    ],
    "name:jpn_x_preferred":[
        "\u5343\u5c71\u533a"
    ],
    "name:kor_x_preferred":[
        "\uccb8\uc0b0\uad6c"
    ],
    "name:nor_x_preferred":[
        "Qianshan"
    ],
    "name:rus_x_preferred":[
        "\u0426\u044f\u043d\u044c\u0448\u0430\u043d\u044c"
    ],
    "name:swe_x_preferred":[
        "Qianshan"
    ],
    "name:unk_x_variant":[
        "T\u2019ang-chia-fang"
    ],
    "name:vie_x_preferred":[
        "Thi\u00ean S\u01a1n"
    ],
    "name:zho_x_preferred":[
        "\u5343\u5c71\u533a"
    ],
    "qs:name":"Tangjiafang",
    "qs:photos_9r":0,
    "qs:photos_sr":0,
    "qs:pop_sr":"3",
    "wd:wordcount":114,
    "wof:name":"Tangjiafang",
    "wof:placetype":"locality",
    "wof:population":1450
},
  "geometry": {"coordinates":[110.36472000000001,26.84],"type":"Point"}
}