{
  "type": "Feature",
  "properties": {
    "gn:admin1_code":"29.0",
    "gn:asciiname":"Shitian",
    "gn:country_code":"CN",
    "gn:dem":1493,
    "gn:feature_class":"P",
    "gn:feature_code":"PPL",
    "gn:name":"Shitian",
    "gn:population":0,
    "gn:timezone":"Asia/Shanghai",
    "iso:country":"CN",
    "name:und_x_variant":[
        "\u72ee\u7530"
    ],
    "wof:name":"Shitian",
    "wof:placetype":"locality"
},
  "geometry": {"coordinates":[103.55737999999999,27.83497],"type":"Point"}
}