{
  "type": "Feature",
  "properties": {
    "gn:admin1_code":"6.0",
    "gn:asciiname":"Zongjiaxiang",
    "gn:country_code":"CN",
    "gn:dem":2789,
    "gn:feature_class":"P",
    "gn:feature_code":"PPL",
    "gn:name":"Zongjiaxiang",
    "gn:population":0,
    "gn:timezone":"Asia/Urumqi",
    "iso:country":"CN",
    "name:und_x_variant":[
        "\u5b97\u52a0\u4e61"
    ],
    "wof:name":"Zongjiaxiang",
    "wof:placetype":"locality"
},
  "geometry": {"coordinates":[96.94687999999999,36.25805],"type":"Point"}
}