{
  "type": "Feature",
  "properties": {
    "gn:admin1_code":"29.0",
    "gn:asciiname":"Dazhaguo",
    "gn:country_code":"CN",
    "gn:dem":1758,
    "gn:feature_class":"P",
    "gn:feature_code":"PPL",
    "gn:name":"Dazhaguo",
    "gn:population":0,
    "gn:timezone":"Asia/Shanghai",
    "iso:country":"CN",
    "name:zho_x_preferred":[
        "\u5927\u624e\u679c"
    ],
    "wof:name":"Dazhaguo",
    "wof:placetype":"locality"
},
  "geometry": {"coordinates":[100.889,24.5928],"type":"Point"}
}