{
  "type": "Feature",
  "properties": {
    "gn:admin1_code":"10",
    "gn:asciiname":"Shangshanqian",
    "gn:country_code":"CN",
    "gn:dem":603,
    "gn:feature_class":"P",
    "gn:feature_code":"PPL",
    "gn:name":"Shangshanqian",
    "gn:population":0,
    "gn:timezone":"Asia/Shanghai",
    "iso:country":"CN",
    "name:zho_x_preferred":[
        "\u4e0a\u5c71\u524d"
    ],
    "wof:name":"Shangshanqian",
    "wof:placetype":"locality"
},
  "geometry": {"coordinates":[117.72920000000001,41.45348],"type":"Point"}
}