{
  "type": "Feature",
  "properties": {
    "gn:admin1_code":"02",
    "gn:asciiname":"Shidi'er Nongchang",
    "gn:country_code":"CN",
    "gn:dem":4,
    "gn:feature_class":"P",
    "gn:feature_code":"PPLF",
    "gn:name":"Shidi\u2019er Nongchang",
    "gn:population":0,
    "gn:timezone":"Asia/Shanghai",
    "iso:country":"CN",
    "name:und_x_variant":[
        "Shidi\u2019er Nongchang",
        "\u5e02\u7b2c\u4e8c\u519c\u573a"
    ],
    "name:zho_x_preferred":[
        "Xiandi\u2019er Nongchang"
    ],
    "wof:name":"Shidi'er Nongchang",
    "wof:placetype":"locality"
},
  "geometry": {"coordinates":[121.52531,30.12953],"type":"Point"}
}