{
  "type": "Feature",
  "properties": {
    "gn:admin1_code":"2.0",
    "gn:asciiname":"Huolongling",
    "gn:country_code":"CN",
    "gn:dem":15,
    "gn:feature_class":"P",
    "gn:feature_code":"PPL",
    "gn:name":"Huolongling",
    "gn:population":0,
    "gn:timezone":"Asia/Shanghai",
    "iso:country":"CN",
    "name:und_x_variant":[
        "\u6d3b\u9f99\u5cad"
    ],
    "wof:name":"Huolongling",
    "wof:placetype":"locality"
},
  "geometry": {"coordinates":[119.83772999999999,30.25761],"type":"Point"}
}