{
  "type": "Feature",
  "properties": {
    "gn:admin1_code":"29.0",
    "gn:asciiname":"Wunajia",
    "gn:country_code":"CN",
    "gn:dem":1881,
    "gn:feature_class":"P",
    "gn:feature_code":"PPL",
    "gn:name":"Wunajia",
    "gn:population":0,
    "gn:timezone":"Asia/Shanghai",
    "iso:country":"CN",
    "name:zho_x_preferred":[
        "\u52a1\u90a3\u621b"
    ],
    "wof:name":"Wunajia",
    "wof:placetype":"locality"
},
  "geometry": {"coordinates":[103.616,26.0311],"type":"Point"}
}