{
  "type": "Feature",
  "properties": {
    "gn:admin1_code":"26.0",
    "gn:asciiname":"Haojia Qucha",
    "gn:country_code":"CN",
    "gn:dem":1107,
    "gn:feature_class":"P",
    "gn:feature_code":"PPL",
    "gn:name":"Haojia Qucha",
    "gn:population":0,
    "gn:timezone":"Asia/Shanghai",
    "iso:country":"CN",
    "name:zho_x_preferred":[
        "\u90dd\u5bb6\u6e20\u5c94"
    ],
    "wof:name":"Haojia Qucha",
    "wof:placetype":"locality"
},
  "geometry": {"coordinates":[110.37,39.3075],"type":"Point"}
}