{
  "type": "Feature",
  "properties": {
    "gn:admin1_code":"32.0",
    "gn:asciiname":"Dalinwan",
    "gn:country_code":"CN",
    "gn:dem":512,
    "gn:feature_class":"P",
    "gn:feature_code":"PPL",
    "gn:name":"Dalinwan",
    "gn:population":0,
    "gn:timezone":"Asia/Shanghai",
    "iso:country":"CN",
    "name:zho_x_preferred":[
        "\u5927\u6797\u6e7e"
    ],
    "wof:name":"Dalinwan",
    "wof:placetype":"locality"
},
  "geometry": {"coordinates":[104.848,31.4247],"type":"Point"}
}