{
  "type": "Feature",
  "properties": {
    "gn:admin1_code":"32.0",
    "gn:asciiname":"Chagusi",
    "gn:country_code":"CN",
    "gn:dem":3705,
    "gn:feature_class":"P",
    "gn:feature_code":"PPL",
    "gn:name":"Chagusi",
    "gn:population":0,
    "gn:timezone":"Asia/Shanghai",
    "iso:country":"CN",
    "name:zho_x_preferred":[
        "\u8336\u8c37\u5bfa"
    ],
    "wof:name":"Chagusi",
    "wof:placetype":"locality"
},
  "geometry": {"coordinates":[102.256,31.7539],"type":"Point"}
}