{
  "type": "Feature",
  "properties": {
    "gn:admin1_code":"12.0",
    "gn:asciiname":"Nanquchong",
    "gn:country_code":"CN",
    "gn:dem":86,
    "gn:feature_class":"P",
    "gn:feature_code":"PPL",
    "gn:name":"Nanquchong",
    "gn:population":0,
    "gn:timezone":"Asia/Shanghai",
    "iso:country":"CN",
    "name:zho_x_preferred":[
        "\u5357\u6e20\u51b2"
    ],
    "wof:name":"Nanquchong",
    "wof:placetype":"locality"
},
  "geometry": {"coordinates":[115.65967000000001,30.38704],"type":"Point"}
}