{
  "type": "Feature",
  "properties": {
    "gn:admin1_code":"23.0",
    "gn:asciiname":"Sizao",
    "gn:country_code":"CN",
    "gn:dem":6,
    "gn:feature_class":"P",
    "gn:feature_code":"PPL",
    "gn:name":"Sizao",
    "gn:population":0,
    "gn:timezone":"Asia/Shanghai",
    "iso:country":"CN",
    "name:und_x_variant":[
        "\u56db\u7076"
    ],
    "wof:name":"Sizao",
    "wof:placetype":"locality"
},
  "geometry": {"coordinates":[121.87607,30.97241],"type":"Point"}
}