{
  "type": "Feature",
  "properties": {
    "gn:admin1_code":"29.0",
    "gn:asciiname":"Heishuijing",
    "gn:country_code":"CN",
    "gn:dem":2197,
    "gn:feature_class":"P",
    "gn:feature_code":"PPL",
    "gn:name":"Heishuijing",
    "gn:population":0,
    "gn:timezone":"Asia/Shanghai",
    "iso:country":"CN",
    "name:zho_x_preferred":[
        "\u9ed1\u6c34\u4e95"
    ],
    "wof:name":"Heishuijing",
    "wof:placetype":"locality"
},
  "geometry": {"coordinates":[100.331,26.3639],"type":"Point"}
}