{
  "type": "Feature",
  "properties": {
    "gn:admin1_code":"3.0",
    "gn:asciiname":"Limu",
    "gn:country_code":"CN",
    "gn:dem":81,
    "gn:feature_class":"P",
    "gn:feature_code":"PPL",
    "gn:name":"Limu",
    "gn:population":0,
    "gn:timezone":"Asia/Shanghai",
    "iso:country":"CN",
    "name:deu_x_preferred":[
        "Limu"
    ],
    "name:fra_x_preferred":[
        "Limu"
    ],
    "name:hye_x_preferred":[
        "\u053c\u056b\u0574\u0578\u0582"
    ],
    "name:ton_x_preferred":[
        "Limu"
    ],
    "name:und_x_variant":[
        "\u91cc\u6728"
    ],
    "wof:name":"Limu",
    "wof:placetype":"locality"
},
  "geometry": {"coordinates":[116.80732999999999,27.78152],"type":"Point"}
}