{
  "type": "Feature",
  "properties": {
    "gn:admin1_code":"32.0",
    "gn:asciiname":"Wan'ertian",
    "gn:country_code":"CN",
    "gn:dem":892,
    "gn:feature_class":"P",
    "gn:feature_code":"PPL",
    "gn:name":"Wan\u2019ertian",
    "gn:population":0,
    "gn:timezone":"Asia/Shanghai",
    "iso:country":"CN",
    "name:und_x_variant":[
        "Wan\u2019ertian",
        "\u7897\u513f\u7530"
    ],
    "wof:name":"Wan'ertian",
    "wof:placetype":"locality"
},
  "geometry": {"coordinates":[106.17046000000001,32.07808],"type":"Point"}
}