{
  "type": "Feature",
  "properties": {
    "gn:admin1_code":"4.0",
    "gn:asciiname":"Laoyougang",
    "gn:country_code":"CN",
    "gn:dem":10,
    "gn:feature_class":"P",
    "gn:feature_code":"PPL",
    "gn:name":"Laoyougang",
    "gn:population":0,
    "gn:timezone":"Asia/Shanghai",
    "iso:country":"CN",
    "name:zho_x_preferred":[
        "\u8001\u5e7c\u5c97"
    ],
    "wof:name":"Laoyougang",
    "wof:placetype":"locality"
},
  "geometry": {"coordinates":[118.68170000000001,32.19873],"type":"Point"}
}