{
  "type": "Feature",
  "properties": {
    "gn:admin1_code":"3.0",
    "gn:asciiname":"Yuandunbei",
    "gn:country_code":"CN",
    "gn:dem":279,
    "gn:feature_class":"P",
    "gn:feature_code":"PPL",
    "gn:name":"Yuandunbei",
    "gn:population":0,
    "gn:timezone":"Asia/Shanghai",
    "iso:country":"CN",
    "name:zho_x_preferred":[
        "\u5706\u58a9\u80cc"
    ],
    "wof:name":"Yuandunbei",
    "wof:placetype":"locality"
},
  "geometry": {"coordinates":[115.6848,24.89591],"type":"Point"}
}