{
  "type": "Feature",
  "properties": {
    "gn:admin1_code":"30.0",
    "gn:asciiname":"Junmasha",
    "gn:country_code":"CN",
    "gn:dem":1,
    "gn:feature_class":"P",
    "gn:feature_code":"PPL",
    "gn:name":"Junmasha",
    "gn:population":0,
    "gn:timezone":"Asia/Shanghai",
    "iso:country":"CN",
    "name:zho_x_preferred":[
        "\u90e1\u9a6c\u6c99"
    ],
    "wof:name":"Junmasha",
    "wof:placetype":"locality"
},
  "geometry": {"coordinates":[113.18373,22.96478],"type":"Point"}
}