{
  "type": "Feature",
  "properties": {
    "gn:admin1_code":"10",
    "gn:asciiname":"Beizhengzhuang",
    "gn:country_code":"CN",
    "gn:dem":34,
    "gn:feature_class":"P",
    "gn:feature_code":"PPL",
    "gn:name":"Beizhengzhuang",
    "gn:population":0,
    "gn:timezone":"Asia/Shanghai",
    "iso:country":"CN",
    "name:zho_x_preferred":[
        "\u5317\u90d1\u5e84"
    ],
    "wof:name":"Beizhengzhuang",
    "wof:placetype":"locality"
},
  "geometry": {"coordinates":[115.5689,36.93123],"type":"Point"}
}