{
  "type": "Feature",
  "properties": {
    "gn:admin1_code":"22.0",
    "gn:asciiname":"Tuanli",
    "gn:country_code":"CN",
    "gn:dem":27,
    "gn:feature_class":"P",
    "gn:feature_code":"PPL",
    "gn:name":"Tuanli",
    "gn:population":0,
    "gn:timezone":"Asia/Shanghai",
    "iso:country":"CN",
    "name:zho_x_preferred":[
        "\u7583\u91cc"
    ],
    "wof:name":"Tuanli",
    "wof:placetype":"locality"
},
  "geometry": {"coordinates":[116.69484,39.9445],"type":"Point"}
}