{
  "type": "Feature",
  "properties": {
    "gn:admin1_code":"1.0",
    "gn:asciiname":"Jiegoucun",
    "gn:country_code":"CN",
    "gn:dem":33,
    "gn:feature_class":"P",
    "gn:feature_code":"PPL",
    "gn:name":"Jiegoucun",
    "gn:population":0,
    "gn:timezone":"Asia/Shanghai",
    "iso:country":"CN",
    "name:zho_x_preferred":[
        "\u89e3\u6c9f\u6751"
    ],
    "wof:name":"Jiegoucun",
    "wof:placetype":"locality"
},
  "geometry": {"coordinates":[116.30723999999999,33.4616],"type":"Point"}
}