{
  "type": "Feature",
  "properties": {
    "gn:admin1_code":"24.0",
    "gn:asciiname":"Lingtoucun",
    "gn:country_code":"CN",
    "gn:dem":1207,
    "gn:feature_class":"P",
    "gn:feature_code":"PPL",
    "gn:name":"Lingtoucun",
    "gn:population":0,
    "gn:timezone":"Asia/Shanghai",
    "iso:country":"CN",
    "name:zho_x_preferred":[
        "\u5cad\u5934\u6751"
    ],
    "wof:name":"Lingtoucun",
    "wof:placetype":"locality"
},
  "geometry": {"coordinates":[110.75506,36.32292],"type":"Point"}
}