{
  "type": "Feature",
  "properties": {
    "gn:admin1_code":"11",
    "gn:asciiname":"Xiao'ao",
    "gn:country_code":"CN",
    "gn:dem":325,
    "gn:feature_class":"P",
    "gn:feature_code":"PPL",
    "gn:name":"Xiao\u2019ao",
    "gn:population":0,
    "gn:timezone":"Asia/Shanghai",
    "iso:country":"CN",
    "name:und_x_variant":[
        "Xiao\u2019ao"
    ],
    "name:zho_x_preferred":[
        "\u5c0f\u5773"
    ],
    "wof:name":"Xiao'ao",
    "wof:placetype":"locality"
},
  "geometry": {"coordinates":[111.15626,27.47699],"type":"Point"}
}