{
  "type": "Feature",
  "properties": {
    "gn:admin1_code":"16.0",
    "gn:asciiname":"Xizhuya",
    "gn:country_code":"CN",
    "gn:dem":275,
    "gn:feature_class":"P",
    "gn:feature_code":"PPL",
    "gn:name":"Xizhuya",
    "gn:population":0,
    "gn:timezone":"Asia/Shanghai",
    "iso:country":"CN",
    "name:zho_x_preferred":[
        "\u897f\u732a\u7259"
    ],
    "wof:name":"Xizhuya",
    "wof:placetype":"locality"
},
  "geometry": {"coordinates":[110.71899999999999,24.3268],"type":"Point"}
}