{
  "type": "Feature",
  "properties": {
    "gn:admin1_code":"14.0",
    "gn:asciiname":"Longbai",
    "gn:country_code":"CN",
    "gn:dem":2911,
    "gn:feature_class":"P",
    "gn:feature_code":"PPL",
    "gn:name":"Longbai",
    "gn:population":0,
    "gn:timezone":"Asia/Urumqi",
    "iso:country":"CN",
    "name:zho_x_preferred":[
        "\u9f99\u767d"
    ],
    "wof:name":"Longbai",
    "wof:placetype":"locality"
},
  "geometry": {"coordinates":[94.89609,29.63143],"type":"Point"}
}