{
  "type": "Feature",
  "properties": {
    "gn:admin1_code":"16.0",
    "gn:asciiname":"Yifeng",
    "gn:country_code":"CN",
    "gn:dem":503,
    "gn:feature_class":"P",
    "gn:feature_code":"PPL",
    "gn:name":"Yifeng",
    "gn:population":0,
    "gn:timezone":"Asia/Shanghai",
    "iso:country":"CN",
    "name:zho_x_preferred":[
        "\u4eea\u51e4"
    ],
    "wof:name":"Yifeng",
    "wof:placetype":"locality"
},
  "geometry": {"coordinates":[108.063,24.9694],"type":"Point"}
}