{
  "type": "Feature",
  "properties": {
    "gn:admin1_code":"11",
    "gn:asciiname":"Moshi",
    "gn:country_code":"CN",
    "gn:dem":416,
    "gn:feature_class":"P",
    "gn:feature_code":"PPL",
    "gn:name":"Moshi",
    "gn:population":0,
    "gn:timezone":"Asia/Shanghai",
    "iso:country":"CN",
    "name:ceb_x_preferred":[
        "Moshi"
    ],
    "name:swa_x_preferred":[
        "Moshi"
    ],
    "name:swe_x_preferred":[
        "Moshi"
    ],
    "name:ukr_x_preferred":[
        "\u041c\u043e\u0448\u0456"
    ],
    "name:zho_x_preferred":[
        "\u78e8\u77f3"
    ],
    "wof:name":"Moshi",
    "wof:placetype":"locality"
},
  "geometry": {"coordinates":[109.78010999999999,26.53558],"type":"Point"}
}