{
  "type": "Feature",
  "properties": {
    "gn:admin1_code":"23",
    "gn:asciiname":"Qianwei",
    "gn:country_code":"CN",
    "gn:dem":5,
    "gn:feature_class":"P",
    "gn:feature_code":"PPL",
    "gn:name":"Qianwei",
    "gn:population":0,
    "gn:timezone":"Asia/Shanghai",
    "iso:country":"CN",
    "name:und_x_variant":[
        "\u524d\u536b"
    ],
    "wof:name":"Qianwei",
    "wof:placetype":"locality"
},
  "geometry": {"coordinates":[121.72217000000001,31.39849],"type":"Point"}
}