{
  "type": "Feature",
  "properties": {
    "gn:admin1_code":"29.0",
    "gn:asciiname":"Shuasongmi",
    "gn:country_code":"CN",
    "gn:dem":2458,
    "gn:feature_class":"P",
    "gn:feature_code":"PPL",
    "gn:name":"Shuasongmi",
    "gn:population":0,
    "gn:timezone":"Asia/Shanghai",
    "iso:country":"CN",
    "name:zho_x_preferred":[
        "\u800d\u677e\u7c73"
    ],
    "wof:name":"Shuasongmi",
    "wof:placetype":"locality"
},
  "geometry": {"coordinates":[100.01300000000001,27.2122],"type":"Point"}
}