{
  "type": "Feature",
  "properties": {
    "gn:admin1_code":"12.0",
    "gn:asciiname":"Jiangan",
    "gn:country_code":"CN",
    "gn:dem":493,
    "gn:feature_class":"P",
    "gn:feature_code":"PPL",
    "gn:name":"Jiangan",
    "gn:population":0,
    "gn:timezone":"Asia/Shanghai",
    "iso:country":"CN",
    "name:zho_x_preferred":[
        "\u7bad\u7aff"
    ],
    "wof:name":"Jiangan",
    "wof:placetype":"locality"
},
  "geometry": {"coordinates":[115.19204000000001,31.44533],"type":"Point"}
}