{
  "type": "Feature",
  "properties": {
    "gn:admin1_code":"02",
    "gn:asciiname":"Ruizhuyang",
    "gn:country_code":"CN",
    "gn:dem":882,
    "gn:feature_class":"P",
    "gn:feature_code":"PPL",
    "gn:name":"Ruizhuyang",
    "gn:population":0,
    "gn:timezone":"Asia/Shanghai",
    "iso:country":"CN",
    "name:und_x_variant":[
        "Tui-chu-yang",
        "Jui-chu-yang",
        "\u745e\u7af9\u579f",
        "Ruizhuyang"
    ],
    "wof:name":"Ruizhuyang",
    "wof:placetype":"locality"
},
  "geometry": {"coordinates":[119.09188,27.74057],"type":"Point"}
}