{
  "type": "Feature",
  "properties": {
    "gn:admin1_code":"3.0",
    "gn:asciiname":"Ruichang",
    "gn:country_code":"CN",
    "gn:dem":38,
    "gn:feature_class":"P",
    "gn:feature_code":"PPL",
    "gn:name":"Ruichang",
    "gn:population":0,
    "gn:timezone":"Asia/Shanghai",
    "iso:country":"CN",
    "name:und_x_variant":[
        "Ruichangshi",
        "\u745e\u660c\u5e02"
    ],
    "wof:name":"Ruichang",
    "wof:placetype":"locality"
},
  "geometry": {"coordinates":[115.65671,29.67965],"type":"Point"}
}