{
  "type": "Feature",
  "properties": {
    "gn:admin1_code":"32.0",
    "gn:asciiname":"Tongding",
    "gn:country_code":"CN",
    "gn:dem":2293,
    "gn:feature_class":"P",
    "gn:feature_code":"PPL",
    "gn:name":"Tongding",
    "gn:population":0,
    "gn:timezone":"Asia/Shanghai",
    "iso:country":"CN",
    "name:zho_x_preferred":[
        "\u540c\u9876"
    ],
    "wof:name":"Tongding",
    "wof:placetype":"locality"
},
  "geometry": {"coordinates":[100.303,28.0479],"type":"Point"}
}