{
  "type": "Feature",
  "properties": {
    "gn:admin1_code":"29.0",
    "gn:asciiname":"Lishadi",
    "gn:country_code":"CN",
    "gn:dem":1665,
    "gn:feature_class":"P",
    "gn:feature_code":"PPL",
    "gn:name":"Lishadi",
    "gn:population":0,
    "gn:timezone":"Asia/Shanghai",
    "iso:country":"CN",
    "wof:name":"Lishadi",
    "wof:placetype":"locality"
},
  "geometry": {"coordinates":[98.91667,27.25],"type":"Point"}
}