{
  "type": "Feature",
  "properties": {
    "gn:admin1_code":"1.0",
    "gn:asciiname":"Ziyoucun",
    "gn:country_code":"CN",
    "gn:dem":33,
    "gn:feature_class":"P",
    "gn:feature_code":"PPL",
    "gn:name":"Ziyoucun",
    "gn:population":0,
    "gn:timezone":"Asia/Shanghai",
    "iso:country":"CN",
    "name:zho_x_preferred":[
        "\u81ea\u7531\u6751"
    ],
    "wof:name":"Ziyoucun",
    "wof:placetype":"locality"
},
  "geometry": {"coordinates":[115.62309999999999,32.43993],"type":"Point"}
}