{
  "type": "Feature",
  "properties": {
    "gn:admin1_code":"20.0",
    "gn:asciiname":"Qianxingren",
    "gn:country_code":"CN",
    "gn:dem":197,
    "gn:feature_class":"P",
    "gn:feature_code":"PPL",
    "gn:name":"Qianxingren",
    "gn:population":0,
    "gn:timezone":"Asia/Shanghai",
    "iso:country":"CN",
    "name:zho_x_preferred":[
        "\u524d\u5174\u4ec1"
    ],
    "wof:name":"Qianxingren",
    "wof:placetype":"locality"
},
  "geometry": {"coordinates":[124.392,48.43663],"type":"Point"}
}