{
  "type": "Feature",
  "properties": {
    "gn:admin1_code":"15.0",
    "gn:asciiname":"Lianqu",
    "gn:country_code":"CN",
    "gn:dem":1384,
    "gn:feature_class":"P",
    "gn:feature_code":"PPL",
    "gn:name":"Lianqu",
    "gn:population":0,
    "gn:timezone":"Asia/Shanghai",
    "iso:country":"CN",
    "name:zho_x_preferred":[
        "\u8fde\u6e20"
    ],
    "wof:name":"Lianqu",
    "wof:placetype":"locality"
},
  "geometry": {"coordinates":[108.34399999999999,36.3275],"type":"Point"}
}