{
  "type": "Feature",
  "properties": {
    "gn:admin1_code":"29",
    "gn:asciiname":"Laoyingwo",
    "gn:country_code":"CN",
    "gn:dem":2204,
    "gn:feature_class":"P",
    "gn:feature_code":"PPL",
    "gn:name":"Laoyingwo",
    "gn:population":0,
    "gn:timezone":"Asia/Shanghai",
    "iso:country":"CN",
    "name:zho_x_preferred":[
        "\u8001\u9e70\u7a9d"
    ],
    "wof:name":"Laoyingwo",
    "wof:placetype":"locality"
},
  "geometry": {"coordinates":[102.72371,24.5749],"type":"Point"}
}