{
  "type": "Feature",
  "properties": {
    "gn:admin1_code":"29.0",
    "gn:asciiname":"Jilecun",
    "gn:country_code":"CN",
    "gn:dem":1852,
    "gn:feature_class":"P",
    "gn:feature_code":"PPL",
    "gn:name":"Jilecun",
    "gn:population":0,
    "gn:timezone":"Asia/Shanghai",
    "iso:country":"CN",
    "name:zho_x_preferred":[
        "\u6781\u4e50\u6751"
    ],
    "wof:name":"Jilecun",
    "wof:placetype":"locality"
},
  "geometry": {"coordinates":[102.496,24.9302],"type":"Point"}
}