{
  "type": "Feature",
  "properties": {
    "gn:admin1_code":"30.0",
    "gn:asciiname":"Hengdong",
    "gn:country_code":"CN",
    "gn:dem":491,
    "gn:feature_class":"P",
    "gn:feature_code":"PPL",
    "gn:name":"Hengdong",
    "gn:population":0,
    "gn:timezone":"Asia/Shanghai",
    "iso:country":"CN",
    "name:zho_x_preferred":[
        "Hengdong"
    ],
    "name:zho_x_variant":[
        "\u6a2a\u6d1e"
    ],
    "wof:name":"Hengdong",
    "wof:placetype":"locality"
},
  "geometry": {"coordinates":[112.61833,24.08361],"type":"Point"}
}