{
  "type": "Feature",
  "properties": {
    "gn:admin1_code":"7",
    "gn:asciiname":"Yuyunji",
    "gn:country_code":"CN",
    "gn:dem":557,
    "gn:feature_class":"P",
    "gn:feature_code":"PPL",
    "gn:name":"Yuyunji",
    "gn:population":0,
    "gn:timezone":"Asia/Shanghai",
    "iso:country":"CN",
    "name:und_x_variant":[
        "\u4fde\u4e91\u9645"
    ],
    "name:zho_x_preferred":[
        "\u4fde\u4e91\u9645"
    ],
    "wof:name":"Yuyunji",
    "wof:placetype":"locality"
},
  "geometry": {"coordinates":[117.46532999999999,26.47616],"type":"Point"}
}