{
  "type": "Feature",
  "properties": {
    "gn:admin1_code":"26.0",
    "gn:asciiname":"Jiefangwan",
    "gn:country_code":"CN",
    "gn:dem":726,
    "gn:feature_class":"P",
    "gn:feature_code":"PPL",
    "gn:name":"Jiefangwan",
    "gn:population":0,
    "gn:timezone":"Asia/Shanghai",
    "iso:country":"CN",
    "name:und_x_variant":[
        "\u89e3\u653e\u6e7e"
    ],
    "wof:name":"Jiefangwan",
    "wof:placetype":"locality"
},
  "geometry": {"coordinates":[108.02958,33.0898],"type":"Point"}
}