{
  "type": "Feature",
  "properties": {
    "gn:admin1_code":"21.0",
    "gn:asciiname":"Xipowa",
    "gn:country_code":"CN",
    "gn:dem":1709,
    "gn:feature_class":"P",
    "gn:feature_code":"PPL",
    "gn:name":"Xipowa",
    "gn:population":0,
    "gn:timezone":"Asia/Shanghai",
    "iso:country":"CN",
    "name:und_x_variant":[
        "\u897f\u5761\u6d3c"
    ],
    "name:zho_x_preferred":[
        "\u897f\u5761\u6d3c"
    ],
    "wof:name":"Xipowa",
    "wof:placetype":"locality"
},
  "geometry": {"coordinates":[106.30115000000001,36.19386],"type":"Point"}
}