{
  "type": "Feature",
  "properties": {
    "gn:admin1_code":"7.0",
    "gn:asciiname":"Guanqiufang",
    "gn:country_code":"CN",
    "gn:dem":284,
    "gn:feature_class":"P",
    "gn:feature_code":"PPL",
    "gn:name":"Guanqiufang",
    "gn:population":0,
    "gn:timezone":"Asia/Shanghai",
    "iso:country":"CN",
    "name:zho_x_preferred":[
        "\u5b98\u4e18\u574a"
    ],
    "wof:name":"Guanqiufang",
    "wof:placetype":"locality"
},
  "geometry": {"coordinates":[117.00281,26.71694],"type":"Point"}
}