{
  "type": "Feature",
  "properties": {
    "gn:admin1_code":"18.0",
    "gn:asciiname":"Tianba",
    "gn:country_code":"CN",
    "gn:dem":1540,
    "gn:feature_class":"P",
    "gn:feature_code":"PPL",
    "gn:name":"Tianba",
    "gn:population":0,
    "gn:timezone":"Asia/Shanghai",
    "iso:country":"CN",
    "name:zho_x_preferred":[
        "\u7530\u575d"
    ],
    "name:zho_x_variant":[
        "\u7530\u575d\u4e61"
    ],
    "wof:name":"Tianba",
    "wof:placetype":"locality"
},
  "geometry": {"coordinates":[103.65900000000001,27.0603],"type":"Point"}
}