{
  "type": "Feature",
  "properties": {
    "gn:admin1_code":"8.0",
    "gn:asciiname":"Yuejincun",
    "gn:country_code":"CN",
    "gn:dem":175,
    "gn:feature_class":"P",
    "gn:feature_code":"PPL",
    "gn:name":"Yuejincun",
    "gn:population":0,
    "gn:timezone":"Asia/Shanghai",
    "iso:country":"CN",
    "name:zho_x_preferred":[
        "\u8dc3\u8fdb\u6751"
    ],
    "wof:name":"Yuejincun",
    "wof:placetype":"locality"
},
  "geometry": {"coordinates":[127.88227999999999,49.3859],"type":"Point"}
}