{
  "type": "Feature",
  "properties": {
    "gn:admin1_code":"33.0",
    "gn:asciiname":"Changhe",
    "gn:country_code":"CN",
    "gn:dem":382,
    "gn:feature_class":"P",
    "gn:feature_code":"PPL",
    "gn:name":"Changhe",
    "gn:population":0,
    "gn:timezone":"Asia/Shanghai",
    "iso:country":"CN",
    "name:deu_x_preferred":[
        "Changhe"
    ],
    "name:fra_x_preferred":[
        "Changhe"
    ],
    "name:pol_x_preferred":[
        "Changhe"
    ],
    "name:por_x_preferred":[
        "Changhe"
    ],
    "name:sco_x_preferred":[
        "Changhe"
    ],
    "name:spa_x_preferred":[
        "Changhe"
    ],
    "name:zho_x_preferred":[
        "\u957f\u6cb3"
    ],
    "name:zho_x_variant":[
        "\u660c\u6cb3\u6c7d\u8f66"
    ],
    "wof:name":"Changhe",
    "wof:placetype":"locality"
},
  "geometry": {"coordinates":[106.62461,29.69397],"type":"Point"}
}