{
  "type": "Feature",
  "properties": {
    "gn:admin1_code":"24.0",
    "gn:asciiname":"Shoukoubu",
    "gn:country_code":"CN",
    "gn:dem":1216,
    "gn:feature_class":"P",
    "gn:feature_code":"PPL",
    "gn:name":"Shoukoubu",
    "gn:population":0,
    "gn:timezone":"Asia/Shanghai",
    "iso:country":"CN",
    "name:zho_x_preferred":[
        "\u5b88\u53e3\u5821"
    ],
    "wof:name":"Shoukoubu",
    "wof:placetype":"locality"
},
  "geometry": {"coordinates":[113.65966,40.41754],"type":"Point"}
}