{
  "type": "Feature",
  "properties": {
    "gn:admin1_code":"24.0",
    "gn:asciiname":"Fuwazhuang",
    "gn:country_code":"CN",
    "gn:dem":760,
    "gn:feature_class":"P",
    "gn:feature_code":"PPL",
    "gn:name":"Fuwazhuang",
    "gn:population":0,
    "gn:timezone":"Asia/Shanghai",
    "iso:country":"CN",
    "name:zho_x_preferred":[
        "\u798f\u6d3c\u5e84"
    ],
    "wof:name":"Fuwazhuang",
    "wof:placetype":"locality"
},
  "geometry": {"coordinates":[111.61998,36.50379],"type":"Point"}
}