{
  "type": "Feature",
  "properties": {
    "gn:admin1_code":"30.0",
    "gn:asciiname":"Changkengwei",
    "gn:country_code":"CN",
    "gn:dem":622,
    "gn:feature_class":"P",
    "gn:feature_code":"PPL",
    "gn:name":"Changkengwei",
    "gn:population":0,
    "gn:timezone":"Asia/Shanghai",
    "iso:country":"CN",
    "name:zho_x_preferred":[
        "Changkengwei"
    ],
    "name:zho_x_variant":[
        "\u957f\u5751\u5c3e"
    ],
    "wof:name":"Changkengwei",
    "wof:placetype":"locality"
},
  "geometry": {"coordinates":[112.47444,24.40444],"type":"Point"}
}