{
  "type": "Feature",
  "properties": {
    "gn:admin1_code":"25",
    "gn:asciiname":"Qianyinjia",
    "gn:country_code":"CN",
    "gn:dem":11,
    "gn:feature_class":"P",
    "gn:feature_code":"PPL",
    "gn:name":"Qianyinjia",
    "gn:population":0,
    "gn:timezone":"Asia/Shanghai",
    "iso:country":"CN",
    "name:zho_x_preferred":[
        "\u524d\u5c39\u5bb6"
    ],
    "wof:name":"Qianyinjia",
    "wof:placetype":"locality"
},
  "geometry": {"coordinates":[117.80800000000001,37.5366],"type":"Point"}
}