{
  "type": "Feature",
  "properties": {
    "gn:admin1_code":"4.0",
    "gn:asciiname":"Jinfu",
    "gn:country_code":"CN",
    "gn:dem":-1,
    "gn:feature_class":"P",
    "gn:feature_code":"PPL",
    "gn:name":"Jinfu",
    "gn:population":0,
    "gn:timezone":"Asia/Shanghai",
    "iso:country":"CN",
    "name:zho_x_preferred":[
        "\u6d25\u5bcc"
    ],
    "wof:name":"Jinfu",
    "wof:placetype":"locality"
},
  "geometry": {"coordinates":[120.17389,33.62512],"type":"Point"}
}