{
  "type": "Feature",
  "properties": {
    "gn:admin1_code":"26.0",
    "gn:asciiname":"Bincaojian",
    "gn:country_code":"CN",
    "gn:dem":1617,
    "gn:feature_class":"P",
    "gn:feature_code":"PPL",
    "gn:name":"Bincaojian",
    "gn:population":0,
    "gn:timezone":"Asia/Shanghai",
    "iso:country":"CN",
    "name:zho_x_preferred":[
        "\u69df\u8349\u6da7"
    ],
    "wof:name":"Bincaojian",
    "wof:placetype":"locality"
},
  "geometry": {"coordinates":[107.56765,37.1875],"type":"Point"}
}