{
  "type": "Feature",
  "properties": {
    "gn:admin1_code":"11.0",
    "gn:asciiname":"Muzitang",
    "gn:country_code":"CN",
    "gn:dem":138,
    "gn:feature_class":"P",
    "gn:feature_code":"PPL",
    "gn:name":"Muzitang",
    "gn:population":0,
    "gn:timezone":"Asia/Shanghai",
    "iso:country":"CN",
    "name:zho_x_preferred":[
        "\u6728\u5b50\u5858"
    ],
    "wof:name":"Muzitang",
    "wof:placetype":"locality"
},
  "geometry": {"coordinates":[113.14082000000001,26.20061],"type":"Point"}
}