{
  "type": "Feature",
  "properties": {
    "gn:admin1_code":"29.0",
    "gn:asciiname":"Banmo",
    "gn:country_code":"CN",
    "gn:dem":1180,
    "gn:feature_class":"P",
    "gn:feature_code":"PPL",
    "gn:name":"Banmo",
    "gn:population":0,
    "gn:timezone":"Asia/Shanghai",
    "iso:country":"CN",
    "name:zho_x_preferred":[
        "\u73ed\u83ab"
    ],
    "wof:name":"Banmo",
    "wof:placetype":"locality"
},
  "geometry": {"coordinates":[99.0694,23.3691],"type":"Point"}
}