{
  "type": "Feature",
  "properties": {
    "gn:admin1_code":"30.0",
    "gn:asciiname":"Yuxincun",
    "gn:country_code":"CN",
    "gn:dem":7,
    "gn:feature_class":"P",
    "gn:feature_code":"PPL",
    "gn:name":"Yuxincun",
    "gn:population":0,
    "gn:timezone":"Asia/Shanghai",
    "iso:country":"CN",
    "name:zho_x_preferred":[
        "\u6e14\u65b0\u6751"
    ],
    "wof:name":"Yuxincun",
    "wof:placetype":"locality"
},
  "geometry": {"coordinates":[116.18709,23.34092],"type":"Point"}
}