{
  "type": "Feature",
  "properties": {
    "gn:admin1_code":"32.0",
    "gn:asciiname":"Kangjiawan",
    "gn:country_code":"CN",
    "gn:dem":820,
    "gn:feature_class":"P",
    "gn:feature_code":"PPL",
    "gn:name":"Kangjiawan",
    "gn:population":0,
    "gn:timezone":"Asia/Shanghai",
    "iso:country":"CN",
    "name:zho_x_preferred":[
        "\u4ea2\u5bb6\u6e7e"
    ],
    "wof:name":"Kangjiawan",
    "wof:placetype":"locality"
},
  "geometry": {"coordinates":[105.75969000000001,32.70502],"type":"Point"}
}