{
  "type": "Feature",
  "properties": {
    "gn:admin1_code":"5.0",
    "gn:asciiname":"Dongling Erdui",
    "gn:country_code":"CN",
    "gn:dem":186,
    "gn:feature_class":"P",
    "gn:feature_code":"PPLF",
    "gn:name":"Dongling Erdui",
    "gn:population":0,
    "gn:timezone":"Asia/Shanghai",
    "iso:country":"CN",
    "name:zho_x_preferred":[
        "\u4e1c\u5cad\u4e8c\u961f"
    ],
    "wof:name":"Dongling Erdui",
    "wof:placetype":"locality"
},
  "geometry": {"coordinates":[126.54973,44.48209],"type":"Point"}
}