{
  "type": "Feature",
  "properties": {
    "gn:admin1_code":"16.0",
    "gn:asciiname":"Dule",
    "gn:country_code":"CN",
    "gn:dem":148,
    "gn:feature_class":"P",
    "gn:feature_code":"PPL",
    "gn:name":"Dule",
    "gn:population":0,
    "gn:timezone":"Asia/Shanghai",
    "iso:country":"CN",
    "name:zho_x_preferred":[
        "\u90fd\u4e50"
    ],
    "wof:name":"Dule",
    "wof:placetype":"locality"
},
  "geometry": {"coordinates":[108.643,24.0524],"type":"Point"}
}