{
  "type": "Feature",
  "properties": {
    "gn:admin1_code":"19.0",
    "gn:asciiname":"Hejiaxin",
    "gn:country_code":"CN",
    "gn:dem":74,
    "gn:feature_class":"P",
    "gn:feature_code":"PPL",
    "gn:name":"Hejiaxin",
    "gn:population":0,
    "gn:timezone":"Asia/Shanghai",
    "iso:country":"CN",
    "name:und_x_variant":[
        "\u6cb3\u5939\u4fe1"
    ],
    "wof:name":"Hejiaxin",
    "wof:placetype":"locality"
},
  "geometry": {"coordinates":[123.34551,40.25226],"type":"Point"}
}