{
  "type": "Feature",
  "properties": {
    "gn:admin1_code":"19.0",
    "gn:asciiname":"Baijia Shichangcun",
    "gn:country_code":"CN",
    "gn:dem":315,
    "gn:feature_class":"P",
    "gn:feature_code":"PPL",
    "gn:name":"Baijia Shichangcun",
    "gn:population":0,
    "gn:timezone":"Asia/Shanghai",
    "iso:country":"CN",
    "name:zho_x_preferred":[
        "\u767d\u5bb6\u77f3\u573a\u6751"
    ],
    "wof:name":"Baijia Shichangcun",
    "wof:placetype":"locality"
},
  "geometry": {"coordinates":[120.532,41.8706],"type":"Point"}
}