{
  "type": "Feature",
  "properties": {
    "gn:admin1_code":"33.0",
    "gn:asciiname":"Juxing",
    "gn:country_code":"CN",
    "gn:dem":283,
    "gn:feature_class":"P",
    "gn:feature_code":"PPL",
    "gn:name":"Juxing",
    "gn:population":0,
    "gn:timezone":"Asia/Shanghai",
    "iso:country":"CN",
    "name:zho_x_preferred":[
        "\u83ca\u661f"
    ],
    "wof:name":"Juxing",
    "wof:placetype":"locality"
},
  "geometry": {"coordinates":[106.4036,30.11158],"type":"Point"}
}