{
  "type": "Feature",
  "properties": {
    "gn:admin1_code":"15.0",
    "gn:asciiname":"Ranping",
    "gn:country_code":"CN",
    "gn:dem":1822,
    "gn:feature_class":"P",
    "gn:feature_code":"PPL",
    "gn:name":"Ranping",
    "gn:population":0,
    "gn:timezone":"Asia/Shanghai",
    "iso:country":"CN",
    "name:und_x_variant":[
        "\u5189\u576a"
    ],
    "wof:name":"Ranping",
    "wof:placetype":"locality"
},
  "geometry": {"coordinates":[105.25279,35.88721],"type":"Point"}
}