{
  "type": "Feature",
  "properties": {
    "gn:admin1_code":"30",
    "gn:asciiname":"Tangxicun",
    "gn:country_code":"CN",
    "gn:dem":22,
    "gn:feature_class":"P",
    "gn:feature_code":"PPL",
    "gn:name":"Tangxicun",
    "gn:population":0,
    "gn:timezone":"Asia/Urumqi",
    "iso:country":"CN",
    "name:zho_x_preferred":[
        "\u5858\u897f\u6751"
    ],
    "wof:name":"Tangxicun",
    "wof:placetype":"locality"
},
  "geometry": {"coordinates":[109.91553999999999,21.00803],"type":"Point"}
}