{
  "type": "Feature",
  "properties": {
    "gn:admin1_code":"2.0",
    "gn:asciiname":"Tujiabu",
    "gn:country_code":"CN",
    "gn:dem":21,
    "gn:feature_class":"P",
    "gn:feature_code":"PPL",
    "gn:name":"Tujiabu",
    "gn:population":0,
    "gn:timezone":"Asia/Shanghai",
    "iso:country":"CN",
    "name:zho_x_preferred":[
        "\u5c60\u5bb6\u57e0"
    ],
    "wof:name":"Tujiabu",
    "wof:placetype":"locality"
},
  "geometry": {"coordinates":[120.83034000000001,29.65825],"type":"Point"}
}