{
  "type": "Feature",
  "properties": {
    "gn:admin1_code":"24",
    "gn:asciiname":"Shanghongchi",
    "gn:cc2":"CN",
    "gn:country_code":"CN",
    "gn:dem":520,
    "gn:feature_class":"P",
    "gn:feature_code":"PPL",
    "gn:name":"Shanghongchi",
    "gn:population":0,
    "gn:timezone":"Asia/Shanghai",
    "iso:country":"CN",
    "name:und_x_variant":[
        "Shang-hung-ch\u2019ih",
        "Shanghongchi"
    ],
    "wof:name":"Shanghongchi",
    "wof:placetype":"locality"
},
  "geometry": {"coordinates":[110.95,34.76667],"type":"Point"}
}