{
  "type": "Feature",
  "properties": {
    "gn:admin1_code":"32.0",
    "gn:asciiname":"Jiezi",
    "gn:country_code":"CN",
    "gn:dem":494,
    "gn:feature_class":"P",
    "gn:feature_code":"PPL",
    "gn:name":"Jiezi",
    "gn:population":0,
    "gn:timezone":"Asia/Shanghai",
    "iso:country":"CN",
    "name:zho_x_preferred":[
        "\u8857\u5b50"
    ],
    "wof:name":"Jiezi",
    "wof:placetype":"locality"
},
  "geometry": {"coordinates":[104.84430999999999,31.58364000000001],"type":"Point"}
}