{
  "type": "Feature",
  "properties": {
    "gn:admin1_code":"14",
    "gn:asciiname":"Lading",
    "gn:country_code":"CN",
    "gn:dem":4385,
    "gn:feature_class":"P",
    "gn:feature_code":"PPL",
    "gn:name":"Lading",
    "gn:population":0,
    "gn:timezone":"Asia/Urumqi",
    "iso:country":"CN",
    "name:zho_x_preferred":[
        "\u62c9\u5b9a"
    ],
    "wof:name":"Lading",
    "wof:placetype":"locality"
},
  "geometry": {"coordinates":[89.5787,28.4212],"type":"Point"}
}