{
  "type": "Feature",
  "properties": {
    "gn:admin1_code":"11",
    "gn:asciiname":"Siduping",
    "gn:country_code":"CN",
    "gn:dem":405,
    "gn:feature_class":"P",
    "gn:feature_code":"PPLA4",
    "gn:name":"Siduping",
    "gn:population":0,
    "gn:timezone":"Asia/Shanghai",
    "iso:country":"CN",
    "name:und_x_variant":[
        "\u56db\u90fd\u576a",
        "Siduping Xiang",
        "\u56db\u90fd\u576a\u4e61"
    ],
    "wof:name":"Siduping",
    "wof:placetype":"locality"
},
  "geometry": {"coordinates":[110.4301,28.9305],"type":"Point"}
}