{
  "type": "Feature",
  "properties": {
    "gn:admin1_code":"1.0",
    "gn:asciiname":"Hushuwangcun",
    "gn:country_code":"CN",
    "gn:dem":36,
    "gn:feature_class":"P",
    "gn:feature_code":"PPL",
    "gn:name":"Hushuwangcun",
    "gn:population":0,
    "gn:timezone":"Asia/Shanghai",
    "iso:country":"CN",
    "name:zho_x_preferred":[
        "\u745a\u6811\u738b\u6751"
    ],
    "wof:name":"Hushuwangcun",
    "wof:placetype":"locality"
},
  "geometry": {"coordinates":[117.38075000000001,33.93884],"type":"Point"}
}