{
  "type": "Feature",
  "properties": {
    "gn:admin1_code":"32.0",
    "gn:asciiname":"Dayanshang",
    "gn:country_code":"CN",
    "gn:dem":396,
    "gn:feature_class":"P",
    "gn:feature_code":"PPL",
    "gn:name":"Dayanshang",
    "gn:population":0,
    "gn:timezone":"Asia/Shanghai",
    "iso:country":"CN",
    "name:zho_x_preferred":[
        "\u5927\u5ca9\u4e0a"
    ],
    "wof:name":"Dayanshang",
    "wof:placetype":"locality"
},
  "geometry": {"coordinates":[104.539,28.7756],"type":"Point"}
}