{
  "type": "Feature",
  "properties": {
    "gn:admin1_code":"2.0",
    "gn:asciiname":"Yaogong",
    "gn:country_code":"CN",
    "gn:dem":7,
    "gn:feature_class":"P",
    "gn:feature_code":"PPL",
    "gn:name":"Yaogong",
    "gn:population":0,
    "gn:timezone":"Asia/Shanghai",
    "iso:country":"CN",
    "name:zho_x_preferred":[
        "\u59da\u5bab"
    ],
    "wof:name":"Yaogong",
    "wof:placetype":"locality"
},
  "geometry": {"coordinates":[122.36443,30.46115],"type":"Point"}
}