{
  "type": "Feature",
  "properties": {
    "gn:admin1_code":"16.0",
    "gn:asciiname":"Chongle",
    "gn:country_code":"CN",
    "gn:dem":14,
    "gn:feature_class":"P",
    "gn:feature_code":"PPL",
    "gn:name":"Chongle",
    "gn:population":0,
    "gn:timezone":"Asia/Shanghai",
    "iso:country":"CN",
    "name:zho_x_preferred":[
        "\u51b2\u52d2"
    ],
    "wof:name":"Chongle",
    "wof:placetype":"locality"
},
  "geometry": {"coordinates":[108.125,21.6698],"type":"Point"}
}