{
  "type": "Feature",
  "properties": {
    "gn:admin1_code":"3.0",
    "gn:asciiname":"Zhishanba",
    "gn:country_code":"CN",
    "gn:dem":185,
    "gn:feature_class":"P",
    "gn:feature_code":"PPL",
    "gn:name":"Zhishanba",
    "gn:population":0,
    "gn:timezone":"Asia/Shanghai",
    "iso:country":"CN",
    "name:zho_x_preferred":[
        "\u8d3d\u5c71\u575d"
    ],
    "wof:name":"Zhishanba",
    "wof:placetype":"locality"
},
  "geometry": {"coordinates":[115.78400000000001,25.4458],"type":"Point"}
}