{
  "type": "Feature",
  "properties": {
    "gn:admin1_code":"22.0",
    "gn:asciiname":"Xingfeng",
    "gn:country_code":"CN",
    "gn:dem":43,
    "gn:feature_class":"P",
    "gn:feature_code":"PPLA3",
    "gn:name":"Xingfeng",
    "gn:population":0,
    "gn:timezone":"Asia/Shanghai",
    "iso:country":"CN",
    "name:und_x_variant":[
        "Xingfeng Jiedao",
        "Daxing Qu"
    ],
    "name:zho_x_preferred":[
        "\u5174\u4e30"
    ],
    "name:zho_x_variant":[
        "\u5174\u4e30\u8857\u9053",
        "\u5927\u5174\u533a"
    ],
    "wof:name":"Xingfeng",
    "wof:placetype":"locality"
},
  "geometry": {"coordinates":[116.33660999999999,39.72965],"type":"Point"}
}