{
  "type": "Feature",
  "properties": {
    "gn:admin1_code":"11.0",
    "gn:asciiname":"Chebei",
    "gn:country_code":"CN",
    "gn:dem":101,
    "gn:feature_class":"P",
    "gn:feature_code":"PPL",
    "gn:name":"Chebei",
    "gn:population":0,
    "gn:timezone":"Asia/Shanghai",
    "iso:country":"CN",
    "name:zho_x_preferred":[
        "\u8f66\u9642"
    ],
    "wof:name":"Chebei",
    "wof:placetype":"locality"
},
  "geometry": {"coordinates":[113.01123,26.76579000000001],"type":"Point"}
}