{
  "type": "Feature",
  "properties": {
    "gn:admin1_code":"30",
    "gn:asciiname":"Wurengen",
    "gn:country_code":"CN",
    "gn:dem":36,
    "gn:feature_class":"P",
    "gn:feature_code":"PPL",
    "gn:name":"Wurengen",
    "gn:population":0,
    "gn:timezone":"Asia/Urumqi",
    "iso:country":"CN",
    "name:zho_x_preferred":[
        "\u4f0d\u7a14\u6839"
    ],
    "wof:name":"Wurengen",
    "wof:placetype":"locality"
},
  "geometry": {"coordinates":[111.27224,21.63531],"type":"Point"}
}