{
  "type": "Feature",
  "properties": {
    "gn:admin1_code":"1.0",
    "gn:asciiname":"Daqiaofancun",
    "gn:country_code":"CN",
    "gn:dem":40,
    "gn:feature_class":"P",
    "gn:feature_code":"PPL",
    "gn:name":"Daqiaofancun",
    "gn:population":0,
    "gn:timezone":"Asia/Shanghai",
    "iso:country":"CN",
    "name:zho_x_preferred":[
        "\u5927\u6865\u7548\u6751"
    ],
    "wof:name":"Daqiaofancun",
    "wof:placetype":"locality"
},
  "geometry": {"coordinates":[116.58372,31.79941],"type":"Point"}
}