{
  "type": "Feature",
  "properties": {
    "gn:admin1_code":"14.0",
    "gn:asciiname":"Zhanie Muchang",
    "gn:country_code":"CN",
    "gn:dem":4493,
    "gn:feature_class":"P",
    "gn:feature_code":"PPLF",
    "gn:name":"Zhanie Muchang",
    "gn:population":0,
    "gn:timezone":"Asia/Urumqi",
    "iso:country":"CN",
    "name:zho_x_preferred":[
        "\u624e\u8042\u7267\u573a"
    ],
    "wof:name":"Zhanie Muchang",
    "wof:placetype":"locality"
},
  "geometry": {"coordinates":[96.25565,30.18598],"type":"Point"}
}