{
  "type": "Feature",
  "properties": {
    "gn:admin1_code":"33.0",
    "gn:asciiname":"Wuhe",
    "gn:country_code":"CN",
    "gn:dem":461,
    "gn:feature_class":"P",
    "gn:feature_code":"PPL",
    "gn:name":"Wuhe",
    "gn:population":0,
    "gn:timezone":"Asia/Shanghai",
    "iso:country":"CN",
    "name:ceb_x_preferred":[
        "Wuhe"
    ],
    "name:deu_x_preferred":[
        "Wuhe"
    ],
    "name:zho_x_preferred":[
        "\u4e94\u5408"
    ],
    "wof:name":"Wuhe",
    "wof:placetype":"locality"
},
  "geometry": {"coordinates":[107.11863999999998,29.84678],"type":"Point"}
}