{
  "type": "Feature",
  "properties": {
    "gn:admin1_code":"29.0",
    "gn:asciiname":"Erzi",
    "gn:country_code":"CN",
    "gn:dem":2431,
    "gn:feature_class":"P",
    "gn:feature_code":"PPL",
    "gn:name":"Erzi",
    "gn:population":0,
    "gn:timezone":"Asia/Shanghai",
    "iso:country":"CN",
    "name:rus_x_preferred":[
        "\u042d\u0440\u0437\u0438"
    ],
    "name:und_x_variant":[
        "\u8033\u5b50"
    ],
    "wof:name":"Erzi",
    "wof:placetype":"locality"
},
  "geometry": {"coordinates":[103.72834,26.89666],"type":"Point"}
}