{
  "type": "Feature",
  "properties": {
    "gn:admin1_code":"3.0",
    "gn:asciiname":"Xiaogang",
    "gn:country_code":"CN",
    "gn:dem":118,
    "gn:feature_class":"P",
    "gn:feature_code":"PPL",
    "gn:name":"Xiaogang",
    "gn:population":0,
    "gn:timezone":"Asia/Shanghai",
    "iso:country":"CN",
    "name:ces_x_preferred":[
        "Siao-kang"
    ],
    "name:deu_x_preferred":[
        "Xiaogang"
    ],
    "name:fra_x_preferred":[
        "Xiaogang"
    ],
    "name:und_x_variant":[
        "\u5c0f\u5c97"
    ],
    "wof:name":"Xiaogang",
    "wof:placetype":"locality"
},
  "geometry": {"coordinates":[115.57656,27.64001],"type":"Point"}
}