{
  "type": "Feature",
  "properties": {
    "gn:admin1_code":"11",
    "gn:asciiname":"Xinghua",
    "gn:country_code":"CN",
    "gn:dem":433,
    "gn:feature_class":"P",
    "gn:feature_code":"PPL",
    "gn:name":"Xinghua",
    "gn:population":0,
    "gn:timezone":"Asia/Shanghai",
    "iso:country":"CN",
    "name:ceb_x_preferred":[
        "Xinghua"
    ],
    "name:deu_x_preferred":[
        "Xinghua"
    ],
    "name:fra_x_preferred":[
        "Xinghua"
    ],
    "name:swe_x_preferred":[
        "Xinghua"
    ],
    "wof:name":"Xinghua",
    "wof:placetype":"locality"
},
  "geometry": {"coordinates":[109.86139,26.26278],"type":"Point"}
}