{
  "type": "Feature",
  "properties": {
    "gn:admin1_code":"23.0",
    "gn:asciiname":"Sanzao",
    "gn:country_code":"CN",
    "gn:dem":3,
    "gn:feature_class":"P",
    "gn:feature_code":"PPL",
    "gn:name":"Sanzao",
    "gn:population":0,
    "gn:timezone":"Asia/Shanghai",
    "iso:country":"CN",
    "name:zho_x_preferred":[
        "Sanzao"
    ],
    "name:zho_x_variant":[
        "\u4e09\u7076"
    ],
    "wof:name":"Sanzao",
    "wof:placetype":"locality"
},
  "geometry": {"coordinates":[121.64569,31.18957],"type":"Point"}
}