{
  "type": "Feature",
  "properties": {
    "gn:admin1_code":"32.0",
    "gn:asciiname":"Jianggai",
    "gn:country_code":"CN",
    "gn:dem":3454,
    "gn:feature_class":"P",
    "gn:feature_code":"PPL",
    "gn:name":"Jianggai",
    "gn:population":0,
    "gn:timezone":"Asia/Shanghai",
    "iso:country":"CN",
    "name:zho_x_preferred":[
        "\u59dc\u76d6"
    ],
    "wof:name":"Jianggai",
    "wof:placetype":"locality"
},
  "geometry": {"coordinates":[100.64700000000001,29.0516],"type":"Point"}
}