{
  "type": "Feature",
  "properties": {
    "gn:admin1_code":"1.0",
    "gn:asciiname":"Guanlingcun",
    "gn:country_code":"CN",
    "gn:dem":54,
    "gn:feature_class":"P",
    "gn:feature_code":"PPL",
    "gn:name":"Guanlingcun",
    "gn:population":0,
    "gn:timezone":"Asia/Shanghai",
    "iso:country":"CN",
    "name:zho_x_preferred":[
        "\u7ba1\u5cad\u6751"
    ],
    "wof:name":"Guanlingcun",
    "wof:placetype":"locality"
},
  "geometry": {"coordinates":[116.79721000000001,31.32442],"type":"Point"}
}