{
  "type": "Feature",
  "properties": {
    "gn:admin1_code":"24.0",
    "gn:asciiname":"Changxincun",
    "gn:country_code":"CN",
    "gn:dem":1009,
    "gn:feature_class":"P",
    "gn:feature_code":"PPL",
    "gn:name":"Changxincun",
    "gn:population":0,
    "gn:timezone":"Asia/Shanghai",
    "iso:country":"CN",
    "name:zho_x_preferred":[
        "\u5e38\u8f9b\u6751"
    ],
    "wof:name":"Changxincun",
    "wof:placetype":"locality"
},
  "geometry": {"coordinates":[112.90322999999999,39.52222],"type":"Point"}
}