{
  "type": "Feature",
  "properties": {
    "gn:admin1_code":"9.0",
    "gn:asciiname":"Sangshuling",
    "gn:country_code":"CN",
    "gn:dem":776,
    "gn:feature_class":"P",
    "gn:feature_code":"PPL",
    "gn:name":"Sangshuling",
    "gn:population":0,
    "gn:timezone":"Asia/Shanghai",
    "iso:country":"CN",
    "name:zho_x_preferred":[
        "\u6851\u6811\u5cad"
    ],
    "wof:name":"Sangshuling",
    "wof:placetype":"locality"
},
  "geometry": {"coordinates":[111.20780999999999,34.13034],"type":"Point"}
}