{
  "type": "Feature",
  "properties": {
    "gn:admin1_code":"15.0",
    "gn:asciiname":"Shejiamen",
    "gn:country_code":"CN",
    "gn:dem":1059,
    "gn:feature_class":"P",
    "gn:feature_code":"PPL",
    "gn:name":"Shejiamen",
    "gn:population":0,
    "gn:timezone":"Asia/Shanghai",
    "iso:country":"CN",
    "name:zho_x_preferred":[
        "\u4f58\u5bb6\u95e8"
    ],
    "wof:name":"Shejiamen",
    "wof:placetype":"locality"
},
  "geometry": {"coordinates":[106.306,34.4913],"type":"Point"}
}