{
  "type": "Feature",
  "properties": {
    "gn:admin1_code":"11.0",
    "gn:asciiname":"Shangxujiayuan",
    "gn:country_code":"CN",
    "gn:dem":187,
    "gn:feature_class":"P",
    "gn:feature_code":"PPL",
    "gn:name":"Shangxujiayuan",
    "gn:population":0,
    "gn:timezone":"Asia/Shanghai",
    "iso:country":"CN",
    "name:zho_x_preferred":[
        "\u4e0a\u5f90\u5bb6\u9662"
    ],
    "wof:name":"Shangxujiayuan",
    "wof:placetype":"locality"
},
  "geometry": {"coordinates":[111.73701,26.65331],"type":"Point"}
}