{
  "type": "Feature",
  "properties": {
    "gn:admin1_code":"10",
    "gn:asciiname":"Kuancheng",
    "gn:country_code":"CN",
    "gn:dem":303,
    "gn:feature_class":"P",
    "gn:feature_code":"PPLA3",
    "gn:name":"Kuancheng",
    "gn:population":0,
    "gn:timezone":"Asia/Shanghai",
    "iso:country":"CN",
    "name:deu_x_preferred":[
        "Kuancheng"
    ],
    "name:fra_x_preferred":[
        "Kuancheng"
    ],
    "name:nor_x_preferred":[
        "Kuancheng"
    ],
    "name:swe_x_preferred":[
        "Kuancheng"
    ],
    "name:und_x_variant":[
        "K\u2019uan-chieng",
        "Kwancheng",
        "Kwangheng"
    ],
    "name:zho_x_preferred":[
        "\u5bbd\u57ce"
    ],
    "wof:name":"Kuancheng",
    "wof:placetype":"locality"
},
  "geometry": {"coordinates":[118.4825,40.60556],"type":"Point"}
}