{
  "type": "Feature",
  "properties": {
    "gn:admin1_code":"19.0",
    "gn:asciiname":"Qiaotuncun",
    "gn:country_code":"CN",
    "gn:dem":4,
    "gn:feature_class":"P",
    "gn:feature_code":"PPL",
    "gn:name":"Qiaotuncun",
    "gn:population":0,
    "gn:timezone":"Asia/Shanghai",
    "iso:country":"CN",
    "name:zho_x_preferred":[
        "\u4e54\u5c6f\u6751"
    ],
    "wof:name":"Qiaotuncun",
    "wof:placetype":"locality"
},
  "geometry": {"coordinates":[122.79083,39.73132],"type":"Point"}
}