{
  "type": "Feature",
  "properties": {
    "gn:admin1_code":"10.0",
    "gn:asciiname":"Xiaodian",
    "gn:cc2":"CN",
    "gn:country_code":"CN",
    "gn:dem":25,
    "gn:feature_class":"P",
    "gn:feature_code":"PPL",
    "gn:name":"Xiaodian",
    "gn:population":0,
    "gn:timezone":"Asia/Shanghai",
    "iso:country":"CN",
    "name:und_x_variant":[
        "Hsiao-tien",
        "Xiaodian"
    ],
    "wof:name":"Xiaodian",
    "wof:placetype":"locality"
},
  "geometry": {"coordinates":[115.45,38.55],"type":"Point"}
}