{
  "type": "Feature",
  "properties": {
    "gn:admin1_code":"20.0",
    "gn:asciiname":"Houxingquan",
    "gn:country_code":"CN",
    "gn:dem":1576,
    "gn:feature_class":"P",
    "gn:feature_code":"PPL",
    "gn:name":"Houxingquan",
    "gn:population":0,
    "gn:timezone":"Asia/Shanghai",
    "iso:country":"CN",
    "name:und_x_variant":[
        "\u540e\u5174\u6cc9"
    ],
    "wof:name":"Houxingquan",
    "wof:placetype":"locality"
},
  "geometry": {"coordinates":[111.99154,39.86888],"type":"Point"}
}