{
  "type": "Feature",
  "properties": {
    "gn:admin1_code":"24",
    "gn:asciiname":"Renjiazhuang",
    "gn:country_code":"CN",
    "gn:dem":1654,
    "gn:feature_class":"P",
    "gn:feature_code":"PPL",
    "gn:name":"Renjiazhuang",
    "gn:population":0,
    "gn:timezone":"Asia/Shanghai",
    "iso:country":"CN",
    "wof:name":"Renjiazhuang",
    "wof:placetype":"locality"
},
  "geometry": {"coordinates":[111.41249999999999,37.70333],"type":"Point"}
}