{
  "type": "Feature",
  "properties": {
    "gn:admin1_code":"32.0",
    "gn:asciiname":"Baoshiyan",
    "gn:country_code":"CN",
    "gn:dem":317,
    "gn:feature_class":"P",
    "gn:feature_code":"PPL",
    "gn:name":"Baoshiyan",
    "gn:population":0,
    "gn:timezone":"Asia/Shanghai",
    "iso:country":"CN",
    "name:zho_x_preferred":[
        "\u5b9d\u77f3\u5ca9"
    ],
    "wof:name":"Baoshiyan",
    "wof:placetype":"locality"
},
  "geometry": {"coordinates":[105.304,30.5756],"type":"Point"}
}