{
  "type": "Feature",
  "properties": {
    "gn:admin1_code":"3",
    "gn:asciiname":"Fenglin",
    "gn:country_code":"CN",
    "gn:dem":166,
    "gn:feature_class":"P",
    "gn:feature_code":"PPL",
    "gn:name":"Fenglin",
    "gn:population":0,
    "gn:timezone":"Asia/Shanghai",
    "iso:country":"CN",
    "name:ceb_x_preferred":[
        "Fenglin"
    ],
    "name:deu_x_preferred":[
        "Fenglin"
    ],
    "name:swe_x_preferred":[
        "Fenglin"
    ],
    "name:zho_x_preferred":[
        "\u67ab\u6797"
    ],
    "wof:name":"Fenglin",
    "wof:placetype":"locality"
},
  "geometry": {"coordinates":[118.03700000000001,28.8452],"type":"Point"}
}