{
  "type": "Feature",
  "properties": {
    "gn:admin1_code":"4.0",
    "gn:asciiname":"Erlian",
    "gn:country_code":"CN",
    "gn:dem":4,
    "gn:feature_class":"P",
    "gn:feature_code":"PPL",
    "gn:name":"Erlian",
    "gn:population":0,
    "gn:timezone":"Asia/Shanghai",
    "iso:country":"CN",
    "name:pol_x_preferred":[
        "Erlian"
    ],
    "name:zho_x_preferred":[
        "\u4e8c\u8054"
    ],
    "wof:name":"Erlian",
    "wof:placetype":"locality"
},
  "geometry": {"coordinates":[120.58005,32.82096],"type":"Point"}
}