{
  "type": "Feature",
  "properties": {
    "gn:admin1_code":"2.0",
    "gn:asciiname":"Diaomachang",
    "gn:country_code":"CN",
    "gn:dem":24,
    "gn:feature_class":"P",
    "gn:feature_code":"PPLF",
    "gn:name":"Diaomachang",
    "gn:population":0,
    "gn:timezone":"Asia/Shanghai",
    "iso:country":"CN",
    "name:zho_x_preferred":[
        "\u8c03\u9a6c\u573a"
    ],
    "wof:name":"Diaomachang",
    "wof:placetype":"locality"
},
  "geometry": {"coordinates":[120.7405,29.95887],"type":"Point"}
}