{
  "type": "Feature",
  "properties": {
    "gn:admin1_code":"15.0",
    "gn:asciiname":"Xiaolu",
    "gn:country_code":"CN",
    "gn:dem":1451,
    "gn:feature_class":"P",
    "gn:feature_code":"PPL",
    "gn:name":"Xiaolu",
    "gn:population":0,
    "gn:timezone":"Asia/Shanghai",
    "iso:country":"CN",
    "name:zho_x_preferred":[
        "\u5c0f\u82a6"
    ],
    "wof:name":"Xiaolu",
    "wof:placetype":"locality"
},
  "geometry": {"coordinates":[104.732,36.4372],"type":"Point"}
}