{
  "type": "Feature",
  "properties": {
    "gn:admin1_code":"18",
    "gn:asciiname":"Manaitun",
    "gn:country_code":"CN",
    "gn:dem":1388,
    "gn:feature_class":"P",
    "gn:feature_code":"PPL",
    "gn:name":"Manaitun",
    "gn:population":0,
    "gn:timezone":"Asia/Shanghai",
    "iso:country":"CN",
    "name:zho_x_preferred":[
        "\u9a6c\u4e43\u5c6f"
    ],
    "wof:name":"Manaitun",
    "wof:placetype":"locality"
},
  "geometry": {"coordinates":[105.173,25.5179],"type":"Point"}
}