{
  "type": "Feature",
  "properties": {
    "gn:admin1_code":"24.0",
    "gn:asciiname":"Shijiatan",
    "gn:country_code":"CN",
    "gn:dem":308,
    "gn:feature_class":"P",
    "gn:feature_code":"PPL",
    "gn:name":"Shijiatan",
    "gn:population":0,
    "gn:timezone":"Asia/Shanghai",
    "iso:country":"CN",
    "name:zho_x_preferred":[
        "\u53f2\u5bb6\u6ee9"
    ],
    "wof:name":"Shijiatan",
    "wof:placetype":"locality"
},
  "geometry": {"coordinates":[111.58053,34.87298],"type":"Point"}
}