{
  "type": "Feature",
  "properties": {
    "gn:admin1_code":"25",
    "gn:asciiname":"Nanmafang",
    "gn:country_code":"CN",
    "gn:dem":53,
    "gn:feature_class":"P",
    "gn:feature_code":"PPL",
    "gn:name":"Nanmafang",
    "gn:population":0,
    "gn:timezone":"Asia/Shanghai",
    "iso:country":"CN",
    "name:zho_x_preferred":[
        "\u5357\u9a6c\u574a"
    ],
    "wof:name":"Nanmafang",
    "wof:placetype":"locality"
},
  "geometry": {"coordinates":[118.32599999999999,36.8406],"type":"Point"}
}