{
  "type": "Feature",
  "properties": {
    "gn:admin1_code":"32.0",
    "gn:asciiname":"Taziwan",
    "gn:country_code":"CN",
    "gn:dem":592,
    "gn:feature_class":"P",
    "gn:feature_code":"PPL",
    "gn:name":"Taziwan",
    "gn:population":0,
    "gn:timezone":"Asia/Shanghai",
    "iso:country":"CN",
    "name:zho_x_preferred":[
        "\u5854\u5b50\u6e7e"
    ],
    "wof:name":"Taziwan",
    "wof:placetype":"locality"
},
  "geometry": {"coordinates":[106.38200000000001,31.7139],"type":"Point"}
}