{
  "type": "Feature",
  "properties": {
    "gn:admin1_code":"19.0",
    "gn:asciiname":"Xiwangjia Gangzi",
    "gn:country_code":"CN",
    "gn:dem":6,
    "gn:feature_class":"P",
    "gn:feature_code":"PPL",
    "gn:name":"Xiwangjia Gangzi",
    "gn:population":0,
    "gn:timezone":"Asia/Shanghai",
    "iso:country":"CN",
    "name:zho_x_preferred":[
        "\u897f\u738b\u5bb6\u5c97\u5b50"
    ],
    "wof:name":"Xiwangjia Gangzi",
    "wof:placetype":"locality"
},
  "geometry": {"coordinates":[122.08499999999999,41.1923],"type":"Point"}
}