{
  "type": "Feature",
  "properties": {
    "gn:admin1_code":"19",
    "gn:asciiname":"Dahujia Buzi",
    "gn:country_code":"CN",
    "gn:dem":329,
    "gn:feature_class":"P",
    "gn:feature_code":"PPL",
    "gn:name":"Dahujia Buzi",
    "gn:population":0,
    "gn:timezone":"Asia/Shanghai",
    "iso:country":"CN",
    "name:und_x_variant":[
        "Dahujia Puzi",
        "\u5927\u80e1\u5bb6\u5821\u5b50",
        "Dahujiabaozi",
        "Dahujia Buzi"
    ],
    "wof:name":"Dahujia Buzi",
    "wof:placetype":"locality"
},
  "geometry": {"coordinates":[124.42008,41.21621],"type":"Point"}
}