{
  "type": "Feature",
  "properties": {
    "gn:admin1_code":"10",
    "gn:asciiname":"Sa'erying",
    "gn:country_code":"CN",
    "gn:dem":738,
    "gn:feature_class":"P",
    "gn:feature_code":"PPL",
    "gn:name":"Sa\u2019erying",
    "gn:population":0,
    "gn:timezone":"Asia/Shanghai",
    "iso:country":"CN",
    "name:und_x_variant":[
        "Sa\u2019erying"
    ],
    "name:zho_x_preferred":[
        "\u6492\u4e8c\u8425"
    ],
    "wof:name":"Sa'erying",
    "wof:placetype":"locality"
},
  "geometry": {"coordinates":[116.56079,41.24721],"type":"Point"}
}