{
  "type": "Feature",
  "properties": {
    "gn:admin1_code":"11",
    "gn:asciiname":"Jiuzitang",
    "gn:country_code":"CN",
    "gn:dem":471,
    "gn:feature_class":"P",
    "gn:feature_code":"PPL",
    "gn:name":"Jiuzitang",
    "gn:population":0,
    "gn:timezone":"Asia/Shanghai",
    "iso:country":"CN",
    "name:zho_x_preferred":[
        "\u4e5d\u5b50\u5858"
    ],
    "wof:name":"Jiuzitang",
    "wof:placetype":"locality"
},
  "geometry": {"coordinates":[110.99695,27.42732],"type":"Point"}
}