{
  "type": "Feature",
  "properties": {
    "gn:admin1_code":"4.0",
    "gn:asciiname":"Yangchangcun",
    "gn:country_code":"CN",
    "gn:dem":0,
    "gn:feature_class":"P",
    "gn:feature_code":"PPL",
    "gn:name":"Yangchangcun",
    "gn:population":0,
    "gn:timezone":"Asia/Shanghai",
    "iso:country":"CN",
    "name:zho_x_preferred":[
        "\u6768\u573a\u6751"
    ],
    "wof:name":"Yangchangcun",
    "wof:placetype":"locality"
},
  "geometry": {"coordinates":[119.28931,34.5163],"type":"Point"}
}