{
  "type": "Feature",
  "properties": {
    "gn:admin1_code":"16.0",
    "gn:asciiname":"Fenglao",
    "gn:country_code":"CN",
    "gn:dem":312,
    "gn:feature_class":"P",
    "gn:feature_code":"PPL",
    "gn:name":"Fenglao",
    "gn:population":0,
    "gn:timezone":"Asia/Shanghai",
    "iso:country":"CN",
    "name:zho_x_preferred":[
        "\u98ce\u8001"
    ],
    "wof:name":"Fenglao",
    "wof:placetype":"locality"
},
  "geometry": {"coordinates":[106.18899999999999,24.3326],"type":"Point"}
}