{
  "type": "Feature",
  "properties": {
    "gn:admin1_code":"1.0",
    "gn:asciiname":"Xinqiao",
    "gn:country_code":"CN",
    "gn:dem":30,
    "gn:feature_class":"P",
    "gn:feature_code":"PPL",
    "gn:name":"Xinqiao",
    "gn:population":0,
    "gn:timezone":"Asia/Shanghai",
    "iso:country":"CN",
    "name:ceb_x_preferred":[
        "Xinqiao"
    ],
    "name:deu_x_preferred":[
        "Xinqiao"
    ],
    "name:swe_x_preferred":[
        "Xinqiao"
    ],
    "wof:name":"Xinqiao",
    "wof:placetype":"locality"
},
  "geometry": {"coordinates":[117.98333,30.93333],"type":"Point"}
}