{
  "type": "Feature",
  "properties": {
    "gn:admin1_code":"25",
    "gn:asciiname":"Zaobatou",
    "gn:country_code":"CN",
    "gn:dem":8,
    "gn:feature_class":"P",
    "gn:feature_code":"PPL",
    "gn:name":"Zaobatou",
    "gn:population":0,
    "gn:timezone":"Asia/Shanghai",
    "iso:country":"CN",
    "name:zho_x_preferred":[
        "\u7682\u575d\u5934"
    ],
    "wof:name":"Zaobatou",
    "wof:placetype":"locality"
},
  "geometry": {"coordinates":[118.548,37.6608],"type":"Point"}
}