{
  "type": "Feature",
  "properties": {
    "gn:admin1_code":"14.0",
    "gn:asciiname":"Zasa",
    "gn:country_code":"CN",
    "gn:dem":4618,
    "gn:feature_class":"P",
    "gn:feature_code":"PPL",
    "gn:name":"Zasa",
    "gn:population":0,
    "gn:timezone":"Asia/Urumqi",
    "iso:country":"CN",
    "name:bod_x_preferred":[
        "Zasa"
    ],
    "name:zho_x_preferred":[
        "Zhasa"
    ],
    "name:zho_x_variant":[
        "\u624e\u8428",
        "Bayi Gongshe",
        "\u516b\u4e00\u516c\u793e"
    ],
    "wof:name":"Zasa",
    "wof:placetype":"locality"
},
  "geometry": {"coordinates":[92.301,31.701],"type":"Point"}
}