{
  "type": "Feature",
  "properties": {
    "gn:admin1_code":"8.0",
    "gn:asciiname":"Heping Linchang",
    "gn:country_code":"CN",
    "gn:dem":485,
    "gn:feature_class":"P",
    "gn:feature_code":"PPLF",
    "gn:name":"Heping Linchang",
    "gn:population":0,
    "gn:timezone":"Asia/Shanghai",
    "iso:country":"CN",
    "name:und_x_variant":[
        "\u548c\u5e73\u6797\u573a"
    ],
    "wof:name":"Heping Linchang",
    "wof:placetype":"locality"
},
  "geometry": {"coordinates":[130.86112,44.15707],"type":"Point"}
}