{
  "type": "Feature",
  "properties": {
    "gn:admin1_code":"31.0",
    "gn:asciiname":"Dongfang Shifan Muchang",
    "gn:country_code":"CN",
    "gn:dem":39,
    "gn:feature_class":"P",
    "gn:feature_code":"PPLF",
    "gn:name":"Dongfang Shifan Muchang",
    "gn:population":0,
    "gn:timezone":"Asia/Shanghai",
    "iso:country":"CN",
    "name:und_x_variant":[
        "\u4e1c\u65b9\u793a\u8303\u7267\u573a"
    ],
    "wof:name":"Dongfang Shifan Muchang",
    "wof:placetype":"locality"
},
  "geometry": {"coordinates":[108.75636000000002,19.06162],"type":"Point"}
}