{
  "type": "Feature",
  "properties": {
    "gn:admin1_code":"01",
    "gn:asciiname":"Liujicun",
    "gn:country_code":"CN",
    "gn:dem":39,
    "gn:feature_class":"P",
    "gn:feature_code":"PPL",
    "gn:name":"Liujicun",
    "gn:population":0,
    "gn:timezone":"Asia/Shanghai",
    "iso:country":"CN",
    "name:und_x_variant":[
        "Chang-hsin-liu-chi",
        "Chang-hsin-liu",
        "Liuji",
        "Liujicun"
    ],
    "name:zho_x_preferred":[
        "\u6e9c\u96c6\u6751"
    ],
    "name:zho_x_variant":[
        "\u516d\u96c6\u6751"
    ],
    "wof:name":"Liujicun",
    "wof:placetype":"locality"
},
  "geometry": {"coordinates":[115.8321,33.70413],"type":"Point"}
}