{
  "type": "Feature",
  "properties": {
    "gn:admin1_code":"14.0",
    "gn:asciiname":"Ritama",
    "gn:country_code":"CN",
    "gn:dem":4188,
    "gn:feature_class":"P",
    "gn:feature_code":"PPL",
    "gn:name":"Ritama",
    "gn:population":0,
    "gn:timezone":"Asia/Urumqi",
    "iso:country":"CN",
    "name:zho_x_preferred":[
        "\u65e5\u5854\u9ebb"
    ],
    "wof:name":"Ritama",
    "wof:placetype":"locality"
},
  "geometry": {"coordinates":[96.90922,31.4934],"type":"Point"}
}