{
  "type": "Feature",
  "properties": {
    "gn:admin1_code":"30.0",
    "gn:asciiname":"Jiaotang",
    "gn:country_code":"CN",
    "gn:dem":21,
    "gn:feature_class":"P",
    "gn:feature_code":"PPL",
    "gn:name":"Jiaotang",
    "gn:population":0,
    "gn:timezone":"Asia/Shanghai",
    "iso:country":"CN",
    "name:zho_x_preferred":[
        "\u80f6\u5858"
    ],
    "wof:name":"Jiaotang",
    "wof:placetype":"locality"
},
  "geometry": {"coordinates":[116.55982,23.7136],"type":"Point"}
}