{
  "type": "Feature",
  "properties": {
    "gn:admin1_code":"8.0",
    "gn:asciiname":"Xilincun",
    "gn:country_code":"CN",
    "gn:dem":59,
    "gn:feature_class":"P",
    "gn:feature_code":"PPL",
    "gn:name":"Xilincun",
    "gn:population":0,
    "gn:timezone":"Asia/Shanghai",
    "iso:country":"CN",
    "name:zho_x_preferred":[
        "\u897f\u6797\u6751"
    ],
    "wof:name":"Xilincun",
    "wof:placetype":"locality"
},
  "geometry": {"coordinates":[132.25783999999999,46.9973],"type":"Point"}
}