{
  "type": "Feature",
  "properties": {
    "gn:admin1_code":"11",
    "gn:asciiname":"Liujiahu Nongchang",
    "gn:country_code":"CN",
    "gn:dem":31,
    "gn:feature_class":"P",
    "gn:feature_code":"PPLF",
    "gn:name":"Liujiahu Nongchang",
    "gn:population":0,
    "gn:timezone":"Asia/Shanghai",
    "iso:country":"CN",
    "wof:name":"Liujiahu Nongchang",
    "wof:placetype":"locality"
},
  "geometry": {"coordinates":[112.57889,28.83],"type":"Point"}
}