{
  "type": "Feature",
  "properties": {
    "gn:admin1_code":"32.0",
    "gn:asciiname":"Feigeze",
    "gn:country_code":"CN",
    "gn:dem":2083,
    "gn:feature_class":"P",
    "gn:feature_code":"PPL",
    "gn:name":"Feigeze",
    "gn:population":0,
    "gn:timezone":"Asia/Shanghai",
    "iso:country":"CN",
    "name:zho_x_preferred":[
        "\u83f2\u5404\u5219"
    ],
    "wof:name":"Feigeze",
    "wof:placetype":"locality"
},
  "geometry": {"coordinates":[102.77186,27.31186],"type":"Point"}
}