{
  "type": "Feature",
  "properties": {
    "gn:admin1_code":"26",
    "gn:asciiname":"Jijiadian",
    "gn:country_code":"CN",
    "gn:dem":561,
    "gn:feature_class":"P",
    "gn:feature_code":"PPL",
    "gn:name":"Jijiadian",
    "gn:population":0,
    "gn:timezone":"Asia/Shanghai",
    "iso:country":"CN",
    "wof:name":"Jijiadian",
    "wof:placetype":"locality"
},
  "geometry": {"coordinates":[107.29028,34.33972],"type":"Point"}
}