{
  "type": "Feature",
  "properties": {
    "gn:admin1_code":"8.0",
    "gn:asciiname":"Gongqing Ershiwudui",
    "gn:country_code":"CN",
    "gn:dem":99,
    "gn:feature_class":"P",
    "gn:feature_code":"PPLF",
    "gn:name":"Gongqing Ershiwudui",
    "gn:population":0,
    "gn:timezone":"Asia/Shanghai",
    "iso:country":"CN",
    "name:zho_x_preferred":[
        "\u5171\u9752\u4e8c\u5341\u4e94\u961f"
    ],
    "wof:name":"Gongqing Ershiwudui",
    "wof:placetype":"locality"
},
  "geometry": {"coordinates":[130.63371000000001,47.55931],"type":"Point"}
}