{
  "type": "Feature",
  "properties": {
    "gn:admin1_code":"29.0",
    "gn:asciiname":"Daqing",
    "gn:country_code":"CN",
    "gn:dem":1749,
    "gn:feature_class":"P",
    "gn:feature_code":"PPL",
    "gn:name":"Daqing",
    "gn:population":0,
    "gn:timezone":"Asia/Shanghai",
    "iso:country":"CN",
    "name:afr_x_preferred":[
        "Daqing"
    ],
    "name:ara_x_preferred":[
        "\u062f\u0627\u062a\u0634\u064a\u0646\u063a"
    ],
    "name:bak_x_preferred":[
        "\u0414\u0430\u0446\u0438\u043d"
    ],
    "name:bel_x_preferred":[
        "\u0414\u0430\u0446\u044b\u043d"
    ],
    "name:cdo_x_preferred":[
        "D\u00e2i-k\u00e9ng"
    ],
    "name:ces_x_preferred":[
        "Ta-\u010dching"
    ],
    "name:dan_x_preferred":[
        "Daqing"
    ],
    "name:deu_x_preferred":[
        "Daqing"
    ],
    "name:epo_x_preferred":[
        "Dacin"
    ],
    "name:eus_x_preferred":[
        "Daqing"
    ],
    "name:fas_x_preferred":[
        "\u062f\u0627\u06a9\u06cc\u0646\u06af"
    ],
    "name:fin_x_preferred":[
        "Daqing"
    ],
    "name:fra_x_preferred":[
        "Daqing"
    ],
    "name:heb_x_preferred":[
        "\u05d3\u05d0\u05d2\u05d9\u05e0\u05d2"
    ],
    "name:ind_x_preferred":[
        "Daqing"
    ],
    "name:ita_x_preferred":[
        "Daqing"
    ],
    "name:jpn_x_preferred":[
        "\u5927\u6176\u5e02"
    ],
    "name:kik_x_preferred":[
        "Daqing"
    ],
    "name:kor_x_preferred":[
        "\ub2e4\uce6d\uc2dc"
    ],
    "name:lit_x_preferred":[
        "Da\u010dingas"
    ],
    "name:mlg_x_preferred":[
        "Daqing"
    ],
    "name:mon_x_preferred":[
        "\u0414\u0430\u0447\u0438\u043d"
    ],
    "name:nld_x_preferred":[
        "Daqing"
    ],
    "name:nno_x_preferred":[
        "Daqing"
    ],
    "name:nor_x_preferred":[
        "Daqing"
    ],
    "name:pam_x_preferred":[
        "Daqing"
    ],
    "name:pol_x_preferred":[
        "Daqing"
    ],
    "name:por_x_preferred":[
        "Daqing"
    ],
    "name:rus_x_preferred":[
        "\u0414\u0430\u0446\u0438\u043d"
    ],
    "name:spa_x_preferred":[
        "Daqing"
    ],
    "name:swe_x_preferred":[
        "Daqing"
    ],
    "name:tgl_x_preferred":[
        "Daqing"
    ],
    "name:tur_x_preferred":[
        "Daqing"
    ],
    "name:uig_x_preferred":[
        "\u062f\u0627\u0686\u0649\u06ad \u0634\u06d5\u06be\u0649\u0631"
    ],
    "name:ukr_x_preferred":[
        "\u0414\u0430\u0446\u0456\u043d"
    ],
    "name:urd_x_preferred":[
        "\u062f\u0627\u0686\u06cc\u0646\u06af"
    ],
    "name:vie_x_preferred":[
        "\u0110\u1ea1i Kh\u00e1nh"
    ],
    "name:war_x_preferred":[
        "Daqing"
    ],
    "name:wuu_x_preferred":[
        "\u5927\u5e86\u5e02"
    ],
    "name:zho_x_preferred":[
        "\u5927\u7b90"
    ],
    "name:zho_x_variant":[
        "\u5927\u5e86\u5e02"
    ],
    "wof:name":"Daqing",
    "wof:placetype":"locality"
},
  "geometry": {"coordinates":[101.322,26.4291],"type":"Point"}
}