{
  "type": "Feature",
  "properties": {
    "gn:country":"CN",
    "gn:fcode":"ADM3",
    "gn:population":0,
    "iso:country":"CN",
    "name:und_x_variant":[
        "Changning Xian"
    ],
    "name:zho_x_preferred":[
        "\u5e38\u5b81\u5e02"
    ],
    "name:zho_x_variant":[
        "\u5e38\u5b81"
    ],
    "qs:name":"Changning Shi",
    "qs:photos_9r":0,
    "qs:photos_sr":0,
    "qs:pop_sr":"0",
    "wof:name":"Changning Shi",
    "wof:placetype":"localadmin",
    "wof:population":0
},
  "geometry": {"coordinates":[112.42737,26.32277],"type":"Point"}
}