{
  "type": "Feature",
  "properties": {
    "gn:admin1_code":"9.0",
    "gn:asciiname":"Xiazhouwan",
    "gn:country_code":"CN",
    "gn:dem":138,
    "gn:feature_class":"P",
    "gn:feature_code":"PPL",
    "gn:name":"Xiazhouwan",
    "gn:population":0,
    "gn:timezone":"Asia/Shanghai",
    "iso:country":"CN",
    "name:zho_x_preferred":[
        "\u4e0b\u5468\u6e7e"
    ],
    "wof:name":"Xiazhouwan",
    "wof:placetype":"locality"
},
  "geometry": {"coordinates":[113.94370000000001,32.56171],"type":"Point"}
}