{
  "type": "Feature",
  "properties": {
    "gn:admin1_code":"4.0",
    "gn:asciiname":"Dajiangqiao",
    "gn:country_code":"CN",
    "gn:dem":8,
    "gn:feature_class":"P",
    "gn:feature_code":"PPL",
    "gn:name":"Dajiangqiao",
    "gn:population":0,
    "gn:timezone":"Asia/Shanghai",
    "iso:country":"CN",
    "name:zho_x_preferred":[
        "\u5927\u6c5f\u6865"
    ],
    "wof:name":"Dajiangqiao",
    "wof:placetype":"locality"
},
  "geometry": {"coordinates":[119.56292000000001,31.97376],"type":"Point"}
}