{
  "type": "Feature",
  "properties": {
    "iso:country":"CN",
    "qs:name":"\u9686\u52a1",
    "qs:name_adm0":"\u4e2d\u570b",
    "qs:name_adm1":"\u9752\u6d77\u7701",
    "qs:photos":490,
    "qs:photos_1k":99,
    "qs:photos_9k":2,
    "qs:photos_9r":5,
    "qs:photos_all":490,
    "qs:photos_sr":7,
    "qs:placetype":"Town",
    "qs:pop_sr":"0",
    "wof:name":"\u9686\u52a1",
    "wof:placetype":"locality"
},
  "geometry": {"coordinates":[102.009773,35.508823],"type":"Point"}
}