{
  "type": "Feature",
  "properties": {
    "gn:admin1_code":"10.0",
    "gn:asciiname":"Xihouzhuang",
    "gn:country_code":"CN",
    "gn:dem":5,
    "gn:feature_class":"P",
    "gn:feature_code":"PPL",
    "gn:name":"Xihouzhuang",
    "gn:population":0,
    "gn:timezone":"Asia/Shanghai",
    "iso:country":"CN",
    "name:zho_x_preferred":[
        "\u897f\u4faf\u5e84"
    ],
    "wof:name":"Xihouzhuang",
    "wof:placetype":"locality"
},
  "geometry": {"coordinates":[117.607,38.2162],"type":"Point"}
}