{
  "type": "Feature",
  "properties": {
    "gn:admin1_code":"3.0",
    "gn:asciiname":"Guilong",
    "gn:country_code":"CN",
    "gn:dem":174,
    "gn:feature_class":"P",
    "gn:feature_code":"PPL",
    "gn:name":"Guilong",
    "gn:population":0,
    "gn:timezone":"Asia/Shanghai",
    "iso:country":"CN",
    "name:und_x_variant":[
        "\u6842\u9f99"
    ],
    "wof:name":"Guilong",
    "wof:placetype":"locality"
},
  "geometry": {"coordinates":[115.63239,25.95832],"type":"Point"}
}