{
  "type": "Feature",
  "properties": {
    "gn:admin1_code":"32.0",
    "gn:asciiname":"Cunkecun",
    "gn:country_code":"CN",
    "gn:dem":3789,
    "gn:feature_class":"P",
    "gn:feature_code":"PPL",
    "gn:name":"Cunkecun",
    "gn:population":0,
    "gn:timezone":"Asia/Shanghai",
    "iso:country":"CN",
    "name:zho_x_preferred":[
        "\u6751\u67ef\u6751"
    ],
    "wof:name":"Cunkecun",
    "wof:placetype":"locality"
},
  "geometry": {"coordinates":[99.4363,32.005],"type":"Point"}
}