{
  "type": "Feature",
  "properties": {
    "gn:admin1_code":"26.0",
    "gn:asciiname":"Baojiagoucun",
    "gn:country_code":"CN",
    "gn:dem":912,
    "gn:feature_class":"P",
    "gn:feature_code":"PPL",
    "gn:name":"Baojiagoucun",
    "gn:population":0,
    "gn:timezone":"Asia/Shanghai",
    "iso:country":"CN",
    "name:zho_x_preferred":[
        "\u9c8d\u5bb6\u6c9f\u6751"
    ],
    "wof:name":"Baojiagoucun",
    "wof:placetype":"locality"
},
  "geometry": {"coordinates":[110.111,37.05444],"type":"Point"}
}