{
  "type": "Feature",
  "properties": {
    "gn:admin1_code":"16.0",
    "gn:asciiname":"Longkang",
    "gn:country_code":"CN",
    "gn:dem":545,
    "gn:feature_class":"P",
    "gn:feature_code":"PPL",
    "gn:name":"Longkang",
    "gn:population":0,
    "gn:timezone":"Asia/Shanghai",
    "iso:country":"CN",
    "name:zho_x_preferred":[
        "\u9f99\u4ea2"
    ],
    "name:zho_x_variant":[
        "\u9f99\u4ea2\u9547"
    ],
    "wof:name":"Longkang",
    "wof:placetype":"locality"
},
  "geometry": {"coordinates":[107.776,24.4205],"type":"Point"}
}