{
  "type": "Feature",
  "properties": {
    "gn:admin1_code":"7.0",
    "gn:asciiname":"Qingzhoukeng",
    "gn:country_code":"CN",
    "gn:dem":344,
    "gn:feature_class":"P",
    "gn:feature_code":"PPL",
    "gn:name":"Qingzhoukeng",
    "gn:population":0,
    "gn:timezone":"Asia/Shanghai",
    "iso:country":"CN",
    "name:und_x_variant":[
        "\u9752\u5dde\u5751"
    ],
    "name:zho_x_preferred":[
        "\u9752\u5dde\u5751"
    ],
    "wof:name":"Qingzhoukeng",
    "wof:placetype":"locality"
},
  "geometry": {"coordinates":[116.74296,26.2035],"type":"Point"}
}