{
  "type": "Feature",
  "properties": {
    "gn:admin1_code":"19.0",
    "gn:asciiname":"Jiayun",
    "gn:country_code":"CN",
    "gn:dem":15,
    "gn:feature_class":"P",
    "gn:feature_code":"PPL",
    "gn:name":"Jiayun",
    "gn:population":0,
    "gn:timezone":"Asia/Shanghai",
    "iso:country":"CN",
    "name:und_x_variant":[
        "\u7532\u4e91"
    ],
    "name:zho_x_preferred":[
        "\u7532\u4e91"
    ],
    "wof:name":"Jiayun",
    "wof:placetype":"locality"
},
  "geometry": {"coordinates":[123.78494000000001,40.07483],"type":"Point"}
}