{
  "type": "Feature",
  "properties": {
    "gn:admin1_code":"12.0",
    "gn:asciiname":"Bianpu",
    "gn:country_code":"CN",
    "gn:dem":173,
    "gn:feature_class":"P",
    "gn:feature_code":"PPL",
    "gn:name":"Bianpu",
    "gn:population":0,
    "gn:timezone":"Asia/Shanghai",
    "iso:country":"CN",
    "name:zho_x_preferred":[
        "\u8fb9\u94fa"
    ],
    "wof:name":"Bianpu",
    "wof:placetype":"locality"
},
  "geometry": {"coordinates":[115.38928,31.22263],"type":"Point"}
}