{
  "type": "Feature",
  "properties": {
    "gn:admin1_code":"4.0",
    "gn:asciiname":"Wuyeling",
    "gn:country_code":"CN",
    "gn:dem":26,
    "gn:feature_class":"P",
    "gn:feature_code":"PPL",
    "gn:name":"Wuyeling",
    "gn:population":0,
    "gn:timezone":"Asia/Shanghai",
    "iso:country":"CN",
    "name:zho_x_preferred":[
        "\u5434\u51b6\u5cad"
    ],
    "wof:name":"Wuyeling",
    "wof:placetype":"locality"
},
  "geometry": {"coordinates":[119.42592,31.37441],"type":"Point"}
}