{
  "type": "Feature",
  "properties": {
    "gn:admin1_code":"8.0",
    "gn:asciiname":"Laodongtou",
    "gn:country_code":"CN",
    "gn:dem":206,
    "gn:feature_class":"P",
    "gn:feature_code":"PPL",
    "gn:name":"Laodongtou",
    "gn:population":0,
    "gn:timezone":"Asia/Shanghai",
    "iso:country":"CN",
    "name:zho_x_preferred":[
        "\u8001\u8463\u5934"
    ],
    "wof:name":"Laodongtou",
    "wof:placetype":"locality"
},
  "geometry": {"coordinates":[124.53942000000001,48.56924],"type":"Point"}
}