{
  "type": "Feature",
  "properties": {
    "gn:admin1_code":"7.0",
    "gn:asciiname":"Wengdi",
    "gn:country_code":"CN",
    "gn:dem":445,
    "gn:feature_class":"P",
    "gn:feature_code":"PPL",
    "gn:name":"Wengdi",
    "gn:population":0,
    "gn:timezone":"Asia/Shanghai",
    "iso:country":"CN",
    "name:und_x_variant":[
        "\u7fc1\u5730"
    ],
    "name:zho_x_preferred":[
        "\u7fc1\u5730"
    ],
    "wof:name":"Wengdi",
    "wof:placetype":"locality"
},
  "geometry": {"coordinates":[117.11602999999999,26.47979],"type":"Point"}
}