{
  "type": "Feature",
  "properties": {
    "gn:admin1_code":"32.0",
    "gn:asciiname":"Bu'erjiao",
    "gn:country_code":"CN",
    "gn:dem":2695,
    "gn:feature_class":"P",
    "gn:feature_code":"PPL",
    "gn:name":"Bu\u2019erjiao",
    "gn:population":0,
    "gn:timezone":"Asia/Shanghai",
    "iso:country":"CN",
    "name:und_x_variant":[
        "Bu\u2019erjiao"
    ],
    "name:zho_x_preferred":[
        "\u5e03\u5c14\u811a"
    ],
    "wof:name":"Bu'erjiao",
    "wof:placetype":"locality"
},
  "geometry": {"coordinates":[100.872,27.7052],"type":"Point"}
}