{
  "type": "Feature",
  "properties": {
    "gn:admin1_code":"2.0",
    "gn:asciiname":"Huangshengtang",
    "gn:country_code":"CN",
    "gn:dem":69,
    "gn:feature_class":"P",
    "gn:feature_code":"PPL",
    "gn:name":"Huangshengtang",
    "gn:population":0,
    "gn:timezone":"Asia/Shanghai",
    "iso:country":"CN",
    "name:zho_x_preferred":[
        "\u51f0\u5347\u5858"
    ],
    "wof:name":"Huangshengtang",
    "wof:placetype":"locality"
},
  "geometry": {"coordinates":[120.0797,29.45676],"type":"Point"}
}