{
  "type": "Feature",
  "properties": {
    "gn:admin1_code":"14.0",
    "gn:asciiname":"Caiqinka",
    "gn:country_code":"CN",
    "gn:dem":4211,
    "gn:feature_class":"P",
    "gn:feature_code":"PPL",
    "gn:name":"Caiqinka",
    "gn:population":0,
    "gn:timezone":"Asia/Urumqi",
    "iso:country":"CN",
    "name:zho_x_preferred":[
        "\u624d\u94a6\u5361"
    ],
    "wof:name":"Caiqinka",
    "wof:placetype":"locality"
},
  "geometry": {"coordinates":[93.95363,31.16287],"type":"Point"}
}