{
  "type": "Feature",
  "properties": {
    "gn:admin1_code":"32.0",
    "gn:asciiname":"Fangjia Liangzi",
    "gn:country_code":"CN",
    "gn:dem":454,
    "gn:feature_class":"P",
    "gn:feature_code":"PPL",
    "gn:name":"Fangjia Liangzi",
    "gn:population":0,
    "gn:timezone":"Asia/Shanghai",
    "iso:country":"CN",
    "name:zho_x_preferred":[
        "\u65b9\u5bb6\u6881\u5b50"
    ],
    "wof:name":"Fangjia Liangzi",
    "wof:placetype":"locality"
},
  "geometry": {"coordinates":[106.68634,30.61356],"type":"Point"}
}