{
  "type": "Feature",
  "properties": {
    "gn:admin1_code":"07",
    "gn:asciiname":"Zhoushan",
    "gn:country_code":"CN",
    "gn:dem":408,
    "gn:feature_class":"P",
    "gn:feature_code":"PPL",
    "gn:name":"Zhoushan",
    "gn:population":0,
    "gn:timezone":"Asia/Shanghai",
    "iso:country":"CN",
    "name:und_x_variant":[
        "Zhoujiashan",
        "Zhoushan"
    ],
    "name:zho_x_preferred":[
        "\u5468\u5c71"
    ],
    "wof:name":"Zhoushan",
    "wof:placetype":"locality"
},
  "geometry": {"coordinates":[120.38802,27.29769000000001],"type":"Point"}
}