{
  "type": "Feature",
  "properties": {
    "gn:admin1_code":"8.0",
    "gn:asciiname":"Wengudacun",
    "gn:country_code":"CN",
    "gn:dem":156,
    "gn:feature_class":"P",
    "gn:feature_code":"PPL",
    "gn:name":"Wengudacun",
    "gn:population":0,
    "gn:timezone":"Asia/Shanghai",
    "iso:country":"CN",
    "name:zho_x_preferred":[
        "\u6587\u56fa\u8fbe\u6751"
    ],
    "wof:name":"Wengudacun",
    "wof:placetype":"locality"
},
  "geometry": {"coordinates":[123.54288,47.57289],"type":"Point"}
}