{
  "type": "Feature",
  "properties": {
    "gn:admin1_code":"8.0",
    "gn:asciiname":"Wusicun",
    "gn:country_code":"CN",
    "gn:dem":257,
    "gn:feature_class":"P",
    "gn:feature_code":"PPL",
    "gn:name":"Wusicun",
    "gn:population":0,
    "gn:timezone":"Asia/Shanghai",
    "iso:country":"CN",
    "name:zho_x_preferred":[
        "\u4e94\u56db\u6751"
    ],
    "wof:name":"Wusicun",
    "wof:placetype":"locality"
},
  "geometry": {"coordinates":[125.1836,48.74084000000001],"type":"Point"}
}