{
  "type": "Feature",
  "properties": {
    "gn:admin1_code":"32.0",
    "gn:asciiname":"Niubaoshan",
    "gn:country_code":"CN",
    "gn:dem":971,
    "gn:feature_class":"P",
    "gn:feature_code":"PPL",
    "gn:name":"Niubaoshan",
    "gn:population":0,
    "gn:timezone":"Asia/Shanghai",
    "iso:country":"CN",
    "name:zho_x_preferred":[
        "\u725b\u5b9d\u5c71"
    ],
    "wof:name":"Niubaoshan",
    "wof:placetype":"locality"
},
  "geometry": {"coordinates":[103.4709,28.99284],"type":"Point"}
}