{
  "type": "Feature",
  "properties": {
    "gn:admin1_code":"32.0",
    "gn:asciiname":"Heyanba",
    "gn:country_code":"CN",
    "gn:dem":336,
    "gn:feature_class":"P",
    "gn:feature_code":"PPL",
    "gn:name":"Heyanba",
    "gn:population":0,
    "gn:timezone":"Asia/Shanghai",
    "iso:country":"CN",
    "name:zho_x_preferred":[
        "\u6cb3\u5830\u575d"
    ],
    "wof:name":"Heyanba",
    "wof:placetype":"locality"
},
  "geometry": {"coordinates":[107.06131999999999,30.42212],"type":"Point"}
}