{
  "type": "Feature",
  "properties": {
    "gn:admin1_code":"9.0",
    "gn:asciiname":"Sunhetou",
    "gn:country_code":"CN",
    "gn:dem":170,
    "gn:feature_class":"P",
    "gn:feature_code":"PPL",
    "gn:name":"Sunhetou",
    "gn:population":0,
    "gn:timezone":"Asia/Shanghai",
    "iso:country":"CN",
    "name:zho_x_preferred":[
        "\u5b59\u6cb3\u5934"
    ],
    "wof:name":"Sunhetou",
    "wof:placetype":"locality"
},
  "geometry": {"coordinates":[111.76165,32.87294],"type":"Point"}
}