{
  "type": "Feature",
  "properties": {
    "gn:admin1_code":"4.0",
    "gn:asciiname":"Sanxin",
    "gn:country_code":"CN",
    "gn:dem":10,
    "gn:feature_class":"P",
    "gn:feature_code":"PPL",
    "gn:name":"Sanxin",
    "gn:population":0,
    "gn:timezone":"Asia/Shanghai",
    "iso:country":"CN",
    "name:zho_x_preferred":[
        "\u4e09\u65b0"
    ],
    "wof:name":"Sanxin",
    "wof:placetype":"locality"
},
  "geometry": {"coordinates":[118.80333,33.99298],"type":"Point"}
}