{
  "type": "Feature",
  "properties": {
    "gn:admin1_code":"16.0",
    "gn:asciiname":"Xiachangdong",
    "gn:country_code":"CN",
    "gn:dem":286,
    "gn:feature_class":"P",
    "gn:feature_code":"PPL",
    "gn:name":"Xiachangdong",
    "gn:population":0,
    "gn:timezone":"Asia/Shanghai",
    "iso:country":"CN",
    "name:zho_x_preferred":[
        "\u4e0b\u957f\u5cd2"
    ],
    "wof:name":"Xiachangdong",
    "wof:placetype":"locality"
},
  "geometry": {"coordinates":[108.03400000000001,24.7759],"type":"Point"}
}