{
  "type": "Feature",
  "properties": {
    "gn:admin1_code":"24.0",
    "gn:asciiname":"Yang'erta",
    "gn:country_code":"CN",
    "gn:dem":1050,
    "gn:feature_class":"P",
    "gn:feature_code":"PPL",
    "gn:name":"Yang\u2019erta",
    "gn:population":0,
    "gn:timezone":"Asia/Shanghai",
    "iso:country":"CN",
    "name:und_x_variant":[
        "Yang\u2019erta"
    ],
    "name:zho_x_preferred":[
        "\u9633\u5c14\u5854"
    ],
    "wof:name":"Yang'erta",
    "wof:placetype":"locality"
},
  "geometry": {"coordinates":[111.34405,39.41711],"type":"Point"}
}