{
  "type": "Feature",
  "properties": {
    "gn:admin1_code":"29.0",
    "gn:asciiname":"Guangsong",
    "gn:country_code":"CN",
    "gn:dem":1763,
    "gn:feature_class":"P",
    "gn:feature_code":"PPL",
    "gn:name":"Guangsong",
    "gn:population":0,
    "gn:timezone":"Asia/Shanghai",
    "iso:country":"CN",
    "name:zho_x_preferred":[
        "\u5e7f\u5b8b"
    ],
    "wof:name":"Guangsong",
    "wof:placetype":"locality"
},
  "geometry": {"coordinates":[97.8382,24.5123],"type":"Point"}
}