{
  "type": "Feature",
  "properties": {
    "gn:admin1_code":"3.0",
    "gn:asciiname":"Gangzikou",
    "gn:country_code":"CN",
    "gn:dem":16,
    "gn:feature_class":"P",
    "gn:feature_code":"PPL",
    "gn:name":"Gangzikou",
    "gn:population":0,
    "gn:timezone":"Asia/Shanghai",
    "iso:country":"CN",
    "name:und_x_variant":[
        "\u6e2f\u5b50\u53e3"
    ],
    "wof:name":"Gangzikou",
    "wof:placetype":"locality"
},
  "geometry": {"coordinates":[116.03084,28.97878],"type":"Point"}
}