{
  "type": "Feature",
  "properties": {
    "gn:admin1_code":"11.0",
    "gn:asciiname":"Sujia Laowan",
    "gn:country_code":"CN",
    "gn:dem":142,
    "gn:feature_class":"P",
    "gn:feature_code":"PPL",
    "gn:name":"Sujia Laowan",
    "gn:population":0,
    "gn:timezone":"Asia/Shanghai",
    "iso:country":"CN",
    "name:zho_x_preferred":[
        "\u82cf\u5bb6\u8001\u6e7e"
    ],
    "wof:name":"Sujia Laowan",
    "wof:placetype":"locality"
},
  "geometry": {"coordinates":[113.48014999999999,26.69725],"type":"Point"}
}