{
  "type": "Feature",
  "properties": {
    "gn:admin1_code":"1.0",
    "gn:asciiname":"Limiaocun",
    "gn:country_code":"CN",
    "gn:dem":32,
    "gn:feature_class":"P",
    "gn:feature_code":"PPL",
    "gn:name":"Limiaocun",
    "gn:population":0,
    "gn:timezone":"Asia/Shanghai",
    "iso:country":"CN",
    "name:zho_x_preferred":[
        "\u674e\u5e99\u6751"
    ],
    "wof:name":"Limiaocun",
    "wof:placetype":"locality"
},
  "geometry": {"coordinates":[116.12591999999999,32.66168],"type":"Point"}
}