{
  "type": "Feature",
  "properties": {
    "gn:admin1_code":"7.0",
    "gn:asciiname":"Yusanpu",
    "gn:country_code":"CN",
    "gn:dem":395,
    "gn:feature_class":"P",
    "gn:feature_code":"PPL",
    "gn:name":"Yusanpu",
    "gn:population":0,
    "gn:timezone":"Asia/Shanghai",
    "iso:country":"CN",
    "name:zho_x_preferred":[
        "\u96e8\u4f1e\u94fa"
    ],
    "wof:name":"Yusanpu",
    "wof:placetype":"locality"
},
  "geometry": {"coordinates":[118.34822,28.06425],"type":"Point"}
}