{
  "type": "Feature",
  "properties": {
    "gn:admin1_code":"19.0",
    "gn:asciiname":"Xiamadicun",
    "gn:country_code":"CN",
    "gn:dem":351,
    "gn:feature_class":"P",
    "gn:feature_code":"PPL",
    "gn:name":"Xiamadicun",
    "gn:population":0,
    "gn:timezone":"Asia/Shanghai",
    "iso:country":"CN",
    "name:zho_x_preferred":[
        "\u4e0b\u9ebb\u5730\u6751"
    ],
    "wof:name":"Xiamadicun",
    "wof:placetype":"locality"
},
  "geometry": {"coordinates":[120.21429000000001,41.56253],"type":"Point"}
}