{
  "type": "Feature",
  "properties": {
    "gn:admin1_code":"30",
    "gn:asciiname":"Sheqian",
    "gn:country_code":"CN",
    "gn:dem":163,
    "gn:feature_class":"P",
    "gn:feature_code":"PPL",
    "gn:name":"Sheqian",
    "gn:population":0,
    "gn:timezone":"Asia/Shanghai",
    "iso:country":"CN",
    "name:und_x_variant":[
        "\u793e\u524d",
        "Sheqian"
    ],
    "wof:name":"Sheqian",
    "wof:placetype":"locality"
},
  "geometry": {"coordinates":[115.65822,24.05597],"type":"Point"}
}