{
  "type": "Feature",
  "properties": {
    "gn:admin1_code":"15.0",
    "gn:asciiname":"Da'erzang",
    "gn:country_code":"CN",
    "gn:dem":2924,
    "gn:feature_class":"P",
    "gn:feature_code":"PPL",
    "gn:name":"Da\u2019erzang",
    "gn:population":0,
    "gn:timezone":"Asia/Shanghai",
    "iso:country":"CN",
    "name:und_x_variant":[
        "Da\u2019erzang",
        "\u8fbe\u5c14\u85cf"
    ],
    "wof:name":"Da'erzang",
    "wof:placetype":"locality"
},
  "geometry": {"coordinates":[102.72337,35.22944000000001],"type":"Point"}
}