{
  "type": "Feature",
  "properties": {
    "gn:admin1_code":"23.0",
    "gn:asciiname":"Waiqinzhai",
    "gn:country_code":"CN",
    "gn:dem":6,
    "gn:feature_class":"P",
    "gn:feature_code":"PPL",
    "gn:name":"Waiqinzhai",
    "gn:population":0,
    "gn:timezone":"Asia/Shanghai",
    "iso:country":"CN",
    "name:zho_x_preferred":[
        "Waiqinzhai"
    ],
    "name:zho_x_variant":[
        "\u5916\u79e6\u5b85"
    ],
    "wof:name":"Waiqinzhai",
    "wof:placetype":"locality"
},
  "geometry": {"coordinates":[121.56108999999999,31.02271],"type":"Point"}
}