{
  "type": "Feature",
  "properties": {
    "gn:admin1_code":"24.0",
    "gn:asciiname":"Shanggang",
    "gn:country_code":"CN",
    "gn:dem":813,
    "gn:feature_class":"P",
    "gn:feature_code":"PPL",
    "gn:name":"Shanggang",
    "gn:population":0,
    "gn:timezone":"Asia/Shanghai",
    "iso:country":"CN",
    "name:zho_x_preferred":[
        "\u4e0a\u6e2f"
    ],
    "wof:name":"Shanggang",
    "wof:placetype":"locality"
},
  "geometry": {"coordinates":[113.60325,36.40239],"type":"Point"}
}