{
  "type": "Feature",
  "properties": {
    "gn:admin1_code":"1.0",
    "gn:asciiname":"Anjiping",
    "gn:country_code":"CN",
    "gn:dem":503,
    "gn:feature_class":"P",
    "gn:feature_code":"PPL",
    "gn:name":"Anjiping",
    "gn:population":0,
    "gn:timezone":"Asia/Shanghai",
    "iso:country":"CN",
    "name:zho_x_preferred":[
        "\u5b89\u57fa\u576a"
    ],
    "wof:name":"Anjiping",
    "wof:placetype":"locality"
},
  "geometry": {"coordinates":[118.85720000000001,30.30433],"type":"Point"}
}