{
  "type": "Feature",
  "properties": {
    "gn:admin1_code":"11",
    "gn:asciiname":"Sheshiqiao",
    "gn:country_code":"CN",
    "gn:dem":63,
    "gn:feature_class":"P",
    "gn:feature_code":"PPLA4",
    "gn:name":"Sheshiqiao",
    "gn:population":0,
    "gn:timezone":"Asia/Shanghai",
    "iso:country":"CN",
    "name:und_x_variant":[
        "Y\u00fc-shih-ch\u2019iao",
        "She-shih-ch\u2019iao",
        "Sheshiqiao",
        "\u4f58\u5e02\u6865",
        "Sheshiqiao Zhen",
        "\u4f58\u5e02\u6865\u9547"
    ],
    "wof:name":"Sheshiqiao",
    "wof:placetype":"locality"
},
  "geometry": {"coordinates":[111.51815999999999,29.44305],"type":"Point"}
}