{
  "type": "Feature",
  "properties": {
    "gn:admin1_code":"24.0",
    "gn:asciiname":"Jianhecun",
    "gn:country_code":"CN",
    "gn:dem":1294,
    "gn:feature_class":"P",
    "gn:feature_code":"PPL",
    "gn:name":"Jianhecun",
    "gn:population":0,
    "gn:timezone":"Asia/Shanghai",
    "iso:country":"CN",
    "name:zho_x_preferred":[
        "\u7bad\u6cb3\u6751"
    ],
    "wof:name":"Jianhecun",
    "wof:placetype":"locality"
},
  "geometry": {"coordinates":[113.55311,38.20464000000001],"type":"Point"}
}