{
  "type": "Feature",
  "properties": {
    "gn:admin1_code":"10.0",
    "gn:asciiname":"Mazhuangzi",
    "gn:country_code":"CN",
    "gn:dem":7,
    "gn:feature_class":"P",
    "gn:feature_code":"PPL",
    "gn:name":"Mazhuangzi",
    "gn:population":0,
    "gn:timezone":"Asia/Shanghai",
    "iso:country":"CN",
    "name:zho_x_preferred":[
        "\u9a6c\u5e84\u5b50"
    ],
    "wof:name":"Mazhuangzi",
    "wof:placetype":"locality"
},
  "geometry": {"coordinates":[117.41500000000001,38.0298],"type":"Point"}
}