{
  "type": "Feature",
  "properties": {
    "gn:admin1_code":"14.0",
    "gn:asciiname":"Yaqu",
    "gn:country_code":"CN",
    "gn:dem":4581,
    "gn:feature_class":"P",
    "gn:feature_code":"PPL",
    "gn:name":"Yaqu",
    "gn:population":0,
    "gn:timezone":"Asia/Urumqi",
    "iso:country":"CN",
    "name:zho_x_preferred":[
        "\u4e9a\u66f2"
    ],
    "wof:name":"Yaqu",
    "wof:placetype":"locality"
},
  "geometry": {"coordinates":[84.6031,29.385],"type":"Point"}
}