{
  "type": "Feature",
  "properties": {
    "gn:admin1_code":"02",
    "gn:asciiname":"Xiangdongyancun",
    "gn:country_code":"CN",
    "gn:dem":11,
    "gn:feature_class":"P",
    "gn:feature_code":"PPL",
    "gn:name":"Xiangdongyancun",
    "gn:population":0,
    "gn:timezone":"Asia/Shanghai",
    "iso:country":"CN",
    "name:und_x_variant":[
        "Xiangdongyan",
        "Xiangdongyancun"
    ],
    "name:zho_x_preferred":[
        "\u54cd\u52a8\u5ca9"
    ],
    "name:zho_x_variant":[
        "\u54cd\u52a8\u5ca9\u6751"
    ],
    "wof:name":"Xiangdongyancun",
    "wof:placetype":"locality"
},
  "geometry": {"coordinates":[120.72826999999999,27.9555],"type":"Point"}
}