{
  "type": "Feature",
  "properties": {
    "gn:admin1_code":"25",
    "gn:asciiname":"Caijia Zhuangzi",
    "gn:country_code":"CN",
    "gn:dem":4,
    "gn:feature_class":"P",
    "gn:feature_code":"PPL",
    "gn:name":"Caijia Zhuangzi",
    "gn:population":0,
    "gn:timezone":"Asia/Shanghai",
    "iso:country":"CN",
    "name:zho_x_preferred":[
        "\u8521\u5bb6\u5e84\u5b50"
    ],
    "wof:name":"Caijia Zhuangzi",
    "wof:placetype":"locality"
},
  "geometry": {"coordinates":[117.822,38.0248],"type":"Point"}
}