{
  "type": "Feature",
  "properties": {
    "gn:admin1_code":"31.0",
    "gn:asciiname":"Jinjiang Shiqidui",
    "gn:country_code":"CN",
    "gn:dem":89,
    "gn:feature_class":"P",
    "gn:feature_code":"PPLF",
    "gn:name":"Jinjiang Shiqidui",
    "gn:population":0,
    "gn:timezone":"Asia/Shanghai",
    "iso:country":"CN",
    "name:und_x_variant":[
        "\u91d1\u6c5f\u5341\u4e03\u961f"
    ],
    "wof:name":"Jinjiang Shiqidui",
    "wof:placetype":"locality"
},
  "geometry": {"coordinates":[109.60923,18.61668],"type":"Point"}
}