{
  "type": "Feature",
  "properties": {
    "gn:admin1_code":"7.0",
    "gn:asciiname":"Jishan",
    "gn:country_code":"CN",
    "gn:dem":228,
    "gn:feature_class":"P",
    "gn:feature_code":"PPL",
    "gn:name":"Jishan",
    "gn:population":0,
    "gn:timezone":"Asia/Shanghai",
    "iso:country":"CN",
    "name:zho_x_preferred":[
        "\u7ee7\u5584"
    ],
    "wof:name":"Jishan",
    "wof:placetype":"locality"
},
  "geometry": {"coordinates":[118.69121,26.14177],"type":"Point"}
}