{
  "type": "Feature",
  "properties": {
    "gn:admin1_code":"10.0",
    "gn:asciiname":"Miaochengzi",
    "gn:country_code":"CN",
    "gn:dem":234,
    "gn:feature_class":"P",
    "gn:feature_code":"PPL",
    "gn:name":"Miaochengzi",
    "gn:population":0,
    "gn:timezone":"Asia/Shanghai",
    "iso:country":"CN",
    "name:zho_x_preferred":[
        "\u82d7\u57ce\u5b50"
    ],
    "wof:name":"Miaochengzi",
    "wof:placetype":"locality"
},
  "geometry": {"coordinates":[119.72348999999998,40.19537],"type":"Point"}
}