{
  "type": "Feature",
  "properties": {
    "gn:admin1_code":"3.0",
    "gn:asciiname":"Donggushan Linchang",
    "gn:country_code":"CN",
    "gn:dem":87,
    "gn:feature_class":"P",
    "gn:feature_code":"PPLF",
    "gn:name":"Donggushan Linchang",
    "gn:population":0,
    "gn:timezone":"Asia/Shanghai",
    "iso:country":"CN",
    "name:und_x_variant":[
        "\u4e1c\u726f\u5c71\u6797\u573a"
    ],
    "wof:name":"Donggushan Linchang",
    "wof:placetype":"locality"
},
  "geometry": {"coordinates":[115.94412,29.43898],"type":"Point"}
}