{
  "type": "Feature",
  "properties": {
    "gn:admin1_code":"19.0",
    "gn:asciiname":"Xiajian",
    "gn:country_code":"CN",
    "gn:dem":11,
    "gn:feature_class":"P",
    "gn:feature_code":"PPL",
    "gn:name":"Xiajian",
    "gn:population":0,
    "gn:timezone":"Asia/Shanghai",
    "iso:country":"CN",
    "name:und_x_variant":[
        "\u4e0b\u5c16"
    ],
    "name:zho_x_preferred":[
        "\u4e0b\u5c16"
    ],
    "wof:name":"Xiajian",
    "wof:placetype":"locality"
},
  "geometry": {"coordinates":[124.47152,40.18918],"type":"Point"}
}