{
  "type": "Feature",
  "properties": {
    "gn:admin1_code":"15.0",
    "gn:asciiname":"Heishawo",
    "gn:country_code":"CN",
    "gn:dem":1461,
    "gn:feature_class":"P",
    "gn:feature_code":"PPL",
    "gn:name":"Heishawo",
    "gn:population":0,
    "gn:timezone":"Asia/Shanghai",
    "iso:country":"CN",
    "name:zho_x_preferred":[
        "\u9ed1\u6c99\u7a9d"
    ],
    "wof:name":"Heishawo",
    "wof:placetype":"locality"
},
  "geometry": {"coordinates":[96.995,40.3654],"type":"Point"}
}