{
  "type": "Feature",
  "properties": {
    "gn:admin1_code":"3",
    "gn:asciiname":"Tianhu",
    "gn:country_code":"CN",
    "gn:dem":437,
    "gn:feature_class":"P",
    "gn:feature_code":"PPL",
    "gn:name":"Tianhu",
    "gn:population":0,
    "gn:timezone":"Asia/Shanghai",
    "iso:country":"CN",
    "name:zho_x_preferred":[
        "\u5929\u6e56"
    ],
    "wof:name":"Tianhu",
    "wof:placetype":"locality"
},
  "geometry": {"coordinates":[114.02800000000001,26.6707],"type":"Point"}
}