{
  "type": "Feature",
  "properties": {
    "gn:admin1_code":"22.0",
    "gn:asciiname":"Zongjiaying",
    "gn:country_code":"CN",
    "gn:dem":516,
    "gn:feature_class":"P",
    "gn:feature_code":"PPL",
    "gn:name":"Zongjiaying",
    "gn:population":0,
    "gn:timezone":"Asia/Shanghai",
    "iso:country":"CN",
    "name:zho_x_preferred":[
        "\u5b97\u5bb6\u8425"
    ],
    "wof:name":"Zongjiaying",
    "wof:placetype":"locality"
},
  "geometry": {"coordinates":[116.00399,40.43249],"type":"Point"}
}