{
  "type": "Feature",
  "properties": {
    "gn:admin1_code":"12.0",
    "gn:asciiname":"Meijiadian",
    "gn:country_code":"CN",
    "gn:dem":35,
    "gn:feature_class":"P",
    "gn:feature_code":"PPL",
    "gn:name":"Meijiadian",
    "gn:population":0,
    "gn:timezone":"Asia/Shanghai",
    "iso:country":"CN",
    "name:und_x_variant":[
        "\u6885\u5bb6\u5e97"
    ],
    "wof:name":"Meijiadian",
    "wof:placetype":"locality"
},
  "geometry": {"coordinates":[114.82041,30.87324000000001],"type":"Point"}
}