{
  "type": "Feature",
  "properties": {
    "gn:admin1_code":"32.0",
    "gn:asciiname":"Mulin",
    "gn:country_code":"CN",
    "gn:dem":496,
    "gn:feature_class":"P",
    "gn:feature_code":"PPL",
    "gn:name":"Mulin",
    "gn:population":0,
    "gn:timezone":"Asia/Shanghai",
    "iso:country":"CN",
    "name:zho_x_preferred":[
        "\u6728\u6797"
    ],
    "wof:name":"Mulin",
    "wof:placetype":"locality"
},
  "geometry": {"coordinates":[105.886,31.7309],"type":"Point"}
}