{
  "type": "Feature",
  "properties": {
    "gn:admin1_code":"5.0",
    "gn:asciiname":"Houjiatun",
    "gn:country_code":"CN",
    "gn:dem":209,
    "gn:feature_class":"P",
    "gn:feature_code":"PPL",
    "gn:name":"Houjiatun",
    "gn:population":0,
    "gn:timezone":"Asia/Shanghai",
    "iso:country":"CN",
    "name:zho_x_preferred":[
        "\u4faf\u5bb6\u5c6f"
    ],
    "wof:name":"Houjiatun",
    "wof:placetype":"locality"
},
  "geometry": {"coordinates":[124.49212,44.2942],"type":"Point"}
}