{
  "type": "Feature",
  "properties": {
    "gn:admin1_code":"19.0",
    "gn:asciiname":"Niuxintuncun",
    "gn:country_code":"CN",
    "gn:dem":2,
    "gn:feature_class":"P",
    "gn:feature_code":"PPL",
    "gn:name":"Niuxintuncun",
    "gn:population":0,
    "gn:timezone":"Asia/Shanghai",
    "iso:country":"CN",
    "name:zho_x_preferred":[
        "\u725b\u5fc3\u5c6f\u6751"
    ],
    "wof:name":"Niuxintuncun",
    "wof:placetype":"locality"
},
  "geometry": {"coordinates":[120.3206,40.21963],"type":"Point"}
}