{
  "type": "Feature",
  "properties": {
    "gn:admin1_code":"16.0",
    "gn:asciiname":"Shuole",
    "gn:country_code":"CN",
    "gn:dem":335,
    "gn:feature_class":"P",
    "gn:feature_code":"PPL",
    "gn:name":"Shuole",
    "gn:population":0,
    "gn:timezone":"Asia/Shanghai",
    "iso:country":"CN",
    "name:zho_x_preferred":[
        "\u6714\u52d2"
    ],
    "wof:name":"Shuole",
    "wof:placetype":"locality"
},
  "geometry": {"coordinates":[107.46899999999999,23.7802],"type":"Point"}
}