{
  "type": "Feature",
  "properties": {
    "gn:admin1_code":"29.0",
    "gn:asciiname":"Luantou",
    "gn:country_code":"CN",
    "gn:dem":1919,
    "gn:feature_class":"P",
    "gn:feature_code":"PPL",
    "gn:name":"Luantou",
    "gn:population":0,
    "gn:timezone":"Asia/Shanghai",
    "iso:country":"CN",
    "name:zho_x_preferred":[
        "\u4e71\u5934"
    ],
    "wof:name":"Luantou",
    "wof:placetype":"locality"
},
  "geometry": {"coordinates":[103.49299999999999,25.2605],"type":"Point"}
}