{
  "type": "Feature",
  "properties": {
    "gn:admin1_code":"19.0",
    "gn:asciiname":"Gujiatai",
    "gn:country_code":"CN",
    "gn:dem":9,
    "gn:feature_class":"P",
    "gn:feature_code":"PPL",
    "gn:name":"Gujiatai",
    "gn:population":0,
    "gn:timezone":"Asia/Shanghai",
    "iso:country":"CN",
    "name:zho_x_preferred":[
        "\u53e4\u5bb6\u53f0"
    ],
    "wof:name":"Gujiatai",
    "wof:placetype":"locality"
},
  "geometry": {"coordinates":[122.7651,41.2081],"type":"Point"}
}