{
  "type": "Feature",
  "properties": {
    "gn:admin1_code":"29.0",
    "gn:asciiname":"Duzhoutian",
    "gn:country_code":"CN",
    "gn:dem":595,
    "gn:feature_class":"P",
    "gn:feature_code":"PPL",
    "gn:name":"Duzhoutian",
    "gn:population":0,
    "gn:timezone":"Asia/Shanghai",
    "iso:country":"CN",
    "name:zho_x_preferred":[
        "\u8d4c\u5492\u7530"
    ],
    "wof:name":"Duzhoutian",
    "wof:placetype":"locality"
},
  "geometry": {"coordinates":[103.438,22.8954],"type":"Point"}
}