{
  "type": "Feature",
  "properties": {
    "gn:admin1_code":"15.0",
    "gn:asciiname":"Dahejia",
    "gn:country_code":"CN",
    "gn:dem":2218,
    "gn:feature_class":"P",
    "gn:feature_code":"PPL",
    "gn:name":"Dahejia",
    "gn:population":0,
    "gn:timezone":"Asia/Shanghai",
    "iso:country":"CN",
    "name:zho_x_preferred":[
        "\u5927\u4f55\u5bb6"
    ],
    "wof:name":"Dahejia",
    "wof:placetype":"locality"
},
  "geometry": {"coordinates":[103.36799999999999,35.5025],"type":"Point"}
}