{
  "type": "Feature",
  "properties": {
    "gn:admin1_code":"19.0",
    "gn:asciiname":"Changlongtun",
    "gn:country_code":"CN",
    "gn:dem":62,
    "gn:feature_class":"P",
    "gn:feature_code":"PPL",
    "gn:name":"Changlongtun",
    "gn:population":0,
    "gn:timezone":"Asia/Shanghai",
    "iso:country":"CN",
    "name:zho_x_preferred":[
        "\u957f\u9f99\u5c6f"
    ],
    "wof:name":"Changlongtun",
    "wof:placetype":"locality"
},
  "geometry": {"coordinates":[122.91179,39.93016],"type":"Point"}
}