{
  "type": "Feature",
  "properties": {
    "gn:admin1_code":"11.0",
    "gn:asciiname":"Shangbanjie",
    "gn:country_code":"CN",
    "gn:dem":498,
    "gn:feature_class":"P",
    "gn:feature_code":"PPL",
    "gn:name":"Shangbanjie",
    "gn:population":0,
    "gn:timezone":"Asia/Shanghai",
    "iso:country":"CN",
    "name:zho_x_preferred":[
        "\u4e0a\u534a\u754c"
    ],
    "wof:name":"Shangbanjie",
    "wof:placetype":"locality"
},
  "geometry": {"coordinates":[109.81401,27.37159],"type":"Point"}
}