{
  "type": "Feature",
  "properties": {
    "gn:admin1_code":"9.0",
    "gn:asciiname":"Panlao Zhaizi",
    "gn:country_code":"CN",
    "gn:dem":84,
    "gn:feature_class":"P",
    "gn:feature_code":"PPL",
    "gn:name":"Panlao Zhaizi",
    "gn:population":0,
    "gn:timezone":"Asia/Shanghai",
    "iso:country":"CN",
    "name:zho_x_preferred":[
        "\u6f58\u8001\u5b85\u5b50"
    ],
    "wof:name":"Panlao Zhaizi",
    "wof:placetype":"locality"
},
  "geometry": {"coordinates":[115.27401999999999,31.89217],"type":"Point"}
}