{
  "type": "Feature",
  "properties": {
    "gn:admin1_code":"8.0",
    "gn:asciiname":"Lukuantun",
    "gn:country_code":"CN",
    "gn:dem":221,
    "gn:feature_class":"P",
    "gn:feature_code":"PPL",
    "gn:name":"L\u00fckuantun",
    "gn:population":0,
    "gn:timezone":"Asia/Shanghai",
    "iso:country":"CN",
    "name:und_x_variant":[
        "L\u00fckuantun"
    ],
    "name:zho_x_preferred":[
        "\u5415\u5bbd\u5c6f"
    ],
    "wof:name":"Lukuantun",
    "wof:placetype":"locality"
},
  "geometry": {"coordinates":[125.73138,47.19929000000001],"type":"Point"}
}