{
  "type": "Feature",
  "properties": {
    "gn:admin1_code":"11.0",
    "gn:asciiname":"Zhubotang",
    "gn:country_code":"CN",
    "gn:dem":51,
    "gn:feature_class":"P",
    "gn:feature_code":"PPL",
    "gn:name":"Zhubotang",
    "gn:population":0,
    "gn:timezone":"Asia/Shanghai",
    "iso:country":"CN",
    "name:zho_x_preferred":[
        "\u73e0\u6ce2\u5858"
    ],
    "wof:name":"Zhubotang",
    "wof:placetype":"locality"
},
  "geometry": {"coordinates":[112.44907000000001,28.49235],"type":"Point"}
}