{
  "type": "Feature",
  "properties": {
    "gn:admin1_code":"14.0",
    "gn:asciiname":"Gengzhang",
    "gn:country_code":"CN",
    "gn:dem":3076,
    "gn:feature_class":"P",
    "gn:feature_code":"PPLA4",
    "gn:name":"Gengzhang",
    "gn:population":0,
    "gn:timezone":"Asia/Urumqi",
    "iso:country":"CN",
    "name:und_x_variant":[
        "Gengzhang Menbaminzu Xiang",
        "Gengzhang Xiang"
    ],
    "name:zho_x_preferred":[
        "\u66f4\u7ae0"
    ],
    "name:zho_x_variant":[
        "\u66f4\u7ae0\u95e8\u5df4\u6c11\u65cf\u4e61",
        "\u66f4\u7ae0\u4e61"
    ],
    "wof:name":"Gengzhang",
    "wof:placetype":"locality"
},
  "geometry": {"coordinates":[94.09205,29.72786],"type":"Point"}
}