{
  "type": "Feature",
  "properties": {
    "gn:admin1_code":"12.0",
    "gn:asciiname":"Tongmuyuan",
    "gn:country_code":"CN",
    "gn:dem":1451,
    "gn:feature_class":"P",
    "gn:feature_code":"PPL",
    "gn:name":"Tongmuyuan",
    "gn:population":0,
    "gn:timezone":"Asia/Shanghai",
    "iso:country":"CN",
    "name:zho_x_preferred":[
        "\u6850\u6728\u56ed"
    ],
    "wof:name":"Tongmuyuan",
    "wof:placetype":"locality"
},
  "geometry": {"coordinates":[110.98647,31.29451],"type":"Point"}
}