{
  "type": "Feature",
  "properties": {
    "gn:admin1_code":"19.0",
    "gn:asciiname":"Gangshanling",
    "gn:country_code":"CN",
    "gn:dem":520,
    "gn:feature_class":"P",
    "gn:feature_code":"PPL",
    "gn:name":"Gangshanling",
    "gn:population":0,
    "gn:timezone":"Asia/Shanghai",
    "iso:country":"CN",
    "name:zho_x_preferred":[
        "\u5c97\u5c71\u5cad"
    ],
    "wof:name":"Gangshanling",
    "wof:placetype":"locality"
},
  "geometry": {"coordinates":[125.48644,41.52726],"type":"Point"}
}