{
  "type": "Feature",
  "properties": {
    "gn:admin1_code":"24.0",
    "gn:asciiname":"Mimigou",
    "gn:country_code":"CN",
    "gn:dem":1196,
    "gn:feature_class":"P",
    "gn:feature_code":"PPL",
    "gn:name":"Mimigou",
    "gn:population":0,
    "gn:timezone":"Asia/Shanghai",
    "iso:country":"CN",
    "name:zho_x_preferred":[
        "\u7c73\u7c73\u6c9f"
    ],
    "wof:name":"Mimigou",
    "wof:placetype":"locality"
},
  "geometry": {"coordinates":[112.44387,36.41595],"type":"Point"}
}