{
  "type": "Feature",
  "properties": {
    "gn:admin1_code":"19.0",
    "gn:asciiname":"Lianhuapao",
    "gn:country_code":"CN",
    "gn:dem":107,
    "gn:feature_class":"P",
    "gn:feature_code":"PPL",
    "gn:name":"Lianhuapao",
    "gn:population":0,
    "gn:timezone":"Asia/Shanghai",
    "iso:country":"CN",
    "name:zho_x_preferred":[
        "\u83b2\u82b1\u6ce1"
    ],
    "wof:name":"Lianhuapao",
    "wof:placetype":"locality"
},
  "geometry": {"coordinates":[123.97199999999999,42.6408],"type":"Point"}
}