{
  "type": "Feature",
  "properties": {
    "gn:admin1_code":"25",
    "gn:asciiname":"Duanjiabu",
    "gn:country_code":"CN",
    "gn:dem":11,
    "gn:feature_class":"P",
    "gn:feature_code":"PPL",
    "gn:name":"Duanjiabu",
    "gn:population":0,
    "gn:timezone":"Asia/Shanghai",
    "iso:country":"CN",
    "name:zho_x_preferred":[
        "\u6bb5\u5bb6\u57e0"
    ],
    "wof:name":"Duanjiabu",
    "wof:placetype":"locality"
},
  "geometry": {"coordinates":[120.53861000000001,36.12611],"type":"Point"}
}