{
  "type": "Feature",
  "properties": {
    "gn:admin1_code":"9.0",
    "gn:asciiname":"Gengli",
    "gn:country_code":"CN",
    "gn:dem":135,
    "gn:feature_class":"P",
    "gn:feature_code":"PPL",
    "gn:name":"Gengli",
    "gn:population":0,
    "gn:timezone":"Asia/Shanghai",
    "iso:country":"CN",
    "name:und_x_variant":[
        "\u57c2\u91cc",
        "Gengli"
    ],
    "wof:name":"Gengli",
    "wof:placetype":"locality"
},
  "geometry": {"coordinates":[112.83556000000002,33.08669],"type":"Point"}
}