{
  "type": "Feature",
  "properties": {
    "gn:admin1_code":"29.0",
    "gn:asciiname":"Shanlinguoshu",
    "gn:country_code":"CN",
    "gn:dem":2205,
    "gn:feature_class":"P",
    "gn:feature_code":"PPL",
    "gn:name":"Shanlinguoshu",
    "gn:population":0,
    "gn:timezone":"Asia/Shanghai",
    "iso:country":"CN",
    "name:zho_x_preferred":[
        "\u5c71\u6797\u679c\u6811"
    ],
    "wof:name":"Shanlinguoshu",
    "wof:placetype":"locality"
},
  "geometry": {"coordinates":[99.1557,25.27],"type":"Point"}
}