{
  "type": "Feature",
  "properties": {
    "gn:admin1_code":"13.0",
    "gn:asciiname":"Bo'ermaili",
    "gn:country_code":"CN",
    "gn:dem":1361,
    "gn:feature_class":"P",
    "gn:feature_code":"PPL",
    "gn:name":"Bo\u2019ermaili",
    "gn:population":0,
    "gn:timezone":"Asia/Shanghai",
    "iso:country":"CN",
    "name:und_x_variant":[
        "Bo\u2019ermaili"
    ],
    "name:zho_x_preferred":[
        "\u535a\u5c14\u4e70\u91cc"
    ],
    "wof:name":"Bo'ermaili",
    "wof:placetype":"locality"
},
  "geometry": {"coordinates":[79.85281999999999,37.13101],"type":"Point"}
}