{
  "type": "Feature",
  "properties": {
    "gn:admin1_code":"11.0",
    "gn:asciiname":"Waiping",
    "gn:country_code":"CN",
    "gn:dem":451,
    "gn:feature_class":"P",
    "gn:feature_code":"PPL",
    "gn:name":"Waiping",
    "gn:population":0,
    "gn:timezone":"Asia/Shanghai",
    "iso:country":"CN",
    "name:zho_x_preferred":[
        "\u6b6a\u576a"
    ],
    "wof:name":"Waiping",
    "wof:placetype":"locality"
},
  "geometry": {"coordinates":[109.52668,26.864],"type":"Point"}
}