{
  "type": "Feature",
  "properties": {
    "gn:admin1_code":"18",
    "gn:asciiname":"Zhuyouqing",
    "gn:country_code":"CN",
    "gn:dem":1827,
    "gn:feature_class":"P",
    "gn:feature_code":"PPL",
    "gn:name":"Zhuyouqing",
    "gn:population":0,
    "gn:timezone":"Asia/Shanghai",
    "iso:country":"CN",
    "name:zho_x_preferred":[
        "\u6731\u7531\u7b90"
    ],
    "wof:name":"Zhuyouqing",
    "wof:placetype":"locality"
},
  "geometry": {"coordinates":[104.855,26.007],"type":"Point"}
}