{
  "type": "Feature",
  "properties": {
    "gn:admin1_code":"25",
    "gn:asciiname":"Tianjia Zhuangzi",
    "gn:country_code":"CN",
    "gn:dem":7,
    "gn:feature_class":"P",
    "gn:feature_code":"PPL",
    "gn:name":"Tianjia Zhuangzi",
    "gn:population":0,
    "gn:timezone":"Asia/Shanghai",
    "iso:country":"CN",
    "name:zho_x_preferred":[
        "\u7530\u5bb6\u5e84\u5b50"
    ],
    "wof:name":"Tianjia Zhuangzi",
    "wof:placetype":"locality"
},
  "geometry": {"coordinates":[117.878,38.0293],"type":"Point"}
}