{
  "type": "Feature",
  "properties": {
    "gn:admin1_code":"26.0",
    "gn:asciiname":"Fangxiangcun",
    "gn:country_code":"CN",
    "gn:dem":1282,
    "gn:feature_class":"P",
    "gn:feature_code":"PPL",
    "gn:name":"Fangxiangcun",
    "gn:population":0,
    "gn:timezone":"Asia/Shanghai",
    "iso:country":"CN",
    "name:zho_x_preferred":[
        "\u65b9\u76f8\u6751"
    ],
    "wof:name":"Fangxiangcun",
    "wof:placetype":"locality"
},
  "geometry": {"coordinates":[109.58837,35.81428],"type":"Point"}
}