{
  "type": "Feature",
  "properties": {
    "gn:admin1_code":"32.0",
    "gn:asciiname":"Jielie",
    "gn:country_code":"CN",
    "gn:dem":2748,
    "gn:feature_class":"P",
    "gn:feature_code":"PPL",
    "gn:name":"Jielie",
    "gn:population":0,
    "gn:timezone":"Asia/Shanghai",
    "iso:country":"CN",
    "name:zho_x_preferred":[
        "\u7ed3\u5217"
    ],
    "wof:name":"Jielie",
    "wof:placetype":"locality"
},
  "geometry": {"coordinates":[103.009,27.8688],"type":"Point"}
}