{
  "type": "Feature",
  "properties": {
    "gn:admin1_code":"18.0",
    "gn:asciiname":"Huanghuayuan",
    "gn:country_code":"CN",
    "gn:dem":1238,
    "gn:feature_class":"P",
    "gn:feature_code":"PPL",
    "gn:name":"Huanghuayuan",
    "gn:population":0,
    "gn:timezone":"Asia/Shanghai",
    "iso:country":"CN",
    "name:zho_x_preferred":[
        "\u9ec4\u82b1\u56ed"
    ],
    "wof:name":"Huanghuayuan",
    "wof:placetype":"locality"
},
  "geometry": {"coordinates":[107.54300000000001,26.8728],"type":"Point"}
}