{
  "type": "Feature",
  "properties": {
    "gn:admin1_code":"29.0",
    "gn:asciiname":"Luomao'ayi",
    "gn:country_code":"CN",
    "gn:dem":3180,
    "gn:feature_class":"P",
    "gn:feature_code":"PPL",
    "gn:name":"Luomao\u2019ayi",
    "gn:population":0,
    "gn:timezone":"Asia/Shanghai",
    "iso:country":"CN",
    "name:und_x_variant":[
        "Luomao\u2019ayi"
    ],
    "name:zho_x_preferred":[
        "\u7f57\u6bdb\u963f\u8863"
    ],
    "wof:name":"Luomao'ayi",
    "wof:placetype":"locality"
},
  "geometry": {"coordinates":[100.992,27.3504],"type":"Point"}
}