{
  "type": "Feature",
  "properties": {
    "gn:admin1_code":"29.0",
    "gn:asciiname":"Yajiala",
    "gn:country_code":"CN",
    "gn:dem":1271,
    "gn:feature_class":"P",
    "gn:feature_code":"PPL",
    "gn:name":"Yajiala",
    "gn:population":0,
    "gn:timezone":"Asia/Shanghai",
    "iso:country":"CN",
    "name:zho_x_preferred":[
        "\u4e9a\u621b\u814a"
    ],
    "wof:name":"Yajiala",
    "wof:placetype":"locality"
},
  "geometry": {"coordinates":[98.8633,26.8934],"type":"Point"}
}