{
  "type": "Feature",
  "properties": {
    "gn:admin1_code":"29.0",
    "gn:asciiname":"Yonghe",
    "gn:country_code":"CN",
    "gn:dem":2118,
    "gn:feature_class":"P",
    "gn:feature_code":"PPL",
    "gn:name":"Yonghe",
    "gn:population":0,
    "gn:timezone":"Asia/Shanghai",
    "iso:country":"CN",
    "name:ceb_x_preferred":[
        "Yonghe"
    ],
    "name:deu_x_preferred":[
        "Yonghe"
    ],
    "name:rus_x_preferred":[
        "\u042e\u043d\u0445\u044d"
    ],
    "name:zho_x_preferred":[
        "\u6c38\u6cb3"
    ],
    "wof:name":"Yonghe",
    "wof:placetype":"locality"
},
  "geometry": {"coordinates":[100.97,26.0585],"type":"Point"}
}