{
  "type": "Feature",
  "properties": {
    "gn:admin1_code":"24.0",
    "gn:asciiname":"Xiaxi",
    "gn:country_code":"CN",
    "gn:dem":1201,
    "gn:feature_class":"P",
    "gn:feature_code":"PPL",
    "gn:name":"Xiaxi",
    "gn:population":0,
    "gn:timezone":"Asia/Shanghai",
    "iso:country":"CN",
    "name:und_x_variant":[
        "Hsia-hsi",
        "Hsia-hs\u00fc",
        "Xiaxi"
    ],
    "name:zho_x_preferred":[
        "\u4e0b\u6614"
    ],
    "wof:name":"Xiaxi",
    "wof:placetype":"locality"
},
  "geometry": {"coordinates":[111.32026999999999,37.73227],"type":"Point"}
}