{
  "type": "Feature",
  "properties": {
    "gn:admin1_code":"5.0",
    "gn:asciiname":"Qianshanzui",
    "gn:country_code":"CN",
    "gn:dem":196,
    "gn:feature_class":"P",
    "gn:feature_code":"PPL",
    "gn:name":"Qianshanzui",
    "gn:population":0,
    "gn:timezone":"Asia/Shanghai",
    "iso:country":"CN",
    "name:zho_x_preferred":[
        "\u524d\u5c71\u5480"
    ],
    "wof:name":"Qianshanzui",
    "wof:placetype":"locality"
},
  "geometry": {"coordinates":[126.56350999999999,44.75442],"type":"Point"}
}