{
  "type": "Feature",
  "properties": {
    "gn:admin1_code":"9.0",
    "gn:asciiname":"Chengyadi",
    "gn:country_code":"CN",
    "gn:dem":617,
    "gn:feature_class":"P",
    "gn:feature_code":"PPL",
    "gn:name":"Chengyadi",
    "gn:population":0,
    "gn:timezone":"Asia/Shanghai",
    "iso:country":"CN",
    "name:zho_x_preferred":[
        "\u57ce\u5d16\u5730"
    ],
    "wof:name":"Chengyadi",
    "wof:placetype":"locality"
},
  "geometry": {"coordinates":[111.92354,34.91788],"type":"Point"}
}