{
  "type": "Feature",
  "properties": {
    "gn:admin1_code":"21.0",
    "gn:asciiname":"Liwan",
    "gn:country_code":"CN",
    "gn:dem":1586,
    "gn:feature_class":"P",
    "gn:feature_code":"PPL",
    "gn:name":"Liwan",
    "gn:population":0,
    "gn:timezone":"Asia/Shanghai",
    "iso:country":"CN",
    "name:ara_x_preferred":[
        "\u0644\u064a\u0648\u0627\u0646"
    ],
    "name:heb_x_preferred":[
        "\u05dc\u05d9\u05d5\u05d5\u05d0\u05df"
    ],
    "name:ita_x_preferred":[
        "L\u012bw\u0101n"
    ],
    "name:spa_x_preferred":[
        "Liwan"
    ],
    "name:urd_x_preferred":[
        "\u0644\u06cc\u0648\u0627\u0646"
    ],
    "name:zho_x_preferred":[
        "\u91cc\u6e7e"
    ],
    "wof:name":"Liwan",
    "wof:placetype":"locality"
},
  "geometry": {"coordinates":[106.92035,36.09206],"type":"Point"}
}