{
  "type": "Feature",
  "properties": {
    "gn:admin1_code":"15.0",
    "gn:asciiname":"Huoshaogou",
    "gn:country_code":"CN",
    "gn:dem":1942,
    "gn:feature_class":"P",
    "gn:feature_code":"PPL",
    "gn:name":"Huoshaogou",
    "gn:population":0,
    "gn:timezone":"Asia/Shanghai",
    "iso:country":"CN",
    "name:zho_x_preferred":[
        "\u706b\u70e7\u6c9f"
    ],
    "wof:name":"Huoshaogou",
    "wof:placetype":"locality"
},
  "geometry": {"coordinates":[104.024,36.7464],"type":"Point"}
}