{
  "type": "Feature",
  "properties": {
    "gn:admin1_code":"4.0",
    "gn:asciiname":"Xiahedun",
    "gn:country_code":"CN",
    "gn:dem":1,
    "gn:feature_class":"P",
    "gn:feature_code":"PPL",
    "gn:name":"Xiahedun",
    "gn:population":0,
    "gn:timezone":"Asia/Shanghai",
    "iso:country":"CN",
    "name:zho_x_preferred":[
        "Xiahedun"
    ],
    "name:zho_x_variant":[
        "\u4e0b\u6cb3\u58a9"
    ],
    "wof:name":"Xiahedun",
    "wof:placetype":"locality"
},
  "geometry": {"coordinates":[120.03618,34.0163],"type":"Point"}
}