{
  "type": "Feature",
  "properties": {
    "gn:admin1_code":"3.0",
    "gn:asciiname":"Shangliyang",
    "gn:country_code":"CN",
    "gn:dem":269,
    "gn:feature_class":"P",
    "gn:feature_code":"PPL",
    "gn:name":"Shangliyang",
    "gn:population":0,
    "gn:timezone":"Asia/Shanghai",
    "iso:country":"CN",
    "name:zho_x_preferred":[
        "\u4e0a\u91cc\u6d0b"
    ],
    "wof:name":"Shangliyang",
    "wof:placetype":"locality"
},
  "geometry": {"coordinates":[118.43049000000001,28.35615],"type":"Point"}
}