{
  "type": "Feature",
  "properties": {
    "gn:admin1_code":"24.0",
    "gn:asciiname":"Qianjialou",
    "gn:country_code":"CN",
    "gn:dem":829,
    "gn:feature_class":"P",
    "gn:feature_code":"PPL",
    "gn:name":"Qianjialou",
    "gn:population":0,
    "gn:timezone":"Asia/Shanghai",
    "iso:country":"CN",
    "name:zho_x_preferred":[
        "\u524d\u52a0\u697c"
    ],
    "wof:name":"Qianjialou",
    "wof:placetype":"locality"
},
  "geometry": {"coordinates":[111.59148999999999,36.68482],"type":"Point"}
}