{
  "type": "Feature",
  "properties": {
    "gn:admin1_code":"33.0",
    "gn:asciiname":"Fengyun",
    "gn:country_code":"CN",
    "gn:dem":418,
    "gn:feature_class":"P",
    "gn:feature_code":"PPL",
    "gn:name":"Fengyun",
    "gn:population":0,
    "gn:timezone":"Asia/Shanghai",
    "iso:country":"CN",
    "name:deu_x_preferred":[
        "Fengyun"
    ],
    "name:fin_x_preferred":[
        "Feng-Yun"
    ],
    "name:fra_x_preferred":[
        "Feng-Yun"
    ],
    "name:ind_x_preferred":[
        "Fengyun"
    ],
    "name:jpn_x_preferred":[
        "\u98a8\u96f2"
    ],
    "name:por_x_preferred":[
        "Fengyun"
    ],
    "name:rus_x_preferred":[
        "\u0424\u044d\u043d\u044a\u044e\u043d\u044c"
    ],
    "name:spa_x_preferred":[
        "Fengyun"
    ],
    "name:zho_x_preferred":[
        "\u5949\u4e91"
    ],
    "name:zho_x_variant":[
        "\u98ce\u4e91\u7cfb\u5217\u536b\u661f"
    ],
    "wof:name":"Fengyun",
    "wof:placetype":"locality"
},
  "geometry": {"coordinates":[109.22565,30.98871],"type":"Point"}
}