{
  "type": "Feature",
  "properties": {
    "gn:admin1_code":"33.0",
    "gn:asciiname":"Fengyun",
    "gn:country_code":"CN",
    "gn:dem":418,
    "gn:feature_class":"P",
    "gn:feature_code":"PPL",
    "gn:name":"Fengyun",
    "gn:population":0,
    "gn:timezone":"Asia/Shanghai",
    "iso:country":"CN",
    "name:zho_x_preferred":[
        "\u5949\u4e91"
    ],
    "wof:name":"Fengyun",
    "wof:placetype":"locality"
},
  "geometry": {"coordinates":[109.22565,30.98871],"type":"Point"}
}