{
  "type": "Feature",
  "properties": {
    "gn:admin1_code":"18.0",
    "gn:asciiname":"Layue",
    "gn:country_code":"CN",
    "gn:dem":698,
    "gn:feature_class":"P",
    "gn:feature_code":"PPL",
    "gn:name":"Layue",
    "gn:population":0,
    "gn:timezone":"Asia/Shanghai",
    "iso:country":"CN",
    "name:zho_x_preferred":[
        "\u62c9\u7ea6"
    ],
    "wof:name":"Layue",
    "wof:placetype":"locality"
},
  "geometry": {"coordinates":[107.96299999999999,25.5898],"type":"Point"}
}