{
  "type": "Feature",
  "properties": {
    "gn:admin1_code":"4.0",
    "gn:asciiname":"Duanjiuxu",
    "gn:country_code":"CN",
    "gn:dem":4,
    "gn:feature_class":"P",
    "gn:feature_code":"PPLF",
    "gn:name":"Duanjiuxu",
    "gn:population":0,
    "gn:timezone":"Asia/Shanghai",
    "iso:country":"CN",
    "name:zho_x_preferred":[
        "\u77ed\u4e5d\u5729"
    ],
    "wof:name":"Duanjiuxu",
    "wof:placetype":"locality"
},
  "geometry": {"coordinates":[120.45653,32.10965],"type":"Point"}
}