{
  "type": "Feature",
  "properties": {
    "gn:admin1_code":"12.0",
    "gn:asciiname":"Potang'ao",
    "gn:country_code":"CN",
    "gn:dem":46,
    "gn:feature_class":"P",
    "gn:feature_code":"PPL",
    "gn:name":"Potang\u2019ao",
    "gn:population":0,
    "gn:timezone":"Asia/Shanghai",
    "iso:country":"CN",
    "name:zho_x_preferred":[
        "Potang\u2019ao"
    ],
    "name:zho_x_variant":[
        "\u7834\u5858\u5773"
    ],
    "wof:name":"Potang'ao",
    "wof:placetype":"locality"
},
  "geometry": {"coordinates":[115.11096000000001,30.45559],"type":"Point"}
}