{
  "type": "Feature",
  "properties": {
    "gn:admin1_code":"11",
    "gn:asciiname":"Xiahutong",
    "gn:country_code":"CN",
    "gn:dem":295,
    "gn:feature_class":"P",
    "gn:feature_code":"PPL",
    "gn:name":"Xiahutong",
    "gn:population":0,
    "gn:timezone":"Asia/Shanghai",
    "iso:country":"CN",
    "wof:name":"Xiahutong",
    "wof:placetype":"locality"
},
  "geometry": {"coordinates":[111.29528000000001,26.91722],"type":"Point"}
}