{
  "type": "Feature",
  "properties": {
    "gn:admin1_code":"18",
    "gn:asciiname":"Jinliangdi",
    "gn:country_code":"CN",
    "gn:dem":1331,
    "gn:feature_class":"P",
    "gn:feature_code":"PPL",
    "gn:name":"Jinliangdi",
    "gn:population":0,
    "gn:timezone":"Asia/Shanghai",
    "iso:country":"CN",
    "name:zho_x_preferred":[
        "\u91d1\u826f\u5730"
    ],
    "wof:name":"Jinliangdi",
    "wof:placetype":"locality"
},
  "geometry": {"coordinates":[104.748,25.3164],"type":"Point"}
}