{
  "type": "Feature",
  "properties": {
    "gn:admin1_code":"10",
    "gn:asciiname":"Xiaoweizigou",
    "gn:country_code":"CN",
    "gn:dem":977,
    "gn:feature_class":"P",
    "gn:feature_code":"PPL",
    "gn:name":"Xiaoweizigou",
    "gn:population":0,
    "gn:timezone":"Asia/Shanghai",
    "iso:country":"CN",
    "name:zho_x_preferred":[
        "\u5c0f\u82c7\u5b50\u6c9f"
    ],
    "wof:name":"Xiaoweizigou",
    "wof:placetype":"locality"
},
  "geometry": {"coordinates":[118.17408,41.96465],"type":"Point"}
}