{
  "type": "Feature",
  "properties": {
    "gn:admin1_code":"1.0",
    "gn:asciiname":"Siducun",
    "gn:country_code":"CN",
    "gn:dem":38,
    "gn:feature_class":"P",
    "gn:feature_code":"PPL",
    "gn:name":"Siducun",
    "gn:population":0,
    "gn:timezone":"Asia/Shanghai",
    "iso:country":"CN",
    "name:zho_x_preferred":[
        "\u56db\u675c\u6751"
    ],
    "wof:name":"Siducun",
    "wof:placetype":"locality"
},
  "geometry": {"coordinates":[117.29027000000001,32.64959],"type":"Point"}
}