{
  "type": "Feature",
  "properties": {
    "gn:admin1_code":"20.0",
    "gn:asciiname":"Malianqu",
    "gn:country_code":"CN",
    "gn:dem":1859,
    "gn:feature_class":"P",
    "gn:feature_code":"PPL",
    "gn:name":"Malianqu",
    "gn:population":0,
    "gn:timezone":"Asia/Shanghai",
    "iso:country":"CN",
    "name:und_x_variant":[
        "\u9a6c\u83b2\u6e20"
    ],
    "wof:name":"Malianqu",
    "wof:placetype":"locality"
},
  "geometry": {"coordinates":[110.61803,41.21891],"type":"Point"}
}