{
  "type": "Feature",
  "properties": {
    "gn:admin1_code":"18.0",
    "gn:asciiname":"Cenkou",
    "gn:country_code":"CN",
    "gn:dem":396,
    "gn:feature_class":"P",
    "gn:feature_code":"PPL",
    "gn:name":"Cenkou",
    "gn:population":0,
    "gn:timezone":"Asia/Shanghai",
    "iso:country":"CN",
    "name:zho_x_preferred":[
        "\u5c91\u6263"
    ],
    "wof:name":"Cenkou",
    "wof:placetype":"locality"
},
  "geometry": {"coordinates":[109.218,25.754],"type":"Point"}
}