{
  "type": "Feature",
  "properties": {
    "gn:admin1_code":"9",
    "gn:asciiname":"Gouyuan",
    "gn:country_code":"CN",
    "gn:dem":585,
    "gn:feature_class":"P",
    "gn:feature_code":"PPL",
    "gn:name":"Gouyuan",
    "gn:population":0,
    "gn:timezone":"Asia/Shanghai",
    "iso:country":"CN",
    "wof:name":"Gouyuan",
    "wof:placetype":"locality"
},
  "geometry": {"coordinates":[111.73917,34.70028],"type":"Point"}
}