{
  "type": "Feature",
  "properties": {
    "gn:admin1_code":"29.0",
    "gn:asciiname":"Gou'e",
    "gn:country_code":"CN",
    "gn:dem":1163,
    "gn:feature_class":"P",
    "gn:feature_code":"PPL",
    "gn:name":"Gou\u2019e",
    "gn:population":0,
    "gn:timezone":"Asia/Shanghai",
    "iso:country":"CN",
    "name:und_x_variant":[
        "Gou\u2019e"
    ],
    "name:zho_x_preferred":[
        "\u6c9f\u4fc4"
    ],
    "wof:name":"Gou'e",
    "wof:placetype":"locality"
},
  "geometry": {"coordinates":[102.389,22.8761],"type":"Point"}
}