{
  "type": "Feature",
  "properties": {
    "gn:admin1_code":"5.0",
    "gn:asciiname":"Zhaojiajie",
    "gn:country_code":"CN",
    "gn:dem":364,
    "gn:feature_class":"P",
    "gn:feature_code":"PPL",
    "gn:name":"Zhaojiajie",
    "gn:population":0,
    "gn:timezone":"Asia/Shanghai",
    "iso:country":"CN",
    "name:zho_x_preferred":[
        "\u8d75\u5bb6\u8857"
    ],
    "wof:name":"Zhaojiajie",
    "wof:placetype":"locality"
},
  "geometry": {"coordinates":[125.12641000000001,42.72306],"type":"Point"}
}