{
  "type": "Feature",
  "properties": {
    "gn:admin1_code":"29",
    "gn:asciiname":"Tuozhuo",
    "gn:country_code":"CN",
    "gn:dem":1865,
    "gn:feature_class":"P",
    "gn:feature_code":"PPL",
    "gn:name":"Tuozhuo",
    "gn:population":0,
    "gn:timezone":"Asia/Shanghai",
    "iso:country":"CN",
    "name:zho_x_preferred":[
        "\u62d6\u5353"
    ],
    "wof:name":"Tuozhuo",
    "wof:placetype":"locality"
},
  "geometry": {"coordinates":[102.931,24.1111],"type":"Point"}
}