{
  "type": "Feature",
  "properties": {
    "gn:admin1_code":"4.0",
    "gn:asciiname":"Xuelushe",
    "gn:country_code":"CN",
    "gn:dem":1,
    "gn:feature_class":"P",
    "gn:feature_code":"PPL",
    "gn:name":"Xuelushe",
    "gn:population":0,
    "gn:timezone":"Asia/Shanghai",
    "iso:country":"CN",
    "name:zho_x_preferred":[
        "Xuelushe"
    ],
    "name:zho_x_variant":[
        "\u859b\u9646\u820d"
    ],
    "wof:name":"Xuelushe",
    "wof:placetype":"locality"
},
  "geometry": {"coordinates":[119.85468,33.56049],"type":"Point"}
}