{
  "type": "Feature",
  "properties": {
    "gn:admin1_code":"19.0",
    "gn:asciiname":"Wenguan",
    "gn:country_code":"CN",
    "gn:dem":148,
    "gn:feature_class":"P",
    "gn:feature_code":"PPL",
    "gn:name":"Wenguan",
    "gn:population":0,
    "gn:timezone":"Asia/Shanghai",
    "iso:country":"CN",
    "name:und_x_variant":[
        "\u6587\u5b98"
    ],
    "name:zho_x_preferred":[
        "\u6587\u5b98"
    ],
    "wof:name":"Wenguan",
    "wof:placetype":"locality"
},
  "geometry": {"coordinates":[123.22266,40.94965],"type":"Point"}
}