{
  "type": "Feature",
  "properties": {
    "gn:admin1_code":"8.0",
    "gn:asciiname":"Sanxingcun",
    "gn:country_code":"CN",
    "gn:dem":266,
    "gn:feature_class":"P",
    "gn:feature_code":"PPL",
    "gn:name":"Sanxingcun",
    "gn:population":0,
    "gn:timezone":"Asia/Shanghai",
    "iso:country":"CN",
    "name:zho_x_preferred":[
        "\u4e09\u661f\u6751"
    ],
    "wof:name":"Sanxingcun",
    "wof:placetype":"locality"
},
  "geometry": {"coordinates":[125.07541999999999,48.57895],"type":"Point"}
}