{
  "type": "Feature",
  "properties": {
    "gn:admin1_code":"5",
    "gn:asciiname":"Dalazi",
    "gn:country_code":"CN",
    "gn:dem":569,
    "gn:feature_class":"P",
    "gn:feature_code":"PPL",
    "gn:name":"Dalazi",
    "gn:population":0,
    "gn:timezone":"Asia/Shanghai",
    "iso:country":"CN",
    "name:zho_x_preferred":[
        "\u5927\u782c\u5b50"
    ],
    "wof:name":"Dalazi",
    "wof:placetype":"locality"
},
  "geometry": {"coordinates":[127.875,43.4902],"type":"Point"}
}