{
  "type": "Feature",
  "properties": {
    "gn:admin1_code":"18.0",
    "gn:asciiname":"Xiashuida",
    "gn:country_code":"CN",
    "gn:dem":758,
    "gn:feature_class":"P",
    "gn:feature_code":"PPL",
    "gn:name":"Xiashuida",
    "gn:population":0,
    "gn:timezone":"Asia/Shanghai",
    "iso:country":"CN",
    "name:zho_x_preferred":[
        "\u4e0b\u6c34\u8fbe"
    ],
    "wof:name":"Xiashuida",
    "wof:placetype":"locality"
},
  "geometry": {"coordinates":[108.054,25.5999],"type":"Point"}
}