{
  "type": "Feature",
  "properties": {
    "gn:admin1_code":"26.0",
    "gn:asciiname":"Goumen",
    "gn:country_code":"CN",
    "gn:dem":1103,
    "gn:feature_class":"P",
    "gn:feature_code":"PPL",
    "gn:name":"Goumen",
    "gn:population":0,
    "gn:timezone":"Asia/Shanghai",
    "iso:country":"CN",
    "name:und_x_variant":[
        "\u6c9f\u95e8"
    ],
    "wof:name":"Goumen",
    "wof:placetype":"locality"
},
  "geometry": {"coordinates":[107.31252000000001,34.92590999999999],"type":"Point"}
}