{
  "type": "Feature",
  "properties": {
    "gn:admin1_code":"19",
    "gn:asciiname":"Wulong Linchang",
    "gn:country_code":"CN",
    "gn:dem":228,
    "gn:feature_class":"P",
    "gn:feature_code":"PPLF",
    "gn:name":"Wulong Linchang",
    "gn:population":0,
    "gn:timezone":"Asia/Shanghai",
    "iso:country":"CN",
    "name:und_x_variant":[
        "Wu-lung-k\u2019ou",
        "Wu-lung",
        "Wulong",
        "Wulong Linchang",
        "\u4e94\u9f99\u6797\u573a",
        "\u4e94\u9f99"
    ],
    "wof:name":"Wulong Linchang",
    "wof:placetype":"locality"
},
  "geometry": {"coordinates":[124.25072,41.69529],"type":"Point"}
}