{
  "type": "Feature",
  "properties": {
    "gn:admin1_code":"16.0",
    "gn:asciiname":"Dapengchong",
    "gn:country_code":"CN",
    "gn:dem":91,
    "gn:feature_class":"P",
    "gn:feature_code":"PPL",
    "gn:name":"Dapengchong",
    "gn:population":0,
    "gn:timezone":"Asia/Shanghai",
    "iso:country":"CN",
    "name:zho_x_preferred":[
        "\u5927\u670b\u51b2"
    ],
    "wof:name":"Dapengchong",
    "wof:placetype":"locality"
},
  "geometry": {"coordinates":[110.054,22.2818],"type":"Point"}
}