{
  "type": "Feature",
  "properties": {
    "gn:admin1_code":"8.0",
    "gn:asciiname":"Nijiatun",
    "gn:country_code":"CN",
    "gn:dem":201,
    "gn:feature_class":"P",
    "gn:feature_code":"PPL",
    "gn:name":"Nijiatun",
    "gn:population":0,
    "gn:timezone":"Asia/Shanghai",
    "iso:country":"CN",
    "name:zho_x_preferred":[
        "\u502a\u5bb6\u5c6f"
    ],
    "wof:name":"Nijiatun",
    "wof:placetype":"locality"
},
  "geometry": {"coordinates":[126.88179,47.39107],"type":"Point"}
}