{
  "type": "Feature",
  "properties": {
    "gn:admin1_code":"30",
    "gn:asciiname":"Shanjinchang",
    "gn:country_code":"CN",
    "gn:dem":99,
    "gn:feature_class":"P",
    "gn:feature_code":"PPL",
    "gn:name":"Shanjinchang",
    "gn:population":0,
    "gn:timezone":"Asia/Shanghai",
    "iso:country":"CN",
    "name:zho_x_preferred":[
        "\u4e0a\u91d1\u573a"
    ],
    "wof:name":"Shanjinchang",
    "wof:placetype":"locality"
},
  "geometry": {"coordinates":[116.86646,24.07122],"type":"Point"}
}