{
  "type": "Feature",
  "properties": {
    "gn:admin1_code":"29.0",
    "gn:asciiname":"Wuluding",
    "gn:country_code":"CN",
    "gn:dem":1929,
    "gn:feature_class":"P",
    "gn:feature_code":"PPL",
    "gn:name":"Wuluding",
    "gn:population":0,
    "gn:timezone":"Asia/Shanghai",
    "iso:country":"CN",
    "name:zho_x_preferred":[
        "\u96fe\u9732\u9876"
    ],
    "wof:name":"Wuluding",
    "wof:placetype":"locality"
},
  "geometry": {"coordinates":[103.502,24.8519],"type":"Point"}
}