{
  "type": "Feature",
  "properties": {
    "gn:admin1_code":"16",
    "gn:asciiname":"Dianshanli",
    "gn:country_code":"CN",
    "gn:dem":533,
    "gn:feature_class":"P",
    "gn:feature_code":"PPL",
    "gn:name":"Dianshanli",
    "gn:population":0,
    "gn:timezone":"Asia/Shanghai",
    "iso:country":"CN",
    "name:zho_x_preferred":[
        "\u6bbf\u5c71\u91cc"
    ],
    "wof:name":"Dianshanli",
    "wof:placetype":"locality"
},
  "geometry": {"coordinates":[110.63,25.3185],"type":"Point"}
}