{
  "type": "Feature",
  "properties": {
    "gn:admin1_code":"3",
    "gn:asciiname":"Jietoushan",
    "gn:country_code":"CN",
    "gn:dem":412,
    "gn:feature_class":"P",
    "gn:feature_code":"PPL",
    "gn:name":"Jietoushan",
    "gn:population":0,
    "gn:timezone":"Asia/Shanghai",
    "iso:country":"CN",
    "name:zho_x_preferred":[
        "\u754c\u5934\u5c71"
    ],
    "wof:name":"Jietoushan",
    "wof:placetype":"locality"
},
  "geometry": {"coordinates":[113.89700000000001,26.8823],"type":"Point"}
}