{
  "type": "Feature",
  "properties": {
    "gn:admin1_code":"25.0",
    "gn:asciiname":"Houxujiacun",
    "gn:country_code":"CN",
    "gn:dem":44,
    "gn:feature_class":"P",
    "gn:feature_code":"PPL",
    "gn:name":"Houxujiacun",
    "gn:population":0,
    "gn:timezone":"Asia/Shanghai",
    "iso:country":"CN",
    "name:zho_x_preferred":[
        "\u540e\u8bb8\u5bb6\u6751"
    ],
    "wof:name":"Houxujiacun",
    "wof:placetype":"locality"
},
  "geometry": {"coordinates":[120.0274,36.74458],"type":"Point"}
}