{
  "type": "Feature",
  "properties": {
    "gn:admin1_code":"32.0",
    "gn:asciiname":"Zhenggou",
    "gn:country_code":"CN",
    "gn:dem":558,
    "gn:feature_class":"P",
    "gn:feature_code":"PPL",
    "gn:name":"Zhenggou",
    "gn:population":0,
    "gn:timezone":"Asia/Shanghai",
    "iso:country":"CN",
    "name:zho_x_preferred":[
        "\u90d1\u6c9f"
    ],
    "wof:name":"Zhenggou",
    "wof:placetype":"locality"
},
  "geometry": {"coordinates":[103.7984,30.35989],"type":"Point"}
}