{
  "type": "Feature",
  "properties": {
    "gn:admin1_code":"26.0",
    "gn:asciiname":"Wujia Taizi",
    "gn:country_code":"CN",
    "gn:dem":1335,
    "gn:feature_class":"P",
    "gn:feature_code":"PPL",
    "gn:name":"Wujia Taizi",
    "gn:population":0,
    "gn:timezone":"Asia/Shanghai",
    "iso:country":"CN",
    "name:zho_x_preferred":[
        "\u5434\u5bb6\u53f0\u5b50"
    ],
    "wof:name":"Wujia Taizi",
    "wof:placetype":"locality"
},
  "geometry": {"coordinates":[110.07673,34.34035],"type":"Point"}
}