{
  "type": "Feature",
  "properties": {
    "gn:admin1_code":"12.0",
    "gn:asciiname":"Tao'erwan",
    "gn:country_code":"CN",
    "gn:dem":204,
    "gn:feature_class":"P",
    "gn:feature_code":"PPL",
    "gn:name":"Tao\u2019erwan",
    "gn:population":0,
    "gn:timezone":"Asia/Shanghai",
    "iso:country":"CN",
    "name:und_x_variant":[
        "Tao\u2019erwan"
    ],
    "name:zho_x_preferred":[
        "\u6843\u513f\u6e7e"
    ],
    "wof:name":"Tao'erwan",
    "wof:placetype":"locality"
},
  "geometry": {"coordinates":[111.62298,32.12645],"type":"Point"}
}