{
  "type": "Feature",
  "properties": {
    "gn:admin1_code":"2.0",
    "gn:asciiname":"Liguangyang",
    "gn:country_code":"CN",
    "gn:dem":533,
    "gn:feature_class":"P",
    "gn:feature_code":"PPL",
    "gn:name":"Liguangyang",
    "gn:population":0,
    "gn:timezone":"Asia/Shanghai",
    "iso:country":"CN",
    "name:zho_x_preferred":[
        "\u91cc\u5149\u6d0b"
    ],
    "wof:name":"Liguangyang",
    "wof:placetype":"locality"
},
  "geometry": {"coordinates":[120.71102,29.23936],"type":"Point"}
}