{
  "type": "Feature",
  "properties": {
    "gn:admin1_code":"33.0",
    "gn:asciiname":"Baihe",
    "gn:country_code":"CN",
    "gn:dem":182,
    "gn:feature_class":"P",
    "gn:feature_code":"PPLA4",
    "gn:name":"Baihe",
    "gn:population":0,
    "gn:timezone":"Asia/Shanghai",
    "iso:country":"CN",
    "name:deu_x_preferred":[
        "Baihe"
    ],
    "name:nor_x_preferred":[
        "Baihe"
    ],
    "name:und_x_variant":[
        "Baihe Jiedao"
    ],
    "name:zho_x_preferred":[
        "\u767d\u9e64"
    ],
    "name:zho_x_variant":[
        "\u767d\u9e64\u8857\u9053"
    ],
    "wof:name":"Baihe",
    "wof:placetype":"locality"
},
  "geometry": {"coordinates":[108.46372,31.26348],"type":"Point"}
}