{
  "type": "Feature",
  "properties": {
    "gn:admin1_code":"5.0",
    "gn:asciiname":"Majia Tuozi",
    "gn:country_code":"CN",
    "gn:dem":202,
    "gn:feature_class":"P",
    "gn:feature_code":"PPL",
    "gn:name":"Majia Tuozi",
    "gn:population":0,
    "gn:timezone":"Asia/Shanghai",
    "iso:country":"CN",
    "name:zho_x_preferred":[
        "\u9a6c\u5bb6\u5768\u5b50"
    ],
    "wof:name":"Majia Tuozi",
    "wof:placetype":"locality"
},
  "geometry": {"coordinates":[124.40107,44.24118],"type":"Point"}
}