{
  "type": "Feature",
  "properties": {
    "gn:admin1_code":"12.0",
    "gn:asciiname":"Caojiahe",
    "gn:country_code":"CN",
    "gn:dem":764,
    "gn:feature_class":"P",
    "gn:feature_code":"PPL",
    "gn:name":"Caojiahe",
    "gn:population":0,
    "gn:timezone":"Asia/Shanghai",
    "iso:country":"CN",
    "name:zho_x_preferred":[
        "\u66f9\u5bb6\u6cb3"
    ],
    "wof:name":"Caojiahe",
    "wof:placetype":"locality"
},
  "geometry": {"coordinates":[110.94255,30.14129],"type":"Point"}
}