{
  "type": "Feature",
  "properties": {
    "gn:admin1_code":"32.0",
    "gn:asciiname":"Shuangjiang",
    "gn:country_code":"CN",
    "gn:dem":535,
    "gn:feature_class":"P",
    "gn:feature_code":"PPL",
    "gn:name":"Shuangjiang",
    "gn:population":0,
    "gn:timezone":"Asia/Shanghai",
    "iso:country":"CN",
    "name:ceb_x_preferred":[
        "Shuangjiang"
    ],
    "name:deu_x_preferred":[
        "Shuangjiang"
    ],
    "name:zho_x_preferred":[
        "\u53cc\u6c5f"
    ],
    "wof:name":"Shuangjiang",
    "wof:placetype":"locality"
},
  "geometry": {"coordinates":[104.76000000000001,31.7927],"type":"Point"}
}