{
  "type": "Feature",
  "properties": {
    "gn:admin1_code":"2.0",
    "gn:asciiname":"Huchuantou",
    "gn:country_code":"CN",
    "gn:dem":10,
    "gn:feature_class":"P",
    "gn:feature_code":"PPL",
    "gn:name":"Huchuantou",
    "gn:population":0,
    "gn:timezone":"Asia/Shanghai",
    "iso:country":"CN",
    "name:und_x_variant":[
        "\u6e56\u5ddd\u5934"
    ],
    "wof:name":"Huchuantou",
    "wof:placetype":"locality"
},
  "geometry": {"coordinates":[120.62345999999999,30.27127],"type":"Point"}
}