{
  "type": "Feature",
  "properties": {
    "gn:admin1_code":"30.0",
    "gn:asciiname":"Dasanyucun",
    "gn:country_code":"CN",
    "gn:dem":10,
    "gn:feature_class":"P",
    "gn:feature_code":"PPL",
    "gn:name":"Dasanyucun",
    "gn:population":0,
    "gn:timezone":"Asia/Shanghai",
    "iso:country":"CN",
    "name:und_x_variant":[
        "Dasanxu"
    ],
    "name:zho_x_preferred":[
        "\u8fbe\u4e09\u5729\u6751"
    ],
    "name:zho_x_variant":[
        "\u8fbe\u4e09\u5729"
    ],
    "wof:name":"Dasanyucun",
    "wof:placetype":"locality"
},
  "geometry": {"coordinates":[116.23717000000001,23.02457],"type":"Point"}
}