{
  "type": "Feature",
  "properties": {
    "gn:admin1_code":"10.0",
    "gn:asciiname":"Xiaobeitou",
    "gn:country_code":"CN",
    "gn:dem":266,
    "gn:feature_class":"P",
    "gn:feature_code":"PPL",
    "gn:name":"Xiaobeitou",
    "gn:population":0,
    "gn:timezone":"Asia/Shanghai",
    "iso:country":"CN",
    "name:zho_x_preferred":[
        "\u5c0f\u5317\u5934"
    ],
    "wof:name":"Xiaobeitou",
    "wof:placetype":"locality"
},
  "geometry": {"coordinates":[113.98739999999999,38.44647],"type":"Point"}
}