{
  "type": "Feature",
  "properties": {
    "gn:admin1_code":"12.0",
    "gn:asciiname":"Qiaomai Tian",
    "gn:country_code":"CN",
    "gn:dem":335,
    "gn:feature_class":"P",
    "gn:feature_code":"PPL",
    "gn:name":"Qiaomai Tian",
    "gn:population":0,
    "gn:timezone":"Asia/Shanghai",
    "iso:country":"CN",
    "name:zho_x_preferred":[
        "\u835e\u9ea6\u7530"
    ],
    "wof:name":"Qiaomai Tian",
    "wof:placetype":"locality"
},
  "geometry": {"coordinates":[111.89543,31.52326],"type":"Point"}
}