{
  "type": "Feature",
  "properties": {
    "gn:admin1_code":"24.0",
    "gn:asciiname":"Qiyugou",
    "gn:country_code":"CN",
    "gn:dem":1315,
    "gn:feature_class":"P",
    "gn:feature_code":"PPL",
    "gn:name":"Qiyugou",
    "gn:population":0,
    "gn:timezone":"Asia/Shanghai",
    "iso:country":"CN",
    "name:zho_x_preferred":[
        "\u69ed\u6986\u6c9f"
    ],
    "wof:name":"Qiyugou",
    "wof:placetype":"locality"
},
  "geometry": {"coordinates":[112.61252,38.94642],"type":"Point"}
}