{
  "type": "Feature",
  "properties": {
    "gn:admin1_code":"29.0",
    "gn:asciiname":"Shifoshao",
    "gn:country_code":"CN",
    "gn:dem":2336,
    "gn:feature_class":"P",
    "gn:feature_code":"PPL",
    "gn:name":"Shifoshao",
    "gn:population":0,
    "gn:timezone":"Asia/Shanghai",
    "iso:country":"CN",
    "name:zho_x_preferred":[
        "\u77f3\u4f5b\u54e8"
    ],
    "wof:name":"Shifoshao",
    "wof:placetype":"locality"
},
  "geometry": {"coordinates":[100.374,25.3036],"type":"Point"}
}