{
  "type": "Feature",
  "properties": {
    "gn:admin1_code":"11.0",
    "gn:asciiname":"Mahuangtang",
    "gn:country_code":"CN",
    "gn:dem":143,
    "gn:feature_class":"P",
    "gn:feature_code":"PPL",
    "gn:name":"Mahuangtang",
    "gn:population":0,
    "gn:timezone":"Asia/Shanghai",
    "iso:country":"CN",
    "name:zho_x_preferred":[
        "\u8682\u8757\u5858"
    ],
    "wof:name":"Mahuangtang",
    "wof:placetype":"locality"
},
  "geometry": {"coordinates":[113.26732,26.76102],"type":"Point"}
}