{
  "type": "Feature",
  "properties": {
    "gn:admin1_code":"29",
    "gn:asciiname":"Heibainiu",
    "gn:country_code":"CN",
    "gn:dem":1616,
    "gn:feature_class":"P",
    "gn:feature_code":"PPL",
    "gn:name":"Heibainiu",
    "gn:population":0,
    "gn:timezone":"Asia/Shanghai",
    "iso:country":"CN",
    "name:zho_x_preferred":[
        "\u9ed1\u767d\u725b"
    ],
    "wof:name":"Heibainiu",
    "wof:placetype":"locality"
},
  "geometry": {"coordinates":[102.93077,24.07988],"type":"Point"}
}