{
  "type": "Feature",
  "properties": {
    "gn:admin1_code":"14.0",
    "gn:asciiname":"Zhangdonggongma",
    "gn:country_code":"CN",
    "gn:dem":4630,
    "gn:feature_class":"P",
    "gn:feature_code":"PPL",
    "gn:name":"Zhangdonggongma",
    "gn:population":0,
    "gn:timezone":"Asia/Shanghai",
    "iso:country":"CN",
    "name:und_x_variant":[
        "Jiangdongwoma",
        "Zhangdonggongma"
    ],
    "name:zho_x_preferred":[
        "\u6c5f\u4e1c\u6c83\u739b"
    ],
    "name:zho_x_variant":[
        "\u5f20\u4e1c\u8d21\u739b"
    ],
    "wof:name":"Zhangdonggongma",
    "wof:placetype":"locality"
},
  "geometry": {"coordinates":[81.47800000000002,30.8105],"type":"Point"}
}