{
  "type": "Feature",
  "properties": {
    "gn:admin1_code":"9.0",
    "gn:asciiname":"Liuligou",
    "gn:country_code":"CN",
    "gn:dem":372,
    "gn:feature_class":"P",
    "gn:feature_code":"PPL",
    "gn:name":"Liuligou",
    "gn:population":0,
    "gn:timezone":"Asia/Shanghai",
    "iso:country":"CN",
    "name:zho_x_preferred":[
        "\u7409\u7483\u6c9f"
    ],
    "wof:name":"Liuligou",
    "wof:placetype":"locality"
},
  "geometry": {"coordinates":[113.19508999999999,34.28662],"type":"Point"}
}