{
  "type": "Feature",
  "properties": {
    "gn:admin1_code":"25",
    "gn:asciiname":"Miaoyicun",
    "gn:country_code":"CN",
    "gn:dem":25,
    "gn:feature_class":"P",
    "gn:feature_code":"PPL",
    "gn:name":"Miaoyicun",
    "gn:population":0,
    "gn:timezone":"Asia/Shanghai",
    "iso:country":"CN",
    "name:zho_x_preferred":[
        "\u5e99\u4e00\u6751"
    ],
    "wof:name":"Miaoyicun",
    "wof:placetype":"locality"
},
  "geometry": {"coordinates":[117.02800000000001,36.9688],"type":"Point"}
}