{
  "type": "Feature",
  "properties": {
    "gn:admin1_code":"9.0",
    "gn:asciiname":"Gelou",
    "gn:country_code":"CN",
    "gn:dem":50,
    "gn:feature_class":"P",
    "gn:feature_code":"PPL",
    "gn:name":"Gelou",
    "gn:population":0,
    "gn:timezone":"Asia/Shanghai",
    "iso:country":"CN",
    "name:bul_x_preferred":[
        "\u0413\u0435\u043b\u0443"
    ],
    "name:fin_x_preferred":[
        "Gelou"
    ],
    "name:fra_x_preferred":[
        "Gelou"
    ],
    "name:heb_x_preferred":[
        "\u05d2'\u05dc\u05d5"
    ],
    "name:pol_x_preferred":[
        "Gelou"
    ],
    "name:ron_x_preferred":[
        "Gelou"
    ],
    "name:zho_x_preferred":[
        "\u845b\u697c"
    ],
    "wof:name":"Gelou",
    "wof:placetype":"locality"
},
  "geometry": {"coordinates":[114.87229000000001,33.62351],"type":"Point"}
}