{
  "type": "Feature",
  "properties": {
    "gn:admin1_code":"21.0",
    "gn:asciiname":"Maoji Zhaizi",
    "gn:country_code":"CN",
    "gn:dem":1347,
    "gn:feature_class":"P",
    "gn:feature_code":"PPL",
    "gn:name":"Maoji Zhaizi",
    "gn:population":0,
    "gn:timezone":"Asia/Shanghai",
    "iso:country":"CN",
    "name:zho_x_preferred":[
        "\u5192\u8bb0\u5be8\u5b50"
    ],
    "wof:name":"Maoji Zhaizi",
    "wof:placetype":"locality"
},
  "geometry": {"coordinates":[107.42400000000001,37.8793],"type":"Point"}
}