{
  "type": "Feature",
  "properties": {
    "gn:admin1_code":"3.0",
    "gn:asciiname":"Xiangxicun",
    "gn:country_code":"CN",
    "gn:dem":23,
    "gn:feature_class":"P",
    "gn:feature_code":"PPL",
    "gn:name":"Xiangxicun",
    "gn:population":0,
    "gn:timezone":"Asia/Shanghai",
    "iso:country":"CN",
    "name:und_x_variant":[
        "\u8297\u6eaa\u6751"
    ],
    "wof:name":"Xiangxicun",
    "wof:placetype":"locality"
},
  "geometry": {"coordinates":[116.35323,28.59303],"type":"Point"}
}