{
  "type": "Feature",
  "properties": {
    "gn:admin1_code":"26.0",
    "gn:asciiname":"Shangchangjiawan",
    "gn:country_code":"CN",
    "gn:dem":945,
    "gn:feature_class":"P",
    "gn:feature_code":"PPL",
    "gn:name":"Shangchangjiawan",
    "gn:population":0,
    "gn:timezone":"Asia/Shanghai",
    "iso:country":"CN",
    "name:zho_x_preferred":[
        "\u4e0a\u5e38\u5bb6\u6e7e"
    ],
    "wof:name":"Shangchangjiawan",
    "wof:placetype":"locality"
},
  "geometry": {"coordinates":[109.53476999999999,32.46504],"type":"Point"}
}