{
  "type": "Feature",
  "properties": {
    "gn:admin1_code":"04",
    "gn:asciiname":"Doulong",
    "gn:country_code":"CN",
    "gn:dem":2,
    "gn:feature_class":"P",
    "gn:feature_code":"PPL",
    "gn:name":"Doulong",
    "gn:population":0,
    "gn:timezone":"Asia/Shanghai",
    "iso:country":"CN",
    "name:und_x_variant":[
        "\u6597\u9f99"
    ],
    "wof:name":"Doulong",
    "wof:placetype":"locality"
},
  "geometry": {"coordinates":[120.58214,33.46108],"type":"Point"}
}