{
  "type": "Feature",
  "properties": {
    "gn:admin1_code":"16",
    "gn:asciiname":"Chating'ao",
    "gn:country_code":"CN",
    "gn:dem":1560,
    "gn:feature_class":"P",
    "gn:feature_code":"PPL",
    "gn:name":"Chating\u2019ao",
    "gn:population":0,
    "gn:timezone":"Asia/Shanghai",
    "iso:country":"CN",
    "name:und_x_variant":[
        "Chating\u2019ao"
    ],
    "name:zho_x_preferred":[
        "\u8336\u4ead\u51f9"
    ],
    "wof:name":"Chating'ao",
    "wof:placetype":"locality"
},
  "geometry": {"coordinates":[110.837,26.1567],"type":"Point"}
}