{
  "type": "Feature",
  "properties": {
    "gn:admin1_code":"15.0",
    "gn:asciiname":"Lizuizi",
    "gn:country_code":"CN",
    "gn:dem":1448,
    "gn:feature_class":"P",
    "gn:feature_code":"PPL",
    "gn:name":"Lizuizi",
    "gn:population":0,
    "gn:timezone":"Asia/Shanghai",
    "iso:country":"CN",
    "name:und_x_variant":[
        "\u674e\u5480\u5b50"
    ],
    "wof:name":"Lizuizi",
    "wof:placetype":"locality"
},
  "geometry": {"coordinates":[107.73809,36.75758],"type":"Point"}
}