{
  "type": "Feature",
  "properties": {
    "gn:admin1_code":"32.0",
    "gn:asciiname":"Jihaoyuanjia",
    "gn:country_code":"CN",
    "gn:dem":3038,
    "gn:feature_class":"P",
    "gn:feature_code":"PPL",
    "gn:name":"Jihaoyuanjia",
    "gn:population":0,
    "gn:timezone":"Asia/Shanghai",
    "iso:country":"CN",
    "name:zho_x_preferred":[
        "\u53ca\u53f7\u56ed\u7532"
    ],
    "name:zho_x_variant":[
        "\u53ca\u53f7\u5143\u7532"
    ],
    "wof:name":"Jihaoyuanjia",
    "wof:placetype":"locality"
},
  "geometry": {"coordinates":[102.77200000000001,28.4624],"type":"Point"}
}