{
  "type": "Feature",
  "properties": {
    "gn:admin1_code":"14",
    "gn:asciiname":"Jicun",
    "gn:country_code":"CN",
    "gn:dem":4398,
    "gn:feature_class":"P",
    "gn:feature_code":"PPL",
    "gn:name":"Jicun",
    "gn:population":0,
    "gn:timezone":"Asia/Urumqi",
    "iso:country":"CN",
    "name:zho_x_preferred":[
        "\u5409\u6751"
    ],
    "wof:name":"Jicun",
    "wof:placetype":"locality"
},
  "geometry": {"coordinates":[88.80500000000001,28.8353],"type":"Point"}
}