{
  "type": "Feature",
  "properties": {
    "gn:admin1_code":"11.0",
    "gn:asciiname":"Dashuigou",
    "gn:country_code":"CN",
    "gn:dem":222,
    "gn:feature_class":"P",
    "gn:feature_code":"PPL",
    "gn:name":"Dashuigou",
    "gn:population":0,
    "gn:timezone":"Asia/Shanghai",
    "iso:country":"CN",
    "name:zho_x_preferred":[
        "\u6253\u6c34\u6c9f"
    ],
    "wof:name":"Dashuigou",
    "wof:placetype":"locality"
},
  "geometry": {"coordinates":[111.13884,28.75401],"type":"Point"}
}