{
  "type": "Feature",
  "properties": {
    "gn:admin1_code":"12.0",
    "gn:asciiname":"Huangjialing",
    "gn:country_code":"CN",
    "gn:dem":322,
    "gn:feature_class":"P",
    "gn:feature_code":"PPL",
    "gn:name":"Huangjialing",
    "gn:population":0,
    "gn:timezone":"Asia/Shanghai",
    "iso:country":"CN",
    "name:zho_x_preferred":[
        "Huangjialing"
    ],
    "name:zho_x_variant":[
        "\u9ec4\u5bb6\u5cad"
    ],
    "wof:name":"Huangjialing",
    "wof:placetype":"locality"
},
  "geometry": {"coordinates":[111.49254000000001,30.017],"type":"Point"}
}