{
  "type": "Feature",
  "properties": {
    "gn:admin1_code":"10.0",
    "gn:asciiname":"Xinchengzhuang",
    "gn:country_code":"CN",
    "gn:dem":462,
    "gn:feature_class":"P",
    "gn:feature_code":"PPL",
    "gn:name":"Xinchengzhuang",
    "gn:population":0,
    "gn:timezone":"Asia/Shanghai",
    "iso:country":"CN",
    "name:zho_x_preferred":[
        "\u65b0\u57ce\u5e84"
    ],
    "wof:name":"Xinchengzhuang",
    "wof:placetype":"locality"
},
  "geometry": {"coordinates":[114.59926000000002,39.13033],"type":"Point"}
}