{
  "type": "Feature",
  "properties": {
    "gn:admin1_code":"11.0",
    "gn:asciiname":"Liangpaipo",
    "gn:country_code":"CN",
    "gn:dem":264,
    "gn:feature_class":"P",
    "gn:feature_code":"PPL",
    "gn:name":"Liangpaipo",
    "gn:population":0,
    "gn:timezone":"Asia/Shanghai",
    "iso:country":"CN",
    "name:zho_x_preferred":[
        "\u4eae\u6392\u5761"
    ],
    "wof:name":"Liangpaipo",
    "wof:placetype":"locality"
},
  "geometry": {"coordinates":[110.03283,28.39925],"type":"Point"}
}