{
  "type": "Feature",
  "properties": {
    "gn:admin1_code":"11",
    "gn:asciiname":"Maozichong",
    "gn:country_code":"CN",
    "gn:dem":388,
    "gn:feature_class":"P",
    "gn:feature_code":"PPL",
    "gn:name":"Maozichong",
    "gn:population":0,
    "gn:timezone":"Asia/Shanghai",
    "iso:country":"CN",
    "name:zho_x_preferred":[
        "\u732b\u4ed4\u51b2"
    ],
    "wof:name":"Maozichong",
    "wof:placetype":"locality"
},
  "geometry": {"coordinates":[112.16253,25.30248],"type":"Point"}
}