{
  "type": "Feature",
  "properties": {
    "gn:admin1_code":"4.0",
    "gn:asciiname":"Hewanli",
    "gn:country_code":"CN",
    "gn:dem":7,
    "gn:feature_class":"P",
    "gn:feature_code":"PPL",
    "gn:name":"Hewanli",
    "gn:population":0,
    "gn:timezone":"Asia/Shanghai",
    "iso:country":"CN",
    "name:zho_x_preferred":[
        "\u6cb3\u6e7e\u91cc"
    ],
    "wof:name":"Hewanli",
    "wof:placetype":"locality"
},
  "geometry": {"coordinates":[119.76893,32.00825],"type":"Point"}
}