{
  "type": "Feature",
  "properties": {
    "gn:admin1_code":"1.0",
    "gn:asciiname":"Sanxingcun",
    "gn:country_code":"CN",
    "gn:dem":32,
    "gn:feature_class":"P",
    "gn:feature_code":"PPL",
    "gn:name":"Sanxingcun",
    "gn:population":0,
    "gn:timezone":"Asia/Shanghai",
    "iso:country":"CN",
    "name:zho_x_preferred":[
        "\u4e09\u661f\u6751"
    ],
    "wof:name":"Sanxingcun",
    "wof:placetype":"locality"
},
  "geometry": {"coordinates":[116.81054,32.10968],"type":"Point"}
}