{
  "type": "Feature",
  "properties": {
    "gn:admin1_code":"2.0",
    "gn:asciiname":"Taojiayan",
    "gn:country_code":"CN",
    "gn:dem":35,
    "gn:feature_class":"P",
    "gn:feature_code":"PPL",
    "gn:name":"Taojiayan",
    "gn:population":0,
    "gn:timezone":"Asia/Shanghai",
    "iso:country":"CN",
    "name:und_x_variant":[
        "\u9676\u5bb6\u5830"
    ],
    "wof:name":"Taojiayan",
    "wof:placetype":"locality"
},
  "geometry": {"coordinates":[119.58262000000001,30.9161],"type":"Point"}
}