{
  "type": "Feature",
  "properties": {
    "gn:admin1_code":"13",
    "gn:asciiname":"Shiyaofang",
    "gn:country_code":"CN",
    "gn:dem":2948,
    "gn:feature_class":"P",
    "gn:feature_code":"PPL",
    "gn:name":"Shiyaofang",
    "gn:population":0,
    "gn:timezone":"Asia/Urumqi",
    "iso:country":"CN",
    "name:zho_x_preferred":[
        "\u77f3\u7a91\u623f"
    ],
    "wof:name":"Shiyaofang",
    "wof:placetype":"locality"
},
  "geometry": {"coordinates":[94.56483,42.94736],"type":"Point"}
}