{
  "type": "Feature",
  "properties": {
    "gn:admin1_code":"25",
    "gn:asciiname":"Dasuozhuang",
    "gn:country_code":"CN",
    "gn:dem":46,
    "gn:feature_class":"P",
    "gn:feature_code":"PPL",
    "gn:name":"Dasuozhuang",
    "gn:population":0,
    "gn:timezone":"Asia/Shanghai",
    "iso:country":"CN",
    "name:zho_x_preferred":[
        "\u5927\u7d22\u5e84"
    ],
    "wof:name":"Dasuozhuang",
    "wof:placetype":"locality"
},
  "geometry": {"coordinates":[115.54900000000001,36.2752],"type":"Point"}
}