{
  "type": "Feature",
  "properties": {
    "gn:admin1_code":"13",
    "gn:asciiname":"Liuzimiao",
    "gn:country_code":"CN",
    "gn:dem":468,
    "gn:feature_class":"P",
    "gn:feature_code":"PPL",
    "gn:name":"Liuzimiao",
    "gn:population":0,
    "gn:timezone":"Asia/Urumqi",
    "iso:country":"CN",
    "name:zho_x_preferred":[
        "\u7559\u5b50\u5e99"
    ],
    "wof:name":"Liuzimiao",
    "wof:placetype":"locality"
},
  "geometry": {"coordinates":[87.59650999999999,44.18345],"type":"Point"}
}