{
  "type": "Feature",
  "properties": {
    "gn:admin1_code":"02",
    "gn:asciiname":"Jinkeng",
    "gn:cc2":"CN",
    "gn:country_code":"CN",
    "gn:dem":425,
    "gn:feature_class":"P",
    "gn:feature_code":"PPL",
    "gn:name":"Jinkeng",
    "gn:population":0,
    "gn:timezone":"Asia/Shanghai",
    "iso:country":"CN",
    "name:und_x_variant":[
        "Chin-k\u2019eng-k\u2019ou",
        "Jinkeng"
    ],
    "wof:name":"Jinkeng",
    "wof:placetype":"locality"
},
  "geometry": {"coordinates":[120.33444,28.56278],"type":"Point"}
}