{
  "type": "Feature",
  "properties": {
    "gn:admin1_code":"4.0",
    "gn:asciiname":"Xidafangcun",
    "gn:country_code":"CN",
    "gn:dem":5,
    "gn:feature_class":"P",
    "gn:feature_code":"PPL",
    "gn:name":"Xidafangcun",
    "gn:population":0,
    "gn:timezone":"Asia/Shanghai",
    "iso:country":"CN",
    "name:und_x_variant":[
        "\u897f\u5927\u623f\u6751"
    ],
    "name:zho_x_preferred":[
        "\u897f\u5927\u623f\u6751"
    ],
    "wof:name":"Xidafangcun",
    "wof:placetype":"locality"
},
  "geometry": {"coordinates":[120.50483,31.8536],"type":"Point"}
}