{
  "type": "Feature",
  "properties": {
    "gn:admin1_code":"24.0",
    "gn:asciiname":"Xishantou",
    "gn:country_code":"CN",
    "gn:dem":1323,
    "gn:feature_class":"P",
    "gn:feature_code":"PPL",
    "gn:name":"Xishantou",
    "gn:population":0,
    "gn:timezone":"Asia/Shanghai",
    "iso:country":"CN",
    "name:zho_x_preferred":[
        "\u897f\u5c71\u5934"
    ],
    "wof:name":"Xishantou",
    "wof:placetype":"locality"
},
  "geometry": {"coordinates":[111.95401,37.59847],"type":"Point"}
}