{
  "type": "Feature",
  "properties": {
    "gn:admin1_code":"01",
    "gn:asciiname":"Fanghu",
    "gn:country_code":"CN",
    "gn:dem":71,
    "gn:feature_class":"P",
    "gn:feature_code":"PPL",
    "gn:name":"Fanghu",
    "gn:population":0,
    "gn:timezone":"Asia/Shanghai",
    "iso:country":"CN",
    "name:und_x_variant":[
        "Fanghushan",
        "Fanghu"
    ],
    "name:zho_x_preferred":[
        "\u9632\u864e"
    ],
    "wof:name":"Fanghu",
    "wof:placetype":"locality"
},
  "geometry": {"coordinates":[116.92688,31.69049],"type":"Point"}
}