{
  "type": "Feature",
  "properties": {
    "gn:admin1_code":"30.0",
    "gn:asciiname":"Longzui",
    "gn:country_code":"CN",
    "gn:dem":105,
    "gn:feature_class":"P",
    "gn:feature_code":"PPL",
    "gn:name":"Longzui",
    "gn:population":0,
    "gn:timezone":"Asia/Shanghai",
    "iso:country":"CN",
    "name:zho_x_preferred":[
        "Longzui"
    ],
    "name:zho_x_variant":[
        "\u9f99\u5480"
    ],
    "wof:name":"Longzui",
    "wof:placetype":"locality"
},
  "geometry": {"coordinates":[112.31889,24.76472],"type":"Point"}
}