{
  "type": "Feature",
  "properties": {
    "gn:admin1_code":"24.0",
    "gn:asciiname":"Xinyao",
    "gn:cc2":"CN",
    "gn:country_code":"CN",
    "gn:dem":1040,
    "gn:feature_class":"P",
    "gn:feature_code":"PPL",
    "gn:name":"Xinyao",
    "gn:population":0,
    "gn:timezone":"Asia/Shanghai",
    "iso:country":"CN",
    "name:und_x_variant":[
        "Hou-hsin-yao",
        "Hsin-yao",
        "Xinyao"
    ],
    "name:vie_x_preferred":[
        "T\u00e2n dao"
    ],
    "wof:name":"Xinyao",
    "wof:placetype":"locality"
},
  "geometry": {"coordinates":[111.22638999999999,39.09972],"type":"Point"}
}