{
  "type": "Feature",
  "properties": {
    "gn:admin1_code":"2.0",
    "gn:asciiname":"Gongjieling",
    "gn:country_code":"CN",
    "gn:dem":660,
    "gn:feature_class":"P",
    "gn:feature_code":"PPL",
    "gn:name":"Gongjieling",
    "gn:population":0,
    "gn:timezone":"Asia/Shanghai",
    "iso:country":"CN",
    "name:zho_x_preferred":[
        "\u516c\u754c\u5cad"
    ],
    "wof:name":"Gongjieling",
    "wof:placetype":"locality"
},
  "geometry": {"coordinates":[121.02927,29.20399],"type":"Point"}
}