{
  "type": "Feature",
  "properties": {
    "gn:admin1_code":"29.0",
    "gn:asciiname":"Shuixiying",
    "gn:country_code":"CN",
    "gn:dem":2058,
    "gn:feature_class":"P",
    "gn:feature_code":"PPL",
    "gn:name":"Shuixiying",
    "gn:population":0,
    "gn:timezone":"Asia/Shanghai",
    "iso:country":"CN",
    "name:zho_x_preferred":[
        "\u6c34\u897f\u8425"
    ],
    "wof:name":"Shuixiying",
    "wof:placetype":"locality"
},
  "geometry": {"coordinates":[104.191,25.9641],"type":"Point"}
}