{
  "type": "Feature",
  "properties": {
    "gn:admin1_code":"9.0",
    "gn:asciiname":"Tuti",
    "gn:country_code":"CN",
    "gn:dem":1062,
    "gn:feature_class":"P",
    "gn:feature_code":"PPL",
    "gn:name":"Tuti",
    "gn:population":0,
    "gn:timezone":"Asia/Shanghai",
    "iso:country":"CN",
    "name:cat_x_preferred":[
        "Tuti"
    ],
    "name:ceb_x_preferred":[
        "Tuti"
    ],
    "name:deu_x_preferred":[
        "Tuti"
    ],
    "name:fra_x_preferred":[
        "Tuti"
    ],
    "name:por_x_preferred":[
        "Tuti"
    ],
    "name:sco_x_preferred":[
        "Tuti"
    ],
    "name:swe_x_preferred":[
        "Tuti"
    ],
    "name:zho_x_preferred":[
        "\u571f\u68af"
    ],
    "wof:name":"Tuti",
    "wof:placetype":"locality"
},
  "geometry": {"coordinates":[113.62472,35.66453],"type":"Point"}
}