{
  "type": "Feature",
  "properties": {
    "gn:admin1_code":"32.0",
    "gn:asciiname":"Tieqianwan",
    "gn:country_code":"CN",
    "gn:dem":359,
    "gn:feature_class":"P",
    "gn:feature_code":"PPL",
    "gn:name":"Tieqianwan",
    "gn:population":0,
    "gn:timezone":"Asia/Shanghai",
    "iso:country":"CN",
    "name:zho_x_preferred":[
        "\u94c1\u94b1\u5846"
    ],
    "wof:name":"Tieqianwan",
    "wof:placetype":"locality"
},
  "geometry": {"coordinates":[105.27254000000001,30.53962000000001],"type":"Point"}
}