{
  "type": "Feature",
  "properties": {
    "gn:admin1_code":"3.0",
    "gn:asciiname":"Lishaxi",
    "gn:country_code":"CN",
    "gn:dem":165,
    "gn:feature_class":"P",
    "gn:feature_code":"PPL",
    "gn:name":"Lishaxi",
    "gn:population":0,
    "gn:timezone":"Asia/Shanghai",
    "iso:country":"CN",
    "name:zho_x_preferred":[
        "\u91cc\u6c99\u6eaa"
    ],
    "wof:name":"Lishaxi",
    "wof:placetype":"locality"
},
  "geometry": {"coordinates":[117.39116,28.26682000000001],"type":"Point"}
}