{
  "type": "Feature",
  "properties": {
    "gn:admin1_code":"19.0",
    "gn:asciiname":"Da'outun",
    "gn:country_code":"CN",
    "gn:dem":90,
    "gn:feature_class":"P",
    "gn:feature_code":"PPL",
    "gn:name":"Da\u2019outun",
    "gn:population":0,
    "gn:timezone":"Asia/Shanghai",
    "iso:country":"CN",
    "name:und_x_variant":[
        "Da\u2019outun"
    ],
    "name:zho_x_preferred":[
        "\u5927\u6b27\u5c6f"
    ],
    "wof:name":"Da'outun",
    "wof:placetype":"locality"
},
  "geometry": {"coordinates":[122.21299999999999,39.6989],"type":"Point"}
}