{
  "type": "Feature",
  "properties": {
    "gn:admin1_code":"29",
    "gn:asciiname":"Yangjie",
    "gn:country_code":"CN",
    "gn:dem":1846,
    "gn:feature_class":"P",
    "gn:feature_code":"PPL",
    "gn:name":"Yangjie",
    "gn:population":0,
    "gn:timezone":"Asia/Shanghai",
    "iso:country":"CN",
    "wof:name":"Yangjie",
    "wof:placetype":"locality"
},
  "geometry": {"coordinates":[101.92749999999999,25.49056],"type":"Point"}
}