{
  "type": "Feature",
  "properties": {
    "gn:admin1_code":"8.0",
    "gn:asciiname":"Sipailiucun",
    "gn:country_code":"CN",
    "gn:dem":191,
    "gn:feature_class":"P",
    "gn:feature_code":"PPL",
    "gn:name":"Sipailiucun",
    "gn:population":0,
    "gn:timezone":"Asia/Shanghai",
    "iso:country":"CN",
    "name:zho_x_preferred":[
        "\u56db\u6392\u516d\u6751"
    ],
    "wof:name":"Sipailiucun",
    "wof:placetype":"locality"
},
  "geometry": {"coordinates":[125.71424,46.89224],"type":"Point"}
}