{
  "type": "Feature",
  "properties": {
    "gn:admin1_code":"25.0",
    "gn:asciiname":"Dongliangcun",
    "gn:country_code":"CN",
    "gn:dem":11,
    "gn:feature_class":"P",
    "gn:feature_code":"PPL",
    "gn:name":"Dongliangcun",
    "gn:population":0,
    "gn:timezone":"Asia/Shanghai",
    "iso:country":"CN",
    "name:zho_x_preferred":[
        "\u4e1c\u826f\u6751"
    ],
    "wof:name":"Dongliangcun",
    "wof:placetype":"locality"
},
  "geometry": {"coordinates":[120.24617000000001,37.5267],"type":"Point"}
}