{
  "type": "Feature",
  "properties": {
    "gn:admin1_code":"30",
    "gn:asciiname":"Xiahaizai",
    "gn:country_code":"CN",
    "gn:dem":27,
    "gn:feature_class":"P",
    "gn:feature_code":"PPL",
    "gn:name":"Xiahaizai",
    "gn:population":0,
    "gn:timezone":"Asia/Urumqi",
    "iso:country":"CN",
    "name:zho_x_preferred":[
        "\u4e0b\u6d77\u4ed4"
    ],
    "wof:name":"Xiahaizai",
    "wof:placetype":"locality"
},
  "geometry": {"coordinates":[110.48622,20.54746],"type":"Point"}
}