{
  "type": "Feature",
  "properties": {
    "gn:admin1_code":"16.0",
    "gn:asciiname":"Ping'ao",
    "gn:country_code":"CN",
    "gn:dem":180,
    "gn:feature_class":"P",
    "gn:feature_code":"PPL",
    "gn:name":"Ping\u2019ao",
    "gn:population":0,
    "gn:timezone":"Asia/Shanghai",
    "iso:country":"CN",
    "name:und_x_variant":[
        "Ping\u2019ao"
    ],
    "name:zho_x_preferred":[
        "\u5e73\u51f9"
    ],
    "wof:name":"Ping'ao",
    "wof:placetype":"locality"
},
  "geometry": {"coordinates":[109.84099999999999,22.3469],"type":"Point"}
}