{
  "type": "Feature",
  "properties": {
    "gn:admin1_code":"8.0",
    "gn:asciiname":"Fuqiangcun",
    "gn:country_code":"CN",
    "gn:dem":191,
    "gn:feature_class":"P",
    "gn:feature_code":"PPL",
    "gn:name":"Fuqiangcun",
    "gn:population":0,
    "gn:timezone":"Asia/Shanghai",
    "iso:country":"CN",
    "name:zho_x_preferred":[
        "\u5bcc\u5f3a\u6751"
    ],
    "wof:name":"Fuqiangcun",
    "wof:placetype":"locality"
},
  "geometry": {"coordinates":[130.58528000000001,46.37841],"type":"Point"}
}