{
  "type": "Feature",
  "properties": {
    "gn:admin1_code":"1.0",
    "gn:asciiname":"Songkecun",
    "gn:country_code":"CN",
    "gn:dem":63,
    "gn:feature_class":"P",
    "gn:feature_code":"PPL",
    "gn:name":"Songkecun",
    "gn:population":0,
    "gn:timezone":"Asia/Shanghai",
    "iso:country":"CN",
    "name:zho_x_preferred":[
        "\u677e\u68f5\u6751"
    ],
    "wof:name":"Songkecun",
    "wof:placetype":"locality"
},
  "geometry": {"coordinates":[116.71657,31.69952],"type":"Point"}
}