{
  "type": "Feature",
  "properties": {
    "gn:admin1_code":"7.0",
    "gn:asciiname":"Xiaocheng",
    "gn:country_code":"CN",
    "gn:dem":48,
    "gn:feature_class":"P",
    "gn:feature_code":"PPLA4",
    "gn:name":"Xiaocheng",
    "gn:population":0,
    "gn:timezone":"Asia/Shanghai",
    "iso:country":"CN",
    "name:und_x_variant":[
        "Hsiao-ch\u2019eng",
        "Tinhai",
        "Ting-hai",
        "Xiaocheng",
        "Xiaocheng Zhen"
    ],
    "name:zho_x_preferred":[
        "\u7b71\u57d5"
    ],
    "name:zho_x_variant":[
        "\u7b71\u57d5\u9547"
    ],
    "wof:name":"Xiaocheng",
    "wof:placetype":"locality"
},
  "geometry": {"coordinates":[119.78541,26.29433],"type":"Point"}
}