{
  "type": "Feature",
  "properties": {
    "gn:admin1_code":"2.0",
    "gn:asciiname":"Nima",
    "gn:country_code":"CN",
    "gn:dem":99,
    "gn:feature_class":"P",
    "gn:feature_code":"PPL",
    "gn:name":"Nima",
    "gn:population":0,
    "gn:timezone":"Asia/Shanghai",
    "iso:country":"CN",
    "name:und_x_variant":[
        "\u6ce5\u9a6c"
    ],
    "name:zho_x_preferred":[
        "Nima"
    ],
    "wof:name":"Nima",
    "wof:placetype":"locality"
},
  "geometry": {"coordinates":[119.69087,30.32001],"type":"Point"}
}