{
  "type": "Feature",
  "properties": {
    "gn:admin1_code":"14.0",
    "gn:asciiname":"Chanongda",
    "gn:country_code":"CN",
    "gn:dem":4110,
    "gn:feature_class":"P",
    "gn:feature_code":"PPL",
    "gn:name":"Chanongda",
    "gn:population":0,
    "gn:timezone":"Asia/Urumqi",
    "iso:country":"CN",
    "name:zho_x_preferred":[
        "\u67e5\u5f04\u6253"
    ],
    "wof:name":"Chanongda",
    "wof:placetype":"locality"
},
  "geometry": {"coordinates":[95.10905,31.6503],"type":"Point"}
}