{
  "type": "Feature",
  "properties": {
    "gn:admin1_code":"4.0",
    "gn:asciiname":"Qianmatou",
    "gn:country_code":"CN",
    "gn:dem":2,
    "gn:feature_class":"P",
    "gn:feature_code":"PPL",
    "gn:name":"Qianmatou",
    "gn:population":0,
    "gn:timezone":"Asia/Shanghai",
    "iso:country":"CN",
    "name:zho_x_preferred":[
        "Qianmatou"
    ],
    "name:zho_x_variant":[
        "\u94b1\u7801\u5934"
    ],
    "wof:name":"Qianmatou",
    "wof:placetype":"locality"
},
  "geometry": {"coordinates":[119.61863999999998,33.92749],"type":"Point"}
}