{
  "type": "Feature",
  "properties": {
    "gn:admin1_code":"19.0",
    "gn:asciiname":"Jiangjungou",
    "gn:country_code":"CN",
    "gn:dem":145,
    "gn:feature_class":"P",
    "gn:feature_code":"PPL",
    "gn:name":"Jiangjungou",
    "gn:population":0,
    "gn:timezone":"Asia/Shanghai",
    "iso:country":"CN",
    "name:zho_x_preferred":[
        "\u5c06\u519b\u6c9f"
    ],
    "wof:name":"Jiangjungou",
    "wof:placetype":"locality"
},
  "geometry": {"coordinates":[121.63500000000001,41.5713],"type":"Point"}
}