{
  "type": "Feature",
  "properties": {
    "gn:admin1_code":"29",
    "gn:asciiname":"Yulongge",
    "gn:country_code":"CN",
    "gn:dem":1444,
    "gn:feature_class":"P",
    "gn:feature_code":"PPL",
    "gn:name":"Yulongge",
    "gn:population":0,
    "gn:timezone":"Asia/Shanghai",
    "iso:country":"CN",
    "name:zho_x_preferred":[
        "\u96e8\u9f99\u683c"
    ],
    "wof:name":"Yulongge",
    "wof:placetype":"locality"
},
  "geometry": {"coordinates":[103.161,24.4839],"type":"Point"}
}