{
  "type": "Feature",
  "properties": {
    "gn:admin1_code":"07",
    "gn:asciiname":"Baimangkeng",
    "gn:country_code":"CN",
    "gn:dem":604,
    "gn:feature_class":"P",
    "gn:feature_code":"PPL",
    "gn:name":"Baimangkeng",
    "gn:population":0,
    "gn:timezone":"Asia/Shanghai",
    "iso:country":"CN",
    "name:zho_x_preferred":[
        "\u767d\u8292\u5751"
    ],
    "wof:name":"Baimangkeng",
    "wof:placetype":"locality"
},
  "geometry": {"coordinates":[118.09381999999999,25.3069],"type":"Point"}
}