{
  "type": "Feature",
  "properties": {
    "gn:admin1_code":"26",
    "gn:asciiname":"Maojia'ao",
    "gn:country_code":"CN",
    "gn:dem":803,
    "gn:feature_class":"P",
    "gn:feature_code":"PPL",
    "gn:name":"Maojia\u2019ao",
    "gn:population":0,
    "gn:timezone":"Asia/Shanghai",
    "iso:country":"CN",
    "name:zho_x_preferred":[
        "Maojia\u2019ao"
    ],
    "name:zho_x_variant":[
        "\u8d38\u5bb6\u5773"
    ],
    "wof:name":"Maojia'ao",
    "wof:placetype":"locality"
},
  "geometry": {"coordinates":[108.32185,34.60243],"type":"Point"}
}