{
  "type": "Feature",
  "properties": {
    "gn:admin1_code":"4.0",
    "gn:asciiname":"Jiangjiaxiang",
    "gn:country_code":"CN",
    "gn:dem":3,
    "gn:feature_class":"P",
    "gn:feature_code":"PPL",
    "gn:name":"Jiangjiaxiang",
    "gn:population":0,
    "gn:timezone":"Asia/Shanghai",
    "iso:country":"CN",
    "name:zho_x_preferred":[
        "Jiangjiaxiang"
    ],
    "name:zho_x_variant":[
        "\u848b\u5bb6\u5df7"
    ],
    "wof:name":"Jiangjiaxiang",
    "wof:placetype":"locality"
},
  "geometry": {"coordinates":[119.5059,33.58525],"type":"Point"}
}