{
  "type": "Feature",
  "properties": {
    "gn:admin1_code":"33.0",
    "gn:asciiname":"Huangni",
    "gn:country_code":"CN",
    "gn:dem":1368,
    "gn:feature_class":"P",
    "gn:feature_code":"PPL",
    "gn:name":"Huangni",
    "gn:population":0,
    "gn:timezone":"Asia/Shanghai",
    "iso:country":"CN",
    "name:zho_x_preferred":[
        "\u9ec4\u6ce5"
    ],
    "wof:name":"Huangni",
    "wof:placetype":"locality"
},
  "geometry": {"coordinates":[107.66889,29.50076],"type":"Point"}
}