{
  "type": "Feature",
  "properties": {
    "gn:admin1_code":"32.0",
    "gn:asciiname":"Sanyanlong",
    "gn:country_code":"CN",
    "gn:dem":2553,
    "gn:feature_class":"P",
    "gn:feature_code":"PPL",
    "gn:name":"Sanyanlong",
    "gn:population":0,
    "gn:timezone":"Asia/Shanghai",
    "iso:country":"CN",
    "name:zho_x_preferred":[
        "\u4e09\u5ca9\u9f99"
    ],
    "wof:name":"Sanyanlong",
    "wof:placetype":"locality"
},
  "geometry": {"coordinates":[101.27692999999999,28.78469],"type":"Point"}
}