{
  "type": "Feature",
  "properties": {
    "gn:admin1_code":"4.0",
    "gn:asciiname":"Dongmengzibang",
    "gn:country_code":"CN",
    "gn:dem":6,
    "gn:feature_class":"P",
    "gn:feature_code":"PPL",
    "gn:name":"Dongmengzibang",
    "gn:population":0,
    "gn:timezone":"Asia/Shanghai",
    "iso:country":"CN",
    "name:und_x_variant":[
        "\u4e1c\u5b5f\u5b50\u6d5c"
    ],
    "wof:name":"Dongmengzibang",
    "wof:placetype":"locality"
},
  "geometry": {"coordinates":[120.90924,31.20678],"type":"Point"}
}