{
  "type": "Feature",
  "properties": {
    "gn:admin1_code":"25",
    "gn:asciiname":"Xincaiyuan",
    "gn:country_code":"CN",
    "gn:dem":59,
    "gn:feature_class":"P",
    "gn:feature_code":"PPL",
    "gn:name":"Xincaiyuan",
    "gn:population":0,
    "gn:timezone":"Asia/Shanghai",
    "iso:country":"CN",
    "name:zho_x_preferred":[
        "\u65b0\u83dc\u56ed"
    ],
    "wof:name":"Xincaiyuan",
    "wof:placetype":"locality"
},
  "geometry": {"coordinates":[115.33799999999999,34.8605],"type":"Point"}
}