{
  "type": "Feature",
  "properties": {
    "gn:admin1_code":"20.0",
    "gn:asciiname":"Dadong",
    "gn:country_code":"CN",
    "gn:dem":1383,
    "gn:feature_class":"P",
    "gn:feature_code":"PPL",
    "gn:name":"Dadong",
    "gn:population":0,
    "gn:timezone":"Asia/Shanghai",
    "iso:country":"CN",
    "name:und_x_variant":[
        "\u5927\u4e1c"
    ],
    "wof:name":"Dadong",
    "wof:placetype":"locality"
},
  "geometry": {"coordinates":[112.84563,41.82004000000001],"type":"Point"}
}