{
  "type": "Feature",
  "properties": {
    "gn:admin1_code":"29.0",
    "gn:asciiname":"Yanfangkou",
    "gn:country_code":"CN",
    "gn:dem":1186,
    "gn:feature_class":"P",
    "gn:feature_code":"PPL",
    "gn:name":"Yanfangkou",
    "gn:population":0,
    "gn:timezone":"Asia/Shanghai",
    "iso:country":"CN",
    "name:zho_x_preferred":[
        "\u5ca9\u65b9\u53e3"
    ],
    "wof:name":"Yanfangkou",
    "wof:placetype":"locality"
},
  "geometry": {"coordinates":[105.196,27.8015],"type":"Point"}
}