{
  "type": "Feature",
  "properties": {
    "gn:admin1_code":"12",
    "gn:asciiname":"Luoyang",
    "gn:country_code":"CN",
    "gn:dem":101,
    "gn:feature_class":"P",
    "gn:feature_code":"PPLA4",
    "gn:name":"Luoyang",
    "gn:population":0,
    "gn:timezone":"Asia/Shanghai",
    "iso:country":"CN",
    "name:rus_x_preferred":[
        "\u041b\u043e\u044f\u043d"
    ],
    "name:und_x_variant":[
        "Lo-yang-tien",
        "Luoyangdian",
        "Luoyang",
        "\u6d1b\u9633",
        "Luoyang Zhen",
        "\u6d1b\u9633\u9547"
    ],
    "wof:name":"Luoyang",
    "wof:placetype":"locality"
},
  "geometry": {"coordinates":[113.42532,31.47293],"type":"Point"}
}