{
  "type": "Feature",
  "properties": {
    "gn:admin1_code":"12.0",
    "gn:asciiname":"Tianjiazhai",
    "gn:country_code":"CN",
    "gn:dem":720,
    "gn:feature_class":"P",
    "gn:feature_code":"PPL",
    "gn:name":"Tianjiazhai",
    "gn:population":0,
    "gn:timezone":"Asia/Shanghai",
    "iso:country":"CN",
    "name:zho_x_preferred":[
        "\u7530\u5bb6\u5be8"
    ],
    "wof:name":"Tianjiazhai",
    "wof:placetype":"locality"
},
  "geometry": {"coordinates":[109.45793,29.68904],"type":"Point"}
}