{
  "type": "Feature",
  "properties": {
    "gn:admin1_code":"01",
    "gn:asciiname":"Laozhoutou",
    "gn:cc2":"CN",
    "gn:country_code":"CN",
    "gn:dem":9,
    "gn:feature_class":"P",
    "gn:feature_code":"PPL",
    "gn:name":"Laozhoutou",
    "gn:population":0,
    "gn:timezone":"Asia/Shanghai",
    "iso:country":"CN",
    "name:und_x_variant":[
        "Lao-chou-wan",
        "Laoshawan",
        "Laozhoutou"
    ],
    "wof:name":"Laozhoutou",
    "wof:placetype":"locality"
},
  "geometry": {"coordinates":[117.59639,30.80389000000001],"type":"Point"}
}