{
  "type": "Feature",
  "properties": {
    "gn:admin1_code":"18",
    "gn:asciiname":"Yangjiaping",
    "gn:country_code":"CN",
    "gn:dem":1005,
    "gn:feature_class":"P",
    "gn:feature_code":"PPL",
    "gn:name":"Yangjiaping",
    "gn:population":0,
    "gn:timezone":"Asia/Shanghai",
    "iso:country":"CN",
    "name:zho_x_preferred":[
        "\u6768\u5bb6\u576a"
    ],
    "wof:name":"Yangjiaping",
    "wof:placetype":"locality"
},
  "geometry": {"coordinates":[108.39100000000001,28.079],"type":"Point"}
}