{
  "type": "Feature",
  "properties": {
    "gn:admin1_code":"3.0",
    "gn:asciiname":"Gushan",
    "gn:country_code":"CN",
    "gn:dem":118,
    "gn:feature_class":"P",
    "gn:feature_code":"PPL",
    "gn:name":"Gushan",
    "gn:population":0,
    "gn:timezone":"Asia/Shanghai",
    "iso:country":"CN",
    "name:und_x_variant":[
        "\u56fa\u5c71"
    ],
    "wof:name":"Gushan",
    "wof:placetype":"locality"
},
  "geometry": {"coordinates":[115.36612,27.46184],"type":"Point"}
}