{
  "type": "Feature",
  "properties": {
    "gn:admin1_code":"30",
    "gn:asciiname":"Daoche",
    "gn:country_code":"CN",
    "gn:dem":88,
    "gn:feature_class":"P",
    "gn:feature_code":"PPL",
    "gn:name":"Daoche",
    "gn:population":0,
    "gn:timezone":"Asia/Shanghai",
    "iso:country":"CN",
    "name:zho_x_preferred":[
        "\u5230\u8f66"
    ],
    "wof:name":"Daoche",
    "wof:placetype":"locality"
},
  "geometry": {"coordinates":[116.34778,24.52889],"type":"Point"}
}