{
  "type": "Feature",
  "properties": {
    "gn:admin1_code":"26.0",
    "gn:asciiname":"Zhongping",
    "gn:cc2":"CN",
    "gn:country_code":"CN",
    "gn:dem":1204,
    "gn:feature_class":"P",
    "gn:feature_code":"PPL",
    "gn:name":"Zhongping",
    "gn:population":0,
    "gn:timezone":"Asia/Shanghai",
    "iso:country":"CN",
    "name:und_x_variant":[
        "Chung-p\u2019ing",
        "Zhongping"
    ],
    "wof:name":"Zhongping",
    "wof:placetype":"locality"
},
  "geometry": {"coordinates":[107.28888999999999,33.42028],"type":"Point"}
}