{
  "type": "Feature",
  "properties": {
    "gn:admin1_code":"8.0",
    "gn:asciiname":"Yijie",
    "gn:country_code":"CN",
    "gn:dem":114,
    "gn:feature_class":"P",
    "gn:feature_code":"PPL",
    "gn:name":"Yijie",
    "gn:population":0,
    "gn:timezone":"Asia/Shanghai",
    "iso:country":"CN",
    "name:und_x_variant":[
        "\u4e00\u8857"
    ],
    "wof:name":"Yijie",
    "wof:placetype":"locality"
},
  "geometry": {"coordinates":[131.11313999999999,44.07141],"type":"Point"}
}