{
  "type": "Feature",
  "properties": {
    "gn:admin1_code":"7",
    "gn:asciiname":"Fujiashan",
    "gn:country_code":"CN",
    "gn:dem":764,
    "gn:feature_class":"P",
    "gn:feature_code":"PPL",
    "gn:name":"Fujiashan",
    "gn:population":0,
    "gn:timezone":"Asia/Shanghai",
    "iso:country":"CN",
    "name:und_x_variant":[
        "\u5bcc\u5bb6\u5c71",
        "Fujiashan"
    ],
    "wof:name":"Fujiashan",
    "wof:placetype":"locality"
},
  "geometry": {"coordinates":[119.79461999999999,27.26307000000001],"type":"Point"}
}