{
  "type": "Feature",
  "properties": {
    "gn:admin1_code":"18",
    "gn:asciiname":"Douhu",
    "gn:country_code":"CN",
    "gn:dem":1109,
    "gn:feature_class":"P",
    "gn:feature_code":"PPL",
    "gn:name":"Douhu",
    "gn:population":0,
    "gn:timezone":"Asia/Shanghai",
    "iso:country":"CN",
    "name:zho_x_preferred":[
        "\u9661\u864e"
    ],
    "wof:name":"Douhu",
    "wof:placetype":"locality"
},
  "geometry": {"coordinates":[106.93300000000001,26.9751],"type":"Point"}
}