{
  "type": "Feature",
  "properties": {
    "gn:admin1_code":"11.0",
    "gn:asciiname":"Caixia",
    "gn:country_code":"CN",
    "gn:dem":238,
    "gn:feature_class":"P",
    "gn:feature_code":"PPL",
    "gn:name":"Caixia",
    "gn:population":0,
    "gn:timezone":"Asia/Shanghai",
    "iso:country":"CN",
    "name:und_x_variant":[
        "Caixialong"
    ],
    "name:zho_x_preferred":[
        "\u5f69\u971e"
    ],
    "name:zho_x_variant":[
        "\u5f69\u971e\u5785"
    ],
    "wof:name":"Caixia",
    "wof:placetype":"locality"
},
  "geometry": {"coordinates":[113.81895,26.61875],"type":"Point"}
}