{
  "type": "Feature",
  "properties": {
    "gn:admin1_code":"28.0",
    "gn:asciiname":"Youyilu",
    "gn:country_code":"CN",
    "gn:dem":8,
    "gn:feature_class":"P",
    "gn:feature_code":"PPLA4",
    "gn:name":"Youyilu",
    "gn:population":0,
    "gn:timezone":"Asia/Shanghai",
    "iso:country":"CN",
    "name:und_x_variant":[
        "Youyilu Jiedao"
    ],
    "name:zho_x_preferred":[
        "\u53cb\u8c0a\u8def"
    ],
    "name:zho_x_variant":[
        "\u53cb\u8c0a\u8def\u8857\u9053"
    ],
    "wof:name":"Youyilu",
    "wof:placetype":"locality"
},
  "geometry": {"coordinates":[117.19826999999999,39.07673],"type":"Point"}
}