{
  "type": "Feature",
  "properties": {
    "gn:admin1_code":"2.0",
    "gn:asciiname":"Haihong",
    "gn:country_code":"CN",
    "gn:dem":382,
    "gn:feature_class":"P",
    "gn:feature_code":"PPL",
    "gn:name":"Haihong",
    "gn:population":0,
    "gn:timezone":"Asia/Shanghai",
    "iso:country":"CN",
    "name:zho_x_preferred":[
        "\u6d77\u7ea2"
    ],
    "wof:name":"Haihong",
    "wof:placetype":"locality"
},
  "geometry": {"coordinates":[119.79525,29.60908],"type":"Point"}
}