{
  "type": "Feature",
  "properties": {
    "gn:admin1_code":"12.0",
    "gn:asciiname":"Bajie",
    "gn:country_code":"CN",
    "gn:dem":644,
    "gn:feature_class":"P",
    "gn:feature_code":"PPL",
    "gn:name":"Bajie",
    "gn:population":0,
    "gn:timezone":"Asia/Shanghai",
    "iso:country":"CN",
    "name:zho_x_preferred":[
        "Bajie"
    ],
    "name:zho_x_variant":[
        "\u628a\u754c"
    ],
    "wof:name":"Bajie",
    "wof:placetype":"locality"
},
  "geometry": {"coordinates":[109.04968999999998,29.72535],"type":"Point"}
}