{
  "type": "Feature",
  "properties": {
    "gn:admin1_code":"8.0",
    "gn:asciiname":"Qianliujiucun",
    "gn:country_code":"CN",
    "gn:dem":233,
    "gn:feature_class":"P",
    "gn:feature_code":"PPL",
    "gn:name":"Qianliujiucun",
    "gn:population":0,
    "gn:timezone":"Asia/Shanghai",
    "iso:country":"CN",
    "name:zho_x_preferred":[
        "\u524d\u516d\u4e5d\u6751"
    ],
    "wof:name":"Qianliujiucun",
    "wof:placetype":"locality"
},
  "geometry": {"coordinates":[122.86593999999999,46.96285],"type":"Point"}
}