{
  "type": "Feature",
  "properties": {
    "gn:admin1_code":"11.0",
    "gn:asciiname":"Miaobei",
    "gn:country_code":"CN",
    "gn:dem":146,
    "gn:feature_class":"P",
    "gn:feature_code":"PPL",
    "gn:name":"Miaobei",
    "gn:population":0,
    "gn:timezone":"Asia/Shanghai",
    "iso:country":"CN",
    "name:zho_x_preferred":[
        "\u5e99\u80cc"
    ],
    "wof:name":"Miaobei",
    "wof:placetype":"locality"
},
  "geometry": {"coordinates":[113.69553999999999,26.95138],"type":"Point"}
}