{
  "type": "Feature",
  "properties": {
    "gn:admin1_code":"29.0",
    "gn:asciiname":"Mafengzhai",
    "gn:country_code":"CN",
    "gn:dem":1305,
    "gn:feature_class":"P",
    "gn:feature_code":"PPL",
    "gn:name":"Mafengzhai",
    "gn:population":0,
    "gn:timezone":"Asia/Shanghai",
    "iso:country":"CN",
    "name:zho_x_preferred":[
        "\u9ebb\u75af\u5be8"
    ],
    "wof:name":"Mafengzhai",
    "wof:placetype":"locality"
},
  "geometry": {"coordinates":[101.062,22.0729],"type":"Point"}
}