{
  "type": "Feature",
  "properties": {
    "gn:admin1_code":"3.0",
    "gn:asciiname":"Huikengli",
    "gn:country_code":"CN",
    "gn:dem":27,
    "gn:feature_class":"P",
    "gn:feature_code":"PPL",
    "gn:name":"Huikengli",
    "gn:population":0,
    "gn:timezone":"Asia/Shanghai",
    "iso:country":"CN",
    "name:und_x_variant":[
        "\u7070\u5751\u91cc"
    ],
    "wof:name":"Huikengli",
    "wof:placetype":"locality"
},
  "geometry": {"coordinates":[116.41025999999999,29.22388],"type":"Point"}
}