{
  "type": "Feature",
  "properties": {
    "gn:admin1_code":"32.0",
    "gn:asciiname":"Yanhe",
    "gn:country_code":"CN",
    "gn:dem":850,
    "gn:feature_class":"P",
    "gn:feature_code":"PPLA4",
    "gn:name":"Yanhe",
    "gn:population":0,
    "gn:timezone":"Asia/Shanghai",
    "iso:country":"CN",
    "name:ceb_x_preferred":[
        "Yanhe"
    ],
    "name:deu_x_preferred":[
        "Yanhe"
    ],
    "name:fra_x_preferred":[
        "Yanhe"
    ],
    "name:und_x_variant":[
        "Yanhe Xiang",
        "\u76d0\u6cb3\u4e61"
    ],
    "name:zho_x_preferred":[
        "\u76d0\u6cb3"
    ],
    "wof:name":"Yanhe",
    "wof:placetype":"locality"
},
  "geometry": {"coordinates":[106.33871000000001,32.54904000000001],"type":"Point"}
}