{
  "type": "Feature",
  "properties": {
    "gn:admin1_code":"4.0",
    "gn:asciiname":"Shibeijiao",
    "gn:country_code":"CN",
    "gn:dem":1,
    "gn:feature_class":"P",
    "gn:feature_code":"PPL",
    "gn:name":"Shibeijiao",
    "gn:population":0,
    "gn:timezone":"Asia/Shanghai",
    "iso:country":"CN",
    "name:zho_x_preferred":[
        "\u77f3\u7891\u89d2"
    ],
    "wof:name":"Shibeijiao",
    "wof:placetype":"locality"
},
  "geometry": {"coordinates":[120.29900000000001,33.7249],"type":"Point"}
}