{
  "type": "Feature",
  "properties": {
    "gn:admin1_code":"15.0",
    "gn:asciiname":"Hejia Fangzi",
    "gn:country_code":"CN",
    "gn:dem":1377,
    "gn:feature_class":"P",
    "gn:feature_code":"PPL",
    "gn:name":"Hejia Fangzi",
    "gn:population":0,
    "gn:timezone":"Asia/Shanghai",
    "iso:country":"CN",
    "name:zho_x_preferred":[
        "\u8d3a\u5bb6\u623f\u5b50"
    ],
    "wof:name":"Hejia Fangzi",
    "wof:placetype":"locality"
},
  "geometry": {"coordinates":[99.416,39.5333],"type":"Point"}
}