{
  "type": "Feature",
  "properties": {
    "gn:admin1_code":"10",
    "gn:asciiname":"Banshentu",
    "gn:country_code":"CN",
    "gn:dem":1573,
    "gn:feature_class":"P",
    "gn:feature_code":"PPL",
    "gn:name":"Banshentu",
    "gn:population":0,
    "gn:timezone":"Asia/Shanghai",
    "iso:country":"CN",
    "name:zho_x_preferred":[
        "\u677f\u7533\u56fe"
    ],
    "wof:name":"Banshentu",
    "wof:placetype":"locality"
},
  "geometry": {"coordinates":[115.27965,41.2088],"type":"Point"}
}