{
  "type": "Feature",
  "properties": {
    "gn:admin1_code":"2.0",
    "gn:asciiname":"Wenqiao",
    "gn:country_code":"CN",
    "gn:dem":878,
    "gn:feature_class":"P",
    "gn:feature_code":"PPL",
    "gn:name":"Wenqiao",
    "gn:population":0,
    "gn:timezone":"Asia/Shanghai",
    "iso:country":"CN",
    "name:zho_x_preferred":[
        "\u69b2\u6865"
    ],
    "wof:name":"Wenqiao",
    "wof:placetype":"locality"
},
  "geometry": {"coordinates":[119.99191,27.56686],"type":"Point"}
}