{
  "type": "Feature",
  "properties": {
    "gn:admin1_code":"19.0",
    "gn:asciiname":"Nanling",
    "gn:country_code":"CN",
    "gn:dem":5,
    "gn:feature_class":"P",
    "gn:feature_code":"PPL",
    "gn:name":"Nanling",
    "gn:population":0,
    "gn:timezone":"Asia/Shanghai",
    "iso:country":"CN",
    "name:und_x_variant":[
        "\u5357\u51cc"
    ],
    "name:zho_x_preferred":[
        "\u5357\u51cc"
    ],
    "wof:name":"Nanling",
    "wof:placetype":"locality"
},
  "geometry": {"coordinates":[121.23459,40.95816],"type":"Point"}
}