{
  "type": "Feature",
  "properties": {
    "gn:admin1_code":"16.0",
    "gn:asciiname":"Geluowan",
    "gn:country_code":"CN",
    "gn:dem":775,
    "gn:feature_class":"P",
    "gn:feature_code":"PPL",
    "gn:name":"Geluowan",
    "gn:population":0,
    "gn:timezone":"Asia/Shanghai",
    "iso:country":"CN",
    "name:zho_x_preferred":[
        "\u6b4c\u7f57\u6e7e"
    ],
    "wof:name":"Geluowan",
    "wof:placetype":"locality"
},
  "geometry": {"coordinates":[107.137,24.4189],"type":"Point"}
}