{
  "type": "Feature",
  "properties": {
    "gn:admin1_code":"29.0",
    "gn:asciiname":"Futianpai",
    "gn:country_code":"CN",
    "gn:dem":1755,
    "gn:feature_class":"P",
    "gn:feature_code":"PPL",
    "gn:name":"Futianpai",
    "gn:population":0,
    "gn:timezone":"Asia/Shanghai",
    "iso:country":"CN",
    "name:zho_x_preferred":[
        "\u5e9c\u5929\u724c"
    ],
    "wof:name":"Futianpai",
    "wof:placetype":"locality"
},
  "geometry": {"coordinates":[103.669,23.2499],"type":"Point"}
}