{
  "type": "Feature",
  "properties": {
    "gn:admin1_code":"20.0",
    "gn:asciiname":"Dadongbuzi",
    "gn:country_code":"CN",
    "gn:dem":1770,
    "gn:feature_class":"P",
    "gn:feature_code":"PPL",
    "gn:name":"Dadongbuzi",
    "gn:population":0,
    "gn:timezone":"Asia/Shanghai",
    "iso:country":"CN",
    "name:und_x_variant":[
        "\u5927\u4e1c\u535c\u5b50"
    ],
    "wof:name":"Dadongbuzi",
    "wof:placetype":"locality"
},
  "geometry": {"coordinates":[112.48271,41.32234],"type":"Point"}
}