{
  "type": "Feature",
  "properties": {
    "gn:admin1_code":"7.0",
    "gn:asciiname":"Houkeng",
    "gn:country_code":"CN",
    "gn:dem":337,
    "gn:feature_class":"P",
    "gn:feature_code":"PPL",
    "gn:name":"Houkeng",
    "gn:population":0,
    "gn:timezone":"Asia/Shanghai",
    "iso:country":"CN",
    "name:und_x_variant":[
        "\u540e\u5751"
    ],
    "name:zho_x_preferred":[
        "\u540e\u5751"
    ],
    "wof:name":"Houkeng",
    "wof:placetype":"locality"
},
  "geometry": {"coordinates":[117.68004999999999,26.27845],"type":"Point"}
}