{
  "type": "Feature",
  "properties": {
    "gn:admin1_code":"8.0",
    "gn:asciiname":"Xiaoniangou",
    "gn:country_code":"CN",
    "gn:dem":190,
    "gn:feature_class":"P",
    "gn:feature_code":"PPL",
    "gn:name":"Xiaoniangou",
    "gn:population":0,
    "gn:timezone":"Asia/Shanghai",
    "iso:country":"CN",
    "name:zho_x_preferred":[
        "\u5c0f\u78be\u6c9f"
    ],
    "wof:name":"Xiaoniangou",
    "wof:placetype":"locality"
},
  "geometry": {"coordinates":[127.14151,45.53292],"type":"Point"}
}