{
  "type": "Feature",
  "properties": {
    "gn:admin1_code":"3.0",
    "gn:asciiname":"Hepanshi Tongjia",
    "gn:country_code":"CN",
    "gn:dem":36,
    "gn:feature_class":"P",
    "gn:feature_code":"PPL",
    "gn:name":"Hepanshi Tongjia",
    "gn:population":0,
    "gn:timezone":"Asia/Shanghai",
    "iso:country":"CN",
    "name:zho_x_preferred":[
        "\u5408\u76d8\u77f3\u7ae5\u5bb6"
    ],
    "wof:name":"Hepanshi Tongjia",
    "wof:placetype":"locality"
},
  "geometry": {"coordinates":[117.164,28.3277],"type":"Point"}
}