{
  "type": "Feature",
  "properties": {
    "gn:admin1_code":"11.0",
    "gn:asciiname":"Fulichong",
    "gn:country_code":"CN",
    "gn:dem":285,
    "gn:feature_class":"P",
    "gn:feature_code":"PPL",
    "gn:name":"Fulichong",
    "gn:population":0,
    "gn:timezone":"Asia/Shanghai",
    "iso:country":"CN",
    "name:zho_x_preferred":[
        "\u6276\u7acb\u51b2"
    ],
    "wof:name":"Fulichong",
    "wof:placetype":"locality"
},
  "geometry": {"coordinates":[111.62900999999999,27.13771],"type":"Point"}
}