{
  "type": "Feature",
  "properties": {
    "gn:admin1_code":"12.0",
    "gn:asciiname":"Yaobaota",
    "gn:country_code":"CN",
    "gn:dem":423,
    "gn:feature_class":"P",
    "gn:feature_code":"PPL",
    "gn:name":"Yaobaota",
    "gn:population":0,
    "gn:timezone":"Asia/Shanghai",
    "iso:country":"CN",
    "name:zho_x_preferred":[
        "Mebaota"
    ],
    "name:zho_x_variant":[
        "\u4e48\u4fdd\u5854"
    ],
    "wof:name":"Yaobaota",
    "wof:placetype":"locality"
},
  "geometry": {"coordinates":[110.50825,29.75288],"type":"Point"}
}