{
  "type": "Feature",
  "properties": {
    "gn:admin1_code":"15.0",
    "gn:asciiname":"Jiugongxia Baozi",
    "gn:country_code":"CN",
    "gn:dem":1160,
    "gn:feature_class":"P",
    "gn:feature_code":"PPL",
    "gn:name":"Jiugongxia Baozi",
    "gn:population":0,
    "gn:timezone":"Asia/Urumqi",
    "iso:country":"CN",
    "name:zho_x_preferred":[
        "\u4e5d\u5de5\u4e0b\u5821\u5b50"
    ],
    "wof:name":"Jiugongxia Baozi",
    "wof:placetype":"locality"
},
  "geometry": {"coordinates":[95.6982,40.4496],"type":"Point"}
}