{
  "type": "Feature",
  "properties": {
    "gn:admin1_code":"15.0",
    "gn:asciiname":"Yuanshuliang",
    "gn:country_code":"CN",
    "gn:dem":1861,
    "gn:feature_class":"P",
    "gn:feature_code":"PPL",
    "gn:name":"Yuanshuliang",
    "gn:population":0,
    "gn:timezone":"Asia/Shanghai",
    "iso:country":"CN",
    "name:zho_x_preferred":[
        "\u56ed\u6811\u6881"
    ],
    "wof:name":"Yuanshuliang",
    "wof:placetype":"locality"
},
  "geometry": {"coordinates":[106.16200000000001,34.9813],"type":"Point"}
}