{
  "type": "Feature",
  "properties": {
    "gn:admin1_code":"32.0",
    "gn:asciiname":"Lijishan",
    "gn:country_code":"CN",
    "gn:dem":500,
    "gn:feature_class":"P",
    "gn:feature_code":"PPL",
    "gn:name":"Lijishan",
    "gn:population":0,
    "gn:timezone":"Asia/Shanghai",
    "iso:country":"CN",
    "name:zho_x_preferred":[
        "\u674e\u57fa\u5c71"
    ],
    "wof:name":"Lijishan",
    "wof:placetype":"locality"
},
  "geometry": {"coordinates":[106.724,31.4561],"type":"Point"}
}