{
  "type": "Feature",
  "properties": {
    "gn:admin1_code":"14.0",
    "gn:asciiname":"Tarba",
    "gn:country_code":"CN",
    "gn:dem":4648,
    "gn:feature_class":"P",
    "gn:feature_code":"PPL",
    "gn:name":"Tarba",
    "gn:population":0,
    "gn:timezone":"Asia/Urumqi",
    "iso:country":"CN",
    "name:bod_x_preferred":[
        "Tarba"
    ],
    "name:zho_x_preferred":[
        "Daba"
    ],
    "name:zho_x_variant":[
        "\u5927\u5df4"
    ],
    "wof:name":"Tarba",
    "wof:placetype":"locality"
},
  "geometry": {"coordinates":[89.20100000000002,28.901],"type":"Point"}
}