{
  "type": "Feature",
  "properties": {
    "gn:admin1_code":"26",
    "gn:asciiname":"Xiwushi",
    "gn:country_code":"CN",
    "gn:dem":1173,
    "gn:feature_class":"P",
    "gn:feature_code":"PPL",
    "gn:name":"Xiwushi",
    "gn:population":0,
    "gn:timezone":"Asia/Shanghai",
    "iso:country":"CN",
    "name:zho_x_preferred":[
        "\u897f\u4f0d\u4ec0"
    ],
    "wof:name":"Xiwushi",
    "wof:placetype":"locality"
},
  "geometry": {"coordinates":[108.31638999999998,34.76583],"type":"Point"}
}