{
  "type": "Feature",
  "properties": {
    "gn:admin1_code":"13",
    "gn:asciiname":"Tuowantongluke",
    "gn:country_code":"CN",
    "gn:dem":1259,
    "gn:feature_class":"P",
    "gn:feature_code":"PPL",
    "gn:name":"Tuowantongluke",
    "gn:population":0,
    "gn:timezone":"Asia/Shanghai",
    "iso:country":"CN",
    "name:zho_x_preferred":[
        "\u6258\u4e07\u901a\u9c81\u514b"
    ],
    "wof:name":"Tuowantongluke",
    "wof:placetype":"locality"
},
  "geometry": {"coordinates":[76.26382,39.18297000000001],"type":"Point"}
}