{
  "type": "Feature",
  "properties": {
    "gn:admin1_code":"15.0",
    "gn:asciiname":"Tangjiahekou",
    "gn:country_code":"CN",
    "gn:dem":1599,
    "gn:feature_class":"P",
    "gn:feature_code":"PPL",
    "gn:name":"Tangjiahekou",
    "gn:population":0,
    "gn:timezone":"Asia/Shanghai",
    "iso:country":"CN",
    "name:und_x_variant":[
        "\u5510\u5bb6\u6cb3\u53e3"
    ],
    "wof:name":"Tangjiahekou",
    "wof:placetype":"locality"
},
  "geometry": {"coordinates":[105.55875,34.07529],"type":"Point"}
}