{
  "type": "Feature",
  "properties": {
    "gn:admin1_code":"19.0",
    "gn:asciiname":"Zunhua",
    "gn:country_code":"CN",
    "gn:dem":7,
    "gn:feature_class":"P",
    "gn:feature_code":"PPL",
    "gn:name":"Zunhua",
    "gn:population":0,
    "gn:timezone":"Asia/Shanghai",
    "iso:country":"CN",
    "name:ara_x_preferred":[
        "\u0632\u064a\u0646\u0647\u0648\u0627"
    ],
    "name:deu_x_preferred":[
        "Zunhua"
    ],
    "name:fra_x_preferred":[
        "Zunhua"
    ],
    "name:ita_x_preferred":[
        "Zunhua"
    ],
    "name:jpn_x_preferred":[
        "\u9075\u5316\u5e02"
    ],
    "name:kik_x_preferred":[
        "Zunhua"
    ],
    "name:kor_x_preferred":[
        "\ucb4c\ud654\uc2dc"
    ],
    "name:nor_x_preferred":[
        "Zunhua"
    ],
    "name:pam_x_preferred":[
        "Zunhua"
    ],
    "name:pol_x_preferred":[
        "Zunhua"
    ],
    "name:rus_x_preferred":[
        "\u0426\u0437\u0443\u043d\u044c\u0445\u0443\u0430"
    ],
    "name:swe_x_preferred":[
        "Zunhua"
    ],
    "name:urd_x_preferred":[
        "\u0698\u0648\u0646\u06c1\u0648\u0627"
    ],
    "name:vie_x_preferred":[
        "Tu\u00e2n H\u00f3a"
    ],
    "name:zho_x_preferred":[
        "\u9075\u5316"
    ],
    "name:zho_x_variant":[
        "\u9075\u5316\u5e02"
    ],
    "wof:name":"Zunhua",
    "wof:placetype":"locality"
},
  "geometry": {"coordinates":[122.31177,41.36663],"type":"Point"}
}