{
  "type": "Feature",
  "properties": {
    "gn:admin1_code":"19.0",
    "gn:asciiname":"Zunhua",
    "gn:country_code":"CN",
    "gn:dem":7,
    "gn:feature_class":"P",
    "gn:feature_code":"PPL",
    "gn:name":"Zunhua",
    "gn:population":0,
    "gn:timezone":"Asia/Shanghai",
    "iso:country":"CN",
    "name:und_x_variant":[
        "\u9075\u5316"
    ],
    "name:zho_x_preferred":[
        "\u9075\u5316"
    ],
    "wof:name":"Zunhua",
    "wof:placetype":"locality"
},
  "geometry": {"coordinates":[122.31177,41.36663],"type":"Point"}
}