{
  "type": "Feature",
  "properties": {
    "gn:admin1_code":"10",
    "gn:asciiname":"Jiudian",
    "gn:cc2":"CN",
    "gn:country_code":"CN",
    "gn:dem":45,
    "gn:feature_class":"P",
    "gn:feature_code":"PPL",
    "gn:name":"Jiudian",
    "gn:population":0,
    "gn:timezone":"Asia/Shanghai",
    "iso:country":"CN",
    "name:und_x_variant":[
        "Chiu-tien",
        "Jiudian"
    ],
    "wof:name":"Jiudian",
    "wof:placetype":"locality"
},
  "geometry": {"coordinates":[114.94110999999999,36.58917],"type":"Point"}
}