{
  "type": "Feature",
  "properties": {
    "gn:admin1_code":"25.0",
    "gn:asciiname":"Banshexiangcun",
    "gn:country_code":"CN",
    "gn:dem":130,
    "gn:feature_class":"P",
    "gn:feature_code":"PPL",
    "gn:name":"Banshexiangcun",
    "gn:population":0,
    "gn:timezone":"Asia/Shanghai",
    "iso:country":"CN",
    "name:zho_x_preferred":[
        "\u534a\u793e\u4e61\u6751"
    ],
    "wof:name":"Banshexiangcun",
    "wof:placetype":"locality"
},
  "geometry": {"coordinates":[121.05328,36.81868],"type":"Point"}
}