{
  "type": "Feature",
  "properties": {
    "gn:admin1_code":"7.0",
    "gn:asciiname":"Ruiyun",
    "gn:country_code":"CN",
    "gn:dem":1037,
    "gn:feature_class":"P",
    "gn:feature_code":"PPL",
    "gn:name":"Ruiyun",
    "gn:population":0,
    "gn:timezone":"Asia/Shanghai",
    "iso:country":"CN",
    "name:zho_x_preferred":[
        "\u745e\u4e91"
    ],
    "wof:name":"Ruiyun",
    "wof:placetype":"locality"
},
  "geometry": {"coordinates":[118.99447000000001,26.79384000000001],"type":"Point"}
}