{
  "type": "Feature",
  "properties": {
    "gn:admin1_code":"15.0",
    "gn:asciiname":"Diaoping",
    "gn:country_code":"CN",
    "gn:dem":1740,
    "gn:feature_class":"P",
    "gn:feature_code":"PPL",
    "gn:name":"Diaoping",
    "gn:population":0,
    "gn:timezone":"Asia/Shanghai",
    "iso:country":"CN",
    "name:zho_x_preferred":[
        "\u540a\u576a"
    ],
    "wof:name":"Diaoping",
    "wof:placetype":"locality"
},
  "geometry": {"coordinates":[105.77500000000001,34.8955],"type":"Point"}
}