{
  "type": "Feature",
  "properties": {
    "gn:admin1_code":"25",
    "gn:asciiname":"Luozhen",
    "gn:cc2":"CN",
    "gn:country_code":"CN",
    "gn:dem":6,
    "gn:feature_class":"P",
    "gn:feature_code":"PPL",
    "gn:name":"Luozhen",
    "gn:population":0,
    "gn:timezone":"Asia/Shanghai",
    "iso:country":"CN",
    "name:und_x_variant":[
        "Lo-chen",
        "Luozhen"
    ],
    "wof:name":"Luozhen",
    "wof:placetype":"locality"
},
  "geometry": {"coordinates":[118.53333000000001,37.78333],"type":"Point"}
}