{
  "type": "Feature",
  "properties": {
    "gn:admin1_code":"24.0",
    "gn:asciiname":"Nanhuazhi",
    "gn:country_code":"CN",
    "gn:dem":806,
    "gn:feature_class":"P",
    "gn:feature_code":"PPL",
    "gn:name":"Nanhuazhi",
    "gn:population":0,
    "gn:timezone":"Asia/Shanghai",
    "iso:country":"CN",
    "name:zho_x_preferred":[
        "\u5357\u82b1\u679d"
    ],
    "wof:name":"Nanhuazhi",
    "wof:placetype":"locality"
},
  "geometry": {"coordinates":[111.72096999999999,37.26269],"type":"Point"}
}