{
  "type": "Feature",
  "properties": {
    "gn:admin1_code":"21.0",
    "gn:asciiname":"Houwangou",
    "gn:country_code":"CN",
    "gn:dem":1828,
    "gn:feature_class":"P",
    "gn:feature_code":"PPL",
    "gn:name":"Houwangou",
    "gn:population":0,
    "gn:timezone":"Asia/Shanghai",
    "iso:country":"CN",
    "name:zho_x_preferred":[
        "\u540e\u6e7e\u6c9f"
    ],
    "wof:name":"Houwangou",
    "wof:placetype":"locality"
},
  "geometry": {"coordinates":[106.363,35.8305],"type":"Point"}
}