{
  "type": "Feature",
  "properties": {
    "gn:admin1_code":"02",
    "gn:asciiname":"Longdengtou",
    "gn:country_code":"CN",
    "gn:dem":8,
    "gn:feature_class":"P",
    "gn:feature_code":"PPL",
    "gn:name":"Longdengtou",
    "gn:population":0,
    "gn:timezone":"Asia/Shanghai",
    "iso:country":"CN",
    "name:und_x_variant":[
        "\u9f99\u706f\u5934",
        "Longdengbang"
    ],
    "wof:name":"Longdengtou",
    "wof:placetype":"locality"
},
  "geometry": {"coordinates":[121.20335,30.68137],"type":"Point"}
}