{
  "type": "Feature",
  "properties": {
    "gn:admin1_code":"4.0",
    "gn:asciiname":"Xiejin Shizu",
    "gn:country_code":"CN",
    "gn:dem":6,
    "gn:feature_class":"P",
    "gn:feature_code":"PPLF",
    "gn:name":"Xiejin Shizu",
    "gn:population":0,
    "gn:timezone":"Asia/Shanghai",
    "iso:country":"CN",
    "name:zho_x_preferred":[
        "\u534f\u8fdb\u5341\u7ec4"
    ],
    "wof:name":"Xiejin Shizu",
    "wof:placetype":"locality"
},
  "geometry": {"coordinates":[121.43241999999999,32.01476],"type":"Point"}
}