{
  "type": "Feature",
  "properties": {
    "gn:admin1_code":"11.0",
    "gn:asciiname":"Yetianchong",
    "gn:country_code":"CN",
    "gn:dem":314,
    "gn:feature_class":"P",
    "gn:feature_code":"PPL",
    "gn:name":"Yetianchong",
    "gn:population":0,
    "gn:timezone":"Asia/Shanghai",
    "iso:country":"CN",
    "name:zho_x_preferred":[
        "\u91ce\u7530\u51b2"
    ],
    "wof:name":"Yetianchong",
    "wof:placetype":"locality"
},
  "geometry": {"coordinates":[109.74236000000001,27.30524],"type":"Point"}
}