{
  "type": "Feature",
  "properties": {
    "gn:admin1_code":"3.0",
    "gn:asciiname":"Waijing",
    "gn:country_code":"CN",
    "gn:dem":372,
    "gn:feature_class":"P",
    "gn:feature_code":"PPL",
    "gn:name":"Waijing",
    "gn:population":0,
    "gn:timezone":"Asia/Shanghai",
    "iso:country":"CN",
    "name:und_x_variant":[
        "\u5916\u8ff3"
    ],
    "wof:name":"Waijing",
    "wof:placetype":"locality"
},
  "geometry": {"coordinates":[114.77831999999999,24.706],"type":"Point"}
}