{
  "type": "Feature",
  "properties": {
    "gn:admin1_code":"8.0",
    "gn:asciiname":"Wangshengcun",
    "gn:country_code":"CN",
    "gn:dem":63,
    "gn:feature_class":"P",
    "gn:feature_code":"PPL",
    "gn:name":"Wangshengcun",
    "gn:population":0,
    "gn:timezone":"Asia/Shanghai",
    "iso:country":"CN",
    "name:zho_x_preferred":[
        "\u65fa\u76db\u6751"
    ],
    "wof:name":"Wangshengcun",
    "wof:placetype":"locality"
},
  "geometry": {"coordinates":[131.81645,46.8628],"type":"Point"}
}