{
  "type": "Feature",
  "properties": {
    "gn:admin1_code":"18.0",
    "gn:asciiname":"Shangpaiwai",
    "gn:country_code":"CN",
    "gn:dem":1068,
    "gn:feature_class":"P",
    "gn:feature_code":"PPL",
    "gn:name":"Shangpaiwai",
    "gn:population":0,
    "gn:timezone":"Asia/Shanghai",
    "iso:country":"CN",
    "name:zho_x_preferred":[
        "\u4e0a\u6392\u5916"
    ],
    "wof:name":"Shangpaiwai",
    "wof:placetype":"locality"
},
  "geometry": {"coordinates":[108.155,26.0777],"type":"Point"}
}