{
  "type": "Feature",
  "properties": {
    "gn:admin1_code":"29.0",
    "gn:asciiname":"Xianshuidong",
    "gn:country_code":"CN",
    "gn:dem":2053,
    "gn:feature_class":"P",
    "gn:feature_code":"PPL",
    "gn:name":"Xianshuidong",
    "gn:population":0,
    "gn:timezone":"Asia/Shanghai",
    "iso:country":"CN",
    "name:zho_x_preferred":[
        "\u4ed9\u6c34\u6d1e"
    ],
    "wof:name":"Xianshuidong",
    "wof:placetype":"locality"
},
  "geometry": {"coordinates":[99.7547,25.0531],"type":"Point"}
}