{
  "type": "Feature",
  "properties": {
    "gn:admin1_code":"33.0",
    "gn:asciiname":"Ranjiaxi",
    "gn:country_code":"CN",
    "gn:dem":460,
    "gn:feature_class":"P",
    "gn:feature_code":"PPL",
    "gn:name":"Ranjiaxi",
    "gn:population":0,
    "gn:timezone":"Asia/Shanghai",
    "iso:country":"CN",
    "name:zho_x_preferred":[
        "\u5189\u5bb6\u6eaa"
    ],
    "wof:name":"Ranjiaxi",
    "wof:placetype":"locality"
},
  "geometry": {"coordinates":[109.02875,28.78645],"type":"Point"}
}