{
  "type": "Feature",
  "properties": {
    "gn:admin1_code":"8.0",
    "gn:asciiname":"Shenbacun",
    "gn:country_code":"CN",
    "gn:dem":145,
    "gn:feature_class":"P",
    "gn:feature_code":"PPL",
    "gn:name":"Shenbacun",
    "gn:population":0,
    "gn:timezone":"Asia/Shanghai",
    "iso:country":"CN",
    "name:zho_x_preferred":[
        "\u6c88\u516b\u6751"
    ],
    "wof:name":"Shenbacun",
    "wof:placetype":"locality"
},
  "geometry": {"coordinates":[126.71496999999999,46.2846],"type":"Point"}
}