{
  "type": "Feature",
  "properties": {
    "gn:admin1_code":"25",
    "gn:asciiname":"Qiankuhe",
    "gn:country_code":"CN",
    "gn:dem":177,
    "gn:feature_class":"P",
    "gn:feature_code":"PPL",
    "gn:name":"Qiankuhe",
    "gn:population":0,
    "gn:timezone":"Asia/Shanghai",
    "iso:country":"CN",
    "name:zho_x_preferred":[
        "\u524d\u67af\u6cb3"
    ],
    "wof:name":"Qiankuhe",
    "wof:placetype":"locality"
},
  "geometry": {"coordinates":[117.471,36.332],"type":"Point"}
}