{
  "type": "Feature",
  "properties": {
    "gn:admin1_code":"25.0",
    "gn:asciiname":"Zhaoxian",
    "gn:country_code":"CN",
    "gn:dem":28,
    "gn:feature_class":"P",
    "gn:feature_code":"PPL",
    "gn:name":"Zhaoxian",
    "gn:population":0,
    "gn:timezone":"Asia/Shanghai",
    "iso:country":"CN",
    "name:zho_x_preferred":[
        "\u62db\u8d24"
    ],
    "wof:name":"Zhaoxian",
    "wof:placetype":"locality"
},
  "geometry": {"coordinates":[120.04767,37.35437],"type":"Point"}
}