{
  "type": "Feature",
  "properties": {
    "gn:admin1_code":"21.0",
    "gn:asciiname":"Cungou",
    "gn:country_code":"CN",
    "gn:dem":1737,
    "gn:feature_class":"P",
    "gn:feature_code":"PPL",
    "gn:name":"Cungou",
    "gn:population":0,
    "gn:timezone":"Asia/Shanghai",
    "iso:country":"CN",
    "name:zho_x_preferred":[
        "\u6751\u6c9f"
    ],
    "wof:name":"Cungou",
    "wof:placetype":"locality"
},
  "geometry": {"coordinates":[105.71599999999999,36.6058],"type":"Point"}
}