{
  "type": "Feature",
  "properties": {
    "gn:admin1_code":"3",
    "gn:asciiname":"Minfeng",
    "gn:country_code":"CN",
    "gn:dem":384,
    "gn:feature_class":"P",
    "gn:feature_code":"PPL",
    "gn:name":"Minfeng",
    "gn:population":0,
    "gn:timezone":"Asia/Shanghai",
    "iso:country":"CN",
    "name:zho_x_preferred":[
        "\u6c11\u4e30"
    ],
    "wof:name":"Minfeng",
    "wof:placetype":"locality"
},
  "geometry": {"coordinates":[114.55522000000001,26.17223],"type":"Point"}
}