{
  "type": "Feature",
  "properties": {
    "gn:admin1_code":"02",
    "gn:asciiname":"Shujia",
    "gn:cc2":"CN",
    "gn:country_code":"CN",
    "gn:dem":88,
    "gn:feature_class":"P",
    "gn:feature_code":"PPL",
    "gn:name":"Shujia",
    "gn:population":0,
    "gn:timezone":"Asia/Shanghai",
    "iso:country":"CN",
    "name:und_x_variant":[
        "Shu-chia",
        "Shujia"
    ],
    "wof:name":"Shujia",
    "wof:placetype":"locality"
},
  "geometry": {"coordinates":[122.15028,30.05417000000001],"type":"Point"}
}