{
  "type": "Feature",
  "properties": {
    "gn:admin1_code":"14.0",
    "gn:asciiname":"Zangdog",
    "gn:country_code":"CN",
    "gn:dem":3742,
    "gn:feature_class":"P",
    "gn:feature_code":"PPLF",
    "gn:name":"Zangdog",
    "gn:population":0,
    "gn:timezone":"Asia/Urumqi",
    "iso:country":"CN",
    "name:bod_x_preferred":[
        "Zangdog"
    ],
    "name:bod_x_variant":[
        "\u0f42\u0f59\u0f44\u0f0b\u0f62\u0f9f\u0f7c\u0f42\u0f66"
    ],
    "name:zho_x_preferred":[
        "Zhangduo"
    ],
    "name:zho_x_variant":[
        "\u7ae0\u591a",
        "Lamu Qu",
        "\u62c9\u6728\u533a"
    ],
    "wof:name":"Zangdog",
    "wof:placetype":"locality"
},
  "geometry": {"coordinates":[91.48676,29.77585],"type":"Point"}
}