{
  "type": "Feature",
  "properties": {
    "gn:admin1_code":"21.0",
    "gn:asciiname":"Hejia Taozi",
    "gn:country_code":"CN",
    "gn:dem":2248,
    "gn:feature_class":"P",
    "gn:feature_code":"PPL",
    "gn:name":"Hejia Taozi",
    "gn:population":0,
    "gn:timezone":"Asia/Shanghai",
    "iso:country":"CN",
    "name:zho_x_preferred":[
        "\u8d3a\u5bb6\u5957\u5b50"
    ],
    "wof:name":"Hejia Taozi",
    "wof:placetype":"locality"
},
  "geometry": {"coordinates":[106.142,35.7783],"type":"Point"}
}