{
  "type": "Feature",
  "properties": {
    "gn:admin1_code":"30",
    "gn:asciiname":"Xiedi",
    "gn:country_code":"CN",
    "gn:dem":209,
    "gn:feature_class":"P",
    "gn:feature_code":"PPL",
    "gn:name":"Xiedi",
    "gn:population":0,
    "gn:timezone":"Asia/Shanghai",
    "iso:country":"CN",
    "name:zho_x_preferred":[
        "\u87f9\u5730"
    ],
    "wof:name":"Xiedi",
    "wof:placetype":"locality"
},
  "geometry": {"coordinates":[116.64585,23.82215],"type":"Point"}
}