{
  "type": "Feature",
  "properties": {
    "gn:admin1_code":"5.0",
    "gn:asciiname":"Machangtun",
    "gn:country_code":"CN",
    "gn:dem":139,
    "gn:feature_class":"P",
    "gn:feature_code":"PPL",
    "gn:name":"Machangtun",
    "gn:population":0,
    "gn:timezone":"Asia/Shanghai",
    "iso:country":"CN",
    "name:zho_x_preferred":[
        "\u9a6c\u573a\u5c6f"
    ],
    "wof:name":"Machangtun",
    "wof:placetype":"locality"
},
  "geometry": {"coordinates":[123.38175,45.50824],"type":"Point"}
}