{
  "type": "Feature",
  "properties": {
    "gn:admin1_code":"12.0",
    "gn:asciiname":"Youzhahe",
    "gn:country_code":"CN",
    "gn:dem":25,
    "gn:feature_class":"P",
    "gn:feature_code":"PPL",
    "gn:name":"Youzhahe",
    "gn:population":0,
    "gn:timezone":"Asia/Shanghai",
    "iso:country":"CN",
    "name:zho_x_preferred":[
        "\u6cb9\u69a8\u6cb3"
    ],
    "wof:name":"Youzhahe",
    "wof:placetype":"locality"
},
  "geometry": {"coordinates":[113.48909999999999,29.94478],"type":"Point"}
}