{
  "type": "Feature",
  "properties": {
    "gn:admin1_code":"16.0",
    "gn:asciiname":"Yangwu",
    "gn:country_code":"CN",
    "gn:dem":108,
    "gn:feature_class":"P",
    "gn:feature_code":"PPL",
    "gn:name":"Yangwu",
    "gn:population":0,
    "gn:timezone":"Asia/Shanghai",
    "iso:country":"CN",
    "name:zho_x_preferred":[
        "\u6768\u5c4b"
    ],
    "wof:name":"Yangwu",
    "wof:placetype":"locality"
},
  "geometry": {"coordinates":[108.434,22.8185],"type":"Point"}
}