{
  "type": "Feature",
  "properties": {
    "gn:admin1_code":"32.0",
    "gn:asciiname":"Diaolinyan",
    "gn:country_code":"CN",
    "gn:dem":2017,
    "gn:feature_class":"P",
    "gn:feature_code":"PPL",
    "gn:name":"Diaolinyan",
    "gn:population":0,
    "gn:timezone":"Asia/Shanghai",
    "iso:country":"CN",
    "name:zho_x_preferred":[
        "\u5201\u6797\u5ca9"
    ],
    "wof:name":"Diaolinyan",
    "wof:placetype":"locality"
},
  "geometry": {"coordinates":[104.361,32.7246],"type":"Point"}
}