{
  "type": "Feature",
  "properties": {
    "gn:admin1_code":"29.0",
    "gn:asciiname":"Juebalin",
    "gn:country_code":"CN",
    "gn:dem":2137,
    "gn:feature_class":"P",
    "gn:feature_code":"PPL",
    "gn:name":"Juebalin",
    "gn:population":0,
    "gn:timezone":"Asia/Shanghai",
    "iso:country":"CN",
    "name:zho_x_preferred":[
        "\u8568\u575d\u6797"
    ],
    "wof:name":"Juebalin",
    "wof:placetype":"locality"
},
  "geometry": {"coordinates":[100.033,24.6737],"type":"Point"}
}