{
  "type": "Feature",
  "properties": {
    "gn:admin1_code":"12.0",
    "gn:asciiname":"Zhouxiawan",
    "gn:country_code":"CN",
    "gn:dem":28,
    "gn:feature_class":"P",
    "gn:feature_code":"PPL",
    "gn:name":"Zhouxiawan",
    "gn:population":0,
    "gn:timezone":"Asia/Shanghai",
    "iso:country":"CN",
    "name:und_x_variant":[
        "\u5468\u4e0b\u5846"
    ],
    "wof:name":"Zhouxiawan",
    "wof:placetype":"locality"
},
  "geometry": {"coordinates":[115.27003000000001,30.28984],"type":"Point"}
}