{
  "type": "Feature",
  "properties": {
    "gn:admin1_code":"15.0",
    "gn:asciiname":"Xiaowan Nongchang Linchang",
    "gn:country_code":"CN",
    "gn:dem":1181,
    "gn:feature_class":"P",
    "gn:feature_code":"PPLF",
    "gn:name":"Xiaowan Nongchang Linchang",
    "gn:population":0,
    "gn:timezone":"Asia/Urumqi",
    "iso:country":"CN",
    "name:eng_x_preferred":[
        "Xiaowan Agricultural Tree Nongchang"
    ],
    "name:zho_x_preferred":[
        "\u5c0f\u5b9b\u519c\u573a\u6797\u573a"
    ],
    "wof:name":"Xiaowan Nongchang Linchang",
    "wof:placetype":"locality"
},
  "geometry": {"coordinates":[95.81738,40.5415],"type":"Point"}
}