{
  "type": "Feature",
  "properties": {
    "gn:admin1_code":"4.0",
    "gn:asciiname":"Zhuhu",
    "gn:country_code":"CN",
    "gn:dem":8,
    "gn:feature_class":"P",
    "gn:feature_code":"PPL",
    "gn:name":"Zhuhu",
    "gn:population":0,
    "gn:timezone":"Asia/Shanghai",
    "iso:country":"CN",
    "name:zho_x_preferred":[
        "\u73e0\u6e56"
    ],
    "wof:name":"Zhuhu",
    "wof:placetype":"locality"
},
  "geometry": {"coordinates":[119.42359999999999,32.73733],"type":"Point"}
}