{
  "type": "Feature",
  "properties": {
    "gn:admin1_code":"30.0",
    "gn:asciiname":"Leigongkeng",
    "gn:country_code":"CN",
    "gn:dem":305,
    "gn:feature_class":"P",
    "gn:feature_code":"PPL",
    "gn:name":"Leigongkeng",
    "gn:population":0,
    "gn:timezone":"Asia/Shanghai",
    "iso:country":"CN",
    "name:zho_x_preferred":[
        "Leigongkeng"
    ],
    "name:zho_x_variant":[
        "\u96f7\u516c\u5751"
    ],
    "wof:name":"Leigongkeng",
    "wof:placetype":"locality"
},
  "geometry": {"coordinates":[114.93575,24.02958],"type":"Point"}
}