{
  "type": "Feature",
  "properties": {
    "gn:admin1_code":"6.0",
    "gn:asciiname":"Xiege",
    "gn:country_code":"CN",
    "gn:dem":3687,
    "gn:feature_class":"P",
    "gn:feature_code":"PPL",
    "gn:name":"Xiege",
    "gn:population":0,
    "gn:timezone":"Asia/Urumqi",
    "iso:country":"CN",
    "name:zho_x_preferred":[
        "\u6b47\u683c"
    ],
    "wof:name":"Xiege",
    "wof:placetype":"locality"
},
  "geometry": {"coordinates":[96.84492,33.32037],"type":"Point"}
}