{
  "type": "Feature",
  "properties": {
    "gn:admin1_code":"2.0",
    "gn:asciiname":"Yunjitang",
    "gn:country_code":"CN",
    "gn:dem":48,
    "gn:feature_class":"P",
    "gn:feature_code":"PPL",
    "gn:name":"Yunjitang",
    "gn:population":0,
    "gn:timezone":"Asia/Shanghai",
    "iso:country":"CN",
    "name:zho_x_preferred":[
        "\u8fd0\u6d4e\u5802"
    ],
    "wof:name":"Yunjitang",
    "wof:placetype":"locality"
},
  "geometry": {"coordinates":[120.51707,27.15755],"type":"Point"}
}