{
  "type": "Feature",
  "properties": {
    "gn:admin1_code":"33.0",
    "gn:asciiname":"Bake",
    "gn:country_code":"CN",
    "gn:dem":331,
    "gn:feature_class":"P",
    "gn:feature_code":"PPLA4",
    "gn:name":"Bake",
    "gn:population":0,
    "gn:timezone":"Asia/Shanghai",
    "iso:country":"CN",
    "name:und_x_variant":[
        "Bake Zhen"
    ],
    "name:zho_x_preferred":[
        "\u516b\u9897"
    ],
    "name:zho_x_variant":[
        "\u516b\u9897\u9547",
        "\u516b\u9897\u8857\u9053"
    ],
    "wof:name":"Bake",
    "wof:placetype":"locality"
},
  "geometry": {"coordinates":[107.02290000000001,29.90059],"type":"Point"}
}