{
  "type": "Feature",
  "properties": {
    "gn:admin1_code":"32.0",
    "gn:asciiname":"Rekepu",
    "gn:country_code":"CN",
    "gn:dem":2556,
    "gn:feature_class":"P",
    "gn:feature_code":"PPL",
    "gn:name":"Rekepu",
    "gn:population":0,
    "gn:timezone":"Asia/Shanghai",
    "iso:country":"CN",
    "name:zho_x_preferred":[
        "\u70ed\u514b\u666e"
    ],
    "wof:name":"Rekepu",
    "wof:placetype":"locality"
},
  "geometry": {"coordinates":[101.974,28.5335],"type":"Point"}
}