{
  "type": "Feature",
  "properties": {
    "gn:admin1_code":"19.0",
    "gn:asciiname":"Zhihetun",
    "gn:country_code":"CN",
    "gn:dem":223,
    "gn:feature_class":"P",
    "gn:feature_code":"PPL",
    "gn:name":"Zhihetun",
    "gn:population":0,
    "gn:timezone":"Asia/Shanghai",
    "iso:country":"CN",
    "name:zho_x_preferred":[
        "\u81f4\u548c\u5c6f"
    ],
    "wof:name":"Zhihetun",
    "wof:placetype":"locality"
},
  "geometry": {"coordinates":[124.48987,42.61863],"type":"Point"}
}