{
  "type": "Feature",
  "properties": {
    "gn:admin1_code":"09",
    "gn:asciiname":"Nanhedian",
    "gn:country_code":"CN",
    "gn:dem":185,
    "gn:feature_class":"P",
    "gn:feature_code":"PPL",
    "gn:name":"Nanhedian",
    "gn:population":0,
    "gn:timezone":"Asia/Shanghai",
    "iso:country":"CN",
    "name:und_x_variant":[
        "Nan-ho-tien",
        "\u5357\u6cb3\u5e97",
        "Nanhedian"
    ],
    "wof:name":"Nanhedian",
    "wof:placetype":"locality"
},
  "geometry": {"coordinates":[112.41182999999999,33.36205],"type":"Point"}
}