{
  "type": "Feature",
  "properties": {
    "gn:admin1_code":"29.0",
    "gn:asciiname":"Luodu",
    "gn:country_code":"CN",
    "gn:dem":1004,
    "gn:feature_class":"P",
    "gn:feature_code":"PPL",
    "gn:name":"Luodu",
    "gn:population":0,
    "gn:timezone":"Asia/Shanghai",
    "iso:country":"CN",
    "name:zho_x_preferred":[
        "\u502e\u675c"
    ],
    "wof:name":"Luodu",
    "wof:placetype":"locality"
},
  "geometry": {"coordinates":[102.401,22.778],"type":"Point"}
}