{
  "type": "Feature",
  "properties": {
    "gn:admin1_code":"30",
    "gn:asciiname":"Hewukeng",
    "gn:country_code":"CN",
    "gn:dem":230,
    "gn:feature_class":"P",
    "gn:feature_code":"PPL",
    "gn:name":"Hewukeng",
    "gn:population":0,
    "gn:timezone":"Asia/Shanghai",
    "iso:country":"CN",
    "name:zho_x_preferred":[
        "\u4f55\u5c4b\u5751"
    ],
    "wof:name":"Hewukeng",
    "wof:placetype":"locality"
},
  "geometry": {"coordinates":[115.72633999999999,24.41681],"type":"Point"}
}