{
  "type": "Feature",
  "properties": {
    "gn:admin1_code":"19.0",
    "gn:asciiname":"Congtun",
    "gn:country_code":"CN",
    "gn:dem":47,
    "gn:feature_class":"P",
    "gn:feature_code":"PPL",
    "gn:name":"Congtun",
    "gn:population":0,
    "gn:timezone":"Asia/Shanghai",
    "iso:country":"CN",
    "name:und_x_variant":[
        "\u4e1b\u5c6f"
    ],
    "name:zho_x_preferred":[
        "\u4e1b\u5c6f"
    ],
    "wof:name":"Congtun",
    "wof:placetype":"locality"
},
  "geometry": {"coordinates":[122.41424000000001,39.75844],"type":"Point"}
}