{
  "type": "Feature",
  "properties": {
    "gn:admin1_code":"29.0",
    "gn:asciiname":"Xiaozhaicun",
    "gn:country_code":"CN",
    "gn:dem":1554,
    "gn:feature_class":"P",
    "gn:feature_code":"PPL",
    "gn:name":"Xiaozhaicun",
    "gn:population":0,
    "gn:timezone":"Asia/Shanghai",
    "iso:country":"CN",
    "name:zho_x_preferred":[
        "\u5c0f\u5be8\u6751"
    ],
    "wof:name":"Xiaozhaicun",
    "wof:placetype":"locality"
},
  "geometry": {"coordinates":[102.931,27.212],"type":"Point"}
}