{
  "type": "Feature",
  "properties": {
    "gn:admin1_code":"26.0",
    "gn:asciiname":"Dongchenjia Hecun",
    "gn:country_code":"CN",
    "gn:dem":944,
    "gn:feature_class":"P",
    "gn:feature_code":"PPL",
    "gn:name":"Dongchenjia Hecun",
    "gn:population":0,
    "gn:timezone":"Asia/Shanghai",
    "iso:country":"CN",
    "name:zho_x_preferred":[
        "\u4e1c\u9648\u5bb6\u6cb3\u6751"
    ],
    "wof:name":"Dongchenjia Hecun",
    "wof:placetype":"locality"
},
  "geometry": {"coordinates":[110.328,37.2591],"type":"Point"}
}