{
  "type": "Feature",
  "properties": {
    "gn:admin1_code":"29.0",
    "gn:asciiname":"Keti",
    "gn:country_code":"CN",
    "gn:dem":1901,
    "gn:feature_class":"P",
    "gn:feature_code":"PPL",
    "gn:name":"Keti",
    "gn:population":0,
    "gn:timezone":"Asia/Shanghai",
    "iso:country":"CN",
    "name:und_x_variant":[
        "\u514b\u68af"
    ],
    "wof:name":"Keti",
    "wof:placetype":"locality"
},
  "geometry": {"coordinates":[102.42037000000001,25.61026],"type":"Point"}
}