{
  "type": "Feature",
  "properties": {
    "gn:admin1_code":"9.0",
    "gn:asciiname":"Qianzhaolou",
    "gn:country_code":"CN",
    "gn:dem":53,
    "gn:feature_class":"P",
    "gn:feature_code":"PPL",
    "gn:name":"Qianzhaolou",
    "gn:population":0,
    "gn:timezone":"Asia/Shanghai",
    "iso:country":"CN",
    "name:zho_x_preferred":[
        "\u524d\u8d75\u697c"
    ],
    "wof:name":"Qianzhaolou",
    "wof:placetype":"locality"
},
  "geometry": {"coordinates":[114.53718000000001,33.14043],"type":"Point"}
}