{
  "type": "Feature",
  "properties": {
    "gn:admin1_code":"4.0",
    "gn:asciiname":"Qianhuangying",
    "gn:country_code":"CN",
    "gn:dem":35,
    "gn:feature_class":"P",
    "gn:feature_code":"PPL",
    "gn:name":"Qianhuangying",
    "gn:population":0,
    "gn:timezone":"Asia/Shanghai",
    "iso:country":"CN",
    "name:zho_x_preferred":[
        "\u524d\u9ec4\u90e2"
    ],
    "wof:name":"Qianhuangying",
    "wof:placetype":"locality"
},
  "geometry": {"coordinates":[118.56141,32.88253],"type":"Point"}
}