{
  "type": "Feature",
  "properties": {
    "gn:admin1_code":"24.0",
    "gn:asciiname":"Wayuancun",
    "gn:country_code":"CN",
    "gn:dem":1116,
    "gn:feature_class":"P",
    "gn:feature_code":"PPL",
    "gn:name":"Wayuancun",
    "gn:population":0,
    "gn:timezone":"Asia/Shanghai",
    "iso:country":"CN",
    "name:zho_x_preferred":[
        "\u74e6\u539f\u6751"
    ],
    "wof:name":"Wayuancun",
    "wof:placetype":"locality"
},
  "geometry": {"coordinates":[110.77903000000001,36.09979000000001],"type":"Point"}
}