{
  "type": "Feature",
  "properties": {
    "gn:admin1_code":"29.0",
    "gn:asciiname":"Kushuzhai",
    "gn:country_code":"CN",
    "gn:dem":1782,
    "gn:feature_class":"P",
    "gn:feature_code":"PPL",
    "gn:name":"Kushuzhai",
    "gn:population":0,
    "gn:timezone":"Asia/Shanghai",
    "iso:country":"CN",
    "name:zho_x_preferred":[
        "\u67af\u6811\u5be8"
    ],
    "wof:name":"Kushuzhai",
    "wof:placetype":"locality"
},
  "geometry": {"coordinates":[99.7504,24.8548],"type":"Point"}
}