{
  "type": "Feature",
  "properties": {
    "gn:admin1_code":"02",
    "gn:asciiname":"Wuyan",
    "gn:country_code":"CN",
    "gn:dem":433,
    "gn:feature_class":"P",
    "gn:feature_code":"PPL",
    "gn:name":"Wuyan",
    "gn:population":0,
    "gn:timezone":"Asia/Shanghai",
    "iso:country":"CN",
    "name:zho_x_preferred":[
        "\u4e4c\u5ca9"
    ],
    "wof:name":"Wuyan",
    "wof:placetype":"locality"
},
  "geometry": {"coordinates":[120.17073000000001,27.90381],"type":"Point"}
}