{
  "type": "Feature",
  "properties": {
    "gn:admin1_code":"5.0",
    "gn:asciiname":"Kuangshan Sandui",
    "gn:country_code":"CN",
    "gn:dem":472,
    "gn:feature_class":"P",
    "gn:feature_code":"PPLF",
    "gn:name":"Kuangshan Sandui",
    "gn:population":0,
    "gn:timezone":"Asia/Shanghai",
    "iso:country":"CN",
    "name:und_x_variant":[
        "\u77ff\u5c71\u4e09\u961f"
    ],
    "wof:name":"Kuangshan Sandui",
    "wof:placetype":"locality"
},
  "geometry": {"coordinates":[125.95304,41.38179],"type":"Point"}
}