{
  "type": "Feature",
  "properties": {
    "gn:admin1_code":"14",
    "gn:asciiname":"Nyangrain",
    "gn:country_code":"CN",
    "gn:dem":3732,
    "gn:feature_class":"P",
    "gn:feature_code":"PPL",
    "gn:name":"Nyangrain",
    "gn:population":0,
    "gn:timezone":"Asia/Urumqi",
    "iso:country":"CN",
    "name:bod_x_preferred":[
        "\u0f49\u0f44\u0f0b\u0f56\u0fb2\u0f53"
    ],
    "name:und_x_variant":[
        "Niangre"
    ],
    "name:zho_x_preferred":[
        "\u5a18\u70ed"
    ],
    "wof:name":"Nyangrain",
    "wof:placetype":"locality"
},
  "geometry": {"coordinates":[91.10614,29.71042000000001],"type":"Point"}
}