{
  "type": "Feature",
  "properties": {
    "gn:admin1_code":"25",
    "gn:asciiname":"Zhangnaimiao",
    "gn:country_code":"CN",
    "gn:dem":54,
    "gn:feature_class":"P",
    "gn:feature_code":"PPL",
    "gn:name":"Zhangnaimiao",
    "gn:population":0,
    "gn:timezone":"Asia/Shanghai",
    "iso:country":"CN",
    "name:zho_x_preferred":[
        "\u5f20\u5976\u5e99"
    ],
    "wof:name":"Zhangnaimiao",
    "wof:placetype":"locality"
},
  "geometry": {"coordinates":[115.861,34.7063],"type":"Point"}
}