{
  "type": "Feature",
  "properties": {
    "gn:admin1_code":"32.0",
    "gn:asciiname":"Tangwantou",
    "gn:country_code":"CN",
    "gn:dem":1099,
    "gn:feature_class":"P",
    "gn:feature_code":"PPL",
    "gn:name":"Tangwantou",
    "gn:population":0,
    "gn:timezone":"Asia/Shanghai",
    "iso:country":"CN",
    "name:zho_x_preferred":[
        "\u5858\u5846\u5934"
    ],
    "wof:name":"Tangwantou",
    "wof:placetype":"locality"
},
  "geometry": {"coordinates":[103.92509,28.78757],"type":"Point"}
}