{
  "type": "Feature",
  "properties": {
    "gn:admin1_code":"32.0",
    "gn:asciiname":"Hada",
    "gn:country_code":"CN",
    "gn:dem":4201,
    "gn:feature_class":"P",
    "gn:feature_code":"PPL",
    "gn:name":"Hada",
    "gn:population":0,
    "gn:timezone":"Asia/Shanghai",
    "iso:country":"CN",
    "name:ceb_x_preferred":[
        "Hada"
    ],
    "name:spa_x_preferred":[
        "Hada"
    ],
    "name:zho_x_preferred":[
        "\u54c8\u8fbe"
    ],
    "wof:name":"Hada",
    "wof:placetype":"locality"
},
  "geometry": {"coordinates":[98.81010000000001,32.631],"type":"Point"}
}