{
  "type": "Feature",
  "properties": {
    "gn:admin1_code":"14.0",
    "gn:asciiname":"Gailawoma",
    "gn:country_code":"CN",
    "gn:dem":4623,
    "gn:feature_class":"P",
    "gn:feature_code":"PPL",
    "gn:name":"Gailawoma",
    "gn:population":0,
    "gn:timezone":"Asia/Urumqi",
    "iso:country":"CN",
    "name:bod_x_preferred":[
        "G\u00eala\u2019ogma"
    ],
    "name:zho_x_preferred":[
        "Gailawoma"
    ],
    "name:zho_x_variant":[
        "\u76d6\u62c9\u6c83\u739b",
        "\u76d6\u62c9\u7a9d\u739b"
    ],
    "wof:name":"Gailawoma",
    "wof:placetype":"locality"
},
  "geometry": {"coordinates":[93.62144000000001,32.3487],"type":"Point"}
}