{
  "type": "Feature",
  "properties": {
    "gn:admin1_code":"32.0",
    "gn:asciiname":"Shuijing",
    "gn:country_code":"CN",
    "gn:dem":1157,
    "gn:feature_class":"P",
    "gn:feature_code":"PPL",
    "gn:name":"Shuijing",
    "gn:population":0,
    "gn:timezone":"Asia/Shanghai",
    "iso:country":"CN",
    "name:zho_x_preferred":[
        "\u6c34\u4e95"
    ],
    "wof:name":"Shuijing",
    "wof:placetype":"locality"
},
  "geometry": {"coordinates":[103.22,29.1842],"type":"Point"}
}