{
  "type": "Feature",
  "properties": {
    "gn:admin1_code":"29.0",
    "gn:asciiname":"Ali",
    "gn:country_code":"CN",
    "gn:dem":1101,
    "gn:feature_class":"P",
    "gn:feature_code":"PPL",
    "gn:name":"Ali",
    "gn:population":0,
    "gn:timezone":"Asia/Shanghai",
    "iso:country":"CN",
    "name:afr_x_preferred":[
        "Ali"
    ],
    "name:ang_x_preferred":[
        "Al\u012b"
    ],
    "name:arg_x_preferred":[
        "Al\u00ed"
    ],
    "name:aze_x_preferred":[
        "\u018fli"
    ],
    "name:ces_x_preferred":[
        "Al\u00ed"
    ],
    "name:dan_x_preferred":[
        "Ali"
    ],
    "name:diq_x_preferred":[
        "Eli"
    ],
    "name:div_x_preferred":[
        "\u07a2\u07a6\u078d\u07a9\u078e\u07ac\u078a\u07a7\u0782\u07aa"
    ],
    "name:hau_x_preferred":[
        "Ali"
    ],
    "name:hrv_x_preferred":[
        "Ali"
    ],
    "name:hun_x_preferred":[
        "Ali kalifa"
    ],
    "name:jpn_x_preferred":[
        "\u30a2\u30ea\u30fc\u30fb\u30a4\u30d6\u30f3\u30fb\u30a2\u30d3\u30fc\u30fb\u30bf\u30fc\u30ea\u30d6"
    ],
    "name:kur_x_preferred":[
        "El\u00ee"
    ],
    "name:lfn_x_preferred":[
        "Ali"
    ],
    "name:lit_x_preferred":[
        "Ali"
    ],
    "name:mzn_x_preferred":[
        "\u0639\u0644\u06cc"
    ],
    "name:pan_x_preferred":[
        "\u0a05\u0a32\u0a40"
    ],
    "name:pnb_x_preferred":[
        "\u0639\u0644\u06cc"
    ],
    "name:por_x_preferred":[
        "Ali"
    ],
    "name:ron_x_preferred":[
        "Ali"
    ],
    "name:sco_x_preferred":[
        "Ali"
    ],
    "name:slk_x_preferred":[
        "Al\u00ed"
    ],
    "name:slv_x_preferred":[
        "Ali"
    ],
    "name:snd_x_preferred":[
        "\u0639\u0644\u064a"
    ],
    "name:som_x_preferred":[
        "Cali"
    ],
    "name:sqi_x_preferred":[
        "Aliu"
    ],
    "name:srp_x_preferred":[
        "\u0410\u043b\u0438\u0458\u0430"
    ],
    "name:tam_x_preferred":[
        "\u0b85\u0bb2\u0bc0"
    ],
    "name:tur_x_preferred":[
        "Ali"
    ],
    "name:uzb_x_preferred":[
        "Ali"
    ],
    "name:war_x_preferred":[
        "Ali"
    ],
    "name:wln_x_preferred":[
        "Ali"
    ],
    "name:wuu_x_preferred":[
        "\u963f\u91cc\u00b7\u672c\u00b7\u963f\u6bd4\u00b7\u5854\u5229\u535c"
    ],
    "name:zho_x_preferred":[
        "\u963f\u91cc"
    ],
    "name:zho_x_variant":[
        "\u963f\u91cc\u00b7\u672c\u00b7\u963f\u6bd4\u00b7\u5854\u5229\u535c"
    ],
    "wof:name":"Ali",
    "wof:placetype":"locality"
},
  "geometry": {"coordinates":[99.6678,22.1339],"type":"Point"}
}