{
  "type": "Feature",
  "properties": {
    "gn:admin1_code":"29.0",
    "gn:asciiname":"Ali",
    "gn:country_code":"CN",
    "gn:dem":1101,
    "gn:feature_class":"P",
    "gn:feature_code":"PPL",
    "gn:name":"Ali",
    "gn:population":0,
    "gn:timezone":"Asia/Shanghai",
    "iso:country":"CN",
    "name:zho_x_preferred":[
        "\u963f\u91cc"
    ],
    "wof:name":"Ali",
    "wof:placetype":"locality"
},
  "geometry": {"coordinates":[99.6678,22.1339],"type":"Point"}
}