{
  "type": "Feature",
  "properties": {
    "gn:admin1_code":"8.0",
    "gn:asciiname":"Ganmianshicun",
    "gn:country_code":"CN",
    "gn:dem":557,
    "gn:feature_class":"P",
    "gn:feature_code":"PPL",
    "gn:name":"Ganmianshicun",
    "gn:population":0,
    "gn:timezone":"Asia/Shanghai",
    "iso:country":"CN",
    "name:zho_x_preferred":[
        "\u64c0\u9762\u77f3\u6751"
    ],
    "wof:name":"Ganmianshicun",
    "wof:placetype":"locality"
},
  "geometry": {"coordinates":[130.15566000000001,44.54955],"type":"Point"}
}