{
  "type": "Feature",
  "properties": {
    "gn:admin1_code":"4.0",
    "gn:asciiname":"Xijinqiao",
    "gn:country_code":"CN",
    "gn:dem":9,
    "gn:feature_class":"P",
    "gn:feature_code":"PPL",
    "gn:name":"Xijinqiao",
    "gn:population":0,
    "gn:timezone":"Asia/Shanghai",
    "iso:country":"CN",
    "name:und_x_variant":[
        "Hsi-chin-ch\u2019iao"
    ],
    "wof:name":"Xijinqiao",
    "wof:placetype":"locality"
},
  "geometry": {"coordinates":[120.5425,31.30806],"type":"Point"}
}