{
  "type": "Feature",
  "properties": {
    "gn:admin1_code":"18",
    "gn:asciiname":"Ximan",
    "gn:country_code":"CN",
    "gn:dem":680,
    "gn:feature_class":"P",
    "gn:feature_code":"PPL",
    "gn:name":"Ximan",
    "gn:population":0,
    "gn:timezone":"Asia/Shanghai",
    "iso:country":"CN",
    "name:zho_x_preferred":[
        "\u559c\u6ee1"
    ],
    "wof:name":"Ximan",
    "wof:placetype":"locality"
},
  "geometry": {"coordinates":[105.892,25.3531],"type":"Point"}
}