{
  "type": "Feature",
  "properties": {
    "gn:admin1_code":"10",
    "gn:asciiname":"Wula Hada",
    "gn:country_code":"CN",
    "gn:dem":874,
    "gn:feature_class":"P",
    "gn:feature_code":"PPL",
    "gn:name":"Wula Hada",
    "gn:population":0,
    "gn:timezone":"Asia/Shanghai",
    "iso:country":"CN",
    "name:zho_x_preferred":[
        "\u4e4c\u62c9\u54c8\u8fbe"
    ],
    "wof:name":"Wula Hada",
    "wof:placetype":"locality"
},
  "geometry": {"coordinates":[114.94450000000001,40.89002],"type":"Point"}
}