{
  "type": "Feature",
  "properties": {
    "gn:admin1_code":"32.0",
    "gn:asciiname":"Laohuoshan",
    "gn:country_code":"CN",
    "gn:dem":2418,
    "gn:feature_class":"P",
    "gn:feature_code":"PPL",
    "gn:name":"Laohuoshan",
    "gn:population":0,
    "gn:timezone":"Asia/Shanghai",
    "iso:country":"CN",
    "name:zho_x_preferred":[
        "\u8001\u706b\u5c71"
    ],
    "wof:name":"Laohuoshan",
    "wof:placetype":"locality"
},
  "geometry": {"coordinates":[101.881,28.6489],"type":"Point"}
}