{
  "type": "Feature",
  "properties": {
    "gn:admin1_code":"4.0",
    "gn:asciiname":"Jinchencun",
    "gn:country_code":"CN",
    "gn:dem":41,
    "gn:feature_class":"P",
    "gn:feature_code":"PPL",
    "gn:name":"Jinchencun",
    "gn:population":0,
    "gn:timezone":"Asia/Shanghai",
    "iso:country":"CN",
    "name:zho_x_preferred":[
        "\u91d1\u9648\u6751"
    ],
    "wof:name":"Jinchencun",
    "wof:placetype":"locality"
},
  "geometry": {"coordinates":[118.84148999999999,32.51312],"type":"Point"}
}