{
  "type": "Feature",
  "properties": {
    "gn:admin1_code":"1.0",
    "gn:asciiname":"Huasicun",
    "gn:country_code":"CN",
    "gn:dem":41,
    "gn:feature_class":"P",
    "gn:feature_code":"PPL",
    "gn:name":"Huasicun",
    "gn:population":0,
    "gn:timezone":"Asia/Shanghai",
    "iso:country":"CN",
    "name:zho_x_preferred":[
        "\u534e\u5bfa\u6751"
    ],
    "wof:name":"Huasicun",
    "wof:placetype":"locality"
},
  "geometry": {"coordinates":[115.66677,33.71993],"type":"Point"}
}