{
  "type": "Feature",
  "properties": {
    "gn:admin1_code":"11.0",
    "gn:asciiname":"Longbeng",
    "gn:country_code":"CN",
    "gn:dem":552,
    "gn:feature_class":"P",
    "gn:feature_code":"PPL",
    "gn:name":"Longbeng",
    "gn:population":0,
    "gn:timezone":"Asia/Shanghai",
    "iso:country":"CN",
    "name:zho_x_preferred":[
        "\u9f99\u5d29"
    ],
    "wof:name":"Longbeng",
    "wof:placetype":"locality"
},
  "geometry": {"coordinates":[109.15488000000001,27.2596],"type":"Point"}
}