{
  "type": "Feature",
  "properties": {
    "gn:admin1_code":"19.0",
    "gn:asciiname":"Dahouhai",
    "gn:country_code":"CN",
    "gn:dem":10,
    "gn:feature_class":"P",
    "gn:feature_code":"PPL",
    "gn:name":"Dahouhai",
    "gn:population":0,
    "gn:timezone":"Asia/Shanghai",
    "iso:country":"CN",
    "name:zho_x_preferred":[
        "\u5927\u540e\u6d77"
    ],
    "wof:name":"Dahouhai",
    "wof:placetype":"locality"
},
  "geometry": {"coordinates":[121.628,39.2756],"type":"Point"}
}