{
  "type": "Feature",
  "properties": {
    "gn:admin1_code":"4.0",
    "gn:asciiname":"Cuotouxu",
    "gn:country_code":"CN",
    "gn:dem":5,
    "gn:feature_class":"P",
    "gn:feature_code":"PPL",
    "gn:name":"Cuotouxu",
    "gn:population":0,
    "gn:timezone":"Asia/Shanghai",
    "iso:country":"CN",
    "name:zho_x_preferred":[
        "\u64ae\u5934\u5729"
    ],
    "wof:name":"Cuotouxu",
    "wof:placetype":"locality"
},
  "geometry": {"coordinates":[120.83861,32.24519],"type":"Point"}
}