{
  "type": "Feature",
  "properties": {
    "gn:admin1_code":"7.0",
    "gn:asciiname":"Yaobiankeng",
    "gn:country_code":"CN",
    "gn:dem":353,
    "gn:feature_class":"P",
    "gn:feature_code":"PPL",
    "gn:name":"Yaobiankeng",
    "gn:population":0,
    "gn:timezone":"Asia/Shanghai",
    "iso:country":"CN",
    "name:zho_x_preferred":[
        "\u7476\u8fb9\u5751"
    ],
    "wof:name":"Yaobiankeng",
    "wof:placetype":"locality"
},
  "geometry": {"coordinates":[117.06692,26.85577],"type":"Point"}
}