{
  "type": "Feature",
  "properties": {
    "gn:admin1_code":"14.0",
    "gn:asciiname":"Gongleika",
    "gn:country_code":"CN",
    "gn:dem":4230,
    "gn:feature_class":"P",
    "gn:feature_code":"PPL",
    "gn:name":"Gongleika",
    "gn:population":0,
    "gn:timezone":"Asia/Urumqi",
    "iso:country":"CN",
    "name:zho_x_preferred":[
        "\u8d21\u96f7\u5361"
    ],
    "wof:name":"Gongleika",
    "wof:placetype":"locality"
},
  "geometry": {"coordinates":[94.38571,31.271],"type":"Point"}
}