{
  "type": "Feature",
  "properties": {
    "gn:admin1_code":"18.0",
    "gn:asciiname":"Hetaowan",
    "gn:country_code":"CN",
    "gn:dem":811,
    "gn:feature_class":"P",
    "gn:feature_code":"PPL",
    "gn:name":"Hetaowan",
    "gn:population":0,
    "gn:timezone":"Asia/Shanghai",
    "iso:country":"CN",
    "name:zho_x_preferred":[
        "\u6838\u6843\u6e7e"
    ],
    "wof:name":"Hetaowan",
    "wof:placetype":"locality"
},
  "geometry": {"coordinates":[108.61199999999999,28.1396],"type":"Point"}
}