{
  "type": "Feature",
  "properties": {
    "gn:admin1_code":"15.0",
    "gn:asciiname":"Huangqu Xiaomiao",
    "gn:country_code":"CN",
    "gn:dem":1110,
    "gn:feature_class":"P",
    "gn:feature_code":"PPL",
    "gn:name":"Huangqu Xiaomiao",
    "gn:population":0,
    "gn:timezone":"Asia/Urumqi",
    "iso:country":"CN",
    "name:zho_x_preferred":[
        "\u9ec4\u6e20\u5c0f\u5e99"
    ],
    "wof:name":"Huangqu Xiaomiao",
    "wof:placetype":"locality"
},
  "geometry": {"coordinates":[94.68089999999999,40.2308],"type":"Point"}
}