{
  "type": "Feature",
  "properties": {
    "gn:admin1_code":"25.0",
    "gn:asciiname":"Dadijicun",
    "gn:country_code":"CN",
    "gn:dem":66,
    "gn:feature_class":"P",
    "gn:feature_code":"PPL",
    "gn:name":"Dadijicun",
    "gn:population":0,
    "gn:timezone":"Asia/Shanghai",
    "iso:country":"CN",
    "name:zho_x_preferred":[
        "\u5927\u8fea\u5409\u6751"
    ],
    "wof:name":"Dadijicun",
    "wof:placetype":"locality"
},
  "geometry": {"coordinates":[119.43795,35.7121],"type":"Point"}
}