{
  "type": "Feature",
  "properties": {
    "gn:admin1_code":"2.0",
    "gn:asciiname":"Sifangkeng",
    "gn:country_code":"CN",
    "gn:dem":200,
    "gn:feature_class":"P",
    "gn:feature_code":"PPL",
    "gn:name":"Sifangkeng",
    "gn:population":0,
    "gn:timezone":"Asia/Shanghai",
    "iso:country":"CN",
    "name:zho_x_preferred":[
        "\u56db\u65b9\u5751"
    ],
    "wof:name":"Sifangkeng",
    "wof:placetype":"locality"
},
  "geometry": {"coordinates":[119.92722000000001,27.76418],"type":"Point"}
}