{
  "type": "Feature",
  "properties": {
    "gn:admin1_code":"18.0",
    "gn:asciiname":"Dongyuan",
    "gn:country_code":"CN",
    "gn:dem":632,
    "gn:feature_class":"P",
    "gn:feature_code":"PPL",
    "gn:name":"Dongyuan",
    "gn:population":0,
    "gn:timezone":"Asia/Shanghai",
    "iso:country":"CN",
    "name:ceb_x_preferred":[
        "Dongyuan"
    ],
    "name:deu_x_preferred":[
        "Dongyuan"
    ],
    "name:nor_x_preferred":[
        "Dongyuan"
    ],
    "name:zho_x_preferred":[
        "\u6d1e\u9662"
    ],
    "wof:name":"Dongyuan",
    "wof:placetype":"locality"
},
  "geometry": {"coordinates":[108.63,26.9311],"type":"Point"}
}