{
  "type": "Feature",
  "properties": {
    "gn:admin1_code":"19",
    "gn:asciiname":"Ta-chia-la-tzu",
    "gn:country_code":"CN",
    "gn:dem":538,
    "gn:feature_class":"P",
    "gn:feature_code":"PPL",
    "gn:name":"Ta-chia-la-tzu",
    "gn:population":0,
    "gn:timezone":"Asia/Shanghai",
    "iso:country":"CN",
    "wof:name":"Ta-chia-la-tzu",
    "wof:placetype":"locality"
},
  "geometry": {"coordinates":[125.22194,41.03361],"type":"Point"}
}