{
  "type": "Feature",
  "properties": {
    "gn:admin1_code":"30.0",
    "gn:asciiname":"Xinlou",
    "gn:country_code":"CN",
    "gn:dem":174,
    "gn:feature_class":"P",
    "gn:feature_code":"PPL",
    "gn:name":"Xinlou",
    "gn:population":0,
    "gn:timezone":"Asia/Shanghai",
    "iso:country":"CN",
    "name:zho_x_preferred":[
        "Xinlou"
    ],
    "name:zho_x_variant":[
        "\u65b0\u697c"
    ],
    "wof:name":"Xinlou",
    "wof:placetype":"locality"
},
  "geometry": {"coordinates":[114.93444,24.27472],"type":"Point"}
}