{
  "type": "Feature",
  "properties": {
    "gn:admin1_code":"10.0",
    "gn:asciiname":"Lingjiaoqiao",
    "gn:country_code":"CN",
    "gn:dem":19,
    "gn:feature_class":"P",
    "gn:feature_code":"PPL",
    "gn:name":"Lingjiaoqiao",
    "gn:population":0,
    "gn:timezone":"Asia/Shanghai",
    "iso:country":"CN",
    "name:zho_x_preferred":[
        "\u51cc\u89d2\u6865"
    ],
    "wof:name":"Lingjiaoqiao",
    "wof:placetype":"locality"
},
  "geometry": {"coordinates":[115.67202,38.99795],"type":"Point"}
}