{
  "type": "Feature",
  "properties": {
    "gn:admin1_code":"26",
    "gn:asciiname":"Wujialing",
    "gn:cc2":"CN",
    "gn:country_code":"CN",
    "gn:dem":921,
    "gn:feature_class":"P",
    "gn:feature_code":"PPL",
    "gn:name":"Wujialing",
    "gn:population":0,
    "gn:timezone":"Asia/Shanghai",
    "iso:country":"CN",
    "name:und_x_variant":[
        "Wu-chia-ling",
        "Wujialing"
    ],
    "wof:name":"Wujialing",
    "wof:placetype":"locality"
},
  "geometry": {"coordinates":[110.42667,36.27083],"type":"Point"}
}