{
  "type": "Feature",
  "properties": {
    "gn:admin1_code":"23.0",
    "gn:asciiname":"Baimatang",
    "gn:country_code":"CN",
    "gn:dem":3,
    "gn:feature_class":"P",
    "gn:feature_code":"PPL",
    "gn:name":"Baimatang",
    "gn:population":0,
    "gn:timezone":"Asia/Shanghai",
    "iso:country":"CN",
    "name:zho_x_preferred":[
        "Baimatang"
    ],
    "name:zho_x_variant":[
        "\u767d\u9a6c\u5858"
    ],
    "wof:name":"Baimatang",
    "wof:placetype":"locality"
},
  "geometry": {"coordinates":[121.21669,31.18481],"type":"Point"}
}