{
  "type": "Feature",
  "properties": {
    "gn:admin1_code":"15.0",
    "gn:asciiname":"Nanhu Dadui",
    "gn:country_code":"CN",
    "gn:dem":2079,
    "gn:feature_class":"P",
    "gn:feature_code":"PPLF",
    "gn:name":"Nanhu Dadui",
    "gn:population":0,
    "gn:timezone":"Asia/Shanghai",
    "iso:country":"CN",
    "name:zho_x_preferred":[
        "\u5357\u6e56\u5927\u961f"
    ],
    "wof:name":"Nanhu Dadui",
    "wof:placetype":"locality"
},
  "geometry": {"coordinates":[96.746,39.8623],"type":"Point"}
}