{
  "type": "Feature",
  "properties": {
    "gn:admin1_code":"19",
    "gn:asciiname":"Zhangyizhancun",
    "gn:country_code":"CN",
    "gn:dem":20,
    "gn:feature_class":"P",
    "gn:feature_code":"PPL",
    "gn:name":"Zhangyizhancun",
    "gn:population":0,
    "gn:timezone":"Asia/Shanghai",
    "iso:country":"CN",
    "name:und_x_variant":[
        "Zhangyizhan"
    ],
    "name:zho_x_preferred":[
        "\u5f70\u9a7f\u7ad9\u6751"
    ],
    "wof:name":"Zhangyizhancun",
    "wof:placetype":"locality"
},
  "geometry": {"coordinates":[123.07746000000002,41.64856],"type":"Point"}
}