{
  "type": "Feature",
  "properties": {
    "gn:admin1_code":"15.0",
    "gn:asciiname":"Yangwanliang",
    "gn:country_code":"CN",
    "gn:dem":1525,
    "gn:feature_class":"P",
    "gn:feature_code":"PPL",
    "gn:name":"Yangwanliang",
    "gn:population":0,
    "gn:timezone":"Asia/Shanghai",
    "iso:country":"CN",
    "name:und_x_variant":[
        "\u6768\u6e7e\u6881"
    ],
    "wof:name":"Yangwanliang",
    "wof:placetype":"locality"
},
  "geometry": {"coordinates":[107.09984,36.15194],"type":"Point"}
}