{
  "type": "Feature",
  "properties": {
    "gn:admin1_code":"14",
    "gn:asciiname":"Xiongma",
    "gn:country_code":"CN",
    "gn:dem":3984,
    "gn:feature_class":"P",
    "gn:feature_code":"PPL",
    "gn:name":"Xiongma",
    "gn:population":0,
    "gn:timezone":"Asia/Urumqi",
    "iso:country":"CN",
    "name:zho_x_preferred":[
        "\u96c4\u739b"
    ],
    "wof:name":"Xiongma",
    "wof:placetype":"locality"
},
  "geometry": {"coordinates":[88.4744,29.06900000000001],"type":"Point"}
}