{
  "type": "Feature",
  "properties": {
    "gn:admin1_code":"32.0",
    "gn:asciiname":"Dengshenguan",
    "gn:country_code":"CN",
    "gn:dem":641,
    "gn:feature_class":"P",
    "gn:feature_code":"PPL",
    "gn:name":"Dengshenguan",
    "gn:population":0,
    "gn:timezone":"Asia/Shanghai",
    "iso:country":"CN",
    "name:zho_x_preferred":[
        "\u706f\u795e\u89c2"
    ],
    "wof:name":"Dengshenguan",
    "wof:placetype":"locality"
},
  "geometry": {"coordinates":[104.771,31.7389],"type":"Point"}
}