{
  "type": "Feature",
  "properties": {
    "gn:admin1_code":"26.0",
    "gn:asciiname":"Xialuojiawan",
    "gn:country_code":"CN",
    "gn:dem":1319,
    "gn:feature_class":"P",
    "gn:feature_code":"PPL",
    "gn:name":"Xialuojiawan",
    "gn:population":0,
    "gn:timezone":"Asia/Shanghai",
    "iso:country":"CN",
    "name:zho_x_preferred":[
        "\u4e0b\u7f57\u5bb6\u6e7e"
    ],
    "wof:name":"Xialuojiawan",
    "wof:placetype":"locality"
},
  "geometry": {"coordinates":[108.81364000000001,36.80451],"type":"Point"}
}