{
  "type": "Feature",
  "properties": {
    "gn:admin1_code":"19.0",
    "gn:asciiname":"Zhangheling",
    "gn:country_code":"CN",
    "gn:dem":329,
    "gn:feature_class":"P",
    "gn:feature_code":"PPL",
    "gn:name":"Zhangheling",
    "gn:population":0,
    "gn:timezone":"Asia/Shanghai",
    "iso:country":"CN",
    "name:und_x_variant":[
        "\u5f20\u5408\u5cad"
    ],
    "wof:name":"Zhangheling",
    "wof:placetype":"locality"
},
  "geometry": {"coordinates":[122.33798,40.14213],"type":"Point"}
}