{
  "type": "Feature",
  "properties": {
    "gn:admin1_code":"5.0",
    "gn:asciiname":"Xiaozhangjiayao",
    "gn:country_code":"CN",
    "gn:dem":151,
    "gn:feature_class":"P",
    "gn:feature_code":"PPL",
    "gn:name":"Xiaozhangjiayao",
    "gn:population":0,
    "gn:timezone":"Asia/Shanghai",
    "iso:country":"CN",
    "name:zho_x_preferred":[
        "\u5c0f\u5f20\u5bb6\u7a91"
    ],
    "wof:name":"Xiaozhangjiayao",
    "wof:placetype":"locality"
},
  "geometry": {"coordinates":[123.69476,44.03034],"type":"Point"}
}