{
  "type": "Feature",
  "properties": {
    "gn:admin1_code":"20",
    "gn:asciiname":"Wenkutu",
    "gn:country_code":"CN",
    "gn:dem":550,
    "gn:feature_class":"P",
    "gn:feature_code":"PPLA4",
    "gn:name":"Wenkutu",
    "gn:population":0,
    "gn:timezone":"Asia/Shanghai",
    "iso:country":"CN",
    "name:und_x_variant":[
        "Wenkutu Xiang"
    ],
    "name:zho_x_preferred":[
        "\u6e29\u5e93\u56fe"
    ],
    "name:zho_x_variant":[
        "\u6e29\u5e93\u56fe\u4e61"
    ],
    "wof:name":"Wenkutu",
    "wof:placetype":"locality"
},
  "geometry": {"coordinates":[122.48447,49.44647],"type":"Point"}
}