{
  "type": "Feature",
  "properties": {
    "gn:admin1_code":"30.0",
    "gn:asciiname":"Aoding",
    "gn:country_code":"CN",
    "gn:dem":396,
    "gn:feature_class":"P",
    "gn:feature_code":"PPL",
    "gn:name":"Aoding",
    "gn:population":0,
    "gn:timezone":"Asia/Shanghai",
    "iso:country":"CN",
    "name:zho_x_preferred":[
        "\u5773\u9876"
    ],
    "wof:name":"Aoding",
    "wof:placetype":"locality"
},
  "geometry": {"coordinates":[113.34541000000002,24.48195],"type":"Point"}
}