{
  "type": "Feature",
  "properties": {
    "gn:admin1_code":"19.0",
    "gn:asciiname":"Shanghunjiugou",
    "gn:country_code":"CN",
    "gn:dem":105,
    "gn:feature_class":"P",
    "gn:feature_code":"PPL",
    "gn:name":"Shanghunjiugou",
    "gn:population":0,
    "gn:timezone":"Asia/Shanghai",
    "iso:country":"CN",
    "name:zho_x_preferred":[
        "\u4e0a\u6d51\u9152\u6c9f"
    ],
    "wof:name":"Shanghunjiugou",
    "wof:placetype":"locality"
},
  "geometry": {"coordinates":[120.87236,41.10284],"type":"Point"}
}