{
  "type": "Feature",
  "properties": {
    "gn:admin1_code":"18",
    "gn:asciiname":"Chahe Xiaozhai",
    "gn:country_code":"CN",
    "gn:dem":1555,
    "gn:feature_class":"P",
    "gn:feature_code":"PPL",
    "gn:name":"Chahe Xiaozhai",
    "gn:population":0,
    "gn:timezone":"Asia/Shanghai",
    "iso:country":"CN",
    "name:zho_x_preferred":[
        "\u5c94\u6cb3\u5c0f\u5be8"
    ],
    "wof:name":"Chahe Xiaozhai",
    "wof:placetype":"locality"
},
  "geometry": {"coordinates":[104.554,25.5362],"type":"Point"}
}