{
  "type": "Feature",
  "properties": {
    "gn:admin1_code":"19.0",
    "gn:asciiname":"Douzhangzicun",
    "gn:country_code":"CN",
    "gn:dem":521,
    "gn:feature_class":"P",
    "gn:feature_code":"PPL",
    "gn:name":"Douzhangzicun",
    "gn:population":0,
    "gn:timezone":"Asia/Shanghai",
    "iso:country":"CN",
    "name:zho_x_preferred":[
        "\u7aa6\u6756\u5b50\u6751"
    ],
    "wof:name":"Douzhangzicun",
    "wof:placetype":"locality"
},
  "geometry": {"coordinates":[119.595,40.6871],"type":"Point"}
}