{
  "type": "Feature",
  "properties": {
    "gn:admin1_code":"14.0",
    "gn:asciiname":"Dabagong",
    "gn:country_code":"CN",
    "gn:dem":3986,
    "gn:feature_class":"P",
    "gn:feature_code":"PPL",
    "gn:name":"Dabagong",
    "gn:population":0,
    "gn:timezone":"Asia/Urumqi",
    "iso:country":"CN",
    "name:zho_x_preferred":[
        "\u8fbe\u5df4\u8d21"
    ],
    "wof:name":"Dabagong",
    "wof:placetype":"locality"
},
  "geometry": {"coordinates":[98.7388,29.46968],"type":"Point"}
}