{
  "type": "Feature",
  "properties": {
    "gn:admin1_code":"02",
    "gn:asciiname":"Xintangtou",
    "gn:country_code":"CN",
    "gn:dem":6,
    "gn:feature_class":"P",
    "gn:feature_code":"PPL",
    "gn:name":"Xintangtou",
    "gn:population":0,
    "gn:timezone":"Asia/Shanghai",
    "iso:country":"CN",
    "name:und_x_variant":[
        "\u65b0\u5858\u5934"
    ],
    "wof:name":"Xintangtou",
    "wof:placetype":"locality"
},
  "geometry": {"coordinates":[121.48818,30.1297],"type":"Point"}
}