{
  "type": "Feature",
  "properties": {
    "gn:admin1_code":"29.0",
    "gn:asciiname":"Hetaozhai",
    "gn:country_code":"CN",
    "gn:dem":1937,
    "gn:feature_class":"P",
    "gn:feature_code":"PPL",
    "gn:name":"Hetaozhai",
    "gn:population":0,
    "gn:timezone":"Asia/Shanghai",
    "iso:country":"CN",
    "name:zho_x_preferred":[
        "\u6838\u6843\u5be8"
    ],
    "wof:name":"Hetaozhai",
    "wof:placetype":"locality"
},
  "geometry": {"coordinates":[103.94199999999999,23.9365],"type":"Point"}
}