{
  "type": "Feature",
  "properties": {
    "gn:admin1_code":"2.0",
    "gn:asciiname":"Caomen",
    "gn:country_code":"CN",
    "gn:dem":306,
    "gn:feature_class":"P",
    "gn:feature_code":"PPL",
    "gn:name":"Caomen",
    "gn:population":0,
    "gn:timezone":"Asia/Shanghai",
    "iso:country":"CN",
    "name:zho_x_preferred":[
        "\u66f9\u95e8"
    ],
    "wof:name":"Caomen",
    "wof:placetype":"locality"
},
  "geometry": {"coordinates":[118.31673000000001,29.20088],"type":"Point"}
}