{
  "type": "Feature",
  "properties": {
    "gn:admin1_code":"29",
    "gn:asciiname":"Shanggongjiaying",
    "gn:country_code":"CN",
    "gn:dem":1593,
    "gn:feature_class":"P",
    "gn:feature_code":"PPL",
    "gn:name":"Shanggongjiaying",
    "gn:population":0,
    "gn:timezone":"Asia/Shanghai",
    "iso:country":"CN",
    "name:zho_x_preferred":[
        "\u4e0a\u9f9a\u5bb6\u8425"
    ],
    "wof:name":"Shanggongjiaying",
    "wof:placetype":"locality"
},
  "geometry": {"coordinates":[102.20188,24.70703],"type":"Point"}
}