{
  "type": "Feature",
  "properties": {
    "gn:admin1_code":"19.0",
    "gn:asciiname":"Houyingzicun",
    "gn:country_code":"CN",
    "gn:dem":38,
    "gn:feature_class":"P",
    "gn:feature_code":"PPL",
    "gn:name":"Houyingzicun",
    "gn:population":0,
    "gn:timezone":"Asia/Shanghai",
    "iso:country":"CN",
    "name:zho_x_preferred":[
        "\u540e\u8425\u5b50\u6751"
    ],
    "wof:name":"Houyingzicun",
    "wof:placetype":"locality"
},
  "geometry": {"coordinates":[122.786,42.0316],"type":"Point"}
}