{
  "type": "Feature",
  "properties": {
    "gn:admin1_code":"5.0",
    "gn:asciiname":"Kaohecun",
    "gn:country_code":"CN",
    "gn:dem":182,
    "gn:feature_class":"P",
    "gn:feature_code":"PPL",
    "gn:name":"Kaohecun",
    "gn:population":0,
    "gn:timezone":"Asia/Shanghai",
    "iso:country":"CN",
    "name:zho_x_preferred":[
        "\u9760\u6cb3\u6751"
    ],
    "wof:name":"Kaohecun",
    "wof:placetype":"locality"
},
  "geometry": {"coordinates":[126.62092,44.59515],"type":"Point"}
}