{
  "type": "Feature",
  "properties": {
    "gn:admin1_code":"29.0",
    "gn:asciiname":"Dakamo",
    "gn:country_code":"CN",
    "gn:dem":2284,
    "gn:feature_class":"P",
    "gn:feature_code":"PPL",
    "gn:name":"Dakamo",
    "gn:population":0,
    "gn:timezone":"Asia/Shanghai",
    "iso:country":"CN",
    "name:zho_x_preferred":[
        "\u5927\u5361\u83ab"
    ],
    "wof:name":"Dakamo",
    "wof:placetype":"locality"
},
  "geometry": {"coordinates":[101.971,25.9125],"type":"Point"}
}