{
  "type": "Feature",
  "properties": {
    "gn:admin1_code":"26.0",
    "gn:asciiname":"Tuojiachuancun",
    "gn:country_code":"CN",
    "gn:dem":909,
    "gn:feature_class":"P",
    "gn:feature_code":"PPL",
    "gn:name":"Tuojiachuancun",
    "gn:population":0,
    "gn:timezone":"Asia/Shanghai",
    "iso:country":"CN",
    "name:zho_x_preferred":[
        "\u62d3\u5bb6\u5ddd\u6751"
    ],
    "wof:name":"Tuojiachuancun",
    "wof:placetype":"locality"
},
  "geometry": {"coordinates":[110.12832,36.72941],"type":"Point"}
}