{
  "type": "Feature",
  "properties": {
    "gn:admin1_code":"9.0",
    "gn:asciiname":"Jiaolou",
    "gn:country_code":"CN",
    "gn:dem":169,
    "gn:feature_class":"P",
    "gn:feature_code":"PPL",
    "gn:name":"Jiaolou",
    "gn:population":0,
    "gn:timezone":"Asia/Shanghai",
    "iso:country":"CN",
    "name:und_x_variant":[
        "\u7126\u697c",
        "Jiaolou"
    ],
    "wof:name":"Jiaolou",
    "wof:placetype":"locality"
},
  "geometry": {"coordinates":[112.97574,33.9757],"type":"Point"}
}