{
  "type": "Feature",
  "properties": {
    "gn:admin1_code":"16.0",
    "gn:asciiname":"Zuotang",
    "gn:country_code":"CN",
    "gn:dem":218,
    "gn:feature_class":"P",
    "gn:feature_code":"PPL",
    "gn:name":"Zuotang",
    "gn:population":0,
    "gn:timezone":"Asia/Shanghai",
    "iso:country":"CN",
    "name:zho_x_preferred":[
        "\u5ea7\u5858"
    ],
    "wof:name":"Zuotang",
    "wof:placetype":"locality"
},
  "geometry": {"coordinates":[110.761,22.82800000000001],"type":"Point"}
}