{
  "type": "Feature",
  "properties": {
    "gn:admin1_code":"18",
    "gn:asciiname":"Honghuayuan",
    "gn:country_code":"CN",
    "gn:dem":900,
    "gn:feature_class":"P",
    "gn:feature_code":"PPL",
    "gn:name":"Honghuayuan",
    "gn:population":0,
    "gn:timezone":"Asia/Shanghai",
    "iso:country":"CN",
    "name:zho_x_preferred":[
        "\u7ea2\u82b1\u56ed"
    ],
    "wof:name":"Honghuayuan",
    "wof:placetype":"locality"
},
  "geometry": {"coordinates":[107.429,29.0463],"type":"Point"}
}