{
  "type": "Feature",
  "properties": {
    "gn:admin1_code":"6.0",
    "gn:asciiname":"Zhaomuchuan",
    "gn:country_code":"CN",
    "gn:dem":1814,
    "gn:feature_class":"P",
    "gn:feature_code":"PPL",
    "gn:name":"Zhaomuchuan",
    "gn:population":0,
    "gn:timezone":"Asia/Shanghai",
    "iso:country":"CN",
    "name:und_x_variant":[
        "\u8d75\u6728\u5ddd"
    ],
    "wof:name":"Zhaomuchuan",
    "wof:placetype":"locality"
},
  "geometry": {"coordinates":[102.73748000000001,35.83603],"type":"Point"}
}