{
  "type": "Feature",
  "properties": {
    "gn:admin1_code":"29.0",
    "gn:asciiname":"Caiyun",
    "gn:country_code":"CN",
    "gn:dem":1385,
    "gn:feature_class":"P",
    "gn:feature_code":"PPL",
    "gn:name":"Caiyun",
    "gn:population":0,
    "gn:timezone":"Asia/Shanghai",
    "iso:country":"CN",
    "name:zho_x_preferred":[
        "\u5f69\u4e91"
    ],
    "wof:name":"Caiyun",
    "wof:placetype":"locality"
},
  "geometry": {"coordinates":[101.89100000000001,24.9878],"type":"Point"}
}