{
  "type": "Feature",
  "properties": {
    "gn:admin1_code":"18",
    "gn:asciiname":"Changlingzi",
    "gn:country_code":"CN",
    "gn:dem":1333,
    "gn:feature_class":"P",
    "gn:feature_code":"PPL",
    "gn:name":"Changlingzi",
    "gn:population":0,
    "gn:timezone":"Asia/Shanghai",
    "iso:country":"CN",
    "name:zho_x_preferred":[
        "\u957f\u5cad\u5b50"
    ],
    "wof:name":"Changlingzi",
    "wof:placetype":"locality"
},
  "geometry": {"coordinates":[105.03400000000001,25.7413],"type":"Point"}
}