{
  "type": "Feature",
  "properties": {
    "gn:admin1_code":"30",
    "gn:asciiname":"Sanpinzhai",
    "gn:country_code":"CN",
    "gn:dem":98,
    "gn:feature_class":"P",
    "gn:feature_code":"PPL",
    "gn:name":"Sanpinzhai",
    "gn:population":0,
    "gn:timezone":"Asia/Urumqi",
    "iso:country":"CN",
    "name:zho_x_preferred":[
        "San-p\u2019in-chai"
    ],
    "name:zho_x_variant":[
        "\u4e09\u54c1\u658b"
    ],
    "wof:name":"Sanpinzhai",
    "wof:placetype":"locality"
},
  "geometry": {"coordinates":[110.09255,20.51063],"type":"Point"}
}