{
  "type": "Feature",
  "properties": {
    "gn:admin1_code":"7",
    "gn:asciiname":"Shangmiaoyang",
    "gn:country_code":"CN",
    "gn:dem":963,
    "gn:feature_class":"P",
    "gn:feature_code":"PPL",
    "gn:name":"Shangmiaoyang",
    "gn:population":0,
    "gn:timezone":"Asia/Shanghai",
    "iso:country":"CN",
    "name:und_x_variant":[
        "\u4e0a\u6e3a\u6d0b",
        "Shangmiaoyang"
    ],
    "wof:name":"Shangmiaoyang",
    "wof:placetype":"locality"
},
  "geometry": {"coordinates":[119.35933,27.50168],"type":"Point"}
}