{
  "type": "Feature",
  "properties": {
    "gn:admin1_code":"4.0",
    "gn:asciiname":"Binjiangcun",
    "gn:country_code":"CN",
    "gn:dem":5,
    "gn:feature_class":"P",
    "gn:feature_code":"PPL",
    "gn:name":"Binjiangcun",
    "gn:population":0,
    "gn:timezone":"Asia/Shanghai",
    "iso:country":"CN",
    "name:zho_x_preferred":[
        "\u6ee8\u6c5f\u6751"
    ],
    "wof:name":"Binjiangcun",
    "wof:placetype":"locality"
},
  "geometry": {"coordinates":[118.87002,32.24173],"type":"Point"}
}