{
  "type": "Feature",
  "properties": {
    "gn:admin1_code":"29.0",
    "gn:asciiname":"Luku",
    "gn:country_code":"CN",
    "gn:dem":1543,
    "gn:feature_class":"P",
    "gn:feature_code":"PPL",
    "gn:name":"Luku",
    "gn:population":0,
    "gn:timezone":"Asia/Shanghai",
    "iso:country":"CN",
    "name:zho_x_preferred":[
        "\u565c\u67af"
    ],
    "wof:name":"Luku",
    "wof:placetype":"locality"
},
  "geometry": {"coordinates":[104.149,27.5922],"type":"Point"}
}