{
  "type": "Feature",
  "properties": {
    "gn:admin1_code":"02",
    "gn:asciiname":"Zhujia",
    "gn:country_code":"CN",
    "gn:dem":19,
    "gn:feature_class":"P",
    "gn:feature_code":"PPL",
    "gn:name":"Zhujia",
    "gn:population":0,
    "gn:timezone":"Asia/Shanghai",
    "iso:country":"CN",
    "name:und_x_variant":[
        "\u7afa\u5bb6"
    ],
    "name:zho_x_preferred":[
        "\u7afa\u5bb6"
    ],
    "wof:name":"Zhujia",
    "wof:placetype":"locality"
},
  "geometry": {"coordinates":[121.4175,29.47778],"type":"Point"}
}