{
  "type": "Feature",
  "properties": {
    "gn:admin1_code":"28.0",
    "gn:asciiname":"Xinhe",
    "gn:country_code":"CN",
    "gn:dem":3,
    "gn:feature_class":"P",
    "gn:feature_code":"PPLA4",
    "gn:name":"Xinhe",
    "gn:population":0,
    "gn:timezone":"Asia/Shanghai",
    "iso:country":"CN",
    "name:ceb_x_preferred":[
        "Xinhe"
    ],
    "name:deu_x_preferred":[
        "Xinhe"
    ],
    "name:fra_x_preferred":[
        "Xinhe"
    ],
    "name:kor_x_preferred":[
        "\uc2e0\ud5c8\ud604"
    ],
    "name:und_x_variant":[
        "Hsin-ho",
        "Sinho",
        "Xinhe Jiedao"
    ],
    "name:zho_x_preferred":[
        "\u65b0\u6cb3"
    ],
    "name:zho_x_variant":[
        "\u65b0\u6cb3\u8857\u9053"
    ],
    "wof:name":"Xinhe",
    "wof:placetype":"locality"
},
  "geometry": {"coordinates":[117.62139000000001,39.03972],"type":"Point"}
}