{
  "type": "Feature",
  "properties": {
    "gn:admin1_code":"29",
    "gn:asciiname":"Ba'an",
    "gn:country_code":"CN",
    "gn:dem":1549,
    "gn:feature_class":"P",
    "gn:feature_code":"PPL",
    "gn:name":"Ba\u2019an",
    "gn:population":0,
    "gn:timezone":"Asia/Shanghai",
    "iso:country":"CN",
    "name:und_x_variant":[
        "Ba\u2019an"
    ],
    "name:zho_x_preferred":[
        "\u5c9c\u5b89"
    ],
    "wof:name":"Ba'an",
    "wof:placetype":"locality"
},
  "geometry": {"coordinates":[104.81100000000001,24.2253],"type":"Point"}
}