{
  "type": "Feature",
  "properties": {
    "gn:admin1_code":"24.0",
    "gn:asciiname":"Gezhai",
    "gn:country_code":"CN",
    "gn:dem":787,
    "gn:feature_class":"P",
    "gn:feature_code":"PPL",
    "gn:name":"Gezhai",
    "gn:population":0,
    "gn:timezone":"Asia/Shanghai",
    "iso:country":"CN",
    "name:und_x_variant":[
        "\u845b\u5be8"
    ],
    "name:zho_x_preferred":[
        "\u845b\u5be8"
    ],
    "wof:name":"Gezhai",
    "wof:placetype":"locality"
},
  "geometry": {"coordinates":[111.43603,35.33862],"type":"Point"}
}