{
  "type": "Feature",
  "properties": {
    "gn:admin1_code":"24",
    "gn:asciiname":"Nanbai",
    "gn:cc2":"CN",
    "gn:country_code":"CN",
    "gn:dem":811,
    "gn:feature_class":"P",
    "gn:feature_code":"PPL",
    "gn:name":"Nanbai",
    "gn:population":0,
    "gn:timezone":"Asia/Shanghai",
    "iso:country":"CN",
    "name:ara_x_preferred":[
        "\u0646\u0627\u0646\u0628\u0627\u064a"
    ],
    "name:und_x_variant":[
        "Shang-nan-pai-ts\u2019un",
        "Nan-pei-ts\u2019un",
        "Nan-pai",
        "Nan-pai-ts\u2019un",
        "Nanbai"
    ],
    "wof:name":"Nanbai",
    "wof:placetype":"locality"
},
  "geometry": {"coordinates":[112.98999999999999,38.63472],"type":"Point"}
}