{
  "type": "Feature",
  "properties": {
    "gn:admin1_code":"30.0",
    "gn:asciiname":"Qilingxia",
    "gn:country_code":"CN",
    "gn:dem":130,
    "gn:feature_class":"P",
    "gn:feature_code":"PPL",
    "gn:name":"Qilingxia",
    "gn:population":0,
    "gn:timezone":"Asia/Shanghai",
    "iso:country":"CN",
    "name:zho_x_preferred":[
        "\u65d7\u5cad\u4e0b"
    ],
    "wof:name":"Qilingxia",
    "wof:placetype":"locality"
},
  "geometry": {"coordinates":[115.33393999999998,23.1279],"type":"Point"}
}