{
  "type": "Feature",
  "properties": {
    "gn:admin1_code":"2.0",
    "gn:asciiname":"Wailuojia",
    "gn:country_code":"CN",
    "gn:dem":199,
    "gn:feature_class":"P",
    "gn:feature_code":"PPL",
    "gn:name":"Wailuojia",
    "gn:population":0,
    "gn:timezone":"Asia/Shanghai",
    "iso:country":"CN",
    "name:zho_x_preferred":[
        "\u5916\u7f57\u5bb6"
    ],
    "wof:name":"Wailuojia",
    "wof:placetype":"locality"
},
  "geometry": {"coordinates":[119.90582000000001,29.61795],"type":"Point"}
}