{
  "type": "Feature",
  "properties": {
    "gn:admin1_code":"3.0",
    "gn:asciiname":"Baishu",
    "gn:country_code":"CN",
    "gn:dem":72,
    "gn:feature_class":"P",
    "gn:feature_code":"PPL",
    "gn:name":"Baishu",
    "gn:population":0,
    "gn:timezone":"Asia/Shanghai",
    "iso:country":"CN",
    "name:und_x_variant":[
        "\u67cf\u6811"
    ],
    "wof:name":"Baishu",
    "wof:placetype":"locality"
},
  "geometry": {"coordinates":[115.05901,28.36491],"type":"Point"}
}