{
  "type": "Feature",
  "properties": {
    "gn:admin1_code":"2.0",
    "gn:asciiname":"Jiupao",
    "gn:country_code":"CN",
    "gn:dem":616,
    "gn:feature_class":"P",
    "gn:feature_code":"PPL",
    "gn:name":"Jiupao",
    "gn:population":0,
    "gn:timezone":"Asia/Shanghai",
    "iso:country":"CN",
    "name:zho_x_preferred":[
        "\u4e5d\u70ae"
    ],
    "wof:name":"Jiupao",
    "wof:placetype":"locality"
},
  "geometry": {"coordinates":[119.89525999999999,28.52151],"type":"Point"}
}