{
  "type": "Feature",
  "properties": {
    "gn:admin1_code":"3.0",
    "gn:asciiname":"Qianshan",
    "gn:country_code":"CN",
    "gn:dem":112,
    "gn:feature_class":"P",
    "gn:feature_code":"PPL",
    "gn:name":"Qianshan",
    "gn:population":0,
    "gn:timezone":"Asia/Shanghai",
    "iso:country":"CN",
    "name:ceb_x_preferred":[
        "Qianshan"
    ],
    "name:deu_x_preferred":[
        "Qianshan"
    ],
    "name:fra_x_preferred":[
        "Qianshan"
    ],
    "name:nor_x_preferred":[
        "Qianshan"
    ],
    "name:rus_x_preferred":[
        "\u0426\u044f\u043d\u044c\u0448\u0430\u043d\u044c"
    ],
    "name:swe_x_preferred":[
        "Qianshan"
    ],
    "name:zho_x_preferred":[
        "\u524d\u5c71"
    ],
    "wof:name":"Qianshan",
    "wof:placetype":"locality"
},
  "geometry": {"coordinates":[117.92464,28.48994],"type":"Point"}
}