{
  "type": "Feature",
  "properties": {
    "gn:admin1_code":"24.0",
    "gn:asciiname":"Zhiyucun",
    "gn:country_code":"CN",
    "gn:dem":1040,
    "gn:feature_class":"P",
    "gn:feature_code":"PPL",
    "gn:name":"Zhiyucun",
    "gn:population":0,
    "gn:timezone":"Asia/Shanghai",
    "iso:country":"CN",
    "name:und_x_variant":[
        "Chih-y\u00fc",
        "Zhiyu",
        "Zhiyucun"
    ],
    "name:zho_x_preferred":[
        "\u76f4\u5cea\u6751"
    ],
    "wof:name":"Zhiyucun",
    "wof:placetype":"locality"
},
  "geometry": {"coordinates":[114.23556000000001,39.7045],"type":"Point"}
}