{
  "type": "Feature",
  "properties": {
    "gn:admin1_code":"02",
    "gn:asciiname":"Madarencun",
    "gn:country_code":"CN",
    "gn:dem":61,
    "gn:feature_class":"P",
    "gn:feature_code":"PPL",
    "gn:name":"Madarencun",
    "gn:population":0,
    "gn:timezone":"Asia/Shanghai",
    "iso:country":"CN",
    "name:und_x_variant":[
        "Ma-ta-jen",
        "Madaren",
        "Madarencun"
    ],
    "name:zho_x_preferred":[
        "\u9a6c\u5927\u4ec1\u6751"
    ],
    "wof:name":"Madarencun",
    "wof:placetype":"locality"
},
  "geometry": {"coordinates":[120.8242,28.78602],"type":"Point"}
}