{
  "type": "Feature",
  "properties": {
    "gn:admin1_code":"02",
    "gn:asciiname":"Xinlincun",
    "gn:country_code":"CN",
    "gn:dem":7,
    "gn:feature_class":"P",
    "gn:feature_code":"PPL",
    "gn:name":"Xinlincun",
    "gn:population":0,
    "gn:timezone":"Asia/Shanghai",
    "iso:country":"CN",
    "name:und_x_variant":[
        "Lin-hsia-fan",
        "Xinlin",
        "Xinlincun"
    ],
    "name:zho_x_preferred":[
        "\u65b0\u6797"
    ],
    "name:zho_x_variant":[
        "\u65b0\u6797\u6751"
    ],
    "wof:name":"Xinlincun",
    "wof:placetype":"locality"
},
  "geometry": {"coordinates":[121.52991000000002,29.81488],"type":"Point"}
}