{
  "type": "Feature",
  "properties": {
    "gn:admin1_code":"12.0",
    "gn:asciiname":"Gaojia Shangwan",
    "gn:country_code":"CN",
    "gn:dem":70,
    "gn:feature_class":"P",
    "gn:feature_code":"PPL",
    "gn:name":"Gaojia Shangwan",
    "gn:population":0,
    "gn:timezone":"Asia/Shanghai",
    "iso:country":"CN",
    "name:und_x_variant":[
        "\u9ad8\u5bb6\u4e0a\u5846"
    ],
    "wof:name":"Gaojia Shangwan",
    "wof:placetype":"locality"
},
  "geometry": {"coordinates":[115.21359,30.65049],"type":"Point"}
}