{
  "type": "Feature",
  "properties": {
    "gn:admin1_code":"3.0",
    "gn:asciiname":"Datangyuan",
    "gn:country_code":"CN",
    "gn:dem":200,
    "gn:feature_class":"P",
    "gn:feature_code":"PPL",
    "gn:name":"Datangyuan",
    "gn:population":0,
    "gn:timezone":"Asia/Shanghai",
    "iso:country":"CN",
    "name:und_x_variant":[
        "\u5927\u5858\u6e90"
    ],
    "wof:name":"Datangyuan",
    "wof:placetype":"locality"
},
  "geometry": {"coordinates":[114.14026,27.92588],"type":"Point"}
}