{
  "type": "Feature",
  "properties": {
    "gn:admin1_code":"24",
    "gn:asciiname":"Tuban",
    "gn:cc2":"CN",
    "gn:country_code":"CN",
    "gn:dem":1030,
    "gn:feature_class":"P",
    "gn:feature_code":"PPL",
    "gn:name":"Tuban",
    "gn:population":0,
    "gn:timezone":"Asia/Shanghai",
    "iso:country":"CN",
    "name:ara_x_preferred":[
        "\u062a\u0648\u0628\u0627\u0646"
    ],
    "name:ben_x_preferred":[
        "\u09a4\u09c1\u09ac\u09be\u09a8"
    ],
    "name:bis_x_preferred":[
        "Tuban"
    ],
    "name:ceb_x_preferred":[
        "Tuban"
    ],
    "name:deu_x_preferred":[
        "Tuban"
    ],
    "name:ell_x_preferred":[
        "\u03a4\u03bf\u03c5\u03bc\u03c0\u03ac\u03bd"
    ],
    "name:fas_x_preferred":[
        "\u062a\u0648\u0628\u0627\u0646"
    ],
    "name:fra_x_preferred":[
        "Tuban"
    ],
    "name:heb_x_preferred":[
        "\u05d8\u05d5\u05d1\u05d0\u05df"
    ],
    "name:hin_x_preferred":[
        "\u091f\u094d\u092f\u0942\u092c\u0928"
    ],
    "name:hun_x_preferred":[
        "Tuban"
    ],
    "name:ind_x_preferred":[
        "Tuban"
    ],
    "name:ita_x_preferred":[
        "Tuban"
    ],
    "name:jav_x_preferred":[
        "Tuban"
    ],
    "name:kor_x_preferred":[
        "\ud22c\ubc18"
    ],
    "name:mlg_x_preferred":[
        "Tuban"
    ],
    "name:pol_x_preferred":[
        "Tuban"
    ],
    "name:por_x_preferred":[
        "Tuban"
    ],
    "name:rus_x_preferred":[
        "\u0422\u0443\u0431\u0430\u043d"
    ],
    "name:swe_x_preferred":[
        "Tuban"
    ],
    "name:tur_x_preferred":[
        "Tuban"
    ],
    "name:ukr_x_preferred":[
        "\u0422\u0443\u0431\u0430\u043d"
    ],
    "name:und_x_variant":[
        "Tiu-tan-chen",
        "T\u2019u-fan",
        "T\u2019u-fan-chen"
    ],
    "name:urd_x_preferred":[
        "\u062a\u0648\u0628\u0627\u0646"
    ],
    "name:vie_x_preferred":[
        "Tuban"
    ],
    "wof:name":"Tuban",
    "wof:placetype":"locality"
},
  "geometry": {"coordinates":[110.66667,38.05],"type":"Point"}
}