{
  "type": "Feature",
  "properties": {
    "gn:admin1_code":"24",
    "gn:asciiname":"Ehutan",
    "gn:cc2":"CN",
    "gn:country_code":"CN",
    "gn:dem":1228,
    "gn:feature_class":"P",
    "gn:feature_code":"PPL",
    "gn:name":"Ehutan",
    "gn:population":0,
    "gn:timezone":"Asia/Shanghai",
    "iso:country":"CN",
    "name:und_x_variant":[
        "O-hu-t\u2019an",
        "Ehutan"
    ],
    "wof:name":"Ehutan",
    "wof:placetype":"locality"
},
  "geometry": {"coordinates":[111.31194000000001,38.51972],"type":"Point"}
}