{
  "type": "Feature",
  "properties": {
    "gn:admin1_code":"18",
    "gn:asciiname":"Meitankong",
    "gn:country_code":"CN",
    "gn:dem":1194,
    "gn:feature_class":"P",
    "gn:feature_code":"PPL",
    "gn:name":"Meitankong",
    "gn:population":0,
    "gn:timezone":"Asia/Shanghai",
    "iso:country":"CN",
    "name:zho_x_preferred":[
        "\u7164\u70ad\u5b54"
    ],
    "wof:name":"Meitankong",
    "wof:placetype":"locality"
},
  "geometry": {"coordinates":[106.062,27.631],"type":"Point"}
}