{
  "type": "Feature",
  "properties": {
    "gn:admin1_code":"4.0",
    "gn:asciiname":"Danwan",
    "gn:country_code":"CN",
    "gn:dem":25,
    "gn:feature_class":"P",
    "gn:feature_code":"PPL",
    "gn:name":"Danwan",
    "gn:population":0,
    "gn:timezone":"Asia/Shanghai",
    "iso:country":"CN",
    "name:zho_x_preferred":[
        "\u5355\u6e7e"
    ],
    "wof:name":"Danwan",
    "wof:placetype":"locality"
},
  "geometry": {"coordinates":[118.00751,33.91968],"type":"Point"}
}