{
  "type": "Feature",
  "properties": {
    "gn:admin1_code":"24.0",
    "gn:asciiname":"Shanghuizi",
    "gn:country_code":"CN",
    "gn:dem":1443,
    "gn:feature_class":"P",
    "gn:feature_code":"PPL",
    "gn:name":"Shanghuizi",
    "gn:population":0,
    "gn:timezone":"Asia/Shanghai",
    "iso:country":"CN",
    "name:zho_x_preferred":[
        "\u4e0a\u4f1a\u5b50"
    ],
    "wof:name":"Shanghuizi",
    "wof:placetype":"locality"
},
  "geometry": {"coordinates":[111.65682,39.11339],"type":"Point"}
}