{
  "type": "Feature",
  "properties": {
    "gn:admin1_code":"10",
    "gn:asciiname":"Panjia Gouli",
    "gn:country_code":"CN",
    "gn:dem":815,
    "gn:feature_class":"P",
    "gn:feature_code":"PPL",
    "gn:name":"Panjia Gouli",
    "gn:population":0,
    "gn:timezone":"Asia/Shanghai",
    "iso:country":"CN",
    "name:zho_x_preferred":[
        "\u6f58\u5bb6\u6c9f\u91cc"
    ],
    "wof:name":"Panjia Gouli",
    "wof:placetype":"locality"
},
  "geometry": {"coordinates":[117.72143,40.79905],"type":"Point"}
}