{
  "type": "Feature",
  "properties": {
    "gn:admin1_code":"07",
    "gn:asciiname":"Qingwan",
    "gn:country_code":"CN",
    "gn:dem":53,
    "gn:feature_class":"P",
    "gn:feature_code":"PPL",
    "gn:name":"Qingwan",
    "gn:population":0,
    "gn:timezone":"Asia/Shanghai",
    "iso:country":"CN",
    "name:zho_x_preferred":[
        "\u9752\u6e7e"
    ],
    "wof:name":"Qingwan",
    "wof:placetype":"locality"
},
  "geometry": {"coordinates":[120.25147,27.04714],"type":"Point"}
}