{
  "type": "Feature",
  "properties": {
    "gn:admin1_code":"29.0",
    "gn:asciiname":"Mibenghe Laozhai",
    "gn:country_code":"CN",
    "gn:dem":1512,
    "gn:feature_class":"P",
    "gn:feature_code":"PPL",
    "gn:name":"Mibenghe Laozhai",
    "gn:population":0,
    "gn:timezone":"Asia/Shanghai",
    "iso:country":"CN",
    "name:zho_x_preferred":[
        "\u5bc6\u868c\u6cb3\u8001\u5be8"
    ],
    "wof:name":"Mibenghe Laozhai",
    "wof:placetype":"locality"
},
  "geometry": {"coordinates":[100.19799999999999,22.1239],"type":"Point"}
}