{
  "type": "Feature",
  "properties": {
    "gn:admin1_code":"32.0",
    "gn:asciiname":"Toulong",
    "gn:country_code":"CN",
    "gn:dem":369,
    "gn:feature_class":"P",
    "gn:feature_code":"PPL",
    "gn:name":"Toulong",
    "gn:population":0,
    "gn:timezone":"Asia/Shanghai",
    "iso:country":"CN",
    "name:zho_x_preferred":[
        "\u900f\u9f99"
    ],
    "wof:name":"Toulong",
    "wof:placetype":"locality"
},
  "geometry": {"coordinates":[106.559,31.2153],"type":"Point"}
}