{
  "type": "Feature",
  "properties": {
    "gn:admin1_code":"3.0",
    "gn:asciiname":"Xiachakeng",
    "gn:country_code":"CN",
    "gn:dem":111,
    "gn:feature_class":"P",
    "gn:feature_code":"PPL",
    "gn:name":"Xiachakeng",
    "gn:population":0,
    "gn:timezone":"Asia/Shanghai",
    "iso:country":"CN",
    "name:und_x_variant":[
        "\u4e0b\u8336\u5751"
    ],
    "wof:name":"Xiachakeng",
    "wof:placetype":"locality"
},
  "geometry": {"coordinates":[115.93586999999999,27.82629],"type":"Point"}
}