{
  "type": "Feature",
  "properties": {
    "gn:admin1_code":"11",
    "gn:asciiname":"Quanjiaohe",
    "gn:cc2":"CN",
    "gn:country_code":"CN",
    "gn:dem":33,
    "gn:feature_class":"P",
    "gn:feature_code":"PPL",
    "gn:name":"Quanjiaohe",
    "gn:population":0,
    "gn:timezone":"Asia/Shanghai",
    "iso:country":"CN",
    "name:und_x_variant":[
        "Ch\u2019\u00fcan-chiao-ho",
        "Quanjiaohe"
    ],
    "wof:name":"Quanjiaohe",
    "wof:placetype":"locality"
},
  "geometry": {"coordinates":[112.51888999999998,28.48278],"type":"Point"}
}