{
  "type": "Feature",
  "properties": {
    "gn:admin1_code":"33.0",
    "gn:asciiname":"Yeyan",
    "gn:country_code":"CN",
    "gn:dem":462,
    "gn:feature_class":"P",
    "gn:feature_code":"PPL",
    "gn:name":"Yeyan",
    "gn:population":0,
    "gn:timezone":"Asia/Shanghai",
    "iso:country":"CN",
    "name:zho_x_preferred":[
        "\u53f6\u5ca9"
    ],
    "wof:name":"Yeyan",
    "wof:placetype":"locality"
},
  "geometry": {"coordinates":[107.49299999999999,30.74149],"type":"Point"}
}