{
  "type": "Feature",
  "properties": {
    "gn:admin1_code":"26",
    "gn:asciiname":"Diaotai",
    "gn:country_code":"CN",
    "gn:dem":392,
    "gn:feature_class":"P",
    "gn:feature_code":"PPLA4",
    "gn:name":"Diaotai",
    "gn:population":0,
    "gn:timezone":"Asia/Shanghai",
    "iso:country":"CN",
    "name:und_x_variant":[
        "Diaotaizhen",
        "Diaotai"
    ],
    "name:zho_x_preferred":[
        "\u6c48\u53f0"
    ],
    "name:zho_x_variant":[
        "\u6c48\u53f0\u9547"
    ],
    "wof:name":"Diaotai",
    "wof:placetype":"locality"
},
  "geometry": {"coordinates":[108.68639,34.28556],"type":"Point"}
}