{
  "type": "Feature",
  "properties": {
    "gn:admin1_code":"7.0",
    "gn:asciiname":"Hefu",
    "gn:country_code":"CN",
    "gn:dem":386,
    "gn:feature_class":"P",
    "gn:feature_code":"PPL",
    "gn:name":"Hefu",
    "gn:population":0,
    "gn:timezone":"Asia/Shanghai",
    "iso:country":"CN",
    "name:und_x_variant":[
        "\u6cb3\u752b"
    ],
    "name:zho_x_preferred":[
        "\u6cb3\u752b"
    ],
    "wof:name":"Hefu",
    "wof:placetype":"locality"
},
  "geometry": {"coordinates":[116.47487,25.48772],"type":"Point"}
}