{
  "type": "Feature",
  "properties": {
    "gn:admin1_code":"14.0",
    "gn:asciiname":"Bamulong",
    "gn:country_code":"CN",
    "gn:dem":4398,
    "gn:feature_class":"P",
    "gn:feature_code":"PPL",
    "gn:name":"Bamulong",
    "gn:population":0,
    "gn:timezone":"Asia/Urumqi",
    "iso:country":"CN",
    "name:zho_x_preferred":[
        "\u7f62\u6728\u9f99"
    ],
    "wof:name":"Bamulong",
    "wof:placetype":"locality"
},
  "geometry": {"coordinates":[98.59379,29.34864],"type":"Point"}
}