{
  "type": "Feature",
  "properties": {
    "gn:admin1_code":"11.0",
    "gn:asciiname":"Xinyanwan",
    "gn:country_code":"CN",
    "gn:dem":116,
    "gn:feature_class":"P",
    "gn:feature_code":"PPL",
    "gn:name":"Xinyanwan",
    "gn:population":0,
    "gn:timezone":"Asia/Shanghai",
    "iso:country":"CN",
    "name:zho_x_preferred":[
        "Xinyanwan"
    ],
    "name:zho_x_variant":[
        "\u65b0\u5830\u6e7e"
    ],
    "wof:name":"Xinyanwan",
    "wof:placetype":"locality"
},
  "geometry": {"coordinates":[111.31196,29.03964],"type":"Point"}
}