{
  "type": "Feature",
  "properties": {
    "gn:admin1_code":"03",
    "gn:asciiname":"Quangang",
    "gn:country_code":"CN",
    "gn:dem":33,
    "gn:feature_class":"P",
    "gn:feature_code":"PPLA4",
    "gn:name":"Quangang",
    "gn:population":0,
    "gn:timezone":"Asia/Shanghai",
    "iso:country":"CN",
    "name:und_x_variant":[
        "Ch\u2019\u00fcan-chiang-chieh",
        "Ch\u2019\u00fcan-chiang",
        "Quangang",
        "\u6cc9\u6e2f",
        "Quangang Zhen",
        "\u6cc9\u6e2f\u9547"
    ],
    "wof:name":"Quangang",
    "wof:placetype":"locality"
},
  "geometry": {"coordinates":[115.59658,28.15594],"type":"Point"}
}