{
  "type": "Feature",
  "properties": {
    "gn:admin1_code":"32.0",
    "gn:asciiname":"Xiaohongqiao",
    "gn:country_code":"CN",
    "gn:dem":318,
    "gn:feature_class":"P",
    "gn:feature_code":"PPL",
    "gn:name":"Xiaohongqiao",
    "gn:population":0,
    "gn:timezone":"Asia/Shanghai",
    "iso:country":"CN",
    "name:zho_x_preferred":[
        "\u5c0f\u7ea2\u6865"
    ],
    "wof:name":"Xiaohongqiao",
    "wof:placetype":"locality"
},
  "geometry": {"coordinates":[104.96836,28.37964],"type":"Point"}
}