{
  "type": "Feature",
  "properties": {
    "gn:admin1_code":"1.0",
    "gn:asciiname":"Zhakoucun",
    "gn:country_code":"CN",
    "gn:dem":20,
    "gn:feature_class":"P",
    "gn:feature_code":"PPL",
    "gn:name":"Zhakoucun",
    "gn:population":0,
    "gn:timezone":"Asia/Shanghai",
    "iso:country":"CN",
    "name:zho_x_preferred":[
        "\u95f8\u53e3\u6751"
    ],
    "wof:name":"Zhakoucun",
    "wof:placetype":"locality"
},
  "geometry": {"coordinates":[117.08216000000002,32.71249],"type":"Point"}
}