{
  "type": "Feature",
  "properties": {
    "gn:admin1_code":"16.0",
    "gn:asciiname":"Meibu",
    "gn:country_code":"CN",
    "gn:dem":67,
    "gn:feature_class":"P",
    "gn:feature_code":"PPL",
    "gn:name":"Meibu",
    "gn:population":0,
    "gn:timezone":"Asia/Shanghai",
    "iso:country":"CN",
    "name:zho_x_preferred":[
        "\u679a\u57e0"
    ],
    "wof:name":"Meibu",
    "wof:placetype":"locality"
},
  "geometry": {"coordinates":[109.18000000000001,22.4159],"type":"Point"}
}