{
  "type": "Feature",
  "properties": {
    "gn:admin1_code":"3",
    "gn:asciiname":"Heba Shezucun",
    "gn:country_code":"CN",
    "gn:dem":145,
    "gn:feature_class":"P",
    "gn:feature_code":"PPL",
    "gn:name":"Heba Shezucun",
    "gn:population":0,
    "gn:timezone":"Asia/Shanghai",
    "iso:country":"CN",
    "name:zho_x_preferred":[
        "\u6cb3\u575d\u7572\u65cf\u6751"
    ],
    "wof:name":"Heba Shezucun",
    "wof:placetype":"locality"
},
  "geometry": {"coordinates":[114.66011,25.63125],"type":"Point"}
}