{
  "type": "Feature",
  "properties": {
    "gn:admin1_code":"26",
    "gn:asciiname":"Xicheng",
    "gn:country_code":"CN",
    "gn:dem":518,
    "gn:feature_class":"P",
    "gn:feature_code":"PPL",
    "gn:name":"Xicheng",
    "gn:population":0,
    "gn:timezone":"Asia/Shanghai",
    "iso:country":"CN",
    "name:und_x_variant":[
        "Xichengcun",
        "Xicheng"
    ],
    "name:zho_x_preferred":[
        "\u897f\u57ce"
    ],
    "wof:name":"Xicheng",
    "wof:placetype":"locality"
},
  "geometry": {"coordinates":[108.58032,34.41267],"type":"Point"}
}