{
  "type": "Feature",
  "properties": {
    "gn:admin1_code":"16.0",
    "gn:asciiname":"Yubu",
    "gn:country_code":"CN",
    "gn:dem":77,
    "gn:feature_class":"P",
    "gn:feature_code":"PPL",
    "gn:name":"Yubu",
    "gn:population":0,
    "gn:timezone":"Asia/Shanghai",
    "iso:country":"CN",
    "name:kor_x_preferred":[
        "\uc6b0\ubcf4"
    ],
    "name:pol_x_preferred":[
        "Krok Yu"
    ],
    "name:zho_x_preferred":[
        "\u9c7c\u6b65"
    ],
    "wof:name":"Yubu",
    "wof:placetype":"locality"
},
  "geometry": {"coordinates":[109.551,23.8087],"type":"Point"}
}