{
  "type": "Feature",
  "properties": {
    "gn:admin1_code":"08",
    "gn:asciiname":"Fangtai",
    "gn:country_code":"CN",
    "gn:dem":145,
    "gn:feature_class":"P",
    "gn:feature_code":"PPLA4",
    "gn:name":"Fangtai",
    "gn:population":0,
    "gn:timezone":"Asia/Shanghai",
    "iso:country":"CN",
    "name:und_x_variant":[
        "Fangtai Zhen"
    ],
    "name:zho_x_preferred":[
        "\u65b9\u53f0"
    ],
    "name:zho_x_variant":[
        "\u65b9\u53f0\u9547"
    ],
    "wof:name":"Fangtai",
    "wof:placetype":"locality"
},
  "geometry": {"coordinates":[126.93331000000001,46.08917],"type":"Point"}
}