{
  "type": "Feature",
  "properties": {
    "gn:admin1_code":"8.0",
    "gn:asciiname":"Zhonghecun",
    "gn:country_code":"CN",
    "gn:dem":75,
    "gn:feature_class":"P",
    "gn:feature_code":"PPL",
    "gn:name":"Zhonghecun",
    "gn:population":0,
    "gn:timezone":"Asia/Shanghai",
    "iso:country":"CN",
    "name:zho_x_preferred":[
        "\u4e2d\u548c\u6751"
    ],
    "wof:name":"Zhonghecun",
    "wof:placetype":"locality"
},
  "geometry": {"coordinates":[130.63345000000001,47.00261],"type":"Point"}
}