{
  "type": "Feature",
  "properties": {
    "gn:admin1_code":"24.0",
    "gn:asciiname":"Gezhenshuyao",
    "gn:country_code":"CN",
    "gn:dem":930,
    "gn:feature_class":"P",
    "gn:feature_code":"PPL",
    "gn:name":"Gezhenshuyao",
    "gn:population":0,
    "gn:timezone":"Asia/Shanghai",
    "iso:country":"CN",
    "name:zho_x_preferred":[
        "\u572a\u9488\u6811\u8170"
    ],
    "wof:name":"Gezhenshuyao",
    "wof:placetype":"locality"
},
  "geometry": {"coordinates":[112.37779999999999,35.56374],"type":"Point"}
}