{
  "type": "Feature",
  "properties": {
    "gn:admin1_code":"15.0",
    "gn:asciiname":"Kelitai",
    "gn:country_code":"CN",
    "gn:dem":2185,
    "gn:feature_class":"P",
    "gn:feature_code":"PPL",
    "gn:name":"Kelitai",
    "gn:population":0,
    "gn:timezone":"Asia/Shanghai",
    "iso:country":"CN",
    "name:zho_x_preferred":[
        "\u7aa0\u7acb\u53f0"
    ],
    "wof:name":"Kelitai",
    "wof:placetype":"locality"
},
  "geometry": {"coordinates":[104.545,36.0715],"type":"Point"}
}