{
  "type": "Feature",
  "properties": {
    "gn:admin1_code":"32.0",
    "gn:asciiname":"Luogaoyida",
    "gn:country_code":"CN",
    "gn:dem":1975,
    "gn:feature_class":"P",
    "gn:feature_code":"PPL",
    "gn:name":"Luogaoyida",
    "gn:population":0,
    "gn:timezone":"Asia/Shanghai",
    "iso:country":"CN",
    "name:zho_x_preferred":[
        "\u6d1b\u9ad8\u4f9d\u6253"
    ],
    "wof:name":"Luogaoyida",
    "wof:placetype":"locality"
},
  "geometry": {"coordinates":[103.03429,28.302],"type":"Point"}
}