{
  "type": "Feature",
  "properties": {
    "gn:admin1_code":"13.0",
    "gn:asciiname":"La'are Guole",
    "gn:country_code":"CN",
    "gn:dem":1332,
    "gn:feature_class":"P",
    "gn:feature_code":"PPL",
    "gn:name":"La\u2019are Guole",
    "gn:population":0,
    "gn:timezone":"Asia/Shanghai",
    "iso:country":"CN",
    "name:und_x_variant":[
        "La\u2019are Guole"
    ],
    "name:zho_x_preferred":[
        "\u62c9\u963f\u70ed\u679c\u52d2"
    ],
    "wof:name":"La'are Guole",
    "wof:placetype":"locality"
},
  "geometry": {"coordinates":[79.86679000000002,37.1938],"type":"Point"}
}