{
  "type": "Feature",
  "properties": {
    "gn:admin1_code":"11.0",
    "gn:asciiname":"Huataoping",
    "gn:country_code":"CN",
    "gn:dem":727,
    "gn:feature_class":"P",
    "gn:feature_code":"PPL",
    "gn:name":"Huataoping",
    "gn:population":0,
    "gn:timezone":"Asia/Shanghai",
    "iso:country":"CN",
    "name:zho_x_preferred":[
        "\u5212\u6843\u576a"
    ],
    "wof:name":"Huataoping",
    "wof:placetype":"locality"
},
  "geometry": {"coordinates":[109.38539,27.27169],"type":"Point"}
}