{
  "type": "Feature",
  "properties": {
    "gn:admin1_code":"12",
    "gn:asciiname":"Shangdahe",
    "gn:country_code":"CN",
    "gn:dem":531,
    "gn:feature_class":"P",
    "gn:feature_code":"PPL",
    "gn:name":"Shangdahe",
    "gn:population":0,
    "gn:timezone":"Asia/Shanghai",
    "iso:country":"CN",
    "name:zho_x_preferred":[
        "\u4e0a\u8fbe\u6cb3"
    ],
    "wof:name":"Shangdahe",
    "wof:placetype":"locality"
},
  "geometry": {"coordinates":[110.53131,32.0315],"type":"Point"}
}