{
  "type": "Feature",
  "properties": {
    "gn:admin1_code":"30.0",
    "gn:asciiname":"Yingneicun",
    "gn:country_code":"CN",
    "gn:dem":5,
    "gn:feature_class":"P",
    "gn:feature_code":"PPL",
    "gn:name":"Yingneicun",
    "gn:population":0,
    "gn:timezone":"Asia/Shanghai",
    "iso:country":"CN",
    "name:zho_x_preferred":[
        "\u82f1\u5167\u6751"
    ],
    "wof:name":"Yingneicun",
    "wof:placetype":"locality"
},
  "geometry": {"coordinates":[116.29295,23.0377],"type":"Point"}
}