{
  "type": "Feature",
  "properties": {
    "gn:admin1_code":"8.0",
    "gn:asciiname":"Ping'an",
    "gn:country_code":"CN",
    "gn:dem":160,
    "gn:feature_class":"P",
    "gn:feature_code":"PPL",
    "gn:name":"Ping\u2019an",
    "gn:population":0,
    "gn:timezone":"Asia/Shanghai",
    "iso:country":"CN",
    "name:zho_x_preferred":[
        "Ping\u2019an"
    ],
    "name:zho_x_variant":[
        "\u5e73\u5b89"
    ],
    "wof:name":"Ping'an",
    "wof:placetype":"locality"
},
  "geometry": {"coordinates":[127.3582,45.81333],"type":"Point"}
}