{
  "type": "Feature",
  "properties": {
    "gn:admin1_code":"19.0",
    "gn:asciiname":"Shangdidashui",
    "gn:country_code":"CN",
    "gn:dem":551,
    "gn:feature_class":"P",
    "gn:feature_code":"PPL",
    "gn:name":"Shangdidashui",
    "gn:population":0,
    "gn:timezone":"Asia/Shanghai",
    "iso:country":"CN",
    "name:zho_x_preferred":[
        "\u4e0a\u6ef4\u55d2\u6c34"
    ],
    "wof:name":"Shangdidashui",
    "wof:placetype":"locality"
},
  "geometry": {"coordinates":[119.672,41.24388],"type":"Point"}
}