{
  "type": "Feature",
  "properties": {
    "gn:admin1_code":"14.0",
    "gn:asciiname":"Pengdengka",
    "gn:country_code":"CN",
    "gn:dem":3985,
    "gn:feature_class":"P",
    "gn:feature_code":"PPL",
    "gn:name":"Pengdengka",
    "gn:population":0,
    "gn:timezone":"Asia/Urumqi",
    "iso:country":"CN",
    "name:zho_x_preferred":[
        "\u670b\u767b\u5361"
    ],
    "wof:name":"Pengdengka",
    "wof:placetype":"locality"
},
  "geometry": {"coordinates":[94.67372,31.46917],"type":"Point"}
}