{
  "type": "Feature",
  "properties": {
    "gn:admin1_code":"26",
    "gn:asciiname":"Shipingqu",
    "gn:country_code":"CN",
    "gn:dem":1425,
    "gn:feature_class":"P",
    "gn:feature_code":"PPL",
    "gn:name":"Shipingqu",
    "gn:population":0,
    "gn:timezone":"Asia/Shanghai",
    "iso:country":"CN",
    "wof:name":"Shipingqu",
    "wof:placetype":"locality"
},
  "geometry": {"coordinates":[109.25943999999998,32.07833],"type":"Point"}
}