{
  "type": "Feature",
  "properties": {
    "gn:admin1_code":"10.0",
    "gn:asciiname":"Wucun",
    "gn:cc2":"CN",
    "gn:country_code":"CN",
    "gn:dem":46,
    "gn:feature_class":"P",
    "gn:feature_code":"PPL",
    "gn:name":"Wucun",
    "gn:population":0,
    "gn:timezone":"Asia/Shanghai",
    "iso:country":"CN",
    "name:und_x_variant":[
        "Utsun",
        "Wu-ts\u2019un-chen",
        "Wu-ts\u2019un-chan",
        "Wu-ts\u2019un",
        "Wucun"
    ],
    "wof:name":"Wucun",
    "wof:placetype":"locality"
},
  "geometry": {"coordinates":[115.17361,38.87472],"type":"Point"}
}