{
  "type": "Feature",
  "properties": {
    "gn:admin1_code":"10",
    "gn:asciiname":"Nanchenzhuang",
    "gn:country_code":"CN",
    "gn:dem":36,
    "gn:feature_class":"P",
    "gn:feature_code":"PPL",
    "gn:name":"Nanchenzhuang",
    "gn:population":0,
    "gn:timezone":"Asia/Shanghai",
    "iso:country":"CN",
    "name:zho_x_preferred":[
        "\u5357\u9648\u5e84"
    ],
    "wof:name":"Nanchenzhuang",
    "wof:placetype":"locality"
},
  "geometry": {"coordinates":[115.12826,36.93255],"type":"Point"}
}