{
  "type": "Feature",
  "properties": {
    "gn:admin1_code":"24.0",
    "gn:asciiname":"Gongyang",
    "gn:country_code":"CN",
    "gn:dem":1464,
    "gn:feature_class":"P",
    "gn:feature_code":"PPL",
    "gn:name":"Gongyang",
    "gn:population":0,
    "gn:timezone":"Asia/Shanghai",
    "iso:country":"CN",
    "name:zho_x_preferred":[
        "\u5f13\u9633"
    ],
    "wof:name":"Gongyang",
    "wof:placetype":"locality"
},
  "geometry": {"coordinates":[111.28794000000001,37.13494],"type":"Point"}
}