{
  "type": "Feature",
  "properties": {
    "gn:admin1_code":"32.0",
    "gn:asciiname":"Diaofangtou",
    "gn:country_code":"CN",
    "gn:dem":872,
    "gn:feature_class":"P",
    "gn:feature_code":"PPL",
    "gn:name":"Diaofangtou",
    "gn:population":0,
    "gn:timezone":"Asia/Shanghai",
    "iso:country":"CN",
    "name:zho_x_preferred":[
        "\u7889\u623f\u5934"
    ],
    "wof:name":"Diaofangtou",
    "wof:placetype":"locality"
},
  "geometry": {"coordinates":[103.833,28.7082],"type":"Point"}
}