{
  "type": "Feature",
  "properties": {
    "gn:admin1_code":"4.0",
    "gn:asciiname":"Zhanan",
    "gn:country_code":"CN",
    "gn:dem":7,
    "gn:feature_class":"P",
    "gn:feature_code":"PPL",
    "gn:name":"Zhanan",
    "gn:population":0,
    "gn:timezone":"Asia/Shanghai",
    "iso:country":"CN",
    "name:und_x_variant":[
        "\u95f8\u5357"
    ],
    "name:zho_x_preferred":[
        "\u95f8\u5357"
    ],
    "wof:name":"Zhanan",
    "wof:placetype":"locality"
},
  "geometry": {"coordinates":[120.08150000000001,32.26778],"type":"Point"}
}