{
  "type": "Feature",
  "properties": {
    "gn:admin1_code":"10",
    "gn:asciiname":"Duowang",
    "gn:country_code":"CN",
    "gn:dem":20,
    "gn:feature_class":"P",
    "gn:feature_code":"PPL",
    "gn:name":"Duowang",
    "gn:population":0,
    "gn:timezone":"Asia/Shanghai",
    "iso:country":"CN",
    "name:zho_x_preferred":[
        "\u591a\u738b"
    ],
    "wof:name":"Duowang",
    "wof:placetype":"locality"
},
  "geometry": {"coordinates":[116.19614,37.86404],"type":"Point"}
}