{
  "type": "Feature",
  "properties": {
    "gn:admin1_code":"22",
    "gn:asciiname":"Liugezhuang",
    "gn:country_code":"CN",
    "gn:dem":20,
    "gn:feature_class":"P",
    "gn:feature_code":"PPL",
    "gn:name":"Liugezhuang",
    "gn:population":0,
    "gn:timezone":"Asia/Shanghai",
    "iso:country":"CN",
    "name:und_x_variant":[
        "Caoliugezhuang"
    ],
    "name:zho_x_preferred":[
        "\u5218\u5404\u5e84"
    ],
    "wof:name":"Liugezhuang",
    "wof:placetype":"locality"
},
  "geometry": {"coordinates":[116.87394,39.79176],"type":"Point"}
}