{
  "type": "Feature",
  "properties": {
    "gn:admin1_code":"3.0",
    "gn:asciiname":"Dingxi",
    "gn:country_code":"CN",
    "gn:dem":35,
    "gn:feature_class":"P",
    "gn:feature_code":"PPL",
    "gn:name":"Dingxi",
    "gn:population":0,
    "gn:timezone":"Asia/Shanghai",
    "iso:country":"CN",
    "name:ara_x_preferred":[
        "\u062f\u064a\u063a\u0646\u0634\u064a"
    ],
    "name:cdo_x_preferred":[
        "D\u00eang-s\u0103\u0324"
    ],
    "name:ceb_x_preferred":[
        "Dingxi Shi"
    ],
    "name:ces_x_preferred":[
        "Ting-si"
    ],
    "name:dan_x_preferred":[
        "Dingxi"
    ],
    "name:deu_x_preferred":[
        "Dingxi"
    ],
    "name:eus_x_preferred":[
        "Dingxi"
    ],
    "name:fas_x_preferred":[
        "\u062f\u06cc\u0646\u06af\u0633\u06cc"
    ],
    "name:fin_x_preferred":[
        "Dingxi"
    ],
    "name:fra_x_preferred":[
        "Dingxi"
    ],
    "name:hye_x_preferred":[
        "\u0534\u056b\u0576\u057d\u056b"
    ],
    "name:ind_x_preferred":[
        "Dingxi"
    ],
    "name:ita_x_preferred":[
        "Dingxi"
    ],
    "name:jpn_x_preferred":[
        "\u5b9a\u897f\u5e02"
    ],
    "name:kik_x_preferred":[
        "Dingxi"
    ],
    "name:kor_x_preferred":[
        "\ub529\uc2dc\uc2dc"
    ],
    "name:msa_x_preferred":[
        "Dingxi"
    ],
    "name:nld_x_preferred":[
        "Dingxi"
    ],
    "name:nno_x_preferred":[
        "Dingxi"
    ],
    "name:nor_x_preferred":[
        "Dingxi"
    ],
    "name:pam_x_preferred":[
        "Dingxi"
    ],
    "name:pnb_x_preferred":[
        "\u0688\u0646\u06af\u0633\u06cc"
    ],
    "name:pol_x_preferred":[
        "Dingxi"
    ],
    "name:rus_x_preferred":[
        "\u0414\u0438\u043d\u0441\u0438"
    ],
    "name:sin_x_preferred":[
        "\u0da9\u0dd2\u0d82\u0dc3\u0dba\u0dd2"
    ],
    "name:spa_x_preferred":[
        "Dingxi"
    ],
    "name:swe_x_preferred":[
        "Dingxi"
    ],
    "name:tur_x_preferred":[
        "Dingxi"
    ],
    "name:ukr_x_preferred":[
        "\u0414\u0456\u043d\u0441\u0456"
    ],
    "name:und_x_variant":[
        "\u4e01\u6eaa"
    ],
    "name:urd_x_preferred":[
        "\u0688\u0646\u06af\u0634\u06cc"
    ],
    "name:vie_x_preferred":[
        "\u0110\u1ecbnh T\u00e2y"
    ],
    "name:wuu_x_preferred":[
        "\u5b9a\u897f\u5e02"
    ],
    "name:zho_x_preferred":[
        "\u5b9a\u897f\u5e02"
    ],
    "wof:name":"Dingxi",
    "wof:placetype":"locality"
},
  "geometry": {"coordinates":[116.42512000000001,28.37932],"type":"Point"}
}