{
  "type": "Feature",
  "properties": {
    "gn:admin1_code":"8.0",
    "gn:asciiname":"Baofengcun",
    "gn:country_code":"CN",
    "gn:dem":65,
    "gn:feature_class":"P",
    "gn:feature_code":"PPL",
    "gn:name":"Baofengcun",
    "gn:population":0,
    "gn:timezone":"Asia/Shanghai",
    "iso:country":"CN",
    "name:zho_x_preferred":[
        "\u5b9d\u4e30\u6751"
    ],
    "wof:name":"Baofengcun",
    "wof:placetype":"locality"
},
  "geometry": {"coordinates":[133.71159,46.24106],"type":"Point"}
}