{
  "type": "Feature",
  "properties": {
    "gn:admin1_code":"29.0",
    "gn:asciiname":"Langjia Yuanzi",
    "gn:country_code":"CN",
    "gn:dem":1759,
    "gn:feature_class":"P",
    "gn:feature_code":"PPL",
    "gn:name":"Langjia Yuanzi",
    "gn:population":0,
    "gn:timezone":"Asia/Shanghai",
    "iso:country":"CN",
    "name:zho_x_preferred":[
        "\u90ce\u5bb6\u9662\u5b50"
    ],
    "wof:name":"Langjia Yuanzi",
    "wof:placetype":"locality"
},
  "geometry": {"coordinates":[104.925,27.459],"type":"Point"}
}