{
  "type": "Feature",
  "properties": {
    "gn:admin1_code":"16.0",
    "gn:asciiname":"Laoxian",
    "gn:country_code":"CN",
    "gn:dem":262,
    "gn:feature_class":"P",
    "gn:feature_code":"PPL",
    "gn:name":"Laoxian",
    "gn:population":0,
    "gn:timezone":"Asia/Shanghai",
    "iso:country":"CN",
    "name:zho_x_preferred":[
        "\u8001\u53bf"
    ],
    "wof:name":"Laoxian",
    "wof:placetype":"locality"
},
  "geometry": {"coordinates":[110.22499999999999,24.4264],"type":"Point"}
}