{
  "type": "Feature",
  "properties": {
    "gn:admin1_code":"1.0",
    "gn:asciiname":"Yangjiaocun",
    "gn:country_code":"CN",
    "gn:dem":46,
    "gn:feature_class":"P",
    "gn:feature_code":"PPL",
    "gn:name":"Yangjiaocun",
    "gn:population":0,
    "gn:timezone":"Asia/Shanghai",
    "iso:country":"CN",
    "name:zho_x_preferred":[
        "\u7f8a\u89d2\u6751"
    ],
    "wof:name":"Yangjiaocun",
    "wof:placetype":"locality"
},
  "geometry": {"coordinates":[116.25029000000001,30.29969],"type":"Point"}
}