{
  "type": "Feature",
  "properties": {
    "gn:admin1_code":"11.0",
    "gn:asciiname":"Shanshangnie",
    "gn:country_code":"CN",
    "gn:dem":77,
    "gn:feature_class":"P",
    "gn:feature_code":"PPL",
    "gn:name":"Shanshangnie",
    "gn:population":0,
    "gn:timezone":"Asia/Shanghai",
    "iso:country":"CN",
    "name:zho_x_preferred":[
        "\u5c71\u4e0a\u8042"
    ],
    "wof:name":"Shanshangnie",
    "wof:placetype":"locality"
},
  "geometry": {"coordinates":[113.42547999999999,28.30604000000001],"type":"Point"}
}