{
  "type": "Feature",
  "properties": {
    "gn:admin1_code":"16.0",
    "gn:asciiname":"Rongli",
    "gn:country_code":"CN",
    "gn:dem":71,
    "gn:feature_class":"P",
    "gn:feature_code":"PPL",
    "gn:name":"Rongli",
    "gn:population":0,
    "gn:timezone":"Asia/Shanghai",
    "iso:country":"CN",
    "name:zho_x_preferred":[
        "\u5bb9\u8354"
    ],
    "wof:name":"Rongli",
    "wof:placetype":"locality"
},
  "geometry": {"coordinates":[110.16800000000001,23.1458],"type":"Point"}
}