{
  "type": "Feature",
  "properties": {
    "gn:admin1_code":"29.0",
    "gn:asciiname":"Tiexianxi",
    "gn:country_code":"CN",
    "gn:dem":1505,
    "gn:feature_class":"P",
    "gn:feature_code":"PPLA4",
    "gn:name":"Tiexianxi",
    "gn:population":0,
    "gn:timezone":"Asia/Shanghai",
    "iso:country":"CN",
    "name:und_x_variant":[
        "\u94c1\u7ebf\u6eaa",
        "Shoushan",
        "Shoushan Xiang",
        "\u5bff\u5c71",
        "\u5bff\u5c71\u4e61"
    ],
    "wof:name":"Tiexianxi",
    "wof:placetype":"locality"
},
  "geometry": {"coordinates":[103.88939000000001,27.91193],"type":"Point"}
}