{
  "type": "Feature",
  "properties": {
    "gn:admin1_code":"33.0",
    "gn:asciiname":"Hongping",
    "gn:country_code":"CN",
    "gn:dem":1170,
    "gn:feature_class":"P",
    "gn:feature_code":"PPL",
    "gn:name":"Hongping",
    "gn:population":0,
    "gn:timezone":"Asia/Shanghai",
    "iso:country":"CN",
    "name:zho_x_preferred":[
        "\u7ea2\u576a"
    ],
    "wof:name":"Hongping",
    "wof:placetype":"locality"
},
  "geometry": {"coordinates":[108.68562,31.89468],"type":"Point"}
}