{
  "type": "Feature",
  "properties": {
    "gn:admin1_code":"31.0",
    "gn:asciiname":"Songyuan",
    "gn:country_code":"CN",
    "gn:dem":14,
    "gn:feature_class":"P",
    "gn:feature_code":"PPL",
    "gn:name":"Songyuan",
    "gn:population":0,
    "gn:timezone":"Asia/Shanghai",
    "iso:country":"CN",
    "name:ara_x_preferred":[
        "\u0633\u0648\u0646\u063a\u064a\u0648\u0627\u0646"
    ],
    "name:cdo_x_preferred":[
        "S\u1e73\u0300ng-ngu\u00f2ng"
    ],
    "name:ces_x_preferred":[
        "Sung-j\u00fcan"
    ],
    "name:dan_x_preferred":[
        "Songyuan"
    ],
    "name:deu_x_preferred":[
        "Songyuan"
    ],
    "name:eus_x_preferred":[
        "Songyuan"
    ],
    "name:fas_x_preferred":[
        "\u0633\u0627\u0646\u06af\u06cc\u0648\u0627\u0646"
    ],
    "name:fin_x_preferred":[
        "Songyuan"
    ],
    "name:fra_x_preferred":[
        "Songyuan"
    ],
    "name:heb_x_preferred":[
        "\u05e1\u05d5\u05e0\u05d2\u05d9\u05d5\u05d0\u05df"
    ],
    "name:hun_x_preferred":[
        "Songyuan"
    ],
    "name:ita_x_preferred":[
        "Songyuan"
    ],
    "name:jpn_x_preferred":[
        "\u677e\u539f\u5e02"
    ],
    "name:kik_x_preferred":[
        "Songyuan"
    ],
    "name:kor_x_preferred":[
        "\uc479\uc704\uc548\uc2dc"
    ],
    "name:mlg_x_preferred":[
        "Songyuan"
    ],
    "name:nld_x_preferred":[
        "Songyuan"
    ],
    "name:nno_x_preferred":[
        "Songyuan"
    ],
    "name:nor_x_preferred":[
        "Songyuan"
    ],
    "name:pol_x_preferred":[
        "Songyuan"
    ],
    "name:rus_x_preferred":[
        "\u0421\u0443\u043d\u044a\u044e\u0430\u043d\u044c"
    ],
    "name:spa_x_preferred":[
        "Songyuan"
    ],
    "name:swe_x_preferred":[
        "Songyuan"
    ],
    "name:tur_x_preferred":[
        "Songyuan"
    ],
    "name:ukr_x_preferred":[
        "\u0421\u0443\u043d\u2019\u044e\u0430\u043d\u044c"
    ],
    "name:urd_x_preferred":[
        "\u0633\u0648\u0646\u06af\u06cc\u0648\u0627\u0646"
    ],
    "name:vie_x_preferred":[
        "T\u00f9ng Nguy\u00ean"
    ],
    "name:war_x_preferred":[
        "Songyuan"
    ],
    "name:wuu_x_preferred":[
        "\u677e\u539f\u5e02"
    ],
    "name:zho_x_preferred":[
        "\u5b8b\u56ed"
    ],
    "name:zho_x_variant":[
        "\u677e\u539f\u5e02"
    ],
    "wof:name":"Songyuan",
    "wof:placetype":"locality"
},
  "geometry": {"coordinates":[110.55032,19.18073],"type":"Point"}
}