{
  "type": "Feature",
  "properties": {
    "gn:admin1_code":"08",
    "gn:asciiname":"Wudaogou",
    "gn:cc2":"CN",
    "gn:country_code":"CN",
    "gn:dem":454,
    "gn:feature_class":"P",
    "gn:feature_code":"PPL",
    "gn:name":"Wudaogou",
    "gn:population":0,
    "gn:timezone":"Asia/Shanghai",
    "iso:country":"CN",
    "name:eng_x_preferred":[
        "Wudaogou"
    ],
    "name:rus_x_preferred":[
        "\u0423\u0434\u0430\u043e\u0433\u043e\u0443"
    ],
    "name:rus_x_variant":[
        "\u041b\u044e\u0434\u0430\u043e\u0433\u043e\u0443",
        "\u0421\u044b\u0434\u0430\u043e\u0433\u043e\u0443"
    ],
    "name:und_x_variant":[
        "Wu-tao-kou",
        "Wudaogou"
    ],
    "wof:name":"Wudaogou",
    "wof:placetype":"locality"
},
  "geometry": {"coordinates":[126.45,50.25],"type":"Point"}
}