{
  "type": "Feature",
  "properties": {
    "gn:admin1_code":"4.0",
    "gn:asciiname":"Erxu",
    "gn:country_code":"CN",
    "gn:dem":1,
    "gn:feature_class":"P",
    "gn:feature_code":"PPLF",
    "gn:name":"Erxu",
    "gn:population":0,
    "gn:timezone":"Asia/Shanghai",
    "iso:country":"CN",
    "name:zho_x_preferred":[
        "\u4e8c\u5729"
    ],
    "wof:name":"Erxu",
    "wof:placetype":"locality"
},
  "geometry": {"coordinates":[120.32074,31.99492],"type":"Point"}
}