{
  "type": "Feature",
  "properties": {
    "gn:admin1_code":"12.0",
    "gn:asciiname":"Guohaiying",
    "gn:country_code":"CN",
    "gn:dem":57,
    "gn:feature_class":"P",
    "gn:feature_code":"PPL",
    "gn:name":"Guohaiying",
    "gn:population":0,
    "gn:timezone":"Asia/Shanghai",
    "iso:country":"CN",
    "name:zho_x_preferred":[
        "\u90ed\u6d77\u8425"
    ],
    "wof:name":"Guohaiying",
    "wof:placetype":"locality"
},
  "geometry": {"coordinates":[112.37748999999999,31.62387],"type":"Point"}
}