{
  "type": "Feature",
  "properties": {
    "gn:admin1_code":"05",
    "gn:asciiname":"Tso-ho-ts'un",
    "gn:country_code":"CN",
    "gn:dem":306,
    "gn:feature_class":"P",
    "gn:feature_code":"PPL",
    "gn:name":"Tso-ho-ts\u2019un",
    "gn:population":0,
    "gn:timezone":"Asia/Shanghai",
    "iso:country":"CN",
    "wof:name":"Tso-ho-ts'un",
    "wof:placetype":"locality"
},
  "geometry": {"coordinates":[126.09917,42.57667],"type":"Point"}
}