{
  "type": "Feature",
  "properties": {
    "gn:admin1_code":"10",
    "gn:asciiname":"Diaowo Goumen",
    "gn:country_code":"CN",
    "gn:dem":1182,
    "gn:feature_class":"P",
    "gn:feature_code":"PPL",
    "gn:name":"Diaowo Goumen",
    "gn:population":0,
    "gn:timezone":"Asia/Shanghai",
    "iso:country":"CN",
    "name:zho_x_preferred":[
        "\u5201\u7a9d\u6c9f\u95e8"
    ],
    "wof:name":"Diaowo Goumen",
    "wof:placetype":"locality"
},
  "geometry": {"coordinates":[117.66369,42.34236],"type":"Point"}
}