{
  "type": "Feature",
  "properties": {
    "gn:admin1_code":"32.0",
    "gn:asciiname":"Waqie Nongyeshe",
    "gn:country_code":"CN",
    "gn:dem":3454,
    "gn:feature_class":"P",
    "gn:feature_code":"PPLF",
    "gn:name":"Waqie Nongyeshe",
    "gn:population":0,
    "gn:timezone":"Asia/Shanghai",
    "iso:country":"CN",
    "name:zho_x_preferred":[
        "\u74e6\u5207\u519c\u4e1a\u793e"
    ],
    "wof:name":"Waqie Nongyeshe",
    "wof:placetype":"locality"
},
  "geometry": {"coordinates":[102.61799999999999,33.1206],"type":"Point"}
}