{
  "type": "Feature",
  "properties": {
    "gn:admin1_code":"8.0",
    "gn:asciiname":"Nanchangshengcun",
    "gn:country_code":"CN",
    "gn:dem":71,
    "gn:feature_class":"P",
    "gn:feature_code":"PPL",
    "gn:name":"Nanchangshengcun",
    "gn:population":0,
    "gn:timezone":"Asia/Shanghai",
    "iso:country":"CN",
    "name:zho_x_preferred":[
        "\u5357\u660c\u80dc\u6751"
    ],
    "wof:name":"Nanchangshengcun",
    "wof:placetype":"locality"
},
  "geometry": {"coordinates":[131.22243,47.06917],"type":"Point"}
}