{
  "type": "Feature",
  "properties": {
    "gn:admin1_code":"3.0",
    "gn:asciiname":"Foyou Xujia",
    "gn:country_code":"CN",
    "gn:dem":27,
    "gn:feature_class":"P",
    "gn:feature_code":"PPL",
    "gn:name":"Foyou Xujia",
    "gn:population":0,
    "gn:timezone":"Asia/Shanghai",
    "iso:country":"CN",
    "name:und_x_variant":[
        "\u4f5b\u4f51\u5f90\u5bb6"
    ],
    "wof:name":"Foyou Xujia",
    "wof:placetype":"locality"
},
  "geometry": {"coordinates":[116.86857999999999,28.76087],"type":"Point"}
}