{
  "type": "Feature",
  "properties": {
    "gn:admin1_code":"26.0",
    "gn:asciiname":"Renjiamao",
    "gn:country_code":"CN",
    "gn:dem":1388,
    "gn:feature_class":"P",
    "gn:feature_code":"PPL",
    "gn:name":"Renjiamao",
    "gn:population":0,
    "gn:timezone":"Asia/Shanghai",
    "iso:country":"CN",
    "name:zho_x_preferred":[
        "\u4efb\u5bb6\u5cc1"
    ],
    "wof:name":"Renjiamao",
    "wof:placetype":"locality"
},
  "geometry": {"coordinates":[109.24603,37.32851],"type":"Point"}
}