{
  "type": "Feature",
  "properties": {
    "gn:admin1_code":"3.0",
    "gn:asciiname":"Qingshanwu",
    "gn:country_code":"CN",
    "gn:dem":29,
    "gn:feature_class":"P",
    "gn:feature_code":"PPL",
    "gn:name":"Qingshanwu",
    "gn:population":0,
    "gn:timezone":"Asia/Shanghai",
    "iso:country":"CN",
    "name:und_x_variant":[
        "\u9752\u5c71\u575e"
    ],
    "wof:name":"Qingshanwu",
    "wof:placetype":"locality"
},
  "geometry": {"coordinates":[116.58159000000001,29.7912],"type":"Point"}
}