{
  "type": "Feature",
  "properties": {
    "gn:admin1_code":"19",
    "gn:asciiname":"Yujia Buzi",
    "gn:country_code":"CN",
    "gn:dem":317,
    "gn:feature_class":"P",
    "gn:feature_code":"PPL",
    "gn:name":"Yujia Buzi",
    "gn:population":0,
    "gn:timezone":"Asia/Shanghai",
    "iso:country":"CN",
    "name:und_x_variant":[
        "Yujia Puzi",
        "\u4e8e\u5bb6\u5821\u5b50",
        "Yujiapuzi",
        "Yujia Buzi"
    ],
    "wof:name":"Yujia Buzi",
    "wof:placetype":"locality"
},
  "geometry": {"coordinates":[122.97646,40.22927],"type":"Point"}
}