{
  "type": "Feature",
  "properties": {
    "gn:admin1_code":"29.0",
    "gn:asciiname":"Shangmeiziqing",
    "gn:country_code":"CN",
    "gn:dem":1367,
    "gn:feature_class":"P",
    "gn:feature_code":"PPL",
    "gn:name":"Shangmeiziqing",
    "gn:population":0,
    "gn:timezone":"Asia/Shanghai",
    "iso:country":"CN",
    "name:zho_x_preferred":[
        "\u4e0a\u6885\u5b50\u7b90"
    ],
    "wof:name":"Shangmeiziqing",
    "wof:placetype":"locality"
},
  "geometry": {"coordinates":[101.40600000000001,23.2671],"type":"Point"}
}