{
  "type": "Feature",
  "properties": {
    "gn:admin1_code":"9.0",
    "gn:asciiname":"Junchen",
    "gn:country_code":"CN",
    "gn:dem":58,
    "gn:feature_class":"P",
    "gn:feature_code":"PPL",
    "gn:name":"Junchen",
    "gn:population":0,
    "gn:timezone":"Asia/Shanghai",
    "iso:country":"CN",
    "name:aze_x_preferred":[
        "G\u00fcn\u00e7en"
    ],
    "name:bul_x_preferred":[
        "\u0414\u0437\u044e\u043d\u0447\u044a\u043d"
    ],
    "name:jpn_x_preferred":[
        "\u8ecd\u81e3\u5358\u4e8e"
    ],
    "name:kaz_x_preferred":[
        "\u0413\u044e\u043d\u044c\u0447\u0435\u043d\u044c"
    ],
    "name:kor_x_preferred":[
        "\uad70\uc2e0\uc120\uc6b0"
    ],
    "name:mon_x_preferred":[
        "\u0416\u044e\u043d\u0447\u044d\u043d \u0448\u0430\u043d\u044c\u044e\u0439"
    ],
    "name:rus_x_preferred":[
        "\u0426\u0437\u044e\u043d\u044c\u0447\u044d\u043d\u044c"
    ],
    "name:tuk_x_preferred":[
        "Kuni\u00e7en"
    ],
    "name:zho_x_preferred":[
        "\u541b\u9648"
    ],
    "name:zho_x_variant":[
        "\u519b\u81e3\u5355\u4e8e"
    ],
    "wof:name":"Junchen",
    "wof:placetype":"locality"
},
  "geometry": {"coordinates":[114.2978,33.42469000000001],"type":"Point"}
}