{
  "type": "Feature",
  "properties": {
    "gn:admin1_code":"19.0",
    "gn:asciiname":"Manshoucun",
    "gn:country_code":"CN",
    "gn:dem":435,
    "gn:feature_class":"P",
    "gn:feature_code":"PPL",
    "gn:name":"Manshoucun",
    "gn:population":0,
    "gn:timezone":"Asia/Shanghai",
    "iso:country":"CN",
    "name:zho_x_preferred":[
        "\u9992\u9996\u6751"
    ],
    "wof:name":"Manshoucun",
    "wof:placetype":"locality"
},
  "geometry": {"coordinates":[124.34262,41.6088],"type":"Point"}
}