{
  "type": "Feature",
  "properties": {
    "gn:gn_country":"CN",
    "gn:gn_fcode":"PPLA2",
    "gn:gn_pop":501199,
    "gn:population":501199,
    "iso:country":"CN",
    "name:ara_x_preferred":[
        "\u0632\u0648\u0647\u0627\u064a"
    ],
    "name:bul_x_preferred":[
        "\u0414\u0436\u0443\u0445\u0430\u0439"
    ],
    "name:cdo_x_preferred":[
        "Ci\u014f-h\u0101i"
    ],
    "name:ces_x_preferred":[
        "\u010cu-chaj"
    ],
    "name:deu_x_preferred":[
        "Zhuhai"
    ],
    "name:eng_x_preferred":[
        "Zhuhai"
    ],
    "name:epo_x_preferred":[
        "\u011cuhaj"
    ],
    "name:fas_x_preferred":[
        "\u062c\u0648\u0647\u0627\u06cc"
    ],
    "name:fra_x_preferred":[
        "Zhuhai"
    ],
    "name:hak_x_preferred":[
        "Ch\u00fb-h\u00f3i-s\u1e73"
    ],
    "name:ita_x_preferred":[
        "Zhuhai"
    ],
    "name:jpn_x_preferred":[
        "\u73e0\u6d77"
    ],
    "name:jpn_x_variant":[
        "\u73e0\u6d77\u5e02"
    ],
    "name:kor_x_preferred":[
        "\uc8fc\ud558\uc774 \uc2dc"
    ],
    "name:lzh_x_preferred":[
        "\u73e0\u6d77"
    ],
    "name:nan_x_preferred":[
        "Chu-h\u00e1i-chh\u012b"
    ],
    "name:nor_x_preferred":[
        "Zhuhai"
    ],
    "name:rus_x_preferred":[
        "\u0427\u0436\u0443\u0445\u0430\u0439"
    ],
    "name:srp_x_preferred":[
        "\u040f\u0443\u0445\u0430\u0458"
    ],
    "name:uig_x_preferred":[
        "Juxey shehiri"
    ],
    "name:unk_x_variant":[
        "Xiangzhou"
    ],
    "name:urd_x_preferred":[
        "\u0698\u0648\u06c1\u0648\u0626\u06cc"
    ],
    "name:vie_x_preferred":[
        "Ch\u00e2u H\u1ea3i"
    ],
    "name:vie_x_variant":[
        "Chu H\u1ea3i"
    ],
    "name:yue_x_preferred":[
        "\u73e0\u6d77"
    ],
    "name:zho_x_preferred":[
        "\u73e0\u6d77\u5e02"
    ],
    "name:zho_x_variant":[
        "\u73e0\u6d77"
    ],
    "qs_pg:aaroncc":"CN",
    "qs_pg:gn_country":"CN",
    "qs_pg:gn_fcode":"PPLA2",
    "qs_pg:gn_pop":501199,
    "qs_pg:name":"\u73e0\u6d77\u5e02",
    "qs_pg:name_adm0":"\u4e2d\u570b",
    "qs_pg:name_adm1":"\u5e7f\u4e1c\u7701",
    "qs_pg:photos":8,
    "qs_pg:photos_1k":2,
    "qs_pg:photos_9k":21,
    "qs_pg:photos_9r":13,
    "qs_pg:photos_all":4751,
    "qs_pg:photos_sr":1,
    "qs_pg:pop_sr":12,
    "qs_pg:qs_pg_placetype":"localadmin",
    "qs_pg:qs_pg_placetype_gp":"LocalAdmin",
    "qs_pg:woe_adm0":23424781,
    "woe:adm0_id":23424781,
    "woe:name_adm0":"\u4e2d\u570b",
    "woe:name_adm1":"\u5e7f\u4e1c\u7701",
    "woe:placetype":"LocalAdmin",
    "wof:name":"\u73e0\u6d77\u5e02",
    "wof:placetype":"localadmin",
    "wof:population":501199
},
  "geometry": {"coordinates":[113.56778,22.27694],"type":"Point"}
}