{
  "type": "Feature",
  "properties": {
    "gn:admin1_code":"7.0",
    "gn:asciiname":"Tangkeng",
    "gn:country_code":"CN",
    "gn:dem":398,
    "gn:feature_class":"P",
    "gn:feature_code":"PPL",
    "gn:name":"Tangkeng",
    "gn:population":0,
    "gn:timezone":"Asia/Shanghai",
    "iso:country":"CN",
    "name:zho_x_preferred":[
        "\u5858\u5751"
    ],
    "name:zho_x_variant":[
        "\u6c64\u5751\u9547"
    ],
    "wof:name":"Tangkeng",
    "wof:placetype":"locality"
},
  "geometry": {"coordinates":[116.90164,24.6815],"type":"Point"}
}