{
  "type": "Feature",
  "properties": {
    "gn:admin1_code":"3.0",
    "gn:asciiname":"Sanjia",
    "gn:country_code":"CN",
    "gn:dem":44,
    "gn:feature_class":"P",
    "gn:feature_code":"PPL",
    "gn:name":"Sanjia",
    "gn:population":0,
    "gn:timezone":"Asia/Shanghai",
    "iso:country":"CN",
    "name:ceb_x_preferred":[
        "Sanjia"
    ],
    "name:swe_x_preferred":[
        "Sanjia"
    ],
    "name:und_x_variant":[
        "\u4e09\u7532"
    ],
    "wof:name":"Sanjia",
    "wof:placetype":"locality"
},
  "geometry": {"coordinates":[116.96681,29.24991],"type":"Point"}
}