{
  "type": "Feature",
  "properties": {
    "gn:admin1_code":"4.0",
    "gn:asciiname":"Wangongzhuang",
    "gn:country_code":"CN",
    "gn:dem":26,
    "gn:feature_class":"P",
    "gn:feature_code":"PPL",
    "gn:name":"Wangongzhuang",
    "gn:population":0,
    "gn:timezone":"Asia/Shanghai",
    "iso:country":"CN",
    "name:zho_x_preferred":[
        "\u4e07\u516c\u5e84"
    ],
    "wof:name":"Wangongzhuang",
    "wof:placetype":"locality"
},
  "geometry": {"coordinates":[118.77500000000001,33.0061],"type":"Point"}
}