{
  "type": "Feature",
  "properties": {
    "gn:admin1_code":"8.0",
    "gn:asciiname":"Guandi Fangzi",
    "gn:country_code":"CN",
    "gn:dem":159,
    "gn:feature_class":"P",
    "gn:feature_code":"PPL",
    "gn:name":"Guandi Fangzi",
    "gn:population":0,
    "gn:timezone":"Asia/Shanghai",
    "iso:country":"CN",
    "name:zho_x_preferred":[
        "\u5173\u5730\u623f\u5b50"
    ],
    "wof:name":"Guandi Fangzi",
    "wof:placetype":"locality"
},
  "geometry": {"coordinates":[124.47045,47.65834],"type":"Point"}
}