{
  "type": "Feature",
  "properties": {
    "gn:admin1_code":"11.0",
    "gn:asciiname":"Yanzhuhu",
    "gn:country_code":"CN",
    "gn:dem":124,
    "gn:feature_class":"P",
    "gn:feature_code":"PPL",
    "gn:name":"Yanzhuhu",
    "gn:population":0,
    "gn:timezone":"Asia/Shanghai",
    "iso:country":"CN",
    "name:zho_x_preferred":[
        "\u70df\u7af9\u6e56"
    ],
    "wof:name":"Yanzhuhu",
    "wof:placetype":"locality"
},
  "geometry": {"coordinates":[113.49377,27.71214],"type":"Point"}
}