{
  "type": "Feature",
  "properties": {
    "gn:admin1_code":"32.0",
    "gn:asciiname":"Baguashan",
    "gn:country_code":"CN",
    "gn:dem":753,
    "gn:feature_class":"P",
    "gn:feature_code":"PPL",
    "gn:name":"Baguashan",
    "gn:population":0,
    "gn:timezone":"Asia/Shanghai",
    "iso:country":"CN",
    "name:zho_x_preferred":[
        "\u516b\u74dc\u5c71"
    ],
    "wof:name":"Baguashan",
    "wof:placetype":"locality"
},
  "geometry": {"coordinates":[107.53100000000001,31.9611],"type":"Point"}
}