{
  "type": "Feature",
  "properties": {
    "gn:admin1_code":"3.0",
    "gn:asciiname":"Youdianbei",
    "gn:country_code":"CN",
    "gn:dem":422,
    "gn:feature_class":"P",
    "gn:feature_code":"PPL",
    "gn:name":"Youdianbei",
    "gn:population":0,
    "gn:timezone":"Asia/Shanghai",
    "iso:country":"CN",
    "name:und_x_variant":[
        "\u6cb9\u5e97\u80cc"
    ],
    "wof:name":"Youdianbei",
    "wof:placetype":"locality"
},
  "geometry": {"coordinates":[115.33237,25.67382000000001],"type":"Point"}
}