{
  "type": "Feature",
  "properties": {
    "gn:admin1_code":"26.0",
    "gn:asciiname":"Shaiqunling",
    "gn:country_code":"CN",
    "gn:dem":1029,
    "gn:feature_class":"P",
    "gn:feature_code":"PPL",
    "gn:name":"Shaiqunling",
    "gn:population":0,
    "gn:timezone":"Asia/Shanghai",
    "iso:country":"CN",
    "name:zho_x_preferred":[
        "\u6652\u88d9\u5cad"
    ],
    "wof:name":"Shaiqunling",
    "wof:placetype":"locality"
},
  "geometry": {"coordinates":[109.17534999999999,33.63021],"type":"Point"}
}