{
  "type": "Feature",
  "properties": {
    "gn:admin1_code":"32.0",
    "gn:asciiname":"Zhaobi",
    "gn:country_code":"CN",
    "gn:dem":1254,
    "gn:feature_class":"P",
    "gn:feature_code":"PPL",
    "gn:name":"Zhaobi",
    "gn:population":0,
    "gn:timezone":"Asia/Shanghai",
    "iso:country":"CN",
    "name:zho_x_preferred":[
        "\u7167\u58c1"
    ],
    "wof:name":"Zhaobi",
    "wof:placetype":"locality"
},
  "geometry": {"coordinates":[101.94429,26.56538],"type":"Point"}
}