{
  "type": "Feature",
  "properties": {
    "gn:admin1_code":"21.0",
    "gn:asciiname":"Jianfuqiao",
    "gn:country_code":"CN",
    "gn:dem":1109,
    "gn:feature_class":"P",
    "gn:feature_code":"PPL",
    "gn:name":"Jianfuqiao",
    "gn:population":0,
    "gn:timezone":"Asia/Shanghai",
    "iso:country":"CN",
    "name:und_x_variant":[
        "Jianfuqiao Xiang"
    ],
    "name:zho_x_preferred":[
        "\u78b1\u5bcc\u6865"
    ],
    "name:zho_x_variant":[
        "\u78b1\u5bcc\u6865\u4e61"
    ],
    "wof:name":"Jianfuqiao",
    "wof:placetype":"locality"
},
  "geometry": {"coordinates":[106.395,38.3934],"type":"Point"}
}