{
  "type": "Feature",
  "properties": {
    "gn:admin1_code":"19.0",
    "gn:asciiname":"Dapangcun",
    "gn:country_code":"CN",
    "gn:dem":49,
    "gn:feature_class":"P",
    "gn:feature_code":"PPL",
    "gn:name":"Dapangcun",
    "gn:population":0,
    "gn:timezone":"Asia/Shanghai",
    "iso:country":"CN",
    "name:zho_x_preferred":[
        "\u5927\u9004\u6751"
    ],
    "wof:name":"Dapangcun",
    "wof:placetype":"locality"
},
  "geometry": {"coordinates":[121.59999999999999,39.7071],"type":"Point"}
}