{
  "type": "Feature",
  "properties": {
    "gn:admin1_code":"26",
    "gn:asciiname":"Shalingcun",
    "gn:country_code":"CN",
    "gn:dem":381,
    "gn:feature_class":"P",
    "gn:feature_code":"PPL",
    "gn:name":"Shalingcun",
    "gn:population":0,
    "gn:timezone":"Asia/Shanghai",
    "iso:country":"CN",
    "name:und_x_variant":[
        "Shaling"
    ],
    "name:zho_x_preferred":[
        "\u6c99\u82d3"
    ],
    "name:zho_x_variant":[
        "\u6c99\u82d3\u6751"
    ],
    "wof:name":"Shalingcun",
    "wof:placetype":"locality"
},
  "geometry": {"coordinates":[108.78530000000001,34.34645],"type":"Point"}
}