{
  "type": "Feature",
  "properties": {
    "gn:admin1_code":"16",
    "gn:asciiname":"Zhu'anchong",
    "gn:country_code":"CN",
    "gn:dem":346,
    "gn:feature_class":"P",
    "gn:feature_code":"PPL",
    "gn:name":"Zhu\u2019anchong",
    "gn:population":0,
    "gn:timezone":"Asia/Shanghai",
    "iso:country":"CN",
    "name:und_x_variant":[
        "Zhu\u2019anchong"
    ],
    "name:zho_x_preferred":[
        "\u6731\u5b89\u51b2"
    ],
    "wof:name":"Zhu'anchong",
    "wof:placetype":"locality"
},
  "geometry": {"coordinates":[111.185,25.4859],"type":"Point"}
}