{
  "type": "Feature",
  "properties": {
    "gn:admin1_code":"29.0",
    "gn:asciiname":"Wumapu",
    "gn:country_code":"CN",
    "gn:dem":2507,
    "gn:feature_class":"P",
    "gn:feature_code":"PPL",
    "gn:name":"Wumapu",
    "gn:population":0,
    "gn:timezone":"Asia/Shanghai",
    "iso:country":"CN",
    "name:zho_x_preferred":[
        "\u543e\u9a6c\u666e"
    ],
    "wof:name":"Wumapu",
    "wof:placetype":"locality"
},
  "geometry": {"coordinates":[99.1039,26.3147],"type":"Point"}
}