{
  "type": "Feature",
  "properties": {
    "gn:admin1_code":"11",
    "gn:asciiname":"Shufangling",
    "gn:country_code":"CN",
    "gn:dem":93,
    "gn:feature_class":"P",
    "gn:feature_code":"PPL",
    "gn:name":"Shufangling",
    "gn:population":0,
    "gn:timezone":"Asia/Shanghai",
    "iso:country":"CN",
    "name:zho_x_preferred":[
        "\u4e66\u623f\u5cad"
    ],
    "wof:name":"Shufangling",
    "wof:placetype":"locality"
},
  "geometry": {"coordinates":[112.29537999999999,26.85658],"type":"Point"}
}