{
  "type": "Feature",
  "properties": {
    "gn:admin1_code":"1.0",
    "gn:asciiname":"Huachengcun",
    "gn:country_code":"CN",
    "gn:dem":46,
    "gn:feature_class":"P",
    "gn:feature_code":"PPL",
    "gn:name":"Huachengcun",
    "gn:population":0,
    "gn:timezone":"Asia/Shanghai",
    "iso:country":"CN",
    "name:zho_x_preferred":[
        "\u534e\u57ce\u6751"
    ],
    "wof:name":"Huachengcun",
    "wof:placetype":"locality"
},
  "geometry": {"coordinates":[117.21134000000001,31.98324],"type":"Point"}
}