{
  "type": "Feature",
  "properties": {
    "gn:admin1_code":"12.0",
    "gn:asciiname":"Xishunlin Gou",
    "gn:country_code":"CN",
    "gn:dem":34,
    "gn:feature_class":"P",
    "gn:feature_code":"PPL",
    "gn:name":"Xishunlin Gou",
    "gn:population":0,
    "gn:timezone":"Asia/Shanghai",
    "iso:country":"CN",
    "name:zho_x_preferred":[
        "\u897f\u987a\u6797\u6c9f"
    ],
    "wof:name":"Xishunlin Gou",
    "wof:placetype":"locality"
},
  "geometry": {"coordinates":[112.09479,30.14494],"type":"Point"}
}