{
  "type": "Feature",
  "properties": {
    "gn:admin1_code":"9.0",
    "gn:asciiname":"Leiquan",
    "gn:country_code":"CN",
    "gn:dem":584,
    "gn:feature_class":"P",
    "gn:feature_code":"PPL",
    "gn:name":"Leiquan",
    "gn:population":0,
    "gn:timezone":"Asia/Shanghai",
    "iso:country":"CN",
    "name:zho_x_preferred":[
        "\u96f7\u6cc9"
    ],
    "wof:name":"Leiquan",
    "wof:placetype":"locality"
},
  "geometry": {"coordinates":[112.98725,34.23627],"type":"Point"}
}