{
  "type": "Feature",
  "properties": {
    "gn:admin1_code":"14.0",
    "gn:asciiname":"Ciduo",
    "gn:country_code":"CN",
    "gn:dem":4106,
    "gn:feature_class":"P",
    "gn:feature_code":"PPL",
    "gn:name":"Ciduo",
    "gn:population":0,
    "gn:timezone":"Asia/Urumqi",
    "iso:country":"CN",
    "name:zho_x_preferred":[
        "\u6b21\u591a"
    ],
    "wof:name":"Ciduo",
    "wof:placetype":"locality"
},
  "geometry": {"coordinates":[87.90049999999999,29.0194],"type":"Point"}
}