{
  "type": "Feature",
  "properties": {
    "gn:admin1_code":"3.0",
    "gn:asciiname":"Qincun",
    "gn:country_code":"CN",
    "gn:dem":81,
    "gn:feature_class":"P",
    "gn:feature_code":"PPL",
    "gn:name":"Qincun",
    "gn:population":0,
    "gn:timezone":"Asia/Shanghai",
    "iso:country":"CN",
    "name:und_x_variant":[
        "\u94a6\u6751"
    ],
    "wof:name":"Qincun",
    "wof:placetype":"locality"
},
  "geometry": {"coordinates":[114.46892,27.13008],"type":"Point"}
}