{
  "type": "Feature",
  "properties": {
    "gn:admin1_code":"30.0",
    "gn:asciiname":"Sanzhongcun",
    "gn:country_code":"CN",
    "gn:dem":230,
    "gn:feature_class":"P",
    "gn:feature_code":"PPL",
    "gn:name":"Sanzhongcun",
    "gn:population":0,
    "gn:timezone":"Asia/Shanghai",
    "iso:country":"CN",
    "name:zho_x_preferred":[
        "\u4e09\u4e2d\u6751"
    ],
    "wof:name":"Sanzhongcun",
    "wof:placetype":"locality"
},
  "geometry": {"coordinates":[116.80274,24.13289],"type":"Point"}
}