{
  "type": "Feature",
  "properties": {
    "gn:admin1_code":"8.0",
    "gn:asciiname":"Lifangtun",
    "gn:country_code":"CN",
    "gn:dem":226,
    "gn:feature_class":"P",
    "gn:feature_code":"PPL",
    "gn:name":"Lifangtun",
    "gn:population":0,
    "gn:timezone":"Asia/Shanghai",
    "iso:country":"CN",
    "name:und_x_variant":[
        "Li-fang"
    ],
    "name:zho_x_preferred":[
        "\u674e\u82b3\u5c6f"
    ],
    "wof:name":"Lifangtun",
    "wof:placetype":"locality"
},
  "geometry": {"coordinates":[126.6785,47.75084],"type":"Point"}
}