{
  "type": "Feature",
  "properties": {
    "gn:admin1_code":"14.0",
    "gn:asciiname":"Legong",
    "gn:country_code":"CN",
    "gn:dem":4359,
    "gn:feature_class":"P",
    "gn:feature_code":"PPL",
    "gn:name":"Legong",
    "gn:population":0,
    "gn:timezone":"Asia/Urumqi",
    "iso:country":"CN",
    "name:cat_x_preferred":[
        "Legong"
    ],
    "name:deu_x_preferred":[
        "Legong"
    ],
    "name:fra_x_preferred":[
        "Legong"
    ],
    "name:hun_x_preferred":[
        "Legong"
    ],
    "name:ind_x_preferred":[
        "Legong"
    ],
    "name:jav_x_preferred":[
        "Tari Legong"
    ],
    "name:jpn_x_preferred":[
        "\u30ec\u30b4\u30f3"
    ],
    "name:nld_x_preferred":[
        "Legong"
    ],
    "name:spa_x_preferred":[
        "Legong"
    ],
    "name:zho_x_preferred":[
        "\u52d2\u8d21"
    ],
    "wof:name":"Legong",
    "wof:placetype":"locality"
},
  "geometry": {"coordinates":[86.41719999999999,28.6722],"type":"Point"}
}