{
  "type": "Feature",
  "properties": {
    "gn:admin1_code":"33.0",
    "gn:asciiname":"Sanshiliangba",
    "gn:country_code":"CN",
    "gn:dem":757,
    "gn:feature_class":"P",
    "gn:feature_code":"PPL",
    "gn:name":"Sanshiliangba",
    "gn:population":0,
    "gn:timezone":"Asia/Shanghai",
    "iso:country":"CN",
    "name:zho_x_preferred":[
        "\u4e09\u5341\u4e24\u575d"
    ],
    "wof:name":"Sanshiliangba",
    "wof:placetype":"locality"
},
  "geometry": {"coordinates":[109.02725,29.25147],"type":"Point"}
}