{
  "type": "Feature",
  "properties": {
    "gn:admin1_code":"16.0",
    "gn:asciiname":"Gan'ai",
    "gn:country_code":"CN",
    "gn:dem":211,
    "gn:feature_class":"P",
    "gn:feature_code":"PPL",
    "gn:name":"Gan\u2019ai",
    "gn:population":0,
    "gn:timezone":"Asia/Shanghai",
    "iso:country":"CN",
    "name:und_x_variant":[
        "Gan\u2019ai"
    ],
    "name:zho_x_preferred":[
        "\u6562\u66a7"
    ],
    "wof:name":"Gan'ai",
    "wof:placetype":"locality"
},
  "geometry": {"coordinates":[108.119,23.9913],"type":"Point"}
}