{
  "type": "Feature",
  "properties": {
    "gn:admin1_code":"29.0",
    "gn:asciiname":"Longshujiao",
    "gn:country_code":"CN",
    "gn:dem":609,
    "gn:feature_class":"P",
    "gn:feature_code":"PPL",
    "gn:name":"Longshujiao",
    "gn:population":0,
    "gn:timezone":"Asia/Shanghai",
    "iso:country":"CN",
    "name:zho_x_preferred":[
        "\u9f99\u6811\u811a"
    ],
    "wof:name":"Longshujiao",
    "wof:placetype":"locality"
},
  "geometry": {"coordinates":[103.134,22.7284],"type":"Point"}
}