{
  "type": "Feature",
  "properties": {
    "gn:admin1_code":"1.0",
    "gn:asciiname":"Chengying Kaihuangdui",
    "gn:country_code":"CN",
    "gn:dem":14,
    "gn:feature_class":"P",
    "gn:feature_code":"PPLF",
    "gn:name":"Chengying Kaihuangdui",
    "gn:population":0,
    "gn:timezone":"Asia/Shanghai",
    "iso:country":"CN",
    "name:zho_x_preferred":[
        "\u7a0b\u8425\u5f00\u8352\u961f"
    ],
    "wof:name":"Chengying Kaihuangdui",
    "wof:placetype":"locality"
},
  "geometry": {"coordinates":[116.17603,29.86892000000001],"type":"Point"}
}