{
  "type": "Feature",
  "properties": {
    "gn:admin1_code":"26",
    "gn:asciiname":"Qingyangshuping",
    "gn:cc2":"CN",
    "gn:country_code":"CN",
    "gn:dem":1277,
    "gn:feature_class":"P",
    "gn:feature_code":"PPL",
    "gn:name":"Qingyangshuping",
    "gn:population":0,
    "gn:timezone":"Asia/Shanghai",
    "iso:country":"CN",
    "name:und_x_variant":[
        "Ch\u2019ing-yang-shu-p\u2019ing",
        "Qingyangshuping"
    ],
    "wof:name":"Qingyangshuping",
    "wof:placetype":"locality"
},
  "geometry": {"coordinates":[108.73333,36.43333],"type":"Point"}
}