{
  "type": "Feature",
  "properties": {
    "gn:admin1_code":"19.0",
    "gn:asciiname":"Xinglongzhuangcun",
    "gn:country_code":"CN",
    "gn:dem":314,
    "gn:feature_class":"P",
    "gn:feature_code":"PPL",
    "gn:name":"Xinglongzhuangcun",
    "gn:population":0,
    "gn:timezone":"Asia/Shanghai",
    "iso:country":"CN",
    "name:zho_x_preferred":[
        "\u5174\u9686\u5e84\u6751"
    ],
    "wof:name":"Xinglongzhuangcun",
    "wof:placetype":"locality"
},
  "geometry": {"coordinates":[119.78999,41.16824],"type":"Point"}
}