{
  "type": "Feature",
  "properties": {
    "gn:admin1_code":"1.0",
    "gn:asciiname":"Tailaicun",
    "gn:country_code":"CN",
    "gn:dem":10,
    "gn:feature_class":"P",
    "gn:feature_code":"PPL",
    "gn:name":"Tailaicun",
    "gn:population":0,
    "gn:timezone":"Asia/Shanghai",
    "iso:country":"CN",
    "name:zho_x_preferred":[
        "\u592a\u6765\u6751"
    ],
    "wof:name":"Tailaicun",
    "wof:placetype":"locality"
},
  "geometry": {"coordinates":[118.51928999999998,31.7417],"type":"Point"}
}