{
  "type": "Feature",
  "properties": {
    "gn:admin1_code":"29.0",
    "gn:asciiname":"Xiaoduoyi",
    "gn:country_code":"CN",
    "gn:dem":1895,
    "gn:feature_class":"P",
    "gn:feature_code":"PPL",
    "gn:name":"Xiaoduoyi",
    "gn:population":0,
    "gn:timezone":"Asia/Shanghai",
    "iso:country":"CN",
    "name:zho_x_preferred":[
        "\u5c0f\u591a\u4f9d"
    ],
    "wof:name":"Xiaoduoyi",
    "wof:placetype":"locality"
},
  "geometry": {"coordinates":[103.25,23.2535],"type":"Point"}
}