{
  "type": "Feature",
  "properties": {
    "gn:admin1_code":"26",
    "gn:asciiname":"Liugou",
    "gn:country_code":"CN",
    "gn:dem":866,
    "gn:feature_class":"P",
    "gn:feature_code":"PPL",
    "gn:name":"Liugou",
    "gn:population":0,
    "gn:timezone":"Asia/Shanghai",
    "iso:country":"CN",
    "name:und_x_variant":[
        "\u5218\u6c9f",
        "Liugou"
    ],
    "wof:name":"Liugou",
    "wof:placetype":"locality"
},
  "geometry": {"coordinates":[109.31066,34.36866],"type":"Point"}
}