{
  "type": "Feature",
  "properties": {
    "gn:admin1_code":"3",
    "gn:asciiname":"Wumaguicao",
    "gn:country_code":"CN",
    "gn:dem":753,
    "gn:feature_class":"P",
    "gn:feature_code":"PPL",
    "gn:name":"Wumaguicao",
    "gn:population":0,
    "gn:timezone":"Asia/Shanghai",
    "iso:country":"CN",
    "name:zho_x_preferred":[
        "\u4e94\u9a6c\u5f52\u69fd"
    ],
    "wof:name":"Wumaguicao",
    "wof:placetype":"locality"
},
  "geometry": {"coordinates":[114.27200000000001,26.0155],"type":"Point"}
}