{
  "type": "Feature",
  "properties": {
    "gn:admin1_code":"24.0",
    "gn:asciiname":"Xiazhuang",
    "gn:country_code":"CN",
    "gn:dem":585,
    "gn:feature_class":"P",
    "gn:feature_code":"PPL",
    "gn:name":"Xiazhuang",
    "gn:population":0,
    "gn:timezone":"Asia/Shanghai",
    "iso:country":"CN",
    "name:deu_x_preferred":[
        "Xiazhuang"
    ],
    "name:und_x_variant":[
        "Hsia-chuang",
        "Xiazhuang"
    ],
    "name:zho_x_preferred":[
        "\u4e0b\u5e84"
    ],
    "wof:name":"Xiazhuang",
    "wof:placetype":"locality"
},
  "geometry": {"coordinates":[113.34661,38.41339],"type":"Point"}
}