{
  "type": "Feature",
  "properties": {
    "gn:admin1_code":"18",
    "gn:asciiname":"Chenjia Wuji",
    "gn:country_code":"CN",
    "gn:dem":874,
    "gn:feature_class":"P",
    "gn:feature_code":"PPL",
    "gn:name":"Chenjia Wuji",
    "gn:population":0,
    "gn:timezone":"Asia/Shanghai",
    "iso:country":"CN",
    "name:zho_x_preferred":[
        "\u9648\u5bb6\u5c4b\u57fa"
    ],
    "wof:name":"Chenjia Wuji",
    "wof:placetype":"locality"
},
  "geometry": {"coordinates":[108.221,27.225],"type":"Point"}
}