{
  "type": "Feature",
  "properties": {
    "gn:admin1_code":"14.0",
    "gn:asciiname":"Luolong",
    "gn:country_code":"CN",
    "gn:dem":2933,
    "gn:feature_class":"P",
    "gn:feature_code":"PPL",
    "gn:name":"Luolong",
    "gn:population":0,
    "gn:timezone":"Asia/Urumqi",
    "iso:country":"CN",
    "name:zho_x_preferred":[
        "\u7f57\u9f99"
    ],
    "wof:name":"Luolong",
    "wof:placetype":"locality"
},
  "geometry": {"coordinates":[98.96643,29.68261],"type":"Point"}
}