{
  "type": "Feature",
  "properties": {
    "gn:admin1_code":"11",
    "gn:asciiname":"Liangjiatan",
    "gn:country_code":"CN",
    "gn:dem":211,
    "gn:feature_class":"P",
    "gn:feature_code":"PPL",
    "gn:name":"Liangjiatan",
    "gn:population":0,
    "gn:timezone":"Asia/Shanghai",
    "iso:country":"CN",
    "wof:name":"Liangjiatan",
    "wof:placetype":"locality"
},
  "geometry": {"coordinates":[110.03333000000001,28.33333],"type":"Point"}
}