{
  "type": "Feature",
  "properties": {
    "gn:admin1_code":"29.0",
    "gn:asciiname":"Zuomushu",
    "gn:country_code":"CN",
    "gn:dem":1547,
    "gn:feature_class":"P",
    "gn:feature_code":"PPL",
    "gn:name":"Zuomushu",
    "gn:population":0,
    "gn:timezone":"Asia/Shanghai",
    "iso:country":"CN",
    "name:zho_x_preferred":[
        "\u67de\u6728\u6811"
    ],
    "wof:name":"Zuomushu",
    "wof:placetype":"locality"
},
  "geometry": {"coordinates":[98.66160000000001,25.1676],"type":"Point"}
}