{
  "type": "Feature",
  "properties": {
    "gn:admin1_code":"15.0",
    "gn:asciiname":"Shangmengjiagou",
    "gn:country_code":"CN",
    "gn:dem":1843,
    "gn:feature_class":"P",
    "gn:feature_code":"PPL",
    "gn:name":"Shangmengjiagou",
    "gn:population":0,
    "gn:timezone":"Asia/Shanghai",
    "iso:country":"CN",
    "name:zho_x_preferred":[
        "\u4e0a\u8499\u5bb6\u6c9f"
    ],
    "wof:name":"Shangmengjiagou",
    "wof:placetype":"locality"
},
  "geometry": {"coordinates":[104.98099999999999,36.9241],"type":"Point"}
}