{
  "type": "Feature",
  "properties": {
    "gn:admin1_code":"18",
    "gn:asciiname":"Xinlongtian",
    "gn:country_code":"CN",
    "gn:dem":655,
    "gn:feature_class":"P",
    "gn:feature_code":"PPL",
    "gn:name":"Xinlongtian",
    "gn:population":0,
    "gn:timezone":"Asia/Shanghai",
    "iso:country":"CN",
    "name:zho_x_preferred":[
        "\u65b0\u9f99\u7530"
    ],
    "wof:name":"Xinlongtian",
    "wof:placetype":"locality"
},
  "geometry": {"coordinates":[105.83799999999999,28.5845],"type":"Point"}
}