{
  "type": "Feature",
  "properties": {
    "gn:admin1_code":"15.0",
    "gn:asciiname":"Bianwaitou",
    "gn:country_code":"CN",
    "gn:dem":1595,
    "gn:feature_class":"P",
    "gn:feature_code":"PPL",
    "gn:name":"Bianwaitou",
    "gn:population":0,
    "gn:timezone":"Asia/Shanghai",
    "iso:country":"CN",
    "name:zho_x_preferred":[
        "\u8fb9\u5916\u5934"
    ],
    "wof:name":"Bianwaitou",
    "wof:placetype":"locality"
},
  "geometry": {"coordinates":[102.20999999999999,38.4542],"type":"Point"}
}