{
  "type": "Feature",
  "properties": {
    "gn:admin1_code":"16.0",
    "gn:asciiname":"Banjiang",
    "gn:country_code":"CN",
    "gn:dem":156,
    "gn:feature_class":"P",
    "gn:feature_code":"PPL",
    "gn:name":"Banjiang",
    "gn:population":0,
    "gn:timezone":"Asia/Shanghai",
    "iso:country":"CN",
    "name:zho_x_preferred":[
        "\u677f\u6c5f"
    ],
    "wof:name":"Banjiang",
    "wof:placetype":"locality"
},
  "geometry": {"coordinates":[108.65000000000001,23.9095],"type":"Point"}
}