{
  "type": "Feature",
  "properties": {
    "gn:admin1_code":"7.0",
    "gn:asciiname":"Chengji",
    "gn:country_code":"CN",
    "gn:dem":780,
    "gn:feature_class":"P",
    "gn:feature_code":"PPL",
    "gn:name":"Chengji",
    "gn:population":0,
    "gn:timezone":"Asia/Shanghai",
    "iso:country":"CN",
    "name:zho_x_preferred":[
        "Chengji"
    ],
    "name:zho_x_variant":[
        "\u7a0b\u6f08"
    ],
    "wof:name":"Chengji",
    "wof:placetype":"locality"
},
  "geometry": {"coordinates":[119.14028,26.71806],"type":"Point"}
}