{
  "type": "Feature",
  "properties": {
    "gn:admin1_code":"30.0",
    "gn:asciiname":"Silao",
    "gn:country_code":"CN",
    "gn:dem":40,
    "gn:feature_class":"P",
    "gn:feature_code":"PPL",
    "gn:name":"Silao",
    "gn:population":0,
    "gn:timezone":"Asia/Shanghai",
    "iso:country":"CN",
    "name:zho_x_preferred":[
        "\u601d\u52b3"
    ],
    "wof:name":"Silao",
    "wof:placetype":"locality"
},
  "geometry": {"coordinates":[112.23263,22.93312],"type":"Point"}
}