{
  "type": "Feature",
  "properties": {
    "gn:admin1_code":"30.0",
    "gn:asciiname":"Silao",
    "gn:country_code":"CN",
    "gn:dem":40,
    "gn:feature_class":"P",
    "gn:feature_code":"PPL",
    "gn:name":"Silao",
    "gn:population":0,
    "gn:timezone":"Asia/Shanghai",
    "iso:country":"CN",
    "name:ceb_x_preferred":[
        "Silao"
    ],
    "name:fas_x_preferred":[
        "\u0633\u06cc\u0644\u0627\u0648"
    ],
    "name:fra_x_preferred":[
        "Silao"
    ],
    "name:hun_x_preferred":[
        "Silao"
    ],
    "name:ita_x_preferred":[
        "Silao"
    ],
    "name:mlg_x_preferred":[
        "Silao"
    ],
    "name:por_x_preferred":[
        "Silao"
    ],
    "name:rus_x_preferred":[
        "\u0421\u0438\u043b\u0430\u043e"
    ],
    "name:spa_x_preferred":[
        "Silao"
    ],
    "name:srp_x_preferred":[
        "\u0421\u0438\u043b\u0430\u043e"
    ],
    "name:swe_x_preferred":[
        "Silao"
    ],
    "name:zho_x_preferred":[
        "\u601d\u52b3"
    ],
    "wof:name":"Silao",
    "wof:placetype":"locality"
},
  "geometry": {"coordinates":[112.23263,22.93312],"type":"Point"}
}