{
  "type": "Feature",
  "properties": {
    "gn:admin1_code":"4.0",
    "gn:asciiname":"Xinken Yizu",
    "gn:country_code":"CN",
    "gn:dem":1,
    "gn:feature_class":"P",
    "gn:feature_code":"PPLF",
    "gn:name":"Xinken Yizu",
    "gn:population":0,
    "gn:timezone":"Asia/Shanghai",
    "iso:country":"CN",
    "name:zho_x_preferred":[
        "Xinken Yizu"
    ],
    "name:zho_x_variant":[
        "\u65b0\u57a6\u4e00\u7ec4"
    ],
    "wof:name":"Xinken Yizu",
    "wof:placetype":"locality"
},
  "geometry": {"coordinates":[119.53538,34.35841],"type":"Point"}
}