{
  "type": "Feature",
  "properties": {
    "gn:admin1_code":"14.0",
    "gn:asciiname":"Karuduo",
    "gn:country_code":"CN",
    "gn:dem":4041,
    "gn:feature_class":"P",
    "gn:feature_code":"PPL",
    "gn:name":"Karuduo",
    "gn:population":0,
    "gn:timezone":"Asia/Urumqi",
    "iso:country":"CN",
    "name:zho_x_preferred":[
        "\u5361\u5982\u591a"
    ],
    "wof:name":"Karuduo",
    "wof:placetype":"locality"
},
  "geometry": {"coordinates":[91.63751000000001,30.04348],"type":"Point"}
}