{
  "type": "Feature",
  "properties": {
    "gn:admin1_code":"4.0",
    "gn:asciiname":"Xiajiadun",
    "gn:country_code":"CN",
    "gn:dem":-1,
    "gn:feature_class":"P",
    "gn:feature_code":"PPL",
    "gn:name":"Xiajiadun",
    "gn:population":0,
    "gn:timezone":"Asia/Shanghai",
    "iso:country":"CN",
    "name:zho_x_preferred":[
        "\u590f\u5bb6\u58a9"
    ],
    "wof:name":"Xiajiadun",
    "wof:placetype":"locality"
},
  "geometry": {"coordinates":[120.255,33.8029],"type":"Point"}
}