{
  "type": "Feature",
  "properties": {
    "gn:admin1_code":"3.0",
    "gn:asciiname":"Diaozikeng",
    "gn:country_code":"CN",
    "gn:dem":254,
    "gn:feature_class":"P",
    "gn:feature_code":"PPL",
    "gn:name":"Diaozikeng",
    "gn:population":0,
    "gn:timezone":"Asia/Shanghai",
    "iso:country":"CN",
    "name:und_x_variant":[
        "\u5201\u5b50\u5751"
    ],
    "wof:name":"Diaozikeng",
    "wof:placetype":"locality"
},
  "geometry": {"coordinates":[115.68376000000001,24.7938],"type":"Point"}
}