{
  "type": "Feature",
  "properties": {
    "gn:admin1_code":"21.0",
    "gn:asciiname":"Dahuodian",
    "gn:country_code":"CN",
    "gn:dem":1400,
    "gn:feature_class":"P",
    "gn:feature_code":"PPL",
    "gn:name":"Dahuodian",
    "gn:population":0,
    "gn:timezone":"Asia/Shanghai",
    "iso:country":"CN",
    "name:zho_x_preferred":[
        "\u5927\u4f19\u5e97"
    ],
    "wof:name":"Dahuodian",
    "wof:placetype":"locality"
},
  "geometry": {"coordinates":[107.313,37.1196],"type":"Point"}
}