{
  "type": "Feature",
  "properties": {
    "gn:admin1_code":"9",
    "gn:asciiname":"Mengguo",
    "gn:country_code":"CN",
    "gn:dem":50,
    "gn:feature_class":"P",
    "gn:feature_code":"PPL",
    "gn:name":"Mengguo",
    "gn:population":0,
    "gn:timezone":"Asia/Shanghai",
    "iso:country":"CN",
    "name:zho_x_preferred":[
        "\u5b5f\u90ed"
    ],
    "wof:name":"Mengguo",
    "wof:placetype":"locality"
},
  "geometry": {"coordinates":[115.25942000000001,36.14395],"type":"Point"}
}