{
  "type": "Feature",
  "properties": {
    "gn:admin1_code":"29.0",
    "gn:asciiname":"Mugulan Dacun",
    "gn:country_code":"CN",
    "gn:dem":1631,
    "gn:feature_class":"P",
    "gn:feature_code":"PPL",
    "gn:name":"Mugulan Dacun",
    "gn:population":0,
    "gn:timezone":"Asia/Shanghai",
    "iso:country":"CN",
    "name:zho_x_preferred":[
        "\u6728\u53e4\u5170\u5927\u6751"
    ],
    "wof:name":"Mugulan Dacun",
    "wof:placetype":"locality"
},
  "geometry": {"coordinates":[100.59099999999999,25.2406],"type":"Point"}
}