{
  "type": "Feature",
  "properties": {
    "gn:admin1_code":"2.0",
    "gn:asciiname":"Hengxiqiao",
    "gn:country_code":"CN",
    "gn:dem":41,
    "gn:feature_class":"P",
    "gn:feature_code":"PPL",
    "gn:name":"Hengxiqiao",
    "gn:population":0,
    "gn:timezone":"Asia/Shanghai",
    "iso:country":"CN",
    "name:und_x_variant":[
        "\u6a2a\u6eaa\u6865"
    ],
    "wof:name":"Hengxiqiao",
    "wof:placetype":"locality"
},
  "geometry": {"coordinates":[119.77495,30.18511],"type":"Point"}
}