{
  "type": "Feature",
  "properties": {
    "gn:admin1_code":"20",
    "gn:asciiname":"Salqin",
    "gn:cc2":"CN",
    "gn:country_code":"CN",
    "gn:dem":1067,
    "gn:feature_class":"P",
    "gn:feature_code":"PPL",
    "gn:name":"Salqin",
    "gn:population":0,
    "gn:timezone":"Asia/Shanghai",
    "iso:country":"CN",
    "name:ara_x_preferred":[
        "\u0633\u0644\u0642\u064a\u0646"
    ],
    "name:ceb_x_preferred":[
        "Salq\u012bn"
    ],
    "name:deu_x_preferred":[
        "Salqin"
    ],
    "name:fas_x_preferred":[
        "\u0633\u0644\u0642\u06cc\u0646"
    ],
    "name:hye_x_preferred":[
        "\u054d\u0561\u056c\u056f\u056b\u0576"
    ],
    "name:nno_x_preferred":[
        "Salqin"
    ],
    "name:pol_x_preferred":[
        "Salkin"
    ],
    "name:por_x_preferred":[
        "Salqin"
    ],
    "name:rus_x_preferred":[
        "\u0421\u0430\u043b\u044c\u043a\u0438\u043d"
    ],
    "name:swe_x_preferred":[
        "Salq\u012bn"
    ],
    "name:und_x_variant":[
        "Sharqin"
    ],
    "name:urd_x_preferred":[
        "\u0633\u0644\u0642\u06cc\u0646"
    ],
    "name:vie_x_preferred":[
        "Salqin"
    ],
    "name:zho_x_preferred":[
        "\u6c99\u52d2\u94a6"
    ],
    "wof:name":"Salqin",
    "wof:placetype":"locality"
},
  "geometry": {"coordinates":[111.73139,40.55833],"type":"Point"}
}