{
  "type": "Feature",
  "properties": {
    "gn:admin1_code":"20",
    "gn:asciiname":"Salqin",
    "gn:cc2":"CN",
    "gn:country_code":"CN",
    "gn:dem":1067,
    "gn:feature_class":"P",
    "gn:feature_code":"PPL",
    "gn:name":"Salqin",
    "gn:population":0,
    "gn:timezone":"Asia/Shanghai",
    "iso:country":"CN",
    "name:und_x_variant":[
        "Sharqin",
        "Salqin"
    ],
    "wof:name":"Salqin",
    "wof:placetype":"locality"
},
  "geometry": {"coordinates":[111.73139,40.55833],"type":"Point"}
}