{
  "type": "Feature",
  "properties": {
    "gn:admin1_code":"26.0",
    "gn:asciiname":"Lihuacun",
    "gn:country_code":"CN",
    "gn:dem":982,
    "gn:feature_class":"P",
    "gn:feature_code":"PPL",
    "gn:name":"Lihuacun",
    "gn:population":0,
    "gn:timezone":"Asia/Shanghai",
    "iso:country":"CN",
    "name:zho_x_preferred":[
        "\u68a8\u82b1\u6751"
    ],
    "wof:name":"Lihuacun",
    "wof:placetype":"locality"
},
  "geometry": {"coordinates":[109.82946,33.92012],"type":"Point"}
}