{
  "type": "Feature",
  "properties": {
    "gn:admin1_code":"4.0",
    "gn:asciiname":"Yuandaocun",
    "gn:country_code":"CN",
    "gn:dem":0,
    "gn:feature_class":"P",
    "gn:feature_code":"PPL",
    "gn:name":"Yuandaocun",
    "gn:population":0,
    "gn:timezone":"Asia/Shanghai",
    "iso:country":"CN",
    "name:zho_x_preferred":[
        "\u9662\u9053\u6751"
    ],
    "wof:name":"Yuandaocun",
    "wof:placetype":"locality"
},
  "geometry": {"coordinates":[119.92449999999999,33.59808],"type":"Point"}
}