{
  "type": "Feature",
  "properties": {
    "gn:admin1_code":"11.0",
    "gn:asciiname":"Ruidashu",
    "gn:country_code":"CN",
    "gn:dem":618,
    "gn:feature_class":"P",
    "gn:feature_code":"PPL",
    "gn:name":"Ruidashu",
    "gn:population":0,
    "gn:timezone":"Asia/Shanghai",
    "iso:country":"CN",
    "name:zho_x_preferred":[
        "\u745e\u5927\u6811"
    ],
    "wof:name":"Ruidashu",
    "wof:placetype":"locality"
},
  "geometry": {"coordinates":[109.85477,28.54982],"type":"Point"}
}