{
  "type": "Feature",
  "properties": {
    "gn:admin1_code":"14",
    "gn:asciiname":"Chaqiancun",
    "gn:country_code":"CN",
    "gn:dem":4685,
    "gn:feature_class":"P",
    "gn:feature_code":"PPL",
    "gn:name":"Chaqiancun",
    "gn:population":0,
    "gn:timezone":"Asia/Urumqi",
    "iso:country":"CN",
    "name:zho_x_preferred":[
        "\u67e5\u5343\u6751"
    ],
    "wof:name":"Chaqiancun",
    "wof:placetype":"locality"
},
  "geometry": {"coordinates":[88.2068,29.6339],"type":"Point"}
}