{
  "type": "Feature",
  "properties": {
    "gn:admin1_code":"11.0",
    "gn:asciiname":"Zongbao Shuijing",
    "gn:country_code":"CN",
    "gn:dem":622,
    "gn:feature_class":"P",
    "gn:feature_code":"PPL",
    "gn:name":"Zongbao Shuijing",
    "gn:population":0,
    "gn:timezone":"Asia/Shanghai",
    "iso:country":"CN",
    "name:zho_x_preferred":[
        "\u68d5\u5305\u6c34\u4e95"
    ],
    "wof:name":"Zongbao Shuijing",
    "wof:placetype":"locality"
},
  "geometry": {"coordinates":[110.18922000000001,29.68472],"type":"Point"}
}