{
  "type": "Feature",
  "properties": {
    "gn:admin1_code":"26.0",
    "gn:asciiname":"Chiniumaocun",
    "gn:country_code":"CN",
    "gn:dem":934,
    "gn:feature_class":"P",
    "gn:feature_code":"PPL",
    "gn:name":"Chiniumaocun",
    "gn:population":0,
    "gn:timezone":"Asia/Shanghai",
    "iso:country":"CN",
    "name:zho_x_preferred":[
        "\u8d64\u725b\u5cc1\u6751"
    ],
    "wof:name":"Chiniumaocun",
    "wof:placetype":"locality"
},
  "geometry": {"coordinates":[110.49038,37.89522],"type":"Point"}
}