{
  "type": "Feature",
  "properties": {
    "gn:admin1_code":"9.0",
    "gn:asciiname":"Banzhuang",
    "gn:country_code":"CN",
    "gn:dem":57,
    "gn:feature_class":"P",
    "gn:feature_code":"PPL",
    "gn:name":"Banzhuang",
    "gn:population":0,
    "gn:timezone":"Asia/Shanghai",
    "iso:country":"CN",
    "name:zho_x_preferred":[
        "\u73ed\u5e84"
    ],
    "name:zho_x_variant":[
        "\u73ed\u5e84\u9547"
    ],
    "wof:name":"Banzhuang",
    "wof:placetype":"locality"
},
  "geometry": {"coordinates":[114.36313,33.2809],"type":"Point"}
}