{
  "type": "Feature",
  "properties": {
    "gn:admin1_code":"15.0",
    "gn:asciiname":"Dexi",
    "gn:country_code":"CN",
    "gn:dem":2326,
    "gn:feature_class":"P",
    "gn:feature_code":"PPL",
    "gn:name":"Dexi",
    "gn:population":0,
    "gn:timezone":"Asia/Shanghai",
    "iso:country":"CN",
    "name:und_x_variant":[
        "\u7684\u897f"
    ],
    "wof:name":"Dexi",
    "wof:placetype":"locality"
},
  "geometry": {"coordinates":[104.08132999999999,34.47879],"type":"Point"}
}