{
  "type": "Feature",
  "properties": {
    "gn:admin1_code":"09",
    "gn:asciiname":"Ruyang Chengguanzhen",
    "gn:country_code":"CN",
    "gn:dem":321,
    "gn:feature_class":"P",
    "gn:feature_code":"PPLA3",
    "gn:name":"Ruyang Chengguanzhen",
    "gn:population":0,
    "gn:timezone":"Asia/Shanghai",
    "iso:country":"CN",
    "name:und_x_variant":[
        "Ju-yang",
        "I-yang-hsien",
        "I-yang",
        "Ruyang",
        "Ruyang Chengguanzhen"
    ],
    "name:zho_x_preferred":[
        "\u6c5d\u9633\u57ce\u5173\u9547"
    ],
    "wof:name":"Ruyang Chengguanzhen",
    "wof:placetype":"locality"
},
  "geometry": {"coordinates":[112.45833,34.15028],"type":"Point"}
}