{
  "type": "Feature",
  "properties": {
    "gn:admin1_code":"15.0",
    "gn:asciiname":"Suanjiayayao",
    "gn:country_code":"CN",
    "gn:dem":1229,
    "gn:feature_class":"P",
    "gn:feature_code":"PPL",
    "gn:name":"Suanjiayayao",
    "gn:population":0,
    "gn:timezone":"Asia/Shanghai",
    "iso:country":"CN",
    "name:zho_x_preferred":[
        "\u9178\u5bb6\u5d16\u7a91"
    ],
    "wof:name":"Suanjiayayao",
    "wof:placetype":"locality"
},
  "geometry": {"coordinates":[108.16200000000001,35.9573],"type":"Point"}
}