{
  "type": "Feature",
  "properties": {
    "gn:admin1_code":"24",
    "gn:asciiname":"Dongli",
    "gn:country_code":"CN",
    "gn:dem":807,
    "gn:feature_class":"P",
    "gn:feature_code":"PPL",
    "gn:name":"Dongli",
    "gn:population":0,
    "gn:timezone":"Asia/Shanghai",
    "iso:country":"CN",
    "name:ceb_x_preferred":[
        "Dongli"
    ],
    "name:zho_x_preferred":[
        "\u4e1c\u91cc"
    ],
    "wof:name":"Dongli",
    "wof:placetype":"locality"
},
  "geometry": {"coordinates":[112.33203,35.94202999999999],"type":"Point"}
}