{
  "type": "Feature",
  "properties": {
    "gn:admin1_code":"32.0",
    "gn:asciiname":"Juandongzi",
    "gn:country_code":"CN",
    "gn:dem":1551,
    "gn:feature_class":"P",
    "gn:feature_code":"PPL",
    "gn:name":"Juandongzi",
    "gn:population":0,
    "gn:timezone":"Asia/Shanghai",
    "iso:country":"CN",
    "name:zho_x_preferred":[
        "\u6372\u6d1e\u5b50"
    ],
    "name:zho_x_variant":[
        "\u5377\u6d1e\u5b50"
    ],
    "wof:name":"Juandongzi",
    "wof:placetype":"locality"
},
  "geometry": {"coordinates":[104.40029,32.26174],"type":"Point"}
}