{
  "type": "Feature",
  "properties": {
    "gn:admin1_code":"8.0",
    "gn:asciiname":"Chengxiangcun",
    "gn:country_code":"CN",
    "gn:dem":167,
    "gn:feature_class":"P",
    "gn:feature_code":"PPL",
    "gn:name":"Chengxiangcun",
    "gn:population":0,
    "gn:timezone":"Asia/Shanghai",
    "iso:country":"CN",
    "name:zho_x_preferred":[
        "\u8bda\u7965\u6751"
    ],
    "wof:name":"Chengxiangcun",
    "wof:placetype":"locality"
},
  "geometry": {"coordinates":[126.34049,45.34041],"type":"Point"}
}