{
  "type": "Feature",
  "properties": {
    "gn:admin1_code":"11",
    "gn:asciiname":"Qiaomuxia",
    "gn:country_code":"CN",
    "gn:dem":171,
    "gn:feature_class":"P",
    "gn:feature_code":"PPL",
    "gn:name":"Qiaomuxia",
    "gn:population":0,
    "gn:timezone":"Asia/Shanghai",
    "iso:country":"CN",
    "name:zho_x_preferred":[
        "\u6865\u6728\u4e0b"
    ],
    "wof:name":"Qiaomuxia",
    "wof:placetype":"locality"
},
  "geometry": {"coordinates":[112.20381999999999,26.45507000000001],"type":"Point"}
}