{
  "type": "Feature",
  "properties": {
    "gn:admin1_code":"11.0",
    "gn:asciiname":"Huangjinping",
    "gn:country_code":"CN",
    "gn:dem":248,
    "gn:feature_class":"P",
    "gn:feature_code":"PPL",
    "gn:name":"Huangjinping",
    "gn:population":0,
    "gn:timezone":"Asia/Shanghai",
    "iso:country":"CN",
    "name:zho_x_preferred":[
        "\u9ec4\u91d1\u576a"
    ],
    "wof:name":"Huangjinping",
    "wof:placetype":"locality"
},
  "geometry": {"coordinates":[113.33759999999999,28.65707],"type":"Point"}
}