{
  "type": "Feature",
  "properties": {
    "gn:admin1_code":"4.0",
    "gn:asciiname":"Guyuan",
    "gn:country_code":"CN",
    "gn:dem":0,
    "gn:feature_class":"P",
    "gn:feature_code":"PPL",
    "gn:name":"Guyuan",
    "gn:population":0,
    "gn:timezone":"Asia/Shanghai",
    "iso:country":"CN",
    "name:zho_x_preferred":[
        "\u80a1\u56ed"
    ],
    "wof:name":"Guyuan",
    "wof:placetype":"locality"
},
  "geometry": {"coordinates":[120.09967,33.5018],"type":"Point"}
}