{
  "type": "Feature",
  "properties": {
    "gn:admin1_code":"16.0",
    "gn:asciiname":"Baiyao",
    "gn:country_code":"CN",
    "gn:dem":299,
    "gn:feature_class":"P",
    "gn:feature_code":"PPL",
    "gn:name":"Baiyao",
    "gn:population":0,
    "gn:timezone":"Asia/Shanghai",
    "iso:country":"CN",
    "name:und_x_variant":[
        "Baime",
        "Baiyao"
    ],
    "name:zho_x_preferred":[
        "\u767e\u4e48"
    ],
    "wof:name":"Baiyao",
    "wof:placetype":"locality"
},
  "geometry": {"coordinates":[107.102,24.2994],"type":"Point"}
}