{
  "type": "Feature",
  "properties": {
    "gn:admin1_code":"8.0",
    "gn:asciiname":"Changshuihe Nongchang Sifenchang Changbu",
    "gn:country_code":"CN",
    "gn:dem":355,
    "gn:feature_class":"P",
    "gn:feature_code":"PPLF",
    "gn:name":"Changshuihe Nongchang Sifenchang Changbu",
    "gn:population":0,
    "gn:timezone":"Asia/Shanghai",
    "iso:country":"CN",
    "name:zho_x_preferred":[
        "\u957f\u6c34\u6cb3\u519c\u573a\u56db\u5206\u573a\u573a\u90e8"
    ],
    "wof:name":"Changshuihe Nongchang Sifenchang Changbu",
    "wof:placetype":"locality"
},
  "geometry": {"coordinates":[126.98097,48.32549],"type":"Point"}
}