{
  "type": "Feature",
  "properties": {
    "gn:admin1_code":"2",
    "gn:asciiname":"Huangshui",
    "gn:country_code":"CN",
    "gn:dem":128,
    "gn:feature_class":"P",
    "gn:feature_code":"PPL",
    "gn:name":"Huangshui",
    "gn:population":0,
    "gn:timezone":"Asia/Shanghai",
    "iso:country":"CN",
    "name:und_x_variant":[
        "Longxi",
        "Huangshui"
    ],
    "name:zho_x_preferred":[
        "\u9ec4\u6c34"
    ],
    "wof:name":"Huangshui",
    "wof:placetype":"locality"
},
  "geometry": {"coordinates":[120.79827,29.05133],"type":"Point"}
}