{
  "type": "Feature",
  "properties": {
    "gn:admin1_code":"19",
    "gn:asciiname":"Shangdoufufang",
    "gn:country_code":"CN",
    "gn:dem":628,
    "gn:feature_class":"P",
    "gn:feature_code":"PPL",
    "gn:name":"Shangdoufufang",
    "gn:population":0,
    "gn:timezone":"Asia/Shanghai",
    "iso:country":"CN",
    "name:zho_x_preferred":[
        "\u4e0a\u8c46\u8150\u623f"
    ],
    "wof:name":"Shangdoufufang",
    "wof:placetype":"locality"
},
  "geometry": {"coordinates":[119.827,41.5329],"type":"Point"}
}