{
  "type": "Feature",
  "properties": {
    "gn:admin1_code":"25",
    "gn:asciiname":"Lihewan",
    "gn:country_code":"CN",
    "gn:dem":38,
    "gn:feature_class":"P",
    "gn:feature_code":"PPL",
    "gn:name":"Lihewan",
    "gn:population":0,
    "gn:timezone":"Asia/Shanghai",
    "iso:country":"CN",
    "name:zho_x_preferred":[
        "\u674e\u6cb3\u6e7e"
    ],
    "wof:name":"Lihewan",
    "wof:placetype":"locality"
},
  "geometry": {"coordinates":[117.988,34.7456],"type":"Point"}
}