{
  "type": "Feature",
  "properties": {
    "gn:admin1_code":"26.0",
    "gn:asciiname":"Jinhutuocun",
    "gn:country_code":"CN",
    "gn:dem":485,
    "gn:feature_class":"P",
    "gn:feature_code":"PPL",
    "gn:name":"Jinhutuocun",
    "gn:population":0,
    "gn:timezone":"Asia/Shanghai",
    "iso:country":"CN",
    "name:zho_x_preferred":[
        "\u91d1\u4e4e\u6cb1\u6751"
    ],
    "wof:name":"Jinhutuocun",
    "wof:placetype":"locality"
},
  "geometry": {"coordinates":[108.96760999999999,34.18365],"type":"Point"}
}