{
  "type": "Feature",
  "properties": {
    "gn:admin1_code":"29.0",
    "gn:asciiname":"Changtoushang",
    "gn:country_code":"CN",
    "gn:dem":2120,
    "gn:feature_class":"P",
    "gn:feature_code":"PPL",
    "gn:name":"Changtoushang",
    "gn:population":0,
    "gn:timezone":"Asia/Shanghai",
    "iso:country":"CN",
    "name:zho_x_preferred":[
        "\u5382\u5934\u4e0a"
    ],
    "wof:name":"Changtoushang",
    "wof:placetype":"locality"
},
  "geometry": {"coordinates":[99.61369999999999,25.3978],"type":"Point"}
}