{
  "type": "Feature",
  "properties": {
    "gn:admin1_code":"32.0",
    "gn:asciiname":"Liziba",
    "gn:country_code":"CN",
    "gn:dem":453,
    "gn:feature_class":"P",
    "gn:feature_code":"PPL",
    "gn:name":"Liziba",
    "gn:population":0,
    "gn:timezone":"Asia/Shanghai",
    "iso:country":"CN",
    "name:zho_x_preferred":[
        "\u6817\u5b50\u575d"
    ],
    "wof:name":"Liziba",
    "wof:placetype":"locality"
},
  "geometry": {"coordinates":[104.09247000000001,28.61353],"type":"Point"}
}