{
  "type": "Feature",
  "properties": {
    "gn:admin1_code":"26.0",
    "gn:asciiname":"Guandiping",
    "gn:country_code":"CN",
    "gn:dem":1087,
    "gn:feature_class":"P",
    "gn:feature_code":"PPL",
    "gn:name":"Guandiping",
    "gn:population":0,
    "gn:timezone":"Asia/Shanghai",
    "iso:country":"CN",
    "name:und_x_variant":[
        "\u5b98\u5730\u576a"
    ],
    "wof:name":"Guandiping",
    "wof:placetype":"locality"
},
  "geometry": {"coordinates":[107.38449,33.3836],"type":"Point"}
}