{
  "type": "Feature",
  "properties": {
    "gn:admin1_code":"30",
    "gn:asciiname":"Paotai",
    "gn:country_code":"CN",
    "gn:dem":10,
    "gn:feature_class":"P",
    "gn:feature_code":"PPLA4",
    "gn:name":"Paotai",
    "gn:population":0,
    "gn:timezone":"Asia/Shanghai",
    "iso:country":"CN",
    "name:und_x_variant":[
        "\u70ae\u53f0",
        "Paotai Zhen",
        "\u70ae\u53f0\u9547"
    ],
    "wof:name":"Paotai",
    "wof:placetype":"locality"
},
  "geometry": {"coordinates":[116.49553,23.52223],"type":"Point"}
}