{
  "type": "Feature",
  "properties": {
    "gn:admin1_code":"3.0",
    "gn:asciiname":"Guzhuping",
    "gn:country_code":"CN",
    "gn:dem":167,
    "gn:feature_class":"P",
    "gn:feature_code":"PPL",
    "gn:name":"Guzhuping",
    "gn:population":0,
    "gn:timezone":"Asia/Shanghai",
    "iso:country":"CN",
    "name:und_x_variant":[
        "\u53e4\u7af9\u576a"
    ],
    "wof:name":"Guzhuping",
    "wof:placetype":"locality"
},
  "geometry": {"coordinates":[116.9362,27.47716],"type":"Point"}
}