{
  "type": "Feature",
  "properties": {
    "gn:admin1_code":"22.0",
    "gn:asciiname":"Qinglintaicun",
    "gn:country_code":"CN",
    "gn:dem":509,
    "gn:feature_class":"P",
    "gn:feature_code":"PPL",
    "gn:name":"Qinglintaicun",
    "gn:population":0,
    "gn:timezone":"Asia/Shanghai",
    "iso:country":"CN",
    "name:zho_x_preferred":[
        "\u9752\u6797\u53f0\u6751"
    ],
    "wof:name":"Qinglintaicun",
    "wof:placetype":"locality"
},
  "geometry": {"coordinates":[115.68631000000001,39.84609],"type":"Point"}
}