{
  "type": "Feature",
  "properties": {
    "gn:admin1_code":"24.0",
    "gn:asciiname":"Xinjintuan",
    "gn:country_code":"CN",
    "gn:dem":1039,
    "gn:feature_class":"P",
    "gn:feature_code":"PPL",
    "gn:name":"Xinjintuan",
    "gn:population":0,
    "gn:timezone":"Asia/Shanghai",
    "iso:country":"CN",
    "name:zho_x_preferred":[
        "\u65b0\u8fdb\u7583"
    ],
    "wof:name":"Xinjintuan",
    "wof:placetype":"locality"
},
  "geometry": {"coordinates":[112.69832,39.33962],"type":"Point"}
}