{
  "type": "Feature",
  "properties": {
    "gn:admin1_code":"32.0",
    "gn:asciiname":"Lakeluo",
    "gn:country_code":"CN",
    "gn:dem":2699,
    "gn:feature_class":"P",
    "gn:feature_code":"PPL",
    "gn:name":"Lakeluo",
    "gn:population":0,
    "gn:timezone":"Asia/Shanghai",
    "iso:country":"CN",
    "name:zho_x_preferred":[
        "\u62c9\u514b\u6d1b"
    ],
    "wof:name":"Lakeluo",
    "wof:placetype":"locality"
},
  "geometry": {"coordinates":[102.55489,28.38451],"type":"Point"}
}