{
  "type": "Feature",
  "properties": {
    "gn:admin1_code":"26.0",
    "gn:asciiname":"Luyuan",
    "gn:country_code":"CN",
    "gn:dem":1459,
    "gn:feature_class":"P",
    "gn:feature_code":"PPL",
    "gn:name":"Luyuan",
    "gn:population":0,
    "gn:timezone":"Asia/Shanghai",
    "iso:country":"CN",
    "name:zho_x_preferred":[
        "\u7089\u9662"
    ],
    "wof:name":"Luyuan",
    "wof:placetype":"locality"
},
  "geometry": {"coordinates":[110.47458,34.37582],"type":"Point"}
}