{
  "type": "Feature",
  "properties": {
    "gn:admin1_code":"11.0",
    "gn:asciiname":"Dongchongwan",
    "gn:country_code":"CN",
    "gn:dem":327,
    "gn:feature_class":"P",
    "gn:feature_code":"PPL",
    "gn:name":"Dongchongwan",
    "gn:population":0,
    "gn:timezone":"Asia/Shanghai",
    "iso:country":"CN",
    "name:zho_x_preferred":[
        "\u4e1c\u51b2\u6e7e"
    ],
    "wof:name":"Dongchongwan",
    "wof:placetype":"locality"
},
  "geometry": {"coordinates":[109.6956,26.6408],"type":"Point"}
}