{
  "type": "Feature",
  "properties": {
    "gn:admin1_code":"1.0",
    "gn:asciiname":"Fenhongcun",
    "gn:country_code":"CN",
    "gn:dem":30,
    "gn:feature_class":"P",
    "gn:feature_code":"PPL",
    "gn:name":"Fenhongcun",
    "gn:population":0,
    "gn:timezone":"Asia/Shanghai",
    "iso:country":"CN",
    "name:zho_x_preferred":[
        "\u5206\u6d2a\u6751"
    ],
    "wof:name":"Fenhongcun",
    "wof:placetype":"locality"
},
  "geometry": {"coordinates":[115.61362,32.45055],"type":"Point"}
}