{
  "type": "Feature",
  "properties": {
    "gn:admin1_code":"5.0",
    "gn:asciiname":"Xiawazihe Nancun",
    "gn:country_code":"CN",
    "gn:dem":182,
    "gn:feature_class":"P",
    "gn:feature_code":"PPL",
    "gn:name":"Xiawazihe Nancun",
    "gn:population":0,
    "gn:timezone":"Asia/Shanghai",
    "iso:country":"CN",
    "name:zho_x_preferred":[
        "\u4e0b\u6d3c\u5b50\u6cb3\u5357\u6751"
    ],
    "wof:name":"Xiawazihe Nancun",
    "wof:placetype":"locality"
},
  "geometry": {"coordinates":[126.43119,43.97349000000001],"type":"Point"}
}