{
  "type": "Feature",
  "properties": {
    "gn:admin1_code":"24.0",
    "gn:asciiname":"Bujiatuncun",
    "gn:country_code":"CN",
    "gn:dem":1028,
    "gn:feature_class":"P",
    "gn:feature_code":"PPL",
    "gn:name":"Bujiatuncun",
    "gn:population":0,
    "gn:timezone":"Asia/Shanghai",
    "iso:country":"CN",
    "name:zho_x_preferred":[
        "\u9c8d\u5bb6\u5c6f\u6751"
    ],
    "wof:name":"Bujiatuncun",
    "wof:placetype":"locality"
},
  "geometry": {"coordinates":[114.13387,40.42419],"type":"Point"}
}