{
  "type": "Feature",
  "properties": {
    "gn:admin1_code":"29.0",
    "gn:asciiname":"Zhaokala",
    "gn:country_code":"CN",
    "gn:dem":1769,
    "gn:feature_class":"P",
    "gn:feature_code":"PPL",
    "gn:name":"Zhaokala",
    "gn:population":0,
    "gn:timezone":"Asia/Shanghai",
    "iso:country":"CN",
    "name:zho_x_preferred":[
        "\u8d75\u5361\u62c9"
    ],
    "wof:name":"Zhaokala",
    "wof:placetype":"locality"
},
  "geometry": {"coordinates":[100.84,26.1039],"type":"Point"}
}