{
  "type": "Feature",
  "properties": {
    "gn:admin1_code":"18",
    "gn:asciiname":"Shanmuya",
    "gn:country_code":"CN",
    "gn:dem":1326,
    "gn:feature_class":"P",
    "gn:feature_code":"PPL",
    "gn:name":"Shanmuya",
    "gn:population":0,
    "gn:timezone":"Asia/Shanghai",
    "iso:country":"CN",
    "name:zho_x_preferred":[
        "\u5c71\u6728\u57ad"
    ],
    "wof:name":"Shanmuya",
    "wof:placetype":"locality"
},
  "geometry": {"coordinates":[106.51300000000001,27.7812],"type":"Point"}
}