{
  "type": "Feature",
  "properties": {
    "gn:admin1_code":"29.0",
    "gn:asciiname":"Yongguang",
    "gn:country_code":"CN",
    "gn:dem":1655,
    "gn:feature_class":"P",
    "gn:feature_code":"PPL",
    "gn:name":"Yongguang",
    "gn:population":0,
    "gn:timezone":"Asia/Shanghai",
    "iso:country":"CN",
    "name:zho_x_preferred":[
        "\u6c38\u5e7f"
    ],
    "wof:name":"Yongguang",
    "wof:placetype":"locality"
},
  "geometry": {"coordinates":[99.5934,23.1654],"type":"Point"}
}