{
  "type": "Feature",
  "properties": {
    "gn:admin1_code":"19.0",
    "gn:asciiname":"Dongdayingzi",
    "gn:country_code":"CN",
    "gn:dem":128,
    "gn:feature_class":"P",
    "gn:feature_code":"PPL",
    "gn:name":"Dongdayingzi",
    "gn:population":0,
    "gn:timezone":"Asia/Shanghai",
    "iso:country":"CN",
    "name:zho_x_preferred":[
        "\u4e1c\u5927\u8425\u5b50"
    ],
    "wof:name":"Dongdayingzi",
    "wof:placetype":"locality"
},
  "geometry": {"coordinates":[121.392,41.7881],"type":"Point"}
}