{
  "type": "Feature",
  "properties": {
    "gn:admin1_code":"19.0",
    "gn:asciiname":"Gutaizicun",
    "gn:country_code":"CN",
    "gn:dem":120,
    "gn:feature_class":"P",
    "gn:feature_code":"PPL",
    "gn:name":"Gutaizicun",
    "gn:population":0,
    "gn:timezone":"Asia/Shanghai",
    "iso:country":"CN",
    "name:zho_x_preferred":[
        "\u53e4\u53f0\u5b50\u6751"
    ],
    "wof:name":"Gutaizicun",
    "wof:placetype":"locality"
},
  "geometry": {"coordinates":[123.92458000000001,42.64545],"type":"Point"}
}