{
  "type": "Feature",
  "properties": {
    "gn:admin1_code":"29.0",
    "gn:asciiname":"Aciduo",
    "gn:country_code":"CN",
    "gn:dem":1463,
    "gn:feature_class":"P",
    "gn:feature_code":"PPL",
    "gn:name":"Aciduo",
    "gn:population":0,
    "gn:timezone":"Asia/Shanghai",
    "iso:country":"CN",
    "name:zho_x_preferred":[
        "\u963f\u6b64\u6735"
    ],
    "wof:name":"Aciduo",
    "wof:placetype":"locality"
},
  "geometry": {"coordinates":[99.5911,22.4622],"type":"Point"}
}