{
  "type": "Feature",
  "properties": {
    "gn:admin1_code":"20.0",
    "gn:asciiname":"Dapodi",
    "gn:country_code":"CN",
    "gn:dem":1296,
    "gn:feature_class":"P",
    "gn:feature_code":"PPL",
    "gn:name":"Dapodi",
    "gn:population":0,
    "gn:timezone":"Asia/Shanghai",
    "iso:country":"CN",
    "name:und_x_variant":[
        "\u5927\u5761\u5e95"
    ],
    "wof:name":"Dapodi",
    "wof:placetype":"locality"
},
  "geometry": {"coordinates":[113.70475,40.94716],"type":"Point"}
}