{
  "type": "Feature",
  "properties": {
    "gn:admin1_code":"19.0",
    "gn:asciiname":"Yabagou",
    "gn:country_code":"CN",
    "gn:dem":71,
    "gn:feature_class":"P",
    "gn:feature_code":"PPL",
    "gn:name":"Yabagou",
    "gn:population":0,
    "gn:timezone":"Asia/Shanghai",
    "iso:country":"CN",
    "name:zho_x_preferred":[
        "\u54d1\u53ed\u6c9f"
    ],
    "wof:name":"Yabagou",
    "wof:placetype":"locality"
},
  "geometry": {"coordinates":[122.54000000000001,39.8748],"type":"Point"}
}