{
  "type": "Feature",
  "properties": {
    "gn:admin1_code":"1.0",
    "gn:asciiname":"Mofancun",
    "gn:country_code":"CN",
    "gn:dem":349,
    "gn:feature_class":"P",
    "gn:feature_code":"PPL",
    "gn:name":"Mofancun",
    "gn:population":0,
    "gn:timezone":"Asia/Shanghai",
    "iso:country":"CN",
    "name:und_x_variant":[
        "Mofan"
    ],
    "name:zho_x_preferred":[
        "\u6a21\u8303\u6751"
    ],
    "name:zho_x_variant":[
        "\u6a21\u8303"
    ],
    "wof:name":"Mofancun",
    "wof:placetype":"locality"
},
  "geometry": {"coordinates":[118.45935,30.22667],"type":"Point"}
}