{
  "type": "Feature",
  "properties": {
    "gn:admin1_code":"7.0",
    "gn:asciiname":"Jinkeng",
    "gn:country_code":"CN",
    "gn:dem":386,
    "gn:feature_class":"P",
    "gn:feature_code":"PPL",
    "gn:name":"Jinkeng",
    "gn:population":0,
    "gn:timezone":"Asia/Shanghai",
    "iso:country":"CN",
    "name:und_x_variant":[
        "\u91d1\u5751"
    ],
    "name:zho_x_preferred":[
        "\u91d1\u5751"
    ],
    "wof:name":"Jinkeng",
    "wof:placetype":"locality"
},
  "geometry": {"coordinates":[117.28317,26.95544000000001],"type":"Point"}
}