{
  "type": "Feature",
  "properties": {
    "gn:admin1_code":"14",
    "gn:asciiname":"Benxab",
    "gn:country_code":"CN",
    "gn:dem":3425,
    "gn:feature_class":"P",
    "gn:feature_code":"PPL",
    "gn:name":"B\u00eanxab",
    "gn:population":0,
    "gn:timezone":"Asia/Urumqi",
    "iso:country":"CN",
    "name:bod_x_preferred":[
        "\u0f60\u0f56\u0f7a\u0f53\u0f0b\u0f5e\u0f56\u0f66"
    ],
    "wof:name":"Benxab",
    "wof:placetype":"locality"
},
  "geometry": {"coordinates":[91.19844999999999,28.18378],"type":"Point"}
}