{
  "type": "Feature",
  "properties": {
    "gn:admin1_code":"2.0",
    "gn:asciiname":"Qianxincun",
    "gn:country_code":"CN",
    "gn:dem":31,
    "gn:feature_class":"P",
    "gn:feature_code":"PPL",
    "gn:name":"Qianxincun",
    "gn:population":0,
    "gn:timezone":"Asia/Shanghai",
    "iso:country":"CN",
    "name:zho_x_preferred":[
        "\u524d\u65b0\u6751"
    ],
    "wof:name":"Qianxincun",
    "wof:placetype":"locality"
},
  "geometry": {"coordinates":[120.25566999999999,29.62603],"type":"Point"}
}