{
  "type": "Feature",
  "properties": {
    "gn:admin1_code":"2.0",
    "gn:asciiname":"Qianmei",
    "gn:country_code":"CN",
    "gn:dem":13,
    "gn:feature_class":"P",
    "gn:feature_code":"PPL",
    "gn:name":"Qianmei",
    "gn:population":0,
    "gn:timezone":"Asia/Shanghai",
    "iso:country":"CN",
    "name:und_x_variant":[
        "\u524d\u6885"
    ],
    "wof:name":"Qianmei",
    "wof:placetype":"locality"
},
  "geometry": {"coordinates":[120.3925,30.12123],"type":"Point"}
}