{
  "type": "Feature",
  "properties": {
    "gn:admin1_code":"14",
    "gn:asciiname":"Zhaxilin",
    "gn:country_code":"CN",
    "gn:dem":3862,
    "gn:feature_class":"P",
    "gn:feature_code":"PPL",
    "gn:name":"Zhaxilin",
    "gn:population":0,
    "gn:timezone":"Asia/Urumqi",
    "iso:country":"CN",
    "name:zho_x_preferred":[
        "\u624e\u897f\u6797"
    ],
    "wof:name":"Zhaxilin",
    "wof:placetype":"locality"
},
  "geometry": {"coordinates":[89.8135,29.3168],"type":"Point"}
}