{
  "type": "Feature",
  "properties": {
    "gn:admin1_code":"25.0",
    "gn:asciiname":"Yangjiazhuangcun",
    "gn:country_code":"CN",
    "gn:dem":21,
    "gn:feature_class":"P",
    "gn:feature_code":"PPL",
    "gn:name":"Yangjiazhuangcun",
    "gn:population":0,
    "gn:timezone":"Asia/Shanghai",
    "iso:country":"CN",
    "name:zho_x_preferred":[
        "\u6768\u5bb6\u5e84\u6751"
    ],
    "wof:name":"Yangjiazhuangcun",
    "wof:placetype":"locality"
},
  "geometry": {"coordinates":[121.58687999999999,37.45057],"type":"Point"}
}