{
  "type": "Feature",
  "properties": {
    "gn:admin1_code":"13",
    "gn:asciiname":"Majiazhang",
    "gn:country_code":"CN",
    "gn:dem":1011,
    "gn:feature_class":"P",
    "gn:feature_code":"PPL",
    "gn:name":"Majiazhang",
    "gn:population":0,
    "gn:timezone":"Asia/Urumqi",
    "iso:country":"CN",
    "name:zho_x_preferred":[
        "\u9a6c\u5bb6\u5e84"
    ],
    "wof:name":"Majiazhang",
    "wof:placetype":"locality"
},
  "geometry": {"coordinates":[87.33157,43.77211],"type":"Point"}
}