{
  "type": "Feature",
  "properties": {
    "gn:admin1_code":"16.0",
    "gn:asciiname":"Rongdong",
    "gn:country_code":"CN",
    "gn:dem":314,
    "gn:feature_class":"P",
    "gn:feature_code":"PPL",
    "gn:name":"Rongdong",
    "gn:population":0,
    "gn:timezone":"Asia/Shanghai",
    "iso:country":"CN",
    "name:zho_x_preferred":[
        "\u6995\u6d1e"
    ],
    "wof:name":"Rongdong",
    "wof:placetype":"locality"
},
  "geometry": {"coordinates":[110.437,24.3422],"type":"Point"}
}