{
  "type": "Feature",
  "properties": {
    "gn:admin1_code":"19.0",
    "gn:asciiname":"Pijiabucun",
    "gn:country_code":"CN",
    "gn:dem":10,
    "gn:feature_class":"P",
    "gn:feature_code":"PPL",
    "gn:name":"Pijiabucun",
    "gn:population":0,
    "gn:timezone":"Asia/Shanghai",
    "iso:country":"CN",
    "name:zho_x_preferred":[
        "\u76ae\u5bb6\u5821\u6751"
    ],
    "wof:name":"Pijiabucun",
    "wof:placetype":"locality"
},
  "geometry": {"coordinates":[122.91161,41.67969],"type":"Point"}
}