{
  "type": "Feature",
  "properties": {
    "gn:admin1_code":"26.0",
    "gn:asciiname":"Ma'anlingcun",
    "gn:country_code":"CN",
    "gn:dem":1377,
    "gn:feature_class":"P",
    "gn:feature_code":"PPL",
    "gn:name":"Ma\u2019anlingcun",
    "gn:population":0,
    "gn:timezone":"Asia/Shanghai",
    "iso:country":"CN",
    "name:und_x_variant":[
        "Ma\u2019anlingcun"
    ],
    "name:zho_x_preferred":[
        "\u9a6c\u978d\u5cad\u6751"
    ],
    "wof:name":"Ma'anlingcun",
    "wof:placetype":"locality"
},
  "geometry": {"coordinates":[109.57013000000001,33.74275],"type":"Point"}
}