{
  "type": "Feature",
  "properties": {
    "gn:admin1_code":"26.0",
    "gn:asciiname":"Da'erhe",
    "gn:country_code":"CN",
    "gn:dem":702,
    "gn:feature_class":"P",
    "gn:feature_code":"PPL",
    "gn:name":"Da\u2019erhe",
    "gn:population":0,
    "gn:timezone":"Asia/Shanghai",
    "iso:country":"CN",
    "name:und_x_variant":[
        "Da\u2019erhe"
    ],
    "name:zho_x_preferred":[
        "\u6253\u513f\u6cb3"
    ],
    "wof:name":"Da'erhe",
    "wof:placetype":"locality"
},
  "geometry": {"coordinates":[108.67528,33.95180999999999],"type":"Point"}
}