{
  "type": "Feature",
  "properties": {
    "gn:admin1_code":"9.0",
    "gn:asciiname":"Qincunying",
    "gn:country_code":"CN",
    "gn:dem":80,
    "gn:feature_class":"P",
    "gn:feature_code":"PPL",
    "gn:name":"Qincunying",
    "gn:population":0,
    "gn:timezone":"Asia/Shanghai",
    "iso:country":"CN",
    "name:zho_x_preferred":[
        "\u79e6\u6751\u8425"
    ],
    "wof:name":"Qincunying",
    "wof:placetype":"locality"
},
  "geometry": {"coordinates":[113.74755,35.20525],"type":"Point"}
}