{
  "type": "Feature",
  "properties": {
    "gn:admin1_code":"15.0",
    "gn:asciiname":"Zhangshan",
    "gn:country_code":"CN",
    "gn:dem":2000,
    "gn:feature_class":"P",
    "gn:feature_code":"PPL",
    "gn:name":"Zhangshan",
    "gn:population":0,
    "gn:timezone":"Asia/Shanghai",
    "iso:country":"CN",
    "name:zho_x_preferred":[
        "\u5f20\u5c71"
    ],
    "wof:name":"Zhangshan",
    "wof:placetype":"locality"
},
  "geometry": {"coordinates":[106.05,35.4949],"type":"Point"}
}