{
  "type": "Feature",
  "properties": {
    "gn:admin1_code":"32.0",
    "gn:asciiname":"Sali Xicun",
    "gn:country_code":"CN",
    "gn:dem":1924,
    "gn:feature_class":"P",
    "gn:feature_code":"PPL",
    "gn:name":"Sali Xicun",
    "gn:population":0,
    "gn:timezone":"Asia/Shanghai",
    "iso:country":"CN",
    "name:zho_x_preferred":[
        "\u6d12\u91cc\u897f\u6751"
    ],
    "wof:name":"Sali Xicun",
    "wof:placetype":"locality"
},
  "geometry": {"coordinates":[101.78400000000001,26.1984],"type":"Point"}
}