{
  "type": "Feature",
  "properties": {
    "gn:admin1_code":"26.0",
    "gn:asciiname":"Yixincun",
    "gn:country_code":"CN",
    "gn:dem":1016,
    "gn:feature_class":"P",
    "gn:feature_code":"PPL",
    "gn:name":"Yixincun",
    "gn:population":0,
    "gn:timezone":"Asia/Shanghai",
    "iso:country":"CN",
    "name:zho_x_preferred":[
        "\u4e00\u5fc3\u6751"
    ],
    "wof:name":"Yixincun",
    "wof:placetype":"locality"
},
  "geometry": {"coordinates":[108.68597,32.40065999999999],"type":"Point"}
}