{
  "type": "Feature",
  "properties": {
    "gn:admin1_code":"10",
    "gn:asciiname":"Liangjiazhuang",
    "gn:country_code":"CN",
    "gn:dem":1017,
    "gn:feature_class":"P",
    "gn:feature_code":"PPL",
    "gn:name":"Liangjiazhuang",
    "gn:population":0,
    "gn:timezone":"Asia/Shanghai",
    "iso:country":"CN",
    "name:und_x_variant":[
        "Liang-chia-chuang",
        "Liangjiazhuang"
    ],
    "name:zho_x_preferred":[
        "\u6881\u5bb6\u5e84"
    ],
    "wof:name":"Liangjiazhuang",
    "wof:placetype":"locality"
},
  "geometry": {"coordinates":[114.68153999999998,40.91771],"type":"Point"}
}