{
  "type": "Feature",
  "properties": {
    "gn:admin1_code":"25",
    "gn:asciiname":"Qianmingjia",
    "gn:country_code":"CN",
    "gn:dem":16,
    "gn:feature_class":"P",
    "gn:feature_code":"PPL",
    "gn:name":"Qianmingjia",
    "gn:population":0,
    "gn:timezone":"Asia/Shanghai",
    "iso:country":"CN",
    "name:zho_x_preferred":[
        "\u524d\u660e\u5bb6"
    ],
    "wof:name":"Qianmingjia",
    "wof:placetype":"locality"
},
  "geometry": {"coordinates":[116.94499999999999,37.5165],"type":"Point"}
}