{
  "type": "Feature",
  "properties": {
    "gn:admin1_code":"9.0",
    "gn:asciiname":"Mianshu'ao",
    "gn:country_code":"CN",
    "gn:dem":497,
    "gn:feature_class":"P",
    "gn:feature_code":"PPL",
    "gn:name":"Mianshu\u2019ao",
    "gn:population":0,
    "gn:timezone":"Asia/Shanghai",
    "iso:country":"CN",
    "name:und_x_variant":[
        "Mianshu\u2019ao"
    ],
    "name:zho_x_preferred":[
        "\u68c9\u6811\u51f9"
    ],
    "wof:name":"Mianshu'ao",
    "wof:placetype":"locality"
},
  "geometry": {"coordinates":[111.93374,33.40982],"type":"Point"}
}