{
  "type": "Feature",
  "properties": {
    "gn:admin1_code":"4.0",
    "gn:asciiname":"Guanwucun",
    "gn:country_code":"CN",
    "gn:dem":44,
    "gn:feature_class":"P",
    "gn:feature_code":"PPL",
    "gn:name":"Guanwucun",
    "gn:population":0,
    "gn:timezone":"Asia/Shanghai",
    "iso:country":"CN",
    "name:zho_x_preferred":[
        "\u89c2\u4e94\u6751"
    ],
    "wof:name":"Guanwucun",
    "wof:placetype":"locality"
},
  "geometry": {"coordinates":[119.00914,32.50676],"type":"Point"}
}