{
  "type": "Feature",
  "properties": {
    "gn:admin1_code":"32.0",
    "gn:asciiname":"Chengjiawo",
    "gn:country_code":"CN",
    "gn:dem":830,
    "gn:feature_class":"P",
    "gn:feature_code":"PPL",
    "gn:name":"Chengjiawo",
    "gn:population":0,
    "gn:timezone":"Asia/Shanghai",
    "iso:country":"CN",
    "name:zho_x_preferred":[
        "\u7a0b\u5bb6\u7a9d"
    ],
    "wof:name":"Chengjiawo",
    "wof:placetype":"locality"
},
  "geometry": {"coordinates":[102.80413,30.09987000000001],"type":"Point"}
}