{
  "type": "Feature",
  "properties": {
    "gn:admin1_code":"10",
    "gn:asciiname":"Niuzhazi",
    "gn:country_code":"CN",
    "gn:dem":1102,
    "gn:feature_class":"P",
    "gn:feature_code":"PPL",
    "gn:name":"Niuzhazi",
    "gn:population":0,
    "gn:timezone":"Asia/Shanghai",
    "iso:country":"CN",
    "name:zho_x_preferred":[
        "\u725b\u6805\u5b50"
    ],
    "wof:name":"Niuzhazi",
    "wof:placetype":"locality"
},
  "geometry": {"coordinates":[116.87645999999999,41.73005],"type":"Point"}
}