{
  "type": "Feature",
  "properties": {
    "gn:admin1_code":"30",
    "gn:asciiname":"Haishancun",
    "gn:country_code":"CN",
    "gn:dem":7,
    "gn:feature_class":"P",
    "gn:feature_code":"PPL",
    "gn:name":"Haishancun",
    "gn:population":0,
    "gn:timezone":"Asia/Urumqi",
    "iso:country":"CN",
    "name:zho_x_preferred":[
        "\u6d77\u5c71\u6751"
    ],
    "wof:name":"Haishancun",
    "wof:placetype":"locality"
},
  "geometry": {"coordinates":[109.73298,21.16255],"type":"Point"}
}