{
  "type": "Feature",
  "properties": {
    "gn:admin1_code":"16.0",
    "gn:asciiname":"Baimuchong",
    "gn:country_code":"CN",
    "gn:dem":51,
    "gn:feature_class":"P",
    "gn:feature_code":"PPL",
    "gn:name":"Baimuchong",
    "gn:population":0,
    "gn:timezone":"Asia/Shanghai",
    "iso:country":"CN",
    "name:zho_x_preferred":[
        "\u767d\u6728\u51b2"
    ],
    "wof:name":"Baimuchong",
    "wof:placetype":"locality"
},
  "geometry": {"coordinates":[109.764,23.1179],"type":"Point"}
}