{
  "type": "Feature",
  "properties": {
    "gn:admin1_code":"24.0",
    "gn:asciiname":"Zuotoucun",
    "gn:country_code":"CN",
    "gn:dem":896,
    "gn:feature_class":"P",
    "gn:feature_code":"PPL",
    "gn:name":"Zuotoucun",
    "gn:population":0,
    "gn:timezone":"Asia/Shanghai",
    "iso:country":"CN",
    "name:zho_x_preferred":[
        "\u4f5c\u5934\u6751"
    ],
    "wof:name":"Zuotoucun",
    "wof:placetype":"locality"
},
  "geometry": {"coordinates":[112.55851,38.43613],"type":"Point"}
}