{
  "type": "Feature",
  "properties": {
    "gn:admin1_code":"26.0",
    "gn:asciiname":"Xiao'ergou",
    "gn:country_code":"CN",
    "gn:dem":689,
    "gn:feature_class":"P",
    "gn:feature_code":"PPL",
    "gn:name":"Xiao\u2019ergou",
    "gn:population":0,
    "gn:timezone":"Asia/Shanghai",
    "iso:country":"CN",
    "name:und_x_variant":[
        "Xiao\u2019ergou"
    ],
    "name:zho_x_preferred":[
        "\u5c0f\u8033\u6c9f"
    ],
    "wof:name":"Xiao'ergou",
    "wof:placetype":"locality"
},
  "geometry": {"coordinates":[109.64239999999999,33.336],"type":"Point"}
}