{
  "type": "Feature",
  "properties": {
    "gn:admin1_code":"8.0",
    "gn:asciiname":"Hedongcun",
    "gn:country_code":"CN",
    "gn:dem":82,
    "gn:feature_class":"P",
    "gn:feature_code":"PPL",
    "gn:name":"Hedongcun",
    "gn:population":0,
    "gn:timezone":"Asia/Shanghai",
    "iso:country":"CN",
    "name:zho_x_preferred":[
        "\u6cb3\u4e1c\u6751"
    ],
    "wof:name":"Hedongcun",
    "wof:placetype":"locality"
},
  "geometry": {"coordinates":[133.17433,46.25962],"type":"Point"}
}