{
  "type": "Feature",
  "properties": {
    "gn:admin1_code":"29",
    "gn:asciiname":"Lutan",
    "gn:country_code":"CN",
    "gn:dem":1909,
    "gn:feature_class":"P",
    "gn:feature_code":"PPL",
    "gn:name":"Lutan",
    "gn:population":0,
    "gn:timezone":"Asia/Shanghai",
    "iso:country":"CN",
    "name:zho_x_preferred":[
        "\u82a6\u6f6d"
    ],
    "wof:name":"Lutan",
    "wof:placetype":"locality"
},
  "geometry": {"coordinates":[102.259,24.6727],"type":"Point"}
}