{
  "type": "Feature",
  "properties": {
    "gn:admin1_code":"26.0",
    "gn:asciiname":"Changgou",
    "gn:country_code":"CN",
    "gn:dem":660,
    "gn:feature_class":"P",
    "gn:feature_code":"PPL",
    "gn:name":"Changgou",
    "gn:population":0,
    "gn:timezone":"Asia/Shanghai",
    "iso:country":"CN",
    "name:und_x_variant":[
        "\u957f\u6c9f"
    ],
    "wof:name":"Changgou",
    "wof:placetype":"locality"
},
  "geometry": {"coordinates":[107.57953999999999,33.33728],"type":"Point"}
}