{
  "type": "Feature",
  "properties": {
    "gn:admin1_code":"19.0",
    "gn:asciiname":"Zhangbaotun",
    "gn:country_code":"CN",
    "gn:dem":43,
    "gn:feature_class":"P",
    "gn:feature_code":"PPL",
    "gn:name":"Zhangbaotun",
    "gn:population":0,
    "gn:timezone":"Asia/Shanghai",
    "iso:country":"CN",
    "name:und_x_variant":[
        "\u5f20\u5b9d\u5c6f"
    ],
    "name:zho_x_preferred":[
        "\u5f20\u5b9d\u5c6f"
    ],
    "wof:name":"Zhangbaotun",
    "wof:placetype":"locality"
},
  "geometry": {"coordinates":[122.76381000000001,42.08427],"type":"Point"}
}