{
  "type": "Feature",
  "properties": {
    "gn:admin1_code":"19",
    "gn:asciiname":"Jiaojiabaozi",
    "gn:cc2":"CN",
    "gn:country_code":"CN",
    "gn:dem":286,
    "gn:feature_class":"P",
    "gn:feature_code":"PPL",
    "gn:name":"Jiaojiabaozi",
    "gn:population":0,
    "gn:timezone":"Asia/Shanghai",
    "iso:country":"CN",
    "name:und_x_variant":[
        "Ta-p\u2019ao-tzu",
        "Jiaojiabaozi"
    ],
    "wof:name":"Jiaojiabaozi",
    "wof:placetype":"locality"
},
  "geometry": {"coordinates":[125.06139,41.01389],"type":"Point"}
}