{
  "type": "Feature",
  "properties": {
    "gn:admin1_code":"29.0",
    "gn:asciiname":"Shabacan",
    "gn:country_code":"CN",
    "gn:dem":2641,
    "gn:feature_class":"P",
    "gn:feature_code":"PPL",
    "gn:name":"Shabacan",
    "gn:population":0,
    "gn:timezone":"Asia/Shanghai",
    "iso:country":"CN",
    "name:zho_x_preferred":[
        "\u6c99\u5df4\u707f"
    ],
    "wof:name":"Shabacan",
    "wof:placetype":"locality"
},
  "geometry": {"coordinates":[99.48139999999999,27.4783],"type":"Point"}
}