{
  "type": "Feature",
  "properties": {
    "gn:admin1_code":"15.0",
    "gn:asciiname":"Yimen",
    "gn:country_code":"CN",
    "gn:dem":1429,
    "gn:feature_class":"P",
    "gn:feature_code":"PPL",
    "gn:name":"Yimen",
    "gn:population":0,
    "gn:timezone":"Asia/Shanghai",
    "iso:country":"CN",
    "name:und_x_variant":[
        "Yima"
    ],
    "name:zho_x_preferred":[
        "\u4e49\u95e8"
    ],
    "wof:name":"Yimen",
    "wof:placetype":"locality"
},
  "geometry": {"coordinates":[107.595,35.821],"type":"Point"}
}