{
  "type": "Feature",
  "properties": {
    "gn:admin1_code":"24.0",
    "gn:asciiname":"Huanangou",
    "gn:country_code":"CN",
    "gn:dem":1362,
    "gn:feature_class":"P",
    "gn:feature_code":"PPL",
    "gn:name":"Huanangou",
    "gn:population":0,
    "gn:timezone":"Asia/Shanghai",
    "iso:country":"CN",
    "name:zho_x_preferred":[
        "\u5316\u5357\u6c9f"
    ],
    "wof:name":"Huanangou",
    "wof:placetype":"locality"
},
  "geometry": {"coordinates":[113.75503,37.35109],"type":"Point"}
}