{
  "type": "Feature",
  "properties": {
    "gn:admin1_code":"15.0",
    "gn:asciiname":"Guan'er Xiacun",
    "gn:country_code":"CN",
    "gn:dem":1556,
    "gn:feature_class":"P",
    "gn:feature_code":"PPL",
    "gn:name":"Guan\u2019er Xiacun",
    "gn:population":0,
    "gn:timezone":"Asia/Shanghai",
    "iso:country":"CN",
    "name:und_x_variant":[
        "Guan\u2019er Xiacun"
    ],
    "name:zho_x_preferred":[
        "\u89c2\u513f\u4e0b\u6751"
    ],
    "wof:name":"Guan'er Xiacun",
    "wof:placetype":"locality"
},
  "geometry": {"coordinates":[105.02200000000001,34.679],"type":"Point"}
}