{
  "type": "Feature",
  "properties": {
    "gn:admin1_code":"9",
    "gn:asciiname":"Hanwan",
    "gn:country_code":"CN",
    "gn:dem":257,
    "gn:feature_class":"P",
    "gn:feature_code":"PPL",
    "gn:name":"Hanwan",
    "gn:population":0,
    "gn:timezone":"Asia/Shanghai",
    "iso:country":"CN",
    "name:und_x_variant":[
        "\u97e9\u6e7e",
        "Hanwan"
    ],
    "wof:name":"Hanwan",
    "wof:placetype":"locality"
},
  "geometry": {"coordinates":[112.73269000000001,33.69846],"type":"Point"}
}