{
  "type": "Feature",
  "properties": {
    "gn:admin1_code":"2.0",
    "gn:asciiname":"Tongjia'ao",
    "gn:country_code":"CN",
    "gn:dem":70,
    "gn:feature_class":"P",
    "gn:feature_code":"PPL",
    "gn:name":"Tongjia\u2019ao",
    "gn:population":0,
    "gn:timezone":"Asia/Shanghai",
    "iso:country":"CN",
    "name:und_x_variant":[
        "Tongjia\u2019ao",
        "\u7ae5\u5bb6\u5c99"
    ],
    "wof:name":"Tongjia'ao",
    "wof:placetype":"locality"
},
  "geometry": {"coordinates":[121.21826,30.08084],"type":"Point"}
}