{
  "type": "Feature",
  "properties": {
    "gn:admin1_code":"5.0",
    "gn:asciiname":"Hedong",
    "gn:country_code":"CN",
    "gn:dem":425,
    "gn:feature_class":"P",
    "gn:feature_code":"PPL",
    "gn:name":"Hedong",
    "gn:population":0,
    "gn:timezone":"Asia/Shanghai",
    "iso:country":"CN",
    "name:und_x_variant":[
        "\u6cb3\u4e1c",
        "Hedongcun",
        "\u6cb3\u4e1c\u6751"
    ],
    "wof:name":"Hedong",
    "wof:placetype":"locality"
},
  "geometry": {"coordinates":[128.99805000000001,42.56403],"type":"Point"}
}