{
  "type": "Feature",
  "properties": {
    "gn:admin1_code":"01",
    "gn:asciiname":"Guanlukou",
    "gn:cc2":"CN",
    "gn:country_code":"CN",
    "gn:dem":24,
    "gn:feature_class":"P",
    "gn:feature_code":"PPL",
    "gn:name":"Guanlukou",
    "gn:population":0,
    "gn:timezone":"Asia/Shanghai",
    "iso:country":"CN",
    "name:und_x_variant":[
        "Kuan-lu-k\u2019ou",
        "Guanlukou"
    ],
    "wof:name":"Guanlukou",
    "wof:placetype":"locality"
},
  "geometry": {"coordinates":[117.06667,33.25],"type":"Point"}
}