{
  "type": "Feature",
  "properties": {
    "gn:admin1_code":"19.0",
    "gn:asciiname":"Walinggou",
    "gn:country_code":"CN",
    "gn:dem":243,
    "gn:feature_class":"P",
    "gn:feature_code":"PPL",
    "gn:name":"Walinggou",
    "gn:population":0,
    "gn:timezone":"Asia/Shanghai",
    "iso:country":"CN",
    "name:zho_x_preferred":[
        "\u6d3c\u5cad\u6c9f"
    ],
    "wof:name":"Walinggou",
    "wof:placetype":"locality"
},
  "geometry": {"coordinates":[123.41785,40.72407000000001],"type":"Point"}
}