{
  "type": "Feature",
  "properties": {
    "gn:admin1_code":"12.0",
    "gn:asciiname":"Zhangjiayanzi",
    "gn:country_code":"CN",
    "gn:dem":508,
    "gn:feature_class":"P",
    "gn:feature_code":"PPL",
    "gn:name":"Zhangjiayanzi",
    "gn:population":0,
    "gn:timezone":"Asia/Shanghai",
    "iso:country":"CN",
    "name:zho_x_preferred":[
        "\u5f20\u5bb6\u5ca9\u5b50"
    ],
    "wof:name":"Zhangjiayanzi",
    "wof:placetype":"locality"
},
  "geometry": {"coordinates":[110.94972,30.36434],"type":"Point"}
}