{
  "type": "Feature",
  "properties": {
    "gn:admin1_code":"29.0",
    "gn:asciiname":"Suqing",
    "gn:country_code":"CN",
    "gn:dem":1098,
    "gn:feature_class":"P",
    "gn:feature_code":"PPL",
    "gn:name":"Suqing",
    "gn:population":0,
    "gn:timezone":"Asia/Shanghai",
    "iso:country":"CN",
    "name:zho_x_preferred":[
        "\u901f\u5e86"
    ],
    "wof:name":"Suqing",
    "wof:placetype":"locality"
},
  "geometry": {"coordinates":[98.4627,24.6836],"type":"Point"}
}