{
  "type": "Feature",
  "properties": {
    "gn:admin1_code":"19.0",
    "gn:asciiname":"Qiansandaowan",
    "gn:country_code":"CN",
    "gn:dem":7,
    "gn:feature_class":"P",
    "gn:feature_code":"PPL",
    "gn:name":"Qiansandaowan",
    "gn:population":0,
    "gn:timezone":"Asia/Shanghai",
    "iso:country":"CN",
    "name:zho_x_preferred":[
        "\u524d\u4e09\u9053\u6e7e"
    ],
    "wof:name":"Qiansandaowan",
    "wof:placetype":"locality"
},
  "geometry": {"coordinates":[121.753,39.338],"type":"Point"}
}