{
  "type": "Feature",
  "properties": {
    "gn:admin1_code":"25.0",
    "gn:asciiname":"Jiejiagou",
    "gn:country_code":"CN",
    "gn:dem":112,
    "gn:feature_class":"P",
    "gn:feature_code":"PPL",
    "gn:name":"Jiejiagou",
    "gn:population":0,
    "gn:timezone":"Asia/Shanghai",
    "iso:country":"CN",
    "name:zho_x_preferred":[
        "\u89e3\u5bb6\u6c9f"
    ],
    "wof:name":"Jiejiagou",
    "wof:placetype":"locality"
},
  "geometry": {"coordinates":[120.74812,37.14536],"type":"Point"}
}