{
  "type": "Feature",
  "properties": {
    "gn:admin1_code":"19.0",
    "gn:asciiname":"Chatiaogou",
    "gn:country_code":"CN",
    "gn:dem":202,
    "gn:feature_class":"P",
    "gn:feature_code":"PPL",
    "gn:name":"Chatiaogou",
    "gn:population":0,
    "gn:timezone":"Asia/Shanghai",
    "iso:country":"CN",
    "name:zho_x_preferred":[
        "\u8336\u6761\u6c9f"
    ],
    "wof:name":"Chatiaogou",
    "wof:placetype":"locality"
},
  "geometry": {"coordinates":[124.476,42.6838],"type":"Point"}
}