{
  "type": "Feature",
  "properties": {
    "gn:admin1_code":"26.0",
    "gn:asciiname":"Fuyangbeicun",
    "gn:country_code":"CN",
    "gn:dem":487,
    "gn:feature_class":"P",
    "gn:feature_code":"PPL",
    "gn:name":"Fuyangbeicun",
    "gn:population":0,
    "gn:timezone":"Asia/Shanghai",
    "iso:country":"CN",
    "name:zho_x_preferred":[
        "\u5e9c\u9633\u5317\u6751"
    ],
    "wof:name":"Fuyangbeicun",
    "wof:placetype":"locality"
},
  "geometry": {"coordinates":[108.66352000000001,34.3994],"type":"Point"}
}