{
  "type": "Feature",
  "properties": {
    "gn:admin1_code":"16.0",
    "gn:asciiname":"Shangmogu",
    "gn:country_code":"CN",
    "gn:dem":869,
    "gn:feature_class":"P",
    "gn:feature_code":"PPL",
    "gn:name":"Shangmogu",
    "gn:population":0,
    "gn:timezone":"Asia/Shanghai",
    "iso:country":"CN",
    "name:zho_x_preferred":[
        "\u4e0a\u83ab\u53e4"
    ],
    "wof:name":"Shangmogu",
    "wof:placetype":"locality"
},
  "geometry": {"coordinates":[105.95999999999999,23.4927],"type":"Point"}
}