{
  "type": "Feature",
  "properties": {
    "gn:admin1_code":"20.0",
    "gn:asciiname":"Lianghou",
    "gn:country_code":"CN",
    "gn:dem":377,
    "gn:feature_class":"P",
    "gn:feature_code":"PPL",
    "gn:name":"Lianghou",
    "gn:population":0,
    "gn:timezone":"Asia/Shanghai",
    "iso:country":"CN",
    "name:zho_x_preferred":[
        "\u6881\u540e"
    ],
    "wof:name":"Lianghou",
    "wof:placetype":"locality"
},
  "geometry": {"coordinates":[122.38781000000002,48.13462],"type":"Point"}
}