{
  "type": "Feature",
  "properties": {
    "gn:admin1_code":"7.0",
    "gn:asciiname":"Shuangtong",
    "gn:country_code":"CN",
    "gn:dem":745,
    "gn:feature_class":"P",
    "gn:feature_code":"PPL",
    "gn:name":"Shuangtong",
    "gn:population":0,
    "gn:timezone":"Asia/Shanghai",
    "iso:country":"CN",
    "name:zho_x_preferred":[
        "\u53cc\u540c"
    ],
    "wof:name":"Shuangtong",
    "wof:placetype":"locality"
},
  "geometry": {"coordinates":[118.75718999999999,27.91617],"type":"Point"}
}