{
  "type": "Feature",
  "properties": {
    "gn:admin1_code":"19.0",
    "gn:asciiname":"Guangdefu",
    "gn:country_code":"CN",
    "gn:dem":121,
    "gn:feature_class":"P",
    "gn:feature_code":"PPL",
    "gn:name":"Guangdefu",
    "gn:population":0,
    "gn:timezone":"Asia/Shanghai",
    "iso:country":"CN",
    "name:und_x_variant":[
        "\u5e7f\u5fb7\u798f"
    ],
    "name:zho_x_preferred":[
        "\u5e7f\u5fb7\u798f"
    ],
    "wof:name":"Guangdefu",
    "wof:placetype":"locality"
},
  "geometry": {"coordinates":[122.191,39.6179],"type":"Point"}
}