{
  "type": "Feature",
  "properties": {
    "gn:admin1_code":"3",
    "gn:asciiname":"Makou",
    "gn:country_code":"CN",
    "gn:dem":92,
    "gn:feature_class":"P",
    "gn:feature_code":"PPL",
    "gn:name":"Makou",
    "gn:population":0,
    "gn:timezone":"Asia/Shanghai",
    "iso:country":"CN",
    "name:und_x_variant":[
        "\u9a6c\u53e3"
    ],
    "wof:name":"Makou",
    "wof:placetype":"locality"
},
  "geometry": {"coordinates":[116.02227000000001,27.60871],"type":"Point"}
}