{
  "type": "Feature",
  "properties": {
    "gn:admin1_code":"7.0",
    "gn:asciiname":"Xiedi",
    "gn:country_code":"CN",
    "gn:dem":522,
    "gn:feature_class":"P",
    "gn:feature_code":"PPL",
    "gn:name":"Xiedi",
    "gn:population":0,
    "gn:timezone":"Asia/Shanghai",
    "iso:country":"CN",
    "name:und_x_variant":[
        "\u8c22\u5730"
    ],
    "name:zho_x_preferred":[
        "\u8c22\u5730"
    ],
    "wof:name":"Xiedi",
    "wof:placetype":"locality"
},
  "geometry": {"coordinates":[117.07567,26.40015],"type":"Point"}
}