{
  "type": "Feature",
  "properties": {
    "gn:admin1_code":"1.0",
    "gn:asciiname":"Caopitangcun",
    "gn:country_code":"CN",
    "gn:dem":33,
    "gn:feature_class":"P",
    "gn:feature_code":"PPL",
    "gn:name":"Caopitangcun",
    "gn:population":0,
    "gn:timezone":"Asia/Shanghai",
    "iso:country":"CN",
    "name:zho_x_preferred":[
        "\u8349\u76ae\u5858\u6751"
    ],
    "wof:name":"Caopitangcun",
    "wof:placetype":"locality"
},
  "geometry": {"coordinates":[116.72729,31.44733],"type":"Point"}
}