{
  "type": "Feature",
  "properties": {
    "gn:admin1_code":"25",
    "gn:asciiname":"Daliuxi",
    "gn:country_code":"CN",
    "gn:dem":30,
    "gn:feature_class":"P",
    "gn:feature_code":"PPL",
    "gn:name":"Daliuxi",
    "gn:population":0,
    "gn:timezone":"Asia/Shanghai",
    "iso:country":"CN",
    "name:zho_x_preferred":[
        "\u5927\u5218\u897f"
    ],
    "wof:name":"Daliuxi",
    "wof:placetype":"locality"
},
  "geometry": {"coordinates":[116.197,36.7102],"type":"Point"}
}