{
  "type": "Feature",
  "properties": {
    "gn:admin1_code":"11",
    "gn:asciiname":"Niucailing",
    "gn:country_code":"CN",
    "gn:dem":808,
    "gn:feature_class":"P",
    "gn:feature_code":"PPL",
    "gn:name":"Niucailing",
    "gn:population":0,
    "gn:timezone":"Asia/Shanghai",
    "iso:country":"CN",
    "name:zho_x_preferred":[
        "\u725b\u624d\u5cad"
    ],
    "wof:name":"Niucailing",
    "wof:placetype":"locality"
},
  "geometry": {"coordinates":[111.06391000000001,27.42162],"type":"Point"}
}