{
  "type": "Feature",
  "properties": {
    "gn:admin1_code":"22",
    "gn:asciiname":"Huanghuacheng",
    "gn:country_code":"CN",
    "gn:dem":235,
    "gn:feature_class":"P",
    "gn:feature_code":"PPL",
    "gn:name":"Huanghuacheng",
    "gn:population":0,
    "gn:timezone":"Asia/Shanghai",
    "iso:country":"CN",
    "name:zho_x_preferred":[
        "\u9ec4\u82b1\u57ce"
    ],
    "wof:name":"Huanghuacheng",
    "wof:placetype":"locality"
},
  "geometry": {"coordinates":[116.33871000000001,40.40832],"type":"Point"}
}