{
  "type": "Feature",
  "properties": {
    "gn:admin1_code":"22",
    "gn:asciiname":"Huanghuacheng",
    "gn:country_code":"CN",
    "gn:dem":235,
    "gn:feature_class":"P",
    "gn:feature_code":"PPL",
    "gn:name":"Huanghuacheng",
    "gn:population":0,
    "gn:timezone":"Asia/Shanghai",
    "iso:country":"CN",
    "name:ceb_x_preferred":[
        "Huanghuacheng"
    ],
    "name:fas_x_preferred":[
        "\u0647\u0648\u0627\u0646\u06af\u0647\u0648\u0627\u0686\u0646\u06af"
    ],
    "name:swe_x_preferred":[
        "Huanghuacheng"
    ],
    "name:urd_x_preferred":[
        "\u06c1\u0648\u0627\u0646\u06af\u06c1\u0648\u0627\u0686\u06cc\u0646\u06af"
    ],
    "name:zho_x_preferred":[
        "\u9ec4\u82b1\u57ce"
    ],
    "wof:name":"Huanghuacheng",
    "wof:placetype":"locality"
},
  "geometry": {"coordinates":[116.33871000000001,40.40832],"type":"Point"}
}