{
  "type": "Feature",
  "properties": {
    "gn:admin1_code":"12.0",
    "gn:asciiname":"Badui",
    "gn:country_code":"CN",
    "gn:dem":22,
    "gn:feature_class":"P",
    "gn:feature_code":"PPLF",
    "gn:name":"Badui",
    "gn:population":0,
    "gn:timezone":"Asia/Shanghai",
    "iso:country":"CN",
    "name:zho_x_preferred":[
        "\u516b\u961f"
    ],
    "wof:name":"Badui",
    "wof:placetype":"locality"
},
  "geometry": {"coordinates":[114.15836000000002,30.73543],"type":"Point"}
}