{
  "type": "Feature",
  "properties": {
    "gn:admin1_code":"30.0",
    "gn:asciiname":"Benkeng Xincun",
    "gn:country_code":"CN",
    "gn:dem":52,
    "gn:feature_class":"P",
    "gn:feature_code":"PPL",
    "gn:name":"Benkeng Xincun",
    "gn:population":0,
    "gn:timezone":"Asia/Urumqi",
    "iso:country":"CN",
    "name:zho_x_preferred":[
        "\u672c\u5751\u65b0\u6751"
    ],
    "wof:name":"Benkeng Xincun",
    "wof:placetype":"locality"
},
  "geometry": {"coordinates":[110.41846,20.43656],"type":"Point"}
}