{
  "type": "Feature",
  "properties": {
    "gn:admin1_code":"11",
    "gn:asciiname":"Fangshiping",
    "gn:country_code":"CN",
    "gn:dem":96,
    "gn:feature_class":"P",
    "gn:feature_code":"PPLA4",
    "gn:name":"Fangshiping",
    "gn:population":0,
    "gn:timezone":"Asia/Shanghai",
    "iso:country":"CN",
    "name:und_x_variant":[
        "\u65b9\u77f3\u576a",
        "Fangshiping Zhen",
        "\u65b9\u77f3\u576a\u9547"
    ],
    "wof:name":"Fangshiping",
    "wof:placetype":"locality"
},
  "geometry": {"coordinates":[111.43765,29.80104],"type":"Point"}
}