{
  "type": "Feature",
  "properties": {
    "gn:admin1_code":"25.0",
    "gn:asciiname":"Wengjiabucun",
    "gn:country_code":"CN",
    "gn:dem":13,
    "gn:feature_class":"P",
    "gn:feature_code":"PPL",
    "gn:name":"Wengjiabucun",
    "gn:population":0,
    "gn:timezone":"Asia/Shanghai",
    "iso:country":"CN",
    "name:zho_x_preferred":[
        "\u7fc1\u5bb6\u57e0\u6751"
    ],
    "wof:name":"Wengjiabucun",
    "wof:placetype":"locality"
},
  "geometry": {"coordinates":[121.60648999999999,36.84179],"type":"Point"}
}