{
  "type": "Feature",
  "properties": {
    "gn:admin1_code":"9.0",
    "gn:asciiname":"Tanggou",
    "gn:country_code":"CN",
    "gn:dem":411,
    "gn:feature_class":"P",
    "gn:feature_code":"PPL",
    "gn:name":"Tanggou",
    "gn:population":0,
    "gn:timezone":"Asia/Shanghai",
    "iso:country":"CN",
    "name:und_x_variant":[
        "\u5802\u6c9f",
        "Tanggou"
    ],
    "wof:name":"Tanggou",
    "wof:placetype":"locality"
},
  "geometry": {"coordinates":[112.57458,33.79362],"type":"Point"}
}