{
  "type": "Feature",
  "properties": {
    "gn:admin1_code":"25.0",
    "gn:asciiname":"Caoyingzicun",
    "gn:country_code":"CN",
    "gn:dem":78,
    "gn:feature_class":"P",
    "gn:feature_code":"PPL",
    "gn:name":"Caoyingzicun",
    "gn:population":0,
    "gn:timezone":"Asia/Shanghai",
    "iso:country":"CN",
    "name:zho_x_preferred":[
        "\u8349\u8425\u5b50\u6751"
    ],
    "wof:name":"Caoyingzicun",
    "wof:placetype":"locality"
},
  "geometry": {"coordinates":[119.25942999999999,36.05223],"type":"Point"}
}