{
  "type": "Feature",
  "properties": {
    "gn:admin1_code":"26.0",
    "gn:asciiname":"Zhongwan",
    "gn:country_code":"CN",
    "gn:dem":1009,
    "gn:feature_class":"P",
    "gn:feature_code":"PPL",
    "gn:name":"Zhongwan",
    "gn:population":0,
    "gn:timezone":"Asia/Shanghai",
    "iso:country":"CN",
    "name:zho_x_preferred":[
        "\u4e2d\u6e7e"
    ],
    "wof:name":"Zhongwan",
    "wof:placetype":"locality"
},
  "geometry": {"coordinates":[109.34516000000001,32.18317],"type":"Point"}
}