{
  "type": "Feature",
  "properties": {
    "gn:admin1_code":"25",
    "gn:asciiname":"Puyu",
    "gn:country_code":"CN",
    "gn:dem":365,
    "gn:feature_class":"P",
    "gn:feature_code":"PPL",
    "gn:name":"Puyu",
    "gn:population":0,
    "gn:timezone":"Asia/Shanghai",
    "iso:country":"CN",
    "name:zho_x_preferred":[
        "\u6d66\u5cea"
    ],
    "wof:name":"Puyu",
    "wof:placetype":"locality"
},
  "geometry": {"coordinates":[118.13500000000001,36.0695],"type":"Point"}
}