{
  "type": "Feature",
  "properties": {
    "gn:admin1_code":"12.0",
    "gn:asciiname":"Shangjiashan",
    "gn:country_code":"CN",
    "gn:dem":364,
    "gn:feature_class":"P",
    "gn:feature_code":"PPL",
    "gn:name":"Shangjiashan",
    "gn:population":0,
    "gn:timezone":"Asia/Shanghai",
    "iso:country":"CN",
    "name:zho_x_preferred":[
        "\u5c1a\u5bb6\u5c71"
    ],
    "wof:name":"Shangjiashan",
    "wof:placetype":"locality"
},
  "geometry": {"coordinates":[115.89221000000001,30.93342],"type":"Point"}
}