{
  "type": "Feature",
  "properties": {
    "gn:admin1_code":"30.0",
    "gn:asciiname":"Luwu",
    "gn:country_code":"CN",
    "gn:dem":208,
    "gn:feature_class":"P",
    "gn:feature_code":"PPL",
    "gn:name":"L\u00fcwu",
    "gn:population":0,
    "gn:timezone":"Asia/Shanghai",
    "iso:country":"CN",
    "name:und_x_variant":[
        "L\u00fcwu"
    ],
    "name:zho_x_preferred":[
        "\u5415\u5c4b"
    ],
    "wof:name":"Luwu",
    "wof:placetype":"locality"
},
  "geometry": {"coordinates":[114.97024999999999,22.9591],"type":"Point"}
}