{
  "type": "Feature",
  "properties": {
    "gn:admin1_code":"11",
    "gn:asciiname":"Xuetangwan",
    "gn:country_code":"CN",
    "gn:dem":362,
    "gn:feature_class":"P",
    "gn:feature_code":"PPL",
    "gn:name":"Xuetangwan",
    "gn:population":0,
    "gn:timezone":"Asia/Shanghai",
    "iso:country":"CN",
    "name:zho_x_preferred":[
        "\u5b66\u5802\u6e7e"
    ],
    "wof:name":"Xuetangwan",
    "wof:placetype":"locality"
},
  "geometry": {"coordinates":[110.89861000000001,27.47361],"type":"Point"}
}