{
  "type": "Feature",
  "properties": {
    "gn:admin1_code":"2.0",
    "gn:asciiname":"Xiangquan",
    "gn:country_code":"CN",
    "gn:dem":27,
    "gn:feature_class":"P",
    "gn:feature_code":"PPL",
    "gn:name":"Xiangquan",
    "gn:population":0,
    "gn:timezone":"Asia/Shanghai",
    "iso:country":"CN",
    "name:und_x_variant":[
        "\u76f8\u6cc9"
    ],
    "wof:name":"Xiangquan",
    "wof:placetype":"locality"
},
  "geometry": {"coordinates":[119.73438,29.94692],"type":"Point"}
}