{
  "type": "Feature",
  "properties": {
    "gn:admin1_code":"13",
    "gn:asciiname":"Ketazi Tuokayi",
    "gn:country_code":"CN",
    "gn:dem":1268,
    "gn:feature_class":"P",
    "gn:feature_code":"PPL",
    "gn:name":"Ketazi Tuokayi",
    "gn:population":0,
    "gn:timezone":"Asia/Shanghai",
    "iso:country":"CN",
    "name:und_x_variant":[
        "\u79d1\u5854\u5b5c\u6258\u5580\u4f9d"
    ],
    "wof:name":"Ketazi Tuokayi",
    "wof:placetype":"locality"
},
  "geometry": {"coordinates":[76.08665999999999,39.43633],"type":"Point"}
}