{
  "type": "Feature",
  "properties": {
    "gn:admin1_code":"13.0",
    "gn:asciiname":"Sanju",
    "gn:cc2":"CN",
    "gn:country_code":"CN",
    "gn:dem":2028,
    "gn:feature_class":"P",
    "gn:feature_code":"PPL",
    "gn:name":"Sanju",
    "gn:population":0,
    "gn:timezone":"Asia/Shanghai",
    "iso:country":"CN",
    "name:ara_x_preferred":[
        "\u0633\u0627\u0646\u062c\u0648"
    ],
    "name:ben_x_preferred":[
        "\u09b8\u099e\u09cd\u099c\u09c1"
    ],
    "name:fas_x_preferred":[
        "\u0633\u0627\u0646\u062c\u0648"
    ],
    "name:fra_x_preferred":[
        "Sanju"
    ],
    "name:hin_x_preferred":[
        "\u0938\u0902\u091c\u0942"
    ],
    "name:ind_x_preferred":[
        "Sanju"
    ],
    "name:mar_x_preferred":[
        "\u0938\u0902\u091c\u0942"
    ],
    "name:uig_x_preferred":[
        "\u0633\u0627\u0646\u062c\u06c7"
    ],
    "name:uig_x_variant":[
        "\u0421\u0430\u043d\u0497\u0443"
    ],
    "name:und_x_variant":[
        "San-chu",
        "Sanju Bazar",
        "Sang-chu",
        "Sang-chu-pa-cha",
        "Sang-chu-chuang"
    ],
    "name:urd_x_preferred":[
        "\u0633\u0646\u062c\u0648"
    ],
    "wof:name":"Sanju",
    "wof:placetype":"locality"
},
  "geometry": {"coordinates":[78.40944,37.16417],"type":"Point"}
}