{
  "type": "Feature",
  "properties": {
    "gn:admin1_code":"13",
    "gn:asciiname":"Aqike",
    "gn:country_code":"CN",
    "gn:dem":-99,
    "gn:feature_class":"P",
    "gn:feature_code":"PPL",
    "gn:name":"Aqike",
    "gn:population":0,
    "gn:timezone":"Asia/Urumqi",
    "iso:country":"CN",
    "name:und_x_variant":[
        "\u963f\u5176\u514b"
    ],
    "wof:name":"Aqike",
    "wof:placetype":"locality"
},
  "geometry": {"coordinates":[89.01375999999998,42.85973],"type":"Point"}
}