{
  "type": "Feature",
  "properties": {
    "gn:admin1_code":"26.0",
    "gn:asciiname":"Sipingcun",
    "gn:country_code":"CN",
    "gn:dem":1416,
    "gn:feature_class":"P",
    "gn:feature_code":"PPL",
    "gn:name":"Sipingcun",
    "gn:population":0,
    "gn:timezone":"Asia/Shanghai",
    "iso:country":"CN",
    "name:zho_x_preferred":[
        "\u5bfa\u576a\u6751"
    ],
    "wof:name":"Sipingcun",
    "wof:placetype":"locality"
},
  "geometry": {"coordinates":[108.99175,35.30562000000001],"type":"Point"}
}