{
  "type": "Feature",
  "properties": {
    "gn:admin1_code":"11.0",
    "gn:asciiname":"Xiaoniantang",
    "gn:country_code":"CN",
    "gn:dem":134,
    "gn:feature_class":"P",
    "gn:feature_code":"PPL",
    "gn:name":"Xiaoniantang",
    "gn:population":0,
    "gn:timezone":"Asia/Shanghai",
    "iso:country":"CN",
    "name:und_x_variant":[
        "Xiaoyantang"
    ],
    "name:zho_x_preferred":[
        "\u5c0f\u5e74\u5858"
    ],
    "name:zho_x_variant":[
        "\u5c0f\u4e25\u5858"
    ],
    "wof:name":"Xiaoniantang",
    "wof:placetype":"locality"
},
  "geometry": {"coordinates":[113.62754,26.91379],"type":"Point"}
}