{
  "type": "Feature",
  "properties": {
    "gn:admin1_code":"24",
    "gn:asciiname":"Niulangwan",
    "gn:cc2":"CN",
    "gn:country_code":"CN",
    "gn:dem":795,
    "gn:feature_class":"P",
    "gn:feature_code":"PPL",
    "gn:name":"Niulangwan",
    "gn:population":0,
    "gn:timezone":"Asia/Shanghai",
    "iso:country":"CN",
    "name:und_x_variant":[
        "Niu-lo-wan",
        "Niulangwan"
    ],
    "wof:name":"Niulangwan",
    "wof:placetype":"locality"
},
  "geometry": {"coordinates":[113.23611,38.39778],"type":"Point"}
}