{
  "type": "Feature",
  "properties": {
    "gn:admin1_code":"29.0",
    "gn:asciiname":"Kaiji",
    "gn:country_code":"CN",
    "gn:dem":1431,
    "gn:feature_class":"P",
    "gn:feature_code":"PPL",
    "gn:name":"Kaiji",
    "gn:population":0,
    "gn:timezone":"Asia/Shanghai",
    "iso:country":"CN",
    "name:und_x_variant":[
        "\u5f00\u57fa"
    ],
    "wof:name":"Kaiji",
    "wof:placetype":"locality"
},
  "geometry": {"coordinates":[103.26255999999999,27.06047],"type":"Point"}
}