{
  "type": "Feature",
  "properties": {
    "gn:admin1_code":"2.0",
    "gn:asciiname":"Qiansongyuan",
    "gn:country_code":"CN",
    "gn:dem":60,
    "gn:feature_class":"P",
    "gn:feature_code":"PPL",
    "gn:name":"Qiansongyuan",
    "gn:population":0,
    "gn:timezone":"Asia/Shanghai",
    "iso:country":"CN",
    "name:und_x_variant":[
        "\u524d\u677e\u56ed",
        "Qiansongyuan"
    ],
    "wof:name":"Qiansongyuan",
    "wof:placetype":"locality"
},
  "geometry": {"coordinates":[118.97648,28.99532],"type":"Point"}
}