{
  "type": "Feature",
  "properties": {
    "gn:admin1_code":"8.0",
    "gn:asciiname":"Wapendian",
    "gn:country_code":"CN",
    "gn:dem":125,
    "gn:feature_class":"P",
    "gn:feature_code":"PPL",
    "gn:name":"Wapendian",
    "gn:population":0,
    "gn:timezone":"Asia/Shanghai",
    "iso:country":"CN",
    "name:zho_x_preferred":[
        "\u74e6\u76c6\u5e97"
    ],
    "wof:name":"Wapendian",
    "wof:placetype":"locality"
},
  "geometry": {"coordinates":[126.31094,46.17287],"type":"Point"}
}