{
  "type": "Feature",
  "properties": {
    "gn:admin1_code":"19.0",
    "gn:asciiname":"Jiangbaidi",
    "gn:country_code":"CN",
    "gn:dem":33,
    "gn:feature_class":"P",
    "gn:feature_code":"PPL",
    "gn:name":"Jiangbaidi",
    "gn:population":0,
    "gn:timezone":"Asia/Shanghai",
    "iso:country":"CN",
    "name:zho_x_preferred":[
        "\u59dc\u767d\u5730"
    ],
    "wof:name":"Jiangbaidi",
    "wof:placetype":"locality"
},
  "geometry": {"coordinates":[123.11499999999999,39.7464],"type":"Point"}
}