{
  "type": "Feature",
  "properties": {
    "gn:admin1_code":"16.0",
    "gn:asciiname":"Long'er",
    "gn:country_code":"CN",
    "gn:dem":210,
    "gn:feature_class":"P",
    "gn:feature_code":"PPL",
    "gn:name":"Long\u2019er",
    "gn:population":0,
    "gn:timezone":"Asia/Shanghai",
    "iso:country":"CN",
    "name:und_x_variant":[
        "Long\u2019er"
    ],
    "name:zho_x_preferred":[
        "\u9647\u800c"
    ],
    "wof:name":"Long'er",
    "wof:placetype":"locality"
},
  "geometry": {"coordinates":[107.327,22.6725],"type":"Point"}
}