{
  "type": "Feature",
  "properties": {
    "gn:admin1_code":"18",
    "gn:asciiname":"Dapingzi",
    "gn:country_code":"CN",
    "gn:dem":1397,
    "gn:feature_class":"P",
    "gn:feature_code":"PPL",
    "gn:name":"Dapingzi",
    "gn:population":0,
    "gn:timezone":"Asia/Shanghai",
    "iso:country":"CN",
    "name:zho_x_preferred":[
        "\u5927\u576a\u5b50"
    ],
    "wof:name":"Dapingzi",
    "wof:placetype":"locality"
},
  "geometry": {"coordinates":[107.07599999999999,28.5032],"type":"Point"}
}