{
  "type": "Feature",
  "properties": {
    "gn:admin1_code":"30.0",
    "gn:asciiname":"Nanping",
    "gn:country_code":"CN",
    "gn:dem":15,
    "gn:feature_class":"P",
    "gn:feature_code":"PPL",
    "gn:name":"Nanping",
    "gn:population":0,
    "gn:timezone":"Asia/Shanghai",
    "iso:country":"CN",
    "name:afr_x_preferred":[
        "Nanping"
    ],
    "name:ara_x_preferred":[
        "\u0646\u0627\u0646\u0628\u064a\u0646\u063a"
    ],
    "name:bre_x_preferred":[
        "Nanping"
    ],
    "name:cdo_x_preferred":[
        "N\u00e0ng-b\u00ecng"
    ],
    "name:ceb_x_preferred":[
        "Nanping"
    ],
    "name:ces_x_preferred":[
        "Nan-pching"
    ],
    "name:cym_x_preferred":[
        "Nanping"
    ],
    "name:dan_x_preferred":[
        "Nanping"
    ],
    "name:deu_x_preferred":[
        "Nanping"
    ],
    "name:eus_x_preferred":[
        "Nanping"
    ],
    "name:fas_x_preferred":[
        "\u0646\u0627\u0646\u067e\u06cc\u0646\u06af"
    ],
    "name:fin_x_preferred":[
        "Nanping"
    ],
    "name:fra_x_preferred":[
        "Nanping"
    ],
    "name:hak_x_preferred":[
        "N\u00e0m-ph\u00ecn-s\u1e73"
    ],
    "name:ita_x_preferred":[
        "Nanping"
    ],
    "name:jpn_x_preferred":[
        "\u5357\u5e73\u5e02"
    ],
    "name:kik_x_preferred":[
        "Nanping"
    ],
    "name:kor_x_preferred":[
        "\ub09c\ud551\uc2dc"
    ],
    "name:mlg_x_preferred":[
        "Nanping"
    ],
    "name:nld_x_preferred":[
        "Nanping"
    ],
    "name:nno_x_preferred":[
        "Nanping"
    ],
    "name:nor_x_preferred":[
        "Nanping"
    ],
    "name:pam_x_preferred":[
        "Nanping"
    ],
    "name:pnb_x_preferred":[
        "\u0646\u0627\u0646\u067e\u06cc\u0646\u06af"
    ],
    "name:pol_x_preferred":[
        "Nanping"
    ],
    "name:por_x_preferred":[
        "Nanping"
    ],
    "name:rus_x_preferred":[
        "\u041d\u0430\u043d\u044c\u043f\u0438\u043d"
    ],
    "name:spa_x_preferred":[
        "Nanping"
    ],
    "name:swe_x_preferred":[
        "Nanping"
    ],
    "name:tgl_x_preferred":[
        "Nanping"
    ],
    "name:tur_x_preferred":[
        "Nanping"
    ],
    "name:uig_x_preferred":[
        "Nenping shehiri"
    ],
    "name:urd_x_preferred":[
        "\u0646\u0627\u0646\u067e\u0646\u06af"
    ],
    "name:vie_x_preferred":[
        "Nam B\u00ecnh"
    ],
    "name:war_x_preferred":[
        "Nanping"
    ],
    "name:wuu_x_preferred":[
        "\u5357\u5e73\u5e02"
    ],
    "name:zho_x_preferred":[
        "\u5357\u5e73"
    ],
    "name:zho_x_variant":[
        "\u5357\u5e73\u5e02"
    ],
    "wof:name":"Nanping",
    "wof:placetype":"locality"
},
  "geometry": {"coordinates":[112.42474,22.36202],"type":"Point"}
}