{
  "type": "Feature",
  "properties": {
    "gn:admin1_code":"25.0",
    "gn:asciiname":"Dongjingjia",
    "gn:country_code":"CN",
    "gn:dem":8,
    "gn:feature_class":"P",
    "gn:feature_code":"PPL",
    "gn:name":"Dongjingjia",
    "gn:population":0,
    "gn:timezone":"Asia/Shanghai",
    "iso:country":"CN",
    "name:zho_x_preferred":[
        "\u4e1c\u8346\u5bb6"
    ],
    "wof:name":"Dongjingjia",
    "wof:placetype":"locality"
},
  "geometry": {"coordinates":[121.05645,36.66212],"type":"Point"}
}