{
  "type": "Feature",
  "properties": {
    "gn:admin1_code":"3.0",
    "gn:asciiname":"Liantangjiao",
    "gn:country_code":"CN",
    "gn:dem":40,
    "gn:feature_class":"P",
    "gn:feature_code":"PPL",
    "gn:name":"Liantangjiao",
    "gn:population":0,
    "gn:timezone":"Asia/Shanghai",
    "iso:country":"CN",
    "name:und_x_variant":[
        "\u83b2\u5858\u89d2"
    ],
    "wof:name":"Liantangjiao",
    "wof:placetype":"locality"
},
  "geometry": {"coordinates":[115.78932,29.39495],"type":"Point"}
}