{
  "type": "Feature",
  "properties": {
    "gn:admin1_code":"26.0",
    "gn:asciiname":"Zibai Goucun",
    "gn:country_code":"CN",
    "gn:dem":1194,
    "gn:feature_class":"P",
    "gn:feature_code":"PPL",
    "gn:name":"Zibai Goucun",
    "gn:population":0,
    "gn:timezone":"Asia/Shanghai",
    "iso:country":"CN",
    "name:zho_x_preferred":[
        "\u8a3e\u67cf\u6c9f\u6751"
    ],
    "wof:name":"Zibai Goucun",
    "wof:placetype":"locality"
},
  "geometry": {"coordinates":[110.63500000000001,38.8381],"type":"Point"}
}