{
  "type": "Feature",
  "properties": {
    "gn:admin1_code":"16.0",
    "gn:asciiname":"Wang'an",
    "gn:country_code":"CN",
    "gn:dem":133,
    "gn:feature_class":"P",
    "gn:feature_code":"PPL",
    "gn:name":"Wang\u2019an",
    "gn:population":0,
    "gn:timezone":"Asia/Shanghai",
    "iso:country":"CN",
    "name:und_x_variant":[
        "Wang\u2019an"
    ],
    "name:zho_x_preferred":[
        "\u65fa\u5b89"
    ],
    "wof:name":"Wang'an",
    "wof:placetype":"locality"
},
  "geometry": {"coordinates":[110.264,23.1185],"type":"Point"}
}