{
  "type": "Feature",
  "properties": {
    "gn:admin1_code":"5.0",
    "gn:asciiname":"Chengfadang",
    "gn:country_code":"CN",
    "gn:dem":185,
    "gn:feature_class":"P",
    "gn:feature_code":"PPL",
    "gn:name":"Chengfadang",
    "gn:population":0,
    "gn:timezone":"Asia/Shanghai",
    "iso:country":"CN",
    "name:zho_x_preferred":[
        "\u6210\u53d1\u5f53"
    ],
    "wof:name":"Chengfadang",
    "wof:placetype":"locality"
},
  "geometry": {"coordinates":[126.58902,45.1778],"type":"Point"}
}