{
  "type": "Feature",
  "properties": {
    "gn:admin1_code":"11",
    "gn:asciiname":"Hongniqiao",
    "gn:country_code":"CN",
    "gn:dem":79,
    "gn:feature_class":"P",
    "gn:feature_code":"PPL",
    "gn:name":"Hongniqiao",
    "gn:population":0,
    "gn:timezone":"Asia/Shanghai",
    "iso:country":"CN",
    "name:zho_x_preferred":[
        "\u7ea2\u6ce5\u6865"
    ],
    "wof:name":"Hongniqiao",
    "wof:placetype":"locality"
},
  "geometry": {"coordinates":[112.42107,26.48735],"type":"Point"}
}