{
  "type": "Feature",
  "properties": {
    "gn:admin1_code":"8.0",
    "gn:asciiname":"Wangdi Fangzi",
    "gn:country_code":"CN",
    "gn:dem":132,
    "gn:feature_class":"P",
    "gn:feature_code":"PPL",
    "gn:name":"Wangdi Fangzi",
    "gn:population":0,
    "gn:timezone":"Asia/Shanghai",
    "iso:country":"CN",
    "name:zho_x_preferred":[
        "\u738b\u5730\u623f\u5b50"
    ],
    "wof:name":"Wangdi Fangzi",
    "wof:placetype":"locality"
},
  "geometry": {"coordinates":[124.45874000000001,46.114],"type":"Point"}
}