{
  "type": "Feature",
  "properties": {
    "gn:admin1_code":"4.0",
    "gn:asciiname":"Jiantuancun",
    "gn:country_code":"CN",
    "gn:dem":2,
    "gn:feature_class":"P",
    "gn:feature_code":"PPL",
    "gn:name":"Jiantuancun",
    "gn:population":0,
    "gn:timezone":"Asia/Shanghai",
    "iso:country":"CN",
    "name:zho_x_preferred":[
        "\u5efa\u56e2\u6751"
    ],
    "wof:name":"Jiantuancun",
    "wof:placetype":"locality"
},
  "geometry": {"coordinates":[120.44171,32.66809],"type":"Point"}
}