{
  "type": "Feature",
  "properties": {
    "gn:admin1_code":"32.0",
    "gn:asciiname":"Yangjiayuan",
    "gn:country_code":"CN",
    "gn:dem":985,
    "gn:feature_class":"P",
    "gn:feature_code":"PPL",
    "gn:name":"Yangjiayuan",
    "gn:population":0,
    "gn:timezone":"Asia/Shanghai",
    "iso:country":"CN",
    "name:zho_x_preferred":[
        "\u6768\u5bb6\u9662"
    ],
    "wof:name":"Yangjiayuan",
    "wof:placetype":"locality"
},
  "geometry": {"coordinates":[107.38531,31.95013],"type":"Point"}
}