{
  "type": "Feature",
  "properties": {
    "gn:admin1_code":"3.0",
    "gn:asciiname":"Laoshanli",
    "gn:country_code":"CN",
    "gn:dem":100,
    "gn:feature_class":"P",
    "gn:feature_code":"PPL",
    "gn:name":"Laoshanli",
    "gn:population":0,
    "gn:timezone":"Asia/Shanghai",
    "iso:country":"CN",
    "name:zho_x_preferred":[
        "\u8001\u5c71\u91cc"
    ],
    "wof:name":"Laoshanli",
    "wof:placetype":"locality"
},
  "geometry": {"coordinates":[114.602,28.2841],"type":"Point"}
}