{
  "type": "Feature",
  "properties": {
    "gn:admin1_code":"3",
    "gn:asciiname":"Dongxi",
    "gn:country_code":"CN",
    "gn:dem":339,
    "gn:feature_class":"P",
    "gn:feature_code":"PPL",
    "gn:name":"Dongxi",
    "gn:population":0,
    "gn:timezone":"Asia/Shanghai",
    "iso:country":"CN",
    "name:ceb_x_preferred":[
        "Dongxi"
    ],
    "name:swe_x_preferred":[
        "Dongxi"
    ],
    "name:zho_x_preferred":[
        "\u6d1e\u6eaa"
    ],
    "wof:name":"Dongxi",
    "wof:placetype":"locality"
},
  "geometry": {"coordinates":[114.40506000000001,26.15325],"type":"Point"}
}