{
  "type": "Feature",
  "properties": {
    "gn:admin1_code":"12.0",
    "gn:asciiname":"Xiahengchong",
    "gn:country_code":"CN",
    "gn:dem":71,
    "gn:feature_class":"P",
    "gn:feature_code":"PPL",
    "gn:name":"Xiahengchong",
    "gn:population":0,
    "gn:timezone":"Asia/Shanghai",
    "iso:country":"CN",
    "name:zho_x_preferred":[
        "\u4e0b\u6a2a\u51b2"
    ],
    "wof:name":"Xiahengchong",
    "wof:placetype":"locality"
},
  "geometry": {"coordinates":[114.13477,31.54104],"type":"Point"}
}