{
  "type": "Feature",
  "properties": {
    "gn:admin1_code":"32.0",
    "gn:asciiname":"Jingba",
    "gn:country_code":"CN",
    "gn:dem":849,
    "gn:feature_class":"P",
    "gn:feature_code":"PPL",
    "gn:name":"Jingba",
    "gn:population":0,
    "gn:timezone":"Asia/Shanghai",
    "iso:country":"CN",
    "name:und_x_variant":[
        "\u4e95\u575d"
    ],
    "wof:name":"Jingba",
    "wof:placetype":"locality"
},
  "geometry": {"coordinates":[106.90706000000002,32.36786],"type":"Point"}
}