{
  "type": "Feature",
  "properties": {
    "gn:admin1_code":"20",
    "gn:asciiname":"Tariat",
    "gn:cc2":"CN",
    "gn:country_code":"CN",
    "gn:dem":1319,
    "gn:feature_class":"P",
    "gn:feature_code":"PPL",
    "gn:name":"Tariat",
    "gn:population":0,
    "gn:timezone":"Asia/Shanghai",
    "iso:country":"CN",
    "name:ceb_x_preferred":[
        "Tariat Sum"
    ],
    "name:deu_x_preferred":[
        "Tariat"
    ],
    "name:fas_x_preferred":[
        "\u062a\u0627\u0631\u06cc\u0627\u062a"
    ],
    "name:mkd_x_preferred":[
        "\u0422\u0430\u0440\u0438\u0458\u0430\u0442"
    ],
    "name:mon_x_preferred":[
        "\u0422\u0430\u0440\u0438\u0430\u0442 \u0441\u0443\u043c"
    ],
    "name:pol_x_preferred":[
        "Tariat"
    ],
    "name:rus_x_preferred":[
        "\u0422\u0430\u0440\u0438\u0430\u0442"
    ],
    "name:swe_x_preferred":[
        "Tariat"
    ],
    "name:ukr_x_preferred":[
        "\u0422\u0430\u0440\u0456\u0430\u0442"
    ],
    "name:und_x_variant":[
        "T\u2019a-la-t\u2019u"
    ],
    "wof:name":"Tariat",
    "wof:placetype":"locality"
},
  "geometry": {"coordinates":[104.59999999999999,39.23333],"type":"Point"}
}