{
  "type": "Feature",
  "properties": {
    "gn:admin1_code":"20",
    "gn:asciiname":"Tariat",
    "gn:cc2":"CN",
    "gn:country_code":"CN",
    "gn:dem":1319,
    "gn:feature_class":"P",
    "gn:feature_code":"PPL",
    "gn:name":"Tariat",
    "gn:population":0,
    "gn:timezone":"Asia/Shanghai",
    "iso:country":"CN",
    "name:und_x_variant":[
        "T\u2019a-la-t\u2019u",
        "Tariat"
    ],
    "wof:name":"Tariat",
    "wof:placetype":"locality"
},
  "geometry": {"coordinates":[104.59999999999999,39.23333],"type":"Point"}
}