{
  "type": "Feature",
  "properties": {
    "gn:admin1_code":"32.0",
    "gn:asciiname":"Masijia",
    "gn:country_code":"CN",
    "gn:dem":1131,
    "gn:feature_class":"P",
    "gn:feature_code":"PPL",
    "gn:name":"Masijia",
    "gn:population":0,
    "gn:timezone":"Asia/Shanghai",
    "iso:country":"CN",
    "name:zho_x_preferred":[
        "\u9a6c\u65af\u52a0"
    ],
    "wof:name":"Masijia",
    "wof:placetype":"locality"
},
  "geometry": {"coordinates":[103.45956,28.39312],"type":"Point"}
}