{
  "type": "Feature",
  "properties": {
    "gn:admin1_code":"9.0",
    "gn:asciiname":"Wan'andian",
    "gn:country_code":"CN",
    "gn:dem":62,
    "gn:feature_class":"P",
    "gn:feature_code":"PPL",
    "gn:name":"Wan\u2019andian",
    "gn:population":0,
    "gn:timezone":"Asia/Shanghai",
    "iso:country":"CN",
    "name:und_x_variant":[
        "Wan\u2019andian"
    ],
    "name:zho_x_preferred":[
        "\u4e07\u5b89\u5e97"
    ],
    "wof:name":"Wan'andian",
    "wof:placetype":"locality"
},
  "geometry": {"coordinates":[114.55188,32.53868],"type":"Point"}
}