{
  "type": "Feature",
  "properties": {
    "gn:admin1_code":"29",
    "gn:asciiname":"Zhongsuo",
    "gn:country_code":"CN",
    "gn:dem":1907,
    "gn:feature_class":"P",
    "gn:feature_code":"PPL",
    "gn:name":"Zhongsuo",
    "gn:population":0,
    "gn:timezone":"Asia/Shanghai",
    "iso:country":"CN",
    "name:zho_x_preferred":[
        "\u4e2d\u6240"
    ],
    "wof:name":"Zhongsuo",
    "wof:placetype":"locality"
},
  "geometry": {"coordinates":[102.374,24.6956],"type":"Point"}
}