{
  "type": "Feature",
  "properties": {
    "gn:admin1_code":"29.0",
    "gn:asciiname":"Jiudui",
    "gn:country_code":"CN",
    "gn:dem":162,
    "gn:feature_class":"P",
    "gn:feature_code":"PPLF",
    "gn:name":"Jiudui",
    "gn:population":0,
    "gn:timezone":"Asia/Shanghai",
    "iso:country":"CN",
    "name:zho_x_preferred":[
        "\u4e5d\u961f"
    ],
    "wof:name":"Jiudui",
    "wof:placetype":"locality"
},
  "geometry": {"coordinates":[103.982,22.5943],"type":"Point"}
}