{
  "type": "Feature",
  "properties": {
    "gn:admin1_code":"15.0",
    "gn:asciiname":"Po'er",
    "gn:country_code":"CN",
    "gn:dem":2140,
    "gn:feature_class":"P",
    "gn:feature_code":"PPL",
    "gn:name":"Po\u2019er",
    "gn:population":0,
    "gn:timezone":"Asia/Shanghai",
    "iso:country":"CN",
    "name:und_x_variant":[
        "Po\u2019er"
    ],
    "name:zho_x_preferred":[
        "\u5761\u513f"
    ],
    "wof:name":"Po'er",
    "wof:placetype":"locality"
},
  "geometry": {"coordinates":[104.31100000000001,35.0056],"type":"Point"}
}