{
  "type": "Feature",
  "properties": {
    "gn:admin1_code":"10.0",
    "gn:asciiname":"Buli",
    "gn:country_code":"CN",
    "gn:dem":13,
    "gn:feature_class":"P",
    "gn:feature_code":"PPL",
    "gn:name":"Buli",
    "gn:population":0,
    "gn:timezone":"Asia/Shanghai",
    "iso:country":"CN",
    "name:ceb_x_preferred":[
        "Buli"
    ],
    "name:deu_x_preferred":[
        "Buli"
    ],
    "name:hrv_x_preferred":[
        "Buli"
    ],
    "name:nld_x_preferred":[
        "Buli"
    ],
    "name:rus_x_preferred":[
        "\u0411\u0443\u043b\u0438"
    ],
    "name:srp_x_preferred":[
        "\u0411\u0443\u043b\u0438"
    ],
    "name:swe_x_preferred":[
        "Buli"
    ],
    "name:tgl_x_preferred":[
        "Buli"
    ],
    "name:zho_x_preferred":[
        "\u5e03\u91cc"
    ],
    "wof:name":"Buli",
    "wof:placetype":"locality"
},
  "geometry": {"coordinates":[115.83499999999999,38.631],"type":"Point"}
}