{
  "type": "Feature",
  "properties": {
    "gn:admin1_code":"4.0",
    "gn:asciiname":"Tanhuqun",
    "gn:country_code":"CN",
    "gn:dem":5,
    "gn:feature_class":"P",
    "gn:feature_code":"PPL",
    "gn:name":"Tanhuqun",
    "gn:population":0,
    "gn:timezone":"Asia/Shanghai",
    "iso:country":"CN",
    "name:und_x_variant":[
        "\u6f6d\u745a\u7fa4"
    ],
    "name:zho_x_preferred":[
        "\u6f6d\u745a\u7fa4"
    ],
    "wof:name":"Tanhuqun",
    "wof:placetype":"locality"
},
  "geometry": {"coordinates":[120.84206,32.33423],"type":"Point"}
}