{
  "type": "Feature",
  "properties": {
    "gn:admin1_code":"24.0",
    "gn:asciiname":"Jiangzhuang",
    "gn:country_code":"CN",
    "gn:dem":765,
    "gn:feature_class":"P",
    "gn:feature_code":"PPL",
    "gn:name":"Jiangzhuang",
    "gn:population":0,
    "gn:timezone":"Asia/Shanghai",
    "iso:country":"CN",
    "name:zho_x_preferred":[
        "\u5c06\u5e84"
    ],
    "wof:name":"Jiangzhuang",
    "wof:placetype":"locality"
},
  "geometry": {"coordinates":[112.59724,35.82768],"type":"Point"}
}