{
  "type": "Feature",
  "properties": {
    "gn:admin1_code":"26.0",
    "gn:asciiname":"Lijiaping",
    "gn:country_code":"CN",
    "gn:dem":1379,
    "gn:feature_class":"P",
    "gn:feature_code":"PPL",
    "gn:name":"Lijiaping",
    "gn:population":0,
    "gn:timezone":"Asia/Shanghai",
    "iso:country":"CN",
    "name:zho_x_preferred":[
        "\u674e\u5bb6\u576a"
    ],
    "wof:name":"Lijiaping",
    "wof:placetype":"locality"
},
  "geometry": {"coordinates":[108.71545999999999,33.47282],"type":"Point"}
}