{
  "type": "Feature",
  "properties": {
    "gn:admin1_code":"30.0",
    "gn:asciiname":"Mailin",
    "gn:country_code":"CN",
    "gn:dem":28,
    "gn:feature_class":"P",
    "gn:feature_code":"PPL",
    "gn:name":"Mailin",
    "gn:population":0,
    "gn:timezone":"Asia/Urumqi",
    "iso:country":"CN",
    "name:zho_x_preferred":[
        "\u8fc8\u9716"
    ],
    "wof:name":"Mailin",
    "wof:placetype":"locality"
},
  "geometry": {"coordinates":[110.00935,20.31463],"type":"Point"}
}