{
  "type": "Feature",
  "properties": {
    "gn:admin1_code":"25",
    "gn:asciiname":"Liuxinzhuang",
    "gn:country_code":"CN",
    "gn:dem":29,
    "gn:feature_class":"P",
    "gn:feature_code":"PPL",
    "gn:name":"Liuxinzhuang",
    "gn:population":0,
    "gn:timezone":"Asia/Shanghai",
    "iso:country":"CN",
    "name:zho_x_preferred":[
        "\u5218\u8f9b\u5e84"
    ],
    "wof:name":"Liuxinzhuang",
    "wof:placetype":"locality"
},
  "geometry": {"coordinates":[116.06399999999999,37.0375],"type":"Point"}
}