{
  "type": "Feature",
  "properties": {
    "gn:admin1_code":"5.0",
    "gn:asciiname":"Fengshoucun",
    "gn:country_code":"CN",
    "gn:dem":335,
    "gn:feature_class":"P",
    "gn:feature_code":"PPL",
    "gn:name":"Fengshoucun",
    "gn:population":0,
    "gn:timezone":"Asia/Shanghai",
    "iso:country":"CN",
    "name:zho_x_preferred":[
        "\u4e30\u6536\u6751"
    ],
    "wof:name":"Fengshoucun",
    "wof:placetype":"locality"
},
  "geometry": {"coordinates":[125.60782,42.51522],"type":"Point"}
}