{
  "type": "Feature",
  "properties": {
    "gn:admin1_code":"14.0",
    "gn:asciiname":"Saimuka",
    "gn:country_code":"CN",
    "gn:dem":4786,
    "gn:feature_class":"P",
    "gn:feature_code":"PPL",
    "gn:name":"Saimuka",
    "gn:population":0,
    "gn:timezone":"Asia/Shanghai",
    "iso:country":"CN",
    "name:zho_x_preferred":[
        "\u8d5b\u6728\u5361"
    ],
    "wof:name":"Saimuka",
    "wof:placetype":"locality"
},
  "geometry": {"coordinates":[81.74636,30.62621],"type":"Point"}
}