{
  "type": "Feature",
  "properties": {
    "gn:admin1_code":"15.0",
    "gn:asciiname":"Goujia",
    "gn:country_code":"CN",
    "gn:dem":1221,
    "gn:feature_class":"P",
    "gn:feature_code":"PPL",
    "gn:name":"Goujia",
    "gn:population":0,
    "gn:timezone":"Asia/Shanghai",
    "iso:country":"CN",
    "name:zho_x_preferred":[
        "\u82df\u5bb6"
    ],
    "wof:name":"Goujia",
    "wof:placetype":"locality"
},
  "geometry": {"coordinates":[107.767,35.3689],"type":"Point"}
}