{
  "type": "Feature",
  "properties": {
    "gn:admin1_code":"02",
    "gn:asciiname":"Shan-k'eng-t'ou",
    "gn:country_code":"CN",
    "gn:dem":365,
    "gn:feature_class":"P",
    "gn:feature_code":"PPL",
    "gn:name":"Shan-k\u2019eng-t\u2019ou",
    "gn:population":0,
    "gn:timezone":"Asia/Shanghai",
    "iso:country":"CN",
    "wof:name":"Shan-k'eng-t'ou",
    "wof:placetype":"locality"
},
  "geometry": {"coordinates":[120.84472,28.19],"type":"Point"}
}