{
  "type": "Feature",
  "properties": {
    "gn:admin1_code":"5.0",
    "gn:asciiname":"Xinxingtun",
    "gn:country_code":"CN",
    "gn:dem":319,
    "gn:feature_class":"P",
    "gn:feature_code":"PPL",
    "gn:name":"Xinxingtun",
    "gn:population":0,
    "gn:timezone":"Asia/Shanghai",
    "iso:country":"CN",
    "name:und_x_variant":[
        "\u65b0\u5174\u5c6f"
    ],
    "wof:name":"Xinxingtun",
    "wof:placetype":"locality"
},
  "geometry": {"coordinates":[129.02698000000001,43.03532],"type":"Point"}
}