{
  "type": "Feature",
  "properties": {
    "gn:admin1_code":"15.0",
    "gn:asciiname":"Xicha Sidui",
    "gn:country_code":"CN",
    "gn:dem":1237,
    "gn:feature_class":"P",
    "gn:feature_code":"PPLF",
    "gn:name":"Xicha Sidui",
    "gn:population":0,
    "gn:timezone":"Asia/Shanghai",
    "iso:country":"CN",
    "name:zho_x_preferred":[
        "\u897f\u5c94\u56db\u961f"
    ],
    "wof:name":"Xicha Sidui",
    "wof:placetype":"locality"
},
  "geometry": {"coordinates":[98.9036,40.1587],"type":"Point"}
}