{
  "type": "Feature",
  "properties": {
    "gn:admin1_code":"30.0",
    "gn:asciiname":"Mandongkeng",
    "gn:country_code":"CN",
    "gn:dem":93,
    "gn:feature_class":"P",
    "gn:feature_code":"PPL",
    "gn:name":"Mandongkeng",
    "gn:population":0,
    "gn:timezone":"Asia/Shanghai",
    "iso:country":"CN",
    "name:zho_x_preferred":[
        "Mandongkeng"
    ],
    "name:zho_x_variant":[
        "\u6ee1\u4e1c\u5751"
    ],
    "wof:name":"Mandongkeng",
    "wof:placetype":"locality"
},
  "geometry": {"coordinates":[115.28917,24.34806],"type":"Point"}
}