{
  "type": "Feature",
  "properties": {
    "gn:admin1_code":"29",
    "gn:asciiname":"Fangna",
    "gn:country_code":"CN",
    "gn:dem":1150,
    "gn:feature_class":"P",
    "gn:feature_code":"PPL",
    "gn:name":"Fangna",
    "gn:population":0,
    "gn:timezone":"Asia/Shanghai",
    "iso:country":"CN",
    "name:zho_x_preferred":[
        "\u65b9\u90a3"
    ],
    "wof:name":"Fangna",
    "wof:placetype":"locality"
},
  "geometry": {"coordinates":[103.11799999999999,24.2255],"type":"Point"}
}