{
  "type": "Feature",
  "properties": {
    "gn:admin1_code":"3.0",
    "gn:asciiname":"Zhuangtianshang",
    "gn:country_code":"CN",
    "gn:dem":53,
    "gn:feature_class":"P",
    "gn:feature_code":"PPL",
    "gn:name":"Zhuangtianshang",
    "gn:population":0,
    "gn:timezone":"Asia/Shanghai",
    "iso:country":"CN",
    "name:und_x_variant":[
        "\u5e84\u7530\u4e0a"
    ],
    "wof:name":"Zhuangtianshang",
    "wof:placetype":"locality"
},
  "geometry": {"coordinates":[115.2264,28.25455],"type":"Point"}
}