{
  "type": "Feature",
  "properties": {
    "gn:admin1_code":"30",
    "gn:asciiname":"Lizhengzai",
    "gn:country_code":"CN",
    "gn:dem":47,
    "gn:feature_class":"P",
    "gn:feature_code":"PPL",
    "gn:name":"Lizhengzai",
    "gn:population":0,
    "gn:timezone":"Asia/Urumqi",
    "iso:country":"CN",
    "name:zho_x_preferred":[
        "\u91cc\u653f\u4ed4"
    ],
    "wof:name":"Lizhengzai",
    "wof:placetype":"locality"
},
  "geometry": {"coordinates":[110.05793,20.43737],"type":"Point"}
}