{
  "type": "Feature",
  "properties": {
    "gn:admin1_code":"5.0",
    "gn:asciiname":"Paoziyan",
    "gn:country_code":"CN",
    "gn:dem":197,
    "gn:feature_class":"P",
    "gn:feature_code":"PPL",
    "gn:name":"Paoziyan",
    "gn:population":0,
    "gn:timezone":"Asia/Shanghai",
    "iso:country":"CN",
    "name:zho_x_preferred":[
        "\u6ce1\u5b50\u6cbf"
    ],
    "wof:name":"Paoziyan",
    "wof:placetype":"locality"
},
  "geometry": {"coordinates":[126.57135,43.7989],"type":"Point"}
}