{
  "type": "Feature",
  "properties": {
    "gn:admin1_code":"8.0",
    "gn:asciiname":"Tianchengyao",
    "gn:country_code":"CN",
    "gn:dem":176,
    "gn:feature_class":"P",
    "gn:feature_code":"PPL",
    "gn:name":"Tianchengyao",
    "gn:population":0,
    "gn:timezone":"Asia/Shanghai",
    "iso:country":"CN",
    "name:zho_x_preferred":[
        "\u5929\u6210\u7a91"
    ],
    "wof:name":"Tianchengyao",
    "wof:placetype":"locality"
},
  "geometry": {"coordinates":[127.12412,45.32595],"type":"Point"}
}