{
  "type": "Feature",
  "properties": {
    "gn:admin1_code":"4.0",
    "gn:asciiname":"Jiankou",
    "gn:country_code":"CN",
    "gn:dem":4,
    "gn:feature_class":"P",
    "gn:feature_code":"PPL",
    "gn:name":"Jiankou",
    "gn:population":0,
    "gn:timezone":"Asia/Shanghai",
    "iso:country":"CN",
    "name:und_x_variant":[
        "\u5c16\u53e3"
    ],
    "name:zho_x_preferred":[
        "\u5c16\u53e3"
    ],
    "wof:name":"Jiankou",
    "wof:placetype":"locality"
},
  "geometry": {"coordinates":[120.511,32.11928],"type":"Point"}
}