{
  "type": "Feature",
  "properties": {
    "gn:admin1_code":"4.0",
    "gn:asciiname":"Jiankou",
    "gn:country_code":"CN",
    "gn:dem":4,
    "gn:feature_class":"P",
    "gn:feature_code":"PPL",
    "gn:name":"Jiankou",
    "gn:population":0,
    "gn:timezone":"Asia/Shanghai",
    "iso:country":"CN",
    "name:deu_x_preferred":[
        "Jiankou"
    ],
    "name:swe_x_preferred":[
        "Jiankou"
    ],
    "name:ukr_x_preferred":[
        "\u0426\u0437\u044f\u043d\u044c\u043a\u043e\u0443"
    ],
    "name:zho_x_preferred":[
        "\u5c16\u53e3"
    ],
    "wof:name":"Jiankou",
    "wof:placetype":"locality"
},
  "geometry": {"coordinates":[120.511,32.11928],"type":"Point"}
}