{
  "type": "Feature",
  "properties": {
    "gn:admin1_code":"19.0",
    "gn:asciiname":"Dayucun",
    "gn:country_code":"CN",
    "gn:dem":106,
    "gn:feature_class":"P",
    "gn:feature_code":"PPL",
    "gn:name":"Dayucun",
    "gn:population":0,
    "gn:timezone":"Asia/Shanghai",
    "iso:country":"CN",
    "name:zho_x_preferred":[
        "\u5927\u6986\u6751"
    ],
    "wof:name":"Dayucun",
    "wof:placetype":"locality"
},
  "geometry": {"coordinates":[123.92149999999999,43.02382],"type":"Point"}
}