{
  "type": "Feature",
  "properties": {
    "gn:admin1_code":"8.0",
    "gn:asciiname":"Baochangcun",
    "gn:country_code":"CN",
    "gn:dem":235,
    "gn:feature_class":"P",
    "gn:feature_code":"PPL",
    "gn:name":"Baochangcun",
    "gn:population":0,
    "gn:timezone":"Asia/Shanghai",
    "iso:country":"CN",
    "name:zho_x_preferred":[
        "\u5b9d\u660c\u6751"
    ],
    "wof:name":"Baochangcun",
    "wof:placetype":"locality"
},
  "geometry": {"coordinates":[124.76073,48.75654],"type":"Point"}
}