{
  "type": "Feature",
  "properties": {
    "gn:admin1_code":"14.0",
    "gn:asciiname":"Nyainba",
    "gn:country_code":"CN",
    "gn:dem":4510,
    "gn:feature_class":"P",
    "gn:feature_code":"PPL",
    "gn:name":"Nyainba",
    "gn:population":0,
    "gn:timezone":"Asia/Urumqi",
    "iso:country":"CN",
    "name:bod_x_preferred":[
        "Nyainba"
    ],
    "name:zho_x_preferred":[
        "Nianba"
    ],
    "name:zho_x_variant":[
        "\u5ff5\u5df4"
    ],
    "wof:name":"Nyainba",
    "wof:placetype":"locality"
},
  "geometry": {"coordinates":[90.62899,29.05963],"type":"Point"}
}