{
  "type": "Feature",
  "properties": {
    "gn:admin1_code":"30",
    "gn:asciiname":"Pozai",
    "gn:country_code":"CN",
    "gn:dem":19,
    "gn:feature_class":"P",
    "gn:feature_code":"PPL",
    "gn:name":"Pozai",
    "gn:population":0,
    "gn:timezone":"Asia/Urumqi",
    "iso:country":"CN",
    "name:zho_x_preferred":[
        "\u5761\u4ed4"
    ],
    "wof:name":"Pozai",
    "wof:placetype":"locality"
},
  "geometry": {"coordinates":[110.99187999999999,21.66273],"type":"Point"}
}