{
  "type": "Feature",
  "properties": {
    "gn:admin1_code":"26.0",
    "gn:asciiname":"Jiajiazhuang",
    "gn:country_code":"CN",
    "gn:dem":1341,
    "gn:feature_class":"P",
    "gn:feature_code":"PPL",
    "gn:name":"Jiajiazhuang",
    "gn:population":0,
    "gn:timezone":"Asia/Shanghai",
    "iso:country":"CN",
    "name:und_x_variant":[
        "\u8d3e\u5bb6\u5e84"
    ],
    "wof:name":"Jiajiazhuang",
    "wof:placetype":"locality"
},
  "geometry": {"coordinates":[106.64026,34.00172],"type":"Point"}
}