{
  "type": "Feature",
  "properties": {
    "gn:admin1_code":"11.0",
    "gn:asciiname":"Peijiatang",
    "gn:country_code":"CN",
    "gn:dem":72,
    "gn:feature_class":"P",
    "gn:feature_code":"PPL",
    "gn:name":"Peijiatang",
    "gn:population":0,
    "gn:timezone":"Asia/Shanghai",
    "iso:country":"CN",
    "name:zho_x_preferred":[
        "\u57f9\u5bb6\u5858"
    ],
    "wof:name":"Peijiatang",
    "wof:placetype":"locality"
},
  "geometry": {"coordinates":[112.88504,27.63544000000001],"type":"Point"}
}