{
  "type": "Feature",
  "properties": {
    "gn:admin1_code":"24.0",
    "gn:asciiname":"Beidayu",
    "gn:country_code":"CN",
    "gn:dem":992,
    "gn:feature_class":"P",
    "gn:feature_code":"PPL",
    "gn:name":"Beidayu",
    "gn:population":0,
    "gn:timezone":"Asia/Shanghai",
    "iso:country":"CN",
    "name:zho_x_preferred":[
        "\u5317\u5927\u5cea"
    ],
    "wof:name":"Beidayu",
    "wof:placetype":"locality"
},
  "geometry": {"coordinates":[113.46992,38.295],"type":"Point"}
}