{
  "type": "Feature",
  "properties": {
    "gn:admin1_code":"16.0",
    "gn:asciiname":"Huazizhai",
    "gn:country_code":"CN",
    "gn:dem":1367,
    "gn:feature_class":"P",
    "gn:feature_code":"PPL",
    "gn:name":"Huazizhai",
    "gn:population":0,
    "gn:timezone":"Asia/Shanghai",
    "iso:country":"CN",
    "name:zho_x_preferred":[
        "\u82b1\u5b50\u5be8"
    ],
    "wof:name":"Huazizhai",
    "wof:placetype":"locality"
},
  "geometry": {"coordinates":[104.639,24.4017],"type":"Point"}
}