{
  "type": "Feature",
  "properties": {
    "gn:admin1_code":"05",
    "gn:asciiname":"Huiyuande",
    "gn:cc2":"CN",
    "gn:country_code":"CN",
    "gn:dem":233,
    "gn:feature_class":"P",
    "gn:feature_code":"PPL",
    "gn:name":"Huiyuande",
    "gn:population":0,
    "gn:timezone":"Asia/Shanghai",
    "iso:country":"CN",
    "name:und_x_variant":[
        "Hui-yuan-te",
        "Huiyuande"
    ],
    "wof:name":"Huiyuande",
    "wof:placetype":"locality"
},
  "geometry": {"coordinates":[125.93832999999999,43.45694],"type":"Point"}
}