{
  "type": "Feature",
  "properties": {
    "gn:admin1_code":"16.0",
    "gn:asciiname":"Tongsuo",
    "gn:country_code":"CN",
    "gn:dem":165,
    "gn:feature_class":"P",
    "gn:feature_code":"PPL",
    "gn:name":"Tongsuo",
    "gn:population":0,
    "gn:timezone":"Asia/Shanghai",
    "iso:country":"CN",
    "name:zho_x_preferred":[
        "\u94dc\u9501"
    ],
    "wof:name":"Tongsuo",
    "wof:placetype":"locality"
},
  "geometry": {"coordinates":[109.93600000000001,24.8055],"type":"Point"}
}