{
  "type": "Feature",
  "properties": {
    "gn:admin1_code":"26.0",
    "gn:asciiname":"Houyangxie",
    "gn:country_code":"CN",
    "gn:dem":828,
    "gn:feature_class":"P",
    "gn:feature_code":"PPL",
    "gn:name":"Houyangxie",
    "gn:population":0,
    "gn:timezone":"Asia/Shanghai",
    "iso:country":"CN",
    "name:zho_x_preferred":[
        "\u540e\u6768\u659c"
    ],
    "wof:name":"Houyangxie",
    "wof:placetype":"locality"
},
  "geometry": {"coordinates":[110.25227,35.40167],"type":"Point"}
}