{
  "type": "Feature",
  "properties": {
    "gn:admin1_code":"32.0",
    "gn:asciiname":"Sanbi",
    "gn:country_code":"CN",
    "gn:dem":2205,
    "gn:feature_class":"P",
    "gn:feature_code":"PPL",
    "gn:name":"Sanbi",
    "gn:population":0,
    "gn:timezone":"Asia/Shanghai",
    "iso:country":"CN",
    "name:zho_x_preferred":[
        "\u4e09\u6bd4"
    ],
    "wof:name":"Sanbi",
    "wof:placetype":"locality"
},
  "geometry": {"coordinates":[103.066,28.2838],"type":"Point"}
}