{
  "type": "Feature",
  "properties": {
    "gn:admin1_code":"11.0",
    "gn:asciiname":"Banlintou",
    "gn:country_code":"CN",
    "gn:dem":613,
    "gn:feature_class":"P",
    "gn:feature_code":"PPL",
    "gn:name":"Banlintou",
    "gn:population":0,
    "gn:timezone":"Asia/Shanghai",
    "iso:country":"CN",
    "name:zho_x_preferred":[
        "\u677f\u6797\u5934"
    ],
    "wof:name":"Banlintou",
    "wof:placetype":"locality"
},
  "geometry": {"coordinates":[109.91171,26.54464],"type":"Point"}
}