{
  "type": "Feature",
  "properties": {
    "gn:admin1_code":"14.0",
    "gn:asciiname":"Maintangragzi",
    "gn:country_code":"CN",
    "gn:dem":4626,
    "gn:feature_class":"P",
    "gn:feature_code":"PPL",
    "gn:name":"Maintangragzi",
    "gn:population":0,
    "gn:timezone":"Asia/Urumqi",
    "iso:country":"CN",
    "name:bod_x_preferred":[
        "Maintangragzi"
    ],
    "name:zho_x_preferred":[
        "Mendangrezi"
    ],
    "name:zho_x_variant":[
        "\u95e8\u5f53\u60f9\u5b5c",
        "Duoba Qu",
        "\u591a\u5df4\u533a"
    ],
    "wof:name":"Maintangragzi",
    "wof:placetype":"locality"
},
  "geometry": {"coordinates":[89.74569,31.41558],"type":"Point"}
}