{
  "type": "Feature",
  "properties": {
    "gn:admin1_code":"16.0",
    "gn:asciiname":"Shangnonglou",
    "gn:country_code":"CN",
    "gn:dem":460,
    "gn:feature_class":"P",
    "gn:feature_code":"PPL",
    "gn:name":"Shangnonglou",
    "gn:population":0,
    "gn:timezone":"Asia/Shanghai",
    "iso:country":"CN",
    "name:zho_x_preferred":[
        "\u4e0a\u5f04\u697c"
    ],
    "wof:name":"Shangnonglou",
    "wof:placetype":"locality"
},
  "geometry": {"coordinates":[107.904,24.0197],"type":"Point"}
}