{
  "type": "Feature",
  "properties": {
    "gn:admin1_code":"14.0",
    "gn:asciiname":"Dongbo",
    "gn:country_code":"CN",
    "gn:dem":4171,
    "gn:feature_class":"P",
    "gn:feature_code":"PPLF",
    "gn:name":"Dongbo",
    "gn:population":0,
    "gn:timezone":"Asia/Shanghai",
    "iso:country":"CN",
    "name:msa_x_preferred":[
        "Dongbo"
    ],
    "name:zho_x_preferred":[
        "\u4e1c\u6ce2"
    ],
    "wof:name":"Dongbo",
    "wof:placetype":"locality"
},
  "geometry": {"coordinates":[80.12075,31.1184],"type":"Point"}
}