{
  "type": "Feature",
  "properties": {
    "gn:admin1_code":"30",
    "gn:asciiname":"Shabaishui",
    "gn:country_code":"CN",
    "gn:dem":28,
    "gn:feature_class":"P",
    "gn:feature_code":"PPL",
    "gn:name":"Shabaishui",
    "gn:population":0,
    "gn:timezone":"Asia/Urumqi",
    "iso:country":"CN",
    "name:zho_x_preferred":[
        "\u6c99\u767d\u6c34"
    ],
    "wof:name":"Shabaishui",
    "wof:placetype":"locality"
},
  "geometry": {"coordinates":[109.90388,21.0779],"type":"Point"}
}