{
  "type": "Feature",
  "properties": {
    "gn:admin1_code":"7",
    "gn:asciiname":"Lingyuan Famuchang",
    "gn:country_code":"CN",
    "gn:dem":230,
    "gn:feature_class":"P",
    "gn:feature_code":"PPLF",
    "gn:name":"Lingyuan Famuchang",
    "gn:population":0,
    "gn:timezone":"Asia/Shanghai",
    "iso:country":"CN",
    "wof:name":"Lingyuan Famuchang",
    "wof:placetype":"locality"
},
  "geometry": {"coordinates":[117.72833,26.42556],"type":"Point"}
}