{
  "type": "Feature",
  "properties": {
    "gn:admin1_code":"15.0",
    "gn:asciiname":"Shangma",
    "gn:country_code":"CN",
    "gn:dem":1628,
    "gn:feature_class":"P",
    "gn:feature_code":"PPL",
    "gn:name":"Shangma",
    "gn:population":0,
    "gn:timezone":"Asia/Shanghai",
    "iso:country":"CN",
    "name:zho_x_preferred":[
        "\u4e0a\u9a6c"
    ],
    "wof:name":"Shangma",
    "wof:placetype":"locality"
},
  "geometry": {"coordinates":[106.565,35.7271],"type":"Point"}
}