{
  "type": "Feature",
  "properties": {
    "gn:admin1_code":"4.0",
    "gn:asciiname":"Nongchang Liulian",
    "gn:country_code":"CN",
    "gn:dem":4,
    "gn:feature_class":"P",
    "gn:feature_code":"PPLF",
    "gn:name":"Nongchang Liulian",
    "gn:population":0,
    "gn:timezone":"Asia/Shanghai",
    "iso:country":"CN",
    "name:zho_x_preferred":[
        "Nongchang Liulian"
    ],
    "name:zho_x_variant":[
        "\u519c\u573a\u516d\u8fde"
    ],
    "wof:name":"Nongchang Liulian",
    "wof:placetype":"locality"
},
  "geometry": {"coordinates":[121.36151,32.17819],"type":"Point"}
}