{
  "type": "Feature",
  "properties": {
    "gn:admin1_code":"10",
    "gn:asciiname":"Qianxiaomei",
    "gn:country_code":"CN",
    "gn:dem":53,
    "gn:feature_class":"P",
    "gn:feature_code":"PPL",
    "gn:name":"Qianxiaomei",
    "gn:population":0,
    "gn:timezone":"Asia/Shanghai",
    "iso:country":"CN",
    "name:zho_x_preferred":[
        "\u524d\u5c0f\u679a"
    ],
    "wof:name":"Qianxiaomei",
    "wof:placetype":"locality"
},
  "geometry": {"coordinates":[114.66200000000001,37.8277],"type":"Point"}
}