{
  "type": "Feature",
  "properties": {
    "gn:admin1_code":"5.0",
    "gn:asciiname":"Humicun",
    "gn:country_code":"CN",
    "gn:dem":290,
    "gn:feature_class":"P",
    "gn:feature_code":"PPL",
    "gn:name":"Humicun",
    "gn:population":0,
    "gn:timezone":"Asia/Shanghai",
    "iso:country":"CN",
    "name:zho_x_preferred":[
        "\u80e1\u7c73\u6751"
    ],
    "wof:name":"Humicun",
    "wof:placetype":"locality"
},
  "geometry": {"coordinates":[125.39498,43.1908],"type":"Point"}
}