{
  "type": "Feature",
  "properties": {
    "gn:admin1_code":"26.0",
    "gn:asciiname":"Bailongcun",
    "gn:country_code":"CN",
    "gn:dem":451,
    "gn:feature_class":"P",
    "gn:feature_code":"PPL",
    "gn:name":"Bailongcun",
    "gn:population":0,
    "gn:timezone":"Asia/Shanghai",
    "iso:country":"CN",
    "name:zho_x_preferred":[
        "\u767d\u9f99\u6751"
    ],
    "wof:name":"Bailongcun",
    "wof:placetype":"locality"
},
  "geometry": {"coordinates":[108.01085999999999,34.25492],"type":"Point"}
}