{
  "type": "Feature",
  "properties": {
    "gn:admin1_code":"4.0",
    "gn:asciiname":"Guojicun",
    "gn:country_code":"CN",
    "gn:dem":2,
    "gn:feature_class":"P",
    "gn:feature_code":"PPL",
    "gn:name":"Guojicun",
    "gn:population":0,
    "gn:timezone":"Asia/Shanghai",
    "iso:country":"CN",
    "name:zho_x_preferred":[
        "\u90ed\u96c6\u6751"
    ],
    "wof:name":"Guojicun",
    "wof:placetype":"locality"
},
  "geometry": {"coordinates":[119.96483000000001,34.03969],"type":"Point"}
}