{
  "type": "Feature",
  "properties": {
    "gn:admin1_code":"8.0",
    "gn:asciiname":"Sunjiatun",
    "gn:country_code":"CN",
    "gn:dem":282,
    "gn:feature_class":"P",
    "gn:feature_code":"PPL",
    "gn:name":"Sunjiatun",
    "gn:population":0,
    "gn:timezone":"Asia/Shanghai",
    "iso:country":"CN",
    "name:zho_x_preferred":[
        "\u5b59\u5bb6\u5c6f"
    ],
    "wof:name":"Sunjiatun",
    "wof:placetype":"locality"
},
  "geometry": {"coordinates":[126.06802999999999,47.80826],"type":"Point"}
}