{
  "type": "Feature",
  "properties": {
    "gn:admin1_code":"6.0",
    "gn:asciiname":"Qiekuxuema",
    "gn:country_code":"CN",
    "gn:dem":3401,
    "gn:feature_class":"P",
    "gn:feature_code":"PPL",
    "gn:name":"Qiekuxuema",
    "gn:population":0,
    "gn:timezone":"Asia/Shanghai",
    "iso:country":"CN",
    "name:und_x_variant":[
        "\u5207\u5e93\u96ea\u739b"
    ],
    "wof:name":"Qiekuxuema",
    "wof:placetype":"locality"
},
  "geometry": {"coordinates":[100.68455,37.21995],"type":"Point"}
}