{
  "type": "Feature",
  "properties": {
    "gn:admin1_code":"16.0",
    "gn:asciiname":"Jinji",
    "gn:country_code":"CN",
    "gn:dem":81,
    "gn:feature_class":"P",
    "gn:feature_code":"PPL",
    "gn:name":"Jinji",
    "gn:population":0,
    "gn:timezone":"Asia/Shanghai",
    "iso:country":"CN",
    "name:ceb_x_preferred":[
        "Jinji"
    ],
    "name:deu_x_preferred":[
        "Jinji"
    ],
    "name:swe_x_preferred":[
        "Jinji"
    ],
    "name:zho_x_preferred":[
        "\u91d1\u9e21"
    ],
    "wof:name":"Jinji",
    "wof:placetype":"locality"
},
  "geometry": {"coordinates":[109.621,23.8976],"type":"Point"}
}