{
  "type": "Feature",
  "properties": {
    "gn:admin1_code":"30",
    "gn:asciiname":"Shikuaitian",
    "gn:country_code":"CN",
    "gn:dem":30,
    "gn:feature_class":"P",
    "gn:feature_code":"PPL",
    "gn:name":"Shikuaitian",
    "gn:population":0,
    "gn:timezone":"Asia/Urumqi",
    "iso:country":"CN",
    "name:zho_x_preferred":[
        "\u5341\u5feb\u7530"
    ],
    "wof:name":"Shikuaitian",
    "wof:placetype":"locality"
},
  "geometry": {"coordinates":[109.93331999999999,21.50253],"type":"Point"}
}