{
  "type": "Feature",
  "properties": {
    "gn:admin1_code":"26.0",
    "gn:asciiname":"Fumazhuangcun",
    "gn:country_code":"CN",
    "gn:dem":719,
    "gn:feature_class":"P",
    "gn:feature_code":"PPL",
    "gn:name":"Fumazhuangcun",
    "gn:population":0,
    "gn:timezone":"Asia/Shanghai",
    "iso:country":"CN",
    "name:zho_x_preferred":[
        "\u9644\u9a6c\u5e84\u6751"
    ],
    "wof:name":"Fumazhuangcun",
    "wof:placetype":"locality"
},
  "geometry": {"coordinates":[107.79272,34.46769],"type":"Point"}
}