{
  "type": "Feature",
  "properties": {
    "gn:admin1_code":"12.0",
    "gn:asciiname":"Qianwan",
    "gn:country_code":"CN",
    "gn:dem":1036,
    "gn:feature_class":"P",
    "gn:feature_code":"PPL",
    "gn:name":"Qianwan",
    "gn:population":0,
    "gn:timezone":"Asia/Shanghai",
    "iso:country":"CN",
    "name:zho_x_preferred":[
        "\u524d\u6e7e"
    ],
    "wof:name":"Qianwan",
    "wof:placetype":"locality"
},
  "geometry": {"coordinates":[111.49043,31.44484000000001],"type":"Point"}
}