{
  "type": "Feature",
  "properties": {
    "gn:admin1_code":"30",
    "gn:asciiname":"Liuzhangcun",
    "gn:country_code":"CN",
    "gn:dem":7,
    "gn:feature_class":"P",
    "gn:feature_code":"PPL",
    "gn:name":"Liuzhangcun",
    "gn:population":0,
    "gn:timezone":"Asia/Urumqi",
    "iso:country":"CN",
    "name:zho_x_preferred":[
        "\u5218\u5f20\u6751"
    ],
    "wof:name":"Liuzhangcun",
    "wof:placetype":"locality"
},
  "geometry": {"coordinates":[109.74464,20.6633],"type":"Point"}
}