{
  "type": "Feature",
  "properties": {
    "gn:admin1_code":"30",
    "gn:asciiname":"Houhai",
    "gn:country_code":"CN",
    "gn:dem":7,
    "gn:feature_class":"P",
    "gn:feature_code":"PPL",
    "gn:name":"Houhai",
    "gn:population":0,
    "gn:timezone":"Asia/Urumqi",
    "iso:country":"CN",
    "name:und_x_variant":[
        "\u540e\u6d77",
        "Houhaicun",
        "\u540e\u6d77\u6751"
    ],
    "name:zho_x_preferred":[
        "\u540e\u6d77"
    ],
    "wof:name":"Houhai",
    "wof:placetype":"locality"
},
  "geometry": {"coordinates":[110.46496999999999,20.64064],"type":"Point"}
}