{
  "type": "Feature",
  "properties": {
    "gn:admin1_code":"26.0",
    "gn:asciiname":"Houyicun",
    "gn:country_code":"CN",
    "gn:dem":850,
    "gn:feature_class":"P",
    "gn:feature_code":"PPL",
    "gn:name":"Houyicun",
    "gn:population":0,
    "gn:timezone":"Asia/Shanghai",
    "iso:country":"CN",
    "name:zho_x_preferred":[
        "\u539a\u4e49\u6751"
    ],
    "wof:name":"Houyicun",
    "wof:placetype":"locality"
},
  "geometry": {"coordinates":[109.58589000000001,35.26556],"type":"Point"}
}