{
  "type": "Feature",
  "properties": {
    "gn:admin1_code":"32.0",
    "gn:asciiname":"Taipingqiao",
    "gn:country_code":"CN",
    "gn:dem":461,
    "gn:feature_class":"P",
    "gn:feature_code":"PPL",
    "gn:name":"Taipingqiao",
    "gn:population":0,
    "gn:timezone":"Asia/Shanghai",
    "iso:country":"CN",
    "name:zho_x_preferred":[
        "\u592a\u5e73\u6865"
    ],
    "wof:name":"Taipingqiao",
    "wof:placetype":"locality"
},
  "geometry": {"coordinates":[107.908,31.1644],"type":"Point"}
}