{
  "type": "Feature",
  "properties": {
    "gn:admin1_code":"14.0",
    "gn:asciiname":"Zhongcun",
    "gn:country_code":"CN",
    "gn:dem":4739,
    "gn:feature_class":"P",
    "gn:feature_code":"PPL",
    "gn:name":"Zhongcun",
    "gn:population":0,
    "gn:timezone":"Asia/Urumqi",
    "iso:country":"CN",
    "name:zho_x_preferred":[
        "\u949f\u6751"
    ],
    "wof:name":"Zhongcun",
    "wof:placetype":"locality"
},
  "geometry": {"coordinates":[88.1645,28.9778],"type":"Point"}
}