{
  "type": "Feature",
  "properties": {
    "gn:admin1_code":"4.0",
    "gn:asciiname":"Panzhuang",
    "gn:country_code":"CN",
    "gn:dem":4,
    "gn:feature_class":"P",
    "gn:feature_code":"PPL",
    "gn:name":"Panzhuang",
    "gn:population":0,
    "gn:timezone":"Asia/Shanghai",
    "iso:country":"CN",
    "name:zho_x_preferred":[
        "Panzhuang"
    ],
    "name:zho_x_variant":[
        "\u6f58\u5e84"
    ],
    "wof:name":"Panzhuang",
    "wof:placetype":"locality"
},
  "geometry": {"coordinates":[120.04281,34.18482],"type":"Point"}
}