{
  "type": "Feature",
  "properties": {
    "gn:admin1_code":"10",
    "gn:asciiname":"Waimajia",
    "gn:country_code":"CN",
    "gn:dem":1488,
    "gn:feature_class":"P",
    "gn:feature_code":"PPL",
    "gn:name":"Waimajia",
    "gn:population":0,
    "gn:timezone":"Asia/Shanghai",
    "iso:country":"CN",
    "name:zho_x_preferred":[
        "\u5916\u9a6c\u67b6"
    ],
    "wof:name":"Waimajia",
    "wof:placetype":"locality"
},
  "geometry": {"coordinates":[116.13828999999998,41.72398],"type":"Point"}
}