{
  "type": "Feature",
  "properties": {
    "gn:admin1_code":"19.0",
    "gn:asciiname":"Houbaliqiaozi",
    "gn:country_code":"CN",
    "gn:dem":89,
    "gn:feature_class":"P",
    "gn:feature_code":"PPL",
    "gn:name":"Houbaliqiaozi",
    "gn:population":0,
    "gn:timezone":"Asia/Shanghai",
    "iso:country":"CN",
    "name:zho_x_preferred":[
        "\u540e\u516b\u91cc\u6865\u5b50"
    ],
    "wof:name":"Houbaliqiaozi",
    "wof:placetype":"locality"
},
  "geometry": {"coordinates":[124.066,42.5741],"type":"Point"}
}