{
  "type": "Feature",
  "properties": {
    "gn:admin1_code":"12.0",
    "gn:asciiname":"Zhulin'ao",
    "gn:country_code":"CN",
    "gn:dem":112,
    "gn:feature_class":"P",
    "gn:feature_code":"PPL",
    "gn:name":"Zhulin\u2019ao",
    "gn:population":0,
    "gn:timezone":"Asia/Shanghai",
    "iso:country":"CN",
    "name:zho_x_preferred":[
        "Zhulin\u2019ao"
    ],
    "name:zho_x_variant":[
        "\u7af9\u6797\u5773"
    ],
    "wof:name":"Zhulin'ao",
    "wof:placetype":"locality"
},
  "geometry": {"coordinates":[115.50537,30.65596],"type":"Point"}
}