{
  "type": "Feature",
  "properties": {
    "gn:admin1_code":"29",
    "gn:asciiname":"Awushao",
    "gn:country_code":"CN",
    "gn:dem":1624,
    "gn:feature_class":"P",
    "gn:feature_code":"PPL",
    "gn:name":"Awushao",
    "gn:population":0,
    "gn:timezone":"Asia/Shanghai",
    "iso:country":"CN",
    "name:zho_x_preferred":[
        "\u963f\u4e4c\u54e8"
    ],
    "wof:name":"Awushao",
    "wof:placetype":"locality"
},
  "geometry": {"coordinates":[101.916,24.7488],"type":"Point"}
}