{
  "type": "Feature",
  "properties": {
    "gn:admin1_code":"25",
    "gn:asciiname":"Lengjiazhuang",
    "gn:country_code":"CN",
    "gn:dem":174,
    "gn:feature_class":"P",
    "gn:feature_code":"PPL",
    "gn:name":"Lengjiazhuang",
    "gn:population":0,
    "gn:timezone":"Asia/Shanghai",
    "iso:country":"CN",
    "name:zho_x_preferred":[
        "\u51b7\u5bb6\u5e84"
    ],
    "wof:name":"Lengjiazhuang",
    "wof:placetype":"locality"
},
  "geometry": {"coordinates":[117.488,36.2683],"type":"Point"}
}