{
  "type": "Feature",
  "properties": {
    "gn:admin1_code":"22.0",
    "gn:asciiname":"Xiaodecun",
    "gn:country_code":"CN",
    "gn:dem":47,
    "gn:feature_class":"P",
    "gn:feature_code":"PPL",
    "gn:name":"Xiaodecun",
    "gn:population":0,
    "gn:timezone":"Asia/Shanghai",
    "iso:country":"CN",
    "name:zho_x_preferred":[
        "\u5b5d\u5fb7\u6751"
    ],
    "wof:name":"Xiaodecun",
    "wof:placetype":"locality"
},
  "geometry": {"coordinates":[116.77957000000001,40.26377],"type":"Point"}
}