{
  "type": "Feature",
  "properties": {
    "gn:admin1_code":"4.0",
    "gn:asciiname":"Yaogang Bazu",
    "gn:country_code":"CN",
    "gn:dem":2,
    "gn:feature_class":"P",
    "gn:feature_code":"PPLF",
    "gn:name":"Yaogang Bazu",
    "gn:population":0,
    "gn:timezone":"Asia/Shanghai",
    "iso:country":"CN",
    "name:zho_x_preferred":[
        "\u7a91\u6e2f\u516b\u7ec4"
    ],
    "wof:name":"Yaogang Bazu",
    "wof:placetype":"locality"
},
  "geometry": {"coordinates":[120.379,33.0257],"type":"Point"}
}