{
  "type": "Feature",
  "properties": {
    "gn:admin1_code":"32.0",
    "gn:asciiname":"Zhufengwan",
    "gn:country_code":"CN",
    "gn:dem":416,
    "gn:feature_class":"P",
    "gn:feature_code":"PPL",
    "gn:name":"Zhufengwan",
    "gn:population":0,
    "gn:timezone":"Asia/Shanghai",
    "iso:country":"CN",
    "name:zho_x_preferred":[
        "\u6731\u51e4\u6e7e"
    ],
    "wof:name":"Zhufengwan",
    "wof:placetype":"locality"
},
  "geometry": {"coordinates":[104.854,29.9982],"type":"Point"}
}