{
  "type": "Feature",
  "properties": {
    "gn:admin1_code":"26.0",
    "gn:asciiname":"Baiyuncun",
    "gn:country_code":"CN",
    "gn:dem":1586,
    "gn:feature_class":"P",
    "gn:feature_code":"PPL",
    "gn:name":"Baiyuncun",
    "gn:population":0,
    "gn:timezone":"Asia/Shanghai",
    "iso:country":"CN",
    "name:zho_x_preferred":[
        "\u767d\u4e91\u6751"
    ],
    "wof:name":"Baiyuncun",
    "wof:placetype":"locality"
},
  "geometry": {"coordinates":[107.62121,32.59625],"type":"Point"}
}