{
  "type": "Feature",
  "properties": {
    "gn:admin1_code":"32.0",
    "gn:asciiname":"Maike",
    "gn:country_code":"CN",
    "gn:dem":3832,
    "gn:feature_class":"P",
    "gn:feature_code":"PPL",
    "gn:name":"Maike",
    "gn:population":0,
    "gn:timezone":"Asia/Shanghai",
    "iso:country":"CN",
    "name:zho_x_preferred":[
        "\u9ea6\u79d1"
    ],
    "wof:name":"Maike",
    "wof:placetype":"locality"
},
  "geometry": {"coordinates":[100.371,31.3272],"type":"Point"}
}