{
  "type": "Feature",
  "properties": {
    "gn:admin1_code":"02",
    "gn:asciiname":"Dawacuo",
    "gn:country_code":"CN",
    "gn:dem":127,
    "gn:feature_class":"P",
    "gn:feature_code":"PPL",
    "gn:name":"Dawacuo",
    "gn:population":0,
    "gn:timezone":"Asia/Shanghai",
    "iso:country":"CN",
    "name:zho_x_preferred":[
        "\u5927\u74e6\u539d"
    ],
    "wof:name":"Dawacuo",
    "wof:placetype":"locality"
},
  "geometry": {"coordinates":[120.50706,27.22526],"type":"Point"}
}