{
  "type": "Feature",
  "properties": {
    "gn:admin1_code":"4.0",
    "gn:asciiname":"Qianshi",
    "gn:country_code":"CN",
    "gn:dem":8,
    "gn:feature_class":"P",
    "gn:feature_code":"PPL",
    "gn:name":"Qianshi",
    "gn:population":0,
    "gn:timezone":"Asia/Shanghai",
    "iso:country":"CN",
    "name:zho_x_preferred":[
        "\u524d\u65f6"
    ],
    "wof:name":"Qianshi",
    "wof:placetype":"locality"
},
  "geometry": {"coordinates":[120.1414,32.45225],"type":"Point"}
}