{
  "type": "Feature",
  "properties": {
    "gn:admin1_code":"10",
    "gn:asciiname":"Houfeili",
    "gn:cc2":"CN",
    "gn:country_code":"CN",
    "gn:dem":66,
    "gn:feature_class":"P",
    "gn:feature_code":"PPL",
    "gn:name":"Houfeili",
    "gn:population":0,
    "gn:timezone":"Asia/Shanghai",
    "iso:country":"CN",
    "name:und_x_variant":[
        "Hou-p\u2019ei-li",
        "Houfeili"
    ],
    "wof:name":"Houfeili",
    "wof:placetype":"locality"
},
  "geometry": {"coordinates":[114.59417000000001,36.40583],"type":"Point"}
}