{
  "type": "Feature",
  "properties": {
    "gn:admin1_code":"05",
    "gn:asciiname":"Hsin-kang-li",
    "gn:country_code":"CN",
    "gn:dem":523,
    "gn:feature_class":"P",
    "gn:feature_code":"PPL",
    "gn:name":"Hsin-kang-li",
    "gn:population":0,
    "gn:timezone":"Asia/Shanghai",
    "iso:country":"CN",
    "wof:name":"Hsin-kang-li",
    "wof:placetype":"locality"
},
  "geometry": {"coordinates":[127.70083,41.41861],"type":"Point"}
}