{
  "type": "Feature",
  "properties": {
    "gn:admin1_code":"30.0",
    "gn:asciiname":"Fo'ao",
    "gn:country_code":"CN",
    "gn:dem":16,
    "gn:feature_class":"P",
    "gn:feature_code":"PPL",
    "gn:name":"Fo\u2019ao",
    "gn:population":0,
    "gn:timezone":"Asia/Shanghai",
    "iso:country":"CN",
    "name:und_x_variant":[
        "Fo\u2019ao"
    ],
    "name:zho_x_preferred":[
        "\u4f5b\u51f9"
    ],
    "wof:name":"Fo'ao",
    "wof:placetype":"locality"
},
  "geometry": {"coordinates":[112.67422000000001,22.29351],"type":"Point"}
}