{
  "type": "Feature",
  "properties": {
    "gn:admin1_code":"14.0",
    "gn:asciiname":"Chogpu",
    "gn:country_code":"CN",
    "gn:dem":4430,
    "gn:feature_class":"P",
    "gn:feature_code":"PPLF",
    "gn:name":"Chogpu",
    "gn:population":0,
    "gn:timezone":"Asia/Urumqi",
    "iso:country":"CN",
    "name:bod_x_preferred":[
        "Chogpu"
    ],
    "name:zho_x_preferred":[
        "Zhuopu"
    ],
    "name:zho_x_variant":[
        "\u5353\u666e"
    ],
    "wof:name":"Chogpu",
    "wof:placetype":"locality"
},
  "geometry": {"coordinates":[91.70099999999999,29.901],"type":"Point"}
}