{
  "type": "Feature",
  "properties": {
    "gn:admin1_code":"15.0",
    "gn:asciiname":"Songzhuang",
    "gn:country_code":"CN",
    "gn:dem":1919,
    "gn:feature_class":"P",
    "gn:feature_code":"PPL",
    "gn:name":"Songzhuang",
    "gn:population":0,
    "gn:timezone":"Asia/Shanghai",
    "iso:country":"CN",
    "name:und_x_variant":[
        "\u5b8b\u5e84"
    ],
    "wof:name":"Songzhuang",
    "wof:placetype":"locality"
},
  "geometry": {"coordinates":[105.22646,35.46116],"type":"Point"}
}