{
  "type": "Feature",
  "properties": {
    "gn:admin1_code":"3.0",
    "gn:asciiname":"Tongjiawan",
    "gn:country_code":"CN",
    "gn:dem":46,
    "gn:feature_class":"P",
    "gn:feature_code":"PPL",
    "gn:name":"Tongjiawan",
    "gn:population":0,
    "gn:timezone":"Asia/Shanghai",
    "iso:country":"CN",
    "name:zho_x_preferred":[
        "\u7ae5\u5bb6\u6e7e"
    ],
    "wof:name":"Tongjiawan",
    "wof:placetype":"locality"
},
  "geometry": {"coordinates":[117.24227,28.86716],"type":"Point"}
}