{
  "type": "Feature",
  "properties": {
    "gn:admin1_code":"26",
    "gn:asciiname":"Guanshan",
    "gn:cc2":"CN",
    "gn:country_code":"CN",
    "gn:dem":2151,
    "gn:feature_class":"P",
    "gn:feature_code":"PPL",
    "gn:name":"Guanshan",
    "gn:population":0,
    "gn:timezone":"Asia/Shanghai",
    "iso:country":"CN",
    "name:und_x_variant":[
        "Kuan-shan",
        "Guanshan"
    ],
    "wof:name":"Guanshan",
    "wof:placetype":"locality"
},
  "geometry": {"coordinates":[106.55,34.73333],"type":"Point"}
}