{
  "type": "Feature",
  "properties": {
    "gn:admin1_code":"31.0",
    "gn:asciiname":"Meitingcun",
    "gn:country_code":"CN",
    "gn:dem":57,
    "gn:feature_class":"P",
    "gn:feature_code":"PPL",
    "gn:name":"Meitingcun",
    "gn:population":0,
    "gn:timezone":"Asia/Shanghai",
    "iso:country":"CN",
    "name:zho_x_preferred":[
        "Meitingcun"
    ],
    "name:zho_x_variant":[
        "\u7f8e\u4ead\u6751"
    ],
    "wof:name":"Meitingcun",
    "wof:placetype":"locality"
},
  "geometry": {"coordinates":[110.07872999999999,19.83117],"type":"Point"}
}