{
  "type": "Feature",
  "properties": {
    "gn:admin1_code":"1.0",
    "gn:asciiname":"Guanmiaocun",
    "gn:country_code":"CN",
    "gn:dem":72,
    "gn:feature_class":"P",
    "gn:feature_code":"PPL",
    "gn:name":"Guanmiaocun",
    "gn:population":0,
    "gn:timezone":"Asia/Shanghai",
    "iso:country":"CN",
    "name:zho_x_preferred":[
        "\u5173\u5e99\u6751"
    ],
    "wof:name":"Guanmiaocun",
    "wof:placetype":"locality"
},
  "geometry": {"coordinates":[117.42919999999999,31.00605],"type":"Point"}
}