{
  "type": "Feature",
  "properties": {
    "gn:admin1_code":"29.0",
    "gn:asciiname":"Ayuanluye",
    "gn:country_code":"CN",
    "gn:dem":2705,
    "gn:feature_class":"P",
    "gn:feature_code":"PPL",
    "gn:name":"Ayuanluye",
    "gn:population":0,
    "gn:timezone":"Asia/Shanghai",
    "iso:country":"CN",
    "name:zho_x_preferred":[
        "\u963f\u5143\u8def\u7237"
    ],
    "wof:name":"Ayuanluye",
    "wof:placetype":"locality"
},
  "geometry": {"coordinates":[99.2651,26.6133],"type":"Point"}
}