{
  "type": "Feature",
  "properties": {
    "gn:admin1_code":"4.0",
    "gn:asciiname":"Panchakou",
    "gn:country_code":"CN",
    "gn:dem":6,
    "gn:feature_class":"P",
    "gn:feature_code":"PPL",
    "gn:name":"Panchakou",
    "gn:population":0,
    "gn:timezone":"Asia/Shanghai",
    "iso:country":"CN",
    "name:zho_x_preferred":[
        "Panchakou"
    ],
    "name:zho_x_variant":[
        "\u76d8\u5c94\u53e3"
    ],
    "wof:name":"Panchakou",
    "wof:placetype":"locality"
},
  "geometry": {"coordinates":[119.39978000000001,33.13776],"type":"Point"}
}