{
  "type": "Feature",
  "properties": {
    "gn:admin1_code":"4.0",
    "gn:asciiname":"Hutang",
    "gn:country_code":"CN",
    "gn:dem":6,
    "gn:feature_class":"P",
    "gn:feature_code":"PPLA3",
    "gn:name":"Hutang",
    "gn:population":0,
    "gn:timezone":"Asia/Shanghai",
    "iso:country":"CN",
    "name:mlg_x_preferred":[
        "Hutang"
    ],
    "name:und_x_variant":[
        "Hutang Zhen",
        "Wujin Qu"
    ],
    "name:zho_x_preferred":[
        "\u6e56\u5858"
    ],
    "name:zho_x_variant":[
        "\u6e56\u5858\u9547",
        "\u6b66\u8fdb\u533a"
    ],
    "wof:name":"Hutang",
    "wof:placetype":"locality"
},
  "geometry": {"coordinates":[119.94458,31.71581],"type":"Point"}
}