{
  "type": "Feature",
  "properties": {
    "gn:admin1_code":"19.0",
    "gn:asciiname":"Linyezu",
    "gn:country_code":"CN",
    "gn:dem":505,
    "gn:feature_class":"P",
    "gn:feature_code":"PPL",
    "gn:name":"Linyezu",
    "gn:population":0,
    "gn:timezone":"Asia/Shanghai",
    "iso:country":"CN",
    "name:zho_x_preferred":[
        "\u6797\u4e1a\u7ec4"
    ],
    "wof:name":"Linyezu",
    "wof:placetype":"locality"
},
  "geometry": {"coordinates":[125.06999999999999,41.6429],"type":"Point"}
}