{
  "type": "Feature",
  "properties": {
    "gn:admin1_code":"18",
    "gn:asciiname":"Yulang",
    "gn:country_code":"CN",
    "gn:dem":1322,
    "gn:feature_class":"P",
    "gn:feature_code":"PPL",
    "gn:name":"Yulang",
    "gn:population":0,
    "gn:timezone":"Asia/Shanghai",
    "iso:country":"CN",
    "name:zho_x_preferred":[
        "\u9c7c\u6d6a"
    ],
    "wof:name":"Yulang",
    "wof:placetype":"locality"
},
  "geometry": {"coordinates":[105.586,25.1447],"type":"Point"}
}