{
  "type": "Feature",
  "properties": {
    "gn:admin1_code":"2",
    "gn:asciiname":"Baishadai",
    "gn:country_code":"CN",
    "gn:dem":774,
    "gn:feature_class":"P",
    "gn:feature_code":"PPL",
    "gn:name":"Baishadai",
    "gn:population":0,
    "gn:timezone":"Asia/Shanghai",
    "iso:country":"CN",
    "name:zho_x_preferred":[
        "\u767d\u6c99\u5cb1"
    ],
    "wof:name":"Baishadai",
    "wof:placetype":"locality"
},
  "geometry": {"coordinates":[119.58194,27.85444],"type":"Point"}
}