{
  "type": "Feature",
  "properties": {
    "gn:admin1_code":"4.0",
    "gn:asciiname":"Fanguhuang",
    "gn:country_code":"CN",
    "gn:dem":15,
    "gn:feature_class":"P",
    "gn:feature_code":"PPL",
    "gn:name":"Fanguhuang",
    "gn:population":0,
    "gn:timezone":"Asia/Shanghai",
    "iso:country":"CN",
    "name:zho_x_preferred":[
        "\u6a0a\u53e4\u968d"
    ],
    "wof:name":"Fanguhuang",
    "wof:placetype":"locality"
},
  "geometry": {"coordinates":[119.32941,31.95989],"type":"Point"}
}