{
  "type": "Feature",
  "properties": {
    "gn:admin1_code":"02",
    "gn:asciiname":"Dahuangshimen",
    "gn:cc2":"CN",
    "gn:country_code":"CN",
    "gn:dem":35,
    "gn:feature_class":"P",
    "gn:feature_code":"PPL",
    "gn:name":"Dahuangshimen",
    "gn:population":0,
    "gn:timezone":"Asia/Shanghai",
    "iso:country":"CN",
    "name:und_x_variant":[
        "Huang-shih-men",
        "Dahuangshimen"
    ],
    "wof:name":"Dahuangshimen",
    "wof:placetype":"locality"
},
  "geometry": {"coordinates":[122.10889,29.895],"type":"Point"}
}