{
  "type": "Feature",
  "properties": {
    "gn:admin1_code":"30",
    "gn:asciiname":"Xiangche",
    "gn:country_code":"CN",
    "gn:dem":317,
    "gn:feature_class":"P",
    "gn:feature_code":"PPL",
    "gn:name":"Xiangche",
    "gn:population":0,
    "gn:timezone":"Asia/Shanghai",
    "iso:country":"CN",
    "name:zho_x_preferred":[
        "\u9999\u8f66"
    ],
    "wof:name":"Xiangche",
    "wof:placetype":"locality"
},
  "geometry": {"coordinates":[111.76994999999999,23.44807],"type":"Point"}
}