{
  "type": "Feature",
  "properties": {
    "gn:admin1_code":"26.0",
    "gn:asciiname":"Xigoukoucun",
    "gn:country_code":"CN",
    "gn:dem":693,
    "gn:feature_class":"P",
    "gn:feature_code":"PPL",
    "gn:name":"Xigoukoucun",
    "gn:population":0,
    "gn:timezone":"Asia/Shanghai",
    "iso:country":"CN",
    "name:zho_x_preferred":[
        "\u897f\u6c9f\u53e3\u6751"
    ],
    "wof:name":"Xigoukoucun",
    "wof:placetype":"locality"
},
  "geometry": {"coordinates":[110.28339,33.67641],"type":"Point"}
}