{
  "type": "Feature",
  "properties": {
    "gn:admin1_code":"32.0",
    "gn:asciiname":"Qiyazi",
    "gn:country_code":"CN",
    "gn:dem":1213,
    "gn:feature_class":"P",
    "gn:feature_code":"PPL",
    "gn:name":"Qiyazi",
    "gn:population":0,
    "gn:timezone":"Asia/Shanghai",
    "iso:country":"CN",
    "name:und_x_variant":[
        "\u6f06\u57ad\u5b50"
    ],
    "wof:name":"Qiyazi",
    "wof:placetype":"locality"
},
  "geometry": {"coordinates":[106.02218000000001,32.84281],"type":"Point"}
}