{
  "type": "Feature",
  "properties": {
    "gn:admin1_code":"30.0",
    "gn:asciiname":"Shitian",
    "gn:country_code":"CN",
    "gn:dem":95,
    "gn:feature_class":"P",
    "gn:feature_code":"PPL",
    "gn:name":"Shitian",
    "gn:population":0,
    "gn:timezone":"Asia/Shanghai",
    "iso:country":"CN",
    "name:zho_x_preferred":[
        "\u77f3\u7530"
    ],
    "wof:name":"Shitian",
    "wof:placetype":"locality"
},
  "geometry": {"coordinates":[114.22058,23.77101],"type":"Point"}
}