{
  "type": "Feature",
  "properties": {
    "gn:admin1_code":"3.0",
    "gn:asciiname":"Sanchawo",
    "gn:country_code":"CN",
    "gn:dem":251,
    "gn:feature_class":"P",
    "gn:feature_code":"PPL",
    "gn:name":"Sanchawo",
    "gn:population":0,
    "gn:timezone":"Asia/Shanghai",
    "iso:country":"CN",
    "name:und_x_variant":[
        "\u4e09\u5c94\u7a9d"
    ],
    "wof:name":"Sanchawo",
    "wof:placetype":"locality"
},
  "geometry": {"coordinates":[114.45005,28.9684],"type":"Point"}
}