{
  "type": "Feature",
  "properties": {
    "gn:admin1_code":"15.0",
    "gn:asciiname":"Hejiazhuang",
    "gn:country_code":"CN",
    "gn:dem":1729,
    "gn:feature_class":"P",
    "gn:feature_code":"PPL",
    "gn:name":"Hejiazhuang",
    "gn:population":0,
    "gn:timezone":"Asia/Shanghai",
    "iso:country":"CN",
    "name:und_x_variant":[
        "\u4f55\u5bb6\u5e84"
    ],
    "wof:name":"Hejiazhuang",
    "wof:placetype":"locality"
},
  "geometry": {"coordinates":[105.25306999999999,33.7947],"type":"Point"}
}