{
  "type": "Feature",
  "properties": {
    "gn:admin1_code":"12.0",
    "gn:asciiname":"Meiziya",
    "gn:country_code":"CN",
    "gn:dem":115,
    "gn:feature_class":"P",
    "gn:feature_code":"PPL",
    "gn:name":"Meiziya",
    "gn:population":0,
    "gn:timezone":"Asia/Shanghai",
    "iso:country":"CN",
    "name:zho_x_preferred":[
        "Meiziya"
    ],
    "name:zho_x_variant":[
        "\u6885\u5b50\u57ad"
    ],
    "wof:name":"Meiziya",
    "wof:placetype":"locality"
},
  "geometry": {"coordinates":[111.34071000000002,30.76087],"type":"Point"}
}