{
  "type": "Feature",
  "properties": {
    "gn:admin1_code":"32.0",
    "gn:asciiname":"Chebatian",
    "gn:country_code":"CN",
    "gn:dem":574,
    "gn:feature_class":"P",
    "gn:feature_code":"PPL",
    "gn:name":"Chebatian",
    "gn:population":0,
    "gn:timezone":"Asia/Shanghai",
    "iso:country":"CN",
    "name:zho_x_preferred":[
        "\u8f66\u575d\u7530"
    ],
    "wof:name":"Chebatian",
    "wof:placetype":"locality"
},
  "geometry": {"coordinates":[105.47878,28.05089000000001],"type":"Point"}
}