{
  "type": "Feature",
  "properties": {
    "gn:admin1_code":"18",
    "gn:asciiname":"Yangjiqing",
    "gn:country_code":"CN",
    "gn:dem":1529,
    "gn:feature_class":"P",
    "gn:feature_code":"PPL",
    "gn:name":"Yangjiqing",
    "gn:population":0,
    "gn:timezone":"Asia/Shanghai",
    "iso:country":"CN",
    "name:zho_x_preferred":[
        "\u7f8a\u9e21\u7b90"
    ],
    "wof:name":"Yangjiqing",
    "wof:placetype":"locality"
},
  "geometry": {"coordinates":[105.015,25.6992],"type":"Point"}
}