{
  "type": "Feature",
  "properties": {
    "gn:admin1_code":"7.0",
    "gn:asciiname":"Lucongqi",
    "gn:country_code":"CN",
    "gn:dem":499,
    "gn:feature_class":"P",
    "gn:feature_code":"PPL",
    "gn:name":"Lucongqi",
    "gn:population":0,
    "gn:timezone":"Asia/Shanghai",
    "iso:country":"CN",
    "name:zho_x_preferred":[
        "\u82a6\u4e1b\u6b67"
    ],
    "wof:name":"Lucongqi",
    "wof:placetype":"locality"
},
  "geometry": {"coordinates":[118.23188,27.30896],"type":"Point"}
}