{
  "type": "Feature",
  "properties": {
    "gn:admin1_code":"25.0",
    "gn:asciiname":"Xisanduhecun",
    "gn:country_code":"CN",
    "gn:dem":46,
    "gn:feature_class":"P",
    "gn:feature_code":"PPL",
    "gn:name":"Xisanduhecun",
    "gn:population":0,
    "gn:timezone":"Asia/Shanghai",
    "iso:country":"CN",
    "name:zho_x_preferred":[
        "\u897f\u4e09\u90fd\u6cb3\u6751"
    ],
    "wof:name":"Xisanduhecun",
    "wof:placetype":"locality"
},
  "geometry": {"coordinates":[120.54633,36.58002000000001],"type":"Point"}
}