{
  "type": "Feature",
  "properties": {
    "gn:admin1_code":"20.0",
    "gn:asciiname":"Limingtun",
    "gn:country_code":"CN",
    "gn:dem":381,
    "gn:feature_class":"P",
    "gn:feature_code":"PPL",
    "gn:name":"Limingtun",
    "gn:population":0,
    "gn:timezone":"Asia/Shanghai",
    "iso:country":"CN",
    "name:zho_x_preferred":[
        "\u9ece\u660e\u5c6f"
    ],
    "wof:name":"Limingtun",
    "wof:placetype":"locality"
},
  "geometry": {"coordinates":[123.04928,48.44455],"type":"Point"}
}