{
  "type": "Feature",
  "properties": {
    "gn:admin1_code":"02",
    "gn:asciiname":"Nanbaijia",
    "gn:country_code":"CN",
    "gn:dem":8,
    "gn:feature_class":"P",
    "gn:feature_code":"PPL",
    "gn:name":"Nanbaijia",
    "gn:population":0,
    "gn:timezone":"Asia/Shanghai",
    "iso:country":"CN",
    "name:und_x_variant":[
        "Egengtou",
        "Nanbaijia"
    ],
    "name:zho_x_preferred":[
        "\u5357\u767d\u5bb6"
    ],
    "wof:name":"Nanbaijia",
    "wof:placetype":"locality"
},
  "geometry": {"coordinates":[120.6801,27.93102],"type":"Point"}
}