{
  "type": "Feature",
  "properties": {
    "gn:admin1_code":"29.0",
    "gn:asciiname":"Zhashiba",
    "gn:country_code":"CN",
    "gn:dem":1700,
    "gn:feature_class":"P",
    "gn:feature_code":"PPL",
    "gn:name":"Zhashiba",
    "gn:population":0,
    "gn:timezone":"Asia/Shanghai",
    "iso:country":"CN",
    "name:zho_x_preferred":[
        "\u624e\u77f3\u575d"
    ],
    "wof:name":"Zhashiba",
    "wof:placetype":"locality"
},
  "geometry": {"coordinates":[100.408,24.1571],"type":"Point"}
}