{
  "type": "Feature",
  "properties": {
    "gn:admin1_code":"33.0",
    "gn:asciiname":"Xiaochitang",
    "gn:country_code":"CN",
    "gn:dem":756,
    "gn:feature_class":"P",
    "gn:feature_code":"PPL",
    "gn:name":"Xiaochitang",
    "gn:population":0,
    "gn:timezone":"Asia/Shanghai",
    "iso:country":"CN",
    "name:zho_x_preferred":[
        "\u5c0f\u6c60\u5858"
    ],
    "wof:name":"Xiaochitang",
    "wof:placetype":"locality"
},
  "geometry": {"coordinates":[108.57846000000001,28.86625],"type":"Point"}
}