{
  "type": "Feature",
  "properties": {
    "gn:admin1_code":"32.0",
    "gn:asciiname":"Shanmenkou",
    "gn:country_code":"CN",
    "gn:dem":330,
    "gn:feature_class":"P",
    "gn:feature_code":"PPL",
    "gn:name":"Shanmenkou",
    "gn:population":0,
    "gn:timezone":"Asia/Shanghai",
    "iso:country":"CN",
    "name:zho_x_preferred":[
        "\u5c71\u95e8\u53e3"
    ],
    "wof:name":"Shanmenkou",
    "wof:placetype":"locality"
},
  "geometry": {"coordinates":[106.81793999999999,30.43672],"type":"Point"}
}