{
  "type": "Feature",
  "properties": {
    "gn:admin1_code":"18.0",
    "gn:asciiname":"Baijishan",
    "gn:country_code":"CN",
    "gn:dem":975,
    "gn:feature_class":"P",
    "gn:feature_code":"PPL",
    "gn:name":"Baijishan",
    "gn:population":0,
    "gn:timezone":"Asia/Shanghai",
    "iso:country":"CN",
    "name:zho_x_preferred":[
        "\u767d\u57fa\u5c71"
    ],
    "wof:name":"Baijishan",
    "wof:placetype":"locality"
},
  "geometry": {"coordinates":[108.245,26.5713],"type":"Point"}
}