{
  "type": "Feature",
  "properties": {
    "gn:admin1_code":"6.0",
    "gn:asciiname":"Ladege",
    "gn:country_code":"CN",
    "gn:dem":3155,
    "gn:feature_class":"P",
    "gn:feature_code":"PPL",
    "gn:name":"Ladege",
    "gn:population":0,
    "gn:timezone":"Asia/Shanghai",
    "iso:country":"CN",
    "name:zho_x_preferred":[
        "\u62c9\u5fb7\u683c"
    ],
    "wof:name":"Ladege",
    "wof:placetype":"locality"
},
  "geometry": {"coordinates":[101.63493,35.88835],"type":"Point"}
}