{
  "type": "Feature",
  "properties": {
    "gn:admin1_code":"18",
    "gn:asciiname":"Xiaoshan",
    "gn:country_code":"CN",
    "gn:dem":1100,
    "gn:feature_class":"P",
    "gn:feature_code":"PPL",
    "gn:name":"Xiaoshan",
    "gn:population":0,
    "gn:timezone":"Asia/Shanghai",
    "iso:country":"CN",
    "name:zho_x_preferred":[
        "\u5c0f\u5c71"
    ],
    "wof:name":"Xiaoshan",
    "wof:placetype":"locality"
},
  "geometry": {"coordinates":[106.86199999999999,26.6179],"type":"Point"}
}