{
  "type": "Feature",
  "properties": {
    "gn:admin1_code":"4.0",
    "gn:asciiname":"Nanxia",
    "gn:country_code":"CN",
    "gn:dem":5,
    "gn:feature_class":"P",
    "gn:feature_code":"PPL",
    "gn:name":"Nanxia",
    "gn:population":0,
    "gn:timezone":"Asia/Shanghai",
    "iso:country":"CN",
    "name:und_x_variant":[
        "\u5357\u590f"
    ],
    "name:zho_x_preferred":[
        "\u5357\u590f"
    ],
    "wof:name":"Nanxia",
    "wof:placetype":"locality"
},
  "geometry": {"coordinates":[120.42404000000001,32.1425],"type":"Point"}
}