{
  "type": "Feature",
  "properties": {
    "gn:admin1_code":"32.0",
    "gn:asciiname":"Santan",
    "gn:country_code":"CN",
    "gn:dem":678,
    "gn:feature_class":"P",
    "gn:feature_code":"PPL",
    "gn:name":"Santan",
    "gn:population":0,
    "gn:timezone":"Asia/Shanghai",
    "iso:country":"CN",
    "name:ceb_x_preferred":[
        "Santan"
    ],
    "name:swe_x_preferred":[
        "Santan"
    ],
    "name:tgl_x_preferred":[
        "Santan"
    ],
    "name:zho_x_preferred":[
        "\u4e09\u6ee9"
    ],
    "wof:name":"Santan",
    "wof:placetype":"locality"
},
  "geometry": {"coordinates":[105.896,32.6929],"type":"Point"}
}