{
  "type": "Feature",
  "properties": {
    "gn:admin1_code":"5.0",
    "gn:asciiname":"Xiushancun",
    "gn:country_code":"CN",
    "gn:dem":318,
    "gn:feature_class":"P",
    "gn:feature_code":"PPL",
    "gn:name":"Xiushancun",
    "gn:population":0,
    "gn:timezone":"Asia/Shanghai",
    "iso:country":"CN",
    "name:zho_x_preferred":[
        "\u5cab\u5c71\u6751"
    ],
    "wof:name":"Xiushancun",
    "wof:placetype":"locality"
},
  "geometry": {"coordinates":[126.28592999999999,42.92309],"type":"Point"}
}