{
  "type": "Feature",
  "properties": {
    "gn:admin1_code":"1.0",
    "gn:asciiname":"Laodong Zhaicun",
    "gn:country_code":"CN",
    "gn:dem":37,
    "gn:feature_class":"P",
    "gn:feature_code":"PPL",
    "gn:name":"Laodong Zhaicun",
    "gn:population":0,
    "gn:timezone":"Asia/Shanghai",
    "iso:country":"CN",
    "name:zho_x_preferred":[
        "\u8001\u8463\u5be8\u6751"
    ],
    "wof:name":"Laodong Zhaicun",
    "wof:placetype":"locality"
},
  "geometry": {"coordinates":[115.49109,33.06592],"type":"Point"}
}