{
  "type": "Feature",
  "properties": {
    "gn:admin1_code":"24",
    "gn:asciiname":"Guojiazhuang",
    "gn:country_code":"CN",
    "gn:dem":1083,
    "gn:feature_class":"P",
    "gn:feature_code":"PPL",
    "gn:name":"Guojiazhuang",
    "gn:population":0,
    "gn:timezone":"Asia/Shanghai",
    "iso:country":"CN",
    "name:und_x_variant":[
        "Kuo-chia-chuang",
        "Guojiazhuang",
        "\u90ed\u5bb6\u5e84"
    ],
    "wof:name":"Guojiazhuang",
    "wof:placetype":"locality"
},
  "geometry": {"coordinates":[113.62963999999999,39.65277],"type":"Point"}
}