{
  "type": "Feature",
  "properties": {
    "gn:admin1_code":"19",
    "gn:asciiname":"Dongguo",
    "gn:country_code":"CN",
    "gn:dem":5,
    "gn:feature_class":"P",
    "gn:feature_code":"PPL",
    "gn:name":"Dongguo",
    "gn:population":0,
    "gn:timezone":"Asia/Shanghai",
    "iso:country":"CN",
    "name:und_x_variant":[
        "Dongguocun",
        "Dongguo"
    ],
    "name:zho_x_preferred":[
        "\u4e1c\u90ed\u6751"
    ],
    "name:zho_x_variant":[
        "\u4e1c\u90ed"
    ],
    "wof:name":"Dongguo",
    "wof:placetype":"locality"
},
  "geometry": {"coordinates":[121.67972,41.17472],"type":"Point"}
}