{
  "type": "Feature",
  "properties": {
    "gn:admin1_code":"10.0",
    "gn:asciiname":"Dachexing",
    "gn:country_code":"CN",
    "gn:dem":101,
    "gn:feature_class":"P",
    "gn:feature_code":"PPL",
    "gn:name":"Dachexing",
    "gn:population":0,
    "gn:timezone":"Asia/Shanghai",
    "iso:country":"CN",
    "name:und_x_variant":[
        "\u5927\u8f66\u884c"
    ],
    "wof:name":"Dachexing",
    "wof:placetype":"locality"
},
  "geometry": {"coordinates":[114.35680000000001,38.01867],"type":"Point"}
}