{
  "type": "Feature",
  "properties": {
    "gn:admin1_code":"19.0",
    "gn:asciiname":"Dajiangzhangzi",
    "gn:country_code":"CN",
    "gn:dem":521,
    "gn:feature_class":"P",
    "gn:feature_code":"PPL",
    "gn:name":"Dajiangzhangzi",
    "gn:population":0,
    "gn:timezone":"Asia/Shanghai",
    "iso:country":"CN",
    "name:und_x_variant":[
        "\u5927\u59dc\u6756\u5b50"
    ],
    "name:zho_x_preferred":[
        "\u5927\u59dc\u6756\u5b50"
    ],
    "wof:name":"Dajiangzhangzi",
    "wof:placetype":"locality"
},
  "geometry": {"coordinates":[119.48057,40.61106],"type":"Point"}
}