{
  "type": "Feature",
  "properties": {
    "gn:admin1_code":"5.0",
    "gn:asciiname":"Yuanfeng",
    "gn:country_code":"CN",
    "gn:dem":631,
    "gn:feature_class":"P",
    "gn:feature_code":"PPL",
    "gn:name":"Yuanfeng",
    "gn:population":0,
    "gn:timezone":"Asia/Shanghai",
    "iso:country":"CN",
    "name:fra_x_preferred":[
        "Yuanfeng"
    ],
    "name:und_x_variant":[
        "\u5143\u5cf0",
        "Yuanfengcun",
        "\u5143\u5cf0\u6751"
    ],
    "wof:name":"Yuanfeng",
    "wof:placetype":"locality"
},
  "geometry": {"coordinates":[128.93600000000001,42.09838],"type":"Point"}
}