{
  "type": "Feature",
  "properties": {
    "gn:admin1_code":"4.0",
    "gn:asciiname":"Jiaoyingcun",
    "gn:country_code":"CN",
    "gn:dem":31,
    "gn:feature_class":"P",
    "gn:feature_code":"PPL",
    "gn:name":"Jiaoyingcun",
    "gn:population":0,
    "gn:timezone":"Asia/Shanghai",
    "iso:country":"CN",
    "name:zho_x_preferred":[
        "\u7126\u8425\u6751"
    ],
    "wof:name":"Jiaoyingcun",
    "wof:placetype":"locality"
},
  "geometry": {"coordinates":[117.63129000000001,34.03668],"type":"Point"}
}