{
  "type": "Feature",
  "properties": {
    "gn:admin1_code":"32.0",
    "gn:asciiname":"Laoyandian",
    "gn:country_code":"CN",
    "gn:dem":521,
    "gn:feature_class":"P",
    "gn:feature_code":"PPL",
    "gn:name":"Laoyandian",
    "gn:population":0,
    "gn:timezone":"Asia/Shanghai",
    "iso:country":"CN",
    "name:zho_x_preferred":[
        "\u8001\u76d0\u5e97"
    ],
    "wof:name":"Laoyandian",
    "wof:placetype":"locality"
},
  "geometry": {"coordinates":[108.00705000000001,31.06208],"type":"Point"}
}