{
  "type": "Feature",
  "properties": {
    "gn:admin1_code":"16.0",
    "gn:asciiname":"Suoxu",
    "gn:country_code":"CN",
    "gn:dem":525,
    "gn:feature_class":"P",
    "gn:feature_code":"PPL",
    "gn:name":"Suoxu",
    "gn:population":0,
    "gn:timezone":"Asia/Shanghai",
    "iso:country":"CN",
    "name:zho_x_preferred":[
        "\u6240\u5729"
    ],
    "wof:name":"Suoxu",
    "wof:placetype":"locality"
},
  "geometry": {"coordinates":[107.03,24.1431],"type":"Point"}
}