{
  "type": "Feature",
  "properties": {
    "gn:admin1_code":"02",
    "gn:asciiname":"Yaojiafen",
    "gn:country_code":"CN",
    "gn:dem":4,
    "gn:feature_class":"P",
    "gn:feature_code":"PPL",
    "gn:name":"Yaojiafen",
    "gn:population":0,
    "gn:timezone":"Asia/Shanghai",
    "iso:country":"CN",
    "name:und_x_variant":[
        "\u59da\u5bb6\u575f"
    ],
    "wof:name":"Yaojiafen",
    "wof:placetype":"locality"
},
  "geometry": {"coordinates":[121.20889,30.7446],"type":"Point"}
}