{
  "type": "Feature",
  "properties": {
    "gn:admin1_code":"18.0",
    "gn:asciiname":"Labo",
    "gn:country_code":"CN",
    "gn:dem":824,
    "gn:feature_class":"P",
    "gn:feature_code":"PPL",
    "gn:name":"Labo",
    "gn:population":0,
    "gn:timezone":"Asia/Shanghai",
    "iso:country":"CN",
    "name:ceb_x_preferred":[
        "Labo"
    ],
    "name:deu_x_preferred":[
        "Labo"
    ],
    "name:fra_x_preferred":[
        "Labo"
    ],
    "name:nld_x_preferred":[
        "Labo"
    ],
    "name:swe_x_preferred":[
        "Labo"
    ],
    "name:zho_x_preferred":[
        "\u62c9\u4f2f"
    ],
    "wof:name":"Labo",
    "wof:placetype":"locality"
},
  "geometry": {"coordinates":[107.78400000000001,25.5944],"type":"Point"}
}