{
  "type": "Feature",
  "properties": {
    "gn:admin1_code":"18.0",
    "gn:asciiname":"Tongmen",
    "gn:country_code":"CN",
    "gn:dem":593,
    "gn:feature_class":"P",
    "gn:feature_code":"PPL",
    "gn:name":"Tongmen",
    "gn:population":0,
    "gn:timezone":"Asia/Shanghai",
    "iso:country":"CN",
    "name:zho_x_preferred":[
        "\u540c\u95e8"
    ],
    "wof:name":"Tongmen",
    "wof:placetype":"locality"
},
  "geometry": {"coordinates":[109.34699999999999,26.6543],"type":"Point"}
}