{
  "type": "Feature",
  "properties": {
    "gn:admin1_code":"29.0",
    "gn:asciiname":"Tanieku",
    "gn:country_code":"CN",
    "gn:dem":2107,
    "gn:feature_class":"P",
    "gn:feature_code":"PPL",
    "gn:name":"Tanieku",
    "gn:population":0,
    "gn:timezone":"Asia/Shanghai",
    "iso:country":"CN",
    "name:zho_x_preferred":[
        "\u5854\u4e5c\u82e6"
    ],
    "wof:name":"Tanieku",
    "wof:placetype":"locality"
},
  "geometry": {"coordinates":[100.628,25.2654],"type":"Point"}
}