{
  "type": "Feature",
  "properties": {
    "gn:admin1_code":"18.0",
    "gn:asciiname":"Madao",
    "gn:country_code":"CN",
    "gn:dem":909,
    "gn:feature_class":"P",
    "gn:feature_code":"PPL",
    "gn:name":"Madao",
    "gn:population":0,
    "gn:timezone":"Asia/Shanghai",
    "iso:country":"CN",
    "name:zho_x_preferred":[
        "\u9ebb\u9053"
    ],
    "wof:name":"Madao",
    "wof:placetype":"locality"
},
  "geometry": {"coordinates":[107.492,25.3992],"type":"Point"}
}