{
  "type": "Feature",
  "properties": {
    "gn:admin1_code":"10",
    "gn:asciiname":"Pengzhangzi",
    "gn:country_code":"CN",
    "gn:dem":205,
    "gn:feature_class":"P",
    "gn:feature_code":"PPL",
    "gn:name":"Pengzhangzi",
    "gn:population":0,
    "gn:timezone":"Asia/Shanghai",
    "iso:country":"CN",
    "name:zho_x_preferred":[
        "\u5f6d\u6756\u5b50"
    ],
    "wof:name":"Pengzhangzi",
    "wof:placetype":"locality"
},
  "geometry": {"coordinates":[118.88232000000001,40.2389],"type":"Point"}
}