{
  "type": "Feature",
  "properties": {
    "gn:admin1_code":"26.0",
    "gn:asciiname":"Dongshanzhan",
    "gn:country_code":"CN",
    "gn:dem":1382,
    "gn:feature_class":"P",
    "gn:feature_code":"PPL",
    "gn:name":"Dongshanzhan",
    "gn:population":0,
    "gn:timezone":"Asia/Shanghai",
    "iso:country":"CN",
    "name:zho_x_preferred":[
        "\u4e1c\u5c71\u7ad9"
    ],
    "wof:name":"Dongshanzhan",
    "wof:placetype":"locality"
},
  "geometry": {"coordinates":[108.72443,35.66356],"type":"Point"}
}