{
  "type": "Feature",
  "properties": {
    "gn:admin1_code":"25",
    "gn:asciiname":"Daigu",
    "gn:country_code":"CN",
    "gn:dem":510,
    "gn:feature_class":"P",
    "gn:feature_code":"PPL",
    "gn:name":"Daigu",
    "gn:population":0,
    "gn:timezone":"Asia/Shanghai",
    "iso:country":"CN",
    "name:zho_x_preferred":[
        "\u5cb1\u5d2e"
    ],
    "wof:name":"Daigu",
    "wof:placetype":"locality"
},
  "geometry": {"coordinates":[118.092,35.9681],"type":"Point"}
}