{
  "type": "Feature",
  "properties": {
    "gn:admin1_code":"26.0",
    "gn:asciiname":"Dagedacun",
    "gn:country_code":"CN",
    "gn:dem":1296,
    "gn:feature_class":"P",
    "gn:feature_code":"PPL",
    "gn:name":"Dagedacun",
    "gn:population":0,
    "gn:timezone":"Asia/Shanghai",
    "iso:country":"CN",
    "name:zho_x_preferred":[
        "\u5927\u572a\u57af\u6751"
    ],
    "wof:name":"Dagedacun",
    "wof:placetype":"locality"
},
  "geometry": {"coordinates":[109.97057,38.43813],"type":"Point"}
}