{
  "type": "Feature",
  "properties": {
    "gn:admin1_code":"15.0",
    "gn:asciiname":"Yinposhang",
    "gn:country_code":"CN",
    "gn:dem":1851,
    "gn:feature_class":"P",
    "gn:feature_code":"PPL",
    "gn:name":"Yinposhang",
    "gn:population":0,
    "gn:timezone":"Asia/Shanghai",
    "iso:country":"CN",
    "name:zho_x_preferred":[
        "\u9634\u5761\u4e0a"
    ],
    "wof:name":"Yinposhang",
    "wof:placetype":"locality"
},
  "geometry": {"coordinates":[104.80159,33.73309],"type":"Point"}
}