{
  "type": "Feature",
  "properties": {
    "gn:admin1_code":"12.0",
    "gn:asciiname":"Jiejiawan",
    "gn:country_code":"CN",
    "gn:dem":484,
    "gn:feature_class":"P",
    "gn:feature_code":"PPL",
    "gn:name":"Jiejiawan",
    "gn:population":0,
    "gn:timezone":"Asia/Shanghai",
    "iso:country":"CN",
    "name:zho_x_preferred":[
        "\u89e3\u5bb6\u6e7e"
    ],
    "wof:name":"Jiejiawan",
    "wof:placetype":"locality"
},
  "geometry": {"coordinates":[110.77543,32.09273],"type":"Point"}
}