{
  "type": "Feature",
  "properties": {
    "gn:admin1_code":"11",
    "gn:asciiname":"Luozishan Yaozuxiang",
    "gn:country_code":"CN",
    "gn:dem":402,
    "gn:feature_class":"P",
    "gn:feature_code":"PPL",
    "gn:name":"Luozishan Yaozuxiang",
    "gn:population":0,
    "gn:timezone":"Asia/Shanghai",
    "iso:country":"CN",
    "wof:name":"Luozishan Yaozuxiang",
    "wof:placetype":"locality"
},
  "geometry": {"coordinates":[110.41472,27.67722],"type":"Point"}
}