{
  "type": "Feature",
  "properties": {
    "gn:admin1_code":"19.0",
    "gn:asciiname":"Loujiagou",
    "gn:country_code":"CN",
    "gn:dem":70,
    "gn:feature_class":"P",
    "gn:feature_code":"PPL",
    "gn:name":"Loujiagou",
    "gn:population":0,
    "gn:timezone":"Asia/Shanghai",
    "iso:country":"CN",
    "name:zho_x_preferred":[
        "\u5a04\u5bb6\u6c9f"
    ],
    "wof:name":"Loujiagou",
    "wof:placetype":"locality"
},
  "geometry": {"coordinates":[119.77316,40.15223],"type":"Point"}
}