{
  "type": "Feature",
  "properties": {
    "gn:admin1_code":"14.0",
    "gn:asciiname":"Naga'ena",
    "gn:country_code":"CN",
    "gn:dem":4545,
    "gn:feature_class":"P",
    "gn:feature_code":"PPL",
    "gn:name":"Naga\u2019ena",
    "gn:population":0,
    "gn:timezone":"Asia/Urumqi",
    "iso:country":"CN",
    "name:und_x_variant":[
        "Naga\u2019ena"
    ],
    "name:zho_x_preferred":[
        "\u90a3\u560e\u4fc4\u90a3"
    ],
    "wof:name":"Naga'ena",
    "wof:placetype":"locality"
},
  "geometry": {"coordinates":[84.2287,32.4687],"type":"Point"}
}