{
  "type": "Feature",
  "properties": {
    "gn:admin1_code":"5.0",
    "gn:asciiname":"Daqinggoucun",
    "gn:country_code":"CN",
    "gn:dem":617,
    "gn:feature_class":"P",
    "gn:feature_code":"PPL",
    "gn:name":"Daqinggoucun",
    "gn:population":0,
    "gn:timezone":"Asia/Shanghai",
    "iso:country":"CN",
    "name:und_x_variant":[
        "Daqinggou",
        "Daqinggoucun"
    ],
    "name:zho_x_preferred":[
        "\u5927\u9752\u6c9f"
    ],
    "name:zho_x_variant":[
        "\u5927\u9752\u6c9f\u6751"
    ],
    "wof:name":"Daqinggoucun",
    "wof:placetype":"locality"
},
  "geometry": {"coordinates":[126.45363999999999,41.80491],"type":"Point"}
}