{
  "type": "Feature",
  "properties": {
    "gn:admin1_code":"29",
    "gn:asciiname":"Xiaomaidizhuang",
    "gn:country_code":"CN",
    "gn:dem":1686,
    "gn:feature_class":"P",
    "gn:feature_code":"PPL",
    "gn:name":"Xiaomaidizhuang",
    "gn:population":0,
    "gn:timezone":"Asia/Shanghai",
    "iso:country":"CN",
    "name:zho_x_preferred":[
        "\u5c0f\u9ea6\u5730\u5e84"
    ],
    "wof:name":"Xiaomaidizhuang",
    "wof:placetype":"locality"
},
  "geometry": {"coordinates":[103.26900000000001,24.7867],"type":"Point"}
}