{
  "type": "Feature",
  "properties": {
    "gn:admin1_code":"2.0",
    "gn:asciiname":"Xialinchang",
    "gn:country_code":"CN",
    "gn:dem":323,
    "gn:feature_class":"P",
    "gn:feature_code":"PPL",
    "gn:name":"Xialinchang",
    "gn:population":0,
    "gn:timezone":"Asia/Shanghai",
    "iso:country":"CN",
    "name:zho_x_preferred":[
        "\u4e0b\u6797\u5382"
    ],
    "wof:name":"Xialinchang",
    "wof:placetype":"locality"
},
  "geometry": {"coordinates":[120.62054999999999,27.83686],"type":"Point"}
}