{
  "type": "Feature",
  "properties": {
    "gn:admin1_code":"15",
    "gn:asciiname":"Niangmuziwan",
    "gn:country_code":"CN",
    "gn:dem":1588,
    "gn:feature_class":"P",
    "gn:feature_code":"PPL",
    "gn:name":"Niangmuziwan",
    "gn:population":0,
    "gn:timezone":"Asia/Shanghai",
    "iso:country":"CN",
    "wof:name":"Niangmuziwan",
    "wof:placetype":"locality"
},
  "geometry": {"coordinates":[108.36750000000001,35.99417000000001],"type":"Point"}
}