{
  "type": "Feature",
  "properties": {
    "gn:admin1_code":"18.0",
    "gn:asciiname":"Huanglianxi",
    "gn:country_code":"CN",
    "gn:dem":519,
    "gn:feature_class":"P",
    "gn:feature_code":"PPL",
    "gn:name":"Huanglianxi",
    "gn:population":0,
    "gn:timezone":"Asia/Shanghai",
    "iso:country":"CN",
    "name:zho_x_preferred":[
        "\u9ec4\u8fde\u6eaa"
    ],
    "wof:name":"Huanglianxi",
    "wof:placetype":"locality"
},
  "geometry": {"coordinates":[109.111,27.6148],"type":"Point"}
}