{
  "type": "Feature",
  "properties": {
    "gn:admin1_code":"19.0",
    "gn:asciiname":"Erdui",
    "gn:country_code":"CN",
    "gn:dem":243,
    "gn:feature_class":"P",
    "gn:feature_code":"PPLF",
    "gn:name":"Erdui",
    "gn:population":0,
    "gn:timezone":"Asia/Shanghai",
    "iso:country":"CN",
    "name:zho_x_preferred":[
        "\u4e8c\u961f"
    ],
    "wof:name":"Erdui",
    "wof:placetype":"locality"
},
  "geometry": {"coordinates":[125.35299999999999,41.2416],"type":"Point"}
}