{
  "type": "Feature",
  "properties": {
    "gn:admin1_code":"33.0",
    "gn:asciiname":"Xindifang",
    "gn:country_code":"CN",
    "gn:dem":555,
    "gn:feature_class":"P",
    "gn:feature_code":"PPL",
    "gn:name":"Xindifang",
    "gn:population":0,
    "gn:timezone":"Asia/Shanghai",
    "iso:country":"CN",
    "name:zho_x_preferred":[
        "\u65b0\u5730\u65b9"
    ],
    "wof:name":"Xindifang",
    "wof:placetype":"locality"
},
  "geometry": {"coordinates":[109.08732999999999,28.86786],"type":"Point"}
}