{
  "type": "Feature",
  "properties": {
    "gn:admin1_code":"25",
    "gn:asciiname":"Fangtou",
    "gn:country_code":"CN",
    "gn:dem":162,
    "gn:feature_class":"P",
    "gn:feature_code":"PPL",
    "gn:name":"Fangtou",
    "gn:population":0,
    "gn:timezone":"Asia/Shanghai",
    "iso:country":"CN",
    "name:zho_x_preferred":[
        "\u623f\u5934"
    ],
    "wof:name":"Fangtou",
    "wof:placetype":"locality"
},
  "geometry": {"coordinates":[116.614,36.3191],"type":"Point"}
}