{
  "type": "Feature",
  "properties": {
    "gn:admin1_code":"14.0",
    "gn:asciiname":"Qangma",
    "gn:country_code":"CN",
    "gn:dem":4646,
    "gn:feature_class":"P",
    "gn:feature_code":"PPLF",
    "gn:name":"Qangma",
    "gn:population":0,
    "gn:timezone":"Asia/Urumqi",
    "iso:country":"CN",
    "name:bod_x_preferred":[
        "Qangma"
    ],
    "name:zho_x_preferred":[
        "Jiangma"
    ],
    "name:zho_x_variant":[
        "\u6c5f\u9a6c",
        "Gega",
        "\u683c\u560e"
    ],
    "wof:name":"Qangma",
    "wof:placetype":"locality"
},
  "geometry": {"coordinates":[84.001,31.601],"type":"Point"}
}