{
  "type": "Feature",
  "properties": {
    "gn:admin1_code":"23.0",
    "gn:asciiname":"Heqiao",
    "gn:country_code":"CN",
    "gn:dem":5,
    "gn:feature_class":"P",
    "gn:feature_code":"PPL",
    "gn:name":"Heqiao",
    "gn:population":0,
    "gn:timezone":"Asia/Shanghai",
    "iso:country":"CN",
    "name:zho_x_preferred":[
        "Heqiao"
    ],
    "name:zho_x_variant":[
        "\u8d3a\u6865"
    ],
    "wof:name":"Heqiao",
    "wof:placetype":"locality"
},
  "geometry": {"coordinates":[121.09938,31.16698],"type":"Point"}
}