{
  "type": "Feature",
  "properties": {
    "gn:admin1_code":"32.0",
    "gn:asciiname":"Shaku",
    "gn:country_code":"CN",
    "gn:dem":2769,
    "gn:feature_class":"P",
    "gn:feature_code":"PPL",
    "gn:name":"Shaku",
    "gn:population":0,
    "gn:timezone":"Asia/Shanghai",
    "iso:country":"CN",
    "name:zho_x_preferred":[
        "\u6c99\u82e6"
    ],
    "wof:name":"Shaku",
    "wof:placetype":"locality"
},
  "geometry": {"coordinates":[102.816,28.4792],"type":"Point"}
}