{
  "type": "Feature",
  "properties": {
    "gn:admin1_code":"11.0",
    "gn:asciiname":"Wuchong",
    "gn:country_code":"CN",
    "gn:dem":456,
    "gn:feature_class":"P",
    "gn:feature_code":"PPL",
    "gn:name":"Wuchong",
    "gn:population":0,
    "gn:timezone":"Asia/Shanghai",
    "iso:country":"CN",
    "name:zho_x_preferred":[
        "\u5c4b\u51b2"
    ],
    "wof:name":"Wuchong",
    "wof:placetype":"locality"
},
  "geometry": {"coordinates":[110.91589999999999,28.62093],"type":"Point"}
}