{
  "type": "Feature",
  "properties": {
    "gn:admin1_code":"26",
    "gn:asciiname":"Mazhai",
    "gn:cc2":"CN",
    "gn:country_code":"CN",
    "gn:dem":1191,
    "gn:feature_class":"P",
    "gn:feature_code":"PPL",
    "gn:name":"Mazhai",
    "gn:population":0,
    "gn:timezone":"Asia/Shanghai",
    "iso:country":"CN",
    "name:und_x_variant":[
        "Ma-chia-chai",
        "Ma-chai",
        "Mazhai"
    ],
    "wof:name":"Mazhai",
    "wof:placetype":"locality"
},
  "geometry": {"coordinates":[107.76278000000001,35.24833],"type":"Point"}
}