{
  "type": "Feature",
  "properties": {
    "gn:admin1_code":"02",
    "gn:asciiname":"Bulu",
    "gn:country_code":"CN",
    "gn:dem":74,
    "gn:feature_class":"P",
    "gn:feature_code":"PPLA4",
    "gn:name":"Bulu",
    "gn:population":0,
    "gn:timezone":"Asia/Shanghai",
    "iso:country":"CN",
    "name:ceb_x_preferred":[
        "Bulu"
    ],
    "name:deu_x_preferred":[
        "Bulu"
    ],
    "name:fra_x_preferred":[
        "Bulu"
    ],
    "name:ind_x_preferred":[
        "Bulu"
    ],
    "name:ita_x_preferred":[
        "Bulu"
    ],
    "name:nld_x_preferred":[
        "Bulu"
    ],
    "name:srp_x_preferred":[
        "\u0411\u0443\u043b\u0443"
    ],
    "name:swe_x_preferred":[
        "Bulu"
    ],
    "name:und_x_variant":[
        "Pu-lu",
        "P\u2019u-lo",
        "Bulu Xiang"
    ],
    "name:zho_x_preferred":[
        "\u6b65\u8def"
    ],
    "name:zho_x_variant":[
        "\u6b65\u8def\u4e61"
    ],
    "wof:name":"Bulu",
    "wof:placetype":"locality"
},
  "geometry": {"coordinates":[120.71214000000001,28.80012],"type":"Point"}
}