{
  "type": "Feature",
  "properties": {
    "gn:admin1_code":"30",
    "gn:asciiname":"Pengjingli",
    "gn:country_code":"CN",
    "gn:dem":290,
    "gn:feature_class":"P",
    "gn:feature_code":"PPL",
    "gn:name":"Pengjingli",
    "gn:population":0,
    "gn:timezone":"Asia/Shanghai",
    "iso:country":"CN",
    "name:zho_x_preferred":[
        "\u68da\u7ecf\u91cc"
    ],
    "wof:name":"Pengjingli",
    "wof:placetype":"locality"
},
  "geometry": {"coordinates":[115.60146,23.8189],"type":"Point"}
}