{
  "type": "Feature",
  "properties": {
    "gn:admin1_code":"19.0",
    "gn:asciiname":"Zhangjia Wopu",
    "gn:country_code":"CN",
    "gn:dem":496,
    "gn:feature_class":"P",
    "gn:feature_code":"PPL",
    "gn:name":"Zhangjia Wopu",
    "gn:population":0,
    "gn:timezone":"Asia/Shanghai",
    "iso:country":"CN",
    "name:zho_x_preferred":[
        "\u5f20\u5bb6\u7a9d\u94fa"
    ],
    "wof:name":"Zhangjia Wopu",
    "wof:placetype":"locality"
},
  "geometry": {"coordinates":[119.6058,41.4869],"type":"Point"}
}