{
  "type": "Feature",
  "properties": {
    "gn:admin1_code":"15.0",
    "gn:asciiname":"Beishan",
    "gn:country_code":"CN",
    "gn:dem":2051,
    "gn:feature_class":"P",
    "gn:feature_code":"PPL",
    "gn:name":"Beishan",
    "gn:population":0,
    "gn:timezone":"Asia/Shanghai",
    "iso:country":"CN",
    "name:und_x_variant":[
        "\u5317\u5c71"
    ],
    "wof:name":"Beishan",
    "wof:placetype":"locality"
},
  "geometry": {"coordinates":[104.93915,34.2499],"type":"Point"}
}