{
  "type": "Feature",
  "properties": {
    "gn:admin1_code":"24.0",
    "gn:asciiname":"Helaoling",
    "gn:country_code":"CN",
    "gn:dem":1163,
    "gn:feature_class":"P",
    "gn:feature_code":"PPL",
    "gn:name":"Helaoling",
    "gn:population":0,
    "gn:timezone":"Asia/Shanghai",
    "iso:country":"CN",
    "name:zho_x_preferred":[
        "\u6cb3\u635e\u5cad"
    ],
    "wof:name":"Helaoling",
    "wof:placetype":"locality"
},
  "geometry": {"coordinates":[112.79485,38.28901],"type":"Point"}
}