{
  "type": "Feature",
  "properties": {
    "gn:admin1_code":"19.0",
    "gn:asciiname":"Shijia",
    "gn:country_code":"CN",
    "gn:dem":134,
    "gn:feature_class":"P",
    "gn:feature_code":"PPL",
    "gn:name":"Shijia",
    "gn:population":0,
    "gn:timezone":"Asia/Shanghai",
    "iso:country":"CN",
    "name:zho_x_preferred":[
        "\u4ec0\u5bb6"
    ],
    "wof:name":"Shijia",
    "wof:placetype":"locality"
},
  "geometry": {"coordinates":[124.00839000000001,42.8847],"type":"Point"}
}