{
  "type": "Feature",
  "properties": {
    "gn:admin1_code":"5.0",
    "gn:asciiname":"Hekoucun",
    "gn:country_code":"CN",
    "gn:dem":661,
    "gn:feature_class":"P",
    "gn:feature_code":"PPL",
    "gn:name":"Hekoucun",
    "gn:population":0,
    "gn:timezone":"Asia/Shanghai",
    "iso:country":"CN",
    "name:und_x_variant":[
        "\u6cb3\u53e3\u6751"
    ],
    "wof:name":"Hekoucun",
    "wof:placetype":"locality"
},
  "geometry": {"coordinates":[128.10332,41.39236],"type":"Point"}
}