{
  "type": "Feature",
  "properties": {
    "gn:admin1_code":"29.0",
    "gn:asciiname":"Zhangla",
    "gn:country_code":"CN",
    "gn:dem":1420,
    "gn:feature_class":"P",
    "gn:feature_code":"PPL",
    "gn:name":"Zhangla",
    "gn:population":0,
    "gn:timezone":"Asia/Shanghai",
    "iso:country":"CN",
    "name:zho_x_preferred":[
        "\u5f20\u814a"
    ],
    "wof:name":"Zhangla",
    "wof:placetype":"locality"
},
  "geometry": {"coordinates":[98.8797,25.2805],"type":"Point"}
}