{
  "type": "Feature",
  "properties": {
    "gn:admin1_code":"26.0",
    "gn:asciiname":"Renjia Goucun",
    "gn:country_code":"CN",
    "gn:dem":710,
    "gn:feature_class":"P",
    "gn:feature_code":"PPL",
    "gn:name":"Renjia Goucun",
    "gn:population":0,
    "gn:timezone":"Asia/Shanghai",
    "iso:country":"CN",
    "name:zho_x_preferred":[
        "\u4efb\u5bb6\u6c9f\u6751"
    ],
    "wof:name":"Renjia Goucun",
    "wof:placetype":"locality"
},
  "geometry": {"coordinates":[110.675,37.4896],"type":"Point"}
}