{
  "type": "Feature",
  "properties": {
    "gn:admin1_code":"26.0",
    "gn:asciiname":"Qiaojia Maocun",
    "gn:country_code":"CN",
    "gn:dem":879,
    "gn:feature_class":"P",
    "gn:feature_code":"PPL",
    "gn:name":"Qiaojia Maocun",
    "gn:population":0,
    "gn:timezone":"Asia/Shanghai",
    "iso:country":"CN",
    "name:zho_x_preferred":[
        "\u4e54\u5bb6\u5cc1\u6751"
    ],
    "wof:name":"Qiaojia Maocun",
    "wof:placetype":"locality"
},
  "geometry": {"coordinates":[110.545,37.9189],"type":"Point"}
}