{
  "type": "Feature",
  "properties": {
    "gn:admin1_code":"32.0",
    "gn:asciiname":"Luoyandong",
    "gn:country_code":"CN",
    "gn:dem":1081,
    "gn:feature_class":"P",
    "gn:feature_code":"PPL",
    "gn:name":"Luoyandong",
    "gn:population":0,
    "gn:timezone":"Asia/Shanghai",
    "iso:country":"CN",
    "name:zho_x_preferred":[
        "\u7f57\u5ca9\u6d1e"
    ],
    "wof:name":"Luoyandong",
    "wof:placetype":"locality"
},
  "geometry": {"coordinates":[104.1692,28.84745],"type":"Point"}
}