{
  "type": "Feature",
  "properties": {
    "gn:admin1_code":"25",
    "gn:asciiname":"Beiyu",
    "gn:country_code":"CN",
    "gn:dem":338,
    "gn:feature_class":"P",
    "gn:feature_code":"PPL",
    "gn:name":"Beiyu",
    "gn:population":0,
    "gn:timezone":"Asia/Shanghai",
    "iso:country":"CN",
    "name:zho_x_preferred":[
        "\u5317\u5cea"
    ],
    "wof:name":"Beiyu",
    "wof:placetype":"locality"
},
  "geometry": {"coordinates":[118.76000000000001,36.1873],"type":"Point"}
}