{
  "type": "Feature",
  "properties": {
    "gn:admin1_code":"25",
    "gn:asciiname":"Qianliujiakuang",
    "gn:country_code":"CN",
    "gn:dem":78,
    "gn:feature_class":"P",
    "gn:feature_code":"PPL",
    "gn:name":"Qianliujiakuang",
    "gn:population":0,
    "gn:timezone":"Asia/Shanghai",
    "iso:country":"CN",
    "name:zho_x_preferred":[
        "\u524d\u5218\u5bb6\u593c"
    ],
    "wof:name":"Qianliujiakuang",
    "wof:placetype":"locality"
},
  "geometry": {"coordinates":[121.491,37.1643],"type":"Point"}
}