{
  "type": "Feature",
  "properties": {
    "gn:admin1_code":"3",
    "gn:asciiname":"Yanzhuhu",
    "gn:country_code":"CN",
    "gn:dem":492,
    "gn:feature_class":"P",
    "gn:feature_code":"PPL",
    "gn:name":"Yanzhuhu",
    "gn:population":0,
    "gn:timezone":"Asia/Shanghai",
    "iso:country":"CN",
    "name:zho_x_preferred":[
        "\u70df\u7af9\u6e56"
    ],
    "wof:name":"Yanzhuhu",
    "wof:placetype":"locality"
},
  "geometry": {"coordinates":[114.30800000000001,26.6482],"type":"Point"}
}