{
  "type": "Feature",
  "properties": {
    "gn:admin1_code":"29.0",
    "gn:asciiname":"Xiaoqing",
    "gn:country_code":"CN",
    "gn:dem":2084,
    "gn:feature_class":"P",
    "gn:feature_code":"PPL",
    "gn:name":"Xiaoqing",
    "gn:population":0,
    "gn:timezone":"Asia/Shanghai",
    "iso:country":"CN",
    "name:zho_x_preferred":[
        "\u5c0f\u7b90"
    ],
    "wof:name":"Xiaoqing",
    "wof:placetype":"locality"
},
  "geometry": {"coordinates":[103.58499999999999,25.9565],"type":"Point"}
}