{
  "type": "Feature",
  "properties": {
    "gn:admin1_code":"2",
    "gn:asciiname":"Guozhai",
    "gn:country_code":"CN",
    "gn:dem":141,
    "gn:feature_class":"P",
    "gn:feature_code":"PPLA4",
    "gn:name":"Guozhai",
    "gn:population":0,
    "gn:timezone":"Asia/Shanghai",
    "iso:country":"CN",
    "name:und_x_variant":[
        "Guozhai Zhen",
        "Guozhai"
    ],
    "name:zho_x_preferred":[
        "\u90ed\u5b85"
    ],
    "name:zho_x_variant":[
        "\u90ed\u5b85\u9547"
    ],
    "wof:name":"Guozhai",
    "wof:placetype":"locality"
},
  "geometry": {"coordinates":[120.39549,29.22099],"type":"Point"}
}