{
  "type": "Feature",
  "properties": {
    "gn:admin1_code":"26.0",
    "gn:asciiname":"Hualiwan",
    "gn:country_code":"CN",
    "gn:dem":2095,
    "gn:feature_class":"P",
    "gn:feature_code":"PPL",
    "gn:name":"Hualiwan",
    "gn:population":0,
    "gn:timezone":"Asia/Shanghai",
    "iso:country":"CN",
    "name:zho_x_preferred":[
        "\u82b1\u91cc\u6e7e"
    ],
    "wof:name":"Hualiwan",
    "wof:placetype":"locality"
},
  "geometry": {"coordinates":[108.59792,33.87491],"type":"Point"}
}