{
  "type": "Feature",
  "properties": {
    "gn:admin1_code":"24.0",
    "gn:asciiname":"Beiguozhuang",
    "gn:country_code":"CN",
    "gn:dem":1005,
    "gn:feature_class":"P",
    "gn:feature_code":"PPL",
    "gn:name":"Beiguozhuang",
    "gn:population":0,
    "gn:timezone":"Asia/Shanghai",
    "iso:country":"CN",
    "name:und_x_variant":[
        "\u5317\u90ed\u5e84"
    ],
    "wof:name":"Beiguozhuang",
    "wof:placetype":"locality"
},
  "geometry": {"coordinates":[112.96532999999999,39.55731],"type":"Point"}
}