{
  "type": "Feature",
  "properties": {
    "gn:admin1_code":"8.0",
    "gn:asciiname":"Xintunzicun",
    "gn:country_code":"CN",
    "gn:dem":453,
    "gn:feature_class":"P",
    "gn:feature_code":"PPL",
    "gn:name":"Xintunzicun",
    "gn:population":0,
    "gn:timezone":"Asia/Shanghai",
    "iso:country":"CN",
    "name:zho_x_preferred":[
        "\u65b0\u5c6f\u5b50\u6751"
    ],
    "wof:name":"Xintunzicun",
    "wof:placetype":"locality"
},
  "geometry": {"coordinates":[131.09146999999999,44.26859],"type":"Point"}
}