{
  "type": "Feature",
  "properties": {
    "gn:admin1_code":"21.0",
    "gn:asciiname":"Huangping",
    "gn:country_code":"CN",
    "gn:dem":1836,
    "gn:feature_class":"P",
    "gn:feature_code":"PPL",
    "gn:name":"Huangping",
    "gn:population":0,
    "gn:timezone":"Asia/Shanghai",
    "iso:country":"CN",
    "name:zho_x_preferred":[
        "\u9ec4\u576a"
    ],
    "wof:name":"Huangping",
    "wof:placetype":"locality"
},
  "geometry": {"coordinates":[105.791,36.4833],"type":"Point"}
}