{
  "type": "Feature",
  "properties": {
    "gn:admin1_code":"20.0",
    "gn:asciiname":"Tongshengba",
    "gn:country_code":"CN",
    "gn:dem":1537,
    "gn:feature_class":"P",
    "gn:feature_code":"PPL",
    "gn:name":"Tongshengba",
    "gn:population":0,
    "gn:timezone":"Asia/Shanghai",
    "iso:country":"CN",
    "name:und_x_variant":[
        "\u540c\u751f\u575d"
    ],
    "wof:name":"Tongshengba",
    "wof:placetype":"locality"
},
  "geometry": {"coordinates":[113.60514999999999,41.2412],"type":"Point"}
}