{
  "type": "Feature",
  "properties": {
    "gn:admin1_code":"18",
    "gn:asciiname":"Shuikanshang",
    "gn:country_code":"CN",
    "gn:dem":457,
    "gn:feature_class":"P",
    "gn:feature_code":"PPL",
    "gn:name":"Shuikanshang",
    "gn:population":0,
    "gn:timezone":"Asia/Shanghai",
    "iso:country":"CN",
    "name:zho_x_preferred":[
        "\u6c34\u574e\u4e0a"
    ],
    "wof:name":"Shuikanshang",
    "wof:placetype":"locality"
},
  "geometry": {"coordinates":[106.371,28.1752],"type":"Point"}
}