{
  "type": "Feature",
  "properties": {
    "gn:admin1_code":"29.0",
    "gn:asciiname":"Mahuangpo",
    "gn:country_code":"CN",
    "gn:dem":189,
    "gn:feature_class":"P",
    "gn:feature_code":"PPL",
    "gn:name":"Mahuangpo",
    "gn:population":0,
    "gn:timezone":"Asia/Shanghai",
    "iso:country":"CN",
    "name:zho_x_preferred":[
        "\u8682\u8757\u5761"
    ],
    "wof:name":"Mahuangpo",
    "wof:placetype":"locality"
},
  "geometry": {"coordinates":[103.96599999999999,22.5739],"type":"Point"}
}