{
  "type": "Feature",
  "properties": {
    "gn:admin1_code":"4.0",
    "gn:asciiname":"Qianying",
    "gn:country_code":"CN",
    "gn:dem":-3,
    "gn:feature_class":"P",
    "gn:feature_code":"PPL",
    "gn:name":"Qianying",
    "gn:population":0,
    "gn:timezone":"Asia/Shanghai",
    "iso:country":"CN",
    "name:zho_x_preferred":[
        "Qianying"
    ],
    "name:zho_x_variant":[
        "\u524d\u90e2"
    ],
    "wof:name":"Qianying",
    "wof:placetype":"locality"
},
  "geometry": {"coordinates":[120.20860999999999,34.088],"type":"Point"}
}