{
  "type": "Feature",
  "properties": {
    "gn:admin1_code":"11.0",
    "gn:asciiname":"Shangshanchong",
    "gn:country_code":"CN",
    "gn:dem":127,
    "gn:feature_class":"P",
    "gn:feature_code":"PPL",
    "gn:name":"Shangshanchong",
    "gn:population":0,
    "gn:timezone":"Asia/Shanghai",
    "iso:country":"CN",
    "name:zho_x_preferred":[
        "\u4e0a\u5c71\u51b2"
    ],
    "wof:name":"Shangshanchong",
    "wof:placetype":"locality"
},
  "geometry": {"coordinates":[113.38871,27.30365],"type":"Point"}
}