{
  "type": "Feature",
  "properties": {
    "gn:admin1_code":"25",
    "gn:asciiname":"Maoyizhuang",
    "gn:country_code":"CN",
    "gn:dem":159,
    "gn:feature_class":"P",
    "gn:feature_code":"PPL",
    "gn:name":"Maoyizhuang",
    "gn:population":0,
    "gn:timezone":"Asia/Shanghai",
    "iso:country":"CN",
    "name:zho_x_preferred":[
        "\u8302\u4e49\u5e84"
    ],
    "wof:name":"Maoyizhuang",
    "wof:placetype":"locality"
},
  "geometry": {"coordinates":[117.005,35.8512],"type":"Point"}
}