{
  "type": "Feature",
  "properties": {
    "gn:admin1_code":"26.0",
    "gn:asciiname":"Houhezegou",
    "gn:country_code":"CN",
    "gn:dem":1509,
    "gn:feature_class":"P",
    "gn:feature_code":"PPL",
    "gn:name":"Houhezegou",
    "gn:population":0,
    "gn:timezone":"Asia/Shanghai",
    "iso:country":"CN",
    "name:zho_x_preferred":[
        "\u540e\u6cb3\u5219\u6c9f"
    ],
    "wof:name":"Houhezegou",
    "wof:placetype":"locality"
},
  "geometry": {"coordinates":[108.34387,37.28096],"type":"Point"}
}