{
  "type": "Feature",
  "properties": {
    "gn:admin1_code":"24.0",
    "gn:asciiname":"Tadigou",
    "gn:country_code":"CN",
    "gn:dem":1590,
    "gn:feature_class":"P",
    "gn:feature_code":"PPL",
    "gn:name":"Tadigou",
    "gn:population":0,
    "gn:timezone":"Asia/Shanghai",
    "iso:country":"CN",
    "name:zho_x_preferred":[
        "\u5854\u5730\u6c9f"
    ],
    "wof:name":"Tadigou",
    "wof:placetype":"locality"
},
  "geometry": {"coordinates":[111.79933,37.88528],"type":"Point"}
}