{
  "type": "Feature",
  "properties": {
    "gn:admin1_code":"11.0",
    "gn:asciiname":"Kuishan",
    "gn:country_code":"CN",
    "gn:dem":427,
    "gn:feature_class":"P",
    "gn:feature_code":"PPL",
    "gn:name":"Kuishan",
    "gn:population":0,
    "gn:timezone":"Asia/Shanghai",
    "iso:country":"CN",
    "name:zho_x_preferred":[
        "\u9b41\u5c71"
    ],
    "wof:name":"Kuishan",
    "wof:placetype":"locality"
},
  "geometry": {"coordinates":[110.22872,26.37907],"type":"Point"}
}