{
  "type": "Feature",
  "properties": {
    "gn:admin1_code":"32.0",
    "gn:asciiname":"Kanduo",
    "gn:country_code":"CN",
    "gn:dem":3876,
    "gn:feature_class":"P",
    "gn:feature_code":"PPL",
    "gn:name":"Kanduo",
    "gn:population":0,
    "gn:timezone":"Asia/Shanghai",
    "iso:country":"CN",
    "name:zho_x_preferred":[
        "\u574e\u591a"
    ],
    "wof:name":"Kanduo",
    "wof:placetype":"locality"
},
  "geometry": {"coordinates":[99.60441,31.30274],"type":"Point"}
}