{
  "type": "Feature",
  "properties": {
    "gn:admin1_code":"32",
    "gn:asciiname":"Youjun",
    "gn:country_code":"CN",
    "gn:dem":1494,
    "gn:feature_class":"P",
    "gn:feature_code":"PPL",
    "gn:name":"Youjun",
    "gn:population":0,
    "gn:timezone":"Asia/Shanghai",
    "iso:country":"CN",
    "name:und_x_variant":[
        "Yen-chung",
        "Ho-hsi",
        "Hosi",
        "Hexi",
        "Youjun"
    ],
    "name:zho_x_preferred":[
        "\u4f51\u541b"
    ],
    "wof:name":"Youjun",
    "wof:placetype":"locality"
},
  "geometry": {"coordinates":[102.15819999999999,27.73638],"type":"Point"}
}