{
  "type": "Feature",
  "properties": {
    "gn:admin1_code":"15.0",
    "gn:asciiname":"Fuchang",
    "gn:country_code":"CN",
    "gn:dem":1799,
    "gn:feature_class":"P",
    "gn:feature_code":"PPL",
    "gn:name":"Fuchang",
    "gn:population":0,
    "gn:timezone":"Asia/Shanghai",
    "iso:country":"CN",
    "name:und_x_variant":[
        "\u798f\u573a"
    ],
    "name:zho_x_preferred":[
        "\u798f\u573a"
    ],
    "wof:name":"Fuchang",
    "wof:placetype":"locality"
},
  "geometry": {"coordinates":[104.58813000000001,33.14917],"type":"Point"}
}