{
  "type": "Feature",
  "properties": {
    "gn:admin1_code":"11",
    "gn:asciiname":"Shanmu",
    "gn:country_code":"CN",
    "gn:dem":469,
    "gn:feature_class":"P",
    "gn:feature_code":"PPLA4",
    "gn:name":"Shanmu",
    "gn:population":0,
    "gn:timezone":"Asia/Shanghai",
    "iso:country":"CN",
    "name:und_x_variant":[
        "Shanmu Xiang",
        "Shanmu"
    ],
    "name:zho_x_preferred":[
        "\u6749\u6728"
    ],
    "name:zho_x_variant":[
        "\u6749\u6728\u4e61"
    ],
    "wof:name":"Shanmu",
    "wof:placetype":"locality"
},
  "geometry": {"coordinates":[109.84605999999999,29.26674],"type":"Point"}
}