{
  "type": "Feature",
  "properties": {
    "gn:admin1_code":"33.0",
    "gn:asciiname":"Yishi",
    "gn:country_code":"CN",
    "gn:dem":200,
    "gn:feature_class":"P",
    "gn:feature_code":"PPL",
    "gn:name":"Yishi",
    "gn:population":0,
    "gn:timezone":"Asia/Shanghai",
    "iso:country":"CN",
    "name:zho_x_preferred":[
        "\u4ebf\u4e16"
    ],
    "wof:name":"Yishi",
    "wof:placetype":"locality"
},
  "geometry": {"coordinates":[108.16579,31.05512],"type":"Point"}
}