{
  "type": "Feature",
  "properties": {
    "gn:admin1_code":"29.0",
    "gn:asciiname":"Yangguangji",
    "gn:country_code":"CN",
    "gn:dem":2151,
    "gn:feature_class":"P",
    "gn:feature_code":"PPL",
    "gn:name":"Yangguangji",
    "gn:population":0,
    "gn:timezone":"Asia/Shanghai",
    "iso:country":"CN",
    "name:zho_x_preferred":[
        "\u9633\u5149\u96c6"
    ],
    "wof:name":"Yangguangji",
    "wof:placetype":"locality"
},
  "geometry": {"coordinates":[103.09699999999999,25.9492],"type":"Point"}
}