{
  "type": "Feature",
  "properties": {
    "gn:admin1_code":"1.0",
    "gn:asciiname":"Yangrenchong",
    "gn:country_code":"CN",
    "gn:dem":29,
    "gn:feature_class":"P",
    "gn:feature_code":"PPL",
    "gn:name":"Yangrenchong",
    "gn:population":0,
    "gn:timezone":"Asia/Shanghai",
    "iso:country":"CN",
    "name:zho_x_preferred":[
        "Yangrenchong"
    ],
    "name:zho_x_variant":[
        "\u6768\u4ec1\u51b2"
    ],
    "wof:name":"Yangrenchong",
    "wof:placetype":"locality"
},
  "geometry": {"coordinates":[119.17673000000001,31.07892],"type":"Point"}
}