{
  "type": "Feature",
  "properties": {
    "gn:admin1_code":"8.0",
    "gn:asciiname":"Dahutun",
    "gn:country_code":"CN",
    "gn:dem":223,
    "gn:feature_class":"P",
    "gn:feature_code":"PPL",
    "gn:name":"Dahutun",
    "gn:population":0,
    "gn:timezone":"Asia/Shanghai",
    "iso:country":"CN",
    "name:zho_x_preferred":[
        "\u5927\u6237\u5c6f"
    ],
    "wof:name":"Dahutun",
    "wof:placetype":"locality"
},
  "geometry": {"coordinates":[127.68258,46.65632],"type":"Point"}
}