{
  "type": "Feature",
  "properties": {
    "gn:admin1_code":"2.0",
    "gn:asciiname":"Yangjiatang",
    "gn:country_code":"CN",
    "gn:dem":463,
    "gn:feature_class":"P",
    "gn:feature_code":"PPL",
    "gn:name":"Yangjiatang",
    "gn:population":0,
    "gn:timezone":"Asia/Shanghai",
    "iso:country":"CN",
    "name:und_x_variant":[
        "\u9633\u5bb6\u5858"
    ],
    "name:zho_x_preferred":[
        "Yangjiatang"
    ],
    "wof:name":"Yangjiatang",
    "wof:placetype":"locality"
},
  "geometry": {"coordinates":[118.90264999999999,30.05194],"type":"Point"}
}