{
  "type": "Feature",
  "properties": {
    "gn:admin1_code":"20.0",
    "gn:asciiname":"Kabuchu",
    "gn:country_code":"CN",
    "gn:dem":259,
    "gn:feature_class":"P",
    "gn:feature_code":"PPL",
    "gn:name":"Kabuchu",
    "gn:population":0,
    "gn:timezone":"Asia/Shanghai",
    "iso:country":"CN",
    "name:zho_x_preferred":[
        "\u5361\u5e03\u695a"
    ],
    "wof:name":"Kabuchu",
    "wof:placetype":"locality"
},
  "geometry": {"coordinates":[124.51219,49.12792],"type":"Point"}
}