{
  "type": "Feature",
  "properties": {
    "gn:admin1_code":"32.0",
    "gn:asciiname":"Fangjiasi",
    "gn:country_code":"CN",
    "gn:dem":437,
    "gn:feature_class":"P",
    "gn:feature_code":"PPL",
    "gn:name":"Fangjiasi",
    "gn:population":0,
    "gn:timezone":"Asia/Shanghai",
    "iso:country":"CN",
    "name:zho_x_preferred":[
        "\u65b9\u5bb6\u5bfa"
    ],
    "wof:name":"Fangjiasi",
    "wof:placetype":"locality"
},
  "geometry": {"coordinates":[104.449,30.5117],"type":"Point"}
}