{
  "type": "Feature",
  "properties": {
    "gn:admin1_code":"12.0",
    "gn:asciiname":"Wujiataizi",
    "gn:country_code":"CN",
    "gn:dem":580,
    "gn:feature_class":"P",
    "gn:feature_code":"PPL",
    "gn:name":"Wujiataizi",
    "gn:population":0,
    "gn:timezone":"Asia/Shanghai",
    "iso:country":"CN",
    "name:zho_x_preferred":[
        "\u90ac\u5bb6\u53f0\u5b50"
    ],
    "wof:name":"Wujiataizi",
    "wof:placetype":"locality"
},
  "geometry": {"coordinates":[110.12588,31.99095],"type":"Point"}
}