{
  "type": "Feature",
  "properties": {
    "gn:admin1_code":"14.0",
    "gn:asciiname":"Paga",
    "gn:country_code":"CN",
    "gn:dem":4342,
    "gn:feature_class":"P",
    "gn:feature_code":"PPL",
    "gn:name":"Paga",
    "gn:population":0,
    "gn:timezone":"Asia/Urumqi",
    "iso:country":"CN",
    "name:ceb_x_preferred":[
        "Paga"
    ],
    "name:pol_x_preferred":[
        "Paga"
    ],
    "name:swe_x_preferred":[
        "Paga"
    ],
    "name:zho_x_preferred":[
        "\u5e15\u560e"
    ],
    "wof:name":"Paga",
    "wof:placetype":"locality"
},
  "geometry": {"coordinates":[87.4744,29.2178],"type":"Point"}
}