{
  "type": "Feature",
  "properties": {
    "gn:admin1_code":"29.0",
    "gn:asciiname":"Anjiaoxia",
    "gn:country_code":"CN",
    "gn:dem":1844,
    "gn:feature_class":"P",
    "gn:feature_code":"PPL",
    "gn:name":"Anjiaoxia",
    "gn:population":0,
    "gn:timezone":"Asia/Shanghai",
    "iso:country":"CN",
    "name:zho_x_preferred":[
        "\u5eb5\u811a\u4e0b"
    ],
    "wof:name":"Anjiaoxia",
    "wof:placetype":"locality"
},
  "geometry": {"coordinates":[103.449,25.1043],"type":"Point"}
}