{
  "type": "Feature",
  "properties": {
    "gn:admin1_code":"11.0",
    "gn:asciiname":"Bajiaoxi",
    "gn:country_code":"CN",
    "gn:dem":387,
    "gn:feature_class":"P",
    "gn:feature_code":"PPL",
    "gn:name":"Bajiaoxi",
    "gn:population":0,
    "gn:timezone":"Asia/Shanghai",
    "iso:country":"CN",
    "name:zho_x_preferred":[
        "\u82ad\u8549\u6eaa"
    ],
    "wof:name":"Bajiaoxi",
    "wof:placetype":"locality"
},
  "geometry": {"coordinates":[110.35196999999999,28.16745],"type":"Point"}
}