{
  "type": "Feature",
  "properties": {
    "gn:admin1_code":"24",
    "gn:asciiname":"Nanbai",
    "gn:country_code":"CN",
    "gn:dem":752,
    "gn:feature_class":"P",
    "gn:feature_code":"PPL",
    "gn:name":"Nanbai",
    "gn:population":0,
    "gn:timezone":"Asia/Shanghai",
    "iso:country":"CN",
    "name:ara_x_preferred":[
        "\u0646\u0627\u0646\u0628\u0627\u064a"
    ],
    "wof:name":"Nanbai",
    "wof:placetype":"locality"
},
  "geometry": {"coordinates":[112.27694,37.44917],"type":"Point"}
}