{
  "type": "Feature",
  "properties": {
    "gn:admin1_code":"26.0",
    "gn:asciiname":"Wuhoucun",
    "gn:country_code":"CN",
    "gn:dem":481,
    "gn:feature_class":"P",
    "gn:feature_code":"PPL",
    "gn:name":"Wuhoucun",
    "gn:population":0,
    "gn:timezone":"Asia/Shanghai",
    "iso:country":"CN",
    "name:und_x_variant":[
        "\u6b66\u4faf\u6751"
    ],
    "wof:name":"Wuhoucun",
    "wof:placetype":"locality"
},
  "geometry": {"coordinates":[107.34071000000002,33.17498],"type":"Point"}
}