{
  "type": "Feature",
  "properties": {
    "gn:admin1_code":"5.0",
    "gn:asciiname":"Shanghuapi",
    "gn:country_code":"CN",
    "gn:dem":478,
    "gn:feature_class":"P",
    "gn:feature_code":"PPL",
    "gn:name":"Shanghuapi",
    "gn:population":0,
    "gn:timezone":"Asia/Shanghai",
    "iso:country":"CN",
    "name:zho_x_preferred":[
        "\u4e0a\u6866\u76ae"
    ],
    "wof:name":"Shanghuapi",
    "wof:placetype":"locality"
},
  "geometry": {"coordinates":[125.49784,42.11979],"type":"Point"}
}