{
  "type": "Feature",
  "properties": {
    "gn:admin1_code":"07",
    "gn:asciiname":"Kaoyucheng",
    "gn:country_code":"CN",
    "gn:dem":801,
    "gn:feature_class":"P",
    "gn:feature_code":"PPL",
    "gn:name":"Kaoyucheng",
    "gn:population":0,
    "gn:timezone":"Asia/Shanghai",
    "iso:country":"CN",
    "name:zho_x_preferred":[
        "\u9760\u76c2\u57d5"
    ],
    "wof:name":"Kaoyucheng",
    "wof:placetype":"locality"
},
  "geometry": {"coordinates":[117.64949,25.37191],"type":"Point"}
}