{
  "type": "Feature",
  "properties": {
    "gn:admin1_code":"30.0",
    "gn:asciiname":"Chencunwei",
    "gn:country_code":"CN",
    "gn:dem":146,
    "gn:feature_class":"P",
    "gn:feature_code":"PPL",
    "gn:name":"Chencunwei",
    "gn:population":0,
    "gn:timezone":"Asia/Shanghai",
    "iso:country":"CN",
    "name:zho_x_preferred":[
        "\u9648\u6751\u56f4"
    ],
    "wof:name":"Chencunwei",
    "wof:placetype":"locality"
},
  "geometry": {"coordinates":[114.96953000000001,23.753],"type":"Point"}
}