{
  "type": "Feature",
  "properties": {
    "gn:admin1_code":"4.0",
    "gn:asciiname":"Maocaigang",
    "gn:country_code":"CN",
    "gn:dem":4,
    "gn:feature_class":"P",
    "gn:feature_code":"PPL",
    "gn:name":"Maocaigang",
    "gn:population":0,
    "gn:timezone":"Asia/Shanghai",
    "iso:country":"CN",
    "name:zho_x_preferred":[
        "\u8302\u624d\u6e2f"
    ],
    "wof:name":"Maocaigang",
    "wof:placetype":"locality"
},
  "geometry": {"coordinates":[120.59968000000001,31.04212],"type":"Point"}
}