{
  "type": "Feature",
  "properties": {
    "gn:admin1_code":"3.0",
    "gn:asciiname":"Shiluokeng",
    "gn:country_code":"CN",
    "gn:dem":279,
    "gn:feature_class":"P",
    "gn:feature_code":"PPL",
    "gn:name":"Shiluokeng",
    "gn:population":0,
    "gn:timezone":"Asia/Shanghai",
    "iso:country":"CN",
    "name:und_x_variant":[
        "\u77f3\u7f57\u5751"
    ],
    "wof:name":"Shiluokeng",
    "wof:placetype":"locality"
},
  "geometry": {"coordinates":[115.36673,26.70932],"type":"Point"}
}