{
  "type": "Feature",
  "properties": {
    "gn:admin1_code":"12.0",
    "gn:asciiname":"Gengjiaba",
    "gn:country_code":"CN",
    "gn:dem":743,
    "gn:feature_class":"P",
    "gn:feature_code":"PPL",
    "gn:name":"Gengjiaba",
    "gn:population":0,
    "gn:timezone":"Asia/Shanghai",
    "iso:country":"CN",
    "name:zho_x_preferred":[
        "\u803f\u5bb6\u575d"
    ],
    "wof:name":"Gengjiaba",
    "wof:placetype":"locality"
},
  "geometry": {"coordinates":[109.63952999999999,30.50566],"type":"Point"}
}