{
  "type": "Feature",
  "properties": {
    "gn:admin1_code":"32.0",
    "gn:asciiname":"Shuanglongjie",
    "gn:country_code":"CN",
    "gn:dem":484,
    "gn:feature_class":"P",
    "gn:feature_code":"PPL",
    "gn:name":"Shuanglongjie",
    "gn:population":0,
    "gn:timezone":"Asia/Shanghai",
    "iso:country":"CN",
    "name:zho_x_preferred":[
        "\u53cc\u9f99\u8857"
    ],
    "wof:name":"Shuanglongjie",
    "wof:placetype":"locality"
},
  "geometry": {"coordinates":[105.65679,29.87094],"type":"Point"}
}