{
  "type": "Feature",
  "properties": {
    "gn:admin1_code":"1.0",
    "gn:asciiname":"Yanghuachongcun",
    "gn:country_code":"CN",
    "gn:dem":224,
    "gn:feature_class":"P",
    "gn:feature_code":"PPL",
    "gn:name":"Yanghuachongcun",
    "gn:population":0,
    "gn:timezone":"Asia/Shanghai",
    "iso:country":"CN",
    "name:zho_x_preferred":[
        "\u6768\u82b1\u51b2\u6751"
    ],
    "wof:name":"Yanghuachongcun",
    "wof:placetype":"locality"
},
  "geometry": {"coordinates":[116.50485,31.30635],"type":"Point"}
}