{
  "type": "Feature",
  "properties": {
    "gn:admin1_code":"32.0",
    "gn:asciiname":"Qingfu",
    "gn:country_code":"CN",
    "gn:dem":858,
    "gn:feature_class":"P",
    "gn:feature_code":"PPL",
    "gn:name":"Qingfu",
    "gn:population":0,
    "gn:timezone":"Asia/Shanghai",
    "iso:country":"CN",
    "name:zho_x_preferred":[
        "\u9752\u5bcc"
    ],
    "wof:name":"Qingfu",
    "wof:placetype":"locality"
},
  "geometry": {"coordinates":[102.62418,29.35112],"type":"Point"}
}