{
  "type": "Feature",
  "properties": {
    "gn:admin1_code":"3.0",
    "gn:asciiname":"Danchong",
    "gn:country_code":"CN",
    "gn:dem":450,
    "gn:feature_class":"P",
    "gn:feature_code":"PPL",
    "gn:name":"Danchong",
    "gn:population":0,
    "gn:timezone":"Asia/Shanghai",
    "iso:country":"CN",
    "name:und_x_variant":[
        "\u6de1\u51b2"
    ],
    "wof:name":"Danchong",
    "wof:placetype":"locality"
},
  "geometry": {"coordinates":[114.21867,27.6734],"type":"Point"}
}