{
  "type": "Feature",
  "properties": {
    "gn:admin1_code":"11.0",
    "gn:asciiname":"Baiyixuan",
    "gn:country_code":"CN",
    "gn:dem":89,
    "gn:feature_class":"P",
    "gn:feature_code":"PPL",
    "gn:name":"Baiyixuan",
    "gn:population":0,
    "gn:timezone":"Asia/Shanghai",
    "iso:country":"CN",
    "name:zho_x_preferred":[
        "\u767e\u5b9c\u8f69"
    ],
    "wof:name":"Baiyixuan",
    "wof:placetype":"locality"
},
  "geometry": {"coordinates":[113.61242,28.16277],"type":"Point"}
}