{
  "type": "Feature",
  "properties": {
    "gn:admin1_code":"14.0",
    "gn:asciiname":"Jiacong",
    "gn:country_code":"CN",
    "gn:dem":3789,
    "gn:feature_class":"P",
    "gn:feature_code":"PPL",
    "gn:name":"Jiacong",
    "gn:population":0,
    "gn:timezone":"Asia/Urumqi",
    "iso:country":"CN",
    "name:zho_x_preferred":[
        "\u52a0\u4ece"
    ],
    "wof:name":"Jiacong",
    "wof:placetype":"locality"
},
  "geometry": {"coordinates":[96.74831,30.37769],"type":"Point"}
}