{
  "type": "Feature",
  "properties": {
    "gn:admin1_code":"26.0",
    "gn:asciiname":"Xinghuagou",
    "gn:country_code":"CN",
    "gn:dem":917,
    "gn:feature_class":"P",
    "gn:feature_code":"PPL",
    "gn:name":"Xinghuagou",
    "gn:population":0,
    "gn:timezone":"Asia/Shanghai",
    "iso:country":"CN",
    "name:zho_x_preferred":[
        "\u674f\u82b1\u72d7"
    ],
    "wof:name":"Xinghuagou",
    "wof:placetype":"locality"
},
  "geometry": {"coordinates":[109.0663,34.93384],"type":"Point"}
}