{
  "type": "Feature",
  "properties": {
    "gn:admin1_code":"30.0",
    "gn:asciiname":"Huangshikeng",
    "gn:country_code":"CN",
    "gn:dem":12,
    "gn:feature_class":"P",
    "gn:feature_code":"PPL",
    "gn:name":"Huangshikeng",
    "gn:population":0,
    "gn:timezone":"Asia/Shanghai",
    "iso:country":"CN",
    "name:zho_x_preferred":[
        "\u9ec4\u72ee\u5751"
    ],
    "wof:name":"Huangshikeng",
    "wof:placetype":"locality"
},
  "geometry": {"coordinates":[112.58266,22.21411],"type":"Point"}
}