{
  "type": "Feature",
  "properties": {
    "gn:admin1_code":"7",
    "gn:asciiname":"Meiyang",
    "gn:country_code":"CN",
    "gn:dem":687,
    "gn:feature_class":"P",
    "gn:feature_code":"PPL",
    "gn:name":"Meiyang",
    "gn:population":0,
    "gn:timezone":"Asia/Shanghai",
    "iso:country":"CN",
    "name:und_x_variant":[
        "\u6885\u6d0b",
        "Meiyang"
    ],
    "wof:name":"Meiyang",
    "wof:placetype":"locality"
},
  "geometry": {"coordinates":[119.99329,27.13069],"type":"Point"}
}