{
  "type": "Feature",
  "properties": {
    "gn:admin1_code":"32",
    "gn:asciiname":"Shiguchang",
    "gn:country_code":"CN",
    "gn:dem":493,
    "gn:feature_class":"P",
    "gn:feature_code":"PPL",
    "gn:name":"Shiguchang",
    "gn:population":0,
    "gn:timezone":"Asia/Shanghai",
    "iso:country":"CN",
    "name:zho_x_preferred":[
        "\u65f6\u53e4\u573a"
    ],
    "wof:name":"Shiguchang",
    "wof:placetype":"locality"
},
  "geometry": {"coordinates":[105.47465,31.62198],"type":"Point"}
}