{
  "type": "Feature",
  "properties": {
    "gn:admin1_code":"8.0",
    "gn:asciiname":"Hongfeng",
    "gn:country_code":"CN",
    "gn:dem":87,
    "gn:feature_class":"P",
    "gn:feature_code":"PPL",
    "gn:name":"Hongfeng",
    "gn:population":0,
    "gn:timezone":"Asia/Shanghai",
    "iso:country":"CN",
    "name:zho_x_preferred":[
        "\u7ea2\u4e30"
    ],
    "wof:name":"Hongfeng",
    "wof:placetype":"locality"
},
  "geometry": {"coordinates":[130.78136000000001,47.55945],"type":"Point"}
}