{
  "type": "Feature",
  "properties": {
    "gn:admin1_code":"24.0",
    "gn:asciiname":"Xiannancun",
    "gn:country_code":"CN",
    "gn:dem":504,
    "gn:feature_class":"P",
    "gn:feature_code":"PPL",
    "gn:name":"Xiannancun",
    "gn:population":0,
    "gn:timezone":"Asia/Shanghai",
    "iso:country":"CN",
    "name:zho_x_preferred":[
        "\u53bf\u5357\u6751"
    ],
    "wof:name":"Xiannancun",
    "wof:placetype":"locality"
},
  "geometry": {"coordinates":[110.67968999999999,34.68386],"type":"Point"}
}