{
  "type": "Feature",
  "properties": {
    "gn:admin1_code":"11",
    "gn:asciiname":"Pingtan",
    "gn:country_code":"CN",
    "gn:dem":438,
    "gn:feature_class":"P",
    "gn:feature_code":"PPL",
    "gn:name":"Pingtan",
    "gn:population":0,
    "gn:timezone":"Asia/Shanghai",
    "iso:country":"CN",
    "name:ceb_x_preferred":[
        "Pingtan"
    ],
    "wof:name":"Pingtan",
    "wof:placetype":"locality"
},
  "geometry": {"coordinates":[109.72278,26.065],"type":"Point"}
}