{
  "type": "Feature",
  "properties": {
    "gn:admin1_code":"11",
    "gn:asciiname":"Baimaotang",
    "gn:country_code":"CN",
    "gn:dem":549,
    "gn:feature_class":"P",
    "gn:feature_code":"PPL",
    "gn:name":"Baimaotang",
    "gn:population":0,
    "gn:timezone":"Asia/Shanghai",
    "iso:country":"CN",
    "name:zho_x_preferred":[
        "\u767d\u6bdb\u5858"
    ],
    "wof:name":"Baimaotang",
    "wof:placetype":"locality"
},
  "geometry": {"coordinates":[111.7364,27.93992],"type":"Point"}
}