{
  "type": "Feature",
  "properties": {
    "gn:admin1_code":"29.0",
    "gn:asciiname":"Guidong Dazhai",
    "gn:country_code":"CN",
    "gn:dem":1296,
    "gn:feature_class":"P",
    "gn:feature_code":"PPL",
    "gn:name":"Guidong Dazhai",
    "gn:population":0,
    "gn:timezone":"Asia/Shanghai",
    "iso:country":"CN",
    "name:zho_x_preferred":[
        "\u5f52\u6d1e\u5927\u5be8"
    ],
    "wof:name":"Guidong Dazhai",
    "wof:placetype":"locality"
},
  "geometry": {"coordinates":[102.685,22.9419],"type":"Point"}
}