{
  "type": "Feature",
  "properties": {
    "gn:admin1_code":"7",
    "gn:asciiname":"Xiasha",
    "gn:country_code":"CN",
    "gn:dem":11,
    "gn:feature_class":"P",
    "gn:feature_code":"PPL",
    "gn:name":"Xiasha",
    "gn:population":0,
    "gn:timezone":"Asia/Shanghai",
    "iso:country":"CN",
    "name:und_x_variant":[
        "Xiaosha"
    ],
    "name:zho_x_preferred":[
        "\u4e0b\u6c99"
    ],
    "wof:name":"Xiasha",
    "wof:placetype":"locality"
},
  "geometry": {"coordinates":[119.60232000000001,25.81022],"type":"Point"}
}