{
  "type": "Feature",
  "properties": {
    "gn:admin1_code":"02",
    "gn:asciiname":"Shicang Xiacun",
    "gn:country_code":"CN",
    "gn:dem":16,
    "gn:feature_class":"P",
    "gn:feature_code":"PPL",
    "gn:name":"Shicang Xiacun",
    "gn:population":0,
    "gn:timezone":"Asia/Shanghai",
    "iso:country":"CN",
    "name:und_x_variant":[
        "Shicangxia"
    ],
    "name:zho_x_preferred":[
        "\u77f3\u4ed3\u4e0b\u6751"
    ],
    "wof:name":"Shicang Xiacun",
    "wof:placetype":"locality"
},
  "geometry": {"coordinates":[121.40369,28.42712],"type":"Point"}
}