{
  "type": "Feature",
  "properties": {
    "gn:admin1_code":"4.0",
    "gn:asciiname":"Chuannancun",
    "gn:country_code":"CN",
    "gn:dem":4,
    "gn:feature_class":"P",
    "gn:feature_code":"PPL",
    "gn:name":"Chuannancun",
    "gn:population":0,
    "gn:timezone":"Asia/Shanghai",
    "iso:country":"CN",
    "name:zho_x_preferred":[
        "\u5ddd\u5357\u6751"
    ],
    "wof:name":"Chuannancun",
    "wof:placetype":"locality"
},
  "geometry": {"coordinates":[120.69452,32.99811],"type":"Point"}
}