{
  "type": "Feature",
  "properties": {
    "gn:admin1_code":"15",
    "gn:asciiname":"Sanligeta",
    "gn:country_code":"CN",
    "gn:dem":1367,
    "gn:feature_class":"P",
    "gn:feature_code":"PPL",
    "gn:name":"Sanligeta",
    "gn:population":0,
    "gn:timezone":"Asia/Shanghai",
    "iso:country":"CN",
    "wof:name":"Sanligeta",
    "wof:placetype":"locality"
},
  "geometry": {"coordinates":[107.54528000000001,35.96583],"type":"Point"}
}