{
  "type": "Feature",
  "properties": {
    "gn:admin1_code":"18.0",
    "gn:asciiname":"Bianyao",
    "gn:country_code":"CN",
    "gn:dem":911,
    "gn:feature_class":"P",
    "gn:feature_code":"PPL",
    "gn:name":"Bianyao",
    "gn:population":0,
    "gn:timezone":"Asia/Shanghai",
    "iso:country":"CN",
    "name:zho_x_preferred":[
        "\u8d2c\u8981"
    ],
    "wof:name":"Bianyao",
    "wof:placetype":"locality"
},
  "geometry": {"coordinates":[107.369,25.6659],"type":"Point"}
}