{
  "type": "Feature",
  "properties": {
    "gn:admin1_code":"5",
    "gn:asciiname":"Erdao Goushangtun",
    "gn:country_code":"CN",
    "gn:dem":337,
    "gn:feature_class":"P",
    "gn:feature_code":"PPL",
    "gn:name":"Erdao Goushangtun",
    "gn:population":0,
    "gn:timezone":"Asia/Shanghai",
    "iso:country":"CN",
    "name:zho_x_preferred":[
        "\u4e8c\u9053\u6c9f\u4e0a\u5c6f"
    ],
    "wof:name":"Erdao Goushangtun",
    "wof:placetype":"locality"
},
  "geometry": {"coordinates":[127.02422,43.60629],"type":"Point"}
}