{
  "type": "Feature",
  "properties": {
    "gn:admin1_code":"30.0",
    "gn:asciiname":"Wunitian",
    "gn:country_code":"CN",
    "gn:dem":144,
    "gn:feature_class":"P",
    "gn:feature_code":"PPL",
    "gn:name":"Wunitian",
    "gn:population":0,
    "gn:timezone":"Asia/Shanghai",
    "iso:country":"CN",
    "name:zho_x_preferred":[
        "Wunitian"
    ],
    "name:zho_x_variant":[
        "\u4e4c\u576d\u7530"
    ],
    "wof:name":"Wunitian",
    "wof:placetype":"locality"
},
  "geometry": {"coordinates":[114.35598,24.20943],"type":"Point"}
}