{
  "type": "Feature",
  "properties": {
    "gn:admin1_code":"14.0",
    "gn:asciiname":"Godam",
    "gn:country_code":"CN",
    "gn:dem":4742,
    "gn:feature_class":"P",
    "gn:feature_code":"PPLF",
    "gn:name":"Godam",
    "gn:population":0,
    "gn:timezone":"Asia/Urumqi",
    "iso:country":"CN",
    "name:bod_x_preferred":[
        "Godam"
    ],
    "name:zho_x_preferred":[
        "Guodang"
    ],
    "name:zho_x_variant":[
        "\u679c\u5f53",
        "Gelagongma",
        "\u683c\u62c9\u8d21\u739b"
    ],
    "wof:name":"Godam",
    "wof:placetype":"locality"
},
  "geometry": {"coordinates":[93.301,32.901],"type":"Point"}
}