{
  "type": "Feature",
  "properties": {
    "gn:admin1_code":"9.0",
    "gn:asciiname":"Dongwadian",
    "gn:country_code":"CN",
    "gn:dem":213,
    "gn:feature_class":"P",
    "gn:feature_code":"PPL",
    "gn:name":"Dongwadian",
    "gn:population":0,
    "gn:timezone":"Asia/Shanghai",
    "iso:country":"CN",
    "name:zho_x_preferred":[
        "\u4e1c\u74e6\u5e97"
    ],
    "wof:name":"Dongwadian",
    "wof:placetype":"locality"
},
  "geometry": {"coordinates":[113.3505,34.49325],"type":"Point"}
}