{
  "type": "Feature",
  "properties": {
    "gn:admin1_code":"10.0",
    "gn:asciiname":"Luobuwo",
    "gn:country_code":"CN",
    "gn:dem":9,
    "gn:feature_class":"P",
    "gn:feature_code":"PPL",
    "gn:name":"Luobuwo",
    "gn:population":0,
    "gn:timezone":"Asia/Shanghai",
    "iso:country":"CN",
    "name:zho_x_preferred":[
        "\u7f57\u535c\u7a9d"
    ],
    "wof:name":"Luobuwo",
    "wof:placetype":"locality"
},
  "geometry": {"coordinates":[117.70822,39.61456],"type":"Point"}
}