{
  "type": "Feature",
  "properties": {
    "gn:admin1_code":"09",
    "gn:asciiname":"Mashankou",
    "gn:country_code":"CN",
    "gn:dem":208,
    "gn:feature_class":"P",
    "gn:feature_code":"PPLA4",
    "gn:name":"Mashankou",
    "gn:population":0,
    "gn:timezone":"Asia/Shanghai",
    "iso:country":"CN",
    "name:und_x_variant":[
        "\u9a6c\u5c71\u53e3",
        "Mashankou Zhen",
        "\u9a6c\u5c71\u53e3\u9547",
        "Mashankou"
    ],
    "wof:name":"Mashankou",
    "wof:placetype":"locality"
},
  "geometry": {"coordinates":[112.00261,33.20577],"type":"Point"}
}