{
  "type": "Feature",
  "properties": {
    "gn:admin1_code":"32.0",
    "gn:asciiname":"Huangjueshu",
    "gn:country_code":"CN",
    "gn:dem":675,
    "gn:feature_class":"P",
    "gn:feature_code":"PPL",
    "gn:name":"Huangjueshu",
    "gn:population":0,
    "gn:timezone":"Asia/Shanghai",
    "iso:country":"CN",
    "name:zho_x_preferred":[
        "\u9ec4\u6877\u6811"
    ],
    "wof:name":"Huangjueshu",
    "wof:placetype":"locality"
},
  "geometry": {"coordinates":[105.273,28.0954],"type":"Point"}
}