{
  "type": "Feature",
  "properties": {
    "gn:admin1_code":"32.0",
    "gn:asciiname":"Hongqiaogou",
    "gn:country_code":"CN",
    "gn:dem":3200,
    "gn:feature_class":"P",
    "gn:feature_code":"PPL",
    "gn:name":"Hongqiaogou",
    "gn:population":0,
    "gn:timezone":"Asia/Shanghai",
    "iso:country":"CN",
    "name:zho_x_preferred":[
        "\u7ea2\u6865\u6c9f"
    ],
    "wof:name":"Hongqiaogou",
    "wof:placetype":"locality"
},
  "geometry": {"coordinates":[102.52417,31.5111],"type":"Point"}
}