{
  "type": "Feature",
  "properties": {
    "gn:admin1_code":"32",
    "gn:asciiname":"Liangjiashan",
    "gn:country_code":"CN",
    "gn:dem":568,
    "gn:feature_class":"P",
    "gn:feature_code":"PPL",
    "gn:name":"Liangjiashan",
    "gn:population":0,
    "gn:timezone":"Asia/Shanghai",
    "iso:country":"CN",
    "name:zho_x_preferred":[
        "\u6881\u5bb6\u5c71"
    ],
    "wof:name":"Liangjiashan",
    "wof:placetype":"locality"
},
  "geometry": {"coordinates":[105.79416000000001,31.92032],"type":"Point"}
}