{
  "type": "Feature",
  "properties": {
    "gn:admin1_code":"26.0",
    "gn:asciiname":"Houweizhaicun",
    "gn:country_code":"CN",
    "gn:dem":388,
    "gn:feature_class":"P",
    "gn:feature_code":"PPL",
    "gn:name":"Houweizhaicun",
    "gn:population":0,
    "gn:timezone":"Asia/Shanghai",
    "iso:country":"CN",
    "name:zho_x_preferred":[
        "\u540e\u56f4\u5be8\u6751"
    ],
    "wof:name":"Houweizhaicun",
    "wof:placetype":"locality"
},
  "geometry": {"coordinates":[108.8049,34.29487],"type":"Point"}
}