{
  "type": "Feature",
  "properties": {
    "gn:admin1_code":"24",
    "gn:asciiname":"Guxian",
    "gn:cc2":"CN",
    "gn:country_code":"CN",
    "gn:dem":1210,
    "gn:feature_class":"P",
    "gn:feature_code":"PPL",
    "gn:name":"Guxian",
    "gn:population":0,
    "gn:timezone":"Asia/Shanghai",
    "iso:country":"CN",
    "name:und_x_variant":[
        "Ku-hsien-ts\u2019un",
        "Ku-hsien",
        "Guxian"
    ],
    "wof:name":"Guxian",
    "wof:placetype":"locality"
},
  "geometry": {"coordinates":[111.17749999999999,38.27861],"type":"Point"}
}