{
  "type": "Feature",
  "properties": {
    "gn:admin1_code":"18",
    "gn:asciiname":"Manaoshan",
    "gn:country_code":"CN",
    "gn:dem":803,
    "gn:feature_class":"P",
    "gn:feature_code":"PPL",
    "gn:name":"Manaoshan",
    "gn:population":0,
    "gn:timezone":"Asia/Shanghai",
    "iso:country":"CN",
    "name:zho_x_preferred":[
        "\u9a6c\u8111\u5c71"
    ],
    "wof:name":"Manaoshan",
    "wof:placetype":"locality"
},
  "geometry": {"coordinates":[107.655,27.8888],"type":"Point"}
}