{
  "type": "Feature",
  "properties": {
    "gn:admin1_code":"11.0",
    "gn:asciiname":"Qifangqiao",
    "gn:country_code":"CN",
    "gn:dem":287,
    "gn:feature_class":"P",
    "gn:feature_code":"PPL",
    "gn:name":"Qifangqiao",
    "gn:population":0,
    "gn:timezone":"Asia/Shanghai",
    "iso:country":"CN",
    "name:zho_x_preferred":[
        "\u4e03\u65b9\u6865"
    ],
    "wof:name":"Qifangqiao",
    "wof:placetype":"locality"
},
  "geometry": {"coordinates":[109.74309,28.26808],"type":"Point"}
}