{
  "type": "Feature",
  "properties": {
    "gn:admin1_code":"29.0",
    "gn:asciiname":"Maocaoshui",
    "gn:country_code":"CN",
    "gn:dem":1435,
    "gn:feature_class":"P",
    "gn:feature_code":"PPL",
    "gn:name":"Maocaoshui",
    "gn:population":0,
    "gn:timezone":"Asia/Shanghai",
    "iso:country":"CN",
    "name:zho_x_preferred":[
        "\u8305\u8349\u6c34"
    ],
    "wof:name":"Maocaoshui",
    "wof:placetype":"locality"
},
  "geometry": {"coordinates":[99.42359999999999,24.0724],"type":"Point"}
}