{
  "type": "Feature",
  "properties": {
    "gn:admin1_code":"29",
    "gn:asciiname":"Baizhujing",
    "gn:country_code":"CN",
    "gn:dem":1419,
    "gn:feature_class":"P",
    "gn:feature_code":"PPL",
    "gn:name":"Baizhujing",
    "gn:population":0,
    "gn:timezone":"Asia/Shanghai",
    "iso:country":"CN",
    "name:zho_x_preferred":[
        "\u767e\u7af9\u9631"
    ],
    "wof:name":"Baizhujing",
    "wof:placetype":"locality"
},
  "geometry": {"coordinates":[104.59,23.1989],"type":"Point"}
}