{
  "type": "Feature",
  "properties": {
    "gn:admin1_code":"32.0",
    "gn:asciiname":"Tianwanyizu",
    "gn:country_code":"CN",
    "gn:dem":1417,
    "gn:feature_class":"P",
    "gn:feature_code":"PPL",
    "gn:name":"Tianwanyizu",
    "gn:population":0,
    "gn:timezone":"Asia/Shanghai",
    "iso:country":"CN",
    "name:zho_x_preferred":[
        "\u7530\u6e7e\u5f5d\u65cf"
    ],
    "wof:name":"Tianwanyizu",
    "wof:placetype":"locality"
},
  "geometry": {"coordinates":[102.17547999999999,29.44272],"type":"Point"}
}