{
  "type": "Feature",
  "properties": {
    "gn:admin1_code":"14.0",
    "gn:asciiname":"Caodeka",
    "gn:country_code":"CN",
    "gn:dem":4402,
    "gn:feature_class":"P",
    "gn:feature_code":"PPL",
    "gn:name":"Caodeka",
    "gn:population":0,
    "gn:timezone":"Asia/Urumqi",
    "iso:country":"CN",
    "name:zho_x_preferred":[
        "\u66f9\u5f97\u5580"
    ],
    "wof:name":"Caodeka",
    "wof:placetype":"locality"
},
  "geometry": {"coordinates":[94.43029,31.18399],"type":"Point"}
}