{
  "type": "Feature",
  "properties": {
    "gn:admin1_code":"18.0",
    "gn:asciiname":"Gannao",
    "gn:country_code":"CN",
    "gn:dem":788,
    "gn:feature_class":"P",
    "gn:feature_code":"PPL",
    "gn:name":"Gannao",
    "gn:population":0,
    "gn:timezone":"Asia/Shanghai",
    "iso:country":"CN",
    "name:zho_x_preferred":[
        "\u5e72\u8111"
    ],
    "wof:name":"Gannao",
    "wof:placetype":"locality"
},
  "geometry": {"coordinates":[108.099,26.2753],"type":"Point"}
}