{
  "type": "Feature",
  "properties": {
    "gn:admin1_code":"24.0",
    "gn:asciiname":"Xiawangzhuang",
    "gn:country_code":"CN",
    "gn:dem":797,
    "gn:feature_class":"P",
    "gn:feature_code":"PPL",
    "gn:name":"Xiawangzhuang",
    "gn:population":0,
    "gn:timezone":"Asia/Shanghai",
    "iso:country":"CN",
    "name:zho_x_preferred":[
        "\u4e0b\u738b\u5e84"
    ],
    "wof:name":"Xiawangzhuang",
    "wof:placetype":"locality"
},
  "geometry": {"coordinates":[112.70516000000001,38.64657],"type":"Point"}
}