{
  "type": "Feature",
  "properties": {
    "gn:admin1_code":"2",
    "gn:asciiname":"Jinxi",
    "gn:country_code":"CN",
    "gn:dem":82,
    "gn:feature_class":"P",
    "gn:feature_code":"PPL",
    "gn:name":"Jinxi",
    "gn:population":0,
    "gn:timezone":"Asia/Shanghai",
    "iso:country":"CN",
    "name:ceb_x_preferred":[
        "Jinxi"
    ],
    "name:deu_x_preferred":[
        "Jinxi"
    ],
    "name:und_x_variant":[
        "\u664b\u6eaa"
    ],
    "name:zho_x_preferred":[
        "\u664b\u6eaa"
    ],
    "wof:name":"Jinxi",
    "wof:placetype":"locality"
},
  "geometry": {"coordinates":[121.00888999999999,29.57417],"type":"Point"}
}