{
  "type": "Feature",
  "properties": {
    "gn:admin1_code":"7.0",
    "gn:asciiname":"Matou Xiacun",
    "gn:country_code":"CN",
    "gn:dem":332,
    "gn:feature_class":"P",
    "gn:feature_code":"PPL",
    "gn:name":"Matou Xiacun",
    "gn:population":0,
    "gn:timezone":"Asia/Shanghai",
    "iso:country":"CN",
    "name:zho_x_preferred":[
        "\u9a6c\u5934\u4e0b\u6751"
    ],
    "wof:name":"Matou Xiacun",
    "wof:placetype":"locality"
},
  "geometry": {"coordinates":[119.84557,26.99335],"type":"Point"}
}