{
  "type": "Feature",
  "properties": {
    "gn:admin1_code":"7.0",
    "gn:asciiname":"Xiahengshan",
    "gn:country_code":"CN",
    "gn:dem":8,
    "gn:feature_class":"P",
    "gn:feature_code":"PPL",
    "gn:name":"Xiahengshan",
    "gn:population":0,
    "gn:timezone":"Asia/Shanghai",
    "iso:country":"CN",
    "name:zho_x_preferred":[
        "\u4e0b\u6a2a\u5c71"
    ],
    "wof:name":"Xiahengshan",
    "wof:placetype":"locality"
},
  "geometry": {"coordinates":[118.99599000000001,25.39907],"type":"Point"}
}