{
  "type": "Feature",
  "properties": {
    "gn:admin1_code":"3.0",
    "gn:asciiname":"Lingdi",
    "gn:country_code":"CN",
    "gn:dem":222,
    "gn:feature_class":"P",
    "gn:feature_code":"PPL",
    "gn:name":"Lingdi",
    "gn:population":0,
    "gn:timezone":"Asia/Shanghai",
    "iso:country":"CN",
    "name:zho_x_preferred":[
        "\u5cad\u5e95"
    ],
    "wof:name":"Lingdi",
    "wof:placetype":"locality"
},
  "geometry": {"coordinates":[118.04391,28.69494000000001],"type":"Point"}
}