{
  "type": "Feature",
  "properties": {
    "gn:admin1_code":"29.0",
    "gn:asciiname":"Bengnong",
    "gn:country_code":"CN",
    "gn:dem":1124,
    "gn:feature_class":"P",
    "gn:feature_code":"PPL",
    "gn:name":"Bengnong",
    "gn:population":0,
    "gn:timezone":"Asia/Shanghai",
    "iso:country":"CN",
    "name:zho_x_preferred":[
        "\u5d29\u5f04"
    ],
    "wof:name":"Bengnong",
    "wof:placetype":"locality"
},
  "geometry": {"coordinates":[99.3973,23.4516],"type":"Point"}
}