{
  "type": "Feature",
  "properties": {
    "gn:admin1_code":"29.0",
    "gn:asciiname":"Xiaosongke",
    "gn:country_code":"CN",
    "gn:dem":2348,
    "gn:feature_class":"P",
    "gn:feature_code":"PPL",
    "gn:name":"Xiaosongke",
    "gn:population":0,
    "gn:timezone":"Asia/Shanghai",
    "iso:country":"CN",
    "name:zho_x_preferred":[
        "\u5c0f\u677e\u79d1"
    ],
    "wof:name":"Xiaosongke",
    "wof:placetype":"locality"
},
  "geometry": {"coordinates":[103.611,26.2658],"type":"Point"}
}