{
  "type": "Feature",
  "properties": {
    "gn:admin1_code":"1.0",
    "gn:asciiname":"Humacun",
    "gn:country_code":"CN",
    "gn:dem":26,
    "gn:feature_class":"P",
    "gn:feature_code":"PPL",
    "gn:name":"Humacun",
    "gn:population":0,
    "gn:timezone":"Asia/Shanghai",
    "iso:country":"CN",
    "name:zho_x_preferred":[
        "\u80e1\u9a6c\u6751"
    ],
    "wof:name":"Humacun",
    "wof:placetype":"locality"
},
  "geometry": {"coordinates":[116.53581,32.7135],"type":"Point"}
}