{
  "type": "Feature",
  "properties": {
    "gn:admin1_code":"07",
    "gn:asciiname":"Dunshang",
    "gn:country_code":"CN",
    "gn:dem":16,
    "gn:feature_class":"P",
    "gn:feature_code":"PPL",
    "gn:name":"Dunshang",
    "gn:population":0,
    "gn:timezone":"Asia/Shanghai",
    "iso:country":"CN",
    "name:und_x_variant":[
        "\u58a9\u4e0a",
        "Dunshang"
    ],
    "wof:name":"Dunshang",
    "wof:placetype":"locality"
},
  "geometry": {"coordinates":[118.15062,24.51722],"type":"Point"}
}