{
  "type": "Feature",
  "properties": {
    "gn:admin1_code":"1.0",
    "gn:asciiname":"Keqiaocun",
    "gn:country_code":"CN",
    "gn:dem":14,
    "gn:feature_class":"P",
    "gn:feature_code":"PPL",
    "gn:name":"Keqiaocun",
    "gn:population":0,
    "gn:timezone":"Asia/Shanghai",
    "iso:country":"CN",
    "name:zho_x_preferred":[
        "\u67ef\u6865\u6751"
    ],
    "wof:name":"Keqiaocun",
    "wof:placetype":"locality"
},
  "geometry": {"coordinates":[117.256,31.57906],"type":"Point"}
}