{
  "type": "Feature",
  "properties": {
    "gn:admin1_code":"32",
    "gn:asciiname":"Songlin",
    "gn:country_code":"CN",
    "gn:dem":1632,
    "gn:feature_class":"P",
    "gn:feature_code":"PPL",
    "gn:name":"Songlin",
    "gn:population":0,
    "gn:timezone":"Asia/Shanghai",
    "iso:country":"CN",
    "name:und_x_variant":[
        "Sung-lin",
        "Songlin"
    ],
    "name:zho_x_preferred":[
        "\u677e\u6797"
    ],
    "wof:name":"Songlin",
    "wof:placetype":"locality"
},
  "geometry": {"coordinates":[102.1653,28.21082],"type":"Point"}
}