{
  "type": "Feature",
  "properties": {
    "gn:admin1_code":"01",
    "gn:asciiname":"Dingcheng",
    "gn:country_code":"CN",
    "gn:dem":68,
    "gn:feature_class":"P",
    "gn:feature_code":"PPLA3",
    "gn:name":"Dingcheng",
    "gn:population":0,
    "gn:timezone":"Asia/Shanghai",
    "iso:country":"CN",
    "name:ceb_x_preferred":[
        "Dingcheng"
    ],
    "name:und_x_variant":[
        "Dingyuan"
    ],
    "name:zho_x_preferred":[
        "Y\u00fcan-t\u2019ing"
    ],
    "name:zho_x_variant":[
        "Ting-ch\u2019eng-chen",
        "\u5b9a\u57ce",
        "Ting-y\u00fcan-hsien",
        "Ting-y\u00fcan"
    ],
    "wof:name":"Dingcheng",
    "wof:placetype":"locality"
},
  "geometry": {"coordinates":[117.65952,32.51609000000001],"type":"Point"}
}