{
  "type": "Feature",
  "properties": {
    "gn:admin1_code":"25",
    "gn:asciiname":"Laoniuzhai",
    "gn:country_code":"CN",
    "gn:dem":429,
    "gn:feature_class":"P",
    "gn:feature_code":"PPL",
    "gn:name":"Laoniuzhai",
    "gn:population":0,
    "gn:timezone":"Asia/Shanghai",
    "iso:country":"CN",
    "name:zho_x_preferred":[
        "\u8001\u725b\u5be8"
    ],
    "wof:name":"Laoniuzhai",
    "wof:placetype":"locality"
},
  "geometry": {"coordinates":[117.29000000000001,36.3809],"type":"Point"}
}