{
  "type": "Feature",
  "properties": {
    "gn:admin1_code":"7.0",
    "gn:asciiname":"Dongfang",
    "gn:country_code":"CN",
    "gn:dem":33,
    "gn:feature_class":"P",
    "gn:feature_code":"PPL",
    "gn:name":"Dongfang",
    "gn:population":0,
    "gn:timezone":"Asia/Shanghai",
    "iso:country":"CN",
    "name:ceb_x_preferred":[
        "Dongfang"
    ],
    "name:deu_x_preferred":[
        "Dongfang"
    ],
    "name:nld_x_preferred":[
        "Dongfang"
    ],
    "name:swe_x_preferred":[
        "Dongfang"
    ],
    "name:zho_x_preferred":[
        "\u4e1c\u65b9"
    ],
    "wof:name":"Dongfang",
    "wof:placetype":"locality"
},
  "geometry": {"coordinates":[117.28556,23.95694],"type":"Point"}
}