{
  "type": "Feature",
  "properties": {
    "gn:admin1_code":"30",
    "gn:asciiname":"Nan'anxu",
    "gn:country_code":"CN",
    "gn:dem":15,
    "gn:feature_class":"P",
    "gn:feature_code":"PPL",
    "gn:name":"Nan\u2019anxu",
    "gn:population":0,
    "gn:timezone":"Asia/Urumqi",
    "iso:country":"CN",
    "name:zho_x_preferred":[
        "\u5357\u5b89\u5729"
    ],
    "name:zho_x_variant":[
        "Nan\u2019anxu"
    ],
    "wof:name":"Nan'anxu",
    "wof:placetype":"locality"
},
  "geometry": {"coordinates":[110.66972,21.53582],"type":"Point"}
}