{
  "type": "Feature",
  "properties": {
    "gn:admin1_code":"11.0",
    "gn:asciiname":"Yilingmiao",
    "gn:country_code":"CN",
    "gn:dem":35,
    "gn:feature_class":"P",
    "gn:feature_code":"PPL",
    "gn:name":"Yilingmiao",
    "gn:population":0,
    "gn:timezone":"Asia/Shanghai",
    "iso:country":"CN",
    "name:zho_x_preferred":[
        "\u79fb\u7075\u5e99"
    ],
    "wof:name":"Yilingmiao",
    "wof:placetype":"locality"
},
  "geometry": {"coordinates":[112.44353999999998,29.40011],"type":"Point"}
}