{
  "type": "Feature",
  "properties": {
    "gn:admin1_code":"30.0",
    "gn:asciiname":"Houtangcun",
    "gn:country_code":"CN",
    "gn:dem":155,
    "gn:feature_class":"P",
    "gn:feature_code":"PPL",
    "gn:name":"Houtangcun",
    "gn:population":0,
    "gn:timezone":"Asia/Shanghai",
    "iso:country":"CN",
    "name:zho_x_preferred":[
        "\u539a\u5858\u6751"
    ],
    "wof:name":"Houtangcun",
    "wof:placetype":"locality"
},
  "geometry": {"coordinates":[113.70417999999999,25.20227],"type":"Point"}
}