{
  "type": "Feature",
  "properties": {
    "gn:admin1_code":"26.0",
    "gn:asciiname":"Heijiawancun",
    "gn:country_code":"CN",
    "gn:dem":1113,
    "gn:feature_class":"P",
    "gn:feature_code":"PPL",
    "gn:name":"Heijiawancun",
    "gn:population":0,
    "gn:timezone":"Asia/Shanghai",
    "iso:country":"CN",
    "name:zho_x_preferred":[
        "\u9ed1\u5bb6\u6e7e\u6751"
    ],
    "wof:name":"Heijiawancun",
    "wof:placetype":"locality"
},
  "geometry": {"coordinates":[110.06581,35.51313],"type":"Point"}
}