{
  "type": "Feature",
  "properties": {
    "gn:admin1_code":"29.0",
    "gn:asciiname":"Xujiawan",
    "gn:country_code":"CN",
    "gn:dem":1582,
    "gn:feature_class":"P",
    "gn:feature_code":"PPL",
    "gn:name":"Xujiawan",
    "gn:population":0,
    "gn:timezone":"Asia/Shanghai",
    "iso:country":"CN",
    "name:zho_x_preferred":[
        "\u8bb8\u5bb6\u6e7e"
    ],
    "wof:name":"Xujiawan",
    "wof:placetype":"locality"
},
  "geometry": {"coordinates":[100.518,25.8943],"type":"Point"}
}