{
  "type": "Feature",
  "properties": {
    "gn:admin1_code":"3.0",
    "gn:asciiname":"Leitang",
    "gn:country_code":"CN",
    "gn:dem":272,
    "gn:feature_class":"P",
    "gn:feature_code":"PPL",
    "gn:name":"Leitang",
    "gn:population":0,
    "gn:timezone":"Asia/Shanghai",
    "iso:country":"CN",
    "name:zho_x_preferred":[
        "\u96f7\u5858"
    ],
    "wof:name":"Leitang",
    "wof:placetype":"locality"
},
  "geometry": {"coordinates":[118.14503000000001,28.30839000000001],"type":"Point"}
}