{
  "type": "Feature",
  "properties": {
    "gn:admin1_code":"02",
    "gn:asciiname":"Fuming",
    "gn:country_code":"CN",
    "gn:dem":4,
    "gn:feature_class":"P",
    "gn:feature_code":"PPLA4",
    "gn:name":"Fuming",
    "gn:population":0,
    "gn:timezone":"Asia/Shanghai",
    "iso:country":"CN",
    "name:und_x_variant":[
        "Fuming Jiedao",
        "Fuming"
    ],
    "name:zho_x_preferred":[
        "\u798f\u660e"
    ],
    "name:zho_x_variant":[
        "\u798f\u660e\u8857\u9053"
    ],
    "wof:name":"Fuming",
    "wof:placetype":"locality"
},
  "geometry": {"coordinates":[121.60186000000002,29.87316],"type":"Point"}
}