{
  "type": "Feature",
  "properties": {
    "gn:admin1_code":"30.0",
    "gn:asciiname":"Shenyong",
    "gn:country_code":"CN",
    "gn:dem":8,
    "gn:feature_class":"P",
    "gn:feature_code":"PPL",
    "gn:name":"Shenyong",
    "gn:population":0,
    "gn:timezone":"Asia/Shanghai",
    "iso:country":"CN",
    "name:zho_x_preferred":[
        "\u6df1\u6d8c"
    ],
    "wof:name":"Shenyong",
    "wof:placetype":"locality"
},
  "geometry": {"coordinates":[115.04765999999999,22.84395],"type":"Point"}
}