{
  "type": "Feature",
  "properties": {
    "gn:admin1_code":"19.0",
    "gn:asciiname":"Shangchangmao",
    "gn:country_code":"CN",
    "gn:dem":71,
    "gn:feature_class":"P",
    "gn:feature_code":"PPL",
    "gn:name":"Shangchangmao",
    "gn:population":0,
    "gn:timezone":"Asia/Shanghai",
    "iso:country":"CN",
    "name:zho_x_preferred":[
        "\u4e0a\u957f\u8302"
    ],
    "wof:name":"Shangchangmao",
    "wof:placetype":"locality"
},
  "geometry": {"coordinates":[120.56222,40.76721],"type":"Point"}
}