{
  "type": "Feature",
  "properties": {
    "gn:admin1_code":"19.0",
    "gn:asciiname":"Liujianfangcun",
    "gn:country_code":"CN",
    "gn:dem":10,
    "gn:feature_class":"P",
    "gn:feature_code":"PPL",
    "gn:name":"Liujianfangcun",
    "gn:population":0,
    "gn:timezone":"Asia/Shanghai",
    "iso:country":"CN",
    "name:zho_x_preferred":[
        "\u516d\u95f4\u623f\u6751"
    ],
    "wof:name":"Liujianfangcun",
    "wof:placetype":"locality"
},
  "geometry": {"coordinates":[122.57161000000001,41.32312],"type":"Point"}
}