{
  "type": "Feature",
  "properties": {
    "gn:admin1_code":"8.0",
    "gn:asciiname":"Jianguocun",
    "gn:country_code":"CN",
    "gn:dem":210,
    "gn:feature_class":"P",
    "gn:feature_code":"PPL",
    "gn:name":"Jianguocun",
    "gn:population":0,
    "gn:timezone":"Asia/Shanghai",
    "iso:country":"CN",
    "name:zho_x_preferred":[
        "\u5efa\u56fd\u6751"
    ],
    "wof:name":"Jianguocun",
    "wof:placetype":"locality"
},
  "geometry": {"coordinates":[124.54367999999999,48.06415],"type":"Point"}
}