{
  "type": "Feature",
  "properties": {
    "gn:admin1_code":"32.0",
    "gn:asciiname":"Qinggang",
    "gn:country_code":"CN",
    "gn:dem":412,
    "gn:feature_class":"P",
    "gn:feature_code":"PPL",
    "gn:name":"Qinggang",
    "gn:population":0,
    "gn:timezone":"Asia/Shanghai",
    "iso:country":"CN",
    "name:zho_x_preferred":[
        "\u9752\u5c97"
    ],
    "wof:name":"Qinggang",
    "wof:placetype":"locality"
},
  "geometry": {"coordinates":[104.25667,30.00839],"type":"Point"}
}