{
  "type": "Feature",
  "properties": {
    "gn:admin1_code":"15.0",
    "gn:asciiname":"Guanghua",
    "gn:country_code":"CN",
    "gn:dem":1014,
    "gn:feature_class":"P",
    "gn:feature_code":"PPL",
    "gn:name":"Guanghua",
    "gn:population":0,
    "gn:timezone":"Asia/Shanghai",
    "iso:country":"CN",
    "name:ceb_x_preferred":[
        "Guanghua"
    ],
    "name:deu_x_preferred":[
        "Guanghua"
    ],
    "name:pol_x_preferred":[
        "Guanghua"
    ],
    "name:swe_x_preferred":[
        "Guanghua"
    ],
    "name:und_x_variant":[
        "\u5e7f\u5316"
    ],
    "wof:name":"Guanghua",
    "wof:placetype":"locality"
},
  "geometry": {"coordinates":[105.64575000000001,33.70912],"type":"Point"}
}