{
  "type": "Feature",
  "properties": {
    "gn:admin1_code":"30.0",
    "gn:asciiname":"Yutian",
    "gn:country_code":"CN",
    "gn:dem":128,
    "gn:feature_class":"P",
    "gn:feature_code":"PPL",
    "gn:name":"Yutian",
    "gn:population":0,
    "gn:timezone":"Asia/Shanghai",
    "iso:country":"CN",
    "name:ceb_x_preferred":[
        "Yutian"
    ],
    "name:deu_x_preferred":[
        "Yutian"
    ],
    "name:fra_x_preferred":[
        "Yutian"
    ],
    "name:kor_x_preferred":[
        "\uc704\ud188\ud604"
    ],
    "name:nor_x_preferred":[
        "Yutian"
    ],
    "name:swe_x_preferred":[
        "Yutian"
    ],
    "name:zho_x_preferred":[
        "Yutian"
    ],
    "name:zho_x_variant":[
        "\u9c7c\u7530"
    ],
    "wof:name":"Yutian",
    "wof:placetype":"locality"
},
  "geometry": {"coordinates":[112.32111,24.79556],"type":"Point"}
}