{
  "type": "Feature",
  "properties": {
    "gn:admin1_code":"24.0",
    "gn:asciiname":"Zhuangwodun",
    "gn:country_code":"CN",
    "gn:dem":1261,
    "gn:feature_class":"P",
    "gn:feature_code":"PPL",
    "gn:name":"Zhuangwodun",
    "gn:population":0,
    "gn:timezone":"Asia/Shanghai",
    "iso:country":"CN",
    "name:zho_x_preferred":[
        "\u5e84\u7a9d\u58a9"
    ],
    "wof:name":"Zhuangwodun",
    "wof:placetype":"locality"
},
  "geometry": {"coordinates":[112.96178,40.32159],"type":"Point"}
}