{
  "type": "Feature",
  "properties": {
    "gn:admin1_code":"1.0",
    "gn:asciiname":"Zhangjicun",
    "gn:country_code":"CN",
    "gn:dem":35,
    "gn:feature_class":"P",
    "gn:feature_code":"PPL",
    "gn:name":"Zhangjicun",
    "gn:population":0,
    "gn:timezone":"Asia/Shanghai",
    "iso:country":"CN",
    "name:zho_x_preferred":[
        "\u5f20\u96c6\u6751"
    ],
    "wof:name":"Zhangjicun",
    "wof:placetype":"locality"
},
  "geometry": {"coordinates":[116.19441999999999,32.19023],"type":"Point"}
}