{
  "type": "Feature",
  "properties": {
    "gn:admin1_code":"11.0",
    "gn:asciiname":"Tangtouting",
    "gn:country_code":"CN",
    "gn:dem":95,
    "gn:feature_class":"P",
    "gn:feature_code":"PPL",
    "gn:name":"Tangtouting",
    "gn:population":0,
    "gn:timezone":"Asia/Shanghai",
    "iso:country":"CN",
    "name:zho_x_preferred":[
        "\u5858\u5934\u753a"
    ],
    "wof:name":"Tangtouting",
    "wof:placetype":"locality"
},
  "geometry": {"coordinates":[112.82068,26.82932000000001],"type":"Point"}
}