{
  "type": "Feature",
  "properties": {
    "gn:admin1_code":"15.0",
    "gn:asciiname":"Jijiawan",
    "gn:country_code":"CN",
    "gn:dem":1474,
    "gn:feature_class":"P",
    "gn:feature_code":"PPL",
    "gn:name":"Jijiawan",
    "gn:population":0,
    "gn:timezone":"Asia/Shanghai",
    "iso:country":"CN",
    "name:und_x_variant":[
        "\u59ec\u5bb6\u6e7e"
    ],
    "wof:name":"Jijiawan",
    "wof:placetype":"locality"
},
  "geometry": {"coordinates":[107.21826,36.07151],"type":"Point"}
}