{
  "type": "Feature",
  "properties": {
    "gn:admin1_code":"1.0",
    "gn:asciiname":"Yingangcun",
    "gn:country_code":"CN",
    "gn:dem":23,
    "gn:feature_class":"P",
    "gn:feature_code":"PPL",
    "gn:name":"Yingangcun",
    "gn:population":0,
    "gn:timezone":"Asia/Shanghai",
    "iso:country":"CN",
    "name:zho_x_preferred":[
        "\u6bb7\u6e2f\u6751"
    ],
    "wof:name":"Yingangcun",
    "wof:placetype":"locality"
},
  "geometry": {"coordinates":[116.53082000000001,32.76621],"type":"Point"}
}