{
  "type": "Feature",
  "properties": {
    "gn:admin1_code":"16.0",
    "gn:asciiname":"Jundong",
    "gn:country_code":"CN",
    "gn:dem":157,
    "gn:feature_class":"P",
    "gn:feature_code":"PPL",
    "gn:name":"Jundong",
    "gn:population":0,
    "gn:timezone":"Asia/Shanghai",
    "iso:country":"CN",
    "name:zho_x_preferred":[
        "\u541b\u578c"
    ],
    "wof:name":"Jundong",
    "wof:placetype":"locality"
},
  "geometry": {"coordinates":[110.89400000000001,22.7419],"type":"Point"}
}