{
  "type": "Feature",
  "properties": {
    "gn:admin1_code":"10.0",
    "gn:asciiname":"Shangliyu",
    "gn:country_code":"CN",
    "gn:dem":102,
    "gn:feature_class":"P",
    "gn:feature_code":"PPL",
    "gn:name":"Shangliyu",
    "gn:population":0,
    "gn:timezone":"Asia/Shanghai",
    "iso:country":"CN",
    "name:zho_x_preferred":[
        "\u4e0a\u68a8\u5cea"
    ],
    "wof:name":"Shangliyu",
    "wof:placetype":"locality"
},
  "geometry": {"coordinates":[118.994,40.03078],"type":"Point"}
}