{
  "type": "Feature",
  "properties": {
    "gn:admin1_code":"29.0",
    "gn:asciiname":"Hemo Xiazhai",
    "gn:country_code":"CN",
    "gn:dem":1226,
    "gn:feature_class":"P",
    "gn:feature_code":"PPL",
    "gn:name":"Hemo Xiazhai",
    "gn:population":0,
    "gn:timezone":"Asia/Shanghai",
    "iso:country":"CN",
    "name:zho_x_preferred":[
        "\u8d3a\u83ab\u4e0b\u5be8"
    ],
    "wof:name":"Hemo Xiazhai",
    "wof:placetype":"locality"
},
  "geometry": {"coordinates":[99.35380000000001,22.1962],"type":"Point"}
}