{
  "type": "Feature",
  "properties": {
    "gn:admin1_code":"15.0",
    "gn:asciiname":"Gaowan",
    "gn:country_code":"CN",
    "gn:dem":1127,
    "gn:feature_class":"P",
    "gn:feature_code":"PPL",
    "gn:name":"Gaowan",
    "gn:population":0,
    "gn:timezone":"Asia/Shanghai",
    "iso:country":"CN",
    "name:zho_x_preferred":[
        "\u9ad8\u6e7e"
    ],
    "wof:name":"Gaowan",
    "wof:placetype":"locality"
},
  "geometry": {"coordinates":[105.795,34.5685],"type":"Point"}
}