{
  "type": "Feature",
  "properties": {
    "gn:admin1_code":"2.0",
    "gn:asciiname":"Baishi",
    "gn:country_code":"CN",
    "gn:dem":459,
    "gn:feature_class":"P",
    "gn:feature_code":"PPL",
    "gn:name":"Baishi",
    "gn:population":0,
    "gn:timezone":"Asia/Shanghai",
    "iso:country":"CN",
    "name:zho_x_preferred":[
        "\u767d\u77f3"
    ],
    "wof:name":"Baishi",
    "wof:placetype":"locality"
},
  "geometry": {"coordinates":[118.77656,28.61986],"type":"Point"}
}