{
  "type": "Feature",
  "properties": {
    "gn:admin1_code":"30.0",
    "gn:asciiname":"Hebuling",
    "gn:country_code":"CN",
    "gn:dem":260,
    "gn:feature_class":"P",
    "gn:feature_code":"PPL",
    "gn:name":"Hebuling",
    "gn:population":0,
    "gn:timezone":"Asia/Shanghai",
    "iso:country":"CN",
    "name:zho_x_preferred":[
        "Hebuling"
    ],
    "name:zho_x_variant":[
        "\u6cb3\u5e03\u5cad"
    ],
    "wof:name":"Hebuling",
    "wof:placetype":"locality"
},
  "geometry": {"coordinates":[115.33944,24.01167],"type":"Point"}
}