{
  "type": "Feature",
  "properties": {
    "gn:admin1_code":"19.0",
    "gn:asciiname":"Shujigou",
    "gn:country_code":"CN",
    "gn:dem":305,
    "gn:feature_class":"P",
    "gn:feature_code":"PPL",
    "gn:name":"Shujigou",
    "gn:population":0,
    "gn:timezone":"Asia/Shanghai",
    "iso:country":"CN",
    "name:zho_x_preferred":[
        "\u6811\u57fa\u6c9f"
    ],
    "wof:name":"Shujigou",
    "wof:placetype":"locality"
},
  "geometry": {"coordinates":[124.65057,42.11292],"type":"Point"}
}