{
  "type": "Feature",
  "properties": {
    "gn:admin1_code":"7.0",
    "gn:asciiname":"Xintiankeng",
    "gn:country_code":"CN",
    "gn:dem":704,
    "gn:feature_class":"P",
    "gn:feature_code":"PPL",
    "gn:name":"Xintiankeng",
    "gn:population":0,
    "gn:timezone":"Asia/Shanghai",
    "iso:country":"CN",
    "name:zho_x_preferred":[
        "\u65b0\u7530\u5751"
    ],
    "wof:name":"Xintiankeng",
    "wof:placetype":"locality"
},
  "geometry": {"coordinates":[116.98623000000001,25.43369],"type":"Point"}
}