{
  "type": "Feature",
  "properties": {
    "gn:admin1_code":"19.0",
    "gn:asciiname":"Xiaotuanpiao",
    "gn:country_code":"CN",
    "gn:dem":65,
    "gn:feature_class":"P",
    "gn:feature_code":"PPL",
    "gn:name":"Xiaotuanpiao",
    "gn:population":0,
    "gn:timezone":"Asia/Shanghai",
    "iso:country":"CN",
    "name:zho_x_preferred":[
        "\u5c0f\u56e2\u74e2"
    ],
    "wof:name":"Xiaotuanpiao",
    "wof:placetype":"locality"
},
  "geometry": {"coordinates":[120.36,40.4601],"type":"Point"}
}