{
  "type": "Feature",
  "properties": {
    "gn:admin1_code":"2.0",
    "gn:asciiname":"Chenjiamen",
    "gn:country_code":"CN",
    "gn:dem":7,
    "gn:feature_class":"P",
    "gn:feature_code":"PPL",
    "gn:name":"Chenjiamen",
    "gn:population":0,
    "gn:timezone":"Asia/Shanghai",
    "iso:country":"CN",
    "name:und_x_variant":[
        "\u9648\u5bb6\u95e8"
    ],
    "wof:name":"Chenjiamen",
    "wof:placetype":"locality"
},
  "geometry": {"coordinates":[120.70484999999999,30.75189],"type":"Point"}
}