{
  "type": "Feature",
  "properties": {
    "gn:admin1_code":"4.0",
    "gn:asciiname":"Zhangniancun",
    "gn:country_code":"CN",
    "gn:dem":30,
    "gn:feature_class":"P",
    "gn:feature_code":"PPL",
    "gn:name":"Zhangniancun",
    "gn:population":0,
    "gn:timezone":"Asia/Shanghai",
    "iso:country":"CN",
    "name:zho_x_preferred":[
        "\u5f20\u57ab\u6751"
    ],
    "wof:name":"Zhangniancun",
    "wof:placetype":"locality"
},
  "geometry": {"coordinates":[117.68051,34.41005],"type":"Point"}
}