{
  "type": "Feature",
  "properties": {
    "gn:admin1_code":"9.0",
    "gn:asciiname":"Minglangsi",
    "gn:country_code":"CN",
    "gn:dem":76,
    "gn:feature_class":"P",
    "gn:feature_code":"PPL",
    "gn:name":"Minglangsi",
    "gn:population":0,
    "gn:timezone":"Asia/Shanghai",
    "iso:country":"CN",
    "name:zho_x_preferred":[
        "\u660e\u90ce\u5bfa"
    ],
    "wof:name":"Minglangsi",
    "wof:placetype":"locality"
},
  "geometry": {"coordinates":[113.94762,34.17583],"type":"Point"}
}