{
  "type": "Feature",
  "properties": {
    "gn:admin1_code":"29.0",
    "gn:asciiname":"Longtangba",
    "gn:country_code":"CN",
    "gn:dem":1498,
    "gn:feature_class":"P",
    "gn:feature_code":"PPL",
    "gn:name":"Longtangba",
    "gn:population":0,
    "gn:timezone":"Asia/Shanghai",
    "iso:country":"CN",
    "name:zho_x_preferred":[
        "\u9f99\u5858\u575d"
    ],
    "wof:name":"Longtangba",
    "wof:placetype":"locality"
},
  "geometry": {"coordinates":[101.01000000000001,23.0729],"type":"Point"}
}