{
  "type": "Feature",
  "properties": {
    "gn:admin1_code":"10.0",
    "gn:asciiname":"Daodigou",
    "gn:country_code":"CN",
    "gn:dem":474,
    "gn:feature_class":"P",
    "gn:feature_code":"PPL",
    "gn:name":"Daodigou",
    "gn:population":0,
    "gn:timezone":"Asia/Shanghai",
    "iso:country":"CN",
    "name:und_x_variant":[
        "\u7a3b\u5730\u6c9f"
    ],
    "wof:name":"Daodigou",
    "wof:placetype":"locality"
},
  "geometry": {"coordinates":[114.1403,38.81264],"type":"Point"}
}