{
  "type": "Feature",
  "properties": {
    "gn:admin1_code":"18",
    "gn:asciiname":"Rongma",
    "gn:country_code":"CN",
    "gn:dem":1299,
    "gn:feature_class":"P",
    "gn:feature_code":"PPL",
    "gn:name":"Rongma",
    "gn:population":0,
    "gn:timezone":"Asia/Shanghai",
    "iso:country":"CN",
    "name:msa_x_preferred":[
        "Rongma"
    ],
    "name:zho_x_preferred":[
        "\u5197\u9ebb"
    ],
    "wof:name":"Rongma",
    "wof:placetype":"locality"
},
  "geometry": {"coordinates":[105.633,25.1017],"type":"Point"}
}