{
  "type": "Feature",
  "properties": {
    "gn:admin1_code":"25",
    "gn:asciiname":"Dayuzhuang",
    "gn:country_code":"CN",
    "gn:dem":29,
    "gn:feature_class":"P",
    "gn:feature_code":"PPL",
    "gn:name":"Dayuzhuang",
    "gn:population":0,
    "gn:timezone":"Asia/Shanghai",
    "iso:country":"CN",
    "name:zho_x_preferred":[
        "\u5927\u4e8e\u5e84"
    ],
    "wof:name":"Dayuzhuang",
    "wof:placetype":"locality"
},
  "geometry": {"coordinates":[116.04900000000001,37.3448],"type":"Point"}
}