{
  "type": "Feature",
  "properties": {
    "gn:admin1_code":"29.0",
    "gn:asciiname":"Yangkongzhai",
    "gn:country_code":"CN",
    "gn:dem":1872,
    "gn:feature_class":"P",
    "gn:feature_code":"PPL",
    "gn:name":"Yangkongzhai",
    "gn:population":0,
    "gn:timezone":"Asia/Shanghai",
    "iso:country":"CN",
    "name:zho_x_preferred":[
        "\u6768\u63a7\u5be8"
    ],
    "wof:name":"Yangkongzhai",
    "wof:placetype":"locality"
},
  "geometry": {"coordinates":[100.036,23.0195],"type":"Point"}
}