{
  "type": "Feature",
  "properties": {
    "iso:country":"CN",
    "name:deu_x_preferred":[
        "Taxkorgan"
    ],
    "name:fas_x_preferred":[
        "\u062a\u0627\u0634\u06a9\u0648\u0631\u06af\u0627\u0646"
    ],
    "name:gan_x_preferred":[
        "\u5854\u4ec0\u5e93\u5c14\u5e72\u5854\u5409\u514b\u81ea\u6cbb\u53bf"
    ],
    "name:jpn_x_preferred":[
        "\u30bf\u30b7\u30e5\u30af\u30eb\u30ac\u30f3\u30fb\u30bf\u30b8\u30af\u81ea\u6cbb\u770c"
    ],
    "name:nob_x_preferred":[
        "Taxkorgan"
    ],
    "name:oci_x_preferred":[
        "Taxkorgan"
    ],
    "name:pol_x_preferred":[
        "Taxkorgan"
    ],
    "name:spa_x_preferred":[
        "Tashkurg\u00e1n Tayiko"
    ],
    "name:swe_x_preferred":[
        "Tashqurqan"
    ],
    "name:vie_x_preferred":[
        "Taxkorgan"
    ],
    "name:wuu_x_preferred":[
        "\u5854\u4ec0\u5e93\u5c14\u5e72\u5854\u5409\u514b\u81ea\u6cbb\u53bf"
    ],
    "name:zho_x_preferred":[
        "\u5854\u4ec0\u5e93\u5c14\u5e72\u5854\u5409\u514b\u81ea\u6cbb\u53bf"
    ],
    "qs:name":"\u5854\u4ec0\u5e93\u5c14\u5e72\u5854\u5409\u514b\u81ea\u6cbb\u53bf",
    "qs:name_adm0":"\u4e2d\u570b",
    "qs:name_adm1":"\u65b0\u7586\u7ef4\u543e\u5c14\u81ea\u6cbb\u533a",
    "qs:photos":3,
    "qs:photos_1k":1,
    "qs:photos_9k":2,
    "qs:photos_9r":5,
    "qs:photos_all":439,
    "qs:photos_sr":1,
    "qs:placetype":"LocalAdmin",
    "qs:pop_sr":"0",
    "wd:wordcount":638,
    "wof:name":"\u5854\u4ec0\u5e93\u5c14\u5e72\u5854\u5409\u514b\u81ea\u6cbb\u53bf",
    "wof:placetype":"localadmin"
},
  "geometry": {"coordinates":[75.219955,37.784305],"type":"Point"}
}