{
  "type": "Feature",
  "properties": {
    "gn:admin1_code":"12.0",
    "gn:asciiname":"Tielukeng",
    "gn:country_code":"CN",
    "gn:dem":388,
    "gn:feature_class":"P",
    "gn:feature_code":"PPL",
    "gn:name":"Tielukeng",
    "gn:population":0,
    "gn:timezone":"Asia/Shanghai",
    "iso:country":"CN",
    "name:zho_x_preferred":[
        "\u94c1\u7089\u5751"
    ],
    "wof:name":"Tielukeng",
    "wof:placetype":"locality"
},
  "geometry": {"coordinates":[110.92161000000002,32.4648],"type":"Point"}
}