{
  "type": "Feature",
  "properties": {
    "gn:admin1_code":"25.0",
    "gn:asciiname":"Guojiachahecun",
    "gn:country_code":"CN",
    "gn:dem":7,
    "gn:feature_class":"P",
    "gn:feature_code":"PPL",
    "gn:name":"Guojiachahecun",
    "gn:population":0,
    "gn:timezone":"Asia/Shanghai",
    "iso:country":"CN",
    "name:zho_x_preferred":[
        "\u90ed\u5bb6\u5c94\u6cb3\u6751"
    ],
    "wof:name":"Guojiachahecun",
    "wof:placetype":"locality"
},
  "geometry": {"coordinates":[119.40328,36.90464],"type":"Point"}
}