{
  "type": "Feature",
  "properties": {
    "gn:admin1_code":"15.0",
    "gn:asciiname":"Xuanwo",
    "gn:country_code":"CN",
    "gn:dem":2606,
    "gn:feature_class":"P",
    "gn:feature_code":"PPL",
    "gn:name":"Xuanwo",
    "gn:population":0,
    "gn:timezone":"Asia/Shanghai",
    "iso:country":"CN",
    "name:und_x_variant":[
        "\u6f29\u7a9d"
    ],
    "wof:name":"Xuanwo",
    "wof:placetype":"locality"
},
  "geometry": {"coordinates":[104.04691,34.25441],"type":"Point"}
}