{
  "type": "Feature",
  "properties": {
    "gn:admin1_code":"14.0",
    "gn:asciiname":"Nianbocun",
    "gn:country_code":"CN",
    "gn:dem":4524,
    "gn:feature_class":"P",
    "gn:feature_code":"PPL",
    "gn:name":"Nianbocun",
    "gn:population":0,
    "gn:timezone":"Asia/Urumqi",
    "iso:country":"CN",
    "name:zho_x_preferred":[
        "\u5ff5\u6ce2\u6751"
    ],
    "wof:name":"Nianbocun",
    "wof:placetype":"locality"
},
  "geometry": {"coordinates":[92.68337,31.27549],"type":"Point"}
}