{
  "type": "Feature",
  "properties": {
    "gn:admin1_code":"30.0",
    "gn:asciiname":"Baihuawei",
    "gn:country_code":"CN",
    "gn:dem":310,
    "gn:feature_class":"P",
    "gn:feature_code":"PPL",
    "gn:name":"Baihuawei",
    "gn:population":0,
    "gn:timezone":"Asia/Shanghai",
    "iso:country":"CN",
    "name:zho_x_preferred":[
        "Baihuawei"
    ],
    "name:zho_x_variant":[
        "\u767d\u82b1\u56f4"
    ],
    "wof:name":"Baihuawei",
    "wof:placetype":"locality"
},
  "geometry": {"coordinates":[113.26139000000001,25.17833],"type":"Point"}
}