{
  "type": "Feature",
  "properties": {
    "gn:admin1_code":"30.0",
    "gn:asciiname":"Baishuibiao",
    "gn:country_code":"CN",
    "gn:dem":393,
    "gn:feature_class":"P",
    "gn:feature_code":"PPL",
    "gn:name":"Baishuibiao",
    "gn:population":0,
    "gn:timezone":"Asia/Shanghai",
    "iso:country":"CN",
    "name:zho_x_preferred":[
        "Baishuibiao"
    ],
    "name:zho_x_variant":[
        "\u767d\u6c34\u8868"
    ],
    "wof:name":"Baishuibiao",
    "wof:placetype":"locality"
},
  "geometry": {"coordinates":[112.83861,23.74194],"type":"Point"}
}