{
  "type": "Feature",
  "properties": {
    "gn:admin1_code":"2.0",
    "gn:asciiname":"Dashi'ao",
    "gn:country_code":"CN",
    "gn:dem":7,
    "gn:feature_class":"P",
    "gn:feature_code":"PPL",
    "gn:name":"Dashi\u2019ao",
    "gn:population":0,
    "gn:timezone":"Asia/Shanghai",
    "iso:country":"CN",
    "name:und_x_variant":[
        "Dashi\u2019ao"
    ],
    "name:zho_x_preferred":[
        "\u5927\u4f7f\u5c99"
    ],
    "wof:name":"Dashi'ao",
    "wof:placetype":"locality"
},
  "geometry": {"coordinates":[122.27947,30.04347000000001],"type":"Point"}
}