{
  "type": "Feature",
  "properties": {
    "gn:admin1_code":"2.0",
    "gn:asciiname":"Lengshuikong",
    "gn:country_code":"CN",
    "gn:dem":193,
    "gn:feature_class":"P",
    "gn:feature_code":"PPL",
    "gn:name":"Lengshuikong",
    "gn:population":0,
    "gn:timezone":"Asia/Shanghai",
    "iso:country":"CN",
    "name:zho_x_preferred":[
        "\u51b7\u6c34\u5b54"
    ],
    "wof:name":"Lengshuikong",
    "wof:placetype":"locality"
},
  "geometry": {"coordinates":[120.86866999999999,29.36795],"type":"Point"}
}