{
  "type": "Feature",
  "properties": {
    "gn:admin1_code":"9.0",
    "gn:asciiname":"Gushi",
    "gn:country_code":"CN",
    "gn:dem":583,
    "gn:feature_class":"P",
    "gn:feature_code":"PPL",
    "gn:name":"Gushi",
    "gn:population":0,
    "gn:timezone":"Asia/Shanghai",
    "iso:country":"CN",
    "name:ceb_x_preferred":[
        "Gushi"
    ],
    "name:nld_x_preferred":[
        "Gushi"
    ],
    "name:und_x_variant":[
        "\u5b64\u77f3"
    ],
    "wof:name":"Gushi",
    "wof:placetype":"locality"
},
  "geometry": {"coordinates":[112.47452,33.95669],"type":"Point"}
}