{
  "type": "Feature",
  "properties": {
    "gn:admin1_code":"1.0",
    "gn:asciiname":"Jiuxianwancun",
    "gn:country_code":"CN",
    "gn:dem":17,
    "gn:feature_class":"P",
    "gn:feature_code":"PPL",
    "gn:name":"Jiuxianwancun",
    "gn:population":0,
    "gn:timezone":"Asia/Shanghai",
    "iso:country":"CN",
    "name:zho_x_preferred":[
        "\u65e7\u53bf\u6e7e\u6751"
    ],
    "wof:name":"Jiuxianwancun",
    "wof:placetype":"locality"
},
  "geometry": {"coordinates":[117.87985,33.13304],"type":"Point"}
}