{
  "type": "Feature",
  "properties": {
    "gn:admin1_code":"10",
    "gn:asciiname":"Qianmengting",
    "gn:country_code":"CN",
    "gn:dem":27,
    "gn:feature_class":"P",
    "gn:feature_code":"PPL",
    "gn:name":"Qianmengting",
    "gn:population":0,
    "gn:timezone":"Asia/Shanghai",
    "iso:country":"CN",
    "name:zho_x_preferred":[
        "\u524d\u5b5f\u753a"
    ],
    "wof:name":"Qianmengting",
    "wof:placetype":"locality"
},
  "geometry": {"coordinates":[116.03888999999999,37.42289],"type":"Point"}
}