{
  "type": "Feature",
  "properties": {
    "gn:admin1_code":"9",
    "gn:asciiname":"Yanjialou",
    "gn:country_code":"CN",
    "gn:dem":1090,
    "gn:feature_class":"P",
    "gn:feature_code":"PPL",
    "gn:name":"Yanjialou",
    "gn:population":0,
    "gn:timezone":"Asia/Shanghai",
    "iso:country":"CN",
    "name:zho_x_preferred":[
        "\u960e\u5bb6\u697c"
    ],
    "wof:name":"Yanjialou",
    "wof:placetype":"locality"
},
  "geometry": {"coordinates":[110.53018,34.26433],"type":"Point"}
}