{
  "type": "Feature",
  "properties": {
    "gn:admin1_code":"13",
    "gn:asciiname":"Yisantuan Silian",
    "gn:country_code":"CN",
    "gn:dem":1010,
    "gn:feature_class":"P",
    "gn:feature_code":"PPL",
    "gn:name":"Yisantuan Silian",
    "gn:population":0,
    "gn:timezone":"Asia/Shanghai",
    "iso:country":"CN",
    "name:und_x_variant":[
        "\u4e00\u4e09\u56e2\u56db\u8fde"
    ],
    "wof:name":"Yisantuan Silian",
    "wof:placetype":"locality"
},
  "geometry": {"coordinates":[81.44169000000002,40.6128],"type":"Point"}
}