{
  "type": "Feature",
  "properties": {
    "gn:admin1_code":"29.0",
    "gn:asciiname":"Zuojiazhai",
    "gn:country_code":"CN",
    "gn:dem":1690,
    "gn:feature_class":"P",
    "gn:feature_code":"PPL",
    "gn:name":"Zuojiazhai",
    "gn:population":0,
    "gn:timezone":"Asia/Shanghai",
    "iso:country":"CN",
    "name:zho_x_preferred":[
        "\u5de6\u5bb6\u5be8"
    ],
    "wof:name":"Zuojiazhai",
    "wof:placetype":"locality"
},
  "geometry": {"coordinates":[99.3616,23.8877],"type":"Point"}
}