{
  "type": "Feature",
  "properties": {
    "gn:admin1_code":"32.0",
    "gn:asciiname":"Wuni",
    "gn:country_code":"CN",
    "gn:dem":2398,
    "gn:feature_class":"P",
    "gn:feature_code":"PPL",
    "gn:name":"Wuni",
    "gn:population":0,
    "gn:timezone":"Asia/Shanghai",
    "iso:country":"CN",
    "name:zho_x_preferred":[
        "\u4e4c\u5c3c"
    ],
    "wof:name":"Wuni",
    "wof:placetype":"locality"
},
  "geometry": {"coordinates":[103.21455,28.06239],"type":"Point"}
}