{
  "type": "Feature",
  "properties": {
    "gn:admin1_code":"19.0",
    "gn:asciiname":"Botuozi",
    "gn:country_code":"CN",
    "gn:dem":63,
    "gn:feature_class":"P",
    "gn:feature_code":"PPL",
    "gn:name":"Botuozi",
    "gn:population":0,
    "gn:timezone":"Asia/Shanghai",
    "iso:country":"CN",
    "name:und_x_variant":[
        "\u8584\u5768\u5b50"
    ],
    "name:zho_x_preferred":[
        "\u8584\u5768\u5b50"
    ],
    "wof:name":"Botuozi",
    "wof:placetype":"locality"
},
  "geometry": {"coordinates":[122.88794,42.28424],"type":"Point"}
}