{
  "type": "Feature",
  "properties": {
    "gn:admin1_code":"19.0",
    "gn:asciiname":"Huashuyuan",
    "gn:country_code":"CN",
    "gn:dem":56,
    "gn:feature_class":"P",
    "gn:feature_code":"PPL",
    "gn:name":"Huashuyuan",
    "gn:population":0,
    "gn:timezone":"Asia/Shanghai",
    "iso:country":"CN",
    "name:zho_x_preferred":[
        "\u6866\u6811\u56ed"
    ],
    "wof:name":"Huashuyuan",
    "wof:placetype":"locality"
},
  "geometry": {"coordinates":[121.806,41.5839],"type":"Point"}
}