{
  "type": "Feature",
  "properties": {
    "gn:admin1_code":"33.0",
    "gn:asciiname":"Xianba",
    "gn:country_code":"CN",
    "gn:dem":514,
    "gn:feature_class":"P",
    "gn:feature_code":"PPL",
    "gn:name":"Xianba",
    "gn:population":0,
    "gn:timezone":"Asia/Shanghai",
    "iso:country":"CN",
    "name:zho_x_preferred":[
        "\u53bf\u575d"
    ],
    "wof:name":"Xianba",
    "wof:placetype":"locality"
},
  "geometry": {"coordinates":[108.85805999999999,29.57195],"type":"Point"}
}