{
  "type": "Feature",
  "properties": {
    "gn:admin1_code":"29",
    "gn:asciiname":"Lumingkou",
    "gn:country_code":"CN",
    "gn:dem":2206,
    "gn:feature_class":"P",
    "gn:feature_code":"PPL",
    "gn:name":"Lumingkou",
    "gn:population":0,
    "gn:timezone":"Asia/Shanghai",
    "iso:country":"CN",
    "name:zho_x_preferred":[
        "\u9e7f\u9e23\u53e3"
    ],
    "wof:name":"Lumingkou",
    "wof:placetype":"locality"
},
  "geometry": {"coordinates":[101.078,24.8724],"type":"Point"}
}