{
  "type": "Feature",
  "properties": {
    "gn:admin1_code":"23.0",
    "gn:asciiname":"Xujiatang",
    "gn:country_code":"CN",
    "gn:dem":6,
    "gn:feature_class":"P",
    "gn:feature_code":"PPL",
    "gn:name":"Xujiatang",
    "gn:population":0,
    "gn:timezone":"Asia/Shanghai",
    "iso:country":"CN",
    "name:und_x_variant":[
        "\u5f90\u5bb6\u5802"
    ],
    "wof:name":"Xujiatang",
    "wof:placetype":"locality"
},
  "geometry": {"coordinates":[121.56708,30.96347],"type":"Point"}
}