{
  "type": "Feature",
  "properties": {
    "gn:admin1_code":"30.0",
    "gn:asciiname":"Gaogangli",
    "gn:country_code":"CN",
    "gn:dem":27,
    "gn:feature_class":"P",
    "gn:feature_code":"PPL",
    "gn:name":"Gaogangli",
    "gn:population":0,
    "gn:timezone":"Asia/Shanghai",
    "iso:country":"CN",
    "name:zho_x_preferred":[
        "\u9ad8\u5c97\u91cc"
    ],
    "wof:name":"Gaogangli",
    "wof:placetype":"locality"
},
  "geometry": {"coordinates":[112.45944,22.22517],"type":"Point"}
}