{
  "type": "Feature",
  "properties": {
    "gn:admin1_code":"5.0",
    "gn:asciiname":"Huoliaoguigou",
    "gn:country_code":"CN",
    "gn:dem":356,
    "gn:feature_class":"P",
    "gn:feature_code":"PPL",
    "gn:name":"Huoliaoguigou",
    "gn:population":0,
    "gn:timezone":"Asia/Shanghai",
    "iso:country":"CN",
    "name:zho_x_preferred":[
        "\u706b\u71ce\u9b3c\u6c9f"
    ],
    "wof:name":"Huoliaoguigou",
    "wof:placetype":"locality"
},
  "geometry": {"coordinates":[125.16634000000001,42.7374],"type":"Point"}
}