{
  "type": "Feature",
  "properties": {
    "gn:admin1_code":"3.0",
    "gn:asciiname":"Hutian",
    "gn:country_code":"CN",
    "gn:dem":212,
    "gn:feature_class":"P",
    "gn:feature_code":"PPL",
    "gn:name":"Hutian",
    "gn:population":0,
    "gn:timezone":"Asia/Shanghai",
    "iso:country":"CN",
    "name:und_x_variant":[
        "\u6e56\u7530"
    ],
    "wof:name":"Hutian",
    "wof:placetype":"locality"
},
  "geometry": {"coordinates":[116.0437,26.47098],"type":"Point"}
}