{
  "type": "Feature",
  "properties": {
    "gn:admin1_code":"26.0",
    "gn:asciiname":"Liyuancun",
    "gn:country_code":"CN",
    "gn:dem":772,
    "gn:feature_class":"P",
    "gn:feature_code":"PPL",
    "gn:name":"Liyuancun",
    "gn:population":0,
    "gn:timezone":"Asia/Shanghai",
    "iso:country":"CN",
    "name:zho_x_preferred":[
        "\u68a8\u56ed\u6751"
    ],
    "wof:name":"Liyuancun",
    "wof:placetype":"locality"
},
  "geometry": {"coordinates":[110.64511,33.67808],"type":"Point"}
}