{
  "type": "Feature",
  "properties": {
    "gn:admin1_code":"3",
    "gn:asciiname":"Huxu",
    "gn:country_code":"CN",
    "gn:dem":48,
    "gn:feature_class":"P",
    "gn:feature_code":"PPLA4",
    "gn:name":"Huxu",
    "gn:population":0,
    "gn:timezone":"Asia/Shanghai",
    "iso:country":"CN",
    "name:und_x_variant":[
        "\u864e\u5729",
        "Huxu Xiang",
        "\u864e\u5729\u4e61"
    ],
    "wof:name":"Huxu",
    "wof:placetype":"locality"
},
  "geometry": {"coordinates":[116.57447999999999,28.17702],"type":"Point"}
}