{
  "type": "Feature",
  "properties": {
    "gn:admin1_code":"22.0",
    "gn:asciiname":"Liangjiayuan",
    "gn:country_code":"CN",
    "gn:dem":67,
    "gn:feature_class":"P",
    "gn:feature_code":"PPL",
    "gn:name":"Liangjiayuan",
    "gn:population":0,
    "gn:timezone":"Asia/Shanghai",
    "iso:country":"CN",
    "name:zho_x_preferred":[
        "\u6881\u5bb6\u56ed"
    ],
    "wof:name":"Liangjiayuan",
    "wof:placetype":"locality"
},
  "geometry": {"coordinates":[116.11178999999998,40.10882],"type":"Point"}
}