{
  "type": "Feature",
  "properties": {
    "gn:admin1_code":"29.0",
    "gn:asciiname":"Zhongluoduo",
    "gn:country_code":"CN",
    "gn:dem":1353,
    "gn:feature_class":"P",
    "gn:feature_code":"PPL",
    "gn:name":"Zhongluoduo",
    "gn:population":0,
    "gn:timezone":"Asia/Shanghai",
    "iso:country":"CN",
    "name:zho_x_preferred":[
        "\u4e2d\u502e\u6735"
    ],
    "wof:name":"Zhongluoduo",
    "wof:placetype":"locality"
},
  "geometry": {"coordinates":[104.014,23.5683],"type":"Point"}
}