{
  "type": "Feature",
  "properties": {
    "gn:admin1_code":"19.0",
    "gn:asciiname":"Xiaomizigou",
    "gn:country_code":"CN",
    "gn:dem":62,
    "gn:feature_class":"P",
    "gn:feature_code":"PPL",
    "gn:name":"Xiaomizigou",
    "gn:population":0,
    "gn:timezone":"Asia/Shanghai",
    "iso:country":"CN",
    "name:zho_x_preferred":[
        "\u5c0f\u7cdc\u5b50\u6c9f"
    ],
    "wof:name":"Xiaomizigou",
    "wof:placetype":"locality"
},
  "geometry": {"coordinates":[120.142,40.334],"type":"Point"}
}