{
  "type": "Feature",
  "properties": {
    "gn:admin1_code":"9.0",
    "gn:asciiname":"Dongqiaogang",
    "gn:country_code":"CN",
    "gn:dem":57,
    "gn:feature_class":"P",
    "gn:feature_code":"PPL",
    "gn:name":"Dongqiaogang",
    "gn:population":0,
    "gn:timezone":"Asia/Shanghai",
    "iso:country":"CN",
    "name:zho_x_preferred":[
        "\u8463\u6865\u5c97"
    ],
    "wof:name":"Dongqiaogang",
    "wof:placetype":"locality"
},
  "geometry": {"coordinates":[114.21512,33.79718],"type":"Point"}
}