{
  "type": "Feature",
  "properties": {
    "gn:admin1_code":"5.0",
    "gn:asciiname":"Tianhuofang",
    "gn:country_code":"CN",
    "gn:dem":201,
    "gn:feature_class":"P",
    "gn:feature_code":"PPL",
    "gn:name":"Tianhuofang",
    "gn:population":0,
    "gn:timezone":"Asia/Shanghai",
    "iso:country":"CN",
    "name:zho_x_preferred":[
        "\u7530\u4f19\u623f"
    ],
    "wof:name":"Tianhuofang",
    "wof:placetype":"locality"
},
  "geometry": {"coordinates":[124.43883,43.40986],"type":"Point"}
}