{
  "type": "Feature",
  "properties": {
    "gn:admin1_code":"11",
    "gn:asciiname":"Wanlichong",
    "gn:country_code":"CN",
    "gn:dem":195,
    "gn:feature_class":"P",
    "gn:feature_code":"PPL",
    "gn:name":"Wanlichong",
    "gn:population":0,
    "gn:timezone":"Asia/Shanghai",
    "iso:country":"CN",
    "name:zho_x_preferred":[
        "\u4e07\u91cc\u51b2"
    ],
    "wof:name":"Wanlichong",
    "wof:placetype":"locality"
},
  "geometry": {"coordinates":[111.24715999999999,26.30879],"type":"Point"}
}