{
  "type": "Feature",
  "properties": {
    "gn:admin1_code":"32.0",
    "gn:asciiname":"Jingziping",
    "gn:country_code":"CN",
    "gn:dem":623,
    "gn:feature_class":"P",
    "gn:feature_code":"PPL",
    "gn:name":"Jingziping",
    "gn:population":0,
    "gn:timezone":"Asia/Shanghai",
    "iso:country":"CN",
    "name:und_x_variant":[
        "\u4e95\u5b50\u576a"
    ],
    "wof:name":"Jingziping",
    "wof:placetype":"locality"
},
  "geometry": {"coordinates":[106.24760999999999,32.02798],"type":"Point"}
}