{
  "type": "Feature",
  "properties": {
    "gn:admin1_code":"9.0",
    "gn:asciiname":"Yanghuya",
    "gn:country_code":"CN",
    "gn:dem":825,
    "gn:feature_class":"P",
    "gn:feature_code":"PPL",
    "gn:name":"Yanghuya",
    "gn:population":0,
    "gn:timezone":"Asia/Shanghai",
    "iso:country":"CN",
    "name:zho_x_preferred":[
        "\u7f8a\u864e\u5d16"
    ],
    "wof:name":"Yanghuya",
    "wof:placetype":"locality"
},
  "geometry": {"coordinates":[111.86969000000001,34.86733],"type":"Point"}
}