{
  "type": "Feature",
  "properties": {
    "gn:admin1_code":"24.0",
    "gn:asciiname":"Shanqingyucun",
    "gn:country_code":"CN",
    "gn:dem":963,
    "gn:feature_class":"P",
    "gn:feature_code":"PPL",
    "gn:name":"Shanqingyucun",
    "gn:population":0,
    "gn:timezone":"Asia/Shanghai",
    "iso:country":"CN",
    "name:zho_x_preferred":[
        "\u5584\u5e86\u5cea\u6751"
    ],
    "wof:name":"Shanqingyucun",
    "wof:placetype":"locality"
},
  "geometry": {"coordinates":[110.97566,37.86361],"type":"Point"}
}