{
  "type": "Feature",
  "properties": {
    "gn:admin1_code":"2.0",
    "gn:asciiname":"Fengjialou",
    "gn:country_code":"CN",
    "gn:dem":118,
    "gn:feature_class":"P",
    "gn:feature_code":"PPL",
    "gn:name":"Fengjialou",
    "gn:population":0,
    "gn:timezone":"Asia/Shanghai",
    "iso:country":"CN",
    "name:zho_x_preferred":[
        "\u51af\u5bb6\u697c"
    ],
    "wof:name":"Fengjialou",
    "wof:placetype":"locality"
},
  "geometry": {"coordinates":[120.24899000000001,29.21521],"type":"Point"}
}