{
  "type": "Feature",
  "properties": {
    "gn:admin1_code":"13",
    "gn:asciiname":"Erlinglian",
    "gn:country_code":"CN",
    "gn:dem":1050,
    "gn:feature_class":"P",
    "gn:feature_code":"PPL",
    "gn:name":"Erlinglian",
    "gn:population":0,
    "gn:timezone":"Asia/Shanghai",
    "iso:country":"CN",
    "name:und_x_variant":[
        "\u4e8c\u96f6\u8fde"
    ],
    "wof:name":"Erlinglian",
    "wof:placetype":"locality"
},
  "geometry": {"coordinates":[80.13999,40.35928],"type":"Point"}
}