{
  "type": "Feature",
  "properties": {
    "gn:admin1_code":"3.0",
    "gn:asciiname":"Chajia",
    "gn:country_code":"CN",
    "gn:dem":189,
    "gn:feature_class":"P",
    "gn:feature_code":"PPL",
    "gn:name":"Chajia",
    "gn:population":0,
    "gn:timezone":"Asia/Shanghai",
    "iso:country":"CN",
    "name:und_x_variant":[
        "\u67e5\u5bb6"
    ],
    "wof:name":"Chajia",
    "wof:placetype":"locality"
},
  "geometry": {"coordinates":[114.4665,29.02151],"type":"Point"}
}