{
  "type": "Feature",
  "properties": {
    "gn:admin1_code":"7",
    "gn:asciiname":"Houkeng",
    "gn:country_code":"CN",
    "gn:dem":535,
    "gn:feature_class":"P",
    "gn:feature_code":"PPL",
    "gn:name":"Houkeng",
    "gn:population":0,
    "gn:timezone":"Asia/Shanghai",
    "iso:country":"CN",
    "name:zho_x_preferred":[
        "\u540e\u5751"
    ],
    "wof:name":"Houkeng",
    "wof:placetype":"locality"
},
  "geometry": {"coordinates":[117.79277999999999,24.93667],"type":"Point"}
}