{
  "type": "Feature",
  "properties": {
    "gn:admin1_code":"30",
    "gn:asciiname":"Shunao Linchang",
    "gn:country_code":"CN",
    "gn:dem":157,
    "gn:feature_class":"P",
    "gn:feature_code":"PPLF",
    "gn:name":"Shunao Linchang",
    "gn:population":0,
    "gn:timezone":"Asia/Shanghai",
    "iso:country":"CN",
    "name:zho_x_preferred":[
        "\u68b3\u8111\u6797\u573a"
    ],
    "wof:name":"Shunao Linchang",
    "wof:placetype":"locality"
},
  "geometry": {"coordinates":[113.90389,23.49167000000001],"type":"Point"}
}