{
  "type": "Feature",
  "properties": {
    "gn:admin1_code":"3.0",
    "gn:asciiname":"Lunyuanwu",
    "gn:country_code":"CN",
    "gn:dem":112,
    "gn:feature_class":"P",
    "gn:feature_code":"PPL",
    "gn:name":"Lunyuanwu",
    "gn:population":0,
    "gn:timezone":"Asia/Shanghai",
    "iso:country":"CN",
    "name:zho_x_preferred":[
        "\u8f6e\u6e90\u575e"
    ],
    "wof:name":"Lunyuanwu",
    "wof:placetype":"locality"
},
  "geometry": {"coordinates":[117.526,28.4754],"type":"Point"}
}