{
  "type": "Feature",
  "properties": {
    "gn:admin1_code":"30.0",
    "gn:asciiname":"Kuicheng",
    "gn:country_code":"CN",
    "gn:dem":208,
    "gn:feature_class":"P",
    "gn:feature_code":"PPL",
    "gn:name":"Kuicheng",
    "gn:population":0,
    "gn:timezone":"Asia/Shanghai",
    "iso:country":"CN",
    "name:und_x_variant":[
        "Tucheng"
    ],
    "name:zho_x_preferred":[
        "\u8475\u57d5"
    ],
    "name:zho_x_variant":[
        "\u8456\u7a0b"
    ],
    "wof:name":"Kuicheng",
    "wof:placetype":"locality"
},
  "geometry": {"coordinates":[116.66113,23.83181],"type":"Point"}
}