{
  "type": "Feature",
  "properties": {
    "gn:admin1_code":"9.0",
    "gn:asciiname":"Xichangqiaocun",
    "gn:country_code":"CN",
    "gn:dem":99,
    "gn:feature_class":"P",
    "gn:feature_code":"PPL",
    "gn:name":"Xichangqiaocun",
    "gn:population":0,
    "gn:timezone":"Asia/Shanghai",
    "iso:country":"CN",
    "name:und_x_variant":[
        "\u897f\u957f\u6865\u6751"
    ],
    "name:zho_x_preferred":[
        "\u897f\u957f\u6865\u6751"
    ],
    "wof:name":"Xichangqiaocun",
    "wof:placetype":"locality"
},
  "geometry": {"coordinates":[113.33492,33.94924],"type":"Point"}
}