{
  "type": "Feature",
  "properties": {
    "gn:admin1_code":"16.0",
    "gn:asciiname":"Weiyawai",
    "gn:country_code":"CN",
    "gn:dem":911,
    "gn:feature_class":"P",
    "gn:feature_code":"PPL",
    "gn:name":"Weiyawai",
    "gn:population":0,
    "gn:timezone":"Asia/Shanghai",
    "iso:country":"CN",
    "name:zho_x_preferred":[
        "\u5c3e\u7259\u6b6a"
    ],
    "wof:name":"Weiyawai",
    "wof:placetype":"locality"
},
  "geometry": {"coordinates":[105.035,24.8128],"type":"Point"}
}