{
  "type": "Feature",
  "properties": {
    "gn:admin1_code":"30.0",
    "gn:asciiname":"Xialiang",
    "gn:country_code":"CN",
    "gn:dem":16,
    "gn:feature_class":"P",
    "gn:feature_code":"PPL",
    "gn:name":"Xialiang",
    "gn:population":0,
    "gn:timezone":"Asia/Shanghai",
    "iso:country":"CN",
    "name:zho_x_preferred":[
        "\u4e0b\u826f"
    ],
    "wof:name":"Xialiang",
    "wof:placetype":"locality"
},
  "geometry": {"coordinates":[114.51143999999999,23.0941],"type":"Point"}
}