{
  "type": "Feature",
  "properties": {
    "gn:admin1_code":"05",
    "gn:asciiname":"Xinglongshan",
    "gn:cc2":"CN",
    "gn:country_code":"CN",
    "gn:dem":169,
    "gn:feature_class":"P",
    "gn:feature_code":"PPL",
    "gn:name":"Xinglongshan",
    "gn:population":0,
    "gn:timezone":"Asia/Shanghai",
    "iso:country":"CN",
    "name:und_x_variant":[
        "Hsing-lung-shan",
        "Xinglongshan"
    ],
    "wof:name":"Xinglongshan",
    "wof:placetype":"locality"
},
  "geometry": {"coordinates":[122.40000000000001,44.81667],"type":"Point"}
}