{
  "type": "Feature",
  "properties": {
    "gn:admin1_code":"10.0",
    "gn:asciiname":"Gaisupu",
    "gn:country_code":"CN",
    "gn:dem":10,
    "gn:feature_class":"P",
    "gn:feature_code":"PPL",
    "gn:name":"Gaisupu",
    "gn:population":0,
    "gn:timezone":"Asia/Shanghai",
    "iso:country":"CN",
    "name:zho_x_preferred":[
        "\u76d6\u5bbf\u94fa"
    ],
    "wof:name":"Gaisupu",
    "wof:placetype":"locality"
},
  "geometry": {"coordinates":[116.818,38.6408],"type":"Point"}
}