{
  "type": "Feature",
  "properties": {
    "gn:admin1_code":"3.0",
    "gn:asciiname":"Sugutang",
    "gn:country_code":"CN",
    "gn:dem":51,
    "gn:feature_class":"P",
    "gn:feature_code":"PPL",
    "gn:name":"Sugutang",
    "gn:population":0,
    "gn:timezone":"Asia/Shanghai",
    "iso:country":"CN",
    "name:und_x_variant":[
        "\u82cf\u59d1\u5858"
    ],
    "wof:name":"Sugutang",
    "wof:placetype":"locality"
},
  "geometry": {"coordinates":[115.46756999999999,28.76966],"type":"Point"}
}