{
  "type": "Feature",
  "properties": {
    "gn:admin1_code":"31.0",
    "gn:asciiname":"Lanpo",
    "gn:country_code":"CN",
    "gn:dem":3,
    "gn:feature_class":"P",
    "gn:feature_code":"PPL",
    "gn:name":"Lanpo",
    "gn:population":0,
    "gn:timezone":"Asia/Shanghai",
    "iso:country":"CN",
    "name:zho_x_preferred":[
        "Lanpo"
    ],
    "name:zho_x_variant":[
        "\u6984\u5761"
    ],
    "wof:name":"Lanpo",
    "wof:placetype":"locality"
},
  "geometry": {"coordinates":[110.69956999999999,20.05273],"type":"Point"}
}