{
  "type": "Feature",
  "properties": {
    "gn:admin1_code":"25",
    "gn:asciiname":"Lufang Dongcun",
    "gn:country_code":"CN",
    "gn:dem":35,
    "gn:feature_class":"P",
    "gn:feature_code":"PPL",
    "gn:name":"Lufang Dongcun",
    "gn:population":0,
    "gn:timezone":"Asia/Shanghai",
    "iso:country":"CN",
    "name:zho_x_preferred":[
        "\u9c81\u574a\u4e1c\u6751"
    ],
    "wof:name":"Lufang Dongcun",
    "wof:placetype":"locality"
},
  "geometry": {"coordinates":[117.962,34.7153],"type":"Point"}
}