{
  "type": "Feature",
  "properties": {
    "gn:admin1_code":"33.0",
    "gn:asciiname":"Xinsheng",
    "gn:country_code":"CN",
    "gn:dem":380,
    "gn:feature_class":"P",
    "gn:feature_code":"PPL",
    "gn:name":"Xinsheng",
    "gn:population":0,
    "gn:timezone":"Asia/Shanghai",
    "iso:country":"CN",
    "name:ceb_x_preferred":[
        "Xinsheng"
    ],
    "name:deu_x_preferred":[
        "Xinsheng"
    ],
    "name:swe_x_preferred":[
        "Xinsheng"
    ],
    "name:zho_x_preferred":[
        "\u65b0\u751f"
    ],
    "wof:name":"Xinsheng",
    "wof:placetype":"locality"
},
  "geometry": {"coordinates":[105.60137,29.54183],"type":"Point"}
}