{
  "type": "Feature",
  "properties": {
    "gn:admin1_code":"16.0",
    "gn:asciiname":"Tuoling",
    "gn:country_code":"CN",
    "gn:dem":131,
    "gn:feature_class":"P",
    "gn:feature_code":"PPL",
    "gn:name":"Tuoling",
    "gn:population":0,
    "gn:timezone":"Asia/Shanghai",
    "iso:country":"CN",
    "name:zho_x_preferred":[
        "\u9a6e\u96f6"
    ],
    "wof:name":"Tuoling",
    "wof:placetype":"locality"
},
  "geometry": {"coordinates":[107.444,22.124],"type":"Point"}
}