{
  "type": "Feature",
  "properties": {
    "gn:admin1_code":"32.0",
    "gn:asciiname":"Shucai",
    "gn:country_code":"CN",
    "gn:dem":387,
    "gn:feature_class":"P",
    "gn:feature_code":"PPL",
    "gn:name":"Shucai",
    "gn:population":0,
    "gn:timezone":"Asia/Shanghai",
    "iso:country":"CN",
    "name:zho_x_preferred":[
        "\u852c\u83dc"
    ],
    "wof:name":"Shucai",
    "wof:placetype":"locality"
},
  "geometry": {"coordinates":[106.06,31.3622],"type":"Point"}
}