{
  "type": "Feature",
  "properties": {
    "gn:admin1_code":"7",
    "gn:asciiname":"Puyang",
    "gn:country_code":"CN",
    "gn:dem":604,
    "gn:feature_class":"P",
    "gn:feature_code":"PPL",
    "gn:name":"Puyang",
    "gn:population":0,
    "gn:timezone":"Asia/Shanghai",
    "iso:country":"CN",
    "name:afr_x_preferred":[
        "Puyang"
    ],
    "name:ara_x_preferred":[
        "\u0628\u0648\u064a\u0627\u0646\u063a"
    ],
    "name:bul_x_preferred":[
        "\u041f\u0443\u044f\u043d"
    ],
    "name:cdo_x_preferred":[
        "B\u016dk-i\u00f2ng"
    ],
    "name:ces_x_preferred":[
        "Pchu-jang"
    ],
    "name:dan_x_preferred":[
        "Puyang"
    ],
    "name:deu_x_preferred":[
        "Puyang"
    ],
    "name:epo_x_preferred":[
        "Pujang"
    ],
    "name:eus_x_preferred":[
        "Puyang"
    ],
    "name:fas_x_preferred":[
        "\u067e\u0648\u06cc\u0627\u0646\u06af"
    ],
    "name:fin_x_preferred":[
        "Puyang"
    ],
    "name:fra_x_preferred":[
        "Puyang"
    ],
    "name:heb_x_preferred":[
        "\u05e4\u05d5\u05d9\u05d0\u05e0\u05d2"
    ],
    "name:hun_x_preferred":[
        "Puyang"
    ],
    "name:ita_x_preferred":[
        "Puyang"
    ],
    "name:jpn_x_preferred":[
        "\u6fee\u967d\u5e02"
    ],
    "name:kik_x_preferred":[
        "Puyang"
    ],
    "name:kor_x_preferred":[
        "\ud478\uc591\uc2dc"
    ],
    "name:mlg_x_preferred":[
        "Puyang"
    ],
    "name:nld_x_preferred":[
        "Puyang"
    ],
    "name:nno_x_preferred":[
        "Puyang"
    ],
    "name:nor_x_preferred":[
        "Puyang"
    ],
    "name:pam_x_preferred":[
        "Puyang"
    ],
    "name:pol_x_preferred":[
        "Puyang"
    ],
    "name:por_x_preferred":[
        "Puyang"
    ],
    "name:rus_x_preferred":[
        "\u041f\u0443\u044f\u043d"
    ],
    "name:spa_x_preferred":[
        "Puyang"
    ],
    "name:srp_x_preferred":[
        "\u041f\u0443\u0458\u0430\u043d\u0433"
    ],
    "name:swe_x_preferred":[
        "Puyang"
    ],
    "name:tur_x_preferred":[
        "Puyang"
    ],
    "name:ukr_x_preferred":[
        "\u041f\u0443\u044f\u043d"
    ],
    "name:und_x_variant":[
        "\u84b2\u6d0b"
    ],
    "name:urd_x_preferred":[
        "\u067e\u0648\u06cc\u0627\u0646\u06af"
    ],
    "name:vie_x_preferred":[
        "B\u1ed9c D\u01b0\u01a1ng"
    ],
    "name:war_x_preferred":[
        "Puyang"
    ],
    "name:zho_x_preferred":[
        "\u6fee\u9633\u5e02"
    ],
    "wof:name":"Puyang",
    "wof:placetype":"locality"
},
  "geometry": {"coordinates":[119.7525,27.17688],"type":"Point"}
}