{
  "type": "Feature",
  "properties": {
    "gn:admin1_code":"7",
    "gn:asciiname":"Puyang",
    "gn:country_code":"CN",
    "gn:dem":604,
    "gn:feature_class":"P",
    "gn:feature_code":"PPL",
    "gn:name":"Puyang",
    "gn:population":0,
    "gn:timezone":"Asia/Shanghai",
    "iso:country":"CN",
    "name:und_x_variant":[
        "\u84b2\u6d0b",
        "Puyang"
    ],
    "wof:name":"Puyang",
    "wof:placetype":"locality"
},
  "geometry": {"coordinates":[119.7525,27.17688],"type":"Point"}
}