{
  "type": "Feature",
  "properties": {
    "gn:admin1_code":"9.0",
    "gn:asciiname":"Xiaoyingcun",
    "gn:country_code":"CN",
    "gn:dem":121,
    "gn:feature_class":"P",
    "gn:feature_code":"PPL",
    "gn:name":"Xiaoyingcun",
    "gn:population":0,
    "gn:timezone":"Asia/Shanghai",
    "iso:country":"CN",
    "name:zho_x_preferred":[
        "\u8096\u8425\u6751"
    ],
    "wof:name":"Xiaoyingcun",
    "wof:placetype":"locality"
},
  "geometry": {"coordinates":[113.15302,33.60996],"type":"Point"}
}