{
  "type": "Feature",
  "properties": {
    "gn:admin1_code":"6.0",
    "gn:asciiname":"Minrongcai",
    "gn:country_code":"CN",
    "gn:dem":4497,
    "gn:feature_class":"P",
    "gn:feature_code":"PPL",
    "gn:name":"Minrongcai",
    "gn:population":0,
    "gn:timezone":"Asia/Urumqi",
    "iso:country":"CN",
    "name:zho_x_preferred":[
        "\u6c11\u8363\u91c7"
    ],
    "wof:name":"Minrongcai",
    "wof:placetype":"locality"
},
  "geometry": {"coordinates":[96.64685,32.16191],"type":"Point"}
}