{
  "type": "Feature",
  "properties": {
    "gn:admin1_code":"18",
    "gn:asciiname":"Wanlongpo",
    "gn:country_code":"CN",
    "gn:dem":1173,
    "gn:feature_class":"P",
    "gn:feature_code":"PPL",
    "gn:name":"Wanlongpo",
    "gn:population":0,
    "gn:timezone":"Asia/Shanghai",
    "iso:country":"CN",
    "name:zho_x_preferred":[
        "\u6e7e\u9f99\u5761"
    ],
    "wof:name":"Wanlongpo",
    "wof:placetype":"locality"
},
  "geometry": {"coordinates":[105.30500000000001,26.21],"type":"Point"}
}