{
  "type": "Feature",
  "properties": {
    "gn:admin1_code":"19.0",
    "gn:asciiname":"Qinghedongcun",
    "gn:country_code":"CN",
    "gn:dem":89,
    "gn:feature_class":"P",
    "gn:feature_code":"PPL",
    "gn:name":"Qinghedongcun",
    "gn:population":0,
    "gn:timezone":"Asia/Shanghai",
    "iso:country":"CN",
    "name:zho_x_preferred":[
        "\u6e05\u6cb3\u6d1e\u6751"
    ],
    "wof:name":"Qinghedongcun",
    "wof:placetype":"locality"
},
  "geometry": {"coordinates":[121.434,41.709],"type":"Point"}
}