{
  "type": "Feature",
  "properties": {
    "gn:admin1_code":"30.0",
    "gn:asciiname":"Jiusancun",
    "gn:country_code":"CN",
    "gn:dem":25,
    "gn:feature_class":"P",
    "gn:feature_code":"PPL",
    "gn:name":"Jiusancun",
    "gn:population":0,
    "gn:timezone":"Asia/Shanghai",
    "iso:country":"CN",
    "name:zho_x_preferred":[
        "\u4e5d\u4e09\u6751"
    ],
    "wof:name":"Jiusancun",
    "wof:placetype":"locality"
},
  "geometry": {"coordinates":[112.12173,22.06344],"type":"Point"}
}