{
  "type": "Feature",
  "properties": {
    "gn:admin1_code":"3.0",
    "gn:asciiname":"Shangluokeng",
    "gn:country_code":"CN",
    "gn:dem":110,
    "gn:feature_class":"P",
    "gn:feature_code":"PPL",
    "gn:name":"Shangluokeng",
    "gn:population":0,
    "gn:timezone":"Asia/Shanghai",
    "iso:country":"CN",
    "name:und_x_variant":[
        "\u4e0a\u7f57\u5751"
    ],
    "wof:name":"Shangluokeng",
    "wof:placetype":"locality"
},
  "geometry": {"coordinates":[115.03901,26.71502000000001],"type":"Point"}
}