{
  "type": "Feature",
  "properties": {
    "gn:admin1_code":"30",
    "gn:asciiname":"Luogang",
    "gn:country_code":"CN",
    "gn:dem":245,
    "gn:feature_class":"P",
    "gn:feature_code":"PPLA4",
    "gn:name":"Luogang",
    "gn:population":0,
    "gn:timezone":"Asia/Shanghai",
    "iso:country":"CN",
    "name:und_x_variant":[
        "Lo-kang",
        "Luogang",
        "Luogang Zhen",
        "\u87ba\u5c97\u9547"
    ],
    "name:zho_x_preferred":[
        "\u87ba\u5c97"
    ],
    "wof:name":"Luogang",
    "wof:placetype":"locality"
},
  "geometry": {"coordinates":[112.50951000000001,23.72988],"type":"Point"}
}