{
  "type": "Feature",
  "properties": {
    "gn:admin1_code":"5.0",
    "gn:asciiname":"Majiadian",
    "gn:country_code":"CN",
    "gn:dem":471,
    "gn:feature_class":"P",
    "gn:feature_code":"PPL",
    "gn:name":"Majiadian",
    "gn:population":0,
    "gn:timezone":"Asia/Shanghai",
    "iso:country":"CN",
    "name:ceb_x_preferred":[
        "Majiadian"
    ],
    "name:swe_x_preferred":[
        "Majiadian"
    ],
    "name:und_x_variant":[
        "\u9a6c\u5bb6\u5e97"
    ],
    "wof:name":"Majiadian",
    "wof:placetype":"locality"
},
  "geometry": {"coordinates":[126.85778000000001,42.80562000000001],"type":"Point"}
}