{
  "type": "Feature",
  "properties": {
    "gn:admin1_code":"3.0",
    "gn:asciiname":"Jinshan Yinbei",
    "gn:country_code":"CN",
    "gn:dem":508,
    "gn:feature_class":"P",
    "gn:feature_code":"PPL",
    "gn:name":"Jinshan Yinbei",
    "gn:population":0,
    "gn:timezone":"Asia/Shanghai",
    "iso:country":"CN",
    "name:und_x_variant":[
        "\u91d1\u5c71\u5370\u80cc"
    ],
    "wof:name":"Jinshan Yinbei",
    "wof:placetype":"locality"
},
  "geometry": {"coordinates":[115.30228,25.41946],"type":"Point"}
}