{
  "type": "Feature",
  "properties": {
    "gn:admin1_code":"11.0",
    "gn:asciiname":"Changshoushan",
    "gn:country_code":"CN",
    "gn:dem":340,
    "gn:feature_class":"P",
    "gn:feature_code":"PPL",
    "gn:name":"Changshoushan",
    "gn:population":0,
    "gn:timezone":"Asia/Shanghai",
    "iso:country":"CN",
    "name:zho_x_preferred":[
        "\u957f\u5bff\u5c71"
    ],
    "wof:name":"Changshoushan",
    "wof:placetype":"locality"
},
  "geometry": {"coordinates":[113.80519,28.1039],"type":"Point"}
}