{
  "type": "Feature",
  "properties": {
    "gn:admin1_code":"30.0",
    "gn:asciiname":"Shuanggang",
    "gn:country_code":"CN",
    "gn:dem":0,
    "gn:feature_class":"P",
    "gn:feature_code":"PPL",
    "gn:name":"Shuanggang",
    "gn:population":0,
    "gn:timezone":"Asia/Shanghai",
    "iso:country":"CN",
    "name:zho_x_preferred":[
        "\u96d9\u5d17"
    ],
    "wof:name":"Shuanggang",
    "wof:placetype":"locality"
},
  "geometry": {"coordinates":[113.47489,23.09403],"type":"Point"}
}