{
  "type": "Feature",
  "properties": {
    "gn:admin1_code":"31.0",
    "gn:asciiname":"Shiyuan",
    "gn:country_code":"CN",
    "gn:dem":48,
    "gn:feature_class":"P",
    "gn:feature_code":"PPL",
    "gn:name":"Shiyuan",
    "gn:population":0,
    "gn:timezone":"Asia/Shanghai",
    "iso:country":"CN",
    "name:zho_x_preferred":[
        "\u83b3\u56ed"
    ],
    "wof:name":"Shiyuan",
    "wof:placetype":"locality"
},
  "geometry": {"coordinates":[108.98862,19.49687],"type":"Point"}
}