{
  "type": "Feature",
  "properties": {
    "gn:admin1_code":"30.0",
    "gn:asciiname":"Dazhutang",
    "gn:country_code":"CN",
    "gn:dem":617,
    "gn:feature_class":"P",
    "gn:feature_code":"PPL",
    "gn:name":"Dazhutang",
    "gn:population":0,
    "gn:timezone":"Asia/Shanghai",
    "iso:country":"CN",
    "name:zho_x_preferred":[
        "Dazhutang"
    ],
    "name:zho_x_variant":[
        "\u5927\u7af9\u5858"
    ],
    "wof:name":"Dazhutang",
    "wof:placetype":"locality"
},
  "geometry": {"coordinates":[113.94722,25.23389],"type":"Point"}
}