{
  "type": "Feature",
  "properties": {
    "gn:admin1_code":"19.0",
    "gn:asciiname":"Raogou",
    "gn:country_code":"CN",
    "gn:dem":99,
    "gn:feature_class":"P",
    "gn:feature_code":"PPL",
    "gn:name":"Raogou",
    "gn:population":0,
    "gn:timezone":"Asia/Shanghai",
    "iso:country":"CN",
    "name:und_x_variant":[
        "\u7ed5\u6c9f"
    ],
    "wof:name":"Raogou",
    "wof:placetype":"locality"
},
  "geometry": {"coordinates":[123.95048,40.26077],"type":"Point"}
}