{
  "type": "Feature",
  "properties": {
    "gn:admin1_code":"32.0",
    "gn:asciiname":"Aojia",
    "gn:country_code":"CN",
    "gn:dem":375,
    "gn:feature_class":"P",
    "gn:feature_code":"PPL",
    "gn:name":"Aojia",
    "gn:population":0,
    "gn:timezone":"Asia/Shanghai",
    "iso:country":"CN",
    "name:zho_x_preferred":[
        "\u6556\u5bb6"
    ],
    "wof:name":"Aojia",
    "wof:placetype":"locality"
},
  "geometry": {"coordinates":[103.96016,29.42721],"type":"Point"}
}