{
  "type": "Feature",
  "properties": {
    "gn:admin1_code":"29.0",
    "gn:asciiname":"Pingtandi",
    "gn:country_code":"CN",
    "gn:dem":2130,
    "gn:feature_class":"P",
    "gn:feature_code":"PPL",
    "gn:name":"Pingtandi",
    "gn:population":0,
    "gn:timezone":"Asia/Shanghai",
    "iso:country":"CN",
    "name:zho_x_preferred":[
        "\u5e73\u5766\u5730"
    ],
    "wof:name":"Pingtandi",
    "wof:placetype":"locality"
},
  "geometry": {"coordinates":[99.87269999999999,24.9418],"type":"Point"}
}