{
  "type": "Feature",
  "properties": {
    "gn:admin1_code":"26.0",
    "gn:asciiname":"Zhaopancun",
    "gn:country_code":"CN",
    "gn:dem":1417,
    "gn:feature_class":"P",
    "gn:feature_code":"PPL",
    "gn:name":"Zhaopancun",
    "gn:population":0,
    "gn:timezone":"Asia/Shanghai",
    "iso:country":"CN",
    "name:zho_x_preferred":[
        "\u8d75\u7554\u6751"
    ],
    "wof:name":"Zhaopancun",
    "wof:placetype":"locality"
},
  "geometry": {"coordinates":[108.21679,36.62412],"type":"Point"}
}