{
  "type": "Feature",
  "properties": {
    "gn:admin1_code":"29.0",
    "gn:asciiname":"Tangbu",
    "gn:country_code":"CN",
    "gn:dem":3309,
    "gn:feature_class":"P",
    "gn:feature_code":"PPL",
    "gn:name":"Tangbu",
    "gn:population":0,
    "gn:timezone":"Asia/Shanghai",
    "iso:country":"CN",
    "name:zho_x_preferred":[
        "\u5858\u5e03"
    ],
    "wof:name":"Tangbu",
    "wof:placetype":"locality"
},
  "geometry": {"coordinates":[99.7458,27.847],"type":"Point"}
}