{
  "type": "Feature",
  "properties": {
    "gn:admin1_code":"5.0",
    "gn:asciiname":"Houxia Sandao",
    "gn:country_code":"CN",
    "gn:dem":169,
    "gn:feature_class":"P",
    "gn:feature_code":"PPL",
    "gn:name":"Houxia Sandao",
    "gn:population":0,
    "gn:timezone":"Asia/Shanghai",
    "iso:country":"CN",
    "name:zho_x_preferred":[
        "\u540e\u4e0b\u4e09\u9053"
    ],
    "wof:name":"Houxia Sandao",
    "wof:placetype":"locality"
},
  "geometry": {"coordinates":[126.83777000000001,45.03308],"type":"Point"}
}