{
  "type": "Feature",
  "properties": {
    "gn:admin1_code":"32.0",
    "gn:asciiname":"Liangzishang",
    "gn:country_code":"CN",
    "gn:dem":2643,
    "gn:feature_class":"P",
    "gn:feature_code":"PPL",
    "gn:name":"Liangzishang",
    "gn:population":0,
    "gn:timezone":"Asia/Shanghai",
    "iso:country":"CN",
    "name:zho_x_preferred":[
        "\u6881\u5b50\u4e0a"
    ],
    "wof:name":"Liangzishang",
    "wof:placetype":"locality"
},
  "geometry": {"coordinates":[103.117,31.6814],"type":"Point"}
}