{
  "type": "Feature",
  "properties": {
    "gn:admin1_code":"33.0",
    "gn:asciiname":"Dingmu",
    "gn:country_code":"CN",
    "gn:dem":1290,
    "gn:feature_class":"P",
    "gn:feature_code":"PPL",
    "gn:name":"Dingmu",
    "gn:population":0,
    "gn:timezone":"Asia/Shanghai",
    "iso:country":"CN",
    "name:zho_x_preferred":[
        "\u4e01\u6728"
    ],
    "wof:name":"Dingmu",
    "wof:placetype":"locality"
},
  "geometry": {"coordinates":[107.96016000000002,29.11034],"type":"Point"}
}