{
  "type": "Feature",
  "properties": {
    "gn:admin1_code":"10.0",
    "gn:asciiname":"Guojiawu",
    "gn:country_code":"CN",
    "gn:dem":42,
    "gn:feature_class":"P",
    "gn:feature_code":"PPL",
    "gn:name":"Guojiawu",
    "gn:population":0,
    "gn:timezone":"Asia/Shanghai",
    "iso:country":"CN",
    "name:zho_x_preferred":[
        "\u56fd\u5bb6\u52a1"
    ],
    "wof:name":"Guojiawu",
    "wof:placetype":"locality"
},
  "geometry": {"coordinates":[115.93346,39.37589000000001],"type":"Point"}
}