{
  "type": "Feature",
  "properties": {
    "gn:admin1_code":"24.0",
    "gn:asciiname":"Youfangyaocun",
    "gn:country_code":"CN",
    "gn:dem":1120,
    "gn:feature_class":"P",
    "gn:feature_code":"PPL",
    "gn:name":"Youfangyaocun",
    "gn:population":0,
    "gn:timezone":"Asia/Shanghai",
    "iso:country":"CN",
    "name:zho_x_preferred":[
        "\u6cb9\u623f\u7a91\u6751"
    ],
    "wof:name":"Youfangyaocun",
    "wof:placetype":"locality"
},
  "geometry": {"coordinates":[114.10636,40.32549],"type":"Point"}
}