{
  "type": "Feature",
  "properties": {
    "gn:admin1_code":"12.0",
    "gn:asciiname":"Hekoudian",
    "gn:country_code":"CN",
    "gn:dem":163,
    "gn:feature_class":"P",
    "gn:feature_code":"PPL",
    "gn:name":"Hekoudian",
    "gn:population":0,
    "gn:timezone":"Asia/Shanghai",
    "iso:country":"CN",
    "name:zho_x_preferred":[
        "\u6cb3\u53e3\u5e97"
    ],
    "wof:name":"Hekoudian",
    "wof:placetype":"locality"
},
  "geometry": {"coordinates":[110.80119999999999,32.80563],"type":"Point"}
}