{
  "type": "Feature",
  "properties": {
    "gn:admin1_code":"11.0",
    "gn:asciiname":"Aoyutang",
    "gn:country_code":"CN",
    "gn:dem":55,
    "gn:feature_class":"P",
    "gn:feature_code":"PPL",
    "gn:name":"Aoyutang",
    "gn:population":0,
    "gn:timezone":"Asia/Shanghai",
    "iso:country":"CN",
    "name:zho_x_preferred":[
        "\u9ccc\u9c7c\u5858"
    ],
    "wof:name":"Aoyutang",
    "wof:placetype":"locality"
},
  "geometry": {"coordinates":[113.10446,28.31644],"type":"Point"}
}