{
  "type": "Feature",
  "properties": {
    "gn:admin1_code":"14.0",
    "gn:asciiname":"Qinmaduo",
    "gn:country_code":"CN",
    "gn:dem":2935,
    "gn:feature_class":"P",
    "gn:feature_code":"PPL",
    "gn:name":"Qinmaduo",
    "gn:population":0,
    "gn:timezone":"Asia/Urumqi",
    "iso:country":"CN",
    "name:zho_x_preferred":[
        "\u52e4\u9a6c\u591a"
    ],
    "wof:name":"Qinmaduo",
    "wof:placetype":"locality"
},
  "geometry": {"coordinates":[94.19033,29.20363],"type":"Point"}
}