{
  "type": "Feature",
  "properties": {
    "gn:admin1_code":"30.0",
    "gn:asciiname":"Rujing",
    "gn:country_code":"CN",
    "gn:dem":310,
    "gn:feature_class":"P",
    "gn:feature_code":"PPL",
    "gn:name":"Rujing",
    "gn:population":0,
    "gn:timezone":"Asia/Shanghai",
    "iso:country":"CN",
    "name:fas_x_preferred":[
        "\u0631\u0648\u062c\u06cc\u0646\u06af"
    ],
    "name:fra_x_preferred":[
        "Rujing"
    ],
    "name:jpn_x_preferred":[
        "\u5929\u7ae5\u5982\u6d44"
    ],
    "name:pol_x_preferred":[
        "Tiantong Rujing"
    ],
    "name:zho_x_preferred":[
        "\u5112\u5f84"
    ],
    "wof:name":"Rujing",
    "wof:placetype":"locality"
},
  "geometry": {"coordinates":[115.26378,23.93348],"type":"Point"}
}