{
  "type": "Feature",
  "properties": {
    "gn:admin1_code":"30.0",
    "gn:asciiname":"Rujing",
    "gn:country_code":"CN",
    "gn:dem":310,
    "gn:feature_class":"P",
    "gn:feature_code":"PPL",
    "gn:name":"Rujing",
    "gn:population":0,
    "gn:timezone":"Asia/Shanghai",
    "iso:country":"CN",
    "name:und_x_variant":[
        "\u5112\u5f84"
    ],
    "name:zho_x_preferred":[
        "\u5112\u5f84"
    ],
    "wof:name":"Rujing",
    "wof:placetype":"locality"
},
  "geometry": {"coordinates":[115.26378,23.93348],"type":"Point"}
}