{
  "type": "Feature",
  "properties": {
    "gn:admin1_code":"32.0",
    "gn:asciiname":"Cebianwan",
    "gn:country_code":"CN",
    "gn:dem":411,
    "gn:feature_class":"P",
    "gn:feature_code":"PPL",
    "gn:name":"Cebianwan",
    "gn:population":0,
    "gn:timezone":"Asia/Shanghai",
    "iso:country":"CN",
    "name:zho_x_preferred":[
        "\u4fa7\u8fb9\u6e7e"
    ],
    "wof:name":"Cebianwan",
    "wof:placetype":"locality"
},
  "geometry": {"coordinates":[104.56399999999999,30.1287],"type":"Point"}
}