{
  "type": "Feature",
  "properties": {
    "gn:admin1_code":"3.0",
    "gn:asciiname":"Shixi Zoujia",
    "gn:country_code":"CN",
    "gn:dem":41,
    "gn:feature_class":"P",
    "gn:feature_code":"PPL",
    "gn:name":"Shixi Zoujia",
    "gn:population":0,
    "gn:timezone":"Asia/Shanghai",
    "iso:country":"CN",
    "name:zho_x_preferred":[
        "\u77f3\u6eaa\u90b9\u5bb6"
    ],
    "wof:name":"Shixi Zoujia",
    "wof:placetype":"locality"
},
  "geometry": {"coordinates":[115.337,28.2952],"type":"Point"}
}