{
  "type": "Feature",
  "properties": {
    "gn:admin1_code":"33.0",
    "gn:asciiname":"Niuchang",
    "gn:country_code":"CN",
    "gn:dem":516,
    "gn:feature_class":"P",
    "gn:feature_code":"PPLF",
    "gn:name":"Niuchang",
    "gn:population":0,
    "gn:timezone":"Asia/Shanghai",
    "iso:country":"CN",
    "name:zho_x_preferred":[
        "\u725b\u573a"
    ],
    "wof:name":"Niuchang",
    "wof:placetype":"locality"
},
  "geometry": {"coordinates":[109.11169,28.43965],"type":"Point"}
}