{
  "type": "Feature",
  "properties": {
    "gn:admin1_code":"16.0",
    "gn:asciiname":"Yacaigen",
    "gn:country_code":"CN",
    "gn:dem":70,
    "gn:feature_class":"P",
    "gn:feature_code":"PPL",
    "gn:name":"Yacaigen",
    "gn:population":0,
    "gn:timezone":"Asia/Shanghai",
    "iso:country":"CN",
    "name:zho_x_preferred":[
        "\u4e9a\u83dc\u6839"
    ],
    "wof:name":"Yacaigen",
    "wof:placetype":"locality"
},
  "geometry": {"coordinates":[109.107,22.1545],"type":"Point"}
}