{
  "type": "Feature",
  "properties": {
    "gn:admin1_code":"32.0",
    "gn:asciiname":"Dubai",
    "gn:country_code":"CN",
    "gn:dem":2454,
    "gn:feature_class":"P",
    "gn:feature_code":"PPL",
    "gn:name":"Dubai",
    "gn:population":0,
    "gn:timezone":"Asia/Shanghai",
    "iso:country":"CN",
    "name:zho_x_preferred":[
        "\u675c\u67cf"
    ],
    "wof:name":"Dubai",
    "wof:placetype":"locality"
},
  "geometry": {"coordinates":[101.252,28.7539],"type":"Point"}
}