{
  "type": "Feature",
  "properties": {
    "gn:admin1_code":"21.0",
    "gn:asciiname":"Haoziwan Zhongzhuang",
    "gn:country_code":"CN",
    "gn:dem":2057,
    "gn:feature_class":"P",
    "gn:feature_code":"PPL",
    "gn:name":"Haoziwan Zhongzhuang",
    "gn:population":0,
    "gn:timezone":"Asia/Shanghai",
    "iso:country":"CN",
    "name:zho_x_preferred":[
        "\u84bf\u5b50\u6e7e\u4e2d\u5e84"
    ],
    "wof:name":"Haoziwan Zhongzhuang",
    "wof:placetype":"locality"
},
  "geometry": {"coordinates":[105.57056,35.99707],"type":"Point"}
}