{
  "type": "Feature",
  "properties": {
    "gn:admin1_code":"4.0",
    "gn:asciiname":"Wuzhuangcun",
    "gn:country_code":"CN",
    "gn:dem":2,
    "gn:feature_class":"P",
    "gn:feature_code":"PPL",
    "gn:name":"Wuzhuangcun",
    "gn:population":0,
    "gn:timezone":"Asia/Shanghai",
    "iso:country":"CN",
    "name:zho_x_preferred":[
        "\u6b66\u5e84\u6751"
    ],
    "wof:name":"Wuzhuangcun",
    "wof:placetype":"locality"
},
  "geometry": {"coordinates":[119.34166999999999,34.13348],"type":"Point"}
}