{
  "type": "Feature",
  "properties": {
    "gn:admin1_code":"18",
    "gn:asciiname":"Dalukou",
    "gn:country_code":"CN",
    "gn:dem":1279,
    "gn:feature_class":"P",
    "gn:feature_code":"PPL",
    "gn:name":"Dalukou",
    "gn:population":0,
    "gn:timezone":"Asia/Shanghai",
    "iso:country":"CN",
    "name:zho_x_preferred":[
        "\u5927\u8def\u53e3"
    ],
    "wof:name":"Dalukou",
    "wof:placetype":"locality"
},
  "geometry": {"coordinates":[106.116,26.6275],"type":"Point"}
}