{
  "type": "Feature",
  "properties": {
    "gn:admin1_code":"32",
    "gn:asciiname":"Shigu",
    "gn:country_code":"CN",
    "gn:dem":1539,
    "gn:feature_class":"P",
    "gn:feature_code":"PPL",
    "gn:name":"Shigu",
    "gn:population":0,
    "gn:timezone":"Asia/Shanghai",
    "iso:country":"CN",
    "name:ceb_x_preferred":[
        "Shigu"
    ],
    "name:deu_x_preferred":[
        "Shigu"
    ],
    "name:und_x_variant":[
        "Shih-ku",
        "Shigu"
    ],
    "name:zho_x_preferred":[
        "\u77f3\u9f13"
    ],
    "wof:name":"Shigu",
    "wof:placetype":"locality"
},
  "geometry": {"coordinates":[103.76411,31.60505],"type":"Point"}
}