{
  "type": "Feature",
  "properties": {
    "gn:admin1_code":"29.0",
    "gn:asciiname":"Huangteng",
    "gn:country_code":"CN",
    "gn:dem":1820,
    "gn:feature_class":"P",
    "gn:feature_code":"PPL",
    "gn:name":"Huangteng",
    "gn:population":0,
    "gn:timezone":"Asia/Shanghai",
    "iso:country":"CN",
    "name:zho_x_preferred":[
        "\u9ec4\u85e4"
    ],
    "wof:name":"Huangteng",
    "wof:placetype":"locality"
},
  "geometry": {"coordinates":[100.03,23.091],"type":"Point"}
}