{
  "type": "Feature",
  "properties": {
    "gn:admin1_code":"11.0",
    "gn:asciiname":"Wudutan",
    "gn:country_code":"CN",
    "gn:dem":304,
    "gn:feature_class":"P",
    "gn:feature_code":"PPL",
    "gn:name":"Wudutan",
    "gn:population":0,
    "gn:timezone":"Asia/Shanghai",
    "iso:country":"CN",
    "name:zho_x_preferred":[
        "\u4e94\u6e21\u6f6d"
    ],
    "wof:name":"Wudutan",
    "wof:placetype":"locality"
},
  "geometry": {"coordinates":[110.02518000000001,29.44261],"type":"Point"}
}