{
  "type": "Feature",
  "properties": {
    "gn:admin1_code":"24",
    "gn:asciiname":"Xi'ao",
    "gn:country_code":"CN",
    "gn:dem":1358,
    "gn:feature_class":"P",
    "gn:feature_code":"PPL",
    "gn:name":"Xi\u2019ao",
    "gn:population":0,
    "gn:timezone":"Asia/Shanghai",
    "iso:country":"CN",
    "wof:name":"Xi'ao",
    "wof:placetype":"locality"
},
  "geometry": {"coordinates":[111.02583,35.98860999999999],"type":"Point"}
}