{
  "type": "Feature",
  "properties": {
    "gn:admin1_code":"16",
    "gn:asciiname":"Shashuping",
    "gn:country_code":"CN",
    "gn:dem":221,
    "gn:feature_class":"P",
    "gn:feature_code":"PPL",
    "gn:name":"Shashuping",
    "gn:population":0,
    "gn:timezone":"Asia/Shanghai",
    "iso:country":"CN",
    "name:zho_x_preferred":[
        "\u6749\u6811\u576a"
    ],
    "wof:name":"Shashuping",
    "wof:placetype":"locality"
},
  "geometry": {"coordinates":[110.386,25.5745],"type":"Point"}
}