{
  "type": "Feature",
  "properties": {
    "gn:admin1_code":"4.0",
    "gn:asciiname":"Xiaogaojiaxia",
    "gn:country_code":"CN",
    "gn:dem":3,
    "gn:feature_class":"P",
    "gn:feature_code":"PPL",
    "gn:name":"Xiaogaojiaxia",
    "gn:population":0,
    "gn:timezone":"Asia/Shanghai",
    "iso:country":"CN",
    "name:zho_x_preferred":[
        "\u5c0f\u9ad8\u5bb6\u53a6"
    ],
    "wof:name":"Xiaogaojiaxia",
    "wof:placetype":"locality"
},
  "geometry": {"coordinates":[119.62882999999999,32.82788],"type":"Point"}
}