{
  "type": "Feature",
  "properties": {
    "gn:admin1_code":"16.0",
    "gn:asciiname":"Qilong",
    "gn:country_code":"CN",
    "gn:dem":135,
    "gn:feature_class":"P",
    "gn:feature_code":"PPL",
    "gn:name":"Qilong",
    "gn:population":0,
    "gn:timezone":"Asia/Shanghai",
    "iso:country":"CN",
    "name:ceb_x_preferred":[
        "Qilong"
    ],
    "name:deu_x_preferred":[
        "Qilong"
    ],
    "name:swe_x_preferred":[
        "Qilong"
    ],
    "name:zho_x_preferred":[
        "\u5176\u9f99"
    ],
    "wof:name":"Qilong",
    "wof:placetype":"locality"
},
  "geometry": {"coordinates":[107.682,21.7044],"type":"Point"}
}