{
  "type": "Feature",
  "properties": {
    "gn:admin1_code":"26.0",
    "gn:asciiname":"Xiafengjiabu",
    "gn:country_code":"CN",
    "gn:dem":566,
    "gn:feature_class":"P",
    "gn:feature_code":"PPL",
    "gn:name":"Xiafengjiabu",
    "gn:population":0,
    "gn:timezone":"Asia/Shanghai",
    "iso:country":"CN",
    "name:und_x_variant":[
        "\u4e0b\u51af\u5bb6\u5821"
    ],
    "wof:name":"Xiafengjiabu",
    "wof:placetype":"locality"
},
  "geometry": {"coordinates":[107.88836000000001,34.16329],"type":"Point"}
}