{
  "type": "Feature",
  "properties": {
    "gn:admin1_code":"9.0",
    "gn:asciiname":"Longhutan",
    "gn:country_code":"CN",
    "gn:dem":128,
    "gn:feature_class":"P",
    "gn:feature_code":"PPL",
    "gn:name":"Longhutan",
    "gn:population":0,
    "gn:timezone":"Asia/Shanghai",
    "iso:country":"CN",
    "name:zho_x_preferred":[
        "\u9f99\u864e\u6ee9"
    ],
    "wof:name":"Longhutan",
    "wof:placetype":"locality"
},
  "geometry": {"coordinates":[112.63035000000001,34.71168],"type":"Point"}
}