{
  "type": "Feature",
  "properties": {
    "gn:admin1_code":"16.0",
    "gn:asciiname":"Gute",
    "gn:country_code":"CN",
    "gn:dem":285,
    "gn:feature_class":"P",
    "gn:feature_code":"PPL",
    "gn:name":"Gute",
    "gn:population":0,
    "gn:timezone":"Asia/Shanghai",
    "iso:country":"CN",
    "name:deu_x_preferred":[
        "Gute"
    ],
    "name:fin_x_preferred":[
        "Gute"
    ],
    "name:fra_x_preferred":[
        "Gute"
    ],
    "name:swe_x_preferred":[
        "Gute"
    ],
    "name:zho_x_preferred":[
        "\u53e4\u7279"
    ],
    "wof:name":"Gute",
    "wof:placetype":"locality"
},
  "geometry": {"coordinates":[111.331,22.9947],"type":"Point"}
}