{
  "type": "Feature",
  "properties": {
    "gn:admin1_code":"05",
    "gn:asciiname":"Hanjiutongzi",
    "gn:country_code":"CN",
    "gn:dem":232,
    "gn:feature_class":"P",
    "gn:feature_code":"PPL",
    "gn:name":"Hanjiutongzi",
    "gn:population":0,
    "gn:timezone":"Asia/Shanghai",
    "iso:country":"CN",
    "wof:name":"Hanjiutongzi",
    "wof:placetype":"locality"
},
  "geometry": {"coordinates":[125.21028,43.74028],"type":"Point"}
}