{
  "type": "Feature",
  "properties": {
    "gn:admin1_code":"15.0",
    "gn:asciiname":"Keya",
    "gn:country_code":"CN",
    "gn:dem":1983,
    "gn:feature_class":"P",
    "gn:feature_code":"PPL",
    "gn:name":"Keya",
    "gn:population":0,
    "gn:timezone":"Asia/Shanghai",
    "iso:country":"CN",
    "name:zho_x_preferred":[
        "\u79d1\u5d16"
    ],
    "wof:name":"Keya",
    "wof:placetype":"locality"
},
  "geometry": {"coordinates":[104.4928,33.99697],"type":"Point"}
}