{
  "type": "Feature",
  "properties": {
    "gn:admin1_code":"1.0",
    "gn:asciiname":"Qilidian",
    "gn:country_code":"CN",
    "gn:dem":51,
    "gn:feature_class":"P",
    "gn:feature_code":"PPL",
    "gn:name":"Qilidian",
    "gn:population":0,
    "gn:timezone":"Asia/Shanghai",
    "iso:country":"CN",
    "name:zho_x_preferred":[
        "Qilidian"
    ],
    "name:zho_x_variant":[
        "\u4e03\u91cc\u5e97"
    ],
    "wof:name":"Qilidian",
    "wof:placetype":"locality"
},
  "geometry": {"coordinates":[119.38898,30.87057],"type":"Point"}
}