{
  "type": "Feature",
  "properties": {
    "gn:admin1_code":"8.0",
    "gn:asciiname":"Chengyicun",
    "gn:country_code":"CN",
    "gn:dem":62,
    "gn:feature_class":"P",
    "gn:feature_code":"PPL",
    "gn:name":"Chengyicun",
    "gn:population":0,
    "gn:timezone":"Asia/Shanghai",
    "iso:country":"CN",
    "name:zho_x_preferred":[
        "\u8bda\u4e49\u6751"
    ],
    "wof:name":"Chengyicun",
    "wof:placetype":"locality"
},
  "geometry": {"coordinates":[132.10911999999999,47.15469],"type":"Point"}
}