{
  "type": "Feature",
  "properties": {
    "gn:admin1_code":"2.0",
    "gn:asciiname":"Dishantou",
    "gn:country_code":"CN",
    "gn:dem":615,
    "gn:feature_class":"P",
    "gn:feature_code":"PPL",
    "gn:name":"Dishantou",
    "gn:population":0,
    "gn:timezone":"Asia/Shanghai",
    "iso:country":"CN",
    "name:zho_x_preferred":[
        "\u5e95\u5c71\u5934"
    ],
    "wof:name":"Dishantou",
    "wof:placetype":"locality"
},
  "geometry": {"coordinates":[120.00742,28.78004],"type":"Point"}
}