{
  "type": "Feature",
  "properties": {
    "gn:admin1_code":"14.0",
    "gn:asciiname":"Cigulongcun",
    "gn:country_code":"CN",
    "gn:dem":4579,
    "gn:feature_class":"P",
    "gn:feature_code":"PPL",
    "gn:name":"Cigulongcun",
    "gn:population":0,
    "gn:timezone":"Asia/Urumqi",
    "iso:country":"CN",
    "name:zho_x_preferred":[
        "\u6b21\u53e4\u9f99\u6751"
    ],
    "wof:name":"Cigulongcun",
    "wof:placetype":"locality"
},
  "geometry": {"coordinates":[90.91467,28.82134000000001],"type":"Point"}
}