{
  "type": "Feature",
  "properties": {
    "gn:admin1_code":"30.0",
    "gn:asciiname":"Modaokeng",
    "gn:country_code":"CN",
    "gn:dem":454,
    "gn:feature_class":"P",
    "gn:feature_code":"PPL",
    "gn:name":"Modaokeng",
    "gn:population":0,
    "gn:timezone":"Asia/Urumqi",
    "iso:country":"CN",
    "name:zho_x_preferred":[
        "\u78e8\u5200\u5751"
    ],
    "wof:name":"Modaokeng",
    "wof:placetype":"locality"
},
  "geometry": {"coordinates":[111.39936000000002,22.44773],"type":"Point"}
}