{
  "type": "Feature",
  "properties": {
    "gn:admin1_code":"7.0",
    "gn:asciiname":"Cuodou",
    "gn:country_code":"CN",
    "gn:dem":450,
    "gn:feature_class":"P",
    "gn:feature_code":"PPL",
    "gn:name":"Cuodou",
    "gn:population":0,
    "gn:timezone":"Asia/Shanghai",
    "iso:country":"CN",
    "name:zho_x_preferred":[
        "\u539d\u6597"
    ],
    "wof:name":"Cuodou",
    "wof:placetype":"locality"
},
  "geometry": {"coordinates":[118.66215,25.1275],"type":"Point"}
}