{
  "type": "Feature",
  "properties": {
    "gn:admin1_code":"26.0",
    "gn:asciiname":"Xiaoguojiaba",
    "gn:country_code":"CN",
    "gn:dem":993,
    "gn:feature_class":"P",
    "gn:feature_code":"PPL",
    "gn:name":"Xiaoguojiaba",
    "gn:population":0,
    "gn:timezone":"Asia/Shanghai",
    "iso:country":"CN",
    "name:und_x_variant":[
        "\u5c0f\u90ed\u5bb6\u575d"
    ],
    "wof:name":"Xiaoguojiaba",
    "wof:placetype":"locality"
},
  "geometry": {"coordinates":[105.96243,33.29989],"type":"Point"}
}