{
  "type": "Feature",
  "properties": {
    "gn:admin1_code":"29.0",
    "gn:asciiname":"Sifangshi",
    "gn:country_code":"CN",
    "gn:dem":1097,
    "gn:feature_class":"P",
    "gn:feature_code":"PPL",
    "gn:name":"Sifangshi",
    "gn:population":0,
    "gn:timezone":"Asia/Shanghai",
    "iso:country":"CN",
    "name:zho_x_preferred":[
        "\u56db\u65b9\u77f3"
    ],
    "wof:name":"Sifangshi",
    "wof:placetype":"locality"
},
  "geometry": {"coordinates":[103.88500000000001,27.8589],"type":"Point"}
}