{
  "type": "Feature",
  "properties": {
    "gn:admin1_code":"13",
    "gn:asciiname":"Wutangsayi",
    "gn:country_code":"CN",
    "gn:dem":1544,
    "gn:feature_class":"P",
    "gn:feature_code":"PPL",
    "gn:name":"Wutangsayi",
    "gn:population":0,
    "gn:timezone":"Asia/Urumqi",
    "iso:country":"CN",
    "name:zho_x_preferred":[
        "\u4e4c\u5802\u8428\u4f9d"
    ],
    "wof:name":"Wutangsayi",
    "wof:placetype":"locality"
},
  "geometry": {"coordinates":[87.3961,41.38252],"type":"Point"}
}