{
  "type": "Feature",
  "properties": {
    "gn:admin1_code":"8.0",
    "gn:asciiname":"Dapuchang",
    "gn:country_code":"CN",
    "gn:dem":415,
    "gn:feature_class":"P",
    "gn:feature_code":"PPL",
    "gn:name":"Dapuchang",
    "gn:population":0,
    "gn:timezone":"Asia/Shanghai",
    "iso:country":"CN",
    "name:zho_x_preferred":[
        "\u5927\u8461\u573a"
    ],
    "wof:name":"Dapuchang",
    "wof:placetype":"locality"
},
  "geometry": {"coordinates":[126.10760000000001,49.59367],"type":"Point"}
}