{
  "type": "Feature",
  "properties": {
    "gn:admin1_code":"12.0",
    "gn:asciiname":"Houchenjiaying",
    "gn:country_code":"CN",
    "gn:dem":73,
    "gn:feature_class":"P",
    "gn:feature_code":"PPL",
    "gn:name":"Houchenjiaying",
    "gn:population":0,
    "gn:timezone":"Asia/Shanghai",
    "iso:country":"CN",
    "name:zho_x_preferred":[
        "\u540e\u9648\u5bb6\u8425"
    ],
    "wof:name":"Houchenjiaying",
    "wof:placetype":"locality"
},
  "geometry": {"coordinates":[112.13624,32.06583],"type":"Point"}
}