{
  "type": "Feature",
  "properties": {
    "gn:admin1_code":"1.0",
    "gn:asciiname":"Xiaozhangwancun",
    "gn:country_code":"CN",
    "gn:dem":32,
    "gn:feature_class":"P",
    "gn:feature_code":"PPL",
    "gn:name":"Xiaozhangwancun",
    "gn:population":0,
    "gn:timezone":"Asia/Shanghai",
    "iso:country":"CN",
    "name:zho_x_preferred":[
        "\u5c0f\u5f20\u6e7e\u6751"
    ],
    "wof:name":"Xiaozhangwancun",
    "wof:placetype":"locality"
},
  "geometry": {"coordinates":[115.30575,32.58307],"type":"Point"}
}