{
  "type": "Feature",
  "properties": {
    "gn:admin1_code":"19.0",
    "gn:asciiname":"Dingguantuo",
    "gn:country_code":"CN",
    "gn:dem":8,
    "gn:feature_class":"P",
    "gn:feature_code":"PPL",
    "gn:name":"Dingguantuo",
    "gn:population":0,
    "gn:timezone":"Asia/Shanghai",
    "iso:country":"CN",
    "name:zho_x_preferred":[
        "\u4e01\u7ba1\u5768"
    ],
    "wof:name":"Dingguantuo",
    "wof:placetype":"locality"
},
  "geometry": {"coordinates":[122.821,41.2519],"type":"Point"}
}