{
  "type": "Feature",
  "properties": {
    "gn:admin1_code":"29.0",
    "gn:asciiname":"Songqu",
    "gn:country_code":"CN",
    "gn:dem":2057,
    "gn:feature_class":"P",
    "gn:feature_code":"PPL",
    "gn:name":"Songqu",
    "gn:population":0,
    "gn:timezone":"Asia/Shanghai",
    "iso:country":"CN",
    "name:zho_x_preferred":[
        "\u677e\u66f2"
    ],
    "wof:name":"Songqu",
    "wof:placetype":"locality"
},
  "geometry": {"coordinates":[99.39,26.2457],"type":"Point"}
}