{
  "type": "Feature",
  "properties": {
    "gn:admin1_code":"3.0",
    "gn:asciiname":"Shangwuzi",
    "gn:country_code":"CN",
    "gn:dem":232,
    "gn:feature_class":"P",
    "gn:feature_code":"PPL",
    "gn:name":"Shangwuzi",
    "gn:population":0,
    "gn:timezone":"Asia/Shanghai",
    "iso:country":"CN",
    "name:und_x_variant":[
        "\u4e0a\u5c4b\u5b50"
    ],
    "wof:name":"Shangwuzi",
    "wof:placetype":"locality"
},
  "geometry": {"coordinates":[115.21382,26.37558],"type":"Point"}
}