{
  "type": "Feature",
  "properties": {
    "gn:admin1_code":"20.0",
    "gn:asciiname":"Wadi",
    "gn:country_code":"CN",
    "gn:dem":369,
    "gn:feature_class":"P",
    "gn:feature_code":"PPLA4",
    "gn:name":"Wadi",
    "gn:population":0,
    "gn:timezone":"Asia/Shanghai",
    "iso:country":"CN",
    "name:und_x_variant":[
        "Wadi Xiang"
    ],
    "name:zho_x_preferred":[
        "\u6d3c\u5824"
    ],
    "name:zho_x_variant":[
        "\u6d3c\u5824\u4e61"
    ],
    "wof:name":"Wadi",
    "wof:placetype":"locality"
},
  "geometry": {"coordinates":[122.18803,47.2726],"type":"Point"}
}