{
  "type": "Feature",
  "properties": {
    "gn:admin1_code":"18",
    "gn:asciiname":"Kuzhuzhai",
    "gn:country_code":"CN",
    "gn:dem":969,
    "gn:feature_class":"P",
    "gn:feature_code":"PPL",
    "gn:name":"Kuzhuzhai",
    "gn:population":0,
    "gn:timezone":"Asia/Shanghai",
    "iso:country":"CN",
    "name:zho_x_preferred":[
        "\u82e6\u7af9\u5be8"
    ],
    "wof:name":"Kuzhuzhai",
    "wof:placetype":"locality"
},
  "geometry": {"coordinates":[107.101,26.0697],"type":"Point"}
}