{
  "type": "Feature",
  "properties": {
    "gn:admin1_code":"8.0",
    "gn:asciiname":"Xinqiangcun",
    "gn:country_code":"CN",
    "gn:dem":180,
    "gn:feature_class":"P",
    "gn:feature_code":"PPL",
    "gn:name":"Xinqiangcun",
    "gn:population":0,
    "gn:timezone":"Asia/Shanghai",
    "iso:country":"CN",
    "name:zho_x_preferred":[
        "\u65b0\u5f3a\u6751"
    ],
    "wof:name":"Xinqiangcun",
    "wof:placetype":"locality"
},
  "geometry": {"coordinates":[126.48203999999998,45.5226],"type":"Point"}
}