{
  "type": "Feature",
  "properties": {
    "gn:admin1_code":"9.0",
    "gn:asciiname":"Lufen",
    "gn:country_code":"CN",
    "gn:dem":187,
    "gn:feature_class":"P",
    "gn:feature_code":"PPL",
    "gn:name":"L\u00fcfen",
    "gn:population":0,
    "gn:timezone":"Asia/Shanghai",
    "iso:country":"CN",
    "name:und_x_variant":[
        "L\u00fcfen"
    ],
    "name:zho_x_preferred":[
        "\u5415\u575f"
    ],
    "wof:name":"Lufen",
    "wof:placetype":"locality"
},
  "geometry": {"coordinates":[113.25879,33.05323],"type":"Point"}
}