{
  "type": "Feature",
  "properties": {
    "gn:admin1_code":"32.0",
    "gn:asciiname":"Wenjiatun",
    "gn:country_code":"CN",
    "gn:dem":1673,
    "gn:feature_class":"P",
    "gn:feature_code":"PPL",
    "gn:name":"Wenjiatun",
    "gn:population":0,
    "gn:timezone":"Asia/Shanghai",
    "iso:country":"CN",
    "name:zho_x_preferred":[
        "\u6587\u5bb6\u5c6f"
    ],
    "wof:name":"Wenjiatun",
    "wof:placetype":"locality"
},
  "geometry": {"coordinates":[102.169,28.3951],"type":"Point"}
}