{
  "type": "Feature",
  "properties": {
    "gn:admin1_code":"4.0",
    "gn:asciiname":"Maocaozhuang",
    "gn:country_code":"CN",
    "gn:dem":56,
    "gn:feature_class":"P",
    "gn:feature_code":"PPL",
    "gn:name":"Maocaozhuang",
    "gn:population":0,
    "gn:timezone":"Asia/Shanghai",
    "iso:country":"CN",
    "name:zho_x_preferred":[
        "\u8305\u8349\u5e84"
    ],
    "wof:name":"Maocaozhuang",
    "wof:placetype":"locality"
},
  "geometry": {"coordinates":[119.10151999999999,32.4616],"type":"Point"}
}