{
  "type": "Feature",
  "properties": {
    "gn:admin1_code":"31.0",
    "gn:asciiname":"Gaomo",
    "gn:country_code":"CN",
    "gn:dem":92,
    "gn:feature_class":"P",
    "gn:feature_code":"PPL",
    "gn:name":"Gaomo",
    "gn:population":0,
    "gn:timezone":"Asia/Shanghai",
    "iso:country":"CN",
    "name:zho_x_preferred":[
        "\u9ad8\u58a8"
    ],
    "wof:name":"Gaomo",
    "wof:placetype":"locality"
},
  "geometry": {"coordinates":[110.64442,19.52605],"type":"Point"}
}