{
  "type": "Feature",
  "properties": {
    "gn:admin1_code":"3.0",
    "gn:asciiname":"Yujiaqiao",
    "gn:country_code":"CN",
    "gn:dem":27,
    "gn:feature_class":"P",
    "gn:feature_code":"PPL",
    "gn:name":"Yujiaqiao",
    "gn:population":0,
    "gn:timezone":"Asia/Shanghai",
    "iso:country":"CN",
    "name:und_x_variant":[
        "\u4f59\u5bb6\u6865"
    ],
    "wof:name":"Yujiaqiao",
    "wof:placetype":"locality"
},
  "geometry": {"coordinates":[116.90006,29.35144],"type":"Point"}
}