{
  "type": "Feature",
  "properties": {
    "gn:admin1_code":"19.0",
    "gn:asciiname":"Gangyao",
    "gn:country_code":"CN",
    "gn:dem":135,
    "gn:feature_class":"P",
    "gn:feature_code":"PPL",
    "gn:name":"Gangyao",
    "gn:population":0,
    "gn:timezone":"Asia/Shanghai",
    "iso:country":"CN",
    "name:zho_x_preferred":[
        "\u7f38\u7a91"
    ],
    "wof:name":"Gangyao",
    "wof:placetype":"locality"
},
  "geometry": {"coordinates":[120.60176,40.8263],"type":"Point"}
}