{
  "type": "Feature",
  "properties": {
    "gn:admin1_code":"3",
    "gn:asciiname":"Wannianshan",
    "gn:country_code":"CN",
    "gn:dem":396,
    "gn:feature_class":"P",
    "gn:feature_code":"PPL",
    "gn:name":"Wannianshan",
    "gn:population":0,
    "gn:timezone":"Asia/Shanghai",
    "iso:country":"CN",
    "name:zho_x_preferred":[
        "\u4e07\u5e74\u5c71"
    ],
    "wof:name":"Wannianshan",
    "wof:placetype":"locality"
},
  "geometry": {"coordinates":[114.202,26.8262],"type":"Point"}
}