{
  "type": "Feature",
  "properties": {
    "gn:admin1_code":"19.0",
    "gn:asciiname":"Daoliuhezicun",
    "gn:country_code":"CN",
    "gn:dem":96,
    "gn:feature_class":"P",
    "gn:feature_code":"PPL",
    "gn:name":"Daoliuhezicun",
    "gn:population":0,
    "gn:timezone":"Asia/Shanghai",
    "iso:country":"CN",
    "name:zho_x_preferred":[
        "\u5012\u6d41\u6cb3\u5b50\u6751"
    ],
    "wof:name":"Daoliuhezicun",
    "wof:placetype":"locality"
},
  "geometry": {"coordinates":[120.73099999999999,40.9926],"type":"Point"}
}