{
  "type": "Feature",
  "properties": {
    "gn:admin1_code":"19.0",
    "gn:asciiname":"Gaocheng Wobu",
    "gn:country_code":"CN",
    "gn:dem":66,
    "gn:feature_class":"P",
    "gn:feature_code":"PPL",
    "gn:name":"Gaocheng Wobu",
    "gn:population":0,
    "gn:timezone":"Asia/Shanghai",
    "iso:country":"CN",
    "name:zho_x_preferred":[
        "\u9ad8\u6210\u7a9d\u5821"
    ],
    "wof:name":"Gaocheng Wobu",
    "wof:placetype":"locality"
},
  "geometry": {"coordinates":[122.958,42.4483],"type":"Point"}
}