{
  "type": "Feature",
  "properties": {
    "gn:admin1_code":"19.0",
    "gn:asciiname":"Suzhangzi",
    "gn:country_code":"CN",
    "gn:dem":298,
    "gn:feature_class":"P",
    "gn:feature_code":"PPL",
    "gn:name":"Suzhangzi",
    "gn:population":0,
    "gn:timezone":"Asia/Shanghai",
    "iso:country":"CN",
    "name:zho_x_preferred":[
        "\u82cf\u6756\u5b50"
    ],
    "wof:name":"Suzhangzi",
    "wof:placetype":"locality"
},
  "geometry": {"coordinates":[120.54058000000001,41.00381],"type":"Point"}
}