{
  "type": "Feature",
  "properties": {
    "gn:admin1_code":"20.0",
    "gn:asciiname":"Dongcha",
    "gn:country_code":"CN",
    "gn:dem":1339,
    "gn:feature_class":"P",
    "gn:feature_code":"PPL",
    "gn:name":"Dongcha",
    "gn:population":0,
    "gn:timezone":"Asia/Shanghai",
    "iso:country":"CN",
    "name:und_x_variant":[
        "\u4e1c\u5c94"
    ],
    "wof:name":"Dongcha",
    "wof:placetype":"locality"
},
  "geometry": {"coordinates":[111.54056,39.80828],"type":"Point"}
}