{
  "type": "Feature",
  "properties": {
    "gn:admin1_code":"11",
    "gn:asciiname":"Tongchongcha",
    "gn:country_code":"CN",
    "gn:dem":508,
    "gn:feature_class":"P",
    "gn:feature_code":"PPL",
    "gn:name":"Tongchongcha",
    "gn:population":0,
    "gn:timezone":"Asia/Shanghai",
    "iso:country":"CN",
    "name:zho_x_preferred":[
        "\u6850\u51b2\u5c94"
    ],
    "wof:name":"Tongchongcha",
    "wof:placetype":"locality"
},
  "geometry": {"coordinates":[111.81328999999999,25.0439],"type":"Point"}
}