{
  "type": "Feature",
  "properties": {
    "gn:admin1_code":"28",
    "gn:asciiname":"Yingpanquan",
    "gn:country_code":"CN",
    "gn:dem":3,
    "gn:feature_class":"P",
    "gn:feature_code":"PPL",
    "gn:name":"Yingpanquan",
    "gn:population":0,
    "gn:timezone":"Asia/Shanghai",
    "iso:country":"CN",
    "name:zho_x_preferred":[
        "\u8425\u76d8\u5708"
    ],
    "wof:name":"Yingpanquan",
    "wof:placetype":"locality"
},
  "geometry": {"coordinates":[117.47898000000001,38.93842],"type":"Point"}
}