{
  "type": "Feature",
  "properties": {
    "gn:admin1_code":"4.0",
    "gn:asciiname":"Song'an",
    "gn:country_code":"CN",
    "gn:dem":42,
    "gn:feature_class":"P",
    "gn:feature_code":"PPL",
    "gn:name":"Song\u2019an",
    "gn:population":0,
    "gn:timezone":"Asia/Shanghai",
    "iso:country":"CN",
    "name:und_x_variant":[
        "Song\u2019an"
    ],
    "name:zho_x_preferred":[
        "\u5b8b\u5eb5"
    ],
    "wof:name":"Song'an",
    "wof:placetype":"locality"
},
  "geometry": {"coordinates":[116.752,34.7115],"type":"Point"}
}