{
  "type": "Feature",
  "properties": {
    "gn:admin1_code":"03",
    "gn:asciiname":"Huaqiao",
    "gn:country_code":"CN",
    "gn:dem":87,
    "gn:feature_class":"P",
    "gn:feature_code":"PPLA4",
    "gn:name":"Huaqiao",
    "gn:population":0,
    "gn:timezone":"Asia/Shanghai",
    "iso:country":"CN",
    "name:ceb_x_preferred":[
        "Huaqiao"
    ],
    "name:deu_x_preferred":[
        "Huaqiao"
    ],
    "name:swe_x_preferred":[
        "Huaqiao"
    ],
    "name:und_x_variant":[
        "Hua-ch\u2019iao",
        "\u82b1\u6865",
        "Huaqiao Xiang",
        "\u82b1\u6865\u4e61"
    ],
    "wof:name":"Huaqiao",
    "wof:placetype":"locality"
},
  "geometry": {"coordinates":[114.95941000000001,28.53491],"type":"Point"}
}