{
  "type": "Feature",
  "properties": {
    "gn:admin1_code":"29.0",
    "gn:asciiname":"Gouyitou",
    "gn:country_code":"CN",
    "gn:dem":2268,
    "gn:feature_class":"P",
    "gn:feature_code":"PPL",
    "gn:name":"Gouyitou",
    "gn:population":0,
    "gn:timezone":"Asia/Shanghai",
    "iso:country":"CN",
    "name:zho_x_preferred":[
        "\u6c9f\u8fe4\u5934"
    ],
    "wof:name":"Gouyitou",
    "wof:placetype":"locality"
},
  "geometry": {"coordinates":[100.76300000000001,24.3649],"type":"Point"}
}