{
  "type": "Feature",
  "properties": {
    "gn:admin1_code":"02",
    "gn:asciiname":"Huangshi'ao",
    "gn:country_code":"CN",
    "gn:dem":26,
    "gn:feature_class":"P",
    "gn:feature_code":"PPL",
    "gn:name":"Huangshi\u2019ao",
    "gn:population":0,
    "gn:timezone":"Asia/Shanghai",
    "iso:country":"CN",
    "name:und_x_variant":[
        "Huang-shan-ao",
        "Huangshi\u2019ao"
    ],
    "wof:name":"Huangshi'ao",
    "wof:placetype":"locality"
},
  "geometry": {"coordinates":[121.51111000000002,29.45194],"type":"Point"}
}