{
  "type": "Feature",
  "properties": {
    "gn:admin1_code":"29.0",
    "gn:asciiname":"Chenjiazhai",
    "gn:country_code":"CN",
    "gn:dem":1801,
    "gn:feature_class":"P",
    "gn:feature_code":"PPL",
    "gn:name":"Chenjiazhai",
    "gn:population":0,
    "gn:timezone":"Asia/Shanghai",
    "iso:country":"CN",
    "name:zho_x_preferred":[
        "\u9648\u5bb6\u5be8"
    ],
    "wof:name":"Chenjiazhai",
    "wof:placetype":"locality"
},
  "geometry": {"coordinates":[99.79859999999999,24.2942],"type":"Point"}
}