{
  "type": "Feature",
  "properties": {
    "gn:admin1_code":"24.0",
    "gn:asciiname":"Xiaonangou",
    "gn:country_code":"CN",
    "gn:dem":1169,
    "gn:feature_class":"P",
    "gn:feature_code":"PPL",
    "gn:name":"Xiaonangou",
    "gn:population":0,
    "gn:timezone":"Asia/Shanghai",
    "iso:country":"CN",
    "name:zho_x_preferred":[
        "\u5c0f\u5357\u6c9f"
    ],
    "wof:name":"Xiaonangou",
    "wof:placetype":"locality"
},
  "geometry": {"coordinates":[110.96613000000001,36.03133],"type":"Point"}
}