{
  "type": "Feature",
  "properties": {
    "gn:admin1_code":"29",
    "gn:asciiname":"Tianguanchang",
    "gn:country_code":"CN",
    "gn:dem":1219,
    "gn:feature_class":"P",
    "gn:feature_code":"PPL",
    "gn:name":"Tianguanchang",
    "gn:population":0,
    "gn:timezone":"Asia/Shanghai",
    "iso:country":"CN",
    "name:zho_x_preferred":[
        "\u6dfb\u5b98\u5382"
    ],
    "wof:name":"Tianguanchang",
    "wof:placetype":"locality"
},
  "geometry": {"coordinates":[101.44499999999999,24.4375],"type":"Point"}
}