{
  "type": "Feature",
  "properties": {
    "gn:admin1_code":"9.0",
    "gn:asciiname":"Xihuangzhuang",
    "gn:country_code":"CN",
    "gn:dem":168,
    "gn:feature_class":"P",
    "gn:feature_code":"PPL",
    "gn:name":"Xihuangzhuang",
    "gn:population":0,
    "gn:timezone":"Asia/Shanghai",
    "iso:country":"CN",
    "name:zho_x_preferred":[
        "\u897f\u9ec4\u5e84"
    ],
    "wof:name":"Xihuangzhuang",
    "wof:placetype":"locality"
},
  "geometry": {"coordinates":[113.38573,32.42225999999999],"type":"Point"}
}