{
  "type": "Feature",
  "properties": {
    "gn:admin1_code":"32.0",
    "gn:asciiname":"Zuoga",
    "gn:country_code":"CN",
    "gn:dem":2089,
    "gn:feature_class":"P",
    "gn:feature_code":"PPL",
    "gn:name":"Zuoga",
    "gn:population":0,
    "gn:timezone":"Asia/Shanghai",
    "iso:country":"CN",
    "name:zho_x_preferred":[
        "\u4f5c\u560e"
    ],
    "wof:name":"Zuoga",
    "wof:placetype":"locality"
},
  "geometry": {"coordinates":[102.467,28.4899],"type":"Point"}
}