{
  "type": "Feature",
  "properties": {
    "gn:admin1_code":"8.0",
    "gn:asciiname":"Hongguang Gongduan",
    "gn:country_code":"CN",
    "gn:dem":431,
    "gn:feature_class":"P",
    "gn:feature_code":"PPLF",
    "gn:name":"Hongguang Gongduan",
    "gn:population":0,
    "gn:timezone":"Asia/Shanghai",
    "iso:country":"CN",
    "name:zho_x_preferred":[
        "\u7ea2\u5149\u5de5\u6bb5"
    ],
    "wof:name":"Hongguang Gongduan",
    "wof:placetype":"locality"
},
  "geometry": {"coordinates":[127.60980000000001,48.17969],"type":"Point"}
}