{
  "type": "Feature",
  "properties": {
    "gn:admin1_code":"12.0",
    "gn:asciiname":"Heliu",
    "gn:country_code":"CN",
    "gn:dem":35,
    "gn:feature_class":"P",
    "gn:feature_code":"PPL",
    "gn:name":"Heliu",
    "gn:population":0,
    "gn:timezone":"Asia/Shanghai",
    "iso:country":"CN",
    "name:ceb_x_preferred":[
        "Heliu"
    ],
    "name:swe_x_preferred":[
        "Heliu"
    ],
    "name:und_x_variant":[
        "\u6cb3\u5218"
    ],
    "wof:name":"Heliu",
    "wof:placetype":"locality"
},
  "geometry": {"coordinates":[114.48336,30.53372],"type":"Point"}
}