{
  "type": "Feature",
  "properties": {
    "gn:admin1_code":"26.0",
    "gn:asciiname":"Xigonghecun",
    "gn:country_code":"CN",
    "gn:dem":791,
    "gn:feature_class":"P",
    "gn:feature_code":"PPL",
    "gn:name":"Xigonghecun",
    "gn:population":0,
    "gn:timezone":"Asia/Shanghai",
    "iso:country":"CN",
    "name:und_x_variant":[
        "\u897f\u5bab\u6cb3\u6751"
    ],
    "wof:name":"Xigonghecun",
    "wof:placetype":"locality"
},
  "geometry": {"coordinates":[107.13664,33.42849],"type":"Point"}
}