{
  "type": "Feature",
  "properties": {
    "gn:admin1_code":"20.0",
    "gn:asciiname":"Houwanzi",
    "gn:country_code":"CN",
    "gn:dem":1610,
    "gn:feature_class":"P",
    "gn:feature_code":"PPL",
    "gn:name":"Houwanzi",
    "gn:population":0,
    "gn:timezone":"Asia/Shanghai",
    "iso:country":"CN",
    "name:und_x_variant":[
        "\u540e\u6e7e\u5b50"
    ],
    "wof:name":"Houwanzi",
    "wof:placetype":"locality"
},
  "geometry": {"coordinates":[111.9119,39.79039],"type":"Point"}
}