{
  "type": "Feature",
  "properties": {
    "gn:admin1_code":"29",
    "gn:asciiname":"Laoliujia",
    "gn:country_code":"CN",
    "gn:dem":1895,
    "gn:feature_class":"P",
    "gn:feature_code":"PPL",
    "gn:name":"Laoliujia",
    "gn:population":0,
    "gn:timezone":"Asia/Shanghai",
    "iso:country":"CN",
    "name:zho_x_preferred":[
        "\u8001\u5218\u5bb6"
    ],
    "wof:name":"Laoliujia",
    "wof:placetype":"locality"
},
  "geometry": {"coordinates":[101.376,24.5459],"type":"Point"}
}