{
  "type": "Feature",
  "properties": {
    "gn:admin1_code":"26",
    "gn:asciiname":"Shiliping",
    "gn:cc2":"CN",
    "gn:country_code":"CN",
    "gn:dem":762,
    "gn:feature_class":"P",
    "gn:feature_code":"PPL",
    "gn:name":"Shiliping",
    "gn:population":0,
    "gn:timezone":"Asia/Shanghai",
    "iso:country":"CN",
    "name:und_x_variant":[
        "Shih-li-p\u2019ing",
        "Shiliping"
    ],
    "wof:name":"Shiliping",
    "wof:placetype":"locality"
},
  "geometry": {"coordinates":[110.25,36.08333],"type":"Point"}
}