{
  "type": "Feature",
  "properties": {
    "gn:admin1_code":"29",
    "gn:asciiname":"Pujiajing",
    "gn:country_code":"CN",
    "gn:dem":1303,
    "gn:feature_class":"P",
    "gn:feature_code":"PPL",
    "gn:name":"Pujiajing",
    "gn:population":0,
    "gn:timezone":"Asia/Shanghai",
    "iso:country":"CN",
    "name:zho_x_preferred":[
        "\u666e\u5bb6\u5883"
    ],
    "wof:name":"Pujiajing",
    "wof:placetype":"locality"
},
  "geometry": {"coordinates":[103.12,24.1057],"type":"Point"}
}