{
  "type": "Feature",
  "properties": {
    "gn:admin1_code":"30.0",
    "gn:asciiname":"Xinxiangcun",
    "gn:country_code":"CN",
    "gn:dem":13,
    "gn:feature_class":"P",
    "gn:feature_code":"PPL",
    "gn:name":"Xinxiangcun",
    "gn:population":0,
    "gn:timezone":"Asia/Shanghai",
    "iso:country":"CN",
    "name:zho_x_preferred":[
        "\u65b0\u4e61\u6751"
    ],
    "wof:name":"Xinxiangcun",
    "wof:placetype":"locality"
},
  "geometry": {"coordinates":[117.02469000000001,23.42038],"type":"Point"}
}