{
  "type": "Feature",
  "properties": {
    "gn:admin1_code":"9.0",
    "gn:asciiname":"Linggen",
    "gn:country_code":"CN",
    "gn:dem":1097,
    "gn:feature_class":"P",
    "gn:feature_code":"PPL",
    "gn:name":"Linggen",
    "gn:population":0,
    "gn:timezone":"Asia/Shanghai",
    "iso:country":"CN",
    "name:zho_x_preferred":[
        "\u5cad\u6839"
    ],
    "wof:name":"Linggen",
    "wof:placetype":"locality"
},
  "geometry": {"coordinates":[110.92243999999999,33.79554],"type":"Point"}
}