{
  "type": "Feature",
  "properties": {
    "gn:admin1_code":"22.0",
    "gn:asciiname":"Yushu Dixiacun",
    "gn:country_code":"CN",
    "gn:dem":597,
    "gn:feature_class":"P",
    "gn:feature_code":"PPL",
    "gn:name":"Yushu Dixiacun",
    "gn:population":0,
    "gn:timezone":"Asia/Shanghai",
    "iso:country":"CN",
    "name:zho_x_preferred":[
        "\u6986\u6811\u5e95\u4e0b\u6751"
    ],
    "wof:name":"Yushu Dixiacun",
    "wof:placetype":"locality"
},
  "geometry": {"coordinates":[116.80392999999999,40.72437],"type":"Point"}
}