{
  "type": "Feature",
  "properties": {
    "gn:admin1_code":"18",
    "gn:asciiname":"Sandaoguai",
    "gn:country_code":"CN",
    "gn:dem":1723,
    "gn:feature_class":"P",
    "gn:feature_code":"PPL",
    "gn:name":"Sandaoguai",
    "gn:population":0,
    "gn:timezone":"Asia/Shanghai",
    "iso:country":"CN",
    "name:zho_x_preferred":[
        "\u4e09\u9053\u62d0"
    ],
    "wof:name":"Sandaoguai",
    "wof:placetype":"locality"
},
  "geometry": {"coordinates":[104.63,24.8315],"type":"Point"}
}