{
  "type": "Feature",
  "properties": {
    "gn:admin1_code":"15.0",
    "gn:asciiname":"Jichang",
    "gn:country_code":"CN",
    "gn:dem":2236,
    "gn:feature_class":"P",
    "gn:feature_code":"PPL",
    "gn:name":"Jichang",
    "gn:population":0,
    "gn:timezone":"Asia/Shanghai",
    "iso:country":"CN",
    "name:zho_x_preferred":[
        "\u96c6\u573a"
    ],
    "wof:name":"Jichang",
    "wof:placetype":"locality"
},
  "geometry": {"coordinates":[103.43600000000001,36.053],"type":"Point"}
}