{
  "type": "Feature",
  "properties": {
    "gn:admin1_code":"1.0",
    "gn:asciiname":"Xiayingcun",
    "gn:country_code":"CN",
    "gn:dem":30,
    "gn:feature_class":"P",
    "gn:feature_code":"PPL",
    "gn:name":"Xiayingcun",
    "gn:population":0,
    "gn:timezone":"Asia/Shanghai",
    "iso:country":"CN",
    "name:und_x_variant":[
        "Xiaying"
    ],
    "name:zho_x_preferred":[
        "\u590f\u90e2\u6751"
    ],
    "wof:name":"Xiayingcun",
    "wof:placetype":"locality"
},
  "geometry": {"coordinates":[115.98333,33.14167],"type":"Point"}
}