{
  "type": "Feature",
  "properties": {
    "gn:admin1_code":"32.0",
    "gn:asciiname":"Chenjiashan",
    "gn:country_code":"CN",
    "gn:dem":1289,
    "gn:feature_class":"P",
    "gn:feature_code":"PPL",
    "gn:name":"Chenjiashan",
    "gn:population":0,
    "gn:timezone":"Asia/Shanghai",
    "iso:country":"CN",
    "name:zho_x_preferred":[
        "\u9648\u5bb6\u5c71"
    ],
    "wof:name":"Chenjiashan",
    "wof:placetype":"locality"
},
  "geometry": {"coordinates":[106.55685,32.43383],"type":"Point"}
}