{
  "type": "Feature",
  "properties": {
    "gn:admin1_code":"13",
    "gn:asciiname":"Xiaojingzi",
    "gn:country_code":"CN",
    "gn:dem":1086,
    "gn:feature_class":"P",
    "gn:feature_code":"PPL",
    "gn:name":"Xiaojingzi",
    "gn:population":0,
    "gn:timezone":"Asia/Urumqi",
    "iso:country":"CN",
    "name:und_x_variant":[
        "\u785d\u4e95\u5b50"
    ],
    "wof:name":"Xiaojingzi",
    "wof:placetype":"locality"
},
  "geometry": {"coordinates":[87.39584000000001,42.14608],"type":"Point"}
}