{
  "type": "Feature",
  "properties": {
    "gn:admin1_code":"10.0",
    "gn:asciiname":"Nan'erbu",
    "gn:country_code":"CN",
    "gn:dem":12,
    "gn:feature_class":"P",
    "gn:feature_code":"PPL",
    "gn:name":"Nan\u2019erbu",
    "gn:population":0,
    "gn:timezone":"Asia/Shanghai",
    "iso:country":"CN",
    "name:und_x_variant":[
        "Nan\u2019erbu"
    ],
    "name:zho_x_preferred":[
        "\u5357\u4e8c\u5821"
    ],
    "wof:name":"Nan'erbu",
    "wof:placetype":"locality"
},
  "geometry": {"coordinates":[116.68431,39.20609],"type":"Point"}
}