{
  "type": "Feature",
  "properties": {
    "gn:admin1_code":"11.0",
    "gn:asciiname":"Qingtanwan",
    "gn:country_code":"CN",
    "gn:dem":74,
    "gn:feature_class":"P",
    "gn:feature_code":"PPL",
    "gn:name":"Qingtanwan",
    "gn:population":0,
    "gn:timezone":"Asia/Shanghai",
    "iso:country":"CN",
    "name:zho_x_preferred":[
        "\u6e05\u6f6d\u6e7e"
    ],
    "wof:name":"Qingtanwan",
    "wof:placetype":"locality"
},
  "geometry": {"coordinates":[113.32876,27.92484],"type":"Point"}
}