{
  "type": "Feature",
  "properties": {
    "gn:admin1_code":"26.0",
    "gn:asciiname":"Buchengcun",
    "gn:country_code":"CN",
    "gn:dem":637,
    "gn:feature_class":"P",
    "gn:feature_code":"PPL",
    "gn:name":"Buchengcun",
    "gn:population":0,
    "gn:timezone":"Asia/Shanghai",
    "iso:country":"CN",
    "name:zho_x_preferred":[
        "\u5821\u57ce\u6751"
    ],
    "wof:name":"Buchengcun",
    "wof:placetype":"locality"
},
  "geometry": {"coordinates":[109.97314,35.11557],"type":"Point"}
}