{
  "type": "Feature",
  "properties": {
    "gn:admin1_code":"29.0",
    "gn:asciiname":"Shizhuang",
    "gn:country_code":"CN",
    "gn:dem":3040,
    "gn:feature_class":"P",
    "gn:feature_code":"PPL",
    "gn:name":"Shizhuang",
    "gn:population":0,
    "gn:timezone":"Asia/Shanghai",
    "iso:country":"CN",
    "name:zho_x_preferred":[
        "\u77f3\u5e84"
    ],
    "wof:name":"Shizhuang",
    "wof:placetype":"locality"
},
  "geometry": {"coordinates":[103.00700000000001,26.1463],"type":"Point"}
}