{
  "type": "Feature",
  "properties": {
    "gn:admin1_code":"9",
    "gn:asciiname":"Baiqiu",
    "gn:country_code":"CN",
    "gn:dem":119,
    "gn:feature_class":"P",
    "gn:feature_code":"PPL",
    "gn:name":"Baiqiu",
    "gn:population":0,
    "gn:timezone":"Asia/Shanghai",
    "iso:country":"CN",
    "name:zho_x_preferred":[
        "\u767d\u79cb"
    ],
    "wof:name":"Baiqiu",
    "wof:placetype":"locality"
},
  "geometry": {"coordinates":[112.65506999999999,32.72826],"type":"Point"}
}