{
  "type": "Feature",
  "properties": {
    "gn:admin1_code":"02",
    "gn:asciiname":"Daixi",
    "gn:country_code":"CN",
    "gn:dem":4,
    "gn:feature_class":"P",
    "gn:feature_code":"PPLA4",
    "gn:name":"Daixi",
    "gn:population":0,
    "gn:timezone":"Asia/Shanghai",
    "iso:country":"CN",
    "name:und_x_variant":[
        "\u5cb1\u897f",
        "Daixi Zhen",
        "\u5cb1\u897f\u9547"
    ],
    "wof:name":"Daixi",
    "wof:placetype":"locality"
},
  "geometry": {"coordinates":[122.12264,30.29345],"type":"Point"}
}