{
  "type": "Feature",
  "properties": {
    "gn:admin1_code":"4.0",
    "gn:asciiname":"Huailiuxiang",
    "gn:country_code":"CN",
    "gn:dem":25,
    "gn:feature_class":"P",
    "gn:feature_code":"PPL",
    "gn:name":"Huailiuxiang",
    "gn:population":0,
    "gn:timezone":"Asia/Shanghai",
    "iso:country":"CN",
    "name:zho_x_preferred":[
        "\u69d0\u67f3\u5df7"
    ],
    "wof:name":"Huailiuxiang",
    "wof:placetype":"locality"
},
  "geometry": {"coordinates":[119.36044,32.49743],"type":"Point"}
}