{
  "type": "Feature",
  "properties": {
    "gn:admin1_code":"19.0",
    "gn:asciiname":"Qiansanjia",
    "gn:country_code":"CN",
    "gn:dem":9,
    "gn:feature_class":"P",
    "gn:feature_code":"PPL",
    "gn:name":"Qiansanjia",
    "gn:population":0,
    "gn:timezone":"Asia/Shanghai",
    "iso:country":"CN",
    "name:und_x_variant":[
        "\u524d\u4e09\u5bb6"
    ],
    "wof:name":"Qiansanjia",
    "wof:placetype":"locality"
},
  "geometry": {"coordinates":[122.51788999999999,40.86724],"type":"Point"}
}