{
  "type": "Feature",
  "properties": {
    "gn:admin1_code":"15.0",
    "gn:asciiname":"Dujiagou Yuanyuan",
    "gn:country_code":"CN",
    "gn:dem":1610,
    "gn:feature_class":"P",
    "gn:feature_code":"PPL",
    "gn:name":"Dujiagou Yuanyuan",
    "gn:population":0,
    "gn:timezone":"Asia/Shanghai",
    "iso:country":"CN",
    "name:und_x_variant":[
        "\u675c\u5bb6\u6c9f\u586c\u586c"
    ],
    "wof:name":"Dujiagou Yuanyuan",
    "wof:placetype":"locality"
},
  "geometry": {"coordinates":[107.52021999999999,36.59902],"type":"Point"}
}