{
  "type": "Feature",
  "properties": {
    "gn:admin1_code":"7",
    "gn:asciiname":"Dingkeliao",
    "gn:country_code":"CN",
    "gn:dem":120,
    "gn:feature_class":"P",
    "gn:feature_code":"PPL",
    "gn:name":"Dingkeliao",
    "gn:population":0,
    "gn:timezone":"Asia/Shanghai",
    "iso:country":"CN",
    "name:zho_x_preferred":[
        "\u9876\u5ba2\u5bee"
    ],
    "wof:name":"Dingkeliao",
    "wof:placetype":"locality"
},
  "geometry": {"coordinates":[117.27916999999999,24.15194],"type":"Point"}
}