{
  "type": "Feature",
  "properties": {
    "gn:admin1_code":"9.0",
    "gn:asciiname":"Daliuzhuang",
    "gn:country_code":"CN",
    "gn:dem":85,
    "gn:feature_class":"P",
    "gn:feature_code":"PPL",
    "gn:name":"Daliuzhuang",
    "gn:population":0,
    "gn:timezone":"Asia/Shanghai",
    "iso:country":"CN",
    "name:und_x_variant":[
        "\u5927\u5218\u5e84"
    ],
    "name:zho_x_preferred":[
        "\u5927\u5218\u5e84"
    ],
    "wof:name":"Daliuzhuang",
    "wof:placetype":"locality"
},
  "geometry": {"coordinates":[113.74979999999999,33.28878],"type":"Point"}
}