{
  "type": "Feature",
  "properties": {
    "gn:admin1_code":"8.0",
    "gn:asciiname":"Hongxing Erfenchang Ershisandui",
    "gn:country_code":"CN",
    "gn:dem":327,
    "gn:feature_class":"P",
    "gn:feature_code":"PPLF",
    "gn:name":"Hongxing Erfenchang Ershisandui",
    "gn:population":0,
    "gn:timezone":"Asia/Shanghai",
    "iso:country":"CN",
    "name:zho_x_preferred":[
        "\u7ea2\u661f\u4e8c\u5206\u573a\u4e8c\u5341\u4e09\u961f"
    ],
    "wof:name":"Hongxing Erfenchang Ershisandui",
    "wof:placetype":"locality"
},
  "geometry": {"coordinates":[127.12954000000001,48.24646],"type":"Point"}
}