{
  "type": "Feature",
  "properties": {
    "gn:admin1_code":"14.0",
    "gn:asciiname":"Gucun",
    "gn:country_code":"CN",
    "gn:dem":3364,
    "gn:feature_class":"P",
    "gn:feature_code":"PPL",
    "gn:name":"Gucun",
    "gn:population":0,
    "gn:timezone":"Asia/Urumqi",
    "iso:country":"CN",
    "name:zho_x_preferred":[
        "\u8c37\u6751"
    ],
    "wof:name":"Gucun",
    "wof:placetype":"locality"
},
  "geometry": {"coordinates":[95.37699000000001,30.36845],"type":"Point"}
}