{
  "type": "Feature",
  "properties": {
    "gn:admin1_code":"7",
    "gn:asciiname":"Gongziwei",
    "gn:country_code":"CN",
    "gn:dem":306,
    "gn:feature_class":"P",
    "gn:feature_code":"PPL",
    "gn:name":"Gongziwei",
    "gn:population":0,
    "gn:timezone":"Asia/Shanghai",
    "iso:country":"CN",
    "name:und_x_variant":[
        "\u5bab\u5b50\u5c3e",
        "Gongziwei"
    ],
    "wof:name":"Gongziwei",
    "wof:placetype":"locality"
},
  "geometry": {"coordinates":[118.30062,24.7704],"type":"Point"}
}