{
  "type": "Feature",
  "properties": {
    "gn:admin1_code":"30",
    "gn:asciiname":"Jiang'an",
    "gn:country_code":"CN",
    "gn:dem":17,
    "gn:feature_class":"P",
    "gn:feature_code":"PPL",
    "gn:name":"Jiang\u2019an",
    "gn:population":0,
    "gn:timezone":"Asia/Urumqi",
    "iso:country":"CN",
    "name:deu_x_preferred":[
        "Jiang\u2019an"
    ],
    "name:fra_x_preferred":[
        "Jiang'an"
    ],
    "name:nor_x_preferred":[
        "Jiang'an"
    ],
    "name:rus_x_preferred":[
        "\u0426\u0437\u044f\u043d\u044a\u0430\u043d\u044c"
    ],
    "name:swe_x_preferred":[
        "Jiang'an"
    ],
    "name:zho_x_preferred":[
        "\u6c5f\u5cb8"
    ],
    "name:zho_x_variant":[
        "Jiang\u2019an"
    ],
    "wof:name":"Jiang'an",
    "wof:placetype":"locality"
},
  "geometry": {"coordinates":[110.67314,21.63244],"type":"Point"}
}