{
  "type": "Feature",
  "properties": {
    "gn:admin1_code":"25",
    "gn:asciiname":"Houyaocun",
    "gn:country_code":"CN",
    "gn:dem":45,
    "gn:feature_class":"P",
    "gn:feature_code":"PPL",
    "gn:name":"Houyaocun",
    "gn:population":0,
    "gn:timezone":"Asia/Shanghai",
    "iso:country":"CN",
    "name:zho_x_preferred":[
        "\u540e\u59da\u6751"
    ],
    "wof:name":"Houyaocun",
    "wof:placetype":"locality"
},
  "geometry": {"coordinates":[117.93000000000001,34.8301],"type":"Point"}
}