{
  "type": "Feature",
  "properties": {
    "gn:admin1_code":"32.0",
    "gn:asciiname":"Zhujialiang",
    "gn:country_code":"CN",
    "gn:dem":541,
    "gn:feature_class":"P",
    "gn:feature_code":"PPL",
    "gn:name":"Zhujialiang",
    "gn:population":0,
    "gn:timezone":"Asia/Shanghai",
    "iso:country":"CN",
    "name:zho_x_preferred":[
        "\u6731\u5bb6\u6881"
    ],
    "wof:name":"Zhujialiang",
    "wof:placetype":"locality"
},
  "geometry": {"coordinates":[106.21502,31.8497],"type":"Point"}
}