{
  "type": "Feature",
  "properties": {
    "gn:admin1_code":"07",
    "gn:asciiname":"Jitou",
    "gn:country_code":"CN",
    "gn:dem":676,
    "gn:feature_class":"P",
    "gn:feature_code":"PPL",
    "gn:name":"Jitou",
    "gn:population":0,
    "gn:timezone":"Asia/Shanghai",
    "iso:country":"CN",
    "name:zho_x_preferred":[
        "\u6f08\u5934"
    ],
    "wof:name":"Jitou",
    "wof:placetype":"locality"
},
  "geometry": {"coordinates":[118.28749999999999,25.93944],"type":"Point"}
}