{
  "type": "Feature",
  "properties": {
    "gn:admin1_code":"16.0",
    "gn:asciiname":"Dongsun",
    "gn:country_code":"CN",
    "gn:dem":611,
    "gn:feature_class":"P",
    "gn:feature_code":"PPL",
    "gn:name":"Dongsun",
    "gn:population":0,
    "gn:timezone":"Asia/Shanghai",
    "iso:country":"CN",
    "name:zho_x_preferred":[
        "\u51ac\u7b0b"
    ],
    "wof:name":"Dongsun",
    "wof:placetype":"locality"
},
  "geometry": {"coordinates":[110.27500000000001,22.9423],"type":"Point"}
}