{
  "type": "Feature",
  "properties": {
    "gn:admin1_code":"25",
    "gn:asciiname":"Hanbuzhuang",
    "gn:country_code":"CN",
    "gn:dem":187,
    "gn:feature_class":"P",
    "gn:feature_code":"PPL",
    "gn:name":"Hanbuzhuang",
    "gn:population":0,
    "gn:timezone":"Asia/Shanghai",
    "iso:country":"CN",
    "name:zho_x_preferred":[
        "\u542b\u54fa\u5e84"
    ],
    "wof:name":"Hanbuzhuang",
    "wof:placetype":"locality"
},
  "geometry": {"coordinates":[117.654,35.4372],"type":"Point"}
}