{
  "type": "Feature",
  "properties": {
    "gn:admin1_code":"7",
    "gn:asciiname":"Xizhuang",
    "gn:country_code":"CN",
    "gn:dem":25,
    "gn:feature_class":"P",
    "gn:feature_code":"PPL",
    "gn:name":"Xizhuang",
    "gn:population":0,
    "gn:timezone":"Asia/Shanghai",
    "iso:country":"CN",
    "name:und_x_variant":[
        "Xiazhuang"
    ],
    "name:zho_x_preferred":[
        "\u897f\u5e84"
    ],
    "wof:name":"Xizhuang",
    "wof:placetype":"locality"
},
  "geometry": {"coordinates":[118.4575,24.85806],"type":"Point"}
}