{
  "type": "Feature",
  "properties": {
    "gn:admin1_code":"8.0",
    "gn:asciiname":"Minxingcun",
    "gn:country_code":"CN",
    "gn:dem":155,
    "gn:feature_class":"P",
    "gn:feature_code":"PPL",
    "gn:name":"Minxingcun",
    "gn:population":0,
    "gn:timezone":"Asia/Shanghai",
    "iso:country":"CN",
    "name:zho_x_preferred":[
        "\u6c11\u5174\u6751"
    ],
    "wof:name":"Minxingcun",
    "wof:placetype":"locality"
},
  "geometry": {"coordinates":[127.01528999999999,46.8544],"type":"Point"}
}