{
  "type": "Feature",
  "properties": {
    "gn:admin1_code":"32.0",
    "gn:asciiname":"Huajiangou",
    "gn:country_code":"CN",
    "gn:dem":300,
    "gn:feature_class":"P",
    "gn:feature_code":"PPL",
    "gn:name":"Huajiangou",
    "gn:population":0,
    "gn:timezone":"Asia/Shanghai",
    "iso:country":"CN",
    "name:zho_x_preferred":[
        "\u94e7\u5c16\u6c9f"
    ],
    "wof:name":"Huajiangou",
    "wof:placetype":"locality"
},
  "geometry": {"coordinates":[105.992,30.785],"type":"Point"}
}