{
  "type": "Feature",
  "properties": {
    "gn:admin1_code":"7",
    "gn:asciiname":"Jianbing",
    "gn:country_code":"CN",
    "gn:dem":67,
    "gn:feature_class":"P",
    "gn:feature_code":"PPL",
    "gn:name":"Jianbing",
    "gn:population":0,
    "gn:timezone":"Asia/Shanghai",
    "iso:country":"CN",
    "name:tgl_x_preferred":[
        "Jianbing"
    ],
    "name:und_x_variant":[
        "\u5efa\u67c4"
    ],
    "wof:name":"Jianbing",
    "wof:placetype":"locality"
},
  "geometry": {"coordinates":[119.68444,27.21333],"type":"Point"}
}