{
  "type": "Feature",
  "properties": {
    "gn:admin1_code":"24.0",
    "gn:asciiname":"Liulizhuang",
    "gn:country_code":"CN",
    "gn:dem":1379,
    "gn:feature_class":"P",
    "gn:feature_code":"PPL",
    "gn:name":"Liulizhuang",
    "gn:population":0,
    "gn:timezone":"Asia/Shanghai",
    "iso:country":"CN",
    "name:zho_x_preferred":[
        "\u516d\u91cc\u5e84"
    ],
    "wof:name":"Liulizhuang",
    "wof:placetype":"locality"
},
  "geometry": {"coordinates":[112.36892,39.91642],"type":"Point"}
}