{
  "type": "Feature",
  "properties": {
    "gn:admin1_code":"12.0",
    "gn:asciiname":"Shanyangping",
    "gn:country_code":"CN",
    "gn:dem":872,
    "gn:feature_class":"P",
    "gn:feature_code":"PPL",
    "gn:name":"Shanyangping",
    "gn:population":0,
    "gn:timezone":"Asia/Shanghai",
    "iso:country":"CN",
    "name:zho_x_preferred":[
        "Shanyangping"
    ],
    "name:zho_x_variant":[
        "\u5c71\u7f8a\u576a"
    ],
    "wof:name":"Shanyangping",
    "wof:placetype":"locality"
},
  "geometry": {"coordinates":[110.26743999999999,29.77336],"type":"Point"}
}