{
  "type": "Feature",
  "properties": {
    "gn:admin1_code":"12.0",
    "gn:asciiname":"Huluqiu",
    "gn:country_code":"CN",
    "gn:dem":301,
    "gn:feature_class":"P",
    "gn:feature_code":"PPL",
    "gn:name":"Huluqiu",
    "gn:population":0,
    "gn:timezone":"Asia/Shanghai",
    "iso:country":"CN",
    "name:zho_x_preferred":[
        "\u846b\u82a6\u4e18"
    ],
    "wof:name":"Huluqiu",
    "wof:placetype":"locality"
},
  "geometry": {"coordinates":[110.27976,31.22409],"type":"Point"}
}