{
  "type": "Feature",
  "properties": {
    "gn:admin1_code":"4.0",
    "gn:asciiname":"Huashencun",
    "gn:country_code":"CN",
    "gn:dem":3,
    "gn:feature_class":"P",
    "gn:feature_code":"PPL",
    "gn:name":"Huashencun",
    "gn:population":0,
    "gn:timezone":"Asia/Shanghai",
    "iso:country":"CN",
    "name:zho_x_preferred":[
        "\u82b1\u6c88\u6751"
    ],
    "wof:name":"Huashencun",
    "wof:placetype":"locality"
},
  "geometry": {"coordinates":[119.89032,32.83649],"type":"Point"}
}