{
  "type": "Feature",
  "properties": {
    "gn:admin1_code":"29",
    "gn:asciiname":"Zhongjile",
    "gn:country_code":"CN",
    "gn:dem":1838,
    "gn:feature_class":"P",
    "gn:feature_code":"PPL",
    "gn:name":"Zhongjile",
    "gn:population":0,
    "gn:timezone":"Asia/Shanghai",
    "iso:country":"CN",
    "name:zho_x_preferred":[
        "\u4e2d\u5409\u4e50"
    ],
    "wof:name":"Zhongjile",
    "wof:placetype":"locality"
},
  "geometry": {"coordinates":[101.64400000000001,24.9421],"type":"Point"}
}