{
  "type": "Feature",
  "properties": {
    "gn:admin1_code":"10",
    "gn:asciiname":"Sanjie",
    "gn:country_code":"CN",
    "gn:dem":11,
    "gn:feature_class":"P",
    "gn:feature_code":"PPL",
    "gn:name":"Sanjie",
    "gn:population":0,
    "gn:timezone":"Asia/Shanghai",
    "iso:country":"CN",
    "name:ceb_x_preferred":[
        "Sanjie"
    ],
    "name:deu_x_preferred":[
        "Sanjie"
    ],
    "name:swe_x_preferred":[
        "Sanjie"
    ],
    "name:zho_x_preferred":[
        "\u4e09\u6770"
    ],
    "wof:name":"Sanjie",
    "wof:placetype":"locality"
},
  "geometry": {"coordinates":[116.14700000000001,38.713],"type":"Point"}
}