{
  "type": "Feature",
  "properties": {
    "gn:admin1_code":"32.0",
    "gn:asciiname":"Ruo'erzhai",
    "gn:country_code":"CN",
    "gn:dem":3416,
    "gn:feature_class":"P",
    "gn:feature_code":"PPL",
    "gn:name":"Ruo\u2019erzhai",
    "gn:population":0,
    "gn:timezone":"Asia/Shanghai",
    "iso:country":"CN",
    "name:und_x_variant":[
        "Ruo\u2019erzhai"
    ],
    "name:zho_x_preferred":[
        "\u82e5\u5c14\u5be8"
    ],
    "wof:name":"Ruo'erzhai",
    "wof:placetype":"locality"
},
  "geometry": {"coordinates":[103.753,32.3861],"type":"Point"}
}