{
  "type": "Feature",
  "properties": {
    "gn:admin1_code":"11.0",
    "gn:asciiname":"Yishanwan",
    "gn:country_code":"CN",
    "gn:dem":299,
    "gn:feature_class":"P",
    "gn:feature_code":"PPL",
    "gn:name":"Yishanwan",
    "gn:population":0,
    "gn:timezone":"Asia/Shanghai",
    "iso:country":"CN",
    "name:zho_x_preferred":[
        "\u76ca\u5c71\u6e7e"
    ],
    "wof:name":"Yishanwan",
    "wof:placetype":"locality"
},
  "geometry": {"coordinates":[111.58848,28.1847],"type":"Point"}
}