{
  "type": "Feature",
  "properties": {
    "gn:admin1_code":"24",
    "gn:asciiname":"Qingliangsi",
    "gn:cc2":"CN",
    "gn:country_code":"CN",
    "gn:dem":1049,
    "gn:feature_class":"P",
    "gn:feature_code":"PPL",
    "gn:name":"Qingliangsi",
    "gn:population":0,
    "gn:timezone":"Asia/Shanghai",
    "iso:country":"CN",
    "name:und_x_variant":[
        "Ch\u2019ing-liang-ssu",
        "Wei-hsing-chuang",
        "Weixingzhuang",
        "Qingliangsi"
    ],
    "wof:name":"Qingliangsi",
    "wof:placetype":"locality"
},
  "geometry": {"coordinates":[110.83056000000001,37.98306],"type":"Point"}
}