{
  "type": "Feature",
  "properties": {
    "gn:admin1_code":"5.0",
    "gn:asciiname":"Dongjiancao",
    "gn:country_code":"CN",
    "gn:dem":240,
    "gn:feature_class":"P",
    "gn:feature_code":"PPL",
    "gn:name":"Dongjiancao",
    "gn:population":0,
    "gn:timezone":"Asia/Shanghai",
    "iso:country":"CN",
    "name:zho_x_preferred":[
        "\u4e1c\u78b1\u8349"
    ],
    "wof:name":"Dongjiancao",
    "wof:placetype":"locality"
},
  "geometry": {"coordinates":[125.42865999999999,43.7267],"type":"Point"}
}