{
  "type": "Feature",
  "properties": {
    "gn:admin1_code":"3.0",
    "gn:asciiname":"Yamen Chenjia",
    "gn:country_code":"CN",
    "gn:dem":40,
    "gn:feature_class":"P",
    "gn:feature_code":"PPL",
    "gn:name":"Yamen Chenjia",
    "gn:population":0,
    "gn:timezone":"Asia/Shanghai",
    "iso:country":"CN",
    "name:zho_x_preferred":[
        "\u8859\u95e8\u9648\u5bb6"
    ],
    "wof:name":"Yamen Chenjia",
    "wof:placetype":"locality"
},
  "geometry": {"coordinates":[115.212,28.3214],"type":"Point"}
}