{
  "type": "Feature",
  "properties": {
    "gn:admin1_code":"18",
    "gn:asciiname":"Jia'er",
    "gn:country_code":"CN",
    "gn:dem":802,
    "gn:feature_class":"P",
    "gn:feature_code":"PPL",
    "gn:name":"Jia\u2019er",
    "gn:population":0,
    "gn:timezone":"Asia/Shanghai",
    "iso:country":"CN",
    "name:und_x_variant":[
        "Jia\u2019er"
    ],
    "name:zho_x_preferred":[
        "\u7532\u8033"
    ],
    "wof:name":"Jia'er",
    "wof:placetype":"locality"
},
  "geometry": {"coordinates":[107.14400000000001,25.6479],"type":"Point"}
}