{
  "type": "Feature",
  "properties": {
    "gn:admin1_code":"9.0",
    "gn:asciiname":"Yuankang",
    "gn:country_code":"CN",
    "gn:dem":375,
    "gn:feature_class":"P",
    "gn:feature_code":"PPL",
    "gn:name":"Yuankang",
    "gn:population":0,
    "gn:timezone":"Asia/Shanghai",
    "iso:country":"CN",
    "name:fra_x_preferred":[
        "Yuankang"
    ],
    "wof:name":"Yuankang",
    "wof:placetype":"locality"
},
  "geometry": {"coordinates":[113.74278,35.90694000000001],"type":"Point"}
}