{
  "type": "Feature",
  "properties": {
    "gn:admin1_code":"30.0",
    "gn:asciiname":"Beimen",
    "gn:country_code":"CN",
    "gn:dem":82,
    "gn:feature_class":"P",
    "gn:feature_code":"PPL",
    "gn:name":"Beimen",
    "gn:population":0,
    "gn:timezone":"Asia/Urumqi",
    "iso:country":"CN",
    "name:zho_x_preferred":[
        "\u5317\u95e8"
    ],
    "wof:name":"Beimen",
    "wof:placetype":"locality"
},
  "geometry": {"coordinates":[110.16195999999999,20.33723],"type":"Point"}
}