{
  "type": "Feature",
  "properties": {
    "gn:admin1_code":"19.0",
    "gn:asciiname":"Dabeiwazi",
    "gn:country_code":"CN",
    "gn:dem":105,
    "gn:feature_class":"P",
    "gn:feature_code":"PPL",
    "gn:name":"Dabeiwazi",
    "gn:population":0,
    "gn:timezone":"Asia/Shanghai",
    "iso:country":"CN",
    "name:zho_x_preferred":[
        "\u5927\u5317\u6d3c\u5b50"
    ],
    "wof:name":"Dabeiwazi",
    "wof:placetype":"locality"
},
  "geometry": {"coordinates":[123.687,43.1975],"type":"Point"}
}