{
  "type": "Feature",
  "properties": {
    "gn:admin1_code":"11.0",
    "gn:asciiname":"Xiamuguaxi",
    "gn:country_code":"CN",
    "gn:dem":171,
    "gn:feature_class":"P",
    "gn:feature_code":"PPL",
    "gn:name":"Xiamuguaxi",
    "gn:population":0,
    "gn:timezone":"Asia/Shanghai",
    "iso:country":"CN",
    "name:zho_x_preferred":[
        "\u4e0b\u6728\u74dc\u6eaa"
    ],
    "wof:name":"Xiamuguaxi",
    "wof:placetype":"locality"
},
  "geometry": {"coordinates":[111.92607,28.32231],"type":"Point"}
}