{
  "type": "Feature",
  "properties": {
    "gn:admin1_code":"5.0",
    "gn:asciiname":"Xiningcun",
    "gn:country_code":"CN",
    "gn:dem":320,
    "gn:feature_class":"P",
    "gn:feature_code":"PPL",
    "gn:name":"Xiningcun",
    "gn:population":0,
    "gn:timezone":"Asia/Shanghai",
    "iso:country":"CN",
    "name:zho_x_preferred":[
        "\u897f\u5b81\u6751"
    ],
    "wof:name":"Xiningcun",
    "wof:placetype":"locality"
},
  "geometry": {"coordinates":[126.10366999999999,42.71584],"type":"Point"}
}