{
  "type": "Feature",
  "properties": {
    "gn:admin1_code":"26",
    "gn:asciiname":"Dongzhangcun",
    "gn:country_code":"CN",
    "gn:dem":389,
    "gn:feature_class":"P",
    "gn:feature_code":"PPL",
    "gn:name":"Dongzhangcun",
    "gn:population":0,
    "gn:timezone":"Asia/Shanghai",
    "iso:country":"CN",
    "name:und_x_variant":[
        "Dongzhang",
        "\u4e1c\u5f20",
        "Dongzhangcun"
    ],
    "name:zho_x_preferred":[
        "\u4e1c\u5f20"
    ],
    "name:zho_x_variant":[
        "\u4e1c\u5f20\u6751"
    ],
    "wof:name":"Dongzhangcun",
    "wof:placetype":"locality"
},
  "geometry": {"coordinates":[108.71147999999999,34.28959],"type":"Point"}
}