{
  "type": "Feature",
  "properties": {
    "gn:admin1_code":"30",
    "gn:asciiname":"Xiliaojiao",
    "gn:country_code":"CN",
    "gn:dem":42,
    "gn:feature_class":"P",
    "gn:feature_code":"PPL",
    "gn:name":"Xiliaojiao",
    "gn:population":0,
    "gn:timezone":"Asia/Shanghai",
    "iso:country":"CN",
    "wof:name":"Xiliaojiao",
    "wof:placetype":"locality"
},
  "geometry": {"coordinates":[116.16972,23.58944],"type":"Point"}
}