{
  "type": "Feature",
  "properties": {
    "gn:admin1_code":"18",
    "gn:asciiname":"Shashuzui",
    "gn:country_code":"CN",
    "gn:dem":1338,
    "gn:feature_class":"P",
    "gn:feature_code":"PPL",
    "gn:name":"Shashuzui",
    "gn:population":0,
    "gn:timezone":"Asia/Shanghai",
    "iso:country":"CN",
    "name:zho_x_preferred":[
        "\u6749\u6811\u5480"
    ],
    "wof:name":"Shashuzui",
    "wof:placetype":"locality"
},
  "geometry": {"coordinates":[107.27500000000001,28.3172],"type":"Point"}
}