{
  "type": "Feature",
  "properties": {
    "gn:admin1_code":"14.0",
    "gn:asciiname":"Paglung",
    "gn:country_code":"CN",
    "gn:dem":4613,
    "gn:feature_class":"P",
    "gn:feature_code":"PPL",
    "gn:name":"Paglung",
    "gn:population":0,
    "gn:timezone":"Asia/Urumqi",
    "iso:country":"CN",
    "name:bod_x_preferred":[
        "Paglung"
    ],
    "name:zho_x_preferred":[
        "Palong"
    ],
    "name:zho_x_variant":[
        "\u5e15\u9f99",
        "Chaqu Gongshe",
        "\u8336\u66f2\u516c\u793e"
    ],
    "wof:name":"Paglung",
    "wof:placetype":"locality"
},
  "geometry": {"coordinates":[91.70099999999999,31.701],"type":"Point"}
}