{
  "type": "Feature",
  "properties": {
    "gn:admin1_code":"4.0",
    "gn:asciiname":"Hedui",
    "gn:country_code":"CN",
    "gn:dem":3,
    "gn:feature_class":"P",
    "gn:feature_code":"PPL",
    "gn:name":"Hedui",
    "gn:population":0,
    "gn:timezone":"Asia/Shanghai",
    "iso:country":"CN",
    "name:zho_x_preferred":[
        "Hedui"
    ],
    "name:zho_x_variant":[
        "\u6cb3\u5806"
    ],
    "wof:name":"Hedui",
    "wof:placetype":"locality"
},
  "geometry": {"coordinates":[119.07523,34.48558],"type":"Point"}
}