{
  "type": "Feature",
  "properties": {
    "gn:admin1_code":"11.0",
    "gn:asciiname":"Bianhetang",
    "gn:country_code":"CN",
    "gn:dem":109,
    "gn:feature_class":"P",
    "gn:feature_code":"PPL",
    "gn:name":"Bianhetang",
    "gn:population":0,
    "gn:timezone":"Asia/Shanghai",
    "iso:country":"CN",
    "name:zho_x_preferred":[
        "\u4fbf\u6cb3\u5858"
    ],
    "wof:name":"Bianhetang",
    "wof:placetype":"locality"
},
  "geometry": {"coordinates":[112.26221,28.21383],"type":"Point"}
}