{
  "type": "Feature",
  "properties": {
    "gn:admin1_code":"14.0",
    "gn:asciiname":"Qiemeng",
    "gn:country_code":"CN",
    "gn:dem":4544,
    "gn:feature_class":"P",
    "gn:feature_code":"PPL",
    "gn:name":"Qiemeng",
    "gn:population":0,
    "gn:timezone":"Asia/Urumqi",
    "iso:country":"CN",
    "name:zho_x_preferred":[
        "\u4e14\u8499"
    ],
    "wof:name":"Qiemeng",
    "wof:placetype":"locality"
},
  "geometry": {"coordinates":[86.1718,29.25800000000001],"type":"Point"}
}