{
  "type": "Feature",
  "properties": {
    "gn:admin1_code":"30",
    "gn:asciiname":"Kengtou",
    "gn:country_code":"CN",
    "gn:dem":16,
    "gn:feature_class":"P",
    "gn:feature_code":"PPL",
    "gn:name":"Kengtou",
    "gn:population":0,
    "gn:timezone":"Asia/Urumqi",
    "iso:country":"CN",
    "name:zho_x_preferred":[
        "\u5751\u5934"
    ],
    "wof:name":"Kengtou",
    "wof:placetype":"locality"
},
  "geometry": {"coordinates":[109.9468,20.33414],"type":"Point"}
}