{
  "type": "Feature",
  "properties": {
    "gn:admin1_code":"01",
    "gn:asciiname":"Dakuijiagang",
    "gn:cc2":"CN",
    "gn:country_code":"CN",
    "gn:dem":25,
    "gn:feature_class":"P",
    "gn:feature_code":"PPL",
    "gn:name":"Dakuijiagang",
    "gn:population":0,
    "gn:timezone":"Asia/Shanghai",
    "iso:country":"CN",
    "name:und_x_variant":[
        "Ta-k\u2019uei-chia-kang",
        "Dakuijiagang"
    ],
    "wof:name":"Dakuijiagang",
    "wof:placetype":"locality"
},
  "geometry": {"coordinates":[117.21666999999999,32.48333],"type":"Point"}
}