{
  "type": "Feature",
  "properties": {
    "gn:admin1_code":"32.0",
    "gn:asciiname":"Mawodi",
    "gn:country_code":"CN",
    "gn:dem":2608,
    "gn:feature_class":"P",
    "gn:feature_code":"PPL",
    "gn:name":"Mawodi",
    "gn:population":0,
    "gn:timezone":"Asia/Shanghai",
    "iso:country":"CN",
    "name:zho_x_preferred":[
        "\u9ebb\u7a9d\u5730"
    ],
    "wof:name":"Mawodi",
    "wof:placetype":"locality"
},
  "geometry": {"coordinates":[100.934,28.0408],"type":"Point"}
}