{
  "type": "Feature",
  "properties": {
    "gn:admin1_code":"5.0",
    "gn:asciiname":"Ping'anbucun",
    "gn:country_code":"CN",
    "gn:dem":166,
    "gn:feature_class":"P",
    "gn:feature_code":"PPL",
    "gn:name":"Ping\u2019anbucun",
    "gn:population":0,
    "gn:timezone":"Asia/Shanghai",
    "iso:country":"CN",
    "name:und_x_variant":[
        "Ping\u2019anbucun"
    ],
    "name:zho_x_preferred":[
        "\u5e73\u5b89\u5821\u6751"
    ],
    "wof:name":"Ping'anbucun",
    "wof:placetype":"locality"
},
  "geometry": {"coordinates":[125.58401000000001,44.75431],"type":"Point"}
}