{
  "type": "Feature",
  "properties": {
    "gn:admin1_code":"11",
    "gn:asciiname":"Futang",
    "gn:country_code":"CN",
    "gn:dem":187,
    "gn:feature_class":"P",
    "gn:feature_code":"PPLA4",
    "gn:name":"Futang",
    "gn:population":0,
    "gn:timezone":"Asia/Shanghai",
    "iso:country":"CN",
    "name:und_x_variant":[
        "Futang Xiang",
        "\u5bcc\u5858\u4e61",
        "Futang"
    ],
    "name:zho_x_preferred":[
        "\u5bcc\u5858"
    ],
    "wof:name":"Futang",
    "wof:placetype":"locality"
},
  "geometry": {"coordinates":[111.59944,25.55889],"type":"Point"}
}