{
  "type": "Feature",
  "properties": {
    "gn:admin1_code":"9.0",
    "gn:asciiname":"Fengjiazhuang",
    "gn:country_code":"CN",
    "gn:dem":315,
    "gn:feature_class":"P",
    "gn:feature_code":"PPL",
    "gn:name":"Fengjiazhuang",
    "gn:population":0,
    "gn:timezone":"Asia/Shanghai",
    "iso:country":"CN",
    "name:zho_x_preferred":[
        "\u51af\u5bb6\u5e84"
    ],
    "wof:name":"Fengjiazhuang",
    "wof:placetype":"locality"
},
  "geometry": {"coordinates":[111.4867,32.83735],"type":"Point"}
}