{
  "type": "Feature",
  "properties": {
    "gn:admin1_code":"10",
    "gn:asciiname":"Xixuzhuang",
    "gn:country_code":"CN",
    "gn:dem":20,
    "gn:feature_class":"P",
    "gn:feature_code":"PPL",
    "gn:name":"Xixuzhuang",
    "gn:population":0,
    "gn:timezone":"Asia/Shanghai",
    "iso:country":"CN",
    "name:zho_x_preferred":[
        "\u897f\u5f90\u5e84"
    ],
    "wof:name":"Xixuzhuang",
    "wof:placetype":"locality"
},
  "geometry": {"coordinates":[116.2473,37.89601],"type":"Point"}
}