{
  "type": "Feature",
  "properties": {
    "gn:admin1_code":"11.0",
    "gn:asciiname":"Jinpenxing",
    "gn:country_code":"CN",
    "gn:dem":436,
    "gn:feature_class":"P",
    "gn:feature_code":"PPL",
    "gn:name":"Jinpenxing",
    "gn:population":0,
    "gn:timezone":"Asia/Shanghai",
    "iso:country":"CN",
    "name:zho_x_preferred":[
        "\u91d1\u76c6\u5f62"
    ],
    "wof:name":"Jinpenxing",
    "wof:placetype":"locality"
},
  "geometry": {"coordinates":[113.80231999999999,26.60518],"type":"Point"}
}