{
  "type": "Feature",
  "properties": {
    "gn:admin1_code":"26.0",
    "gn:asciiname":"Caoyingcun",
    "gn:country_code":"CN",
    "gn:dem":911,
    "gn:feature_class":"P",
    "gn:feature_code":"PPL",
    "gn:name":"Caoyingcun",
    "gn:population":0,
    "gn:timezone":"Asia/Shanghai",
    "iso:country":"CN",
    "name:zho_x_preferred":[
        "\u66f9\u8425\u6751"
    ],
    "wof:name":"Caoyingcun",
    "wof:placetype":"locality"
},
  "geometry": {"coordinates":[110.84641999999999,33.62619],"type":"Point"}
}