{
  "type": "Feature",
  "properties": {
    "gn:country":"CN",
    "gn:fcode":"ADM3",
    "gn:pop":0,
    "iso:country":"CN",
    "name:unk_x_variant":[
        "Lin-ch\u2019\u00fc Hsien"
    ],
    "name:zho_x_preferred":[
        "\u4e34\u6710\u53bf"
    ],
    "name:zho_x_variant":[
        "\u4e34\u6710"
    ],
    "qs:name":"Linqu Xian",
    "qs:photos_9r":0,
    "qs:photos_sr":0,
    "qs:pop_sr":"0",
    "wd:wordcount":146,
    "wof:name":"Linqu Xian",
    "wof:placetype":"localadmin",
    "wof:population":0
},
  "geometry": {"coordinates":[118.57389000000001,36.36278],"type":"Point"}
}