{
  "type": "Feature",
  "properties": {
    "gn:country":"CN",
    "gn:fcode":"ADM3",
    "gn:pop":0,
    "iso:country":"CN",
    "name:ceb_x_preferred":[
        "Linqu Xian"
    ],
    "name:deu_x_preferred":[
        "Linqu"
    ],
    "name:eng_x_preferred":[
        "Linqu County"
    ],
    "name:fas_x_preferred":[
        "\u0634\u0647\u0631\u0633\u062a\u0627\u0646 \u0644\u06cc\u0646\u0686\u0648"
    ],
    "name:gan_x_preferred":[
        "\u4e34\u6710\u53bf"
    ],
    "name:jpn_x_preferred":[
        "\u81e8\u30af\u770c"
    ],
    "name:kor_x_preferred":[
        "\ub9b0\ucd94\ud604"
    ],
    "name:nan_x_preferred":[
        "L\u00eem-k\u00fb-ko\u0101n"
    ],
    "name:nld_x_preferred":[
        "Linqu"
    ],
    "name:nob_x_preferred":[
        "Linqu"
    ],
    "name:rus_x_preferred":[
        "\u041b\u0438\u043d\u044c\u0446\u044e\u0439"
    ],
    "name:slv_x_preferred":[
        "okro\u017eje Linqu"
    ],
    "name:swe_x_preferred":[
        "Linqu"
    ],
    "name:unk_x_variant":[
        "Lin-ch\u2019\u00fc Hsien"
    ],
    "name:vie_x_preferred":[
        "L\u00e2m C\u00f9"
    ],
    "name:wuu_x_preferred":[
        "\u4e34\u6710\u53bf"
    ],
    "name:yue_x_preferred":[
        "\u81e8\u6710"
    ],
    "name:zho_x_preferred":[
        "\u4e34\u6710\u53bf"
    ],
    "name:zho_x_variant":[
        "\u4e34\u6710"
    ],
    "qs:name":"Linqu Xian",
    "qs:photos_9r":0,
    "qs:photos_sr":0,
    "qs:pop_sr":"0",
    "wd:wordcount":146,
    "wof:name":"Linqu Xian",
    "wof:placetype":"localadmin",
    "wof:population":0
},
  "geometry": {"coordinates":[118.57389000000001,36.36278],"type":"Point"}
}