{
  "type": "Feature",
  "properties": {
    "gn:admin1_code":"10",
    "gn:asciiname":"Chenhuangfu",
    "gn:country_code":"CN",
    "gn:dem":8,
    "gn:feature_class":"P",
    "gn:feature_code":"PPL",
    "gn:name":"Chenhuangfu",
    "gn:population":0,
    "gn:timezone":"Asia/Shanghai",
    "iso:country":"CN",
    "name:zho_x_preferred":[
        "\u9648\u9ec4\u752b"
    ],
    "wof:name":"Chenhuangfu",
    "wof:placetype":"locality"
},
  "geometry": {"coordinates":[116.58499999999999,38.82],"type":"Point"}
}