{
  "type": "Feature",
  "properties": {
    "gn:admin1_code":"26.0",
    "gn:asciiname":"Huajiazhuangcun",
    "gn:country_code":"CN",
    "gn:dem":1237,
    "gn:feature_class":"P",
    "gn:feature_code":"PPL",
    "gn:name":"Huajiazhuangcun",
    "gn:population":0,
    "gn:timezone":"Asia/Shanghai",
    "iso:country":"CN",
    "name:zho_x_preferred":[
        "\u82b1\u5bb6\u5e84\u6751"
    ],
    "wof:name":"Huajiazhuangcun",
    "wof:placetype":"locality"
},
  "geometry": {"coordinates":[109.06317,35.70737000000001],"type":"Point"}
}