{
  "type": "Feature",
  "properties": {
    "gn:admin1_code":"30",
    "gn:asciiname":"Songbaigen",
    "gn:country_code":"CN",
    "gn:dem":92,
    "gn:feature_class":"P",
    "gn:feature_code":"PPL",
    "gn:name":"Songbaigen",
    "gn:population":0,
    "gn:timezone":"Asia/Urumqi",
    "iso:country":"CN",
    "name:zho_x_preferred":[
        "\u677e\u67cf\u6839"
    ],
    "wof:name":"Songbaigen",
    "wof:placetype":"locality"
},
  "geometry": {"coordinates":[110.64708,22.22954],"type":"Point"}
}