{
  "type": "Feature",
  "properties": {
    "gn:admin1_code":"21",
    "gn:asciiname":"Huangquqiao",
    "gn:cc2":"CN",
    "gn:country_code":"CN",
    "gn:dem":1094,
    "gn:feature_class":"P",
    "gn:feature_code":"PPL",
    "gn:name":"Huangquqiao",
    "gn:population":0,
    "gn:timezone":"Asia/Shanghai",
    "iso:country":"CN",
    "name:und_x_variant":[
        "Hui-nung",
        "Huang-ch\u2019\u00fc-ch\u2019iao",
        "Hwangchukiao",
        "Huangquqiao"
    ],
    "wof:name":"Huangquqiao",
    "wof:placetype":"locality"
},
  "geometry": {"coordinates":[106.68138999999999,39.01611],"type":"Point"}
}