{
  "type": "Feature",
  "properties": {
    "gn:admin1_code":"3.0",
    "gn:asciiname":"Tongluowo",
    "gn:country_code":"CN",
    "gn:dem":355,
    "gn:feature_class":"P",
    "gn:feature_code":"PPL",
    "gn:name":"Tongluowo",
    "gn:population":0,
    "gn:timezone":"Asia/Shanghai",
    "iso:country":"CN",
    "name:zho_x_preferred":[
        "\u94dc\u9523\u7a9d"
    ],
    "wof:name":"Tongluowo",
    "wof:placetype":"locality"
},
  "geometry": {"coordinates":[115.494,25.8735],"type":"Point"}
}