{
  "type": "Feature",
  "properties": {
    "gn:admin1_code":"5.0",
    "gn:asciiname":"Wudaoyangcha",
    "gn:country_code":"CN",
    "gn:dem":719,
    "gn:feature_class":"P",
    "gn:feature_code":"PPL",
    "gn:name":"Wudaoyangcha",
    "gn:population":0,
    "gn:timezone":"Asia/Shanghai",
    "iso:country":"CN",
    "name:und_x_variant":[
        "\u4e94\u9053\u7f8a\u5c94"
    ],
    "wof:name":"Wudaoyangcha",
    "wof:placetype":"locality"
},
  "geometry": {"coordinates":[126.91468999999999,41.8792],"type":"Point"}
}