{
  "type": "Feature",
  "properties": {
    "gn:admin1_code":"18.0",
    "gn:asciiname":"Hexi",
    "gn:country_code":"CN",
    "gn:dem":723,
    "gn:feature_class":"P",
    "gn:feature_code":"PPLA4",
    "gn:name":"Hexi",
    "gn:population":0,
    "gn:timezone":"Asia/Shanghai",
    "iso:country":"CN",
    "name:und_x_variant":[
        "Hexi Zhen"
    ],
    "name:zho_x_preferred":[
        "\u548c\u6eaa"
    ],
    "name:zho_x_variant":[
        "\u548c\u6eaa\u9547"
    ],
    "wof:name":"Hexi",
    "wof:placetype":"locality"
},
  "geometry": {"coordinates":[107.43361000000002,28.45667000000001],"type":"Point"}
}