{
  "type": "Feature",
  "properties": {
    "gn:admin1_code":"18.0",
    "gn:asciiname":"Hexi",
    "gn:country_code":"CN",
    "gn:dem":723,
    "gn:feature_class":"P",
    "gn:feature_code":"PPLA4",
    "gn:name":"Hexi",
    "gn:population":0,
    "gn:timezone":"Asia/Shanghai",
    "iso:country":"CN",
    "name:ceb_x_preferred":[
        "Hexi"
    ],
    "name:deu_x_preferred":[
        "Hexi"
    ],
    "name:eus_x_preferred":[
        "Hexi"
    ],
    "name:fra_x_preferred":[
        "Hexi"
    ],
    "name:nld_x_preferred":[
        "H\u00e0 T\u00e2y"
    ],
    "name:und_x_variant":[
        "Hexi Zhen"
    ],
    "name:vie_x_preferred":[
        "H\u00e0 T\u00e2y"
    ],
    "name:zho_x_preferred":[
        "\u548c\u6eaa"
    ],
    "name:zho_x_variant":[
        "\u548c\u6eaa\u9547"
    ],
    "wof:name":"Hexi",
    "wof:placetype":"locality"
},
  "geometry": {"coordinates":[107.43361000000002,28.45667000000001],"type":"Point"}
}