{
  "type": "Feature",
  "properties": {
    "gn:admin1_code":"3.0",
    "gn:asciiname":"Lannihu",
    "gn:country_code":"CN",
    "gn:dem":425,
    "gn:feature_class":"P",
    "gn:feature_code":"PPL",
    "gn:name":"Lannihu",
    "gn:population":0,
    "gn:timezone":"Asia/Shanghai",
    "iso:country":"CN",
    "name:und_x_variant":[
        "\u6ee5\u6ce5\u6e56"
    ],
    "wof:name":"Lannihu",
    "wof:placetype":"locality"
},
  "geometry": {"coordinates":[115.48425,26.69109000000001],"type":"Point"}
}