{
  "type": "Feature",
  "properties": {
    "gn:admin1_code":"13.0",
    "gn:asciiname":"Qiaokeqi",
    "gn:country_code":"CN",
    "gn:dem":1199,
    "gn:feature_class":"P",
    "gn:feature_code":"PPL",
    "gn:name":"Qiaokeqi",
    "gn:population":0,
    "gn:timezone":"Asia/Shanghai",
    "iso:country":"CN",
    "name:zho_x_preferred":[
        "\u4e54\u514b\u5176"
    ],
    "wof:name":"Qiaokeqi",
    "wof:placetype":"locality"
},
  "geometry": {"coordinates":[76.76985999999999,39.78407],"type":"Point"}
}