{
  "type": "Feature",
  "properties": {
    "gn:admin1_code":"14.0",
    "gn:asciiname":"Batuocun",
    "gn:country_code":"CN",
    "gn:dem":2815,
    "gn:feature_class":"P",
    "gn:feature_code":"PPL",
    "gn:name":"Batuocun",
    "gn:population":0,
    "gn:timezone":"Asia/Urumqi",
    "iso:country":"CN",
    "name:zho_x_preferred":[
        "\u5df4\u59a5\u6751"
    ],
    "wof:name":"Batuocun",
    "wof:placetype":"locality"
},
  "geometry": {"coordinates":[95.58996999999999,30.07366],"type":"Point"}
}