{
  "type": "Feature",
  "properties": {
    "gn:admin1_code":"11.0",
    "gn:asciiname":"Xintangpu",
    "gn:country_code":"CN",
    "gn:dem":87,
    "gn:feature_class":"P",
    "gn:feature_code":"PPL",
    "gn:name":"Xintangpu",
    "gn:population":0,
    "gn:timezone":"Asia/Shanghai",
    "iso:country":"CN",
    "name:zho_x_preferred":[
        "\u65b0\u5858\u94fa"
    ],
    "wof:name":"Xintangpu",
    "wof:placetype":"locality"
},
  "geometry": {"coordinates":[112.62587000000001,26.74924],"type":"Point"}
}