{
  "type": "Feature",
  "properties": {
    "gn:admin1_code":"4.0",
    "gn:asciiname":"Renyicun",
    "gn:country_code":"CN",
    "gn:dem":4,
    "gn:feature_class":"P",
    "gn:feature_code":"PPL",
    "gn:name":"Renyicun",
    "gn:population":0,
    "gn:timezone":"Asia/Shanghai",
    "iso:country":"CN",
    "name:zho_x_preferred":[
        "\u4efb\u4e00\u6751"
    ],
    "wof:name":"Renyicun",
    "wof:placetype":"locality"
},
  "geometry": {"coordinates":[119.87819,32.8702],"type":"Point"}
}