{
  "type": "Feature",
  "properties": {
    "gn:admin1_code":"26",
    "gn:asciiname":"Chencun",
    "gn:country_code":"CN",
    "gn:dem":707,
    "gn:feature_class":"P",
    "gn:feature_code":"PPL",
    "gn:name":"Chencun",
    "gn:population":0,
    "gn:timezone":"Asia/Shanghai",
    "iso:country":"CN",
    "name:und_x_variant":[
        "Ch\u2019en-ts\u2019un",
        "Ch\u2019en-ts\u2019un-chen",
        "Chencun",
        "\u9648\u6751"
    ],
    "wof:name":"Chencun",
    "wof:placetype":"locality"
},
  "geometry": {"coordinates":[107.26034,34.48313],"type":"Point"}
}