{
  "type": "Feature",
  "properties": {
    "gn:admin1_code":"30",
    "gn:asciiname":"Binlangcun",
    "gn:country_code":"CN",
    "gn:dem":66,
    "gn:feature_class":"P",
    "gn:feature_code":"PPL",
    "gn:name":"Binlangcun",
    "gn:population":0,
    "gn:timezone":"Asia/Urumqi",
    "iso:country":"CN",
    "name:zho_x_preferred":[
        "\u69df\u6994\u6751"
    ],
    "wof:name":"Binlangcun",
    "wof:placetype":"locality"
},
  "geometry": {"coordinates":[110.16166,20.30865],"type":"Point"}
}