{
  "type": "Feature",
  "properties": {
    "gn:admin1_code":"29.0",
    "gn:asciiname":"Dazhaizi",
    "gn:country_code":"CN",
    "gn:dem":1523,
    "gn:feature_class":"P",
    "gn:feature_code":"PPL",
    "gn:name":"Dazhaizi",
    "gn:population":0,
    "gn:timezone":"Asia/Shanghai",
    "iso:country":"CN",
    "name:zho_x_preferred":[
        "\u5927\u5be8\u5b50"
    ],
    "wof:name":"Dazhaizi",
    "wof:placetype":"locality"
},
  "geometry": {"coordinates":[98.56319999999999,24.751],"type":"Point"}
}