{
  "type": "Feature",
  "properties": {
    "gn:admin1_code":"5.0",
    "gn:asciiname":"Changjiucun",
    "gn:country_code":"CN",
    "gn:dem":198,
    "gn:feature_class":"P",
    "gn:feature_code":"PPL",
    "gn:name":"Changjiucun",
    "gn:population":0,
    "gn:timezone":"Asia/Shanghai",
    "iso:country":"CN",
    "name:zho_x_preferred":[
        "\u957f\u4e45\u6751"
    ],
    "wof:name":"Changjiucun",
    "wof:placetype":"locality"
},
  "geometry": {"coordinates":[126.3866,44.70757],"type":"Point"}
}