{
  "type": "Feature",
  "properties": {
    "gn:admin1_code":"18.0",
    "gn:asciiname":"Zhengping",
    "gn:country_code":"CN",
    "gn:dem":1634,
    "gn:feature_class":"P",
    "gn:feature_code":"PPL",
    "gn:name":"Zhengping",
    "gn:population":0,
    "gn:timezone":"Asia/Shanghai",
    "iso:country":"CN",
    "name:zho_x_preferred":[
        "\u6b63\u5e73"
    ],
    "wof:name":"Zhengping",
    "wof:placetype":"locality"
},
  "geometry": {"coordinates":[105.65300000000001,26.7862],"type":"Point"}
}