{
  "type": "Feature",
  "properties": {
    "gn:admin1_code":"16.0",
    "gn:asciiname":"Balao",
    "gn:country_code":"CN",
    "gn:dem":663,
    "gn:feature_class":"P",
    "gn:feature_code":"PPL",
    "gn:name":"Balao",
    "gn:population":0,
    "gn:timezone":"Asia/Shanghai",
    "iso:country":"CN",
    "name:ceb_x_preferred":[
        "Bal\u00e1o"
    ],
    "name:pol_x_preferred":[
        "Balao"
    ],
    "name:que_x_preferred":[
        "Balao"
    ],
    "name:spa_x_preferred":[
        "Balao"
    ],
    "name:swe_x_preferred":[
        "Bal\u00e1o"
    ],
    "name:zho_x_preferred":[
        "\u575d\u52b3"
    ],
    "name:zho_x_variant":[
        "\u5df4\u52b3"
    ],
    "wof:name":"Balao",
    "wof:placetype":"locality"
},
  "geometry": {"coordinates":[107.589,25.0816],"type":"Point"}
}