{
  "type": "Feature",
  "properties": {
    "gn:admin1_code":"11.0",
    "gn:asciiname":"Simenkou",
    "gn:country_code":"CN",
    "gn:dem":87,
    "gn:feature_class":"P",
    "gn:feature_code":"PPL",
    "gn:name":"Simenkou",
    "gn:population":0,
    "gn:timezone":"Asia/Shanghai",
    "iso:country":"CN",
    "name:zho_x_preferred":[
        "\u5bfa\u95e8\u53e3"
    ],
    "wof:name":"Simenkou",
    "wof:placetype":"locality"
},
  "geometry": {"coordinates":[111.35952,28.39132],"type":"Point"}
}