{
  "type": "Feature",
  "properties": {
    "gn:admin1_code":"9.0",
    "gn:asciiname":"Xunduo",
    "gn:country_code":"CN",
    "gn:dem":214,
    "gn:feature_class":"P",
    "gn:feature_code":"PPL",
    "gn:name":"Xunduo",
    "gn:population":0,
    "gn:timezone":"Asia/Shanghai",
    "iso:country":"CN",
    "name:und_x_variant":[
        "\u8340\u579b",
        "Xunduo"
    ],
    "wof:name":"Xunduo",
    "wof:placetype":"locality"
},
  "geometry": {"coordinates":[112.36409,33.39712],"type":"Point"}
}