{
  "type": "Feature",
  "properties": {
    "gn:admin1_code":"24",
    "gn:asciiname":"Pingsong",
    "gn:cc2":"CN",
    "gn:country_code":"CN",
    "gn:dem":1238,
    "gn:feature_class":"P",
    "gn:feature_code":"PPL",
    "gn:name":"Pingsong",
    "gn:population":0,
    "gn:timezone":"Asia/Shanghai",
    "iso:country":"CN",
    "name:und_x_variant":[
        "P\u2019ing-sung-ts\u2019un",
        "P\u2019ing-sung",
        "Pingsong"
    ],
    "wof:name":"Pingsong",
    "wof:placetype":"locality"
},
  "geometry": {"coordinates":[113.64749999999999,37.27167],"type":"Point"}
}