{
  "type": "Feature",
  "properties": {
    "gn:admin1_code":"32.0",
    "gn:asciiname":"Fancaodi",
    "gn:country_code":"CN",
    "gn:dem":1097,
    "gn:feature_class":"P",
    "gn:feature_code":"PPL",
    "gn:name":"Fancaodi",
    "gn:population":0,
    "gn:timezone":"Asia/Shanghai",
    "iso:country":"CN",
    "name:zho_x_preferred":[
        "\u7ffb\u8349\u5730"
    ],
    "wof:name":"Fancaodi",
    "wof:placetype":"locality"
},
  "geometry": {"coordinates":[106.92962,32.2606],"type":"Point"}
}