{
  "type": "Feature",
  "properties": {
    "gn:admin1_code":"10",
    "gn:asciiname":"Hujia",
    "gn:country_code":"CN",
    "gn:dem":8,
    "gn:feature_class":"P",
    "gn:feature_code":"PPL",
    "gn:name":"Hujia",
    "gn:population":0,
    "gn:timezone":"Asia/Shanghai",
    "iso:country":"CN",
    "name:deu_x_preferred":[
        "Hujia"
    ],
    "name:spa_x_preferred":[
        "Hujia"
    ],
    "name:zho_x_preferred":[
        "\u80e1\u5bb6"
    ],
    "wof:name":"Hujia",
    "wof:placetype":"locality"
},
  "geometry": {"coordinates":[116.383,38.724],"type":"Point"}
}