{
  "type": "Feature",
  "properties": {
    "gn:admin1_code":"24.0",
    "gn:asciiname":"Huangtufang",
    "gn:country_code":"CN",
    "gn:dem":1191,
    "gn:feature_class":"P",
    "gn:feature_code":"PPL",
    "gn:name":"Huangtufang",
    "gn:population":0,
    "gn:timezone":"Asia/Shanghai",
    "iso:country":"CN",
    "name:zho_x_preferred":[
        "\u9ec4\u571f\u574a"
    ],
    "wof:name":"Huangtufang",
    "wof:placetype":"locality"
},
  "geometry": {"coordinates":[113.03812000000001,38.32092],"type":"Point"}
}