{
  "type": "Feature",
  "properties": {
    "gn:admin1_code":"15.0",
    "gn:asciiname":"Mahalou",
    "gn:country_code":"CN",
    "gn:dem":3269,
    "gn:feature_class":"P",
    "gn:feature_code":"PPL",
    "gn:name":"Mahalou",
    "gn:population":0,
    "gn:timezone":"Asia/Shanghai",
    "iso:country":"CN",
    "name:zho_x_preferred":[
        "\u9ebb\u54c8\u5a04"
    ],
    "wof:name":"Mahalou",
    "wof:placetype":"locality"
},
  "geometry": {"coordinates":[102.718,34.7338],"type":"Point"}
}