{
  "type": "Feature",
  "properties": {
    "gn:admin1_code":"11",
    "gn:asciiname":"Zhouwenmiao",
    "gn:country_code":"CN",
    "gn:dem":33,
    "gn:feature_class":"P",
    "gn:feature_code":"PPLA4",
    "gn:name":"Zhouwenmiao",
    "gn:population":0,
    "gn:timezone":"Asia/Shanghai",
    "iso:country":"CN",
    "name:und_x_variant":[
        "\u5468\u6587\u5e99",
        "Zhouwenmiao Xiang",
        "\u5468\u6587\u5e99\u4e61"
    ],
    "wof:name":"Zhouwenmiao",
    "wof:placetype":"locality"
},
  "geometry": {"coordinates":[112.0517,28.9121],"type":"Point"}
}