{
  "type": "Feature",
  "properties": {
    "iso:country":"CN",
    "qs:name":"\u5174\u5e73\u5e02",
    "qs:name_adm0":"\u4e2d\u570b",
    "qs:name_adm1":"\u965d\u897f\u7701",
    "qs:photos":5,
    "qs:photos_1k":1,
    "qs:photos_9k":1,
    "qs:photos_9r":1,
    "qs:photos_all":5,
    "qs:photos_sr":1,
    "qs:placetype":"LocalAdmin",
    "qs:pop_sr":"0",
    "wof:name":"\u5174\u5e73\u5e02",
    "wof:placetype":"localadmin"
},
  "geometry": {"coordinates":[108.424758,34.268566],"type":"Point"}
}