{
  "type": "Feature",
  "properties": {
    "gn:admin1_code":"21.0",
    "gn:asciiname":"Liumiao",
    "gn:country_code":"CN",
    "gn:dem":1183,
    "gn:feature_class":"P",
    "gn:feature_code":"PPL",
    "gn:name":"Liumiao",
    "gn:population":0,
    "gn:timezone":"Asia/Shanghai",
    "iso:country":"CN",
    "name:zho_x_preferred":[
        "\u5218\u5e99"
    ],
    "wof:name":"Liumiao",
    "wof:placetype":"locality"
},
  "geometry": {"coordinates":[105.729,37.4927],"type":"Point"}
}