{
  "type": "Feature",
  "properties": {
    "gn:admin1_code":"26.0",
    "gn:asciiname":"Qingjiagou",
    "gn:country_code":"CN",
    "gn:dem":1304,
    "gn:feature_class":"P",
    "gn:feature_code":"PPL",
    "gn:name":"Qingjiagou",
    "gn:population":0,
    "gn:timezone":"Asia/Shanghai",
    "iso:country":"CN",
    "name:und_x_variant":[
        "\u9752\u5bb6\u6c9f"
    ],
    "wof:name":"Qingjiagou",
    "wof:placetype":"locality"
},
  "geometry": {"coordinates":[106.58895,33.22983],"type":"Point"}
}