{
  "type": "Feature",
  "properties": {
    "gn:admin1_code":"16.0",
    "gn:asciiname":"Yatang",
    "gn:country_code":"CN",
    "gn:dem":176,
    "gn:feature_class":"P",
    "gn:feature_code":"PPL",
    "gn:name":"Yatang",
    "gn:population":0,
    "gn:timezone":"Asia/Shanghai",
    "iso:country":"CN",
    "name:zho_x_preferred":[
        "\u9e2d\u5858"
    ],
    "wof:name":"Yatang",
    "wof:placetype":"locality"
},
  "geometry": {"coordinates":[110.351,22.5631],"type":"Point"}
}