{
  "type": "Feature",
  "properties": {
    "gn:admin1_code":"18",
    "gn:asciiname":"Tonggujing",
    "gn:country_code":"CN",
    "gn:dem":1399,
    "gn:feature_class":"P",
    "gn:feature_code":"PPL",
    "gn:name":"Tonggujing",
    "gn:population":0,
    "gn:timezone":"Asia/Shanghai",
    "iso:country":"CN",
    "name:zho_x_preferred":[
        "\u94dc\u9f13\u4e95"
    ],
    "wof:name":"Tonggujing",
    "wof:placetype":"locality"
},
  "geometry": {"coordinates":[105.51600000000001,25.1679],"type":"Point"}
}