{
  "type": "Feature",
  "properties": {
    "gn:admin1_code":"10.0",
    "gn:asciiname":"Beifengzhuang",
    "gn:country_code":"CN",
    "gn:dem":16,
    "gn:feature_class":"P",
    "gn:feature_code":"PPL",
    "gn:name":"Beifengzhuang",
    "gn:population":0,
    "gn:timezone":"Asia/Shanghai",
    "iso:country":"CN",
    "name:zho_x_preferred":[
        "\u5317\u51af\u5e84"
    ],
    "wof:name":"Beifengzhuang",
    "wof:placetype":"locality"
},
  "geometry": {"coordinates":[116.102,38.2606],"type":"Point"}
}