{
  "type": "Feature",
  "properties": {
    "gn:admin1_code":"18",
    "gn:asciiname":"Nanmuwo",
    "gn:country_code":"CN",
    "gn:dem":1018,
    "gn:feature_class":"P",
    "gn:feature_code":"PPL",
    "gn:name":"Nanmuwo",
    "gn:population":0,
    "gn:timezone":"Asia/Shanghai",
    "iso:country":"CN",
    "name:zho_x_preferred":[
        "\u6960\u6728\u7a9d"
    ],
    "wof:name":"Nanmuwo",
    "wof:placetype":"locality"
},
  "geometry": {"coordinates":[106.673,28.1481],"type":"Point"}
}