{
  "type": "Feature",
  "properties": {
    "gn:admin1_code":"32.0",
    "gn:asciiname":"Ruxu",
    "gn:country_code":"CN",
    "gn:dem":4176,
    "gn:feature_class":"P",
    "gn:feature_code":"PPL",
    "gn:name":"Ruxu",
    "gn:population":0,
    "gn:timezone":"Asia/Shanghai",
    "iso:country":"CN",
    "name:zho_x_preferred":[
        "\u5982\u987b"
    ],
    "wof:name":"Ruxu",
    "wof:placetype":"locality"
},
  "geometry": {"coordinates":[99.47539999999999,31.1945],"type":"Point"}
}