{
  "type": "Feature",
  "properties": {
    "gn:admin1_code":"4.0",
    "gn:asciiname":"Sicang Sizu",
    "gn:country_code":"CN",
    "gn:dem":5,
    "gn:feature_class":"P",
    "gn:feature_code":"PPL",
    "gn:name":"Sicang Sizu",
    "gn:population":0,
    "gn:timezone":"Asia/Shanghai",
    "iso:country":"CN",
    "name:und_x_variant":[
        "\u56db\u4ed3\u56db\u7ec4"
    ],
    "name:zho_x_preferred":[
        "\u56db\u4ed3\u56db\u7ec4"
    ],
    "wof:name":"Sicang Sizu",
    "wof:placetype":"locality"
},
  "geometry": {"coordinates":[120.60871000000002,32.75274],"type":"Point"}
}