{
  "type": "Feature",
  "properties": {
    "gn:admin1_code":"18",
    "gn:asciiname":"Fujia Yuanzi",
    "gn:country_code":"CN",
    "gn:dem":2235,
    "gn:feature_class":"P",
    "gn:feature_code":"PPL",
    "gn:name":"Fujia Yuanzi",
    "gn:population":0,
    "gn:timezone":"Asia/Shanghai",
    "iso:country":"CN",
    "name:zho_x_preferred":[
        "\u4ed8\u5bb6\u9662\u5b50"
    ],
    "wof:name":"Fujia Yuanzi",
    "wof:placetype":"locality"
},
  "geometry": {"coordinates":[104.288,27.0196],"type":"Point"}
}