{
  "type": "Feature",
  "properties": {
    "gn:admin1_code":"12.0",
    "gn:asciiname":"Shejiawan",
    "gn:country_code":"CN",
    "gn:dem":182,
    "gn:feature_class":"P",
    "gn:feature_code":"PPL",
    "gn:name":"Shejiawan",
    "gn:population":0,
    "gn:timezone":"Asia/Shanghai",
    "iso:country":"CN",
    "name:zho_x_preferred":[
        "\u4f58\u5bb6\u6e7e"
    ],
    "wof:name":"Shejiawan",
    "wof:placetype":"locality"
},
  "geometry": {"coordinates":[112.97398,31.66805],"type":"Point"}
}