{
  "type": "Feature",
  "properties": {
    "gn:admin1_code":"2.0",
    "gn:asciiname":"Xiashuige",
    "gn:country_code":"CN",
    "gn:dem":44,
    "gn:feature_class":"P",
    "gn:feature_code":"PPL",
    "gn:name":"Xiashuige",
    "gn:population":0,
    "gn:timezone":"Asia/Shanghai",
    "iso:country":"CN",
    "name:zho_x_preferred":[
        "\u4e0b\u6c34\u9601"
    ],
    "wof:name":"Xiashuige",
    "wof:placetype":"locality"
},
  "geometry": {"coordinates":[120.20976,29.80168],"type":"Point"}
}