{
  "type": "Feature",
  "properties": {
    "gn:admin1_code":"12.0",
    "gn:asciiname":"Wujiabian",
    "gn:country_code":"CN",
    "gn:dem":122,
    "gn:feature_class":"P",
    "gn:feature_code":"PPL",
    "gn:name":"Wujiabian",
    "gn:population":0,
    "gn:timezone":"Asia/Shanghai",
    "iso:country":"CN",
    "name:zho_x_preferred":[
        "\u90ac\u5bb6\u8fb9"
    ],
    "wof:name":"Wujiabian",
    "wof:placetype":"locality"
},
  "geometry": {"coordinates":[114.9139,31.25961],"type":"Point"}
}