{
  "type": "Feature",
  "properties": {
    "gn:admin1_code":"13.0",
    "gn:asciiname":"Tierimu",
    "gn:country_code":"CN",
    "gn:dem":1206,
    "gn:feature_class":"P",
    "gn:feature_code":"PPLA4",
    "gn:name":"Tierimu",
    "gn:population":0,
    "gn:timezone":"Asia/Shanghai",
    "iso:country":"CN",
    "name:zho_x_preferred":[
        "\u94c1\u65e5\u6728"
    ],
    "wof:name":"Tierimu",
    "wof:placetype":"locality"
},
  "geometry": {"coordinates":[76.73250999999998,39.51068],"type":"Point"}
}