{
  "type": "Feature",
  "properties": {
    "gn:admin1_code":"8.0",
    "gn:asciiname":"Beizifu",
    "gn:country_code":"CN",
    "gn:dem":142,
    "gn:feature_class":"P",
    "gn:feature_code":"PPL",
    "gn:name":"Beizifu",
    "gn:population":0,
    "gn:timezone":"Asia/Shanghai",
    "iso:country":"CN",
    "name:zho_x_preferred":[
        "\u8d1d\u5b50\u5e9c"
    ],
    "wof:name":"Beizifu",
    "wof:placetype":"locality"
},
  "geometry": {"coordinates":[124.34935,46.66346],"type":"Point"}
}