{
  "type": "Feature",
  "properties": {
    "gn:admin1_code":"32.0",
    "gn:asciiname":"Minyuan",
    "gn:country_code":"CN",
    "gn:dem":1521,
    "gn:feature_class":"P",
    "gn:feature_code":"PPL",
    "gn:name":"Minyuan",
    "gn:population":0,
    "gn:timezone":"Asia/Shanghai",
    "iso:country":"CN",
    "name:zho_x_preferred":[
        "\u6c11\u6e90"
    ],
    "wof:name":"Minyuan",
    "wof:placetype":"locality"
},
  "geometry": {"coordinates":[102.18300000000001,27.9357],"type":"Point"}
}