{
  "type": "Feature",
  "properties": {
    "gn:admin1_code":"11.0",
    "gn:asciiname":"Pufengyuan",
    "gn:country_code":"CN",
    "gn:dem":27,
    "gn:feature_class":"P",
    "gn:feature_code":"PPL",
    "gn:name":"Pufengyuan",
    "gn:population":0,
    "gn:timezone":"Asia/Shanghai",
    "iso:country":"CN",
    "name:zho_x_preferred":[
        "\u666e\u4e30\u57b8"
    ],
    "wof:name":"Pufengyuan",
    "wof:placetype":"locality"
},
  "geometry": {"coordinates":[112.55004,29.10514],"type":"Point"}
}