{
  "type": "Feature",
  "properties": {
    "gn:admin1_code":"9.0",
    "gn:asciiname":"Siyuanzhuang",
    "gn:country_code":"CN",
    "gn:dem":64,
    "gn:feature_class":"P",
    "gn:feature_code":"PPL",
    "gn:name":"Siyuanzhuang",
    "gn:population":0,
    "gn:timezone":"Asia/Shanghai",
    "iso:country":"CN",
    "name:zho_x_preferred":[
        "\u5bfa\u9662\u5e84"
    ],
    "wof:name":"Siyuanzhuang",
    "wof:placetype":"locality"
},
  "geometry": {"coordinates":[114.34724,34.24587],"type":"Point"}
}