{
  "type": "Feature",
  "properties": {
    "gn:admin1_code":"2.0",
    "gn:asciiname":"Putaokeng",
    "gn:country_code":"CN",
    "gn:dem":776,
    "gn:feature_class":"P",
    "gn:feature_code":"PPL",
    "gn:name":"Putaokeng",
    "gn:population":0,
    "gn:timezone":"Asia/Shanghai",
    "iso:country":"CN",
    "name:zho_x_preferred":[
        "\u8461\u8404\u5751"
    ],
    "wof:name":"Putaokeng",
    "wof:placetype":"locality"
},
  "geometry": {"coordinates":[119.72336,27.44631],"type":"Point"}
}