{
  "type": "Feature",
  "properties": {
    "gn:admin1_code":"12.0",
    "gn:asciiname":"Chenggao",
    "gn:country_code":"CN",
    "gn:dem":75,
    "gn:feature_class":"P",
    "gn:feature_code":"PPL",
    "gn:name":"Chenggao",
    "gn:population":0,
    "gn:timezone":"Asia/Shanghai",
    "iso:country":"CN",
    "name:zho_x_preferred":[
        "Chenggao"
    ],
    "name:zho_x_variant":[
        "\u6210\u9ad8"
    ],
    "wof:name":"Chenggao",
    "wof:placetype":"locality"
},
  "geometry": {"coordinates":[114.90354000000001,29.5891],"type":"Point"}
}