{
  "type": "Feature",
  "properties": {
    "gn:admin1_code":"29",
    "gn:asciiname":"Dufangzi",
    "gn:country_code":"CN",
    "gn:dem":1889,
    "gn:feature_class":"P",
    "gn:feature_code":"PPL",
    "gn:name":"Dufangzi",
    "gn:population":0,
    "gn:timezone":"Asia/Shanghai",
    "iso:country":"CN",
    "name:zho_x_preferred":[
        "\u72ec\u623f\u5b50"
    ],
    "wof:name":"Dufangzi",
    "wof:placetype":"locality"
},
  "geometry": {"coordinates":[102.149,24.9346],"type":"Point"}
}