{
  "type": "Feature",
  "properties": {
    "gn:admin1_code":"24.0",
    "gn:asciiname":"Fengshangzhang",
    "gn:country_code":"CN",
    "gn:dem":1114,
    "gn:feature_class":"P",
    "gn:feature_code":"PPL",
    "gn:name":"Fengshangzhang",
    "gn:population":0,
    "gn:timezone":"Asia/Shanghai",
    "iso:country":"CN",
    "name:zho_x_preferred":[
        "\u5cf0\u4e0a\u638c"
    ],
    "wof:name":"Fengshangzhang",
    "wof:placetype":"locality"
},
  "geometry": {"coordinates":[113.1404,35.99109],"type":"Point"}
}