{
  "type": "Feature",
  "properties": {
    "gn:admin1_code":"19.0",
    "gn:asciiname":"Qiansantaizicun",
    "gn:country_code":"CN",
    "gn:dem":88,
    "gn:feature_class":"P",
    "gn:feature_code":"PPL",
    "gn:name":"Qiansantaizicun",
    "gn:population":0,
    "gn:timezone":"Asia/Shanghai",
    "iso:country":"CN",
    "name:zho_x_preferred":[
        "\u524d\u4e09\u53f0\u5b50\u6751"
    ],
    "wof:name":"Qiansantaizicun",
    "wof:placetype":"locality"
},
  "geometry": {"coordinates":[124.03846,42.60018],"type":"Point"}
}