{
  "type": "Feature",
  "properties": {
    "gn:admin1_code":"30.0",
    "gn:asciiname":"Yuanjiang",
    "gn:country_code":"CN",
    "gn:dem":72,
    "gn:feature_class":"P",
    "gn:feature_code":"PPL",
    "gn:name":"Yuanjiang",
    "gn:population":0,
    "gn:timezone":"Asia/Shanghai",
    "iso:country":"CN",
    "name:zho_x_preferred":[
        "Yuanjiang"
    ],
    "name:zho_x_variant":[
        "\u5143\u6c5f"
    ],
    "wof:name":"Yuanjiang",
    "wof:placetype":"locality"
},
  "geometry": {"coordinates":[112.64556,24.31306],"type":"Point"}
}