{
  "type": "Feature",
  "properties": {
    "gn:admin1_code":"7",
    "gn:asciiname":"Wuzhai",
    "gn:country_code":"CN",
    "gn:dem":15,
    "gn:feature_class":"P",
    "gn:feature_code":"PPL",
    "gn:name":"Wuzhai",
    "gn:population":0,
    "gn:timezone":"Asia/Shanghai",
    "iso:country":"CN",
    "name:zho_x_preferred":[
        "\u5434\u5b85"
    ],
    "wof:name":"Wuzhai",
    "wof:placetype":"locality"
},
  "geometry": {"coordinates":[117.81412,24.5051],"type":"Point"}
}