{
  "type": "Feature",
  "properties": {
    "gn:admin1_code":"10",
    "gn:asciiname":"Fangmachang",
    "gn:country_code":"CN",
    "gn:dem":624,
    "gn:feature_class":"P",
    "gn:feature_code":"PPL",
    "gn:name":"Fangmachang",
    "gn:population":0,
    "gn:timezone":"Asia/Shanghai",
    "iso:country":"CN",
    "name:zho_x_preferred":[
        "\u653e\u9a6c\u573a"
    ],
    "wof:name":"Fangmachang",
    "wof:placetype":"locality"
},
  "geometry": {"coordinates":[118.23255,41.21728],"type":"Point"}
}