{
  "type": "Feature",
  "properties": {
    "gn:admin1_code":"4.0",
    "gn:asciiname":"Tangwa",
    "gn:country_code":"CN",
    "gn:dem":1,
    "gn:feature_class":"P",
    "gn:feature_code":"PPL",
    "gn:name":"Tangwa",
    "gn:population":0,
    "gn:timezone":"Asia/Shanghai",
    "iso:country":"CN",
    "name:zho_x_preferred":[
        "Tangwa"
    ],
    "name:zho_x_variant":[
        "\u5510\u6d3c"
    ],
    "wof:name":"Tangwa",
    "wof:placetype":"locality"
},
  "geometry": {"coordinates":[119.401,33.94459000000001],"type":"Point"}
}