{
  "type": "Feature",
  "properties": {
    "gn:admin1_code":"10.0",
    "gn:asciiname":"Sidaowa",
    "gn:country_code":"CN",
    "gn:dem":642,
    "gn:feature_class":"P",
    "gn:feature_code":"PPL",
    "gn:name":"Sidaowa",
    "gn:population":0,
    "gn:timezone":"Asia/Shanghai",
    "iso:country":"CN",
    "name:zho_x_preferred":[
        "\u56db\u9053\u6d3c"
    ],
    "wof:name":"Sidaowa",
    "wof:placetype":"locality"
},
  "geometry": {"coordinates":[113.77160000000001,38.48113],"type":"Point"}
}