{
  "type": "Feature",
  "properties": {
    "gn:admin1_code":"1.0",
    "gn:asciiname":"Chenjiachong",
    "gn:country_code":"CN",
    "gn:dem":113,
    "gn:feature_class":"P",
    "gn:feature_code":"PPL",
    "gn:name":"Chenjiachong",
    "gn:population":0,
    "gn:timezone":"Asia/Shanghai",
    "iso:country":"CN",
    "name:zho_x_preferred":[
        "Chenjiachong"
    ],
    "name:zho_x_variant":[
        "\u9648\u5bb6\u51b2"
    ],
    "wof:name":"Chenjiachong",
    "wof:placetype":"locality"
},
  "geometry": {"coordinates":[119.06023,30.88715],"type":"Point"}
}