{
  "type": "Feature",
  "properties": {
    "gn:admin1_code":"12.0",
    "gn:asciiname":"Zhongjiawan",
    "gn:country_code":"CN",
    "gn:dem":26,
    "gn:feature_class":"P",
    "gn:feature_code":"PPL",
    "gn:name":"Zhongjiawan",
    "gn:population":0,
    "gn:timezone":"Asia/Shanghai",
    "iso:country":"CN",
    "name:und_x_variant":[
        "\u949f\u5bb6\u5846"
    ],
    "wof:name":"Zhongjiawan",
    "wof:placetype":"locality"
},
  "geometry": {"coordinates":[114.1532,30.40071],"type":"Point"}
}