{
  "type": "Feature",
  "properties": {
    "gn:admin1_code":"7.0",
    "gn:asciiname":"Xianan",
    "gn:country_code":"CN",
    "gn:dem":320,
    "gn:feature_class":"P",
    "gn:feature_code":"PPLA4",
    "gn:name":"Xianan",
    "gn:population":0,
    "gn:timezone":"Asia/Shanghai",
    "iso:country":"CN",
    "name:und_x_variant":[
        "\u4e0b\u5357",
        "Chengjiao"
    ],
    "name:zho_x_preferred":[
        "\u57ce\u90ca"
    ],
    "wof:name":"Xianan",
    "wof:placetype":"locality"
},
  "geometry": {"coordinates":[116.65897,26.26663],"type":"Point"}
}