{
  "type": "Feature",
  "properties": {
    "gn:admin1_code":"11.0",
    "gn:asciiname":"Maoliyin",
    "gn:country_code":"CN",
    "gn:dem":349,
    "gn:feature_class":"P",
    "gn:feature_code":"PPL",
    "gn:name":"Maoliyin",
    "gn:population":0,
    "gn:timezone":"Asia/Shanghai",
    "iso:country":"CN",
    "name:zho_x_preferred":[
        "\u6bdb\u6817\u57a0"
    ],
    "wof:name":"Maoliyin",
    "wof:placetype":"locality"
},
  "geometry": {"coordinates":[113.89378000000001,28.8618],"type":"Point"}
}