{
  "type": "Feature",
  "properties": {
    "gn:admin1_code":"32.0",
    "gn:asciiname":"Haitangjing",
    "gn:country_code":"CN",
    "gn:dem":370,
    "gn:feature_class":"P",
    "gn:feature_code":"PPL",
    "gn:name":"Haitangjing",
    "gn:population":0,
    "gn:timezone":"Asia/Shanghai",
    "iso:country":"CN",
    "name:zho_x_preferred":[
        "\u6d77\u5858\u4e95"
    ],
    "wof:name":"Haitangjing",
    "wof:placetype":"locality"
},
  "geometry": {"coordinates":[106.10299999999999,31.1133],"type":"Point"}
}