{
  "type": "Feature",
  "properties": {
    "gn:admin1_code":"4.0",
    "gn:asciiname":"Caojiadun",
    "gn:country_code":"CN",
    "gn:dem":3,
    "gn:feature_class":"P",
    "gn:feature_code":"PPL",
    "gn:name":"Caojiadun",
    "gn:population":0,
    "gn:timezone":"Asia/Shanghai",
    "iso:country":"CN",
    "name:und_x_variant":[
        "\u66f9\u5bb6\u58a9"
    ],
    "name:zho_x_preferred":[
        "\u66f9\u5bb6\u58a9"
    ],
    "wof:name":"Caojiadun",
    "wof:placetype":"locality"
},
  "geometry": {"coordinates":[120.38818000000001,32.83008],"type":"Point"}
}