{
  "type": "Feature",
  "properties": {
    "gn:admin1_code":"29.0",
    "gn:asciiname":"Xinchong",
    "gn:country_code":"CN",
    "gn:dem":2431,
    "gn:feature_class":"P",
    "gn:feature_code":"PPL",
    "gn:name":"Xinchong",
    "gn:population":0,
    "gn:timezone":"Asia/Shanghai",
    "iso:country":"CN",
    "name:zho_x_preferred":[
        "\u65b0\u5145"
    ],
    "wof:name":"Xinchong",
    "wof:placetype":"locality"
},
  "geometry": {"coordinates":[99.90009999999999,26.05],"type":"Point"}
}