{
  "type": "Feature",
  "properties": {
    "gn:admin1_code":"26.0",
    "gn:asciiname":"Gengyuanpan",
    "gn:country_code":"CN",
    "gn:dem":1692,
    "gn:feature_class":"P",
    "gn:feature_code":"PPL",
    "gn:name":"Gengyuanpan",
    "gn:population":0,
    "gn:timezone":"Asia/Shanghai",
    "iso:country":"CN",
    "name:und_x_variant":[
        "\u803f\u586c\u7554"
    ],
    "wof:name":"Gengyuanpan",
    "wof:placetype":"locality"
},
  "geometry": {"coordinates":[107.41012000000001,36.91346],"type":"Point"}
}