{
  "type": "Feature",
  "properties": {
    "gn:admin1_code":"32.0",
    "gn:asciiname":"Xian'echi",
    "gn:country_code":"CN",
    "gn:dem":936,
    "gn:feature_class":"P",
    "gn:feature_code":"PPL",
    "gn:name":"Xian\u2019echi",
    "gn:population":0,
    "gn:timezone":"Asia/Shanghai",
    "iso:country":"CN",
    "name:und_x_variant":[
        "Xian\u2019echi"
    ],
    "name:zho_x_preferred":[
        "\u4ed9\u9e45\u6c60"
    ],
    "wof:name":"Xian'echi",
    "wof:placetype":"locality"
},
  "geometry": {"coordinates":[105.232,32.1422],"type":"Point"}
}