{
  "type": "Feature",
  "properties": {
    "gn:admin1_code":"15.0",
    "gn:asciiname":"Gudonggou",
    "gn:country_code":"CN",
    "gn:dem":2345,
    "gn:feature_class":"P",
    "gn:feature_code":"PPL",
    "gn:name":"Gudonggou",
    "gn:population":0,
    "gn:timezone":"Asia/Shanghai",
    "iso:country":"CN",
    "name:zho_x_preferred":[
        "\u53e4\u6d1e\u6c9f"
    ],
    "wof:name":"Gudonggou",
    "wof:placetype":"locality"
},
  "geometry": {"coordinates":[103.589,35.306],"type":"Point"}
}