{
  "type": "Feature",
  "properties": {
    "gn:admin1_code":"15.0",
    "gn:asciiname":"Baijiaoli",
    "gn:country_code":"CN",
    "gn:dem":2032,
    "gn:feature_class":"P",
    "gn:feature_code":"PPL",
    "gn:name":"Baijiaoli",
    "gn:population":0,
    "gn:timezone":"Asia/Shanghai",
    "iso:country":"CN",
    "name:zho_x_preferred":[
        "\u767d\u89d2\u91cc"
    ],
    "wof:name":"Baijiaoli",
    "wof:placetype":"locality"
},
  "geometry": {"coordinates":[104.70963,33.41298],"type":"Point"}
}