{
  "type": "Feature",
  "properties": {
    "gn:admin1_code":"18.0",
    "gn:asciiname":"Gaoxing",
    "gn:country_code":"CN",
    "gn:dem":645,
    "gn:feature_class":"P",
    "gn:feature_code":"PPL",
    "gn:name":"Gaoxing",
    "gn:population":0,
    "gn:timezone":"Asia/Shanghai",
    "iso:country":"CN",
    "name:zho_x_preferred":[
        "\u9ad8\u5174"
    ],
    "wof:name":"Gaoxing",
    "wof:placetype":"locality"
},
  "geometry": {"coordinates":[108.46299999999999,25.9773],"type":"Point"}
}