{
  "type": "Feature",
  "properties": {
    "gn:admin1_code":"4.0",
    "gn:asciiname":"Laozhaixu",
    "gn:country_code":"CN",
    "gn:dem":26,
    "gn:feature_class":"P",
    "gn:feature_code":"PPL",
    "gn:name":"Laozhaixu",
    "gn:population":0,
    "gn:timezone":"Asia/Shanghai",
    "iso:country":"CN",
    "name:zho_x_preferred":[
        "\u8001\u5b85\u5729"
    ],
    "wof:name":"Laozhaixu",
    "wof:placetype":"locality"
},
  "geometry": {"coordinates":[117.681,34.3458],"type":"Point"}
}