{
  "type": "Feature",
  "properties": {
    "gn:admin1_code":"10.0",
    "gn:asciiname":"Liuzhidui",
    "gn:country_code":"CN",
    "gn:dem":6,
    "gn:feature_class":"P",
    "gn:feature_code":"PPLF",
    "gn:name":"Liuzhidui",
    "gn:population":0,
    "gn:timezone":"Asia/Shanghai",
    "iso:country":"CN",
    "name:zho_x_preferred":[
        "\u516d\u652f\u961f"
    ],
    "wof:name":"Liuzhidui",
    "wof:placetype":"locality"
},
  "geometry": {"coordinates":[119.49782,39.81605],"type":"Point"}
}