{
  "type": "Feature",
  "properties": {
    "gn:admin1_code":"3.0",
    "gn:asciiname":"Yutang",
    "gn:country_code":"CN",
    "gn:dem":73,
    "gn:feature_class":"P",
    "gn:feature_code":"PPL",
    "gn:name":"Yutang",
    "gn:population":0,
    "gn:timezone":"Asia/Shanghai",
    "iso:country":"CN",
    "name:und_x_variant":[
        "\u6e14\u5858"
    ],
    "wof:name":"Yutang",
    "wof:placetype":"locality"
},
  "geometry": {"coordinates":[114.88814000000001,27.38253],"type":"Point"}
}