{
  "type": "Feature",
  "properties": {
    "gn:admin1_code":"13.0",
    "gn:asciiname":"Daizimale Maili",
    "gn:country_code":"CN",
    "gn:dem":1339,
    "gn:feature_class":"P",
    "gn:feature_code":"PPL",
    "gn:name":"Daizimale Maili",
    "gn:population":0,
    "gn:timezone":"Asia/Shanghai",
    "iso:country":"CN",
    "name:zho_x_preferred":[
        "\u4ee3\u5b5c\u739b\u52d2\u4e70\u91cc"
    ],
    "wof:name":"Daizimale Maili",
    "wof:placetype":"locality"
},
  "geometry": {"coordinates":[79.95035,37.16081],"type":"Point"}
}