{
  "type": "Feature",
  "properties": {
    "gn:admin1_code":"14.0",
    "gn:asciiname":"Macu",
    "gn:country_code":"CN",
    "gn:dem":4664,
    "gn:feature_class":"P",
    "gn:feature_code":"PPL",
    "gn:name":"Macu",
    "gn:population":0,
    "gn:timezone":"Asia/Shanghai",
    "iso:country":"CN",
    "name:zho_x_preferred":[
        "\u739b\u7c97"
    ],
    "wof:name":"Macu",
    "wof:placetype":"locality"
},
  "geometry": {"coordinates":[81.0271,30.9871],"type":"Point"}
}