{
  "type": "Feature",
  "properties": {
    "gn:admin1_code":"16.0",
    "gn:asciiname":"Youcheng Xincun",
    "gn:country_code":"CN",
    "gn:dem":158,
    "gn:feature_class":"P",
    "gn:feature_code":"PPL",
    "gn:name":"Youcheng Xincun",
    "gn:population":0,
    "gn:timezone":"Asia/Shanghai",
    "iso:country":"CN",
    "name:zho_x_preferred":[
        "\u6709\u6210\u65b0\u6751"
    ],
    "wof:name":"Youcheng Xincun",
    "wof:placetype":"locality"
},
  "geometry": {"coordinates":[109.449,24.1677],"type":"Point"}
}