{
  "type": "Feature",
  "properties": {
    "gn:admin1_code":"19.0",
    "gn:asciiname":"Gaoligoucun",
    "gn:country_code":"CN",
    "gn:dem":106,
    "gn:feature_class":"P",
    "gn:feature_code":"PPL",
    "gn:name":"Gaoligoucun",
    "gn:population":0,
    "gn:timezone":"Asia/Shanghai",
    "iso:country":"CN",
    "name:zho_x_preferred":[
        "\u9ad8\u529b\u6c9f\u6751"
    ],
    "wof:name":"Gaoligoucun",
    "wof:placetype":"locality"
},
  "geometry": {"coordinates":[123.50700000000001,42.4074],"type":"Point"}
}