{
  "type": "Feature",
  "properties": {
    "gn:admin1_code":"8.0",
    "gn:asciiname":"Fadacun",
    "gn:country_code":"CN",
    "gn:dem":223,
    "gn:feature_class":"P",
    "gn:feature_code":"PPL",
    "gn:name":"Fadacun",
    "gn:population":0,
    "gn:timezone":"Asia/Shanghai",
    "iso:country":"CN",
    "name:zho_x_preferred":[
        "\u53d1\u8fbe\u6751"
    ],
    "wof:name":"Fadacun",
    "wof:placetype":"locality"
},
  "geometry": {"coordinates":[127.56964000000001,46.66867],"type":"Point"}
}