{
  "type": "Feature",
  "properties": {
    "gn:admin1_code":"32.0",
    "gn:asciiname":"Zhongxinliang",
    "gn:country_code":"CN",
    "gn:dem":865,
    "gn:feature_class":"P",
    "gn:feature_code":"PPL",
    "gn:name":"Zhongxinliang",
    "gn:population":0,
    "gn:timezone":"Asia/Shanghai",
    "iso:country":"CN",
    "name:zho_x_preferred":[
        "\u4e2d\u5fc3\u6881"
    ],
    "wof:name":"Zhongxinliang",
    "wof:placetype":"locality"
},
  "geometry": {"coordinates":[108.08119000000001,31.28708],"type":"Point"}
}