{
  "type": "Feature",
  "properties": {
    "gn:admin1_code":"32.0",
    "gn:asciiname":"Zezong",
    "gn:country_code":"CN",
    "gn:dem":2256,
    "gn:feature_class":"P",
    "gn:feature_code":"PPL",
    "gn:name":"Zezong",
    "gn:population":0,
    "gn:timezone":"Asia/Shanghai",
    "iso:country":"CN",
    "name:zho_x_preferred":[
        "\u5219\u5b97"
    ],
    "wof:name":"Zezong",
    "wof:placetype":"locality"
},
  "geometry": {"coordinates":[102.676,27.3237],"type":"Point"}
}