{
  "type": "Feature",
  "properties": {
    "gn:admin1_code":"31.0",
    "gn:asciiname":"Kengdong",
    "gn:country_code":"CN",
    "gn:dem":8,
    "gn:feature_class":"P",
    "gn:feature_code":"PPL",
    "gn:name":"Kengdong",
    "gn:population":0,
    "gn:timezone":"Asia/Shanghai",
    "iso:country":"CN",
    "name:zho_x_preferred":[
        "Kengdong"
    ],
    "name:zho_x_variant":[
        "\u5751\u4e1c"
    ],
    "wof:name":"Kengdong",
    "wof:placetype":"locality"
},
  "geometry": {"coordinates":[110.74250000000001,20.00268],"type":"Point"}
}