{
  "type": "Feature",
  "properties": {
    "gn:admin1_code":"32.0",
    "gn:asciiname":"Dawancuncun",
    "gn:country_code":"CN",
    "gn:dem":2712,
    "gn:feature_class":"P",
    "gn:feature_code":"PPL",
    "gn:name":"Dawancuncun",
    "gn:population":0,
    "gn:timezone":"Asia/Shanghai",
    "iso:country":"CN",
    "name:zho_x_preferred":[
        "\u5927\u6e7e\u6751\u6751"
    ],
    "wof:name":"Dawancuncun",
    "wof:placetype":"locality"
},
  "geometry": {"coordinates":[101.26600000000001,27.1413],"type":"Point"}
}