{
  "type": "Feature",
  "properties": {
    "gn:admin1_code":"14.0",
    "gn:asciiname":"Linzhouding",
    "gn:country_code":"CN",
    "gn:dem":3860,
    "gn:feature_class":"P",
    "gn:feature_code":"PPL",
    "gn:name":"Linzhouding",
    "gn:population":0,
    "gn:timezone":"Asia/Urumqi",
    "iso:country":"CN",
    "name:bod_x_preferred":[
        "Lh\u00fcnzhubd\u00eang"
    ],
    "name:zho_x_preferred":[
        "\u6797\u5468\u9876"
    ],
    "wof:name":"Linzhouding",
    "wof:placetype":"locality"
},
  "geometry": {"coordinates":[91.107,29.907],"type":"Point"}
}