{
  "type": "Feature",
  "properties": {
    "gn:admin1_code":"10",
    "gn:asciiname":"Zhangqiusi",
    "gn:country_code":"CN",
    "gn:dem":17,
    "gn:feature_class":"P",
    "gn:feature_code":"PPL",
    "gn:name":"Zhangqiusi",
    "gn:population":0,
    "gn:timezone":"Asia/Shanghai",
    "iso:country":"CN",
    "name:zho_x_preferred":[
        "\u5f20\u79cb\u5bfa"
    ],
    "wof:name":"Zhangqiusi",
    "wof:placetype":"locality"
},
  "geometry": {"coordinates":[116.2467,37.81548],"type":"Point"}
}