{
  "type": "Feature",
  "properties": {
    "gn:admin1_code":"3",
    "gn:asciiname":"Shijiutang",
    "gn:country_code":"CN",
    "gn:dem":79,
    "gn:feature_class":"P",
    "gn:feature_code":"PPL",
    "gn:name":"Shijiutang",
    "gn:population":0,
    "gn:timezone":"Asia/Shanghai",
    "iso:country":"CN",
    "name:zho_x_preferred":[
        "\u77f3\u4e5d\u5858"
    ],
    "wof:name":"Shijiutang",
    "wof:placetype":"locality"
},
  "geometry": {"coordinates":[114.76300000000001,26.6687],"type":"Point"}
}