{
  "type": "Feature",
  "properties": {
    "gn:admin1_code":"26.0",
    "gn:asciiname":"Zifangcun",
    "gn:country_code":"CN",
    "gn:dem":672,
    "gn:feature_class":"P",
    "gn:feature_code":"PPL",
    "gn:name":"Zifangcun",
    "gn:population":0,
    "gn:timezone":"Asia/Shanghai",
    "iso:country":"CN",
    "name:zho_x_preferred":[
        "\u5b50\u623f\u6751"
    ],
    "wof:name":"Zifangcun",
    "wof:placetype":"locality"
},
  "geometry": {"coordinates":[109.27734,32.95538],"type":"Point"}
}