{
  "type": "Feature",
  "properties": {
    "gn:admin1_code":"26.0",
    "gn:asciiname":"Foyemiao",
    "gn:country_code":"CN",
    "gn:dem":1135,
    "gn:feature_class":"P",
    "gn:feature_code":"PPL",
    "gn:name":"Foyemiao",
    "gn:population":0,
    "gn:timezone":"Asia/Shanghai",
    "iso:country":"CN",
    "name:zho_x_preferred":[
        "\u4f5b\u7237\u5e99"
    ],
    "wof:name":"Foyemiao",
    "wof:placetype":"locality"
},
  "geometry": {"coordinates":[107.01461999999999,33.31665],"type":"Point"}
}