{
  "type": "Feature",
  "properties": {
    "gn:admin1_code":"30",
    "gn:asciiname":"Diaoloucun",
    "gn:country_code":"CN",
    "gn:dem":99,
    "gn:feature_class":"P",
    "gn:feature_code":"PPL",
    "gn:name":"Diaoloucun",
    "gn:population":0,
    "gn:timezone":"Asia/Urumqi",
    "iso:country":"CN",
    "name:zho_x_preferred":[
        "\u8c03\u697c\u6751"
    ],
    "wof:name":"Diaoloucun",
    "wof:placetype":"locality"
},
  "geometry": {"coordinates":[110.21526,21.27912],"type":"Point"}
}