{
  "type": "Feature",
  "properties": {
    "gn:admin1_code":"7.0",
    "gn:asciiname":"Yangdicun",
    "gn:country_code":"CN",
    "gn:dem":434,
    "gn:feature_class":"P",
    "gn:feature_code":"PPL",
    "gn:name":"Yangdicun",
    "gn:population":0,
    "gn:timezone":"Asia/Shanghai",
    "iso:country":"CN",
    "name:und_x_variant":[
        "\u6768\u5730\u6751"
    ],
    "name:zho_x_preferred":[
        "\u6768\u5730\u6751"
    ],
    "wof:name":"Yangdicun",
    "wof:placetype":"locality"
},
  "geometry": {"coordinates":[117.11144,26.45094000000001],"type":"Point"}
}