{
  "type": "Feature",
  "properties": {
    "gn:admin1_code":"18.0",
    "gn:asciiname":"Mianduo",
    "gn:country_code":"CN",
    "gn:dem":732,
    "gn:feature_class":"P",
    "gn:feature_code":"PPL",
    "gn:name":"Mianduo",
    "gn:population":0,
    "gn:timezone":"Asia/Shanghai",
    "iso:country":"CN",
    "name:zho_x_preferred":[
        "\u68c9\u6735"
    ],
    "wof:name":"Mianduo",
    "wof:placetype":"locality"
},
  "geometry": {"coordinates":[107.78700000000001,26.306],"type":"Point"}
}