{
  "type": "Feature",
  "properties": {
    "gn:admin1_code":"19.0",
    "gn:asciiname":"Quanshuiye",
    "gn:country_code":"CN",
    "gn:dem":399,
    "gn:feature_class":"P",
    "gn:feature_code":"PPL",
    "gn:name":"Quanshuiye",
    "gn:population":0,
    "gn:timezone":"Asia/Shanghai",
    "iso:country":"CN",
    "name:und_x_variant":[
        "\u6cc9\u6c34\u6db2"
    ],
    "wof:name":"Quanshuiye",
    "wof:placetype":"locality"
},
  "geometry": {"coordinates":[124.98739999999999,41.04125],"type":"Point"}
}