{
  "type": "Feature",
  "properties": {
    "gn:admin1_code":"5.0",
    "gn:asciiname":"Sidaohezi",
    "gn:country_code":"CN",
    "gn:dem":407,
    "gn:feature_class":"P",
    "gn:feature_code":"PPL",
    "gn:name":"Sidaohezi",
    "gn:population":0,
    "gn:timezone":"Asia/Shanghai",
    "iso:country":"CN",
    "name:und_x_variant":[
        "\u56db\u9053\u6cb3\u5b50"
    ],
    "wof:name":"Sidaohezi",
    "wof:placetype":"locality"
},
  "geometry": {"coordinates":[126.73565000000001,41.78339],"type":"Point"}
}