{
  "type": "Feature",
  "properties": {
    "gn:admin1_code":"10",
    "gn:asciiname":"Feicheng",
    "gn:country_code":"CN",
    "gn:dem":22,
    "gn:feature_class":"P",
    "gn:feature_code":"PPL",
    "gn:name":"Feicheng",
    "gn:population":0,
    "gn:timezone":"Asia/Shanghai",
    "iso:country":"CN",
    "name:deu_x_preferred":[
        "Feicheng"
    ],
    "name:ell_x_preferred":[
        "\u03a6\u03ad\u03b9\u03c4\u03c3\u03b5\u03bd\u03b3\u03ba"
    ],
    "name:fas_x_preferred":[
        "\u0641\u06cc\u0686\u0646\u06af"
    ],
    "name:fra_x_preferred":[
        "Feicheng"
    ],
    "name:hak_x_preferred":[
        "Ph\u00ec-s\u00e0ng"
    ],
    "name:ita_x_preferred":[
        "Feicheng"
    ],
    "name:jpn_x_preferred":[
        "\u80a5\u57ce\u5e02"
    ],
    "name:kik_x_preferred":[
        "Feicheng"
    ],
    "name:kor_x_preferred":[
        "\ud398\uc774\uccad\uc2dc"
    ],
    "name:mlg_x_preferred":[
        "Feicheng"
    ],
    "name:nor_x_preferred":[
        "Feicheng"
    ],
    "name:rus_x_preferred":[
        "\u0424\u044d\u0439\u0447\u044d\u043d"
    ],
    "name:swe_x_preferred":[
        "Feicheng"
    ],
    "name:vie_x_preferred":[
        "Ph\u00ec Th\u00e0nh"
    ],
    "name:zho_x_preferred":[
        "\u80a5\u57ce"
    ],
    "name:zho_x_variant":[
        "\u80a5\u57ce\u5e02"
    ],
    "wof:name":"Feicheng",
    "wof:placetype":"locality"
},
  "geometry": {"coordinates":[116.31307,37.62473],"type":"Point"}
}