{
  "type": "Feature",
  "properties": {
    "gn:admin1_code":"10",
    "gn:asciiname":"Feicheng",
    "gn:country_code":"CN",
    "gn:dem":22,
    "gn:feature_class":"P",
    "gn:feature_code":"PPL",
    "gn:name":"Feicheng",
    "gn:population":0,
    "gn:timezone":"Asia/Shanghai",
    "iso:country":"CN",
    "name:zho_x_preferred":[
        "\u80a5\u57ce"
    ],
    "wof:name":"Feicheng",
    "wof:placetype":"locality"
},
  "geometry": {"coordinates":[116.31307,37.62473],"type":"Point"}
}