{
  "type": "Feature",
  "properties": {
    "gn:admin1_code":"4.0",
    "gn:asciiname":"Xijiao'an",
    "gn:country_code":"CN",
    "gn:dem":6,
    "gn:feature_class":"P",
    "gn:feature_code":"PPL",
    "gn:name":"Xijiao\u2019an",
    "gn:population":0,
    "gn:timezone":"Asia/Shanghai",
    "iso:country":"CN",
    "name:und_x_variant":[
        "Xijiao\u2019an"
    ],
    "name:zho_x_preferred":[
        "\u6d17\u811a\u5eb5"
    ],
    "wof:name":"Xijiao'an",
    "wof:placetype":"locality"
},
  "geometry": {"coordinates":[120.37605000000001,32.11854],"type":"Point"}
}