{
  "type": "Feature",
  "properties": {
    "gn:admin1_code":"15.0",
    "gn:asciiname":"Yinpoli",
    "gn:country_code":"CN",
    "gn:dem":1618,
    "gn:feature_class":"P",
    "gn:feature_code":"PPL",
    "gn:name":"Yinpoli",
    "gn:population":0,
    "gn:timezone":"Asia/Shanghai",
    "iso:country":"CN",
    "name:und_x_variant":[
        "\u9634\u5761\u91cc"
    ],
    "wof:name":"Yinpoli",
    "wof:placetype":"locality"
},
  "geometry": {"coordinates":[105.37513,33.30438],"type":"Point"}
}