{
  "type": "Feature",
  "properties": {
    "gn:admin1_code":"25",
    "gn:asciiname":"Anjia Taizi",
    "gn:country_code":"CN",
    "gn:dem":177,
    "gn:feature_class":"P",
    "gn:feature_code":"PPL",
    "gn:name":"Anjia Taizi",
    "gn:population":0,
    "gn:timezone":"Asia/Shanghai",
    "iso:country":"CN",
    "name:zho_x_preferred":[
        "\u5b89\u5bb6\u53f0\u5b50"
    ],
    "wof:name":"Anjia Taizi",
    "wof:placetype":"locality"
},
  "geometry": {"coordinates":[117.589,36.2168],"type":"Point"}
}