{
  "type": "Feature",
  "properties": {
    "gn:admin1_code":"30.0",
    "gn:asciiname":"Wujiaoping",
    "gn:country_code":"CN",
    "gn:dem":695,
    "gn:feature_class":"P",
    "gn:feature_code":"PPL",
    "gn:name":"Wujiaoping",
    "gn:population":0,
    "gn:timezone":"Asia/Shanghai",
    "iso:country":"CN",
    "name:zho_x_preferred":[
        "Wujiaoping"
    ],
    "name:zho_x_variant":[
        "\u4e94\u89d2\u576a"
    ],
    "wof:name":"Wujiaoping",
    "wof:placetype":"locality"
},
  "geometry": {"coordinates":[112.20722000000001,24.74917],"type":"Point"}
}