{
  "type": "Feature",
  "properties": {
    "gn:admin1_code":"32.0",
    "gn:asciiname":"Majia'an",
    "gn:country_code":"CN",
    "gn:dem":564,
    "gn:feature_class":"P",
    "gn:feature_code":"PPL",
    "gn:name":"Majia\u2019an",
    "gn:population":0,
    "gn:timezone":"Asia/Shanghai",
    "iso:country":"CN",
    "name:zho_x_preferred":[
        "\u9a6c\u5bb6\u5eb5"
    ],
    "name:zho_x_variant":[
        "Majia\u2019an"
    ],
    "wof:name":"Majia'an",
    "wof:placetype":"locality"
},
  "geometry": {"coordinates":[103.60552,30.6884],"type":"Point"}
}