{
  "type": "Feature",
  "properties": {
    "gn:admin1_code":"19.0",
    "gn:asciiname":"Nongmin",
    "gn:country_code":"CN",
    "gn:dem":13,
    "gn:feature_class":"P",
    "gn:feature_code":"PPL",
    "gn:name":"Nongmin",
    "gn:population":0,
    "gn:timezone":"Asia/Shanghai",
    "iso:country":"CN",
    "name:und_x_variant":[
        "\u519c\u6c11"
    ],
    "wof:name":"Nongmin",
    "wof:placetype":"locality"
},
  "geometry": {"coordinates":[122.38468,40.38763],"type":"Point"}
}