{
  "type": "Feature",
  "properties": {
    "gn:admin1_code":"29.0",
    "gn:asciiname":"Mangnong",
    "gn:country_code":"CN",
    "gn:dem":1037,
    "gn:feature_class":"P",
    "gn:feature_code":"PPL",
    "gn:name":"Mangnong",
    "gn:population":0,
    "gn:timezone":"Asia/Shanghai",
    "iso:country":"CN",
    "name:zho_x_preferred":[
        "\u8292\u5f04"
    ],
    "wof:name":"Mangnong",
    "wof:placetype":"locality"
},
  "geometry": {"coordinates":[98.1361,25.1338],"type":"Point"}
}