{
  "type": "Feature",
  "properties": {
    "gn:admin1_code":"3.0",
    "gn:asciiname":"Jingziqiu",
    "gn:country_code":"CN",
    "gn:dem":153,
    "gn:feature_class":"P",
    "gn:feature_code":"PPL",
    "gn:name":"Jingziqiu",
    "gn:population":0,
    "gn:timezone":"Asia/Shanghai",
    "iso:country":"CN",
    "name:und_x_variant":[
        "\u4e95\u5b50\u4e18"
    ],
    "wof:name":"Jingziqiu",
    "wof:placetype":"locality"
},
  "geometry": {"coordinates":[115.36620000000001,26.19017],"type":"Point"}
}