{
  "type": "Feature",
  "properties": {
    "gn:admin1_code":"32.0",
    "gn:asciiname":"Tianyouzhai",
    "gn:country_code":"CN",
    "gn:dem":382,
    "gn:feature_class":"P",
    "gn:feature_code":"PPL",
    "gn:name":"Tianyouzhai",
    "gn:population":0,
    "gn:timezone":"Asia/Shanghai",
    "iso:country":"CN",
    "name:zho_x_preferred":[
        "\u5929\u4f51\u5be8"
    ],
    "wof:name":"Tianyouzhai",
    "wof:placetype":"locality"
},
  "geometry": {"coordinates":[104.86799999999999,29.7196],"type":"Point"}
}