{
  "type": "Feature",
  "properties": {
    "gn:admin1_code":"3.0",
    "gn:asciiname":"Neilingli",
    "gn:country_code":"CN",
    "gn:dem":52,
    "gn:feature_class":"P",
    "gn:feature_code":"PPL",
    "gn:name":"Neilingli",
    "gn:population":0,
    "gn:timezone":"Asia/Shanghai",
    "iso:country":"CN",
    "name:und_x_variant":[
        "\u5185\u5cad\u91cc"
    ],
    "wof:name":"Neilingli",
    "wof:placetype":"locality"
},
  "geometry": {"coordinates":[115.13979999999999,28.35261],"type":"Point"}
}