{
  "type": "Feature",
  "properties": {
    "iso:country":"CN",
    "name:ara_x_preferred":[
        "\u062c\u064a\u0646\u0634\u0649"
    ],
    "name:ben_x_preferred":[
        "\u099c\u09bf\u09a8\u09b6\u09bf"
    ],
    "name:ell_x_preferred":[
        "\u03a4\u03b6\u03af\u03bd\u03be\u03b9"
    ],
    "name:eng_x_preferred":[
        "Jinxi"
    ],
    "name:fas_x_preferred":[
        "\u062c\u06cc\u0646\u06a9\u0633\u06cc"
    ],
    "name:heb_x_preferred":[
        "\u05d2'\u05d9\u05e0\u05e7\u05e1\u05d9"
    ],
    "name:hin_x_preferred":[
        "\u091c\u093f\u0902\u0915\u094d\u0938\u0940"
    ],
    "name:hun_x_preferred":[
        "Csinhszi"
    ],
    "name:ind_x_preferred":[
        "Jinxi"
    ],
    "name:ita_x_preferred":[
        "Jinxi"
    ],
    "name:jpn_x_preferred":[
        "\u9326\u6e13\u93ae"
    ],
    "name:kor_x_preferred":[
        "\uc9c4\uc2dc"
    ],
    "name:nld_x_preferred":[
        "Jinxi"
    ],
    "name:pol_x_preferred":[
        "Jinxi"
    ],
    "name:rus_x_preferred":[
        "\u0426\u0437\u0438\u043d\u044c\u0441\u0438"
    ],
    "name:swe_x_preferred":[
        "Jinxi"
    ],
    "name:tur_x_preferred":[
        "Jinxi"
    ],
    "name:ukr_x_preferred":[
        "\u0426\u0437\u0438\u043d\u044c\u0441\u0456"
    ],
    "name:urd_x_preferred":[
        "\u062c\u0646\u0632\u06cc"
    ],
    "name:vie_x_preferred":[
        "Kim Kh\u00ea"
    ],
    "name:zho_cn_x_preferred":[
        "\u9526\u6eaa"
    ],
    "name:zho_tw_x_preferred":[
        "\u9326\u6eaa"
    ],
    "name:zho_x_preferred":[
        "\u9526\u897f\u5e02"
    ],
    "qs:name":"\u9526\u897f\u5e02",
    "qs:name_adm0":"\u4e2d\u570b",
    "qs:name_adm1":"\u8fbd\u5b81\u7701",
    "qs:photos":40,
    "qs:photos_1k":8,
    "qs:photos_9k":1,
    "qs:photos_9r":2,
    "qs:photos_all":40,
    "qs:photos_sr":2,
    "qs:placetype":"Town",
    "qs:pop_sr":"0",
    "wof:name":"Jinxi",
    "wof:placetype":"locality"
},
  "geometry": {"coordinates":[120.852355,40.741014],"type":"Point"}
}