{
  "type": "Feature",
  "properties": {
    "iso:country":"CN",
    "qs:name":"\u9526\u897f\u5e02",
    "qs:name_adm0":"\u4e2d\u570b",
    "qs:name_adm1":"\u8fbd\u5b81\u7701",
    "qs:photos":40,
    "qs:photos_1k":8,
    "qs:photos_9k":1,
    "qs:photos_9r":2,
    "qs:photos_all":40,
    "qs:photos_sr":2,
    "qs:placetype":"Town",
    "qs:pop_sr":"0",
    "wof:name":"\u9526\u897f\u5e02",
    "wof:placetype":"locality"
},
  "geometry": {"coordinates":[120.852355,40.741014],"type":"Point"}
}