{
  "type": "Feature",
  "properties": {
    "gn:admin1_code":"24.0",
    "gn:asciiname":"Erfenguan",
    "gn:country_code":"CN",
    "gn:dem":1327,
    "gn:feature_class":"P",
    "gn:feature_code":"PPL",
    "gn:name":"Erfenguan",
    "gn:population":0,
    "gn:timezone":"Asia/Shanghai",
    "iso:country":"CN",
    "name:zho_x_preferred":[
        "\u4e8c\u5206\u5173"
    ],
    "wof:name":"Erfenguan",
    "wof:placetype":"locality"
},
  "geometry": {"coordinates":[112.28148,40.19864000000001],"type":"Point"}
}