{
  "type": "Feature",
  "properties": {
    "gn:admin1_code":"9.0",
    "gn:asciiname":"Yangshugou",
    "gn:country_code":"CN",
    "gn:dem":611,
    "gn:feature_class":"P",
    "gn:feature_code":"PPL",
    "gn:name":"Yangshugou",
    "gn:population":0,
    "gn:timezone":"Asia/Shanghai",
    "iso:country":"CN",
    "name:und_x_variant":[
        "\u6768\u6811\u6c9f",
        "Yangshugou"
    ],
    "wof:name":"Yangshugou",
    "wof:placetype":"locality"
},
  "geometry": {"coordinates":[112.48677000000001,33.88356],"type":"Point"}
}