{
  "type": "Feature",
  "properties": {
    "gn:admin1_code":"24.0",
    "gn:asciiname":"Beilantai",
    "gn:country_code":"CN",
    "gn:dem":768,
    "gn:feature_class":"P",
    "gn:feature_code":"PPL",
    "gn:name":"Beilantai",
    "gn:population":0,
    "gn:timezone":"Asia/Shanghai",
    "iso:country":"CN",
    "name:zho_x_preferred":[
        "\u5317\u5170\u53f0"
    ],
    "wof:name":"Beilantai",
    "wof:placetype":"locality"
},
  "geometry": {"coordinates":[112.85165000000001,38.50572],"type":"Point"}
}