{
  "type": "Feature",
  "properties": {
    "gn:admin1_code":"4.0",
    "gn:asciiname":"Qinxingcun",
    "gn:country_code":"CN",
    "gn:dem":0,
    "gn:feature_class":"P",
    "gn:feature_code":"PPL",
    "gn:name":"Qinxingcun",
    "gn:population":0,
    "gn:timezone":"Asia/Shanghai",
    "iso:country":"CN",
    "name:zho_x_preferred":[
        "\u79e6\u5174\u6751"
    ],
    "wof:name":"Qinxingcun",
    "wof:placetype":"locality"
},
  "geometry": {"coordinates":[119.95708999999999,33.31769],"type":"Point"}
}