{
  "type": "Feature",
  "properties": {
    "gn:admin1_code":"29.0",
    "gn:asciiname":"Xindifang",
    "gn:country_code":"CN",
    "gn:dem":559,
    "gn:feature_class":"P",
    "gn:feature_code":"PPL",
    "gn:name":"Xindifang",
    "gn:population":0,
    "gn:timezone":"Asia/Shanghai",
    "iso:country":"CN",
    "name:zho_x_preferred":[
        "\u65b0\u5730\u623f"
    ],
    "wof:name":"Xindifang",
    "wof:placetype":"locality"
},
  "geometry": {"coordinates":[103.92100000000001,22.9289],"type":"Point"}
}