{
  "type": "Feature",
  "properties": {
    "gn:admin1_code":"12.0",
    "gn:asciiname":"Hongjiapo",
    "gn:country_code":"CN",
    "gn:dem":724,
    "gn:feature_class":"P",
    "gn:feature_code":"PPL",
    "gn:name":"Hongjiapo",
    "gn:population":0,
    "gn:timezone":"Asia/Shanghai",
    "iso:country":"CN",
    "name:zho_x_preferred":[
        "\u6d2a\u5bb6\u5761"
    ],
    "wof:name":"Hongjiapo",
    "wof:placetype":"locality"
},
  "geometry": {"coordinates":[109.87564,33.14049],"type":"Point"}
}