{
  "type": "Feature",
  "properties": {
    "gn:admin1_code":"2",
    "gn:asciiname":"Xiaojitou",
    "gn:country_code":"CN",
    "gn:dem":1061,
    "gn:feature_class":"P",
    "gn:feature_code":"PPL",
    "gn:name":"Xiaojitou",
    "gn:population":0,
    "gn:timezone":"Asia/Shanghai",
    "iso:country":"CN",
    "name:und_x_variant":[
        "\u5c0f\u9645\u5934"
    ],
    "wof:name":"Xiaojitou",
    "wof:placetype":"locality"
},
  "geometry": {"coordinates":[119.19472,27.52194],"type":"Point"}
}