{
  "type": "Feature",
  "properties": {
    "gn:admin1_code":"32.0",
    "gn:asciiname":"Qiaodun",
    "gn:country_code":"CN",
    "gn:dem":594,
    "gn:feature_class":"P",
    "gn:feature_code":"PPL",
    "gn:name":"Qiaodun",
    "gn:population":0,
    "gn:timezone":"Asia/Shanghai",
    "iso:country":"CN",
    "name:zho_x_preferred":[
        "\u6865\u58a9"
    ],
    "wof:name":"Qiaodun",
    "wof:placetype":"locality"
},
  "geometry": {"coordinates":[103.453,30.2443],"type":"Point"}
}