{
  "type": "Feature",
  "properties": {
    "gn:admin1_code":"10",
    "gn:asciiname":"Shangwopu",
    "gn:country_code":"CN",
    "gn:dem":1573,
    "gn:feature_class":"P",
    "gn:feature_code":"PPL",
    "gn:name":"Shangwopu",
    "gn:population":0,
    "gn:timezone":"Asia/Shanghai",
    "iso:country":"CN",
    "name:zho_x_preferred":[
        "\u4e0a\u7a9d\u94fa"
    ],
    "wof:name":"Shangwopu",
    "wof:placetype":"locality"
},
  "geometry": {"coordinates":[116.08644,41.59182],"type":"Point"}
}