{
  "type": "Feature",
  "properties": {
    "gn:admin1_code":"02",
    "gn:asciiname":"Shibaga",
    "gn:cc2":"CN",
    "gn:country_code":"CN",
    "gn:dem":128,
    "gn:feature_class":"P",
    "gn:feature_code":"PPL",
    "gn:name":"Shibaga",
    "gn:population":0,
    "gn:timezone":"Asia/Shanghai",
    "iso:country":"CN",
    "name:und_x_variant":[
        "Shang-shih-pa-ts\u2019un",
        "Shibaga"
    ],
    "wof:name":"Shibaga",
    "wof:placetype":"locality"
},
  "geometry": {"coordinates":[120.94194,28.14944],"type":"Point"}
}