{
  "type": "Feature",
  "properties": {
    "gn:admin1_code":"16.0",
    "gn:asciiname":"Wanjiang",
    "gn:country_code":"CN",
    "gn:dem":768,
    "gn:feature_class":"P",
    "gn:feature_code":"PPL",
    "gn:name":"Wanjiang",
    "gn:population":0,
    "gn:timezone":"Asia/Shanghai",
    "iso:country":"CN",
    "name:zho_x_preferred":[
        "\u665a\u6c5f"
    ],
    "wof:name":"Wanjiang",
    "wof:placetype":"locality"
},
  "geometry": {"coordinates":[106.55200000000001,23.1338],"type":"Point"}
}