{
  "type": "Feature",
  "properties": {
    "gn:admin1_code":"25.0",
    "gn:asciiname":"Jingquan",
    "gn:country_code":"CN",
    "gn:dem":164,
    "gn:feature_class":"P",
    "gn:feature_code":"PPL",
    "gn:name":"Jingquan",
    "gn:population":0,
    "gn:timezone":"Asia/Shanghai",
    "iso:country":"CN",
    "name:zho_x_preferred":[
        "\u6676\u6cc9"
    ],
    "wof:name":"Jingquan",
    "wof:placetype":"locality"
},
  "geometry": {"coordinates":[121.06018,37.04825],"type":"Point"}
}