{
  "type": "Feature",
  "properties": {
    "gn:admin1_code":"23.0",
    "gn:asciiname":"Sanguang",
    "gn:country_code":"CN",
    "gn:dem":7,
    "gn:feature_class":"P",
    "gn:feature_code":"PPL",
    "gn:name":"Sanguang",
    "gn:population":0,
    "gn:timezone":"Asia/Shanghai",
    "iso:country":"CN",
    "name:zho_x_preferred":[
        "Sanguang"
    ],
    "name:zho_x_variant":[
        "\u4e09\u5149"
    ],
    "wof:name":"Sanguang",
    "wof:placetype":"locality"
},
  "geometry": {"coordinates":[121.26419,31.77983],"type":"Point"}
}