{
  "type": "Feature",
  "properties": {
    "gn:admin1_code":"8.0",
    "gn:asciiname":"Yanjiang",
    "gn:country_code":"CN",
    "gn:dem":85,
    "gn:feature_class":"P",
    "gn:feature_code":"PPLA4",
    "gn:name":"Yanjiang",
    "gn:population":0,
    "gn:timezone":"Asia/Shanghai",
    "iso:country":"CN",
    "name:und_x_variant":[
        "Yanjiang Xiang"
    ],
    "name:zho_x_preferred":[
        "\u6cbf\u6c5f"
    ],
    "name:zho_x_variant":[
        "\u6cbf\u6c5f\u4e61"
    ],
    "wof:name":"Yanjiang",
    "wof:placetype":"locality"
},
  "geometry": {"coordinates":[130.21043999999998,46.7919],"type":"Point"}
}