{
  "type": "Feature",
  "properties": {
    "gn:admin1_code":"8.0",
    "gn:asciiname":"Hongyang Dadui Qingniandian",
    "gn:country_code":"CN",
    "gn:dem":167,
    "gn:feature_class":"P",
    "gn:feature_code":"PPL",
    "gn:name":"Hongyang Dadui Qingniandian",
    "gn:population":0,
    "gn:timezone":"Asia/Shanghai",
    "iso:country":"CN",
    "name:zho_x_preferred":[
        "\u7ea2\u9633\u5927\u961f\u9752\u5e74\u70b9"
    ],
    "wof:name":"Hongyang Dadui Qingniandian",
    "wof:placetype":"locality"
},
  "geometry": {"coordinates":[125.26406,47.32348],"type":"Point"}
}