{
  "type": "Feature",
  "properties": {
    "gn:admin1_code":"3.0",
    "gn:asciiname":"Shuikouwancun",
    "gn:country_code":"CN",
    "gn:dem":19,
    "gn:feature_class":"P",
    "gn:feature_code":"PPL",
    "gn:name":"Shuikouwancun",
    "gn:population":0,
    "gn:timezone":"Asia/Shanghai",
    "iso:country":"CN",
    "name:zho_x_preferred":[
        "\u6c34\u53e3\u4e07\u6751"
    ],
    "wof:name":"Shuikouwancun",
    "wof:placetype":"locality"
},
  "geometry": {"coordinates":[116.12029,28.72623],"type":"Point"}
}