{
  "type": "Feature",
  "properties": {
    "gn:admin1_code":"26.0",
    "gn:asciiname":"Mahewan",
    "gn:country_code":"CN",
    "gn:dem":1256,
    "gn:feature_class":"P",
    "gn:feature_code":"PPL",
    "gn:name":"Mahewan",
    "gn:population":0,
    "gn:timezone":"Asia/Shanghai",
    "iso:country":"CN",
    "name:zho_x_preferred":[
        "\u9a6c\u548c\u6e7e"
    ],
    "wof:name":"Mahewan",
    "wof:placetype":"locality"
},
  "geometry": {"coordinates":[109.24290999999999,36.90022],"type":"Point"}
}