{
  "type": "Feature",
  "properties": {
    "gn:admin1_code":"5.0",
    "gn:asciiname":"Xinjian Linchang",
    "gn:country_code":"CN",
    "gn:dem":560,
    "gn:feature_class":"P",
    "gn:feature_code":"PPLF",
    "gn:name":"Xinjian Linchang",
    "gn:population":0,
    "gn:timezone":"Asia/Shanghai",
    "iso:country":"CN",
    "name:und_x_variant":[
        "\u65b0\u5efa\u6797\u573a"
    ],
    "wof:name":"Xinjian Linchang",
    "wof:placetype":"locality"
},
  "geometry": {"coordinates":[127.85778000000001,42.93281],"type":"Point"}
}