{
  "type": "Feature",
  "properties": {
    "gn:admin1_code":"26.0",
    "gn:asciiname":"Dongtumu",
    "gn:country_code":"CN",
    "gn:dem":1179,
    "gn:feature_class":"P",
    "gn:feature_code":"PPL",
    "gn:name":"Dongtumu",
    "gn:population":0,
    "gn:timezone":"Asia/Shanghai",
    "iso:country":"CN",
    "name:zho_x_preferred":[
        "\u4e1c\u571f\u6728"
    ],
    "wof:name":"Dongtumu",
    "wof:placetype":"locality"
},
  "geometry": {"coordinates":[109.55522000000001,38.48996],"type":"Point"}
}