{
  "type": "Feature",
  "properties": {
    "gn:admin1_code":"32.0",
    "gn:asciiname":"Chuanlin",
    "gn:country_code":"CN",
    "gn:dem":496,
    "gn:feature_class":"P",
    "gn:feature_code":"PPL",
    "gn:name":"Chuanlin",
    "gn:population":0,
    "gn:timezone":"Asia/Shanghai",
    "iso:country":"CN",
    "name:zho_x_preferred":[
        "\u8239\u6797"
    ],
    "wof:name":"Chuanlin",
    "wof:placetype":"locality"
},
  "geometry": {"coordinates":[105.15300000000001,31.4752],"type":"Point"}
}