{
  "type": "Feature",
  "properties": {
    "gn:admin1_code":"11.0",
    "gn:asciiname":"Fenxiang",
    "gn:country_code":"CN",
    "gn:dem":452,
    "gn:feature_class":"P",
    "gn:feature_code":"PPL",
    "gn:name":"Fenxiang",
    "gn:population":0,
    "gn:timezone":"Asia/Shanghai",
    "iso:country":"CN",
    "name:zho_x_preferred":[
        "\u82ac\u9999"
    ],
    "wof:name":"Fenxiang",
    "wof:placetype":"locality"
},
  "geometry": {"coordinates":[111.26752,25.8815],"type":"Point"}
}