{
  "type": "Feature",
  "properties": {
    "gn:admin1_code":"12.0",
    "gn:asciiname":"Beikou",
    "gn:country_code":"CN",
    "gn:dem":1097,
    "gn:feature_class":"P",
    "gn:feature_code":"PPL",
    "gn:name":"Beikou",
    "gn:population":0,
    "gn:timezone":"Asia/Shanghai",
    "iso:country":"CN",
    "name:zho_x_preferred":[
        "\u7891\u53e3"
    ],
    "wof:name":"Beikou",
    "wof:placetype":"locality"
},
  "geometry": {"coordinates":[110.50324000000001,31.91073],"type":"Point"}
}