{
  "type": "Feature",
  "properties": {
    "gn:admin1_code":"11.0",
    "gn:asciiname":"Dajiangbian",
    "gn:country_code":"CN",
    "gn:dem":1251,
    "gn:feature_class":"P",
    "gn:feature_code":"PPL",
    "gn:name":"Dajiangbian",
    "gn:population":0,
    "gn:timezone":"Asia/Shanghai",
    "iso:country":"CN",
    "name:zho_x_preferred":[
        "\u5927\u6c5f\u8fb9"
    ],
    "wof:name":"Dajiangbian",
    "wof:placetype":"locality"
},
  "geometry": {"coordinates":[110.52332,26.3843],"type":"Point"}
}