{
  "type": "Feature",
  "properties": {
    "gn:admin1_code":"2.0",
    "gn:asciiname":"Huaihuashu",
    "gn:country_code":"CN",
    "gn:dem":556,
    "gn:feature_class":"P",
    "gn:feature_code":"PPL",
    "gn:name":"Huaihuashu",
    "gn:population":0,
    "gn:timezone":"Asia/Shanghai",
    "iso:country":"CN",
    "name:zho_x_preferred":[
        "\u69d0\u82b1\u6811"
    ],
    "wof:name":"Huaihuashu",
    "wof:placetype":"locality"
},
  "geometry": {"coordinates":[120.30919,28.78556],"type":"Point"}
}