{
  "type": "Feature",
  "properties": {
    "gn:admin1_code":"3.0",
    "gn:asciiname":"Guosicun",
    "gn:country_code":"CN",
    "gn:dem":27,
    "gn:feature_class":"P",
    "gn:feature_code":"PPL",
    "gn:name":"Guosicun",
    "gn:population":0,
    "gn:timezone":"Asia/Shanghai",
    "iso:country":"CN",
    "name:und_x_variant":[
        "\u90ed\u6cd7\u6751"
    ],
    "wof:name":"Guosicun",
    "wof:placetype":"locality"
},
  "geometry": {"coordinates":[116.52784,28.64095],"type":"Point"}
}