{
  "type": "Feature",
  "properties": {
    "gn:admin1_code":"16.0",
    "gn:asciiname":"Longfeng",
    "gn:country_code":"CN",
    "gn:dem":60,
    "gn:feature_class":"P",
    "gn:feature_code":"PPL",
    "gn:name":"Longfeng",
    "gn:population":0,
    "gn:timezone":"Asia/Shanghai",
    "iso:country":"CN",
    "name:ceb_x_preferred":[
        "Longfeng"
    ],
    "name:deu_x_preferred":[
        "Longfeng"
    ],
    "name:mlg_x_preferred":[
        "Longfeng"
    ],
    "name:zho_x_preferred":[
        "\u9f99\u51e4"
    ],
    "wof:name":"Longfeng",
    "wof:placetype":"locality"
},
  "geometry": {"coordinates":[110.721,23.121],"type":"Point"}
}