{
  "type": "Feature",
  "properties": {
    "gn:admin1_code":"29",
    "gn:asciiname":"Heiyicang",
    "gn:country_code":"CN",
    "gn:dem":1815,
    "gn:feature_class":"P",
    "gn:feature_code":"PPL",
    "gn:name":"Heiyicang",
    "gn:population":0,
    "gn:timezone":"Asia/Shanghai",
    "iso:country":"CN",
    "name:zho_x_preferred":[
        "\u9ed1\u9091\u82cd"
    ],
    "wof:name":"Heiyicang",
    "wof:placetype":"locality"
},
  "geometry": {"coordinates":[101.59,24.9718],"type":"Point"}
}