{
  "type": "Feature",
  "properties": {
    "gn:admin1_code":"10",
    "gn:asciiname":"Hetaomu",
    "gn:country_code":"CN",
    "gn:dem":957,
    "gn:feature_class":"P",
    "gn:feature_code":"PPL",
    "gn:name":"Hetaomu",
    "gn:population":0,
    "gn:timezone":"Asia/Shanghai",
    "iso:country":"CN",
    "name:zho_x_preferred":[
        "\u6838\u6843\u6728"
    ],
    "wof:name":"Hetaomu",
    "wof:placetype":"locality"
},
  "geometry": {"coordinates":[118.07846000000001,42.09325],"type":"Point"}
}