{
  "type": "Feature",
  "properties": {
    "gn:admin1_code":"12.0",
    "gn:asciiname":"Jieshou",
    "gn:country_code":"CN",
    "gn:dem":444,
    "gn:feature_class":"P",
    "gn:feature_code":"PPL",
    "gn:name":"Jieshou",
    "gn:population":0,
    "gn:timezone":"Asia/Shanghai",
    "iso:country":"CN",
    "name:zho_x_preferred":[
        "Jieshou"
    ],
    "name:zho_x_variant":[
        "\u754c\u9996"
    ],
    "wof:name":"Jieshou",
    "wof:placetype":"locality"
},
  "geometry": {"coordinates":[114.91604,29.66],"type":"Point"}
}