{
  "type": "Feature",
  "properties": {
    "gn:admin1_code":"24.0",
    "gn:asciiname":"Xinglin",
    "gn:country_code":"CN",
    "gn:dem":464,
    "gn:feature_class":"P",
    "gn:feature_code":"PPL",
    "gn:name":"Xinglin",
    "gn:population":0,
    "gn:timezone":"Asia/Shanghai",
    "iso:country":"CN",
    "name:und_x_variant":[
        "\u674f\u6797"
    ],
    "wof:name":"Xinglin",
    "wof:placetype":"locality"
},
  "geometry": {"coordinates":[111.13581000000001,35.71337],"type":"Point"}
}