{
  "type": "Feature",
  "properties": {
    "gn:admin1_code":"29.0",
    "gn:asciiname":"Zhengjia",
    "gn:country_code":"CN",
    "gn:dem":1934,
    "gn:feature_class":"P",
    "gn:feature_code":"PPL",
    "gn:name":"Zhengjia",
    "gn:population":0,
    "gn:timezone":"Asia/Shanghai",
    "iso:country":"CN",
    "name:zho_x_preferred":[
        "\u90d1\u5bb6"
    ],
    "wof:name":"Zhengjia",
    "wof:placetype":"locality"
},
  "geometry": {"coordinates":[101.157,25.4228],"type":"Point"}
}