{
  "type": "Feature",
  "properties": {
    "gn:admin1_code":"26.0",
    "gn:asciiname":"Yuxingzhuang",
    "gn:cc2":"CN",
    "gn:country_code":"CN",
    "gn:dem":1092,
    "gn:feature_class":"P",
    "gn:feature_code":"PPL",
    "gn:name":"Yuxingzhuang",
    "gn:population":0,
    "gn:timezone":"Asia/Shanghai",
    "iso:country":"CN",
    "name:und_x_variant":[
        "Y\u00fc-hsing-chuang",
        "Yuxingzhuang"
    ],
    "wof:name":"Yuxingzhuang",
    "wof:placetype":"locality"
},
  "geometry": {"coordinates":[109.93222,38.15083],"type":"Point"}
}