{
  "type": "Feature",
  "properties": {
    "gn:admin1_code":"4.0",
    "gn:asciiname":"Tiaohe",
    "gn:country_code":"CN",
    "gn:dem":0,
    "gn:feature_class":"P",
    "gn:feature_code":"PPL",
    "gn:name":"Tiaohe",
    "gn:population":0,
    "gn:timezone":"Asia/Shanghai",
    "iso:country":"CN",
    "name:zho_x_preferred":[
        "Tiaohe"
    ],
    "name:zho_x_variant":[
        "\u6761\u6cb3"
    ],
    "wof:name":"Tiaohe",
    "wof:placetype":"locality"
},
  "geometry": {"coordinates":[119.01675,34.45767],"type":"Point"}
}