{
  "type": "Feature",
  "properties": {
    "gn:admin1_code":"10.0",
    "gn:asciiname":"Qianpeizhuang",
    "gn:country_code":"CN",
    "gn:dem":69,
    "gn:feature_class":"P",
    "gn:feature_code":"PPL",
    "gn:name":"Qianpeizhuang",
    "gn:population":0,
    "gn:timezone":"Asia/Shanghai",
    "iso:country":"CN",
    "name:zho_x_preferred":[
        "\u524d\u88f4\u5e84"
    ],
    "wof:name":"Qianpeizhuang",
    "wof:placetype":"locality"
},
  "geometry": {"coordinates":[118.60057,40.08434000000001],"type":"Point"}
}