{
  "type": "Feature",
  "properties": {
    "gn:admin1_code":"29.0",
    "gn:asciiname":"Mugudi",
    "gn:country_code":"CN",
    "gn:dem":1803,
    "gn:feature_class":"P",
    "gn:feature_code":"PPL",
    "gn:name":"Mugudi",
    "gn:population":0,
    "gn:timezone":"Asia/Shanghai",
    "iso:country":"CN",
    "name:zho_x_preferred":[
        "\u4ea9\u8c37\u5730"
    ],
    "wof:name":"Mugudi",
    "wof:placetype":"locality"
},
  "geometry": {"coordinates":[100.974,25.4568],"type":"Point"}
}