{
  "type": "Feature",
  "properties": {
    "gn:admin1_code":"11",
    "gn:asciiname":"Haojiping Yaozuxiang",
    "gn:country_code":"CN",
    "gn:dem":733,
    "gn:feature_class":"P",
    "gn:feature_code":"PPL",
    "gn:name":"Haojiping Yaozuxiang",
    "gn:population":0,
    "gn:timezone":"Asia/Shanghai",
    "iso:country":"CN",
    "wof:name":"Haojiping Yaozuxiang",
    "wof:placetype":"locality"
},
  "geometry": {"coordinates":[110.43361000000002,27.58],"type":"Point"}
}