{
  "type": "Feature",
  "properties": {
    "gn:admin1_code":"32.0",
    "gn:asciiname":"Lian'erwa",
    "gn:country_code":"CN",
    "gn:dem":1921,
    "gn:feature_class":"P",
    "gn:feature_code":"PPL",
    "gn:name":"Lian\u2019erwa",
    "gn:population":0,
    "gn:timezone":"Asia/Shanghai",
    "iso:country":"CN",
    "name:und_x_variant":[
        "Lian\u2019erwa"
    ],
    "name:zho_x_preferred":[
        "\u8fde\u4e8c\u74e6"
    ],
    "wof:name":"Lian'erwa",
    "wof:placetype":"locality"
},
  "geometry": {"coordinates":[102.208,28.4325],"type":"Point"}
}