{
  "type": "Feature",
  "properties": {
    "gn:admin1_code":"15.0",
    "gn:asciiname":"Wujia Shawo",
    "gn:country_code":"CN",
    "gn:dem":1339,
    "gn:feature_class":"P",
    "gn:feature_code":"PPL",
    "gn:name":"Wujia Shawo",
    "gn:population":0,
    "gn:timezone":"Asia/Urumqi",
    "iso:country":"CN",
    "name:zho_x_preferred":[
        "\u5434\u5bb6\u6c99\u7a9d"
    ],
    "wof:name":"Wujia Shawo",
    "wof:placetype":"locality"
},
  "geometry": {"coordinates":[96.2439,40.3462],"type":"Point"}
}