{
  "type": "Feature",
  "properties": {
    "gn:admin1_code":"26",
    "gn:asciiname":"Changtanba",
    "gn:cc2":"CN",
    "gn:country_code":"CN",
    "gn:dem":822,
    "gn:feature_class":"P",
    "gn:feature_code":"PPL",
    "gn:name":"Changtanba",
    "gn:population":0,
    "gn:timezone":"Asia/Shanghai",
    "iso:country":"CN",
    "name:und_x_variant":[
        "Ch\u2019ang-t\u2019an-pa",
        "Changtanba"
    ],
    "wof:name":"Changtanba",
    "wof:placetype":"locality"
},
  "geometry": {"coordinates":[107.89388999999998,32.25028],"type":"Point"}
}