{
  "type": "Feature",
  "properties": {
    "gn:admin1_code":"19.0",
    "gn:asciiname":"Songgangbucun",
    "gn:country_code":"CN",
    "gn:dem":123,
    "gn:feature_class":"P",
    "gn:feature_code":"PPL",
    "gn:name":"Songgangbucun",
    "gn:population":0,
    "gn:timezone":"Asia/Shanghai",
    "iso:country":"CN",
    "name:und_x_variant":[
        "Songgangbaocun",
        "\u677e\u5c97\u5821\u6751",
        "Songgangbucun"
    ],
    "name:zho_x_preferred":[
        "\u677e\u5c97\u5821\u6751"
    ],
    "wof:name":"Songgangbucun",
    "wof:placetype":"locality"
},
  "geometry": {"coordinates":[123.8015,41.68315],"type":"Point"}
}