{
  "type": "Feature",
  "properties": {
    "gn:admin1_code":"18.0",
    "gn:asciiname":"Shipuyang",
    "gn:country_code":"CN",
    "gn:dem":1003,
    "gn:feature_class":"P",
    "gn:feature_code":"PPL",
    "gn:name":"Shipuyang",
    "gn:population":0,
    "gn:timezone":"Asia/Shanghai",
    "iso:country":"CN",
    "name:zho_x_preferred":[
        "\u72ee\u6251\u9633"
    ],
    "wof:name":"Shipuyang",
    "wof:placetype":"locality"
},
  "geometry": {"coordinates":[107.16,26.5359],"type":"Point"}
}