{
  "type": "Feature",
  "properties": {
    "gn:admin1_code":"4.0",
    "gn:asciiname":"Yingxiangxiang",
    "gn:country_code":"CN",
    "gn:dem":16,
    "gn:feature_class":"P",
    "gn:feature_code":"PPL",
    "gn:name":"Yingxiangxiang",
    "gn:population":0,
    "gn:timezone":"Asia/Shanghai",
    "iso:country":"CN",
    "name:zho_x_preferred":[
        "\u8fce\u7965\u5df7"
    ],
    "wof:name":"Yingxiangxiang",
    "wof:placetype":"locality"
},
  "geometry": {"coordinates":[119.06083999999998,31.74939],"type":"Point"}
}