{
  "type": "Feature",
  "properties": {
    "gn:admin1_code":"5.0",
    "gn:asciiname":"Wangzifen",
    "gn:country_code":"CN",
    "gn:dem":252,
    "gn:feature_class":"P",
    "gn:feature_code":"PPL",
    "gn:name":"Wangzifen",
    "gn:population":0,
    "gn:timezone":"Asia/Shanghai",
    "iso:country":"CN",
    "name:zho_x_preferred":[
        "\u738b\u5b50\u575f"
    ],
    "wof:name":"Wangzifen",
    "wof:placetype":"locality"
},
  "geometry": {"coordinates":[124.54788000000001,44.06884],"type":"Point"}
}