{
  "type": "Feature",
  "properties": {
    "gn:admin1_code":"01",
    "gn:asciiname":"Tingtancun",
    "gn:country_code":"CN",
    "gn:dem":95,
    "gn:feature_class":"P",
    "gn:feature_code":"PPL",
    "gn:name":"Tingtancun",
    "gn:population":0,
    "gn:timezone":"Asia/Shanghai",
    "iso:country":"CN",
    "name:und_x_variant":[
        "T\u2019ing-t\u2019an-chen",
        "Tingtan",
        "\u6c40\u6f6d",
        "Tingtancun"
    ],
    "name:zho_x_preferred":[
        "\u6c40\u6f6d\u6751"
    ],
    "wof:name":"Tingtancun",
    "wof:placetype":"locality"
},
  "geometry": {"coordinates":[118.25787,30.7019],"type":"Point"}
}