{
  "type": "Feature",
  "properties": {
    "gn:admin1_code":"15.0",
    "gn:asciiname":"Hongqu",
    "gn:country_code":"CN",
    "gn:dem":1575,
    "gn:feature_class":"P",
    "gn:feature_code":"PPL",
    "gn:name":"Hongqu",
    "gn:population":0,
    "gn:timezone":"Asia/Shanghai",
    "iso:country":"CN",
    "name:zho_x_preferred":[
        "\u7ea2\u6e20"
    ],
    "wof:name":"Hongqu",
    "wof:placetype":"locality"
},
  "geometry": {"coordinates":[104.48,36.6772],"type":"Point"}
}