{
  "type": "Feature",
  "properties": {
    "gn:admin1_code":"19.0",
    "gn:asciiname":"Baicangyingzi",
    "gn:country_code":"CN",
    "gn:dem":191,
    "gn:feature_class":"P",
    "gn:feature_code":"PPL",
    "gn:name":"Baicangyingzi",
    "gn:population":0,
    "gn:timezone":"Asia/Shanghai",
    "iso:country":"CN",
    "name:zho_x_preferred":[
        "\u767d\u82cd\u8425\u5b50"
    ],
    "wof:name":"Baicangyingzi",
    "wof:placetype":"locality"
},
  "geometry": {"coordinates":[120.992,42.0087],"type":"Point"}
}