{
  "type": "Feature",
  "properties": {
    "gn:admin1_code":"4.0",
    "gn:asciiname":"Dongfengduncun",
    "gn:country_code":"CN",
    "gn:dem":8,
    "gn:feature_class":"P",
    "gn:feature_code":"PPL",
    "gn:name":"Dongfengduncun",
    "gn:population":0,
    "gn:timezone":"Asia/Shanghai",
    "iso:country":"CN",
    "name:zho_x_preferred":[
        "\u4e1c\u4e30\u58a9\u6751"
    ],
    "wof:name":"Dongfengduncun",
    "wof:placetype":"locality"
},
  "geometry": {"coordinates":[118.82849,34.6355],"type":"Point"}
}