{
  "type": "Feature",
  "properties": {
    "gn:admin1_code":"29.0",
    "gn:asciiname":"Xinwafang",
    "gn:country_code":"CN",
    "gn:dem":1289,
    "gn:feature_class":"P",
    "gn:feature_code":"PPL",
    "gn:name":"Xinwafang",
    "gn:population":0,
    "gn:timezone":"Asia/Shanghai",
    "iso:country":"CN",
    "name:zho_x_preferred":[
        "\u65b0\u74e6\u623f"
    ],
    "wof:name":"Xinwafang",
    "wof:placetype":"locality"
},
  "geometry": {"coordinates":[103.286,23.4302],"type":"Point"}
}