{
  "type": "Feature",
  "properties": {
    "gn:admin1_code":"3.0",
    "gn:asciiname":"Goutang",
    "gn:country_code":"CN",
    "gn:dem":59,
    "gn:feature_class":"P",
    "gn:feature_code":"PPL",
    "gn:name":"Goutang",
    "gn:population":0,
    "gn:timezone":"Asia/Shanghai",
    "iso:country":"CN",
    "name:und_x_variant":[
        "\u94a9\u5858"
    ],
    "wof:name":"Goutang",
    "wof:placetype":"locality"
},
  "geometry": {"coordinates":[115.02162,28.20782],"type":"Point"}
}