{
  "type": "Feature",
  "properties": {
    "gn:admin1_code":"10.0",
    "gn:asciiname":"Nanxinzhuang",
    "gn:country_code":"CN",
    "gn:dem":1589,
    "gn:feature_class":"P",
    "gn:feature_code":"PPL",
    "gn:name":"Nanxinzhuang",
    "gn:population":0,
    "gn:timezone":"Asia/Shanghai",
    "iso:country":"CN",
    "name:zho_x_preferred":[
        "\u5357\u8f9b\u5e84"
    ],
    "wof:name":"Nanxinzhuang",
    "wof:placetype":"locality"
},
  "geometry": {"coordinates":[113.83528,38.98705],"type":"Point"}
}