{
  "type": "Feature",
  "properties": {
    "gn:admin1_code":"29.0",
    "gn:asciiname":"Lagan",
    "gn:country_code":"CN",
    "gn:dem":1030,
    "gn:feature_class":"P",
    "gn:feature_code":"PPL",
    "gn:name":"Lagan",
    "gn:population":0,
    "gn:timezone":"Asia/Shanghai",
    "iso:country":"CN",
    "name:bul_x_preferred":[
        "\u041b\u0430\u0433\u0430\u043d"
    ],
    "name:ceb_x_preferred":[
        "Lagan"
    ],
    "name:deu_x_preferred":[
        "Lagan"
    ],
    "name:fin_x_preferred":[
        "Lagan"
    ],
    "name:fra_x_preferred":[
        "Lagan"
    ],
    "name:ita_x_preferred":[
        "Lagan"
    ],
    "name:nld_x_preferred":[
        "Lagan"
    ],
    "name:nno_x_preferred":[
        "Lagan"
    ],
    "name:nor_x_preferred":[
        "Lagan"
    ],
    "name:pol_x_preferred":[
        "Lagan"
    ],
    "name:slv_x_preferred":[
        "Lagan"
    ],
    "name:swe_x_preferred":[
        "Lagan"
    ],
    "name:ukr_x_preferred":[
        "\u041b\u0430\u0433\u0430\u043d"
    ],
    "name:zho_x_preferred":[
        "\u814a\u8d76"
    ],
    "wof:name":"Lagan",
    "wof:placetype":"locality"
},
  "geometry": {"coordinates":[100.256,21.7043],"type":"Point"}
}