{
  "type": "Feature",
  "properties": {
    "gn:admin1_code":"32",
    "gn:asciiname":"Qimulin",
    "gn:country_code":"CN",
    "gn:dem":1811,
    "gn:feature_class":"P",
    "gn:feature_code":"PPL",
    "gn:name":"Qimulin",
    "gn:population":0,
    "gn:timezone":"Asia/Shanghai",
    "iso:country":"CN",
    "name:zho_x_preferred":[
        "\u6864\u6728\u6797"
    ],
    "wof:name":"Qimulin",
    "wof:placetype":"locality"
},
  "geometry": {"coordinates":[101.74449,28.47288],"type":"Point"}
}