{
  "type": "Feature",
  "properties": {
    "gn:admin1_code":"4.0",
    "gn:asciiname":"Wanghong Shuangcun",
    "gn:country_code":"CN",
    "gn:dem":39,
    "gn:feature_class":"P",
    "gn:feature_code":"PPL",
    "gn:name":"Wanghong Shuangcun",
    "gn:population":0,
    "gn:timezone":"Asia/Shanghai",
    "iso:country":"CN",
    "name:zho_x_preferred":[
        "\u738b\u6d2a\u723d\u6751"
    ],
    "wof:name":"Wanghong Shuangcun",
    "wof:placetype":"locality"
},
  "geometry": {"coordinates":[118.86853000000001,34.89111],"type":"Point"}
}