{
  "type": "Feature",
  "properties": {
    "gn:admin1_code":"02",
    "gn:asciiname":"Shuangxicun",
    "gn:country_code":"CN",
    "gn:dem":14,
    "gn:feature_class":"P",
    "gn:feature_code":"PPL",
    "gn:name":"Shuangxicun",
    "gn:population":0,
    "gn:timezone":"Asia/Shanghai",
    "iso:country":"CN",
    "name:und_x_variant":[
        "Shuang-ch\u2019i",
        "Shuangxi",
        "Shuangxicun"
    ],
    "name:zho_x_preferred":[
        "\u53cc\u6eaa"
    ],
    "name:zho_x_variant":[
        "\u53cc\u6eaa\u6751"
    ],
    "wof:name":"Shuangxicun",
    "wof:placetype":"locality"
},
  "geometry": {"coordinates":[120.43908999999999,28.15509],"type":"Point"}
}