{
  "type": "Feature",
  "properties": {
    "gn:admin1_code":"19.0",
    "gn:asciiname":"Xiao'an",
    "gn:country_code":"CN",
    "gn:dem":545,
    "gn:feature_class":"P",
    "gn:feature_code":"PPL",
    "gn:name":"Xiao\u2019an",
    "gn:population":0,
    "gn:timezone":"Asia/Shanghai",
    "iso:country":"CN",
    "name:und_x_variant":[
        "\u5c0f\u978d"
    ],
    "name:zho_x_preferred":[
        "Xiao\u2019an"
    ],
    "name:zho_x_variant":[
        "\u5c0f\u978d"
    ],
    "wof:name":"Xiao'an",
    "wof:placetype":"locality"
},
  "geometry": {"coordinates":[119.654,40.4567],"type":"Point"}
}