{
  "type": "Feature",
  "properties": {
    "gn:admin1_code":"29.0",
    "gn:asciiname":"Duochecun",
    "gn:country_code":"CN",
    "gn:dem":2002,
    "gn:feature_class":"P",
    "gn:feature_code":"PPL",
    "gn:name":"Duochecun",
    "gn:population":0,
    "gn:timezone":"Asia/Shanghai",
    "iso:country":"CN",
    "name:zho_x_preferred":[
        "\u54c6\u8f66\u6751"
    ],
    "wof:name":"Duochecun",
    "wof:placetype":"locality"
},
  "geometry": {"coordinates":[102.926,27.2689],"type":"Point"}
}