{
  "type": "Feature",
  "properties": {
    "gn:admin1_code":"1.0",
    "gn:asciiname":"Pingshancun",
    "gn:country_code":"CN",
    "gn:dem":34,
    "gn:feature_class":"P",
    "gn:feature_code":"PPL",
    "gn:name":"Pingshancun",
    "gn:population":0,
    "gn:timezone":"Asia/Shanghai",
    "iso:country":"CN",
    "name:und_x_variant":[
        "Pingshan"
    ],
    "name:zho_x_preferred":[
        "\u5e73\u5c71\u6751"
    ],
    "wof:name":"Pingshancun",
    "wof:placetype":"locality"
},
  "geometry": {"coordinates":[116.82147000000001,33.82849],"type":"Point"}
}