{
  "type": "Feature",
  "properties": {
    "gn:admin1_code":"11.0",
    "gn:asciiname":"Lishupao",
    "gn:country_code":"CN",
    "gn:dem":907,
    "gn:feature_class":"P",
    "gn:feature_code":"PPL",
    "gn:name":"Lishupao",
    "gn:population":0,
    "gn:timezone":"Asia/Shanghai",
    "iso:country":"CN",
    "name:zho_x_preferred":[
        "\u6817\u6811\u5789"
    ],
    "wof:name":"Lishupao",
    "wof:placetype":"locality"
},
  "geometry": {"coordinates":[109.76576,29.63969],"type":"Point"}
}