{
  "type": "Feature",
  "properties": {
    "gn:admin1_code":"10.0",
    "gn:asciiname":"Diaonan",
    "gn:country_code":"CN",
    "gn:dem":15,
    "gn:feature_class":"P",
    "gn:feature_code":"PPL",
    "gn:name":"Diaonan",
    "gn:population":0,
    "gn:timezone":"Asia/Shanghai",
    "iso:country":"CN",
    "name:zho_x_preferred":[
        "\u5201\u5357"
    ],
    "wof:name":"Diaonan",
    "wof:placetype":"locality"
},
  "geometry": {"coordinates":[117.01300000000001,37.8556],"type":"Point"}
}