{
  "type": "Feature",
  "properties": {
    "gn:admin1_code":"32.0",
    "gn:asciiname":"Shigulu",
    "gn:country_code":"CN",
    "gn:dem":1859,
    "gn:feature_class":"P",
    "gn:feature_code":"PPL",
    "gn:name":"Shigulu",
    "gn:population":0,
    "gn:timezone":"Asia/Shanghai",
    "iso:country":"CN",
    "name:zho_x_preferred":[
        "\u77f3\u53e4\u8def"
    ],
    "wof:name":"Shigulu",
    "wof:placetype":"locality"
},
  "geometry": {"coordinates":[102.11709999999999,28.48462],"type":"Point"}
}