{
  "type": "Feature",
  "properties": {
    "gn:admin1_code":"15.0",
    "gn:asciiname":"Xiagaileng",
    "gn:country_code":"CN",
    "gn:dem":1411,
    "gn:feature_class":"P",
    "gn:feature_code":"PPL",
    "gn:name":"Xiagaileng",
    "gn:population":0,
    "gn:timezone":"Asia/Shanghai",
    "iso:country":"CN",
    "name:zho_x_preferred":[
        "\u4e0b\u76d6\u5844"
    ],
    "wof:name":"Xiagaileng",
    "wof:placetype":"locality"
},
  "geometry": {"coordinates":[106.985,35.7901],"type":"Point"}
}