{
  "type": "Feature",
  "properties": {
    "gn:admin1_code":"4.0",
    "gn:asciiname":"Jilingcun",
    "gn:country_code":"CN",
    "gn:dem":62,
    "gn:feature_class":"P",
    "gn:feature_code":"PPL",
    "gn:name":"Jilingcun",
    "gn:population":0,
    "gn:timezone":"Asia/Shanghai",
    "iso:country":"CN",
    "name:zho_x_preferred":[
        "\u5b63\u5cad\u6751"
    ],
    "wof:name":"Jilingcun",
    "wof:placetype":"locality"
},
  "geometry": {"coordinates":[118.6297,34.63269],"type":"Point"}
}