{
  "type": "Feature",
  "properties": {
    "gn:admin1_code":"19",
    "gn:asciiname":"Xixiang Dabucun",
    "gn:country_code":"CN",
    "gn:dem":335,
    "gn:feature_class":"P",
    "gn:feature_code":"PPL",
    "gn:name":"Xixiang Dabucun",
    "gn:population":0,
    "gn:timezone":"Asia/Shanghai",
    "iso:country":"CN",
    "name:und_x_variant":[
        "Xixiang Dapu",
        "\u897f\u53a2\u5927\u5821",
        "Xixiandapu",
        "Xixiang Dabu",
        "Xixiang Dabucun"
    ],
    "name:zho_x_preferred":[
        "\u897f\u53a2\u5927\u5821\u6751"
    ],
    "wof:name":"Xixiang Dabucun",
    "wof:placetype":"locality"
},
  "geometry": {"coordinates":[124.53959999999999,41.50335],"type":"Point"}
}