{
  "type": "Feature",
  "properties": {
    "gn:admin1_code":"07",
    "gn:asciiname":"Tadou",
    "gn:country_code":"CN",
    "gn:dem":220,
    "gn:feature_class":"P",
    "gn:feature_code":"PPLA4",
    "gn:name":"Tadou",
    "gn:population":0,
    "gn:timezone":"Asia/Shanghai",
    "iso:country":"CN",
    "name:und_x_variant":[
        "Lien-ho",
        "T\u2019a-tou",
        "Tadou",
        "\u5854\u515c",
        "Lianhe Xiang",
        "\u8054\u5408\u4e61"
    ],
    "wof:name":"Tadou",
    "wof:placetype":"locality"
},
  "geometry": {"coordinates":[118.22972,26.37157],"type":"Point"}
}