{
  "type": "Feature",
  "properties": {
    "gn:admin1_code":"26.0",
    "gn:asciiname":"Xi'alabu",
    "gn:country_code":"CN",
    "gn:dem":1296,
    "gn:feature_class":"P",
    "gn:feature_code":"PPL",
    "gn:name":"Xi\u2019alabu",
    "gn:population":0,
    "gn:timezone":"Asia/Shanghai",
    "iso:country":"CN",
    "name:und_x_variant":[
        "Xi\u2019alabu"
    ],
    "name:zho_x_preferred":[
        "\u897f\u554a\u62c9\u5821"
    ],
    "wof:name":"Xi'alabu",
    "wof:placetype":"locality"
},
  "geometry": {"coordinates":[109.819,38.7553],"type":"Point"}
}