{
  "type": "Feature",
  "properties": {
    "gn:admin1_code":"32.0",
    "gn:asciiname":"Songxin",
    "gn:country_code":"CN",
    "gn:dem":1147,
    "gn:feature_class":"P",
    "gn:feature_code":"PPL",
    "gn:name":"Songxin",
    "gn:population":0,
    "gn:timezone":"Asia/Shanghai",
    "iso:country":"CN",
    "name:zho_x_preferred":[
        "\u677e\u65b0"
    ],
    "wof:name":"Songxin",
    "wof:placetype":"locality"
},
  "geometry": {"coordinates":[102.62021,27.21269],"type":"Point"}
}