{
  "type": "Feature",
  "properties": {
    "gn:admin1_code":"3.0",
    "gn:asciiname":"Zhelan",
    "gn:country_code":"CN",
    "gn:dem":82,
    "gn:feature_class":"P",
    "gn:feature_code":"PPL",
    "gn:name":"Zhelan",
    "gn:population":0,
    "gn:timezone":"Asia/Shanghai",
    "iso:country":"CN",
    "name:und_x_variant":[
        "\u67d8\u5170"
    ],
    "wof:name":"Zhelan",
    "wof:placetype":"locality"
},
  "geometry": {"coordinates":[114.90472,28.09903],"type":"Point"}
}