{
  "type": "Feature",
  "properties": {
    "gn:admin1_code":"6.0",
    "gn:asciiname":"Wen'e",
    "gn:country_code":"CN",
    "gn:dem":3701,
    "gn:feature_class":"P",
    "gn:feature_code":"PPL",
    "gn:name":"Wen\u2019e",
    "gn:population":0,
    "gn:timezone":"Asia/Urumqi",
    "iso:country":"CN",
    "name:und_x_variant":[
        "Wen\u2019e"
    ],
    "name:zho_x_preferred":[
        "\u6587\u989d"
    ],
    "wof:name":"Wen'e",
    "wof:placetype":"locality"
},
  "geometry": {"coordinates":[96.41670999999999,32.37591],"type":"Point"}
}