{
  "type": "Feature",
  "properties": {
    "gn:admin1_code":"1.0",
    "gn:asciiname":"Zhuduncun",
    "gn:country_code":"CN",
    "gn:dem":17,
    "gn:feature_class":"P",
    "gn:feature_code":"PPL",
    "gn:name":"Zhuduncun",
    "gn:population":0,
    "gn:timezone":"Asia/Shanghai",
    "iso:country":"CN",
    "name:zho_x_preferred":[
        "\u6731\u58a9\u6751"
    ],
    "wof:name":"Zhuduncun",
    "wof:placetype":"locality"
},
  "geometry": {"coordinates":[117.30616999999999,31.26089],"type":"Point"}
}