{
  "type": "Feature",
  "properties": {
    "gn:admin1_code":"9.0",
    "gn:asciiname":"Laozhuang",
    "gn:country_code":"CN",
    "gn:dem":135,
    "gn:feature_class":"P",
    "gn:feature_code":"PPL",
    "gn:name":"Laozhuang",
    "gn:population":0,
    "gn:timezone":"Asia/Shanghai",
    "iso:country":"CN",
    "name:und_x_variant":[
        "\u8001\u5e84",
        "Laozhuang"
    ],
    "wof:name":"Laozhuang",
    "wof:placetype":"locality"
},
  "geometry": {"coordinates":[112.85029,33.07725],"type":"Point"}
}