{
  "type": "Feature",
  "properties": {
    "gn:admin1_code":"4.0",
    "gn:asciiname":"Zhangsi",
    "gn:country_code":"CN",
    "gn:dem":42,
    "gn:feature_class":"P",
    "gn:feature_code":"PPL",
    "gn:name":"Zhangsi",
    "gn:population":0,
    "gn:timezone":"Asia/Shanghai",
    "iso:country":"CN",
    "name:zho_x_preferred":[
        "\u5f20\u5bfa"
    ],
    "wof:name":"Zhangsi",
    "wof:placetype":"locality"
},
  "geometry": {"coordinates":[119.39924000000001,32.1082],"type":"Point"}
}