{
  "type": "Feature",
  "properties": {
    "gn:admin1_code":"2.0",
    "gn:asciiname":"Tangjia'an",
    "gn:country_code":"CN",
    "gn:dem":208,
    "gn:feature_class":"P",
    "gn:feature_code":"PPL",
    "gn:name":"Tangjia\u2019an",
    "gn:population":0,
    "gn:timezone":"Asia/Shanghai",
    "iso:country":"CN",
    "name:und_x_variant":[
        "Tangjia\u2019an",
        "\u5510\u5bb6\u5eb5"
    ],
    "wof:name":"Tangjia'an",
    "wof:placetype":"locality"
},
  "geometry": {"coordinates":[119.49086,30.48606],"type":"Point"}
}