{
  "type": "Feature",
  "properties": {
    "gn:admin1_code":"19.0",
    "gn:asciiname":"Dayang",
    "gn:country_code":"CN",
    "gn:dem":425,
    "gn:feature_class":"P",
    "gn:feature_code":"PPL",
    "gn:name":"Dayang",
    "gn:population":0,
    "gn:timezone":"Asia/Shanghai",
    "iso:country":"CN",
    "name:ceb_x_preferred":[
        "Dayang"
    ],
    "name:msa_x_preferred":[
        "Dayang"
    ],
    "name:swe_x_preferred":[
        "Dayang"
    ],
    "name:zho_x_preferred":[
        "\u5927\u592e"
    ],
    "wof:name":"Dayang",
    "wof:placetype":"locality"
},
  "geometry": {"coordinates":[125.00887,41.63582],"type":"Point"}
}