{
  "type": "Feature",
  "properties": {
    "gn:admin1_code":"19.0",
    "gn:asciiname":"Mangniutuncun",
    "gn:country_code":"CN",
    "gn:dem":70,
    "gn:feature_class":"P",
    "gn:feature_code":"PPL",
    "gn:name":"Mangniutuncun",
    "gn:population":0,
    "gn:timezone":"Asia/Shanghai",
    "iso:country":"CN",
    "name:zho_x_preferred":[
        "\u7264\u725b\u5c6f\u6751"
    ],
    "wof:name":"Mangniutuncun",
    "wof:placetype":"locality"
},
  "geometry": {"coordinates":[121.41200000000001,41.6478],"type":"Point"}
}