{
  "type": "Feature",
  "properties": {
    "gn:admin1_code":"12.0",
    "gn:asciiname":"Shuangjingyuan",
    "gn:country_code":"CN",
    "gn:dem":33,
    "gn:feature_class":"P",
    "gn:feature_code":"PPL",
    "gn:name":"Shuangjingyuan",
    "gn:population":0,
    "gn:timezone":"Asia/Shanghai",
    "iso:country":"CN",
    "name:zho_x_preferred":[
        "Shuangjingyuan"
    ],
    "name:zho_x_variant":[
        "\u53cc\u5f84\u6e90"
    ],
    "wof:name":"Shuangjingyuan",
    "wof:placetype":"locality"
},
  "geometry": {"coordinates":[115.19386000000002,30.10191],"type":"Point"}
}