{
  "type": "Feature",
  "properties": {
    "gn:admin1_code":"25.0",
    "gn:asciiname":"Xiwangyizhuang",
    "gn:country_code":"CN",
    "gn:dem":14,
    "gn:feature_class":"P",
    "gn:feature_code":"PPL",
    "gn:name":"Xiwangyizhuang",
    "gn:population":0,
    "gn:timezone":"Asia/Shanghai",
    "iso:country":"CN",
    "name:zho_x_preferred":[
        "\u897f\u738b\u76ca\u5e84"
    ],
    "wof:name":"Xiwangyizhuang",
    "wof:placetype":"locality"
},
  "geometry": {"coordinates":[120.06956,36.39527],"type":"Point"}
}