{
  "type": "Feature",
  "properties": {
    "gn:admin1_code":"32.0",
    "gn:asciiname":"Shibatou",
    "gn:country_code":"CN",
    "gn:dem":443,
    "gn:feature_class":"P",
    "gn:feature_code":"PPL",
    "gn:name":"Shibatou",
    "gn:population":0,
    "gn:timezone":"Asia/Shanghai",
    "iso:country":"CN",
    "name:zho_x_preferred":[
        "\u77f3\u575d\u5934"
    ],
    "wof:name":"Shibatou",
    "wof:placetype":"locality"
},
  "geometry": {"coordinates":[105.49299999999999,28.4832],"type":"Point"}
}