{
  "type": "Feature",
  "properties": {
    "gn:admin1_code":"4.0",
    "gn:asciiname":"Wanmatou",
    "gn:country_code":"CN",
    "gn:dem":24,
    "gn:feature_class":"P",
    "gn:feature_code":"PPL",
    "gn:name":"Wanmatou",
    "gn:population":0,
    "gn:timezone":"Asia/Shanghai",
    "iso:country":"CN",
    "name:zho_x_preferred":[
        "\u6e7e\u7801\u5934"
    ],
    "wof:name":"Wanmatou",
    "wof:placetype":"locality"
},
  "geometry": {"coordinates":[119.35574,31.88715],"type":"Point"}
}