{
  "type": "Feature",
  "properties": {
    "gn:admin1_code":"8.0",
    "gn:asciiname":"Shengpingcun",
    "gn:country_code":"CN",
    "gn:dem":159,
    "gn:feature_class":"P",
    "gn:feature_code":"PPL",
    "gn:name":"Shengpingcun",
    "gn:population":0,
    "gn:timezone":"Asia/Shanghai",
    "iso:country":"CN",
    "name:zho_x_preferred":[
        "\u80dc\u5e73\u6751"
    ],
    "wof:name":"Shengpingcun",
    "wof:placetype":"locality"
},
  "geometry": {"coordinates":[126.32102999999999,45.25729000000001],"type":"Point"}
}