{
  "type": "Feature",
  "properties": {
    "gn:admin1_code":"1.0",
    "gn:asciiname":"Daloucun",
    "gn:country_code":"CN",
    "gn:dem":29,
    "gn:feature_class":"P",
    "gn:feature_code":"PPL",
    "gn:name":"Daloucun",
    "gn:population":0,
    "gn:timezone":"Asia/Shanghai",
    "iso:country":"CN",
    "name:zho_x_preferred":[
        "\u5927\u697c\u6751"
    ],
    "wof:name":"Daloucun",
    "wof:placetype":"locality"
},
  "geometry": {"coordinates":[116.32698000000001,33.32003],"type":"Point"}
}