{
  "type": "Feature",
  "properties": {
    "gn:admin1_code":"8.0",
    "gn:asciiname":"Touwobu",
    "gn:country_code":"CN",
    "gn:dem":178,
    "gn:feature_class":"P",
    "gn:feature_code":"PPL",
    "gn:name":"Touwobu",
    "gn:population":0,
    "gn:timezone":"Asia/Shanghai",
    "iso:country":"CN",
    "name:zho_x_preferred":[
        "\u5934\u7a9d\u5821"
    ],
    "wof:name":"Touwobu",
    "wof:placetype":"locality"
},
  "geometry": {"coordinates":[126.26503,46.48746],"type":"Point"}
}