{
  "type": "Feature",
  "properties": {
    "gn:admin1_code":"32.0",
    "gn:asciiname":"Aidianzi",
    "gn:country_code":"CN",
    "gn:dem":348,
    "gn:feature_class":"P",
    "gn:feature_code":"PPL",
    "gn:name":"Aidianzi",
    "gn:population":0,
    "gn:timezone":"Asia/Shanghai",
    "iso:country":"CN",
    "name:zho_x_preferred":[
        "\u77ee\u5e97\u5b50"
    ],
    "wof:name":"Aidianzi",
    "wof:placetype":"locality"
},
  "geometry": {"coordinates":[105.0929,29.3372],"type":"Point"}
}