{
  "type": "Feature",
  "properties": {
    "gn:admin1_code":"7.0",
    "gn:asciiname":"Tianluokeng",
    "gn:country_code":"CN",
    "gn:dem":753,
    "gn:feature_class":"P",
    "gn:feature_code":"PPL",
    "gn:name":"Tianluokeng",
    "gn:population":0,
    "gn:timezone":"Asia/Shanghai",
    "iso:country":"CN",
    "name:zho_x_preferred":[
        "\u7530\u87ba\u5751"
    ],
    "wof:name":"Tianluokeng",
    "wof:placetype":"locality"
},
  "geometry": {"coordinates":[116.72,25.1681],"type":"Point"}
}