{
  "type": "Feature",
  "properties": {
    "gn:admin1_code":"2.0",
    "gn:asciiname":"Dacankeng",
    "gn:country_code":"CN",
    "gn:dem":182,
    "gn:feature_class":"P",
    "gn:feature_code":"PPL",
    "gn:name":"Dacankeng",
    "gn:population":0,
    "gn:timezone":"Asia/Shanghai",
    "iso:country":"CN",
    "name:zho_x_preferred":[
        "\u5927\u8695\u5751"
    ],
    "wof:name":"Dacankeng",
    "wof:placetype":"locality"
},
  "geometry": {"coordinates":[121.45388,29.03836],"type":"Point"}
}