{
  "type": "Feature",
  "properties": {
    "gn:admin1_code":"10",
    "gn:asciiname":"Beigounao",
    "gn:country_code":"CN",
    "gn:dem":635,
    "gn:feature_class":"P",
    "gn:feature_code":"PPL",
    "gn:name":"Beigounao",
    "gn:population":0,
    "gn:timezone":"Asia/Shanghai",
    "iso:country":"CN",
    "name:zho_x_preferred":[
        "\u5317\u6c9f\u8111"
    ],
    "wof:name":"Beigounao",
    "wof:placetype":"locality"
},
  "geometry": {"coordinates":[116.97579,41.1129],"type":"Point"}
}