{
  "type": "Feature",
  "properties": {
    "gn:admin1_code":"4.0",
    "gn:asciiname":"Liutingcun",
    "gn:country_code":"CN",
    "gn:dem":4,
    "gn:feature_class":"P",
    "gn:feature_code":"PPL",
    "gn:name":"Liutingcun",
    "gn:population":0,
    "gn:timezone":"Asia/Shanghai",
    "iso:country":"CN",
    "name:zho_x_preferred":[
        "\u5218\u5385\u6751"
    ],
    "wof:name":"Liutingcun",
    "wof:placetype":"locality"
},
  "geometry": {"coordinates":[118.79309000000001,34.29132],"type":"Point"}
}