{
  "type": "Feature",
  "properties": {
    "gn:admin1_code":"5.0",
    "gn:asciiname":"Zamucun",
    "gn:country_code":"CN",
    "gn:dem":264,
    "gn:feature_class":"P",
    "gn:feature_code":"PPL",
    "gn:name":"Zamucun",
    "gn:population":0,
    "gn:timezone":"Asia/Shanghai",
    "iso:country":"CN",
    "name:zho_x_preferred":[
        "\u6742\u6728\u6751"
    ],
    "wof:name":"Zamucun",
    "wof:placetype":"locality"
},
  "geometry": {"coordinates":[124.93371999999999,43.02125],"type":"Point"}
}