{
  "type": "Feature",
  "properties": {
    "gn:admin1_code":"8.0",
    "gn:asciiname":"Xingzhancun",
    "gn:country_code":"CN",
    "gn:dem":273,
    "gn:feature_class":"P",
    "gn:feature_code":"PPL",
    "gn:name":"Xingzhancun",
    "gn:population":0,
    "gn:timezone":"Asia/Shanghai",
    "iso:country":"CN",
    "name:zho_x_preferred":[
        "\u5174\u5c55\u6751"
    ],
    "wof:name":"Xingzhancun",
    "wof:placetype":"locality"
},
  "geometry": {"coordinates":[126.24636,47.54361],"type":"Point"}
}