{
  "type": "Feature",
  "properties": {
    "gn:admin1_code":"1.0",
    "gn:asciiname":"Liuloucun",
    "gn:country_code":"CN",
    "gn:dem":33,
    "gn:feature_class":"P",
    "gn:feature_code":"PPL",
    "gn:name":"Liuloucun",
    "gn:population":0,
    "gn:timezone":"Asia/Shanghai",
    "iso:country":"CN",
    "name:zho_x_preferred":[
        "\u5218\u697c\u6751"
    ],
    "wof:name":"Liuloucun",
    "wof:placetype":"locality"
},
  "geometry": {"coordinates":[116.60902,33.85869],"type":"Point"}
}