{
  "type": "Feature",
  "properties": {
    "gn:admin1_code":"11.0",
    "gn:asciiname":"Shashupo",
    "gn:country_code":"CN",
    "gn:dem":318,
    "gn:feature_class":"P",
    "gn:feature_code":"PPL",
    "gn:name":"Shashupo",
    "gn:population":0,
    "gn:timezone":"Asia/Shanghai",
    "iso:country":"CN",
    "name:zho_x_preferred":[
        "\u6749\u6811\u5761"
    ],
    "wof:name":"Shashupo",
    "wof:placetype":"locality"
},
  "geometry": {"coordinates":[113.65136,28.89874],"type":"Point"}
}