{
  "type": "Feature",
  "properties": {
    "gn:admin1_code":"04",
    "gn:asciiname":"Huqiu",
    "gn:country_code":"CN",
    "gn:dem":5,
    "gn:feature_class":"P",
    "gn:feature_code":"PPL",
    "gn:name":"Huqiu",
    "gn:population":0,
    "gn:timezone":"Asia/Shanghai",
    "iso:country":"CN",
    "name:und_x_variant":[
        "Hu-ch\u2019iu-shan",
        "Huqiu"
    ],
    "name:zho_x_preferred":[
        "\u864e\u4e18"
    ],
    "wof:name":"Huqiu",
    "wof:placetype":"locality"
},
  "geometry": {"coordinates":[120.58392000000001,31.33691],"type":"Point"}
}