{
  "type": "Feature",
  "properties": {
    "gn:admin1_code":"19.0",
    "gn:asciiname":"Beiyingzi",
    "gn:country_code":"CN",
    "gn:dem":528,
    "gn:feature_class":"P",
    "gn:feature_code":"PPL",
    "gn:name":"Beiyingzi",
    "gn:population":0,
    "gn:timezone":"Asia/Shanghai",
    "iso:country":"CN",
    "name:zho_x_preferred":[
        "\u5317\u8425\u5b50"
    ],
    "wof:name":"Beiyingzi",
    "wof:placetype":"locality"
},
  "geometry": {"coordinates":[119.82145,41.61628],"type":"Point"}
}