{
  "type": "Feature",
  "properties": {
    "gn:admin1_code":"30",
    "gn:asciiname":"Pangdongxu",
    "gn:country_code":"CN",
    "gn:dem":74,
    "gn:feature_class":"P",
    "gn:feature_code":"PPL",
    "gn:name":"Pangdongxu",
    "gn:population":0,
    "gn:timezone":"Asia/Shanghai",
    "iso:country":"CN",
    "name:zho_x_preferred":[
        "\u5e9e\u6d1e\u5729"
    ],
    "wof:name":"Pangdongxu",
    "wof:placetype":"locality"
},
  "geometry": {"coordinates":[111.52771,22.14067],"type":"Point"}
}