{
  "type": "Feature",
  "properties": {
    "gn:admin1_code":"30.0",
    "gn:asciiname":"Caibian",
    "gn:country_code":"CN",
    "gn:dem":9,
    "gn:feature_class":"P",
    "gn:feature_code":"PPL",
    "gn:name":"Caibian",
    "gn:population":0,
    "gn:timezone":"Asia/Shanghai",
    "iso:country":"CN",
    "name:zho_x_preferred":[
        "\u8521\u4fbf"
    ],
    "wof:name":"Caibian",
    "wof:placetype":"locality"
},
  "geometry": {"coordinates":[112.76472,23.32391],"type":"Point"}
}