{
  "type": "Feature",
  "properties": {
    "gn:admin1_code":"3",
    "gn:asciiname":"Wanjiaozi",
    "gn:country_code":"CN",
    "gn:dem":313,
    "gn:feature_class":"P",
    "gn:feature_code":"PPL",
    "gn:name":"Wanjiaozi",
    "gn:population":0,
    "gn:timezone":"Asia/Shanghai",
    "iso:country":"CN",
    "name:zho_x_preferred":[
        "\u5f2f\u89d2\u5b50"
    ],
    "wof:name":"Wanjiaozi",
    "wof:placetype":"locality"
},
  "geometry": {"coordinates":[114.30200000000001,25.8517],"type":"Point"}
}