{
  "type": "Feature",
  "properties": {
    "gn:admin1_code":"30.0",
    "gn:asciiname":"Yushui",
    "gn:country_code":"CN",
    "gn:dem":17,
    "gn:feature_class":"P",
    "gn:feature_code":"PPL",
    "gn:name":"Yushui",
    "gn:population":0,
    "gn:timezone":"Asia/Shanghai",
    "iso:country":"CN",
    "name:ceb_x_preferred":[
        "Yushui"
    ],
    "name:fra_x_preferred":[
        "Yushui"
    ],
    "name:zho_x_preferred":[
        "\u6d74\u6c34"
    ],
    "wof:name":"Yushui",
    "wof:placetype":"locality"
},
  "geometry": {"coordinates":[112.44025000000001,22.43304],"type":"Point"}
}