{
  "type": "Feature",
  "properties": {
    "gn:admin1_code":"16",
    "gn:asciiname":"Xinpujie",
    "gn:country_code":"CN",
    "gn:dem":336,
    "gn:feature_class":"P",
    "gn:feature_code":"PPL",
    "gn:name":"Xinpujie",
    "gn:population":0,
    "gn:timezone":"Asia/Shanghai",
    "iso:country":"CN",
    "name:zho_x_preferred":[
        "\u65b0\u94fa\u8857"
    ],
    "wof:name":"Xinpujie",
    "wof:placetype":"locality"
},
  "geometry": {"coordinates":[110.675,25.8332],"type":"Point"}
}