{
  "type": "Feature",
  "properties": {
    "gn:admin1_code":"18",
    "gn:asciiname":"Gaotun",
    "gn:cc2":"CN",
    "gn:country_code":"CN",
    "gn:dem":454,
    "gn:feature_class":"P",
    "gn:feature_code":"PPL",
    "gn:name":"Gaotun",
    "gn:population":0,
    "gn:timezone":"Asia/Shanghai",
    "iso:country":"CN",
    "name:und_x_variant":[
        "Gaotun Zhen",
        "Gaotun"
    ],
    "wof:name":"Gaotun",
    "wof:placetype":"locality"
},
  "geometry": {"coordinates":[109.16056,26.33667],"type":"Point"}
}