{
  "type": "Feature",
  "properties": {
    "gn:admin1_code":"26",
    "gn:asciiname":"Dongwangzhuang",
    "gn:country_code":"CN",
    "gn:dem":1087,
    "gn:feature_class":"P",
    "gn:feature_code":"PPL",
    "gn:name":"Dongwangzhuang",
    "gn:population":0,
    "gn:timezone":"Asia/Shanghai",
    "iso:country":"CN",
    "name:zho_x_preferred":[
        "\u4e1c\u738b\u5e84"
    ],
    "wof:name":"Dongwangzhuang",
    "wof:placetype":"locality"
},
  "geometry": {"coordinates":[108.40833000000001,34.71333],"type":"Point"}
}