{
  "type": "Feature",
  "properties": {
    "gn:admin1_code":"12.0",
    "gn:asciiname":"Huang'aowu",
    "gn:country_code":"CN",
    "gn:dem":53,
    "gn:feature_class":"P",
    "gn:feature_code":"PPL",
    "gn:name":"Huang\u2019aowu",
    "gn:population":0,
    "gn:timezone":"Asia/Shanghai",
    "iso:country":"CN",
    "name:und_x_variant":[
        "Huang\u2019aowu"
    ],
    "name:zho_x_preferred":[
        "\u9ec4\u51f9\u5c4b"
    ],
    "wof:name":"Huang'aowu",
    "wof:placetype":"locality"
},
  "geometry": {"coordinates":[114.91042,30.97801],"type":"Point"}
}