{
  "type": "Feature",
  "properties": {
    "gn:admin1_code":"25",
    "gn:asciiname":"Tumeiyu",
    "gn:country_code":"CN",
    "gn:dem":431,
    "gn:feature_class":"P",
    "gn:feature_code":"PPL",
    "gn:name":"Tumeiyu",
    "gn:population":0,
    "gn:timezone":"Asia/Shanghai",
    "iso:country":"CN",
    "name:zho_x_preferred":[
        "\u571f\u7709\u5cea"
    ],
    "wof:name":"Tumeiyu",
    "wof:placetype":"locality"
},
  "geometry": {"coordinates":[118.04600000000001,36.0038],"type":"Point"}
}