{
  "type": "Feature",
  "properties": {
    "gn:admin1_code":"30.0",
    "gn:asciiname":"Qiaoshan",
    "gn:country_code":"CN",
    "gn:dem":14,
    "gn:feature_class":"P",
    "gn:feature_code":"PPL",
    "gn:name":"Qiaoshan",
    "gn:population":0,
    "gn:timezone":"Asia/Shanghai",
    "iso:country":"CN",
    "name:und_x_variant":[
        "\u6865\u5c71"
    ],
    "name:zho_x_preferred":[
        "\u6865\u5c71"
    ],
    "wof:name":"Qiaoshan",
    "wof:placetype":"locality"
},
  "geometry": {"coordinates":[113.42122999999999,22.98522],"type":"Point"}
}