{
  "type": "Feature",
  "properties": {
    "gn:admin1_code":"25.0",
    "gn:asciiname":"Wawuzhuangcun",
    "gn:country_code":"CN",
    "gn:dem":18,
    "gn:feature_class":"P",
    "gn:feature_code":"PPL",
    "gn:name":"Wawuzhuangcun",
    "gn:population":0,
    "gn:timezone":"Asia/Shanghai",
    "iso:country":"CN",
    "name:zho_x_preferred":[
        "\u74e6\u5c4b\u5e84\u6751"
    ],
    "wof:name":"Wawuzhuangcun",
    "wof:placetype":"locality"
},
  "geometry": {"coordinates":[119.94508,36.40733],"type":"Point"}
}