{
  "type": "Feature",
  "properties": {
    "gn:admin1_code":"14.0",
    "gn:asciiname":"Gasicun",
    "gn:country_code":"CN",
    "gn:dem":3869,
    "gn:feature_class":"P",
    "gn:feature_code":"PPL",
    "gn:name":"Gasicun",
    "gn:population":0,
    "gn:timezone":"Asia/Urumqi",
    "iso:country":"CN",
    "name:zho_x_preferred":[
        "\u560e\u56db\u6751"
    ],
    "wof:name":"Gasicun",
    "wof:placetype":"locality"
},
  "geometry": {"coordinates":[98.17794000000001,31.52988],"type":"Point"}
}