{
  "type": "Feature",
  "properties": {
    "gn:admin1_code":"29.0",
    "gn:asciiname":"Xiaohaidao",
    "gn:country_code":"CN",
    "gn:dem":1489,
    "gn:feature_class":"P",
    "gn:feature_code":"PPL",
    "gn:name":"Xiaohaidao",
    "gn:population":0,
    "gn:timezone":"Asia/Shanghai",
    "iso:country":"CN",
    "name:zho_x_preferred":[
        "\u5c0f\u6d77\u5c9b"
    ],
    "wof:name":"Xiaohaidao",
    "wof:placetype":"locality"
},
  "geometry": {"coordinates":[97.7782,24.396],"type":"Point"}
}