{
  "type": "Feature",
  "properties": {
    "gn:admin1_code":"33.0",
    "gn:asciiname":"Xishaxi",
    "gn:country_code":"CN",
    "gn:dem":427,
    "gn:feature_class":"P",
    "gn:feature_code":"PPL",
    "gn:name":"Xishaxi",
    "gn:population":0,
    "gn:timezone":"Asia/Shanghai",
    "iso:country":"CN",
    "name:zho_x_preferred":[
        "\u7ec6\u6c99\u6eaa"
    ],
    "wof:name":"Xishaxi",
    "wof:placetype":"locality"
},
  "geometry": {"coordinates":[109.00693,28.94527],"type":"Point"}
}