{
  "type": "Feature",
  "properties": {
    "gn:admin1_code":"11",
    "gn:asciiname":"Chuankouwukuang",
    "gn:country_code":"CN",
    "gn:dem":183,
    "gn:feature_class":"P",
    "gn:feature_code":"PPL",
    "gn:name":"Chuankouwukuang",
    "gn:population":0,
    "gn:timezone":"Asia/Shanghai",
    "iso:country":"CN",
    "wof:name":"Chuankouwukuang",
    "wof:placetype":"locality"
},
  "geometry": {"coordinates":[113.01528,26.89444],"type":"Point"}
}