{
  "type": "Feature",
  "properties": {
    "gn:admin1_code":"19.0",
    "gn:asciiname":"Xiquegoucun",
    "gn:country_code":"CN",
    "gn:dem":196,
    "gn:feature_class":"P",
    "gn:feature_code":"PPL",
    "gn:name":"Xiquegoucun",
    "gn:population":0,
    "gn:timezone":"Asia/Shanghai",
    "iso:country":"CN",
    "name:zho_x_preferred":[
        "\u559c\u9e4a\u6c9f\u6751"
    ],
    "wof:name":"Xiquegoucun",
    "wof:placetype":"locality"
},
  "geometry": {"coordinates":[124.38894000000001,42.45908],"type":"Point"}
}