{
  "type": "Feature",
  "properties": {
    "gn:admin1_code":"3.0",
    "gn:asciiname":"Kaifengtian",
    "gn:country_code":"CN",
    "gn:dem":349,
    "gn:feature_class":"P",
    "gn:feature_code":"PPL",
    "gn:name":"Kaifengtian",
    "gn:population":0,
    "gn:timezone":"Asia/Shanghai",
    "iso:country":"CN",
    "name:und_x_variant":[
        "\u51ef\u4e30\u7530"
    ],
    "wof:name":"Kaifengtian",
    "wof:placetype":"locality"
},
  "geometry": {"coordinates":[115.965,25.97126],"type":"Point"}
}