{
  "type": "Feature",
  "properties": {
    "gn:admin1_code":"9.0",
    "gn:asciiname":"Pantai",
    "gn:country_code":"CN",
    "gn:dem":34,
    "gn:feature_class":"P",
    "gn:feature_code":"PPL",
    "gn:name":"Pantai",
    "gn:population":0,
    "gn:timezone":"Asia/Shanghai",
    "iso:country":"CN",
    "name:epo_x_preferred":[
        "Pantai"
    ],
    "name:ind_x_preferred":[
        "Pantai"
    ],
    "name:msa_x_preferred":[
        "Pantai"
    ],
    "name:zho_x_preferred":[
        "\u6f58\u53f0"
    ],
    "wof:name":"Pantai",
    "wof:placetype":"locality"
},
  "geometry": {"coordinates":[115.80159,32.42318],"type":"Point"}
}