{
  "type": "Feature",
  "properties": {
    "gn:admin1_code":"4.0",
    "gn:asciiname":"Laowuji",
    "gn:country_code":"CN",
    "gn:dem":-2,
    "gn:feature_class":"P",
    "gn:feature_code":"PPL",
    "gn:name":"Laowuji",
    "gn:population":0,
    "gn:timezone":"Asia/Shanghai",
    "iso:country":"CN",
    "name:zho_x_preferred":[
        "Laowuji"
    ],
    "name:zho_x_variant":[
        "\u8001\u5c4b\u57fa"
    ],
    "wof:name":"Laowuji",
    "wof:placetype":"locality"
},
  "geometry": {"coordinates":[119.96612,33.69139000000001],"type":"Point"}
}