{
  "type": "Feature",
  "properties": {
    "gn:admin1_code":"30",
    "gn:asciiname":"Haotan",
    "gn:country_code":"CN",
    "gn:dem":23,
    "gn:feature_class":"P",
    "gn:feature_code":"PPL",
    "gn:name":"Haotan",
    "gn:population":0,
    "gn:timezone":"Asia/Urumqi",
    "iso:country":"CN",
    "name:zho_x_preferred":[
        "\u869d\u6f6d"
    ],
    "wof:name":"Haotan",
    "wof:placetype":"locality"
},
  "geometry": {"coordinates":[110.32088,20.82318],"type":"Point"}
}