{
  "type": "Feature",
  "properties": {
    "gn:admin1_code":"16.0",
    "gn:asciiname":"Shangying",
    "gn:country_code":"CN",
    "gn:dem":134,
    "gn:feature_class":"P",
    "gn:feature_code":"PPL",
    "gn:name":"Shangying",
    "gn:population":0,
    "gn:timezone":"Asia/Shanghai",
    "iso:country":"CN",
    "name:zho_x_preferred":[
        "\u4e0a\u82f1"
    ],
    "wof:name":"Shangying",
    "wof:placetype":"locality"
},
  "geometry": {"coordinates":[107.96299999999999,22.3515],"type":"Point"}
}