{
  "type": "Feature",
  "properties": {
    "gn:admin1_code":"07",
    "gn:asciiname":"Yangdaoling",
    "gn:country_code":"CN",
    "gn:dem":304,
    "gn:feature_class":"P",
    "gn:feature_code":"PPL",
    "gn:name":"Yangdaoling",
    "gn:population":0,
    "gn:timezone":"Asia/Shanghai",
    "iso:country":"CN",
    "name:zho_x_preferred":[
        "\u6d0b\u9053\u5cad"
    ],
    "wof:name":"Yangdaoling",
    "wof:placetype":"locality"
},
  "geometry": {"coordinates":[117.20573,26.01226],"type":"Point"}
}