{
  "type": "Feature",
  "properties": {
    "gn:admin1_code":"15.0",
    "gn:asciiname":"Silitian",
    "gn:country_code":"CN",
    "gn:dem":1363,
    "gn:feature_class":"P",
    "gn:feature_code":"PPL",
    "gn:name":"Silitian",
    "gn:population":0,
    "gn:timezone":"Asia/Shanghai",
    "iso:country":"CN",
    "name:zho_x_preferred":[
        "\u5bfa\u91cc\u7530"
    ],
    "wof:name":"Silitian",
    "wof:placetype":"locality"
},
  "geometry": {"coordinates":[107.69199999999999,35.6784],"type":"Point"}
}