{
  "type": "Feature",
  "properties": {
    "gn:admin1_code":"26.0",
    "gn:asciiname":"Longdonggou",
    "gn:country_code":"CN",
    "gn:dem":1357,
    "gn:feature_class":"P",
    "gn:feature_code":"PPL",
    "gn:name":"Longdonggou",
    "gn:population":0,
    "gn:timezone":"Asia/Shanghai",
    "iso:country":"CN",
    "name:zho_x_preferred":[
        "\u9f99\u6d1e\u6c9f"
    ],
    "wof:name":"Longdonggou",
    "wof:placetype":"locality"
},
  "geometry": {"coordinates":[109.08819,32.11868],"type":"Point"}
}