{
  "type": "Feature",
  "properties": {
    "gn:admin1_code":"4.0",
    "gn:asciiname":"Lucun",
    "gn:country_code":"CN",
    "gn:dem":3,
    "gn:feature_class":"P",
    "gn:feature_code":"PPL",
    "gn:name":"Lucun",
    "gn:population":0,
    "gn:timezone":"Asia/Shanghai",
    "iso:country":"CN",
    "name:ceb_x_preferred":[
        "Lucun"
    ],
    "name:swe_x_preferred":[
        "Lucun"
    ],
    "name:zho_x_preferred":[
        "\u5362\u6751"
    ],
    "wof:name":"Lucun",
    "wof:placetype":"locality"
},
  "geometry": {"coordinates":[119.9787,33.26093],"type":"Point"}
}