{
  "type": "Feature",
  "properties": {
    "gn:admin1_code":"11.0",
    "gn:asciiname":"Jiukouyan",
    "gn:country_code":"CN",
    "gn:dem":60,
    "gn:feature_class":"P",
    "gn:feature_code":"PPL",
    "gn:name":"Jiukouyan",
    "gn:population":0,
    "gn:timezone":"Asia/Shanghai",
    "iso:country":"CN",
    "name:zho_x_preferred":[
        "Jiukouyan"
    ],
    "name:zho_x_variant":[
        "\u4e5d\u53e3\u5830"
    ],
    "wof:name":"Jiukouyan",
    "wof:placetype":"locality"
},
  "geometry": {"coordinates":[111.38869,29.58504000000001],"type":"Point"}
}