{
  "type": "Feature",
  "properties": {
    "gn:admin1_code":"32.0",
    "gn:asciiname":"Gubuluoha",
    "gn:country_code":"CN",
    "gn:dem":1232,
    "gn:feature_class":"P",
    "gn:feature_code":"PPL",
    "gn:name":"Gubuluoha",
    "gn:population":0,
    "gn:timezone":"Asia/Shanghai",
    "iso:country":"CN",
    "name:zho_x_preferred":[
        "\u8c37\u5e03\u6d1b\u54c8"
    ],
    "wof:name":"Gubuluoha",
    "wof:placetype":"locality"
},
  "geometry": {"coordinates":[102.685,28.8979],"type":"Point"}
}