{
  "type": "Feature",
  "properties": {
    "gn:admin1_code":"18",
    "gn:asciiname":"Jiaowu",
    "gn:country_code":"CN",
    "gn:dem":549,
    "gn:feature_class":"P",
    "gn:feature_code":"PPL",
    "gn:name":"Jiaowu",
    "gn:population":0,
    "gn:timezone":"Asia/Shanghai",
    "iso:country":"CN",
    "name:zho_x_preferred":[
        "\u4ea4\u543e"
    ],
    "wof:name":"Jiaowu",
    "wof:placetype":"locality"
},
  "geometry": {"coordinates":[106.752,25.3004],"type":"Point"}
}