{
  "type": "Feature",
  "properties": {
    "gn:admin1_code":"32.0",
    "gn:asciiname":"Xiala",
    "gn:country_code":"CN",
    "gn:dem":3638,
    "gn:feature_class":"P",
    "gn:feature_code":"PPL",
    "gn:name":"Xiala",
    "gn:population":0,
    "gn:timezone":"Asia/Shanghai",
    "iso:country":"CN",
    "name:zho_x_preferred":[
        "\u5477\u62c9"
    ],
    "wof:name":"Xiala",
    "wof:placetype":"locality"
},
  "geometry": {"coordinates":[99.4606,31.9986],"type":"Point"}
}