{
  "type": "Feature",
  "properties": {
    "gn:admin1_code":"15",
    "gn:asciiname":"Jing'an",
    "gn:country_code":"CN",
    "gn:dem":1428,
    "gn:feature_class":"P",
    "gn:feature_code":"PPLA4",
    "gn:name":"Jing\u2019an",
    "gn:population":0,
    "gn:timezone":"Asia/Shanghai",
    "iso:country":"CN",
    "name:und_x_variant":[
        "Jing\u2019an",
        "Jing\u2019an Xiang"
    ],
    "name:zho_x_preferred":[
        "\u9756\u5b89"
    ],
    "name:zho_x_variant":[
        "\u9756\u5b89\u4e61"
    ],
    "wof:name":"Jing'an",
    "wof:placetype":"locality"
},
  "geometry": {"coordinates":[100.41094,39.10438],"type":"Point"}
}