{
  "type": "Feature",
  "properties": {
    "gn:admin1_code":"25.0",
    "gn:asciiname":"Xiaorenhe",
    "gn:cc2":"CN",
    "gn:country_code":"CN",
    "gn:dem":70,
    "gn:feature_class":"P",
    "gn:feature_code":"PPL",
    "gn:name":"Xiaorenhe",
    "gn:population":0,
    "gn:timezone":"Asia/Shanghai",
    "iso:country":"CN",
    "name:zho_x_preferred":[
        "\u5c0f\u4ec1\u548c"
    ],
    "wof:name":"Xiaorenhe",
    "wof:placetype":"locality"
},
  "geometry": {"coordinates":[119.57279,36.11874],"type":"Point"}
}