{
  "type": "Feature",
  "properties": {
    "gn:admin1_code":"12.0",
    "gn:asciiname":"Dianzigang",
    "gn:country_code":"CN",
    "gn:dem":138,
    "gn:feature_class":"P",
    "gn:feature_code":"PPL",
    "gn:name":"Dianzigang",
    "gn:population":0,
    "gn:timezone":"Asia/Shanghai",
    "iso:country":"CN",
    "name:zho_x_preferred":[
        "\u5e97\u5b50\u5c97"
    ],
    "wof:name":"Dianzigang",
    "wof:placetype":"locality"
},
  "geometry": {"coordinates":[112.53313,31.64509],"type":"Point"}
}