{
  "type": "Feature",
  "properties": {
    "gn:admin1_code":"26.0",
    "gn:asciiname":"Xiayuanzi",
    "gn:country_code":"CN",
    "gn:dem":630,
    "gn:feature_class":"P",
    "gn:feature_code":"PPL",
    "gn:name":"Xiayuanzi",
    "gn:population":0,
    "gn:timezone":"Asia/Shanghai",
    "iso:country":"CN",
    "name:zho_x_preferred":[
        "\u4e0b\u9662\u5b50"
    ],
    "wof:name":"Xiayuanzi",
    "wof:placetype":"locality"
},
  "geometry": {"coordinates":[109.10464,32.95292],"type":"Point"}
}