{
  "type": "Feature",
  "properties": {
    "gn:admin1_code":"20.0",
    "gn:asciiname":"Shangshengjitu",
    "gn:country_code":"CN",
    "gn:dem":1593,
    "gn:feature_class":"P",
    "gn:feature_code":"PPL",
    "gn:name":"Shangshengjitu",
    "gn:population":0,
    "gn:timezone":"Asia/Shanghai",
    "iso:country":"CN",
    "name:und_x_variant":[
        "\u4e0a\u751f\u9e21\u56fe"
    ],
    "wof:name":"Shangshengjitu",
    "wof:placetype":"locality"
},
  "geometry": {"coordinates":[110.26819999999999,40.94736],"type":"Point"}
}