{
  "type": "Feature",
  "properties": {
    "gn:admin1_code":"7",
    "gn:asciiname":"Hengshan",
    "gn:country_code":"CN",
    "gn:dem":885,
    "gn:feature_class":"P",
    "gn:feature_code":"PPL",
    "gn:name":"Hengshan",
    "gn:population":0,
    "gn:timezone":"Asia/Shanghai",
    "iso:country":"CN",
    "name:ceb_x_preferred":[
        "Hengshan"
    ],
    "name:deu_x_preferred":[
        "Hengshan"
    ],
    "name:fra_x_preferred":[
        "Hengshan"
    ],
    "name:nor_x_preferred":[
        "Hengshan"
    ],
    "name:pol_x_preferred":[
        "Heng Shan"
    ],
    "name:rus_x_preferred":[
        "\u0425\u044d\u043d\u0448\u0430\u043d\u044c"
    ],
    "name:swe_x_preferred":[
        "Hengshan"
    ],
    "name:und_x_variant":[
        "\u6a2a\u5c71"
    ],
    "wof:name":"Hengshan",
    "wof:placetype":"locality"
},
  "geometry": {"coordinates":[119.50141000000001,27.64262],"type":"Point"}
}