{
  "type": "Feature",
  "properties": {
    "gn:admin1_code":"15.0",
    "gn:asciiname":"Zhongchuan",
    "gn:country_code":"CN",
    "gn:dem":1642,
    "gn:feature_class":"P",
    "gn:feature_code":"PPL",
    "gn:name":"Zhongchuan",
    "gn:population":0,
    "gn:timezone":"Asia/Shanghai",
    "iso:country":"CN",
    "name:zho_x_preferred":[
        "\u4e2d\u5ddd"
    ],
    "wof:name":"Zhongchuan",
    "wof:placetype":"locality"
},
  "geometry": {"coordinates":[106.057,35.2171],"type":"Point"}
}