{
  "type": "Feature",
  "properties": {
    "gn:country":"CN",
    "gn:fcode":"PPLA4",
    "gn:pop":155000,
    "iso:country":"CN",
    "name:unk_x_variant":[
        "\u6881\u6e56"
    ],
    "qs:name":"Lianghu",
    "qs:photos_9r":0,
    "qs:photos_sr":0,
    "qs:pop_sr":"9",
    "wof:name":"Lianghu",
    "wof:placetype":"locality",
    "wof:population":155000
},
  "geometry": {"coordinates":[120.89845,29.99152],"type":"Point"}
}