{
  "type": "Feature",
  "properties": {
    "gn:admin1_code":"29.0",
    "gn:asciiname":"Qitaipo",
    "gn:country_code":"CN",
    "gn:dem":1856,
    "gn:feature_class":"P",
    "gn:feature_code":"PPL",
    "gn:name":"Qitaipo",
    "gn:population":0,
    "gn:timezone":"Asia/Shanghai",
    "iso:country":"CN",
    "name:zho_x_preferred":[
        "\u4e03\u53f0\u5761"
    ],
    "wof:name":"Qitaipo",
    "wof:placetype":"locality"
},
  "geometry": {"coordinates":[99.8541,24.5291],"type":"Point"}
}