{
  "type": "Feature",
  "properties": {
    "gn:admin1_code":"10",
    "gn:asciiname":"Lao-yen-miao",
    "gn:country_code":"CN",
    "gn:dem":529,
    "gn:feature_class":"P",
    "gn:feature_code":"PPL",
    "gn:name":"Lao-yen-miao",
    "gn:population":0,
    "gn:timezone":"Asia/Shanghai",
    "iso:country":"CN",
    "name:und_x_variant":[
        "Laoyemiao"
    ],
    "name:zho_x_preferred":[
        "\u8001\u7237\u5e99"
    ],
    "wof:name":"Lao-yen-miao",
    "wof:placetype":"locality"
},
  "geometry": {"coordinates":[117.68583,40.5375],"type":"Point"}
}