{
  "type": "Feature",
  "properties": {
    "gn:admin1_code":"24.0",
    "gn:asciiname":"Xiawangcun",
    "gn:country_code":"CN",
    "gn:dem":371,
    "gn:feature_class":"P",
    "gn:feature_code":"PPL",
    "gn:name":"Xiawangcun",
    "gn:population":0,
    "gn:timezone":"Asia/Shanghai",
    "iso:country":"CN",
    "name:zho_x_preferred":[
        "\u4e0b\u738b\u6751"
    ],
    "wof:name":"Xiawangcun",
    "wof:placetype":"locality"
},
  "geometry": {"coordinates":[111.00494,35.09641],"type":"Point"}
}