{
  "type": "Feature",
  "properties": {
    "gn:admin1_code":"1.0",
    "gn:asciiname":"Xizhucun",
    "gn:country_code":"CN",
    "gn:dem":29,
    "gn:feature_class":"P",
    "gn:feature_code":"PPL",
    "gn:name":"Xizhucun",
    "gn:population":0,
    "gn:timezone":"Asia/Shanghai",
    "iso:country":"CN",
    "name:zho_x_preferred":[
        "\u897f\u6731\u6751"
    ],
    "wof:name":"Xizhucun",
    "wof:placetype":"locality"
},
  "geometry": {"coordinates":[117.24854000000001,32.89813],"type":"Point"}
}