{
  "type": "Feature",
  "properties": {
    "gn:admin1_code":"3.0",
    "gn:asciiname":"Guanbei Zhoujia",
    "gn:country_code":"CN",
    "gn:dem":46,
    "gn:feature_class":"P",
    "gn:feature_code":"PPL",
    "gn:name":"Guanbei Zhoujia",
    "gn:population":0,
    "gn:timezone":"Asia/Shanghai",
    "iso:country":"CN",
    "name:zho_x_preferred":[
        "\u89c2\u80cc\u5468\u5bb6"
    ],
    "wof:name":"Guanbei Zhoujia",
    "wof:placetype":"locality"
},
  "geometry": {"coordinates":[115.268,28.4468],"type":"Point"}
}