{
  "type": "Feature",
  "properties": {
    "gn:admin1_code":"20.0",
    "gn:asciiname":"Kayadu Erben",
    "gn:country_code":"CN",
    "gn:dem":236,
    "gn:feature_class":"P",
    "gn:feature_code":"PPL",
    "gn:name":"Kayadu Erben",
    "gn:population":0,
    "gn:timezone":"Asia/Shanghai",
    "iso:country":"CN",
    "name:zho_x_preferred":[
        "\u5580\u7259\u90fd\u5c14\u672c"
    ],
    "wof:name":"Kayadu Erben",
    "wof:placetype":"locality"
},
  "geometry": {"coordinates":[123.96981,48.75336],"type":"Point"}
}