{
  "type": "Feature",
  "properties": {
    "gn:admin1_code":"16.0",
    "gn:asciiname":"Luzhi",
    "gn:country_code":"CN",
    "gn:dem":134,
    "gn:feature_class":"P",
    "gn:feature_code":"PPL",
    "gn:name":"Luzhi",
    "gn:population":0,
    "gn:timezone":"Asia/Shanghai",
    "iso:country":"CN",
    "name:fra_x_preferred":[
        "Luzhi"
    ],
    "name:jpn_x_preferred":[
        "\u30ed\u30af\u76f4\u93ae"
    ],
    "name:wuu_x_preferred":[
        "\u752a\u76f4\u9547"
    ],
    "name:zho_x_preferred":[
        "\u6e0c\u6cbb"
    ],
    "name:zho_x_variant":[
        "\u752a\u76f4\u9547"
    ],
    "wof:name":"Luzhi",
    "wof:placetype":"locality"
},
  "geometry": {"coordinates":[107.621,23.3236],"type":"Point"}
}