{
  "type": "Feature",
  "properties": {
    "gn:admin1_code":"29.0",
    "gn:asciiname":"Yanjinggou",
    "gn:country_code":"CN",
    "gn:dem":2185,
    "gn:feature_class":"P",
    "gn:feature_code":"PPL",
    "gn:name":"Yanjinggou",
    "gn:population":0,
    "gn:timezone":"Asia/Shanghai",
    "iso:country":"CN",
    "name:zho_x_preferred":[
        "\u76d0\u4e95\u6c9f"
    ],
    "wof:name":"Yanjinggou",
    "wof:placetype":"locality"
},
  "geometry": {"coordinates":[101.389,25.5049],"type":"Point"}
}