{
  "type": "Feature",
  "properties": {
    "gn:admin1_code":"9.0",
    "gn:asciiname":"Caomiaochen",
    "gn:country_code":"CN",
    "gn:dem":162,
    "gn:feature_class":"P",
    "gn:feature_code":"PPL",
    "gn:name":"Caomiaochen",
    "gn:population":0,
    "gn:timezone":"Asia/Shanghai",
    "iso:country":"CN",
    "name:und_x_variant":[
        "\u8349\u5e99\u9648",
        "Caomiaochen"
    ],
    "wof:name":"Caomiaochen",
    "wof:placetype":"locality"
},
  "geometry": {"coordinates":[112.98529000000001,33.88461],"type":"Point"}
}