{
  "type": "Feature",
  "properties": {
    "gn:admin1_code":"8.0",
    "gn:asciiname":"Jinshahecun",
    "gn:country_code":"CN",
    "gn:dem":344,
    "gn:feature_class":"P",
    "gn:feature_code":"PPL",
    "gn:name":"Jinshahecun",
    "gn:population":0,
    "gn:timezone":"Asia/Shanghai",
    "iso:country":"CN",
    "name:zho_x_preferred":[
        "\u91d1\u6c99\u6cb3\u6751"
    ],
    "wof:name":"Jinshahecun",
    "wof:placetype":"locality"
},
  "geometry": {"coordinates":[128.76911999999999,44.99069],"type":"Point"}
}