{
  "type": "Feature",
  "properties": {
    "gn:admin1_code":"1.0",
    "gn:asciiname":"Qiqiaocun",
    "gn:country_code":"CN",
    "gn:dem":5,
    "gn:feature_class":"P",
    "gn:feature_code":"PPL",
    "gn:name":"Qiqiaocun",
    "gn:population":0,
    "gn:timezone":"Asia/Shanghai",
    "iso:country":"CN",
    "name:zho_x_preferred":[
        "\u621a\u6865\u6751"
    ],
    "wof:name":"Qiqiaocun",
    "wof:placetype":"locality"
},
  "geometry": {"coordinates":[118.58646,31.33127],"type":"Point"}
}