{
  "type": "Feature",
  "properties": {
    "gn:admin1_code":"3",
    "gn:asciiname":"Jiangbei",
    "gn:country_code":"CN",
    "gn:dem":103,
    "gn:feature_class":"P",
    "gn:feature_code":"PPL",
    "gn:name":"Jiangbei",
    "gn:population":0,
    "gn:timezone":"Asia/Shanghai",
    "iso:country":"CN",
    "name:deu_x_preferred":[
        "Jiangbei"
    ],
    "name:fra_x_preferred":[
        "Jiangbei"
    ],
    "name:nor_x_preferred":[
        "Jiangbei"
    ],
    "name:swe_x_preferred":[
        "Jiangbei"
    ],
    "name:vie_x_preferred":[
        "Giang B\u1eafc"
    ],
    "name:zho_x_preferred":[
        "\u6c5f\u80cc"
    ],
    "wof:name":"Jiangbei",
    "wof:placetype":"locality"
},
  "geometry": {"coordinates":[114.60984999999999,26.46424],"type":"Point"}
}