{
  "type": "Feature",
  "properties": {
    "gn:admin1_code":"24",
    "gn:asciiname":"Podi",
    "gn:cc2":"CN",
    "gn:country_code":"CN",
    "gn:dem":1064,
    "gn:feature_class":"P",
    "gn:feature_code":"PPL",
    "gn:name":"Podi",
    "gn:population":0,
    "gn:timezone":"Asia/Shanghai",
    "iso:country":"CN",
    "name:und_x_variant":[
        "P\u2019o-ti",
        "Podi"
    ],
    "wof:name":"Podi",
    "wof:placetype":"locality"
},
  "geometry": {"coordinates":[112.34999999999999,37.16667],"type":"Point"}
}