{
  "type": "Feature",
  "properties": {
    "gn:admin1_code":"24.0",
    "gn:asciiname":"Qijiazhuangcun",
    "gn:country_code":"CN",
    "gn:dem":891,
    "gn:feature_class":"P",
    "gn:feature_code":"PPL",
    "gn:name":"Qijiazhuangcun",
    "gn:population":0,
    "gn:timezone":"Asia/Shanghai",
    "iso:country":"CN",
    "name:zho_x_preferred":[
        "\u7941\u5bb6\u5e84\u6751"
    ],
    "wof:name":"Qijiazhuangcun",
    "wof:placetype":"locality"
},
  "geometry": {"coordinates":[114.33999,39.20961],"type":"Point"}
}