{
  "type": "Feature",
  "properties": {
    "gn:admin1_code":"8.0",
    "gn:asciiname":"Wanglutun",
    "gn:country_code":"CN",
    "gn:dem":124,
    "gn:feature_class":"P",
    "gn:feature_code":"PPL",
    "gn:name":"Wanglutun",
    "gn:population":0,
    "gn:timezone":"Asia/Shanghai",
    "iso:country":"CN",
    "name:zho_x_preferred":[
        "\u738b\u8def\u5c6f"
    ],
    "wof:name":"Wanglutun",
    "wof:placetype":"locality"
},
  "geometry": {"coordinates":[125.31089,45.48585],"type":"Point"}
}