{
  "type": "Feature",
  "properties": {
    "gn:admin1_code":"26.0",
    "gn:asciiname":"Hepancun",
    "gn:country_code":"CN",
    "gn:dem":1356,
    "gn:feature_class":"P",
    "gn:feature_code":"PPL",
    "gn:name":"Hepancun",
    "gn:population":0,
    "gn:timezone":"Asia/Shanghai",
    "iso:country":"CN",
    "name:zho_x_preferred":[
        "\u6cb3\u7554\u6751"
    ],
    "wof:name":"Hepancun",
    "wof:placetype":"locality"
},
  "geometry": {"coordinates":[108.31788,37.0099],"type":"Point"}
}