{
  "type": "Feature",
  "properties": {
    "gn:admin1_code":"5.0",
    "gn:asciiname":"Nijia Wazi",
    "gn:country_code":"CN",
    "gn:dem":192,
    "gn:feature_class":"P",
    "gn:feature_code":"PPL",
    "gn:name":"Nijia Wazi",
    "gn:population":0,
    "gn:timezone":"Asia/Shanghai",
    "iso:country":"CN",
    "name:zho_x_preferred":[
        "\u502a\u5bb6\u6d3c\u5b50"
    ],
    "wof:name":"Nijia Wazi",
    "wof:placetype":"locality"
},
  "geometry": {"coordinates":[126.74396000000002,44.66357],"type":"Point"}
}