{
  "type": "Feature",
  "properties": {
    "gn:admin1_code":"24.0",
    "gn:asciiname":"Anxiangsi",
    "gn:country_code":"CN",
    "gn:dem":1022,
    "gn:feature_class":"P",
    "gn:feature_code":"PPL",
    "gn:name":"Anxiangsi",
    "gn:population":0,
    "gn:timezone":"Asia/Shanghai",
    "iso:country":"CN",
    "name:und_x_variant":[
        "\u5b89\u7965\u5bfa"
    ],
    "wof:name":"Anxiangsi",
    "wof:placetype":"locality"
},
  "geometry": {"coordinates":[112.84061,39.50151],"type":"Point"}
}