{
  "type": "Feature",
  "properties": {
    "gn:admin1_code":"11.0",
    "gn:asciiname":"Tudiwan",
    "gn:country_code":"CN",
    "gn:dem":471,
    "gn:feature_class":"P",
    "gn:feature_code":"PPL",
    "gn:name":"Tudiwan",
    "gn:population":0,
    "gn:timezone":"Asia/Shanghai",
    "iso:country":"CN",
    "name:zho_x_preferred":[
        "\u571f\u5730\u6e7e"
    ],
    "wof:name":"Tudiwan",
    "wof:placetype":"locality"
},
  "geometry": {"coordinates":[111.22423999999999,28.11068],"type":"Point"}
}