{
  "type": "Feature",
  "properties": {
    "gn:admin1_code":"18.0",
    "gn:asciiname":"Paishou",
    "gn:country_code":"CN",
    "gn:dem":779,
    "gn:feature_class":"P",
    "gn:feature_code":"PPL",
    "gn:name":"Paishou",
    "gn:population":0,
    "gn:timezone":"Asia/Shanghai",
    "iso:country":"CN",
    "name:zho_x_preferred":[
        "\u6392\u5bff"
    ],
    "wof:name":"Paishou",
    "wof:placetype":"locality"
},
  "geometry": {"coordinates":[108.05500000000001,26.1286],"type":"Point"}
}