{
  "type": "Feature",
  "properties": {
    "gn:admin1_code":"10.0",
    "gn:asciiname":"Yantou",
    "gn:country_code":"CN",
    "gn:dem":312,
    "gn:feature_class":"P",
    "gn:feature_code":"PPL",
    "gn:name":"Yantou",
    "gn:population":0,
    "gn:timezone":"Asia/Shanghai",
    "iso:country":"CN",
    "name:und_x_variant":[
        "\u71d5\u5934"
    ],
    "wof:name":"Yantou",
    "wof:placetype":"locality"
},
  "geometry": {"coordinates":[114.18961000000002,38.77307],"type":"Point"}
}