{
  "type": "Feature",
  "properties": {
    "gn:admin1_code":"29.0",
    "gn:asciiname":"Laolaihong",
    "gn:country_code":"CN",
    "gn:dem":3138,
    "gn:feature_class":"P",
    "gn:feature_code":"PPL",
    "gn:name":"Laolaihong",
    "gn:population":0,
    "gn:timezone":"Asia/Shanghai",
    "iso:country":"CN",
    "name:zho_x_preferred":[
        "\u8001\u6765\u7ea2"
    ],
    "wof:name":"Laolaihong",
    "wof:placetype":"locality"
},
  "geometry": {"coordinates":[102.967,26.2485],"type":"Point"}
}