{
  "type": "Feature",
  "properties": {
    "gn:admin1_code":"5.0",
    "gn:asciiname":"Shajia Yaozi",
    "gn:country_code":"CN",
    "gn:dem":153,
    "gn:feature_class":"P",
    "gn:feature_code":"PPL",
    "gn:name":"Shajia Yaozi",
    "gn:population":0,
    "gn:timezone":"Asia/Shanghai",
    "iso:country":"CN",
    "name:zho_x_preferred":[
        "\u6c99\u5bb6\u7a91\u5b50"
    ],
    "wof:name":"Shajia Yaozi",
    "wof:placetype":"locality"
},
  "geometry": {"coordinates":[123.52894000000001,44.43642],"type":"Point"}
}