{
  "type": "Feature",
  "properties": {
    "gn:admin1_code":"18",
    "gn:asciiname":"Caijiazhai",
    "gn:country_code":"CN",
    "gn:dem":1540,
    "gn:feature_class":"P",
    "gn:feature_code":"PPL",
    "gn:name":"Caijiazhai",
    "gn:population":0,
    "gn:timezone":"Asia/Shanghai",
    "iso:country":"CN",
    "name:zho_x_preferred":[
        "\u8521\u5bb6\u5be8"
    ],
    "wof:name":"Caijiazhai",
    "wof:placetype":"locality"
},
  "geometry": {"coordinates":[105.827,27.116],"type":"Point"}
}