{
  "type": "Feature",
  "properties": {
    "gn:admin1_code":"3.0",
    "gn:asciiname":"Zhaigongba",
    "gn:country_code":"CN",
    "gn:dem":244,
    "gn:feature_class":"P",
    "gn:feature_code":"PPL",
    "gn:name":"Zhaigongba",
    "gn:population":0,
    "gn:timezone":"Asia/Shanghai",
    "iso:country":"CN",
    "name:und_x_variant":[
        "\u658b\u516c\u575d"
    ],
    "wof:name":"Zhaigongba",
    "wof:placetype":"locality"
},
  "geometry": {"coordinates":[115.63021999999999,26.5711],"type":"Point"}
}