{
  "type": "Feature",
  "properties": {
    "gn:admin1_code":"14.0",
    "gn:asciiname":"Xumai",
    "gn:country_code":"CN",
    "gn:dem":3909,
    "gn:feature_class":"P",
    "gn:feature_code":"PPLA4",
    "gn:name":"Xumai",
    "gn:population":0,
    "gn:timezone":"Asia/Urumqi",
    "iso:country":"CN",
    "name:bod_x_preferred":[
        "Xumai"
    ],
    "name:und_x_variant":[
        "Xumai Xiang"
    ],
    "name:zho_x_preferred":[
        "\u7eed\u8fc8"
    ],
    "name:zho_x_variant":[
        "\u7eed\u8fc8\u4e61"
    ],
    "wof:name":"Xumai",
    "wof:placetype":"locality"
},
  "geometry": {"coordinates":[90.26423,29.46921],"type":"Point"}
}