{
  "type": "Feature",
  "properties": {
    "gn:admin1_code":"8.0",
    "gn:asciiname":"Xianwaimao Luchang",
    "gn:country_code":"CN",
    "gn:dem":255,
    "gn:feature_class":"P",
    "gn:feature_code":"PPLF",
    "gn:name":"Xianwaimao Luchang",
    "gn:population":0,
    "gn:timezone":"Asia/Shanghai",
    "iso:country":"CN",
    "name:zho_x_preferred":[
        "\u53bf\u5916\u8d38\u9e7f\u573a"
    ],
    "wof:name":"Xianwaimao Luchang",
    "wof:placetype":"locality"
},
  "geometry": {"coordinates":[127.9663,49.43056],"type":"Point"}
}