{
  "type": "Feature",
  "properties": {
    "gn:admin1_code":"1.0",
    "gn:asciiname":"Yinying",
    "gn:country_code":"CN",
    "gn:dem":33,
    "gn:feature_class":"P",
    "gn:feature_code":"PPL",
    "gn:name":"Yinying",
    "gn:population":0,
    "gn:timezone":"Asia/Shanghai",
    "iso:country":"CN",
    "name:zho_x_preferred":[
        "\u6bb7\u90e2"
    ],
    "wof:name":"Yinying",
    "wof:placetype":"locality"
},
  "geometry": {"coordinates":[118.54631000000001,32.45171],"type":"Point"}
}