{
  "type": "Feature",
  "properties": {
    "gn:admin1_code":"32.0",
    "gn:asciiname":"Piannali",
    "gn:country_code":"CN",
    "gn:dem":1461,
    "gn:feature_class":"P",
    "gn:feature_code":"PPL",
    "gn:name":"Piannali",
    "gn:population":0,
    "gn:timezone":"Asia/Shanghai",
    "iso:country":"CN",
    "name:zho_x_preferred":[
        "\u7247\u90a3\u7acb"
    ],
    "wof:name":"Piannali",
    "wof:placetype":"locality"
},
  "geometry": {"coordinates":[101.78100000000001,26.33184],"type":"Point"}
}