{
  "type": "Feature",
  "properties": {
    "gn:admin1_code":"3.0",
    "gn:asciiname":"Lichuan",
    "gn:country_code":"CN",
    "gn:dem":74,
    "gn:feature_class":"P",
    "gn:feature_code":"PPL",
    "gn:name":"Lichuan",
    "gn:population":0,
    "gn:timezone":"Asia/Shanghai",
    "iso:country":"CN",
    "name:ceb_x_preferred":[
        "Lichuan"
    ],
    "name:deu_x_preferred":[
        "Lichuan"
    ],
    "name:fra_x_preferred":[
        "Lichuan"
    ],
    "name:nor_x_preferred":[
        "Lichuan"
    ],
    "name:swe_x_preferred":[
        "Lichuan"
    ],
    "name:und_x_variant":[
        "\u67a5\u5ddd"
    ],
    "wof:name":"Lichuan",
    "wof:placetype":"locality"
},
  "geometry": {"coordinates":[115.08403,27.57257],"type":"Point"}
}