{
  "type": "Feature",
  "properties": {
    "gn:admin1_code":"30.0",
    "gn:asciiname":"Baigeping",
    "gn:country_code":"CN",
    "gn:dem":73,
    "gn:feature_class":"P",
    "gn:feature_code":"PPL",
    "gn:name":"Baigeping",
    "gn:population":0,
    "gn:timezone":"Asia/Shanghai",
    "iso:country":"CN",
    "name:zho_x_preferred":[
        "\u767d\u9e3d\u576a"
    ],
    "wof:name":"Baigeping",
    "wof:placetype":"locality"
},
  "geometry": {"coordinates":[114.20757,23.67066],"type":"Point"}
}