{
  "type": "Feature",
  "properties": {
    "gn:admin1_code":"30.0",
    "gn:asciiname":"Dushucun",
    "gn:country_code":"CN",
    "gn:dem":11,
    "gn:feature_class":"P",
    "gn:feature_code":"PPL",
    "gn:name":"Dushucun",
    "gn:population":0,
    "gn:timezone":"Asia/Shanghai",
    "iso:country":"CN",
    "name:zho_x_preferred":[
        "\u72ec\u6811\u6751"
    ],
    "wof:name":"Dushucun",
    "wof:placetype":"locality"
},
  "geometry": {"coordinates":[116.65130000000001,23.59241],"type":"Point"}
}