{
  "type": "Feature",
  "properties": {
    "gn:admin1_code":"19.0",
    "gn:asciiname":"Damengou",
    "gn:country_code":"CN",
    "gn:dem":249,
    "gn:feature_class":"P",
    "gn:feature_code":"PPL",
    "gn:name":"Damengou",
    "gn:population":0,
    "gn:timezone":"Asia/Shanghai",
    "iso:country":"CN",
    "name:und_x_variant":[
        "\u5927\u95e8\u6c9f"
    ],
    "wof:name":"Damengou",
    "wof:placetype":"locality"
},
  "geometry": {"coordinates":[124.65000999999999,41.77181],"type":"Point"}
}