{
  "type": "Feature",
  "properties": {
    "gn:admin1_code":"32.0",
    "gn:asciiname":"Yiwanshui",
    "gn:country_code":"CN",
    "gn:dem":1276,
    "gn:feature_class":"P",
    "gn:feature_code":"PPL",
    "gn:name":"Yiwanshui",
    "gn:population":0,
    "gn:timezone":"Asia/Shanghai",
    "iso:country":"CN",
    "name:zho_x_preferred":[
        "\u4e00\u6e7e\u6c34"
    ],
    "wof:name":"Yiwanshui",
    "wof:placetype":"locality"
},
  "geometry": {"coordinates":[108.26900000000001,31.9042],"type":"Point"}
}