{
  "type": "Feature",
  "properties": {
    "gn:admin1_code":"19.0",
    "gn:asciiname":"Xiaoqiaozi",
    "gn:country_code":"CN",
    "gn:dem":27,
    "gn:feature_class":"P",
    "gn:feature_code":"PPL",
    "gn:name":"Xiaoqiaozi",
    "gn:population":0,
    "gn:timezone":"Asia/Shanghai",
    "iso:country":"CN",
    "name:und_x_variant":[
        "\u5c0f\u6865\u5b50"
    ],
    "name:zho_x_preferred":[
        "\u5c0f\u6865\u5b50"
    ],
    "wof:name":"Xiaoqiaozi",
    "wof:placetype":"locality"
},
  "geometry": {"coordinates":[122.8079,41.84285],"type":"Point"}
}