{
  "type": "Feature",
  "properties": {
    "gn:admin1_code":"1.0",
    "gn:asciiname":"Yujiafancun",
    "gn:country_code":"CN",
    "gn:dem":314,
    "gn:feature_class":"P",
    "gn:feature_code":"PPL",
    "gn:name":"Yujiafancun",
    "gn:population":0,
    "gn:timezone":"Asia/Shanghai",
    "iso:country":"CN",
    "name:und_x_variant":[
        "Yujiafan"
    ],
    "name:zho_x_preferred":[
        "\u4fde\u5bb6\u7548\u6751"
    ],
    "wof:name":"Yujiafancun",
    "wof:placetype":"locality"
},
  "geometry": {"coordinates":[116.1643,31.21741],"type":"Point"}
}