{
  "type": "Feature",
  "properties": {
    "gn:admin1_code":"02",
    "gn:asciiname":"Guihua",
    "gn:cc2":"CN",
    "gn:country_code":"CN",
    "gn:dem":3,
    "gn:feature_class":"P",
    "gn:feature_code":"PPL",
    "gn:name":"Guihua",
    "gn:population":0,
    "gn:timezone":"Asia/Shanghai",
    "iso:country":"CN",
    "name:ceb_x_preferred":[
        "Guihua"
    ],
    "name:deu_x_preferred":[
        "Guihua"
    ],
    "name:swe_x_preferred":[
        "Guihua"
    ],
    "name:und_x_variant":[
        "Kuei-hua-y\u00fcan"
    ],
    "wof:name":"Guihua",
    "wof:placetype":"locality"
},
  "geometry": {"coordinates":[122.33083000000001,30.44778],"type":"Point"}
}