{
  "type": "Feature",
  "properties": {
    "gn:admin1_code":"16.0",
    "gn:asciiname":"Xintian",
    "gn:country_code":"CN",
    "gn:dem":202,
    "gn:feature_class":"P",
    "gn:feature_code":"PPL",
    "gn:name":"Xintian",
    "gn:population":0,
    "gn:timezone":"Asia/Shanghai",
    "iso:country":"CN",
    "name:ceb_x_preferred":[
        "Xintian"
    ],
    "name:deu_x_preferred":[
        "Xintian"
    ],
    "name:zho_x_preferred":[
        "\u65b0\u7530"
    ],
    "name:zho_x_variant":[
        "\u65b0\u7530\u9109"
    ],
    "wof:name":"Xintian",
    "wof:placetype":"locality"
},
  "geometry": {"coordinates":[111.334,24.3808],"type":"Point"}
}