{
  "type": "Feature",
  "properties": {
    "gn:admin1_code":"25.0",
    "gn:asciiname":"Yahoucun",
    "gn:country_code":"CN",
    "gn:dem":305,
    "gn:feature_class":"P",
    "gn:feature_code":"PPL",
    "gn:name":"Yahoucun",
    "gn:population":0,
    "gn:timezone":"Asia/Shanghai",
    "iso:country":"CN",
    "name:zho_x_preferred":[
        "\u7259\u540e\u6751"
    ],
    "wof:name":"Yahoucun",
    "wof:placetype":"locality"
},
  "geometry": {"coordinates":[121.06229999999999,37.23898],"type":"Point"}
}