{
  "type": "Feature",
  "properties": {
    "gn:admin1_code":"9.0",
    "gn:asciiname":"Zhoucun",
    "gn:country_code":"CN",
    "gn:dem":192,
    "gn:feature_class":"P",
    "gn:feature_code":"PPL",
    "gn:name":"Zhoucun",
    "gn:population":0,
    "gn:timezone":"Asia/Shanghai",
    "iso:country":"CN",
    "name:und_x_variant":[
        "Miaocun"
    ],
    "name:zho_x_preferred":[
        "\u5468\u6751"
    ],
    "wof:name":"Zhoucun",
    "wof:placetype":"locality"
},
  "geometry": {"coordinates":[112.26628999999998,34.53552],"type":"Point"}
}