{
  "type": "Feature",
  "properties": {
    "gn:admin1_code":"30.0",
    "gn:asciiname":"Tongdeli",
    "gn:country_code":"CN",
    "gn:dem":2,
    "gn:feature_class":"P",
    "gn:feature_code":"PPL",
    "gn:name":"Tongdeli",
    "gn:population":0,
    "gn:timezone":"Asia/Shanghai",
    "iso:country":"CN",
    "name:zho_x_preferred":[
        "\u540c\u5fb7\u91cc"
    ],
    "wof:name":"Tongdeli",
    "wof:placetype":"locality"
},
  "geometry": {"coordinates":[112.63370999999999,22.39822],"type":"Point"}
}