{
  "type": "Feature",
  "properties": {
    "gn:admin1_code":"8.0",
    "gn:asciiname":"Chaoyangcun",
    "gn:country_code":"CN",
    "gn:dem":348,
    "gn:feature_class":"P",
    "gn:feature_code":"PPL",
    "gn:name":"Chaoyangcun",
    "gn:population":0,
    "gn:timezone":"Asia/Shanghai",
    "iso:country":"CN",
    "name:zho_x_preferred":[
        "\u671d\u9633\u6751"
    ],
    "wof:name":"Chaoyangcun",
    "wof:placetype":"locality"
},
  "geometry": {"coordinates":[130.06541999999999,45.15322000000001],"type":"Point"}
}