{
  "type": "Feature",
  "properties": {
    "gn:admin1_code":"30.0",
    "gn:asciiname":"Xinxiang",
    "gn:country_code":"CN",
    "gn:dem":20,
    "gn:feature_class":"P",
    "gn:feature_code":"PPL",
    "gn:name":"Xinxiang",
    "gn:population":0,
    "gn:timezone":"Asia/Shanghai",
    "iso:country":"CN",
    "name:afr_x_preferred":[
        "Xinxiang"
    ],
    "name:ara_x_preferred":[
        "\u0634\u064a\u0646\u0634\u064a\u0627\u0646\u063a"
    ],
    "name:ast_x_preferred":[
        "Xinxiang"
    ],
    "name:bul_x_preferred":[
        "\u0421\u0438\u043d\u0441\u044f\u043d"
    ],
    "name:cdo_x_preferred":[
        "S\u012dng-hi\u014fng"
    ],
    "name:ces_x_preferred":[
        "Sin-siang"
    ],
    "name:dan_x_preferred":[
        "Xinxiang"
    ],
    "name:deu_x_preferred":[
        "Xinxiang"
    ],
    "name:epo_x_preferred":[
        "Sinsjan"
    ],
    "name:eus_x_preferred":[
        "Xinxiang"
    ],
    "name:fas_x_preferred":[
        "\u0634\u06cc\u0646\u0634\u06cc\u0627\u0646\u06af"
    ],
    "name:fin_x_preferred":[
        "Xinxiang"
    ],
    "name:fra_x_preferred":[
        "Xinxiang"
    ],
    "name:ind_x_preferred":[
        "Xinxiang"
    ],
    "name:ita_x_preferred":[
        "Xinxiang"
    ],
    "name:jpn_x_preferred":[
        "\u65b0\u90f7\u5e02"
    ],
    "name:kik_x_preferred":[
        "Xinxiang"
    ],
    "name:kor_x_preferred":[
        "\uc2e0\uc0f9\uc2dc"
    ],
    "name:mlg_x_preferred":[
        "Xinxiang"
    ],
    "name:nld_x_preferred":[
        "Xinxiang"
    ],
    "name:nno_x_preferred":[
        "Xinxiang"
    ],
    "name:nor_x_preferred":[
        "Xinxiang"
    ],
    "name:pam_x_preferred":[
        "Xinxiang"
    ],
    "name:pol_x_preferred":[
        "Xinxiang"
    ],
    "name:por_x_preferred":[
        "Xinxiang"
    ],
    "name:rus_x_preferred":[
        "\u0421\u0438\u043d\u044c\u0441\u044f\u043d"
    ],
    "name:spa_x_preferred":[
        "Xinxiang"
    ],
    "name:srp_x_preferred":[
        "\u0421\u0438\u043d\u0441\u0458\u0430\u043d\u0433"
    ],
    "name:swe_x_preferred":[
        "Xinxiang"
    ],
    "name:tur_x_preferred":[
        "Xinxiang"
    ],
    "name:uig_x_preferred":[
        "\u0634\u0649\u0646\u0634\u064a\u0627\u06ad \u0634\u06d5\u06be\u0649\u0631\u0649"
    ],
    "name:urd_x_preferred":[
        "\u0634\u0646\u0634\u06cc\u0627\u0646\u06af"
    ],
    "name:vie_x_preferred":[
        "T\u00e2n H\u01b0\u01a1ng"
    ],
    "name:war_x_preferred":[
        "Xinxiang"
    ],
    "name:zho_x_preferred":[
        "\u65b0\u4e61"
    ],
    "name:zho_x_variant":[
        "\u65b0\u4e61\u5e02"
    ],
    "wof:name":"Xinxiang",
    "wof:placetype":"locality"
},
  "geometry": {"coordinates":[116.39739,22.97024],"type":"Point"}
}