{
  "type": "Feature",
  "properties": {
    "gn:admin1_code":"25",
    "gn:asciiname":"Huili",
    "gn:country_code":"CN",
    "gn:dem":41,
    "gn:feature_class":"P",
    "gn:feature_code":"PPLA4",
    "gn:name":"Huili",
    "gn:population":0,
    "gn:timezone":"Asia/Shanghai",
    "iso:country":"CN",
    "name:und_x_variant":[
        "Huili Zhen"
    ],
    "name:zho_x_preferred":[
        "\u56de\u91cc"
    ],
    "name:zho_x_variant":[
        "\u56de\u91cc\u9547"
    ],
    "wof:name":"Huili",
    "wof:placetype":"locality"
},
  "geometry": {"coordinates":[121.31842,37.33302],"type":"Point"}
}