{
  "type": "Feature",
  "properties": {
    "gn:admin1_code":"15.0",
    "gn:asciiname":"Tielubei",
    "gn:country_code":"CN",
    "gn:dem":1681,
    "gn:feature_class":"P",
    "gn:feature_code":"PPL",
    "gn:name":"Tielubei",
    "gn:population":0,
    "gn:timezone":"Asia/Shanghai",
    "iso:country":"CN",
    "name:und_x_variant":[
        "\u94c1\u7089\u80cc"
    ],
    "wof:name":"Tielubei",
    "wof:placetype":"locality"
},
  "geometry": {"coordinates":[105.19499,33.09502],"type":"Point"}
}