{
  "type": "Feature",
  "properties": {
    "gn:admin1_code":"2.0",
    "gn:asciiname":"Quchitan",
    "gn:country_code":"CN",
    "gn:dem":470,
    "gn:feature_class":"P",
    "gn:feature_code":"PPL",
    "gn:name":"Quchitan",
    "gn:population":0,
    "gn:timezone":"Asia/Shanghai",
    "iso:country":"CN",
    "name:zho_x_preferred":[
        "\u66f2\u5c3a\u6f6d"
    ],
    "wof:name":"Quchitan",
    "wof:placetype":"locality"
},
  "geometry": {"coordinates":[119.90852,27.46368],"type":"Point"}
}