{
  "type": "Feature",
  "properties": {
    "gn:admin1_code":"15.0",
    "gn:asciiname":"Huangjiayuan",
    "gn:country_code":"CN",
    "gn:dem":1478,
    "gn:feature_class":"P",
    "gn:feature_code":"PPL",
    "gn:name":"Huangjiayuan",
    "gn:population":0,
    "gn:timezone":"Asia/Shanghai",
    "iso:country":"CN",
    "name:und_x_variant":[
        "\u9ec4\u5bb6\u586c"
    ],
    "wof:name":"Huangjiayuan",
    "wof:placetype":"locality"
},
  "geometry": {"coordinates":[107.55800000000001,36.025],"type":"Point"}
}