{
  "type": "Feature",
  "properties": {
    "gn:admin1_code":"30",
    "gn:asciiname":"Pinghai",
    "gn:country_code":"CN",
    "gn:dem":30,
    "gn:feature_class":"P",
    "gn:feature_code":"PPLA4",
    "gn:name":"Pinghai",
    "gn:population":0,
    "gn:timezone":"Asia/Shanghai",
    "iso:country":"CN",
    "name:und_x_variant":[
        "Pinghoi",
        "\u5e73\u6d77",
        "Pinghai",
        "Pinghai Zhen",
        "\u5e73\u6d77\u9547"
    ],
    "wof:name":"Pinghai",
    "wof:placetype":"locality"
},
  "geometry": {"coordinates":[114.87206999999999,22.61762],"type":"Point"}
}