{
  "type": "Feature",
  "properties": {
    "gn:admin1_code":"11.0",
    "gn:asciiname":"Huangjiazui",
    "gn:country_code":"CN",
    "gn:dem":52,
    "gn:feature_class":"P",
    "gn:feature_code":"PPL",
    "gn:name":"Huangjiazui",
    "gn:population":0,
    "gn:timezone":"Asia/Shanghai",
    "iso:country":"CN",
    "name:zho_x_preferred":[
        "\u7687\u5609\u5480"
    ],
    "wof:name":"Huangjiazui",
    "wof:placetype":"locality"
},
  "geometry": {"coordinates":[112.93814,27.38846],"type":"Point"}
}