{
  "type": "Feature",
  "properties": {
    "gn:admin1_code":"3.0",
    "gn:asciiname":"Guazhoucun",
    "gn:country_code":"CN",
    "gn:dem":19,
    "gn:feature_class":"P",
    "gn:feature_code":"PPL",
    "gn:name":"Guazhoucun",
    "gn:population":0,
    "gn:timezone":"Asia/Shanghai",
    "iso:country":"CN",
    "name:und_x_variant":[
        "\u74dc\u6d32\u6751"
    ],
    "wof:name":"Guazhoucun",
    "wof:placetype":"locality"
},
  "geometry": {"coordinates":[115.93991,28.78539],"type":"Point"}
}