{
  "type": "Feature",
  "properties": {
    "gn:admin1_code":"10",
    "gn:asciiname":"Xiangshuigou",
    "gn:country_code":"CN",
    "gn:dem":1176,
    "gn:feature_class":"P",
    "gn:feature_code":"PPL",
    "gn:name":"Xiangshuigou",
    "gn:population":0,
    "gn:timezone":"Asia/Shanghai",
    "iso:country":"CN",
    "name:und_x_variant":[
        "Hsiang-shui-kou",
        "Xiangshuigou"
    ],
    "name:zho_x_preferred":[
        "\u54cd\u6c34\u6c9f"
    ],
    "wof:name":"Xiangshuigou",
    "wof:placetype":"locality"
},
  "geometry": {"coordinates":[114.24531,40.18464],"type":"Point"}
}