{
  "type": "Feature",
  "properties": {
    "gn:admin1_code":"7",
    "gn:asciiname":"Houcuodi",
    "gn:country_code":"CN",
    "gn:dem":8,
    "gn:feature_class":"P",
    "gn:feature_code":"PPL",
    "gn:name":"Houcuodi",
    "gn:population":0,
    "gn:timezone":"Asia/Shanghai",
    "iso:country":"CN",
    "name:zho_x_preferred":[
        "\u540e\u539d\u5e95"
    ],
    "wof:name":"Houcuodi",
    "wof:placetype":"locality"
},
  "geometry": {"coordinates":[119.20922,25.30767],"type":"Point"}
}