{
  "type": "Feature",
  "properties": {
    "gn:admin1_code":"19.0",
    "gn:asciiname":"Xiaoxinglonggou",
    "gn:country_code":"CN",
    "gn:dem":149,
    "gn:feature_class":"P",
    "gn:feature_code":"PPL",
    "gn:name":"Xiaoxinglonggou",
    "gn:population":0,
    "gn:timezone":"Asia/Shanghai",
    "iso:country":"CN",
    "name:zho_x_preferred":[
        "\u5c0f\u5174\u9686\u6c9f"
    ],
    "wof:name":"Xiaoxinglonggou",
    "wof:placetype":"locality"
},
  "geometry": {"coordinates":[124.02749,42.78258],"type":"Point"}
}