{
  "type": "Feature",
  "properties": {
    "gn:admin1_code":"1.0",
    "gn:asciiname":"Zhashancun",
    "gn:country_code":"CN",
    "gn:dem":41,
    "gn:feature_class":"P",
    "gn:feature_code":"PPL",
    "gn:name":"Zhashancun",
    "gn:population":0,
    "gn:timezone":"Asia/Shanghai",
    "iso:country":"CN",
    "name:zho_x_preferred":[
        "\u95f8\u5c71\u6751"
    ],
    "wof:name":"Zhashancun",
    "wof:placetype":"locality"
},
  "geometry": {"coordinates":[117.21210000000001,31.31293],"type":"Point"}
}