{
  "type": "Feature",
  "properties": {
    "gn:admin1_code":"29.0",
    "gn:asciiname":"Dengmu",
    "gn:country_code":"CN",
    "gn:dem":2298,
    "gn:feature_class":"P",
    "gn:feature_code":"PPL",
    "gn:name":"Dengmu",
    "gn:population":0,
    "gn:timezone":"Asia/Shanghai",
    "iso:country":"CN",
    "name:zho_x_preferred":[
        "\u767b\u6bcd"
    ],
    "wof:name":"Dengmu",
    "wof:placetype":"locality"
},
  "geometry": {"coordinates":[99.7026,25.749],"type":"Point"}
}