{
  "type": "Feature",
  "properties": {
    "gn:admin1_code":"9.0",
    "gn:asciiname":"Maichuan",
    "gn:country_code":"CN",
    "gn:dem":155,
    "gn:feature_class":"P",
    "gn:feature_code":"PPL",
    "gn:name":"Maichuan",
    "gn:population":0,
    "gn:timezone":"Asia/Shanghai",
    "iso:country":"CN",
    "name:und_x_variant":[
        "\u9ea6\u5ddd",
        "Maichuan"
    ],
    "wof:name":"Maichuan",
    "wof:placetype":"locality"
},
  "geometry": {"coordinates":[112.97186000000001,33.59312],"type":"Point"}
}