{
  "type": "Feature",
  "properties": {
    "gn:admin1_code":"33.0",
    "gn:asciiname":"Shouba",
    "gn:country_code":"CN",
    "gn:dem":339,
    "gn:feature_class":"P",
    "gn:feature_code":"PPL",
    "gn:name":"Shouba",
    "gn:population":0,
    "gn:timezone":"Asia/Shanghai",
    "iso:country":"CN",
    "name:zho_x_preferred":[
        "\u624b\u628a"
    ],
    "wof:name":"Shouba",
    "wof:placetype":"locality"
},
  "geometry": {"coordinates":[105.90791000000002,30.37379],"type":"Point"}
}