{
  "type": "Feature",
  "properties": {
    "gn:admin1_code":"29.0",
    "gn:asciiname":"Baiwangzhai",
    "gn:country_code":"CN",
    "gn:dem":2188,
    "gn:feature_class":"P",
    "gn:feature_code":"PPL",
    "gn:name":"Baiwangzhai",
    "gn:population":0,
    "gn:timezone":"Asia/Shanghai",
    "iso:country":"CN",
    "name:zho_x_preferred":[
        "\u767e\u738b\u5be8"
    ],
    "wof:name":"Baiwangzhai",
    "wof:placetype":"locality"
},
  "geometry": {"coordinates":[102.45699999999999,25.07800000000001],"type":"Point"}
}