{
  "type": "Feature",
  "properties": {
    "gn:admin1_code":"32.0",
    "gn:asciiname":"Shandingshang",
    "gn:country_code":"CN",
    "gn:dem":259,
    "gn:feature_class":"P",
    "gn:feature_code":"PPL",
    "gn:name":"Shandingshang",
    "gn:population":0,
    "gn:timezone":"Asia/Shanghai",
    "iso:country":"CN",
    "name:zho_x_preferred":[
        "\u5c71\u9876\u4e0a"
    ],
    "wof:name":"Shandingshang",
    "wof:placetype":"locality"
},
  "geometry": {"coordinates":[105.73853,28.63213],"type":"Point"}
}