{
  "type": "Feature",
  "properties": {
    "gn:admin1_code":"12.0",
    "gn:asciiname":"Daganxi",
    "gn:country_code":"CN",
    "gn:dem":1089,
    "gn:feature_class":"P",
    "gn:feature_code":"PPL",
    "gn:name":"Daganxi",
    "gn:population":0,
    "gn:timezone":"Asia/Shanghai",
    "iso:country":"CN",
    "name:zho_x_preferred":[
        "\u5927\u5e72\u6eaa"
    ],
    "wof:name":"Daganxi",
    "wof:placetype":"locality"
},
  "geometry": {"coordinates":[110.38598,31.88797000000001],"type":"Point"}
}