{
  "type": "Feature",
  "properties": {
    "gn:admin1_code":"31",
    "gn:asciiname":"Zhousancun",
    "gn:country_code":"CN",
    "gn:dem":205,
    "gn:feature_class":"P",
    "gn:feature_code":"PPL",
    "gn:name":"Zhousancun",
    "gn:population":0,
    "gn:timezone":"Asia/Shanghai",
    "iso:country":"CN",
    "name:zho_x_preferred":[
        "\u5468\u4e09\u6751"
    ],
    "wof:name":"Zhousancun",
    "wof:placetype":"locality"
},
  "geometry": {"coordinates":[109.53256,19.21129],"type":"Point"}
}