{
  "type": "Feature",
  "properties": {
    "gn:admin1_code":"25.0",
    "gn:asciiname":"Erlicun",
    "gn:country_code":"CN",
    "gn:dem":92,
    "gn:feature_class":"P",
    "gn:feature_code":"PPL",
    "gn:name":"Erlicun",
    "gn:population":0,
    "gn:timezone":"Asia/Shanghai",
    "iso:country":"CN",
    "name:zho_x_preferred":[
        "\u4e8c\u91cc\u6751"
    ],
    "wof:name":"Erlicun",
    "wof:placetype":"locality"
},
  "geometry": {"coordinates":[117.93714,36.63996],"type":"Point"}
}