{
  "type": "Feature",
  "properties": {
    "gn:admin1_code":"33.0",
    "gn:asciiname":"Fanjiawan",
    "gn:country_code":"CN",
    "gn:dem":486,
    "gn:feature_class":"P",
    "gn:feature_code":"PPL",
    "gn:name":"Fanjiawan",
    "gn:population":0,
    "gn:timezone":"Asia/Shanghai",
    "iso:country":"CN",
    "name:zho_x_preferred":[
        "\u8303\u5bb6\u6e7e"
    ],
    "wof:name":"Fanjiawan",
    "wof:placetype":"locality"
},
  "geometry": {"coordinates":[109.66545000000001,31.28024000000001],"type":"Point"}
}