{
  "type": "Feature",
  "properties": {
    "gn:admin1_code":"14.0",
    "gn:asciiname":"Mode",
    "gn:country_code":"CN",
    "gn:dem":2612,
    "gn:feature_class":"P",
    "gn:feature_code":"PPL",
    "gn:name":"Mode",
    "gn:population":0,
    "gn:timezone":"Asia/Urumqi",
    "iso:country":"CN",
    "name:zho_x_preferred":[
        "\u83ab\u5f97"
    ],
    "wof:name":"Mode",
    "wof:placetype":"locality"
},
  "geometry": {"coordinates":[98.5381,28.59559],"type":"Point"}
}