{
  "type": "Feature",
  "properties": {
    "gn:admin1_code":"14.0",
    "gn:asciiname":"Mode",
    "gn:country_code":"CN",
    "gn:dem":2612,
    "gn:feature_class":"P",
    "gn:feature_code":"PPL",
    "gn:name":"Mode",
    "gn:population":0,
    "gn:timezone":"Asia/Urumqi",
    "iso:country":"CN",
    "name:ara_x_preferred":[
        "\u0645\u062f"
    ],
    "name:ceb_x_preferred":[
        "Mode"
    ],
    "name:ces_x_preferred":[
        "M\u00f3d"
    ],
    "name:deu_x_preferred":[
        "Mode"
    ],
    "name:est_x_preferred":[
        "Moodus"
    ],
    "name:fin_x_preferred":[
        "Moodi"
    ],
    "name:fra_x_preferred":[
        "Mode"
    ],
    "name:ita_x_preferred":[
        "Mode"
    ],
    "name:jpn_x_preferred":[
        "\u30e2\u30fc\u30c9"
    ],
    "name:scn_x_preferred":[
        "Modu"
    ],
    "name:sun_x_preferred":[
        "Mode"
    ],
    "name:swe_x_preferred":[
        "Mode"
    ],
    "name:vie_x_preferred":[
        "Mode"
    ],
    "name:zho_x_preferred":[
        "\u83ab\u5f97"
    ],
    "wof:name":"Mode",
    "wof:placetype":"locality"
},
  "geometry": {"coordinates":[98.5381,28.59559],"type":"Point"}
}