{
  "type": "Feature",
  "properties": {
    "gn:admin1_code":"16.0",
    "gn:asciiname":"Pomao",
    "gn:country_code":"CN",
    "gn:dem":280,
    "gn:feature_class":"P",
    "gn:feature_code":"PPL",
    "gn:name":"Pomao",
    "gn:population":0,
    "gn:timezone":"Asia/Shanghai",
    "iso:country":"CN",
    "name:zho_x_preferred":[
        "\u5761\u5e3d"
    ],
    "wof:name":"Pomao",
    "wof:placetype":"locality"
},
  "geometry": {"coordinates":[107.47199999999999,23.5284],"type":"Point"}
}