{
  "type": "Feature",
  "properties": {
    "gn:admin1_code":"21.0",
    "gn:asciiname":"Gudigou",
    "gn:country_code":"CN",
    "gn:dem":1701,
    "gn:feature_class":"P",
    "gn:feature_code":"PPL",
    "gn:name":"Gudigou",
    "gn:population":0,
    "gn:timezone":"Asia/Shanghai",
    "iso:country":"CN",
    "name:zho_x_preferred":[
        "\u8c37\u5730\u6c9f"
    ],
    "wof:name":"Gudigou",
    "wof:placetype":"locality"
},
  "geometry": {"coordinates":[105.411,36.8802],"type":"Point"}
}