{
  "type": "Feature",
  "properties": {
    "gn:admin1_code":"29.0",
    "gn:asciiname":"Shangmawu",
    "gn:country_code":"CN",
    "gn:dem":1759,
    "gn:feature_class":"P",
    "gn:feature_code":"PPL",
    "gn:name":"Shangmawu",
    "gn:population":0,
    "gn:timezone":"Asia/Shanghai",
    "iso:country":"CN",
    "name:zho_x_preferred":[
        "\u4e0a\u9a6c\u52a1"
    ],
    "wof:name":"Shangmawu",
    "wof:placetype":"locality"
},
  "geometry": {"coordinates":[100.09999999999999,24.5093],"type":"Point"}
}