{
  "type": "Feature",
  "properties": {
    "gn:admin1_code":"26.0",
    "gn:asciiname":"Dongcuncun",
    "gn:country_code":"CN",
    "gn:dem":715,
    "gn:feature_class":"P",
    "gn:feature_code":"PPL",
    "gn:name":"Dongcuncun",
    "gn:population":0,
    "gn:timezone":"Asia/Shanghai",
    "iso:country":"CN",
    "name:zho_x_preferred":[
        "\u4e1c\u6751\u6751"
    ],
    "wof:name":"Dongcuncun",
    "wof:placetype":"locality"
},
  "geometry": {"coordinates":[109.90191000000002,33.86965],"type":"Point"}
}