{
  "type": "Feature",
  "properties": {
    "gn:admin1_code":"32.0",
    "gn:asciiname":"Chaobeigou",
    "gn:country_code":"CN",
    "gn:dem":1145,
    "gn:feature_class":"P",
    "gn:feature_code":"PPL",
    "gn:name":"Chaobeigou",
    "gn:population":0,
    "gn:timezone":"Asia/Shanghai",
    "iso:country":"CN",
    "name:zho_x_preferred":[
        "\u671d\u5317\u6c9f"
    ],
    "wof:name":"Chaobeigou",
    "wof:placetype":"locality"
},
  "geometry": {"coordinates":[104.959,32.0565],"type":"Point"}
}