{
  "type": "Feature",
  "properties": {
    "gn:admin1_code":"1.0",
    "gn:asciiname":"Xuyingcun",
    "gn:country_code":"CN",
    "gn:dem":41,
    "gn:feature_class":"P",
    "gn:feature_code":"PPL",
    "gn:name":"Xuyingcun",
    "gn:population":0,
    "gn:timezone":"Asia/Shanghai",
    "iso:country":"CN",
    "name:zho_x_preferred":[
        "\u5f90\u8425\u6751"
    ],
    "wof:name":"Xuyingcun",
    "wof:placetype":"locality"
},
  "geometry": {"coordinates":[115.29273000000001,32.8913],"type":"Point"}
}