{
  "type": "Feature",
  "properties": {
    "gn:admin1_code":"24.0",
    "gn:asciiname":"Hujiaping",
    "gn:country_code":"CN",
    "gn:dem":1359,
    "gn:feature_class":"P",
    "gn:feature_code":"PPL",
    "gn:name":"Hujiaping",
    "gn:population":0,
    "gn:timezone":"Asia/Shanghai",
    "iso:country":"CN",
    "name:zho_x_preferred":[
        "\u80e1\u5bb6\u576a"
    ],
    "wof:name":"Hujiaping",
    "wof:placetype":"locality"
},
  "geometry": {"coordinates":[112.63573999999998,37.29797],"type":"Point"}
}