{
  "type": "Feature",
  "properties": {
    "gn:admin1_code":"32.0",
    "gn:asciiname":"Li'erping",
    "gn:country_code":"CN",
    "gn:dem":1515,
    "gn:feature_class":"P",
    "gn:feature_code":"PPL",
    "gn:name":"Li\u2019erping",
    "gn:population":0,
    "gn:timezone":"Asia/Shanghai",
    "iso:country":"CN",
    "name:zho_x_preferred":[
        "\u68a8\u513f\u576a"
    ],
    "name:zho_x_variant":[
        "Li\u2019erping"
    ],
    "wof:name":"Li'erping",
    "wof:placetype":"locality"
},
  "geometry": {"coordinates":[102.58018,29.55162],"type":"Point"}
}