{
  "type": "Feature",
  "properties": {
    "gn:admin1_code":"1.0",
    "gn:asciiname":"Changtang",
    "gn:country_code":"CN",
    "gn:dem":28,
    "gn:feature_class":"P",
    "gn:feature_code":"PPL",
    "gn:name":"Changtang",
    "gn:population":0,
    "gn:timezone":"Asia/Shanghai",
    "iso:country":"CN",
    "name:bih_x_preferred":[
        "\u091a\u093e\u0902\u0917\u0924\u093e\u0902\u0917"
    ],
    "name:ces_x_preferred":[
        "\u010changthang"
    ],
    "name:deu_x_preferred":[
        "Changthang"
    ],
    "name:fin_x_preferred":[
        "Changtang"
    ],
    "name:fra_x_preferred":[
        "Changtang"
    ],
    "name:hin_x_preferred":[
        "\u091a\u093e\u0902\u0917\u0925\u0902\u0917"
    ],
    "name:ita_x_preferred":[
        "Qiangtang"
    ],
    "name:lit_x_preferred":[
        "\u010cangtangas"
    ],
    "name:mwl_x_preferred":[
        "Changtang"
    ],
    "name:nld_x_preferred":[
        "Changthang"
    ],
    "name:pnb_x_preferred":[
        "\u0686\u0627\u0646\u06af \u062a\u06be\u0627\u0646\u06af"
    ],
    "name:rus_x_preferred":[
        "\u0427\u0430\u043d\u0433\u0442\u0430\u043d"
    ],
    "name:zho_x_preferred":[
        "\u957f\u5858"
    ],
    "name:zho_x_variant":[
        "\u85cf\u5317\u9ad8\u539f"
    ],
    "wof:name":"Changtang",
    "wof:placetype":"locality"
},
  "geometry": {"coordinates":[118.79706000000002,32.71543],"type":"Point"}
}