{
  "type": "Feature",
  "properties": {
    "gn:admin1_code":"11.0",
    "gn:asciiname":"Tongzhong",
    "gn:country_code":"CN",
    "gn:dem":590,
    "gn:feature_class":"P",
    "gn:feature_code":"PPL",
    "gn:name":"Tongzhong",
    "gn:population":0,
    "gn:timezone":"Asia/Shanghai",
    "iso:country":"CN",
    "name:zho_x_preferred":[
        "\u94dc\u949f"
    ],
    "wof:name":"Tongzhong",
    "wof:placetype":"locality"
},
  "geometry": {"coordinates":[111.07623999999998,27.51045],"type":"Point"}
}