{
  "type": "Feature",
  "properties": {
    "gn:admin1_code":"8.0",
    "gn:asciiname":"Dashishan",
    "gn:country_code":"CN",
    "gn:dem":319,
    "gn:feature_class":"P",
    "gn:feature_code":"PPL",
    "gn:name":"Dashishan",
    "gn:population":0,
    "gn:timezone":"Asia/Shanghai",
    "iso:country":"CN",
    "name:zho_x_preferred":[
        "\u6253\u77f3\u5c71"
    ],
    "wof:name":"Dashishan",
    "wof:placetype":"locality"
},
  "geometry": {"coordinates":[125.59643,49.14466],"type":"Point"}
}