{
  "type": "Feature",
  "properties": {
    "gn:admin1_code":"12.0",
    "gn:asciiname":"Wuliu Xinchang",
    "gn:country_code":"CN",
    "gn:dem":33,
    "gn:feature_class":"P",
    "gn:feature_code":"PPL",
    "gn:name":"Wuliu Xinchang",
    "gn:population":0,
    "gn:timezone":"Asia/Shanghai",
    "iso:country":"CN",
    "name:zho_x_preferred":[
        "\u5434\u5218\u65b0\u573a"
    ],
    "wof:name":"Wuliu Xinchang",
    "wof:placetype":"locality"
},
  "geometry": {"coordinates":[113.11302000000001,30.71956],"type":"Point"}
}