{
  "type": "Feature",
  "properties": {
    "gn:admin1_code":"30.0",
    "gn:asciiname":"Jingzi",
    "gn:country_code":"CN",
    "gn:dem":243,
    "gn:feature_class":"P",
    "gn:feature_code":"PPL",
    "gn:name":"Jingzi",
    "gn:population":0,
    "gn:timezone":"Asia/Shanghai",
    "iso:country":"CN",
    "name:zho_x_preferred":[
        "\u5f84\u5b50"
    ],
    "wof:name":"Jingzi",
    "wof:placetype":"locality"
},
  "geometry": {"coordinates":[113.93677,23.96969],"type":"Point"}
}