{
  "type": "Feature",
  "properties": {
    "gn:admin1_code":"32.0",
    "gn:asciiname":"Sanceng Fangzi",
    "gn:country_code":"CN",
    "gn:dem":375,
    "gn:feature_class":"P",
    "gn:feature_code":"PPL",
    "gn:name":"Sanceng Fangzi",
    "gn:population":0,
    "gn:timezone":"Asia/Shanghai",
    "iso:country":"CN",
    "name:zho_x_preferred":[
        "\u4e09\u5c42\u623f\u5b50"
    ],
    "wof:name":"Sanceng Fangzi",
    "wof:placetype":"locality"
},
  "geometry": {"coordinates":[106.23519,31.1038],"type":"Point"}
}