{
  "type": "Feature",
  "properties": {
    "gn:admin1_code":"4.0",
    "gn:asciiname":"Jifanli",
    "gn:country_code":"CN",
    "gn:dem":8,
    "gn:feature_class":"P",
    "gn:feature_code":"PPL",
    "gn:name":"Jifanli",
    "gn:population":0,
    "gn:timezone":"Asia/Shanghai",
    "iso:country":"CN",
    "name:zho_x_preferred":[
        "Jifanli"
    ],
    "name:zho_x_variant":[
        "\u96c6\u51e1\u91cc"
    ],
    "wof:name":"Jifanli",
    "wof:placetype":"locality"
},
  "geometry": {"coordinates":[120.53391000000001,30.82114],"type":"Point"}
}