{
  "type": "Feature",
  "properties": {
    "gn:admin1_code":"8.0",
    "gn:asciiname":"Liangzhongchangcun",
    "gn:country_code":"CN",
    "gn:dem":156,
    "gn:feature_class":"P",
    "gn:feature_code":"PPLF",
    "gn:name":"Liangzhongchangcun",
    "gn:population":0,
    "gn:timezone":"Asia/Shanghai",
    "iso:country":"CN",
    "name:zho_x_preferred":[
        "\u826f\u79cd\u573a\u6751"
    ],
    "wof:name":"Liangzhongchangcun",
    "wof:placetype":"locality"
},
  "geometry": {"coordinates":[126.32028,46.93602],"type":"Point"}
}