{
  "type": "Feature",
  "properties": {
    "gn:admin1_code":"12.0",
    "gn:asciiname":"Dawotuo",
    "gn:country_code":"CN",
    "gn:dem":1264,
    "gn:feature_class":"P",
    "gn:feature_code":"PPL",
    "gn:name":"Dawotuo",
    "gn:population":0,
    "gn:timezone":"Asia/Shanghai",
    "iso:country":"CN",
    "name:zho_x_preferred":[
        "\u5927\u6da1\u5768"
    ],
    "wof:name":"Dawotuo",
    "wof:placetype":"locality"
},
  "geometry": {"coordinates":[109.02630000000001,29.4745],"type":"Point"}
}