{
  "type": "Feature",
  "properties": {
    "gn:admin1_code":"9",
    "gn:asciiname":"Tiefosi",
    "gn:country_code":"CN",
    "gn:dem":40,
    "gn:feature_class":"P",
    "gn:feature_code":"PPL",
    "gn:name":"Tiefosi",
    "gn:population":0,
    "gn:timezone":"Asia/Shanghai",
    "iso:country":"CN",
    "name:zho_x_preferred":[
        "\u94c1\u4f5b\u5bfa"
    ],
    "wof:name":"Tiefosi",
    "wof:placetype":"locality"
},
  "geometry": {"coordinates":[115.517,33.72],"type":"Point"}
}