{
  "type": "Feature",
  "properties": {
    "gn:admin1_code":"15.0",
    "gn:asciiname":"Huajianbu",
    "gn:country_code":"CN",
    "gn:dem":1959,
    "gn:feature_class":"P",
    "gn:feature_code":"PPL",
    "gn:name":"Huajianbu",
    "gn:population":0,
    "gn:timezone":"Asia/Shanghai",
    "iso:country":"CN",
    "name:zho_x_preferred":[
        "\u94e7\u5c16\u5821"
    ],
    "wof:name":"Huajianbu",
    "wof:placetype":"locality"
},
  "geometry": {"coordinates":[104.788,35.451],"type":"Point"}
}