{
  "type": "Feature",
  "properties": {
    "gn:admin1_code":"15.0",
    "gn:asciiname":"Yangjiadagou",
    "gn:country_code":"CN",
    "gn:dem":1806,
    "gn:feature_class":"P",
    "gn:feature_code":"PPL",
    "gn:name":"Yangjiadagou",
    "gn:population":0,
    "gn:timezone":"Asia/Shanghai",
    "iso:country":"CN",
    "name:und_x_variant":[
        "\u6768\u5bb6\u5927\u6c9f"
    ],
    "wof:name":"Yangjiadagou",
    "wof:placetype":"locality"
},
  "geometry": {"coordinates":[105.28425,35.07949],"type":"Point"}
}