{
  "type": "Feature",
  "properties": {
    "gn:admin1_code":"16.0",
    "gn:asciiname":"Guli",
    "gn:country_code":"CN",
    "gn:dem":309,
    "gn:feature_class":"P",
    "gn:feature_code":"PPL",
    "gn:name":"Guli",
    "gn:population":0,
    "gn:timezone":"Asia/Shanghai",
    "iso:country":"CN",
    "name:bel_x_preferred":[
        "\u0413\u0443\u043b\u0456"
    ],
    "name:ceb_x_preferred":[
        "Guli"
    ],
    "name:hye_x_preferred":[
        "\u0533\u0578\u0582\u056c\u056b"
    ],
    "name:mlg_x_preferred":[
        "Guli"
    ],
    "name:rus_x_preferred":[
        "\u0413\u0443\u043b\u0438"
    ],
    "name:swe_x_preferred":[
        "Guli"
    ],
    "name:ukr_x_preferred":[
        "\u0413\u0443\u043b\u0456"
    ],
    "name:zho_x_preferred":[
        "\u53e4\u5229"
    ],
    "wof:name":"Guli",
    "wof:placetype":"locality"
},
  "geometry": {"coordinates":[110.41,24.0012],"type":"Point"}
}