{
  "type": "Feature",
  "properties": {
    "gn:admin1_code":"24.0",
    "gn:asciiname":"Tulinbei",
    "gn:country_code":"CN",
    "gn:dem":1065,
    "gn:feature_class":"P",
    "gn:feature_code":"PPL",
    "gn:name":"Tulinbei",
    "gn:population":0,
    "gn:timezone":"Asia/Shanghai",
    "iso:country":"CN",
    "name:zho_x_preferred":[
        "\u571f\u6797\u80cc"
    ],
    "wof:name":"Tulinbei",
    "wof:placetype":"locality"
},
  "geometry": {"coordinates":[113.66119,36.82083],"type":"Point"}
}