{
  "type": "Feature",
  "properties": {
    "gn:admin1_code":"33.0",
    "gn:asciiname":"Shangzengtan",
    "gn:country_code":"CN",
    "gn:dem":300,
    "gn:feature_class":"P",
    "gn:feature_code":"PPL",
    "gn:name":"Shangzengtan",
    "gn:population":0,
    "gn:timezone":"Asia/Shanghai",
    "iso:country":"CN",
    "name:zho_x_preferred":[
        "\u4e0a\u7f7e\u8c2d"
    ],
    "wof:name":"Shangzengtan",
    "wof:placetype":"locality"
},
  "geometry": {"coordinates":[108.41692999999999,28.95485],"type":"Point"}
}