{
  "type": "Feature",
  "properties": {
    "gn:admin1_code":"19.0",
    "gn:asciiname":"Longfenggoucun",
    "gn:country_code":"CN",
    "gn:dem":88,
    "gn:feature_class":"P",
    "gn:feature_code":"PPL",
    "gn:name":"Longfenggoucun",
    "gn:population":0,
    "gn:timezone":"Asia/Shanghai",
    "iso:country":"CN",
    "name:zho_x_preferred":[
        "\u9f99\u51e4\u6c9f\u6751"
    ],
    "wof:name":"Longfenggoucun",
    "wof:placetype":"locality"
},
  "geometry": {"coordinates":[123.72615999999999,42.8784],"type":"Point"}
}