{
  "type": "Feature",
  "properties": {
    "gn:admin1_code":"29.0",
    "gn:asciiname":"Yakouzhe Zhongzhai",
    "gn:country_code":"CN",
    "gn:dem":1475,
    "gn:feature_class":"P",
    "gn:feature_code":"PPL",
    "gn:name":"Yakouzhe Zhongzhai",
    "gn:population":0,
    "gn:timezone":"Asia/Shanghai",
    "iso:country":"CN",
    "name:zho_x_preferred":[
        "\u4e2b\u53e3\u906e\u4e2d\u5be8"
    ],
    "wof:name":"Yakouzhe Zhongzhai",
    "wof:placetype":"locality"
},
  "geometry": {"coordinates":[102.73399999999999,22.83],"type":"Point"}
}