{
  "type": "Feature",
  "properties": {
    "gn:admin1_code":"6.0",
    "gn:asciiname":"Changxiwa",
    "gn:country_code":"CN",
    "gn:dem":2016,
    "gn:feature_class":"P",
    "gn:feature_code":"PPL",
    "gn:name":"Changxiwa",
    "gn:population":0,
    "gn:timezone":"Asia/Shanghai",
    "iso:country":"CN",
    "name:und_x_variant":[
        "\u957f\u897f\u54c7",
        "Xing\u2019er Zangzu Xiang",
        "Xing\u2019er Zangzu",
        "\u674f\u513f\u85cf\u65cf\u4e61",
        "\u674f\u513f\u85cf\u65cf"
    ],
    "wof:name":"Changxiwa",
    "wof:placetype":"locality"
},
  "geometry": {"coordinates":[102.70992,35.88355],"type":"Point"}
}