{
  "type": "Feature",
  "properties": {
    "gn:admin1_code":"4.0",
    "gn:asciiname":"Pijiaduncun",
    "gn:country_code":"CN",
    "gn:dem":5,
    "gn:feature_class":"P",
    "gn:feature_code":"PPL",
    "gn:name":"Pijiaduncun",
    "gn:population":0,
    "gn:timezone":"Asia/Shanghai",
    "iso:country":"CN",
    "name:zho_x_preferred":[
        "\u62ab\u7532\u58a9\u6751"
    ],
    "wof:name":"Pijiaduncun",
    "wof:placetype":"locality"
},
  "geometry": {"coordinates":[119.21191,34.3277],"type":"Point"}
}