{
  "type": "Feature",
  "properties": {
    "gn:admin1_code":"30",
    "gn:asciiname":"Haoyi",
    "gn:country_code":"CN",
    "gn:dem":39,
    "gn:feature_class":"P",
    "gn:feature_code":"PPLA4",
    "gn:name":"Haoyi",
    "gn:population":0,
    "gn:timezone":"Asia/Shanghai",
    "iso:country":"CN",
    "name:und_x_variant":[
        "\u597d\u4e49",
        "Haoyi Zhen",
        "\u597d\u4e49\u9547"
    ],
    "wof:name":"Haoyi",
    "wof:placetype":"locality"
},
  "geometry": {"coordinates":[114.75473999999998,23.37046],"type":"Point"}
}