{
  "type": "Feature",
  "properties": {
    "gn:admin1_code":"1.0",
    "gn:asciiname":"Hejiawancun",
    "gn:country_code":"CN",
    "gn:dem":412,
    "gn:feature_class":"P",
    "gn:feature_code":"PPL",
    "gn:name":"Hejiawancun",
    "gn:population":0,
    "gn:timezone":"Asia/Shanghai",
    "iso:country":"CN",
    "name:zho_x_preferred":[
        "\u4f55\u5bb6\u6e7e\u6751"
    ],
    "wof:name":"Hejiawancun",
    "wof:placetype":"locality"
},
  "geometry": {"coordinates":[115.77652,31.67136],"type":"Point"}
}