{
  "type": "Feature",
  "properties": {
    "gn:admin1_code":"11.0",
    "gn:asciiname":"Xin'anyuan",
    "gn:country_code":"CN",
    "gn:dem":32,
    "gn:feature_class":"P",
    "gn:feature_code":"PPL",
    "gn:name":"Xin\u2019anyuan",
    "gn:population":0,
    "gn:timezone":"Asia/Shanghai",
    "iso:country":"CN",
    "name:und_x_variant":[
        "Xin\u2019anyuan"
    ],
    "name:zho_x_preferred":[
        "\u65b0\u5b89\u57b8"
    ],
    "wof:name":"Xin'anyuan",
    "wof:placetype":"locality"
},
  "geometry": {"coordinates":[112.12159,29.40474],"type":"Point"}
}