{
  "type": "Feature",
  "properties": {
    "gn:admin1_code":"30.0",
    "gn:asciiname":"Lianshan",
    "gn:country_code":"CN",
    "gn:dem":299,
    "gn:feature_class":"P",
    "gn:feature_code":"PPL",
    "gn:name":"Lianshan",
    "gn:population":0,
    "gn:timezone":"Asia/Shanghai",
    "iso:country":"CN",
    "name:ceb_x_preferred":[
        "Lianshan"
    ],
    "name:deu_x_preferred":[
        "Lianshan"
    ],
    "name:fra_x_preferred":[
        "Lianshan"
    ],
    "name:nor_x_preferred":[
        "Lianshan"
    ],
    "name:swe_x_preferred":[
        "Lianshan"
    ],
    "name:zho_x_preferred":[
        "\u8054\u5c71"
    ],
    "wof:name":"Lianshan",
    "wof:placetype":"locality"
},
  "geometry": {"coordinates":[113.23472,24.42611],"type":"Point"}
}