{
  "type": "Feature",
  "properties": {
    "gn:admin1_code":"18",
    "gn:asciiname":"Gongjia'ao",
    "gn:country_code":"CN",
    "gn:dem":813,
    "gn:feature_class":"P",
    "gn:feature_code":"PPL",
    "gn:name":"Gongjia\u2019ao",
    "gn:population":0,
    "gn:timezone":"Asia/Shanghai",
    "iso:country":"CN",
    "name:und_x_variant":[
        "Gongjia\u2019ao"
    ],
    "name:zho_x_preferred":[
        "\u9f9a\u5bb6\u5773"
    ],
    "wof:name":"Gongjia'ao",
    "wof:placetype":"locality"
},
  "geometry": {"coordinates":[108.286,27.4455],"type":"Point"}
}