{
  "type": "Feature",
  "properties": {
    "gn:admin1_code":"19.0",
    "gn:asciiname":"Wuwei",
    "gn:country_code":"CN",
    "gn:dem":160,
    "gn:feature_class":"P",
    "gn:feature_code":"PPL",
    "gn:name":"Wuwei",
    "gn:population":0,
    "gn:timezone":"Asia/Shanghai",
    "iso:country":"CN",
    "name:und_x_variant":[
        "\u4e94\u5473"
    ],
    "wof:name":"Wuwei",
    "wof:placetype":"locality"
},
  "geometry": {"coordinates":[124.08362,41.8103],"type":"Point"}
}