{
  "type": "Feature",
  "properties": {
    "gn:admin1_code":"16.0",
    "gn:asciiname":"Nianlun",
    "gn:country_code":"CN",
    "gn:dem":933,
    "gn:feature_class":"P",
    "gn:feature_code":"PPL",
    "gn:name":"Nianlun",
    "gn:population":0,
    "gn:timezone":"Asia/Shanghai",
    "iso:country":"CN",
    "name:zho_x_preferred":[
        "\u5ff5\u4f26"
    ],
    "wof:name":"Nianlun",
    "wof:placetype":"locality"
},
  "geometry": {"coordinates":[106.15600000000001,23.1839],"type":"Point"}
}