{
  "type": "Feature",
  "properties": {
    "gn:admin1_code":"8.0",
    "gn:asciiname":"Tongyicun",
    "gn:country_code":"CN",
    "gn:dem":303,
    "gn:feature_class":"P",
    "gn:feature_code":"PPL",
    "gn:name":"Tongyicun",
    "gn:population":0,
    "gn:timezone":"Asia/Shanghai",
    "iso:country":"CN",
    "name:zho_x_preferred":[
        "\u540c\u610f\u6751"
    ],
    "wof:name":"Tongyicun",
    "wof:placetype":"locality"
},
  "geometry": {"coordinates":[126.25727000000001,47.93537],"type":"Point"}
}