{
  "type": "Feature",
  "properties": {
    "gn:admin1_code":"29.0",
    "gn:asciiname":"Kuchaba",
    "gn:country_code":"CN",
    "gn:dem":1149,
    "gn:feature_class":"P",
    "gn:feature_code":"PPL",
    "gn:name":"Kuchaba",
    "gn:population":0,
    "gn:timezone":"Asia/Shanghai",
    "iso:country":"CN",
    "name:zho_x_preferred":[
        "\u82e6\u8336\u575d"
    ],
    "wof:name":"Kuchaba",
    "wof:placetype":"locality"
},
  "geometry": {"coordinates":[105.227,27.7977],"type":"Point"}
}