{
  "type": "Feature",
  "properties": {
    "gn:admin1_code":"26.0",
    "gn:asciiname":"Dianzhencun",
    "gn:country_code":"CN",
    "gn:dem":501,
    "gn:feature_class":"P",
    "gn:feature_code":"PPL",
    "gn:name":"Dianzhencun",
    "gn:population":0,
    "gn:timezone":"Asia/Shanghai",
    "iso:country":"CN",
    "name:zho_x_preferred":[
        "\u6bbf\u9547\u6751"
    ],
    "wof:name":"Dianzhencun",
    "wof:placetype":"locality"
},
  "geometry": {"coordinates":[108.34578,34.06767],"type":"Point"}
}