{
  "type": "Feature",
  "properties": {
    "gn:admin1_code":"8.0",
    "gn:asciiname":"Congshantun",
    "gn:country_code":"CN",
    "gn:dem":148,
    "gn:feature_class":"P",
    "gn:feature_code":"PPL",
    "gn:name":"Congshantun",
    "gn:population":0,
    "gn:timezone":"Asia/Shanghai",
    "iso:country":"CN",
    "name:zho_x_preferred":[
        "\u4e1b\u5c71\u5c6f"
    ],
    "wof:name":"Congshantun",
    "wof:placetype":"locality"
},
  "geometry": {"coordinates":[127.96599000000001,45.90168],"type":"Point"}
}