{
  "type": "Feature",
  "properties": {
    "gn:admin1_code":"32.0",
    "gn:asciiname":"Xiayibuli",
    "gn:country_code":"CN",
    "gn:dem":3108,
    "gn:feature_class":"P",
    "gn:feature_code":"PPL",
    "gn:name":"Xiayibuli",
    "gn:population":0,
    "gn:timezone":"Asia/Shanghai",
    "iso:country":"CN",
    "name:zho_x_preferred":[
        "\u5477\u8863\u5e03\u91cc"
    ],
    "wof:name":"Xiayibuli",
    "wof:placetype":"locality"
},
  "geometry": {"coordinates":[100.407,30.5132],"type":"Point"}
}