{
  "type": "Feature",
  "properties": {
    "gn:admin1_code":"29.0",
    "gn:asciiname":"Tanglishu",
    "gn:country_code":"CN",
    "gn:dem":1548,
    "gn:feature_class":"P",
    "gn:feature_code":"PPL",
    "gn:name":"Tanglishu",
    "gn:population":0,
    "gn:timezone":"Asia/Shanghai",
    "iso:country":"CN",
    "name:zho_x_preferred":[
        "\u5858\u68a8\u6811"
    ],
    "wof:name":"Tanglishu",
    "wof:placetype":"locality"
},
  "geometry": {"coordinates":[103.542,23.8934],"type":"Point"}
}