{
  "type": "Feature",
  "properties": {
    "gn:admin1_code":"30",
    "gn:asciiname":"Gaomugen",
    "gn:country_code":"CN",
    "gn:dem":22,
    "gn:feature_class":"P",
    "gn:feature_code":"PPL",
    "gn:name":"Gaomugen",
    "gn:population":0,
    "gn:timezone":"Asia/Shanghai",
    "iso:country":"CN",
    "name:zho_x_preferred":[
        "\u9ad8\u6728\u6839"
    ],
    "wof:name":"Gaomugen",
    "wof:placetype":"locality"
},
  "geometry": {"coordinates":[111.59578,21.88898],"type":"Point"}
}