{
  "type": "Feature",
  "properties": {
    "gn:admin1_code":"3.0",
    "gn:asciiname":"Shizhuxia",
    "gn:country_code":"CN",
    "gn:dem":262,
    "gn:feature_class":"P",
    "gn:feature_code":"PPL",
    "gn:name":"Shizhuxia",
    "gn:population":0,
    "gn:timezone":"Asia/Shanghai",
    "iso:country":"CN",
    "name:und_x_variant":[
        "\u5b9e\u7af9\u4e0b"
    ],
    "wof:name":"Shizhuxia",
    "wof:placetype":"locality"
},
  "geometry": {"coordinates":[116.15966,26.34895],"type":"Point"}
}