{
  "type": "Feature",
  "properties": {
    "gn:admin1_code":"26.0",
    "gn:asciiname":"Shizibacun",
    "gn:country_code":"CN",
    "gn:dem":903,
    "gn:feature_class":"P",
    "gn:feature_code":"PPL",
    "gn:name":"Shizibacun",
    "gn:population":0,
    "gn:timezone":"Asia/Shanghai",
    "iso:country":"CN",
    "name:und_x_variant":[
        "\u72ee\u5b50\u575d\u6751"
    ],
    "wof:name":"Shizibacun",
    "wof:placetype":"locality"
},
  "geometry": {"coordinates":[106.94071,33.36946],"type":"Point"}
}