{
  "type": "Feature",
  "properties": {
    "gn:admin1_code":"26.0",
    "gn:asciiname":"Nanzhangjia Goucun",
    "gn:country_code":"CN",
    "gn:dem":977,
    "gn:feature_class":"P",
    "gn:feature_code":"PPL",
    "gn:name":"Nanzhangjia Goucun",
    "gn:population":0,
    "gn:timezone":"Asia/Shanghai",
    "iso:country":"CN",
    "name:zho_x_preferred":[
        "\u5357\u5f20\u5bb6\u6c9f\u6751"
    ],
    "wof:name":"Nanzhangjia Goucun",
    "wof:placetype":"locality"
},
  "geometry": {"coordinates":[110.131,37.5204],"type":"Point"}
}