{
  "type": "Feature",
  "properties": {
    "gn:admin1_code":"29.0",
    "gn:asciiname":"Bangmai",
    "gn:country_code":"CN",
    "gn:dem":1840,
    "gn:feature_class":"P",
    "gn:feature_code":"PPL",
    "gn:name":"Bangmai",
    "gn:population":0,
    "gn:timezone":"Asia/Shanghai",
    "iso:country":"CN",
    "name:zho_x_preferred":[
        "\u90a6\u8fc8"
    ],
    "wof:name":"Bangmai",
    "wof:placetype":"locality"
},
  "geometry": {"coordinates":[99.89879999999999,23.4435],"type":"Point"}
}