{
  "type": "Feature",
  "properties": {
    "gn:admin1_code":"19",
    "gn:asciiname":"Taling",
    "gn:country_code":"CN",
    "gn:dem":90,
    "gn:feature_class":"P",
    "gn:feature_code":"PPLA4",
    "gn:name":"Taling",
    "gn:population":0,
    "gn:timezone":"Asia/Shanghai",
    "iso:country":"CN",
    "name:und_x_variant":[
        "\u5854\u5cad",
        "Talingmanzu",
        "Talingmazu Zhen",
        "\u5854\u5cad\u6ee1\u65cf\u9547",
        "\u5854\u5cad\u6ee1\u65cf"
    ],
    "wof:name":"Taling",
    "wof:placetype":"locality"
},
  "geometry": {"coordinates":[123.10946,40.05175],"type":"Point"}
}