{
  "type": "Feature",
  "properties": {
    "gn:admin1_code":"19.0",
    "gn:asciiname":"Yangchangzigoucun",
    "gn:country_code":"CN",
    "gn:dem":276,
    "gn:feature_class":"P",
    "gn:feature_code":"PPL",
    "gn:name":"Yangchangzigoucun",
    "gn:population":0,
    "gn:timezone":"Asia/Shanghai",
    "iso:country":"CN",
    "name:zho_x_preferred":[
        "\u7f8a\u80a0\u5b50\u6c9f\u6751"
    ],
    "wof:name":"Yangchangzigoucun",
    "wof:placetype":"locality"
},
  "geometry": {"coordinates":[120.557,41.7928],"type":"Point"}
}