{
  "type": "Feature",
  "properties": {
    "gn:admin1_code":"11.0",
    "gn:asciiname":"Lishu'ao",
    "gn:country_code":"CN",
    "gn:dem":101,
    "gn:feature_class":"P",
    "gn:feature_code":"PPL",
    "gn:name":"Lishu\u2019ao",
    "gn:population":0,
    "gn:timezone":"Asia/Shanghai",
    "iso:country":"CN",
    "name:und_x_variant":[
        "Lishu\u2019ao"
    ],
    "name:zho_x_preferred":[
        "\u68a8\u6811\u5773"
    ],
    "wof:name":"Lishu'ao",
    "wof:placetype":"locality"
},
  "geometry": {"coordinates":[111.32747000000001,28.67229],"type":"Point"}
}