{
  "type": "Feature",
  "properties": {
    "gn:admin1_code":"20",
    "gn:asciiname":"Bailang",
    "gn:cc2":"CN",
    "gn:country_code":"CN",
    "gn:dem":1189,
    "gn:feature_class":"P",
    "gn:feature_code":"PPL",
    "gn:name":"Bailang",
    "gn:population":0,
    "gn:timezone":"Asia/Shanghai",
    "iso:country":"CN",
    "name:und_x_variant":[
        "Pailan",
        "Pai-lang",
        "Bailang"
    ],
    "wof:name":"Bailang",
    "wof:placetype":"locality"
},
  "geometry": {"coordinates":[120.11667,47.11667],"type":"Point"}
}