{
  "type": "Feature",
  "properties": {
    "gn:admin1_code":"32.0",
    "gn:asciiname":"Qiujilangwa",
    "gn:country_code":"CN",
    "gn:dem":3477,
    "gn:feature_class":"P",
    "gn:feature_code":"PPL",
    "gn:name":"Qiujilangwa",
    "gn:population":0,
    "gn:timezone":"Asia/Shanghai",
    "iso:country":"CN",
    "name:zho_x_preferred":[
        "\u6c42\u5409\u90ce\u54c7"
    ],
    "wof:name":"Qiujilangwa",
    "wof:placetype":"locality"
},
  "geometry": {"coordinates":[103.123,33.3571],"type":"Point"}
}