{
  "type": "Feature",
  "properties": {
    "gn:admin1_code":"25",
    "gn:asciiname":"Ziludizhong",
    "gn:country_code":"CN",
    "gn:dem":44,
    "gn:feature_class":"P",
    "gn:feature_code":"PPL",
    "gn:name":"Ziludizhong",
    "gn:population":0,
    "gn:timezone":"Asia/Shanghai",
    "iso:country":"CN",
    "name:zho_x_preferred":[
        "\u5b50\u8def\u5824\u4e2d"
    ],
    "wof:name":"Ziludizhong",
    "wof:placetype":"locality"
},
  "geometry": {"coordinates":[115.67,35.9446],"type":"Point"}
}