{
  "type": "Feature",
  "properties": {
    "gn:admin1_code":"33",
    "gn:asciiname":"Fenshui",
    "gn:country_code":"CN",
    "gn:dem":484,
    "gn:feature_class":"P",
    "gn:feature_code":"PPLA4",
    "gn:name":"Fenshui",
    "gn:population":0,
    "gn:timezone":"Asia/Shanghai",
    "iso:country":"CN",
    "name:ceb_x_preferred":[
        "Fenshui"
    ],
    "name:swe_x_preferred":[
        "Fenshui"
    ],
    "name:und_x_variant":[
        "Fen-shui-ling",
        "Fenshuichang",
        "Fenshui Zhen"
    ],
    "name:zho_x_preferred":[
        "\u5206\u6c34"
    ],
    "name:zho_x_variant":[
        "\u5206\u6c34\u9547",
        "\u5206\u6c34\u4e61"
    ],
    "wof:name":"Fenshui",
    "wof:placetype":"locality"
},
  "geometry": {"coordinates":[108.08333,30.7197],"type":"Point"}
}