{
  "type": "Feature",
  "properties": {
    "gn:admin1_code":"30.0",
    "gn:asciiname":"Tangdongcun",
    "gn:country_code":"CN",
    "gn:dem":8,
    "gn:feature_class":"P",
    "gn:feature_code":"PPL",
    "gn:name":"Tangdongcun",
    "gn:population":0,
    "gn:timezone":"Asia/Urumqi",
    "iso:country":"CN",
    "name:zho_x_preferred":[
        "\u5858\u4e1c\u6751"
    ],
    "wof:name":"Tangdongcun",
    "wof:placetype":"locality"
},
  "geometry": {"coordinates":[109.84608,20.54337],"type":"Point"}
}