{
  "type": "Feature",
  "properties": {
    "gn:admin1_code":"10",
    "gn:asciiname":"Kaidifang",
    "gn:country_code":"CN",
    "gn:dem":1514,
    "gn:feature_class":"P",
    "gn:feature_code":"PPL",
    "gn:name":"Kaidifang",
    "gn:population":0,
    "gn:timezone":"Asia/Shanghai",
    "iso:country":"CN",
    "name:zho_x_preferred":[
        "\u5f00\u5730\u623f"
    ],
    "wof:name":"Kaidifang",
    "wof:placetype":"locality"
},
  "geometry": {"coordinates":[114.68131,41.99923],"type":"Point"}
}