{
  "type": "Feature",
  "properties": {
    "gn:admin1_code":"12.0",
    "gn:asciiname":"Yindishan",
    "gn:country_code":"CN",
    "gn:dem":1332,
    "gn:feature_class":"P",
    "gn:feature_code":"PPL",
    "gn:name":"Yindishan",
    "gn:population":0,
    "gn:timezone":"Asia/Shanghai",
    "iso:country":"CN",
    "name:zho_x_preferred":[
        "\u9634\u5730\u5c71"
    ],
    "wof:name":"Yindishan",
    "wof:placetype":"locality"
},
  "geometry": {"coordinates":[109.111,30.38782],"type":"Point"}
}