{
  "type": "Feature",
  "properties": {
    "gn:admin1_code":"29.0",
    "gn:asciiname":"Jiangjiayan",
    "gn:country_code":"CN",
    "gn:dem":2545,
    "gn:feature_class":"P",
    "gn:feature_code":"PPL",
    "gn:name":"Jiangjiayan",
    "gn:population":0,
    "gn:timezone":"Asia/Shanghai",
    "iso:country":"CN",
    "name:zho_x_preferred":[
        "\u59dc\u5bb6\u5ca9"
    ],
    "wof:name":"Jiangjiayan",
    "wof:placetype":"locality"
},
  "geometry": {"coordinates":[103.295,26.3092],"type":"Point"}
}