{
  "type": "Feature",
  "properties": {
    "gn:admin1_code":"16.0",
    "gn:asciiname":"Dongmin",
    "gn:country_code":"CN",
    "gn:dem":200,
    "gn:feature_class":"P",
    "gn:feature_code":"PPL",
    "gn:name":"Dongmin",
    "gn:population":0,
    "gn:timezone":"Asia/Shanghai",
    "iso:country":"CN",
    "name:zho_x_preferred":[
        "\u51ac\u6c11"
    ],
    "wof:name":"Dongmin",
    "wof:placetype":"locality"
},
  "geometry": {"coordinates":[107.08,22.6281],"type":"Point"}
}