{
  "type": "Feature",
  "properties": {
    "gn:admin1_code":"3",
    "gn:asciiname":"Fengshukeng",
    "gn:country_code":"CN",
    "gn:dem":238,
    "gn:feature_class":"P",
    "gn:feature_code":"PPL",
    "gn:name":"Fengshukeng",
    "gn:population":0,
    "gn:timezone":"Asia/Shanghai",
    "iso:country":"CN",
    "name:zho_x_preferred":[
        "\u67ab\u6811\u5751"
    ],
    "wof:name":"Fengshukeng",
    "wof:placetype":"locality"
},
  "geometry": {"coordinates":[114.883,25.57800000000001],"type":"Point"}
}