{
  "type": "Feature",
  "properties": {
    "gn:admin1_code":"29",
    "gn:asciiname":"Mashang",
    "gn:country_code":"CN",
    "gn:dem":1481,
    "gn:feature_class":"P",
    "gn:feature_code":"PPL",
    "gn:name":"Mashang",
    "gn:population":0,
    "gn:timezone":"Asia/Shanghai",
    "iso:country":"CN",
    "name:zho_x_preferred":[
        "\u9a6c\u4e0a"
    ],
    "wof:name":"Mashang",
    "wof:placetype":"locality"
},
  "geometry": {"coordinates":[105.242,23.3553],"type":"Point"}
}