{
  "type": "Feature",
  "properties": {
    "gn:admin1_code":"16",
    "gn:asciiname":"Jiacao",
    "gn:country_code":"CN",
    "gn:dem":335,
    "gn:feature_class":"P",
    "gn:feature_code":"PPL",
    "gn:name":"Jiacao",
    "gn:population":0,
    "gn:timezone":"Asia/Shanghai",
    "iso:country":"CN",
    "name:zho_x_preferred":[
        "\u5047\u69fd"
    ],
    "wof:name":"Jiacao",
    "wof:placetype":"locality"
},
  "geometry": {"coordinates":[110.51000000000001,24.3295],"type":"Point"}
}