{
  "type": "Feature",
  "properties": {
    "gn:admin1_code":"33.0",
    "gn:asciiname":"Minhe",
    "gn:country_code":"CN",
    "gn:dem":289,
    "gn:feature_class":"P",
    "gn:feature_code":"PPL",
    "gn:name":"Minhe",
    "gn:population":0,
    "gn:timezone":"Asia/Shanghai",
    "iso:country":"CN",
    "name:ceb_x_preferred":[
        "Minhe"
    ],
    "name:deu_x_preferred":[
        "Minhe"
    ],
    "name:zho_x_preferred":[
        "\u6c11\u548c"
    ],
    "wof:name":"Minhe",
    "wof:placetype":"locality"
},
  "geometry": {"coordinates":[106.05905,29.57223],"type":"Point"}
}