{
  "type": "Feature",
  "properties": {
    "gn:admin1_code":"18",
    "gn:asciiname":"Shibaoqiao",
    "gn:country_code":"CN",
    "gn:dem":1587,
    "gn:feature_class":"P",
    "gn:feature_code":"PPL",
    "gn:name":"Shibaoqiao",
    "gn:population":0,
    "gn:timezone":"Asia/Shanghai",
    "iso:country":"CN",
    "name:zho_x_preferred":[
        "\u77f3\u4fdd\u6865"
    ],
    "wof:name":"Shibaoqiao",
    "wof:placetype":"locality"
},
  "geometry": {"coordinates":[103.712,27.0971],"type":"Point"}
}