{
  "type": "Feature",
  "properties": {
    "gn:admin1_code":"31",
    "gn:asciiname":"Laichao",
    "gn:country_code":"CN",
    "gn:dem":129,
    "gn:feature_class":"P",
    "gn:feature_code":"PPL",
    "gn:name":"Laichao",
    "gn:population":0,
    "gn:timezone":"Asia/Shanghai",
    "iso:country":"CN",
    "name:und_x_variant":[
        "\u6765\u671d"
    ],
    "wof:name":"Laichao",
    "wof:placetype":"locality"
},
  "geometry": {"coordinates":[109.98151,19.40484],"type":"Point"}
}