{
  "type": "Feature",
  "properties": {
    "gn:admin1_code":"12.0",
    "gn:asciiname":"Shaoji'ao",
    "gn:country_code":"CN",
    "gn:dem":1157,
    "gn:feature_class":"P",
    "gn:feature_code":"PPL",
    "gn:name":"Shaoji\u2019ao",
    "gn:population":0,
    "gn:timezone":"Asia/Shanghai",
    "iso:country":"CN",
    "name:und_x_variant":[
        "Shaoji\u2019ao"
    ],
    "name:zho_x_preferred":[
        "\u7b72\u7b95\u51f9"
    ],
    "wof:name":"Shaoji'ao",
    "wof:placetype":"locality"
},
  "geometry": {"coordinates":[111.104,32.17653],"type":"Point"}
}