{
  "type": "Feature",
  "properties": {
    "gn:admin1_code":"02",
    "gn:asciiname":"Jushuicun",
    "gn:country_code":"CN",
    "gn:dem":326,
    "gn:feature_class":"P",
    "gn:feature_code":"PPL",
    "gn:name":"Jushuicun",
    "gn:population":0,
    "gn:timezone":"Asia/Shanghai",
    "iso:country":"CN",
    "name:und_x_variant":[
        "Jushui"
    ],
    "name:zho_x_preferred":[
        "\u83ca\u6c34\u6751"
    ],
    "wof:name":"Jushuicun",
    "wof:placetype":"locality"
},
  "geometry": {"coordinates":[118.95947,27.60651],"type":"Point"}
}