{
  "type": "Feature",
  "properties": {
    "gn:admin1_code":"9",
    "gn:asciiname":"Zhaoguanzhuang",
    "gn:country_code":"CN",
    "gn:dem":61,
    "gn:feature_class":"P",
    "gn:feature_code":"PPL",
    "gn:name":"Zhaoguanzhuang",
    "gn:population":0,
    "gn:timezone":"Asia/Shanghai",
    "iso:country":"CN",
    "name:zho_x_preferred":[
        "\u8d75\u5173\u5e84"
    ],
    "wof:name":"Zhaoguanzhuang",
    "wof:placetype":"locality"
},
  "geometry": {"coordinates":[114.63722,35.38861],"type":"Point"}
}