{
  "type": "Feature",
  "properties": {
    "gn:admin1_code":"8.0",
    "gn:asciiname":"Kaifatun",
    "gn:country_code":"CN",
    "gn:dem":216,
    "gn:feature_class":"P",
    "gn:feature_code":"PPL",
    "gn:name":"Kaifatun",
    "gn:population":0,
    "gn:timezone":"Asia/Shanghai",
    "iso:country":"CN",
    "name:zho_x_preferred":[
        "\u5f00\u53d1\u5c6f"
    ],
    "wof:name":"Kaifatun",
    "wof:placetype":"locality"
},
  "geometry": {"coordinates":[127.47551,44.8502],"type":"Point"}
}