{
  "type": "Feature",
  "properties": {
    "gn:admin1_code":"7",
    "gn:asciiname":"Jiangyuan",
    "gn:country_code":"CN",
    "gn:dem":710,
    "gn:feature_class":"P",
    "gn:feature_code":"PPL",
    "gn:name":"Jiangyuan",
    "gn:population":0,
    "gn:timezone":"Asia/Shanghai",
    "iso:country":"CN",
    "name:ceb_x_preferred":[
        "Jiangyuan"
    ],
    "name:fra_x_preferred":[
        "Jiangyuan"
    ],
    "name:kor_x_preferred":[
        "\uc7a5\uc704\uc548"
    ],
    "name:und_x_variant":[
        "\u6c5f\u6e90"
    ],
    "wof:name":"Jiangyuan",
    "wof:placetype":"locality"
},
  "geometry": {"coordinates":[119.36444,27.17],"type":"Point"}
}