{
  "type": "Feature",
  "properties": {
    "gn:admin1_code":"15.0",
    "gn:asciiname":"Guantan",
    "gn:country_code":"CN",
    "gn:dem":2431,
    "gn:feature_class":"P",
    "gn:feature_code":"PPL",
    "gn:name":"Guantan",
    "gn:population":0,
    "gn:timezone":"Asia/Shanghai",
    "iso:country":"CN",
    "name:und_x_variant":[
        "\u5173\u6ee9"
    ],
    "wof:name":"Guantan",
    "wof:placetype":"locality"
},
  "geometry": {"coordinates":[102.86223,35.52849000000001],"type":"Point"}
}