{
  "type": "Feature",
  "properties": {
    "gn:admin1_code":"30.0",
    "gn:asciiname":"Baishi'ao",
    "gn:country_code":"CN",
    "gn:dem":132,
    "gn:feature_class":"P",
    "gn:feature_code":"PPL",
    "gn:name":"Baishi\u2019ao",
    "gn:population":0,
    "gn:timezone":"Asia/Shanghai",
    "iso:country":"CN",
    "name:zho_x_preferred":[
        "\u767d\u77f3\u5773"
    ],
    "name:zho_x_variant":[
        "Baishi\u2019ao"
    ],
    "wof:name":"Baishi'ao",
    "wof:placetype":"locality"
},
  "geometry": {"coordinates":[111.7285,23.0808],"type":"Point"}
}