{
  "type": "Feature",
  "properties": {
    "gn:admin1_code":"1.0",
    "gn:asciiname":"Jiagoucun",
    "gn:country_code":"CN",
    "gn:dem":38,
    "gn:feature_class":"P",
    "gn:feature_code":"PPL",
    "gn:name":"Jiagoucun",
    "gn:population":0,
    "gn:timezone":"Asia/Shanghai",
    "iso:country":"CN",
    "name:zho_x_preferred":[
        "\u5939\u6c9f\u6751"
    ],
    "wof:name":"Jiagoucun",
    "wof:placetype":"locality"
},
  "geometry": {"coordinates":[117.05278,33.89389],"type":"Point"}
}