{
  "type": "Feature",
  "properties": {
    "gn:admin1_code":"08",
    "gn:asciiname":"Nongjiang",
    "gn:country_code":"CN",
    "gn:dem":59,
    "gn:feature_class":"P",
    "gn:feature_code":"PPL",
    "gn:name":"Nongjiang",
    "gn:population":0,
    "gn:timezone":"Asia/Shanghai",
    "iso:country":"CN",
    "name:und_x_variant":[
        "Nongjiangxiang",
        "Nongjiang"
    ],
    "wof:name":"Nongjiang",
    "wof:placetype":"locality"
},
  "geometry": {"coordinates":[134.28528,48.28778],"type":"Point"}
}