{
  "type": "Feature",
  "properties": {
    "gn:admin1_code":"32.0",
    "gn:asciiname":"Fangjiagou",
    "gn:country_code":"CN",
    "gn:dem":392,
    "gn:feature_class":"P",
    "gn:feature_code":"PPL",
    "gn:name":"Fangjiagou",
    "gn:population":0,
    "gn:timezone":"Asia/Shanghai",
    "iso:country":"CN",
    "name:zho_x_preferred":[
        "\u65b9\u52a0\u6c9f"
    ],
    "wof:name":"Fangjiagou",
    "wof:placetype":"locality"
},
  "geometry": {"coordinates":[104.334,29.9375],"type":"Point"}
}