{
  "type": "Feature",
  "properties": {
    "gn:admin1_code":"14.0",
    "gn:asciiname":"Rexi",
    "gn:country_code":"CN",
    "gn:dem":3730,
    "gn:feature_class":"P",
    "gn:feature_code":"PPL",
    "gn:name":"Rexi",
    "gn:population":0,
    "gn:timezone":"Asia/Urumqi",
    "iso:country":"CN",
    "name:bod_x_preferred":[
        "Ra\u2019gyi"
    ],
    "name:zho_x_preferred":[
        "Rexi"
    ],
    "name:zho_x_variant":[
        "\u70ed\u897f"
    ],
    "wof:name":"Rexi",
    "wof:placetype":"locality"
},
  "geometry": {"coordinates":[96.76132,31.1291],"type":"Point"}
}