{
  "type": "Feature",
  "properties": {
    "gn:admin1_code":"11.0",
    "gn:asciiname":"Ailuojie",
    "gn:country_code":"CN",
    "gn:dem":841,
    "gn:feature_class":"P",
    "gn:feature_code":"PPL",
    "gn:name":"Ailuojie",
    "gn:population":0,
    "gn:timezone":"Asia/Shanghai",
    "iso:country":"CN",
    "name:zho_x_preferred":[
        "\u77ee\u843d\u754c"
    ],
    "wof:name":"Ailuojie",
    "wof:placetype":"locality"
},
  "geometry": {"coordinates":[110.01111000000002,28.62301],"type":"Point"}
}