{
  "type": "Feature",
  "properties": {
    "gn:admin1_code":"24.0",
    "gn:asciiname":"Dongxiangzhai",
    "gn:country_code":"CN",
    "gn:dem":1047,
    "gn:feature_class":"P",
    "gn:feature_code":"PPL",
    "gn:name":"Dongxiangzhai",
    "gn:population":0,
    "gn:timezone":"Asia/Shanghai",
    "iso:country":"CN",
    "name:und_x_variant":[
        "\u4e1c\u4e61\u5be8"
    ],
    "name:zho_x_preferred":[
        "\u4e1c\u4e61\u5be8"
    ],
    "wof:name":"Dongxiangzhai",
    "wof:placetype":"locality"
},
  "geometry": {"coordinates":[113.43716999999999,39.57471],"type":"Point"}
}