{
  "type": "Feature",
  "properties": {
    "gn:admin1_code":"25",
    "gn:asciiname":"Shuirundao",
    "gn:country_code":"CN",
    "gn:dem":187,
    "gn:feature_class":"P",
    "gn:feature_code":"PPL",
    "gn:name":"Shuirundao",
    "gn:population":0,
    "gn:timezone":"Asia/Shanghai",
    "iso:country":"CN",
    "name:zho_x_preferred":[
        "\u6c34\u6da6\u9053"
    ],
    "wof:name":"Shuirundao",
    "wof:placetype":"locality"
},
  "geometry": {"coordinates":[119.04300000000001,36.2018],"type":"Point"}
}