{
  "type": "Feature",
  "properties": {
    "gn:admin1_code":"32.0",
    "gn:asciiname":"Linglongshan",
    "gn:country_code":"CN",
    "gn:dem":1624,
    "gn:feature_class":"P",
    "gn:feature_code":"PPL",
    "gn:name":"Linglongshan",
    "gn:population":0,
    "gn:timezone":"Asia/Shanghai",
    "iso:country":"CN",
    "name:zho_x_preferred":[
        "\u7075\u9f99\u5c71"
    ],
    "wof:name":"Linglongshan",
    "wof:placetype":"locality"
},
  "geometry": {"coordinates":[104.136,31.8129],"type":"Point"}
}