{
  "type": "Feature",
  "properties": {
    "gn:admin1_code":"24.0",
    "gn:asciiname":"Sutu",
    "gn:country_code":"CN",
    "gn:dem":848,
    "gn:feature_class":"P",
    "gn:feature_code":"PPL",
    "gn:name":"Sutu",
    "gn:population":0,
    "gn:timezone":"Asia/Shanghai",
    "iso:country":"CN",
    "name:ceb_x_preferred":[
        "Sutu"
    ],
    "name:zho_x_preferred":[
        "\u82cf\u571f"
    ],
    "wof:name":"Sutu",
    "wof:placetype":"locality"
},
  "geometry": {"coordinates":[110.47626,36.63807],"type":"Point"}
}