{
  "type": "Feature",
  "properties": {
    "gn:admin1_code":"8.0",
    "gn:asciiname":"Ziweicun",
    "gn:country_code":"CN",
    "gn:dem":155,
    "gn:feature_class":"P",
    "gn:feature_code":"PPL",
    "gn:name":"Ziweicun",
    "gn:population":0,
    "gn:timezone":"Asia/Shanghai",
    "iso:country":"CN",
    "name:zho_x_preferred":[
        "\u81ea\u536b\u6751"
    ],
    "wof:name":"Ziweicun",
    "wof:placetype":"locality"
},
  "geometry": {"coordinates":[125.46274,46.45708],"type":"Point"}
}