{
  "type": "Feature",
  "properties": {
    "gn:country":"CN",
    "gn:fcode":"PPL",
    "gn:population":980,
    "iso:country":"CN",
    "name:und_x_variant":[
        "Lien-p\u2019u"
    ],
    "name:zho_x_preferred":[
        "\u4e0a\u83b2"
    ],
    "name:zho_x_variant":[
        "\u4e0a\u83b2\u4e61"
    ],
    "qs:name":"Shanglian",
    "qs:photos_9r":0,
    "qs:photos_sr":0,
    "qs:pop_sr":"2",
    "wof:name":"Shanglian",
    "wof:placetype":"locality",
    "wof:population":980
},
  "geometry": {"coordinates":[118.64556,26.03556],"type":"Point"}
}