{
  "type": "Feature",
  "properties": {
    "gn:admin1_code":"18.0",
    "gn:asciiname":"Gongtiao",
    "gn:country_code":"CN",
    "gn:dem":655,
    "gn:feature_class":"P",
    "gn:feature_code":"PPL",
    "gn:name":"Gongtiao",
    "gn:population":0,
    "gn:timezone":"Asia/Shanghai",
    "iso:country":"CN",
    "name:zho_x_preferred":[
        "\u516c\u6311"
    ],
    "wof:name":"Gongtiao",
    "wof:placetype":"locality"
},
  "geometry": {"coordinates":[108.29000000000001,25.8442],"type":"Point"}
}