{
  "type": "Feature",
  "properties": {
    "gn:admin1_code":"32.0",
    "gn:asciiname":"Laiwulada",
    "gn:country_code":"CN",
    "gn:dem":2703,
    "gn:feature_class":"P",
    "gn:feature_code":"PPL",
    "gn:name":"Laiwulada",
    "gn:population":0,
    "gn:timezone":"Asia/Shanghai",
    "iso:country":"CN",
    "name:zho_x_preferred":[
        "\u6765\u5c4b\u62c9\u6253"
    ],
    "wof:name":"Laiwulada",
    "wof:placetype":"locality"
},
  "geometry": {"coordinates":[102.503,28.0073],"type":"Point"}
}