{
  "type": "Feature",
  "properties": {
    "gn:admin1_code":"04",
    "gn:asciiname":"Guabu",
    "gn:country_code":"CN",
    "gn:dem":10,
    "gn:feature_class":"P",
    "gn:feature_code":"PPLA4",
    "gn:name":"Guabu",
    "gn:population":0,
    "gn:timezone":"Asia/Shanghai",
    "iso:country":"CN",
    "name:und_x_variant":[
        "Kua-fou",
        "Kua-fou-chen",
        "Kua-pu",
        "Guabu",
        "\u74dc\u57e0",
        "Guabu Zhen"
    ],
    "wof:name":"Guabu",
    "wof:placetype":"locality"
},
  "geometry": {"coordinates":[118.88408,32.24898],"type":"Point"}
}