{
  "type": "Feature",
  "properties": {
    "gn:admin1_code":"16.0",
    "gn:asciiname":"Dongbu",
    "gn:country_code":"CN",
    "gn:dem":146,
    "gn:feature_class":"P",
    "gn:feature_code":"PPL",
    "gn:name":"Dongbu",
    "gn:population":0,
    "gn:timezone":"Asia/Shanghai",
    "iso:country":"CN",
    "name:zho_x_preferred":[
        "\u5cbd\u5e03"
    ],
    "wof:name":"Dongbu",
    "wof:placetype":"locality"
},
  "geometry": {"coordinates":[107.67100000000001,22.0782],"type":"Point"}
}