{
  "type": "Feature",
  "properties": {
    "gn:admin1_code":"11",
    "gn:asciiname":"Tangjia Wuli",
    "gn:country_code":"CN",
    "gn:dem":516,
    "gn:feature_class":"P",
    "gn:feature_code":"PPL",
    "gn:name":"Tangjia Wuli",
    "gn:population":0,
    "gn:timezone":"Asia/Shanghai",
    "iso:country":"CN",
    "name:zho_x_preferred":[
        "\u5510\u5bb6\u5c4b\u91cc"
    ],
    "wof:name":"Tangjia Wuli",
    "wof:placetype":"locality"
},
  "geometry": {"coordinates":[111.50214,25.97635],"type":"Point"}
}