{
  "type": "Feature",
  "properties": {
    "gn:admin1_code":"20.0",
    "gn:asciiname":"Yingongwan",
    "gn:country_code":"CN",
    "gn:dem":1584,
    "gn:feature_class":"P",
    "gn:feature_code":"PPL",
    "gn:name":"Yingongwan",
    "gn:population":0,
    "gn:timezone":"Asia/Shanghai",
    "iso:country":"CN",
    "name:und_x_variant":[
        "\u94f6\u8d21\u6e7e"
    ],
    "wof:name":"Yingongwan",
    "wof:placetype":"locality"
},
  "geometry": {"coordinates":[111.55096,41.29388],"type":"Point"}
}