{
  "type": "Feature",
  "properties": {
    "gn:admin1_code":"4.0",
    "gn:asciiname":"Rubuzhuang",
    "gn:country_code":"CN",
    "gn:dem":6,
    "gn:feature_class":"P",
    "gn:feature_code":"PPL",
    "gn:name":"Rubuzhuang",
    "gn:population":0,
    "gn:timezone":"Asia/Shanghai",
    "iso:country":"CN",
    "name:und_x_variant":[
        "\u8339\u5821\u5e84"
    ],
    "name:zho_x_preferred":[
        "\u8339\u5821\u5e84"
    ],
    "wof:name":"Rubuzhuang",
    "wof:placetype":"locality"
},
  "geometry": {"coordinates":[120.19999,32.29979],"type":"Point"}
}