{
  "type": "Feature",
  "properties": {
    "gn:admin1_code":"18",
    "gn:asciiname":"Pinghua",
    "gn:country_code":"CN",
    "gn:dem":676,
    "gn:feature_class":"P",
    "gn:feature_code":"PPL",
    "gn:name":"Pinghua",
    "gn:population":0,
    "gn:timezone":"Asia/Shanghai",
    "iso:country":"CN",
    "name:ast_x_preferred":[
        "Chinu ping"
    ],
    "name:cat_x_preferred":[
        "Ping"
    ],
    "name:cdo_x_preferred":[
        "\u5ee3\u897f\u5e73\u8a71"
    ],
    "name:fra_x_preferred":[
        "Pinghua"
    ],
    "name:jpn_x_preferred":[
        "\u5e83\u897f\u5e73\u8a71"
    ],
    "name:nor_x_preferred":[
        "Pinghua"
    ],
    "name:spa_x_preferred":[
        "Chino ping"
    ],
    "name:swe_x_preferred":[
        "Pinghua"
    ],
    "name:tha_x_preferred":[
        "\u0e20\u0e32\u0e29\u0e32\u0e08\u0e35\u0e19\u0e1c\u0e34\u0e07"
    ],
    "name:tur_x_preferred":[
        "Pinghua"
    ],
    "name:vie_x_preferred":[
        "Ti\u1ebfng B\u00ecnh"
    ],
    "name:zho_x_preferred":[
        "\u5e73\u534e"
    ],
    "name:zho_x_variant":[
        "\u5ee3\u897f\u5e73\u8a71"
    ],
    "wof:name":"Pinghua",
    "wof:placetype":"locality"
},
  "geometry": {"coordinates":[105.997,24.8602],"type":"Point"}
}