{
  "type": "Feature",
  "properties": {
    "gn:admin1_code":"2.0",
    "gn:asciiname":"Dashiyan",
    "gn:country_code":"CN",
    "gn:dem":43,
    "gn:feature_class":"P",
    "gn:feature_code":"PPL",
    "gn:name":"Dashiyan",
    "gn:population":0,
    "gn:timezone":"Asia/Shanghai",
    "iso:country":"CN",
    "name:zho_x_preferred":[
        "\u5927\u5e02\u5830"
    ],
    "wof:name":"Dashiyan",
    "wof:placetype":"locality"
},
  "geometry": {"coordinates":[121.63035000000001,28.29189],"type":"Point"}
}