{
  "type": "Feature",
  "properties": {
    "gn:admin1_code":"3.0",
    "gn:asciiname":"Longmenfan",
    "gn:country_code":"CN",
    "gn:dem":109,
    "gn:feature_class":"P",
    "gn:feature_code":"PPLA4",
    "gn:name":"Longmenfan",
    "gn:population":0,
    "gn:timezone":"Asia/Shanghai",
    "iso:country":"CN",
    "name:und_x_variant":[
        "\u9f99\u95e8\u7548\u4e61",
        "Longmenfan Xiang",
        "Longmenfan"
    ],
    "name:zho_x_preferred":[
        "\u9f99\u95e8\u7548"
    ],
    "wof:name":"Longmenfan",
    "wof:placetype":"locality"
},
  "geometry": {"coordinates":[117.65112999999999,28.50046],"type":"Point"}
}