{
  "type": "Feature",
  "properties": {
    "gn:admin1_code":"29.0",
    "gn:asciiname":"Anishigua",
    "gn:country_code":"CN",
    "gn:dem":2583,
    "gn:feature_class":"P",
    "gn:feature_code":"PPL",
    "gn:name":"Anishigua",
    "gn:population":0,
    "gn:timezone":"Asia/Shanghai",
    "iso:country":"CN",
    "name:zho_x_preferred":[
        "\u963f\u5c3c\u65bd\u74dc"
    ],
    "wof:name":"Anishigua",
    "wof:placetype":"locality"
},
  "geometry": {"coordinates":[99.4075,26.7245],"type":"Point"}
}