{
  "type": "Feature",
  "properties": {
    "gn:admin1_code":"21.0",
    "gn:asciiname":"Luozhuangke",
    "gn:country_code":"CN",
    "gn:dem":1704,
    "gn:feature_class":"P",
    "gn:feature_code":"PPL",
    "gn:name":"Luozhuangke",
    "gn:population":0,
    "gn:timezone":"Asia/Shanghai",
    "iso:country":"CN",
    "name:zho_x_preferred":[
        "\u7f57\u5e84\u79d1"
    ],
    "wof:name":"Luozhuangke",
    "wof:placetype":"locality"
},
  "geometry": {"coordinates":[107.127,37.3909],"type":"Point"}
}