{
  "type": "Feature",
  "properties": {
    "gn:admin1_code":"20",
    "gn:asciiname":"Ar Hob",
    "gn:cc2":"CN",
    "gn:country_code":"CN",
    "gn:dem":1281,
    "gn:feature_class":"P",
    "gn:feature_code":"PPL",
    "gn:name":"Ar Hob",
    "gn:population":0,
    "gn:timezone":"Asia/Shanghai",
    "iso:country":"CN",
    "name:und_x_variant":[
        "Ar Hob Xiang",
        "Ar Hob"
    ],
    "wof:name":"Ar Hob",
    "wof:placetype":"locality"
},
  "geometry": {"coordinates":[115.51027999999999,42.29361],"type":"Point"}
}