{
  "type": "Feature",
  "properties": {
    "gn:admin1_code":"5.0",
    "gn:asciiname":"Guojiatuncun",
    "gn:country_code":"CN",
    "gn:dem":213,
    "gn:feature_class":"P",
    "gn:feature_code":"PPL",
    "gn:name":"Guojiatuncun",
    "gn:population":0,
    "gn:timezone":"Asia/Shanghai",
    "iso:country":"CN",
    "name:zho_x_preferred":[
        "\u56fd\u5bb6\u5c6f\u6751"
    ],
    "wof:name":"Guojiatuncun",
    "wof:placetype":"locality"
},
  "geometry": {"coordinates":[125.15824000000001,44.02823],"type":"Point"}
}