{
  "type": "Feature",
  "properties": {
    "gn:admin1_code":"3.0",
    "gn:asciiname":"Qincaitang",
    "gn:country_code":"CN",
    "gn:dem":41,
    "gn:feature_class":"P",
    "gn:feature_code":"PPL",
    "gn:name":"Qincaitang",
    "gn:population":0,
    "gn:timezone":"Asia/Shanghai",
    "iso:country":"CN",
    "name:und_x_variant":[
        "\u82b9\u83dc\u5858"
    ],
    "wof:name":"Qincaitang",
    "wof:placetype":"locality"
},
  "geometry": {"coordinates":[115.42368,28.71085],"type":"Point"}
}