{
  "type": "Feature",
  "properties": {
    "gn:admin1_code":"29.0",
    "gn:asciiname":"Lao'ercun",
    "gn:country_code":"CN",
    "gn:dem":1365,
    "gn:feature_class":"P",
    "gn:feature_code":"PPL",
    "gn:name":"Lao\u2019ercun",
    "gn:population":0,
    "gn:timezone":"Asia/Shanghai",
    "iso:country":"CN",
    "name:und_x_variant":[
        "Lao\u2019ercun"
    ],
    "name:zho_x_preferred":[
        "\u8001\u8033\u6751"
    ],
    "wof:name":"Lao'ercun",
    "wof:placetype":"locality"
},
  "geometry": {"coordinates":[101.917,25.0213],"type":"Point"}
}