{
  "type": "Feature",
  "properties": {
    "gn:admin1_code":"21.0",
    "gn:asciiname":"Beiwali",
    "gn:country_code":"CN",
    "gn:dem":1818,
    "gn:feature_class":"P",
    "gn:feature_code":"PPL",
    "gn:name":"Beiwali",
    "gn:population":0,
    "gn:timezone":"Asia/Shanghai",
    "iso:country":"CN",
    "name:zho_x_preferred":[
        "\u5317\u6d3c\u91cc"
    ],
    "wof:name":"Beiwali",
    "wof:placetype":"locality"
},
  "geometry": {"coordinates":[106.24628,36.26189],"type":"Point"}
}