{
  "type": "Feature",
  "properties": {
    "gn:admin1_code":"1.0",
    "gn:asciiname":"Jiulongcun",
    "gn:country_code":"CN",
    "gn:dem":74,
    "gn:feature_class":"P",
    "gn:feature_code":"PPL",
    "gn:name":"Jiulongcun",
    "gn:population":0,
    "gn:timezone":"Asia/Shanghai",
    "iso:country":"CN",
    "name:zho_x_preferred":[
        "\u4e5d\u9f99\u6751"
    ],
    "wof:name":"Jiulongcun",
    "wof:placetype":"locality"
},
  "geometry": {"coordinates":[116.58138,31.69951],"type":"Point"}
}