{
  "type": "Feature",
  "properties": {
    "gn:admin1_code":"10.0",
    "gn:asciiname":"Yinjiagou",
    "gn:country_code":"CN",
    "gn:dem":888,
    "gn:feature_class":"P",
    "gn:feature_code":"PPL",
    "gn:name":"Yinjiagou",
    "gn:population":0,
    "gn:timezone":"Asia/Shanghai",
    "iso:country":"CN",
    "name:zho_x_preferred":[
        "\u6bb7\u5bb6\u6c9f"
    ],
    "wof:name":"Yinjiagou",
    "wof:placetype":"locality"
},
  "geometry": {"coordinates":[114.81236,40.23354000000001],"type":"Point"}
}