{
  "type": "Feature",
  "properties": {
    "gn:admin1_code":"29.0",
    "gn:asciiname":"Shangdongguantun",
    "gn:country_code":"CN",
    "gn:dem":1648,
    "gn:feature_class":"P",
    "gn:feature_code":"PPL",
    "gn:name":"Shangdongguantun",
    "gn:population":0,
    "gn:timezone":"Asia/Shanghai",
    "iso:country":"CN",
    "name:zho_x_preferred":[
        "\u4e0a\u8463\u5b98\u5c6f"
    ],
    "wof:name":"Shangdongguantun",
    "wof:placetype":"locality"
},
  "geometry": {"coordinates":[99.2242,25.1088],"type":"Point"}
}