{
  "type": "Feature",
  "properties": {
    "gn:admin1_code":"12.0",
    "gn:asciiname":"Chongyugou",
    "gn:country_code":"CN",
    "gn:dem":379,
    "gn:feature_class":"P",
    "gn:feature_code":"PPL",
    "gn:name":"Chongyugou",
    "gn:population":0,
    "gn:timezone":"Asia/Shanghai",
    "iso:country":"CN",
    "name:zho_x_preferred":[
        "\u866b\u7fbd\u6c9f"
    ],
    "wof:name":"Chongyugou",
    "wof:placetype":"locality"
},
  "geometry": {"coordinates":[111.06938999999998,32.78673],"type":"Point"}
}