{
  "type": "Feature",
  "properties": {
    "gn:admin1_code":"30.0",
    "gn:asciiname":"Nongchang",
    "gn:country_code":"CN",
    "gn:dem":16,
    "gn:feature_class":"P",
    "gn:feature_code":"PPL",
    "gn:name":"Nongchang",
    "gn:population":0,
    "gn:timezone":"Asia/Shanghai",
    "iso:country":"CN",
    "name:zho_x_preferred":[
        "\u8fb2\u5834"
    ],
    "wof:name":"Nongchang",
    "wof:placetype":"locality"
},
  "geometry": {"coordinates":[112.94687999999999,22.11473],"type":"Point"}
}