{
  "type": "Feature",
  "properties": {
    "gn:admin1_code":"4.0",
    "gn:asciiname":"Zhuanghu",
    "gn:country_code":"CN",
    "gn:dem":5,
    "gn:feature_class":"P",
    "gn:feature_code":"PPL",
    "gn:name":"Zhuanghu",
    "gn:population":0,
    "gn:timezone":"Asia/Shanghai",
    "iso:country":"CN",
    "name:zho_x_preferred":[
        "Zhuanghu"
    ],
    "name:zho_x_variant":[
        "\u5e84\u6e56"
    ],
    "wof:name":"Zhuanghu",
    "wof:placetype":"locality"
},
  "geometry": {"coordinates":[121.61028,31.83755],"type":"Point"}
}