{
  "type": "Feature",
  "properties": {
    "gn:admin1_code":"11.0",
    "gn:asciiname":"Jipoyan",
    "gn:country_code":"CN",
    "gn:dem":663,
    "gn:feature_class":"P",
    "gn:feature_code":"PPL",
    "gn:name":"Jipoyan",
    "gn:population":0,
    "gn:timezone":"Asia/Shanghai",
    "iso:country":"CN",
    "name:zho_x_preferred":[
        "\u9e21\u5a46\u5ca9"
    ],
    "wof:name":"Jipoyan",
    "wof:placetype":"locality"
},
  "geometry": {"coordinates":[110.06594,26.45794],"type":"Point"}
}