{
  "type": "Feature",
  "properties": {
    "gn:admin1_code":"19.0",
    "gn:asciiname":"Xiaoliangzigou",
    "gn:country_code":"CN",
    "gn:dem":268,
    "gn:feature_class":"P",
    "gn:feature_code":"PPL",
    "gn:name":"Xiaoliangzigou",
    "gn:population":0,
    "gn:timezone":"Asia/Shanghai",
    "iso:country":"CN",
    "name:zho_x_preferred":[
        "\u5c0f\u4eae\u5b50\u6c9f"
    ],
    "wof:name":"Xiaoliangzigou",
    "wof:placetype":"locality"
},
  "geometry": {"coordinates":[124.71496,40.73808],"type":"Point"}
}