{
  "type": "Feature",
  "properties": {
    "gn:admin1_code":"29.0",
    "gn:asciiname":"Badong",
    "gn:country_code":"CN",
    "gn:dem":1485,
    "gn:feature_class":"P",
    "gn:feature_code":"PPL",
    "gn:name":"Badong",
    "gn:population":0,
    "gn:timezone":"Asia/Shanghai",
    "iso:country":"CN",
    "name:zho_x_preferred":[
        "\u5df4\u4e1c"
    ],
    "wof:name":"Badong",
    "wof:placetype":"locality"
},
  "geometry": {"coordinates":[102.47,22.9406],"type":"Point"}
}