{
  "type": "Feature",
  "properties": {
    "gn:admin1_code":"07",
    "gn:asciiname":"Fuzhu",
    "gn:country_code":"CN",
    "gn:dem":546,
    "gn:feature_class":"P",
    "gn:feature_code":"PPL",
    "gn:name":"Fuzhu",
    "gn:population":0,
    "gn:timezone":"Asia/Shanghai",
    "iso:country":"CN",
    "name:zho_x_preferred":[
        "\u6d6e\u7af9"
    ],
    "wof:name":"Fuzhu",
    "wof:placetype":"locality"
},
  "geometry": {"coordinates":[117.16079000000001,25.67557],"type":"Point"}
}