{
  "type": "Feature",
  "properties": {
    "gn:admin1_code":"4.0",
    "gn:asciiname":"Jiagangcun",
    "gn:country_code":"CN",
    "gn:dem":9,
    "gn:feature_class":"P",
    "gn:feature_code":"PPL",
    "gn:name":"Jiagangcun",
    "gn:population":0,
    "gn:timezone":"Asia/Shanghai",
    "iso:country":"CN",
    "name:zho_x_preferred":[
        "\u5939\u5c97\u6751"
    ],
    "wof:name":"Jiagangcun",
    "wof:placetype":"locality"
},
  "geometry": {"coordinates":[118.80150999999999,31.98651],"type":"Point"}
}