{
  "type": "Feature",
  "properties": {
    "gn:admin1_code":"5.0",
    "gn:asciiname":"Xiaolangshan",
    "gn:country_code":"CN",
    "gn:dem":151,
    "gn:feature_class":"P",
    "gn:feature_code":"PPL",
    "gn:name":"Xiaolangshan",
    "gn:population":0,
    "gn:timezone":"Asia/Shanghai",
    "iso:country":"CN",
    "name:zho_x_preferred":[
        "\u5c0f\u72fc\u5c71"
    ],
    "wof:name":"Xiaolangshan",
    "wof:placetype":"locality"
},
  "geometry": {"coordinates":[123.80732999999999,44.64383],"type":"Point"}
}