{
  "type": "Feature",
  "properties": {
    "gn:admin1_code":"19.0",
    "gn:asciiname":"Sidawang",
    "gn:country_code":"CN",
    "gn:dem":207,
    "gn:feature_class":"P",
    "gn:feature_code":"PPL",
    "gn:name":"Sidawang",
    "gn:population":0,
    "gn:timezone":"Asia/Shanghai",
    "iso:country":"CN",
    "name:zho_x_preferred":[
        "\u56db\u5927\u671b"
    ],
    "wof:name":"Sidawang",
    "wof:placetype":"locality"
},
  "geometry": {"coordinates":[121.44499999999999,38.9473],"type":"Point"}
}