{
  "type": "Feature",
  "properties": {
    "gn:admin1_code":"15.0",
    "gn:asciiname":"Lijiachawan",
    "gn:country_code":"CN",
    "gn:dem":2156,
    "gn:feature_class":"P",
    "gn:feature_code":"PPL",
    "gn:name":"Lijiachawan",
    "gn:population":0,
    "gn:timezone":"Asia/Shanghai",
    "iso:country":"CN",
    "name:zho_x_preferred":[
        "\u674e\u5bb6\u5c94\u6e7e"
    ],
    "wof:name":"Lijiachawan",
    "wof:placetype":"locality"
},
  "geometry": {"coordinates":[104.931,35.4429],"type":"Point"}
}