{
  "type": "Feature",
  "properties": {
    "gn:admin1_code":"15.0",
    "gn:asciiname":"Zhangqi",
    "gn:country_code":"CN",
    "gn:dem":1530,
    "gn:feature_class":"P",
    "gn:feature_code":"PPL",
    "gn:name":"Zhangqi",
    "gn:population":0,
    "gn:timezone":"Asia/Shanghai",
    "iso:country":"CN",
    "name:zho_x_preferred":[
        "\u5f20\u65d7"
    ],
    "wof:name":"Zhangqi",
    "wof:placetype":"locality"
},
  "geometry": {"coordinates":[107.55200000000001,35.9704],"type":"Point"}
}