{
  "type": "Feature",
  "properties": {
    "gn:admin1_code":"12.0",
    "gn:asciiname":"Jiangliangting",
    "gn:country_code":"CN",
    "gn:dem":26,
    "gn:feature_class":"P",
    "gn:feature_code":"PPL",
    "gn:name":"Jiangliangting",
    "gn:population":0,
    "gn:timezone":"Asia/Shanghai",
    "iso:country":"CN",
    "name:zho_x_preferred":[
        "Jiangliangting"
    ],
    "name:zho_x_variant":[
        "\u6c5f\u51c9\u4ead"
    ],
    "wof:name":"Jiangliangting",
    "wof:placetype":"locality"
},
  "geometry": {"coordinates":[115.44023,30.27269],"type":"Point"}
}