{
  "type": "Feature",
  "properties": {
    "gn:admin1_code":"10",
    "gn:asciiname":"Shuihutong",
    "gn:country_code":"CN",
    "gn:dem":335,
    "gn:feature_class":"P",
    "gn:feature_code":"PPL",
    "gn:name":"Shuihutong",
    "gn:population":0,
    "gn:timezone":"Asia/Shanghai",
    "iso:country":"CN",
    "name:zho_x_preferred":[
        "\u6c34\u80e1\u540c"
    ],
    "wof:name":"Shuihutong",
    "wof:placetype":"locality"
},
  "geometry": {"coordinates":[118.98596999999999,40.46511],"type":"Point"}
}