{
  "type": "Feature",
  "properties": {
    "gn:admin1_code":"4.0",
    "gn:asciiname":"Gangbu Nongchang",
    "gn:country_code":"CN",
    "gn:dem":1,
    "gn:feature_class":"P",
    "gn:feature_code":"PPLF",
    "gn:name":"Gangbu Nongchang",
    "gn:population":0,
    "gn:timezone":"Asia/Shanghai",
    "iso:country":"CN",
    "wof:name":"Gangbu Nongchang",
    "wof:placetype":"locality"
},
  "geometry": {"coordinates":[119.03333000000001,34.59167],"type":"Point"}
}