{
  "type": "Feature",
  "properties": {
    "gn:admin1_code":"3",
    "gn:asciiname":"Shantiankeng",
    "gn:country_code":"CN",
    "gn:dem":122,
    "gn:feature_class":"P",
    "gn:feature_code":"PPL",
    "gn:name":"Shantiankeng",
    "gn:population":0,
    "gn:timezone":"Asia/Shanghai",
    "iso:country":"CN",
    "name:zho_x_preferred":[
        "\u5c71\u7530\u5751"
    ],
    "wof:name":"Shantiankeng",
    "wof:placetype":"locality"
},
  "geometry": {"coordinates":[114.587,26.3301],"type":"Point"}
}