{
  "type": "Feature",
  "properties": {
    "gn:admin1_code":"32.0",
    "gn:asciiname":"Duanjingshan",
    "gn:country_code":"CN",
    "gn:dem":268,
    "gn:feature_class":"P",
    "gn:feature_code":"PPL",
    "gn:name":"Duanjingshan",
    "gn:population":0,
    "gn:timezone":"Asia/Shanghai",
    "iso:country":"CN",
    "name:zho_x_preferred":[
        "\u6bb5\u4e95\u5c71"
    ],
    "wof:name":"Duanjingshan",
    "wof:placetype":"locality"
},
  "geometry": {"coordinates":[104.93425000000001,28.62313],"type":"Point"}
}