{
  "type": "Feature",
  "properties": {
    "gn:admin1_code":"14.0",
    "gn:asciiname":"Bariguomacun",
    "gn:country_code":"CN",
    "gn:dem":4895,
    "gn:feature_class":"P",
    "gn:feature_code":"PPL",
    "gn:name":"Bariguomacun",
    "gn:population":0,
    "gn:timezone":"Asia/Urumqi",
    "iso:country":"CN",
    "name:zho_x_preferred":[
        "\u5df4\u65e5\u679c\u739b\u6751"
    ],
    "wof:name":"Bariguomacun",
    "wof:placetype":"locality"
},
  "geometry": {"coordinates":[92.01721999999999,32.03142],"type":"Point"}
}