{
  "type": "Feature",
  "properties": {
    "gn:admin1_code":"19.0",
    "gn:asciiname":"Xiazhuantai",
    "gn:country_code":"CN",
    "gn:dem":185,
    "gn:feature_class":"P",
    "gn:feature_code":"PPL",
    "gn:name":"Xiazhuantai",
    "gn:population":0,
    "gn:timezone":"Asia/Shanghai",
    "iso:country":"CN",
    "name:und_x_variant":[
        "\u4e0b\u7816\u53f0"
    ],
    "name:zho_x_preferred":[
        "\u4e0b\u7816\u53f0"
    ],
    "wof:name":"Xiazhuantai",
    "wof:placetype":"locality"
},
  "geometry": {"coordinates":[123.88936,42.00253],"type":"Point"}
}