{
  "type": "Feature",
  "properties": {
    "gn:admin1_code":"32.0",
    "gn:asciiname":"Shulinzi",
    "gn:country_code":"CN",
    "gn:dem":721,
    "gn:feature_class":"P",
    "gn:feature_code":"PPL",
    "gn:name":"Shulinzi",
    "gn:population":0,
    "gn:timezone":"Asia/Shanghai",
    "iso:country":"CN",
    "name:zho_x_preferred":[
        "\u758f\u6797\u5b50"
    ],
    "wof:name":"Shulinzi",
    "wof:placetype":"locality"
},
  "geometry": {"coordinates":[107.34043,31.61402],"type":"Point"}
}