{
  "type": "Feature",
  "properties": {
    "gn:admin1_code":"26.0",
    "gn:asciiname":"Huangtuliang",
    "gn:country_code":"CN",
    "gn:dem":1045,
    "gn:feature_class":"P",
    "gn:feature_code":"PPL",
    "gn:name":"Huangtuliang",
    "gn:population":0,
    "gn:timezone":"Asia/Shanghai",
    "iso:country":"CN",
    "name:zho_x_preferred":[
        "\u9ec4\u571f\u6881"
    ],
    "wof:name":"Huangtuliang",
    "wof:placetype":"locality"
},
  "geometry": {"coordinates":[108.84417999999999,33.93631],"type":"Point"}
}