{
  "type": "Feature",
  "properties": {
    "gn:admin1_code":"24.0",
    "gn:asciiname":"Shangliugou",
    "gn:country_code":"CN",
    "gn:dem":1415,
    "gn:feature_class":"P",
    "gn:feature_code":"PPL",
    "gn:name":"Shangliugou",
    "gn:population":0,
    "gn:timezone":"Asia/Shanghai",
    "iso:country":"CN",
    "name:zho_x_preferred":[
        "\u4e0a\u67f3\u6c9f"
    ],
    "wof:name":"Shangliugou",
    "wof:placetype":"locality"
},
  "geometry": {"coordinates":[112.4079,39.73161],"type":"Point"}
}