{
  "type": "Feature",
  "properties": {
    "gn:admin1_code":"32.0",
    "gn:asciiname":"Gaozong",
    "gn:country_code":"CN",
    "gn:dem":471,
    "gn:feature_class":"P",
    "gn:feature_code":"PPL",
    "gn:name":"Gaozong",
    "gn:population":0,
    "gn:timezone":"Asia/Shanghai",
    "iso:country":"CN",
    "name:deu_x_preferred":[
        "Gaozong"
    ],
    "name:fra_x_preferred":[
        "Gaozong"
    ],
    "name:mar_x_preferred":[
        "\u0915\u093e\u0913\u091c\u093e\u0901\u0917"
    ],
    "name:nld_x_preferred":[
        "Gaozong"
    ],
    "name:pol_x_preferred":[
        "Gaozong"
    ],
    "name:tha_x_preferred":[
        "\u0e08\u0e31\u0e01\u0e23\u0e1e\u0e23\u0e23\u0e14\u0e34\u0e40\u0e01\u0e32\u0e08\u0e07"
    ],
    "name:zho_x_preferred":[
        "\u9ad8\u679e"
    ],
    "wof:name":"Gaozong",
    "wof:placetype":"locality"
},
  "geometry": {"coordinates":[104.026,30.0553],"type":"Point"}
}