{
  "type": "Feature",
  "properties": {
    "gn:admin1_code":"15.0",
    "gn:asciiname":"Xingwan",
    "gn:country_code":"CN",
    "gn:dem":1820,
    "gn:feature_class":"P",
    "gn:feature_code":"PPL",
    "gn:name":"Xingwan",
    "gn:population":0,
    "gn:timezone":"Asia/Shanghai",
    "iso:country":"CN",
    "name:und_x_variant":[
        "\u674f\u6e7e"
    ],
    "wof:name":"Xingwan",
    "wof:placetype":"locality"
},
  "geometry": {"coordinates":[105.54889,35.36767000000001],"type":"Point"}
}