{
  "type": "Feature",
  "properties": {
    "gn:admin1_code":"32.0",
    "gn:asciiname":"Yuanbaishu",
    "gn:country_code":"CN",
    "gn:dem":855,
    "gn:feature_class":"P",
    "gn:feature_code":"PPL",
    "gn:name":"Yuanbaishu",
    "gn:population":0,
    "gn:timezone":"Asia/Shanghai",
    "iso:country":"CN",
    "name:zho_x_preferred":[
        "\u56ed\u67cf\u6811"
    ],
    "name:zho_x_variant":[
        "\u5706\u67cf\u6811"
    ],
    "wof:name":"Yuanbaishu",
    "wof:placetype":"locality"
},
  "geometry": {"coordinates":[105.828,32.15351],"type":"Point"}
}