{
  "type": "Feature",
  "properties": {
    "gn:admin1_code":"24.0",
    "gn:asciiname":"Daobazui",
    "gn:country_code":"CN",
    "gn:dem":1311,
    "gn:feature_class":"P",
    "gn:feature_code":"PPL",
    "gn:name":"Daobazui",
    "gn:population":0,
    "gn:timezone":"Asia/Shanghai",
    "iso:country":"CN",
    "name:zho_x_preferred":[
        "\u5200\u628a\u5480"
    ],
    "wof:name":"Daobazui",
    "wof:placetype":"locality"
},
  "geometry": {"coordinates":[113.23199,36.73431],"type":"Point"}
}