{
  "type": "Feature",
  "properties": {
    "gn:admin1_code":"30",
    "gn:asciiname":"Luoshun",
    "gn:country_code":"CN",
    "gn:dem":161,
    "gn:feature_class":"P",
    "gn:feature_code":"PPL",
    "gn:name":"Luoshun",
    "gn:population":0,
    "gn:timezone":"Asia/Shanghai",
    "iso:country":"CN",
    "name:und_x_variant":[
        "\u7f57\u987a",
        "Luoshun Zhen",
        "\u7f57\u987a\u9547"
    ],
    "wof:name":"Luoshun",
    "wof:placetype":"locality"
},
  "geometry": {"coordinates":[111.41956999999999,23.10412],"type":"Point"}
}