{
  "type": "Feature",
  "properties": {
    "gn:admin1_code":"29.0",
    "gn:asciiname":"Mengkang",
    "gn:country_code":"CN",
    "gn:dem":1045,
    "gn:feature_class":"P",
    "gn:feature_code":"PPL",
    "gn:name":"Mengkang",
    "gn:population":0,
    "gn:timezone":"Asia/Shanghai",
    "iso:country":"CN",
    "name:zho_x_preferred":[
        "\u52d0\u5eb7"
    ],
    "wof:name":"Mengkang",
    "wof:placetype":"locality"
},
  "geometry": {"coordinates":[100.387,22.2418],"type":"Point"}
}