{
  "type": "Feature",
  "properties": {
    "gn:admin1_code":"25",
    "gn:asciiname":"Zhuquantun",
    "gn:country_code":"CN",
    "gn:dem":34,
    "gn:feature_class":"P",
    "gn:feature_code":"PPL",
    "gn:name":"Zhuquantun",
    "gn:population":0,
    "gn:timezone":"Asia/Shanghai",
    "iso:country":"CN",
    "name:zho_x_preferred":[
        "\u73e0\u6cc9\u5c6f"
    ],
    "wof:name":"Zhuquantun",
    "wof:placetype":"locality"
},
  "geometry": {"coordinates":[115.819,37.0239],"type":"Point"}
}