{
  "type": "Feature",
  "properties": {
    "gn:admin1_code":"8.0",
    "gn:asciiname":"Maoshengcun",
    "gn:country_code":"CN",
    "gn:dem":60,
    "gn:feature_class":"P",
    "gn:feature_code":"PPL",
    "gn:name":"Maoshengcun",
    "gn:population":0,
    "gn:timezone":"Asia/Shanghai",
    "iso:country":"CN",
    "name:zho_x_preferred":[
        "\u8302\u76db\u6751"
    ],
    "wof:name":"Maoshengcun",
    "wof:placetype":"locality"
},
  "geometry": {"coordinates":[132.15313,47.21205],"type":"Point"}
}