{
  "type": "Feature",
  "properties": {
    "gn:admin1_code":"19.0",
    "gn:asciiname":"Zhoujiagou",
    "gn:country_code":"CN",
    "gn:dem":75,
    "gn:feature_class":"P",
    "gn:feature_code":"PPL",
    "gn:name":"Zhoujiagou",
    "gn:population":0,
    "gn:timezone":"Asia/Shanghai",
    "iso:country":"CN",
    "name:und_x_variant":[
        "\u5468\u5bb6\u6c9f"
    ],
    "wof:name":"Zhoujiagou",
    "wof:placetype":"locality"
},
  "geometry": {"coordinates":[123.59242999999999,40.1077],"type":"Point"}
}