{
  "type": "Feature",
  "properties": {
    "gn:admin1_code":"11.0",
    "gn:asciiname":"Baijia Wuli",
    "gn:country_code":"CN",
    "gn:dem":57,
    "gn:feature_class":"P",
    "gn:feature_code":"PPL",
    "gn:name":"Baijia Wuli",
    "gn:population":0,
    "gn:timezone":"Asia/Shanghai",
    "iso:country":"CN",
    "name:zho_x_preferred":[
        "\u767d\u5bb6\u5c4b\u91cc"
    ],
    "wof:name":"Baijia Wuli",
    "wof:placetype":"locality"
},
  "geometry": {"coordinates":[113.28458999999999,28.78258],"type":"Point"}
}