{
  "type": "Feature",
  "properties": {
    "gn:admin1_code":"30.0",
    "gn:asciiname":"Qilixicun",
    "gn:country_code":"CN",
    "gn:dem":448,
    "gn:feature_class":"P",
    "gn:feature_code":"PPL",
    "gn:name":"Qilixicun",
    "gn:population":0,
    "gn:timezone":"Asia/Shanghai",
    "iso:country":"CN",
    "name:und_x_variant":[
        "Qilixi"
    ],
    "name:zho_x_preferred":[
        "\u4e03\u91cc\u6eaa\u6751"
    ],
    "name:zho_x_variant":[
        "\u4e03\u91cc\u6eaa"
    ],
    "wof:name":"Qilixicun",
    "wof:placetype":"locality"
},
  "geometry": {"coordinates":[116.76231,24.65244],"type":"Point"}
}