{
  "type": "Feature",
  "properties": {
    "gn:admin1_code":"29",
    "gn:asciiname":"Hemozhan",
    "gn:country_code":"CN",
    "gn:dem":1822,
    "gn:feature_class":"P",
    "gn:feature_code":"PPL",
    "gn:name":"Hemozhan",
    "gn:population":0,
    "gn:timezone":"Asia/Shanghai",
    "iso:country":"CN",
    "name:zho_x_preferred":[
        "\u548c\u6469\u7ad9"
    ],
    "wof:name":"Hemozhan",
    "wof:placetype":"locality"
},
  "geometry": {"coordinates":[103.35299999999999,24.892],"type":"Point"}
}