{
  "type": "Feature",
  "properties": {
    "gn:admin1_code":"4.0",
    "gn:asciiname":"Feiling",
    "gn:country_code":"CN",
    "gn:dem":29,
    "gn:feature_class":"P",
    "gn:feature_code":"PPL",
    "gn:name":"Feiling",
    "gn:population":0,
    "gn:timezone":"Asia/Shanghai",
    "iso:country":"CN",
    "name:und_x_variant":[
        "\u8d39\u5cad"
    ],
    "wof:name":"Feiling",
    "wof:placetype":"locality"
},
  "geometry": {"coordinates":[118.67562,34.43045],"type":"Point"}
}