{
  "type": "Feature",
  "properties": {
    "gn:admin1_code":"12.0",
    "gn:asciiname":"Liujiapo",
    "gn:country_code":"CN",
    "gn:dem":49,
    "gn:feature_class":"P",
    "gn:feature_code":"PPL",
    "gn:name":"Liujiapo",
    "gn:population":0,
    "gn:timezone":"Asia/Shanghai",
    "iso:country":"CN",
    "name:zho_x_preferred":[
        "Liujiapo"
    ],
    "name:zho_x_variant":[
        "\u5218\u5bb6\u5761"
    ],
    "wof:name":"Liujiapo",
    "wof:placetype":"locality"
},
  "geometry": {"coordinates":[111.79371999999999,30.46423],"type":"Point"}
}