{
  "type": "Feature",
  "properties": {
    "gn:admin1_code":"16.0",
    "gn:asciiname":"Zaohekeng",
    "gn:country_code":"CN",
    "gn:dem":17,
    "gn:feature_class":"P",
    "gn:feature_code":"PPL",
    "gn:name":"Zaohekeng",
    "gn:population":0,
    "gn:timezone":"Asia/Shanghai",
    "iso:country":"CN",
    "name:zho_x_preferred":[
        "\u65e9\u79be\u5751"
    ],
    "wof:name":"Zaohekeng",
    "wof:placetype":"locality"
},
  "geometry": {"coordinates":[108.792,21.7603],"type":"Point"}
}