{
  "type": "Feature",
  "properties": {
    "gn:admin1_code":"26.0",
    "gn:asciiname":"Jinzougou",
    "gn:country_code":"CN",
    "gn:dem":742,
    "gn:feature_class":"P",
    "gn:feature_code":"PPL",
    "gn:name":"Jinzougou",
    "gn:population":0,
    "gn:timezone":"Asia/Shanghai",
    "iso:country":"CN",
    "name:zho_x_preferred":[
        "\u8fd1\u8d70\u6c9f"
    ],
    "wof:name":"Jinzougou",
    "wof:placetype":"locality"
},
  "geometry": {"coordinates":[109.24677,32.9436],"type":"Point"}
}