{
  "type": "Feature",
  "properties": {
    "gn:admin1_code":"12.0",
    "gn:asciiname":"Tianjia Menlou",
    "gn:country_code":"CN",
    "gn:dem":54,
    "gn:feature_class":"P",
    "gn:feature_code":"PPL",
    "gn:name":"Tianjia Menlou",
    "gn:population":0,
    "gn:timezone":"Asia/Shanghai",
    "iso:country":"CN",
    "name:zho_x_preferred":[
        "\u7530\u5bb6\u95e8\u697c"
    ],
    "wof:name":"Tianjia Menlou",
    "wof:placetype":"locality"
},
  "geometry": {"coordinates":[112.98300999999999,30.80799],"type":"Point"}
}