{
  "type": "Feature",
  "properties": {
    "gn:admin1_code":"5.0",
    "gn:asciiname":"Zhongli",
    "gn:country_code":"CN",
    "gn:dem":530,
    "gn:feature_class":"P",
    "gn:feature_code":"PPL",
    "gn:name":"Zhongli",
    "gn:population":0,
    "gn:timezone":"Asia/Shanghai",
    "iso:country":"CN",
    "name:und_x_variant":[
        "\u4ef2\u91cc",
        "Zhonglicun",
        "\u4ef2\u91cc\u6751"
    ],
    "wof:name":"Zhongli",
    "wof:placetype":"locality"
},
  "geometry": {"coordinates":[128.87164000000001,42.74845],"type":"Point"}
}