{
  "type": "Feature",
  "properties": {
    "gn:admin1_code":"5.0",
    "gn:asciiname":"Zhongli",
    "gn:country_code":"CN",
    "gn:dem":530,
    "gn:feature_class":"P",
    "gn:feature_code":"PPL",
    "gn:name":"Zhongli",
    "gn:population":0,
    "gn:timezone":"Asia/Shanghai",
    "iso:country":"CN",
    "name:ben_x_preferred":[
        "\u099d\u0982\u09b2\u09bf"
    ],
    "name:ell_x_preferred":[
        "\u0396\u03bf\u03bd\u03b3\u03ba\u03bb\u03af"
    ],
    "name:fas_x_preferred":[
        "\u0698\u0648\u0646\u06af\u0644\u06cc"
    ],
    "name:heb_x_preferred":[
        "\u05d6'\u05d5\u05e0\u05d2\u05dc\u05d9"
    ],
    "name:hin_x_preferred":[
        "\u091d\u094b\u0902\u0917\u0932\u0940"
    ],
    "name:ind_x_preferred":[
        "Zhongli"
    ],
    "name:por_x_preferred":[
        "Zhongli"
    ],
    "name:tur_x_preferred":[
        "Zhongli"
    ],
    "name:ukr_x_preferred":[
        "\u0427\u0430\u043d\u0442\u0456\u043d"
    ],
    "name:und_x_variant":[
        "\u4ef2\u91cc",
        "Zhonglicun",
        "\u4ef2\u91cc\u6751"
    ],
    "name:urd_x_preferred":[
        "\u0632\u06c1\u0648\u0646\u06af\u0644\u06cc"
    ],
    "wof:name":"Zhongli",
    "wof:placetype":"locality"
},
  "geometry": {"coordinates":[128.87164000000001,42.74845],"type":"Point"}
}