{
  "type": "Feature",
  "properties": {
    "gn:admin1_code":"32.0",
    "gn:asciiname":"Aduping",
    "gn:country_code":"CN",
    "gn:dem":2343,
    "gn:feature_class":"P",
    "gn:feature_code":"PPL",
    "gn:name":"Aduping",
    "gn:population":0,
    "gn:timezone":"Asia/Shanghai",
    "iso:country":"CN",
    "name:zho_x_preferred":[
        "\u963f\u90fd\u576a"
    ],
    "wof:name":"Aduping",
    "wof:placetype":"locality"
},
  "geometry": {"coordinates":[101.786,27.8071],"type":"Point"}
}