{
  "type": "Feature",
  "properties": {
    "gn:admin1_code":"18",
    "gn:asciiname":"Duru",
    "gn:country_code":"CN",
    "gn:dem":649,
    "gn:feature_class":"P",
    "gn:feature_code":"PPLA3",
    "gn:name":"Duru",
    "gn:population":0,
    "gn:timezone":"Asia/Shanghai",
    "iso:country":"CN",
    "name:ita_x_preferred":[
        "Duru"
    ],
    "name:swa_x_preferred":[
        "Duru"
    ],
    "name:und_x_variant":[
        "Wuchuan",
        "Tu-ju",
        "Wu-ch\u2019uan-hsien",
        "Wuchwan",
        "Wuchwan-hsien",
        "Wuchuan Gelaozu Miaozu Zizhixian",
        "Duru Zhen"
    ],
    "name:zho_x_preferred":[
        "\u90fd\u6fe1"
    ],
    "name:zho_x_variant":[
        "\u52a1\u5ddd\u4ee1\u4f6c\u65cf\u82d7\u65cf\u81ea\u6cbb\u53bf",
        "\u90fd\u6fe1\u9547"
    ],
    "wof:name":"Duru",
    "wof:placetype":"locality"
},
  "geometry": {"coordinates":[107.887,28.5255],"type":"Point"}
}