{
  "type": "Feature",
  "properties": {
    "gn:admin1_code":"8.0",
    "gn:asciiname":"Sidaohezi",
    "gn:country_code":"CN",
    "gn:dem":330,
    "gn:feature_class":"P",
    "gn:feature_code":"PPL",
    "gn:name":"Sidaohezi",
    "gn:population":0,
    "gn:timezone":"Asia/Shanghai",
    "iso:country":"CN",
    "name:zho_x_preferred":[
        "\u56db\u9053\u6cb3\u5b50"
    ],
    "wof:name":"Sidaohezi",
    "wof:placetype":"locality"
},
  "geometry": {"coordinates":[127.56276,45.44081],"type":"Point"}
}