{
  "type": "Feature",
  "properties": {
    "gn:admin1_code":"5.0",
    "gn:asciiname":"Dujia Datun",
    "gn:country_code":"CN",
    "gn:dem":220,
    "gn:feature_class":"P",
    "gn:feature_code":"PPL",
    "gn:name":"Dujia Datun",
    "gn:population":0,
    "gn:timezone":"Asia/Shanghai",
    "iso:country":"CN",
    "name:zho_x_preferred":[
        "\u675c\u5bb6\u5927\u5c6f"
    ],
    "wof:name":"Dujia Datun",
    "wof:placetype":"locality"
},
  "geometry": {"coordinates":[125.64323,43.90903],"type":"Point"}
}