{
  "type": "Feature",
  "properties": {
    "gn:admin1_code":"3.0",
    "gn:asciiname":"Jiangxiatang",
    "gn:country_code":"CN",
    "gn:dem":403,
    "gn:feature_class":"P",
    "gn:feature_code":"PPL",
    "gn:name":"Jiangxiatang",
    "gn:population":0,
    "gn:timezone":"Asia/Shanghai",
    "iso:country":"CN",
    "name:und_x_variant":[
        "\u6c5f\u4e0b\u5858"
    ],
    "wof:name":"Jiangxiatang",
    "wof:placetype":"locality"
},
  "geometry": {"coordinates":[115.69993999999998,26.35942],"type":"Point"}
}