{
  "type": "Feature",
  "properties": {
    "gn:admin1_code":"10",
    "gn:asciiname":"Yangcaogou",
    "gn:country_code":"CN",
    "gn:dem":799,
    "gn:feature_class":"P",
    "gn:feature_code":"PPL",
    "gn:name":"Yangcaogou",
    "gn:population":0,
    "gn:timezone":"Asia/Shanghai",
    "iso:country":"CN",
    "name:zho_x_preferred":[
        "\u7f8a\u8349\u6c9f"
    ],
    "wof:name":"Yangcaogou",
    "wof:placetype":"locality"
},
  "geometry": {"coordinates":[116.48463,41.06886],"type":"Point"}
}