{
  "type": "Feature",
  "properties": {
    "gn:admin1_code":"15.0",
    "gn:asciiname":"Yuezangfu",
    "gn:country_code":"CN",
    "gn:dem":1965,
    "gn:feature_class":"P",
    "gn:feature_code":"PPL",
    "gn:name":"Yuezangfu",
    "gn:population":0,
    "gn:timezone":"Asia/Shanghai",
    "iso:country":"CN",
    "name:und_x_variant":[
        "\u5cb3\u85cf\u752b"
    ],
    "name:zho_x_preferred":[
        "\u5cb3\u85cf\u752b"
    ],
    "wof:name":"Yuezangfu",
    "wof:placetype":"locality"
},
  "geometry": {"coordinates":[104.43098999999999,33.93193],"type":"Point"}
}