{
  "type": "Feature",
  "properties": {
    "gn:admin1_code":"19.0",
    "gn:asciiname":"Maxigou",
    "gn:country_code":"CN",
    "gn:dem":631,
    "gn:feature_class":"P",
    "gn:feature_code":"PPL",
    "gn:name":"Maxigou",
    "gn:population":0,
    "gn:timezone":"Asia/Shanghai",
    "iso:country":"CN",
    "name:zho_x_preferred":[
        "\u9a6c\u897f\u6c9f"
    ],
    "wof:name":"Maxigou",
    "wof:placetype":"locality"
},
  "geometry": {"coordinates":[119.50740999999999,41.45512],"type":"Point"}
}