{
  "type": "Feature",
  "properties": {
    "gn:admin1_code":"24.0",
    "gn:asciiname":"Xiantaicun",
    "gn:country_code":"CN",
    "gn:dem":796,
    "gn:feature_class":"P",
    "gn:feature_code":"PPL",
    "gn:name":"Xiantaicun",
    "gn:population":0,
    "gn:timezone":"Asia/Shanghai",
    "iso:country":"CN",
    "name:zho_x_preferred":[
        "\u4ed9\u53f0\u6751"
    ],
    "wof:name":"Xiantaicun",
    "wof:placetype":"locality"
},
  "geometry": {"coordinates":[112.08954,37.10533],"type":"Point"}
}