{
  "type": "Feature",
  "properties": {
    "gn:admin1_code":"4.0",
    "gn:asciiname":"Wushan",
    "gn:country_code":"CN",
    "gn:dem":36,
    "gn:feature_class":"P",
    "gn:feature_code":"PPL",
    "gn:name":"Wushan",
    "gn:population":0,
    "gn:timezone":"Asia/Shanghai",
    "iso:country":"CN",
    "name:und_x_variant":[
        "Wu-shan-chen",
        "Wushan"
    ],
    "wof:name":"Wushan",
    "wof:placetype":"locality"
},
  "geometry": {"coordinates":[118.96348999999999,31.72776],"type":"Point"}
}