{
  "type": "Feature",
  "properties": {
    "gn:admin1_code":"18.0",
    "gn:asciiname":"Shangguise",
    "gn:country_code":"CN",
    "gn:dem":775,
    "gn:feature_class":"P",
    "gn:feature_code":"PPL",
    "gn:name":"Shangguise",
    "gn:population":0,
    "gn:timezone":"Asia/Shanghai",
    "iso:country":"CN",
    "name:zho_x_preferred":[
        "\u4e0a\u6842\u8272"
    ],
    "wof:name":"Shangguise",
    "wof:placetype":"locality"
},
  "geometry": {"coordinates":[108.94799999999999,26.9863],"type":"Point"}
}