{
  "type": "Feature",
  "properties": {
    "gn:admin1_code":"29.0",
    "gn:asciiname":"Zhegao",
    "gn:country_code":"CN",
    "gn:dem":1097,
    "gn:feature_class":"P",
    "gn:feature_code":"PPL",
    "gn:name":"Zhegao",
    "gn:population":0,
    "gn:timezone":"Asia/Shanghai",
    "iso:country":"CN",
    "name:zho_x_preferred":[
        "\u906e\u544a"
    ],
    "wof:name":"Zhegao",
    "wof:placetype":"locality"
},
  "geometry": {"coordinates":[98.4216,24.5928],"type":"Point"}
}