{
  "type": "Feature",
  "properties": {
    "gn:admin1_code":"19.0",
    "gn:asciiname":"Xiangbizi",
    "gn:country_code":"CN",
    "gn:dem":7,
    "gn:feature_class":"P",
    "gn:feature_code":"PPL",
    "gn:name":"Xiangbizi",
    "gn:population":0,
    "gn:timezone":"Asia/Shanghai",
    "iso:country":"CN",
    "name:zho_x_preferred":[
        "\u8c61\u9f3b\u5b50"
    ],
    "wof:name":"Xiangbizi",
    "wof:placetype":"locality"
},
  "geometry": {"coordinates":[122.51000000000001,41.1426],"type":"Point"}
}