{
  "type": "Feature",
  "properties": {
    "gn:admin1_code":"11.0",
    "gn:asciiname":"Jiashan",
    "gn:country_code":"CN",
    "gn:dem":87,
    "gn:feature_class":"P",
    "gn:feature_code":"PPLA4",
    "gn:name":"Jiashan",
    "gn:population":0,
    "gn:timezone":"Asia/Shanghai",
    "iso:country":"CN",
    "name:und_x_variant":[
        "\u5939\u5c71",
        "Yangping",
        "\u6768\u576a"
    ],
    "name:zho_x_preferred":[
        "Jiashan Zhen"
    ],
    "name:zho_x_variant":[
        "\u5939\u5c71\u9547"
    ],
    "wof:name":"Jiashan",
    "wof:placetype":"locality"
},
  "geometry": {"coordinates":[111.43850999999999,29.50937],"type":"Point"}
}