{
  "type": "Feature",
  "properties": {
    "gn:admin1_code":"24.0",
    "gn:asciiname":"Shuishentang",
    "gn:country_code":"CN",
    "gn:dem":1241,
    "gn:feature_class":"P",
    "gn:feature_code":"PPL",
    "gn:name":"Shuishentang",
    "gn:population":0,
    "gn:timezone":"Asia/Shanghai",
    "iso:country":"CN",
    "name:zho_x_preferred":[
        "\u6c34\u6df1\u5858"
    ],
    "wof:name":"Shuishentang",
    "wof:placetype":"locality"
},
  "geometry": {"coordinates":[112.95432,40.24779],"type":"Point"}
}