{
  "type": "Feature",
  "properties": {
    "gn:admin1_code":"24.0",
    "gn:asciiname":"Yincun",
    "gn:country_code":"CN",
    "gn:dem":811,
    "gn:feature_class":"P",
    "gn:feature_code":"PPL",
    "gn:name":"Yincun",
    "gn:population":0,
    "gn:timezone":"Asia/Shanghai",
    "iso:country":"CN",
    "name:und_x_variant":[
        "Yin-ts\u2019un",
        "Yincun"
    ],
    "name:zho_x_preferred":[
        "\u5c39\u6751"
    ],
    "wof:name":"Yincun",
    "wof:placetype":"locality"
},
  "geometry": {"coordinates":[112.65528,38.47833],"type":"Point"}
}