{
  "type": "Feature",
  "properties": {
    "gn:admin1_code":"32.0",
    "gn:asciiname":"Daijiashan",
    "gn:country_code":"CN",
    "gn:dem":897,
    "gn:feature_class":"P",
    "gn:feature_code":"PPL",
    "gn:name":"Daijiashan",
    "gn:population":0,
    "gn:timezone":"Asia/Shanghai",
    "iso:country":"CN",
    "name:zho_x_preferred":[
        "\u4ee3\u5bb6\u5c71"
    ],
    "wof:name":"Daijiashan",
    "wof:placetype":"locality"
},
  "geometry": {"coordinates":[105.58883,32.462],"type":"Point"}
}