{
  "type": "Feature",
  "properties": {
    "gn:admin1_code":"11",
    "gn:asciiname":"Dengjialing",
    "gn:country_code":"CN",
    "gn:dem":264,
    "gn:feature_class":"P",
    "gn:feature_code":"PPL",
    "gn:name":"Dengjialing",
    "gn:population":0,
    "gn:timezone":"Asia/Shanghai",
    "iso:country":"CN",
    "name:zho_x_preferred":[
        "\u9093\u5bb6\u5cad"
    ],
    "wof:name":"Dengjialing",
    "wof:placetype":"locality"
},
  "geometry": {"coordinates":[111.39024999999999,26.7163],"type":"Point"}
}