{
  "type": "Feature",
  "properties": {
    "gn:admin1_code":"26.0",
    "gn:asciiname":"Shunyangcun",
    "gn:country_code":"CN",
    "gn:dem":468,
    "gn:feature_class":"P",
    "gn:feature_code":"PPL",
    "gn:name":"Shunyangcun",
    "gn:population":0,
    "gn:timezone":"Asia/Shanghai",
    "iso:country":"CN",
    "name:zho_x_preferred":[
        "\u987a\u9633\u6751"
    ],
    "wof:name":"Shunyangcun",
    "wof:placetype":"locality"
},
  "geometry": {"coordinates":[109.16122,34.80088],"type":"Point"}
}