{
  "type": "Feature",
  "properties": {
    "gn:admin1_code":"4.0",
    "gn:asciiname":"Dongheping",
    "gn:country_code":"CN",
    "gn:dem":9,
    "gn:feature_class":"P",
    "gn:feature_code":"PPL",
    "gn:name":"Dongheping",
    "gn:population":0,
    "gn:timezone":"Asia/Shanghai",
    "iso:country":"CN",
    "name:zho_x_preferred":[
        "\u4e1c\u548c\u5e73"
    ],
    "wof:name":"Dongheping",
    "wof:placetype":"locality"
},
  "geometry": {"coordinates":[118.77667,33.69013],"type":"Point"}
}