{
  "type": "Feature",
  "properties": {
    "gn:admin1_code":"12.0",
    "gn:asciiname":"Xiangshucao",
    "gn:country_code":"CN",
    "gn:dem":915,
    "gn:feature_class":"P",
    "gn:feature_code":"PPL",
    "gn:name":"Xiangshucao",
    "gn:population":0,
    "gn:timezone":"Asia/Shanghai",
    "iso:country":"CN",
    "name:zho_x_preferred":[
        "Xiangshucao"
    ],
    "name:zho_x_variant":[
        "\u9999\u6811\u69fd"
    ],
    "wof:name":"Xiangshucao",
    "wof:placetype":"locality"
},
  "geometry": {"coordinates":[109.18089999999999,29.96033],"type":"Point"}
}