{
  "type": "Feature",
  "properties": {
    "gn:admin1_code":"9.0",
    "gn:asciiname":"Xuanhuabu",
    "gn:country_code":"CN",
    "gn:dem":80,
    "gn:feature_class":"P",
    "gn:feature_code":"PPL",
    "gn:name":"Xuanhuabu",
    "gn:population":0,
    "gn:timezone":"Asia/Shanghai",
    "iso:country":"CN",
    "name:zho_x_preferred":[
        "\u5ba3\u5316\u5821"
    ],
    "wof:name":"Xuanhuabu",
    "wof:placetype":"locality"
},
  "geometry": {"coordinates":[113.98097,35.01698],"type":"Point"}
}