{
  "type": "Feature",
  "properties": {
    "gn:admin1_code":"24.0",
    "gn:asciiname":"Yangmanliang",
    "gn:country_code":"CN",
    "gn:dem":1304,
    "gn:feature_class":"P",
    "gn:feature_code":"PPL",
    "gn:name":"Yangmanliang",
    "gn:population":0,
    "gn:timezone":"Asia/Shanghai",
    "iso:country":"CN",
    "name:zho_x_preferred":[
        "\u9633\u6f2b\u6881"
    ],
    "wof:name":"Yangmanliang",
    "wof:placetype":"locality"
},
  "geometry": {"coordinates":[111.40338,39.23219],"type":"Point"}
}