{
  "type": "Feature",
  "properties": {
    "gn:admin1_code":"7.0",
    "gn:asciiname":"Xiaoji",
    "gn:country_code":"CN",
    "gn:dem":638,
    "gn:feature_class":"P",
    "gn:feature_code":"PPL",
    "gn:name":"Xiaoji",
    "gn:population":0,
    "gn:timezone":"Asia/Shanghai",
    "iso:country":"CN",
    "name:zho_x_preferred":[
        "Xiaoji"
    ],
    "name:zho_x_variant":[
        "\u5c0f\u5409"
    ],
    "wof:name":"Xiaoji",
    "wof:placetype":"locality"
},
  "geometry": {"coordinates":[118.63278,26.56889],"type":"Point"}
}