{
  "type": "Feature",
  "properties": {
    "gn:admin1_code":"15.0",
    "gn:asciiname":"Hedayuan",
    "gn:country_code":"CN",
    "gn:dem":1524,
    "gn:feature_class":"P",
    "gn:feature_code":"PPL",
    "gn:name":"Hedayuan",
    "gn:population":0,
    "gn:timezone":"Asia/Shanghai",
    "iso:country":"CN",
    "name:und_x_variant":[
        "\u4f55\u5927\u586c"
    ],
    "wof:name":"Hedayuan",
    "wof:placetype":"locality"
},
  "geometry": {"coordinates":[107.35301,36.46073],"type":"Point"}
}