{
  "type": "Feature",
  "properties": {
    "gn:admin1_code":"4.0",
    "gn:asciiname":"Zhoufeng",
    "gn:country_code":"CN",
    "gn:dem":4,
    "gn:feature_class":"P",
    "gn:feature_code":"PPL",
    "gn:name":"Zhoufeng",
    "gn:population":0,
    "gn:timezone":"Asia/Shanghai",
    "iso:country":"CN",
    "name:zho_x_preferred":[
        "\u5468\u51af"
    ],
    "wof:name":"Zhoufeng",
    "wof:placetype":"locality"
},
  "geometry": {"coordinates":[119.58374000000001,32.73622],"type":"Point"}
}