{
  "type": "Feature",
  "properties": {
    "gn:admin1_code":"16.0",
    "gn:asciiname":"Liuwancun",
    "gn:country_code":"CN",
    "gn:dem":430,
    "gn:feature_class":"P",
    "gn:feature_code":"PPL",
    "gn:name":"Liuwancun",
    "gn:population":0,
    "gn:timezone":"Asia/Shanghai",
    "iso:country":"CN",
    "name:zho_x_preferred":[
        "\u516d\u4e07\u6751"
    ],
    "wof:name":"Liuwancun",
    "wof:placetype":"locality"
},
  "geometry": {"coordinates":[106.624,24.1615],"type":"Point"}
}