{
  "type": "Feature",
  "properties": {
    "gn:admin1_code":"3.0",
    "gn:asciiname":"Gangbei",
    "gn:country_code":"CN",
    "gn:dem":88,
    "gn:feature_class":"P",
    "gn:feature_code":"PPL",
    "gn:name":"Gangbei",
    "gn:population":0,
    "gn:timezone":"Asia/Shanghai",
    "iso:country":"CN",
    "name:und_x_variant":[
        "\u6e2f\u5317"
    ],
    "wof:name":"Gangbei",
    "wof:placetype":"locality"
},
  "geometry": {"coordinates":[117.23482,29.76077],"type":"Point"}
}