{
  "type": "Feature",
  "properties": {
    "gn:admin1_code":"29.0",
    "gn:asciiname":"Yuntaisi",
    "gn:country_code":"CN",
    "gn:dem":1777,
    "gn:feature_class":"P",
    "gn:feature_code":"PPL",
    "gn:name":"Yuntaisi",
    "gn:population":0,
    "gn:timezone":"Asia/Shanghai",
    "iso:country":"CN",
    "name:zho_x_preferred":[
        "\u4e91\u53f0\u5bfa"
    ],
    "wof:name":"Yuntaisi",
    "wof:placetype":"locality"
},
  "geometry": {"coordinates":[97.8479,24.7739],"type":"Point"}
}