{
  "type": "Feature",
  "properties": {
    "gn:admin1_code":"10",
    "gn:asciiname":"Han'erzhuang",
    "gn:country_code":"CN",
    "gn:dem":159,
    "gn:feature_class":"P",
    "gn:feature_code":"PPL",
    "gn:name":"Han\u2019erzhuang",
    "gn:population":0,
    "gn:timezone":"Asia/Shanghai",
    "iso:country":"CN",
    "name:und_x_variant":[
        "Han-erh-chuang",
        "Han\u2019erzhuang"
    ],
    "wof:name":"Han'erzhuang",
    "wof:placetype":"locality"
},
  "geometry": {"coordinates":[118.21444,40.36389000000001],"type":"Point"}
}