{
  "type": "Feature",
  "properties": {
    "gn:admin1_code":"8.0",
    "gn:asciiname":"Fushanyongcun",
    "gn:country_code":"CN",
    "gn:dem":211,
    "gn:feature_class":"P",
    "gn:feature_code":"PPL",
    "gn:name":"Fushanyongcun",
    "gn:population":0,
    "gn:timezone":"Asia/Shanghai",
    "iso:country":"CN",
    "name:zho_x_preferred":[
        "\u798f\u5c71\u6c38\u6751"
    ],
    "wof:name":"Fushanyongcun",
    "wof:placetype":"locality"
},
  "geometry": {"coordinates":[123.2303,47.60696],"type":"Point"}
}