{
  "type": "Feature",
  "properties": {
    "gn:admin1_code":"5.0",
    "gn:asciiname":"Pingbuzicun",
    "gn:country_code":"CN",
    "gn:dem":231,
    "gn:feature_class":"P",
    "gn:feature_code":"PPL",
    "gn:name":"Pingbuzicun",
    "gn:population":0,
    "gn:timezone":"Asia/Shanghai",
    "iso:country":"CN",
    "name:zho_x_preferred":[
        "\u5e73\u57e0\u5b50\u6751"
    ],
    "wof:name":"Pingbuzicun",
    "wof:placetype":"locality"
},
  "geometry": {"coordinates":[125.94717,43.42917],"type":"Point"}
}