{
  "type": "Feature",
  "properties": {
    "gn:admin1_code":"19.0",
    "gn:asciiname":"Beidianzicun",
    "gn:country_code":"CN",
    "gn:dem":537,
    "gn:feature_class":"P",
    "gn:feature_code":"PPL",
    "gn:name":"Beidianzicun",
    "gn:population":0,
    "gn:timezone":"Asia/Shanghai",
    "iso:country":"CN",
    "name:zho_x_preferred":[
        "\u5317\u5e97\u5b50\u6751"
    ],
    "wof:name":"Beidianzicun",
    "wof:placetype":"locality"
},
  "geometry": {"coordinates":[125.13612999999999,41.99381],"type":"Point"}
}