{
  "type": "Feature",
  "properties": {
    "gn:admin1_code":"7",
    "gn:asciiname":"Xizhuzhai",
    "gn:country_code":"CN",
    "gn:dem":673,
    "gn:feature_class":"P",
    "gn:feature_code":"PPL",
    "gn:name":"Xizhuzhai",
    "gn:population":0,
    "gn:timezone":"Asia/Shanghai",
    "iso:country":"CN",
    "name:und_x_variant":[
        "\u897f\u7af9\u5b85",
        "Xizhuzhai"
    ],
    "wof:name":"Xizhuzhai",
    "wof:placetype":"locality"
},
  "geometry": {"coordinates":[119.95553999999998,27.2632],"type":"Point"}
}