{
  "type": "Feature",
  "properties": {
    "gn:admin1_code":"01",
    "gn:asciiname":"Huanggang",
    "gn:cc2":"CN",
    "gn:country_code":"CN",
    "gn:dem":29,
    "gn:feature_class":"P",
    "gn:feature_code":"PPL",
    "gn:name":"Huanggang",
    "gn:population":0,
    "gn:timezone":"Asia/Shanghai",
    "iso:country":"CN",
    "name:und_x_variant":[
        "Huang-kang-ssu",
        "Huang-kang",
        "Huanggang"
    ],
    "wof:name":"Huanggang",
    "wof:placetype":"locality"
},
  "geometry": {"coordinates":[115.81667,32.61667],"type":"Point"}
}