{
  "type": "Feature",
  "properties": {
    "gn:admin1_code":"32.0",
    "gn:asciiname":"Toupingzi",
    "gn:country_code":"CN",
    "gn:dem":1423,
    "gn:feature_class":"P",
    "gn:feature_code":"PPL",
    "gn:name":"Toupingzi",
    "gn:population":0,
    "gn:timezone":"Asia/Shanghai",
    "iso:country":"CN",
    "name:zho_x_preferred":[
        "\u5934\u576a\u5b50"
    ],
    "wof:name":"Toupingzi",
    "wof:placetype":"locality"
},
  "geometry": {"coordinates":[103.655,28.3472],"type":"Point"}
}