{
  "type": "Feature",
  "properties": {
    "gn:admin1_code":"10",
    "gn:asciiname":"Wangbojigou",
    "gn:country_code":"CN",
    "gn:dem":1366,
    "gn:feature_class":"P",
    "gn:feature_code":"PPL",
    "gn:name":"Wangbojigou",
    "gn:population":0,
    "gn:timezone":"Asia/Shanghai",
    "iso:country":"CN",
    "name:zho_x_preferred":[
        "\u738b\u7c38\u7b95\u6c9f"
    ],
    "wof:name":"Wangbojigou",
    "wof:placetype":"locality"
},
  "geometry": {"coordinates":[114.6619,41.23738],"type":"Point"}
}