{
  "type": "Feature",
  "properties": {
    "gn:admin1_code":"29",
    "gn:asciiname":"Yixi",
    "gn:country_code":"CN",
    "gn:dem":1915,
    "gn:feature_class":"P",
    "gn:feature_code":"PPL",
    "gn:name":"Yixi",
    "gn:population":0,
    "gn:timezone":"Asia/Shanghai",
    "iso:country":"CN",
    "name:zho_x_preferred":[
        "\u8fe4\u5e2d"
    ],
    "wof:name":"Yixi",
    "wof:placetype":"locality"
},
  "geometry": {"coordinates":[102.28100000000001,23.5135],"type":"Point"}
}