{
  "type": "Feature",
  "properties": {
    "gn:admin1_code":"30.0",
    "gn:asciiname":"Dajiangdi",
    "gn:country_code":"CN",
    "gn:dem":138,
    "gn:feature_class":"P",
    "gn:feature_code":"PPL",
    "gn:name":"Dajiangdi",
    "gn:population":0,
    "gn:timezone":"Asia/Shanghai",
    "iso:country":"CN",
    "name:zho_x_preferred":[
        "\u5927\u964d\u5e95"
    ],
    "wof:name":"Dajiangdi",
    "wof:placetype":"locality"
},
  "geometry": {"coordinates":[111.90113999999998,23.19795],"type":"Point"}
}