{
  "type": "Feature",
  "properties": {
    "gn:admin1_code":"29.0",
    "gn:asciiname":"Datianyakou",
    "gn:country_code":"CN",
    "gn:dem":1676,
    "gn:feature_class":"P",
    "gn:feature_code":"PPL",
    "gn:name":"Datianyakou",
    "gn:population":0,
    "gn:timezone":"Asia/Shanghai",
    "iso:country":"CN",
    "name:zho_x_preferred":[
        "\u5927\u7530\u4e2b\u53e3"
    ],
    "wof:name":"Datianyakou",
    "wof:placetype":"locality"
},
  "geometry": {"coordinates":[99.45650000000001,24.3442],"type":"Point"}
}