{
  "type": "Feature",
  "properties": {
    "gn:admin1_code":"30.0",
    "gn:asciiname":"Xiwa",
    "gn:country_code":"CN",
    "gn:dem":91,
    "gn:feature_class":"P",
    "gn:feature_code":"PPL",
    "gn:name":"Xiwa",
    "gn:population":0,
    "gn:timezone":"Asia/Urumqi",
    "iso:country":"CN",
    "name:zho_x_preferred":[
        "\u897f\u6316"
    ],
    "wof:name":"Xiwa",
    "wof:placetype":"locality"
},
  "geometry": {"coordinates":[109.91587,20.5801],"type":"Point"}
}