{
  "type": "Feature",
  "properties": {
    "gn:admin1_code":"2.0",
    "gn:asciiname":"Toutang",
    "gn:country_code":"CN",
    "gn:dem":40,
    "gn:feature_class":"P",
    "gn:feature_code":"PPL",
    "gn:name":"Toutang",
    "gn:population":0,
    "gn:timezone":"Asia/Shanghai",
    "iso:country":"CN",
    "name:zho_x_preferred":[
        "\u5934\u5858"
    ],
    "wof:name":"Toutang",
    "wof:placetype":"locality"
},
  "geometry": {"coordinates":[121.07407000000001,28.95155],"type":"Point"}
}