{
  "type": "Feature",
  "properties": {
    "gn:admin1_code":"24.0",
    "gn:asciiname":"Xiayangluo",
    "gn:country_code":"CN",
    "gn:dem":1255,
    "gn:feature_class":"P",
    "gn:feature_code":"PPL",
    "gn:name":"Xiayangluo",
    "gn:population":0,
    "gn:timezone":"Asia/Shanghai",
    "iso:country":"CN",
    "name:zho_x_preferred":[
        "\u4e0b\u7f8a\u843d"
    ],
    "wof:name":"Xiayangluo",
    "wof:placetype":"locality"
},
  "geometry": {"coordinates":[113.62384,40.13414],"type":"Point"}
}