{
  "type": "Feature",
  "properties": {
    "gn:admin1_code":"7.0",
    "gn:asciiname":"Xiyuan",
    "gn:country_code":"CN",
    "gn:dem":158,
    "gn:feature_class":"P",
    "gn:feature_code":"PPL",
    "gn:name":"Xiyuan",
    "gn:population":0,
    "gn:timezone":"Asia/Shanghai",
    "iso:country":"CN",
    "name:deu_x_preferred":[
        "Xiyuan"
    ],
    "name:zho_x_preferred":[
        "\u6eaa\u6e90"
    ],
    "wof:name":"Xiyuan",
    "wof:placetype":"locality"
},
  "geometry": {"coordinates":[118.08506,27.2794],"type":"Point"}
}