{
  "type": "Feature",
  "properties": {
    "gn:admin1_code":"8.0",
    "gn:asciiname":"Fengmishan Liudui",
    "gn:country_code":"CN",
    "gn:dem":106,
    "gn:feature_class":"P",
    "gn:feature_code":"PPLF",
    "gn:name":"Fengmishan Liudui",
    "gn:population":0,
    "gn:timezone":"Asia/Shanghai",
    "iso:country":"CN",
    "name:zho_x_preferred":[
        "\u8702\u871c\u5c71\u516d\u961f"
    ],
    "wof:name":"Fengmishan Liudui",
    "wof:placetype":"locality"
},
  "geometry": {"coordinates":[132.1103,45.3969],"type":"Point"}
}