{
  "type": "Feature",
  "properties": {
    "gn:admin1_code":"26.0",
    "gn:asciiname":"Manpo",
    "gn:country_code":"CN",
    "gn:dem":885,
    "gn:feature_class":"P",
    "gn:feature_code":"PPL",
    "gn:name":"Manpo",
    "gn:population":0,
    "gn:timezone":"Asia/Shanghai",
    "iso:country":"CN",
    "name:zho_x_preferred":[
        "\u5881\u5761"
    ],
    "wof:name":"Manpo",
    "wof:placetype":"locality"
},
  "geometry": {"coordinates":[110.66705,33.15782],"type":"Point"}
}