{
  "type": "Feature",
  "properties": {
    "gn:admin1_code":"32.0",
    "gn:asciiname":"Anshan",
    "gn:country_code":"CN",
    "gn:dem":644,
    "gn:feature_class":"P",
    "gn:feature_code":"PPL",
    "gn:name":"Anshan",
    "gn:population":0,
    "gn:timezone":"Asia/Shanghai",
    "iso:country":"CN",
    "name:zho_x_preferred":[
        "\u978d\u5c71"
    ],
    "wof:name":"Anshan",
    "wof:placetype":"locality"
},
  "geometry": {"coordinates":[107.411,31.5602],"type":"Point"}
}