{
  "type": "Feature",
  "properties": {
    "gn:admin1_code":"19.0",
    "gn:asciiname":"Jingquancun",
    "gn:country_code":"CN",
    "gn:dem":25,
    "gn:feature_class":"P",
    "gn:feature_code":"PPL",
    "gn:name":"Jingquancun",
    "gn:population":0,
    "gn:timezone":"Asia/Shanghai",
    "iso:country":"CN",
    "name:zho_x_preferred":[
        "\u4e95\u6cc9\u6751"
    ],
    "wof:name":"Jingquancun",
    "wof:placetype":"locality"
},
  "geometry": {"coordinates":[123.26221,41.39331],"type":"Point"}
}