{
  "type": "Feature",
  "properties": {
    "gn:admin1_code":"32.0",
    "gn:asciiname":"Guji Buzi",
    "gn:country_code":"CN",
    "gn:dem":2179,
    "gn:feature_class":"P",
    "gn:feature_code":"PPL",
    "gn:name":"Guji Buzi",
    "gn:population":0,
    "gn:timezone":"Asia/Shanghai",
    "iso:country":"CN",
    "name:zho_x_preferred":[
        "\u53e4\u57fa\u5821\u5b50"
    ],
    "wof:name":"Guji Buzi",
    "wof:placetype":"locality"
},
  "geometry": {"coordinates":[102.036,29.0262],"type":"Point"}
}