{
  "type": "Feature",
  "properties": {
    "gn:admin1_code":"2.0",
    "gn:asciiname":"Zhongdai",
    "gn:country_code":"CN",
    "gn:dem":8,
    "gn:feature_class":"P",
    "gn:feature_code":"PPL",
    "gn:name":"Zhongdai",
    "gn:population":0,
    "gn:timezone":"Asia/Shanghai",
    "iso:country":"CN",
    "name:und_x_variant":[
        "Chung-tai-chen",
        "Chung-tai",
        "Zhongdai",
        "\u949f\u57ed",
        "Zhongdaizhen",
        "\u949f\u57ed\u9547"
    ],
    "wof:name":"Zhongdai",
    "wof:placetype":"locality"
},
  "geometry": {"coordinates":[120.99363,30.77019],"type":"Point"}
}