{
  "type": "Feature",
  "properties": {
    "gn:admin1_code":"9",
    "gn:asciiname":"Loumatou",
    "gn:country_code":"CN",
    "gn:dem":59,
    "gn:feature_class":"P",
    "gn:feature_code":"PPL",
    "gn:name":"Loumatou",
    "gn:population":0,
    "gn:timezone":"Asia/Shanghai",
    "iso:country":"CN",
    "name:zho_x_preferred":[
        "\u5a04\u9a6c\u5934"
    ],
    "wof:name":"Loumatou",
    "wof:placetype":"locality"
},
  "geometry": {"coordinates":[114.956,34.4068],"type":"Point"}
}