{
  "type": "Feature",
  "properties": {
    "gn:admin1_code":"10.0",
    "gn:asciiname":"Shijiagou",
    "gn:country_code":"CN",
    "gn:dem":1073,
    "gn:feature_class":"P",
    "gn:feature_code":"PPL",
    "gn:name":"Shijiagou",
    "gn:population":0,
    "gn:timezone":"Asia/Shanghai",
    "iso:country":"CN",
    "name:zho_x_preferred":[
        "\u53f2\u5bb6\u6c9f"
    ],
    "wof:name":"Shijiagou",
    "wof:placetype":"locality"
},
  "geometry": {"coordinates":[114.81641,40.30487],"type":"Point"}
}