{
  "type": "Feature",
  "properties": {
    "gn:admin1_code":"5.0",
    "gn:asciiname":"Dongshantun",
    "gn:country_code":"CN",
    "gn:dem":208,
    "gn:feature_class":"P",
    "gn:feature_code":"PPL",
    "gn:name":"Dongshantun",
    "gn:population":0,
    "gn:timezone":"Asia/Shanghai",
    "iso:country":"CN",
    "name:und_x_variant":[
        "\u4e1c\u5c71\u5c6f"
    ],
    "wof:name":"Dongshantun",
    "wof:placetype":"locality"
},
  "geometry": {"coordinates":[129.56254999999999,42.84152],"type":"Point"}
}