{
  "type": "Feature",
  "properties": {
    "gn:admin1_code":"1.0",
    "gn:asciiname":"Daduncun",
    "gn:country_code":"CN",
    "gn:dem":28,
    "gn:feature_class":"P",
    "gn:feature_code":"PPL",
    "gn:name":"Daduncun",
    "gn:population":0,
    "gn:timezone":"Asia/Shanghai",
    "iso:country":"CN",
    "name:zho_x_preferred":[
        "\u5927\u58a9\u6751"
    ],
    "wof:name":"Daduncun",
    "wof:placetype":"locality"
},
  "geometry": {"coordinates":[116.13032,32.12611],"type":"Point"}
}