{
  "type": "Feature",
  "properties": {
    "gn:admin1_code":"18",
    "gn:asciiname":"Yangfangzi",
    "gn:country_code":"CN",
    "gn:dem":1258,
    "gn:feature_class":"P",
    "gn:feature_code":"PPL",
    "gn:name":"Yangfangzi",
    "gn:population":0,
    "gn:timezone":"Asia/Shanghai",
    "iso:country":"CN",
    "name:zho_x_preferred":[
        "\u6d0b\u623f\u5b50"
    ],
    "wof:name":"Yangfangzi",
    "wof:placetype":"locality"
},
  "geometry": {"coordinates":[106.79600000000001,28.2697],"type":"Point"}
}