{
  "type": "Feature",
  "properties": {
    "gn:admin1_code":"1.0",
    "gn:asciiname":"Longgucun",
    "gn:country_code":"CN",
    "gn:dem":109,
    "gn:feature_class":"P",
    "gn:feature_code":"PPL",
    "gn:name":"Longgucun",
    "gn:population":0,
    "gn:timezone":"Asia/Shanghai",
    "iso:country":"CN",
    "name:zho_x_preferred":[
        "\u9f99\u9aa8\u6751"
    ],
    "wof:name":"Longgucun",
    "wof:placetype":"locality"
},
  "geometry": {"coordinates":[116.76702,31.22428],"type":"Point"}
}