{
  "type": "Feature",
  "properties": {
    "gn:admin1_code":"11",
    "gn:asciiname":"Xiangcao",
    "gn:country_code":"CN",
    "gn:dem":964,
    "gn:feature_class":"P",
    "gn:feature_code":"PPL",
    "gn:name":"Xiangcao",
    "gn:population":0,
    "gn:timezone":"Asia/Shanghai",
    "iso:country":"CN",
    "name:zho_x_preferred":[
        "\u9999\u8349"
    ],
    "wof:name":"Xiangcao",
    "wof:placetype":"locality"
},
  "geometry": {"coordinates":[111.89811,25.1858],"type":"Point"}
}