{
  "type": "Feature",
  "properties": {
    "gn:admin1_code":"29.0",
    "gn:asciiname":"Waipula",
    "gn:country_code":"CN",
    "gn:dem":1488,
    "gn:feature_class":"P",
    "gn:feature_code":"PPL",
    "gn:name":"Waipula",
    "gn:population":0,
    "gn:timezone":"Asia/Shanghai",
    "iso:country":"CN",
    "name:zho_x_preferred":[
        "\u5916\u666e\u62c9"
    ],
    "wof:name":"Waipula",
    "wof:placetype":"locality"
},
  "geometry": {"coordinates":[101.47,25.9107],"type":"Point"}
}