{
  "type": "Feature",
  "properties": {
    "gn:admin1_code":"3.0",
    "gn:asciiname":"Jiziling",
    "gn:country_code":"CN",
    "gn:dem":135,
    "gn:feature_class":"P",
    "gn:feature_code":"PPL",
    "gn:name":"Jiziling",
    "gn:population":0,
    "gn:timezone":"Asia/Shanghai",
    "iso:country":"CN",
    "name:und_x_variant":[
        "\u5409\u5b50\u5cad"
    ],
    "wof:name":"Jiziling",
    "wof:placetype":"locality"
},
  "geometry": {"coordinates":[114.24330999999999,28.13821],"type":"Point"}
}