{
  "type": "Feature",
  "properties": {
    "gn:admin1_code":"2.0",
    "gn:asciiname":"Wangjiaran",
    "gn:country_code":"CN",
    "gn:dem":389,
    "gn:feature_class":"P",
    "gn:feature_code":"PPL",
    "gn:name":"Wangjiaran",
    "gn:population":0,
    "gn:timezone":"Asia/Shanghai",
    "iso:country":"CN",
    "name:zho_x_preferred":[
        "\u738b\u5bb6\u67d3"
    ],
    "wof:name":"Wangjiaran",
    "wof:placetype":"locality"
},
  "geometry": {"coordinates":[121.01045999999999,29.91344],"type":"Point"}
}