{
  "type": "Feature",
  "properties": {
    "gn:admin1_code":"2",
    "gn:asciiname":"Huangcun",
    "gn:country_code":"CN",
    "gn:dem":1077,
    "gn:feature_class":"P",
    "gn:feature_code":"PPL",
    "gn:name":"Huangcun",
    "gn:population":0,
    "gn:timezone":"Asia/Shanghai",
    "iso:country":"CN",
    "name:und_x_variant":[
        "\u8352\u6751",
        "Huangcun"
    ],
    "wof:name":"Huangcun",
    "wof:placetype":"locality"
},
  "geometry": {"coordinates":[119.23184999999999,27.92513],"type":"Point"}
}