{
  "type": "Feature",
  "properties": {
    "gn:admin1_code":"9.0",
    "gn:asciiname":"Dongchang",
    "gn:country_code":"CN",
    "gn:dem":88,
    "gn:feature_class":"P",
    "gn:feature_code":"PPL",
    "gn:name":"Dongchang",
    "gn:population":0,
    "gn:timezone":"Asia/Shanghai",
    "iso:country":"CN",
    "name:ceb_x_preferred":[
        "Dongchang"
    ],
    "name:deu_x_preferred":[
        "Dongchang"
    ],
    "name:zho_x_preferred":[
        "\u4e1c\u5e38"
    ],
    "wof:name":"Dongchang",
    "wof:placetype":"locality"
},
  "geometry": {"coordinates":[113.47177000000001,35.16211],"type":"Point"}
}