{
  "type": "Feature",
  "properties": {
    "gn:admin1_code":"29.0",
    "gn:asciiname":"Haikoucun",
    "gn:country_code":"CN",
    "gn:dem":1009,
    "gn:feature_class":"P",
    "gn:feature_code":"PPL",
    "gn:name":"Haikoucun",
    "gn:population":0,
    "gn:timezone":"Asia/Shanghai",
    "iso:country":"CN",
    "name:zho_x_preferred":[
        "\u6d77\u53e3\u6751"
    ],
    "wof:name":"Haikoucun",
    "wof:placetype":"locality"
},
  "geometry": {"coordinates":[102.926,27.1978],"type":"Point"}
}