{
  "type": "Feature",
  "properties": {
    "gn:admin1_code":"30.0",
    "gn:asciiname":"Xintingxia",
    "gn:country_code":"CN",
    "gn:dem":100,
    "gn:feature_class":"P",
    "gn:feature_code":"PPL",
    "gn:name":"Xintingxia",
    "gn:population":0,
    "gn:timezone":"Asia/Shanghai",
    "iso:country":"CN",
    "name:zho_x_preferred":[
        "\u65b0\u5385\u4e0b"
    ],
    "wof:name":"Xintingxia",
    "wof:placetype":"locality"
},
  "geometry": {"coordinates":[113.81999999999999,24.25083],"type":"Point"}
}