{
  "type": "Feature",
  "properties": {
    "gn:admin1_code":"30",
    "gn:asciiname":"Mingjiao",
    "gn:country_code":"CN",
    "gn:dem":20,
    "gn:feature_class":"P",
    "gn:feature_code":"PPL",
    "gn:name":"Mingjiao",
    "gn:population":0,
    "gn:timezone":"Asia/Urumqi",
    "iso:country":"CN",
    "name:zho_x_preferred":[
        "\u540d\u6559"
    ],
    "wof:name":"Mingjiao",
    "wof:placetype":"locality"
},
  "geometry": {"coordinates":[110.55265,21.74521],"type":"Point"}
}