{
  "type": "Feature",
  "properties": {
    "gn:admin1_code":"32.0",
    "gn:asciiname":"Zhongxiang",
    "gn:country_code":"CN",
    "gn:dem":412,
    "gn:feature_class":"P",
    "gn:feature_code":"PPL",
    "gn:name":"Zhongxiang",
    "gn:population":0,
    "gn:timezone":"Asia/Shanghai",
    "iso:country":"CN",
    "name:und_x_variant":[
        "Chung-hsiang-chen",
        "Zhongxiangzhen",
        "Zhongxiangchang",
        "Zhongxiang"
    ],
    "name:zho_x_preferred":[
        "\u9221\u7965"
    ],
    "wof:name":"Zhongxiang",
    "wof:placetype":"locality"
},
  "geometry": {"coordinates":[104.13706000000001,29.82587],"type":"Point"}
}