{
  "type": "Feature",
  "properties": {
    "gn:admin1_code":"32.0",
    "gn:asciiname":"Zhongxiang",
    "gn:country_code":"CN",
    "gn:dem":412,
    "gn:feature_class":"P",
    "gn:feature_code":"PPL",
    "gn:name":"Zhongxiang",
    "gn:population":0,
    "gn:timezone":"Asia/Shanghai",
    "iso:country":"CN",
    "name:ceb_x_preferred":[
        "Zhongxiang"
    ],
    "name:ces_x_preferred":[
        "\u010cung-siang"
    ],
    "name:deu_x_preferred":[
        "Zhongxiang"
    ],
    "name:epo_x_preferred":[
        "Zhongxiang"
    ],
    "name:fra_x_preferred":[
        "Zhongxiang"
    ],
    "name:ita_x_preferred":[
        "Zhongxiang"
    ],
    "name:jpn_x_preferred":[
        "\u937e\u7965\u5e02"
    ],
    "name:kik_x_preferred":[
        "Zhongxiang"
    ],
    "name:kor_x_preferred":[
        "\uc911\uc0f9\uc2dc"
    ],
    "name:mlg_x_preferred":[
        "Zhongxiang"
    ],
    "name:nor_x_preferred":[
        "Zhongxiang"
    ],
    "name:pam_x_preferred":[
        "Zhongxiang"
    ],
    "name:pol_x_preferred":[
        "Zhongxiang"
    ],
    "name:swe_x_preferred":[
        "Zhongxiang"
    ],
    "name:und_x_variant":[
        "Chung-hsiang-chen",
        "Zhongxiangzhen",
        "Zhongxiangchang"
    ],
    "name:vie_x_preferred":[
        "Chung T\u01b0\u1eddng"
    ],
    "name:zho_x_preferred":[
        "\u9221\u7965"
    ],
    "name:zho_x_variant":[
        "\u949f\u7965\u5e02"
    ],
    "wof:name":"Zhongxiang",
    "wof:placetype":"locality"
},
  "geometry": {"coordinates":[104.13706000000001,29.82587],"type":"Point"}
}