{
  "type": "Feature",
  "properties": {
    "gn:admin1_code":"19.0",
    "gn:asciiname":"Fulouxigou",
    "gn:country_code":"CN",
    "gn:dem":262,
    "gn:feature_class":"P",
    "gn:feature_code":"PPL",
    "gn:name":"Fulouxigou",
    "gn:population":0,
    "gn:timezone":"Asia/Shanghai",
    "iso:country":"CN",
    "name:und_x_variant":[
        "\u5bcc\u697c\u897f\u6c9f"
    ],
    "name:zho_x_preferred":[
        "\u5bcc\u697c\u897f\u6c9f"
    ],
    "wof:name":"Fulouxigou",
    "wof:placetype":"locality"
},
  "geometry": {"coordinates":[124.25414000000001,41.42683],"type":"Point"}
}