{
  "type": "Feature",
  "properties": {
    "gn:admin1_code":"26.0",
    "gn:asciiname":"Mingyueguancun",
    "gn:country_code":"CN",
    "gn:dem":861,
    "gn:feature_class":"P",
    "gn:feature_code":"PPL",
    "gn:name":"Mingyueguancun",
    "gn:population":0,
    "gn:timezone":"Asia/Shanghai",
    "iso:country":"CN",
    "name:und_x_variant":[
        "\u660e\u6708\u89c2\u6751"
    ],
    "wof:name":"Mingyueguancun",
    "wof:placetype":"locality"
},
  "geometry": {"coordinates":[108.02415999999999,32.97079],"type":"Point"}
}