{
  "type": "Feature",
  "properties": {
    "gn:admin1_code":"7.0",
    "gn:asciiname":"Jiulin",
    "gn:country_code":"CN",
    "gn:dem":9,
    "gn:feature_class":"P",
    "gn:feature_code":"PPL",
    "gn:name":"Jiulin",
    "gn:population":0,
    "gn:timezone":"Asia/Shanghai",
    "iso:country":"CN",
    "name:zho_x_preferred":[
        "\u9e20\u6797"
    ],
    "wof:name":"Jiulin",
    "wof:placetype":"locality"
},
  "geometry": {"coordinates":[118.86918,25.23446],"type":"Point"}
}