{
  "type": "Feature",
  "properties": {
    "gn:admin1_code":"12.0",
    "gn:asciiname":"Tujianao",
    "gn:country_code":"CN",
    "gn:dem":144,
    "gn:feature_class":"P",
    "gn:feature_code":"PPL",
    "gn:name":"Tujianao",
    "gn:population":0,
    "gn:timezone":"Asia/Shanghai",
    "iso:country":"CN",
    "name:zho_x_preferred":[
        "Tujianao"
    ],
    "name:zho_x_variant":[
        "\u6d82\u5bb6\u57b4"
    ],
    "wof:name":"Tujianao",
    "wof:placetype":"locality"
},
  "geometry": {"coordinates":[111.81955000000001,30.68605],"type":"Point"}
}