{
  "type": "Feature",
  "properties": {
    "gn:admin1_code":"1.0",
    "gn:asciiname":"Changlucun",
    "gn:country_code":"CN",
    "gn:dem":149,
    "gn:feature_class":"P",
    "gn:feature_code":"PPL",
    "gn:name":"Changlucun",
    "gn:population":0,
    "gn:timezone":"Asia/Shanghai",
    "iso:country":"CN",
    "name:zho_x_preferred":[
        "\u957f\u82a6\u6751"
    ],
    "wof:name":"Changlucun",
    "wof:placetype":"locality"
},
  "geometry": {"coordinates":[117.97945,30.25146],"type":"Point"}
}