{
  "type": "Feature",
  "properties": {
    "gn:admin1_code":"25",
    "gn:asciiname":"Linquanyu",
    "gn:country_code":"CN",
    "gn:dem":126,
    "gn:feature_class":"P",
    "gn:feature_code":"PPL",
    "gn:name":"Linquanyu",
    "gn:population":0,
    "gn:timezone":"Asia/Shanghai",
    "iso:country":"CN",
    "name:zho_x_preferred":[
        "\u6797\u6cc9\u5cea"
    ],
    "wof:name":"Linquanyu",
    "wof:placetype":"locality"
},
  "geometry": {"coordinates":[118.904,36.4831],"type":"Point"}
}