{
  "type": "Feature",
  "properties": {
    "gn:admin1_code":"11.0",
    "gn:asciiname":"Guoyangjia",
    "gn:country_code":"CN",
    "gn:dem":38,
    "gn:feature_class":"P",
    "gn:feature_code":"PPL",
    "gn:name":"Guoyangjia",
    "gn:population":0,
    "gn:timezone":"Asia/Shanghai",
    "iso:country":"CN",
    "name:zho_x_preferred":[
        "Guoyangjia"
    ],
    "name:zho_x_variant":[
        "\u8662\u6768\u5bb6"
    ],
    "wof:name":"Guoyangjia",
    "wof:placetype":"locality"
},
  "geometry": {"coordinates":[111.62465,29.02777],"type":"Point"}
}