{
  "type": "Feature",
  "properties": {
    "gn:admin1_code":"19.0",
    "gn:asciiname":"Shanwanzi",
    "gn:country_code":"CN",
    "gn:dem":574,
    "gn:feature_class":"P",
    "gn:feature_code":"PPL",
    "gn:name":"Shanwanzi",
    "gn:population":0,
    "gn:timezone":"Asia/Shanghai",
    "iso:country":"CN",
    "name:und_x_variant":[
        "\u5c71\u6e7e\u5b50"
    ],
    "name:zho_x_preferred":[
        "\u5c71\u6e7e\u5b50"
    ],
    "wof:name":"Shanwanzi",
    "wof:placetype":"locality"
},
  "geometry": {"coordinates":[119.61799999999999,40.5094],"type":"Point"}
}