{
  "type": "Feature",
  "properties": {
    "gn:admin1_code":"11",
    "gn:asciiname":"Leigongta",
    "gn:country_code":"CN",
    "gn:dem":65,
    "gn:feature_class":"P",
    "gn:feature_code":"PPLA4",
    "gn:name":"Leigongta",
    "gn:population":0,
    "gn:timezone":"Asia/Shanghai",
    "iso:country":"CN",
    "name:und_x_variant":[
        "\u96f7\u516c\u5854",
        "Leigongta Zhen",
        "\u96f7\u516c\u5854\u9547"
    ],
    "wof:name":"Leigongta",
    "wof:placetype":"locality"
},
  "geometry": {"coordinates":[111.76927000000001,29.79269],"type":"Point"}
}