{
  "type": "Feature",
  "properties": {
    "gn:admin1_code":"03",
    "gn:asciiname":"Dongqiao",
    "gn:cc2":"CN",
    "gn:country_code":"CN",
    "gn:dem":117,
    "gn:feature_class":"P",
    "gn:feature_code":"PPL",
    "gn:name":"Dongqiao",
    "gn:population":0,
    "gn:timezone":"Asia/Shanghai",
    "iso:country":"CN",
    "name:und_x_variant":[
        "Tung-ch\u2019iao",
        "Dongqiao"
    ],
    "wof:name":"Dongqiao",
    "wof:placetype":"locality"
},
  "geometry": {"coordinates":[113.68333,27.45],"type":"Point"}
}