{
  "type": "Feature",
  "properties": {
    "gn:admin1_code":"32.0",
    "gn:asciiname":"Gaqie",
    "gn:country_code":"CN",
    "gn:dem":2570,
    "gn:feature_class":"P",
    "gn:feature_code":"PPL",
    "gn:name":"Gaqie",
    "gn:population":0,
    "gn:timezone":"Asia/Shanghai",
    "iso:country":"CN",
    "name:zho_x_preferred":[
        "\u560e\u4e14"
    ],
    "wof:name":"Gaqie",
    "wof:placetype":"locality"
},
  "geometry": {"coordinates":[102.863,27.6368],"type":"Point"}
}