{
  "type": "Feature",
  "properties": {
    "gn:admin1_code":"15.0",
    "gn:asciiname":"Liangshuixia",
    "gn:country_code":"CN",
    "gn:dem":1461,
    "gn:feature_class":"P",
    "gn:feature_code":"PPL",
    "gn:name":"Liangshuixia",
    "gn:population":0,
    "gn:timezone":"Asia/Shanghai",
    "iso:country":"CN",
    "name:und_x_variant":[
        "\u51c9\u6c34\u5ce1"
    ],
    "wof:name":"Liangshuixia",
    "wof:placetype":"locality"
},
  "geometry": {"coordinates":[105.64885,33.67257],"type":"Point"}
}