{
  "type": "Feature",
  "properties": {
    "gn:admin1_code":"21.0",
    "gn:asciiname":"Yuanyaoxian",
    "gn:country_code":"CN",
    "gn:dem":1735,
    "gn:feature_class":"P",
    "gn:feature_code":"PPL",
    "gn:name":"Yuanyaoxian",
    "gn:population":0,
    "gn:timezone":"Asia/Shanghai",
    "iso:country":"CN",
    "name:und_x_variant":[
        "\u8881\u5d3e\u5c98"
    ],
    "name:zho_x_preferred":[
        "\u8881\u5d3e\u5c98"
    ],
    "wof:name":"Yuanyaoxian",
    "wof:placetype":"locality"
},
  "geometry": {"coordinates":[106.54181,36.8063],"type":"Point"}
}