{
  "type": "Feature",
  "properties": {
    "gn:admin1_code":"30",
    "gn:asciiname":"Laochating",
    "gn:country_code":"CN",
    "gn:dem":462,
    "gn:feature_class":"P",
    "gn:feature_code":"PPL",
    "gn:name":"Laochating",
    "gn:population":0,
    "gn:timezone":"Asia/Shanghai",
    "iso:country":"CN",
    "name:zho_x_preferred":[
        "\u8001\u8336\u4ead"
    ],
    "wof:name":"Laochating",
    "wof:placetype":"locality"
},
  "geometry": {"coordinates":[115.60391,24.56205],"type":"Point"}
}