{
  "type": "Feature",
  "properties": {
    "gn:admin1_code":"4.0",
    "gn:asciiname":"Daizhuang",
    "gn:country_code":"CN",
    "gn:dem":6,
    "gn:feature_class":"P",
    "gn:feature_code":"PPL",
    "gn:name":"Daizhuang",
    "gn:population":0,
    "gn:timezone":"Asia/Shanghai",
    "iso:country":"CN",
    "name:zho_x_preferred":[
        "Daizhuang"
    ],
    "name:zho_x_variant":[
        "\u6234\u5e84"
    ],
    "wof:name":"Daizhuang",
    "wof:placetype":"locality"
},
  "geometry": {"coordinates":[119.34672,33.1572],"type":"Point"}
}