{
  "type": "Feature",
  "properties": {
    "gn:admin1_code":"11.0",
    "gn:asciiname":"Laotangwan",
    "gn:country_code":"CN",
    "gn:dem":103,
    "gn:feature_class":"P",
    "gn:feature_code":"PPL",
    "gn:name":"Laotangwan",
    "gn:population":0,
    "gn:timezone":"Asia/Shanghai",
    "iso:country":"CN",
    "name:zho_x_preferred":[
        "\u8001\u5858\u6e7e"
    ],
    "wof:name":"Laotangwan",
    "wof:placetype":"locality"
},
  "geometry": {"coordinates":[112.38017000000001,28.14764000000001],"type":"Point"}
}