{
  "type": "Feature",
  "properties": {
    "gn:admin1_code":"03",
    "gn:asciiname":"Fufang",
    "gn:country_code":"CN",
    "gn:dem":149,
    "gn:feature_class":"P",
    "gn:feature_code":"PPLA4",
    "gn:name":"Fufang",
    "gn:population":0,
    "gn:timezone":"Asia/Shanghai",
    "iso:country":"CN",
    "name:und_x_variant":[
        "Fu-fang-hs\u00fc",
        "Fu-chia",
        "Fufang",
        "\u5085\u574a",
        "Fufang Xiang",
        "\u5085\u574a\u4e61"
    ],
    "wof:name":"Fufang",
    "wof:placetype":"locality"
},
  "geometry": {"coordinates":[116.59414,26.97277],"type":"Point"}
}