{
  "type": "Feature",
  "properties": {
    "gn:admin1_code":"19.0",
    "gn:asciiname":"Dongbeigou",
    "gn:country_code":"CN",
    "gn:dem":131,
    "gn:feature_class":"P",
    "gn:feature_code":"PPL",
    "gn:name":"Dongbeigou",
    "gn:population":0,
    "gn:timezone":"Asia/Shanghai",
    "iso:country":"CN",
    "name:und_x_variant":[
        "\u4e1c\u5317\u6c9f"
    ],
    "wof:name":"Dongbeigou",
    "wof:placetype":"locality"
},
  "geometry": {"coordinates":[122.152,40.0053],"type":"Point"}
}