{
  "type": "Feature",
  "properties": {
    "gn:admin1_code":"14.0",
    "gn:asciiname":"Musuo",
    "gn:country_code":"CN",
    "gn:dem":4416,
    "gn:feature_class":"P",
    "gn:feature_code":"PPL",
    "gn:name":"Musuo",
    "gn:population":0,
    "gn:timezone":"Asia/Urumqi",
    "iso:country":"CN",
    "name:zho_x_preferred":[
        "\u6728\u7d22"
    ],
    "wof:name":"Musuo",
    "wof:placetype":"locality"
},
  "geometry": {"coordinates":[92.91898,31.81321],"type":"Point"}
}