{
  "type": "Feature",
  "properties": {
    "gn:admin1_code":"04",
    "gn:asciiname":"Mengzhaicun",
    "gn:country_code":"CN",
    "gn:dem":41,
    "gn:feature_class":"P",
    "gn:feature_code":"PPL",
    "gn:name":"Mengzhaicun",
    "gn:population":0,
    "gn:timezone":"Asia/Shanghai",
    "iso:country":"CN",
    "name:und_x_variant":[
        "Meng-chai",
        "Mengzhai",
        "Mengzhaicun"
    ],
    "name:zho_x_preferred":[
        "\u5b5f\u5be8\u6751"
    ],
    "wof:name":"Mengzhaicun",
    "wof:placetype":"locality"
},
  "geometry": {"coordinates":[116.85669,34.6297],"type":"Point"}
}