{
  "type": "Feature",
  "properties": {
    "gn:admin1_code":"7.0",
    "gn:asciiname":"Yushui",
    "gn:country_code":"CN",
    "gn:dem":602,
    "gn:feature_class":"P",
    "gn:feature_code":"PPL",
    "gn:name":"Yushui",
    "gn:population":0,
    "gn:timezone":"Asia/Shanghai",
    "iso:country":"CN",
    "name:zho_x_preferred":[
        "\u7389\u6c34"
    ],
    "wof:name":"Yushui",
    "wof:placetype":"locality"
},
  "geometry": {"coordinates":[118.67653,25.96401],"type":"Point"}
}