{
  "type": "Feature",
  "properties": {
    "gn:admin1_code":"21.0",
    "gn:asciiname":"Humaqi",
    "gn:country_code":"CN",
    "gn:dem":1491,
    "gn:feature_class":"P",
    "gn:feature_code":"PPL",
    "gn:name":"Humaqi",
    "gn:population":0,
    "gn:timezone":"Asia/Shanghai",
    "iso:country":"CN",
    "name:und_x_variant":[
        "\u80e1\u9ebb\u65d7"
    ],
    "name:zho_x_preferred":[
        "\u80e1\u9ebb\u65d7"
    ],
    "wof:name":"Humaqi",
    "wof:placetype":"locality"
},
  "geometry": {"coordinates":[106.05165,36.81969],"type":"Point"}
}