{
  "type": "Feature",
  "properties": {
    "gn:admin1_code":"12.0",
    "gn:asciiname":"Xiaoduchuan",
    "gn:country_code":"CN",
    "gn:dem":427,
    "gn:feature_class":"P",
    "gn:feature_code":"PPLA3",
    "gn:name":"Xiaoduchuan",
    "gn:population":0,
    "gn:timezone":"Asia/Shanghai",
    "iso:country":"CN",
    "name:und_x_variant":[
        "Xiaoduchuan Jiedao"
    ],
    "name:zho_x_preferred":[
        "\u5c0f\u6e21\u8239"
    ],
    "name:zho_x_variant":[
        "\u5c0f\u6e21\u8239\u8857\u9053"
    ],
    "wof:name":"Xiaoduchuan",
    "wof:placetype":"locality"
},
  "geometry": {"coordinates":[109.47615999999999,30.29113],"type":"Point"}
}