{
  "type": "Feature",
  "properties": {
    "gn:admin1_code":"15.0",
    "gn:asciiname":"Jiumuyuan",
    "gn:country_code":"CN",
    "gn:dem":1568,
    "gn:feature_class":"P",
    "gn:feature_code":"PPL",
    "gn:name":"Jiumuyuan",
    "gn:population":0,
    "gn:timezone":"Asia/Shanghai",
    "iso:country":"CN",
    "name:zho_x_preferred":[
        "\u4e5d\u4ea9\u56ed"
    ],
    "wof:name":"Jiumuyuan",
    "wof:placetype":"locality"
},
  "geometry": {"coordinates":[106.09999999999999,34.4408],"type":"Point"}
}