{
  "type": "Feature",
  "properties": {
    "gn:admin1_code":"29.0",
    "gn:asciiname":"Mangang",
    "gn:country_code":"CN",
    "gn:dem":1203,
    "gn:feature_class":"P",
    "gn:feature_code":"PPL",
    "gn:name":"Mangang",
    "gn:population":0,
    "gn:timezone":"Asia/Shanghai",
    "iso:country":"CN",
    "name:zho_x_preferred":[
        "\u66fc\u5c97"
    ],
    "wof:name":"Mangang",
    "wof:placetype":"locality"
},
  "geometry": {"coordinates":[100.80800000000001,24.5513],"type":"Point"}
}