{
  "type": "Feature",
  "properties": {
    "gn:admin1_code":"6.0",
    "gn:asciiname":"Qumuri",
    "gn:country_code":"CN",
    "gn:dem":2748,
    "gn:feature_class":"P",
    "gn:feature_code":"PPL",
    "gn:name":"Qumuri",
    "gn:population":0,
    "gn:timezone":"Asia/Shanghai",
    "iso:country":"CN",
    "name:und_x_variant":[
        "\u66f2\u6728\u65e5"
    ],
    "wof:name":"Qumuri",
    "wof:placetype":"locality"
},
  "geometry": {"coordinates":[102.49531,35.71256],"type":"Point"}
}