{
  "type": "Feature",
  "properties": {
    "gn:admin1_code":"30.0",
    "gn:asciiname":"Longcheng",
    "gn:country_code":"CN",
    "gn:dem":45,
    "gn:feature_class":"P",
    "gn:feature_code":"PPLA4",
    "gn:name":"Longcheng",
    "gn:population":0,
    "gn:timezone":"Asia/Shanghai",
    "iso:country":"CN",
    "name:und_x_variant":[
        "Longcheng Jiedao"
    ],
    "name:zho_x_preferred":[
        "\u9f99\u57ce"
    ],
    "name:zho_x_variant":[
        "\u9f99\u57ce\u8857\u9053"
    ],
    "wof:name":"Longcheng",
    "wof:placetype":"locality"
},
  "geometry": {"coordinates":[114.2152,22.70241],"type":"Point"}
}