{
  "type": "Feature",
  "properties": {
    "gn:admin1_code":"29",
    "gn:asciiname":"Nabi",
    "gn:country_code":"CN",
    "gn:dem":754,
    "gn:feature_class":"P",
    "gn:feature_code":"PPL",
    "gn:name":"Nabi",
    "gn:population":0,
    "gn:timezone":"Asia/Shanghai",
    "iso:country":"CN",
    "name:ceb_x_preferred":[
        "Nabi"
    ],
    "name:deu_x_preferred":[
        "Nabi"
    ],
    "name:epo_x_preferred":[
        "Nabi"
    ],
    "name:fra_x_preferred":[
        "Nabi"
    ],
    "name:kaz_x_preferred":[
        "\u041d\u04d9\u0431\u0438"
    ],
    "name:kor_x_preferred":[
        "\ub098\ube44"
    ],
    "name:nds_x_preferred":[
        "Nabi"
    ],
    "name:rus_x_preferred":[
        "\u041d\u0430\u0431\u0438"
    ],
    "name:swe_x_preferred":[
        "Nabi"
    ],
    "name:zho_x_preferred":[
        "\u90a3\u6bd5"
    ],
    "wof:name":"Nabi",
    "wof:placetype":"locality"
},
  "geometry": {"coordinates":[105.91,23.5233],"type":"Point"}
}