{
  "type": "Feature",
  "properties": {
    "gn:admin1_code":"32.0",
    "gn:asciiname":"Hepiao",
    "gn:country_code":"CN",
    "gn:dem":1036,
    "gn:feature_class":"P",
    "gn:feature_code":"PPL",
    "gn:name":"Hepiao",
    "gn:population":0,
    "gn:timezone":"Asia/Shanghai",
    "iso:country":"CN",
    "name:zho_x_preferred":[
        "\u6cb3\u6f02"
    ],
    "wof:name":"Hepiao",
    "wof:placetype":"locality"
},
  "geometry": {"coordinates":[101.9357,26.42572],"type":"Point"}
}