{
  "type": "Feature",
  "properties": {
    "gn:admin1_code":"10.0",
    "gn:asciiname":"Xizhuang'er",
    "gn:country_code":"CN",
    "gn:dem":499,
    "gn:feature_class":"P",
    "gn:feature_code":"PPL",
    "gn:name":"Xizhuang\u2019er",
    "gn:population":0,
    "gn:timezone":"Asia/Shanghai",
    "iso:country":"CN",
    "name:und_x_variant":[
        "Xizhuang\u2019er"
    ],
    "name:zho_x_preferred":[
        "\u897f\u5e84\u5c14"
    ],
    "wof:name":"Xizhuang'er",
    "wof:placetype":"locality"
},
  "geometry": {"coordinates":[114.94945,39.20573],"type":"Point"}
}