{
  "type": "Feature",
  "properties": {
    "gn:admin1_code":"8.0",
    "gn:asciiname":"Dongfanghong",
    "gn:country_code":"CN",
    "gn:dem":211,
    "gn:feature_class":"P",
    "gn:feature_code":"PPL",
    "gn:name":"Dongfanghong",
    "gn:population":0,
    "gn:timezone":"Asia/Shanghai",
    "iso:country":"CN",
    "name:zho_x_preferred":[
        "\u4e1c\u65b9\u7ea2"
    ],
    "wof:name":"Dongfanghong",
    "wof:placetype":"locality"
},
  "geometry": {"coordinates":[123.44143,47.93412],"type":"Point"}
}