{
  "type": "Feature",
  "properties": {
    "gn:admin1_code":"10.0",
    "gn:asciiname":"Dawang Gezhuang",
    "gn:country_code":"CN",
    "gn:dem":28,
    "gn:feature_class":"P",
    "gn:feature_code":"PPL",
    "gn:name":"Dawang Gezhuang",
    "gn:population":0,
    "gn:timezone":"Asia/Shanghai",
    "iso:country":"CN",
    "name:zho_x_preferred":[
        "\u5927\u738b\u5404\u5e84"
    ],
    "wof:name":"Dawang Gezhuang",
    "wof:placetype":"locality"
},
  "geometry": {"coordinates":[118.89208000000001,39.6716],"type":"Point"}
}