{
  "type": "Feature",
  "properties": {
    "gn:admin1_code":"4.0",
    "gn:asciiname":"Xiezhuangcun",
    "gn:country_code":"CN",
    "gn:dem":31,
    "gn:feature_class":"P",
    "gn:feature_code":"PPL",
    "gn:name":"Xiezhuangcun",
    "gn:population":0,
    "gn:timezone":"Asia/Shanghai",
    "iso:country":"CN",
    "name:zho_x_preferred":[
        "\u8c22\u5e84\u6751"
    ],
    "wof:name":"Xiezhuangcun",
    "wof:placetype":"locality"
},
  "geometry": {"coordinates":[118.09229000000001,34.03570999999999],"type":"Point"}
}