{
  "type": "Feature",
  "properties": {
    "gn:admin1_code":"9.0",
    "gn:asciiname":"Xiaoligang",
    "gn:country_code":"CN",
    "gn:dem":129,
    "gn:feature_class":"P",
    "gn:feature_code":"PPL",
    "gn:name":"Xiaoligang",
    "gn:population":0,
    "gn:timezone":"Asia/Shanghai",
    "iso:country":"CN",
    "name:zho_x_preferred":[
        "\u5c0f\u674e\u5c97"
    ],
    "wof:name":"Xiaoligang",
    "wof:placetype":"locality"
},
  "geometry": {"coordinates":[112.88755999999999,32.53058],"type":"Point"}
}