{
  "type": "Feature",
  "properties": {
    "gn:admin1_code":"6.0",
    "gn:asciiname":"Regong",
    "gn:country_code":"CN",
    "gn:dem":2752,
    "gn:feature_class":"P",
    "gn:feature_code":"PPL",
    "gn:name":"Regong",
    "gn:population":0,
    "gn:timezone":"Asia/Shanghai",
    "iso:country":"CN",
    "name:zho_x_preferred":[
        "\u70ed\u5171"
    ],
    "wof:name":"Regong",
    "wof:placetype":"locality"
},
  "geometry": {"coordinates":[101.32429999999999,35.8686],"type":"Point"}
}