{
  "type": "Feature",
  "properties": {
    "gn:admin1_code":"08",
    "gn:asciiname":"Bohai",
    "gn:country_code":"CN",
    "gn:dem":288,
    "gn:feature_class":"P",
    "gn:feature_code":"PPLA4",
    "gn:name":"Bohai",
    "gn:population":0,
    "gn:timezone":"Asia/Shanghai",
    "iso:country":"CN",
    "name:ces_x_preferred":[
        "Po-chaj"
    ],
    "name:deu_x_preferred":[
        "Bohai"
    ],
    "name:fra_x_preferred":[
        "Bohai"
    ],
    "name:ind_x_preferred":[
        "Bohai"
    ],
    "name:kor_x_preferred":[
        "\ubc1c\ud574"
    ],
    "name:nld_x_preferred":[
        "Bohai"
    ],
    "name:pol_x_preferred":[
        "Bohai"
    ],
    "name:spa_x_preferred":[
        "Bohai"
    ],
    "name:und_x_variant":[
        "Bohai Zhen"
    ],
    "name:vie_x_preferred":[
        "B\u1ed9t H\u1ea3i"
    ],
    "name:zho_x_preferred":[
        "\u6e24\u6d77"
    ],
    "name:zho_x_variant":[
        "\u6e24\u6d77\u9547"
    ],
    "wof:name":"Bohai",
    "wof:placetype":"locality"
},
  "geometry": {"coordinates":[129.15000000000001,44.11667],"type":"Point"}
}