{
  "type": "Feature",
  "properties": {
    "gn:admin1_code":"2.0",
    "gn:asciiname":"Kengxi",
    "gn:country_code":"CN",
    "gn:dem":937,
    "gn:feature_class":"P",
    "gn:feature_code":"PPL",
    "gn:name":"Kengxi",
    "gn:population":0,
    "gn:timezone":"Asia/Shanghai",
    "iso:country":"CN",
    "name:zho_x_preferred":[
        "\u5751\u897f"
    ],
    "wof:name":"Kengxi",
    "wof:placetype":"locality"
},
  "geometry": {"coordinates":[119.23177,27.63047000000001],"type":"Point"}
}