{
  "type": "Feature",
  "properties": {
    "gn:admin1_code":"7.0",
    "gn:asciiname":"Yutan",
    "gn:country_code":"CN",
    "gn:dem":71,
    "gn:feature_class":"P",
    "gn:feature_code":"PPL",
    "gn:name":"Yutan",
    "gn:population":0,
    "gn:timezone":"Asia/Shanghai",
    "iso:country":"CN",
    "name:ceb_x_preferred":[
        "Yutan"
    ],
    "name:deu_x_preferred":[
        "Yutan"
    ],
    "name:swe_x_preferred":[
        "Yutan"
    ],
    "name:zho_x_preferred":[
        "\u9c7c\u6f6d"
    ],
    "wof:name":"Yutan",
    "wof:placetype":"locality"
},
  "geometry": {"coordinates":[119.73378,26.60687],"type":"Point"}
}