{
  "type": "Feature",
  "properties": {
    "gn:admin1_code":"4.0",
    "gn:asciiname":"Daoyangshu",
    "gn:country_code":"CN",
    "gn:dem":6,
    "gn:feature_class":"P",
    "gn:feature_code":"PPL",
    "gn:name":"Daoyangshu",
    "gn:population":0,
    "gn:timezone":"Asia/Shanghai",
    "iso:country":"CN",
    "name:zho_x_preferred":[
        "\u5012\u6768\u6811"
    ],
    "wof:name":"Daoyangshu",
    "wof:placetype":"locality"
},
  "geometry": {"coordinates":[120.72263,32.33819],"type":"Point"}
}