{
  "type": "Feature",
  "properties": {
    "gn:admin1_code":"32.0",
    "gn:asciiname":"Mao'er Wuji",
    "gn:country_code":"CN",
    "gn:dem":433,
    "gn:feature_class":"P",
    "gn:feature_code":"PPL",
    "gn:name":"Mao\u2019er Wuji",
    "gn:population":0,
    "gn:timezone":"Asia/Shanghai",
    "iso:country":"CN",
    "name:und_x_variant":[
        "Mao\u2019er Wuji"
    ],
    "name:zho_x_preferred":[
        "\u732b\u513f\u5c4b\u57fa"
    ],
    "wof:name":"Mao'er Wuji",
    "wof:placetype":"locality"
},
  "geometry": {"coordinates":[104.84399999999999,29.6981],"type":"Point"}
}