{
  "type": "Feature",
  "properties": {
    "gn:admin1_code":"18",
    "gn:asciiname":"Dadongkou",
    "gn:country_code":"CN",
    "gn:dem":1505,
    "gn:feature_class":"P",
    "gn:feature_code":"PPL",
    "gn:name":"Dadongkou",
    "gn:population":0,
    "gn:timezone":"Asia/Shanghai",
    "iso:country":"CN",
    "name:zho_x_preferred":[
        "\u5927\u6d1e\u53e3"
    ],
    "wof:name":"Dadongkou",
    "wof:placetype":"locality"
},
  "geometry": {"coordinates":[106.964,26.5677],"type":"Point"}
}