{
  "type": "Feature",
  "properties": {
    "gn:admin1_code":"11",
    "gn:asciiname":"Dadili",
    "gn:country_code":"CN",
    "gn:dem":246,
    "gn:feature_class":"P",
    "gn:feature_code":"PPL",
    "gn:name":"Dadili",
    "gn:population":0,
    "gn:timezone":"Asia/Shanghai",
    "iso:country":"CN",
    "name:und_x_variant":[
        "\u5927\u5730\u91cc",
        "Dadili"
    ],
    "wof:name":"Dadili",
    "wof:placetype":"locality"
},
  "geometry": {"coordinates":[111.96861,25.73667],"type":"Point"}
}