{
  "type": "Feature",
  "properties": {
    "gn:admin1_code":"24.0",
    "gn:asciiname":"Jinjiazhuang",
    "gn:country_code":"CN",
    "gn:dem":1107,
    "gn:feature_class":"P",
    "gn:feature_code":"PPL",
    "gn:name":"Jinjiazhuang",
    "gn:population":0,
    "gn:timezone":"Asia/Shanghai",
    "iso:country":"CN",
    "name:zho_x_preferred":[
        "\u91d1\u5bb6\u5e84"
    ],
    "wof:name":"Jinjiazhuang",
    "wof:placetype":"locality"
},
  "geometry": {"coordinates":[113.31368000000001,37.82955],"type":"Point"}
}