{
  "type": "Feature",
  "properties": {
    "gn:admin1_code":"10",
    "gn:asciiname":"Shangwafang",
    "gn:country_code":"CN",
    "gn:dem":1191,
    "gn:feature_class":"P",
    "gn:feature_code":"PPL",
    "gn:name":"Shangwafang",
    "gn:population":0,
    "gn:timezone":"Asia/Shanghai",
    "iso:country":"CN",
    "name:zho_x_preferred":[
        "\u4e0a\u74e6\u623f"
    ],
    "wof:name":"Shangwafang",
    "wof:placetype":"locality"
},
  "geometry": {"coordinates":[115.57776,40.64304],"type":"Point"}
}