{
  "type": "Feature",
  "properties": {
    "gn:admin1_code":"11.0",
    "gn:asciiname":"Qiaojiagou",
    "gn:country_code":"CN",
    "gn:dem":542,
    "gn:feature_class":"P",
    "gn:feature_code":"PPL",
    "gn:name":"Qiaojiagou",
    "gn:population":0,
    "gn:timezone":"Asia/Shanghai",
    "iso:country":"CN",
    "name:zho_x_preferred":[
        "\u6865\u67b6\u6c9f"
    ],
    "wof:name":"Qiaojiagou",
    "wof:placetype":"locality"
},
  "geometry": {"coordinates":[109.48744000000001,29.4712],"type":"Point"}
}