{
  "type": "Feature",
  "properties": {
    "gn:admin1_code":"29.0",
    "gn:asciiname":"Limizha",
    "gn:country_code":"CN",
    "gn:dem":1736,
    "gn:feature_class":"P",
    "gn:feature_code":"PPL",
    "gn:name":"Limizha",
    "gn:population":0,
    "gn:timezone":"Asia/Shanghai",
    "iso:country":"CN",
    "name:zho_x_preferred":[
        "\u5229\u7c73\u4e4d"
    ],
    "wof:name":"Limizha",
    "wof:placetype":"locality"
},
  "geometry": {"coordinates":[101.61499999999999,25.7769],"type":"Point"}
}