{
  "type": "Feature",
  "properties": {
    "gn:admin1_code":"09",
    "gn:asciiname":"Wamiaoji",
    "gn:country_code":"CN",
    "gn:dem":78,
    "gn:feature_class":"P",
    "gn:feature_code":"PPL",
    "gn:name":"Wamiaoji",
    "gn:population":0,
    "gn:timezone":"Asia/Shanghai",
    "iso:country":"CN",
    "name:und_x_variant":[
        "Wa-miao-chi",
        "Wamiaoji"
    ],
    "name:zho_x_preferred":[
        "\u74e6\u5e99\u96c6"
    ],
    "wof:name":"Wamiaoji",
    "wof:placetype":"locality"
},
  "geometry": {"coordinates":[115.50851000000002,32.04940999999999],"type":"Point"}
}