{
  "type": "Feature",
  "properties": {
    "gn:admin1_code":"32.0",
    "gn:asciiname":"Ganjiaqiao",
    "gn:country_code":"CN",
    "gn:dem":381,
    "gn:feature_class":"P",
    "gn:feature_code":"PPL",
    "gn:name":"Ganjiaqiao",
    "gn:population":0,
    "gn:timezone":"Asia/Shanghai",
    "iso:country":"CN",
    "name:zho_x_preferred":[
        "\u7518\u5bb6\u6865"
    ],
    "wof:name":"Ganjiaqiao",
    "wof:placetype":"locality"
},
  "geometry": {"coordinates":[105.255,29.4802],"type":"Point"}
}