{
  "type": "Feature",
  "properties": {
    "gn:admin1_code":"9",
    "gn:asciiname":"Nanlicun",
    "gn:country_code":"CN",
    "gn:dem":113,
    "gn:feature_class":"P",
    "gn:feature_code":"PPL",
    "gn:name":"Nanlicun",
    "gn:population":0,
    "gn:timezone":"Asia/Shanghai",
    "iso:country":"CN",
    "wof:name":"Nanlicun",
    "wof:placetype":"locality"
},
  "geometry": {"coordinates":[113.08611000000001,35.0575],"type":"Point"}
}