{
  "type": "Feature",
  "properties": {
    "gn:admin1_code":"15.0",
    "gn:asciiname":"Potou",
    "gn:country_code":"CN",
    "gn:dem":1854,
    "gn:feature_class":"P",
    "gn:feature_code":"PPL",
    "gn:name":"Potou",
    "gn:population":0,
    "gn:timezone":"Asia/Shanghai",
    "iso:country":"CN",
    "name:und_x_variant":[
        "\u5761\u5934"
    ],
    "name:zho_x_preferred":[
        "\u5761\u5934"
    ],
    "wof:name":"Potou",
    "wof:placetype":"locality"
},
  "geometry": {"coordinates":[104.40976999999999,34.03569],"type":"Point"}
}