{
  "type": "Feature",
  "properties": {
    "gn:admin1_code":"4.0",
    "gn:asciiname":"Tenggang",
    "gn:country_code":"CN",
    "gn:dem":52,
    "gn:feature_class":"P",
    "gn:feature_code":"PPL",
    "gn:name":"Tenggang",
    "gn:population":0,
    "gn:timezone":"Asia/Shanghai",
    "iso:country":"CN",
    "name:zho_x_preferred":[
        "\u6ed5\u5c97"
    ],
    "wof:name":"Tenggang",
    "wof:placetype":"locality"
},
  "geometry": {"coordinates":[118.55307000000001,32.77200999999999],"type":"Point"}
}