{
  "type": "Feature",
  "properties": {
    "gn:admin1_code":"30",
    "gn:asciiname":"Lincuo",
    "gn:country_code":"CN",
    "gn:dem":85,
    "gn:feature_class":"P",
    "gn:feature_code":"PPL",
    "gn:name":"Lincuo",
    "gn:population":0,
    "gn:timezone":"Asia/Shanghai",
    "iso:country":"CN",
    "wof:name":"Lincuo",
    "wof:placetype":"locality"
},
  "geometry": {"coordinates":[116.78444,23.67583],"type":"Point"}
}