{
  "type": "Feature",
  "properties": {
    "gn:admin1_code":"20",
    "gn:asciiname":"Tulihe",
    "gn:country_code":"CN",
    "gn:dem":733,
    "gn:feature_class":"P",
    "gn:feature_code":"PPLA4",
    "gn:name":"Tulihe",
    "gn:population":0,
    "gn:timezone":"Asia/Shanghai",
    "iso:country":"CN",
    "name:und_x_variant":[
        "T\u2019u-li-ho",
        "Tulihe",
        "Tulihe Zhen"
    ],
    "name:zho_x_preferred":[
        "\u56fe\u91cc\u6cb3"
    ],
    "name:zho_x_variant":[
        "\u56fe\u91cc\u6cb3\u9547"
    ],
    "wof:name":"Tulihe",
    "wof:placetype":"locality"
},
  "geometry": {"coordinates":[121.67443,50.48354000000001],"type":"Point"}
}