{
  "type": "Feature",
  "properties": {
    "gn:admin1_code":"19.0",
    "gn:asciiname":"Tazigoucun",
    "gn:country_code":"CN",
    "gn:dem":219,
    "gn:feature_class":"P",
    "gn:feature_code":"PPL",
    "gn:name":"Tazigoucun",
    "gn:population":0,
    "gn:timezone":"Asia/Shanghai",
    "iso:country":"CN",
    "name:zho_x_preferred":[
        "\u5854\u5b50\u6c9f\u6751"
    ],
    "wof:name":"Tazigoucun",
    "wof:placetype":"locality"
},
  "geometry": {"coordinates":[121.755,41.9881],"type":"Point"}
}