{
  "type": "Feature",
  "properties": {
    "gn:admin1_code":"30.0",
    "gn:asciiname":"Luowen",
    "gn:country_code":"CN",
    "gn:dem":33,
    "gn:feature_class":"P",
    "gn:feature_code":"PPL",
    "gn:name":"Luowen",
    "gn:population":0,
    "gn:timezone":"Asia/Shanghai",
    "iso:country":"CN",
    "name:zho_x_preferred":[
        "\u7f85\u7a69"
    ],
    "wof:name":"Luowen",
    "wof:placetype":"locality"
},
  "geometry": {"coordinates":[112.6434,22.87894],"type":"Point"}
}