{
  "type": "Feature",
  "properties": {
    "gn:admin1_code":"14.0",
    "gn:asciiname":"Benzha",
    "gn:country_code":"CN",
    "gn:dem":3850,
    "gn:feature_class":"P",
    "gn:feature_code":"PPL",
    "gn:name":"Benzha",
    "gn:population":0,
    "gn:timezone":"Asia/Urumqi",
    "iso:country":"CN",
    "name:zho_x_preferred":[
        "\u672c\u6e23"
    ],
    "wof:name":"Benzha",
    "wof:placetype":"locality"
},
  "geometry": {"coordinates":[91.85525,29.38901],"type":"Point"}
}