{
  "type": "Feature",
  "properties": {
    "gn:admin1_code":"14.0",
    "gn:asciiname":"Retuo",
    "gn:country_code":"CN",
    "gn:dem":3383,
    "gn:feature_class":"P",
    "gn:feature_code":"PPL",
    "gn:name":"Retuo",
    "gn:population":0,
    "gn:timezone":"Asia/Urumqi",
    "iso:country":"CN",
    "name:zho_x_preferred":[
        "\u60f9\u8131"
    ],
    "wof:name":"Retuo",
    "wof:placetype":"locality"
},
  "geometry": {"coordinates":[97.25498,31.02698],"type":"Point"}
}