{
  "type": "Feature",
  "properties": {
    "gn:country":"CN",
    "gn:fcode":"PPL",
    "gn:pop":87961,
    "iso:country":"CN",
    "name:unk_x_variant":[
        "Y\u00fc"
    ],
    "name:zho_x_preferred":[
        "\u988d\u5ddd"
    ],
    "qs:name":"\u5cea\u5dde",
    "qs:name_adm0":"\u4e2d\u570b",
    "qs:name_adm1":"\u6cb3\u5357\u7701",
    "qs:photos_9k":1,
    "qs:photos_9r":1,
    "qs:photos_all":1,
    "qs:photos_sr":0,
    "qs:placetype":"Town",
    "qs:pop_sr":"8",
    "wof:name":"\u5cea\u5dde",
    "wof:placetype":"locality",
    "wof:population":87961
},
  "geometry": {"coordinates":[113.46389000000001,34.16278],"type":"Point"}
}