{
  "type": "Feature",
  "properties": {
    "gn:admin1_code":"29.0",
    "gn:asciiname":"Qiwuka",
    "gn:country_code":"CN",
    "gn:dem":2119,
    "gn:feature_class":"P",
    "gn:feature_code":"PPL",
    "gn:name":"Qiwuka",
    "gn:population":0,
    "gn:timezone":"Asia/Shanghai",
    "iso:country":"CN",
    "name:zho_x_preferred":[
        "\u4e03\u4e94\u5361"
    ],
    "wof:name":"Qiwuka",
    "wof:placetype":"locality"
},
  "geometry": {"coordinates":[103.563,26.5778],"type":"Point"}
}