{
  "type": "Feature",
  "properties": {
    "gn:admin1_code":"30",
    "gn:asciiname":"Lixing Nongchang",
    "gn:country_code":"CN",
    "gn:dem":160,
    "gn:feature_class":"P",
    "gn:feature_code":"PPLF",
    "gn:name":"Lixing Nongchang",
    "gn:population":0,
    "gn:timezone":"Asia/Shanghai",
    "iso:country":"CN",
    "name:zho_x_preferred":[
        "\u91cc\u884c\u519c\u573a"
    ],
    "wof:name":"Lixing Nongchang",
    "wof:placetype":"locality"
},
  "geometry": {"coordinates":[116.44414999999999,23.08307000000001],"type":"Point"}
}