{
  "type": "Feature",
  "properties": {
    "gn:admin1_code":"18.0",
    "gn:asciiname":"Banzhuyuan",
    "gn:country_code":"CN",
    "gn:dem":414,
    "gn:feature_class":"P",
    "gn:feature_code":"PPL",
    "gn:name":"Banzhuyuan",
    "gn:population":0,
    "gn:timezone":"Asia/Shanghai",
    "iso:country":"CN",
    "name:zho_x_preferred":[
        "\u73ed\u7af9\u56ed"
    ],
    "wof:name":"Banzhuyuan",
    "wof:placetype":"locality"
},
  "geometry": {"coordinates":[108.56999999999999,28.618],"type":"Point"}
}