{
  "type": "Feature",
  "properties": {
    "gn:admin1_code":"29.0",
    "gn:asciiname":"Langtangzhai",
    "gn:country_code":"CN",
    "gn:dem":1399,
    "gn:feature_class":"P",
    "gn:feature_code":"PPL",
    "gn:name":"Langtangzhai",
    "gn:population":0,
    "gn:timezone":"Asia/Shanghai",
    "iso:country":"CN",
    "name:zho_x_preferred":[
        "\u6d6a\u6c64\u5be8"
    ],
    "wof:name":"Langtangzhai",
    "wof:placetype":"locality"
},
  "geometry": {"coordinates":[101.81399999999999,23.0938],"type":"Point"}
}