{
  "type": "Feature",
  "properties": {
    "gn:admin1_code":"18.0",
    "gn:asciiname":"Houqing",
    "gn:country_code":"CN",
    "gn:dem":1629,
    "gn:feature_class":"P",
    "gn:feature_code":"PPL",
    "gn:name":"Houqing",
    "gn:population":0,
    "gn:timezone":"Asia/Shanghai",
    "iso:country":"CN",
    "wof:name":"Houqing",
    "wof:placetype":"locality"
},
  "geometry": {"coordinates":[105.2175,27.34389],"type":"Point"}
}