{
  "type": "Feature",
  "properties": {
    "gn:admin1_code":"16.0",
    "gn:asciiname":"Shiwukeng",
    "gn:country_code":"CN",
    "gn:dem":185,
    "gn:feature_class":"P",
    "gn:feature_code":"PPL",
    "gn:name":"Shiwukeng",
    "gn:population":0,
    "gn:timezone":"Asia/Shanghai",
    "iso:country":"CN",
    "name:zho_x_preferred":[
        "\u77f3\u5c4b\u5751"
    ],
    "wof:name":"Shiwukeng",
    "wof:placetype":"locality"
},
  "geometry": {"coordinates":[111.26000000000001,22.8862],"type":"Point"}
}