{
  "type": "Feature",
  "properties": {
    "gn:admin1_code":"32.0",
    "gn:asciiname":"Dadong",
    "gn:country_code":"CN",
    "gn:dem":713,
    "gn:feature_class":"P",
    "gn:feature_code":"PPL",
    "gn:name":"Dadong",
    "gn:population":0,
    "gn:timezone":"Asia/Shanghai",
    "iso:country":"CN",
    "name:zho_x_preferred":[
        "\u5927\u6d1e"
    ],
    "wof:name":"Dadong",
    "wof:placetype":"locality"
},
  "geometry": {"coordinates":[108.03400000000001,31.8023],"type":"Point"}
}