{
  "type": "Feature",
  "properties": {
    "gn:admin1_code":"10",
    "gn:asciiname":"Duanlutou",
    "gn:cc2":"CN",
    "gn:country_code":"CN",
    "gn:dem":32,
    "gn:feature_class":"P",
    "gn:feature_code":"PPL",
    "gn:name":"Duanlutou",
    "gn:population":0,
    "gn:timezone":"Asia/Shanghai",
    "iso:country":"CN",
    "name:und_x_variant":[
        "Tuan-lu-t\u2019ou",
        "Tuan-lu-t\u2019ou-chen",
        "Duanlutou"
    ],
    "wof:name":"Duanlutou",
    "wof:placetype":"locality"
},
  "geometry": {"coordinates":[115.66500000000001,37.17389],"type":"Point"}
}