{
  "type": "Feature",
  "properties": {
    "gn:admin1_code":"15.0",
    "gn:asciiname":"Nibamisu",
    "gn:country_code":"CN",
    "gn:dem":2761,
    "gn:feature_class":"P",
    "gn:feature_code":"PPL",
    "gn:name":"Nibamisu",
    "gn:population":0,
    "gn:timezone":"Asia/Shanghai",
    "iso:country":"CN",
    "name:und_x_variant":[
        "\u5c3c\u5df4\u7c73\u82cf"
    ],
    "wof:name":"Nibamisu",
    "wof:placetype":"locality"
},
  "geometry": {"coordinates":[103.67238999999999,34.01271],"type":"Point"}
}