{
  "type": "Feature",
  "properties": {
    "gn:admin1_code":"7",
    "gn:asciiname":"Gengwei",
    "gn:country_code":"CN",
    "gn:dem":142,
    "gn:feature_class":"P",
    "gn:feature_code":"PPL",
    "gn:name":"Gengwei",
    "gn:population":0,
    "gn:timezone":"Asia/Shanghai",
    "iso:country":"CN",
    "name:zho_x_preferred":[
        "\u57c2\u5c3e"
    ],
    "wof:name":"Gengwei",
    "wof:placetype":"locality"
},
  "geometry": {"coordinates":[117.96917999999999,26.72487000000001],"type":"Point"}
}