{
  "type": "Feature",
  "properties": {
    "gn:admin1_code":"19.0",
    "gn:asciiname":"Yangcaiyuan",
    "gn:country_code":"CN",
    "gn:dem":99,
    "gn:feature_class":"P",
    "gn:feature_code":"PPL",
    "gn:name":"Yangcaiyuan",
    "gn:population":0,
    "gn:timezone":"Asia/Shanghai",
    "iso:country":"CN",
    "name:zho_x_preferred":[
        "\u6768\u83dc\u56ed"
    ],
    "wof:name":"Yangcaiyuan",
    "wof:placetype":"locality"
},
  "geometry": {"coordinates":[123.45699999999999,43.0195],"type":"Point"}
}