{
  "type": "Feature",
  "properties": {
    "gn:admin1_code":"26.0",
    "gn:asciiname":"Guojia Zuicun",
    "gn:country_code":"CN",
    "gn:dem":902,
    "gn:feature_class":"P",
    "gn:feature_code":"PPL",
    "gn:name":"Guojia Zuicun",
    "gn:population":0,
    "gn:timezone":"Asia/Shanghai",
    "iso:country":"CN",
    "name:zho_x_preferred":[
        "\u90ed\u5bb6\u5480\u6751"
    ],
    "wof:name":"Guojia Zuicun",
    "wof:placetype":"locality"
},
  "geometry": {"coordinates":[110.261,37.3852],"type":"Point"}
}