{
  "type": "Feature",
  "properties": {
    "gn:admin1_code":"11.0",
    "gn:asciiname":"Shamaochong",
    "gn:country_code":"CN",
    "gn:dem":297,
    "gn:feature_class":"P",
    "gn:feature_code":"PPL",
    "gn:name":"Shamaochong",
    "gn:population":0,
    "gn:timezone":"Asia/Shanghai",
    "iso:country":"CN",
    "name:zho_x_preferred":[
        "\u7eb1\u5e3d\u51b2"
    ],
    "wof:name":"Shamaochong",
    "wof:placetype":"locality"
},
  "geometry": {"coordinates":[111.69741999999999,28.11779000000001],"type":"Point"}
}