{
  "type": "Feature",
  "properties": {
    "gn:admin1_code":"32.0",
    "gn:asciiname":"Hekanshang",
    "gn:country_code":"CN",
    "gn:dem":1231,
    "gn:feature_class":"P",
    "gn:feature_code":"PPL",
    "gn:name":"Hekanshang",
    "gn:population":0,
    "gn:timezone":"Asia/Shanghai",
    "iso:country":"CN",
    "name:zho_x_preferred":[
        "\u6cb3\u574e\u4e0a"
    ],
    "wof:name":"Hekanshang",
    "wof:placetype":"locality"
},
  "geometry": {"coordinates":[105.62335,27.90891],"type":"Point"}
}