{
  "type": "Feature",
  "properties": {
    "gn:admin1_code":"10",
    "gn:asciiname":"Beitaozi",
    "gn:country_code":"CN",
    "gn:dem":9,
    "gn:feature_class":"P",
    "gn:feature_code":"PPL",
    "gn:name":"Beitaozi",
    "gn:population":0,
    "gn:timezone":"Asia/Shanghai",
    "iso:country":"CN",
    "name:zho_x_preferred":[
        "\u5317\u6843\u5b50"
    ],
    "wof:name":"Beitaozi",
    "wof:placetype":"locality"
},
  "geometry": {"coordinates":[116.464,38.7382],"type":"Point"}
}