{
  "type": "Feature",
  "properties": {
    "gn:admin1_code":"15.0",
    "gn:asciiname":"Tiemuxian",
    "gn:country_code":"CN",
    "gn:dem":2138,
    "gn:feature_class":"P",
    "gn:feature_code":"PPL",
    "gn:name":"Tiemuxian",
    "gn:population":0,
    "gn:timezone":"Asia/Shanghai",
    "iso:country":"CN",
    "name:zho_x_preferred":[
        "\u94c1\u6728\u5c98"
    ],
    "wof:name":"Tiemuxian",
    "wof:placetype":"locality"
},
  "geometry": {"coordinates":[103.09699999999999,36.4882],"type":"Point"}
}