{
  "type": "Feature",
  "properties": {
    "gn:admin1_code":"32.0",
    "gn:asciiname":"Zhenjing",
    "gn:country_code":"CN",
    "gn:dem":283,
    "gn:feature_class":"P",
    "gn:feature_code":"PPL",
    "gn:name":"Zhenjing",
    "gn:population":0,
    "gn:timezone":"Asia/Shanghai",
    "iso:country":"CN",
    "name:zho_x_preferred":[
        "\u771f\u4e95"
    ],
    "wof:name":"Zhenjing",
    "wof:placetype":"locality"
},
  "geometry": {"coordinates":[106.76600000000001,31.0051],"type":"Point"}
}