{
  "type": "Feature",
  "properties": {
    "gn:admin1_code":"2.0",
    "gn:asciiname":"Shaxikou",
    "gn:country_code":"CN",
    "gn:dem":9,
    "gn:feature_class":"P",
    "gn:feature_code":"PPL",
    "gn:name":"Shaxikou",
    "gn:population":0,
    "gn:timezone":"Asia/Shanghai",
    "iso:country":"CN",
    "name:und_x_variant":[
        "\u6c99\u6eaa\u53e3"
    ],
    "wof:name":"Shaxikou",
    "wof:placetype":"locality"
},
  "geometry": {"coordinates":[119.90340999999999,30.26056],"type":"Point"}
}