{
  "type": "Feature",
  "properties": {
    "gn:admin1_code":"9.0",
    "gn:asciiname":"Xingtai",
    "gn:country_code":"CN",
    "gn:dem":105,
    "gn:feature_class":"P",
    "gn:feature_code":"PPL",
    "gn:name":"Xingtai",
    "gn:population":0,
    "gn:timezone":"Asia/Shanghai",
    "iso:country":"CN",
    "name:afr_x_preferred":[
        "Xingtai"
    ],
    "name:ara_x_preferred":[
        "\u0634\u064a\u0646\u063a\u062a\u0627\u064a"
    ],
    "name:bul_x_preferred":[
        "\u0421\u0438\u043d\u0442\u0430\u0439"
    ],
    "name:cat_x_preferred":[
        "Xingtai"
    ],
    "name:cdo_x_preferred":[
        "H\u00ecng-d\u00e0i"
    ],
    "name:ceb_x_preferred":[
        "Xingtai"
    ],
    "name:ces_x_preferred":[
        "Sing-tchaj"
    ],
    "name:dan_x_preferred":[
        "Xingtai"
    ],
    "name:deu_x_preferred":[
        "Xingtai"
    ],
    "name:epo_x_preferred":[
        "Sintaj"
    ],
    "name:eus_x_preferred":[
        "Xingtai"
    ],
    "name:fas_x_preferred":[
        "\u0634\u06cc\u0646\u06af\u062a\u0627\u06cc"
    ],
    "name:fin_x_preferred":[
        "Xingtai"
    ],
    "name:fra_x_preferred":[
        "Xingtai"
    ],
    "name:ita_x_preferred":[
        "Xingtai"
    ],
    "name:jpn_x_preferred":[
        "\u30b1\u30a4\u53f0\u5e02"
    ],
    "name:kik_x_preferred":[
        "Xingtai"
    ],
    "name:kor_x_preferred":[
        "\uc2f1\ud0c0\uc774\uc2dc"
    ],
    "name:mlg_x_preferred":[
        "Xingtai"
    ],
    "name:nld_x_preferred":[
        "Xingtai"
    ],
    "name:nno_x_preferred":[
        "Xingtai"
    ],
    "name:nor_x_preferred":[
        "Xingtai"
    ],
    "name:pam_x_preferred":[
        "Xingtai"
    ],
    "name:pol_x_preferred":[
        "Xingtai"
    ],
    "name:por_x_preferred":[
        "Xingtai"
    ],
    "name:rus_x_preferred":[
        "\u0421\u0438\u043d\u0442\u0430\u0439"
    ],
    "name:spa_x_preferred":[
        "Xingtai"
    ],
    "name:srp_x_preferred":[
        "\u0421\u0438\u043d\u0433\u0442\u0430\u0458"
    ],
    "name:swe_x_preferred":[
        "Xingtai"
    ],
    "name:tur_x_preferred":[
        "Xingtai"
    ],
    "name:ukr_x_preferred":[
        "\u0421\u0456\u043d\u0442\u0430\u0439"
    ],
    "name:urd_x_preferred":[
        "\u0634\u0646\u06af\u062a\u0627\u0626\u06cc"
    ],
    "name:vie_x_preferred":[
        "H\u00ecnh \u0110\u00e0i"
    ],
    "name:war_x_preferred":[
        "Xingtai"
    ],
    "name:wuu_x_preferred":[
        "\u90a2\u53f0\u5e02"
    ],
    "name:zho_x_preferred":[
        "\u90a2\u53f0"
    ],
    "name:zho_x_variant":[
        "\u90a2\u53f0\u5e02"
    ],
    "wof:name":"Xingtai",
    "wof:placetype":"locality"
},
  "geometry": {"coordinates":[114.23033,32.17134],"type":"Point"}
}