{
  "type": "Feature",
  "properties": {
    "gn:admin1_code":"2.0",
    "gn:asciiname":"Guichuan",
    "gn:country_code":"CN",
    "gn:dem":510,
    "gn:feature_class":"P",
    "gn:feature_code":"PPL",
    "gn:name":"Guichuan",
    "gn:population":0,
    "gn:timezone":"Asia/Shanghai",
    "iso:country":"CN",
    "name:zho_x_preferred":[
        "\u6842\u5ddd"
    ],
    "wof:name":"Guichuan",
    "wof:placetype":"locality"
},
  "geometry": {"coordinates":[120.34408000000001,28.48222],"type":"Point"}
}