{
  "type": "Feature",
  "properties": {
    "gn:admin1_code":"11",
    "gn:asciiname":"Qingmugang",
    "gn:country_code":"CN",
    "gn:dem":296,
    "gn:feature_class":"P",
    "gn:feature_code":"PPL",
    "gn:name":"Qingmugang",
    "gn:population":0,
    "gn:timezone":"Asia/Shanghai",
    "iso:country":"CN",
    "name:zho_x_preferred":[
        "\u9752\u6728\u5c97"
    ],
    "wof:name":"Qingmugang",
    "wof:placetype":"locality"
},
  "geometry": {"coordinates":[111.19558000000001,25.11045],"type":"Point"}
}