{
  "type": "Feature",
  "properties": {
    "gn:admin1_code":"14.0",
    "gn:asciiname":"Dongdoucun",
    "gn:country_code":"CN",
    "gn:dem":3497,
    "gn:feature_class":"P",
    "gn:feature_code":"PPL",
    "gn:name":"Dongdoucun",
    "gn:population":0,
    "gn:timezone":"Asia/Urumqi",
    "iso:country":"CN",
    "name:zho_x_preferred":[
        "\u4e1c\u6597\u6751"
    ],
    "wof:name":"Dongdoucun",
    "wof:placetype":"locality"
},
  "geometry": {"coordinates":[98.35436,31.67625],"type":"Point"}
}