{
  "type": "Feature",
  "properties": {
    "gn:admin1_code":"8.0",
    "gn:asciiname":"Gaohuaitun",
    "gn:country_code":"CN",
    "gn:dem":305,
    "gn:feature_class":"P",
    "gn:feature_code":"PPL",
    "gn:name":"Gaohuaitun",
    "gn:population":0,
    "gn:timezone":"Asia/Shanghai",
    "iso:country":"CN",
    "name:zho_x_preferred":[
        "\u9ad8\u69d0\u5c6f"
    ],
    "wof:name":"Gaohuaitun",
    "wof:placetype":"locality"
},
  "geometry": {"coordinates":[125.49652,48.28211],"type":"Point"}
}