{
  "type": "Feature",
  "properties": {
    "gn:admin1_code":"30",
    "gn:asciiname":"Yuanxiapai",
    "gn:country_code":"CN",
    "gn:dem":196,
    "gn:feature_class":"P",
    "gn:feature_code":"PPL",
    "gn:name":"Yuanxiapai",
    "gn:population":0,
    "gn:timezone":"Asia/Shanghai",
    "iso:country":"CN",
    "name:zho_x_preferred":[
        "\u56ed\u4e0b\u6392"
    ],
    "wof:name":"Yuanxiapai",
    "wof:placetype":"locality"
},
  "geometry": {"coordinates":[115.60927,23.44953],"type":"Point"}
}