{
  "type": "Feature",
  "properties": {
    "gn:admin1_code":"11.0",
    "gn:asciiname":"Shangbuhao",
    "gn:country_code":"CN",
    "gn:dem":832,
    "gn:feature_class":"P",
    "gn:feature_code":"PPL",
    "gn:name":"Shangbuhao",
    "gn:population":0,
    "gn:timezone":"Asia/Shanghai",
    "iso:country":"CN",
    "name:zho_x_preferred":[
        "\u4e0a\u8865\u6beb"
    ],
    "wof:name":"Shangbuhao",
    "wof:placetype":"locality"
},
  "geometry": {"coordinates":[109.58346,28.38141],"type":"Point"}
}