{
  "type": "Feature",
  "properties": {
    "gn:admin1_code":"32.0",
    "gn:asciiname":"Fengyazi",
    "gn:country_code":"CN",
    "gn:dem":1308,
    "gn:feature_class":"P",
    "gn:feature_code":"PPL",
    "gn:name":"Fengyazi",
    "gn:population":0,
    "gn:timezone":"Asia/Shanghai",
    "iso:country":"CN",
    "name:und_x_variant":[
        "\u51e4\u57ad\u5b50"
    ],
    "wof:name":"Fengyazi",
    "wof:placetype":"locality"
},
  "geometry": {"coordinates":[106.80171,32.50365],"type":"Point"}
}