{
  "type": "Feature",
  "properties": {
    "gn:admin1_code":"14.0",
    "gn:asciiname":"Doxu",
    "gn:country_code":"CN",
    "gn:dem":3969,
    "gn:feature_class":"P",
    "gn:feature_code":"PPL",
    "gn:name":"Doxu",
    "gn:population":0,
    "gn:timezone":"Asia/Urumqi",
    "iso:country":"CN",
    "name:bod_x_preferred":[
        "Doxu"
    ],
    "name:zho_x_preferred":[
        "Duoxi"
    ],
    "name:zho_x_variant":[
        "\u593a\u897f",
        "Huola Gongshe",
        "\u706b\u62c9\u516c\u793e"
    ],
    "wof:name":"Doxu",
    "wof:placetype":"locality"
},
  "geometry": {"coordinates":[98.49742999999999,29.49173],"type":"Point"}
}