{
  "type": "Feature",
  "properties": {
    "gn:admin1_code":"13",
    "gn:asciiname":"Wugedan Guoleng",
    "gn:country_code":"CN",
    "gn:dem":2115,
    "gn:feature_class":"P",
    "gn:feature_code":"PPL",
    "gn:name":"Wugedan Guoleng",
    "gn:population":0,
    "gn:timezone":"Asia/Urumqi",
    "iso:country":"CN",
    "name:und_x_variant":[
        "\u4e4c\u683c\u65e6\u90ed\u695e"
    ],
    "wof:name":"Wugedan Guoleng",
    "wof:placetype":"locality"
},
  "geometry": {"coordinates":[86.32600000000002,42.88856],"type":"Point"}
}