{
  "type": "Feature",
  "properties": {
    "gn:admin1_code":"05",
    "gn:asciiname":"Xisanhao",
    "gn:cc2":"CN",
    "gn:country_code":"CN",
    "gn:dem":205,
    "gn:feature_class":"P",
    "gn:feature_code":"PPL",
    "gn:name":"Xisanhao",
    "gn:population":0,
    "gn:timezone":"Asia/Shanghai",
    "iso:country":"CN",
    "name:und_x_variant":[
        "Hsi-san-hao",
        "Wu-tzu-san-hao",
        "Xisanhao"
    ],
    "wof:name":"Xisanhao",
    "wof:placetype":"locality"
},
  "geometry": {"coordinates":[126.40000000000001,45.11667],"type":"Point"}
}