{
  "type": "Feature",
  "properties": {
    "gn:admin1_code":"9.0",
    "gn:asciiname":"Sumiao",
    "gn:country_code":"CN",
    "gn:dem":100,
    "gn:feature_class":"P",
    "gn:feature_code":"PPL",
    "gn:name":"Sumiao",
    "gn:population":0,
    "gn:timezone":"Asia/Shanghai",
    "iso:country":"CN",
    "name:zho_x_preferred":[
        "\u82cf\u5e99"
    ],
    "wof:name":"Sumiao",
    "wof:placetype":"locality"
},
  "geometry": {"coordinates":[114.13204,32.22848],"type":"Point"}
}