{
  "type": "Feature",
  "properties": {
    "gn:admin1_code":"25",
    "gn:asciiname":"Xiaobuling",
    "gn:country_code":"CN",
    "gn:dem":47,
    "gn:feature_class":"P",
    "gn:feature_code":"PPL",
    "gn:name":"Xiaobuling",
    "gn:population":0,
    "gn:timezone":"Asia/Shanghai",
    "iso:country":"CN",
    "name:zho_x_preferred":[
        "\u5c0f\u57e0\u5cad"
    ],
    "wof:name":"Xiaobuling",
    "wof:placetype":"locality"
},
  "geometry": {"coordinates":[118.30800000000001,34.6822],"type":"Point"}
}