{
  "type": "Feature",
  "properties": {
    "gn:admin1_code":"3",
    "gn:asciiname":"Xiaokeng",
    "gn:country_code":"CN",
    "gn:dem":99,
    "gn:feature_class":"P",
    "gn:feature_code":"PPL",
    "gn:name":"Xiaokeng",
    "gn:population":0,
    "gn:timezone":"Asia/Shanghai",
    "iso:country":"CN",
    "name:zho_x_preferred":[
        "\u5c0f\u5751"
    ],
    "wof:name":"Xiaokeng",
    "wof:placetype":"locality"
},
  "geometry": {"coordinates":[114.72199999999999,26.788],"type":"Point"}
}