{
  "type": "Feature",
  "properties": {
    "gn:admin1_code":"11.0",
    "gn:asciiname":"Fengdong",
    "gn:country_code":"CN",
    "gn:dem":167,
    "gn:feature_class":"P",
    "gn:feature_code":"PPL",
    "gn:name":"Fengdong",
    "gn:population":0,
    "gn:timezone":"Asia/Shanghai",
    "iso:country":"CN",
    "name:zho_x_preferred":[
        "Fengdong"
    ],
    "name:zho_x_variant":[
        "\u98ce\u6d1e"
    ],
    "wof:name":"Fengdong",
    "wof:placetype":"locality"
},
  "geometry": {"coordinates":[111.00216,29.519],"type":"Point"}
}