{
  "type": "Feature",
  "properties": {
    "gn:admin1_code":"4.0",
    "gn:asciiname":"Chenshifang",
    "gn:country_code":"CN",
    "gn:dem":32,
    "gn:feature_class":"P",
    "gn:feature_code":"PPL",
    "gn:name":"Chenshifang",
    "gn:population":0,
    "gn:timezone":"Asia/Shanghai",
    "iso:country":"CN",
    "name:zho_x_preferred":[
        "\u9648\u62fe\u623f"
    ],
    "wof:name":"Chenshifang",
    "wof:placetype":"locality"
},
  "geometry": {"coordinates":[119.22875000000001,32.50206],"type":"Point"}
}