{
  "type": "Feature",
  "properties": {
    "gn:admin1_code":"7.0",
    "gn:asciiname":"Dianqianban",
    "gn:country_code":"CN",
    "gn:dem":782,
    "gn:feature_class":"P",
    "gn:feature_code":"PPL",
    "gn:name":"Dianqianban",
    "gn:population":0,
    "gn:timezone":"Asia/Shanghai",
    "iso:country":"CN",
    "name:zho_x_preferred":[
        "\u5e97\u524d\u5742"
    ],
    "wof:name":"Dianqianban",
    "wof:placetype":"locality"
},
  "geometry": {"coordinates":[118.61224,26.14498],"type":"Point"}
}