{
  "type": "Feature",
  "properties": {
    "gn:admin1_code":"11.0",
    "gn:asciiname":"Tuluping",
    "gn:country_code":"CN",
    "gn:dem":571,
    "gn:feature_class":"P",
    "gn:feature_code":"PPL",
    "gn:name":"Tuluping",
    "gn:population":0,
    "gn:timezone":"Asia/Shanghai",
    "iso:country":"CN",
    "name:zho_x_preferred":[
        "\u571f\u9e7f\u576a"
    ],
    "wof:name":"Tuluping",
    "wof:placetype":"locality"
},
  "geometry": {"coordinates":[109.3462,27.28365],"type":"Point"}
}