{
  "type": "Feature",
  "properties": {
    "gn:admin1_code":"18",
    "gn:asciiname":"Fengyanpo",
    "gn:country_code":"CN",
    "gn:dem":900,
    "gn:feature_class":"P",
    "gn:feature_code":"PPL",
    "gn:name":"Fengyanpo",
    "gn:population":0,
    "gn:timezone":"Asia/Shanghai",
    "iso:country":"CN",
    "name:zho_x_preferred":[
        "\u8702\u5ca9\u5761"
    ],
    "wof:name":"Fengyanpo",
    "wof:placetype":"locality"
},
  "geometry": {"coordinates":[107.637,27.6434],"type":"Point"}
}