{
  "type": "Feature",
  "properties": {
    "gn:admin1_code":"4.0",
    "gn:asciiname":"Yanling",
    "gn:country_code":"CN",
    "gn:dem":9,
    "gn:feature_class":"P",
    "gn:feature_code":"PPLA4",
    "gn:name":"Yanling",
    "gn:population":0,
    "gn:timezone":"Asia/Shanghai",
    "iso:country":"CN",
    "name:ceb_x_preferred":[
        "Yanling"
    ],
    "name:deu_x_preferred":[
        "Yanling"
    ],
    "name:fra_x_preferred":[
        "Yanling"
    ],
    "name:kor_x_preferred":[
        "\uc60c\ub9c1\ud604"
    ],
    "name:nor_x_preferred":[
        "Yanling"
    ],
    "name:rus_x_preferred":[
        "\u042f\u043d\u044c\u043b\u0438\u043d"
    ],
    "name:swe_x_preferred":[
        "Yanling"
    ],
    "name:und_x_variant":[
        "Yen-ling",
        "Yen-ling-chen",
        "Yanling",
        "Yanling Zhen"
    ],
    "name:zho_x_preferred":[
        "\u5ef6\u9675"
    ],
    "name:zho_x_variant":[
        "\u5ef6\u9675\u9547"
    ],
    "wof:name":"Yanling",
    "wof:placetype":"locality"
},
  "geometry": {"coordinates":[119.47678000000001,31.88071],"type":"Point"}
}