{
  "type": "Feature",
  "properties": {
    "gn:admin1_code":"29.0",
    "gn:asciiname":"Tu'erli",
    "gn:country_code":"CN",
    "gn:dem":1157,
    "gn:feature_class":"P",
    "gn:feature_code":"PPL",
    "gn:name":"Tu\u2019erli",
    "gn:population":0,
    "gn:timezone":"Asia/Shanghai",
    "iso:country":"CN",
    "name:und_x_variant":[
        "Tu\u2019erli"
    ],
    "name:zho_x_preferred":[
        "\u571f\u5c14\u91cc"
    ],
    "wof:name":"Tu'erli",
    "wof:placetype":"locality"
},
  "geometry": {"coordinates":[99.63379999999999,22.7892],"type":"Point"}
}