{
  "type": "Feature",
  "properties": {
    "gn:admin1_code":"11.0",
    "gn:asciiname":"Yanzikou",
    "gn:country_code":"CN",
    "gn:dem":40,
    "gn:feature_class":"P",
    "gn:feature_code":"PPL",
    "gn:name":"Yanzikou",
    "gn:population":0,
    "gn:timezone":"Asia/Shanghai",
    "iso:country":"CN",
    "name:zho_x_preferred":[
        "\u71d5\u5b50\u53e3"
    ],
    "wof:name":"Yanzikou",
    "wof:placetype":"locality"
},
  "geometry": {"coordinates":[111.86326,28.81417],"type":"Point"}
}