{
  "type": "Feature",
  "properties": {
    "gn:admin1_code":"30.0",
    "gn:asciiname":"Bengongdong",
    "gn:country_code":"CN",
    "gn:dem":144,
    "gn:feature_class":"P",
    "gn:feature_code":"PPL",
    "gn:name":"Bengongdong",
    "gn:population":0,
    "gn:timezone":"Asia/Shanghai",
    "iso:country":"CN",
    "name:zho_x_preferred":[
        "Bengongdong"
    ],
    "name:zho_x_variant":[
        "\u672c\u516c\u6d1e"
    ],
    "wof:name":"Bengongdong",
    "wof:placetype":"locality"
},
  "geometry": {"coordinates":[112.41194,24.95],"type":"Point"}
}