{
  "type": "Feature",
  "properties": {
    "gn:admin1_code":"12.0",
    "gn:asciiname":"Jiaoxia",
    "gn:country_code":"CN",
    "gn:dem":89,
    "gn:feature_class":"P",
    "gn:feature_code":"PPL",
    "gn:name":"Jiaoxia",
    "gn:population":0,
    "gn:timezone":"Asia/Shanghai",
    "iso:country":"CN",
    "name:zho_x_preferred":[
        "Jiaoxia"
    ],
    "name:zho_x_variant":[
        "\u7126\u590f"
    ],
    "wof:name":"Jiaoxia",
    "wof:placetype":"locality"
},
  "geometry": {"coordinates":[114.43243,29.61223],"type":"Point"}
}