{
  "type": "Feature",
  "properties": {
    "gn:admin1_code":"25",
    "gn:asciiname":"Peijiazhuang",
    "gn:country_code":"CN",
    "gn:dem":368,
    "gn:feature_class":"P",
    "gn:feature_code":"PPL",
    "gn:name":"Peijiazhuang",
    "gn:population":0,
    "gn:timezone":"Asia/Shanghai",
    "iso:country":"CN",
    "name:zho_x_preferred":[
        "\u88f4\u5bb6\u5e84"
    ],
    "wof:name":"Peijiazhuang",
    "wof:placetype":"locality"
},
  "geometry": {"coordinates":[117.947,36.2246],"type":"Point"}
}