{
  "type": "Feature",
  "properties": {
    "gn:admin1_code":"32.0",
    "gn:asciiname":"Wenjing",
    "gn:country_code":"CN",
    "gn:dem":379,
    "gn:feature_class":"P",
    "gn:feature_code":"PPL",
    "gn:name":"Wenjing",
    "gn:population":0,
    "gn:timezone":"Asia/Shanghai",
    "iso:country":"CN",
    "name:und_x_variant":[
        "Wen-ching",
        "Wenjing"
    ],
    "name:zho_x_preferred":[
        "\u6587\u4e95"
    ],
    "wof:name":"Wenjing",
    "wof:placetype":"locality"
},
  "geometry": {"coordinates":[105.67058,30.87989],"type":"Point"}
}