{
  "type": "Feature",
  "properties": {
    "gn:admin1_code":"14.0",
    "gn:asciiname":"Bazhong",
    "gn:country_code":"CN",
    "gn:dem":3509,
    "gn:feature_class":"P",
    "gn:feature_code":"PPL",
    "gn:name":"Bazhong",
    "gn:population":0,
    "gn:timezone":"Asia/Urumqi",
    "iso:country":"CN",
    "name:ara_x_preferred":[
        "\u0628\u0627\u062a\u0634\u0648\u0646\u063a"
    ],
    "name:cdo_x_preferred":[
        "B\u0103-d\u1e73\u0306ng"
    ],
    "name:ceb_x_preferred":[
        "Bazhong Shi"
    ],
    "name:ces_x_preferred":[
        "Pa-\u010dung"
    ],
    "name:dan_x_preferred":[
        "Bazhong"
    ],
    "name:deu_x_preferred":[
        "Bazhong"
    ],
    "name:eus_x_preferred":[
        "Bazhong"
    ],
    "name:fas_x_preferred":[
        "\u0628\u0627\u0698\u0627\u0646\u06af"
    ],
    "name:fin_x_preferred":[
        "Bazhong"
    ],
    "name:fra_x_preferred":[
        "Bazhong"
    ],
    "name:hak_x_preferred":[
        "P\u00e2-ch\u00fbng-s\u1e73"
    ],
    "name:ita_x_preferred":[
        "Bazhong"
    ],
    "name:jpn_x_preferred":[
        "\u5df4\u4e2d\u5e02"
    ],
    "name:kaz_x_preferred":[
        "\u0411\u0430\u0447\u0436\u0443\u043d"
    ],
    "name:kik_x_preferred":[
        "Bazhong"
    ],
    "name:kor_x_preferred":[
        "\ubc14\uc911\uc2dc"
    ],
    "name:nld_x_preferred":[
        "Bazhong"
    ],
    "name:nno_x_preferred":[
        "Bazhong"
    ],
    "name:nor_x_preferred":[
        "Bazhong"
    ],
    "name:pol_x_preferred":[
        "Bazhong"
    ],
    "name:rus_x_preferred":[
        "\u0411\u0430\u0447\u0436\u0443\u043d"
    ],
    "name:spa_x_preferred":[
        "Bazhong"
    ],
    "name:swe_x_preferred":[
        "Bazhong"
    ],
    "name:tur_x_preferred":[
        "Bazhong"
    ],
    "name:urd_x_preferred":[
        "\u0628\u0627\u0698\u0648\u0646\u06af"
    ],
    "name:vie_x_preferred":[
        "Ba Trung"
    ],
    "name:wuu_x_preferred":[
        "\u5df4\u4e2d\u5e02"
    ],
    "name:zho_x_preferred":[
        "\u5df4\u4e2d"
    ],
    "name:zho_x_variant":[
        "\u5df4\u4e2d\u5e02"
    ],
    "wof:name":"Bazhong",
    "wof:placetype":"locality"
},
  "geometry": {"coordinates":[98.72986,29.89386],"type":"Point"}
}