{
  "type": "Feature",
  "properties": {
    "gn:admin1_code":"14.0",
    "gn:asciiname":"Bazhong",
    "gn:country_code":"CN",
    "gn:dem":3509,
    "gn:feature_class":"P",
    "gn:feature_code":"PPL",
    "gn:name":"Bazhong",
    "gn:population":0,
    "gn:timezone":"Asia/Urumqi",
    "iso:country":"CN",
    "name:zho_x_preferred":[
        "\u5df4\u4e2d"
    ],
    "wof:name":"Bazhong",
    "wof:placetype":"locality"
},
  "geometry": {"coordinates":[98.72986,29.89386],"type":"Point"}
}