{
  "type": "Feature",
  "properties": {
    "gn:admin1_code":"26.0",
    "gn:asciiname":"Dawo",
    "gn:country_code":"CN",
    "gn:dem":1607,
    "gn:feature_class":"P",
    "gn:feature_code":"PPL",
    "gn:name":"Dawo",
    "gn:population":0,
    "gn:timezone":"Asia/Shanghai",
    "iso:country":"CN",
    "name:fra_x_preferred":[
        "Dawo"
    ],
    "name:zho_x_preferred":[
        "\u5927\u7a9d"
    ],
    "wof:name":"Dawo",
    "wof:placetype":"locality"
},
  "geometry": {"coordinates":[109.36541,33.68092],"type":"Point"}
}