{
  "type": "Feature",
  "properties": {
    "gn:admin1_code":"4.0",
    "gn:asciiname":"Wukongqiao",
    "gn:country_code":"CN",
    "gn:dem":5,
    "gn:feature_class":"P",
    "gn:feature_code":"PPL",
    "gn:name":"Wukongqiao",
    "gn:population":0,
    "gn:timezone":"Asia/Shanghai",
    "iso:country":"CN",
    "name:zho_x_preferred":[
        "Wukongqiao"
    ],
    "name:zho_x_variant":[
        "\u609f\u7a7a\u6865"
    ],
    "wof:name":"Wukongqiao",
    "wof:placetype":"locality"
},
  "geometry": {"coordinates":[121.66884,31.95467],"type":"Point"}
}