{
  "type": "Feature",
  "properties": {
    "gn:admin1_code":"9.0",
    "gn:asciiname":"Xiangmahe",
    "gn:country_code":"CN",
    "gn:dem":554,
    "gn:feature_class":"P",
    "gn:feature_code":"PPL",
    "gn:name":"Xiangmahe",
    "gn:population":0,
    "gn:timezone":"Asia/Shanghai",
    "iso:country":"CN",
    "name:und_x_variant":[
        "\u60f3\u9a6c\u6cb3",
        "Xiangmahe"
    ],
    "wof:name":"Xiangmahe",
    "wof:placetype":"locality"
},
  "geometry": {"coordinates":[112.38281000000001,33.71694],"type":"Point"}
}