{
  "type": "Feature",
  "properties": {
    "gn:admin1_code":"31",
    "gn:asciiname":"Huangling Nongchang",
    "gn:country_code":"CN",
    "gn:dem":118,
    "gn:feature_class":"P",
    "gn:feature_code":"PPLF",
    "gn:name":"Huangling Nongchang",
    "gn:population":0,
    "gn:timezone":"Asia/Shanghai",
    "iso:country":"CN",
    "name:und_x_variant":[
        "\u9ec4\u5cad\u519c\u573a"
    ],
    "wof:name":"Huangling Nongchang",
    "wof:placetype":"locality"
},
  "geometry": {"coordinates":[109.95822,19.37758],"type":"Point"}
}