{
  "type": "Feature",
  "properties": {
    "gn:admin1_code":"19.0",
    "gn:asciiname":"Beixiaowacun",
    "gn:country_code":"CN",
    "gn:dem":4,
    "gn:feature_class":"P",
    "gn:feature_code":"PPL",
    "gn:name":"Beixiaowacun",
    "gn:population":0,
    "gn:timezone":"Asia/Shanghai",
    "iso:country":"CN",
    "name:zho_x_preferred":[
        "\u5317\u5c0f\u6d3c\u6751"
    ],
    "wof:name":"Beixiaowacun",
    "wof:placetype":"locality"
},
  "geometry": {"coordinates":[122.063,41.0464],"type":"Point"}
}