{
  "type": "Feature",
  "properties": {
    "gn:admin1_code":"30.0",
    "gn:asciiname":"Shantangxia",
    "gn:country_code":"CN",
    "gn:dem":24,
    "gn:feature_class":"P",
    "gn:feature_code":"PPL",
    "gn:name":"Shantangxia",
    "gn:population":0,
    "gn:timezone":"Asia/Shanghai",
    "iso:country":"CN",
    "name:zho_x_preferred":[
        "\u5c71\u5858\u4e0b"
    ],
    "wof:name":"Shantangxia",
    "wof:placetype":"locality"
},
  "geometry": {"coordinates":[112.40233000000001,22.1556],"type":"Point"}
}