{
  "type": "Feature",
  "properties": {
    "gn:admin1_code":"15.0",
    "gn:asciiname":"Shigaokuang",
    "gn:country_code":"CN",
    "gn:dem":1842,
    "gn:feature_class":"P",
    "gn:feature_code":"PPL",
    "gn:name":"Shigaokuang",
    "gn:population":0,
    "gn:timezone":"Asia/Shanghai",
    "iso:country":"CN",
    "name:zho_x_preferred":[
        "\u77f3\u818f\u77ff"
    ],
    "wof:name":"Shigaokuang",
    "wof:placetype":"locality"
},
  "geometry": {"coordinates":[103.889,37.2545],"type":"Point"}
}