{
  "type": "Feature",
  "properties": {
    "gn:admin1_code":"26.0",
    "gn:asciiname":"Zhenggoucun",
    "gn:country_code":"CN",
    "gn:dem":488,
    "gn:feature_class":"P",
    "gn:feature_code":"PPL",
    "gn:name":"Zhenggoucun",
    "gn:population":0,
    "gn:timezone":"Asia/Shanghai",
    "iso:country":"CN",
    "name:zho_x_preferred":[
        "\u6b63\u6c9f\u6751"
    ],
    "wof:name":"Zhenggoucun",
    "wof:placetype":"locality"
},
  "geometry": {"coordinates":[108.83938999999999,32.48188],"type":"Point"}
}