{
  "type": "Feature",
  "properties": {
    "gn:admin1_code":"32.0",
    "gn:asciiname":"Jueluo",
    "gn:country_code":"CN",
    "gn:dem":1907,
    "gn:feature_class":"P",
    "gn:feature_code":"PPL",
    "gn:name":"Jueluo",
    "gn:population":0,
    "gn:timezone":"Asia/Shanghai",
    "iso:country":"CN",
    "name:zho_x_preferred":[
        "\u89c9\u6d1b"
    ],
    "wof:name":"Jueluo",
    "wof:placetype":"locality"
},
  "geometry": {"coordinates":[103.11613,28.41092],"type":"Point"}
}