{
  "type": "Feature",
  "properties": {
    "gn:admin1_code":"21.0",
    "gn:asciiname":"Tangjiapo",
    "gn:country_code":"CN",
    "gn:dem":2026,
    "gn:feature_class":"P",
    "gn:feature_code":"PPL",
    "gn:name":"Tangjiapo",
    "gn:population":0,
    "gn:timezone":"Asia/Shanghai",
    "iso:country":"CN",
    "name:zho_x_preferred":[
        "\u5510\u5bb6\u5761"
    ],
    "wof:name":"Tangjiapo",
    "wof:placetype":"locality"
},
  "geometry": {"coordinates":[105.235,36.6767],"type":"Point"}
}