{
  "type": "Feature",
  "properties": {
    "gn:admin1_code":"7",
    "gn:asciiname":"Shangdeng",
    "gn:country_code":"CN",
    "gn:dem":326,
    "gn:feature_class":"P",
    "gn:feature_code":"PPL",
    "gn:name":"Shangdeng",
    "gn:population":0,
    "gn:timezone":"Asia/Shanghai",
    "iso:country":"CN",
    "name:zho_x_preferred":[
        "\u4e0a\u767b"
    ],
    "wof:name":"Shangdeng",
    "wof:placetype":"locality"
},
  "geometry": {"coordinates":[116.38556,24.99194],"type":"Point"}
}