{
  "type": "Feature",
  "properties": {
    "gn:admin1_code":"3",
    "gn:asciiname":"Xishanxian",
    "gn:country_code":"CN",
    "gn:dem":179,
    "gn:feature_class":"P",
    "gn:feature_code":"PPL",
    "gn:name":"Xishanxian",
    "gn:population":0,
    "gn:timezone":"Asia/Shanghai",
    "iso:country":"CN",
    "name:zho_x_preferred":[
        "\u897f\u5c71\u5f26"
    ],
    "wof:name":"Xishanxian",
    "wof:placetype":"locality"
},
  "geometry": {"coordinates":[114.86799999999999,26.3998],"type":"Point"}
}