{
  "type": "Feature",
  "properties": {
    "gn:admin1_code":"8.0",
    "gn:asciiname":"Yuhong",
    "gn:country_code":"CN",
    "gn:dem":90,
    "gn:feature_class":"P",
    "gn:feature_code":"PPL",
    "gn:name":"Yuhong",
    "gn:population":0,
    "gn:timezone":"Asia/Shanghai",
    "iso:country":"CN",
    "name:zho_x_preferred":[
        "\u80b2\u7ea2"
    ],
    "wof:name":"Yuhong",
    "wof:placetype":"locality"
},
  "geometry": {"coordinates":[129.92807999999999,49.02103],"type":"Point"}
}