{
  "type": "Feature",
  "properties": {
    "gn:admin1_code":"5.0",
    "gn:asciiname":"Xintian Dadui Renshenchang",
    "gn:country_code":"CN",
    "gn:dem":331,
    "gn:feature_class":"P",
    "gn:feature_code":"PPLF",
    "gn:name":"Xintian Dadui Renshenchang",
    "gn:population":0,
    "gn:timezone":"Asia/Shanghai",
    "iso:country":"CN",
    "name:und_x_variant":[
        "\u65b0\u7530\u5927\u961f\u4eba\u53c2\u573a"
    ],
    "wof:name":"Xintian Dadui Renshenchang",
    "wof:placetype":"locality"
},
  "geometry": {"coordinates":[129.56646000000001,43.20072],"type":"Point"}
}