{
  "type": "Feature",
  "properties": {
    "gn:admin1_code":"11",
    "gn:asciiname":"Zhouhetang",
    "gn:country_code":"CN",
    "gn:dem":108,
    "gn:feature_class":"P",
    "gn:feature_code":"PPL",
    "gn:name":"Zhouhetang",
    "gn:population":0,
    "gn:timezone":"Asia/Shanghai",
    "iso:country":"CN",
    "name:zho_x_preferred":[
        "\u5468\u79be\u5858"
    ],
    "wof:name":"Zhouhetang",
    "wof:placetype":"locality"
},
  "geometry": {"coordinates":[111.71083,26.43689],"type":"Point"}
}