{
  "type": "Feature",
  "properties": {
    "gn:admin1_code":"32.0",
    "gn:asciiname":"Risegong",
    "gn:country_code":"CN",
    "gn:dem":3974,
    "gn:feature_class":"P",
    "gn:feature_code":"PPL",
    "gn:name":"Risegong",
    "gn:population":0,
    "gn:timezone":"Asia/Shanghai",
    "iso:country":"CN",
    "name:zho_x_preferred":[
        "\u65e5\u8272\u8d21"
    ],
    "wof:name":"Risegong",
    "wof:placetype":"locality"
},
  "geometry": {"coordinates":[99.5121,29.0157],"type":"Point"}
}