{
  "type": "Feature",
  "properties": {
    "gn:admin1_code":"2.0",
    "gn:asciiname":"Yuzhai",
    "gn:country_code":"CN",
    "gn:dem":332,
    "gn:feature_class":"P",
    "gn:feature_code":"PPL",
    "gn:name":"Yuzhai",
    "gn:population":0,
    "gn:timezone":"Asia/Shanghai",
    "iso:country":"CN",
    "name:swe_x_preferred":[
        "Yuzhai"
    ],
    "name:zho_x_preferred":[
        "\u55bb\u5b85"
    ],
    "wof:name":"Yuzhai",
    "wof:placetype":"locality"
},
  "geometry": {"coordinates":[119.87403999999999,28.10594],"type":"Point"}
}