{
  "type": "Feature",
  "properties": {
    "gn:admin1_code":"4.0",
    "gn:asciiname":"Fuxing",
    "gn:country_code":"CN",
    "gn:dem":8,
    "gn:feature_class":"P",
    "gn:feature_code":"PPL",
    "gn:name":"Fuxing",
    "gn:population":0,
    "gn:timezone":"Asia/Shanghai",
    "iso:country":"CN",
    "name:zho_x_preferred":[
        "Fuxing"
    ],
    "name:zho_x_variant":[
        "\u526f\u5174"
    ],
    "wof:name":"Fuxing",
    "wof:placetype":"locality"
},
  "geometry": {"coordinates":[119.26904999999999,33.07955],"type":"Point"}
}