{
  "type": "Feature",
  "properties": {
    "gn:admin1_code":"8.0",
    "gn:asciiname":"Jinshengtaitun",
    "gn:country_code":"CN",
    "gn:dem":196,
    "gn:feature_class":"P",
    "gn:feature_code":"PPL",
    "gn:name":"Jinshengtaitun",
    "gn:population":0,
    "gn:timezone":"Asia/Shanghai",
    "iso:country":"CN",
    "name:zho_x_preferred":[
        "\u91d1\u751f\u592a\u5c6f"
    ],
    "wof:name":"Jinshengtaitun",
    "wof:placetype":"locality"
},
  "geometry": {"coordinates":[125.96616000000002,46.84971],"type":"Point"}
}