{
  "type": "Feature",
  "properties": {
    "gn:admin1_code":"3.0",
    "gn:asciiname":"Yanfang",
    "gn:country_code":"CN",
    "gn:dem":143,
    "gn:feature_class":"P",
    "gn:feature_code":"PPL",
    "gn:name":"Yanfang",
    "gn:population":0,
    "gn:timezone":"Asia/Shanghai",
    "iso:country":"CN",
    "name:und_x_variant":[
        "\u4e25\u574a"
    ],
    "wof:name":"Yanfang",
    "wof:placetype":"locality"
},
  "geometry": {"coordinates":[116.65097,28.16808],"type":"Point"}
}