{
  "type": "Feature",
  "properties": {
    "gn:admin1_code":"16.0",
    "gn:asciiname":"Na'ai",
    "gn:country_code":"CN",
    "gn:dem":703,
    "gn:feature_class":"P",
    "gn:feature_code":"PPL",
    "gn:name":"Na\u2019ai",
    "gn:population":0,
    "gn:timezone":"Asia/Shanghai",
    "iso:country":"CN",
    "name:und_x_variant":[
        "Na\u2019ai"
    ],
    "name:zho_x_preferred":[
        "\u90a3\u7231"
    ],
    "wof:name":"Na'ai",
    "wof:placetype":"locality"
},
  "geometry": {"coordinates":[107.23999999999999,24.5437],"type":"Point"}
}