{
  "type": "Feature",
  "properties": {
    "gn:admin1_code":"25",
    "gn:asciiname":"Changzuo",
    "gn:country_code":"CN",
    "gn:dem":133,
    "gn:feature_class":"P",
    "gn:feature_code":"PPL",
    "gn:name":"Changzuo",
    "gn:population":0,
    "gn:timezone":"Asia/Shanghai",
    "iso:country":"CN",
    "name:zho_x_preferred":[
        "\u957f\u5ea7"
    ],
    "wof:name":"Changzuo",
    "wof:placetype":"locality"
},
  "geometry": {"coordinates":[117.21899999999999,35.4635],"type":"Point"}
}