{
  "type": "Feature",
  "properties": {
    "gn:admin1_code":"16.0",
    "gn:asciiname":"Bugou",
    "gn:country_code":"CN",
    "gn:dem":1379,
    "gn:feature_class":"P",
    "gn:feature_code":"PPL",
    "gn:name":"Bugou",
    "gn:population":0,
    "gn:timezone":"Asia/Shanghai",
    "iso:country":"CN",
    "name:zho_x_preferred":[
        "\u6b65\u6c9f"
    ],
    "wof:name":"Bugou",
    "wof:placetype":"locality"
},
  "geometry": {"coordinates":[105.54600000000001,24.5698],"type":"Point"}
}