{
  "type": "Feature",
  "properties": {
    "gn:admin1_code":"30",
    "gn:asciiname":"Shagu",
    "gn:country_code":"CN",
    "gn:dem":28,
    "gn:feature_class":"P",
    "gn:feature_code":"PPL",
    "gn:name":"Shagu",
    "gn:population":0,
    "gn:timezone":"Asia/Urumqi",
    "iso:country":"CN",
    "name:und_x_variant":[
        "\u6c99\u53e4",
        "Shagu"
    ],
    "wof:name":"Shagu",
    "wof:placetype":"locality"
},
  "geometry": {"coordinates":[110.06462000000001,21.40863],"type":"Point"}
}