{
  "type": "Feature",
  "properties": {
    "gn:admin1_code":"15.0",
    "gn:asciiname":"Majiaxian",
    "gn:country_code":"CN",
    "gn:dem":2055,
    "gn:feature_class":"P",
    "gn:feature_code":"PPL",
    "gn:name":"Majiaxian",
    "gn:population":0,
    "gn:timezone":"Asia/Shanghai",
    "iso:country":"CN",
    "name:zho_x_preferred":[
        "\u9ebb\u5bb6\u5c98"
    ],
    "wof:name":"Majiaxian",
    "wof:placetype":"locality"
},
  "geometry": {"coordinates":[104.444,35.7665],"type":"Point"}
}