{
  "type": "Feature",
  "properties": {
    "gn:admin1_code":"1.0",
    "gn:asciiname":"Beixucun",
    "gn:country_code":"CN",
    "gn:dem":14,
    "gn:feature_class":"P",
    "gn:feature_code":"PPL",
    "gn:name":"Beixucun",
    "gn:population":0,
    "gn:timezone":"Asia/Shanghai",
    "iso:country":"CN",
    "name:zho_x_preferred":[
        "\u5317\u5f90\u6751"
    ],
    "wof:name":"Beixucun",
    "wof:placetype":"locality"
},
  "geometry": {"coordinates":[117.34166999999999,31.74432],"type":"Point"}
}