{
  "type": "Feature",
  "properties": {
    "gn:admin1_code":"10",
    "gn:asciiname":"Gaoxindian",
    "gn:country_code":"CN",
    "gn:dem":23,
    "gn:feature_class":"P",
    "gn:feature_code":"PPL",
    "gn:name":"Gaoxindian",
    "gn:population":0,
    "gn:timezone":"Asia/Shanghai",
    "iso:country":"CN",
    "name:zho_x_preferred":[
        "\u9ad8\u8f9b\u5e97"
    ],
    "wof:name":"Gaoxindian",
    "wof:placetype":"locality"
},
  "geometry": {"coordinates":[116.22284999999999,37.61705],"type":"Point"}
}