{
  "type": "Feature",
  "properties": {
    "gn:admin1_code":"10",
    "gn:asciiname":"Beidougong",
    "gn:country_code":"CN",
    "gn:dem":67,
    "gn:feature_class":"P",
    "gn:feature_code":"PPL",
    "gn:name":"Beidougong",
    "gn:population":0,
    "gn:timezone":"Asia/Shanghai",
    "iso:country":"CN",
    "name:zho_x_preferred":[
        "\u5317\u8c46\u516c"
    ],
    "wof:name":"Beidougong",
    "wof:placetype":"locality"
},
  "geometry": {"coordinates":[114.476,36.464],"type":"Point"}
}