{
  "type": "Feature",
  "properties": {
    "gn:admin1_code":"07",
    "gn:asciiname":"Wandai",
    "gn:country_code":"CN",
    "gn:dem":590,
    "gn:feature_class":"P",
    "gn:feature_code":"PPL",
    "gn:name":"Wandai",
    "gn:population":0,
    "gn:timezone":"Asia/Shanghai",
    "iso:country":"CN",
    "name:zho_x_preferred":[
        "\u4e07\u4ee3"
    ],
    "wof:name":"Wandai",
    "wof:placetype":"locality"
},
  "geometry": {"coordinates":[118.07469,25.34419],"type":"Point"}
}