{
  "type": "Feature",
  "properties": {
    "gn:admin1_code":"30.0",
    "gn:asciiname":"Tianzhongjian",
    "gn:country_code":"CN",
    "gn:dem":59,
    "gn:feature_class":"P",
    "gn:feature_code":"PPL",
    "gn:name":"Tianzhongjian",
    "gn:population":0,
    "gn:timezone":"Asia/Shanghai",
    "iso:country":"CN",
    "name:zho_x_preferred":[
        "\u7530\u4e2d\u95f4"
    ],
    "wof:name":"Tianzhongjian",
    "wof:placetype":"locality"
},
  "geometry": {"coordinates":[113.52075000000001,23.64298],"type":"Point"}
}