{
  "type": "Feature",
  "properties": {
    "gn:admin1_code":"29.0",
    "gn:asciiname":"Da'eduo",
    "gn:country_code":"CN",
    "gn:dem":1829,
    "gn:feature_class":"P",
    "gn:feature_code":"PPL",
    "gn:name":"Da\u2019eduo",
    "gn:population":0,
    "gn:timezone":"Asia/Shanghai",
    "iso:country":"CN",
    "name:und_x_variant":[
        "Da\u2019eduo"
    ],
    "name:zho_x_preferred":[
        "\u6253\u4fc4\u6735"
    ],
    "wof:name":"Da'eduo",
    "wof:placetype":"locality"
},
  "geometry": {"coordinates":[98.93000000000001,27.2566],"type":"Point"}
}