{
  "type": "Feature",
  "properties": {
    "gn:admin1_code":"6.0",
    "gn:asciiname":"Caijin",
    "gn:country_code":"CN",
    "gn:dem":4339,
    "gn:feature_class":"P",
    "gn:feature_code":"PPL",
    "gn:name":"Caijin",
    "gn:population":0,
    "gn:timezone":"Asia/Urumqi",
    "iso:country":"CN",
    "name:zho_x_preferred":[
        "\u91c7\u5c3d"
    ],
    "wof:name":"Caijin",
    "wof:placetype":"locality"
},
  "geometry": {"coordinates":[96.30544,32.20122],"type":"Point"}
}