{
  "type": "Feature",
  "properties": {
    "gn:admin1_code":"8.0",
    "gn:asciiname":"Qingmingcun",
    "gn:country_code":"CN",
    "gn:dem":179,
    "gn:feature_class":"P",
    "gn:feature_code":"PPL",
    "gn:name":"Qingmingcun",
    "gn:population":0,
    "gn:timezone":"Asia/Shanghai",
    "iso:country":"CN",
    "name:zho_x_preferred":[
        "\u6e05\u660e\u6751"
    ],
    "wof:name":"Qingmingcun",
    "wof:placetype":"locality"
},
  "geometry": {"coordinates":[127.27381,46.44778],"type":"Point"}
}