{
  "type": "Feature",
  "properties": {
    "gn:admin1_code":"4.0",
    "gn:asciiname":"Niuwan",
    "gn:country_code":"CN",
    "gn:dem":9,
    "gn:feature_class":"P",
    "gn:feature_code":"PPL",
    "gn:name":"Niuwan",
    "gn:population":0,
    "gn:timezone":"Asia/Shanghai",
    "iso:country":"CN",
    "name:zho_x_preferred":[
        "\u94ae\u6e7e"
    ],
    "wof:name":"Niuwan",
    "wof:placetype":"locality"
},
  "geometry": {"coordinates":[118.87952,34.08058],"type":"Point"}
}