{
  "type": "Feature",
  "properties": {
    "gn:admin1_code":"5.0",
    "gn:asciiname":"Shuilongkou",
    "gn:country_code":"CN",
    "gn:dem":197,
    "gn:feature_class":"P",
    "gn:feature_code":"PPL",
    "gn:name":"Shuilongkou",
    "gn:population":0,
    "gn:timezone":"Asia/Shanghai",
    "iso:country":"CN",
    "name:zho_x_preferred":[
        "\u6c34\u9f99\u53e3"
    ],
    "wof:name":"Shuilongkou",
    "wof:placetype":"locality"
},
  "geometry": {"coordinates":[124.65398,44.78404000000001],"type":"Point"}
}