{
  "type": "Feature",
  "properties": {
    "gn:admin1_code":"11.0",
    "gn:asciiname":"Shangnanyuan",
    "gn:country_code":"CN",
    "gn:dem":190,
    "gn:feature_class":"P",
    "gn:feature_code":"PPL",
    "gn:name":"Shangnanyuan",
    "gn:population":0,
    "gn:timezone":"Asia/Shanghai",
    "iso:country":"CN",
    "name:zho_x_preferred":[
        "\u4e0a\u5357\u6e90"
    ],
    "wof:name":"Shangnanyuan",
    "wof:placetype":"locality"
},
  "geometry": {"coordinates":[113.55488,28.65908],"type":"Point"}
}