{
  "type": "Feature",
  "properties": {
    "gn:admin1_code":"20.0",
    "gn:asciiname":"Majige'ersuhai",
    "gn:country_code":"CN",
    "gn:dem":1022,
    "gn:feature_class":"P",
    "gn:feature_code":"PPL",
    "gn:name":"Majige\u2019ersuhai",
    "gn:population":0,
    "gn:timezone":"Asia/Shanghai",
    "iso:country":"CN",
    "name:und_x_variant":[
        "Majige\u2019ersuhai"
    ],
    "name:zho_x_preferred":[
        "\u739b\u5409\u683c\u5c14\u82cf\u4ea5"
    ],
    "wof:name":"Majige'ersuhai",
    "wof:placetype":"locality"
},
  "geometry": {"coordinates":[100.43277,41.37156],"type":"Point"}
}