{
  "type": "Feature",
  "properties": {
    "gn:admin1_code":"15",
    "gn:asciiname":"Guojiayao",
    "gn:country_code":"CN",
    "gn:dem":2249,
    "gn:feature_class":"P",
    "gn:feature_code":"PPL",
    "gn:name":"Guojiayao",
    "gn:population":0,
    "gn:timezone":"Asia/Shanghai",
    "iso:country":"CN",
    "name:zho_x_preferred":[
        "\u90ed\u5bb6\u7a91"
    ],
    "wof:name":"Guojiayao",
    "wof:placetype":"locality"
},
  "geometry": {"coordinates":[104.23099999999999,36.9991],"type":"Point"}
}