{
  "type": "Feature",
  "properties": {
    "gn:admin1_code":"15.0",
    "gn:asciiname":"Zhuandong",
    "gn:country_code":"CN",
    "gn:dem":1096,
    "gn:feature_class":"P",
    "gn:feature_code":"PPL",
    "gn:name":"Zhuandong",
    "gn:population":0,
    "gn:timezone":"Asia/Shanghai",
    "iso:country":"CN",
    "name:zho_x_preferred":[
        "\u7816\u6d1e"
    ],
    "wof:name":"Zhuandong",
    "wof:placetype":"locality"
},
  "geometry": {"coordinates":[108.163,35.591],"type":"Point"}
}