{
  "type": "Feature",
  "properties": {
    "gn:admin1_code":"2.0",
    "gn:asciiname":"Qiaomaiwu",
    "gn:country_code":"CN",
    "gn:dem":203,
    "gn:feature_class":"P",
    "gn:feature_code":"PPL",
    "gn:name":"Qiaomaiwu",
    "gn:population":0,
    "gn:timezone":"Asia/Shanghai",
    "iso:country":"CN",
    "name:zho_x_preferred":[
        "\u835e\u9ea6\u575e"
    ],
    "wof:name":"Qiaomaiwu",
    "wof:placetype":"locality"
},
  "geometry": {"coordinates":[118.51456,28.44816],"type":"Point"}
}