{
  "type": "Feature",
  "properties": {
    "gn:admin1_code":"4.0",
    "gn:asciiname":"Zhangbaoshancun",
    "gn:country_code":"CN",
    "gn:dem":2,
    "gn:feature_class":"P",
    "gn:feature_code":"PPL",
    "gn:name":"Zhangbaoshancun",
    "gn:population":0,
    "gn:timezone":"Asia/Shanghai",
    "iso:country":"CN",
    "name:zho_x_preferred":[
        "\u5f20\u5b9d\u5c71\u6751"
    ],
    "wof:name":"Zhangbaoshancun",
    "wof:placetype":"locality"
},
  "geometry": {"coordinates":[119.43926999999999,34.42029],"type":"Point"}
}