{
  "type": "Feature",
  "properties": {
    "gn:admin1_code":"19.0",
    "gn:asciiname":"Suliyingzi",
    "gn:country_code":"CN",
    "gn:dem":287,
    "gn:feature_class":"P",
    "gn:feature_code":"PPL",
    "gn:name":"Suliyingzi",
    "gn:population":0,
    "gn:timezone":"Asia/Shanghai",
    "iso:country":"CN",
    "name:und_x_variant":[
        "\u82cf\u529b\u8425\u5b50"
    ],
    "name:zho_x_preferred":[
        "\u82cf\u529b\u8425\u5b50"
    ],
    "wof:name":"Suliyingzi",
    "wof:placetype":"locality"
},
  "geometry": {"coordinates":[121.752,42.277],"type":"Point"}
}