{
  "type": "Feature",
  "properties": {
    "gn:admin1_code":"29.0",
    "gn:asciiname":"Zengjia Pingzi",
    "gn:country_code":"CN",
    "gn:dem":1690,
    "gn:feature_class":"P",
    "gn:feature_code":"PPL",
    "gn:name":"Zengjia Pingzi",
    "gn:population":0,
    "gn:timezone":"Asia/Shanghai",
    "iso:country":"CN",
    "name:zho_x_preferred":[
        "\u66fe\u5bb6\u576a\u5b50"
    ],
    "wof:name":"Zengjia Pingzi",
    "wof:placetype":"locality"
},
  "geometry": {"coordinates":[104.483,26.5139],"type":"Point"}
}