{
  "type": "Feature",
  "properties": {
    "gn:admin1_code":"16.0",
    "gn:asciiname":"Yalong",
    "gn:country_code":"CN",
    "gn:dem":148,
    "gn:feature_class":"P",
    "gn:feature_code":"PPL",
    "gn:name":"Yalong",
    "gn:population":0,
    "gn:timezone":"Asia/Shanghai",
    "iso:country":"CN",
    "name:nld_x_preferred":[
        "Yalong"
    ],
    "name:zho_x_preferred":[
        "\u96c5\u9f99"
    ],
    "wof:name":"Yalong",
    "wof:placetype":"locality"
},
  "geometry": {"coordinates":[108.914,24.9785],"type":"Point"}
}