{
  "type": "Feature",
  "properties": {
    "gn:admin1_code":"10.0",
    "gn:asciiname":"Nanhe",
    "gn:country_code":"CN",
    "gn:dem":203,
    "gn:feature_class":"P",
    "gn:feature_code":"PPL",
    "gn:name":"Nanhe",
    "gn:population":0,
    "gn:timezone":"Asia/Shanghai",
    "iso:country":"CN",
    "name:und_x_variant":[
        "\u5357\u6cb3"
    ],
    "wof:name":"Nanhe",
    "wof:placetype":"locality"
},
  "geometry": {"coordinates":[114.48336999999999,38.61734000000001],"type":"Point"}
}