{
  "type": "Feature",
  "properties": {
    "gn:admin1_code":"25.0",
    "gn:asciiname":"Xiujia",
    "gn:country_code":"CN",
    "gn:dem":54,
    "gn:feature_class":"P",
    "gn:feature_code":"PPL",
    "gn:name":"Xiujia",
    "gn:population":0,
    "gn:timezone":"Asia/Shanghai",
    "iso:country":"CN",
    "name:zho_x_preferred":[
        "\u4fee\u5bb6"
    ],
    "wof:name":"Xiujia",
    "wof:placetype":"locality"
},
  "geometry": {"coordinates":[120.98278999999999,36.7033],"type":"Point"}
}