{
  "type": "Feature",
  "properties": {
    "gn:admin1_code":"29",
    "gn:asciiname":"Liujie",
    "gn:country_code":"CN",
    "gn:dem":1803,
    "gn:feature_class":"P",
    "gn:feature_code":"PPL",
    "gn:name":"Liujie",
    "gn:population":0,
    "gn:timezone":"Asia/Shanghai",
    "iso:country":"CN",
    "name:zho_x_preferred":[
        "\u516d\u8857"
    ],
    "wof:name":"Liujie",
    "wof:placetype":"locality"
},
  "geometry": {"coordinates":[102.76000000000001,24.1875],"type":"Point"}
}