{
  "type": "Feature",
  "properties": {
    "gn:admin1_code":"7",
    "gn:asciiname":"Chijiao",
    "gn:country_code":"CN",
    "gn:dem":14,
    "gn:feature_class":"P",
    "gn:feature_code":"PPL",
    "gn:name":"Chijiao",
    "gn:population":0,
    "gn:timezone":"Asia/Shanghai",
    "iso:country":"CN",
    "name:und_x_variant":[
        "Ch\u2019ih-chiao",
        "Chijiao"
    ],
    "name:zho_x_preferred":[
        "\u8d64\u7901"
    ],
    "wof:name":"Chijiao",
    "wof:placetype":"locality"
},
  "geometry": {"coordinates":[119.50435,25.43829],"type":"Point"}
}