{
  "type": "Feature",
  "properties": {
    "gn:admin1_code":"10.0",
    "gn:asciiname":"Ying'er",
    "gn:country_code":"CN",
    "gn:dem":790,
    "gn:feature_class":"P",
    "gn:feature_code":"PPL",
    "gn:name":"Ying\u2019er",
    "gn:population":0,
    "gn:timezone":"Asia/Shanghai",
    "iso:country":"CN",
    "name:und_x_variant":[
        "Ying\u2019er"
    ],
    "name:zho_x_preferred":[
        "\u8425\u5c14"
    ],
    "wof:name":"Ying'er",
    "wof:placetype":"locality"
},
  "geometry": {"coordinates":[114.77412,39.25589],"type":"Point"}
}