{
  "type": "Feature",
  "properties": {
    "gn:admin1_code":"14.0",
    "gn:asciiname":"Kaqiuchukucun",
    "gn:country_code":"CN",
    "gn:dem":4944,
    "gn:feature_class":"P",
    "gn:feature_code":"PPL",
    "gn:name":"Kaqiuchukucun",
    "gn:population":0,
    "gn:timezone":"Asia/Urumqi",
    "iso:country":"CN",
    "name:zho_x_preferred":[
        "\u5494\u79cb\u695a\u5e93\u6751"
    ],
    "wof:name":"Kaqiuchukucun",
    "wof:placetype":"locality"
},
  "geometry": {"coordinates":[91.8154,31.01003],"type":"Point"}
}