{
  "type": "Feature",
  "properties": {
    "gn:admin1_code":"11.0",
    "gn:asciiname":"Zhujiajiao",
    "gn:country_code":"CN",
    "gn:dem":93,
    "gn:feature_class":"P",
    "gn:feature_code":"PPL",
    "gn:name":"Zhujiajiao",
    "gn:population":0,
    "gn:timezone":"Asia/Shanghai",
    "iso:country":"CN",
    "name:ceb_x_preferred":[
        "Zhujiajiao"
    ],
    "name:deu_x_preferred":[
        "Zhujiajiao"
    ],
    "name:fas_x_preferred":[
        "\u0698\u0648\u062c\u06cc\u0627\u062c\u06cc\u0627\u0648"
    ],
    "name:fin_x_preferred":[
        "Zhujiajiao"
    ],
    "name:jpn_x_preferred":[
        "\u6731\u5bb6\u89d2\u93ae"
    ],
    "name:kor_x_preferred":[
        "\uc8fc\uc790\uc790\uc624"
    ],
    "name:mlg_x_preferred":[
        "Zhujiajiao"
    ],
    "name:nor_x_preferred":[
        "Zhujiajiao"
    ],
    "name:ron_x_preferred":[
        "Zhujiajiao"
    ],
    "name:swe_x_preferred":[
        "Zhujiajiao"
    ],
    "name:wuu_x_preferred":[
        "\u6731\u5bb6\u89d2"
    ],
    "name:zho_x_preferred":[
        "\u6731\u5bb6\u811a"
    ],
    "name:zho_x_variant":[
        "\u6731\u5bb6\u89d2\u9547"
    ],
    "wof:name":"Zhujiajiao",
    "wof:placetype":"locality"
},
  "geometry": {"coordinates":[112.79516,26.78888],"type":"Point"}
}