{
  "type": "Feature",
  "properties": {
    "gn:admin1_code":"32.0",
    "gn:asciiname":"Caochang",
    "gn:country_code":"CN",
    "gn:dem":1315,
    "gn:feature_class":"P",
    "gn:feature_code":"PPL",
    "gn:name":"Caochang",
    "gn:population":0,
    "gn:timezone":"Asia/Shanghai",
    "iso:country":"CN",
    "name:zho_x_preferred":[
        "\u8349\u573a"
    ],
    "wof:name":"Caochang",
    "wof:placetype":"locality"
},
  "geometry": {"coordinates":[102.08275999999999,26.93477],"type":"Point"}
}