{
  "type": "Feature",
  "properties": {
    "gn:admin1_code":"32.0",
    "gn:asciiname":"Jinshitou",
    "gn:country_code":"CN",
    "gn:dem":453,
    "gn:feature_class":"P",
    "gn:feature_code":"PPL",
    "gn:name":"Jinshitou",
    "gn:population":0,
    "gn:timezone":"Asia/Shanghai",
    "iso:country":"CN",
    "name:zho_x_preferred":[
        "\u91d1\u77f3\u5934"
    ],
    "wof:name":"Jinshitou",
    "wof:placetype":"locality"
},
  "geometry": {"coordinates":[106.643,31.5329],"type":"Point"}
}