{
  "type": "Feature",
  "properties": {
    "gn:admin1_code":"29.0",
    "gn:asciiname":"Digubai Laozhai",
    "gn:country_code":"CN",
    "gn:dem":1038,
    "gn:feature_class":"P",
    "gn:feature_code":"PPL",
    "gn:name":"Digubai Laozhai",
    "gn:population":0,
    "gn:timezone":"Asia/Shanghai",
    "iso:country":"CN",
    "name:zho_x_preferred":[
        "\u5730\u53e4\u767d\u8001\u5be8"
    ],
    "wof:name":"Digubai Laozhai",
    "wof:placetype":"locality"
},
  "geometry": {"coordinates":[103.504,23.0065],"type":"Point"}
}