{
  "type": "Feature",
  "properties": {
    "gn:admin1_code":"1.0",
    "gn:asciiname":"Hebaocun",
    "gn:country_code":"CN",
    "gn:dem":18,
    "gn:feature_class":"P",
    "gn:feature_code":"PPL",
    "gn:name":"Hebaocun",
    "gn:population":0,
    "gn:timezone":"Asia/Shanghai",
    "iso:country":"CN",
    "name:zho_x_preferred":[
        "\u8377\u82de\u6751"
    ],
    "wof:name":"Hebaocun",
    "wof:placetype":"locality"
},
  "geometry": {"coordinates":[116.63249999999999,30.35142],"type":"Point"}
}