{
  "type": "Feature",
  "properties": {
    "gn:admin1_code":"29.0",
    "gn:asciiname":"Habiedeka",
    "gn:country_code":"CN",
    "gn:dem":1888,
    "gn:feature_class":"P",
    "gn:feature_code":"PPL",
    "gn:name":"Habiedeka",
    "gn:population":0,
    "gn:timezone":"Asia/Shanghai",
    "iso:country":"CN",
    "name:zho_x_preferred":[
        "\u54c8\u522b\u7684\u5361"
    ],
    "wof:name":"Habiedeka",
    "wof:placetype":"locality"
},
  "geometry": {"coordinates":[99.7166,23.038],"type":"Point"}
}