{
  "type": "Feature",
  "properties": {
    "gn:admin1_code":"7",
    "gn:asciiname":"Danchi",
    "gn:country_code":"CN",
    "gn:dem":889,
    "gn:feature_class":"P",
    "gn:feature_code":"PPL",
    "gn:name":"Danchi",
    "gn:population":0,
    "gn:timezone":"Asia/Shanghai",
    "iso:country":"CN",
    "name:und_x_variant":[
        "\u4e39\u6c60",
        "Danchi"
    ],
    "wof:name":"Danchi",
    "wof:placetype":"locality"
},
  "geometry": {"coordinates":[119.78519,27.20734],"type":"Point"}
}