{
  "type": "Feature",
  "properties": {
    "gn:admin1_code":"10",
    "gn:asciiname":"Jiashihe",
    "gn:country_code":"CN",
    "gn:dem":1470,
    "gn:feature_class":"P",
    "gn:feature_code":"PPL",
    "gn:name":"Jiashihe",
    "gn:population":0,
    "gn:timezone":"Asia/Shanghai",
    "iso:country":"CN",
    "name:zho_x_preferred":[
        "\u7532\u77f3\u6cb3"
    ],
    "wof:name":"Jiashihe",
    "wof:placetype":"locality"
},
  "geometry": {"coordinates":[114.96796999999999,41.16378],"type":"Point"}
}