{
  "type": "Feature",
  "properties": {
    "gn:admin1_code":"1.0",
    "gn:asciiname":"Chenzhuanjing",
    "gn:country_code":"CN",
    "gn:dem":33,
    "gn:feature_class":"P",
    "gn:feature_code":"PPL",
    "gn:name":"Chenzhuanjing",
    "gn:population":0,
    "gn:timezone":"Asia/Shanghai",
    "iso:country":"CN",
    "name:zho_x_preferred":[
        "\u9648\u7816\u4e95"
    ],
    "wof:name":"Chenzhuanjing",
    "wof:placetype":"locality"
},
  "geometry": {"coordinates":[118.67775,32.72524],"type":"Point"}
}