{
  "type": "Feature",
  "properties": {
    "gn:admin1_code":"29.0",
    "gn:asciiname":"Gelong",
    "gn:country_code":"CN",
    "gn:dem":1227,
    "gn:feature_class":"P",
    "gn:feature_code":"PPL",
    "gn:name":"Gelong",
    "gn:population":0,
    "gn:timezone":"Asia/Shanghai",
    "iso:country":"CN",
    "name:zho_x_preferred":[
        "\u683c\u7b3c"
    ],
    "wof:name":"Gelong",
    "wof:placetype":"locality"
},
  "geometry": {"coordinates":[99.26090000000001,23.2369],"type":"Point"}
}