{
  "type": "Feature",
  "properties": {
    "gn:admin1_code":"4.0",
    "gn:asciiname":"Yanghu",
    "gn:country_code":"CN",
    "gn:dem":3,
    "gn:feature_class":"P",
    "gn:feature_code":"PPL",
    "gn:name":"Yanghu",
    "gn:population":0,
    "gn:timezone":"Asia/Shanghai",
    "iso:country":"CN",
    "name:zho_x_preferred":[
        "Yanghu"
    ],
    "name:zho_x_variant":[
        "\u6d0b\u6e56"
    ],
    "wof:name":"Yanghu",
    "wof:placetype":"locality"
},
  "geometry": {"coordinates":[119.61727999999999,33.41329],"type":"Point"}
}