{
  "type": "Feature",
  "properties": {
    "gn:admin1_code":"11",
    "gn:asciiname":"Taokeng",
    "gn:country_code":"CN",
    "gn:dem":176,
    "gn:feature_class":"P",
    "gn:feature_code":"PPLA4",
    "gn:name":"Taokeng",
    "gn:population":0,
    "gn:timezone":"Asia/Shanghai",
    "iso:country":"CN",
    "name:und_x_variant":[
        "Kengkouxu",
        "Taokeng Xiang"
    ],
    "name:zho_x_preferred":[
        "\u6843\u5751"
    ],
    "name:zho_x_variant":[
        "\u5751\u53e3\u5729",
        "\u6843\u5751\u4e61"
    ],
    "wof:name":"Taokeng",
    "wof:placetype":"locality"
},
  "geometry": {"coordinates":[113.74970999999999,26.66776],"type":"Point"}
}