{
  "type": "Feature",
  "properties": {
    "gn:admin1_code":"9.0",
    "gn:asciiname":"Huozhai",
    "gn:country_code":"CN",
    "gn:dem":70,
    "gn:feature_class":"P",
    "gn:feature_code":"PPL",
    "gn:name":"Huozhai",
    "gn:population":0,
    "gn:timezone":"Asia/Shanghai",
    "iso:country":"CN",
    "name:zho_x_preferred":[
        "\u970d\u5be8"
    ],
    "wof:name":"Huozhai",
    "wof:placetype":"locality"
},
  "geometry": {"coordinates":[114.28154000000001,34.48855],"type":"Point"}
}