{
  "type": "Feature",
  "properties": {
    "gn:admin1_code":"10.0",
    "gn:asciiname":"Cuijiazhuang",
    "gn:country_code":"CN",
    "gn:dem":11,
    "gn:feature_class":"P",
    "gn:feature_code":"PPL",
    "gn:name":"Cuijiazhuang",
    "gn:population":0,
    "gn:timezone":"Asia/Shanghai",
    "iso:country":"CN",
    "name:zho_x_preferred":[
        "\u5d14\u5bb6\u5e84"
    ],
    "wof:name":"Cuijiazhuang",
    "wof:placetype":"locality"
},
  "geometry": {"coordinates":[116.01900000000001,38.6174],"type":"Point"}
}