{
  "type": "Feature",
  "properties": {
    "gn:admin1_code":"07",
    "gn:asciiname":"Chencuokeng",
    "gn:country_code":"CN",
    "gn:dem":690,
    "gn:feature_class":"P",
    "gn:feature_code":"PPL",
    "gn:name":"Chencuokeng",
    "gn:population":0,
    "gn:timezone":"Asia/Shanghai",
    "iso:country":"CN",
    "name:zho_x_preferred":[
        "\u9648\u539d\u5751"
    ],
    "wof:name":"Chencuokeng",
    "wof:placetype":"locality"
},
  "geometry": {"coordinates":[117.6555,25.8038],"type":"Point"}
}