{
  "type": "Feature",
  "properties": {
    "gn:admin1_code":"6.0",
    "gn:asciiname":"Miyahai",
    "gn:country_code":"CN",
    "gn:dem":2253,
    "gn:feature_class":"P",
    "gn:feature_code":"PPL",
    "gn:name":"Miyahai",
    "gn:population":0,
    "gn:timezone":"Asia/Shanghai",
    "iso:country":"CN",
    "name:und_x_variant":[
        "\u7c73\u7259\u4ea5"
    ],
    "wof:name":"Miyahai",
    "wof:placetype":"locality"
},
  "geometry": {"coordinates":[102.55982,35.72172],"type":"Point"}
}