{
  "type": "Feature",
  "properties": {
    "gn:admin1_code":"02",
    "gn:asciiname":"Xi'ao",
    "gn:country_code":"CN",
    "gn:dem":37,
    "gn:feature_class":"P",
    "gn:feature_code":"PPL",
    "gn:name":"Xi\u2019ao",
    "gn:population":0,
    "gn:timezone":"Asia/Shanghai",
    "iso:country":"CN",
    "name:und_x_variant":[
        "Hsi-ao",
        "Xi\u2019ao",
        "\u897f\u5c99"
    ],
    "wof:name":"Xi'ao",
    "wof:placetype":"locality"
},
  "geometry": {"coordinates":[122.30015,29.86129],"type":"Point"}
}