{
  "type": "Feature",
  "properties": {
    "gn:admin1_code":"11.0",
    "gn:asciiname":"Hubixi",
    "gn:country_code":"CN",
    "gn:dem":407,
    "gn:feature_class":"P",
    "gn:feature_code":"PPL",
    "gn:name":"Hubixi",
    "gn:population":0,
    "gn:timezone":"Asia/Shanghai",
    "iso:country":"CN",
    "name:zho_x_preferred":[
        "\u80e1\u6bd5\u6eaa"
    ],
    "wof:name":"Hubixi",
    "wof:placetype":"locality"
},
  "geometry": {"coordinates":[109.70782,28.80692],"type":"Point"}
}