{
  "type": "Feature",
  "properties": {
    "gn:admin1_code":"2.0",
    "gn:asciiname":"Xiawangqiu",
    "gn:country_code":"CN",
    "gn:dem":58,
    "gn:feature_class":"P",
    "gn:feature_code":"PPL",
    "gn:name":"Xiawangqiu",
    "gn:population":0,
    "gn:timezone":"Asia/Shanghai",
    "iso:country":"CN",
    "name:zho_x_preferred":[
        "\u4e0b\u738b\u90b1"
    ],
    "wof:name":"Xiawangqiu",
    "wof:placetype":"locality"
},
  "geometry": {"coordinates":[121.03637999999999,29.11749],"type":"Point"}
}