{
  "type": "Feature",
  "properties": {
    "gn:admin1_code":"6.0",
    "gn:asciiname":"Wengni'a",
    "gn:country_code":"CN",
    "gn:dem":3043,
    "gn:feature_class":"P",
    "gn:feature_code":"PPL",
    "gn:name":"Wengni\u2019a",
    "gn:population":0,
    "gn:timezone":"Asia/Shanghai",
    "iso:country":"CN",
    "name:und_x_variant":[
        "Wengni\u2019a",
        "\u7fc1\u5c3c\u963f"
    ],
    "wof:name":"Wengni'a",
    "wof:placetype":"locality"
},
  "geometry": {"coordinates":[102.0964,35.52862000000001],"type":"Point"}
}