{
  "type": "Feature",
  "properties": {
    "gn:admin1_code":"32.0",
    "gn:asciiname":"Jiankang",
    "gn:country_code":"CN",
    "gn:dem":2030,
    "gn:feature_class":"P",
    "gn:feature_code":"PPL",
    "gn:name":"Jiankang",
    "gn:population":0,
    "gn:timezone":"Asia/Shanghai",
    "iso:country":"CN",
    "name:zho_x_preferred":[
        "\u5065\u5eb7"
    ],
    "wof:name":"Jiankang",
    "wof:placetype":"locality"
},
  "geometry": {"coordinates":[102.639,30.5965],"type":"Point"}
}