{
  "type": "Feature",
  "properties": {
    "gn:admin1_code":"3.0",
    "gn:asciiname":"Chifeng",
    "gn:country_code":"CN",
    "gn:dem":176,
    "gn:feature_class":"P",
    "gn:feature_code":"PPL",
    "gn:name":"Chifeng",
    "gn:population":0,
    "gn:timezone":"Asia/Shanghai",
    "iso:country":"CN",
    "name:afr_x_preferred":[
        "Chifeng"
    ],
    "name:ara_x_preferred":[
        "\u062a\u0634\u064a\u0641\u0646\u063a"
    ],
    "name:cdo_x_preferred":[
        "Chi\u00e1h-h\u016dng"
    ],
    "name:ceb_x_preferred":[
        "Chifeng"
    ],
    "name:ces_x_preferred":[
        "\u010cch\u2019-feng"
    ],
    "name:dan_x_preferred":[
        "Chifeng"
    ],
    "name:deu_x_preferred":[
        "Chifeng"
    ],
    "name:est_x_preferred":[
        "Chifeng"
    ],
    "name:eus_x_preferred":[
        "Chifeng"
    ],
    "name:fas_x_preferred":[
        "\u0686\u06cc\u0641\u0646\u06af"
    ],
    "name:fin_x_preferred":[
        "Chifeng"
    ],
    "name:fra_x_preferred":[
        "Chifeng"
    ],
    "name:hak_x_preferred":[
        "Chhak-f\u00fbng-s\u1e73"
    ],
    "name:ita_x_preferred":[
        "Chifeng"
    ],
    "name:jpn_x_preferred":[
        "\u8d64\u5cf0\u5e02"
    ],
    "name:kik_x_preferred":[
        "Chifeng"
    ],
    "name:kor_x_preferred":[
        "\uce20\ud391\uc2dc"
    ],
    "name:mlg_x_preferred":[
        "Chifeng"
    ],
    "name:mon_x_preferred":[
        "\u0423\u043b\u0430\u0430\u043d\u0445\u0430\u0434"
    ],
    "name:nld_x_preferred":[
        "Chifeng"
    ],
    "name:nor_x_preferred":[
        "Chifeng"
    ],
    "name:pol_x_preferred":[
        "Chifeng"
    ],
    "name:rus_x_preferred":[
        "\u0427\u0438\u0444\u044d\u043d"
    ],
    "name:spa_x_preferred":[
        "Ulanhad"
    ],
    "name:srp_x_preferred":[
        "\u0427\u0438\u0444\u0435\u043d\u0433"
    ],
    "name:swe_x_preferred":[
        "Chifeng"
    ],
    "name:tur_x_preferred":[
        "Chifeng"
    ],
    "name:und_x_variant":[
        "\u6c60\u4e30"
    ],
    "name:urd_x_preferred":[
        "\u0686\u06cc\u0641\u06cc\u0646\u06af"
    ],
    "name:vie_x_preferred":[
        "X\u00edch Phong"
    ],
    "name:war_x_preferred":[
        "Chifeng"
    ],
    "name:wuu_x_preferred":[
        "\u8d64\u5cf0\u5e02"
    ],
    "name:zho_x_preferred":[
        "\u8d64\u5cf0\u5e02"
    ],
    "wof:name":"Chifeng",
    "wof:placetype":"locality"
},
  "geometry": {"coordinates":[116.4181,27.15954],"type":"Point"}
}