{
  "type": "Feature",
  "properties": {
    "gn:admin1_code":"3.0",
    "gn:asciiname":"Chifeng",
    "gn:country_code":"CN",
    "gn:dem":176,
    "gn:feature_class":"P",
    "gn:feature_code":"PPL",
    "gn:name":"Chifeng",
    "gn:population":0,
    "gn:timezone":"Asia/Shanghai",
    "iso:country":"CN",
    "name:und_x_variant":[
        "\u6c60\u4e30"
    ],
    "wof:name":"Chifeng",
    "wof:placetype":"locality"
},
  "geometry": {"coordinates":[116.4181,27.15954],"type":"Point"}
}