{
  "type": "Feature",
  "properties": {
    "gn:admin1_code":"02",
    "gn:asciiname":"Damazhu",
    "gn:country_code":"CN",
    "gn:dem":50,
    "gn:feature_class":"P",
    "gn:feature_code":"PPL",
    "gn:name":"Damazhu",
    "gn:population":0,
    "gn:timezone":"Asia/Shanghai",
    "iso:country":"CN",
    "name:und_x_variant":[
        "\u5927\u9a6c\u67f1"
    ],
    "wof:name":"Damazhu",
    "wof:placetype":"locality"
},
  "geometry": {"coordinates":[121.94583,30.10806],"type":"Point"}
}