{
  "type": "Feature",
  "properties": {
    "gn:admin1_code":"9",
    "gn:asciiname":"Dingliuyuan",
    "gn:country_code":"CN",
    "gn:dem":41,
    "gn:feature_class":"P",
    "gn:feature_code":"PPL",
    "gn:name":"Dingliuyuan",
    "gn:population":0,
    "gn:timezone":"Asia/Shanghai",
    "iso:country":"CN",
    "name:zho_x_preferred":[
        "\u4e01\u67f3\u5143"
    ],
    "wof:name":"Dingliuyuan",
    "wof:placetype":"locality"
},
  "geometry": {"coordinates":[116.22199999999999,34.0277],"type":"Point"}
}