{
  "type": "Feature",
  "properties": {
    "gn:admin1_code":"16.0",
    "gn:asciiname":"Zhenlong",
    "gn:cc2":"CN",
    "gn:country_code":"CN",
    "gn:dem":145,
    "gn:feature_class":"P",
    "gn:feature_code":"PPL",
    "gn:name":"Zhenlong",
    "gn:population":0,
    "gn:timezone":"Asia/Shanghai",
    "iso:country":"CN",
    "name:und_x_variant":[
        "Chen-lung",
        "Chen-lung-hs\u00fc",
        "Zhenlong"
    ],
    "wof:name":"Zhenlong",
    "wof:placetype":"locality"
},
  "geometry": {"coordinates":[108.68333,22.55],"type":"Point"}
}