{
  "type": "Feature",
  "properties": {
    "gn:admin1_code":"32",
    "gn:asciiname":"Qianfo",
    "gn:country_code":"CN",
    "gn:dem":402,
    "gn:feature_class":"P",
    "gn:feature_code":"PPL",
    "gn:name":"Qianfo",
    "gn:population":0,
    "gn:timezone":"Asia/Shanghai",
    "iso:country":"CN",
    "name:und_x_variant":[
        "Ch\u2019ien-fo",
        "Qianfo"
    ],
    "name:zho_x_preferred":[
        "\u5343\u4f5b"
    ],
    "wof:name":"Qianfo",
    "wof:placetype":"locality"
},
  "geometry": {"coordinates":[106.27196000000001,31.71354],"type":"Point"}
}