{
  "type": "Feature",
  "properties": {
    "gn:admin1_code":"5.0",
    "gn:asciiname":"Xilaidong Zhongcun",
    "gn:country_code":"CN",
    "gn:dem":484,
    "gn:feature_class":"P",
    "gn:feature_code":"PPL",
    "gn:name":"Xilaidong Zhongcun",
    "gn:population":0,
    "gn:timezone":"Asia/Shanghai",
    "iso:country":"CN",
    "wof:name":"Xilaidong Zhongcun",
    "wof:placetype":"locality"
},
  "geometry": {"coordinates":[129.65304,42.52752],"type":"Point"}
}