{
  "type": "Feature",
  "properties": {
    "gn:admin1_code":"25",
    "gn:asciiname":"Dabutou",
    "gn:country_code":"CN",
    "gn:dem":166,
    "gn:feature_class":"P",
    "gn:feature_code":"PPL",
    "gn:name":"Dabutou",
    "gn:population":0,
    "gn:timezone":"Asia/Shanghai",
    "iso:country":"CN",
    "name:zho_x_preferred":[
        "\u5927\u57e0\u5934"
    ],
    "wof:name":"Dabutou",
    "wof:placetype":"locality"
},
  "geometry": {"coordinates":[117.43899999999999,36.2813],"type":"Point"}
}