{
  "type": "Feature",
  "properties": {
    "gn:admin1_code":"24.0",
    "gn:asciiname":"Hanjiaji",
    "gn:country_code":"CN",
    "gn:dem":993,
    "gn:feature_class":"P",
    "gn:feature_code":"PPL",
    "gn:name":"Hanjiaji",
    "gn:population":0,
    "gn:timezone":"Asia/Shanghai",
    "iso:country":"CN",
    "name:zho_x_preferred":[
        "\u97e9\u5bb6\u5409"
    ],
    "wof:name":"Hanjiaji",
    "wof:placetype":"locality"
},
  "geometry": {"coordinates":[110.81966,38.40163],"type":"Point"}
}