{
  "type": "Feature",
  "properties": {
    "gn:admin1_code":"5.0",
    "gn:asciiname":"Lidiantun",
    "gn:country_code":"CN",
    "gn:dem":150,
    "gn:feature_class":"P",
    "gn:feature_code":"PPL",
    "gn:name":"Lidiantun",
    "gn:population":0,
    "gn:timezone":"Asia/Shanghai",
    "iso:country":"CN",
    "name:zho_x_preferred":[
        "\u674e\u5e97\u5c6f"
    ],
    "wof:name":"Lidiantun",
    "wof:placetype":"locality"
},
  "geometry": {"coordinates":[122.87463,45.29525],"type":"Point"}
}