{
  "type": "Feature",
  "properties": {
    "gn:admin1_code":"30",
    "gn:asciiname":"Mai'ao",
    "gn:country_code":"CN",
    "gn:dem":53,
    "gn:feature_class":"P",
    "gn:feature_code":"PPL",
    "gn:name":"Mai\u2019ao",
    "gn:population":0,
    "gn:timezone":"Asia/Urumqi",
    "iso:country":"CN",
    "name:zho_x_preferred":[
        "Mai\u2019ao"
    ],
    "name:zho_x_variant":[
        "\u8fc8\u9068"
    ],
    "wof:name":"Mai'ao",
    "wof:placetype":"locality"
},
  "geometry": {"coordinates":[110.34111,20.57639],"type":"Point"}
}