{
  "type": "Feature",
  "properties": {
    "gn:admin1_code":"20.0",
    "gn:asciiname":"Qianyaozi",
    "gn:country_code":"CN",
    "gn:dem":1817,
    "gn:feature_class":"P",
    "gn:feature_code":"PPL",
    "gn:name":"Qianyaozi",
    "gn:population":0,
    "gn:timezone":"Asia/Shanghai",
    "iso:country":"CN",
    "name:und_x_variant":[
        "\u524d\u7a91\u5b50"
    ],
    "wof:name":"Qianyaozi",
    "wof:placetype":"locality"
},
  "geometry": {"coordinates":[111.06632999999999,41.03491],"type":"Point"}
}