{
  "type": "Feature",
  "properties": {
    "gn:admin1_code":"25",
    "gn:asciiname":"Yaowangzhuang",
    "gn:country_code":"CN",
    "gn:dem":57,
    "gn:feature_class":"P",
    "gn:feature_code":"PPL",
    "gn:name":"Yaowangzhuang",
    "gn:population":0,
    "gn:timezone":"Asia/Shanghai",
    "iso:country":"CN",
    "name:zho_x_preferred":[
        "\u5c27\u738b\u5e84"
    ],
    "wof:name":"Yaowangzhuang",
    "wof:placetype":"locality"
},
  "geometry": {"coordinates":[118.36499999999999,36.8184],"type":"Point"}
}