{
  "type": "Feature",
  "properties": {
    "gn:admin1_code":"26.0",
    "gn:asciiname":"Xibaicun",
    "gn:country_code":"CN",
    "gn:dem":820,
    "gn:feature_class":"P",
    "gn:feature_code":"PPL",
    "gn:name":"Xibaicun",
    "gn:population":0,
    "gn:timezone":"Asia/Shanghai",
    "iso:country":"CN",
    "name:zho_x_preferred":[
        "\u897f\u767d\u6751"
    ],
    "wof:name":"Xibaicun",
    "wof:placetype":"locality"
},
  "geometry": {"coordinates":[107.4824,34.53588],"type":"Point"}
}