{
  "type": "Feature",
  "properties": {
    "gn:admin1_code":"20.0",
    "gn:asciiname":"Houshifenzi",
    "gn:country_code":"CN",
    "gn:dem":1590,
    "gn:feature_class":"P",
    "gn:feature_code":"PPL",
    "gn:name":"Houshifenzi",
    "gn:population":0,
    "gn:timezone":"Asia/Shanghai",
    "iso:country":"CN",
    "name:und_x_variant":[
        "\u540e\u5341\u5206\u5b50"
    ],
    "wof:name":"Houshifenzi",
    "wof:placetype":"locality"
},
  "geometry": {"coordinates":[109.78458000000001,41.14275],"type":"Point"}
}