{
  "type": "Feature",
  "properties": {
    "gn:admin1_code":"12.0",
    "gn:asciiname":"Changchengya",
    "gn:country_code":"CN",
    "gn:dem":1050,
    "gn:feature_class":"P",
    "gn:feature_code":"PPL",
    "gn:name":"Changchengya",
    "gn:population":0,
    "gn:timezone":"Asia/Shanghai",
    "iso:country":"CN",
    "name:zho_x_preferred":[
        "\u957f\u57ce\u57ad"
    ],
    "wof:name":"Changchengya",
    "wof:placetype":"locality"
},
  "geometry": {"coordinates":[111.27822999999999,31.14103],"type":"Point"}
}