{
  "type": "Feature",
  "properties": {
    "gn:admin1_code":"8.0",
    "gn:asciiname":"Houguojia",
    "gn:country_code":"CN",
    "gn:dem":181,
    "gn:feature_class":"P",
    "gn:feature_code":"PPL",
    "gn:name":"Houguojia",
    "gn:population":0,
    "gn:timezone":"Asia/Shanghai",
    "iso:country":"CN",
    "name:zho_x_preferred":[
        "\u540e\u56fd\u5bb6"
    ],
    "wof:name":"Houguojia",
    "wof:placetype":"locality"
},
  "geometry": {"coordinates":[124.60362000000001,48.33794],"type":"Point"}
}