{
  "type": "Feature",
  "properties": {
    "gn:admin1_code":"20.0",
    "gn:asciiname":"Galabu'er Gacha",
    "gn:country_code":"CN",
    "gn:dem":606,
    "gn:feature_class":"P",
    "gn:feature_code":"PPL",
    "gn:name":"Galabu\u2019er Gacha",
    "gn:population":0,
    "gn:timezone":"Asia/Shanghai",
    "iso:country":"CN",
    "name:und_x_variant":[
        "Galabu\u2019er Gacha"
    ],
    "name:zho_x_preferred":[
        "\u560e\u62c9\u5e03\u5c14\u560e\u67e5"
    ],
    "wof:name":"Galabu'er Gacha",
    "wof:placetype":"locality"
},
  "geometry": {"coordinates":[118.34787,49.20958],"type":"Point"}
}