{
  "type": "Feature",
  "properties": {
    "gn:admin1_code":"20.0",
    "gn:asciiname":"Chagan Nuo'ermiao",
    "gn:country_code":"CN",
    "gn:dem":569,
    "gn:feature_class":"P",
    "gn:feature_code":"PPL",
    "gn:name":"Chagan Nuo\u2019ermiao",
    "gn:population":0,
    "gn:timezone":"Asia/Shanghai",
    "iso:country":"CN",
    "name:und_x_variant":[
        "Chagan Nuo\u2019ermiao"
    ],
    "name:zho_x_preferred":[
        "\u67e5\u5e72\u8bfa\u5c14\u5e99"
    ],
    "wof:name":"Chagan Nuo'ermiao",
    "wof:placetype":"locality"
},
  "geometry": {"coordinates":[116.35961,48.46021],"type":"Point"}
}