{
  "type": "Feature",
  "properties": {
    "gn:admin1_code":"30.0",
    "gn:asciiname":"Rentang",
    "gn:country_code":"CN",
    "gn:dem":51,
    "gn:feature_class":"P",
    "gn:feature_code":"PPL",
    "gn:name":"Rentang",
    "gn:population":0,
    "gn:timezone":"Asia/Shanghai",
    "iso:country":"CN",
    "name:zho_x_preferred":[
        "\u7a14\u5858"
    ],
    "wof:name":"Rentang",
    "wof:placetype":"locality"
},
  "geometry": {"coordinates":[113.48041000000001,23.63565],"type":"Point"}
}