{
  "type": "Feature",
  "properties": {
    "gn:admin1_code":"12.0",
    "gn:asciiname":"Tujiahe",
    "gn:country_code":"CN",
    "gn:dem":28,
    "gn:feature_class":"P",
    "gn:feature_code":"PPL",
    "gn:name":"Tujiahe",
    "gn:population":0,
    "gn:timezone":"Asia/Shanghai",
    "iso:country":"CN",
    "name:und_x_variant":[
        "\u571f\u5bb6\u6cb3"
    ],
    "wof:name":"Tujiahe",
    "wof:placetype":"locality"
},
  "geometry": {"coordinates":[114.42816000000001,30.72956],"type":"Point"}
}