{
  "type": "Feature",
  "properties": {
    "gn:admin1_code":"16.0",
    "gn:asciiname":"Chengjiao",
    "gn:country_code":"CN",
    "gn:dem":89,
    "gn:feature_class":"P",
    "gn:feature_code":"PPL",
    "gn:name":"Chengjiao",
    "gn:population":0,
    "gn:timezone":"Asia/Shanghai",
    "iso:country":"CN",
    "name:ceb_x_preferred":[
        "Chengjiao"
    ],
    "name:deu_x_preferred":[
        "Chengjiao"
    ],
    "name:swe_x_preferred":[
        "Chengjiao"
    ],
    "name:zho_x_preferred":[
        "\u6210\u6559"
    ],
    "wof:name":"Chengjiao",
    "wof:placetype":"locality"
},
  "geometry": {"coordinates":[108.08199999999999,21.8407],"type":"Point"}
}