{
  "type": "Feature",
  "properties": {
    "gn:admin1_code":"09",
    "gn:asciiname":"Songzhai",
    "gn:country_code":"CN",
    "gn:dem":212,
    "gn:feature_class":"P",
    "gn:feature_code":"PPL",
    "gn:name":"Songzhai",
    "gn:population":0,
    "gn:timezone":"Asia/Shanghai",
    "iso:country":"CN",
    "name:und_x_variant":[
        "Sung-chai",
        "Songzhai"
    ],
    "name:zho_x_preferred":[
        "\u5b8b\u5be8"
    ],
    "wof:name":"Songzhai",
    "wof:placetype":"locality"
},
  "geometry": {"coordinates":[113.53979,34.50519],"type":"Point"}
}