{
  "type": "Feature",
  "properties": {
    "gn:admin1_code":"4.0",
    "gn:asciiname":"Fuqiaocun",
    "gn:country_code":"CN",
    "gn:dem":4,
    "gn:feature_class":"P",
    "gn:feature_code":"PPL",
    "gn:name":"Fuqiaocun",
    "gn:population":0,
    "gn:timezone":"Asia/Shanghai",
    "iso:country":"CN",
    "name:und_x_variant":[
        "\u6d6e\u6865\u6751"
    ],
    "name:zho_x_preferred":[
        "\u6d6e\u6865\u6751"
    ],
    "wof:name":"Fuqiaocun",
    "wof:placetype":"locality"
},
  "geometry": {"coordinates":[120.69119000000001,31.2592],"type":"Point"}
}