{
  "type": "Feature",
  "properties": {
    "gn:admin1_code":"2.0",
    "gn:asciiname":"Xiaoshuibu",
    "gn:country_code":"CN",
    "gn:dem":15,
    "gn:feature_class":"P",
    "gn:feature_code":"PPL",
    "gn:name":"Xiaoshuibu",
    "gn:population":0,
    "gn:timezone":"Asia/Shanghai",
    "iso:country":"CN",
    "name:zho_x_preferred":[
        "\u5c0f\u6c34\u57e0"
    ],
    "wof:name":"Xiaoshuibu",
    "wof:placetype":"locality"
},
  "geometry": {"coordinates":[121.25843999999999,28.10963],"type":"Point"}
}