{
  "type": "Feature",
  "properties": {
    "gn:admin1_code":"12.0",
    "gn:asciiname":"Fujiachong",
    "gn:country_code":"CN",
    "gn:dem":33,
    "gn:feature_class":"P",
    "gn:feature_code":"PPL",
    "gn:name":"Fujiachong",
    "gn:population":0,
    "gn:timezone":"Asia/Shanghai",
    "iso:country":"CN",
    "name:zho_x_preferred":[
        "\u5085\u5bb6\u51b2"
    ],
    "wof:name":"Fujiachong",
    "wof:placetype":"locality"
},
  "geometry": {"coordinates":[113.68255000000001,30.95974],"type":"Point"}
}