{
  "type": "Feature",
  "properties": {
    "gn:admin1_code":"29.0",
    "gn:asciiname":"Henanjiao",
    "gn:country_code":"CN",
    "gn:dem":1634,
    "gn:feature_class":"P",
    "gn:feature_code":"PPL",
    "gn:name":"Henanjiao",
    "gn:population":0,
    "gn:timezone":"Asia/Shanghai",
    "iso:country":"CN",
    "name:zho_x_preferred":[
        "\u6cb3\u5357\u89d2"
    ],
    "wof:name":"Henanjiao",
    "wof:placetype":"locality"
},
  "geometry": {"coordinates":[103.66200000000001,23.2691],"type":"Point"}
}