{
  "type": "Feature",
  "properties": {
    "gn:admin1_code":"7.0",
    "gn:asciiname":"Yangkeng",
    "gn:country_code":"CN",
    "gn:dem":429,
    "gn:feature_class":"P",
    "gn:feature_code":"PPL",
    "gn:name":"Yangkeng",
    "gn:population":0,
    "gn:timezone":"Asia/Shanghai",
    "iso:country":"CN",
    "name:und_x_variant":[
        "\u6d0b\u5751"
    ],
    "name:zho_x_preferred":[
        "\u6d0b\u5751"
    ],
    "wof:name":"Yangkeng",
    "wof:placetype":"locality"
},
  "geometry": {"coordinates":[118.04902,26.59689],"type":"Point"}
}