{
  "type": "Feature",
  "properties": {
    "gn:admin1_code":"9.0",
    "gn:asciiname":"Yinglie",
    "gn:country_code":"CN",
    "gn:dem":118,
    "gn:feature_class":"P",
    "gn:feature_code":"PPL",
    "gn:name":"Yinglie",
    "gn:population":0,
    "gn:timezone":"Asia/Shanghai",
    "iso:country":"CN",
    "name:zho_x_preferred":[
        "\u82f1\u70c8"
    ],
    "wof:name":"Yinglie",
    "wof:placetype":"locality"
},
  "geometry": {"coordinates":[114.20683,36.25847],"type":"Point"}
}