{
  "type": "Feature",
  "properties": {
    "gn:admin1_code":"21.0",
    "gn:asciiname":"Zhujiaquan",
    "gn:country_code":"CN",
    "gn:dem":2026,
    "gn:feature_class":"P",
    "gn:feature_code":"PPL",
    "gn:name":"Zhujiaquan",
    "gn:population":0,
    "gn:timezone":"Asia/Shanghai",
    "iso:country":"CN",
    "name:zho_x_preferred":[
        "\u6731\u5bb6\u5708"
    ],
    "wof:name":"Zhujiaquan",
    "wof:placetype":"locality"
},
  "geometry": {"coordinates":[105.405,37.2988],"type":"Point"}
}