{
  "type": "Feature",
  "properties": {
    "gn:admin1_code":"1.0",
    "gn:asciiname":"Huangchongcun",
    "gn:country_code":"CN",
    "gn:dem":35,
    "gn:feature_class":"P",
    "gn:feature_code":"PPL",
    "gn:name":"Huangchongcun",
    "gn:population":0,
    "gn:timezone":"Asia/Shanghai",
    "iso:country":"CN",
    "name:zho_x_preferred":[
        "\u9ec4\u51b2\u6751"
    ],
    "wof:name":"Huangchongcun",
    "wof:placetype":"locality"
},
  "geometry": {"coordinates":[117.47259,30.91426],"type":"Point"}
}