{
  "type": "Feature",
  "properties": {
    "gn:admin1_code":"18.0",
    "gn:asciiname":"Ganyezhai",
    "gn:country_code":"CN",
    "gn:dem":834,
    "gn:feature_class":"P",
    "gn:feature_code":"PPL",
    "gn:name":"Ganyezhai",
    "gn:population":0,
    "gn:timezone":"Asia/Shanghai",
    "iso:country":"CN",
    "name:zho_x_preferred":[
        "\u5e72\u91ce\u5be8"
    ],
    "wof:name":"Ganyezhai",
    "wof:placetype":"locality"
},
  "geometry": {"coordinates":[107.88200000000001,26.2403],"type":"Point"}
}