{
  "type": "Feature",
  "properties": {
    "gn:admin1_code":"18",
    "gn:asciiname":"Luohua",
    "gn:country_code":"CN",
    "gn:dem":822,
    "gn:feature_class":"P",
    "gn:feature_code":"PPL",
    "gn:name":"Luohua",
    "gn:population":0,
    "gn:timezone":"Asia/Shanghai",
    "iso:country":"CN",
    "name:zho_x_preferred":[
        "\u843d\u5316"
    ],
    "wof:name":"Luohua",
    "wof:placetype":"locality"
},
  "geometry": {"coordinates":[106.01900000000001,24.8929],"type":"Point"}
}