{
  "type": "Feature",
  "properties": {
    "gn:admin1_code":"13",
    "gn:asciiname":"Yekeli",
    "gn:country_code":"CN",
    "gn:dem":1058,
    "gn:feature_class":"P",
    "gn:feature_code":"PPL",
    "gn:name":"Yekeli",
    "gn:population":0,
    "gn:timezone":"Asia/Shanghai",
    "iso:country":"CN",
    "name:und_x_variant":[
        "\u4e5f\u514b\u529b"
    ],
    "wof:name":"Yekeli",
    "wof:placetype":"locality"
},
  "geometry": {"coordinates":[80.19041999999997,40.80327],"type":"Point"}
}