{
  "type": "Feature",
  "properties": {
    "gn:admin1_code":"6.0",
    "gn:asciiname":"Qihe'angtan",
    "gn:country_code":"CN",
    "gn:dem":2964,
    "gn:feature_class":"P",
    "gn:feature_code":"PPL",
    "gn:name":"Qihe\u2019angtan",
    "gn:population":0,
    "gn:timezone":"Asia/Shanghai",
    "iso:country":"CN",
    "name:und_x_variant":[
        "Qihe\u2019angtan"
    ],
    "name:zho_x_preferred":[
        "\u5176\u5408\u6602\u6ee9"
    ],
    "wof:name":"Qihe'angtan",
    "wof:placetype":"locality"
},
  "geometry": {"coordinates":[102.11399,36.00708],"type":"Point"}
}