{
  "type": "Feature",
  "properties": {
    "gn:admin1_code":"19.0",
    "gn:asciiname":"Mengtuncun",
    "gn:country_code":"CN",
    "gn:dem":50,
    "gn:feature_class":"P",
    "gn:feature_code":"PPL",
    "gn:name":"Mengtuncun",
    "gn:population":0,
    "gn:timezone":"Asia/Shanghai",
    "iso:country":"CN",
    "name:zho_x_preferred":[
        "\u5b5f\u5c6f\u6751"
    ],
    "wof:name":"Mengtuncun",
    "wof:placetype":"locality"
},
  "geometry": {"coordinates":[122.541,42.0986],"type":"Point"}
}