{
  "type": "Feature",
  "properties": {
    "gn:admin1_code":"26.0",
    "gn:asciiname":"Weijia Yuanzi",
    "gn:country_code":"CN",
    "gn:dem":846,
    "gn:feature_class":"P",
    "gn:feature_code":"PPL",
    "gn:name":"Weijia Yuanzi",
    "gn:population":0,
    "gn:timezone":"Asia/Shanghai",
    "iso:country":"CN",
    "name:zho_x_preferred":[
        "\u9b4f\u5bb6\u9662\u5b50"
    ],
    "wof:name":"Weijia Yuanzi",
    "wof:placetype":"locality"
},
  "geometry": {"coordinates":[108.13079,33.52525],"type":"Point"}
}