{
  "type": "Feature",
  "properties": {
    "gn:admin1_code":"30.0",
    "gn:asciiname":"Zhangkengwei",
    "gn:country_code":"CN",
    "gn:dem":137,
    "gn:feature_class":"P",
    "gn:feature_code":"PPL",
    "gn:name":"Zhangkengwei",
    "gn:population":0,
    "gn:timezone":"Asia/Shanghai",
    "iso:country":"CN",
    "name:zho_x_preferred":[
        "\u5f20\u5751\u5c3e"
    ],
    "wof:name":"Zhangkengwei",
    "wof:placetype":"locality"
},
  "geometry": {"coordinates":[113.82193999999998,24.07889],"type":"Point"}
}