{
  "type": "Feature",
  "properties": {
    "gn:admin1_code":"16.0",
    "gn:asciiname":"Fujiang",
    "gn:country_code":"CN",
    "gn:dem":182,
    "gn:feature_class":"P",
    "gn:feature_code":"PPL",
    "gn:name":"Fujiang",
    "gn:population":0,
    "gn:timezone":"Asia/Shanghai",
    "iso:country":"CN",
    "name:zho_x_preferred":[
        "\u798f\u6c5f"
    ],
    "wof:name":"Fujiang",
    "wof:placetype":"locality"
},
  "geometry": {"coordinates":[108.31999999999999,23.4794],"type":"Point"}
}