{
  "type": "Feature",
  "properties": {
    "gn:admin1_code":"25.0",
    "gn:asciiname":"Jiwangcun",
    "gn:country_code":"CN",
    "gn:dem":42,
    "gn:feature_class":"P",
    "gn:feature_code":"PPL",
    "gn:name":"Jiwangcun",
    "gn:population":0,
    "gn:timezone":"Asia/Shanghai",
    "iso:country":"CN",
    "name:zho_x_preferred":[
        "\u5180\u738b\u6751"
    ],
    "wof:name":"Jiwangcun",
    "wof:placetype":"locality"
},
  "geometry": {"coordinates":[115.79679,36.04104],"type":"Point"}
}