{
  "type": "Feature",
  "properties": {
    "gn:admin1_code":"15.0",
    "gn:asciiname":"Fengjiayuan",
    "gn:country_code":"CN",
    "gn:dem":1462,
    "gn:feature_class":"P",
    "gn:feature_code":"PPL",
    "gn:name":"Fengjiayuan",
    "gn:population":0,
    "gn:timezone":"Asia/Shanghai",
    "iso:country":"CN",
    "name:zho_x_preferred":[
        "\u51af\u5bb6\u9662"
    ],
    "wof:name":"Fengjiayuan",
    "wof:placetype":"locality"
},
  "geometry": {"coordinates":[106.55,34.1327],"type":"Point"}
}