{
  "type": "Feature",
  "properties": {
    "gn:admin1_code":"3.0",
    "gn:asciiname":"Kuiqian",
    "gn:country_code":"CN",
    "gn:dem":57,
    "gn:feature_class":"P",
    "gn:feature_code":"PPL",
    "gn:name":"Kuiqian",
    "gn:population":0,
    "gn:timezone":"Asia/Shanghai",
    "iso:country":"CN",
    "name:und_x_variant":[
        "\u8475\u524d"
    ],
    "wof:name":"Kuiqian",
    "wof:placetype":"locality"
},
  "geometry": {"coordinates":[117.00954,29.33597],"type":"Point"}
}