{
  "type": "Feature",
  "properties": {
    "gn:admin1_code":"3.0",
    "gn:asciiname":"Shebei",
    "gn:country_code":"CN",
    "gn:dem":209,
    "gn:feature_class":"P",
    "gn:feature_code":"PPL",
    "gn:name":"Shebei",
    "gn:population":0,
    "gn:timezone":"Asia/Shanghai",
    "iso:country":"CN",
    "name:und_x_variant":[
        "\u793e\u80cc"
    ],
    "wof:name":"Shebei",
    "wof:placetype":"locality"
},
  "geometry": {"coordinates":[115.09784000000001,25.85415],"type":"Point"}
}