{
  "type": "Feature",
  "properties": {
    "gn:admin1_code":"9",
    "gn:asciiname":"Housanli",
    "gn:country_code":"CN",
    "gn:dem":46,
    "gn:feature_class":"P",
    "gn:feature_code":"PPL",
    "gn:name":"Housanli",
    "gn:population":0,
    "gn:timezone":"Asia/Shanghai",
    "iso:country":"CN",
    "name:zho_x_preferred":[
        "\u540e\u4e09\u91cc"
    ],
    "wof:name":"Housanli",
    "wof:placetype":"locality"
},
  "geometry": {"coordinates":[115.82989999999999,35.99917],"type":"Point"}
}