{
  "type": "Feature",
  "properties": {
    "gn:admin1_code":"16.0",
    "gn:asciiname":"Ke'ai",
    "gn:country_code":"CN",
    "gn:dem":633,
    "gn:feature_class":"P",
    "gn:feature_code":"PPL",
    "gn:name":"Ke\u2019ai",
    "gn:population":0,
    "gn:timezone":"Asia/Shanghai",
    "iso:country":"CN",
    "name:und_x_variant":[
        "Ke\u2019ai"
    ],
    "name:zho_x_preferred":[
        "\u53ef\u7231"
    ],
    "wof:name":"Ke'ai",
    "wof:placetype":"locality"
},
  "geometry": {"coordinates":[108.369,24.8752],"type":"Point"}
}