{
  "type": "Feature",
  "properties": {
    "gn:admin1_code":"2",
    "gn:asciiname":"Bogutou",
    "gn:country_code":"CN",
    "gn:dem":148,
    "gn:feature_class":"P",
    "gn:feature_code":"PPL",
    "gn:name":"Bogutou",
    "gn:population":0,
    "gn:timezone":"Asia/Shanghai",
    "iso:country":"CN",
    "name:zho_x_preferred":[
        "\u9e41\u9e2a\u5934"
    ],
    "wof:name":"Bogutou",
    "wof:placetype":"locality"
},
  "geometry": {"coordinates":[119.20576,28.9579],"type":"Point"}
}