{
  "type": "Feature",
  "properties": {
    "gn:admin1_code":"18",
    "gn:asciiname":"La'ao",
    "gn:country_code":"CN",
    "gn:dem":992,
    "gn:feature_class":"P",
    "gn:feature_code":"PPL",
    "gn:name":"La\u2019ao",
    "gn:population":0,
    "gn:timezone":"Asia/Shanghai",
    "iso:country":"CN",
    "name:und_x_variant":[
        "La\u2019ao"
    ],
    "name:zho_x_preferred":[
        "\u62c9\u50b2"
    ],
    "wof:name":"La'ao",
    "wof:placetype":"locality"
},
  "geometry": {"coordinates":[106.867,25.7768],"type":"Point"}
}