{
  "type": "Feature",
  "properties": {
    "gn:admin1_code":"32.0",
    "gn:asciiname":"Laoxiongping",
    "gn:country_code":"CN",
    "gn:dem":981,
    "gn:feature_class":"P",
    "gn:feature_code":"PPL",
    "gn:name":"Laoxiongping",
    "gn:population":0,
    "gn:timezone":"Asia/Shanghai",
    "iso:country":"CN",
    "name:zho_x_preferred":[
        "\u8001\u718a\u576a"
    ],
    "wof:name":"Laoxiongping",
    "wof:placetype":"locality"
},
  "geometry": {"coordinates":[103.949,28.7096],"type":"Point"}
}