{
  "type": "Feature",
  "properties": {
    "gn:admin1_code":"26.0",
    "gn:asciiname":"Wenjiagou",
    "gn:country_code":"CN",
    "gn:dem":1181,
    "gn:feature_class":"P",
    "gn:feature_code":"PPL",
    "gn:name":"Wenjiagou",
    "gn:population":0,
    "gn:timezone":"Asia/Shanghai",
    "iso:country":"CN",
    "name:zho_x_preferred":[
        "\u95ee\u5bb6\u6c9f"
    ],
    "wof:name":"Wenjiagou",
    "wof:placetype":"locality"
},
  "geometry": {"coordinates":[109.33977,33.16035],"type":"Point"}
}