{
  "type": "Feature",
  "properties": {
    "gn:admin1_code":"3.0",
    "gn:asciiname":"Duanzinao",
    "gn:country_code":"CN",
    "gn:dem":150,
    "gn:feature_class":"P",
    "gn:feature_code":"PPL",
    "gn:name":"Duanzinao",
    "gn:population":0,
    "gn:timezone":"Asia/Shanghai",
    "iso:country":"CN",
    "name:und_x_variant":[
        "\u5845\u5b50\u8111"
    ],
    "wof:name":"Duanzinao",
    "wof:placetype":"locality"
},
  "geometry": {"coordinates":[115.61490000000001,26.02595],"type":"Point"}
}