{
  "type": "Feature",
  "properties": {
    "gn:admin1_code":"25",
    "gn:asciiname":"Taitou",
    "gn:country_code":"CN",
    "gn:dem":506,
    "gn:feature_class":"P",
    "gn:feature_code":"PPL",
    "gn:name":"Taitou",
    "gn:population":0,
    "gn:timezone":"Asia/Shanghai",
    "iso:country":"CN",
    "name:zho_x_preferred":[
        "\u62ac\u5934"
    ],
    "wof:name":"Taitou",
    "wof:placetype":"locality"
},
  "geometry": {"coordinates":[118.49299999999999,36.083],"type":"Point"}
}