{
  "type": "Feature",
  "properties": {
    "gn:admin1_code":"19.0",
    "gn:asciiname":"Minjitun",
    "gn:country_code":"CN",
    "gn:dem":8,
    "gn:feature_class":"P",
    "gn:feature_code":"PPL",
    "gn:name":"Minjitun",
    "gn:population":0,
    "gn:timezone":"Asia/Shanghai",
    "iso:country":"CN",
    "name:zho_x_preferred":[
        "\u6c11\u96c6\u5c6f"
    ],
    "wof:name":"Minjitun",
    "wof:placetype":"locality"
},
  "geometry": {"coordinates":[122.47119000000001,41.37536],"type":"Point"}
}