{
  "type": "Feature",
  "properties": {
    "gn:admin1_code":"3.0",
    "gn:asciiname":"Tianjing",
    "gn:country_code":"CN",
    "gn:dem":120,
    "gn:feature_class":"P",
    "gn:feature_code":"PPL",
    "gn:name":"Tianjing",
    "gn:population":0,
    "gn:timezone":"Asia/Shanghai",
    "iso:country":"CN",
    "name:fra_x_preferred":[
        "Tianjing"
    ],
    "name:und_x_variant":[
        "\u5929\u4e95"
    ],
    "name:vie_x_preferred":[
        "Thi\u00ean Kinh"
    ],
    "wof:name":"Tianjing",
    "wof:placetype":"locality"
},
  "geometry": {"coordinates":[115.52719999999999,27.58873],"type":"Point"}
}