{
  "type": "Feature",
  "properties": {
    "gn:admin1_code":"32.0",
    "gn:asciiname":"Heishuihao",
    "gn:country_code":"CN",
    "gn:dem":391,
    "gn:feature_class":"P",
    "gn:feature_code":"PPL",
    "gn:name":"Heishuihao",
    "gn:population":0,
    "gn:timezone":"Asia/Shanghai",
    "iso:country":"CN",
    "name:zho_x_preferred":[
        "\u9ed1\u6c34\u6d69"
    ],
    "wof:name":"Heishuihao",
    "wof:placetype":"locality"
},
  "geometry": {"coordinates":[105.49518,30.9724],"type":"Point"}
}