{
  "type": "Feature",
  "properties": {
    "gn:admin1_code":"16.0",
    "gn:asciiname":"Hongbeicheng",
    "gn:country_code":"CN",
    "gn:dem":47,
    "gn:feature_class":"P",
    "gn:feature_code":"PPL",
    "gn:name":"Hongbeicheng",
    "gn:population":0,
    "gn:timezone":"Asia/Shanghai",
    "iso:country":"CN",
    "name:zho_x_preferred":[
        "\u7ea2\u7891\u57ce"
    ],
    "wof:name":"Hongbeicheng",
    "wof:placetype":"locality"
},
  "geometry": {"coordinates":[109.33199999999999,21.697],"type":"Point"}
}