{
  "type": "Feature",
  "properties": {
    "gn:admin1_code":"32.0",
    "gn:asciiname":"Siwa Gongba",
    "gn:country_code":"CN",
    "gn:dem":3611,
    "gn:feature_class":"P",
    "gn:feature_code":"PPL",
    "gn:name":"Siwa Gongba",
    "gn:population":0,
    "gn:timezone":"Asia/Shanghai",
    "iso:country":"CN",
    "name:zho_x_preferred":[
        "\u56db\u6d3c\u5171\u5df4"
    ],
    "wof:name":"Siwa Gongba",
    "wof:placetype":"locality"
},
  "geometry": {"coordinates":[101.685,32.9925],"type":"Point"}
}