{
  "type": "Feature",
  "properties": {
    "gn:admin1_code":"4.0",
    "gn:asciiname":"Xiaoxugang",
    "gn:country_code":"CN",
    "gn:dem":8,
    "gn:feature_class":"P",
    "gn:feature_code":"PPL",
    "gn:name":"Xiaoxugang",
    "gn:population":0,
    "gn:timezone":"Asia/Shanghai",
    "iso:country":"CN",
    "name:zho_x_preferred":[
        "Xiaoxugang"
    ],
    "name:zho_x_variant":[
        "\u5c0f\u5729\u6e2f"
    ],
    "wof:name":"Xiaoxugang",
    "wof:placetype":"locality"
},
  "geometry": {"coordinates":[120.63994,30.94526],"type":"Point"}
}