{
  "type": "Feature",
  "properties": {
    "gn:admin1_code":"12.0",
    "gn:asciiname":"Heilonggou",
    "gn:country_code":"CN",
    "gn:dem":795,
    "gn:feature_class":"P",
    "gn:feature_code":"PPL",
    "gn:name":"Heilonggou",
    "gn:population":0,
    "gn:timezone":"Asia/Shanghai",
    "iso:country":"CN",
    "name:zho_x_preferred":[
        "\u9ed1\u9f99\u6c9f"
    ],
    "wof:name":"Heilonggou",
    "wof:placetype":"locality"
},
  "geometry": {"coordinates":[111.17444999999999,31.75881],"type":"Point"}
}