{
  "type": "Feature",
  "properties": {
    "gn:admin1_code":"4.0",
    "gn:asciiname":"Liuliancun",
    "gn:country_code":"CN",
    "gn:dem":3,
    "gn:feature_class":"P",
    "gn:feature_code":"PPL",
    "gn:name":"Liuliancun",
    "gn:population":0,
    "gn:timezone":"Asia/Shanghai",
    "iso:country":"CN",
    "name:zho_x_preferred":[
        "\u516d\u8054\u6751"
    ],
    "wof:name":"Liuliancun",
    "wof:placetype":"locality"
},
  "geometry": {"coordinates":[120.01672000000001,34.08252],"type":"Point"}
}