{
  "type": "Feature",
  "properties": {
    "gn:admin1_code":"15.0",
    "gn:asciiname":"Xuejiashui",
    "gn:country_code":"CN",
    "gn:dem":2546,
    "gn:feature_class":"P",
    "gn:feature_code":"PPL",
    "gn:name":"Xuejiashui",
    "gn:population":0,
    "gn:timezone":"Asia/Shanghai",
    "iso:country":"CN",
    "name:zho_x_preferred":[
        "\u859b\u5bb6\u6c34"
    ],
    "wof:name":"Xuejiashui",
    "wof:placetype":"locality"
},
  "geometry": {"coordinates":[103.126,37.4364],"type":"Point"}
}