{
  "type": "Feature",
  "properties": {
    "gn:country":"CN",
    "gn:fcode":"PPLA3",
    "gn:pop":0,
    "iso:country":"CN",
    "name:ceb_x_preferred":[
        "Jiading Qu"
    ],
    "name:ces_x_preferred":[
        "\u0164Ia-ting"
    ],
    "name:cym_x_preferred":[
        "Ardal Jiading"
    ],
    "name:deu_x_preferred":[
        "Jiading"
    ],
    "name:eng_x_preferred":[
        "Jiading District"
    ],
    "name:eus_x_preferred":[
        "Jiading Barrutia"
    ],
    "name:fas_x_preferred":[
        "\u0698\u06cc\u0627\u062f\u06cc\u0646\u06af"
    ],
    "name:gan_x_preferred":[
        "\u5609\u5b9a\u533a"
    ],
    "name:jpn_x_preferred":[
        "\u5609\u5b9a\u533a"
    ],
    "name:kor_x_preferred":[
        "\uc790\ub529\uad6c"
    ],
    "name:lzh_x_preferred":[
        "\u5609\u5b9a\u5340"
    ],
    "name:nan_x_preferred":[
        "Ka-t\u0113ng-khu"
    ],
    "name:nld_x_preferred":[
        "Jiading"
    ],
    "name:nob_x_preferred":[
        "Jiading"
    ],
    "name:por_x_preferred":[
        "Jiading"
    ],
    "name:rus_x_preferred":[
        "\u0426\u0437\u044f\u0434\u0438\u043d"
    ],
    "name:spa_x_preferred":[
        "Jiading"
    ],
    "name:swe_x_preferred":[
        "Jiading"
    ],
    "name:tur_x_preferred":[
        "Jiading"
    ],
    "name:ukr_x_preferred":[
        "\u0420\u0430\u0439\u043e\u043d \u0426\u0437\u044f\u0434\u0456\u043d"
    ],
    "name:unk_x_variant":[
        "\u65b0\u6210\u8def"
    ],
    "name:vie_x_preferred":[
        "Gia \u0110\u1ecbnh"
    ],
    "name:wuu_x_preferred":[
        "\u5609\u5b9a\u533a"
    ],
    "name:yue_x_preferred":[
        "\u5609\u5b9a\u5340"
    ],
    "name:zho_x_preferred":[
        "\u5609\u5b9a\u533a"
    ],
    "qs:name":"Xinchenglu",
    "qs:photos_9r":0,
    "qs:photos_sr":0,
    "qs:pop_sr":"0",
    "wd:wordcount":444,
    "wof:name":"Xinchenglu",
    "wof:placetype":"locality",
    "wof:population":0
},
  "geometry": {"coordinates":[121.26305000000001,31.38864],"type":"Point"}
}