{
  "type": "Feature",
  "properties": {
    "gn:country":"CN",
    "gn:fcode":"PPLA3",
    "gn:pop":0,
    "iso:country":"CN",
    "name:unk_x_variant":[
        "\u65b0\u6210\u8def"
    ],
    "name:zho_x_preferred":[
        "\u5609\u5b9a\u533a"
    ],
    "qs:name":"Xinchenglu",
    "qs:photos_9r":0,
    "qs:photos_sr":0,
    "qs:pop_sr":"0",
    "wd:wordcount":444,
    "wof:name":"Xinchenglu",
    "wof:placetype":"locality",
    "wof:population":0
},
  "geometry": {"coordinates":[121.26305000000001,31.38864],"type":"Point"}
}