{
  "type": "Feature",
  "properties": {
    "gn:admin1_code":"8.0",
    "gn:asciiname":"Heshengcun",
    "gn:country_code":"CN",
    "gn:dem":160,
    "gn:feature_class":"P",
    "gn:feature_code":"PPL",
    "gn:name":"Heshengcun",
    "gn:population":0,
    "gn:timezone":"Asia/Shanghai",
    "iso:country":"CN",
    "name:zho_x_preferred":[
        "\u5408\u80dc\u6751"
    ],
    "wof:name":"Heshengcun",
    "wof:placetype":"locality"
},
  "geometry": {"coordinates":[125.66114,46.24268],"type":"Point"}
}