{
  "type": "Feature",
  "properties": {
    "gn:admin1_code":"16.0",
    "gn:asciiname":"Luancun",
    "gn:country_code":"CN",
    "gn:dem":94,
    "gn:feature_class":"P",
    "gn:feature_code":"PPL",
    "gn:name":"Luancun",
    "gn:population":0,
    "gn:timezone":"Asia/Shanghai",
    "iso:country":"CN",
    "name:zho_x_preferred":[
        "\u9e3e\u6751"
    ],
    "wof:name":"Luancun",
    "wof:placetype":"locality"
},
  "geometry": {"coordinates":[108.82599999999999,23.4478],"type":"Point"}
}