{
  "type": "Feature",
  "properties": {
    "gn:admin1_code":"24.0",
    "gn:asciiname":"Shangwuqicun",
    "gn:country_code":"CN",
    "gn:dem":1009,
    "gn:feature_class":"P",
    "gn:feature_code":"PPL",
    "gn:name":"Shangwuqicun",
    "gn:population":0,
    "gn:timezone":"Asia/Shanghai",
    "iso:country":"CN",
    "name:zho_x_preferred":[
        "\u4e0a\u543e\u5176\u6751"
    ],
    "wof:name":"Shangwuqicun",
    "wof:placetype":"locality"
},
  "geometry": {"coordinates":[114.00346,40.38095],"type":"Point"}
}