{
  "type": "Feature",
  "properties": {
    "gn:admin1_code":"33.0",
    "gn:asciiname":"Tanjia",
    "gn:country_code":"CN",
    "gn:dem":1156,
    "gn:feature_class":"P",
    "gn:feature_code":"PPL",
    "gn:name":"Tanjia",
    "gn:population":0,
    "gn:timezone":"Asia/Shanghai",
    "iso:country":"CN",
    "name:zho_x_preferred":[
        "\u8c2d\u5bb6"
    ],
    "wof:name":"Tanjia",
    "wof:placetype":"locality"
},
  "geometry": {"coordinates":[109.13912999999999,28.55641],"type":"Point"}
}