{
  "type": "Feature",
  "properties": {
    "gn:admin1_code":"10.0",
    "gn:asciiname":"Hehe",
    "gn:country_code":"CN",
    "gn:dem":102,
    "gn:feature_class":"P",
    "gn:feature_code":"PPL",
    "gn:name":"Hehe",
    "gn:population":0,
    "gn:timezone":"Asia/Shanghai",
    "iso:country":"CN",
    "name:und_x_variant":[
        "\u6cb3\u5408"
    ],
    "wof:name":"Hehe",
    "wof:placetype":"locality"
},
  "geometry": {"coordinates":[114.60363999999998,38.50491],"type":"Point"}
}