{
  "type": "Feature",
  "properties": {
    "gn:admin1_code":"8.0",
    "gn:asciiname":"Xinyikuang Sannongchang",
    "gn:country_code":"CN",
    "gn:dem":146,
    "gn:feature_class":"P",
    "gn:feature_code":"PPLF",
    "gn:name":"Xinyikuang Sannongchang",
    "gn:population":0,
    "gn:timezone":"Asia/Shanghai",
    "iso:country":"CN",
    "name:zho_x_preferred":[
        "\u65b0\u4e00\u77ff\u4e09\u519c\u573a"
    ],
    "wof:name":"Xinyikuang Sannongchang",
    "wof:placetype":"locality"
},
  "geometry": {"coordinates":[130.40706,47.3797],"type":"Point"}
}