{
  "type": "Feature",
  "properties": {
    "gn:admin1_code":"12.0",
    "gn:asciiname":"Meiping",
    "gn:country_code":"CN",
    "gn:dem":355,
    "gn:feature_class":"P",
    "gn:feature_code":"PPL",
    "gn:name":"Meiping",
    "gn:population":0,
    "gn:timezone":"Asia/Shanghai",
    "iso:country":"CN",
    "name:ita_x_preferred":[
        "Meiping"
    ],
    "name:zho_x_preferred":[
        "Meiping"
    ],
    "name:zho_x_variant":[
        "\u6885\u576a"
    ],
    "wof:name":"Meiping",
    "wof:placetype":"locality"
},
  "geometry": {"coordinates":[111.29273000000001,30.06048],"type":"Point"}
}