{
  "type": "Feature",
  "properties": {
    "gn:admin1_code":"8.0",
    "gn:asciiname":"Jianbian Nongchang Laoshierdui",
    "gn:country_code":"CN",
    "gn:dem":308,
    "gn:feature_class":"P",
    "gn:feature_code":"PPLF",
    "gn:name":"Jianbian Nongchang Laoshierdui",
    "gn:population":0,
    "gn:timezone":"Asia/Shanghai",
    "iso:country":"CN",
    "name:zho_x_preferred":[
        "\u5efa\u8fb9\u519c\u573a\u8001\u5341\u4e8c\u961f"
    ],
    "wof:name":"Jianbian Nongchang Laoshierdui",
    "wof:placetype":"locality"
},
  "geometry": {"coordinates":[125.32071000000001,50.00012],"type":"Point"}
}