{
  "type": "Feature",
  "properties": {
    "gn:admin1_code":"2.0",
    "gn:asciiname":"Baijielingtou",
    "gn:country_code":"CN",
    "gn:dem":422,
    "gn:feature_class":"P",
    "gn:feature_code":"PPL",
    "gn:name":"Baijielingtou",
    "gn:population":0,
    "gn:timezone":"Asia/Shanghai",
    "iso:country":"CN",
    "name:zho_x_preferred":[
        "\u767d\u8282\u5cad\u5934"
    ],
    "wof:name":"Baijielingtou",
    "wof:placetype":"locality"
},
  "geometry": {"coordinates":[120.42581,28.98371],"type":"Point"}
}