{
  "type": "Feature",
  "properties": {
    "gn:admin1_code":"29.0",
    "gn:asciiname":"Lameidi",
    "gn:country_code":"CN",
    "gn:dem":1702,
    "gn:feature_class":"P",
    "gn:feature_code":"PPL",
    "gn:name":"Lameidi",
    "gn:population":0,
    "gn:timezone":"Asia/Shanghai",
    "iso:country":"CN",
    "name:zho_x_preferred":[
        "\u814a\u7f8e\u5e95"
    ],
    "wof:name":"Lameidi",
    "wof:placetype":"locality"
},
  "geometry": {"coordinates":[99.0899,27.2087],"type":"Point"}
}