{
  "type": "Feature",
  "properties": {
    "gn:admin1_code":"8.0",
    "gn:asciiname":"Yumajia",
    "gn:country_code":"CN",
    "gn:dem":211,
    "gn:feature_class":"P",
    "gn:feature_code":"PPL",
    "gn:name":"Yumajia",
    "gn:population":0,
    "gn:timezone":"Asia/Shanghai",
    "iso:country":"CN",
    "name:zho_x_preferred":[
        "\u4e8e\u9a6c\u67b6"
    ],
    "wof:name":"Yumajia",
    "wof:placetype":"locality"
},
  "geometry": {"coordinates":[123.26425,47.83969],"type":"Point"}
}