{
  "type": "Feature",
  "properties": {
    "gn:admin1_code":"15.0",
    "gn:asciiname":"Qijiagou",
    "gn:country_code":"CN",
    "gn:dem":1710,
    "gn:feature_class":"P",
    "gn:feature_code":"PPL",
    "gn:name":"Qijiagou",
    "gn:population":0,
    "gn:timezone":"Asia/Shanghai",
    "iso:country":"CN",
    "name:zho_x_preferred":[
        "\u7941\u5bb6\u6c9f"
    ],
    "wof:name":"Qijiagou",
    "wof:placetype":"locality"
},
  "geometry": {"coordinates":[106.092,34.91],"type":"Point"}
}