{
  "type": "Feature",
  "properties": {
    "gn:admin1_code":"11",
    "gn:asciiname":"Yanjiao",
    "gn:country_code":"CN",
    "gn:dem":542,
    "gn:feature_class":"P",
    "gn:feature_code":"PPL",
    "gn:name":"Yanjiao",
    "gn:population":0,
    "gn:timezone":"Asia/Shanghai",
    "iso:country":"CN",
    "name:zho_x_preferred":[
        "\u71d5\u90ca\u9547"
    ],
    "wof:name":"Yanjiao",
    "wof:placetype":"locality"
},
  "geometry": {"coordinates":[109.91833,26.35333],"type":"Point"}
}