{
  "type": "Feature",
  "properties": {
    "gn:admin1_code":"7.0",
    "gn:asciiname":"Lijialou",
    "gn:country_code":"CN",
    "gn:dem":275,
    "gn:feature_class":"P",
    "gn:feature_code":"PPL",
    "gn:name":"Lijialou",
    "gn:population":0,
    "gn:timezone":"Asia/Shanghai",
    "iso:country":"CN",
    "name:zho_x_preferred":[
        "\u91cc\u5bb6\u697c"
    ],
    "wof:name":"Lijialou",
    "wof:placetype":"locality"
},
  "geometry": {"coordinates":[119.89234,26.96757],"type":"Point"}
}