{
  "type": "Feature",
  "properties": {
    "gn:admin1_code":"8.0",
    "gn:asciiname":"Bingzhoulitun",
    "gn:country_code":"CN",
    "gn:dem":261,
    "gn:feature_class":"P",
    "gn:feature_code":"PPL",
    "gn:name":"Bingzhoulitun",
    "gn:population":0,
    "gn:timezone":"Asia/Shanghai",
    "iso:country":"CN",
    "name:zho_x_preferred":[
        "\u6ee8\u5dde\u674e\u5c6f"
    ],
    "wof:name":"Bingzhoulitun",
    "wof:placetype":"locality"
},
  "geometry": {"coordinates":[126.46118,48.22569],"type":"Point"}
}