{
  "type": "Feature",
  "properties": {
    "gn:admin1_code":"11.0",
    "gn:asciiname":"Wuli'an",
    "gn:country_code":"CN",
    "gn:dem":568,
    "gn:feature_class":"P",
    "gn:feature_code":"PPL",
    "gn:name":"Wuli\u2019an",
    "gn:population":0,
    "gn:timezone":"Asia/Shanghai",
    "iso:country":"CN",
    "name:und_x_variant":[
        "Wuli\u2019an"
    ],
    "name:zho_x_preferred":[
        "\u4e94\u91cc\u5eb5"
    ],
    "wof:name":"Wuli'an",
    "wof:placetype":"locality"
},
  "geometry": {"coordinates":[109.74387,25.93983],"type":"Point"}
}