{
  "type": "Feature",
  "properties": {
    "gn:admin1_code":"30.0",
    "gn:asciiname":"Dagu'ao",
    "gn:country_code":"CN",
    "gn:dem":746,
    "gn:feature_class":"P",
    "gn:feature_code":"PPL",
    "gn:name":"Dagu\u2019ao",
    "gn:population":0,
    "gn:timezone":"Asia/Shanghai",
    "iso:country":"CN",
    "name:zho_x_preferred":[
        "Dagu\u2019ao"
    ],
    "name:zho_x_variant":[
        "\u5927\u53e4\u5773"
    ],
    "wof:name":"Dagu'ao",
    "wof:placetype":"locality"
},
  "geometry": {"coordinates":[112.14082999999999,24.64083],"type":"Point"}
}