{
  "type": "Feature",
  "properties": {
    "gn:admin1_code":"3",
    "gn:asciiname":"Huangkeng",
    "gn:country_code":"CN",
    "gn:dem":96,
    "gn:feature_class":"P",
    "gn:feature_code":"PPL",
    "gn:name":"Huangkeng",
    "gn:population":0,
    "gn:timezone":"Asia/Shanghai",
    "iso:country":"CN",
    "name:zho_x_preferred":[
        "\u9ec4\u5751"
    ],
    "wof:name":"Huangkeng",
    "wof:placetype":"locality"
},
  "geometry": {"coordinates":[114.863,26.6894],"type":"Point"}
}