{
  "type": "Feature",
  "properties": {
    "gn:admin1_code":"29.0",
    "gn:asciiname":"Xiaoheba",
    "gn:country_code":"CN",
    "gn:dem":2386,
    "gn:feature_class":"P",
    "gn:feature_code":"PPL",
    "gn:name":"Xiaoheba",
    "gn:population":0,
    "gn:timezone":"Asia/Shanghai",
    "iso:country":"CN",
    "name:zho_x_preferred":[
        "\u5c0f\u6cb3\u575d"
    ],
    "wof:name":"Xiaoheba",
    "wof:placetype":"locality"
},
  "geometry": {"coordinates":[101.13200000000001,24.4376],"type":"Point"}
}