{
  "type": "Feature",
  "properties": {
    "gn:admin1_code":"5.0",
    "gn:asciiname":"Renyicun",
    "gn:country_code":"CN",
    "gn:dem":344,
    "gn:feature_class":"P",
    "gn:feature_code":"PPL",
    "gn:name":"Renyicun",
    "gn:population":0,
    "gn:timezone":"Asia/Shanghai",
    "iso:country":"CN",
    "name:und_x_variant":[
        "Renyi Yidui"
    ],
    "name:zho_x_preferred":[
        "\u4ec1\u4e49\u6751"
    ],
    "name:zho_x_variant":[
        "\u4ec1\u4e49\u4e00\u961f"
    ],
    "wof:name":"Renyicun",
    "wof:placetype":"locality"
},
  "geometry": {"coordinates":[125.57939,42.70104],"type":"Point"}
}