{
  "type": "Feature",
  "properties": {
    "gn:admin1_code":"26",
    "gn:asciiname":"Taodabu",
    "gn:country_code":"CN",
    "gn:dem":535,
    "gn:feature_class":"P",
    "gn:feature_code":"PPL",
    "gn:name":"Taodabu",
    "gn:population":0,
    "gn:timezone":"Asia/Shanghai",
    "iso:country":"CN",
    "name:zho_x_preferred":[
        "\u6843\u5927\u5821"
    ],
    "wof:name":"Taodabu",
    "wof:placetype":"locality"
},
  "geometry": {"coordinates":[108.22348999999998,34.33302],"type":"Point"}
}