{
  "type": "Feature",
  "properties": {
    "gn:admin1_code":"7.0",
    "gn:asciiname":"Zhuangshang",
    "gn:country_code":"CN",
    "gn:dem":166,
    "gn:feature_class":"P",
    "gn:feature_code":"PPL",
    "gn:name":"Zhuangshang",
    "gn:population":0,
    "gn:timezone":"Asia/Shanghai",
    "iso:country":"CN",
    "name:zho_x_preferred":[
        "\u5e84\u4e0a"
    ],
    "wof:name":"Zhuangshang",
    "wof:placetype":"locality"
},
  "geometry": {"coordinates":[117.62363999999999,27.14701],"type":"Point"}
}