{
  "type": "Feature",
  "properties": {
    "gn:admin1_code":"12.0",
    "gn:asciiname":"Guanjiaping",
    "gn:country_code":"CN",
    "gn:dem":970,
    "gn:feature_class":"P",
    "gn:feature_code":"PPL",
    "gn:name":"Guanjiaping",
    "gn:population":0,
    "gn:timezone":"Asia/Shanghai",
    "iso:country":"CN",
    "name:zho_x_preferred":[
        "\u5b98\u5bb6\u576a"
    ],
    "wof:name":"Guanjiaping",
    "wof:placetype":"locality"
},
  "geometry": {"coordinates":[110.58695,31.88865],"type":"Point"}
}