{
  "type": "Feature",
  "properties": {
    "gn:admin1_code":"12.0",
    "gn:asciiname":"Nandazaiwu",
    "gn:country_code":"CN",
    "gn:dem":126,
    "gn:feature_class":"P",
    "gn:feature_code":"PPL",
    "gn:name":"Nandazaiwu",
    "gn:population":0,
    "gn:timezone":"Asia/Shanghai",
    "iso:country":"CN",
    "name:zho_x_preferred":[
        "\u5357\u5927\u5728\u5c4b"
    ],
    "wof:name":"Nandazaiwu",
    "wof:placetype":"locality"
},
  "geometry": {"coordinates":[113.73675,29.29913],"type":"Point"}
}