{
  "type": "Feature",
  "properties": {
    "gn:admin1_code":"29.0",
    "gn:asciiname":"Xinganhe",
    "gn:country_code":"CN",
    "gn:dem":1068,
    "gn:feature_class":"P",
    "gn:feature_code":"PPL",
    "gn:name":"Xinganhe",
    "gn:population":0,
    "gn:timezone":"Asia/Shanghai",
    "iso:country":"CN",
    "name:zho_x_preferred":[
        "\u65b0\u5e72\u6cb3"
    ],
    "wof:name":"Xinganhe",
    "wof:placetype":"locality"
},
  "geometry": {"coordinates":[99.6129,22.3946],"type":"Point"}
}