{
  "type": "Feature",
  "properties": {
    "gn:admin1_code":"11.0",
    "gn:asciiname":"Zhaojia Chayuan",
    "gn:country_code":"CN",
    "gn:dem":754,
    "gn:feature_class":"P",
    "gn:feature_code":"PPL",
    "gn:name":"Zhaojia Chayuan",
    "gn:population":0,
    "gn:timezone":"Asia/Shanghai",
    "iso:country":"CN",
    "name:zho_x_preferred":[
        "\u8d75\u5bb6\u8336\u56ed"
    ],
    "wof:name":"Zhaojia Chayuan",
    "wof:placetype":"locality"
},
  "geometry": {"coordinates":[109.84499,29.7322],"type":"Point"}
}