{
  "type": "Feature",
  "properties": {
    "gn:admin1_code":"32.0",
    "gn:asciiname":"Yangsanzui",
    "gn:country_code":"CN",
    "gn:dem":405,
    "gn:feature_class":"P",
    "gn:feature_code":"PPL",
    "gn:name":"Yangsanzui",
    "gn:population":0,
    "gn:timezone":"Asia/Shanghai",
    "iso:country":"CN",
    "name:zho_x_preferred":[
        "\u9633\u4e09\u5480"
    ],
    "wof:name":"Yangsanzui",
    "wof:placetype":"locality"
},
  "geometry": {"coordinates":[105.38599000000001,31.2987],"type":"Point"}
}