{
  "type": "Feature",
  "properties": {
    "gn:admin1_code":"29.0",
    "gn:asciiname":"Maciyi",
    "gn:country_code":"CN",
    "gn:dem":1672,
    "gn:feature_class":"P",
    "gn:feature_code":"PPL",
    "gn:name":"Maciyi",
    "gn:population":0,
    "gn:timezone":"Asia/Shanghai",
    "iso:country":"CN",
    "name:zho_x_preferred":[
        "\u9a6c\u6b21\u9091"
    ],
    "wof:name":"Maciyi",
    "wof:placetype":"locality"
},
  "geometry": {"coordinates":[103.414,23.1232],"type":"Point"}
}