{
  "type": "Feature",
  "properties": {
    "gn:admin1_code":"21.0",
    "gn:asciiname":"Hezuizi",
    "gn:country_code":"CN",
    "gn:dem":1766,
    "gn:feature_class":"P",
    "gn:feature_code":"PPL",
    "gn:name":"Hezuizi",
    "gn:population":0,
    "gn:timezone":"Asia/Shanghai",
    "iso:country":"CN",
    "name:und_x_variant":[
        "\u8d3a\u5480\u5b50"
    ],
    "name:zho_x_preferred":[
        "\u8d3a\u5480\u5b50"
    ],
    "wof:name":"Hezuizi",
    "wof:placetype":"locality"
},
  "geometry": {"coordinates":[106.40228999999999,36.34523],"type":"Point"}
}