{
  "type": "Feature",
  "properties": {
    "gn:admin1_code":"18",
    "gn:asciiname":"Na'an",
    "gn:country_code":"CN",
    "gn:dem":539,
    "gn:feature_class":"P",
    "gn:feature_code":"PPL",
    "gn:name":"Na\u2019an",
    "gn:population":0,
    "gn:timezone":"Asia/Shanghai",
    "iso:country":"CN",
    "name:ces_x_preferred":[
        "Na'an"
    ],
    "name:deu_x_preferred":[
        "Na\u02bfan"
    ],
    "name:fra_x_preferred":[
        "Na'an"
    ],
    "name:heb_x_preferred":[
        "\u05e0\u05e2\u05df"
    ],
    "name:nno_x_preferred":[
        "Na'an"
    ],
    "name:pol_x_preferred":[
        "Na\u2019an"
    ],
    "name:rus_x_preferred":[
        "\u041d\u0430\u0430\u043d"
    ],
    "name:und_x_variant":[
        "Na\u2019an"
    ],
    "name:zho_x_preferred":[
        "\u7eb3\u5cb8"
    ],
    "wof:name":"Na'an",
    "wof:placetype":"locality"
},
  "geometry": {"coordinates":[106.274,25.1087],"type":"Point"}
}