{
  "type": "Feature",
  "properties": {
    "gn:admin1_code":"32.0",
    "gn:asciiname":"Dengmapo",
    "gn:country_code":"CN",
    "gn:dem":2593,
    "gn:feature_class":"P",
    "gn:feature_code":"PPL",
    "gn:name":"Dengmapo",
    "gn:population":0,
    "gn:timezone":"Asia/Shanghai",
    "iso:country":"CN",
    "name:zho_x_preferred":[
        "\u7b49\u9a6c\u5761"
    ],
    "wof:name":"Dengmapo",
    "wof:placetype":"locality"
},
  "geometry": {"coordinates":[102.846,26.4192],"type":"Point"}
}