{
  "type": "Feature",
  "properties": {
    "gn:admin1_code":"8.0",
    "gn:asciiname":"Xinfucun",
    "gn:country_code":"CN",
    "gn:dem":253,
    "gn:feature_class":"P",
    "gn:feature_code":"PPL",
    "gn:name":"Xinfucun",
    "gn:population":0,
    "gn:timezone":"Asia/Shanghai",
    "iso:country":"CN",
    "name:zho_x_preferred":[
        "\u65b0\u798f\u6751"
    ],
    "wof:name":"Xinfucun",
    "wof:placetype":"locality"
},
  "geometry": {"coordinates":[126.15817,47.79364],"type":"Point"}
}