{
  "type": "Feature",
  "properties": {
    "gn:admin1_code":"2.0",
    "gn:asciiname":"Xuejia Zhaiji",
    "gn:country_code":"CN",
    "gn:dem":6,
    "gn:feature_class":"P",
    "gn:feature_code":"PPL",
    "gn:name":"Xuejia Zhaiji",
    "gn:population":0,
    "gn:timezone":"Asia/Shanghai",
    "iso:country":"CN",
    "name:und_x_variant":[
        "\u859b\u5bb6\u5b85\u57fa"
    ],
    "wof:name":"Xuejia Zhaiji",
    "wof:placetype":"locality"
},
  "geometry": {"coordinates":[120.84365,30.89847],"type":"Point"}
}