{
  "type": "Feature",
  "properties": {
    "gn:admin1_code":"10.0",
    "gn:asciiname":"Jiaoqu",
    "gn:country_code":"CN",
    "gn:dem":32,
    "gn:feature_class":"P",
    "gn:feature_code":"PPL",
    "gn:name":"Jiaoqu",
    "gn:population":0,
    "gn:timezone":"Asia/Shanghai",
    "iso:country":"CN",
    "name:eus_x_preferred":[
        "Jiaoqu"
    ],
    "name:rus_x_preferred":[
        "\u0426\u0437\u044f\u043e\u0446\u044e\u0439"
    ],
    "name:swe_x_preferred":[
        "Jiaoqu"
    ],
    "name:zho_x_preferred":[
        "\u4ea4\u6e20"
    ],
    "wof:name":"Jiaoqu",
    "wof:placetype":"locality"
},
  "geometry": {"coordinates":[115.99683,39.37008],"type":"Point"}
}