{
  "type": "Feature",
  "properties": {
    "gn:admin1_code":"3.0",
    "gn:asciiname":"Bianshanxia",
    "gn:country_code":"CN",
    "gn:dem":161,
    "gn:feature_class":"P",
    "gn:feature_code":"PPL",
    "gn:name":"Bianshanxia",
    "gn:population":0,
    "gn:timezone":"Asia/Shanghai",
    "iso:country":"CN",
    "name:und_x_variant":[
        "\u8fb9\u5c71\u4e0b"
    ],
    "wof:name":"Bianshanxia",
    "wof:placetype":"locality"
},
  "geometry": {"coordinates":[114.07441,27.75376],"type":"Point"}
}