{
  "type": "Feature",
  "properties": {
    "gn:admin1_code":"10",
    "gn:asciiname":"Zhijiabao",
    "gn:country_code":"CN",
    "gn:dem":1355,
    "gn:feature_class":"P",
    "gn:feature_code":"PPL",
    "gn:name":"Zhijiabao",
    "gn:population":0,
    "gn:timezone":"Asia/Shanghai",
    "iso:country":"CN",
    "wof:name":"Zhijiabao",
    "wof:placetype":"locality"
},
  "geometry": {"coordinates":[113.98944,41.31306],"type":"Point"}
}