{
  "type": "Feature",
  "properties": {
    "gn:admin1_code":"3.0",
    "gn:asciiname":"Yangsheng",
    "gn:country_code":"CN",
    "gn:dem":253,
    "gn:feature_class":"P",
    "gn:feature_code":"PPL",
    "gn:name":"Yangsheng",
    "gn:population":0,
    "gn:timezone":"Asia/Shanghai",
    "iso:country":"CN",
    "name:und_x_variant":[
        "\u6768\u80dc"
    ],
    "wof:name":"Yangsheng",
    "wof:placetype":"locality"
},
  "geometry": {"coordinates":[115.60181,25.46267000000001],"type":"Point"}
}