{
  "type": "Feature",
  "properties": {
    "gn:admin1_code":"1.0",
    "gn:asciiname":"Yuantuanji",
    "gn:cc2":"CN",
    "gn:country_code":"CN",
    "gn:dem":60,
    "gn:feature_class":"P",
    "gn:feature_code":"PPL",
    "gn:name":"Yuantuanji",
    "gn:population":0,
    "gn:timezone":"Asia/Shanghai",
    "iso:country":"CN",
    "name:und_x_variant":[
        "Y\u00fcan-t\u2019uan",
        "Y\u00fcan-t\u2019uan-chi",
        "Yuantuanji"
    ],
    "wof:name":"Yuantuanji",
    "wof:placetype":"locality"
},
  "geometry": {"coordinates":[117.37472,32.07556],"type":"Point"}
}