{
  "type": "Feature",
  "properties": {
    "gn:admin1_code":"10.0",
    "gn:asciiname":"Jiazui",
    "gn:country_code":"CN",
    "gn:dem":568,
    "gn:feature_class":"P",
    "gn:feature_code":"PPL",
    "gn:name":"Jiazui",
    "gn:population":0,
    "gn:timezone":"Asia/Shanghai",
    "iso:country":"CN",
    "name:zho_x_preferred":[
        "\u7532\u5634"
    ],
    "wof:name":"Jiazui",
    "wof:placetype":"locality"
},
  "geometry": {"coordinates":[115.55879,40.39651],"type":"Point"}
}