{
  "type": "Feature",
  "properties": {
    "gn:admin1_code":"30",
    "gn:asciiname":"Nanhe",
    "gn:country_code":"CN",
    "gn:dem":17,
    "gn:feature_class":"P",
    "gn:feature_code":"PPL",
    "gn:name":"Nanhe",
    "gn:population":0,
    "gn:timezone":"Asia/Urumqi",
    "iso:country":"CN",
    "name:deu_x_preferred":[
        "Nanhe"
    ],
    "name:fra_x_preferred":[
        "Nanhe"
    ],
    "name:zho_x_preferred":[
        "\u5357\u548c"
    ],
    "wof:name":"Nanhe",
    "wof:placetype":"locality"
},
  "geometry": {"coordinates":[110.25355999999999,21.36526],"type":"Point"}
}