{
  "type": "Feature",
  "properties": {
    "gn:admin1_code":"19.0",
    "gn:asciiname":"Tiechangbucun",
    "gn:country_code":"CN",
    "gn:dem":36,
    "gn:feature_class":"P",
    "gn:feature_code":"PPL",
    "gn:name":"Tiechangbucun",
    "gn:population":0,
    "gn:timezone":"Asia/Shanghai",
    "iso:country":"CN",
    "name:zho_x_preferred":[
        "\u94c1\u5382\u5821\u6751"
    ],
    "wof:name":"Tiechangbucun",
    "wof:placetype":"locality"
},
  "geometry": {"coordinates":[119.80547,40.15324],"type":"Point"}
}