{
  "type": "Feature",
  "properties": {
    "gn:admin1_code":"26.0",
    "gn:asciiname":"Nanchangzihao",
    "gn:country_code":"CN",
    "gn:dem":1348,
    "gn:feature_class":"P",
    "gn:feature_code":"PPL",
    "gn:name":"Nanchangzihao",
    "gn:population":0,
    "gn:timezone":"Asia/Shanghai",
    "iso:country":"CN",
    "name:zho_x_preferred":[
        "\u5357\u573a\u5b50\u58d5"
    ],
    "wof:name":"Nanchangzihao",
    "wof:placetype":"locality"
},
  "geometry": {"coordinates":[107.80977,37.72564000000001],"type":"Point"}
}