{
  "type": "Feature",
  "properties": {
    "gn:admin1_code":"25.0",
    "gn:asciiname":"Luwucun",
    "gn:country_code":"CN",
    "gn:dem":10,
    "gn:feature_class":"P",
    "gn:feature_code":"PPL",
    "gn:name":"Luwucun",
    "gn:population":0,
    "gn:timezone":"Asia/Shanghai",
    "iso:country":"CN",
    "name:zho_x_preferred":[
        "\u9c81\u5434\u6751"
    ],
    "wof:name":"Luwucun",
    "wof:placetype":"locality"
},
  "geometry": {"coordinates":[118.16983999999999,37.05316],"type":"Point"}
}