{
  "type": "Feature",
  "properties": {
    "gn:admin1_code":"11.0",
    "gn:asciiname":"Denglongshan",
    "gn:country_code":"CN",
    "gn:dem":112,
    "gn:feature_class":"P",
    "gn:feature_code":"PPL",
    "gn:name":"Denglongshan",
    "gn:population":0,
    "gn:timezone":"Asia/Shanghai",
    "iso:country":"CN",
    "name:zho_x_preferred":[
        "\u706f\u9f99\u5c71"
    ],
    "wof:name":"Denglongshan",
    "wof:placetype":"locality"
},
  "geometry": {"coordinates":[113.48945000000001,28.27628],"type":"Point"}
}