{
  "type": "Feature",
  "properties": {
    "gn:admin1_code":"4.0",
    "gn:asciiname":"Zhanggu",
    "gn:country_code":"CN",
    "gn:dem":28,
    "gn:feature_class":"P",
    "gn:feature_code":"PPL",
    "gn:name":"Zhanggu",
    "gn:population":0,
    "gn:timezone":"Asia/Shanghai",
    "iso:country":"CN",
    "name:und_x_variant":[
        "\u5f20\u8c37"
    ],
    "wof:name":"Zhanggu",
    "wof:placetype":"locality"
},
  "geometry": {"coordinates":[118.72681,34.49639000000001],"type":"Point"}
}