{
  "type": "Feature",
  "properties": {
    "gn:admin1_code":"14.0",
    "gn:asciiname":"Layong",
    "gn:country_code":"CN",
    "gn:dem":4502,
    "gn:feature_class":"P",
    "gn:feature_code":"PPL",
    "gn:name":"Layong",
    "gn:population":0,
    "gn:timezone":"Asia/Urumqi",
    "iso:country":"CN",
    "name:zho_x_preferred":[
        "\u62c9\u7528"
    ],
    "wof:name":"Layong",
    "wof:placetype":"locality"
},
  "geometry": {"coordinates":[97.2428,30.4709],"type":"Point"}
}