{
  "type": "Feature",
  "properties": {
    "gn:admin1_code":"12.0",
    "gn:asciiname":"Gujiawan",
    "gn:country_code":"CN",
    "gn:dem":200,
    "gn:feature_class":"P",
    "gn:feature_code":"PPL",
    "gn:name":"Gujiawan",
    "gn:population":0,
    "gn:timezone":"Asia/Shanghai",
    "iso:country":"CN",
    "name:zho_x_preferred":[
        "\u987e\u5bb6\u5846"
    ],
    "wof:name":"Gujiawan",
    "wof:placetype":"locality"
},
  "geometry": {"coordinates":[113.63643999999999,32.11663],"type":"Point"}
}