{
  "type": "Feature",
  "properties": {
    "gn:admin1_code":"30.0",
    "gn:asciiname":"Pianshanling",
    "gn:country_code":"CN",
    "gn:dem":158,
    "gn:feature_class":"P",
    "gn:feature_code":"PPL",
    "gn:name":"Pianshanling",
    "gn:population":0,
    "gn:timezone":"Asia/Shanghai",
    "iso:country":"CN",
    "name:zho_x_preferred":[
        "Pianshanling"
    ],
    "name:zho_x_variant":[
        "\u504f\u5c71\u5cad"
    ],
    "wof:name":"Pianshanling",
    "wof:placetype":"locality"
},
  "geometry": {"coordinates":[113.43194,25.05611],"type":"Point"}
}