{
  "type": "Feature",
  "properties": {
    "gn:admin1_code":"32.0",
    "gn:asciiname":"Teya",
    "gn:country_code":"CN",
    "gn:dem":3253,
    "gn:feature_class":"P",
    "gn:feature_code":"PPL",
    "gn:name":"Teya",
    "gn:population":0,
    "gn:timezone":"Asia/Shanghai",
    "iso:country":"CN",
    "name:ceb_x_preferred":[
        "Teya"
    ],
    "name:deu_x_preferred":[
        "Teya"
    ],
    "name:spa_x_preferred":[
        "Teya"
    ],
    "name:swe_x_preferred":[
        "Teya"
    ],
    "name:zho_x_preferred":[
        "\u7279\u7259"
    ],
    "wof:name":"Teya",
    "wof:placetype":"locality"
},
  "geometry": {"coordinates":[101.077,30.9583],"type":"Point"}
}