{
  "type": "Feature",
  "properties": {
    "gn:admin1_code":"19.0",
    "gn:asciiname":"Liujiagou",
    "gn:country_code":"CN",
    "gn:dem":134,
    "gn:feature_class":"P",
    "gn:feature_code":"PPL",
    "gn:name":"Liujiagou",
    "gn:population":0,
    "gn:timezone":"Asia/Shanghai",
    "iso:country":"CN",
    "name:und_x_variant":[
        "\u5218\u5bb6\u6c9f"
    ],
    "name:zho_x_preferred":[
        "\u5218\u5bb6\u6c9f"
    ],
    "wof:name":"Liujiagou",
    "wof:placetype":"locality"
},
  "geometry": {"coordinates":[125.23718,40.65974],"type":"Point"}
}