{
  "type": "Feature",
  "properties": {
    "gn:admin1_code":"9",
    "gn:asciiname":"Majiazhuang",
    "gn:country_code":"CN",
    "gn:dem":349,
    "gn:feature_class":"P",
    "gn:feature_code":"PPL",
    "gn:name":"Majiazhuang",
    "gn:population":0,
    "gn:timezone":"Asia/Shanghai",
    "iso:country":"CN",
    "name:und_x_variant":[
        "Mazhuang"
    ],
    "name:zho_x_preferred":[
        "\u9a6c\u5bb6\u5e84"
    ],
    "wof:name":"Majiazhuang",
    "wof:placetype":"locality"
},
  "geometry": {"coordinates":[111.55007000000001,33.44315],"type":"Point"}
}