{
  "type": "Feature",
  "properties": {
    "gn:admin1_code":"26.0",
    "gn:asciiname":"Tianchaocun",
    "gn:country_code":"CN",
    "gn:dem":576,
    "gn:feature_class":"P",
    "gn:feature_code":"PPL",
    "gn:name":"Tianchaocun",
    "gn:population":0,
    "gn:timezone":"Asia/Shanghai",
    "iso:country":"CN",
    "name:zho_x_preferred":[
        "\u7530\u6641\u6751"
    ],
    "wof:name":"Tianchaocun",
    "wof:placetype":"locality"
},
  "geometry": {"coordinates":[108.27731,34.40633],"type":"Point"}
}