{
  "type": "Feature",
  "properties": {
    "gn:admin1_code":"32.0",
    "gn:asciiname":"Shuanglongsi",
    "gn:country_code":"CN",
    "gn:dem":569,
    "gn:feature_class":"P",
    "gn:feature_code":"PPL",
    "gn:name":"Shuanglongsi",
    "gn:population":0,
    "gn:timezone":"Asia/Shanghai",
    "iso:country":"CN",
    "name:zho_x_preferred":[
        "\u53cc\u9f99\u5bfa"
    ],
    "wof:name":"Shuanglongsi",
    "wof:placetype":"locality"
},
  "geometry": {"coordinates":[104.36499999999999,31.4222],"type":"Point"}
}