{
  "type": "Feature",
  "properties": {
    "gn:admin1_code":"11",
    "gn:asciiname":"Chaoyang",
    "gn:country_code":"CN",
    "gn:dem":698,
    "gn:feature_class":"P",
    "gn:feature_code":"PPL",
    "gn:name":"Chaoyang",
    "gn:population":0,
    "gn:timezone":"Asia/Shanghai",
    "iso:country":"CN",
    "name:ceb_x_preferred":[
        "Chaoyang"
    ],
    "name:ces_x_preferred":[
        "\u010cchao-jang"
    ],
    "name:deu_x_preferred":[
        "Chaoyang"
    ],
    "name:eus_x_preferred":[
        "Chaoyang"
    ],
    "name:fra_x_preferred":[
        "Chaoyang"
    ],
    "name:mlg_x_preferred":[
        "Chaoyang"
    ],
    "name:nld_x_preferred":[
        "Chaoyang"
    ],
    "name:nor_x_preferred":[
        "Chaoyang"
    ],
    "name:pol_x_preferred":[
        "Chaoyang"
    ],
    "name:rus_x_preferred":[
        "\u0427\u0430\u043e\u044f\u043d"
    ],
    "name:spa_x_preferred":[
        "Chaoyang"
    ],
    "name:swe_x_preferred":[
        "Chaoyang"
    ],
    "name:tur_x_preferred":[
        "Chaoyang"
    ],
    "wof:name":"Chaoyang",
    "wof:placetype":"locality"
},
  "geometry": {"coordinates":[111.30083,27.46944],"type":"Point"}
}