{
  "type": "Feature",
  "properties": {
    "gn:admin1_code":"1.0",
    "gn:asciiname":"Dongwulizhuangcun",
    "gn:country_code":"CN",
    "gn:dem":29,
    "gn:feature_class":"P",
    "gn:feature_code":"PPL",
    "gn:name":"Dongwulizhuangcun",
    "gn:population":0,
    "gn:timezone":"Asia/Shanghai",
    "iso:country":"CN",
    "name:zho_x_preferred":[
        "\u4e1c\u4e94\u91cc\u5e84\u6751"
    ],
    "wof:name":"Dongwulizhuangcun",
    "wof:placetype":"locality"
},
  "geometry": {"coordinates":[115.99481000000002,32.6279],"type":"Point"}
}