{
  "type": "Feature",
  "properties": {
    "gn:admin1_code":"18",
    "gn:asciiname":"Mayangpo",
    "gn:country_code":"CN",
    "gn:dem":1213,
    "gn:feature_class":"P",
    "gn:feature_code":"PPL",
    "gn:name":"Mayangpo",
    "gn:population":0,
    "gn:timezone":"Asia/Shanghai",
    "iso:country":"CN",
    "name:zho_x_preferred":[
        "\u9ebb\u79e7\u5761"
    ],
    "wof:name":"Mayangpo",
    "wof:placetype":"locality"
},
  "geometry": {"coordinates":[105.226,25.9336],"type":"Point"}
}