{
  "type": "Feature",
  "properties": {
    "gn:admin1_code":"29.0",
    "gn:asciiname":"Malade",
    "gn:country_code":"CN",
    "gn:dem":1862,
    "gn:feature_class":"P",
    "gn:feature_code":"PPL",
    "gn:name":"Malade",
    "gn:population":0,
    "gn:timezone":"Asia/Shanghai",
    "iso:country":"CN",
    "name:zho_x_preferred":[
        "\u9a82\u62c9\u7684"
    ],
    "wof:name":"Malade",
    "wof:placetype":"locality"
},
  "geometry": {"coordinates":[99.7302,22.6855],"type":"Point"}
}