{
  "type": "Feature",
  "properties": {
    "gn:admin1_code":"10",
    "gn:asciiname":"Kangmachang",
    "gn:country_code":"CN",
    "gn:dem":42,
    "gn:feature_class":"P",
    "gn:feature_code":"PPL",
    "gn:name":"Kangmachang",
    "gn:population":0,
    "gn:timezone":"Asia/Shanghai",
    "iso:country":"CN",
    "name:zho_x_preferred":[
        "\u5eb7\u9a6c\u660c"
    ],
    "wof:name":"Kangmachang",
    "wof:placetype":"locality"
},
  "geometry": {"coordinates":[114.886,36.8026],"type":"Point"}
}