{
  "type": "Feature",
  "properties": {
    "gn:admin1_code":"32.0",
    "gn:asciiname":"Zhu'erwo",
    "gn:country_code":"CN",
    "gn:dem":1792,
    "gn:feature_class":"P",
    "gn:feature_code":"PPL",
    "gn:name":"Zhu\u2019erwo",
    "gn:population":0,
    "gn:timezone":"Asia/Shanghai",
    "iso:country":"CN",
    "name:und_x_variant":[
        "Zhu\u2019erwo"
    ],
    "name:zho_x_preferred":[
        "\u7af9\u513f\u7a9d"
    ],
    "wof:name":"Zhu'erwo",
    "wof:placetype":"locality"
},
  "geometry": {"coordinates":[103.44,28.3119],"type":"Point"}
}