{
  "type": "Feature",
  "properties": {
    "gn:admin1_code":"4.0",
    "gn:asciiname":"Xiachenzhuang",
    "gn:country_code":"CN",
    "gn:dem":25,
    "gn:feature_class":"P",
    "gn:feature_code":"PPL",
    "gn:name":"Xiachenzhuang",
    "gn:population":0,
    "gn:timezone":"Asia/Shanghai",
    "iso:country":"CN",
    "name:zho_x_preferred":[
        "\u4e0b\u9648\u5e84"
    ],
    "wof:name":"Xiachenzhuang",
    "wof:placetype":"locality"
},
  "geometry": {"coordinates":[118.67492,32.93584],"type":"Point"}
}