{
  "type": "Feature",
  "properties": {
    "gn:admin1_code":"4.0",
    "gn:asciiname":"Panjidun",
    "gn:country_code":"CN",
    "gn:dem":7,
    "gn:feature_class":"P",
    "gn:feature_code":"PPL",
    "gn:name":"Panjidun",
    "gn:population":0,
    "gn:timezone":"Asia/Shanghai",
    "iso:country":"CN",
    "name:zho_x_preferred":[
        "\u76d8\u57fa\u58a9"
    ],
    "wof:name":"Panjidun",
    "wof:placetype":"locality"
},
  "geometry": {"coordinates":[121.35262,32.08629000000001],"type":"Point"}
}