{
  "type": "Feature",
  "properties": {
    "gn:admin1_code":"24.0",
    "gn:asciiname":"Xihuyan",
    "gn:country_code":"CN",
    "gn:dem":850,
    "gn:feature_class":"P",
    "gn:feature_code":"PPL",
    "gn:name":"Xihuyan",
    "gn:population":0,
    "gn:timezone":"Asia/Shanghai",
    "iso:country":"CN",
    "name:zho_x_preferred":[
        "\u897f\u547c\u5ef6"
    ],
    "wof:name":"Xihuyan",
    "wof:placetype":"locality"
},
  "geometry": {"coordinates":[112.55745,38.49335],"type":"Point"}
}