{
  "type": "Feature",
  "properties": {
    "gn:admin1_code":"4.0",
    "gn:asciiname":"Daqiaocun",
    "gn:country_code":"CN",
    "gn:dem":32,
    "gn:feature_class":"P",
    "gn:feature_code":"PPL",
    "gn:name":"Daqiaocun",
    "gn:population":0,
    "gn:timezone":"Asia/Shanghai",
    "iso:country":"CN",
    "name:zho_x_preferred":[
        "\u5927\u6865\u6751"
    ],
    "wof:name":"Daqiaocun",
    "wof:placetype":"locality"
},
  "geometry": {"coordinates":[117.97168000000001,34.03607],"type":"Point"}
}