{
  "type": "Feature",
  "properties": {
    "gn:admin1_code":"16.0",
    "gn:asciiname":"Xiajia",
    "gn:country_code":"CN",
    "gn:dem":377,
    "gn:feature_class":"P",
    "gn:feature_code":"PPL",
    "gn:name":"Xiajia",
    "gn:population":0,
    "gn:timezone":"Asia/Shanghai",
    "iso:country":"CN",
    "name:zho_x_preferred":[
        "\u4e0b\u52a0"
    ],
    "wof:name":"Xiajia",
    "wof:placetype":"locality"
},
  "geometry": {"coordinates":[107.63500000000001,24.0055],"type":"Point"}
}