{
  "type": "Feature",
  "properties": {
    "gn:admin1_code":"18.0",
    "gn:asciiname":"Gechangping",
    "gn:country_code":"CN",
    "gn:dem":599,
    "gn:feature_class":"P",
    "gn:feature_code":"PPL",
    "gn:name":"Gechangping",
    "gn:population":0,
    "gn:timezone":"Asia/Shanghai",
    "iso:country":"CN",
    "name:zho_x_preferred":[
        "\u6b4c\u573a\u576a"
    ],
    "wof:name":"Gechangping",
    "wof:placetype":"locality"
},
  "geometry": {"coordinates":[109.25700000000001,26.9445],"type":"Point"}
}