{
  "type": "Feature",
  "properties": {
    "gn:admin1_code":"2",
    "gn:asciiname":"Kuzhujing",
    "gn:country_code":"CN",
    "gn:dem":630,
    "gn:feature_class":"P",
    "gn:feature_code":"PPL",
    "gn:name":"Kuzhujing",
    "gn:population":0,
    "gn:timezone":"Asia/Shanghai",
    "iso:country":"CN",
    "name:zho_x_preferred":[
        "\u5e93\u7af9\u4e95"
    ],
    "wof:name":"Kuzhujing",
    "wof:placetype":"locality"
},
  "geometry": {"coordinates":[119.77222,27.79139],"type":"Point"}
}