{
  "type": "Feature",
  "properties": {
    "gn:admin1_code":"24.0",
    "gn:asciiname":"Jiaozili",
    "gn:country_code":"CN",
    "gn:dem":949,
    "gn:feature_class":"P",
    "gn:feature_code":"PPL",
    "gn:name":"Jiaozili",
    "gn:population":0,
    "gn:timezone":"Asia/Shanghai",
    "iso:country":"CN",
    "name:zho_x_preferred":[
        "\u4ea4\u5b50\u91cc"
    ],
    "wof:name":"Jiaozili",
    "wof:placetype":"locality"
},
  "geometry": {"coordinates":[111.56341,36.99433],"type":"Point"}
}