{
  "type": "Feature",
  "properties": {
    "gn:admin1_code":"30.0",
    "gn:asciiname":"Fengshanxin",
    "gn:country_code":"CN",
    "gn:dem":15,
    "gn:feature_class":"P",
    "gn:feature_code":"PPL",
    "gn:name":"Fengshanxin",
    "gn:population":0,
    "gn:timezone":"Asia/Shanghai",
    "iso:country":"CN",
    "name:zho_x_preferred":[
        "\u9cf3\u5c71\u65b0"
    ],
    "wof:name":"Fengshanxin",
    "wof:placetype":"locality"
},
  "geometry": {"coordinates":[113.00694,22.30929],"type":"Point"}
}