{
  "type": "Feature",
  "properties": {
    "gn:admin1_code":"25",
    "gn:asciiname":"Shezhuang",
    "gn:country_code":"CN",
    "gn:dem":28,
    "gn:feature_class":"P",
    "gn:feature_code":"PPL",
    "gn:name":"Shezhuang",
    "gn:population":0,
    "gn:timezone":"Asia/Shanghai",
    "iso:country":"CN",
    "name:zho_x_preferred":[
        "\u4f58\u5e84"
    ],
    "wof:name":"Shezhuang",
    "wof:placetype":"locality"
},
  "geometry": {"coordinates":[116.02800000000001,37.0648],"type":"Point"}
}