{
  "type": "Feature",
  "properties": {
    "gn:admin1_code":"8.0",
    "gn:asciiname":"Yejiatun",
    "gn:country_code":"CN",
    "gn:dem":189,
    "gn:feature_class":"P",
    "gn:feature_code":"PPL",
    "gn:name":"Yejiatun",
    "gn:population":0,
    "gn:timezone":"Asia/Shanghai",
    "iso:country":"CN",
    "name:zho_x_preferred":[
        "\u53f6\u5bb6\u5c6f"
    ],
    "wof:name":"Yejiatun",
    "wof:placetype":"locality"
},
  "geometry": {"coordinates":[125.63630000000001,45.87600000000001],"type":"Point"}
}