{
  "type": "Feature",
  "properties": {
    "gn:admin1_code":"30.0",
    "gn:asciiname":"Pudongcun",
    "gn:country_code":"CN",
    "gn:dem":6,
    "gn:feature_class":"P",
    "gn:feature_code":"PPL",
    "gn:name":"Pudongcun",
    "gn:population":0,
    "gn:timezone":"Asia/Shanghai",
    "iso:country":"CN",
    "name:zho_x_preferred":[
        "\u6d66\u4e1c\u6751"
    ],
    "wof:name":"Pudongcun",
    "wof:placetype":"locality"
},
  "geometry": {"coordinates":[116.30951,23.54916],"type":"Point"}
}