{
  "type": "Feature",
  "properties": {
    "gn:admin1_code":"1.0",
    "gn:asciiname":"Taomiaocun",
    "gn:country_code":"CN",
    "gn:dem":37,
    "gn:feature_class":"P",
    "gn:feature_code":"PPL",
    "gn:name":"Taomiaocun",
    "gn:population":0,
    "gn:timezone":"Asia/Shanghai",
    "iso:country":"CN",
    "name:zho_x_preferred":[
        "\u9676\u5e99\u6751"
    ],
    "wof:name":"Taomiaocun",
    "wof:placetype":"locality"
},
  "geometry": {"coordinates":[116.0213,33.66856],"type":"Point"}
}