{
  "type": "Feature",
  "properties": {
    "gn:admin1_code":"29.0",
    "gn:asciiname":"Tengmieshan",
    "gn:country_code":"CN",
    "gn:dem":1259,
    "gn:feature_class":"P",
    "gn:feature_code":"PPL",
    "gn:name":"Tengmieshan",
    "gn:population":0,
    "gn:timezone":"Asia/Shanghai",
    "iso:country":"CN",
    "name:zho_x_preferred":[
        "\u85e4\u7bfe\u5c71"
    ],
    "wof:name":"Tengmieshan",
    "wof:placetype":"locality"
},
  "geometry": {"coordinates":[101.327,21.7801],"type":"Point"}
}