{
  "type": "Feature",
  "properties": {
    "gn:admin1_code":"11.0",
    "gn:asciiname":"Angjiahu",
    "gn:country_code":"CN",
    "gn:dem":419,
    "gn:feature_class":"P",
    "gn:feature_code":"PPL",
    "gn:name":"Angjiahu",
    "gn:population":0,
    "gn:timezone":"Asia/Shanghai",
    "iso:country":"CN",
    "name:zho_x_preferred":[
        "\u6602\u5bb6\u6e56"
    ],
    "wof:name":"Angjiahu",
    "wof:placetype":"locality"
},
  "geometry": {"coordinates":[109.66101,28.83017000000001],"type":"Point"}
}