{
  "type": "Feature",
  "properties": {
    "gn:admin1_code":"30",
    "gn:asciiname":"Tianqinglang",
    "gn:cc2":"CN",
    "gn:country_code":"CN",
    "gn:dem":31,
    "gn:feature_class":"P",
    "gn:feature_code":"PPL",
    "gn:name":"Tianqinglang",
    "gn:population":0,
    "gn:timezone":"Asia/Urumqi",
    "iso:country":"CN",
    "name:zho_x_preferred":[
        "Tien-ch\u2019ing-lang"
    ],
    "wof:name":"Tianqinglang",
    "wof:placetype":"locality"
},
  "geometry": {"coordinates":[110.23778,20.30556],"type":"Point"}
}