{
  "type": "Feature",
  "properties": {
    "gn:admin1_code":"13",
    "gn:asciiname":"Yilaleke",
    "gn:country_code":"CN",
    "gn:dem":1385,
    "gn:feature_class":"P",
    "gn:feature_code":"PPL",
    "gn:name":"Yilaleke",
    "gn:population":0,
    "gn:timezone":"Asia/Shanghai",
    "iso:country":"CN",
    "name:und_x_variant":[
        "\u4f9d\u62c9\u52d2\u514b"
    ],
    "wof:name":"Yilaleke",
    "wof:placetype":"locality"
},
  "geometry": {"coordinates":[76.03641999999998,39.56424000000001],"type":"Point"}
}