{
  "type": "Feature",
  "properties": {
    "gn:admin1_code":"18",
    "gn:asciiname":"Narong",
    "gn:country_code":"CN",
    "gn:dem":749,
    "gn:feature_class":"P",
    "gn:feature_code":"PPL",
    "gn:name":"Narong",
    "gn:population":0,
    "gn:timezone":"Asia/Shanghai",
    "iso:country":"CN",
    "name:zho_x_preferred":[
        "\u7eb3\u7ed2"
    ],
    "wof:name":"Narong",
    "wof:placetype":"locality"
},
  "geometry": {"coordinates":[105.96299999999999,25.1518],"type":"Point"}
}