{
  "type": "Feature",
  "properties": {
    "gn:admin1_code":"16.0",
    "gn:asciiname":"Nongcai",
    "gn:country_code":"CN",
    "gn:dem":672,
    "gn:feature_class":"P",
    "gn:feature_code":"PPL",
    "gn:name":"Nongcai",
    "gn:population":0,
    "gn:timezone":"Asia/Shanghai",
    "iso:country":"CN",
    "name:zho_x_preferred":[
        "\u5f04\u624d"
    ],
    "wof:name":"Nongcai",
    "wof:placetype":"locality"
},
  "geometry": {"coordinates":[107.82899999999999,24.1773],"type":"Point"}
}