{
  "type": "Feature",
  "properties": {
    "gn:admin1_code":"24.0",
    "gn:asciiname":"Liujiawan",
    "gn:country_code":"CN",
    "gn:dem":1418,
    "gn:feature_class":"P",
    "gn:feature_code":"PPL",
    "gn:name":"Liujiawan",
    "gn:population":0,
    "gn:timezone":"Asia/Shanghai",
    "iso:country":"CN",
    "name:zho_x_preferred":[
        "\u5218\u5bb6\u6e7e"
    ],
    "wof:name":"Liujiawan",
    "wof:placetype":"locality"
},
  "geometry": {"coordinates":[111.60578,39.52768],"type":"Point"}
}