{
  "type": "Feature",
  "properties": {
    "gn:admin1_code":"29.0",
    "gn:asciiname":"Laozhaizi",
    "gn:country_code":"CN",
    "gn:dem":1852,
    "gn:feature_class":"P",
    "gn:feature_code":"PPL",
    "gn:name":"Laozhaizi",
    "gn:population":0,
    "gn:timezone":"Asia/Shanghai",
    "iso:country":"CN",
    "name:zho_x_preferred":[
        "\u8001\u5be8\u5b50"
    ],
    "wof:name":"Laozhaizi",
    "wof:placetype":"locality"
},
  "geometry": {"coordinates":[98.6225,24.8663],"type":"Point"}
}