{
  "type": "Feature",
  "properties": {
    "gn:admin1_code":"30",
    "gn:asciiname":"Wushi",
    "gn:country_code":"CN",
    "gn:dem":152,
    "gn:feature_class":"P",
    "gn:feature_code":"PPLA4",
    "gn:name":"Wushi",
    "gn:population":0,
    "gn:timezone":"Asia/Shanghai",
    "iso:country":"CN",
    "name:ceb_x_preferred":[
        "Wushi"
    ],
    "name:deu_x_preferred":[
        "Wushi"
    ],
    "name:fra_x_preferred":[
        "Wushi"
    ],
    "name:swe_x_preferred":[
        "Wushi"
    ],
    "name:und_x_variant":[
        "\u4e4c\u77f3",
        "Wushi Zhen",
        "\u4e4c\u77f3\u9547"
    ],
    "wof:name":"Wushi",
    "wof:placetype":"locality"
},
  "geometry": {"coordinates":[115.19441999999999,23.62639],"type":"Point"}
}