{
  "type": "Feature",
  "properties": {
    "gn:admin1_code":"2.0",
    "gn:asciiname":"Tangxili",
    "gn:country_code":"CN",
    "gn:dem":388,
    "gn:feature_class":"P",
    "gn:feature_code":"PPL",
    "gn:name":"Tangxili",
    "gn:population":0,
    "gn:timezone":"Asia/Shanghai",
    "iso:country":"CN",
    "name:zho_x_preferred":[
        "\u5858\u6eaa\u91cc"
    ],
    "wof:name":"Tangxili",
    "wof:placetype":"locality"
},
  "geometry": {"coordinates":[119.44234,28.95701],"type":"Point"}
}