{
  "type": "Feature",
  "properties": {
    "gn:admin1_code":"16.0",
    "gn:asciiname":"Lalian",
    "gn:country_code":"CN",
    "gn:dem":118,
    "gn:feature_class":"P",
    "gn:feature_code":"PPL",
    "gn:name":"Lalian",
    "gn:population":0,
    "gn:timezone":"Asia/Shanghai",
    "iso:country":"CN",
    "name:ceb_x_preferred":[
        "L\u0101li\u0101n"
    ],
    "name:fas_x_preferred":[
        "\u0644\u0627\u0644\u06cc\u0627\u0646"
    ],
    "name:fra_x_preferred":[
        "Lalian"
    ],
    "name:pol_x_preferred":[
        "Lalian"
    ],
    "name:por_x_preferred":[
        "Lalian"
    ],
    "name:urd_x_preferred":[
        "\u0644\u0627\u0644\u06cc\u0627\u06ba"
    ],
    "name:zho_x_preferred":[
        "\u62c9\u7ec3"
    ],
    "wof:name":"Lalian",
    "wof:placetype":"locality"
},
  "geometry": {"coordinates":[109.702,24.7152],"type":"Point"}
}