{
  "type": "Feature",
  "properties": {
    "gn:admin1_code":"5.0",
    "gn:asciiname":"Xinxingcun",
    "gn:country_code":"CN",
    "gn:dem":159,
    "gn:feature_class":"P",
    "gn:feature_code":"PPL",
    "gn:name":"Xinxingcun",
    "gn:population":0,
    "gn:timezone":"Asia/Shanghai",
    "iso:country":"CN",
    "name:zho_x_preferred":[
        "\u65b0\u5174\u6751"
    ],
    "wof:name":"Xinxingcun",
    "wof:placetype":"locality"
},
  "geometry": {"coordinates":[122.53442,45.21692],"type":"Point"}
}