{
  "type": "Feature",
  "properties": {
    "gn:admin1_code":"5.0",
    "gn:asciiname":"Dongshihao",
    "gn:country_code":"CN",
    "gn:dem":169,
    "gn:feature_class":"P",
    "gn:feature_code":"PPL",
    "gn:name":"Dongshihao",
    "gn:population":0,
    "gn:timezone":"Asia/Shanghai",
    "iso:country":"CN",
    "name:zho_x_preferred":[
        "\u4e1c\u5341\u53f7"
    ],
    "wof:name":"Dongshihao",
    "wof:placetype":"locality"
},
  "geometry": {"coordinates":[123.84372999999999,44.30246],"type":"Point"}
}