{
  "type": "Feature",
  "properties": {
    "gn:admin1_code":"13",
    "gn:asciiname":"A'erxianguole",
    "gn:country_code":"CN",
    "gn:dem":2285,
    "gn:feature_class":"P",
    "gn:feature_code":"PPL",
    "gn:name":"A\u2019erxianguole",
    "gn:population":0,
    "gn:timezone":"Asia/Urumqi",
    "iso:country":"CN",
    "name:und_x_variant":[
        "A\u2019erxianguole",
        "\u963f\u5c14\u5148\u90ed\u52d2"
    ],
    "wof:name":"A'erxianguole",
    "wof:placetype":"locality"
},
  "geometry": {"coordinates":[84.6524,43.2582],"type":"Point"}
}