{
  "type": "Feature",
  "properties": {
    "gn:admin1_code":"16.0",
    "gn:asciiname":"Nuning",
    "gn:country_code":"CN",
    "gn:dem":255,
    "gn:feature_class":"P",
    "gn:feature_code":"PPL",
    "gn:name":"Nuning",
    "gn:population":0,
    "gn:timezone":"Asia/Shanghai",
    "iso:country":"CN",
    "name:zho_x_preferred":[
        "\u6012\u4f5e"
    ],
    "wof:name":"Nuning",
    "wof:placetype":"locality"
},
  "geometry": {"coordinates":[106.97199999999999,22.2621],"type":"Point"}
}