{
  "type": "Feature",
  "properties": {
    "gn:admin1_code":"20.0",
    "gn:asciiname":"Ganzhihan",
    "gn:country_code":"CN",
    "gn:dem":1580,
    "gn:feature_class":"P",
    "gn:feature_code":"PPL",
    "gn:name":"Ganzhihan",
    "gn:population":0,
    "gn:timezone":"Asia/Shanghai",
    "iso:country":"CN",
    "name:und_x_variant":[
        "\u5e72\u53ea\u6c49"
    ],
    "wof:name":"Ganzhihan",
    "wof:placetype":"locality"
},
  "geometry": {"coordinates":[111.38742000000001,41.06113],"type":"Point"}
}