{
  "type": "Feature",
  "properties": {
    "gn:admin1_code":"24.0",
    "gn:asciiname":"Duanzhuang",
    "gn:country_code":"CN",
    "gn:dem":1121,
    "gn:feature_class":"P",
    "gn:feature_code":"PPL",
    "gn:name":"Duanzhuang",
    "gn:population":0,
    "gn:timezone":"Asia/Shanghai",
    "iso:country":"CN",
    "name:zho_x_preferred":[
        "\u6bb5\u5e84"
    ],
    "wof:name":"Duanzhuang",
    "wof:placetype":"locality"
},
  "geometry": {"coordinates":[111.86857000000001,35.67742],"type":"Point"}
}