{
  "type": "Feature",
  "properties": {
    "gn:admin1_code":"11",
    "gn:asciiname":"Tawo",
    "gn:country_code":"CN",
    "gn:dem":419,
    "gn:feature_class":"P",
    "gn:feature_code":"PPLA4",
    "gn:name":"Tawo",
    "gn:population":0,
    "gn:timezone":"Asia/Shanghai",
    "iso:country":"CN",
    "name:und_x_variant":[
        "Tawo Zhen",
        "Tawo"
    ],
    "name:zho_x_preferred":[
        "\u5854\u5367"
    ],
    "name:zho_x_variant":[
        "\u5854\u5367\u9547"
    ],
    "wof:name":"Tawo",
    "wof:placetype":"locality"
},
  "geometry": {"coordinates":[109.95846,29.19476],"type":"Point"}
}