{
  "type": "Feature",
  "properties": {
    "gn:admin1_code":"11",
    "gn:asciiname":"Shangjiaping",
    "gn:country_code":"CN",
    "gn:dem":1222,
    "gn:feature_class":"P",
    "gn:feature_code":"PPL",
    "gn:name":"Shangjiaping",
    "gn:population":0,
    "gn:timezone":"Asia/Shanghai",
    "iso:country":"CN",
    "name:zho_x_preferred":[
        "\u5c1a\u5bb6\u576a"
    ],
    "wof:name":"Shangjiaping",
    "wof:placetype":"locality"
},
  "geometry": {"coordinates":[111.90718,25.22822],"type":"Point"}
}