{
  "type": "Feature",
  "properties": {
    "gn:admin1_code":"3.0",
    "gn:asciiname":"Xintianpu",
    "gn:country_code":"CN",
    "gn:dem":9,
    "gn:feature_class":"P",
    "gn:feature_code":"PPL",
    "gn:name":"Xintianpu",
    "gn:population":0,
    "gn:timezone":"Asia/Shanghai",
    "iso:country":"CN",
    "name:und_x_variant":[
        "\u65b0\u6dfb\u94fa"
    ],
    "wof:name":"Xintianpu",
    "wof:placetype":"locality"
},
  "geometry": {"coordinates":[116.00633000000001,28.74231],"type":"Point"}
}