{
  "type": "Feature",
  "properties": {
    "gn:admin1_code":"3.0",
    "gn:asciiname":"Dongjiadian",
    "gn:country_code":"CN",
    "gn:dem":131,
    "gn:feature_class":"P",
    "gn:feature_code":"PPL",
    "gn:name":"Dongjiadian",
    "gn:population":0,
    "gn:timezone":"Asia/Shanghai",
    "iso:country":"CN",
    "name:und_x_variant":[
        "\u8463\u5bb6\u5e97"
    ],
    "wof:name":"Dongjiadian",
    "wof:placetype":"locality"
},
  "geometry": {"coordinates":[115.02312999999999,28.63300000000001],"type":"Point"}
}