{
  "type": "Feature",
  "properties": {
    "gn:admin1_code":"22.0",
    "gn:asciiname":"Baimaguancun",
    "gn:country_code":"CN",
    "gn:dem":373,
    "gn:feature_class":"P",
    "gn:feature_code":"PPL",
    "gn:name":"Baimaguancun",
    "gn:population":0,
    "gn:timezone":"Asia/Shanghai",
    "iso:country":"CN",
    "name:zho_x_preferred":[
        "\u767d\u9a6c\u5173\u6751"
    ],
    "wof:name":"Baimaguancun",
    "wof:placetype":"locality"
},
  "geometry": {"coordinates":[116.90966,40.71384000000001],"type":"Point"}
}