{
  "type": "Feature",
  "properties": {
    "gn:admin1_code":"4.0",
    "gn:asciiname":"Jinhuyuye",
    "gn:country_code":"CN",
    "gn:dem":7,
    "gn:feature_class":"P",
    "gn:feature_code":"PPL",
    "gn:name":"Jinhuyuye",
    "gn:population":0,
    "gn:timezone":"Asia/Shanghai",
    "iso:country":"CN",
    "name:zho_x_preferred":[
        "Jinhuyuye"
    ],
    "name:zho_x_variant":[
        "\u91d1\u6e56\u6e14\u4e1a"
    ],
    "wof:name":"Jinhuyuye",
    "wof:placetype":"locality"
},
  "geometry": {"coordinates":[119.28463000000001,33.15432],"type":"Point"}
}