{
  "type": "Feature",
  "properties": {
    "gn:admin1_code":"10",
    "gn:asciiname":"Taipingwan",
    "gn:country_code":"CN",
    "gn:dem":1015,
    "gn:feature_class":"P",
    "gn:feature_code":"PPL",
    "gn:name":"Taipingwan",
    "gn:population":0,
    "gn:timezone":"Asia/Shanghai",
    "iso:country":"CN",
    "name:zho_x_preferred":[
        "\u592a\u5e73\u6e7e"
    ],
    "wof:name":"Taipingwan",
    "wof:placetype":"locality"
},
  "geometry": {"coordinates":[114.4794,40.83448],"type":"Point"}
}