{
  "type": "Feature",
  "properties": {
    "gn:admin1_code":"32.0",
    "gn:asciiname":"Xinsancun",
    "gn:country_code":"CN",
    "gn:dem":1367,
    "gn:feature_class":"P",
    "gn:feature_code":"PPL",
    "gn:name":"Xinsancun",
    "gn:population":0,
    "gn:timezone":"Asia/Shanghai",
    "iso:country":"CN",
    "name:zho_x_preferred":[
        "\u65b0\u4e09\u6751"
    ],
    "wof:name":"Xinsancun",
    "wof:placetype":"locality"
},
  "geometry": {"coordinates":[102.08799999999999,26.1423],"type":"Point"}
}