{
  "type": "Feature",
  "properties": {
    "gn:admin1_code":"8.0",
    "gn:asciiname":"Qianshengcun",
    "gn:country_code":"CN",
    "gn:dem":166,
    "gn:feature_class":"P",
    "gn:feature_code":"PPL",
    "gn:name":"Qianshengcun",
    "gn:population":0,
    "gn:timezone":"Asia/Shanghai",
    "iso:country":"CN",
    "name:zho_x_preferred":[
        "\u524d\u80dc\u6751"
    ],
    "wof:name":"Qianshengcun",
    "wof:placetype":"locality"
},
  "geometry": {"coordinates":[125.36382,45.92428],"type":"Point"}
}