{
  "type": "Feature",
  "properties": {
    "gn:admin1_code":"16.0",
    "gn:asciiname":"Mojiawan",
    "gn:country_code":"CN",
    "gn:dem":700,
    "gn:feature_class":"P",
    "gn:feature_code":"PPL",
    "gn:name":"Mojiawan",
    "gn:population":0,
    "gn:timezone":"Asia/Shanghai",
    "iso:country":"CN",
    "name:zho_x_preferred":[
        "\u83ab\u5bb6\u6e7e"
    ],
    "wof:name":"Mojiawan",
    "wof:placetype":"locality"
},
  "geometry": {"coordinates":[106.995,25.0649],"type":"Point"}
}