{
  "type": "Feature",
  "properties": {
    "gn:admin1_code":"25",
    "gn:asciiname":"Beisongling",
    "gn:country_code":"CN",
    "gn:dem":4,
    "gn:feature_class":"P",
    "gn:feature_code":"PPL",
    "gn:name":"Beisongling",
    "gn:population":0,
    "gn:timezone":"Asia/Shanghai",
    "iso:country":"CN",
    "name:zho_x_preferred":[
        "\u5317\u5b8b\u5cad"
    ],
    "wof:name":"Beisongling",
    "wof:placetype":"locality"
},
  "geometry": {"coordinates":[119.017,37.0751],"type":"Point"}
}