{
  "type": "Feature",
  "properties": {
    "gn:admin1_code":"9.0",
    "gn:asciiname":"Jingqianying",
    "gn:country_code":"CN",
    "gn:dem":151,
    "gn:feature_class":"P",
    "gn:feature_code":"PPL",
    "gn:name":"Jingqianying",
    "gn:population":0,
    "gn:timezone":"Asia/Shanghai",
    "iso:country":"CN",
    "name:zho_x_preferred":[
        "\u4e95\u524d\u8425"
    ],
    "wof:name":"Jingqianying",
    "wof:placetype":"locality"
},
  "geometry": {"coordinates":[111.78774,32.6316],"type":"Point"}
}