{
  "type": "Feature",
  "properties": {
    "gn:admin1_code":"24.0",
    "gn:asciiname":"Hedi",
    "gn:country_code":"CN",
    "gn:dem":1861,
    "gn:feature_class":"P",
    "gn:feature_code":"PPL",
    "gn:name":"Hedi",
    "gn:population":0,
    "gn:timezone":"Asia/Shanghai",
    "iso:country":"CN",
    "name:zho_x_preferred":[
        "\u6cb3\u5e95"
    ],
    "wof:name":"Hedi",
    "wof:placetype":"locality"
},
  "geometry": {"coordinates":[112.06139,36.78946],"type":"Point"}
}