{
  "type": "Feature",
  "properties": {
    "gn:admin1_code":"30",
    "gn:asciiname":"Anmin",
    "gn:country_code":"CN",
    "gn:dem":37,
    "gn:feature_class":"P",
    "gn:feature_code":"PPL",
    "gn:name":"Anmin",
    "gn:population":0,
    "gn:timezone":"Asia/Shanghai",
    "iso:country":"CN",
    "name:zho_x_preferred":[
        "\u5b89\u6c11"
    ],
    "wof:name":"Anmin",
    "wof:placetype":"locality"
},
  "geometry": {"coordinates":[116.94844000000001,23.77407],"type":"Point"}
}