{
  "type": "Feature",
  "properties": {
    "gn:admin1_code":"12.0",
    "gn:asciiname":"Huangnitu",
    "gn:country_code":"CN",
    "gn:dem":722,
    "gn:feature_class":"P",
    "gn:feature_code":"PPL",
    "gn:name":"Huangnitu",
    "gn:population":0,
    "gn:timezone":"Asia/Shanghai",
    "iso:country":"CN",
    "name:zho_x_preferred":[
        "\u9ec4\u6ce5\u51f8"
    ],
    "wof:name":"Huangnitu",
    "wof:placetype":"locality"
},
  "geometry": {"coordinates":[110.11154999999999,32.52648],"type":"Point"}
}