{
  "type": "Feature",
  "properties": {
    "gn:admin1_code":"14.0",
    "gn:asciiname":"Baixiong",
    "gn:country_code":"CN",
    "gn:dem":3770,
    "gn:feature_class":"P",
    "gn:feature_code":"PPL",
    "gn:name":"Baixiong",
    "gn:population":0,
    "gn:timezone":"Asia/Urumqi",
    "iso:country":"CN",
    "name:zho_x_preferred":[
        "\u767d\u96c4"
    ],
    "wof:name":"Baixiong",
    "wof:placetype":"locality"
},
  "geometry": {"coordinates":[93.69114,30.39653],"type":"Point"}
}