{
  "type": "Feature",
  "properties": {
    "gn:admin1_code":"8.0",
    "gn:asciiname":"Toujingcun",
    "gn:country_code":"CN",
    "gn:dem":218,
    "gn:feature_class":"P",
    "gn:feature_code":"PPL",
    "gn:name":"Toujingcun",
    "gn:population":0,
    "gn:timezone":"Asia/Shanghai",
    "iso:country":"CN",
    "name:zho_x_preferred":[
        "\u5934\u4e95\u6751"
    ],
    "wof:name":"Toujingcun",
    "wof:placetype":"locality"
},
  "geometry": {"coordinates":[127.2726,47.39822],"type":"Point"}
}