{
  "type": "Feature",
  "properties": {
    "gn:admin1_code":"22.0",
    "gn:asciiname":"Taozhuang",
    "gn:country_code":"CN",
    "gn:dem":37,
    "gn:feature_class":"P",
    "gn:feature_code":"PPL",
    "gn:name":"Taozhuang",
    "gn:population":0,
    "gn:timezone":"Asia/Shanghai",
    "iso:country":"CN",
    "name:mlg_x_preferred":[
        "Taozhuang"
    ],
    "name:zho_x_preferred":[
        "\u9676\u5e84"
    ],
    "name:zho_x_variant":[
        "\u9676\u5e84\u9547"
    ],
    "wof:name":"Taozhuang",
    "wof:placetype":"locality"
},
  "geometry": {"coordinates":[116.50857000000001,39.86696],"type":"Point"}
}