{
  "type": "Feature",
  "properties": {
    "gn:admin1_code":"18",
    "gn:asciiname":"Baihejing",
    "gn:country_code":"CN",
    "gn:dem":1004,
    "gn:feature_class":"P",
    "gn:feature_code":"PPL",
    "gn:name":"Baihejing",
    "gn:population":0,
    "gn:timezone":"Asia/Shanghai",
    "iso:country":"CN",
    "name:zho_x_preferred":[
        "\u767d\u9e64\u4e95"
    ],
    "wof:name":"Baihejing",
    "wof:placetype":"locality"
},
  "geometry": {"coordinates":[107.029,27.0987],"type":"Point"}
}