{
  "type": "Feature",
  "properties": {
    "gn:admin1_code":"1.0",
    "gn:asciiname":"Zhuduncun",
    "gn:country_code":"CN",
    "gn:dem":54,
    "gn:feature_class":"P",
    "gn:feature_code":"PPL",
    "gn:name":"Zhuduncun",
    "gn:population":0,
    "gn:timezone":"Asia/Shanghai",
    "iso:country":"CN",
    "name:zho_x_preferred":[
        "\u795d\u58a9\u6751"
    ],
    "wof:name":"Zhuduncun",
    "wof:placetype":"locality"
},
  "geometry": {"coordinates":[116.63760000000001,31.67389],"type":"Point"}
}