{
  "type": "Feature",
  "properties": {
    "gn:admin1_code":"4.0",
    "gn:asciiname":"Wangying",
    "gn:country_code":"CN",
    "gn:dem":0,
    "gn:feature_class":"P",
    "gn:feature_code":"PPL",
    "gn:name":"Wangying",
    "gn:population":0,
    "gn:timezone":"Asia/Shanghai",
    "iso:country":"CN",
    "name:zho_x_preferred":[
        "Wangying"
    ],
    "name:zho_x_variant":[
        "\u6c6a\u8425"
    ],
    "wof:name":"Wangying",
    "wof:placetype":"locality"
},
  "geometry": {"coordinates":[120.14543,34.26867],"type":"Point"}
}