{
  "type": "Feature",
  "properties": {
    "gn:admin1_code":"12",
    "gn:asciiname":"Bailizhou",
    "gn:country_code":"CN",
    "gn:dem":45,
    "gn:feature_class":"P",
    "gn:feature_code":"PPLA4",
    "gn:name":"Bailizhou",
    "gn:population":0,
    "gn:timezone":"Asia/Shanghai",
    "iso:country":"CN",
    "name:und_x_variant":[
        "\u767e\u91cc\u6d32",
        "Bailizhou Zhen",
        "\u767e\u91cc\u6d32\u9547"
    ],
    "wof:name":"Bailizhou",
    "wof:placetype":"locality"
},
  "geometry": {"coordinates":[111.80041,30.40522],"type":"Point"}
}