{
  "type": "Feature",
  "properties": {
    "gn:admin1_code":"1.0",
    "gn:asciiname":"Tongxing",
    "gn:country_code":"CN",
    "gn:dem":20,
    "gn:feature_class":"P",
    "gn:feature_code":"PPL",
    "gn:name":"Tongxing",
    "gn:population":0,
    "gn:timezone":"Asia/Shanghai",
    "iso:country":"CN",
    "name:zho_x_preferred":[
        "\u540c\u5174"
    ],
    "wof:name":"Tongxing",
    "wof:placetype":"locality"
},
  "geometry": {"coordinates":[116.50154000000001,29.91214],"type":"Point"}
}