{
  "type": "Feature",
  "properties": {
    "gn:admin1_code":"3.0",
    "gn:asciiname":"Yangtiekeng",
    "gn:country_code":"CN",
    "gn:dem":41,
    "gn:feature_class":"P",
    "gn:feature_code":"PPL",
    "gn:name":"Yangtiekeng",
    "gn:population":0,
    "gn:timezone":"Asia/Shanghai",
    "iso:country":"CN",
    "name:und_x_variant":[
        "\u6768\u94c1\u5751"
    ],
    "wof:name":"Yangtiekeng",
    "wof:placetype":"locality"
},
  "geometry": {"coordinates":[116.35973,28.14022000000001],"type":"Point"}
}