{
  "type": "Feature",
  "properties": {
    "gn:admin1_code":"4.0",
    "gn:asciiname":"Pu'ancun",
    "gn:country_code":"CN",
    "gn:dem":4,
    "gn:feature_class":"P",
    "gn:feature_code":"PPL",
    "gn:name":"Pu\u2019ancun",
    "gn:population":0,
    "gn:timezone":"Asia/Shanghai",
    "iso:country":"CN",
    "name:und_x_variant":[
        "Pu\u2019ancun"
    ],
    "name:zho_x_preferred":[
        "\u666e\u5b89\u6751"
    ],
    "wof:name":"Pu'ancun",
    "wof:placetype":"locality"
},
  "geometry": {"coordinates":[119.14447,34.48108],"type":"Point"}
}