{
  "type": "Feature",
  "properties": {
    "gn:admin1_code":"18",
    "gn:asciiname":"Banposhang",
    "gn:country_code":"CN",
    "gn:dem":1479,
    "gn:feature_class":"P",
    "gn:feature_code":"PPL",
    "gn:name":"Banposhang",
    "gn:population":0,
    "gn:timezone":"Asia/Shanghai",
    "iso:country":"CN",
    "name:zho_x_preferred":[
        "\u534a\u5761\u4e0a"
    ],
    "wof:name":"Banposhang",
    "wof:placetype":"locality"
},
  "geometry": {"coordinates":[105.905,26.5348],"type":"Point"}
}