{
  "type": "Feature",
  "properties": {
    "gn:admin1_code":"9.0",
    "gn:asciiname":"Shiwulibu",
    "gn:country_code":"CN",
    "gn:dem":143,
    "gn:feature_class":"P",
    "gn:feature_code":"PPL",
    "gn:name":"Shiwulibu",
    "gn:population":0,
    "gn:timezone":"Asia/Shanghai",
    "iso:country":"CN",
    "name:zho_x_preferred":[
        "\u5341\u4e94\u91cc\u5821"
    ],
    "wof:name":"Shiwulibu",
    "wof:placetype":"locality"
},
  "geometry": {"coordinates":[112.66185,33.12779],"type":"Point"}
}