{
  "type": "Feature",
  "properties": {
    "gn:admin1_code":"19.0",
    "gn:asciiname":"Dianxinzi",
    "gn:country_code":"CN",
    "gn:dem":88,
    "gn:feature_class":"P",
    "gn:feature_code":"PPL",
    "gn:name":"Dianxinzi",
    "gn:population":0,
    "gn:timezone":"Asia/Shanghai",
    "iso:country":"CN",
    "name:und_x_variant":[
        "\u5e97\u5fc3\u5b50"
    ],
    "wof:name":"Dianxinzi",
    "wof:placetype":"locality"
},
  "geometry": {"coordinates":[123.98591,40.59685],"type":"Point"}
}