{
  "type": "Feature",
  "properties": {
    "gn:admin1_code":"7",
    "gn:asciiname":"Jiangxia",
    "gn:country_code":"CN",
    "gn:dem":509,
    "gn:feature_class":"P",
    "gn:feature_code":"PPL",
    "gn:name":"Jiangxia",
    "gn:population":0,
    "gn:timezone":"Asia/Shanghai",
    "iso:country":"CN",
    "name:zho_x_preferred":[
        "\u6c5f\u4e0b"
    ],
    "wof:name":"Jiangxia",
    "wof:placetype":"locality"
},
  "geometry": {"coordinates":[118.42097,25.96142],"type":"Point"}
}