{
  "type": "Feature",
  "properties": {
    "gn:admin1_code":"30.0",
    "gn:asciiname":"Qunshengcun",
    "gn:country_code":"CN",
    "gn:dem":83,
    "gn:feature_class":"P",
    "gn:feature_code":"PPL",
    "gn:name":"Qunshengcun",
    "gn:population":0,
    "gn:timezone":"Asia/Shanghai",
    "iso:country":"CN",
    "name:zho_x_preferred":[
        "\u7fa4\u80dc\u6751"
    ],
    "wof:name":"Qunshengcun",
    "wof:placetype":"locality"
},
  "geometry": {"coordinates":[111.64667,23.73877],"type":"Point"}
}