{
  "type": "Feature",
  "properties": {
    "gn:admin1_code":"1.0",
    "gn:asciiname":"Zhaixia",
    "gn:country_code":"CN",
    "gn:dem":428,
    "gn:feature_class":"P",
    "gn:feature_code":"PPL",
    "gn:name":"Zhaixia",
    "gn:population":0,
    "gn:timezone":"Asia/Shanghai",
    "iso:country":"CN",
    "name:zho_x_preferred":[
        "\u5be8\u4e0b"
    ],
    "wof:name":"Zhaixia",
    "wof:placetype":"locality"
},
  "geometry": {"coordinates":[118.34237,30.03616],"type":"Point"}
}