{
  "type": "Feature",
  "properties": {
    "gn:admin1_code":"14.0",
    "gn:asciiname":"Luotepu",
    "gn:country_code":"CN",
    "gn:dem":4430,
    "gn:feature_class":"P",
    "gn:feature_code":"PPL",
    "gn:name":"Luotepu",
    "gn:population":0,
    "gn:timezone":"Asia/Urumqi",
    "iso:country":"CN",
    "name:zho_x_preferred":[
        "\u6d1b\u7279\u666e"
    ],
    "wof:name":"Luotepu",
    "wof:placetype":"locality"
},
  "geometry": {"coordinates":[96.27099,30.9436],"type":"Point"}
}