{
  "type": "Feature",
  "properties": {
    "gn:admin1_code":"7",
    "gn:asciiname":"Tianmazhong Zhuchang",
    "gn:country_code":"CN",
    "gn:dem":29,
    "gn:feature_class":"P",
    "gn:feature_code":"PPLF",
    "gn:name":"Tianmazhong Zhuchang",
    "gn:population":0,
    "gn:timezone":"Asia/Shanghai",
    "iso:country":"CN",
    "name:und_x_variant":[
        "Yaoma Nongchang",
        "\u5929\u9a6c\u519c\u573a",
        "Tianma Nongchang",
        "Tianmazhong Zhuchang"
    ],
    "wof:name":"Tianmazhong Zhuchang",
    "wof:placetype":"locality"
},
  "geometry": {"coordinates":[118.1147,24.62629],"type":"Point"}
}