{
  "type": "Feature",
  "properties": {
    "gn:admin1_code":"25.0",
    "gn:asciiname":"Sanlihezicun",
    "gn:country_code":"CN",
    "gn:dem":53,
    "gn:feature_class":"P",
    "gn:feature_code":"PPL",
    "gn:name":"Sanlihezicun",
    "gn:population":0,
    "gn:timezone":"Asia/Shanghai",
    "iso:country":"CN",
    "name:zho_x_preferred":[
        "\u4e09\u91cc\u6cb3\u5b50\u6751"
    ],
    "wof:name":"Sanlihezicun",
    "wof:placetype":"locality"
},
  "geometry": {"coordinates":[119.93528000000001,37.15068],"type":"Point"}
}