{
  "type": "Feature",
  "properties": {
    "gn:admin1_code":"19.0",
    "gn:asciiname":"Dabajiazi",
    "gn:country_code":"CN",
    "gn:dem":22,
    "gn:feature_class":"P",
    "gn:feature_code":"PPL",
    "gn:name":"Dabajiazi",
    "gn:population":0,
    "gn:timezone":"Asia/Shanghai",
    "iso:country":"CN",
    "name:und_x_variant":[
        "\u5927\u516b\u5bb6\u5b50"
    ],
    "name:zho_x_preferred":[
        "\u5927\u516b\u5bb6\u5b50"
    ],
    "wof:name":"Dabajiazi",
    "wof:placetype":"locality"
},
  "geometry": {"coordinates":[121.37376999999999,41.22248],"type":"Point"}
}