{
  "type": "Feature",
  "properties": {
    "gn:admin1_code":"13.0",
    "gn:asciiname":"Wutanleke",
    "gn:country_code":"CN",
    "gn:dem":2673,
    "gn:feature_class":"P",
    "gn:feature_code":"PPL",
    "gn:name":"Wutanleke",
    "gn:population":0,
    "gn:timezone":"Asia/Shanghai",
    "iso:country":"CN",
    "name:zho_x_preferred":[
        "\u4e4c\u5766\u52d2\u514b"
    ],
    "wof:name":"Wutanleke",
    "wof:placetype":"locality"
},
  "geometry": {"coordinates":[80.71111999999999,36.2182],"type":"Point"}
}