{
  "type": "Feature",
  "properties": {
    "gn:admin1_code":"30.0",
    "gn:asciiname":"Yuanqiancun",
    "gn:country_code":"CN",
    "gn:dem":20,
    "gn:feature_class":"P",
    "gn:feature_code":"PPL",
    "gn:name":"Yuanqiancun",
    "gn:population":0,
    "gn:timezone":"Asia/Shanghai",
    "iso:country":"CN",
    "name:zho_x_preferred":[
        "\u9662\u524d\u6751"
    ],
    "wof:name":"Yuanqiancun",
    "wof:placetype":"locality"
},
  "geometry": {"coordinates":[116.93696,23.71037],"type":"Point"}
}