{
  "type": "Feature",
  "properties": {
    "gn:admin1_code":"10.0",
    "gn:asciiname":"Xilaolizhuang",
    "gn:country_code":"CN",
    "gn:dem":37,
    "gn:feature_class":"P",
    "gn:feature_code":"PPL",
    "gn:name":"Xilaolizhuang",
    "gn:population":0,
    "gn:timezone":"Asia/Shanghai",
    "iso:country":"CN",
    "name:zho_x_preferred":[
        "\u897f\u8001\u91cc\u5e84"
    ],
    "wof:name":"Xilaolizhuang",
    "wof:placetype":"locality"
},
  "geometry": {"coordinates":[118.67173,39.64439],"type":"Point"}
}