{
  "type": "Feature",
  "properties": {
    "gn:admin1_code":"30.0",
    "gn:asciiname":"Baishinao",
    "gn:country_code":"CN",
    "gn:dem":330,
    "gn:feature_class":"P",
    "gn:feature_code":"PPL",
    "gn:name":"Baishinao",
    "gn:population":0,
    "gn:timezone":"Asia/Shanghai",
    "iso:country":"CN",
    "name:und_x_variant":[
        "\u767d\u77f3\u8111"
    ],
    "name:zho_x_preferred":[
        "\u767d\u77f3\u8111"
    ],
    "wof:name":"Baishinao",
    "wof:placetype":"locality"
},
  "geometry": {"coordinates":[115.19450999999999,23.52003],"type":"Point"}
}