{
  "type": "Feature",
  "properties": {
    "gn:admin1_code":"32.0",
    "gn:asciiname":"Maogushan",
    "gn:country_code":"CN",
    "gn:dem":2054,
    "gn:feature_class":"P",
    "gn:feature_code":"PPL",
    "gn:name":"Maogushan",
    "gn:population":0,
    "gn:timezone":"Asia/Shanghai",
    "iso:country":"CN",
    "name:zho_x_preferred":[
        "\u6bdb\u59d1\u5c71"
    ],
    "wof:name":"Maogushan",
    "wof:placetype":"locality"
},
  "geometry": {"coordinates":[101.80544999999999,27.95642],"type":"Point"}
}