{
  "type": "Feature",
  "properties": {
    "gn:admin1_code":"20.0",
    "gn:asciiname":"Hongfeng",
    "gn:country_code":"CN",
    "gn:dem":574,
    "gn:feature_class":"P",
    "gn:feature_code":"PPL",
    "gn:name":"Hongfeng",
    "gn:population":0,
    "gn:timezone":"Asia/Shanghai",
    "iso:country":"CN",
    "name:zho_x_preferred":[
        "\u7ea2\u4e30"
    ],
    "wof:name":"Hongfeng",
    "wof:placetype":"locality"
},
  "geometry": {"coordinates":[117.52482000000001,48.37924],"type":"Point"}
}