{
  "type": "Feature",
  "properties": {
    "gn:admin1_code":"12.0",
    "gn:asciiname":"Wantan",
    "gn:country_code":"CN",
    "gn:dem":1173,
    "gn:feature_class":"P",
    "gn:feature_code":"PPLA4",
    "gn:name":"Wantan",
    "gn:population":0,
    "gn:timezone":"Asia/Shanghai",
    "iso:country":"CN",
    "name:und_x_variant":[
        "Wan-y\u00fcn",
        "Wantan",
        "\u6e7e\u6f6d",
        "Wantan Zhen",
        "\u6e7e\u6f6d\u9547"
    ],
    "wof:name":"Wantan",
    "wof:placetype":"locality"
},
  "geometry": {"coordinates":[110.42359,30.04829],"type":"Point"}
}