{
  "type": "Feature",
  "properties": {
    "gn:admin1_code":"3.0",
    "gn:asciiname":"Jinxia",
    "gn:country_code":"CN",
    "gn:dem":307,
    "gn:feature_class":"P",
    "gn:feature_code":"PPL",
    "gn:name":"Jinxia",
    "gn:population":0,
    "gn:timezone":"Asia/Shanghai",
    "iso:country":"CN",
    "name:zho_x_preferred":[
        "\u9526\u4e0b"
    ],
    "wof:name":"Jinxia",
    "wof:placetype":"locality"
},
  "geometry": {"coordinates":[115.372,24.9738],"type":"Point"}
}