{
  "type": "Feature",
  "properties": {
    "gn:admin1_code":"1.0",
    "gn:asciiname":"Zhaoyuancun",
    "gn:country_code":"CN",
    "gn:dem":38,
    "gn:feature_class":"P",
    "gn:feature_code":"PPL",
    "gn:name":"Zhaoyuancun",
    "gn:population":0,
    "gn:timezone":"Asia/Shanghai",
    "iso:country":"CN",
    "name:zho_x_preferred":[
        "\u8d75\u56ed\u6751"
    ],
    "name:zho_x_variant":[
        "\u8d75\u5143\u6751"
    ],
    "wof:name":"Zhaoyuancun",
    "wof:placetype":"locality"
},
  "geometry": {"coordinates":[116.49451000000001,31.84991],"type":"Point"}
}