{
  "type": "Feature",
  "properties": {
    "gn:admin1_code":"32.0",
    "gn:asciiname":"Maobazi",
    "gn:country_code":"CN",
    "gn:dem":633,
    "gn:feature_class":"P",
    "gn:feature_code":"PPL",
    "gn:name":"Maobazi",
    "gn:population":0,
    "gn:timezone":"Asia/Shanghai",
    "iso:country":"CN",
    "name:zho_x_preferred":[
        "\u8305\u575d\u5b50"
    ],
    "wof:name":"Maobazi",
    "wof:placetype":"locality"
},
  "geometry": {"coordinates":[105.15936000000001,32.2381],"type":"Point"}
}