{
  "type": "Feature",
  "properties": {
    "gn:admin1_code":"19.0",
    "gn:asciiname":"Caojia Wopucun",
    "gn:country_code":"CN",
    "gn:dem":199,
    "gn:feature_class":"P",
    "gn:feature_code":"PPL",
    "gn:name":"Caojia Wopucun",
    "gn:population":0,
    "gn:timezone":"Asia/Shanghai",
    "iso:country":"CN",
    "name:und_x_variant":[
        "Caojiawopucun",
        "Caojia Wopucun"
    ],
    "name:zho_x_preferred":[
        "\u66f9\u5bb6\u7a9d\u94fa\u6751"
    ],
    "wof:name":"Caojia Wopucun",
    "wof:placetype":"locality"
},
  "geometry": {"coordinates":[120.61691999999999,41.52221],"type":"Point"}
}