{
  "type": "Feature",
  "properties": {
    "gn:admin1_code":"12.0",
    "gn:asciiname":"Dunshang",
    "gn:country_code":"CN",
    "gn:dem":167,
    "gn:feature_class":"P",
    "gn:feature_code":"PPL",
    "gn:name":"Dunshang",
    "gn:population":0,
    "gn:timezone":"Asia/Shanghai",
    "iso:country":"CN",
    "name:zho_x_preferred":[
        "Dunshang"
    ],
    "name:zho_x_variant":[
        "\u58a9\u4e0a"
    ],
    "wof:name":"Dunshang",
    "wof:placetype":"locality"
},
  "geometry": {"coordinates":[114.31676000000002,29.45331],"type":"Point"}
}