{
  "type": "Feature",
  "properties": {
    "gn:admin1_code":"19.0",
    "gn:asciiname":"Douhugou",
    "gn:country_code":"CN",
    "gn:dem":551,
    "gn:feature_class":"P",
    "gn:feature_code":"PPL",
    "gn:name":"Douhugou",
    "gn:population":0,
    "gn:timezone":"Asia/Shanghai",
    "iso:country":"CN",
    "name:zho_x_preferred":[
        "\u6597\u864e\u6c9f"
    ],
    "wof:name":"Douhugou",
    "wof:placetype":"locality"
},
  "geometry": {"coordinates":[124.803,42.1719],"type":"Point"}
}