{
  "type": "Feature",
  "properties": {
    "gn:admin1_code":"9.0",
    "gn:asciiname":"Xiaweimusi",
    "gn:country_code":"CN",
    "gn:dem":347,
    "gn:feature_class":"P",
    "gn:feature_code":"PPL",
    "gn:name":"Xiaweimusi",
    "gn:population":0,
    "gn:timezone":"Asia/Shanghai",
    "iso:country":"CN",
    "name:zho_x_preferred":[
        "\u4e0b\u5582\u6bcd\u5bfa"
    ],
    "wof:name":"Xiaweimusi",
    "wof:placetype":"locality"
},
  "geometry": {"coordinates":[112.21592,34.20809000000001],"type":"Point"}
}