{
  "type": "Feature",
  "properties": {
    "gn:admin1_code":"19.0",
    "gn:asciiname":"Dadaohugou",
    "gn:country_code":"CN",
    "gn:dem":408,
    "gn:feature_class":"P",
    "gn:feature_code":"PPL",
    "gn:name":"Dadaohugou",
    "gn:population":0,
    "gn:timezone":"Asia/Shanghai",
    "iso:country":"CN",
    "name:zho_x_preferred":[
        "\u5927\u9053\u864e\u6c9f"
    ],
    "wof:name":"Dadaohugou",
    "wof:placetype":"locality"
},
  "geometry": {"coordinates":[119.53257000000001,40.87599],"type":"Point"}
}