{
  "type": "Feature",
  "properties": {
    "gn:admin1_code":"28.0",
    "gn:asciiname":"Yangzhuangzi",
    "gn:country_code":"CN",
    "gn:dem":11,
    "gn:feature_class":"P",
    "gn:feature_code":"PPL",
    "gn:name":"Yangzhuangzi",
    "gn:population":0,
    "gn:timezone":"Asia/Shanghai",
    "iso:country":"CN",
    "name:zho_x_preferred":[
        "\u6768\u5e84\u5b50"
    ],
    "wof:name":"Yangzhuangzi",
    "wof:placetype":"locality"
},
  "geometry": {"coordinates":[116.94289999999999,39.33872],"type":"Point"}
}