{
  "type": "Feature",
  "properties": {
    "gn:admin1_code":"26.0",
    "gn:asciiname":"Hedatai",
    "gn:country_code":"CN",
    "gn:dem":1549,
    "gn:feature_class":"P",
    "gn:feature_code":"PPL",
    "gn:name":"Hedatai",
    "gn:population":0,
    "gn:timezone":"Asia/Shanghai",
    "iso:country":"CN",
    "name:zho_x_preferred":[
        "\u4f55\u5927\u53f0"
    ],
    "wof:name":"Hedatai",
    "wof:placetype":"locality"
},
  "geometry": {"coordinates":[107.43125000000001,37.06293],"type":"Point"}
}