{
  "type": "Feature",
  "properties": {
    "gn:admin1_code":"29.0",
    "gn:asciiname":"Tiposi",
    "gn:country_code":"CN",
    "gn:dem":2409,
    "gn:feature_class":"P",
    "gn:feature_code":"PPL",
    "gn:name":"Tiposi",
    "gn:population":0,
    "gn:timezone":"Asia/Shanghai",
    "iso:country":"CN",
    "name:zho_x_preferred":[
        "\u68af\u5761\u5bfa"
    ],
    "wof:name":"Tiposi",
    "wof:placetype":"locality"
},
  "geometry": {"coordinates":[100.426,25.1365],"type":"Point"}
}