{
  "type": "Feature",
  "properties": {
    "gn:admin1_code":"5.0",
    "gn:asciiname":"Baomacun",
    "gn:country_code":"CN",
    "gn:dem":688,
    "gn:feature_class":"P",
    "gn:feature_code":"PPL",
    "gn:name":"Baomacun",
    "gn:population":0,
    "gn:timezone":"Asia/Shanghai",
    "iso:country":"CN",
    "name:zho_x_preferred":[
        "\u5b9d\u9a6c\u6751"
    ],
    "wof:name":"Baomacun",
    "wof:placetype":"locality"
},
  "geometry": {"coordinates":[128.06861000000001,42.45619],"type":"Point"}
}