{
  "type": "Feature",
  "properties": {
    "gn:admin1_code":"15.0",
    "gn:asciiname":"Nanliqigou",
    "gn:country_code":"CN",
    "gn:dem":1692,
    "gn:feature_class":"P",
    "gn:feature_code":"PPL",
    "gn:name":"Nanliqigou",
    "gn:population":0,
    "gn:timezone":"Asia/Shanghai",
    "iso:country":"CN",
    "name:und_x_variant":[
        "\u5357\u91cc\u65d7\u6c9f"
    ],
    "wof:name":"Nanliqigou",
    "wof:placetype":"locality"
},
  "geometry": {"coordinates":[106.71714,36.80065],"type":"Point"}
}