{
  "type": "Feature",
  "properties": {
    "gn:admin1_code":"1.0",
    "gn:asciiname":"Huayuanhucun",
    "gn:country_code":"CN",
    "gn:dem":21,
    "gn:feature_class":"P",
    "gn:feature_code":"PPL",
    "gn:name":"Huayuanhucun",
    "gn:population":0,
    "gn:timezone":"Asia/Shanghai",
    "iso:country":"CN",
    "name:zho_x_preferred":[
        "\u82b1\u56ed\u6e56\u6751"
    ],
    "wof:name":"Huayuanhucun",
    "wof:placetype":"locality"
},
  "geometry": {"coordinates":[117.81873,33.01068],"type":"Point"}
}