{
  "type": "Feature",
  "properties": {
    "gn:admin1_code":"1.0",
    "gn:asciiname":"Tuanduncun",
    "gn:country_code":"CN",
    "gn:dem":98,
    "gn:feature_class":"P",
    "gn:feature_code":"PPL",
    "gn:name":"Tuanduncun",
    "gn:population":0,
    "gn:timezone":"Asia/Shanghai",
    "iso:country":"CN",
    "name:zho_x_preferred":[
        "\u56e2\u58a9\u6751"
    ],
    "wof:name":"Tuanduncun",
    "wof:placetype":"locality"
},
  "geometry": {"coordinates":[116.4153,31.48602],"type":"Point"}
}