{
  "type": "Feature",
  "properties": {
    "gn:admin1_code":"32.0",
    "gn:asciiname":"Likere",
    "gn:country_code":"CN",
    "gn:dem":2529,
    "gn:feature_class":"P",
    "gn:feature_code":"PPL",
    "gn:name":"Likere",
    "gn:population":0,
    "gn:timezone":"Asia/Shanghai",
    "iso:country":"CN",
    "name:zho_x_preferred":[
        "\u91cc\u67ef\u60f9"
    ],
    "wof:name":"Likere",
    "wof:placetype":"locality"
},
  "geometry": {"coordinates":[102.586,28.2953],"type":"Point"}
}