{
  "type": "Feature",
  "properties": {
    "gn:admin1_code":"19.0",
    "gn:asciiname":"Xiashifodong",
    "gn:country_code":"CN",
    "gn:dem":212,
    "gn:feature_class":"P",
    "gn:feature_code":"PPL",
    "gn:name":"Xiashifodong",
    "gn:population":0,
    "gn:timezone":"Asia/Shanghai",
    "iso:country":"CN",
    "name:zho_x_preferred":[
        "\u4e0b\u77f3\u4f5b\u6d1e"
    ],
    "wof:name":"Xiashifodong",
    "wof:placetype":"locality"
},
  "geometry": {"coordinates":[120.62246,41.14342],"type":"Point"}
}