{
  "type": "Feature",
  "properties": {
    "gn:admin1_code":"30.0",
    "gn:asciiname":"Weigang",
    "gn:country_code":"CN",
    "gn:dem":143,
    "gn:feature_class":"P",
    "gn:feature_code":"PPL",
    "gn:name":"Weigang",
    "gn:population":0,
    "gn:timezone":"Asia/Shanghai",
    "iso:country":"CN",
    "name:und_x_variant":[
        "\u56f4\u5c97"
    ],
    "name:zho_x_preferred":[
        "\u56f4\u5c97"
    ],
    "wof:name":"Weigang",
    "wof:placetype":"locality"
},
  "geometry": {"coordinates":[114.87184999999999,23.34211],"type":"Point"}
}