{
  "type": "Feature",
  "properties": {
    "gn:admin1_code":"10",
    "gn:asciiname":"Dongliangma",
    "gn:country_code":"CN",
    "gn:dem":40,
    "gn:feature_class":"P",
    "gn:feature_code":"PPL",
    "gn:name":"Dongliangma",
    "gn:population":0,
    "gn:timezone":"Asia/Shanghai",
    "iso:country":"CN",
    "name:zho_x_preferred":[
        "\u4e1c\u826f\u9a6c"
    ],
    "wof:name":"Dongliangma",
    "wof:placetype":"locality"
},
  "geometry": {"coordinates":[115.184,37.9427],"type":"Point"}
}