{
  "type": "Feature",
  "properties": {
    "gn:admin1_code":"18",
    "gn:asciiname":"Guiganping",
    "gn:country_code":"CN",
    "gn:dem":1265,
    "gn:feature_class":"P",
    "gn:feature_code":"PPL",
    "gn:name":"Guiganping",
    "gn:population":0,
    "gn:timezone":"Asia/Shanghai",
    "iso:country":"CN",
    "name:zho_x_preferred":[
        "\u8be1\u6746\u576a"
    ],
    "wof:name":"Guiganping",
    "wof:placetype":"locality"
},
  "geometry": {"coordinates":[105.408,25.2782],"type":"Point"}
}