{
  "type": "Feature",
  "properties": {
    "gn:admin1_code":"5.0",
    "gn:asciiname":"Dadihe",
    "gn:country_code":"CN",
    "gn:dem":516,
    "gn:feature_class":"P",
    "gn:feature_code":"PPL",
    "gn:name":"Dadihe",
    "gn:population":0,
    "gn:timezone":"Asia/Shanghai",
    "iso:country":"CN",
    "name:zho_x_preferred":[
        "\u5927\u5730\u6cb3"
    ],
    "wof:name":"Dadihe",
    "wof:placetype":"locality"
},
  "geometry": {"coordinates":[126.45668999999999,42.39414],"type":"Point"}
}