{
  "type": "Feature",
  "properties": {
    "gn:admin1_code":"19.0",
    "gn:asciiname":"Laozhangzicun",
    "gn:country_code":"CN",
    "gn:dem":492,
    "gn:feature_class":"P",
    "gn:feature_code":"PPL",
    "gn:name":"Laozhangzicun",
    "gn:population":0,
    "gn:timezone":"Asia/Shanghai",
    "iso:country":"CN",
    "name:zho_x_preferred":[
        "\u8001\u6756\u5b50\u6751"
    ],
    "wof:name":"Laozhangzicun",
    "wof:placetype":"locality"
},
  "geometry": {"coordinates":[119.49066999999999,41.01938],"type":"Point"}
}