{
  "type": "Feature",
  "properties": {
    "gn:admin1_code":"4.0",
    "gn:asciiname":"Baijiazha",
    "gn:country_code":"CN",
    "gn:dem":5,
    "gn:feature_class":"P",
    "gn:feature_code":"PPL",
    "gn:name":"Baijiazha",
    "gn:population":0,
    "gn:timezone":"Asia/Shanghai",
    "iso:country":"CN",
    "name:zho_x_preferred":[
        "\u67cf\u5bb6\u95f8"
    ],
    "wof:name":"Baijiazha",
    "wof:placetype":"locality"
},
  "geometry": {"coordinates":[120.45956,32.15728],"type":"Point"}
}