{
  "type": "Feature",
  "properties": {
    "gn:admin1_code":"24.0",
    "gn:asciiname":"Shanshenyu",
    "gn:country_code":"CN",
    "gn:dem":1300,
    "gn:feature_class":"P",
    "gn:feature_code":"PPL",
    "gn:name":"Shanshenyu",
    "gn:population":0,
    "gn:timezone":"Asia/Shanghai",
    "iso:country":"CN",
    "name:zho_x_preferred":[
        "\u5c71\u795e\u5cea"
    ],
    "wof:name":"Shanshenyu",
    "wof:placetype":"locality"
},
  "geometry": {"coordinates":[111.07729999999999,36.86622],"type":"Point"}
}