{
  "type": "Feature",
  "properties": {
    "gn:admin1_code":"3.0",
    "gn:asciiname":"Pengjing",
    "gn:country_code":"CN",
    "gn:dem":452,
    "gn:feature_class":"P",
    "gn:feature_code":"PPL",
    "gn:name":"Pengjing",
    "gn:population":0,
    "gn:timezone":"Asia/Shanghai",
    "iso:country":"CN",
    "name:und_x_variant":[
        "\u68da\u5f84"
    ],
    "wof:name":"Pengjing",
    "wof:placetype":"locality"
},
  "geometry": {"coordinates":[114.39176,27.54059],"type":"Point"}
}