{
  "type": "Feature",
  "properties": {
    "gn:admin1_code":"11",
    "gn:asciiname":"Xiejia",
    "gn:country_code":"CN",
    "gn:dem":418,
    "gn:feature_class":"P",
    "gn:feature_code":"PPL",
    "gn:name":"Xiejia",
    "gn:population":0,
    "gn:timezone":"Asia/Shanghai",
    "iso:country":"CN",
    "name:und_x_variant":[
        "\u8c22\u5bb6",
        "Xiejia"
    ],
    "wof:name":"Xiejia",
    "wof:placetype":"locality"
},
  "geometry": {"coordinates":[111.44611,25.80444],"type":"Point"}
}