{
  "type": "Feature",
  "properties": {
    "gn:admin1_code":"2.0",
    "gn:asciiname":"Boshumiao",
    "gn:country_code":"CN",
    "gn:dem":8,
    "gn:feature_class":"P",
    "gn:feature_code":"PPL",
    "gn:name":"Boshumiao",
    "gn:population":0,
    "gn:timezone":"Asia/Shanghai",
    "iso:country":"CN",
    "name:und_x_variant":[
        "\u4f2f\u5885\u5e99"
    ],
    "wof:name":"Boshumiao",
    "wof:placetype":"locality"
},
  "geometry": {"coordinates":[120.66033,30.47315],"type":"Point"}
}