{
  "type": "Feature",
  "properties": {
    "gn:admin1_code":"32.0",
    "gn:asciiname":"Xifanzai",
    "gn:country_code":"CN",
    "gn:dem":2331,
    "gn:feature_class":"P",
    "gn:feature_code":"PPL",
    "gn:name":"Xifanzai",
    "gn:population":0,
    "gn:timezone":"Asia/Shanghai",
    "iso:country":"CN",
    "name:zho_x_preferred":[
        "\u897f\u756a\u518d"
    ],
    "wof:name":"Xifanzai",
    "wof:placetype":"locality"
},
  "geometry": {"coordinates":[102.55947999999999,28.93999],"type":"Point"}
}