{
  "type": "Feature",
  "properties": {
    "gn:admin1_code":"3.0",
    "gn:asciiname":"Zhangling",
    "gn:country_code":"CN",
    "gn:dem":545,
    "gn:feature_class":"P",
    "gn:feature_code":"PPL",
    "gn:name":"Zhangling",
    "gn:population":0,
    "gn:timezone":"Asia/Shanghai",
    "iso:country":"CN",
    "name:und_x_variant":[
        "\u6f33\u5cad"
    ],
    "wof:name":"Zhangling",
    "wof:placetype":"locality"
},
  "geometry": {"coordinates":[116.38141,27.32019],"type":"Point"}
}