{
  "type": "Feature",
  "properties": {
    "gn:admin1_code":"11.0",
    "gn:asciiname":"Luositan",
    "gn:country_code":"CN",
    "gn:dem":453,
    "gn:feature_class":"P",
    "gn:feature_code":"PPL",
    "gn:name":"Luositan",
    "gn:population":0,
    "gn:timezone":"Asia/Shanghai",
    "iso:country":"CN",
    "name:zho_x_preferred":[
        "\u87ba\u86f3\u6ee9"
    ],
    "wof:name":"Luositan",
    "wof:placetype":"locality"
},
  "geometry": {"coordinates":[109.40769,29.47257],"type":"Point"}
}