{
  "type": "Feature",
  "properties": {
    "gn:admin1_code":"21.0",
    "gn:asciiname":"Qianshi",
    "gn:country_code":"CN",
    "gn:dem":1692,
    "gn:feature_class":"P",
    "gn:feature_code":"PPL",
    "gn:name":"Qianshi",
    "gn:population":0,
    "gn:timezone":"Asia/Shanghai",
    "iso:country":"CN",
    "name:und_x_variant":[
        "\u5343\u77f3"
    ],
    "name:zho_x_preferred":[
        "\u5343\u77f3"
    ],
    "wof:name":"Qianshi",
    "wof:placetype":"locality"
},
  "geometry": {"coordinates":[106.39556,36.47831],"type":"Point"}
}