{
  "type": "Feature",
  "properties": {
    "gn:admin1_code":"14.0",
    "gn:asciiname":"Jiejiao",
    "gn:country_code":"CN",
    "gn:dem":3726,
    "gn:feature_class":"P",
    "gn:feature_code":"PPL",
    "gn:name":"Jiejiao",
    "gn:population":0,
    "gn:timezone":"Asia/Urumqi",
    "iso:country":"CN",
    "name:zho_x_preferred":[
        "\u63a5\u4ea4"
    ],
    "wof:name":"Jiejiao",
    "wof:placetype":"locality"
},
  "geometry": {"coordinates":[95.58058,30.76639],"type":"Point"}
}