{
  "type": "Feature",
  "properties": {
    "gn:admin1_code":"3.0",
    "gn:asciiname":"Mibu",
    "gn:country_code":"CN",
    "gn:dem":222,
    "gn:feature_class":"P",
    "gn:feature_code":"PPL",
    "gn:name":"Mibu",
    "gn:population":0,
    "gn:timezone":"Asia/Shanghai",
    "iso:country":"CN",
    "name:und_x_variant":[
        "\u5bc6\u57e0"
    ],
    "wof:name":"Mibu",
    "wof:placetype":"locality"
},
  "geometry": {"coordinates":[116.31146,26.17145],"type":"Point"}
}