{
  "type": "Feature",
  "properties": {
    "gn:admin1_code":"15.0",
    "gn:asciiname":"Maquankou",
    "gn:country_code":"CN",
    "gn:dem":2304,
    "gn:feature_class":"P",
    "gn:feature_code":"PPL",
    "gn:name":"Maquankou",
    "gn:population":0,
    "gn:timezone":"Asia/Shanghai",
    "iso:country":"CN",
    "name:zho_x_preferred":[
        "\u9a6c\u5708\u53e3"
    ],
    "wof:name":"Maquankou",
    "wof:placetype":"locality"
},
  "geometry": {"coordinates":[100.129,38.62300000000001],"type":"Point"}
}