{
  "type": "Feature",
  "properties": {
    "gn:admin1_code":"29.0",
    "gn:asciiname":"Anjiaba",
    "gn:country_code":"CN",
    "gn:dem":1716,
    "gn:feature_class":"P",
    "gn:feature_code":"PPL",
    "gn:name":"Anjiaba",
    "gn:population":0,
    "gn:timezone":"Asia/Shanghai",
    "iso:country":"CN",
    "name:zho_x_preferred":[
        "\u5b89\u5bb6\u575d"
    ],
    "wof:name":"Anjiaba",
    "wof:placetype":"locality"
},
  "geometry": {"coordinates":[104.717,27.4497],"type":"Point"}
}