{
  "type": "Feature",
  "properties": {
    "gn:admin1_code":"26.0",
    "gn:asciiname":"Yindongwan",
    "gn:country_code":"CN",
    "gn:dem":1142,
    "gn:feature_class":"P",
    "gn:feature_code":"PPL",
    "gn:name":"Yindongwan",
    "gn:population":0,
    "gn:timezone":"Asia/Shanghai",
    "iso:country":"CN",
    "name:zho_x_preferred":[
        "\u94f6\u6d1e\u6e7e"
    ],
    "wof:name":"Yindongwan",
    "wof:placetype":"locality"
},
  "geometry": {"coordinates":[109.5121,32.11985],"type":"Point"}
}