{
  "type": "Feature",
  "properties": {
    "gn:admin1_code":"25",
    "gn:asciiname":"Lanjiazhuang",
    "gn:country_code":"CN",
    "gn:dem":8,
    "gn:feature_class":"P",
    "gn:feature_code":"PPL",
    "gn:name":"Lanjiazhuang",
    "gn:population":0,
    "gn:timezone":"Asia/Shanghai",
    "iso:country":"CN",
    "name:zho_x_preferred":[
        "\u84dd\u5bb6\u5e84"
    ],
    "wof:name":"Lanjiazhuang",
    "wof:placetype":"locality"
},
  "geometry": {"coordinates":[120.221,36.3059],"type":"Point"}
}