{
  "type": "Feature",
  "properties": {
    "gn:admin1_code":"13.0",
    "gn:asciiname":"Gurt",
    "gn:country_code":"CN",
    "gn:dem":399,
    "gn:feature_class":"P",
    "gn:feature_code":"PPL",
    "gn:name":"Gurt",
    "gn:population":0,
    "gn:timezone":"Asia/Urumqi",
    "iso:country":"CN",
    "name:uig_x_preferred":[
        "\u06af\u06c8\u0631\u062a"
    ],
    "name:uig_x_variant":[
        "\u0413\u04af\u0440\u0442",
        "G\u00fcrt"
    ],
    "name:und_x_variant":[
        "Gu\u2019ertu",
        "Gu\u2019ertu Zhen"
    ],
    "name:zho_x_preferred":[
        "\u53e4\u5c14\u56fe"
    ],
    "name:zho_x_variant":[
        "\u53e4\u5c14\u56fe\u9547"
    ],
    "wof:name":"Gurt",
    "wof:placetype":"locality"
},
  "geometry": {"coordinates":[83.91190999999998,44.55417],"type":"Point"}
}