{
  "type": "Feature",
  "properties": {
    "gn:admin1_code":"2.0",
    "gn:asciiname":"Youzhukeng",
    "gn:country_code":"CN",
    "gn:dem":55,
    "gn:feature_class":"P",
    "gn:feature_code":"PPL",
    "gn:name":"Youzhukeng",
    "gn:population":0,
    "gn:timezone":"Asia/Shanghai",
    "iso:country":"CN",
    "name:zho_x_preferred":[
        "\u6cb9\u7af9\u5751"
    ],
    "wof:name":"Youzhukeng",
    "wof:placetype":"locality"
},
  "geometry": {"coordinates":[121.6281,28.45896],"type":"Point"}
}