{
  "type": "Feature",
  "properties": {
    "gn:admin1_code":"26.0",
    "gn:asciiname":"Shangluocun",
    "gn:country_code":"CN",
    "gn:dem":910,
    "gn:feature_class":"P",
    "gn:feature_code":"PPL",
    "gn:name":"Shangluocun",
    "gn:population":0,
    "gn:timezone":"Asia/Shanghai",
    "iso:country":"CN",
    "name:zho_x_preferred":[
        "\u5c1a\u7f57\u6751"
    ],
    "wof:name":"Shangluocun",
    "wof:placetype":"locality"
},
  "geometry": {"coordinates":[110.35105,36.29563],"type":"Point"}
}