{
  "type": "Feature",
  "properties": {
    "gn:admin1_code":"29.0",
    "gn:asciiname":"Dashiban",
    "gn:country_code":"CN",
    "gn:dem":1604,
    "gn:feature_class":"P",
    "gn:feature_code":"PPL",
    "gn:name":"Dashiban",
    "gn:population":0,
    "gn:timezone":"Asia/Shanghai",
    "iso:country":"CN",
    "name:und_x_variant":[
        "\u5927\u77f3\u677f"
    ],
    "wof:name":"Dashiban",
    "wof:placetype":"locality"
},
  "geometry": {"coordinates":[103.503,26.993],"type":"Point"}
}