{
  "type": "Feature",
  "properties": {
    "gn:admin1_code":"29.0",
    "gn:asciiname":"Gusuandeng",
    "gn:country_code":"CN",
    "gn:dem":2406,
    "gn:feature_class":"P",
    "gn:feature_code":"PPL",
    "gn:name":"Gusuandeng",
    "gn:population":0,
    "gn:timezone":"Asia/Shanghai",
    "iso:country":"CN",
    "name:zho_x_preferred":[
        "\u83c7\u849c\u767b"
    ],
    "wof:name":"Gusuandeng",
    "wof:placetype":"locality"
},
  "geometry": {"coordinates":[99.18129999999999,26.6562],"type":"Point"}
}