{
  "type": "Feature",
  "properties": {
    "gn:admin1_code":"19.0",
    "gn:asciiname":"Shangbu",
    "gn:country_code":"CN",
    "gn:dem":112,
    "gn:feature_class":"P",
    "gn:feature_code":"PPL",
    "gn:name":"Shangbu",
    "gn:population":0,
    "gn:timezone":"Asia/Shanghai",
    "iso:country":"CN",
    "name:und_x_variant":[
        "Shangpu",
        "\u4e0a\u5821",
        "Shangbu"
    ],
    "wof:name":"Shangbu",
    "wof:placetype":"locality"
},
  "geometry": {"coordinates":[122.95166,40.77198],"type":"Point"}
}