{
  "type": "Feature",
  "properties": {
    "gn:admin1_code":"4.0",
    "gn:asciiname":"Meiduocun",
    "gn:country_code":"CN",
    "gn:dem":6,
    "gn:feature_class":"P",
    "gn:feature_code":"PPL",
    "gn:name":"Meiduocun",
    "gn:population":0,
    "gn:timezone":"Asia/Shanghai",
    "iso:country":"CN",
    "name:und_x_variant":[
        "Meiduo",
        "\u6885\u579b",
        "Meiduocun"
    ],
    "name:zho_x_preferred":[
        "\u6885\u579b\u6751"
    ],
    "wof:name":"Meiduocun",
    "wof:placetype":"locality"
},
  "geometry": {"coordinates":[120.10590000000001,32.40051],"type":"Point"}
}