{
  "type": "Feature",
  "properties": {
    "gn:admin1_code":"7.0",
    "gn:asciiname":"Zhankeng",
    "gn:country_code":"CN",
    "gn:dem":384,
    "gn:feature_class":"P",
    "gn:feature_code":"PPL",
    "gn:name":"Zhankeng",
    "gn:population":0,
    "gn:timezone":"Asia/Shanghai",
    "iso:country":"CN",
    "name:und_x_variant":[
        "\u8a79\u5751"
    ],
    "name:zho_x_preferred":[
        "\u8a79\u5751"
    ],
    "wof:name":"Zhankeng",
    "wof:placetype":"locality"
},
  "geometry": {"coordinates":[116.75709999999999,25.48515],"type":"Point"}
}