{
  "type": "Feature",
  "properties": {
    "gn:admin1_code":"19.0",
    "gn:asciiname":"Ping'andi",
    "gn:country_code":"CN",
    "gn:dem":207,
    "gn:feature_class":"P",
    "gn:feature_code":"PPL",
    "gn:name":"Ping\u2019andi",
    "gn:population":0,
    "gn:timezone":"Asia/Shanghai",
    "iso:country":"CN",
    "name:und_x_variant":[
        "Ping\u2019andi"
    ],
    "name:zho_x_preferred":[
        "\u5e73\u5b89\u5730"
    ],
    "wof:name":"Ping'andi",
    "wof:placetype":"locality"
},
  "geometry": {"coordinates":[120.49299999999999,41.6468],"type":"Point"}
}