{
  "type": "Feature",
  "properties": {
    "gn:admin1_code":"7.0",
    "gn:asciiname":"Xianqianwan",
    "gn:country_code":"CN",
    "gn:dem":633,
    "gn:feature_class":"P",
    "gn:feature_code":"PPL",
    "gn:name":"Xianqianwan",
    "gn:population":0,
    "gn:timezone":"Asia/Shanghai",
    "iso:country":"CN",
    "name:zho_x_preferred":[
        "\u5148\u524d\u6e7e"
    ],
    "wof:name":"Xianqianwan",
    "wof:placetype":"locality"
},
  "geometry": {"coordinates":[118.78036000000002,25.78646],"type":"Point"}
}