{
  "type": "Feature",
  "properties": {
    "gn:admin1_code":"26.0",
    "gn:asciiname":"Wayaogou",
    "gn:country_code":"CN",
    "gn:dem":1112,
    "gn:feature_class":"P",
    "gn:feature_code":"PPL",
    "gn:name":"Wayaogou",
    "gn:population":0,
    "gn:timezone":"Asia/Shanghai",
    "iso:country":"CN",
    "name:zho_x_preferred":[
        "\u74e6\u7a91\u6c9f"
    ],
    "wof:name":"Wayaogou",
    "wof:placetype":"locality"
},
  "geometry": {"coordinates":[109.38333,33.47632],"type":"Point"}
}