{
  "type": "Feature",
  "properties": {
    "gn:admin1_code":"19",
    "gn:asciiname":"Pianling",
    "gn:country_code":"CN",
    "gn:dem":202,
    "gn:feature_class":"P",
    "gn:feature_code":"PPLA4",
    "gn:name":"Pianling",
    "gn:population":0,
    "gn:timezone":"Asia/Shanghai",
    "iso:country":"CN",
    "name:und_x_variant":[
        "\u504f\u5cad",
        "Pianling Zhen",
        "\u504f\u5cad\u9547"
    ],
    "wof:name":"Pianling",
    "wof:placetype":"locality"
},
  "geometry": {"coordinates":[123.15867,40.47798],"type":"Point"}
}