{
  "type": "Feature",
  "properties": {
    "gn:admin1_code":"3.0",
    "gn:asciiname":"Zhangshang",
    "gn:country_code":"CN",
    "gn:dem":284,
    "gn:feature_class":"P",
    "gn:feature_code":"PPL",
    "gn:name":"Zhangshang",
    "gn:population":0,
    "gn:timezone":"Asia/Shanghai",
    "iso:country":"CN",
    "name:zho_x_preferred":[
        "\u5d82\u4e0a"
    ],
    "wof:name":"Zhangshang",
    "wof:placetype":"locality"
},
  "geometry": {"coordinates":[115.429,26.2823],"type":"Point"}
}