{
  "type": "Feature",
  "properties": {
    "gn:admin1_code":"20",
    "gn:asciiname":"T'ou-p'ai-tzu",
    "gn:country_code":"CN",
    "gn:dem":539,
    "gn:feature_class":"P",
    "gn:feature_code":"PPL",
    "gn:name":"T\u2019ou-p\u2019ai-tzu",
    "gn:population":0,
    "gn:timezone":"Asia/Shanghai",
    "iso:country":"CN",
    "wof:name":"T'ou-p'ai-tzu",
    "wof:placetype":"locality"
},
  "geometry": {"coordinates":[119.33111,42.57278],"type":"Point"}
}