{
  "type": "Feature",
  "properties": {
    "gn:admin1_code":"26",
    "gn:asciiname":"Caojiadian",
    "gn:cc2":"CN",
    "gn:country_code":"CN",
    "gn:dem":1226,
    "gn:feature_class":"P",
    "gn:feature_code":"PPL",
    "gn:name":"Caojiadian",
    "gn:population":0,
    "gn:timezone":"Asia/Shanghai",
    "iso:country":"CN",
    "name:und_x_variant":[
        "Ts\u2019ao-chia-tien",
        "Caojiadian"
    ],
    "wof:name":"Caojiadian",
    "wof:placetype":"locality"
},
  "geometry": {"coordinates":[108.18528000000001,35.165],"type":"Point"}
}