{
  "type": "Feature",
  "properties": {
    "gn:admin1_code":"02",
    "gn:asciiname":"Feitou",
    "gn:country_code":"CN",
    "gn:dem":112,
    "gn:feature_class":"P",
    "gn:feature_code":"PPL",
    "gn:name":"Feitou",
    "gn:population":0,
    "gn:timezone":"Asia/Shanghai",
    "iso:country":"CN",
    "name:und_x_variant":[
        "Fei-t\u2019ou-ts\u2019un",
        "Feitou",
        "Feng-t\u2019ou"
    ],
    "name:zho_x_preferred":[
        "\u7829\u5934"
    ],
    "wof:name":"Feitou",
    "wof:placetype":"locality"
},
  "geometry": {"coordinates":[121.01703000000001,28.38327],"type":"Point"}
}