{
  "type": "Feature",
  "properties": {
    "gn:admin1_code":"4.0",
    "gn:asciiname":"Yangxidu",
    "gn:country_code":"CN",
    "gn:dem":9,
    "gn:feature_class":"P",
    "gn:feature_code":"PPL",
    "gn:name":"Yangxidu",
    "gn:population":0,
    "gn:timezone":"Asia/Shanghai",
    "iso:country":"CN",
    "name:zho_x_preferred":[
        "\u6d0b\u6eaa\u6e21"
    ],
    "wof:name":"Yangxidu",
    "wof:placetype":"locality"
},
  "geometry": {"coordinates":[119.72064,31.676],"type":"Point"}
}