{
  "type": "Feature",
  "properties": {
    "gn:admin1_code":"10",
    "gn:asciiname":"Nanwangzhuang",
    "gn:country_code":"CN",
    "gn:dem":35,
    "gn:feature_class":"P",
    "gn:feature_code":"PPL",
    "gn:name":"Nanwangzhuang",
    "gn:population":0,
    "gn:timezone":"Asia/Shanghai",
    "iso:country":"CN",
    "name:zho_x_preferred":[
        "\u5357\u738b\u5e84"
    ],
    "wof:name":"Nanwangzhuang",
    "wof:placetype":"locality"
},
  "geometry": {"coordinates":[115.765,36.9883],"type":"Point"}
}