{
  "type": "Feature",
  "properties": {
    "gn:admin1_code":"26.0",
    "gn:asciiname":"Caijiamaocun",
    "gn:country_code":"CN",
    "gn:dem":1570,
    "gn:feature_class":"P",
    "gn:feature_code":"PPL",
    "gn:name":"Caijiamaocun",
    "gn:population":0,
    "gn:timezone":"Asia/Shanghai",
    "iso:country":"CN",
    "name:zho_x_preferred":[
        "\u8521\u5bb6\u5cc1\u6751"
    ],
    "wof:name":"Caijiamaocun",
    "wof:placetype":"locality"
},
  "geometry": {"coordinates":[108.5968,37.35771],"type":"Point"}
}