{
  "type": "Feature",
  "properties": {
    "gn:admin1_code":"29.0",
    "gn:asciiname":"Aihua",
    "gn:country_code":"CN",
    "gn:dem":1180,
    "gn:feature_class":"P",
    "gn:feature_code":"PPLA3",
    "gn:name":"Aihua",
    "gn:population":0,
    "gn:timezone":"Asia/Shanghai",
    "iso:country":"CN",
    "name:und_x_variant":[
        "Yunxian",
        "Aihua"
    ],
    "name:zho_x_preferred":[
        "Y\u00fcn-ch\u2019eng-chen"
    ],
    "name:zho_x_variant":[
        "Y\u00fcn-hsien",
        "Y\u00fcnchow",
        "Y\u00fcn"
    ],
    "wof:name":"Aihua",
    "wof:placetype":"locality"
},
  "geometry": {"coordinates":[100.09999999999999,24.41667],"type":"Point"}
}