{
  "type": "Feature",
  "properties": {
    "gn:admin1_code":"14.0",
    "gn:asciiname":"Kadai",
    "gn:country_code":"CN",
    "gn:dem":2923,
    "gn:feature_class":"P",
    "gn:feature_code":"PPL",
    "gn:name":"Kadai",
    "gn:population":0,
    "gn:timezone":"Asia/Urumqi",
    "iso:country":"CN",
    "name:zho_x_preferred":[
        "\u5361\u4ee3"
    ],
    "wof:name":"Kadai",
    "wof:placetype":"locality"
},
  "geometry": {"coordinates":[95.68966,29.89812],"type":"Point"}
}