{
  "type": "Feature",
  "properties": {
    "gn:admin1_code":"30",
    "gn:asciiname":"Niubeikeng",
    "gn:country_code":"CN",
    "gn:dem":456,
    "gn:feature_class":"P",
    "gn:feature_code":"PPL",
    "gn:name":"Niubeikeng",
    "gn:population":0,
    "gn:timezone":"Asia/Shanghai",
    "iso:country":"CN",
    "name:zho_x_preferred":[
        "\u725b\u80cc\u5751"
    ],
    "wof:name":"Niubeikeng",
    "wof:placetype":"locality"
},
  "geometry": {"coordinates":[116.15451000000002,24.80913],"type":"Point"}
}