{
  "type": "Feature",
  "properties": {
    "gn:admin1_code":"18",
    "gn:asciiname":"Zhuangzitou",
    "gn:country_code":"CN",
    "gn:dem":947,
    "gn:feature_class":"P",
    "gn:feature_code":"PPL",
    "gn:name":"Zhuangzitou",
    "gn:population":0,
    "gn:timezone":"Asia/Shanghai",
    "iso:country":"CN",
    "name:zho_x_preferred":[
        "\u5e84\u5b50\u5934"
    ],
    "wof:name":"Zhuangzitou",
    "wof:placetype":"locality"
},
  "geometry": {"coordinates":[106.63,28.3438],"type":"Point"}
}