{
  "type": "Feature",
  "properties": {
    "gn:admin1_code":"11.0",
    "gn:asciiname":"Hangshang",
    "gn:country_code":"CN",
    "gn:dem":758,
    "gn:feature_class":"P",
    "gn:feature_code":"PPL",
    "gn:name":"Hangshang",
    "gn:population":0,
    "gn:timezone":"Asia/Shanghai",
    "iso:country":"CN",
    "name:zho_x_preferred":[
        "\u592f\u5c1a"
    ],
    "wof:name":"Hangshang",
    "wof:placetype":"locality"
},
  "geometry": {"coordinates":[109.41282,28.27496],"type":"Point"}
}