{
  "type": "Feature",
  "properties": {
    "gn:admin1_code":"9",
    "gn:asciiname":"Liugushi",
    "gn:country_code":"CN",
    "gn:dem":53,
    "gn:feature_class":"P",
    "gn:feature_code":"PPL",
    "gn:name":"Liugushi",
    "gn:population":0,
    "gn:timezone":"Asia/Shanghai",
    "iso:country":"CN",
    "name:zho_x_preferred":[
        "\u7559\u56fa\u4ec0"
    ],
    "wof:name":"Liugushi",
    "wof:placetype":"locality"
},
  "geometry": {"coordinates":[115.05061000000001,36.06172],"type":"Point"}
}