{
  "type": "Feature",
  "properties": {
    "gn:admin1_code":"14.0",
    "gn:asciiname":"Genyunduo",
    "gn:country_code":"CN",
    "gn:dem":4356,
    "gn:feature_class":"P",
    "gn:feature_code":"PPL",
    "gn:name":"Genyunduo",
    "gn:population":0,
    "gn:timezone":"Asia/Urumqi",
    "iso:country":"CN",
    "name:zho_x_preferred":[
        "\u6839\u4e91\u591a"
    ],
    "wof:name":"Genyunduo",
    "wof:placetype":"locality"
},
  "geometry": {"coordinates":[97.35883,30.37812000000001],"type":"Point"}
}