{
  "type": "Feature",
  "properties": {
    "gn:admin1_code":"10.0",
    "gn:asciiname":"Qiaonanyu",
    "gn:country_code":"CN",
    "gn:dem":781,
    "gn:feature_class":"P",
    "gn:feature_code":"PPL",
    "gn:name":"Qiaonanyu",
    "gn:population":0,
    "gn:timezone":"Asia/Shanghai",
    "iso:country":"CN",
    "name:zho_x_preferred":[
        "\u6865\u5357\u5cea"
    ],
    "wof:name":"Qiaonanyu",
    "wof:placetype":"locality"
},
  "geometry": {"coordinates":[113.84554,38.10366],"type":"Point"}
}