{
  "type": "Feature",
  "properties": {
    "gn:admin1_code":"14.0",
    "gn:asciiname":"Qunayancai",
    "gn:country_code":"CN",
    "gn:dem":4668,
    "gn:feature_class":"P",
    "gn:feature_code":"PPL",
    "gn:name":"Qunayancai",
    "gn:population":0,
    "gn:timezone":"Asia/Urumqi",
    "iso:country":"CN",
    "name:zho_x_preferred":[
        "\u66f2\u90a3\u708e\u91c7"
    ],
    "wof:name":"Qunayancai",
    "wof:placetype":"locality"
},
  "geometry": {"coordinates":[90.23312,31.98402],"type":"Point"}
}