{
  "type": "Feature",
  "properties": {
    "gn:admin1_code":"19.0",
    "gn:asciiname":"Zhujiabu",
    "gn:country_code":"CN",
    "gn:dem":64,
    "gn:feature_class":"P",
    "gn:feature_code":"PPL",
    "gn:name":"Zhujiabu",
    "gn:population":0,
    "gn:timezone":"Asia/Shanghai",
    "iso:country":"CN",
    "name:und_x_variant":[
        "Zhujiapu",
        "\u891a\u5bb6\u5821",
        "Zhujiabu"
    ],
    "wof:name":"Zhujiabu",
    "wof:placetype":"locality"
},
  "geometry": {"coordinates":[122.90354000000001,40.86227],"type":"Point"}
}