{
  "type": "Feature",
  "properties": {
    "gn:admin1_code":"18.0",
    "gn:asciiname":"Zhijie",
    "gn:country_code":"CN",
    "gn:dem":1952,
    "gn:feature_class":"P",
    "gn:feature_code":"PPL",
    "gn:name":"Zhijie",
    "gn:population":0,
    "gn:timezone":"Asia/Shanghai",
    "iso:country":"CN",
    "wof:name":"Zhijie",
    "wof:placetype":"locality"
},
  "geometry": {"coordinates":[104.78333000000001,26.85833],"type":"Point"}
}