{
  "type": "Feature",
  "properties": {
    "gn:admin1_code":"8.0",
    "gn:asciiname":"Lifangba",
    "gn:country_code":"CN",
    "gn:dem":144,
    "gn:feature_class":"P",
    "gn:feature_code":"PPL",
    "gn:name":"Lifangba",
    "gn:population":0,
    "gn:timezone":"Asia/Shanghai",
    "iso:country":"CN",
    "name:zho_x_preferred":[
        "\u674e\u623f\u628a"
    ],
    "wof:name":"Lifangba",
    "wof:placetype":"locality"
},
  "geometry": {"coordinates":[127.25445999999999,46.21003],"type":"Point"}
}