{
  "type": "Feature",
  "properties": {
    "gn:admin1_code":"0.0",
    "gn:asciiname":"Man-k'uang",
    "gn:country_code":"CN",
    "gn:dem":1471,
    "gn:feature_class":"P",
    "gn:feature_code":"PPL",
    "gn:name":"Man-k\u2019uang",
    "gn:population":0,
    "gn:timezone":"Asia/Shanghai",
    "iso:country":"CN",
    "wof:name":"Man-k'uang",
    "wof:placetype":"locality"
},
  "geometry": {"coordinates":[99.51775000000001,24.13082],"type":"Point"}
}