{
  "type": "Feature",
  "properties": {
    "gn:admin1_code":"4.0",
    "gn:asciiname":"Weicaicun",
    "gn:country_code":"CN",
    "gn:dem":19,
    "gn:feature_class":"P",
    "gn:feature_code":"PPL",
    "gn:name":"Weicaicun",
    "gn:population":0,
    "gn:timezone":"Asia/Shanghai",
    "iso:country":"CN",
    "name:zho_x_preferred":[
        "\u7ef4\u624d\u6751"
    ],
    "wof:name":"Weicaicun",
    "wof:placetype":"locality"
},
  "geometry": {"coordinates":[118.61669999999999,33.03247],"type":"Point"}
}