{
  "type": "Feature",
  "properties": {
    "gn:admin1_code":"14.0",
    "gn:asciiname":"Bamaka",
    "gn:country_code":"CN",
    "gn:dem":4811,
    "gn:feature_class":"P",
    "gn:feature_code":"PPL",
    "gn:name":"Bamaka",
    "gn:population":0,
    "gn:timezone":"Asia/Urumqi",
    "iso:country":"CN",
    "name:zho_x_preferred":[
        "\u53ed\u739b\u5361"
    ],
    "wof:name":"Bamaka",
    "wof:placetype":"locality"
},
  "geometry": {"coordinates":[93.92958,30.80588],"type":"Point"}
}