{
  "type": "Feature",
  "properties": {
    "gn:admin1_code":"13.0",
    "gn:asciiname":"Bagejigedai",
    "gn:country_code":"CN",
    "gn:dem":1294,
    "gn:feature_class":"P",
    "gn:feature_code":"PPL",
    "gn:name":"Bagejigedai",
    "gn:population":0,
    "gn:timezone":"Asia/Shanghai",
    "iso:country":"CN",
    "name:und_x_variant":[
        "Bageji Gedai"
    ],
    "name:zho_x_preferred":[
        "\u5df4\u683c\u5409\u683c\u4ee3"
    ],
    "wof:name":"Bagejigedai",
    "wof:placetype":"locality"
},
  "geometry": {"coordinates":[79.53801,37.49933],"type":"Point"}
}