{
  "type": "Feature",
  "properties": {
    "gn:admin1_code":"26.0",
    "gn:asciiname":"Shuangzhuangcun",
    "gn:country_code":"CN",
    "gn:dem":1092,
    "gn:feature_class":"P",
    "gn:feature_code":"PPL",
    "gn:name":"Shuangzhuangcun",
    "gn:population":0,
    "gn:timezone":"Asia/Shanghai",
    "iso:country":"CN",
    "name:zho_x_preferred":[
        "\u53cc\u5e84\u6751"
    ],
    "wof:name":"Shuangzhuangcun",
    "wof:placetype":"locality"
},
  "geometry": {"coordinates":[109.46691,33.33058],"type":"Point"}
}