{
  "type": "Feature",
  "properties": {
    "gn:admin1_code":"19.0",
    "gn:asciiname":"Shangdian",
    "gn:country_code":"CN",
    "gn:dem":292,
    "gn:feature_class":"P",
    "gn:feature_code":"PPL",
    "gn:name":"Shangdian",
    "gn:population":0,
    "gn:timezone":"Asia/Shanghai",
    "iso:country":"CN",
    "name:und_x_variant":[
        "\u4e0a\u5e97"
    ],
    "name:zho_x_preferred":[
        "\u4e0a\u5e97"
    ],
    "wof:name":"Shangdian",
    "wof:placetype":"locality"
},
  "geometry": {"coordinates":[120.503,41.4135],"type":"Point"}
}