{
  "type": "Feature",
  "properties": {
    "gn:admin1_code":"14.0",
    "gn:asciiname":"Chibda",
    "gn:country_code":"CN",
    "gn:dem":4522,
    "gn:feature_class":"P",
    "gn:feature_code":"PPL",
    "gn:name":"Chibda",
    "gn:population":0,
    "gn:timezone":"Asia/Urumqi",
    "iso:country":"CN",
    "name:bod_x_preferred":[
        "Chibda"
    ],
    "name:zho_x_preferred":[
        "Chibuda"
    ],
    "name:zho_x_variant":[
        "\u5c3a\u5e03\u8fbe"
    ],
    "wof:name":"Chibda",
    "wof:placetype":"locality"
},
  "geometry": {"coordinates":[88.70100000000002,28.901],"type":"Point"}
}