{
  "type": "Feature",
  "properties": {
    "gn:admin1_code":"16.0",
    "gn:asciiname":"Liuridong",
    "gn:country_code":"CN",
    "gn:dem":133,
    "gn:feature_class":"P",
    "gn:feature_code":"PPL",
    "gn:name":"Liuridong",
    "gn:population":0,
    "gn:timezone":"Asia/Shanghai",
    "iso:country":"CN",
    "name:zho_x_preferred":[
        "\u516d\u65e5\u578c"
    ],
    "wof:name":"Liuridong",
    "wof:placetype":"locality"
},
  "geometry": {"coordinates":[110.541,22.9967],"type":"Point"}
}