{
  "type": "Feature",
  "properties": {
    "gn:admin1_code":"32.0",
    "gn:asciiname":"Rendeng",
    "gn:country_code":"CN",
    "gn:dem":3362,
    "gn:feature_class":"P",
    "gn:feature_code":"PPL",
    "gn:name":"Rendeng",
    "gn:population":0,
    "gn:timezone":"Asia/Shanghai",
    "iso:country":"CN",
    "name:zho_x_preferred":[
        "\u4ec1\u706f"
    ],
    "wof:name":"Rendeng",
    "wof:placetype":"locality"
},
  "geometry": {"coordinates":[99.15940000000001,31.0662],"type":"Point"}
}