{
  "type": "Feature",
  "properties": {
    "gn:admin1_code":"15.0",
    "gn:asciiname":"Pengjiaquan",
    "gn:country_code":"CN",
    "gn:dem":1969,
    "gn:feature_class":"P",
    "gn:feature_code":"PPL",
    "gn:name":"Pengjiaquan",
    "gn:population":0,
    "gn:timezone":"Asia/Shanghai",
    "iso:country":"CN",
    "name:zho_x_preferred":[
        "\u5f6d\u5bb6\u5708"
    ],
    "wof:name":"Pengjiaquan",
    "wof:placetype":"locality"
},
  "geometry": {"coordinates":[103.879,36.5804],"type":"Point"}
}