{
  "type": "Feature",
  "properties": {
    "gn:admin1_code":"26.0",
    "gn:asciiname":"Houjiahe",
    "gn:country_code":"CN",
    "gn:dem":1226,
    "gn:feature_class":"P",
    "gn:feature_code":"PPL",
    "gn:name":"Houjiahe",
    "gn:population":0,
    "gn:timezone":"Asia/Shanghai",
    "iso:country":"CN",
    "name:zho_x_preferred":[
        "\u5019\u5bb6\u6cb3"
    ],
    "wof:name":"Houjiahe",
    "wof:placetype":"locality"
},
  "geometry": {"coordinates":[108.94414999999999,36.9567],"type":"Point"}
}