{
  "type": "Feature",
  "properties": {
    "gn:admin1_code":"7",
    "gn:asciiname":"Jiuduqiao",
    "gn:country_code":"CN",
    "gn:dem":577,
    "gn:feature_class":"P",
    "gn:feature_code":"PPL",
    "gn:name":"Jiuduqiao",
    "gn:population":0,
    "gn:timezone":"Asia/Shanghai",
    "iso:country":"CN",
    "name:zho_x_preferred":[
        "\u4e5d\u6e21\u6865"
    ],
    "wof:name":"Jiuduqiao",
    "wof:placetype":"locality"
},
  "geometry": {"coordinates":[118.62721999999999,26.66565],"type":"Point"}
}