{
  "type": "Feature",
  "properties": {
    "gn:admin1_code":"3.0",
    "gn:asciiname":"Waibi",
    "gn:country_code":"CN",
    "gn:dem":547,
    "gn:feature_class":"P",
    "gn:feature_code":"PPL",
    "gn:name":"Waibi",
    "gn:population":0,
    "gn:timezone":"Asia/Shanghai",
    "iso:country":"CN",
    "name:und_x_variant":[
        "\u5916\u58c1"
    ],
    "wof:name":"Waibi",
    "wof:placetype":"locality"
},
  "geometry": {"coordinates":[117.12676999999999,29.89337],"type":"Point"}
}