{
  "type": "Feature",
  "properties": {
    "gn:admin1_code":"29.0",
    "gn:asciiname":"Lahami",
    "gn:country_code":"CN",
    "gn:dem":928,
    "gn:feature_class":"P",
    "gn:feature_code":"PPL",
    "gn:name":"Lahami",
    "gn:population":0,
    "gn:timezone":"Asia/Shanghai",
    "iso:country":"CN",
    "name:zho_x_preferred":[
        "\u814a\u54c8\u8ff7"
    ],
    "wof:name":"Lahami",
    "wof:placetype":"locality"
},
  "geometry": {"coordinates":[103.379,22.9398],"type":"Point"}
}