{
  "type": "Feature",
  "properties": {
    "gn:admin1_code":"7.0",
    "gn:asciiname":"Laifu",
    "gn:country_code":"CN",
    "gn:dem":295,
    "gn:feature_class":"P",
    "gn:feature_code":"PPL",
    "gn:name":"Laifu",
    "gn:population":0,
    "gn:timezone":"Asia/Shanghai",
    "iso:country":"CN",
    "name:zho_x_preferred":[
        "\u6765\u798f"
    ],
    "wof:name":"Laifu",
    "wof:placetype":"locality"
},
  "geometry": {"coordinates":[116.19476,25.03689],"type":"Point"}
}