{
  "type": "Feature",
  "properties": {
    "gn:admin1_code":"1.0",
    "gn:asciiname":"Wucheng",
    "gn:country_code":"CN",
    "gn:dem":11,
    "gn:feature_class":"P",
    "gn:feature_code":"PPLA3",
    "gn:name":"Wucheng",
    "gn:population":0,
    "gn:timezone":"Asia/Shanghai",
    "iso:country":"CN",
    "name:und_x_variant":[
        "Wu-wei-hsien",
        "Wuwei",
        "Wuweichow",
        "Wucheng",
        "Wuwei Xian"
    ],
    "name:zho_x_preferred":[
        "\u65e0\u4e3a\u53bf"
    ],
    "wof:name":"Wucheng",
    "wof:placetype":"locality"
},
  "geometry": {"coordinates":[117.90192999999999,31.2837],"type":"Point"}
}