{
  "type": "Feature",
  "properties": {
    "gn:admin1_code":"26.0",
    "gn:asciiname":"Weijialiang",
    "gn:country_code":"CN",
    "gn:dem":1038,
    "gn:feature_class":"P",
    "gn:feature_code":"PPL",
    "gn:name":"Weijialiang",
    "gn:population":0,
    "gn:timezone":"Asia/Shanghai",
    "iso:country":"CN",
    "name:zho_x_preferred":[
        "\u97e6\u5bb6\u6881"
    ],
    "wof:name":"Weijialiang",
    "wof:placetype":"locality"
},
  "geometry": {"coordinates":[109.77143,38.22763],"type":"Point"}
}