{
  "type": "Feature",
  "properties": {
    "gn:admin1_code":"08",
    "gn:asciiname":"Tuoyaozi",
    "gn:country_code":"CN",
    "gn:dem":187,
    "gn:feature_class":"P",
    "gn:feature_code":"PPLA4",
    "gn:name":"Tuoyaozi",
    "gn:population":0,
    "gn:timezone":"Asia/Shanghai",
    "iso:country":"CN",
    "name:und_x_variant":[
        "T\u2019o-yao-tzu",
        "Tuoyaozi",
        "Tuoyaozi Zhen"
    ],
    "name:zho_x_preferred":[
        "\u9a7c\u8170\u5b50"
    ],
    "name:zho_x_variant":[
        "\u9a7c\u8170\u5b50\u9547"
    ],
    "wof:name":"Tuoyaozi",
    "wof:placetype":"locality"
},
  "geometry": {"coordinates":[130.77772999999999,46.23771],"type":"Point"}
}