{
  "type": "Feature",
  "properties": {
    "gn:country":"CN",
    "gn:fcode":"PPL",
    "gn:population":770,
    "iso:country":"CN",
    "name:und_x_variant":[
        "Hsiao-chiang-k\u2019ou"
    ],
    "qs:name":"Xiaojiangkou",
    "qs:photos_9r":0,
    "qs:photos_sr":0,
    "qs:pop_sr":"2",
    "wof:name":"Xiaojiangkou",
    "wof:placetype":"locality",
    "wof:population":770
},
  "geometry": {"coordinates":[110.44667,27.88028],"type":"Point"}
}