{
  "type": "Feature",
  "properties": {
    "gn:admin1_code":"32.0",
    "gn:asciiname":"Longbu",
    "gn:country_code":"CN",
    "gn:dem":3598,
    "gn:feature_class":"P",
    "gn:feature_code":"PPL",
    "gn:name":"Longbu",
    "gn:population":0,
    "gn:timezone":"Asia/Shanghai",
    "iso:country":"CN",
    "name:zho_x_preferred":[
        "\u9f99\u5e03"
    ],
    "wof:name":"Longbu",
    "wof:placetype":"locality"
},
  "geometry": {"coordinates":[101.401,30.5374],"type":"Point"}
}