{
  "type": "Feature",
  "properties": {
    "gn:admin1_code":"8.0",
    "gn:asciiname":"Changsheng",
    "gn:country_code":"CN",
    "gn:dem":159,
    "gn:feature_class":"P",
    "gn:feature_code":"PPLA4",
    "gn:name":"Changsheng",
    "gn:population":0,
    "gn:timezone":"Asia/Shanghai",
    "iso:country":"CN",
    "name:ceb_x_preferred":[
        "Changsheng"
    ],
    "name:deu_x_preferred":[
        "Changsheng"
    ],
    "name:swe_x_preferred":[
        "Changsheng"
    ],
    "name:und_x_variant":[
        "Changsheng Xiang"
    ],
    "name:zho_x_preferred":[
        "\u660c\u76db"
    ],
    "name:zho_x_variant":[
        "\u660c\u76db\u4e61"
    ],
    "wof:name":"Changsheng",
    "wof:placetype":"locality"
},
  "geometry": {"coordinates":[126.2666,46.56496],"type":"Point"}
}