{
  "type": "Feature",
  "properties": {
    "gn:admin1_code":"7",
    "gn:asciiname":"Daban",
    "gn:country_code":"CN",
    "gn:dem":494,
    "gn:feature_class":"P",
    "gn:feature_code":"PPL",
    "gn:name":"Daban",
    "gn:population":0,
    "gn:timezone":"Asia/Shanghai",
    "iso:country":"CN",
    "wof:name":"Daban",
    "wof:placetype":"locality"
},
  "geometry": {"coordinates":[117.48193999999999,25.42556],"type":"Point"}
}