{
  "type": "Feature",
  "properties": {
    "gn:admin1_code":"24.0",
    "gn:asciiname":"Caoduoshan",
    "gn:country_code":"CN",
    "gn:dem":1582,
    "gn:feature_class":"P",
    "gn:feature_code":"PPL",
    "gn:name":"Caoduoshan",
    "gn:population":0,
    "gn:timezone":"Asia/Shanghai",
    "iso:country":"CN",
    "name:zho_x_preferred":[
        "\u8349\u579b\u5c71"
    ],
    "wof:name":"Caoduoshan",
    "wof:placetype":"locality"
},
  "geometry": {"coordinates":[111.59819,39.60658],"type":"Point"}
}