{
  "type": "Feature",
  "properties": {
    "gn:admin1_code":"3.0",
    "gn:asciiname":"Fujia Lingli",
    "gn:country_code":"CN",
    "gn:dem":96,
    "gn:feature_class":"P",
    "gn:feature_code":"PPL",
    "gn:name":"Fujia Lingli",
    "gn:population":0,
    "gn:timezone":"Asia/Shanghai",
    "iso:country":"CN",
    "name:und_x_variant":[
        "\u5085\u5bb6\u5cad\u9ece"
    ],
    "wof:name":"Fujia Lingli",
    "wof:placetype":"locality"
},
  "geometry": {"coordinates":[114.52146,27.40191],"type":"Point"}
}