{
  "type": "Feature",
  "properties": {
    "gn:admin1_code":"3.0",
    "gn:asciiname":"Tumu",
    "gn:country_code":"CN",
    "gn:dem":16,
    "gn:feature_class":"P",
    "gn:feature_code":"PPL",
    "gn:name":"Tumu",
    "gn:population":0,
    "gn:timezone":"Asia/Shanghai",
    "iso:country":"CN",
    "name:ceb_x_preferred":[
        "Tumu"
    ],
    "name:deu_x_preferred":[
        "Tumu"
    ],
    "name:ind_x_preferred":[
        "Tumu"
    ],
    "name:nld_x_preferred":[
        "Tumu"
    ],
    "name:swe_x_preferred":[
        "Tumu"
    ],
    "name:und_x_variant":[
        "\u571f\u76ee"
    ],
    "wof:name":"Tumu",
    "wof:placetype":"locality"
},
  "geometry": {"coordinates":[116.15843,29.48859],"type":"Point"}
}