{
  "type": "Feature",
  "properties": {
    "gn:admin1_code":"33.0",
    "gn:asciiname":"Tianchikou",
    "gn:country_code":"CN",
    "gn:dem":438,
    "gn:feature_class":"P",
    "gn:feature_code":"PPL",
    "gn:name":"Tianchikou",
    "gn:population":0,
    "gn:timezone":"Asia/Shanghai",
    "iso:country":"CN",
    "name:zho_x_preferred":[
        "\u5929\u6c60\u53e3"
    ],
    "wof:name":"Tianchikou",
    "wof:placetype":"locality"
},
  "geometry": {"coordinates":[107.5802,30.2747],"type":"Point"}
}