{
  "type": "Feature",
  "properties": {
    "gn:admin1_code":"11.0",
    "gn:asciiname":"Damuchong",
    "gn:country_code":"CN",
    "gn:dem":150,
    "gn:feature_class":"P",
    "gn:feature_code":"PPL",
    "gn:name":"Damuchong",
    "gn:population":0,
    "gn:timezone":"Asia/Shanghai",
    "iso:country":"CN",
    "name:zho_x_preferred":[
        "\u5927\u6728\u51b2"
    ],
    "wof:name":"Damuchong",
    "wof:placetype":"locality"
},
  "geometry": {"coordinates":[113.05766,26.36789000000001],"type":"Point"}
}