{
  "type": "Feature",
  "properties": {
    "gn:admin1_code":"19.0",
    "gn:asciiname":"Houfang Ganbucun",
    "gn:country_code":"CN",
    "gn:dem":20,
    "gn:feature_class":"P",
    "gn:feature_code":"PPL",
    "gn:name":"Houfang Ganbucun",
    "gn:population":0,
    "gn:timezone":"Asia/Shanghai",
    "iso:country":"CN",
    "name:und_x_variant":[
        "Houfangganbucun",
        "Houfang Ganbucun"
    ],
    "name:zho_x_preferred":[
        "\u540e\u65b9\u5e72\u5821\u6751"
    ],
    "wof:name":"Houfang Ganbucun",
    "wof:placetype":"locality"
},
  "geometry": {"coordinates":[123.15125999999999,41.37902],"type":"Point"}
}