{
  "type": "Feature",
  "properties": {
    "gn:admin1_code":"3.0",
    "gn:asciiname":"Hejiaqiao",
    "gn:country_code":"CN",
    "gn:dem":21,
    "gn:feature_class":"P",
    "gn:feature_code":"PPL",
    "gn:name":"Hejiaqiao",
    "gn:population":0,
    "gn:timezone":"Asia/Shanghai",
    "iso:country":"CN",
    "name:und_x_variant":[
        "\u4f55\u5bb6\u6865"
    ],
    "wof:name":"Hejiaqiao",
    "wof:placetype":"locality"
},
  "geometry": {"coordinates":[116.62878000000001,28.65648],"type":"Point"}
}