{
  "type": "Feature",
  "properties": {
    "gn:country":"CN",
    "gn:fcode":"PPL",
    "gn:pop":2413,
    "iso:country":"CN",
    "name:zho_x_preferred":[
        "\u970d\u5e84\u5b50"
    ],
    "qs:name":"Huozhuangzi",
    "qs:photos_9r":0,
    "qs:photos_sr":0,
    "qs:pop_sr":"4",
    "wof:name":"Huozhuangzi",
    "wof:placetype":"locality",
    "wof:population":2413
},
  "geometry": {"coordinates":[117.31358,39.29148],"type":"Point"}
}