{
  "type": "Feature",
  "properties": {
    "gn:admin1_code":"25",
    "gn:asciiname":"Shaojing",
    "gn:country_code":"CN",
    "gn:dem":42,
    "gn:feature_class":"P",
    "gn:feature_code":"PPL",
    "gn:name":"Shaojing",
    "gn:population":0,
    "gn:timezone":"Asia/Shanghai",
    "iso:country":"CN",
    "name:zho_x_preferred":[
        "\u90b5\u51c0"
    ],
    "wof:name":"Shaojing",
    "wof:placetype":"locality"
},
  "geometry": {"coordinates":[115.59502000000001,36.39672],"type":"Point"}
}