{
  "type": "Feature",
  "properties": {
    "gn:admin1_code":"9.0",
    "gn:asciiname":"Wenwa",
    "gn:country_code":"CN",
    "gn:dem":127,
    "gn:feature_class":"P",
    "gn:feature_code":"PPL",
    "gn:name":"Wenwa",
    "gn:population":0,
    "gn:timezone":"Asia/Shanghai",
    "iso:country":"CN",
    "name:zho_x_preferred":[
        "\u6587\u6d3c"
    ],
    "wof:name":"Wenwa",
    "wof:placetype":"locality"
},
  "geometry": {"coordinates":[113.11324999999999,32.8284],"type":"Point"}
}