{
  "type": "Feature",
  "properties": {
    "gn:admin1_code":"31.0",
    "gn:asciiname":"Qierui",
    "gn:country_code":"CN",
    "gn:dem":19,
    "gn:feature_class":"P",
    "gn:feature_code":"PPL",
    "gn:name":"Qierui",
    "gn:population":0,
    "gn:timezone":"Asia/Shanghai",
    "iso:country":"CN",
    "name:und_x_variant":[
        "\u8304\u82ae"
    ],
    "wof:name":"Qierui",
    "wof:placetype":"locality"
},
  "geometry": {"coordinates":[110.56502,19.91863],"type":"Point"}
}