{
  "type": "Feature",
  "properties": {
    "gn:admin1_code":"31.0",
    "gn:asciiname":"Mengya",
    "gn:country_code":"CN",
    "gn:dem":303,
    "gn:feature_class":"P",
    "gn:feature_code":"PPL",
    "gn:name":"Mengya",
    "gn:population":0,
    "gn:timezone":"Asia/Shanghai",
    "iso:country":"CN",
    "name:zho_x_preferred":[
        "\u840c\u82bd"
    ],
    "wof:name":"Mengya",
    "wof:placetype":"locality"
},
  "geometry": {"coordinates":[109.39453,19.03087],"type":"Point"}
}