{
  "type": "Feature",
  "properties": {
    "gn:admin1_code":"8.0",
    "gn:asciiname":"Yuliangzi",
    "gn:country_code":"CN",
    "gn:dem":160,
    "gn:feature_class":"P",
    "gn:feature_code":"PPL",
    "gn:name":"Yuliangzi",
    "gn:population":0,
    "gn:timezone":"Asia/Shanghai",
    "iso:country":"CN",
    "name:zho_x_preferred":[
        "\u6e14\u4eae\u5b50"
    ],
    "wof:name":"Yuliangzi",
    "wof:placetype":"locality"
},
  "geometry": {"coordinates":[124.66591,47.74314],"type":"Point"}
}