{
  "type": "Feature",
  "properties": {
    "gn:admin1_code":"7",
    "gn:asciiname":"Dafang Nongchang",
    "gn:country_code":"CN",
    "gn:dem":14,
    "gn:feature_class":"P",
    "gn:feature_code":"PPLF",
    "gn:name":"Dafang Nongchang",
    "gn:population":0,
    "gn:timezone":"Asia/Shanghai",
    "iso:country":"CN",
    "name:zho_x_preferred":[
        "\u5927\u623f\u519c\u573a"
    ],
    "wof:name":"Dafang Nongchang",
    "wof:placetype":"locality"
},
  "geometry": {"coordinates":[117.54389,24.52472],"type":"Point"}
}