{
  "type": "Feature",
  "properties": {
    "gn:admin1_code":"03",
    "gn:asciiname":"Baimazhai",
    "gn:country_code":"CN",
    "gn:dem":28,
    "gn:feature_class":"P",
    "gn:feature_code":"PPL",
    "gn:name":"Baimazhai",
    "gn:population":0,
    "gn:timezone":"Asia/Shanghai",
    "iso:country":"CN",
    "name:und_x_variant":[
        "Pai-ma-chai",
        "Pai-ma",
        "Baimazhai",
        "\u767d\u9a6c\u5be8",
        "Baimaji"
    ],
    "wof:name":"Baimazhai",
    "wof:placetype":"locality"
},
  "geometry": {"coordinates":[115.89051000000001,28.10542],"type":"Point"}
}