{
  "type": "Feature",
  "properties": {
    "gn:admin1_code":"32.0",
    "gn:asciiname":"Longwangtang",
    "gn:country_code":"CN",
    "gn:dem":312,
    "gn:feature_class":"P",
    "gn:feature_code":"PPL",
    "gn:name":"Longwangtang",
    "gn:population":0,
    "gn:timezone":"Asia/Shanghai",
    "iso:country":"CN",
    "name:zho_x_preferred":[
        "\u9f99\u738b\u5858"
    ],
    "wof:name":"Longwangtang",
    "wof:placetype":"locality"
},
  "geometry": {"coordinates":[105.307,30.4155],"type":"Point"}
}