{
  "type": "Feature",
  "properties": {
    "gn:admin1_code":"25.0",
    "gn:asciiname":"Liuzhuangcun",
    "gn:country_code":"CN",
    "gn:dem":46,
    "gn:feature_class":"P",
    "gn:feature_code":"PPL",
    "gn:name":"Liuzhuangcun",
    "gn:population":0,
    "gn:timezone":"Asia/Shanghai",
    "iso:country":"CN",
    "name:zho_x_preferred":[
        "\u5218\u5e84\u6751"
    ],
    "wof:name":"Liuzhuangcun",
    "wof:placetype":"locality"
},
  "geometry": {"coordinates":[115.52558000000001,36.08871],"type":"Point"}
}