{
  "type": "Feature",
  "properties": {
    "gn:admin1_code":"15.0",
    "gn:asciiname":"Touba",
    "gn:country_code":"CN",
    "gn:dem":1342,
    "gn:feature_class":"P",
    "gn:feature_code":"PPL",
    "gn:name":"Touba",
    "gn:population":0,
    "gn:timezone":"Asia/Shanghai",
    "iso:country":"CN",
    "name:afr_x_preferred":[
        "Touba"
    ],
    "name:bel_x_preferred":[
        "\u0422\u0443\u0431\u0430"
    ],
    "name:cat_x_preferred":[
        "Touba"
    ],
    "name:ceb_x_preferred":[
        "Touba"
    ],
    "name:deu_x_preferred":[
        "Touba"
    ],
    "name:epo_x_preferred":[
        "Tuba"
    ],
    "name:eus_x_preferred":[
        "Touba"
    ],
    "name:fas_x_preferred":[
        "\u0637\u0648\u0628\u06cc"
    ],
    "name:fra_x_preferred":[
        "Touba"
    ],
    "name:ind_x_preferred":[
        "Touba"
    ],
    "name:ita_x_preferred":[
        "Touba"
    ],
    "name:jpn_x_preferred":[
        "\u30c8\u30a5\u30fc\u30d0"
    ],
    "name:kor_x_preferred":[
        "\ud22c\ubc14"
    ],
    "name:lit_x_preferred":[
        "Tuba"
    ],
    "name:msa_x_preferred":[
        "Touba"
    ],
    "name:nld_x_preferred":[
        "Touba"
    ],
    "name:pol_x_preferred":[
        "Touba"
    ],
    "name:ron_x_preferred":[
        "Touba"
    ],
    "name:rus_x_preferred":[
        "\u0422\u0443\u0431\u0430"
    ],
    "name:sna_x_preferred":[
        "Touba"
    ],
    "name:spa_x_preferred":[
        "Touba"
    ],
    "name:swe_x_preferred":[
        "Touba"
    ],
    "name:tur_x_preferred":[
        "Touba"
    ],
    "name:urd_x_preferred":[
        "\u062a\u0648\u0628\u0627"
    ],
    "name:vep_x_preferred":[
        "Tub"
    ],
    "name:wol_x_preferred":[
        "Tuubaa"
    ],
    "name:zho_x_preferred":[
        "\u5934\u575d"
    ],
    "name:zho_x_variant":[
        "\u5716\u5df4"
    ],
    "wof:name":"Touba",
    "wof:placetype":"locality"
},
  "geometry": {"coordinates":[103.25,38.8225],"type":"Point"}
}