{
  "type": "Feature",
  "properties": {
    "gn:admin1_code":"7.0",
    "gn:asciiname":"Changhua",
    "gn:country_code":"CN",
    "gn:dem":222,
    "gn:feature_class":"P",
    "gn:feature_code":"PPL",
    "gn:name":"Changhua",
    "gn:population":0,
    "gn:timezone":"Asia/Shanghai",
    "iso:country":"CN",
    "name:ces_x_preferred":[
        "\u010cang-chua"
    ],
    "name:deu_x_preferred":[
        "Changhua"
    ],
    "name:fas_x_preferred":[
        "\u062c\u0627\u0646\u06af\u0648\u0622"
    ],
    "name:fin_x_preferred":[
        "Changhua"
    ],
    "name:fra_x_preferred":[
        "Changhua"
    ],
    "name:hak_x_preferred":[
        "Ch\u00f4ng-fa-s\u1e73"
    ],
    "name:ita_x_preferred":[
        "Changhua"
    ],
    "name:jpn_x_preferred":[
        "\u5f70\u5316\u5e02"
    ],
    "name:kor_x_preferred":[
        "\uc7a5\ud654\uc2dc"
    ],
    "name:lit_x_preferred":[
        "D\u017eanghua"
    ],
    "name:nld_x_preferred":[
        "Changhua"
    ],
    "name:pol_x_preferred":[
        "Zhanghua"
    ],
    "name:por_x_preferred":[
        "Changhua"
    ],
    "name:rus_x_preferred":[
        "\u0427\u0436\u0430\u043d\u0445\u0443\u0430"
    ],
    "name:spa_x_preferred":[
        "Changhua"
    ],
    "name:tha_x_preferred":[
        "\u0e08\u0e31\u0e07\u0e2e\u0e27\u0e48\u0e32"
    ],
    "name:tur_x_preferred":[
        "Changhua"
    ],
    "name:ukr_x_preferred":[
        "\u0427\u0436\u0430\u043d\u0445\u0443\u0430"
    ],
    "name:und_x_variant":[
        "\u957f\u534e"
    ],
    "name:urd_x_preferred":[
        "\u0686\u0627\u0646\u06af\u06c1\u0648\u0627 \u0634\u06c1\u0631"
    ],
    "name:vie_x_preferred":[
        "Ch\u01b0\u01a1ng H\u00f3a"
    ],
    "name:war_x_preferred":[
        "Changhua"
    ],
    "name:zho_x_preferred":[
        "\u5f70\u5316\u5e02"
    ],
    "wof:name":"Changhua",
    "wof:placetype":"locality"
},
  "geometry": {"coordinates":[118.37796000000002,26.1779],"type":"Point"}
}