{
  "type": "Feature",
  "properties": {
    "gn:admin1_code":"12.0",
    "gn:asciiname":"Sanyanba",
    "gn:country_code":"CN",
    "gn:dem":636,
    "gn:feature_class":"P",
    "gn:feature_code":"PPL",
    "gn:name":"Sanyanba",
    "gn:population":0,
    "gn:timezone":"Asia/Shanghai",
    "iso:country":"CN",
    "name:zho_x_preferred":[
        "\u4e09\u5830\u575d"
    ],
    "wof:name":"Sanyanba",
    "wof:placetype":"locality"
},
  "geometry": {"coordinates":[109.81923999999999,30.52708],"type":"Point"}
}