{
  "type": "Feature",
  "properties": {
    "gn:admin1_code":"16.0",
    "gn:asciiname":"Luobudong",
    "gn:country_code":"CN",
    "gn:dem":268,
    "gn:feature_class":"P",
    "gn:feature_code":"PPL",
    "gn:name":"Luobudong",
    "gn:population":0,
    "gn:timezone":"Asia/Shanghai",
    "iso:country":"CN",
    "name:zho_x_preferred":[
        "\u841d\u535c\u5cd2"
    ],
    "wof:name":"Luobudong",
    "wof:placetype":"locality"
},
  "geometry": {"coordinates":[108.592,24.3726],"type":"Point"}
}