{
  "type": "Feature",
  "properties": {
    "gn:admin1_code":"12",
    "gn:asciiname":"Sandian",
    "gn:country_code":"CN",
    "gn:dem":31,
    "gn:feature_class":"P",
    "gn:feature_code":"PPLA4",
    "gn:name":"Sandian",
    "gn:population":0,
    "gn:timezone":"Asia/Shanghai",
    "iso:country":"CN",
    "name:und_x_variant":[
        "San-tien-shih",
        "San-tien-chieh",
        "San-tien",
        "Sandian",
        "\u4e09\u5e97",
        "Sandian Jiedao",
        "\u4e09\u5e97\u8857\u9053"
    ],
    "wof:name":"Sandian",
    "wof:placetype":"locality"
},
  "geometry": {"coordinates":[114.7919,30.93093],"type":"Point"}
}