{
  "type": "Feature",
  "properties": {
    "gn:admin1_code":"12",
    "gn:asciiname":"Sandian",
    "gn:country_code":"CN",
    "gn:dem":31,
    "gn:feature_class":"P",
    "gn:feature_code":"PPLA4",
    "gn:name":"Sandian",
    "gn:population":0,
    "gn:timezone":"Asia/Shanghai",
    "iso:country":"CN",
    "name:ceb_x_preferred":[
        "Sand\u012b\u0101n"
    ],
    "name:fas_x_preferred":[
        "\u0633\u0646\u062f\u06cc\u0627\u0646"
    ],
    "name:msa_x_preferred":[
        "Sandian"
    ],
    "name:swe_x_preferred":[
        "Sand\u012b\u0101n"
    ],
    "name:ukr_x_preferred":[
        "\u0421\u0430\u043d\u0434\u0456\u0430\u043d"
    ],
    "name:und_x_variant":[
        "San-tien-shih",
        "San-tien-chieh",
        "San-tien",
        "\u4e09\u5e97",
        "Sandian Jiedao",
        "\u4e09\u5e97\u8857\u9053"
    ],
    "wof:name":"Sandian",
    "wof:placetype":"locality"
},
  "geometry": {"coordinates":[114.7919,30.93093],"type":"Point"}
}