{
  "type": "Feature",
  "properties": {
    "gn:admin1_code":"6.0",
    "gn:asciiname":"Kanariwa",
    "gn:country_code":"CN",
    "gn:dem":3760,
    "gn:feature_class":"P",
    "gn:feature_code":"PPL",
    "gn:name":"Kanariwa",
    "gn:population":0,
    "gn:timezone":"Asia/Urumqi",
    "iso:country":"CN",
    "wof:name":"Kanariwa",
    "wof:placetype":"locality"
},
  "geometry": {"coordinates":[96.81851,33.3655],"type":"Point"}
}