{
  "type": "Feature",
  "properties": {
    "gn:admin1_code":"9.0",
    "gn:asciiname":"Badian",
    "gn:country_code":"CN",
    "gn:dem":41,
    "gn:feature_class":"P",
    "gn:feature_code":"PPL",
    "gn:name":"Badian",
    "gn:population":0,
    "gn:timezone":"Asia/Shanghai",
    "iso:country":"CN",
    "name:ceb_x_preferred":[
        "Badian"
    ],
    "name:deu_x_preferred":[
        "Badian"
    ],
    "name:zho_x_preferred":[
        "\u516b\u5e97"
    ],
    "wof:name":"Badian",
    "wof:placetype":"locality"
},
  "geometry": {"coordinates":[115.89437,32.25717],"type":"Point"}
}