{
  "type": "Feature",
  "properties": {
    "gn:admin1_code":"32.0",
    "gn:asciiname":"Buridengcuo",
    "gn:country_code":"CN",
    "gn:dem":3657,
    "gn:feature_class":"P",
    "gn:feature_code":"PPL",
    "gn:name":"Buridengcuo",
    "gn:population":0,
    "gn:timezone":"Asia/Shanghai",
    "iso:country":"CN",
    "name:zho_x_preferred":[
        "\u5e03\u65e5\u9093\u63aa"
    ],
    "wof:name":"Buridengcuo",
    "wof:placetype":"locality"
},
  "geometry": {"coordinates":[100.31100000000001,31.9431],"type":"Point"}
}