{
  "type": "Feature",
  "properties": {
    "gn:admin1_code":"8.0",
    "gn:asciiname":"Wanliucun",
    "gn:country_code":"CN",
    "gn:dem":156,
    "gn:feature_class":"P",
    "gn:feature_code":"PPL",
    "gn:name":"Wanliucun",
    "gn:population":0,
    "gn:timezone":"Asia/Shanghai",
    "iso:country":"CN",
    "name:zho_x_preferred":[
        "\u4e07\u67f3\u6751"
    ],
    "wof:name":"Wanliucun",
    "wof:placetype":"locality"
},
  "geometry": {"coordinates":[128.57588000000001,46.25431],"type":"Point"}
}