{
  "type": "Feature",
  "properties": {
    "gn:admin1_code":"7.0",
    "gn:asciiname":"Ruigou",
    "gn:country_code":"CN",
    "gn:dem":58,
    "gn:feature_class":"P",
    "gn:feature_code":"PPL",
    "gn:name":"Ruigou",
    "gn:population":0,
    "gn:timezone":"Asia/Shanghai",
    "iso:country":"CN",
    "name:zho_x_preferred":[
        "\u745e\u6c9f"
    ],
    "wof:name":"Ruigou",
    "wof:placetype":"locality"
},
  "geometry": {"coordinates":[118.77070999999999,25.34362],"type":"Point"}
}