{
  "type": "Feature",
  "properties": {
    "gn:admin1_code":"21.0",
    "gn:asciiname":"Lijia Zhaizi",
    "gn:country_code":"CN",
    "gn:dem":1132,
    "gn:feature_class":"P",
    "gn:feature_code":"PPL",
    "gn:name":"Lijia Zhaizi",
    "gn:population":0,
    "gn:timezone":"Asia/Shanghai",
    "iso:country":"CN",
    "name:zho_x_preferred":[
        "\u674e\u5bb6\u5be8\u5b50"
    ],
    "wof:name":"Lijia Zhaizi",
    "wof:placetype":"locality"
},
  "geometry": {"coordinates":[105.994,38.0772],"type":"Point"}
}