{
  "type": "Feature",
  "properties": {
    "gn:admin1_code":"15.0",
    "gn:asciiname":"Lijiabanzhuang",
    "gn:country_code":"CN",
    "gn:dem":1385,
    "gn:feature_class":"P",
    "gn:feature_code":"PPL",
    "gn:name":"Lijiabanzhuang",
    "gn:population":0,
    "gn:timezone":"Asia/Shanghai",
    "iso:country":"CN",
    "name:und_x_variant":[
        "\u674e\u5bb6\u534a\u5e84"
    ],
    "wof:name":"Lijiabanzhuang",
    "wof:placetype":"locality"
},
  "geometry": {"coordinates":[107.06506,36.79307],"type":"Point"}
}