{
  "type": "Feature",
  "properties": {
    "gn:admin1_code":"3",
    "gn:asciiname":"Xiaoluodou",
    "gn:country_code":"CN",
    "gn:dem":191,
    "gn:feature_class":"P",
    "gn:feature_code":"PPL",
    "gn:name":"Xiaoluodou",
    "gn:population":0,
    "gn:timezone":"Asia/Shanghai",
    "iso:country":"CN",
    "name:zho_x_preferred":[
        "\u5c0f\u7f57\u8538"
    ],
    "wof:name":"Xiaoluodou",
    "wof:placetype":"locality"
},
  "geometry": {"coordinates":[114.83799999999999,25.2405],"type":"Point"}
}