{
  "type": "Feature",
  "properties": {
    "gn:admin1_code":"4.0",
    "gn:asciiname":"Chongtouzhuang",
    "gn:country_code":"CN",
    "gn:dem":8,
    "gn:feature_class":"P",
    "gn:feature_code":"PPL",
    "gn:name":"Chongtouzhuang",
    "gn:population":0,
    "gn:timezone":"Asia/Shanghai",
    "iso:country":"CN",
    "name:und_x_variant":[
        "\u5d07\u5934\u5e84"
    ],
    "wof:name":"Chongtouzhuang",
    "wof:placetype":"locality"
},
  "geometry": {"coordinates":[120.00548999999999,32.30217],"type":"Point"}
}