{
  "type": "Feature",
  "properties": {
    "gn:admin1_code":"11.0",
    "gn:asciiname":"Zhangjia Yuanzi",
    "gn:country_code":"CN",
    "gn:dem":335,
    "gn:feature_class":"P",
    "gn:feature_code":"PPL",
    "gn:name":"Zhangjia Yuanzi",
    "gn:population":0,
    "gn:timezone":"Asia/Shanghai",
    "iso:country":"CN",
    "name:zho_x_preferred":[
        "\u5f20\u5bb6\u9662\u5b50"
    ],
    "wof:name":"Zhangjia Yuanzi",
    "wof:placetype":"locality"
},
  "geometry": {"coordinates":[109.47874,27.45268],"type":"Point"}
}