{
  "type": "Feature",
  "properties": {
    "gn:admin1_code":"16.0",
    "gn:asciiname":"Longqie",
    "gn:country_code":"CN",
    "gn:dem":654,
    "gn:feature_class":"P",
    "gn:feature_code":"PPL",
    "gn:name":"Longqie",
    "gn:population":0,
    "gn:timezone":"Asia/Shanghai",
    "iso:country":"CN",
    "name:zho_x_preferred":[
        "\u9f99\u5207"
    ],
    "wof:name":"Longqie",
    "wof:placetype":"locality"
},
  "geometry": {"coordinates":[107.172,24.7844],"type":"Point"}
}