{
  "type": "Feature",
  "properties": {
    "gn:admin1_code":"20.0",
    "gn:asciiname":"Housha Wanzi",
    "gn:country_code":"CN",
    "gn:dem":1441,
    "gn:feature_class":"P",
    "gn:feature_code":"PPL",
    "gn:name":"Housha Wanzi",
    "gn:population":0,
    "gn:timezone":"Asia/Shanghai",
    "iso:country":"CN",
    "name:und_x_variant":[
        "\u540e\u6c99\u6e7e\u5b50"
    ],
    "wof:name":"Housha Wanzi",
    "wof:placetype":"locality"
},
  "geometry": {"coordinates":[110.21869,40.87773],"type":"Point"}
}