{
  "type": "Feature",
  "properties": {
    "gn:admin1_code":"33",
    "gn:asciiname":"Linjiang",
    "gn:country_code":"CN",
    "gn:dem":270,
    "gn:feature_class":"P",
    "gn:feature_code":"PPLA4",
    "gn:name":"Linjiang",
    "gn:population":0,
    "gn:timezone":"Asia/Shanghai",
    "iso:country":"CN",
    "name:ceb_x_preferred":[
        "Linjiang Shi"
    ],
    "name:deu_x_preferred":[
        "Linjiang"
    ],
    "name:fra_x_preferred":[
        "Linjiang"
    ],
    "name:ita_x_preferred":[
        "Linjiang"
    ],
    "name:jpn_x_preferred":[
        "\u81e8\u6c5f\u5e02"
    ],
    "name:kik_x_preferred":[
        "Linjiang"
    ],
    "name:kor_x_preferred":[
        "\ub9b0\uc7a5\uc2dc"
    ],
    "name:mlg_x_preferred":[
        "Linjiang"
    ],
    "name:nld_x_preferred":[
        "Linjiang"
    ],
    "name:nor_x_preferred":[
        "Linjiang"
    ],
    "name:pol_x_preferred":[
        "Linjiang"
    ],
    "name:rus_x_preferred":[
        "\u041b\u0438\u043d\u044c\u0446\u0437\u044f\u043d"
    ],
    "name:swe_x_preferred":[
        "Linjiang"
    ],
    "name:und_x_variant":[
        "Lin-chiang-ch\u2019ang",
        "Linjiangchang",
        "Linjiang Zhen"
    ],
    "name:urd_x_preferred":[
        "\u0644\u0646\u062c\u06cc\u0627\u0646\u06af"
    ],
    "name:vie_x_preferred":[
        "L\u00e2m Giang"
    ],
    "name:zho_x_preferred":[
        "\u4e34\u6c5f"
    ],
    "name:zho_x_variant":[
        "\u4e34\u6c5f\u9547",
        "\u4e34\u6c5f\u5e02"
    ],
    "wof:name":"Linjiang",
    "wof:placetype":"locality"
},
  "geometry": {"coordinates":[105.95663,29.24522],"type":"Point"}
}