{
  "type": "Feature",
  "properties": {
    "gn:admin1_code":"4.0",
    "gn:asciiname":"Xiaonian",
    "gn:country_code":"CN",
    "gn:dem":5,
    "gn:feature_class":"P",
    "gn:feature_code":"PPL",
    "gn:name":"Xiaonian",
    "gn:population":0,
    "gn:timezone":"Asia/Shanghai",
    "iso:country":"CN",
    "name:zho_x_preferred":[
        "Xiaonian"
    ],
    "name:zho_x_variant":[
        "\u5c0f\u57dd"
    ],
    "wof:name":"Xiaonian",
    "wof:placetype":"locality"
},
  "geometry": {"coordinates":[119.45746,33.87],"type":"Point"}
}