{
  "type": "Feature",
  "properties": {
    "gn:admin1_code":"5.0",
    "gn:asciiname":"Yaoweizicun",
    "gn:country_code":"CN",
    "gn:dem":134,
    "gn:feature_class":"P",
    "gn:feature_code":"PPL",
    "gn:name":"Yaoweizicun",
    "gn:population":0,
    "gn:timezone":"Asia/Shanghai",
    "iso:country":"CN",
    "name:zho_x_preferred":[
        "\u8170\u56f4\u5b50\u6751"
    ],
    "wof:name":"Yaoweizicun",
    "wof:placetype":"locality"
},
  "geometry": {"coordinates":[123.29922000000001,45.86963],"type":"Point"}
}