{
  "type": "Feature",
  "properties": {
    "gn:admin1_code":"25",
    "gn:asciiname":"Qiganshicun",
    "gn:country_code":"CN",
    "gn:dem":18,
    "gn:feature_class":"P",
    "gn:feature_code":"PPL",
    "gn:name":"Qiganshicun",
    "gn:population":0,
    "gn:timezone":"Asia/Shanghai",
    "iso:country":"CN",
    "name:und_x_variant":[
        "Qiganshi",
        "Qiganshicun"
    ],
    "name:zho_x_preferred":[
        "\u65d7\u6746\u77f3"
    ],
    "name:zho_x_variant":[
        "\u65d7\u6746\u77f3\u6751"
    ],
    "wof:name":"Qiganshicun",
    "wof:placetype":"locality"
},
  "geometry": {"coordinates":[121.48882999999999,36.80155],"type":"Point"}
}