{
  "type": "Feature",
  "properties": {
    "gn:admin1_code":"30.0",
    "gn:asciiname":"Xiajing",
    "gn:country_code":"CN",
    "gn:dem":167,
    "gn:feature_class":"P",
    "gn:feature_code":"PPL",
    "gn:name":"Xiajing",
    "gn:population":0,
    "gn:timezone":"Asia/Shanghai",
    "iso:country":"CN",
    "name:und_x_variant":[
        "\u4e0b\u5f84"
    ],
    "name:zho_x_preferred":[
        "\u4e0b\u5f84"
    ],
    "wof:name":"Xiajing",
    "wof:placetype":"locality"
},
  "geometry": {"coordinates":[114.75391999999999,23.61322],"type":"Point"}
}