{
  "type": "Feature",
  "properties": {
    "gn:admin1_code":"32.0",
    "gn:asciiname":"Fenquan",
    "gn:country_code":"CN",
    "gn:dem":453,
    "gn:feature_class":"P",
    "gn:feature_code":"PPL",
    "gn:name":"Fenquan",
    "gn:population":0,
    "gn:timezone":"Asia/Shanghai",
    "iso:country":"CN",
    "name:zho_x_preferred":[
        "\u5206\u5168"
    ],
    "wof:name":"Fenquan",
    "wof:placetype":"locality"
},
  "geometry": {"coordinates":[103.98480000000001,29.73079],"type":"Point"}
}