{
  "type": "Feature",
  "properties": {
    "gn:admin1_code":"26.0",
    "gn:asciiname":"Hujiayuancun",
    "gn:country_code":"CN",
    "gn:dem":1132,
    "gn:feature_class":"P",
    "gn:feature_code":"PPL",
    "gn:name":"Hujiayuancun",
    "gn:population":0,
    "gn:timezone":"Asia/Shanghai",
    "iso:country":"CN",
    "name:zho_x_preferred":[
        "\u80e1\u5bb6\u586c\u6751"
    ],
    "wof:name":"Hujiayuancun",
    "wof:placetype":"locality"
},
  "geometry": {"coordinates":[109.27687,35.44838],"type":"Point"}
}