{
  "type": "Feature",
  "properties": {
    "gn:admin1_code":"23.0",
    "gn:asciiname":"Wangmengjing",
    "gn:country_code":"CN",
    "gn:dem":4,
    "gn:feature_class":"P",
    "gn:feature_code":"PPL",
    "gn:name":"Wangmengjing",
    "gn:population":0,
    "gn:timezone":"Asia/Shanghai",
    "iso:country":"CN",
    "name:zho_x_preferred":[
        "Wangmengjing"
    ],
    "name:zho_x_variant":[
        "\u738b\u5b5f\u6cfe"
    ],
    "wof:name":"Wangmengjing",
    "wof:placetype":"locality"
},
  "geometry": {"coordinates":[121.21707000000001,31.09946],"type":"Point"}
}