{
  "type": "Feature",
  "properties": {
    "gn:admin1_code":"10.0",
    "gn:asciiname":"Dongxindian",
    "gn:country_code":"CN",
    "gn:dem":16,
    "gn:feature_class":"P",
    "gn:feature_code":"PPL",
    "gn:name":"Dongxindian",
    "gn:population":0,
    "gn:timezone":"Asia/Shanghai",
    "iso:country":"CN",
    "name:zho_x_preferred":[
        "\u4e1c\u8f9b\u5e97"
    ],
    "wof:name":"Dongxindian",
    "wof:placetype":"locality"
},
  "geometry": {"coordinates":[116.34999999999999,38.0438],"type":"Point"}
}