{
  "type": "Feature",
  "properties": {
    "gn:admin1_code":"4.0",
    "gn:asciiname":"Tengjia",
    "gn:country_code":"CN",
    "gn:dem":30,
    "gn:feature_class":"P",
    "gn:feature_code":"PPL",
    "gn:name":"Tengjia",
    "gn:population":0,
    "gn:timezone":"Asia/Shanghai",
    "iso:country":"CN",
    "name:zho_x_preferred":[
        "\u6ed5\u5bb6"
    ],
    "wof:name":"Tengjia",
    "wof:placetype":"locality"
},
  "geometry": {"coordinates":[119.15645000000001,31.97274],"type":"Point"}
}