{
  "type": "Feature",
  "properties": {
    "gn:admin1_code":"30",
    "gn:asciiname":"Jinhu",
    "gn:country_code":"CN",
    "gn:dem":12,
    "gn:feature_class":"P",
    "gn:feature_code":"PPL",
    "gn:name":"Jinhu",
    "gn:population":0,
    "gn:timezone":"Asia/Shanghai",
    "iso:country":"CN",
    "name:ceb_x_preferred":[
        "Jinhu"
    ],
    "name:deu_x_preferred":[
        "Jinhu"
    ],
    "name:fra_x_preferred":[
        "Jinhu"
    ],
    "wof:name":"Jinhu",
    "wof:placetype":"locality"
},
  "geometry": {"coordinates":[116.09166999999999,23.41556],"type":"Point"}
}