{
  "type": "Feature",
  "properties": {
    "gn:admin1_code":"7.0",
    "gn:asciiname":"Dafen",
    "gn:country_code":"CN",
    "gn:dem":761,
    "gn:feature_class":"P",
    "gn:feature_code":"PPL",
    "gn:name":"Dafen",
    "gn:population":0,
    "gn:timezone":"Asia/Shanghai",
    "iso:country":"CN",
    "name:fra_x_preferred":[
        "Dafen"
    ],
    "name:nld_x_preferred":[
        "Dafen"
    ],
    "name:zho_x_preferred":[
        "\u5927\u574b"
    ],
    "wof:name":"Dafen",
    "wof:placetype":"locality"
},
  "geometry": {"coordinates":[118.00790000000001,26.14514],"type":"Point"}
}