{
  "type": "Feature",
  "properties": {
    "gn:admin1_code":"10.0",
    "gn:asciiname":"Huanghuachang",
    "gn:country_code":"CN",
    "gn:dem":478,
    "gn:feature_class":"P",
    "gn:feature_code":"PPL",
    "gn:name":"Huanghuachang",
    "gn:population":0,
    "gn:timezone":"Asia/Shanghai",
    "iso:country":"CN",
    "name:deu_x_preferred":[
        "Huanghuachang"
    ],
    "name:zho_x_preferred":[
        "\u9ec4\u82b1\u573a"
    ],
    "wof:name":"Huanghuachang",
    "wof:placetype":"locality"
},
  "geometry": {"coordinates":[117.39475,40.23845],"type":"Point"}
}