{
  "type": "Feature",
  "properties": {
    "gn:admin1_code":"18",
    "gn:asciiname":"Xiayun",
    "gn:country_code":"CN",
    "gn:dem":584,
    "gn:feature_class":"P",
    "gn:feature_code":"PPL",
    "gn:name":"Xiayun",
    "gn:population":0,
    "gn:timezone":"Asia/Shanghai",
    "iso:country":"CN",
    "name:zho_x_preferred":[
        "\u4e0b\u4e91"
    ],
    "wof:name":"Xiayun",
    "wof:placetype":"locality"
},
  "geometry": {"coordinates":[105.931,25.4978],"type":"Point"}
}