{
  "type": "Feature",
  "properties": {
    "gn:admin1_code":"4.0",
    "gn:asciiname":"Hongzhuanshi Sanzu",
    "gn:country_code":"CN",
    "gn:dem":4,
    "gn:feature_class":"P",
    "gn:feature_code":"PPL",
    "gn:name":"Hongzhuanshi Sanzu",
    "gn:population":0,
    "gn:timezone":"Asia/Shanghai",
    "iso:country":"CN",
    "name:und_x_variant":[
        "\u7ea2\u4e13\u5341\u4e09\u7ec4"
    ],
    "name:zho_x_preferred":[
        "\u7ea2\u4e13\u5341\u4e09\u7ec4"
    ],
    "wof:name":"Hongzhuanshi Sanzu",
    "wof:placetype":"locality"
},
  "geometry": {"coordinates":[120.79756,32.31536],"type":"Point"}
}