{
  "type": "Feature",
  "properties": {
    "gn:admin1_code":"30.0",
    "gn:asciiname":"Dajiang",
    "gn:country_code":"CN",
    "gn:dem":435,
    "gn:feature_class":"P",
    "gn:feature_code":"PPL",
    "gn:name":"Dajiang",
    "gn:population":0,
    "gn:timezone":"Asia/Shanghai",
    "iso:country":"CN",
    "name:ceb_x_preferred":[
        "Dajiang"
    ],
    "name:swe_x_preferred":[
        "Dajiang"
    ],
    "name:zho_x_preferred":[
        "Dajiang"
    ],
    "name:zho_x_variant":[
        "\u5927\u6c5f"
    ],
    "wof:name":"Dajiang",
    "wof:placetype":"locality"
},
  "geometry": {"coordinates":[112.50306,24.57194],"type":"Point"}
}