{
  "type": "Feature",
  "properties": {
    "gn:admin1_code":"19.0",
    "gn:asciiname":"Dawafang",
    "gn:country_code":"CN",
    "gn:dem":39,
    "gn:feature_class":"P",
    "gn:feature_code":"PPL",
    "gn:name":"Dawafang",
    "gn:population":0,
    "gn:timezone":"Asia/Shanghai",
    "iso:country":"CN",
    "name:und_x_variant":[
        "\u5927\u74e6\u623f"
    ],
    "name:zho_x_preferred":[
        "\u5927\u74e6\u623f"
    ],
    "wof:name":"Dawafang",
    "wof:placetype":"locality"
},
  "geometry": {"coordinates":[122.14899,39.32991],"type":"Point"}
}