{
  "type": "Feature",
  "properties": {
    "gn:admin1_code":"6.0",
    "gn:asciiname":"Laishuoke",
    "gn:country_code":"CN",
    "gn:dem":4055,
    "gn:feature_class":"P",
    "gn:feature_code":"PPL",
    "gn:name":"Laishuoke",
    "gn:population":0,
    "gn:timezone":"Asia/Urumqi",
    "iso:country":"CN",
    "name:zho_x_preferred":[
        "\u6765\u8bf4\u53ef"
    ],
    "wof:name":"Laishuoke",
    "wof:placetype":"locality"
},
  "geometry": {"coordinates":[97.06637000000001,32.27659],"type":"Point"}
}