{
  "type": "Feature",
  "properties": {
    "gn:admin1_code":"29.0",
    "gn:asciiname":"Xiaonongchang",
    "gn:country_code":"CN",
    "gn:dem":3120,
    "gn:feature_class":"P",
    "gn:feature_code":"PPLF",
    "gn:name":"Xiaonongchang",
    "gn:population":0,
    "gn:timezone":"Asia/Shanghai",
    "iso:country":"CN",
    "name:zho_x_preferred":[
        "\u5c0f\u519c\u573a"
    ],
    "wof:name":"Xiaonongchang",
    "wof:placetype":"locality"
},
  "geometry": {"coordinates":[101.03,27.0803],"type":"Point"}
}