{
  "type": "Feature",
  "properties": {
    "gn:admin1_code":"11.0",
    "gn:asciiname":"Choumushu",
    "gn:country_code":"CN",
    "gn:dem":194,
    "gn:feature_class":"P",
    "gn:feature_code":"PPL",
    "gn:name":"Choumushu",
    "gn:population":0,
    "gn:timezone":"Asia/Shanghai",
    "iso:country":"CN",
    "name:zho_x_preferred":[
        "Choumushu"
    ],
    "name:zho_x_variant":[
        "\u7a20\u6728\u6811"
    ],
    "wof:name":"Choumushu",
    "wof:placetype":"locality"
},
  "geometry": {"coordinates":[110.83190999999999,28.93608],"type":"Point"}
}