{
  "type": "Feature",
  "properties": {
    "gn:admin1_code":"26.0",
    "gn:asciiname":"Xiangdicun",
    "gn:country_code":"CN",
    "gn:dem":421,
    "gn:feature_class":"P",
    "gn:feature_code":"PPL",
    "gn:name":"Xiangdicun",
    "gn:population":0,
    "gn:timezone":"Asia/Shanghai",
    "iso:country":"CN",
    "name:zho_x_preferred":[
        "\u76f8\u5e95\u6751"
    ],
    "wof:name":"Xiangdicun",
    "wof:placetype":"locality"
},
  "geometry": {"coordinates":[110.02849999999999,34.95208],"type":"Point"}
}