{
  "type": "Feature",
  "properties": {
    "gn:admin1_code":"30.0",
    "gn:asciiname":"Shenxiantang",
    "gn:country_code":"CN",
    "gn:dem":265,
    "gn:feature_class":"P",
    "gn:feature_code":"PPL",
    "gn:name":"Shenxiantang",
    "gn:population":0,
    "gn:timezone":"Asia/Shanghai",
    "iso:country":"CN",
    "name:zho_x_preferred":[
        "\u795e\u4ed9\u5858"
    ],
    "wof:name":"Shenxiantang",
    "wof:placetype":"locality"
},
  "geometry": {"coordinates":[112.81722000000001,24.27278],"type":"Point"}
}