{
  "type": "Feature",
  "properties": {
    "gn:admin1_code":"18.0",
    "gn:asciiname":"Baibei",
    "gn:country_code":"CN",
    "gn:dem":687,
    "gn:feature_class":"P",
    "gn:feature_code":"PPL",
    "gn:name":"Baibei",
    "gn:population":0,
    "gn:timezone":"Asia/Shanghai",
    "iso:country":"CN",
    "name:zho_x_preferred":[
        "\u6446\u8d1d"
    ],
    "wof:name":"Baibei",
    "wof:placetype":"locality"
},
  "geometry": {"coordinates":[108.15600000000001,25.8575],"type":"Point"}
}