{
  "type": "Feature",
  "properties": {
    "gn:admin1_code":"4.0",
    "gn:asciiname":"Renzhong",
    "gn:country_code":"CN",
    "gn:dem":6,
    "gn:feature_class":"P",
    "gn:feature_code":"PPL",
    "gn:name":"Renzhong",
    "gn:population":0,
    "gn:timezone":"Asia/Shanghai",
    "iso:country":"CN",
    "name:zho_x_preferred":[
        "\u4eba\u4f17"
    ],
    "wof:name":"Renzhong",
    "wof:placetype":"locality"
},
  "geometry": {"coordinates":[119.49809,32.33859],"type":"Point"}
}