{
  "type": "Feature",
  "properties": {
    "gn:admin1_code":"32.0",
    "gn:asciiname":"Ciba",
    "gn:country_code":"CN",
    "gn:dem":2419,
    "gn:feature_class":"P",
    "gn:feature_code":"PPL",
    "gn:name":"Ciba",
    "gn:population":0,
    "gn:timezone":"Asia/Shanghai",
    "iso:country":"CN",
    "name:ceb_x_preferred":[
        "Ciba"
    ],
    "name:deu_x_preferred":[
        "Ciba"
    ],
    "name:epo_x_preferred":[
        "Ciba"
    ],
    "name:hun_x_preferred":[
        "Ciba"
    ],
    "name:ron_x_preferred":[
        "Ciba"
    ],
    "name:swe_x_preferred":[
        "Ciba"
    ],
    "name:zho_x_preferred":[
        "\u6b21\u5df4"
    ],
    "wof:name":"Ciba",
    "wof:placetype":"locality"
},
  "geometry": {"coordinates":[101.95099999999999,30.7656],"type":"Point"}
}