{
  "type": "Feature",
  "properties": {
    "gn:admin1_code":"9",
    "gn:asciiname":"Yangzhuang",
    "gn:country_code":"CN",
    "gn:dem":340,
    "gn:feature_class":"P",
    "gn:feature_code":"PPL",
    "gn:name":"Yangzhuang",
    "gn:population":0,
    "gn:timezone":"Asia/Shanghai",
    "iso:country":"CN",
    "name:zho_x_preferred":[
        "\u6768\u5e84"
    ],
    "wof:name":"Yangzhuang",
    "wof:placetype":"locality"
},
  "geometry": {"coordinates":[111.50400999999999,34.80597],"type":"Point"}
}