{
  "type": "Feature",
  "properties": {
    "gn:admin1_code":"31.0",
    "gn:asciiname":"Liugong Nongchang",
    "gn:country_code":"CN",
    "gn:dem":223,
    "gn:feature_class":"P",
    "gn:feature_code":"PPLF",
    "gn:name":"Liugong Nongchang",
    "gn:population":0,
    "gn:timezone":"Asia/Shanghai",
    "iso:country":"CN",
    "name:und_x_variant":[
        "\u516d\u5f13\u519c\u573a"
    ],
    "wof:name":"Liugong Nongchang",
    "wof:placetype":"locality"
},
  "geometry": {"coordinates":[109.77795999999999,18.5267],"type":"Point"}
}