{
  "type": "Feature",
  "properties": {
    "gn:admin1_code":"05",
    "gn:asciiname":"Li-ta-ch'iao",
    "gn:country_code":"CN",
    "gn:dem":335,
    "gn:feature_class":"P",
    "gn:feature_code":"PPL",
    "gn:name":"Li-ta-ch\u2019iao",
    "gn:population":0,
    "gn:timezone":"Asia/Shanghai",
    "iso:country":"CN",
    "wof:name":"Li-ta-ch'iao",
    "wof:placetype":"locality"
},
  "geometry": {"coordinates":[125.93416999999999,42.91972],"type":"Point"}
}