{
  "type": "Feature",
  "properties": {
    "gn:admin1_code":"3.0",
    "gn:asciiname":"Dongjiashi",
    "gn:country_code":"CN",
    "gn:dem":64,
    "gn:feature_class":"P",
    "gn:feature_code":"PPL",
    "gn:name":"Dongjiashi",
    "gn:population":0,
    "gn:timezone":"Asia/Shanghai",
    "iso:country":"CN",
    "name:und_x_variant":[
        "\u8463\u5bb6\u77f3"
    ],
    "wof:name":"Dongjiashi",
    "wof:placetype":"locality"
},
  "geometry": {"coordinates":[116.49798,27.86989],"type":"Point"}
}