{
  "type": "Feature",
  "properties": {
    "gn:admin1_code":"4.0",
    "gn:asciiname":"Dachanghou",
    "gn:country_code":"CN",
    "gn:dem":44,
    "gn:feature_class":"P",
    "gn:feature_code":"PPL",
    "gn:name":"Dachanghou",
    "gn:population":0,
    "gn:timezone":"Asia/Shanghai",
    "iso:country":"CN",
    "name:zho_x_preferred":[
        "\u5927\u573a\u540e"
    ],
    "wof:name":"Dachanghou",
    "wof:placetype":"locality"
},
  "geometry": {"coordinates":[119.04612,32.31608],"type":"Point"}
}