{
  "type": "Feature",
  "properties": {
    "gn:admin1_code":"9.0",
    "gn:asciiname":"Hualizhuang",
    "gn:country_code":"CN",
    "gn:dem":52,
    "gn:feature_class":"P",
    "gn:feature_code":"PPL",
    "gn:name":"Hualizhuang",
    "gn:population":0,
    "gn:timezone":"Asia/Shanghai",
    "iso:country":"CN",
    "name:zho_x_preferred":[
        "\u82b1\u674e\u5e84"
    ],
    "wof:name":"Hualizhuang",
    "wof:placetype":"locality"
},
  "geometry": {"coordinates":[114.9354,33.65658],"type":"Point"}
}