{
  "type": "Feature",
  "properties": {
    "gn:admin1_code":"30",
    "gn:asciiname":"Hulutian",
    "gn:country_code":"CN",
    "gn:dem":498,
    "gn:feature_class":"P",
    "gn:feature_code":"PPL",
    "gn:name":"Hulutian",
    "gn:population":0,
    "gn:timezone":"Asia/Shanghai",
    "iso:country":"CN",
    "name:zho_x_preferred":[
        "\u846b\u82a6\u7530"
    ],
    "wof:name":"Hulutian",
    "wof:placetype":"locality"
},
  "geometry": {"coordinates":[116.38223000000001,23.73537],"type":"Point"}
}