{
  "type": "Feature",
  "properties": {
    "gn:admin1_code":"30.0",
    "gn:admin2_code":"1809857",
    "gn:asciiname":"Qunxing",
    "gn:country_code":"CN",
    "gn:dem":-6,
    "gn:feature_class":"P",
    "gn:feature_code":"PPL",
    "gn:name":"Qunxing",
    "gn:population":0,
    "gn:timezone":"Asia/Shanghai",
    "iso:country":"CN",
    "name:zho_x_preferred":[
        "\u7fa4\u661f"
    ],
    "wof:name":"Qunxing",
    "wof:placetype":"locality"
},
  "geometry": {"coordinates":[113.50163999999999,22.97649],"type":"Point"}
}