{
  "type": "Feature",
  "properties": {
    "gn:admin1_code":"5.0",
    "gn:asciiname":"Mengyicun",
    "gn:country_code":"CN",
    "gn:dem":145,
    "gn:feature_class":"P",
    "gn:feature_code":"PPL",
    "gn:name":"Mengyicun",
    "gn:population":0,
    "gn:timezone":"Asia/Shanghai",
    "iso:country":"CN",
    "name:zho_x_preferred":[
        "\u5b5f\u76ca\u6751"
    ],
    "wof:name":"Mengyicun",
    "wof:placetype":"locality"
},
  "geometry": {"coordinates":[123.41265,44.0534],"type":"Point"}
}