{
  "type": "Feature",
  "properties": {
    "gn:admin1_code":"25.0",
    "gn:asciiname":"Ruanjiakou",
    "gn:country_code":"CN",
    "gn:dem":68,
    "gn:feature_class":"P",
    "gn:feature_code":"PPL",
    "gn:name":"Ruanjiakou",
    "gn:population":0,
    "gn:timezone":"Asia/Shanghai",
    "iso:country":"CN",
    "name:zho_x_preferred":[
        "\u962e\u5bb6\u53e3"
    ],
    "wof:name":"Ruanjiakou",
    "wof:placetype":"locality"
},
  "geometry": {"coordinates":[122.0885,37.42331],"type":"Point"}
}