{
  "type": "Feature",
  "properties": {
    "gn:admin1_code":"4.0",
    "gn:asciiname":"Zhengjiaxu",
    "gn:country_code":"CN",
    "gn:dem":4,
    "gn:feature_class":"P",
    "gn:feature_code":"PPL",
    "gn:name":"Zhengjiaxu",
    "gn:population":0,
    "gn:timezone":"Asia/Shanghai",
    "iso:country":"CN",
    "name:zho_x_preferred":[
        "Zhengjiaxu"
    ],
    "name:zho_x_variant":[
        "\u90d1\u5bb6\u5729"
    ],
    "wof:name":"Zhengjiaxu",
    "wof:placetype":"locality"
},
  "geometry": {"coordinates":[119.1812,33.19709],"type":"Point"}
}