{
  "type": "Feature",
  "properties": {
    "gn:admin1_code":"29.0",
    "gn:asciiname":"Dashuijing",
    "gn:country_code":"CN",
    "gn:dem":2352,
    "gn:feature_class":"P",
    "gn:feature_code":"PPL",
    "gn:name":"Dashuijing",
    "gn:population":0,
    "gn:timezone":"Asia/Shanghai",
    "iso:country":"CN",
    "name:und_x_variant":[
        "\u5927\u6c34\u4e95"
    ],
    "wof:name":"Dashuijing",
    "wof:placetype":"locality"
},
  "geometry": {"coordinates":[103.73474,26.63109],"type":"Point"}
}