{
  "type": "Feature",
  "properties": {
    "gn:admin1_code":"32.0",
    "gn:asciiname":"Maqianpo",
    "gn:country_code":"CN",
    "gn:dem":908,
    "gn:feature_class":"P",
    "gn:feature_code":"PPL",
    "gn:name":"Maqianpo",
    "gn:population":0,
    "gn:timezone":"Asia/Shanghai",
    "iso:country":"CN",
    "name:zho_x_preferred":[
        "\u9a6c\u524d\u5761"
    ],
    "wof:name":"Maqianpo",
    "wof:placetype":"locality"
},
  "geometry": {"coordinates":[107.41500000000001,31.9555],"type":"Point"}
}