{
  "type": "Feature",
  "properties": {
    "gn:admin1_code":"16",
    "gn:asciiname":"Mishaidi",
    "gn:country_code":"CN",
    "gn:dem":400,
    "gn:feature_class":"P",
    "gn:feature_code":"PPL",
    "gn:name":"Mishaidi",
    "gn:population":0,
    "gn:timezone":"Asia/Shanghai",
    "iso:country":"CN",
    "name:zho_x_preferred":[
        "\u7c73\u7b5b\u5e95"
    ],
    "wof:name":"Mishaidi",
    "wof:placetype":"locality"
},
  "geometry": {"coordinates":[110.09399999999999,25.542],"type":"Point"}
}