{
  "type": "Feature",
  "properties": {
    "gn:admin1_code":"5.0",
    "gn:asciiname":"Mingnandong",
    "gn:country_code":"CN",
    "gn:dem":523,
    "gn:feature_class":"P",
    "gn:feature_code":"PPL",
    "gn:name":"Mingnandong",
    "gn:population":0,
    "gn:timezone":"Asia/Shanghai",
    "iso:country":"CN",
    "name:und_x_variant":[
        "\u660e\u5357\u6d1e"
    ],
    "wof:name":"Mingnandong",
    "wof:placetype":"locality"
},
  "geometry": {"coordinates":[129.19465,42.45771],"type":"Point"}
}