{
  "type": "Feature",
  "properties": {
    "gn:admin1_code":"11.0",
    "gn:asciiname":"Zenongping",
    "gn:country_code":"CN",
    "gn:dem":596,
    "gn:feature_class":"P",
    "gn:feature_code":"PPL",
    "gn:name":"Zenongping",
    "gn:population":0,
    "gn:timezone":"Asia/Shanghai",
    "iso:country":"CN",
    "name:zho_x_preferred":[
        "\u6cfd\u519c\u576a"
    ],
    "wof:name":"Zenongping",
    "wof:placetype":"locality"
},
  "geometry": {"coordinates":[109.45153000000001,28.9807],"type":"Point"}
}