{
  "type": "Feature",
  "properties": {
    "gn:admin1_code":"3",
    "gn:asciiname":"Heshuxia",
    "gn:country_code":"CN",
    "gn:dem":115,
    "gn:feature_class":"P",
    "gn:feature_code":"PPL",
    "gn:name":"Heshuxia",
    "gn:population":0,
    "gn:timezone":"Asia/Shanghai",
    "iso:country":"CN",
    "name:zho_x_preferred":[
        "\u8377\u6811\u4e0b"
    ],
    "wof:name":"Heshuxia",
    "wof:placetype":"locality"
},
  "geometry": {"coordinates":[114.976,25.8657],"type":"Point"}
}