{
  "type": "Feature",
  "properties": {
    "gn:admin1_code":"13",
    "gn:asciiname":"Shamenzi",
    "gn:country_code":"CN",
    "gn:dem":957,
    "gn:feature_class":"P",
    "gn:feature_code":"PPL",
    "gn:name":"Shamenzi",
    "gn:population":0,
    "gn:timezone":"Asia/Urumqi",
    "iso:country":"CN",
    "name:und_x_variant":[
        "\u6c99\u95e8\u5b50"
    ],
    "wof:name":"Shamenzi",
    "wof:placetype":"locality"
},
  "geometry": {"coordinates":[89.36815,43.20429],"type":"Point"}
}