{
  "type": "Feature",
  "properties": {
    "gn:admin1_code":"18.0",
    "gn:asciiname":"Zaiyong",
    "gn:country_code":"CN",
    "gn:dem":660,
    "gn:feature_class":"P",
    "gn:feature_code":"PPL",
    "gn:name":"Zaiyong",
    "gn:population":0,
    "gn:timezone":"Asia/Shanghai",
    "iso:country":"CN",
    "name:zho_x_preferred":[
        "\u5bb0\u52c7"
    ],
    "wof:name":"Zaiyong",
    "wof:placetype":"locality"
},
  "geometry": {"coordinates":[108.25700000000001,26.137],"type":"Point"}
}