{
  "type": "Feature",
  "properties": {
    "gn:admin1_code":"29",
    "gn:asciiname":"Tongziping",
    "gn:country_code":"CN",
    "gn:dem":1432,
    "gn:feature_class":"P",
    "gn:feature_code":"PPL",
    "gn:name":"Tongziping",
    "gn:population":0,
    "gn:timezone":"Asia/Shanghai",
    "iso:country":"CN",
    "name:zho_x_preferred":[
        "\u6850\u5b50\u576a"
    ],
    "wof:name":"Tongziping",
    "wof:placetype":"locality"
},
  "geometry": {"coordinates":[105.17,23.4353],"type":"Point"}
}