{
  "type": "Feature",
  "properties": {
    "gn:admin1_code":"24.0",
    "gn:asciiname":"Laohugedong",
    "gn:country_code":"CN",
    "gn:dem":1412,
    "gn:feature_class":"P",
    "gn:feature_code":"PPL",
    "gn:name":"Laohugedong",
    "gn:population":0,
    "gn:timezone":"Asia/Shanghai",
    "iso:country":"CN",
    "name:zho_x_preferred":[
        "\u8001\u864e\u7599\u6d1e"
    ],
    "wof:name":"Laohugedong",
    "wof:placetype":"locality"
},
  "geometry": {"coordinates":[111.02142000000001,36.31612],"type":"Point"}
}