{
  "type": "Feature",
  "properties": {
    "gn:admin1_code":"9",
    "gn:asciiname":"Chuzhuang",
    "gn:country_code":"CN",
    "gn:dem":47,
    "gn:feature_class":"P",
    "gn:feature_code":"PPL",
    "gn:name":"Chuzhuang",
    "gn:population":0,
    "gn:timezone":"Asia/Shanghai",
    "iso:country":"CN",
    "name:zho_x_preferred":[
        "\u695a\u5e84"
    ],
    "wof:name":"Chuzhuang",
    "wof:placetype":"locality"
},
  "geometry": {"coordinates":[115.99679999999999,36.0349],"type":"Point"}
}