{
  "type": "Feature",
  "properties": {
    "gn:admin1_code":"4.0",
    "gn:asciiname":"Yifengsi",
    "gn:country_code":"CN",
    "gn:dem":4,
    "gn:feature_class":"P",
    "gn:feature_code":"PPL",
    "gn:name":"Yifengsi",
    "gn:population":0,
    "gn:timezone":"Asia/Shanghai",
    "iso:country":"CN",
    "name:zho_x_preferred":[
        "\u79fb\u51e4\u5bfa"
    ],
    "wof:name":"Yifengsi",
    "wof:placetype":"locality"
},
  "geometry": {"coordinates":[119.9091,32.69181],"type":"Point"}
}