{
  "type": "Feature",
  "properties": {
    "gn:admin1_code":"18.0",
    "gn:asciiname":"Changfeng",
    "gn:country_code":"CN",
    "gn:dem":842,
    "gn:feature_class":"P",
    "gn:feature_code":"PPL",
    "gn:name":"Changfeng",
    "gn:population":0,
    "gn:timezone":"Asia/Shanghai",
    "iso:country":"CN",
    "name:fra_x_preferred":[
        "Changfeng"
    ],
    "name:pol_x_preferred":[
        "Changfeng"
    ],
    "name:zho_x_preferred":[
        "\u957f\u4e30"
    ],
    "wof:name":"Changfeng",
    "wof:placetype":"locality"
},
  "geometry": {"coordinates":[108.075,26.3717],"type":"Point"}
}