{
  "type": "Feature",
  "properties": {
    "gn:admin1_code":"12.0",
    "gn:asciiname":"Xiadongling",
    "gn:country_code":"CN",
    "gn:dem":27,
    "gn:feature_class":"P",
    "gn:feature_code":"PPL",
    "gn:name":"Xiadongling",
    "gn:population":0,
    "gn:timezone":"Asia/Shanghai",
    "iso:country":"CN",
    "name:zho_x_preferred":[
        "\u4e0b\u4e1c\u5cad"
    ],
    "wof:name":"Xiadongling",
    "wof:placetype":"locality"
},
  "geometry": {"coordinates":[114.00855,30.19446],"type":"Point"}
}