{
  "type": "Feature",
  "properties": {
    "gn:admin1_code":"9",
    "gn:asciiname":"Xindongbei",
    "gn:country_code":"CN",
    "gn:dem":54,
    "gn:feature_class":"P",
    "gn:feature_code":"PPL",
    "gn:name":"Xindongbei",
    "gn:population":0,
    "gn:timezone":"Asia/Shanghai",
    "iso:country":"CN",
    "name:zho_x_preferred":[
        "\u65b0\u4e1c\u5317"
    ],
    "wof:name":"Xindongbei",
    "wof:placetype":"locality"
},
  "geometry": {"coordinates":[115.30509000000001,35.63335],"type":"Point"}
}