{
  "type": "Feature",
  "properties": {
    "gn:admin1_code":"25",
    "gn:asciiname":"Yinjialin",
    "gn:country_code":"CN",
    "gn:dem":56,
    "gn:feature_class":"P",
    "gn:feature_code":"PPL",
    "gn:name":"Yinjialin",
    "gn:population":0,
    "gn:timezone":"Asia/Shanghai",
    "iso:country":"CN",
    "name:zho_x_preferred":[
        "\u6bb7\u5bb6\u6797"
    ],
    "wof:name":"Yinjialin",
    "wof:placetype":"locality"
},
  "geometry": {"coordinates":[116.866,36.5838],"type":"Point"}
}