{
  "type": "Feature",
  "properties": {
    "gn:admin1_code":"2.0",
    "gn:asciiname":"Gaolongchang",
    "gn:country_code":"CN",
    "gn:dem":12,
    "gn:feature_class":"P",
    "gn:feature_code":"PPL",
    "gn:name":"Gaolongchang",
    "gn:population":0,
    "gn:timezone":"Asia/Shanghai",
    "iso:country":"CN",
    "name:und_x_variant":[
        "\u9ad8\u5784\u573a"
    ],
    "wof:name":"Gaolongchang",
    "wof:placetype":"locality"
},
  "geometry": {"coordinates":[120.39388999999998,30.1761],"type":"Point"}
}