{
  "type": "Feature",
  "properties": {
    "gn:admin1_code":"29.0",
    "gn:asciiname":"Chenjiacun",
    "gn:country_code":"CN",
    "gn:dem":2367,
    "gn:feature_class":"P",
    "gn:feature_code":"PPL",
    "gn:name":"Chenjiacun",
    "gn:population":0,
    "gn:timezone":"Asia/Shanghai",
    "iso:country":"CN",
    "name:zho_x_preferred":[
        "\u9648\u5bb6\u6751"
    ],
    "wof:name":"Chenjiacun",
    "wof:placetype":"locality"
},
  "geometry": {"coordinates":[103.399,26.2174],"type":"Point"}
}