{
  "type": "Feature",
  "properties": {
    "gn:admin1_code":"30",
    "gn:asciiname":"Nankeng",
    "gn:country_code":"CN",
    "gn:dem":213,
    "gn:feature_class":"P",
    "gn:feature_code":"PPL",
    "gn:name":"Nankeng",
    "gn:population":0,
    "gn:timezone":"Asia/Shanghai",
    "iso:country":"CN",
    "name:und_x_variant":[
        "\u5357\u5751",
        "Wunikeng"
    ],
    "wof:name":"Nankeng",
    "wof:placetype":"locality"
},
  "geometry": {"coordinates":[115.36944,24.38799],"type":"Point"}
}