{
  "type": "Feature",
  "properties": {
    "gn:admin1_code":"7",
    "gn:asciiname":"Jinyuan",
    "gn:country_code":"CN",
    "gn:dem":13,
    "gn:feature_class":"P",
    "gn:feature_code":"PPL",
    "gn:name":"Jinyuan",
    "gn:population":0,
    "gn:timezone":"Asia/Shanghai",
    "iso:country":"CN",
    "name:und_x_variant":[
        "\u9526\u56ed",
        "Jinyuan"
    ],
    "wof:name":"Jinyuan",
    "wof:placetype":"locality"
},
  "geometry": {"coordinates":[118.02412,24.59542],"type":"Point"}
}