{
  "type": "Feature",
  "properties": {
    "gn:admin1_code":"32.0",
    "gn:asciiname":"Longchipu",
    "gn:country_code":"CN",
    "gn:dem":383,
    "gn:feature_class":"P",
    "gn:feature_code":"PPL",
    "gn:name":"Longchipu",
    "gn:population":0,
    "gn:timezone":"Asia/Shanghai",
    "iso:country":"CN",
    "name:zho_x_preferred":[
        "\u9f99\u6c60\u94fa"
    ],
    "wof:name":"Longchipu",
    "wof:placetype":"locality"
},
  "geometry": {"coordinates":[103.944,29.5151],"type":"Point"}
}