{
  "type": "Feature",
  "properties": {
    "gn:admin1_code":"19.0",
    "gn:asciiname":"Lugou",
    "gn:country_code":"CN",
    "gn:dem":42,
    "gn:feature_class":"P",
    "gn:feature_code":"PPL",
    "gn:name":"L\u00fcgou",
    "gn:population":0,
    "gn:timezone":"Asia/Shanghai",
    "iso:country":"CN",
    "name:und_x_variant":[
        "L\u00fcgou"
    ],
    "name:zho_x_preferred":[
        "\u5415\u6c9f"
    ],
    "wof:name":"Lugou",
    "wof:placetype":"locality"
},
  "geometry": {"coordinates":[121.837,39.8425],"type":"Point"}
}