{
  "type": "Feature",
  "properties": {
    "gn:admin1_code":"1.0",
    "gn:asciiname":"Liuqingcun",
    "gn:country_code":"CN",
    "gn:dem":119,
    "gn:feature_class":"P",
    "gn:feature_code":"PPL",
    "gn:name":"Liuqingcun",
    "gn:population":0,
    "gn:timezone":"Asia/Shanghai",
    "iso:country":"CN",
    "name:zho_x_preferred":[
        "\u67f3\u9752\u6751"
    ],
    "wof:name":"Liuqingcun",
    "wof:placetype":"locality"
},
  "geometry": {"coordinates":[115.96832999999999,30.62765],"type":"Point"}
}