{
  "type": "Feature",
  "properties": {
    "gn:admin1_code":"25.0",
    "gn:asciiname":"Kongchongshui",
    "gn:cc2":"CN",
    "gn:country_code":"CN",
    "gn:dem":66,
    "gn:feature_class":"P",
    "gn:feature_code":"PPL",
    "gn:name":"Kongchongshui",
    "gn:population":0,
    "gn:timezone":"Asia/Shanghai",
    "iso:country":"CN",
    "name:zho_x_preferred":[
        "\u7a7a\u51b2\u6c34"
    ],
    "wof:name":"Kongchongshui",
    "wof:placetype":"locality"
},
  "geometry": {"coordinates":[119.33262000000001,35.55693],"type":"Point"}
}