{
  "type": "Feature",
  "properties": {
    "gn:admin1_code":"29",
    "gn:asciiname":"Xinlupo",
    "gn:country_code":"CN",
    "gn:dem":1417,
    "gn:feature_class":"P",
    "gn:feature_code":"PPL",
    "gn:name":"Xinlupo",
    "gn:population":0,
    "gn:timezone":"Asia/Shanghai",
    "iso:country":"CN",
    "name:zho_x_preferred":[
        "\u65b0\u8def\u5761"
    ],
    "wof:name":"Xinlupo",
    "wof:placetype":"locality"
},
  "geometry": {"coordinates":[104.747,23.1747],"type":"Point"}
}