{
  "type": "Feature",
  "properties": {
    "gn:admin1_code":"19.0",
    "gn:asciiname":"Houtianjia Youfang",
    "gn:country_code":"CN",
    "gn:dem":85,
    "gn:feature_class":"P",
    "gn:feature_code":"PPL",
    "gn:name":"Houtianjia Youfang",
    "gn:population":0,
    "gn:timezone":"Asia/Shanghai",
    "iso:country":"CN",
    "name:zho_x_preferred":[
        "\u540e\u7530\u5bb6\u6cb9\u574a"
    ],
    "wof:name":"Houtianjia Youfang",
    "wof:placetype":"locality"
},
  "geometry": {"coordinates":[123.50175,42.90973],"type":"Point"}
}