{
  "type": "Feature",
  "properties": {
    "gn:admin1_code":"25.0",
    "gn:asciiname":"Wangbingmajicun",
    "gn:country_code":"CN",
    "gn:dem":44,
    "gn:feature_class":"P",
    "gn:feature_code":"PPL",
    "gn:name":"Wangbingmajicun",
    "gn:population":0,
    "gn:timezone":"Asia/Shanghai",
    "iso:country":"CN",
    "name:zho_x_preferred":[
        "\u738b\u5175\u9a6c\u96c6\u6751"
    ],
    "wof:name":"Wangbingmajicun",
    "wof:placetype":"locality"
},
  "geometry": {"coordinates":[116.0145,35.5563],"type":"Point"}
}