{
  "type": "Feature",
  "properties": {
    "gn:admin1_code":"15.0",
    "gn:asciiname":"Nianjiazhuang",
    "gn:country_code":"CN",
    "gn:dem":2251,
    "gn:feature_class":"P",
    "gn:feature_code":"PPL",
    "gn:name":"Nianjiazhuang",
    "gn:population":0,
    "gn:timezone":"Asia/Shanghai",
    "iso:country":"CN",
    "name:zho_x_preferred":[
        "\u5e74\u5bb6\u5e84"
    ],
    "wof:name":"Nianjiazhuang",
    "wof:placetype":"locality"
},
  "geometry": {"coordinates":[103.30500000000001,35.4007],"type":"Point"}
}