{
  "type": "Feature",
  "properties": {
    "gn:admin1_code":"14.0",
    "gn:asciiname":"Jiarigong",
    "gn:country_code":"CN",
    "gn:dem":4339,
    "gn:feature_class":"P",
    "gn:feature_code":"PPL",
    "gn:name":"Jiarigong",
    "gn:population":0,
    "gn:timezone":"Asia/Urumqi",
    "iso:country":"CN",
    "name:zho_x_preferred":[
        "\u7532\u65e5\u5171"
    ],
    "wof:name":"Jiarigong",
    "wof:placetype":"locality"
},
  "geometry": {"coordinates":[92.19553000000001,28.93019],"type":"Point"}
}