{
  "type": "Feature",
  "properties": {
    "gn:admin1_code":"14.0",
    "gn:asciiname":"Eka Muchang",
    "gn:country_code":"CN",
    "gn:dem":4596,
    "gn:feature_class":"P",
    "gn:feature_code":"PPLF",
    "gn:name":"Eka Muchang",
    "gn:population":0,
    "gn:timezone":"Asia/Urumqi",
    "iso:country":"CN",
    "name:zho_x_preferred":[
        "\u9102\u5361\u7267\u573a"
    ],
    "wof:name":"Eka Muchang",
    "wof:placetype":"locality"
},
  "geometry": {"coordinates":[96.30991,30.13484],"type":"Point"}
}