{
  "type": "Feature",
  "properties": {
    "gn:admin1_code":"13",
    "gn:asciiname":"Bositan",
    "gn:country_code":"CN",
    "gn:dem":1056,
    "gn:feature_class":"P",
    "gn:feature_code":"PPL",
    "gn:name":"Bositan",
    "gn:population":0,
    "gn:timezone":"Asia/Shanghai",
    "iso:country":"CN",
    "name:und_x_variant":[
        "\u535a\u65af\u5766"
    ],
    "wof:name":"Bositan",
    "wof:placetype":"locality"
},
  "geometry": {"coordinates":[79.72159000000001,40.55535],"type":"Point"}
}