{
  "type": "Feature",
  "properties": {
    "gn:admin1_code":"15.0",
    "gn:asciiname":"Jienaoqi",
    "gn:country_code":"CN",
    "gn:dem":1745,
    "gn:feature_class":"P",
    "gn:feature_code":"PPL",
    "gn:name":"Jienaoqi",
    "gn:population":0,
    "gn:timezone":"Asia/Shanghai",
    "iso:country":"CN",
    "name:zho_x_preferred":[
        "\u7ed3\u8111\u7566"
    ],
    "wof:name":"Jienaoqi",
    "wof:placetype":"locality"
},
  "geometry": {"coordinates":[102.434,37.9731],"type":"Point"}
}