{
  "type": "Feature",
  "properties": {
    "gn:admin1_code":"6.0",
    "gn:asciiname":"Maituotang",
    "gn:country_code":"CN",
    "gn:dem":4194,
    "gn:feature_class":"P",
    "gn:feature_code":"PPL",
    "gn:name":"Maituotang",
    "gn:population":0,
    "gn:timezone":"Asia/Shanghai",
    "iso:country":"CN",
    "name:zho_x_preferred":[
        "\u9ea6\u6258\u5858"
    ],
    "wof:name":"Maituotang",
    "wof:placetype":"locality"
},
  "geometry": {"coordinates":[100.89894,33.14356],"type":"Point"}
}