{
  "type": "Feature",
  "properties": {
    "gn:admin1_code":"30",
    "gn:asciiname":"Nadie",
    "gn:country_code":"CN",
    "gn:dem":24,
    "gn:feature_class":"P",
    "gn:feature_code":"PPL",
    "gn:name":"Nadie",
    "gn:population":0,
    "gn:timezone":"Asia/Urumqi",
    "iso:country":"CN",
    "name:und_x_variant":[
        "Nasuowei",
        "Nadie"
    ],
    "name:zho_x_preferred":[
        "\u90a3\u53e0"
    ],
    "wof:name":"Nadie",
    "wof:placetype":"locality"
},
  "geometry": {"coordinates":[110.45859,21.43006],"type":"Point"}
}