{
  "type": "Feature",
  "properties": {
    "gn:admin1_code":"10",
    "gn:asciiname":"Dingjiakeng",
    "gn:country_code":"CN",
    "gn:dem":1042,
    "gn:feature_class":"P",
    "gn:feature_code":"PPL",
    "gn:name":"Dingjiakeng",
    "gn:population":0,
    "gn:timezone":"Asia/Shanghai",
    "iso:country":"CN",
    "name:zho_x_preferred":[
        "\u4e01\u5bb6\u5751"
    ],
    "wof:name":"Dingjiakeng",
    "wof:placetype":"locality"
},
  "geometry": {"coordinates":[115.97398,40.72626],"type":"Point"}
}