{
  "type": "Feature",
  "properties": {
    "gn:admin1_code":"2.0",
    "gn:asciiname":"Wangpiwu",
    "gn:country_code":"CN",
    "gn:dem":544,
    "gn:feature_class":"P",
    "gn:feature_code":"PPL",
    "gn:name":"Wangpiwu",
    "gn:population":0,
    "gn:timezone":"Asia/Shanghai",
    "iso:country":"CN",
    "name:und_x_variant":[
        "\u738b\u76ae\u575e",
        "Wangpiwu"
    ],
    "wof:name":"Wangpiwu",
    "wof:placetype":"locality"
},
  "geometry": {"coordinates":[119.69125,29.50079],"type":"Point"}
}