{
  "type": "Feature",
  "properties": {
    "gn:admin1_code":"32.0",
    "gn:asciiname":"Hala",
    "gn:country_code":"CN",
    "gn:dem":3693,
    "gn:feature_class":"P",
    "gn:feature_code":"PPL",
    "gn:name":"Hala",
    "gn:population":0,
    "gn:timezone":"Asia/Shanghai",
    "iso:country":"CN",
    "name:ceb_x_preferred":[
        "Hala"
    ],
    "name:deu_x_preferred":[
        "Hala"
    ],
    "name:hsb_x_preferred":[
        "Hala"
    ],
    "name:jpn_x_preferred":[
        "\u30cf\u30fc\u30e9"
    ],
    "name:pol_x_preferred":[
        "Hala"
    ],
    "name:slk_x_preferred":[
        "Hala"
    ],
    "name:slv_x_preferred":[
        "Hala"
    ],
    "name:srp_x_preferred":[
        "\u0425\u0430\u043b\u0430"
    ],
    "name:swe_x_preferred":[
        "Hala"
    ],
    "name:zho_x_preferred":[
        "\u54c8\u62c9"
    ],
    "wof:name":"Hala",
    "wof:placetype":"locality"
},
  "geometry": {"coordinates":[100.68000000000001,29.6003],"type":"Point"}
}