{
  "type": "Feature",
  "properties": {
    "gn:admin1_code":"32.0",
    "gn:asciiname":"Hala",
    "gn:country_code":"CN",
    "gn:dem":3693,
    "gn:feature_class":"P",
    "gn:feature_code":"PPL",
    "gn:name":"Hala",
    "gn:population":0,
    "gn:timezone":"Asia/Shanghai",
    "iso:country":"CN",
    "name:zho_x_preferred":[
        "\u54c8\u62c9"
    ],
    "wof:name":"Hala",
    "wof:placetype":"locality"
},
  "geometry": {"coordinates":[100.68000000000001,29.6003],"type":"Point"}
}