{
  "type": "Feature",
  "properties": {
    "gn:admin1_code":"24.0",
    "gn:asciiname":"Changyazi",
    "gn:country_code":"CN",
    "gn:dem":1892,
    "gn:feature_class":"P",
    "gn:feature_code":"PPL",
    "gn:name":"Changyazi",
    "gn:population":0,
    "gn:timezone":"Asia/Shanghai",
    "iso:country":"CN",
    "name:zho_x_preferred":[
        "\u957f\u5d16\u5b50"
    ],
    "wof:name":"Changyazi",
    "wof:placetype":"locality"
},
  "geometry": {"coordinates":[111.84528,38.58892],"type":"Point"}
}