{
  "type": "Feature",
  "properties": {
    "gn:admin1_code":"31.0",
    "gn:asciiname":"Wenfengling",
    "gn:country_code":"CN",
    "gn:dem":24,
    "gn:feature_class":"P",
    "gn:feature_code":"PPL",
    "gn:name":"Wenfengling",
    "gn:population":0,
    "gn:timezone":"Asia/Shanghai",
    "iso:country":"CN",
    "name:zho_x_preferred":[
        "\u6587\u5cf0\u5cad"
    ],
    "wof:name":"Wenfengling",
    "wof:placetype":"locality"
},
  "geometry": {"coordinates":[110.51412000000001,19.33771],"type":"Point"}
}