{
  "type": "Feature",
  "properties": {
    "gn:admin1_code":"3.0",
    "gn:asciiname":"Zhushuikeng",
    "gn:country_code":"CN",
    "gn:dem":139,
    "gn:feature_class":"P",
    "gn:feature_code":"PPL",
    "gn:name":"Zhushuikeng",
    "gn:population":0,
    "gn:timezone":"Asia/Shanghai",
    "iso:country":"CN",
    "name:und_x_variant":[
        "\u7af9\u6c34\u5751"
    ],
    "wof:name":"Zhushuikeng",
    "wof:placetype":"locality"
},
  "geometry": {"coordinates":[115.16249000000001,25.94277],"type":"Point"}
}