{
  "type": "Feature",
  "properties": {
    "gn:admin1_code":"13.0",
    "gn:asciiname":"Kalajiaomake",
    "gn:country_code":"CN",
    "gn:dem":915,
    "gn:feature_class":"P",
    "gn:feature_code":"PPL",
    "gn:name":"Kalajiaomake",
    "gn:population":0,
    "gn:timezone":"Asia/Urumqi",
    "iso:country":"CN",
    "name:zho_x_preferred":[
        "\u5361\u62c9\u89c9\u9a6c\u514b"
    ],
    "wof:name":"Kalajiaomake",
    "wof:placetype":"locality"
},
  "geometry": {"coordinates":[84.92801999999998,40.95452],"type":"Point"}
}