{
  "type": "Feature",
  "properties": {
    "gn:admin1_code":"12.0",
    "gn:asciiname":"Nanbian",
    "gn:country_code":"CN",
    "gn:dem":389,
    "gn:feature_class":"P",
    "gn:feature_code":"PPL",
    "gn:name":"Nanbian",
    "gn:population":0,
    "gn:timezone":"Asia/Shanghai",
    "iso:country":"CN",
    "name:zho_x_preferred":[
        "Nanbian"
    ],
    "name:zho_x_variant":[
        "\u5357\u8fb9"
    ],
    "wof:name":"Nanbian",
    "wof:placetype":"locality"
},
  "geometry": {"coordinates":[111.27288,30.9611],"type":"Point"}
}