{
  "type": "Feature",
  "properties": {
    "gn:admin1_code":"11.0",
    "gn:asciiname":"Liaojiamen",
    "gn:country_code":"CN",
    "gn:dem":32,
    "gn:feature_class":"P",
    "gn:feature_code":"PPL",
    "gn:name":"Liaojiamen",
    "gn:population":0,
    "gn:timezone":"Asia/Shanghai",
    "iso:country":"CN",
    "name:zho_x_preferred":[
        "\u5ed6\u5bb6\u95e8"
    ],
    "wof:name":"Liaojiamen",
    "wof:placetype":"locality"
},
  "geometry": {"coordinates":[112.44713,29.55043],"type":"Point"}
}