{
  "type": "Feature",
  "properties": {
    "gn:admin1_code":"4.0",
    "gn:asciiname":"Caojiayuangou",
    "gn:country_code":"CN",
    "gn:dem":6,
    "gn:feature_class":"P",
    "gn:feature_code":"PPL",
    "gn:name":"Caojiayuangou",
    "gn:population":0,
    "gn:timezone":"Asia/Shanghai",
    "iso:country":"CN",
    "name:und_x_variant":[
        "\u66f9\u5bb6\u56ed\u6c9f"
    ],
    "name:zho_x_preferred":[
        "\u66f9\u5bb6\u56ed\u6c9f"
    ],
    "wof:name":"Caojiayuangou",
    "wof:placetype":"locality"
},
  "geometry": {"coordinates":[120.40687,32.50937],"type":"Point"}
}