{
  "type": "Feature",
  "properties": {
    "gn:admin1_code":"12",
    "gn:asciiname":"Gaojiayan",
    "gn:country_code":"CN",
    "gn:dem":230,
    "gn:feature_class":"P",
    "gn:feature_code":"PPLA4",
    "gn:name":"Gaojiayan",
    "gn:population":0,
    "gn:timezone":"Asia/Shanghai",
    "iso:country":"CN",
    "name:und_x_variant":[
        "Kao-chia-yen",
        "Gaojiayan",
        "\u9ad8\u5bb6\u5830",
        "Gaojiayan Zhen",
        "\u9ad8\u5bb6\u5830\u9547"
    ],
    "wof:name":"Gaojiayan",
    "wof:placetype":"locality"
},
  "geometry": {"coordinates":[111.05573,30.60881],"type":"Point"}
}