{
  "type": "Feature",
  "properties": {
    "gn:admin1_code":"32.0",
    "gn:asciiname":"Rengugongba",
    "gn:country_code":"CN",
    "gn:dem":3752,
    "gn:feature_class":"P",
    "gn:feature_code":"PPL",
    "gn:name":"Rengugongba",
    "gn:population":0,
    "gn:timezone":"Asia/Shanghai",
    "iso:country":"CN",
    "name:zho_x_preferred":[
        "\u4ec1\u53e4\u8d21\u5df4"
    ],
    "wof:name":"Rengugongba",
    "wof:placetype":"locality"
},
  "geometry": {"coordinates":[99.163,32.2829],"type":"Point"}
}