{
  "type": "Feature",
  "properties": {
    "gn:admin1_code":"1.0",
    "gn:asciiname":"Jienancun",
    "gn:country_code":"CN",
    "gn:dem":70,
    "gn:feature_class":"P",
    "gn:feature_code":"PPL",
    "gn:name":"Jienancun",
    "gn:population":0,
    "gn:timezone":"Asia/Shanghai",
    "iso:country":"CN",
    "name:zho_x_preferred":[
        "\u8857\u5357\u6751"
    ],
    "wof:name":"Jienancun",
    "wof:placetype":"locality"
},
  "geometry": {"coordinates":[117.39507999999999,32.6095],"type":"Point"}
}