{
  "type": "Feature",
  "properties": {
    "gn:admin1_code":"25.0",
    "gn:asciiname":"Xiaomajia",
    "gn:cc2":"CN",
    "gn:country_code":"CN",
    "gn:dem":40,
    "gn:feature_class":"P",
    "gn:feature_code":"PPL",
    "gn:name":"Xiaomajia",
    "gn:population":0,
    "gn:timezone":"Asia/Shanghai",
    "iso:country":"CN",
    "name:zho_x_preferred":[
        "\u5c0f\u9a6c\u5bb6"
    ],
    "wof:name":"Xiaomajia",
    "wof:placetype":"locality"
},
  "geometry": {"coordinates":[119.94118,35.80559],"type":"Point"}
}