{
  "type": "Feature",
  "properties": {
    "gn:admin1_code":"30",
    "gn:asciiname":"Zhangguan",
    "gn:country_code":"CN",
    "gn:dem":95,
    "gn:feature_class":"P",
    "gn:feature_code":"PPL",
    "gn:name":"Zhangguan",
    "gn:population":0,
    "gn:timezone":"Asia/Urumqi",
    "iso:country":"CN",
    "name:zho_x_preferred":[
        "\u7ae0\u5b98"
    ],
    "wof:name":"Zhangguan",
    "wof:placetype":"locality"
},
  "geometry": {"coordinates":[110.55607999999999,22.14545],"type":"Point"}
}