{
  "type": "Feature",
  "properties": {
    "gn:admin1_code":"15.0",
    "gn:asciiname":"Yashang",
    "gn:country_code":"CN",
    "gn:dem":2541,
    "gn:feature_class":"P",
    "gn:feature_code":"PPL",
    "gn:name":"Yashang",
    "gn:population":0,
    "gn:timezone":"Asia/Shanghai",
    "iso:country":"CN",
    "name:zho_x_preferred":[
        "\u5d16\u4e0a"
    ],
    "wof:name":"Yashang",
    "wof:placetype":"locality"
},
  "geometry": {"coordinates":[104.81865999999999,33.65537],"type":"Point"}
}