{
  "type": "Feature",
  "properties": {
    "gn:admin1_code":"26.0",
    "gn:asciiname":"Xiaohuangpancun",
    "gn:country_code":"CN",
    "gn:dem":793,
    "gn:feature_class":"P",
    "gn:feature_code":"PPL",
    "gn:name":"Xiaohuangpancun",
    "gn:population":0,
    "gn:timezone":"Asia/Shanghai",
    "iso:country":"CN",
    "name:zho_x_preferred":[
        "\u5c0f\u9ec4\u7554\u6751"
    ],
    "wof:name":"Xiaohuangpancun",
    "wof:placetype":"locality"
},
  "geometry": {"coordinates":[110.55865,37.1746],"type":"Point"}
}