{
  "type": "Feature",
  "properties": {
    "gn:admin1_code":"8.0",
    "gn:asciiname":"Haojiatun",
    "gn:country_code":"CN",
    "gn:dem":121,
    "gn:feature_class":"P",
    "gn:feature_code":"PPL",
    "gn:name":"Haojiatun",
    "gn:population":0,
    "gn:timezone":"Asia/Shanghai",
    "iso:country":"CN",
    "name:zho_x_preferred":[
        "\u90dd\u5bb6\u5c6f"
    ],
    "wof:name":"Haojiatun",
    "wof:placetype":"locality"
},
  "geometry": {"coordinates":[127.00320000000001,45.93489],"type":"Point"}
}