{
  "type": "Feature",
  "properties": {
    "gn:admin1_code":"9.0",
    "gn:asciiname":"Lijiapo",
    "gn:country_code":"CN",
    "gn:dem":979,
    "gn:feature_class":"P",
    "gn:feature_code":"PPL",
    "gn:name":"Lijiapo",
    "gn:population":0,
    "gn:timezone":"Asia/Shanghai",
    "iso:country":"CN",
    "name:und_x_variant":[
        "\u674e\u5bb6\u5761",
        "Lijiapo"
    ],
    "wof:name":"Lijiapo",
    "wof:placetype":"locality"
},
  "geometry": {"coordinates":[112.03475,33.32546],"type":"Point"}
}