{
  "type": "Feature",
  "properties": {
    "gn:admin1_code":"8.0",
    "gn:asciiname":"Zhaoguang Erfenchang Shiqidui",
    "gn:country_code":"CN",
    "gn:dem":288,
    "gn:feature_class":"P",
    "gn:feature_code":"PPLF",
    "gn:name":"Zhaoguang Erfenchang Shiqidui",
    "gn:population":0,
    "gn:timezone":"Asia/Shanghai",
    "iso:country":"CN",
    "name:zho_x_preferred":[
        "\u8d75\u5149\u4e8c\u5206\u573a\u5341\u4e03\u961f"
    ],
    "wof:name":"Zhaoguang Erfenchang Shiqidui",
    "wof:placetype":"locality"
},
  "geometry": {"coordinates":[126.65218,48.04216],"type":"Point"}
}