{
  "type": "Feature",
  "properties": {
    "gn:admin1_code":"7.0",
    "gn:asciiname":"Xiazhuangyang",
    "gn:country_code":"CN",
    "gn:dem":144,
    "gn:feature_class":"P",
    "gn:feature_code":"PPL",
    "gn:name":"Xiazhuangyang",
    "gn:population":0,
    "gn:timezone":"Asia/Shanghai",
    "iso:country":"CN",
    "name:zho_x_preferred":[
        "\u4e0b\u5e84\u6d0b"
    ],
    "wof:name":"Xiazhuangyang",
    "wof:placetype":"locality"
},
  "geometry": {"coordinates":[117.77287,26.50446],"type":"Point"}
}