{
  "type": "Feature",
  "properties": {
    "gn:admin1_code":"19.0",
    "gn:asciiname":"Houfengjiatun",
    "gn:country_code":"CN",
    "gn:dem":58,
    "gn:feature_class":"P",
    "gn:feature_code":"PPL",
    "gn:name":"Houfengjiatun",
    "gn:population":0,
    "gn:timezone":"Asia/Shanghai",
    "iso:country":"CN",
    "name:zho_x_preferred":[
        "\u540e\u51af\u5bb6\u5c6f"
    ],
    "wof:name":"Houfengjiatun",
    "wof:placetype":"locality"
},
  "geometry": {"coordinates":[122.754,42.2502],"type":"Point"}
}