{
  "type": "Feature",
  "properties": {
    "gn:admin1_code":"29.0",
    "gn:asciiname":"Fujiazhai",
    "gn:country_code":"CN",
    "gn:dem":1892,
    "gn:feature_class":"P",
    "gn:feature_code":"PPL",
    "gn:name":"Fujiazhai",
    "gn:population":0,
    "gn:timezone":"Asia/Shanghai",
    "iso:country":"CN",
    "name:zho_x_preferred":[
        "\u4ed8\u5bb6\u5be8"
    ],
    "wof:name":"Fujiazhai",
    "wof:placetype":"locality"
},
  "geometry": {"coordinates":[104.736,27.3536],"type":"Point"}
}