{
  "type": "Feature",
  "properties": {
    "gn:admin1_code":"06",
    "gn:asciiname":"Zhiqing Songduo",
    "gn:country_code":"CN",
    "gn:dem":3778,
    "gn:feature_class":"P",
    "gn:feature_code":"PPLA3",
    "gn:name":"Zhiqing Songduo",
    "gn:population":0,
    "gn:timezone":"Asia/Shanghai",
    "iso:country":"CN",
    "name:und_x_variant":[
        "Chiu-chih",
        "Jigzhi",
        "Chih-ch\u2019ing-sung-to",
        "Chugq\u00eansumdo",
        "Zhiqing Songduo",
        "Zhiqing Songduo Zhen",
        "Jiuzhi",
        "Jiuzhi Xian"
    ],
    "name:zho_x_preferred":[
        "\u667a\u9752\u677e\u591a"
    ],
    "name:zho_x_variant":[
        "\u667a\u9752\u677e\u591a\u9547",
        "\u4e45\u6cbb",
        "\u4e45\u6cbb\u53bf"
    ],
    "wof:name":"Zhiqing Songduo",
    "wof:placetype":"locality"
},
  "geometry": {"coordinates":[101.43333,33.43333],"type":"Point"}
}