{
  "type": "Feature",
  "properties": {
    "gn:admin1_code":"29.0",
    "gn:asciiname":"Hemuzha",
    "gn:country_code":"CN",
    "gn:dem":2057,
    "gn:feature_class":"P",
    "gn:feature_code":"PPL",
    "gn:name":"Hemuzha",
    "gn:population":0,
    "gn:timezone":"Asia/Shanghai",
    "iso:country":"CN",
    "name:zho_x_preferred":[
        "\u548c\u7766\u624e"
    ],
    "wof:name":"Hemuzha",
    "wof:placetype":"locality"
},
  "geometry": {"coordinates":[103.89100000000001,26.3636],"type":"Point"}
}