{
  "type": "Feature",
  "properties": {
    "gn:admin1_code":"25",
    "gn:asciiname":"Changyugou",
    "gn:country_code":"CN",
    "gn:dem":44,
    "gn:feature_class":"P",
    "gn:feature_code":"PPL",
    "gn:name":"Changyugou",
    "gn:population":0,
    "gn:timezone":"Asia/Shanghai",
    "iso:country":"CN",
    "name:zho_x_preferred":[
        "\u5e38\u4e8e\u6c9f"
    ],
    "wof:name":"Changyugou",
    "wof:placetype":"locality"
},
  "geometry": {"coordinates":[117.976,34.8254],"type":"Point"}
}