{
  "type": "Feature",
  "properties": {
    "gn:admin1_code":"29.0",
    "gn:asciiname":"Xiaochangping",
    "gn:country_code":"CN",
    "gn:dem":2207,
    "gn:feature_class":"P",
    "gn:feature_code":"PPL",
    "gn:name":"Xiaochangping",
    "gn:population":0,
    "gn:timezone":"Asia/Shanghai",
    "iso:country":"CN",
    "name:zho_x_preferred":[
        "\u5c0f\u957f\u576a"
    ],
    "wof:name":"Xiaochangping",
    "wof:placetype":"locality"
},
  "geometry": {"coordinates":[100.715,26.7686],"type":"Point"}
}