{
  "type": "Feature",
  "properties": {
    "gn:admin1_code":"3.0",
    "gn:asciiname":"Caijiapu",
    "gn:country_code":"CN",
    "gn:dem":65,
    "gn:feature_class":"P",
    "gn:feature_code":"PPL",
    "gn:name":"Caijiapu",
    "gn:population":0,
    "gn:timezone":"Asia/Shanghai",
    "iso:country":"CN",
    "name:und_x_variant":[
        "\u8521\u5bb6\u94fa"
    ],
    "wof:name":"Caijiapu",
    "wof:placetype":"locality"
},
  "geometry": {"coordinates":[115.64867,28.61758],"type":"Point"}
}