{
  "type": "Feature",
  "properties": {
    "gn:admin1_code":"25",
    "gn:asciiname":"Dongdaxutuan",
    "gn:country_code":"CN",
    "gn:dem":114,
    "gn:feature_class":"P",
    "gn:feature_code":"PPL",
    "gn:name":"Dongdaxutuan",
    "gn:population":0,
    "gn:timezone":"Asia/Shanghai",
    "iso:country":"CN",
    "name:zho_x_preferred":[
        "\u4e1c\u5927\u5f90\u7583"
    ],
    "wof:name":"Dongdaxutuan",
    "wof:placetype":"locality"
},
  "geometry": {"coordinates":[118.572,35.4277],"type":"Point"}
}