{
  "type": "Feature",
  "properties": {
    "gn:admin1_code":"32",
    "gn:asciiname":"Beicheng",
    "gn:country_code":"CN",
    "gn:dem":387,
    "gn:feature_class":"P",
    "gn:feature_code":"PPL",
    "gn:name":"Beicheng",
    "gn:population":0,
    "gn:timezone":"Asia/Shanghai",
    "iso:country":"CN",
    "name:zho_x_preferred":[
        "\u5317\u57ce"
    ],
    "wof:name":"Beicheng",
    "wof:placetype":"locality"
},
  "geometry": {"coordinates":[106.41719000000001,30.57164],"type":"Point"}
}