{
  "type": "Feature",
  "properties": {
    "gn:admin1_code":"19.0",
    "gn:asciiname":"Qiange Zhenbucun",
    "gn:country_code":"CN",
    "gn:dem":8,
    "gn:feature_class":"P",
    "gn:feature_code":"PPL",
    "gn:name":"Qiange Zhenbucun",
    "gn:population":0,
    "gn:timezone":"Asia/Shanghai",
    "iso:country":"CN",
    "name:zho_x_preferred":[
        "\u524d\u9769\u9547\u5821\u6751"
    ],
    "wof:name":"Qiange Zhenbucun",
    "wof:placetype":"locality"
},
  "geometry": {"coordinates":[121.51217,38.98823],"type":"Point"}
}