{
  "type": "Feature",
  "properties": {
    "gn:admin1_code":"22.0",
    "gn:asciiname":"Mayu",
    "gn:country_code":"CN",
    "gn:dem":102,
    "gn:feature_class":"P",
    "gn:feature_code":"PPL",
    "gn:name":"Mayu",
    "gn:population":0,
    "gn:timezone":"Asia/Shanghai",
    "iso:country":"CN",
    "name:ceb_x_preferred":[
        "Mayu"
    ],
    "name:swe_x_preferred":[
        "Mayu"
    ],
    "name:zho_x_preferred":[
        "\u9ebb\u5cea"
    ],
    "wof:name":"Mayu",
    "wof:placetype":"locality"
},
  "geometry": {"coordinates":[116.12182,39.93374],"type":"Point"}
}