{
  "type": "Feature",
  "properties": {
    "gn:admin1_code":"18.0",
    "gn:asciiname":"Longtan",
    "gn:country_code":"CN",
    "gn:dem":1289,
    "gn:feature_class":"P",
    "gn:feature_code":"PPL",
    "gn:name":"Longtan",
    "gn:population":0,
    "gn:timezone":"Asia/Shanghai",
    "iso:country":"CN",
    "name:ceb_x_preferred":[
        "Longtan"
    ],
    "name:deu_x_preferred":[
        "Longtan"
    ],
    "name:fra_x_preferred":[
        "Longtan"
    ],
    "wof:name":"Longtan",
    "wof:placetype":"locality"
},
  "geometry": {"coordinates":[105.76667,26.29444],"type":"Point"}
}