{
  "type": "Feature",
  "properties": {
    "gn:admin1_code":"24.0",
    "gn:asciiname":"Huyingou",
    "gn:country_code":"CN",
    "gn:dem":1825,
    "gn:feature_class":"P",
    "gn:feature_code":"PPL",
    "gn:name":"Huyingou",
    "gn:population":0,
    "gn:timezone":"Asia/Shanghai",
    "iso:country":"CN",
    "name:zho_x_preferred":[
        "\u62a4\u94f6\u6c9f"
    ],
    "wof:name":"Huyingou",
    "wof:placetype":"locality"
},
  "geometry": {"coordinates":[113.59981000000001,38.9657],"type":"Point"}
}