{
  "type": "Feature",
  "properties": {
    "gn:admin1_code":"32.0",
    "gn:asciiname":"Tianjingwan",
    "gn:country_code":"CN",
    "gn:dem":339,
    "gn:feature_class":"P",
    "gn:feature_code":"PPL",
    "gn:name":"Tianjingwan",
    "gn:population":0,
    "gn:timezone":"Asia/Shanghai",
    "iso:country":"CN",
    "name:zho_x_preferred":[
        "\u5929\u4e95\u6e7e"
    ],
    "wof:name":"Tianjingwan",
    "wof:placetype":"locality"
},
  "geometry": {"coordinates":[106.58393,31.09824],"type":"Point"}
}