{
  "type": "Feature",
  "properties": {
    "gn:admin1_code":"7.0",
    "gn:asciiname":"Guizhukeng",
    "gn:country_code":"CN",
    "gn:dem":467,
    "gn:feature_class":"P",
    "gn:feature_code":"PPL",
    "gn:name":"Guizhukeng",
    "gn:population":0,
    "gn:timezone":"Asia/Shanghai",
    "iso:country":"CN",
    "name:zho_x_preferred":[
        "\u6842\u7af9\u5751"
    ],
    "wof:name":"Guizhukeng",
    "wof:placetype":"locality"
},
  "geometry": {"coordinates":[116.14164,25.28424],"type":"Point"}
}