{
  "type": "Feature",
  "properties": {
    "gn:admin1_code":"1.0",
    "gn:asciiname":"Huihuangcun",
    "gn:country_code":"CN",
    "gn:dem":201,
    "gn:feature_class":"P",
    "gn:feature_code":"PPL",
    "gn:name":"Huihuangcun",
    "gn:population":0,
    "gn:timezone":"Asia/Shanghai",
    "iso:country":"CN",
    "name:zho_x_preferred":[
        "\u8f89\u714c\u6751"
    ],
    "wof:name":"Huihuangcun",
    "wof:placetype":"locality"
},
  "geometry": {"coordinates":[117.76849,29.94488],"type":"Point"}
}