{
  "type": "Feature",
  "properties": {
    "gn:admin1_code":"29.0",
    "gn:asciiname":"Shidiao",
    "gn:country_code":"CN",
    "gn:dem":2704,
    "gn:feature_class":"P",
    "gn:feature_code":"PPL",
    "gn:name":"Shidiao",
    "gn:population":0,
    "gn:timezone":"Asia/Shanghai",
    "iso:country":"CN",
    "name:und_x_variant":[
        "\u77f3\u7889"
    ],
    "wof:name":"Shidiao",
    "wof:placetype":"locality"
},
  "geometry": {"coordinates":[103.595,28.0518],"type":"Point"}
}