{
  "type": "Feature",
  "properties": {
    "gn:admin1_code":"23.0",
    "gn:asciiname":"Shanhaiqiao",
    "gn:country_code":"CN",
    "gn:dem":5,
    "gn:feature_class":"P",
    "gn:feature_code":"PPL",
    "gn:name":"Shanhaiqiao",
    "gn:population":0,
    "gn:timezone":"Asia/Shanghai",
    "iso:country":"CN",
    "name:zho_x_preferred":[
        "Shanhaiqiao"
    ],
    "name:zho_x_variant":[
        "\u5c71\u6d77\u6865"
    ],
    "wof:name":"Shanhaiqiao",
    "wof:placetype":"locality"
},
  "geometry": {"coordinates":[121.05956999999999,31.1466],"type":"Point"}
}