{
  "type": "Feature",
  "properties": {
    "gn:admin1_code":"9.0",
    "gn:asciiname":"Zhangzhuyuan",
    "gn:country_code":"CN",
    "gn:dem":79,
    "gn:feature_class":"P",
    "gn:feature_code":"PPL",
    "gn:name":"Zhangzhuyuan",
    "gn:population":0,
    "gn:timezone":"Asia/Shanghai",
    "iso:country":"CN",
    "name:und_x_variant":[
        "\u5f20\u7af9\u56ed"
    ],
    "name:zho_x_preferred":[
        "\u5f20\u7af9\u56ed"
    ],
    "wof:name":"Zhangzhuyuan",
    "wof:placetype":"locality"
},
  "geometry": {"coordinates":[113.84806,33.05494],"type":"Point"}
}