{
  "type": "Feature",
  "properties": {
    "gn:admin1_code":"8.0",
    "gn:asciiname":"Jidongcun",
    "gn:country_code":"CN",
    "gn:dem":104,
    "gn:feature_class":"P",
    "gn:feature_code":"PPL",
    "gn:name":"Jidongcun",
    "gn:population":0,
    "gn:timezone":"Asia/Shanghai",
    "iso:country":"CN",
    "name:zho_x_preferred":[
        "\u7ee7\u4e1c\u6751"
    ],
    "wof:name":"Jidongcun",
    "wof:placetype":"locality"
},
  "geometry": {"coordinates":[129.55313000000001,46.48031],"type":"Point"}
}