{
  "type": "Feature",
  "properties": {
    "gn:admin1_code":"32.0",
    "gn:asciiname":"Dahala",
    "gn:country_code":"CN",
    "gn:dem":1774,
    "gn:feature_class":"P",
    "gn:feature_code":"PPL",
    "gn:name":"Dahala",
    "gn:population":0,
    "gn:timezone":"Asia/Shanghai",
    "iso:country":"CN",
    "name:zho_x_preferred":[
        "\u5927\u54c8\u62c9"
    ],
    "wof:name":"Dahala",
    "wof:placetype":"locality"
},
  "geometry": {"coordinates":[102.31999999999999,26.4794],"type":"Point"}
}