{
  "type": "Feature",
  "properties": {
    "gn:admin1_code":"18",
    "gn:asciiname":"Shabaopu",
    "gn:cc2":"CN",
    "gn:country_code":"CN",
    "gn:dem":857,
    "gn:feature_class":"P",
    "gn:feature_code":"PPL",
    "gn:name":"Shabaopu",
    "gn:population":0,
    "gn:timezone":"Asia/Shanghai",
    "iso:country":"CN",
    "name:und_x_variant":[
        "Sha-pao-p\u2019u",
        "Shabaopu"
    ],
    "wof:name":"Shabaopu",
    "wof:placetype":"locality"
},
  "geometry": {"coordinates":[107.51667,26.33333],"type":"Point"}
}