{
  "type": "Feature",
  "properties": {
    "gn:admin1_code":"2.0",
    "gn:asciiname":"Jiejia",
    "gn:country_code":"CN",
    "gn:dem":181,
    "gn:feature_class":"P",
    "gn:feature_code":"PPL",
    "gn:name":"Jiejia",
    "gn:population":0,
    "gn:timezone":"Asia/Shanghai",
    "iso:country":"CN",
    "name:und_x_variant":[
        "\u63ed\u5bb6",
        "Jiejia"
    ],
    "wof:name":"Jiejia",
    "wof:placetype":"locality"
},
  "geometry": {"coordinates":[119.16795999999999,29.40384],"type":"Point"}
}