{
  "type": "Feature",
  "properties": {
    "gn:admin1_code":"8.0",
    "gn:asciiname":"Dufatun",
    "gn:country_code":"CN",
    "gn:dem":135,
    "gn:feature_class":"P",
    "gn:feature_code":"PPL",
    "gn:name":"Dufatun",
    "gn:population":0,
    "gn:timezone":"Asia/Shanghai",
    "iso:country":"CN",
    "name:zho_x_preferred":[
        "\u675c\u53d1\u5c6f"
    ],
    "wof:name":"Dufatun",
    "wof:placetype":"locality"
},
  "geometry": {"coordinates":[128.10058000000001,46.04087],"type":"Point"}
}