{
  "type": "Feature",
  "properties": {
    "gn:admin1_code":"29.0",
    "gn:asciiname":"Shannaobao",
    "gn:country_code":"CN",
    "gn:dem":1487,
    "gn:feature_class":"P",
    "gn:feature_code":"PPL",
    "gn:name":"Shannaobao",
    "gn:population":0,
    "gn:timezone":"Asia/Shanghai",
    "iso:country":"CN",
    "name:zho_x_preferred":[
        "\u5c71\u57b4\u5305"
    ],
    "wof:name":"Shannaobao",
    "wof:placetype":"locality"
},
  "geometry": {"coordinates":[103.926,27.5157],"type":"Point"}
}