{
  "type": "Feature",
  "properties": {
    "gn:admin1_code":"3.0",
    "gn:asciiname":"Dawuchang",
    "gn:country_code":"CN",
    "gn:dem":859,
    "gn:feature_class":"P",
    "gn:feature_code":"PPL",
    "gn:name":"Dawuchang",
    "gn:population":0,
    "gn:timezone":"Asia/Shanghai",
    "iso:country":"CN",
    "name:und_x_variant":[
        "\u5927\u5c4b\u573a"
    ],
    "wof:name":"Dawuchang",
    "wof:placetype":"locality"
},
  "geometry": {"coordinates":[115.85981,24.97642],"type":"Point"}
}