{
  "type": "Feature",
  "properties": {
    "gn:admin1_code":"15.0",
    "gn:asciiname":"Yinpo",
    "gn:country_code":"CN",
    "gn:dem":1120,
    "gn:feature_class":"P",
    "gn:feature_code":"PPL",
    "gn:name":"Yinpo",
    "gn:population":0,
    "gn:timezone":"Asia/Shanghai",
    "iso:country":"CN",
    "name:und_x_variant":[
        "\u9634\u5761"
    ],
    "wof:name":"Yinpo",
    "wof:placetype":"locality"
},
  "geometry": {"coordinates":[105.78811,33.6946],"type":"Point"}
}