{
  "type": "Feature",
  "properties": {
    "gn:admin1_code":"19.0",
    "gn:asciiname":"Xin'ancun",
    "gn:country_code":"CN",
    "gn:dem":5,
    "gn:feature_class":"P",
    "gn:feature_code":"PPL",
    "gn:name":"Xin\u2019ancun",
    "gn:population":0,
    "gn:timezone":"Asia/Shanghai",
    "iso:country":"CN",
    "name:und_x_variant":[
        "Xin\u2019ancun"
    ],
    "name:zho_x_preferred":[
        "\u65b0\u5b89\u6751"
    ],
    "wof:name":"Xin'ancun",
    "wof:placetype":"locality"
},
  "geometry": {"coordinates":[124.20843000000001,39.95017],"type":"Point"}
}