{
  "type": "Feature",
  "properties": {
    "gn:admin1_code":"25.0",
    "gn:asciiname":"Caogezhuang",
    "gn:country_code":"CN",
    "gn:dem":20,
    "gn:feature_class":"P",
    "gn:feature_code":"PPL",
    "gn:name":"Caogezhuang",
    "gn:population":0,
    "gn:timezone":"Asia/Shanghai",
    "iso:country":"CN",
    "name:zho_x_preferred":[
        "\u66f9\u6208\u5e84"
    ],
    "wof:name":"Caogezhuang",
    "wof:placetype":"locality"
},
  "geometry": {"coordinates":[119.53654,36.55911],"type":"Point"}
}