{
  "type": "Feature",
  "properties": {
    "gn:admin1_code":"16.0",
    "gn:asciiname":"Xinning",
    "gn:country_code":"CN",
    "gn:dem":86,
    "gn:feature_class":"P",
    "gn:feature_code":"PPL",
    "gn:name":"Xinning",
    "gn:population":0,
    "gn:timezone":"Asia/Shanghai",
    "iso:country":"CN",
    "name:deu_x_preferred":[
        "Xinning"
    ],
    "name:zho_x_preferred":[
        "\u65b0\u5b81"
    ],
    "wof:name":"Xinning",
    "wof:placetype":"locality"
},
  "geometry": {"coordinates":[109.051,22.9419],"type":"Point"}
}