{
  "type": "Feature",
  "properties": {
    "gn:admin1_code":"19.0",
    "gn:asciiname":"Yuanjia Buzi",
    "gn:country_code":"CN",
    "gn:dem":401,
    "gn:feature_class":"P",
    "gn:feature_code":"PPL",
    "gn:name":"Yuanjia Buzi",
    "gn:population":0,
    "gn:timezone":"Asia/Shanghai",
    "iso:country":"CN",
    "name:und_x_variant":[
        "Yuanjia Puzi",
        "Yuanjia Buzi"
    ],
    "name:zho_x_preferred":[
        "\u82d1\u5bb6\u5821\u5b50"
    ],
    "wof:name":"Yuanjia Buzi",
    "wof:placetype":"locality"
},
  "geometry": {"coordinates":[124.00192,41.09479],"type":"Point"}
}