{
  "type": "Feature",
  "properties": {
    "gn:admin1_code":"32.0",
    "gn:asciiname":"Changlinpan",
    "gn:country_code":"CN",
    "gn:dem":668,
    "gn:feature_class":"P",
    "gn:feature_code":"PPL",
    "gn:name":"Changlinpan",
    "gn:population":0,
    "gn:timezone":"Asia/Shanghai",
    "iso:country":"CN",
    "name:zho_x_preferred":[
        "\u957f\u6797\u7554"
    ],
    "wof:name":"Changlinpan",
    "wof:placetype":"locality"
},
  "geometry": {"coordinates":[103.721,31.032],"type":"Point"}
}