{
  "type": "Feature",
  "properties": {
    "gn:admin1_code":"9.0",
    "gn:asciiname":"Dazhouwa",
    "gn:country_code":"CN",
    "gn:dem":190,
    "gn:feature_class":"P",
    "gn:feature_code":"PPL",
    "gn:name":"Dazhouwa",
    "gn:population":0,
    "gn:timezone":"Asia/Shanghai",
    "iso:country":"CN",
    "name:zho_x_preferred":[
        "\u5927\u5468\u6d3c"
    ],
    "wof:name":"Dazhouwa",
    "wof:placetype":"locality"
},
  "geometry": {"coordinates":[111.9756,33.02977],"type":"Point"}
}