{
  "type": "Feature",
  "properties": {
    "gn:admin1_code":"24",
    "gn:asciiname":"Liuquan",
    "gn:cc2":"CN",
    "gn:country_code":"CN",
    "gn:dem":1345,
    "gn:feature_class":"P",
    "gn:feature_code":"PPL",
    "gn:name":"Liuquan",
    "gn:population":0,
    "gn:timezone":"Asia/Shanghai",
    "iso:country":"CN",
    "name:und_x_variant":[
        "Liu-ch\u2019\u00fcan-ts\u2019un",
        "Liu-ch\u2019\u00fcan",
        "Liuquan"
    ],
    "wof:name":"Liuquan",
    "wof:placetype":"locality"
},
  "geometry": {"coordinates":[113.44167,35.795],"type":"Point"}
}