{
  "type": "Feature",
  "properties": {
    "gn:admin1_code":"3.0",
    "gn:asciiname":"Guanzhuan",
    "gn:country_code":"CN",
    "gn:dem":310,
    "gn:feature_class":"P",
    "gn:feature_code":"PPL",
    "gn:name":"Guanzhuan",
    "gn:population":0,
    "gn:timezone":"Asia/Shanghai",
    "iso:country":"CN",
    "name:und_x_variant":[
        "\u5b98\u7816"
    ],
    "wof:name":"Guanzhuan",
    "wof:placetype":"locality"
},
  "geometry": {"coordinates":[116.62775999999999,26.95182],"type":"Point"}
}