{
  "type": "Feature",
  "properties": {
    "gn:admin1_code":"5.0",
    "gn:asciiname":"Xihuanzidong",
    "gn:country_code":"CN",
    "gn:dem":237,
    "gn:feature_class":"P",
    "gn:feature_code":"PPL",
    "gn:name":"Xihuanzidong",
    "gn:population":0,
    "gn:timezone":"Asia/Shanghai",
    "iso:country":"CN",
    "name:zho_x_preferred":[
        "\u897f\u737e\u5b50\u6d1e"
    ],
    "wof:name":"Xihuanzidong",
    "wof:placetype":"locality"
},
  "geometry": {"coordinates":[124.58734,44.11367],"type":"Point"}
}