{
  "type": "Feature",
  "properties": {
    "gn:admin1_code":"15.0",
    "gn:asciiname":"Taojia Xianzi",
    "gn:country_code":"CN",
    "gn:dem":2007,
    "gn:feature_class":"P",
    "gn:feature_code":"PPL",
    "gn:name":"Taojia Xianzi",
    "gn:population":0,
    "gn:timezone":"Asia/Shanghai",
    "iso:country":"CN",
    "name:zho_x_preferred":[
        "\u9676\u5bb6\u5c98\u5b50"
    ],
    "wof:name":"Taojia Xianzi",
    "wof:placetype":"locality"
},
  "geometry": {"coordinates":[104.771,36.2117],"type":"Point"}
}