{
  "type": "Feature",
  "properties": {
    "gn:admin1_code":"24.0",
    "gn:asciiname":"Qiangjiayingcun",
    "gn:country_code":"CN",
    "gn:dem":989,
    "gn:feature_class":"P",
    "gn:feature_code":"PPL",
    "gn:name":"Qiangjiayingcun",
    "gn:population":0,
    "gn:timezone":"Asia/Shanghai",
    "iso:country":"CN",
    "name:zho_x_preferred":[
        "\u5f3a\u5bb6\u8425\u6751"
    ],
    "wof:name":"Qiangjiayingcun",
    "wof:placetype":"locality"
},
  "geometry": {"coordinates":[114.00606999999999,40.11139],"type":"Point"}
}