{
  "type": "Feature",
  "properties": {
    "gn:admin1_code":"19.0",
    "gn:asciiname":"Tianqiaoshancun",
    "gn:country_code":"CN",
    "gn:dem":212,
    "gn:feature_class":"P",
    "gn:feature_code":"PPL",
    "gn:name":"Tianqiaoshancun",
    "gn:population":0,
    "gn:timezone":"Asia/Shanghai",
    "iso:country":"CN",
    "name:zho_x_preferred":[
        "\u5929\u6865\u5c71\u6751"
    ],
    "wof:name":"Tianqiaoshancun",
    "wof:placetype":"locality"
},
  "geometry": {"coordinates":[124.17700000000001,42.737],"type":"Point"}
}