{
  "type": "Feature",
  "properties": {
    "gn:admin1_code":"4.0",
    "gn:asciiname":"Zhaozhuang",
    "gn:country_code":"CN",
    "gn:dem":3,
    "gn:feature_class":"P",
    "gn:feature_code":"PPL",
    "gn:name":"Zhaozhuang",
    "gn:population":0,
    "gn:timezone":"Asia/Shanghai",
    "iso:country":"CN",
    "name:zho_x_preferred":[
        "Zhaozhuang"
    ],
    "name:zho_x_variant":[
        "\u8d75\u5e84"
    ],
    "wof:name":"Zhaozhuang",
    "wof:placetype":"locality"
},
  "geometry": {"coordinates":[119.16124000000001,34.36419],"type":"Point"}
}