{
  "type": "Feature",
  "properties": {
    "gn:admin1_code":"19.0",
    "gn:asciiname":"Wujialing",
    "gn:country_code":"CN",
    "gn:dem":137,
    "gn:feature_class":"P",
    "gn:feature_code":"PPL",
    "gn:name":"Wujialing",
    "gn:population":0,
    "gn:timezone":"Asia/Shanghai",
    "iso:country":"CN",
    "name:und_x_variant":[
        "\u5434\u5bb6\u5cad"
    ],
    "wof:name":"Wujialing",
    "wof:placetype":"locality"
},
  "geometry": {"coordinates":[123.85223999999999,40.42154],"type":"Point"}
}