{
  "type": "Feature",
  "properties": {
    "gn:admin1_code":"3.0",
    "gn:asciiname":"Qurandian",
    "gn:country_code":"CN",
    "gn:dem":30,
    "gn:feature_class":"P",
    "gn:feature_code":"PPL",
    "gn:name":"Qurandian",
    "gn:population":0,
    "gn:timezone":"Asia/Shanghai",
    "iso:country":"CN",
    "name:und_x_variant":[
        "\u5c48\u67d3\u5e97"
    ],
    "wof:name":"Qurandian",
    "wof:placetype":"locality"
},
  "geometry": {"coordinates":[116.20573,29.58478],"type":"Point"}
}