{
  "type": "Feature",
  "properties": {
    "gn:admin1_code":"12.0",
    "gn:asciiname":"Yuanjia Zhuangzi",
    "gn:country_code":"CN",
    "gn:dem":914,
    "gn:feature_class":"P",
    "gn:feature_code":"PPL",
    "gn:name":"Yuanjia Zhuangzi",
    "gn:population":0,
    "gn:timezone":"Asia/Shanghai",
    "iso:country":"CN",
    "name:zho_x_preferred":[
        "\u8881\u5bb6\u5e84\u5b50"
    ],
    "wof:name":"Yuanjia Zhuangzi",
    "wof:placetype":"locality"
},
  "geometry": {"coordinates":[111.58334000000001,31.69341],"type":"Point"}
}