{
  "type": "Feature",
  "properties": {
    "gn:admin1_code":"29.0",
    "gn:asciiname":"Xiabanghai",
    "gn:country_code":"CN",
    "gn:dem":1473,
    "gn:feature_class":"P",
    "gn:feature_code":"PPL",
    "gn:name":"Xiabanghai",
    "gn:population":0,
    "gn:timezone":"Asia/Shanghai",
    "iso:country":"CN",
    "name:zho_x_preferred":[
        "\u4e0b\u90a6\u6d77"
    ],
    "wof:name":"Xiabanghai",
    "wof:placetype":"locality"
},
  "geometry": {"coordinates":[100.108,24.1707],"type":"Point"}
}