{
  "type": "Feature",
  "properties": {
    "gn:admin1_code":"12.0",
    "gn:asciiname":"Zijingpo",
    "gn:country_code":"CN",
    "gn:dem":874,
    "gn:feature_class":"P",
    "gn:feature_code":"PPL",
    "gn:name":"Zijingpo",
    "gn:population":0,
    "gn:timezone":"Asia/Shanghai",
    "iso:country":"CN",
    "name:zho_x_preferred":[
        "\u7d2b\u8346\u5761"
    ],
    "wof:name":"Zijingpo",
    "wof:placetype":"locality"
},
  "geometry": {"coordinates":[111.57677,31.52173],"type":"Point"}
}