{
  "type": "Feature",
  "properties": {
    "gn:admin1_code":"19.0",
    "gn:asciiname":"Linchang",
    "gn:country_code":"CN",
    "gn:dem":320,
    "gn:feature_class":"P",
    "gn:feature_code":"PPLF",
    "gn:name":"Linchang",
    "gn:population":0,
    "gn:timezone":"Asia/Shanghai",
    "iso:country":"CN",
    "name:zho_x_preferred":[
        "\u6797\u573a"
    ],
    "wof:name":"Linchang",
    "wof:placetype":"locality"
},
  "geometry": {"coordinates":[119.90716999999999,40.29736],"type":"Point"}
}