{
  "type": "Feature",
  "properties": {
    "gn:admin1_code":"15.0",
    "gn:asciiname":"Songjiatai",
    "gn:country_code":"CN",
    "gn:dem":2262,
    "gn:feature_class":"P",
    "gn:feature_code":"PPL",
    "gn:name":"Songjiatai",
    "gn:population":0,
    "gn:timezone":"Asia/Shanghai",
    "iso:country":"CN",
    "name:zho_x_preferred":[
        "\u5b8b\u5bb6\u53f0"
    ],
    "wof:name":"Songjiatai",
    "wof:placetype":"locality"
},
  "geometry": {"coordinates":[101.045,38.49],"type":"Point"}
}