{
  "type": "Feature",
  "properties": {
    "gn:admin1_code":"26.0",
    "gn:asciiname":"Chengguan",
    "gn:country_code":"CN",
    "gn:dem":759,
    "gn:feature_class":"P",
    "gn:feature_code":"PPL",
    "gn:name":"Chengguan",
    "gn:population":0,
    "gn:timezone":"Asia/Shanghai",
    "iso:country":"CN",
    "name:ceb_x_preferred":[
        "Chengguan"
    ],
    "name:deu_x_preferred":[
        "Chengguan"
    ],
    "name:fra_x_preferred":[
        "Chengguan"
    ],
    "name:jpn_x_preferred":[
        "\u57ce\u95a2\u533a"
    ],
    "name:kor_x_preferred":[
        "\uccad\uad00\uad6c"
    ],
    "name:nld_x_preferred":[
        "Chengguan"
    ],
    "name:nor_x_preferred":[
        "Chengguan"
    ],
    "name:rus_x_preferred":[
        "\u0427\u044d\u043d\u0433\u0443\u0430\u043d\u044c"
    ],
    "name:swe_x_preferred":[
        "Chengguan"
    ],
    "name:zho_x_preferred":[
        "\u57ce\u5173"
    ],
    "name:zho_x_variant":[
        "\u57ce\u5173\u533a"
    ],
    "wof:name":"Chengguan",
    "wof:placetype":"locality"
},
  "geometry": {"coordinates":[110.38986,33.24702],"type":"Point"}
}