{
  "type": "Feature",
  "properties": {
    "gn:admin1_code":"4.0",
    "gn:asciiname":"Zhengyang Erzu",
    "gn:country_code":"CN",
    "gn:dem":2,
    "gn:feature_class":"P",
    "gn:feature_code":"PPLF",
    "gn:name":"Zhengyang Erzu",
    "gn:population":0,
    "gn:timezone":"Asia/Shanghai",
    "iso:country":"CN",
    "name:zho_x_preferred":[
        "\u6b63\u6d0b\u4e8c\u7ec4"
    ],
    "wof:name":"Zhengyang Erzu",
    "wof:placetype":"locality"
},
  "geometry": {"coordinates":[120.32599999999999,33.4383],"type":"Point"}
}