{
  "type": "Feature",
  "properties": {
    "gn:admin1_code":"5.0",
    "gn:asciiname":"Yumuqiaozi",
    "gn:country_code":"CN",
    "gn:dem":571,
    "gn:feature_class":"P",
    "gn:feature_code":"PPL",
    "gn:name":"Yumuqiaozi",
    "gn:population":0,
    "gn:timezone":"Asia/Shanghai",
    "iso:country":"CN",
    "name:und_x_variant":[
        "\u6986\u6728\u6865\u5b50"
    ],
    "wof:name":"Yumuqiaozi",
    "wof:placetype":"locality"
},
  "geometry": {"coordinates":[126.60329,41.94106],"type":"Point"}
}