{
  "type": "Feature",
  "properties": {
    "gn:admin1_code":"24.0",
    "gn:asciiname":"Laoshusi",
    "gn:country_code":"CN",
    "gn:dem":1620,
    "gn:feature_class":"P",
    "gn:feature_code":"PPL",
    "gn:name":"Laoshusi",
    "gn:population":0,
    "gn:timezone":"Asia/Shanghai",
    "iso:country":"CN",
    "name:zho_x_preferred":[
        "\u8001\u4e66\u5bfa"
    ],
    "wof:name":"Laoshusi",
    "wof:placetype":"locality"
},
  "geometry": {"coordinates":[112.18856,38.09487],"type":"Point"}
}