{
  "type": "Feature",
  "properties": {
    "gn:admin1_code":"11.0",
    "gn:asciiname":"Shoutuan",
    "gn:country_code":"CN",
    "gn:dem":164,
    "gn:feature_class":"P",
    "gn:feature_code":"PPL",
    "gn:name":"Shoutuan",
    "gn:population":0,
    "gn:timezone":"Asia/Shanghai",
    "iso:country":"CN",
    "name:zho_x_preferred":[
        "\u9996\u56e2"
    ],
    "wof:name":"Shoutuan",
    "wof:placetype":"locality"
},
  "geometry": {"coordinates":[113.58792,26.94672000000001],"type":"Point"}
}