{
  "type": "Feature",
  "properties": {
    "gn:admin1_code":"33.0",
    "gn:asciiname":"Dongyue",
    "gn:country_code":"CN",
    "gn:dem":243,
    "gn:feature_class":"P",
    "gn:feature_code":"PPL",
    "gn:name":"Dongyue",
    "gn:population":0,
    "gn:timezone":"Asia/Shanghai",
    "iso:country":"CN",
    "name:zho_x_preferred":[
        "\u4e1c\u5cb3"
    ],
    "wof:name":"Dongyue",
    "wof:placetype":"locality"
},
  "geometry": {"coordinates":[108.57028,31.38394000000001],"type":"Point"}
}