{
  "type": "Feature",
  "properties": {
    "gn:admin1_code":"18",
    "gn:asciiname":"Banna",
    "gn:country_code":"CN",
    "gn:dem":1029,
    "gn:feature_class":"P",
    "gn:feature_code":"PPL",
    "gn:name":"Banna",
    "gn:population":0,
    "gn:timezone":"Asia/Shanghai",
    "iso:country":"CN",
    "name:ceb_x_preferred":[
        "Banna"
    ],
    "name:deu_x_preferred":[
        "Banna"
    ],
    "name:fra_x_preferred":[
        "Banna"
    ],
    "name:ita_x_preferred":[
        "Banna"
    ],
    "name:swe_x_preferred":[
        "Banna"
    ],
    "name:zho_x_preferred":[
        "\u677f\u7eb3"
    ],
    "wof:name":"Banna",
    "wof:placetype":"locality"
},
  "geometry": {"coordinates":[105.71599999999999,24.9921],"type":"Point"}
}