{
  "type": "Feature",
  "properties": {
    "gn:admin1_code":"1.0",
    "gn:asciiname":"Caizhucun",
    "gn:country_code":"CN",
    "gn:dem":28,
    "gn:feature_class":"P",
    "gn:feature_code":"PPL",
    "gn:name":"Caizhucun",
    "gn:population":0,
    "gn:timezone":"Asia/Shanghai",
    "iso:country":"CN",
    "name:zho_x_preferred":[
        "\u8521\u6731\u6751"
    ],
    "wof:name":"Caizhucun",
    "wof:placetype":"locality"
},
  "geometry": {"coordinates":[116.31426999999999,32.75976],"type":"Point"}
}