{
  "type": "Feature",
  "properties": {
    "gn:admin1_code":"4.0",
    "gn:asciiname":"Erhecun",
    "gn:country_code":"CN",
    "gn:dem":15,
    "gn:feature_class":"P",
    "gn:feature_code":"PPL",
    "gn:name":"Erhecun",
    "gn:population":0,
    "gn:timezone":"Asia/Shanghai",
    "iso:country":"CN",
    "name:zho_x_preferred":[
        "\u4e8c\u6cb3\u6751"
    ],
    "wof:name":"Erhecun",
    "wof:placetype":"locality"
},
  "geometry": {"coordinates":[118.38531999999999,33.24988],"type":"Point"}
}