{
  "type": "Feature",
  "properties": {
    "gn:admin1_code":"3.0",
    "gn:asciiname":"Tujia Wuchang",
    "gn:country_code":"CN",
    "gn:dem":487,
    "gn:feature_class":"P",
    "gn:feature_code":"PPL",
    "gn:name":"Tujia Wuchang",
    "gn:population":0,
    "gn:timezone":"Asia/Shanghai",
    "iso:country":"CN",
    "name:und_x_variant":[
        "\u6d82\u5bb6\u5c4b\u573a"
    ],
    "wof:name":"Tujia Wuchang",
    "wof:placetype":"locality"
},
  "geometry": {"coordinates":[115.12136,28.94498],"type":"Point"}
}