{
  "type": "Feature",
  "properties": {
    "gn:admin1_code":"1.0",
    "gn:asciiname":"Nanyingcun",
    "gn:country_code":"CN",
    "gn:dem":50,
    "gn:feature_class":"P",
    "gn:feature_code":"PPL",
    "gn:name":"Nanyingcun",
    "gn:population":0,
    "gn:timezone":"Asia/Shanghai",
    "iso:country":"CN",
    "name:zho_x_preferred":[
        "\u5357\u90e2\u6751"
    ],
    "wof:name":"Nanyingcun",
    "wof:placetype":"locality"
},
  "geometry": {"coordinates":[117.21838,32.17896],"type":"Point"}
}