{
  "type": "Feature",
  "properties": {
    "gn:admin1_code":"30.0",
    "gn:asciiname":"Chelu",
    "gn:country_code":"CN",
    "gn:dem":318,
    "gn:feature_class":"P",
    "gn:feature_code":"PPL",
    "gn:name":"Chelu",
    "gn:population":0,
    "gn:timezone":"Asia/Shanghai",
    "iso:country":"CN",
    "name:zho_x_preferred":[
        "Chelu"
    ],
    "name:zho_x_variant":[
        "\u8f66\u8def"
    ],
    "wof:name":"Chelu",
    "wof:placetype":"locality"
},
  "geometry": {"coordinates":[112.63388999999999,24.42528],"type":"Point"}
}