{
  "type": "Feature",
  "properties": {
    "gn:admin1_code":"33.0",
    "gn:asciiname":"Zhenzhu",
    "gn:country_code":"CN",
    "gn:dem":716,
    "gn:feature_class":"P",
    "gn:feature_code":"PPL",
    "gn:name":"Zhenzhu",
    "gn:population":0,
    "gn:timezone":"Asia/Shanghai",
    "iso:country":"CN",
    "name:zho_x_preferred":[
        "\u73cd\u73e0"
    ],
    "wof:name":"Zhenzhu",
    "wof:placetype":"locality"
},
  "geometry": {"coordinates":[108.50368,29.24466],"type":"Point"}
}