{
  "type": "Feature",
  "properties": {
    "gn:admin1_code":"9.0",
    "gn:asciiname":"Hongzhuang",
    "gn:country_code":"CN",
    "gn:dem":97,
    "gn:feature_class":"P",
    "gn:feature_code":"PPL",
    "gn:name":"Hongzhuang",
    "gn:population":0,
    "gn:timezone":"Asia/Shanghai",
    "iso:country":"CN",
    "name:zho_x_preferred":[
        "\u6d2a\u5e84"
    ],
    "wof:name":"Hongzhuang",
    "wof:placetype":"locality"
},
  "geometry": {"coordinates":[113.63266000000002,34.98278],"type":"Point"}
}