{
  "type": "Feature",
  "properties": {
    "gn:admin1_code":"3",
    "gn:asciiname":"Wuxi",
    "gn:country_code":"CN",
    "gn:dem":65,
    "gn:feature_class":"P",
    "gn:feature_code":"PPL",
    "gn:name":"Wuxi",
    "gn:population":0,
    "gn:timezone":"Asia/Shanghai",
    "iso:country":"CN",
    "name:zho_x_preferred":[
        "\u6b66\u6eaa"
    ],
    "wof:name":"Wuxi",
    "wof:placetype":"locality"
},
  "geometry": {"coordinates":[114.81319000000001,26.77035],"type":"Point"}
}