{
  "type": "Feature",
  "properties": {
    "gn:admin1_code":"19.0",
    "gn:asciiname":"Zhaowopeng",
    "gn:country_code":"CN",
    "gn:dem":62,
    "gn:feature_class":"P",
    "gn:feature_code":"PPL",
    "gn:name":"Zhaowopeng",
    "gn:population":0,
    "gn:timezone":"Asia/Shanghai",
    "iso:country":"CN",
    "name:zho_x_preferred":[
        "\u8d75\u7a9d\u68da"
    ],
    "wof:name":"Zhaowopeng",
    "wof:placetype":"locality"
},
  "geometry": {"coordinates":[121.994,39.7015],"type":"Point"}
}