{
  "type": "Feature",
  "properties": {
    "gn:admin1_code":"4.0",
    "gn:asciiname":"Zhuyingxi",
    "gn:country_code":"CN",
    "gn:dem":8,
    "gn:feature_class":"P",
    "gn:feature_code":"PPL",
    "gn:name":"Zhuyingxi",
    "gn:population":0,
    "gn:timezone":"Asia/Shanghai",
    "iso:country":"CN",
    "name:zho_x_preferred":[
        "\u6731\u8425\u897f"
    ],
    "wof:name":"Zhuyingxi",
    "wof:placetype":"locality"
},
  "geometry": {"coordinates":[119.25669000000001,32.33683],"type":"Point"}
}