{
  "type": "Feature",
  "properties": {
    "gn:admin1_code":"25",
    "gn:asciiname":"Huangheya",
    "gn:cc2":"CN",
    "gn:country_code":"CN",
    "gn:dem":26,
    "gn:feature_class":"P",
    "gn:feature_code":"PPL",
    "gn:name":"Huangheya",
    "gn:population":0,
    "gn:timezone":"Asia/Shanghai",
    "iso:country":"CN",
    "name:und_x_variant":[
        "Huang-ho-yai",
        "Huanghoya",
        "Huangheya"
    ],
    "wof:name":"Huangheya",
    "wof:placetype":"locality"
},
  "geometry": {"coordinates":[116.33333,37.35],"type":"Point"}
}