{
  "type": "Feature",
  "properties": {
    "gn:admin1_code":"7.0",
    "gn:asciiname":"Xiaoqiancun",
    "gn:country_code":"CN",
    "gn:dem":822,
    "gn:feature_class":"P",
    "gn:feature_code":"PPL",
    "gn:name":"Xiaoqiancun",
    "gn:population":0,
    "gn:timezone":"Asia/Shanghai",
    "iso:country":"CN",
    "name:und_x_variant":[
        "\u5c0f\u524d\u6751"
    ],
    "name:zho_x_preferred":[
        "\u5c0f\u524d\u6751"
    ],
    "wof:name":"Xiaoqiancun",
    "wof:placetype":"locality"
},
  "geometry": {"coordinates":[117.67045,26.20101],"type":"Point"}
}