{
  "type": "Feature",
  "properties": {
    "gn:admin1_code":"4.0",
    "gn:asciiname":"Majiadun",
    "gn:country_code":"CN",
    "gn:dem":2,
    "gn:feature_class":"P",
    "gn:feature_code":"PPL",
    "gn:name":"Majiadun",
    "gn:population":0,
    "gn:timezone":"Asia/Shanghai",
    "iso:country":"CN",
    "name:zho_x_preferred":[
        "\u9a6c\u5bb6\u58a9"
    ],
    "wof:name":"Majiadun",
    "wof:placetype":"locality"
},
  "geometry": {"coordinates":[119.53283,33.25411],"type":"Point"}
}