{
  "type": "Feature",
  "properties": {
    "gn:admin1_code":"26.0",
    "gn:asciiname":"Liyayaocun",
    "gn:country_code":"CN",
    "gn:dem":1289,
    "gn:feature_class":"P",
    "gn:feature_code":"PPL",
    "gn:name":"Liyayaocun",
    "gn:population":0,
    "gn:timezone":"Asia/Shanghai",
    "iso:country":"CN",
    "name:zho_x_preferred":[
        "\u674e\u5d16\u7a91\u6751"
    ],
    "wof:name":"Liyayaocun",
    "wof:placetype":"locality"
},
  "geometry": {"coordinates":[109.44253999999999,37.00948],"type":"Point"}
}