{
  "type": "Feature",
  "properties": {
    "gn:admin1_code":"03",
    "gn:asciiname":"Heshi",
    "gn:country_code":"CN",
    "gn:dem":49,
    "gn:feature_class":"P",
    "gn:feature_code":"PPLA4",
    "gn:name":"Heshi",
    "gn:population":0,
    "gn:timezone":"Asia/Shanghai",
    "iso:country":"CN",
    "name:und_x_variant":[
        "\u5408\u5e02",
        "Heshi Zhen",
        "\u5408\u5e02\u9547"
    ],
    "wof:name":"Heshi",
    "wof:placetype":"locality"
},
  "geometry": {"coordinates":[116.65039,28.02002],"type":"Point"}
}