{
  "type": "Feature",
  "properties": {
    "gn:admin1_code":"31",
    "gn:asciiname":"Lintian",
    "gn:country_code":"CN",
    "gn:dem":175,
    "gn:feature_class":"P",
    "gn:feature_code":"PPL",
    "gn:name":"Lintian",
    "gn:population":0,
    "gn:timezone":"Asia/Shanghai",
    "iso:country":"CN",
    "name:und_x_variant":[
        "\u6797\u7530",
        "Lintian Nongchang"
    ],
    "name:zho_x_preferred":[
        "\u6797\u7530\u519c\u573a"
    ],
    "wof:name":"Lintian",
    "wof:placetype":"locality"
},
  "geometry": {"coordinates":[109.953,18.9241],"type":"Point"}
}