{
  "type": "Feature",
  "properties": {
    "gn:admin1_code":"12.0",
    "gn:asciiname":"Lijiaxinchang",
    "gn:country_code":"CN",
    "gn:dem":28,
    "gn:feature_class":"P",
    "gn:feature_code":"PPL",
    "gn:name":"Lijiaxinchang",
    "gn:population":0,
    "gn:timezone":"Asia/Shanghai",
    "iso:country":"CN",
    "name:zho_x_preferred":[
        "Lijiaxinchang"
    ],
    "name:zho_x_variant":[
        "\u674e\u5bb6\u65b0\u573a"
    ],
    "wof:name":"Lijiaxinchang",
    "wof:placetype":"locality"
},
  "geometry": {"coordinates":[112.91571,30.00396],"type":"Point"}
}