{
  "type": "Feature",
  "properties": {
    "gn:admin1_code":"32.0",
    "gn:asciiname":"Zi'eryizu",
    "gn:country_code":"CN",
    "gn:dem":2175,
    "gn:feature_class":"P",
    "gn:feature_code":"PPL",
    "gn:name":"Zi\u2019eryizu",
    "gn:population":0,
    "gn:timezone":"Asia/Shanghai",
    "iso:country":"CN",
    "name:zho_x_preferred":[
        "\u5b50\u8033\u5f5d\u65cf"
    ],
    "name:zho_x_variant":[
        "Zi\u2019eryizu"
    ],
    "wof:name":"Zi'eryizu",
    "wof:placetype":"locality"
},
  "geometry": {"coordinates":[101.61821999999999,28.38619000000001],"type":"Point"}
}