{
  "type": "Feature",
  "properties": {
    "gn:admin1_code":"1.0",
    "gn:asciiname":"Qimiaocun",
    "gn:country_code":"CN",
    "gn:dem":25,
    "gn:feature_class":"P",
    "gn:feature_code":"PPL",
    "gn:name":"Qimiaocun",
    "gn:population":0,
    "gn:timezone":"Asia/Shanghai",
    "iso:country":"CN",
    "name:zho_x_preferred":[
        "\u9f50\u5e99\u6751"
    ],
    "wof:name":"Qimiaocun",
    "wof:placetype":"locality"
},
  "geometry": {"coordinates":[116.71886000000001,32.99121],"type":"Point"}
}