{
  "type": "Feature",
  "properties": {
    "gn:admin1_code":"4.0",
    "gn:asciiname":"Baiyang",
    "gn:country_code":"CN",
    "gn:dem":27,
    "gn:feature_class":"P",
    "gn:feature_code":"PPL",
    "gn:name":"Baiyang",
    "gn:population":0,
    "gn:timezone":"Asia/Shanghai",
    "iso:country":"CN",
    "name:zho_x_preferred":[
        "\u767d\u7f8a"
    ],
    "wof:name":"Baiyang",
    "wof:placetype":"locality"
},
  "geometry": {"coordinates":[119.25064999999999,32.39479],"type":"Point"}
}