{
  "type": "Feature",
  "properties": {
    "gn:admin1_code":"32.0",
    "gn:asciiname":"Fanjiawan",
    "gn:country_code":"CN",
    "gn:dem":817,
    "gn:feature_class":"P",
    "gn:feature_code":"PPL",
    "gn:name":"Fanjiawan",
    "gn:population":0,
    "gn:timezone":"Asia/Shanghai",
    "iso:country":"CN",
    "name:zho_x_preferred":[
        "\u8303\u5bb6\u6e7e"
    ],
    "name:zho_x_variant":[
        "\u8303\u5bb6\u5f2f"
    ],
    "wof:name":"Fanjiawan",
    "wof:placetype":"locality"
},
  "geometry": {"coordinates":[107.76900000000001,32.2891],"type":"Point"}
}