{
  "type": "Feature",
  "properties": {
    "gn:admin1_code":"11.0",
    "gn:asciiname":"Huaqiao Yangjia",
    "gn:country_code":"CN",
    "gn:dem":265,
    "gn:feature_class":"P",
    "gn:feature_code":"PPL",
    "gn:name":"Huaqiao Yangjia",
    "gn:population":0,
    "gn:timezone":"Asia/Shanghai",
    "iso:country":"CN",
    "name:zho_x_preferred":[
        "\u82b1\u6865\u6768\u5bb6"
    ],
    "wof:name":"Huaqiao Yangjia",
    "wof:placetype":"locality"
},
  "geometry": {"coordinates":[109.90864000000001,27.63705],"type":"Point"}
}