{
  "type": "Feature",
  "properties": {
    "gn:admin1_code":"19.0",
    "gn:asciiname":"Chengjia Wobu",
    "gn:country_code":"CN",
    "gn:dem":89,
    "gn:feature_class":"P",
    "gn:feature_code":"PPL",
    "gn:name":"Chengjia Wobu",
    "gn:population":0,
    "gn:timezone":"Asia/Shanghai",
    "iso:country":"CN",
    "name:und_x_variant":[
        "Chengjiawobao",
        "Chengjia Wobu"
    ],
    "name:zho_x_preferred":[
        "\u7a0b\u5bb6\u7a9d\u5821"
    ],
    "wof:name":"Chengjia Wobu",
    "wof:placetype":"locality"
},
  "geometry": {"coordinates":[123.73,42.9233],"type":"Point"}
}