{
  "type": "Feature",
  "properties": {
    "gn:admin1_code":"1.0",
    "gn:asciiname":"Tongxincun",
    "gn:country_code":"CN",
    "gn:dem":37,
    "gn:feature_class":"P",
    "gn:feature_code":"PPL",
    "gn:name":"Tongxincun",
    "gn:population":0,
    "gn:timezone":"Asia/Shanghai",
    "iso:country":"CN",
    "name:zho_x_preferred":[
        "\u540c\u5fc3\u6751"
    ],
    "wof:name":"Tongxincun",
    "wof:placetype":"locality"
},
  "geometry": {"coordinates":[115.68743000000001,33.35749000000001],"type":"Point"}
}