{
  "type": "Feature",
  "properties": {
    "gn:admin1_code":"29.0",
    "gn:asciiname":"Dafagu",
    "gn:country_code":"CN",
    "gn:dem":1901,
    "gn:feature_class":"P",
    "gn:feature_code":"PPL",
    "gn:name":"Dafagu",
    "gn:population":0,
    "gn:timezone":"Asia/Shanghai",
    "iso:country":"CN",
    "name:zho_x_preferred":[
        "\u5927\u6cd5\u53e4"
    ],
    "wof:name":"Dafagu",
    "wof:placetype":"locality"
},
  "geometry": {"coordinates":[103.30200000000001,25.566],"type":"Point"}
}