{
  "type": "Feature",
  "properties": {
    "gn:admin1_code":"25",
    "gn:asciiname":"Zhongxin'an",
    "gn:country_code":"CN",
    "gn:dem":8,
    "gn:feature_class":"P",
    "gn:feature_code":"PPL",
    "gn:name":"Zhongxin\u2019an",
    "gn:population":0,
    "gn:timezone":"Asia/Shanghai",
    "iso:country":"CN",
    "name:und_x_variant":[
        "Zhongxin\u2019an"
    ],
    "name:zho_x_preferred":[
        "\u4e2d\u8f9b\u5b89"
    ],
    "wof:name":"Zhongxin'an",
    "wof:placetype":"locality"
},
  "geometry": {"coordinates":[118.15900000000001,37.1536],"type":"Point"}
}