{
  "type": "Feature",
  "properties": {
    "gn:admin1_code":"29.0",
    "gn:asciiname":"Xicun",
    "gn:country_code":"CN",
    "gn:dem":1810,
    "gn:feature_class":"P",
    "gn:feature_code":"PPL",
    "gn:name":"Xicun",
    "gn:population":0,
    "gn:timezone":"Asia/Shanghai",
    "iso:country":"CN",
    "name:zho_x_preferred":[
        "\u897f\u6751"
    ],
    "wof:name":"Xicun",
    "wof:placetype":"locality"
},
  "geometry": {"coordinates":[102.298,25.3553],"type":"Point"}
}