{
  "type": "Feature",
  "properties": {
    "gn:admin1_code":"10",
    "gn:asciiname":"Dongxinzhuang",
    "gn:country_code":"CN",
    "gn:dem":13,
    "gn:feature_class":"P",
    "gn:feature_code":"PPL",
    "gn:name":"Dongxinzhuang",
    "gn:population":0,
    "gn:timezone":"Asia/Shanghai",
    "iso:country":"CN",
    "name:zho_x_preferred":[
        "\u4e1c\u8f9b\u5e84"
    ],
    "wof:name":"Dongxinzhuang",
    "wof:placetype":"locality"
},
  "geometry": {"coordinates":[116.73399999999999,38.7592],"type":"Point"}
}