{
  "type": "Feature",
  "properties": {
    "gn:admin1_code":"4.0",
    "gn:asciiname":"Zhuze",
    "gn:country_code":"CN",
    "gn:dem":2,
    "gn:feature_class":"P",
    "gn:feature_code":"PPLA4",
    "gn:name":"Zhuze",
    "gn:population":0,
    "gn:timezone":"Asia/Shanghai",
    "iso:country":"CN",
    "name:und_x_variant":[
        "Zhuze Zhen",
        "\u7af9\u7ba6\u9547",
        "Zhuze"
    ],
    "name:zho_x_preferred":[
        "\u7af9\u7ba6"
    ],
    "wof:name":"Zhuze",
    "wof:placetype":"locality"
},
  "geometry": {"coordinates":[119.36056000000001,31.55746],"type":"Point"}
}