{
  "type": "Feature",
  "properties": {
    "gn:admin1_code":"9.0",
    "gn:asciiname":"Pangwa",
    "gn:country_code":"CN",
    "gn:dem":131,
    "gn:feature_class":"P",
    "gn:feature_code":"PPL",
    "gn:name":"Pangwa",
    "gn:population":0,
    "gn:timezone":"Asia/Shanghai",
    "iso:country":"CN",
    "name:zho_x_preferred":[
        "\u5e9e\u6d3c"
    ],
    "wof:name":"Pangwa",
    "wof:placetype":"locality"
},
  "geometry": {"coordinates":[113.98689,32.62149],"type":"Point"}
}