{
  "type": "Feature",
  "properties": {
    "gn:admin1_code":"1.0",
    "gn:asciiname":"Donglaozhaicun",
    "gn:country_code":"CN",
    "gn:dem":29,
    "gn:feature_class":"P",
    "gn:feature_code":"PPL",
    "gn:name":"Donglaozhaicun",
    "gn:population":0,
    "gn:timezone":"Asia/Shanghai",
    "iso:country":"CN",
    "name:und_x_variant":[
        "Donglaozhai"
    ],
    "name:zho_x_preferred":[
        "\u8463\u8001\u5be8\u6751"
    ],
    "wof:name":"Donglaozhaicun",
    "wof:placetype":"locality"
},
  "geometry": {"coordinates":[116.20726999999999,33.1781],"type":"Point"}
}