{
  "type": "Feature",
  "properties": {
    "gn:admin1_code":"18",
    "gn:asciiname":"Laomuwan",
    "gn:country_code":"CN",
    "gn:dem":1152,
    "gn:feature_class":"P",
    "gn:feature_code":"PPL",
    "gn:name":"Laomuwan",
    "gn:population":0,
    "gn:timezone":"Asia/Shanghai",
    "iso:country":"CN",
    "name:zho_x_preferred":[
        "\u8001\u6728\u6e7e"
    ],
    "wof:name":"Laomuwan",
    "wof:placetype":"locality"
},
  "geometry": {"coordinates":[107.063,28.5877],"type":"Point"}
}