{
  "type": "Feature",
  "properties": {
    "gn:admin1_code":"3.0",
    "gn:asciiname":"Tuanjiecun",
    "gn:country_code":"CN",
    "gn:dem":20,
    "gn:feature_class":"P",
    "gn:feature_code":"PPL",
    "gn:name":"Tuanjiecun",
    "gn:population":0,
    "gn:timezone":"Asia/Shanghai",
    "iso:country":"CN",
    "name:und_x_variant":[
        "\u56e2\u7ed3\u6751"
    ],
    "wof:name":"Tuanjiecun",
    "wof:placetype":"locality"
},
  "geometry": {"coordinates":[116.05707,28.86402],"type":"Point"}
}