{
  "type": "Feature",
  "properties": {
    "gn:admin1_code":"3.0",
    "gn:asciiname":"Koushang Hejia",
    "gn:country_code":"CN",
    "gn:dem":26,
    "gn:feature_class":"P",
    "gn:feature_code":"PPL",
    "gn:name":"Koushang Hejia",
    "gn:population":0,
    "gn:timezone":"Asia/Shanghai",
    "iso:country":"CN",
    "name:und_x_variant":[
        "\u53e3\u4e0a\u4f55\u5bb6"
    ],
    "wof:name":"Koushang Hejia",
    "wof:placetype":"locality"
},
  "geometry": {"coordinates":[116.02983999999999,28.38036],"type":"Point"}
}