{
  "type": "Feature",
  "properties": {
    "gn:admin1_code":"32.0",
    "gn:asciiname":"Gexicun",
    "gn:country_code":"CN",
    "gn:dem":3574,
    "gn:feature_class":"P",
    "gn:feature_code":"PPL",
    "gn:name":"Gexicun",
    "gn:population":0,
    "gn:timezone":"Asia/Shanghai",
    "iso:country":"CN",
    "name:zho_x_preferred":[
        "\u683c\u897f\u6751"
    ],
    "wof:name":"Gexicun",
    "wof:placetype":"locality"
},
  "geometry": {"coordinates":[101.496,30.4549],"type":"Point"}
}