{
  "type": "Feature",
  "properties": {
    "gn:admin1_code":"29",
    "gn:asciiname":"Lanting",
    "gn:country_code":"CN",
    "gn:dem":1116,
    "gn:feature_class":"P",
    "gn:feature_code":"PPL",
    "gn:name":"Lanting",
    "gn:population":0,
    "gn:timezone":"Asia/Shanghai",
    "iso:country":"CN",
    "name:zho_x_preferred":[
        "\u5170\u4ead"
    ],
    "wof:name":"Lanting",
    "wof:placetype":"locality"
},
  "geometry": {"coordinates":[104.71599999999999,24.3955],"type":"Point"}
}