{
  "type": "Feature",
  "properties": {
    "gn:admin1_code":"15.0",
    "gn:asciiname":"Miba",
    "gn:country_code":"CN",
    "gn:dem":1017,
    "gn:feature_class":"P",
    "gn:feature_code":"PPLA4",
    "gn:name":"Miba",
    "gn:population":0,
    "gn:timezone":"Asia/Shanghai",
    "iso:country":"CN",
    "name:und_x_variant":[
        "\u8ff7\u575d"
    ],
    "wof:name":"Miba",
    "wof:placetype":"locality"
},
  "geometry": {"coordinates":[105.78189999999999,33.54272],"type":"Point"}
}