{
  "type": "Feature",
  "properties": {
    "gn:admin1_code":"25",
    "gn:asciiname":"Nanmachang",
    "gn:country_code":"CN",
    "gn:dem":147,
    "gn:feature_class":"P",
    "gn:feature_code":"PPLF",
    "gn:name":"Nanmachang",
    "gn:population":0,
    "gn:timezone":"Asia/Shanghai",
    "iso:country":"CN",
    "name:zho_x_preferred":[
        "\u5357\u9a6c\u573a"
    ],
    "wof:name":"Nanmachang",
    "wof:placetype":"locality"
},
  "geometry": {"coordinates":[117.473,34.7854],"type":"Point"}
}