{
  "type": "Feature",
  "properties": {
    "gn:admin1_code":"26.0",
    "gn:asciiname":"ShiqiaoShancun",
    "gn:country_code":"CN",
    "gn:dem":815,
    "gn:feature_class":"P",
    "gn:feature_code":"PPL",
    "gn:name":"ShiqiaoShancun",
    "gn:population":0,
    "gn:timezone":"Asia/Shanghai",
    "iso:country":"CN",
    "name:zho_x_preferred":[
        "\u77f3\u6865\u5c71\u6751"
    ],
    "wof:name":"ShiqiaoShancun",
    "wof:placetype":"locality"
},
  "geometry": {"coordinates":[110.38258999999999,37.14639],"type":"Point"}
}