{
  "type": "Feature",
  "properties": {
    "gn:admin1_code":"11.0",
    "gn:asciiname":"Hefeng Daokou",
    "gn:country_code":"CN",
    "gn:dem":28,
    "gn:feature_class":"P",
    "gn:feature_code":"PPL",
    "gn:name":"Hefeng Daokou",
    "gn:population":0,
    "gn:timezone":"Asia/Shanghai",
    "iso:country":"CN",
    "name:zho_x_preferred":[
        "\u548c\u4e30\u5012\u53e3"
    ],
    "wof:name":"Hefeng Daokou",
    "wof:placetype":"locality"
},
  "geometry": {"coordinates":[112.40949999999999,28.99778],"type":"Point"}
}