{
  "type": "Feature",
  "properties": {
    "gn:admin1_code":"19.0",
    "gn:asciiname":"Laotai Wobu",
    "gn:country_code":"CN",
    "gn:dem":105,
    "gn:feature_class":"P",
    "gn:feature_code":"PPL",
    "gn:name":"Laotai Wobu",
    "gn:population":0,
    "gn:timezone":"Asia/Shanghai",
    "iso:country":"CN",
    "name:und_x_variant":[
        "Laotaiwobao",
        "\u8001\u53f0\u7a9d\u5821",
        "Laotai Wobu"
    ],
    "name:zho_x_preferred":[
        "\u8001\u53f0\u7a9d\u5821"
    ],
    "wof:name":"Laotai Wobu",
    "wof:placetype":"locality"
},
  "geometry": {"coordinates":[122.76098,42.51287],"type":"Point"}
}