{
  "type": "Feature",
  "properties": {
    "gn:admin1_code":"11.0",
    "gn:asciiname":"Bagan",
    "gn:country_code":"CN",
    "gn:dem":251,
    "gn:feature_class":"P",
    "gn:feature_code":"PPL",
    "gn:name":"Bagan",
    "gn:population":0,
    "gn:timezone":"Asia/Shanghai",
    "iso:country":"CN",
    "name:zho_x_preferred":[
        "\u62d4\u5e72"
    ],
    "wof:name":"Bagan",
    "wof:placetype":"locality"
},
  "geometry": {"coordinates":[111.49802,24.98325],"type":"Point"}
}