{
  "type": "Feature",
  "properties": {
    "gn:admin1_code":"24.0",
    "gn:asciiname":"Anzegou",
    "gn:country_code":"CN",
    "gn:dem":1402,
    "gn:feature_class":"P",
    "gn:feature_code":"PPL",
    "gn:name":"Anzegou",
    "gn:population":0,
    "gn:timezone":"Asia/Shanghai",
    "iso:country":"CN",
    "name:zho_x_preferred":[
        "\u5b89\u6cfd\u6c9f"
    ],
    "wof:name":"Anzegou",
    "wof:placetype":"locality"
},
  "geometry": {"coordinates":[111.92966,36.49871],"type":"Point"}
}