{
  "type": "Feature",
  "properties": {
    "gn:admin1_code":"3.0",
    "gn:asciiname":"Xinjiecun Linchang",
    "gn:country_code":"CN",
    "gn:dem":92,
    "gn:feature_class":"P",
    "gn:feature_code":"PPLF",
    "gn:name":"Xinjiecun Linchang",
    "gn:population":0,
    "gn:timezone":"Asia/Shanghai",
    "iso:country":"CN",
    "name:und_x_variant":[
        "\u65b0\u8857\u6751\u6797\u573a"
    ],
    "wof:name":"Xinjiecun Linchang",
    "wof:placetype":"locality"
},
  "geometry": {"coordinates":[116.52623,27.33546],"type":"Point"}
}