{
  "type": "Feature",
  "properties": {
    "gn:admin1_code":"29.0",
    "gn:asciiname":"Gaogula",
    "gn:country_code":"CN",
    "gn:dem":2127,
    "gn:feature_class":"P",
    "gn:feature_code":"PPL",
    "gn:name":"Gaogula",
    "gn:population":0,
    "gn:timezone":"Asia/Shanghai",
    "iso:country":"CN",
    "name:zho_x_preferred":[
        "\u9ad8\u59d1\u62c9"
    ],
    "wof:name":"Gaogula",
    "wof:placetype":"locality"
},
  "geometry": {"coordinates":[102.139,25.6811],"type":"Point"}
}