{
  "type": "Feature",
  "properties": {
    "gn:admin1_code":"11",
    "gn:asciiname":"Langtang",
    "gn:cc2":"CN",
    "gn:country_code":"CN",
    "gn:dem":199,
    "gn:feature_class":"P",
    "gn:feature_code":"PPL",
    "gn:name":"Langtang",
    "gn:population":0,
    "gn:timezone":"Asia/Shanghai",
    "iso:country":"CN",
    "name:und_x_variant":[
        "Tuanjieshan",
        "Langtang"
    ],
    "wof:name":"Langtang",
    "wof:placetype":"locality"
},
  "geometry": {"coordinates":[111.10611000000002,27.99222],"type":"Point"}
}