{
  "type": "Feature",
  "properties": {
    "gn:admin1_code":"33.0",
    "gn:asciiname":"Shanlin",
    "gn:country_code":"CN",
    "gn:dem":754,
    "gn:feature_class":"P",
    "gn:feature_code":"PPL",
    "gn:name":"Shanlin",
    "gn:population":0,
    "gn:timezone":"Asia/Shanghai",
    "iso:country":"CN",
    "name:fra_x_preferred":[
        "Shanlin"
    ],
    "name:spa_x_preferred":[
        "Shanlin"
    ],
    "name:zho_x_preferred":[
        "\u6749\u6797"
    ],
    "wof:name":"Shanlin",
    "wof:placetype":"locality"
},
  "geometry": {"coordinates":[108.64078000000001,29.72698],"type":"Point"}
}