{
  "type": "Feature",
  "properties": {
    "gn:admin1_code":"9.0",
    "gn:asciiname":"Wucheniu",
    "gn:country_code":"CN",
    "gn:dem":80,
    "gn:feature_class":"P",
    "gn:feature_code":"PPL",
    "gn:name":"Wucheniu",
    "gn:population":0,
    "gn:timezone":"Asia/Shanghai",
    "iso:country":"CN",
    "name:und_x_variant":[
        "\u4e94\u8f66\u725b"
    ],
    "name:zho_x_preferred":[
        "\u4e94\u8f66\u725b"
    ],
    "wof:name":"Wucheniu",
    "wof:placetype":"locality"
},
  "geometry": {"coordinates":[113.83176,33.10394],"type":"Point"}
}