{
  "type": "Feature",
  "properties": {
    "gn:admin1_code":"18.0",
    "gn:asciiname":"Cenxian",
    "gn:country_code":"CN",
    "gn:dem":507,
    "gn:feature_class":"P",
    "gn:feature_code":"PPL",
    "gn:name":"Cenxian",
    "gn:population":0,
    "gn:timezone":"Asia/Shanghai",
    "iso:country":"CN",
    "name:zho_x_preferred":[
        "\u5c91\u663e"
    ],
    "wof:name":"Cenxian",
    "wof:placetype":"locality"
},
  "geometry": {"coordinates":[109.32899999999999,25.8763],"type":"Point"}
}