{
  "type": "Feature",
  "properties": {
    "gn:admin1_code":"24.0",
    "gn:asciiname":"Xipingyandi",
    "gn:country_code":"CN",
    "gn:dem":780,
    "gn:feature_class":"P",
    "gn:feature_code":"PPL",
    "gn:name":"Xipingyandi",
    "gn:population":0,
    "gn:timezone":"Asia/Shanghai",
    "iso:country":"CN",
    "name:zho_x_preferred":[
        "\u897f\u5e73\u5ca9\u5e95"
    ],
    "wof:name":"Xipingyandi",
    "wof:placetype":"locality"
},
  "geometry": {"coordinates":[112.59128,35.81919],"type":"Point"}
}