{
  "type": "Feature",
  "properties": {
    "gn:admin1_code":"12.0",
    "gn:asciiname":"Qiujiawan",
    "gn:country_code":"CN",
    "gn:dem":40,
    "gn:feature_class":"P",
    "gn:feature_code":"PPL",
    "gn:name":"Qiujiawan",
    "gn:population":0,
    "gn:timezone":"Asia/Shanghai",
    "iso:country":"CN",
    "name:und_x_variant":[
        "\u4e18\u5bb6\u5846"
    ],
    "wof:name":"Qiujiawan",
    "wof:placetype":"locality"
},
  "geometry": {"coordinates":[114.31913,30.22068],"type":"Point"}
}