{
  "type": "Feature",
  "properties": {
    "gn:admin1_code":"9.0",
    "gn:asciiname":"Zhangjunmu",
    "gn:cc2":"CN",
    "gn:country_code":"CN",
    "gn:dem":69,
    "gn:feature_class":"P",
    "gn:feature_code":"PPL",
    "gn:name":"Zhangjunmu",
    "gn:population":0,
    "gn:timezone":"Asia/Shanghai",
    "iso:country":"CN",
    "name:und_x_variant":[
        "Chang-ch\u00fcn-mu",
        "Zhangjunmu"
    ],
    "wof:name":"Zhangjunmu",
    "wof:placetype":"locality"
},
  "geometry": {"coordinates":[115.13333,34.85],"type":"Point"}
}