{
  "type": "Feature",
  "properties": {
    "gn:admin1_code":"30.0",
    "gn:asciiname":"Jiaokengjing",
    "gn:country_code":"CN",
    "gn:dem":370,
    "gn:feature_class":"P",
    "gn:feature_code":"PPL",
    "gn:name":"Jiaokengjing",
    "gn:population":0,
    "gn:timezone":"Asia/Shanghai",
    "iso:country":"CN",
    "name:zho_x_preferred":[
        "\u8549\u5751\u8ff3"
    ],
    "wof:name":"Jiaokengjing",
    "wof:placetype":"locality"
},
  "geometry": {"coordinates":[112.62555999999999,24.03194],"type":"Point"}
}