{
  "type": "Feature",
  "properties": {
    "gn:admin1_code":"21.0",
    "gn:asciiname":"Qian'ercha",
    "gn:country_code":"CN",
    "gn:dem":2053,
    "gn:feature_class":"P",
    "gn:feature_code":"PPL",
    "gn:name":"Qian\u2019ercha",
    "gn:population":0,
    "gn:timezone":"Asia/Shanghai",
    "iso:country":"CN",
    "name:und_x_variant":[
        "Qian\u2019ercha"
    ],
    "name:zho_x_preferred":[
        "\u8fc1\u513f\u5c94"
    ],
    "wof:name":"Qian'ercha",
    "wof:placetype":"locality"
},
  "geometry": {"coordinates":[106.038,35.9466],"type":"Point"}
}