{
  "type": "Feature",
  "properties": {
    "gn:admin1_code":"32.0",
    "gn:asciiname":"Lujiaolada",
    "gn:country_code":"CN",
    "gn:dem":2804,
    "gn:feature_class":"P",
    "gn:feature_code":"PPL",
    "gn:name":"Lujiaolada",
    "gn:population":0,
    "gn:timezone":"Asia/Shanghai",
    "iso:country":"CN",
    "name:zho_x_preferred":[
        "\u9c81\u89d2\u62c9\u6253"
    ],
    "wof:name":"Lujiaolada",
    "wof:placetype":"locality"
},
  "geometry": {"coordinates":[102.505,27.9796],"type":"Point"}
}