{
  "type": "Feature",
  "properties": {
    "gn:admin1_code":"7.0",
    "gn:asciiname":"Shen'an",
    "gn:country_code":"CN",
    "gn:dem":155,
    "gn:feature_class":"P",
    "gn:feature_code":"PPL",
    "gn:name":"Shen\u2019an",
    "gn:population":0,
    "gn:timezone":"Asia/Shanghai",
    "iso:country":"CN",
    "name:und_x_variant":[
        "Shen\u2019an"
    ],
    "name:zho_x_preferred":[
        "\u6df1\u57b5"
    ],
    "wof:name":"Shen'an",
    "wof:placetype":"locality"
},
  "geometry": {"coordinates":[118.27209999999999,25.13458],"type":"Point"}
}