{
  "type": "Feature",
  "properties": {
    "gn:admin1_code":"15.0",
    "gn:asciiname":"Shundebu",
    "gn:country_code":"CN",
    "gn:dem":1804,
    "gn:feature_class":"P",
    "gn:feature_code":"PPL",
    "gn:name":"Shundebu",
    "gn:population":0,
    "gn:timezone":"Asia/Shanghai",
    "iso:country":"CN",
    "name:zho_x_preferred":[
        "\u987a\u5fb7\u5821"
    ],
    "wof:name":"Shundebu",
    "wof:placetype":"locality"
},
  "geometry": {"coordinates":[99.4704,39.2111],"type":"Point"}
}