{
  "type": "Feature",
  "properties": {
    "gn:admin1_code":"12.0",
    "gn:asciiname":"Chuncaoyu",
    "gn:country_code":"CN",
    "gn:dem":1021,
    "gn:feature_class":"P",
    "gn:feature_code":"PPL",
    "gn:name":"Chuncaoyu",
    "gn:population":0,
    "gn:timezone":"Asia/Shanghai",
    "iso:country":"CN",
    "name:zho_x_preferred":[
        "\u6625\u8349\u5cea"
    ],
    "wof:name":"Chuncaoyu",
    "wof:placetype":"locality"
},
  "geometry": {"coordinates":[110.88668,31.94984],"type":"Point"}
}