{
  "type": "Feature",
  "properties": {
    "gn:admin1_code":"2.0",
    "gn:asciiname":"Zhinan",
    "gn:country_code":"CN",
    "gn:dem":713,
    "gn:feature_class":"P",
    "gn:feature_code":"PPL",
    "gn:name":"Zhinan",
    "gn:population":0,
    "gn:timezone":"Asia/Shanghai",
    "iso:country":"CN",
    "name:und_x_variant":[
        "\u6307\u5357"
    ],
    "name:zho_x_preferred":[
        "Zhinan"
    ],
    "wof:name":"Zhinan",
    "wof:placetype":"locality"
},
  "geometry": {"coordinates":[119.57962000000001,30.36957],"type":"Point"}
}