{
  "type": "Feature",
  "properties": {
    "gn:admin1_code":"19.0",
    "gn:asciiname":"Hanjiagou",
    "gn:country_code":"CN",
    "gn:dem":40,
    "gn:feature_class":"P",
    "gn:feature_code":"PPL",
    "gn:name":"Hanjiagou",
    "gn:population":0,
    "gn:timezone":"Asia/Shanghai",
    "iso:country":"CN",
    "name:und_x_variant":[
        "\u97e9\u5bb6\u6c9f"
    ],
    "name:zho_x_preferred":[
        "\u97e9\u5bb6\u6c9f"
    ],
    "wof:name":"Hanjiagou",
    "wof:placetype":"locality"
},
  "geometry": {"coordinates":[120.76918000000001,40.67356],"type":"Point"}
}