{
  "type": "Feature",
  "properties": {
    "gn:admin1_code":"29.0",
    "gn:asciiname":"Cunpu",
    "gn:country_code":"CN",
    "gn:dem":2133,
    "gn:feature_class":"P",
    "gn:feature_code":"PPL",
    "gn:name":"Cunpu",
    "gn:population":0,
    "gn:timezone":"Asia/Shanghai",
    "iso:country":"CN",
    "name:zho_x_preferred":[
        "\u5b58\u94fa"
    ],
    "wof:name":"Cunpu",
    "wof:placetype":"locality"
},
  "geometry": {"coordinates":[98.8379,27.6085],"type":"Point"}
}