{
  "type": "Feature",
  "properties": {
    "gn:admin1_code":"24.0",
    "gn:asciiname":"Wangbu",
    "gn:country_code":"CN",
    "gn:dem":1654,
    "gn:feature_class":"P",
    "gn:feature_code":"PPL",
    "gn:name":"Wangbu",
    "gn:population":0,
    "gn:timezone":"Asia/Shanghai",
    "iso:country":"CN",
    "name:zho_x_preferred":[
        "\u738b\u5821"
    ],
    "wof:name":"Wangbu",
    "wof:placetype":"locality"
},
  "geometry": {"coordinates":[111.55367,38.42553],"type":"Point"}
}