{
  "type": "Feature",
  "properties": {
    "gn:admin1_code":"5.0",
    "gn:asciiname":"Houjinchan",
    "gn:country_code":"CN",
    "gn:dem":264,
    "gn:feature_class":"P",
    "gn:feature_code":"PPL",
    "gn:name":"Houjinchan",
    "gn:population":0,
    "gn:timezone":"Asia/Shanghai",
    "iso:country":"CN",
    "name:zho_x_preferred":[
        "\u540e\u91d1\u87fe"
    ],
    "wof:name":"Houjinchan",
    "wof:placetype":"locality"
},
  "geometry": {"coordinates":[122.04749,45.56652],"type":"Point"}
}