{
  "type": "Feature",
  "properties": {
    "gn:admin1_code":"12.0",
    "gn:asciiname":"Mingjiawan",
    "gn:country_code":"CN",
    "gn:dem":250,
    "gn:feature_class":"P",
    "gn:feature_code":"PPL",
    "gn:name":"Mingjiawan",
    "gn:population":0,
    "gn:timezone":"Asia/Shanghai",
    "iso:country":"CN",
    "name:zho_x_preferred":[
        "\u660e\u5bb6\u5846"
    ],
    "wof:name":"Mingjiawan",
    "wof:placetype":"locality"
},
  "geometry": {"coordinates":[113.73354999999999,32.24621],"type":"Point"}
}