{
  "type": "Feature",
  "properties": {
    "gn:admin1_code":"1.0",
    "gn:asciiname":"Yuantanqiao",
    "gn:country_code":"CN",
    "gn:dem":10,
    "gn:feature_class":"P",
    "gn:feature_code":"PPL",
    "gn:name":"Yuantanqiao",
    "gn:population":0,
    "gn:timezone":"Asia/Shanghai",
    "iso:country":"CN",
    "name:und_x_variant":[
        "Y\u00fcan-t\u2019an-ch\u2019iao",
        "Yuantanqiao"
    ],
    "wof:name":"Yuantanqiao",
    "wof:placetype":"locality"
},
  "geometry": {"coordinates":[118.40387,31.01562],"type":"Point"}
}