{
  "type": "Feature",
  "properties": {
    "gn:admin1_code":"32.0",
    "gn:asciiname":"Jiabulamo",
    "gn:country_code":"CN",
    "gn:dem":2636,
    "gn:feature_class":"P",
    "gn:feature_code":"PPL",
    "gn:name":"Jiabulamo",
    "gn:population":0,
    "gn:timezone":"Asia/Shanghai",
    "iso:country":"CN",
    "name:zho_x_preferred":[
        "\u7532\u8865\u62c9\u83ab"
    ],
    "wof:name":"Jiabulamo",
    "wof:placetype":"locality"
},
  "geometry": {"coordinates":[103.07599999999999,27.9596],"type":"Point"}
}