{
  "type": "Feature",
  "properties": {
    "gn:admin1_code":"29.0",
    "gn:asciiname":"Maliuzhai",
    "gn:country_code":"CN",
    "gn:dem":1118,
    "gn:feature_class":"P",
    "gn:feature_code":"PPL",
    "gn:name":"Maliuzhai",
    "gn:population":0,
    "gn:timezone":"Asia/Shanghai",
    "iso:country":"CN",
    "name:zho_x_preferred":[
        "\u9a82\u69b4\u5be8"
    ],
    "wof:name":"Maliuzhai",
    "wof:placetype":"locality"
},
  "geometry": {"coordinates":[99.44240000000001,24.0578],"type":"Point"}
}