{
  "type": "Feature",
  "properties": {
    "gn:admin1_code":"15.0",
    "gn:asciiname":"Xiangla",
    "gn:country_code":"CN",
    "gn:dem":2757,
    "gn:feature_class":"P",
    "gn:feature_code":"PPL",
    "gn:name":"Xiangla",
    "gn:population":0,
    "gn:timezone":"Asia/Shanghai",
    "iso:country":"CN",
    "name:und_x_variant":[
        "\u9999\u62c9"
    ],
    "wof:name":"Xiangla",
    "wof:placetype":"locality"
},
  "geometry": {"coordinates":[102.86753,35.10451],"type":"Point"}
}