{
  "type": "Feature",
  "properties": {
    "gn:admin1_code":"3",
    "gn:asciiname":"Baitianbu",
    "gn:country_code":"CN",
    "gn:dem":137,
    "gn:feature_class":"P",
    "gn:feature_code":"PPL",
    "gn:name":"Baitianbu",
    "gn:population":0,
    "gn:timezone":"Asia/Shanghai",
    "iso:country":"CN",
    "name:zho_x_preferred":[
        "\u767d\u7530\u57e0"
    ],
    "wof:name":"Baitianbu",
    "wof:placetype":"locality"
},
  "geometry": {"coordinates":[114.64530000000001,25.52523],"type":"Point"}
}