{
  "type": "Feature",
  "properties": {
    "gn:admin1_code":"15.0",
    "gn:asciiname":"Shijia Goumen",
    "gn:country_code":"CN",
    "gn:dem":1790,
    "gn:feature_class":"P",
    "gn:feature_code":"PPL",
    "gn:name":"Shijia Goumen",
    "gn:population":0,
    "gn:timezone":"Asia/Shanghai",
    "iso:country":"CN",
    "name:zho_x_preferred":[
        "\u77f3\u5bb6\u6c9f\u95e8"
    ],
    "wof:name":"Shijia Goumen",
    "wof:placetype":"locality"
},
  "geometry": {"coordinates":[103.602,35.76300000000001],"type":"Point"}
}