{
  "type": "Feature",
  "properties": {
    "gn:admin1_code":"24",
    "gn:asciiname":"Sanjiao",
    "gn:cc2":"CN",
    "gn:country_code":"CN",
    "gn:dem":838,
    "gn:feature_class":"P",
    "gn:feature_code":"PPL",
    "gn:name":"Sanjiao",
    "gn:population":0,
    "gn:timezone":"Asia/Shanghai",
    "iso:country":"CN",
    "name:ceb_x_preferred":[
        "Sanjiao"
    ],
    "name:deu_x_preferred":[
        "Sanjiao"
    ],
    "name:swe_x_preferred":[
        "Sanjiao"
    ],
    "name:und_x_variant":[
        "San-chiao-chen",
        "San\u2019tszyaochzhen\u2019",
        "San-chiao-ch\u2019\u00fc",
        "Sankiaochen",
        "Sanjiao"
    ],
    "wof:name":"Sanjiao",
    "wof:placetype":"locality"
},
  "geometry": {"coordinates":[110.96250000000001,37.78611],"type":"Point"}
}