{
  "type": "Feature",
  "properties": {
    "gn:admin1_code":"08",
    "gn:asciiname":"Wumahe",
    "gn:country_code":"CN",
    "gn:dem":244,
    "gn:feature_class":"P",
    "gn:feature_code":"PPLA3",
    "gn:name":"Wumahe",
    "gn:population":0,
    "gn:timezone":"Asia/Shanghai",
    "iso:country":"CN",
    "name:und_x_variant":[
        "Wumahe Jiedao",
        "Wumahe Qu"
    ],
    "name:zho_x_preferred":[
        "\u4e4c\u9a6c\u6cb3"
    ],
    "name:zho_x_variant":[
        "\u4e4c\u9a6c\u6cb3\u8857\u9053",
        "\u4e4c\u9a6c\u6cb3\u533a"
    ],
    "wof:name":"Wumahe",
    "wof:placetype":"locality"
},
  "geometry": {"coordinates":[128.79276999999999,47.72348],"type":"Point"}
}