{
  "type": "Feature",
  "properties": {
    "gn:admin1_code":"18",
    "gn:asciiname":"Shuangshuzhi",
    "gn:country_code":"CN",
    "gn:dem":1769,
    "gn:feature_class":"P",
    "gn:feature_code":"PPL",
    "gn:name":"Shuangshuzhi",
    "gn:population":0,
    "gn:timezone":"Asia/Shanghai",
    "iso:country":"CN",
    "name:zho_x_preferred":[
        "\u53cc\u6811\u679d"
    ],
    "wof:name":"Shuangshuzhi",
    "wof:placetype":"locality"
},
  "geometry": {"coordinates":[104.941,26.9894],"type":"Point"}
}