{
  "type": "Feature",
  "properties": {
    "gn:admin1_code":"12.0",
    "gn:asciiname":"Wangshanting",
    "gn:country_code":"CN",
    "gn:dem":338,
    "gn:feature_class":"P",
    "gn:feature_code":"PPL",
    "gn:name":"Wangshanting",
    "gn:population":0,
    "gn:timezone":"Asia/Shanghai",
    "iso:country":"CN",
    "name:zho_x_preferred":[
        "Wangshanting"
    ],
    "name:zho_x_variant":[
        "\u671b\u5c71\u4ead"
    ],
    "wof:name":"Wangshanting",
    "wof:placetype":"locality"
},
  "geometry": {"coordinates":[111.20444999999999,30.43514],"type":"Point"}
}