{
  "type": "Feature",
  "properties": {
    "gn:admin1_code":"18",
    "gn:asciiname":"Tanping",
    "gn:country_code":"CN",
    "gn:dem":1364,
    "gn:feature_class":"P",
    "gn:feature_code":"PPL",
    "gn:name":"Tanping",
    "gn:population":0,
    "gn:timezone":"Asia/Shanghai",
    "iso:country":"CN",
    "name:zho_x_preferred":[
        "\u6f6d\u576a"
    ],
    "wof:name":"Tanping",
    "wof:placetype":"locality"
},
  "geometry": {"coordinates":[105.479,25.2867],"type":"Point"}
}