{
  "type": "Feature",
  "properties": {
    "gn:admin1_code":"13.0",
    "gn:asciiname":"Alashankou",
    "gn:country_code":"CN",
    "gn:dem":307,
    "gn:feature_class":"P",
    "gn:feature_code":"PPL",
    "gn:name":"Alashankou",
    "gn:population":0,
    "gn:timezone":"Asia/Urumqi",
    "iso:country":"CN",
    "name:eng_x_preferred":[
        "Alashankou"
    ],
    "name:zho_x_preferred":[
        "\u963f\u62c9\u5c71\u53e3"
    ],
    "name:zho_x_variant":[
        "\u0100l\u0101sh\u0101nk\u01d2u"
    ],
    "wof:name":"Alashankou",
    "wof:placetype":"locality"
},
  "geometry": {"coordinates":[82.56981,45.17018],"type":"Point"}
}