{
  "type": "Feature",
  "properties": {
    "gn:admin1_code":"13.0",
    "gn:asciiname":"Alashankou",
    "gn:country_code":"CN",
    "gn:dem":307,
    "gn:feature_class":"P",
    "gn:feature_code":"PPL",
    "gn:name":"Alashankou",
    "gn:population":0,
    "gn:timezone":"Asia/Urumqi",
    "iso:country":"CN",
    "name:deu_x_preferred":[
        "Alashankou"
    ],
    "name:eng_x_preferred":[
        "Alashankou"
    ],
    "name:fas_x_preferred":[
        "\u06af\u0631\u062f\u0646\u0647 \u0622\u0644\u0627\u062a\u0627\u0648"
    ],
    "name:ita_x_preferred":[
        "Alashankou"
    ],
    "name:jpn_x_preferred":[
        "\u963f\u62c9\u5c71\u53e3\u5e02"
    ],
    "name:kik_x_preferred":[
        "Alashankou"
    ],
    "name:kor_x_preferred":[
        "\uc544\ub77c\uc0b0\ucee4\uc6b0\uc2dc"
    ],
    "name:rus_x_preferred":[
        "\u0410\u043b\u0430\u0448\u0430\u043d\u044c\u043a\u043e\u0443"
    ],
    "name:tur_x_preferred":[
        "Alashankou"
    ],
    "name:uig_x_preferred":[
        "\u0626\u0627\u0644\u0627\u062a\u0627\u06cb \u0626\u06d0\u063a\u0649\u0632\u0649"
    ],
    "name:urd_x_preferred":[
        "\u0627\u0644\u0627\u0634\u0627\u0646\u06a9\u0648\u0648"
    ],
    "name:zho_x_preferred":[
        "\u963f\u62c9\u5c71\u53e3"
    ],
    "name:zho_x_variant":[
        "\u0100l\u0101sh\u0101nk\u01d2u",
        "\u963f\u62c9\u5c71\u53e3\u5e02"
    ],
    "wof:name":"Alashankou",
    "wof:placetype":"locality"
},
  "geometry": {"coordinates":[82.56981,45.17018],"type":"Point"}
}