{
  "type": "Feature",
  "properties": {
    "gn:admin1_code":"18.0",
    "gn:asciiname":"Touzhai",
    "gn:country_code":"CN",
    "gn:dem":1287,
    "gn:feature_class":"P",
    "gn:feature_code":"PPL",
    "gn:name":"Touzhai",
    "gn:population":0,
    "gn:timezone":"Asia/Shanghai",
    "iso:country":"CN",
    "name:zho_x_preferred":[
        "\u5934\u5be8"
    ],
    "wof:name":"Touzhai",
    "wof:placetype":"locality"
},
  "geometry": {"coordinates":[107.29600000000001,26.8504],"type":"Point"}
}