{
  "type": "Feature",
  "properties": {
    "gn:admin1_code":"26.0",
    "gn:asciiname":"Shenjiayuancun",
    "gn:country_code":"CN",
    "gn:dem":1108,
    "gn:feature_class":"P",
    "gn:feature_code":"PPL",
    "gn:name":"Shenjiayuancun",
    "gn:population":0,
    "gn:timezone":"Asia/Shanghai",
    "iso:country":"CN",
    "name:zho_x_preferred":[
        "\u795e\u5bb6\u586c\u6751"
    ],
    "wof:name":"Shenjiayuancun",
    "wof:placetype":"locality"
},
  "geometry": {"coordinates":[107.8554,34.70313],"type":"Point"}
}