{
  "type": "Feature",
  "properties": {
    "gn:admin1_code":"19.0",
    "gn:asciiname":"Longwang Miaozi",
    "gn:country_code":"CN",
    "gn:dem":391,
    "gn:feature_class":"P",
    "gn:feature_code":"PPL",
    "gn:name":"Longwang Miaozi",
    "gn:population":0,
    "gn:timezone":"Asia/Shanghai",
    "iso:country":"CN",
    "name:und_x_variant":[
        "\u9f99\u738b\u5e99\u5b50"
    ],
    "wof:name":"Longwang Miaozi",
    "wof:placetype":"locality"
},
  "geometry": {"coordinates":[122.81375,40.23649],"type":"Point"}
}