{
  "type": "Feature",
  "properties": {
    "gn:admin1_code":"14.0",
    "gn:asciiname":"Leguxi",
    "gn:country_code":"CN",
    "gn:dem":4383,
    "gn:feature_class":"P",
    "gn:feature_code":"PPL",
    "gn:name":"Leguxi",
    "gn:population":0,
    "gn:timezone":"Asia/Urumqi",
    "iso:country":"CN",
    "name:zho_x_preferred":[
        "\u52d2\u53e4\u559c"
    ],
    "wof:name":"Leguxi",
    "wof:placetype":"locality"
},
  "geometry": {"coordinates":[96.52212,29.45123],"type":"Point"}
}