{
  "type": "Feature",
  "properties": {
    "gn:admin1_code":"3.0",
    "gn:asciiname":"Shanhucun",
    "gn:country_code":"CN",
    "gn:dem":20,
    "gn:feature_class":"P",
    "gn:feature_code":"PPL",
    "gn:name":"Shanhucun",
    "gn:population":0,
    "gn:timezone":"Asia/Shanghai",
    "iso:country":"CN",
    "name:und_x_variant":[
        "\u5c71\u6e56\u6751"
    ],
    "wof:name":"Shanhucun",
    "wof:placetype":"locality"
},
  "geometry": {"coordinates":[116.02836000000001,28.65812],"type":"Point"}
}