{
  "type": "Feature",
  "properties": {
    "gn:admin1_code":"19.0",
    "gn:asciiname":"Guojiazhuang",
    "gn:country_code":"CN",
    "gn:dem":42,
    "gn:feature_class":"P",
    "gn:feature_code":"PPL",
    "gn:name":"Guojiazhuang",
    "gn:population":0,
    "gn:timezone":"Asia/Shanghai",
    "iso:country":"CN",
    "name:zho_x_preferred":[
        "\u90ed\u5bb6\u5e84"
    ],
    "wof:name":"Guojiazhuang",
    "wof:placetype":"locality"
},
  "geometry": {"coordinates":[120.23859,40.45652000000001],"type":"Point"}
}