{
  "type": "Feature",
  "properties": {
    "gn:admin1_code":"20.0",
    "gn:asciiname":"Getazi",
    "gn:country_code":"CN",
    "gn:dem":1666,
    "gn:feature_class":"P",
    "gn:feature_code":"PPL",
    "gn:name":"Getazi",
    "gn:population":0,
    "gn:timezone":"Asia/Shanghai",
    "iso:country":"CN",
    "name:und_x_variant":[
        "\u572a\u5854\u5b50"
    ],
    "wof:name":"Getazi",
    "wof:placetype":"locality"
},
  "geometry": {"coordinates":[111.1837,40.99672],"type":"Point"}
}