{
  "type": "Feature",
  "properties": {
    "gn:admin1_code":"19.0",
    "gn:asciiname":"Zhongsuotun",
    "gn:country_code":"CN",
    "gn:dem":38,
    "gn:feature_class":"P",
    "gn:feature_code":"PPL",
    "gn:name":"Zhongsuotun",
    "gn:population":0,
    "gn:timezone":"Asia/Shanghai",
    "iso:country":"CN",
    "name:und_x_variant":[
        "\u4e2d\u6240\u5c6f"
    ],
    "name:zho_x_preferred":[
        "\u4e2d\u6240\u5c6f"
    ],
    "wof:name":"Zhongsuotun",
    "wof:placetype":"locality"
},
  "geometry": {"coordinates":[122.90582999999999,41.03729000000001],"type":"Point"}
}