{
  "type": "Feature",
  "properties": {
    "gn:admin1_code":"9.0",
    "gn:asciiname":"Tumen",
    "gn:country_code":"CN",
    "gn:dem":177,
    "gn:feature_class":"P",
    "gn:feature_code":"PPL",
    "gn:name":"Tumen",
    "gn:population":0,
    "gn:timezone":"Asia/Shanghai",
    "iso:country":"CN",
    "name:zho_x_preferred":[
        "\u571f\u95e8"
    ],
    "wof:name":"Tumen",
    "wof:placetype":"locality"
},
  "geometry": {"coordinates":[111.63665,32.81721],"type":"Point"}
}