{
  "type": "Feature",
  "properties": {
    "gn:admin1_code":"6.0",
    "gn:asciiname":"Zhalu Woma",
    "gn:country_code":"CN",
    "gn:dem":4428,
    "gn:feature_class":"P",
    "gn:feature_code":"PPL",
    "gn:name":"Zhal\u00fc Woma",
    "gn:population":0,
    "gn:timezone":"Asia/Urumqi",
    "iso:country":"CN",
    "name:und_x_variant":[
        "Zhal\u00fc Woma"
    ],
    "name:zho_x_preferred":[
        "\u624e\u5415\u7a9d\u739b"
    ],
    "wof:name":"Zhalu Woma",
    "wof:placetype":"locality"
},
  "geometry": {"coordinates":[96.31479,33.31034],"type":"Point"}
}