{
  "type": "Feature",
  "properties": {
    "gn:admin1_code":"19",
    "gn:asciiname":"Wangjiazhuang",
    "gn:country_code":"CN",
    "gn:dem":19,
    "gn:feature_class":"P",
    "gn:feature_code":"PPLA4",
    "gn:name":"Wangjiazhuang",
    "gn:population":0,
    "gn:timezone":"Asia/Shanghai",
    "iso:country":"CN",
    "name:und_x_variant":[
        "Wanjia Zhen",
        "Wangjiazhuang"
    ],
    "name:zho_x_preferred":[
        "\u738b\u5bb6\u5e84"
    ],
    "name:zho_x_variant":[
        "\u4e07\u5bb6\u9547"
    ],
    "wof:name":"Wangjiazhuang",
    "wof:placetype":"locality"
},
  "geometry": {"coordinates":[119.85503,40.05507],"type":"Point"}
}