{
  "type": "Feature",
  "properties": {
    "gn:admin1_code":"19.0",
    "gn:asciiname":"Dawangtun",
    "gn:country_code":"CN",
    "gn:dem":36,
    "gn:feature_class":"P",
    "gn:feature_code":"PPL",
    "gn:name":"Dawangtun",
    "gn:population":0,
    "gn:timezone":"Asia/Shanghai",
    "iso:country":"CN",
    "name:und_x_variant":[
        "\u5927\u738b\u5c6f"
    ],
    "name:zho_x_preferred":[
        "\u5927\u738b\u5c6f"
    ],
    "wof:name":"Dawangtun",
    "wof:placetype":"locality"
},
  "geometry": {"coordinates":[122.755,39.7286],"type":"Point"}
}