{
  "type": "Feature",
  "properties": {
    "gn:admin1_code":"33.0",
    "gn:asciiname":"Niumen",
    "gn:country_code":"CN",
    "gn:dem":466,
    "gn:feature_class":"P",
    "gn:feature_code":"PPL",
    "gn:name":"Niumen",
    "gn:population":0,
    "gn:timezone":"Asia/Shanghai",
    "iso:country":"CN",
    "name:zho_x_preferred":[
        "\u725b\u95e8"
    ],
    "wof:name":"Niumen",
    "wof:placetype":"locality"
},
  "geometry": {"coordinates":[108.55888,31.04597],"type":"Point"}
}