{
  "type": "Feature",
  "properties": {
    "gn:admin1_code":"32.0",
    "gn:asciiname":"Waku",
    "gn:country_code":"CN",
    "gn:dem":2182,
    "gn:feature_class":"P",
    "gn:feature_code":"PPL",
    "gn:name":"Waku",
    "gn:population":0,
    "gn:timezone":"Asia/Shanghai",
    "iso:country":"CN",
    "name:zho_x_preferred":[
        "\u6316\u82e6"
    ],
    "wof:name":"Waku",
    "wof:placetype":"locality"
},
  "geometry": {"coordinates":[102.878,28.7982],"type":"Point"}
}