{
  "type": "Feature",
  "properties": {
    "gn:admin1_code":"11.0",
    "gn:asciiname":"Longfengshan",
    "gn:country_code":"CN",
    "gn:dem":70,
    "gn:feature_class":"P",
    "gn:feature_code":"PPL",
    "gn:name":"Longfengshan",
    "gn:population":0,
    "gn:timezone":"Asia/Shanghai",
    "iso:country":"CN",
    "name:zho_x_preferred":[
        "\u9f99\u51e4\u5c71"
    ],
    "wof:name":"Longfengshan",
    "wof:placetype":"locality"
},
  "geometry": {"coordinates":[112.57281999999999,28.17958],"type":"Point"}
}