{
  "type": "Feature",
  "properties": {
    "gn:admin1_code":"19.0",
    "gn:asciiname":"Kangxiloucun",
    "gn:country_code":"CN",
    "gn:dem":57,
    "gn:feature_class":"P",
    "gn:feature_code":"PPL",
    "gn:name":"Kangxiloucun",
    "gn:population":0,
    "gn:timezone":"Asia/Shanghai",
    "iso:country":"CN",
    "name:zho_x_preferred":[
        "\u5eb7\u7199\u697c\u6751"
    ],
    "wof:name":"Kangxiloucun",
    "wof:placetype":"locality"
},
  "geometry": {"coordinates":[123.723,42.2796],"type":"Point"}
}