{
  "type": "Feature",
  "properties": {
    "gn:admin1_code":"25",
    "gn:asciiname":"Xiashipen",
    "gn:country_code":"CN",
    "gn:dem":227,
    "gn:feature_class":"P",
    "gn:feature_code":"PPL",
    "gn:name":"Xiashipen",
    "gn:population":0,
    "gn:timezone":"Asia/Shanghai",
    "iso:country":"CN",
    "name:zho_x_preferred":[
        "\u4e0b\u77f3\u76c6"
    ],
    "wof:name":"Xiashipen",
    "wof:placetype":"locality"
},
  "geometry": {"coordinates":[118.18300000000001,35.4066],"type":"Point"}
}