{
  "type": "Feature",
  "properties": {
    "gn:admin1_code":"24.0",
    "gn:asciiname":"Tanzhuangcun",
    "gn:country_code":"CN",
    "gn:dem":1028,
    "gn:feature_class":"P",
    "gn:feature_code":"PPL",
    "gn:name":"Tanzhuangcun",
    "gn:population":0,
    "gn:timezone":"Asia/Shanghai",
    "iso:country":"CN",
    "name:zho_x_preferred":[
        "\u8c2d\u5e84\u6751"
    ],
    "wof:name":"Tanzhuangcun",
    "wof:placetype":"locality"
},
  "geometry": {"coordinates":[110.79719,36.93773],"type":"Point"}
}