{
  "type": "Feature",
  "properties": {
    "gn:admin1_code":"5.0",
    "gn:asciiname":"Yaohaocun",
    "gn:country_code":"CN",
    "gn:dem":147,
    "gn:feature_class":"P",
    "gn:feature_code":"PPL",
    "gn:name":"Yaohaocun",
    "gn:population":0,
    "gn:timezone":"Asia/Shanghai",
    "iso:country":"CN",
    "name:zho_x_preferred":[
        "\u8170\u53f7\u6751"
    ],
    "wof:name":"Yaohaocun",
    "wof:placetype":"locality"
},
  "geometry": {"coordinates":[126.1532,45.08356],"type":"Point"}
}