{
  "type": "Feature",
  "properties": {
    "gn:admin1_code":"1.0",
    "gn:asciiname":"Jiangyangmiao",
    "gn:country_code":"CN",
    "gn:dem":14,
    "gn:feature_class":"P",
    "gn:feature_code":"PPL",
    "gn:name":"Jiangyangmiao",
    "gn:population":0,
    "gn:timezone":"Asia/Shanghai",
    "iso:country":"CN",
    "name:zho_x_preferred":[
        "\u6c5f\u6d0b\u5e99"
    ],
    "wof:name":"Jiangyangmiao",
    "wof:placetype":"locality"
},
  "geometry": {"coordinates":[118.14024000000001,31.14372],"type":"Point"}
}