{
  "type": "Feature",
  "properties": {
    "gn:admin1_code":"32.0",
    "gn:asciiname":"Lihehao",
    "gn:country_code":"CN",
    "gn:dem":315,
    "gn:feature_class":"P",
    "gn:feature_code":"PPL",
    "gn:name":"Lihehao",
    "gn:population":0,
    "gn:timezone":"Asia/Shanghai",
    "iso:country":"CN",
    "name:zho_x_preferred":[
        "\u5229\u548c\u53f7"
    ],
    "wof:name":"Lihehao",
    "wof:placetype":"locality"
},
  "geometry": {"coordinates":[104.98399999999999,29.3889],"type":"Point"}
}