{
  "type": "Feature",
  "properties": {
    "gn:admin1_code":"32.0",
    "gn:asciiname":"Yaojiagou",
    "gn:country_code":"CN",
    "gn:dem":559,
    "gn:feature_class":"P",
    "gn:feature_code":"PPL",
    "gn:name":"Yaojiagou",
    "gn:population":0,
    "gn:timezone":"Asia/Shanghai",
    "iso:country":"CN",
    "name:zho_x_preferred":[
        "\u59da\u5bb6\u6c9f"
    ],
    "wof:name":"Yaojiagou",
    "wof:placetype":"locality"
},
  "geometry": {"coordinates":[105.35257,32.27288],"type":"Point"}
}