{
  "type": "Feature",
  "properties": {
    "gn:admin1_code":"14.0",
    "gn:asciiname":"Kalongcun",
    "gn:country_code":"CN",
    "gn:dem":4005,
    "gn:feature_class":"P",
    "gn:feature_code":"PPL",
    "gn:name":"Kalongcun",
    "gn:population":0,
    "gn:timezone":"Asia/Urumqi",
    "iso:country":"CN",
    "name:zho_x_preferred":[
        "\u5361\u9f99\u6751"
    ],
    "wof:name":"Kalongcun",
    "wof:placetype":"locality"
},
  "geometry": {"coordinates":[97.12633,29.95609],"type":"Point"}
}