{
  "type": "Feature",
  "properties": {
    "gn:admin1_code":"9.0",
    "gn:asciiname":"Peizhuang",
    "gn:country_code":"CN",
    "gn:dem":99,
    "gn:feature_class":"P",
    "gn:feature_code":"PPL",
    "gn:name":"Peizhuang",
    "gn:population":0,
    "gn:timezone":"Asia/Shanghai",
    "iso:country":"CN",
    "name:zho_x_preferred":[
        "\u88f4\u5e84"
    ],
    "wof:name":"Peizhuang",
    "wof:placetype":"locality"
},
  "geometry": {"coordinates":[114.45247000000001,35.8205],"type":"Point"}
}