{
  "type": "Feature",
  "properties": {
    "gn:admin1_code":"19.0",
    "gn:asciiname":"Yulinbucun",
    "gn:country_code":"CN",
    "gn:dem":34,
    "gn:feature_class":"P",
    "gn:feature_code":"PPL",
    "gn:name":"Yulinbucun",
    "gn:population":0,
    "gn:timezone":"Asia/Shanghai",
    "iso:country":"CN",
    "name:zho_x_preferred":[
        "\u6986\u6797\u5821\u6751"
    ],
    "wof:name":"Yulinbucun",
    "wof:placetype":"locality"
},
  "geometry": {"coordinates":[122.289,40.3288],"type":"Point"}
}