{
  "type": "Feature",
  "properties": {
    "gn:admin1_code":"30.0",
    "gn:asciiname":"Niupitan",
    "gn:country_code":"CN",
    "gn:dem":73,
    "gn:feature_class":"P",
    "gn:feature_code":"PPL",
    "gn:name":"Niupitan",
    "gn:population":0,
    "gn:timezone":"Asia/Shanghai",
    "iso:country":"CN",
    "name:zho_x_preferred":[
        "\u725b\u76ae\u6ee9"
    ],
    "wof:name":"Niupitan",
    "wof:placetype":"locality"
},
  "geometry": {"coordinates":[111.40181,22.70903],"type":"Point"}
}