{
  "type": "Feature",
  "properties": {
    "gn:admin1_code":"09",
    "gn:asciiname":"Suzhuang",
    "gn:country_code":"CN",
    "gn:dem":88,
    "gn:feature_class":"P",
    "gn:feature_code":"PPL",
    "gn:name":"Suzhuang",
    "gn:population":0,
    "gn:timezone":"Asia/Shanghai",
    "iso:country":"CN",
    "name:und_x_variant":[
        "Hao-chuang",
        "Haozhuang",
        "Suzhuang"
    ],
    "name:zho_x_preferred":[
        "\u82cf\u5e84"
    ],
    "wof:name":"Suzhuang",
    "wof:placetype":"locality"
},
  "geometry": {"coordinates":[113.64807999999999,33.93729],"type":"Point"}
}