{
  "type": "Feature",
  "properties": {
    "gn:admin1_code":"14.0",
    "gn:asciiname":"Eke",
    "gn:country_code":"CN",
    "gn:dem":2625,
    "gn:feature_class":"P",
    "gn:feature_code":"PPL",
    "gn:name":"Eke",
    "gn:population":0,
    "gn:timezone":"Asia/Urumqi",
    "iso:country":"CN",
    "name:zho_x_preferred":[
        "\u4fc4\u79d1"
    ],
    "wof:name":"Eke",
    "wof:placetype":"locality"
},
  "geometry": {"coordinates":[97.91592,29.02049],"type":"Point"}
}