{
  "type": "Feature",
  "properties": {
    "gn:admin1_code":"18",
    "gn:asciiname":"Mulinyan",
    "gn:country_code":"CN",
    "gn:dem":971,
    "gn:feature_class":"P",
    "gn:feature_code":"PPL",
    "gn:name":"Mulinyan",
    "gn:population":0,
    "gn:timezone":"Asia/Shanghai",
    "iso:country":"CN",
    "name:zho_x_preferred":[
        "\u6728\u6797\u5ca9"
    ],
    "wof:name":"Mulinyan",
    "wof:placetype":"locality"
},
  "geometry": {"coordinates":[106.379,28.0912],"type":"Point"}
}