{
  "type": "Feature",
  "properties": {
    "gn:admin1_code":"11.0",
    "gn:asciiname":"Xianfan",
    "gn:country_code":"CN",
    "gn:dem":80,
    "gn:feature_class":"P",
    "gn:feature_code":"PPL",
    "gn:name":"Xianfan",
    "gn:population":0,
    "gn:timezone":"Asia/Shanghai",
    "iso:country":"CN",
    "name:zho_x_preferred":[
        "Xianfan"
    ],
    "name:zho_x_variant":[
        "\u663e\u51e1"
    ],
    "wof:name":"Xianfan",
    "wof:placetype":"locality"
},
  "geometry": {"coordinates":[111.42121000000002,29.17202],"type":"Point"}
}