{
  "type": "Feature",
  "properties": {
    "gn:admin1_code":"8.0",
    "gn:asciiname":"Qianfeng Gongqu",
    "gn:country_code":"CN",
    "gn:dem":408,
    "gn:feature_class":"P",
    "gn:feature_code":"PPLF",
    "gn:name":"Qianfeng Gongqu",
    "gn:population":0,
    "gn:timezone":"Asia/Shanghai",
    "iso:country":"CN",
    "name:zho_x_preferred":[
        "\u524d\u950b\u5de5\u533a"
    ],
    "wof:name":"Qianfeng Gongqu",
    "wof:placetype":"locality"
},
  "geometry": {"coordinates":[127.55551,47.96304],"type":"Point"}
}