{
  "type": "Feature",
  "properties": {
    "gn:admin1_code":"5.0",
    "gn:asciiname":"Shuanglongquancun",
    "gn:country_code":"CN",
    "gn:dem":169,
    "gn:feature_class":"P",
    "gn:feature_code":"PPL",
    "gn:name":"Shuanglongquancun",
    "gn:population":0,
    "gn:timezone":"Asia/Shanghai",
    "iso:country":"CN",
    "name:zho_x_preferred":[
        "\u53cc\u9f99\u6cc9\u6751"
    ],
    "wof:name":"Shuanglongquancun",
    "wof:placetype":"locality"
},
  "geometry": {"coordinates":[126.13409,45.03987],"type":"Point"}
}