{
  "type": "Feature",
  "properties": {
    "gn:admin1_code":"5.0",
    "gn:asciiname":"Longhecun",
    "gn:country_code":"CN",
    "gn:dem":317,
    "gn:feature_class":"P",
    "gn:feature_code":"PPL",
    "gn:name":"Longhecun",
    "gn:population":0,
    "gn:timezone":"Asia/Shanghai",
    "iso:country":"CN",
    "name:zho_x_preferred":[
        "\u9f99\u6cb3\u6751"
    ],
    "wof:name":"Longhecun",
    "wof:placetype":"locality"
},
  "geometry": {"coordinates":[125.7208,42.59199],"type":"Point"}
}