{
  "type": "Feature",
  "properties": {
    "gn:admin1_code":"4.0",
    "gn:asciiname":"Rongjia",
    "gn:country_code":"CN",
    "gn:dem":5,
    "gn:feature_class":"P",
    "gn:feature_code":"PPL",
    "gn:name":"Rongjia",
    "gn:population":0,
    "gn:timezone":"Asia/Shanghai",
    "iso:country":"CN",
    "name:zho_x_preferred":[
        "\u620e\u5bb6"
    ],
    "wof:name":"Rongjia",
    "wof:placetype":"locality"
},
  "geometry": {"coordinates":[119.82004000000001,32.08308],"type":"Point"}
}