{
  "type": "Feature",
  "properties": {
    "gn:admin1_code":"30",
    "gn:asciiname":"Chaolian",
    "gn:country_code":"CN",
    "gn:dem":15,
    "gn:feature_class":"P",
    "gn:feature_code":"PPLA4",
    "gn:name":"Chaolian",
    "gn:population":0,
    "gn:timezone":"Asia/Shanghai",
    "iso:country":"CN",
    "name:und_x_variant":[
        "Chaolian Jiedao",
        "\u6f6e\u8fde\u8857\u9053"
    ],
    "wof:name":"Chaolian",
    "wof:placetype":"locality"
},
  "geometry": {"coordinates":[113.11015999999999,22.63285],"type":"Point"}
}