{
  "type": "Feature",
  "properties": {
    "gn:admin1_code":"7.0",
    "gn:asciiname":"Huluping",
    "gn:country_code":"CN",
    "gn:dem":324,
    "gn:feature_class":"P",
    "gn:feature_code":"PPL",
    "gn:name":"Huluping",
    "gn:population":0,
    "gn:timezone":"Asia/Shanghai",
    "iso:country":"CN",
    "name:zho_x_preferred":[
        "\u6e56\u82a6\u576a"
    ],
    "wof:name":"Huluping",
    "wof:placetype":"locality"
},
  "geometry": {"coordinates":[116.64138,24.65982],"type":"Point"}
}