{
  "type": "Feature",
  "properties": {
    "gn:admin1_code":"14.0",
    "gn:asciiname":"Gyaqung",
    "gn:country_code":"CN",
    "gn:dem":4094,
    "gn:feature_class":"P",
    "gn:feature_code":"PPLF",
    "gn:name":"Gyaqung",
    "gn:population":0,
    "gn:timezone":"Asia/Urumqi",
    "iso:country":"CN",
    "name:bod_x_preferred":[
        "Gyaqung"
    ],
    "name:zho_x_preferred":[
        "Jiaqiong"
    ],
    "name:zho_x_variant":[
        "\u7532\u7a77"
    ],
    "wof:name":"Gyaqung",
    "wof:placetype":"locality"
},
  "geometry": {"coordinates":[88.501,29.101],"type":"Point"}
}