{
  "type": "Feature",
  "properties": {
    "gn:admin1_code":"19.0",
    "gn:asciiname":"Hanchengcun",
    "gn:country_code":"CN",
    "gn:dem":40,
    "gn:feature_class":"P",
    "gn:feature_code":"PPL",
    "gn:name":"Hanchengcun",
    "gn:population":0,
    "gn:timezone":"Asia/Shanghai",
    "iso:country":"CN",
    "name:und_x_variant":[
        "Hanchengbao",
        "Hanchengbu"
    ],
    "name:zho_x_preferred":[
        "\u97e9\u57ce\u6751"
    ],
    "name:zho_x_variant":[
        "\u97e9\u6210\u5821"
    ],
    "wof:name":"Hanchengcun",
    "wof:placetype":"locality"
},
  "geometry": {"coordinates":[123.364,41.6182],"type":"Point"}
}