{
  "type": "Feature",
  "properties": {
    "gn:admin1_code":"29",
    "gn:asciiname":"Heqi",
    "gn:country_code":"CN",
    "gn:dem":1890,
    "gn:feature_class":"P",
    "gn:feature_code":"PPL",
    "gn:name":"Heqi",
    "gn:population":0,
    "gn:timezone":"Asia/Shanghai",
    "iso:country":"CN",
    "name:und_x_variant":[
        "\u4f55\u65d7"
    ],
    "wof:name":"Heqi",
    "wof:placetype":"locality"
},
  "geometry": {"coordinates":[103.80417,25.42789],"type":"Point"}
}