{
  "type": "Feature",
  "properties": {
    "gn:admin1_code":"15.0",
    "gn:asciiname":"Wenquanli",
    "gn:country_code":"CN",
    "gn:dem":2180,
    "gn:feature_class":"P",
    "gn:feature_code":"PPL",
    "gn:name":"Wenquanli",
    "gn:population":0,
    "gn:timezone":"Asia/Shanghai",
    "iso:country":"CN",
    "name:zho_x_preferred":[
        "\u6e29\u6cc9\u91cc"
    ],
    "wof:name":"Wenquanli",
    "wof:placetype":"locality"
},
  "geometry": {"coordinates":[104.492,35.5553],"type":"Point"}
}