{
  "type": "Feature",
  "properties": {
    "gn:admin1_code":"3.0",
    "gn:asciiname":"Pailoudi",
    "gn:country_code":"CN",
    "gn:dem":58,
    "gn:feature_class":"P",
    "gn:feature_code":"PPL",
    "gn:name":"Pailoudi",
    "gn:population":0,
    "gn:timezone":"Asia/Shanghai",
    "iso:country":"CN",
    "name:zho_x_preferred":[
        "\u724c\u697c\u5e95"
    ],
    "wof:name":"Pailoudi",
    "wof:placetype":"locality"
},
  "geometry": {"coordinates":[117.22243,28.48784],"type":"Point"}
}