{
  "type": "Feature",
  "properties": {
    "gn:admin1_code":"12.0",
    "gn:asciiname":"Qingyanggang",
    "gn:country_code":"CN",
    "gn:dem":38,
    "gn:feature_class":"P",
    "gn:feature_code":"PPL",
    "gn:name":"Qingyanggang",
    "gn:population":0,
    "gn:timezone":"Asia/Shanghai",
    "iso:country":"CN",
    "name:zho_x_preferred":[
        "\u9752\u7f8a\u5c97"
    ],
    "wof:name":"Qingyanggang",
    "wof:placetype":"locality"
},
  "geometry": {"coordinates":[112.03752,30.12533],"type":"Point"}
}