{
  "type": "Feature",
  "properties": {
    "gn:admin1_code":"29.0",
    "gn:asciiname":"Gantianwu",
    "gn:country_code":"CN",
    "gn:dem":2095,
    "gn:feature_class":"P",
    "gn:feature_code":"PPL",
    "gn:name":"Gantianwu",
    "gn:population":0,
    "gn:timezone":"Asia/Shanghai",
    "iso:country":"CN",
    "name:zho_x_preferred":[
        "\u5e72\u5929\u5c4b"
    ],
    "wof:name":"Gantianwu",
    "wof:placetype":"locality"
},
  "geometry": {"coordinates":[99.416,26.224],"type":"Point"}
}