{
  "type": "Feature",
  "properties": {
    "gn:admin1_code":"15.0",
    "gn:asciiname":"Dongfeng Nongchang",
    "gn:country_code":"CN",
    "gn:dem":1096,
    "gn:feature_class":"P",
    "gn:feature_code":"PPLF",
    "gn:name":"Dongfeng Nongchang",
    "gn:population":0,
    "gn:timezone":"Asia/Urumqi",
    "iso:country":"CN",
    "name:zho_x_preferred":[
        "\u4e1c\u98ce\u519c\u573a"
    ],
    "wof:name":"Dongfeng Nongchang",
    "wof:placetype":"locality"
},
  "geometry": {"coordinates":[94.81927,40.22535],"type":"Point"}
}