{
  "type": "Feature",
  "properties": {
    "gn:admin1_code":"9.0",
    "gn:asciiname":"Huanglianshu",
    "gn:country_code":"CN",
    "gn:dem":178,
    "gn:feature_class":"P",
    "gn:feature_code":"PPL",
    "gn:name":"Huanglianshu",
    "gn:population":0,
    "gn:timezone":"Asia/Shanghai",
    "iso:country":"CN",
    "name:zho_x_preferred":[
        "\u9ec4\u695d\u6811"
    ],
    "wof:name":"Huanglianshu",
    "wof:placetype":"locality"
},
  "geometry": {"coordinates":[111.31999999999999,32.98033],"type":"Point"}
}