{
  "type": "Feature",
  "properties": {
    "gn:admin1_code":"20.0",
    "gn:asciiname":"Maorentaolegai",
    "gn:country_code":"CN",
    "gn:dem":980,
    "gn:feature_class":"P",
    "gn:feature_code":"PPL",
    "gn:name":"Maorentaolegai",
    "gn:population":0,
    "gn:timezone":"Asia/Shanghai",
    "iso:country":"CN",
    "name:zho_x_preferred":[
        "\u6bdb\u4ec1\u9676\u52d2\u76d6"
    ],
    "wof:name":"Maorentaolegai",
    "wof:placetype":"locality"
},
  "geometry": {"coordinates":[100.97221,41.53131],"type":"Point"}
}