{
  "type": "Feature",
  "properties": {
    "gn:admin1_code":"8.0",
    "gn:asciiname":"Dongdiyingzi",
    "gn:country_code":"CN",
    "gn:dem":140,
    "gn:feature_class":"P",
    "gn:feature_code":"PPL",
    "gn:name":"Dongdiyingzi",
    "gn:population":0,
    "gn:timezone":"Asia/Shanghai",
    "iso:country":"CN",
    "name:zho_x_preferred":[
        "\u4e1c\u5730\u8425\u5b50"
    ],
    "wof:name":"Dongdiyingzi",
    "wof:placetype":"locality"
},
  "geometry": {"coordinates":[128.29858999999999,49.45812],"type":"Point"}
}