{
  "type": "Feature",
  "properties": {
    "gn:admin1_code":"11",
    "gn:asciiname":"Niqiutang",
    "gn:country_code":"CN",
    "gn:dem":110,
    "gn:feature_class":"P",
    "gn:feature_code":"PPL",
    "gn:name":"Niqiutang",
    "gn:population":0,
    "gn:timezone":"Asia/Shanghai",
    "iso:country":"CN",
    "name:zho_x_preferred":[
        "\u6ce5\u79cb\u5858"
    ],
    "wof:name":"Niqiutang",
    "wof:placetype":"locality"
},
  "geometry": {"coordinates":[112.31609,26.41445],"type":"Point"}
}