{
  "type": "Feature",
  "properties": {
    "gn:admin1_code":"30",
    "gn:asciiname":"Jinkengtian",
    "gn:country_code":"CN",
    "gn:dem":120,
    "gn:feature_class":"P",
    "gn:feature_code":"PPL",
    "gn:name":"Jinkengtian",
    "gn:population":0,
    "gn:timezone":"Asia/Shanghai",
    "iso:country":"CN",
    "name:zho_x_preferred":[
        "\u91d1\u5751\u7530"
    ],
    "wof:name":"Jinkengtian",
    "wof:placetype":"locality"
},
  "geometry": {"coordinates":[111.87367999999999,22.21863],"type":"Point"}
}