{
  "type": "Feature",
  "properties": {
    "gn:admin1_code":"8.0",
    "gn:asciiname":"Akebielidou",
    "gn:country_code":"CN",
    "gn:dem":506,
    "gn:feature_class":"P",
    "gn:feature_code":"PPLA4",
    "gn:name":"Akebielidou",
    "gn:population":0,
    "gn:timezone":"Asia/Urumqi",
    "iso:country":"CN",
    "name:und_x_variant":[
        "Akebielidou Xiang"
    ],
    "name:zho_x_preferred":[
        "\u963f\u514b\u522b\u91cc\u6597"
    ],
    "name:zho_x_variant":[
        "\u963f\u514b\u522b\u91cc\u6597\u4e61"
    ],
    "wof:name":"Akebielidou",
    "wof:placetype":"locality"
},
  "geometry": {"coordinates":[83.43329,46.21659],"type":"Point"}
}