{
  "type": "Feature",
  "properties": {
    "gn:admin1_code":"29.0",
    "gn:asciiname":"Tanggu",
    "gn:country_code":"CN",
    "gn:dem":2754,
    "gn:feature_class":"P",
    "gn:feature_code":"PPL",
    "gn:name":"Tanggu",
    "gn:population":0,
    "gn:timezone":"Asia/Shanghai",
    "iso:country":"CN",
    "name:zho_x_preferred":[
        "\u5858\u53e4"
    ],
    "wof:name":"Tanggu",
    "wof:placetype":"locality"
},
  "geometry": {"coordinates":[100.07899999999999,27.9412],"type":"Point"}
}