{
  "type": "Feature",
  "properties": {
    "gn:admin1_code":"3",
    "gn:asciiname":"Huang'anxu",
    "gn:country_code":"CN",
    "gn:dem":194,
    "gn:feature_class":"P",
    "gn:feature_code":"PPL",
    "gn:name":"Huang\u2019anxu",
    "gn:population":0,
    "gn:timezone":"Asia/Shanghai",
    "iso:country":"CN",
    "name:und_x_variant":[
        "Huang\u2019anxu",
        "\u9ec4\u5b89\u5729"
    ],
    "wof:name":"Huang'anxu",
    "wof:placetype":"locality"
},
  "geometry": {"coordinates":[115.83767,25.82451],"type":"Point"}
}