{
  "type": "Feature",
  "properties": {
    "gn:admin1_code":"30.0",
    "gn:asciiname":"Liantiancun",
    "gn:country_code":"CN",
    "gn:dem":0,
    "gn:feature_class":"P",
    "gn:feature_code":"PPL",
    "gn:name":"Liantiancun",
    "gn:population":0,
    "gn:timezone":"Asia/Shanghai",
    "iso:country":"CN",
    "name:zho_x_preferred":[
        "\u8054\u7530\u6751"
    ],
    "wof:name":"Liantiancun",
    "wof:placetype":"locality"
},
  "geometry": {"coordinates":[115.28131,22.93782],"type":"Point"}
}