{
  "type": "Feature",
  "properties": {
    "gn:admin1_code":"5.0",
    "gn:asciiname":"Liutiaogoucun",
    "gn:country_code":"CN",
    "gn:dem":418,
    "gn:feature_class":"P",
    "gn:feature_code":"PPL",
    "gn:name":"Liutiaogoucun",
    "gn:population":0,
    "gn:timezone":"Asia/Shanghai",
    "iso:country":"CN",
    "name:zho_x_preferred":[
        "\u67f3\u6761\u6c9f\u6751"
    ],
    "wof:name":"Liutiaogoucun",
    "wof:placetype":"locality"
},
  "geometry": {"coordinates":[125.93472,41.73502],"type":"Point"}
}