{
  "type": "Feature",
  "properties": {
    "gn:admin1_code":"26.0",
    "gn:asciiname":"Hansicun",
    "gn:country_code":"CN",
    "gn:dem":771,
    "gn:feature_class":"P",
    "gn:feature_code":"PPL",
    "gn:name":"Hansicun",
    "gn:population":0,
    "gn:timezone":"Asia/Shanghai",
    "iso:country":"CN",
    "name:und_x_variant":[
        "\u97e9\u5bfa\u6751"
    ],
    "wof:name":"Hansicun",
    "wof:placetype":"locality"
},
  "geometry": {"coordinates":[109.28804,34.10095],"type":"Point"}
}