{
  "type": "Feature",
  "properties": {
    "gn:admin1_code":"15.0",
    "gn:asciiname":"Lujiawan",
    "gn:country_code":"CN",
    "gn:dem":1741,
    "gn:feature_class":"P",
    "gn:feature_code":"PPL",
    "gn:name":"Lujiawan",
    "gn:population":0,
    "gn:timezone":"Asia/Shanghai",
    "iso:country":"CN",
    "name:und_x_variant":[
        "\u82a6\u5bb6\u6e7e"
    ],
    "wof:name":"Lujiawan",
    "wof:placetype":"locality"
},
  "geometry": {"coordinates":[106.6199,36.34669],"type":"Point"}
}