{
  "type": "Feature",
  "properties": {
    "gn:admin1_code":"4.0",
    "gn:asciiname":"Chenghuangtan",
    "gn:country_code":"CN",
    "gn:dem":3,
    "gn:feature_class":"P",
    "gn:feature_code":"PPL",
    "gn:name":"Chenghuangtan",
    "gn:population":0,
    "gn:timezone":"Asia/Shanghai",
    "iso:country":"CN",
    "name:zho_x_preferred":[
        "\u57ce\u968d\u6f6d"
    ],
    "wof:name":"Chenghuangtan",
    "wof:placetype":"locality"
},
  "geometry": {"coordinates":[120.99724000000001,31.48777],"type":"Point"}
}