{
  "type": "Feature",
  "properties": {
    "gn:admin1_code":"26",
    "gn:asciiname":"Fangjiahe",
    "gn:country_code":"CN",
    "gn:dem":788,
    "gn:feature_class":"P",
    "gn:feature_code":"PPL",
    "gn:name":"Fangjiahe",
    "gn:population":0,
    "gn:timezone":"Asia/Shanghai",
    "iso:country":"CN",
    "name:zho_x_preferred":[
        "\u623f\u5bb6\u6cb3"
    ],
    "wof:name":"Fangjiahe",
    "wof:placetype":"locality"
},
  "geometry": {"coordinates":[109.19504000000001,34.32727],"type":"Point"}
}