{
  "type": "Feature",
  "properties": {
    "gn:admin1_code":"30",
    "gn:asciiname":"Qilingshan",
    "gn:country_code":"CN",
    "gn:dem":204,
    "gn:feature_class":"P",
    "gn:feature_code":"PPL",
    "gn:name":"Qilingshan",
    "gn:population":0,
    "gn:timezone":"Asia/Shanghai",
    "iso:country":"CN",
    "name:zho_x_preferred":[
        "\u5c90\u5cad\u5c71"
    ],
    "wof:name":"Qilingshan",
    "wof:placetype":"locality"
},
  "geometry": {"coordinates":[115.61494,24.4164],"type":"Point"}
}