{
  "type": "Feature",
  "properties": {
    "gn:admin1_code":"11",
    "gn:asciiname":"Jinlansi",
    "gn:cc2":"CN",
    "gn:country_code":"CN",
    "gn:dem":130,
    "gn:feature_class":"P",
    "gn:feature_code":"PPL",
    "gn:name":"Jinlansi",
    "gn:population":0,
    "gn:timezone":"Asia/Shanghai",
    "iso:country":"CN",
    "name:und_x_variant":[
        "Chin-lan-ssu",
        "Kinlanshih",
        "Chin-lan-shih",
        "Jinlansi"
    ],
    "wof:name":"Jinlansi",
    "wof:placetype":"locality"
},
  "geometry": {"coordinates":[112.0925,27.125],"type":"Point"}
}