{
  "type": "Feature",
  "properties": {
    "gn:admin1_code":"23.0",
    "gn:asciiname":"Xiasanxing",
    "gn:country_code":"CN",
    "gn:dem":6,
    "gn:feature_class":"P",
    "gn:feature_code":"PPL",
    "gn:name":"Xiasanxing",
    "gn:population":0,
    "gn:timezone":"Asia/Shanghai",
    "iso:country":"CN",
    "name:und_x_variant":[
        "Hsia-san-hsing-chen",
        "San-hsing-chen",
        "Xiasanxing",
        "\u4e0b\u4e09\u661f"
    ],
    "wof:name":"Xiasanxing",
    "wof:placetype":"locality"
},
  "geometry": {"coordinates":[121.44887,31.65882],"type":"Point"}
}