{
  "type": "Feature",
  "properties": {
    "gn:admin1_code":"16.0",
    "gn:asciiname":"Danwu",
    "gn:country_code":"CN",
    "gn:dem":92,
    "gn:feature_class":"P",
    "gn:feature_code":"PPL",
    "gn:name":"Danwu",
    "gn:population":0,
    "gn:timezone":"Asia/Shanghai",
    "iso:country":"CN",
    "name:zho_x_preferred":[
        "\u6de1\u5c4b"
    ],
    "wof:name":"Danwu",
    "wof:placetype":"locality"
},
  "geometry": {"coordinates":[109.15000000000001,22.1975],"type":"Point"}
}