{
  "type": "Feature",
  "properties": {
    "gn:admin1_code":"3.0",
    "gn:asciiname":"Jinyitang",
    "gn:country_code":"CN",
    "gn:dem":650,
    "gn:feature_class":"P",
    "gn:feature_code":"PPL",
    "gn:name":"Jinyitang",
    "gn:population":0,
    "gn:timezone":"Asia/Shanghai",
    "iso:country":"CN",
    "name:und_x_variant":[
        "\u9526\u8863\u5802"
    ],
    "wof:name":"Jinyitang",
    "wof:placetype":"locality"
},
  "geometry": {"coordinates":[115.4011,26.5645],"type":"Point"}
}