{
  "type": "Feature",
  "properties": {
    "gn:admin1_code":"1.0",
    "gn:asciiname":"Citanghe",
    "gn:country_code":"CN",
    "gn:dem":39,
    "gn:feature_class":"P",
    "gn:feature_code":"PPL",
    "gn:name":"Citanghe",
    "gn:population":0,
    "gn:timezone":"Asia/Shanghai",
    "iso:country":"CN",
    "name:zho_x_preferred":[
        "\u7960\u5802\u4f55"
    ],
    "wof:name":"Citanghe",
    "wof:placetype":"locality"
},
  "geometry": {"coordinates":[118.38388,31.88266],"type":"Point"}
}