{
  "type": "Feature",
  "properties": {
    "gn:admin1_code":"30",
    "gn:asciiname":"Dali",
    "gn:country_code":"CN",
    "gn:dem":0,
    "gn:feature_class":"P",
    "gn:feature_code":"PPLA4",
    "gn:name":"Dali",
    "gn:population":0,
    "gn:timezone":"Asia/Shanghai",
    "iso:country":"CN",
    "name:ara_x_preferred":[
        "\u062f\u0627\u0644\u064a"
    ],
    "name:ben_x_preferred":[
        "\u09a6\u09be\u09b2\u09bf"
    ],
    "name:deu_x_preferred":[
        "Dali"
    ],
    "name:ell_x_preferred":[
        "\u039d\u03c4\u03b1\u03bb\u03af"
    ],
    "name:eng_x_preferred":[
        "Dali"
    ],
    "name:fas_x_preferred":[
        "\u062f\u0627\u0644\u06cc"
    ],
    "name:fra_x_preferred":[
        "Dali"
    ],
    "name:heb_x_preferred":[
        "\u05d3\u05d0\u05dc\u05d9"
    ],
    "name:hin_x_preferred":[
        "\u0921\u0948\u0932\u0940"
    ],
    "name:hun_x_preferred":[
        "Dali"
    ],
    "name:ind_x_preferred":[
        "Dali"
    ],
    "name:ita_x_preferred":[
        "Dali"
    ],
    "name:jpn_x_preferred":[
        "\u5927\u7406\u5ddd"
    ],
    "name:kor_x_preferred":[
        "\ub2ec\ub9ac"
    ],
    "name:nld_x_preferred":[
        "Dali"
    ],
    "name:nor_x_preferred":[
        "Dali"
    ],
    "name:pol_x_preferred":[
        "Dali"
    ],
    "name:por_x_preferred":[
        "Dali"
    ],
    "name:rus_x_preferred":[
        "\u0440\u0435\u043a\u0430 \u0414\u0430\u043b\u0438"
    ],
    "name:spa_x_preferred":[
        "Dali"
    ],
    "name:swe_x_preferred":[
        "Dali"
    ],
    "name:tur_x_preferred":[
        "Dali"
    ],
    "name:ukr_x_preferred":[
        "\u0414\u0430\u043b\u0456"
    ],
    "name:und_x_variant":[
        "Dalijieban"
    ],
    "name:urd_x_preferred":[
        "\u0688\u0627\u0644\u06cc"
    ],
    "name:vie_x_preferred":[
        "S\u00f4ng Dali"
    ],
    "name:zho_cn_x_preferred":[
        "\u5927\u91cc\u6eaa"
    ],
    "name:zho_tw_x_preferred":[
        "\u5927\u7406\u6cb3"
    ],
    "name:zho_x_preferred":[
        "\u5927\u6ca5"
    ],
    "name:zho_x_variant":[
        "\u5927\u6ca5\u9547"
    ],
    "wof:name":"Dali",
    "wof:placetype":"locality"
},
  "geometry": {"coordinates":[113.11673,23.11974],"type":"Point"}
}