{
  "type": "Feature",
  "properties": {
    "gn:admin1_code":"30",
    "gn:asciiname":"Dali",
    "gn:country_code":"CN",
    "gn:dem":0,
    "gn:feature_class":"P",
    "gn:feature_code":"PPLA4",
    "gn:name":"Dali",
    "gn:population":0,
    "gn:timezone":"Asia/Shanghai",
    "iso:country":"CN",
    "name:fas_x_preferred":[
        "\u062f\u0627\u0644\u06cc"
    ],
    "name:nor_x_preferred":[
        "Dali"
    ],
    "name:und_x_variant":[
        "Dalijieban"
    ],
    "name:zho_x_preferred":[
        "\u5927\u6ca5"
    ],
    "name:zho_x_variant":[
        "\u5927\u6ca5\u9547"
    ],
    "wof:name":"Dali",
    "wof:placetype":"locality"
},
  "geometry": {"coordinates":[113.11673,23.11974],"type":"Point"}
}