{
  "type": "Feature",
  "properties": {
    "gn:admin1_code":"5.0",
    "gn:asciiname":"Daying Chengzicun",
    "gn:country_code":"CN",
    "gn:dem":225,
    "gn:feature_class":"P",
    "gn:feature_code":"PPL",
    "gn:name":"Daying Chengzicun",
    "gn:population":0,
    "gn:timezone":"Asia/Shanghai",
    "iso:country":"CN",
    "name:zho_x_preferred":[
        "\u5927\u8425\u57ce\u5b50\u6751"
    ],
    "wof:name":"Daying Chengzicun",
    "wof:placetype":"locality"
},
  "geometry": {"coordinates":[125.97658,43.89817],"type":"Point"}
}