{
  "type": "Feature",
  "properties": {
    "gn:admin1_code":"19.0",
    "gn:asciiname":"Laolongtan",
    "gn:country_code":"CN",
    "gn:dem":494,
    "gn:feature_class":"P",
    "gn:feature_code":"PPL",
    "gn:name":"Laolongtan",
    "gn:population":0,
    "gn:timezone":"Asia/Shanghai",
    "iso:country":"CN",
    "name:zho_x_preferred":[
        "\u8001\u9f99\u6ee9"
    ],
    "wof:name":"Laolongtan",
    "wof:placetype":"locality"
},
  "geometry": {"coordinates":[124.66754,41.62262],"type":"Point"}
}