{
  "type": "Feature",
  "properties": {
    "gn:admin1_code":"7.0",
    "gn:asciiname":"Yungui",
    "gn:country_code":"CN",
    "gn:dem":287,
    "gn:feature_class":"P",
    "gn:feature_code":"PPL",
    "gn:name":"Yungui",
    "gn:population":0,
    "gn:timezone":"Asia/Shanghai",
    "iso:country":"CN",
    "name:zho_x_preferred":[
        "\u4e91\u8d35"
    ],
    "wof:name":"Yungui",
    "wof:placetype":"locality"
},
  "geometry": {"coordinates":[117.89561999999999,25.39625],"type":"Point"}
}