{
  "type": "Feature",
  "properties": {
    "gn:admin1_code":"32.0",
    "gn:asciiname":"Tangduo",
    "gn:country_code":"CN",
    "gn:dem":3289,
    "gn:feature_class":"P",
    "gn:feature_code":"PPL",
    "gn:name":"Tangduo",
    "gn:population":0,
    "gn:timezone":"Asia/Shanghai",
    "iso:country":"CN",
    "name:zho_x_preferred":[
        "\u5510\u591a"
    ],
    "wof:name":"Tangduo",
    "wof:placetype":"locality"
},
  "geometry": {"coordinates":[100.60599999999999,29.0867],"type":"Point"}
}