{
  "type": "Feature",
  "properties": {
    "gn:admin1_code":"12.0",
    "gn:asciiname":"Lijiahekan",
    "gn:country_code":"CN",
    "gn:dem":431,
    "gn:feature_class":"P",
    "gn:feature_code":"PPL",
    "gn:name":"Lijiahekan",
    "gn:population":0,
    "gn:timezone":"Asia/Shanghai",
    "iso:country":"CN",
    "name:zho_x_preferred":[
        "\u674e\u5bb6\u6cb3\u574e"
    ],
    "wof:name":"Lijiahekan",
    "wof:placetype":"locality"
},
  "geometry": {"coordinates":[110.08916000000001,32.21777],"type":"Point"}
}