{
  "type": "Feature",
  "properties": {
    "gn:admin1_code":"26.0",
    "gn:asciiname":"Shimiaoliangcun",
    "gn:country_code":"CN",
    "gn:dem":1090,
    "gn:feature_class":"P",
    "gn:feature_code":"PPL",
    "gn:name":"Shimiaoliangcun",
    "gn:population":0,
    "gn:timezone":"Asia/Shanghai",
    "iso:country":"CN",
    "name:zho_x_preferred":[
        "\u77f3\u5e99\u6881\u6751"
    ],
    "wof:name":"Shimiaoliangcun",
    "wof:placetype":"locality"
},
  "geometry": {"coordinates":[110.8438,38.9361],"type":"Point"}
}