{
  "type": "Feature",
  "properties": {
    "gn:admin1_code":"2.0",
    "gn:asciiname":"Lu'ao",
    "gn:country_code":"CN",
    "gn:dem":1077,
    "gn:feature_class":"P",
    "gn:feature_code":"PPL",
    "gn:name":"Lu\u2019ao",
    "gn:population":0,
    "gn:timezone":"Asia/Shanghai",
    "iso:country":"CN",
    "name:und_x_variant":[
        "\u7089\u5c99"
    ],
    "name:zho_x_preferred":[
        "Lu\u2019ao"
    ],
    "wof:name":"Lu'ao",
    "wof:placetype":"locality"
},
  "geometry": {"coordinates":[119.19271000000001,27.92305],"type":"Point"}
}