{
  "type": "Feature",
  "properties": {
    "gn:admin1_code":"23",
    "gn:asciiname":"Zhuqiao",
    "gn:country_code":"CN",
    "gn:dem":4,
    "gn:feature_class":"P",
    "gn:feature_code":"PPL",
    "gn:name":"Zhuqiao",
    "gn:population":0,
    "gn:timezone":"Asia/Shanghai",
    "iso:country":"CN",
    "name:und_x_variant":[
        "Chu-ch\u2019iao",
        "Zhuqiao",
        "\u6d19\u6865"
    ],
    "wof:name":"Zhuqiao",
    "wof:placetype":"locality"
},
  "geometry": {"coordinates":[121.10652,30.96938],"type":"Point"}
}