{
  "type": "Feature",
  "properties": {
    "gn:admin1_code":"07",
    "gn:asciiname":"Jinguotou",
    "gn:country_code":"CN",
    "gn:dem":79,
    "gn:feature_class":"P",
    "gn:feature_code":"PPL",
    "gn:name":"Jinguotou",
    "gn:population":0,
    "gn:timezone":"Asia/Shanghai",
    "iso:country":"CN",
    "name:zho_x_preferred":[
        "\u91d1\u679c\u5934"
    ],
    "wof:name":"Jinguotou",
    "wof:placetype":"locality"
},
  "geometry": {"coordinates":[118.51895,25.2043],"type":"Point"}
}