{
  "type": "Feature",
  "properties": {
    "gn:admin1_code":"33.0",
    "gn:asciiname":"Minfu",
    "gn:country_code":"CN",
    "gn:dem":856,
    "gn:feature_class":"P",
    "gn:feature_code":"PPL",
    "gn:name":"Minfu",
    "gn:population":0,
    "gn:timezone":"Asia/Shanghai",
    "iso:country":"CN",
    "name:zho_x_preferred":[
        "\u6c11\u798f"
    ],
    "wof:name":"Minfu",
    "wof:placetype":"locality"
},
  "geometry": {"coordinates":[108.73781,31.90481],"type":"Point"}
}