{
  "type": "Feature",
  "properties": {
    "gn:admin1_code":"14.0",
    "gn:asciiname":"Damudanga",
    "gn:country_code":"CN",
    "gn:dem":4777,
    "gn:feature_class":"P",
    "gn:feature_code":"PPL",
    "gn:name":"Damudanga",
    "gn:population":0,
    "gn:timezone":"Asia/Urumqi",
    "iso:country":"CN",
    "name:zho_x_preferred":[
        "\u8fbe\u6728\u5355\u560e"
    ],
    "wof:name":"Damudanga",
    "wof:placetype":"locality"
},
  "geometry": {"coordinates":[93.56028000000001,29.64073],"type":"Point"}
}