{
  "type": "Feature",
  "properties": {
    "gn:admin1_code":"12.0",
    "gn:asciiname":"Wayaochong",
    "gn:country_code":"CN",
    "gn:dem":361,
    "gn:feature_class":"P",
    "gn:feature_code":"PPL",
    "gn:name":"Wayaochong",
    "gn:population":0,
    "gn:timezone":"Asia/Shanghai",
    "iso:country":"CN",
    "name:zho_x_preferred":[
        "\u74e6\u7a91\u51b2"
    ],
    "wof:name":"Wayaochong",
    "wof:placetype":"locality"
},
  "geometry": {"coordinates":[111.71272,31.15573],"type":"Point"}
}