{
  "type": "Feature",
  "properties": {
    "gn:admin1_code":"29.0",
    "gn:asciiname":"Yuwang Pingzhai",
    "gn:country_code":"CN",
    "gn:dem":1075,
    "gn:feature_class":"P",
    "gn:feature_code":"PPL",
    "gn:name":"Yuwang Pingzhai",
    "gn:population":0,
    "gn:timezone":"Asia/Shanghai",
    "iso:country":"CN",
    "name:zho_x_preferred":[
        "\u79b9\u738b\u5e73\u5be8"
    ],
    "wof:name":"Yuwang Pingzhai",
    "wof:placetype":"locality"
},
  "geometry": {"coordinates":[103.97799999999999,24.3694],"type":"Point"}
}