{
  "type": "Feature",
  "properties": {
    "gn:admin1_code":"3.0",
    "gn:asciiname":"Dengban Shijia",
    "gn:country_code":"CN",
    "gn:dem":202,
    "gn:feature_class":"P",
    "gn:feature_code":"PPL",
    "gn:name":"Dengban Shijia",
    "gn:population":0,
    "gn:timezone":"Asia/Shanghai",
    "iso:country":"CN",
    "name:und_x_variant":[
        "\u9093\u5742\u77f3\u5bb6"
    ],
    "wof:name":"Dengban Shijia",
    "wof:placetype":"locality"
},
  "geometry": {"coordinates":[115.46464,27.04996],"type":"Point"}
}