{
  "type": "Feature",
  "properties": {
    "iso:country":"CN",
    "name:eng_x_preferred":[
        "Hunyuan"
    ],
    "name:zho_x_preferred":[
        "\u6d51\u6e90\u53bf"
    ],
    "qs:name":"\u6d51\u6e90\u53bf",
    "qs:name_adm0":"\u4e2d\u570b",
    "qs:name_adm1":"\u5c71\u897f\u7701",
    "qs:photos":182,
    "qs:photos_1k":37,
    "qs:photos_9k":2,
    "qs:photos_9r":5,
    "qs:photos_all":351,
    "qs:photos_sr":4,
    "qs:placetype":"LocalAdmin",
    "qs:pop_sr":"0",
    "wof:name":"Hunyuan",
    "wof:placetype":"localadmin"
},
  "geometry": {"coordinates":[113.709194,39.660041],"type":"Point"}
}