{
  "type": "Feature",
  "properties": {
    "gn:admin1_code":"11",
    "gn:asciiname":"Xiegongtan",
    "gn:country_code":"CN",
    "gn:dem":193,
    "gn:feature_class":"P",
    "gn:feature_code":"PPL",
    "gn:name":"Xiegongtan",
    "gn:population":0,
    "gn:timezone":"Asia/Shanghai",
    "iso:country":"CN",
    "name:zho_x_preferred":[
        "\u8c22\u516c\u6ee9"
    ],
    "wof:name":"Xiegongtan",
    "wof:placetype":"locality"
},
  "geometry": {"coordinates":[111.32702,27.72784],"type":"Point"}
}