{
  "type": "Feature",
  "properties": {
    "gn:admin1_code":"32.0",
    "gn:asciiname":"Gawa",
    "gn:country_code":"CN",
    "gn:dem":2746,
    "gn:feature_class":"P",
    "gn:feature_code":"PPL",
    "gn:name":"Gawa",
    "gn:population":0,
    "gn:timezone":"Asia/Shanghai",
    "iso:country":"CN",
    "name:bar_x_preferred":[
        "Gawa"
    ],
    "name:ceb_x_preferred":[
        "Gawa"
    ],
    "name:swe_x_preferred":[
        "Gawa"
    ],
    "name:zho_x_preferred":[
        "\u560e\u54c7"
    ],
    "wof:name":"Gawa",
    "wof:placetype":"locality"
},
  "geometry": {"coordinates":[103.346,33.6745],"type":"Point"}
}