{
  "type": "Feature",
  "properties": {
    "gn:admin1_code":"5.0",
    "gn:asciiname":"Shengmingcun",
    "gn:country_code":"CN",
    "gn:dem":182,
    "gn:feature_class":"P",
    "gn:feature_code":"PPL",
    "gn:name":"Shengmingcun",
    "gn:population":0,
    "gn:timezone":"Asia/Shanghai",
    "iso:country":"CN",
    "name:zho_x_preferred":[
        "\u80dc\u660e\u6751"
    ],
    "wof:name":"Shengmingcun",
    "wof:placetype":"locality"
},
  "geometry": {"coordinates":[126.41815,44.97493],"type":"Point"}
}