{
  "type": "Feature",
  "properties": {
    "gn:admin1_code":"7.0",
    "gn:asciiname":"Henglu",
    "gn:country_code":"CN",
    "gn:dem":464,
    "gn:feature_class":"P",
    "gn:feature_code":"PPL",
    "gn:name":"Henglu",
    "gn:population":0,
    "gn:timezone":"Asia/Shanghai",
    "iso:country":"CN",
    "name:und_x_variant":[
        "\u6a2a\u8def"
    ],
    "name:zho_x_preferred":[
        "\u6a2a\u8def"
    ],
    "wof:name":"Henglu",
    "wof:placetype":"locality"
},
  "geometry": {"coordinates":[116.71539,26.64016],"type":"Point"}
}