{
  "type": "Feature",
  "properties": {
    "gn:admin1_code":"11.0",
    "gn:asciiname":"Longchongtan",
    "gn:country_code":"CN",
    "gn:dem":235,
    "gn:feature_class":"P",
    "gn:feature_code":"PPL",
    "gn:name":"Longchongtan",
    "gn:population":0,
    "gn:timezone":"Asia/Shanghai",
    "iso:country":"CN",
    "name:zho_x_preferred":[
        "\u9f99\u51b2\u6f6d"
    ],
    "wof:name":"Longchongtan",
    "wof:placetype":"locality"
},
  "geometry": {"coordinates":[110.39361,28.60056],"type":"Point"}
}