{
  "type": "Feature",
  "properties": {
    "gn:admin1_code":"3",
    "gn:asciiname":"Nanyingzonghekenzhichang",
    "gn:country_code":"CN",
    "gn:dem":51,
    "gn:feature_class":"P",
    "gn:feature_code":"PPL",
    "gn:name":"Nanyingzonghekenzhichang",
    "gn:population":0,
    "gn:timezone":"Asia/Shanghai",
    "iso:country":"CN",
    "wof:name":"Nanyingzonghekenzhichang",
    "wof:placetype":"locality"
},
  "geometry": {"coordinates":[115.11028,27.82528],"type":"Point"}
}