{
  "type": "Feature",
  "properties": {
    "gn:admin1_code":"9.0",
    "gn:asciiname":"Dongyao",
    "gn:country_code":"CN",
    "gn:dem":486,
    "gn:feature_class":"P",
    "gn:feature_code":"PPL",
    "gn:name":"Dongyao",
    "gn:population":0,
    "gn:timezone":"Asia/Shanghai",
    "iso:country":"CN",
    "name:zho_x_preferred":[
        "\u4e1c\u7a91"
    ],
    "wof:name":"Dongyao",
    "wof:placetype":"locality"
},
  "geometry": {"coordinates":[111.89697,34.12749],"type":"Point"}
}