{
  "type": "Feature",
  "properties": {
    "gn:admin1_code":"3.0",
    "gn:asciiname":"Shangtujia",
    "gn:country_code":"CN",
    "gn:dem":21,
    "gn:feature_class":"P",
    "gn:feature_code":"PPL",
    "gn:name":"Shangtujia",
    "gn:population":0,
    "gn:timezone":"Asia/Shanghai",
    "iso:country":"CN",
    "name:und_x_variant":[
        "\u4e0a\u6d82\u5bb6"
    ],
    "wof:name":"Shangtujia",
    "wof:placetype":"locality"
},
  "geometry": {"coordinates":[115.83257,28.66271],"type":"Point"}
}