{
  "type": "Feature",
  "properties": {
    "gn:admin1_code":"5.0",
    "gn:asciiname":"Lisheng Weizi",
    "gn:country_code":"CN",
    "gn:dem":190,
    "gn:feature_class":"P",
    "gn:feature_code":"PPL",
    "gn:name":"Lisheng Weizi",
    "gn:population":0,
    "gn:timezone":"Asia/Shanghai",
    "iso:country":"CN",
    "name:zho_x_preferred":[
        "\u674e\u751f\u56f4\u5b50"
    ],
    "wof:name":"Lisheng Weizi",
    "wof:placetype":"locality"
},
  "geometry": {"coordinates":[124.31233,44.34645],"type":"Point"}
}