{
  "type": "Feature",
  "properties": {
    "gn:admin1_code":"20.0",
    "gn:asciiname":"Xixiaokuang",
    "gn:country_code":"CN",
    "gn:dem":688,
    "gn:feature_class":"P",
    "gn:feature_code":"PPL",
    "gn:name":"Xixiaokuang",
    "gn:population":0,
    "gn:timezone":"Asia/Shanghai",
    "iso:country":"CN",
    "name:zho_x_preferred":[
        "\u897f\u5c0f\u77ff"
    ],
    "wof:name":"Xixiaokuang",
    "wof:placetype":"locality"
},
  "geometry": {"coordinates":[119.70208999999998,48.55185],"type":"Point"}
}