{
  "type": "Feature",
  "properties": {
    "gn:admin1_code":"7",
    "gn:asciiname":"Xibianshan",
    "gn:country_code":"CN",
    "gn:dem":469,
    "gn:feature_class":"P",
    "gn:feature_code":"PPL",
    "gn:name":"Xibianshan",
    "gn:population":0,
    "gn:timezone":"Asia/Shanghai",
    "iso:country":"CN",
    "name:zho_x_preferred":[
        "\u6eaa\u8fb9\u5c71"
    ],
    "wof:name":"Xibianshan",
    "wof:placetype":"locality"
},
  "geometry": {"coordinates":[118.56868,25.48024],"type":"Point"}
}