{
  "type": "Feature",
  "properties": {
    "gn:admin1_code":"24.0",
    "gn:asciiname":"Qingyahuai",
    "gn:country_code":"CN",
    "gn:dem":1140,
    "gn:feature_class":"P",
    "gn:feature_code":"PPL",
    "gn:name":"Qingyahuai",
    "gn:population":0,
    "gn:timezone":"Asia/Shanghai",
    "iso:country":"CN",
    "name:zho_x_preferred":[
        "\u9752\u5d16\u69d0"
    ],
    "wof:name":"Qingyahuai",
    "wof:placetype":"locality"
},
  "geometry": {"coordinates":[112.28144,38.05475],"type":"Point"}
}