{
  "type": "Feature",
  "properties": {
    "gn:admin1_code":"26.0",
    "gn:asciiname":"Lujia Shancun",
    "gn:country_code":"CN",
    "gn:dem":884,
    "gn:feature_class":"P",
    "gn:feature_code":"PPL",
    "gn:name":"L\u00fcjia Shancun",
    "gn:population":0,
    "gn:timezone":"Asia/Shanghai",
    "iso:country":"CN",
    "name:und_x_variant":[
        "L\u00fcjia Shancun"
    ],
    "name:zho_x_preferred":[
        "\u5415\u5bb6\u5c71\u6751"
    ],
    "wof:name":"Lujia Shancun",
    "wof:placetype":"locality"
},
  "geometry": {"coordinates":[110.36499999999999,37.2134],"type":"Point"}
}