{
  "type": "Feature",
  "properties": {
    "gn:admin1_code":"11.0",
    "gn:asciiname":"Longji",
    "gn:country_code":"CN",
    "gn:dem":163,
    "gn:feature_class":"P",
    "gn:feature_code":"PPL",
    "gn:name":"Longji",
    "gn:population":0,
    "gn:timezone":"Asia/Shanghai",
    "iso:country":"CN",
    "name:und_x_variant":[
        "Longxia"
    ],
    "name:zho_x_preferred":[
        "\u9f99\u96c6"
    ],
    "name:zho_x_variant":[
        "\u9f99\u4e0b"
    ],
    "wof:name":"Longji",
    "wof:placetype":"locality"
},
  "geometry": {"coordinates":[113.81815,26.95819],"type":"Point"}
}