{
  "type": "Feature",
  "properties": {
    "gn:admin1_code":"5.0",
    "gn:asciiname":"Huanxicun",
    "gn:country_code":"CN",
    "gn:dem":184,
    "gn:feature_class":"P",
    "gn:feature_code":"PPL",
    "gn:name":"Huanxicun",
    "gn:population":0,
    "gn:timezone":"Asia/Shanghai",
    "iso:country":"CN",
    "name:zho_x_preferred":[
        "\u6b22\u559c\u6751"
    ],
    "wof:name":"Huanxicun",
    "wof:placetype":"locality"
},
  "geometry": {"coordinates":[125.71935000000001,45.13335],"type":"Point"}
}