{
  "type": "Feature",
  "properties": {
    "gn:admin1_code":"2.0",
    "gn:asciiname":"Shanghe",
    "gn:country_code":"CN",
    "gn:dem":300,
    "gn:feature_class":"P",
    "gn:feature_code":"PPL",
    "gn:name":"Shanghe",
    "gn:population":0,
    "gn:timezone":"Asia/Shanghai",
    "iso:country":"CN",
    "name:zho_x_preferred":[
        "\u4e0a\u548c"
    ],
    "wof:name":"Shanghe",
    "wof:placetype":"locality"
},
  "geometry": {"coordinates":[120.01408000000001,29.65719],"type":"Point"}
}