{
  "type": "Feature",
  "properties": {
    "gn:admin1_code":"26",
    "gn:asciiname":"Caoping",
    "gn:cc2":"CN",
    "gn:country_code":"CN",
    "gn:dem":1099,
    "gn:feature_class":"P",
    "gn:feature_code":"PPL",
    "gn:name":"Caoping",
    "gn:population":0,
    "gn:timezone":"Asia/Shanghai",
    "iso:country":"CN",
    "name:und_x_variant":[
        "Caopingjie",
        "Ts\u2019ao-chia-p\u2019ing",
        "Caojiaping",
        "Ts\u2019ao-p\u2019ing-chieh",
        "Caoping"
    ],
    "wof:name":"Caoping",
    "wof:placetype":"locality"
},
  "geometry": {"coordinates":[109.42722000000001,33.74194],"type":"Point"}
}