{
  "type": "Feature",
  "properties": {
    "gn:admin1_code":"12.0",
    "gn:asciiname":"Yangcitang",
    "gn:country_code":"CN",
    "gn:dem":130,
    "gn:feature_class":"P",
    "gn:feature_code":"PPL",
    "gn:name":"Yangcitang",
    "gn:population":0,
    "gn:timezone":"Asia/Shanghai",
    "iso:country":"CN",
    "name:zho_x_preferred":[
        "\u6768\u7960\u5802"
    ],
    "wof:name":"Yangcitang",
    "wof:placetype":"locality"
},
  "geometry": {"coordinates":[112.01314000000001,30.98653],"type":"Point"}
}