{
  "type": "Feature",
  "properties": {
    "gn:admin1_code":"32.0",
    "gn:asciiname":"Lujiang",
    "gn:country_code":"CN",
    "gn:dem":351,
    "gn:feature_class":"P",
    "gn:feature_code":"PPL",
    "gn:name":"Lujiang",
    "gn:population":0,
    "gn:timezone":"Asia/Shanghai",
    "iso:country":"CN",
    "name:zho_x_preferred":[
        "\u6cf8\u6c5f"
    ],
    "wof:name":"Lujiang",
    "wof:placetype":"locality"
},
  "geometry": {"coordinates":[105.541,29.1471],"type":"Point"}
}