{
  "type": "Feature",
  "properties": {
    "gn:admin1_code":"4.0",
    "gn:asciiname":"Qiangmin",
    "gn:country_code":"CN",
    "gn:dem":4,
    "gn:feature_class":"P",
    "gn:feature_code":"PPL",
    "gn:name":"Qiangmin",
    "gn:population":0,
    "gn:timezone":"Asia/Shanghai",
    "iso:country":"CN",
    "name:und_x_variant":[
        "\u5f3a\u6c11"
    ],
    "wof:name":"Qiangmin",
    "wof:placetype":"locality"
},
  "geometry": {"coordinates":[121.33738999999998,32.29361],"type":"Point"}
}