{
  "type": "Feature",
  "properties": {
    "gn:admin1_code":"19.0",
    "gn:asciiname":"Wangjia Tuozi",
    "gn:country_code":"CN",
    "gn:dem":5,
    "gn:feature_class":"P",
    "gn:feature_code":"PPL",
    "gn:name":"Wangjia Tuozi",
    "gn:population":0,
    "gn:timezone":"Asia/Shanghai",
    "iso:country":"CN",
    "name:zho_x_preferred":[
        "\u738b\u5bb6\u5768\u5b50"
    ],
    "wof:name":"Wangjia Tuozi",
    "wof:placetype":"locality"
},
  "geometry": {"coordinates":[123.53700000000001,39.9313],"type":"Point"}
}