{
  "type": "Feature",
  "properties": {
    "gn:admin1_code":"15.0",
    "gn:asciiname":"Mu'er",
    "gn:country_code":"CN",
    "gn:dem":2512,
    "gn:feature_class":"P",
    "gn:feature_code":"PPLA4",
    "gn:name":"Mu\u2019er",
    "gn:population":0,
    "gn:timezone":"Asia/Shanghai",
    "iso:country":"CN",
    "name:und_x_variant":[
        "Mu\u2019er",
        "\u6728\u8033",
        "Mu\u2019er Xiang",
        "\u6728\u8033\u4e61"
    ],
    "wof:name":"Mu'er",
    "wof:placetype":"locality"
},
  "geometry": {"coordinates":[103.58544999999999,34.56612],"type":"Point"}
}