{
  "type": "Feature",
  "properties": {
    "gn:admin1_code":"3.0",
    "gn:asciiname":"Liguankeng",
    "gn:country_code":"CN",
    "gn:dem":448,
    "gn:feature_class":"P",
    "gn:feature_code":"PPL",
    "gn:name":"Liguankeng",
    "gn:population":0,
    "gn:timezone":"Asia/Shanghai",
    "iso:country":"CN",
    "name:zho_x_preferred":[
        "\u91cc\u7ba1\u5751"
    ],
    "wof:name":"Liguankeng",
    "wof:placetype":"locality"
},
  "geometry": {"coordinates":[117.46892,28.09754],"type":"Point"}
}