{
  "type": "Feature",
  "properties": {
    "gn:admin1_code":"9.0",
    "gn:asciiname":"Hangjia'ao",
    "gn:country_code":"CN",
    "gn:dem":842,
    "gn:feature_class":"P",
    "gn:feature_code":"PPL",
    "gn:name":"Hangjia\u2019ao",
    "gn:population":0,
    "gn:timezone":"Asia/Shanghai",
    "iso:country":"CN",
    "name:und_x_variant":[
        "Hangjia\u2019ao"
    ],
    "name:zho_x_preferred":[
        "\u676d\u5bb6\u51f9"
    ],
    "wof:name":"Hangjia'ao",
    "wof:placetype":"locality"
},
  "geometry": {"coordinates":[111.03091000000001,34.5557],"type":"Point"}
}