{
  "type": "Feature",
  "properties": {
    "gn:admin1_code":"4.0",
    "gn:asciiname":"Wazhuangcun",
    "gn:country_code":"CN",
    "gn:dem":32,
    "gn:feature_class":"P",
    "gn:feature_code":"PPL",
    "gn:name":"Wazhuangcun",
    "gn:population":0,
    "gn:timezone":"Asia/Shanghai",
    "iso:country":"CN",
    "name:zho_x_preferred":[
        "\u74e6\u5e84\u6751"
    ],
    "wof:name":"Wazhuangcun",
    "wof:placetype":"locality"
},
  "geometry": {"coordinates":[117.36188,34.33008],"type":"Point"}
}