{
  "type": "Feature",
  "properties": {
    "gn:admin1_code":"16.0",
    "gn:asciiname":"Zhenhong",
    "gn:country_code":"CN",
    "gn:dem":446,
    "gn:feature_class":"P",
    "gn:feature_code":"PPL",
    "gn:name":"Zhenhong",
    "gn:population":0,
    "gn:timezone":"Asia/Shanghai",
    "iso:country":"CN",
    "name:zho_x_preferred":[
        "\u9547\u6d2a"
    ],
    "wof:name":"Zhenhong",
    "wof:placetype":"locality"
},
  "geometry": {"coordinates":[106.56399999999999,24.3308],"type":"Point"}
}