{
  "type": "Feature",
  "properties": {
    "gn:admin1_code":"14.0",
    "gn:asciiname":"Palie",
    "gn:country_code":"CN",
    "gn:dem":4461,
    "gn:feature_class":"P",
    "gn:feature_code":"PPL",
    "gn:name":"Palie",
    "gn:population":0,
    "gn:timezone":"Asia/Urumqi",
    "iso:country":"CN",
    "name:zho_x_preferred":[
        "\u5e15\u5217"
    ],
    "wof:name":"Palie",
    "wof:placetype":"locality"
},
  "geometry": {"coordinates":[87.8334,28.7859],"type":"Point"}
}