{
  "type": "Feature",
  "properties": {
    "gn:admin1_code":"20.0",
    "gn:asciiname":"Dajiti Sandui",
    "gn:country_code":"CN",
    "gn:dem":1050,
    "gn:feature_class":"P",
    "gn:feature_code":"PPLF",
    "gn:name":"Dajiti Sandui",
    "gn:population":0,
    "gn:timezone":"Asia/Shanghai",
    "iso:country":"CN",
    "name:zho_x_preferred":[
        "\u5927\u96c6\u4f53\u4e09\u961f"
    ],
    "wof:name":"Dajiti Sandui",
    "wof:placetype":"locality"
},
  "geometry": {"coordinates":[121.18919,48.40562],"type":"Point"}
}