{
  "type": "Feature",
  "properties": {
    "gn:admin1_code":"3",
    "gn:asciiname":"Shanggutian",
    "gn:country_code":"CN",
    "gn:dem":279,
    "gn:feature_class":"P",
    "gn:feature_code":"PPL",
    "gn:name":"Shanggutian",
    "gn:population":0,
    "gn:timezone":"Asia/Shanghai",
    "iso:country":"CN",
    "name:zho_x_preferred":[
        "\u4e0a\u53e4\u7530"
    ],
    "wof:name":"Shanggutian",
    "wof:placetype":"locality"
},
  "geometry": {"coordinates":[113.98999999999999,26.6831],"type":"Point"}
}