{
  "type": "Feature",
  "properties": {
    "gn:admin1_code":"19.0",
    "gn:asciiname":"Xiashulinzi",
    "gn:country_code":"CN",
    "gn:dem":245,
    "gn:feature_class":"P",
    "gn:feature_code":"PPL",
    "gn:name":"Xiashulinzi",
    "gn:population":0,
    "gn:timezone":"Asia/Shanghai",
    "iso:country":"CN",
    "name:zho_x_preferred":[
        "\u4e0b\u6811\u6797\u5b50"
    ],
    "wof:name":"Xiashulinzi",
    "wof:placetype":"locality"
},
  "geometry": {"coordinates":[120.88763,42.06986],"type":"Point"}
}