{
  "type": "Feature",
  "properties": {
    "gn:admin1_code":"26.0",
    "gn:asciiname":"Niujiagoucun",
    "gn:country_code":"CN",
    "gn:dem":1637,
    "gn:feature_class":"P",
    "gn:feature_code":"PPL",
    "gn:name":"Niujiagoucun",
    "gn:population":0,
    "gn:timezone":"Asia/Shanghai",
    "iso:country":"CN",
    "name:und_x_variant":[
        "\u725b\u5bb6\u6c9f\u6751"
    ],
    "wof:name":"Niujiagoucun",
    "wof:placetype":"locality"
},
  "geometry": {"coordinates":[107.32913000000001,34.09009],"type":"Point"}
}