{
  "type": "Feature",
  "properties": {
    "gn:admin1_code":"32.0",
    "gn:asciiname":"Zhonggou",
    "gn:country_code":"CN",
    "gn:dem":444,
    "gn:feature_class":"P",
    "gn:feature_code":"PPL",
    "gn:name":"Zhonggou",
    "gn:population":0,
    "gn:timezone":"Asia/Shanghai",
    "iso:country":"CN",
    "name:zho_x_preferred":[
        "\u4e2d\u6c9f"
    ],
    "wof:name":"Zhonggou",
    "wof:placetype":"locality"
},
  "geometry": {"coordinates":[104.747,30.673],"type":"Point"}
}