{
  "type": "Feature",
  "properties": {
    "gn:admin1_code":"4.0",
    "gn:asciiname":"Baishengxu",
    "gn:country_code":"CN",
    "gn:dem":2,
    "gn:feature_class":"P",
    "gn:feature_code":"PPL",
    "gn:name":"Baishengxu",
    "gn:population":0,
    "gn:timezone":"Asia/Shanghai",
    "iso:country":"CN",
    "name:zho_x_preferred":[
        "\u67cf\u76db\u5729"
    ],
    "wof:name":"Baishengxu",
    "wof:placetype":"locality"
},
  "geometry": {"coordinates":[120.24370999999999,31.99525],"type":"Point"}
}