{
  "type": "Feature",
  "properties": {
    "gn:admin1_code":"11",
    "gn:asciiname":"Huajiangdong",
    "gn:country_code":"CN",
    "gn:dem":339,
    "gn:feature_class":"P",
    "gn:feature_code":"PPL",
    "gn:name":"Huajiangdong",
    "gn:population":0,
    "gn:timezone":"Asia/Shanghai",
    "iso:country":"CN",
    "name:zho_x_preferred":[
        "\u82b1\u6c5f\u6d1e"
    ],
    "wof:name":"Huajiangdong",
    "wof:placetype":"locality"
},
  "geometry": {"coordinates":[111.66658,25.03077],"type":"Point"}
}