{
  "type": "Feature",
  "properties": {
    "gn:admin1_code":"26.0",
    "gn:asciiname":"Liulangcun",
    "gn:country_code":"CN",
    "gn:dem":691,
    "gn:feature_class":"P",
    "gn:feature_code":"PPL",
    "gn:name":"Liulangcun",
    "gn:population":0,
    "gn:timezone":"Asia/Shanghai",
    "iso:country":"CN",
    "name:zho_x_preferred":[
        "\u516d\u90ce\u6751"
    ],
    "wof:name":"Liulangcun",
    "wof:placetype":"locality"
},
  "geometry": {"coordinates":[108.83353,32.83808],"type":"Point"}
}