{
  "type": "Feature",
  "properties": {
    "gn:admin1_code":"3.0",
    "gn:asciiname":"Yaoziqian",
    "gn:country_code":"CN",
    "gn:dem":23,
    "gn:feature_class":"P",
    "gn:feature_code":"PPL",
    "gn:name":"Yaoziqian",
    "gn:population":0,
    "gn:timezone":"Asia/Shanghai",
    "iso:country":"CN",
    "name:und_x_variant":[
        "\u7a91\u5b50\u524d"
    ],
    "wof:name":"Yaoziqian",
    "wof:placetype":"locality"
},
  "geometry": {"coordinates":[116.66211,29.45288],"type":"Point"}
}