{
  "type": "Feature",
  "properties": {
    "gn:admin1_code":"10",
    "gn:asciiname":"Naobaodi",
    "gn:country_code":"CN",
    "gn:dem":1376,
    "gn:feature_class":"P",
    "gn:feature_code":"PPL",
    "gn:name":"Naobaodi",
    "gn:population":0,
    "gn:timezone":"Asia/Shanghai",
    "iso:country":"CN",
    "name:zho_x_preferred":[
        "\u8111\u5305\u5e95"
    ],
    "wof:name":"Naobaodi",
    "wof:placetype":"locality"
},
  "geometry": {"coordinates":[114.85187000000001,41.48356],"type":"Point"}
}