{
  "type": "Feature",
  "properties": {
    "gn:admin1_code":"3.0",
    "gn:asciiname":"Jiaolinkeng",
    "gn:country_code":"CN",
    "gn:dem":373,
    "gn:feature_class":"P",
    "gn:feature_code":"PPL",
    "gn:name":"Jiaolinkeng",
    "gn:population":0,
    "gn:timezone":"Asia/Shanghai",
    "iso:country":"CN",
    "name:und_x_variant":[
        "\u8549\u6797\u5751"
    ],
    "wof:name":"Jiaolinkeng",
    "wof:placetype":"locality"
},
  "geometry": {"coordinates":[115.8313,25.71637],"type":"Point"}
}