{
  "type": "Feature",
  "properties": {
    "gn:admin1_code":"15.0",
    "gn:asciiname":"Huamajing",
    "gn:country_code":"CN",
    "gn:dem":1509,
    "gn:feature_class":"P",
    "gn:feature_code":"PPL",
    "gn:name":"Huamajing",
    "gn:population":0,
    "gn:timezone":"Asia/Shanghai",
    "iso:country":"CN",
    "name:zho_x_preferred":[
        "\u6866\u9a6c\u4e95"
    ],
    "wof:name":"Huamajing",
    "wof:placetype":"locality"
},
  "geometry": {"coordinates":[103.279,38.0699],"type":"Point"}
}