{
  "type": "Feature",
  "properties": {
    "gn:admin1_code":"09",
    "gn:asciiname":"Beidu",
    "gn:country_code":"CN",
    "gn:dem":95,
    "gn:feature_class":"P",
    "gn:feature_code":"PPLA4",
    "gn:name":"Beidu",
    "gn:population":0,
    "gn:timezone":"Asia/Shanghai",
    "iso:country":"CN",
    "name:und_x_variant":[
        "Pei-tu",
        "Pei-tu-chieh",
        "\u5317\u6e21",
        "Beidu Zhen",
        "Beidu"
    ],
    "wof:name":"Beidu",
    "wof:placetype":"locality"
},
  "geometry": {"coordinates":[113.28713,33.70735],"type":"Point"}
}