{
  "type": "Feature",
  "properties": {
    "gn:admin1_code":"29.0",
    "gn:asciiname":"Jinzhulin",
    "gn:country_code":"CN",
    "gn:dem":1708,
    "gn:feature_class":"P",
    "gn:feature_code":"PPL",
    "gn:name":"Jinzhulin",
    "gn:population":0,
    "gn:timezone":"Asia/Yangon",
    "iso:country":"CN",
    "name:zho_x_preferred":[
        "\u91d1\u7af9\u6797"
    ],
    "wof:name":"Jinzhulin",
    "wof:placetype":"locality"
},
  "geometry": {"coordinates":[98.6862,23.9112],"type":"Point"}
}