{
  "type": "Feature",
  "properties": {
    "gn:admin1_code":"15.0",
    "gn:asciiname":"Xinnong",
    "gn:country_code":"CN",
    "gn:dem":1695,
    "gn:feature_class":"P",
    "gn:feature_code":"PPLF",
    "gn:name":"Xinnong",
    "gn:population":0,
    "gn:timezone":"Asia/Shanghai",
    "iso:country":"CN",
    "name:zho_x_preferred":[
        "\u65b0\u519c"
    ],
    "wof:name":"Xinnong",
    "wof:placetype":"locality"
},
  "geometry": {"coordinates":[103.42700000000001,36.296],"type":"Point"}
}