{
  "type": "Feature",
  "properties": {
    "gn:admin1_code":"29.0",
    "gn:asciiname":"Xiaozhatang",
    "gn:country_code":"CN",
    "gn:dem":2000,
    "gn:feature_class":"P",
    "gn:feature_code":"PPL",
    "gn:name":"Xiaozhatang",
    "gn:population":0,
    "gn:timezone":"Asia/Shanghai",
    "iso:country":"CN",
    "name:zho_x_preferred":[
        "\u5c0f\u95f8\u5858"
    ],
    "wof:name":"Xiaozhatang",
    "wof:placetype":"locality"
},
  "geometry": {"coordinates":[103.773,26.107],"type":"Point"}
}