{
  "type": "Feature",
  "properties": {
    "gn:admin1_code":"1.0",
    "gn:asciiname":"Malaojiacun",
    "gn:country_code":"CN",
    "gn:dem":40,
    "gn:feature_class":"P",
    "gn:feature_code":"PPL",
    "gn:name":"Malaojiacun",
    "gn:population":0,
    "gn:timezone":"Asia/Shanghai",
    "iso:country":"CN",
    "name:zho_x_preferred":[
        "\u9a6c\u8001\u5bb6\u6751"
    ],
    "wof:name":"Malaojiacun",
    "wof:placetype":"locality"
},
  "geometry": {"coordinates":[115.86682999999999,33.7931],"type":"Point"}
}