{
  "type": "Feature",
  "properties": {
    "gn:admin1_code":"7.0",
    "gn:asciiname":"Dongyuan",
    "gn:country_code":"CN",
    "gn:dem":30,
    "gn:feature_class":"P",
    "gn:feature_code":"PPL",
    "gn:name":"Dongyuan",
    "gn:population":0,
    "gn:timezone":"Asia/Shanghai",
    "iso:country":"CN",
    "name:und_x_variant":[
        "\u4e1c\u56ed",
        "\u4e1c\u56ed\u6751"
    ],
    "name:zho_x_preferred":[
        "Dongyuancun"
    ],
    "wof:name":"Dongyuan",
    "wof:placetype":"locality"
},
  "geometry": {"coordinates":[119.33063,26.1458],"type":"Point"}
}