{
  "type": "Feature",
  "properties": {
    "gn:admin1_code":"32.0",
    "gn:asciiname":"Wujia Citang",
    "gn:country_code":"CN",
    "gn:dem":381,
    "gn:feature_class":"P",
    "gn:feature_code":"PPL",
    "gn:name":"Wujia Citang",
    "gn:population":0,
    "gn:timezone":"Asia/Shanghai",
    "iso:country":"CN",
    "name:zho_x_preferred":[
        "\u5434\u5bb6\u7960\u5802"
    ],
    "wof:name":"Wujia Citang",
    "wof:placetype":"locality"
},
  "geometry": {"coordinates":[106.73139999999999,30.47332],"type":"Point"}
}