{
  "type": "Feature",
  "properties": {
    "gn:admin1_code":"10",
    "gn:asciiname":"Mangshikou",
    "gn:cc2":"CN",
    "gn:country_code":"CN",
    "gn:dem":686,
    "gn:feature_class":"P",
    "gn:feature_code":"PPL",
    "gn:name":"Mangshikou",
    "gn:population":0,
    "gn:timezone":"Asia/Shanghai",
    "iso:country":"CN",
    "name:und_x_variant":[
        "Mang-shih-k\u2019ou",
        "Mangshikou"
    ],
    "wof:name":"Mangshikou",
    "wof:placetype":"locality"
},
  "geometry": {"coordinates":[115.20528,39.79028],"type":"Point"}
}