{
  "type": "Feature",
  "properties": {
    "gn:admin1_code":"4.0",
    "gn:asciiname":"Lixu",
    "gn:country_code":"CN",
    "gn:dem":2,
    "gn:feature_class":"P",
    "gn:feature_code":"PPL",
    "gn:name":"Lixu",
    "gn:population":0,
    "gn:timezone":"Asia/Shanghai",
    "iso:country":"CN",
    "name:fas_x_preferred":[
        "\u0644\u06cc\u0634\u0648"
    ],
    "name:zho_x_preferred":[
        "Lixu"
    ],
    "name:zho_x_variant":[
        "\u674e\u5729",
        "\u9ece\u5729\u9547"
    ],
    "wof:name":"Lixu",
    "wof:placetype":"locality"
},
  "geometry": {"coordinates":[119.05083999999999,34.33766],"type":"Point"}
}