{
  "type": "Feature",
  "properties": {
    "gn:admin1_code":"32.0",
    "gn:asciiname":"Doupingba",
    "gn:country_code":"CN",
    "gn:dem":552,
    "gn:feature_class":"P",
    "gn:feature_code":"PPL",
    "gn:name":"Doupingba",
    "gn:population":0,
    "gn:timezone":"Asia/Shanghai",
    "iso:country":"CN",
    "name:zho_x_preferred":[
        "\u8c46\u576a\u575d"
    ],
    "wof:name":"Doupingba",
    "wof:placetype":"locality"
},
  "geometry": {"coordinates":[104.777,31.8309],"type":"Point"}
}