{
  "type": "Feature",
  "properties": {
    "gn:admin1_code":"12.0",
    "gn:asciiname":"Xiaolonghouzhou",
    "gn:country_code":"CN",
    "gn:dem":79,
    "gn:feature_class":"P",
    "gn:feature_code":"PPL",
    "gn:name":"Xiaolonghouzhou",
    "gn:population":0,
    "gn:timezone":"Asia/Shanghai",
    "iso:country":"CN",
    "name:zho_x_preferred":[
        "\u5c0f\u9f99\u540e\u6d32"
    ],
    "wof:name":"Xiaolonghouzhou",
    "wof:placetype":"locality"
},
  "geometry": {"coordinates":[111.83453,32.12867],"type":"Point"}
}