{
  "type": "Feature",
  "properties": {
    "gn:admin1_code":"1.0",
    "gn:asciiname":"Luoxicun",
    "gn:country_code":"CN",
    "gn:dem":99,
    "gn:feature_class":"P",
    "gn:feature_code":"PPL",
    "gn:name":"Luoxicun",
    "gn:population":0,
    "gn:timezone":"Asia/Shanghai",
    "iso:country":"CN",
    "name:zho_x_preferred":[
        "\u7f57\u6eaa\u6751"
    ],
    "wof:name":"Luoxicun",
    "wof:placetype":"locality"
},
  "geometry": {"coordinates":[116.27097000000001,30.54793],"type":"Point"}
}