{
  "type": "Feature",
  "properties": {
    "gn:admin1_code":"10",
    "gn:asciiname":"Daweizhuang",
    "gn:country_code":"CN",
    "gn:dem":152,
    "gn:feature_class":"P",
    "gn:feature_code":"PPL",
    "gn:name":"Daweizhuang",
    "gn:population":0,
    "gn:timezone":"Asia/Shanghai",
    "iso:country":"CN",
    "name:zho_x_preferred":[
        "\u5927\u97e6\u5e84"
    ],
    "wof:name":"Daweizhuang",
    "wof:placetype":"locality"
},
  "geometry": {"coordinates":[118.21997,40.35156],"type":"Point"}
}