{
  "type": "Feature",
  "properties": {
    "gn:admin1_code":"25.0",
    "gn:asciiname":"Qianpuxia",
    "gn:country_code":"CN",
    "gn:dem":33,
    "gn:feature_class":"P",
    "gn:feature_code":"PPL",
    "gn:name":"Qianpuxia",
    "gn:population":0,
    "gn:timezone":"Asia/Shanghai",
    "iso:country":"CN",
    "name:zho_x_preferred":[
        "\u524d\u94fa\u4e0b"
    ],
    "wof:name":"Qianpuxia",
    "wof:placetype":"locality"
},
  "geometry": {"coordinates":[120.48654999999999,36.41602],"type":"Point"}
}