{
  "type": "Feature",
  "properties": {
    "gn:admin1_code":"24.0",
    "gn:asciiname":"Nanlimocun",
    "gn:country_code":"CN",
    "gn:dem":918,
    "gn:feature_class":"P",
    "gn:feature_code":"PPL",
    "gn:name":"Nanlimocun",
    "gn:population":0,
    "gn:timezone":"Asia/Shanghai",
    "iso:country":"CN",
    "name:zho_x_preferred":[
        "\u5357\u674e\u672b\u6751"
    ],
    "wof:name":"Nanlimocun",
    "wof:placetype":"locality"
},
  "geometry": {"coordinates":[112.98942,36.13264],"type":"Point"}
}