{
  "type": "Feature",
  "properties": {
    "gn:admin1_code":"5.0",
    "gn:asciiname":"Dongjiujiang",
    "gn:country_code":"CN",
    "gn:dem":139,
    "gn:feature_class":"P",
    "gn:feature_code":"PPL",
    "gn:name":"Dongjiujiang",
    "gn:population":0,
    "gn:timezone":"Asia/Shanghai",
    "iso:country":"CN",
    "name:zho_x_preferred":[
        "\u4e1c\u4e5d\u6c5f"
    ],
    "wof:name":"Dongjiujiang",
    "wof:placetype":"locality"
},
  "geometry": {"coordinates":[123.43210999999999,44.9762],"type":"Point"}
}