{
  "type": "Feature",
  "properties": {
    "gn:admin1_code":"12.0",
    "gn:asciiname":"Xingzhai",
    "gn:country_code":"CN",
    "gn:dem":373,
    "gn:feature_class":"P",
    "gn:feature_code":"PPL",
    "gn:name":"Xingzhai",
    "gn:population":0,
    "gn:timezone":"Asia/Shanghai",
    "iso:country":"CN",
    "name:zho_x_preferred":[
        "\u661f\u5be8"
    ],
    "wof:name":"Xingzhai",
    "wof:placetype":"locality"
},
  "geometry": {"coordinates":[111.28986999999999,32.32937],"type":"Point"}
}