{
  "type": "Feature",
  "properties": {
    "gn:admin1_code":"25",
    "gn:asciiname":"Xuji",
    "gn:country_code":"CN",
    "gn:dem":43,
    "gn:feature_class":"P",
    "gn:feature_code":"PPL",
    "gn:name":"Xuji",
    "gn:population":0,
    "gn:timezone":"Asia/Shanghai",
    "iso:country":"CN",
    "name:zho_x_preferred":[
        "\u5f90\u96c6"
    ],
    "wof:name":"Xuji",
    "wof:placetype":"locality"
},
  "geometry": {"coordinates":[115.69365999999999,36.00980999999999],"type":"Point"}
}