{
  "type": "Feature",
  "properties": {
    "gn:admin1_code":"19",
    "gn:asciiname":"Dasuhe",
    "gn:country_code":"CN",
    "gn:dem":437,
    "gn:feature_class":"P",
    "gn:feature_code":"PPLA4",
    "gn:name":"Dasuhe",
    "gn:population":0,
    "gn:timezone":"Asia/Shanghai",
    "iso:country":"CN",
    "name:und_x_variant":[
        "Ta-su-ho",
        "Dasuhe",
        "\u5927\u82cf\u6cb3",
        "Dasuhe Xiang",
        "\u5927\u82cf\u6cb3\u4e61"
    ],
    "wof:name":"Dasuhe",
    "wof:placetype":"locality"
},
  "geometry": {"coordinates":[124.95623999999999,41.91817],"type":"Point"}
}