{
  "type": "Feature",
  "properties": {
    "gn:admin1_code":"16.0",
    "gn:asciiname":"Luqiong",
    "gn:country_code":"CN",
    "gn:dem":265,
    "gn:feature_class":"P",
    "gn:feature_code":"PPL",
    "gn:name":"Luqiong",
    "gn:population":0,
    "gn:timezone":"Asia/Shanghai",
    "iso:country":"CN",
    "name:zho_x_preferred":[
        "\u6e0c\u743c"
    ],
    "wof:name":"Luqiong",
    "wof:placetype":"locality"
},
  "geometry": {"coordinates":[107.803,22.2422],"type":"Point"}
}