{
  "type": "Feature",
  "properties": {
    "iso:country":"CN",
    "qs:name":"\u78a7\u9633\u9547",
    "qs:name_adm0":"\u4e2d\u570b",
    "qs:name_adm1":"\u5b89\u5fbd\u7701",
    "qs:photos":301,
    "qs:photos_1k":61,
    "qs:photos_9k":1,
    "qs:photos_9r":5,
    "qs:photos_all":301,
    "qs:photos_sr":5,
    "qs:placetype":"Town",
    "qs:pop_sr":"0",
    "wof:name":"\u78a7\u9633\u9547",
    "wof:placetype":"locality"
},
  "geometry": {"coordinates":[117.948446,29.924588],"type":"Point"}
}