{
  "type": "Feature",
  "properties": {
    "gn:admin1_code":"19.0",
    "gn:asciiname":"Xiahuayuan",
    "gn:country_code":"CN",
    "gn:dem":368,
    "gn:feature_class":"P",
    "gn:feature_code":"PPL",
    "gn:name":"Xiahuayuan",
    "gn:population":0,
    "gn:timezone":"Asia/Shanghai",
    "iso:country":"CN",
    "name:und_x_variant":[
        "\u4e0b\u82b1\u56ed"
    ],
    "name:zho_x_preferred":[
        "\u4e0b\u82b1\u56ed"
    ],
    "wof:name":"Xiahuayuan",
    "wof:placetype":"locality"
},
  "geometry": {"coordinates":[125.34372,41.50984],"type":"Point"}
}