{
  "type": "Feature",
  "properties": {
    "gn:admin1_code":"3.0",
    "gn:asciiname":"Tielu",
    "gn:country_code":"CN",
    "gn:dem":57,
    "gn:feature_class":"P",
    "gn:feature_code":"PPLA4",
    "gn:name":"Tielu",
    "gn:population":0,
    "gn:timezone":"Asia/Shanghai",
    "iso:country":"CN",
    "name:und_x_variant":[
        "\u94c1\u8def",
        "Tielu Zhen",
        "\u94c1\u8def\u9547"
    ],
    "wof:name":"Tielu",
    "wof:placetype":"locality"
},
  "geometry": {"coordinates":[115.78811,27.87229],"type":"Point"}
}