{
  "type": "Feature",
  "properties": {
    "gn:admin1_code":"4.0",
    "gn:asciiname":"Yangwei",
    "gn:cc2":"CN",
    "gn:country_code":"CN",
    "gn:dem":2,
    "gn:feature_class":"P",
    "gn:feature_code":"PPL",
    "gn:name":"Yangwei",
    "gn:population":0,
    "gn:timezone":"Asia/Shanghai",
    "iso:country":"CN",
    "name:und_x_variant":[
        "Yang-y\u00fc",
        "Yeh-chuang",
        "Yang-wei-tzu",
        "Yang-hs\u00fc",
        "Yangwei"
    ],
    "wof:name":"Yangwei",
    "wof:placetype":"locality"
},
  "geometry": {"coordinates":[119.94667,34.10694],"type":"Point"}
}