{
  "type": "Feature",
  "properties": {
    "gn:admin1_code":"5.0",
    "gn:asciiname":"Nonglincun",
    "gn:country_code":"CN",
    "gn:dem":151,
    "gn:feature_class":"P",
    "gn:feature_code":"PPL",
    "gn:name":"Nonglincun",
    "gn:population":0,
    "gn:timezone":"Asia/Shanghai",
    "iso:country":"CN",
    "name:zho_x_preferred":[
        "\u519c\u6797\u6751"
    ],
    "wof:name":"Nonglincun",
    "wof:placetype":"locality"
},
  "geometry": {"coordinates":[124.78016,45.20201],"type":"Point"}
}