{
  "type": "Feature",
  "properties": {
    "gn:admin1_code":"8.0",
    "gn:asciiname":"Zhuxishantun",
    "gn:country_code":"CN",
    "gn:dem":144,
    "gn:feature_class":"P",
    "gn:feature_code":"PPL",
    "gn:name":"Zhuxishantun",
    "gn:population":0,
    "gn:timezone":"Asia/Shanghai",
    "iso:country":"CN",
    "name:zho_x_preferred":[
        "\u6731\u9521\u5c71\u5c6f"
    ],
    "wof:name":"Zhuxishantun",
    "wof:placetype":"locality"
},
  "geometry": {"coordinates":[123.23520000000001,46.51016],"type":"Point"}
}