{
  "type": "Feature",
  "properties": {
    "gn:admin1_code":"08",
    "gn:asciiname":"Kangjin",
    "gn:country_code":"CN",
    "gn:dem":154,
    "gn:feature_class":"P",
    "gn:feature_code":"PPLA4",
    "gn:name":"Kangjin",
    "gn:population":0,
    "gn:timezone":"Asia/Shanghai",
    "iso:country":"CN",
    "name:und_x_variant":[
        "K\u2019ang-chin-ching",
        "K\u2019ang-chin-chen",
        "K\u2019ang-chia-ching",
        "Kangjinjing",
        "Kangjin",
        "Kangjin Zhen"
    ],
    "name:zho_x_preferred":[
        "\u5eb7\u91d1"
    ],
    "name:zho_x_variant":[
        "\u5eb7\u91d1\u9547"
    ],
    "wof:name":"Kangjin",
    "wof:placetype":"locality"
},
  "geometry": {"coordinates":[126.80405,46.1971],"type":"Point"}
}