{
  "type": "Feature",
  "properties": {
    "gn:admin1_code":"15.0",
    "gn:asciiname":"Shuangbuzi",
    "gn:country_code":"CN",
    "gn:dem":1693,
    "gn:feature_class":"P",
    "gn:feature_code":"PPL",
    "gn:name":"Shuangbuzi",
    "gn:population":0,
    "gn:timezone":"Asia/Shanghai",
    "iso:country":"CN",
    "name:und_x_variant":[
        "\u53cc\u5821\u5b50"
    ],
    "wof:name":"Shuangbuzi",
    "wof:placetype":"locality"
},
  "geometry": {"coordinates":[105.95199,35.3049],"type":"Point"}
}