{
  "type": "Feature",
  "properties": {
    "gn:admin1_code":"11",
    "gn:asciiname":"Hua'eli",
    "gn:country_code":"CN",
    "gn:dem":171,
    "gn:feature_class":"P",
    "gn:feature_code":"PPL",
    "gn:name":"Hua\u2019eli",
    "gn:population":0,
    "gn:timezone":"Asia/Shanghai",
    "iso:country":"CN",
    "name:und_x_variant":[
        "Hua\u2019eli"
    ],
    "name:zho_x_preferred":[
        "\u82b1\u843c\u91cc"
    ],
    "wof:name":"Hua'eli",
    "wof:placetype":"locality"
},
  "geometry": {"coordinates":[111.84644,27.71663],"type":"Point"}
}