{
  "type": "Feature",
  "properties": {
    "gn:admin1_code":"25.0",
    "gn:asciiname":"Wangpingfangcun",
    "gn:country_code":"CN",
    "gn:dem":43,
    "gn:feature_class":"P",
    "gn:feature_code":"PPL",
    "gn:name":"Wangpingfangcun",
    "gn:population":0,
    "gn:timezone":"Asia/Shanghai",
    "iso:country":"CN",
    "name:zho_x_preferred":[
        "\u738b\u5e73\u574a\u6751"
    ],
    "wof:name":"Wangpingfangcun",
    "wof:placetype":"locality"
},
  "geometry": {"coordinates":[115.90278000000001,35.22044],"type":"Point"}
}