{
  "type": "Feature",
  "properties": {
    "gn:admin1_code":"29.0",
    "gn:asciiname":"Xinglongjie",
    "gn:country_code":"CN",
    "gn:dem":1306,
    "gn:feature_class":"P",
    "gn:feature_code":"PPL",
    "gn:name":"Xinglongjie",
    "gn:population":0,
    "gn:timezone":"Asia/Shanghai",
    "iso:country":"CN",
    "name:zho_x_preferred":[
        "\u5174\u9686\u8857"
    ],
    "wof:name":"Xinglongjie",
    "wof:placetype":"locality"
},
  "geometry": {"coordinates":[104.396,23.0024],"type":"Point"}
}