{
  "type": "Feature",
  "properties": {
    "gn:admin1_code":"11.0",
    "gn:asciiname":"Genglong",
    "gn:country_code":"CN",
    "gn:dem":933,
    "gn:feature_class":"P",
    "gn:feature_code":"PPL",
    "gn:name":"Genglong",
    "gn:population":0,
    "gn:timezone":"Asia/Shanghai",
    "iso:country":"CN",
    "name:zho_x_preferred":[
        "\u8015\u9f99"
    ],
    "wof:name":"Genglong",
    "wof:placetype":"locality"
},
  "geometry": {"coordinates":[109.63248,28.42119000000001],"type":"Point"}
}