{
  "type": "Feature",
  "properties": {
    "gn:admin1_code":"10",
    "gn:asciiname":"Xizhangzi",
    "gn:country_code":"CN",
    "gn:dem":713,
    "gn:feature_class":"P",
    "gn:feature_code":"PPL",
    "gn:name":"Xizhangzi",
    "gn:population":0,
    "gn:timezone":"Asia/Shanghai",
    "iso:country":"CN",
    "name:zho_x_preferred":[
        "\u897f\u6756\u5b50"
    ],
    "wof:name":"Xizhangzi",
    "wof:placetype":"locality"
},
  "geometry": {"coordinates":[118.50226000000001,40.91073],"type":"Point"}
}