{
  "type": "Feature",
  "properties": {
    "gn:admin1_code":"32.0",
    "gn:asciiname":"Yanri'a",
    "gn:country_code":"CN",
    "gn:dem":3565,
    "gn:feature_class":"P",
    "gn:feature_code":"PPL",
    "gn:name":"Yanri\u2019a",
    "gn:population":0,
    "gn:timezone":"Asia/Shanghai",
    "iso:country":"CN",
    "name:und_x_variant":[
        "Yanri\u2019a"
    ],
    "name:zho_x_preferred":[
        "\u4e25\u65e5\u963f"
    ],
    "wof:name":"Yanri'a",
    "wof:placetype":"locality"
},
  "geometry": {"coordinates":[97.6836,32.5858],"type":"Point"}
}