{
  "type": "Feature",
  "properties": {
    "gn:admin1_code":"11.0",
    "gn:asciiname":"Bilongwan",
    "gn:country_code":"CN",
    "gn:dem":421,
    "gn:feature_class":"P",
    "gn:feature_code":"PPL",
    "gn:name":"Bilongwan",
    "gn:population":0,
    "gn:timezone":"Asia/Shanghai",
    "iso:country":"CN",
    "name:zho_x_preferred":[
        "\u78a7\u9f99\u6e7e"
    ],
    "wof:name":"Bilongwan",
    "wof:placetype":"locality"
},
  "geometry": {"coordinates":[110.23241000000002,29.14759],"type":"Point"}
}