{
  "type": "Feature",
  "properties": {
    "gn:admin1_code":"26.0",
    "gn:asciiname":"Canggou",
    "gn:country_code":"CN",
    "gn:dem":1401,
    "gn:feature_class":"P",
    "gn:feature_code":"PPL",
    "gn:name":"Canggou",
    "gn:population":0,
    "gn:timezone":"Asia/Shanghai",
    "iso:country":"CN",
    "name:zho_x_preferred":[
        "\u4ed3\u6c9f"
    ],
    "wof:name":"Canggou",
    "wof:placetype":"locality"
},
  "geometry": {"coordinates":[108.71293,33.24904],"type":"Point"}
}