{
  "type": "Feature",
  "properties": {
    "gn:admin1_code":"29.0",
    "gn:asciiname":"Menglianba",
    "gn:country_code":"CN",
    "gn:dem":1075,
    "gn:feature_class":"P",
    "gn:feature_code":"PPL",
    "gn:name":"Menglianba",
    "gn:population":0,
    "gn:timezone":"Asia/Shanghai",
    "iso:country":"CN",
    "name:zho_x_preferred":[
        "\u5b5f\u8fde\u575d"
    ],
    "wof:name":"Menglianba",
    "wof:placetype":"locality"
},
  "geometry": {"coordinates":[98.84529999999999,25.3317],"type":"Point"}
}