{
  "type": "Feature",
  "properties": {
    "gn:admin1_code":"30",
    "gn:asciiname":"Shifentian",
    "gn:country_code":"CN",
    "gn:dem":35,
    "gn:feature_class":"P",
    "gn:feature_code":"PPL",
    "gn:name":"Shifentian",
    "gn:population":0,
    "gn:timezone":"Asia/Shanghai",
    "iso:country":"CN",
    "name:zho_x_preferred":[
        "\u4ec0\u4efd\u7530"
    ],
    "wof:name":"Shifentian",
    "wof:placetype":"locality"
},
  "geometry": {"coordinates":[111.58011999999999,22.10447000000001],"type":"Point"}
}