{
  "type": "Feature",
  "properties": {
    "gn:admin1_code":"12.0",
    "gn:asciiname":"Chongnei Hujia",
    "gn:country_code":"CN",
    "gn:dem":84,
    "gn:feature_class":"P",
    "gn:feature_code":"PPL",
    "gn:name":"Chongnei Hujia",
    "gn:population":0,
    "gn:timezone":"Asia/Shanghai",
    "iso:country":"CN",
    "name:zho_x_preferred":[
        "\u51b2\u5185\u80e1\u5bb6"
    ],
    "wof:name":"Chongnei Hujia",
    "wof:placetype":"locality"
},
  "geometry": {"coordinates":[113.85396,29.34627],"type":"Point"}
}