{
  "type": "Feature",
  "properties": {
    "gn:admin1_code":"12.0",
    "gn:asciiname":"Longping",
    "gn:country_code":"CN",
    "gn:dem":631,
    "gn:feature_class":"P",
    "gn:feature_code":"PPL",
    "gn:name":"Longping",
    "gn:population":0,
    "gn:timezone":"Asia/Shanghai",
    "iso:country":"CN",
    "name:zho_x_preferred":[
        "\u9f99\u576a"
    ],
    "wof:name":"Longping",
    "wof:placetype":"locality"
},
  "geometry": {"coordinates":[109.28740999999999,29.80132],"type":"Point"}
}