{
  "type": "Feature",
  "properties": {
    "gn:admin1_code":"25.0",
    "gn:asciiname":"Jingjiagou",
    "gn:country_code":"CN",
    "gn:dem":179,
    "gn:feature_class":"P",
    "gn:feature_code":"PPL",
    "gn:name":"Jingjiagou",
    "gn:population":0,
    "gn:timezone":"Asia/Shanghai",
    "iso:country":"CN",
    "name:zho_x_preferred":[
        "\u4e95\u5bb6\u6c9f"
    ],
    "wof:name":"Jingjiagou",
    "wof:placetype":"locality"
},
  "geometry": {"coordinates":[119.46221,35.75874],"type":"Point"}
}