{
  "type": "Feature",
  "properties": {
    "gn:admin1_code":"29.0",
    "gn:asciiname":"Changheba",
    "gn:country_code":"CN",
    "gn:dem":1433,
    "gn:feature_class":"P",
    "gn:feature_code":"PPL",
    "gn:name":"Changheba",
    "gn:population":0,
    "gn:timezone":"Asia/Shanghai",
    "iso:country":"CN",
    "name:zho_x_preferred":[
        "\u957f\u6cb3\u575d"
    ],
    "wof:name":"Changheba",
    "wof:placetype":"locality"
},
  "geometry": {"coordinates":[104.563,27.5637],"type":"Point"}
}