{
  "type": "Feature",
  "properties": {
    "gn:admin1_code":"1.0",
    "gn:asciiname":"Weigangcun",
    "gn:country_code":"CN",
    "gn:dem":18,
    "gn:feature_class":"P",
    "gn:feature_code":"PPL",
    "gn:name":"Weigangcun",
    "gn:population":0,
    "gn:timezone":"Asia/Shanghai",
    "iso:country":"CN",
    "name:zho_x_preferred":[
        "\u9b4f\u5c97\u6751"
    ],
    "wof:name":"Weigangcun",
    "wof:placetype":"locality"
},
  "geometry": {"coordinates":[117.25837,32.98661],"type":"Point"}
}