{
  "type": "Feature",
  "properties": {
    "gn:admin1_code":"20",
    "gn:asciiname":"Nan-t'ai-tzu",
    "gn:country_code":"CN",
    "gn:dem":1562,
    "gn:feature_class":"P",
    "gn:feature_code":"PPL",
    "gn:name":"Nan-t\u2019ai-tzu",
    "gn:population":0,
    "gn:timezone":"Asia/Shanghai",
    "iso:country":"CN",
    "wof:name":"Nan-t'ai-tzu",
    "wof:placetype":"locality"
},
  "geometry": {"coordinates":[117.35861,42.7725],"type":"Point"}
}