{
  "type": "Feature",
  "properties": {
    "gn:admin1_code":"12.0",
    "gn:asciiname":"Zhonglongping",
    "gn:country_code":"CN",
    "gn:dem":884,
    "gn:feature_class":"P",
    "gn:feature_code":"PPL",
    "gn:name":"Zhonglongping",
    "gn:population":0,
    "gn:timezone":"Asia/Shanghai",
    "iso:country":"CN",
    "name:zho_x_preferred":[
        "\u4e2d\u9f99\u576a"
    ],
    "wof:name":"Zhonglongping",
    "wof:placetype":"locality"
},
  "geometry": {"coordinates":[110.27845000000001,29.80953],"type":"Point"}
}