{
  "type": "Feature",
  "properties": {
    "gn:admin1_code":"8.0",
    "gn:asciiname":"Libaimaotun",
    "gn:country_code":"CN",
    "gn:dem":177,
    "gn:feature_class":"P",
    "gn:feature_code":"PPL",
    "gn:name":"Libaimaotun",
    "gn:population":0,
    "gn:timezone":"Asia/Shanghai",
    "iso:country":"CN",
    "name:zho_x_preferred":[
        "\u674e\u767d\u6bdb\u5c6f"
    ],
    "wof:name":"Libaimaotun",
    "wof:placetype":"locality"
},
  "geometry": {"coordinates":[123.94917,48.10243],"type":"Point"}
}