{
  "type": "Feature",
  "properties": {
    "gn:admin1_code":"7",
    "gn:asciiname":"Baixikeng",
    "gn:country_code":"CN",
    "gn:dem":781,
    "gn:feature_class":"P",
    "gn:feature_code":"PPL",
    "gn:name":"Baixikeng",
    "gn:population":0,
    "gn:timezone":"Asia/Shanghai",
    "iso:country":"CN",
    "name:zho_x_preferred":[
        "\u767d\u897f\u5751"
    ],
    "wof:name":"Baixikeng",
    "wof:placetype":"locality"
},
  "geometry": {"coordinates":[117.74262,24.92619],"type":"Point"}
}