{
  "type": "Feature",
  "properties": {
    "gn:admin1_code":"7.0",
    "gn:asciiname":"Chixiacun",
    "gn:country_code":"CN",
    "gn:dem":26,
    "gn:feature_class":"P",
    "gn:feature_code":"PPL",
    "gn:name":"Chixiacun",
    "gn:population":0,
    "gn:timezone":"Asia/Shanghai",
    "iso:country":"CN",
    "name:zho_x_preferred":[
        "\u6c60\u4e0b\u6751"
    ],
    "wof:name":"Chixiacun",
    "wof:placetype":"locality"
},
  "geometry": {"coordinates":[119.74101,26.67875],"type":"Point"}
}