{
  "type": "Feature",
  "properties": {
    "gn:admin1_code":"15.0",
    "gn:asciiname":"Xiadongwan",
    "gn:country_code":"CN",
    "gn:dem":2373,
    "gn:feature_class":"P",
    "gn:feature_code":"PPL",
    "gn:name":"Xiadongwan",
    "gn:population":0,
    "gn:timezone":"Asia/Shanghai",
    "iso:country":"CN",
    "name:zho_x_preferred":[
        "\u4e0b\u4e1c\u6e7e"
    ],
    "wof:name":"Xiadongwan",
    "wof:placetype":"locality"
},
  "geometry": {"coordinates":[103.38,35.3116],"type":"Point"}
}