{
  "type": "Feature",
  "properties": {
    "gn:admin1_code":"4.0",
    "gn:asciiname":"Liuli Sancun",
    "gn:country_code":"CN",
    "gn:dem":41,
    "gn:feature_class":"P",
    "gn:feature_code":"PPL",
    "gn:name":"Liuli Sancun",
    "gn:population":0,
    "gn:timezone":"Asia/Shanghai",
    "iso:country":"CN",
    "name:zho_x_preferred":[
        "\u5218\u674e\u4e09\u6751"
    ],
    "wof:name":"Liuli Sancun",
    "wof:placetype":"locality"
},
  "geometry": {"coordinates":[116.68628,34.75592],"type":"Point"}
}