{
  "type": "Feature",
  "properties": {
    "gn:admin1_code":"4.0",
    "gn:asciiname":"Fanghucun",
    "gn:country_code":"CN",
    "gn:dem":27,
    "gn:feature_class":"P",
    "gn:feature_code":"PPL",
    "gn:name":"Fanghucun",
    "gn:population":0,
    "gn:timezone":"Asia/Shanghai",
    "iso:country":"CN",
    "name:zho_x_preferred":[
        "\u623f\u6e56\u6751"
    ],
    "wof:name":"Fanghucun",
    "wof:placetype":"locality"
},
  "geometry": {"coordinates":[118.54688,33.74811],"type":"Point"}
}