{
  "type": "Feature",
  "properties": {
    "gn:admin1_code":"11.0",
    "gn:asciiname":"Zhoujiawuchang",
    "gn:country_code":"CN",
    "gn:dem":546,
    "gn:feature_class":"P",
    "gn:feature_code":"PPL",
    "gn:name":"Zhoujiawuchang",
    "gn:population":0,
    "gn:timezone":"Asia/Shanghai",
    "iso:country":"CN",
    "name:zho_x_preferred":[
        "\u5468\u5bb6\u5c4b\u573a"
    ],
    "wof:name":"Zhoujiawuchang",
    "wof:placetype":"locality"
},
  "geometry": {"coordinates":[112.34855,26.03939],"type":"Point"}
}