{
  "type": "Feature",
  "properties": {
    "gn:admin1_code":"13",
    "gn:asciiname":"Zerifukaner",
    "gn:country_code":"CN",
    "gn:dem":-90,
    "gn:feature_class":"P",
    "gn:feature_code":"PPL",
    "gn:name":"Zerifukaner",
    "gn:population":0,
    "gn:timezone":"Asia/Urumqi",
    "iso:country":"CN",
    "name:und_x_variant":[
        "\u6cfd\u65e5\u752b\u574e\u513f"
    ],
    "wof:name":"Zerifukaner",
    "wof:placetype":"locality"
},
  "geometry": {"coordinates":[89.553,42.76238],"type":"Point"}
}