{
  "type": "Feature",
  "properties": {
    "gn:admin1_code":"25.0",
    "gn:asciiname":"Zhangguantuncun",
    "gn:country_code":"CN",
    "gn:dem":34,
    "gn:feature_class":"P",
    "gn:feature_code":"PPL",
    "gn:name":"Zhangguantuncun",
    "gn:population":0,
    "gn:timezone":"Asia/Shanghai",
    "iso:country":"CN",
    "name:zho_x_preferred":[
        "\u5f20\u5b98\u5c6f\u6751"
    ],
    "wof:name":"Zhangguantuncun",
    "wof:placetype":"locality"
},
  "geometry": {"coordinates":[115.75568,36.88641],"type":"Point"}
}