{
  "type": "Feature",
  "properties": {
    "gn:admin1_code":"9.0",
    "gn:asciiname":"Shuzhuang",
    "gn:country_code":"CN",
    "gn:dem":44,
    "gn:feature_class":"P",
    "gn:feature_code":"PPL",
    "gn:name":"Shuzhuang",
    "gn:population":0,
    "gn:timezone":"Asia/Shanghai",
    "iso:country":"CN",
    "name:zho_x_preferred":[
        "\u675f\u5e84"
    ],
    "wof:name":"Shuzhuang",
    "wof:placetype":"locality"
},
  "geometry": {"coordinates":[114.97731,33.38109],"type":"Point"}
}