{
  "type": "Feature",
  "properties": {
    "gn:admin1_code":"32.0",
    "gn:asciiname":"Danshuigou",
    "gn:country_code":"CN",
    "gn:dem":863,
    "gn:feature_class":"P",
    "gn:feature_code":"PPL",
    "gn:name":"Danshuigou",
    "gn:population":0,
    "gn:timezone":"Asia/Shanghai",
    "iso:country":"CN",
    "name:zho_x_preferred":[
        "\u6de1\u6c34\u6c9f"
    ],
    "wof:name":"Danshuigou",
    "wof:placetype":"locality"
},
  "geometry": {"coordinates":[104.247,31.5577],"type":"Point"}
}