{
  "type": "Feature",
  "properties": {
    "gn:admin1_code":"14.0",
    "gn:asciiname":"Gericun",
    "gn:country_code":"CN",
    "gn:dem":2032,
    "gn:feature_class":"P",
    "gn:feature_code":"PPL",
    "gn:name":"Gericun",
    "gn:population":0,
    "gn:timezone":"Asia/Urumqi",
    "iso:country":"CN",
    "name:zho_x_preferred":[
        "\u683c\u65e5\u6751"
    ],
    "wof:name":"Gericun",
    "wof:placetype":"locality"
},
  "geometry": {"coordinates":[98.25996000000001,28.78272],"type":"Point"}
}