{
  "type": "Feature",
  "properties": {
    "gn:admin1_code":"19.0",
    "gn:asciiname":"Taipu",
    "gn:country_code":"CN",
    "gn:dem":305,
    "gn:feature_class":"P",
    "gn:feature_code":"PPL",
    "gn:name":"Taipu",
    "gn:population":0,
    "gn:timezone":"Asia/Shanghai",
    "iso:country":"CN",
    "name:ceb_x_preferred":[
        "Taipu"
    ],
    "name:swe_x_preferred":[
        "Taipu"
    ],
    "name:und_x_variant":[
        "Taibao"
    ],
    "name:zho_x_preferred":[
        "\u53f0\u5b9d"
    ],
    "wof:name":"Taipu",
    "wof:placetype":"locality"
},
  "geometry": {"coordinates":[124.718,41.6741],"type":"Point"}
}