{
  "type": "Feature",
  "properties": {
    "gn:admin1_code":"32.0",
    "gn:asciiname":"Xikoushang",
    "gn:country_code":"CN",
    "gn:dem":851,
    "gn:feature_class":"P",
    "gn:feature_code":"PPL",
    "gn:name":"Xikoushang",
    "gn:population":0,
    "gn:timezone":"Asia/Shanghai",
    "iso:country":"CN",
    "name:zho_x_preferred":[
        "\u6eaa\u53e3\u4e0a"
    ],
    "wof:name":"Xikoushang",
    "wof:placetype":"locality"
},
  "geometry": {"coordinates":[103.045,30.3242],"type":"Point"}
}