{
  "type": "Feature",
  "properties": {
    "gn:admin1_code":"07",
    "gn:asciiname":"Jujiang",
    "gn:country_code":"CN",
    "gn:dem":-9999,
    "gn:feature_class":"P",
    "gn:feature_code":"PPL",
    "gn:name":"Jujiang",
    "gn:population":0,
    "gn:timezone":"Asia/Shanghai",
    "iso:country":"CN",
    "name:zho_x_preferred":[
        "\u6dd7\u6c5f"
    ],
    "wof:name":"Jujiang",
    "wof:placetype":"locality"
},
  "geometry": {"coordinates":[118.35556,24.57619],"type":"Point"}
}