{
  "type": "Feature",
  "properties": {
    "gn:admin1_code":"9",
    "gn:asciiname":"Qianlichang",
    "gn:country_code":"CN",
    "gn:dem":71,
    "gn:feature_class":"P",
    "gn:feature_code":"PPL",
    "gn:name":"Qianlichang",
    "gn:population":0,
    "gn:timezone":"Asia/Shanghai",
    "iso:country":"CN",
    "name:zho_x_preferred":[
        "\u524d\u674e\u573a"
    ],
    "wof:name":"Qianlichang",
    "wof:placetype":"locality"
},
  "geometry": {"coordinates":[114.95399999999999,34.9184],"type":"Point"}
}