{
  "type": "Feature",
  "properties": {
    "gn:admin1_code":"29.0",
    "gn:asciiname":"Jiangwei",
    "gn:country_code":"CN",
    "gn:dem":1518,
    "gn:feature_class":"P",
    "gn:feature_code":"PPL",
    "gn:name":"Jiangwei",
    "gn:population":0,
    "gn:timezone":"Asia/Shanghai",
    "iso:country":"CN",
    "name:zho_x_preferred":[
        "\u6c5f\u5c3e"
    ],
    "wof:name":"Jiangwei",
    "wof:placetype":"locality"
},
  "geometry": {"coordinates":[104.23,24.8735],"type":"Point"}
}