{
  "type": "Feature",
  "properties": {
    "gn:admin1_code":"12.0",
    "gn:asciiname":"Ganwan",
    "gn:country_code":"CN",
    "gn:dem":762,
    "gn:feature_class":"P",
    "gn:feature_code":"PPL",
    "gn:name":"Ganwan",
    "gn:population":0,
    "gn:timezone":"Asia/Shanghai",
    "iso:country":"CN",
    "name:zho_x_preferred":[
        "\u5e72\u6e7e"
    ],
    "wof:name":"Ganwan",
    "wof:placetype":"locality"
},
  "geometry": {"coordinates":[110.50239999999999,29.77548],"type":"Point"}
}