{
  "type": "Feature",
  "properties": {
    "gn:admin1_code":"32.0",
    "gn:asciiname":"Nanhekan",
    "gn:country_code":"CN",
    "gn:dem":503,
    "gn:feature_class":"P",
    "gn:feature_code":"PPL",
    "gn:name":"Nanhekan",
    "gn:population":0,
    "gn:timezone":"Asia/Shanghai",
    "iso:country":"CN",
    "name:zho_x_preferred":[
        "\u5357\u6cb3\u574e"
    ],
    "wof:name":"Nanhekan",
    "wof:placetype":"locality"
},
  "geometry": {"coordinates":[103.45462000000001,30.39072],"type":"Point"}
}