{
  "type": "Feature",
  "properties": {
    "gn:admin1_code":"1.0",
    "gn:asciiname":"Longgeng",
    "gn:country_code":"CN",
    "gn:dem":18,
    "gn:feature_class":"P",
    "gn:feature_code":"PPL",
    "gn:name":"Longgeng",
    "gn:population":0,
    "gn:timezone":"Asia/Shanghai",
    "iso:country":"CN",
    "name:zho_x_preferred":[
        "\u5784\u57c2"
    ],
    "wof:name":"Longgeng",
    "wof:placetype":"locality"
},
  "geometry": {"coordinates":[118.1634,31.14414],"type":"Point"}
}