{
  "type": "Feature",
  "properties": {
    "gn:admin1_code":"30.0",
    "gn:asciiname":"Baiyucun",
    "gn:country_code":"CN",
    "gn:dem":519,
    "gn:feature_class":"P",
    "gn:feature_code":"PPL",
    "gn:name":"Baiyucun",
    "gn:population":0,
    "gn:timezone":"Asia/Shanghai",
    "iso:country":"CN",
    "name:und_x_variant":[
        "Baiyun"
    ],
    "name:zho_x_preferred":[
        "\u767d\u7389\u6751"
    ],
    "wof:name":"Baiyucun",
    "wof:placetype":"locality"
},
  "geometry": {"coordinates":[116.37103,24.67426],"type":"Point"}
}