{
  "type": "Feature",
  "properties": {
    "gn:admin1_code":"26.0",
    "gn:asciiname":"Caijiahecun",
    "gn:country_code":"CN",
    "gn:dem":1056,
    "gn:feature_class":"P",
    "gn:feature_code":"PPL",
    "gn:name":"Caijiahecun",
    "gn:population":0,
    "gn:timezone":"Asia/Shanghai",
    "iso:country":"CN",
    "name:zho_x_preferred":[
        "\u8521\u5bb6\u6cb3\u6751"
    ],
    "wof:name":"Caijiahecun",
    "wof:placetype":"locality"
},
  "geometry": {"coordinates":[108.29098,34.98282],"type":"Point"}
}