{
  "type": "Feature",
  "properties": {
    "gn:admin1_code":"30",
    "gn:asciiname":"Dongqianxi",
    "gn:country_code":"CN",
    "gn:dem":10,
    "gn:feature_class":"P",
    "gn:feature_code":"PPL",
    "gn:name":"Dongqianxi",
    "gn:population":0,
    "gn:timezone":"Asia/Shanghai",
    "iso:country":"CN",
    "name:zho_x_preferred":[
        "\u4e1c\u524d\u6eaa"
    ],
    "wof:name":"Dongqianxi",
    "wof:placetype":"locality"
},
  "geometry": {"coordinates":[116.75400999999999,23.51783],"type":"Point"}
}