{
  "type": "Feature",
  "properties": {
    "gn:admin1_code":"9",
    "gn:asciiname":"Yuangudui",
    "gn:country_code":"CN",
    "gn:dem":70,
    "gn:feature_class":"P",
    "gn:feature_code":"PPL",
    "gn:name":"Yuangudui",
    "gn:population":0,
    "gn:timezone":"Asia/Shanghai",
    "iso:country":"CN",
    "name:zho_x_preferred":[
        "\u8881\u580c\u5806"
    ],
    "wof:name":"Yuangudui",
    "wof:placetype":"locality"
},
  "geometry": {"coordinates":[115.056,34.9235],"type":"Point"}
}