{
  "type": "Feature",
  "properties": {
    "gn:admin1_code":"29.0",
    "gn:asciiname":"Laocangzhai",
    "gn:country_code":"CN",
    "gn:dem":1302,
    "gn:feature_class":"P",
    "gn:feature_code":"PPL",
    "gn:name":"Laocangzhai",
    "gn:population":0,
    "gn:timezone":"Asia/Shanghai",
    "iso:country":"CN",
    "name:zho_x_preferred":[
        "\u8001\u4ed3\u5be8"
    ],
    "wof:name":"Laocangzhai",
    "wof:placetype":"locality"
},
  "geometry": {"coordinates":[101.776,22.9954],"type":"Point"}
}