{
  "type": "Feature",
  "properties": {
    "gn:admin1_code":"19.0",
    "gn:asciiname":"Baiyingao",
    "gn:country_code":"CN",
    "gn:dem":149,
    "gn:feature_class":"P",
    "gn:feature_code":"PPL",
    "gn:name":"Baiyingao",
    "gn:population":0,
    "gn:timezone":"Asia/Shanghai",
    "iso:country":"CN",
    "name:und_x_variant":[
        "\u767d\u97f3\u768b"
    ],
    "name:zho_x_preferred":[
        "\u767d\u97f3\u768b"
    ],
    "wof:name":"Baiyingao",
    "wof:placetype":"locality"
},
  "geometry": {"coordinates":[122.80356,42.61507],"type":"Point"}
}