{
  "type": "Feature",
  "properties": {
    "gn:admin1_code":"25",
    "gn:asciiname":"Donggao'anran",
    "gn:country_code":"CN",
    "gn:dem":22,
    "gn:feature_class":"P",
    "gn:feature_code":"PPL",
    "gn:name":"Donggao\u2019anran",
    "gn:population":0,
    "gn:timezone":"Asia/Shanghai",
    "iso:country":"CN",
    "name:und_x_variant":[
        "Donggao\u2019anran"
    ],
    "name:zho_x_preferred":[
        "\u4e1c\u9ad8\u5b89\u7136"
    ],
    "wof:name":"Donggao'anran",
    "wof:placetype":"locality"
},
  "geometry": {"coordinates":[116.693,37.3465],"type":"Point"}
}