{
  "type": "Feature",
  "properties": {
    "gn:admin1_code":"26.0",
    "gn:asciiname":"Baixinzhuang",
    "gn:country_code":"CN",
    "gn:dem":1686,
    "gn:feature_class":"P",
    "gn:feature_code":"PPL",
    "gn:name":"Baixinzhuang",
    "gn:population":0,
    "gn:timezone":"Asia/Shanghai",
    "iso:country":"CN",
    "name:zho_x_preferred":[
        "\u767d\u65b0\u5e84"
    ],
    "wof:name":"Baixinzhuang",
    "wof:placetype":"locality"
},
  "geometry": {"coordinates":[107.44092000000001,37.28893],"type":"Point"}
}