{
  "type": "Feature",
  "properties": {
    "gn:admin1_code":"18",
    "gn:asciiname":"Gaoshizhuang",
    "gn:country_code":"CN",
    "gn:dem":1104,
    "gn:feature_class":"P",
    "gn:feature_code":"PPL",
    "gn:name":"Gaoshizhuang",
    "gn:population":0,
    "gn:timezone":"Asia/Shanghai",
    "iso:country":"CN",
    "name:zho_x_preferred":[
        "\u9ad8\u77f3\u6869"
    ],
    "wof:name":"Gaoshizhuang",
    "wof:placetype":"locality"
},
  "geometry": {"coordinates":[107.86199999999999,27.5073],"type":"Point"}
}