{
  "type": "Feature",
  "properties": {
    "gn:admin1_code":"11.0",
    "gn:asciiname":"Dapingtou",
    "gn:country_code":"CN",
    "gn:dem":426,
    "gn:feature_class":"P",
    "gn:feature_code":"PPL",
    "gn:name":"Dapingtou",
    "gn:population":0,
    "gn:timezone":"Asia/Shanghai",
    "iso:country":"CN",
    "name:zho_x_preferred":[
        "\u5927\u576a\u5934"
    ],
    "wof:name":"Dapingtou",
    "wof:placetype":"locality"
},
  "geometry": {"coordinates":[110.09963,26.5527],"type":"Point"}
}