{
  "type": "Feature",
  "properties": {
    "gn:admin1_code":"12.0",
    "gn:asciiname":"Caochong",
    "gn:country_code":"CN",
    "gn:dem":152,
    "gn:feature_class":"P",
    "gn:feature_code":"PPL",
    "gn:name":"Caochong",
    "gn:population":0,
    "gn:timezone":"Asia/Shanghai",
    "iso:country":"CN",
    "name:zho_x_preferred":[
        "\u8349\u51b2"
    ],
    "wof:name":"Caochong",
    "wof:placetype":"locality"
},
  "geometry": {"coordinates":[113.28252999999999,31.2506],"type":"Point"}
}