{
  "type": "Feature",
  "properties": {
    "gn:admin1_code":"14",
    "gn:asciiname":"Lungring",
    "gn:country_code":"CN",
    "gn:dem":4417,
    "gn:feature_class":"P",
    "gn:feature_code":"PPL",
    "gn:name":"Lungring",
    "gn:population":0,
    "gn:timezone":"Asia/Urumqi",
    "iso:country":"CN",
    "name:bod_x_preferred":[
        "\u0f63\u0f74\u0f44\u0f0b\u0f62\u0f72\u0f44"
    ],
    "name:und_x_variant":[
        "Longren"
    ],
    "name:zho_x_preferred":[
        "\u9f99\u4ec1"
    ],
    "wof:name":"Lungring",
    "wof:placetype":"locality"
},
  "geometry": {"coordinates":[91.32016,30.50075],"type":"Point"}
}