{
  "type": "Feature",
  "properties": {
    "gn:admin1_code":"29.0",
    "gn:asciiname":"Zhangmen",
    "gn:country_code":"CN",
    "gn:dem":1559,
    "gn:feature_class":"P",
    "gn:feature_code":"PPL",
    "gn:name":"Zhangmen",
    "gn:population":0,
    "gn:timezone":"Asia/Shanghai",
    "iso:country":"CN",
    "name:zho_x_preferred":[
        "\u7ae0\u95e8"
    ],
    "wof:name":"Zhangmen",
    "wof:placetype":"locality"
},
  "geometry": {"coordinates":[101.215,24.1514],"type":"Point"}
}