{
  "type": "Feature",
  "properties": {
    "gn:admin1_code":"19.0",
    "gn:asciiname":"Guodafa",
    "gn:country_code":"CN",
    "gn:dem":138,
    "gn:feature_class":"P",
    "gn:feature_code":"PPL",
    "gn:name":"Guodafa",
    "gn:population":0,
    "gn:timezone":"Asia/Shanghai",
    "iso:country":"CN",
    "name:zho_x_preferred":[
        "\u90ed\u5927\u53d1"
    ],
    "wof:name":"Guodafa",
    "wof:placetype":"locality"
},
  "geometry": {"coordinates":[121.83344,41.75559000000001],"type":"Point"}
}