{
  "type": "Feature",
  "properties": {
    "gn:admin1_code":"11.0",
    "gn:asciiname":"Chayewan",
    "gn:country_code":"CN",
    "gn:dem":735,
    "gn:feature_class":"P",
    "gn:feature_code":"PPL",
    "gn:name":"Chayewan",
    "gn:population":0,
    "gn:timezone":"Asia/Shanghai",
    "iso:country":"CN",
    "name:zho_x_preferred":[
        "\u8336\u53f6\u5f2f"
    ],
    "wof:name":"Chayewan",
    "wof:placetype":"locality"
},
  "geometry": {"coordinates":[110.6071,29.5087],"type":"Point"}
}