{
  "type": "Feature",
  "properties": {
    "gn:admin1_code":"4.0",
    "gn:asciiname":"Qudong",
    "gn:country_code":"CN",
    "gn:dem":-1,
    "gn:feature_class":"P",
    "gn:feature_code":"PPL",
    "gn:name":"Qudong",
    "gn:population":0,
    "gn:timezone":"Asia/Shanghai",
    "iso:country":"CN",
    "name:und_x_variant":[
        "\u6e20\u4e1c"
    ],
    "wof:name":"Qudong",
    "wof:placetype":"locality"
},
  "geometry": {"coordinates":[120.25319,33.9502],"type":"Point"}
}