{
  "type": "Feature",
  "properties": {
    "gn:admin1_code":"11.0",
    "gn:asciiname":"Shangshidong",
    "gn:country_code":"CN",
    "gn:dem":274,
    "gn:feature_class":"P",
    "gn:feature_code":"PPL",
    "gn:name":"Shangshidong",
    "gn:population":0,
    "gn:timezone":"Asia/Shanghai",
    "iso:country":"CN",
    "name:zho_x_preferred":[
        "\u4e0a\u77f3\u6d1e"
    ],
    "wof:name":"Shangshidong",
    "wof:placetype":"locality"
},
  "geometry": {"coordinates":[111.99088999999999,26.99526],"type":"Point"}
}