{
  "type": "Feature",
  "properties": {
    "gn:admin1_code":"08",
    "gn:asciiname":"Zhangyutun",
    "gn:country_code":"CN",
    "gn:dem":247,
    "gn:feature_class":"P",
    "gn:feature_code":"PPL",
    "gn:name":"Zhangyutun",
    "gn:population":0,
    "gn:timezone":"Asia/Shanghai",
    "iso:country":"CN",
    "name:und_x_variant":[
        "Ch\u2019eng-pai-lu-t\u2019un",
        "Zhangyutun"
    ],
    "name:zho_x_preferred":[
        "\u5f20\u7fbd\u5c6f"
    ],
    "wof:name":"Zhangyutun",
    "wof:placetype":"locality"
},
  "geometry": {"coordinates":[126.36062,48.19876],"type":"Point"}
}