{
  "type": "Feature",
  "properties": {
    "gn:admin1_code":"02",
    "gn:asciiname":"Shanxialiu",
    "gn:cc2":"CN",
    "gn:country_code":"CN",
    "gn:dem":53,
    "gn:feature_class":"P",
    "gn:feature_code":"PPL",
    "gn:name":"Shanxialiu",
    "gn:population":0,
    "gn:timezone":"Asia/Shanghai",
    "iso:country":"CN",
    "name:und_x_variant":[
        "Shan-hsia",
        "Shanxialiu"
    ],
    "name:zho_x_preferred":[
        "\u5c71\u4e0b\u5218"
    ],
    "wof:name":"Shanxialiu",
    "wof:placetype":"locality"
},
  "geometry": {"coordinates":[121.37860999999999,29.40722],"type":"Point"}
}