{
  "type": "Feature",
  "properties": {
    "gn:admin1_code":"8.0",
    "gn:asciiname":"Laodong",
    "gn:country_code":"CN",
    "gn:dem":212,
    "gn:feature_class":"P",
    "gn:feature_code":"PPLA4",
    "gn:name":"Laodong",
    "gn:population":0,
    "gn:timezone":"Asia/Shanghai",
    "iso:country":"CN",
    "name:und_x_variant":[
        "Laodong Xiang"
    ],
    "name:zho_x_preferred":[
        "\u52b3\u52a8"
    ],
    "name:zho_x_variant":[
        "\u52b3\u52a8\u4e61"
    ],
    "wof:name":"Laodong",
    "wof:placetype":"locality"
},
  "geometry": {"coordinates":[125.93198999999998,46.75494000000001],"type":"Point"}
}