{
  "type": "Feature",
  "properties": {
    "gn:admin1_code":"4.0",
    "gn:asciiname":"Zhenmeng",
    "gn:country_code":"CN",
    "gn:dem":7,
    "gn:feature_class":"P",
    "gn:feature_code":"PPL",
    "gn:name":"Zhenmeng",
    "gn:population":0,
    "gn:timezone":"Asia/Shanghai",
    "iso:country":"CN",
    "name:und_x_variant":[
        "\u9707\u8499"
    ],
    "wof:name":"Zhenmeng",
    "wof:placetype":"locality"
},
  "geometry": {"coordinates":[121.0891,31.97443],"type":"Point"}
}