{
  "type": "Feature",
  "properties": {
    "gn:admin1_code":"6.0",
    "gn:asciiname":"Xielangkou",
    "gn:country_code":"CN",
    "gn:dem":4415,
    "gn:feature_class":"P",
    "gn:feature_code":"PPL",
    "gn:name":"Xielangkou",
    "gn:population":0,
    "gn:timezone":"Asia/Urumqi",
    "iso:country":"CN",
    "name:zho_x_preferred":[
        "\u534f\u6d6a\u6263"
    ],
    "wof:name":"Xielangkou",
    "wof:placetype":"locality"
},
  "geometry": {"coordinates":[96.72797,33.05038],"type":"Point"}
}