{
  "type": "Feature",
  "properties": {
    "gn:admin1_code":"19.0",
    "gn:asciiname":"Xiaojiayingzi",
    "gn:country_code":"CN",
    "gn:dem":763,
    "gn:feature_class":"P",
    "gn:feature_code":"PPL",
    "gn:name":"Xiaojiayingzi",
    "gn:population":0,
    "gn:timezone":"Asia/Shanghai",
    "iso:country":"CN",
    "name:und_x_variant":[
        "\u8096\u5bb6\u8425\u5b50"
    ],
    "name:zho_x_preferred":[
        "\u8096\u5bb6\u8425\u5b50"
    ],
    "wof:name":"Xiaojiayingzi",
    "wof:placetype":"locality"
},
  "geometry": {"coordinates":[119.87665,41.54183],"type":"Point"}
}