{
  "type": "Feature",
  "properties": {
    "gn:admin1_code":"32.0",
    "gn:asciiname":"Zumu",
    "gn:country_code":"CN",
    "gn:dem":2851,
    "gn:feature_class":"P",
    "gn:feature_code":"PPL",
    "gn:name":"Zumu",
    "gn:population":0,
    "gn:timezone":"Asia/Shanghai",
    "iso:country":"CN",
    "name:zho_x_preferred":[
        "\u8db3\u6728"
    ],
    "wof:name":"Zumu",
    "wof:placetype":"locality"
},
  "geometry": {"coordinates":[101.465,27.756],"type":"Point"}
}