{
  "type": "Feature",
  "properties": {
    "gn:admin1_code":"30",
    "gn:asciiname":"Meihua",
    "gn:country_code":"CN",
    "gn:dem":429,
    "gn:feature_class":"P",
    "gn:feature_code":"PPLA4",
    "gn:name":"Meihua",
    "gn:population":0,
    "gn:timezone":"Asia/Shanghai",
    "iso:country":"CN",
    "name:und_x_variant":[
        "\u6885\u82b1",
        "Meihua Zhen",
        "\u6885\u82b1\u9547"
    ],
    "wof:name":"Meihua",
    "wof:placetype":"locality"
},
  "geometry": {"coordinates":[113.07341,25.17678],"type":"Point"}
}