{
  "type": "Feature",
  "properties": {
    "gn:admin1_code":"26",
    "gn:asciiname":"Fengyangpo",
    "gn:country_code":"CN",
    "gn:dem":518,
    "gn:feature_class":"P",
    "gn:feature_code":"PPL",
    "gn:name":"Fengyangpo",
    "gn:population":0,
    "gn:timezone":"Asia/Shanghai",
    "iso:country":"CN",
    "name:zho_x_preferred":[
        "\u98ce\u9633\u5761"
    ],
    "wof:name":"Fengyangpo",
    "wof:placetype":"locality"
},
  "geometry": {"coordinates":[108.21589,34.3304],"type":"Point"}
}