{
  "type": "Feature",
  "properties": {
    "gn:admin1_code":"16.0",
    "gn:asciiname":"Liujin",
    "gn:country_code":"CN",
    "gn:dem":461,
    "gn:feature_class":"P",
    "gn:feature_code":"PPL",
    "gn:name":"Liujin",
    "gn:population":0,
    "gn:timezone":"Asia/Shanghai",
    "iso:country":"CN",
    "name:zho_x_preferred":[
        "\u516d\u8fdb"
    ],
    "wof:name":"Liujin",
    "wof:placetype":"locality"
},
  "geometry": {"coordinates":[110.401,24.1549],"type":"Point"}
}