{
  "type": "Feature",
  "properties": {
    "gn:admin1_code":"4.0",
    "gn:asciiname":"Qiuduncun",
    "gn:country_code":"CN",
    "gn:dem":6,
    "gn:feature_class":"P",
    "gn:feature_code":"PPL",
    "gn:name":"Qiuduncun",
    "gn:population":0,
    "gn:timezone":"Asia/Shanghai",
    "iso:country":"CN",
    "name:zho_x_preferred":[
        "\u90b1\u58a9\u6751"
    ],
    "wof:name":"Qiuduncun",
    "wof:placetype":"locality"
},
  "geometry": {"coordinates":[120.76251000000001,32.65149],"type":"Point"}
}