{
  "type": "Feature",
  "properties": {
    "gn:admin1_code":"20.0",
    "gn:asciiname":"Qinghe",
    "gn:country_code":"CN",
    "gn:dem":316,
    "gn:feature_class":"P",
    "gn:feature_code":"PPL",
    "gn:name":"Qinghe",
    "gn:population":0,
    "gn:timezone":"Asia/Shanghai",
    "iso:country":"CN",
    "name:zho_x_preferred":[
        "\u5e86\u548c"
    ],
    "wof:name":"Qinghe",
    "wof:placetype":"locality"
},
  "geometry": {"coordinates":[124.62744000000001,49.42189000000001],"type":"Point"}
}