{
  "type": "Feature",
  "properties": {
    "gn:admin1_code":"5.0",
    "gn:asciiname":"Xixinli",
    "gn:country_code":"CN",
    "gn:dem":167,
    "gn:feature_class":"P",
    "gn:feature_code":"PPL",
    "gn:name":"Xixinli",
    "gn:population":0,
    "gn:timezone":"Asia/Shanghai",
    "iso:country":"CN",
    "name:zho_x_preferred":[
        "\u897f\u65b0\u7acb"
    ],
    "wof:name":"Xixinli",
    "wof:placetype":"locality"
},
  "geometry": {"coordinates":[122.50415,44.69047],"type":"Point"}
}