{
  "type": "Feature",
  "properties": {
    "gn:admin1_code":"3.0",
    "gn:asciiname":"Zhongcun",
    "gn:country_code":"CN",
    "gn:dem":299,
    "gn:feature_class":"P",
    "gn:feature_code":"PPL",
    "gn:name":"Zhongcun",
    "gn:population":0,
    "gn:timezone":"Asia/Shanghai",
    "iso:country":"CN",
    "name:und_x_variant":[
        "\u4e2d\u6751"
    ],
    "wof:name":"Zhongcun",
    "wof:placetype":"locality"
},
  "geometry": {"coordinates":[116.35363999999998,26.0805],"type":"Point"}
}