{
  "type": "Feature",
  "properties": {
    "gn:admin1_code":"11.0",
    "gn:asciiname":"Wugongqi",
    "gn:country_code":"CN",
    "gn:dem":640,
    "gn:feature_class":"P",
    "gn:feature_code":"PPL",
    "gn:name":"Wugongqi",
    "gn:population":0,
    "gn:timezone":"Asia/Shanghai",
    "iso:country":"CN",
    "name:zho_x_preferred":[
        "\u8708\u86a3\u5c90"
    ],
    "wof:name":"Wugongqi",
    "wof:placetype":"locality"
},
  "geometry": {"coordinates":[111.95648,24.85976],"type":"Point"}
}