{
  "type": "Feature",
  "properties": {
    "gn:admin1_code":"18.0",
    "gn:asciiname":"Wengbingchong",
    "gn:country_code":"CN",
    "gn:dem":1014,
    "gn:feature_class":"P",
    "gn:feature_code":"PPL",
    "gn:name":"Wengbingchong",
    "gn:population":0,
    "gn:timezone":"Asia/Shanghai",
    "iso:country":"CN",
    "name:zho_x_preferred":[
        "\u7fc1\u4e19\u51b2"
    ],
    "wof:name":"Wengbingchong",
    "wof:placetype":"locality"
},
  "geometry": {"coordinates":[107.658,25.985],"type":"Point"}
}