{
  "type": "Feature",
  "properties": {
    "gn:admin1_code":"5.0",
    "gn:asciiname":"Liangwocun",
    "gn:country_code":"CN",
    "gn:dem":133,
    "gn:feature_class":"P",
    "gn:feature_code":"PPL",
    "gn:name":"Liangwocun",
    "gn:population":0,
    "gn:timezone":"Asia/Shanghai",
    "iso:country":"CN",
    "name:zho_x_preferred":[
        "\u7cae\u7a9d\u6751"
    ],
    "wof:name":"Liangwocun",
    "wof:placetype":"locality"
},
  "geometry": {"coordinates":[124.90102,45.09508],"type":"Point"}
}