{
  "type": "Feature",
  "properties": {
    "gn:admin1_code":"14.0",
    "gn:asciiname":"Duozhacun",
    "gn:country_code":"CN",
    "gn:dem":4118,
    "gn:feature_class":"P",
    "gn:feature_code":"PPL",
    "gn:name":"Duozhacun",
    "gn:population":0,
    "gn:timezone":"Asia/Urumqi",
    "iso:country":"CN",
    "name:zho_x_preferred":[
        "\u591a\u4e4d\u6751"
    ],
    "wof:name":"Duozhacun",
    "wof:placetype":"locality"
},
  "geometry": {"coordinates":[92.4457,28.96824],"type":"Point"}
}