{
  "type": "Feature",
  "properties": {
    "gn:admin1_code":"19.0",
    "gn:asciiname":"Huangshalu",
    "gn:country_code":"CN",
    "gn:dem":172,
    "gn:feature_class":"P",
    "gn:feature_code":"PPL",
    "gn:name":"Huangshalu",
    "gn:population":0,
    "gn:timezone":"Asia/Shanghai",
    "iso:country":"CN",
    "name:und_x_variant":[
        "\u9ec4\u6c99\u8def"
    ],
    "wof:name":"Huangshalu",
    "wof:placetype":"locality"
},
  "geometry": {"coordinates":[124.55453,41.98315],"type":"Point"}
}