{
  "type": "Feature",
  "properties": {
    "gn:admin1_code":"01",
    "gn:asciiname":"Dahuaping",
    "gn:cc2":"CN",
    "gn:country_code":"CN",
    "gn:dem":247,
    "gn:feature_class":"P",
    "gn:feature_code":"PPL",
    "gn:name":"Dahuaping",
    "gn:population":0,
    "gn:timezone":"Asia/Shanghai",
    "iso:country":"CN",
    "name:und_x_variant":[
        "Ta-hua-p\u2019ing",
        "Dahuaping"
    ],
    "wof:name":"Dahuaping",
    "wof:placetype":"locality"
},
  "geometry": {"coordinates":[116.21222,31.22944],"type":"Point"}
}