{
  "type": "Feature",
  "properties": {
    "gn:admin1_code":"10",
    "gn:asciiname":"Binggoumenzi",
    "gn:country_code":"CN",
    "gn:dem":436,
    "gn:feature_class":"P",
    "gn:feature_code":"PPL",
    "gn:name":"Binggoumenzi",
    "gn:population":0,
    "gn:timezone":"Asia/Shanghai",
    "iso:country":"CN",
    "name:zho_x_preferred":[
        "\u51b0\u6c9f\u95e8\u5b50"
    ],
    "wof:name":"Binggoumenzi",
    "wof:placetype":"locality"
},
  "geometry": {"coordinates":[118.94499,40.60047],"type":"Point"}
}