{
  "type": "Feature",
  "properties": {
    "gn:admin1_code":"29.0",
    "gn:asciiname":"Tangbugu",
    "gn:country_code":"CN",
    "gn:dem":3246,
    "gn:feature_class":"P",
    "gn:feature_code":"PPL",
    "gn:name":"Tangbugu",
    "gn:population":0,
    "gn:timezone":"Asia/Shanghai",
    "iso:country":"CN",
    "name:zho_x_preferred":[
        "\u5858\u5e03\u8c37"
    ],
    "wof:name":"Tangbugu",
    "wof:placetype":"locality"
},
  "geometry": {"coordinates":[99.73690000000001,27.6136],"type":"Point"}
}