{
  "type": "Feature",
  "properties": {
    "gn:admin1_code":"8.0",
    "gn:asciiname":"Yuxincun",
    "gn:country_code":"CN",
    "gn:dem":111,
    "gn:feature_class":"P",
    "gn:feature_code":"PPL",
    "gn:name":"Yuxincun",
    "gn:population":0,
    "gn:timezone":"Asia/Shanghai",
    "iso:country":"CN",
    "name:zho_x_preferred":[
        "\u88d5\u65b0\u6751"
    ],
    "wof:name":"Yuxincun",
    "wof:placetype":"locality"
},
  "geometry": {"coordinates":[130.50901000000002,46.70004],"type":"Point"}
}