{
  "type": "Feature",
  "properties": {
    "gn:admin1_code":"11",
    "gn:asciiname":"Xiaochongyuan",
    "gn:country_code":"CN",
    "gn:dem":737,
    "gn:feature_class":"P",
    "gn:feature_code":"PPL",
    "gn:name":"Xiaochongyuan",
    "gn:population":0,
    "gn:timezone":"Asia/Shanghai",
    "iso:country":"CN",
    "name:und_x_variant":[
        "\u5c0f\u51b2\u6c85",
        "Xiaochongyuan"
    ],
    "wof:name":"Xiaochongyuan",
    "wof:placetype":"locality"
},
  "geometry": {"coordinates":[112.13889,25.11333],"type":"Point"}
}