{
  "type": "Feature",
  "properties": {
    "gn:admin1_code":"12.0",
    "gn:asciiname":"Yanjia Chang",
    "gn:country_code":"CN",
    "gn:dem":28,
    "gn:feature_class":"P",
    "gn:feature_code":"PPL",
    "gn:name":"Yanjia Chang",
    "gn:population":0,
    "gn:timezone":"Asia/Shanghai",
    "iso:country":"CN",
    "name:zho_x_preferred":[
        "\u4e25\u5bb6\u573a"
    ],
    "wof:name":"Yanjia Chang",
    "wof:placetype":"locality"
},
  "geometry": {"coordinates":[112.72607000000001,30.0338],"type":"Point"}
}