{
  "type": "Feature",
  "properties": {
    "gn:admin1_code":"18.0",
    "gn:asciiname":"Xialeitang",
    "gn:country_code":"CN",
    "gn:dem":679,
    "gn:feature_class":"P",
    "gn:feature_code":"PPL",
    "gn:name":"Xialeitang",
    "gn:population":0,
    "gn:timezone":"Asia/Shanghai",
    "iso:country":"CN",
    "name:zho_x_preferred":[
        "\u4e0b\u96f7\u5858"
    ],
    "wof:name":"Xialeitang",
    "wof:placetype":"locality"
},
  "geometry": {"coordinates":[107.77200000000001,26.1539],"type":"Point"}
}