{
  "type": "Feature",
  "properties": {
    "gn:admin1_code":"11.0",
    "gn:asciiname":"Songmaochong",
    "gn:country_code":"CN",
    "gn:dem":86,
    "gn:feature_class":"P",
    "gn:feature_code":"PPL",
    "gn:name":"Songmaochong",
    "gn:population":0,
    "gn:timezone":"Asia/Shanghai",
    "iso:country":"CN",
    "name:zho_x_preferred":[
        "\u677e\u6bdb\u51b2"
    ],
    "wof:name":"Songmaochong",
    "wof:placetype":"locality"
},
  "geometry": {"coordinates":[113.22495000000001,27.88766],"type":"Point"}
}