{
  "type": "Feature",
  "properties": {
    "gn:admin1_code":"21.0",
    "gn:asciiname":"Zhengshanzhuang",
    "gn:country_code":"CN",
    "gn:dem":1742,
    "gn:feature_class":"P",
    "gn:feature_code":"PPL",
    "gn:name":"Zhengshanzhuang",
    "gn:population":0,
    "gn:timezone":"Asia/Shanghai",
    "iso:country":"CN",
    "name:und_x_variant":[
        "\u90d1\u5c71\u5e84"
    ],
    "name:zho_x_preferred":[
        "\u90d1\u5c71\u5e84"
    ],
    "wof:name":"Zhengshanzhuang",
    "wof:placetype":"locality"
},
  "geometry": {"coordinates":[106.74126,36.05068],"type":"Point"}
}