{
  "type": "Feature",
  "properties": {
    "gn:admin1_code":"9.0",
    "gn:asciiname":"Nanguzhuang",
    "gn:country_code":"CN",
    "gn:dem":234,
    "gn:feature_class":"P",
    "gn:feature_code":"PPLA4",
    "gn:name":"Nanguzhuang",
    "gn:population":0,
    "gn:timezone":"Asia/Shanghai",
    "iso:country":"CN",
    "name:und_x_variant":[
        "Nanguzhuang Jiedao",
        "\u5357\u987e\u5e84\u8857\u9053",
        "Nanguzhuang"
    ],
    "name:zho_x_preferred":[
        "\u5357\u987e\u5e84"
    ],
    "wof:name":"Nanguzhuang",
    "wof:placetype":"locality"
},
  "geometry": {"coordinates":[112.87657,33.90019],"type":"Point"}
}