{
  "type": "Feature",
  "properties": {
    "gn:admin1_code":"9.0",
    "gn:asciiname":"Heishiwa",
    "gn:country_code":"CN",
    "gn:dem":710,
    "gn:feature_class":"P",
    "gn:feature_code":"PPL",
    "gn:name":"Heishiwa",
    "gn:population":0,
    "gn:timezone":"Asia/Shanghai",
    "iso:country":"CN",
    "name:und_x_variant":[
        "\u9ed1\u77f3\u6d3c",
        "Heishiwa"
    ],
    "wof:name":"Heishiwa",
    "wof:placetype":"locality"
},
  "geometry": {"coordinates":[112.1508,33.61479],"type":"Point"}
}