{
  "type": "Feature",
  "properties": {
    "gn:admin1_code":"14.0",
    "gn:asciiname":"Wanong",
    "gn:country_code":"CN",
    "gn:dem":4363,
    "gn:feature_class":"P",
    "gn:feature_code":"PPL",
    "gn:name":"Wanong",
    "gn:population":0,
    "gn:timezone":"Asia/Urumqi",
    "iso:country":"CN",
    "name:zho_x_preferred":[
        "\u74e6\u5f04"
    ],
    "wof:name":"Wanong",
    "wof:placetype":"locality"
},
  "geometry": {"coordinates":[96.10871,30.78723],"type":"Point"}
}