{
  "type": "Feature",
  "properties": {
    "gn:admin1_code":"14.0",
    "gn:asciiname":"Layuecun",
    "gn:country_code":"CN",
    "gn:dem":2605,
    "gn:feature_class":"P",
    "gn:feature_code":"PPL",
    "gn:name":"Layuecun",
    "gn:population":0,
    "gn:timezone":"Asia/Urumqi",
    "iso:country":"CN",
    "name:zho_x_preferred":[
        "\u62c9\u6708\u6751"
    ],
    "wof:name":"Layuecun",
    "wof:placetype":"locality"
},
  "geometry": {"coordinates":[94.86702,29.98983],"type":"Point"}
}