{
  "type": "Feature",
  "properties": {
    "gn:admin1_code":"1.0",
    "gn:asciiname":"Qinfengcun",
    "gn:country_code":"CN",
    "gn:dem":50,
    "gn:feature_class":"P",
    "gn:feature_code":"PPL",
    "gn:name":"Qinfengcun",
    "gn:population":0,
    "gn:timezone":"Asia/Shanghai",
    "iso:country":"CN",
    "name:zho_x_preferred":[
        "\u52e4\u4e30\u6751"
    ],
    "wof:name":"Qinfengcun",
    "wof:placetype":"locality"
},
  "geometry": {"coordinates":[117.77669,32.7317],"type":"Point"}
}