{
  "type": "Feature",
  "properties": {
    "gn:admin1_code":"8.0",
    "gn:asciiname":"Yongxincun",
    "gn:country_code":"CN",
    "gn:dem":127,
    "gn:feature_class":"P",
    "gn:feature_code":"PPL",
    "gn:name":"Yongxincun",
    "gn:population":0,
    "gn:timezone":"Asia/Shanghai",
    "iso:country":"CN",
    "name:zho_x_preferred":[
        "\u6c38\u65b0\u6751"
    ],
    "wof:name":"Yongxincun",
    "wof:placetype":"locality"
},
  "geometry": {"coordinates":[131.79845,45.45644],"type":"Point"}
}