{
  "type": "Feature",
  "properties": {
    "gn:admin1_code":"29.0",
    "gn:asciiname":"Laobu",
    "gn:country_code":"CN",
    "gn:dem":1990,
    "gn:feature_class":"P",
    "gn:feature_code":"PPL",
    "gn:name":"Laobu",
    "gn:population":0,
    "gn:timezone":"Asia/Shanghai",
    "iso:country":"CN",
    "name:zho_x_preferred":[
        "\u8001\u5821"
    ],
    "wof:name":"Laobu",
    "wof:placetype":"locality"
},
  "geometry": {"coordinates":[104.08199999999999,26.2457],"type":"Point"}
}