{
  "type": "Feature",
  "properties": {
    "gn:admin1_code":"12.0",
    "gn:asciiname":"Zhangjialong",
    "gn:country_code":"CN",
    "gn:dem":27,
    "gn:feature_class":"P",
    "gn:feature_code":"PPL",
    "gn:name":"Zhangjialong",
    "gn:population":0,
    "gn:timezone":"Asia/Shanghai",
    "iso:country":"CN",
    "name:zho_x_preferred":[
        "Zhangjialong"
    ],
    "name:zho_x_variant":[
        "\u5f20\u5bb6\u5784"
    ],
    "wof:name":"Zhangjialong",
    "wof:placetype":"locality"
},
  "geometry": {"coordinates":[115.07658000000001,29.84802],"type":"Point"}
}