{
  "type": "Feature",
  "properties": {
    "gn:admin1_code":"32.0",
    "gn:asciiname":"Shangmaidi",
    "gn:country_code":"CN",
    "gn:dem":2310,
    "gn:feature_class":"P",
    "gn:feature_code":"PPL",
    "gn:name":"Shangmaidi",
    "gn:population":0,
    "gn:timezone":"Asia/Shanghai",
    "iso:country":"CN",
    "name:zho_x_preferred":[
        "\u4e0a\u9ea6\u5730"
    ],
    "wof:name":"Shangmaidi",
    "wof:placetype":"locality"
},
  "geometry": {"coordinates":[101.205,27.7967],"type":"Point"}
}