{
  "type": "Feature",
  "properties": {
    "gn:admin1_code":"06",
    "gn:asciiname":"Gushan",
    "gn:cc2":"CN",
    "gn:country_code":"CN",
    "gn:dem":2289,
    "gn:feature_class":"P",
    "gn:feature_code":"PPL",
    "gn:name":"Gushan",
    "gn:population":0,
    "gn:timezone":"Asia/Shanghai",
    "iso:country":"CN",
    "name:ceb_x_preferred":[
        "Gushan"
    ],
    "name:deu_x_preferred":[
        "Gushan"
    ],
    "name:swe_x_preferred":[
        "Gushan"
    ],
    "name:und_x_variant":[
        "Min-ho",
        "Ku-shan-chen",
        "Ku-shan-i",
        "Ku-shan",
        "Ku-shan-pao",
        "Gushan"
    ],
    "wof:name":"Gushan",
    "wof:placetype":"locality"
},
  "geometry": {"coordinates":[102.7775,36.11889],"type":"Point"}
}