{
  "type": "Feature",
  "properties": {
    "gn:admin1_code":"24.0",
    "gn:asciiname":"Yuling",
    "gn:country_code":"CN",
    "gn:dem":1414,
    "gn:feature_class":"P",
    "gn:feature_code":"PPLA4",
    "gn:name":"Yuling",
    "gn:population":0,
    "gn:timezone":"Asia/Shanghai",
    "iso:country":"CN",
    "name:und_x_variant":[
        "Y\u00fc-lin-ts\u2019un",
        "Yuling",
        "\u6986\u5cad",
        "Yuling Xiang",
        "\u6986\u5cad\u4e61"
    ],
    "wof:name":"Yuling",
    "wof:placetype":"locality"
},
  "geometry": {"coordinates":[112.42944,39.55583],"type":"Point"}
}