{
  "type": "Feature",
  "properties": {
    "gn:admin1_code":"29.0",
    "gn:asciiname":"Guangyun",
    "gn:country_code":"CN",
    "gn:dem":775,
    "gn:feature_class":"P",
    "gn:feature_code":"PPL",
    "gn:name":"Guangyun",
    "gn:population":0,
    "gn:timezone":"Asia/Shanghai",
    "iso:country":"CN",
    "name:fra_x_preferred":[
        "Guangyun"
    ],
    "name:nor_x_preferred":[
        "Guangyun"
    ],
    "name:zho_x_preferred":[
        "\u5e7f\u5141"
    ],
    "wof:name":"Guangyun",
    "wof:placetype":"locality"
},
  "geometry": {"coordinates":[97.807,23.9854],"type":"Point"}
}