{
  "type": "Feature",
  "properties": {
    "gn:admin1_code":"16",
    "gn:asciiname":"Liangjiang",
    "gn:country_code":"CN",
    "gn:dem":160,
    "gn:feature_class":"P",
    "gn:feature_code":"PPL",
    "gn:name":"Liangjiang",
    "gn:population":0,
    "gn:timezone":"Asia/Shanghai",
    "iso:country":"CN",
    "name:ceb_x_preferred":[
        "Liangjiang"
    ],
    "name:deu_x_preferred":[
        "Liangjiang"
    ],
    "wof:name":"Liangjiang",
    "wof:placetype":"locality"
},
  "geometry": {"coordinates":[110.36667,24.63333],"type":"Point"}
}