{
  "type": "Feature",
  "properties": {
    "gn:admin1_code":"12.0",
    "gn:asciiname":"Sanchagang",
    "gn:country_code":"CN",
    "gn:dem":25,
    "gn:feature_class":"P",
    "gn:feature_code":"PPL",
    "gn:name":"Sanchagang",
    "gn:population":0,
    "gn:timezone":"Asia/Shanghai",
    "iso:country":"CN",
    "name:zho_x_preferred":[
        "\u4e09\u6c4a\u6e2f"
    ],
    "wof:name":"Sanchagang",
    "wof:placetype":"locality"
},
  "geometry": {"coordinates":[113.94871999999999,30.74492],"type":"Point"}
}