{
  "type": "Feature",
  "properties": {
    "gn:admin1_code":"26.0",
    "gn:asciiname":"Lijiawan",
    "gn:country_code":"CN",
    "gn:dem":1194,
    "gn:feature_class":"P",
    "gn:feature_code":"PPL",
    "gn:name":"Lijiawan",
    "gn:population":0,
    "gn:timezone":"Asia/Shanghai",
    "iso:country":"CN",
    "name:und_x_variant":[
        "\u674e\u5bb6\u6e7e"
    ],
    "wof:name":"Lijiawan",
    "wof:placetype":"locality"
},
  "geometry": {"coordinates":[105.87618999999999,33.37758],"type":"Point"}
}