{
  "type": "Feature",
  "properties": {
    "gn:admin1_code":"9.0",
    "gn:asciiname":"Zhuanggou",
    "gn:country_code":"CN",
    "gn:dem":237,
    "gn:feature_class":"P",
    "gn:feature_code":"PPL",
    "gn:name":"Zhuanggou",
    "gn:population":0,
    "gn:timezone":"Asia/Shanghai",
    "iso:country":"CN",
    "name:zho_x_preferred":[
        "\u5e84\u6c9f"
    ],
    "wof:name":"Zhuanggou",
    "wof:placetype":"locality"
},
  "geometry": {"coordinates":[112.34151,34.75216],"type":"Point"}
}