{
  "type": "Feature",
  "properties": {
    "gn:admin1_code":"25.0",
    "gn:asciiname":"Dingmazhuangcun",
    "gn:country_code":"CN",
    "gn:dem":35,
    "gn:feature_class":"P",
    "gn:feature_code":"PPL",
    "gn:name":"Dingmazhuangcun",
    "gn:population":0,
    "gn:timezone":"Asia/Shanghai",
    "iso:country":"CN",
    "name:zho_x_preferred":[
        "\u4e01\u9a6c\u5e84\u6751"
    ],
    "wof:name":"Dingmazhuangcun",
    "wof:placetype":"locality"
},
  "geometry": {"coordinates":[115.8948,36.7069],"type":"Point"}
}