{
  "type": "Feature",
  "properties": {
    "gn:admin1_code":"29.0",
    "gn:asciiname":"Tangfang Pojiao",
    "gn:country_code":"CN",
    "gn:dem":1965,
    "gn:feature_class":"P",
    "gn:feature_code":"PPL",
    "gn:name":"Tangfang Pojiao",
    "gn:population":0,
    "gn:timezone":"Asia/Shanghai",
    "iso:country":"CN",
    "name:zho_x_preferred":[
        "\u5858\u623f\u5761\u811a"
    ],
    "wof:name":"Tangfang Pojiao",
    "wof:placetype":"locality"
},
  "geometry": {"coordinates":[103.554,27.2582],"type":"Point"}
}