{
  "type": "Feature",
  "properties": {
    "gn:admin1_code":"24.0",
    "gn:asciiname":"Lijiabu",
    "gn:country_code":"CN",
    "gn:dem":1480,
    "gn:feature_class":"P",
    "gn:feature_code":"PPL",
    "gn:name":"Lijiabu",
    "gn:population":0,
    "gn:timezone":"Asia/Shanghai",
    "iso:country":"CN",
    "name:und_x_variant":[
        "\u674e\u5bb6\u5821"
    ],
    "name:zho_x_preferred":[
        "\u674e\u5bb6\u5821"
    ],
    "wof:name":"Lijiabu",
    "wof:placetype":"locality"
},
  "geometry": {"coordinates":[112.60353000000001,39.45147],"type":"Point"}
}