{
  "type": "Feature",
  "properties": {
    "gn:admin1_code":"32.0",
    "gn:asciiname":"Jinshaba",
    "gn:country_code":"CN",
    "gn:dem":443,
    "gn:feature_class":"P",
    "gn:feature_code":"PPL",
    "gn:name":"Jinshaba",
    "gn:population":0,
    "gn:timezone":"Asia/Shanghai",
    "iso:country":"CN",
    "name:zho_x_preferred":[
        "\u91d1\u6c99\u575d"
    ],
    "wof:name":"Jinshaba",
    "wof:placetype":"locality"
},
  "geometry": {"coordinates":[103.41108,29.84981],"type":"Point"}
}