{
  "type": "Feature",
  "properties": {
    "gn:admin1_code":"24.0",
    "gn:asciiname":"Pinglongtou",
    "gn:country_code":"CN",
    "gn:dem":1125,
    "gn:feature_class":"P",
    "gn:feature_code":"PPL",
    "gn:name":"Pinglongtou",
    "gn:population":0,
    "gn:timezone":"Asia/Shanghai",
    "iso:country":"CN",
    "name:zho_x_preferred":[
        "\u576a\u9f99\u5934"
    ],
    "wof:name":"Pinglongtou",
    "wof:placetype":"locality"
},
  "geometry": {"coordinates":[113.09363999999999,37.76666],"type":"Point"}
}