{
  "type": "Feature",
  "properties": {
    "gn:admin1_code":"4.0",
    "gn:asciiname":"Sunxu",
    "gn:country_code":"CN",
    "gn:dem":27,
    "gn:feature_class":"P",
    "gn:feature_code":"PPL",
    "gn:name":"Sunxu",
    "gn:population":0,
    "gn:timezone":"Asia/Shanghai",
    "iso:country":"CN",
    "name:zho_x_preferred":[
        "\u5b59\u5729"
    ],
    "wof:name":"Sunxu",
    "wof:placetype":"locality"
},
  "geometry": {"coordinates":[118.556,33.7537],"type":"Point"}
}