{
  "type": "Feature",
  "properties": {
    "gn:admin1_code":"18",
    "gn:asciiname":"Datiankouzi",
    "gn:country_code":"CN",
    "gn:dem":1676,
    "gn:feature_class":"P",
    "gn:feature_code":"PPL",
    "gn:name":"Datiankouzi",
    "gn:population":0,
    "gn:timezone":"Asia/Shanghai",
    "iso:country":"CN",
    "name:zho_x_preferred":[
        "\u5927\u7530\u53e3\u5b50"
    ],
    "wof:name":"Datiankouzi",
    "wof:placetype":"locality"
},
  "geometry": {"coordinates":[104.485,25.8447],"type":"Point"}
}