{
  "type": "Feature",
  "properties": {
    "gn:admin1_code":"7",
    "gn:asciiname":"Shuitou",
    "gn:country_code":"CN",
    "gn:dem":897,
    "gn:feature_class":"P",
    "gn:feature_code":"PPL",
    "gn:name":"Shuitou",
    "gn:population":0,
    "gn:timezone":"Asia/Shanghai",
    "iso:country":"CN",
    "name:zho_x_preferred":[
        "\u6c34\u5934"
    ],
    "name:zho_x_variant":[
        "\u6c34\u5934\u9547"
    ],
    "wof:name":"Shuitou",
    "wof:placetype":"locality"
},
  "geometry": {"coordinates":[117.07778,24.56889],"type":"Point"}
}