{
  "type": "Feature",
  "properties": {
    "gn:admin1_code":"32.0",
    "gn:asciiname":"Shida'an",
    "gn:country_code":"CN",
    "gn:dem":2565,
    "gn:feature_class":"P",
    "gn:feature_code":"PPL",
    "gn:name":"Shida\u2019an",
    "gn:population":0,
    "gn:timezone":"Asia/Shanghai",
    "iso:country":"CN",
    "name:und_x_variant":[
        "Shida\u2019an"
    ],
    "name:zho_x_preferred":[
        "\u77f3\u8fbe\u5b89"
    ],
    "wof:name":"Shida'an",
    "wof:placetype":"locality"
},
  "geometry": {"coordinates":[102.041,31.5065],"type":"Point"}
}