{
  "type": "Feature",
  "properties": {
    "gn:admin1_code":"01",
    "gn:asciiname":"Gupei",
    "gn:cc2":"CN",
    "gn:country_code":"CN",
    "gn:dem":23,
    "gn:feature_class":"P",
    "gn:feature_code":"PPL",
    "gn:name":"Gupei",
    "gn:population":0,
    "gn:timezone":"Asia/Shanghai",
    "iso:country":"CN",
    "name:und_x_variant":[
        "Ku-p\u2019ei",
        "Ku-p\u2019ei-chi",
        "Gupei"
    ],
    "wof:name":"Gupei",
    "wof:placetype":"locality"
},
  "geometry": {"coordinates":[117.99333,32.97889],"type":"Point"}
}