{
  "type": "Feature",
  "properties": {
    "gn:admin1_code":"4.0",
    "gn:asciiname":"Daxuzhuang",
    "gn:country_code":"CN",
    "gn:dem":9,
    "gn:feature_class":"P",
    "gn:feature_code":"PPL",
    "gn:name":"Daxuzhuang",
    "gn:population":0,
    "gn:timezone":"Asia/Shanghai",
    "iso:country":"CN",
    "name:zho_x_preferred":[
        "\u5927\u8bb8\u5e84"
    ],
    "wof:name":"Daxuzhuang",
    "wof:placetype":"locality"
},
  "geometry": {"coordinates":[118.73399999999999,34.3586],"type":"Point"}
}