{
  "type": "Feature",
  "properties": {
    "gn:admin1_code":"10.0",
    "gn:asciiname":"Lihuzhuang",
    "gn:country_code":"CN",
    "gn:dem":7,
    "gn:feature_class":"P",
    "gn:feature_code":"PPL",
    "gn:name":"Lihuzhuang",
    "gn:population":0,
    "gn:timezone":"Asia/Shanghai",
    "iso:country":"CN",
    "name:zho_x_preferred":[
        "\u674e\u864e\u5e84"
    ],
    "wof:name":"Lihuzhuang",
    "wof:placetype":"locality"
},
  "geometry": {"coordinates":[117.81896999999999,39.62099],"type":"Point"}
}