{
  "type": "Feature",
  "properties": {
    "gn:admin1_code":"3.0",
    "gn:asciiname":"Yangmeijiang",
    "gn:country_code":"CN",
    "gn:dem":68,
    "gn:feature_class":"P",
    "gn:feature_code":"PPL",
    "gn:name":"Yangmeijiang",
    "gn:population":0,
    "gn:timezone":"Asia/Shanghai",
    "iso:country":"CN",
    "name:und_x_variant":[
        "\u6768\u679a\u6c5f"
    ],
    "wof:name":"Yangmeijiang",
    "wof:placetype":"locality"
},
  "geometry": {"coordinates":[115.0903,27.77743],"type":"Point"}
}