{
  "type": "Feature",
  "properties": {
    "gn:admin1_code":"08",
    "gn:asciiname":"Shiliuzhan",
    "gn:country_code":"CN",
    "gn:dem":306,
    "gn:feature_class":"P",
    "gn:feature_code":"PPL",
    "gn:name":"Shiliuzhan",
    "gn:population":0,
    "gn:timezone":"Asia/Shanghai",
    "iso:country":"CN",
    "name:und_x_variant":[
        "Shih-liu-chan",
        "Shiliuzhan"
    ],
    "name:zho_x_preferred":[
        "\u5341\u516d\u7ad9"
    ],
    "wof:name":"Shiliuzhan",
    "wof:placetype":"locality"
},
  "geometry": {"coordinates":[125.70689,52.00525],"type":"Point"}
}