{
  "type": "Feature",
  "properties": {
    "gn:admin1_code":"33.0",
    "gn:asciiname":"Maojiaba",
    "gn:country_code":"CN",
    "gn:dem":707,
    "gn:feature_class":"P",
    "gn:feature_code":"PPL",
    "gn:name":"Maojiaba",
    "gn:population":0,
    "gn:timezone":"Asia/Shanghai",
    "iso:country":"CN",
    "name:zho_x_preferred":[
        "\u6bdb\u5bb6\u575d"
    ],
    "wof:name":"Maojiaba",
    "wof:placetype":"locality"
},
  "geometry": {"coordinates":[107.35299999999999,28.865],"type":"Point"}
}