{
  "type": "Feature",
  "properties": {
    "gn:admin1_code":"26.0",
    "gn:asciiname":"Jiapocun",
    "gn:country_code":"CN",
    "gn:dem":748,
    "gn:feature_class":"P",
    "gn:feature_code":"PPL",
    "gn:name":"Jiapocun",
    "gn:population":0,
    "gn:timezone":"Asia/Shanghai",
    "iso:country":"CN",
    "name:zho_x_preferred":[
        "\u8d3e\u5761\u6751"
    ],
    "wof:name":"Jiapocun",
    "wof:placetype":"locality"
},
  "geometry": {"coordinates":[109.18415,34.92857],"type":"Point"}
}