{
  "type": "Feature",
  "properties": {
    "gn:admin1_code":"8.0",
    "gn:asciiname":"Zhengyangcun",
    "gn:country_code":"CN",
    "gn:dem":171,
    "gn:feature_class":"P",
    "gn:feature_code":"PPL",
    "gn:name":"Zhengyangcun",
    "gn:population":0,
    "gn:timezone":"Asia/Shanghai",
    "iso:country":"CN",
    "name:zho_x_preferred":[
        "\u6b63\u9633\u6751"
    ],
    "wof:name":"Zhengyangcun",
    "wof:placetype":"locality"
},
  "geometry": {"coordinates":[130.46218000000002,45.91072],"type":"Point"}
}