{
  "type": "Feature",
  "properties": {
    "gn:admin1_code":"4.0",
    "gn:asciiname":"Nantonggang Er'zu",
    "gn:country_code":"CN",
    "gn:dem":10,
    "gn:feature_class":"P",
    "gn:feature_code":"PPLF",
    "gn:name":"Nantonggang Er\u2019zu",
    "gn:population":0,
    "gn:timezone":"Asia/Shanghai",
    "iso:country":"CN",
    "name:und_x_variant":[
        "Nantonggang Er\u2019zu"
    ],
    "name:zho_x_preferred":[
        "\u5357\u901a\u6e2f\u4e8c\u7ec4"
    ],
    "wof:name":"Nantonggang Er'zu",
    "wof:placetype":"locality"
},
  "geometry": {"coordinates":[120.82422,32.0201],"type":"Point"}
}