{
  "type": "Feature",
  "properties": {
    "gn:admin1_code":"12.0",
    "gn:asciiname":"Xiongjiatian",
    "gn:country_code":"CN",
    "gn:dem":35,
    "gn:feature_class":"P",
    "gn:feature_code":"PPL",
    "gn:name":"Xiongjiatian",
    "gn:population":0,
    "gn:timezone":"Asia/Shanghai",
    "iso:country":"CN",
    "name:und_x_variant":[
        "\u718a\u5bb6\u7530"
    ],
    "wof:name":"Xiongjiatian",
    "wof:placetype":"locality"
},
  "geometry": {"coordinates":[114.22060999999999,30.82053],"type":"Point"}
}