{
  "type": "Feature",
  "properties": {
    "gn:admin1_code":"2.0",
    "gn:asciiname":"Fotang",
    "gn:country_code":"CN",
    "gn:dem":1157,
    "gn:feature_class":"P",
    "gn:feature_code":"PPL",
    "gn:name":"Fotang",
    "gn:population":0,
    "gn:timezone":"Asia/Shanghai",
    "iso:country":"CN",
    "name:und_x_variant":[
        "\u4f5b\u5802"
    ],
    "wof:name":"Fotang",
    "wof:placetype":"locality"
},
  "geometry": {"coordinates":[119.1139,30.30956],"type":"Point"}
}