{
  "type": "Feature",
  "properties": {
    "gn:admin1_code":"21.0",
    "gn:asciiname":"Zhangjia Shanpozi",
    "gn:country_code":"CN",
    "gn:dem":1856,
    "gn:feature_class":"P",
    "gn:feature_code":"PPL",
    "gn:name":"Zhangjia Shanpozi",
    "gn:population":0,
    "gn:timezone":"Asia/Shanghai",
    "iso:country":"CN",
    "name:zho_x_preferred":[
        "\u5f20\u5bb6\u5c71\u5761\u5b50"
    ],
    "wof:name":"Zhangjia Shanpozi",
    "wof:placetype":"locality"
},
  "geometry": {"coordinates":[106.366,37.1103],"type":"Point"}
}