{
  "type": "Feature",
  "properties": {
    "gn:admin1_code":"16",
    "gn:asciiname":"Xiaoheping",
    "gn:country_code":"CN",
    "gn:dem":465,
    "gn:feature_class":"P",
    "gn:feature_code":"PPL",
    "gn:name":"Xiaoheping",
    "gn:population":0,
    "gn:timezone":"Asia/Shanghai",
    "iso:country":"CN",
    "name:zho_x_preferred":[
        "\u5c0f\u79be\u576a"
    ],
    "wof:name":"Xiaoheping",
    "wof:placetype":"locality"
},
  "geometry": {"coordinates":[111.334,25.8888],"type":"Point"}
}