{
  "type": "Feature",
  "properties": {
    "gn:admin1_code":"05",
    "gn:asciiname":"Sanjiazi",
    "gn:country_code":"CN",
    "gn:dem":34,
    "gn:feature_class":"P",
    "gn:feature_code":"PPLA4",
    "gn:name":"Sanjiazi",
    "gn:population":0,
    "gn:timezone":"Asia/Shanghai",
    "iso:country":"CN",
    "name:und_x_variant":[
        "San-chia-tzu",
        "Sanjiazi",
        "\u4e09\u5bb6\u5b50",
        "Sanjiazi Manzu Xiang",
        "\u4e09\u5bb6\u5b50\u6ee1\u65cf\u4e61"
    ],
    "name:zho_x_preferred":[
        "\u4e09\u5bb6\u5b50\u6751"
    ],
    "wof:name":"Sanjiazi",
    "wof:placetype":"locality"
},
  "geometry": {"coordinates":[130.30556000000001,42.84],"type":"Point"}
}