{
  "type": "Feature",
  "properties": {
    "gn:admin1_code":"13.0",
    "gn:asciiname":"Yingwusitang",
    "gn:country_code":"CN",
    "gn:dem":1171,
    "gn:feature_class":"P",
    "gn:feature_code":"PPL",
    "gn:name":"Yingwusitang",
    "gn:population":0,
    "gn:timezone":"Asia/Shanghai",
    "iso:country":"CN",
    "name:zho_x_preferred":[
        "\u82f1\u543e\u65af\u5858"
    ],
    "wof:name":"Yingwusitang",
    "wof:placetype":"locality"
},
  "geometry": {"coordinates":[77.4846,39.08047],"type":"Point"}
}