{
  "type": "Feature",
  "properties": {
    "gn:admin1_code":"11.0",
    "gn:asciiname":"Jianzhupo",
    "gn:country_code":"CN",
    "gn:dem":277,
    "gn:feature_class":"P",
    "gn:feature_code":"PPL",
    "gn:name":"Jianzhupo",
    "gn:population":0,
    "gn:timezone":"Asia/Shanghai",
    "iso:country":"CN",
    "name:zho_x_preferred":[
        "\u7bad\u7af9\u5761"
    ],
    "wof:name":"Jianzhupo",
    "wof:placetype":"locality"
},
  "geometry": {"coordinates":[113.64408,27.86572],"type":"Point"}
}