{
  "type": "Feature",
  "properties": {
    "gn:admin1_code":"19.0",
    "gn:asciiname":"Fengshan",
    "gn:country_code":"CN",
    "gn:dem":382,
    "gn:feature_class":"P",
    "gn:feature_code":"PPL",
    "gn:name":"Fengshan",
    "gn:population":0,
    "gn:timezone":"Asia/Shanghai",
    "iso:country":"CN",
    "name:und_x_variant":[
        "\u5c01\u5c71"
    ],
    "name:zho_x_preferred":[
        "\u5c01\u5c71"
    ],
    "wof:name":"Fengshan",
    "wof:placetype":"locality"
},
  "geometry": {"coordinates":[120.23699999999999,41.5491],"type":"Point"}
}