{
  "type": "Feature",
  "properties": {
    "gn:admin1_code":"33.0",
    "gn:asciiname":"Puguang",
    "gn:country_code":"CN",
    "gn:dem":1044,
    "gn:feature_class":"P",
    "gn:feature_code":"PPL",
    "gn:name":"Puguang",
    "gn:population":0,
    "gn:timezone":"Asia/Shanghai",
    "iso:country":"CN",
    "name:zho_x_preferred":[
        "\u666e\u5e7f"
    ],
    "wof:name":"Puguang",
    "wof:placetype":"locality"
},
  "geometry": {"coordinates":[108.27606000000002,31.06031],"type":"Point"}
}