{
  "type": "Feature",
  "properties": {
    "gn:admin1_code":"19.0",
    "gn:asciiname":"Wujiabucun",
    "gn:country_code":"CN",
    "gn:dem":47,
    "gn:feature_class":"P",
    "gn:feature_code":"PPL",
    "gn:name":"Wujiabucun",
    "gn:population":0,
    "gn:timezone":"Asia/Shanghai",
    "iso:country":"CN",
    "name:zho_x_preferred":[
        "\u5434\u5bb6\u5821\u6751"
    ],
    "wof:name":"Wujiabucun",
    "wof:placetype":"locality"
},
  "geometry": {"coordinates":[123.07299999999999,42.3065],"type":"Point"}
}