{
  "type": "Feature",
  "properties": {
    "gn:admin1_code":"1.0",
    "gn:asciiname":"Liandezhou",
    "gn:country_code":"CN",
    "gn:dem":11,
    "gn:feature_class":"P",
    "gn:feature_code":"PPL",
    "gn:name":"Liandezhou",
    "gn:population":0,
    "gn:timezone":"Asia/Shanghai",
    "iso:country":"CN",
    "name:zho_x_preferred":[
        "\u8fde\u5fb7\u5468"
    ],
    "wof:name":"Liandezhou",
    "wof:placetype":"locality"
},
  "geometry": {"coordinates":[118.30359,31.51174],"type":"Point"}
}