{
  "type": "Feature",
  "properties": {
    "gn:admin1_code":"11.0",
    "gn:asciiname":"Shatianwan",
    "gn:country_code":"CN",
    "gn:dem":60,
    "gn:feature_class":"P",
    "gn:feature_code":"PPL",
    "gn:name":"Shatianwan",
    "gn:population":0,
    "gn:timezone":"Asia/Shanghai",
    "iso:country":"CN",
    "name:zho_x_preferred":[
        "\u6c99\u7530\u6e7e"
    ],
    "wof:name":"Shatianwan",
    "wof:placetype":"locality"
},
  "geometry": {"coordinates":[112.62041000000001,28.03863],"type":"Point"}
}