{
  "type": "Feature",
  "properties": {
    "gn:admin1_code":"10.0",
    "gn:asciiname":"Xihetun",
    "gn:country_code":"CN",
    "gn:dem":8,
    "gn:feature_class":"P",
    "gn:feature_code":"PPL",
    "gn:name":"Xihetun",
    "gn:population":0,
    "gn:timezone":"Asia/Shanghai",
    "iso:country":"CN",
    "name:zho_x_preferred":[
        "\u7fd5\u548c\u5c6f"
    ],
    "wof:name":"Xihetun",
    "wof:placetype":"locality"
},
  "geometry": {"coordinates":[117.009,38.4324],"type":"Point"}
}