{
  "type": "Feature",
  "properties": {
    "gn:admin1_code":"15.0",
    "gn:asciiname":"Dingyangwan",
    "gn:country_code":"CN",
    "gn:dem":1739,
    "gn:feature_class":"P",
    "gn:feature_code":"PPL",
    "gn:name":"Dingyangwan",
    "gn:population":0,
    "gn:timezone":"Asia/Shanghai",
    "iso:country":"CN",
    "name:und_x_variant":[
        "\u4e01\u9633\u6e7e"
    ],
    "wof:name":"Dingyangwan",
    "wof:placetype":"locality"
},
  "geometry": {"coordinates":[106.60877000000001,36.67446],"type":"Point"}
}