{
  "type": "Feature",
  "properties": {
    "gn:admin1_code":"32.0",
    "gn:asciiname":"Touping",
    "gn:country_code":"CN",
    "gn:dem":1344,
    "gn:feature_class":"P",
    "gn:feature_code":"PPL",
    "gn:name":"Touping",
    "gn:population":0,
    "gn:timezone":"Asia/Shanghai",
    "iso:country":"CN",
    "name:zho_x_preferred":[
        "\u5934\u576a"
    ],
    "wof:name":"Touping",
    "wof:placetype":"locality"
},
  "geometry": {"coordinates":[103.971,31.4259],"type":"Point"}
}