{
  "type": "Feature",
  "properties": {
    "gn:admin1_code":"10",
    "gn:asciiname":"Senjitu",
    "gn:cc2":"CN",
    "gn:country_code":"CN",
    "gn:dem":1131,
    "gn:feature_class":"P",
    "gn:feature_code":"PPL",
    "gn:name":"Senjitu",
    "gn:population":0,
    "gn:timezone":"Asia/Shanghai",
    "iso:country":"CN",
    "name:und_x_variant":[
        "Wai-kou-men",
        "Sen-chi-t\u2019u",
        "Vaigoumyn\u2019tsza",
        "Vaygoum\u00f6n\u2019tzsa",
        "Wai-kou-men-tzu",
        "Senjitu"
    ],
    "wof:name":"Senjitu",
    "wof:placetype":"locality"
},
  "geometry": {"coordinates":[116.56,41.87917],"type":"Point"}
}