{
  "type": "Feature",
  "properties": {
    "gn:admin1_code":"11.0",
    "gn:asciiname":"Shiyancao",
    "gn:country_code":"CN",
    "gn:dem":757,
    "gn:feature_class":"P",
    "gn:feature_code":"PPL",
    "gn:name":"Shiyancao",
    "gn:population":0,
    "gn:timezone":"Asia/Shanghai",
    "iso:country":"CN",
    "name:zho_x_preferred":[
        "\u77f3\u5ca9\u6f15"
    ],
    "wof:name":"Shiyancao",
    "wof:placetype":"locality"
},
  "geometry": {"coordinates":[111.77789,24.95818],"type":"Point"}
}