{
  "type": "Feature",
  "properties": {
    "gn:admin1_code":"32.0",
    "gn:asciiname":"Jinjiling",
    "gn:country_code":"CN",
    "gn:dem":2746,
    "gn:feature_class":"P",
    "gn:feature_code":"PPL",
    "gn:name":"Jinjiling",
    "gn:population":0,
    "gn:timezone":"Asia/Shanghai",
    "iso:country":"CN",
    "name:zho_x_preferred":[
        "\u91d1\u9e21\u5cad"
    ],
    "wof:name":"Jinjiling",
    "wof:placetype":"locality"
},
  "geometry": {"coordinates":[102.41500000000001,27.1284],"type":"Point"}
}