{
  "type": "Feature",
  "properties": {
    "gn:admin1_code":"7.0",
    "gn:asciiname":"Kefang",
    "gn:country_code":"CN",
    "gn:dem":326,
    "gn:feature_class":"P",
    "gn:feature_code":"PPL",
    "gn:name":"Kefang",
    "gn:population":0,
    "gn:timezone":"Asia/Shanghai",
    "iso:country":"CN",
    "name:zho_x_preferred":[
        "\u67ef\u574a"
    ],
    "wof:name":"Kefang",
    "wof:placetype":"locality"
},
  "geometry": {"coordinates":[116.76975,25.82954],"type":"Point"}
}