{
  "type": "Feature",
  "properties": {
    "gn:admin1_code":"2.0",
    "gn:asciiname":"Jieqiao",
    "gn:country_code":"CN",
    "gn:dem":140,
    "gn:feature_class":"P",
    "gn:feature_code":"PPL",
    "gn:name":"Jieqiao",
    "gn:population":0,
    "gn:timezone":"Asia/Shanghai",
    "iso:country":"CN",
    "name:und_x_variant":[
        "\u754c\u6865"
    ],
    "name:zho_x_preferred":[
        "Jieqiao"
    ],
    "wof:name":"Jieqiao",
    "wof:placetype":"locality"
},
  "geometry": {"coordinates":[119.57895000000001,30.16154],"type":"Point"}
}