{
  "type": "Feature",
  "properties": {
    "gn:admin1_code":"19.0",
    "gn:asciiname":"Xiaozhangjiatun",
    "gn:country_code":"CN",
    "gn:dem":53,
    "gn:feature_class":"P",
    "gn:feature_code":"PPL",
    "gn:name":"Xiaozhangjiatun",
    "gn:population":0,
    "gn:timezone":"Asia/Shanghai",
    "iso:country":"CN",
    "name:zho_x_preferred":[
        "\u5c0f\u5f20\u5bb6\u5c6f"
    ],
    "wof:name":"Xiaozhangjiatun",
    "wof:placetype":"locality"
},
  "geometry": {"coordinates":[122.33799999999999,39.1752],"type":"Point"}
}