{
  "type": "Feature",
  "properties": {
    "gn:admin1_code":"3.0",
    "gn:asciiname":"Shawoli",
    "gn:country_code":"CN",
    "gn:dem":247,
    "gn:feature_class":"P",
    "gn:feature_code":"PPL",
    "gn:name":"Shawoli",
    "gn:population":0,
    "gn:timezone":"Asia/Shanghai",
    "iso:country":"CN",
    "name:zho_x_preferred":[
        "\u6c99\u7a9d\u7acb"
    ],
    "wof:name":"Shawoli",
    "wof:placetype":"locality"
},
  "geometry": {"coordinates":[114.366,27.7109],"type":"Point"}
}