{
  "type": "Feature",
  "properties": {
    "gn:admin1_code":"16.0",
    "gn:asciiname":"Luo'ai",
    "gn:country_code":"CN",
    "gn:dem":91,
    "gn:feature_class":"P",
    "gn:feature_code":"PPL",
    "gn:name":"Luo\u2019ai",
    "gn:population":0,
    "gn:timezone":"Asia/Shanghai",
    "iso:country":"CN",
    "name:und_x_variant":[
        "Luo\u2019ai"
    ],
    "name:zho_x_preferred":[
        "\u7f57\u77ee"
    ],
    "wof:name":"Luo'ai",
    "wof:placetype":"locality"
},
  "geometry": {"coordinates":[110.46899999999999,23.1382],"type":"Point"}
}