{
  "type": "Feature",
  "properties": {
    "gn:admin1_code":"12.0",
    "gn:asciiname":"Panjiawan",
    "gn:country_code":"CN",
    "gn:dem":49,
    "gn:feature_class":"P",
    "gn:feature_code":"PPL",
    "gn:name":"Panjiawan",
    "gn:population":0,
    "gn:timezone":"Asia/Shanghai",
    "iso:country":"CN",
    "name:und_x_variant":[
        "\u6f58\u5bb6\u5846"
    ],
    "wof:name":"Panjiawan",
    "wof:placetype":"locality"
},
  "geometry": {"coordinates":[115.22757,30.33277],"type":"Point"}
}