{
  "type": "Feature",
  "properties": {
    "gn:admin1_code":"32.0",
    "gn:asciiname":"Shaguanhe",
    "gn:country_code":"CN",
    "gn:dem":1277,
    "gn:feature_class":"P",
    "gn:feature_code":"PPL",
    "gn:name":"Shaguanhe",
    "gn:population":0,
    "gn:timezone":"Asia/Shanghai",
    "iso:country":"CN",
    "name:zho_x_preferred":[
        "\u6c99\u7f50\u6cb3"
    ],
    "wof:name":"Shaguanhe",
    "wof:placetype":"locality"
},
  "geometry": {"coordinates":[108.253,31.9953],"type":"Point"}
}