{
  "type": "Feature",
  "properties": {
    "gn:admin1_code":"7",
    "gn:asciiname":"Ganping",
    "gn:country_code":"CN",
    "gn:dem":279,
    "gn:feature_class":"P",
    "gn:feature_code":"PPL",
    "gn:name":"Ganping",
    "gn:population":0,
    "gn:timezone":"Asia/Shanghai",
    "iso:country":"CN",
    "name:zho_x_preferred":[
        "\u67d1\u576a"
    ],
    "wof:name":"Ganping",
    "wof:placetype":"locality"
},
  "geometry": {"coordinates":[117.8066,24.08854],"type":"Point"}
}