{
  "type": "Feature",
  "properties": {
    "gn:admin1_code":"30",
    "gn:asciiname":"Linjiang",
    "gn:country_code":"CN",
    "gn:dem":40,
    "gn:feature_class":"P",
    "gn:feature_code":"PPLA4",
    "gn:name":"Linjiang",
    "gn:population":0,
    "gn:timezone":"Asia/Shanghai",
    "iso:country":"CN",
    "name:und_x_variant":[
        "\u4e34\u6c5f",
        "Linjiang Zhen",
        "\u4e34\u6c5f\u9547"
    ],
    "wof:name":"Linjiang",
    "wof:placetype":"locality"
},
  "geometry": {"coordinates":[114.69396999999999,23.65125],"type":"Point"}
}