{
  "type": "Feature",
  "properties": {
    "gn:admin1_code":"12",
    "gn:asciiname":"Guchengfan",
    "gn:country_code":"CN",
    "gn:dem":105,
    "gn:feature_class":"P",
    "gn:feature_code":"PPL",
    "gn:name":"Guchengfan",
    "gn:population":0,
    "gn:timezone":"Asia/Shanghai",
    "iso:country":"CN",
    "name:und_x_variant":[
        "Ku-ch\u2019eng-fan",
        "Gucheng",
        "Guchengfan",
        "\u53e4\u57ce\u7548"
    ],
    "wof:name":"Guchengfan",
    "wof:placetype":"locality"
},
  "geometry": {"coordinates":[113.22517999999999,31.42205],"type":"Point"}
}