{
  "type": "Feature",
  "properties": {
    "gn:admin1_code":"3.0",
    "gn:asciiname":"Xiangjia",
    "gn:country_code":"CN",
    "gn:dem":128,
    "gn:feature_class":"P",
    "gn:feature_code":"PPL",
    "gn:name":"Xiangjia",
    "gn:population":0,
    "gn:timezone":"Asia/Shanghai",
    "iso:country":"CN",
    "name:zho_x_preferred":[
        "\u9879\u5bb6"
    ],
    "wof:name":"Xiangjia",
    "wof:placetype":"locality"
},
  "geometry": {"coordinates":[118.25646999999999,28.35837],"type":"Point"}
}