{
  "type": "Feature",
  "properties": {
    "gn:admin1_code":"9.0",
    "gn:asciiname":"Woniudian",
    "gn:country_code":"CN",
    "gn:dem":80,
    "gn:feature_class":"P",
    "gn:feature_code":"PPL",
    "gn:name":"Woniudian",
    "gn:population":0,
    "gn:timezone":"Asia/Shanghai",
    "iso:country":"CN",
    "name:zho_x_preferred":[
        "\u5367\u725b\u5e97"
    ],
    "wof:name":"Woniudian",
    "wof:placetype":"locality"
},
  "geometry": {"coordinates":[114.17601999999999,32.24149],"type":"Point"}
}