{
  "type": "Feature",
  "properties": {
    "gn:admin1_code":"9",
    "gn:asciiname":"Dajizhuang",
    "gn:country_code":"CN",
    "gn:dem":48,
    "gn:feature_class":"P",
    "gn:feature_code":"PPL",
    "gn:name":"Dajizhuang",
    "gn:population":0,
    "gn:timezone":"Asia/Shanghai",
    "iso:country":"CN",
    "name:zho_x_preferred":[
        "\u5927\u8ba1\u5e84"
    ],
    "wof:name":"Dajizhuang",
    "wof:placetype":"locality"
},
  "geometry": {"coordinates":[114.901,33.7063],"type":"Point"}
}