{
  "type": "Feature",
  "properties": {
    "gn:admin1_code":"30",
    "gn:asciiname":"Xinliao",
    "gn:country_code":"CN",
    "gn:dem":7,
    "gn:feature_class":"P",
    "gn:feature_code":"PPLA4",
    "gn:name":"Xinliao",
    "gn:population":0,
    "gn:timezone":"Asia/Urumqi",
    "iso:country":"CN",
    "name:und_x_variant":[
        "Xinliao Zhen",
        "\u65b0\u5bee\u9547"
    ],
    "name:zho_x_preferred":[
        "\u65b0\u5bee"
    ],
    "wof:name":"Xinliao",
    "wof:placetype":"locality"
},
  "geometry": {"coordinates":[110.4631,20.62049],"type":"Point"}
}