{
  "type": "Feature",
  "properties": {
    "gn:admin1_code":"29.0",
    "gn:asciiname":"Xiji",
    "gn:country_code":"CN",
    "gn:dem":2097,
    "gn:feature_class":"P",
    "gn:feature_code":"PPL",
    "gn:name":"Xiji",
    "gn:population":0,
    "gn:timezone":"Asia/Shanghai",
    "iso:country":"CN",
    "name:zho_x_preferred":[
        "\u7ec6\u53ca"
    ],
    "wof:name":"Xiji",
    "wof:placetype":"locality"
},
  "geometry": {"coordinates":[104.19199999999999,25.9059],"type":"Point"}
}