{
  "type": "Feature",
  "properties": {
    "gn:admin1_code":"32.0",
    "gn:asciiname":"Tingying",
    "gn:country_code":"CN",
    "gn:dem":389,
    "gn:feature_class":"P",
    "gn:feature_code":"PPL",
    "gn:name":"Tingying",
    "gn:population":0,
    "gn:timezone":"Asia/Shanghai",
    "iso:country":"CN",
    "name:zho_x_preferred":[
        "\u5ead\u82f1"
    ],
    "wof:name":"Tingying",
    "wof:placetype":"locality"
},
  "geometry": {"coordinates":[105.57299999999999,30.7906],"type":"Point"}
}