{
  "type": "Feature",
  "properties": {
    "gn:admin1_code":"24",
    "gn:asciiname":"Beiyao",
    "gn:cc2":"CN",
    "gn:country_code":"CN",
    "gn:dem":1040,
    "gn:feature_class":"P",
    "gn:feature_code":"PPL",
    "gn:name":"Beiyao",
    "gn:population":0,
    "gn:timezone":"Asia/Shanghai",
    "iso:country":"CN",
    "name:und_x_variant":[
        "Pei-yao",
        "Pei-yao-t\u2019ou",
        "Beiyao"
    ],
    "wof:name":"Beiyao",
    "wof:placetype":"locality"
},
  "geometry": {"coordinates":[111.51667,39.41667],"type":"Point"}
}