{
  "type": "Feature",
  "properties": {
    "gn:admin1_code":"32.0",
    "gn:asciiname":"Yangjiawu",
    "gn:country_code":"CN",
    "gn:dem":890,
    "gn:feature_class":"P",
    "gn:feature_code":"PPL",
    "gn:name":"Yangjiawu",
    "gn:population":0,
    "gn:timezone":"Asia/Shanghai",
    "iso:country":"CN",
    "name:zho_x_preferred":[
        "\u6768\u5bb6\u5c4b"
    ],
    "wof:name":"Yangjiawu",
    "wof:placetype":"locality"
},
  "geometry": {"coordinates":[106.84095000000001,32.31131],"type":"Point"}
}