{
  "type": "Feature",
  "properties": {
    "gn:admin1_code":"7.0",
    "gn:asciiname":"Liukeng",
    "gn:country_code":"CN",
    "gn:dem":140,
    "gn:feature_class":"P",
    "gn:feature_code":"PPL",
    "gn:name":"Liukeng",
    "gn:population":0,
    "gn:timezone":"Asia/Shanghai",
    "iso:country":"CN",
    "name:zho_x_preferred":[
        "\u7559\u5751"
    ],
    "wof:name":"Liukeng",
    "wof:placetype":"locality"
},
  "geometry": {"coordinates":[117.88678,26.37961],"type":"Point"}
}