{
  "type": "Feature",
  "properties": {
    "gn:admin1_code":"11.0",
    "gn:asciiname":"Xiangkou",
    "gn:country_code":"CN",
    "gn:dem":85,
    "gn:feature_class":"P",
    "gn:feature_code":"PPL",
    "gn:name":"Xiangkou",
    "gn:population":0,
    "gn:timezone":"Asia/Shanghai",
    "iso:country":"CN",
    "name:zho_x_preferred":[
        "\u5df7\u53e3"
    ],
    "wof:name":"Xiangkou",
    "wof:placetype":"locality"
},
  "geometry": {"coordinates":[113.42637000000001,28.56786],"type":"Point"}
}