{
  "type": "Feature",
  "properties": {
    "gn:admin1_code":"30.0",
    "gn:asciiname":"Benghu",
    "gn:country_code":"CN",
    "gn:dem":54,
    "gn:feature_class":"P",
    "gn:feature_code":"PPL",
    "gn:name":"Benghu",
    "gn:population":0,
    "gn:timezone":"Asia/Shanghai",
    "iso:country":"CN",
    "name:zho_x_preferred":[
        "\u868c\u6e56"
    ],
    "wof:name":"Benghu",
    "wof:placetype":"locality"
},
  "geometry": {"coordinates":[113.13472,24.17444],"type":"Point"}
}