{
  "type": "Feature",
  "properties": {
    "gn:admin1_code":"21.0",
    "gn:asciiname":"Luwa",
    "gn:country_code":"CN",
    "gn:dem":1740,
    "gn:feature_class":"P",
    "gn:feature_code":"PPL",
    "gn:name":"Luwa",
    "gn:population":0,
    "gn:timezone":"Asia/Shanghai",
    "iso:country":"CN",
    "name:und_x_variant":[
        "\u8def\u6d3c"
    ],
    "name:zho_x_preferred":[
        "\u8def\u6d3c"
    ],
    "wof:name":"Luwa",
    "wof:placetype":"locality"
},
  "geometry": {"coordinates":[106.58189,36.1509],"type":"Point"}
}