{
  "type": "Feature",
  "properties": {
    "gn:admin1_code":"18.0",
    "gn:asciiname":"Zongping",
    "gn:country_code":"CN",
    "gn:dem":754,
    "gn:feature_class":"P",
    "gn:feature_code":"PPLA4",
    "gn:name":"Zongping",
    "gn:population":0,
    "gn:timezone":"Asia/Shanghai",
    "iso:country":"CN",
    "name:und_x_variant":[
        "Zongping Xiang"
    ],
    "name:zho_x_preferred":[
        "\u68d5\u576a"
    ],
    "name:zho_x_variant":[
        "\u68d5\u5e73\u4e61"
    ],
    "wof:name":"Zongping",
    "wof:placetype":"locality"
},
  "geometry": {"coordinates":[107.65373999999998,28.67295],"type":"Point"}
}