{
  "type": "Feature",
  "properties": {
    "gn:admin1_code":"2.0",
    "gn:asciiname":"Nanhebang",
    "gn:country_code":"CN",
    "gn:dem":6,
    "gn:feature_class":"P",
    "gn:feature_code":"PPL",
    "gn:name":"Nanhebang",
    "gn:population":0,
    "gn:timezone":"Asia/Shanghai",
    "iso:country":"CN",
    "name:zho_x_preferred":[
        "\u5357\u6cb3\u6d5c"
    ],
    "wof:name":"Nanhebang",
    "wof:placetype":"locality"
},
  "geometry": {"coordinates":[121.13218999999999,30.6627],"type":"Point"}
}