{
  "type": "Feature",
  "properties": {
    "gn:admin1_code":"15.0",
    "gn:asciiname":"Xiaohancha",
    "gn:country_code":"CN",
    "gn:dem":1963,
    "gn:feature_class":"P",
    "gn:feature_code":"PPL",
    "gn:name":"Xiaohancha",
    "gn:population":0,
    "gn:timezone":"Asia/Shanghai",
    "iso:country":"CN",
    "name:zho_x_preferred":[
        "\u5c0f\u6c49\u5c94"
    ],
    "wof:name":"Xiaohancha",
    "wof:placetype":"locality"
},
  "geometry": {"coordinates":[105.348,36.4098],"type":"Point"}
}