{
  "type": "Feature",
  "properties": {
    "gn:admin1_code":"1.0",
    "gn:asciiname":"Xiaoshancun",
    "gn:country_code":"CN",
    "gn:dem":60,
    "gn:feature_class":"P",
    "gn:feature_code":"PPL",
    "gn:name":"Xiaoshancun",
    "gn:population":0,
    "gn:timezone":"Asia/Shanghai",
    "iso:country":"CN",
    "name:zho_x_preferred":[
        "\u5c0f\u5c71\u6751"
    ],
    "wof:name":"Xiaoshancun",
    "wof:placetype":"locality"
},
  "geometry": {"coordinates":[118.53270999999999,32.67169000000001],"type":"Point"}
}