{
  "type": "Feature",
  "properties": {
    "gn:admin1_code":"26.0",
    "gn:asciiname":"Jiantou",
    "gn:country_code":"CN",
    "gn:dem":551,
    "gn:feature_class":"P",
    "gn:feature_code":"PPL",
    "gn:name":"Jiantou",
    "gn:population":0,
    "gn:timezone":"Asia/Shanghai",
    "iso:country":"CN",
    "name:und_x_variant":[
        "Jiantou"
    ],
    "name:zho_x_preferred":[
        "\u6da7\u5934"
    ],
    "wof:name":"Jiantou",
    "wof:placetype":"locality"
},
  "geometry": {"coordinates":[109.24776,34.90778],"type":"Point"}
}