{
  "type": "Feature",
  "properties": {
    "gn:admin1_code":"20.0",
    "gn:asciiname":"Fudetun",
    "gn:country_code":"CN",
    "gn:dem":303,
    "gn:feature_class":"P",
    "gn:feature_code":"PPL",
    "gn:name":"Fudetun",
    "gn:population":0,
    "gn:timezone":"Asia/Shanghai",
    "iso:country":"CN",
    "name:zho_x_preferred":[
        "\u798f\u5fb7\u5c6f"
    ],
    "wof:name":"Fudetun",
    "wof:placetype":"locality"
},
  "geometry": {"coordinates":[123.96053000000001,48.62557],"type":"Point"}
}