{
  "type": "Feature",
  "properties": {
    "gn:admin1_code":"13",
    "gn:asciiname":"Aitikan",
    "gn:country_code":"CN",
    "gn:dem":-63,
    "gn:feature_class":"P",
    "gn:feature_code":"PPL",
    "gn:name":"Aitikan",
    "gn:population":0,
    "gn:timezone":"Asia/Urumqi",
    "iso:country":"CN",
    "name:und_x_variant":[
        "\u827e\u63d0\u574e"
    ],
    "wof:name":"Aitikan",
    "wof:placetype":"locality"
},
  "geometry": {"coordinates":[88.83896999999997,42.68286],"type":"Point"}
}