{
  "type": "Feature",
  "properties": {
    "gn:admin1_code":"25",
    "gn:asciiname":"Tushanxi",
    "gn:country_code":"CN",
    "gn:dem":139,
    "gn:feature_class":"P",
    "gn:feature_code":"PPL",
    "gn:name":"Tushanxi",
    "gn:population":0,
    "gn:timezone":"Asia/Shanghai",
    "iso:country":"CN",
    "name:zho_x_preferred":[
        "\u571f\u5c71\u897f"
    ],
    "wof:name":"Tushanxi",
    "wof:placetype":"locality"
},
  "geometry": {"coordinates":[118.101,35.3843],"type":"Point"}
}