{
  "type": "Feature",
  "properties": {
    "gn:admin1_code":"8.0",
    "gn:asciiname":"Yuanlincun",
    "gn:country_code":"CN",
    "gn:dem":140,
    "gn:feature_class":"P",
    "gn:feature_code":"PPL",
    "gn:name":"Yuanlincun",
    "gn:population":0,
    "gn:timezone":"Asia/Shanghai",
    "iso:country":"CN",
    "name:zho_x_preferred":[
        "\u56ed\u6797\u6751"
    ],
    "wof:name":"Yuanlincun",
    "wof:placetype":"locality"
},
  "geometry": {"coordinates":[131.25291999999999,46.67898],"type":"Point"}
}