{
  "type": "Feature",
  "properties": {
    "gn:admin1_code":"16.0",
    "gn:asciiname":"Luliu",
    "gn:country_code":"CN",
    "gn:dem":130,
    "gn:feature_class":"P",
    "gn:feature_code":"PPL",
    "gn:name":"L\u00fcliu",
    "gn:population":0,
    "gn:timezone":"Asia/Shanghai",
    "iso:country":"CN",
    "name:und_x_variant":[
        "L\u00fcliu"
    ],
    "name:zho_x_preferred":[
        "\u7eff\u6d41"
    ],
    "wof:name":"Luliu",
    "wof:placetype":"locality"
},
  "geometry": {"coordinates":[108.413,22.9472],"type":"Point"}
}