{
  "type": "Feature",
  "properties": {
    "gn:admin1_code":"32.0",
    "gn:asciiname":"Nantian",
    "gn:country_code":"CN",
    "gn:dem":2329,
    "gn:feature_class":"P",
    "gn:feature_code":"PPL",
    "gn:name":"Nantian",
    "gn:population":0,
    "gn:timezone":"Asia/Shanghai",
    "iso:country":"CN",
    "name:zho_x_preferred":[
        "\u5357\u5929"
    ],
    "wof:name":"Nantian",
    "wof:placetype":"locality"
},
  "geometry": {"coordinates":[101.931,27.5869],"type":"Point"}
}