{
  "type": "Feature",
  "properties": {
    "gn:admin1_code":"19.0",
    "gn:asciiname":"Deyutun",
    "gn:country_code":"CN",
    "gn:dem":238,
    "gn:feature_class":"P",
    "gn:feature_code":"PPL",
    "gn:name":"Deyutun",
    "gn:population":0,
    "gn:timezone":"Asia/Shanghai",
    "iso:country":"CN",
    "name:zho_x_preferred":[
        "\u5fb7\u4f59\u5c6f"
    ],
    "wof:name":"Deyutun",
    "wof:placetype":"locality"
},
  "geometry": {"coordinates":[124.407,42.6072],"type":"Point"}
}