{
  "type": "Feature",
  "properties": {
    "gn:admin1_code":"14.0",
    "gn:asciiname":"Yelongcun",
    "gn:country_code":"CN",
    "gn:dem":4708,
    "gn:feature_class":"P",
    "gn:feature_code":"PPL",
    "gn:name":"Yelongcun",
    "gn:population":0,
    "gn:timezone":"Asia/Urumqi",
    "iso:country":"CN",
    "name:zho_x_preferred":[
        "\u53f6\u9686\u6751"
    ],
    "wof:name":"Yelongcun",
    "wof:placetype":"locality"
},
  "geometry": {"coordinates":[92.14634,30.32951],"type":"Point"}
}