{
  "type": "Feature",
  "properties": {
    "gn:admin1_code":"4.0",
    "gn:asciiname":"Houcong Jiazhuang",
    "gn:country_code":"CN",
    "gn:dem":14,
    "gn:feature_class":"P",
    "gn:feature_code":"PPL",
    "gn:name":"Houcong Jiazhuang",
    "gn:population":0,
    "gn:timezone":"Asia/Shanghai",
    "iso:country":"CN",
    "name:zho_x_preferred":[
        "\u540e\u4e1b\u5bb6\u5e84"
    ],
    "wof:name":"Houcong Jiazhuang",
    "wof:placetype":"locality"
},
  "geometry": {"coordinates":[119.17637000000001,31.7751],"type":"Point"}
}