{
  "type": "Feature",
  "properties": {
    "gn:admin1_code":"32.0",
    "gn:asciiname":"Zheru",
    "gn:country_code":"CN",
    "gn:dem":3237,
    "gn:feature_class":"P",
    "gn:feature_code":"PPL",
    "gn:name":"Zheru",
    "gn:population":0,
    "gn:timezone":"Asia/Shanghai",
    "iso:country":"CN",
    "name:zho_x_preferred":[
        "\u8fd9\u5982"
    ],
    "wof:name":"Zheru",
    "wof:placetype":"locality"
},
  "geometry": {"coordinates":[102.151,32.1835],"type":"Point"}
}