{
  "type": "Feature",
  "properties": {
    "gn:admin1_code":"16.0",
    "gn:asciiname":"Shuanggao",
    "gn:country_code":"CN",
    "gn:dem":198,
    "gn:feature_class":"P",
    "gn:feature_code":"PPL",
    "gn:name":"Shuanggao",
    "gn:population":0,
    "gn:timezone":"Asia/Shanghai",
    "iso:country":"CN",
    "name:zho_x_preferred":[
        "\u53cc\u544a"
    ],
    "wof:name":"Shuanggao",
    "wof:placetype":"locality"
},
  "geometry": {"coordinates":[109.93899999999999,24.0849],"type":"Point"}
}