{
  "type": "Feature",
  "properties": {
    "gn:admin1_code":"32.0",
    "gn:asciiname":"Xiamayixi",
    "gn:country_code":"CN",
    "gn:dem":3279,
    "gn:feature_class":"P",
    "gn:feature_code":"PPL",
    "gn:name":"Xiamayixi",
    "gn:population":0,
    "gn:timezone":"Asia/Shanghai",
    "iso:country":"CN",
    "name:zho_x_preferred":[
        "\u4e0b\u739b\u4f0a\u5e0c"
    ],
    "wof:name":"Xiamayixi",
    "wof:placetype":"locality"
},
  "geometry": {"coordinates":[100.98219,29.53482],"type":"Point"}
}