{
  "type": "Feature",
  "properties": {
    "gn:admin1_code":"29.0",
    "gn:asciiname":"Shaojia Liangzi",
    "gn:country_code":"CN",
    "gn:dem":2240,
    "gn:feature_class":"P",
    "gn:feature_code":"PPL",
    "gn:name":"Shaojia Liangzi",
    "gn:population":0,
    "gn:timezone":"Asia/Shanghai",
    "iso:country":"CN",
    "name:zho_x_preferred":[
        "\u90b5\u5bb6\u6881\u5b50"
    ],
    "wof:name":"Shaojia Liangzi",
    "wof:placetype":"locality"
},
  "geometry": {"coordinates":[104.249,26.2369],"type":"Point"}
}