{
  "type": "Feature",
  "properties": {
    "gn:admin1_code":"10.0",
    "gn:asciiname":"Xingshutai",
    "gn:country_code":"CN",
    "gn:dem":1027,
    "gn:feature_class":"P",
    "gn:feature_code":"PPL",
    "gn:name":"Xingshutai",
    "gn:population":0,
    "gn:timezone":"Asia/Shanghai",
    "iso:country":"CN",
    "name:zho_x_preferred":[
        "\u674f\u6811\u53f0"
    ],
    "wof:name":"Xingshutai",
    "wof:placetype":"locality"
},
  "geometry": {"coordinates":[114.83421,39.25423],"type":"Point"}
}