{
  "type": "Feature",
  "properties": {
    "gn:admin1_code":"4.0",
    "gn:asciiname":"Yanshanhecun",
    "gn:country_code":"CN",
    "gn:dem":16,
    "gn:feature_class":"P",
    "gn:feature_code":"PPL",
    "gn:name":"Yanshanhecun",
    "gn:population":0,
    "gn:timezone":"Asia/Shanghai",
    "iso:country":"CN",
    "name:zho_x_preferred":[
        "\u6cbf\u5c71\u6cb3\u6751"
    ],
    "wof:name":"Yanshanhecun",
    "wof:placetype":"locality"
},
  "geometry": {"coordinates":[119.33051,32.3775],"type":"Point"}
}