{
  "type": "Feature",
  "properties": {
    "gn:admin1_code":"11.0",
    "gn:asciiname":"Xiatang",
    "gn:country_code":"CN",
    "gn:dem":274,
    "gn:feature_class":"P",
    "gn:feature_code":"PPL",
    "gn:name":"Xiatang",
    "gn:population":0,
    "gn:timezone":"Asia/Shanghai",
    "iso:country":"CN",
    "name:zho_x_preferred":[
        "\u867e\u5858"
    ],
    "wof:name":"Xiatang",
    "wof:placetype":"locality"
},
  "geometry": {"coordinates":[112.49606,25.6169],"type":"Point"}
}