{
  "type": "Feature",
  "properties": {
    "gn:admin1_code":"14.0",
    "gn:asciiname":"Nana",
    "gn:country_code":"CN",
    "gn:dem":4986,
    "gn:feature_class":"P",
    "gn:feature_code":"PPL",
    "gn:name":"Nana",
    "gn:population":0,
    "gn:timezone":"Asia/Urumqi",
    "iso:country":"CN",
    "name:zho_x_preferred":[
        "\u7eb3\u90a3"
    ],
    "wof:name":"Nana",
    "wof:placetype":"locality"
},
  "geometry": {"coordinates":[86.0197,30.2488],"type":"Point"}
}