{
  "type": "Feature",
  "properties": {
    "gn:admin1_code":"32.0",
    "gn:asciiname":"Anyuan",
    "gn:country_code":"CN",
    "gn:dem":319,
    "gn:feature_class":"P",
    "gn:feature_code":"PPL",
    "gn:name":"Anyuan",
    "gn:population":0,
    "gn:timezone":"Asia/Shanghai",
    "iso:country":"CN",
    "name:ceb_x_preferred":[
        "Anyuan"
    ],
    "name:deu_x_preferred":[
        "Anyuan"
    ],
    "name:fra_x_preferred":[
        "Anyuan"
    ],
    "name:nor_x_preferred":[
        "Anyuan"
    ],
    "name:swe_x_preferred":[
        "Anyuan"
    ],
    "name:zho_x_preferred":[
        "\u5b89\u8fdc"
    ],
    "wof:name":"Anyuan",
    "wof:placetype":"locality"
},
  "geometry": {"coordinates":[105.10332,28.57745],"type":"Point"}
}