{
  "type": "Feature",
  "properties": {
    "gn:admin1_code":"4.0",
    "gn:asciiname":"Ouchicun",
    "gn:country_code":"CN",
    "gn:dem":5,
    "gn:feature_class":"P",
    "gn:feature_code":"PPL",
    "gn:name":"Ouchicun",
    "gn:population":0,
    "gn:timezone":"Asia/Shanghai",
    "iso:country":"CN",
    "name:zho_x_preferred":[
        "\u85d5\u6c60\u6751"
    ],
    "wof:name":"Ouchicun",
    "wof:placetype":"locality"
},
  "geometry": {"coordinates":[119.01672000000001,34.13928],"type":"Point"}
}