{
  "type": "Feature",
  "properties": {
    "gn:admin1_code":"19.0",
    "gn:asciiname":"Nanchangyuan",
    "gn:country_code":"CN",
    "gn:dem":22,
    "gn:feature_class":"P",
    "gn:feature_code":"PPL",
    "gn:name":"Nanchangyuan",
    "gn:population":0,
    "gn:timezone":"Asia/Shanghai",
    "iso:country":"CN",
    "name:zho_x_preferred":[
        "\u5357\u573a\u9662"
    ],
    "wof:name":"Nanchangyuan",
    "wof:placetype":"locality"
},
  "geometry": {"coordinates":[122.956,39.7363],"type":"Point"}
}