{
  "type": "Feature",
  "properties": {
    "gn:admin1_code":"10",
    "gn:asciiname":"Chenyanggou",
    "gn:country_code":"CN",
    "gn:dem":1392,
    "gn:feature_class":"P",
    "gn:feature_code":"PPL",
    "gn:name":"Chenyanggou",
    "gn:population":0,
    "gn:timezone":"Asia/Shanghai",
    "iso:country":"CN",
    "name:zho_x_preferred":[
        "\u9648\u7f8a\u6c9f"
    ],
    "wof:name":"Chenyanggou",
    "wof:placetype":"locality"
},
  "geometry": {"coordinates":[114.67997,41.15974],"type":"Point"}
}