{
  "type": "Feature",
  "properties": {
    "gn:admin1_code":"6.0",
    "gn:asciiname":"Waka",
    "gn:country_code":"CN",
    "gn:dem":3911,
    "gn:feature_class":"P",
    "gn:feature_code":"PPL",
    "gn:name":"Waka",
    "gn:population":0,
    "gn:timezone":"Asia/Urumqi",
    "iso:country":"CN",
    "name:arg_x_preferred":[
        "Waka"
    ],
    "name:bul_x_preferred":[
        "\u0412\u0430\u043a\u0430"
    ],
    "name:ceb_x_preferred":[
        "Waka"
    ],
    "name:deu_x_preferred":[
        "Waka"
    ],
    "name:fra_x_preferred":[
        "Waka"
    ],
    "name:heb_x_preferred":[
        "\u05d5\u05d0\u05e7\u05d4"
    ],
    "name:ind_x_preferred":[
        "Waka"
    ],
    "name:mri_x_preferred":[
        "Waka"
    ],
    "name:nds_x_preferred":[
        "Waka"
    ],
    "name:nld_x_preferred":[
        "Waka"
    ],
    "name:nor_x_preferred":[
        "Waka"
    ],
    "name:pol_x_preferred":[
        "Waka"
    ],
    "name:por_x_preferred":[
        "Waka"
    ],
    "name:rus_x_preferred":[
        "\u0412\u0430\u043a\u0430"
    ],
    "name:spa_x_preferred":[
        "Waka"
    ],
    "name:swe_x_preferred":[
        "Waka"
    ],
    "name:ukr_x_preferred":[
        "\u0412\u0430\u043a\u0430"
    ],
    "name:zho_x_preferred":[
        "\u74e6\u5361"
    ],
    "wof:name":"Waka",
    "wof:placetype":"locality"
},
  "geometry": {"coordinates":[96.02451000000001,31.89854],"type":"Point"}
}