{
  "type": "Feature",
  "properties": {
    "gn:admin1_code":"2.0",
    "gn:asciiname":"Qianshan",
    "gn:country_code":"CN",
    "gn:dem":21,
    "gn:feature_class":"P",
    "gn:feature_code":"PPL",
    "gn:name":"Qianshan",
    "gn:population":0,
    "gn:timezone":"Asia/Shanghai",
    "iso:country":"CN",
    "name:und_x_variant":[
        "\u524d\u5c71\u6751",
        "Qianshancun",
        "Qianshan",
        "\u524d\u5c71"
    ],
    "wof:name":"Qianshan",
    "wof:placetype":"locality"
},
  "geometry": {"coordinates":[119.87623000000001,29.98617],"type":"Point"}
}