{
  "type": "Feature",
  "properties": {
    "gn:admin1_code":"15.0",
    "gn:asciiname":"Baicaowan",
    "gn:country_code":"CN",
    "gn:dem":1399,
    "gn:feature_class":"P",
    "gn:feature_code":"PPL",
    "gn:name":"Baicaowan",
    "gn:population":0,
    "gn:timezone":"Asia/Shanghai",
    "iso:country":"CN",
    "name:und_x_variant":[
        "\u767d\u8349\u6e7e"
    ],
    "wof:name":"Baicaowan",
    "wof:placetype":"locality"
},
  "geometry": {"coordinates":[107.55146000000001,36.09042],"type":"Point"}
}