{
  "type": "Feature",
  "properties": {
    "gn:admin1_code":"25",
    "gn:asciiname":"Nanguozhuang",
    "gn:country_code":"CN",
    "gn:dem":15,
    "gn:feature_class":"P",
    "gn:feature_code":"PPL",
    "gn:name":"Nanguozhuang",
    "gn:population":0,
    "gn:timezone":"Asia/Shanghai",
    "iso:country":"CN",
    "name:zho_x_preferred":[
        "\u5357\u90ed\u5e84"
    ],
    "wof:name":"Nanguozhuang",
    "wof:placetype":"locality"
},
  "geometry": {"coordinates":[117.908,36.9977],"type":"Point"}
}