{
  "type": "Feature",
  "properties": {
    "gn:admin1_code":"30.0",
    "gn:asciiname":"Gaozhangcun",
    "gn:country_code":"CN",
    "gn:dem":76,
    "gn:feature_class":"P",
    "gn:feature_code":"PPL",
    "gn:name":"Gaozhangcun",
    "gn:population":0,
    "gn:timezone":"Asia/Urumqi",
    "iso:country":"CN",
    "name:zho_x_preferred":[
        "\u9ad8\u7ae0\u6751"
    ],
    "wof:name":"Gaozhangcun",
    "wof:placetype":"locality"
},
  "geometry": {"coordinates":[110.74777,22.21403],"type":"Point"}
}