{
  "type": "Feature",
  "properties": {
    "gn:admin1_code":"19.0",
    "gn:asciiname":"Dafujiatun",
    "gn:country_code":"CN",
    "gn:dem":60,
    "gn:feature_class":"P",
    "gn:feature_code":"PPL",
    "gn:name":"Dafujiatun",
    "gn:population":0,
    "gn:timezone":"Asia/Shanghai",
    "iso:country":"CN",
    "name:und_x_variant":[
        "\u5927\u4ed8\u5bb6\u5c6f"
    ],
    "name:zho_x_preferred":[
        "\u5927\u4ed8\u5bb6\u5c6f"
    ],
    "wof:name":"Dafujiatun",
    "wof:placetype":"locality"
},
  "geometry": {"coordinates":[121.98622,39.93977],"type":"Point"}
}