{
  "type": "Feature",
  "properties": {
    "gn:admin1_code":"32.0",
    "gn:asciiname":"Zishengqiao",
    "gn:country_code":"CN",
    "gn:dem":463,
    "gn:feature_class":"P",
    "gn:feature_code":"PPL",
    "gn:name":"Zishengqiao",
    "gn:population":0,
    "gn:timezone":"Asia/Shanghai",
    "iso:country":"CN",
    "name:zho_x_preferred":[
        "\u81ea\u751f\u6865"
    ],
    "wof:name":"Zishengqiao",
    "wof:placetype":"locality"
},
  "geometry": {"coordinates":[107.79242000000001,30.95695],"type":"Point"}
}