{
  "type": "Feature",
  "properties": {
    "gn:admin1_code":"3.0",
    "gn:asciiname":"Luoqiu",
    "gn:country_code":"CN",
    "gn:dem":108,
    "gn:feature_class":"P",
    "gn:feature_code":"PPL",
    "gn:name":"Luoqiu",
    "gn:population":0,
    "gn:timezone":"Asia/Shanghai",
    "iso:country":"CN",
    "name:und_x_variant":[
        "\u7f57\u4e18"
    ],
    "wof:name":"Luoqiu",
    "wof:placetype":"locality"
},
  "geometry": {"coordinates":[114.44069,27.17028],"type":"Point"}
}