{
  "type": "Feature",
  "properties": {
    "gn:admin1_code":"32.0",
    "gn:asciiname":"Xienigou",
    "gn:country_code":"CN",
    "gn:dem":1948,
    "gn:feature_class":"P",
    "gn:feature_code":"PPL",
    "gn:name":"Xienigou",
    "gn:population":0,
    "gn:timezone":"Asia/Shanghai",
    "iso:country":"CN",
    "name:zho_x_preferred":[
        "\u5378\u6ce5\u6c9f"
    ],
    "wof:name":"Xienigou",
    "wof:placetype":"locality"
},
  "geometry": {"coordinates":[102.36499999999999,29.6893],"type":"Point"}
}