{
  "type": "Feature",
  "properties": {
    "gn:admin1_code":"15.0",
    "gn:asciiname":"Yuzhong Chengguanzhen",
    "gn:country_code":"CN",
    "gn:dem":1981,
    "gn:feature_class":"P",
    "gn:feature_code":"PPLA3",
    "gn:name":"Yuzhong Chengguanzhen",
    "gn:population":0,
    "gn:timezone":"Asia/Shanghai",
    "iso:country":"CN",
    "name:und_x_variant":[
        "Chin",
        "Y\u00fc-chung-hsien",
        "Chin-ch\u2019eng",
        "Y\u00fc-chung",
        "Yuzhong",
        "Yuzhong Chengguanzhen",
        "Yuzhong Xian"
    ],
    "name:zho_x_preferred":[
        "\u6986\u4e2d\u57ce\u5173\u9547"
    ],
    "name:zho_x_variant":[
        "\u6986\u4e2d\u53bf"
    ],
    "wof:name":"Yuzhong Chengguanzhen",
    "wof:placetype":"locality"
},
  "geometry": {"coordinates":[104.1125,35.84278],"type":"Point"}
}