{
  "type": "Feature",
  "properties": {
    "gn:admin1_code":"4.0",
    "gn:asciiname":"Maodi Xudai",
    "gn:country_code":"CN",
    "gn:dem":5,
    "gn:feature_class":"P",
    "gn:feature_code":"PPL",
    "gn:name":"Maodi Xudai",
    "gn:population":0,
    "gn:timezone":"Asia/Shanghai",
    "iso:country":"CN",
    "name:zho_x_preferred":[
        "\u5e3d\u955d\u5729\u57ed"
    ],
    "wof:name":"Maodi Xudai",
    "wof:placetype":"locality"
},
  "geometry": {"coordinates":[119.8603,32.0836],"type":"Point"}
}