{
  "type": "Feature",
  "properties": {
    "gn:admin1_code":"29.0",
    "gn:asciiname":"Yunkan",
    "gn:country_code":"CN",
    "gn:dem":508,
    "gn:feature_class":"P",
    "gn:feature_code":"PPL",
    "gn:name":"Yunkan",
    "gn:population":0,
    "gn:timezone":"Asia/Shanghai",
    "iso:country":"CN",
    "name:zho_x_preferred":[
        "\u5141\u574e"
    ],
    "wof:name":"Yunkan",
    "wof:placetype":"locality"
},
  "geometry": {"coordinates":[99.0879,23.6044],"type":"Point"}
}