{
  "type": "Feature",
  "properties": {
    "gn:admin1_code":"11.0",
    "gn:asciiname":"Aokou",
    "gn:country_code":"CN",
    "gn:dem":869,
    "gn:feature_class":"P",
    "gn:feature_code":"PPL",
    "gn:name":"Aokou",
    "gn:population":0,
    "gn:timezone":"Asia/Shanghai",
    "iso:country":"CN",
    "name:zho_x_preferred":[
        "\u5773\u53e3"
    ],
    "wof:name":"Aokou",
    "wof:placetype":"locality"
},
  "geometry": {"coordinates":[109.53834000000001,29.31516],"type":"Point"}
}