{
  "type": "Feature",
  "properties": {
    "gn:admin1_code":"29.0",
    "gn:asciiname":"Luziqing",
    "gn:country_code":"CN",
    "gn:dem":1767,
    "gn:feature_class":"P",
    "gn:feature_code":"PPL",
    "gn:name":"Luziqing",
    "gn:population":0,
    "gn:timezone":"Asia/Shanghai",
    "iso:country":"CN",
    "name:zho_x_preferred":[
        "\u82a6\u5b50\u7b90"
    ],
    "wof:name":"Luziqing",
    "wof:placetype":"locality"
},
  "geometry": {"coordinates":[103.084,23.2999],"type":"Point"}
}