{
  "type": "Feature",
  "properties": {
    "gn:admin1_code":"2.0",
    "gn:asciiname":"Nantiandun",
    "gn:country_code":"CN",
    "gn:dem":907,
    "gn:feature_class":"P",
    "gn:feature_code":"PPL",
    "gn:name":"Nantiandun",
    "gn:population":0,
    "gn:timezone":"Asia/Shanghai",
    "iso:country":"CN",
    "name:zho_x_preferred":[
        "\u5357\u7530\u58a9"
    ],
    "wof:name":"Nantiandun",
    "wof:placetype":"locality"
},
  "geometry": {"coordinates":[119.22733999999998,27.69019],"type":"Point"}
}