{
  "type": "Feature",
  "properties": {
    "gn:admin1_code":"16.0",
    "gn:asciiname":"Jimuling",
    "gn:country_code":"CN",
    "gn:dem":53,
    "gn:feature_class":"P",
    "gn:feature_code":"PPL",
    "gn:name":"Jimuling",
    "gn:population":0,
    "gn:timezone":"Asia/Shanghai",
    "iso:country":"CN",
    "name:zho_x_preferred":[
        "\u9e21\u6bcd\u5cad"
    ],
    "wof:name":"Jimuling",
    "wof:placetype":"locality"
},
  "geometry": {"coordinates":[109.735,23.0661],"type":"Point"}
}