{
  "type": "Feature",
  "properties": {
    "gn:admin1_code":"4.0",
    "gn:asciiname":"Tiaoyancun",
    "gn:country_code":"CN",
    "gn:dem":8,
    "gn:feature_class":"P",
    "gn:feature_code":"PPL",
    "gn:name":"Tiaoyancun",
    "gn:population":0,
    "gn:timezone":"Asia/Shanghai",
    "iso:country":"CN",
    "name:zho_x_preferred":[
        "\u6761\u6cbf\u6751"
    ],
    "wof:name":"Tiaoyancun",
    "wof:placetype":"locality"
},
  "geometry": {"coordinates":[119.28167999999999,33.74628],"type":"Point"}
}