{
  "type": "Feature",
  "properties": {
    "gn:admin1_code":"8.0",
    "gn:asciiname":"Xidacun",
    "gn:country_code":"CN",
    "gn:dem":288,
    "gn:feature_class":"P",
    "gn:feature_code":"PPL",
    "gn:name":"Xidacun",
    "gn:population":0,
    "gn:timezone":"Asia/Shanghai",
    "iso:country":"CN",
    "name:zho_x_preferred":[
        "\u897f\u5927\u6751"
    ],
    "wof:name":"Xidacun",
    "wof:placetype":"locality"
},
  "geometry": {"coordinates":[125.22635,48.09889],"type":"Point"}
}