{
  "type": "Feature",
  "properties": {
    "gn:admin1_code":"32.0",
    "gn:asciiname":"Bishihou",
    "gn:country_code":"CN",
    "gn:dem":2704,
    "gn:feature_class":"P",
    "gn:feature_code":"PPL",
    "gn:name":"Bishihou",
    "gn:population":0,
    "gn:timezone":"Asia/Shanghai",
    "iso:country":"CN",
    "name:zho_x_preferred":[
        "\u6bd4\u65f6\u5019"
    ],
    "wof:name":"Bishihou",
    "wof:placetype":"locality"
},
  "geometry": {"coordinates":[102.795,28.2674],"type":"Point"}
}