{
  "type": "Feature",
  "properties": {
    "gn:admin1_code":"10.0",
    "gn:asciiname":"Nan'anzhuang",
    "gn:country_code":"CN",
    "gn:dem":239,
    "gn:feature_class":"P",
    "gn:feature_code":"PPL",
    "gn:name":"Nan\u2019anzhuang",
    "gn:population":0,
    "gn:timezone":"Asia/Shanghai",
    "iso:country":"CN",
    "name:und_x_variant":[
        "Nan\u2019anzhuang"
    ],
    "name:zho_x_preferred":[
        "\u5357\u5b89\u5e84"
    ],
    "wof:name":"Nan'anzhuang",
    "wof:placetype":"locality"
},
  "geometry": {"coordinates":[115.56010000000001,39.53819],"type":"Point"}
}