{
  "type": "Feature",
  "properties": {
    "gn:admin1_code":"32.0",
    "gn:asciiname":"Wupao",
    "gn:country_code":"CN",
    "gn:dem":599,
    "gn:feature_class":"P",
    "gn:feature_code":"PPL",
    "gn:name":"Wupao",
    "gn:population":0,
    "gn:timezone":"Asia/Shanghai",
    "iso:country":"CN",
    "name:zho_x_preferred":[
        "\u4e4c\u629b"
    ],
    "wof:name":"Wupao",
    "wof:placetype":"locality"
},
  "geometry": {"coordinates":[104.02406000000001,29.84925],"type":"Point"}
}