{
  "type": "Feature",
  "properties": {
    "gn:admin1_code":"19.0",
    "gn:asciiname":"Huosanjiacun",
    "gn:country_code":"CN",
    "gn:dem":16,
    "gn:feature_class":"P",
    "gn:feature_code":"PPL",
    "gn:name":"Huosanjiacun",
    "gn:population":0,
    "gn:timezone":"Asia/Shanghai",
    "iso:country":"CN",
    "name:zho_x_preferred":[
        "\u970d\u4e09\u5bb6\u6751"
    ],
    "wof:name":"Huosanjiacun",
    "wof:placetype":"locality"
},
  "geometry": {"coordinates":[121.535,41.238],"type":"Point"}
}