{
  "type": "Feature",
  "properties": {
    "gn:admin1_code":"6.0",
    "gn:asciiname":"Suod Xiuma",
    "gn:country_code":"CN",
    "gn:dem":3465,
    "gn:feature_class":"P",
    "gn:feature_code":"PPL",
    "gn:name":"Suod Xiuma",
    "gn:population":0,
    "gn:timezone":"Asia/Shanghai",
    "iso:country":"CN",
    "name:und_x_variant":[
        "\u68ad\u5730\u4f11\u739b"
    ],
    "wof:name":"Suod Xiuma",
    "wof:placetype":"locality"
},
  "geometry": {"coordinates":[100.88796000000001,35.39717],"type":"Point"}
}