{
  "type": "Feature",
  "properties": {
    "gn:admin1_code":"29.0",
    "gn:asciiname":"Budai",
    "gn:country_code":"CN",
    "gn:dem":1543,
    "gn:feature_class":"P",
    "gn:feature_code":"PPL",
    "gn:name":"Budai",
    "gn:population":0,
    "gn:timezone":"Asia/Shanghai",
    "iso:country":"CN",
    "name:zho_x_preferred":[
        "\u8865\u6b79"
    ],
    "wof:name":"Budai",
    "wof:placetype":"locality"
},
  "geometry": {"coordinates":[104.27500000000001,24.7662],"type":"Point"}
}