{
  "type": "Feature",
  "properties": {
    "gn:admin1_code":"1.0",
    "gn:asciiname":"Zhangdu",
    "gn:country_code":"CN",
    "gn:dem":50,
    "gn:feature_class":"P",
    "gn:feature_code":"PPLA4",
    "gn:name":"Zhangdu",
    "gn:population":0,
    "gn:timezone":"Asia/Shanghai",
    "iso:country":"CN",
    "name:und_x_variant":[
        "Chang-chia-tu-chen",
        "Chang-tu",
        "Chang-chia-tu",
        "Changkiatu",
        "Zhangdu",
        "\u7ae0\u6e21",
        "Zhangdu Zhen",
        "\u7ae0\u6e21\u9547"
    ],
    "wof:name":"Zhangdu",
    "wof:placetype":"locality"
},
  "geometry": {"coordinates":[118.22796,30.59637],"type":"Point"}
}