{
  "type": "Feature",
  "properties": {
    "gn:admin1_code":"30.0",
    "gn:asciiname":"Tanghucun",
    "gn:country_code":"CN",
    "gn:dem":189,
    "gn:feature_class":"P",
    "gn:feature_code":"PPL",
    "gn:name":"Tanghucun",
    "gn:population":0,
    "gn:timezone":"Asia/Shanghai",
    "iso:country":"CN",
    "name:zho_x_preferred":[
        "\u6c64\u6e56\u6751"
    ],
    "wof:name":"Tanghucun",
    "wof:placetype":"locality"
},
  "geometry": {"coordinates":[115.91625999999999,24.38125],"type":"Point"}
}