{
  "type": "Feature",
  "properties": {
    "gn:admin1_code":"1.0",
    "gn:asciiname":"Hanzhuangcun",
    "gn:country_code":"CN",
    "gn:dem":32,
    "gn:feature_class":"P",
    "gn:feature_code":"PPL",
    "gn:name":"Hanzhuangcun",
    "gn:population":0,
    "gn:timezone":"Asia/Shanghai",
    "iso:country":"CN",
    "name:zho_x_preferred":[
        "\u97e9\u5e84\u6751"
    ],
    "wof:name":"Hanzhuangcun",
    "wof:placetype":"locality"
},
  "geometry": {"coordinates":[116.26528999999999,33.30067],"type":"Point"}
}