{
  "type": "Feature",
  "properties": {
    "gn:admin1_code":"4.0",
    "gn:asciiname":"Jiulicun",
    "gn:country_code":"CN",
    "gn:dem":3,
    "gn:feature_class":"P",
    "gn:feature_code":"PPL",
    "gn:name":"Jiulicun",
    "gn:population":0,
    "gn:timezone":"Asia/Shanghai",
    "iso:country":"CN",
    "name:zho_x_preferred":[
        "\u4e5d\u91cc\u6751"
    ],
    "wof:name":"Jiulicun",
    "wof:placetype":"locality"
},
  "geometry": {"coordinates":[119.19768999999999,35.01813],"type":"Point"}
}