{
  "type": "Feature",
  "properties": {
    "gn:admin1_code":"14.0",
    "gn:asciiname":"Rimu",
    "gn:country_code":"CN",
    "gn:dem":3232,
    "gn:feature_class":"P",
    "gn:feature_code":"PPL",
    "gn:name":"Rimu",
    "gn:population":0,
    "gn:timezone":"Asia/Urumqi",
    "iso:country":"CN",
    "name:bod_x_preferred":[
        "Rimu"
    ],
    "name:zho_x_preferred":[
        "\u65e5\u6728"
    ],
    "name:zho_x_variant":[
        "Xingmu Gongshe",
        "\u661f\u6728\u516c\u793e"
    ],
    "wof:name":"Rimu",
    "wof:placetype":"locality"
},
  "geometry": {"coordinates":[96.09684,29.89446],"type":"Point"}
}