{
  "type": "Feature",
  "properties": {
    "gn:admin1_code":"3.0",
    "gn:asciiname":"Lingbei",
    "gn:country_code":"CN",
    "gn:dem":128,
    "gn:feature_class":"P",
    "gn:feature_code":"PPL",
    "gn:name":"Lingbei",
    "gn:population":0,
    "gn:timezone":"Asia/Shanghai",
    "iso:country":"CN",
    "name:deu_x_preferred":[
        "Lingbei"
    ],
    "name:zho_x_preferred":[
        "\u5cad\u80cc"
    ],
    "wof:name":"Lingbei",
    "wof:placetype":"locality"
},
  "geometry": {"coordinates":[114.38200000000001,27.079],"type":"Point"}
}