{
  "type": "Feature",
  "properties": {
    "gn:admin1_code":"26.0",
    "gn:asciiname":"Changmingcun",
    "gn:country_code":"CN",
    "gn:dem":906,
    "gn:feature_class":"P",
    "gn:feature_code":"PPL",
    "gn:name":"Changmingcun",
    "gn:population":0,
    "gn:timezone":"Asia/Shanghai",
    "iso:country":"CN",
    "name:zho_x_preferred":[
        "\u957f\u547d\u6751"
    ],
    "wof:name":"Changmingcun",
    "wof:placetype":"locality"
},
  "geometry": {"coordinates":[110.27725,36.24504],"type":"Point"}
}