{
  "type": "Feature",
  "properties": {
    "gn:admin1_code":"16.0",
    "gn:asciiname":"Longhu",
    "gn:country_code":"CN",
    "gn:dem":288,
    "gn:feature_class":"P",
    "gn:feature_code":"PPL",
    "gn:name":"Longhu",
    "gn:population":0,
    "gn:timezone":"Asia/Shanghai",
    "iso:country":"CN",
    "name:ceb_x_preferred":[
        "Longhu"
    ],
    "name:deu_x_preferred":[
        "Longhu"
    ],
    "name:zho_x_preferred":[
        "\u9647\u547c"
    ],
    "wof:name":"Longhu",
    "wof:placetype":"locality"
},
  "geometry": {"coordinates":[106.842,22.5259],"type":"Point"}
}