{
  "type": "Feature",
  "properties": {
    "gn:admin1_code":"8.0",
    "gn:asciiname":"Shuangquancun",
    "gn:country_code":"CN",
    "gn:dem":287,
    "gn:feature_class":"P",
    "gn:feature_code":"PPL",
    "gn:name":"Shuangquancun",
    "gn:population":0,
    "gn:timezone":"Asia/Shanghai",
    "iso:country":"CN",
    "name:zho_x_preferred":[
        "\u53cc\u6cc9\u6751"
    ],
    "wof:name":"Shuangquancun",
    "wof:placetype":"locality"
},
  "geometry": {"coordinates":[125.70707,49.19542],"type":"Point"}
}