{
  "type": "Feature",
  "properties": {
    "gn:admin1_code":"09",
    "gn:asciiname":"Lugang",
    "gn:country_code":"CN",
    "gn:dem":72,
    "gn:feature_class":"P",
    "gn:feature_code":"PPL",
    "gn:name":"Lugang",
    "gn:population":0,
    "gn:timezone":"Asia/Shanghai",
    "iso:country":"CN",
    "name:ceb_x_preferred":[
        "Lugang"
    ],
    "name:swe_x_preferred":[
        "Lugang"
    ],
    "wof:name":"Lugang",
    "wof:placetype":"locality"
},
  "geometry": {"coordinates":[114.49666999999999,35.00417],"type":"Point"}
}