{
  "type": "Feature",
  "properties": {
    "gn:admin1_code":"4.0",
    "gn:asciiname":"Shihu Linchang",
    "gn:country_code":"CN",
    "gn:dem":42,
    "gn:feature_class":"P",
    "gn:feature_code":"PPLF",
    "gn:name":"Shihu Linchang",
    "gn:population":0,
    "gn:timezone":"Asia/Shanghai",
    "iso:country":"CN",
    "name:und_x_variant":[
        "\u77f3\u6e56\u6797\u573a"
    ],
    "wof:name":"Shihu Linchang",
    "wof:placetype":"locality"
},
  "geometry": {"coordinates":[118.66063,34.51311],"type":"Point"}
}