{
  "type": "Feature",
  "properties": {
    "gn:admin1_code":"12.0",
    "gn:asciiname":"Liuji",
    "gn:country_code":"CN",
    "gn:dem":39,
    "gn:feature_class":"P",
    "gn:feature_code":"PPL",
    "gn:name":"Liuji",
    "gn:population":0,
    "gn:timezone":"Asia/Shanghai",
    "iso:country":"CN",
    "name:ceb_x_preferred":[
        "Liuji"
    ],
    "name:deu_x_preferred":[
        "Liuji"
    ],
    "name:swe_x_preferred":[
        "Liuji"
    ],
    "name:zho_x_preferred":[
        "\u5218\u96c6"
    ],
    "wof:name":"Liuji",
    "wof:placetype":"locality"
},
  "geometry": {"coordinates":[112.67326,30.94114],"type":"Point"}
}