{
  "type": "Feature",
  "properties": {
    "gn:admin1_code":"20",
    "gn:asciiname":"Yuan-pao-lung",
    "gn:country_code":"CN",
    "gn:dem":500,
    "gn:feature_class":"P",
    "gn:feature_code":"PPL",
    "gn:name":"Y\u00fcan-pao-lung",
    "gn:population":0,
    "gn:timezone":"Asia/Shanghai",
    "iso:country":"CN",
    "wof:name":"Yuan-pao-lung",
    "wof:placetype":"locality"
},
  "geometry": {"coordinates":[119.24722,42.39861],"type":"Point"}
}