{
  "type": "Feature",
  "properties": {
    "gn:admin1_code":"4.0",
    "gn:asciiname":"Fengshancun",
    "gn:country_code":"CN",
    "gn:dem":39,
    "gn:feature_class":"P",
    "gn:feature_code":"PPL",
    "gn:name":"Fengshancun",
    "gn:population":0,
    "gn:timezone":"Asia/Shanghai",
    "iso:country":"CN",
    "name:und_x_variant":[
        "Fengshan",
        "Fengshancun"
    ],
    "name:zho_x_preferred":[
        "\u5cf0\u5c71"
    ],
    "name:zho_x_variant":[
        "\u5cf0\u5c71\u6751"
    ],
    "wof:name":"Fengshancun",
    "wof:placetype":"locality"
},
  "geometry": {"coordinates":[117.64252,34.0813],"type":"Point"}
}