{
  "type": "Feature",
  "properties": {
    "gn:admin1_code":"29.0",
    "gn:asciiname":"Shangxiezhai",
    "gn:country_code":"CN",
    "gn:dem":1766,
    "gn:feature_class":"P",
    "gn:feature_code":"PPL",
    "gn:name":"Shangxiezhai",
    "gn:population":0,
    "gn:timezone":"Asia/Shanghai",
    "iso:country":"CN",
    "name:zho_x_preferred":[
        "\u4e0a\u5199\u5be8"
    ],
    "wof:name":"Shangxiezhai",
    "wof:placetype":"locality"
},
  "geometry": {"coordinates":[99.12130000000001,24.6126],"type":"Point"}
}