{
  "type": "Feature",
  "properties": {
    "gn:admin1_code":"18.0",
    "gn:asciiname":"Zhuchangping",
    "gn:country_code":"CN",
    "gn:dem":1583,
    "gn:feature_class":"P",
    "gn:feature_code":"PPL",
    "gn:name":"Zhuchangping",
    "gn:population":0,
    "gn:timezone":"Asia/Shanghai",
    "iso:country":"CN",
    "wof:name":"Zhuchangping",
    "wof:placetype":"locality"
},
  "geometry": {"coordinates":[104.73333,24.85417],"type":"Point"}
}