{
  "type": "Feature",
  "properties": {
    "gn:admin1_code":"09",
    "gn:asciiname":"Shuangmiao",
    "gn:country_code":"CN",
    "gn:dem":82,
    "gn:feature_class":"P",
    "gn:feature_code":"PPLA4",
    "gn:name":"Shuangmiao",
    "gn:population":0,
    "gn:timezone":"Asia/Shanghai",
    "iso:country":"CN",
    "name:ceb_x_preferred":[
        "Shuangmiao"
    ],
    "name:swe_x_preferred":[
        "Shuangmiao"
    ],
    "name:und_x_variant":[
        "Shuang-miao-chieh",
        "Shuangmiao"
    ],
    "name:zho_x_preferred":[
        "\u53cc\u5e99"
    ],
    "wof:name":"Shuangmiao",
    "wof:placetype":"locality"
},
  "geometry": {"coordinates":[113.63424000000001,33.9075],"type":"Point"}
}