{
  "type": "Feature",
  "properties": {
    "gn:admin1_code":"25",
    "gn:asciiname":"Chaomi",
    "gn:country_code":"CN",
    "gn:dem":71,
    "gn:feature_class":"P",
    "gn:feature_code":"PPL",
    "gn:name":"Chaomi",
    "gn:population":0,
    "gn:timezone":"Asia/Shanghai",
    "iso:country":"CN",
    "name:zho_x_preferred":[
        "\u7092\u7c73"
    ],
    "wof:name":"Chaomi",
    "wof:placetype":"locality"
},
  "geometry": {"coordinates":[118.11199999999999,36.7628],"type":"Point"}
}