{
  "type": "Feature",
  "properties": {
    "gn:admin1_code":"11.0",
    "gn:asciiname":"Tuqiangwan",
    "gn:country_code":"CN",
    "gn:dem":566,
    "gn:feature_class":"P",
    "gn:feature_code":"PPL",
    "gn:name":"Tuqiangwan",
    "gn:population":0,
    "gn:timezone":"Asia/Shanghai",
    "iso:country":"CN",
    "name:zho_x_preferred":[
        "\u571f\u5899\u6e7e"
    ],
    "wof:name":"Tuqiangwan",
    "wof:placetype":"locality"
},
  "geometry": {"coordinates":[110.94329999999999,28.85365],"type":"Point"}
}