{
  "type": "Feature",
  "properties": {
    "gn:admin1_code":"03",
    "gn:asciiname":"Changxi",
    "gn:country_code":"CN",
    "gn:dem":367,
    "gn:feature_class":"P",
    "gn:feature_code":"PPL",
    "gn:name":"Changxi",
    "gn:population":0,
    "gn:timezone":"Asia/Shanghai",
    "iso:country":"CN",
    "name:dan_x_preferred":[
        "Changxi"
    ],
    "name:fas_x_preferred":[
        "\u0686\u0627\u0646\u06af\u200c\u0634\u06cc"
    ],
    "name:hun_x_preferred":[
        "Csang-hszi"
    ],
    "name:swe_x_preferred":[
        "Chang Xi"
    ],
    "name:zho_x_preferred":[
        "\u957f\u6eaa"
    ],
    "wof:name":"Changxi",
    "wof:placetype":"locality"
},
  "geometry": {"coordinates":[115.60341,24.99492],"type":"Point"}
}