{
  "type": "Feature",
  "properties": {
    "gn:admin1_code":"03",
    "gn:asciiname":"Mingkou",
    "gn:country_code":"CN",
    "gn:dem":43,
    "gn:feature_class":"P",
    "gn:feature_code":"PPLA4",
    "gn:name":"Mingkou",
    "gn:population":0,
    "gn:timezone":"Asia/Shanghai",
    "iso:country":"CN",
    "name:und_x_variant":[
        "\u540d\u53e3",
        "Mingkou Zhen",
        "\u540d\u53e3\u9547"
    ],
    "wof:name":"Mingkou",
    "wof:placetype":"locality"
},
  "geometry": {"coordinates":[117.43058000000001,28.91852],"type":"Point"}
}