{
  "type": "Feature",
  "properties": {
    "gn:admin1_code":"30",
    "gn:asciiname":"Leliu",
    "gn:country_code":"CN",
    "gn:dem":5,
    "gn:feature_class":"P",
    "gn:feature_code":"PPLA4",
    "gn:name":"Leliu",
    "gn:population":0,
    "gn:timezone":"Asia/Shanghai",
    "iso:country":"CN",
    "name:und_x_variant":[
        "Leliu Jiedao"
    ],
    "name:zho_x_preferred":[
        "\u52d2\u6d41"
    ],
    "name:zho_x_variant":[
        "\u52d2\u6d41\u8857\u9053"
    ],
    "wof:name":"Leliu",
    "wof:placetype":"locality"
},
  "geometry": {"coordinates":[113.11897999999999,22.86056],"type":"Point"}
}