{
  "type": "Feature",
  "properties": {
    "gn:admin1_code":"19.0",
    "gn:asciiname":"Zhashancun",
    "gn:country_code":"CN",
    "gn:dem":72,
    "gn:feature_class":"P",
    "gn:feature_code":"PPL",
    "gn:name":"Zhashancun",
    "gn:population":0,
    "gn:timezone":"Asia/Shanghai",
    "iso:country":"CN",
    "name:zho_x_preferred":[
        "\u781f\u5c71\u6751"
    ],
    "wof:name":"Zhashancun",
    "wof:placetype":"locality"
},
  "geometry": {"coordinates":[120.664,40.7129],"type":"Point"}
}