{
  "type": "Feature",
  "properties": {
    "gn:admin1_code":"29.0",
    "gn:asciiname":"Dadi",
    "gn:country_code":"CN",
    "gn:dem":1918,
    "gn:feature_class":"P",
    "gn:feature_code":"PPL",
    "gn:name":"Dadi",
    "gn:population":0,
    "gn:timezone":"Asia/Shanghai",
    "iso:country":"CN",
    "name:zho_x_preferred":[
        "\u5927\u5730"
    ],
    "wof:name":"Dadi",
    "wof:placetype":"locality"
},
  "geometry": {"coordinates":[104.34,27.6285],"type":"Point"}
}