{
  "type": "Feature",
  "properties": {
    "gn:admin1_code":"19.0",
    "gn:asciiname":"Pingshanzicun",
    "gn:country_code":"CN",
    "gn:dem":79,
    "gn:feature_class":"P",
    "gn:feature_code":"PPL",
    "gn:name":"Pingshanzicun",
    "gn:population":0,
    "gn:timezone":"Asia/Shanghai",
    "iso:country":"CN",
    "name:zho_x_preferred":[
        "\u5e73\u5c71\u5b50\u6751"
    ],
    "wof:name":"Pingshanzicun",
    "wof:placetype":"locality"
},
  "geometry": {"coordinates":[120.11688999999998,40.63768],"type":"Point"}
}