{
  "type": "Feature",
  "properties": {
    "gn:admin1_code":"3.0",
    "gn:asciiname":"Shayuanshi",
    "gn:country_code":"CN",
    "gn:dem":401,
    "gn:feature_class":"P",
    "gn:feature_code":"PPL",
    "gn:name":"Shayuanshi",
    "gn:population":0,
    "gn:timezone":"Asia/Shanghai",
    "iso:country":"CN",
    "name:und_x_variant":[
        "\u6c99\u56ed\u77f3"
    ],
    "wof:name":"Shayuanshi",
    "wof:placetype":"locality"
},
  "geometry": {"coordinates":[114.32373,24.66004],"type":"Point"}
}