{
  "type": "Feature",
  "properties": {
    "gn:admin1_code":"14.0",
    "gn:asciiname":"Gongma",
    "gn:country_code":"CN",
    "gn:dem":3309,
    "gn:feature_class":"P",
    "gn:feature_code":"PPL",
    "gn:name":"Gongma",
    "gn:population":0,
    "gn:timezone":"Asia/Urumqi",
    "iso:country":"CN",
    "name:zho_x_preferred":[
        "\u8d21\u739b"
    ],
    "wof:name":"Gongma",
    "wof:placetype":"locality"
},
  "geometry": {"coordinates":[95.45001000000001,29.75129],"type":"Point"}
}