{
  "type": "Feature",
  "properties": {
    "gn:admin1_code":"1.0",
    "gn:asciiname":"Dongkengxi",
    "gn:country_code":"CN",
    "gn:dem":377,
    "gn:feature_class":"P",
    "gn:feature_code":"PPL",
    "gn:name":"Dongkengxi",
    "gn:population":0,
    "gn:timezone":"Asia/Shanghai",
    "iso:country":"CN",
    "name:zho_x_preferred":[
        "\u4e1c\u5751\u6eaa"
    ],
    "wof:name":"Dongkengxi",
    "wof:placetype":"locality"
},
  "geometry": {"coordinates":[118.28212000000001,29.97618],"type":"Point"}
}