{
  "type": "Feature",
  "properties": {
    "gn:admin1_code":"32.0",
    "gn:asciiname":"Dongrong",
    "gn:country_code":"CN",
    "gn:dem":3046,
    "gn:feature_class":"P",
    "gn:feature_code":"PPL",
    "gn:name":"Dongrong",
    "gn:population":0,
    "gn:timezone":"Asia/Urumqi",
    "iso:country":"CN",
    "name:zho_x_preferred":[
        "\u51ac\u7ed2"
    ],
    "wof:name":"Dongrong",
    "wof:placetype":"locality"
},
  "geometry": {"coordinates":[98.7718,31.4804],"type":"Point"}
}