{
  "type": "Feature",
  "properties": {
    "gn:admin1_code":"12.0",
    "gn:asciiname":"Chuzhuang",
    "gn:country_code":"CN",
    "gn:dem":232,
    "gn:feature_class":"P",
    "gn:feature_code":"PPL",
    "gn:name":"Chuzhuang",
    "gn:population":0,
    "gn:timezone":"Asia/Shanghai",
    "iso:country":"CN",
    "name:zho_x_preferred":[
        "\u891a\u5e84"
    ],
    "wof:name":"Chuzhuang",
    "wof:placetype":"locality"
},
  "geometry": {"coordinates":[113.00282,32.32495],"type":"Point"}
}