{
  "type": "Feature",
  "properties": {
    "gn:admin1_code":"25.0",
    "gn:asciiname":"Fuzishicun",
    "gn:country_code":"CN",
    "gn:dem":159,
    "gn:feature_class":"P",
    "gn:feature_code":"PPL",
    "gn:name":"Fuzishicun",
    "gn:population":0,
    "gn:timezone":"Asia/Shanghai",
    "iso:country":"CN",
    "name:zho_x_preferred":[
        "\u592b\u5b50\u77f3\u6751"
    ],
    "wof:name":"Fuzishicun",
    "wof:placetype":"locality"
},
  "geometry": {"coordinates":[120.27848,37.20447],"type":"Point"}
}