{
  "type": "Feature",
  "properties": {
    "gn:admin1_code":"14.0",
    "gn:asciiname":"Rabdain",
    "gn:country_code":"CN",
    "gn:dem":3336,
    "gn:feature_class":"P",
    "gn:feature_code":"PPLF",
    "gn:name":"Rabdain",
    "gn:population":0,
    "gn:timezone":"Asia/Urumqi",
    "iso:country":"CN",
    "name:bod_x_preferred":[
        "Rabdain"
    ],
    "name:zho_x_preferred":[
        "Randeng"
    ],
    "name:zho_x_variant":[
        "\u7136\u706f"
    ],
    "wof:name":"Rabdain",
    "wof:placetype":"locality"
},
  "geometry": {"coordinates":[98.49754,31.74957],"type":"Point"}
}