{
  "type": "Feature",
  "properties": {
    "gn:admin1_code":"16.0",
    "gn:asciiname":"Dongsang",
    "gn:country_code":"CN",
    "gn:dem":89,
    "gn:feature_class":"P",
    "gn:feature_code":"PPL",
    "gn:name":"Dongsang",
    "gn:population":0,
    "gn:timezone":"Asia/Shanghai",
    "iso:country":"CN",
    "name:zho_x_preferred":[
        "\u5cbd\u6851"
    ],
    "wof:name":"Dongsang",
    "wof:placetype":"locality"
},
  "geometry": {"coordinates":[108.44499999999999,22.2256],"type":"Point"}
}