{
  "type": "Feature",
  "properties": {
    "gn:admin1_code":"8.0",
    "gn:asciiname":"Linancun",
    "gn:country_code":"CN",
    "gn:dem":125,
    "gn:feature_class":"P",
    "gn:feature_code":"PPL",
    "gn:name":"Linancun",
    "gn:population":0,
    "gn:timezone":"Asia/Shanghai",
    "iso:country":"CN",
    "name:zho_x_preferred":[
        "\u5229\u5357\u6751"
    ],
    "wof:name":"Linancun",
    "wof:placetype":"locality"
},
  "geometry": {"coordinates":[127.88236999999999,46.03722],"type":"Point"}
}