{
  "type": "Feature",
  "properties": {
    "gn:admin1_code":"30.0",
    "gn:asciiname":"Dakengkou",
    "gn:country_code":"CN",
    "gn:dem":79,
    "gn:feature_class":"P",
    "gn:feature_code":"PPL",
    "gn:name":"Dakengkou",
    "gn:population":0,
    "gn:timezone":"Asia/Shanghai",
    "iso:country":"CN",
    "name:zho_x_preferred":[
        "Dakengkou"
    ],
    "name:zho_x_variant":[
        "\u5927\u5751\u53e3"
    ],
    "wof:name":"Dakengkou",
    "wof:placetype":"locality"
},
  "geometry": {"coordinates":[112.82472,24.04444],"type":"Point"}
}