{
  "type": "Feature",
  "properties": {
    "gn:admin1_code":"32.0",
    "gn:asciiname":"Cizhuping",
    "gn:country_code":"CN",
    "gn:dem":1692,
    "gn:feature_class":"P",
    "gn:feature_code":"PPL",
    "gn:name":"Cizhuping",
    "gn:population":0,
    "gn:timezone":"Asia/Shanghai",
    "iso:country":"CN",
    "name:zho_x_preferred":[
        "\u523a\u7af9\u576a"
    ],
    "wof:name":"Cizhuping",
    "wof:placetype":"locality"
},
  "geometry": {"coordinates":[103.45699999999999,27.914],"type":"Point"}
}