{
  "type": "Feature",
  "properties": {
    "gn:admin1_code":"9.0",
    "gn:asciiname":"Qiandulou",
    "gn:country_code":"CN",
    "gn:dem":134,
    "gn:feature_class":"P",
    "gn:feature_code":"PPL",
    "gn:name":"Qiandulou",
    "gn:population":0,
    "gn:timezone":"Asia/Shanghai",
    "iso:country":"CN",
    "name:zho_x_preferred":[
        "\u524d\u675c\u697c"
    ],
    "wof:name":"Qiandulou",
    "wof:placetype":"locality"
},
  "geometry": {"coordinates":[112.99491999999999,32.62649],"type":"Point"}
}