{
  "type": "Feature",
  "properties": {
    "gn:admin1_code":"4.0",
    "gn:asciiname":"Sunjicun",
    "gn:country_code":"CN",
    "gn:dem":8,
    "gn:feature_class":"P",
    "gn:feature_code":"PPL",
    "gn:name":"Sunjicun",
    "gn:population":0,
    "gn:timezone":"Asia/Shanghai",
    "iso:country":"CN",
    "name:und_x_variant":[
        "Sunji"
    ],
    "name:zho_x_preferred":[
        "\u5b59\u96c6\u6751"
    ],
    "wof:name":"Sunjicun",
    "wof:placetype":"locality"
},
  "geometry": {"coordinates":[119.05907999999999,33.18732],"type":"Point"}
}