{
  "type": "Feature",
  "properties": {
    "gn:admin1_code":"30.0",
    "gn:asciiname":"Fuluzhou",
    "gn:country_code":"CN",
    "gn:dem":-1,
    "gn:feature_class":"P",
    "gn:feature_code":"PPL",
    "gn:name":"Fuluzhou",
    "gn:population":0,
    "gn:timezone":"Asia/Shanghai",
    "iso:country":"CN",
    "name:zho_x_preferred":[
        "\u798f\u7984\u6d32"
    ],
    "wof:name":"Fuluzhou",
    "wof:placetype":"locality"
},
  "geometry": {"coordinates":[113.59222,22.8861],"type":"Point"}
}