{
  "type": "Feature",
  "properties": {
    "gn:admin1_code":"32.0",
    "gn:asciiname":"Huishan",
    "gn:country_code":"CN",
    "gn:dem":407,
    "gn:feature_class":"P",
    "gn:feature_code":"PPL",
    "gn:name":"Huishan",
    "gn:population":0,
    "gn:timezone":"Asia/Shanghai",
    "iso:country":"CN",
    "name:zho_x_preferred":[
        "\u8f89\u5c71"
    ],
    "wof:name":"Huishan",
    "wof:placetype":"locality"
},
  "geometry": {"coordinates":[103.88094,29.40086],"type":"Point"}
}