{
  "type": "Feature",
  "properties": {
    "gn:admin1_code":"29.0",
    "gn:asciiname":"Nanben Xinzhai",
    "gn:country_code":"CN",
    "gn:dem":1773,
    "gn:feature_class":"P",
    "gn:feature_code":"PPL",
    "gn:name":"Nanben Xinzhai",
    "gn:population":0,
    "gn:timezone":"Asia/Shanghai",
    "iso:country":"CN",
    "name:zho_x_preferred":[
        "\u5357\u672c\u65b0\u5be8"
    ],
    "wof:name":"Nanben Xinzhai",
    "wof:placetype":"locality"
},
  "geometry": {"coordinates":[99.7218,22.8341],"type":"Point"}
}