{
  "type": "Feature",
  "properties": {
    "gn:admin1_code":"19.0",
    "gn:asciiname":"Lingdong Xiaowangjiatun",
    "gn:country_code":"CN",
    "gn:dem":23,
    "gn:feature_class":"P",
    "gn:feature_code":"PPL",
    "gn:name":"Lingdong Xiaowangjiatun",
    "gn:population":0,
    "gn:timezone":"Asia/Shanghai",
    "iso:country":"CN",
    "name:zho_x_preferred":[
        "\u5cad\u4e1c\u5c0f\u738b\u5bb6\u5c6f"
    ],
    "wof:name":"Lingdong Xiaowangjiatun",
    "wof:placetype":"locality"
},
  "geometry": {"coordinates":[122.09699999999999,39.2857],"type":"Point"}
}