{
  "type": "Feature",
  "properties": {
    "gn:admin1_code":"4.0",
    "gn:asciiname":"Zhoujiaqiao",
    "gn:country_code":"CN",
    "gn:dem":5,
    "gn:feature_class":"P",
    "gn:feature_code":"PPL",
    "gn:name":"Zhoujiaqiao",
    "gn:population":0,
    "gn:timezone":"Asia/Shanghai",
    "iso:country":"CN",
    "name:und_x_variant":[
        "\u5468\u5bb6\u6865"
    ],
    "name:zho_x_preferred":[
        "\u5468\u5bb6\u6865"
    ],
    "wof:name":"Zhoujiaqiao",
    "wof:placetype":"locality"
},
  "geometry": {"coordinates":[120.20358,32.25078],"type":"Point"}
}