{
  "type": "Feature",
  "properties": {
    "gn:admin1_code":"14.0",
    "gn:asciiname":"Genacun",
    "gn:country_code":"CN",
    "gn:dem":5113,
    "gn:feature_class":"P",
    "gn:feature_code":"PPL",
    "gn:name":"Genacun",
    "gn:population":0,
    "gn:timezone":"Asia/Urumqi",
    "iso:country":"CN",
    "name:zho_x_preferred":[
        "\u683c\u7eb3\u6751"
    ],
    "wof:name":"Genacun",
    "wof:placetype":"locality"
},
  "geometry": {"coordinates":[90.03189,31.28177],"type":"Point"}
}