{
  "type": "Feature",
  "properties": {
    "gn:admin1_code":"29.0",
    "gn:asciiname":"Ziwei",
    "gn:country_code":"CN",
    "gn:dem":2142,
    "gn:feature_class":"P",
    "gn:feature_code":"PPL",
    "gn:name":"Ziwei",
    "gn:population":0,
    "gn:timezone":"Asia/Shanghai",
    "iso:country":"CN",
    "name:zho_x_preferred":[
        "\u7d2b\u5fae"
    ],
    "wof:name":"Ziwei",
    "wof:placetype":"locality"
},
  "geometry": {"coordinates":[100.10599999999999,24.9081],"type":"Point"}
}