{
  "type": "Feature",
  "properties": {
    "gn:admin1_code":"10",
    "gn:asciiname":"Fanquan",
    "gn:country_code":"CN",
    "gn:dem":53,
    "gn:feature_class":"P",
    "gn:feature_code":"PPL",
    "gn:name":"Fanquan",
    "gn:population":0,
    "gn:timezone":"Asia/Shanghai",
    "iso:country":"CN",
    "name:zho_x_preferred":[
        "\u6a0a\u5708"
    ],
    "wof:name":"Fanquan",
    "wof:placetype":"locality"
},
  "geometry": {"coordinates":[114.98099999999999,36.2499],"type":"Point"}
}