{
  "type": "Feature",
  "properties": {
    "gn:admin1_code":"26.0",
    "gn:asciiname":"Xinzhuang",
    "gn:country_code":"CN",
    "gn:dem":1386,
    "gn:feature_class":"P",
    "gn:feature_code":"PPL",
    "gn:name":"Xinzhuang",
    "gn:population":0,
    "gn:timezone":"Asia/Shanghai",
    "iso:country":"CN",
    "name:und_x_variant":[
        "\u65b0\u5e84"
    ],
    "wof:name":"Xinzhuang",
    "wof:placetype":"locality"
},
  "geometry": {"coordinates":[107.66367,34.92703],"type":"Point"}
}