{
  "type": "Feature",
  "properties": {
    "gn:admin1_code":"20",
    "gn:asciiname":"Guluebulong",
    "gn:country_code":"CN",
    "gn:dem":1056,
    "gn:feature_class":"P",
    "gn:feature_code":"PPL",
    "gn:name":"Gul\u00fcebulong",
    "gn:population":0,
    "gn:timezone":"Asia/Shanghai",
    "iso:country":"CN",
    "name:und_x_variant":[
        "Shui-ch\u2019\u00fcan",
        "Gul\u00fcebulong"
    ],
    "wof:name":"Guluebulong",
    "wof:placetype":"locality"
},
  "geometry": {"coordinates":[108.80194,41.18389000000001],"type":"Point"}
}