{
  "type": "Feature",
  "properties": {
    "gn:admin1_code":"29.0",
    "gn:asciiname":"Yixilie",
    "gn:country_code":"CN",
    "gn:dem":2583,
    "gn:feature_class":"P",
    "gn:feature_code":"PPL",
    "gn:name":"Yixilie",
    "gn:population":0,
    "gn:timezone":"Asia/Shanghai",
    "iso:country":"CN",
    "name:zho_x_preferred":[
        "\u4ee5\u4e60\u70c8"
    ],
    "wof:name":"Yixilie",
    "wof:placetype":"locality"
},
  "geometry": {"coordinates":[99.33880000000001,26.8465],"type":"Point"}
}