{
  "type": "Feature",
  "properties": {
    "gn:admin1_code":"25.0",
    "gn:asciiname":"Wulong",
    "gn:country_code":"CN",
    "gn:dem":47,
    "gn:feature_class":"P",
    "gn:feature_code":"PPL",
    "gn:name":"Wulong",
    "gn:population":0,
    "gn:timezone":"Asia/Shanghai",
    "iso:country":"CN",
    "name:zho_x_preferred":[
        "\u4e94\u9f99"
    ],
    "wof:name":"Wulong",
    "wof:placetype":"locality"
},
  "geometry": {"coordinates":[120.73269000000001,36.88339000000001],"type":"Point"}
}