{
  "type": "Feature",
  "properties": {
    "gn:admin1_code":"10",
    "gn:asciiname":"Minghua",
    "gn:cc2":"CN",
    "gn:country_code":"CN",
    "gn:dem":30,
    "gn:feature_class":"P",
    "gn:feature_code":"PPL",
    "gn:name":"Minghua",
    "gn:population":0,
    "gn:timezone":"Asia/Shanghai",
    "iso:country":"CN",
    "name:deu_x_preferred":[
        "Minghua"
    ],
    "name:und_x_variant":[
        "Ming-hua-chen",
        "Minghua"
    ],
    "wof:name":"Minghua",
    "wof:placetype":"locality"
},
  "geometry": {"coordinates":[115.57056,37.3025],"type":"Point"}
}