{
  "type": "Feature",
  "properties": {
    "gn:admin1_code":"12.0",
    "gn:asciiname":"Taolinhe",
    "gn:country_code":"CN",
    "gn:dem":57,
    "gn:feature_class":"P",
    "gn:feature_code":"PPL",
    "gn:name":"Taolinhe",
    "gn:population":0,
    "gn:timezone":"Asia/Shanghai",
    "iso:country":"CN",
    "name:zho_x_preferred":[
        "\u6843\u6797\u6cb3"
    ],
    "wof:name":"Taolinhe",
    "wof:placetype":"locality"
},
  "geometry": {"coordinates":[115.09122000000001,31.16519000000001],"type":"Point"}
}