{
  "type": "Feature",
  "properties": {
    "gn:admin1_code":"16.0",
    "gn:asciiname":"Zhongliuquan",
    "gn:country_code":"CN",
    "gn:dem":199,
    "gn:feature_class":"P",
    "gn:feature_code":"PPL",
    "gn:name":"Zhongliuquan",
    "gn:population":0,
    "gn:timezone":"Asia/Shanghai",
    "iso:country":"CN",
    "name:zho_x_preferred":[
        "\u4e2d\u516d\u5168"
    ],
    "wof:name":"Zhongliuquan",
    "wof:placetype":"locality"
},
  "geometry": {"coordinates":[109.895,24.5931],"type":"Point"}
}