{
  "type": "Feature",
  "properties": {
    "gn:admin1_code":"8.0",
    "gn:asciiname":"Dawucun",
    "gn:country_code":"CN",
    "gn:dem":245,
    "gn:feature_class":"P",
    "gn:feature_code":"PPL",
    "gn:name":"Dawucun",
    "gn:population":0,
    "gn:timezone":"Asia/Shanghai",
    "iso:country":"CN",
    "name:zho_x_preferred":[
        "\u5927\u4e94\u6751"
    ],
    "wof:name":"Dawucun",
    "wof:placetype":"locality"
},
  "geometry": {"coordinates":[130.59034,45.7338],"type":"Point"}
}