{
  "type": "Feature",
  "properties": {
    "gn:admin1_code":"9.0",
    "gn:asciiname":"Kangjiazhuang",
    "gn:country_code":"CN",
    "gn:dem":949,
    "gn:feature_class":"P",
    "gn:feature_code":"PPL",
    "gn:name":"Kangjiazhuang",
    "gn:population":0,
    "gn:timezone":"Asia/Shanghai",
    "iso:country":"CN",
    "name:und_x_variant":[
        "\u5eb7\u5bb6\u5e84",
        "Kangjiazhuang"
    ],
    "wof:name":"Kangjiazhuang",
    "wof:placetype":"locality"
},
  "geometry": {"coordinates":[112.22257999999999,33.80789],"type":"Point"}
}