{
  "type": "Feature",
  "properties": {
    "gn:admin1_code":"15.0",
    "gn:asciiname":"Xibanshan",
    "gn:country_code":"CN",
    "gn:dem":1968,
    "gn:feature_class":"P",
    "gn:feature_code":"PPL",
    "gn:name":"Xibanshan",
    "gn:population":0,
    "gn:timezone":"Asia/Shanghai",
    "iso:country":"CN",
    "name:und_x_variant":[
        "\u897f\u534a\u5c71"
    ],
    "name:zho_x_preferred":[
        "\u897f\u534a\u5c71"
    ],
    "wof:name":"Xibanshan",
    "wof:placetype":"locality"
},
  "geometry": {"coordinates":[104.34797,33.81252],"type":"Point"}
}