{
  "type": "Feature",
  "properties": {
    "gn:admin1_code":"26",
    "gn:asciiname":"Chuanbei",
    "gn:country_code":"CN",
    "gn:dem":379,
    "gn:feature_class":"P",
    "gn:feature_code":"PPL",
    "gn:name":"Chuanbei",
    "gn:population":0,
    "gn:timezone":"Asia/Shanghai",
    "iso:country":"CN",
    "name:zho_x_preferred":[
        "\u5ddd\u5317"
    ],
    "wof:name":"Chuanbei",
    "wof:placetype":"locality"
},
  "geometry": {"coordinates":[109.20806,34.61619],"type":"Point"}
}