{
  "type": "Feature",
  "properties": {
    "gn:admin1_code":"3",
    "gn:asciiname":"Qianshan",
    "gn:country_code":"CN",
    "gn:dem":203,
    "gn:feature_class":"P",
    "gn:feature_code":"PPLA4",
    "gn:name":"Qianshan",
    "gn:population":0,
    "gn:timezone":"Asia/Shanghai",
    "iso:country":"CN",
    "name:ceb_x_preferred":[
        "Qianshan"
    ],
    "name:deu_x_preferred":[
        "Qianshan"
    ],
    "name:fra_x_preferred":[
        "Qianshan"
    ],
    "name:nor_x_preferred":[
        "Qianshan"
    ],
    "name:rus_x_preferred":[
        "\u0426\u044f\u043d\u044c\u0448\u0430\u043d\u044c"
    ],
    "name:swe_x_preferred":[
        "Qianshan"
    ],
    "name:und_x_variant":[
        "\u5343\u5584",
        "Qianshan Xiang",
        "\u5343\u5584\u4e61"
    ],
    "wof:name":"Qianshan",
    "wof:placetype":"locality"
},
  "geometry": {"coordinates":[116.46983,26.93118],"type":"Point"}
}