{
  "type": "Feature",
  "properties": {
    "gn:admin1_code":"29.0",
    "gn:asciiname":"Xiakaya",
    "gn:country_code":"CN",
    "gn:dem":1564,
    "gn:feature_class":"P",
    "gn:feature_code":"PPL",
    "gn:name":"Xiakaya",
    "gn:population":0,
    "gn:timezone":"Asia/Shanghai",
    "iso:country":"CN",
    "name:zho_x_preferred":[
        "\u4e0b\u5361\u7259"
    ],
    "wof:name":"Xiakaya",
    "wof:placetype":"locality"
},
  "geometry": {"coordinates":[97.8211,25.0621],"type":"Point"}
}