{
  "type": "Feature",
  "properties": {
    "gn:admin1_code":"29.0",
    "gn:asciiname":"Wangjiazhuang",
    "gn:cc2":"CN",
    "gn:country_code":"CN",
    "gn:dem":1987,
    "gn:feature_class":"P",
    "gn:feature_code":"PPL",
    "gn:name":"Wangjiazhuang",
    "gn:population":0,
    "gn:timezone":"Asia/Shanghai",
    "iso:country":"CN",
    "name:und_x_variant":[
        "Shang-hsia-wang-chia-chuang",
        "Wang-chia-chuang",
        "Wangjiazhuang"
    ],
    "wof:name":"Wangjiazhuang",
    "wof:placetype":"locality"
},
  "geometry": {"coordinates":[103.51667,25.48333],"type":"Point"}
}