{
  "type": "Feature",
  "properties": {
    "gn:admin1_code":"12.0",
    "gn:asciiname":"Shiliangzi",
    "gn:country_code":"CN",
    "gn:dem":397,
    "gn:feature_class":"P",
    "gn:feature_code":"PPL",
    "gn:name":"Shiliangzi",
    "gn:population":0,
    "gn:timezone":"Asia/Shanghai",
    "iso:country":"CN",
    "name:zho_x_preferred":[
        "Shiliangzi"
    ],
    "name:zho_x_variant":[
        "\u77f3\u6881\u5b50"
    ],
    "wof:name":"Shiliangzi",
    "wof:placetype":"locality"
},
  "geometry": {"coordinates":[109.20397,29.21281],"type":"Point"}
}