{
  "type": "Feature",
  "properties": {
    "gn:admin1_code":"8.0",
    "gn:asciiname":"Youlicun",
    "gn:country_code":"CN",
    "gn:dem":131,
    "gn:feature_class":"P",
    "gn:feature_code":"PPL",
    "gn:name":"Youlicun",
    "gn:population":0,
    "gn:timezone":"Asia/Shanghai",
    "iso:country":"CN",
    "name:zho_x_preferred":[
        "\u6709\u5229\u6751"
    ],
    "wof:name":"Youlicun",
    "wof:placetype":"locality"
},
  "geometry": {"coordinates":[124.7167,45.53105],"type":"Point"}
}