{
  "type": "Feature",
  "properties": {
    "gn:admin1_code":"11.0",
    "gn:asciiname":"Saguya",
    "gn:country_code":"CN",
    "gn:dem":885,
    "gn:feature_class":"P",
    "gn:feature_code":"PPL",
    "gn:name":"Saguya",
    "gn:population":0,
    "gn:timezone":"Asia/Shanghai",
    "iso:country":"CN",
    "name:zho_x_preferred":[
        "\u6492\u8c37\u57ad"
    ],
    "wof:name":"Saguya",
    "wof:placetype":"locality"
},
  "geometry": {"coordinates":[109.82962999999999,29.60929],"type":"Point"}
}