{
  "type": "Feature",
  "properties": {
    "gn:admin1_code":"10",
    "gn:asciiname":"Hanjia Wopu",
    "gn:country_code":"CN",
    "gn:dem":1219,
    "gn:feature_class":"P",
    "gn:feature_code":"PPL",
    "gn:name":"Hanjia Wopu",
    "gn:population":0,
    "gn:timezone":"Asia/Shanghai",
    "iso:country":"CN",
    "name:zho_x_preferred":[
        "\u97e9\u5bb6\u7a9d\u94fa"
    ],
    "wof:name":"Hanjia Wopu",
    "wof:placetype":"locality"
},
  "geometry": {"coordinates":[116.56018,41.58494],"type":"Point"}
}