{
  "type": "Feature",
  "properties": {
    "gn:admin1_code":"26",
    "gn:asciiname":"Liujiayuan",
    "gn:cc2":"CN",
    "gn:country_code":"CN",
    "gn:dem":846,
    "gn:feature_class":"P",
    "gn:feature_code":"PPL",
    "gn:name":"Liujiayuan",
    "gn:population":0,
    "gn:timezone":"Asia/Shanghai",
    "iso:country":"CN",
    "name:und_x_variant":[
        "Liu-chia-y\u00fcan",
        "Liujiayuan"
    ],
    "wof:name":"Liujiayuan",
    "wof:placetype":"locality"
},
  "geometry": {"coordinates":[110.53722,33.56667],"type":"Point"}
}