{
  "type": "Feature",
  "properties": {
    "gn:admin1_code":"19.0",
    "gn:asciiname":"Dananbei",
    "gn:country_code":"CN",
    "gn:dem":510,
    "gn:feature_class":"P",
    "gn:feature_code":"PPL",
    "gn:name":"Dananbei",
    "gn:population":0,
    "gn:timezone":"Asia/Shanghai",
    "iso:country":"CN",
    "name:und_x_variant":[
        "\u5927\u5357\u80cc"
    ],
    "name:zho_x_preferred":[
        "\u5927\u5357\u80cc"
    ],
    "wof:name":"Dananbei",
    "wof:placetype":"locality"
},
  "geometry": {"coordinates":[122.96044999999999,40.47457],"type":"Point"}
}