{
  "type": "Feature",
  "properties": {
    "gn:admin1_code":"33.0",
    "gn:asciiname":"Dangdangzhai",
    "gn:country_code":"CN",
    "gn:dem":271,
    "gn:feature_class":"P",
    "gn:feature_code":"PPL",
    "gn:name":"Dangdangzhai",
    "gn:population":0,
    "gn:timezone":"Asia/Shanghai",
    "iso:country":"CN",
    "name:zho_x_preferred":[
        "\u88c6\u88c6\u5be8"
    ],
    "wof:name":"Dangdangzhai",
    "wof:placetype":"locality"
},
  "geometry": {"coordinates":[107.98756000000002,30.67167],"type":"Point"}
}