{
  "type": "Feature",
  "properties": {
    "gn:admin1_code":"18.0",
    "gn:asciiname":"Tulizhai",
    "gn:country_code":"CN",
    "gn:dem":811,
    "gn:feature_class":"P",
    "gn:feature_code":"PPL",
    "gn:name":"Tulizhai",
    "gn:population":0,
    "gn:timezone":"Asia/Shanghai",
    "iso:country":"CN",
    "name:zho_x_preferred":[
        "\u5154\u7acb\u5be8"
    ],
    "wof:name":"Tulizhai",
    "wof:placetype":"locality"
},
  "geometry": {"coordinates":[107.92400000000001,26.8288],"type":"Point"}
}