{
  "type": "Feature",
  "properties": {
    "gn:admin1_code":"25.0",
    "gn:asciiname":"Zhanglincun",
    "gn:country_code":"CN",
    "gn:dem":113,
    "gn:feature_class":"P",
    "gn:feature_code":"PPL",
    "gn:name":"Zhanglincun",
    "gn:population":0,
    "gn:timezone":"Asia/Shanghai",
    "iso:country":"CN",
    "name:zho_x_preferred":[
        "\u4ec9\u6797\u6751"
    ],
    "wof:name":"Zhanglincun",
    "wof:placetype":"locality"
},
  "geometry": {"coordinates":[119.48627,35.93107],"type":"Point"}
}