{
  "type": "Feature",
  "properties": {
    "gn:admin1_code":"30.0",
    "gn:asciiname":"Yuankengcun",
    "gn:country_code":"CN",
    "gn:dem":398,
    "gn:feature_class":"P",
    "gn:feature_code":"PPL",
    "gn:name":"Yuankengcun",
    "gn:population":0,
    "gn:timezone":"Asia/Shanghai",
    "iso:country":"CN",
    "name:zho_x_preferred":[
        "\u6e90\u5751\u6751"
    ],
    "wof:name":"Yuankengcun",
    "wof:placetype":"locality"
},
  "geometry": {"coordinates":[116.51571,24.49229],"type":"Point"}
}