{
  "type": "Feature",
  "properties": {
    "gn:admin1_code":"1.0",
    "gn:asciiname":"Daixucun",
    "gn:country_code":"CN",
    "gn:dem":28,
    "gn:feature_class":"P",
    "gn:feature_code":"PPL",
    "gn:name":"Daixucun",
    "gn:population":0,
    "gn:timezone":"Asia/Shanghai",
    "iso:country":"CN",
    "name:zho_x_preferred":[
        "\u6234\u5729\u6751"
    ],
    "wof:name":"Daixucun",
    "wof:placetype":"locality"
},
  "geometry": {"coordinates":[116.258,33.01644],"type":"Point"}
}