{
  "type": "Feature",
  "properties": {
    "gn:admin1_code":"11.0",
    "gn:asciiname":"Yuzuogong",
    "gn:country_code":"CN",
    "gn:dem":89,
    "gn:feature_class":"P",
    "gn:feature_code":"PPL",
    "gn:name":"Yuzuogong",
    "gn:population":0,
    "gn:timezone":"Asia/Shanghai",
    "iso:country":"CN",
    "name:zho_x_preferred":[
        "\u96e8\u4f5c\u516c"
    ],
    "wof:name":"Yuzuogong",
    "wof:placetype":"locality"
},
  "geometry": {"coordinates":[112.24374,28.35103],"type":"Point"}
}