{
  "type": "Feature",
  "properties": {
    "gn:admin1_code":"2",
    "gn:asciiname":"Damingshan",
    "gn:country_code":"CN",
    "gn:dem":321,
    "gn:feature_class":"P",
    "gn:feature_code":"PPL",
    "gn:name":"Damingshan",
    "gn:population":0,
    "gn:timezone":"Asia/Shanghai",
    "iso:country":"CN",
    "name:und_x_variant":[
        "\u5927\u660e\u5c71"
    ],
    "wof:name":"Damingshan",
    "wof:placetype":"locality"
},
  "geometry": {"coordinates":[118.99629,30.07296],"type":"Point"}
}