{
  "type": "Feature",
  "properties": {
    "gn:admin1_code":"26.0",
    "gn:asciiname":"Tuqigou",
    "gn:country_code":"CN",
    "gn:dem":1403,
    "gn:feature_class":"P",
    "gn:feature_code":"PPL",
    "gn:name":"Tuqigou",
    "gn:population":0,
    "gn:timezone":"Asia/Shanghai",
    "iso:country":"CN",
    "name:zho_x_preferred":[
        "\u5c60\u542f\u6c9f"
    ],
    "wof:name":"Tuqigou",
    "wof:placetype":"locality"
},
  "geometry": {"coordinates":[107.48591999999999,32.52764000000001],"type":"Point"}
}