{
  "type": "Feature",
  "properties": {
    "gn:admin1_code":"15.0",
    "gn:asciiname":"Xiuhualou",
    "gn:country_code":"CN",
    "gn:dem":1338,
    "gn:feature_class":"P",
    "gn:feature_code":"PPL",
    "gn:name":"Xiuhualou",
    "gn:population":0,
    "gn:timezone":"Asia/Shanghai",
    "iso:country":"CN",
    "name:zho_x_preferred":[
        "\u7ee3\u82b1\u697c"
    ],
    "wof:name":"Xiuhualou",
    "wof:placetype":"locality"
},
  "geometry": {"coordinates":[108.43000000000001,35.6685],"type":"Point"}
}