{
  "type": "Feature",
  "properties": {
    "gn:admin1_code":"5.0",
    "gn:asciiname":"Tai'angouli",
    "gn:country_code":"CN",
    "gn:dem":561,
    "gn:feature_class":"P",
    "gn:feature_code":"PPL",
    "gn:name":"Tai\u2019angouli",
    "gn:population":0,
    "gn:timezone":"Asia/Shanghai",
    "iso:country":"CN",
    "name:und_x_variant":[
        "Tai\u2019angouli",
        "\u592a\u5b89\u6c9f\u91cc"
    ],
    "wof:name":"Tai'angouli",
    "wof:placetype":"locality"
},
  "geometry": {"coordinates":[125.72372,41.76779000000001],"type":"Point"}
}