{
  "type": "Feature",
  "properties": {
    "gn:admin1_code":"26.0",
    "gn:asciiname":"Fenbaoliang",
    "gn:country_code":"CN",
    "gn:dem":1044,
    "gn:feature_class":"P",
    "gn:feature_code":"PPL",
    "gn:name":"Fenbaoliang",
    "gn:population":0,
    "gn:timezone":"Asia/Shanghai",
    "iso:country":"CN",
    "name:und_x_variant":[
        "\u575f\u5305\u6881"
    ],
    "wof:name":"Fenbaoliang",
    "wof:placetype":"locality"
},
  "geometry": {"coordinates":[106.42034,33.12784],"type":"Point"}
}