{
  "type": "Feature",
  "properties": {
    "gn:admin1_code":"12.0",
    "gn:asciiname":"Yaowutai",
    "gn:country_code":"CN",
    "gn:dem":29,
    "gn:feature_class":"P",
    "gn:feature_code":"PPL",
    "gn:name":"Yaowutai",
    "gn:population":0,
    "gn:timezone":"Asia/Shanghai",
    "iso:country":"CN",
    "name:und_x_variant":[
        "Mewutai",
        "Yaowutai"
    ],
    "name:zho_x_preferred":[
        "\u4e48\u5c4b\u53f0"
    ],
    "wof:name":"Yaowutai",
    "wof:placetype":"locality"
},
  "geometry": {"coordinates":[113.09591,29.93352],"type":"Point"}
}