{
  "type": "Feature",
  "properties": {
    "gn:admin1_code":"3.0",
    "gn:asciiname":"Zhuangqian",
    "gn:country_code":"CN",
    "gn:dem":122,
    "gn:feature_class":"P",
    "gn:feature_code":"PPL",
    "gn:name":"Zhuangqian",
    "gn:population":0,
    "gn:timezone":"Asia/Shanghai",
    "iso:country":"CN",
    "name:und_x_variant":[
        "\u5e84\u524d"
    ],
    "wof:name":"Zhuangqian",
    "wof:placetype":"locality"
},
  "geometry": {"coordinates":[117.14695,29.17355],"type":"Point"}
}