{
  "type": "Feature",
  "properties": {
    "gn:admin1_code":"02",
    "gn:asciiname":"Tang'aozhu",
    "gn:country_code":"CN",
    "gn:dem":8,
    "gn:feature_class":"P",
    "gn:feature_code":"PPL",
    "gn:name":"Tang\u2019aozhu",
    "gn:population":0,
    "gn:timezone":"Asia/Shanghai",
    "iso:country":"CN",
    "name:zho_x_preferred":[
        "T\u2019ang-ao-y\u00fc"
    ],
    "name:zho_x_variant":[
        "Tang\u2019aozhu",
        "\u6c64\u5c99\u6731"
    ],
    "wof:name":"Tang'aozhu",
    "wof:placetype":"locality"
},
  "geometry": {"coordinates":[120.94248,28.04918],"type":"Point"}
}