{
  "type": "Feature",
  "properties": {
    "gn:admin1_code":"25",
    "gn:asciiname":"Panjiaji",
    "gn:country_code":"CN",
    "gn:dem":94,
    "gn:feature_class":"P",
    "gn:feature_code":"PPL",
    "gn:name":"Panjiaji",
    "gn:population":0,
    "gn:timezone":"Asia/Shanghai",
    "iso:country":"CN",
    "name:zho_x_preferred":[
        "\u6f58\u5bb6\u96c6"
    ],
    "wof:name":"Panjiaji",
    "wof:placetype":"locality"
},
  "geometry": {"coordinates":[120.47799999999999,37.4211],"type":"Point"}
}