{
  "type": "Feature",
  "properties": {
    "gn:admin1_code":"02",
    "gn:asciiname":"Zhuqiaotou",
    "gn:country_code":"CN",
    "gn:dem":4,
    "gn:feature_class":"P",
    "gn:feature_code":"PPL",
    "gn:name":"Zhuqiaotou",
    "gn:population":0,
    "gn:timezone":"Asia/Shanghai",
    "iso:country":"CN",
    "name:und_x_variant":[
        "\u7af9\u6865\u5934"
    ],
    "wof:name":"Zhuqiaotou",
    "wof:placetype":"locality"
},
  "geometry": {"coordinates":[121.06179,30.66738],"type":"Point"}
}