{
  "type": "Feature",
  "properties": {
    "gn:admin1_code":"04",
    "gn:asciiname":"Mayidian",
    "gn:cc2":"CN",
    "gn:country_code":"CN",
    "gn:dem":2,
    "gn:feature_class":"P",
    "gn:feature_code":"PPL",
    "gn:name":"Mayidian",
    "gn:population":0,
    "gn:timezone":"Asia/Shanghai",
    "iso:country":"CN",
    "name:und_x_variant":[
        "Ma-i-tien",
        "Ma-i-tien-chen",
        "Mayidian"
    ],
    "wof:name":"Mayidian",
    "wof:placetype":"locality"
},
  "geometry": {"coordinates":[119.26667,33.45],"type":"Point"}
}