{
  "type": "Feature",
  "properties": {
    "gn:admin1_code":"18",
    "gn:asciiname":"Zhaoshouya",
    "gn:country_code":"CN",
    "gn:dem":773,
    "gn:feature_class":"P",
    "gn:feature_code":"PPL",
    "gn:name":"Zhaoshouya",
    "gn:population":0,
    "gn:timezone":"Asia/Shanghai",
    "iso:country":"CN",
    "name:zho_x_preferred":[
        "\u62db\u624b\u57ad"
    ],
    "wof:name":"Zhaoshouya",
    "wof:placetype":"locality"
},
  "geometry": {"coordinates":[107.404,28.0865],"type":"Point"}
}