{
  "type": "Feature",
  "properties": {
    "gn:admin1_code":"30",
    "gn:asciiname":"Zhujie",
    "gn:country_code":"CN",
    "gn:dem":62,
    "gn:feature_class":"P",
    "gn:feature_code":"PPL",
    "gn:name":"Zhujie",
    "gn:population":0,
    "gn:timezone":"Asia/Urumqi",
    "iso:country":"CN",
    "name:zho_x_preferred":[
        "\u7af9\u754c"
    ],
    "wof:name":"Zhujie",
    "wof:placetype":"locality"
},
  "geometry": {"coordinates":[110.44307999999999,21.64829],"type":"Point"}
}