{
  "type": "Feature",
  "properties": {
    "gn:admin1_code":"16",
    "gn:asciiname":"Naju",
    "gn:country_code":"CN",
    "gn:dem":52,
    "gn:feature_class":"P",
    "gn:feature_code":"PPL",
    "gn:name":"Naju",
    "gn:population":0,
    "gn:timezone":"Asia/Shanghai",
    "iso:country":"CN",
    "name:ara_x_preferred":[
        "\u0646\u0627\u062c\u0648"
    ],
    "name:ceb_x_preferred":[
        "Naju"
    ],
    "name:ces_x_preferred":[
        "Nad\u017eu"
    ],
    "name:deu_x_preferred":[
        "Naju"
    ],
    "name:epo_x_preferred":[
        "Na\u011du"
    ],
    "name:fra_x_preferred":[
        "Naju"
    ],
    "name:ita_x_preferred":[
        "Naju"
    ],
    "name:jpn_x_preferred":[
        "\u7f85\u5dde\u5e02"
    ],
    "name:kor_x_preferred":[
        "\ub098\uc8fc\uc2dc"
    ],
    "name:lmo_x_preferred":[
        "Naju"
    ],
    "name:mon_x_preferred":[
        "\u041d\u0430\u0436\u04af"
    ],
    "name:nld_x_preferred":[
        "Naju"
    ],
    "name:nor_x_preferred":[
        "Naju"
    ],
    "name:pol_x_preferred":[
        "Naju"
    ],
    "name:por_x_preferred":[
        "Naju"
    ],
    "name:rus_x_preferred":[
        "\u041d\u0430\u0434\u0436\u0443"
    ],
    "name:spa_x_preferred":[
        "Naju"
    ],
    "name:swe_x_preferred":[
        "Naju"
    ],
    "name:tgl_x_preferred":[
        "Naju"
    ],
    "name:tur_x_preferred":[
        "Naju"
    ],
    "name:urd_x_preferred":[
        "\u0646\u0627\u062c\u0648"
    ],
    "name:vie_x_preferred":[
        "Naju"
    ],
    "name:war_x_preferred":[
        "Naju"
    ],
    "name:zho_x_preferred":[
        "\u90a3\u849f"
    ],
    "name:zho_x_variant":[
        "\u7f85\u5dde\u5e02"
    ],
    "wof:name":"Naju",
    "wof:placetype":"locality"
},
  "geometry": {"coordinates":[108.877,22.0692],"type":"Point"}
}