{
  "type": "Feature",
  "properties": {
    "gn:admin1_code":"1.0",
    "gn:asciiname":"Gediancun",
    "gn:country_code":"CN",
    "gn:dem":27,
    "gn:feature_class":"P",
    "gn:feature_code":"PPL",
    "gn:name":"Gediancun",
    "gn:population":0,
    "gn:timezone":"Asia/Shanghai",
    "iso:country":"CN",
    "name:und_x_variant":[
        "Gedian"
    ],
    "name:zho_x_preferred":[
        "\u845b\u5e97\u6751"
    ],
    "wof:name":"Gediancun",
    "wof:placetype":"locality"
},
  "geometry": {"coordinates":[117.30526999999999,33.5767],"type":"Point"}
}