{
  "type": "Feature",
  "properties": {
    "gn:admin1_code":"24.0",
    "gn:asciiname":"Anzheng",
    "gn:country_code":"CN",
    "gn:dem":1095,
    "gn:feature_class":"P",
    "gn:feature_code":"PPL",
    "gn:name":"Anzheng",
    "gn:population":0,
    "gn:timezone":"Asia/Shanghai",
    "iso:country":"CN",
    "name:zho_x_preferred":[
        "\u8c19\u6b63"
    ],
    "wof:name":"Anzheng",
    "wof:placetype":"locality"
},
  "geometry": {"coordinates":[111.13778000000001,36.6335],"type":"Point"}
}