{
  "type": "Feature",
  "properties": {
    "gn:admin1_code":"10",
    "gn:asciiname":"Tianqiao Muchang",
    "gn:country_code":"CN",
    "gn:dem":1480,
    "gn:feature_class":"P",
    "gn:feature_code":"PPLF",
    "gn:name":"Tianqiao Muchang",
    "gn:population":0,
    "gn:timezone":"Asia/Shanghai",
    "iso:country":"CN",
    "wof:name":"Tianqiao Muchang",
    "wof:placetype":"locality"
},
  "geometry": {"coordinates":[117.28082999999999,42.16389],"type":"Point"}
}