{
  "type": "Feature",
  "properties": {
    "gn:admin1_code":"33.0",
    "gn:asciiname":"Chuanzhumiao",
    "gn:country_code":"CN",
    "gn:dem":292,
    "gn:feature_class":"P",
    "gn:feature_code":"PPL",
    "gn:name":"Chuanzhumiao",
    "gn:population":0,
    "gn:timezone":"Asia/Shanghai",
    "iso:country":"CN",
    "name:zho_x_preferred":[
        "\u5ddd\u4e3b\u5e99"
    ],
    "wof:name":"Chuanzhumiao",
    "wof:placetype":"locality"
},
  "geometry": {"coordinates":[106.49559000000001,30.09399],"type":"Point"}
}