{
  "type": "Feature",
  "properties": {
    "gn:admin1_code":"19.0",
    "gn:asciiname":"Yangmenggoucun",
    "gn:country_code":"CN",
    "gn:dem":99,
    "gn:feature_class":"P",
    "gn:feature_code":"PPL",
    "gn:name":"Yangmenggoucun",
    "gn:population":0,
    "gn:timezone":"Asia/Shanghai",
    "iso:country":"CN",
    "name:zho_x_preferred":[
        "\u6768\u5b5f\u6c9f\u6751"
    ],
    "wof:name":"Yangmenggoucun",
    "wof:placetype":"locality"
},
  "geometry": {"coordinates":[121.06999999999999,41.6059],"type":"Point"}
}