{
  "type": "Feature",
  "properties": {
    "gn:admin1_code":"19.0",
    "gn:asciiname":"Sandaoshihu",
    "gn:country_code":"CN",
    "gn:dem":191,
    "gn:feature_class":"P",
    "gn:feature_code":"PPL",
    "gn:name":"Sandaoshihu",
    "gn:population":0,
    "gn:timezone":"Asia/Shanghai",
    "iso:country":"CN",
    "name:zho_x_preferred":[
        "\u4e09\u9053\u77f3\u80e1"
    ],
    "wof:name":"Sandaoshihu",
    "wof:placetype":"locality"
},
  "geometry": {"coordinates":[121.636,41.5148],"type":"Point"}
}