{
  "type": "Feature",
  "properties": {
    "gn:admin1_code":"26",
    "gn:asciiname":"Beitun",
    "gn:cc2":"CN",
    "gn:country_code":"CN",
    "gn:dem":458,
    "gn:feature_class":"P",
    "gn:feature_code":"PPL",
    "gn:name":"Beitun",
    "gn:population":0,
    "gn:timezone":"Asia/Shanghai",
    "iso:country":"CN",
    "name:deu_x_preferred":[
        "Beitun"
    ],
    "name:und_x_variant":[
        "Pei-t\u2019un-chen",
        "Pei-t\u2019un"
    ],
    "name:zho_x_preferred":[
        "\u5317\u5c6f"
    ],
    "wof:name":"Beitun",
    "wof:placetype":"locality"
},
  "geometry": {"coordinates":[108.60361,34.59861],"type":"Point"}
}