{
  "type": "Feature",
  "properties": {
    "gn:admin1_code":"26.0",
    "gn:asciiname":"Linjiaya",
    "gn:country_code":"CN",
    "gn:dem":660,
    "gn:feature_class":"P",
    "gn:feature_code":"PPL",
    "gn:name":"Linjiaya",
    "gn:population":0,
    "gn:timezone":"Asia/Shanghai",
    "iso:country":"CN",
    "name:zho_x_preferred":[
        "\u853a\u5bb6\u5d16"
    ],
    "wof:name":"Linjiaya",
    "wof:placetype":"locality"
},
  "geometry": {"coordinates":[110.15447,33.32343],"type":"Point"}
}