{
  "type": "Feature",
  "properties": {
    "gn:admin1_code":"8.0",
    "gn:asciiname":"Erzhan",
    "gn:country_code":"CN",
    "gn:dem":236,
    "gn:feature_class":"P",
    "gn:feature_code":"PPL",
    "gn:name":"Erzhan",
    "gn:population":0,
    "gn:timezone":"Asia/Shanghai",
    "iso:country":"CN",
    "name:zho_x_preferred":[
        "\u4e8c\u7ad9"
    ],
    "wof:name":"Erzhan",
    "wof:placetype":"locality"
},
  "geometry": {"coordinates":[129.23861000000002,47.55963],"type":"Point"}
}