{
  "type": "Feature",
  "properties": {
    "gn:admin1_code":"3.0",
    "gn:asciiname":"Zoujialing",
    "gn:country_code":"CN",
    "gn:dem":21,
    "gn:feature_class":"P",
    "gn:feature_code":"PPL",
    "gn:name":"Zoujialing",
    "gn:population":0,
    "gn:timezone":"Asia/Shanghai",
    "iso:country":"CN",
    "name:und_x_variant":[
        "\u90b9\u5bb6\u5cad"
    ],
    "wof:name":"Zoujialing",
    "wof:placetype":"locality"
},
  "geometry": {"coordinates":[116.63244,29.39042],"type":"Point"}
}