{
  "type": "Feature",
  "properties": {
    "gn:admin1_code":"26.0",
    "gn:asciiname":"Baiheping",
    "gn:country_code":"CN",
    "gn:dem":1270,
    "gn:feature_class":"P",
    "gn:feature_code":"PPL",
    "gn:name":"Baiheping",
    "gn:population":0,
    "gn:timezone":"Asia/Shanghai",
    "iso:country":"CN",
    "name:zho_x_preferred":[
        "\u767d\u9e64\u576a"
    ],
    "wof:name":"Baiheping",
    "wof:placetype":"locality"
},
  "geometry": {"coordinates":[106.80942,34.70178],"type":"Point"}
}