{
  "type": "Feature",
  "properties": {
    "gn:admin1_code":"03",
    "gn:asciiname":"Jiading",
    "gn:country_code":"CN",
    "gn:dem":151,
    "gn:feature_class":"P",
    "gn:feature_code":"PPLA3",
    "gn:name":"Jiading",
    "gn:population":0,
    "gn:timezone":"Asia/Shanghai",
    "iso:country":"CN",
    "name:und_x_variant":[
        "Hsin-feng",
        "Sinfeng",
        "Hsin-feng-hsien",
        "Xinfeng",
        "Sinfeng-hsien",
        "Jiading",
        "Xinfeng Xian"
    ],
    "name:zho_x_preferred":[
        "\u5609\u5b9a"
    ],
    "name:zho_x_variant":[
        "\u4fe1\u4e30\u53bf"
    ],
    "wof:name":"Jiading",
    "wof:placetype":"locality"
},
  "geometry": {"coordinates":[114.92804,25.4295],"type":"Point"}
}