{
  "type": "Feature",
  "properties": {
    "gn:admin1_code":"9.0",
    "gn:asciiname":"Hengdipu",
    "gn:country_code":"CN",
    "gn:dem":76,
    "gn:feature_class":"P",
    "gn:feature_code":"PPL",
    "gn:name":"Hengdipu",
    "gn:population":0,
    "gn:timezone":"Asia/Shanghai",
    "iso:country":"CN",
    "name:zho_x_preferred":[
        "\u6a2a\u5824\u94fa"
    ],
    "wof:name":"Hengdipu",
    "wof:placetype":"locality"
},
  "geometry": {"coordinates":[114.23187,34.78515],"type":"Point"}
}