{
  "type": "Feature",
  "properties": {
    "gn:admin1_code":"30",
    "gn:asciiname":"Gaotianwei",
    "gn:country_code":"CN",
    "gn:dem":117,
    "gn:feature_class":"P",
    "gn:feature_code":"PPL",
    "gn:name":"Gaotianwei",
    "gn:population":0,
    "gn:timezone":"Asia/Urumqi",
    "iso:country":"CN",
    "name:zho_x_preferred":[
        "\u9ad8\u7530\u5c3e"
    ],
    "wof:name":"Gaotianwei",
    "wof:placetype":"locality"
},
  "geometry": {"coordinates":[110.2564,20.43555],"type":"Point"}
}