{
  "type": "Feature",
  "properties": {
    "gn:admin1_code":"29",
    "gn:asciiname":"Hantun Shangying",
    "gn:country_code":"CN",
    "gn:dem":1399,
    "gn:feature_class":"P",
    "gn:feature_code":"PPL",
    "gn:name":"Hantun Shangying",
    "gn:population":0,
    "gn:timezone":"Asia/Shanghai",
    "iso:country":"CN",
    "name:zho_x_preferred":[
        "\u6c49\u5c6f\u4e0a\u8425"
    ],
    "wof:name":"Hantun Shangying",
    "wof:placetype":"locality"
},
  "geometry": {"coordinates":[102.685,24.0204],"type":"Point"}
}