{
  "type": "Feature",
  "properties": {
    "gn:admin1_code":"13",
    "gn:asciiname":"Xinjingzi",
    "gn:country_code":"CN",
    "gn:dem":1255,
    "gn:feature_class":"P",
    "gn:feature_code":"PPL",
    "gn:name":"Xinjingzi",
    "gn:population":0,
    "gn:timezone":"Asia/Urumqi",
    "iso:country":"CN",
    "name:und_x_variant":[
        "\u65b0\u4e95\u5b50"
    ],
    "wof:name":"Xinjingzi",
    "wof:placetype":"locality"
},
  "geometry": {"coordinates":[87.55530999999998,42.18827],"type":"Point"}
}