{
  "type": "Feature",
  "properties": {
    "gn:admin1_code":"32.0",
    "gn:asciiname":"Linggang",
    "gn:country_code":"CN",
    "gn:dem":359,
    "gn:feature_class":"P",
    "gn:feature_code":"PPL",
    "gn:name":"Linggang",
    "gn:population":0,
    "gn:timezone":"Asia/Shanghai",
    "iso:country":"CN",
    "name:zho_x_preferred":[
        "\u9675\u5c97"
    ],
    "wof:name":"Linggang",
    "wof:placetype":"locality"
},
  "geometry": {"coordinates":[105.53100000000001,28.9476],"type":"Point"}
}