{
  "type": "Feature",
  "properties": {
    "gn:admin1_code":"24.0",
    "gn:asciiname":"Xiaomaying",
    "gn:country_code":"CN",
    "gn:dem":1443,
    "gn:feature_class":"P",
    "gn:feature_code":"PPL",
    "gn:name":"Xiaomaying",
    "gn:population":0,
    "gn:timezone":"Asia/Shanghai",
    "iso:country":"CN",
    "name:zho_x_preferred":[
        "\u5c0f\u9a6c\u8425"
    ],
    "wof:name":"Xiaomaying",
    "wof:placetype":"locality"
},
  "geometry": {"coordinates":[111.693,39.0985],"type":"Point"}
}