{
  "type": "Feature",
  "properties": {
    "gn:admin1_code":"29.0",
    "gn:asciiname":"Gannimi",
    "gn:country_code":"CN",
    "gn:dem":3123,
    "gn:feature_class":"P",
    "gn:feature_code":"PPL",
    "gn:name":"Gannimi",
    "gn:population":0,
    "gn:timezone":"Asia/Shanghai",
    "iso:country":"CN",
    "name:zho_x_preferred":[
        "\u5e72\u4f60\u7c73"
    ],
    "wof:name":"Gannimi",
    "wof:placetype":"locality"
},
  "geometry": {"coordinates":[100.652,27.6707],"type":"Point"}
}