{
  "type": "Feature",
  "properties": {
    "gn:admin1_code":"26.0",
    "gn:asciiname":"Bianshang",
    "gn:country_code":"CN",
    "gn:dem":1235,
    "gn:feature_class":"P",
    "gn:feature_code":"PPL",
    "gn:name":"Bianshang",
    "gn:population":0,
    "gn:timezone":"Asia/Shanghai",
    "iso:country":"CN",
    "name:zho_x_preferred":[
        "\u782d\u4e0a"
    ],
    "wof:name":"Bianshang",
    "wof:placetype":"locality"
},
  "geometry": {"coordinates":[108.76656,35.8644],"type":"Point"}
}