{
  "type": "Feature",
  "properties": {
    "gn:admin1_code":"26.0",
    "gn:asciiname":"Yangjia Pingcun",
    "gn:country_code":"CN",
    "gn:dem":853,
    "gn:feature_class":"P",
    "gn:feature_code":"PPL",
    "gn:name":"Yangjia Pingcun",
    "gn:population":0,
    "gn:timezone":"Asia/Shanghai",
    "iso:country":"CN",
    "name:zho_x_preferred":[
        "\u6768\u5bb6\u576a\u6751"
    ],
    "wof:name":"Yangjia Pingcun",
    "wof:placetype":"locality"
},
  "geometry": {"coordinates":[110.687,38.6347],"type":"Point"}
}