{
  "type": "Feature",
  "properties": {
    "gn:admin1_code":"23",
    "gn:asciiname":"Chou-chia-chai",
    "gn:country_code":"CN",
    "gn:dem":4,
    "gn:feature_class":"P",
    "gn:feature_code":"PPL",
    "gn:name":"Chou-chia-chai",
    "gn:population":0,
    "gn:timezone":"Asia/Shanghai",
    "iso:country":"CN",
    "wof:name":"Chou-chia-chai",
    "wof:placetype":"locality"
},
  "geometry": {"coordinates":[121.65416999999999,30.89778],"type":"Point"}
}