{
  "type": "Feature",
  "properties": {
    "gn:admin1_code":"11.0",
    "gn:asciiname":"Feng'ao",
    "gn:country_code":"CN",
    "gn:dem":117,
    "gn:feature_class":"P",
    "gn:feature_code":"PPL",
    "gn:name":"Feng\u2019ao",
    "gn:population":0,
    "gn:timezone":"Asia/Shanghai",
    "iso:country":"CN",
    "name:und_x_variant":[
        "Feng\u2019ao"
    ],
    "name:zho_x_preferred":[
        "\u67ab\u5773"
    ],
    "wof:name":"Feng'ao",
    "wof:placetype":"locality"
},
  "geometry": {"coordinates":[112.35457,27.18212],"type":"Point"}
}