{
  "type": "Feature",
  "properties": {
    "gn:admin1_code":"11.0",
    "gn:asciiname":"Zhu'erlun",
    "gn:country_code":"CN",
    "gn:dem":402,
    "gn:feature_class":"P",
    "gn:feature_code":"PPL",
    "gn:name":"Zhu\u2019erlun",
    "gn:population":0,
    "gn:timezone":"Asia/Shanghai",
    "iso:country":"CN",
    "name:und_x_variant":[
        "Zhu\u2019erlun"
    ],
    "name:zho_x_preferred":[
        "\u7af9\u8033\u4ed1"
    ],
    "wof:name":"Zhu'erlun",
    "wof:placetype":"locality"
},
  "geometry": {"coordinates":[111.38854000000001,28.50318],"type":"Point"}
}