{
  "type": "Feature",
  "properties": {
    "gn:admin1_code":"26.0",
    "gn:asciiname":"Xiepocun",
    "gn:country_code":"CN",
    "gn:dem":469,
    "gn:feature_class":"P",
    "gn:feature_code":"PPL",
    "gn:name":"Xiepocun",
    "gn:population":0,
    "gn:timezone":"Asia/Shanghai",
    "iso:country":"CN",
    "name:zho_x_preferred":[
        "\u659c\u5761\u6751"
    ],
    "wof:name":"Xiepocun",
    "wof:placetype":"locality"
},
  "geometry": {"coordinates":[108.00575000000001,34.27755],"type":"Point"}
}