{
  "type": "Feature",
  "properties": {
    "gn:admin1_code":"8.0",
    "gn:asciiname":"Anyangtun",
    "gn:country_code":"CN",
    "gn:dem":72,
    "gn:feature_class":"P",
    "gn:feature_code":"PPL",
    "gn:name":"Anyangtun",
    "gn:population":0,
    "gn:timezone":"Asia/Shanghai",
    "iso:country":"CN",
    "name:zho_x_preferred":[
        "\u5b89\u9633\u5c6f"
    ],
    "wof:name":"Anyangtun",
    "wof:placetype":"locality"
},
  "geometry": {"coordinates":[133.11377999999999,46.16895],"type":"Point"}
}