{
  "type": "Feature",
  "properties": {
    "gn:admin1_code":"33.0",
    "gn:asciiname":"Fuhong",
    "gn:country_code":"CN",
    "gn:dem":163,
    "gn:feature_class":"P",
    "gn:feature_code":"PPL",
    "gn:name":"Fuhong",
    "gn:population":0,
    "gn:timezone":"Asia/Shanghai",
    "iso:country":"CN",
    "name:zho_x_preferred":[
        "\u590d\u6d2a"
    ],
    "wof:name":"Fuhong",
    "wof:placetype":"locality"
},
  "geometry": {"coordinates":[108.4736,31.19568],"type":"Point"}
}