{
  "type": "Feature",
  "properties": {
    "gn:admin1_code":"30",
    "gn:asciiname":"Wanxi",
    "gn:country_code":"CN",
    "gn:dem":151,
    "gn:feature_class":"P",
    "gn:feature_code":"PPL",
    "gn:name":"Wanxi",
    "gn:population":0,
    "gn:timezone":"Asia/Shanghai",
    "iso:country":"CN",
    "name:zho_x_preferred":[
        "\u6e7e\u6eaa"
    ],
    "wof:name":"Wanxi",
    "wof:placetype":"locality"
},
  "geometry": {"coordinates":[116.41415000000001,24.71863],"type":"Point"}
}