{
  "type": "Feature",
  "properties": {
    "gn:admin1_code":"8.0",
    "gn:asciiname":"Minzhutun",
    "gn:country_code":"CN",
    "gn:dem":189,
    "gn:feature_class":"P",
    "gn:feature_code":"PPL",
    "gn:name":"Minzhutun",
    "gn:population":0,
    "gn:timezone":"Asia/Shanghai",
    "iso:country":"CN",
    "name:zho_x_preferred":[
        "\u6c11\u4e3b\u5c6f"
    ],
    "wof:name":"Minzhutun",
    "wof:placetype":"locality"
},
  "geometry": {"coordinates":[128.40239,45.76519],"type":"Point"}
}