{
  "type": "Feature",
  "properties": {
    "gn:admin1_code":"15.0",
    "gn:asciiname":"Dawan",
    "gn:country_code":"CN",
    "gn:dem":2662,
    "gn:feature_class":"P",
    "gn:feature_code":"PPL",
    "gn:name":"Dawan",
    "gn:population":0,
    "gn:timezone":"Asia/Shanghai",
    "iso:country":"CN",
    "name:ceb_x_preferred":[
        "Dawan"
    ],
    "name:deu_x_preferred":[
        "Dawan"
    ],
    "name:ind_x_preferred":[
        "Dawan"
    ],
    "name:swe_x_preferred":[
        "Dawan"
    ],
    "name:zho_x_preferred":[
        "\u5927\u6e7e"
    ],
    "wof:name":"Dawan",
    "wof:placetype":"locality"
},
  "geometry": {"coordinates":[102.839,36.7952],"type":"Point"}
}