{
  "type": "Feature",
  "properties": {
    "gn:admin1_code":"9.0",
    "gn:asciiname":"Shangzhuang",
    "gn:country_code":"CN",
    "gn:dem":1124,
    "gn:feature_class":"P",
    "gn:feature_code":"PPL",
    "gn:name":"Shangzhuang",
    "gn:population":0,
    "gn:timezone":"Asia/Shanghai",
    "iso:country":"CN",
    "name:zho_x_preferred":[
        "\u4e0a\u5e84"
    ],
    "wof:name":"Shangzhuang",
    "wof:placetype":"locality"
},
  "geometry": {"coordinates":[112.21444,33.83704],"type":"Point"}
}