{
  "type": "Feature",
  "properties": {
    "gn:admin1_code":"16.0",
    "gn:asciiname":"Shanglengdong",
    "gn:country_code":"CN",
    "gn:dem":247,
    "gn:feature_class":"P",
    "gn:feature_code":"PPL",
    "gn:name":"Shanglengdong",
    "gn:population":0,
    "gn:timezone":"Asia/Shanghai",
    "iso:country":"CN",
    "name:zho_x_preferred":[
        "\u4e0a\u51b7\u5cd2"
    ],
    "wof:name":"Shanglengdong",
    "wof:placetype":"locality"
},
  "geometry": {"coordinates":[108.169,24.64],"type":"Point"}
}