{
  "type": "Feature",
  "properties": {
    "gn:admin1_code":"15.0",
    "gn:asciiname":"Xiehao",
    "gn:country_code":"CN",
    "gn:dem":2267,
    "gn:feature_class":"P",
    "gn:feature_code":"PPL",
    "gn:name":"Xiehao",
    "gn:population":0,
    "gn:timezone":"Asia/Shanghai",
    "iso:country":"CN",
    "name:zho_x_preferred":[
        "\u90aa\u53f7"
    ],
    "wof:name":"Xiehao",
    "wof:placetype":"locality"
},
  "geometry": {"coordinates":[102.497,37.7066],"type":"Point"}
}