{
  "type": "Feature",
  "properties": {
    "gn:admin1_code":"24.0",
    "gn:asciiname":"Liujinggou",
    "gn:country_code":"CN",
    "gn:dem":1592,
    "gn:feature_class":"P",
    "gn:feature_code":"PPL",
    "gn:name":"Liujinggou",
    "gn:population":0,
    "gn:timezone":"Asia/Shanghai",
    "iso:country":"CN",
    "name:zho_x_preferred":[
        "\u5218\u4e95\u6c9f"
    ],
    "wof:name":"Liujinggou",
    "wof:placetype":"locality"
},
  "geometry": {"coordinates":[112.14011000000001,39.67591],"type":"Point"}
}