{
  "type": "Feature",
  "properties": {
    "gn:admin1_code":"10",
    "gn:asciiname":"Wangjia Xigou",
    "gn:country_code":"CN",
    "gn:dem":676,
    "gn:feature_class":"P",
    "gn:feature_code":"PPL",
    "gn:name":"Wangjia Xigou",
    "gn:population":0,
    "gn:timezone":"Asia/Shanghai",
    "iso:country":"CN",
    "name:zho_x_preferred":[
        "\u738b\u5bb6\u897f\u6c9f"
    ],
    "wof:name":"Wangjia Xigou",
    "wof:placetype":"locality"
},
  "geometry": {"coordinates":[117.74254000000001,40.68681],"type":"Point"}
}