{
  "type": "Feature",
  "properties": {
    "gn:admin1_code":"11.0",
    "gn:asciiname":"Xinhui",
    "gn:country_code":"CN",
    "gn:dem":667,
    "gn:feature_class":"P",
    "gn:feature_code":"PPL",
    "gn:name":"Xinhui",
    "gn:population":0,
    "gn:timezone":"Asia/Shanghai",
    "iso:country":"CN",
    "name:zho_x_preferred":[
        "\u65b0\u56de"
    ],
    "wof:name":"Xinhui",
    "wof:placetype":"locality"
},
  "geometry": {"coordinates":[111.04696,27.52138],"type":"Point"}
}