{
  "type": "Feature",
  "properties": {
    "gn:admin1_code":"19.0",
    "gn:asciiname":"Chengshan",
    "gn:country_code":"CN",
    "gn:dem":27,
    "gn:feature_class":"P",
    "gn:feature_code":"PPL",
    "gn:name":"Chengshan",
    "gn:population":0,
    "gn:timezone":"Asia/Shanghai",
    "iso:country":"CN",
    "name:zho_x_preferred":[
        "\u57ce\u5c71"
    ],
    "name:zho_x_variant":[
        "\u6210\u5c71\u9547"
    ],
    "wof:name":"Chengshan",
    "wof:placetype":"locality"
},
  "geometry": {"coordinates":[123.90519,40.03803],"type":"Point"}
}