{
  "type": "Feature",
  "properties": {
    "gn:admin1_code":"19.0",
    "gn:asciiname":"Dujia Buzi",
    "gn:country_code":"CN",
    "gn:dem":329,
    "gn:feature_class":"P",
    "gn:feature_code":"PPL",
    "gn:name":"Dujia Buzi",
    "gn:population":0,
    "gn:timezone":"Asia/Shanghai",
    "iso:country":"CN",
    "name:und_x_variant":[
        "Dujiapuzi",
        "\u675c\u5bb6\u5821\u5b50",
        "Dujia Buzi"
    ],
    "wof:name":"Dujia Buzi",
    "wof:placetype":"locality"
},
  "geometry": {"coordinates":[123.869,40.9212],"type":"Point"}
}