{
  "type": "Feature",
  "properties": {
    "gn:admin1_code":"32.0",
    "gn:asciiname":"Nilijue",
    "gn:country_code":"CN",
    "gn:dem":2426,
    "gn:feature_class":"P",
    "gn:feature_code":"PPL",
    "gn:name":"Nilijue",
    "gn:population":0,
    "gn:timezone":"Asia/Shanghai",
    "iso:country":"CN",
    "name:zho_x_preferred":[
        "\u5c3c\u7acb\u89c9"
    ],
    "wof:name":"Nilijue",
    "wof:placetype":"locality"
},
  "geometry": {"coordinates":[103.1395,28.19396],"type":"Point"}
}