{
  "type": "Feature",
  "properties": {
    "gn:admin1_code":"19.0",
    "gn:asciiname":"Congjiadian",
    "gn:country_code":"CN",
    "gn:dem":329,
    "gn:feature_class":"P",
    "gn:feature_code":"PPL",
    "gn:name":"Congjiadian",
    "gn:population":0,
    "gn:timezone":"Asia/Shanghai",
    "iso:country":"CN",
    "name:und_x_variant":[
        "\u4e1b\u5bb6\u5e97"
    ],
    "name:zho_x_preferred":[
        "\u4e1b\u5bb6\u5e97"
    ],
    "wof:name":"Congjiadian",
    "wof:placetype":"locality"
},
  "geometry": {"coordinates":[120.01501,41.42681],"type":"Point"}
}