{
  "type": "Feature",
  "properties": {
    "gn:admin1_code":"10",
    "gn:asciiname":"Baifangsi",
    "gn:country_code":"CN",
    "gn:dem":46,
    "gn:feature_class":"P",
    "gn:feature_code":"PPL",
    "gn:name":"Baifangsi",
    "gn:population":0,
    "gn:timezone":"Asia/Shanghai",
    "iso:country":"CN",
    "name:zho_x_preferred":[
        "\u767d\u65b9\u5bfa"
    ],
    "wof:name":"Baifangsi",
    "wof:placetype":"locality"
},
  "geometry": {"coordinates":[117.93971999999999,40.13859],"type":"Point"}
}