{
  "type": "Feature",
  "properties": {
    "gn:admin1_code":"29.0",
    "gn:asciiname":"Bengle Xiazhai",
    "gn:country_code":"CN",
    "gn:dem":1384,
    "gn:feature_class":"P",
    "gn:feature_code":"PPL",
    "gn:name":"Bengle Xiazhai",
    "gn:population":0,
    "gn:timezone":"Asia/Shanghai",
    "iso:country":"CN",
    "name:zho_x_preferred":[
        "\u868c\u52d2\u4e0b\u5be8"
    ],
    "wof:name":"Bengle Xiazhai",
    "wof:placetype":"locality"
},
  "geometry": {"coordinates":[104.337,24.0791],"type":"Point"}
}