{
  "type": "Feature",
  "properties": {
    "gn:admin1_code":"7",
    "gn:asciiname":"Chuanchang",
    "gn:country_code":"CN",
    "gn:dem":378,
    "gn:feature_class":"P",
    "gn:feature_code":"PPL",
    "gn:name":"Chuanchang",
    "gn:population":0,
    "gn:timezone":"Asia/Shanghai",
    "iso:country":"CN",
    "name:zho_x_preferred":[
        "\u8239\u573a"
    ],
    "wof:name":"Chuanchang",
    "wof:placetype":"locality"
},
  "geometry": {"coordinates":[117.4037,24.29102],"type":"Point"}
}