{
  "type": "Feature",
  "properties": {
    "gn:admin1_code":"23.0",
    "gn:asciiname":"Zhangpu",
    "gn:country_code":"CN",
    "gn:dem":5,
    "gn:feature_class":"P",
    "gn:feature_code":"PPL",
    "gn:name":"Zhangpu",
    "gn:population":0,
    "gn:timezone":"Asia/Shanghai",
    "iso:country":"CN",
    "name:zho_x_preferred":[
        "Zhangpu"
    ],
    "name:zho_x_variant":[
        "\u5f20\u6734"
    ],
    "wof:name":"Zhangpu",
    "wof:placetype":"locality"
},
  "geometry": {"coordinates":[121.19786000000001,31.08096],"type":"Point"}
}