{
  "type": "Feature",
  "properties": {
    "gn:admin1_code":"19.0",
    "gn:asciiname":"Xiaohefenchang",
    "gn:country_code":"CN",
    "gn:dem":3,
    "gn:feature_class":"P",
    "gn:feature_code":"PPL",
    "gn:name":"Xiaohefenchang",
    "gn:population":0,
    "gn:timezone":"Asia/Shanghai",
    "iso:country":"CN",
    "name:und_x_variant":[
        "Xiaohe Fenchang"
    ],
    "name:zho_x_preferred":[
        "\u5c0f\u6cb3\u5206\u573a"
    ],
    "wof:name":"Xiaohefenchang",
    "wof:placetype":"locality"
},
  "geometry": {"coordinates":[121.628,40.9077],"type":"Point"}
}