{
  "type": "Feature",
  "properties": {
    "gn:admin1_code":"3",
    "gn:asciiname":"Panjia Zhipeng",
    "gn:country_code":"CN",
    "gn:dem":507,
    "gn:feature_class":"P",
    "gn:feature_code":"PPL",
    "gn:name":"Panjia Zhipeng",
    "gn:population":0,
    "gn:timezone":"Asia/Shanghai",
    "iso:country":"CN",
    "name:zho_x_preferred":[
        "\u6f58\u5bb6\u7eb8\u68da"
    ],
    "wof:name":"Panjia Zhipeng",
    "wof:placetype":"locality"
},
  "geometry": {"coordinates":[114.944,26.4572],"type":"Point"}
}