{
  "type": "Feature",
  "properties": {
    "gn:admin1_code":"15.0",
    "gn:asciiname":"Xiaosonggou",
    "gn:country_code":"CN",
    "gn:dem":2677,
    "gn:feature_class":"P",
    "gn:feature_code":"PPL",
    "gn:name":"Xiaosonggou",
    "gn:population":0,
    "gn:timezone":"Asia/Shanghai",
    "iso:country":"CN",
    "name:zho_x_preferred":[
        "\u5c0f\u5d69\u6c9f"
    ],
    "wof:name":"Xiaosonggou",
    "wof:placetype":"locality"
},
  "geometry": {"coordinates":[103.255,37.0157],"type":"Point"}
}