{
  "type": "Feature",
  "properties": {
    "gn:admin1_code":"25.0",
    "gn:asciiname":"Xugezhuangcun",
    "gn:country_code":"CN",
    "gn:dem":15,
    "gn:feature_class":"P",
    "gn:feature_code":"PPL",
    "gn:name":"Xugezhuangcun",
    "gn:population":0,
    "gn:timezone":"Asia/Shanghai",
    "iso:country":"CN",
    "name:zho_x_preferred":[
        "\u5f90\u6208\u5e84\u6751"
    ],
    "wof:name":"Xugezhuangcun",
    "wof:placetype":"locality"
},
  "geometry": {"coordinates":[120.16875,36.05405],"type":"Point"}
}