{
  "type": "Feature",
  "properties": {
    "gn:admin1_code":"29.0",
    "gn:asciiname":"Tapu",
    "gn:country_code":"CN",
    "gn:dem":1422,
    "gn:feature_class":"P",
    "gn:feature_code":"PPL",
    "gn:name":"Tapu",
    "gn:population":0,
    "gn:timezone":"Asia/Shanghai",
    "iso:country":"CN",
    "name:deu_x_preferred":[
        "Tapu"
    ],
    "name:zho_x_preferred":[
        "\u5854\u666e"
    ],
    "wof:name":"Tapu",
    "wof:placetype":"locality"
},
  "geometry": {"coordinates":[102.553,22.8412],"type":"Point"}
}