{
  "type": "Feature",
  "properties": {
    "gn:admin1_code":"15.0",
    "gn:asciiname":"Zaganguo",
    "gn:country_code":"CN",
    "gn:dem":3253,
    "gn:feature_class":"P",
    "gn:feature_code":"PPL",
    "gn:name":"Zaganguo",
    "gn:population":0,
    "gn:timezone":"Asia/Shanghai",
    "iso:country":"CN",
    "name:zho_x_preferred":[
        "\u6742\u5e72\u679c"
    ],
    "wof:name":"Zaganguo",
    "wof:placetype":"locality"
},
  "geometry": {"coordinates":[102.809,34.4834],"type":"Point"}
}