{
  "type": "Feature",
  "properties": {
    "gn:admin1_code":"1.0",
    "gn:asciiname":"Chalin",
    "gn:country_code":"CN",
    "gn:dem":29,
    "gn:feature_class":"P",
    "gn:feature_code":"PPL",
    "gn:name":"Chalin",
    "gn:population":0,
    "gn:timezone":"Asia/Shanghai",
    "iso:country":"CN",
    "name:ceb_x_preferred":[
        "Chalin"
    ],
    "name:fra_x_preferred":[
        "Chalin"
    ],
    "name:pol_x_preferred":[
        "Chalin"
    ],
    "name:swe_x_preferred":[
        "Chalin"
    ],
    "name:ukr_x_preferred":[
        "\u0425\u0430\u043b\u0456\u043d"
    ],
    "name:zho_x_preferred":[
        "\u8336\u6797"
    ],
    "wof:name":"Chalin",
    "wof:placetype":"locality"
},
  "geometry": {"coordinates":[118.30318,30.9526],"type":"Point"}
}