{
  "type": "Feature",
  "properties": {
    "gn:admin1_code":"9.0",
    "gn:asciiname":"Penbeicun",
    "gn:country_code":"CN",
    "gn:dem":66,
    "gn:feature_class":"P",
    "gn:feature_code":"PPL",
    "gn:name":"Penbeicun",
    "gn:population":0,
    "gn:timezone":"Asia/Shanghai",
    "iso:country":"CN",
    "name:zho_x_preferred":[
        "\u76c6\u5317\u6751"
    ],
    "wof:name":"Penbeicun",
    "wof:placetype":"locality"
},
  "geometry": {"coordinates":[114.02679000000001,33.99217],"type":"Point"}
}