{
  "type": "Feature",
  "properties": {
    "gn:admin1_code":"14.0",
    "gn:asciiname":"Kongdoi",
    "gn:country_code":"CN",
    "gn:dem":4139,
    "gn:feature_class":"P",
    "gn:feature_code":"PPLF",
    "gn:name":"Kongdoi",
    "gn:population":0,
    "gn:timezone":"Asia/Urumqi",
    "iso:country":"CN",
    "name:bod_x_preferred":[
        "Kongdoi"
    ],
    "name:zho_x_preferred":[
        "Gongdui"
    ],
    "name:zho_x_variant":[
        "\u8d21\u5806",
        "Gongkangsha Qu",
        "\u8d21\u5eb7\u6c99\u533a"
    ],
    "wof:name":"Kongdoi",
    "wof:placetype":"locality"
},
  "geometry": {"coordinates":[92.20099999999999,29.101],"type":"Point"}
}