{
  "type": "Feature",
  "properties": {
    "gn:admin1_code":"1.0",
    "gn:asciiname":"Changjiangcun",
    "gn:country_code":"CN",
    "gn:dem":7,
    "gn:feature_class":"P",
    "gn:feature_code":"PPL",
    "gn:name":"Changjiangcun",
    "gn:population":0,
    "gn:timezone":"Asia/Shanghai",
    "iso:country":"CN",
    "name:zho_x_preferred":[
        "\u957f\u6c5f\u6751"
    ],
    "wof:name":"Changjiangcun",
    "wof:placetype":"locality"
},
  "geometry": {"coordinates":[117.73732,30.87445],"type":"Point"}
}