{
  "type": "Feature",
  "properties": {
    "gn:admin1_code":"32.0",
    "gn:asciiname":"Kangmeide",
    "gn:country_code":"CN",
    "gn:dem":3187,
    "gn:feature_class":"P",
    "gn:feature_code":"PPL",
    "gn:name":"Kangmeide",
    "gn:population":0,
    "gn:timezone":"Asia/Shanghai",
    "iso:country":"CN",
    "name:zho_x_preferred":[
        "\u5eb7\u59b9\u5fb7"
    ],
    "wof:name":"Kangmeide",
    "wof:placetype":"locality"
},
  "geometry": {"coordinates":[98.78928999999999,31.22841],"type":"Point"}
}