{
  "type": "Feature",
  "properties": {
    "gn:admin1_code":"21.0",
    "gn:asciiname":"Wangshuitang",
    "gn:country_code":"CN",
    "gn:dem":1505,
    "gn:feature_class":"P",
    "gn:feature_code":"PPL",
    "gn:name":"Wangshuitang",
    "gn:population":0,
    "gn:timezone":"Asia/Shanghai",
    "iso:country":"CN",
    "name:zho_x_preferred":[
        "\u6c6a\u6c34\u5858"
    ],
    "wof:name":"Wangshuitang",
    "wof:placetype":"locality"
},
  "geometry": {"coordinates":[107.098,37.7497],"type":"Point"}
}