{
  "type": "Feature",
  "properties": {
    "gn:admin1_code":"18.0",
    "gn:asciiname":"Aihe",
    "gn:country_code":"CN",
    "gn:dem":919,
    "gn:feature_class":"P",
    "gn:feature_code":"PPL",
    "gn:name":"Aihe",
    "gn:population":0,
    "gn:timezone":"Asia/Shanghai",
    "iso:country":"CN",
    "name:zho_x_preferred":[
        "\u7231\u6cb3"
    ],
    "wof:name":"Aihe",
    "wof:placetype":"locality"
},
  "geometry": {"coordinates":[108.45999999999999,26.8901],"type":"Point"}
}