{
  "type": "Feature",
  "properties": {
    "gn:admin1_code":"11",
    "gn:asciiname":"Zhuzi'ao",
    "gn:country_code":"CN",
    "gn:dem":112,
    "gn:feature_class":"P",
    "gn:feature_code":"PPL",
    "gn:name":"Zhuzi\u2019ao",
    "gn:population":0,
    "gn:timezone":"Asia/Shanghai",
    "iso:country":"CN",
    "name:und_x_variant":[
        "Zhuzi\u2019ao"
    ],
    "name:zho_x_preferred":[
        "\u7af9\u5b50\u5773"
    ],
    "wof:name":"Zhuzi'ao",
    "wof:placetype":"locality"
},
  "geometry": {"coordinates":[111.91664,26.60021],"type":"Point"}
}