{
  "type": "Feature",
  "properties": {
    "gn:admin1_code":"26.0",
    "gn:asciiname":"Daiwanggou",
    "gn:country_code":"CN",
    "gn:dem":1287,
    "gn:feature_class":"P",
    "gn:feature_code":"PPL",
    "gn:name":"Daiwanggou",
    "gn:population":0,
    "gn:timezone":"Asia/Shanghai",
    "iso:country":"CN",
    "name:zho_x_preferred":[
        "\u4ee3\u738b\u6c9f"
    ],
    "wof:name":"Daiwanggou",
    "wof:placetype":"locality"
},
  "geometry": {"coordinates":[108.9773,33.8008],"type":"Point"}
}