{
  "type": "Feature",
  "properties": {
    "gn:admin1_code":"29.0",
    "gn:asciiname":"Chenjia Banpo",
    "gn:country_code":"CN",
    "gn:dem":1851,
    "gn:feature_class":"P",
    "gn:feature_code":"PPL",
    "gn:name":"Chenjia Banpo",
    "gn:population":0,
    "gn:timezone":"Asia/Shanghai",
    "iso:country":"CN",
    "name:zho_x_preferred":[
        "\u9648\u5bb6\u534a\u5761"
    ],
    "wof:name":"Chenjia Banpo",
    "wof:placetype":"locality"
},
  "geometry": {"coordinates":[104.621,26.3453],"type":"Point"}
}