{
  "type": "Feature",
  "properties": {
    "gn:admin1_code":"3.0",
    "gn:asciiname":"Duifeng",
    "gn:country_code":"CN",
    "gn:dem":42,
    "gn:feature_class":"P",
    "gn:feature_code":"PPL",
    "gn:name":"Duifeng",
    "gn:population":0,
    "gn:timezone":"Asia/Shanghai",
    "iso:country":"CN",
    "name:und_x_variant":[
        "\u5806\u5cf0"
    ],
    "wof:name":"Duifeng",
    "wof:placetype":"locality"
},
  "geometry": {"coordinates":[115.05983000000001,28.23893],"type":"Point"}
}