{
  "type": "Feature",
  "properties": {
    "gn:admin1_code":"07",
    "gn:asciiname":"Tanlu",
    "gn:country_code":"CN",
    "gn:dem":797,
    "gn:feature_class":"P",
    "gn:feature_code":"PPL",
    "gn:name":"Tanlu",
    "gn:population":0,
    "gn:timezone":"Asia/Shanghai",
    "iso:country":"CN",
    "name:zho_x_preferred":[
        "\u6f6d\u8def"
    ],
    "wof:name":"Tanlu",
    "wof:placetype":"locality"
},
  "geometry": {"coordinates":[117.42063,25.03009],"type":"Point"}
}