{
  "type": "Feature",
  "properties": {
    "gn:admin1_code":"10",
    "gn:asciiname":"Zhaozhuang",
    "gn:country_code":"CN",
    "gn:dem":17,
    "gn:feature_class":"P",
    "gn:feature_code":"PPL",
    "gn:name":"Zhaozhuang",
    "gn:population":0,
    "gn:timezone":"Asia/Shanghai",
    "iso:country":"CN",
    "name:zho_x_preferred":[
        "\u8d75\u5e84"
    ],
    "wof:name":"Zhaozhuang",
    "wof:placetype":"locality"
},
  "geometry": {"coordinates":[116.37175999999999,37.80427],"type":"Point"}
}