{
  "type": "Feature",
  "properties": {
    "gn:admin1_code":"12.0",
    "gn:asciiname":"Xiaoxiejiawan",
    "gn:country_code":"CN",
    "gn:dem":49,
    "gn:feature_class":"P",
    "gn:feature_code":"PPL",
    "gn:name":"Xiaoxiejiawan",
    "gn:population":0,
    "gn:timezone":"Asia/Shanghai",
    "iso:country":"CN",
    "name:zho_x_preferred":[
        "\u5c0f\u8c22\u5bb6\u6e7e"
    ],
    "wof:name":"Xiaoxiejiawan",
    "wof:placetype":"locality"
},
  "geometry": {"coordinates":[112.21529,30.64309],"type":"Point"}
}