{
  "type": "Feature",
  "properties": {
    "gn:admin1_code":"32.0",
    "gn:asciiname":"Donglonggou",
    "gn:country_code":"CN",
    "gn:dem":3036,
    "gn:feature_class":"P",
    "gn:feature_code":"PPL",
    "gn:name":"Donglonggou",
    "gn:population":0,
    "gn:timezone":"Asia/Shanghai",
    "iso:country":"CN",
    "name:zho_x_preferred":[
        "\u6d1e\u9f99\u6c9f"
    ],
    "wof:name":"Donglonggou",
    "wof:placetype":"locality"
},
  "geometry": {"coordinates":[101.35899999999999,28.1293],"type":"Point"}
}