{
  "type": "Feature",
  "properties": {
    "gn:admin1_code":"19.0",
    "gn:asciiname":"Shandongtoucun",
    "gn:country_code":"CN",
    "gn:dem":12,
    "gn:feature_class":"P",
    "gn:feature_code":"PPL",
    "gn:name":"Shandongtoucun",
    "gn:population":0,
    "gn:timezone":"Asia/Shanghai",
    "iso:country":"CN",
    "name:zho_x_preferred":[
        "\u5c71\u4e1c\u5934\u6751"
    ],
    "wof:name":"Shandongtoucun",
    "wof:placetype":"locality"
},
  "geometry": {"coordinates":[122.03,39.2059],"type":"Point"}
}