{
  "type": "Feature",
  "properties": {
    "gn:admin1_code":"12.0",
    "gn:asciiname":"Laoyawo",
    "gn:country_code":"CN",
    "gn:dem":231,
    "gn:feature_class":"P",
    "gn:feature_code":"PPL",
    "gn:name":"Laoyawo",
    "gn:population":0,
    "gn:timezone":"Asia/Shanghai",
    "iso:country":"CN",
    "name:zho_x_preferred":[
        "\u8001\u9e26\u7a9d"
    ],
    "wof:name":"Laoyawo",
    "wof:placetype":"locality"
},
  "geometry": {"coordinates":[113.0069,32.34307],"type":"Point"}
}