{
  "type": "Feature",
  "properties": {
    "gn:admin1_code":"25",
    "gn:asciiname":"Xutuanzhuang",
    "gn:country_code":"CN",
    "gn:dem":22,
    "gn:feature_class":"P",
    "gn:feature_code":"PPL",
    "gn:name":"Xutuanzhuang",
    "gn:population":0,
    "gn:timezone":"Asia/Shanghai",
    "iso:country":"CN",
    "name:zho_x_preferred":[
        "\u5f90\u7583\u5e84"
    ],
    "wof:name":"Xutuanzhuang",
    "wof:placetype":"locality"
},
  "geometry": {"coordinates":[120.69,36.7461],"type":"Point"}
}