{
  "type": "Feature",
  "properties": {
    "gn:admin1_code":"19.0",
    "gn:asciiname":"Xiaodatai",
    "gn:country_code":"CN",
    "gn:dem":7,
    "gn:feature_class":"P",
    "gn:feature_code":"PPL",
    "gn:name":"Xiaodatai",
    "gn:population":0,
    "gn:timezone":"Asia/Shanghai",
    "iso:country":"CN",
    "name:und_x_variant":[
        "\u5c0f\u5927\u53f0"
    ],
    "name:zho_x_preferred":[
        "\u5c0f\u5927\u53f0"
    ],
    "wof:name":"Xiaodatai",
    "wof:placetype":"locality"
},
  "geometry": {"coordinates":[122.28673999999999,41.35113],"type":"Point"}
}