{
  "type": "Feature",
  "properties": {
    "gn:admin1_code":"3.0",
    "gn:asciiname":"Duanshangcun",
    "gn:country_code":"CN",
    "gn:dem":601,
    "gn:feature_class":"P",
    "gn:feature_code":"PPL",
    "gn:name":"Duanshangcun",
    "gn:population":0,
    "gn:timezone":"Asia/Shanghai",
    "iso:country":"CN",
    "name:zho_x_preferred":[
        "\u5845\u4e0a\u6751"
    ],
    "wof:name":"Duanshangcun",
    "wof:placetype":"locality"
},
  "geometry": {"coordinates":[115.086,28.7956],"type":"Point"}
}