{
  "type": "Feature",
  "properties": {
    "gn:admin1_code":"26.0",
    "gn:asciiname":"Zhaogoumencun",
    "gn:country_code":"CN",
    "gn:dem":1220,
    "gn:feature_class":"P",
    "gn:feature_code":"PPL",
    "gn:name":"Zhaogoumencun",
    "gn:population":0,
    "gn:timezone":"Asia/Shanghai",
    "iso:country":"CN",
    "name:zho_x_preferred":[
        "\u8d75\u6c9f\u95e8\u6751"
    ],
    "wof:name":"Zhaogoumencun",
    "wof:placetype":"locality"
},
  "geometry": {"coordinates":[108.43414,36.72573],"type":"Point"}
}