{
  "type": "Feature",
  "properties": {
    "gn:admin1_code":"32.0",
    "gn:asciiname":"Gongbu",
    "gn:country_code":"CN",
    "gn:dem":4117,
    "gn:feature_class":"P",
    "gn:feature_code":"PPL",
    "gn:name":"Gongbu",
    "gn:population":0,
    "gn:timezone":"Asia/Shanghai",
    "iso:country":"CN",
    "name:zho_x_preferred":[
        "\u8d21\u5e03"
    ],
    "wof:name":"Gongbu",
    "wof:placetype":"locality"
},
  "geometry": {"coordinates":[101.379,30.2504],"type":"Point"}
}