{
  "type": "Feature",
  "properties": {
    "gn:admin1_code":"6.0",
    "gn:asciiname":"Longmen",
    "gn:country_code":"CN",
    "gn:dem":4346,
    "gn:feature_class":"P",
    "gn:feature_code":"PPLA4",
    "gn:name":"Longmen",
    "gn:population":0,
    "gn:timezone":"Asia/Urumqi",
    "iso:country":"CN",
    "name:ceb_x_preferred":[
        "Longmen"
    ],
    "name:deu_x_preferred":[
        "Longmen"
    ],
    "name:fra_x_preferred":[
        "Longmen"
    ],
    "name:mlg_x_preferred":[
        "Longmen"
    ],
    "name:nor_x_preferred":[
        "Longmen"
    ],
    "name:pol_x_preferred":[
        "Longmen"
    ],
    "name:und_x_variant":[
        "Longmen Xiang"
    ],
    "name:vie_x_preferred":[
        "Long M\u00f4n"
    ],
    "name:zho_x_preferred":[
        "\u9f99\u95e8"
    ],
    "name:zho_x_variant":[
        "\u9f99\u95e8\u4e61"
    ],
    "wof:name":"Longmen",
    "wof:placetype":"locality"
},
  "geometry": {"coordinates":[98.92313,37.87776],"type":"Point"}
}