{
  "type": "Feature",
  "properties": {
    "gn:admin1_code":"12.0",
    "gn:asciiname":"Luohanwan",
    "gn:country_code":"CN",
    "gn:dem":355,
    "gn:feature_class":"P",
    "gn:feature_code":"PPL",
    "gn:name":"Luohanwan",
    "gn:population":0,
    "gn:timezone":"Asia/Shanghai",
    "iso:country":"CN",
    "name:zho_x_preferred":[
        "\u7f57\u6c49\u6e7e"
    ],
    "wof:name":"Luohanwan",
    "wof:placetype":"locality"
},
  "geometry": {"coordinates":[109.89542,32.15376],"type":"Point"}
}