{
  "type": "Feature",
  "properties": {
    "gn:admin1_code":"12.0",
    "gn:asciiname":"Lijiasanwan",
    "gn:country_code":"CN",
    "gn:dem":33,
    "gn:feature_class":"P",
    "gn:feature_code":"PPL",
    "gn:name":"Lijiasanwan",
    "gn:population":0,
    "gn:timezone":"Asia/Shanghai",
    "iso:country":"CN",
    "name:zho_x_preferred":[
        "\u674e\u5bb6\u4e09\u6e7e"
    ],
    "wof:name":"Lijiasanwan",
    "wof:placetype":"locality"
},
  "geometry": {"coordinates":[113.10489,30.43015],"type":"Point"}
}