{
  "type": "Feature",
  "properties": {
    "gn:admin1_code":"29.0",
    "gn:asciiname":"Gouzuandong",
    "gn:country_code":"CN",
    "gn:dem":3328,
    "gn:feature_class":"P",
    "gn:feature_code":"PPL",
    "gn:name":"Gouzuandong",
    "gn:population":0,
    "gn:timezone":"Asia/Shanghai",
    "iso:country":"CN",
    "name:zho_x_preferred":[
        "\u72d7\u94bb\u6d1e"
    ],
    "wof:name":"Gouzuandong",
    "wof:placetype":"locality"
},
  "geometry": {"coordinates":[100.809,27.6333],"type":"Point"}
}