{
  "type": "Feature",
  "properties": {
    "gn:admin1_code":"11.0",
    "gn:asciiname":"Jianghukou",
    "gn:country_code":"CN",
    "gn:dem":33,
    "gn:feature_class":"P",
    "gn:feature_code":"PPL",
    "gn:name":"Jianghukou",
    "gn:population":0,
    "gn:timezone":"Asia/Shanghai",
    "iso:country":"CN",
    "name:zho_x_preferred":[
        "\u848b\u6e56\u53e3"
    ],
    "wof:name":"Jianghukou",
    "wof:placetype":"locality"
},
  "geometry": {"coordinates":[112.55059,28.80402],"type":"Point"}
}