{
  "type": "Feature",
  "properties": {
    "gn:admin1_code":"18",
    "gn:asciiname":"Xudiji",
    "gn:country_code":"CN",
    "gn:dem":1574,
    "gn:feature_class":"P",
    "gn:feature_code":"PPL",
    "gn:name":"Xudiji",
    "gn:population":0,
    "gn:timezone":"Asia/Shanghai",
    "iso:country":"CN",
    "name:zho_x_preferred":[
        "\u8bb8\u5730\u57fa"
    ],
    "wof:name":"Xudiji",
    "wof:placetype":"locality"
},
  "geometry": {"coordinates":[104.82299999999999,25.5453],"type":"Point"}
}