{
  "type": "Feature",
  "properties": {
    "gn:admin1_code":"8.0",
    "gn:asciiname":"Junfengcun",
    "gn:country_code":"CN",
    "gn:dem":127,
    "gn:feature_class":"P",
    "gn:feature_code":"PPL",
    "gn:name":"Junfengcun",
    "gn:population":0,
    "gn:timezone":"Asia/Shanghai",
    "iso:country":"CN",
    "name:zho_x_preferred":[
        "\u5cfb\u4e30\u6751"
    ],
    "wof:name":"Junfengcun",
    "wof:placetype":"locality"
},
  "geometry": {"coordinates":[130.2688,47.19837],"type":"Point"}
}