{
  "type": "Feature",
  "properties": {
    "gn:admin1_code":"25",
    "gn:asciiname":"Wanglaojun",
    "gn:country_code":"CN",
    "gn:dem":48,
    "gn:feature_class":"P",
    "gn:feature_code":"PPL",
    "gn:name":"Wanglaojun",
    "gn:population":0,
    "gn:timezone":"Asia/Shanghai",
    "iso:country":"CN",
    "name:zho_x_preferred":[
        "\u738b\u8001\u541b"
    ],
    "wof:name":"Wanglaojun",
    "wof:placetype":"locality"
},
  "geometry": {"coordinates":[115.886,35.8986],"type":"Point"}
}