{
  "type": "Feature",
  "properties": {
    "gn:admin1_code":"29",
    "gn:asciiname":"Lida",
    "gn:cc2":"CN",
    "gn:country_code":"CN",
    "gn:dem":1378,
    "gn:feature_class":"P",
    "gn:feature_code":"PPL",
    "gn:name":"Lida",
    "gn:population":0,
    "gn:timezone":"Asia/Shanghai",
    "iso:country":"CN",
    "name:ara_x_preferred":[
        "\u0644\u064a\u062f\u0627"
    ],
    "name:aze_x_preferred":[
        "Lida"
    ],
    "name:bel_x_preferred":[
        "\u041b\u0456\u0434\u0430"
    ],
    "name:bul_x_preferred":[
        "\u041b\u0438\u0434\u0430"
    ],
    "name:ceb_x_preferred":[
        "Lida"
    ],
    "name:ces_x_preferred":[
        "Lida"
    ],
    "name:che_x_preferred":[
        "\u041b\u0438\u0434\u0430"
    ],
    "name:dan_x_preferred":[
        "Lida"
    ],
    "name:deu_x_preferred":[
        "Lida"
    ],
    "name:dsb_x_preferred":[
        "Lida"
    ],
    "name:epo_x_preferred":[
        "Lida"
    ],
    "name:est_x_preferred":[
        "\u0141ida"
    ],
    "name:fas_x_preferred":[
        "\u0644\u06cc\u062f\u0627"
    ],
    "name:fin_x_preferred":[
        "Lida"
    ],
    "name:fra_x_preferred":[
        "Lida"
    ],
    "name:frr_x_preferred":[
        "Lida"
    ],
    "name:heb_x_preferred":[
        "\u05dc\u05d9\u05d3\u05d0"
    ],
    "name:hrv_x_preferred":[
        "Lida"
    ],
    "name:hsb_x_preferred":[
        "Lida"
    ],
    "name:hun_x_preferred":[
        "Lida"
    ],
    "name:ita_x_preferred":[
        "Lida"
    ],
    "name:kat_x_preferred":[
        "\u10da\u10d8\u10d3\u10d0"
    ],
    "name:lav_x_preferred":[
        "\u013bida"
    ],
    "name:lit_x_preferred":[
        "Lyda"
    ],
    "name:mar_x_preferred":[
        "\u0932\u093f\u0921\u093e"
    ],
    "name:nld_x_preferred":[
        "Lida"
    ],
    "name:nor_x_preferred":[
        "Lida"
    ],
    "name:pol_x_preferred":[
        "Lida"
    ],
    "name:rus_x_preferred":[
        "\u041b\u0438\u0434\u0430"
    ],
    "name:spa_x_preferred":[
        "Lida"
    ],
    "name:sqi_x_preferred":[
        "Lida"
    ],
    "name:srp_x_preferred":[
        "\u041b\u0438\u0434\u0430"
    ],
    "name:swe_x_preferred":[
        "Lida"
    ],
    "name:szl_x_preferred":[
        "Lida"
    ],
    "name:tat_x_preferred":[
        "\u041b\u0438\u0434\u0430"
    ],
    "name:tur_x_preferred":[
        "Lida"
    ],
    "name:udm_x_preferred":[
        "\u041b\u0438\u0434\u0430"
    ],
    "name:ukr_x_preferred":[
        "\u041b\u0456\u0434\u0430"
    ],
    "name:und_x_variant":[
        "Li-ta"
    ],
    "name:urd_x_preferred":[
        "\u0644\u06cc\u062f\u0627"
    ],
    "name:war_x_preferred":[
        "Lida"
    ],
    "name:yid_x_preferred":[
        "\u05dc\u05d9\u05d3\u05d0"
    ],
    "wof:name":"Lida",
    "wof:placetype":"locality"
},
  "geometry": {"coordinates":[105.53,23.53111],"type":"Point"}
}