{
  "type": "Feature",
  "properties": {
    "gn:admin1_code":"4.0",
    "gn:asciiname":"Lujiangcun",
    "gn:country_code":"CN",
    "gn:dem":17,
    "gn:feature_class":"P",
    "gn:feature_code":"PPL",
    "gn:name":"Lujiangcun",
    "gn:population":0,
    "gn:timezone":"Asia/Shanghai",
    "iso:country":"CN",
    "name:zho_x_preferred":[
        "\u82a6\u6c5f\u6751"
    ],
    "wof:name":"Lujiangcun",
    "wof:placetype":"locality"
},
  "geometry": {"coordinates":[119.16211,31.82208],"type":"Point"}
}