{
  "type": "Feature",
  "properties": {
    "gn:admin1_code":"26.0",
    "gn:asciiname":"Zhongba",
    "gn:country_code":"CN",
    "gn:dem":740,
    "gn:feature_class":"P",
    "gn:feature_code":"PPL",
    "gn:name":"Zhongba",
    "gn:population":0,
    "gn:timezone":"Asia/Shanghai",
    "iso:country":"CN",
    "name:ceb_x_preferred":[
        "Zhongba"
    ],
    "name:deu_x_preferred":[
        "Zhongba"
    ],
    "name:und_x_variant":[
        "Chung-pa",
        "Zhongba",
        "Zhongbacun"
    ],
    "name:zho_x_preferred":[
        "\u4e2d\u575d\u6751"
    ],
    "wof:name":"Zhongba",
    "wof:placetype":"locality"
},
  "geometry": {"coordinates":[108.97732999999999,32.31682],"type":"Point"}
}