{
  "type": "Feature",
  "properties": {
    "gn:admin1_code":"18.0",
    "gn:asciiname":"Yaodeng",
    "gn:country_code":"CN",
    "gn:dem":633,
    "gn:feature_class":"P",
    "gn:feature_code":"PPL",
    "gn:name":"Yaodeng",
    "gn:population":0,
    "gn:timezone":"Asia/Shanghai",
    "iso:country":"CN",
    "name:zho_x_preferred":[
        "\u5c27\u7b49"
    ],
    "wof:name":"Yaodeng",
    "wof:placetype":"locality"
},
  "geometry": {"coordinates":[108.86,25.6422],"type":"Point"}
}