{
  "type": "Feature",
  "properties": {
    "gn:admin1_code":"8.0",
    "gn:asciiname":"Xinyoutun",
    "gn:country_code":"CN",
    "gn:dem":213,
    "gn:feature_class":"P",
    "gn:feature_code":"PPL",
    "gn:name":"Xinyoutun",
    "gn:population":0,
    "gn:timezone":"Asia/Shanghai",
    "iso:country":"CN",
    "name:zho_x_preferred":[
        "\u65b0\u6709\u5c6f"
    ],
    "wof:name":"Xinyoutun",
    "wof:placetype":"locality"
},
  "geometry": {"coordinates":[128.07473999999999,45.51127],"type":"Point"}
}