{
  "type": "Feature",
  "properties": {
    "gn:admin1_code":"14.0",
    "gn:asciiname":"Wugeda",
    "gn:country_code":"CN",
    "gn:dem":4032,
    "gn:feature_class":"P",
    "gn:feature_code":"PPL",
    "gn:name":"Wugeda",
    "gn:population":0,
    "gn:timezone":"Asia/Urumqi",
    "iso:country":"CN",
    "name:zho_x_preferred":[
        "\u65e0\u9769\u8fbe"
    ],
    "wof:name":"Wugeda",
    "wof:placetype":"locality"
},
  "geometry": {"coordinates":[97.45641999999999,31.95084],"type":"Point"}
}