{
  "type": "Feature",
  "properties": {
    "gn:admin1_code":"4.0",
    "gn:asciiname":"Beiyang",
    "gn:country_code":"CN",
    "gn:dem":4,
    "gn:feature_class":"P",
    "gn:feature_code":"PPL",
    "gn:name":"Beiyang",
    "gn:population":0,
    "gn:timezone":"Asia/Shanghai",
    "iso:country":"CN",
    "name:deu_x_preferred":[
        "Beiyang"
    ],
    "name:ita_x_preferred":[
        "Beiyang"
    ],
    "name:nor_x_preferred":[
        "Beiyang"
    ],
    "name:rus_x_preferred":[
        "\u0411\u044d\u0439\u044f\u043d"
    ],
    "name:ukr_x_preferred":[
        "\u0411\u0435\u0439\u044f\u043d"
    ],
    "name:zho_x_preferred":[
        "\u5317\u6d0b"
    ],
    "wof:name":"Beiyang",
    "wof:placetype":"locality"
},
  "geometry": {"coordinates":[120.11709,32.21817],"type":"Point"}
}