{
  "type": "Feature",
  "properties": {
    "gn:admin1_code":"11.0",
    "gn:asciiname":"Songjia'ao",
    "gn:country_code":"CN",
    "gn:dem":289,
    "gn:feature_class":"P",
    "gn:feature_code":"PPL",
    "gn:name":"Songjia\u2019ao",
    "gn:population":0,
    "gn:timezone":"Asia/Shanghai",
    "iso:country":"CN",
    "name:und_x_variant":[
        "Songjia\u2019ao"
    ],
    "name:zho_x_preferred":[
        "\u5b8b\u5bb6\u5773"
    ],
    "wof:name":"Songjia'ao",
    "wof:placetype":"locality"
},
  "geometry": {"coordinates":[109.71993000000001,27.43478],"type":"Point"}
}