{
  "type": "Feature",
  "properties": {
    "gn:admin1_code":"29.0",
    "gn:asciiname":"Niushuitang",
    "gn:country_code":"CN",
    "gn:dem":1866,
    "gn:feature_class":"P",
    "gn:feature_code":"PPL",
    "gn:name":"Niushuitang",
    "gn:population":0,
    "gn:timezone":"Asia/Shanghai",
    "iso:country":"CN",
    "name:zho_x_preferred":[
        "\u725b\u6c34\u5858"
    ],
    "wof:name":"Niushuitang",
    "wof:placetype":"locality"
},
  "geometry": {"coordinates":[100.768,26.2034],"type":"Point"}
}