{
  "type": "Feature",
  "properties": {
    "gn:admin1_code":"16.0",
    "gn:asciiname":"Shangnalong",
    "gn:country_code":"CN",
    "gn:dem":224,
    "gn:feature_class":"P",
    "gn:feature_code":"PPL",
    "gn:name":"Shangnalong",
    "gn:population":0,
    "gn:timezone":"Asia/Shanghai",
    "iso:country":"CN",
    "name:zho_x_preferred":[
        "\u4e0a\u90a3\u9f99"
    ],
    "wof:name":"Shangnalong",
    "wof:placetype":"locality"
},
  "geometry": {"coordinates":[108.084,23.5691],"type":"Point"}
}