{
  "type": "Feature",
  "properties": {
    "gn:admin1_code":"19.0",
    "gn:asciiname":"Shangtaizi",
    "gn:country_code":"CN",
    "gn:dem":169,
    "gn:feature_class":"P",
    "gn:feature_code":"PPL",
    "gn:name":"Shangtaizi",
    "gn:population":0,
    "gn:timezone":"Asia/Shanghai",
    "iso:country":"CN",
    "name:und_x_variant":[
        "\u4e0a\u53f0\u5b50"
    ],
    "wof:name":"Shangtaizi",
    "wof:placetype":"locality"
},
  "geometry": {"coordinates":[125.27273,40.95695],"type":"Point"}
}