{
  "type": "Feature",
  "properties": {
    "gn:admin1_code":"14.0",
    "gn:asciiname":"Longbugang",
    "gn:country_code":"CN",
    "gn:dem":3834,
    "gn:feature_class":"P",
    "gn:feature_code":"PPL",
    "gn:name":"Longbugang",
    "gn:population":0,
    "gn:timezone":"Asia/Urumqi",
    "iso:country":"CN",
    "name:zho_x_preferred":[
        "\u9f99\u5e03\u5c97"
    ],
    "wof:name":"Longbugang",
    "wof:placetype":"locality"
},
  "geometry": {"coordinates":[91.68637,29.81937000000001],"type":"Point"}
}