{
  "type": "Feature",
  "properties": {
    "gn:admin1_code":"11",
    "gn:asciiname":"Xiaodongwei",
    "gn:country_code":"CN",
    "gn:dem":235,
    "gn:feature_class":"P",
    "gn:feature_code":"PPL",
    "gn:name":"Xiaodongwei",
    "gn:population":0,
    "gn:timezone":"Asia/Shanghai",
    "iso:country":"CN",
    "name:und_x_variant":[
        "\u5c0f\u6d1e\u5c3e",
        "Xiaodongwei"
    ],
    "wof:name":"Xiaodongwei",
    "wof:placetype":"locality"
},
  "geometry": {"coordinates":[111.40971999999999,25.63389],"type":"Point"}
}