{
  "type": "Feature",
  "properties": {
    "gn:admin1_code":"2.0",
    "gn:asciiname":"Daijiawan",
    "gn:country_code":"CN",
    "gn:dem":8,
    "gn:feature_class":"P",
    "gn:feature_code":"PPL",
    "gn:name":"Daijiawan",
    "gn:population":0,
    "gn:timezone":"Asia/Shanghai",
    "iso:country":"CN",
    "name:und_x_variant":[
        "\u6234\u5bb6\u6e7e"
    ],
    "wof:name":"Daijiawan",
    "wof:placetype":"locality"
},
  "geometry": {"coordinates":[120.40429,30.89131],"type":"Point"}
}