{
  "type": "Feature",
  "properties": {
    "gn:admin1_code":"10.0",
    "gn:asciiname":"Xiangyanghui",
    "gn:country_code":"CN",
    "gn:dem":575,
    "gn:feature_class":"P",
    "gn:feature_code":"PPL",
    "gn:name":"Xiangyanghui",
    "gn:population":0,
    "gn:timezone":"Asia/Shanghai",
    "iso:country":"CN",
    "name:zho_x_preferred":[
        "\u5411\u9633\u4f1a"
    ],
    "wof:name":"Xiangyanghui",
    "wof:placetype":"locality"
},
  "geometry": {"coordinates":[114.49216,39.10074],"type":"Point"}
}