{
  "type": "Feature",
  "properties": {
    "gn:admin1_code":"10",
    "gn:asciiname":"Dawulong",
    "gn:country_code":"CN",
    "gn:dem":24,
    "gn:feature_class":"P",
    "gn:feature_code":"PPL",
    "gn:name":"Dawulong",
    "gn:population":0,
    "gn:timezone":"Asia/Shanghai",
    "iso:country":"CN",
    "name:zho_x_preferred":[
        "\u5927\u4f0d\u9f99"
    ],
    "wof:name":"Dawulong",
    "wof:placetype":"locality"
},
  "geometry": {"coordinates":[116.58629999999999,39.54383],"type":"Point"}
}