{
  "type": "Feature",
  "properties": {
    "gn:admin1_code":"25.0",
    "gn:asciiname":"Qian'ergou",
    "gn:cc2":"CN",
    "gn:country_code":"CN",
    "gn:dem":26,
    "gn:feature_class":"P",
    "gn:feature_code":"PPL",
    "gn:name":"Qian\u2019ergou",
    "gn:population":0,
    "gn:timezone":"Asia/Shanghai",
    "iso:country":"CN",
    "name:und_x_variant":[
        "Qian\u2019ergou"
    ],
    "name:zho_x_preferred":[
        "\u524d\u4e8c\u6c9f"
    ],
    "wof:name":"Qian'ergou",
    "wof:placetype":"locality"
},
  "geometry": {"coordinates":[120.03507,36.05943],"type":"Point"}
}