{
  "type": "Feature",
  "properties": {
    "gn:admin1_code":"29.0",
    "gn:asciiname":"Luchou Xinzhai",
    "gn:country_code":"CN",
    "gn:dem":1366,
    "gn:feature_class":"P",
    "gn:feature_code":"PPL",
    "gn:name":"Luchou Xinzhai",
    "gn:population":0,
    "gn:timezone":"Asia/Shanghai",
    "iso:country":"CN",
    "name:zho_x_preferred":[
        "\u8def\u916c\u65b0\u5be8"
    ],
    "wof:name":"Luchou Xinzhai",
    "wof:placetype":"locality"
},
  "geometry": {"coordinates":[104.39100000000001,24.3303],"type":"Point"}
}