{
  "type": "Feature",
  "properties": {
    "gn:admin1_code":"30.0",
    "gn:asciiname":"Cundongcun",
    "gn:country_code":"CN",
    "gn:dem":184,
    "gn:feature_class":"P",
    "gn:feature_code":"PPL",
    "gn:name":"Cundongcun",
    "gn:population":0,
    "gn:timezone":"Asia/Shanghai",
    "iso:country":"CN",
    "name:zho_x_preferred":[
        "\u6751\u4e1c\u6751"
    ],
    "wof:name":"Cundongcun",
    "wof:placetype":"locality"
},
  "geometry": {"coordinates":[116.35890000000001,24.61054],"type":"Point"}
}