{
  "type": "Feature",
  "properties": {
    "gn:admin1_code":"9.0",
    "gn:asciiname":"Nanzuo",
    "gn:country_code":"CN",
    "gn:dem":130,
    "gn:feature_class":"P",
    "gn:feature_code":"PPL",
    "gn:name":"Nanzuo",
    "gn:population":0,
    "gn:timezone":"Asia/Shanghai",
    "iso:country":"CN",
    "name:zho_x_preferred":[
        "\u5357\u4f5c"
    ],
    "wof:name":"Nanzuo",
    "wof:placetype":"locality"
},
  "geometry": {"coordinates":[112.83635,35.16277],"type":"Point"}
}