{
  "type": "Feature",
  "properties": {
    "gn:admin1_code":"32.0",
    "gn:asciiname":"Dapingshang",
    "gn:country_code":"CN",
    "gn:dem":1091,
    "gn:feature_class":"P",
    "gn:feature_code":"PPL",
    "gn:name":"Dapingshang",
    "gn:population":0,
    "gn:timezone":"Asia/Shanghai",
    "iso:country":"CN",
    "name:zho_x_preferred":[
        "\u5927\u576a\u4e0a"
    ],
    "wof:name":"Dapingshang",
    "wof:placetype":"locality"
},
  "geometry": {"coordinates":[103.12921,30.40815],"type":"Point"}
}