{
  "type": "Feature",
  "properties": {
    "gn:admin1_code":"12.0",
    "gn:asciiname":"Zhujia",
    "gn:country_code":"CN",
    "gn:dem":80,
    "gn:feature_class":"P",
    "gn:feature_code":"PPL",
    "gn:name":"Zhujia",
    "gn:population":0,
    "gn:timezone":"Asia/Shanghai",
    "iso:country":"CN",
    "name:zho_x_preferred":[
        "Zhujia"
    ],
    "name:zho_x_variant":[
        "\u795d\u5bb6"
    ],
    "wof:name":"Zhujia",
    "wof:placetype":"locality"
},
  "geometry": {"coordinates":[114.58042,29.62713],"type":"Point"}
}