{
  "type": "Feature",
  "properties": {
    "gn:admin1_code":"2.0",
    "gn:asciiname":"Shenjiawu",
    "gn:country_code":"CN",
    "gn:dem":96,
    "gn:feature_class":"P",
    "gn:feature_code":"PPL",
    "gn:name":"Shenjiawu",
    "gn:population":0,
    "gn:timezone":"Asia/Shanghai",
    "iso:country":"CN",
    "name:und_x_variant":[
        "\u6c88\u5bb6\u575e"
    ],
    "wof:name":"Shenjiawu",
    "wof:placetype":"locality"
},
  "geometry": {"coordinates":[119.91922,30.18002000000001],"type":"Point"}
}