{
  "type": "Feature",
  "properties": {
    "gn:admin1_code":"2.0",
    "gn:asciiname":"Jiesheng",
    "gn:country_code":"CN",
    "gn:dem":222,
    "gn:feature_class":"P",
    "gn:feature_code":"PPL",
    "gn:name":"Jiesheng",
    "gn:population":0,
    "gn:timezone":"Asia/Shanghai",
    "iso:country":"CN",
    "name:zho_x_preferred":[
        "\u63a5\u80dc"
    ],
    "wof:name":"Jiesheng",
    "wof:placetype":"locality"
},
  "geometry": {"coordinates":[121.31373000000001,29.90037],"type":"Point"}
}