{
  "type": "Feature",
  "properties": {
    "gn:admin1_code":"15.0",
    "gn:asciiname":"Xinjia Tunzhuang",
    "gn:country_code":"CN",
    "gn:dem":1416,
    "gn:feature_class":"P",
    "gn:feature_code":"PPL",
    "gn:name":"Xinjia Tunzhuang",
    "gn:population":0,
    "gn:timezone":"Asia/Shanghai",
    "iso:country":"CN",
    "name:zho_x_preferred":[
        "\u8f9b\u5bb6\u5c6f\u5e84"
    ],
    "wof:name":"Xinjia Tunzhuang",
    "wof:placetype":"locality"
},
  "geometry": {"coordinates":[100.34099999999999,39.1995],"type":"Point"}
}