{
  "type": "Feature",
  "properties": {
    "gn:admin1_code":"32.0",
    "gn:asciiname":"Longshiba",
    "gn:country_code":"CN",
    "gn:dem":855,
    "gn:feature_class":"P",
    "gn:feature_code":"PPL",
    "gn:name":"Longshiba",
    "gn:population":0,
    "gn:timezone":"Asia/Shanghai",
    "iso:country":"CN",
    "name:zho_x_preferred":[
        "\u9f99\u77f3\u575d"
    ],
    "wof:name":"Longshiba",
    "wof:placetype":"locality"
},
  "geometry": {"coordinates":[104.99299999999999,32.1098],"type":"Point"}
}