{
  "type": "Feature",
  "properties": {
    "gn:admin1_code":"22",
    "gn:asciiname":"Tongjunzhuang",
    "gn:country_code":"CN",
    "gn:dem":58,
    "gn:feature_class":"P",
    "gn:feature_code":"PPL",
    "gn:name":"Tongjunzhuang",
    "gn:population":0,
    "gn:timezone":"Asia/Shanghai",
    "iso:country":"CN",
    "name:und_x_variant":[
        "T\u2019ung-ch\u00fcn-chuang",
        "Tongjunzhuang"
    ],
    "name:zho_x_preferred":[
        "\u7edf\u519b\u5e84"
    ],
    "wof:name":"Tongjunzhuang",
    "wof:placetype":"locality"
},
  "geometry": {"coordinates":[116.7359,40.34186],"type":"Point"}
}