{
  "type": "Feature",
  "properties": {
    "gn:admin1_code":"29.0",
    "gn:asciiname":"Hanjiaying",
    "gn:country_code":"CN",
    "gn:dem":1906,
    "gn:feature_class":"P",
    "gn:feature_code":"PPL",
    "gn:name":"Hanjiaying",
    "gn:population":0,
    "gn:timezone":"Asia/Shanghai",
    "iso:country":"CN",
    "name:zho_x_preferred":[
        "\u97e9\u5bb6\u8425"
    ],
    "wof:name":"Hanjiaying",
    "wof:placetype":"locality"
},
  "geometry": {"coordinates":[103.673,27.3677],"type":"Point"}
}