{
  "type": "Feature",
  "properties": {
    "gn:admin1_code":"32.0",
    "gn:asciiname":"Dawodang",
    "gn:country_code":"CN",
    "gn:dem":2838,
    "gn:feature_class":"P",
    "gn:feature_code":"PPL",
    "gn:name":"Dawodang",
    "gn:population":0,
    "gn:timezone":"Asia/Shanghai",
    "iso:country":"CN",
    "name:zho_x_preferred":[
        "\u5927\u7a9d\u51fc"
    ],
    "wof:name":"Dawodang",
    "wof:placetype":"locality"
},
  "geometry": {"coordinates":[101.22,27.0016],"type":"Point"}
}