{
  "type": "Feature",
  "properties": {
    "gn:admin1_code":"5.0",
    "gn:asciiname":"Housanjiazicun",
    "gn:country_code":"CN",
    "gn:dem":175,
    "gn:feature_class":"P",
    "gn:feature_code":"PPL",
    "gn:name":"Housanjiazicun",
    "gn:population":0,
    "gn:timezone":"Asia/Shanghai",
    "iso:country":"CN",
    "name:zho_x_preferred":[
        "\u540e\u4e09\u5bb6\u5b50\u6751"
    ],
    "wof:name":"Housanjiazicun",
    "wof:placetype":"locality"
},
  "geometry": {"coordinates":[126.49276,44.20092],"type":"Point"}
}