{
  "type": "Feature",
  "properties": {
    "gn:admin1_code":"26.0",
    "gn:asciiname":"Houjia Goucun",
    "gn:country_code":"CN",
    "gn:dem":1057,
    "gn:feature_class":"P",
    "gn:feature_code":"PPL",
    "gn:name":"Houjia Goucun",
    "gn:population":0,
    "gn:timezone":"Asia/Shanghai",
    "iso:country":"CN",
    "name:zho_x_preferred":[
        "\u4faf\u5bb6\u6c9f\u6751"
    ],
    "wof:name":"Houjia Goucun",
    "wof:placetype":"locality"
},
  "geometry": {"coordinates":[110.37,37.756],"type":"Point"}
}