{
  "type": "Feature",
  "properties": {
    "gn:admin1_code":"25",
    "gn:asciiname":"Hegouchen",
    "gn:country_code":"CN",
    "gn:dem":25,
    "gn:feature_class":"P",
    "gn:feature_code":"PPL",
    "gn:name":"Hegouchen",
    "gn:population":0,
    "gn:timezone":"Asia/Shanghai",
    "iso:country":"CN",
    "name:zho_x_preferred":[
        "\u6cb3\u6c9f\u9648"
    ],
    "wof:name":"Hegouchen",
    "wof:placetype":"locality"
},
  "geometry": {"coordinates":[116.565,37.4878],"type":"Point"}
}