{
  "type": "Feature",
  "properties": {
    "gn:admin1_code":"7.0",
    "gn:asciiname":"Dali",
    "gn:country_code":"CN",
    "gn:dem":263,
    "gn:feature_class":"P",
    "gn:feature_code":"PPL",
    "gn:name":"Dali",
    "gn:population":0,
    "gn:timezone":"Asia/Shanghai",
    "iso:country":"CN",
    "name:zho_x_preferred":[
        "\u8fbe\u7406"
    ],
    "wof:name":"Dali",
    "wof:placetype":"locality"
},
  "geometry": {"coordinates":[118.12838000000001,25.32308],"type":"Point"}
}