{
  "type": "Feature",
  "properties": {
    "gn:admin1_code":"19.0",
    "gn:asciiname":"Quansheng",
    "gn:country_code":"CN",
    "gn:dem":36,
    "gn:feature_class":"P",
    "gn:feature_code":"PPL",
    "gn:name":"Quansheng",
    "gn:population":0,
    "gn:timezone":"Asia/Shanghai",
    "iso:country":"CN",
    "name:zho_x_preferred":[
        "\u5168\u80dc"
    ],
    "wof:name":"Quansheng",
    "wof:placetype":"locality"
},
  "geometry": {"coordinates":[123.20614,41.84346],"type":"Point"}
}