{
  "type": "Feature",
  "properties": {
    "gn:admin1_code":"11.0",
    "gn:asciiname":"Baishuxia",
    "gn:country_code":"CN",
    "gn:dem":127,
    "gn:feature_class":"P",
    "gn:feature_code":"PPL",
    "gn:name":"Baishuxia",
    "gn:population":0,
    "gn:timezone":"Asia/Shanghai",
    "iso:country":"CN",
    "name:zho_x_preferred":[
        "\u67cf\u6811\u4e0b"
    ],
    "wof:name":"Baishuxia",
    "wof:placetype":"locality"
},
  "geometry": {"coordinates":[113.67292999999999,28.53132],"type":"Point"}
}