{
  "type": "Feature",
  "properties": {
    "gn:admin1_code":"14",
    "gn:asciiname":"Quwada",
    "gn:country_code":"CN",
    "gn:dem":3857,
    "gn:feature_class":"P",
    "gn:feature_code":"PPL",
    "gn:name":"Quwada",
    "gn:population":0,
    "gn:timezone":"Asia/Urumqi",
    "iso:country":"CN",
    "name:zho_x_preferred":[
        "\u66f2\u74e6\u8fbe"
    ],
    "wof:name":"Quwada",
    "wof:placetype":"locality"
},
  "geometry": {"coordinates":[89.0309,29.3881],"type":"Point"}
}