{
  "type": "Feature",
  "properties": {
    "gn:admin1_code":"15.0",
    "gn:asciiname":"Dishuiya",
    "gn:country_code":"CN",
    "gn:dem":1447,
    "gn:feature_class":"P",
    "gn:feature_code":"PPL",
    "gn:name":"Dishuiya",
    "gn:population":0,
    "gn:timezone":"Asia/Shanghai",
    "iso:country":"CN",
    "name:zho_x_preferred":[
        "\u6ef4\u6c34\u5d16"
    ],
    "wof:name":"Dishuiya",
    "wof:placetype":"locality"
},
  "geometry": {"coordinates":[105.69,34.6219],"type":"Point"}
}