{
  "type": "Feature",
  "properties": {
    "gn:admin1_code":"19.0",
    "gn:asciiname":"Tangsengmiao",
    "gn:country_code":"CN",
    "gn:dem":106,
    "gn:feature_class":"P",
    "gn:feature_code":"PPL",
    "gn:name":"Tangsengmiao",
    "gn:population":0,
    "gn:timezone":"Asia/Shanghai",
    "iso:country":"CN",
    "name:zho_x_preferred":[
        "\u5510\u50e7\u5e99"
    ],
    "wof:name":"Tangsengmiao",
    "wof:placetype":"locality"
},
  "geometry": {"coordinates":[123.09003,42.69577],"type":"Point"}
}