{
  "type": "Feature",
  "properties": {
    "gn:admin1_code":"11.0",
    "gn:asciiname":"Shangfulandong",
    "gn:country_code":"CN",
    "gn:dem":842,
    "gn:feature_class":"P",
    "gn:feature_code":"PPL",
    "gn:name":"Shangfulandong",
    "gn:population":0,
    "gn:timezone":"Asia/Shanghai",
    "iso:country":"CN",
    "name:zho_x_preferred":[
        "\u4e0a\u8299\u5170\u6d1e"
    ],
    "wof:name":"Shangfulandong",
    "wof:placetype":"locality"
},
  "geometry": {"coordinates":[114.09363999999999,26.11247],"type":"Point"}
}