{
  "type": "Feature",
  "properties": {
    "gn:admin1_code":"29.0",
    "gn:asciiname":"Luopu",
    "gn:country_code":"CN",
    "gn:dem":1881,
    "gn:feature_class":"P",
    "gn:feature_code":"PPL",
    "gn:name":"Luopu",
    "gn:population":0,
    "gn:timezone":"Asia/Shanghai",
    "iso:country":"CN",
    "name:zho_x_preferred":[
        "\u6d1b\u6734"
    ],
    "wof:name":"Luopu",
    "wof:placetype":"locality"
},
  "geometry": {"coordinates":[102.31,23.2338],"type":"Point"}
}