{
  "type": "Feature",
  "properties": {
    "gn:admin1_code":"29",
    "gn:asciiname":"Xiuxi",
    "gn:country_code":"CN",
    "gn:dem":1821,
    "gn:feature_class":"P",
    "gn:feature_code":"PPL",
    "gn:name":"Xiuxi",
    "gn:population":0,
    "gn:timezone":"Asia/Shanghai",
    "iso:country":"CN",
    "name:zho_x_preferred":[
        "\u79c0\u6eaa"
    ],
    "wof:name":"Xiuxi",
    "wof:placetype":"locality"
},
  "geometry": {"coordinates":[102.42100000000001,24.3306],"type":"Point"}
}