{
  "type": "Feature",
  "properties": {
    "gn:admin1_code":"29.0",
    "gn:asciiname":"Xiaoping",
    "gn:country_code":"CN",
    "gn:dem":1944,
    "gn:feature_class":"P",
    "gn:feature_code":"PPL",
    "gn:name":"Xiaoping",
    "gn:population":0,
    "gn:timezone":"Asia/Shanghai",
    "iso:country":"CN",
    "name:zho_x_preferred":[
        "\u5c0f\u576a"
    ],
    "wof:name":"Xiaoping",
    "wof:placetype":"locality"
},
  "geometry": {"coordinates":[101.009,26.2904],"type":"Point"}
}