{
  "type": "Feature",
  "properties": {
    "gn:admin1_code":"10.0",
    "gn:asciiname":"Dongzhenzhuang",
    "gn:country_code":"CN",
    "gn:dem":45,
    "gn:feature_class":"P",
    "gn:feature_code":"PPL",
    "gn:name":"Dongzhenzhuang",
    "gn:population":0,
    "gn:timezone":"Asia/Shanghai",
    "iso:country":"CN",
    "name:zho_x_preferred":[
        "\u4e1c\u7504\u5e84"
    ],
    "wof:name":"Dongzhenzhuang",
    "wof:placetype":"locality"
},
  "geometry": {"coordinates":[118.65448000000001,39.72493],"type":"Point"}
}