{
  "type": "Feature",
  "properties": {
    "gn:admin1_code":"07",
    "gn:asciiname":"Meiyang",
    "gn:country_code":"CN",
    "gn:dem":981,
    "gn:feature_class":"P",
    "gn:feature_code":"PPL",
    "gn:name":"Meiyang",
    "gn:population":0,
    "gn:timezone":"Asia/Shanghai",
    "iso:country":"CN",
    "name:zho_x_preferred":[
        "\u7f8e\u9633"
    ],
    "wof:name":"Meiyang",
    "wof:placetype":"locality"
},
  "geometry": {"coordinates":[117.90555999999999,25.59972],"type":"Point"}
}