{
  "type": "Feature",
  "properties": {
    "gn:admin1_code":"30.0",
    "gn:asciiname":"Gantaoping",
    "gn:country_code":"CN",
    "gn:dem":214,
    "gn:feature_class":"P",
    "gn:feature_code":"PPL",
    "gn:name":"Gantaoping",
    "gn:population":0,
    "gn:timezone":"Asia/Shanghai",
    "iso:country":"CN",
    "name:zho_x_preferred":[
        "\u7518\u6843\u576a"
    ],
    "wof:name":"Gantaoping",
    "wof:placetype":"locality"
},
  "geometry": {"coordinates":[111.45984,22.49845],"type":"Point"}
}