{
  "type": "Feature",
  "properties": {
    "gn:admin1_code":"29",
    "gn:asciiname":"Songlin",
    "gn:country_code":"CN",
    "gn:dem":1945,
    "gn:feature_class":"P",
    "gn:feature_code":"PPL",
    "gn:name":"Songlin",
    "gn:population":0,
    "gn:timezone":"Asia/Shanghai",
    "iso:country":"CN",
    "name:und_x_variant":[
        "Sung-lin",
        "Songlin",
        "\u677e\u6797"
    ],
    "wof:name":"Songlin",
    "wof:placetype":"locality"
},
  "geometry": {"coordinates":[103.845,25.6939],"type":"Point"}
}