{
  "type": "Feature",
  "properties": {
    "gn:admin1_code":"18",
    "gn:asciiname":"Xiaohebian",
    "gn:country_code":"CN",
    "gn:dem":1914,
    "gn:feature_class":"P",
    "gn:feature_code":"PPL",
    "gn:name":"Xiaohebian",
    "gn:population":0,
    "gn:timezone":"Asia/Shanghai",
    "iso:country":"CN",
    "name:zho_x_preferred":[
        "\u5c0f\u6cb3\u8fb9"
    ],
    "wof:name":"Xiaohebian",
    "wof:placetype":"locality"
},
  "geometry": {"coordinates":[104.864,26.9086],"type":"Point"}
}