{
  "type": "Feature",
  "properties": {
    "gn:admin1_code":"32.0",
    "gn:asciiname":"Panzhihua",
    "gn:country_code":"CN",
    "gn:dem":1101,
    "gn:feature_class":"P",
    "gn:feature_code":"PPLA3",
    "gn:name":"Panzhihua",
    "gn:population":0,
    "gn:timezone":"Asia/Shanghai",
    "iso:country":"CN",
    "name:zho_x_preferred":[
        "\u6500\u679d\u82b1"
    ],
    "wof:name":"Panzhihua",
    "wof:placetype":"locality"
},
  "geometry": {"coordinates":[101.71276,26.58509],"type":"Point"}
}