{
  "type": "Feature",
  "properties": {
    "gn:admin1_code":"26.0",
    "gn:asciiname":"Chigancun",
    "gn:country_code":"CN",
    "gn:dem":925,
    "gn:feature_class":"P",
    "gn:feature_code":"PPL",
    "gn:name":"Chigancun",
    "gn:population":0,
    "gn:timezone":"Asia/Shanghai",
    "iso:country":"CN",
    "name:zho_x_preferred":[
        "\u53f1\u5e72\u6751"
    ],
    "wof:name":"Chigancun",
    "wof:placetype":"locality"
},
  "geometry": {"coordinates":[110.23269000000001,36.21987],"type":"Point"}
}