{
  "type": "Feature",
  "properties": {
    "gn:admin1_code":"14.0",
    "gn:asciiname":"Wangxi",
    "gn:country_code":"CN",
    "gn:dem":4206,
    "gn:feature_class":"P",
    "gn:feature_code":"PPLF",
    "gn:name":"Wangxi",
    "gn:population":0,
    "gn:timezone":"Asia/Urumqi",
    "iso:country":"CN",
    "name:bod_x_preferred":[
        "Wangxi"
    ],
    "name:zho_x_preferred":[
        "\u65fa\u897f"
    ],
    "wof:name":"Wangxi",
    "wof:placetype":"locality"
},
  "geometry": {"coordinates":[96.101,30.701],"type":"Point"}
}