{
  "type": "Feature",
  "properties": {
    "gn:admin1_code":"3.0",
    "gn:asciiname":"Dukeng",
    "gn:country_code":"CN",
    "gn:dem":396,
    "gn:feature_class":"P",
    "gn:feature_code":"PPL",
    "gn:name":"Dukeng",
    "gn:population":0,
    "gn:timezone":"Asia/Shanghai",
    "iso:country":"CN",
    "name:und_x_variant":[
        "\u6e21\u5751"
    ],
    "wof:name":"Dukeng",
    "wof:placetype":"locality"
},
  "geometry": {"coordinates":[114.77578,24.72451],"type":"Point"}
}