{
  "type": "Feature",
  "properties": {
    "gn:admin1_code":"3.0",
    "gn:asciiname":"Tangqiaocun",
    "gn:country_code":"CN",
    "gn:dem":21,
    "gn:feature_class":"P",
    "gn:feature_code":"PPL",
    "gn:name":"Tangqiaocun",
    "gn:population":0,
    "gn:timezone":"Asia/Shanghai",
    "iso:country":"CN",
    "name:und_x_variant":[
        "\u6c64\u6865\u6751"
    ],
    "wof:name":"Tangqiaocun",
    "wof:placetype":"locality"
},
  "geometry": {"coordinates":[115.71628,28.38751],"type":"Point"}
}