{
  "type": "Feature",
  "properties": {
    "gn:admin1_code":"25",
    "gn:asciiname":"Houmiaozhuang",
    "gn:country_code":"CN",
    "gn:dem":52,
    "gn:feature_class":"P",
    "gn:feature_code":"PPL",
    "gn:name":"Houmiaozhuang",
    "gn:population":0,
    "gn:timezone":"Asia/Shanghai",
    "iso:country":"CN",
    "name:zho_x_preferred":[
        "\u540e\u82d7\u5e84"
    ],
    "wof:name":"Houmiaozhuang",
    "wof:placetype":"locality"
},
  "geometry": {"coordinates":[115.639,34.8967],"type":"Point"}
}