{
  "type": "Feature",
  "properties": {
    "gn:admin1_code":"2.0",
    "gn:asciiname":"Wanglouting",
    "gn:country_code":"CN",
    "gn:dem":376,
    "gn:feature_class":"P",
    "gn:feature_code":"PPL",
    "gn:name":"Wanglouting",
    "gn:population":0,
    "gn:timezone":"Asia/Shanghai",
    "iso:country":"CN",
    "name:zho_x_preferred":[
        "\u671b\u697c\u4ead"
    ],
    "wof:name":"Wanglouting",
    "wof:placetype":"locality"
},
  "geometry": {"coordinates":[119.90737,27.56433],"type":"Point"}
}