{
  "type": "Feature",
  "properties": {
    "gn:admin1_code":"30.0",
    "gn:asciiname":"Chadong",
    "gn:country_code":"CN",
    "gn:dem":620,
    "gn:feature_class":"P",
    "gn:feature_code":"PPL",
    "gn:name":"Chadong",
    "gn:population":0,
    "gn:timezone":"Asia/Shanghai",
    "iso:country":"CN",
    "name:zho_x_preferred":[
        "Chadong"
    ],
    "name:zho_x_variant":[
        "\u8336\u6d1e"
    ],
    "wof:name":"Chadong",
    "wof:placetype":"locality"
},
  "geometry": {"coordinates":[112.97701000000001,24.69057],"type":"Point"}
}