{
  "type": "Feature",
  "properties": {
    "gn:admin1_code":"16.0",
    "gn:asciiname":"Heichong",
    "gn:country_code":"CN",
    "gn:dem":880,
    "gn:feature_class":"P",
    "gn:feature_code":"PPL",
    "gn:name":"Heichong",
    "gn:population":0,
    "gn:timezone":"Asia/Shanghai",
    "iso:country":"CN",
    "name:zho_x_preferred":[
        "\u9ed1\u51b2"
    ],
    "wof:name":"Heichong",
    "wof:placetype":"locality"
},
  "geometry": {"coordinates":[111.081,24.7344],"type":"Point"}
}