{
  "type": "Feature",
  "properties": {
    "gn:admin1_code":"32.0",
    "gn:asciiname":"Kongxi",
    "gn:country_code":"CN",
    "gn:dem":780,
    "gn:feature_class":"P",
    "gn:feature_code":"PPL",
    "gn:name":"Kongxi",
    "gn:population":0,
    "gn:timezone":"Asia/Shanghai",
    "iso:country":"CN",
    "name:zho_x_preferred":[
        "\u5b54\u6eaa"
    ],
    "wof:name":"Kongxi",
    "wof:placetype":"locality"
},
  "geometry": {"coordinates":[105.27106999999999,32.5962],"type":"Point"}
}