{
  "type": "Feature",
  "properties": {
    "gn:admin1_code":"25.0",
    "gn:asciiname":"Changqingcun",
    "gn:country_code":"CN",
    "gn:dem":56,
    "gn:feature_class":"P",
    "gn:feature_code":"PPL",
    "gn:name":"Changqingcun",
    "gn:population":0,
    "gn:timezone":"Asia/Shanghai",
    "iso:country":"CN",
    "name:zho_x_preferred":[
        "\u957f\u6e05\u6751"
    ],
    "wof:name":"Changqingcun",
    "wof:placetype":"locality"
},
  "geometry": {"coordinates":[120.44495999999999,36.85289],"type":"Point"}
}