{
  "type": "Feature",
  "properties": {
    "gn:admin1_code":"19.0",
    "gn:asciiname":"Gongjialu",
    "gn:country_code":"CN",
    "gn:dem":383,
    "gn:feature_class":"P",
    "gn:feature_code":"PPL",
    "gn:name":"Gongjialu",
    "gn:population":0,
    "gn:timezone":"Asia/Shanghai",
    "iso:country":"CN",
    "name:zho_x_preferred":[
        "\u5bab\u5bb6\u7089"
    ],
    "wof:name":"Gongjialu",
    "wof:placetype":"locality"
},
  "geometry": {"coordinates":[122.298,39.9562],"type":"Point"}
}