{
  "type": "Feature",
  "properties": {
    "gn:admin1_code":"19.0",
    "gn:asciiname":"Congshengcun",
    "gn:country_code":"CN",
    "gn:dem":126,
    "gn:feature_class":"P",
    "gn:feature_code":"PPL",
    "gn:name":"Congshengcun",
    "gn:population":0,
    "gn:timezone":"Asia/Shanghai",
    "iso:country":"CN",
    "name:zho_x_preferred":[
        "\u4e1b\u751f\u6751"
    ],
    "wof:name":"Congshengcun",
    "wof:placetype":"locality"
},
  "geometry": {"coordinates":[123.73501,42.7671],"type":"Point"}
}