{
  "type": "Feature",
  "properties": {
    "gn:admin1_code":"14",
    "gn:asciiname":"Menzhuo",
    "gn:country_code":"CN",
    "gn:dem":3981,
    "gn:feature_class":"P",
    "gn:feature_code":"PPL",
    "gn:name":"Menzhuo",
    "gn:population":0,
    "gn:timezone":"Asia/Urumqi",
    "iso:country":"CN",
    "name:zho_x_preferred":[
        "\u95f7\u5353"
    ],
    "wof:name":"Menzhuo",
    "wof:placetype":"locality"
},
  "geometry": {"coordinates":[89.5142,29.117],"type":"Point"}
}