{
  "type": "Feature",
  "properties": {
    "gn:admin1_code":"12.0",
    "gn:asciiname":"Minjiahe",
    "gn:country_code":"CN",
    "gn:dem":127,
    "gn:feature_class":"P",
    "gn:feature_code":"PPL",
    "gn:name":"Minjiahe",
    "gn:population":0,
    "gn:timezone":"Asia/Shanghai",
    "iso:country":"CN",
    "name:zho_x_preferred":[
        "\u95f5\u5bb6\u6cb3"
    ],
    "wof:name":"Minjiahe",
    "wof:placetype":"locality"
},
  "geometry": {"coordinates":[115.58704,30.65072],"type":"Point"}
}