{
  "type": "Feature",
  "properties": {
    "gn:admin1_code":"1.0",
    "gn:asciiname":"Haoguangcun",
    "gn:country_code":"CN",
    "gn:dem":21,
    "gn:feature_class":"P",
    "gn:feature_code":"PPL",
    "gn:name":"Haoguangcun",
    "gn:population":0,
    "gn:timezone":"Asia/Shanghai",
    "iso:country":"CN",
    "name:zho_x_preferred":[
        "\u6fe0\u5149\u6751"
    ],
    "wof:name":"Haoguangcun",
    "wof:placetype":"locality"
},
  "geometry": {"coordinates":[117.64637999999999,32.89933],"type":"Point"}
}