{
  "type": "Feature",
  "properties": {
    "gn:admin1_code":"3",
    "gn:asciiname":"Nanchangshixinfengzonghekenzhichang",
    "gn:country_code":"CN",
    "gn:dem":40,
    "gn:feature_class":"P",
    "gn:feature_code":"PPL",
    "gn:name":"Nanchangshixinfengzonghekenzhichang",
    "gn:population":0,
    "gn:timezone":"Asia/Shanghai",
    "iso:country":"CN",
    "wof:name":"Nanchangshixinfengzonghekenzhichang",
    "wof:placetype":"locality"
},
  "geometry": {"coordinates":[115.65389,28.57583],"type":"Point"}
}