{
  "type": "Feature",
  "properties": {
    "gn:admin1_code":"9.0",
    "gn:asciiname":"Lianggou",
    "gn:country_code":"CN",
    "gn:dem":248,
    "gn:feature_class":"P",
    "gn:feature_code":"PPL",
    "gn:name":"Lianggou",
    "gn:population":0,
    "gn:timezone":"Asia/Shanghai",
    "iso:country":"CN",
    "name:zho_x_preferred":[
        "\u6881\u6c9f"
    ],
    "wof:name":"Lianggou",
    "wof:placetype":"locality"
},
  "geometry": {"coordinates":[113.40963000000001,34.65192],"type":"Point"}
}