{
  "type": "Feature",
  "properties": {
    "gn:admin1_code":"26.0",
    "gn:asciiname":"Chenzhuangze",
    "gn:country_code":"CN",
    "gn:dem":1191,
    "gn:feature_class":"P",
    "gn:feature_code":"PPL",
    "gn:name":"Chenzhuangze",
    "gn:population":0,
    "gn:timezone":"Asia/Shanghai",
    "iso:country":"CN",
    "name:zho_x_preferred":[
        "\u9648\u5e84\u5219"
    ],
    "wof:name":"Chenzhuangze",
    "wof:placetype":"locality"
},
  "geometry": {"coordinates":[110.80158,39.10023],"type":"Point"}
}