{
  "type": "Feature",
  "properties": {
    "gn:admin1_code":"04",
    "gn:asciiname":"Gangkou",
    "gn:country_code":"CN",
    "gn:dem":6,
    "gn:feature_class":"P",
    "gn:feature_code":"PPL",
    "gn:name":"Gangkou",
    "gn:population":0,
    "gn:timezone":"Asia/Shanghai",
    "iso:country":"CN",
    "name:deu_x_preferred":[
        "Gangkou"
    ],
    "name:nor_x_preferred":[
        "Gangkou"
    ],
    "name:und_x_variant":[
        "Chiang-k\u2019ou",
        "Kang-k\u2019ou-chen",
        "Chiang-k\u2019ou-chen",
        "Gangkouzhen"
    ],
    "wof:name":"Gangkou",
    "wof:placetype":"locality"
},
  "geometry": {"coordinates":[120.66779,31.75598],"type":"Point"}
}