{
  "type": "Feature",
  "properties": {
    "gn:admin1_code":"32.0",
    "gn:asciiname":"Yifoshan",
    "gn:country_code":"CN",
    "gn:dem":1228,
    "gn:feature_class":"P",
    "gn:feature_code":"PPL",
    "gn:name":"Yifoshan",
    "gn:population":0,
    "gn:timezone":"Asia/Shanghai",
    "iso:country":"CN",
    "name:zho_x_preferred":[
        "\u4e49\u4f5b\u5c71"
    ],
    "wof:name":"Yifoshan",
    "wof:placetype":"locality"
},
  "geometry": {"coordinates":[104.48699999999999,32.3931],"type":"Point"}
}