{
  "type": "Feature",
  "properties": {
    "gn:admin1_code":"2.0",
    "gn:asciiname":"Baojia Shanhou",
    "gn:country_code":"CN",
    "gn:dem":12,
    "gn:feature_class":"P",
    "gn:feature_code":"PPL",
    "gn:name":"Baojia Shanhou",
    "gn:population":0,
    "gn:timezone":"Asia/Shanghai",
    "iso:country":"CN",
    "name:zho_x_preferred":[
        "\u4fdd\u9a7e\u5c71\u540e"
    ],
    "wof:name":"Baojia Shanhou",
    "wof:placetype":"locality"
},
  "geometry": {"coordinates":[120.78055000000001,29.99563],"type":"Point"}
}