{
  "type": "Feature",
  "properties": {
    "gn:admin1_code":"10",
    "gn:asciiname":"Hubanying",
    "gn:country_code":"CN",
    "gn:dem":760,
    "gn:feature_class":"P",
    "gn:feature_code":"PPL",
    "gn:name":"Hubanying",
    "gn:population":0,
    "gn:timezone":"Asia/Shanghai",
    "iso:country":"CN",
    "name:zho_x_preferred":[
        "\u864e\u73ed\u8425"
    ],
    "wof:name":"Hubanying",
    "wof:placetype":"locality"
},
  "geometry": {"coordinates":[116.57464,41.30622],"type":"Point"}
}