{
  "type": "Feature",
  "properties": {
    "gn:admin1_code":"19.0",
    "gn:asciiname":"Dianzi",
    "gn:country_code":"CN",
    "gn:dem":10,
    "gn:feature_class":"P",
    "gn:feature_code":"PPL",
    "gn:name":"Dianzi",
    "gn:population":0,
    "gn:timezone":"Asia/Shanghai",
    "iso:country":"CN",
    "name:und_x_variant":[
        "\u7538\u5b50"
    ],
    "name:zho_x_preferred":[
        "\u7538\u5b50"
    ],
    "wof:name":"Dianzi",
    "wof:placetype":"locality"
},
  "geometry": {"coordinates":[121.76617,39.84274],"type":"Point"}
}