{
  "type": "Feature",
  "properties": {
    "gn:admin1_code":"32.0",
    "gn:asciiname":"Wujia",
    "gn:country_code":"CN",
    "gn:dem":305,
    "gn:feature_class":"P",
    "gn:feature_code":"PPL",
    "gn:name":"Wujia",
    "gn:population":0,
    "gn:timezone":"Asia/Shanghai",
    "iso:country":"CN",
    "name:ara_x_preferred":[
        "\u0648\u0648\u062c\u064a\u0627"
    ],
    "name:ben_x_preferred":[
        "\u0989\u099c\u09bf\u09af\u09bc\u09be"
    ],
    "name:deu_x_preferred":[
        "Wujia"
    ],
    "name:ell_x_preferred":[
        "\u039f\u03c5\u03b9\u03c4\u03b6\u03af\u03b1"
    ],
    "name:fas_x_preferred":[
        "\u0648\u0648\u062c\u06cc\u0627"
    ],
    "name:fra_x_preferred":[
        "Wujia"
    ],
    "name:heb_x_preferred":[
        "\u05d5\u05d5\u05d2'\u05d9\u05d4"
    ],
    "name:hin_x_preferred":[
        "\u0935\u0941\u091c\u093f\u092f\u093e"
    ],
    "name:hun_x_preferred":[
        "Wujia"
    ],
    "name:ind_x_preferred":[
        "Wujia"
    ],
    "name:ita_x_preferred":[
        "Wujia"
    ],
    "name:jpn_x_preferred":[
        "\u30a6\u30fc\u30b8\u30e3\u5ddd"
    ],
    "name:kor_x_preferred":[
        "\uc6b0\uc790"
    ],
    "name:nld_x_preferred":[
        "Wujia"
    ],
    "name:pol_x_preferred":[
        "Wujia"
    ],
    "name:por_x_preferred":[
        "Wujia"
    ],
    "name:rus_x_preferred":[
        "\u043e\u0437\u0435\u0440\u043e \u0423\u0446\u0437\u044f"
    ],
    "name:spa_x_preferred":[
        "Wujia"
    ],
    "name:swe_x_preferred":[
        "Wujia"
    ],
    "name:tur_x_preferred":[
        "Wujia"
    ],
    "name:ukr_x_preferred":[
        "\u0412\u0443\u0434\u0436\u0430"
    ],
    "name:urd_x_preferred":[
        "\u0648\u0648\u062c\u06cc\u0627"
    ],
    "name:vie_x_preferred":[
        "S\u00f4ng \u00d4 Gia"
    ],
    "name:zho_cn_x_preferred":[
        "\u4e4c\u52a0\u6cb3"
    ],
    "name:zho_tw_x_preferred":[
        "\u5433\u5bb6\u6cb3"
    ],
    "name:zho_x_preferred":[
        "\u4e94\u7532"
    ],
    "wof:name":"Wujia",
    "wof:placetype":"locality"
},
  "geometry": {"coordinates":[105.236,29.0871],"type":"Point"}
}