{
  "type": "Feature",
  "properties": {
    "gn:admin1_code":"10",
    "gn:asciiname":"Futujiang",
    "gn:cc2":"CN",
    "gn:country_code":"CN",
    "gn:dem":900,
    "gn:feature_class":"P",
    "gn:feature_code":"PPL",
    "gn:name":"Futujiang",
    "gn:population":0,
    "gn:timezone":"Asia/Shanghai",
    "iso:country":"CN",
    "name:und_x_variant":[
        "Fou-t\u2019u-kou",
        "Futujiang"
    ],
    "wof:name":"Futujiang",
    "wof:placetype":"locality"
},
  "geometry": {"coordinates":[114.35193999999998,40.08694000000001],"type":"Point"}
}