{
  "type": "Feature",
  "properties": {
    "gn:admin1_code":"4.0",
    "gn:asciiname":"Dianwangzhuang",
    "gn:country_code":"CN",
    "gn:dem":1,
    "gn:feature_class":"P",
    "gn:feature_code":"PPL",
    "gn:name":"Dianwangzhuang",
    "gn:population":0,
    "gn:timezone":"Asia/Shanghai",
    "iso:country":"CN",
    "name:zho_x_preferred":[
        "\u6bbf\u738b\u5e84"
    ],
    "wof:name":"Dianwangzhuang",
    "wof:placetype":"locality"
},
  "geometry": {"coordinates":[120.07138,33.20952],"type":"Point"}
}