{
  "type": "Feature",
  "properties": {
    "gn:admin1_code":"18",
    "gn:asciiname":"Shuikousi",
    "gn:country_code":"CN",
    "gn:dem":792,
    "gn:feature_class":"P",
    "gn:feature_code":"PPL",
    "gn:name":"Shuikousi",
    "gn:population":0,
    "gn:timezone":"Asia/Shanghai",
    "iso:country":"CN",
    "name:und_x_variant":[
        "Shui-k\u2019ou-ssu",
        "Shuikousi"
    ],
    "name:zho_x_preferred":[
        "\u6c34\u53e3\u5bfa"
    ],
    "wof:name":"Shuikousi",
    "wof:placetype":"locality"
},
  "geometry": {"coordinates":[106.355,27.7729],"type":"Point"}
}