{
  "type": "Feature",
  "properties": {
    "gn:admin1_code":"3.0",
    "gn:asciiname":"Guhou",
    "gn:country_code":"CN",
    "gn:dem":215,
    "gn:feature_class":"P",
    "gn:feature_code":"PPLA4",
    "gn:name":"Guhou",
    "gn:population":0,
    "gn:timezone":"Asia/Shanghai",
    "iso:country":"CN",
    "name:und_x_variant":[
        "\u56fa\u539a",
        "Guhou Xiang",
        "\u56fa\u539a\u4e61"
    ],
    "wof:name":"Guhou",
    "wof:placetype":"locality"
},
  "geometry": {"coordinates":[116.10997999999999,26.34618],"type":"Point"}
}