{
  "type": "Feature",
  "properties": {
    "gn:admin1_code":"9.0",
    "gn:asciiname":"Beixiyang",
    "gn:country_code":"CN",
    "gn:dem":596,
    "gn:feature_class":"P",
    "gn:feature_code":"PPL",
    "gn:name":"Beixiyang",
    "gn:population":0,
    "gn:timezone":"Asia/Shanghai",
    "iso:country":"CN",
    "name:zho_x_preferred":[
        "\u5317\u897f\u9633"
    ],
    "wof:name":"Beixiyang",
    "wof:placetype":"locality"
},
  "geometry": {"coordinates":[111.7985,34.78883],"type":"Point"}
}