{
  "type": "Feature",
  "properties": {
    "gn:admin1_code":"19.0",
    "gn:asciiname":"Laojinchang",
    "gn:country_code":"CN",
    "gn:dem":258,
    "gn:feature_class":"P",
    "gn:feature_code":"PPL",
    "gn:name":"Laojinchang",
    "gn:population":0,
    "gn:timezone":"Asia/Shanghai",
    "iso:country":"CN",
    "name:zho_x_preferred":[
        "\u8001\u91d1\u5382"
    ],
    "wof:name":"Laojinchang",
    "wof:placetype":"locality"
},
  "geometry": {"coordinates":[124.00502,40.97112],"type":"Point"}
}