{
  "type": "Feature",
  "properties": {
    "gn:admin1_code":"1.0",
    "gn:asciiname":"Zhouwuji",
    "gn:country_code":"CN",
    "gn:dem":8,
    "gn:feature_class":"P",
    "gn:feature_code":"PPL",
    "gn:name":"Zhouwuji",
    "gn:population":0,
    "gn:timezone":"Asia/Shanghai",
    "iso:country":"CN",
    "name:zho_x_preferred":[
        "\u5468\u5c4b\u57fa"
    ],
    "wof:name":"Zhouwuji",
    "wof:placetype":"locality"
},
  "geometry": {"coordinates":[118.55767,31.28969],"type":"Point"}
}