{
  "type": "Feature",
  "properties": {
    "gn:admin1_code":"5.0",
    "gn:asciiname":"Weilushancun",
    "gn:country_code":"CN",
    "gn:dem":238,
    "gn:feature_class":"P",
    "gn:feature_code":"PPL",
    "gn:name":"Weilushancun",
    "gn:population":0,
    "gn:timezone":"Asia/Shanghai",
    "iso:country":"CN",
    "name:zho_x_preferred":[
        "\u82c7\u82a6\u5c71\u6751"
    ],
    "wof:name":"Weilushancun",
    "wof:placetype":"locality"
},
  "geometry": {"coordinates":[124.74697999999999,44.74861],"type":"Point"}
}