{
  "type": "Feature",
  "properties": {
    "gn:admin1_code":"29",
    "gn:asciiname":"Aozeli",
    "gn:country_code":"CN",
    "gn:dem":1545,
    "gn:feature_class":"P",
    "gn:feature_code":"PPL",
    "gn:name":"Aozeli",
    "gn:population":0,
    "gn:timezone":"Asia/Shanghai",
    "iso:country":"CN",
    "name:zho_x_preferred":[
        "\u51f9\u5219\u529b"
    ],
    "wof:name":"Aozeli",
    "wof:placetype":"locality"
},
  "geometry": {"coordinates":[101.783,24.7176],"type":"Point"}
}