{
  "type": "Feature",
  "properties": {
    "gn:admin1_code":"26",
    "gn:asciiname":"Nanningtou",
    "gn:country_code":"CN",
    "gn:dem":966,
    "gn:feature_class":"P",
    "gn:feature_code":"PPL",
    "gn:name":"Nanningtou",
    "gn:population":0,
    "gn:timezone":"Asia/Shanghai",
    "iso:country":"CN",
    "name:und_x_variant":[
        "\u5357\u5b81\u5934"
    ],
    "name:zho_x_preferred":[
        "\u5357\u5b81\u5934"
    ],
    "wof:name":"Nanningtou",
    "wof:placetype":"locality"
},
  "geometry": {"coordinates":[108.38694,34.69],"type":"Point"}
}