{
  "type": "Feature",
  "properties": {
    "gn:admin1_code":"2.0",
    "gn:asciiname":"Xinjiang",
    "gn:country_code":"CN",
    "gn:dem":9,
    "gn:feature_class":"P",
    "gn:feature_code":"PPL",
    "gn:name":"Xinjiang",
    "gn:population":0,
    "gn:timezone":"Asia/Shanghai",
    "iso:country":"CN",
    "name:und_x_variant":[
        "\u8f9b\u6c5f"
    ],
    "wof:name":"Xinjiang",
    "wof:placetype":"locality"
},
  "geometry": {"coordinates":[120.44325000000001,30.46809],"type":"Point"}
}