{
  "type": "Feature",
  "properties": {
    "gn:admin1_code":"4.0",
    "gn:asciiname":"Laozhuangtou Dongdai",
    "gn:country_code":"CN",
    "gn:dem":7,
    "gn:feature_class":"P",
    "gn:feature_code":"PPL",
    "gn:name":"Laozhuangtou Dongdai",
    "gn:population":0,
    "gn:timezone":"Asia/Shanghai",
    "iso:country":"CN",
    "name:und_x_variant":[
        "\u8001\u5e84\u5934\u4e1c\u5788"
    ],
    "name:zho_x_preferred":[
        "\u8001\u5e84\u5934\u4e1c\u5788"
    ],
    "wof:name":"Laozhuangtou Dongdai",
    "wof:placetype":"locality"
},
  "geometry": {"coordinates":[120.23763,32.21108],"type":"Point"}
}