{
  "type": "Feature",
  "properties": {
    "gn:admin1_code":"25",
    "gn:asciiname":"Sangzidian",
    "gn:cc2":"CN",
    "gn:country_code":"CN",
    "gn:dem":25,
    "gn:feature_class":"P",
    "gn:feature_code":"PPL",
    "gn:name":"Sangzidian",
    "gn:population":0,
    "gn:timezone":"Asia/Shanghai",
    "iso:country":"CN",
    "name:und_x_variant":[
        "Sang-tzu-tien",
        "Sangzidian"
    ],
    "wof:name":"Sangzidian",
    "wof:placetype":"locality"
},
  "geometry": {"coordinates":[116.90694000000001,36.785],"type":"Point"}
}