{
  "type": "Feature",
  "properties": {
    "gn:admin1_code":"32.0",
    "gn:asciiname":"Jieshiwan",
    "gn:country_code":"CN",
    "gn:dem":631,
    "gn:feature_class":"P",
    "gn:feature_code":"PPL",
    "gn:name":"Jieshiwan",
    "gn:population":0,
    "gn:timezone":"Asia/Shanghai",
    "iso:country":"CN",
    "name:zho_x_preferred":[
        "\u754c\u77f3\u6e7e"
    ],
    "wof:name":"Jieshiwan",
    "wof:placetype":"locality"
},
  "geometry": {"coordinates":[107.56535,31.34711],"type":"Point"}
}