{
  "type": "Feature",
  "properties": {
    "gn:admin1_code":"19.0",
    "gn:asciiname":"Wofengtu",
    "gn:country_code":"CN",
    "gn:dem":394,
    "gn:feature_class":"P",
    "gn:feature_code":"PPL",
    "gn:name":"Wofengtu",
    "gn:population":0,
    "gn:timezone":"Asia/Shanghai",
    "iso:country":"CN",
    "name:und_x_variant":[
        "\u5367\u98ce\u571f"
    ],
    "name:zho_x_preferred":[
        "\u5367\u98ce\u571f"
    ],
    "wof:name":"Wofengtu",
    "wof:placetype":"locality"
},
  "geometry": {"coordinates":[121.29205,42.37166],"type":"Point"}
}