{
  "type": "Feature",
  "properties": {
    "gn:admin1_code":"06",
    "gn:asciiname":"Gabasumdo",
    "gn:country_code":"CN",
    "gn:dem":3113,
    "gn:feature_class":"P",
    "gn:feature_code":"PPLA3",
    "gn:name":"Gabasumdo",
    "gn:population":0,
    "gn:timezone":"Asia/Shanghai",
    "iso:country":"CN",
    "name:bod_x_preferred":[
        "Gabasumdo"
    ],
    "name:und_x_variant":[
        "Ya-pa-sung-tu",
        "Tongde",
        "T\u2019ung-te",
        "Lo-pa-sung-tu",
        "Ka-pa-sung-tu",
        "Gabasongduo",
        "\u5c15\u5df4\u677e\u591a",
        "Gabasongduo Zhen",
        "Tongde Xian"
    ],
    "name:zho_x_preferred":[
        "\u5c15\u5df4\u677e\u591a\u9547"
    ],
    "name:zho_x_variant":[
        "\u540c\u5fb7",
        "\u540c\u5fb7\u53bf"
    ],
    "wof:name":"Gabasumdo",
    "wof:placetype":"locality"
},
  "geometry": {"coordinates":[100.54994000000001,35.2589],"type":"Point"}
}