{
  "type": "Feature",
  "properties": {
    "gn:admin1_code":"18",
    "gn:asciiname":"Lintan",
    "gn:country_code":"CN",
    "gn:dem":342,
    "gn:feature_class":"P",
    "gn:feature_code":"PPL",
    "gn:name":"Lintan",
    "gn:population":0,
    "gn:timezone":"Asia/Shanghai",
    "iso:country":"CN",
    "name:zho_x_preferred":[
        "\u6dcb\u6ee9"
    ],
    "wof:name":"Lintan",
    "wof:placetype":"locality"
},
  "geometry": {"coordinates":[106.038,28.2091],"type":"Point"}
}