{
  "type": "Feature",
  "properties": {
    "gn:admin1_code":"4.0",
    "gn:asciiname":"Zhupancun",
    "gn:country_code":"CN",
    "gn:dem":4,
    "gn:feature_class":"P",
    "gn:feature_code":"PPL",
    "gn:name":"Zhupancun",
    "gn:population":0,
    "gn:timezone":"Asia/Shanghai",
    "iso:country":"CN",
    "name:zho_x_preferred":[
        "\u6731\u80d6\u6751"
    ],
    "wof:name":"Zhupancun",
    "wof:placetype":"locality"
},
  "geometry": {"coordinates":[119.97051999999999,32.9281],"type":"Point"}
}