{
  "type": "Feature",
  "properties": {
    "gn:admin1_code":"26.0",
    "gn:asciiname":"Zhaishicun",
    "gn:country_code":"CN",
    "gn:dem":802,
    "gn:feature_class":"P",
    "gn:feature_code":"PPL",
    "gn:name":"Zhaishicun",
    "gn:population":0,
    "gn:timezone":"Asia/Shanghai",
    "iso:country":"CN",
    "name:zho_x_preferred":[
        "\u5be8\u77f3\u6751"
    ],
    "wof:name":"Zhaishicun",
    "wof:placetype":"locality"
},
  "geometry": {"coordinates":[110.46408,36.43293],"type":"Point"}
}