{
  "type": "Feature",
  "properties": {
    "gn:admin1_code":"11.0",
    "gn:asciiname":"Kuzhutang",
    "gn:country_code":"CN",
    "gn:dem":91,
    "gn:feature_class":"P",
    "gn:feature_code":"PPL",
    "gn:name":"Kuzhutang",
    "gn:population":0,
    "gn:timezone":"Asia/Shanghai",
    "iso:country":"CN",
    "name:zho_x_preferred":[
        "\u82e6\u682a\u5858"
    ],
    "wof:name":"Kuzhutang",
    "wof:placetype":"locality"
},
  "geometry": {"coordinates":[112.65600000000001,27.72171],"type":"Point"}
}