{
  "type": "Feature",
  "properties": {
    "gn:admin1_code":"08",
    "gn:asciiname":"Manggetu",
    "gn:country_code":"CN",
    "gn:dem":161,
    "gn:feature_class":"P",
    "gn:feature_code":"PPL",
    "gn:name":"Manggetu",
    "gn:population":0,
    "gn:timezone":"Asia/Shanghai",
    "iso:country":"CN",
    "name:und_x_variant":[
        "Mang-ko-t\u2019u",
        "Manggetu"
    ],
    "name:zho_x_preferred":[
        "\u83bd\u683c\u5410"
    ],
    "wof:name":"Manggetu",
    "wof:placetype":"locality"
},
  "geometry": {"coordinates":[124.22234,47.80702],"type":"Point"}
}