{
  "type": "Feature",
  "properties": {
    "gn:admin1_code":"32.0",
    "gn:asciiname":"Yangtianba",
    "gn:country_code":"CN",
    "gn:dem":1104,
    "gn:feature_class":"P",
    "gn:feature_code":"PPL",
    "gn:name":"Yangtianba",
    "gn:population":0,
    "gn:timezone":"Asia/Shanghai",
    "iso:country":"CN",
    "name:zho_x_preferred":[
        "\u6768\u7530\u575d"
    ],
    "wof:name":"Yangtianba",
    "wof:placetype":"locality"
},
  "geometry": {"coordinates":[103.28100000000001,29.6711],"type":"Point"}
}