{
  "type": "Feature",
  "properties": {
    "gn:admin1_code":"16.0",
    "gn:asciiname":"Lugao",
    "gn:country_code":"CN",
    "gn:dem":257,
    "gn:feature_class":"P",
    "gn:feature_code":"PPL",
    "gn:name":"Lugao",
    "gn:population":0,
    "gn:timezone":"Asia/Shanghai",
    "iso:country":"CN",
    "name:zho_x_preferred":[
        "\u6e0c\u9ad8"
    ],
    "wof:name":"Lugao",
    "wof:placetype":"locality"
},
  "geometry": {"coordinates":[108.28700000000001,23.499],"type":"Point"}
}