{
  "type": "Feature",
  "properties": {
    "gn:admin1_code":"3.0",
    "gn:asciiname":"Badongguan",
    "gn:country_code":"CN",
    "gn:dem":424,
    "gn:feature_class":"P",
    "gn:feature_code":"PPL",
    "gn:name":"Badongguan",
    "gn:population":0,
    "gn:timezone":"Asia/Shanghai",
    "iso:country":"CN",
    "name:zho_x_preferred":[
        "\u516b\u6d1e\u704c"
    ],
    "wof:name":"Badongguan",
    "wof:placetype":"locality"
},
  "geometry": {"coordinates":[113.881,27.4164],"type":"Point"}
}