{
  "type": "Feature",
  "properties": {
    "gn:admin1_code":"3.0",
    "gn:asciiname":"Jiangyuanwu",
    "gn:country_code":"CN",
    "gn:dem":80,
    "gn:feature_class":"P",
    "gn:feature_code":"PPL",
    "gn:name":"Jiangyuanwu",
    "gn:population":0,
    "gn:timezone":"Asia/Shanghai",
    "iso:country":"CN",
    "name:und_x_variant":[
        "\u6c5f\u6e90\u575e"
    ],
    "wof:name":"Jiangyuanwu",
    "wof:placetype":"locality"
},
  "geometry": {"coordinates":[117.11283,29.10115],"type":"Point"}
}