{
  "type": "Feature",
  "properties": {
    "gn:admin1_code":"10",
    "gn:asciiname":"Laoxi Yingzi",
    "gn:country_code":"CN",
    "gn:dem":1219,
    "gn:feature_class":"P",
    "gn:feature_code":"PPL",
    "gn:name":"Laoxi Yingzi",
    "gn:population":0,
    "gn:timezone":"Asia/Shanghai",
    "iso:country":"CN",
    "name:zho_x_preferred":[
        "\u8001\u897f\u8425\u5b50"
    ],
    "wof:name":"Laoxi Yingzi",
    "wof:placetype":"locality"
},
  "geometry": {"coordinates":[116.47371,41.88444000000001],"type":"Point"}
}