{
  "type": "Feature",
  "properties": {
    "gn:admin1_code":"33.0",
    "gn:asciiname":"Huangjinbu",
    "gn:country_code":"CN",
    "gn:dem":232,
    "gn:feature_class":"P",
    "gn:feature_code":"PPL",
    "gn:name":"Huangjinbu",
    "gn:population":0,
    "gn:timezone":"Asia/Shanghai",
    "iso:country":"CN",
    "name:zho_x_preferred":[
        "\u9ec4\u91d1\u5821"
    ],
    "wof:name":"Huangjinbu",
    "wof:placetype":"locality"
},
  "geometry": {"coordinates":[106.372,29.3446],"type":"Point"}
}