{
  "type": "Feature",
  "properties": {
    "gn:admin1_code":"24.0",
    "gn:asciiname":"Zhangjiatacun",
    "gn:country_code":"CN",
    "gn:dem":970,
    "gn:feature_class":"P",
    "gn:feature_code":"PPL",
    "gn:name":"Zhangjiatacun",
    "gn:population":0,
    "gn:timezone":"Asia/Shanghai",
    "iso:country":"CN",
    "name:zho_x_preferred":[
        "\u5f20\u5bb6\u5854\u6751"
    ],
    "wof:name":"Zhangjiatacun",
    "wof:placetype":"locality"
},
  "geometry": {"coordinates":[110.89106,37.555],"type":"Point"}
}