{
  "type": "Feature",
  "properties": {
    "gn:admin1_code":"26.0",
    "gn:asciiname":"Wangkelanggou",
    "gn:cc2":"CN",
    "gn:country_code":"CN",
    "gn:dem":1688,
    "gn:feature_class":"P",
    "gn:feature_code":"PPL",
    "gn:name":"Wangkelanggou",
    "gn:population":0,
    "gn:timezone":"Asia/Shanghai",
    "iso:country":"CN",
    "name:und_x_variant":[
        "Wang-k\u2019o-lang-kou",
        "Wangkelanggou"
    ],
    "wof:name":"Wangkelanggou",
    "wof:placetype":"locality"
},
  "geometry": {"coordinates":[108.68333,37.11667],"type":"Point"}
}