{
  "type": "Feature",
  "properties": {
    "gn:admin1_code":"5.0",
    "gn:asciiname":"Qianshi'er Majia",
    "gn:country_code":"CN",
    "gn:dem":194,
    "gn:feature_class":"P",
    "gn:feature_code":"PPL",
    "gn:name":"Qianshi\u2019er Majia",
    "gn:population":0,
    "gn:timezone":"Asia/Shanghai",
    "iso:country":"CN",
    "name:und_x_variant":[
        "Qianshi\u2019er Majia"
    ],
    "name:zho_x_preferred":[
        "\u524d\u5341\u4e8c\u9a6c\u67b6"
    ],
    "wof:name":"Qianshi'er Majia",
    "wof:placetype":"locality"
},
  "geometry": {"coordinates":[124.45017,43.98255],"type":"Point"}
}