{
  "type": "Feature",
  "properties": {
    "gn:admin1_code":"26",
    "gn:asciiname":"Gaolougua",
    "gn:cc2":"CN",
    "gn:country_code":"CN",
    "gn:dem":1384,
    "gn:feature_class":"P",
    "gn:feature_code":"PPL",
    "gn:name":"Gaolougua",
    "gn:population":0,
    "gn:timezone":"Asia/Shanghai",
    "iso:country":"CN",
    "name:und_x_variant":[
        "Kao-lou-kua",
        "Gaolougua"
    ],
    "wof:name":"Gaolougua",
    "wof:placetype":"locality"
},
  "geometry": {"coordinates":[109.06,35.38194],"type":"Point"}
}