{
  "type": "Feature",
  "properties": {
    "gn:admin1_code":"3.0",
    "gn:asciiname":"Taomuwu",
    "gn:country_code":"CN",
    "gn:dem":489,
    "gn:feature_class":"P",
    "gn:feature_code":"PPL",
    "gn:name":"Taomuwu",
    "gn:population":0,
    "gn:timezone":"Asia/Shanghai",
    "iso:country":"CN",
    "name:und_x_variant":[
        "\u6843\u6728\u575e"
    ],
    "wof:name":"Taomuwu",
    "wof:placetype":"locality"
},
  "geometry": {"coordinates":[116.80295,27.65443],"type":"Point"}
}