{
  "type": "Feature",
  "properties": {
    "gn:admin1_code":"29",
    "gn:asciiname":"Haimage",
    "gn:country_code":"CN",
    "gn:dem":1800,
    "gn:feature_class":"P",
    "gn:feature_code":"PPL",
    "gn:name":"Haimage",
    "gn:population":0,
    "gn:timezone":"Asia/Shanghai",
    "iso:country":"CN",
    "name:zho_x_preferred":[
        "\u6d77\u9a6c\u683c"
    ],
    "wof:name":"Haimage",
    "wof:placetype":"locality"
},
  "geometry": {"coordinates":[102.557,23.9416],"type":"Point"}
}