{
  "type": "Feature",
  "properties": {
    "gn:admin1_code":"5.0",
    "gn:asciiname":"Shiyouzongjichang Xincun",
    "gn:country_code":"CN",
    "gn:dem":133,
    "gn:feature_class":"P",
    "gn:feature_code":"PPL",
    "gn:name":"Shiyouzongjichang Xincun",
    "gn:population":0,
    "gn:timezone":"Asia/Shanghai",
    "iso:country":"CN",
    "name:zho_x_preferred":[
        "\u77f3\u6cb9\u603b\u673a\u5382\u65b0\u6751"
    ],
    "wof:name":"Shiyouzongjichang Xincun",
    "wof:placetype":"locality"
},
  "geometry": {"coordinates":[124.58975,45.08463],"type":"Point"}
}