{
  "type": "Feature",
  "properties": {
    "gn:admin1_code":"32.0",
    "gn:asciiname":"Maiba",
    "gn:country_code":"CN",
    "gn:dem":3553,
    "gn:feature_class":"P",
    "gn:feature_code":"PPL",
    "gn:name":"Maiba",
    "gn:population":0,
    "gn:timezone":"Asia/Shanghai",
    "iso:country":"CN",
    "name:zho_x_preferred":[
        "\u9ea6\u5df4"
    ],
    "wof:name":"Maiba",
    "wof:placetype":"locality"
},
  "geometry": {"coordinates":[101.596,30.0746],"type":"Point"}
}