{
  "type": "Feature",
  "properties": {
    "gn:admin1_code":"26.0",
    "gn:asciiname":"Renjia Huochang",
    "gn:country_code":"CN",
    "gn:dem":1228,
    "gn:feature_class":"P",
    "gn:feature_code":"PPL",
    "gn:name":"Renjia Huochang",
    "gn:population":0,
    "gn:timezone":"Asia/Shanghai",
    "iso:country":"CN",
    "name:zho_x_preferred":[
        "\u4efb\u5bb6\u4f19\u573a"
    ],
    "wof:name":"Renjia Huochang",
    "wof:placetype":"locality"
},
  "geometry": {"coordinates":[109.785,38.5334],"type":"Point"}
}