{
  "type": "Feature",
  "properties": {
    "gn:admin1_code":"7",
    "gn:asciiname":"Chaiqiao",
    "gn:country_code":"CN",
    "gn:dem":67,
    "gn:feature_class":"P",
    "gn:feature_code":"PPL",
    "gn:name":"Chaiqiao",
    "gn:population":0,
    "gn:timezone":"Asia/Shanghai",
    "iso:country":"CN",
    "name:zho_x_preferred":[
        "\u67f4\u6865"
    ],
    "wof:name":"Chaiqiao",
    "wof:placetype":"locality"
},
  "geometry": {"coordinates":[117.63611000000002,24.19389],"type":"Point"}
}