{
  "type": "Feature",
  "properties": {
    "gn:admin1_code":"19.0",
    "gn:asciiname":"Luobu Gouliang",
    "gn:country_code":"CN",
    "gn:dem":347,
    "gn:feature_class":"P",
    "gn:feature_code":"PPL",
    "gn:name":"Luobu Gouliang",
    "gn:population":0,
    "gn:timezone":"Asia/Shanghai",
    "iso:country":"CN",
    "name:zho_x_preferred":[
        "\u843d\u9d4f\u6c9f\u6881"
    ],
    "wof:name":"Luobu Gouliang",
    "wof:placetype":"locality"
},
  "geometry": {"coordinates":[119.68000000000001,40.8776],"type":"Point"}
}