{
  "type": "Feature",
  "properties": {
    "gn:admin1_code":"1.0",
    "gn:asciiname":"Zhujicun",
    "gn:country_code":"CN",
    "gn:dem":44,
    "gn:feature_class":"P",
    "gn:feature_code":"PPL",
    "gn:name":"Zhujicun",
    "gn:population":0,
    "gn:timezone":"Asia/Shanghai",
    "iso:country":"CN",
    "name:zho_x_preferred":[
        "\u795d\u96c6\u6751"
    ],
    "wof:name":"Zhujicun",
    "wof:placetype":"locality"
},
  "geometry": {"coordinates":[115.75199000000001,33.98220999999999],"type":"Point"}
}