{
  "type": "Feature",
  "properties": {
    "gn:admin1_code":"18",
    "gn:asciiname":"Yimazhai",
    "gn:country_code":"CN",
    "gn:dem":1319,
    "gn:feature_class":"P",
    "gn:feature_code":"PPL",
    "gn:name":"Yimazhai",
    "gn:population":0,
    "gn:timezone":"Asia/Shanghai",
    "iso:country":"CN",
    "name:zho_x_preferred":[
        "\u59e8\u5988\u5be8"
    ],
    "wof:name":"Yimazhai",
    "wof:placetype":"locality"
},
  "geometry": {"coordinates":[106.751,26.7377],"type":"Point"}
}