{
  "type": "Feature",
  "properties": {
    "gn:admin1_code":"2.0",
    "gn:asciiname":"Xipanwan",
    "gn:country_code":"CN",
    "gn:dem":16,
    "gn:feature_class":"P",
    "gn:feature_code":"PPL",
    "gn:name":"Xipanwan",
    "gn:population":0,
    "gn:timezone":"Asia/Shanghai",
    "iso:country":"CN",
    "name:und_x_variant":[
        "\u897f\u6f58\u6e7e"
    ],
    "wof:name":"Xipanwan",
    "wof:placetype":"locality"
},
  "geometry": {"coordinates":[120.15004,30.62136],"type":"Point"}
}