{
  "type": "Feature",
  "properties": {
    "gn:admin1_code":"12.0",
    "gn:asciiname":"Dajing",
    "gn:country_code":"CN",
    "gn:dem":1139,
    "gn:feature_class":"P",
    "gn:feature_code":"PPL",
    "gn:name":"Dajing",
    "gn:population":0,
    "gn:timezone":"Asia/Shanghai",
    "iso:country":"CN",
    "name:zho_x_preferred":[
        "\u5927\u4e95"
    ],
    "wof:name":"Dajing",
    "wof:placetype":"locality"
},
  "geometry": {"coordinates":[109.04922000000001,30.26026],"type":"Point"}
}