{
  "type": "Feature",
  "properties": {
    "gn:admin1_code":"2",
    "gn:asciiname":"Xiangguchang",
    "gn:country_code":"CN",
    "gn:dem":822,
    "gn:feature_class":"P",
    "gn:feature_code":"PPL",
    "gn:name":"Xiangguchang",
    "gn:population":0,
    "gn:timezone":"Asia/Shanghai",
    "iso:country":"CN",
    "name:zho_x_preferred":[
        "\u9999\u83c7\u5382"
    ],
    "wof:name":"Xiangguchang",
    "wof:placetype":"locality"
},
  "geometry": {"coordinates":[119.56778,27.99361],"type":"Point"}
}