{
  "type": "Feature",
  "properties": {
    "gn:admin1_code":"22.0",
    "gn:asciiname":"ZhangJiaFen Cun",
    "gn:country_code":"CN",
    "gn:dem":254,
    "gn:elevation":"200.0",
    "gn:feature_class":"P",
    "gn:feature_code":"PPL",
    "gn:name":"ZhangJiaFen Cun",
    "gn:population":0,
    "gn:timezone":"Asia/Shanghai",
    "iso:country":"CN",
    "wof:name":"ZhangJiaFen Cun",
    "wof:placetype":"locality"
},
  "geometry": {"coordinates":[116.79062999999999,40.61441],"type":"Point"}
}