{
  "type": "Feature",
  "properties": {
    "gn:admin1_code":"14.0",
    "gn:asciiname":"Qieluomaguo",
    "gn:country_code":"CN",
    "gn:dem":4706,
    "gn:feature_class":"P",
    "gn:feature_code":"PPL",
    "gn:name":"Qieluomaguo",
    "gn:population":0,
    "gn:timezone":"Asia/Urumqi",
    "iso:country":"CN",
    "name:zho_x_preferred":[
        "\u4e14\u6d1b\u9ebb\u679c"
    ],
    "wof:name":"Qieluomaguo",
    "wof:placetype":"locality"
},
  "geometry": {"coordinates":[93.22017,30.86992],"type":"Point"}
}