{
  "type": "Feature",
  "properties": {
    "gn:admin1_code":"33.0",
    "gn:asciiname":"Rongjiang",
    "gn:country_code":"CN",
    "gn:dem":339,
    "gn:feature_class":"P",
    "gn:feature_code":"PPL",
    "gn:name":"Rongjiang",
    "gn:population":0,
    "gn:timezone":"Asia/Shanghai",
    "iso:country":"CN",
    "name:zho_x_preferred":[
        "\u8363\u6c5f"
    ],
    "wof:name":"Rongjiang",
    "wof:placetype":"locality"
},
  "geometry": {"coordinates":[105.36041000000002,29.62419],"type":"Point"}
}