{
  "type": "Feature",
  "properties": {
    "gn:admin1_code":"16.0",
    "gn:asciiname":"Wayinkeng",
    "gn:country_code":"CN",
    "gn:dem":10,
    "gn:feature_class":"P",
    "gn:feature_code":"PPL",
    "gn:name":"Wayinkeng",
    "gn:population":0,
    "gn:timezone":"Asia/Shanghai",
    "iso:country":"CN",
    "name:zho_x_preferred":[
        "\u6316\u94f6\u5751"
    ],
    "wof:name":"Wayinkeng",
    "wof:placetype":"locality"
},
  "geometry": {"coordinates":[108.81399999999999,21.6926],"type":"Point"}
}