{
  "type": "Feature",
  "properties": {
    "gn:admin1_code":"01",
    "gn:asciiname":"Lingjiao",
    "gn:cc2":"CN",
    "gn:country_code":"CN",
    "gn:dem":219,
    "gn:feature_class":"P",
    "gn:feature_code":"PPL",
    "gn:name":"Lingjiao",
    "gn:population":0,
    "gn:timezone":"Asia/Shanghai",
    "iso:country":"CN",
    "name:und_x_variant":[
        "Ling-chiao",
        "Lingjiao"
    ],
    "wof:name":"Lingjiao",
    "wof:placetype":"locality"
},
  "geometry": {"coordinates":[117.85193999999998,29.855],"type":"Point"}
}