{
  "type": "Feature",
  "properties": {
    "gn:admin1_code":"14.0",
    "gn:asciiname":"Riquduocun",
    "gn:country_code":"CN",
    "gn:dem":4048,
    "gn:feature_class":"P",
    "gn:feature_code":"PPL",
    "gn:name":"Riquduocun",
    "gn:population":0,
    "gn:timezone":"Asia/Urumqi",
    "iso:country":"CN",
    "name:zho_x_preferred":[
        "\u65e5\u66f2\u6735\u6751"
    ],
    "wof:name":"Riquduocun",
    "wof:placetype":"locality"
},
  "geometry": {"coordinates":[94.60984000000001,31.66908],"type":"Point"}
}