{
  "type": "Feature",
  "properties": {
    "gn:admin1_code":"22.0",
    "gn:asciiname":"Xiangcunyingcun",
    "gn:country_code":"CN",
    "gn:dem":504,
    "gn:feature_class":"P",
    "gn:feature_code":"PPL",
    "gn:name":"Xiangcunyingcun",
    "gn:population":0,
    "gn:timezone":"Asia/Shanghai",
    "iso:country":"CN",
    "name:zho_x_preferred":[
        "\u9999\u6751\u8425\u6751"
    ],
    "wof:name":"Xiangcunyingcun",
    "wof:placetype":"locality"
},
  "geometry": {"coordinates":[116.08419000000001,40.49476],"type":"Point"}
}