{
  "type": "Feature",
  "properties": {
    "gn:admin1_code":"7.0",
    "gn:asciiname":"Dazhulan",
    "gn:country_code":"CN",
    "gn:dem":883,
    "gn:feature_class":"P",
    "gn:feature_code":"PPL",
    "gn:name":"Dazhulan",
    "gn:population":0,
    "gn:timezone":"Asia/Shanghai",
    "iso:country":"CN",
    "name:zho_x_preferred":[
        "\u5927\u7af9\u5c9a"
    ],
    "wof:name":"Dazhulan",
    "wof:placetype":"locality"
},
  "geometry": {"coordinates":[117.64464,27.69635],"type":"Point"}
}