{
  "type": "Feature",
  "properties": {
    "gn:admin1_code":"32.0",
    "gn:asciiname":"Jiashici",
    "gn:country_code":"CN",
    "gn:dem":368,
    "gn:feature_class":"P",
    "gn:feature_code":"PPL",
    "gn:name":"Jiashici",
    "gn:population":0,
    "gn:timezone":"Asia/Shanghai",
    "iso:country":"CN",
    "name:zho_x_preferred":[
        "\u8d3e\u6c0f\u7960"
    ],
    "wof:name":"Jiashici",
    "wof:placetype":"locality"
},
  "geometry": {"coordinates":[105.76501,31.07561],"type":"Point"}
}