{
  "type": "Feature",
  "properties": {
    "gn:admin1_code":"2.0",
    "gn:asciiname":"Caijiaxu",
    "gn:country_code":"CN",
    "gn:dem":10,
    "gn:feature_class":"P",
    "gn:feature_code":"PPL",
    "gn:name":"Caijiaxu",
    "gn:population":0,
    "gn:timezone":"Asia/Shanghai",
    "iso:country":"CN",
    "name:und_x_variant":[
        "\u8521\u5bb6\u5729"
    ],
    "wof:name":"Caijiaxu",
    "wof:placetype":"locality"
},
  "geometry": {"coordinates":[120.97854,30.55978],"type":"Point"}
}