{
  "type": "Feature",
  "properties": {
    "gn:admin1_code":"1.0",
    "gn:asciiname":"Yanchongcun",
    "gn:country_code":"CN",
    "gn:dem":243,
    "gn:feature_class":"P",
    "gn:feature_code":"PPL",
    "gn:name":"Yanchongcun",
    "gn:population":0,
    "gn:timezone":"Asia/Shanghai",
    "iso:country":"CN",
    "name:zho_x_preferred":[
        "\u70df\u51b2\u6751"
    ],
    "wof:name":"Yanchongcun",
    "wof:placetype":"locality"
},
  "geometry": {"coordinates":[116.09695000000001,30.34756],"type":"Point"}
}