{
  "type": "Feature",
  "properties": {
    "gn:admin1_code":"29",
    "gn:asciiname":"Lanziying",
    "gn:country_code":"CN",
    "gn:dem":1467,
    "gn:feature_class":"P",
    "gn:feature_code":"PPL",
    "gn:name":"Lanziying",
    "gn:population":0,
    "gn:timezone":"Asia/Shanghai",
    "iso:country":"CN",
    "name:zho_x_preferred":[
        "\u5170\u6893\u8425"
    ],
    "wof:name":"Lanziying",
    "wof:placetype":"locality"
},
  "geometry": {"coordinates":[102.369,23.7538],"type":"Point"}
}