{
  "type": "Feature",
  "properties": {
    "gn:admin1_code":"18",
    "gn:asciiname":"Lali",
    "gn:country_code":"CN",
    "gn:dem":986,
    "gn:feature_class":"P",
    "gn:feature_code":"PPL",
    "gn:name":"Lali",
    "gn:population":0,
    "gn:timezone":"Asia/Shanghai",
    "iso:country":"CN",
    "name:ceb_x_preferred":[
        "Lali"
    ],
    "name:deu_x_preferred":[
        "Lali"
    ],
    "name:fra_x_preferred":[
        "Lali"
    ],
    "name:pnb_x_preferred":[
        "\u0644\u0627\u0644\u06cc"
    ],
    "name:swe_x_preferred":[
        "Lali"
    ],
    "name:zho_x_preferred":[
        "\u62c9\u529b"
    ],
    "wof:name":"Lali",
    "wof:placetype":"locality"
},
  "geometry": {"coordinates":[106.866,25.6678],"type":"Point"}
}