{
  "type": "Feature",
  "properties": {
    "gn:admin1_code":"4.0",
    "gn:asciiname":"Hedong",
    "gn:country_code":"CN",
    "gn:dem":6,
    "gn:feature_class":"P",
    "gn:feature_code":"PPL",
    "gn:name":"Hedong",
    "gn:population":0,
    "gn:timezone":"Asia/Shanghai",
    "iso:country":"CN",
    "name:ceb_x_preferred":[
        "Hedong"
    ],
    "name:deu_x_preferred":[
        "Hedong"
    ],
    "name:eus_x_preferred":[
        "Hedong"
    ],
    "name:fra_x_preferred":[
        "Hedong"
    ],
    "name:nor_x_preferred":[
        "Hedong"
    ],
    "name:rus_x_preferred":[
        "\u0425\u044d\u0434\u0443\u043d"
    ],
    "name:swe_x_preferred":[
        "Hedong"
    ],
    "name:zho_x_preferred":[
        "\u6cb3\u4e1c"
    ],
    "wof:name":"Hedong",
    "wof:placetype":"locality"
},
  "geometry": {"coordinates":[119.60278,31.8941],"type":"Point"}
}