{
  "type": "Feature",
  "properties": {
    "gn:admin1_code":"29.0",
    "gn:asciiname":"Caiyuancun",
    "gn:country_code":"CN",
    "gn:dem":1760,
    "gn:feature_class":"P",
    "gn:feature_code":"PPL",
    "gn:name":"Caiyuancun",
    "gn:population":0,
    "gn:timezone":"Asia/Shanghai",
    "iso:country":"CN",
    "name:zho_x_preferred":[
        "\u83dc\u56ed\u6751"
    ],
    "wof:name":"Caiyuancun",
    "wof:placetype":"locality"
},
  "geometry": {"coordinates":[101.901,25.1722],"type":"Point"}
}