{
  "type": "Feature",
  "properties": {
    "gn:admin1_code":"20.0",
    "gn:asciiname":"Lujiaogou",
    "gn:country_code":"CN",
    "gn:dem":539,
    "gn:feature_class":"P",
    "gn:feature_code":"PPL",
    "gn:name":"Lujiaogou",
    "gn:population":0,
    "gn:timezone":"Asia/Shanghai",
    "iso:country":"CN",
    "name:zho_x_preferred":[
        "\u9e7f\u7a96\u6c9f"
    ],
    "wof:name":"Lujiaogou",
    "wof:placetype":"locality"
},
  "geometry": {"coordinates":[121.34784999999999,47.41044],"type":"Point"}
}