{
  "type": "Feature",
  "properties": {
    "gn:admin1_code":"24.0",
    "gn:asciiname":"Nantuanbai",
    "gn:country_code":"CN",
    "gn:dem":808,
    "gn:feature_class":"P",
    "gn:feature_code":"PPL",
    "gn:name":"Nantuanbai",
    "gn:population":0,
    "gn:timezone":"Asia/Shanghai",
    "iso:country":"CN",
    "name:zho_x_preferred":[
        "\u5357\u56e2\u67cf"
    ],
    "wof:name":"Nantuanbai",
    "wof:placetype":"locality"
},
  "geometry": {"coordinates":[112.44642,37.34262],"type":"Point"}
}