{
  "type": "Feature",
  "properties": {
    "gn:admin1_code":"11.0",
    "gn:asciiname":"Xiaxiaoxi",
    "gn:country_code":"CN",
    "gn:dem":387,
    "gn:feature_class":"P",
    "gn:feature_code":"PPL",
    "gn:name":"Xiaxiaoxi",
    "gn:population":0,
    "gn:timezone":"Asia/Shanghai",
    "iso:country":"CN",
    "name:zho_x_preferred":[
        "\u4e0b\u5c0f\u6eaa"
    ],
    "wof:name":"Xiaxiaoxi",
    "wof:placetype":"locality"
},
  "geometry": {"coordinates":[113.21254999999999,25.85125],"type":"Point"}
}