{
  "type": "Feature",
  "properties": {
    "gn:admin1_code":"19.0",
    "gn:asciiname":"Xiaowa Zigou",
    "gn:country_code":"CN",
    "gn:dem":434,
    "gn:feature_class":"P",
    "gn:feature_code":"PPL",
    "gn:name":"Xiaowa Zigou",
    "gn:population":0,
    "gn:timezone":"Asia/Shanghai",
    "iso:country":"CN",
    "name:und_x_variant":[
        "\u5c0f\u74e6\u5b50\u6c9f"
    ],
    "wof:name":"Xiaowa Zigou",
    "wof:placetype":"locality"
},
  "geometry": {"coordinates":[124.91041,41.67693],"type":"Point"}
}