{
  "type": "Feature",
  "properties": {
    "gn:admin1_code":"07",
    "gn:asciiname":"Wan'an",
    "gn:country_code":"CN",
    "gn:dem":271,
    "gn:feature_class":"P",
    "gn:feature_code":"PPLA4",
    "gn:name":"Wan\u2019an",
    "gn:population":0,
    "gn:timezone":"Asia/Shanghai",
    "iso:country":"CN",
    "name:ceb_x_preferred":[
        "Wan\u2019an"
    ],
    "name:deu_x_preferred":[
        "Wan\u2019an"
    ],
    "name:swe_x_preferred":[
        "Wan\u2019an"
    ],
    "name:und_x_variant":[
        "Wan-an-chen",
        "Wan\u2019an Zhen",
        "\u4e07\u5b89\u9547"
    ],
    "name:zho_x_preferred":[
        "\u4e07\u5b89"
    ],
    "wof:name":"Wan'an",
    "wof:placetype":"locality"
},
  "geometry": {"coordinates":[117.42531,26.89649],"type":"Point"}
}