{
  "type": "Feature",
  "properties": {
    "gn:admin1_code":"1.0",
    "gn:asciiname":"Wentiancun",
    "gn:country_code":"CN",
    "gn:dem":339,
    "gn:feature_class":"P",
    "gn:feature_code":"PPL",
    "gn:name":"Wentiancun",
    "gn:population":0,
    "gn:timezone":"Asia/Shanghai",
    "iso:country":"CN",
    "name:zho_x_preferred":[
        "\u6587\u7530\u6751"
    ],
    "wof:name":"Wentiancun",
    "wof:placetype":"locality"
},
  "geometry": {"coordinates":[118.3703,29.61548],"type":"Point"}
}