{
  "type": "Feature",
  "properties": {
    "gn:admin1_code":"11.0",
    "gn:asciiname":"Maowuli",
    "gn:country_code":"CN",
    "gn:dem":257,
    "gn:feature_class":"P",
    "gn:feature_code":"PPL",
    "gn:name":"Maowuli",
    "gn:population":0,
    "gn:timezone":"Asia/Shanghai",
    "iso:country":"CN",
    "name:zho_x_preferred":[
        "\u8305\u5c4b\u91cc"
    ],
    "name:zho_x_variant":[
        "\u6bdb\u5c4b\u91cc"
    ],
    "wof:name":"Maowuli",
    "wof:placetype":"locality"
},
  "geometry": {"coordinates":[113.53455,26.91355],"type":"Point"}
}