{
  "type": "Feature",
  "properties": {
    "gn:admin1_code":"32.0",
    "gn:asciiname":"Jangra",
    "gn:country_code":"CN",
    "gn:dem":3173,
    "gn:feature_class":"P",
    "gn:feature_code":"PPL",
    "gn:name":"Jangra",
    "gn:population":0,
    "gn:timezone":"Asia/Urumqi",
    "iso:country":"CN",
    "wof:name":"Jangra",
    "wof:placetype":"locality"
},
  "geometry": {"coordinates":[98.55,31.71667],"type":"Point"}
}