{
  "type": "Feature",
  "properties": {
    "gn:admin1_code":"24",
    "gn:asciiname":"Kangyi",
    "gn:country_code":"CN",
    "gn:dem":1066,
    "gn:feature_class":"P",
    "gn:feature_code":"PPL",
    "gn:name":"Kangyi",
    "gn:population":0,
    "gn:timezone":"Asia/Shanghai",
    "iso:country":"CN",
    "name:und_x_variant":[
        "K\u2019ang-i-pao",
        "Kangyi"
    ],
    "name:zho_x_preferred":[
        "\u4ea2\u9a7f"
    ],
    "wof:name":"Kangyi",
    "wof:placetype":"locality"
},
  "geometry": {"coordinates":[112.15054000000001,36.43176],"type":"Point"}
}