{
  "type": "Feature",
  "properties": {
    "gn:admin1_code":"15.0",
    "gn:asciiname":"Caoqi",
    "gn:country_code":"CN",
    "gn:dem":1207,
    "gn:feature_class":"P",
    "gn:feature_code":"PPL",
    "gn:name":"Caoqi",
    "gn:population":0,
    "gn:timezone":"Asia/Shanghai",
    "iso:country":"CN",
    "name:und_x_variant":[
        "\u66f9\u65d7"
    ],
    "wof:name":"Caoqi",
    "wof:placetype":"locality"
},
  "geometry": {"coordinates":[107.41907999999999,36.46389],"type":"Point"}
}