{
  "type": "Feature",
  "properties": {
    "gn:admin1_code":"04",
    "gn:asciiname":"Chenyang",
    "gn:cc2":"CN",
    "gn:country_code":"CN",
    "gn:dem":0,
    "gn:feature_class":"P",
    "gn:feature_code":"PPL",
    "gn:name":"Chenyang",
    "gn:population":0,
    "gn:timezone":"Asia/Shanghai",
    "iso:country":"CN",
    "name:und_x_variant":[
        "Ch\u2019en-chia-yang-chen",
        "Ch\u2019en-chia-yang",
        "Chenyang"
    ],
    "name:zho_x_preferred":[
        "\u8fb0\u9633\u9547"
    ],
    "wof:name":"Chenyang",
    "wof:placetype":"locality"
},
  "geometry": {"coordinates":[120.10889,33.76528],"type":"Point"}
}