{
  "type": "Feature",
  "properties": {
    "gn:admin1_code":"16.0",
    "gn:asciiname":"Qingcaoping",
    "gn:country_code":"CN",
    "gn:dem":324,
    "gn:feature_class":"P",
    "gn:feature_code":"PPL",
    "gn:name":"Qingcaoping",
    "gn:population":0,
    "gn:timezone":"Asia/Shanghai",
    "iso:country":"CN",
    "name:zho_x_preferred":[
        "\u9752\u8349\u576a"
    ],
    "wof:name":"Qingcaoping",
    "wof:placetype":"locality"
},
  "geometry": {"coordinates":[111.178,22.9634],"type":"Point"}
}