{
  "type": "Feature",
  "properties": {
    "gn:admin1_code":"12.0",
    "gn:asciiname":"Xiaochen",
    "gn:country_code":"CN",
    "gn:dem":34,
    "gn:feature_class":"P",
    "gn:feature_code":"PPL",
    "gn:name":"Xiaochen",
    "gn:population":0,
    "gn:timezone":"Asia/Shanghai",
    "iso:country":"CN",
    "name:zho_x_preferred":[
        "Xiaochen"
    ],
    "name:zho_x_variant":[
        "\u8096\u9648"
    ],
    "wof:name":"Xiaochen",
    "wof:placetype":"locality"
},
  "geometry": {"coordinates":[114.13064,29.99543],"type":"Point"}
}