{
  "type": "Feature",
  "properties": {
    "gn:admin1_code":"15.0",
    "gn:asciiname":"Hujiamiao",
    "gn:country_code":"CN",
    "gn:dem":1499,
    "gn:feature_class":"P",
    "gn:feature_code":"PPL",
    "gn:name":"Hujiamiao",
    "gn:population":0,
    "gn:timezone":"Asia/Shanghai",
    "iso:country":"CN",
    "name:und_x_variant":[
        "\u80e1\u5bb6\u5e99"
    ],
    "wof:name":"Hujiamiao",
    "wof:placetype":"locality"
},
  "geometry": {"coordinates":[107.61376,36.38287],"type":"Point"}
}