{
  "type": "Feature",
  "properties": {
    "gn:admin1_code":"07",
    "gn:asciiname":"Geqiu",
    "gn:country_code":"CN",
    "gn:dem":1040,
    "gn:feature_class":"P",
    "gn:feature_code":"PPL",
    "gn:name":"Geqiu",
    "gn:population":0,
    "gn:timezone":"Asia/Shanghai",
    "iso:country":"CN",
    "name:zho_x_preferred":[
        "\u683c\u4e18"
    ],
    "wof:name":"Geqiu",
    "wof:placetype":"locality"
},
  "geometry": {"coordinates":[118.13222,25.50694],"type":"Point"}
}