{
  "type": "Feature",
  "properties": {
    "gn:admin1_code":"18",
    "gn:asciiname":"Gele",
    "gn:country_code":"CN",
    "gn:dem":1531,
    "gn:feature_class":"P",
    "gn:feature_code":"PPL",
    "gn:name":"Gele",
    "gn:population":0,
    "gn:timezone":"Asia/Shanghai",
    "iso:country":"CN",
    "name:zho_x_preferred":[
        "\u683c\u52d2"
    ],
    "wof:name":"Gele",
    "wof:placetype":"locality"
},
  "geometry": {"coordinates":[104.574,25.4604],"type":"Point"}
}