{
  "type": "Feature",
  "properties": {
    "gn:admin1_code":"24.0",
    "gn:asciiname":"Anziliang",
    "gn:country_code":"CN",
    "gn:dem":1892,
    "gn:feature_class":"P",
    "gn:feature_code":"PPL",
    "gn:name":"Anziliang",
    "gn:population":0,
    "gn:timezone":"Asia/Shanghai",
    "iso:country":"CN",
    "name:zho_x_preferred":[
        "\u5b89\u5b50\u6881"
    ],
    "wof:name":"Anziliang",
    "wof:placetype":"locality"
},
  "geometry": {"coordinates":[112.20820999999999,38.72967],"type":"Point"}
}