{
  "type": "Feature",
  "properties": {
    "gn:admin1_code":"11.0",
    "gn:asciiname":"Huangtengshu",
    "gn:country_code":"CN",
    "gn:dem":29,
    "gn:feature_class":"P",
    "gn:feature_code":"PPL",
    "gn:name":"Huangtengshu",
    "gn:population":0,
    "gn:timezone":"Asia/Shanghai",
    "iso:country":"CN",
    "name:zho_x_preferred":[
        "\u9ec4\u85e4\u6811"
    ],
    "wof:name":"Huangtengshu",
    "wof:placetype":"locality"
},
  "geometry": {"coordinates":[112.40895999999999,28.63036],"type":"Point"}
}