{
  "type": "Feature",
  "properties": {
    "gn:admin1_code":"21.0",
    "gn:asciiname":"Wanya",
    "gn:country_code":"CN",
    "gn:dem":1982,
    "gn:feature_class":"P",
    "gn:feature_code":"PPL",
    "gn:name":"Wanya",
    "gn:population":0,
    "gn:timezone":"Asia/Shanghai",
    "iso:country":"CN",
    "name:zho_x_preferred":[
        "\u4e07\u5d16"
    ],
    "wof:name":"Wanya",
    "wof:placetype":"locality"
},
  "geometry": {"coordinates":[105.64700000000001,36.011],"type":"Point"}
}