{
  "type": "Feature",
  "properties": {
    "gn:admin1_code":"26.0",
    "gn:asciiname":"Qianwuqi",
    "gn:country_code":"CN",
    "gn:dem":1603,
    "gn:feature_class":"P",
    "gn:feature_code":"PPL",
    "gn:name":"Qianwuqi",
    "gn:population":0,
    "gn:timezone":"Asia/Shanghai",
    "iso:country":"CN",
    "name:zho_x_preferred":[
        "\u524d\u4e94\u65d7"
    ],
    "wof:name":"Qianwuqi",
    "wof:placetype":"locality"
},
  "geometry": {"coordinates":[107.80542,37.15824],"type":"Point"}
}