{
  "type": "Feature",
  "properties": {
    "gn:admin1_code":"10",
    "gn:asciiname":"Shizuizi",
    "gn:country_code":"CN",
    "gn:dem":985,
    "gn:feature_class":"P",
    "gn:feature_code":"PPL",
    "gn:name":"Shizuizi",
    "gn:population":0,
    "gn:timezone":"Asia/Shanghai",
    "iso:country":"CN",
    "wof:name":"Shizuizi",
    "wof:placetype":"locality"
},
  "geometry": {"coordinates":[114.99944000000001,40.98806],"type":"Point"}
}