{
  "type": "Feature",
  "properties": {
    "gn:admin1_code":"1.0",
    "gn:asciiname":"Yangzhenbao",
    "gn:country_code":"CN",
    "gn:dem":63,
    "gn:feature_class":"P",
    "gn:feature_code":"PPL",
    "gn:name":"Yangzhenbao",
    "gn:population":0,
    "gn:timezone":"Asia/Shanghai",
    "iso:country":"CN",
    "name:zho_x_preferred":[
        "\u626c\u771f\u5b9d"
    ],
    "wof:name":"Yangzhenbao",
    "wof:placetype":"locality"
},
  "geometry": {"coordinates":[118.17359,31.79781],"type":"Point"}
}