{
  "type": "Feature",
  "properties": {
    "gn:admin1_code":"9.0",
    "gn:asciiname":"Xulou",
    "gn:country_code":"CN",
    "gn:dem":125,
    "gn:feature_class":"P",
    "gn:feature_code":"PPL",
    "gn:name":"Xulou",
    "gn:population":0,
    "gn:timezone":"Asia/Shanghai",
    "iso:country":"CN",
    "name:zho_x_preferred":[
        "\u620c\u697c"
    ],
    "wof:name":"Xulou",
    "wof:placetype":"locality"
},
  "geometry": {"coordinates":[112.71899000000001,34.88343],"type":"Point"}
}