{
  "type": "Feature",
  "properties": {
    "gn:admin1_code":"2",
    "gn:asciiname":"Xiadongxi",
    "gn:country_code":"CN",
    "gn:dem":1021,
    "gn:feature_class":"P",
    "gn:feature_code":"PPL",
    "gn:name":"Xiadongxi",
    "gn:population":0,
    "gn:timezone":"Asia/Shanghai",
    "iso:country":"CN",
    "name:zho_x_preferred":[
        "\u4e0b\u4e1c\u6eaa"
    ],
    "wof:name":"Xiadongxi",
    "wof:placetype":"locality"
},
  "geometry": {"coordinates":[119.26972000000001,27.61944],"type":"Point"}
}