{
  "type": "Feature",
  "properties": {
    "gn:admin1_code":"21.0",
    "gn:asciiname":"Dawu Kougou Kouzi",
    "gn:country_code":"CN",
    "gn:dem":1163,
    "gn:feature_class":"P",
    "gn:feature_code":"PPL",
    "gn:name":"Dawu Kougou Kouzi",
    "gn:population":0,
    "gn:timezone":"Asia/Shanghai",
    "iso:country":"CN",
    "name:zho_x_preferred":[
        "\u5927\u6b66\u53e3\u6c9f\u53e3\u5b50"
    ],
    "wof:name":"Dawu Kougou Kouzi",
    "wof:placetype":"locality"
},
  "geometry": {"coordinates":[106.429,39.081],"type":"Point"}
}