{
  "type": "Feature",
  "properties": {
    "gn:admin1_code":"3.0",
    "gn:asciiname":"Zhongliancun",
    "gn:country_code":"CN",
    "gn:dem":18,
    "gn:feature_class":"P",
    "gn:feature_code":"PPL",
    "gn:name":"Zhongliancun",
    "gn:population":0,
    "gn:timezone":"Asia/Shanghai",
    "iso:country":"CN",
    "name:und_x_variant":[
        "\u4e2d\u8054\u6751"
    ],
    "wof:name":"Zhongliancun",
    "wof:placetype":"locality"
},
  "geometry": {"coordinates":[115.91697000000001,28.79664],"type":"Point"}
}