{
  "type": "Feature",
  "properties": {
    "gn:admin1_code":"32.0",
    "gn:asciiname":"Shanxizhai",
    "gn:country_code":"CN",
    "gn:dem":1117,
    "gn:feature_class":"P",
    "gn:feature_code":"PPL",
    "gn:name":"Shanxizhai",
    "gn:population":0,
    "gn:timezone":"Asia/Shanghai",
    "iso:country":"CN",
    "name:zho_x_preferred":[
        "\u5c71\u897f\u5be8"
    ],
    "wof:name":"Shanxizhai",
    "wof:placetype":"locality"
},
  "geometry": {"coordinates":[103.593,28.5316],"type":"Point"}
}