{
  "type": "Feature",
  "properties": {
    "gn:admin1_code":"24.0",
    "gn:asciiname":"Houzhuangshang",
    "gn:country_code":"CN",
    "gn:dem":1644,
    "gn:feature_class":"P",
    "gn:feature_code":"PPL",
    "gn:name":"Houzhuangshang",
    "gn:population":0,
    "gn:timezone":"Asia/Shanghai",
    "iso:country":"CN",
    "name:zho_x_preferred":[
        "\u540e\u5e84\u4e0a"
    ],
    "wof:name":"Houzhuangshang",
    "wof:placetype":"locality"
},
  "geometry": {"coordinates":[111.55434,37.99476],"type":"Point"}
}