{
  "type": "Feature",
  "properties": {
    "gn:admin1_code":"19.0",
    "gn:asciiname":"Chengjiatun",
    "gn:country_code":"CN",
    "gn:dem":11,
    "gn:feature_class":"P",
    "gn:feature_code":"PPL",
    "gn:name":"Chengjiatun",
    "gn:population":0,
    "gn:timezone":"Asia/Shanghai",
    "iso:country":"CN",
    "name:zho_x_preferred":[
        "\u7a0b\u5bb6\u5c6f"
    ],
    "wof:name":"Chengjiatun",
    "wof:placetype":"locality"
},
  "geometry": {"coordinates":[120.19917,40.16909],"type":"Point"}
}