{
  "type": "Feature",
  "properties": {
    "gn:admin1_code":"15.0",
    "gn:asciiname":"Wankouchuan",
    "gn:country_code":"CN",
    "gn:dem":2003,
    "gn:feature_class":"P",
    "gn:feature_code":"PPL",
    "gn:name":"Wankouchuan",
    "gn:population":0,
    "gn:timezone":"Asia/Shanghai",
    "iso:country":"CN",
    "name:zho_x_preferred":[
        "\u6e7e\u53e3\u5ddd"
    ],
    "wof:name":"Wankouchuan",
    "wof:placetype":"locality"
},
  "geometry": {"coordinates":[104.809,35.4429],"type":"Point"}
}