{
  "type": "Feature",
  "properties": {
    "gn:admin1_code":"4.0",
    "gn:asciiname":"Huayuangou",
    "gn:country_code":"CN",
    "gn:dem":9,
    "gn:feature_class":"P",
    "gn:feature_code":"PPL",
    "gn:name":"Huayuangou",
    "gn:population":0,
    "gn:timezone":"Asia/Shanghai",
    "iso:country":"CN",
    "name:zho_x_preferred":[
        "\u82b1\u56ed\u6c9f"
    ],
    "wof:name":"Huayuangou",
    "wof:placetype":"locality"
},
  "geometry": {"coordinates":[118.82468,31.87671],"type":"Point"}
}