{
  "type": "Feature",
  "properties": {
    "gn:admin1_code":"24.0",
    "gn:asciiname":"Huangmuyuan",
    "gn:country_code":"CN",
    "gn:dem":906,
    "gn:feature_class":"P",
    "gn:feature_code":"PPL",
    "gn:name":"Huangmuyuan",
    "gn:population":0,
    "gn:timezone":"Asia/Shanghai",
    "iso:country":"CN",
    "name:zho_x_preferred":[
        "\u9ec4\u6728\u539f"
    ],
    "wof:name":"Huangmuyuan",
    "wof:placetype":"locality"
},
  "geometry": {"coordinates":[111.92986999999999,36.32503],"type":"Point"}
}