{
  "type": "Feature",
  "properties": {
    "gn:admin1_code":"30.0",
    "gn:asciiname":"Dadaosha",
    "gn:country_code":"CN",
    "gn:dem":-3,
    "gn:feature_class":"P",
    "gn:feature_code":"PPL",
    "gn:name":"Dadaosha",
    "gn:population":0,
    "gn:timezone":"Asia/Shanghai",
    "iso:country":"CN",
    "name:zho_x_preferred":[
        "\u5927\u5200\u6c99"
    ],
    "wof:name":"Dadaosha",
    "wof:placetype":"locality"
},
  "geometry": {"coordinates":[113.44726,22.91284],"type":"Point"}
}