{
  "type": "Feature",
  "properties": {
    "gn:admin1_code":"15.0",
    "gn:asciiname":"Xiji",
    "gn:country_code":"CN",
    "gn:dem":1402,
    "gn:feature_class":"P",
    "gn:feature_code":"PPLA4",
    "gn:name":"Xiji",
    "gn:population":0,
    "gn:timezone":"Asia/Shanghai",
    "iso:country":"CN",
    "name:und_x_variant":[
        "\u559c\u96c6",
        "Xiji Xiang",
        "\u559c\u96c6\u4e61"
    ],
    "wof:name":"Xiji",
    "wof:placetype":"locality"
},
  "geometry": {"coordinates":[105.27627,33.78198],"type":"Point"}
}