{
  "type": "Feature",
  "properties": {
    "gn:admin1_code":"8.0",
    "gn:asciiname":"Jianhua Yi'erdui",
    "gn:country_code":"CN",
    "gn:dem":272,
    "gn:feature_class":"P",
    "gn:feature_code":"PPLF",
    "gn:name":"Jianhua Yi\u2019erdui",
    "gn:population":0,
    "gn:timezone":"Asia/Shanghai",
    "iso:country":"CN",
    "name:und_x_variant":[
        "Jianhua Yi\u2019erdui"
    ],
    "name:zho_x_preferred":[
        "\u5efa\u534e\u4e00\u4e8c\u961f"
    ],
    "wof:name":"Jianhua Yi'erdui",
    "wof:placetype":"locality"
},
  "geometry": {"coordinates":[125.24018999999998,48.04306],"type":"Point"}
}