{
  "type": "Feature",
  "properties": {
    "gn:admin1_code":"10.0",
    "gn:asciiname":"Gaoxinzhuang",
    "gn:country_code":"CN",
    "gn:dem":10,
    "gn:feature_class":"P",
    "gn:feature_code":"PPL",
    "gn:name":"Gaoxinzhuang",
    "gn:population":0,
    "gn:timezone":"Asia/Shanghai",
    "iso:country":"CN",
    "name:zho_x_preferred":[
        "\u9ad8\u8f9b\u5e84"
    ],
    "wof:name":"Gaoxinzhuang",
    "wof:placetype":"locality"
},
  "geometry": {"coordinates":[116.947,38.1951],"type":"Point"}
}