{
  "type": "Feature",
  "properties": {
    "gn:admin1_code":"9.0",
    "gn:asciiname":"Wangleting",
    "gn:country_code":"CN",
    "gn:dem":60,
    "gn:feature_class":"P",
    "gn:feature_code":"PPL",
    "gn:name":"Wangleting",
    "gn:population":0,
    "gn:timezone":"Asia/Shanghai",
    "iso:country":"CN",
    "name:zho_x_preferred":[
        "\u738b\u4e50\u4ead"
    ],
    "wof:name":"Wangleting",
    "wof:placetype":"locality"
},
  "geometry": {"coordinates":[114.63592,34.3112],"type":"Point"}
}