{
  "type": "Feature",
  "properties": {
    "gn:admin1_code":"1.0",
    "gn:asciiname":"Qigancun",
    "gn:country_code":"CN",
    "gn:dem":37,
    "gn:feature_class":"P",
    "gn:feature_code":"PPL",
    "gn:name":"Qigancun",
    "gn:population":0,
    "gn:timezone":"Asia/Shanghai",
    "iso:country":"CN",
    "name:zho_x_preferred":[
        "\u65d7\u6746\u6751"
    ],
    "wof:name":"Qigancun",
    "wof:placetype":"locality"
},
  "geometry": {"coordinates":[116.89400999999999,32.10902],"type":"Point"}
}