{
  "type": "Feature",
  "properties": {
    "gn:admin1_code":"10",
    "gn:asciiname":"Huangbeiping",
    "gn:country_code":"CN",
    "gn:dem":338,
    "gn:feature_class":"P",
    "gn:feature_code":"PPL",
    "gn:name":"Huangbeiping",
    "gn:population":0,
    "gn:timezone":"Asia/Shanghai",
    "iso:country":"CN",
    "name:zho_x_preferred":[
        "\u9ec4\u5317\u576a"
    ],
    "wof:name":"Huangbeiping",
    "wof:placetype":"locality"
},
  "geometry": {"coordinates":[114.17861000000001,37.59917],"type":"Point"}
}