{
  "type": "Feature",
  "properties": {
    "gn:admin1_code":"29.0",
    "gn:asciiname":"Shanlinjiao",
    "gn:country_code":"CN",
    "gn:dem":2749,
    "gn:feature_class":"P",
    "gn:feature_code":"PPL",
    "gn:name":"Shanlinjiao",
    "gn:population":0,
    "gn:timezone":"Asia/Shanghai",
    "iso:country":"CN",
    "name:zho_x_preferred":[
        "\u5c71\u6797\u811a"
    ],
    "wof:name":"Shanlinjiao",
    "wof:placetype":"locality"
},
  "geometry": {"coordinates":[103.836,27.3776],"type":"Point"}
}