{
  "type": "Feature",
  "properties": {
    "gn:admin1_code":"07",
    "gn:asciiname":"Shanbei",
    "gn:country_code":"CN",
    "gn:dem":657,
    "gn:feature_class":"P",
    "gn:feature_code":"PPL",
    "gn:name":"Shanbei",
    "gn:population":0,
    "gn:timezone":"Asia/Shanghai",
    "iso:country":"CN",
    "name:zho_x_preferred":[
        "\u5c71\u8d1d"
    ],
    "wof:name":"Shanbei",
    "wof:placetype":"locality"
},
  "geometry": {"coordinates":[117.48999999999999,25.06438],"type":"Point"}
}