{
  "type": "Feature",
  "properties": {
    "gn:admin1_code":"32.0",
    "gn:asciiname":"Gaoshanpu",
    "gn:country_code":"CN",
    "gn:dem":491,
    "gn:feature_class":"P",
    "gn:feature_code":"PPL",
    "gn:name":"Gaoshanpu",
    "gn:population":0,
    "gn:timezone":"Asia/Shanghai",
    "iso:country":"CN",
    "name:zho_x_preferred":[
        "\u9ad8\u5c71\u94fa"
    ],
    "wof:name":"Gaoshanpu",
    "wof:placetype":"locality"
},
  "geometry": {"coordinates":[105.14842,31.10976],"type":"Point"}
}