{
  "type": "Feature",
  "properties": {
    "gn:admin1_code":"29.0",
    "gn:asciiname":"Shijiazhai",
    "gn:country_code":"CN",
    "gn:dem":1376,
    "gn:feature_class":"P",
    "gn:feature_code":"PPL",
    "gn:name":"Shijiazhai",
    "gn:population":0,
    "gn:timezone":"Asia/Shanghai",
    "iso:country":"CN",
    "name:zho_x_preferred":[
        "\u65bd\u5bb6\u5be8"
    ],
    "wof:name":"Shijiazhai",
    "wof:placetype":"locality"
},
  "geometry": {"coordinates":[102.89,23.7363],"type":"Point"}
}