{
  "type": "Feature",
  "properties": {
    "gn:admin1_code":"5.0",
    "gn:asciiname":"Xinpingling",
    "gn:country_code":"CN",
    "gn:dem":714,
    "gn:feature_class":"P",
    "gn:feature_code":"PPL",
    "gn:name":"Xinpingling",
    "gn:population":0,
    "gn:timezone":"Asia/Shanghai",
    "iso:country":"CN",
    "name:und_x_variant":[
        "\u65b0\u5e73\u5cad"
    ],
    "wof:name":"Xinpingling",
    "wof:placetype":"locality"
},
  "geometry": {"coordinates":[128.40360000000001,42.67805],"type":"Point"}
}