{
  "type": "Feature",
  "properties": {
    "gn:admin1_code":"24",
    "gn:asciiname":"Tai'er'ao",
    "gn:country_code":"CN",
    "gn:dem":1047,
    "gn:feature_class":"P",
    "gn:feature_code":"PPL",
    "gn:name":"Tai\u2019er\u2019ao",
    "gn:population":0,
    "gn:timezone":"Asia/Shanghai",
    "iso:country":"CN",
    "name:und_x_variant":[
        "Tai\u2019er\u2019ao"
    ],
    "name:zho_x_preferred":[
        "\u592a\u513f\u51f9"
    ],
    "wof:name":"Tai'er'ao",
    "wof:placetype":"locality"
},
  "geometry": {"coordinates":[111.1692,35.87364],"type":"Point"}
}