{
  "type": "Feature",
  "properties": {
    "gn:admin1_code":"19.0",
    "gn:asciiname":"Liuxiaobu",
    "gn:country_code":"CN",
    "gn:dem":531,
    "gn:feature_class":"P",
    "gn:feature_code":"PPL",
    "gn:name":"Liuxiaobu",
    "gn:population":0,
    "gn:timezone":"Asia/Shanghai",
    "iso:country":"CN",
    "name:und_x_variant":[
        "Liuxiaopu",
        "Liuxiaobu"
    ],
    "name:zho_x_preferred":[
        "\u5218\u5c0f\u5821"
    ],
    "wof:name":"Liuxiaobu",
    "wof:placetype":"locality"
},
  "geometry": {"coordinates":[124.726,42.1269],"type":"Point"}
}