{
  "type": "Feature",
  "properties": {
    "gn:admin1_code":"7.0",
    "gn:asciiname":"Xiabaoshan",
    "gn:country_code":"CN",
    "gn:dem":451,
    "gn:feature_class":"P",
    "gn:feature_code":"PPL",
    "gn:name":"Xiabaoshan",
    "gn:population":0,
    "gn:timezone":"Asia/Shanghai",
    "iso:country":"CN",
    "name:und_x_variant":[
        "\u4e0b\u5b9d\u5c71"
    ],
    "name:zho_x_preferred":[
        "\u4e0b\u5b9d\u5c71"
    ],
    "wof:name":"Xiabaoshan",
    "wof:placetype":"locality"
},
  "geometry": {"coordinates":[117.63514000000001,26.48107000000001],"type":"Point"}
}