{
  "type": "Feature",
  "properties": {
    "gn:admin1_code":"1.0",
    "gn:asciiname":"Jinqiaocun",
    "gn:country_code":"CN",
    "gn:dem":5,
    "gn:feature_class":"P",
    "gn:feature_code":"PPL",
    "gn:name":"Jinqiaocun",
    "gn:population":0,
    "gn:timezone":"Asia/Shanghai",
    "iso:country":"CN",
    "name:und_x_variant":[
        "Jinqiao",
        "Jinqiaocun"
    ],
    "name:zho_x_preferred":[
        "\u91d1\u6865"
    ],
    "name:zho_x_variant":[
        "\u91d1\u6865\u6751"
    ],
    "wof:name":"Jinqiaocun",
    "wof:placetype":"locality"
},
  "geometry": {"coordinates":[118.75230000000001,31.17615],"type":"Point"}
}