{
  "type": "Feature",
  "properties": {
    "gn:admin1_code":"19.0",
    "gn:asciiname":"Guangning Wopeng",
    "gn:country_code":"CN",
    "gn:dem":75,
    "gn:feature_class":"P",
    "gn:feature_code":"PPL",
    "gn:name":"Guangning Wopeng",
    "gn:population":0,
    "gn:timezone":"Asia/Shanghai",
    "iso:country":"CN",
    "name:zho_x_preferred":[
        "\u5e7f\u5b81\u7a9d\u68da"
    ],
    "wof:name":"Guangning Wopeng",
    "wof:placetype":"locality"
},
  "geometry": {"coordinates":[123.879,42.5415],"type":"Point"}
}