{
  "type": "Feature",
  "properties": {
    "gn:admin1_code":"32.0",
    "gn:asciiname":"Xiaohuofang",
    "gn:country_code":"CN",
    "gn:dem":1823,
    "gn:feature_class":"P",
    "gn:feature_code":"PPL",
    "gn:name":"Xiaohuofang",
    "gn:population":0,
    "gn:timezone":"Asia/Shanghai",
    "iso:country":"CN",
    "name:zho_x_preferred":[
        "\u5c0f\u4f19\u623f"
    ],
    "wof:name":"Xiaohuofang",
    "wof:placetype":"locality"
},
  "geometry": {"coordinates":[102.08099,29.12948],"type":"Point"}
}