{
  "type": "Feature",
  "properties": {
    "gn:admin1_code":"02",
    "gn:asciiname":"Maozhicun",
    "gn:country_code":"CN",
    "gn:dem":5,
    "gn:feature_class":"P",
    "gn:feature_code":"PPL",
    "gn:name":"Maozhicun",
    "gn:population":0,
    "gn:timezone":"Asia/Shanghai",
    "iso:country":"CN",
    "name:und_x_variant":[
        "Mao-y\u00fc",
        "Maozhi",
        "\u6bdb\u5cd9",
        "Maozhicun"
    ],
    "name:zho_x_preferred":[
        "\u6bdb\u5cd9\u6751"
    ],
    "wof:name":"Maozhicun",
    "wof:placetype":"locality"
},
  "geometry": {"coordinates":[122.06829999999999,30.14893],"type":"Point"}
}