{
  "type": "Feature",
  "properties": {
    "gn:admin1_code":"19.0",
    "gn:asciiname":"Huanggutun",
    "gn:country_code":"CN",
    "gn:dem":19,
    "gn:feature_class":"P",
    "gn:feature_code":"PPL",
    "gn:name":"Huanggutun",
    "gn:population":0,
    "gn:timezone":"Asia/Shanghai",
    "iso:country":"CN",
    "name:zho_x_preferred":[
        "\u7687\u59d1\u5c6f"
    ],
    "wof:name":"Huanggutun",
    "wof:placetype":"locality"
},
  "geometry": {"coordinates":[119.86596000000002,40.09871],"type":"Point"}
}