{
  "type": "Feature",
  "properties": {
    "gn:admin1_code":"1.0",
    "gn:asciiname":"Zhangcun",
    "gn:country_code":"CN",
    "gn:dem":10,
    "gn:feature_class":"P",
    "gn:feature_code":"PPL",
    "gn:name":"Zhangcun",
    "gn:population":0,
    "gn:timezone":"Asia/Shanghai",
    "iso:country":"CN",
    "name:zho_x_preferred":[
        "Zhangcun"
    ],
    "name:zho_x_variant":[
        "\u5f20\u6751"
    ],
    "wof:name":"Zhangcun",
    "wof:placetype":"locality"
},
  "geometry": {"coordinates":[119.06297000000001,31.04693],"type":"Point"}
}