{
  "type": "Feature",
  "properties": {
    "gn:admin1_code":"1.0",
    "gn:asciiname":"Shihekoucun",
    "gn:country_code":"CN",
    "gn:dem":78,
    "gn:feature_class":"P",
    "gn:feature_code":"PPL",
    "gn:name":"Shihekoucun",
    "gn:population":0,
    "gn:timezone":"Asia/Shanghai",
    "iso:country":"CN",
    "name:zho_x_preferred":[
        "\u77f3\u6cb3\u53e3\u6751"
    ],
    "wof:name":"Shihekoucun",
    "wof:placetype":"locality"
},
  "geometry": {"coordinates":[116.52184,31.5186],"type":"Point"}
}