{
  "type": "Feature",
  "properties": {
    "gn:admin1_code":"19.0",
    "gn:asciiname":"Toudaoheshangbaocun",
    "gn:country_code":"CN",
    "gn:dem":468,
    "gn:feature_class":"P",
    "gn:feature_code":"PPL",
    "gn:name":"Toudaoheshangbaocun",
    "gn:population":0,
    "gn:timezone":"Asia/Shanghai",
    "iso:country":"CN",
    "wof:name":"Toudaoheshangbaocun",
    "wof:placetype":"locality"
},
  "geometry": {"coordinates":[125.12463,42.06846],"type":"Point"}
}