{
  "type": "Feature",
  "properties": {
    "gn:admin1_code":"25.0",
    "gn:asciiname":"Dongdazhuang",
    "gn:cc2":"CN",
    "gn:country_code":"CN",
    "gn:dem":8,
    "gn:feature_class":"P",
    "gn:feature_code":"PPL",
    "gn:name":"Dongdazhuang",
    "gn:population":0,
    "gn:timezone":"Asia/Shanghai",
    "iso:country":"CN",
    "name:zho_x_preferred":[
        "\u8463\u5927\u5e84"
    ],
    "wof:name":"Dongdazhuang",
    "wof:placetype":"locality"
},
  "geometry": {"coordinates":[119.76895,35.64721],"type":"Point"}
}