{
  "type": "Feature",
  "properties": {
    "gn:admin1_code":"9.0",
    "gn:asciiname":"Fenghuangtai",
    "gn:country_code":"CN",
    "gn:dem":704,
    "gn:feature_class":"P",
    "gn:feature_code":"PPL",
    "gn:name":"Fenghuangtai",
    "gn:population":0,
    "gn:timezone":"Asia/Shanghai",
    "iso:country":"CN",
    "name:zho_x_preferred":[
        "\u51e4\u51f0\u53f0"
    ],
    "wof:name":"Fenghuangtai",
    "wof:placetype":"locality"
},
  "geometry": {"coordinates":[111.00688999999998,34.5415],"type":"Point"}
}