{
  "type": "Feature",
  "properties": {
    "gn:admin1_code":"11",
    "gn:asciiname":"Muguayu",
    "gn:country_code":"CN",
    "gn:dem":423,
    "gn:feature_class":"P",
    "gn:feature_code":"PPL",
    "gn:name":"Muguayu",
    "gn:population":0,
    "gn:timezone":"Asia/Shanghai",
    "iso:country":"CN",
    "wof:name":"Muguayu",
    "wof:placetype":"locality"
},
  "geometry": {"coordinates":[110.95583000000001,29.71583],"type":"Point"}
}