{
  "type": "Feature",
  "properties": {
    "gn:admin1_code":"25.0",
    "gn:asciiname":"Xilugezhuang",
    "gn:country_code":"CN",
    "gn:dem":7,
    "gn:feature_class":"P",
    "gn:feature_code":"PPL",
    "gn:name":"Xilugezhuang",
    "gn:population":0,
    "gn:timezone":"Asia/Shanghai",
    "iso:country":"CN",
    "name:zho_x_preferred":[
        "\u897f\u9646\u6208\u5e84"
    ],
    "wof:name":"Xilugezhuang",
    "wof:placetype":"locality"
},
  "geometry": {"coordinates":[120.88229,36.44485],"type":"Point"}
}