{
  "type": "Feature",
  "properties": {
    "gn:admin1_code":"18",
    "gn:asciiname":"Angzhe",
    "gn:country_code":"CN",
    "gn:dem":322,
    "gn:feature_class":"P",
    "gn:feature_code":"PPL",
    "gn:name":"Angzhe",
    "gn:population":0,
    "gn:timezone":"Asia/Shanghai",
    "iso:country":"CN",
    "name:zho_x_preferred":[
        "\u6602\u8005"
    ],
    "wof:name":"Angzhe",
    "wof:placetype":"locality"
},
  "geometry": {"coordinates":[106.51600000000001,25.0683],"type":"Point"}
}