{
  "type": "Feature",
  "properties": {
    "gn:admin1_code":"4.0",
    "gn:asciiname":"Lutancun",
    "gn:country_code":"CN",
    "gn:dem":8,
    "gn:feature_class":"P",
    "gn:feature_code":"PPL",
    "gn:name":"L\u00fctancun",
    "gn:population":0,
    "gn:timezone":"Asia/Shanghai",
    "iso:country":"CN",
    "name:und_x_variant":[
        "L\u00fctancun"
    ],
    "name:zho_x_preferred":[
        "\u5415\u6ee9\u6751"
    ],
    "wof:name":"Lutancun",
    "wof:placetype":"locality"
},
  "geometry": {"coordinates":[119.75208000000001,34.03308],"type":"Point"}
}