{
  "type": "Feature",
  "properties": {
    "gn:admin1_code":"18",
    "gn:asciiname":"Dongjiapo",
    "gn:country_code":"CN",
    "gn:dem":1375,
    "gn:feature_class":"P",
    "gn:feature_code":"PPL",
    "gn:name":"Dongjiapo",
    "gn:population":0,
    "gn:timezone":"Asia/Shanghai",
    "iso:country":"CN",
    "name:zho_x_preferred":[
        "\u8463\u5bb6\u5761"
    ],
    "wof:name":"Dongjiapo",
    "wof:placetype":"locality"
},
  "geometry": {"coordinates":[105.30500000000001,25.5759],"type":"Point"}
}