{
  "type": "Feature",
  "properties": {
    "gn:admin1_code":"16.0",
    "gn:asciiname":"Di'ai",
    "gn:country_code":"CN",
    "gn:dem":143,
    "gn:feature_class":"P",
    "gn:feature_code":"PPL",
    "gn:name":"Di\u2019ai",
    "gn:population":0,
    "gn:timezone":"Asia/Shanghai",
    "iso:country":"CN",
    "name:und_x_variant":[
        "Di\u2019ai"
    ],
    "name:zho_x_preferred":[
        "\u5e95\u9698"
    ],
    "wof:name":"Di'ai",
    "wof:placetype":"locality"
},
  "geometry": {"coordinates":[107.643,22.9749],"type":"Point"}
}