{
  "type": "Feature",
  "properties": {
    "gn:admin1_code":"8.0",
    "gn:asciiname":"Xingjia Weizi",
    "gn:country_code":"CN",
    "gn:dem":188,
    "gn:feature_class":"P",
    "gn:feature_code":"PPL",
    "gn:name":"Xingjia Weizi",
    "gn:population":0,
    "gn:timezone":"Asia/Shanghai",
    "iso:country":"CN",
    "name:zho_x_preferred":[
        "\u90a2\u5bb6\u56f4\u5b50"
    ],
    "wof:name":"Xingjia Weizi",
    "wof:placetype":"locality"
},
  "geometry": {"coordinates":[125.58669999999999,47.12753],"type":"Point"}
}