{
  "type": "Feature",
  "properties": {
    "gn:admin1_code":"01",
    "gn:asciiname":"Quantang",
    "gn:cc2":"CN",
    "gn:country_code":"CN",
    "gn:dem":6,
    "gn:feature_class":"P",
    "gn:feature_code":"PPL",
    "gn:name":"Quantang",
    "gn:population":0,
    "gn:timezone":"Asia/Shanghai",
    "iso:country":"CN",
    "name:und_x_variant":[
        "Ch\u2019\u00fcan-t\u2019ang-cheh",
        "Chuan-t\u2019ang-chen",
        "Ch\u2019\u00fcan-t\u2019ang-chieh",
        "Ch\u2019\u00fcan-tang",
        "Quantang"
    ],
    "wof:name":"Quantang",
    "wof:placetype":"locality"
},
  "geometry": {"coordinates":[117.68333,31.18333],"type":"Point"}
}