{
  "type": "Feature",
  "properties": {
    "gn:admin1_code":"4.0",
    "gn:asciiname":"Liuhucun",
    "gn:country_code":"CN",
    "gn:dem":21,
    "gn:feature_class":"P",
    "gn:feature_code":"PPL",
    "gn:name":"Liuhucun",
    "gn:population":0,
    "gn:timezone":"Asia/Shanghai",
    "iso:country":"CN",
    "name:zho_x_preferred":[
        "\u67f3\u6e56\u6751"
    ],
    "wof:name":"Liuhucun",
    "wof:placetype":"locality"
},
  "geometry": {"coordinates":[118.01049999999999,34.09851],"type":"Point"}
}