{
  "type": "Feature",
  "properties": {
    "gn:admin1_code":"3.0",
    "gn:asciiname":"Chenjiaba",
    "gn:country_code":"CN",
    "gn:dem":118,
    "gn:feature_class":"P",
    "gn:feature_code":"PPL",
    "gn:name":"Chenjiaba",
    "gn:population":0,
    "gn:timezone":"Asia/Shanghai",
    "iso:country":"CN",
    "name:und_x_variant":[
        "\u9648\u5bb6\u575d"
    ],
    "wof:name":"Chenjiaba",
    "wof:placetype":"locality"
},
  "geometry": {"coordinates":[115.4687,27.08651],"type":"Point"}
}