{
  "type": "Feature",
  "properties": {
    "gn:admin1_code":"9.0",
    "gn:asciiname":"Yuandongcun",
    "gn:country_code":"CN",
    "gn:dem":403,
    "gn:feature_class":"P",
    "gn:feature_code":"PPL",
    "gn:name":"Yuandongcun",
    "gn:population":0,
    "gn:timezone":"Asia/Shanghai",
    "iso:country":"CN",
    "name:zho_x_preferred":[
        "\u9662\u4e1c\u6751"
    ],
    "wof:name":"Yuandongcun",
    "wof:placetype":"locality"
},
  "geometry": {"coordinates":[111.76551000000001,34.35355999999999],"type":"Point"}
}