{
  "type": "Feature",
  "properties": {
    "gn:admin1_code":"29.0",
    "gn:asciiname":"Yalading",
    "gn:country_code":"CN",
    "gn:dem":2730,
    "gn:feature_class":"P",
    "gn:feature_code":"PPL",
    "gn:name":"Yalading",
    "gn:population":0,
    "gn:timezone":"Asia/Shanghai",
    "iso:country":"CN",
    "name:zho_x_preferred":[
        "\u9e26\u62c9\u4e01"
    ],
    "wof:name":"Yalading",
    "wof:placetype":"locality"
},
  "geometry": {"coordinates":[99.2478,27.8461],"type":"Point"}
}