{
  "type": "Feature",
  "properties": {
    "gn:admin1_code":"11.0",
    "gn:asciiname":"Jianshanchong",
    "gn:country_code":"CN",
    "gn:dem":259,
    "gn:feature_class":"P",
    "gn:feature_code":"PPL",
    "gn:name":"Jianshanchong",
    "gn:population":0,
    "gn:timezone":"Asia/Shanghai",
    "iso:country":"CN",
    "name:zho_x_preferred":[
        "\u95f4\u5c71\u51b2"
    ],
    "wof:name":"Jianshanchong",
    "wof:placetype":"locality"
},
  "geometry": {"coordinates":[113.58472,28.29617],"type":"Point"}
}