{
  "type": "Feature",
  "properties": {
    "gn:admin1_code":"7.0",
    "gn:asciiname":"Wangkeng",
    "gn:country_code":"CN",
    "gn:dem":358,
    "gn:feature_class":"P",
    "gn:feature_code":"PPL",
    "gn:name":"Wangkeng",
    "gn:population":0,
    "gn:timezone":"Asia/Shanghai",
    "iso:country":"CN",
    "name:und_x_variant":[
        "\u738b\u5751"
    ],
    "name:zho_x_preferred":[
        "\u738b\u5751"
    ],
    "wof:name":"Wangkeng",
    "wof:placetype":"locality"
},
  "geometry": {"coordinates":[116.77052999999999,25.79576],"type":"Point"}
}