{
  "type": "Feature",
  "properties": {
    "gn:admin1_code":"23",
    "gn:asciiname":"Qiujiapeng",
    "gn:cc2":"CN",
    "gn:country_code":"CN",
    "gn:dem":3,
    "gn:feature_class":"P",
    "gn:feature_code":"PPL",
    "gn:name":"Qiujiapeng",
    "gn:population":0,
    "gn:timezone":"Asia/Shanghai",
    "iso:country":"CN",
    "name:und_x_variant":[
        "Ch\u2019iu-chia-p\u2019eng",
        "Ch\u2019iu-chia-chai",
        "Qiujiapeng"
    ],
    "wof:name":"Qiujiapeng",
    "wof:placetype":"locality"
},
  "geometry": {"coordinates":[121.80389,31.10583],"type":"Point"}
}