{
  "type": "Feature",
  "properties": {
    "gn:admin1_code":"32.0",
    "gn:asciiname":"Rixiajuemu",
    "gn:country_code":"CN",
    "gn:dem":3149,
    "gn:feature_class":"P",
    "gn:feature_code":"PPL",
    "gn:name":"Rixiajuemu",
    "gn:population":0,
    "gn:timezone":"Asia/Shanghai",
    "iso:country":"CN",
    "name:zho_x_preferred":[
        "\u65e5\u5477\u89c9\u59c6"
    ],
    "wof:name":"Rixiajuemu",
    "wof:placetype":"locality"
},
  "geometry": {"coordinates":[102.54600000000001,27.8371],"type":"Point"}
}