{
  "type": "Feature",
  "properties": {
    "gn:admin1_code":"8.0",
    "gn:asciiname":"Kubaotun",
    "gn:country_code":"CN",
    "gn:dem":185,
    "gn:feature_class":"P",
    "gn:feature_code":"PPL",
    "gn:name":"Kubaotun",
    "gn:population":0,
    "gn:timezone":"Asia/Shanghai",
    "iso:country":"CN",
    "name:zho_x_preferred":[
        "\u5e93\u5b9d\u5c6f"
    ],
    "wof:name":"Kubaotun",
    "wof:placetype":"locality"
},
  "geometry": {"coordinates":[123.73417999999999,48.0213],"type":"Point"}
}