{
  "type": "Feature",
  "properties": {
    "gn:admin1_code":"11.0",
    "gn:asciiname":"Bailiantang",
    "gn:country_code":"CN",
    "gn:dem":50,
    "gn:feature_class":"P",
    "gn:feature_code":"PPL",
    "gn:name":"Bailiantang",
    "gn:population":0,
    "gn:timezone":"Asia/Shanghai",
    "iso:country":"CN",
    "name:zho_x_preferred":[
        "\u767d\u83b2\u5858"
    ],
    "wof:name":"Bailiantang",
    "wof:placetype":"locality"
},
  "geometry": {"coordinates":[113.14519,27.5219],"type":"Point"}
}