{
  "type": "Feature",
  "properties": {
    "gn:admin1_code":"19.0",
    "gn:asciiname":"Songjia Buzi",
    "gn:country_code":"CN",
    "gn:dem":200,
    "gn:feature_class":"P",
    "gn:feature_code":"PPL",
    "gn:name":"Songjia Buzi",
    "gn:population":0,
    "gn:timezone":"Asia/Shanghai",
    "iso:country":"CN",
    "name:und_x_variant":[
        "Songjiapuzi",
        "\u5b8b\u5bb6\u5821\u5b50",
        "Songjia Buzi"
    ],
    "wof:name":"Songjia Buzi",
    "wof:placetype":"locality"
},
  "geometry": {"coordinates":[123.44190999999999,40.42576],"type":"Point"}
}