{
  "type": "Feature",
  "properties": {
    "gn:admin1_code":"31.0",
    "gn:asciiname":"Fangxiang",
    "gn:country_code":"CN",
    "gn:dem":228,
    "gn:feature_class":"P",
    "gn:feature_code":"PPL",
    "gn:name":"Fangxiang",
    "gn:population":0,
    "gn:timezone":"Asia/Shanghai",
    "iso:country":"CN",
    "name:bul_x_preferred":[
        "\u0424\u0430\u043d\u0441\u044f\u043d"
    ],
    "name:deu_x_preferred":[
        "Fangxiang"
    ],
    "name:fin_x_preferred":[
        "Fangxiang"
    ],
    "name:kor_x_preferred":[
        "\ubc29\ud5a5"
    ],
    "name:zho_x_preferred":[
        "\u65b9\u9999"
    ],
    "wof:name":"Fangxiang",
    "wof:placetype":"locality"
},
  "geometry": {"coordinates":[109.46145,19.17945],"type":"Point"}
}