{
  "type": "Feature",
  "properties": {
    "gn:admin1_code":"08",
    "gn:asciiname":"Heigang",
    "gn:country_code":"CN",
    "gn:dem":159,
    "gn:feature_class":"P",
    "gn:feature_code":"PPLA4",
    "gn:name":"Heigang",
    "gn:population":0,
    "gn:timezone":"Asia/Shanghai",
    "iso:country":"CN",
    "name:und_x_variant":[
        "Heigang Xiang"
    ],
    "name:zho_x_preferred":[
        "\u9ed1\u5c97"
    ],
    "name:zho_x_variant":[
        "\u9ed1\u5c97\u4e61"
    ],
    "wof:name":"Heigang",
    "wof:placetype":"locality"
},
  "geometry": {"coordinates":[123.39910999999999,47.24824],"type":"Point"}
}