{
  "type": "Feature",
  "properties": {
    "gn:country":"CN",
    "gn:fcode":"PPL",
    "gn:pop":60444,
    "iso:country":"CN",
    "name:ara_x_preferred":[
        "\u0644\u0648\u0646\u063a \u0643\u0648\u0647"
    ],
    "name:ben_x_preferred":[
        "\u09b2\u0982\u0995\u09c1"
    ],
    "name:dan_x_preferred":[
        "Longkou"
    ],
    "name:deu_x_preferred":[
        "Longkou"
    ],
    "name:ell_x_preferred":[
        "\u039b\u03cc\u03bd\u03b3\u03ba\u03bf\u03c5"
    ],
    "name:eng_x_preferred":[
        "Longkou"
    ],
    "name:epo_x_preferred":[
        "Longkou"
    ],
    "name:fin_x_preferred":[
        "Longkou"
    ],
    "name:fra_x_preferred":[
        "Longkou"
    ],
    "name:gan_x_preferred":[
        "\u9f99\u53e3\u5e02"
    ],
    "name:guj_x_preferred":[
        "\u0ab2\u0acb\u0a82\u0a97\u0a95\u0acb\u0a89"
    ],
    "name:hin_x_preferred":[
        "\u0932\u093e\u0902\u0917\u0915\u0942"
    ],
    "name:ind_x_preferred":[
        "Longkou"
    ],
    "name:ita_x_preferred":[
        "Longkou"
    ],
    "name:jpn_x_preferred":[
        "\u7adc\u53e3\u5e02"
    ],
    "name:kan_x_preferred":[
        "\u0cb2\u0cbe\u0c82\u0c97\u0ccd\u0c95\u0ccc"
    ],
    "name:kik_x_preferred":[
        "Longkou"
    ],
    "name:kor_x_preferred":[
        "\ub8fd\ucee4\uc6b0\uc2dc"
    ],
    "name:lav_x_preferred":[
        "Longkou"
    ],
    "name:lit_x_preferred":[
        "Longkou"
    ],
    "name:mar_x_preferred":[
        "\u0932\u0949\u0902\u0917\u0915\u093e\u090a"
    ],
    "name:msa_x_preferred":[
        "Longkou"
    ],
    "name:nan_x_preferred":[
        "Li\u00f4ng-kh\u00e1u-chh\u012b"
    ],
    "name:nld_x_preferred":[
        "Longkou"
    ],
    "name:nob_x_preferred":[
        "Longkou"
    ],
    "name:pol_x_preferred":[
        "Longkou"
    ],
    "name:rus_x_preferred":[
        "\u041b\u0443\u043d\u043a\u043e\u0443"
    ],
    "name:sin_x_preferred":[
        "\u0dbd\u0ddd\u0db1\u0dca\u0d9c\u0dca\u0d9a\u0ddd"
    ],
    "name:swe_x_preferred":[
        "Longkou"
    ],
    "name:tam_x_preferred":[
        "\u0bb2\u0bcb\u0b99\u0bcd\u0b95\u0bcb\u0bb5\u0bc1"
    ],
    "name:tel_x_preferred":[
        "\u0c32\u0c3e\u0c02\u0c17\u0c4d \u0c15\u0c42"
    ],
    "name:tha_x_preferred":[
        "\u0e2b\u0e25\u0e07\u0e42\u0e02\u0e48\u0e27"
    ],
    "name:tur_x_preferred":[
        "Longkou"
    ],
    "name:ukr_x_preferred":[
        "\u041b\u043e\u0443\u043a\u043e\u0443"
    ],
    "name:unk_x_variant":[
        "Lung-kou-shih"
    ],
    "name:urd_x_preferred":[
        "\u0644\u0648\u0646\u06af\u06a9\u0648\u0648"
    ],
    "name:vie_x_preferred":[
        "Long Kh\u1ea9u"
    ],
    "name:war_x_preferred":[
        "Longkou"
    ],
    "name:wuu_x_preferred":[
        "\u9f99\u53e3\u5e02"
    ],
    "name:yue_x_preferred":[
        "\u9f8d\u53e3"
    ],
    "name:zho_x_preferred":[
        "\u9f99\u6e2f"
    ],
    "name:zho_x_variant":[
        "\u9f99\u6e2f\u8857\u9053",
        "\u9f99\u53e3\u5e02"
    ],
    "qs:name":"Longkou",
    "qs:photos_9r":0,
    "qs:photos_sr":0,
    "qs:pop_sr":"8",
    "wd:wordcount":384,
    "wof:name":"Longkou",
    "wof:placetype":"locality",
    "wof:population":60444
},
  "geometry": {"coordinates":[120.32861,37.65083],"type":"Point"}
}