{
  "type": "Feature",
  "properties": {
    "gn:country":"CN",
    "gn:fcode":"PPL",
    "gn:pop":60444,
    "iso:country":"CN",
    "name:eng_x_preferred":[
        "Longkou"
    ],
    "name:unk_x_variant":[
        "Lung-kou-shih"
    ],
    "name:zho_x_preferred":[
        "\u9f99\u6e2f"
    ],
    "name:zho_x_variant":[
        "\u9f99\u6e2f\u8857\u9053"
    ],
    "qs:name":"Longkou",
    "qs:photos_9r":0,
    "qs:photos_sr":0,
    "qs:pop_sr":"8",
    "wd:wordcount":384,
    "wof:name":"Longkou",
    "wof:placetype":"locality",
    "wof:population":60444
},
  "geometry": {"coordinates":[120.32861,37.65083],"type":"Point"}
}