{
  "type": "Feature",
  "properties": {
    "gn:admin1_code":"26",
    "gn:asciiname":"Wangmeizhuang",
    "gn:country_code":"CN",
    "gn:dem":756,
    "gn:feature_class":"P",
    "gn:feature_code":"PPL",
    "gn:name":"Wangmeizhuang",
    "gn:population":0,
    "gn:timezone":"Asia/Shanghai",
    "iso:country":"CN",
    "name:und_x_variant":[
        "\u738b\u6885\u5e84"
    ],
    "name:zho_x_preferred":[
        "\u738b\u6885\u5e84"
    ],
    "wof:name":"Wangmeizhuang",
    "wof:placetype":"locality"
},
  "geometry": {"coordinates":[108.41916999999999,34.58861],"type":"Point"}
}