{
  "type": "Feature",
  "properties": {
    "gn:admin1_code":"29",
    "gn:asciiname":"Tigupu",
    "gn:country_code":"CN",
    "gn:dem":2111,
    "gn:feature_class":"P",
    "gn:feature_code":"PPL",
    "gn:name":"Tigupu",
    "gn:population":0,
    "gn:timezone":"Asia/Shanghai",
    "iso:country":"CN",
    "name:zho_x_preferred":[
        "\u63d0\u53e4\u94fa"
    ],
    "wof:name":"Tigupu",
    "wof:placetype":"locality"
},
  "geometry": {"coordinates":[102.84699999999999,24.7428],"type":"Point"}
}