{
  "type": "Feature",
  "properties": {
    "gn:admin1_code":"30",
    "gn:asciiname":"Pushaohe",
    "gn:country_code":"CN",
    "gn:dem":403,
    "gn:feature_class":"P",
    "gn:feature_code":"PPL",
    "gn:name":"Pushaohe",
    "gn:population":0,
    "gn:timezone":"Asia/Shanghai",
    "iso:country":"CN",
    "name:zho_x_preferred":[
        "\u8461\u6753\u67ef"
    ],
    "wof:name":"Pushaohe",
    "wof:placetype":"locality"
},
  "geometry": {"coordinates":[116.03216999999999,23.67119],"type":"Point"}
}