{
  "type": "Feature",
  "properties": {
    "gn:admin1_code":"01",
    "gn:asciiname":"Shushan",
    "gn:cc2":"CN",
    "gn:country_code":"CN",
    "gn:dem":10,
    "gn:feature_class":"P",
    "gn:feature_code":"PPL",
    "gn:name":"Shushan",
    "gn:population":0,
    "gn:timezone":"Asia/Shanghai",
    "iso:country":"CN",
    "name:und_x_variant":[
        "Shu-shan-chen",
        "Shushan"
    ],
    "wof:name":"Shushan",
    "wof:placetype":"locality"
},
  "geometry": {"coordinates":[117.61667,31.18333],"type":"Point"}
}