{
  "type": "Feature",
  "properties": {
    "gn:admin1_code":"16.0",
    "gn:asciiname":"Senchong",
    "gn:country_code":"CN",
    "gn:dem":85,
    "gn:feature_class":"P",
    "gn:feature_code":"PPL",
    "gn:name":"Senchong",
    "gn:population":0,
    "gn:timezone":"Asia/Shanghai",
    "iso:country":"CN",
    "name:zho_x_preferred":[
        "\u68ee\u51b2"
    ],
    "wof:name":"Senchong",
    "wof:placetype":"locality"
},
  "geometry": {"coordinates":[110.946,24.2382],"type":"Point"}
}