{
  "type": "Feature",
  "properties": {
    "gn:admin1_code":"9.0",
    "gn:asciiname":"Xiabaobao",
    "gn:country_code":"CN",
    "gn:dem":104,
    "gn:feature_class":"P",
    "gn:feature_code":"PPL",
    "gn:name":"Xiabaobao",
    "gn:population":0,
    "gn:timezone":"Asia/Shanghai",
    "iso:country":"CN",
    "name:und_x_variant":[
        "\u4e0b\u66b4\u9c8d"
    ],
    "name:zho_x_preferred":[
        "\u4e0b\u66b4\u9c8d"
    ],
    "wof:name":"Xiabaobao",
    "wof:placetype":"locality"
},
  "geometry": {"coordinates":[113.75830999999999,33.15263],"type":"Point"}
}