{
  "type": "Feature",
  "properties": {
    "gn:admin1_code":"2.0",
    "gn:asciiname":"Xiangzhou",
    "gn:country_code":"CN",
    "gn:dem":99,
    "gn:feature_class":"P",
    "gn:feature_code":"PPL",
    "gn:name":"Xiangzhou",
    "gn:population":0,
    "gn:timezone":"Asia/Shanghai",
    "iso:country":"CN",
    "name:ceb_x_preferred":[
        "Xiangzhou"
    ],
    "name:deu_x_preferred":[
        "Xiangzhou"
    ],
    "name:fra_x_preferred":[
        "Xiangzhou"
    ],
    "name:kor_x_preferred":[
        "\uc0f9\uc800\uc6b0"
    ],
    "name:nor_x_preferred":[
        "Xiangzhou"
    ],
    "name:swe_x_preferred":[
        "Xiangzhou"
    ],
    "name:zho_x_preferred":[
        "\u8c61\u5468"
    ],
    "wof:name":"Xiangzhou",
    "wof:placetype":"locality"
},
  "geometry": {"coordinates":[121.12286,28.47311],"type":"Point"}
}