{
  "type": "Feature",
  "properties": {
    "gn:admin1_code":"26.0",
    "gn:asciiname":"Chengjiazhuang",
    "gn:country_code":"CN",
    "gn:dem":831,
    "gn:feature_class":"P",
    "gn:feature_code":"PPL",
    "gn:name":"Chengjiazhuang",
    "gn:population":0,
    "gn:timezone":"Asia/Shanghai",
    "iso:country":"CN",
    "name:zho_x_preferred":[
        "\u6210\u5bb6\u5e84"
    ],
    "wof:name":"Chengjiazhuang",
    "wof:placetype":"locality"
},
  "geometry": {"coordinates":[109.79791000000002,35.3528],"type":"Point"}
}