{
  "type": "Feature",
  "properties": {
    "gn:admin1_code":"9",
    "gn:asciiname":"Xiajiaoyuan",
    "gn:country_code":"CN",
    "gn:dem":681,
    "gn:feature_class":"P",
    "gn:feature_code":"PPL",
    "gn:name":"Xiajiaoyuan",
    "gn:population":0,
    "gn:timezone":"Asia/Shanghai",
    "iso:country":"CN",
    "name:zho_x_preferred":[
        "\u4e0b\u7126\u56ed"
    ],
    "wof:name":"Xiajiaoyuan",
    "wof:placetype":"locality"
},
  "geometry": {"coordinates":[112.16356,33.66823],"type":"Point"}
}