{
  "type": "Feature",
  "properties": {
    "gn:admin1_code":"24.0",
    "gn:asciiname":"Yingxicun",
    "gn:country_code":"CN",
    "gn:dem":1067,
    "gn:feature_class":"P",
    "gn:feature_code":"PPL",
    "gn:name":"Yingxicun",
    "gn:population":0,
    "gn:timezone":"Asia/Shanghai",
    "iso:country":"CN",
    "name:zho_x_preferred":[
        "\u83b9\u897f\u6751"
    ],
    "wof:name":"Yingxicun",
    "wof:placetype":"locality"
},
  "geometry": {"coordinates":[110.93401,37.61836],"type":"Point"}
}