{
  "type": "Feature",
  "properties": {
    "gn:admin1_code":"20.0",
    "gn:asciiname":"Hechangwopeng",
    "gn:country_code":"CN",
    "gn:dem":492,
    "gn:feature_class":"P",
    "gn:feature_code":"PPL",
    "gn:name":"Hechangwopeng",
    "gn:population":0,
    "gn:timezone":"Asia/Shanghai",
    "iso:country":"CN",
    "name:zho_x_preferred":[
        "\u4f55\u5e38\u7a9d\u68da"
    ],
    "wof:name":"Hechangwopeng",
    "wof:placetype":"locality"
},
  "geometry": {"coordinates":[122.73899,48.44513],"type":"Point"}
}