{
  "type": "Feature",
  "properties": {
    "gn:admin1_code":"26.0",
    "gn:asciiname":"Yuanjia Wuchang",
    "gn:country_code":"CN",
    "gn:dem":873,
    "gn:feature_class":"P",
    "gn:feature_code":"PPL",
    "gn:name":"Yuanjia Wuchang",
    "gn:population":0,
    "gn:timezone":"Asia/Shanghai",
    "iso:country":"CN",
    "name:zho_x_preferred":[
        "\u8881\u5bb6\u5c4b\u573a"
    ],
    "wof:name":"Yuanjia Wuchang",
    "wof:placetype":"locality"
},
  "geometry": {"coordinates":[109.73678999999998,33.45568],"type":"Point"}
}