{
  "type": "Feature",
  "properties": {
    "gn:admin1_code":"11.0",
    "gn:asciiname":"Shitanping",
    "gn:country_code":"CN",
    "gn:dem":48,
    "gn:feature_class":"P",
    "gn:feature_code":"PPL",
    "gn:name":"Shitanping",
    "gn:population":0,
    "gn:timezone":"Asia/Shanghai",
    "iso:country":"CN",
    "name:zho_x_preferred":[
        "\u77f3\u6f6d\u576a"
    ],
    "wof:name":"Shitanping",
    "wof:placetype":"locality"
},
  "geometry": {"coordinates":[111.86042999999999,28.75962],"type":"Point"}
}