{
  "type": "Feature",
  "properties": {
    "gn:admin1_code":"25",
    "gn:asciiname":"Houchenlou",
    "gn:country_code":"CN",
    "gn:dem":46,
    "gn:feature_class":"P",
    "gn:feature_code":"PPL",
    "gn:name":"Houchenlou",
    "gn:population":0,
    "gn:timezone":"Asia/Shanghai",
    "iso:country":"CN",
    "name:zho_x_preferred":[
        "\u540e\u9648\u697c"
    ],
    "wof:name":"Houchenlou",
    "wof:placetype":"locality"
},
  "geometry": {"coordinates":[115.876,35.2052],"type":"Point"}
}