{
  "type": "Feature",
  "properties": {
    "gn:admin1_code":"1.0",
    "gn:asciiname":"Zhangwangcun",
    "gn:country_code":"CN",
    "gn:dem":26,
    "gn:feature_class":"P",
    "gn:feature_code":"PPL",
    "gn:name":"Zhangwangcun",
    "gn:population":0,
    "gn:timezone":"Asia/Shanghai",
    "iso:country":"CN",
    "name:zho_x_preferred":[
        "\u5f20\u738b\u6751"
    ],
    "wof:name":"Zhangwangcun",
    "wof:placetype":"locality"
},
  "geometry": {"coordinates":[116.72888,32.62048],"type":"Point"}
}