{
  "type": "Feature",
  "properties": {
    "gn:admin1_code":"12",
    "gn:asciiname":"Daqi",
    "gn:country_code":"CN",
    "gn:dem":96,
    "gn:feature_class":"P",
    "gn:feature_code":"PPLA4",
    "gn:name":"Daqi",
    "gn:population":0,
    "gn:timezone":"Asia/Shanghai",
    "iso:country":"CN",
    "name:und_x_variant":[
        "\u5927\u5d0e",
        "\u5927\u5d0e\u4e61",
        "Daqi Xiang"
    ],
    "wof:name":"Daqi",
    "wof:placetype":"locality"
},
  "geometry": {"coordinates":[115.19113,30.85325],"type":"Point"}
}