{
  "type": "Feature",
  "properties": {
    "gn:admin1_code":"19.0",
    "gn:asciiname":"Xiasujiagou",
    "gn:country_code":"CN",
    "gn:dem":120,
    "gn:feature_class":"P",
    "gn:feature_code":"PPL",
    "gn:name":"Xiasujiagou",
    "gn:population":0,
    "gn:timezone":"Asia/Shanghai",
    "iso:country":"CN",
    "name:zho_x_preferred":[
        "\u4e0b\u82cf\u5bb6\u6c9f"
    ],
    "wof:name":"Xiasujiagou",
    "wof:placetype":"locality"
},
  "geometry": {"coordinates":[121.02054,41.24833],"type":"Point"}
}