{
  "type": "Feature",
  "properties": {
    "gn:admin1_code":"04",
    "gn:asciiname":"Dongxiazhen",
    "gn:cc2":"CN",
    "gn:country_code":"CN",
    "gn:dem":0,
    "gn:feature_class":"P",
    "gn:feature_code":"PPL",
    "gn:name":"Dongxiazhen",
    "gn:population":0,
    "gn:timezone":"Asia/Shanghai",
    "iso:country":"CN",
    "name:und_x_variant":[
        "Kuan-chia-she",
        "Tung-hsia",
        "Tung-hsia-chen",
        "Tung-hsia-chuang",
        "Dongxiazhen"
    ],
    "wof:name":"Dongxiazhen",
    "wof:placetype":"locality"
},
  "geometry": {"coordinates":[119.78333000000001,33.38333],"type":"Point"}
}