{
  "type": "Feature",
  "properties": {
    "gn:admin1_code":"32.0",
    "gn:asciiname":"Jinchanggang",
    "gn:country_code":"CN",
    "gn:dem":1461,
    "gn:feature_class":"P",
    "gn:feature_code":"PPL",
    "gn:name":"Jinchanggang",
    "gn:population":0,
    "gn:timezone":"Asia/Shanghai",
    "iso:country":"CN",
    "name:zho_x_preferred":[
        "\u91d1\u957f\u5c97"
    ],
    "wof:name":"Jinchanggang",
    "wof:placetype":"locality"
},
  "geometry": {"coordinates":[102.01000000000001,27.5865],"type":"Point"}
}