{
  "type": "Feature",
  "properties": {
    "gn:admin1_code":"29.0",
    "gn:asciiname":"Yewugan",
    "gn:country_code":"CN",
    "gn:dem":2782,
    "gn:feature_class":"P",
    "gn:feature_code":"PPL",
    "gn:name":"Yewugan",
    "gn:population":0,
    "gn:timezone":"Asia/Shanghai",
    "iso:country":"CN",
    "name:zho_x_preferred":[
        "\u91ce\u7269\u5e72"
    ],
    "wof:name":"Yewugan",
    "wof:placetype":"locality"
},
  "geometry": {"coordinates":[100.77200000000001,26.8797],"type":"Point"}
}