{
  "type": "Feature",
  "properties": {
    "gn:admin1_code":"3",
    "gn:asciiname":"Jiecun",
    "gn:country_code":"CN",
    "gn:dem":190,
    "gn:feature_class":"P",
    "gn:feature_code":"PPLA4",
    "gn:name":"Jiecun",
    "gn:population":0,
    "gn:timezone":"Asia/Shanghai",
    "iso:country":"CN",
    "name:und_x_variant":[
        "Jiecunxu",
        "Jiecun",
        "\u6770\u6751",
        "Jiecun Xiang",
        "\u6770\u6751\u4e61"
    ],
    "wof:name":"Jiecun",
    "wof:placetype":"locality"
},
  "geometry": {"coordinates":[115.43639,26.21889],"type":"Point"}
}