{
  "type": "Feature",
  "properties": {
    "gn:admin1_code":"5.0",
    "gn:asciiname":"Xiaosanyitun",
    "gn:country_code":"CN",
    "gn:dem":160,
    "gn:feature_class":"P",
    "gn:feature_code":"PPL",
    "gn:name":"Xiaosanyitun",
    "gn:population":0,
    "gn:timezone":"Asia/Shanghai",
    "iso:country":"CN",
    "name:zho_x_preferred":[
        "\u5c0f\u4e09\u76ca\u5c6f"
    ],
    "wof:name":"Xiaosanyitun",
    "wof:placetype":"locality"
},
  "geometry": {"coordinates":[123.58423999999999,44.19231],"type":"Point"}
}