{
  "type": "Feature",
  "properties": {
    "gn:admin1_code":"8.0",
    "gn:asciiname":"Hongxing",
    "gn:country_code":"CN",
    "gn:dem":134,
    "gn:feature_class":"P",
    "gn:feature_code":"PPL",
    "gn:name":"Hongxing",
    "gn:population":0,
    "gn:timezone":"Asia/Shanghai",
    "iso:country":"CN",
    "name:ceb_x_preferred":[
        "Hongxing"
    ],
    "name:deu_x_preferred":[
        "Hongxing"
    ],
    "name:zho_x_preferred":[
        "\u7ea2\u661f"
    ],
    "wof:name":"Hongxing",
    "wof:placetype":"locality"
},
  "geometry": {"coordinates":[127.34611,46.09854],"type":"Point"}
}