{
  "type": "Feature",
  "properties": {
    "gn:admin1_code":"26.0",
    "gn:asciiname":"Qianrenjia Goucun",
    "gn:country_code":"CN",
    "gn:dem":884,
    "gn:feature_class":"P",
    "gn:feature_code":"PPL",
    "gn:name":"Qianrenjia Goucun",
    "gn:population":0,
    "gn:timezone":"Asia/Shanghai",
    "iso:country":"CN",
    "name:zho_x_preferred":[
        "\u524d\u4efb\u5bb6\u6c9f\u6751"
    ],
    "wof:name":"Qianrenjia Goucun",
    "wof:placetype":"locality"
},
  "geometry": {"coordinates":[110.44,37.3743],"type":"Point"}
}