{
  "type": "Feature",
  "properties": {
    "gn:admin1_code":"26.0",
    "gn:asciiname":"Machihecun",
    "gn:country_code":"CN",
    "gn:dem":1051,
    "gn:feature_class":"P",
    "gn:feature_code":"PPL",
    "gn:name":"Machihecun",
    "gn:population":0,
    "gn:timezone":"Asia/Shanghai",
    "iso:country":"CN",
    "name:zho_x_preferred":[
        "\u9ebb\u6c60\u6cb3\u6751"
    ],
    "wof:name":"Machihecun",
    "wof:placetype":"locality"
},
  "geometry": {"coordinates":[109.92843999999999,36.69025],"type":"Point"}
}