{
  "type": "Feature",
  "properties": {
    "gn:admin1_code":"4.0",
    "gn:asciiname":"Handongcun",
    "gn:country_code":"CN",
    "gn:dem":14,
    "gn:feature_class":"P",
    "gn:feature_code":"PPL",
    "gn:name":"Handongcun",
    "gn:population":0,
    "gn:timezone":"Asia/Shanghai",
    "iso:country":"CN",
    "name:zho_x_preferred":[
        "\u6db5\u6d1e\u6751"
    ],
    "wof:name":"Handongcun",
    "wof:placetype":"locality"
},
  "geometry": {"coordinates":[118.87347,33.88251],"type":"Point"}
}