{
  "type": "Feature",
  "properties": {
    "gn:admin1_code":"5.0",
    "gn:asciiname":"Zhamen",
    "gn:country_code":"CN",
    "gn:dem":181,
    "gn:feature_class":"P",
    "gn:feature_code":"PPL",
    "gn:name":"Zhamen",
    "gn:population":0,
    "gn:timezone":"Asia/Shanghai",
    "iso:country":"CN",
    "name:zho_x_preferred":[
        "\u95f8\u95e8"
    ],
    "wof:name":"Zhamen",
    "wof:placetype":"locality"
},
  "geometry": {"coordinates":[122.36888,45.62043],"type":"Point"}
}