{
  "type": "Feature",
  "properties": {
    "gn:admin1_code":"5.0",
    "gn:asciiname":"Xiguliu",
    "gn:country_code":"CN",
    "gn:dem":127,
    "gn:feature_class":"P",
    "gn:feature_code":"PPL",
    "gn:name":"Xiguliu",
    "gn:population":0,
    "gn:timezone":"Asia/Shanghai",
    "iso:country":"CN",
    "name:zho_x_preferred":[
        "\u897f\u80a1\u6d41"
    ],
    "wof:name":"Xiguliu",
    "wof:placetype":"locality"
},
  "geometry": {"coordinates":[124.35656000000002,45.46256],"type":"Point"}
}