{
  "type": "Feature",
  "properties": {
    "gn:admin1_code":"1.0",
    "gn:asciiname":"Chengshu'ancun",
    "gn:country_code":"CN",
    "gn:dem":68,
    "gn:feature_class":"P",
    "gn:feature_code":"PPL",
    "gn:name":"Chengshu\u2019ancun",
    "gn:population":0,
    "gn:timezone":"Asia/Shanghai",
    "iso:country":"CN",
    "name:und_x_variant":[
        "Chengshu\u2019ancun"
    ],
    "name:zho_x_preferred":[
        "\u67fd\u6811\u5eb5\u6751"
    ],
    "wof:name":"Chengshu'ancun",
    "wof:placetype":"locality"
},
  "geometry": {"coordinates":[116.53752,31.57848],"type":"Point"}
}