{
  "type": "Feature",
  "properties": {
    "gn:admin1_code":"29.0",
    "gn:asciiname":"Alu",
    "gn:country_code":"CN",
    "gn:dem":1517,
    "gn:feature_class":"P",
    "gn:feature_code":"PPL",
    "gn:name":"Alu",
    "gn:population":0,
    "gn:timezone":"Asia/Shanghai",
    "iso:country":"CN",
    "name:und_x_variant":[
        "\u554a\u565c"
    ],
    "wof:name":"Alu",
    "wof:placetype":"locality"
},
  "geometry": {"coordinates":[102.94096,27.10594],"type":"Point"}
}