{
  "type": "Feature",
  "properties": {
    "gn:admin1_code":"19.0",
    "gn:asciiname":"Xusihua Yingcun",
    "gn:country_code":"CN",
    "gn:dem":200,
    "gn:feature_class":"P",
    "gn:feature_code":"PPL",
    "gn:name":"Xusihua Yingcun",
    "gn:population":0,
    "gn:timezone":"Asia/Shanghai",
    "iso:country":"CN",
    "name:zho_x_preferred":[
        "\u5f90\u56db\u82b1\u8425\u6751"
    ],
    "wof:name":"Xusihua Yingcun",
    "wof:placetype":"locality"
},
  "geometry": {"coordinates":[120.697,41.5481],"type":"Point"}
}