{
  "type": "Feature",
  "properties": {
    "gn:admin1_code":"3.0",
    "gn:asciiname":"Huangtuling",
    "gn:country_code":"CN",
    "gn:dem":62,
    "gn:feature_class":"P",
    "gn:feature_code":"PPL",
    "gn:name":"Huangtuling",
    "gn:population":0,
    "gn:timezone":"Asia/Shanghai",
    "iso:country":"CN",
    "name:und_x_variant":[
        "\u9ec4\u571f\u5cad"
    ],
    "wof:name":"Huangtuling",
    "wof:placetype":"locality"
},
  "geometry": {"coordinates":[115.49172,27.74191],"type":"Point"}
}