{
  "type": "Feature",
  "properties": {
    "gn:admin1_code":"32.0",
    "gn:asciiname":"Xigansacun",
    "gn:country_code":"CN",
    "gn:dem":2524,
    "gn:feature_class":"P",
    "gn:feature_code":"PPL",
    "gn:name":"Xigansacun",
    "gn:population":0,
    "gn:timezone":"Asia/Shanghai",
    "iso:country":"CN",
    "name:zho_x_preferred":[
        "\u897f\u7518\u8428\u6751"
    ],
    "wof:name":"Xigansacun",
    "wof:placetype":"locality"
},
  "geometry": {"coordinates":[103.175,28.39072],"type":"Point"}
}