{
  "type": "Feature",
  "properties": {
    "gn:admin1_code":"1.0",
    "gn:asciiname":"Houxuecun",
    "gn:country_code":"CN",
    "gn:dem":23,
    "gn:feature_class":"P",
    "gn:feature_code":"PPL",
    "gn:name":"Houxuecun",
    "gn:population":0,
    "gn:timezone":"Asia/Shanghai",
    "iso:country":"CN",
    "name:zho_x_preferred":[
        "\u540e\u859b\u6751"
    ],
    "wof:name":"Houxuecun",
    "wof:placetype":"locality"
},
  "geometry": {"coordinates":[117.96979,32.72557],"type":"Point"}
}