{
  "type": "Feature",
  "properties": {
    "gn:admin1_code":"29.0",
    "gn:asciiname":"Nuojia",
    "gn:country_code":"CN",
    "gn:dem":1818,
    "gn:feature_class":"P",
    "gn:feature_code":"PPL",
    "gn:name":"Nuojia",
    "gn:population":0,
    "gn:timezone":"Asia/Shanghai",
    "iso:country":"CN",
    "name:zho_x_preferred":[
        "\u8bfa\u621b"
    ],
    "wof:name":"Nuojia",
    "wof:placetype":"locality"
},
  "geometry": {"coordinates":[104.57599999999999,26.5191],"type":"Point"}
}