{
  "type": "Feature",
  "properties": {
    "gn:admin1_code":"25.0",
    "gn:asciiname":"Wangezhuangcun",
    "gn:country_code":"CN",
    "gn:dem":64,
    "gn:feature_class":"P",
    "gn:feature_code":"PPL",
    "gn:name":"Wangezhuangcun",
    "gn:population":0,
    "gn:timezone":"Asia/Shanghai",
    "iso:country":"CN",
    "name:zho_x_preferred":[
        "\u4e07\u683c\u5e84\u6751"
    ],
    "wof:name":"Wangezhuangcun",
    "wof:placetype":"locality"
},
  "geometry": {"coordinates":[121.40219,37.08731],"type":"Point"}
}