{
  "type": "Feature",
  "properties": {
    "gn:admin1_code":"8.0",
    "gn:asciiname":"Yuanming Sandui",
    "gn:country_code":"CN",
    "gn:dem":228,
    "gn:feature_class":"P",
    "gn:feature_code":"PPLF",
    "gn:name":"Yuanming Sandui",
    "gn:population":0,
    "gn:timezone":"Asia/Shanghai",
    "iso:country":"CN",
    "name:zho_x_preferred":[
        "\u5143\u660e\u4e09\u961f"
    ],
    "wof:name":"Yuanming Sandui",
    "wof:placetype":"locality"
},
  "geometry": {"coordinates":[130.48626999999999,45.79755],"type":"Point"}
}