{
  "type": "Feature",
  "properties": {
    "gn:admin1_code":"4.0",
    "gn:asciiname":"Tongnancun",
    "gn:country_code":"CN",
    "gn:dem":11,
    "gn:feature_class":"P",
    "gn:feature_code":"PPL",
    "gn:name":"Tongnancun",
    "gn:population":0,
    "gn:timezone":"Asia/Shanghai",
    "iso:country":"CN",
    "name:zho_x_preferred":[
        "\u6f7c\u5357\u6751"
    ],
    "wof:name":"Tongnancun",
    "wof:placetype":"locality"
},
  "geometry": {"coordinates":[118.60089000000001,34.24609],"type":"Point"}
}