{
  "type": "Feature",
  "properties": {
    "gn:admin1_code":"11.0",
    "gn:asciiname":"Liuheba",
    "gn:country_code":"CN",
    "gn:dem":75,
    "gn:feature_class":"P",
    "gn:feature_code":"PPL",
    "gn:name":"Liuheba",
    "gn:population":0,
    "gn:timezone":"Asia/Shanghai",
    "iso:country":"CN",
    "name:zho_x_preferred":[
        "\u6d41\u6cb3\u575d"
    ],
    "wof:name":"Liuheba",
    "wof:placetype":"locality"
},
  "geometry": {"coordinates":[112.46681,27.77934],"type":"Point"}
}