{
  "type": "Feature",
  "properties": {
    "gn:admin1_code":"26.0",
    "gn:asciiname":"Yanghezhuang",
    "gn:country_code":"CN",
    "gn:dem":1323,
    "gn:feature_class":"P",
    "gn:feature_code":"PPL",
    "gn:name":"Yanghezhuang",
    "gn:population":0,
    "gn:timezone":"Asia/Shanghai",
    "iso:country":"CN",
    "name:und_x_variant":[
        "\u6768\u6cb3\u5e84"
    ],
    "wof:name":"Yanghezhuang",
    "wof:placetype":"locality"
},
  "geometry": {"coordinates":[107.02507,34.01564],"type":"Point"}
}