{
  "type": "Feature",
  "properties": {
    "gn:admin1_code":"10.0",
    "gn:asciiname":"Shangnanzhuang",
    "gn:country_code":"CN",
    "gn:dem":234,
    "gn:feature_class":"P",
    "gn:feature_code":"PPL",
    "gn:name":"Shangnanzhuang",
    "gn:population":0,
    "gn:timezone":"Asia/Shanghai",
    "iso:country":"CN",
    "name:und_x_variant":[
        "\u4e0a\u5357\u5e84"
    ],
    "wof:name":"Shangnanzhuang",
    "wof:placetype":"locality"
},
  "geometry": {"coordinates":[114.28872,38.61831],"type":"Point"}
}