{
  "type": "Feature",
  "properties": {
    "gn:admin1_code":"1.0",
    "gn:asciiname":"Ruanchengcun",
    "gn:country_code":"CN",
    "gn:dem":35,
    "gn:feature_class":"P",
    "gn:feature_code":"PPL",
    "gn:name":"Ruanchengcun",
    "gn:population":0,
    "gn:timezone":"Asia/Shanghai",
    "iso:country":"CN",
    "name:zho_x_preferred":[
        "\u962e\u57ce\u6751"
    ],
    "wof:name":"Ruanchengcun",
    "wof:placetype":"locality"
},
  "geometry": {"coordinates":[115.53476999999999,32.59507],"type":"Point"}
}