{
  "type": "Feature",
  "properties": {
    "gn:admin1_code":"10",
    "gn:asciiname":"Huaizhen",
    "gn:cc2":"CN",
    "gn:country_code":"CN",
    "gn:dem":12,
    "gn:feature_class":"P",
    "gn:feature_code":"PPL",
    "gn:name":"Huaizhen",
    "gn:population":0,
    "gn:timezone":"Asia/Shanghai",
    "iso:country":"CN",
    "name:und_x_variant":[
        "Khuaychzhen\u2019",
        "Huai-chen",
        "Huaizhen"
    ],
    "wof:name":"Huaizhen",
    "wof:placetype":"locality"
},
  "geometry": {"coordinates":[116.36667,38.21667],"type":"Point"}
}