{
  "type": "Feature",
  "properties": {
    "gn:admin1_code":"18",
    "gn:asciiname":"Liji",
    "gn:country_code":"CN",
    "gn:dem":578,
    "gn:feature_class":"P",
    "gn:feature_code":"PPL",
    "gn:name":"Liji",
    "gn:population":0,
    "gn:timezone":"Asia/Shanghai",
    "iso:country":"CN",
    "name:zho_x_preferred":[
        "\u91cc\u51e0"
    ],
    "wof:name":"Liji",
    "wof:placetype":"locality"
},
  "geometry": {"coordinates":[105.864,25.3047],"type":"Point"}
}