{
  "type": "Feature",
  "properties": {
    "gn:admin1_code":"1.0",
    "gn:asciiname":"Huaifengcun",
    "gn:country_code":"CN",
    "gn:dem":23,
    "gn:feature_class":"P",
    "gn:feature_code":"PPL",
    "gn:name":"Huaifengcun",
    "gn:population":0,
    "gn:timezone":"Asia/Shanghai",
    "iso:country":"CN",
    "name:zho_x_preferred":[
        "\u6dee\u4e30\u6751"
    ],
    "wof:name":"Huaifengcun",
    "wof:placetype":"locality"
},
  "geometry": {"coordinates":[117.26352,32.96364000000001],"type":"Point"}
}