{
  "type": "Feature",
  "properties": {
    "gn:admin1_code":"24.0",
    "gn:asciiname":"Nanhuzhuang",
    "gn:country_code":"CN",
    "gn:dem":1291,
    "gn:feature_class":"P",
    "gn:feature_code":"PPL",
    "gn:name":"Nanhuzhuang",
    "gn:population":0,
    "gn:timezone":"Asia/Shanghai",
    "iso:country":"CN",
    "name:zho_x_preferred":[
        "\u5357\u6e56\u5e84"
    ],
    "wof:name":"Nanhuzhuang",
    "wof:placetype":"locality"
},
  "geometry": {"coordinates":[111.8999,38.41375],"type":"Point"}
}