{
  "type": "Feature",
  "properties": {
    "gn:admin1_code":"26.0",
    "gn:asciiname":"Liangshuijing",
    "gn:country_code":"CN",
    "gn:dem":1305,
    "gn:feature_class":"P",
    "gn:feature_code":"PPL",
    "gn:name":"Liangshuijing",
    "gn:population":0,
    "gn:timezone":"Asia/Shanghai",
    "iso:country":"CN",
    "name:und_x_variant":[
        "\u51c9\u6c34\u4e95"
    ],
    "wof:name":"Liangshuijing",
    "wof:placetype":"locality"
},
  "geometry": {"coordinates":[106.65179999999999,32.91254],"type":"Point"}
}