{
  "type": "Feature",
  "properties": {
    "gn:admin1_code":"19.0",
    "gn:asciiname":"Qingshazicun",
    "gn:country_code":"CN",
    "gn:dem":306,
    "gn:feature_class":"P",
    "gn:feature_code":"PPL",
    "gn:name":"Qingshazicun",
    "gn:population":0,
    "gn:timezone":"Asia/Shanghai",
    "iso:country":"CN",
    "name:zho_x_preferred":[
        "\u9752\u6c99\u5b50\u6751"
    ],
    "wof:name":"Qingshazicun",
    "wof:placetype":"locality"
},
  "geometry": {"coordinates":[119.8854,41.14643],"type":"Point"}
}