{
  "type": "Feature",
  "properties": {
    "gn:admin1_code":"32.0",
    "gn:asciiname":"Duoluogou",
    "gn:country_code":"CN",
    "gn:dem":3243,
    "gn:feature_class":"P",
    "gn:feature_code":"PPL",
    "gn:name":"Duoluogou",
    "gn:population":0,
    "gn:timezone":"Asia/Shanghai",
    "iso:country":"CN",
    "name:zho_x_preferred":[
        "\u591a\u6d1b\u6c9f"
    ],
    "wof:name":"Duoluogou",
    "wof:placetype":"locality"
},
  "geometry": {"coordinates":[102.148,31.0857],"type":"Point"}
}