{
  "type": "Feature",
  "properties": {
    "gn:admin1_code":"25",
    "gn:asciiname":"Qiancaozhuang",
    "gn:country_code":"CN",
    "gn:dem":54,
    "gn:feature_class":"P",
    "gn:feature_code":"PPL",
    "gn:name":"Qiancaozhuang",
    "gn:population":0,
    "gn:timezone":"Asia/Shanghai",
    "iso:country":"CN",
    "name:zho_x_preferred":[
        "\u524d\u66f9\u5e84"
    ],
    "wof:name":"Qiancaozhuang",
    "wof:placetype":"locality"
},
  "geometry": {"coordinates":[115.56082000000001,35.5265],"type":"Point"}
}