{
  "type": "Feature",
  "properties": {
    "gn:admin1_code":"26.0",
    "gn:asciiname":"Haogedacun",
    "gn:country_code":"CN",
    "gn:dem":1262,
    "gn:feature_class":"P",
    "gn:feature_code":"PPL",
    "gn:name":"Haogedacun",
    "gn:population":0,
    "gn:timezone":"Asia/Shanghai",
    "iso:country":"CN",
    "name:zho_x_preferred":[
        "\u90dd\u572a\u57af\u6751"
    ],
    "wof:name":"Haogedacun",
    "wof:placetype":"locality"
},
  "geometry": {"coordinates":[109.98043,38.13508],"type":"Point"}
}