{
  "type": "Feature",
  "properties": {
    "gn:admin1_code":"11.0",
    "gn:asciiname":"Bawanli",
    "gn:country_code":"CN",
    "gn:dem":162,
    "gn:feature_class":"P",
    "gn:feature_code":"PPL",
    "gn:name":"Bawanli",
    "gn:population":0,
    "gn:timezone":"Asia/Shanghai",
    "iso:country":"CN",
    "name:zho_x_preferred":[
        "\u575d\u6e7e\u91cc"
    ],
    "wof:name":"Bawanli",
    "wof:placetype":"locality"
},
  "geometry": {"coordinates":[112.24527999999999,28.17434],"type":"Point"}
}