{
  "type": "Feature",
  "properties": {
    "gn:admin1_code":"18",
    "gn:asciiname":"Dayutang",
    "gn:country_code":"CN",
    "gn:dem":1834,
    "gn:feature_class":"P",
    "gn:feature_code":"PPL",
    "gn:name":"Dayutang",
    "gn:population":0,
    "gn:timezone":"Asia/Shanghai",
    "iso:country":"CN",
    "name:zho_x_preferred":[
        "\u5927\u9c7c\u5858"
    ],
    "wof:name":"Dayutang",
    "wof:placetype":"locality"
},
  "geometry": {"coordinates":[105.502,26.4345],"type":"Point"}
}