{
  "type": "Feature",
  "properties": {
    "gn:admin1_code":"26.0",
    "gn:asciiname":"Gaoyingcun",
    "gn:country_code":"CN",
    "gn:dem":512,
    "gn:feature_class":"P",
    "gn:feature_code":"PPL",
    "gn:name":"Gaoyingcun",
    "gn:population":0,
    "gn:timezone":"Asia/Shanghai",
    "iso:country":"CN",
    "name:und_x_variant":[
        "\u9ad8\u8425\u6751"
    ],
    "wof:name":"Gaoyingcun",
    "wof:placetype":"locality"
},
  "geometry": {"coordinates":[106.98184999999999,33.04453],"type":"Point"}
}