{
  "type": "Feature",
  "properties": {
    "gn:admin1_code":"25",
    "gn:asciiname":"Chaocheng",
    "gn:cc2":"CN",
    "gn:country_code":"CN",
    "gn:dem":43,
    "gn:feature_class":"P",
    "gn:feature_code":"PPL",
    "gn:name":"Chaocheng",
    "gn:population":0,
    "gn:timezone":"Asia/Shanghai",
    "iso:country":"CN",
    "name:und_x_variant":[
        "Kuan-chao",
        "Chaochenghsien",
        "Kuan-chao-hsien",
        "Chaochen",
        "Chaocheng"
    ],
    "name:zho_x_preferred":[
        "\u671d\u57ce\u9547"
    ],
    "wof:name":"Chaocheng",
    "wof:placetype":"locality"
},
  "geometry": {"coordinates":[115.58194,36.05361],"type":"Point"}
}