{
  "type": "Feature",
  "properties": {
    "gn:admin1_code":"29.0",
    "gn:asciiname":"Xunjiawan",
    "gn:country_code":"CN",
    "gn:dem":1742,
    "gn:feature_class":"P",
    "gn:feature_code":"PPL",
    "gn:name":"Xunjiawan",
    "gn:population":0,
    "gn:timezone":"Asia/Shanghai",
    "iso:country":"CN",
    "name:zho_x_preferred":[
        "\u8340\u5bb6\u5f2f"
    ],
    "wof:name":"Xunjiawan",
    "wof:placetype":"locality"
},
  "geometry": {"coordinates":[103.536,26.8416],"type":"Point"}
}