{
  "type": "Feature",
  "properties": {
    "gn:admin1_code":"26.0",
    "gn:asciiname":"Dengtaisi",
    "gn:country_code":"CN",
    "gn:dem":1447,
    "gn:feature_class":"P",
    "gn:feature_code":"PPL",
    "gn:name":"Dengtaisi",
    "gn:population":0,
    "gn:timezone":"Asia/Shanghai",
    "iso:country":"CN",
    "name:und_x_variant":[
        "\u706f\u53f0\u5bfa"
    ],
    "wof:name":"Dengtaisi",
    "wof:placetype":"locality"
},
  "geometry": {"coordinates":[107.94110000000001,33.89216],"type":"Point"}
}