{
  "type": "Feature",
  "properties": {
    "gn:admin1_code":"11",
    "gn:asciiname":"Linmutang",
    "gn:country_code":"CN",
    "gn:dem":560,
    "gn:feature_class":"P",
    "gn:feature_code":"PPL",
    "gn:name":"Linmutang",
    "gn:population":0,
    "gn:timezone":"Asia/Shanghai",
    "iso:country":"CN",
    "name:zho_x_preferred":[
        "\u6797\u6728\u5858"
    ],
    "wof:name":"Linmutang",
    "wof:placetype":"locality"
},
  "geometry": {"coordinates":[111.75799000000001,25.25757],"type":"Point"}
}