{
  "type": "Feature",
  "properties": {
    "gn:admin1_code":"21.0",
    "gn:asciiname":"Zhoushatang",
    "gn:country_code":"CN",
    "gn:dem":1189,
    "gn:feature_class":"P",
    "gn:feature_code":"PPL",
    "gn:name":"Zhoushatang",
    "gn:population":0,
    "gn:timezone":"Asia/Shanghai",
    "iso:country":"CN",
    "name:zho_x_preferred":[
        "\u5468\u6c99\u5858"
    ],
    "wof:name":"Zhoushatang",
    "wof:placetype":"locality"
},
  "geometry": {"coordinates":[105.83799999999999,37.5165],"type":"Point"}
}