{
  "type": "Feature",
  "properties": {
    "gn:admin1_code":"11.0",
    "gn:asciiname":"Raorenping",
    "gn:country_code":"CN",
    "gn:dem":743,
    "gn:feature_class":"P",
    "gn:feature_code":"PPL",
    "gn:name":"Raorenping",
    "gn:population":0,
    "gn:timezone":"Asia/Shanghai",
    "iso:country":"CN",
    "name:zho_x_preferred":[
        "\u9976\u4eba\u576a"
    ],
    "wof:name":"Raorenping",
    "wof:placetype":"locality"
},
  "geometry": {"coordinates":[110.25863,26.42406],"type":"Point"}
}