{
  "type": "Feature",
  "properties": {
    "gn:admin1_code":"3.0",
    "gn:asciiname":"Fenjia",
    "gn:country_code":"CN",
    "gn:dem":86,
    "gn:feature_class":"P",
    "gn:feature_code":"PPL",
    "gn:name":"Fenjia",
    "gn:population":0,
    "gn:timezone":"Asia/Shanghai",
    "iso:country":"CN",
    "name:zho_x_preferred":[
        "\u82ac\u5bb6"
    ],
    "wof:name":"Fenjia",
    "wof:placetype":"locality"
},
  "geometry": {"coordinates":[117.52504999999999,28.68464],"type":"Point"}
}