{
  "type": "Feature",
  "properties": {
    "gn:admin1_code":"8.0",
    "gn:asciiname":"Huanggangtun",
    "gn:country_code":"CN",
    "gn:dem":151,
    "gn:feature_class":"P",
    "gn:feature_code":"PPL",
    "gn:name":"Huanggangtun",
    "gn:population":0,
    "gn:timezone":"Asia/Shanghai",
    "iso:country":"CN",
    "name:zho_x_preferred":[
        "\u9ec4\u5c97\u5c6f"
    ],
    "wof:name":"Huanggangtun",
    "wof:placetype":"locality"
},
  "geometry": {"coordinates":[126.95057,45.58466],"type":"Point"}
}