{
  "type": "Feature",
  "properties": {
    "gn:admin1_code":"11.0",
    "gn:asciiname":"Chuangjian",
    "gn:country_code":"CN",
    "gn:dem":32,
    "gn:feature_class":"P",
    "gn:feature_code":"PPL",
    "gn:name":"Chuangjian",
    "gn:population":0,
    "gn:timezone":"Asia/Shanghai",
    "iso:country":"CN",
    "name:zho_x_preferred":[
        "\u521b\u5efa"
    ],
    "wof:name":"Chuangjian",
    "wof:placetype":"locality"
},
  "geometry": {"coordinates":[112.2672,29.0107],"type":"Point"}
}