{
  "type": "Feature",
  "properties": {
    "gn:admin1_code":"9.0",
    "gn:asciiname":"Huashengzhuang",
    "gn:country_code":"CN",
    "gn:dem":79,
    "gn:feature_class":"P",
    "gn:feature_code":"PPL",
    "gn:name":"Huashengzhuang",
    "gn:population":0,
    "gn:timezone":"Asia/Shanghai",
    "iso:country":"CN",
    "name:zho_x_preferred":[
        "\u82b1\u751f\u5e84"
    ],
    "wof:name":"Huashengzhuang",
    "wof:placetype":"locality"
},
  "geometry": {"coordinates":[114.27929,34.85073],"type":"Point"}
}