{
  "type": "Feature",
  "properties": {
    "gn:admin1_code":"26.0",
    "gn:asciiname":"Xiangumiao",
    "gn:country_code":"CN",
    "gn:dem":904,
    "gn:feature_class":"P",
    "gn:feature_code":"PPL",
    "gn:name":"Xiangumiao",
    "gn:population":0,
    "gn:timezone":"Asia/Shanghai",
    "iso:country":"CN",
    "name:zho_x_preferred":[
        "\u4ed9\u59d1\u5e99"
    ],
    "wof:name":"Xiangumiao",
    "wof:placetype":"locality"
},
  "geometry": {"coordinates":[109.20304,32.60344],"type":"Point"}
}