{
  "type": "Feature",
  "properties": {
    "gn:admin1_code":"24.0",
    "gn:asciiname":"Taohuajie",
    "gn:country_code":"CN",
    "gn:dem":1483,
    "gn:feature_class":"P",
    "gn:feature_code":"PPL",
    "gn:name":"Taohuajie",
    "gn:population":0,
    "gn:timezone":"Asia/Shanghai",
    "iso:country":"CN",
    "name:zho_x_preferred":[
        "\u6843\u82b1\u754c"
    ],
    "wof:name":"Taohuajie",
    "wof:placetype":"locality"
},
  "geometry": {"coordinates":[113.7484,38.72197],"type":"Point"}
}