{
  "type": "Feature",
  "properties": {
    "gn:admin1_code":"09",
    "gn:asciiname":"Chezhan",
    "gn:cc2":"CN",
    "gn:country_code":"CN",
    "gn:dem":47,
    "gn:feature_class":"P",
    "gn:feature_code":"PPL",
    "gn:name":"Chezhan",
    "gn:population":0,
    "gn:timezone":"Asia/Shanghai",
    "iso:country":"CN",
    "name:und_x_variant":[
        "Liudiquan",
        "Chezhan"
    ],
    "wof:name":"Chezhan",
    "wof:placetype":"locality"
},
  "geometry": {"coordinates":[116.02333,34.40944],"type":"Point"}
}