{
  "type": "Feature",
  "properties": {
    "gn:admin1_code":"9.0",
    "gn:asciiname":"Dajingyang",
    "gn:country_code":"CN",
    "gn:dem":98,
    "gn:feature_class":"P",
    "gn:feature_code":"PPL",
    "gn:name":"Dajingyang",
    "gn:population":0,
    "gn:timezone":"Asia/Shanghai",
    "iso:country":"CN",
    "name:zho_x_preferred":[
        "\u5927\u4e95\u6768"
    ],
    "wof:name":"Dajingyang",
    "wof:placetype":"locality"
},
  "geometry": {"coordinates":[112.61709999999999,32.43898],"type":"Point"}
}