{
  "type": "Feature",
  "properties": {
    "gn:admin1_code":"30.0",
    "gn:asciiname":"Zhuzailiao Shangcun",
    "gn:country_code":"CN",
    "gn:dem":116,
    "gn:feature_class":"P",
    "gn:feature_code":"PPL",
    "gn:name":"Zhuzailiao Shangcun",
    "gn:population":0,
    "gn:timezone":"Asia/Urumqi",
    "iso:country":"CN",
    "name:zho_x_preferred":[
        "\u795d\u4ed4\u5bee\u4e0a\u6751"
    ],
    "wof:name":"Zhuzailiao Shangcun",
    "wof:placetype":"locality"
},
  "geometry": {"coordinates":[110.12338,20.34972],"type":"Point"}
}