{
  "type": "Feature",
  "properties": {
    "gn:admin1_code":"15.0",
    "gn:asciiname":"Jiehe",
    "gn:country_code":"CN",
    "gn:dem":1490,
    "gn:feature_class":"P",
    "gn:feature_code":"PPL",
    "gn:name":"Jiehe",
    "gn:population":0,
    "gn:timezone":"Asia/Shanghai",
    "iso:country":"CN",
    "name:zho_x_preferred":[
        "\u9889\u6cb3"
    ],
    "wof:name":"Jiehe",
    "wof:placetype":"locality"
},
  "geometry": {"coordinates":[106.566,35.6151],"type":"Point"}
}