{
  "type": "Feature",
  "properties": {
    "gn:admin1_code":"8.0",
    "gn:asciiname":"Lianhecun",
    "gn:country_code":"CN",
    "gn:dem":247,
    "gn:feature_class":"P",
    "gn:feature_code":"PPL",
    "gn:name":"Lianhecun",
    "gn:population":0,
    "gn:timezone":"Asia/Shanghai",
    "iso:country":"CN",
    "name:zho_x_preferred":[
        "\u8fde\u6cb3\u6751"
    ],
    "wof:name":"Lianhecun",
    "wof:placetype":"locality"
},
  "geometry": {"coordinates":[130.57140999999999,45.04997],"type":"Point"}
}