{
  "type": "Feature",
  "properties": {
    "gn:admin1_code":"29.0",
    "gn:asciiname":"Mizhishan",
    "gn:country_code":"CN",
    "gn:dem":1868,
    "gn:feature_class":"P",
    "gn:feature_code":"PPL",
    "gn:name":"Mizhishan",
    "gn:population":0,
    "gn:timezone":"Asia/Shanghai",
    "iso:country":"CN",
    "name:zho_x_preferred":[
        "\u5bc6\u679d\u5c71"
    ],
    "wof:name":"Mizhishan",
    "wof:placetype":"locality"
},
  "geometry": {"coordinates":[103.14100000000001,25.08],"type":"Point"}
}