{
  "type": "Feature",
  "properties": {
    "gn:admin1_code":"6.0",
    "gn:asciiname":"Sizhongdui",
    "gn:country_code":"CN",
    "gn:dem":3245,
    "gn:feature_class":"P",
    "gn:feature_code":"PPLF",
    "gn:name":"Sizhongdui",
    "gn:population":0,
    "gn:timezone":"Asia/Shanghai",
    "iso:country":"CN",
    "name:und_x_variant":[
        "\u56db\u4e2d\u961f"
    ],
    "wof:name":"Sizhongdui",
    "wof:placetype":"locality"
},
  "geometry": {"coordinates":[99.41625999999999,36.63408],"type":"Point"}
}