{
  "type": "Feature",
  "properties": {
    "gn:admin1_code":"21.0",
    "gn:asciiname":"Shanggao Yaozi",
    "gn:country_code":"CN",
    "gn:dem":1735,
    "gn:feature_class":"P",
    "gn:feature_code":"PPL",
    "gn:name":"Shanggao Yaozi",
    "gn:population":0,
    "gn:timezone":"Asia/Shanghai",
    "iso:country":"CN",
    "name:zho_x_preferred":[
        "\u4e0a\u9ad8\u7a91\u5b50"
    ],
    "wof:name":"Shanggao Yaozi",
    "wof:placetype":"locality"
},
  "geometry": {"coordinates":[106.944,37.2176],"type":"Point"}
}