{
  "type": "Feature",
  "properties": {
    "gn:admin1_code":"11",
    "gn:asciiname":"Huangtingshi",
    "gn:cc2":"CN",
    "gn:country_code":"CN",
    "gn:dem":310,
    "gn:feature_class":"P",
    "gn:feature_code":"PPL",
    "gn:name":"Huangtingshi",
    "gn:population":0,
    "gn:timezone":"Asia/Shanghai",
    "iso:country":"CN",
    "name:und_x_variant":[
        "Huang-t\u2019ing-shih",
        "Huangtingshi"
    ],
    "wof:name":"Huangtingshi",
    "wof:placetype":"locality"
},
  "geometry": {"coordinates":[111.13556,26.9925],"type":"Point"}
}