{
  "type": "Feature",
  "properties": {
    "gn:admin1_code":"10",
    "gn:asciiname":"Xianaling",
    "gn:country_code":"CN",
    "gn:dem":1089,
    "gn:feature_class":"P",
    "gn:feature_code":"PPL",
    "gn:name":"Xianaling",
    "gn:population":0,
    "gn:timezone":"Asia/Shanghai",
    "iso:country":"CN",
    "name:zho_x_preferred":[
        "\u4e0b\u7eb3\u5cad"
    ],
    "wof:name":"Xianaling",
    "wof:placetype":"locality"
},
  "geometry": {"coordinates":[114.18212,40.89889],"type":"Point"}
}