{
  "type": "Feature",
  "properties": {
    "gn:admin1_code":"21.0",
    "gn:asciiname":"Niumao Yaoxian",
    "gn:country_code":"CN",
    "gn:dem":2223,
    "gn:feature_class":"P",
    "gn:feature_code":"PPL",
    "gn:name":"Niumao Yaoxian",
    "gn:population":0,
    "gn:timezone":"Asia/Shanghai",
    "iso:country":"CN",
    "name:zho_x_preferred":[
        "\u725b\u6bdb\u8170\u5c98"
    ],
    "wof:name":"Niumao Yaoxian",
    "wof:placetype":"locality"
},
  "geometry": {"coordinates":[105.755,36.2874],"type":"Point"}
}