{
  "type": "Feature",
  "properties": {
    "gn:admin1_code":"5.0",
    "gn:asciiname":"Shentuncun",
    "gn:country_code":"CN",
    "gn:dem":168,
    "gn:feature_class":"P",
    "gn:feature_code":"PPL",
    "gn:name":"Shentuncun",
    "gn:population":0,
    "gn:timezone":"Asia/Shanghai",
    "iso:country":"CN",
    "name:zho_x_preferred":[
        "\u7533\u5c6f\u6751"
    ],
    "wof:name":"Shentuncun",
    "wof:placetype":"locality"
},
  "geometry": {"coordinates":[126.48933,44.32628],"type":"Point"}
}