{
  "type": "Feature",
  "properties": {
    "gn:admin1_code":"16",
    "gn:asciiname":"Huangmao",
    "gn:cc2":"CN",
    "gn:country_code":"CN",
    "gn:dem":81,
    "gn:feature_class":"P",
    "gn:feature_code":"PPL",
    "gn:name":"Huangmao",
    "gn:population":0,
    "gn:timezone":"Asia/Shanghai",
    "iso:country":"CN",
    "name:und_x_variant":[
        "Huang-mao-hs\u00fc",
        "Huangmao"
    ],
    "wof:name":"Huangmao",
    "wof:placetype":"locality"
},
  "geometry": {"coordinates":[109.64556,23.75111],"type":"Point"}
}