{
  "type": "Feature",
  "properties": {
    "gn:admin1_code":"11",
    "gn:asciiname":"Zhangjialing",
    "gn:country_code":"CN",
    "gn:dem":724,
    "gn:feature_class":"P",
    "gn:feature_code":"PPL",
    "gn:name":"Zhangjialing",
    "gn:population":0,
    "gn:timezone":"Asia/Shanghai",
    "iso:country":"CN",
    "name:und_x_variant":[
        "\u5f20\u5bb6\u5cad",
        "Zhangjialing"
    ],
    "wof:name":"Zhangjialing",
    "wof:placetype":"locality"
},
  "geometry": {"coordinates":[111.76111000000002,25.91611],"type":"Point"}
}