{
  "type": "Feature",
  "properties": {
    "gn:admin1_code":"3.0",
    "gn:asciiname":"Fanshang Huangjia",
    "gn:country_code":"CN",
    "gn:dem":134,
    "gn:feature_class":"P",
    "gn:feature_code":"PPL",
    "gn:name":"Fanshang Huangjia",
    "gn:population":0,
    "gn:timezone":"Asia/Shanghai",
    "iso:country":"CN",
    "name:zho_x_preferred":[
        "\u7548\u4e0a\u9ec4\u5bb6"
    ],
    "wof:name":"Fanshang Huangjia",
    "wof:placetype":"locality"
},
  "geometry": {"coordinates":[117.35760000000001,28.03974],"type":"Point"}
}