{
  "type": "Feature",
  "properties": {
    "gn:admin1_code":"32.0",
    "gn:asciiname":"Ganqing",
    "gn:country_code":"CN",
    "gn:dem":1179,
    "gn:feature_class":"P",
    "gn:feature_code":"PPL",
    "gn:name":"Ganqing",
    "gn:population":0,
    "gn:timezone":"Asia/Shanghai",
    "iso:country":"CN",
    "name:zho_x_preferred":[
        "\u5e72\u7b90"
    ],
    "wof:name":"Ganqing",
    "wof:placetype":"locality"
},
  "geometry": {"coordinates":[101.47096999999999,26.51039],"type":"Point"}
}