{
  "type": "Feature",
  "properties": {
    "gn:admin1_code":"29.0",
    "gn:asciiname":"Gaojiapingzi",
    "gn:country_code":"CN",
    "gn:dem":1692,
    "gn:feature_class":"P",
    "gn:feature_code":"PPL",
    "gn:name":"Gaojiapingzi",
    "gn:population":0,
    "gn:timezone":"Asia/Shanghai",
    "iso:country":"CN",
    "name:zho_x_preferred":[
        "\u9ad8\u5bb6\u576a\u5b50"
    ],
    "wof:name":"Gaojiapingzi",
    "wof:placetype":"locality"
},
  "geometry": {"coordinates":[98.5741,24.6622],"type":"Point"}
}