{
  "type": "Feature",
  "properties": {
    "gn:admin1_code":"32.0",
    "gn:asciiname":"Wanguqiao",
    "gn:country_code":"CN",
    "gn:dem":276,
    "gn:feature_class":"P",
    "gn:feature_code":"PPL",
    "gn:name":"Wanguqiao",
    "gn:population":0,
    "gn:timezone":"Asia/Shanghai",
    "iso:country":"CN",
    "name:zho_x_preferred":[
        "\u4e07\u9f13\u6865"
    ],
    "wof:name":"Wanguqiao",
    "wof:placetype":"locality"
},
  "geometry": {"coordinates":[106.126,30.5505],"type":"Point"}
}