{
  "type": "Feature",
  "properties": {
    "gn:admin1_code":"02",
    "gn:asciiname":"Shifan",
    "gn:country_code":"CN",
    "gn:dem":7,
    "gn:feature_class":"P",
    "gn:feature_code":"PPLA4",
    "gn:name":"Shifan",
    "gn:population":0,
    "gn:timezone":"Asia/Shanghai",
    "iso:country":"CN",
    "name:und_x_variant":[
        "Hsi-p\u2019o-hu",
        "Xipohu",
        "Shifan",
        "Shifan Zhen",
        "Pohu"
    ],
    "name:zho_x_preferred":[
        "\u77f3\u5e06"
    ],
    "name:zho_x_variant":[
        "\u6734\u6e56",
        "\u77f3\u5e06\u9547"
    ],
    "wof:name":"Shifan",
    "wof:placetype":"locality"
},
  "geometry": {"coordinates":[121.02151000000001,28.19346],"type":"Point"}
}