{
  "type": "Feature",
  "properties": {
    "gn:admin1_code":"33.0",
    "gn:asciiname":"Jiaoxi",
    "gn:country_code":"CN",
    "gn:dem":609,
    "gn:feature_class":"P",
    "gn:feature_code":"PPL",
    "gn:name":"Jiaoxi",
    "gn:population":0,
    "gn:timezone":"Asia/Shanghai",
    "iso:country":"CN",
    "name:zho_x_preferred":[
        "\u4ea4\u6eaa"
    ],
    "wof:name":"Jiaoxi",
    "wof:placetype":"locality"
},
  "geometry": {"coordinates":[108.60612999999999,29.22115],"type":"Point"}
}