{
  "type": "Feature",
  "properties": {
    "gn:admin1_code":"11.0",
    "gn:asciiname":"Maxi",
    "gn:country_code":"CN",
    "gn:dem":298,
    "gn:feature_class":"P",
    "gn:feature_code":"PPL",
    "gn:name":"Maxi",
    "gn:population":0,
    "gn:timezone":"Asia/Shanghai",
    "iso:country":"CN",
    "name:zho_x_preferred":[
        "\u9ebb\u6eaa"
    ],
    "wof:name":"Maxi",
    "wof:placetype":"locality"
},
  "geometry": {"coordinates":[111.10559000000001,26.93499000000001],"type":"Point"}
}