{
  "type": "Feature",
  "properties": {
    "gn:admin1_code":"31",
    "gn:asciiname":"Lingmencun",
    "gn:country_code":"CN",
    "gn:dem":259,
    "gn:feature_class":"P",
    "gn:feature_code":"PPL",
    "gn:name":"Lingmencun",
    "gn:population":0,
    "gn:timezone":"Asia/Shanghai",
    "iso:country":"CN",
    "name:zho_x_preferred":[
        "\u5cad\u95e8\u6751"
    ],
    "wof:name":"Lingmencun",
    "wof:placetype":"locality"
},
  "geometry": {"coordinates":[109.96167,19.16028],"type":"Point"}
}