{
  "type": "Feature",
  "properties": {
    "gn:admin1_code":"8.0",
    "gn:asciiname":"Junchuan Ershiyidui",
    "gn:country_code":"CN",
    "gn:dem":65,
    "gn:feature_class":"P",
    "gn:feature_code":"PPLF",
    "gn:name":"Junchuan Ershiyidui",
    "gn:population":0,
    "gn:timezone":"Asia/Shanghai",
    "iso:country":"CN",
    "name:zho_x_preferred":[
        "\u519b\u5ddd\u4e8c\u5341\u4e00\u961f"
    ],
    "wof:name":"Junchuan Ershiyidui",
    "wof:placetype":"locality"
},
  "geometry": {"coordinates":[131.29033999999999,47.53592],"type":"Point"}
}