{
  "type": "Feature",
  "properties": {
    "gn:admin1_code":"5.0",
    "gn:asciiname":"Wangshantun",
    "gn:country_code":"CN",
    "gn:dem":205,
    "gn:feature_class":"P",
    "gn:feature_code":"PPL",
    "gn:name":"Wangshantun",
    "gn:population":0,
    "gn:timezone":"Asia/Shanghai",
    "iso:country":"CN",
    "name:zho_x_preferred":[
        "\u671b\u5c71\u5c6f"
    ],
    "wof:name":"Wangshantun",
    "wof:placetype":"locality"
},
  "geometry": {"coordinates":[126.83301000000002,44.76029000000001],"type":"Point"}
}