{
  "type": "Feature",
  "properties": {
    "gn:admin1_code":"18",
    "gn:asciiname":"Rongjiang",
    "gn:country_code":"CN",
    "gn:dem":930,
    "gn:feature_class":"P",
    "gn:feature_code":"PPL",
    "gn:name":"Rongjiang",
    "gn:population":0,
    "gn:timezone":"Asia/Shanghai",
    "iso:country":"CN",
    "name:zho_x_preferred":[
        "\u5197\u6c5f"
    ],
    "wof:name":"Rongjiang",
    "wof:placetype":"locality"
},
  "geometry": {"coordinates":[106.73699999999999,25.5288],"type":"Point"}
}