{
  "type": "Feature",
  "properties": {
    "gn:admin1_code":"29",
    "gn:asciiname":"Tunlan",
    "gn:country_code":"CN",
    "gn:dem":1024,
    "gn:feature_class":"P",
    "gn:feature_code":"PPL",
    "gn:name":"Tunlan",
    "gn:population":0,
    "gn:timezone":"Asia/Shanghai",
    "iso:country":"CN",
    "name:zho_x_preferred":[
        "\u541e\u5170"
    ],
    "wof:name":"Tunlan",
    "wof:placetype":"locality"
},
  "geometry": {"coordinates":[105.59699999999999,23.3238],"type":"Point"}
}