{
  "type": "Feature",
  "properties": {
    "gn:admin1_code":"33.0",
    "gn:asciiname":"Dazhulin",
    "gn:country_code":"CN",
    "gn:dem":261,
    "gn:feature_class":"P",
    "gn:feature_code":"PPL",
    "gn:name":"Dazhulin",
    "gn:population":0,
    "gn:timezone":"Asia/Shanghai",
    "iso:country":"CN",
    "name:zho_x_preferred":[
        "\u5927\u7af9\u6797"
    ],
    "wof:name":"Dazhulin",
    "wof:placetype":"locality"
},
  "geometry": {"coordinates":[106.81,29.4311],"type":"Point"}
}