{
  "type": "Feature",
  "properties": {
    "gn:admin1_code":"3",
    "gn:asciiname":"Jingzhou",
    "gn:country_code":"CN",
    "gn:dem":148,
    "gn:feature_class":"P",
    "gn:feature_code":"PPL",
    "gn:name":"Jingzhou",
    "gn:population":0,
    "gn:timezone":"Asia/Shanghai",
    "iso:country":"CN",
    "name:zho_x_preferred":[
        "\u4eac\u5dde"
    ],
    "wof:name":"Jingzhou",
    "wof:placetype":"locality"
},
  "geometry": {"coordinates":[114.596,25.5236],"type":"Point"}
}