{
  "type": "Feature",
  "properties": {
    "gn:admin1_code":"3",
    "gn:asciiname":"Jingzhou",
    "gn:country_code":"CN",
    "gn:dem":148,
    "gn:feature_class":"P",
    "gn:feature_code":"PPL",
    "gn:name":"Jingzhou",
    "gn:population":0,
    "gn:timezone":"Asia/Shanghai",
    "iso:country":"CN",
    "name:afr_x_preferred":[
        "Jingzhou"
    ],
    "name:ara_x_preferred":[
        "\u062c\u064a\u0646\u063a\u062a\u0634\u0648"
    ],
    "name:bul_x_preferred":[
        "\u0414\u0437\u0438\u043d\u0434\u0436\u043e\u0443"
    ],
    "name:cat_x_preferred":[
        "Jingzhou"
    ],
    "name:cdo_x_preferred":[
        "G\u012dng-ci\u016d"
    ],
    "name:ces_x_preferred":[
        "\u0164ing-\u010dou"
    ],
    "name:dan_x_preferred":[
        "Jingzhou"
    ],
    "name:deu_x_preferred":[
        "Jingzhou"
    ],
    "name:eus_x_preferred":[
        "Jingzhou"
    ],
    "name:fas_x_preferred":[
        "\u062c\u06cc\u0627\u0646\u06af\u0698\u0648"
    ],
    "name:fin_x_preferred":[
        "Jingzhou"
    ],
    "name:fra_x_preferred":[
        "Jingzhou"
    ],
    "name:heb_x_preferred":[
        "\u05d2'\u05d9\u05e0\u05d2\u05d6'\u05d5\u05d0\u05d5"
    ],
    "name:hrv_x_preferred":[
        "Jingzhou"
    ],
    "name:hun_x_preferred":[
        "Jingzhou"
    ],
    "name:ind_x_preferred":[
        "Jingzhou"
    ],
    "name:ita_x_preferred":[
        "Jingzhou"
    ],
    "name:jpn_x_preferred":[
        "\u834a\u5dde\u5e02"
    ],
    "name:kik_x_preferred":[
        "Jingzhou"
    ],
    "name:kor_x_preferred":[
        "\uc9d5\uc800\uc6b0\uc2dc"
    ],
    "name:mlg_x_preferred":[
        "Jingzhou"
    ],
    "name:nld_x_preferred":[
        "Jingzhou"
    ],
    "name:nno_x_preferred":[
        "Jingzhou"
    ],
    "name:nor_x_preferred":[
        "Jingzhou"
    ],
    "name:pam_x_preferred":[
        "Jingzhou"
    ],
    "name:pol_x_preferred":[
        "Jingzhou"
    ],
    "name:por_x_preferred":[
        "Jingzhou"
    ],
    "name:rus_x_preferred":[
        "\u0426\u0437\u0438\u043d\u0447\u0436\u043e\u0443"
    ],
    "name:spa_x_preferred":[
        "Jingzhou"
    ],
    "name:swe_x_preferred":[
        "Jingzhou"
    ],
    "name:tgl_x_preferred":[
        "Jingzhou"
    ],
    "name:tur_x_preferred":[
        "Jingzhou"
    ],
    "name:ukr_x_preferred":[
        "\u0426\u0437\u0456\u043d\u0447\u0436\u043e\u0443"
    ],
    "name:urd_x_preferred":[
        "\u062c\u0646\u06af\u0698\u0648\u0648"
    ],
    "name:vie_x_preferred":[
        "Kinh Ch\u00e2u"
    ],
    "name:war_x_preferred":[
        "Jingzhou"
    ],
    "name:wuu_x_preferred":[
        "\u8346\u5dde\u5e02"
    ],
    "name:zho_x_preferred":[
        "\u4eac\u5dde"
    ],
    "name:zho_x_variant":[
        "\u8346\u5dde\u5e02"
    ],
    "wof:name":"Jingzhou",
    "wof:placetype":"locality"
},
  "geometry": {"coordinates":[114.596,25.5236],"type":"Point"}
}