{
  "type": "Feature",
  "properties": {
    "gn:admin1_code":"7.0",
    "gn:asciiname":"Lianping",
    "gn:country_code":"CN",
    "gn:dem":774,
    "gn:feature_class":"P",
    "gn:feature_code":"PPL",
    "gn:name":"Lianping",
    "gn:population":0,
    "gn:timezone":"Asia/Shanghai",
    "iso:country":"CN",
    "name:zho_x_preferred":[
        "\u8054\u576a"
    ],
    "wof:name":"Lianping",
    "wof:placetype":"locality"
},
  "geometry": {"coordinates":[118.74357000000001,25.78897000000001],"type":"Point"}
}