{
  "type": "Feature",
  "properties": {
    "gn:admin1_code":"19.0",
    "gn:admin2_code":"2037885.0",
    "gn:asciiname":"Caomeigou",
    "gn:country_code":"CN",
    "gn:dem":95,
    "gn:feature_class":"P",
    "gn:feature_code":"PPL",
    "gn:name":"Caomeigou",
    "gn:population":0,
    "gn:timezone":"Asia/Shanghai",
    "iso:country":"CN",
    "name:zho_x_preferred":[
        "\u8349\u8393\u6c9f"
    ],
    "wof:name":"Caomeigou",
    "wof:placetype":"locality"
},
  "geometry": {"coordinates":[124.34699999999999,40.1424],"type":"Point"}
}