{
  "type": "Feature",
  "properties": {
    "gn:admin1_code":"11.0",
    "gn:asciiname":"Maoyugang",
    "gn:country_code":"CN",
    "gn:dem":129,
    "gn:feature_class":"P",
    "gn:feature_code":"PPL",
    "gn:name":"Maoyugang",
    "gn:population":0,
    "gn:timezone":"Asia/Shanghai",
    "iso:country":"CN",
    "name:zho_x_preferred":[
        "\u732b\u9c7c\u6e2f"
    ],
    "wof:name":"Maoyugang",
    "wof:placetype":"locality"
},
  "geometry": {"coordinates":[113.54773,26.66929],"type":"Point"}
}