{
  "type": "Feature",
  "properties": {
    "gn:admin1_code":"32.0",
    "gn:asciiname":"Fuhua",
    "gn:country_code":"CN",
    "gn:dem":767,
    "gn:feature_class":"P",
    "gn:feature_code":"PPL",
    "gn:name":"Fuhua",
    "gn:population":0,
    "gn:timezone":"Asia/Shanghai",
    "iso:country":"CN",
    "name:zho_x_preferred":[
        "\u5bcc\u534e"
    ],
    "wof:name":"Fuhua",
    "wof:placetype":"locality"
},
  "geometry": {"coordinates":[102.66500000000001,29.3122],"type":"Point"}
}