{
  "type": "Feature",
  "properties": {
    "gn:admin1_code":"19",
    "gn:asciiname":"Bianmen",
    "gn:cc2":"CN",
    "gn:country_code":"CN",
    "gn:dem":78,
    "gn:feature_class":"P",
    "gn:feature_code":"PPL",
    "gn:name":"Bianmen",
    "gn:population":0,
    "gn:timezone":"Asia/Shanghai",
    "iso:country":"CN",
    "name:und_x_variant":[
        "Kao-li-men",
        "Pien-men",
        "Kao-li",
        "Kao-li-men-ts\u2019un",
        "Bianmen"
    ],
    "wof:name":"Bianmen",
    "wof:placetype":"locality"
},
  "geometry": {"coordinates":[124.09889,40.35083],"type":"Point"}
}