{
  "type": "Feature",
  "properties": {
    "iso:country":"CN",
    "qs:name":"\u5b89\u6d77\u9547",
    "qs:name_adm0":"\u4e2d\u570b",
    "qs:name_adm1":"\u798f\u5efa\u7701",
    "qs:photos":42,
    "qs:photos_1k":9,
    "qs:photos_9k":1,
    "qs:photos_9r":2,
    "qs:photos_all":42,
    "qs:photos_sr":2,
    "qs:placetype":"Town",
    "qs:pop_sr":"0",
    "wof:name":"\u5b89\u6d77\u9547",
    "wof:placetype":"locality"
},
  "geometry": {"coordinates":[118.412003,24.702754],"type":"Point"}
}