{
  "type": "Feature",
  "properties": {
    "gn:admin1_code":"14",
    "gn:asciiname":"Duonai",
    "gn:country_code":"CN",
    "gn:dem":4857,
    "gn:feature_class":"P",
    "gn:feature_code":"PPL",
    "gn:name":"Duonai",
    "gn:population":0,
    "gn:timezone":"Asia/Urumqi",
    "iso:country":"CN",
    "name:zho_x_preferred":[
        "\u591a\u4e43"
    ],
    "wof:name":"Duonai",
    "wof:placetype":"locality"
},
  "geometry": {"coordinates":[87.91240000000001,30.9838],"type":"Point"}
}