{
  "type": "Feature",
  "properties": {
    "gn:admin1_code":"30.0",
    "gn:asciiname":"Wushan",
    "gn:country_code":"CN",
    "gn:dem":35,
    "gn:feature_class":"P",
    "gn:feature_code":"PPLA4",
    "gn:name":"Wushan",
    "gn:population":0,
    "gn:timezone":"Asia/Shanghai",
    "iso:country":"CN",
    "name:ceb_x_preferred":[
        "Wushan"
    ],
    "name:deu_x_preferred":[
        "Wushan"
    ],
    "name:fra_x_preferred":[
        "Wushan"
    ],
    "name:kor_x_preferred":[
        "\uc6b0\uc0b0\ud604"
    ],
    "name:nor_x_preferred":[
        "Wushan"
    ],
    "name:swe_x_preferred":[
        "Wushan"
    ],
    "name:und_x_variant":[
        "Wushan Jiedao"
    ],
    "name:zho_x_preferred":[
        "\u4e94\u5c71"
    ],
    "name:zho_x_variant":[
        "\u4e94\u5c71\u8857\u9053"
    ],
    "wof:name":"Wushan",
    "wof:placetype":"locality"
},
  "geometry": {"coordinates":[113.34684,23.15888],"type":"Point"}
}