{
  "type": "Feature",
  "properties": {
    "gn:admin1_code":"8.0",
    "gn:asciiname":"Longquanling",
    "gn:country_code":"CN",
    "gn:dem":391,
    "gn:feature_class":"P",
    "gn:feature_code":"PPL",
    "gn:name":"Longquanling",
    "gn:population":0,
    "gn:timezone":"Asia/Shanghai",
    "iso:country":"CN",
    "name:und_x_variant":[
        "\u9f99\u6cc9\u5cad"
    ],
    "wof:name":"Longquanling",
    "wof:placetype":"locality"
},
  "geometry": {"coordinates":[126.88597,50.73239],"type":"Point"}
}