{
  "type": "Feature",
  "properties": {
    "gn:admin1_code":"18",
    "gn:asciiname":"Puguitang",
    "gn:country_code":"CN",
    "gn:dem":507,
    "gn:feature_class":"P",
    "gn:feature_code":"PPL",
    "gn:name":"Puguitang",
    "gn:population":0,
    "gn:timezone":"Asia/Shanghai",
    "iso:country":"CN",
    "name:zho_x_preferred":[
        "\u6251\u9f9f\u5858"
    ],
    "wof:name":"Puguitang",
    "wof:placetype":"locality"
},
  "geometry": {"coordinates":[108.251,27.9906],"type":"Point"}
}