{
  "type": "Feature",
  "properties": {
    "gn:admin1_code":"10.0",
    "gn:asciiname":"Dacaizhuang",
    "gn:country_code":"CN",
    "gn:dem":970,
    "gn:feature_class":"P",
    "gn:feature_code":"PPL",
    "gn:name":"Dacaizhuang",
    "gn:population":0,
    "gn:timezone":"Asia/Shanghai",
    "iso:country":"CN",
    "name:zho_x_preferred":[
        "\u5927\u8521\u5e84"
    ],
    "wof:name":"Dacaizhuang",
    "wof:placetype":"locality"
},
  "geometry": {"coordinates":[114.84949,40.04987],"type":"Point"}
}