{
  "type": "Feature",
  "properties": {
    "gn:admin1_code":"15.0",
    "gn:asciiname":"Baxicun",
    "gn:country_code":"CN",
    "gn:dem":1680,
    "gn:feature_class":"P",
    "gn:feature_code":"PPL",
    "gn:name":"Baxicun",
    "gn:population":0,
    "gn:timezone":"Asia/Shanghai",
    "iso:country":"CN",
    "name:zho_x_preferred":[
        "\u575d\u897f\u6751"
    ],
    "wof:name":"Baxicun",
    "wof:placetype":"locality"
},
  "geometry": {"coordinates":[99.19289999999999,39.3371],"type":"Point"}
}