{
  "type": "Feature",
  "properties": {
    "gn:admin1_code":"9.0",
    "gn:asciiname":"Shangwangzhuang",
    "gn:country_code":"CN",
    "gn:dem":232,
    "gn:feature_class":"P",
    "gn:feature_code":"PPL",
    "gn:name":"Shangwangzhuang",
    "gn:population":0,
    "gn:timezone":"Asia/Shanghai",
    "iso:country":"CN",
    "name:und_x_variant":[
        "\u4e0a\u738b\u5e84",
        "Shangwangzhuang"
    ],
    "wof:name":"Shangwangzhuang",
    "wof:placetype":"locality"
},
  "geometry": {"coordinates":[112.75415,33.35645],"type":"Point"}
}