{
  "type": "Feature",
  "properties": {
    "gn:admin1_code":"5.0",
    "gn:asciiname":"Hatanggou",
    "gn:country_code":"CN",
    "gn:dem":451,
    "gn:feature_class":"P",
    "gn:feature_code":"PPL",
    "gn:name":"Hatanggou",
    "gn:population":0,
    "gn:timezone":"Asia/Shanghai",
    "iso:country":"CN",
    "name:und_x_variant":[
        "\u54c8\u5858\u6c9f"
    ],
    "wof:name":"Hatanggou",
    "wof:placetype":"locality"
},
  "geometry": {"coordinates":[125.75615999999999,41.31126],"type":"Point"}
}