{
  "type": "Feature",
  "properties": {
    "gn:admin1_code":"18",
    "gn:asciiname":"Laoxiongdong",
    "gn:country_code":"CN",
    "gn:dem":2319,
    "gn:feature_class":"P",
    "gn:feature_code":"PPL",
    "gn:name":"Laoxiongdong",
    "gn:population":0,
    "gn:timezone":"Asia/Shanghai",
    "iso:country":"CN",
    "name:zho_x_preferred":[
        "\u8001\u718a\u6d1e"
    ],
    "wof:name":"Laoxiongdong",
    "wof:placetype":"locality"
},
  "geometry": {"coordinates":[104.006,26.91800000000001],"type":"Point"}
}