{
  "type": "Feature",
  "properties": {
    "gn:admin1_code":"26.0",
    "gn:asciiname":"Fuyuancun",
    "gn:country_code":"CN",
    "gn:dem":594,
    "gn:feature_class":"P",
    "gn:feature_code":"PPL",
    "gn:name":"Fuyuancun",
    "gn:population":0,
    "gn:timezone":"Asia/Shanghai",
    "iso:country":"CN",
    "name:zho_x_preferred":[
        "\u5bcc\u586c\u6751"
    ],
    "wof:name":"Fuyuancun",
    "wof:placetype":"locality"
},
  "geometry": {"coordinates":[109.78722999999999,35.07797],"type":"Point"}
}