{
  "type": "Feature",
  "properties": {
    "gn:admin1_code":"4.0",
    "gn:asciiname":"Zhaoxiaolou",
    "gn:country_code":"CN",
    "gn:dem":39,
    "gn:feature_class":"P",
    "gn:feature_code":"PPL",
    "gn:name":"Zhaoxiaolou",
    "gn:population":0,
    "gn:timezone":"Asia/Shanghai",
    "iso:country":"CN",
    "name:zho_x_preferred":[
        "\u8d75\u5c0f\u697c"
    ],
    "wof:name":"Zhaoxiaolou",
    "wof:placetype":"locality"
},
  "geometry": {"coordinates":[116.989,34.5071],"type":"Point"}
}