{
  "type": "Feature",
  "properties": {
    "gn:admin1_code":"2.0",
    "gn:asciiname":"Tongjiacao",
    "gn:country_code":"CN",
    "gn:dem":6,
    "gn:feature_class":"P",
    "gn:feature_code":"PPL",
    "gn:name":"Tongjiacao",
    "gn:population":0,
    "gn:timezone":"Asia/Shanghai",
    "iso:country":"CN",
    "name:zho_x_preferred":[
        "\u7ae5\u5bb6\u6f15"
    ],
    "wof:name":"Tongjiacao",
    "wof:placetype":"locality"
},
  "geometry": {"coordinates":[121.58041,29.73837],"type":"Point"}
}