{
  "type": "Feature",
  "properties": {
    "gn:admin1_code":"22.0",
    "gn:asciiname":"Hegezhuang",
    "gn:country_code":"CN",
    "gn:dem":41,
    "gn:feature_class":"P",
    "gn:feature_code":"PPL",
    "gn:name":"Hegezhuang",
    "gn:population":0,
    "gn:timezone":"Asia/Shanghai",
    "iso:country":"CN",
    "name:zho_x_preferred":[
        "\u4f55\u5404\u5e84"
    ],
    "wof:name":"Hegezhuang",
    "wof:placetype":"locality"
},
  "geometry": {"coordinates":[116.49066999999999,40.03791],"type":"Point"}
}