{
  "type": "Feature",
  "properties": {
    "gn:admin1_code":"26.0",
    "gn:asciiname":"Yudu",
    "gn:country_code":"CN",
    "gn:dem":840,
    "gn:feature_class":"P",
    "gn:feature_code":"PPL",
    "gn:name":"Yudu",
    "gn:population":0,
    "gn:timezone":"Asia/Shanghai",
    "iso:country":"CN",
    "name:zho_x_preferred":[
        "\u6e14\u6e21"
    ],
    "wof:name":"Yudu",
    "wof:placetype":"locality"
},
  "geometry": {"coordinates":[107.98832,32.3249],"type":"Point"}
}