{
  "type": "Feature",
  "properties": {
    "gn:admin1_code":"10",
    "gn:asciiname":"Houxinzhai",
    "gn:country_code":"CN",
    "gn:dem":49,
    "gn:feature_class":"P",
    "gn:feature_code":"PPL",
    "gn:name":"Houxinzhai",
    "gn:population":0,
    "gn:timezone":"Asia/Shanghai",
    "iso:country":"CN",
    "name:zho_x_preferred":[
        "\u540e\u8f9b\u5be8"
    ],
    "wof:name":"Houxinzhai",
    "wof:placetype":"locality"
},
  "geometry": {"coordinates":[115.04904000000001,36.42244],"type":"Point"}
}