{
  "type": "Feature",
  "properties": {
    "gn:admin1_code":"19.0",
    "gn:asciiname":"Huligou",
    "gn:country_code":"CN",
    "gn:dem":84,
    "gn:feature_class":"P",
    "gn:feature_code":"PPL",
    "gn:name":"Huligou",
    "gn:population":0,
    "gn:timezone":"Asia/Shanghai",
    "iso:country":"CN",
    "name:und_x_variant":[
        "\u72d0\u72f8\u6c9f"
    ],
    "name:zho_x_preferred":[
        "\u72d0\u72f8\u6c9f"
    ],
    "wof:name":"Huligou",
    "wof:placetype":"locality"
},
  "geometry": {"coordinates":[123.37443,42.41721],"type":"Point"}
}