{
  "type": "Feature",
  "properties": {
    "gn:admin1_code":"32.0",
    "gn:asciiname":"Daozhai",
    "gn:country_code":"CN",
    "gn:dem":2670,
    "gn:feature_class":"P",
    "gn:feature_code":"PPL",
    "gn:name":"Daozhai",
    "gn:population":0,
    "gn:timezone":"Asia/Shanghai",
    "iso:country":"CN",
    "name:zho_x_preferred":[
        "\u5012\u5be8"
    ],
    "wof:name":"Daozhai",
    "wof:placetype":"locality"
},
  "geometry": {"coordinates":[100.63500000000001,28.3272],"type":"Point"}
}