{
  "type": "Feature",
  "properties": {
    "gn:admin1_code":"5.0",
    "gn:asciiname":"Xinglongzhencun",
    "gn:country_code":"CN",
    "gn:dem":197,
    "gn:feature_class":"P",
    "gn:feature_code":"PPL",
    "gn:name":"Xinglongzhencun",
    "gn:population":0,
    "gn:timezone":"Asia/Shanghai",
    "iso:country":"CN",
    "name:zho_x_preferred":[
        "\u5174\u9686\u9547\u6751"
    ],
    "wof:name":"Xinglongzhencun",
    "wof:placetype":"locality"
},
  "geometry": {"coordinates":[125.14858,44.5264],"type":"Point"}
}