{
  "type": "Feature",
  "properties": {
    "gn:admin1_code":"24.0",
    "gn:asciiname":"Rili",
    "gn:country_code":"CN",
    "gn:dem":825,
    "gn:feature_class":"P",
    "gn:feature_code":"PPL",
    "gn:name":"Rili",
    "gn:population":0,
    "gn:timezone":"Asia/Shanghai",
    "iso:country":"CN",
    "name:und_x_variant":[
        "\u65e5\u91cc"
    ],
    "wof:name":"Rili",
    "wof:placetype":"locality"
},
  "geometry": {"coordinates":[111.50978000000001,35.24451],"type":"Point"}
}