{
  "type": "Feature",
  "properties": {
    "gn:admin1_code":"4.0",
    "gn:asciiname":"Yuelaiji",
    "gn:country_code":"CN",
    "gn:dem":8,
    "gn:feature_class":"P",
    "gn:feature_code":"PPL",
    "gn:name":"Yuelaiji",
    "gn:population":0,
    "gn:timezone":"Asia/Shanghai",
    "iso:country":"CN",
    "name:und_x_variant":[
        "Y\u00fceh-lai-chi",
        "Yuelaiji"
    ],
    "wof:name":"Yuelaiji",
    "wof:placetype":"locality"
},
  "geometry": {"coordinates":[119.33674999999999,32.36543],"type":"Point"}
}