{
  "type": "Feature",
  "properties": {
    "gn:admin1_code":"09",
    "gn:asciiname":"Wangcun",
    "gn:cc2":"CN",
    "gn:country_code":"CN",
    "gn:dem":237,
    "gn:feature_class":"P",
    "gn:feature_code":"PPL",
    "gn:name":"Wangcun",
    "gn:population":0,
    "gn:timezone":"Asia/Shanghai",
    "iso:country":"CN",
    "name:und_x_variant":[
        "Wang-ts\u2019un",
        "Wangcun"
    ],
    "wof:name":"Wangcun",
    "wof:placetype":"locality"
},
  "geometry": {"coordinates":[113.25639,34.35805999999999],"type":"Point"}
}