{
  "type": "Feature",
  "properties": {
    "gn:admin1_code":"12",
    "gn:asciiname":"Gepu",
    "gn:cc2":"CN",
    "gn:country_code":"CN",
    "gn:dem":27,
    "gn:feature_class":"P",
    "gn:feature_code":"PPL",
    "gn:name":"Gepu",
    "gn:population":0,
    "gn:timezone":"Asia/Shanghai",
    "iso:country":"CN",
    "name:und_x_variant":[
        "Ko-p\u2019u",
        "Gepu"
    ],
    "wof:name":"Gepu",
    "wof:placetype":"locality"
},
  "geometry": {"coordinates":[113.71666999999999,30.93333],"type":"Point"}
}