{
  "type": "Feature",
  "properties": {
    "gn:admin1_code":"30.0",
    "gn:asciiname":"Shanzixia",
    "gn:country_code":"CN",
    "gn:dem":44,
    "gn:feature_class":"P",
    "gn:feature_code":"PPL",
    "gn:name":"Shanzixia",
    "gn:population":0,
    "gn:timezone":"Asia/Shanghai",
    "iso:country":"CN",
    "name:zho_x_preferred":[
        "\u5c71\u5b50\u5413"
    ],
    "wof:name":"Shanzixia",
    "wof:placetype":"locality"
},
  "geometry": {"coordinates":[114.01163,23.59282],"type":"Point"}
}