{
  "type": "Feature",
  "properties": {
    "gn:admin1_code":"24.0",
    "gn:asciiname":"Wenjiagou",
    "gn:cc2":"CN",
    "gn:country_code":"CN",
    "gn:dem":1429,
    "gn:feature_class":"P",
    "gn:feature_code":"PPL",
    "gn:name":"Wenjiagou",
    "gn:population":0,
    "gn:timezone":"Asia/Shanghai",
    "iso:country":"CN",
    "name:und_x_variant":[
        "Wen-chia-kou",
        "Wenjiagou"
    ],
    "wof:name":"Wenjiagou",
    "wof:placetype":"locality"
},
  "geometry": {"coordinates":[111.03333000000001,37.03333],"type":"Point"}
}