{
  "type": "Feature",
  "properties": {
    "gn:admin1_code":"15.0",
    "gn:asciiname":"Huangdunzi Nongchang Erdui",
    "gn:country_code":"CN",
    "gn:dem":1061,
    "gn:feature_class":"P",
    "gn:feature_code":"PPLF",
    "gn:name":"Huangdunzi Nongchang Erdui",
    "gn:population":0,
    "gn:timezone":"Asia/Urumqi",
    "iso:country":"CN",
    "name:eng_x_preferred":[
        "Huangdunzi Nongchang Second Dui"
    ],
    "name:zho_x_preferred":[
        "\u9ec4\u58a9\u5b50\u519c\u573a\u4e8c\u961f"
    ],
    "wof:name":"Huangdunzi Nongchang Erdui",
    "wof:placetype":"locality"
},
  "geometry": {"coordinates":[94.68517,40.39964000000001],"type":"Point"}
}