{
  "type": "Feature",
  "properties": {
    "gn:admin1_code":"32.0",
    "gn:asciiname":"Hepo",
    "gn:country_code":"CN",
    "gn:dem":3188,
    "gn:feature_class":"P",
    "gn:feature_code":"PPL",
    "gn:name":"Hepo",
    "gn:population":0,
    "gn:timezone":"Asia/Shanghai",
    "iso:country":"CN",
    "name:und_x_variant":[
        "Horbo",
        "Hepo"
    ],
    "name:zho_x_preferred":[
        "\u6cb3\u5761"
    ],
    "wof:name":"Hepo",
    "wof:placetype":"locality"
},
  "geometry": {"coordinates":[98.9513,31.38975],"type":"Point"}
}