{
  "type": "Feature",
  "properties": {
    "gn:admin1_code":"19.0",
    "gn:asciiname":"Beiyanggou",
    "gn:country_code":"CN",
    "gn:dem":256,
    "gn:feature_class":"P",
    "gn:feature_code":"PPL",
    "gn:name":"Beiyanggou",
    "gn:population":0,
    "gn:timezone":"Asia/Shanghai",
    "iso:country":"CN",
    "name:zho_x_preferred":[
        "\u5317\u9633\u6c9f"
    ],
    "wof:name":"Beiyanggou",
    "wof:placetype":"locality"
},
  "geometry": {"coordinates":[125.59632999999999,40.98424],"type":"Point"}
}