{
  "type": "Feature",
  "properties": {
    "gn:admin1_code":"4.0",
    "gn:asciiname":"Shixia",
    "gn:country_code":"CN",
    "gn:dem":3,
    "gn:feature_class":"P",
    "gn:feature_code":"PPL",
    "gn:name":"Shixia",
    "gn:population":0,
    "gn:timezone":"Asia/Shanghai",
    "iso:country":"CN",
    "name:zho_x_preferred":[
        "Shixia"
    ],
    "name:zho_x_variant":[
        "\u77f3\u5323"
    ],
    "wof:name":"Shixia",
    "wof:placetype":"locality"
},
  "geometry": {"coordinates":[119.7426,33.34262],"type":"Point"}
}