{
  "type": "Feature",
  "properties": {
    "gn:admin1_code":"24.0",
    "gn:asciiname":"Wochang",
    "gn:country_code":"CN",
    "gn:dem":1491,
    "gn:feature_class":"P",
    "gn:feature_code":"PPL",
    "gn:name":"Wochang",
    "gn:population":0,
    "gn:timezone":"Asia/Shanghai",
    "iso:country":"CN",
    "name:und_x_variant":[
        "\u5367\u5382"
    ],
    "wof:name":"Wochang",
    "wof:placetype":"locality"
},
  "geometry": {"coordinates":[112.24703999999998,39.48428],"type":"Point"}
}