{
  "type": "Feature",
  "properties": {
    "gn:admin1_code":"11.0",
    "gn:asciiname":"Changyuan",
    "gn:country_code":"CN",
    "gn:dem":229,
    "gn:feature_class":"P",
    "gn:feature_code":"PPL",
    "gn:name":"Changyuan",
    "gn:population":0,
    "gn:timezone":"Asia/Shanghai",
    "iso:country":"CN",
    "name:zho_x_preferred":[
        "\u957f\u8fdc"
    ],
    "wof:name":"Changyuan",
    "wof:placetype":"locality"
},
  "geometry": {"coordinates":[109.95789000000001,27.47157],"type":"Point"}
}