{
  "type": "Feature",
  "properties": {
    "gn:admin1_code":"26.0",
    "gn:asciiname":"Wangjiazhuang",
    "gn:country_code":"CN",
    "gn:dem":730,
    "gn:feature_class":"P",
    "gn:feature_code":"PPL",
    "gn:name":"Wangjiazhuang",
    "gn:population":0,
    "gn:timezone":"Asia/Shanghai",
    "iso:country":"CN",
    "name:zho_x_preferred":[
        "\u738b\u5bb6\u5e84"
    ],
    "wof:name":"Wangjiazhuang",
    "wof:placetype":"locality"
},
  "geometry": {"coordinates":[108.87827,34.83125],"type":"Point"}
}