{
  "type": "Feature",
  "properties": {
    "gn:admin1_code":"18.0",
    "gn:asciiname":"Dongwan",
    "gn:country_code":"CN",
    "gn:dem":1069,
    "gn:feature_class":"P",
    "gn:feature_code":"PPL",
    "gn:name":"Dongwan",
    "gn:population":0,
    "gn:timezone":"Asia/Shanghai",
    "iso:country":"CN",
    "name:deu_x_preferred":[
        "Dongwan"
    ],
    "wof:name":"Dongwan",
    "wof:placetype":"locality"
},
  "geometry": {"coordinates":[106.21666999999999,28.22861],"type":"Point"}
}