{
  "type": "Feature",
  "properties": {
    "gn:admin1_code":"07",
    "gn:asciiname":"Guanchengwei",
    "gn:country_code":"CN",
    "gn:dem":100,
    "gn:feature_class":"P",
    "gn:feature_code":"PPL",
    "gn:name":"Guanchengwei",
    "gn:population":0,
    "gn:timezone":"Asia/Shanghai",
    "iso:country":"CN",
    "name:zho_x_preferred":[
        "Kuan-ch\u2019eng"
    ],
    "name:zho_x_variant":[
        "\u5b98\u57ce\u5c3e"
    ],
    "wof:name":"Guanchengwei",
    "wof:placetype":"locality"
},
  "geometry": {"coordinates":[120.40648,27.12323],"type":"Point"}
}