{
  "type": "Feature",
  "properties": {
    "gn:admin1_code":"16.0",
    "gn:asciiname":"Laoshengwu",
    "gn:country_code":"CN",
    "gn:dem":16,
    "gn:feature_class":"P",
    "gn:feature_code":"PPL",
    "gn:name":"Laoshengwu",
    "gn:population":0,
    "gn:timezone":"Asia/Shanghai",
    "iso:country":"CN",
    "name:zho_x_preferred":[
        "\u8001\u76db\u5c4b"
    ],
    "wof:name":"Laoshengwu",
    "wof:placetype":"locality"
},
  "geometry": {"coordinates":[109.27800000000001,21.806],"type":"Point"}
}