{
  "type": "Feature",
  "properties": {
    "gn:admin1_code":"24.0",
    "gn:asciiname":"Nanxincun",
    "gn:country_code":"CN",
    "gn:dem":1400,
    "gn:feature_class":"P",
    "gn:feature_code":"PPL",
    "gn:name":"Nanxincun",
    "gn:population":0,
    "gn:timezone":"Asia/Shanghai",
    "iso:country":"CN",
    "name:zho_x_preferred":[
        "\u5357\u8f9b\u6751"
    ],
    "wof:name":"Nanxincun",
    "wof:placetype":"locality"
},
  "geometry": {"coordinates":[113.03633000000001,40.03877],"type":"Point"}
}