{
  "type": "Feature",
  "properties": {
    "gn:admin1_code":"6.0",
    "gn:asciiname":"Qishiyi Daoban",
    "gn:country_code":"CN",
    "gn:dem":4540,
    "gn:feature_class":"P",
    "gn:feature_code":"PPL",
    "gn:name":"Qishiyi Daoban",
    "gn:population":0,
    "gn:timezone":"Asia/Urumqi",
    "iso:country":"CN",
    "name:und_x_variant":[
        "\u4e03\u5341\u4e00\u9053\u73ed"
    ],
    "wof:name":"Qishiyi Daoban",
    "wof:placetype":"locality"
},
  "geometry": {"coordinates":[93.29640999999999,35.30129],"type":"Point"}
}