{
  "type": "Feature",
  "properties": {
    "gn:admin1_code":"25.0",
    "gn:asciiname":"Zhangshibucun",
    "gn:country_code":"CN",
    "gn:dem":93,
    "gn:feature_class":"P",
    "gn:feature_code":"PPL",
    "gn:name":"Zhangshibucun",
    "gn:population":0,
    "gn:timezone":"Asia/Shanghai",
    "iso:country":"CN",
    "name:zho_x_preferred":[
        "\u5f20\u77f3\u57e0\u6751"
    ],
    "wof:name":"Zhangshibucun",
    "wof:placetype":"locality"
},
  "geometry": {"coordinates":[120.4084,37.30371],"type":"Point"}
}