{
  "type": "Feature",
  "properties": {
    "gn:admin1_code":"12.0",
    "gn:asciiname":"Xiongjiatai",
    "gn:country_code":"CN",
    "gn:dem":112,
    "gn:feature_class":"P",
    "gn:feature_code":"PPL",
    "gn:name":"Xiongjiatai",
    "gn:population":0,
    "gn:timezone":"Asia/Shanghai",
    "iso:country":"CN",
    "name:zho_x_preferred":[
        "\u718a\u5bb6\u53f0"
    ],
    "wof:name":"Xiongjiatai",
    "wof:placetype":"locality"
},
  "geometry": {"coordinates":[112.88106000000001,31.14016],"type":"Point"}
}