{
  "type": "Feature",
  "properties": {
    "gn:admin1_code":"14.0",
    "gn:asciiname":"Dalaicun",
    "gn:country_code":"CN",
    "gn:dem":4725,
    "gn:feature_class":"P",
    "gn:feature_code":"PPL",
    "gn:name":"Dalaicun",
    "gn:population":0,
    "gn:timezone":"Asia/Urumqi",
    "iso:country":"CN",
    "name:zho_x_preferred":[
        "\u8fbe\u6765\u6751"
    ],
    "wof:name":"Dalaicun",
    "wof:placetype":"locality"
},
  "geometry": {"coordinates":[90.55058,32.10584],"type":"Point"}
}