{
  "type": "Feature",
  "properties": {
    "gn:admin1_code":"3.0",
    "gn:asciiname":"Qiujia",
    "gn:country_code":"CN",
    "gn:dem":74,
    "gn:feature_class":"P",
    "gn:feature_code":"PPL",
    "gn:name":"Qiujia",
    "gn:population":0,
    "gn:timezone":"Asia/Shanghai",
    "iso:country":"CN",
    "name:und_x_variant":[
        "\u90b1\u5bb6"
    ],
    "wof:name":"Qiujia",
    "wof:placetype":"locality"
},
  "geometry": {"coordinates":[114.86266999999999,29.21103],"type":"Point"}
}