{
  "type": "Feature",
  "properties": {
    "gn:admin1_code":"1.0",
    "gn:asciiname":"Tianzhucun",
    "gn:country_code":"CN",
    "gn:dem":369,
    "gn:feature_class":"P",
    "gn:feature_code":"PPL",
    "gn:name":"Tianzhucun",
    "gn:population":0,
    "gn:timezone":"Asia/Shanghai",
    "iso:country":"CN",
    "name:zho_x_preferred":[
        "\u5929\u7afa\u6751"
    ],
    "wof:name":"Tianzhucun",
    "wof:placetype":"locality"
},
  "geometry": {"coordinates":[118.72369,30.59967],"type":"Point"}
}