{
  "type": "Feature",
  "properties": {
    "gn:admin1_code":"32.0",
    "gn:asciiname":"Gongyi",
    "gn:country_code":"CN",
    "gn:dem":1768,
    "gn:feature_class":"P",
    "gn:feature_code":"PPL",
    "gn:name":"Gongyi",
    "gn:population":0,
    "gn:timezone":"Asia/Shanghai",
    "iso:country":"CN",
    "name:zho_x_preferred":[
        "\u516c\u76ca"
    ],
    "wof:name":"Gongyi",
    "wof:placetype":"locality"
},
  "geometry": {"coordinates":[102.358,29.0546],"type":"Point"}
}