{
  "type": "Feature",
  "properties": {
    "gn:admin1_code":"10",
    "gn:asciiname":"Tiechuangkou",
    "gn:country_code":"CN",
    "gn:dem":48,
    "gn:feature_class":"P",
    "gn:feature_code":"PPL",
    "gn:name":"Tiechuangkou",
    "gn:population":0,
    "gn:timezone":"Asia/Shanghai",
    "iso:country":"CN",
    "name:zho_x_preferred":[
        "\u94c1\u7a97\u53e3"
    ],
    "wof:name":"Tiechuangkou",
    "wof:placetype":"locality"
},
  "geometry": {"coordinates":[115.18079,36.31606],"type":"Point"}
}