{
  "type": "Feature",
  "properties": {
    "gn:admin1_code":"4.0",
    "gn:asciiname":"Dongxiangcun",
    "gn:country_code":"CN",
    "gn:dem":12,
    "gn:feature_class":"P",
    "gn:feature_code":"PPL",
    "gn:name":"Dongxiangcun",
    "gn:population":0,
    "gn:timezone":"Asia/Shanghai",
    "iso:country":"CN",
    "name:zho_x_preferred":[
        "\u8463\u5df7\u6751"
    ],
    "wof:name":"Dongxiangcun",
    "wof:placetype":"locality"
},
  "geometry": {"coordinates":[118.83629999999999,33.6991],"type":"Point"}
}