{
  "type": "Feature",
  "properties": {
    "gn:admin1_code":"32.0",
    "gn:asciiname":"Zhengyuan",
    "gn:country_code":"CN",
    "gn:dem":580,
    "gn:feature_class":"P",
    "gn:feature_code":"PPL",
    "gn:name":"Zhengyuan",
    "gn:population":0,
    "gn:timezone":"Asia/Shanghai",
    "iso:country":"CN",
    "name:und_x_variant":[
        "Zhengyuanxiang",
        "\u6b63\u6e90\u4e61"
    ],
    "name:zho_x_preferred":[
        "\u6b63\u6e90"
    ],
    "wof:name":"Zhengyuan",
    "wof:placetype":"locality"
},
  "geometry": {"coordinates":[106.33411,32.40461],"type":"Point"}
}