{
  "type": "Feature",
  "properties": {
    "gn:admin1_code":"2.0",
    "gn:asciiname":"Lutang",
    "gn:country_code":"CN",
    "gn:dem":71,
    "gn:feature_class":"P",
    "gn:feature_code":"PPL",
    "gn:name":"L\u00fctang",
    "gn:population":0,
    "gn:timezone":"Asia/Shanghai",
    "iso:country":"CN",
    "name:und_x_variant":[
        "L\u00fctang"
    ],
    "name:zho_x_preferred":[
        "\u5415\u5858"
    ],
    "wof:name":"Lutang",
    "wof:placetype":"locality"
},
  "geometry": {"coordinates":[119.10886000000001,29.05291],"type":"Point"}
}