{
  "type": "Feature",
  "properties": {
    "gn:admin1_code":"16.0",
    "gn:asciiname":"Zhendi",
    "gn:country_code":"CN",
    "gn:dem":37,
    "gn:feature_class":"P",
    "gn:feature_code":"PPL",
    "gn:name":"Zhendi",
    "gn:population":0,
    "gn:timezone":"Asia/Shanghai",
    "iso:country":"CN",
    "name:zho_x_preferred":[
        "\u5733\u5e95"
    ],
    "wof:name":"Zhendi",
    "wof:placetype":"locality"
},
  "geometry": {"coordinates":[111.065,23.7206],"type":"Point"}
}