{
  "type": "Feature",
  "properties": {
    "gn:admin1_code":"25.0",
    "gn:asciiname":"Xiongyasuo",
    "gn:country_code":"CN",
    "gn:dem":30,
    "gn:feature_class":"P",
    "gn:feature_code":"PPL",
    "gn:name":"Xiongyasuo",
    "gn:population":0,
    "gn:timezone":"Asia/Shanghai",
    "iso:country":"CN",
    "name:zho_x_preferred":[
        "\u96c4\u5d16\u6240"
    ],
    "wof:name":"Xiongyasuo",
    "wof:placetype":"locality"
},
  "geometry": {"coordinates":[120.86418,36.584],"type":"Point"}
}