{
  "type": "Feature",
  "properties": {
    "gn:admin1_code":"29.0",
    "gn:asciiname":"Dadianhe",
    "gn:country_code":"CN",
    "gn:dem":2151,
    "gn:feature_class":"P",
    "gn:feature_code":"PPL",
    "gn:name":"Dadianhe",
    "gn:population":0,
    "gn:timezone":"Asia/Shanghai",
    "iso:country":"CN",
    "name:zho_x_preferred":[
        "\u6253\u975b\u6cb3"
    ],
    "wof:name":"Dadianhe",
    "wof:placetype":"locality"
},
  "geometry": {"coordinates":[98.4729,24.5506],"type":"Point"}
}