{
  "type": "Feature",
  "properties": {
    "gn:admin1_code":"7.0",
    "gn:asciiname":"Qianding",
    "gn:country_code":"CN",
    "gn:dem":128,
    "gn:feature_class":"P",
    "gn:feature_code":"PPL",
    "gn:name":"Qianding",
    "gn:population":0,
    "gn:timezone":"Asia/Shanghai",
    "iso:country":"CN",
    "name:und_x_variant":[
        "\u4e7e\u9876"
    ],
    "name:zho_x_preferred":[
        "Qianding"
    ],
    "wof:name":"Qianding",
    "wof:placetype":"locality"
},
  "geometry": {"coordinates":[119.28095999999999,26.15833],"type":"Point"}
}