{
  "type": "Feature",
  "properties": {
    "gn:admin1_code":"26.0",
    "gn:asciiname":"Niutoushan",
    "gn:country_code":"CN",
    "gn:dem":845,
    "gn:feature_class":"P",
    "gn:feature_code":"PPL",
    "gn:name":"Niutoushan",
    "gn:population":0,
    "gn:timezone":"Asia/Shanghai",
    "iso:country":"CN",
    "name:zho_x_preferred":[
        "\u725b\u5934\u5c71"
    ],
    "wof:name":"Niutoushan",
    "wof:placetype":"locality"
},
  "geometry": {"coordinates":[109.38146999999999,32.43841],"type":"Point"}
}