{
  "type": "Feature",
  "properties": {
    "gn:admin1_code":"3",
    "gn:asciiname":"Dakengwei",
    "gn:country_code":"CN",
    "gn:dem":184,
    "gn:feature_class":"P",
    "gn:feature_code":"PPL",
    "gn:name":"Dakengwei",
    "gn:population":0,
    "gn:timezone":"Asia/Shanghai",
    "iso:country":"CN",
    "name:zho_x_preferred":[
        "\u5927\u5751\u5c3e"
    ],
    "wof:name":"Dakengwei",
    "wof:placetype":"locality"
},
  "geometry": {"coordinates":[114.952,26.2724],"type":"Point"}
}