{
  "type": "Feature",
  "properties": {
    "gn:admin1_code":"16.0",
    "gn:asciiname":"Pinglu",
    "gn:country_code":"CN",
    "gn:dem":114,
    "gn:feature_class":"P",
    "gn:feature_code":"PPL",
    "gn:name":"Pinglu",
    "gn:population":0,
    "gn:timezone":"Asia/Shanghai",
    "iso:country":"CN",
    "name:deu_x_preferred":[
        "Pinglu"
    ],
    "name:swe_x_preferred":[
        "Pinglu"
    ],
    "name:zho_x_preferred":[
        "\u5e73\u9646"
    ],
    "wof:name":"Pinglu",
    "wof:placetype":"locality"
},
  "geometry": {"coordinates":[108.289,23.0955],"type":"Point"}
}