{
  "type": "Feature",
  "properties": {
    "gn:admin1_code":"20.0",
    "gn:asciiname":"Paotai Lazi",
    "gn:country_code":"CN",
    "gn:dem":402,
    "gn:feature_class":"P",
    "gn:feature_code":"PPL",
    "gn:name":"Paotai Lazi",
    "gn:population":0,
    "gn:timezone":"Asia/Shanghai",
    "iso:country":"CN",
    "name:zho_x_preferred":[
        "\u70ae\u53f0\u782c\u5b50"
    ],
    "wof:name":"Paotai Lazi",
    "wof:placetype":"locality"
},
  "geometry": {"coordinates":[122.10787999999999,47.6243],"type":"Point"}
}