{
  "type": "Feature",
  "properties": {
    "gn:admin1_code":"32.0",
    "gn:asciiname":"Mu'erzong",
    "gn:country_code":"CN",
    "gn:dem":3599,
    "gn:feature_class":"P",
    "gn:feature_code":"PPL",
    "gn:name":"Mu\u2019erzong",
    "gn:population":0,
    "gn:timezone":"Asia/Shanghai",
    "iso:country":"CN",
    "name:zho_x_preferred":[
        "\u6728\u5c14\u5b97"
    ],
    "name:zho_x_variant":[
        "Mu\u2019erzong"
    ],
    "wof:name":"Mu'erzong",
    "wof:placetype":"locality"
},
  "geometry": {"coordinates":[101.72228,31.87199],"type":"Point"}
}