{
  "type": "Feature",
  "properties": {
    "gn:admin1_code":"3.0",
    "gn:asciiname":"Tuziliao",
    "gn:country_code":"CN",
    "gn:dem":474,
    "gn:feature_class":"P",
    "gn:feature_code":"PPL",
    "gn:name":"Tuziliao",
    "gn:population":0,
    "gn:timezone":"Asia/Shanghai",
    "iso:country":"CN",
    "name:und_x_variant":[
        "\u5154\u5b50\u5bee"
    ],
    "wof:name":"Tuziliao",
    "wof:placetype":"locality"
},
  "geometry": {"coordinates":[116.17337000000001,26.50753],"type":"Point"}
}