{
  "type": "Feature",
  "properties": {
    "gn:admin1_code":"32.0",
    "gn:asciiname":"Qiujianian",
    "gn:country_code":"CN",
    "gn:dem":473,
    "gn:feature_class":"P",
    "gn:feature_code":"PPL",
    "gn:name":"Qiujianian",
    "gn:population":0,
    "gn:timezone":"Asia/Shanghai",
    "iso:country":"CN",
    "name:zho_x_preferred":[
        "\u90b1\u5bb6\u78be"
    ],
    "wof:name":"Qiujianian",
    "wof:placetype":"locality"
},
  "geometry": {"coordinates":[104.24475,30.8104],"type":"Point"}
}