{
  "type": "Feature",
  "properties": {
    "gn:admin1_code":"7.0",
    "gn:asciiname":"Hengyuan",
    "gn:country_code":"CN",
    "gn:dem":436,
    "gn:feature_class":"P",
    "gn:feature_code":"PPL",
    "gn:name":"Hengyuan",
    "gn:population":0,
    "gn:timezone":"Asia/Shanghai",
    "iso:country":"CN",
    "name:zho_x_preferred":[
        "\u6a2a\u6e90"
    ],
    "wof:name":"Hengyuan",
    "wof:placetype":"locality"
},
  "geometry": {"coordinates":[118.16236000000001,27.969],"type":"Point"}
}