{
  "type": "Feature",
  "properties": {
    "gn:admin1_code":"29.0",
    "gn:asciiname":"Dashipen",
    "gn:country_code":"CN",
    "gn:dem":2016,
    "gn:feature_class":"P",
    "gn:feature_code":"PPL",
    "gn:name":"Dashipen",
    "gn:population":0,
    "gn:timezone":"Asia/Shanghai",
    "iso:country":"CN",
    "name:und_x_variant":[
        "\u5927\u77f3\u76c6"
    ],
    "wof:name":"Dashipen",
    "wof:placetype":"locality"
},
  "geometry": {"coordinates":[103.69341,26.02515],"type":"Point"}
}