{
  "type": "Feature",
  "properties": {
    "gn:admin1_code":"20",
    "gn:asciiname":"Tuozaminnutuke",
    "gn:country_code":"CN",
    "gn:dem":529,
    "gn:feature_class":"P",
    "gn:feature_code":"PPLA4",
    "gn:name":"Tuozaminnutuke",
    "gn:population":0,
    "gn:timezone":"Asia/Shanghai",
    "iso:country":"CN",
    "name:und_x_variant":[
        "Tuozhaminnutuke",
        "Tuozaminnutuke",
        "T\u2019o-cha-min-nu-t\u2019u-k\u2019o",
        "Tuozhamin",
        "Tuozhamin Xiang"
    ],
    "name:zho_x_preferred":[
        "\u6258\u624e\u654f"
    ],
    "name:zho_x_variant":[
        "\u6258\u624e\u654f\u4e61"
    ],
    "wof:name":"Tuozaminnutuke",
    "wof:placetype":"locality"
},
  "geometry": {"coordinates":[123.10306,50.15944],"type":"Point"}
}