{
  "type": "Feature",
  "properties": {
    "gn:admin1_code":"9.0",
    "gn:asciiname":"Houjiazhuang",
    "gn:country_code":"CN",
    "gn:dem":152,
    "gn:feature_class":"P",
    "gn:feature_code":"PPL",
    "gn:name":"Houjiazhuang",
    "gn:population":0,
    "gn:timezone":"Asia/Shanghai",
    "iso:country":"CN",
    "name:zho_x_preferred":[
        "\u540e\u8d3e\u5e84"
    ],
    "wof:name":"Houjiazhuang",
    "wof:placetype":"locality"
},
  "geometry": {"coordinates":[113.07172,33.0382],"type":"Point"}
}