{
  "type": "Feature",
  "properties": {
    "gn:admin1_code":"8.0",
    "gn:asciiname":"Xiaosihecun",
    "gn:country_code":"CN",
    "gn:dem":120,
    "gn:feature_class":"P",
    "gn:feature_code":"PPL",
    "gn:name":"Xiaosihecun",
    "gn:population":0,
    "gn:timezone":"Asia/Shanghai",
    "iso:country":"CN",
    "name:zho_x_preferred":[
        "\u5c0f\u56db\u5408\u6751"
    ],
    "wof:name":"Xiaosihecun",
    "wof:placetype":"locality"
},
  "geometry": {"coordinates":[130.20988,46.39384],"type":"Point"}
}