{
  "type": "Feature",
  "properties": {
    "gn:admin1_code":"29.0",
    "gn:asciiname":"Guidehai",
    "gn:country_code":"CN",
    "gn:dem":1678,
    "gn:feature_class":"P",
    "gn:feature_code":"PPL",
    "gn:name":"Guidehai",
    "gn:population":0,
    "gn:timezone":"Asia/Shanghai",
    "iso:country":"CN",
    "name:zho_x_preferred":[
        "\u5f52\u5f97\u6d77"
    ],
    "wof:name":"Guidehai",
    "wof:placetype":"locality"
},
  "geometry": {"coordinates":[102.357,23.2153],"type":"Point"}
}