{
  "type": "Feature",
  "properties": {
    "gn:admin1_code":"29",
    "gn:asciiname":"Xujiatou",
    "gn:country_code":"CN",
    "gn:dem":1754,
    "gn:feature_class":"P",
    "gn:feature_code":"PPL",
    "gn:name":"Xujiatou",
    "gn:population":0,
    "gn:timezone":"Asia/Shanghai",
    "iso:country":"CN",
    "name:zho_x_preferred":[
        "\u5f90\u5bb6\u5934"
    ],
    "wof:name":"Xujiatou",
    "wof:placetype":"locality"
},
  "geometry": {"coordinates":[102.789,24.4023],"type":"Point"}
}