{
  "type": "Feature",
  "properties": {
    "gn:country":"CN",
    "gn:fcode":"PPL",
    "gn:pop":61292,
    "iso:country":"CN",
    "name:eng_x_preferred":[
        "Tianchang"
    ],
    "name:swe_x_preferred":[
        "Tianchang"
    ],
    "name:unk_x_variant":[
        "Ching-nan"
    ],
    "name:zho_x_preferred":[
        "\u5929\u957f\u9547"
    ],
    "qs:name":"Tianchang",
    "qs:photos_9r":0,
    "qs:photos_sr":0,
    "qs:pop_sr":"8",
    "wd:wordcount":36,
    "wof:name":"Tianchang",
    "wof:placetype":"locality",
    "wof:population":61292
},
  "geometry": {"coordinates":[114.01555999999999,37.99806],"type":"Point"}
}