{
  "type": "Feature",
  "properties": {
    "gn:admin1_code":"25.0",
    "gn:asciiname":"Hanjialiu",
    "gn:cc2":"CN",
    "gn:country_code":"CN",
    "gn:dem":23,
    "gn:feature_class":"P",
    "gn:feature_code":"PPL",
    "gn:name":"Hanjialiu",
    "gn:population":0,
    "gn:timezone":"Asia/Shanghai",
    "iso:country":"CN",
    "name:zho_x_preferred":[
        "\u97e9\u5bb6\u6e9c"
    ],
    "wof:name":"Hanjialiu",
    "wof:placetype":"locality"
},
  "geometry": {"coordinates":[119.76147,35.73772],"type":"Point"}
}