{
  "type": "Feature",
  "properties": {
    "gn:admin1_code":"29.0",
    "gn:asciiname":"Benglongdong",
    "gn:country_code":"CN",
    "gn:dem":1127,
    "gn:feature_class":"P",
    "gn:feature_code":"PPL",
    "gn:name":"Benglongdong",
    "gn:population":0,
    "gn:timezone":"Asia/Shanghai",
    "iso:country":"CN",
    "name:zho_x_preferred":[
        "\u5d29\u9f99\u4e1c"
    ],
    "wof:name":"Benglongdong",
    "wof:placetype":"locality"
},
  "geometry": {"coordinates":[97.7855,24.0266],"type":"Point"}
}