{
  "type": "Feature",
  "properties": {
    "gn:admin1_code":"16.0",
    "gn:asciiname":"Liuchengshang",
    "gn:country_code":"CN",
    "gn:dem":629,
    "gn:feature_class":"P",
    "gn:feature_code":"PPL",
    "gn:name":"Liuchengshang",
    "gn:population":0,
    "gn:timezone":"Asia/Shanghai",
    "iso:country":"CN",
    "name:zho_x_preferred":[
        "\u516d\u57ce\u4e0a"
    ],
    "wof:name":"Liuchengshang",
    "wof:placetype":"locality"
},
  "geometry": {"coordinates":[107.611,24.0487],"type":"Point"}
}