{
  "type": "Feature",
  "properties": {
    "gn:admin1_code":"33.0",
    "gn:asciiname":"Wanqing",
    "gn:country_code":"CN",
    "gn:dem":742,
    "gn:feature_class":"P",
    "gn:feature_code":"PPL",
    "gn:name":"Wanqing",
    "gn:population":0,
    "gn:timezone":"Asia/Shanghai",
    "iso:country":"CN",
    "name:zho_x_preferred":[
        "\u4e07\u5e86"
    ],
    "wof:name":"Wanqing",
    "wof:placetype":"locality"
},
  "geometry": {"coordinates":[108.61735,29.4893],"type":"Point"}
}