{
  "type": "Feature",
  "properties": {
    "gn:admin1_code":"12.0",
    "gn:asciiname":"Liufangwan",
    "gn:country_code":"CN",
    "gn:dem":181,
    "gn:feature_class":"P",
    "gn:feature_code":"PPL",
    "gn:name":"Liufangwan",
    "gn:population":0,
    "gn:timezone":"Asia/Shanghai",
    "iso:country":"CN",
    "name:zho_x_preferred":[
        "\u516d\u623f\u5846"
    ],
    "wof:name":"Liufangwan",
    "wof:placetype":"locality"
},
  "geometry": {"coordinates":[112.98406,32.17378],"type":"Point"}
}