{
  "type": "Feature",
  "properties": {
    "gn:admin1_code":"2.0",
    "gn:asciiname":"Dajianxi",
    "gn:country_code":"CN",
    "gn:dem":113,
    "gn:feature_class":"P",
    "gn:feature_code":"PPL",
    "gn:name":"Dajianxi",
    "gn:population":0,
    "gn:timezone":"Asia/Shanghai",
    "iso:country":"CN",
    "name:zho_x_preferred":[
        "\u5927\u517c\u6eaa"
    ],
    "wof:name":"Dajianxi",
    "wof:placetype":"locality"
},
  "geometry": {"coordinates":[120.3943,29.62978],"type":"Point"}
}