{
  "type": "Feature",
  "properties": {
    "gn:admin1_code":"19.0",
    "gn:asciiname":"Nanbo Bugou",
    "gn:country_code":"CN",
    "gn:dem":313,
    "gn:feature_class":"P",
    "gn:feature_code":"PPL",
    "gn:name":"Nanbo Bugou",
    "gn:population":0,
    "gn:timezone":"Asia/Shanghai",
    "iso:country":"CN",
    "name:und_x_variant":[
        "Nanbopugou",
        "\u5357\u62e8\u5821\u6c9f",
        "Nanbo Bugou"
    ],
    "wof:name":"Nanbo Bugou",
    "wof:placetype":"locality"
},
  "geometry": {"coordinates":[124.92716,41.69736],"type":"Point"}
}