{
  "type": "Feature",
  "properties": {
    "gn:admin1_code":"1.0",
    "gn:asciiname":"Gaofengcun",
    "gn:country_code":"CN",
    "gn:dem":38,
    "gn:feature_class":"P",
    "gn:feature_code":"PPL",
    "gn:name":"Gaofengcun",
    "gn:population":0,
    "gn:timezone":"Asia/Shanghai",
    "iso:country":"CN",
    "name:zho_x_preferred":[
        "\u9ad8\u5cf0\u6751"
    ],
    "wof:name":"Gaofengcun",
    "wof:placetype":"locality"
},
  "geometry": {"coordinates":[116.66228999999998,30.67266],"type":"Point"}
}