{
  "type": "Feature",
  "properties": {
    "gn:admin1_code":"14",
    "gn:asciiname":"Longsang",
    "gn:country_code":"CN",
    "gn:dem":3883,
    "gn:feature_class":"P",
    "gn:feature_code":"PPL",
    "gn:name":"Longsang",
    "gn:population":0,
    "gn:timezone":"Asia/Urumqi",
    "iso:country":"CN",
    "name:zho_x_preferred":[
        "\u9f99\u6851"
    ],
    "wof:name":"Longsang",
    "wof:placetype":"locality"
},
  "geometry": {"coordinates":[89.2891,29.2842],"type":"Point"}
}