{
  "type": "Feature",
  "properties": {
    "gn:admin1_code":"5.0",
    "gn:asciiname":"Shangdaziying",
    "gn:country_code":"CN",
    "gn:dem":205,
    "gn:feature_class":"P",
    "gn:feature_code":"PPL",
    "gn:name":"Shangdaziying",
    "gn:population":0,
    "gn:timezone":"Asia/Shanghai",
    "iso:country":"CN",
    "name:zho_x_preferred":[
        "\u4e0a\u8fbe\u5b50\u8425"
    ],
    "wof:name":"Shangdaziying",
    "wof:placetype":"locality"
},
  "geometry": {"coordinates":[125.83902,44.72766],"type":"Point"}
}