{
  "type": "Feature",
  "properties": {
    "gn:admin1_code":"30",
    "gn:asciiname":"Yingli",
    "gn:country_code":"CN",
    "gn:dem":527,
    "gn:feature_class":"P",
    "gn:feature_code":"PPL",
    "gn:name":"Yingli",
    "gn:population":0,
    "gn:timezone":"Asia/Shanghai",
    "iso:country":"CN",
    "name:zho_x_preferred":[
        "\u8425\u91cc"
    ],
    "wof:name":"Yingli",
    "wof:placetype":"locality"
},
  "geometry": {"coordinates":[115.45995000000001,23.4084],"type":"Point"}
}