{
  "type": "Feature",
  "properties": {
    "gn:admin1_code":"30",
    "gn:asciiname":"Yingli",
    "gn:country_code":"CN",
    "gn:dem":527,
    "gn:feature_class":"P",
    "gn:feature_code":"PPL",
    "gn:name":"Yingli",
    "gn:population":0,
    "gn:timezone":"Asia/Shanghai",
    "iso:country":"CN",
    "name:fin_x_preferred":[
        "Yingli"
    ],
    "name:fra_x_preferred":[
        "Yingli"
    ],
    "name:ita_x_preferred":[
        "Yingli"
    ],
    "name:jpn_x_preferred":[
        "\u82f1\u5229\u7dd1\u8272\u80fd\u6e90"
    ],
    "name:rus_x_preferred":[
        "Yingli"
    ],
    "name:spa_x_preferred":[
        "Yingli"
    ],
    "name:zho_x_preferred":[
        "\u8425\u91cc"
    ],
    "name:zho_x_variant":[
        "\u82f1\u5229\u7eff\u8272\u80fd\u6e90\u63a7\u80a1\u6709\u9650\u516c\u53f8"
    ],
    "wof:name":"Yingli",
    "wof:placetype":"locality"
},
  "geometry": {"coordinates":[115.45995000000001,23.4084],"type":"Point"}
}