{
  "type": "Feature",
  "properties": {
    "gn:admin1_code":"14.0",
    "gn:asciiname":"Zhonghu",
    "gn:country_code":"CN",
    "gn:dem":3531,
    "gn:feature_class":"P",
    "gn:feature_code":"PPL",
    "gn:name":"Zhonghu",
    "gn:population":0,
    "gn:timezone":"Asia/Urumqi",
    "iso:country":"CN",
    "name:zho_x_preferred":[
        "\u949f\u4e92"
    ],
    "wof:name":"Zhonghu",
    "wof:placetype":"locality"
},
  "geometry": {"coordinates":[95.13175,31.16746],"type":"Point"}
}