{
  "type": "Feature",
  "properties": {
    "gn:admin1_code":"3.0",
    "gn:asciiname":"Chuntang",
    "gn:country_code":"CN",
    "gn:dem":166,
    "gn:feature_class":"P",
    "gn:feature_code":"PPL",
    "gn:name":"Chuntang",
    "gn:population":0,
    "gn:timezone":"Asia/Shanghai",
    "iso:country":"CN",
    "name:und_x_variant":[
        "\u7eaf\u5858"
    ],
    "wof:name":"Chuntang",
    "wof:placetype":"locality"
},
  "geometry": {"coordinates":[115.66612000000001,26.03111],"type":"Point"}
}