{
  "type": "Feature",
  "properties": {
    "gn:admin1_code":"24",
    "gn:asciiname":"Haojiaping",
    "gn:country_code":"CN",
    "gn:dem":1398,
    "gn:feature_class":"P",
    "gn:feature_code":"PPL",
    "gn:name":"Haojiaping",
    "gn:population":0,
    "gn:timezone":"Asia/Shanghai",
    "iso:country":"CN",
    "name:und_x_variant":[
        "Ho-chia-p\u2019ing",
        "Hao-chia-p\u2019ing",
        "Haojiaping",
        "\u90dd\u5bb6\u576a"
    ],
    "wof:name":"Haojiaping",
    "wof:placetype":"locality"
},
  "geometry": {"coordinates":[112.91898999999999,39.83234],"type":"Point"}
}