{
  "type": "Feature",
  "properties": {
    "gn:admin1_code":"4.0",
    "gn:asciiname":"Hetang",
    "gn:country_code":"CN",
    "gn:dem":6,
    "gn:feature_class":"P",
    "gn:feature_code":"PPL",
    "gn:name":"Hetang",
    "gn:population":0,
    "gn:timezone":"Asia/Shanghai",
    "iso:country":"CN",
    "name:zho_x_preferred":[
        "Hetang"
    ],
    "name:zho_x_variant":[
        "\u6cb3\u5858"
    ],
    "wof:name":"Hetang",
    "wof:placetype":"locality"
},
  "geometry": {"coordinates":[121.40403999999999,32.06607],"type":"Point"}
}