{
  "type": "Feature",
  "properties": {
    "gn:admin1_code":"32",
    "gn:asciiname":"Guojia Cunjie",
    "gn:country_code":"CN",
    "gn:dem":817,
    "gn:feature_class":"P",
    "gn:feature_code":"PPL",
    "gn:name":"Guojia Cunjie",
    "gn:population":0,
    "gn:timezone":"Asia/Shanghai",
    "iso:country":"CN",
    "name:zho_x_preferred":[
        "\u90ed\u5bb6\u6751\u8857"
    ],
    "wof:name":"Guojia Cunjie",
    "wof:placetype":"locality"
},
  "geometry": {"coordinates":[105.46946,32.24789000000001],"type":"Point"}
}