{
  "type": "Feature",
  "properties": {
    "gn:admin1_code":"29",
    "gn:asciiname":"Nanxi",
    "gn:cc2":"CN",
    "gn:country_code":"CN",
    "gn:dem":110,
    "gn:feature_class":"P",
    "gn:feature_code":"PPL",
    "gn:name":"Nanxi",
    "gn:population":0,
    "gn:timezone":"Asia/Shanghai",
    "iso:country":"CN",
    "name:ceb_x_preferred":[
        "Nan Xi"
    ],
    "name:ces_x_preferred":[
        "Nan-si"
    ],
    "name:deu_x_preferred":[
        "Nanxi"
    ],
    "name:fra_x_preferred":[
        "Nanxi"
    ],
    "name:kor_x_preferred":[
        "\ub09c\uc2dc"
    ],
    "name:nor_x_preferred":[
        "Nanxi"
    ],
    "name:swe_x_preferred":[
        "Nan Xi"
    ],
    "name:und_x_variant":[
        "Nan-ch\u2019i-chieh"
    ],
    "wof:name":"Nanxi",
    "wof:placetype":"locality"
},
  "geometry": {"coordinates":[103.93277999999999,22.64028],"type":"Point"}
}