{
  "type": "Feature",
  "properties": {
    "gn:admin1_code":"29",
    "gn:asciiname":"Nanxi",
    "gn:cc2":"CN",
    "gn:country_code":"CN",
    "gn:dem":110,
    "gn:feature_class":"P",
    "gn:feature_code":"PPL",
    "gn:name":"Nanxi",
    "gn:population":0,
    "gn:timezone":"Asia/Shanghai",
    "iso:country":"CN",
    "name:und_x_variant":[
        "Nan-ch\u2019i-chieh",
        "Nanxi"
    ],
    "wof:name":"Nanxi",
    "wof:placetype":"locality"
},
  "geometry": {"coordinates":[103.93277999999999,22.64028],"type":"Point"}
}