{
  "type": "Feature",
  "properties": {
    "gn:admin1_code":"29.0",
    "gn:asciiname":"Liziyuan",
    "gn:country_code":"CN",
    "gn:dem":2083,
    "gn:feature_class":"P",
    "gn:feature_code":"PPL",
    "gn:name":"Liziyuan",
    "gn:population":0,
    "gn:timezone":"Asia/Shanghai",
    "iso:country":"CN",
    "name:zho_x_preferred":[
        "\u6817\u5b50\u56ed"
    ],
    "wof:name":"Liziyuan",
    "wof:placetype":"locality"
},
  "geometry": {"coordinates":[100.623,25.2499],"type":"Point"}
}