{
  "type": "Feature",
  "properties": {
    "gn:admin1_code":"3.0",
    "gn:asciiname":"Le'an Xian Damatou Zonghe Kenzhichang",
    "gn:country_code":"CN",
    "gn:dem":131,
    "gn:feature_class":"P",
    "gn:feature_code":"PPLF",
    "gn:name":"Le\u2019an Xian Damatou Zonghe Kenzhichang",
    "gn:population":0,
    "gn:timezone":"Asia/Shanghai",
    "iso:country":"CN",
    "name:und_x_variant":[
        "Le\u2019an Xian Damatou Zonghe Kenzhichang",
        "\u4e50\u5b89\u53bf\u5927\u9a6c\u5934\u7efc\u5408\u57a6\u6b96\u573a"
    ],
    "wof:name":"Le'an Xian Damatou Zonghe Kenzhichang",
    "wof:placetype":"locality"
},
  "geometry": {"coordinates":[115.74178999999999,27.40234],"type":"Point"}
}