{
  "type": "Feature",
  "properties": {
    "gn:admin1_code":"29.0",
    "gn:asciiname":"Laobaizhai",
    "gn:country_code":"CN",
    "gn:dem":1350,
    "gn:feature_class":"P",
    "gn:feature_code":"PPL",
    "gn:name":"Laobaizhai",
    "gn:population":0,
    "gn:timezone":"Asia/Shanghai",
    "iso:country":"CN",
    "name:zho_x_preferred":[
        "\u8001\u767d\u5be8"
    ],
    "wof:name":"Laobaizhai",
    "wof:placetype":"locality"
},
  "geometry": {"coordinates":[101.22199999999999,22.923],"type":"Point"}
}