{
  "type": "Feature",
  "properties": {
    "gn:admin1_code":"30.0",
    "gn:asciiname":"Zhubeidong",
    "gn:country_code":"CN",
    "gn:dem":114,
    "gn:feature_class":"P",
    "gn:feature_code":"PPL",
    "gn:name":"Zhubeidong",
    "gn:population":0,
    "gn:timezone":"Asia/Shanghai",
    "iso:country":"CN",
    "name:zho_x_preferred":[
        "Zhubeidong"
    ],
    "name:zho_x_variant":[
        "\u6731\u9642\u578c"
    ],
    "wof:name":"Zhubeidong",
    "wof:placetype":"locality"
},
  "geometry": {"coordinates":[112.57306,24.20778],"type":"Point"}
}