{
  "type": "Feature",
  "properties": {
    "gn:admin1_code":"24.0",
    "gn:asciiname":"Hounangou",
    "gn:country_code":"CN",
    "gn:dem":1204,
    "gn:feature_class":"P",
    "gn:feature_code":"PPL",
    "gn:name":"Hounangou",
    "gn:population":0,
    "gn:timezone":"Asia/Shanghai",
    "iso:country":"CN",
    "name:und_x_variant":[
        "\u540e\u5357\u6c9f"
    ],
    "wof:name":"Hounangou",
    "wof:placetype":"locality"
},
  "geometry": {"coordinates":[112.44673,39.43436],"type":"Point"}
}