{
  "type": "Feature",
  "properties": {
    "gn:admin1_code":"11.0",
    "gn:asciiname":"Huilongshan",
    "gn:country_code":"CN",
    "gn:dem":56,
    "gn:feature_class":"P",
    "gn:feature_code":"PPL",
    "gn:name":"Huilongshan",
    "gn:population":0,
    "gn:timezone":"Asia/Shanghai",
    "iso:country":"CN",
    "name:zho_x_preferred":[
        "\u4f1a\u9f99\u5c71"
    ],
    "wof:name":"Huilongshan",
    "wof:placetype":"locality"
},
  "geometry": {"coordinates":[112.31364000000001,28.57495],"type":"Point"}
}