{
  "type": "Feature",
  "properties": {
    "gn:admin1_code":"29.0",
    "gn:asciiname":"Dudidubo",
    "gn:country_code":"CN",
    "gn:dem":1757,
    "gn:feature_class":"P",
    "gn:feature_code":"PPL",
    "gn:name":"Dudidubo",
    "gn:population":0,
    "gn:timezone":"Asia/Shanghai",
    "iso:country":"CN",
    "name:zho_x_preferred":[
        "\u72ec\u5e95\u72ec\u535a"
    ],
    "wof:name":"Dudidubo",
    "wof:placetype":"locality"
},
  "geometry": {"coordinates":[101.42700000000001,25.8909],"type":"Point"}
}