{
  "type": "Feature",
  "properties": {
    "gn:admin1_code":"26.0",
    "gn:asciiname":"Chejiashan",
    "gn:country_code":"CN",
    "gn:dem":1306,
    "gn:feature_class":"P",
    "gn:feature_code":"PPL",
    "gn:name":"Chejiashan",
    "gn:population":0,
    "gn:timezone":"Asia/Shanghai",
    "iso:country":"CN",
    "name:und_x_variant":[
        "\u8f66\u5bb6\u5c71"
    ],
    "wof:name":"Chejiashan",
    "wof:placetype":"locality"
},
  "geometry": {"coordinates":[107.18831000000002,34.86143],"type":"Point"}
}