{
  "type": "Feature",
  "properties": {
    "gn:admin1_code":"13",
    "gn:asciiname":"Xiakale",
    "gn:country_code":"CN",
    "gn:dem":1043,
    "gn:feature_class":"P",
    "gn:feature_code":"PPL",
    "gn:name":"Xiakale",
    "gn:population":0,
    "gn:timezone":"Asia/Shanghai",
    "iso:country":"CN",
    "name:und_x_variant":[
        "\u590f\u5580\u52d2"
    ],
    "wof:name":"Xiakale",
    "wof:placetype":"locality"
},
  "geometry": {"coordinates":[80.53081999999998,40.67681],"type":"Point"}
}