{
  "type": "Feature",
  "properties": {
    "gn:admin1_code":"24.0",
    "gn:asciiname":"Jiantou",
    "gn:country_code":"CN",
    "gn:dem":1277,
    "gn:feature_class":"P",
    "gn:feature_code":"PPL",
    "gn:name":"Jiantou",
    "gn:population":0,
    "gn:timezone":"Asia/Shanghai",
    "iso:country":"CN",
    "name:zho_x_preferred":[
        "\u6da7\u5934"
    ],
    "wof:name":"Jiantou",
    "wof:placetype":"locality"
},
  "geometry": {"coordinates":[113.84187,39.32947],"type":"Point"}
}