{
  "type": "Feature",
  "properties": {
    "gn:admin1_code":"3",
    "gn:asciiname":"Wangbudian",
    "gn:country_code":"CN",
    "gn:dem":98,
    "gn:feature_class":"P",
    "gn:feature_code":"PPL",
    "gn:name":"Wangbudian",
    "gn:population":0,
    "gn:timezone":"Asia/Shanghai",
    "iso:country":"CN",
    "name:zho_x_preferred":[
        "\u7f51\u57e0\u5e97"
    ],
    "wof:name":"Wangbudian",
    "wof:placetype":"locality"
},
  "geometry": {"coordinates":[114.55500000000001,26.3564],"type":"Point"}
}