{
  "type": "Feature",
  "properties": {
    "gn:admin1_code":"13.0",
    "gn:asciiname":"Serigate",
    "gn:country_code":"CN",
    "gn:dem":3517,
    "gn:feature_class":"P",
    "gn:feature_code":"PPL",
    "gn:name":"Serigate",
    "gn:population":0,
    "gn:timezone":"Asia/Shanghai",
    "iso:country":"CN",
    "name:zho_x_preferred":[
        "\u8272\u65e5\u5c15\u7279"
    ],
    "wof:name":"Serigate",
    "wof:placetype":"locality"
},
  "geometry": {"coordinates":[77.76260000000001,36.91249000000001],"type":"Point"}
}