{
  "type": "Feature",
  "properties": {
    "gn:admin1_code":"26.0",
    "gn:asciiname":"Donggedu",
    "gn:country_code":"CN",
    "gn:dem":1301,
    "gn:feature_class":"P",
    "gn:feature_code":"PPL",
    "gn:name":"Donggedu",
    "gn:population":0,
    "gn:timezone":"Asia/Shanghai",
    "iso:country":"CN",
    "name:zho_x_preferred":[
        "\u4e1c\u572a\u5835"
    ],
    "wof:name":"Donggedu",
    "wof:placetype":"locality"
},
  "geometry": {"coordinates":[110.181,38.96682],"type":"Point"}
}