{
  "type": "Feature",
  "properties": {
    "gn:admin1_code":"4.0",
    "gn:asciiname":"Xingou",
    "gn:cc2":"CN",
    "gn:country_code":"CN",
    "gn:dem":-2,
    "gn:feature_class":"P",
    "gn:feature_code":"PPL",
    "gn:name":"Xingou",
    "gn:population":0,
    "gn:timezone":"Asia/Shanghai",
    "iso:country":"CN",
    "name:und_x_variant":[
        "Hsin-kou",
        "Xingou"
    ],
    "wof:name":"Xingou",
    "wof:placetype":"locality"
},
  "geometry": {"coordinates":[119.71666999999999,33.76667],"type":"Point"}
}