{
  "type": "Feature",
  "properties": {
    "gn:admin1_code":"24.0",
    "gn:asciiname":"Dongwa",
    "gn:country_code":"CN",
    "gn:dem":1454,
    "gn:feature_class":"P",
    "gn:feature_code":"PPL",
    "gn:name":"Dongwa",
    "gn:population":0,
    "gn:timezone":"Asia/Shanghai",
    "iso:country":"CN",
    "name:zho_x_preferred":[
        "\u4e1c\u6d3c"
    ],
    "wof:name":"Dongwa",
    "wof:placetype":"locality"
},
  "geometry": {"coordinates":[111.95126,38.09172],"type":"Point"}
}