{
  "type": "Feature",
  "properties": {
    "gn:admin1_code":"1.0",
    "gn:asciiname":"Xinglongsicun",
    "gn:country_code":"CN",
    "gn:dem":31,
    "gn:feature_class":"P",
    "gn:feature_code":"PPL",
    "gn:name":"Xinglongsicun",
    "gn:population":0,
    "gn:timezone":"Asia/Shanghai",
    "iso:country":"CN",
    "name:zho_x_preferred":[
        "\u5174\u9f99\u5bfa\u6751"
    ],
    "wof:name":"Xinglongsicun",
    "wof:placetype":"locality"
},
  "geometry": {"coordinates":[115.73211999999999,32.97114000000001],"type":"Point"}
}