{
  "type": "Feature",
  "properties": {
    "gn:admin1_code":"32.0",
    "gn:asciiname":"Damakou",
    "gn:country_code":"CN",
    "gn:dem":388,
    "gn:feature_class":"P",
    "gn:feature_code":"PPL",
    "gn:name":"Damakou",
    "gn:population":0,
    "gn:timezone":"Asia/Shanghai",
    "iso:country":"CN",
    "name:zho_x_preferred":[
        "\u5927\u9a6c\u53e3"
    ],
    "wof:name":"Damakou",
    "wof:placetype":"locality"
},
  "geometry": {"coordinates":[105.117,30.4938],"type":"Point"}
}