{
  "type": "Feature",
  "properties": {
    "gn:admin1_code":"19.0",
    "gn:asciiname":"Xiaofangshen",
    "gn:country_code":"CN",
    "gn:dem":15,
    "gn:feature_class":"P",
    "gn:feature_code":"PPL",
    "gn:name":"Xiaofangshen",
    "gn:population":0,
    "gn:timezone":"Asia/Shanghai",
    "iso:country":"CN",
    "name:und_x_variant":[
        "\u5c0f\u623f\u8eab"
    ],
    "wof:name":"Xiaofangshen",
    "wof:placetype":"locality"
},
  "geometry": {"coordinates":[122.23864,40.33928],"type":"Point"}
}