{
  "type": "Feature",
  "properties": {
    "gn:admin1_code":"19.0",
    "gn:asciiname":"Gengjiawazi",
    "gn:country_code":"CN",
    "gn:dem":303,
    "gn:feature_class":"P",
    "gn:feature_code":"PPL",
    "gn:name":"Gengjiawazi",
    "gn:population":0,
    "gn:timezone":"Asia/Shanghai",
    "iso:country":"CN",
    "name:zho_x_preferred":[
        "\u803f\u5bb6\u6d3c\u5b50"
    ],
    "wof:name":"Gengjiawazi",
    "wof:placetype":"locality"
},
  "geometry": {"coordinates":[121.619,42.3582],"type":"Point"}
}