{
  "type": "Feature",
  "properties": {
    "gn:admin1_code":"24.0",
    "gn:asciiname":"Shangniuhai",
    "gn:country_code":"CN",
    "gn:dem":1294,
    "gn:feature_class":"P",
    "gn:feature_code":"PPL",
    "gn:name":"Shangniuhai",
    "gn:population":0,
    "gn:timezone":"Asia/Shanghai",
    "iso:country":"CN",
    "name:und_x_variant":[
        "\u4e0a\u725b\u8fd8"
    ],
    "name:zho_x_preferred":[
        "\u4e0a\u725b\u8fd8"
    ],
    "wof:name":"Shangniuhai",
    "wof:placetype":"locality"
},
  "geometry": {"coordinates":[113.89062,39.39126],"type":"Point"}
}