{
  "type": "Feature",
  "properties": {
    "gn:admin1_code":"32.0",
    "gn:asciiname":"Yiqugou",
    "gn:country_code":"CN",
    "gn:dem":2906,
    "gn:feature_class":"P",
    "gn:feature_code":"PPL",
    "gn:name":"Yiqugou",
    "gn:population":0,
    "gn:timezone":"Asia/Shanghai",
    "iso:country":"CN",
    "name:zho_x_preferred":[
        "\u5f5d\u6e20\u6c9f"
    ],
    "wof:name":"Yiqugou",
    "wof:placetype":"locality"
},
  "geometry": {"coordinates":[102.398,28.1807],"type":"Point"}
}