{
  "type": "Feature",
  "properties": {
    "gn:admin1_code":"15.0",
    "gn:asciiname":"Shangchoushui Yangquan",
    "gn:country_code":"CN",
    "gn:dem":3054,
    "gn:feature_class":"P",
    "gn:feature_code":"PPLF",
    "gn:name":"Shangchoushui Yangquan",
    "gn:population":0,
    "gn:timezone":"Asia/Shanghai",
    "iso:country":"CN",
    "name:zho_x_preferred":[
        "\u4e0a\u81ed\u6c34\u7f8a\u5708"
    ],
    "wof:name":"Shangchoushui Yangquan",
    "wof:placetype":"locality"
},
  "geometry": {"coordinates":[98.2894,39.4661],"type":"Point"}
}