{
  "type": "Feature",
  "properties": {
    "gn:admin1_code":"4.0",
    "gn:asciiname":"Houheqiao",
    "gn:country_code":"CN",
    "gn:dem":1,
    "gn:feature_class":"P",
    "gn:feature_code":"PPL",
    "gn:name":"Houheqiao",
    "gn:population":0,
    "gn:timezone":"Asia/Shanghai",
    "iso:country":"CN",
    "name:zho_x_preferred":[
        "Houheqiao"
    ],
    "name:zho_x_variant":[
        "\u540e\u4f55\u6865"
    ],
    "wof:name":"Houheqiao",
    "wof:placetype":"locality"
},
  "geometry": {"coordinates":[119.34208,33.62158],"type":"Point"}
}