{
  "type": "Feature",
  "properties": {
    "gn:admin1_code":"19.0",
    "gn:asciiname":"Helongcun",
    "gn:country_code":"CN",
    "gn:dem":38,
    "gn:feature_class":"P",
    "gn:feature_code":"PPL",
    "gn:name":"Helongcun",
    "gn:population":0,
    "gn:timezone":"Asia/Shanghai",
    "iso:country":"CN",
    "name:zho_x_preferred":[
        "\u5408\u9686\u6751"
    ],
    "wof:name":"Helongcun",
    "wof:placetype":"locality"
},
  "geometry": {"coordinates":[123.98390999999999,40.03026],"type":"Point"}
}