{
  "type": "Feature",
  "properties": {
    "gn:admin1_code":"30",
    "gn:asciiname":"Dongbianlong",
    "gn:country_code":"CN",
    "gn:dem":6,
    "gn:feature_class":"P",
    "gn:feature_code":"PPL",
    "gn:name":"Dongbianlong",
    "gn:population":0,
    "gn:timezone":"Asia/Shanghai",
    "iso:country":"CN",
    "name:zho_x_preferred":[
        "\u4e1c\u8fb9\u9686"
    ],
    "wof:name":"Dongbianlong",
    "wof:placetype":"locality"
},
  "geometry": {"coordinates":[115.03400999999999,22.78719],"type":"Point"}
}