{
  "type": "Feature",
  "properties": {
    "gn:admin1_code":"30",
    "gn:asciiname":"Shuangjiao",
    "gn:country_code":"CN",
    "gn:dem":92,
    "gn:feature_class":"P",
    "gn:feature_code":"PPLA4",
    "gn:name":"Shuangjiao",
    "gn:population":0,
    "gn:timezone":"Asia/Shanghai",
    "iso:country":"CN",
    "name:und_x_variant":[
        "Shuang-chiao",
        "Shuang-chiao-hs\u00fc",
        "Shuangjiao",
        "Shuangjiao Zhen",
        "\u53cc\u7a96\u9547"
    ],
    "name:zho_x_preferred":[
        "\u53cc\u6ed8"
    ],
    "wof:name":"Shuangjiao",
    "wof:placetype":"locality"
},
  "geometry": {"coordinates":[111.35908000000001,22.09874],"type":"Point"}
}