{
  "type": "Feature",
  "properties": {
    "gn:admin1_code":"19.0",
    "gn:asciiname":"Zhujia Tuozi",
    "gn:country_code":"CN",
    "gn:dem":87,
    "gn:feature_class":"P",
    "gn:feature_code":"PPL",
    "gn:name":"Zhujia Tuozi",
    "gn:population":0,
    "gn:timezone":"Asia/Shanghai",
    "iso:country":"CN",
    "name:zho_x_preferred":[
        "\u6731\u5bb6\u5768\u5b50"
    ],
    "wof:name":"Zhujia Tuozi",
    "wof:placetype":"locality"
},
  "geometry": {"coordinates":[123.568,42.8862],"type":"Point"}
}