{
  "type": "Feature",
  "properties": {
    "gn:admin1_code":"32.0",
    "gn:asciiname":"Shigaopu",
    "gn:country_code":"CN",
    "gn:dem":461,
    "gn:feature_class":"P",
    "gn:feature_code":"PPL",
    "gn:name":"Shigaopu",
    "gn:population":0,
    "gn:timezone":"Asia/Shanghai",
    "iso:country":"CN",
    "name:zho_x_preferred":[
        "\u89c6\u9ad8\u94fa"
    ],
    "wof:name":"Shigaopu",
    "wof:placetype":"locality"
},
  "geometry": {"coordinates":[104.05629999999999,30.2461],"type":"Point"}
}