{
  "type": "Feature",
  "properties": {
    "gn:admin1_code":"30",
    "gn:asciiname":"Guanxianshi",
    "gn:country_code":"CN",
    "gn:dem":27,
    "gn:feature_class":"P",
    "gn:feature_code":"PPL",
    "gn:name":"Guanxianshi",
    "gn:population":0,
    "gn:timezone":"Asia/Urumqi",
    "iso:country":"CN",
    "name:und_x_variant":[
        "Guanxianwei",
        "Guanxianshi"
    ],
    "name:zho_x_preferred":[
        "\u5b98\u8d24\u5e02"
    ],
    "wof:name":"Guanxianshi",
    "wof:placetype":"locality"
},
  "geometry": {"coordinates":[110.26339,20.81269],"type":"Point"}
}