{
  "type": "Feature",
  "properties": {
    "gn:admin1_code":"2.0",
    "gn:asciiname":"Mojia Liangting",
    "gn:country_code":"CN",
    "gn:dem":8,
    "gn:feature_class":"P",
    "gn:feature_code":"PPL",
    "gn:name":"Mojia Liangting",
    "gn:population":0,
    "gn:timezone":"Asia/Shanghai",
    "iso:country":"CN",
    "name:und_x_variant":[
        "\u83ab\u5bb6\u51c9\u4ead"
    ],
    "wof:name":"Mojia Liangting",
    "wof:placetype":"locality"
},
  "geometry": {"coordinates":[119.69973,30.80309],"type":"Point"}
}