{
  "type": "Feature",
  "properties": {
    "gn:admin1_code":"29.0",
    "gn:asciiname":"Daliandi",
    "gn:country_code":"CN",
    "gn:dem":1977,
    "gn:feature_class":"P",
    "gn:feature_code":"PPL",
    "gn:name":"Daliandi",
    "gn:population":0,
    "gn:timezone":"Asia/Shanghai",
    "iso:country":"CN",
    "name:zho_x_preferred":[
        "\u8fbe\u8fde\u5730"
    ],
    "wof:name":"Daliandi",
    "wof:placetype":"locality"
},
  "geometry": {"coordinates":[103.518,25.7765],"type":"Point"}
}