{
  "type": "Feature",
  "properties": {
    "gn:admin1_code":"16.0",
    "gn:asciiname":"Dahao",
    "gn:country_code":"CN",
    "gn:dem":122,
    "gn:feature_class":"P",
    "gn:feature_code":"PPL",
    "gn:name":"Dahao",
    "gn:population":0,
    "gn:timezone":"Asia/Shanghai",
    "iso:country":"CN",
    "name:fas_x_preferred":[
        "\u062f\u0627\u0647\u0627\u0648"
    ],
    "name:zho_x_preferred":[
        "\u8fbe\u660a"
    ],
    "wof:name":"Dahao",
    "wof:placetype":"locality"
},
  "geometry": {"coordinates":[109.871,23.5922],"type":"Point"}
}