{
  "type": "Feature",
  "properties": {
    "gn:admin1_code":"14.0",
    "gn:asciiname":"Gedu",
    "gn:country_code":"CN",
    "gn:dem":5105,
    "gn:feature_class":"P",
    "gn:feature_code":"PPL",
    "gn:name":"Gedu",
    "gn:population":0,
    "gn:timezone":"Asia/Urumqi",
    "iso:country":"CN",
    "name:bod_x_preferred":[
        "G\u00eadur"
    ],
    "name:und_x_variant":[
        "Baisha Gongshe"
    ],
    "name:zho_x_preferred":[
        "\u683c\u90fd"
    ],
    "name:zho_x_variant":[
        "\u767d\u6c99\u516c\u793e"
    ],
    "wof:name":"Gedu",
    "wof:placetype":"locality"
},
  "geometry": {"coordinates":[90.501,28.401],"type":"Point"}
}