{
  "type": "Feature",
  "properties": {
    "gn:admin1_code":"26.0",
    "gn:asciiname":"Shuangliuwancun",
    "gn:country_code":"CN",
    "gn:dem":1175,
    "gn:feature_class":"P",
    "gn:feature_code":"PPL",
    "gn:name":"Shuangliuwancun",
    "gn:population":0,
    "gn:timezone":"Asia/Shanghai",
    "iso:country":"CN",
    "name:zho_x_preferred":[
        "\u53cc\u5218\u6e7e\u6751"
    ],
    "wof:name":"Shuangliuwancun",
    "wof:placetype":"locality"
},
  "geometry": {"coordinates":[109.66293,37.0758],"type":"Point"}
}