{
  "type": "Feature",
  "properties": {
    "gn:admin1_code":"4.0",
    "gn:asciiname":"Zhuhang",
    "gn:country_code":"CN",
    "gn:dem":7,
    "gn:feature_class":"P",
    "gn:feature_code":"PPLA4",
    "gn:name":"Zhuhang",
    "gn:population":0,
    "gn:timezone":"Asia/Shanghai",
    "iso:country":"CN",
    "name:und_x_variant":[
        "Chu-hang-chen",
        "Chu-hang",
        "Chu-hsing-chen",
        "Zhuhang",
        "\u7af9\u884c",
        "Zhuhang Zhen"
    ],
    "name:zho_x_preferred":[
        "\u7af9\u884c\u9547"
    ],
    "wof:name":"Zhuhang",
    "wof:placetype":"locality"
},
  "geometry": {"coordinates":[120.98193000000001,31.90005],"type":"Point"}
}