{
  "type": "Feature",
  "properties": {
    "gn:admin1_code":"24.0",
    "gn:asciiname":"Gejiaopo",
    "gn:country_code":"CN",
    "gn:dem":862,
    "gn:feature_class":"P",
    "gn:feature_code":"PPL",
    "gn:name":"Gejiaopo",
    "gn:population":0,
    "gn:timezone":"Asia/Shanghai",
    "iso:country":"CN",
    "name:zho_x_preferred":[
        "\u7599\u811a\u5761"
    ],
    "wof:name":"Gejiaopo",
    "wof:placetype":"locality"
},
  "geometry": {"coordinates":[113.17349,35.46697],"type":"Point"}
}