{
  "type": "Feature",
  "properties": {
    "gn:admin1_code":"14.0",
    "gn:asciiname":"Jiangda",
    "gn:country_code":"CN",
    "gn:dem":4395,
    "gn:feature_class":"P",
    "gn:feature_code":"PPL",
    "gn:name":"Jiangda",
    "gn:population":0,
    "gn:timezone":"Asia/Urumqi",
    "iso:country":"CN",
    "name:zho_x_preferred":[
        "\u6c5f\u8fbe"
    ],
    "wof:name":"Jiangda",
    "wof:placetype":"locality"
},
  "geometry": {"coordinates":[97.48941000000001,30.91975],"type":"Point"}
}