{
  "type": "Feature",
  "properties": {
    "gn:admin1_code":"05",
    "gn:asciiname":"Xilin",
    "gn:cc2":"CN",
    "gn:country_code":"CN",
    "gn:dem":324,
    "gn:feature_class":"P",
    "gn:feature_code":"PPL",
    "gn:name":"Xilin",
    "gn:population":0,
    "gn:timezone":"Asia/Shanghai",
    "iso:country":"CN",
    "name:ceb_x_preferred":[
        "Xilin"
    ],
    "name:deu_x_preferred":[
        "Xilin"
    ],
    "name:fra_x_preferred":[
        "Xilin"
    ],
    "name:nno_x_preferred":[
        "Xilin"
    ],
    "name:nor_x_preferred":[
        "Xilin"
    ],
    "name:rus_x_preferred":[
        "\u0421\u0438\u043b\u0438\u043d\u044c"
    ],
    "name:swe_x_preferred":[
        "Xilin"
    ],
    "name:und_x_variant":[
        "Hsi-lin-ho-t\u2019un"
    ],
    "wof:name":"Xilin",
    "wof:placetype":"locality"
},
  "geometry": {"coordinates":[126.26167,42.84917],"type":"Point"}
}