{
  "type": "Feature",
  "properties": {
    "gn:admin1_code":"10",
    "gn:asciiname":"Hezi",
    "gn:country_code":"CN",
    "gn:dem":1367,
    "gn:feature_class":"P",
    "gn:feature_code":"PPL",
    "gn:name":"Hezi",
    "gn:population":0,
    "gn:timezone":"Asia/Shanghai",
    "iso:country":"CN",
    "name:ukr_x_preferred":[
        "\u0413\u0435\u0437\u0456"
    ],
    "name:zho_x_preferred":[
        "\u6cb3\u5b50"
    ],
    "wof:name":"Hezi",
    "wof:placetype":"locality"
},
  "geometry": {"coordinates":[115.09538000000001,41.5888],"type":"Point"}
}