{
  "type": "Feature",
  "properties": {
    "gn:admin1_code":"3",
    "gn:asciiname":"Shukou",
    "gn:country_code":"CN",
    "gn:dem":65,
    "gn:feature_class":"P",
    "gn:feature_code":"PPL",
    "gn:name":"Shukou",
    "gn:population":0,
    "gn:timezone":"Asia/Shanghai",
    "iso:country":"CN",
    "name:zho_x_preferred":[
        "\u8700\u53e3"
    ],
    "wof:name":"Shukou",
    "wof:placetype":"locality"
},
  "geometry": {"coordinates":[114.81976,26.7498],"type":"Point"}
}