{
  "type": "Feature",
  "properties": {
    "gn:admin1_code":"24.0",
    "gn:asciiname":"Longyuzui",
    "gn:country_code":"CN",
    "gn:dem":1347,
    "gn:feature_class":"P",
    "gn:feature_code":"PPL",
    "gn:name":"Longyuzui",
    "gn:population":0,
    "gn:timezone":"Asia/Shanghai",
    "iso:country":"CN",
    "name:zho_x_preferred":[
        "\u9f99\u7389\u5480"
    ],
    "wof:name":"Longyuzui",
    "wof:placetype":"locality"
},
  "geometry": {"coordinates":[111.50285,38.97923],"type":"Point"}
}