{
  "type": "Feature",
  "properties": {
    "gn:admin1_code":"1.0",
    "gn:asciiname":"Tangyancun",
    "gn:country_code":"CN",
    "gn:dem":28,
    "gn:feature_class":"P",
    "gn:feature_code":"PPL",
    "gn:name":"Tangyancun",
    "gn:population":0,
    "gn:timezone":"Asia/Shanghai",
    "iso:country":"CN",
    "name:zho_x_preferred":[
        "\u5858\u6cbf\u6751"
    ],
    "wof:name":"Tangyancun",
    "wof:placetype":"locality"
},
  "geometry": {"coordinates":[116.52200000000001,32.75137],"type":"Point"}
}