{
  "type": "Feature",
  "properties": {
    "gn:admin1_code":"15.0",
    "gn:asciiname":"Meibaijia",
    "gn:country_code":"CN",
    "gn:dem":1361,
    "gn:feature_class":"P",
    "gn:feature_code":"PPL",
    "gn:name":"Meibaijia",
    "gn:population":0,
    "gn:timezone":"Asia/Shanghai",
    "iso:country":"CN",
    "name:zho_x_preferred":[
        "\u6885\u767d\u5bb6"
    ],
    "wof:name":"Meibaijia",
    "wof:placetype":"locality"
},
  "geometry": {"coordinates":[107.623,35.6266],"type":"Point"}
}