{
  "type": "Feature",
  "properties": {
    "gn:admin1_code":"9.0",
    "gn:asciiname":"Xiangshuihe",
    "gn:country_code":"CN",
    "gn:dem":266,
    "gn:feature_class":"P",
    "gn:feature_code":"PPL",
    "gn:name":"Xiangshuihe",
    "gn:population":0,
    "gn:timezone":"Asia/Shanghai",
    "iso:country":"CN",
    "name:und_x_variant":[
        "\u54cd\u6c34\u6cb3",
        "Xiangshuihe"
    ],
    "wof:name":"Xiangshuihe",
    "wof:placetype":"locality"
},
  "geometry": {"coordinates":[112.08056000000001,33.20030999999999],"type":"Point"}
}