{
  "type": "Feature",
  "properties": {
    "gn:admin1_code":"19.0",
    "gn:asciiname":"Danjiawanzi",
    "gn:country_code":"CN",
    "gn:dem":29,
    "gn:feature_class":"P",
    "gn:feature_code":"PPL",
    "gn:name":"Danjiawanzi",
    "gn:population":0,
    "gn:timezone":"Asia/Shanghai",
    "iso:country":"CN",
    "name:zho_x_preferred":[
        "\u5355\u5bb6\u6e7e\u5b50"
    ],
    "wof:name":"Danjiawanzi",
    "wof:placetype":"locality"
},
  "geometry": {"coordinates":[120.04600000000001,40.1454],"type":"Point"}
}