{
  "type": "Feature",
  "properties": {
    "gn:admin1_code":"11.0",
    "gn:asciiname":"Dahuangtu'ao",
    "gn:country_code":"CN",
    "gn:dem":441,
    "gn:feature_class":"P",
    "gn:feature_code":"PPL",
    "gn:name":"Dahuangtu\u2019ao",
    "gn:population":0,
    "gn:timezone":"Asia/Shanghai",
    "iso:country":"CN",
    "name:und_x_variant":[
        "Dahuangtu\u2019ao"
    ],
    "name:zho_x_preferred":[
        "\u5927\u9ec4\u571f\u5773"
    ],
    "wof:name":"Dahuangtu'ao",
    "wof:placetype":"locality"
},
  "geometry": {"coordinates":[109.58268,28.00567],"type":"Point"}
}