{
  "type": "Feature",
  "properties": {
    "gn:admin1_code":"14.0",
    "gn:asciiname":"Angmuqincun",
    "gn:country_code":"CN",
    "gn:dem":4568,
    "gn:feature_class":"P",
    "gn:feature_code":"PPL",
    "gn:name":"Angmuqincun",
    "gn:population":0,
    "gn:timezone":"Asia/Urumqi",
    "iso:country":"CN",
    "name:zho_x_preferred":[
        "\u6602\u6728\u94a6\u6751"
    ],
    "wof:name":"Angmuqincun",
    "wof:placetype":"locality"
},
  "geometry": {"coordinates":[92.16861,31.33113],"type":"Point"}
}