{
  "type": "Feature",
  "properties": {
    "gn:admin1_code":"5.0",
    "gn:asciiname":"Wendaogou",
    "gn:country_code":"CN",
    "gn:dem":195,
    "gn:feature_class":"P",
    "gn:feature_code":"PPL",
    "gn:name":"Wendaogou",
    "gn:population":0,
    "gn:timezone":"Asia/Shanghai",
    "iso:country":"CN",
    "name:zho_x_preferred":[
        "\u6587\u9053\u6c9f"
    ],
    "wof:name":"Wendaogou",
    "wof:placetype":"locality"
},
  "geometry": {"coordinates":[124.69414,44.39627],"type":"Point"}
}