{
  "type": "Feature",
  "properties": {
    "gn:admin1_code":"30.0",
    "gn:asciiname":"Taoxi",
    "gn:country_code":"CN",
    "gn:dem":207,
    "gn:feature_class":"P",
    "gn:feature_code":"PPL",
    "gn:name":"Taoxi",
    "gn:population":0,
    "gn:timezone":"Asia/Shanghai",
    "iso:country":"CN",
    "name:zho_x_preferred":[
        "Taoxi"
    ],
    "name:zho_x_variant":[
        "\u9676\u9521"
    ],
    "wof:name":"Taoxi",
    "wof:placetype":"locality"
},
  "geometry": {"coordinates":[115.21832999999999,24.64361],"type":"Point"}
}