{
  "type": "Feature",
  "properties": {
    "gn:admin1_code":"24.0",
    "gn:asciiname":"Liugou",
    "gn:country_code":"CN",
    "gn:dem":1648,
    "gn:feature_class":"P",
    "gn:feature_code":"PPL",
    "gn:name":"Liugou",
    "gn:population":0,
    "gn:timezone":"Asia/Shanghai",
    "iso:country":"CN",
    "name:und_x_variant":[
        "\u67f3\u6c9f"
    ],
    "wof:name":"Liugou",
    "wof:placetype":"locality"
},
  "geometry": {"coordinates":[112.09753000000001,39.65308],"type":"Point"}
}