{
  "type": "Feature",
  "properties": {
    "gn:admin1_code":"32.0",
    "gn:asciiname":"Zhinancun",
    "gn:country_code":"CN",
    "gn:dem":388,
    "gn:feature_class":"P",
    "gn:feature_code":"PPL",
    "gn:name":"Zhinancun",
    "gn:population":0,
    "gn:timezone":"Asia/Shanghai",
    "iso:country":"CN",
    "name:zho_x_preferred":[
        "\u6307\u5357\u6751"
    ],
    "wof:name":"Zhinancun",
    "wof:placetype":"locality"
},
  "geometry": {"coordinates":[105.38200000000001,31.2123],"type":"Point"}
}