{
  "type": "Feature",
  "properties": {
    "gn:admin1_code":"7.0",
    "gn:asciiname":"Tanxia",
    "gn:country_code":"CN",
    "gn:dem":17,
    "gn:feature_class":"P",
    "gn:feature_code":"PPL",
    "gn:name":"Tanxia",
    "gn:population":0,
    "gn:timezone":"Asia/Shanghai",
    "iso:country":"CN",
    "name:und_x_variant":[
        "\u6f6d\u4e0b"
    ],
    "name:zho_x_preferred":[
        "Tanxia"
    ],
    "wof:name":"Tanxia",
    "wof:placetype":"locality"
},
  "geometry": {"coordinates":[119.34592000000001,26.10369],"type":"Point"}
}