{
  "type": "Feature",
  "properties": {
    "gn:admin1_code":"26.0",
    "gn:asciiname":"Citang",
    "gn:country_code":"CN",
    "gn:dem":712,
    "gn:feature_class":"P",
    "gn:feature_code":"PPL",
    "gn:name":"Citang",
    "gn:population":0,
    "gn:timezone":"Asia/Shanghai",
    "iso:country":"CN",
    "name:zho_x_preferred":[
        "\u8bcd\u5802"
    ],
    "wof:name":"Citang",
    "wof:placetype":"locality"
},
  "geometry": {"coordinates":[109.42156,32.77648],"type":"Point"}
}