{
  "type": "Feature",
  "properties": {
    "gn:admin1_code":"30",
    "gn:asciiname":"Shanweicun",
    "gn:country_code":"CN",
    "gn:dem":7,
    "gn:feature_class":"P",
    "gn:feature_code":"PPL",
    "gn:name":"Shanweicun",
    "gn:population":0,
    "gn:timezone":"Asia/Urumqi",
    "iso:country":"CN",
    "name:und_x_variant":[
        "Shanwei",
        "Shanweicun"
    ],
    "name:zho_x_preferred":[
        "\u5c71\u5c3e\u6751"
    ],
    "wof:name":"Shanweicun",
    "wof:placetype":"locality"
},
  "geometry": {"coordinates":[110.01810999999999,20.86339],"type":"Point"}
}