{
  "type": "Feature",
  "properties": {
    "gn:admin1_code":"11.0",
    "gn:asciiname":"Tuishanzui",
    "gn:country_code":"CN",
    "gn:dem":33,
    "gn:feature_class":"P",
    "gn:feature_code":"PPL",
    "gn:name":"Tuishanzui",
    "gn:population":0,
    "gn:timezone":"Asia/Shanghai",
    "iso:country":"CN",
    "name:zho_x_preferred":[
        "\u63a8\u5c71\u5480"
    ],
    "wof:name":"Tuishanzui",
    "wof:placetype":"locality"
},
  "geometry": {"coordinates":[112.89485999999999,28.86768],"type":"Point"}
}