{
  "type": "Feature",
  "properties": {
    "gn:admin1_code":"7.0",
    "gn:asciiname":"Baluo",
    "gn:country_code":"CN",
    "gn:dem":704,
    "gn:feature_class":"P",
    "gn:feature_code":"PPL",
    "gn:name":"Baluo",
    "gn:population":0,
    "gn:timezone":"Asia/Shanghai",
    "iso:country":"CN",
    "name:zho_x_preferred":[
        "\u516b\u7ba9"
    ],
    "wof:name":"Baluo",
    "wof:placetype":"locality"
},
  "geometry": {"coordinates":[119.98138,27.36737],"type":"Point"}
}