{
  "type": "Feature",
  "properties": {
    "gn:admin1_code":"9.0",
    "gn:asciiname":"Niuzhuang",
    "gn:country_code":"CN",
    "gn:dem":146,
    "gn:feature_class":"P",
    "gn:feature_code":"PPL",
    "gn:name":"Niuzhuang",
    "gn:population":0,
    "gn:timezone":"Asia/Shanghai",
    "iso:country":"CN",
    "name:und_x_variant":[
        "\u725b\u5e84",
        "Niuzhuang"
    ],
    "wof:name":"Niuzhuang",
    "wof:placetype":"locality"
},
  "geometry": {"coordinates":[112.86494999999999,33.16384],"type":"Point"}
}