{
  "type": "Feature",
  "properties": {
    "gn:admin1_code":"19.0",
    "gn:asciiname":"Shangsijiazi",
    "gn:country_code":"CN",
    "gn:dem":127,
    "gn:feature_class":"P",
    "gn:feature_code":"PPL",
    "gn:name":"Shangsijiazi",
    "gn:population":0,
    "gn:timezone":"Asia/Shanghai",
    "iso:country":"CN",
    "name:zho_x_preferred":[
        "\u4e0a\u56db\u5bb6\u5b50"
    ],
    "wof:name":"Shangsijiazi",
    "wof:placetype":"locality"
},
  "geometry": {"coordinates":[123.881,42.8568],"type":"Point"}
}