{
  "type": "Feature",
  "properties": {
    "gn:admin1_code":"20.0",
    "gn:asciiname":"Ronghuahexi Erdui",
    "gn:country_code":"CN",
    "gn:dem":266,
    "gn:feature_class":"P",
    "gn:feature_code":"PPLF",
    "gn:name":"Ronghuahexi Erdui",
    "gn:population":0,
    "gn:timezone":"Asia/Shanghai",
    "iso:country":"CN",
    "name:zho_x_preferred":[
        "\u8363\u82b1\u6cb3\u897f\u4e8c\u961f"
    ],
    "wof:name":"Ronghuahexi Erdui",
    "wof:placetype":"locality"
},
  "geometry": {"coordinates":[123.30557,48.28167],"type":"Point"}
}