{
  "type": "Feature",
  "properties": {
    "gn:admin1_code":"6.0",
    "gn:asciiname":"Jianshe",
    "gn:country_code":"CN",
    "gn:dem":4106,
    "gn:feature_class":"P",
    "gn:feature_code":"PPLA4",
    "gn:name":"Jianshe",
    "gn:population":0,
    "gn:timezone":"Asia/Shanghai",
    "iso:country":"CN",
    "name:ceb_x_preferred":[
        "Jianshe"
    ],
    "name:deu_x_preferred":[
        "Jianshe"
    ],
    "name:swe_x_preferred":[
        "Jianshe"
    ],
    "name:und_x_variant":[
        "Ciwada",
        "Jianshe Xiang"
    ],
    "name:zho_x_preferred":[
        "\u5efa\u8bbe"
    ],
    "name:zho_x_variant":[
        "\u6b21\u54c7\u8fbe",
        "\u5efa\u8bbe\u4e61"
    ],
    "wof:name":"Jianshe",
    "wof:placetype":"locality"
},
  "geometry": {"coordinates":[99.40000000000001,33.68333],"type":"Point"}
}