{
  "type": "Feature",
  "properties": {
    "gn:admin1_code":"10",
    "gn:asciiname":"Dadong",
    "gn:country_code":"CN",
    "gn:dem":9,
    "gn:feature_class":"P",
    "gn:feature_code":"PPL",
    "gn:name":"Dadong",
    "gn:population":0,
    "gn:timezone":"Asia/Shanghai",
    "iso:country":"CN",
    "name:zho_x_preferred":[
        "\u5927\u8463"
    ],
    "wof:name":"Dadong",
    "wof:placetype":"locality"
},
  "geometry": {"coordinates":[116.441,38.8119],"type":"Point"}
}