{
  "type": "Feature",
  "properties": {
    "gn:admin1_code":"2.0",
    "gn:asciiname":"Baishuyuan",
    "gn:country_code":"CN",
    "gn:dem":689,
    "gn:feature_class":"P",
    "gn:feature_code":"PPL",
    "gn:name":"Baishuyuan",
    "gn:population":0,
    "gn:timezone":"Asia/Shanghai",
    "iso:country":"CN",
    "name:zho_x_preferred":[
        "\u767d\u672f\u56ed"
    ],
    "wof:name":"Baishuyuan",
    "wof:placetype":"locality"
},
  "geometry": {"coordinates":[120.56238999999999,29.51591],"type":"Point"}
}