{
  "type": "Feature",
  "properties": {
    "gn:admin1_code":"26.0",
    "gn:asciiname":"Xiaotiangou",
    "gn:country_code":"CN",
    "gn:dem":1155,
    "gn:feature_class":"P",
    "gn:feature_code":"PPL",
    "gn:name":"Xiaotiangou",
    "gn:population":0,
    "gn:timezone":"Asia/Shanghai",
    "iso:country":"CN",
    "name:und_x_variant":[
        "\u5c0f\u7530\u6c9f"
    ],
    "wof:name":"Xiaotiangou",
    "wof:placetype":"locality"
},
  "geometry": {"coordinates":[106.20329,33.47008],"type":"Point"}
}