{
  "type": "Feature",
  "properties": {
    "gn:admin1_code":"29.0",
    "gn:asciiname":"Mudengdong",
    "gn:country_code":"CN",
    "gn:dem":2315,
    "gn:feature_class":"P",
    "gn:feature_code":"PPL",
    "gn:name":"Mudengdong",
    "gn:population":0,
    "gn:timezone":"Asia/Shanghai",
    "iso:country":"CN",
    "name:zho_x_preferred":[
        "\u6728\u767b\u6d1e"
    ],
    "wof:name":"Mudengdong",
    "wof:placetype":"locality"
},
  "geometry": {"coordinates":[103.172,23.2985],"type":"Point"}
}