{
  "type": "Feature",
  "properties": {
    "gn:admin1_code":"4.0",
    "gn:asciiname":"Zhaojiadai",
    "gn:country_code":"CN",
    "gn:dem":7,
    "gn:feature_class":"P",
    "gn:feature_code":"PPL",
    "gn:name":"Zhaojiadai",
    "gn:population":0,
    "gn:timezone":"Asia/Shanghai",
    "iso:country":"CN",
    "name:zho_x_preferred":[
        "Zhaojiadai"
    ],
    "name:zho_x_variant":[
        "\u8d75\u5bb6\u5788"
    ],
    "wof:name":"Zhaojiadai",
    "wof:placetype":"locality"
},
  "geometry": {"coordinates":[121.02209999999999,32.42926],"type":"Point"}
}