{
  "type": "Feature",
  "properties": {
    "gn:admin1_code":"13",
    "gn:asciiname":"Yujimai Airike",
    "gn:country_code":"CN",
    "gn:dem":1272,
    "gn:feature_class":"P",
    "gn:feature_code":"PPL",
    "gn:name":"Yujimai Airike",
    "gn:population":0,
    "gn:timezone":"Asia/Shanghai",
    "iso:country":"CN",
    "name:und_x_variant":[
        "\u7389\u5409\u4e70\u827e\u65e5\u514b"
    ],
    "wof:name":"Yujimai Airike",
    "wof:placetype":"locality"
},
  "geometry": {"coordinates":[77.28171,38.19866],"type":"Point"}
}