{
  "type": "Feature",
  "properties": {
    "gn:admin1_code":"30",
    "gn:asciiname":"Jinzhuyuan",
    "gn:country_code":"CN",
    "gn:dem":626,
    "gn:feature_class":"P",
    "gn:feature_code":"PPL",
    "gn:name":"Jinzhuyuan",
    "gn:population":0,
    "gn:timezone":"Asia/Shanghai",
    "iso:country":"CN",
    "name:und_x_variant":[
        "\u91d1\u7af9\u56ed"
    ],
    "wof:name":"Jinzhuyuan",
    "wof:placetype":"locality"
},
  "geometry": {"coordinates":[113.994,24.0556],"type":"Point"}
}