{
  "type": "Feature",
  "properties": {
    "gn:admin1_code":"16.0",
    "gn:asciiname":"Meng'e",
    "gn:country_code":"CN",
    "gn:dem":758,
    "gn:feature_class":"P",
    "gn:feature_code":"PPL",
    "gn:name":"Meng\u2019e",
    "gn:population":0,
    "gn:timezone":"Asia/Shanghai",
    "iso:country":"CN",
    "name:und_x_variant":[
        "Meng\u2019e"
    ],
    "name:zho_x_preferred":[
        "\u731b\u5ce8"
    ],
    "wof:name":"Meng'e",
    "wof:placetype":"locality"
},
  "geometry": {"coordinates":[106.95399999999999,24.4172],"type":"Point"}
}