{
  "type": "Feature",
  "properties": {
    "gn:admin1_code":"30",
    "gn:asciiname":"Shangyingzi",
    "gn:country_code":"CN",
    "gn:dem":387,
    "gn:feature_class":"P",
    "gn:feature_code":"PPL",
    "gn:name":"Shangyingzi",
    "gn:population":0,
    "gn:timezone":"Asia/Shanghai",
    "iso:country":"CN",
    "name:zho_x_preferred":[
        "\u4e0a\u8425\u5b50"
    ],
    "wof:name":"Shangyingzi",
    "wof:placetype":"locality"
},
  "geometry": {"coordinates":[115.80761,24.63398],"type":"Point"}
}