{
  "type": "Feature",
  "properties": {
    "gn:admin1_code":"29.0",
    "gn:asciiname":"Heiyudong",
    "gn:country_code":"CN",
    "gn:dem":1638,
    "gn:feature_class":"P",
    "gn:feature_code":"PPL",
    "gn:name":"Heiyudong",
    "gn:population":0,
    "gn:timezone":"Asia/Shanghai",
    "iso:country":"CN",
    "name:zho_x_preferred":[
        "\u9ed1\u9c7c\u6d1e"
    ],
    "wof:name":"Heiyudong",
    "wof:placetype":"locality"
},
  "geometry": {"coordinates":[103.72199999999999,26.5519],"type":"Point"}
}