{
  "type": "Feature",
  "properties": {
    "gn:admin1_code":"25",
    "gn:asciiname":"Zhuchen Dongcun",
    "gn:country_code":"CN",
    "gn:dem":63,
    "gn:feature_class":"P",
    "gn:feature_code":"PPL",
    "gn:name":"Zhuchen Dongcun",
    "gn:population":0,
    "gn:timezone":"Asia/Shanghai",
    "iso:country":"CN",
    "name:zho_x_preferred":[
        "\u6731\u9648\u4e1c\u6751"
    ],
    "wof:name":"Zhuchen Dongcun",
    "wof:placetype":"locality"
},
  "geometry": {"coordinates":[118.247,34.9763],"type":"Point"}
}