{
  "type": "Feature",
  "properties": {
    "gn:admin1_code":"29.0",
    "gn:asciiname":"Laoqiaozhai",
    "gn:country_code":"CN",
    "gn:dem":1417,
    "gn:feature_class":"P",
    "gn:feature_code":"PPL",
    "gn:name":"Laoqiaozhai",
    "gn:population":0,
    "gn:timezone":"Asia/Shanghai",
    "iso:country":"CN",
    "name:zho_x_preferred":[
        "\u8001\u835e\u5be8"
    ],
    "wof:name":"Laoqiaozhai",
    "wof:placetype":"locality"
},
  "geometry": {"coordinates":[99.074,24.7547],"type":"Point"}
}