{
  "type": "Feature",
  "properties": {
    "gn:admin1_code":"29.0",
    "gn:asciiname":"Xinshuitian",
    "gn:country_code":"CN",
    "gn:dem":2017,
    "gn:feature_class":"P",
    "gn:feature_code":"PPL",
    "gn:name":"Xinshuitian",
    "gn:population":0,
    "gn:timezone":"Asia/Shanghai",
    "iso:country":"CN",
    "name:zho_x_preferred":[
        "\u65b0\u6c34\u7530"
    ],
    "wof:name":"Xinshuitian",
    "wof:placetype":"locality"
},
  "geometry": {"coordinates":[104.423,27.5519],"type":"Point"}
}