{
  "type": "Feature",
  "properties": {
    "gn:admin1_code":"10",
    "gn:asciiname":"Luyingzi",
    "gn:country_code":"CN",
    "gn:dem":552,
    "gn:feature_class":"P",
    "gn:feature_code":"PPL",
    "gn:name":"L\u00fcyingzi",
    "gn:population":0,
    "gn:timezone":"Asia/Shanghai",
    "iso:country":"CN",
    "name:und_x_variant":[
        "L\u00fcyingzi"
    ],
    "name:zho_x_preferred":[
        "\u5415\u8425\u5b50"
    ],
    "wof:name":"Luyingzi",
    "wof:placetype":"locality"
},
  "geometry": {"coordinates":[116.80772,40.89156],"type":"Point"}
}