{
  "type": "Feature",
  "properties": {
    "gn:admin1_code":"24.0",
    "gn:asciiname":"Danmadao",
    "gn:country_code":"CN",
    "gn:dem":1803,
    "gn:feature_class":"P",
    "gn:feature_code":"PPL",
    "gn:name":"Danmadao",
    "gn:population":0,
    "gn:timezone":"Asia/Shanghai",
    "iso:country":"CN",
    "name:zho_x_preferred":[
        "\u5355\u9a6c\u9053"
    ],
    "wof:name":"Danmadao",
    "wof:placetype":"locality"
},
  "geometry": {"coordinates":[113.03136000000001,39.26607],"type":"Point"}
}