{
  "type": "Feature",
  "properties": {
    "gn:admin1_code":"9",
    "gn:asciiname":"Shiyongji",
    "gn:country_code":"CN",
    "gn:dem":50,
    "gn:feature_class":"P",
    "gn:feature_code":"PPL",
    "gn:name":"Shiyongji",
    "gn:population":0,
    "gn:timezone":"Asia/Shanghai",
    "iso:country":"CN",
    "name:zho_x_preferred":[
        "\u65f6\u6c38\u96c6"
    ],
    "name:zho_x_variant":[
        "\u65f6\u96cd\u96c6"
    ],
    "wof:name":"Shiyongji",
    "wof:placetype":"locality"
},
  "geometry": {"coordinates":[115.47,35.8029],"type":"Point"}
}