{
  "type": "Feature",
  "properties": {
    "gn:admin1_code":"14.0",
    "gn:asciiname":"Buzecun",
    "gn:country_code":"CN",
    "gn:dem":3025,
    "gn:feature_class":"P",
    "gn:feature_code":"PPL",
    "gn:name":"Buzecun",
    "gn:population":0,
    "gn:timezone":"Asia/Urumqi",
    "iso:country":"CN",
    "name:zho_x_preferred":[
        "\u5e03\u5219\u6751"
    ],
    "wof:name":"Buzecun",
    "wof:placetype":"locality"
},
  "geometry": {"coordinates":[97.24160000000001,30.0731],"type":"Point"}
}