{
  "type": "Feature",
  "properties": {
    "gn:admin1_code":"29.0",
    "gn:asciiname":"Lixinhe",
    "gn:country_code":"CN",
    "gn:dem":2062,
    "gn:feature_class":"P",
    "gn:feature_code":"PPL",
    "gn:name":"Lixinhe",
    "gn:population":0,
    "gn:timezone":"Asia/Shanghai",
    "iso:country":"CN",
    "name:zho_x_preferred":[
        "\u7acb\u65b0\u6cb3"
    ],
    "wof:name":"Lixinhe",
    "wof:placetype":"locality"
},
  "geometry": {"coordinates":[100.39100000000001,24.5243],"type":"Point"}
}