{
  "type": "Feature",
  "properties": {
    "gn:admin1_code":"8.0",
    "gn:asciiname":"Erlongcun",
    "gn:country_code":"CN",
    "gn:dem":182,
    "gn:feature_class":"P",
    "gn:feature_code":"PPL",
    "gn:name":"Erlongcun",
    "gn:population":0,
    "gn:timezone":"Asia/Shanghai",
    "iso:country":"CN",
    "name:zho_x_preferred":[
        "\u4e8c\u9f99\u6751"
    ],
    "wof:name":"Erlongcun",
    "wof:placetype":"locality"
},
  "geometry": {"coordinates":[125.49581000000001,46.18729],"type":"Point"}
}