{
  "type": "Feature",
  "properties": {
    "gn:admin1_code":"12.0",
    "gn:asciiname":"Yinfengzui",
    "gn:country_code":"CN",
    "gn:dem":805,
    "gn:feature_class":"P",
    "gn:feature_code":"PPL",
    "gn:name":"Yinfengzui",
    "gn:population":0,
    "gn:timezone":"Asia/Shanghai",
    "iso:country":"CN",
    "name:zho_x_preferred":[
        "\u94f6\u5cf0\u5480"
    ],
    "wof:name":"Yinfengzui",
    "wof:placetype":"locality"
},
  "geometry": {"coordinates":[110.75264,30.29231],"type":"Point"}
}