{
  "type": "Feature",
  "properties": {
    "gn:admin1_code":"32.0",
    "gn:asciiname":"Banzhuzui",
    "gn:country_code":"CN",
    "gn:dem":551,
    "gn:feature_class":"P",
    "gn:feature_code":"PPL",
    "gn:name":"Banzhuzui",
    "gn:population":0,
    "gn:timezone":"Asia/Shanghai",
    "iso:country":"CN",
    "name:zho_x_preferred":[
        "\u6591\u7af9\u5480"
    ],
    "wof:name":"Banzhuzui",
    "wof:placetype":"locality"
},
  "geometry": {"coordinates":[106.23718999999998,31.50561],"type":"Point"}
}