{
  "type": "Feature",
  "properties": {
    "gn:admin1_code":"30",
    "gn:asciiname":"Dahu",
    "gn:country_code":"CN",
    "gn:dem":5,
    "gn:feature_class":"P",
    "gn:feature_code":"PPLA4",
    "gn:name":"Dahu",
    "gn:population":0,
    "gn:timezone":"Asia/Shanghai",
    "iso:country":"CN",
    "name:deu_x_preferred":[
        "Dahu"
    ],
    "name:fra_x_preferred":[
        "Dahu"
    ],
    "name:frp_x_preferred":[
        "Dahu"
    ],
    "name:heb_x_preferred":[
        "Dahu"
    ],
    "name:ita_x_preferred":[
        "Dahu"
    ],
    "name:lmo_x_preferred":[
        "Da\u00f9"
    ],
    "name:mkd_x_preferred":[
        "\u0414\u0430\u0445\u0443"
    ],
    "name:nld_x_preferred":[
        "Dahu"
    ],
    "name:por_x_preferred":[
        "Dahu"
    ],
    "name:rus_x_preferred":[
        "\u0414\u0430\u0445\u0443"
    ],
    "name:spa_x_preferred":[
        "Dahu"
    ],
    "name:srp_x_preferred":[
        "\u0414\u0430\u0445\u0443"
    ],
    "name:und_x_variant":[
        "Dahu Zhen",
        "\u5927\u6e56\u9547"
    ],
    "name:zho_x_preferred":[
        "\u5927\u6e56"
    ],
    "wof:name":"Dahu",
    "wof:placetype":"locality"
},
  "geometry": {"coordinates":[115.56838999999999,22.83772],"type":"Point"}
}