{
  "type": "Feature",
  "properties": {
    "gn:admin1_code":"32.0",
    "gn:asciiname":"Anaxiji",
    "gn:country_code":"CN",
    "gn:dem":2166,
    "gn:feature_class":"P",
    "gn:feature_code":"PPL",
    "gn:name":"Anaxiji",
    "gn:population":0,
    "gn:timezone":"Asia/Shanghai",
    "iso:country":"CN",
    "name:zho_x_preferred":[
        "\u963f\u90a3\u5e0c\u57fa"
    ],
    "wof:name":"Anaxiji",
    "wof:placetype":"locality"
},
  "geometry": {"coordinates":[102.322,28.1426],"type":"Point"}
}