{
  "type": "Feature",
  "properties": {
    "gn:admin1_code":"03",
    "gn:asciiname":"Gujiang",
    "gn:country_code":"CN",
    "gn:dem":64,
    "gn:feature_class":"P",
    "gn:feature_code":"PPLA4",
    "gn:name":"Gujiang",
    "gn:population":0,
    "gn:timezone":"Asia/Shanghai",
    "iso:country":"CN",
    "name:und_x_variant":[
        "Ku-chiang",
        "Gujiang",
        "\u56fa\u6c5f",
        "Gujiang Zhen",
        "\u56fa\u6c5f\u9547"
    ],
    "wof:name":"Gujiang",
    "wof:placetype":"locality"
},
  "geometry": {"coordinates":[114.788,27.18809000000001],"type":"Point"}
}