{
  "type": "Feature",
  "properties": {
    "gn:admin1_code":"18",
    "gn:asciiname":"Zhu'erba",
    "gn:country_code":"CN",
    "gn:dem":1338,
    "gn:feature_class":"P",
    "gn:feature_code":"PPL",
    "gn:name":"Zhu\u2019erba",
    "gn:population":0,
    "gn:timezone":"Asia/Shanghai",
    "iso:country":"CN",
    "name:und_x_variant":[
        "Zhu\u2019erba"
    ],
    "name:zho_x_preferred":[
        "\u732a\u513f\u575d"
    ],
    "wof:name":"Zhu'erba",
    "wof:placetype":"locality"
},
  "geometry": {"coordinates":[105.44,27.6429],"type":"Point"}
}