{
  "type": "Feature",
  "properties": {
    "gn:admin1_code":"1.0",
    "gn:asciiname":"Qiyingcun",
    "gn:country_code":"CN",
    "gn:dem":34,
    "gn:feature_class":"P",
    "gn:feature_code":"PPL",
    "gn:name":"Qiyingcun",
    "gn:population":0,
    "gn:timezone":"Asia/Shanghai",
    "iso:country":"CN",
    "name:zho_x_preferred":[
        "\u9f50\u90e2\u6751"
    ],
    "wof:name":"Qiyingcun",
    "wof:placetype":"locality"
},
  "geometry": {"coordinates":[115.54688,32.61144],"type":"Point"}
}