{
  "type": "Feature",
  "properties": {
    "gn:admin1_code":"16.0",
    "gn:asciiname":"Hemiao",
    "gn:country_code":"CN",
    "gn:dem":311,
    "gn:feature_class":"P",
    "gn:feature_code":"PPL",
    "gn:name":"Hemiao",
    "gn:population":0,
    "gn:timezone":"Asia/Shanghai",
    "iso:country":"CN",
    "name:zho_x_preferred":[
        "\u79be\u82d7"
    ],
    "wof:name":"Hemiao",
    "wof:placetype":"locality"
},
  "geometry": {"coordinates":[107.22199999999999,22.8928],"type":"Point"}
}