{
  "type": "Feature",
  "properties": {
    "gn:admin1_code":"32.0",
    "gn:asciiname":"Wuri",
    "gn:country_code":"CN",
    "gn:dem":3403,
    "gn:feature_class":"P",
    "gn:feature_code":"PPL",
    "gn:name":"Wuri",
    "gn:population":0,
    "gn:timezone":"Asia/Shanghai",
    "iso:country":"CN",
    "name:ceb_x_preferred":[
        "Wuri"
    ],
    "name:deu_x_preferred":[
        "Wuri"
    ],
    "name:swe_x_preferred":[
        "Wuri"
    ],
    "name:zho_x_preferred":[
        "\u5434\u65e5"
    ],
    "wof:name":"Wuri",
    "wof:placetype":"locality"
},
  "geometry": {"coordinates":[100.336,30.5435],"type":"Point"}
}