{
  "type": "Feature",
  "properties": {
    "gn:admin1_code":"16.0",
    "gn:asciiname":"Dadongkou",
    "gn:country_code":"CN",
    "gn:dem":157,
    "gn:feature_class":"P",
    "gn:feature_code":"PPL",
    "gn:name":"Dadongkou",
    "gn:population":0,
    "gn:timezone":"Asia/Shanghai",
    "iso:country":"CN",
    "name:zho_x_preferred":[
        "\u5927\u578c\u53e3"
    ],
    "wof:name":"Dadongkou",
    "wof:placetype":"locality"
},
  "geometry": {"coordinates":[109.392,22.4029],"type":"Point"}
}