{
  "type": "Feature",
  "properties": {
    "gn:admin1_code":"14.0",
    "gn:asciiname":"Dongwanjian",
    "gn:country_code":"CN",
    "gn:dem":4548,
    "gn:feature_class":"P",
    "gn:feature_code":"PPL",
    "gn:name":"Dongwanjian",
    "gn:population":0,
    "gn:timezone":"Asia/Urumqi",
    "iso:country":"CN",
    "name:zho_x_preferred":[
        "\u4e1c\u6e7e\u95f4"
    ],
    "wof:name":"Dongwanjian",
    "wof:placetype":"locality"
},
  "geometry": {"coordinates":[90.56344,28.7073],"type":"Point"}
}