{
  "type": "Feature",
  "properties": {
    "gn:admin1_code":"9.0",
    "gn:asciiname":"Xiahuangye",
    "gn:country_code":"CN",
    "gn:dem":840,
    "gn:feature_class":"P",
    "gn:feature_code":"PPL",
    "gn:name":"Xiahuangye",
    "gn:population":0,
    "gn:timezone":"Asia/Shanghai",
    "iso:country":"CN",
    "name:zho_x_preferred":[
        "\u4e0b\u9ec4\u53f6"
    ],
    "wof:name":"Xiahuangye",
    "wof:placetype":"locality"
},
  "geometry": {"coordinates":[110.8913,34.03083],"type":"Point"}
}