{
  "type": "Feature",
  "properties": {
    "gn:admin1_code":"22.0",
    "gn:asciiname":"Yadicun",
    "gn:country_code":"CN",
    "gn:dem":28,
    "gn:feature_class":"P",
    "gn:feature_code":"PPL",
    "gn:name":"Yadicun",
    "gn:population":0,
    "gn:timezone":"Asia/Shanghai",
    "iso:country":"CN",
    "name:zho_x_preferred":[
        "\u62bc\u5824\u6751"
    ],
    "wof:name":"Yadicun",
    "wof:placetype":"locality"
},
  "geometry": {"coordinates":[116.37685,39.4584],"type":"Point"}
}