{
  "type": "Feature",
  "properties": {
    "gn:admin1_code":"9.0",
    "gn:asciiname":"Shifan",
    "gn:country_code":"CN",
    "gn:dem":128,
    "gn:feature_class":"P",
    "gn:feature_code":"PPL",
    "gn:name":"Shifan",
    "gn:population":0,
    "gn:timezone":"Asia/Shanghai",
    "iso:country":"CN",
    "name:zho_x_preferred":[
        "\u77f3\u7548"
    ],
    "wof:name":"Shifan",
    "wof:placetype":"locality"
},
  "geometry": {"coordinates":[113.84918,32.14045],"type":"Point"}
}