{
  "type": "Feature",
  "properties": {
    "gn:admin1_code":"15.0",
    "gn:asciiname":"Dengdatai",
    "gn:country_code":"CN",
    "gn:dem":1430,
    "gn:feature_class":"P",
    "gn:feature_code":"PPL",
    "gn:name":"Dengdatai",
    "gn:population":0,
    "gn:timezone":"Asia/Shanghai",
    "iso:country":"CN",
    "name:und_x_variant":[
        "\u9093\u5927\u53f0"
    ],
    "wof:name":"Dengdatai",
    "wof:placetype":"locality"
},
  "geometry": {"coordinates":[107.11908,36.3037],"type":"Point"}
}