{
  "type": "Feature",
  "properties": {
    "gn:admin1_code":"14.0",
    "gn:asciiname":"Langshacun",
    "gn:country_code":"CN",
    "gn:dem":3505,
    "gn:feature_class":"P",
    "gn:feature_code":"PPL",
    "gn:name":"Langshacun",
    "gn:population":0,
    "gn:timezone":"Asia/Urumqi",
    "iso:country":"CN",
    "name:zho_x_preferred":[
        "\u6717\u6c99\u6751"
    ],
    "wof:name":"Langshacun",
    "wof:placetype":"locality"
},
  "geometry": {"coordinates":[93.13019,29.96137],"type":"Point"}
}