{
  "type": "Feature",
  "properties": {
    "gn:admin1_code":"2.0",
    "gn:asciiname":"Yantuo'ao",
    "gn:country_code":"CN",
    "gn:dem":486,
    "gn:feature_class":"P",
    "gn:feature_code":"PPL",
    "gn:name":"Yantuo\u2019ao",
    "gn:population":0,
    "gn:timezone":"Asia/Shanghai",
    "iso:country":"CN",
    "name:und_x_variant":[
        "Yantuo\u2019ao"
    ],
    "name:zho_x_preferred":[
        "\u4e25\u9a6e\u5c99"
    ],
    "wof:name":"Yantuo'ao",
    "wof:placetype":"locality"
},
  "geometry": {"coordinates":[119.9233,27.8222],"type":"Point"}
}