{
  "type": "Feature",
  "properties": {
    "gn:admin1_code":"4.0",
    "gn:asciiname":"Xiecun",
    "gn:country_code":"CN",
    "gn:dem":5,
    "gn:feature_class":"P",
    "gn:feature_code":"PPL",
    "gn:name":"Xiecun",
    "gn:population":0,
    "gn:timezone":"Asia/Shanghai",
    "iso:country":"CN",
    "name:zho_x_preferred":[
        "Xiecun"
    ],
    "name:zho_x_variant":[
        "\u8c22\u6751"
    ],
    "wof:name":"Xiecun",
    "wof:placetype":"locality"
},
  "geometry": {"coordinates":[121.56683,31.95275],"type":"Point"}
}