{
  "type": "Feature",
  "properties": {
    "gn:admin1_code":"4.0",
    "gn:asciiname":"Aikoucun",
    "gn:country_code":"CN",
    "gn:dem":7,
    "gn:feature_class":"P",
    "gn:feature_code":"PPL",
    "gn:name":"Aikoucun",
    "gn:population":0,
    "gn:timezone":"Asia/Shanghai",
    "iso:country":"CN",
    "name:zho_x_preferred":[
        "\u827e\u53e3\u6751"
    ],
    "wof:name":"Aikoucun",
    "wof:placetype":"locality"
},
  "geometry": {"coordinates":[119.26569000000001,33.60748],"type":"Point"}
}