{
  "type": "Feature",
  "properties": {
    "gn:admin1_code":"7.0",
    "gn:asciiname":"Lidun",
    "gn:country_code":"CN",
    "gn:dem":358,
    "gn:feature_class":"P",
    "gn:feature_code":"PPL",
    "gn:name":"Lidun",
    "gn:population":0,
    "gn:timezone":"Asia/Shanghai",
    "iso:country":"CN",
    "name:zho_x_preferred":[
        "\u7acb\u58a9"
    ],
    "wof:name":"Lidun",
    "wof:placetype":"locality"
},
  "geometry": {"coordinates":[118.2439,26.6588],"type":"Point"}
}