{
  "type": "Feature",
  "properties": {
    "gn:admin1_code":"26.0",
    "gn:asciiname":"Wangjiahe",
    "gn:cc2":"CN",
    "gn:country_code":"CN",
    "gn:dem":921,
    "gn:feature_class":"P",
    "gn:feature_code":"PPL",
    "gn:name":"Wangjiahe",
    "gn:population":0,
    "gn:timezone":"Asia/Shanghai",
    "iso:country":"CN",
    "name:und_x_variant":[
        "Wang-chia-ho",
        "Wangjiahe"
    ],
    "wof:name":"Wangjiahe",
    "wof:placetype":"locality"
},
  "geometry": {"coordinates":[106.65000000000001,33.33333],"type":"Point"}
}