{
  "type": "Feature",
  "properties": {
    "gn:admin1_code":"32.0",
    "gn:asciiname":"Wazidui",
    "gn:country_code":"CN",
    "gn:dem":762,
    "gn:feature_class":"P",
    "gn:feature_code":"PPL",
    "gn:name":"Wazidui",
    "gn:population":0,
    "gn:timezone":"Asia/Shanghai",
    "iso:country":"CN",
    "name:zho_x_preferred":[
        "\u74e6\u5b50\u5806"
    ],
    "wof:name":"Wazidui",
    "wof:placetype":"locality"
},
  "geometry": {"coordinates":[103.22282,30.16572],"type":"Point"}
}