{
  "type": "Feature",
  "properties": {
    "gn:admin1_code":"24.0",
    "gn:asciiname":"Wenshang",
    "gn:country_code":"CN",
    "gn:dem":1017,
    "gn:feature_class":"P",
    "gn:feature_code":"PPL",
    "gn:name":"Wenshang",
    "gn:population":0,
    "gn:timezone":"Asia/Shanghai",
    "iso:country":"CN",
    "name:zho_x_preferred":[
        "\u6587\u4e0a"
    ],
    "wof:name":"Wenshang",
    "wof:placetype":"locality"
},
  "geometry": {"coordinates":[112.30953999999998,36.18079],"type":"Point"}
}