{
  "type": "Feature",
  "properties": {
    "gn:admin1_code":"1.0",
    "gn:asciiname":"Liufuzhuangcun",
    "gn:country_code":"CN",
    "gn:dem":37,
    "gn:feature_class":"P",
    "gn:feature_code":"PPL",
    "gn:name":"Liufuzhuangcun",
    "gn:population":0,
    "gn:timezone":"Asia/Shanghai",
    "iso:country":"CN",
    "name:zho_x_preferred":[
        "\u5218\u4f0f\u5e84\u6751"
    ],
    "wof:name":"Liufuzhuangcun",
    "wof:placetype":"locality"
},
  "geometry": {"coordinates":[115.55328,33.08533],"type":"Point"}
}