{
  "type": "Feature",
  "properties": {
    "gn:admin1_code":"32.0",
    "gn:asciiname":"Chunjing",
    "gn:country_code":"CN",
    "gn:dem":2075,
    "gn:feature_class":"P",
    "gn:feature_code":"PPL",
    "gn:name":"Chunjing",
    "gn:population":0,
    "gn:timezone":"Asia/Shanghai",
    "iso:country":"CN",
    "name:zho_x_preferred":[
        "\u6625\u666f"
    ],
    "wof:name":"Chunjing",
    "wof:placetype":"locality"
},
  "geometry": {"coordinates":[102.482,28.7319],"type":"Point"}
}