{
  "type": "Feature",
  "properties": {
    "gn:admin1_code":"11.0",
    "gn:asciiname":"Wangjia Wanli",
    "gn:country_code":"CN",
    "gn:dem":168,
    "gn:feature_class":"P",
    "gn:feature_code":"PPL",
    "gn:name":"Wangjia Wanli",
    "gn:population":0,
    "gn:timezone":"Asia/Shanghai",
    "iso:country":"CN",
    "name:zho_x_preferred":[
        "\u738b\u5bb6\u6e7e\u91cc"
    ],
    "wof:name":"Wangjia Wanli",
    "wof:placetype":"locality"
},
  "geometry": {"coordinates":[113.67724,26.73538],"type":"Point"}
}