{
  "type": "Feature",
  "properties": {
    "gn:admin1_code":"19.0",
    "gn:asciiname":"Xiapingzhoucun",
    "gn:country_code":"CN",
    "gn:dem":41,
    "gn:feature_class":"P",
    "gn:feature_code":"PPL",
    "gn:name":"Xiapingzhoucun",
    "gn:population":0,
    "gn:timezone":"Asia/Shanghai",
    "iso:country":"CN",
    "name:zho_x_preferred":[
        "\u4e0b\u5e73\u6d32\u6751"
    ],
    "wof:name":"Xiapingzhoucun",
    "wof:placetype":"locality"
},
  "geometry": {"coordinates":[123.39521000000001,41.27454],"type":"Point"}
}