{
  "type": "Feature",
  "properties": {
    "gn:admin1_code":"4.0",
    "gn:asciiname":"Zaohuji",
    "gn:country_code":"CN",
    "gn:dem":43,
    "gn:feature_class":"P",
    "gn:feature_code":"PPL",
    "gn:name":"Zaohuji",
    "gn:population":0,
    "gn:timezone":"Asia/Shanghai",
    "iso:country":"CN",
    "name:zho_x_preferred":[
        "\u67a3\u80e1\u96c6"
    ],
    "wof:name":"Zaohuji",
    "wof:placetype":"locality"
},
  "geometry": {"coordinates":[116.761,34.5992],"type":"Point"}
}