{
  "type": "Feature",
  "properties": {
    "gn:admin1_code":"32.0",
    "gn:asciiname":"Xieping",
    "gn:country_code":"CN",
    "gn:dem":900,
    "gn:feature_class":"P",
    "gn:feature_code":"PPL",
    "gn:name":"Xieping",
    "gn:population":0,
    "gn:timezone":"Asia/Shanghai",
    "iso:country":"CN",
    "name:zho_x_preferred":[
        "\u659c\u576a"
    ],
    "wof:name":"Xieping",
    "wof:placetype":"locality"
},
  "geometry": {"coordinates":[107.935,31.5498],"type":"Point"}
}