{
  "type": "Feature",
  "properties": {
    "gn:admin1_code":"8.0",
    "gn:asciiname":"Ju'ercun",
    "gn:country_code":"CN",
    "gn:dem":175,
    "gn:feature_class":"P",
    "gn:feature_code":"PPL",
    "gn:name":"Ju\u2019ercun",
    "gn:population":0,
    "gn:timezone":"Asia/Shanghai",
    "iso:country":"CN",
    "name:und_x_variant":[
        "Ju\u2019ercun"
    ],
    "name:zho_x_preferred":[
        "\u5de8\u4e8c\u6751"
    ],
    "wof:name":"Ju'ercun",
    "wof:placetype":"locality"
},
  "geometry": {"coordinates":[123.98771000000001,48.09511],"type":"Point"}
}