{
  "type": "Feature",
  "properties": {
    "gn:admin1_code":"19.0",
    "gn:asciiname":"Qutuncun",
    "gn:country_code":"CN",
    "gn:dem":37,
    "gn:feature_class":"P",
    "gn:feature_code":"PPL",
    "gn:name":"Qutuncun",
    "gn:population":0,
    "gn:timezone":"Asia/Shanghai",
    "iso:country":"CN",
    "name:zho_x_preferred":[
        "\u66f2\u5c6f\u6751"
    ],
    "wof:name":"Qutuncun",
    "wof:placetype":"locality"
},
  "geometry": {"coordinates":[122.24299999999999,39.5115],"type":"Point"}
}