{
  "type": "Feature",
  "properties": {
    "gn:admin1_code":"25.0",
    "gn:asciiname":"Runhecun",
    "gn:country_code":"CN",
    "gn:dem":46,
    "gn:feature_class":"P",
    "gn:feature_code":"PPL",
    "gn:name":"Runhecun",
    "gn:population":0,
    "gn:timezone":"Asia/Shanghai",
    "iso:country":"CN",
    "name:zho_x_preferred":[
        "\u95f0\u6cb3\u6751"
    ],
    "wof:name":"Runhecun",
    "wof:placetype":"locality"
},
  "geometry": {"coordinates":[115.8246,35.2396],"type":"Point"}
}