{
  "type": "Feature",
  "properties": {
    "gn:admin1_code":"25",
    "gn:asciiname":"Zhanglaozhuang",
    "gn:country_code":"CN",
    "gn:dem":29,
    "gn:feature_class":"P",
    "gn:feature_code":"PPL",
    "gn:name":"Zhanglaozhuang",
    "gn:population":0,
    "gn:timezone":"Asia/Shanghai",
    "iso:country":"CN",
    "name:zho_x_preferred":[
        "\u5f20\u8001\u5e84"
    ],
    "wof:name":"Zhanglaozhuang",
    "wof:placetype":"locality"
},
  "geometry": {"coordinates":[116.358,36.9548],"type":"Point"}
}