{
  "type": "Feature",
  "properties": {
    "gn:admin1_code":"1.0",
    "gn:asciiname":"Anchongcun",
    "gn:country_code":"CN",
    "gn:dem":64,
    "gn:feature_class":"P",
    "gn:feature_code":"PPL",
    "gn:name":"Anchongcun",
    "gn:population":0,
    "gn:timezone":"Asia/Shanghai",
    "iso:country":"CN",
    "name:zho_x_preferred":[
        "\u6697\u51b2\u6751"
    ],
    "wof:name":"Anchongcun",
    "wof:placetype":"locality"
},
  "geometry": {"coordinates":[116.55055,30.75124000000001],"type":"Point"}
}