{
  "type": "Feature",
  "properties": {
    "gn:admin1_code":"25.0",
    "gn:asciiname":"Yinzi",
    "gn:country_code":"CN",
    "gn:dem":71,
    "gn:feature_class":"P",
    "gn:feature_code":"PPLA4",
    "gn:name":"Yinzi",
    "gn:population":0,
    "gn:timezone":"Asia/Shanghai",
    "iso:country":"CN",
    "name:fas_x_preferred":[
        "\u06cc\u06cc\u0646\u0632\u06cc"
    ],
    "name:und_x_variant":[
        "Yin-tzu-K\u2019uang",
        "Yinzikuang",
        "Yinzi",
        "Yinzi Zhen"
    ],
    "name:urd_x_preferred":[
        "\u06cc\u0646\u0632\u06cc"
    ],
    "name:zho_x_preferred":[
        "\u836b\u5b50"
    ],
    "name:zho_x_variant":[
        "\u836b\u5b50\u9547"
    ],
    "wof:name":"Yinzi",
    "wof:placetype":"locality"
},
  "geometry": {"coordinates":[122.31281,37.21496],"type":"Point"}
}