{
  "type": "Feature",
  "properties": {
    "gn:admin1_code":"11.0",
    "gn:asciiname":"Zhongniushi",
    "gn:country_code":"CN",
    "gn:dem":1355,
    "gn:feature_class":"P",
    "gn:feature_code":"PPL",
    "gn:name":"Zhongniushi",
    "gn:population":0,
    "gn:timezone":"Asia/Shanghai",
    "iso:country":"CN",
    "name:zho_x_preferred":[
        "\u4e2d\u725b\u77f3"
    ],
    "wof:name":"Zhongniushi",
    "wof:placetype":"locality"
},
  "geometry": {"coordinates":[114.04477,26.43078],"type":"Point"}
}