{
  "type": "Feature",
  "properties": {
    "gn:admin1_code":"33.0",
    "gn:asciiname":"Maojitang",
    "gn:country_code":"CN",
    "gn:dem":606,
    "gn:feature_class":"P",
    "gn:feature_code":"PPL",
    "gn:name":"Maojitang",
    "gn:population":0,
    "gn:timezone":"Asia/Shanghai",
    "iso:country":"CN",
    "name:zho_x_preferred":[
        "\u6bdb\u9e21\u8d9f"
    ],
    "wof:name":"Maojitang",
    "wof:placetype":"locality"
},
  "geometry": {"coordinates":[108.62814,28.46125],"type":"Point"}
}