{
  "type": "Feature",
  "properties": {
    "gn:admin1_code":"21.0",
    "gn:asciiname":"Lujiatai",
    "gn:country_code":"CN",
    "gn:dem":1688,
    "gn:feature_class":"P",
    "gn:feature_code":"PPL",
    "gn:name":"Lujiatai",
    "gn:population":0,
    "gn:timezone":"Asia/Shanghai",
    "iso:country":"CN",
    "name:zho_x_preferred":[
        "\u82a6\u5bb6\u53f0"
    ],
    "wof:name":"Lujiatai",
    "wof:placetype":"locality"
},
  "geometry": {"coordinates":[106.49594999999999,36.24617],"type":"Point"}
}