{
  "type": "Feature",
  "properties": {
    "gn:admin1_code":"16.0",
    "gn:asciiname":"Tuojiu",
    "gn:country_code":"CN",
    "gn:dem":126,
    "gn:feature_class":"P",
    "gn:feature_code":"PPL",
    "gn:name":"Tuojiu",
    "gn:population":0,
    "gn:timezone":"Asia/Shanghai",
    "iso:country":"CN",
    "name:zho_x_preferred":[
        "\u9a6e\u65e7"
    ],
    "wof:name":"Tuojiu",
    "wof:placetype":"locality"
},
  "geometry": {"coordinates":[108.75,22.9498],"type":"Point"}
}