{
  "type": "Feature",
  "properties": {
    "gn:admin1_code":"25.0",
    "gn:asciiname":"Yancheng",
    "gn:country_code":"CN",
    "gn:dem":27,
    "gn:feature_class":"P",
    "gn:feature_code":"PPLA3",
    "gn:name":"Yancheng",
    "gn:population":0,
    "gn:timezone":"Asia/Shanghai",
    "iso:country":"CN",
    "name:und_x_variant":[
        "Ch\u2019i-ho",
        "Qihe",
        "Yen-ch\u2019eng-chen",
        "Yen-ch\u2019eng",
        "Yancheng",
        "Yancheng Jiedao"
    ],
    "name:zho_x_preferred":[
        "\u664f\u57ce"
    ],
    "name:zho_x_variant":[
        "\u664f\u57ce\u8857\u9053"
    ],
    "wof:name":"Yancheng",
    "wof:placetype":"locality"
},
  "geometry": {"coordinates":[116.74388999999999,36.79944],"type":"Point"}
}