{
  "type": "Feature",
  "properties": {
    "gn:admin1_code":"25.0",
    "gn:asciiname":"Yancheng",
    "gn:country_code":"CN",
    "gn:dem":27,
    "gn:feature_class":"P",
    "gn:feature_code":"PPLA3",
    "gn:name":"Yancheng",
    "gn:population":0,
    "gn:timezone":"Asia/Shanghai",
    "iso:country":"CN",
    "name:deu_x_preferred":[
        "Qihe"
    ],
    "name:fas_x_preferred":[
        "\u0634\u0647\u0631\u0633\u062a\u0627\u0646 \u0686\u06cc\u0647\u0647"
    ],
    "name:jpn_x_preferred":[
        "\u6589\u6cb3\u770c"
    ],
    "name:kor_x_preferred":[
        "\uce58\ud5c8\ud604"
    ],
    "name:nor_x_preferred":[
        "Qihe"
    ],
    "name:rus_x_preferred":[
        "\u0426\u0438\u0445\u044d"
    ],
    "name:swe_x_preferred":[
        "Qihe"
    ],
    "name:und_x_variant":[
        "Ch\u2019i-ho",
        "Qihe",
        "Yen-ch\u2019eng-chen",
        "Yen-ch\u2019eng",
        "Yancheng",
        "Yancheng Jiedao"
    ],
    "name:vie_x_preferred":[
        "T\u1ec1 H\u00e0"
    ],
    "name:zho_x_preferred":[
        "\u664f\u57ce"
    ],
    "name:zho_x_variant":[
        "\u664f\u57ce\u8857\u9053",
        "\u9f50\u6cb3\u53bf"
    ],
    "wof:name":"Yancheng",
    "wof:placetype":"locality"
},
  "geometry": {"coordinates":[116.74388999999999,36.79944],"type":"Point"}
}