{
  "type": "Feature",
  "properties": {
    "gn:admin1_code":"25",
    "gn:asciiname":"Qianyudian",
    "gn:country_code":"CN",
    "gn:dem":55,
    "gn:feature_class":"P",
    "gn:feature_code":"PPL",
    "gn:name":"Qianyudian",
    "gn:population":0,
    "gn:timezone":"Asia/Shanghai",
    "iso:country":"CN",
    "name:zho_x_preferred":[
        "\u524d\u4e8e\u5e97"
    ],
    "wof:name":"Qianyudian",
    "wof:placetype":"locality"
},
  "geometry": {"coordinates":[118.67700000000001,34.9104],"type":"Point"}
}