{
  "type": "Feature",
  "properties": {
    "gn:admin1_code":"15",
    "gn:asciiname":"Huixian Chengguanzhen",
    "gn:country_code":"CN",
    "gn:dem":911,
    "gn:feature_class":"P",
    "gn:feature_code":"PPLA3",
    "gn:name":"Huixian Chengguanzhen",
    "gn:population":0,
    "gn:timezone":"Asia/Shanghai",
    "iso:country":"CN",
    "name:und_x_variant":[
        "Khuysyan\u2019",
        "Hui",
        "Hui-hsien",
        "Hui-ch\u2019eng",
        "Hui-hsien-ch\u2019eng",
        "Huixian Chengguanzhen",
        "\u5fbd\u53bf\u57ce\u5173\u9547",
        "Huixian",
        "Chengguan Zhen",
        "\u5fbd\u53bf",
        "\u57ce\u5173\u9547"
    ],
    "wof:name":"Huixian Chengguanzhen",
    "wof:placetype":"locality"
},
  "geometry": {"coordinates":[106.08083000000001,33.76833],"type":"Point"}
}