{
  "type": "Feature",
  "properties": {
    "date:inception_lower":"2019-01-01",
    "date:inception_upper":"2019-12-31",
    "iso:country":"CN",
    "wof:name":"Beijing Daxing International Airport",
    "wof:placetype":"campus"
},
  "geometry": {"coordinates":[116.41010300000001,39.51106],"type":"Point"}
}