{
  "type": "Feature",
  "properties": {
    "gn:admin1_code":"16.0",
    "gn:asciiname":"Xinshangbai",
    "gn:country_code":"CN",
    "gn:dem":116,
    "gn:feature_class":"P",
    "gn:feature_code":"PPL",
    "gn:name":"Xinshangbai",
    "gn:population":0,
    "gn:timezone":"Asia/Shanghai",
    "iso:country":"CN",
    "name:zho_x_preferred":[
        "\u65b0\u4e0a\u767d"
    ],
    "wof:name":"Xinshangbai",
    "wof:placetype":"locality"
},
  "geometry": {"coordinates":[109.441,23.6488],"type":"Point"}
}