{
  "type": "Feature",
  "properties": {
    "gn:admin1_code":"12.0",
    "gn:asciiname":"Shiyanjiao",
    "gn:country_code":"CN",
    "gn:dem":113,
    "gn:feature_class":"P",
    "gn:feature_code":"PPL",
    "gn:name":"Shiyanjiao",
    "gn:population":0,
    "gn:timezone":"Asia/Shanghai",
    "iso:country":"CN",
    "name:zho_x_preferred":[
        "\u5341\u5830\u89d2"
    ],
    "wof:name":"Shiyanjiao",
    "wof:placetype":"locality"
},
  "geometry": {"coordinates":[112.84078999999998,31.20922],"type":"Point"}
}