{
  "type": "Feature",
  "properties": {
    "gn:admin1_code":"1.0",
    "gn:asciiname":"Erguanqu Shibadui",
    "gn:country_code":"CN",
    "gn:dem":36,
    "gn:feature_class":"P",
    "gn:feature_code":"PPLF",
    "gn:name":"Erguanqu Shibadui",
    "gn:population":0,
    "gn:timezone":"Asia/Shanghai",
    "iso:country":"CN",
    "name:zho_x_preferred":[
        "Erguanqu Shibadui"
    ],
    "name:zho_x_variant":[
        "\u4e8c\u7ba1\u533a\u5341\u516b\u961f"
    ],
    "wof:name":"Erguanqu Shibadui",
    "wof:placetype":"locality"
},
  "geometry": {"coordinates":[119.09569,31.01516],"type":"Point"}
}