{
  "type": "Feature",
  "properties": {
    "gn:admin1_code":"19.0",
    "gn:asciiname":"Honglian",
    "gn:country_code":"CN",
    "gn:dem":159,
    "gn:feature_class":"P",
    "gn:feature_code":"PPL",
    "gn:name":"Honglian",
    "gn:population":0,
    "gn:timezone":"Asia/Shanghai",
    "iso:country":"CN",
    "name:und_x_variant":[
        "\u7ea2\u8138"
    ],
    "name:zho_x_preferred":[
        "\u7ea2\u8138"
    ],
    "wof:name":"Honglian",
    "wof:placetype":"locality"
},
  "geometry": {"coordinates":[123.92655000000001,41.34038],"type":"Point"}
}