{
  "type": "Feature",
  "properties": {
    "gn:admin1_code":"7",
    "gn:asciiname":"Shanqianhu",
    "gn:country_code":"CN",
    "gn:dem":817,
    "gn:feature_class":"P",
    "gn:feature_code":"PPL",
    "gn:name":"Shanqianhu",
    "gn:population":0,
    "gn:timezone":"Asia/Shanghai",
    "iso:country":"CN",
    "name:zho_x_preferred":[
        "\u4e0a\u524d\u6e56"
    ],
    "wof:name":"Shanqianhu",
    "wof:placetype":"locality"
},
  "geometry": {"coordinates":[118.47638999999999,25.82778],"type":"Point"}
}