{
  "type": "Feature",
  "properties": {
    "gn:admin1_code":"26.0",
    "gn:asciiname":"Zhenchuanbu",
    "gn:cc2":"CN",
    "gn:country_code":"CN",
    "gn:dem":879,
    "gn:feature_class":"P",
    "gn:feature_code":"PPL",
    "gn:name":"Zhenchuanbu",
    "gn:population":0,
    "gn:timezone":"Asia/Shanghai",
    "iso:country":"CN",
    "name:und_x_variant":[
        "Chenchwanpu",
        "Chen-ch\u2019uan",
        "Chen-ch\u2019uan-pu",
        "Chen-ch\u2019uan-pao",
        "Zhenchuanbu"
    ],
    "wof:name":"Zhenchuanbu",
    "wof:placetype":"locality"
},
  "geometry": {"coordinates":[110.09166999999999,37.85167],"type":"Point"}
}