{
  "type": "Feature",
  "properties": {
    "gn:admin1_code":"6.0",
    "gn:asciiname":"Baoretong",
    "gn:country_code":"CN",
    "gn:dem":3897,
    "gn:feature_class":"P",
    "gn:feature_code":"PPL",
    "gn:name":"Baoretong",
    "gn:population":0,
    "gn:timezone":"Asia/Urumqi",
    "iso:country":"CN",
    "name:zho_x_preferred":[
        "\u5b9d\u70ed\u901a"
    ],
    "wof:name":"Baoretong",
    "wof:placetype":"locality"
},
  "geometry": {"coordinates":[95.75593000000001,32.66746],"type":"Point"}
}