{
  "type": "Feature",
  "properties": {
    "gn:admin1_code":"18",
    "gn:asciiname":"Laoyashui",
    "gn:country_code":"CN",
    "gn:dem":952,
    "gn:feature_class":"P",
    "gn:feature_code":"PPL",
    "gn:name":"Laoyashui",
    "gn:population":0,
    "gn:timezone":"Asia/Shanghai",
    "iso:country":"CN",
    "name:zho_x_preferred":[
        "\u8001\u9e26\u6c34"
    ],
    "wof:name":"Laoyashui",
    "wof:placetype":"locality"
},
  "geometry": {"coordinates":[107.422,27.2069],"type":"Point"}
}