{
  "type": "Feature",
  "properties": {
    "gn:admin1_code":"11.0",
    "gn:asciiname":"Maoxi",
    "gn:country_code":"CN",
    "gn:dem":370,
    "gn:feature_class":"P",
    "gn:feature_code":"PPL",
    "gn:name":"Maoxi",
    "gn:population":0,
    "gn:timezone":"Asia/Shanghai",
    "iso:country":"CN",
    "name:zho_x_preferred":[
        "\u6bdb\u6eaa"
    ],
    "wof:name":"Maoxi",
    "wof:placetype":"locality"
},
  "geometry": {"coordinates":[109.18913000000001,27.38708],"type":"Point"}
}