{
  "type": "Feature",
  "properties": {
    "gn:admin1_code":"21",
    "gn:asciiname":"Shizilu",
    "gn:cc2":"CN",
    "gn:country_code":"CN",
    "gn:dem":1839,
    "gn:feature_class":"P",
    "gn:feature_code":"PPL",
    "gn:name":"Shizilu",
    "gn:population":0,
    "gn:timezone":"Asia/Shanghai",
    "iso:country":"CN",
    "name:und_x_variant":[
        "Shih-tzu-lu",
        "Shizilu"
    ],
    "wof:name":"Shizilu",
    "wof:placetype":"locality"
},
  "geometry": {"coordinates":[106.30389,35.69083],"type":"Point"}
}