{
  "type": "Feature",
  "properties": {
    "gn:admin1_code":"3.0",
    "gn:asciiname":"Sheshenmiao",
    "gn:country_code":"CN",
    "gn:dem":109,
    "gn:feature_class":"P",
    "gn:feature_code":"PPL",
    "gn:name":"Sheshenmiao",
    "gn:population":0,
    "gn:timezone":"Asia/Shanghai",
    "iso:country":"CN",
    "name:und_x_variant":[
        "\u793e\u795e\u5e99"
    ],
    "wof:name":"Sheshenmiao",
    "wof:placetype":"locality"
},
  "geometry": {"coordinates":[115.49145,27.18704],"type":"Point"}
}