{
  "type": "Feature",
  "properties": {
    "gn:admin1_code":"2.0",
    "gn:asciiname":"Tianzhongyang",
    "gn:country_code":"CN",
    "gn:dem":478,
    "gn:feature_class":"P",
    "gn:feature_code":"PPL",
    "gn:name":"Tianzhongyang",
    "gn:population":0,
    "gn:timezone":"Asia/Shanghai",
    "iso:country":"CN",
    "name:zho_x_preferred":[
        "\u7530\u4e2d\u592e"
    ],
    "wof:name":"Tianzhongyang",
    "wof:placetype":"locality"
},
  "geometry": {"coordinates":[120.77479,29.01896],"type":"Point"}
}