{
  "type": "Feature",
  "properties": {
    "gn:admin1_code":"9.0",
    "gn:asciiname":"Guidongcun",
    "gn:country_code":"CN",
    "gn:dem":61,
    "gn:feature_class":"P",
    "gn:feature_code":"PPL",
    "gn:name":"Guidongcun",
    "gn:population":0,
    "gn:timezone":"Asia/Shanghai",
    "iso:country":"CN",
    "name:zho_x_preferred":[
        "\u5f52\u4e1c\u6751"
    ],
    "wof:name":"Guidongcun",
    "wof:placetype":"locality"
},
  "geometry": {"coordinates":[114.18882000000001,33.58882],"type":"Point"}
}