{
  "type": "Feature",
  "properties": {
    "gn:admin1_code":"02",
    "gn:asciiname":"Juyu",
    "gn:country_code":"CN",
    "gn:dem":51,
    "gn:feature_class":"P",
    "gn:feature_code":"PPL",
    "gn:name":"Juyu",
    "gn:population":0,
    "gn:timezone":"Asia/Shanghai",
    "iso:country":"CN",
    "name:und_x_variant":[
        "Yangwei",
        "Juyu"
    ],
    "name:zho_x_preferred":[
        "\u5de8\u5c7f"
    ],
    "wof:name":"Juyu",
    "wof:placetype":"locality"
},
  "geometry": {"coordinates":[120.08875,27.69206],"type":"Point"}
}