{
  "type": "Feature",
  "properties": {
    "gn:admin1_code":"2.0",
    "gn:asciiname":"Luoshufang",
    "gn:country_code":"CN",
    "gn:dem":33,
    "gn:feature_class":"P",
    "gn:feature_code":"PPL",
    "gn:name":"Luoshufang",
    "gn:population":0,
    "gn:timezone":"Asia/Shanghai",
    "iso:country":"CN",
    "name:und_x_variant":[
        "\u6d1b\u4e66\u623f"
    ],
    "wof:name":"Luoshufang",
    "wof:placetype":"locality"
},
  "geometry": {"coordinates":[119.5527,30.63708],"type":"Point"}
}