{
  "type": "Feature",
  "properties": {
    "gn:admin1_code":"18.0",
    "gn:asciiname":"Pingya",
    "gn:country_code":"CN",
    "gn:dem":529,
    "gn:feature_class":"P",
    "gn:feature_code":"PPL",
    "gn:name":"Pingya",
    "gn:population":0,
    "gn:timezone":"Asia/Shanghai",
    "iso:country":"CN",
    "name:zho_x_preferred":[
        "\u5e73\u7259"
    ],
    "wof:name":"Pingya",
    "wof:placetype":"locality"
},
  "geometry": {"coordinates":[108.699,27.5066],"type":"Point"}
}