{
  "type": "Feature",
  "properties": {
    "gn:admin1_code":"8.0",
    "gn:asciiname":"Simajia",
    "gn:country_code":"CN",
    "gn:dem":189,
    "gn:feature_class":"P",
    "gn:feature_code":"PPL",
    "gn:name":"Simajia",
    "gn:population":0,
    "gn:timezone":"Asia/Shanghai",
    "iso:country":"CN",
    "name:zho_x_preferred":[
        "\u56db\u9a6c\u67b6"
    ],
    "wof:name":"Simajia",
    "wof:placetype":"locality"
},
  "geometry": {"coordinates":[125.31171000000001,47.45345],"type":"Point"}
}