{
  "type": "Feature",
  "properties": {
    "gn:admin1_code":"14.0",
    "gn:asciiname":"Sebujuecun",
    "gn:country_code":"CN",
    "gn:dem":4780,
    "gn:feature_class":"P",
    "gn:feature_code":"PPL",
    "gn:name":"Sebujuecun",
    "gn:population":0,
    "gn:timezone":"Asia/Urumqi",
    "iso:country":"CN",
    "name:zho_x_preferred":[
        "\u8272\u5e03\u89c9\u6751"
    ],
    "wof:name":"Sebujuecun",
    "wof:placetype":"locality"
},
  "geometry": {"coordinates":[91.849,32.07615],"type":"Point"}
}