{
  "type": "Feature",
  "properties": {
    "gn:admin1_code":"19.0",
    "gn:asciiname":"Xiaoyingzi",
    "gn:country_code":"CN",
    "gn:dem":45,
    "gn:feature_class":"P",
    "gn:feature_code":"PPL",
    "gn:name":"Xiaoyingzi",
    "gn:population":0,
    "gn:timezone":"Asia/Shanghai",
    "iso:country":"CN",
    "name:und_x_variant":[
        "\u5c0f\u8425\u5b50"
    ],
    "name:zho_x_preferred":[
        "\u5c0f\u8425\u5b50"
    ],
    "wof:name":"Xiaoyingzi",
    "wof:placetype":"locality"
},
  "geometry": {"coordinates":[123.33693999999998,42.04454000000001],"type":"Point"}
}