{
  "type": "Feature",
  "properties": {
    "gn:admin1_code":"12",
    "gn:asciiname":"Luodian",
    "gn:country_code":"CN",
    "gn:dem":96,
    "gn:feature_class":"P",
    "gn:feature_code":"PPLA4",
    "gn:name":"Luodian",
    "gn:population":0,
    "gn:timezone":"Asia/Shanghai",
    "iso:country":"CN",
    "name:und_x_variant":[
        "Lo-chia-tien",
        "Luojiadian",
        "Luodian",
        "\u9a86\u5e97",
        "Luodian Xiang",
        "\u9a86\u5e97\u4e61"
    ],
    "wof:name":"Luodian",
    "wof:placetype":"locality"
},
  "geometry": {"coordinates":[113.77938,31.54731],"type":"Point"}
}