{
  "type": "Feature",
  "properties": {
    "gn:admin1_code":"14.0",
    "gn:asciiname":"Bangxing",
    "gn:country_code":"CN",
    "gn:dem":2039,
    "gn:feature_class":"P",
    "gn:feature_code":"PPLF",
    "gn:name":"Bangxing",
    "gn:population":0,
    "gn:timezone":"Asia/Urumqi",
    "iso:country":"CN",
    "name:bod_x_preferred":[
        "Bangxing"
    ],
    "name:ceb_x_preferred":[
        "Bangxing"
    ],
    "name:fas_x_preferred":[
        "\u0628\u0627\u0646\u06af\u0634\u06cc\u0646\u06af"
    ],
    "name:fra_x_preferred":[
        "Bangxing"
    ],
    "name:msa_x_preferred":[
        "Bangxing"
    ],
    "name:swe_x_preferred":[
        "Bangxing"
    ],
    "name:zho_x_preferred":[
        "Pangxin"
    ],
    "name:zho_x_variant":[
        "\u65c1\u8f9b",
        "\u65c1\u8f9b\u4e61"
    ],
    "wof:name":"Bangxing",
    "wof:placetype":"locality"
},
  "geometry": {"coordinates":[95.41667,29.61667000000001],"type":"Point"}
}