{
  "type": "Feature",
  "properties": {
    "gn:admin1_code":"33.0",
    "gn:asciiname":"Xixin",
    "gn:country_code":"CN",
    "gn:dem":1192,
    "gn:feature_class":"P",
    "gn:feature_code":"PPLA4",
    "gn:name":"Xixin",
    "gn:population":0,
    "gn:timezone":"Asia/Shanghai",
    "iso:country":"CN",
    "name:und_x_variant":[
        "Xixin Xiang",
        "Xijiaoxi"
    ],
    "name:zho_x_preferred":[
        "\u6d17\u65b0"
    ],
    "name:zho_x_variant":[
        "\u6d17\u65b0\u4e61",
        "\u6d17\u811a\u6eaa"
    ],
    "wof:name":"Xixin",
    "wof:placetype":"locality"
},
  "geometry": {"coordinates":[108.39533,29.9189],"type":"Point"}
}