{
  "type": "Feature",
  "properties": {
    "gn:country":"CN",
    "gn:fcode":"PPLA3",
    "gn:population":60335,
    "iso:country":"CN",
    "name:eng_x_historical":[
        "Tai Ping"
    ],
    "name:eng_x_preferred":[
        "Tai Ping"
    ],
    "name:und_x_variant":[
        "Taiping-fu"
    ],
    "name:zho_x_preferred":[
        "Tang-t\u2019u"
    ],
    "name:zho_x_variant":[
        "Tang-t\u2019u-hsien",
        "\u59d1\u719f"
    ],
    "qs:name":"Gushu",
    "qs:photos_9r":0,
    "qs:photos_sr":0,
    "qs:pop_sr":"8",
    "wof:name":"Gushu",
    "wof:placetype":"locality",
    "wof:population":60335
},
  "geometry": {"coordinates":[118.48147,31.56055],"type":"Point"}
}