{
  "type": "Feature",
  "properties": {
    "gn:admin1_code":"3.0",
    "gn:asciiname":"Daoshan",
    "gn:country_code":"CN",
    "gn:dem":123,
    "gn:feature_class":"P",
    "gn:feature_code":"PPL",
    "gn:name":"Daoshan",
    "gn:population":0,
    "gn:timezone":"Asia/Shanghai",
    "iso:country":"CN",
    "name:und_x_variant":[
        "\u9053\u5c71"
    ],
    "wof:name":"Daoshan",
    "wof:placetype":"locality"
},
  "geometry": {"coordinates":[115.4444,29.40757],"type":"Point"}
}