{
  "type": "Feature",
  "properties": {
    "gn:admin1_code":"26.0",
    "gn:asciiname":"Kuanpingcun",
    "gn:country_code":"CN",
    "gn:dem":1255,
    "gn:feature_class":"P",
    "gn:feature_code":"PPL",
    "gn:name":"Kuanpingcun",
    "gn:population":0,
    "gn:timezone":"Asia/Shanghai",
    "iso:country":"CN",
    "name:zho_x_preferred":[
        "\u5bbd\u576a\u6751"
    ],
    "wof:name":"Kuanpingcun",
    "wof:placetype":"locality"
},
  "geometry": {"coordinates":[110.47638999999999,33.28331],"type":"Point"}
}