{
  "type": "Feature",
  "properties": {
    "gn:admin1_code":"15.0",
    "gn:asciiname":"Neigu",
    "gn:country_code":"CN",
    "gn:dem":1272,
    "gn:feature_class":"P",
    "gn:feature_code":"PPL",
    "gn:name":"Neigu",
    "gn:population":0,
    "gn:timezone":"Asia/Shanghai",
    "iso:country":"CN",
    "name:und_x_variant":[
        "\u5185\u8c37"
    ],
    "wof:name":"Neigu",
    "wof:placetype":"locality"
},
  "geometry": {"coordinates":[106.39131999999999,33.85833],"type":"Point"}
}