{
  "type": "Feature",
  "properties": {
    "gn:admin1_code":"22.0",
    "gn:asciiname":"Shiziyingcun",
    "gn:country_code":"CN",
    "gn:dem":541,
    "gn:feature_class":"P",
    "gn:feature_code":"PPL",
    "gn:name":"Shiziyingcun",
    "gn:population":0,
    "gn:timezone":"Asia/Shanghai",
    "iso:country":"CN",
    "name:zho_x_preferred":[
        "\u72ee\u5b50\u8425\u6751"
    ],
    "wof:name":"Shiziyingcun",
    "wof:placetype":"locality"
},
  "geometry": {"coordinates":[116.18167,40.54395],"type":"Point"}
}