{
  "type": "Feature",
  "properties": {
    "gn:admin1_code":"29.0",
    "gn:asciiname":"Xujia Liangzi",
    "gn:country_code":"CN",
    "gn:dem":1702,
    "gn:feature_class":"P",
    "gn:feature_code":"PPL",
    "gn:name":"Xujia Liangzi",
    "gn:population":0,
    "gn:timezone":"Asia/Shanghai",
    "iso:country":"CN",
    "name:zho_x_preferred":[
        "\u5f90\u5bb6\u6881\u5b50"
    ],
    "wof:name":"Xujia Liangzi",
    "wof:placetype":"locality"
},
  "geometry": {"coordinates":[103.143,26.4538],"type":"Point"}
}