{
  "type": "Feature",
  "properties": {
    "gn:admin1_code":"25.0",
    "gn:asciiname":"Liangyin",
    "gn:cc2":"CN",
    "gn:country_code":"CN",
    "gn:dem":78,
    "gn:feature_class":"P",
    "gn:feature_code":"PPL",
    "gn:name":"Liangyin",
    "gn:population":0,
    "gn:timezone":"Asia/Shanghai",
    "iso:country":"CN",
    "name:zho_x_preferred":[
        "\u6881\u5c39"
    ],
    "wof:name":"Liangyin",
    "wof:placetype":"locality"
},
  "geometry": {"coordinates":[119.64561,36.16357],"type":"Point"}
}