{
  "type": "Feature",
  "properties": {
    "gn:admin1_code":"29.0",
    "gn:asciiname":"Lugu",
    "gn:country_code":"CN",
    "gn:dem":1882,
    "gn:feature_class":"P",
    "gn:feature_code":"PPL",
    "gn:name":"Lugu",
    "gn:population":0,
    "gn:timezone":"Asia/Shanghai",
    "iso:country":"CN",
    "name:ceb_x_preferred":[
        "Lugu"
    ],
    "name:deu_x_preferred":[
        "Lugu"
    ],
    "name:nld_x_preferred":[
        "Lugu"
    ],
    "name:swe_x_preferred":[
        "Lugu"
    ],
    "name:zho_x_preferred":[
        "\u9c81\u53e4"
    ],
    "wof:name":"Lugu",
    "wof:placetype":"locality"
},
  "geometry": {"coordinates":[103.31999999999999,25.5117],"type":"Point"}
}