{
  "type": "Feature",
  "properties": {
    "gn:admin1_code":"3",
    "gn:asciiname":"Yanxi",
    "gn:country_code":"CN",
    "gn:dem":69,
    "gn:feature_class":"P",
    "gn:feature_code":"PPL",
    "gn:name":"Yanxi",
    "gn:population":0,
    "gn:timezone":"Asia/Shanghai",
    "iso:country":"CN",
    "name:ceb_x_preferred":[
        "Yanxi"
    ],
    "name:deu_x_preferred":[
        "Yanxi"
    ],
    "name:swe_x_preferred":[
        "Yanxi"
    ],
    "name:zho_x_preferred":[
        "\u6cbf\u6eaa"
    ],
    "wof:name":"Yanxi",
    "wof:placetype":"locality"
},
  "geometry": {"coordinates":[114.95175,26.8093],"type":"Point"}
}