{
  "type": "Feature",
  "properties": {
    "gn:admin1_code":"9.0",
    "gn:asciiname":"Xihuangpeng",
    "gn:country_code":"CN",
    "gn:dem":177,
    "gn:feature_class":"P",
    "gn:feature_code":"PPL",
    "gn:name":"Xihuangpeng",
    "gn:population":0,
    "gn:timezone":"Asia/Shanghai",
    "iso:country":"CN",
    "name:zho_x_preferred":[
        "\u897f\u9ec4\u68da"
    ],
    "wof:name":"Xihuangpeng",
    "wof:placetype":"locality"
},
  "geometry": {"coordinates":[113.44522000000001,32.43190999999999],"type":"Point"}
}