{
  "type": "Feature",
  "properties": {
    "gn:admin1_code":"14.0",
    "gn:asciiname":"Qianacun",
    "gn:country_code":"CN",
    "gn:dem":3673,
    "gn:feature_class":"P",
    "gn:feature_code":"PPL",
    "gn:name":"Qianacun",
    "gn:population":0,
    "gn:timezone":"Asia/Urumqi",
    "iso:country":"CN",
    "name:zho_x_preferred":[
        "\u6070\u90a3\u6751"
    ],
    "wof:name":"Qianacun",
    "wof:placetype":"locality"
},
  "geometry": {"coordinates":[93.33486000000001,29.73821],"type":"Point"}
}