{
  "type": "Feature",
  "properties": {
    "gn:admin1_code":"10.0",
    "gn:asciiname":"Wushimudi",
    "gn:country_code":"CN",
    "gn:dem":657,
    "gn:feature_class":"P",
    "gn:feature_code":"PPL",
    "gn:name":"Wushimudi",
    "gn:population":0,
    "gn:timezone":"Asia/Shanghai",
    "iso:country":"CN",
    "name:zho_x_preferred":[
        "\u4e94\u5341\u4ea9\u5730"
    ],
    "wof:name":"Wushimudi",
    "wof:placetype":"locality"
},
  "geometry": {"coordinates":[114.947,39.42076],"type":"Point"}
}