{
  "type": "Feature",
  "properties": {
    "gn:admin1_code":"16.0",
    "gn:asciiname":"Longkong",
    "gn:country_code":"CN",
    "gn:dem":148,
    "gn:feature_class":"P",
    "gn:feature_code":"PPL",
    "gn:name":"Longkong",
    "gn:population":0,
    "gn:timezone":"Asia/Shanghai",
    "iso:country":"CN",
    "name:zho_x_preferred":[
        "\u9f99\u7a7a"
    ],
    "wof:name":"Longkong",
    "wof:placetype":"locality"
},
  "geometry": {"coordinates":[107.80200000000001,23.1618],"type":"Point"}
}