{
  "type": "Feature",
  "properties": {
    "gn:admin1_code":"10",
    "gn:asciiname":"Xihuzhuang",
    "gn:country_code":"CN",
    "gn:dem":45,
    "gn:feature_class":"P",
    "gn:feature_code":"PPL",
    "gn:name":"Xihuzhuang",
    "gn:population":0,
    "gn:timezone":"Asia/Shanghai",
    "iso:country":"CN",
    "name:zho_x_preferred":[
        "\u897f\u547c\u5e84"
    ],
    "wof:name":"Xihuzhuang",
    "wof:placetype":"locality"
},
  "geometry": {"coordinates":[115.26367,36.35631],"type":"Point"}
}