{
  "type": "Feature",
  "properties": {
    "gn:admin1_code":"32.0",
    "gn:asciiname":"Shengquan",
    "gn:country_code":"CN",
    "gn:dem":433,
    "gn:feature_class":"P",
    "gn:feature_code":"PPL",
    "gn:name":"Shengquan",
    "gn:population":0,
    "gn:timezone":"Asia/Shanghai",
    "iso:country":"CN",
    "name:zho_x_preferred":[
        "\u80dc\u6cc9"
    ],
    "wof:name":"Shengquan",
    "wof:placetype":"locality"
},
  "geometry": {"coordinates":[104.10518999999999,29.49784],"type":"Point"}
}