{
  "type": "Feature",
  "properties": {
    "gn:admin1_code":"29.0",
    "gn:asciiname":"Dachunshu",
    "gn:country_code":"CN",
    "gn:dem":1167,
    "gn:feature_class":"P",
    "gn:feature_code":"PPL",
    "gn:name":"Dachunshu",
    "gn:population":0,
    "gn:timezone":"Asia/Shanghai",
    "iso:country":"CN",
    "name:zho_x_preferred":[
        "\u5927\u6625\u6811"
    ],
    "wof:name":"Dachunshu",
    "wof:placetype":"locality"
},
  "geometry": {"coordinates":[101.26300000000001,22.6535],"type":"Point"}
}