{
  "type": "Feature",
  "properties": {
    "gn:admin1_code":"33.0",
    "gn:asciiname":"Yangling",
    "gn:country_code":"CN",
    "gn:dem":551,
    "gn:feature_class":"P",
    "gn:feature_code":"PPL",
    "gn:name":"Yangling",
    "gn:population":0,
    "gn:timezone":"Asia/Shanghai",
    "iso:country":"CN",
    "name:zho_x_preferred":[
        "\u6768\u5cad"
    ],
    "wof:name":"Yangling",
    "wof:placetype":"locality"
},
  "geometry": {"coordinates":[107.67608,29.7784],"type":"Point"}
}