{
  "type": "Feature",
  "properties": {
    "gn:admin1_code":"26.0",
    "gn:asciiname":"Honghuacun",
    "gn:country_code":"CN",
    "gn:dem":556,
    "gn:feature_class":"P",
    "gn:feature_code":"PPL",
    "gn:name":"Honghuacun",
    "gn:population":0,
    "gn:timezone":"Asia/Shanghai",
    "iso:country":"CN",
    "name:und_x_variant":[
        "\u5b8f\u5316\u6751"
    ],
    "wof:name":"Honghuacun",
    "wof:placetype":"locality"
},
  "geometry": {"coordinates":[109.30103,34.94186],"type":"Point"}
}