{
  "type": "Feature",
  "properties": {
    "gn:admin1_code":"29.0",
    "gn:asciiname":"Guiwu",
    "gn:country_code":"CN",
    "gn:dem":3741,
    "gn:feature_class":"P",
    "gn:feature_code":"PPL",
    "gn:name":"Guiwu",
    "gn:population":0,
    "gn:timezone":"Asia/Shanghai",
    "iso:country":"CN",
    "name:zho_x_preferred":[
        "\u89c4\u543e"
    ],
    "wof:name":"Guiwu",
    "wof:placetype":"locality"
},
  "geometry": {"coordinates":[99.0324,29.0143],"type":"Point"}
}