{
  "type": "Feature",
  "properties": {
    "gn:admin1_code":"4.0",
    "gn:asciiname":"Guozuicun",
    "gn:country_code":"CN",
    "gn:dem":16,
    "gn:feature_class":"P",
    "gn:feature_code":"PPL",
    "gn:name":"Guozuicun",
    "gn:population":0,
    "gn:timezone":"Asia/Shanghai",
    "iso:country":"CN",
    "name:zho_x_preferred":[
        "\u90ed\u5634\u6751"
    ],
    "wof:name":"Guozuicun",
    "wof:placetype":"locality"
},
  "geometry": {"coordinates":[118.22607000000001,33.60651],"type":"Point"}
}