{
  "type": "Feature",
  "properties": {
    "gn:admin1_code":"32.0",
    "gn:asciiname":"Lianghekou",
    "gn:country_code":"CN",
    "gn:dem":2809,
    "gn:feature_class":"P",
    "gn:feature_code":"PPL",
    "gn:name":"Lianghekou",
    "gn:population":0,
    "gn:timezone":"Asia/Shanghai",
    "iso:country":"CN",
    "name:zho_x_preferred":[
        "\u4e24\u6cb3\u53e3"
    ],
    "wof:name":"Lianghekou",
    "wof:placetype":"locality"
},
  "geometry": {"coordinates":[102.44315,30.88527],"type":"Point"}
}