{
  "type": "Feature",
  "properties": {
    "gn:admin1_code":"15.0",
    "gn:asciiname":"Mayaogou",
    "gn:country_code":"CN",
    "gn:dem":2162,
    "gn:feature_class":"P",
    "gn:feature_code":"PPL",
    "gn:name":"Mayaogou",
    "gn:population":0,
    "gn:timezone":"Asia/Shanghai",
    "iso:country":"CN",
    "name:zho_x_preferred":[
        "\u9a6c\u7a91\u6c9f"
    ],
    "wof:name":"Mayaogou",
    "wof:placetype":"locality"
},
  "geometry": {"coordinates":[104.52500000000001,35.896],"type":"Point"}
}