{
  "type": "Feature",
  "properties": {
    "gn:admin1_code":"3",
    "gn:asciiname":"Shatian",
    "gn:country_code":"CN",
    "gn:dem":132,
    "gn:feature_class":"P",
    "gn:feature_code":"PPLA4",
    "gn:name":"Shatian",
    "gn:population":0,
    "gn:timezone":"Asia/Shanghai",
    "iso:country":"CN",
    "name:ceb_x_preferred":[
        "Shatian"
    ],
    "name:deu_x_preferred":[
        "Shatian"
    ],
    "name:jpn_x_preferred":[
        "\u6c99\u7530"
    ],
    "name:swe_x_preferred":[
        "Shatian"
    ],
    "name:und_x_variant":[
        "Shatian Zhen",
        "\u6c99\u7530\u9547"
    ],
    "name:zho_x_preferred":[
        "\u6c99\u7530"
    ],
    "wof:name":"Shatian",
    "wof:placetype":"locality"
},
  "geometry": {"coordinates":[118.2807,28.33801],"type":"Point"}
}