{
  "type": "Feature",
  "properties": {
    "gn:admin1_code":"3",
    "gn:asciiname":"Baixu",
    "gn:country_code":"CN",
    "gn:dem":40,
    "gn:feature_class":"P",
    "gn:feature_code":"PPLA4",
    "gn:name":"Baixu",
    "gn:population":0,
    "gn:timezone":"Asia/Shanghai",
    "iso:country":"CN",
    "name:und_x_variant":[
        "\u767d\u5729",
        "Baixu Xiang",
        "\u767d\u5729\u4e61"
    ],
    "wof:name":"Baixu",
    "wof:placetype":"locality"
},
  "geometry": {"coordinates":[116.25248999999999,28.26156],"type":"Point"}
}