{
  "type": "Feature",
  "properties": {
    "gn:admin1_code":"12.0",
    "gn:asciiname":"Danggou",
    "gn:country_code":"CN",
    "gn:dem":426,
    "gn:feature_class":"P",
    "gn:feature_code":"PPL",
    "gn:name":"Danggou",
    "gn:population":0,
    "gn:timezone":"Asia/Shanghai",
    "iso:country":"CN",
    "name:zho_x_preferred":[
        "\u7800\u6c9f"
    ],
    "wof:name":"Danggou",
    "wof:placetype":"locality"
},
  "geometry": {"coordinates":[111.08613,33.12437],"type":"Point"}
}