{
  "type": "Feature",
  "properties": {
    "gn:admin1_code":"9.0",
    "gn:asciiname":"Qiancheng'ergang",
    "gn:country_code":"CN",
    "gn:dem":69,
    "gn:feature_class":"P",
    "gn:feature_code":"PPL",
    "gn:name":"Qiancheng\u2019ergang",
    "gn:population":0,
    "gn:timezone":"Asia/Shanghai",
    "iso:country":"CN",
    "name:und_x_variant":[
        "Qiancheng\u2019ergang"
    ],
    "name:zho_x_preferred":[
        "\u524d\u57ce\u8033\u5c97"
    ],
    "wof:name":"Qiancheng'ergang",
    "wof:placetype":"locality"
},
  "geometry": {"coordinates":[114.40646,34.47284000000001],"type":"Point"}
}