{
  "type": "Feature",
  "properties": {
    "gn:admin1_code":"26.0",
    "gn:asciiname":"Dijia Goumenxia",
    "gn:country_code":"CN",
    "gn:dem":1215,
    "gn:feature_class":"P",
    "gn:feature_code":"PPL",
    "gn:name":"Dijia Goumenxia",
    "gn:population":0,
    "gn:timezone":"Asia/Shanghai",
    "iso:country":"CN",
    "name:zho_x_preferred":[
        "\u7fdf\u5bb6\u6c9f\u95e8\u4e0b"
    ],
    "wof:name":"Dijia Goumenxia",
    "wof:placetype":"locality"
},
  "geometry": {"coordinates":[106.89158,34.51452],"type":"Point"}
}