{
  "type": "Feature",
  "properties": {
    "gn:admin1_code":"12",
    "gn:asciiname":"Shahe",
    "gn:cc2":"CN",
    "gn:country_code":"CN",
    "gn:dem":300,
    "gn:feature_class":"P",
    "gn:feature_code":"PPL",
    "gn:name":"Shahe",
    "gn:population":0,
    "gn:timezone":"Asia/Shanghai",
    "iso:country":"CN",
    "name:und_x_variant":[
        "Sha-ho-tien",
        "Shahe"
    ],
    "wof:name":"Shahe",
    "wof:placetype":"locality"
},
  "geometry": {"coordinates":[111.22111,32.20694],"type":"Point"}
}