{
  "type": "Feature",
  "properties": {
    "gn:admin1_code":"21.0",
    "gn:asciiname":"Butai",
    "gn:country_code":"CN",
    "gn:dem":1618,
    "gn:feature_class":"P",
    "gn:feature_code":"PPL",
    "gn:name":"Butai",
    "gn:population":0,
    "gn:timezone":"Asia/Shanghai",
    "iso:country":"CN",
    "name:zho_x_preferred":[
        "\u5821\u53f0"
    ],
    "wof:name":"Butai",
    "wof:placetype":"locality"
},
  "geometry": {"coordinates":[105.86,36.6111],"type":"Point"}
}