{
  "type": "Feature",
  "properties": {
    "gn:admin1_code":"25",
    "gn:asciiname":"Jiuxian",
    "gn:cc2":"CN",
    "gn:country_code":"CN",
    "gn:dem":129,
    "gn:feature_class":"P",
    "gn:feature_code":"PPL",
    "gn:name":"Jiuxian",
    "gn:population":0,
    "gn:timezone":"Asia/Shanghai",
    "iso:country":"CN",
    "name:ceb_x_preferred":[
        "Jiuxian"
    ],
    "name:deu_x_preferred":[
        "Jiuxian"
    ],
    "name:swe_x_preferred":[
        "Jiuxian"
    ],
    "name:und_x_variant":[
        "Chiu-hsien",
        "Chiu-hsien-chuang"
    ],
    "wof:name":"Jiuxian",
    "wof:placetype":"locality"
},
  "geometry": {"coordinates":[117.21666999999999,36.15],"type":"Point"}
}