{
  "type": "Feature",
  "properties": {
    "gn:admin1_code":"29.0",
    "gn:asciiname":"Bifeng",
    "gn:country_code":"CN",
    "gn:dem":1356,
    "gn:feature_class":"P",
    "gn:feature_code":"PPL",
    "gn:name":"Bifeng",
    "gn:population":0,
    "gn:timezone":"Asia/Shanghai",
    "iso:country":"CN",
    "name:zho_x_preferred":[
        "\u78a7\u5cf0"
    ],
    "wof:name":"Bifeng",
    "wof:placetype":"locality"
},
  "geometry": {"coordinates":[101.01900000000001,26.4352],"type":"Point"}
}