{
  "type": "Feature",
  "properties": {
    "gn:admin1_code":"32.0",
    "gn:asciiname":"Yujia",
    "gn:country_code":"CN",
    "gn:dem":2079,
    "gn:feature_class":"P",
    "gn:feature_code":"PPL",
    "gn:name":"Yujia",
    "gn:population":0,
    "gn:timezone":"Asia/Shanghai",
    "iso:country":"CN",
    "name:zho_x_preferred":[
        "\u4e8e\u5bb6"
    ],
    "wof:name":"Yujia",
    "wof:placetype":"locality"
},
  "geometry": {"coordinates":[102.03916,28.03758],"type":"Point"}
}