{
  "type": "Feature",
  "properties": {
    "gn:admin1_code":"10.0",
    "gn:asciiname":"Daliushu",
    "gn:country_code":"CN",
    "gn:dem":328,
    "gn:feature_class":"P",
    "gn:feature_code":"PPL",
    "gn:name":"Daliushu",
    "gn:population":0,
    "gn:timezone":"Asia/Shanghai",
    "iso:country":"CN",
    "name:und_x_variant":[
        "\u5927\u67f3\u6811"
    ],
    "wof:name":"Daliushu",
    "wof:placetype":"locality"
},
  "geometry": {"coordinates":[114.11176,38.90507],"type":"Point"}
}