{
  "type": "Feature",
  "properties": {
    "gn:admin1_code":"33.0",
    "gn:asciiname":"Gaoxin",
    "gn:country_code":"CN",
    "gn:dem":642,
    "gn:feature_class":"P",
    "gn:feature_code":"PPL",
    "gn:name":"Gaoxin",
    "gn:population":0,
    "gn:timezone":"Asia/Shanghai",
    "iso:country":"CN",
    "name:zho_x_preferred":[
        "\u9ad8\u65b0"
    ],
    "wof:name":"Gaoxin",
    "wof:placetype":"locality"
},
  "geometry": {"coordinates":[108.97851,30.82745],"type":"Point"}
}