{
  "type": "Feature",
  "properties": {
    "gn:admin1_code":"11.0",
    "gn:asciiname":"Huangnanchong",
    "gn:country_code":"CN",
    "gn:dem":43,
    "gn:feature_class":"P",
    "gn:feature_code":"PPL",
    "gn:name":"Huangnanchong",
    "gn:population":0,
    "gn:timezone":"Asia/Shanghai",
    "iso:country":"CN",
    "name:zho_x_preferred":[
        "\u9ec4\u5357\u51b2"
    ],
    "wof:name":"Huangnanchong",
    "wof:placetype":"locality"
},
  "geometry": {"coordinates":[112.03569,28.59043],"type":"Point"}
}