{
  "type": "Feature",
  "properties": {
    "gn:admin1_code":"1.0",
    "gn:asciiname":"Shangshan Menli",
    "gn:country_code":"CN",
    "gn:dem":83,
    "gn:feature_class":"P",
    "gn:feature_code":"PPL",
    "gn:name":"Shangshan Menli",
    "gn:population":0,
    "gn:timezone":"Asia/Shanghai",
    "iso:country":"CN",
    "name:zho_x_preferred":[
        "\u4e0a\u5c71\u95e8\u91cc"
    ],
    "wof:name":"Shangshan Menli",
    "wof:placetype":"locality"
},
  "geometry": {"coordinates":[119.34219,31.15673],"type":"Point"}
}