{
  "type": "Feature",
  "properties": {
    "gn:admin1_code":"14",
    "gn:asciiname":"Yamu",
    "gn:country_code":"CN",
    "gn:dem":4474,
    "gn:feature_class":"P",
    "gn:feature_code":"PPL",
    "gn:name":"Yamu",
    "gn:population":0,
    "gn:timezone":"Asia/Urumqi",
    "iso:country":"CN",
    "name:zho_x_preferred":[
        "\u4e9a\u6728"
    ],
    "wof:name":"Yamu",
    "wof:placetype":"locality"
},
  "geometry": {"coordinates":[89.5179,29.6232],"type":"Point"}
}