{
  "type": "Feature",
  "properties": {
    "gn:admin1_code":"19",
    "gn:asciiname":"Ximu",
    "gn:country_code":"CN",
    "gn:dem":77,
    "gn:feature_class":"P",
    "gn:feature_code":"PPLA4",
    "gn:name":"Ximu",
    "gn:population":0,
    "gn:timezone":"Asia/Shanghai",
    "iso:country":"CN",
    "name:und_x_variant":[
        "Hsi-shui-ch\u2019eng",
        "Ximucheng",
        "Hsin-mu-ch\u2019eng",
        "Shimucheng",
        "Hsi-mu-ch\u2019eng",
        "Ximu Zhen",
        "Ximu"
    ],
    "name:zho_x_preferred":[
        "\u6790\u6728"
    ],
    "name:zho_x_variant":[
        "\u6790\u6728\u9547"
    ],
    "wof:name":"Ximu",
    "wof:placetype":"locality"
},
  "geometry": {"coordinates":[122.90743000000001,40.6997],"type":"Point"}
}