{
  "type": "Feature",
  "properties": {
    "gn:admin1_code":"16.0",
    "gn:asciiname":"Zhuziling",
    "gn:country_code":"CN",
    "gn:dem":14,
    "gn:feature_class":"P",
    "gn:feature_code":"PPL",
    "gn:name":"Zhuziling",
    "gn:population":0,
    "gn:timezone":"Asia/Shanghai",
    "iso:country":"CN",
    "name:zho_x_preferred":[
        "\u7af9\u5b50\u5cad"
    ],
    "wof:name":"Zhuziling",
    "wof:placetype":"locality"
},
  "geometry": {"coordinates":[108.714,22.0834],"type":"Point"}
}