{
  "type": "Feature",
  "properties": {
    "gn:admin1_code":"4.0",
    "gn:asciiname":"Gaojiatangcun",
    "gn:country_code":"CN",
    "gn:dem":0,
    "gn:feature_class":"P",
    "gn:feature_code":"PPL",
    "gn:name":"Gaojiatangcun",
    "gn:population":0,
    "gn:timezone":"Asia/Shanghai",
    "iso:country":"CN",
    "name:zho_x_preferred":[
        "\u9ad8\u5bb6\u8361\u6751"
    ],
    "wof:name":"Gaojiatangcun",
    "wof:placetype":"locality"
},
  "geometry": {"coordinates":[119.91710999999999,32.88593],"type":"Point"}
}