{
  "type": "Feature",
  "properties": {
    "gn:admin1_code":"11.0",
    "gn:asciiname":"Huangyegang",
    "gn:country_code":"CN",
    "gn:dem":86,
    "gn:feature_class":"P",
    "gn:feature_code":"PPL",
    "gn:name":"Huangyegang",
    "gn:population":0,
    "gn:timezone":"Asia/Shanghai",
    "iso:country":"CN",
    "name:zho_x_preferred":[
        "Huangyegang"
    ],
    "name:zho_x_variant":[
        "\u9ec4\u53f6\u5c97"
    ],
    "wof:name":"Huangyegang",
    "wof:placetype":"locality"
},
  "geometry": {"coordinates":[111.56748,29.18568],"type":"Point"}
}