{
  "type": "Feature",
  "properties": {
    "gn:admin1_code":"19.0",
    "gn:asciiname":"Yangjia Buzi",
    "gn:country_code":"CN",
    "gn:dem":262,
    "gn:feature_class":"P",
    "gn:feature_code":"PPL",
    "gn:name":"Yangjia Buzi",
    "gn:population":0,
    "gn:timezone":"Asia/Shanghai",
    "iso:country":"CN",
    "name:zho_x_preferred":[
        "\u6768\u5bb6\u5821\u5b50"
    ],
    "wof:name":"Yangjia Buzi",
    "wof:placetype":"locality"
},
  "geometry": {"coordinates":[124.44499999999999,42.4181],"type":"Point"}
}