{
  "type": "Feature",
  "properties": {
    "gn:admin1_code":"2",
    "gn:asciiname":"Daijiafan",
    "gn:country_code":"CN",
    "gn:dem":253,
    "gn:feature_class":"P",
    "gn:feature_code":"PPL",
    "gn:name":"Daijiafan",
    "gn:population":0,
    "gn:timezone":"Asia/Shanghai",
    "iso:country":"CN",
    "name:und_x_variant":[
        "\u6234\u5bb6\u7548",
        "Daijiafan"
    ],
    "wof:name":"Daijiafan",
    "wof:placetype":"locality"
},
  "geometry": {"coordinates":[119.81731000000001,29.71712],"type":"Point"}
}