{
  "type": "Feature",
  "properties": {
    "gn:admin1_code":"18",
    "gn:asciiname":"Malongtian",
    "gn:country_code":"CN",
    "gn:dem":1135,
    "gn:feature_class":"P",
    "gn:feature_code":"PPL",
    "gn:name":"Malongtian",
    "gn:population":0,
    "gn:timezone":"Asia/Shanghai",
    "iso:country":"CN",
    "name:zho_x_preferred":[
        "\u9a6c\u9f99\u7530"
    ],
    "wof:name":"Malongtian",
    "wof:placetype":"locality"
},
  "geometry": {"coordinates":[106.316,25.8105],"type":"Point"}
}