{
  "type": "Feature",
  "properties": {
    "gn:admin1_code":"25.0",
    "gn:asciiname":"Xiaohe Dongcun",
    "gn:country_code":"CN",
    "gn:dem":2,
    "gn:feature_class":"P",
    "gn:feature_code":"PPL",
    "gn:name":"Xiaohe Dongcun",
    "gn:population":0,
    "gn:timezone":"Asia/Shanghai",
    "iso:country":"CN",
    "name:zho_x_preferred":[
        "\u5c0f\u6cb3\u4e1c\u6751"
    ],
    "wof:name":"Xiaohe Dongcun",
    "wof:placetype":"locality"
},
  "geometry": {"coordinates":[120.01129,35.84492],"type":"Point"}
}