{
  "type": "Feature",
  "properties": {
    "gn:admin1_code":"25",
    "gn:asciiname":"Donggouyu",
    "gn:country_code":"CN",
    "gn:dem":151,
    "gn:feature_class":"P",
    "gn:feature_code":"PPL",
    "gn:name":"Donggouyu",
    "gn:population":0,
    "gn:timezone":"Asia/Shanghai",
    "iso:country":"CN",
    "name:zho_x_preferred":[
        "\u4e1c\u6c9f\u5cea"
    ],
    "wof:name":"Donggouyu",
    "wof:placetype":"locality"
},
  "geometry": {"coordinates":[117.783,35.1497],"type":"Point"}
}