{
  "type": "Feature",
  "properties": {
    "gn:admin1_code":"4.0",
    "gn:asciiname":"Xujia Bandai",
    "gn:country_code":"CN",
    "gn:dem":6,
    "gn:feature_class":"P",
    "gn:feature_code":"PPL",
    "gn:name":"Xujia Bandai",
    "gn:population":0,
    "gn:timezone":"Asia/Shanghai",
    "iso:country":"CN",
    "name:zho_x_preferred":[
        "\u5f90\u5bb6\u534a\u5788"
    ],
    "wof:name":"Xujia Bandai",
    "wof:placetype":"locality"
},
  "geometry": {"coordinates":[120.30701000000001,32.05484000000001],"type":"Point"}
}