{
  "type": "Feature",
  "properties": {
    "gn:admin1_code":"11.0",
    "gn:asciiname":"Modaoyuan",
    "gn:country_code":"CN",
    "gn:dem":667,
    "gn:feature_class":"P",
    "gn:feature_code":"PPL",
    "gn:name":"Modaoyuan",
    "gn:population":0,
    "gn:timezone":"Asia/Shanghai",
    "iso:country":"CN",
    "name:zho_x_preferred":[
        "\u78e8\u5200\u6c85"
    ],
    "wof:name":"Modaoyuan",
    "wof:placetype":"locality"
},
  "geometry": {"coordinates":[112.09768,25.1012],"type":"Point"}
}