{
  "type": "Feature",
  "properties": {
    "gn:admin1_code":"15.0",
    "gn:asciiname":"Fanjiayuan",
    "gn:country_code":"CN",
    "gn:dem":1699,
    "gn:feature_class":"P",
    "gn:feature_code":"PPL",
    "gn:name":"Fanjiayuan",
    "gn:population":0,
    "gn:timezone":"Asia/Shanghai",
    "iso:country":"CN",
    "name:zho_x_preferred":[
        "\u8303\u5bb6\u9662"
    ],
    "wof:name":"Fanjiayuan",
    "wof:placetype":"locality"
},
  "geometry": {"coordinates":[106.468,34.1259],"type":"Point"}
}