{
  "type": "Feature",
  "properties": {
    "gn:admin1_code":"5.0",
    "gn:asciiname":"Xinyicun",
    "gn:country_code":"CN",
    "gn:dem":174,
    "gn:feature_class":"P",
    "gn:feature_code":"PPL",
    "gn:name":"Xinyicun",
    "gn:population":0,
    "gn:timezone":"Asia/Shanghai",
    "iso:country":"CN",
    "name:zho_x_preferred":[
        "\u65b0\u4e49\u6751"
    ],
    "wof:name":"Xinyicun",
    "wof:placetype":"locality"
},
  "geometry": {"coordinates":[126.68227,44.80915],"type":"Point"}
}