{
  "type": "Feature",
  "properties": {
    "gn:admin1_code":"12.0",
    "gn:asciiname":"Xiabeilong",
    "gn:country_code":"CN",
    "gn:dem":29,
    "gn:feature_class":"P",
    "gn:feature_code":"PPL",
    "gn:name":"Xiabeilong",
    "gn:population":0,
    "gn:timezone":"Asia/Shanghai",
    "iso:country":"CN",
    "name:zho_x_preferred":[
        "Xiabeilong"
    ],
    "name:zho_x_variant":[
        "\u4e0b\u5317\u5785"
    ],
    "wof:name":"Xiabeilong",
    "wof:placetype":"locality"
},
  "geometry": {"coordinates":[115.33817000000001,29.83318],"type":"Point"}
}