{
  "type": "Feature",
  "properties": {
    "gn:admin1_code":"19",
    "gn:asciiname":"Damintun",
    "gn:cc2":"CN",
    "gn:country_code":"CN",
    "gn:dem":29,
    "gn:feature_class":"P",
    "gn:feature_code":"PPL",
    "gn:name":"Damintun",
    "gn:population":0,
    "gn:timezone":"Asia/Shanghai",
    "iso:country":"CN",
    "name:und_x_variant":[
        "Ta-min-t\u2019un",
        "Damintun"
    ],
    "wof:name":"Damintun",
    "wof:placetype":"locality"
},
  "geometry": {"coordinates":[122.94611,41.84944],"type":"Point"}
}