{
  "type": "Feature",
  "properties": {
    "gn:admin1_code":"14.0",
    "gn:asciiname":"Jiangga",
    "gn:country_code":"CN",
    "gn:dem":3982,
    "gn:feature_class":"P",
    "gn:feature_code":"PPL",
    "gn:name":"Jiangga",
    "gn:population":0,
    "gn:timezone":"Asia/Urumqi",
    "iso:country":"CN",
    "name:zho_x_preferred":[
        "\u6c5f\u560e"
    ],
    "wof:name":"Jiangga",
    "wof:placetype":"locality"
},
  "geometry": {"coordinates":[88.4306,29.0313],"type":"Point"}
}