{
  "type": "Feature",
  "properties": {
    "gn:admin1_code":"20.0",
    "gn:asciiname":"Zuofeng",
    "gn:country_code":"CN",
    "gn:dem":1482,
    "gn:feature_class":"P",
    "gn:feature_code":"PPL",
    "gn:name":"Zuofeng",
    "gn:population":0,
    "gn:timezone":"Asia/Shanghai",
    "iso:country":"CN",
    "name:und_x_variant":[
        "\u5ea7\u5cf0"
    ],
    "wof:name":"Zuofeng",
    "wof:placetype":"locality"
},
  "geometry": {"coordinates":[111.98157,39.89638],"type":"Point"}
}