{
  "type": "Feature",
  "properties": {
    "gn:admin1_code":"29.0",
    "gn:asciiname":"Xiaocunzi",
    "gn:country_code":"CN",
    "gn:dem":2045,
    "gn:feature_class":"P",
    "gn:feature_code":"PPL",
    "gn:name":"Xiaocunzi",
    "gn:population":0,
    "gn:timezone":"Asia/Shanghai",
    "iso:country":"CN",
    "name:zho_x_preferred":[
        "\u5c0f\u6751\u5b50"
    ],
    "wof:name":"Xiaocunzi",
    "wof:placetype":"locality"
},
  "geometry": {"coordinates":[104.136,25.8175],"type":"Point"}
}