{
  "type": "Feature",
  "properties": {
    "gn:admin1_code":"4.0",
    "gn:asciiname":"Fudu",
    "gn:country_code":"CN",
    "gn:dem":6,
    "gn:feature_class":"P",
    "gn:feature_code":"PPL",
    "gn:name":"Fudu",
    "gn:population":0,
    "gn:timezone":"Asia/Shanghai",
    "iso:country":"CN",
    "name:zho_x_preferred":[
        "Fudu"
    ],
    "name:zho_x_variant":[
        "\u5bcc\u6e0e"
    ],
    "wof:name":"Fudu",
    "wof:placetype":"locality"
},
  "geometry": {"coordinates":[121.07641,31.65222],"type":"Point"}
}