{
  "type": "Feature",
  "properties": {
    "gn:admin1_code":"8.0",
    "gn:asciiname":"Yulin",
    "gn:country_code":"CN",
    "gn:dem":196,
    "gn:feature_class":"P",
    "gn:feature_code":"PPLA4",
    "gn:name":"Yulin",
    "gn:population":0,
    "gn:timezone":"Asia/Shanghai",
    "iso:country":"CN",
    "name:ceb_x_preferred":[
        "Yulin"
    ],
    "name:deu_x_preferred":[
        "Yulin"
    ],
    "name:eus_x_preferred":[
        "Yulin"
    ],
    "name:fin_x_preferred":[
        "Yulin"
    ],
    "name:fra_x_preferred":[
        "Yulin"
    ],
    "name:kor_x_preferred":[
        "\uc704\ub9b0\uc2dc"
    ],
    "name:nld_x_preferred":[
        "Yulin"
    ],
    "name:nor_x_preferred":[
        "Yulin"
    ],
    "name:pol_x_preferred":[
        "Yulin"
    ],
    "name:rus_x_preferred":[
        "\u042e\u0439\u043b\u0438\u043d\u044c"
    ],
    "name:spa_x_preferred":[
        "Yulin"
    ],
    "name:swe_x_preferred":[
        "Yulin"
    ],
    "name:tur_x_preferred":[
        "Yulin"
    ],
    "name:und_x_variant":[
        "Yulin Xiang"
    ],
    "name:zho_x_preferred":[
        "\u80b2\u6797"
    ],
    "name:zho_x_variant":[
        "\u80b2\u6797\u4e61"
    ],
    "wof:name":"Yulin",
    "wof:placetype":"locality"
},
  "geometry": {"coordinates":[125.63021000000001,47.12978],"type":"Point"}
}