{
  "type": "Feature",
  "properties": {
    "gn:admin1_code":"8.0",
    "gn:asciiname":"Yulin",
    "gn:country_code":"CN",
    "gn:dem":196,
    "gn:feature_class":"P",
    "gn:feature_code":"PPLA4",
    "gn:name":"Yulin",
    "gn:population":0,
    "gn:timezone":"Asia/Shanghai",
    "iso:country":"CN",
    "name:und_x_variant":[
        "Yulin Xiang"
    ],
    "name:zho_x_preferred":[
        "\u80b2\u6797"
    ],
    "name:zho_x_variant":[
        "\u80b2\u6797\u4e61"
    ],
    "wof:name":"Yulin",
    "wof:placetype":"locality"
},
  "geometry": {"coordinates":[125.63021000000001,47.12978],"type":"Point"}
}