{
  "type": "Feature",
  "properties": {
    "iso:country":"CN",
    "qs:name":"\u4e7e\u53bf",
    "qs:name_adm0":"\u4e2d\u570b",
    "qs:name_adm1":"\u965d\u897f\u7701",
    "qs:photos":28,
    "qs:photos_1k":6,
    "qs:photos_9k":1,
    "qs:photos_9r":2,
    "qs:photos_all":28,
    "qs:photos_sr":2,
    "qs:placetype":"LocalAdmin",
    "qs:pop_sr":"0",
    "wd:wordcount":81,
    "wof:name":"\u4e7e\u53bf",
    "wof:placetype":"localadmin"
},
  "geometry": {"coordinates":[108.2139775,34.574519],"type":"Point"}
}