{
  "type": "Feature",
  "properties": {
    "iso:country":"CN",
    "name:ara_x_preferred":[
        "\u0645\u0642\u0627\u0637\u0639\u0629 \u062a\u0634\u064a\u0627\u0646"
    ],
    "name:ben_x_preferred":[
        "\u0995\u09bf\u09af\u09bc\u09be\u09a8 \u0995\u09be\u0989\u09a8\u09cd\u099f\u09bf"
    ],
    "name:cat_x_preferred":[
        "Qian"
    ],
    "name:ceb_x_preferred":[
        "Qian Xian"
    ],
    "name:dan_x_preferred":[
        "Qian"
    ],
    "name:deu_x_preferred":[
        "Qian"
    ],
    "name:ell_x_preferred":[
        "\u039a\u03b9\u03ac\u03bd"
    ],
    "name:eng_x_preferred":[
        "Qian County"
    ],
    "name:fas_x_preferred":[
        "\u0634\u0647\u0631\u0633\u062a\u0627\u0646 \u0686\u06cc\u0627\u0646"
    ],
    "name:fin_x_preferred":[
        "Qianin kunta"
    ],
    "name:gan_x_preferred":[
        "\u4e7e\u53bf"
    ],
    "name:guj_x_preferred":[
        "\u0a95\u0acd\u0ab5\u0abf\u0a85\u0aa8 \u0a95\u0abe\u0a89\u0aa8\u0acd\u0a9f\u0ac0"
    ],
    "name:hin_x_preferred":[
        "\u0915\u093f\u092f\u093e\u0928 \u0915\u093e\u0909\u0902\u091f\u0940"
    ],
    "name:ind_x_preferred":[
        "Qian County"
    ],
    "name:jpn_x_preferred":[
        "\u4e7e\u770c"
    ],
    "name:kan_x_preferred":[
        "\u0c95\u0cbf\u0caf\u0cbe\u0ca8\u0ccd \u0c95\u0ccc\u0c82\u0c9f\u0cbf"
    ],
    "name:kor_x_preferred":[
        "\uccb8\ud604"
    ],
    "name:lav_x_preferred":[
        "Ciano apgabals"
    ],
    "name:lit_x_preferred":[
        "\u0104iano sritis"
    ],
    "name:mar_x_preferred":[
        "\u0915\u094d\u0935\u093f\u092f\u0928 \u0915\u093e\u0909\u0902\u091f\u0940"
    ],
    "name:msa_x_preferred":[
        "Qian County"
    ],
    "name:nan_x_preferred":[
        "Khi\u00e2n-ko\u0101n"
    ],
    "name:nld_x_preferred":[
        "Qian"
    ],
    "name:nob_x_preferred":[
        "Qian"
    ],
    "name:pol_x_preferred":[
        "Powiat Qian"
    ],
    "name:por_x_preferred":[
        "Qianxian"
    ],
    "name:rus_x_preferred":[
        "\u0426\u044f\u043d\u044c\u0441\u044f\u043d\u044c"
    ],
    "name:sin_x_preferred":[
        "\u0d9a\u0dd4\u0d89\u0d87\u0db1\u0dca \u0db4\u0dc5\u0dcf\u0dad"
    ],
    "name:spa_x_preferred":[
        "Qian"
    ],
    "name:swe_x_preferred":[
        "Qian"
    ],
    "name:tel_x_preferred":[
        "\u0c15\u0c3f\u0c2f\u0c3e\u0c28\u0c4d \u0c15\u0c4c\u0c02\u0c1f\u0c40"
    ],
    "name:tha_x_preferred":[
        "\u0e40\u0e04\u0e35\u0e22\u0e19 \u0e0b\u0e34\u0e15\u0e35\u0e49"
    ],
    "name:tur_x_preferred":[
        "Qian"
    ],
    "name:ukr_x_preferred":[
        "\u041e\u043a\u0440\u0443\u0433 \u0426\u044f\u043d\u044c\u0441\u044f\u043d\u044c"
    ],
    "name:urd_x_preferred":[
        "\u0642\u06cc\u0627\u0646 \u06a9\u0627\u0624\u0646\u0679\u06cc"
    ],
    "name:vie_x_preferred":[
        "C\u00e0n"
    ],
    "name:wuu_x_preferred":[
        "\u4e7e\u53bf"
    ],
    "name:yue_x_preferred":[
        "\u4e7e\u7e23"
    ],
    "name:zho_x_preferred":[
        "\u4e7e\u53bf"
    ],
    "qs:name":"\u4e7e\u53bf",
    "qs:name_adm0":"\u4e2d\u570b",
    "qs:name_adm1":"\u965d\u897f\u7701",
    "qs:photos":28,
    "qs:photos_1k":6,
    "qs:photos_9k":1,
    "qs:photos_9r":2,
    "qs:photos_all":28,
    "qs:photos_sr":2,
    "qs:placetype":"LocalAdmin",
    "qs:pop_sr":"0",
    "wd:wordcount":81,
    "wof:name":"\u4e7e\u53bf",
    "wof:placetype":"localadmin"
},
  "geometry": {"coordinates":[108.2139775,34.574519],"type":"Point"}
}