{
  "type": "Feature",
  "properties": {
    "gn:admin1_code":"9.0",
    "gn:asciiname":"Hedazhuang",
    "gn:country_code":"CN",
    "gn:dem":232,
    "gn:feature_class":"P",
    "gn:feature_code":"PPL",
    "gn:name":"Hedazhuang",
    "gn:population":0,
    "gn:timezone":"Asia/Shanghai",
    "iso:country":"CN",
    "name:zho_x_preferred":[
        "\u4f55\u5927\u5e84"
    ],
    "wof:name":"Hedazhuang",
    "wof:placetype":"locality"
},
  "geometry": {"coordinates":[113.69982,32.68537],"type":"Point"}
}