{
  "type": "Feature",
  "properties": {
    "gn:admin1_code":"3.0",
    "gn:asciiname":"Yangwuchang",
    "gn:country_code":"CN",
    "gn:dem":64,
    "gn:feature_class":"P",
    "gn:feature_code":"PPL",
    "gn:name":"Yangwuchang",
    "gn:population":0,
    "gn:timezone":"Asia/Shanghai",
    "iso:country":"CN",
    "name:und_x_variant":[
        "\u6768\u5c4b\u573a"
    ],
    "wof:name":"Yangwuchang",
    "wof:placetype":"locality"
},
  "geometry": {"coordinates":[116.4114,29.64047],"type":"Point"}
}