{
  "type": "Feature",
  "properties": {
    "gn:admin1_code":"7",
    "gn:asciiname":"Bao'an",
    "gn:country_code":"CN",
    "gn:dem":25,
    "gn:feature_class":"P",
    "gn:feature_code":"PPL",
    "gn:name":"Bao\u2019an",
    "gn:population":0,
    "gn:timezone":"Asia/Shanghai",
    "iso:country":"CN",
    "name:ceb_x_preferred":[
        "Bao'an"
    ],
    "name:deu_x_preferred":[
        "Bao\u2019an"
    ],
    "name:nor_x_preferred":[
        "Bao'an"
    ],
    "name:pol_x_preferred":[
        "Bao\u2019an"
    ],
    "name:zho_x_preferred":[
        "\u4fdd\u5b89"
    ],
    "wof:name":"Bao'an",
    "wof:placetype":"locality"
},
  "geometry": {"coordinates":[117.83999,24.07663],"type":"Point"}
}