{
  "type": "Feature",
  "properties": {
    "gn:admin1_code":"29",
    "gn:asciiname":"Maidichong",
    "gn:country_code":"CN",
    "gn:dem":1872,
    "gn:feature_class":"P",
    "gn:feature_code":"PPL",
    "gn:name":"Maidichong",
    "gn:population":0,
    "gn:timezone":"Asia/Shanghai",
    "iso:country":"CN",
    "name:zho_x_preferred":[
        "\u9ea6\u5730\u51b2"
    ],
    "wof:name":"Maidichong",
    "wof:placetype":"locality"
},
  "geometry": {"coordinates":[101.27500000000001,24.6826],"type":"Point"}
}