{
  "type": "Feature",
  "properties": {
    "gn:admin1_code":"8.0",
    "gn:asciiname":"Chenpaicun",
    "gn:country_code":"CN",
    "gn:dem":116,
    "gn:feature_class":"P",
    "gn:feature_code":"PPL",
    "gn:name":"Chenpaicun",
    "gn:population":0,
    "gn:timezone":"Asia/Shanghai",
    "iso:country":"CN",
    "name:zho_x_preferred":[
        "\u9648\u6392\u6751"
    ],
    "wof:name":"Chenpaicun",
    "wof:placetype":"locality"
},
  "geometry": {"coordinates":[126.82528000000001,46.00122],"type":"Point"}
}