{
  "type": "Feature",
  "properties": {
    "gn:admin1_code":"15.0",
    "gn:asciiname":"Yangou",
    "gn:country_code":"CN",
    "gn:dem":1913,
    "gn:feature_class":"P",
    "gn:feature_code":"PPL",
    "gn:name":"Yangou",
    "gn:population":0,
    "gn:timezone":"Asia/Shanghai",
    "iso:country":"CN",
    "name:zho_x_preferred":[
        "\u76d0\u6c9f"
    ],
    "wof:name":"Yangou",
    "wof:placetype":"locality"
},
  "geometry": {"coordinates":[104.473,35.80300000000001],"type":"Point"}
}