{
  "type": "Feature",
  "properties": {
    "gn:admin1_code":"3.0",
    "gn:asciiname":"Lanfen",
    "gn:country_code":"CN",
    "gn:dem":185,
    "gn:feature_class":"P",
    "gn:feature_code":"PPL",
    "gn:name":"Lanfen",
    "gn:population":0,
    "gn:timezone":"Asia/Shanghai",
    "iso:country":"CN",
    "name:und_x_variant":[
        "\u5170\u82ac"
    ],
    "wof:name":"Lanfen",
    "wof:placetype":"locality"
},
  "geometry": {"coordinates":[115.19138,26.17466],"type":"Point"}
}