{
  "type": "Feature",
  "properties": {
    "gn:admin1_code":"30",
    "gn:asciiname":"Yongle",
    "gn:country_code":"CN",
    "gn:dem":44,
    "gn:feature_class":"P",
    "gn:feature_code":"PPL",
    "gn:name":"Yongle",
    "gn:population":0,
    "gn:timezone":"Asia/Urumqi",
    "iso:country":"CN",
    "name:zho_x_preferred":[
        "\u6c38\u4e50"
    ],
    "wof:name":"Yongle",
    "wof:placetype":"locality"
},
  "geometry": {"coordinates":[111.14488,21.78636],"type":"Point"}
}