{
  "type": "Feature",
  "properties": {
    "gn:admin1_code":"20",
    "gn:asciiname":"Yonghong Linchang",
    "gn:country_code":"CN",
    "gn:dem":817,
    "gn:feature_class":"P",
    "gn:feature_code":"PPLF",
    "gn:name":"Yonghong Linchang",
    "gn:population":0,
    "gn:timezone":"Asia/Shanghai",
    "iso:country":"CN",
    "wof:name":"Yonghong Linchang",
    "wof:placetype":"locality"
},
  "geometry": {"coordinates":[120.87222,51.19972],"type":"Point"}
}