{
  "type": "Feature",
  "properties": {
    "gn:admin1_code":"30",
    "gn:asciiname":"Dachi Nongchang",
    "gn:country_code":"CN",
    "gn:dem":128,
    "gn:feature_class":"P",
    "gn:feature_code":"PPLF",
    "gn:name":"Dachi Nongchang",
    "gn:population":0,
    "gn:timezone":"Asia/Shanghai",
    "iso:country":"CN",
    "name:zho_x_preferred":[
        "\u5927\u6c60\u519c\u573a"
    ],
    "wof:name":"Dachi Nongchang",
    "wof:placetype":"locality"
},
  "geometry": {"coordinates":[116.3519,23.38845],"type":"Point"}
}