{
  "type": "Feature",
  "properties": {
    "gn:admin1_code":"16.0",
    "gn:asciiname":"Citai",
    "gn:country_code":"CN",
    "gn:dem":785,
    "gn:feature_class":"P",
    "gn:feature_code":"PPL",
    "gn:name":"Citai",
    "gn:population":0,
    "gn:timezone":"Asia/Shanghai",
    "iso:country":"CN",
    "name:zho_x_preferred":[
        "\u6148\u53f0"
    ],
    "wof:name":"Citai",
    "wof:placetype":"locality"
},
  "geometry": {"coordinates":[106.29300000000001,23.0393],"type":"Point"}
}