{
  "type": "Feature",
  "properties": {
    "gn:admin1_code":"10.0",
    "gn:asciiname":"Laomumiao",
    "gn:country_code":"CN",
    "gn:dem":5,
    "gn:feature_class":"P",
    "gn:feature_code":"PPL",
    "gn:name":"Laomumiao",
    "gn:population":0,
    "gn:timezone":"Asia/Shanghai",
    "iso:country":"CN",
    "name:zho_x_preferred":[
        "\u8001\u6bcd\u5e99"
    ],
    "wof:name":"Laomumiao",
    "wof:placetype":"locality"
},
  "geometry": {"coordinates":[118.23224,39.36433],"type":"Point"}
}