{
  "type": "Feature",
  "properties": {
    "gn:admin1_code":"25.0",
    "gn:asciiname":"Shiquantou",
    "gn:country_code":"CN",
    "gn:dem":58,
    "gn:feature_class":"P",
    "gn:feature_code":"PPL",
    "gn:name":"Shiquantou",
    "gn:population":0,
    "gn:timezone":"Asia/Shanghai",
    "iso:country":"CN",
    "name:zho_x_preferred":[
        "\u77f3\u6cc9\u5934"
    ],
    "wof:name":"Shiquantou",
    "wof:placetype":"locality"
},
  "geometry": {"coordinates":[120.52481,36.49181],"type":"Point"}
}