{
  "type": "Feature",
  "properties": {
    "gn:admin1_code":"24",
    "gn:asciiname":"Fengzijian",
    "gn:country_code":"CN",
    "gn:dem":1304,
    "gn:feature_class":"P",
    "gn:feature_code":"PPL",
    "gn:name":"Fengzijian",
    "gn:population":0,
    "gn:timezone":"Asia/Shanghai",
    "iso:country":"CN",
    "name:und_x_variant":[
        "Feng-tzu-chien",
        "Fengzijian"
    ],
    "name:zho_x_preferred":[
        "\u5cf0\u5b50\u6da7"
    ],
    "wof:name":"Fengzijian",
    "wof:placetype":"locality"
},
  "geometry": {"coordinates":[112.95687,40.04594],"type":"Point"}
}