{
  "type": "Feature",
  "properties": {
    "gn:admin1_code":"25",
    "gn:asciiname":"Lijiazhaicun",
    "gn:country_code":"CN",
    "gn:dem":77,
    "gn:feature_class":"P",
    "gn:feature_code":"PPL",
    "gn:name":"Lijiazhaicun",
    "gn:population":0,
    "gn:timezone":"Asia/Shanghai",
    "iso:country":"CN",
    "name:und_x_variant":[
        "Li-chia-chai",
        "Lijiazhai",
        "Lijiazhaicun"
    ],
    "name:zho_x_preferred":[
        "\u5386\u5bb6\u5be8"
    ],
    "name:zho_x_variant":[
        "\u5389\u5bb6\u5be8",
        "\u5389\u5bb6\u5be8\u6751"
    ],
    "wof:name":"Lijiazhaicun",
    "wof:placetype":"locality"
},
  "geometry": {"coordinates":[119.08874,35.24658],"type":"Point"}
}