{
  "type": "Feature",
  "properties": {
    "gn:admin1_code":"20.0",
    "gn:asciiname":"Bayan Wula",
    "gn:country_code":"CN",
    "gn:dem":614,
    "gn:feature_class":"P",
    "gn:feature_code":"PPL",
    "gn:name":"Bayan Wula",
    "gn:population":0,
    "gn:timezone":"Asia/Shanghai",
    "iso:country":"CN",
    "name:zho_x_preferred":[
        "\u5df4\u5f66\u4e4c\u62c9"
    ],
    "wof:name":"Bayan Wula",
    "wof:placetype":"locality"
},
  "geometry": {"coordinates":[118.28854,49.16564],"type":"Point"}
}