{
  "type": "Feature",
  "properties": {
    "gn:admin1_code":"32.0",
    "gn:asciiname":"Shitigou",
    "gn:country_code":"CN",
    "gn:dem":478,
    "gn:feature_class":"P",
    "gn:feature_code":"PPL",
    "gn:name":"Shitigou",
    "gn:population":0,
    "gn:timezone":"Asia/Shanghai",
    "iso:country":"CN",
    "name:zho_x_preferred":[
        "\u77f3\u68af\u6c9f"
    ],
    "wof:name":"Shitigou",
    "wof:placetype":"locality"
},
  "geometry": {"coordinates":[104.378,28.5615],"type":"Point"}
}