{
  "type": "Feature",
  "properties": {
    "gn:admin1_code":"11.0",
    "gn:asciiname":"Bushajie",
    "gn:country_code":"CN",
    "gn:dem":1062,
    "gn:feature_class":"P",
    "gn:feature_code":"PPL",
    "gn:name":"Bushajie",
    "gn:population":0,
    "gn:timezone":"Asia/Shanghai",
    "iso:country":"CN",
    "name:zho_x_preferred":[
        "\u5e03\u6c99\u754c"
    ],
    "wof:name":"Bushajie",
    "wof:placetype":"locality"
},
  "geometry": {"coordinates":[110.17237,26.89472],"type":"Point"}
}