{
  "type": "Feature",
  "properties": {
    "gn:admin1_code":"25.0",
    "gn:asciiname":"Yandunjiaocun",
    "gn:country_code":"CN",
    "gn:dem":11,
    "gn:feature_class":"P",
    "gn:feature_code":"PPL",
    "gn:name":"Yandunjiaocun",
    "gn:population":0,
    "gn:timezone":"Asia/Shanghai",
    "iso:country":"CN",
    "name:zho_x_preferred":[
        "\u70df\u58a9\u89d2\u6751"
    ],
    "wof:name":"Yandunjiaocun",
    "wof:placetype":"locality"
},
  "geometry": {"coordinates":[122.56045,37.29539000000001],"type":"Point"}
}