{
  "type": "Feature",
  "properties": {
    "gn:admin1_code":"4.0",
    "gn:asciiname":"Jianbeicun",
    "gn:country_code":"CN",
    "gn:dem":21,
    "gn:feature_class":"P",
    "gn:feature_code":"PPL",
    "gn:name":"Jianbeicun",
    "gn:population":0,
    "gn:timezone":"Asia/Shanghai",
    "iso:country":"CN",
    "name:zho_x_preferred":[
        "\u6da7\u5317\u6751"
    ],
    "wof:name":"Jianbeicun",
    "wof:placetype":"locality"
},
  "geometry": {"coordinates":[118.10492000000001,33.36591],"type":"Point"}
}