{
  "type": "Feature",
  "properties": {
    "gn:admin1_code":"4.0",
    "gn:asciiname":"Baojiancun",
    "gn:country_code":"CN",
    "gn:dem":6,
    "gn:feature_class":"P",
    "gn:feature_code":"PPL",
    "gn:name":"Baojiancun",
    "gn:population":0,
    "gn:timezone":"Asia/Shanghai",
    "iso:country":"CN",
    "name:zho_x_preferred":[
        "\u4fdd\u5065\u6751"
    ],
    "wof:name":"Baojiancun",
    "wof:placetype":"locality"
},
  "geometry": {"coordinates":[120.10774000000001,31.62418],"type":"Point"}
}