{
  "type": "Feature",
  "properties": {
    "gn:admin1_code":"21.0",
    "gn:asciiname":"Zhouzhaike",
    "gn:country_code":"CN",
    "gn:dem":1737,
    "gn:feature_class":"P",
    "gn:feature_code":"PPL",
    "gn:name":"Zhouzhaike",
    "gn:population":0,
    "gn:timezone":"Asia/Shanghai",
    "iso:country":"CN",
    "name:zho_x_preferred":[
        "\u5468\u5be8\u67ef"
    ],
    "wof:name":"Zhouzhaike",
    "wof:placetype":"locality"
},
  "geometry": {"coordinates":[105.18899999999999,36.9096],"type":"Point"}
}