{
  "type": "Feature",
  "properties": {
    "gn:admin1_code":"12.0",
    "gn:asciiname":"Xicaodian",
    "gn:country_code":"CN",
    "gn:dem":86,
    "gn:feature_class":"P",
    "gn:feature_code":"PPL",
    "gn:name":"Xicaodian",
    "gn:population":0,
    "gn:timezone":"Asia/Shanghai",
    "iso:country":"CN",
    "name:zho_x_preferred":[
        "\u897f\u8349\u5e97"
    ],
    "wof:name":"Xicaodian",
    "wof:placetype":"locality"
},
  "geometry": {"coordinates":[113.8287,31.53643],"type":"Point"}
}