{
  "type": "Feature",
  "properties": {
    "gn:admin1_code":"16.0",
    "gn:asciiname":"Tuzhudong",
    "gn:country_code":"CN",
    "gn:dem":635,
    "gn:feature_class":"P",
    "gn:feature_code":"PPL",
    "gn:name":"Tuzhudong",
    "gn:population":0,
    "gn:timezone":"Asia/Shanghai",
    "iso:country":"CN",
    "name:zho_x_preferred":[
        "\u571f\u67f1\u578c"
    ],
    "wof:name":"Tuzhudong",
    "wof:placetype":"locality"
},
  "geometry": {"coordinates":[110.876,22.6886],"type":"Point"}
}