{
  "type": "Feature",
  "properties": {
    "gn:admin1_code":"4.0",
    "gn:asciiname":"Siyuan",
    "gn:country_code":"CN",
    "gn:dem":6,
    "gn:feature_class":"P",
    "gn:feature_code":"PPL",
    "gn:name":"Siyuan",
    "gn:population":0,
    "gn:timezone":"Asia/Shanghai",
    "iso:country":"CN",
    "name:zho_x_preferred":[
        "Siyuan"
    ],
    "name:zho_x_variant":[
        "\u601d\u6e90"
    ],
    "wof:name":"Siyuan",
    "wof:placetype":"locality"
},
  "geometry": {"coordinates":[120.96071000000001,32.17072],"type":"Point"}
}