{
  "type": "Feature",
  "properties": {
    "gn:admin1_code":"7.0",
    "gn:asciiname":"Xiashandeng",
    "gn:country_code":"CN",
    "gn:dem":848,
    "gn:feature_class":"P",
    "gn:feature_code":"PPL",
    "gn:name":"Xiashandeng",
    "gn:population":0,
    "gn:timezone":"Asia/Shanghai",
    "iso:country":"CN",
    "name:zho_x_preferred":[
        "\u4e0b\u5c71\u767b"
    ],
    "wof:name":"Xiashandeng",
    "wof:placetype":"locality"
},
  "geometry": {"coordinates":[118.97821,26.81425],"type":"Point"}
}