{
  "type": "Feature",
  "properties": {
    "gn:admin1_code":"25.0",
    "gn:asciiname":"Wangjiahetou",
    "gn:country_code":"CN",
    "gn:dem":21,
    "gn:feature_class":"P",
    "gn:feature_code":"PPL",
    "gn:name":"Wangjiahetou",
    "gn:population":0,
    "gn:timezone":"Asia/Shanghai",
    "iso:country":"CN",
    "name:zho_x_preferred":[
        "\u738b\u5bb6\u6cb3\u5934"
    ],
    "wof:name":"Wangjiahetou",
    "wof:placetype":"locality"
},
  "geometry": {"coordinates":[119.98480000000001,36.38292],"type":"Point"}
}