{
  "type": "Feature",
  "properties": {
    "gn:admin1_code":"26",
    "gn:asciiname":"Jiyi",
    "gn:cc2":"CN",
    "gn:country_code":"CN",
    "gn:dem":754,
    "gn:feature_class":"P",
    "gn:feature_code":"PPL",
    "gn:name":"Jiyi",
    "gn:population":0,
    "gn:timezone":"Asia/Shanghai",
    "iso:country":"CN",
    "name:und_x_variant":[
        "Chi-i",
        "I-chi-chen",
        "Chi-i-chen",
        "Jiyi"
    ],
    "wof:name":"Jiyi",
    "wof:placetype":"locality"
},
  "geometry": {"coordinates":[110.37528,35.82444],"type":"Point"}
}