{
  "type": "Feature",
  "properties": {
    "gn:admin1_code":"8.0",
    "gn:asciiname":"Aizhengcun",
    "gn:country_code":"CN",
    "gn:dem":186,
    "gn:feature_class":"P",
    "gn:feature_code":"PPL",
    "gn:name":"Aizhengcun",
    "gn:population":0,
    "gn:timezone":"Asia/Shanghai",
    "iso:country":"CN",
    "name:zho_x_preferred":[
        "\u7231\u653f\u6751"
    ],
    "wof:name":"Aizhengcun",
    "wof:placetype":"locality"
},
  "geometry": {"coordinates":[126.67919999999999,47.63595],"type":"Point"}
}