{
  "type": "Feature",
  "properties": {
    "gn:admin1_code":"8.0",
    "gn:asciiname":"Balipengzi",
    "gn:country_code":"CN",
    "gn:dem":337,
    "gn:feature_class":"P",
    "gn:feature_code":"PPL",
    "gn:name":"Balipengzi",
    "gn:population":0,
    "gn:timezone":"Asia/Shanghai",
    "iso:country":"CN",
    "name:zho_x_preferred":[
        "\u516b\u91cc\u68da\u5b50"
    ],
    "wof:name":"Balipengzi",
    "wof:placetype":"locality"
},
  "geometry": {"coordinates":[127.98945000000001,47.93458],"type":"Point"}
}