{
  "type": "Feature",
  "properties": {
    "gn:admin1_code":"19.0",
    "gn:asciiname":"Shangzhangjia Buzi",
    "gn:country_code":"CN",
    "gn:dem":124,
    "gn:feature_class":"P",
    "gn:feature_code":"PPL",
    "gn:name":"Shangzhangjia Buzi",
    "gn:population":0,
    "gn:timezone":"Asia/Shanghai",
    "iso:country":"CN",
    "name:und_x_variant":[
        "Shangzhangjia Puzi",
        "\u4e0a\u5f20\u5bb6\u5821\u5b50",
        "Shangzhangjia Buzi"
    ],
    "wof:name":"Shangzhangjia Buzi",
    "wof:placetype":"locality"
},
  "geometry": {"coordinates":[123.57769999999999,40.49019000000001],"type":"Point"}
}