{
  "type": "Feature",
  "properties": {
    "gn:admin1_code":"1.0",
    "gn:asciiname":"Liuxiecun",
    "gn:country_code":"CN",
    "gn:dem":33,
    "gn:feature_class":"P",
    "gn:feature_code":"PPL",
    "gn:name":"Liuxiecun",
    "gn:population":0,
    "gn:timezone":"Asia/Shanghai",
    "iso:country":"CN",
    "name:zho_x_preferred":[
        "\u5218\u534f\u6751"
    ],
    "wof:name":"Liuxiecun",
    "wof:placetype":"locality"
},
  "geometry": {"coordinates":[115.71271000000002,33.31769],"type":"Point"}
}