{
  "type": "Feature",
  "properties": {
    "gn:admin1_code":"20.0",
    "gn:asciiname":"Xiaoliujia Weizi",
    "gn:country_code":"CN",
    "gn:dem":354,
    "gn:feature_class":"P",
    "gn:feature_code":"PPL",
    "gn:name":"Xiaoliujia Weizi",
    "gn:population":0,
    "gn:timezone":"Asia/Shanghai",
    "iso:country":"CN",
    "name:zho_x_preferred":[
        "\u5c0f\u5218\u5bb6\u5d34\u5b50"
    ],
    "wof:name":"Xiaoliujia Weizi",
    "wof:placetype":"locality"
},
  "geometry": {"coordinates":[122.77137999999999,48.10164],"type":"Point"}
}