{
  "type": "Feature",
  "properties": {
    "gn:admin1_code":"10",
    "gn:asciiname":"Xihangu",
    "gn:country_code":"CN",
    "gn:dem":41,
    "gn:feature_class":"P",
    "gn:feature_code":"PPL",
    "gn:name":"Xihangu",
    "gn:population":0,
    "gn:timezone":"Asia/Shanghai",
    "iso:country":"CN",
    "name:zho_x_preferred":[
        "\u897f\u97e9\u56fa"
    ],
    "wof:name":"Xihangu",
    "wof:placetype":"locality"
},
  "geometry": {"coordinates":[115.09672999999999,36.77781],"type":"Point"}
}