{
  "type": "Feature",
  "properties": {
    "gn:admin1_code":"07",
    "gn:asciiname":"Lingbian",
    "gn:country_code":"CN",
    "gn:dem":578,
    "gn:feature_class":"P",
    "gn:feature_code":"PPL",
    "gn:name":"Lingbian",
    "gn:population":0,
    "gn:timezone":"Asia/Shanghai",
    "iso:country":"CN",
    "name:zho_x_preferred":[
        "\u5cad\u8fb9"
    ],
    "wof:name":"Lingbian",
    "wof:placetype":"locality"
},
  "geometry": {"coordinates":[117.64019,25.09201],"type":"Point"}
}