{
  "type": "Feature",
  "properties": {
    "gn:admin1_code":"7",
    "gn:asciiname":"Dawucun",
    "gn:country_code":"CN",
    "gn:dem":16,
    "gn:feature_class":"P",
    "gn:feature_code":"PPL",
    "gn:name":"Dawucun",
    "gn:population":0,
    "gn:timezone":"Asia/Shanghai",
    "iso:country":"CN",
    "name:zho_x_preferred":[
        "\u5927\u68a7\u6751"
    ],
    "wof:name":"Dawucun",
    "wof:placetype":"locality"
},
  "geometry": {"coordinates":[117.29611,23.75111],"type":"Point"}
}