{
  "type": "Feature",
  "properties": {
    "gn:admin1_code":"33.0",
    "gn:asciiname":"Guojialin",
    "gn:country_code":"CN",
    "gn:dem":910,
    "gn:feature_class":"P",
    "gn:feature_code":"PPL",
    "gn:name":"Guojialin",
    "gn:population":0,
    "gn:timezone":"Asia/Shanghai",
    "iso:country":"CN",
    "name:zho_x_preferred":[
        "\u90ed\u5bb6\u6797"
    ],
    "wof:name":"Guojialin",
    "wof:placetype":"locality"
},
  "geometry": {"coordinates":[107.34699999999999,28.9984],"type":"Point"}
}