{
  "type": "Feature",
  "properties": {
    "gn:admin1_code":"26.0",
    "gn:asciiname":"Dianfangcun",
    "gn:country_code":"CN",
    "gn:dem":1210,
    "gn:feature_class":"P",
    "gn:feature_code":"PPL",
    "gn:name":"Dianfangcun",
    "gn:population":0,
    "gn:timezone":"Asia/Shanghai",
    "iso:country":"CN",
    "name:zho_x_preferred":[
        "\u5e97\u574a\u6751"
    ],
    "wof:name":"Dianfangcun",
    "wof:placetype":"locality"
},
  "geometry": {"coordinates":[110.06735999999999,38.38318],"type":"Point"}
}