{
  "type": "Feature",
  "properties": {
    "gn:admin1_code":"4.0",
    "gn:asciiname":"Xicaotian",
    "gn:country_code":"CN",
    "gn:dem":6,
    "gn:feature_class":"P",
    "gn:feature_code":"PPL",
    "gn:name":"Xicaotian",
    "gn:population":0,
    "gn:timezone":"Asia/Shanghai",
    "iso:country":"CN",
    "name:zho_x_preferred":[
        "\u897f\u8349\u7530"
    ],
    "wof:name":"Xicaotian",
    "wof:placetype":"locality"
},
  "geometry": {"coordinates":[120.50324000000001,30.98847],"type":"Point"}
}