{
  "type": "Feature",
  "properties": {
    "gn:admin1_code":"18.0",
    "gn:asciiname":"Sanxi",
    "gn:country_code":"CN",
    "gn:dem":614,
    "gn:feature_class":"P",
    "gn:feature_code":"PPL",
    "gn:name":"Sanxi",
    "gn:population":0,
    "gn:timezone":"Asia/Shanghai",
    "iso:country":"CN",
    "name:zho_x_preferred":[
        "\u4f1e\u6eaa"
    ],
    "wof:name":"Sanxi",
    "wof:placetype":"locality"
},
  "geometry": {"coordinates":[109.271,26.874],"type":"Point"}
}