{
  "type": "Feature",
  "properties": {
    "gn:admin1_code":"32.0",
    "gn:asciiname":"Henabian",
    "gn:country_code":"CN",
    "gn:dem":764,
    "gn:feature_class":"P",
    "gn:feature_code":"PPL",
    "gn:name":"Henabian",
    "gn:population":0,
    "gn:timezone":"Asia/Shanghai",
    "iso:country":"CN",
    "name:zho_x_preferred":[
        "\u6cb3\u90a3\u8fb9"
    ],
    "wof:name":"Henabian",
    "wof:placetype":"locality"
},
  "geometry": {"coordinates":[105.45699999999999,32.1777],"type":"Point"}
}