{
  "type": "Feature",
  "properties": {
    "gn:admin1_code":"1.0",
    "gn:asciiname":"Gelin",
    "gn:country_code":"CN",
    "gn:dem":19,
    "gn:feature_class":"P",
    "gn:feature_code":"PPLA4",
    "gn:name":"Gelin",
    "gn:population":0,
    "gn:timezone":"Asia/Shanghai",
    "iso:country":"CN",
    "name:und_x_variant":[
        "\u845b\u6797",
        "Gelin Xiang",
        "\u845b\u6797\u4e61"
    ],
    "wof:name":"Gelin",
    "wof:placetype":"locality"
},
  "geometry": {"coordinates":[118.38196000000001,30.88267],"type":"Point"}
}