{
  "type": "Feature",
  "properties": {
    "gn:admin1_code":"9",
    "gn:asciiname":"Anzhai",
    "gn:country_code":"CN",
    "gn:dem":55,
    "gn:feature_class":"P",
    "gn:feature_code":"PPL",
    "gn:name":"Anzhai",
    "gn:population":0,
    "gn:timezone":"Asia/Shanghai",
    "iso:country":"CN",
    "name:zho_x_preferred":[
        "\u5b89\u5be8"
    ],
    "wof:name":"Anzhai",
    "wof:placetype":"locality"
},
  "geometry": {"coordinates":[115.10290000000001,35.66239],"type":"Point"}
}