{
  "type": "Feature",
  "properties": {
    "gn:admin1_code":"32.0",
    "gn:asciiname":"Yuqingmiao",
    "gn:country_code":"CN",
    "gn:dem":687,
    "gn:feature_class":"P",
    "gn:feature_code":"PPL",
    "gn:name":"Yuqingmiao",
    "gn:population":0,
    "gn:timezone":"Asia/Shanghai",
    "iso:country":"CN",
    "name:zho_x_preferred":[
        "\u96e8\u6674\u5e99"
    ],
    "wof:name":"Yuqingmiao",
    "wof:placetype":"locality"
},
  "geometry": {"coordinates":[104.95399999999999,31.8243],"type":"Point"}
}