{
  "type": "Feature",
  "properties": {
    "gn:admin1_code":"04",
    "gn:asciiname":"Liji",
    "gn:country_code":"CN",
    "gn:dem":5,
    "gn:feature_class":"P",
    "gn:feature_code":"PPLA4",
    "gn:name":"Liji",
    "gn:population":0,
    "gn:timezone":"Asia/Shanghai",
    "iso:country":"CN",
    "name:und_x_variant":[
        "Xiaoliji",
        "Li-chi",
        "Hsiao-li-chi",
        "Hsiao-li",
        "Liji",
        "\u674e\u96c6",
        "Liji Xiang",
        "\u674e\u96c6\u4e61"
    ],
    "wof:name":"Liji",
    "wof:placetype":"locality"
},
  "geometry": {"coordinates":[119.25278,34.105],"type":"Point"}
}