{
  "type": "Feature",
  "properties": {
    "gn:admin1_code":"32.0",
    "gn:asciiname":"Zharong",
    "gn:country_code":"CN",
    "gn:dem":3039,
    "gn:feature_class":"P",
    "gn:feature_code":"PPL",
    "gn:name":"Zharong",
    "gn:population":0,
    "gn:timezone":"Asia/Shanghai",
    "iso:country":"CN",
    "name:zho_x_preferred":[
        "\u624e\u7ed2"
    ],
    "wof:name":"Zharong",
    "wof:placetype":"locality"
},
  "geometry": {"coordinates":[99.2046,28.4728],"type":"Point"}
}