{
  "type": "Feature",
  "properties": {
    "gn:admin1_code":"11.0",
    "gn:asciiname":"Sumizui",
    "gn:country_code":"CN",
    "gn:dem":33,
    "gn:feature_class":"P",
    "gn:feature_code":"PPL",
    "gn:name":"Sumizui",
    "gn:population":0,
    "gn:timezone":"Asia/Shanghai",
    "iso:country":"CN",
    "name:zho_x_preferred":[
        "\u7c9f\u7c73\u5480"
    ],
    "wof:name":"Sumizui",
    "wof:placetype":"locality"
},
  "geometry": {"coordinates":[113.28973000000001,29.53988],"type":"Point"}
}