{
  "type": "Feature",
  "properties": {
    "gn:admin1_code":"4.0",
    "gn:asciiname":"Yongxingcun Sizu",
    "gn:country_code":"CN",
    "gn:dem":4,
    "gn:feature_class":"P",
    "gn:feature_code":"PPLF",
    "gn:name":"Yongxingcun Sizu",
    "gn:population":0,
    "gn:timezone":"Asia/Shanghai",
    "iso:country":"CN",
    "name:zho_x_preferred":[
        "\u6c38\u5174\u6751\u56db\u7ec4"
    ],
    "wof:name":"Yongxingcun Sizu",
    "wof:placetype":"locality"
},
  "geometry": {"coordinates":[120.48844,32.00672],"type":"Point"}
}