{
  "type": "Feature",
  "properties": {
    "gn:admin1_code":"26.0",
    "gn:asciiname":"Quli",
    "gn:country_code":"CN",
    "gn:dem":870,
    "gn:feature_class":"P",
    "gn:feature_code":"PPL",
    "gn:name":"Quli",
    "gn:population":0,
    "gn:timezone":"Asia/Shanghai",
    "iso:country":"CN",
    "name:zho_x_preferred":[
        "\u66f2\u674e"
    ],
    "wof:name":"Quli",
    "wof:placetype":"locality"
},
  "geometry": {"coordinates":[110.23705,34.11979],"type":"Point"}
}