{
  "type": "Feature",
  "properties": {
    "gn:admin1_code":"10.0",
    "gn:asciiname":"Yaohuali",
    "gn:country_code":"CN",
    "gn:dem":5,
    "gn:feature_class":"P",
    "gn:feature_code":"PPL",
    "gn:name":"Yaohuali",
    "gn:population":0,
    "gn:timezone":"Asia/Shanghai",
    "iso:country":"CN",
    "name:zho_x_preferred":[
        "\u8000\u534e\u91cc"
    ],
    "wof:name":"Yaohuali",
    "wof:placetype":"locality"
},
  "geometry": {"coordinates":[119.57493999999998,39.9218],"type":"Point"}
}