{
  "type": "Feature",
  "properties": {
    "gn:admin1_code":"15.0",
    "gn:asciiname":"Tugou Xindui",
    "gn:country_code":"CN",
    "gn:dem":2404,
    "gn:feature_class":"P",
    "gn:feature_code":"PPLF",
    "gn:name":"Tugou Xindui",
    "gn:population":0,
    "gn:timezone":"Asia/Shanghai",
    "iso:country":"CN",
    "name:zho_x_preferred":[
        "\u571f\u6c9f\u65b0\u961f"
    ],
    "wof:name":"Tugou Xindui",
    "wof:placetype":"locality"
},
  "geometry": {"coordinates":[101.51300000000001,38.3056],"type":"Point"}
}