{
  "type": "Feature",
  "properties": {
    "gn:admin1_code":"30",
    "gn:asciiname":"Tianyang",
    "gn:country_code":"CN",
    "gn:dem":98,
    "gn:feature_class":"P",
    "gn:feature_code":"PPL",
    "gn:name":"Tianyang",
    "gn:population":0,
    "gn:timezone":"Asia/Urumqi",
    "iso:country":"CN",
    "name:und_x_variant":[
        "\u7530\u6d0b"
    ],
    "name:zho_x_preferred":[
        "T\u2019ien-yang"
    ],
    "wof:name":"Tianyang",
    "wof:placetype":"locality"
},
  "geometry": {"coordinates":[110.29549,20.52266],"type":"Point"}
}