{
  "type": "Feature",
  "properties": {
    "gn:admin1_code":"8.0",
    "gn:asciiname":"Xingshan",
    "gn:country_code":"CN",
    "gn:dem":309,
    "gn:feature_class":"P",
    "gn:feature_code":"PPL",
    "gn:name":"Xingshan",
    "gn:population":0,
    "gn:timezone":"Asia/Shanghai",
    "iso:country":"CN",
    "name:zho_x_preferred":[
        "\u661f\u5c71"
    ],
    "wof:name":"Xingshan",
    "wof:placetype":"locality"
},
  "geometry": {"coordinates":[126.55763,51.22162],"type":"Point"}
}