{
  "type": "Feature",
  "properties": {
    "gn:admin1_code":"29.0",
    "gn:asciiname":"Yiyidu",
    "gn:country_code":"CN",
    "gn:dem":1413,
    "gn:feature_class":"P",
    "gn:feature_code":"PPL",
    "gn:name":"Yiyidu",
    "gn:population":0,
    "gn:timezone":"Asia/Shanghai",
    "iso:country":"CN",
    "name:zho_x_preferred":[
        "\u9091\u5b9c\u90fd"
    ],
    "wof:name":"Yiyidu",
    "wof:placetype":"locality"
},
  "geometry": {"coordinates":[102.422,23.2835],"type":"Point"}
}