{
  "type": "Feature",
  "properties": {
    "gn:admin1_code":"19.0",
    "gn:asciiname":"Gongguanyingzi",
    "gn:country_code":"CN",
    "gn:dem":318,
    "gn:feature_class":"P",
    "gn:feature_code":"PPL",
    "gn:name":"Gongguanyingzi",
    "gn:population":0,
    "gn:timezone":"Asia/Shanghai",
    "iso:country":"CN",
    "name:zho_x_preferred":[
        "\u5bab\u5b98\u8425\u5b50"
    ],
    "wof:name":"Gongguanyingzi",
    "wof:placetype":"locality"
},
  "geometry": {"coordinates":[121.622,42.2766],"type":"Point"}
}