{
  "type": "Feature",
  "properties": {
    "gn:admin1_code":"19.0",
    "gn:asciiname":"Xiawopengcun",
    "gn:country_code":"CN",
    "gn:dem":174,
    "gn:feature_class":"P",
    "gn:feature_code":"PPL",
    "gn:name":"Xiawopengcun",
    "gn:population":0,
    "gn:timezone":"Asia/Shanghai",
    "iso:country":"CN",
    "name:zho_x_preferred":[
        "\u4e0b\u7a9d\u68da\u6751"
    ],
    "wof:name":"Xiawopengcun",
    "wof:placetype":"locality"
},
  "geometry": {"coordinates":[124.28400000000001,41.9776],"type":"Point"}
}