{
  "type": "Feature",
  "properties": {
    "gn:admin1_code":"32.0",
    "gn:asciiname":"Songshu",
    "gn:country_code":"CN",
    "gn:dem":1216,
    "gn:feature_class":"P",
    "gn:feature_code":"PPL",
    "gn:name":"Songshu",
    "gn:population":0,
    "gn:timezone":"Asia/Shanghai",
    "iso:country":"CN",
    "name:zho_x_preferred":[
        "\u677e\u6811"
    ],
    "wof:name":"Songshu",
    "wof:placetype":"locality"
},
  "geometry": {"coordinates":[103.42789,28.28083],"type":"Point"}
}