{
  "type": "Feature",
  "properties": {
    "gn:admin1_code":"10.0",
    "gn:asciiname":"Tashang",
    "gn:country_code":"CN",
    "gn:dem":13,
    "gn:feature_class":"P",
    "gn:feature_code":"PPL",
    "gn:name":"Tashang",
    "gn:population":0,
    "gn:timezone":"Asia/Shanghai",
    "iso:country":"CN",
    "name:zho_x_preferred":[
        "\u5854\u4e0a"
    ],
    "name:zho_x_variant":[
        "\u5854\u4e0a\u9547"
    ],
    "wof:name":"Tashang",
    "wof:placetype":"locality"
},
  "geometry": {"coordinates":[117.196,38.1315],"type":"Point"}
}