{
  "type": "Feature",
  "properties": {
    "gn:admin1_code":"18.0",
    "gn:asciiname":"Hangdeng",
    "gn:country_code":"CN",
    "gn:dem":778,
    "gn:feature_class":"P",
    "gn:feature_code":"PPL",
    "gn:name":"Hangdeng",
    "gn:population":0,
    "gn:timezone":"Asia/Shanghai",
    "iso:country":"CN",
    "name:zho_x_preferred":[
        "\u592f\u767b"
    ],
    "wof:name":"Hangdeng",
    "wof:placetype":"locality"
},
  "geometry": {"coordinates":[109.33799999999999,28.0595],"type":"Point"}
}