{
  "type": "Feature",
  "properties": {
    "gn:admin1_code":"29",
    "gn:asciiname":"Aguhei",
    "gn:country_code":"CN",
    "gn:dem":1732,
    "gn:feature_class":"P",
    "gn:feature_code":"PPL",
    "gn:name":"Aguhei",
    "gn:population":0,
    "gn:timezone":"Asia/Shanghai",
    "iso:country":"CN",
    "name:zho_x_preferred":[
        "\u963f\u53e4\u9ed1"
    ],
    "wof:name":"Aguhei",
    "wof:placetype":"locality"
},
  "geometry": {"coordinates":[101.93899999999999,24.3133],"type":"Point"}
}