{
  "type": "Feature",
  "properties": {
    "gn:admin1_code":"12.0",
    "gn:asciiname":"Laohuchong",
    "gn:country_code":"CN",
    "gn:dem":175,
    "gn:feature_class":"P",
    "gn:feature_code":"PPL",
    "gn:name":"Laohuchong",
    "gn:population":0,
    "gn:timezone":"Asia/Shanghai",
    "iso:country":"CN",
    "name:zho_x_preferred":[
        "\u8001\u864e\u51b2"
    ],
    "wof:name":"Laohuchong",
    "wof:placetype":"locality"
},
  "geometry": {"coordinates":[113.41419999999999,32.01893],"type":"Point"}
}