{
  "type": "Feature",
  "properties": {
    "gn:admin1_code":"23.0",
    "gn:asciiname":"Dianxi",
    "gn:country_code":"CN",
    "gn:dem":5,
    "gn:feature_class":"P",
    "gn:feature_code":"PPL",
    "gn:name":"Dianxi",
    "gn:population":0,
    "gn:timezone":"Asia/Shanghai",
    "iso:country":"CN",
    "name:und_x_variant":[
        "\u6dc0\u897f"
    ],
    "wof:name":"Dianxi",
    "wof:placetype":"locality"
},
  "geometry": {"coordinates":[120.92949,31.13308],"type":"Point"}
}