{
  "type": "Feature",
  "properties": {
    "gn:admin1_code":"8.0",
    "gn:asciiname":"Wanzengdian",
    "gn:country_code":"CN",
    "gn:dem":150,
    "gn:feature_class":"P",
    "gn:feature_code":"PPL",
    "gn:name":"Wanzengdian",
    "gn:population":0,
    "gn:timezone":"Asia/Shanghai",
    "iso:country":"CN",
    "name:zho_x_preferred":[
        "\u4e07\u589e\u5e97"
    ],
    "wof:name":"Wanzengdian",
    "wof:placetype":"locality"
},
  "geometry": {"coordinates":[125.0059,47.00684],"type":"Point"}
}