{
  "type": "Feature",
  "properties": {
    "gn:admin1_code":"9.0",
    "gn:asciiname":"Wanjie",
    "gn:country_code":"CN",
    "gn:dem":146,
    "gn:feature_class":"P",
    "gn:feature_code":"PPL",
    "gn:name":"Wanjie",
    "gn:population":0,
    "gn:timezone":"Asia/Shanghai",
    "iso:country":"CN",
    "name:und_x_variant":[
        "\u6e7e\u8857",
        "Wanjie"
    ],
    "wof:name":"Wanjie",
    "wof:placetype":"locality"
},
  "geometry": {"coordinates":[112.76657,33.11016],"type":"Point"}
}