{
  "type": "Feature",
  "properties": {
    "gn:admin1_code":"30.0",
    "gn:asciiname":"Qianbeiling",
    "gn:country_code":"CN",
    "gn:dem":122,
    "gn:feature_class":"P",
    "gn:feature_code":"PPL",
    "gn:name":"Qianbeiling",
    "gn:population":0,
    "gn:timezone":"Asia/Shanghai",
    "iso:country":"CN",
    "name:zho_x_preferred":[
        "\u524d\u80cc\u5cad"
    ],
    "wof:name":"Qianbeiling",
    "wof:placetype":"locality"
},
  "geometry": {"coordinates":[114.28104999999999,25.07491],"type":"Point"}
}