{
  "type": "Feature",
  "properties": {
    "gn:admin1_code":"9.0",
    "gn:asciiname":"Tianchigou",
    "gn:country_code":"CN",
    "gn:dem":432,
    "gn:feature_class":"P",
    "gn:feature_code":"PPL",
    "gn:name":"Tianchigou",
    "gn:population":0,
    "gn:timezone":"Asia/Shanghai",
    "iso:country":"CN",
    "name:zho_x_preferred":[
        "\u5929\u6c60\u6c9f"
    ],
    "wof:name":"Tianchigou",
    "wof:placetype":"locality"
},
  "geometry": {"coordinates":[111.11745000000001,33.39507],"type":"Point"}
}