{
  "type": "Feature",
  "properties": {
    "gn:admin1_code":"22.0",
    "gn:asciiname":"Suanzaoyucun",
    "gn:country_code":"CN",
    "gn:dem":142,
    "gn:feature_class":"P",
    "gn:feature_code":"PPL",
    "gn:name":"Suanzaoyucun",
    "gn:population":0,
    "gn:timezone":"Asia/Shanghai",
    "iso:country":"CN",
    "name:zho_x_preferred":[
        "\u9178\u67a3\u5cea\u6751"
    ],
    "wof:name":"Suanzaoyucun",
    "wof:placetype":"locality"
},
  "geometry": {"coordinates":[117.30885000000001,40.15781],"type":"Point"}
}