{
  "type": "Feature",
  "properties": {
    "gn:admin1_code":"8.0",
    "gn:asciiname":"Xichangfa",
    "gn:country_code":"CN",
    "gn:dem":191,
    "gn:feature_class":"P",
    "gn:feature_code":"PPL",
    "gn:name":"Xichangfa",
    "gn:population":0,
    "gn:timezone":"Asia/Shanghai",
    "iso:country":"CN",
    "name:zho_x_preferred":[
        "\u897f\u957f\u53d1"
    ],
    "wof:name":"Xichangfa",
    "wof:placetype":"locality"
},
  "geometry": {"coordinates":[126.23018999999999,46.53116],"type":"Point"}
}