{
  "type": "Feature",
  "properties": {
    "gn:admin1_code":"3.0",
    "gn:asciiname":"Jiangling",
    "gn:country_code":"CN",
    "gn:dem":229,
    "gn:feature_class":"P",
    "gn:feature_code":"PPL",
    "gn:name":"Jiangling",
    "gn:population":0,
    "gn:timezone":"Asia/Shanghai",
    "iso:country":"CN",
    "name:kor_x_preferred":[
        "\uac15\ub989"
    ],
    "name:und_x_variant":[
        "\u59dc\u5cad"
    ],
    "name:zho_x_preferred":[
        "\u6c5f\u9675"
    ],
    "wof:name":"Jiangling",
    "wof:placetype":"locality"
},
  "geometry": {"coordinates":[114.24823000000001,27.72237],"type":"Point"}
}