{
  "type": "Feature",
  "properties": {
    "gn:admin1_code":"29.0",
    "gn:asciiname":"Gonghaiba",
    "gn:country_code":"CN",
    "gn:dem":2142,
    "gn:feature_class":"P",
    "gn:feature_code":"PPL",
    "gn:name":"Gonghaiba",
    "gn:population":0,
    "gn:timezone":"Asia/Shanghai",
    "iso:country":"CN",
    "name:zho_x_preferred":[
        "\u5bab\u6d77\u575d"
    ],
    "wof:name":"Gonghaiba",
    "wof:placetype":"locality"
},
  "geometry": {"coordinates":[103.188,26.4315],"type":"Point"}
}