{
  "type": "Feature",
  "properties": {
    "gn:admin1_code":"7",
    "gn:asciiname":"Qibaigang",
    "gn:country_code":"CN",
    "gn:dem":601,
    "gn:feature_class":"P",
    "gn:feature_code":"PPL",
    "gn:name":"Qibaigang",
    "gn:population":0,
    "gn:timezone":"Asia/Shanghai",
    "iso:country":"CN",
    "name:und_x_variant":[
        "\u4e03\u5b9d\u5c97",
        "Qibaigang"
    ],
    "wof:name":"Qibaigang",
    "wof:placetype":"locality"
},
  "geometry": {"coordinates":[119.285,27.42287],"type":"Point"}
}