{
  "type": "Feature",
  "properties": {
    "gn:admin1_code":"26.0",
    "gn:asciiname":"Chenxiwan",
    "gn:country_code":"CN",
    "gn:dem":1495,
    "gn:feature_class":"P",
    "gn:feature_code":"PPL",
    "gn:name":"Chenxiwan",
    "gn:population":0,
    "gn:timezone":"Asia/Shanghai",
    "iso:country":"CN",
    "name:zho_x_preferred":[
        "\u9648\u897f\u6e7e"
    ],
    "wof:name":"Chenxiwan",
    "wof:placetype":"locality"
},
  "geometry": {"coordinates":[108.34721999999999,37.35787],"type":"Point"}
}