{
  "type": "Feature",
  "properties": {
    "gn:admin1_code":"7.0",
    "gn:asciiname":"Baiyeche",
    "gn:country_code":"CN",
    "gn:dem":179,
    "gn:feature_class":"P",
    "gn:feature_code":"PPL",
    "gn:name":"Baiyeche",
    "gn:population":0,
    "gn:timezone":"Asia/Shanghai",
    "iso:country":"CN",
    "name:und_x_variant":[
        "\u767e\u53f6\u8f66"
    ],
    "name:zho_x_preferred":[
        "\u767e\u53f6\u8f66"
    ],
    "wof:name":"Baiyeche",
    "wof:placetype":"locality"
},
  "geometry": {"coordinates":[117.35120000000001,26.04936],"type":"Point"}
}