{
  "type": "Feature",
  "properties": {
    "gn:admin1_code":"11.0",
    "gn:asciiname":"Houjia Taishang",
    "gn:country_code":"CN",
    "gn:dem":88,
    "gn:feature_class":"P",
    "gn:feature_code":"PPL",
    "gn:name":"Houjia Taishang",
    "gn:population":0,
    "gn:timezone":"Asia/Shanghai",
    "iso:country":"CN",
    "name:zho_x_preferred":[
        "\u4faf\u5bb6\u53f0\u4e0a"
    ],
    "wof:name":"Houjia Taishang",
    "wof:placetype":"locality"
},
  "geometry": {"coordinates":[113.19186999999999,27.48668],"type":"Point"}
}