{
  "type": "Feature",
  "properties": {
    "gn:admin1_code":"15.0",
    "gn:asciiname":"Peijiagou",
    "gn:country_code":"CN",
    "gn:dem":2283,
    "gn:feature_class":"P",
    "gn:feature_code":"PPL",
    "gn:name":"Peijiagou",
    "gn:population":0,
    "gn:timezone":"Asia/Shanghai",
    "iso:country":"CN",
    "name:und_x_variant":[
        "\u88f4\u5bb6\u6c9f"
    ],
    "wof:name":"Peijiagou",
    "wof:placetype":"locality"
},
  "geometry": {"coordinates":[104.43715,34.88328],"type":"Point"}
}