{
  "type": "Feature",
  "properties": {
    "gn:admin1_code":"1.0",
    "gn:asciiname":"Xiangdongkeng",
    "gn:country_code":"CN",
    "gn:dem":283,
    "gn:feature_class":"P",
    "gn:feature_code":"PPL",
    "gn:name":"Xiangdongkeng",
    "gn:population":0,
    "gn:timezone":"Asia/Shanghai",
    "iso:country":"CN",
    "name:und_x_variant":[
        "\u5411\u4e1c\u5751",
        "Xiangdongkeng"
    ],
    "wof:name":"Xiangdongkeng",
    "wof:placetype":"locality"
},
  "geometry": {"coordinates":[118.64618,29.93562],"type":"Point"}
}