{
  "type": "Feature",
  "properties": {
    "gn:admin1_code":"30",
    "gn:asciiname":"Xiaogang",
    "gn:country_code":"CN",
    "gn:dem":1,
    "gn:feature_class":"P",
    "gn:feature_code":"PPL",
    "gn:name":"Xiaogang",
    "gn:population":0,
    "gn:timezone":"Asia/Shanghai",
    "iso:country":"CN",
    "name:ces_x_preferred":[
        "Siao-kang"
    ],
    "name:deu_x_preferred":[
        "Xiaogang"
    ],
    "name:fra_x_preferred":[
        "Xiaogang"
    ],
    "name:zho_x_preferred":[
        "\u5c0f\u5188"
    ],
    "wof:name":"Xiaogang",
    "wof:placetype":"locality"
},
  "geometry": {"coordinates":[112.97543,22.47209],"type":"Point"}
}