{
  "type": "Feature",
  "properties": {
    "gn:admin1_code":"9.0",
    "gn:asciiname":"Anjiawa",
    "gn:country_code":"CN",
    "gn:dem":1112,
    "gn:feature_class":"P",
    "gn:feature_code":"PPL",
    "gn:name":"Anjiawa",
    "gn:population":0,
    "gn:timezone":"Asia/Shanghai",
    "iso:country":"CN",
    "name:zho_x_preferred":[
        "\u5b89\u5bb6\u6d3c"
    ],
    "wof:name":"Anjiawa",
    "wof:placetype":"locality"
},
  "geometry": {"coordinates":[111.12715,34.57716],"type":"Point"}
}