{
  "type": "Feature",
  "properties": {
    "gn:admin1_code":"15.0",
    "gn:asciiname":"Xinzhuangli",
    "gn:country_code":"CN",
    "gn:dem":2056,
    "gn:feature_class":"P",
    "gn:feature_code":"PPL",
    "gn:name":"Xinzhuangli",
    "gn:population":0,
    "gn:timezone":"Asia/Shanghai",
    "iso:country":"CN",
    "name:und_x_variant":[
        "\u65b0\u5e84\u91cc"
    ],
    "name:zho_x_preferred":[
        "\u65b0\u5e84\u91cc"
    ],
    "wof:name":"Xinzhuangli",
    "wof:placetype":"locality"
},
  "geometry": {"coordinates":[104.94387,33.92615],"type":"Point"}
}