{
  "type": "Feature",
  "properties": {
    "gn:admin1_code":"15.0",
    "gn:asciiname":"Xianzi",
    "gn:country_code":"CN",
    "gn:dem":1797,
    "gn:feature_class":"P",
    "gn:feature_code":"PPL",
    "gn:name":"Xianzi",
    "gn:population":0,
    "gn:timezone":"Asia/Shanghai",
    "iso:country":"CN",
    "name:zho_x_preferred":[
        "\u5c98\u5b50"
    ],
    "wof:name":"Xianzi",
    "wof:placetype":"locality"
},
  "geometry": {"coordinates":[103.842,36.424],"type":"Point"}
}