{
  "type": "Feature",
  "properties": {
    "gn:admin1_code":"9.0",
    "gn:asciiname":"Hougang",
    "gn:country_code":"CN",
    "gn:dem":62,
    "gn:feature_class":"P",
    "gn:feature_code":"PPL",
    "gn:name":"Hougang",
    "gn:population":0,
    "gn:timezone":"Asia/Shanghai",
    "iso:country":"CN",
    "name:fas_x_preferred":[
        "\u0647\u0648\u06af\u0627\u0646\u06af"
    ],
    "name:fin_x_preferred":[
        "Hougang"
    ],
    "name:ind_x_preferred":[
        "Hougang"
    ],
    "name:zho_x_preferred":[
        "\u4faf\u5c97"
    ],
    "wof:name":"Hougang",
    "wof:placetype":"locality"
},
  "geometry": {"coordinates":[115.58008999999998,32.10654],"type":"Point"}
}