{
  "type": "Feature",
  "properties": {
    "gn:admin1_code":"25",
    "gn:asciiname":"Nantaitou",
    "gn:country_code":"CN",
    "gn:dem":7,
    "gn:feature_class":"P",
    "gn:feature_code":"PPL",
    "gn:name":"Nantaitou",
    "gn:population":0,
    "gn:timezone":"Asia/Shanghai",
    "iso:country":"CN",
    "name:zho_x_preferred":[
        "\u5357\u53f0\u5934"
    ],
    "wof:name":"Nantaitou",
    "wof:placetype":"locality"
},
  "geometry": {"coordinates":[118.657,37.0141],"type":"Point"}
}