{
  "type": "Feature",
  "properties": {
    "gn:admin1_code":"10.0",
    "gn:asciiname":"Yanwa",
    "gn:cc2":"CN",
    "gn:country_code":"CN",
    "gn:dem":609,
    "gn:feature_class":"P",
    "gn:feature_code":"PPL",
    "gn:name":"Yanwa",
    "gn:population":0,
    "gn:timezone":"Asia/Shanghai",
    "iso:country":"CN",
    "name:und_x_variant":[
        "Yen-wa",
        "Yanwa"
    ],
    "wof:name":"Yanwa",
    "wof:placetype":"locality"
},
  "geometry": {"coordinates":[113.76667,36.46667],"type":"Point"}
}