{
  "type": "Feature",
  "properties": {
    "gn:admin1_code":"30.0",
    "gn:asciiname":"Yangguangcun",
    "gn:country_code":"CN",
    "gn:dem":10,
    "gn:feature_class":"P",
    "gn:feature_code":"PPL",
    "gn:name":"Yangguangcun",
    "gn:population":0,
    "gn:timezone":"Asia/Shanghai",
    "iso:country":"CN",
    "name:zho_x_preferred":[
        "\u6d0b\u5149\u6751"
    ],
    "wof:name":"Yangguangcun",
    "wof:placetype":"locality"
},
  "geometry": {"coordinates":[116.66473000000001,23.60476],"type":"Point"}
}