{
  "type": "Feature",
  "properties": {
    "gn:admin1_code":"9.0",
    "gn:asciiname":"Wantanggeng",
    "gn:country_code":"CN",
    "gn:dem":128,
    "gn:feature_class":"P",
    "gn:feature_code":"PPL",
    "gn:name":"Wantanggeng",
    "gn:population":0,
    "gn:timezone":"Asia/Shanghai",
    "iso:country":"CN",
    "name:zho_x_preferred":[
        "\u5f2f\u5858\u57c2"
    ],
    "wof:name":"Wantanggeng",
    "wof:placetype":"locality"
},
  "geometry": {"coordinates":[113.85257,32.09037],"type":"Point"}
}