{
  "type": "Feature",
  "properties": {
    "gn:admin1_code":"1.0",
    "gn:asciiname":"Luoguo",
    "gn:country_code":"CN",
    "gn:dem":128,
    "gn:feature_class":"P",
    "gn:feature_code":"PPL",
    "gn:name":"Luoguo",
    "gn:population":0,
    "gn:timezone":"Asia/Shanghai",
    "iso:country":"CN",
    "name:und_x_variant":[
        "\u843d\u679c"
    ],
    "name:zho_x_preferred":[
        "Luoguo"
    ],
    "wof:name":"Luoguo",
    "wof:placetype":"locality"
},
  "geometry": {"coordinates":[118.9752,30.73892],"type":"Point"}
}