{
  "type": "Feature",
  "properties": {
    "gn:admin1_code":"19.0",
    "gn:asciiname":"Zhengjiachang",
    "gn:country_code":"CN",
    "gn:dem":8,
    "gn:feature_class":"P",
    "gn:feature_code":"PPL",
    "gn:name":"Zhengjiachang",
    "gn:population":0,
    "gn:timezone":"Asia/Shanghai",
    "iso:country":"CN",
    "name:und_x_variant":[
        "\u90d1\u5bb6\u5382"
    ],
    "name:zho_x_preferred":[
        "\u90d1\u5bb6\u5382"
    ],
    "wof:name":"Zhengjiachang",
    "wof:placetype":"locality"
},
  "geometry": {"coordinates":[122.75708,41.14114],"type":"Point"}
}