{
  "type": "Feature",
  "properties": {
    "gn:admin1_code":"12.0",
    "gn:asciiname":"Yujiatai",
    "gn:country_code":"CN",
    "gn:dem":475,
    "gn:feature_class":"P",
    "gn:feature_code":"PPL",
    "gn:name":"Yujiatai",
    "gn:population":0,
    "gn:timezone":"Asia/Shanghai",
    "iso:country":"CN",
    "name:zho_x_preferred":[
        "\u4f59\u5bb6\u53f0"
    ],
    "wof:name":"Yujiatai",
    "wof:placetype":"locality"
},
  "geometry": {"coordinates":[111.93102,31.4244],"type":"Point"}
}