{
  "type": "Feature",
  "properties": {
    "gn:admin1_code":"32.0",
    "gn:asciiname":"Sansongping",
    "gn:country_code":"CN",
    "gn:dem":3499,
    "gn:feature_class":"P",
    "gn:feature_code":"PPL",
    "gn:name":"Sansongping",
    "gn:population":0,
    "gn:timezone":"Asia/Shanghai",
    "iso:country":"CN",
    "name:zho_x_preferred":[
        "\u4e09\u677e\u576a"
    ],
    "wof:name":"Sansongping",
    "wof:placetype":"locality"
},
  "geometry": {"coordinates":[102.59408000000001,31.52531],"type":"Point"}
}