{
  "type": "Feature",
  "properties": {
    "gn:admin1_code":"18.0",
    "gn:asciiname":"Yunshe",
    "gn:country_code":"CN",
    "gn:dem":397,
    "gn:feature_class":"P",
    "gn:feature_code":"PPL",
    "gn:name":"Yunshe",
    "gn:population":0,
    "gn:timezone":"Asia/Shanghai",
    "iso:country":"CN",
    "name:zho_x_preferred":[
        "\u4e91\u820d"
    ],
    "wof:name":"Yunshe",
    "wof:placetype":"locality"
},
  "geometry": {"coordinates":[108.81399999999999,27.7474],"type":"Point"}
}