{
  "type": "Feature",
  "properties": {
    "gn:admin1_code":"18",
    "gn:asciiname":"Xuhuatun",
    "gn:country_code":"CN",
    "gn:dem":1580,
    "gn:feature_class":"P",
    "gn:feature_code":"PPL",
    "gn:name":"Xuhuatun",
    "gn:population":0,
    "gn:timezone":"Asia/Shanghai",
    "iso:country":"CN",
    "name:zho_x_preferred":[
        "\u5f90\u82b1\u5c6f"
    ],
    "wof:name":"Xuhuatun",
    "wof:placetype":"locality"
},
  "geometry": {"coordinates":[105.253,27.3439],"type":"Point"}
}