{
  "type": "Feature",
  "properties": {
    "gn:admin1_code":"23.0",
    "gn:asciiname":"Hongguang",
    "gn:country_code":"CN",
    "gn:dem":3,
    "gn:feature_class":"P",
    "gn:feature_code":"PPL",
    "gn:name":"Hongguang",
    "gn:population":0,
    "gn:timezone":"Asia/Shanghai",
    "iso:country":"CN",
    "name:zho_x_preferred":[
        "Hongguang"
    ],
    "name:zho_x_variant":[
        "\u7ea2\u5149"
    ],
    "wof:name":"Hongguang",
    "wof:placetype":"locality"
},
  "geometry": {"coordinates":[121.39879000000001,31.32732],"type":"Point"}
}