{
  "type": "Feature",
  "properties": {
    "gn:admin1_code":"9.0",
    "gn:asciiname":"Gedisi",
    "gn:country_code":"CN",
    "gn:dem":346,
    "gn:feature_class":"P",
    "gn:feature_code":"PPL",
    "gn:name":"Gedisi",
    "gn:population":0,
    "gn:timezone":"Asia/Shanghai",
    "iso:country":"CN",
    "name:zho_x_preferred":[
        "\u683c\u5824\u5bfa"
    ],
    "wof:name":"Gedisi",
    "wof:placetype":"locality"
},
  "geometry": {"coordinates":[111.66074,32.6388],"type":"Point"}
}