{
  "type": "Feature",
  "properties": {
    "gn:admin1_code":"33.0",
    "gn:asciiname":"Baizhu",
    "gn:country_code":"CN",
    "gn:dem":911,
    "gn:feature_class":"P",
    "gn:feature_code":"PPL",
    "gn:name":"Baizhu",
    "gn:population":0,
    "gn:timezone":"Asia/Shanghai",
    "iso:country":"CN",
    "name:zho_x_preferred":[
        "\u67cf\u7af9"
    ],
    "wof:name":"Baizhu",
    "wof:placetype":"locality"
},
  "geometry": {"coordinates":[108.09117999999999,30.96235],"type":"Point"}
}