{
  "type": "Feature",
  "properties": {
    "gn:admin1_code":"26.0",
    "gn:asciiname":"Gangou Yuanzi",
    "gn:country_code":"CN",
    "gn:dem":1025,
    "gn:feature_class":"P",
    "gn:feature_code":"PPL",
    "gn:name":"Gangou Yuanzi",
    "gn:population":0,
    "gn:timezone":"Asia/Shanghai",
    "iso:country":"CN",
    "name:zho_x_preferred":[
        "\u5e72\u6c9f\u9662\u5b50"
    ],
    "wof:name":"Gangou Yuanzi",
    "wof:placetype":"locality"
},
  "geometry": {"coordinates":[109.14643999999998,33.25414],"type":"Point"}
}