{
  "type": "Feature",
  "properties": {
    "gn:admin1_code":"29.0",
    "gn:asciiname":"Xiaodulong",
    "gn:country_code":"CN",
    "gn:dem":2013,
    "gn:feature_class":"P",
    "gn:feature_code":"PPL",
    "gn:name":"Xiaodulong",
    "gn:population":0,
    "gn:timezone":"Asia/Shanghai",
    "iso:country":"CN",
    "name:zho_x_preferred":[
        "\u5c0f\u72ec\u9f99"
    ],
    "wof:name":"Xiaodulong",
    "wof:placetype":"locality"
},
  "geometry": {"coordinates":[103.836,24.8472],"type":"Point"}
}