{
  "type": "Feature",
  "properties": {
    "gn:admin1_code":"7.0",
    "gn:asciiname":"Shuigou",
    "gn:country_code":"CN",
    "gn:dem":444,
    "gn:feature_class":"P",
    "gn:feature_code":"PPL",
    "gn:name":"Shuigou",
    "gn:population":0,
    "gn:timezone":"Asia/Shanghai",
    "iso:country":"CN",
    "name:und_x_variant":[
        "\u6c34\u6c9f"
    ],
    "name:zho_x_preferred":[
        "\u6c34\u6c9f"
    ],
    "wof:name":"Shuigou",
    "wof:placetype":"locality"
},
  "geometry": {"coordinates":[118.46646,26.49678],"type":"Point"}
}