{
  "type": "Feature",
  "properties": {
    "gn:admin1_code":"19.0",
    "gn:asciiname":"Xilao Guyucun",
    "gn:country_code":"CN",
    "gn:dem":178,
    "gn:feature_class":"P",
    "gn:feature_code":"PPL",
    "gn:name":"Xilao Guyucun",
    "gn:population":0,
    "gn:timezone":"Asia/Shanghai",
    "iso:country":"CN",
    "name:und_x_variant":[
        "Xilaoguyucun",
        "Xilao Guyucun"
    ],
    "name:zho_x_preferred":[
        "\u897f\u8001\u8c37\u5cea\u6751"
    ],
    "wof:name":"Xilao Guyucun",
    "wof:placetype":"locality"
},
  "geometry": {"coordinates":[124.27754,42.47266],"type":"Point"}
}