{
  "type": "Feature",
  "properties": {
    "gn:admin1_code":"2.0",
    "gn:asciiname":"Guo'ao",
    "gn:country_code":"CN",
    "gn:dem":502,
    "gn:feature_class":"P",
    "gn:feature_code":"PPL",
    "gn:name":"Guo\u2019ao",
    "gn:population":0,
    "gn:timezone":"Asia/Shanghai",
    "iso:country":"CN",
    "name:und_x_variant":[
        "Guo\u2019ao"
    ],
    "name:zho_x_preferred":[
        "\u90ed\u5c99"
    ],
    "wof:name":"Guo'ao",
    "wof:placetype":"locality"
},
  "geometry": {"coordinates":[120.39051000000001,27.94843],"type":"Point"}
}