{
  "type": "Feature",
  "properties": {
    "gn:admin1_code":"24.0",
    "gn:asciiname":"Xiangling",
    "gn:country_code":"CN",
    "gn:dem":428,
    "gn:feature_class":"P",
    "gn:feature_code":"PPLA4",
    "gn:name":"Xiangling",
    "gn:population":0,
    "gn:timezone":"Asia/Shanghai",
    "iso:country":"CN",
    "name:und_x_variant":[
        "Syanlin",
        "Hsiang-ling-ch\u2019eng",
        "Chiu-hsiang-ling",
        "Hsiang-ling",
        "Sianglinghsien",
        "Hsiang-ling-hsien",
        "Xiangling",
        "\u8944\u9675",
        "Xiangling Zhen",
        "\u8944\u9675\u9547"
    ],
    "wof:name":"Xiangling",
    "wof:placetype":"locality"
},
  "geometry": {"coordinates":[111.40000000000001,36.02722],"type":"Point"}
}