{
  "type": "Feature",
  "properties": {
    "gn:admin1_code":"30.0",
    "gn:asciiname":"Luobaijiao",
    "gn:country_code":"CN",
    "gn:dem":237,
    "gn:feature_class":"P",
    "gn:feature_code":"PPL",
    "gn:name":"Luobaijiao",
    "gn:population":0,
    "gn:timezone":"Asia/Shanghai",
    "iso:country":"CN",
    "name:zho_x_preferred":[
        "\u7f57\u767d\u89d2"
    ],
    "wof:name":"Luobaijiao",
    "wof:placetype":"locality"
},
  "geometry": {"coordinates":[112.17431999999999,22.45057000000001],"type":"Point"}
}