{
  "type": "Feature",
  "properties": {
    "gn:admin1_code":"8.0",
    "gn:asciiname":"Dabaishuncun",
    "gn:country_code":"CN",
    "gn:dem":191,
    "gn:feature_class":"P",
    "gn:feature_code":"PPL",
    "gn:name":"Dabaishuncun",
    "gn:population":0,
    "gn:timezone":"Asia/Shanghai",
    "iso:country":"CN",
    "name:zho_x_preferred":[
        "\u5927\u767e\u987a\u6751"
    ],
    "wof:name":"Dabaishuncun",
    "wof:placetype":"locality"
},
  "geometry": {"coordinates":[129.95623999999998,45.68045],"type":"Point"}
}