{
  "type": "Feature",
  "properties": {
    "gn:admin1_code":"3.0",
    "gn:asciiname":"Laojiayuan",
    "gn:country_code":"CN",
    "gn:dem":142,
    "gn:feature_class":"P",
    "gn:feature_code":"PPL",
    "gn:name":"Laojiayuan",
    "gn:population":0,
    "gn:timezone":"Asia/Shanghai",
    "iso:country":"CN",
    "name:zho_x_preferred":[
        "\u8001\u5bb6\u6e90"
    ],
    "wof:name":"Laojiayuan",
    "wof:placetype":"locality"
},
  "geometry": {"coordinates":[117.67946000000001,28.21109],"type":"Point"}
}