{
  "type": "Feature",
  "properties": {
    "gn:admin1_code":"26.0",
    "gn:asciiname":"Nanzhai",
    "gn:country_code":"CN",
    "gn:dem":903,
    "gn:feature_class":"P",
    "gn:feature_code":"PPLA4",
    "gn:name":"Nanzhai",
    "gn:population":0,
    "gn:timezone":"Asia/Shanghai",
    "iso:country":"CN",
    "name:und_x_variant":[
        "\u5357\u5be8",
        "Nanzhai Zhen",
        "\u5357\u5be8\u9547"
    ],
    "wof:name":"Nanzhai",
    "wof:placetype":"locality"
},
  "geometry": {"coordinates":[107.17366,34.65714000000001],"type":"Point"}
}