{
  "type": "Feature",
  "properties": {
    "gn:admin1_code":"30",
    "gn:asciiname":"Jingmen",
    "gn:country_code":"CN",
    "gn:dem":99,
    "gn:feature_class":"P",
    "gn:feature_code":"PPLA4",
    "gn:name":"Jingmen",
    "gn:population":0,
    "gn:timezone":"Asia/Shanghai",
    "iso:country":"CN",
    "name:und_x_variant":[
        "Jingmen Zhen"
    ],
    "name:zho_x_preferred":[
        "\u5f84\u95e8"
    ],
    "name:zho_x_variant":[
        "\u5f84\u95e8\u9547"
    ],
    "wof:name":"Jingmen",
    "wof:placetype":"locality"
},
  "geometry": {"coordinates":[116.35972,24.07083],"type":"Point"}
}