{
  "type": "Feature",
  "properties": {
    "gn:admin1_code":"30",
    "gn:asciiname":"Jingmen",
    "gn:country_code":"CN",
    "gn:dem":99,
    "gn:feature_class":"P",
    "gn:feature_code":"PPLA4",
    "gn:name":"Jingmen",
    "gn:population":0,
    "gn:timezone":"Asia/Shanghai",
    "iso:country":"CN",
    "name:ara_x_preferred":[
        "\u0645\u062f\u064a\u0646\u0629 \u062c\u064a\u0646\u063a\u0645\u0646"
    ],
    "name:cdo_x_preferred":[
        "G\u012dng-mu\u00f2ng"
    ],
    "name:ceb_x_preferred":[
        "Jingmen Shi"
    ],
    "name:ces_x_preferred":[
        "\u0164ing-men"
    ],
    "name:dan_x_preferred":[
        "Jingmen"
    ],
    "name:deu_x_preferred":[
        "Jingmen"
    ],
    "name:eus_x_preferred":[
        "Jingmen"
    ],
    "name:fas_x_preferred":[
        "\u062c\u06cc\u0646\u06af\u0645\u0646"
    ],
    "name:fin_x_preferred":[
        "Jingmen"
    ],
    "name:fra_x_preferred":[
        "Jingmen"
    ],
    "name:ita_x_preferred":[
        "Jingmen"
    ],
    "name:jpn_x_preferred":[
        "\u834a\u9580\u5e02"
    ],
    "name:kik_x_preferred":[
        "Jingmen"
    ],
    "name:kor_x_preferred":[
        "\uc9d5\uba3c\uc2dc"
    ],
    "name:mlg_x_preferred":[
        "Jingmen"
    ],
    "name:nld_x_preferred":[
        "Jingmen"
    ],
    "name:nno_x_preferred":[
        "Jingmen"
    ],
    "name:nor_x_preferred":[
        "Jingmen"
    ],
    "name:pam_x_preferred":[
        "Jingmen"
    ],
    "name:pol_x_preferred":[
        "Jingmen"
    ],
    "name:por_x_preferred":[
        "Jingmen"
    ],
    "name:rus_x_preferred":[
        "\u0426\u0437\u0438\u043d\u043c\u044d\u043d\u044c"
    ],
    "name:spa_x_preferred":[
        "Jingmen"
    ],
    "name:swe_x_preferred":[
        "Jingmen"
    ],
    "name:tgl_x_preferred":[
        "Jingmen"
    ],
    "name:tur_x_preferred":[
        "Jingmen"
    ],
    "name:und_x_variant":[
        "Jingmen Zhen"
    ],
    "name:urd_x_preferred":[
        "\u062c\u0646\u06af\u0645\u06cc\u0646"
    ],
    "name:vie_x_preferred":[
        "Kinh M\u00f4n"
    ],
    "name:war_x_preferred":[
        "Jingmen"
    ],
    "name:zho_x_preferred":[
        "\u5f84\u95e8"
    ],
    "name:zho_x_variant":[
        "\u5f84\u95e8\u9547",
        "\u8346\u95e8\u5e02"
    ],
    "wof:name":"Jingmen",
    "wof:placetype":"locality"
},
  "geometry": {"coordinates":[116.35972,24.07083],"type":"Point"}
}