{
  "type": "Feature",
  "properties": {
    "gn:admin1_code":"20.0",
    "gn:asciiname":"Xinsheng Wudui",
    "gn:country_code":"CN",
    "gn:dem":380,
    "gn:feature_class":"P",
    "gn:feature_code":"PPLF",
    "gn:name":"Xinsheng Wudui",
    "gn:population":0,
    "gn:timezone":"Asia/Shanghai",
    "iso:country":"CN",
    "name:zho_x_preferred":[
        "\u65b0\u80dc\u4e94\u961f"
    ],
    "wof:name":"Xinsheng Wudui",
    "wof:placetype":"locality"
},
  "geometry": {"coordinates":[123.27589,48.65507],"type":"Point"}
}