{
  "type": "Feature",
  "properties": {
    "gn:admin1_code":"13",
    "gn:asciiname":"Shuiliying Sanlian",
    "gn:country_code":"CN",
    "gn:dem":477,
    "gn:feature_class":"P",
    "gn:feature_code":"PPL",
    "gn:name":"Shuiliying Sanlian",
    "gn:population":0,
    "gn:timezone":"Asia/Urumqi",
    "iso:country":"CN",
    "name:zho_x_preferred":[
        "\u6c34\u5229\u8425\u4e09\u8fde"
    ],
    "wof:name":"Shuiliying Sanlian",
    "wof:placetype":"locality"
},
  "geometry": {"coordinates":[87.54118000000003,44.14682],"type":"Point"}
}