{
  "type": "Feature",
  "properties": {
    "gn:admin1_code":"10",
    "gn:asciiname":"Yangmengzhuang",
    "gn:country_code":"CN",
    "gn:dem":13,
    "gn:feature_class":"P",
    "gn:feature_code":"PPL",
    "gn:name":"Yangmengzhuang",
    "gn:population":0,
    "gn:timezone":"Asia/Shanghai",
    "iso:country":"CN",
    "name:zho_x_preferred":[
        "\u6768\u5b5f\u5e84"
    ],
    "wof:name":"Yangmengzhuang",
    "wof:placetype":"locality"
},
  "geometry": {"coordinates":[115.804,38.9258],"type":"Point"}
}