{
  "type": "Feature",
  "properties": {
    "gn:admin1_code":"32.0",
    "gn:asciiname":"Fengjiawan",
    "gn:country_code":"CN",
    "gn:dem":489,
    "gn:feature_class":"P",
    "gn:feature_code":"PPL",
    "gn:name":"Fengjiawan",
    "gn:population":0,
    "gn:timezone":"Asia/Shanghai",
    "iso:country":"CN",
    "name:und_x_variant":[
        "\u5949\u5bb6\u6e7e"
    ],
    "wof:name":"Fengjiawan",
    "wof:placetype":"locality"
},
  "geometry": {"coordinates":[106.26322,32.23132],"type":"Point"}
}