{
  "type": "Feature",
  "properties": {
    "gn:admin1_code":"16.0",
    "gn:asciiname":"Guifeng",
    "gn:country_code":"CN",
    "gn:dem":495,
    "gn:feature_class":"P",
    "gn:feature_code":"PPL",
    "gn:name":"Guifeng",
    "gn:population":0,
    "gn:timezone":"Asia/Shanghai",
    "iso:country":"CN",
    "name:zho_x_preferred":[
        "\u89c4\u4e30"
    ],
    "wof:name":"Guifeng",
    "wof:placetype":"locality"
},
  "geometry": {"coordinates":[105.616,23.0914],"type":"Point"}
}