{
  "type": "Feature",
  "properties": {
    "gn:admin1_code":"2.0",
    "gn:asciiname":"Shuidong",
    "gn:country_code":"CN",
    "gn:dem":39,
    "gn:feature_class":"P",
    "gn:feature_code":"PPL",
    "gn:name":"Shuidong",
    "gn:population":0,
    "gn:timezone":"Asia/Shanghai",
    "iso:country":"CN",
    "name:und_x_variant":[
        "\u6c34\u8463",
        "Shuidong"
    ],
    "wof:name":"Shuidong",
    "wof:placetype":"locality"
},
  "geometry": {"coordinates":[119.43076000000001,29.20695],"type":"Point"}
}