{
  "type": "Feature",
  "properties": {
    "gn:admin1_code":"4.0",
    "gn:asciiname":"Meijiadun",
    "gn:country_code":"CN",
    "gn:dem":1,
    "gn:feature_class":"P",
    "gn:feature_code":"PPL",
    "gn:name":"Meijiadun",
    "gn:population":0,
    "gn:timezone":"Asia/Shanghai",
    "iso:country":"CN",
    "name:zho_x_preferred":[
        "\u6885\u5bb6\u58a9"
    ],
    "wof:name":"Meijiadun",
    "wof:placetype":"locality"
},
  "geometry": {"coordinates":[120.30683000000001,32.81491],"type":"Point"}
}