{
  "type": "Feature",
  "properties": {
    "gn:admin1_code":"4.0",
    "gn:asciiname":"Wangguoxu",
    "gn:country_code":"CN",
    "gn:dem":6,
    "gn:feature_class":"P",
    "gn:feature_code":"PPL",
    "gn:name":"Wangguoxu",
    "gn:population":0,
    "gn:timezone":"Asia/Shanghai",
    "iso:country":"CN",
    "name:zho_x_preferred":[
        "\u738b\u90ed\u5729"
    ],
    "wof:name":"Wangguoxu",
    "wof:placetype":"locality"
},
  "geometry": {"coordinates":[120.73999999999999,32.0775],"type":"Point"}
}