{
  "type": "Feature",
  "properties": {
    "gn:admin1_code":"19.0",
    "gn:asciiname":"Yangshudi",
    "gn:country_code":"CN",
    "gn:dem":38,
    "gn:feature_class":"P",
    "gn:feature_code":"PPL",
    "gn:name":"Yangshudi",
    "gn:population":0,
    "gn:timezone":"Asia/Shanghai",
    "iso:country":"CN",
    "name:und_x_variant":[
        "\u6768\u6811\u5e95"
    ],
    "name:zho_x_preferred":[
        "\u6768\u6811\u5e95"
    ],
    "wof:name":"Yangshudi",
    "wof:placetype":"locality"
},
  "geometry": {"coordinates":[122.19522000000001,39.5149],"type":"Point"}
}