{
  "type": "Feature",
  "properties": {
    "gn:admin1_code":"11.0",
    "gn:asciiname":"Guanjingping",
    "gn:country_code":"CN",
    "gn:dem":82,
    "gn:feature_class":"P",
    "gn:feature_code":"PPL",
    "gn:name":"Guanjingping",
    "gn:population":0,
    "gn:timezone":"Asia/Shanghai",
    "iso:country":"CN",
    "name:zho_x_preferred":[
        "Guanjingping"
    ],
    "name:zho_x_variant":[
        "\u89c2\u4e95\u576a"
    ],
    "wof:name":"Guanjingping",
    "wof:placetype":"locality"
},
  "geometry": {"coordinates":[111.55933,29.34407],"type":"Point"}
}