{
  "type": "Feature",
  "properties": {
    "gn:admin1_code":"3.0",
    "gn:asciiname":"Wugumiao",
    "gn:country_code":"CN",
    "gn:dem":183,
    "gn:feature_class":"P",
    "gn:feature_code":"PPL",
    "gn:name":"Wugumiao",
    "gn:population":0,
    "gn:timezone":"Asia/Shanghai",
    "iso:country":"CN",
    "name:und_x_variant":[
        "\u4e94\u8c37\u5e99"
    ],
    "wof:name":"Wugumiao",
    "wof:placetype":"locality"
},
  "geometry": {"coordinates":[115.18789,29.19354],"type":"Point"}
}