{
  "type": "Feature",
  "properties": {
    "gn:admin1_code":"10.0",
    "gn:asciiname":"Nanzhongyuan",
    "gn:country_code":"CN",
    "gn:dem":13,
    "gn:feature_class":"P",
    "gn:feature_code":"PPL",
    "gn:name":"Nanzhongyuan",
    "gn:population":0,
    "gn:timezone":"Asia/Shanghai",
    "iso:country":"CN",
    "name:zho_x_preferred":[
        "\u5357\u4e2d\u539f"
    ],
    "wof:name":"Nanzhongyuan",
    "wof:placetype":"locality"
},
  "geometry": {"coordinates":[116.21599999999999,38.4518],"type":"Point"}
}