{
  "type": "Feature",
  "properties": {
    "gn:admin1_code":"29.0",
    "gn:asciiname":"Sunjiazhuang",
    "gn:country_code":"CN",
    "gn:dem":1891,
    "gn:feature_class":"P",
    "gn:feature_code":"PPL",
    "gn:name":"Sunjiazhuang",
    "gn:population":0,
    "gn:timezone":"Asia/Shanghai",
    "iso:country":"CN",
    "name:zho_x_preferred":[
        "\u5b59\u5bb6\u5e84"
    ],
    "wof:name":"Sunjiazhuang",
    "wof:placetype":"locality"
},
  "geometry": {"coordinates":[103.56100000000001,25.0334],"type":"Point"}
}