{
  "type": "Feature",
  "properties": {
    "gn:admin1_code":"8.0",
    "gn:asciiname":"Hekoucun",
    "gn:country_code":"CN",
    "gn:dem":176,
    "gn:feature_class":"P",
    "gn:feature_code":"PPL",
    "gn:name":"Hekoucun",
    "gn:population":0,
    "gn:timezone":"Asia/Shanghai",
    "iso:country":"CN",
    "name:zho_x_preferred":[
        "\u6cb3\u53e3\u6751"
    ],
    "wof:name":"Hekoucun",
    "wof:placetype":"locality"
},
  "geometry": {"coordinates":[130.19277,45.9815],"type":"Point"}
}