{
  "type": "Feature",
  "properties": {
    "gn:admin1_code":"3.0",
    "gn:asciiname":"Tengqiao Fenchang",
    "gn:country_code":"CN",
    "gn:dem":111,
    "gn:feature_class":"P",
    "gn:feature_code":"PPLF",
    "gn:name":"Tengqiao Fenchang",
    "gn:population":0,
    "gn:timezone":"Asia/Shanghai",
    "iso:country":"CN",
    "name:und_x_variant":[
        "\u85e4\u6865\u5206\u573a"
    ],
    "wof:name":"Tengqiao Fenchang",
    "wof:placetype":"locality"
},
  "geometry": {"coordinates":[114.77909,28.49907],"type":"Point"}
}