{
  "type": "Feature",
  "properties": {
    "gn:admin1_code":"14.0",
    "gn:asciiname":"Guole",
    "gn:country_code":"CN",
    "gn:dem":4261,
    "gn:feature_class":"P",
    "gn:feature_code":"PPL",
    "gn:name":"Guole",
    "gn:population":0,
    "gn:timezone":"Asia/Urumqi",
    "iso:country":"CN",
    "name:zho_x_preferred":[
        "\u679c\u52d2"
    ],
    "wof:name":"Guole",
    "wof:placetype":"locality"
},
  "geometry": {"coordinates":[96.27160000000001,30.73601],"type":"Point"}
}