{
  "type": "Feature",
  "properties": {
    "gn:admin1_code":"26.0",
    "gn:asciiname":"Yuanzili",
    "gn:country_code":"CN",
    "gn:dem":906,
    "gn:feature_class":"P",
    "gn:feature_code":"PPL",
    "gn:name":"Yuanzili",
    "gn:population":0,
    "gn:timezone":"Asia/Shanghai",
    "iso:country":"CN",
    "name:und_x_variant":[
        "\u56ed\u5b50\u91cc"
    ],
    "wof:name":"Yuanzili",
    "wof:placetype":"locality"
},
  "geometry": {"coordinates":[106.16616999999999,33.39596],"type":"Point"}
}