{
  "type": "Feature",
  "properties": {
    "gn:admin1_code":"24.0",
    "gn:asciiname":"Houbeitou",
    "gn:country_code":"CN",
    "gn:dem":692,
    "gn:feature_class":"P",
    "gn:feature_code":"PPL",
    "gn:name":"Houbeitou",
    "gn:population":0,
    "gn:timezone":"Asia/Shanghai",
    "iso:country":"CN",
    "name:zho_x_preferred":[
        "\u540e\u5317\u5934"
    ],
    "wof:name":"Houbeitou",
    "wof:placetype":"locality"
},
  "geometry": {"coordinates":[110.41304,36.89943],"type":"Point"}
}