{
  "type": "Feature",
  "properties": {
    "gn:admin1_code":"14.0",
    "gn:asciiname":"Xiangrenlunkang",
    "gn:country_code":"CN",
    "gn:dem":4550,
    "gn:feature_class":"P",
    "gn:feature_code":"PPL",
    "gn:name":"Xiangrenlunkang",
    "gn:population":0,
    "gn:timezone":"Asia/Urumqi",
    "iso:country":"CN",
    "name:zho_x_preferred":[
        "\u9999\u4ec1\u4f26\u5eb7"
    ],
    "wof:name":"Xiangrenlunkang",
    "wof:placetype":"locality"
},
  "geometry": {"coordinates":[91.87354999999999,30.59836],"type":"Point"}
}