{
  "type": "Feature",
  "properties": {
    "gn:admin1_code":"07",
    "gn:asciiname":"Chendong",
    "gn:country_code":"CN",
    "gn:dem":367,
    "gn:feature_class":"P",
    "gn:feature_code":"PPLA4",
    "gn:name":"Chendong",
    "gn:population":0,
    "gn:timezone":"Asia/Shanghai",
    "iso:country":"CN",
    "name:und_x_variant":[
        "Chendong Xiang"
    ],
    "name:zho_x_preferred":[
        "Ch\u2019en-tung"
    ],
    "name:zho_x_variant":[
        "\u9648\u4e1c\u4e61"
    ],
    "wof:name":"Chendong",
    "wof:placetype":"locality"
},
  "geometry": {"coordinates":[116.91049,24.72014],"type":"Point"}
}