{
  "type": "Feature",
  "properties": {
    "gn:admin1_code":"11",
    "gn:asciiname":"Xiacha",
    "gn:country_code":"CN",
    "gn:dem":259,
    "gn:feature_class":"P",
    "gn:feature_code":"PPL",
    "gn:name":"Xiacha",
    "gn:population":0,
    "gn:timezone":"Asia/Shanghai",
    "iso:country":"CN",
    "name:und_x_variant":[
        "\u4e0b\u69ce",
        "Xiacha"
    ],
    "wof:name":"Xiacha",
    "wof:placetype":"locality"
},
  "geometry": {"coordinates":[112.1675,25.9725],"type":"Point"}
}