{
  "type": "Feature",
  "properties": {
    "gn:admin1_code":"4.0",
    "gn:asciiname":"Xudaicun",
    "gn:country_code":"CN",
    "gn:dem":6,
    "gn:feature_class":"P",
    "gn:feature_code":"PPL",
    "gn:name":"Xudaicun",
    "gn:population":0,
    "gn:timezone":"Asia/Shanghai",
    "iso:country":"CN",
    "name:zho_x_preferred":[
        "\u8bb8\u6234\u6751"
    ],
    "wof:name":"Xudaicun",
    "wof:placetype":"locality"
},
  "geometry": {"coordinates":[119.72204000000001,32.91129],"type":"Point"}
}