{
  "type": "Feature",
  "properties": {
    "gn:admin1_code":"05",
    "gn:asciiname":"Sunjiajie",
    "gn:cc2":"CN",
    "gn:country_code":"CN",
    "gn:dem":339,
    "gn:feature_class":"P",
    "gn:feature_code":"PPL",
    "gn:name":"Sunjiajie",
    "gn:population":0,
    "gn:timezone":"Asia/Shanghai",
    "iso:country":"CN",
    "name:und_x_variant":[
        "Chou-chia-chieh",
        "Sunjiajie"
    ],
    "wof:name":"Sunjiajie",
    "wof:placetype":"locality"
},
  "geometry": {"coordinates":[126.1925,42.59167],"type":"Point"}
}