{
  "type": "Feature",
  "properties": {
    "gn:admin1_code":"4.0",
    "gn:asciiname":"Xiangyang",
    "gn:country_code":"CN",
    "gn:dem":4,
    "gn:feature_class":"P",
    "gn:feature_code":"PPL",
    "gn:name":"Xiangyang",
    "gn:population":0,
    "gn:timezone":"Asia/Shanghai",
    "iso:country":"CN",
    "name:afr_x_preferred":[
        "Xiangyang"
    ],
    "name:ara_x_preferred":[
        "\u0634\u064a\u0627\u0646\u063a\u064a\u0627\u0646\u063a"
    ],
    "name:cdo_x_preferred":[
        "Si\u014fng-i\u00f2ng"
    ],
    "name:ceb_x_preferred":[
        "Xiangyang"
    ],
    "name:ces_x_preferred":[
        "Siang-jang"
    ],
    "name:cym_x_preferred":[
        "Xiangyang"
    ],
    "name:dan_x_preferred":[
        "Xiangfan"
    ],
    "name:deu_x_preferred":[
        "Xiangyang"
    ],
    "name:eus_x_preferred":[
        "Xiangfan"
    ],
    "name:fas_x_preferred":[
        "\u0634\u06cc\u0627\u0646\u06af\u06cc\u0627\u0646\u06af"
    ],
    "name:fin_x_preferred":[
        "Xiangyang"
    ],
    "name:fra_x_preferred":[
        "Xiangyang"
    ],
    "name:heb_x_preferred":[
        "\u05e7\u05e1\u05d9\u05d0\u05e0\u05d2\u05d9\u05d0\u05e0\u05d2"
    ],
    "name:hun_x_preferred":[
        "Xiangyang"
    ],
    "name:ind_x_preferred":[
        "Xiangyang"
    ],
    "name:ita_x_preferred":[
        "Xiangyang"
    ],
    "name:jpn_x_preferred":[
        "\u8944\u967d\u5e02"
    ],
    "name:kik_x_preferred":[
        "Xiangyang"
    ],
    "name:kor_x_preferred":[
        "\uc0f9\uc591\uc2dc"
    ],
    "name:mlg_x_preferred":[
        "Xiangyang"
    ],
    "name:nld_x_preferred":[
        "Xiangyang"
    ],
    "name:nno_x_preferred":[
        "Xiangyang"
    ],
    "name:nor_x_preferred":[
        "Xiangfan"
    ],
    "name:pam_x_preferred":[
        "Xiangyang"
    ],
    "name:pol_x_preferred":[
        "Xiangyang"
    ],
    "name:por_x_preferred":[
        "Xiangyang"
    ],
    "name:rus_x_preferred":[
        "\u0421\u044f\u043d\u044a\u044f\u043d"
    ],
    "name:spa_x_preferred":[
        "Xiangyang"
    ],
    "name:srp_x_preferred":[
        "\u0421\u0458\u0430\u043d\u0433\u0458\u0430\u043d\u0433"
    ],
    "name:swe_x_preferred":[
        "Xiangyang"
    ],
    "name:tgl_x_preferred":[
        "Xiangyang"
    ],
    "name:tur_x_preferred":[
        "Xiangyang"
    ],
    "name:ukr_x_preferred":[
        "\u0421\u044f\u043d'\u044f\u043d"
    ],
    "name:urd_x_preferred":[
        "\u0634\u06cc\u0627\u0646\u06af\u06cc\u0627\u0646\u06af"
    ],
    "name:vie_x_preferred":[
        "T\u01b0\u01a1ng D\u01b0\u01a1ng"
    ],
    "name:war_x_preferred":[
        "Xiangfan"
    ],
    "name:zho_x_preferred":[
        "\u5411\u9633"
    ],
    "name:zho_x_variant":[
        "\u8944\u9633\u5e02"
    ],
    "wof:name":"Xiangyang",
    "wof:placetype":"locality"
},
  "geometry": {"coordinates":[120.77522999999999,32.49251],"type":"Point"}
}