{
  "type": "Feature",
  "properties": {
    "gn:admin1_code":"29.0",
    "gn:asciiname":"Tuantuanhe",
    "gn:country_code":"CN",
    "gn:dem":1948,
    "gn:feature_class":"P",
    "gn:feature_code":"PPL",
    "gn:name":"Tuantuanhe",
    "gn:population":0,
    "gn:timezone":"Asia/Shanghai",
    "iso:country":"CN",
    "name:zho_x_preferred":[
        "\u56e2\u56e2\u6cb3"
    ],
    "wof:name":"Tuantuanhe",
    "wof:placetype":"locality"
},
  "geometry": {"coordinates":[103.268,25.3996],"type":"Point"}
}