{
  "type": "Feature",
  "properties": {
    "gn:admin1_code":"18.0",
    "gn:asciiname":"Songbai",
    "gn:country_code":"CN",
    "gn:dem":2133,
    "gn:feature_class":"P",
    "gn:feature_code":"PPL",
    "gn:name":"Songbai",
    "gn:population":0,
    "gn:timezone":"Asia/Shanghai",
    "iso:country":"CN",
    "wof:name":"Songbai",
    "wof:placetype":"locality"
},
  "geometry": {"coordinates":[104.56667,26.15833],"type":"Point"}
}