{
  "type": "Feature",
  "properties": {
    "gn:admin1_code":"11",
    "gn:asciiname":"Sanyantang",
    "gn:country_code":"CN",
    "gn:dem":35,
    "gn:feature_class":"P",
    "gn:feature_code":"PPLA4",
    "gn:name":"Sanyantang",
    "gn:population":0,
    "gn:timezone":"Asia/Shanghai",
    "iso:country":"CN",
    "name:und_x_variant":[
        "San-yen-t\u2019ang",
        "Sanyantang",
        "Sanyantang Zhen"
    ],
    "name:zho_x_preferred":[
        "\u4e09\u773c\u5858"
    ],
    "name:zho_x_variant":[
        "\u4e09\u773c\u5858\u9547"
    ],
    "wof:name":"Sanyantang",
    "wof:placetype":"locality"
},
  "geometry": {"coordinates":[112.35693999999999,28.76722],"type":"Point"}
}