{
  "type": "Feature",
  "properties": {
    "gn:admin1_code":"8.0",
    "gn:asciiname":"Tanyaogou",
    "gn:country_code":"CN",
    "gn:dem":75,
    "gn:feature_class":"P",
    "gn:feature_code":"PPL",
    "gn:name":"Tanyaogou",
    "gn:population":0,
    "gn:timezone":"Asia/Shanghai",
    "iso:country":"CN",
    "name:zho_x_preferred":[
        "\u78b3\u7a91\u6c9f"
    ],
    "wof:name":"Tanyaogou",
    "wof:placetype":"locality"
},
  "geometry": {"coordinates":[130.79781,47.96512],"type":"Point"}
}