{
  "type": "Feature",
  "properties": {
    "gn:admin1_code":"05",
    "gn:asciiname":"Daxicha",
    "gn:country_code":"CN",
    "gn:dem":724,
    "gn:feature_class":"P",
    "gn:feature_code":"PPL",
    "gn:name":"Daxicha",
    "gn:population":0,
    "gn:timezone":"Asia/Shanghai",
    "iso:country":"CN",
    "name:und_x_variant":[
        "\u5927\u897f\u5c94"
    ],
    "wof:name":"Daxicha",
    "wof:placetype":"locality"
},
  "geometry": {"coordinates":[126.94528,42.18694],"type":"Point"}
}