{
  "type": "Feature",
  "properties": {
    "gn:admin1_code":"24",
    "gn:asciiname":"Jingwan",
    "gn:cc2":"CN",
    "gn:country_code":"CN",
    "gn:dem":1014,
    "gn:feature_class":"P",
    "gn:feature_code":"PPL",
    "gn:name":"Jingwan",
    "gn:population":0,
    "gn:timezone":"Asia/Shanghai",
    "iso:country":"CN",
    "name:und_x_variant":[
        "Ching-wan",
        "Jingwan"
    ],
    "wof:name":"Jingwan",
    "wof:placetype":"locality"
},
  "geometry": {"coordinates":[113.16667,35.46667],"type":"Point"}
}