{
  "type": "Feature",
  "properties": {
    "gn:admin1_code":"16",
    "gn:asciiname":"Xiatiandun",
    "gn:country_code":"CN",
    "gn:dem":161,
    "gn:feature_class":"P",
    "gn:feature_code":"PPL",
    "gn:name":"Xiatiandun",
    "gn:population":0,
    "gn:timezone":"Asia/Shanghai",
    "iso:country":"CN",
    "name:zho_x_preferred":[
        "\u4e0b\u7530\u58a9"
    ],
    "wof:name":"Xiatiandun",
    "wof:placetype":"locality"
},
  "geometry": {"coordinates":[110.364,24.7829],"type":"Point"}
}