{
  "type": "Feature",
  "properties": {
    "gn:admin1_code":"11.0",
    "gn:asciiname":"Qiuzhai",
    "gn:country_code":"CN",
    "gn:dem":447,
    "gn:feature_class":"P",
    "gn:feature_code":"PPL",
    "gn:name":"Qiuzhai",
    "gn:population":0,
    "gn:timezone":"Asia/Shanghai",
    "iso:country":"CN",
    "name:zho_x_preferred":[
        "\u79cb\u5be8"
    ],
    "wof:name":"Qiuzhai",
    "wof:placetype":"locality"
},
  "geometry": {"coordinates":[109.12486,27.18393],"type":"Point"}
}