{
  "type": "Feature",
  "properties": {
    "gn:admin1_code":"12.0",
    "gn:asciiname":"Shangleijiaxiang",
    "gn:country_code":"CN",
    "gn:dem":39,
    "gn:feature_class":"P",
    "gn:feature_code":"PPL",
    "gn:name":"Shangleijiaxiang",
    "gn:population":0,
    "gn:timezone":"Asia/Shanghai",
    "iso:country":"CN",
    "name:zho_x_preferred":[
        "\u4e0a\u96f7\u5bb6\u5df7"
    ],
    "wof:name":"Shangleijiaxiang",
    "wof:placetype":"locality"
},
  "geometry": {"coordinates":[112.16594000000001,29.7658],"type":"Point"}
}