{
  "type": "Feature",
  "properties": {
    "gn:admin1_code":"15.0",
    "gn:asciiname":"Liushui",
    "gn:country_code":"CN",
    "gn:dem":1734,
    "gn:feature_class":"P",
    "gn:feature_code":"PPL",
    "gn:name":"Liushui",
    "gn:population":0,
    "gn:timezone":"Asia/Shanghai",
    "iso:country":"CN",
    "name:zho_x_preferred":[
        "\u6d41\u6c34"
    ],
    "wof:name":"Liushui",
    "wof:placetype":"locality"
},
  "geometry": {"coordinates":[105.34399999999999,34.59],"type":"Point"}
}