{
  "type": "Feature",
  "properties": {
    "gn:admin1_code":"5",
    "gn:asciiname":"Liushuhezi",
    "gn:country_code":"CN",
    "gn:dem":280,
    "gn:feature_class":"P",
    "gn:feature_code":"PPL",
    "gn:name":"Liushuhezi",
    "gn:population":0,
    "gn:timezone":"Asia/Shanghai",
    "iso:country":"CN",
    "name:zho_x_preferred":[
        "\u67f3\u6811\u6cb3\u5b50"
    ],
    "wof:name":"Liushuhezi",
    "wof:placetype":"locality"
},
  "geometry": {"coordinates":[127.214,43.4183],"type":"Point"}
}