{
  "type": "Feature",
  "properties": {
    "gn:admin1_code":"16.0",
    "gn:asciiname":"Shangdiaojing",
    "gn:country_code":"CN",
    "gn:dem":651,
    "gn:feature_class":"P",
    "gn:feature_code":"PPL",
    "gn:name":"Shangdiaojing",
    "gn:population":0,
    "gn:timezone":"Asia/Shanghai",
    "iso:country":"CN",
    "name:zho_x_preferred":[
        "\u4e0a\u540a\u4e95"
    ],
    "wof:name":"Shangdiaojing",
    "wof:placetype":"locality"
},
  "geometry": {"coordinates":[107.087,24.4393],"type":"Point"}
}