{
  "type": "Feature",
  "properties": {
    "gn:admin1_code":"29.0",
    "gn:asciiname":"Manpai",
    "gn:country_code":"CN",
    "gn:dem":1433,
    "gn:feature_class":"P",
    "gn:feature_code":"PPL",
    "gn:name":"Manpai",
    "gn:population":0,
    "gn:timezone":"Asia/Shanghai",
    "iso:country":"CN",
    "name:zho_x_preferred":[
        "\u66fc\u6d3e"
    ],
    "wof:name":"Manpai",
    "wof:placetype":"locality"
},
  "geometry": {"coordinates":[97.9241,24.4651],"type":"Point"}
}