{
  "type": "Feature",
  "properties": {
    "gn:admin1_code":"6.0",
    "gn:asciiname":"Guogai",
    "gn:country_code":"CN",
    "gn:dem":3137,
    "gn:feature_class":"P",
    "gn:feature_code":"PPL",
    "gn:name":"Guogai",
    "gn:population":0,
    "gn:timezone":"Asia/Shanghai",
    "iso:country":"CN",
    "name:zho_x_preferred":[
        "\u8fc7\u6539"
    ],
    "wof:name":"Guogai",
    "wof:placetype":"locality"
},
  "geometry": {"coordinates":[101.8672,35.37164],"type":"Point"}
}