{
  "type": "Feature",
  "properties": {
    "gn:admin1_code":"29.0",
    "gn:asciiname":"Tuguanfen",
    "gn:country_code":"CN",
    "gn:dem":1793,
    "gn:feature_class":"P",
    "gn:feature_code":"PPL",
    "gn:name":"Tuguanfen",
    "gn:population":0,
    "gn:timezone":"Asia/Shanghai",
    "iso:country":"CN",
    "name:zho_x_preferred":[
        "\u571f\u5b98\u575f"
    ],
    "wof:name":"Tuguanfen",
    "wof:placetype":"locality"
},
  "geometry": {"coordinates":[104.88500000000001,27.4713],"type":"Point"}
}