{
  "type": "Feature",
  "properties": {
    "gn:admin1_code":"3.0",
    "gn:asciiname":"Yantongkeng",
    "gn:country_code":"CN",
    "gn:dem":586,
    "gn:feature_class":"P",
    "gn:feature_code":"PPL",
    "gn:name":"Yantongkeng",
    "gn:population":0,
    "gn:timezone":"Asia/Shanghai",
    "iso:country":"CN",
    "name:und_x_variant":[
        "\u70df\u6850\u5751"
    ],
    "wof:name":"Yantongkeng",
    "wof:placetype":"locality"
},
  "geometry": {"coordinates":[114.7296,29.38529],"type":"Point"}
}