{
  "type": "Feature",
  "properties": {
    "gn:admin1_code":"9.0",
    "gn:asciiname":"Houwangzhuang",
    "gn:country_code":"CN",
    "gn:dem":67,
    "gn:feature_class":"P",
    "gn:feature_code":"PPL",
    "gn:name":"Houwangzhuang",
    "gn:population":0,
    "gn:timezone":"Asia/Shanghai",
    "iso:country":"CN",
    "name:zho_x_preferred":[
        "\u540e\u738b\u5e84"
    ],
    "wof:name":"Houwangzhuang",
    "wof:placetype":"locality"
},
  "geometry": {"coordinates":[114.43626999999999,35.48854],"type":"Point"}
}