{
  "type": "Feature",
  "properties": {
    "gn:admin1_code":"16.0",
    "gn:asciiname":"Lawai",
    "gn:country_code":"CN",
    "gn:dem":273,
    "gn:feature_class":"P",
    "gn:feature_code":"PPL",
    "gn:name":"Lawai",
    "gn:population":0,
    "gn:timezone":"Asia/Shanghai",
    "iso:country":"CN",
    "name:zho_x_preferred":[
        "\u62c9\u6b6a"
    ],
    "wof:name":"Lawai",
    "wof:placetype":"locality"
},
  "geometry": {"coordinates":[108.00700000000001,24.281],"type":"Point"}
}