{
  "type": "Feature",
  "properties": {
    "gn:admin1_code":"11",
    "gn:asciiname":"Dapujie",
    "gn:cc2":"CN",
    "gn:country_code":"CN",
    "gn:dem":59,
    "gn:feature_class":"P",
    "gn:feature_code":"PPL",
    "gn:name":"Dapujie",
    "gn:population":0,
    "gn:timezone":"Asia/Shanghai",
    "iso:country":"CN",
    "name:und_x_variant":[
        "Ta-p\u2019u-chieh",
        "Ta-pao",
        "Dapujie"
    ],
    "wof:name":"Dapujie",
    "wof:placetype":"locality"
},
  "geometry": {"coordinates":[112.77861,27.00528],"type":"Point"}
}