{
  "type": "Feature",
  "properties": {
    "gn:admin1_code":"25.0",
    "gn:asciiname":"Dawangjia Shagou",
    "gn:country_code":"CN",
    "gn:dem":32,
    "gn:feature_class":"P",
    "gn:feature_code":"PPL",
    "gn:name":"Dawangjia Shagou",
    "gn:population":0,
    "gn:timezone":"Asia/Shanghai",
    "iso:country":"CN",
    "name:zho_x_preferred":[
        "\u5927\u738b\u5bb6\u6c99\u6c9f"
    ],
    "wof:name":"Dawangjia Shagou",
    "wof:placetype":"locality"
},
  "geometry": {"coordinates":[119.10118,35.08597],"type":"Point"}
}