{
  "type": "Feature",
  "properties": {
    "gn:admin1_code":"16",
    "gn:asciiname":"Dabitou",
    "gn:country_code":"CN",
    "gn:dem":194,
    "gn:feature_class":"P",
    "gn:feature_code":"PPL",
    "gn:name":"Dabitou",
    "gn:population":0,
    "gn:timezone":"Asia/Shanghai",
    "iso:country":"CN",
    "name:zho_x_preferred":[
        "\u5927\u6bd5\u5934"
    ],
    "wof:name":"Dabitou",
    "wof:placetype":"locality"
},
  "geometry": {"coordinates":[110.864,25.8104],"type":"Point"}
}