{
  "type": "Feature",
  "properties": {
    "gn:admin1_code":"1.0",
    "gn:asciiname":"Huangyangcun",
    "gn:country_code":"CN",
    "gn:dem":27,
    "gn:feature_class":"P",
    "gn:feature_code":"PPL",
    "gn:name":"Huangyangcun",
    "gn:population":0,
    "gn:timezone":"Asia/Shanghai",
    "iso:country":"CN",
    "name:zho_x_preferred":[
        "\u9ec4\u6d0b\u6751"
    ],
    "wof:name":"Huangyangcun",
    "wof:placetype":"locality"
},
  "geometry": {"coordinates":[116.16137999999999,32.52426],"type":"Point"}
}