{
  "type": "Feature",
  "properties": {
    "gn:admin1_code":"3.0",
    "gn:asciiname":"Yangliugang",
    "gn:country_code":"CN",
    "gn:dem":71,
    "gn:feature_class":"P",
    "gn:feature_code":"PPL",
    "gn:name":"Yangliugang",
    "gn:population":0,
    "gn:timezone":"Asia/Shanghai",
    "iso:country":"CN",
    "name:und_x_variant":[
        "\u6768\u67f3\u5c97"
    ],
    "wof:name":"Yangliugang",
    "wof:placetype":"locality"
},
  "geometry": {"coordinates":[115.30023,28.46938],"type":"Point"}
}