{
  "type": "Feature",
  "properties": {
    "gn:admin1_code":"11.0",
    "gn:asciiname":"Shangjietou",
    "gn:country_code":"CN",
    "gn:dem":98,
    "gn:feature_class":"P",
    "gn:feature_code":"PPL",
    "gn:name":"Shangjietou",
    "gn:population":0,
    "gn:timezone":"Asia/Shanghai",
    "iso:country":"CN",
    "name:zho_x_preferred":[
        "\u4e0a\u8857\u5934"
    ],
    "wof:name":"Shangjietou",
    "wof:placetype":"locality"
},
  "geometry": {"coordinates":[113.85966999999999,28.65421],"type":"Point"}
}