{
  "type": "Feature",
  "properties": {
    "gn:admin1_code":"29.0",
    "gn:asciiname":"Shaotingcun",
    "gn:country_code":"CN",
    "gn:dem":846,
    "gn:feature_class":"P",
    "gn:feature_code":"PPL",
    "gn:name":"Shaotingcun",
    "gn:population":0,
    "gn:timezone":"Asia/Shanghai",
    "iso:country":"CN",
    "name:zho_x_preferred":[
        "\u7ecd\u5ef7\u6751"
    ],
    "wof:name":"Shaotingcun",
    "wof:placetype":"locality"
},
  "geometry": {"coordinates":[103.887,28.5483],"type":"Point"}
}