{
  "type": "Feature",
  "properties": {
    "gn:admin1_code":"16.0",
    "gn:asciiname":"Penlong",
    "gn:country_code":"CN",
    "gn:dem":53,
    "gn:feature_class":"P",
    "gn:feature_code":"PPL",
    "gn:name":"Penlong",
    "gn:population":0,
    "gn:timezone":"Asia/Shanghai",
    "iso:country":"CN",
    "name:zho_x_preferred":[
        "\u76c6\u9f99"
    ],
    "wof:name":"Penlong",
    "wof:placetype":"locality"
},
  "geometry": {"coordinates":[110.34699999999999,23.335],"type":"Point"}
}