{
  "type": "Feature",
  "properties": {
    "gn:admin1_code":"9.0",
    "gn:asciiname":"Dahechong",
    "gn:country_code":"CN",
    "gn:dem":81,
    "gn:feature_class":"P",
    "gn:feature_code":"PPL",
    "gn:name":"Dahechong",
    "gn:population":0,
    "gn:timezone":"Asia/Shanghai",
    "iso:country":"CN",
    "name:zho_x_preferred":[
        "\u5927\u4f55\u51b2"
    ],
    "wof:name":"Dahechong",
    "wof:placetype":"locality"
},
  "geometry": {"coordinates":[114.50657,31.99054000000001],"type":"Point"}
}