{
  "type": "Feature",
  "properties": {
    "gn:admin1_code":"8.0",
    "gn:asciiname":"Shiba Dayuan",
    "gn:country_code":"CN",
    "gn:dem":157,
    "gn:feature_class":"P",
    "gn:feature_code":"PPL",
    "gn:name":"Shiba Dayuan",
    "gn:population":0,
    "gn:timezone":"Asia/Shanghai",
    "iso:country":"CN",
    "name:zho_x_preferred":[
        "\u5341\u516b\u5927\u9662"
    ],
    "wof:name":"Shiba Dayuan",
    "wof:placetype":"locality"
},
  "geometry": {"coordinates":[124.81901000000001,47.22436],"type":"Point"}
}