{
  "type": "Feature",
  "properties": {
    "gn:admin1_code":"18",
    "gn:asciiname":"Pinghu",
    "gn:cc2":"CN",
    "gn:country_code":"CN",
    "gn:dem":707,
    "gn:feature_class":"P",
    "gn:feature_code":"PPL",
    "gn:name":"Pinghu",
    "gn:population":0,
    "gn:timezone":"Asia/Shanghai",
    "iso:country":"CN",
    "name:und_x_variant":[
        "Chiu-p\u2019ing-chou",
        "P\u2019ing-chou-ku-chih",
        "Pingchowhsien",
        "Pingtang",
        "P\u2019ing-chou-ch\u2019eng",
        "P\u2019ing-chou",
        "Pinghu"
    ],
    "wof:name":"Pinghu",
    "wof:placetype":"locality"
},
  "geometry": {"coordinates":[107.31667,25.83333],"type":"Point"}
}