{
  "type": "Feature",
  "properties": {
    "gn:admin1_code":"18",
    "gn:asciiname":"Pinghu",
    "gn:cc2":"CN",
    "gn:country_code":"CN",
    "gn:dem":707,
    "gn:feature_class":"P",
    "gn:feature_code":"PPL",
    "gn:name":"Pinghu",
    "gn:population":0,
    "gn:timezone":"Asia/Shanghai",
    "iso:country":"CN",
    "name:ara_x_preferred":[
        "\u0628\u0646\u063a\u0647\u0648"
    ],
    "name:deu_x_preferred":[
        "Pinghu"
    ],
    "name:fra_x_preferred":[
        "Pinghu"
    ],
    "name:ita_x_preferred":[
        "Pinghu"
    ],
    "name:jpn_x_preferred":[
        "\u5e73\u6e56\u5e02"
    ],
    "name:kik_x_preferred":[
        "Pinghu"
    ],
    "name:kor_x_preferred":[
        "\ud551\ud6c4\uc2dc"
    ],
    "name:mlg_x_preferred":[
        "Pinghu"
    ],
    "name:nor_x_preferred":[
        "Pinghu"
    ],
    "name:swe_x_preferred":[
        "Pinghu"
    ],
    "name:tgl_x_preferred":[
        "Pinghu"
    ],
    "name:und_x_variant":[
        "Chiu-p\u2019ing-chou",
        "P\u2019ing-chou-ku-chih",
        "Pingchowhsien",
        "Pingtang",
        "P\u2019ing-chou-ch\u2019eng",
        "P\u2019ing-chou"
    ],
    "name:urd_x_preferred":[
        "\u067e\u0646\u06af\u06c1\u0648"
    ],
    "name:vie_x_preferred":[
        "B\u00ecnh H\u1ed3"
    ],
    "name:war_x_preferred":[
        "Pinghu"
    ],
    "name:wuu_x_preferred":[
        "\u5e73\u6e56\u5e02"
    ],
    "name:zho_x_preferred":[
        "\u5e73\u6e56\u5e02"
    ],
    "wof:name":"Pinghu",
    "wof:placetype":"locality"
},
  "geometry": {"coordinates":[107.31667,25.83333],"type":"Point"}
}