{
  "type": "Feature",
  "properties": {
    "gn:admin1_code":"32.0",
    "gn:asciiname":"Wanjiaolin",
    "gn:country_code":"CN",
    "gn:dem":459,
    "gn:feature_class":"P",
    "gn:feature_code":"PPL",
    "gn:name":"Wanjiaolin",
    "gn:population":0,
    "gn:timezone":"Asia/Shanghai",
    "iso:country":"CN",
    "name:zho_x_preferred":[
        "\u4e07\u89d2\u6797"
    ],
    "wof:name":"Wanjiaolin",
    "wof:placetype":"locality"
},
  "geometry": {"coordinates":[104.41254000000001,30.20492],"type":"Point"}
}