{
  "type": "Feature",
  "properties": {
    "gn:admin1_code":"8.0",
    "gn:asciiname":"Houshanwanzi",
    "gn:country_code":"CN",
    "gn:dem":157,
    "gn:feature_class":"P",
    "gn:feature_code":"PPL",
    "gn:name":"Houshanwanzi",
    "gn:population":0,
    "gn:timezone":"Asia/Shanghai",
    "iso:country":"CN",
    "name:zho_x_preferred":[
        "\u540e\u5c71\u6e7e\u5b50"
    ],
    "wof:name":"Houshanwanzi",
    "wof:placetype":"locality"
},
  "geometry": {"coordinates":[126.14793,46.91368],"type":"Point"}
}