{
  "type": "Feature",
  "properties": {
    "gn:admin1_code":"19.0",
    "gn:asciiname":"Goukoucun",
    "gn:country_code":"CN",
    "gn:dem":80,
    "gn:feature_class":"P",
    "gn:feature_code":"PPL",
    "gn:name":"Goukoucun",
    "gn:population":0,
    "gn:timezone":"Asia/Shanghai",
    "iso:country":"CN",
    "name:zho_x_preferred":[
        "\u6c9f\u53e3\u6751"
    ],
    "wof:name":"Goukoucun",
    "wof:placetype":"locality"
},
  "geometry": {"coordinates":[122.389,39.8308],"type":"Point"}
}