{
  "type": "Feature",
  "properties": {
    "gn:country":"CN",
    "gn:fcode":"PPL",
    "gn:population":0,
    "iso:country":"CN",
    "name:und_x_variant":[
        "Pingsha"
    ],
    "name:zho_x_preferred":[
        "\u5e73\u6c99"
    ],
    "qs:name":"\u5e73\u6c99\u534e\u4fa8\u6797\u573a",
    "qs:name_adm0":"\u4e2d\u570b",
    "qs:name_adm1":"\u5e7f\u4e1c\u7701",
    "qs:photos":110,
    "qs:photos_1k":22,
    "qs:photos_9k":1,
    "qs:photos_9r":3,
    "qs:photos_all":110,
    "qs:photos_sr":3,
    "qs:placetype":"Town",
    "qs:pop_sr":"0",
    "wof:name":"\u5e73\u6c99\u534e\u4fa8\u6797\u573a",
    "wof:placetype":"locality",
    "wof:population":0
},
  "geometry": {"coordinates":[112.78077,22.50462],"type":"Point"}
}