{
  "type": "Feature",
  "properties": {
    "gn:admin1_code":"18",
    "gn:asciiname":"Xunjiapo",
    "gn:country_code":"CN",
    "gn:dem":923,
    "gn:feature_class":"P",
    "gn:feature_code":"PPL",
    "gn:name":"Xunjiapo",
    "gn:population":0,
    "gn:timezone":"Asia/Shanghai",
    "iso:country":"CN",
    "name:zho_x_preferred":[
        "\u65ec\u5bb6\u5761"
    ],
    "wof:name":"Xunjiapo",
    "wof:placetype":"locality"
},
  "geometry": {"coordinates":[107.687,28.5301],"type":"Point"}
}