{
  "type": "Feature",
  "properties": {
    "gn:admin1_code":"29.0",
    "gn:asciiname":"Qiangsheng",
    "gn:country_code":"CN",
    "gn:dem":1033,
    "gn:feature_class":"P",
    "gn:feature_code":"PPL",
    "gn:name":"Qiangsheng",
    "gn:population":0,
    "gn:timezone":"Asia/Shanghai",
    "iso:country":"CN",
    "name:und_x_variant":[
        "\u5f3a\u80dc"
    ],
    "wof:name":"Qiangsheng",
    "wof:placetype":"locality"
},
  "geometry": {"coordinates":[103.90770999999999,28.33511],"type":"Point"}
}