{
  "type": "Feature",
  "properties": {
    "gn:admin1_code":"7.0",
    "gn:asciiname":"Wengjiang",
    "gn:country_code":"CN",
    "gn:dem":12,
    "gn:feature_class":"P",
    "gn:feature_code":"PPL",
    "gn:name":"Wengjiang",
    "gn:population":0,
    "gn:timezone":"Asia/Shanghai",
    "iso:country":"CN",
    "name:zho_x_preferred":[
        "\u7fc1\u6c5f"
    ],
    "wof:name":"Wengjiang",
    "wof:placetype":"locality"
},
  "geometry": {"coordinates":[120.1863,27.19838],"type":"Point"}
}