{
  "type": "Feature",
  "properties": {
    "gn:admin1_code":"22",
    "gn:asciiname":"Xixiaoyingcun",
    "gn:country_code":"CN",
    "gn:dem":51,
    "gn:feature_class":"P",
    "gn:feature_code":"PPL",
    "gn:name":"Xixiaoyingcun",
    "gn:population":0,
    "gn:timezone":"Asia/Shanghai",
    "iso:country":"CN",
    "name:und_x_variant":[
        "Xixiaoying"
    ],
    "name:zho_x_preferred":[
        "\u897f\u5c0f\u8425\u6751"
    ],
    "wof:name":"Xixiaoyingcun",
    "wof:placetype":"locality"
},
  "geometry": {"coordinates":[116.15087,40.07699],"type":"Point"}
}