{
  "type": "Feature",
  "properties": {
    "gn:country":"CN",
    "gn:fcode":"PPLA3",
    "gn:pop":0,
    "iso:country":"CN",
    "name:unk_x_variant":[
        "An-ning-chiao"
    ],
    "name:zho_x_preferred":[
        "\u957f\u5b81"
    ],
    "qs:name":"\u957f\u5b81\u53bf",
    "qs:name_adm0":"\u4e2d\u570b",
    "qs:name_adm1":"\u56db\u5ddd\u7701",
    "qs:photos":3,
    "qs:photos_1k":1,
    "qs:photos_9k":1,
    "qs:photos_9r":1,
    "qs:photos_all":3,
    "qs:photos_sr":1,
    "qs:placetype":"LocalAdmin",
    "qs:pop_sr":"5",
    "wd:wordcount":35,
    "wof:name":"\u957f\u5b81\u53bf",
    "wof:placetype":"localadmin",
    "wof:population":0
},
  "geometry": {"coordinates":[104.92086999999999,28.57772],"type":"Point"}
}