{
  "type": "Feature",
  "properties": {
    "gn:country":"CN",
    "gn:fcode":"PPLA3",
    "gn:population":0,
    "iso:country":"CN",
    "name:ceb_x_preferred":[
        "Changning Xian"
    ],
    "name:dan_x_preferred":[
        "Changning"
    ],
    "name:deu_x_preferred":[
        "Changning"
    ],
    "name:eng_x_preferred":[
        "Changning County"
    ],
    "name:fas_x_preferred":[
        "\u0634\u0647\u0631\u0633\u062a\u0627\u0646 \u0634\u0627\u0646\u06af\u0646\u06cc\u0646\u06af"
    ],
    "name:gan_x_preferred":[
        "\u957f\u5b81\u53bf"
    ],
    "name:hak_x_preferred":[
        "Chh\u00f2ng-n\u00e8n-yen"
    ],
    "name:jpn_x_preferred":[
        "\u9577\u5be7\u770c"
    ],
    "name:kor_x_preferred":[
        "\ucc3d\ub2dd \ud604"
    ],
    "name:nan_x_preferred":[
        "Ti\u00f4ng-l\u00eang-ko\u0101n"
    ],
    "name:nld_x_preferred":[
        "Changning"
    ],
    "name:nob_x_preferred":[
        "Changning"
    ],
    "name:rus_x_preferred":[
        "\u0427\u0430\u043d\u043d\u0438\u043d"
    ],
    "name:swe_x_preferred":[
        "Changning"
    ],
    "name:und_x_variant":[
        "An-ning-chiao"
    ],
    "name:vie_x_preferred":[
        "Nam Kh\u00ea"
    ],
    "name:wuu_x_preferred":[
        "\u957f\u5b81\u53bf"
    ],
    "name:zho_x_preferred":[
        "\u957f\u5b81"
    ],
    "name:zho_x_variant":[
        "\u957f\u5b81\u53bf"
    ],
    "qs:name":"\u957f\u5b81\u53bf",
    "qs:name_adm0":"\u4e2d\u570b",
    "qs:name_adm1":"\u56db\u5ddd\u7701",
    "qs:photos":3,
    "qs:photos_1k":1,
    "qs:photos_9k":1,
    "qs:photos_9r":1,
    "qs:photos_all":3,
    "qs:photos_sr":1,
    "qs:placetype":"LocalAdmin",
    "qs:pop_sr":"5",
    "wd:wordcount":35,
    "wof:name":"\u957f\u5b81\u53bf",
    "wof:placetype":"localadmin",
    "wof:population":0
},
  "geometry": {"coordinates":[104.92086999999999,28.57772],"type":"Point"}
}