{
  "type": "Feature",
  "properties": {
    "gn:admin1_code":"1.0",
    "gn:asciiname":"Gaopengcun",
    "gn:country_code":"CN",
    "gn:dem":32,
    "gn:feature_class":"P",
    "gn:feature_code":"PPL",
    "gn:name":"Gaopengcun",
    "gn:population":0,
    "gn:timezone":"Asia/Shanghai",
    "iso:country":"CN",
    "name:zho_x_preferred":[
        "\u9ad8\u5f6d\u6751"
    ],
    "wof:name":"Gaopengcun",
    "wof:placetype":"locality"
},
  "geometry": {"coordinates":[117.14588999999999,33.79257],"type":"Point"}
}