{
  "type": "Feature",
  "properties": {
    "gn:admin1_code":"19.0",
    "gn:asciiname":"Dangputuncun",
    "gn:country_code":"CN",
    "gn:dem":148,
    "gn:feature_class":"P",
    "gn:feature_code":"PPL",
    "gn:name":"Dangputuncun",
    "gn:population":0,
    "gn:timezone":"Asia/Shanghai",
    "iso:country":"CN",
    "name:zho_x_preferred":[
        "\u5f53\u94fa\u5c6f\u6751"
    ],
    "wof:name":"Dangputuncun",
    "wof:placetype":"locality"
},
  "geometry": {"coordinates":[124.17,42.1754],"type":"Point"}
}