{
  "type": "Feature",
  "properties": {
    "gn:admin1_code":"9.0",
    "gn:asciiname":"Qianmagou",
    "gn:country_code":"CN",
    "gn:dem":1032,
    "gn:feature_class":"P",
    "gn:feature_code":"PPL",
    "gn:name":"Qianmagou",
    "gn:population":0,
    "gn:timezone":"Asia/Shanghai",
    "iso:country":"CN",
    "name:zho_x_preferred":[
        "\u524d\u9ebb\u6c9f"
    ],
    "wof:name":"Qianmagou",
    "wof:placetype":"locality"
},
  "geometry": {"coordinates":[111.21550999999999,34.37567],"type":"Point"}
}