{
  "type": "Feature",
  "properties": {
    "gn:admin1_code":"16.0",
    "gn:asciiname":"Jielei",
    "gn:country_code":"CN",
    "gn:dem":771,
    "gn:feature_class":"P",
    "gn:feature_code":"PPL",
    "gn:name":"Jielei",
    "gn:population":0,
    "gn:timezone":"Asia/Shanghai",
    "iso:country":"CN",
    "name:zho_x_preferred":[
        "\u4ecb\u7c7b"
    ],
    "wof:name":"Jielei",
    "wof:placetype":"locality"
},
  "geometry": {"coordinates":[106.91200000000001,24.2533],"type":"Point"}
}