{
  "type": "Feature",
  "properties": {
    "gn:admin1_code":"15.0",
    "gn:asciiname":"Dahanchuan",
    "gn:country_code":"CN",
    "gn:dem":2509,
    "gn:feature_class":"P",
    "gn:feature_code":"PPL",
    "gn:name":"Dahanchuan",
    "gn:population":0,
    "gn:timezone":"Asia/Shanghai",
    "iso:country":"CN",
    "name:zho_x_preferred":[
        "\u5927\u65f1\u5ddd"
    ],
    "wof:name":"Dahanchuan",
    "wof:placetype":"locality"
},
  "geometry": {"coordinates":[103.45,37.2613],"type":"Point"}
}