{
  "type": "Feature",
  "properties": {
    "gn:admin1_code":"26.0",
    "gn:asciiname":"Tianjiapo",
    "gn:country_code":"CN",
    "gn:dem":1197,
    "gn:feature_class":"P",
    "gn:feature_code":"PPL",
    "gn:name":"Tianjiapo",
    "gn:population":0,
    "gn:timezone":"Asia/Shanghai",
    "iso:country":"CN",
    "name:und_x_variant":[
        "\u7530\u5bb6\u5761"
    ],
    "wof:name":"Tianjiapo",
    "wof:placetype":"locality"
},
  "geometry": {"coordinates":[107.13397000000001,33.30631],"type":"Point"}
}