{
  "type": "Feature",
  "properties": {
    "gn:admin1_code":"4.0",
    "gn:asciiname":"Shanguangcun",
    "gn:country_code":"CN",
    "gn:dem":5,
    "gn:feature_class":"P",
    "gn:feature_code":"PPL",
    "gn:name":"Shanguangcun",
    "gn:population":0,
    "gn:timezone":"Asia/Shanghai",
    "iso:country":"CN",
    "name:zho_x_preferred":[
        "\u5c71\u5e7f\u6751"
    ],
    "wof:name":"Shanguangcun",
    "wof:placetype":"locality"
},
  "geometry": {"coordinates":[119.50951999999999,32.70312],"type":"Point"}
}