{
  "type": "Feature",
  "properties": {
    "gn:admin1_code":"18.0",
    "gn:asciiname":"Xiajiadi",
    "gn:country_code":"CN",
    "gn:dem":932,
    "gn:feature_class":"P",
    "gn:feature_code":"PPL",
    "gn:name":"Xiajiadi",
    "gn:population":0,
    "gn:timezone":"Asia/Shanghai",
    "iso:country":"CN",
    "name:zho_x_preferred":[
        "\u4e0b\u7532\u5730"
    ],
    "wof:name":"Xiajiadi",
    "wof:placetype":"locality"
},
  "geometry": {"coordinates":[107.41500000000001,25.7962],"type":"Point"}
}