{
  "type": "Feature",
  "properties": {
    "gn:admin1_code":"1.0",
    "gn:asciiname":"Dazhucun",
    "gn:country_code":"CN",
    "gn:dem":27,
    "gn:feature_class":"P",
    "gn:feature_code":"PPL",
    "gn:name":"Dazhucun",
    "gn:population":0,
    "gn:timezone":"Asia/Shanghai",
    "iso:country":"CN",
    "name:zho_x_preferred":[
        "\u5927\u795d\u6751"
    ],
    "wof:name":"Dazhucun",
    "wof:placetype":"locality"
},
  "geometry": {"coordinates":[116.92247999999999,33.26508],"type":"Point"}
}