{
  "type": "Feature",
  "properties": {
    "gn:admin1_code":"32.0",
    "gn:asciiname":"Dacungou",
    "gn:country_code":"CN",
    "gn:dem":1927,
    "gn:feature_class":"P",
    "gn:feature_code":"PPL",
    "gn:name":"Dacungou",
    "gn:population":0,
    "gn:timezone":"Asia/Shanghai",
    "iso:country":"CN",
    "name:zho_x_preferred":[
        "\u5927\u6751\u6c9f"
    ],
    "wof:name":"Dacungou",
    "wof:placetype":"locality"
},
  "geometry": {"coordinates":[102.2042,28.27862],"type":"Point"}
}