{
  "type": "Feature",
  "properties": {
    "gn:admin1_code":"19.0",
    "gn:asciiname":"Tumen Lingqian",
    "gn:country_code":"CN",
    "gn:dem":232,
    "gn:feature_class":"P",
    "gn:feature_code":"PPL",
    "gn:name":"Tumen Lingqian",
    "gn:population":0,
    "gn:timezone":"Asia/Shanghai",
    "iso:country":"CN",
    "name:zho_x_preferred":[
        "\u571f\u95e8\u5cad\u524d"
    ],
    "wof:name":"Tumen Lingqian",
    "wof:placetype":"locality"
},
  "geometry": {"coordinates":[124.39641,40.56224],"type":"Point"}
}