{
  "type": "Feature",
  "properties": {
    "gn:admin1_code":"10",
    "gn:asciiname":"Wenjiaying",
    "gn:country_code":"CN",
    "gn:dem":1346,
    "gn:feature_class":"P",
    "gn:feature_code":"PPL",
    "gn:name":"Wenjiaying",
    "gn:population":0,
    "gn:timezone":"Asia/Shanghai",
    "iso:country":"CN",
    "name:zho_x_preferred":[
        "\u6e29\u5bb6\u8425"
    ],
    "wof:name":"Wenjiaying",
    "wof:placetype":"locality"
},
  "geometry": {"coordinates":[114.34435000000001,41.65868],"type":"Point"}
}