{
  "type": "Feature",
  "properties": {
    "gn:admin1_code":"10",
    "gn:asciiname":"Madiantou",
    "gn:cc2":"CN",
    "gn:country_code":"CN",
    "gn:dem":1085,
    "gn:feature_class":"P",
    "gn:feature_code":"PPL",
    "gn:name":"Madiantou",
    "gn:population":0,
    "gn:timezone":"Asia/Shanghai",
    "iso:country":"CN",
    "name:und_x_variant":[
        "Ma-tien-t\u2019ou",
        "Madiantou"
    ],
    "wof:name":"Madiantou",
    "wof:placetype":"locality"
},
  "geometry": {"coordinates":[113.91667,36.93333],"type":"Point"}
}