{
  "type": "Feature",
  "properties": {
    "gn:admin1_code":"26.0",
    "gn:asciiname":"Zhanghecun",
    "gn:country_code":"CN",
    "gn:dem":815,
    "gn:feature_class":"P",
    "gn:feature_code":"PPL",
    "gn:name":"Zhanghecun",
    "gn:population":0,
    "gn:timezone":"Asia/Shanghai",
    "iso:country":"CN",
    "name:zho_x_preferred":[
        "\u5f20\u6cb3\u6751"
    ],
    "wof:name":"Zhanghecun",
    "wof:placetype":"locality"
},
  "geometry": {"coordinates":[110.15322,33.85413],"type":"Point"}
}