{
  "type": "Feature",
  "properties": {
    "gn:admin1_code":"30",
    "gn:asciiname":"Jiukaitian",
    "gn:country_code":"CN",
    "gn:dem":557,
    "gn:feature_class":"P",
    "gn:feature_code":"PPL",
    "gn:name":"Jiukaitian",
    "gn:population":0,
    "gn:timezone":"Asia/Urumqi",
    "iso:country":"CN",
    "name:zho_x_preferred":[
        "\u65e7\u5f00\u7530"
    ],
    "wof:name":"Jiukaitian",
    "wof:placetype":"locality"
},
  "geometry": {"coordinates":[111.23488,22.20463],"type":"Point"}
}