{
  "type": "Feature",
  "properties": {
    "gn:admin1_code":"8.0",
    "gn:asciiname":"Changzhengcun",
    "gn:country_code":"CN",
    "gn:dem":246,
    "gn:feature_class":"P",
    "gn:feature_code":"PPL",
    "gn:name":"Changzhengcun",
    "gn:population":0,
    "gn:timezone":"Asia/Shanghai",
    "iso:country":"CN",
    "name:zho_x_preferred":[
        "\u957f\u5f81\u6751"
    ],
    "wof:name":"Changzhengcun",
    "wof:placetype":"locality"
},
  "geometry": {"coordinates":[125.78294,47.77829000000001],"type":"Point"}
}