{
  "type": "Feature",
  "properties": {
    "gn:admin1_code":"4.0",
    "gn:asciiname":"Zhuqiucun",
    "gn:country_code":"CN",
    "gn:dem":7,
    "gn:feature_class":"P",
    "gn:feature_code":"PPL",
    "gn:name":"Zhuqiucun",
    "gn:population":0,
    "gn:timezone":"Asia/Shanghai",
    "iso:country":"CN",
    "name:und_x_variant":[
        "Zhuqiu",
        "Zhuqiucun"
    ],
    "name:zho_x_preferred":[
        "\u9a7b\u4e18"
    ],
    "name:zho_x_variant":[
        "\u9a7b\u4e18\u6751"
    ],
    "wof:name":"Zhuqiucun",
    "wof:placetype":"locality"
},
  "geometry": {"coordinates":[118.74353000000001,34.23328],"type":"Point"}
}