{
  "type": "Feature",
  "properties": {
    "gn:admin1_code":"32.0",
    "gn:asciiname":"Shantoushan",
    "gn:country_code":"CN",
    "gn:dem":1778,
    "gn:feature_class":"P",
    "gn:feature_code":"PPL",
    "gn:name":"Shantoushan",
    "gn:population":0,
    "gn:timezone":"Asia/Shanghai",
    "iso:country":"CN",
    "name:zho_x_preferred":[
        "\u5c71\u5934\u5c71"
    ],
    "wof:name":"Shantoushan",
    "wof:placetype":"locality"
},
  "geometry": {"coordinates":[102.334,26.4356],"type":"Point"}
}