{
  "type": "Feature",
  "properties": {
    "gn:admin1_code":"30",
    "gn:asciiname":"Fengdong",
    "gn:country_code":"CN",
    "gn:dem":57,
    "gn:feature_class":"P",
    "gn:feature_code":"PPL",
    "gn:name":"Fengdong",
    "gn:population":0,
    "gn:timezone":"Asia/Urumqi",
    "iso:country":"CN",
    "name:zho_x_preferred":[
        "\u4e30\u578c"
    ],
    "wof:name":"Fengdong",
    "wof:placetype":"locality"
},
  "geometry": {"coordinates":[111.27495999999999,21.7637],"type":"Point"}
}