{
  "type": "Feature",
  "properties": {
    "gn:admin1_code":"14.0",
    "gn:asciiname":"Langda",
    "gn:country_code":"CN",
    "gn:dem":3170,
    "gn:feature_class":"P",
    "gn:feature_code":"PPL",
    "gn:name":"Langda",
    "gn:population":0,
    "gn:timezone":"Asia/Kolkata",
    "iso:country":"CN",
    "name:zho_x_preferred":[
        "\u6717\u6253"
    ],
    "wof:name":"Langda",
    "wof:placetype":"locality"
},
  "geometry": {"coordinates":[94.24199,29.01806],"type":"Point"}
}