{
  "type": "Feature",
  "properties": {
    "gn:admin1_code":"4.0",
    "gn:asciiname":"Xushe",
    "gn:country_code":"CN",
    "gn:dem":1,
    "gn:feature_class":"P",
    "gn:feature_code":"PPL",
    "gn:name":"Xushe",
    "gn:population":0,
    "gn:timezone":"Asia/Shanghai",
    "iso:country":"CN",
    "name:zho_x_preferred":[
        "Xushe"
    ],
    "name:zho_x_variant":[
        "\u5f90\u820d"
    ],
    "wof:name":"Xushe",
    "wof:placetype":"locality"
},
  "geometry": {"coordinates":[119.89229,33.40759],"type":"Point"}
}