{
  "type": "Feature",
  "properties": {
    "gn:admin1_code":"25.0",
    "gn:asciiname":"Shijiabucun",
    "gn:country_code":"CN",
    "gn:dem":61,
    "gn:feature_class":"P",
    "gn:feature_code":"PPL",
    "gn:name":"Shijiabucun",
    "gn:population":0,
    "gn:timezone":"Asia/Shanghai",
    "iso:country":"CN",
    "name:zho_x_preferred":[
        "\u77f3\u5bb6\u57e0\u6751"
    ],
    "wof:name":"Shijiabucun",
    "wof:placetype":"locality"
},
  "geometry": {"coordinates":[119.27837,36.239],"type":"Point"}
}