{
  "type": "Feature",
  "properties": {
    "gn:admin1_code":"02",
    "gn:asciiname":"Datianping",
    "gn:country_code":"CN",
    "gn:dem":353,
    "gn:feature_class":"P",
    "gn:feature_code":"PPL",
    "gn:name":"Datianping",
    "gn:population":0,
    "gn:timezone":"Asia/Shanghai",
    "iso:country":"CN",
    "name:zho_x_preferred":[
        "\u5927\u7530\u5e73"
    ],
    "wof:name":"Datianping",
    "wof:placetype":"locality"
},
  "geometry": {"coordinates":[120.40406000000002,27.82876],"type":"Point"}
}