{
  "type": "Feature",
  "properties": {
    "gn:admin1_code":"8.0",
    "gn:asciiname":"Nanda",
    "gn:country_code":"CN",
    "gn:dem":135,
    "gn:feature_class":"P",
    "gn:feature_code":"PPL",
    "gn:name":"Nanda",
    "gn:population":0,
    "gn:timezone":"Asia/Shanghai",
    "iso:country":"CN",
    "name:ceb_x_preferred":[
        "Nanda"
    ],
    "name:deu_x_preferred":[
        "Nanda"
    ],
    "name:por_x_preferred":[
        "Nanda"
    ],
    "name:rus_x_preferred":[
        "\u041d\u0430\u043d\u0434\u0430"
    ],
    "name:swe_x_preferred":[
        "Nanda"
    ],
    "name:zho_x_preferred":[
        "\u5357\u5927"
    ],
    "wof:name":"Nanda",
    "wof:placetype":"locality"
},
  "geometry": {"coordinates":[123.72381,46.42258],"type":"Point"}
}