{
  "type": "Feature",
  "properties": {
    "gn:admin1_code":"19.0",
    "gn:asciiname":"Xiaoyitun",
    "gn:country_code":"CN",
    "gn:dem":30,
    "gn:feature_class":"P",
    "gn:feature_code":"PPL",
    "gn:name":"Xiaoyitun",
    "gn:population":0,
    "gn:timezone":"Asia/Shanghai",
    "iso:country":"CN",
    "name:und_x_variant":[
        "\u5c0f\u8863\u5c6f"
    ],
    "name:zho_x_preferred":[
        "\u5c0f\u8863\u5c6f"
    ],
    "wof:name":"Xiaoyitun",
    "wof:placetype":"locality"
},
  "geometry": {"coordinates":[122.90486,39.73875],"type":"Point"}
}