{
  "type": "Feature",
  "properties": {
    "gn:admin1_code":"11.0",
    "gn:asciiname":"Changtanping",
    "gn:country_code":"CN",
    "gn:dem":176,
    "gn:feature_class":"P",
    "gn:feature_code":"PPL",
    "gn:name":"Changtanping",
    "gn:population":0,
    "gn:timezone":"Asia/Shanghai",
    "iso:country":"CN",
    "name:zho_x_preferred":[
        "\u957f\u6ee9\u576a"
    ],
    "name:zho_x_variant":[
        "\u957f\u6f6d\u576a\u4e61"
    ],
    "wof:name":"Changtanping",
    "wof:placetype":"locality"
},
  "geometry": {"coordinates":[110.60630999999999,28.74844],"type":"Point"}
}