{
  "type": "Feature",
  "properties": {
    "gn:admin1_code":"33.0",
    "gn:asciiname":"Shanlin",
    "gn:country_code":"CN",
    "gn:dem":806,
    "gn:feature_class":"P",
    "gn:feature_code":"PPL",
    "gn:name":"Shanlin",
    "gn:population":0,
    "gn:timezone":"Asia/Shanghai",
    "iso:country":"CN",
    "name:fra_x_preferred":[
        "Shanlin"
    ],
    "name:spa_x_preferred":[
        "Shanlin"
    ],
    "name:zho_x_preferred":[
        "\u5c71\u6797"
    ],
    "wof:name":"Shanlin",
    "wof:placetype":"locality"
},
  "geometry": {"coordinates":[106.88500000000001,29.1081],"type":"Point"}
}