{
  "type": "Feature",
  "properties": {
    "gn:admin1_code":"3.0",
    "gn:asciiname":"Luojiabian",
    "gn:country_code":"CN",
    "gn:dem":429,
    "gn:feature_class":"P",
    "gn:feature_code":"PPL",
    "gn:name":"Luojiabian",
    "gn:population":0,
    "gn:timezone":"Asia/Shanghai",
    "iso:country":"CN",
    "name:und_x_variant":[
        "\u7f57\u5bb6\u8fb9"
    ],
    "wof:name":"Luojiabian",
    "wof:placetype":"locality"
},
  "geometry": {"coordinates":[116.3391,27.57028],"type":"Point"}
}