{
  "type": "Feature",
  "properties": {
    "gn:admin1_code":"25",
    "gn:asciiname":"Houwangzhuang",
    "gn:country_code":"CN",
    "gn:dem":31,
    "gn:feature_class":"P",
    "gn:feature_code":"PPL",
    "gn:name":"Houwangzhuang",
    "gn:population":0,
    "gn:timezone":"Asia/Shanghai",
    "iso:country":"CN",
    "name:zho_x_preferred":[
        "\u4faf\u738b\u5e84"
    ],
    "wof:name":"Houwangzhuang",
    "wof:placetype":"locality"
},
  "geometry": {"coordinates":[116.142,37.1771],"type":"Point"}
}