{
  "type": "Feature",
  "properties": {
    "gn:admin1_code":"19.0",
    "gn:asciiname":"Heshang Gouli",
    "gn:country_code":"CN",
    "gn:dem":598,
    "gn:feature_class":"P",
    "gn:feature_code":"PPL",
    "gn:name":"Heshang Gouli",
    "gn:population":0,
    "gn:timezone":"Asia/Shanghai",
    "iso:country":"CN",
    "name:zho_x_preferred":[
        "\u548c\u5c1a\u6c9f\u91cc"
    ],
    "wof:name":"Heshang Gouli",
    "wof:placetype":"locality"
},
  "geometry": {"coordinates":[120.14394,41.24042],"type":"Point"}
}