{
  "type": "Feature",
  "properties": {
    "gn:admin1_code":"30.0",
    "gn:asciiname":"Liucuozhaicun",
    "gn:country_code":"CN",
    "gn:dem":30,
    "gn:feature_class":"P",
    "gn:feature_code":"PPL",
    "gn:name":"Liucuozhaicun",
    "gn:population":0,
    "gn:timezone":"Asia/Shanghai",
    "iso:country":"CN",
    "name:zho_x_preferred":[
        "\u5218\u539d\u5be8\u6751"
    ],
    "wof:name":"Liucuozhaicun",
    "wof:placetype":"locality"
},
  "geometry": {"coordinates":[116.36578,23.61455],"type":"Point"}
}