{
  "type": "Feature",
  "properties": {
    "gn:admin1_code":"3.0",
    "gn:asciiname":"Liyong",
    "gn:country_code":"CN",
    "gn:dem":86,
    "gn:feature_class":"P",
    "gn:feature_code":"PPL",
    "gn:name":"Liyong",
    "gn:population":0,
    "gn:timezone":"Asia/Shanghai",
    "iso:country":"CN",
    "name:und_x_variant":[
        "\u5229\u7528"
    ],
    "wof:name":"Liyong",
    "wof:placetype":"locality"
},
  "geometry": {"coordinates":[117.38970999999999,29.37803],"type":"Point"}
}