{
  "type": "Feature",
  "properties": {
    "gn:admin1_code":"15.0",
    "gn:asciiname":"Chengquan",
    "gn:country_code":"CN",
    "gn:dem":2742,
    "gn:feature_class":"P",
    "gn:feature_code":"PPL",
    "gn:name":"Chengquan",
    "gn:population":0,
    "gn:timezone":"Asia/Shanghai",
    "iso:country":"CN",
    "name:zho_x_preferred":[
        "\u57ce\u6cc9"
    ],
    "wof:name":"Chengquan",
    "wof:placetype":"locality"
},
  "geometry": {"coordinates":[102.84999999999999,37.2433],"type":"Point"}
}