{
  "type": "Feature",
  "properties": {
    "gn:admin1_code":"25",
    "gn:asciiname":"Pange",
    "gn:country_code":"CN",
    "gn:dem":40,
    "gn:feature_class":"P",
    "gn:feature_code":"PPL",
    "gn:name":"Pange",
    "gn:population":0,
    "gn:timezone":"Asia/Shanghai",
    "iso:country":"CN",
    "name:als_x_preferred":[
        "Pange"
    ],
    "name:cat_x_preferred":[
        "Pange"
    ],
    "name:ceb_x_preferred":[
        "Pange"
    ],
    "name:deu_x_preferred":[
        "Pange"
    ],
    "name:eus_x_preferred":[
        "Pange"
    ],
    "name:fra_x_preferred":[
        "Pange"
    ],
    "name:hun_x_preferred":[
        "Pange"
    ],
    "name:ita_x_preferred":[
        "Pange"
    ],
    "name:kaz_x_preferred":[
        "\u041f\u0430\u043d\u0436"
    ],
    "name:lat_x_preferred":[
        "Pange"
    ],
    "name:ltz_x_preferred":[
        "Pange"
    ],
    "name:msa_x_preferred":[
        "Pange"
    ],
    "name:nld_x_preferred":[
        "Pange"
    ],
    "name:oci_x_preferred":[
        "Pange"
    ],
    "name:pfl_x_preferred":[
        "Pange"
    ],
    "name:pol_x_preferred":[
        "Pange"
    ],
    "name:rus_x_preferred":[
        "\u041f\u0430\u043d\u0436"
    ],
    "name:slk_x_preferred":[
        "Pange"
    ],
    "name:spa_x_preferred":[
        "Pange"
    ],
    "name:swe_x_preferred":[
        "Pange"
    ],
    "name:ukr_x_preferred":[
        "\u041f\u0430\u043d\u0436"
    ],
    "name:uzb_x_preferred":[
        "Pange"
    ],
    "name:vie_x_preferred":[
        "Pange"
    ],
    "name:vol_x_preferred":[
        "Pange"
    ],
    "name:war_x_preferred":[
        "Pange"
    ],
    "name:zho_x_preferred":[
        "\u6f58\u9601"
    ],
    "name:zho_x_variant":[
        "\u5e9e\u65e5"
    ],
    "wof:name":"Pange",
    "wof:placetype":"locality"
},
  "geometry": {"coordinates":[116.26300000000001,34.973],"type":"Point"}
}