{
  "type": "Feature",
  "properties": {
    "gn:admin1_code":"14.0",
    "gn:asciiname":"Galangcun",
    "gn:country_code":"CN",
    "gn:dem":2714,
    "gn:feature_class":"P",
    "gn:feature_code":"PPL",
    "gn:name":"Galangcun",
    "gn:population":0,
    "gn:timezone":"Asia/Urumqi",
    "iso:country":"CN",
    "name:zho_x_preferred":[
        "\u560e\u6717\u6751"
    ],
    "wof:name":"Galangcun",
    "wof:placetype":"locality"
},
  "geometry": {"coordinates":[95.62384,29.92383],"type":"Point"}
}