{
  "type": "Feature",
  "properties": {
    "gn:admin1_code":"32.0",
    "gn:asciiname":"Liangbashan",
    "gn:country_code":"CN",
    "gn:dem":2785,
    "gn:feature_class":"P",
    "gn:feature_code":"PPL",
    "gn:name":"Liangbashan",
    "gn:population":0,
    "gn:timezone":"Asia/Shanghai",
    "iso:country":"CN",
    "name:zho_x_preferred":[
        "\u51c9\u5df4\u5c71"
    ],
    "wof:name":"Liangbashan",
    "wof:placetype":"locality"
},
  "geometry": {"coordinates":[102.06699999999999,27.4742],"type":"Point"}
}