{
  "type": "Feature",
  "properties": {
    "gn:admin1_code":"19.0",
    "gn:asciiname":"Huangzhangzicun",
    "gn:country_code":"CN",
    "gn:dem":249,
    "gn:feature_class":"P",
    "gn:feature_code":"PPL",
    "gn:name":"Huangzhangzicun",
    "gn:population":0,
    "gn:timezone":"Asia/Shanghai",
    "iso:country":"CN",
    "name:zho_x_preferred":[
        "\u9ec4\u6756\u5b50\u6751"
    ],
    "wof:name":"Huangzhangzicun",
    "wof:placetype":"locality"
},
  "geometry": {"coordinates":[120.605,41.6635],"type":"Point"}
}