{
  "type": "Feature",
  "properties": {
    "gn:admin1_code":"24",
    "gn:asciiname":"Sanjiao",
    "gn:cc2":"CN",
    "gn:country_code":"CN",
    "gn:dem":964,
    "gn:feature_class":"P",
    "gn:feature_code":"PPL",
    "gn:name":"Sanjiao",
    "gn:population":0,
    "gn:timezone":"Asia/Shanghai",
    "iso:country":"CN",
    "name:und_x_variant":[
        "San-chiao-chen",
        "San-chiao",
        "Sanjiao"
    ],
    "wof:name":"Sanjiao",
    "wof:placetype":"locality"
},
  "geometry": {"coordinates":[112.49194,38.37639],"type":"Point"}
}