{
  "type": "Feature",
  "properties": {
    "gn:admin1_code":"15.0",
    "gn:asciiname":"Caogouquan",
    "gn:country_code":"CN",
    "gn:dem":2950,
    "gn:feature_class":"P",
    "gn:feature_code":"PPL",
    "gn:name":"Caogouquan",
    "gn:population":0,
    "gn:timezone":"Asia/Shanghai",
    "iso:country":"CN",
    "name:zho_x_preferred":[
        "\u8349\u6c9f\u5708"
    ],
    "wof:name":"Caogouquan",
    "wof:placetype":"locality"
},
  "geometry": {"coordinates":[103.276,37.2143],"type":"Point"}
}