{
  "type": "Feature",
  "properties": {
    "gn:admin1_code":"6.0",
    "gn:asciiname":"Yeniugou",
    "gn:country_code":"CN",
    "gn:dem":3683,
    "gn:feature_class":"P",
    "gn:feature_code":"PPLA4",
    "gn:name":"Yeniugou",
    "gn:population":0,
    "gn:timezone":"Asia/Shanghai",
    "iso:country":"CN",
    "name:und_x_variant":[
        "Yeh-niu-Kou",
        "Yeniugou",
        "Yeniugou Xiang"
    ],
    "name:zho_x_preferred":[
        "\u91ce\u725b\u6c9f"
    ],
    "name:zho_x_variant":[
        "\u91ce\u725b\u6c9f\u4e61"
    ],
    "wof:name":"Yeniugou",
    "wof:placetype":"locality"
},
  "geometry": {"coordinates":[99.51866,38.42731],"type":"Point"}
}