{
  "type": "Feature",
  "properties": {
    "gn:admin1_code":"5.0",
    "gn:asciiname":"Wanpucun",
    "gn:country_code":"CN",
    "gn:dem":543,
    "gn:feature_class":"P",
    "gn:feature_code":"PPL",
    "gn:name":"Wanpucun",
    "gn:population":0,
    "gn:timezone":"Asia/Shanghai",
    "iso:country":"CN",
    "name:zho_x_preferred":[
        "\u7897\u94fa\u6751"
    ],
    "wof:name":"Wanpucun",
    "wof:placetype":"locality"
},
  "geometry": {"coordinates":[128.17636999999999,43.38154],"type":"Point"}
}