{
  "type": "Feature",
  "properties": {
    "gn:admin1_code":"5.0",
    "gn:asciiname":"Gongjuchang Jiashudian",
    "gn:country_code":"CN",
    "gn:dem":443,
    "gn:feature_class":"P",
    "gn:feature_code":"PPL",
    "gn:name":"Gongjuchang Jiashudian",
    "gn:population":0,
    "gn:timezone":"Asia/Shanghai",
    "iso:country":"CN",
    "name:zho_x_preferred":[
        "\u5de5\u5177\u5382\u5bb6\u5c5e\u70b9"
    ],
    "wof:name":"Gongjuchang Jiashudian",
    "wof:placetype":"locality"
},
  "geometry": {"coordinates":[127.50417,43.35345],"type":"Point"}
}