{
  "type": "Feature",
  "properties": {
    "gn:admin1_code":"8.0",
    "gn:asciiname":"Zhanxincun",
    "gn:country_code":"CN",
    "gn:dem":265,
    "gn:feature_class":"P",
    "gn:feature_code":"PPL",
    "gn:name":"Zhanxincun",
    "gn:population":0,
    "gn:timezone":"Asia/Shanghai",
    "iso:country":"CN",
    "name:zho_x_preferred":[
        "\u5c55\u65b0\u6751"
    ],
    "wof:name":"Zhanxincun",
    "wof:placetype":"locality"
},
  "geometry": {"coordinates":[125.20269,48.84819],"type":"Point"}
}