{
  "type": "Feature",
  "properties": {
    "gn:admin1_code":"30",
    "gn:asciiname":"Jianbei",
    "gn:country_code":"CN",
    "gn:dem":383,
    "gn:feature_class":"P",
    "gn:feature_code":"PPL",
    "gn:name":"Jianbei",
    "gn:population":0,
    "gn:timezone":"Asia/Shanghai",
    "iso:country":"CN",
    "name:zho_x_preferred":[
        "\u7b80\u80cc"
    ],
    "wof:name":"Jianbei",
    "wof:placetype":"locality"
},
  "geometry": {"coordinates":[115.44413,23.47631],"type":"Point"}
}