{
  "type": "Feature",
  "properties": {
    "gn:admin1_code":"7.0",
    "gn:asciiname":"Shenhui",
    "gn:country_code":"CN",
    "gn:dem":122,
    "gn:feature_class":"P",
    "gn:feature_code":"PPL",
    "gn:name":"Shenhui",
    "gn:population":0,
    "gn:timezone":"Asia/Shanghai",
    "iso:country":"CN",
    "name:fra_x_preferred":[
        "Shenhui"
    ],
    "name:jpn_x_preferred":[
        "\u8377\u6ca2\u795e\u4f1a"
    ],
    "name:pol_x_preferred":[
        "Heze Shenhui"
    ],
    "name:zho_x_preferred":[
        "\u6df1\u8f89"
    ],
    "name:zho_x_variant":[
        "\u83cf\u6cfd\u795e\u4f1a"
    ],
    "wof:name":"Shenhui",
    "wof:placetype":"locality"
},
  "geometry": {"coordinates":[118.28543999999999,25.13972],"type":"Point"}
}