{
  "type": "Feature",
  "properties": {
    "gn:admin1_code":"12.0",
    "gn:asciiname":"Guantangjiao",
    "gn:country_code":"CN",
    "gn:dem":89,
    "gn:feature_class":"P",
    "gn:feature_code":"PPL",
    "gn:name":"Guantangjiao",
    "gn:population":0,
    "gn:timezone":"Asia/Shanghai",
    "iso:country":"CN",
    "name:zho_x_preferred":[
        "\u5b98\u5858\u89d2"
    ],
    "wof:name":"Guantangjiao",
    "wof:placetype":"locality"
},
  "geometry": {"coordinates":[113.67646000000001,29.52779],"type":"Point"}
}