{
  "type": "Feature",
  "properties": {
    "gn:admin1_code":"29.0",
    "gn:asciiname":"Laolinzhai",
    "gn:country_code":"CN",
    "gn:dem":1201,
    "gn:feature_class":"P",
    "gn:feature_code":"PPL",
    "gn:name":"Laolinzhai",
    "gn:population":0,
    "gn:timezone":"Asia/Shanghai",
    "iso:country":"CN",
    "name:zho_x_preferred":[
        "\u8001\u6797\u5be8"
    ],
    "wof:name":"Laolinzhai",
    "wof:placetype":"locality"
},
  "geometry": {"coordinates":[102.361,22.6869],"type":"Point"}
}