{
  "type": "Feature",
  "properties": {
    "gn:admin1_code":"8.0",
    "gn:asciiname":"Guolaowugou",
    "gn:country_code":"CN",
    "gn:dem":446,
    "gn:feature_class":"P",
    "gn:feature_code":"PPL",
    "gn:name":"Guolaowugou",
    "gn:population":0,
    "gn:timezone":"Asia/Shanghai",
    "iso:country":"CN",
    "name:zho_x_preferred":[
        "\u90ed\u8001\u4e94\u6c9f"
    ],
    "wof:name":"Guolaowugou",
    "wof:placetype":"locality"
},
  "geometry": {"coordinates":[128.79053000000002,44.17953],"type":"Point"}
}