{
  "type": "Feature",
  "properties": {
    "gn:admin1_code":"31.0",
    "gn:asciiname":"Lipaitang",
    "gn:country_code":"CN",
    "gn:dem":9,
    "gn:feature_class":"P",
    "gn:feature_code":"PPL",
    "gn:name":"Lipaitang",
    "gn:population":0,
    "gn:timezone":"Asia/Shanghai",
    "iso:country":"CN",
    "name:zho_x_preferred":[
        "\u674e\u6392\u5858"
    ],
    "wof:name":"Lipaitang",
    "wof:placetype":"locality"
},
  "geometry": {"coordinates":[110.48347,19.05601],"type":"Point"}
}