{
  "type": "Feature",
  "properties": {
    "gn:admin1_code":"29.0",
    "gn:asciiname":"Luogewo",
    "gn:country_code":"CN",
    "gn:dem":2792,
    "gn:feature_class":"P",
    "gn:feature_code":"PPL",
    "gn:name":"Luogewo",
    "gn:population":0,
    "gn:timezone":"Asia/Shanghai",
    "iso:country":"CN",
    "name:und_x_variant":[
        "\u843d\u683c\u5367"
    ],
    "wof:name":"Luogewo",
    "wof:placetype":"locality"
},
  "geometry": {"coordinates":[102.57250999999999,26.10575],"type":"Point"}
}