{
  "type": "Feature",
  "properties": {
    "gn:admin1_code":"12.0",
    "gn:asciiname":"Nanling",
    "gn:country_code":"CN",
    "gn:dem":32,
    "gn:feature_class":"P",
    "gn:feature_code":"PPL",
    "gn:name":"Nanling",
    "gn:population":0,
    "gn:timezone":"Asia/Shanghai",
    "iso:country":"CN",
    "name:ceb_x_preferred":[
        "Nanling"
    ],
    "name:deu_x_preferred":[
        "Nanling"
    ],
    "name:nor_x_preferred":[
        "Nanling"
    ],
    "name:swe_x_preferred":[
        "Nanling"
    ],
    "name:zho_x_preferred":[
        "\u5357\u5cad"
    ],
    "wof:name":"Nanling",
    "wof:placetype":"locality"
},
  "geometry": {"coordinates":[112.96295000000001,29.74931],"type":"Point"}
}