{
  "type": "Feature",
  "properties": {
    "gn:admin1_code":"24.0",
    "gn:asciiname":"Anjialing",
    "gn:country_code":"CN",
    "gn:dem":1114,
    "gn:feature_class":"P",
    "gn:feature_code":"PPL",
    "gn:name":"Anjialing",
    "gn:population":0,
    "gn:timezone":"Asia/Shanghai",
    "iso:country":"CN",
    "name:zho_x_preferred":[
        "\u5b89\u5bb6\u5cad"
    ],
    "wof:name":"Anjialing",
    "wof:placetype":"locality"
},
  "geometry": {"coordinates":[111.01477,36.49857],"type":"Point"}
}