{
  "type": "Feature",
  "properties": {
    "gn:admin1_code":"7.0",
    "gn:asciiname":"Xiaguanliao",
    "gn:country_code":"CN",
    "gn:dem":414,
    "gn:feature_class":"P",
    "gn:feature_code":"PPL",
    "gn:name":"Xiaguanliao",
    "gn:population":0,
    "gn:timezone":"Asia/Shanghai",
    "iso:country":"CN",
    "name:zho_x_preferred":[
        "\u4e0b\u5b98\u5bee"
    ],
    "wof:name":"Xiaguanliao",
    "wof:placetype":"locality"
},
  "geometry": {"coordinates":[116.71655,26.39859],"type":"Point"}
}