{
  "type": "Feature",
  "properties": {
    "gn:admin1_code":"11.0",
    "gn:asciiname":"Laoyuanchong",
    "gn:country_code":"CN",
    "gn:dem":278,
    "gn:feature_class":"P",
    "gn:feature_code":"PPL",
    "gn:name":"Laoyuanchong",
    "gn:population":0,
    "gn:timezone":"Asia/Shanghai",
    "iso:country":"CN",
    "name:zho_x_preferred":[
        "\u8001\u8881\u51b2"
    ],
    "wof:name":"Laoyuanchong",
    "wof:placetype":"locality"
},
  "geometry": {"coordinates":[112.97418,25.84627],"type":"Point"}
}