{
  "type": "Feature",
  "properties": {
    "gn:admin1_code":"20",
    "gn:asciiname":"Ih Hairhan Sum",
    "gn:cc2":"CN",
    "gn:country_code":"CN",
    "gn:dem":1301,
    "gn:feature_class":"P",
    "gn:feature_code":"PPL",
    "gn:name":"Ih Hairhan Sum",
    "gn:population":0,
    "gn:timezone":"Asia/Shanghai",
    "iso:country":"CN",
    "name:und_x_variant":[
        "Ih Hairhan",
        "Ih Hairhan Sum"
    ],
    "wof:name":"Ih Hairhan Sum",
    "wof:placetype":"locality"
},
  "geometry": {"coordinates":[115.58917,42.755],"type":"Point"}
}