{
  "type": "Feature",
  "properties": {
    "gn:admin1_code":"4.0",
    "gn:asciiname":"Shang'anziqiao",
    "gn:country_code":"CN",
    "gn:dem":24,
    "gn:feature_class":"P",
    "gn:feature_code":"PPL",
    "gn:name":"Shang\u2019anziqiao",
    "gn:population":0,
    "gn:timezone":"Asia/Shanghai",
    "iso:country":"CN",
    "name:und_x_variant":[
        "Shang\u2019anziqiao"
    ],
    "name:zho_x_preferred":[
        "\u4e0a\u6848\u5b50\u6865"
    ],
    "wof:name":"Shang'anziqiao",
    "wof:placetype":"locality"
},
  "geometry": {"coordinates":[119.1028,31.48526],"type":"Point"}
}