{
  "type": "Feature",
  "properties": {
    "gn:admin1_code":"19.0",
    "gn:asciiname":"Yaozhan",
    "gn:country_code":"CN",
    "gn:dem":494,
    "gn:feature_class":"P",
    "gn:feature_code":"PPL",
    "gn:name":"Yaozhan",
    "gn:population":0,
    "gn:timezone":"Asia/Shanghai",
    "iso:country":"CN",
    "name:zho_x_preferred":[
        "\u8170\u7ad9"
    ],
    "wof:name":"Yaozhan",
    "wof:placetype":"locality"
},
  "geometry": {"coordinates":[124.914,42.0038],"type":"Point"}
}