{
  "type": "Feature",
  "properties": {
    "gn:admin1_code":"4.0",
    "gn:asciiname":"Baochengshan",
    "gn:country_code":"CN",
    "gn:dem":11,
    "gn:feature_class":"P",
    "gn:feature_code":"PPL",
    "gn:name":"Baochengshan",
    "gn:population":0,
    "gn:timezone":"Asia/Shanghai",
    "iso:country":"CN",
    "name:zho_x_preferred":[
        "\u5821\u57ce\u5c71"
    ],
    "wof:name":"Baochengshan",
    "wof:placetype":"locality"
},
  "geometry": {"coordinates":[119.71389000000001,32.10451],"type":"Point"}
}