{
  "type": "Feature",
  "properties": {
    "gn:admin1_code":"29",
    "gn:asciiname":"Lushige",
    "gn:country_code":"CN",
    "gn:dem":1839,
    "gn:feature_class":"P",
    "gn:feature_code":"PPL",
    "gn:name":"Lushige",
    "gn:population":0,
    "gn:timezone":"Asia/Shanghai",
    "iso:country":"CN",
    "name:zho_x_preferred":[
        "\u9c81\u58eb\u683c"
    ],
    "wof:name":"Lushige",
    "wof:placetype":"locality"
},
  "geometry": {"coordinates":[102.664,23.8055],"type":"Point"}
}