{
  "type": "Feature",
  "properties": {
    "gn:admin1_code":"1.0",
    "gn:asciiname":"Baimishan Nongchang Sanfenchangcun",
    "gn:country_code":"CN",
    "gn:dem":62,
    "gn:feature_class":"P",
    "gn:feature_code":"PPLF",
    "gn:name":"Baimishan Nongchang Sanfenchangcun",
    "gn:population":0,
    "gn:timezone":"Asia/Shanghai",
    "iso:country":"CN",
    "name:zho_x_preferred":[
        "\u767d\u7c73\u5c71\u519c\u573a\u4e09\u5206\u573a\u6751"
    ],
    "wof:name":"Baimishan Nongchang Sanfenchangcun",
    "wof:placetype":"locality"
},
  "geometry": {"coordinates":[118.24890000000001,32.56049],"type":"Point"}
}