{
  "type": "Feature",
  "properties": {
    "gn:admin1_code":"1.0",
    "gn:asciiname":"Huangcuncun",
    "gn:country_code":"CN",
    "gn:dem":274,
    "gn:feature_class":"P",
    "gn:feature_code":"PPL",
    "gn:name":"Huangcuncun",
    "gn:population":0,
    "gn:timezone":"Asia/Shanghai",
    "iso:country":"CN",
    "name:und_x_variant":[
        "Huangcun"
    ],
    "name:zho_x_preferred":[
        "\u7bc1\u6751\u6751"
    ],
    "wof:name":"Huangcuncun",
    "wof:placetype":"locality"
},
  "geometry": {"coordinates":[118.15448000000001,29.9585],"type":"Point"}
}