{
  "type": "Feature",
  "properties": {
    "gn:admin1_code":"10.0",
    "gn:asciiname":"Dongmiwu",
    "gn:country_code":"CN",
    "gn:dem":110,
    "gn:feature_class":"P",
    "gn:feature_code":"PPL",
    "gn:name":"Dongmiwu",
    "gn:population":0,
    "gn:timezone":"Asia/Shanghai",
    "iso:country":"CN",
    "name:zho_x_preferred":[
        "\u4e1c\u5bc6\u575e"
    ],
    "wof:name":"Dongmiwu",
    "wof:placetype":"locality"
},
  "geometry": {"coordinates":[118.74487999999999,40.15327],"type":"Point"}
}