{
  "type": "Feature",
  "properties": {
    "gn:admin1_code":"26.0",
    "gn:asciiname":"Jiajiagou",
    "gn:country_code":"CN",
    "gn:dem":818,
    "gn:feature_class":"P",
    "gn:feature_code":"PPL",
    "gn:name":"Jiajiagou",
    "gn:population":0,
    "gn:timezone":"Asia/Shanghai",
    "iso:country":"CN",
    "name:zho_x_preferred":[
        "\u8d3e\u5bb6\u6c9f"
    ],
    "wof:name":"Jiajiagou",
    "wof:placetype":"locality"
},
  "geometry": {"coordinates":[108.39328,33.1332],"type":"Point"}
}