{
  "type": "Feature",
  "properties": {
    "gn:admin1_code":"32.0",
    "gn:asciiname":"Lamashan",
    "gn:country_code":"CN",
    "gn:dem":3168,
    "gn:feature_class":"P",
    "gn:feature_code":"PPL",
    "gn:name":"Lamashan",
    "gn:population":0,
    "gn:timezone":"Asia/Shanghai",
    "iso:country":"CN",
    "name:ceb_x_preferred":[
        "Lamash\u0101n"
    ],
    "name:fas_x_preferred":[
        "\u0644\u0627\u0645\u0634\u0627\u0646"
    ],
    "name:msa_x_preferred":[
        "Lamashan"
    ],
    "name:swe_x_preferred":[
        "Lamash\u0101n"
    ],
    "name:urd_x_preferred":[
        "\u0644\u0627\u0645\u0627\u0634\u0627\u0646"
    ],
    "name:zho_x_preferred":[
        "\u5587\u561b\u5c71"
    ],
    "wof:name":"Lamashan",
    "wof:placetype":"locality"
},
  "geometry": {"coordinates":[101.43205,27.76662],"type":"Point"}
}