{
  "type": "Feature",
  "properties": {
    "gn:admin1_code":"32.0",
    "gn:asciiname":"Yuhuangmiao",
    "gn:country_code":"CN",
    "gn:dem":326,
    "gn:feature_class":"P",
    "gn:feature_code":"PPL",
    "gn:name":"Yuhuangmiao",
    "gn:population":0,
    "gn:timezone":"Asia/Shanghai",
    "iso:country":"CN",
    "name:zho_x_preferred":[
        "\u7389\u7687\u5e99"
    ],
    "wof:name":"Yuhuangmiao",
    "wof:placetype":"locality"
},
  "geometry": {"coordinates":[106.238,31.1978],"type":"Point"}
}