{
  "type": "Feature",
  "properties": {
    "gn:admin1_code":"3.0",
    "gn:asciiname":"Jiaohuxi",
    "gn:country_code":"CN",
    "gn:dem":30,
    "gn:feature_class":"P",
    "gn:feature_code":"PPL",
    "gn:name":"Jiaohuxi",
    "gn:population":0,
    "gn:timezone":"Asia/Shanghai",
    "iso:country":"CN",
    "name:und_x_variant":[
        "\u86df\u6e56\u6eaa"
    ],
    "wof:name":"Jiaohuxi",
    "wof:placetype":"locality"
},
  "geometry": {"coordinates":[115.48838000000001,28.00457],"type":"Point"}
}