{
  "type": "Feature",
  "properties": {
    "gn:admin1_code":"24.0",
    "gn:asciiname":"Huangjita",
    "gn:country_code":"CN",
    "gn:dem":1796,
    "gn:feature_class":"P",
    "gn:feature_code":"PPL",
    "gn:name":"Huangjita",
    "gn:population":0,
    "gn:timezone":"Asia/Shanghai",
    "iso:country":"CN",
    "name:zho_x_preferred":[
        "\u9ec4\u9e21\u5854"
    ],
    "wof:name":"Huangjita",
    "wof:placetype":"locality"
},
  "geometry": {"coordinates":[111.47359,37.84084],"type":"Point"}
}