{
  "type": "Feature",
  "properties": {
    "gn:admin1_code":"8.0",
    "gn:asciiname":"Hongshengcun",
    "gn:country_code":"CN",
    "gn:dem":207,
    "gn:feature_class":"P",
    "gn:feature_code":"PPL",
    "gn:name":"Hongshengcun",
    "gn:population":0,
    "gn:timezone":"Asia/Shanghai",
    "iso:country":"CN",
    "name:zho_x_preferred":[
        "\u7ea2\u80dc\u6751"
    ],
    "wof:name":"Hongshengcun",
    "wof:placetype":"locality"
},
  "geometry": {"coordinates":[122.97342,47.30274],"type":"Point"}
}