{
  "type": "Feature",
  "properties": {
    "gn:admin1_code":"02",
    "gn:asciiname":"Chaodongwu",
    "gn:country_code":"CN",
    "gn:dem":3,
    "gn:feature_class":"P",
    "gn:feature_code":"PPL",
    "gn:name":"Chaodongwu",
    "gn:population":0,
    "gn:timezone":"Asia/Shanghai",
    "iso:country":"CN",
    "name:zho_x_preferred":[
        "\u671d\u4e1c\u5c4b"
    ],
    "wof:name":"Chaodongwu",
    "wof:placetype":"locality"
},
  "geometry": {"coordinates":[121.56057,28.33959],"type":"Point"}
}