{
  "type": "Feature",
  "properties": {
    "gn:admin1_code":"15.0",
    "gn:asciiname":"Luping",
    "gn:country_code":"CN",
    "gn:dem":2194,
    "gn:feature_class":"P",
    "gn:feature_code":"PPL",
    "gn:name":"Luping",
    "gn:population":0,
    "gn:timezone":"Asia/Shanghai",
    "iso:country":"CN",
    "name:zho_x_preferred":[
        "\u9e7f\u576a"
    ],
    "wof:name":"Luping",
    "wof:placetype":"locality"
},
  "geometry": {"coordinates":[104.708,35.7577],"type":"Point"}
}