{
  "type": "Feature",
  "properties": {
    "gn:admin1_code":"11",
    "gn:asciiname":"Dazhongtang",
    "gn:country_code":"CN",
    "gn:dem":922,
    "gn:feature_class":"P",
    "gn:feature_code":"PPL",
    "gn:name":"Dazhongtang",
    "gn:population":0,
    "gn:timezone":"Asia/Shanghai",
    "iso:country":"CN",
    "name:und_x_variant":[
        "\u5927\u4e2d\u5802",
        "Dazhongtang"
    ],
    "wof:name":"Dazhongtang",
    "wof:placetype":"locality"
},
  "geometry": {"coordinates":[112.00722,25.98833],"type":"Point"}
}