{
  "type": "Feature",
  "properties": {
    "gn:admin1_code":"14.0",
    "gn:asciiname":"Baili",
    "gn:country_code":"CN",
    "gn:dem":3846,
    "gn:feature_class":"P",
    "gn:feature_code":"PPL",
    "gn:name":"Baili",
    "gn:population":0,
    "gn:timezone":"Asia/Urumqi",
    "iso:country":"CN",
    "name:zho_x_preferred":[
        "\u767d\u91cc"
    ],
    "wof:name":"Baili",
    "wof:placetype":"locality"
},
  "geometry": {"coordinates":[96.32283,30.90451],"type":"Point"}
}