{
  "type": "Feature",
  "properties": {
    "gn:admin1_code":"31.0",
    "gn:asciiname":"Qiyi Dui",
    "gn:country_code":"CN",
    "gn:dem":47,
    "gn:feature_class":"P",
    "gn:feature_code":"PPLF",
    "gn:name":"Qiyi Dui",
    "gn:population":0,
    "gn:timezone":"Asia/Shanghai",
    "iso:country":"CN",
    "name:und_x_variant":[
        "\u4e03\u4e00\u961f"
    ],
    "wof:name":"Qiyi Dui",
    "wof:placetype":"locality"
},
  "geometry": {"coordinates":[110.20207000000001,18.70847],"type":"Point"}
}