{
  "type": "Feature",
  "properties": {
    "gn:admin1_code":"16.0",
    "gn:asciiname":"Nalu",
    "gn:country_code":"CN",
    "gn:dem":795,
    "gn:feature_class":"P",
    "gn:feature_code":"PPL",
    "gn:name":"Nalu",
    "gn:population":0,
    "gn:timezone":"Asia/Shanghai",
    "iso:country":"CN",
    "name:zho_x_preferred":[
        "\u90a3\u9e7f"
    ],
    "wof:name":"Nalu",
    "wof:placetype":"locality"
},
  "geometry": {"coordinates":[105.875,24.193],"type":"Point"}
}