{
  "type": "Feature",
  "properties": {
    "gn:admin1_code":"16.0",
    "gn:asciiname":"Daliang",
    "gn:country_code":"CN",
    "gn:dem":312,
    "gn:feature_class":"P",
    "gn:feature_code":"PPL",
    "gn:name":"Daliang",
    "gn:population":0,
    "gn:timezone":"Asia/Shanghai",
    "iso:country":"CN",
    "name:ceb_x_preferred":[
        "Daliang"
    ],
    "name:swe_x_preferred":[
        "Daliang"
    ],
    "name:zho_x_preferred":[
        "\u8fbe\u826f"
    ],
    "wof:name":"Daliang",
    "wof:placetype":"locality"
},
  "geometry": {"coordinates":[106.996,25.1351],"type":"Point"}
}