{
  "type": "Feature",
  "properties": {
    "gn:admin1_code":"29.0",
    "gn:asciiname":"Lengzhuping",
    "gn:country_code":"CN",
    "gn:dem":1338,
    "gn:feature_class":"P",
    "gn:feature_code":"PPL",
    "gn:name":"Lengzhuping",
    "gn:population":0,
    "gn:timezone":"Asia/Shanghai",
    "iso:country":"CN",
    "name:zho_x_preferred":[
        "\u51b7\u7af9\u576a"
    ],
    "wof:name":"Lengzhuping",
    "wof:placetype":"locality"
},
  "geometry": {"coordinates":[104.303,27.8968],"type":"Point"}
}