{
  "type": "Feature",
  "properties": {
    "gn:admin1_code":"29.0",
    "gn:asciiname":"Jinchanghe",
    "gn:country_code":"CN",
    "gn:dem":2046,
    "gn:feature_class":"P",
    "gn:feature_code":"PPL",
    "gn:name":"Jinchanghe",
    "gn:population":0,
    "gn:timezone":"Asia/Shanghai",
    "iso:country":"CN",
    "name:zho_x_preferred":[
        "\u91d1\u573a\u6cb3"
    ],
    "wof:name":"Jinchanghe",
    "wof:placetype":"locality"
},
  "geometry": {"coordinates":[97.7818,24.7331],"type":"Point"}
}