{
  "type": "Feature",
  "properties": {
    "gn:admin1_code":"19.0",
    "gn:asciiname":"Caochuankou",
    "gn:country_code":"CN",
    "gn:dem":103,
    "gn:feature_class":"P",
    "gn:feature_code":"PPL",
    "gn:name":"Caochuankou",
    "gn:population":0,
    "gn:timezone":"Asia/Shanghai",
    "iso:country":"CN",
    "name:zho_x_preferred":[
        "\u66f9\u8239\u53e3"
    ],
    "wof:name":"Caochuankou",
    "wof:placetype":"locality"
},
  "geometry": {"coordinates":[123.66800000000001,43.2189],"type":"Point"}
}