{
  "type": "Feature",
  "properties": {
    "gn:admin1_code":"3.0",
    "gn:asciiname":"Jinjia",
    "gn:country_code":"CN",
    "gn:dem":15,
    "gn:feature_class":"P",
    "gn:feature_code":"PPL",
    "gn:name":"Jinjia",
    "gn:population":0,
    "gn:timezone":"Asia/Shanghai",
    "iso:country":"CN",
    "name:und_x_variant":[
        "\u91d1\u5bb6"
    ],
    "wof:name":"Jinjia",
    "wof:placetype":"locality"
},
  "geometry": {"coordinates":[116.55786999999999,29.41243],"type":"Point"}
}