{
  "type": "Feature",
  "properties": {
    "gn:admin1_code":"05",
    "gn:asciiname":"Weihulingcun",
    "gn:country_code":"CN",
    "gn:dem":523,
    "gn:feature_class":"P",
    "gn:feature_code":"PPL",
    "gn:name":"Weihulingcun",
    "gn:population":0,
    "gn:timezone":"Asia/Shanghai",
    "iso:country":"CN",
    "name:und_x_variant":[
        "Weihuling",
        "Weihulingcun"
    ],
    "name:zho_x_preferred":[
        "\u5a01\u864e\u5cad"
    ],
    "name:zho_x_variant":[
        "\u5a01\u864e\u5cad\u6751"
    ],
    "wof:name":"Weihulingcun",
    "wof:placetype":"locality"
},
  "geometry": {"coordinates":[127.81775,43.55291],"type":"Point"}
}