{
  "type": "Feature",
  "properties": {
    "gn:admin1_code":"32.0",
    "gn:asciiname":"Puguangsi",
    "gn:country_code":"CN",
    "gn:dem":384,
    "gn:feature_class":"P",
    "gn:feature_code":"PPL",
    "gn:name":"Puguangsi",
    "gn:population":0,
    "gn:timezone":"Asia/Shanghai",
    "iso:country":"CN",
    "name:zho_x_preferred":[
        "\u666e\u5149\u5bfa"
    ],
    "wof:name":"Puguangsi",
    "wof:placetype":"locality"
},
  "geometry": {"coordinates":[105.70128,30.85301],"type":"Point"}
}