{
  "type": "Feature",
  "properties": {
    "gn:admin1_code":"8.0",
    "gn:asciiname":"Laozuojiatun",
    "gn:country_code":"CN",
    "gn:dem":322,
    "gn:feature_class":"P",
    "gn:feature_code":"PPL",
    "gn:name":"Laozuojiatun",
    "gn:population":0,
    "gn:timezone":"Asia/Shanghai",
    "iso:country":"CN",
    "name:zho_x_preferred":[
        "\u8001\u5de6\u5bb6\u5c6f"
    ],
    "wof:name":"Laozuojiatun",
    "wof:placetype":"locality"
},
  "geometry": {"coordinates":[125.10308000000001,48.86975],"type":"Point"}
}