{
  "type": "Feature",
  "properties": {
    "gn:admin1_code":"18",
    "gn:asciiname":"Neimaobu",
    "gn:country_code":"CN",
    "gn:dem":1439,
    "gn:feature_class":"P",
    "gn:feature_code":"PPL",
    "gn:name":"Neimaobu",
    "gn:population":0,
    "gn:timezone":"Asia/Shanghai",
    "iso:country":"CN",
    "name:zho_x_preferred":[
        "\u5185\u6bdb\u5821"
    ],
    "wof:name":"Neimaobu",
    "wof:placetype":"locality"
},
  "geometry": {"coordinates":[106.989,26.5337],"type":"Point"}
}