{
  "type": "Feature",
  "properties": {
    "gn:admin1_code":"5.0",
    "gn:asciiname":"Longyan Xiacun",
    "gn:country_code":"CN",
    "gn:dem":526,
    "gn:feature_class":"P",
    "gn:feature_code":"PPL",
    "gn:name":"Longyan Xiacun",
    "gn:population":0,
    "gn:timezone":"Asia/Shanghai",
    "iso:country":"CN",
    "name:zho_x_preferred":[
        "\u9f99\u5ca9\u4e0b\u6751"
    ],
    "wof:name":"Longyan Xiacun",
    "wof:placetype":"locality"
},
  "geometry": {"coordinates":[129.20400000000001,42.44931],"type":"Point"}
}