{
  "type": "Feature",
  "properties": {
    "gn:admin1_code":"2.0",
    "gn:asciiname":"Ruoxi",
    "gn:country_code":"CN",
    "gn:dem":502,
    "gn:feature_class":"P",
    "gn:feature_code":"PPL",
    "gn:name":"Ruoxi",
    "gn:population":0,
    "gn:timezone":"Asia/Shanghai",
    "iso:country":"CN",
    "name:zho_x_preferred":[
        "\u7bac\u6eaa"
    ],
    "wof:name":"Ruoxi",
    "wof:placetype":"locality"
},
  "geometry": {"coordinates":[121.09872,29.63449],"type":"Point"}
}