{
  "type": "Feature",
  "properties": {
    "gn:admin1_code":"8.0",
    "gn:asciiname":"Qingsongcun",
    "gn:country_code":"CN",
    "gn:dem":122,
    "gn:feature_class":"P",
    "gn:feature_code":"PPL",
    "gn:name":"Qingsongcun",
    "gn:population":0,
    "gn:timezone":"Asia/Shanghai",
    "iso:country":"CN",
    "name:zho_x_preferred":[
        "\u9752\u677e\u6751"
    ],
    "wof:name":"Qingsongcun",
    "wof:placetype":"locality"
},
  "geometry": {"coordinates":[126.32738000000001,45.77773],"type":"Point"}
}