{
  "type": "Feature",
  "properties": {
    "gn:admin1_code":"26.0",
    "gn:asciiname":"Sanzhangping",
    "gn:country_code":"CN",
    "gn:dem":1146,
    "gn:feature_class":"P",
    "gn:feature_code":"PPL",
    "gn:name":"Sanzhangping",
    "gn:population":0,
    "gn:timezone":"Asia/Shanghai",
    "iso:country":"CN",
    "name:zho_x_preferred":[
        "\u6563\u638c\u576a"
    ],
    "wof:name":"Sanzhangping",
    "wof:placetype":"locality"
},
  "geometry": {"coordinates":[107.75637,32.89575],"type":"Point"}
}