{
  "type": "Feature",
  "properties": {
    "gn:admin1_code":"32.0",
    "gn:asciiname":"Laoha",
    "gn:country_code":"CN",
    "gn:dem":2637,
    "gn:feature_class":"P",
    "gn:feature_code":"PPL",
    "gn:name":"Laoha",
    "gn:population":0,
    "gn:timezone":"Asia/Shanghai",
    "iso:country":"CN",
    "name:zho_x_preferred":[
        "\u8001\u54c8"
    ],
    "wof:name":"Laoha",
    "wof:placetype":"locality"
},
  "geometry": {"coordinates":[102.629,27.3978],"type":"Point"}
}