{
  "type": "Feature",
  "properties": {
    "gn:admin1_code":"16",
    "gn:asciiname":"Zhoujiabu",
    "gn:country_code":"CN",
    "gn:dem":608,
    "gn:feature_class":"P",
    "gn:feature_code":"PPL",
    "gn:name":"Zhoujiabu",
    "gn:population":0,
    "gn:timezone":"Asia/Shanghai",
    "iso:country":"CN",
    "name:zho_x_preferred":[
        "\u5468\u5bb6\u5821"
    ],
    "wof:name":"Zhoujiabu",
    "wof:placetype":"locality"
},
  "geometry": {"coordinates":[109.98699999999999,25.5286],"type":"Point"}
}