{
  "type": "Feature",
  "properties": {
    "gn:admin1_code":"25",
    "gn:asciiname":"Dasunzhuang",
    "gn:country_code":"CN",
    "gn:dem":28,
    "gn:feature_class":"P",
    "gn:feature_code":"PPL",
    "gn:name":"Dasunzhuang",
    "gn:population":0,
    "gn:timezone":"Asia/Shanghai",
    "iso:country":"CN",
    "name:zho_x_preferred":[
        "\u5927\u5b59\u5e84"
    ],
    "wof:name":"Dasunzhuang",
    "wof:placetype":"locality"
},
  "geometry": {"coordinates":[116.236,37.2928],"type":"Point"}
}