{
  "type": "Feature",
  "properties": {
    "gn:admin1_code":"30",
    "gn:asciiname":"Tangkou",
    "gn:country_code":"CN",
    "gn:dem":3,
    "gn:feature_class":"P",
    "gn:feature_code":"PPLA4",
    "gn:name":"Tangkou",
    "gn:population":0,
    "gn:timezone":"Asia/Shanghai",
    "iso:country":"CN",
    "name:und_x_variant":[
        "Tangkou Zhen",
        "\u5858\u53e3\u9547"
    ],
    "name:zho_x_preferred":[
        "\u5858\u53e3"
    ],
    "wof:name":"Tangkou",
    "wof:placetype":"locality"
},
  "geometry": {"coordinates":[112.61725,22.36777],"type":"Point"}
}