{
  "type": "Feature",
  "properties": {
    "gn:admin1_code":"6.0",
    "gn:asciiname":"Kangmusi",
    "gn:country_code":"CN",
    "gn:dem":2688,
    "gn:feature_class":"P",
    "gn:feature_code":"PPL",
    "gn:name":"Kangmusi",
    "gn:population":0,
    "gn:timezone":"Asia/Shanghai",
    "iso:country":"CN",
    "name:und_x_variant":[
        "\u5eb7\u6728\u5bfa"
    ],
    "wof:name":"Kangmusi",
    "wof:placetype":"locality"
},
  "geometry": {"coordinates":[102.42428,35.7004],"type":"Point"}
}