{
  "type": "Feature",
  "properties": {
    "gn:admin1_code":"8.0",
    "gn:asciiname":"Xinghua",
    "gn:country_code":"CN",
    "gn:dem":107,
    "gn:feature_class":"P",
    "gn:feature_code":"PPL",
    "gn:name":"Xinghua",
    "gn:population":0,
    "gn:timezone":"Asia/Shanghai",
    "iso:country":"CN",
    "name:zho_x_preferred":[
        "\u5174\u534e"
    ],
    "wof:name":"Xinghua",
    "wof:placetype":"locality"
},
  "geometry": {"coordinates":[130.27106000000001,47.09117],"type":"Point"}
}