{
  "type": "Feature",
  "properties": {
    "gn:admin1_code":"14.0",
    "gn:asciiname":"Dangzaka",
    "gn:country_code":"CN",
    "gn:dem":3988,
    "gn:feature_class":"P",
    "gn:feature_code":"PPL",
    "gn:name":"Dangzaka",
    "gn:population":0,
    "gn:timezone":"Asia/Urumqi",
    "iso:country":"CN",
    "name:zho_x_preferred":[
        "\u5f53\u6742\u5361"
    ],
    "wof:name":"Dangzaka",
    "wof:placetype":"locality"
},
  "geometry": {"coordinates":[96.45072,31.40951],"type":"Point"}
}