{
  "type": "Feature",
  "properties": {
    "gn:admin1_code":"3.0",
    "gn:asciiname":"Sishi'an",
    "gn:country_code":"CN",
    "gn:dem":353,
    "gn:feature_class":"P",
    "gn:feature_code":"PPL",
    "gn:name":"Sishi\u2019an",
    "gn:population":0,
    "gn:timezone":"Asia/Shanghai",
    "iso:country":"CN",
    "name:und_x_variant":[
        "Sishi\u2019an",
        "\u5bfa\u77f3\u5eb5"
    ],
    "wof:name":"Sishi'an",
    "wof:placetype":"locality"
},
  "geometry": {"coordinates":[115.60679,24.85496],"type":"Point"}
}