{
  "type": "Feature",
  "properties": {
    "gn:admin1_code":"14.0",
    "gn:asciiname":"Zhadaida",
    "gn:country_code":"CN",
    "gn:dem":4826,
    "gn:feature_class":"P",
    "gn:feature_code":"PPL",
    "gn:name":"Zhadaida",
    "gn:population":0,
    "gn:timezone":"Asia/Urumqi",
    "iso:country":"CN",
    "name:bod_x_preferred":[
        "Zhagd\u00eada"
    ],
    "name:zho_x_preferred":[
        "Zhadaida"
    ],
    "name:zho_x_variant":[
        "\u624e\u5446\u8fbe"
    ],
    "wof:name":"Zhadaida",
    "wof:placetype":"locality"
},
  "geometry": {"coordinates":[93.306,32.306],"type":"Point"}
}