{
  "type": "Feature",
  "properties": {
    "gn:admin1_code":"1.0",
    "gn:asciiname":"Houfanjiachong",
    "gn:country_code":"CN",
    "gn:dem":37,
    "gn:feature_class":"P",
    "gn:feature_code":"PPL",
    "gn:name":"Houfanjiachong",
    "gn:population":0,
    "gn:timezone":"Asia/Shanghai",
    "iso:country":"CN",
    "name:zho_x_preferred":[
        "\u540e\u8303\u5bb6\u51b2"
    ],
    "wof:name":"Houfanjiachong",
    "wof:placetype":"locality"
},
  "geometry": {"coordinates":[119.16943999999999,31.06096],"type":"Point"}
}