{
  "type": "Feature",
  "properties": {
    "gn:admin1_code":"8.0",
    "gn:asciiname":"Zhangyunqing",
    "gn:country_code":"CN",
    "gn:dem":155,
    "gn:feature_class":"P",
    "gn:feature_code":"PPL",
    "gn:name":"Zhangyunqing",
    "gn:population":0,
    "gn:timezone":"Asia/Shanghai",
    "iso:country":"CN",
    "name:zho_x_preferred":[
        "\u5f20\u4e91\u5e86"
    ],
    "wof:name":"Zhangyunqing",
    "wof:placetype":"locality"
},
  "geometry": {"coordinates":[125.16746999999999,47.06567],"type":"Point"}
}