{
  "type": "Feature",
  "properties": {
    "gn:admin1_code":"24.0",
    "gn:asciiname":"Nanchang",
    "gn:country_code":"CN",
    "gn:dem":637,
    "gn:feature_class":"P",
    "gn:feature_code":"PPL",
    "gn:name":"Nanchang",
    "gn:population":0,
    "gn:timezone":"Asia/Shanghai",
    "iso:country":"CN",
    "name:zho_x_preferred":[
        "\u5357\u5e38"
    ],
    "wof:name":"Nanchang",
    "wof:placetype":"locality"
},
  "geometry": {"coordinates":[111.74257,35.64728],"type":"Point"}
}