{
  "type": "Feature",
  "properties": {
    "gn:admin1_code":"12.0",
    "gn:asciiname":"Beitingzi",
    "gn:country_code":"CN",
    "gn:dem":93,
    "gn:feature_class":"P",
    "gn:feature_code":"PPL",
    "gn:name":"Beitingzi",
    "gn:population":0,
    "gn:timezone":"Asia/Shanghai",
    "iso:country":"CN",
    "name:zho_x_preferred":[
        "Beitingzi"
    ],
    "name:zho_x_variant":[
        "\u7891\u4ead\u5b50"
    ],
    "wof:name":"Beitingzi",
    "wof:placetype":"locality"
},
  "geometry": {"coordinates":[111.64821000000001,30.199],"type":"Point"}
}