{
  "type": "Feature",
  "properties": {
    "gn:admin1_code":"16",
    "gn:asciiname":"Pingshajiang",
    "gn:country_code":"CN",
    "gn:dem":844,
    "gn:feature_class":"P",
    "gn:feature_code":"PPL",
    "gn:name":"Pingshajiang",
    "gn:population":0,
    "gn:timezone":"Asia/Shanghai",
    "iso:country":"CN",
    "name:zho_x_preferred":[
        "\u5e73\u6c99\u6c5f"
    ],
    "wof:name":"Pingshajiang",
    "wof:placetype":"locality"
},
  "geometry": {"coordinates":[110.723,25.2468],"type":"Point"}
}