{
  "type": "Feature",
  "properties": {
    "gn:admin1_code":"1.0",
    "gn:asciiname":"Tonghua",
    "gn:country_code":"CN",
    "gn:dem":81,
    "gn:feature_class":"P",
    "gn:feature_code":"PPL",
    "gn:name":"Tonghua",
    "gn:population":0,
    "gn:timezone":"Asia/Shanghai",
    "iso:country":"CN",
    "name:ara_x_preferred":[
        "\u062a\u0648\u0646\u063a\u0647\u0648\u0627"
    ],
    "name:ast_x_preferred":[
        "Tonghua"
    ],
    "name:cdo_x_preferred":[
        "T\u016dng-hu\u00e1"
    ],
    "name:ces_x_preferred":[
        "Tchung-chua"
    ],
    "name:dan_x_preferred":[
        "Tonghua"
    ],
    "name:deu_x_preferred":[
        "Tonghua"
    ],
    "name:epo_x_preferred":[
        "Tonghua"
    ],
    "name:eus_x_preferred":[
        "Tonghua"
    ],
    "name:fas_x_preferred":[
        "\u062a\u0627\u0646\u06af\u0647\u0648\u0627"
    ],
    "name:fin_x_preferred":[
        "Tonghua"
    ],
    "name:fra_x_preferred":[
        "Tonghua"
    ],
    "name:ita_x_preferred":[
        "Tonghua"
    ],
    "name:jpn_x_preferred":[
        "\u901a\u5316\u5e02"
    ],
    "name:kik_x_preferred":[
        "Tonghua"
    ],
    "name:kor_x_preferred":[
        "\ud241\ud654\uc2dc"
    ],
    "name:mlg_x_preferred":[
        "Tonghua"
    ],
    "name:nld_x_preferred":[
        "Tonghua"
    ],
    "name:nno_x_preferred":[
        "Tonghua"
    ],
    "name:nor_x_preferred":[
        "Tonghua"
    ],
    "name:pol_x_preferred":[
        "Tonghua"
    ],
    "name:por_x_preferred":[
        "Tonghua"
    ],
    "name:rus_x_preferred":[
        "\u0422\u0443\u043d\u0445\u0443\u0430"
    ],
    "name:spa_x_preferred":[
        "Tonghua"
    ],
    "name:swe_x_preferred":[
        "Tonghua"
    ],
    "name:tur_x_preferred":[
        "Tonghua"
    ],
    "name:urd_x_preferred":[
        "\u062a\u0648\u0646\u06af\u06c1\u0648\u0627"
    ],
    "name:vie_x_preferred":[
        "Th\u00f4ng H\u00f3a"
    ],
    "name:war_x_preferred":[
        "Tonghua"
    ],
    "name:wuu_x_preferred":[
        "\u901a\u5316\u5e02"
    ],
    "name:zho_x_preferred":[
        "\u6850\u82b1"
    ],
    "name:zho_x_variant":[
        "\u901a\u5316\u5e02"
    ],
    "wof:name":"Tonghua",
    "wof:placetype":"locality"
},
  "geometry": {"coordinates":[119.17046999999999,30.70868],"type":"Point"}
}