{
  "type": "Feature",
  "properties": {
    "gn:admin1_code":"15.0",
    "gn:asciiname":"Renjiagou",
    "gn:country_code":"CN",
    "gn:dem":1924,
    "gn:feature_class":"P",
    "gn:feature_code":"PPL",
    "gn:name":"Renjiagou",
    "gn:population":0,
    "gn:timezone":"Asia/Shanghai",
    "iso:country":"CN",
    "name:und_x_variant":[
        "\u4efb\u5bb6\u6c9f"
    ],
    "wof:name":"Renjiagou",
    "wof:placetype":"locality"
},
  "geometry": {"coordinates":[105.41267000000001,35.38811],"type":"Point"}
}