{
  "type": "Feature",
  "properties": {
    "gn:admin1_code":"11.0",
    "gn:asciiname":"Jiuyangping",
    "gn:country_code":"CN",
    "gn:dem":1377,
    "gn:feature_class":"P",
    "gn:feature_code":"PPL",
    "gn:name":"Jiuyangping",
    "gn:population":0,
    "gn:timezone":"Asia/Shanghai",
    "iso:country":"CN",
    "name:zho_x_preferred":[
        "\u4e5d\u7f8a\u576a"
    ],
    "wof:name":"Jiuyangping",
    "wof:placetype":"locality"
},
  "geometry": {"coordinates":[109.67982000000001,29.60014],"type":"Point"}
}