{
  "type": "Feature",
  "properties": {
    "gn:admin1_code":"8.0",
    "gn:asciiname":"Wanjiacun",
    "gn:country_code":"CN",
    "gn:dem":276,
    "gn:feature_class":"P",
    "gn:feature_code":"PPL",
    "gn:name":"Wanjiacun",
    "gn:population":0,
    "gn:timezone":"Asia/Shanghai",
    "iso:country":"CN",
    "name:zho_x_preferred":[
        "\u4e07\u5bb6\u6751"
    ],
    "wof:name":"Wanjiacun",
    "wof:placetype":"locality"
},
  "geometry": {"coordinates":[129.83172999999999,44.90751],"type":"Point"}
}