{
  "type": "Feature",
  "properties": {
    "gn:admin1_code":"3.0",
    "gn:asciiname":"Chejia",
    "gn:country_code":"CN",
    "gn:dem":28,
    "gn:feature_class":"P",
    "gn:feature_code":"PPL",
    "gn:name":"Chejia",
    "gn:population":0,
    "gn:timezone":"Asia/Shanghai",
    "iso:country":"CN",
    "name:und_x_variant":[
        "\u8f66\u5bb6"
    ],
    "wof:name":"Chejia",
    "wof:placetype":"locality"
},
  "geometry": {"coordinates":[116.22588,28.44435],"type":"Point"}
}