{
  "type": "Feature",
  "properties": {
    "gn:admin1_code":"31.0",
    "gn:asciiname":"Bujiatou",
    "gn:country_code":"CN",
    "gn:dem":49,
    "gn:feature_class":"P",
    "gn:feature_code":"PPL",
    "gn:name":"Bujiatou",
    "gn:population":0,
    "gn:timezone":"Asia/Shanghai",
    "iso:country":"CN",
    "name:zho_x_preferred":[
        "\u5e03\u52a0\u5934"
    ],
    "wof:name":"Bujiatou",
    "wof:placetype":"locality"
},
  "geometry": {"coordinates":[109.36286,18.35896],"type":"Point"}
}