{
  "type": "Feature",
  "properties": {
    "gn:admin1_code":"32.0",
    "gn:asciiname":"Chongling",
    "gn:country_code":"CN",
    "gn:dem":591,
    "gn:feature_class":"P",
    "gn:feature_code":"PPL",
    "gn:name":"Chongling",
    "gn:population":0,
    "gn:timezone":"Asia/Shanghai",
    "iso:country":"CN",
    "name:zho_x_preferred":[
        "\u5d07\u5cad"
    ],
    "wof:name":"Chongling",
    "wof:placetype":"locality"
},
  "geometry": {"coordinates":[105.34399999999999,31.8535],"type":"Point"}
}