{
  "type": "Feature",
  "properties": {
    "gn:admin1_code":"31.0",
    "gn:asciiname":"Shangwei",
    "gn:country_code":"CN",
    "gn:dem":76,
    "gn:feature_class":"P",
    "gn:feature_code":"PPL",
    "gn:name":"Shangwei",
    "gn:population":0,
    "gn:timezone":"Asia/Shanghai",
    "iso:country":"CN",
    "name:zho_x_preferred":[
        "\u4e0a\u4f4d"
    ],
    "wof:name":"Shangwei",
    "wof:placetype":"locality"
},
  "geometry": {"coordinates":[109.98820000000001,19.5528],"type":"Point"}
}