{
  "type": "Feature",
  "properties": {
    "gn:admin1_code":"8.0",
    "gn:asciiname":"Xilinhe",
    "gn:country_code":"CN",
    "gn:dem":177,
    "gn:feature_class":"P",
    "gn:feature_code":"PPL",
    "gn:name":"Xilinhe",
    "gn:population":0,
    "gn:timezone":"Asia/Shanghai",
    "iso:country":"CN",
    "name:zho_x_preferred":[
        "\u7ec6\u6797\u6cb3"
    ],
    "wof:name":"Xilinhe",
    "wof:placetype":"locality"
},
  "geometry": {"coordinates":[128.75878,45.32231],"type":"Point"}
}