{
  "type": "Feature",
  "properties": {
    "gn:admin1_code":"10",
    "gn:asciiname":"Xiaoyizhuang",
    "gn:country_code":"CN",
    "gn:dem":47,
    "gn:feature_class":"P",
    "gn:feature_code":"PPL",
    "gn:name":"Xiaoyizhuang",
    "gn:population":0,
    "gn:timezone":"Asia/Shanghai",
    "iso:country":"CN",
    "name:zho_x_preferred":[
        "\u5c0f\u79fb\u5e84"
    ],
    "wof:name":"Xiaoyizhuang",
    "wof:placetype":"locality"
},
  "geometry": {"coordinates":[114.985,36.6207],"type":"Point"}
}