{
  "type": "Feature",
  "properties": {
    "gn:admin1_code":"13.0",
    "gn:asciiname":"Sagankuduk",
    "gn:cc2":"CN",
    "gn:country_code":"CN",
    "gn:dem":1377,
    "gn:feature_class":"P",
    "gn:feature_code":"PPL",
    "gn:name":"Sagankuduk",
    "gn:population":0,
    "gn:timezone":"Asia/Shanghai",
    "iso:country":"CN",
    "name:uig_x_preferred":[
        "Sa\u01a3ank\u0329uduk\u0329"
    ],
    "name:uig_x_variant":[
        "Saghanquduq",
        "\u0633\u0627\u063a\u0627\u0646\u0642\u06c7\u062f\u06c7\u0642",
        "\u0421\u0430\u0493\u0430\u043d\u049b\u0443\u0434\u0443\u049b"
    ],
    "name:und_x_variant":[
        "Sa-kan-k\u2019u-tu-k\u2019o",
        "Sagankuduk"
    ],
    "wof:name":"Sagankuduk",
    "wof:placetype":"locality"
},
  "geometry": {"coordinates":[78.16667,40.16667],"type":"Point"}
}