{
  "type": "Feature",
  "properties": {
    "gn:admin1_code":"29.0",
    "gn:asciiname":"Anailong",
    "gn:country_code":"CN",
    "gn:dem":1627,
    "gn:feature_class":"P",
    "gn:feature_code":"PPL",
    "gn:name":"Anailong",
    "gn:population":0,
    "gn:timezone":"Asia/Shanghai",
    "iso:country":"CN",
    "name:zho_x_preferred":[
        "\u554a\u5948\u9f99"
    ],
    "wof:name":"Anailong",
    "wof:placetype":"locality"
},
  "geometry": {"coordinates":[104.023,23.8087],"type":"Point"}
}