{
  "type": "Feature",
  "properties": {
    "gn:admin1_code":"8.0",
    "gn:asciiname":"Fudeshan",
    "gn:country_code":"CN",
    "gn:dem":262,
    "gn:feature_class":"P",
    "gn:feature_code":"PPL",
    "gn:name":"Fudeshan",
    "gn:population":0,
    "gn:timezone":"Asia/Shanghai",
    "iso:country":"CN",
    "name:zho_x_preferred":[
        "\u4ed8\u5fb7\u5c71"
    ],
    "wof:name":"Fudeshan",
    "wof:placetype":"locality"
},
  "geometry": {"coordinates":[126.03959999999999,47.2651],"type":"Point"}
}