{
  "type": "Feature",
  "properties": {
    "gn:admin1_code":"6.0",
    "gn:asciiname":"Baimasi",
    "gn:country_code":"CN",
    "gn:dem":2818,
    "gn:feature_class":"P",
    "gn:feature_code":"PPL",
    "gn:name":"Baimasi",
    "gn:population":0,
    "gn:timezone":"Asia/Shanghai",
    "iso:country":"CN",
    "name:zho_x_preferred":[
        "\u767d\u9a6c\u5bfa"
    ],
    "wof:name":"Baimasi",
    "wof:placetype":"locality"
},
  "geometry": {"coordinates":[101.54721000000001,36.24509000000001],"type":"Point"}
}