{
  "type": "Feature",
  "properties": {
    "gn:admin1_code":"31",
    "gn:asciiname":"Licai Nongchang",
    "gn:country_code":"CN",
    "gn:dem":177,
    "gn:feature_class":"P",
    "gn:feature_code":"PPLF",
    "gn:name":"Licai Nongchang",
    "gn:population":0,
    "gn:timezone":"Asia/Shanghai",
    "iso:country":"CN",
    "name:und_x_variant":[
        "\u7acb\u624d\u519c\u573a"
    ],
    "wof:name":"Licai Nongchang",
    "wof:placetype":"locality"
},
  "geometry": {"coordinates":[109.30356999999999,18.40999],"type":"Point"}
}