{
  "type": "Feature",
  "properties": {
    "gn:admin1_code":"4.0",
    "gn:asciiname":"Fufeng",
    "gn:country_code":"CN",
    "gn:dem":3,
    "gn:feature_class":"P",
    "gn:feature_code":"PPL",
    "gn:name":"Fufeng",
    "gn:population":0,
    "gn:timezone":"Asia/Shanghai",
    "iso:country":"CN",
    "name:und_x_variant":[
        "\u961c\u4e30"
    ],
    "wof:name":"Fufeng",
    "wof:placetype":"locality"
},
  "geometry": {"coordinates":[120.48038,33.21977],"type":"Point"}
}