{
  "type": "Feature",
  "properties": {
    "gn:admin1_code":"26.0",
    "gn:asciiname":"Zhujiaya",
    "gn:country_code":"CN",
    "gn:dem":819,
    "gn:feature_class":"P",
    "gn:feature_code":"PPL",
    "gn:name":"Zhujiaya",
    "gn:population":0,
    "gn:timezone":"Asia/Shanghai",
    "iso:country":"CN",
    "name:und_x_variant":[
        "\u6731\u5bb6\u57ad"
    ],
    "wof:name":"Zhujiaya",
    "wof:placetype":"locality"
},
  "geometry": {"coordinates":[106.11557000000001,32.99669],"type":"Point"}
}