{
  "type": "Feature",
  "properties": {
    "gn:admin1_code":"30.0",
    "gn:asciiname":"Aowei",
    "gn:country_code":"CN",
    "gn:dem":-3,
    "gn:feature_class":"P",
    "gn:feature_code":"PPL",
    "gn:name":"Aowei",
    "gn:population":0,
    "gn:timezone":"Asia/Shanghai",
    "iso:country":"CN",
    "name:zho_x_preferred":[
        "\u6fb3\u5c3e"
    ],
    "wof:name":"Aowei",
    "wof:placetype":"locality"
},
  "geometry": {"coordinates":[113.3385,22.6836],"type":"Point"}
}