{
  "type": "Feature",
  "properties": {
    "gn:admin1_code":"2.0",
    "gn:asciiname":"Ertangmiao",
    "gn:country_code":"CN",
    "gn:dem":4,
    "gn:feature_class":"P",
    "gn:feature_code":"PPL",
    "gn:name":"Ertangmiao",
    "gn:population":0,
    "gn:timezone":"Asia/Shanghai",
    "iso:country":"CN",
    "name:zho_x_preferred":[
        "\u4e8c\u5858\u5e99"
    ],
    "wof:name":"Ertangmiao",
    "wof:placetype":"locality"
},
  "geometry": {"coordinates":[121.51712000000001,28.4773],"type":"Point"}
}