{
  "type": "Feature",
  "properties": {
    "gn:admin1_code":"9.0",
    "gn:asciiname":"Houzhanglou",
    "gn:country_code":"CN",
    "gn:dem":55,
    "gn:feature_class":"P",
    "gn:feature_code":"PPL",
    "gn:name":"Houzhanglou",
    "gn:population":0,
    "gn:timezone":"Asia/Shanghai",
    "iso:country":"CN",
    "name:zho_x_preferred":[
        "\u540e\u5f20\u697c"
    ],
    "wof:name":"Houzhanglou",
    "wof:placetype":"locality"
},
  "geometry": {"coordinates":[114.6328,33.84370999999999],"type":"Point"}
}