{
  "type": "Feature",
  "properties": {
    "gn:admin1_code":"20.0",
    "gn:asciiname":"Sanbachaxi",
    "gn:country_code":"CN",
    "gn:dem":1412,
    "gn:feature_class":"P",
    "gn:feature_code":"PPL",
    "gn:name":"Sanbachaxi",
    "gn:population":0,
    "gn:timezone":"Asia/Shanghai",
    "iso:country":"CN",
    "name:und_x_variant":[
        "\u4e09\u5df4\u5c94\u897f"
    ],
    "wof:name":"Sanbachaxi",
    "wof:placetype":"locality"
},
  "geometry": {"coordinates":[113.22806,41.59123],"type":"Point"}
}