{
  "type": "Feature",
  "properties": {
    "gn:admin1_code":"33.0",
    "gn:asciiname":"Yanjiachong",
    "gn:country_code":"CN",
    "gn:dem":437,
    "gn:feature_class":"P",
    "gn:feature_code":"PPL",
    "gn:name":"Yanjiachong",
    "gn:population":0,
    "gn:timezone":"Asia/Shanghai",
    "iso:country":"CN",
    "name:zho_x_preferred":[
        "\u664f\u5bb6\u51b2"
    ],
    "wof:name":"Yanjiachong",
    "wof:placetype":"locality"
},
  "geometry": {"coordinates":[107.35867,30.25775],"type":"Point"}
}