{
  "type": "Feature",
  "properties": {
    "gn:admin1_code":"30",
    "gn:asciiname":"Taohe",
    "gn:country_code":"CN",
    "gn:dem":25,
    "gn:feature_class":"P",
    "gn:feature_code":"PPLA4",
    "gn:name":"Taohe",
    "gn:population":0,
    "gn:timezone":"Asia/Shanghai",
    "iso:country":"CN",
    "name:und_x_variant":[
        "Taohe Zhen",
        "\u9676\u6cb3\u9547"
    ],
    "name:zho_x_preferred":[
        "\u9676\u6cb3"
    ],
    "wof:name":"Taohe",
    "wof:placetype":"locality"
},
  "geometry": {"coordinates":[115.41058999999998,22.8954],"type":"Point"}
}