{
  "type": "Feature",
  "properties": {
    "gn:admin1_code":"11.0",
    "gn:asciiname":"Xianiujiang",
    "gn:country_code":"CN",
    "gn:dem":1019,
    "gn:feature_class":"P",
    "gn:feature_code":"PPL",
    "gn:name":"Xianiujiang",
    "gn:population":0,
    "gn:timezone":"Asia/Shanghai",
    "iso:country":"CN",
    "name:zho_x_preferred":[
        "\u4e0b\u725b\u6c5f"
    ],
    "wof:name":"Xianiujiang",
    "wof:placetype":"locality"
},
  "geometry": {"coordinates":[113.83087999999999,25.94126],"type":"Point"}
}