{
  "type": "Feature",
  "properties": {
    "gn:admin1_code":"19.0",
    "gn:asciiname":"Xingxingshi",
    "gn:country_code":"CN",
    "gn:dem":45,
    "gn:feature_class":"P",
    "gn:feature_code":"PPL",
    "gn:name":"Xingxingshi",
    "gn:population":0,
    "gn:timezone":"Asia/Shanghai",
    "iso:country":"CN",
    "name:und_x_variant":[
        "\u661f\u661f\u77f3"
    ],
    "wof:name":"Xingxingshi",
    "wof:placetype":"locality"
},
  "geometry": {"coordinates":[123.55165,40.26093],"type":"Point"}
}