{
  "type": "Feature",
  "properties": {
    "gn:admin1_code":"24.0",
    "gn:asciiname":"Hounangoucun",
    "gn:country_code":"CN",
    "gn:dem":1034,
    "gn:feature_class":"P",
    "gn:feature_code":"PPL",
    "gn:name":"Hounangoucun",
    "gn:population":0,
    "gn:timezone":"Asia/Shanghai",
    "iso:country":"CN",
    "name:zho_x_preferred":[
        "\u540e\u5357\u6c9f\u6751"
    ],
    "wof:name":"Hounangoucun",
    "wof:placetype":"locality"
},
  "geometry": {"coordinates":[110.91143999999998,37.89912],"type":"Point"}
}