{
  "type": "Feature",
  "properties": {
    "gn:admin1_code":"32.0",
    "gn:asciiname":"Dayangtian",
    "gn:country_code":"CN",
    "gn:dem":439,
    "gn:feature_class":"P",
    "gn:feature_code":"PPL",
    "gn:name":"Dayangtian",
    "gn:population":0,
    "gn:timezone":"Asia/Shanghai",
    "iso:country":"CN",
    "name:zho_x_preferred":[
        "\u5927\u79e7\u7530"
    ],
    "wof:name":"Dayangtian",
    "wof:placetype":"locality"
},
  "geometry": {"coordinates":[104.87398,28.08503],"type":"Point"}
}