{
  "type": "Feature",
  "properties": {
    "gn:admin1_code":"3.0",
    "gn:asciiname":"Hantiantou",
    "gn:country_code":"CN",
    "gn:dem":158,
    "gn:feature_class":"P",
    "gn:feature_code":"PPL",
    "gn:name":"Hantiantou",
    "gn:population":0,
    "gn:timezone":"Asia/Shanghai",
    "iso:country":"CN",
    "name:und_x_variant":[
        "\u6c49\u7530\u5934"
    ],
    "wof:name":"Hantiantou",
    "wof:placetype":"locality"
},
  "geometry": {"coordinates":[115.69023,26.11697],"type":"Point"}
}