{
  "type": "Feature",
  "properties": {
    "gn:admin1_code":"10.0",
    "gn:asciiname":"Weiganzhuang",
    "gn:country_code":"CN",
    "gn:dem":16,
    "gn:feature_class":"P",
    "gn:feature_code":"PPL",
    "gn:name":"Weiganzhuang",
    "gn:population":0,
    "gn:timezone":"Asia/Shanghai",
    "iso:country":"CN",
    "name:zho_x_preferred":[
        "\u56f4\u6746\u5e84"
    ],
    "wof:name":"Weiganzhuang",
    "wof:placetype":"locality"
},
  "geometry": {"coordinates":[119.03403,39.59015],"type":"Point"}
}