{
  "type": "Feature",
  "properties": {
    "gn:admin1_code":"29.0",
    "gn:asciiname":"Miduo",
    "gn:country_code":"CN",
    "gn:dem":1704,
    "gn:feature_class":"P",
    "gn:feature_code":"PPL",
    "gn:name":"Miduo",
    "gn:population":0,
    "gn:timezone":"Asia/Shanghai",
    "iso:country":"CN",
    "name:zho_x_preferred":[
        "\u7c73\u6735"
    ],
    "wof:name":"Miduo",
    "wof:placetype":"locality"
},
  "geometry": {"coordinates":[103.545,23.7425],"type":"Point"}
}