{
  "type": "Feature",
  "properties": {
    "gn:admin1_code":"18.0",
    "gn:asciiname":"Zhujiaxi",
    "gn:country_code":"CN",
    "gn:dem":593,
    "gn:feature_class":"P",
    "gn:feature_code":"PPL",
    "gn:name":"Zhujiaxi",
    "gn:population":0,
    "gn:timezone":"Asia/Shanghai",
    "iso:country":"CN",
    "name:zho_x_preferred":[
        "\u795d\u5bb6\u6eaa"
    ],
    "wof:name":"Zhujiaxi",
    "wof:placetype":"locality"
},
  "geometry": {"coordinates":[109.001,27.9579],"type":"Point"}
}