{
  "type": "Feature",
  "properties": {
    "gn:admin1_code":"2.0",
    "gn:asciiname":"Duchuan",
    "gn:country_code":"CN",
    "gn:dem":45,
    "gn:feature_class":"P",
    "gn:feature_code":"PPL",
    "gn:name":"Duchuan",
    "gn:population":0,
    "gn:timezone":"Asia/Shanghai",
    "iso:country":"CN",
    "name:und_x_variant":[
        "\u6e0e\u5ddd"
    ],
    "wof:name":"Duchuan",
    "wof:placetype":"locality"
},
  "geometry": {"coordinates":[121.25842,30.06826],"type":"Point"}
}