{
  "type": "Feature",
  "properties": {
    "gn:admin1_code":"29",
    "gn:asciiname":"Dahuashan",
    "gn:country_code":"CN",
    "gn:dem":870,
    "gn:feature_class":"P",
    "gn:feature_code":"PPL",
    "gn:name":"Dahuashan",
    "gn:population":0,
    "gn:timezone":"Asia/Shanghai",
    "iso:country":"CN",
    "name:zho_x_preferred":[
        "\u5927\u82b1\u5c71"
    ],
    "wof:name":"Dahuashan",
    "wof:placetype":"locality"
},
  "geometry": {"coordinates":[104.607,22.8444],"type":"Point"}
}