{
  "type": "Feature",
  "properties": {
    "gn:admin1_code":"12.0",
    "gn:asciiname":"Xucaopo",
    "gn:country_code":"CN",
    "gn:dem":110,
    "gn:feature_class":"P",
    "gn:feature_code":"PPL",
    "gn:name":"Xucaopo",
    "gn:population":0,
    "gn:timezone":"Asia/Shanghai",
    "iso:country":"CN",
    "name:zho_x_preferred":[
        "\u84c4\u8349\u5761"
    ],
    "wof:name":"Xucaopo",
    "wof:placetype":"locality"
},
  "geometry": {"coordinates":[113.29443999999999,31.80558],"type":"Point"}
}