{
  "type": "Feature",
  "properties": {
    "gn:admin1_code":"4.0",
    "gn:asciiname":"Lingyuancun",
    "gn:country_code":"CN",
    "gn:dem":23,
    "gn:feature_class":"P",
    "gn:feature_code":"PPL",
    "gn:name":"Lingyuancun",
    "gn:population":0,
    "gn:timezone":"Asia/Shanghai",
    "iso:country":"CN",
    "name:zho_x_preferred":[
        "\u9675\u56ed\u6751"
    ],
    "wof:name":"Lingyuancun",
    "wof:placetype":"locality"
},
  "geometry": {"coordinates":[118.43188000000001,34.03113],"type":"Point"}
}