{
  "type": "Feature",
  "properties": {
    "gn:admin1_code":"22",
    "gn:asciiname":"Tailing",
    "gn:country_code":"CN",
    "gn:dem":162,
    "gn:feature_class":"P",
    "gn:feature_code":"PPL",
    "gn:name":"Tailing",
    "gn:population":0,
    "gn:timezone":"Asia/Shanghai",
    "iso:country":"CN",
    "name:deu_x_preferred":[
        "Tailing"
    ],
    "name:zho_x_preferred":[
        "\u6cf0\u9675"
    ],
    "wof:name":"Tailing",
    "wof:placetype":"locality"
},
  "geometry": {"coordinates":[116.21669,40.31966],"type":"Point"}
}