{
  "type": "Feature",
  "properties": {
    "gn:admin1_code":"9",
    "gn:asciiname":"Modaling",
    "gn:country_code":"CN",
    "gn:dem":918,
    "gn:feature_class":"P",
    "gn:feature_code":"PPL",
    "gn:name":"Modaling",
    "gn:population":0,
    "gn:timezone":"Asia/Shanghai",
    "iso:country":"CN",
    "name:und_x_variant":[
        "\u6ca1\u5927\u5cad",
        "Modaling"
    ],
    "wof:name":"Modaling",
    "wof:placetype":"locality"
},
  "geometry": {"coordinates":[112.24906,33.78001],"type":"Point"}
}