{
  "type": "Feature",
  "properties": {
    "gn:admin1_code":"29.0",
    "gn:asciiname":"Kayaobo",
    "gn:country_code":"CN",
    "gn:dem":2247,
    "gn:feature_class":"P",
    "gn:feature_code":"PPL",
    "gn:name":"Kayaobo",
    "gn:population":0,
    "gn:timezone":"Asia/Shanghai",
    "iso:country":"CN",
    "name:und_x_variant":[
        "Kamebo"
    ],
    "name:zho_x_preferred":[
        "\u5361\u4e48\u7c38"
    ],
    "wof:name":"Kayaobo",
    "wof:placetype":"locality"
},
  "geometry": {"coordinates":[101.375,25.4145],"type":"Point"}
}