{
  "type": "Feature",
  "properties": {
    "gn:admin1_code":"5.0",
    "gn:asciiname":"Erlijiecun",
    "gn:country_code":"CN",
    "gn:dem":160,
    "gn:feature_class":"P",
    "gn:feature_code":"PPL",
    "gn:name":"Erlijiecun",
    "gn:population":0,
    "gn:timezone":"Asia/Shanghai",
    "iso:country":"CN",
    "name:zho_x_preferred":[
        "\u4e8c\u91cc\u754c\u6751"
    ],
    "wof:name":"Erlijiecun",
    "wof:placetype":"locality"
},
  "geometry": {"coordinates":[124.55098999999998,43.68504],"type":"Point"}
}