{
  "type": "Feature",
  "properties": {
    "gn:admin1_code":"26.0",
    "gn:asciiname":"Shiqizhai",
    "gn:country_code":"CN",
    "gn:dem":497,
    "gn:feature_class":"P",
    "gn:feature_code":"PPL",
    "gn:name":"Shiqizhai",
    "gn:population":0,
    "gn:timezone":"Asia/Shanghai",
    "iso:country":"CN",
    "name:zho_x_preferred":[
        "\u62fe\u65d7\u5be8"
    ],
    "wof:name":"Shiqizhai",
    "wof:placetype":"locality"
},
  "geometry": {"coordinates":[109.22139,34.22239],"type":"Point"}
}