{
  "type": "Feature",
  "properties": {
    "gn:admin1_code":"25",
    "gn:asciiname":"Changgangji",
    "gn:country_code":"CN",
    "gn:dem":53,
    "gn:feature_class":"P",
    "gn:feature_code":"PPL",
    "gn:name":"Changgangji",
    "gn:population":0,
    "gn:timezone":"Asia/Shanghai",
    "iso:country":"CN",
    "name:zho_x_preferred":[
        "\u957f\u5c97\u96c6"
    ],
    "wof:name":"Changgangji",
    "wof:placetype":"locality"
},
  "geometry": {"coordinates":[115.467,35.1283],"type":"Point"}
}