{
  "type": "Feature",
  "properties": {
    "gn:admin1_code":"19.0",
    "gn:asciiname":"Hanjia Wobu",
    "gn:country_code":"CN",
    "gn:dem":93,
    "gn:feature_class":"P",
    "gn:feature_code":"PPL",
    "gn:name":"Hanjia Wobu",
    "gn:population":0,
    "gn:timezone":"Asia/Shanghai",
    "iso:country":"CN",
    "name:und_x_variant":[
        "Hanjiawobao",
        "Hanjia Wobu"
    ],
    "name:zho_x_preferred":[
        "\u97e9\u5bb6\u7a9d\u5821"
    ],
    "wof:name":"Hanjia Wobu",
    "wof:placetype":"locality"
},
  "geometry": {"coordinates":[123.36,42.5652],"type":"Point"}
}