{
  "type": "Feature",
  "properties": {
    "gn:admin1_code":"15.0",
    "gn:asciiname":"Wayao Muchang",
    "gn:country_code":"CN",
    "gn:dem":2720,
    "gn:feature_class":"P",
    "gn:feature_code":"PPLF",
    "gn:name":"Wayao Muchang",
    "gn:population":0,
    "gn:timezone":"Asia/Shanghai",
    "iso:country":"CN",
    "name:und_x_variant":[
        "\u74e6\u7a91\u7267\u573a"
    ],
    "wof:name":"Wayao Muchang",
    "wof:placetype":"locality"
},
  "geometry": {"coordinates":[104.61223,34.29233],"type":"Point"}
}