{
  "type": "Feature",
  "properties": {
    "gn:admin1_code":"26.0",
    "gn:asciiname":"Shijiamao",
    "gn:country_code":"CN",
    "gn:dem":1113,
    "gn:feature_class":"P",
    "gn:feature_code":"PPL",
    "gn:name":"Shijiamao",
    "gn:population":0,
    "gn:timezone":"Asia/Shanghai",
    "iso:country":"CN",
    "name:zho_x_preferred":[
        "\u77f3\u5bb6\u5cc1"
    ],
    "wof:name":"Shijiamao",
    "wof:placetype":"locality"
},
  "geometry": {"coordinates":[110.79273000000001,39.15003],"type":"Point"}
}