{
  "type": "Feature",
  "properties": {
    "gn:admin1_code":"9",
    "gn:asciiname":"Xiyuanfeng",
    "gn:country_code":"CN",
    "gn:dem":78,
    "gn:feature_class":"P",
    "gn:feature_code":"PPL",
    "gn:name":"Xiyuanfeng",
    "gn:population":0,
    "gn:timezone":"Asia/Shanghai",
    "iso:country":"CN",
    "name:zho_x_preferred":[
        "\u897f\u5143\u5c01"
    ],
    "wof:name":"Xiyuanfeng",
    "wof:placetype":"locality"
},
  "geometry": {"coordinates":[113.72817999999999,35.31055999999999],"type":"Point"}
}