{
  "type": "Feature",
  "properties": {
    "gn:admin1_code":"1.0",
    "gn:asciiname":"Mazhongcun",
    "gn:country_code":"CN",
    "gn:dem":9,
    "gn:feature_class":"P",
    "gn:feature_code":"PPL",
    "gn:name":"Mazhongcun",
    "gn:population":0,
    "gn:timezone":"Asia/Shanghai",
    "iso:country":"CN",
    "name:zho_x_preferred":[
        "\u9a6c\u4e2d\u6751"
    ],
    "wof:name":"Mazhongcun",
    "wof:placetype":"locality"
},
  "geometry": {"coordinates":[118.00548999999999,31.0365],"type":"Point"}
}