{
  "type": "Feature",
  "properties": {
    "gn:admin1_code":"26.0",
    "gn:asciiname":"Zaoyuancun",
    "gn:country_code":"CN",
    "gn:dem":261,
    "gn:feature_class":"P",
    "gn:feature_code":"PPL",
    "gn:name":"Zaoyuancun",
    "gn:population":0,
    "gn:timezone":"Asia/Shanghai",
    "iso:country":"CN",
    "name:zho_x_preferred":[
        "\u67a3\u56ed\u6751"
    ],
    "wof:name":"Zaoyuancun",
    "wof:placetype":"locality"
},
  "geometry": {"coordinates":[109.06242,32.68465],"type":"Point"}
}