{
  "type": "Feature",
  "properties": {
    "gn:admin1_code":"19.0",
    "gn:asciiname":"Beixinglong",
    "gn:country_code":"CN",
    "gn:dem":64,
    "gn:feature_class":"P",
    "gn:feature_code":"PPL",
    "gn:name":"Beixinglong",
    "gn:population":0,
    "gn:timezone":"Asia/Shanghai",
    "iso:country":"CN",
    "name:zho_x_preferred":[
        "\u5317\u5174\u9686"
    ],
    "wof:name":"Beixinglong",
    "wof:placetype":"locality"
},
  "geometry": {"coordinates":[122.87406,39.90743],"type":"Point"}
}