{
  "type": "Feature",
  "properties": {
    "gn:admin1_code":"32.0",
    "gn:asciiname":"Kongdongshan",
    "gn:country_code":"CN",
    "gn:dem":248,
    "gn:feature_class":"P",
    "gn:feature_code":"PPL",
    "gn:name":"Kongdongshan",
    "gn:population":0,
    "gn:timezone":"Asia/Shanghai",
    "iso:country":"CN",
    "name:zho_x_preferred":[
        "\u7a7a\u6d1e\u5c71"
    ],
    "wof:name":"Kongdongshan",
    "wof:placetype":"locality"
},
  "geometry": {"coordinates":[106.962,30.8627],"type":"Point"}
}