{
  "type": "Feature",
  "properties": {
    "gn:admin1_code":"30.0",
    "gn:asciiname":"Muluwei",
    "gn:country_code":"CN",
    "gn:dem":232,
    "gn:feature_class":"P",
    "gn:feature_code":"PPL",
    "gn:name":"Muluwei",
    "gn:population":0,
    "gn:timezone":"Asia/Urumqi",
    "iso:country":"CN",
    "name:zho_x_preferred":[
        "\u6728\u8f82\u56f4"
    ],
    "wof:name":"Muluwei",
    "wof:placetype":"locality"
},
  "geometry": {"coordinates":[111.05757,22.52461],"type":"Point"}
}