{
  "type": "Feature",
  "properties": {
    "gn:admin1_code":"24.0",
    "gn:asciiname":"Qianyaopenyao",
    "gn:country_code":"CN",
    "gn:dem":995,
    "gn:feature_class":"P",
    "gn:feature_code":"PPL",
    "gn:name":"Qianyaopenyao",
    "gn:population":0,
    "gn:timezone":"Asia/Shanghai",
    "iso:country":"CN",
    "name:zho_x_preferred":[
        "\u524d\u8170\u76c6\u8170"
    ],
    "wof:name":"Qianyaopenyao",
    "wof:placetype":"locality"
},
  "geometry": {"coordinates":[112.29165999999999,35.77079000000001],"type":"Point"}
}