{
  "type": "Feature",
  "properties": {
    "gn:admin1_code":"13",
    "gn:asciiname":"Jigerangqiong Wutaike",
    "gn:country_code":"CN",
    "gn:dem":2254,
    "gn:feature_class":"P",
    "gn:feature_code":"PPL",
    "gn:name":"Jigerangqiong Wutaike",
    "gn:population":0,
    "gn:timezone":"Asia/Urumqi",
    "iso:country":"CN",
    "name:und_x_variant":[
        "\u5409\u683c\u8ba9\u743c\u4e4c\u53f0\u514b"
    ],
    "wof:name":"Jigerangqiong Wutaike",
    "wof:placetype":"locality"
},
  "geometry": {"coordinates":[94.17285,43.57923],"type":"Point"}
}