{
  "type": "Feature",
  "properties": {
    "gn:admin1_code":"11.0",
    "gn:asciiname":"Aipo",
    "gn:country_code":"CN",
    "gn:dem":972,
    "gn:feature_class":"P",
    "gn:feature_code":"PPL",
    "gn:name":"Aipo",
    "gn:population":0,
    "gn:timezone":"Asia/Shanghai",
    "iso:country":"CN",
    "name:zho_x_preferred":[
        "\u77ee\u5761"
    ],
    "wof:name":"Aipo",
    "wof:placetype":"locality"
},
  "geometry": {"coordinates":[109.39376,28.28751],"type":"Point"}
}