{
  "type": "Feature",
  "properties": {
    "gn:admin1_code":"29.0",
    "gn:asciiname":"Najiu",
    "gn:country_code":"CN",
    "gn:dem":973,
    "gn:feature_class":"P",
    "gn:feature_code":"PPL",
    "gn:name":"Najiu",
    "gn:population":0,
    "gn:timezone":"Asia/Shanghai",
    "iso:country":"CN",
    "name:zho_x_preferred":[
        "\u90a3\u65e7"
    ],
    "wof:name":"Najiu",
    "wof:placetype":"locality"
},
  "geometry": {"coordinates":[101.867,25.9244],"type":"Point"}
}