{
  "type": "Feature",
  "properties": {
    "gn:admin1_code":"8.0",
    "gn:asciiname":"Banjiehecun",
    "gn:country_code":"CN",
    "gn:dem":203,
    "gn:feature_class":"P",
    "gn:feature_code":"PPL",
    "gn:name":"Banjiehecun",
    "gn:population":0,
    "gn:timezone":"Asia/Shanghai",
    "iso:country":"CN",
    "name:zho_x_preferred":[
        "\u534a\u622a\u6cb3\u6751"
    ],
    "wof:name":"Banjiehecun",
    "wof:placetype":"locality"
},
  "geometry": {"coordinates":[131.62295,46.05531],"type":"Point"}
}