{
  "type": "Feature",
  "properties": {
    "gn:admin1_code":"4.0",
    "gn:asciiname":"Chengxiang Xincun",
    "gn:country_code":"CN",
    "gn:dem":3,
    "gn:feature_class":"P",
    "gn:feature_code":"PPL",
    "gn:name":"Chengxiang Xincun",
    "gn:population":0,
    "gn:timezone":"Asia/Shanghai",
    "iso:country":"CN",
    "name:zho_x_preferred":[
        "\u57ce\u4e61\u65b0\u6751"
    ],
    "wof:name":"Chengxiang Xincun",
    "wof:placetype":"locality"
},
  "geometry": {"coordinates":[119.52141,32.79442],"type":"Point"}
}