{
  "type": "Feature",
  "properties": {
    "gn:admin1_code":"16",
    "gn:asciiname":"Baiyunkou",
    "gn:country_code":"CN",
    "gn:dem":272,
    "gn:feature_class":"P",
    "gn:feature_code":"PPL",
    "gn:name":"Baiyunkou",
    "gn:population":0,
    "gn:timezone":"Asia/Shanghai",
    "iso:country":"CN",
    "name:zho_x_preferred":[
        "\u767d\u4e91\u53e3"
    ],
    "wof:name":"Baiyunkou",
    "wof:placetype":"locality"
},
  "geometry": {"coordinates":[109.31100000000001,25.5143],"type":"Point"}
}