{
  "type": "Feature",
  "properties": {
    "gn:admin1_code":"19.0",
    "gn:asciiname":"Hongdaizigoushanggou",
    "gn:country_code":"CN",
    "gn:dem":222,
    "gn:feature_class":"P",
    "gn:feature_code":"PPL",
    "gn:name":"Hongdaizigoushanggou",
    "gn:population":0,
    "gn:timezone":"Asia/Shanghai",
    "iso:country":"CN",
    "name:und_x_variant":[
        "Hongdaizi Goushanggou"
    ],
    "name:zho_x_preferred":[
        "\u7ea2\u4ee3\u5b50\u6c9f\u4e0a\u6c9f"
    ],
    "wof:name":"Hongdaizigoushanggou",
    "wof:placetype":"locality"
},
  "geometry": {"coordinates":[123.77800000000001,42.0552],"type":"Point"}
}