{
  "type": "Feature",
  "properties": {
    "gn:admin1_code":"7.0",
    "gn:asciiname":"Xiaxunyuan",
    "gn:country_code":"CN",
    "gn:dem":368,
    "gn:feature_class":"P",
    "gn:feature_code":"PPL",
    "gn:name":"Xiaxunyuan",
    "gn:population":0,
    "gn:timezone":"Asia/Shanghai",
    "iso:country":"CN",
    "name:zho_x_preferred":[
        "\u4e0b\u5dfd\u6e90"
    ],
    "wof:name":"Xiaxunyuan",
    "wof:placetype":"locality"
},
  "geometry": {"coordinates":[118.46415,28.0403],"type":"Point"}
}