{
  "type": "Feature",
  "properties": {
    "gn:admin1_code":"2.0",
    "gn:asciiname":"Zhou'aodi",
    "gn:country_code":"CN",
    "gn:dem":658,
    "gn:feature_class":"P",
    "gn:feature_code":"PPL",
    "gn:name":"Zhou\u2019aodi",
    "gn:population":0,
    "gn:timezone":"Asia/Shanghai",
    "iso:country":"CN",
    "name:und_x_variant":[
        "Zhou\u2019aodi"
    ],
    "name:zho_x_preferred":[
        "\u5468\u5c99\u5e95"
    ],
    "wof:name":"Zhou'aodi",
    "wof:placetype":"locality"
},
  "geometry": {"coordinates":[119.88009,27.57145],"type":"Point"}
}