{
  "type": "Feature",
  "properties": {
    "gn:admin1_code":"3.0",
    "gn:asciiname":"Lingxiawei",
    "gn:country_code":"CN",
    "gn:dem":189,
    "gn:feature_class":"P",
    "gn:feature_code":"PPL",
    "gn:name":"Lingxiawei",
    "gn:population":0,
    "gn:timezone":"Asia/Shanghai",
    "iso:country":"CN",
    "name:und_x_variant":[
        "\u5cad\u4e0b\u5c3e"
    ],
    "wof:name":"Lingxiawei",
    "wof:placetype":"locality"
},
  "geometry": {"coordinates":[115.05607000000001,26.5133],"type":"Point"}
}