{
  "type": "Feature",
  "properties": {
    "gn:admin1_code":"18",
    "gn:asciiname":"Lubao Pingzi",
    "gn:country_code":"CN",
    "gn:dem":2313,
    "gn:feature_class":"P",
    "gn:feature_code":"PPL",
    "gn:name":"Lubao Pingzi",
    "gn:population":0,
    "gn:timezone":"Asia/Shanghai",
    "iso:country":"CN",
    "name:zho_x_preferred":[
        "\u9646\u4fdd\u576a\u5b50"
    ],
    "wof:name":"Lubao Pingzi",
    "wof:placetype":"locality"
},
  "geometry": {"coordinates":[103.986,26.6304],"type":"Point"}
}