{
  "type": "Feature",
  "properties": {
    "gn:admin1_code":"7",
    "gn:asciiname":"Tu'an",
    "gn:country_code":"CN",
    "gn:dem":43,
    "gn:feature_class":"P",
    "gn:feature_code":"PPL",
    "gn:name":"Tu\u2019an",
    "gn:population":0,
    "gn:timezone":"Asia/Shanghai",
    "iso:country":"CN",
    "name:und_x_variant":[
        "\u571f\u57b5"
    ],
    "name:zho_x_preferred":[
        "Tu\u2019an"
    ],
    "wof:name":"Tu'an",
    "wof:placetype":"locality"
},
  "geometry": {"coordinates":[118.49442000000001,24.76881],"type":"Point"}
}