{
  "type": "Feature",
  "properties": {
    "gn:admin1_code":"04",
    "gn:asciiname":"Sanchang",
    "gn:country_code":"CN",
    "gn:dem":6,
    "gn:feature_class":"P",
    "gn:feature_code":"PPLA4",
    "gn:name":"Sanchang",
    "gn:population":0,
    "gn:timezone":"Asia/Shanghai",
    "iso:country":"CN",
    "name:und_x_variant":[
        "San-ch\u2019ang-shih",
        "Sanchang",
        "\u4e09\u5382",
        "Sanchang Zhen",
        "\u4e09\u5382\u9547"
    ],
    "wof:name":"Sanchang",
    "wof:placetype":"locality"
},
  "geometry": {"coordinates":[121.24102999999999,31.89468],"type":"Point"}
}