{
  "type": "Feature",
  "properties": {
    "gn:admin1_code":"4.0",
    "gn:asciiname":"Gaogongdao",
    "gn:country_code":"CN",
    "gn:dem":-9999,
    "gn:feature_class":"P",
    "gn:feature_code":"PPLA4",
    "gn:name":"Gaogongdao",
    "gn:population":0,
    "gn:timezone":"Asia/Shanghai",
    "iso:country":"CN",
    "name:und_x_variant":[
        "\u9ad8\u516c\u5c9b",
        "Gaogongdao Xiang",
        "\u9ad8\u516c\u5c9b\u4e61"
    ],
    "wof:name":"Gaogongdao",
    "wof:placetype":"locality"
},
  "geometry": {"coordinates":[119.47499999999999,34.69583],"type":"Point"}
}