{
  "type": "Feature",
  "properties": {
    "gn:admin1_code":"30",
    "gn:asciiname":"Outang",
    "gn:country_code":"CN",
    "gn:dem":118,
    "gn:feature_class":"P",
    "gn:feature_code":"PPL",
    "gn:name":"Outang",
    "gn:population":0,
    "gn:timezone":"Asia/Shanghai",
    "iso:country":"CN",
    "name:zho_x_preferred":[
        "\u85d5\u5858"
    ],
    "wof:name":"Outang",
    "wof:placetype":"locality"
},
  "geometry": {"coordinates":[112.83538,22.68681],"type":"Point"}
}