{
  "type": "Feature",
  "properties": {
    "gn:admin1_code":"12",
    "gn:asciiname":"Wangfudian",
    "gn:cc2":"CN",
    "gn:country_code":"CN",
    "gn:dem":111,
    "gn:feature_class":"P",
    "gn:feature_code":"PPL",
    "gn:name":"Wangfudian",
    "gn:population":0,
    "gn:timezone":"Asia/Shanghai",
    "iso:country":"CN",
    "name:und_x_variant":[
        "Wang-fu-tien",
        "Wangfudian"
    ],
    "wof:name":"Wangfudian",
    "wof:placetype":"locality"
},
  "geometry": {"coordinates":[114.96666999999999,31.35],"type":"Point"}
}