{
  "type": "Feature",
  "properties": {
    "gn:admin1_code":"19.0",
    "gn:asciiname":"Yuxincun",
    "gn:country_code":"CN",
    "gn:dem":3,
    "gn:feature_class":"P",
    "gn:feature_code":"PPL",
    "gn:name":"Yuxincun",
    "gn:population":0,
    "gn:timezone":"Asia/Shanghai",
    "iso:country":"CN",
    "name:zho_x_preferred":[
        "\u80b2\u65b0\u6751"
    ],
    "wof:name":"Yuxincun",
    "wof:placetype":"locality"
},
  "geometry": {"coordinates":[121.90900000000001,41.0802],"type":"Point"}
}