{
  "type": "Feature",
  "properties": {
    "gn:admin1_code":"15.0",
    "gn:asciiname":"Layinuo",
    "gn:country_code":"CN",
    "gn:dem":2188,
    "gn:feature_class":"P",
    "gn:feature_code":"PPL",
    "gn:name":"Layinuo",
    "gn:population":0,
    "gn:timezone":"Asia/Shanghai",
    "iso:country":"CN",
    "name:zho_x_preferred":[
        "\u62c9\u4ea6\u8bfa"
    ],
    "wof:name":"Layinuo",
    "wof:placetype":"locality"
},
  "geometry": {"coordinates":[104.46883,33.54578],"type":"Point"}
}