{
  "type": "Feature",
  "properties": {
    "gn:admin1_code":"1.0",
    "gn:asciiname":"Xueyuan",
    "gn:country_code":"CN",
    "gn:dem":98,
    "gn:feature_class":"P",
    "gn:feature_code":"PPLF",
    "gn:name":"Xueyuan",
    "gn:population":0,
    "gn:timezone":"Asia/Shanghai",
    "iso:country":"CN",
    "name:zho_x_preferred":[
        "\u5b66\u56ed"
    ],
    "wof:name":"Xueyuan",
    "wof:placetype":"locality"
},
  "geometry": {"coordinates":[118.31295,30.57524],"type":"Point"}
}