{
  "type": "Feature",
  "properties": {
    "gn:admin1_code":"25",
    "gn:asciiname":"Chenliuzhuang",
    "gn:country_code":"CN",
    "gn:dem":51,
    "gn:feature_class":"P",
    "gn:feature_code":"PPL",
    "gn:name":"Chenliuzhuang",
    "gn:population":0,
    "gn:timezone":"Asia/Shanghai",
    "iso:country":"CN",
    "name:zho_x_preferred":[
        "\u9648\u5218\u5e84"
    ],
    "wof:name":"Chenliuzhuang",
    "wof:placetype":"locality"
},
  "geometry": {"coordinates":[115.529,35.6831],"type":"Point"}
}