{
  "type": "Feature",
  "properties": {
    "gn:admin1_code":"6.0",
    "gn:asciiname":"Dongxia",
    "gn:country_code":"CN",
    "gn:dem":2813,
    "gn:feature_class":"P",
    "gn:feature_code":"PPLA4",
    "gn:name":"Dongxia",
    "gn:population":0,
    "gn:timezone":"Asia/Shanghai",
    "iso:country":"CN",
    "name:und_x_variant":[
        "Dongxia Xiang"
    ],
    "name:zho_x_preferred":[
        "\u4e1c\u5ce1"
    ],
    "name:zho_x_variant":[
        "\u4e1c\u5ce1\u4e61"
    ],
    "wof:name":"Dongxia",
    "wof:placetype":"locality"
},
  "geometry": {"coordinates":[101.32598,36.68207],"type":"Point"}
}