{
  "type": "Feature",
  "properties": {
    "gn:admin1_code":"26.0",
    "gn:asciiname":"Taobuwancun",
    "gn:country_code":"CN",
    "gn:dem":1126,
    "gn:feature_class":"P",
    "gn:feature_code":"PPL",
    "gn:name":"Taobuwancun",
    "gn:population":0,
    "gn:timezone":"Asia/Shanghai",
    "iso:country":"CN",
    "name:zho_x_preferred":[
        "\u6843\u535c\u6e7e\u6751"
    ],
    "wof:name":"Taobuwancun",
    "wof:placetype":"locality"
},
  "geometry": {"coordinates":[109.89172000000001,37.37353],"type":"Point"}
}