{
  "type": "Feature",
  "properties": {
    "gn:admin1_code":"4.0",
    "gn:asciiname":"Nanxucun",
    "gn:country_code":"CN",
    "gn:dem":5,
    "gn:feature_class":"P",
    "gn:feature_code":"PPL",
    "gn:name":"Nanxucun",
    "gn:population":0,
    "gn:timezone":"Asia/Shanghai",
    "iso:country":"CN",
    "name:zho_x_preferred":[
        "\u5357\u5f90\u6751"
    ],
    "wof:name":"Nanxucun",
    "wof:placetype":"locality"
},
  "geometry": {"coordinates":[119.33172999999999,33.5675],"type":"Point"}
}