{
  "type": "Feature",
  "properties": {
    "gn:admin1_code":"3.0",
    "gn:asciiname":"Bangpei",
    "gn:country_code":"CN",
    "gn:dem":548,
    "gn:feature_class":"P",
    "gn:feature_code":"PPL",
    "gn:name":"Bangpei",
    "gn:population":0,
    "gn:timezone":"Asia/Shanghai",
    "iso:country":"CN",
    "name:und_x_variant":[
        "\u585d\u57f9"
    ],
    "wof:name":"Bangpei",
    "wof:placetype":"locality"
},
  "geometry": {"coordinates":[114.75517000000001,28.98839000000001],"type":"Point"}
}