{
  "type": "Feature",
  "properties": {
    "gn:admin1_code":"32.0",
    "gn:asciiname":"Zhi'er",
    "gn:country_code":"CN",
    "gn:dem":2610,
    "gn:feature_class":"P",
    "gn:feature_code":"PPL",
    "gn:name":"Zhi\u2019er",
    "gn:population":0,
    "gn:timezone":"Asia/Shanghai",
    "iso:country":"CN",
    "name:und_x_variant":[
        "Zhi\u2019er"
    ],
    "name:zho_x_preferred":[
        "\u77e5\u5c14"
    ],
    "wof:name":"Zhi'er",
    "wof:placetype":"locality"
},
  "geometry": {"coordinates":[103.14100000000001,32.2998],"type":"Point"}
}