{
  "type": "Feature",
  "properties": {
    "gn:admin1_code":"14.0",
    "gn:asciiname":"Caimamaguo",
    "gn:country_code":"CN",
    "gn:dem":4520,
    "gn:feature_class":"P",
    "gn:feature_code":"PPL",
    "gn:name":"Caimamaguo",
    "gn:population":0,
    "gn:timezone":"Asia/Urumqi",
    "iso:country":"CN",
    "name:zho_x_preferred":[
        "\u624d\u9ebb\u739b\u679c"
    ],
    "wof:name":"Caimamaguo",
    "wof:placetype":"locality"
},
  "geometry": {"coordinates":[96.61574,30.63775],"type":"Point"}
}