{
  "type": "Feature",
  "properties": {
    "gn:admin1_code":"32.0",
    "gn:asciiname":"Baobaoshang",
    "gn:country_code":"CN",
    "gn:dem":1446,
    "gn:feature_class":"P",
    "gn:feature_code":"PPL",
    "gn:name":"Baobaoshang",
    "gn:population":0,
    "gn:timezone":"Asia/Shanghai",
    "iso:country":"CN",
    "name:zho_x_preferred":[
        "\u5305\u5305\u4e0a"
    ],
    "wof:name":"Baobaoshang",
    "wof:placetype":"locality"
},
  "geometry": {"coordinates":[103.366,27.735],"type":"Point"}
}