{
  "type": "Feature",
  "properties": {
    "gn:admin1_code":"19",
    "gn:asciiname":"Lijiabao",
    "gn:country_code":"CN",
    "gn:dem":38,
    "gn:feature_class":"P",
    "gn:feature_code":"PPLA4",
    "gn:name":"Lijiabao",
    "gn:population":0,
    "gn:timezone":"Asia/Shanghai",
    "iso:country":"CN",
    "name:und_x_variant":[
        "Lijiabao Xiang",
        "Lijiabao"
    ],
    "name:zho_x_preferred":[
        "\u674e\u5bb6\u5821"
    ],
    "name:zho_x_variant":[
        "\u674e\u5bb6\u5821\u4e61"
    ],
    "wof:name":"Lijiabao",
    "wof:placetype":"locality"
},
  "geometry": {"coordinates":[119.80576000000001,40.10875],"type":"Point"}
}