{
  "type": "Feature",
  "properties": {
    "gn:admin1_code":"26.0",
    "gn:asciiname":"Shiyazi",
    "gn:country_code":"CN",
    "gn:dem":942,
    "gn:feature_class":"P",
    "gn:feature_code":"PPL",
    "gn:name":"Shiyazi",
    "gn:population":0,
    "gn:timezone":"Asia/Shanghai",
    "iso:country":"CN",
    "name:und_x_variant":[
        "\u77f3\u57ad\u5b50"
    ],
    "wof:name":"Shiyazi",
    "wof:placetype":"locality"
},
  "geometry": {"coordinates":[106.17041999999999,33.49612],"type":"Point"}
}