{
  "type": "Feature",
  "properties": {
    "gn:admin1_code":"7.0",
    "gn:asciiname":"Houxi",
    "gn:country_code":"CN",
    "gn:dem":31,
    "gn:feature_class":"P",
    "gn:feature_code":"PPL",
    "gn:name":"Houxi",
    "gn:population":0,
    "gn:timezone":"Asia/Shanghai",
    "iso:country":"CN",
    "name:fas_x_preferred":[
        "\u0647\u0648\u06a9\u0633\u06cc"
    ],
    "name:zho_x_preferred":[
        "\u540e\u6eaa"
    ],
    "name:zho_x_variant":[
        "\u540e\u6eaa\u9547"
    ],
    "wof:name":"Houxi",
    "wof:placetype":"locality"
},
  "geometry": {"coordinates":[117.84875,24.16312000000001],"type":"Point"}
}