{
  "type": "Feature",
  "properties": {
    "gn:admin1_code":"15.0",
    "gn:asciiname":"Wenhua",
    "gn:country_code":"CN",
    "gn:dem":1426,
    "gn:feature_class":"P",
    "gn:feature_code":"PPL",
    "gn:name":"Wenhua",
    "gn:population":0,
    "gn:timezone":"Asia/Shanghai",
    "iso:country":"CN",
    "name:deu_x_preferred":[
        "Wenhua"
    ],
    "name:zho_x_preferred":[
        "\u6587\u5316"
    ],
    "wof:name":"Wenhua",
    "wof:placetype":"locality"
},
  "geometry": {"coordinates":[104.67400000000001,36.6047],"type":"Point"}
}