{
  "type": "Feature",
  "properties": {
    "gn:admin1_code":"16",
    "gn:asciiname":"Xinan",
    "gn:country_code":"CN",
    "gn:dem":210,
    "gn:feature_class":"P",
    "gn:feature_code":"PPL",
    "gn:name":"Xinan",
    "gn:population":0,
    "gn:timezone":"Asia/Shanghai",
    "iso:country":"CN",
    "name:ceb_x_preferred":[
        "Xinan"
    ],
    "name:deu_x_preferred":[
        "Xinan"
    ],
    "name:swe_x_preferred":[
        "Xinan"
    ],
    "wof:name":"Xinan",
    "wof:placetype":"locality"
},
  "geometry": {"coordinates":[110.03082999999999,25.40833],"type":"Point"}
}