{
  "type": "Feature",
  "properties": {
    "gn:admin1_code":"18",
    "gn:asciiname":"Liuyang",
    "gn:country_code":"CN",
    "gn:dem":747,
    "gn:feature_class":"P",
    "gn:feature_code":"PPL",
    "gn:name":"Liuyang",
    "gn:population":0,
    "gn:timezone":"Asia/Shanghai",
    "iso:country":"CN",
    "name:zho_x_preferred":[
        "\u516d\u7f8a"
    ],
    "wof:name":"Liuyang",
    "wof:placetype":"locality"
},
  "geometry": {"coordinates":[105.98999999999999,27.7288],"type":"Point"}
}