{
  "type": "Feature",
  "properties": {
    "gn:admin1_code":"4.0",
    "gn:asciiname":"Xingfuzhuangcun",
    "gn:country_code":"CN",
    "gn:dem":2,
    "gn:feature_class":"P",
    "gn:feature_code":"PPL",
    "gn:name":"Xingfuzhuangcun",
    "gn:population":0,
    "gn:timezone":"Asia/Shanghai",
    "iso:country":"CN",
    "name:zho_x_preferred":[
        "\u5e78\u798f\u5e84\u6751"
    ],
    "wof:name":"Xingfuzhuangcun",
    "wof:placetype":"locality"
},
  "geometry": {"coordinates":[120.15289,32.92029],"type":"Point"}
}