{
  "type": "Feature",
  "properties": {
    "gn:admin1_code":"25",
    "gn:asciiname":"Damozhuang Beiling",
    "gn:country_code":"CN",
    "gn:dem":166,
    "gn:feature_class":"P",
    "gn:feature_code":"PPL",
    "gn:name":"Damozhuang Beiling",
    "gn:population":0,
    "gn:timezone":"Asia/Shanghai",
    "iso:country":"CN",
    "name:zho_x_preferred":[
        "\u5927\u83ab\u5e84\u5317\u5cad"
    ],
    "wof:name":"Damozhuang Beiling",
    "wof:placetype":"locality"
},
  "geometry": {"coordinates":[118.846,35.8599],"type":"Point"}
}