{
  "type": "Feature",
  "properties": {
    "gn:admin1_code":"24.0",
    "gn:asciiname":"Dongzhuangcun",
    "gn:country_code":"CN",
    "gn:dem":767,
    "gn:feature_class":"P",
    "gn:feature_code":"PPL",
    "gn:name":"Dongzhuangcun",
    "gn:population":0,
    "gn:timezone":"Asia/Shanghai",
    "iso:country":"CN",
    "name:zho_x_preferred":[
        "\u4e1c\u5e84\u6751"
    ],
    "wof:name":"Dongzhuangcun",
    "wof:placetype":"locality"
},
  "geometry": {"coordinates":[112.45263,37.69136],"type":"Point"}
}