{
  "type": "Feature",
  "properties": {
    "gn:admin1_code":"5.0",
    "gn:asciiname":"Luweicun",
    "gn:country_code":"CN",
    "gn:dem":273,
    "gn:feature_class":"P",
    "gn:feature_code":"PPL",
    "gn:name":"Luweicun",
    "gn:population":0,
    "gn:timezone":"Asia/Shanghai",
    "iso:country":"CN",
    "name:zho_x_preferred":[
        "\u82a6\u82c7\u6751"
    ],
    "wof:name":"Luweicun",
    "wof:placetype":"locality"
},
  "geometry": {"coordinates":[126.09571,43.64192],"type":"Point"}
}