{
  "type": "Feature",
  "properties": {
    "gn:admin1_code":"15.0",
    "gn:asciiname":"Yangshan",
    "gn:country_code":"CN",
    "gn:dem":2298,
    "gn:feature_class":"P",
    "gn:feature_code":"PPL",
    "gn:name":"Yangshan",
    "gn:population":0,
    "gn:timezone":"Asia/Shanghai",
    "iso:country":"CN",
    "name:und_x_variant":[
        "\u9633\u5c71"
    ],
    "name:zho_x_preferred":[
        "\u9633\u5c71"
    ],
    "wof:name":"Yangshan",
    "wof:placetype":"locality"
},
  "geometry": {"coordinates":[104.30419999999999,33.61371],"type":"Point"}
}