{
  "type": "Feature",
  "properties": {
    "gn:admin1_code":"16.0",
    "gn:asciiname":"Liuwan Linchang Chayechang",
    "gn:country_code":"CN",
    "gn:dem":427,
    "gn:feature_class":"P",
    "gn:feature_code":"PPLF",
    "gn:name":"Liuwan Linchang Chayechang",
    "gn:population":0,
    "gn:timezone":"Asia/Shanghai",
    "iso:country":"CN",
    "name:zho_x_preferred":[
        "\u516d\u4e07\u6797\u573a\u8336\u53f6\u573a"
    ],
    "wof:name":"Liuwan Linchang Chayechang",
    "wof:placetype":"locality"
},
  "geometry": {"coordinates":[109.869,22.5739],"type":"Point"}
}