{
  "type": "Feature",
  "properties": {
    "gn:admin1_code":"2.0",
    "gn:asciiname":"Jiangshantou",
    "gn:country_code":"CN",
    "gn:dem":54,
    "gn:feature_class":"P",
    "gn:feature_code":"PPL",
    "gn:name":"Jiangshantou",
    "gn:population":0,
    "gn:timezone":"Asia/Shanghai",
    "iso:country":"CN",
    "name:zho_x_preferred":[
        "\u59dc\u5c71\u5934"
    ],
    "wof:name":"Jiangshantou",
    "wof:placetype":"locality"
},
  "geometry": {"coordinates":[119.59390999999999,29.07543],"type":"Point"}
}