{
  "type": "Feature",
  "properties": {
    "gn:admin1_code":"29.0",
    "gn:asciiname":"Danaozui",
    "gn:country_code":"CN",
    "gn:dem":2223,
    "gn:feature_class":"P",
    "gn:feature_code":"PPL",
    "gn:name":"Danaozui",
    "gn:population":0,
    "gn:timezone":"Asia/Shanghai",
    "iso:country":"CN",
    "name:zho_x_preferred":[
        "\u5927\u8111\u5480"
    ],
    "wof:name":"Danaozui",
    "wof:placetype":"locality"
},
  "geometry": {"coordinates":[101.145,26.7309],"type":"Point"}
}