{
  "type": "Feature",
  "properties": {
    "gn:admin1_code":"16",
    "gn:asciiname":"Muluchong",
    "gn:country_code":"CN",
    "gn:dem":553,
    "gn:feature_class":"P",
    "gn:feature_code":"PPL",
    "gn:name":"Mul\u00fcchong",
    "gn:population":0,
    "gn:timezone":"Asia/Shanghai",
    "iso:country":"CN",
    "name:und_x_variant":[
        "Mul\u00fcchong"
    ],
    "name:zho_x_preferred":[
        "\u6728\u5f8b\u51b2"
    ],
    "wof:name":"Muluchong",
    "wof:placetype":"locality"
},
  "geometry": {"coordinates":[110.379,25.9439],"type":"Point"}
}