{
  "type": "Feature",
  "properties": {
    "gn:admin1_code":"25.0",
    "gn:asciiname":"Xiabozicun",
    "gn:country_code":"CN",
    "gn:dem":25,
    "gn:feature_class":"P",
    "gn:feature_code":"PPL",
    "gn:name":"Xiabozicun",
    "gn:population":0,
    "gn:timezone":"Asia/Shanghai",
    "iso:country":"CN",
    "name:zho_x_preferred":[
        "\u4e0b\u6cca\u5b50\u6751"
    ],
    "wof:name":"Xiabozicun",
    "wof:placetype":"locality"
},
  "geometry": {"coordinates":[121.85088,37.05011],"type":"Point"}
}