{
  "type": "Feature",
  "properties": {
    "gn:admin1_code":"16.0",
    "gn:asciiname":"Guyuan",
    "gn:country_code":"CN",
    "gn:dem":178,
    "gn:feature_class":"P",
    "gn:feature_code":"PPL",
    "gn:name":"Guyuan",
    "gn:population":0,
    "gn:timezone":"Asia/Shanghai",
    "iso:country":"CN",
    "name:ara_x_preferred":[
        "\u062c\u0648\u064a\u0648\u0627\u0646"
    ],
    "name:cdo_x_preferred":[
        "G\u00f3-ngu\u00f2ng"
    ],
    "name:ces_x_preferred":[
        "Ku-j\u00fcan"
    ],
    "name:dan_x_preferred":[
        "Guyuan"
    ],
    "name:deu_x_preferred":[
        "Guyuan"
    ],
    "name:eus_x_preferred":[
        "Guyuan"
    ],
    "name:fas_x_preferred":[
        "\u06af\u0648\u06cc\u0648\u0627\u0646"
    ],
    "name:fin_x_preferred":[
        "Guyuan"
    ],
    "name:fra_x_preferred":[
        "Guyuan"
    ],
    "name:ita_x_preferred":[
        "Guyuan"
    ],
    "name:jpn_x_preferred":[
        "\u56fa\u539f\u5e02"
    ],
    "name:kik_x_preferred":[
        "Guyuan"
    ],
    "name:kor_x_preferred":[
        "\uad6c\uc704\uc548\uc2dc"
    ],
    "name:nld_x_preferred":[
        "Guyuan"
    ],
    "name:nno_x_preferred":[
        "Guyuan"
    ],
    "name:nor_x_preferred":[
        "Guyuan"
    ],
    "name:pol_x_preferred":[
        "Guyuan"
    ],
    "name:rus_x_preferred":[
        "\u0413\u0443\u044e\u0430\u043d\u044c"
    ],
    "name:spa_x_preferred":[
        "Guyuan"
    ],
    "name:swe_x_preferred":[
        "Guyuan"
    ],
    "name:tur_x_preferred":[
        "Guyuan"
    ],
    "name:urd_x_preferred":[
        "\u06af\u0648\u06cc\u0648\u0627\u0646"
    ],
    "name:vie_x_preferred":[
        "C\u1ed1 Nguy\u00ean"
    ],
    "name:zho_x_preferred":[
        "\u53e4\u8fdc"
    ],
    "name:zho_x_variant":[
        "\u56fa\u539f\u5e02"
    ],
    "wof:name":"Guyuan",
    "wof:placetype":"locality"
},
  "geometry": {"coordinates":[109.761,23.7021],"type":"Point"}
}