{
  "type": "Feature",
  "properties": {
    "gn:admin1_code":"9.0",
    "gn:asciiname":"Yanqiu",
    "gn:cc2":"CN",
    "gn:country_code":"CN",
    "gn:dem":183,
    "gn:feature_class":"P",
    "gn:feature_code":"PPL",
    "gn:name":"Yanqiu",
    "gn:population":0,
    "gn:timezone":"Asia/Shanghai",
    "iso:country":"CN",
    "name:und_x_variant":[
        "Yen-ch\u2019iu",
        "Yanqiu"
    ],
    "wof:name":"Yanqiu",
    "wof:placetype":"locality"
},
  "geometry": {"coordinates":[112.28917,34.54417],"type":"Point"}
}