{
  "type": "Feature",
  "properties": {
    "gn:admin1_code":"1.0",
    "gn:asciiname":"Yanlicun",
    "gn:country_code":"CN",
    "gn:dem":72,
    "gn:feature_class":"P",
    "gn:feature_code":"PPL",
    "gn:name":"Yanlicun",
    "gn:population":0,
    "gn:timezone":"Asia/Shanghai",
    "iso:country":"CN",
    "name:zho_x_preferred":[
        "\u71d5\u674e\u6751"
    ],
    "wof:name":"Yanlicun",
    "wof:placetype":"locality"
},
  "geometry": {"coordinates":[118.07617999999999,32.24121],"type":"Point"}
}