{
  "type": "Feature",
  "properties": {
    "gn:admin1_code":"31.0",
    "gn:asciiname":"Maozhan",
    "gn:country_code":"CN",
    "gn:dem":223,
    "gn:feature_class":"P",
    "gn:feature_code":"PPL",
    "gn:name":"Maozhan",
    "gn:population":0,
    "gn:timezone":"Asia/Shanghai",
    "iso:country":"CN",
    "name:und_x_variant":[
        "\u6bdb\u6808"
    ],
    "wof:name":"Maozhan",
    "wof:placetype":"locality"
},
  "geometry": {"coordinates":[109.51196000000002,18.94761],"type":"Point"}
}