{
  "type": "Feature",
  "properties": {
    "gn:admin1_code":"32.0",
    "gn:asciiname":"Majingzi",
    "gn:country_code":"CN",
    "gn:dem":563,
    "gn:feature_class":"P",
    "gn:feature_code":"PPL",
    "gn:name":"Majingzi",
    "gn:population":0,
    "gn:timezone":"Asia/Shanghai",
    "iso:country":"CN",
    "name:zho_x_preferred":[
        "\u9a6c\u9888\u5b50"
    ],
    "wof:name":"Majingzi",
    "wof:placetype":"locality"
},
  "geometry": {"coordinates":[105.80468999999999,28.06668],"type":"Point"}
}