{
  "type": "Feature",
  "properties": {
    "gn:admin1_code":"6.0",
    "gn:asciiname":"Rebusa",
    "gn:country_code":"CN",
    "gn:dem":2968,
    "gn:feature_class":"P",
    "gn:feature_code":"PPL",
    "gn:name":"Rebusa",
    "gn:population":0,
    "gn:timezone":"Asia/Shanghai",
    "iso:country":"CN",
    "name:und_x_variant":[
        "\u70ed\u5e03\u8428"
    ],
    "wof:name":"Rebusa",
    "wof:placetype":"locality"
},
  "geometry": {"coordinates":[102.03046000000001,35.66097],"type":"Point"}
}