{
  "type": "Feature",
  "properties": {
    "gn:admin1_code":"11.0",
    "gn:asciiname":"Wangjia Xinwu",
    "gn:country_code":"CN",
    "gn:dem":65,
    "gn:feature_class":"P",
    "gn:feature_code":"PPL",
    "gn:name":"Wangjia Xinwu",
    "gn:population":0,
    "gn:timezone":"Asia/Shanghai",
    "iso:country":"CN",
    "name:zho_x_preferred":[
        "\u738b\u5bb6\u65b0\u5c4b"
    ],
    "wof:name":"Wangjia Xinwu",
    "wof:placetype":"locality"
},
  "geometry": {"coordinates":[112.97814,27.07206],"type":"Point"}
}