{
  "type": "Feature",
  "properties": {
    "gn:admin1_code":"11.0",
    "gn:asciiname":"Xitangxia",
    "gn:country_code":"CN",
    "gn:dem":81,
    "gn:feature_class":"P",
    "gn:feature_code":"PPL",
    "gn:name":"Xitangxia",
    "gn:population":0,
    "gn:timezone":"Asia/Shanghai",
    "iso:country":"CN",
    "name:zho_x_preferred":[
        "\u897f\u5858\u4e0b"
    ],
    "wof:name":"Xitangxia",
    "wof:placetype":"locality"
},
  "geometry": {"coordinates":[113.53194000000001,27.53651],"type":"Point"}
}