{
  "type": "Feature",
  "properties": {
    "gn:admin1_code":"8.0",
    "gn:asciiname":"Zuzhicun",
    "gn:country_code":"CN",
    "gn:dem":211,
    "gn:feature_class":"P",
    "gn:feature_code":"PPL",
    "gn:name":"Zuzhicun",
    "gn:population":0,
    "gn:timezone":"Asia/Shanghai",
    "iso:country":"CN",
    "name:zho_x_preferred":[
        "\u7ec4\u7ec7\u6751"
    ],
    "wof:name":"Zuzhicun",
    "wof:placetype":"locality"
},
  "geometry": {"coordinates":[126.46145,47.56148],"type":"Point"}
}