{
  "type": "Feature",
  "properties": {
    "gn:admin1_code":"4.0",
    "gn:asciiname":"Mabeicun",
    "gn:country_code":"CN",
    "gn:dem":4,
    "gn:feature_class":"P",
    "gn:feature_code":"PPL",
    "gn:name":"Mabeicun",
    "gn:population":0,
    "gn:timezone":"Asia/Shanghai",
    "iso:country":"CN",
    "name:zho_x_preferred":[
        "\u9a6c\u5317\u6751"
    ],
    "wof:name":"Mabeicun",
    "wof:placetype":"locality"
},
  "geometry": {"coordinates":[119.26349,33.46850999999999],"type":"Point"}
}