{
  "type": "Feature",
  "properties": {
    "gn:admin1_code":"10",
    "gn:asciiname":"Qianmozhuang",
    "gn:country_code":"CN",
    "gn:dem":48,
    "gn:feature_class":"P",
    "gn:feature_code":"PPL",
    "gn:name":"Qianmozhuang",
    "gn:population":0,
    "gn:timezone":"Asia/Shanghai",
    "iso:country":"CN",
    "name:zho_x_preferred":[
        "\u524d\u78e8\u5e84"
    ],
    "wof:name":"Qianmozhuang",
    "wof:placetype":"locality"
},
  "geometry": {"coordinates":[115.148,36.37199],"type":"Point"}
}