{
  "type": "Feature",
  "properties": {
    "gn:admin1_code":"32.0",
    "gn:asciiname":"Qiaobanpu",
    "gn:country_code":"CN",
    "gn:dem":410,
    "gn:feature_class":"P",
    "gn:feature_code":"PPL",
    "gn:name":"Qiaobanpu",
    "gn:population":0,
    "gn:timezone":"Asia/Shanghai",
    "iso:country":"CN",
    "name:zho_x_preferred":[
        "\u6865\u677f\u94fa"
    ],
    "wof:name":"Qiaobanpu",
    "wof:placetype":"locality"
},
  "geometry": {"coordinates":[104.355,28.5113],"type":"Point"}
}