{
  "type": "Feature",
  "properties": {
    "gn:admin1_code":"11",
    "gn:asciiname":"Daguquan",
    "gn:country_code":"CN",
    "gn:dem":467,
    "gn:feature_class":"P",
    "gn:feature_code":"PPL",
    "gn:name":"Daguquan",
    "gn:population":0,
    "gn:timezone":"Asia/Shanghai",
    "iso:country":"CN",
    "name:und_x_variant":[
        "\u6253\u9f13\u6cc9"
    ],
    "name:zho_x_preferred":[
        "\u6253\u9f13\u6cc9"
    ],
    "name:zho_x_variant":[
        "\u6253\u9f13\u6cc9\u4e61"
    ],
    "wof:name":"Daguquan",
    "wof:placetype":"locality"
},
  "geometry": {"coordinates":[110.08114999999999,29.43354],"type":"Point"}
}