{
  "type": "Feature",
  "properties": {
    "gn:admin1_code":"12.0",
    "gn:asciiname":"Laoguashi",
    "gn:country_code":"CN",
    "gn:dem":1507,
    "gn:feature_class":"P",
    "gn:feature_code":"PPL",
    "gn:name":"Laoguashi",
    "gn:population":0,
    "gn:timezone":"Asia/Shanghai",
    "iso:country":"CN",
    "name:zho_x_preferred":[
        "\u8001\u9e39\u77f3"
    ],
    "wof:name":"Laoguashi",
    "wof:placetype":"locality"
},
  "geometry": {"coordinates":[109.21944999999999,30.56527],"type":"Point"}
}