{
  "type": "Feature",
  "properties": {
    "gn:admin1_code":"10",
    "gn:asciiname":"Jiazi",
    "gn:country_code":"CN",
    "gn:dem":34,
    "gn:feature_class":"P",
    "gn:feature_code":"PPL",
    "gn:name":"Jiazi",
    "gn:population":0,
    "gn:timezone":"Asia/Shanghai",
    "iso:country":"CN",
    "name:zho_x_preferred":[
        "\u5bb6\u5b50"
    ],
    "wof:name":"Jiazi",
    "wof:placetype":"locality"
},
  "geometry": {"coordinates":[115.68783999999999,36.97589],"type":"Point"}
}