{
  "type": "Feature",
  "properties": {
    "gn:admin1_code":"16",
    "gn:asciiname":"Xialinjiang",
    "gn:country_code":"CN",
    "gn:dem":187,
    "gn:feature_class":"P",
    "gn:feature_code":"PPL",
    "gn:name":"Xialinjiang",
    "gn:population":0,
    "gn:timezone":"Asia/Shanghai",
    "iso:country":"CN",
    "name:zho_x_preferred":[
        "\u4e0b\u6797\u6c5f"
    ],
    "wof:name":"Xialinjiang",
    "wof:placetype":"locality"
},
  "geometry": {"coordinates":[109.619,25.7718],"type":"Point"}
}