{
  "type": "Feature",
  "properties": {
    "gn:admin1_code":"8.0",
    "gn:asciiname":"Yaogongcun",
    "gn:country_code":"CN",
    "gn:dem":200,
    "gn:feature_class":"P",
    "gn:feature_code":"PPL",
    "gn:name":"Yaogongcun",
    "gn:population":0,
    "gn:timezone":"Asia/Shanghai",
    "iso:country":"CN",
    "name:zho_x_preferred":[
        "\u8170\u8d21\u6751"
    ],
    "wof:name":"Yaogongcun",
    "wof:placetype":"locality"
},
  "geometry": {"coordinates":[127.02681,44.80167],"type":"Point"}
}