{
  "type": "Feature",
  "properties": {
    "gn:admin1_code":"29",
    "gn:asciiname":"Hainuo",
    "gn:country_code":"CN",
    "gn:dem":1589,
    "gn:feature_class":"P",
    "gn:feature_code":"PPL",
    "gn:name":"Hainuo",
    "gn:population":0,
    "gn:timezone":"Asia/Shanghai",
    "iso:country":"CN",
    "name:zho_x_preferred":[
        "\u6d77\u7cef"
    ],
    "wof:name":"Hainuo",
    "wof:placetype":"locality"
},
  "geometry": {"coordinates":[102.32299999999999,23.6738],"type":"Point"}
}