{
  "type": "Feature",
  "properties": {
    "gn:admin1_code":"14.0",
    "gn:asciiname":"Samxar",
    "gn:country_code":"CN",
    "gn:dem":3853,
    "gn:feature_class":"P",
    "gn:feature_code":"PPLF",
    "gn:name":"Samxar",
    "gn:population":0,
    "gn:timezone":"Asia/Urumqi",
    "iso:country":"CN",
    "name:bod_x_preferred":[
        "Samxar"
    ],
    "name:zho_x_preferred":[
        "Sangxia"
    ],
    "name:zho_x_variant":[
        "\u6851\u590f",
        "Quxia",
        "\u66f2\u590f"
    ],
    "wof:name":"Samxar",
    "wof:placetype":"locality"
},
  "geometry": {"coordinates":[88.905,29.205],"type":"Point"}
}