{
  "type": "Feature",
  "properties": {
    "gn:admin1_code":"32.0",
    "gn:asciiname":"Anyingba",
    "gn:country_code":"CN",
    "gn:dem":707,
    "gn:feature_class":"P",
    "gn:feature_code":"PPL",
    "gn:name":"Anyingba",
    "gn:population":0,
    "gn:timezone":"Asia/Shanghai",
    "iso:country":"CN",
    "name:zho_x_preferred":[
        "\u5b89\u8425\u575d"
    ],
    "wof:name":"Anyingba",
    "wof:placetype":"locality"
},
  "geometry": {"coordinates":[102.92100000000001,30.1783],"type":"Point"}
}