{
  "type": "Feature",
  "properties": {
    "gn:admin1_code":"32.0",
    "gn:asciiname":"Zha'en",
    "gn:country_code":"CN",
    "gn:dem":3565,
    "gn:feature_class":"P",
    "gn:feature_code":"PPL",
    "gn:name":"Zha\u2019en",
    "gn:population":0,
    "gn:timezone":"Asia/Shanghai",
    "iso:country":"CN",
    "name:und_x_variant":[
        "Zha\u2019en"
    ],
    "name:zho_x_preferred":[
        "\u624e\u6069"
    ],
    "wof:name":"Zha'en",
    "wof:placetype":"locality"
},
  "geometry": {"coordinates":[100.18600000000001,31.784],"type":"Point"}
}