{
  "type": "Feature",
  "properties": {
    "gn:admin1_code":"29",
    "gn:asciiname":"Shijia",
    "gn:country_code":"CN",
    "gn:dem":1356,
    "gn:feature_class":"P",
    "gn:feature_code":"PPL",
    "gn:name":"Shijia",
    "gn:population":0,
    "gn:timezone":"Asia/Shanghai",
    "iso:country":"CN",
    "name:ceb_x_preferred":[
        "Shijia"
    ],
    "name:swe_x_preferred":[
        "Shijia"
    ],
    "name:zho_x_preferred":[
        "\u53f2\u5bb6"
    ],
    "wof:name":"Shijia",
    "wof:placetype":"locality"
},
  "geometry": {"coordinates":[105.417,23.6449],"type":"Point"}
}