{
  "type": "Feature",
  "properties": {
    "gn:admin1_code":"3.0",
    "gn:asciiname":"Wutang",
    "gn:country_code":"CN",
    "gn:dem":103,
    "gn:feature_class":"P",
    "gn:feature_code":"PPL",
    "gn:name":"Wutang",
    "gn:population":0,
    "gn:timezone":"Asia/Shanghai",
    "iso:country":"CN",
    "name:deu_x_preferred":[
        "Wudang"
    ],
    "name:eus_x_preferred":[
        "Wudang"
    ],
    "name:fra_x_preferred":[
        "Wudang"
    ],
    "name:swe_x_preferred":[
        "Wudang"
    ],
    "name:zho_x_preferred":[
        "\u575e\u5858"
    ],
    "wof:name":"Wutang",
    "wof:placetype":"locality"
},
  "geometry": {"coordinates":[117.58408,28.52313],"type":"Point"}
}