{
  "type": "Feature",
  "properties": {
    "gn:admin1_code":"14.0",
    "gn:asciiname":"Magonglu",
    "gn:country_code":"CN",
    "gn:dem":4277,
    "gn:feature_class":"P",
    "gn:feature_code":"PPL",
    "gn:name":"Magonglu",
    "gn:population":0,
    "gn:timezone":"Asia/Urumqi",
    "iso:country":"CN",
    "name:zho_x_preferred":[
        "\u9a6c\u516c\u8def"
    ],
    "wof:name":"Magonglu",
    "wof:placetype":"locality"
},
  "geometry": {"coordinates":[92.24077,30.09674],"type":"Point"}
}