{
  "type": "Feature",
  "properties": {
    "gn:admin1_code":"4.0",
    "gn:asciiname":"Datuancun",
    "gn:country_code":"CN",
    "gn:dem":2,
    "gn:feature_class":"P",
    "gn:feature_code":"PPL",
    "gn:name":"Datuancun",
    "gn:population":0,
    "gn:timezone":"Asia/Shanghai",
    "iso:country":"CN",
    "name:zho_x_preferred":[
        "\u5927\u56e2\u6751"
    ],
    "wof:name":"Datuancun",
    "wof:placetype":"locality"
},
  "geometry": {"coordinates":[120.04712000000001,33.50311],"type":"Point"}
}