{
  "type": "Feature",
  "properties": {
    "gn:admin1_code":"32.0",
    "gn:asciiname":"Zhangjia Aoshang",
    "gn:country_code":"CN",
    "gn:dem":347,
    "gn:feature_class":"P",
    "gn:feature_code":"PPL",
    "gn:name":"Zhangjia Aoshang",
    "gn:population":0,
    "gn:timezone":"Asia/Shanghai",
    "iso:country":"CN",
    "name:zho_x_preferred":[
        "\u5f20\u5bb6\u5787\u4e0a"
    ],
    "wof:name":"Zhangjia Aoshang",
    "wof:placetype":"locality"
},
  "geometry": {"coordinates":[105.08847,29.24868],"type":"Point"}
}