{
  "type": "Feature",
  "properties": {
    "gn:admin1_code":"29.0",
    "gn:asciiname":"Gangfang",
    "gn:country_code":"CN",
    "gn:dem":1708,
    "gn:feature_class":"P",
    "gn:feature_code":"PPL",
    "gn:name":"Gangfang",
    "gn:population":0,
    "gn:timezone":"Asia/Shanghai",
    "iso:country":"CN",
    "name:zho_x_preferred":[
        "\u5c97\u623f"
    ],
    "wof:name":"Gangfang",
    "wof:placetype":"locality"
},
  "geometry": {"coordinates":[97.79689999999999,24.4651],"type":"Point"}
}