{
  "type": "Feature",
  "properties": {
    "gn:admin1_code":"25.0",
    "gn:asciiname":"Dangdao",
    "gn:country_code":"CN",
    "gn:dem":136,
    "gn:feature_class":"P",
    "gn:feature_code":"PPL",
    "gn:name":"Dangdao",
    "gn:population":0,
    "gn:timezone":"Asia/Shanghai",
    "iso:country":"CN",
    "name:zho_x_preferred":[
        "\u5f53\u9053"
    ],
    "wof:name":"Dangdao",
    "wof:placetype":"locality"
},
  "geometry": {"coordinates":[121.10478000000001,36.95953],"type":"Point"}
}