{
  "type": "Feature",
  "properties": {
    "gn:admin1_code":"32.0",
    "gn:asciiname":"Youfangzui",
    "gn:country_code":"CN",
    "gn:dem":305,
    "gn:feature_class":"P",
    "gn:feature_code":"PPL",
    "gn:name":"Youfangzui",
    "gn:population":0,
    "gn:timezone":"Asia/Shanghai",
    "iso:country":"CN",
    "name:zho_x_preferred":[
        "\u6cb9\u574a\u5480"
    ],
    "wof:name":"Youfangzui",
    "wof:placetype":"locality"
},
  "geometry": {"coordinates":[105.69199999999999,28.6445],"type":"Point"}
}