{
  "type": "Feature",
  "properties": {
    "gn:admin1_code":"32.0",
    "gn:asciiname":"Haizitou",
    "gn:country_code":"CN",
    "gn:dem":2446,
    "gn:feature_class":"P",
    "gn:feature_code":"PPL",
    "gn:name":"Haizitou",
    "gn:population":0,
    "gn:timezone":"Asia/Shanghai",
    "iso:country":"CN",
    "name:zho_x_preferred":[
        "\u6d77\u5b50\u5934"
    ],
    "wof:name":"Haizitou",
    "wof:placetype":"locality"
},
  "geometry": {"coordinates":[102.669,26.2813],"type":"Point"}
}