{
  "type": "Feature",
  "properties": {
    "gn:admin1_code":"2.0",
    "gn:asciiname":"Ruanmiao",
    "gn:country_code":"CN",
    "gn:dem":23,
    "gn:feature_class":"P",
    "gn:feature_code":"PPL",
    "gn:name":"Ruanmiao",
    "gn:population":0,
    "gn:timezone":"Asia/Shanghai",
    "iso:country":"CN",
    "name:zho_x_preferred":[
        "\u962e\u5e99"
    ],
    "wof:name":"Ruanmiao",
    "wof:placetype":"locality"
},
  "geometry": {"coordinates":[120.83166,29.56118],"type":"Point"}
}