{
  "type": "Feature",
  "properties": {
    "gn:admin1_code":"3.0",
    "gn:asciiname":"Lingnao",
    "gn:country_code":"CN",
    "gn:dem":217,
    "gn:feature_class":"P",
    "gn:feature_code":"PPL",
    "gn:name":"Lingnao",
    "gn:population":0,
    "gn:timezone":"Asia/Shanghai",
    "iso:country":"CN",
    "name:und_x_variant":[
        "\u5cad\u57b4"
    ],
    "wof:name":"Lingnao",
    "wof:placetype":"locality"
},
  "geometry": {"coordinates":[116.03552999999999,26.75626],"type":"Point"}
}