{
  "type": "Feature",
  "properties": {
    "gn:admin1_code":"25",
    "gn:asciiname":"Mankoucun",
    "gn:country_code":"CN",
    "gn:dem":36,
    "gn:feature_class":"P",
    "gn:feature_code":"PPL",
    "gn:name":"Mankoucun",
    "gn:population":0,
    "gn:timezone":"Asia/Shanghai",
    "iso:country":"CN",
    "name:und_x_variant":[
        "Mankou",
        "Mankoucun"
    ],
    "name:zho_x_preferred":[
        "\u6ee1\u53e3"
    ],
    "name:zho_x_variant":[
        "\u6ee1\u53e3\u6751"
    ],
    "wof:name":"Mankoucun",
    "wof:placetype":"locality"
},
  "geometry": {"coordinates":[116.91812,34.96329],"type":"Point"}
}