{
  "type": "Feature",
  "properties": {
    "gn:admin1_code":"16.0",
    "gn:asciiname":"Nazu",
    "gn:country_code":"CN",
    "gn:dem":741,
    "gn:feature_class":"P",
    "gn:feature_code":"PPL",
    "gn:name":"Nazu",
    "gn:population":0,
    "gn:timezone":"Asia/Shanghai",
    "iso:country":"CN",
    "name:zho_x_preferred":[
        "\u90a3\u8db3"
    ],
    "wof:name":"Nazu",
    "wof:placetype":"locality"
},
  "geometry": {"coordinates":[106.486,23.1188],"type":"Point"}
}