{
  "type": "Feature",
  "properties": {
    "gn:admin1_code":"24.0",
    "gn:asciiname":"Huangyupo",
    "gn:country_code":"CN",
    "gn:dem":1653,
    "gn:feature_class":"P",
    "gn:feature_code":"PPL",
    "gn:name":"Huangyupo",
    "gn:population":0,
    "gn:timezone":"Asia/Shanghai",
    "iso:country":"CN",
    "name:zho_x_preferred":[
        "\u9ec4\u6986\u5761"
    ],
    "wof:name":"Huangyupo",
    "wof:placetype":"locality"
},
  "geometry": {"coordinates":[112.15049,39.58812],"type":"Point"}
}