{
  "type": "Feature",
  "properties": {
    "gn:admin1_code":"4.0",
    "gn:asciiname":"Dazhai Jitou",
    "gn:country_code":"CN",
    "gn:dem":3,
    "gn:feature_class":"P",
    "gn:feature_code":"PPL",
    "gn:name":"Dazhai Jitou",
    "gn:population":0,
    "gn:timezone":"Asia/Shanghai",
    "iso:country":"CN",
    "name:zho_x_preferred":[
        "\u5927\u5be8\u77f6\u5934"
    ],
    "wof:name":"Dazhai Jitou",
    "wof:placetype":"locality"
},
  "geometry": {"coordinates":[119.51879,32.28443],"type":"Point"}
}