{
  "type": "Feature",
  "properties": {
    "gn:admin1_code":"5.0",
    "gn:asciiname":"Beihuangnitun",
    "gn:country_code":"CN",
    "gn:dem":309,
    "gn:feature_class":"P",
    "gn:feature_code":"PPL",
    "gn:name":"Beihuangnitun",
    "gn:population":0,
    "gn:timezone":"Asia/Shanghai",
    "iso:country":"CN",
    "name:zho_x_preferred":[
        "\u5317\u9ec4\u6ce5\u5c6f"
    ],
    "wof:name":"Beihuangnitun",
    "wof:placetype":"locality"
},
  "geometry": {"coordinates":[126.14251000000002,43.24141],"type":"Point"}
}