{
  "type": "Feature",
  "properties": {
    "gn:admin1_code":"26.0",
    "gn:asciiname":"Caofangzi",
    "gn:country_code":"CN",
    "gn:dem":1103,
    "gn:feature_class":"P",
    "gn:feature_code":"PPL",
    "gn:name":"Caofangzi",
    "gn:population":0,
    "gn:timezone":"Asia/Shanghai",
    "iso:country":"CN",
    "name:und_x_variant":[
        "\u8349\u623f\u5b50"
    ],
    "wof:name":"Caofangzi",
    "wof:placetype":"locality"
},
  "geometry": {"coordinates":[106.96516,33.79495],"type":"Point"}
}