{
  "type": "Feature",
  "properties": {
    "gn:admin1_code":"29.0",
    "gn:asciiname":"Qiaotou Dacun",
    "gn:country_code":"CN",
    "gn:dem":2267,
    "gn:feature_class":"P",
    "gn:feature_code":"PPL",
    "gn:name":"Qiaotou Dacun",
    "gn:population":0,
    "gn:timezone":"Asia/Shanghai",
    "iso:country":"CN",
    "name:zho_x_preferred":[
        "\u6865\u5934\u5927\u6751"
    ],
    "wof:name":"Qiaotou Dacun",
    "wof:placetype":"locality"
},
  "geometry": {"coordinates":[99.32089999999999,27.1644],"type":"Point"}
}