{
  "type": "Feature",
  "properties": {
    "gn:admin1_code":"29.0",
    "gn:asciiname":"Shandifang",
    "gn:country_code":"CN",
    "gn:dem":1697,
    "gn:feature_class":"P",
    "gn:feature_code":"PPL",
    "gn:name":"Shandifang",
    "gn:population":0,
    "gn:timezone":"Asia/Shanghai",
    "iso:country":"CN",
    "name:zho_x_preferred":[
        "\u5c71\u5730\u623f"
    ],
    "wof:name":"Shandifang",
    "wof:placetype":"locality"
},
  "geometry": {"coordinates":[100.027,25.6435],"type":"Point"}
}