{
  "type": "Feature",
  "properties": {
    "gn:admin1_code":"29",
    "gn:asciiname":"Luo-chai (1)",
    "gn:country_code":"CN",
    "gn:dem":110,
    "gn:feature_class":"P",
    "gn:feature_code":"PPL",
    "gn:name":"Luo-chai (1)",
    "gn:population":0,
    "gn:timezone":"Asia/Shanghai",
    "iso:country":"CN",
    "wof:name":"Luo-chai (1)",
    "wof:placetype":"locality"
},
  "geometry": {"coordinates":[103.94611,22.63028],"type":"Point"}
}