{
  "type": "Feature",
  "properties": {
    "gn:admin1_code":"31",
    "gn:asciiname":"Linwang",
    "gn:country_code":"CN",
    "gn:dem":7,
    "gn:feature_class":"P",
    "gn:feature_code":"PPL",
    "gn:name":"Linwang",
    "gn:population":0,
    "gn:timezone":"Asia/Shanghai",
    "iso:country":"CN",
    "name:und_x_variant":[
        "Lin-wang-ts\u2019un",
        "Linwang",
        "\u6797\u65fa"
    ],
    "wof:name":"Linwang",
    "wof:placetype":"locality"
},
  "geometry": {"coordinates":[109.69485,18.30771],"type":"Point"}
}