{
  "type": "Feature",
  "properties": {
    "gn:admin1_code":"24.0",
    "gn:asciiname":"Zhangying",
    "gn:cc2":"CN",
    "gn:country_code":"CN",
    "gn:dem":403,
    "gn:feature_class":"P",
    "gn:feature_code":"PPL",
    "gn:name":"Zhangying",
    "gn:population":0,
    "gn:timezone":"Asia/Shanghai",
    "iso:country":"CN",
    "name:und_x_variant":[
        "Chang-ying",
        "Chang-ying-chen",
        "Zhangying"
    ],
    "wof:name":"Zhangying",
    "wof:placetype":"locality"
},
  "geometry": {"coordinates":[110.37528,35.00056],"type":"Point"}
}