{
  "type": "Feature",
  "properties": {
    "gn:admin1_code":"29",
    "gn:asciiname":"Tazigeng",
    "gn:country_code":"CN",
    "gn:dem":1755,
    "gn:feature_class":"P",
    "gn:feature_code":"PPL",
    "gn:name":"Tazigeng",
    "gn:population":0,
    "gn:timezone":"Asia/Shanghai",
    "iso:country":"CN",
    "name:zho_x_preferred":[
        "\u4ed6\u8d44\u57c2"
    ],
    "wof:name":"Tazigeng",
    "wof:placetype":"locality"
},
  "geometry": {"coordinates":[101.87,24.3119],"type":"Point"}
}