{
  "type": "Feature",
  "properties": {
    "gn:admin1_code":"30",
    "gn:asciiname":"Maogang",
    "gn:country_code":"CN",
    "gn:dem":2,
    "gn:feature_class":"P",
    "gn:feature_code":"PPL",
    "gn:name":"Maogang",
    "gn:population":0,
    "gn:timezone":"Asia/Shanghai",
    "iso:country":"CN",
    "name:zho_x_preferred":[
        "\u8306\u6e2f"
    ],
    "wof:name":"Maogang",
    "wof:placetype":"locality"
},
  "geometry": {"coordinates":[116.51353,23.16216],"type":"Point"}
}