{
  "type": "Feature",
  "properties": {
    "gn:admin1_code":"7.0",
    "gn:asciiname":"Pingxi",
    "gn:country_code":"CN",
    "gn:dem":510,
    "gn:feature_class":"P",
    "gn:feature_code":"PPL",
    "gn:name":"Pingxi",
    "gn:population":0,
    "gn:timezone":"Asia/Shanghai",
    "iso:country":"CN",
    "name:zho_x_preferred":[
        "\u576a\u6eaa"
    ],
    "wof:name":"Pingxi",
    "wof:placetype":"locality"
},
  "geometry": {"coordinates":[118.87572,26.4245],"type":"Point"}
}