{
  "type": "Feature",
  "properties": {
    "gn:admin1_code":"26",
    "gn:asciiname":"Haojiabian",
    "gn:cc2":"CN",
    "gn:country_code":"CN",
    "gn:dem":1394,
    "gn:feature_class":"P",
    "gn:feature_code":"PPL",
    "gn:name":"Haojiabian",
    "gn:population":0,
    "gn:timezone":"Asia/Shanghai",
    "iso:country":"CN",
    "name:und_x_variant":[
        "Hao-chia-pien",
        "Hao-chia-ch\u2019\u00fc",
        "Haojiabian"
    ],
    "wof:name":"Haojiabian",
    "wof:placetype":"locality"
},
  "geometry": {"coordinates":[107.76667,37.01667],"type":"Point"}
}