{
  "type": "Feature",
  "properties": {
    "gn:admin1_code":"1.0",
    "gn:asciiname":"Jiangshancun",
    "gn:country_code":"CN",
    "gn:dem":347,
    "gn:feature_class":"P",
    "gn:feature_code":"PPL",
    "gn:name":"Jiangshancun",
    "gn:population":0,
    "gn:timezone":"Asia/Shanghai",
    "iso:country":"CN",
    "name:zho_x_preferred":[
        "\u6c5f\u5c71\u6751"
    ],
    "wof:name":"Jiangshancun",
    "wof:placetype":"locality"
},
  "geometry": {"coordinates":[116.74441000000002,31.09618],"type":"Point"}
}