{
  "type": "Feature",
  "properties": {
    "gn:admin1_code":"21.0",
    "gn:asciiname":"Xiajinggou",
    "gn:country_code":"CN",
    "gn:dem":2140,
    "gn:feature_class":"P",
    "gn:feature_code":"PPL",
    "gn:name":"Xiajinggou",
    "gn:population":0,
    "gn:timezone":"Asia/Shanghai",
    "iso:country":"CN",
    "name:zho_x_preferred":[
        "\u4e0b\u4e95\u6c9f"
    ],
    "wof:name":"Xiajinggou",
    "wof:placetype":"locality"
},
  "geometry": {"coordinates":[105.45999999999999,36.3213],"type":"Point"}
}