{
  "type": "Feature",
  "properties": {
    "gn:admin1_code":"18",
    "gn:asciiname":"Jiaxiong",
    "gn:country_code":"CN",
    "gn:dem":500,
    "gn:feature_class":"P",
    "gn:feature_code":"PPL",
    "gn:name":"Jiaxiong",
    "gn:population":0,
    "gn:timezone":"Asia/Shanghai",
    "iso:country":"CN",
    "name:zho_x_preferred":[
        "\u7532\u96c4"
    ],
    "wof:name":"Jiaxiong",
    "wof:placetype":"locality"
},
  "geometry": {"coordinates":[108.101,26.0031],"type":"Point"}
}