{
  "type": "Feature",
  "properties": {
    "gn:admin1_code":"14.0",
    "gn:asciiname":"Rituocun",
    "gn:country_code":"CN",
    "gn:dem":2938,
    "gn:feature_class":"P",
    "gn:feature_code":"PPL",
    "gn:name":"Rituocun",
    "gn:population":0,
    "gn:timezone":"Asia/Urumqi",
    "iso:country":"CN",
    "name:zho_x_preferred":[
        "\u65e5\u6258\u6751"
    ],
    "wof:name":"Rituocun",
    "wof:placetype":"locality"
},
  "geometry": {"coordinates":[97.84653,29.03299],"type":"Point"}
}