{
  "type": "Feature",
  "properties": {
    "gn:admin1_code":"29.0",
    "gn:asciiname":"Badoushan",
    "gn:country_code":"CN",
    "gn:dem":2114,
    "gn:feature_class":"P",
    "gn:feature_code":"PPL",
    "gn:name":"Badoushan",
    "gn:population":0,
    "gn:timezone":"Asia/Shanghai",
    "iso:country":"CN",
    "name:zho_x_preferred":[
        "\u516b\u6597\u5c71"
    ],
    "wof:name":"Badoushan",
    "wof:placetype":"locality"
},
  "geometry": {"coordinates":[101.73,23.5632],"type":"Point"}
}