{
  "type": "Feature",
  "properties": {
    "gn:admin1_code":"9.0",
    "gn:asciiname":"Duyingzi",
    "gn:country_code":"CN",
    "gn:dem":33,
    "gn:feature_class":"P",
    "gn:feature_code":"PPL",
    "gn:name":"Duyingzi",
    "gn:population":0,
    "gn:timezone":"Asia/Shanghai",
    "iso:country":"CN",
    "name:zho_x_preferred":[
        "\u675c\u8425\u5b5c"
    ],
    "wof:name":"Duyingzi",
    "wof:placetype":"locality"
},
  "geometry": {"coordinates":[115.44147,32.43667],"type":"Point"}
}