{
  "type": "Feature",
  "properties": {
    "gn:admin1_code":"18.0",
    "gn:asciiname":"Wenshan",
    "gn:country_code":"CN",
    "gn:dem":1211,
    "gn:feature_class":"P",
    "gn:feature_code":"PPL",
    "gn:name":"Wenshan",
    "gn:population":0,
    "gn:timezone":"Asia/Shanghai",
    "iso:country":"CN",
    "name:ceb_x_preferred":[
        "Wenshan"
    ],
    "name:deu_x_preferred":[
        "Wenshan"
    ],
    "name:fas_x_preferred":[
        "\u0648\u0646\u0634\u0627\u0646"
    ],
    "name:heb_x_preferred":[
        "\u05d5\u05d5\u05e0\u05e9\u05d0\u05df"
    ],
    "name:hun_x_preferred":[
        "Wenshan"
    ],
    "name:nld_x_preferred":[
        "Wenshan"
    ],
    "name:pol_x_preferred":[
        "Wenshan"
    ],
    "name:rus_x_preferred":[
        "\u0412\u044d\u043d\u044c\u0448\u0430\u043d\u044c"
    ],
    "name:spa_x_preferred":[
        "Wenshan"
    ],
    "name:zho_x_preferred":[
        "\u6587\u5c71"
    ],
    "wof:name":"Wenshan",
    "wof:placetype":"locality"
},
  "geometry": {"coordinates":[105.60599999999999,25.7298],"type":"Point"}
}