{
  "type": "Feature",
  "properties": {
    "gn:admin1_code":"18.0",
    "gn:asciiname":"Wenshan",
    "gn:country_code":"CN",
    "gn:dem":1211,
    "gn:feature_class":"P",
    "gn:feature_code":"PPL",
    "gn:name":"Wenshan",
    "gn:population":0,
    "gn:timezone":"Asia/Shanghai",
    "iso:country":"CN",
    "name:zho_x_preferred":[
        "\u6587\u5c71"
    ],
    "wof:name":"Wenshan",
    "wof:placetype":"locality"
},
  "geometry": {"coordinates":[105.60599999999999,25.7298],"type":"Point"}
}