{
  "type": "Feature",
  "properties": {
    "gn:admin1_code":"18",
    "gn:asciiname":"Duijiawan",
    "gn:country_code":"CN",
    "gn:dem":656,
    "gn:feature_class":"P",
    "gn:feature_code":"PPL",
    "gn:name":"Duijiawan",
    "gn:population":0,
    "gn:timezone":"Asia/Shanghai",
    "iso:country":"CN",
    "name:zho_x_preferred":[
        "\u5bf9\u5bb6\u6e7e"
    ],
    "wof:name":"Duijiawan",
    "wof:placetype":"locality"
},
  "geometry": {"coordinates":[108.369,27.7836],"type":"Point"}
}