{
  "type": "Feature",
  "properties": {
    "gn:admin1_code":"19.0",
    "gn:asciiname":"Xiahewan",
    "gn:country_code":"CN",
    "gn:dem":42,
    "gn:feature_class":"P",
    "gn:feature_code":"PPL",
    "gn:name":"Xiahewan",
    "gn:population":0,
    "gn:timezone":"Asia/Shanghai",
    "iso:country":"CN",
    "name:zho_x_preferred":[
        "\u4e0b\u6cb3\u6e7e"
    ],
    "wof:name":"Xiahewan",
    "wof:placetype":"locality"
},
  "geometry": {"coordinates":[123.35745,41.7054],"type":"Point"}
}