{
  "type": "Feature",
  "properties": {
    "gn:admin1_code":"2.0",
    "gn:asciiname":"Waifan",
    "gn:country_code":"CN",
    "gn:dem":174,
    "gn:feature_class":"P",
    "gn:feature_code":"PPL",
    "gn:name":"Waifan",
    "gn:population":0,
    "gn:timezone":"Asia/Shanghai",
    "iso:country":"CN",
    "name:zho_x_preferred":[
        "\u5916\u7548"
    ],
    "wof:name":"Waifan",
    "wof:placetype":"locality"
},
  "geometry": {"coordinates":[119.59275,28.93158],"type":"Point"}
}