{
  "type": "Feature",
  "properties": {
    "gn:admin1_code":"4.0",
    "gn:asciiname":"Xiaoqingyangcun",
    "gn:country_code":"CN",
    "gn:dem":5,
    "gn:feature_class":"P",
    "gn:feature_code":"PPL",
    "gn:name":"Xiaoqingyangcun",
    "gn:population":0,
    "gn:timezone":"Asia/Shanghai",
    "iso:country":"CN",
    "name:und_x_variant":[
        "\u5c0f\u9752\u9633\u6751"
    ],
    "name:zho_x_preferred":[
        "\u5c0f\u9752\u9633\u6751"
    ],
    "wof:name":"Xiaoqingyangcun",
    "wof:placetype":"locality"
},
  "geometry": {"coordinates":[120.2458,31.7459],"type":"Point"}
}