{
  "type": "Feature",
  "properties": {
    "gn:admin1_code":"7",
    "gn:asciiname":"Longshuiliao",
    "gn:country_code":"CN",
    "gn:dem":30,
    "gn:feature_class":"P",
    "gn:feature_code":"PPL",
    "gn:name":"Longshuiliao",
    "gn:population":0,
    "gn:timezone":"Asia/Shanghai",
    "iso:country":"CN",
    "name:zho_x_preferred":[
        "\u9f99\u6c34\u5bee"
    ],
    "wof:name":"Longshuiliao",
    "wof:placetype":"locality"
},
  "geometry": {"coordinates":[118.5629,24.62286],"type":"Point"}
}