{
  "type": "Feature",
  "properties": {
    "gn:admin1_code":"30.0",
    "gn:asciiname":"Dongwu Weizai",
    "gn:country_code":"CN",
    "gn:dem":-1,
    "gn:feature_class":"P",
    "gn:feature_code":"PPL",
    "gn:name":"Dongwu Weizai",
    "gn:population":0,
    "gn:timezone":"Asia/Shanghai",
    "iso:country":"CN",
    "name:zho_x_preferred":[
        "\u4e1c\u4e94\u56f4\u4ed4"
    ],
    "wof:name":"Dongwu Weizai",
    "wof:placetype":"locality"
},
  "geometry": {"coordinates":[113.37752,22.2142],"type":"Point"}
}