{
  "type": "Feature",
  "properties": {
    "gn:admin1_code":"18",
    "gn:asciiname":"Baiyarong",
    "gn:country_code":"CN",
    "gn:dem":1123,
    "gn:feature_class":"P",
    "gn:feature_code":"PPL",
    "gn:name":"Baiyarong",
    "gn:population":0,
    "gn:timezone":"Asia/Shanghai",
    "iso:country":"CN",
    "name:zho_x_preferred":[
        "\u6446\u4e9a\u8363"
    ],
    "wof:name":"Baiyarong",
    "wof:placetype":"locality"
},
  "geometry": {"coordinates":[106.741,26.2868],"type":"Point"}
}