{
  "type": "Feature",
  "properties": {
    "gn:admin1_code":"29.0",
    "gn:asciiname":"Tuzhihua",
    "gn:country_code":"CN",
    "gn:dem":2930,
    "gn:feature_class":"P",
    "gn:feature_code":"PPL",
    "gn:name":"Tuzhihua",
    "gn:population":0,
    "gn:timezone":"Asia/Shanghai",
    "iso:country":"CN",
    "name:zho_x_preferred":[
        "\u5410\u679d\u82b1"
    ],
    "wof:name":"Tuzhihua",
    "wof:placetype":"locality"
},
  "geometry": {"coordinates":[99.7397,26.8543],"type":"Point"}
}