{
  "type": "Feature",
  "properties": {
    "gn:admin1_code":"24.0",
    "gn:asciiname":"Zhudongshe",
    "gn:cc2":"CN",
    "gn:country_code":"CN",
    "gn:dem":859,
    "gn:feature_class":"P",
    "gn:feature_code":"PPL",
    "gn:name":"Zhudongshe",
    "gn:population":0,
    "gn:timezone":"Asia/Shanghai",
    "iso:country":"CN",
    "name:und_x_variant":[
        "Shang-tung-she",
        "Chu-tung-she",
        "Zhudongshe"
    ],
    "wof:name":"Zhudongshe",
    "wof:placetype":"locality"
},
  "geometry": {"coordinates":[113.0025,38.74139],"type":"Point"}
}