{
  "type": "Feature",
  "properties": {
    "gn:admin1_code":"07",
    "gn:asciiname":"Hushi",
    "gn:country_code":"CN",
    "gn:dem":11,
    "gn:feature_class":"P",
    "gn:feature_code":"PPLA4",
    "gn:name":"Hushi",
    "gn:population":0,
    "gn:timezone":"Asia/Shanghai",
    "iso:country":"CN",
    "name:heb_x_preferred":[
        "\u05d7\u05d5\u05e9\u05d9"
    ],
    "name:und_x_variant":[
        "Hu-shih",
        "Hushi",
        "Hushi Zhen"
    ],
    "name:zho_x_preferred":[
        "\u7b0f\u77f3"
    ],
    "name:zho_x_variant":[
        "\u7b0f\u77f3\u9547"
    ],
    "wof:name":"Hushi",
    "wof:placetype":"locality"
},
  "geometry": {"coordinates":[119.08842,25.31778],"type":"Point"}
}