{
  "type": "Feature",
  "properties": {
    "gn:admin1_code":"32.0",
    "gn:asciiname":"Tanchanggou",
    "gn:country_code":"CN",
    "gn:dem":1270,
    "gn:feature_class":"P",
    "gn:feature_code":"PPL",
    "gn:name":"Tanchanggou",
    "gn:population":0,
    "gn:timezone":"Asia/Shanghai",
    "iso:country":"CN",
    "name:zho_x_preferred":[
        "\u575b\u5382\u6c9f"
    ],
    "wof:name":"Tanchanggou",
    "wof:placetype":"locality"
},
  "geometry": {"coordinates":[105.59332000000001,27.95371],"type":"Point"}
}