{
  "type": "Feature",
  "properties": {
    "gn:admin1_code":"29",
    "gn:asciiname":"Chung-chai (1)",
    "gn:country_code":"CN",
    "gn:dem":169,
    "gn:feature_class":"P",
    "gn:feature_code":"PPL",
    "gn:name":"Chung-chai (1)",
    "gn:population":0,
    "gn:timezone":"Asia/Shanghai",
    "iso:country":"CN",
    "wof:name":"Chung-chai (1)",
    "wof:placetype":"locality"
},
  "geometry": {"coordinates":[103.97556,22.60611],"type":"Point"}
}