{
  "type": "Feature",
  "properties": {
    "gn:admin1_code":"4.0",
    "gn:asciiname":"Haziba",
    "gn:country_code":"CN",
    "gn:dem":3,
    "gn:feature_class":"P",
    "gn:feature_code":"PPL",
    "gn:name":"Haziba",
    "gn:population":0,
    "gn:timezone":"Asia/Shanghai",
    "iso:country":"CN",
    "name:zho_x_preferred":[
        "\u86e4\u5b50\u575d"
    ],
    "wof:name":"Haziba",
    "wof:placetype":"locality"
},
  "geometry": {"coordinates":[120.23659000000001,32.04866],"type":"Point"}
}