{
  "type": "Feature",
  "properties": {
    "gn:admin1_code":"14.0",
    "gn:asciiname":"Baoyiyake",
    "gn:country_code":"CN",
    "gn:dem":3994,
    "gn:feature_class":"P",
    "gn:feature_code":"PPL",
    "gn:name":"Baoyiyake",
    "gn:population":0,
    "gn:timezone":"Asia/Urumqi",
    "iso:country":"CN",
    "name:zho_x_preferred":[
        "\u4fdd\u610f\u5440\u53ef"
    ],
    "wof:name":"Baoyiyake",
    "wof:placetype":"locality"
},
  "geometry": {"coordinates":[97.44374999999999,31.97364],"type":"Point"}
}