{
  "type": "Feature",
  "properties": {
    "gn:admin1_code":"30",
    "gn:asciiname":"Xinbuyuan",
    "gn:country_code":"CN",
    "gn:dem":28,
    "gn:feature_class":"P",
    "gn:feature_code":"PPL",
    "gn:name":"Xinbuyuan",
    "gn:population":0,
    "gn:timezone":"Asia/Shanghai",
    "iso:country":"CN",
    "name:zho_x_preferred":[
        "\u65b0\u57d4\u56ed"
    ],
    "wof:name":"Xinbuyuan",
    "wof:placetype":"locality"
},
  "geometry": {"coordinates":[116.18308,23.70851],"type":"Point"}
}