{
  "type": "Feature",
  "properties": {
    "gn:admin1_code":"26.0",
    "gn:asciiname":"Shijiawan",
    "gn:country_code":"CN",
    "gn:dem":1354,
    "gn:feature_class":"P",
    "gn:feature_code":"PPL",
    "gn:name":"Shijiawan",
    "gn:population":0,
    "gn:timezone":"Asia/Shanghai",
    "iso:country":"CN",
    "name:und_x_variant":[
        "\u77f3\u5bb6\u6e7e"
    ],
    "wof:name":"Shijiawan",
    "wof:placetype":"locality"
},
  "geometry": {"coordinates":[107.73138,34.79778],"type":"Point"}
}