{
  "type": "Feature",
  "properties": {
    "gn:admin1_code":"02",
    "gn:asciiname":"Shangfangcun",
    "gn:country_code":"CN",
    "gn:dem":55,
    "gn:feature_class":"P",
    "gn:feature_code":"PPL",
    "gn:name":"Shangfangcun",
    "gn:population":0,
    "gn:timezone":"Asia/Shanghai",
    "iso:country":"CN",
    "name:und_x_variant":[
        "Shang-wang",
        "Shangfang",
        "Shangfangcun"
    ],
    "name:zho_x_preferred":[
        "\u4e0a\u623f\u6751"
    ],
    "wof:name":"Shangfangcun",
    "wof:placetype":"locality"
},
  "geometry": {"coordinates":[121.46301,28.96207],"type":"Point"}
}