{
  "type": "Feature",
  "properties": {
    "gn:admin1_code":"14.0",
    "gn:asciiname":"Renqinglincun",
    "gn:country_code":"CN",
    "gn:dem":4030,
    "gn:feature_class":"P",
    "gn:feature_code":"PPL",
    "gn:name":"Renqinglincun",
    "gn:population":0,
    "gn:timezone":"Asia/Urumqi",
    "iso:country":"CN",
    "name:zho_x_preferred":[
        "\u4ec1\u9752\u6797\u6751"
    ],
    "wof:name":"Renqinglincun",
    "wof:placetype":"locality"
},
  "geometry": {"coordinates":[91.96543,29.73628],"type":"Point"}
}