{
  "type": "Feature",
  "properties": {
    "gn:admin1_code":"3.0",
    "gn:asciiname":"Zhuguang",
    "gn:country_code":"CN",
    "gn:dem":20,
    "gn:feature_class":"P",
    "gn:feature_code":"PPL",
    "gn:name":"Zhuguang",
    "gn:population":0,
    "gn:timezone":"Asia/Shanghai",
    "iso:country":"CN",
    "name:und_x_variant":[
        "\u73e0\u5149"
    ],
    "wof:name":"Zhuguang",
    "wof:placetype":"locality"
},
  "geometry": {"coordinates":[116.41876000000001,29.32828],"type":"Point"}
}