{
  "type": "Feature",
  "properties": {
    "gn:admin1_code":"08",
    "gn:asciiname":"Sandaohezi",
    "gn:cc2":"CN",
    "gn:country_code":"CN",
    "gn:dem":377,
    "gn:feature_class":"P",
    "gn:feature_code":"PPL",
    "gn:name":"Sandaohezi",
    "gn:population":0,
    "gn:timezone":"Asia/Shanghai",
    "iso:country":"CN",
    "name:und_x_variant":[
        "San-tao-ho-tzu",
        "Sandaohezi"
    ],
    "wof:name":"Sandaohezi",
    "wof:placetype":"locality"
},
  "geometry": {"coordinates":[129.76667,44.05],"type":"Point"}
}