{
  "type": "Feature",
  "properties": {
    "gn:admin1_code":"8.0",
    "gn:asciiname":"Xingluncun",
    "gn:country_code":"CN",
    "gn:dem":161,
    "gn:feature_class":"P",
    "gn:feature_code":"PPL",
    "gn:name":"Xingluncun",
    "gn:population":0,
    "gn:timezone":"Asia/Shanghai",
    "iso:country":"CN",
    "name:zho_x_preferred":[
        "\u5174\u4f26\u6751"
    ],
    "wof:name":"Xingluncun",
    "wof:placetype":"locality"
},
  "geometry": {"coordinates":[126.37045999999999,47.10285],"type":"Point"}
}