{
  "type": "Feature",
  "properties": {
    "gn:admin1_code":"26",
    "gn:asciiname":"Erdaohe",
    "gn:country_code":"CN",
    "gn:dem":1033,
    "gn:feature_class":"P",
    "gn:feature_code":"PPL",
    "gn:name":"Erdaohe",
    "gn:population":0,
    "gn:timezone":"Asia/Shanghai",
    "iso:country":"CN",
    "name:und_x_variant":[
        "Erh-tao-ho",
        "Erdaohe",
        "\u4e8c\u9053\u6cb3"
    ],
    "wof:name":"Erdaohe",
    "wof:placetype":"locality"
},
  "geometry": {"coordinates":[106.54049000000001,32.93845],"type":"Point"}
}