{
  "type": "Feature",
  "properties": {
    "gn:admin1_code":"11.0",
    "gn:asciiname":"Bitangwan",
    "gn:country_code":"CN",
    "gn:dem":156,
    "gn:feature_class":"P",
    "gn:feature_code":"PPL",
    "gn:name":"Bitangwan",
    "gn:population":0,
    "gn:timezone":"Asia/Shanghai",
    "iso:country":"CN",
    "name:zho_x_preferred":[
        "\u78a7\u5802\u6e7e"
    ],
    "wof:name":"Bitangwan",
    "wof:placetype":"locality"
},
  "geometry": {"coordinates":[111.98260000000001,27.18698],"type":"Point"}
}