{
  "type": "Feature",
  "properties": {
    "gn:admin1_code":"12.0",
    "gn:asciiname":"Shenhexiang",
    "gn:country_code":"CN",
    "gn:dem":462,
    "gn:feature_class":"P",
    "gn:feature_code":"PPL",
    "gn:name":"Shenhexiang",
    "gn:population":0,
    "gn:timezone":"Asia/Shanghai",
    "iso:country":"CN",
    "name:zho_x_preferred":[
        "\u6df1\u6cb3\u4e61"
    ],
    "wof:name":"Shenhexiang",
    "wof:placetype":"locality"
},
  "geometry": {"coordinates":[110.21930999999999,32.11233],"type":"Point"}
}