{
  "type": "Feature",
  "properties": {
    "gn:admin1_code":"19.0",
    "gn:asciiname":"Xiao'anxintai",
    "gn:country_code":"CN",
    "gn:dem":57,
    "gn:feature_class":"P",
    "gn:feature_code":"PPL",
    "gn:name":"Xiao\u2019anxintai",
    "gn:population":0,
    "gn:timezone":"Asia/Shanghai",
    "iso:country":"CN",
    "name:und_x_variant":[
        "Xiao\u2019anxintai"
    ],
    "name:zho_x_preferred":[
        "\u5c0f\u5b89\u5fc3\u53f0"
    ],
    "wof:name":"Xiao'anxintai",
    "wof:placetype":"locality"
},
  "geometry": {"coordinates":[123.581,42.1293],"type":"Point"}
}