{
  "type": "Feature",
  "properties": {
    "gn:admin1_code":"18",
    "gn:asciiname":"Huangguazhai",
    "gn:country_code":"CN",
    "gn:dem":599,
    "gn:feature_class":"P",
    "gn:feature_code":"PPL",
    "gn:name":"Huangguazhai",
    "gn:population":0,
    "gn:timezone":"Asia/Shanghai",
    "iso:country":"CN",
    "name:zho_x_preferred":[
        "\u9ec4\u74dc\u5be8"
    ],
    "wof:name":"Huangguazhai",
    "wof:placetype":"locality"
},
  "geometry": {"coordinates":[106.696,25.47300000000001],"type":"Point"}
}