{
  "type": "Feature",
  "properties": {
    "gn:admin1_code":"1.0",
    "gn:asciiname":"Niexiaomiaocun",
    "gn:country_code":"CN",
    "gn:dem":34,
    "gn:feature_class":"P",
    "gn:feature_code":"PPL",
    "gn:name":"Niexiaomiaocun",
    "gn:population":0,
    "gn:timezone":"Asia/Shanghai",
    "iso:country":"CN",
    "name:zho_x_preferred":[
        "\u8042\u5c0f\u5e99\u6751"
    ],
    "wof:name":"Niexiaomiaocun",
    "wof:placetype":"locality"
},
  "geometry": {"coordinates":[115.97729,33.38068],"type":"Point"}
}