{
  "type": "Feature",
  "properties": {
    "gn:admin1_code":"32.0",
    "gn:asciiname":"Loufangping",
    "gn:country_code":"CN",
    "gn:dem":817,
    "gn:feature_class":"P",
    "gn:feature_code":"PPL",
    "gn:name":"Loufangping",
    "gn:population":0,
    "gn:timezone":"Asia/Shanghai",
    "iso:country":"CN",
    "name:zho_x_preferred":[
        "\u697c\u623f\u576a"
    ],
    "wof:name":"Loufangping",
    "wof:placetype":"locality"
},
  "geometry": {"coordinates":[107.747,31.7848],"type":"Point"}
}