{
  "type": "Feature",
  "properties": {
    "gn:admin1_code":"15.0",
    "gn:asciiname":"Xixilu",
    "gn:country_code":"CN",
    "gn:dem":2490,
    "gn:feature_class":"P",
    "gn:feature_code":"PPL",
    "gn:name":"Xixilu",
    "gn:population":0,
    "gn:timezone":"Asia/Shanghai",
    "iso:country":"CN",
    "name:zho_x_preferred":[
        "\u897f\u897f\u8def"
    ],
    "wof:name":"Xixilu",
    "wof:placetype":"locality"
},
  "geometry": {"coordinates":[104.50489,34.08656],"type":"Point"}
}