{
  "type": "Feature",
  "properties": {
    "gn:admin1_code":"19.0",
    "gn:asciiname":"Xiaosanjiacun",
    "gn:country_code":"CN",
    "gn:dem":271,
    "gn:feature_class":"P",
    "gn:feature_code":"PPL",
    "gn:name":"Xiaosanjiacun",
    "gn:population":0,
    "gn:timezone":"Asia/Shanghai",
    "iso:country":"CN",
    "name:zho_x_preferred":[
        "\u8096\u4e09\u5bb6\u6751"
    ],
    "wof:name":"Xiaosanjiacun",
    "wof:placetype":"locality"
},
  "geometry": {"coordinates":[119.98036999999999,41.37091],"type":"Point"}
}