{
  "type": "Feature",
  "properties": {
    "gn:admin1_code":"22.0",
    "gn:asciiname":"Shiyaocun",
    "gn:country_code":"CN",
    "gn:dem":824,
    "gn:feature_class":"P",
    "gn:feature_code":"PPL",
    "gn:name":"Shiyaocun",
    "gn:population":0,
    "gn:timezone":"Asia/Shanghai",
    "iso:country":"CN",
    "name:zho_x_preferred":[
        "\u77f3\u7a91\u6751"
    ],
    "wof:name":"Shiyaocun",
    "wof:placetype":"locality"
},
  "geometry": {"coordinates":[116.47217999999999,40.49417],"type":"Point"}
}