{
  "type": "Feature",
  "properties": {
    "gn:admin1_code":"7",
    "gn:asciiname":"Nanyuan",
    "gn:country_code":"CN",
    "gn:dem":306,
    "gn:feature_class":"P",
    "gn:feature_code":"PPL",
    "gn:name":"Nanyuan",
    "gn:population":0,
    "gn:timezone":"Asia/Shanghai",
    "iso:country":"CN",
    "name:ceb_x_preferred":[
        "Nanyuan"
    ],
    "name:swe_x_preferred":[
        "Nanyuan"
    ],
    "name:und_x_variant":[
        "\u5357\u6e90"
    ],
    "name:zho_x_preferred":[
        "\u5357\u82d1"
    ],
    "wof:name":"Nanyuan",
    "wof:placetype":"locality"
},
  "geometry": {"coordinates":[118.56056,27.90028],"type":"Point"}
}