{
  "type": "Feature",
  "properties": {
    "gn:admin1_code":"14.0",
    "gn:asciiname":"Qieqin",
    "gn:country_code":"CN",
    "gn:dem":5579,
    "gn:feature_class":"P",
    "gn:feature_code":"PPLF",
    "gn:name":"Qieqin",
    "gn:population":0,
    "gn:timezone":"Asia/Urumqi",
    "iso:country":"CN",
    "name:bod_x_preferred":[
        "Q\u00eaq\u00ean"
    ],
    "name:msa_x_preferred":[
        "Q\u00eaq\u00ean"
    ],
    "name:und_x_variant":[
        "Q\u00eaq\u00ean"
    ],
    "name:zho_x_preferred":[
        "Qieqin"
    ],
    "name:zho_x_variant":[
        "\u5207\u94a6"
    ],
    "wof:name":"Qieqin",
    "wof:placetype":"locality"
},
  "geometry": {"coordinates":[86.40000000000001,29.88333],"type":"Point"}
}