{
  "type": "Feature",
  "properties": {
    "gn:admin1_code":"26.0",
    "gn:asciiname":"Chaicuncun",
    "gn:country_code":"CN",
    "gn:dem":819,
    "gn:feature_class":"P",
    "gn:feature_code":"PPL",
    "gn:name":"Chaicuncun",
    "gn:population":0,
    "gn:timezone":"Asia/Shanghai",
    "iso:country":"CN",
    "name:zho_x_preferred":[
        "\u67f4\u6751\u6751"
    ],
    "wof:name":"Chaicuncun",
    "wof:placetype":"locality"
},
  "geometry": {"coordinates":[110.41736000000002,36.23754],"type":"Point"}
}