{
  "type": "Feature",
  "properties": {
    "gn:admin1_code":"14",
    "gn:asciiname":"Saida",
    "gn:country_code":"CN",
    "gn:dem":3635,
    "gn:feature_class":"P",
    "gn:feature_code":"PPL",
    "gn:name":"Saida",
    "gn:population":0,
    "gn:timezone":"Asia/Urumqi",
    "iso:country":"CN",
    "name:bod_x_preferred":[
        "\u0f5f\u0f66\u0f0b\u0f58\u0f51\u0f60"
    ],
    "name:ceb_x_preferred":[
        "Saida"
    ],
    "name:deu_x_preferred":[
        "Saida"
    ],
    "name:fas_x_preferred":[
        "\u0633\u0639\u06cc\u062f\u0647"
    ],
    "name:heb_x_preferred":[
        "\u05e1\u05d9\u05d9\u05d3\u05d0"
    ],
    "name:ind_x_preferred":[
        "Saida"
    ],
    "name:kor_x_preferred":[
        "\uc0ac\uc774\ub2e4"
    ],
    "name:lit_x_preferred":[
        "Saida"
    ],
    "name:nld_x_preferred":[
        "Saida"
    ],
    "name:por_x_preferred":[
        "Sa\u00edda"
    ],
    "name:ron_x_preferred":[
        "Saida"
    ],
    "name:rus_x_preferred":[
        "\u0421\u0430\u0438\u0434\u0430"
    ],
    "name:swe_x_preferred":[
        "Saida"
    ],
    "wof:name":"Saida",
    "wof:placetype":"locality"
},
  "geometry": {"coordinates":[90.65849,29.3322],"type":"Point"}
}