{
  "type": "Feature",
  "properties": {
    "gn:admin1_code":"14",
    "gn:asciiname":"Saida",
    "gn:country_code":"CN",
    "gn:dem":3635,
    "gn:feature_class":"P",
    "gn:feature_code":"PPL",
    "gn:name":"Saida",
    "gn:population":0,
    "gn:timezone":"Asia/Urumqi",
    "iso:country":"CN",
    "name:bod_x_preferred":[
        "\u0f5f\u0f66\u0f0b\u0f58\u0f51\u0f60"
    ],
    "wof:name":"Saida",
    "wof:placetype":"locality"
},
  "geometry": {"coordinates":[90.65849,29.3322],"type":"Point"}
}