{
  "type": "Feature",
  "properties": {
    "gn:admin1_code":"10.0",
    "gn:asciiname":"Xinqingyuan",
    "gn:country_code":"CN",
    "gn:dem":32,
    "gn:feature_class":"P",
    "gn:feature_code":"PPL",
    "gn:name":"Xinqingyuan",
    "gn:population":0,
    "gn:timezone":"Asia/Shanghai",
    "iso:country":"CN",
    "name:zho_x_preferred":[
        "\u99a8\u5e86\u56ed"
    ],
    "wof:name":"Xinqingyuan",
    "wof:placetype":"locality"
},
  "geometry": {"coordinates":[119.4795,39.82691],"type":"Point"}
}