{
  "type": "Feature",
  "properties": {
    "gn:admin1_code":"10.0",
    "gn:asciiname":"Houheiwangzhuang",
    "gn:country_code":"CN",
    "gn:dem":16,
    "gn:feature_class":"P",
    "gn:feature_code":"PPL",
    "gn:name":"Houheiwangzhuang",
    "gn:population":0,
    "gn:timezone":"Asia/Shanghai",
    "iso:country":"CN",
    "name:zho_x_preferred":[
        "\u540e\u9ed1\u738b\u5e84"
    ],
    "wof:name":"Houheiwangzhuang",
    "wof:placetype":"locality"
},
  "geometry": {"coordinates":[118.97018,39.48795],"type":"Point"}
}