{
  "type": "Feature",
  "properties": {
    "gn:admin1_code":"9.0",
    "gn:asciiname":"Zhongyuemiao",
    "gn:country_code":"CN",
    "gn:dem":387,
    "gn:feature_class":"P",
    "gn:feature_code":"PPL",
    "gn:name":"Zhongyuemiao",
    "gn:population":0,
    "gn:timezone":"Asia/Shanghai",
    "iso:country":"CN",
    "name:zho_x_preferred":[
        "\u4e2d\u5cb3\u5e99"
    ],
    "wof:name":"Zhongyuemiao",
    "wof:placetype":"locality"
},
  "geometry": {"coordinates":[113.0663,34.46068],"type":"Point"}
}