{
  "type": "Feature",
  "properties": {
    "gn:admin1_code":"9.0",
    "gn:asciiname":"Zhucheng",
    "gn:country_code":"CN",
    "gn:dem":531,
    "gn:feature_class":"P",
    "gn:feature_code":"PPL",
    "gn:name":"Zhucheng",
    "gn:population":0,
    "gn:timezone":"Asia/Shanghai",
    "iso:country":"CN",
    "name:deu_x_preferred":[
        "Zhucheng"
    ],
    "name:fra_x_preferred":[
        "Zhucheng"
    ],
    "name:ita_x_preferred":[
        "Zhucheng"
    ],
    "name:jpn_x_preferred":[
        "\u8af8\u57ce\u5e02"
    ],
    "name:kat_x_preferred":[
        "\u10ef\u10e3\u10e9\u10d4\u10dc\u10d8"
    ],
    "name:kik_x_preferred":[
        "Zhucheng"
    ],
    "name:kor_x_preferred":[
        "\uc8fc\uccad\uc2dc"
    ],
    "name:nor_x_preferred":[
        "Zhucheng"
    ],
    "name:pol_x_preferred":[
        "Zhucheng"
    ],
    "name:rus_x_preferred":[
        "\u0427\u0436\u0443\u0447\u044d\u043d"
    ],
    "name:spa_x_preferred":[
        "Zhucheng"
    ],
    "name:swe_x_preferred":[
        "Zhucheng"
    ],
    "name:urd_x_preferred":[
        "\u0698\u0648\u0686\u06cc\u0646\u06af"
    ],
    "name:vie_x_preferred":[
        "Ch\u01b0 Th\u00e0nh"
    ],
    "name:war_x_preferred":[
        "Zhucheng"
    ],
    "name:zho_x_preferred":[
        "\u6731\u57ce"
    ],
    "name:zho_x_variant":[
        "\u8bf8\u57ce\u5e02"
    ],
    "wof:name":"Zhucheng",
    "wof:placetype":"locality"
},
  "geometry": {"coordinates":[111.68346,34.7632],"type":"Point"}
}