{
  "type": "Feature",
  "properties": {
    "gn:admin1_code":"14.0",
    "gn:asciiname":"Mayong",
    "gn:country_code":"CN",
    "gn:dem":4671,
    "gn:feature_class":"P",
    "gn:feature_code":"PPL",
    "gn:name":"Mayong",
    "gn:population":0,
    "gn:timezone":"Asia/Urumqi",
    "iso:country":"CN",
    "name:ceb_x_preferred":[
        "Mayong"
    ],
    "name:ind_x_preferred":[
        "Mayong"
    ],
    "name:nld_x_preferred":[
        "Mayong"
    ],
    "name:swe_x_preferred":[
        "Mayong"
    ],
    "name:zho_x_preferred":[
        "\u739b\u62e5"
    ],
    "wof:name":"Mayong",
    "wof:placetype":"locality"
},
  "geometry": {"coordinates":[86.10550000000001,30.8918],"type":"Point"}
}