{
  "type": "Feature",
  "properties": {
    "gn:admin1_code":"18",
    "gn:asciiname":"Ganjiawan",
    "gn:country_code":"CN",
    "gn:dem":1298,
    "gn:feature_class":"P",
    "gn:feature_code":"PPL",
    "gn:name":"Ganjiawan",
    "gn:population":0,
    "gn:timezone":"Asia/Shanghai",
    "iso:country":"CN",
    "name:zho_x_preferred":[
        "\u7518\u5bb6\u6e7e"
    ],
    "wof:name":"Ganjiawan",
    "wof:placetype":"locality"
},
  "geometry": {"coordinates":[107.199,28.8241],"type":"Point"}
}