{
  "type": "Feature",
  "properties": {
    "gn:admin1_code":"15.0",
    "gn:asciiname":"Dashazigou",
    "gn:country_code":"CN",
    "gn:dem":1671,
    "gn:feature_class":"P",
    "gn:feature_code":"PPL",
    "gn:name":"Dashazigou",
    "gn:population":0,
    "gn:timezone":"Asia/Shanghai",
    "iso:country":"CN",
    "name:zho_x_preferred":[
        "\u5927\u6c99\u5b50\u6c9f"
    ],
    "wof:name":"Dashazigou",
    "wof:placetype":"locality"
},
  "geometry": {"coordinates":[102.152,39.1296],"type":"Point"}
}