{
  "type": "Feature",
  "properties": {
    "gn:admin1_code":"12.0",
    "gn:asciiname":"Paixingwan",
    "gn:country_code":"CN",
    "gn:dem":126,
    "gn:feature_class":"P",
    "gn:feature_code":"PPL",
    "gn:name":"Paixingwan",
    "gn:population":0,
    "gn:timezone":"Asia/Shanghai",
    "iso:country":"CN",
    "name:zho_x_preferred":[
        "Paixingwan"
    ],
    "name:zho_x_variant":[
        "\u7c30\u5f62\u6e7e"
    ],
    "wof:name":"Paixingwan",
    "wof:placetype":"locality"
},
  "geometry": {"coordinates":[115.50046,30.79118],"type":"Point"}
}