{
  "type": "Feature",
  "properties": {
    "gn:admin1_code":"1.0",
    "gn:asciiname":"Zhangchongcun",
    "gn:country_code":"CN",
    "gn:dem":200,
    "gn:feature_class":"P",
    "gn:feature_code":"PPL",
    "gn:name":"Zhangchongcun",
    "gn:population":0,
    "gn:timezone":"Asia/Shanghai",
    "iso:country":"CN",
    "name:zho_x_preferred":[
        "\u5f20\u51b2\u6751"
    ],
    "wof:name":"Zhangchongcun",
    "wof:placetype":"locality"
},
  "geometry": {"coordinates":[115.98968000000001,31.50171],"type":"Point"}
}