{
  "type": "Feature",
  "properties": {
    "gn:admin1_code":"32.0",
    "gn:asciiname":"Xinlongchang",
    "gn:country_code":"CN",
    "gn:dem":352,
    "gn:feature_class":"P",
    "gn:feature_code":"PPL",
    "gn:name":"Xinlongchang",
    "gn:population":0,
    "gn:timezone":"Asia/Shanghai",
    "iso:country":"CN",
    "name:zho_x_preferred":[
        "\u65b0\u9f99\u573a"
    ],
    "wof:name":"Xinlongchang",
    "wof:placetype":"locality"
},
  "geometry": {"coordinates":[105.18858,29.75262],"type":"Point"}
}