{
  "type": "Feature",
  "properties": {
    "gn:admin1_code":"26.0",
    "gn:asciiname":"Chegeyuancun",
    "gn:country_code":"CN",
    "gn:dem":1179,
    "gn:feature_class":"P",
    "gn:feature_code":"PPL",
    "gn:name":"Chegeyuancun",
    "gn:population":0,
    "gn:timezone":"Asia/Shanghai",
    "iso:country":"CN",
    "name:zho_x_preferred":[
        "\u8f66\u6b4c\u586c\u6751"
    ],
    "wof:name":"Chegeyuancun",
    "wof:placetype":"locality"
},
  "geometry": {"coordinates":[110.09519,36.78477],"type":"Point"}
}