{
  "type": "Feature",
  "properties": {
    "gn:admin1_code":"3.0",
    "gn:asciiname":"Baofeng",
    "gn:country_code":"CN",
    "gn:dem":124,
    "gn:feature_class":"P",
    "gn:feature_code":"PPLA4",
    "gn:name":"Baofeng",
    "gn:population":0,
    "gn:timezone":"Asia/Shanghai",
    "iso:country":"CN",
    "name:und_x_variant":[
        "\u5b9d\u5cf0",
        "Baofeng Zhen",
        "\u5b9d\u5cf0\u9547"
    ],
    "wof:name":"Baofeng",
    "wof:placetype":"locality"
},
  "geometry": {"coordinates":[115.40235,29.00687000000001],"type":"Point"}
}