{
  "type": "Feature",
  "properties": {
    "gn:admin1_code":"4.0",
    "gn:asciiname":"Xiaoyaozhuang",
    "gn:country_code":"CN",
    "gn:dem":10,
    "gn:feature_class":"P",
    "gn:feature_code":"PPL",
    "gn:name":"Xiaoyaozhuang",
    "gn:population":0,
    "gn:timezone":"Asia/Shanghai",
    "iso:country":"CN",
    "name:zho_x_preferred":[
        "\u5c0f\u8170\u5e84"
    ],
    "wof:name":"Xiaoyaozhuang",
    "wof:placetype":"locality"
},
  "geometry": {"coordinates":[118.89264,32.25984],"type":"Point"}
}