{
  "type": "Feature",
  "properties": {
    "gn:admin1_code":"19.0",
    "gn:asciiname":"Xiaocaoyu",
    "gn:country_code":"CN",
    "gn:dem":137,
    "gn:feature_class":"P",
    "gn:feature_code":"PPL",
    "gn:name":"Xiaocaoyu",
    "gn:population":0,
    "gn:timezone":"Asia/Shanghai",
    "iso:country":"CN",
    "name:und_x_variant":[
        "\u5c0f\u69fd\u5cea"
    ],
    "wof:name":"Xiaocaoyu",
    "wof:placetype":"locality"
},
  "geometry": {"coordinates":[122.49773999999999,40.18336],"type":"Point"}
}