{
  "type": "Feature",
  "properties": {
    "gn:admin1_code":"7.0",
    "gn:asciiname":"Laishangdui",
    "gn:country_code":"CN",
    "gn:dem":526,
    "gn:feature_class":"P",
    "gn:feature_code":"PPL",
    "gn:name":"Laishangdui",
    "gn:population":0,
    "gn:timezone":"Asia/Shanghai",
    "iso:country":"CN",
    "name:zho_x_preferred":[
        "\u8d56\u4e0a\u961f"
    ],
    "wof:name":"Laishangdui",
    "wof:placetype":"locality"
},
  "geometry": {"coordinates":[116.60807,25.9027],"type":"Point"}
}