{
  "type": "Feature",
  "properties": {
    "gn:admin1_code":"32.0",
    "gn:asciiname":"Fangshan",
    "gn:country_code":"CN",
    "gn:dem":303,
    "gn:feature_class":"P",
    "gn:feature_code":"PPL",
    "gn:name":"Fangshan",
    "gn:population":0,
    "gn:timezone":"Asia/Shanghai",
    "iso:country":"CN",
    "name:zho_x_preferred":[
        "\u65b9\u5c71"
    ],
    "wof:name":"Fangshan",
    "wof:placetype":"locality"
},
  "geometry": {"coordinates":[104.866,28.8844],"type":"Point"}
}