{
  "type": "Feature",
  "properties": {
    "gn:admin1_code":"3",
    "gn:asciiname":"Donglinshan",
    "gn:country_code":"CN",
    "gn:dem":492,
    "gn:feature_class":"P",
    "gn:feature_code":"PPL",
    "gn:name":"Donglinshan",
    "gn:population":0,
    "gn:timezone":"Asia/Shanghai",
    "iso:country":"CN",
    "name:zho_x_preferred":[
        "\u4e1c\u6797\u5c71"
    ],
    "wof:name":"Donglinshan",
    "wof:placetype":"locality"
},
  "geometry": {"coordinates":[114.333,25.663],"type":"Point"}
}