{
  "type": "Feature",
  "properties": {
    "gn:admin1_code":"10",
    "gn:asciiname":"Xiaosandaochuan",
    "gn:country_code":"CN",
    "gn:dem":1281,
    "gn:feature_class":"P",
    "gn:feature_code":"PPL",
    "gn:name":"Xiaosandaochuan",
    "gn:population":0,
    "gn:timezone":"Asia/Shanghai",
    "iso:country":"CN",
    "name:zho_x_preferred":[
        "\u5c0f\u4e09\u9053\u5ddd"
    ],
    "wof:name":"Xiaosandaochuan",
    "wof:placetype":"locality"
},
  "geometry": {"coordinates":[115.99563000000001,41.24379],"type":"Point"}
}