{
  "type": "Feature",
  "properties": {
    "gn:admin1_code":"21.0",
    "gn:asciiname":"Yanjiagou",
    "gn:country_code":"CN",
    "gn:dem":1467,
    "gn:feature_class":"P",
    "gn:feature_code":"PPL",
    "gn:name":"Yanjiagou",
    "gn:population":0,
    "gn:timezone":"Asia/Shanghai",
    "iso:country":"CN",
    "name:und_x_variant":[
        "\u5ef6\u5bb6\u6c9f"
    ],
    "name:zho_x_preferred":[
        "\u5ef6\u5bb6\u6c9f"
    ],
    "wof:name":"Yanjiagou",
    "wof:placetype":"locality"
},
  "geometry": {"coordinates":[106.14282,36.5226],"type":"Point"}
}