{
  "type": "Feature",
  "properties": {
    "gn:admin1_code":"11.0",
    "gn:asciiname":"Matuli",
    "gn:country_code":"CN",
    "gn:dem":200,
    "gn:feature_class":"P",
    "gn:feature_code":"PPL",
    "gn:name":"Matuli",
    "gn:population":0,
    "gn:timezone":"Asia/Shanghai",
    "iso:country":"CN",
    "name:zho_x_preferred":[
        "\u9ebb\u571f\u91cc"
    ],
    "wof:name":"Matuli",
    "wof:placetype":"locality"
},
  "geometry": {"coordinates":[113.58271000000001,26.95883],"type":"Point"}
}