{
  "type": "Feature",
  "properties": {
    "gn:admin1_code":"32.0",
    "gn:asciiname":"Sanbaicun",
    "gn:country_code":"CN",
    "gn:dem":327,
    "gn:feature_class":"P",
    "gn:feature_code":"PPL",
    "gn:name":"Sanbaicun",
    "gn:population":0,
    "gn:timezone":"Asia/Shanghai",
    "iso:country":"CN",
    "name:zho_x_preferred":[
        "\u4e09\u767e\u6751"
    ],
    "wof:name":"Sanbaicun",
    "wof:placetype":"locality"
},
  "geometry": {"coordinates":[105.574,29.9089],"type":"Point"}
}