{
  "type": "Feature",
  "properties": {
    "iso:country":"CN",
    "name:eng_x_preferred":[
        "Jinjiang"
    ],
    "name:zho_x_preferred":[
        "\u664b\u6c5f\u5e02"
    ],
    "qs:name":"\u664b\u6c5f\u5e02",
    "qs:name_adm0":"\u4e2d\u570b",
    "qs:name_adm1":"\u798f\u5efa\u7701",
    "qs:photos":7,
    "qs:photos_1k":1,
    "qs:photos_9k":1,
    "qs:photos_9r":4,
    "qs:photos_all":195,
    "qs:photos_sr":1,
    "qs:placetype":"LocalAdmin",
    "qs:pop_sr":"0",
    "wof:name":"Jinjiang",
    "wof:placetype":"localadmin"
},
  "geometry": {"coordinates":[118.580224,24.803876],"type":"Point"}
}