{
  "type": "Feature",
  "properties": {
    "gn:admin1_code":"15",
    "gn:asciiname":"Lianhuacheng",
    "gn:cc2":"CN",
    "gn:country_code":"CN",
    "gn:dem":1781,
    "gn:feature_class":"P",
    "gn:feature_code":"PPL",
    "gn:name":"Lianhuacheng",
    "gn:population":0,
    "gn:timezone":"Asia/Shanghai",
    "iso:country":"CN",
    "name:und_x_variant":[
        "Lyan\u2019khuachen",
        "Lien-hua-ch\u2019eng",
        "Lien-hua-tsch\u00f6ng",
        "Lien-hua-chen",
        "Lianhuacheng"
    ],
    "wof:name":"Lianhuacheng",
    "wof:placetype":"locality"
},
  "geometry": {"coordinates":[105.76667,35.03333],"type":"Point"}
}