{
  "type": "Feature",
  "properties": {
    "gn:admin1_code":"29",
    "gn:asciiname":"Xiaogezhang",
    "gn:country_code":"CN",
    "gn:dem":1708,
    "gn:feature_class":"P",
    "gn:feature_code":"PPL",
    "gn:name":"Xiaogezhang",
    "gn:population":0,
    "gn:timezone":"Asia/Shanghai",
    "iso:country":"CN",
    "name:zho_x_preferred":[
        "\u5c0f\u6208\u4e08"
    ],
    "wof:name":"Xiaogezhang",
    "wof:placetype":"locality"
},
  "geometry": {"coordinates":[103.28100000000001,24.6786],"type":"Point"}
}