{
  "type": "Feature",
  "properties": {
    "gn:admin1_code":"5.0",
    "gn:asciiname":"Tazigou Linchang",
    "gn:country_code":"CN",
    "gn:dem":673,
    "gn:feature_class":"P",
    "gn:feature_code":"PPLF",
    "gn:name":"Tazigou Linchang",
    "gn:population":0,
    "gn:timezone":"Asia/Shanghai",
    "iso:country":"CN",
    "name:und_x_variant":[
        "\u5854\u5b50\u6c9f\u6797\u573a"
    ],
    "wof:name":"Tazigou Linchang",
    "wof:placetype":"locality"
},
  "geometry": {"coordinates":[130.12706,43.43885],"type":"Point"}
}