{
  "type": "Feature",
  "properties": {
    "gn:admin1_code":"25",
    "gn:asciiname":"Sishe Guanzhuang",
    "gn:country_code":"CN",
    "gn:dem":196,
    "gn:feature_class":"P",
    "gn:feature_code":"PPL",
    "gn:name":"Sishe Guanzhuang",
    "gn:population":0,
    "gn:timezone":"Asia/Shanghai",
    "iso:country":"CN",
    "name:zho_x_preferred":[
        "\u56db\u793e\u5b98\u5e84"
    ],
    "wof:name":"Sishe Guanzhuang",
    "wof:placetype":"locality"
},
  "geometry": {"coordinates":[118.78400000000001,35.9543],"type":"Point"}
}