{
  "type": "Feature",
  "properties": {
    "gn:admin1_code":"19.0",
    "gn:asciiname":"Xigushanzi",
    "gn:country_code":"CN",
    "gn:dem":133,
    "gn:feature_class":"P",
    "gn:feature_code":"PPL",
    "gn:name":"Xigushanzi",
    "gn:population":0,
    "gn:timezone":"Asia/Shanghai",
    "iso:country":"CN",
    "name:zho_x_preferred":[
        "\u897f\u5b64\u5c71\u5b50"
    ],
    "wof:name":"Xigushanzi",
    "wof:placetype":"locality"
},
  "geometry": {"coordinates":[120.51228,40.89847],"type":"Point"}
}