{
  "type": "Feature",
  "properties": {
    "gn:admin1_code":"3.0",
    "gn:asciiname":"Dianshangcun",
    "gn:country_code":"CN",
    "gn:dem":67,
    "gn:feature_class":"P",
    "gn:feature_code":"PPL",
    "gn:name":"Dianshangcun",
    "gn:population":0,
    "gn:timezone":"Asia/Shanghai",
    "iso:country":"CN",
    "name:zho_x_preferred":[
        "\u5e97\u4e0a\u6751"
    ],
    "wof:name":"Dianshangcun",
    "wof:placetype":"locality"
},
  "geometry": {"coordinates":[117.334,28.6789],"type":"Point"}
}