{
  "type": "Feature",
  "properties": {
    "gn:admin1_code":"29.0",
    "gn:asciiname":"Huangmeimao",
    "gn:country_code":"CN",
    "gn:dem":1420,
    "gn:feature_class":"P",
    "gn:feature_code":"PPL",
    "gn:name":"Huangmeimao",
    "gn:population":0,
    "gn:timezone":"Asia/Shanghai",
    "iso:country":"CN",
    "name:zho_x_preferred":[
        "\u9ec4\u7709\u6bdb"
    ],
    "wof:name":"Huangmeimao",
    "wof:placetype":"locality"
},
  "geometry": {"coordinates":[100.39100000000001,26.6964],"type":"Point"}
}