{
  "type": "Feature",
  "properties": {
    "gn:admin1_code":"15.0",
    "gn:asciiname":"Gongjiawan",
    "gn:country_code":"CN",
    "gn:dem":1020,
    "gn:feature_class":"P",
    "gn:feature_code":"PPL",
    "gn:name":"Gongjiawan",
    "gn:population":0,
    "gn:timezone":"Asia/Shanghai",
    "iso:country":"CN",
    "name:und_x_variant":[
        "\u516c\u5bb6\u6e7e"
    ],
    "wof:name":"Gongjiawan",
    "wof:placetype":"locality"
},
  "geometry": {"coordinates":[105.69978999999999,33.16491],"type":"Point"}
}