{
  "type": "Feature",
  "properties": {
    "gn:admin1_code":"32.0",
    "gn:asciiname":"Ebarong Yicun",
    "gn:country_code":"CN",
    "gn:dem":3272,
    "gn:feature_class":"P",
    "gn:feature_code":"PPL",
    "gn:name":"Ebarong Yicun",
    "gn:population":0,
    "gn:timezone":"Asia/Shanghai",
    "iso:country":"CN",
    "name:zho_x_preferred":[
        "\u4fc4\u5df4\u7ed2\u4e00\u6751"
    ],
    "wof:name":"Ebarong Yicun",
    "wof:placetype":"locality"
},
  "geometry": {"coordinates":[101.44499999999999,29.6847],"type":"Point"}
}