{
  "type": "Feature",
  "properties": {
    "gn:admin1_code":"30",
    "gn:asciiname":"Liangzikeng",
    "gn:country_code":"CN",
    "gn:dem":80,
    "gn:feature_class":"P",
    "gn:feature_code":"PPL",
    "gn:name":"Liangzikeng",
    "gn:population":0,
    "gn:timezone":"Asia/Urumqi",
    "iso:country":"CN",
    "name:zho_x_preferred":[
        "\u826f\u5b50\u5751"
    ],
    "wof:name":"Liangzikeng",
    "wof:placetype":"locality"
},
  "geometry": {"coordinates":[110.6352,21.97735],"type":"Point"}
}