{
  "type": "Feature",
  "properties": {
    "gn:admin1_code":"20",
    "gn:asciiname":"Shih-ta-fen",
    "gn:country_code":"CN",
    "gn:dem":806,
    "gn:feature_class":"P",
    "gn:feature_code":"PPL",
    "gn:name":"Shih-ta-fen",
    "gn:population":0,
    "gn:timezone":"Asia/Shanghai",
    "iso:country":"CN",
    "wof:name":"Shih-ta-fen",
    "wof:placetype":"locality"
},
  "geometry": {"coordinates":[118.79722,42.71528],"type":"Point"}
}