{
  "type": "Feature",
  "properties": {
    "gn:admin1_code":"18.0",
    "gn:asciiname":"Yin'ao",
    "gn:country_code":"CN",
    "gn:dem":972,
    "gn:feature_class":"P",
    "gn:feature_code":"PPL",
    "gn:name":"Yin\u2019ao",
    "gn:population":0,
    "gn:timezone":"Asia/Shanghai",
    "iso:country":"CN",
    "name:und_x_variant":[
        "Yin\u2019ao"
    ],
    "name:zho_x_preferred":[
        "\u94f6\u5773"
    ],
    "wof:name":"Yin'ao",
    "wof:placetype":"locality"
},
  "geometry": {"coordinates":[108.56999999999999,27.6852],"type":"Point"}
}