{
  "type": "Feature",
  "properties": {
    "gn:admin1_code":"18",
    "gn:asciiname":"Dalang",
    "gn:country_code":"CN",
    "gn:dem":470,
    "gn:feature_class":"P",
    "gn:feature_code":"PPL",
    "gn:name":"Dalang",
    "gn:population":0,
    "gn:timezone":"Asia/Shanghai",
    "iso:country":"CN",
    "name:ceb_x_preferred":[
        "Dalang"
    ],
    "name:deu_x_preferred":[
        "Dalang"
    ],
    "name:nld_x_preferred":[
        "Dalang"
    ],
    "name:sco_x_preferred":[
        "Dalang"
    ],
    "name:swe_x_preferred":[
        "Dalang"
    ],
    "name:zho_x_preferred":[
        "\u6253\u90ce"
    ],
    "wof:name":"Dalang",
    "wof:placetype":"locality"
},
  "geometry": {"coordinates":[106.61799999999999,25.3657],"type":"Point"}
}