{
  "type": "Feature",
  "properties": {
    "gn:admin1_code":"1.0",
    "gn:asciiname":"Jiufengcun",
    "gn:country_code":"CN",
    "gn:dem":8,
    "gn:feature_class":"P",
    "gn:feature_code":"PPL",
    "gn:name":"Jiufengcun",
    "gn:population":0,
    "gn:timezone":"Asia/Shanghai",
    "iso:country":"CN",
    "name:zho_x_preferred":[
        "\u4e5d\u5cf0\u6751"
    ],
    "wof:name":"Jiufengcun",
    "wof:placetype":"locality"
},
  "geometry": {"coordinates":[117.57550000000001,31.41089],"type":"Point"}
}