{
  "type": "Feature",
  "properties": {
    "gn:admin1_code":"3.0",
    "gn:asciiname":"Keli",
    "gn:country_code":"CN",
    "gn:dem":71,
    "gn:feature_class":"P",
    "gn:feature_code":"PPL",
    "gn:name":"Keli",
    "gn:population":0,
    "gn:timezone":"Asia/Shanghai",
    "iso:country":"CN",
    "name:und_x_variant":[
        "\u79d1\u91cc"
    ],
    "wof:name":"Keli",
    "wof:placetype":"locality"
},
  "geometry": {"coordinates":[116.51394000000001,28.27337],"type":"Point"}
}