{
  "type": "Feature",
  "properties": {
    "gn:admin1_code":"26.0",
    "gn:asciiname":"Guxiancun",
    "gn:country_code":"CN",
    "gn:dem":700,
    "gn:feature_class":"P",
    "gn:feature_code":"PPL",
    "gn:name":"Guxiancun",
    "gn:population":0,
    "gn:timezone":"Asia/Shanghai",
    "iso:country":"CN",
    "name:zho_x_preferred":[
        "\u987e\u8d24\u6751"
    ],
    "wof:name":"Guxiancun",
    "wof:placetype":"locality"
},
  "geometry": {"coordinates":[110.16929,35.21656],"type":"Point"}
}