{
  "type": "Feature",
  "properties": {
    "gn:admin1_code":"32.0",
    "gn:asciiname":"Maniuwan",
    "gn:country_code":"CN",
    "gn:dem":800,
    "gn:feature_class":"P",
    "gn:feature_code":"PPL",
    "gn:name":"Maniuwan",
    "gn:population":0,
    "gn:timezone":"Asia/Shanghai",
    "iso:country":"CN",
    "name:zho_x_preferred":[
        "\u9a6c\u725b\u6e7e"
    ],
    "wof:name":"Maniuwan",
    "wof:placetype":"locality"
},
  "geometry": {"coordinates":[103.904,28.6555],"type":"Point"}
}