{
  "type": "Feature",
  "properties": {
    "gn:admin1_code":"18",
    "gn:asciiname":"Baishuilong",
    "gn:country_code":"CN",
    "gn:dem":1034,
    "gn:feature_class":"P",
    "gn:feature_code":"PPL",
    "gn:name":"Baishuilong",
    "gn:population":0,
    "gn:timezone":"Asia/Shanghai",
    "iso:country":"CN",
    "name:zho_x_preferred":[
        "\u767d\u6c34\u9647"
    ],
    "wof:name":"Baishuilong",
    "wof:placetype":"locality"
},
  "geometry": {"coordinates":[106.934,26.7316],"type":"Point"}
}