{
  "type": "Feature",
  "properties": {
    "gn:admin1_code":"33.0",
    "gn:asciiname":"Aijiaping",
    "gn:country_code":"CN",
    "gn:dem":653,
    "gn:feature_class":"P",
    "gn:feature_code":"PPL",
    "gn:name":"Aijiaping",
    "gn:population":0,
    "gn:timezone":"Asia/Shanghai",
    "iso:country":"CN",
    "name:zho_x_preferred":[
        "\u827e\u5bb6\u576a"
    ],
    "wof:name":"Aijiaping",
    "wof:placetype":"locality"
},
  "geometry": {"coordinates":[108.06462000000001,29.29277],"type":"Point"}
}