{
  "type": "Feature",
  "properties": {
    "gn:admin1_code":"4.0",
    "gn:asciiname":"Jia'nongdai",
    "gn:country_code":"CN",
    "gn:dem":7,
    "gn:feature_class":"P",
    "gn:feature_code":"PPL",
    "gn:name":"Jia\u2019nongdai",
    "gn:population":0,
    "gn:timezone":"Asia/Shanghai",
    "iso:country":"CN",
    "name:und_x_variant":[
        "Jia\u2019nongdai"
    ],
    "name:zho_x_preferred":[
        "\u5939\u5f04\u5788"
    ],
    "wof:name":"Jia'nongdai",
    "wof:placetype":"locality"
},
  "geometry": {"coordinates":[120.09183,32.05136],"type":"Point"}
}