{
  "type": "Feature",
  "properties": {
    "gn:admin1_code":"32.0",
    "gn:asciiname":"Yangjianian",
    "gn:country_code":"CN",
    "gn:dem":821,
    "gn:feature_class":"P",
    "gn:feature_code":"PPL",
    "gn:name":"Yangjianian",
    "gn:population":0,
    "gn:timezone":"Asia/Shanghai",
    "iso:country":"CN",
    "name:zho_x_preferred":[
        "\u6768\u5bb6\u78be"
    ],
    "wof:name":"Yangjianian",
    "wof:placetype":"locality"
},
  "geometry": {"coordinates":[103.85414,31.13943],"type":"Point"}
}