{
  "type": "Feature",
  "properties": {
    "gn:admin1_code":"26.0",
    "gn:asciiname":"Liangyayaocun",
    "gn:country_code":"CN",
    "gn:dem":965,
    "gn:feature_class":"P",
    "gn:feature_code":"PPL",
    "gn:name":"Liangyayaocun",
    "gn:population":0,
    "gn:timezone":"Asia/Shanghai",
    "iso:country":"CN",
    "name:zho_x_preferred":[
        "\u6881\u5d16\u7a91\u6751"
    ],
    "wof:name":"Liangyayaocun",
    "wof:placetype":"locality"
},
  "geometry": {"coordinates":[110.1134,37.69541],"type":"Point"}
}