{
  "type": "Feature",
  "properties": {
    "gn:admin1_code":"4.0",
    "gn:asciiname":"Biandanjie",
    "gn:country_code":"CN",
    "gn:dem":7,
    "gn:feature_class":"P",
    "gn:feature_code":"PPL",
    "gn:name":"Biandanjie",
    "gn:population":0,
    "gn:timezone":"Asia/Shanghai",
    "iso:country":"CN",
    "name:zho_x_preferred":[
        "\u6241\u62c5\u8857"
    ],
    "wof:name":"Biandanjie",
    "wof:placetype":"locality"
},
  "geometry": {"coordinates":[119.78051000000001,32.23191],"type":"Point"}
}