{
  "type": "Feature",
  "properties": {
    "gn:admin1_code":"18",
    "gn:asciiname":"Maomianping",
    "gn:country_code":"CN",
    "gn:dem":1416,
    "gn:feature_class":"P",
    "gn:feature_code":"PPL",
    "gn:name":"Maomianping",
    "gn:population":0,
    "gn:timezone":"Asia/Shanghai",
    "iso:country":"CN",
    "name:zho_x_preferred":[
        "\u8305\u9762\u576a"
    ],
    "wof:name":"Maomianping",
    "wof:placetype":"locality"
},
  "geometry": {"coordinates":[107.634,28.6135],"type":"Point"}
}