{
  "type": "Feature",
  "properties": {
    "gn:admin1_code":"16.0",
    "gn:asciiname":"Luxie",
    "gn:country_code":"CN",
    "gn:dem":181,
    "gn:feature_class":"P",
    "gn:feature_code":"PPL",
    "gn:name":"Luxie",
    "gn:population":0,
    "gn:timezone":"Asia/Shanghai",
    "iso:country":"CN",
    "name:zho_x_preferred":[
        "\u6e0c\u8c22"
    ],
    "wof:name":"Luxie",
    "wof:placetype":"locality"
},
  "geometry": {"coordinates":[108.541,23.1978],"type":"Point"}
}