{
  "type": "Feature",
  "properties": {
    "gn:admin1_code":"8.0",
    "gn:asciiname":"Pubucun",
    "gn:country_code":"CN",
    "gn:dem":335,
    "gn:feature_class":"P",
    "gn:feature_code":"PPL",
    "gn:name":"Pubucun",
    "gn:population":0,
    "gn:timezone":"Asia/Shanghai",
    "iso:country":"CN",
    "name:zho_x_preferred":[
        "\u7011\u5e03\u6751"
    ],
    "wof:name":"Pubucun",
    "wof:placetype":"locality"
},
  "geometry": {"coordinates":[128.95258000000001,44.05827],"type":"Point"}
}