{
  "type": "Feature",
  "properties": {
    "gn:admin1_code":"33.0",
    "gn:asciiname":"Mingzhushan",
    "gn:country_code":"CN",
    "gn:dem":284,
    "gn:feature_class":"P",
    "gn:feature_code":"PPL",
    "gn:name":"Mingzhushan",
    "gn:population":0,
    "gn:timezone":"Asia/Shanghai",
    "iso:country":"CN",
    "name:zho_x_preferred":[
        "\u660e\u73e0\u5c71"
    ],
    "wof:name":"Mingzhushan",
    "wof:placetype":"locality"
},
  "geometry": {"coordinates":[106.384,29.6238],"type":"Point"}
}