{
  "type": "Feature",
  "properties": {
    "gn:admin1_code":"8.0",
    "gn:asciiname":"Zhongzhicun",
    "gn:country_code":"CN",
    "gn:dem":215,
    "gn:feature_class":"P",
    "gn:feature_code":"PPL",
    "gn:name":"Zhongzhicun",
    "gn:population":0,
    "gn:timezone":"Asia/Shanghai",
    "iso:country":"CN",
    "name:zho_x_preferred":[
        "\u4e2d\u81f4\u6751"
    ],
    "wof:name":"Zhongzhicun",
    "wof:placetype":"locality"
},
  "geometry": {"coordinates":[125.62875,47.36531],"type":"Point"}
}