{
  "type": "Feature",
  "properties": {
    "gn:admin1_code":"16.0",
    "gn:asciiname":"Kuguatang",
    "gn:country_code":"CN",
    "gn:dem":1529,
    "gn:feature_class":"P",
    "gn:feature_code":"PPL",
    "gn:name":"Kuguatang",
    "gn:population":0,
    "gn:timezone":"Asia/Shanghai",
    "iso:country":"CN",
    "name:zho_x_preferred":[
        "\u82e6\u74dc\u5858"
    ],
    "wof:name":"Kuguatang",
    "wof:placetype":"locality"
},
  "geometry": {"coordinates":[105.253,24.5213],"type":"Point"}
}