{
  "type": "Feature",
  "properties": {
    "gn:admin1_code":"8.0",
    "gn:asciiname":"Yikeshucun",
    "gn:country_code":"CN",
    "gn:dem":133,
    "gn:feature_class":"P",
    "gn:feature_code":"PPL",
    "gn:name":"Yikeshucun",
    "gn:population":0,
    "gn:timezone":"Asia/Shanghai",
    "iso:country":"CN",
    "name:zho_x_preferred":[
        "\u4e00\u68f5\u6811\u6751"
    ],
    "wof:name":"Yikeshucun",
    "wof:placetype":"locality"
},
  "geometry": {"coordinates":[124.10044000000001,45.92811],"type":"Point"}
}