{
  "type": "Feature",
  "properties": {
    "gn:admin1_code":"8.0",
    "gn:asciiname":"Beidatongcun",
    "gn:country_code":"CN",
    "gn:dem":60,
    "gn:feature_class":"P",
    "gn:feature_code":"PPL",
    "gn:name":"Beidatongcun",
    "gn:population":0,
    "gn:timezone":"Asia/Shanghai",
    "iso:country":"CN",
    "name:zho_x_preferred":[
        "\u5317\u5927\u901a\u6751"
    ],
    "wof:name":"Beidatongcun",
    "wof:placetype":"locality"
},
  "geometry": {"coordinates":[133.37799999999999,45.7968],"type":"Point"}
}