{
  "type": "Feature",
  "properties": {
    "gn:admin1_code":"3.0",
    "gn:asciiname":"Xianshanling",
    "gn:country_code":"CN",
    "gn:dem":605,
    "gn:feature_class":"P",
    "gn:feature_code":"PPL",
    "gn:name":"Xianshanling",
    "gn:population":0,
    "gn:timezone":"Asia/Shanghai",
    "iso:country":"CN",
    "name:zho_x_preferred":[
        "\u4ed9\u5c71\u5cad"
    ],
    "wof:name":"Xianshanling",
    "wof:placetype":"locality"
},
  "geometry": {"coordinates":[117.8167,27.94415],"type":"Point"}
}