{
  "type": "Feature",
  "properties": {
    "gn:admin1_code":"24.0",
    "gn:asciiname":"Zeshan",
    "gn:cc2":"CN",
    "gn:country_code":"CN",
    "gn:dem":1334,
    "gn:feature_class":"P",
    "gn:feature_code":"PPL",
    "gn:name":"Zeshan",
    "gn:population":0,
    "gn:timezone":"Asia/Shanghai",
    "iso:country":"CN",
    "name:und_x_variant":[
        "Tse-shan-ts\u2019un",
        "Tse-shan",
        "Zeshan"
    ],
    "wof:name":"Zeshan",
    "wof:placetype":"locality"
},
  "geometry": {"coordinates":[111.93583,38.24194],"type":"Point"}
}