{
  "type": "Feature",
  "properties": {
    "gn:admin1_code":"4.0",
    "gn:asciiname":"Gonggou",
    "gn:country_code":"CN",
    "gn:dem":1,
    "gn:feature_class":"P",
    "gn:feature_code":"PPL",
    "gn:name":"Gonggou",
    "gn:population":0,
    "gn:timezone":"Asia/Shanghai",
    "iso:country":"CN",
    "name:zho_x_preferred":[
        "Gonggou"
    ],
    "name:zho_x_variant":[
        "\u6c5e\u6c9f"
    ],
    "wof:name":"Gonggou",
    "wof:placetype":"locality"
},
  "geometry": {"coordinates":[119.96509,33.28713],"type":"Point"}
}