{
  "type": "Feature",
  "properties": {
    "gn:admin1_code":"24",
    "gn:asciiname":"Damaijiao",
    "gn:country_code":"CN",
    "gn:dem":1089,
    "gn:feature_class":"P",
    "gn:feature_code":"PPL",
    "gn:name":"Damaijiao",
    "gn:population":0,
    "gn:timezone":"Asia/Shanghai",
    "iso:country":"CN",
    "name:und_x_variant":[
        "Ta-mai-chiao",
        "Ta-mai-chiao-chen",
        "Damaijiao"
    ],
    "name:zho_x_preferred":[
        "\u5927\u9ea6\u90ca"
    ],
    "wof:name":"Damaijiao",
    "wof:placetype":"locality"
},
  "geometry": {"coordinates":[111.4241,37.02144000000001],"type":"Point"}
}