{
  "type": "Feature",
  "properties": {
    "gn:admin1_code":"30.0",
    "gn:asciiname":"Lingwei",
    "gn:country_code":"CN",
    "gn:dem":65,
    "gn:feature_class":"P",
    "gn:feature_code":"PPL",
    "gn:name":"Lingwei",
    "gn:population":0,
    "gn:timezone":"Asia/Shanghai",
    "iso:country":"CN",
    "name:zho_x_preferred":[
        "\u7075\u5c3e"
    ],
    "wof:name":"Lingwei",
    "wof:placetype":"locality"
},
  "geometry": {"coordinates":[111.74723,23.79943],"type":"Point"}
}