{
  "type": "Feature",
  "properties": {
    "gn:admin1_code":"14.0",
    "gn:asciiname":"Ganggang",
    "gn:country_code":"CN",
    "gn:dem":4394,
    "gn:feature_class":"P",
    "gn:feature_code":"PPL",
    "gn:name":"Ganggang",
    "gn:population":0,
    "gn:timezone":"Asia/Urumqi",
    "iso:country":"CN",
    "name:zho_x_preferred":[
        "\u5188\u5188"
    ],
    "wof:name":"Ganggang",
    "wof:placetype":"locality"
},
  "geometry": {"coordinates":[88.3292,28.2716],"type":"Point"}
}