{
  "type": "Feature",
  "properties": {
    "gn:admin1_code":"15.0",
    "gn:asciiname":"Jumicha",
    "gn:country_code":"CN",
    "gn:dem":1995,
    "gn:feature_class":"P",
    "gn:feature_code":"PPL",
    "gn:name":"Jumicha",
    "gn:population":0,
    "gn:timezone":"Asia/Shanghai",
    "iso:country":"CN",
    "name:zho_x_preferred":[
        "\u805a\u7c73\u5c94"
    ],
    "wof:name":"Jumicha",
    "wof:placetype":"locality"
},
  "geometry": {"coordinates":[104.223,35.98699999999999],"type":"Point"}
}