{
  "type": "Feature",
  "properties": {
    "gn:admin1_code":"12.0",
    "gn:asciiname":"Qiaojiachong",
    "gn:country_code":"CN",
    "gn:dem":485,
    "gn:feature_class":"P",
    "gn:feature_code":"PPL",
    "gn:name":"Qiaojiachong",
    "gn:population":0,
    "gn:timezone":"Asia/Shanghai",
    "iso:country":"CN",
    "name:zho_x_preferred":[
        "Qiaojiachong"
    ],
    "name:zho_x_variant":[
        "\u4e54\u5bb6\u51b2"
    ],
    "wof:name":"Qiaojiachong",
    "wof:placetype":"locality"
},
  "geometry": {"coordinates":[111.29130000000001,30.86187],"type":"Point"}
}