{
  "type": "Feature",
  "properties": {
    "gn:admin1_code":"32",
    "gn:asciiname":"Changle",
    "gn:country_code":"CN",
    "gn:dem":500,
    "gn:feature_class":"P",
    "gn:feature_code":"PPL",
    "gn:name":"Changle",
    "gn:population":0,
    "gn:timezone":"Asia/Shanghai",
    "iso:country":"CN",
    "wof:name":"Changle",
    "wof:placetype":"locality"
},
  "geometry": {"coordinates":[106.63333,30.78333],"type":"Point"}
}