{
  "type": "Feature",
  "properties": {
    "gn:admin1_code":"30",
    "gn:asciiname":"Xianshuitang",
    "gn:country_code":"CN",
    "gn:dem":54,
    "gn:feature_class":"P",
    "gn:feature_code":"PPL",
    "gn:name":"Xianshuitang",
    "gn:population":0,
    "gn:timezone":"Asia/Shanghai",
    "iso:country":"CN",
    "name:zho_x_preferred":[
        "\u9c9c\u6c34\u5858"
    ],
    "wof:name":"Xianshuitang",
    "wof:placetype":"locality"
},
  "geometry": {"coordinates":[114.82138999999999,22.89186],"type":"Point"}
}