{
  "type": "Feature",
  "properties": {
    "gn:admin1_code":"19.0",
    "gn:asciiname":"Xishiqihu",
    "gn:country_code":"CN",
    "gn:dem":13,
    "gn:feature_class":"P",
    "gn:feature_code":"PPL",
    "gn:name":"Xishiqihu",
    "gn:population":0,
    "gn:timezone":"Asia/Shanghai",
    "iso:country":"CN",
    "name:und_x_variant":[
        "\u897f\u5341\u4e03\u6237"
    ],
    "name:zho_x_preferred":[
        "\u897f\u5341\u4e03\u6237"
    ],
    "wof:name":"Xishiqihu",
    "wof:placetype":"locality"
},
  "geometry": {"coordinates":[122.28352,41.58834],"type":"Point"}
}