{
  "type": "Feature",
  "properties": {
    "gn:admin1_code":"32.0",
    "gn:asciiname":"Miaogang",
    "gn:country_code":"CN",
    "gn:dem":1126,
    "gn:feature_class":"P",
    "gn:feature_code":"PPL",
    "gn:name":"Miaogang",
    "gn:population":0,
    "gn:timezone":"Asia/Shanghai",
    "iso:country":"CN",
    "name:zho_x_preferred":[
        "\u5e99\u5c97"
    ],
    "wof:name":"Miaogang",
    "wof:placetype":"locality"
},
  "geometry": {"coordinates":[103.77500000000001,28.7214],"type":"Point"}
}