{
  "type": "Feature",
  "properties": {
    "gn:admin1_code":"4.0",
    "gn:asciiname":"Louzicun",
    "gn:country_code":"CN",
    "gn:dem":1,
    "gn:feature_class":"P",
    "gn:feature_code":"PPL",
    "gn:name":"Louzicun",
    "gn:population":0,
    "gn:timezone":"Asia/Shanghai",
    "iso:country":"CN",
    "name:zho_x_preferred":[
        "\u5a04\u5b50\u6751"
    ],
    "wof:name":"Louzicun",
    "wof:placetype":"locality"
},
  "geometry": {"coordinates":[120.29633,33.03448],"type":"Point"}
}