{
  "type": "Feature",
  "properties": {
    "gn:admin1_code":"13",
    "gn:asciiname":"Youkakeya Yilake",
    "gn:country_code":"CN",
    "gn:dem":1253,
    "gn:feature_class":"P",
    "gn:feature_code":"PPL",
    "gn:name":"Youkakeya Yilake",
    "gn:population":0,
    "gn:timezone":"Asia/Shanghai",
    "iso:country":"CN",
    "name:zho_x_preferred":[
        "\u5c24\u5580\u514b\u4e9a\u4f9d\u62c9\u514b"
    ],
    "wof:name":"Youkakeya Yilake",
    "wof:placetype":"locality"
},
  "geometry": {"coordinates":[76.2162,39.35975],"type":"Point"}
}