{
  "type": "Feature",
  "properties": {
    "gn:admin1_code":"1.0",
    "gn:asciiname":"Fucun",
    "gn:country_code":"CN",
    "gn:dem":10,
    "gn:feature_class":"P",
    "gn:feature_code":"PPL",
    "gn:name":"Fucun",
    "gn:population":0,
    "gn:timezone":"Asia/Shanghai",
    "iso:country":"CN",
    "name:zho_x_preferred":[
        "\u5bcc\u6751"
    ],
    "wof:name":"Fucun",
    "wof:placetype":"locality"
},
  "geometry": {"coordinates":[119.08727,31.14597],"type":"Point"}
}