{
  "type": "Feature",
  "properties": {
    "gn:admin1_code":"24.0",
    "gn:asciiname":"Wangtongcun",
    "gn:country_code":"CN",
    "gn:dem":392,
    "gn:feature_class":"P",
    "gn:feature_code":"PPL",
    "gn:name":"Wangtongcun",
    "gn:population":0,
    "gn:timezone":"Asia/Shanghai",
    "iso:country":"CN",
    "name:zho_x_preferred":[
        "\u738b\u6850\u6751"
    ],
    "wof:name":"Wangtongcun",
    "wof:placetype":"locality"
},
  "geometry": {"coordinates":[110.94109,35.10362],"type":"Point"}
}