{
  "type": "Feature",
  "properties": {
    "gn:admin1_code":"7",
    "gn:asciiname":"Shizilei",
    "gn:country_code":"CN",
    "gn:dem":127,
    "gn:feature_class":"P",
    "gn:feature_code":"PPL",
    "gn:name":"Shizilei",
    "gn:population":0,
    "gn:timezone":"Asia/Shanghai",
    "iso:country":"CN",
    "name:zho_x_preferred":[
        "\u77f3\u5b50\u78ca"
    ],
    "wof:name":"Shizilei",
    "wof:placetype":"locality"
},
  "geometry": {"coordinates":[119.26673,25.76369],"type":"Point"}
}