{
  "type": "Feature",
  "properties": {
    "gn:admin1_code":"10.0",
    "gn:asciiname":"Gaomatou",
    "gn:country_code":"CN",
    "gn:dem":16,
    "gn:feature_class":"P",
    "gn:feature_code":"PPL",
    "gn:name":"Gaomatou",
    "gn:population":0,
    "gn:timezone":"Asia/Shanghai",
    "iso:country":"CN",
    "name:zho_x_preferred":[
        "\u9ad8\u9a6c\u5934"
    ],
    "wof:name":"Gaomatou",
    "wof:placetype":"locality"
},
  "geometry": {"coordinates":[116.15000000000001,38.1739],"type":"Point"}
}