{
  "type": "Feature",
  "properties": {
    "gn:admin1_code":"11.0",
    "gn:asciiname":"Wujiacang",
    "gn:country_code":"CN",
    "gn:dem":70,
    "gn:feature_class":"P",
    "gn:feature_code":"PPL",
    "gn:name":"Wujiacang",
    "gn:population":0,
    "gn:timezone":"Asia/Shanghai",
    "iso:country":"CN",
    "name:zho_x_preferred":[
        "\u5434\u5bb6\u4ed3"
    ],
    "wof:name":"Wujiacang",
    "wof:placetype":"locality"
},
  "geometry": {"coordinates":[113.20798000000001,26.92191],"type":"Point"}
}