{
  "type": "Feature",
  "properties": {
    "gn:admin1_code":"2.0",
    "gn:asciiname":"Dongpu",
    "gn:country_code":"CN",
    "gn:dem":9,
    "gn:feature_class":"P",
    "gn:feature_code":"PPL",
    "gn:name":"Dongpu",
    "gn:population":0,
    "gn:timezone":"Asia/Shanghai",
    "iso:country":"CN",
    "name:und_x_variant":[
        "\u4e1c\u84b2",
        "Tung-mu-ts\u2019un"
    ],
    "wof:name":"Dongpu",
    "wof:placetype":"locality"
},
  "geometry": {"coordinates":[121.05297,30.13349],"type":"Point"}
}