{
  "type": "Feature",
  "properties": {
    "gn:admin1_code":"04",
    "gn:asciiname":"Chahe",
    "gn:cc2":"CN",
    "gn:country_code":"CN",
    "gn:dem":9,
    "gn:feature_class":"P",
    "gn:feature_code":"PPL",
    "gn:name":"Chahe",
    "gn:population":0,
    "gn:timezone":"Asia/Shanghai",
    "iso:country":"CN",
    "name:ceb_x_preferred":[
        "Chahe"
    ],
    "name:swe_x_preferred":[
        "Chahe"
    ],
    "name:und_x_variant":[
        "Ch\u2019a-ho",
        "Ch\u2019a-ho-chen",
        "Chahe"
    ],
    "wof:name":"Chahe",
    "wof:placetype":"locality"
},
  "geometry": {"coordinates":[119.03278,33.26694000000001],"type":"Point"}
}