{
  "type": "Feature",
  "properties": {
    "gn:admin1_code":"32.0",
    "gn:asciiname":"Ranli",
    "gn:country_code":"CN",
    "gn:dem":3217,
    "gn:feature_class":"P",
    "gn:feature_code":"PPL",
    "gn:name":"Ranli",
    "gn:population":0,
    "gn:timezone":"Asia/Shanghai",
    "iso:country":"CN",
    "name:zho_x_preferred":[
        "\u7136\u91cc"
    ],
    "wof:name":"Ranli",
    "wof:placetype":"locality"
},
  "geometry": {"coordinates":[100.83884,28.8945],"type":"Point"}
}