{
  "type": "Feature",
  "properties": {
    "gn:admin1_code":"26.0",
    "gn:asciiname":"Duyongcun",
    "gn:country_code":"CN",
    "gn:dem":449,
    "gn:feature_class":"P",
    "gn:feature_code":"PPL",
    "gn:name":"Duyongcun",
    "gn:population":0,
    "gn:timezone":"Asia/Shanghai",
    "iso:country":"CN",
    "name:zho_x_preferred":[
        "\u675c\u6c38\u6751"
    ],
    "wof:name":"Duyongcun",
    "wof:placetype":"locality"
},
  "geometry": {"coordinates":[108.9042,34.13136],"type":"Point"}
}