{
  "type": "Feature",
  "properties": {
    "gn:admin1_code":"1.0",
    "gn:asciiname":"Yanglincun",
    "gn:country_code":"CN",
    "gn:dem":58,
    "gn:feature_class":"P",
    "gn:feature_code":"PPL",
    "gn:name":"Yanglincun",
    "gn:population":0,
    "gn:timezone":"Asia/Shanghai",
    "iso:country":"CN",
    "name:und_x_variant":[
        "Yanglin"
    ],
    "name:zho_x_preferred":[
        "\u6768\u6797\u6751"
    ],
    "wof:name":"Yanglincun",
    "wof:placetype":"locality"
},
  "geometry": {"coordinates":[118.88952999999999,30.76251],"type":"Point"}
}