{
  "type": "Feature",
  "properties": {
    "gn:admin1_code":"4.0",
    "gn:asciiname":"Linzhuang",
    "gn:country_code":"CN",
    "gn:dem":4,
    "gn:feature_class":"P",
    "gn:feature_code":"PPL",
    "gn:name":"Linzhuang",
    "gn:population":0,
    "gn:timezone":"Asia/Shanghai",
    "iso:country":"CN",
    "name:zho_x_preferred":[
        "Linzhuang"
    ],
    "name:zho_x_variant":[
        "\u6797\u5e84"
    ],
    "wof:name":"Linzhuang",
    "wof:placetype":"locality"
},
  "geometry": {"coordinates":[119.35348,33.31049],"type":"Point"}
}