{
  "type": "Feature",
  "properties": {
    "gn:admin1_code":"30.0",
    "gn:asciiname":"Yangmeishu",
    "gn:country_code":"CN",
    "gn:dem":77,
    "gn:feature_class":"P",
    "gn:feature_code":"PPL",
    "gn:name":"Yangmeishu",
    "gn:population":0,
    "gn:timezone":"Asia/Shanghai",
    "iso:country":"CN",
    "name:zho_x_preferred":[
        "\u6768\u6885\u6811"
    ],
    "wof:name":"Yangmeishu",
    "wof:placetype":"locality"
},
  "geometry": {"coordinates":[113.11278,24.11722],"type":"Point"}
}