{
  "type": "Feature",
  "properties": {
    "gn:admin1_code":"1.0",
    "gn:asciiname":"Xuqiangcun",
    "gn:country_code":"CN",
    "gn:dem":24,
    "gn:feature_class":"P",
    "gn:feature_code":"PPL",
    "gn:name":"Xuqiangcun",
    "gn:population":0,
    "gn:timezone":"Asia/Shanghai",
    "iso:country":"CN",
    "name:zho_x_preferred":[
        "\u8bb8\u5899\u6751"
    ],
    "wof:name":"Xuqiangcun",
    "wof:placetype":"locality"
},
  "geometry": {"coordinates":[116.84286000000002,32.34328],"type":"Point"}
}