{
  "type": "Feature",
  "properties": {
    "gn:admin1_code":"26.0",
    "gn:asciiname":"Donghuanlecun",
    "gn:country_code":"CN",
    "gn:dem":483,
    "gn:feature_class":"P",
    "gn:feature_code":"PPL",
    "gn:name":"Donghuanlecun",
    "gn:population":0,
    "gn:timezone":"Asia/Shanghai",
    "iso:country":"CN",
    "name:zho_x_preferred":[
        "\u4e1c\u6b22\u4e50\u6751"
    ],
    "wof:name":"Donghuanlecun",
    "wof:placetype":"locality"
},
  "geometry": {"coordinates":[108.12872,34.14565],"type":"Point"}
}