{
  "type": "Feature",
  "properties": {
    "gn:admin1_code":"4.0",
    "gn:asciiname":"Bindongcun",
    "gn:country_code":"CN",
    "gn:dem":1,
    "gn:feature_class":"P",
    "gn:feature_code":"PPL",
    "gn:name":"Bindongcun",
    "gn:population":0,
    "gn:timezone":"Asia/Shanghai",
    "iso:country":"CN",
    "name:zho_x_preferred":[
        "\u6ee8\u4e1c\u6751"
    ],
    "wof:name":"Bindongcun",
    "wof:placetype":"locality"
},
  "geometry": {"coordinates":[120.22888,33.92212],"type":"Point"}
}