{
  "type": "Feature",
  "properties": {
    "gn:admin1_code":"12.0",
    "gn:asciiname":"Xuquanli",
    "gn:country_code":"CN",
    "gn:dem":26,
    "gn:feature_class":"P",
    "gn:feature_code":"PPL",
    "gn:name":"Xuquanli",
    "gn:population":0,
    "gn:timezone":"Asia/Shanghai",
    "iso:country":"CN",
    "name:zho_x_preferred":[
        "Xuquanli"
    ],
    "name:zho_x_variant":[
        "\u8bb8\u5708\u91cc"
    ],
    "wof:name":"Xuquanli",
    "wof:placetype":"locality"
},
  "geometry": {"coordinates":[115.42126,30.11338],"type":"Point"}
}