{
  "type": "Feature",
  "properties": {
    "gn:admin1_code":"06",
    "gn:asciiname":"Caojiapu",
    "gn:cc2":"CN",
    "gn:country_code":"CN",
    "gn:dem":2422,
    "gn:feature_class":"P",
    "gn:feature_code":"PPL",
    "gn:name":"Caojiapu",
    "gn:population":0,
    "gn:timezone":"Asia/Shanghai",
    "iso:country":"CN",
    "name:und_x_variant":[
        "Ts\u2019ao-chia-p\u2019u",
        "Caojiapu"
    ],
    "wof:name":"Caojiapu",
    "wof:placetype":"locality"
},
  "geometry": {"coordinates":[102.03333000000001,36.61667],"type":"Point"}
}