{
  "type": "Feature",
  "properties": {
    "gn:admin1_code":"32.0",
    "gn:asciiname":"Guihua",
    "gn:country_code":"CN",
    "gn:dem":527,
    "gn:feature_class":"P",
    "gn:feature_code":"PPL",
    "gn:name":"Guihua",
    "gn:population":0,
    "gn:timezone":"Asia/Shanghai",
    "iso:country":"CN",
    "name:ceb_x_preferred":[
        "Guihua"
    ],
    "name:deu_x_preferred":[
        "Guihua"
    ],
    "name:swe_x_preferred":[
        "Guihua"
    ],
    "name:zho_x_preferred":[
        "\u6842\u82b1"
    ],
    "wof:name":"Guihua",
    "wof:placetype":"locality"
},
  "geometry": {"coordinates":[105.586,31.2138],"type":"Point"}
}