{
  "type": "Feature",
  "properties": {
    "gn:admin1_code":"30",
    "gn:asciiname":"Xiajingdi",
    "gn:country_code":"CN",
    "gn:dem":146,
    "gn:feature_class":"P",
    "gn:feature_code":"PPL",
    "gn:name":"Xiajingdi",
    "gn:population":0,
    "gn:timezone":"Asia/Urumqi",
    "iso:country":"CN",
    "name:zho_x_preferred":[
        "\u4e0b\u5f84\u5730"
    ],
    "wof:name":"Xiajingdi",
    "wof:placetype":"locality"
},
  "geometry": {"coordinates":[111.1046,21.8648],"type":"Point"}
}