{
  "type": "Feature",
  "properties": {
    "gn:admin1_code":"32.0",
    "gn:asciiname":"Yinjiahe",
    "gn:country_code":"CN",
    "gn:dem":860,
    "gn:feature_class":"P",
    "gn:feature_code":"PPL",
    "gn:name":"Yinjiahe",
    "gn:population":0,
    "gn:timezone":"Asia/Shanghai",
    "iso:country":"CN",
    "name:zho_x_preferred":[
        "\u5c39\u5bb6\u6cb3"
    ],
    "wof:name":"Yinjiahe",
    "wof:placetype":"locality"
},
  "geometry": {"coordinates":[105.69329,32.65961],"type":"Point"}
}