{
  "type": "Feature",
  "properties": {
    "gn:admin1_code":"18",
    "gn:asciiname":"Fannong",
    "gn:country_code":"CN",
    "gn:dem":1922,
    "gn:feature_class":"P",
    "gn:feature_code":"PPL",
    "gn:name":"Fannong",
    "gn:population":0,
    "gn:timezone":"Asia/Shanghai",
    "iso:country":"CN",
    "name:zho_x_preferred":[
        "\u7ffb\u5f04"
    ],
    "wof:name":"Fannong",
    "wof:placetype":"locality"
},
  "geometry": {"coordinates":[103.98999999999999,27.0428],"type":"Point"}
}