{
  "type": "Feature",
  "properties": {
    "gn:admin1_code":"14.0",
    "gn:asciiname":"De'adeng",
    "gn:country_code":"CN",
    "gn:dem":4206,
    "gn:feature_class":"P",
    "gn:feature_code":"PPL",
    "gn:name":"De\u2019adeng",
    "gn:population":0,
    "gn:timezone":"Asia/Urumqi",
    "iso:country":"CN",
    "name:und_x_variant":[
        "De\u2019adeng"
    ],
    "name:zho_x_preferred":[
        "\u5f97\u963f\u7b49"
    ],
    "wof:name":"De'adeng",
    "wof:placetype":"locality"
},
  "geometry": {"coordinates":[94.25823,31.29676],"type":"Point"}
}