{
  "type": "Feature",
  "properties": {
    "gn:admin1_code":"04",
    "gn:asciiname":"Guanlin",
    "gn:country_code":"CN",
    "gn:dem":9,
    "gn:feature_class":"P",
    "gn:feature_code":"PPLA4",
    "gn:name":"Guanlin",
    "gn:population":0,
    "gn:timezone":"Asia/Shanghai",
    "iso:country":"CN",
    "name:und_x_variant":[
        "Kuan-lin-chen",
        "Kuan-lin",
        "Kuan-ts\u2019un",
        "Kuan-ts\u2019un-chen",
        "Guanlin",
        "Guanlin Zhen"
    ],
    "name:zho_x_preferred":[
        "\u5b98\u6797"
    ],
    "name:zho_x_variant":[
        "\u5b98\u6797\u9547"
    ],
    "wof:name":"Guanlin",
    "wof:placetype":"locality"
},
  "geometry": {"coordinates":[119.71164,31.50404],"type":"Point"}
}