{
  "type": "Feature",
  "properties": {
    "gn:admin1_code":"29.0",
    "gn:asciiname":"Yujiaying",
    "gn:country_code":"CN",
    "gn:dem":1720,
    "gn:feature_class":"P",
    "gn:feature_code":"PPL",
    "gn:name":"Yujiaying",
    "gn:population":0,
    "gn:timezone":"Asia/Shanghai",
    "iso:country":"CN",
    "name:zho_x_preferred":[
        "\u4f59\u5bb6\u8425"
    ],
    "wof:name":"Yujiaying",
    "wof:placetype":"locality"
},
  "geometry": {"coordinates":[98.4862,24.9188],"type":"Point"}
}