{
  "type": "Feature",
  "properties": {
    "gn:admin1_code":"18",
    "gn:asciiname":"Bijiashan",
    "gn:country_code":"CN",
    "gn:dem":1048,
    "gn:feature_class":"P",
    "gn:feature_code":"PPL",
    "gn:name":"Bijiashan",
    "gn:population":0,
    "gn:timezone":"Asia/Shanghai",
    "iso:country":"CN",
    "name:zho_x_preferred":[
        "\u7b14\u67b6\u5c71"
    ],
    "wof:name":"Bijiashan",
    "wof:placetype":"locality"
},
  "geometry": {"coordinates":[108.045,27.4556],"type":"Point"}
}