{
  "type": "Feature",
  "properties": {
    "gn:admin1_code":"9.0",
    "gn:asciiname":"Gengjia",
    "gn:country_code":"CN",
    "gn:dem":126,
    "gn:feature_class":"P",
    "gn:feature_code":"PPL",
    "gn:name":"Gengjia",
    "gn:population":0,
    "gn:timezone":"Asia/Shanghai",
    "iso:country":"CN",
    "name:zho_x_preferred":[
        "\u803f\u5bb6"
    ],
    "wof:name":"Gengjia",
    "wof:placetype":"locality"
},
  "geometry": {"coordinates":[113.91278,34.52649],"type":"Point"}
}