{
  "type": "Feature",
  "properties": {
    "gn:admin1_code":"30",
    "gn:asciiname":"Dachuan'ao",
    "gn:country_code":"CN",
    "gn:dem":13,
    "gn:feature_class":"P",
    "gn:feature_code":"PPL",
    "gn:name":"Dachuan\u2019ao",
    "gn:population":0,
    "gn:timezone":"Asia/Shanghai",
    "iso:country":"CN",
    "name:zho_x_preferred":[
        "\u5927\u8239\u6fb3"
    ],
    "name:zho_x_variant":[
        "Dachuan\u2019ao"
    ],
    "wof:name":"Dachuan'ao",
    "wof:placetype":"locality"
},
  "geometry": {"coordinates":[116.95863,23.42196],"type":"Point"}
}