{
  "type": "Feature",
  "properties": {
    "gn:admin1_code":"26.0",
    "gn:asciiname":"Hudugou",
    "gn:country_code":"CN",
    "gn:dem":1228,
    "gn:feature_class":"P",
    "gn:feature_code":"PPL",
    "gn:name":"Hudugou",
    "gn:population":0,
    "gn:timezone":"Asia/Shanghai",
    "iso:country":"CN",
    "name:zho_x_preferred":[
        "\u864e\u6bd2\u6c9f"
    ],
    "wof:name":"Hudugou",
    "wof:placetype":"locality"
},
  "geometry": {"coordinates":[110.80695,39.31781],"type":"Point"}
}