{
  "type": "Feature",
  "properties": {
    "gn:admin1_code":"29.0",
    "gn:asciiname":"Shijiashan",
    "gn:country_code":"CN",
    "gn:dem":1557,
    "gn:feature_class":"P",
    "gn:feature_code":"PPL",
    "gn:name":"Shijiashan",
    "gn:population":0,
    "gn:timezone":"Asia/Shanghai",
    "iso:country":"CN",
    "name:zho_x_preferred":[
        "\u77f3\u5bb6\u5c71"
    ],
    "wof:name":"Shijiashan",
    "wof:placetype":"locality"
},
  "geometry": {"coordinates":[100.85599999999999,24.6162],"type":"Point"}
}