{
  "type": "Feature",
  "properties": {
    "gn:admin1_code":"18.0",
    "gn:asciiname":"Bixue",
    "gn:country_code":"CN",
    "gn:dem":693,
    "gn:feature_class":"P",
    "gn:feature_code":"PPL",
    "gn:name":"Bixue",
    "gn:population":0,
    "gn:timezone":"Asia/Shanghai",
    "iso:country":"CN",
    "name:zho_x_preferred":[
        "\u6bd5\u5b66"
    ],
    "wof:name":"Bixue",
    "wof:placetype":"locality"
},
  "geometry": {"coordinates":[108.19499999999999,25.7154],"type":"Point"}
}