{
  "type": "Feature",
  "properties": {
    "gn:admin1_code":"11",
    "gn:asciiname":"Gaofeng",
    "gn:country_code":"CN",
    "gn:dem":724,
    "gn:feature_class":"P",
    "gn:feature_code":"PPLA4",
    "gn:name":"Gaofeng",
    "gn:population":0,
    "gn:timezone":"Asia/Shanghai",
    "iso:country":"CN",
    "name:und_x_variant":[
        "Gaofeng Tujiazu Xiang",
        "Tanjiaqiao"
    ],
    "name:zho_x_preferred":[
        "\u8983\u5bb6\u6865"
    ],
    "name:zho_x_variant":[
        "\u9ad8\u5cf0",
        "\u9ad8\u5cf0\u571f\u5bb6\u65cf\u4e61"
    ],
    "wof:name":"Gaofeng",
    "wof:placetype":"locality"
},
  "geometry": {"coordinates":[110.91708,29.43683],"type":"Point"}
}