{
  "type": "Feature",
  "properties": {
    "gn:admin1_code":"3",
    "gn:asciiname":"Shapingli",
    "gn:country_code":"CN",
    "gn:dem":175,
    "gn:feature_class":"P",
    "gn:feature_code":"PPL",
    "gn:name":"Shapingli",
    "gn:population":0,
    "gn:timezone":"Asia/Shanghai",
    "iso:country":"CN",
    "name:zho_x_preferred":[
        "\u6c99\u576a\u91cc"
    ],
    "wof:name":"Shapingli",
    "wof:placetype":"locality"
},
  "geometry": {"coordinates":[114.038,26.8789],"type":"Point"}
}