{
  "type": "Feature",
  "properties": {
    "gn:admin1_code":"11.0",
    "gn:asciiname":"Jingxingqiao",
    "gn:country_code":"CN",
    "gn:dem":530,
    "gn:feature_class":"P",
    "gn:feature_code":"PPL",
    "gn:name":"Jingxingqiao",
    "gn:population":0,
    "gn:timezone":"Asia/Shanghai",
    "iso:country":"CN",
    "name:zho_x_preferred":[
        "\u666f\u5174\u6865"
    ],
    "wof:name":"Jingxingqiao",
    "wof:placetype":"locality"
},
  "geometry": {"coordinates":[110.59352,27.42433],"type":"Point"}
}