{
  "type": "Feature",
  "properties": {
    "gn:admin1_code":"1.0",
    "gn:asciiname":"Xiatangji",
    "gn:cc2":"CN",
    "gn:country_code":"CN",
    "gn:dem":44,
    "gn:feature_class":"P",
    "gn:feature_code":"PPL",
    "gn:name":"Xiatangji",
    "gn:population":0,
    "gn:timezone":"Asia/Shanghai",
    "iso:country":"CN",
    "name:und_x_variant":[
        "Hsia-t\u2019ang-chi",
        "Hsia-t\u2019ang",
        "Hsia-t\u2019ang-chen",
        "Siatangtsi",
        "Xiatangji"
    ],
    "wof:name":"Xiatangji",
    "wof:placetype":"locality"
},
  "geometry": {"coordinates":[117.2075,32.19028],"type":"Point"}
}