{
  "type": "Feature",
  "properties": {
    "gn:admin1_code":"4.0",
    "gn:asciiname":"Lukoucun",
    "gn:country_code":"CN",
    "gn:dem":3,
    "gn:feature_class":"P",
    "gn:feature_code":"PPL",
    "gn:name":"Lukoucun",
    "gn:population":0,
    "gn:timezone":"Asia/Shanghai",
    "iso:country":"CN",
    "name:zho_x_preferred":[
        "\u9646\u53e3\u6751"
    ],
    "wof:name":"Lukoucun",
    "wof:placetype":"locality"
},
  "geometry": {"coordinates":[118.99951,34.32208],"type":"Point"}
}