{
  "type": "Feature",
  "properties": {
    "gn:admin1_code":"15.0",
    "gn:asciiname":"Erdun Sidui",
    "gn:country_code":"CN",
    "gn:dem":1382,
    "gn:feature_class":"P",
    "gn:feature_code":"PPLF",
    "gn:name":"Erdun Sidui",
    "gn:population":0,
    "gn:timezone":"Asia/Shanghai",
    "iso:country":"CN",
    "name:zho_x_preferred":[
        "\u4e8c\u58a9\u56db\u961f"
    ],
    "wof:name":"Erdun Sidui",
    "wof:placetype":"locality"
},
  "geometry": {"coordinates":[98.7072,39.7528],"type":"Point"}
}