{
  "type": "Feature",
  "properties": {
    "gn:admin1_code":"7",
    "gn:asciiname":"Shoujinliao",
    "gn:country_code":"CN",
    "gn:dem":685,
    "gn:feature_class":"P",
    "gn:feature_code":"PPL",
    "gn:name":"Shoujinliao",
    "gn:population":0,
    "gn:timezone":"Asia/Shanghai",
    "iso:country":"CN",
    "name:zho_x_preferred":[
        "\u624b\u5dfe\u5bee"
    ],
    "wof:name":"Shoujinliao",
    "wof:placetype":"locality"
},
  "geometry": {"coordinates":[117.25461,24.80811],"type":"Point"}
}