{
  "type": "Feature",
  "properties": {
    "gn:admin1_code":"32.0",
    "gn:asciiname":"Tangqingba",
    "gn:country_code":"CN",
    "gn:dem":399,
    "gn:feature_class":"P",
    "gn:feature_code":"PPL",
    "gn:name":"Tangqingba",
    "gn:population":0,
    "gn:timezone":"Asia/Shanghai",
    "iso:country":"CN",
    "name:zho_x_preferred":[
        "\u5858\u6e05\u575d"
    ],
    "wof:name":"Tangqingba",
    "wof:placetype":"locality"
},
  "geometry": {"coordinates":[106.254,31.63300000000001],"type":"Point"}
}