{
  "type": "Feature",
  "properties": {
    "gn:admin1_code":"2.0",
    "gn:asciiname":"Xiayang'er",
    "gn:country_code":"CN",
    "gn:dem":121,
    "gn:feature_class":"P",
    "gn:feature_code":"PPL",
    "gn:name":"Xiayang\u2019er",
    "gn:population":0,
    "gn:timezone":"Asia/Shanghai",
    "iso:country":"CN",
    "name:und_x_variant":[
        "Xiayang\u2019er"
    ],
    "name:zho_x_preferred":[
        "\u4e0b\u6768\u4e8c"
    ],
    "wof:name":"Xiayang'er",
    "wof:placetype":"locality"
},
  "geometry": {"coordinates":[121.31244,29.4285],"type":"Point"}
}