{
  "type": "Feature",
  "properties": {
    "gn:admin1_code":"01",
    "gn:asciiname":"Huji",
    "gn:cc2":"CN",
    "gn:country_code":"CN",
    "gn:dem":28,
    "gn:feature_class":"P",
    "gn:feature_code":"PPL",
    "gn:name":"Huji",
    "gn:population":0,
    "gn:timezone":"Asia/Shanghai",
    "iso:country":"CN",
    "name:ceb_x_preferred":[
        "Huji"
    ],
    "name:swe_x_preferred":[
        "Huji"
    ],
    "name:und_x_variant":[
        "Hu-chi"
    ],
    "wof:name":"Huji",
    "wof:placetype":"locality"
},
  "geometry": {"coordinates":[116.17610999999999,32.97472],"type":"Point"}
}