{
  "type": "Feature",
  "properties": {
    "gn:admin1_code":"32.0",
    "gn:asciiname":"Haluo",
    "gn:country_code":"CN",
    "gn:dem":2986,
    "gn:feature_class":"P",
    "gn:feature_code":"PPL",
    "gn:name":"Haluo",
    "gn:population":0,
    "gn:timezone":"Asia/Shanghai",
    "iso:country":"CN",
    "name:zho_x_preferred":[
        "\u54c8\u7f57"
    ],
    "wof:name":"Haluo",
    "wof:placetype":"locality"
},
  "geometry": {"coordinates":[100.613,27.945],"type":"Point"}
}