{
  "type": "Feature",
  "properties": {
    "gn:admin1_code":"18.0",
    "gn:asciiname":"Shuishijiao",
    "gn:country_code":"CN",
    "gn:dem":791,
    "gn:feature_class":"P",
    "gn:feature_code":"PPL",
    "gn:name":"Shuishijiao",
    "gn:population":0,
    "gn:timezone":"Asia/Shanghai",
    "iso:country":"CN",
    "name:zho_x_preferred":[
        "\u6c34\u77f3\u811a"
    ],
    "wof:name":"Shuishijiao",
    "wof:placetype":"locality"
},
  "geometry": {"coordinates":[107.76194,28.9725],"type":"Point"}
}