{
  "type": "Feature",
  "properties": {
    "gn:admin1_code":"24",
    "gn:asciiname":"Wuling",
    "gn:country_code":"CN",
    "gn:dem":1018,
    "gn:feature_class":"P",
    "gn:feature_code":"PPLA3",
    "gn:name":"Wuling",
    "gn:population":0,
    "gn:timezone":"Asia/Shanghai",
    "iso:country":"CN",
    "name:und_x_variant":[
        "Lingkiuhsien",
        "Lingqiu",
        "Wuling",
        "Lingqiu Xian",
        "Wuling Zhen",
        "\u7075\u4e18\u53bf",
        "\u6b66\u7075\u9547"
    ],
    "name:zho_x_preferred":[
        "Ling-ch\u2019iu-hsien"
    ],
    "name:zho_x_variant":[
        "Ling-ch\u2019iu",
        "\u6b66\u7075"
    ],
    "wof:name":"Wuling",
    "wof:placetype":"locality"
},
  "geometry": {"coordinates":[114.14843,39.46799],"type":"Point"}
}