{
  "type": "Feature",
  "properties": {
    "gn:admin1_code":"11.0",
    "gn:asciiname":"Huangni'ao",
    "gn:country_code":"CN",
    "gn:dem":100,
    "gn:feature_class":"P",
    "gn:feature_code":"PPL",
    "gn:name":"Huangni\u2019ao",
    "gn:population":0,
    "gn:timezone":"Asia/Shanghai",
    "iso:country":"CN",
    "name:und_x_variant":[
        "Huangni\u2019ao"
    ],
    "name:zho_x_preferred":[
        "\u9ec4\u6ce5\u5773"
    ],
    "wof:name":"Huangni'ao",
    "wof:placetype":"locality"
},
  "geometry": {"coordinates":[112.64649,27.69103],"type":"Point"}
}