{
  "type": "Feature",
  "properties": {
    "gn:admin1_code":"4.0",
    "gn:asciiname":"Donghaicun Nongyezu",
    "gn:country_code":"CN",
    "gn:dem":1,
    "gn:feature_class":"P",
    "gn:feature_code":"PPLF",
    "gn:name":"Donghaicun Nongyezu",
    "gn:population":0,
    "gn:timezone":"Asia/Shanghai",
    "iso:country":"CN",
    "name:zho_x_preferred":[
        "\u4e1c\u6d77\u6751\u519c\u4e1a\u7ec4"
    ],
    "wof:name":"Donghaicun Nongyezu",
    "wof:placetype":"locality"
},
  "geometry": {"coordinates":[120.548,33.4444],"type":"Point"}
}