{
  "type": "Feature",
  "properties": {
    "gn:admin1_code":"30.0",
    "gn:asciiname":"Linhai",
    "gn:country_code":"CN",
    "gn:dem":2,
    "gn:feature_class":"P",
    "gn:feature_code":"PPL",
    "gn:name":"Linhai",
    "gn:population":0,
    "gn:timezone":"Asia/Shanghai",
    "iso:country":"CN",
    "name:ara_x_preferred":[
        "\u0644\u064a\u0646\u0647\u0627\u064a"
    ],
    "name:deu_x_preferred":[
        "Linhai"
    ],
    "name:est_x_preferred":[
        "Linhai"
    ],
    "name:fra_x_preferred":[
        "Linhai"
    ],
    "name:ita_x_preferred":[
        "Linhai"
    ],
    "name:jpn_x_preferred":[
        "\u81e8\u6d77\u5e02"
    ],
    "name:kik_x_preferred":[
        "Linhai"
    ],
    "name:kor_x_preferred":[
        "\ub9b0\ud558\uc774\uc2dc"
    ],
    "name:mlg_x_preferred":[
        "Linhai"
    ],
    "name:nor_x_preferred":[
        "Linhai"
    ],
    "name:swe_x_preferred":[
        "Linhai"
    ],
    "name:tgl_x_preferred":[
        "Linhai"
    ],
    "name:vie_x_preferred":[
        "L\u00e2m H\u1ea3i"
    ],
    "name:war_x_preferred":[
        "Linhai"
    ],
    "name:wuu_x_preferred":[
        "\u4e34\u6d77\u5e02"
    ],
    "name:zho_x_preferred":[
        "\u6dcb\u6d77"
    ],
    "name:zho_x_variant":[
        "\u4e34\u6d77\u5e02"
    ],
    "wof:name":"Linhai",
    "wof:placetype":"locality"
},
  "geometry": {"coordinates":[113.15549,22.72379],"type":"Point"}
}