{
  "type": "Feature",
  "properties": {
    "gn:admin1_code":"19.0",
    "gn:asciiname":"Beiweizi",
    "gn:country_code":"CN",
    "gn:dem":72,
    "gn:feature_class":"P",
    "gn:feature_code":"PPL",
    "gn:name":"Beiweizi",
    "gn:population":0,
    "gn:timezone":"Asia/Shanghai",
    "iso:country":"CN",
    "name:und_x_variant":[
        "\u5317\u9688\u5b50"
    ],
    "wof:name":"Beiweizi",
    "wof:placetype":"locality"
},
  "geometry": {"coordinates":[123.49575,40.33976],"type":"Point"}
}