{
  "type": "Feature",
  "properties": {
    "gn:admin1_code":"3.0",
    "gn:asciiname":"Gengxi",
    "gn:country_code":"CN",
    "gn:dem":98,
    "gn:feature_class":"P",
    "gn:feature_code":"PPL",
    "gn:name":"Gengxi",
    "gn:population":0,
    "gn:timezone":"Asia/Shanghai",
    "iso:country":"CN",
    "name:und_x_variant":[
        "\u8d53\u6eaa"
    ],
    "wof:name":"Gengxi",
    "wof:placetype":"locality"
},
  "geometry": {"coordinates":[116.58223999999998,27.19745],"type":"Point"}
}