{
  "type": "Feature",
  "properties": {
    "gn:admin1_code":"12.0",
    "gn:asciiname":"Liansihong",
    "gn:country_code":"CN",
    "gn:dem":62,
    "gn:feature_class":"P",
    "gn:feature_code":"PPL",
    "gn:name":"Liansihong",
    "gn:population":0,
    "gn:timezone":"Asia/Shanghai",
    "iso:country":"CN",
    "name:zho_x_preferred":[
        "\u8fde\u6cd7\u6d2a"
    ],
    "wof:name":"Liansihong",
    "wof:placetype":"locality"
},
  "geometry": {"coordinates":[112.26775000000001,31.78477],"type":"Point"}
}