{
  "type": "Feature",
  "properties": {
    "gn:admin1_code":"12.0",
    "gn:asciiname":"Xiadouguanglong",
    "gn:country_code":"CN",
    "gn:dem":80,
    "gn:feature_class":"P",
    "gn:feature_code":"PPL",
    "gn:name":"Xiadouguanglong",
    "gn:population":0,
    "gn:timezone":"Asia/Shanghai",
    "iso:country":"CN",
    "name:zho_x_preferred":[
        "\u4e0b\u6597\u5149\u5784"
    ],
    "wof:name":"Xiadouguanglong",
    "wof:placetype":"locality"
},
  "geometry": {"coordinates":[113.96373,29.52152],"type":"Point"}
}