{
  "type": "Feature",
  "properties": {
    "gn:admin1_code":"5.0",
    "gn:asciiname":"Ningjiatun",
    "gn:country_code":"CN",
    "gn:dem":202,
    "gn:feature_class":"P",
    "gn:feature_code":"PPL",
    "gn:name":"Ningjiatun",
    "gn:population":0,
    "gn:timezone":"Asia/Shanghai",
    "iso:country":"CN",
    "name:zho_x_preferred":[
        "\u5b81\u5bb6\u5c6f"
    ],
    "wof:name":"Ningjiatun",
    "wof:placetype":"locality"
},
  "geometry": {"coordinates":[124.71174999999999,44.5481],"type":"Point"}
}