{
  "type": "Feature",
  "properties": {
    "gn:admin1_code":"32.0",
    "gn:asciiname":"Gaosheng",
    "gn:country_code":"CN",
    "gn:dem":643,
    "gn:feature_class":"P",
    "gn:feature_code":"PPL",
    "gn:name":"Gaosheng",
    "gn:population":0,
    "gn:timezone":"Asia/Shanghai",
    "iso:country":"CN",
    "name:zho_x_preferred":[
        "\u9ad8\u5347"
    ],
    "wof:name":"Gaosheng",
    "wof:placetype":"locality"
},
  "geometry": {"coordinates":[107.07452000000001,31.77822],"type":"Point"}
}