{
  "type": "Feature",
  "properties": {
    "gn:admin1_code":"12.0",
    "gn:asciiname":"Xinxigou",
    "gn:country_code":"CN",
    "gn:dem":508,
    "gn:feature_class":"P",
    "gn:feature_code":"PPL",
    "gn:name":"Xinxigou",
    "gn:population":0,
    "gn:timezone":"Asia/Shanghai",
    "iso:country":"CN",
    "name:zho_x_preferred":[
        "Xinxigou"
    ],
    "name:zho_x_variant":[
        "\u65b0\u6eaa\u6c9f"
    ],
    "wof:name":"Xinxigou",
    "wof:placetype":"locality"
},
  "geometry": {"coordinates":[109.3099,29.4079],"type":"Point"}
}