{
  "type": "Feature",
  "properties": {
    "gn:admin1_code":"20.0",
    "gn:asciiname":"Sandaoying",
    "gn:country_code":"CN",
    "gn:dem":1607,
    "gn:feature_class":"P",
    "gn:feature_code":"PPL",
    "gn:name":"Sandaoying",
    "gn:population":0,
    "gn:timezone":"Asia/Shanghai",
    "iso:country":"CN",
    "name:und_x_variant":[
        "\u4e09\u9053\u8425"
    ],
    "wof:name":"Sandaoying",
    "wof:placetype":"locality"
},
  "geometry": {"coordinates":[111.60151,41.19435],"type":"Point"}
}