{
  "type": "Feature",
  "properties": {
    "gn:admin1_code":"29.0",
    "gn:asciiname":"Yanqing",
    "gn:country_code":"CN",
    "gn:dem":1969,
    "gn:feature_class":"P",
    "gn:feature_code":"PPL",
    "gn:name":"Yanqing",
    "gn:population":0,
    "gn:timezone":"Asia/Shanghai",
    "iso:country":"CN",
    "name:est_x_preferred":[
        "Yanqing"
    ],
    "name:zho_x_preferred":[
        "\u884d\u5e86"
    ],
    "wof:name":"Yanqing",
    "wof:placetype":"locality"
},
  "geometry": {"coordinates":[100.193,26.3479],"type":"Point"}
}