{
  "type": "Feature",
  "properties": {
    "gn:admin1_code":"12.0",
    "gn:asciiname":"Zengji",
    "gn:country_code":"CN",
    "gn:dem":82,
    "gn:feature_class":"P",
    "gn:feature_code":"PPLA4",
    "gn:name":"Zengji",
    "gn:population":0,
    "gn:timezone":"Asia/Shanghai",
    "iso:country":"CN",
    "name:und_x_variant":[
        "Tseng-chia-chi",
        "Zengjiaji",
        "Zengji",
        "\u66fe\u96c6",
        "Zengji Zhen",
        "\u66fe\u96c6\u9547"
    ],
    "wof:name":"Zengji",
    "wof:placetype":"locality"
},
  "geometry": {"coordinates":[112.36982999999999,30.72028],"type":"Point"}
}