{
  "type": "Feature",
  "properties": {
    "gn:admin1_code":"14.0",
    "gn:asciiname":"Kaixi",
    "gn:country_code":"CN",
    "gn:dem":4349,
    "gn:feature_class":"P",
    "gn:feature_code":"PPL",
    "gn:name":"Kaixi",
    "gn:population":0,
    "gn:timezone":"Asia/Urumqi",
    "iso:country":"CN",
    "name:bod_x_preferred":[
        "Kaixi"
    ],
    "name:zho_x_preferred":[
        "Gexi"
    ],
    "name:zho_x_variant":[
        "\u683c\u897f"
    ],
    "wof:name":"Kaixi",
    "wof:placetype":"locality"
},
  "geometry": {"coordinates":[91.24684000000001,28.35916],"type":"Point"}
}