{
  "type": "Feature",
  "properties": {
    "gn:admin1_code":"25",
    "gn:asciiname":"Majia Zhuangzi",
    "gn:country_code":"CN",
    "gn:dem":7,
    "gn:feature_class":"P",
    "gn:feature_code":"PPL",
    "gn:name":"Majia Zhuangzi",
    "gn:population":0,
    "gn:timezone":"Asia/Shanghai",
    "iso:country":"CN",
    "name:zho_x_preferred":[
        "\u9a6c\u5bb6\u5e84\u5b50"
    ],
    "wof:name":"Majia Zhuangzi",
    "wof:placetype":"locality"
},
  "geometry": {"coordinates":[118.16316999999999,37.77093],"type":"Point"}
}