{
  "type": "Feature",
  "properties": {
    "gn:admin1_code":"16.0",
    "gn:asciiname":"Wailong",
    "gn:country_code":"CN",
    "gn:dem":882,
    "gn:feature_class":"P",
    "gn:feature_code":"PPL",
    "gn:name":"Wailong",
    "gn:population":0,
    "gn:timezone":"Asia/Shanghai",
    "iso:country":"CN",
    "name:zho_x_preferred":[
        "\u5916\u5784"
    ],
    "wof:name":"Wailong",
    "wof:placetype":"locality"
},
  "geometry": {"coordinates":[105.809,23.2021],"type":"Point"}
}