{
  "type": "Feature",
  "properties": {
    "gn:admin1_code":"19.0",
    "gn:asciiname":"Shanggangzi",
    "gn:country_code":"CN",
    "gn:dem":291,
    "gn:feature_class":"P",
    "gn:feature_code":"PPL",
    "gn:name":"Shanggangzi",
    "gn:population":0,
    "gn:timezone":"Asia/Shanghai",
    "iso:country":"CN",
    "name:zho_x_preferred":[
        "\u4e0a\u5c97\u5b50"
    ],
    "wof:name":"Shanggangzi",
    "wof:placetype":"locality"
},
  "geometry": {"coordinates":[124.53565999999999,41.8286],"type":"Point"}
}