{
  "type": "Feature",
  "properties": {
    "gn:admin1_code":"2.0",
    "gn:asciiname":"Dafangling",
    "gn:country_code":"CN",
    "gn:dem":126,
    "gn:feature_class":"P",
    "gn:feature_code":"PPL",
    "gn:name":"Dafangling",
    "gn:population":0,
    "gn:timezone":"Asia/Shanghai",
    "iso:country":"CN",
    "name:zho_x_preferred":[
        "\u5927\u65b9\u5cad"
    ],
    "wof:name":"Dafangling",
    "wof:placetype":"locality"
},
  "geometry": {"coordinates":[120.91212,29.559],"type":"Point"}
}