{
  "type": "Feature",
  "properties": {
    "gn:admin1_code":"2.0",
    "gn:asciiname":"Mengwuli",
    "gn:country_code":"CN",
    "gn:dem":105,
    "gn:feature_class":"P",
    "gn:feature_code":"PPL",
    "gn:name":"Mengwuli",
    "gn:population":0,
    "gn:timezone":"Asia/Shanghai",
    "iso:country":"CN",
    "name:und_x_variant":[
        "\u5b5f\u575e\u91cc"
    ],
    "name:zho_x_preferred":[
        "Mengwuli"
    ],
    "wof:name":"Mengwuli",
    "wof:placetype":"locality"
},
  "geometry": {"coordinates":[119.74997999999999,30.18333],"type":"Point"}
}