{
  "type": "Feature",
  "properties": {
    "gn:admin1_code":"2.0",
    "gn:asciiname":"Zaoyuan",
    "gn:country_code":"CN",
    "gn:dem":95,
    "gn:feature_class":"P",
    "gn:feature_code":"PPL",
    "gn:name":"Zaoyuan",
    "gn:population":0,
    "gn:timezone":"Asia/Shanghai",
    "iso:country":"CN",
    "name:zho_x_preferred":[
        "\u67a3\u56ed"
    ],
    "wof:name":"Zaoyuan",
    "wof:placetype":"locality"
},
  "geometry": {"coordinates":[119.18746000000002,29.37906],"type":"Point"}
}