{
  "type": "Feature",
  "properties": {
    "gn:admin1_code":"29",
    "gn:asciiname":"Xiaopuhe",
    "gn:country_code":"CN",
    "gn:dem":1894,
    "gn:feature_class":"P",
    "gn:feature_code":"PPL",
    "gn:name":"Xiaopuhe",
    "gn:population":0,
    "gn:timezone":"Asia/Shanghai",
    "iso:country":"CN",
    "name:zho_x_preferred":[
        "\u5c0f\u666e\u6cb3"
    ],
    "wof:name":"Xiaopuhe",
    "wof:placetype":"locality"
},
  "geometry": {"coordinates":[102.571,24.8835],"type":"Point"}
}