{
  "type": "Feature",
  "properties": {
    "gn:admin1_code":"12.0",
    "gn:asciiname":"Honghe",
    "gn:country_code":"CN",
    "gn:dem":2120,
    "gn:feature_class":"P",
    "gn:feature_code":"PPL",
    "gn:name":"Honghe",
    "gn:population":0,
    "gn:timezone":"Asia/Shanghai",
    "iso:country":"CN",
    "name:zho_x_preferred":[
        "\u7ea2\u6cb3"
    ],
    "wof:name":"Honghe",
    "wof:placetype":"locality"
},
  "geometry": {"coordinates":[110.4624,31.66495],"type":"Point"}
}