{
  "type": "Feature",
  "properties": {
    "gn:admin1_code":"7.0",
    "gn:asciiname":"Panqi",
    "gn:country_code":"CN",
    "gn:dem":574,
    "gn:feature_class":"P",
    "gn:feature_code":"PPL",
    "gn:name":"Panqi",
    "gn:population":0,
    "gn:timezone":"Asia/Shanghai",
    "iso:country":"CN",
    "name:und_x_variant":[
        "\u76d8\u5898"
    ],
    "wof:name":"Panqi",
    "wof:placetype":"locality"
},
  "geometry": {"coordinates":[118.03829,26.37166],"type":"Point"}
}