{
  "type": "Feature",
  "properties": {
    "gn:admin1_code":"11.0",
    "gn:asciiname":"Zheguyan",
    "gn:country_code":"CN",
    "gn:dem":558,
    "gn:feature_class":"P",
    "gn:feature_code":"PPL",
    "gn:name":"Zheguyan",
    "gn:population":0,
    "gn:timezone":"Asia/Shanghai",
    "iso:country":"CN",
    "name:zho_x_preferred":[
        "\u906e\u9aa8\u5ca9"
    ],
    "wof:name":"Zheguyan",
    "wof:placetype":"locality"
},
  "geometry": {"coordinates":[109.79375,29.08962],"type":"Point"}
}