{
  "type": "Feature",
  "properties": {
    "gn:admin1_code":"29.0",
    "gn:asciiname":"Dachizhang",
    "gn:country_code":"CN",
    "gn:dem":2011,
    "gn:feature_class":"P",
    "gn:feature_code":"PPL",
    "gn:name":"Dachizhang",
    "gn:population":0,
    "gn:timezone":"Asia/Shanghai",
    "iso:country":"CN",
    "name:zho_x_preferred":[
        "\u5927\u8d64\u7ae0"
    ],
    "wof:name":"Dachizhang",
    "wof:placetype":"locality"
},
  "geometry": {"coordinates":[103.696,25.7967],"type":"Point"}
}