{
  "type": "Feature",
  "properties": {
    "gn:admin1_code":"1.0",
    "gn:asciiname":"Donghu",
    "gn:country_code":"CN",
    "gn:dem":22,
    "gn:feature_class":"P",
    "gn:feature_code":"PPL",
    "gn:name":"Donghu",
    "gn:population":0,
    "gn:timezone":"Asia/Shanghai",
    "iso:country":"CN",
    "name:ceb_x_preferred":[
        "Donghu"
    ],
    "name:deu_x_preferred":[
        "Donghu"
    ],
    "name:fra_x_preferred":[
        "Donghu"
    ],
    "name:zho_x_preferred":[
        "\u4e1c\u6e56"
    ],
    "wof:name":"Donghu",
    "wof:placetype":"locality"
},
  "geometry": {"coordinates":[118.39153,31.85181],"type":"Point"}
}