{
  "type": "Feature",
  "properties": {
    "gn:admin1_code":"19.0",
    "gn:asciiname":"Anzishancun",
    "gn:country_code":"CN",
    "gn:dem":38,
    "gn:feature_class":"P",
    "gn:feature_code":"PPL",
    "gn:name":"Anzishancun",
    "gn:population":0,
    "gn:timezone":"Asia/Shanghai",
    "iso:country":"CN",
    "name:zho_x_preferred":[
        "\u5b89\u5b50\u5c71\u6751"
    ],
    "wof:name":"Anzishancun",
    "wof:placetype":"locality"
},
  "geometry": {"coordinates":[121.1172,40.93632],"type":"Point"}
}