{
  "type": "Feature",
  "properties": {
    "gn:admin1_code":"19.0",
    "gn:asciiname":"Houxinfabu",
    "gn:country_code":"CN",
    "gn:dem":81,
    "gn:feature_class":"P",
    "gn:feature_code":"PPL",
    "gn:name":"Houxinfabu",
    "gn:population":0,
    "gn:timezone":"Asia/Shanghai",
    "iso:country":"CN",
    "name:und_x_variant":[
        "Houxinfabao",
        "Houxinfabu"
    ],
    "name:zho_x_preferred":[
        "\u540e\u65b0\u53d1\u5821"
    ],
    "wof:name":"Houxinfabu",
    "wof:placetype":"locality"
},
  "geometry": {"coordinates":[123.58201,42.78848],"type":"Point"}
}