{
  "type": "Feature",
  "properties": {
    "gn:admin1_code":"12.0",
    "gn:asciiname":"Shanxiazheng",
    "gn:country_code":"CN",
    "gn:dem":141,
    "gn:feature_class":"P",
    "gn:feature_code":"PPL",
    "gn:name":"Shanxiazheng",
    "gn:population":0,
    "gn:timezone":"Asia/Shanghai",
    "iso:country":"CN",
    "name:zho_x_preferred":[
        "Shanxiazheng"
    ],
    "name:zho_x_variant":[
        "\u5c71\u4e0b\u90d1"
    ],
    "wof:name":"Shanxiazheng",
    "wof:placetype":"locality"
},
  "geometry": {"coordinates":[114.74111000000001,29.91091],"type":"Point"}
}