{
  "type": "Feature",
  "properties": {
    "gn:admin1_code":"4.0",
    "gn:asciiname":"Dashengxu",
    "gn:country_code":"CN",
    "gn:dem":3,
    "gn:feature_class":"P",
    "gn:feature_code":"PPL",
    "gn:name":"Dashengxu",
    "gn:population":0,
    "gn:timezone":"Asia/Shanghai",
    "iso:country":"CN",
    "name:zho_x_preferred":[
        "\u5927\u751f\u5729"
    ],
    "wof:name":"Dashengxu",
    "wof:placetype":"locality"
},
  "geometry": {"coordinates":[120.50270999999999,32.00459],"type":"Point"}
}