{
  "type": "Feature",
  "properties": {
    "gn:admin1_code":"7.0",
    "gn:asciiname":"Xiaojiangfang",
    "gn:country_code":"CN",
    "gn:dem":213,
    "gn:feature_class":"P",
    "gn:feature_code":"PPL",
    "gn:name":"Xiaojiangfang",
    "gn:population":0,
    "gn:timezone":"Asia/Shanghai",
    "iso:country":"CN",
    "name:und_x_variant":[
        "\u5c0f\u6c5f\u574a"
    ],
    "name:zho_x_preferred":[
        "\u5c0f\u6c5f\u574a"
    ],
    "wof:name":"Xiaojiangfang",
    "wof:placetype":"locality"
},
  "geometry": {"coordinates":[117.14903,26.0529],"type":"Point"}
}