{
  "type": "Feature",
  "properties": {
    "gn:admin1_code":"32.0",
    "gn:asciiname":"Padu",
    "gn:country_code":"CN",
    "gn:dem":2501,
    "gn:feature_class":"P",
    "gn:feature_code":"PPL",
    "gn:name":"Padu",
    "gn:population":0,
    "gn:timezone":"Asia/Shanghai",
    "iso:country":"CN",
    "name:est_x_preferred":[
        "Padu"
    ],
    "name:hye_x_preferred":[
        "\u054a\u0561\u0564\u0578\u0582"
    ],
    "name:pol_x_preferred":[
        "Padu"
    ],
    "name:vol_x_preferred":[
        "Padu"
    ],
    "name:zho_x_preferred":[
        "\u5e15\u90fd"
    ],
    "wof:name":"Padu",
    "wof:placetype":"locality"
},
  "geometry": {"coordinates":[103.20999999999999,28.387],"type":"Point"}
}