{
  "type": "Feature",
  "properties": {
    "gn:admin1_code":"19",
    "gn:asciiname":"Nianzigou",
    "gn:country_code":"CN",
    "gn:dem":651,
    "gn:feature_class":"P",
    "gn:feature_code":"PPL",
    "gn:name":"Nianzigou",
    "gn:population":0,
    "gn:timezone":"Asia/Shanghai",
    "iso:country":"CN",
    "wof:name":"Nianzigou",
    "wof:placetype":"locality"
},
  "geometry": {"coordinates":[119.67333000000001,40.75222],"type":"Point"}
}