{
  "type": "Feature",
  "properties": {
    "gn:admin1_code":"12.0",
    "gn:asciiname":"Dawang Shanke",
    "gn:country_code":"CN",
    "gn:dem":28,
    "gn:feature_class":"P",
    "gn:feature_code":"PPL",
    "gn:name":"Dawang Shanke",
    "gn:population":0,
    "gn:timezone":"Asia/Shanghai",
    "iso:country":"CN",
    "name:zho_x_preferred":[
        "\u5927\u738b\u5c71\u67ef"
    ],
    "wof:name":"Dawang Shanke",
    "wof:placetype":"locality"
},
  "geometry": {"coordinates":[115.10601,30.04792],"type":"Point"}
}