{
  "type": "Feature",
  "properties": {
    "gn:admin1_code":"29",
    "gn:asciiname":"Jiulong",
    "gn:country_code":"CN",
    "gn:dem":1818,
    "gn:feature_class":"P",
    "gn:feature_code":"PPL",
    "gn:name":"Jiulong",
    "gn:population":0,
    "gn:timezone":"Asia/Shanghai",
    "iso:country":"CN",
    "name:ceb_x_preferred":[
        "Jiulong"
    ],
    "name:deu_x_preferred":[
        "Jiulong"
    ],
    "name:fra_x_preferred":[
        "Jiulong"
    ],
    "name:nor_x_preferred":[
        "Jiulong"
    ],
    "name:swe_x_preferred":[
        "Jiulong"
    ],
    "name:vie_x_preferred":[
        "C\u1eedu Long"
    ],
    "name:zho_x_preferred":[
        "\u4e5d\u9f99"
    ],
    "name:zho_x_variant":[
        "\u4e5d\u9f8d"
    ],
    "wof:name":"Jiulong",
    "wof:placetype":"locality"
},
  "geometry": {"coordinates":[102.151,24.2674],"type":"Point"}
}