{
  "type": "Feature",
  "properties": {
    "gn:admin1_code":"3.0",
    "gn:asciiname":"Cengkeng",
    "gn:country_code":"CN",
    "gn:dem":336,
    "gn:feature_class":"P",
    "gn:feature_code":"PPL",
    "gn:name":"Cengkeng",
    "gn:population":0,
    "gn:timezone":"Asia/Shanghai",
    "iso:country":"CN",
    "name:und_x_variant":[
        "\u5c42\u5751"
    ],
    "wof:name":"Cengkeng",
    "wof:placetype":"locality"
},
  "geometry": {"coordinates":[115.82832000000001,26.79912],"type":"Point"}
}