{
  "type": "Feature",
  "properties": {
    "gn:admin1_code":"30.0",
    "gn:asciiname":"Fulaiwei",
    "gn:country_code":"CN",
    "gn:dem":60,
    "gn:feature_class":"P",
    "gn:feature_code":"PPL",
    "gn:name":"Fulaiwei",
    "gn:population":0,
    "gn:timezone":"Asia/Shanghai",
    "iso:country":"CN",
    "name:zho_x_preferred":[
        "\u6276\u8d56\u56f4"
    ],
    "wof:name":"Fulaiwei",
    "wof:placetype":"locality"
},
  "geometry": {"coordinates":[112.10114,23.39083],"type":"Point"}
}