{
  "type": "Feature",
  "properties": {
    "gn:admin1_code":"1.0",
    "gn:asciiname":"Wangdacun",
    "gn:country_code":"CN",
    "gn:dem":34,
    "gn:feature_class":"P",
    "gn:feature_code":"PPL",
    "gn:name":"Wangdacun",
    "gn:population":0,
    "gn:timezone":"Asia/Shanghai",
    "iso:country":"CN",
    "name:und_x_variant":[
        "Wangdazhuang"
    ],
    "name:zho_x_preferred":[
        "\u738b\u5927\u6751"
    ],
    "wof:name":"Wangdacun",
    "wof:placetype":"locality"
},
  "geometry": {"coordinates":[115.98333,33.56667],"type":"Point"}
}