{
  "type": "Feature",
  "properties": {
    "gn:admin1_code":"32",
    "gn:asciiname":"Fubian",
    "gn:country_code":"CN",
    "gn:dem":2816,
    "gn:feature_class":"P",
    "gn:feature_code":"PPL",
    "gn:name":"Fubian",
    "gn:population":0,
    "gn:timezone":"Asia/Shanghai",
    "iso:country":"CN",
    "name:und_x_variant":[
        "Pupientun",
        "Fu-pien-t\u2019un",
        "Fu-pien",
        "Fubian"
    ],
    "name:zho_x_preferred":[
        "\u629a\u8fb9"
    ],
    "wof:name":"Fubian",
    "wof:placetype":"locality"
},
  "geometry": {"coordinates":[102.47694,31.28489],"type":"Point"}
}