{
  "type": "Feature",
  "properties": {
    "gn:admin1_code":"4.0",
    "gn:asciiname":"Sanzhexu",
    "gn:country_code":"CN",
    "gn:dem":4,
    "gn:feature_class":"P",
    "gn:feature_code":"PPL",
    "gn:name":"Sanzhexu",
    "gn:population":0,
    "gn:timezone":"Asia/Shanghai",
    "iso:country":"CN",
    "name:zho_x_preferred":[
        "\u4e09\u6298\u5729"
    ],
    "wof:name":"Sanzhexu",
    "wof:placetype":"locality"
},
  "geometry": {"coordinates":[120.35894999999999,32.01485],"type":"Point"}
}