{
  "type": "Feature",
  "properties": {
    "gn:admin1_code":"21.0",
    "gn:asciiname":"Yushu Taizi",
    "gn:country_code":"CN",
    "gn:dem":1317,
    "gn:feature_class":"P",
    "gn:feature_code":"PPL",
    "gn:name":"Yushu Taizi",
    "gn:population":0,
    "gn:timezone":"Asia/Shanghai",
    "iso:country":"CN",
    "name:zho_x_preferred":[
        "\u6986\u6811\u53f0\u5b50"
    ],
    "wof:name":"Yushu Taizi",
    "wof:placetype":"locality"
},
  "geometry": {"coordinates":[104.82599999999999,37.3878],"type":"Point"}
}