{
  "type": "Feature",
  "properties": {
    "gn:admin1_code":"15.0",
    "gn:asciiname":"Heiyemiao",
    "gn:country_code":"CN",
    "gn:dem":2125,
    "gn:feature_class":"P",
    "gn:feature_code":"PPL",
    "gn:name":"Heiyemiao",
    "gn:population":0,
    "gn:timezone":"Asia/Shanghai",
    "iso:country":"CN",
    "name:zho_x_preferred":[
        "\u9ed1\u7237\u5e99"
    ],
    "wof:name":"Heiyemiao",
    "wof:placetype":"locality"
},
  "geometry": {"coordinates":[104.26900000000001,35.0479],"type":"Point"}
}