{
  "type": "Feature",
  "properties": {
    "gn:admin1_code":"30.0",
    "gn:asciiname":"Makengkou",
    "gn:country_code":"CN",
    "gn:dem":198,
    "gn:feature_class":"P",
    "gn:feature_code":"PPL",
    "gn:name":"Makengkou",
    "gn:population":0,
    "gn:timezone":"Asia/Urumqi",
    "iso:country":"CN",
    "name:zho_x_preferred":[
        "\u9a6c\u5751\u53e3"
    ],
    "wof:name":"Makengkou",
    "wof:placetype":"locality"
},
  "geometry": {"coordinates":[110.86393,22.37462],"type":"Point"}
}