{
  "type": "Feature",
  "properties": {
    "gn:admin1_code":"8.0",
    "gn:asciiname":"Xinrongcun",
    "gn:country_code":"CN",
    "gn:dem":276,
    "gn:feature_class":"P",
    "gn:feature_code":"PPL",
    "gn:name":"Xinrongcun",
    "gn:population":0,
    "gn:timezone":"Asia/Shanghai",
    "iso:country":"CN",
    "name:zho_x_preferred":[
        "\u65b0\u8363\u6751"
    ],
    "wof:name":"Xinrongcun",
    "wof:placetype":"locality"
},
  "geometry": {"coordinates":[125.4406,48.1046],"type":"Point"}
}