{
  "type": "Feature",
  "properties": {
    "gn:admin1_code":"19.0",
    "gn:asciiname":"Dazhangzi",
    "gn:country_code":"CN",
    "gn:dem":469,
    "gn:feature_class":"P",
    "gn:feature_code":"PPL",
    "gn:name":"Dazhangzi",
    "gn:population":0,
    "gn:timezone":"Asia/Shanghai",
    "iso:country":"CN",
    "name:zho_x_preferred":[
        "\u5927\u6756\u5b50"
    ],
    "wof:name":"Dazhangzi",
    "wof:placetype":"locality"
},
  "geometry": {"coordinates":[119.33664,41.27601],"type":"Point"}
}