{
  "type": "Feature",
  "properties": {
    "iso:country":"CN",
    "qs:name":"\u5357\u6d77\u533a",
    "qs:name_adm0":"\u4e2d\u570b",
    "qs:name_adm1":"\u5e7f\u4e1c\u7701",
    "qs:photos":194,
    "qs:photos_1k":39,
    "qs:photos_9k":3,
    "qs:photos_9r":5,
    "qs:photos_all":631,
    "qs:photos_sr":4,
    "qs:placetype":"LocalAdmin",
    "qs:pop_sr":"0",
    "wd:wordcount":304,
    "wof:name":"\u5357\u6d77\u533a",
    "wof:placetype":"localadmin"
},
  "geometry": {"coordinates":[113.168792,23.098681],"type":"Point"}
}