{
  "type": "Feature",
  "properties": {
    "iso:country":"CN",
    "name:ara_x_preferred":[
        "\u0645\u0642\u0627\u0637\u0639\u0629 \u0646\u0627\u0646\u0647\u0627\u064a"
    ],
    "name:ceb_x_preferred":[
        "Nanhai District"
    ],
    "name:ces_x_preferred":[
        "Nan-chaj"
    ],
    "name:cym_x_preferred":[
        "Ardal Nanhai"
    ],
    "name:deu_x_preferred":[
        "Nanhai"
    ],
    "name:eng_x_preferred":[
        "Nanhai District"
    ],
    "name:fas_x_preferred":[
        "\u0646\u0627\u0646\u0647\u0627\u06cc"
    ],
    "name:fin_x_preferred":[
        "Nanhain kaupunkialue"
    ],
    "name:gan_x_preferred":[
        "\u5357\u6d77\u533a"
    ],
    "name:hak_x_preferred":[
        "N\u00e0m-h\u00f3i-kh\u00ee"
    ],
    "name:ind_x_preferred":[
        "Distrik Nanhai"
    ],
    "name:jpn_x_preferred":[
        "\u5357\u6d77\u533a"
    ],
    "name:kor_x_preferred":[
        "\ub09c\ud558\uc774\uad6c"
    ],
    "name:mwl_x_preferred":[
        "Nanhai"
    ],
    "name:nan_x_preferred":[
        "L\u00e2m-h\u00e1i-khu"
    ],
    "name:nld_x_preferred":[
        "Nanhai"
    ],
    "name:nob_x_preferred":[
        "Nanhai"
    ],
    "name:rus_x_preferred":[
        "\u041d\u0430\u043d\u044c\u0445\u0430\u0439"
    ],
    "name:spa_x_preferred":[
        "Nanhai"
    ],
    "name:swe_x_preferred":[
        "Nanhai"
    ],
    "name:urd_x_preferred":[
        "\u0646\u0627\u0646 \u06c1\u0627\u0626\u06cc"
    ],
    "name:vie_x_preferred":[
        "Nam H\u1ea3i"
    ],
    "name:wuu_x_preferred":[
        "\u5357\u6d77\u533a"
    ],
    "name:yue_x_preferred":[
        "\u5357\u6d77"
    ],
    "name:zho_x_preferred":[
        "\u5357\u6d77\u533a"
    ],
    "qs:name":"\u5357\u6d77\u533a",
    "qs:name_adm0":"\u4e2d\u570b",
    "qs:name_adm1":"\u5e7f\u4e1c\u7701",
    "qs:photos":194,
    "qs:photos_1k":39,
    "qs:photos_9k":3,
    "qs:photos_9r":5,
    "qs:photos_all":631,
    "qs:photos_sr":4,
    "qs:placetype":"LocalAdmin",
    "qs:pop_sr":"0",
    "wd:wordcount":304,
    "wof:name":"\u5357\u6d77\u533a",
    "wof:placetype":"localadmin"
},
  "geometry": {"coordinates":[113.168792,23.098681],"type":"Point"}
}