{
  "type": "Feature",
  "properties": {
    "gn:admin1_code":"4.0",
    "gn:asciiname":"Zhaozhuang",
    "gn:cc2":"CN",
    "gn:country_code":"CN",
    "gn:dem":41,
    "gn:feature_class":"P",
    "gn:feature_code":"PPL",
    "gn:name":"Zhaozhuang",
    "gn:population":0,
    "gn:timezone":"Asia/Shanghai",
    "iso:country":"CN",
    "name:und_x_variant":[
        "Chao-chuang",
        "Chao-chuang-chi",
        "Zhaozhuang"
    ],
    "wof:name":"Zhaozhuang",
    "wof:placetype":"locality"
},
  "geometry": {"coordinates":[116.46138999999999,34.73361],"type":"Point"}
}