{
  "type": "Feature",
  "properties": {
    "gn:admin1_code":"30",
    "gn:asciiname":"Gutang",
    "gn:country_code":"CN",
    "gn:dem":161,
    "gn:feature_class":"P",
    "gn:feature_code":"PPL",
    "gn:name":"Gutang",
    "gn:population":0,
    "gn:timezone":"Asia/Urumqi",
    "iso:country":"CN",
    "name:zho_x_preferred":[
        "\u53e4\u5858"
    ],
    "wof:name":"Gutang",
    "wof:placetype":"locality"
},
  "geometry": {"coordinates":[111.18828999999999,22.1135],"type":"Point"}
}