{
  "type": "Feature",
  "properties": {
    "gn:admin1_code":"29.0",
    "gn:asciiname":"Yabazhai",
    "gn:country_code":"CN",
    "gn:dem":1417,
    "gn:feature_class":"P",
    "gn:feature_code":"PPL",
    "gn:name":"Yabazhai",
    "gn:population":0,
    "gn:timezone":"Asia/Shanghai",
    "iso:country":"CN",
    "name:zho_x_preferred":[
        "\u4e2b\u5df4\u5be8"
    ],
    "wof:name":"Yabazhai",
    "wof:placetype":"locality"
},
  "geometry": {"coordinates":[104.709,25.1745],"type":"Point"}
}