{
  "type": "Feature",
  "properties": {
    "gn:admin1_code":"20.0",
    "gn:asciiname":"Laodongdian",
    "gn:country_code":"CN",
    "gn:dem":261,
    "gn:feature_class":"P",
    "gn:feature_code":"PPL",
    "gn:name":"Laodongdian",
    "gn:population":0,
    "gn:timezone":"Asia/Shanghai",
    "iso:country":"CN",
    "name:zho_x_preferred":[
        "\u8001\u8463\u70b9"
    ],
    "wof:name":"Laodongdian",
    "wof:placetype":"locality"
},
  "geometry": {"coordinates":[125.19331,49.80668],"type":"Point"}
}