{
  "type": "Feature",
  "properties": {
    "gn:admin1_code":"2.0",
    "gn:asciiname":"Huangjia Muqiao",
    "gn:country_code":"CN",
    "gn:dem":8,
    "gn:feature_class":"P",
    "gn:feature_code":"PPL",
    "gn:name":"Huangjia Muqiao",
    "gn:population":0,
    "gn:timezone":"Asia/Shanghai",
    "iso:country":"CN",
    "name:und_x_variant":[
        "\u9ec4\u5bb6\u6728\u6865"
    ],
    "wof:name":"Huangjia Muqiao",
    "wof:placetype":"locality"
},
  "geometry": {"coordinates":[120.63511,30.55551],"type":"Point"}
}