{
  "type": "Feature",
  "properties": {
    "gn:admin1_code":"07",
    "gn:asciiname":"Cangtou",
    "gn:country_code":"CN",
    "gn:dem":263,
    "gn:feature_class":"P",
    "gn:feature_code":"PPL",
    "gn:name":"Cangtou",
    "gn:population":0,
    "gn:timezone":"Asia/Shanghai",
    "iso:country":"CN",
    "name:und_x_variant":[
        "Cangtouli",
        "Cangtou"
    ],
    "name:zho_x_preferred":[
        "\u82cd\u5934"
    ],
    "wof:name":"Cangtou",
    "wof:placetype":"locality"
},
  "geometry": {"coordinates":[120.30229,27.18966],"type":"Point"}
}