{
  "type": "Feature",
  "properties": {
    "gn:admin1_code":"8.0",
    "gn:asciiname":"Fuqiang Jingyingsuo",
    "gn:country_code":"CN",
    "gn:dem":241,
    "gn:feature_class":"P",
    "gn:feature_code":"PPLF",
    "gn:name":"Fuqiang Jingyingsuo",
    "gn:population":0,
    "gn:timezone":"Asia/Shanghai",
    "iso:country":"CN",
    "name:zho_x_preferred":[
        "\u5bcc\u5f3a\u7ecf\u8425\u6240"
    ],
    "wof:name":"Fuqiang Jingyingsuo",
    "wof:placetype":"locality"
},
  "geometry": {"coordinates":[129.45318,48.8365],"type":"Point"}
}