{
  "type": "Feature",
  "properties": {
    "gn:admin1_code":"14.0",
    "gn:asciiname":"Yigongbaicun",
    "gn:country_code":"CN",
    "gn:dem":1872,
    "gn:feature_class":"P",
    "gn:feature_code":"PPL",
    "gn:name":"Yigongbaicun",
    "gn:population":0,
    "gn:timezone":"Asia/Urumqi",
    "iso:country":"CN",
    "name:zho_x_preferred":[
        "\u6613\u516c\u767d\u6751"
    ],
    "wof:name":"Yigongbaicun",
    "wof:placetype":"locality"
},
  "geometry": {"coordinates":[95.18097,29.29428],"type":"Point"}
}