{
  "type": "Feature",
  "properties": {
    "gn:admin1_code":"9.0",
    "gn:asciiname":"Yichang",
    "gn:country_code":"CN",
    "gn:dem":189,
    "gn:feature_class":"P",
    "gn:feature_code":"PPL",
    "gn:name":"Yichang",
    "gn:population":0,
    "gn:timezone":"Asia/Shanghai",
    "iso:country":"CN",
    "name:afr_x_preferred":[
        "Yichang"
    ],
    "name:ara_x_preferred":[
        "\u064a\u064a\u062a\u0634\u0627\u0646\u063a"
    ],
    "name:bul_x_preferred":[
        "\u0418\u0447\u0430\u043d"
    ],
    "name:cdo_x_preferred":[
        "Ng\u00ec-chi\u014fng"
    ],
    "name:ceb_x_preferred":[
        "Yichang"
    ],
    "name:ces_x_preferred":[
        "I-\u010dchang"
    ],
    "name:cym_x_preferred":[
        "Yichang"
    ],
    "name:dan_x_preferred":[
        "Yichang"
    ],
    "name:deu_x_preferred":[
        "Yichang"
    ],
    "name:epo_x_preferred":[
        "Ji\u0109ang"
    ],
    "name:eus_x_preferred":[
        "Yichang"
    ],
    "name:fas_x_preferred":[
        "\u0627\u06cc\u0686\u0627\u0646\u06af"
    ],
    "name:fin_x_preferred":[
        "Yichang"
    ],
    "name:fra_x_preferred":[
        "Yichang"
    ],
    "name:ind_x_preferred":[
        "Yichang"
    ],
    "name:ita_x_preferred":[
        "Yichang"
    ],
    "name:jpn_x_preferred":[
        "\u5b9c\u660c\u5e02"
    ],
    "name:kik_x_preferred":[
        "Yichang"
    ],
    "name:kor_x_preferred":[
        "\uc774\ucc3d\uc2dc"
    ],
    "name:mlg_x_preferred":[
        "Yichang"
    ],
    "name:nld_x_preferred":[
        "Yichang"
    ],
    "name:nno_x_preferred":[
        "Yichang"
    ],
    "name:nor_x_preferred":[
        "Yichang"
    ],
    "name:pam_x_preferred":[
        "Yichang"
    ],
    "name:pol_x_preferred":[
        "Yichang"
    ],
    "name:por_x_preferred":[
        "Yichang"
    ],
    "name:rus_x_preferred":[
        "\u0418\u0447\u0430\u043d"
    ],
    "name:spa_x_preferred":[
        "Yichang"
    ],
    "name:srp_x_preferred":[
        "\u0408\u0438\u0447\u0430\u043d\u0433"
    ],
    "name:swe_x_preferred":[
        "Yichang"
    ],
    "name:tgl_x_preferred":[
        "Yichang"
    ],
    "name:tur_x_preferred":[
        "Yichang"
    ],
    "name:ukr_x_preferred":[
        "\u0406\u0447\u0430\u043d"
    ],
    "name:urd_x_preferred":[
        "\u06cc\u0686\u0646\u06af"
    ],
    "name:vep_x_preferred":[
        "I\u010dan"
    ],
    "name:vie_x_preferred":[
        "Nghi X\u01b0\u01a1ng"
    ],
    "name:war_x_preferred":[
        "Yichang"
    ],
    "name:wuu_x_preferred":[
        "\u5b9c\u660c\u5e02"
    ],
    "name:zho_x_preferred":[
        "\u4e00\u573a"
    ],
    "name:zho_x_variant":[
        "\u5b9c\u660c\u5e02"
    ],
    "wof:name":"Yichang",
    "wof:placetype":"locality"
},
  "geometry": {"coordinates":[112.90913999999999,34.13735],"type":"Point"}
}