{
  "type": "Feature",
  "properties": {
    "gn:admin1_code":"32.0",
    "gn:asciiname":"Xingsheng",
    "gn:country_code":"CN",
    "gn:dem":540,
    "gn:feature_class":"P",
    "gn:feature_code":"PPL",
    "gn:name":"Xingsheng",
    "gn:population":0,
    "gn:timezone":"Asia/Shanghai",
    "iso:country":"CN",
    "name:zho_x_preferred":[
        "\u5174\u76db"
    ],
    "wof:name":"Xingsheng",
    "wof:placetype":"locality"
},
  "geometry": {"coordinates":[103.99733999999999,30.23434],"type":"Point"}
}