{
  "type": "Feature",
  "properties": {
    "gn:admin1_code":"21.0",
    "gn:asciiname":"Wanglejing Xigou",
    "gn:country_code":"CN",
    "gn:dem":1575,
    "gn:feature_class":"P",
    "gn:feature_code":"PPL",
    "gn:name":"Wanglejing Xigou",
    "gn:population":0,
    "gn:timezone":"Asia/Shanghai",
    "iso:country":"CN",
    "name:zho_x_preferred":[
        "\u738b\u4e50\u4e95\u897f\u6c9f"
    ],
    "wof:name":"Wanglejing Xigou",
    "wof:placetype":"locality"
},
  "geometry": {"coordinates":[107.145,37.7885],"type":"Point"}
}