{
  "type": "Feature",
  "properties": {
    "gn:admin1_code":"21.0",
    "gn:asciiname":"Shuangqu Wudui",
    "gn:country_code":"CN",
    "gn:dem":1097,
    "gn:feature_class":"P",
    "gn:feature_code":"PPLF",
    "gn:name":"Shuangqu Wudui",
    "gn:population":0,
    "gn:timezone":"Asia/Shanghai",
    "iso:country":"CN",
    "name:zho_x_preferred":[
        "\u53cc\u6e20\u4e94\u961f"
    ],
    "wof:name":"Shuangqu Wudui",
    "wof:placetype":"locality"
},
  "geometry": {"coordinates":[106.658,38.9448],"type":"Point"}
}