{
  "type": "Feature",
  "properties": {
    "gn:admin1_code":"8.0",
    "gn:asciiname":"Ershihao",
    "gn:country_code":"CN",
    "gn:dem":153,
    "gn:feature_class":"P",
    "gn:feature_code":"PPLF",
    "gn:name":"Ershihao",
    "gn:population":0,
    "gn:timezone":"Asia/Shanghai",
    "iso:country":"CN",
    "name:zho_x_preferred":[
        "\u4e8c\u5341\u53f7"
    ],
    "wof:name":"Ershihao",
    "wof:placetype":"locality"
},
  "geometry": {"coordinates":[124.88209000000001,47.12116],"type":"Point"}
}