{
  "type": "Feature",
  "properties": {
    "gn:admin1_code":"26.0",
    "gn:asciiname":"Xiwancun",
    "gn:country_code":"CN",
    "gn:dem":350,
    "gn:feature_class":"P",
    "gn:feature_code":"PPL",
    "gn:name":"Xiwancun",
    "gn:population":0,
    "gn:timezone":"Asia/Shanghai",
    "iso:country":"CN",
    "name:zho_x_preferred":[
        "\u897f\u6e7e\u6751"
    ],
    "wof:name":"Xiwancun",
    "wof:placetype":"locality"
},
  "geometry": {"coordinates":[109.73779,34.84650999999999],"type":"Point"}
}