{
  "type": "Feature",
  "properties": {
    "gn:admin1_code":"25",
    "gn:asciiname":"Qianfoshan",
    "gn:country_code":"CN",
    "gn:dem":245,
    "gn:feature_class":"P",
    "gn:feature_code":"PPL",
    "gn:name":"Qianfoshan",
    "gn:population":0,
    "gn:timezone":"Asia/Shanghai",
    "iso:country":"CN",
    "name:zho_x_preferred":[
        "\u5343\u4f5b\u5c71"
    ],
    "wof:name":"Qianfoshan",
    "wof:placetype":"locality"
},
  "geometry": {"coordinates":[117.029,36.6364],"type":"Point"}
}