{
  "type": "Feature",
  "properties": {
    "gn:admin1_code":"26.0",
    "gn:asciiname":"Jintuncun",
    "gn:country_code":"CN",
    "gn:dem":1090,
    "gn:feature_class":"P",
    "gn:feature_code":"PPL",
    "gn:name":"Jintuncun",
    "gn:population":0,
    "gn:timezone":"Asia/Shanghai",
    "iso:country":"CN",
    "name:zho_x_preferred":[
        "\u91d1\u5c6f\u6751"
    ],
    "wof:name":"Jintuncun",
    "wof:placetype":"locality"
},
  "geometry": {"coordinates":[109.77981,36.41887],"type":"Point"}
}