{
  "type": "Feature",
  "properties": {
    "gn:admin1_code":"31.0",
    "gn:asciiname":"Diaonancun",
    "gn:country_code":"CN",
    "gn:dem":120,
    "gn:feature_class":"P",
    "gn:feature_code":"PPL",
    "gn:name":"Diaonancun",
    "gn:population":0,
    "gn:timezone":"Asia/Shanghai",
    "iso:country":"CN",
    "name:zho_x_preferred":[
        "\u8c03\u5357\u6751"
    ],
    "wof:name":"Diaonancun",
    "wof:placetype":"locality"
},
  "geometry": {"coordinates":[109.38500000000001,19.5015],"type":"Point"}
}