{
  "type": "Feature",
  "properties": {
    "gn:admin1_code":"26.0",
    "gn:asciiname":"Dayanmaoze",
    "gn:country_code":"CN",
    "gn:dem":1140,
    "gn:feature_class":"P",
    "gn:feature_code":"PPL",
    "gn:name":"Dayanmaoze",
    "gn:population":0,
    "gn:timezone":"Asia/Shanghai",
    "iso:country":"CN",
    "name:zho_x_preferred":[
        "\u6253\u96c1\u5cc1\u5219"
    ],
    "wof:name":"Dayanmaoze",
    "wof:placetype":"locality"
},
  "geometry": {"coordinates":[109.05949,37.88955],"type":"Point"}
}