{
  "type": "Feature",
  "properties": {
    "gn:admin1_code":"11",
    "gn:asciiname":"Sanyanqiao",
    "gn:cc2":"CN",
    "gn:country_code":"CN",
    "gn:dem":95,
    "gn:feature_class":"P",
    "gn:feature_code":"PPL",
    "gn:name":"Sanyanqiao",
    "gn:population":0,
    "gn:timezone":"Asia/Shanghai",
    "iso:country":"CN",
    "name:und_x_variant":[
        "San-yen-ch\u2019iao",
        "Sanyanqiao"
    ],
    "wof:name":"Sanyanqiao",
    "wof:placetype":"locality"
},
  "geometry": {"coordinates":[113.71666999999999,28.66667],"type":"Point"}
}