{
  "type": "Feature",
  "properties": {
    "gn:admin1_code":"32.0",
    "gn:asciiname":"Cajieqi",
    "gn:country_code":"CN",
    "gn:dem":4586,
    "gn:feature_class":"P",
    "gn:feature_code":"PPL",
    "gn:name":"Cajieqi",
    "gn:population":0,
    "gn:timezone":"Asia/Shanghai",
    "iso:country":"CN",
    "name:zho_x_preferred":[
        "\u64e6\u7ed3\u5176"
    ],
    "wof:name":"Cajieqi",
    "wof:placetype":"locality"
},
  "geometry": {"coordinates":[101.036,29.4891],"type":"Point"}
}