{
  "type": "Feature",
  "properties": {
    "gn:admin1_code":"4.0",
    "gn:asciiname":"Xinfu Sanzu",
    "gn:country_code":"CN",
    "gn:dem":3,
    "gn:feature_class":"P",
    "gn:feature_code":"PPLF",
    "gn:name":"Xinfu Sanzu",
    "gn:population":0,
    "gn:timezone":"Asia/Shanghai",
    "iso:country":"CN",
    "name:zho_x_preferred":[
        "Xinfu Sanzu"
    ],
    "name:zho_x_variant":[
        "\u65b0\u5bcc\u4e09\u7ec4"
    ],
    "wof:name":"Xinfu Sanzu",
    "wof:placetype":"locality"
},
  "geometry": {"coordinates":[121.22596,32.09448],"type":"Point"}
}