{
  "type": "Feature",
  "properties": {
    "gn:admin1_code":"4.0",
    "gn:asciiname":"Xuqin",
    "gn:country_code":"CN",
    "gn:dem":4,
    "gn:feature_class":"P",
    "gn:feature_code":"PPL",
    "gn:name":"Xuqin",
    "gn:population":0,
    "gn:timezone":"Asia/Shanghai",
    "iso:country":"CN",
    "name:zho_x_preferred":[
        "Xuqin"
    ],
    "name:zho_x_variant":[
        "\u8bb8\u79e6"
    ],
    "wof:name":"Xuqin",
    "wof:placetype":"locality"
},
  "geometry": {"coordinates":[119.72228,33.00356],"type":"Point"}
}