{
  "type": "Feature",
  "properties": {
    "gn:admin1_code":"11.0",
    "gn:asciiname":"Xiangzikou Zhaojia",
    "gn:country_code":"CN",
    "gn:dem":109,
    "gn:feature_class":"P",
    "gn:feature_code":"PPL",
    "gn:name":"Xiangzikou Zhaojia",
    "gn:population":0,
    "gn:timezone":"Asia/Shanghai",
    "iso:country":"CN",
    "name:zho_x_preferred":[
        "\u5df7\u5b50\u53e3\u8d75\u5bb6"
    ],
    "wof:name":"Xiangzikou Zhaojia",
    "wof:placetype":"locality"
},
  "geometry": {"coordinates":[111.83280999999999,26.37735],"type":"Point"}
}