{
  "type": "Feature",
  "properties": {
    "gn:admin1_code":"10.0",
    "gn:asciiname":"Jiemahe",
    "gn:country_code":"CN",
    "gn:dem":9,
    "gn:feature_class":"P",
    "gn:feature_code":"PPL",
    "gn:name":"Jiemahe",
    "gn:population":0,
    "gn:timezone":"Asia/Shanghai",
    "iso:country":"CN",
    "name:zho_x_preferred":[
        "\u4ecb\u9a6c\u6cb3"
    ],
    "wof:name":"Jiemahe",
    "wof:placetype":"locality"
},
  "geometry": {"coordinates":[118.81189999999999,39.32346],"type":"Point"}
}