{
  "type": "Feature",
  "properties": {
    "gn:admin1_code":"1.0",
    "gn:asciiname":"Daluozhuang",
    "gn:country_code":"CN",
    "gn:dem":42,
    "gn:feature_class":"P",
    "gn:feature_code":"PPL",
    "gn:name":"Daluozhuang",
    "gn:population":0,
    "gn:timezone":"Asia/Shanghai",
    "iso:country":"CN",
    "name:zho_x_preferred":[
        "\u5927\u7f57\u5e84"
    ],
    "wof:name":"Daluozhuang",
    "wof:placetype":"locality"
},
  "geometry": {"coordinates":[118.63097,32.6386],"type":"Point"}
}