{
  "type": "Feature",
  "properties": {
    "gn:admin1_code":"32.0",
    "gn:asciiname":"Baijiachong",
    "gn:country_code":"CN",
    "gn:dem":304,
    "gn:feature_class":"P",
    "gn:feature_code":"PPL",
    "gn:name":"Baijiachong",
    "gn:population":0,
    "gn:timezone":"Asia/Shanghai",
    "iso:country":"CN",
    "name:zho_x_preferred":[
        "\u767e\u5bb6\u51b2"
    ],
    "wof:name":"Baijiachong",
    "wof:placetype":"locality"
},
  "geometry": {"coordinates":[104.92700000000001,29.0977],"type":"Point"}
}