{
  "type": "Feature",
  "properties": {
    "gn:admin1_code":"32.0",
    "gn:asciiname":"Shanshuping",
    "gn:country_code":"CN",
    "gn:dem":2472,
    "gn:feature_class":"P",
    "gn:feature_code":"PPL",
    "gn:name":"Shanshuping",
    "gn:population":0,
    "gn:timezone":"Asia/Shanghai",
    "iso:country":"CN",
    "name:zho_x_preferred":[
        "\u886b\u6811\u576a"
    ],
    "wof:name":"Shanshuping",
    "wof:placetype":"locality"
},
  "geometry": {"coordinates":[101.85629,27.7104],"type":"Point"}
}