{
  "type": "Feature",
  "properties": {
    "gn:admin1_code":"19.0",
    "gn:asciiname":"Xiaoliujiajie",
    "gn:country_code":"CN",
    "gn:dem":451,
    "gn:feature_class":"P",
    "gn:feature_code":"PPL",
    "gn:name":"Xiaoliujiajie",
    "gn:population":0,
    "gn:timezone":"Asia/Shanghai",
    "iso:country":"CN",
    "name:zho_x_preferred":[
        "\u5c0f\u5218\u5bb6\u8857"
    ],
    "wof:name":"Xiaoliujiajie",
    "wof:placetype":"locality"
},
  "geometry": {"coordinates":[123.82966,41.10046],"type":"Point"}
}