{
  "type": "Feature",
  "properties": {
    "gn:admin1_code":"16.0",
    "gn:asciiname":"Tongkuai",
    "gn:country_code":"CN",
    "gn:dem":128,
    "gn:feature_class":"P",
    "gn:feature_code":"PPL",
    "gn:name":"Tongkuai",
    "gn:population":0,
    "gn:timezone":"Asia/Shanghai",
    "iso:country":"CN",
    "name:zho_x_preferred":[
        "\u901a\u5feb"
    ],
    "wof:name":"Tongkuai",
    "wof:placetype":"locality"
},
  "geometry": {"coordinates":[108.249,22.3901],"type":"Point"}
}