{
  "type": "Feature",
  "properties": {
    "gn:admin1_code":"16.0",
    "gn:asciiname":"Shang'a",
    "gn:country_code":"CN",
    "gn:dem":896,
    "gn:feature_class":"P",
    "gn:feature_code":"PPL",
    "gn:name":"Shang\u2019a",
    "gn:population":0,
    "gn:timezone":"Asia/Shanghai",
    "iso:country":"CN",
    "name:und_x_variant":[
        "Shang\u2019a"
    ],
    "name:zho_x_preferred":[
        "\u4e0a\u963f"
    ],
    "wof:name":"Shang'a",
    "wof:placetype":"locality"
},
  "geometry": {"coordinates":[106.614,23.2855],"type":"Point"}
}