{
  "type": "Feature",
  "properties": {
    "gn:admin1_code":"12.0",
    "gn:asciiname":"Linjiacitang",
    "gn:country_code":"CN",
    "gn:dem":39,
    "gn:feature_class":"P",
    "gn:feature_code":"PPL",
    "gn:name":"Linjiacitang",
    "gn:population":0,
    "gn:timezone":"Asia/Shanghai",
    "iso:country":"CN",
    "name:zho_x_preferred":[
        "\u6797\u5bb6\u7960\u5802"
    ],
    "wof:name":"Linjiacitang",
    "wof:placetype":"locality"
},
  "geometry": {"coordinates":[112.34744999999999,30.02444],"type":"Point"}
}