{
  "type": "Feature",
  "properties": {
    "gn:admin1_code":"7.0",
    "gn:asciiname":"Jiudulan",
    "gn:country_code":"CN",
    "gn:dem":13,
    "gn:feature_class":"P",
    "gn:feature_code":"PPL",
    "gn:name":"Jiudulan",
    "gn:population":0,
    "gn:timezone":"Asia/Shanghai",
    "iso:country":"CN",
    "name:zho_x_preferred":[
        "\u4e5d\u90fd\u680f"
    ],
    "wof:name":"Jiudulan",
    "wof:placetype":"locality"
},
  "geometry": {"coordinates":[119.16871999999999,25.91529],"type":"Point"}
}