{
  "type": "Feature",
  "properties": {
    "gn:admin1_code":"14.0",
    "gn:asciiname":"Suxiong",
    "gn:country_code":"CN",
    "gn:dem":4410,
    "gn:feature_class":"P",
    "gn:feature_code":"PPL",
    "gn:name":"Suxiong",
    "gn:population":0,
    "gn:timezone":"Asia/Urumqi",
    "iso:country":"CN",
    "name:zho_x_preferred":[
        "\u82cf\u96c4"
    ],
    "wof:name":"Suxiong",
    "wof:placetype":"locality"
},
  "geometry": {"coordinates":[93.83892,31.24693],"type":"Point"}
}