{
  "type": "Feature",
  "properties": {
    "gn:admin1_code":"32",
    "gn:asciiname":"Shangluba",
    "gn:country_code":"CN",
    "gn:dem":601,
    "gn:feature_class":"P",
    "gn:feature_code":"PPL",
    "gn:name":"Shangluba",
    "gn:population":0,
    "gn:timezone":"Asia/Shanghai",
    "iso:country":"CN",
    "name:und_x_variant":[
        "Luba",
        "Shangluba"
    ],
    "name:zho_x_preferred":[
        "\u4e0a\u9c81\u575d"
    ],
    "wof:name":"Shangluba",
    "wof:placetype":"locality"
},
  "geometry": {"coordinates":[107.20913,32.40613],"type":"Point"}
}