{
  "type": "Feature",
  "properties": {
    "gn:admin1_code":"30.0",
    "gn:asciiname":"Shizhu",
    "gn:country_code":"CN",
    "gn:dem":105,
    "gn:feature_class":"P",
    "gn:feature_code":"PPL",
    "gn:name":"Shizhu",
    "gn:population":0,
    "gn:timezone":"Asia/Shanghai",
    "iso:country":"CN",
    "name:zho_x_preferred":[
        "\u77f3\u73e0"
    ],
    "wof:name":"Shizhu",
    "wof:placetype":"locality"
},
  "geometry": {"coordinates":[115.02285000000001,23.21735],"type":"Point"}
}