{
  "type": "Feature",
  "properties": {
    "gn:admin1_code":"18.0",
    "gn:asciiname":"Chashu",
    "gn:country_code":"CN",
    "gn:dem":978,
    "gn:feature_class":"P",
    "gn:feature_code":"PPL",
    "gn:name":"Chashu",
    "gn:population":0,
    "gn:timezone":"Asia/Shanghai",
    "iso:country":"CN",
    "wof:name":"Chashu",
    "wof:placetype":"locality"
},
  "geometry": {"coordinates":[107.0575,28.33639],"type":"Point"}
}