{
  "type": "Feature",
  "properties": {
    "gn:admin1_code":"16.0",
    "gn:asciiname":"Shangtuoling",
    "gn:country_code":"CN",
    "gn:dem":103,
    "gn:feature_class":"P",
    "gn:feature_code":"PPL",
    "gn:name":"Shangtuoling",
    "gn:population":0,
    "gn:timezone":"Asia/Shanghai",
    "iso:country":"CN",
    "name:zho_x_preferred":[
        "\u4e0a\u9a6e\u5cad"
    ],
    "wof:name":"Shangtuoling",
    "wof:placetype":"locality"
},
  "geometry": {"coordinates":[107.58499999999999,23.3061],"type":"Point"}
}