{
  "type": "Feature",
  "properties": {
    "gn:admin1_code":"2.0",
    "gn:asciiname":"Jizhi",
    "gn:country_code":"CN",
    "gn:dem":32,
    "gn:feature_class":"P",
    "gn:feature_code":"PPL",
    "gn:name":"Jizhi",
    "gn:population":0,
    "gn:timezone":"Asia/Shanghai",
    "iso:country":"CN",
    "name:zho_x_preferred":[
        "\u79ef\u5cd9"
    ],
    "wof:name":"Jizhi",
    "wof:placetype":"locality"
},
  "geometry": {"coordinates":[120.33026,29.91491],"type":"Point"}
}