{
  "type": "Feature",
  "properties": {
    "gn:admin1_code":"14.0",
    "gn:asciiname":"Garyarsa",
    "gn:country_code":"CN",
    "gn:dem":4435,
    "gn:feature_class":"P",
    "gn:feature_code":"PPL",
    "gn:name":"Garyarsa",
    "gn:population":0,
    "gn:timezone":"Asia/Shanghai",
    "iso:country":"CN",
    "name:bod_x_preferred":[
        "Garyarsa"
    ],
    "name:bod_x_variant":[
        "Gartog"
    ],
    "name:und_x_variant":[
        "Ya-so",
        "Gartok",
        "Ya-sha",
        "Ko-ta-k\u2019o",
        "Ka-erh-ya-sha",
        "Ka-erh-tu",
        "Ko-erh-ya-sha",
        "Ka-ta-k\u2019o",
        "Garyarsa"
    ],
    "name:zho_x_preferred":[
        "Ga\u2019eryasha"
    ],
    "name:zho_x_variant":[
        "\u5676\u5c14\u96c5\u6c99",
        "Gadake",
        "\u5676\u5927\u514b",
        "\u5676\u5c14\u4e9a\u6c99"
    ],
    "wof:name":"Garyarsa",
    "wof:placetype":"locality"
},
  "geometry": {"coordinates":[80.3351,31.7295],"type":"Point"}
}