{
  "type": "Feature",
  "properties": {
    "gn:admin1_code":"19",
    "gn:asciiname":"Cangshicun",
    "gn:country_code":"CN",
    "gn:dem":162,
    "gn:feature_class":"P",
    "gn:feature_code":"PPL",
    "gn:name":"Cangshicun",
    "gn:population":0,
    "gn:timezone":"Asia/Shanghai",
    "iso:country":"CN",
    "name:und_x_variant":[
        "Ts\u2019ang-shih",
        "Cangshi",
        "\u82cd\u77f3",
        "Cangshicun"
    ],
    "name:zho_x_preferred":[
        "\u82cd\u77f3\u6751"
    ],
    "wof:name":"Cangshicun",
    "wof:placetype":"locality"
},
  "geometry": {"coordinates":[124.52309,41.98238],"type":"Point"}
}