{
  "type": "Feature",
  "properties": {
    "gn:admin1_code":"30.0",
    "gn:asciiname":"Maiyuan",
    "gn:country_code":"CN",
    "gn:dem":84,
    "gn:feature_class":"P",
    "gn:feature_code":"PPL",
    "gn:name":"Maiyuan",
    "gn:population":0,
    "gn:timezone":"Asia/Shanghai",
    "iso:country":"CN",
    "name:zho_x_preferred":[
        "\u8109\u6e90"
    ],
    "wof:name":"Maiyuan",
    "wof:placetype":"locality"
},
  "geometry": {"coordinates":[112.43841,23.19874],"type":"Point"}
}