{
  "type": "Feature",
  "properties": {
    "gn:admin1_code":"19.0",
    "gn:asciiname":"Hujiawopeng",
    "gn:country_code":"CN",
    "gn:dem":37,
    "gn:feature_class":"P",
    "gn:feature_code":"PPL",
    "gn:name":"Hujiawopeng",
    "gn:population":0,
    "gn:timezone":"Asia/Shanghai",
    "iso:country":"CN",
    "name:zho_x_preferred":[
        "\u80e1\u5bb6\u7a9d\u68da"
    ],
    "wof:name":"Hujiawopeng",
    "wof:placetype":"locality"
},
  "geometry": {"coordinates":[123.175,42.0249],"type":"Point"}
}