{
  "type": "Feature",
  "properties": {
    "gn:admin1_code":"10",
    "gn:asciiname":"Yanzhi",
    "gn:country_code":"CN",
    "gn:dem":1188,
    "gn:feature_class":"P",
    "gn:feature_code":"PPL",
    "gn:name":"Yanzhi",
    "gn:population":0,
    "gn:timezone":"Asia/Shanghai",
    "iso:country":"CN",
    "name:zho_x_preferred":[
        "\u80ed\u8102"
    ],
    "wof:name":"Yanzhi",
    "wof:placetype":"locality"
},
  "geometry": {"coordinates":[115.86400999999999,41.0805],"type":"Point"}
}