{
  "type": "Feature",
  "properties": {
    "gn:admin1_code":"29.0",
    "gn:asciiname":"Mashaiku",
    "gn:country_code":"CN",
    "gn:dem":3179,
    "gn:feature_class":"P",
    "gn:feature_code":"PPL",
    "gn:name":"Mashaiku",
    "gn:population":0,
    "gn:timezone":"Asia/Shanghai",
    "iso:country":"CN",
    "name:zho_x_preferred":[
        "\u9a6c\u7b5b\u5e93"
    ],
    "wof:name":"Mashaiku",
    "wof:placetype":"locality"
},
  "geometry": {"coordinates":[99.5545,27.0382],"type":"Point"}
}