{
  "type": "Feature",
  "properties": {
    "gn:admin1_code":"25",
    "gn:asciiname":"Maqihe",
    "gn:country_code":"CN",
    "gn:dem":160,
    "gn:feature_class":"P",
    "gn:feature_code":"PPL",
    "gn:name":"Maqihe",
    "gn:population":0,
    "gn:timezone":"Asia/Shanghai",
    "iso:country":"CN",
    "name:zho_x_preferred":[
        "\u9a6c\u4e93\u6cb3"
    ],
    "wof:name":"Maqihe",
    "wof:placetype":"locality"
},
  "geometry": {"coordinates":[118.928,35.3399],"type":"Point"}
}