{
  "type": "Feature",
  "properties": {
    "gn:admin1_code":"5.0",
    "gn:asciiname":"Wudicun",
    "gn:country_code":"CN",
    "gn:dem":289,
    "gn:feature_class":"P",
    "gn:feature_code":"PPL",
    "gn:name":"Wudicun",
    "gn:population":0,
    "gn:timezone":"Asia/Shanghai",
    "iso:country":"CN",
    "name:zho_x_preferred":[
        "\u4e94\u6ef4\u6751"
    ],
    "wof:name":"Wudicun",
    "wof:placetype":"locality"
},
  "geometry": {"coordinates":[127.45021,44.37385],"type":"Point"}
}