{
  "type": "Feature",
  "properties": {
    "gn:admin1_code":"2.0",
    "gn:asciiname":"Shanwai",
    "gn:country_code":"CN",
    "gn:dem":129,
    "gn:feature_class":"P",
    "gn:feature_code":"PPL",
    "gn:name":"Shanwai",
    "gn:population":0,
    "gn:timezone":"Asia/Shanghai",
    "iso:country":"CN",
    "name:zho_x_preferred":[
        "\u5c71\u5916"
    ],
    "wof:name":"Shanwai",
    "wof:placetype":"locality"
},
  "geometry": {"coordinates":[118.59735999999999,28.77352],"type":"Point"}
}