{
  "type": "Feature",
  "properties": {
    "gn:admin1_code":"12.0",
    "gn:asciiname":"Heshangbao",
    "gn:country_code":"CN",
    "gn:dem":1514,
    "gn:feature_class":"P",
    "gn:feature_code":"PPL",
    "gn:name":"Heshangbao",
    "gn:population":0,
    "gn:timezone":"Asia/Shanghai",
    "iso:country":"CN",
    "name:zho_x_preferred":[
        "\u548c\u5c1a\u5305"
    ],
    "wof:name":"Heshangbao",
    "wof:placetype":"locality"
},
  "geometry": {"coordinates":[110.37927999999999,30.1363],"type":"Point"}
}