{
  "type": "Feature",
  "properties": {
    "gn:admin1_code":"32.0",
    "gn:asciiname":"Banbanpeng",
    "gn:country_code":"CN",
    "gn:dem":3909,
    "gn:feature_class":"P",
    "gn:feature_code":"PPL",
    "gn:name":"Banbanpeng",
    "gn:population":0,
    "gn:timezone":"Asia/Shanghai",
    "iso:country":"CN",
    "name:zho_x_preferred":[
        "\u677f\u677f\u68da"
    ],
    "wof:name":"Banbanpeng",
    "wof:placetype":"locality"
},
  "geometry": {"coordinates":[103.16670999999999,31.73341],"type":"Point"}
}