{
  "type": "Feature",
  "properties": {
    "gn:admin1_code":"24.0",
    "gn:asciiname":"Hualingou",
    "gn:country_code":"CN",
    "gn:dem":2135,
    "gn:feature_class":"P",
    "gn:feature_code":"PPL",
    "gn:name":"Hualingou",
    "gn:population":0,
    "gn:timezone":"Asia/Shanghai",
    "iso:country":"CN",
    "name:zho_x_preferred":[
        "\u6866\u6797\u6c9f"
    ],
    "wof:name":"Hualingou",
    "wof:placetype":"locality"
},
  "geometry": {"coordinates":[111.98246,38.75684],"type":"Point"}
}