{
  "type": "Feature",
  "properties": {
    "gn:admin1_code":"12.0",
    "gn:asciiname":"Yaojia Wo",
    "gn:country_code":"CN",
    "gn:dem":401,
    "gn:feature_class":"P",
    "gn:feature_code":"PPL",
    "gn:name":"Yaojia Wo",
    "gn:population":0,
    "gn:timezone":"Asia/Shanghai",
    "iso:country":"CN",
    "name:zho_x_preferred":[
        "\u59da\u5bb6\u7a9d"
    ],
    "wof:name":"Yaojia Wo",
    "wof:placetype":"locality"
},
  "geometry": {"coordinates":[111.24633,32.00530999999999],"type":"Point"}
}