{
  "type": "Feature",
  "properties": {
    "gn:admin1_code":"12.0",
    "gn:asciiname":"Zhuta",
    "gn:country_code":"CN",
    "gn:dem":1064,
    "gn:feature_class":"P",
    "gn:feature_code":"PPL",
    "gn:name":"Zhuta",
    "gn:population":0,
    "gn:timezone":"Asia/Shanghai",
    "iso:country":"CN",
    "name:zho_x_preferred":[
        "Zhuta"
    ],
    "name:zho_x_variant":[
        "\u7af9\u5854"
    ],
    "wof:name":"Zhuta",
    "wof:placetype":"locality"
},
  "geometry": {"coordinates":[110.21241000000001,29.76707],"type":"Point"}
}