{
  "type": "Feature",
  "properties": {
    "gn:admin1_code":"3.0",
    "gn:asciiname":"Shabei",
    "gn:country_code":"CN",
    "gn:dem":192,
    "gn:feature_class":"P",
    "gn:feature_code":"PPL",
    "gn:name":"Shabei",
    "gn:population":0,
    "gn:timezone":"Asia/Shanghai",
    "iso:country":"CN",
    "name:und_x_variant":[
        "\u6749\u80cc"
    ],
    "wof:name":"Shabei",
    "wof:placetype":"locality"
},
  "geometry": {"coordinates":[115.73598,25.79922],"type":"Point"}
}