{
  "type": "Feature",
  "properties": {
    "gn:admin1_code":"32.0",
    "gn:asciiname":"Yantoushang",
    "gn:country_code":"CN",
    "gn:dem":1241,
    "gn:feature_class":"P",
    "gn:feature_code":"PPL",
    "gn:name":"Yantoushang",
    "gn:population":0,
    "gn:timezone":"Asia/Shanghai",
    "iso:country":"CN",
    "name:zho_x_preferred":[
        "\u5ca9\u5934\u4e0a"
    ],
    "wof:name":"Yantoushang",
    "wof:placetype":"locality"
},
  "geometry": {"coordinates":[104.56102,27.88879],"type":"Point"}
}