{
  "type": "Feature",
  "properties": {
    "gn:admin1_code":"11.0",
    "gn:asciiname":"Maxiangkou",
    "gn:country_code":"CN",
    "gn:dem":64,
    "gn:feature_class":"P",
    "gn:feature_code":"PPL",
    "gn:name":"Maxiangkou",
    "gn:population":0,
    "gn:timezone":"Asia/Shanghai",
    "iso:country":"CN",
    "name:zho_x_preferred":[
        "\u9a6c\u5df7\u53e3"
    ],
    "wof:name":"Maxiangkou",
    "wof:placetype":"locality"
},
  "geometry": {"coordinates":[111.4336,28.75927],"type":"Point"}
}