{
  "type": "Feature",
  "properties": {
    "gn:admin1_code":"12.0",
    "gn:asciiname":"Yinfangping",
    "gn:country_code":"CN",
    "gn:dem":1623,
    "gn:feature_class":"P",
    "gn:feature_code":"PPL",
    "gn:name":"Yinfangping",
    "gn:population":0,
    "gn:timezone":"Asia/Shanghai",
    "iso:country":"CN",
    "name:zho_x_preferred":[
        "\u94f6\u653e\u576a"
    ],
    "wof:name":"Yinfangping",
    "wof:placetype":"locality"
},
  "geometry": {"coordinates":[110.52428,31.69538],"type":"Point"}
}