{
  "type": "Feature",
  "properties": {
    "gn:admin1_code":"02",
    "gn:asciiname":"Jielucun",
    "gn:country_code":"CN",
    "gn:dem":10,
    "gn:feature_class":"P",
    "gn:feature_code":"PPL",
    "gn:name":"Jielucun",
    "gn:population":0,
    "gn:timezone":"Asia/Shanghai",
    "iso:country":"CN",
    "name:und_x_variant":[
        "Jielu",
        "Jielucun"
    ],
    "name:zho_x_preferred":[
        "Chieh-lu-ts\u2019un"
    ],
    "name:zho_x_variant":[
        "\u8857\u8def\u6751"
    ],
    "wof:name":"Jielucun",
    "wof:placetype":"locality"
},
  "geometry": {"coordinates":[120.52002,27.85088],"type":"Point"}
}