{
  "type": "Feature",
  "properties": {
    "gn:admin1_code":"30.0",
    "gn:asciiname":"Longtoutan",
    "gn:country_code":"CN",
    "gn:dem":46,
    "gn:feature_class":"P",
    "gn:feature_code":"PPL",
    "gn:name":"Longtoutan",
    "gn:population":0,
    "gn:timezone":"Asia/Shanghai",
    "iso:country":"CN",
    "name:zho_x_preferred":[
        "\u9f99\u5934\u6f6d"
    ],
    "wof:name":"Longtoutan",
    "wof:placetype":"locality"
},
  "geometry": {"coordinates":[114.48005999999999,23.34023],"type":"Point"}
}