{
  "type": "Feature",
  "properties": {
    "gn:admin1_code":"16.0",
    "gn:asciiname":"Xia'ai",
    "gn:country_code":"CN",
    "gn:dem":315,
    "gn:feature_class":"P",
    "gn:feature_code":"PPL",
    "gn:name":"Xia\u2019ai",
    "gn:population":0,
    "gn:timezone":"Asia/Shanghai",
    "iso:country":"CN",
    "name:und_x_variant":[
        "Xia\u2019ai"
    ],
    "name:zho_x_preferred":[
        "\u4e0b\u7231"
    ],
    "wof:name":"Xia'ai",
    "wof:placetype":"locality"
},
  "geometry": {"coordinates":[108.015,24.7496],"type":"Point"}
}