{
  "type": "Feature",
  "properties": {
    "gn:admin1_code":"16.0",
    "gn:asciiname":"Nazhou",
    "gn:country_code":"CN",
    "gn:dem":273,
    "gn:feature_class":"P",
    "gn:feature_code":"PPL",
    "gn:name":"Nazhou",
    "gn:population":0,
    "gn:timezone":"Asia/Shanghai",
    "iso:country":"CN",
    "name:zho_x_preferred":[
        "\u7eb3\u5dde"
    ],
    "wof:name":"Nazhou",
    "wof:placetype":"locality"
},
  "geometry": {"coordinates":[107.178,25.0305],"type":"Point"}
}