{
  "type": "Feature",
  "properties": {
    "gn:country":"CN",
    "gn:fcode":"PPL",
    "gn:pop":2270,
    "iso:country":"CN",
    "name:mlg_x_preferred":[
        "Linkou"
    ],
    "name:rus_x_preferred":[
        "\u041b\u0438\u043d\u044c\u043a\u043e\u0443"
    ],
    "qs:name":"Linkou",
    "qs:photos_9r":0,
    "qs:photos_sr":0,
    "qs:pop_sr":"4",
    "wd:wordcount":76,
    "wof:name":"Linkou",
    "wof:placetype":"locality",
    "wof:population":2270
},
  "geometry": {"coordinates":[109.86360999999999,26.24806],"type":"Point"}
}