{
  "type": "Feature",
  "properties": {
    "gn:country":"CN",
    "gn:fcode":"PPL",
    "gn:population":2270,
    "iso:country":"CN",
    "name:ara_x_preferred":[
        "\u0644\u064a\u0646\u0643\u0648"
    ],
    "name:ben_x_preferred":[
        "\u09b2\u09bf\u09a8\u0995\u09cb\u0989"
    ],
    "name:deu_x_preferred":[
        "Linkou"
    ],
    "name:ell_x_preferred":[
        "\u039b\u03af\u03bd\u03ba\u03bf\u03c5"
    ],
    "name:fas_x_preferred":[
        "\u0644\u06cc\u0646\u06a9\u0648"
    ],
    "name:fra_x_preferred":[
        "Linkou"
    ],
    "name:heb_x_preferred":[
        "\u05dc\u05d9\u05e0\u05d5\u05e7\u05d5\u05d0\u05d5"
    ],
    "name:hin_x_preferred":[
        "\u0932\u093f\u0902\u0915\u093e\u0909"
    ],
    "name:hun_x_preferred":[
        "Linkou"
    ],
    "name:ind_x_preferred":[
        "Linkou"
    ],
    "name:ita_x_preferred":[
        "Linkou"
    ],
    "name:jpn_x_preferred":[
        "\u6797\u53e3"
    ],
    "name:kor_x_preferred":[
        "\ub9b0\ucee4\uc6b0"
    ],
    "name:mlg_x_preferred":[
        "Linkou"
    ],
    "name:nld_x_preferred":[
        "Linkou"
    ],
    "name:pol_x_preferred":[
        "Linkou"
    ],
    "name:por_x_preferred":[
        "Linkou"
    ],
    "name:rus_x_preferred":[
        "\u041b\u0438\u043d\u044c\u043a\u043e\u0443"
    ],
    "name:spa_x_preferred":[
        "Linkou"
    ],
    "name:swe_x_preferred":[
        "Linkou"
    ],
    "name:tur_x_preferred":[
        "Linkou"
    ],
    "name:ukr_x_preferred":[
        "\u041b\u0456\u043d\u044c\u043a\u043e\u0443"
    ],
    "name:urd_x_preferred":[
        "\u0644\u0646\u06a9\u0648"
    ],
    "name:vie_x_preferred":[
        "L\u00e2m Kh\u1ea9u"
    ],
    "name:zho_tw_x_preferred":[
        "\u6797\u53e3"
    ],
    "qs:name":"Linkou",
    "qs:photos_9r":0,
    "qs:photos_sr":0,
    "qs:pop_sr":"4",
    "wd:wordcount":76,
    "wof:name":"Linkou",
    "wof:placetype":"locality",
    "wof:population":2270
},
  "geometry": {"coordinates":[109.86360999999999,26.24806],"type":"Point"}
}