{
  "type": "Feature",
  "properties": {
    "gn:admin1_code":"18.0",
    "gn:asciiname":"Tangdang",
    "gn:country_code":"CN",
    "gn:dem":908,
    "gn:feature_class":"P",
    "gn:feature_code":"PPL",
    "gn:name":"Tangdang",
    "gn:population":0,
    "gn:timezone":"Asia/Shanghai",
    "iso:country":"CN",
    "name:zho_x_preferred":[
        "\u5858\u5f53"
    ],
    "wof:name":"Tangdang",
    "wof:placetype":"locality"
},
  "geometry": {"coordinates":[107.825,25.5986],"type":"Point"}
}