{
  "type": "Feature",
  "properties": {
    "gn:admin1_code":"2.0",
    "gn:asciiname":"Dajingtou",
    "gn:country_code":"CN",
    "gn:dem":7,
    "gn:feature_class":"P",
    "gn:feature_code":"PPL",
    "gn:name":"Dajingtou",
    "gn:population":0,
    "gn:timezone":"Asia/Shanghai",
    "iso:country":"CN",
    "name:zho_x_preferred":[
        "\u5927\u4e95\u5934"
    ],
    "wof:name":"Dajingtou",
    "wof:placetype":"locality"
},
  "geometry": {"coordinates":[121.21210000000001,28.58001],"type":"Point"}
}