{
  "type": "Feature",
  "properties": {
    "gn:admin1_code":"14.0",
    "gn:asciiname":"Zulu",
    "gn:country_code":"CN",
    "gn:dem":3254,
    "gn:feature_class":"P",
    "gn:feature_code":"PPL",
    "gn:name":"Zulu",
    "gn:population":0,
    "gn:timezone":"Asia/Urumqi",
    "iso:country":"CN",
    "name:ara_x_preferred":[
        "\u0632\u0648\u0644\u0648"
    ],
    "name:ceb_x_preferred":[
        "Zulu"
    ],
    "name:ces_x_preferred":[
        "Zulu"
    ],
    "name:dan_x_preferred":[
        "Zulu"
    ],
    "name:deu_x_preferred":[
        "Zulu"
    ],
    "name:fas_x_preferred":[
        "\u0632\u0648\u0644\u0648"
    ],
    "name:fin_x_preferred":[
        "Zulu"
    ],
    "name:fra_x_preferred":[
        "Zulu"
    ],
    "name:fry_x_preferred":[
        "Zulu"
    ],
    "name:heb_x_preferred":[
        "\u05d6\u05d5\u05dc\u05d5"
    ],
    "name:ind_x_preferred":[
        "Zulu"
    ],
    "name:ita_x_preferred":[
        "Zulu"
    ],
    "name:jpn_x_preferred":[
        "\u30ba\u30fc\u30eb\u30fc"
    ],
    "name:nld_x_preferred":[
        "Zoeloe"
    ],
    "name:nno_x_preferred":[
        "Zulu"
    ],
    "name:nor_x_preferred":[
        "Zulu"
    ],
    "name:pol_x_preferred":[
        "Zulu"
    ],
    "name:por_x_preferred":[
        "Zulu"
    ],
    "name:som_x_preferred":[
        "Zulu"
    ],
    "name:spa_x_preferred":[
        "Zul\u00fa"
    ],
    "name:swe_x_preferred":[
        "Zulu"
    ],
    "name:tur_x_preferred":[
        "Zulu"
    ],
    "name:zho_x_preferred":[
        "\u8db3\u9c81"
    ],
    "wof:name":"Zulu",
    "wof:placetype":"locality"
},
  "geometry": {"coordinates":[93.88785,29.21046],"type":"Point"}
}