{
  "type": "Feature",
  "properties": {
    "gn:admin1_code":"14.0",
    "gn:asciiname":"Zulu",
    "gn:country_code":"CN",
    "gn:dem":3254,
    "gn:feature_class":"P",
    "gn:feature_code":"PPL",
    "gn:name":"Zulu",
    "gn:population":0,
    "gn:timezone":"Asia/Urumqi",
    "iso:country":"CN",
    "name:zho_x_preferred":[
        "\u8db3\u9c81"
    ],
    "wof:name":"Zulu",
    "wof:placetype":"locality"
},
  "geometry": {"coordinates":[93.88785,29.21046],"type":"Point"}
}