{
  "type": "Feature",
  "properties": {
    "gn:admin1_code":"30",
    "gn:asciiname":"Liuli",
    "gn:country_code":"CN",
    "gn:dem":124,
    "gn:feature_class":"P",
    "gn:feature_code":"PPLA4",
    "gn:name":"Liuli",
    "gn:population":0,
    "gn:timezone":"Asia/Shanghai",
    "iso:country":"CN",
    "name:und_x_variant":[
        "\u516d\u91cc",
        "Liuli Zhen",
        "\u516d\u91cc\u9547"
    ],
    "wof:name":"Liuli",
    "wof:placetype":"locality"
},
  "geometry": {"coordinates":[113.96552,24.31138],"type":"Point"}
}