{
  "type": "Feature",
  "properties": {
    "gn:admin1_code":"7.0",
    "gn:asciiname":"Gaizhushan",
    "gn:country_code":"CN",
    "gn:dem":640,
    "gn:feature_class":"P",
    "gn:feature_code":"PPL",
    "gn:name":"Gaizhushan",
    "gn:population":0,
    "gn:timezone":"Asia/Shanghai",
    "iso:country":"CN",
    "name:zho_x_preferred":[
        "\u76d6\u7af9\u5c71"
    ],
    "wof:name":"Gaizhushan",
    "wof:placetype":"locality"
},
  "geometry": {"coordinates":[117.77379000000001,26.28565],"type":"Point"}
}