{
  "type": "Feature",
  "properties": {
    "gn:admin1_code":"4.0",
    "gn:asciiname":"Chaishi",
    "gn:country_code":"CN",
    "gn:dem":2,
    "gn:feature_class":"P",
    "gn:feature_code":"PPL",
    "gn:name":"Chaishi",
    "gn:population":0,
    "gn:timezone":"Asia/Shanghai",
    "iso:country":"CN",
    "name:zho_x_preferred":[
        "Chaishi"
    ],
    "name:zho_x_variant":[
        "\u67f4\u5e02"
    ],
    "wof:name":"Chaishi",
    "wof:placetype":"locality"
},
  "geometry": {"coordinates":[119.27778000000001,34.36671],"type":"Point"}
}