{
  "type": "Feature",
  "properties": {
    "gn:admin1_code":"9.0",
    "gn:asciiname":"Lataigou",
    "gn:country_code":"CN",
    "gn:dem":770,
    "gn:feature_class":"P",
    "gn:feature_code":"PPL",
    "gn:name":"Lataigou",
    "gn:population":0,
    "gn:timezone":"Asia/Shanghai",
    "iso:country":"CN",
    "name:und_x_variant":[
        "\u8721\u53f0\u6c9f",
        "Lataigou"
    ],
    "wof:name":"Lataigou",
    "wof:placetype":"locality"
},
  "geometry": {"coordinates":[112.18095,33.63395],"type":"Point"}
}