{
  "type": "Feature",
  "properties": {
    "gn:admin1_code":"16.0",
    "gn:asciiname":"Pingdong",
    "gn:country_code":"CN",
    "gn:dem":557,
    "gn:feature_class":"P",
    "gn:feature_code":"PPL",
    "gn:name":"Pingdong",
    "gn:population":0,
    "gn:timezone":"Asia/Shanghai",
    "iso:country":"CN",
    "name:ceb_x_preferred":[
        "Pingdong"
    ],
    "name:swe_x_preferred":[
        "Pingdong"
    ],
    "name:zho_x_preferred":[
        "\u5e73\u5cd2"
    ],
    "wof:name":"Pingdong",
    "wof:placetype":"locality"
},
  "geometry": {"coordinates":[107.121,24.6846],"type":"Point"}
}