{
  "type": "Feature",
  "properties": {
    "gn:admin1_code":"32.0",
    "gn:asciiname":"Longdantian",
    "gn:country_code":"CN",
    "gn:dem":579,
    "gn:feature_class":"P",
    "gn:feature_code":"PPL",
    "gn:name":"Longdantian",
    "gn:population":0,
    "gn:timezone":"Asia/Shanghai",
    "iso:country":"CN",
    "name:zho_x_preferred":[
        "\u9f99\u80c6\u7530"
    ],
    "wof:name":"Longdantian",
    "wof:placetype":"locality"
},
  "geometry": {"coordinates":[103.98814,28.91107],"type":"Point"}
}