{
  "type": "Feature",
  "properties": {
    "gn:admin1_code":"9.0",
    "gn:asciiname":"Zhuanjiaoshi",
    "gn:country_code":"CN",
    "gn:dem":1435,
    "gn:feature_class":"P",
    "gn:feature_code":"PPL",
    "gn:name":"Zhuanjiaoshi",
    "gn:population":0,
    "gn:timezone":"Asia/Shanghai",
    "iso:country":"CN",
    "name:und_x_variant":[
        "\u8f6c\u89d2\u77f3",
        "Zhuanjiaoshi"
    ],
    "wof:name":"Zhuanjiaoshi",
    "wof:placetype":"locality"
},
  "geometry": {"coordinates":[112.24012,33.67117],"type":"Point"}
}