{
  "type": "Feature",
  "properties": {
    "gn:admin1_code":"30.0",
    "gn:asciiname":"Dakeng",
    "gn:country_code":"CN",
    "gn:dem":288,
    "gn:feature_class":"P",
    "gn:feature_code":"PPL",
    "gn:name":"Dakeng",
    "gn:population":0,
    "gn:timezone":"Asia/Shanghai",
    "iso:country":"CN",
    "name:zho_x_preferred":[
        "Dakeng"
    ],
    "name:zho_x_variant":[
        "\u5927\u5751"
    ],
    "wof:name":"Dakeng",
    "wof:placetype":"locality"
},
  "geometry": {"coordinates":[114.88443999999998,24.52056],"type":"Point"}
}