{
  "type": "Feature",
  "properties": {
    "gn:admin1_code":"12.0",
    "gn:asciiname":"Xiongjia",
    "gn:country_code":"CN",
    "gn:dem":32,
    "gn:feature_class":"P",
    "gn:feature_code":"PPL",
    "gn:name":"Xiongjia",
    "gn:population":0,
    "gn:timezone":"Asia/Shanghai",
    "iso:country":"CN",
    "name:und_x_variant":[
        "\u718a\u5bb6"
    ],
    "wof:name":"Xiongjia",
    "wof:placetype":"locality"
},
  "geometry": {"coordinates":[114.36721,30.45972],"type":"Point"}
}