{
  "type": "Feature",
  "properties": {
    "gn:admin1_code":"26.0",
    "gn:asciiname":"Magou",
    "gn:country_code":"CN",
    "gn:dem":1202,
    "gn:feature_class":"P",
    "gn:feature_code":"PPL",
    "gn:name":"Magou",
    "gn:population":0,
    "gn:timezone":"Asia/Shanghai",
    "iso:country":"CN",
    "name:nld_x_preferred":[
        "Euploea magou"
    ],
    "name:srp_x_preferred":[
        "Euploea magou"
    ],
    "name:swe_x_preferred":[
        "Euploea magou"
    ],
    "name:zho_x_preferred":[
        "\u9a6c\u6c9f"
    ],
    "wof:name":"Magou",
    "wof:placetype":"locality"
},
  "geometry": {"coordinates":[109.0312,35.47005],"type":"Point"}
}