{
  "type": "Feature",
  "properties": {
    "gn:admin1_code":"12.0",
    "gn:asciiname":"Waxuepu",
    "gn:country_code":"CN",
    "gn:dem":367,
    "gn:feature_class":"P",
    "gn:feature_code":"PPL",
    "gn:name":"Waxuepu",
    "gn:population":0,
    "gn:timezone":"Asia/Shanghai",
    "iso:country":"CN",
    "name:zho_x_preferred":[
        "\u74e6\u5b66\u94fa"
    ],
    "wof:name":"Waxuepu",
    "wof:placetype":"locality"
},
  "geometry": {"coordinates":[115.48457999999999,31.23884],"type":"Point"}
}