{
  "type": "Feature",
  "properties": {
    "gn:admin1_code":"02",
    "gn:asciiname":"Shaobailing",
    "gn:cc2":"CN",
    "gn:country_code":"CN",
    "gn:dem":8,
    "gn:feature_class":"P",
    "gn:feature_code":"PPL",
    "gn:name":"Shaobailing",
    "gn:population":0,
    "gn:timezone":"Asia/Shanghai",
    "iso:country":"CN",
    "name:und_x_variant":[
        "Shao-pai",
        "Shaobailing"
    ],
    "wof:name":"Shaobailing",
    "wof:placetype":"locality"
},
  "geometry": {"coordinates":[121.73694,29.81417],"type":"Point"}
}