{
  "type": "Feature",
  "properties": {
    "gn:admin1_code":"32.0",
    "gn:asciiname":"Wanjinqiao",
    "gn:country_code":"CN",
    "gn:dem":355,
    "gn:feature_class":"P",
    "gn:feature_code":"PPL",
    "gn:name":"Wanjinqiao",
    "gn:population":0,
    "gn:timezone":"Asia/Shanghai",
    "iso:country":"CN",
    "name:zho_x_preferred":[
        "\u4e07\u91d1\u6865"
    ],
    "wof:name":"Wanjinqiao",
    "wof:placetype":"locality"
},
  "geometry": {"coordinates":[104.53100000000001,29.1221],"type":"Point"}
}