{
  "type": "Feature",
  "properties": {
    "gn:admin1_code":"32.0",
    "gn:asciiname":"Panlongmiao",
    "gn:country_code":"CN",
    "gn:dem":601,
    "gn:feature_class":"P",
    "gn:feature_code":"PPL",
    "gn:name":"Panlongmiao",
    "gn:population":0,
    "gn:timezone":"Asia/Shanghai",
    "iso:country":"CN",
    "name:zho_x_preferred":[
        "\u87e0\u9f99\u5e99"
    ],
    "wof:name":"Panlongmiao",
    "wof:placetype":"locality"
},
  "geometry": {"coordinates":[105.86578,31.70058],"type":"Point"}
}