{
  "type": "Feature",
  "properties": {
    "gn:admin1_code":"25.0",
    "gn:asciiname":"Wangcunloucun",
    "gn:country_code":"CN",
    "gn:dem":161,
    "gn:feature_class":"P",
    "gn:feature_code":"PPL",
    "gn:name":"Wangcunloucun",
    "gn:population":0,
    "gn:timezone":"Asia/Shanghai",
    "iso:country":"CN",
    "name:zho_x_preferred":[
        "\u738b\u6751\u697c\u6751"
    ],
    "wof:name":"Wangcunloucun",
    "wof:placetype":"locality"
},
  "geometry": {"coordinates":[118.62482,36.42075],"type":"Point"}
}