{
  "type": "Feature",
  "properties": {
    "gn:admin1_code":"29.0",
    "gn:asciiname":"Xiaxiangshan",
    "gn:country_code":"CN",
    "gn:dem":1843,
    "gn:feature_class":"P",
    "gn:feature_code":"PPL",
    "gn:name":"Xiaxiangshan",
    "gn:population":0,
    "gn:timezone":"Asia/Shanghai",
    "iso:country":"CN",
    "name:zho_x_preferred":[
        "\u4e0b\u54cd\u5c71"
    ],
    "wof:name":"Xiaxiangshan",
    "wof:placetype":"locality"
},
  "geometry": {"coordinates":[99.1404,24.7348],"type":"Point"}
}