{
  "type": "Feature",
  "properties": {
    "gn:admin1_code":"32.0",
    "gn:asciiname":"Namo",
    "gn:country_code":"CN",
    "gn:dem":3144,
    "gn:feature_class":"P",
    "gn:feature_code":"PPL",
    "gn:name":"Namo",
    "gn:population":0,
    "gn:timezone":"Asia/Shanghai",
    "iso:country":"CN",
    "name:ceb_x_preferred":[
        "Namo"
    ],
    "name:swe_x_preferred":[
        "Namo"
    ],
    "name:zho_x_preferred":[
        "\u7eb3\u83ab"
    ],
    "wof:name":"Namo",
    "wof:placetype":"locality"
},
  "geometry": {"coordinates":[99.29340000000001,28.5309],"type":"Point"}
}