{
  "type": "Feature",
  "properties": {
    "gn:admin1_code":"32.0",
    "gn:asciiname":"Banzhulin",
    "gn:country_code":"CN",
    "gn:dem":842,
    "gn:feature_class":"P",
    "gn:feature_code":"PPL",
    "gn:name":"Banzhulin",
    "gn:population":0,
    "gn:timezone":"Asia/Shanghai",
    "iso:country":"CN",
    "name:zho_x_preferred":[
        "\u6591\u7af9\u6797"
    ],
    "wof:name":"Banzhulin",
    "wof:placetype":"locality"
},
  "geometry": {"coordinates":[104.459,28.0495],"type":"Point"}
}