{
  "type": "Feature",
  "properties": {
    "gn:admin1_code":"30.0",
    "gn:asciiname":"Gangxiacun",
    "gn:country_code":"CN",
    "gn:dem":106,
    "gn:feature_class":"P",
    "gn:feature_code":"PPL",
    "gn:name":"Gangxiacun",
    "gn:population":0,
    "gn:timezone":"Asia/Shanghai",
    "iso:country":"CN",
    "name:zho_x_preferred":[
        "\u5c97\u4e0b\u6751"
    ],
    "wof:name":"Gangxiacun",
    "wof:placetype":"locality"
},
  "geometry": {"coordinates":[116.87761999999999,24.09487],"type":"Point"}
}