{
  "type": "Feature",
  "properties": {
    "gn:admin1_code":"9.0",
    "gn:asciiname":"Shangyanzhuang",
    "gn:country_code":"CN",
    "gn:dem":211,
    "gn:feature_class":"P",
    "gn:feature_code":"PPLA4",
    "gn:name":"Shangyanzhuang",
    "gn:population":0,
    "gn:timezone":"Asia/Shanghai",
    "iso:country":"CN",
    "name:und_x_variant":[
        "\u4e0a\u960e\u5e84",
        "Shangyanzhuang Xiang",
        "\u4e0a\u960e\u5e84\u4e61"
    ],
    "wof:name":"Shangyanzhuang",
    "wof:placetype":"locality"
},
  "geometry": {"coordinates":[114.26352,38.58117],"type":"Point"}
}