{
  "type": "Feature",
  "properties": {
    "gn:admin1_code":"18",
    "gn:asciiname":"Hejia",
    "gn:country_code":"CN",
    "gn:dem":1184,
    "gn:feature_class":"P",
    "gn:feature_code":"PPL",
    "gn:name":"Hejia",
    "gn:population":0,
    "gn:timezone":"Asia/Shanghai",
    "iso:country":"CN",
    "name:zho_x_preferred":[
        "\u6cb3\u5939"
    ],
    "wof:name":"Hejia",
    "wof:placetype":"locality"
},
  "geometry": {"coordinates":[107.58199999999999,28.7905],"type":"Point"}
}