{
  "type": "Feature",
  "properties": {
    "gn:admin1_code":"2",
    "gn:asciiname":"Dongfengyingshi",
    "gn:country_code":"CN",
    "gn:dem":157,
    "gn:feature_class":"P",
    "gn:feature_code":"PPL",
    "gn:name":"Dongfengyingshi",
    "gn:population":0,
    "gn:timezone":"Asia/Shanghai",
    "iso:country":"CN",
    "wof:name":"Dongfengyingshi",
    "wof:placetype":"locality"
},
  "geometry": {"coordinates":[119.88639000000001,28.9875],"type":"Point"}
}