{
  "type": "Feature",
  "properties": {
    "gn:admin1_code":"9.0",
    "gn:asciiname":"Nianpanqiao",
    "gn:country_code":"CN",
    "gn:dem":113,
    "gn:feature_class":"P",
    "gn:feature_code":"PPL",
    "gn:name":"Nianpanqiao",
    "gn:population":0,
    "gn:timezone":"Asia/Shanghai",
    "iso:country":"CN",
    "name:zho_x_preferred":[
        "\u78be\u76d8\u6865"
    ],
    "wof:name":"Nianpanqiao",
    "wof:placetype":"locality"
},
  "geometry": {"coordinates":[112.76152999999999,32.82783],"type":"Point"}
}