{
  "type": "Feature",
  "properties": {
    "gn:admin1_code":"30",
    "gn:asciiname":"Xuxi",
    "gn:country_code":"CN",
    "gn:dem":98,
    "gn:feature_class":"P",
    "gn:feature_code":"PPL",
    "gn:name":"Xuxi",
    "gn:population":0,
    "gn:timezone":"Asia/Shanghai",
    "iso:country":"CN",
    "name:zho_x_preferred":[
        "\u5f90\u6eaa"
    ],
    "wof:name":"Xuxi",
    "wof:placetype":"locality"
},
  "geometry": {"coordinates":[116.08232,24.55712],"type":"Point"}
}