{
  "type": "Feature",
  "properties": {
    "gn:admin1_code":"18",
    "gn:asciiname":"Bapaishan",
    "gn:country_code":"CN",
    "gn:dem":844,
    "gn:feature_class":"P",
    "gn:feature_code":"PPL",
    "gn:name":"Bapaishan",
    "gn:population":0,
    "gn:timezone":"Asia/Shanghai",
    "iso:country":"CN",
    "name:zho_x_preferred":[
        "\u516b\u6392\u5c71"
    ],
    "wof:name":"Bapaishan",
    "wof:placetype":"locality"
},
  "geometry": {"coordinates":[107.111,25.6051],"type":"Point"}
}