{
  "type": "Feature",
  "properties": {
    "gn:admin1_code":"01",
    "gn:asciiname":"Shitou",
    "gn:cc2":"CN",
    "gn:country_code":"CN",
    "gn:dem":22,
    "gn:feature_class":"P",
    "gn:feature_code":"PPL",
    "gn:name":"Shitou",
    "gn:population":0,
    "gn:timezone":"Asia/Shanghai",
    "iso:country":"CN",
    "name:und_x_variant":[
        "Shih-tsui-t\u2019ou",
        "Shih-t\u2019ou",
        "Shitou"
    ],
    "wof:name":"Shitou",
    "wof:placetype":"locality"
},
  "geometry": {"coordinates":[117.26528,31.42778],"type":"Point"}
}