{
  "type": "Feature",
  "properties": {
    "gn:admin1_code":"2.0",
    "gn:asciiname":"Fangmache",
    "gn:country_code":"CN",
    "gn:dem":190,
    "gn:feature_class":"P",
    "gn:feature_code":"PPL",
    "gn:name":"Fangmache",
    "gn:population":0,
    "gn:timezone":"Asia/Shanghai",
    "iso:country":"CN",
    "name:zho_x_preferred":[
        "\u65b9\u9ebb\u8f66"
    ],
    "wof:name":"Fangmache",
    "wof:placetype":"locality"
},
  "geometry": {"coordinates":[119.67525999999999,28.95113],"type":"Point"}
}