{
  "type": "Feature",
  "properties": {
    "gn:admin1_code":"2.0",
    "gn:asciiname":"Yipeng",
    "gn:country_code":"CN",
    "gn:dem":11,
    "gn:feature_class":"P",
    "gn:feature_code":"PPLA4",
    "gn:name":"Yipeng",
    "gn:population":0,
    "gn:timezone":"Asia/Shanghai",
    "iso:country":"CN",
    "name:und_x_variant":[
        "\u4e49\u84ec",
        "Yipeng Zhen",
        "\u4e49\u84ec\u9547"
    ],
    "wof:name":"Yipeng",
    "wof:placetype":"locality"
},
  "geometry": {"coordinates":[120.48884,30.26158],"type":"Point"}
}