{
  "type": "Feature",
  "properties": {
    "gn:admin1_code":"29.0",
    "gn:asciiname":"Simatou",
    "gn:country_code":"CN",
    "gn:dem":1243,
    "gn:feature_class":"P",
    "gn:feature_code":"PPL",
    "gn:name":"Simatou",
    "gn:population":0,
    "gn:timezone":"Asia/Shanghai",
    "iso:country":"CN",
    "name:zho_x_preferred":[
        "\u56db\u9a82\u5934"
    ],
    "wof:name":"Simatou",
    "wof:placetype":"locality"
},
  "geometry": {"coordinates":[104.217,28.4299],"type":"Point"}
}