{
  "type": "Feature",
  "properties": {
    "gn:admin1_code":"12.0",
    "gn:asciiname":"Yaodianzi",
    "gn:country_code":"CN",
    "gn:dem":1312,
    "gn:feature_class":"P",
    "gn:feature_code":"PPL",
    "gn:name":"Yaodianzi",
    "gn:population":0,
    "gn:timezone":"Asia/Shanghai",
    "iso:country":"CN",
    "name:und_x_variant":[
        "Medianzi",
        "Yaodianzi"
    ],
    "name:zho_x_preferred":[
        "\u4e48\u5e97\u5b50"
    ],
    "wof:name":"Yaodianzi",
    "wof:placetype":"locality"
},
  "geometry": {"coordinates":[109.82747000000001,31.68376],"type":"Point"}
}