{
  "type": "Feature",
  "properties": {
    "gn:admin1_code":"33.0",
    "gn:asciiname":"Jiewangmiao",
    "gn:country_code":"CN",
    "gn:dem":423,
    "gn:feature_class":"P",
    "gn:feature_code":"PPL",
    "gn:name":"Jiewangmiao",
    "gn:population":0,
    "gn:timezone":"Asia/Shanghai",
    "iso:country":"CN",
    "name:zho_x_preferred":[
        "\u7ed3\u738b\u5e99"
    ],
    "wof:name":"Jiewangmiao",
    "wof:placetype":"locality"
},
  "geometry": {"coordinates":[107.43742,30.72785],"type":"Point"}
}