{
  "type": "Feature",
  "properties": {
    "gn:admin1_code":"11.0",
    "gn:asciiname":"Longtangwan",
    "gn:country_code":"CN",
    "gn:dem":94,
    "gn:feature_class":"P",
    "gn:feature_code":"PPL",
    "gn:name":"Longtangwan",
    "gn:population":0,
    "gn:timezone":"Asia/Shanghai",
    "iso:country":"CN",
    "name:und_x_variant":[
        "Longtanwan"
    ],
    "name:zho_x_preferred":[
        "\u9f99\u5858\u6e7e"
    ],
    "wof:name":"Longtangwan",
    "wof:placetype":"locality"
},
  "geometry": {"coordinates":[112.28138,26.38843],"type":"Point"}
}