{
  "type": "Feature",
  "properties": {
    "gn:admin1_code":"32.0",
    "gn:asciiname":"Xinwuzui",
    "gn:country_code":"CN",
    "gn:dem":385,
    "gn:feature_class":"P",
    "gn:feature_code":"PPL",
    "gn:name":"Xinwuzui",
    "gn:population":0,
    "gn:timezone":"Asia/Shanghai",
    "iso:country":"CN",
    "name:zho_x_preferred":[
        "\u65b0\u5c4b\u5480"
    ],
    "wof:name":"Xinwuzui",
    "wof:placetype":"locality"
},
  "geometry": {"coordinates":[104.71643,28.95535],"type":"Point"}
}