{
  "type": "Feature",
  "properties": {
    "gn:admin1_code":"04",
    "gn:asciiname":"Chemahu",
    "gn:country_code":"CN",
    "gn:dem":5,
    "gn:feature_class":"P",
    "gn:feature_code":"PPL",
    "gn:name":"Chemahu",
    "gn:population":0,
    "gn:timezone":"Asia/Shanghai",
    "iso:country":"CN",
    "name:und_x_variant":[
        "Hsi-ch\u2019e-ma-hu",
        "Chemahu",
        "\u8f66\u9a6c\u6e56"
    ],
    "wof:name":"Chemahu",
    "wof:placetype":"locality"
},
  "geometry": {"coordinates":[120.61409,32.18725999999999],"type":"Point"}
}