{
  "type": "Feature",
  "properties": {
    "gn:admin1_code":"15.0",
    "gn:asciiname":"Lidizhuang",
    "gn:country_code":"CN",
    "gn:dem":1437,
    "gn:feature_class":"P",
    "gn:feature_code":"PPL",
    "gn:name":"Lidizhuang",
    "gn:population":0,
    "gn:timezone":"Asia/Shanghai",
    "iso:country":"CN",
    "name:zho_x_preferred":[
        "\u674e\u5730\u5e84"
    ],
    "wof:name":"Lidizhuang",
    "wof:placetype":"locality"
},
  "geometry": {"coordinates":[107.236,35.8242],"type":"Point"}
}