{
  "type": "Feature",
  "properties": {
    "gn:admin1_code":"3.0",
    "gn:asciiname":"Ganxitang",
    "gn:country_code":"CN",
    "gn:dem":91,
    "gn:feature_class":"P",
    "gn:feature_code":"PPL",
    "gn:name":"Ganxitang",
    "gn:population":0,
    "gn:timezone":"Asia/Shanghai",
    "iso:country":"CN",
    "name:und_x_variant":[
        "\u67d1\u6eaa\u5858"
    ],
    "wof:name":"Ganxitang",
    "wof:placetype":"locality"
},
  "geometry": {"coordinates":[114.86709,27.15378],"type":"Point"}
}