{
  "type": "Feature",
  "properties": {
    "gn:admin1_code":"3",
    "gn:asciiname":"Longbu",
    "gn:country_code":"CN",
    "gn:dem":183,
    "gn:feature_class":"P",
    "gn:feature_code":"PPL",
    "gn:name":"Longbu",
    "gn:population":0,
    "gn:timezone":"Asia/Shanghai",
    "iso:country":"CN",
    "name:zho_x_preferred":[
        "\u9f99\u57e0"
    ],
    "wof:name":"Longbu",
    "wof:placetype":"locality"
},
  "geometry": {"coordinates":[114.95473,25.76549],"type":"Point"}
}