{
  "type": "Feature",
  "properties": {
    "gn:admin1_code":"26.0",
    "gn:asciiname":"Chunshupo",
    "gn:country_code":"CN",
    "gn:dem":546,
    "gn:feature_class":"P",
    "gn:feature_code":"PPL",
    "gn:name":"Chunshupo",
    "gn:population":0,
    "gn:timezone":"Asia/Shanghai",
    "iso:country":"CN",
    "name:zho_x_preferred":[
        "\u693f\u6811\u5761"
    ],
    "wof:name":"Chunshupo",
    "wof:placetype":"locality"
},
  "geometry": {"coordinates":[109.05092999999999,32.772],"type":"Point"}
}