{
  "type": "Feature",
  "properties": {
    "gn:admin1_code":"5.0",
    "gn:asciiname":"Huashutun",
    "gn:country_code":"CN",
    "gn:dem":188,
    "gn:feature_class":"P",
    "gn:feature_code":"PPL",
    "gn:name":"Huashutun",
    "gn:population":0,
    "gn:timezone":"Asia/Shanghai",
    "iso:country":"CN",
    "name:zho_x_preferred":[
        "\u6866\u6811\u5c6f"
    ],
    "wof:name":"Huashutun",
    "wof:placetype":"locality"
},
  "geometry": {"coordinates":[126.58016000000001,44.5741],"type":"Point"}
}