{
  "type": "Feature",
  "properties": {
    "gn:admin1_code":"25.0",
    "gn:asciiname":"Guichengjiangjia",
    "gn:country_code":"CN",
    "gn:dem":76,
    "gn:feature_class":"P",
    "gn:feature_code":"PPL",
    "gn:name":"Guichengjiangjia",
    "gn:population":0,
    "gn:timezone":"Asia/Shanghai",
    "iso:country":"CN",
    "name:zho_x_preferred":[
        "\u5f52\u57ce\u59dc\u5bb6"
    ],
    "wof:name":"Guichengjiangjia",
    "wof:placetype":"locality"
},
  "geometry": {"coordinates":[120.56836,37.59618],"type":"Point"}
}