{
  "type": "Feature",
  "properties": {
    "gn:admin1_code":"15.0",
    "gn:asciiname":"Xujiapingzhuang",
    "gn:country_code":"CN",
    "gn:dem":1722,
    "gn:feature_class":"P",
    "gn:feature_code":"PPL",
    "gn:name":"Xujiapingzhuang",
    "gn:population":0,
    "gn:timezone":"Asia/Shanghai",
    "iso:country":"CN",
    "name:und_x_variant":[
        "\u5f90\u5bb6\u5e73\u5e84"
    ],
    "wof:name":"Xujiapingzhuang",
    "wof:placetype":"locality"
},
  "geometry": {"coordinates":[106.77253,36.90703],"type":"Point"}
}