{
  "type": "Feature",
  "properties": {
    "gn:admin1_code":"10",
    "gn:asciiname":"Qiaojiazhuang",
    "gn:country_code":"CN",
    "gn:dem":275,
    "gn:feature_class":"P",
    "gn:feature_code":"PPL",
    "gn:name":"Qiaojiazhuang",
    "gn:population":0,
    "gn:timezone":"Asia/Shanghai",
    "iso:country":"CN",
    "name:zho_x_preferred":[
        "\u4e54\u5bb6\u5e84"
    ],
    "wof:name":"Qiaojiazhuang",
    "wof:placetype":"locality"
},
  "geometry": {"coordinates":[114.27200000000001,37.849],"type":"Point"}
}