{
  "type": "Feature",
  "properties": {
    "gn:admin1_code":"10",
    "gn:asciiname":"Wujiagou",
    "gn:country_code":"CN",
    "gn:dem":1154,
    "gn:feature_class":"P",
    "gn:feature_code":"PPL",
    "gn:name":"Wujiagou",
    "gn:population":0,
    "gn:timezone":"Asia/Shanghai",
    "iso:country":"CN",
    "name:zho_x_preferred":[
        "\u6b66\u5bb6\u6c9f"
    ],
    "wof:name":"Wujiagou",
    "wof:placetype":"locality"
},
  "geometry": {"coordinates":[115.70116000000002,40.82732],"type":"Point"}
}