{
  "type": "Feature",
  "properties": {
    "gn:admin1_code":"16.0",
    "gn:asciiname":"Gongdidong",
    "gn:country_code":"CN",
    "gn:dem":103,
    "gn:feature_class":"P",
    "gn:feature_code":"PPL",
    "gn:name":"Gongdidong",
    "gn:population":0,
    "gn:timezone":"Asia/Shanghai",
    "iso:country":"CN",
    "name:zho_x_preferred":[
        "\u516c\u5e95\u578c"
    ],
    "wof:name":"Gongdidong",
    "wof:placetype":"locality"
},
  "geometry": {"coordinates":[110.506,23.0838],"type":"Point"}
}