{
  "type": "Feature",
  "properties": {
    "gn:admin1_code":"26.0",
    "gn:asciiname":"Luobaizhaicun",
    "gn:country_code":"CN",
    "gn:dem":369,
    "gn:feature_class":"P",
    "gn:feature_code":"PPL",
    "gn:name":"Luobaizhaicun",
    "gn:population":0,
    "gn:timezone":"Asia/Shanghai",
    "iso:country":"CN",
    "name:zho_x_preferred":[
        "\u7f57\u767e\u5be8\u6751"
    ],
    "wof:name":"Luobaizhaicun",
    "wof:placetype":"locality"
},
  "geometry": {"coordinates":[109.07798,34.41220999999999],"type":"Point"}
}