{
  "type": "Feature",
  "properties": {
    "gn:admin1_code":"26",
    "gn:asciiname":"Dishuiya",
    "gn:country_code":"CN",
    "gn:dem":788,
    "gn:feature_class":"P",
    "gn:feature_code":"PPL",
    "gn:name":"Dishuiya",
    "gn:population":0,
    "gn:timezone":"Asia/Shanghai",
    "iso:country":"CN",
    "name:und_x_variant":[
        "Ti-shui-ya",
        "Dishuiya"
    ],
    "name:zho_x_preferred":[
        "\u6ef4\u6c34\u5d16"
    ],
    "wof:name":"Dishuiya",
    "wof:placetype":"locality"
},
  "geometry": {"coordinates":[110.38162,36.55755],"type":"Point"}
}