{
  "type": "Feature",
  "properties": {
    "gn:admin1_code":"18",
    "gn:asciiname":"Shangyoumai",
    "gn:country_code":"CN",
    "gn:dem":733,
    "gn:feature_class":"P",
    "gn:feature_code":"PPL",
    "gn:name":"Shangyoumai",
    "gn:population":0,
    "gn:timezone":"Asia/Shanghai",
    "iso:country":"CN",
    "name:zho_x_preferred":[
        "\u4e0a\u6cb9\u8fc8"
    ],
    "wof:name":"Shangyoumai",
    "wof:placetype":"locality"
},
  "geometry": {"coordinates":[105.996,25.0575],"type":"Point"}
}