{
  "type": "Feature",
  "properties": {
    "gn:admin1_code":"3.0",
    "gn:asciiname":"Shanxiacun",
    "gn:country_code":"CN",
    "gn:dem":327,
    "gn:feature_class":"P",
    "gn:feature_code":"PPL",
    "gn:name":"Shanxiacun",
    "gn:population":0,
    "gn:timezone":"Asia/Shanghai",
    "iso:country":"CN",
    "name:und_x_variant":[
        "\u5c71\u4e0b\u6751"
    ],
    "wof:name":"Shanxiacun",
    "wof:placetype":"locality"
},
  "geometry": {"coordinates":[116.53151,26.64296],"type":"Point"}
}