{
  "type": "Feature",
  "properties": {
    "gn:admin1_code":"25",
    "gn:asciiname":"Kangyi",
    "gn:cc2":"CN",
    "gn:country_code":"CN",
    "gn:dem":42,
    "gn:feature_class":"P",
    "gn:feature_code":"PPL",
    "gn:name":"Kangyi",
    "gn:population":0,
    "gn:timezone":"Asia/Shanghai",
    "iso:country":"CN",
    "name:und_x_variant":[
        "Kangzhuangyi",
        "K\u2019ang-chuang-i",
        "Kangyi"
    ],
    "wof:name":"Kangyi",
    "wof:placetype":"locality"
},
  "geometry": {"coordinates":[116.51721999999999,35.56917],"type":"Point"}
}