{
  "type": "Feature",
  "properties": {
    "gn:admin1_code":"8.0",
    "gn:asciiname":"Yongjiucun",
    "gn:country_code":"CN",
    "gn:dem":143,
    "gn:feature_class":"P",
    "gn:feature_code":"PPL",
    "gn:name":"Yongjiucun",
    "gn:population":0,
    "gn:timezone":"Asia/Shanghai",
    "iso:country":"CN",
    "name:zho_x_preferred":[
        "\u6c38\u4e45\u6751"
    ],
    "wof:name":"Yongjiucun",
    "wof:placetype":"locality"
},
  "geometry": {"coordinates":[126.31702,46.2046],"type":"Point"}
}