{
  "type": "Feature",
  "properties": {
    "gn:admin1_code":"24",
    "gn:asciiname":"Sitou",
    "gn:cc2":"CN",
    "gn:country_code":"CN",
    "gn:dem":1188,
    "gn:feature_class":"P",
    "gn:feature_code":"PPL",
    "gn:name":"Sitou",
    "gn:population":0,
    "gn:timezone":"Asia/Shanghai",
    "iso:country":"CN",
    "name:und_x_variant":[
        "Ssu-t\u2019ou-ts\u2019un",
        "Ssu-t\u2019ou",
        "Sitou"
    ],
    "name:zho_x_preferred":[
        "\u5bfa\u5934\u9547"
    ],
    "wof:name":"Sitou",
    "wof:placetype":"locality"
},
  "geometry": {"coordinates":[113.55,36.15],"type":"Point"}
}