{
  "type": "Feature",
  "properties": {
    "gn:admin1_code":"14.0",
    "gn:asciiname":"Chongxia",
    "gn:country_code":"CN",
    "gn:dem":3857,
    "gn:feature_class":"P",
    "gn:feature_code":"PPL",
    "gn:name":"Chongxia",
    "gn:population":0,
    "gn:timezone":"Asia/Urumqi",
    "iso:country":"CN",
    "name:zho_x_preferred":[
        "\u866b\u867e"
    ],
    "wof:name":"Chongxia",
    "wof:placetype":"locality"
},
  "geometry": {"coordinates":[98.07787999999999,31.4621],"type":"Point"}
}