{
  "type": "Feature",
  "properties": {
    "gn:admin1_code":"10",
    "gn:asciiname":"Shi'erlizhuang",
    "gn:country_code":"CN",
    "gn:dem":33,
    "gn:feature_class":"P",
    "gn:feature_code":"PPL",
    "gn:name":"Shi\u2019erlizhuang",
    "gn:population":0,
    "gn:timezone":"Asia/Shanghai",
    "iso:country":"CN",
    "name:und_x_variant":[
        "Shi\u2019erlizhuang"
    ],
    "name:zho_x_preferred":[
        "\u5341\u4e8c\u91cc\u5e84"
    ],
    "wof:name":"Shi'erlizhuang",
    "wof:placetype":"locality"
},
  "geometry": {"coordinates":[115.81,37.1912],"type":"Point"}
}