{
  "type": "Feature",
  "properties": {
    "gn:admin1_code":"3.0",
    "gn:asciiname":"Paitou",
    "gn:country_code":"CN",
    "gn:dem":83,
    "gn:feature_class":"P",
    "gn:feature_code":"PPL",
    "gn:name":"Paitou",
    "gn:population":0,
    "gn:timezone":"Asia/Shanghai",
    "iso:country":"CN",
    "name:und_x_variant":[
        "\u724c\u5934"
    ],
    "wof:name":"Paitou",
    "wof:placetype":"locality"
},
  "geometry": {"coordinates":[115.44992999999999,28.92048],"type":"Point"}
}