{
  "type": "Feature",
  "properties": {
    "gn:admin1_code":"14.0",
    "gn:asciiname":"Laqiang",
    "gn:country_code":"CN",
    "gn:dem":4660,
    "gn:feature_class":"P",
    "gn:feature_code":"PPL",
    "gn:name":"Laqiang",
    "gn:population":0,
    "gn:timezone":"Asia/Urumqi",
    "iso:country":"CN",
    "name:zho_x_preferred":[
        "\u62c9\u5f3a"
    ],
    "wof:name":"Laqiang",
    "wof:placetype":"locality"
},
  "geometry": {"coordinates":[88.044,28.3824],"type":"Point"}
}