{
  "type": "Feature",
  "properties": {
    "gn:admin1_code":"1.0",
    "gn:asciiname":"Lizikeng",
    "gn:country_code":"CN",
    "gn:dem":366,
    "gn:feature_class":"P",
    "gn:feature_code":"PPL",
    "gn:name":"Lizikeng",
    "gn:population":0,
    "gn:timezone":"Asia/Shanghai",
    "iso:country":"CN",
    "name:zho_x_preferred":[
        "\u91cc\u6893\u5751"
    ],
    "wof:name":"Lizikeng",
    "wof:placetype":"locality"
},
  "geometry": {"coordinates":[118.07964,29.94486],"type":"Point"}
}