{
  "type": "Feature",
  "properties": {
    "gn:admin1_code":"16",
    "gn:asciiname":"Qishuling",
    "gn:country_code":"CN",
    "gn:dem":993,
    "gn:feature_class":"P",
    "gn:feature_code":"PPL",
    "gn:name":"Qishuling",
    "gn:population":0,
    "gn:timezone":"Asia/Shanghai",
    "iso:country":"CN",
    "name:zho_x_preferred":[
        "\u6f06\u6811\u5cad"
    ],
    "wof:name":"Qishuling",
    "wof:placetype":"locality"
},
  "geometry": {"coordinates":[110.551,26.0727],"type":"Point"}
}