{
  "type": "Feature",
  "properties": {
    "gn:admin1_code":"19",
    "gn:asciiname":"Ganzhaocun",
    "gn:country_code":"CN",
    "gn:dem":307,
    "gn:feature_class":"P",
    "gn:feature_code":"PPL",
    "gn:name":"Ganzhaocun",
    "gn:population":0,
    "gn:timezone":"Asia/Shanghai",
    "iso:country":"CN",
    "name:und_x_variant":[
        "Kan-chao",
        "Ganzhao",
        "Ganzhaocun"
    ],
    "name:zho_x_preferred":[
        "\u7518\u62db\u6751"
    ],
    "wof:name":"Ganzhaocun",
    "wof:placetype":"locality"
},
  "geometry": {"coordinates":[119.84456000000002,41.24782],"type":"Point"}
}