{
  "type": "Feature",
  "properties": {
    "gn:admin1_code":"29.0",
    "gn:asciiname":"Gaofeng",
    "gn:country_code":"CN",
    "gn:dem":1555,
    "gn:feature_class":"P",
    "gn:feature_code":"PPL",
    "gn:name":"Gaofeng",
    "gn:population":0,
    "gn:timezone":"Asia/Shanghai",
    "iso:country":"CN",
    "name:zho_x_preferred":[
        "\u9ad8\u4e30"
    ],
    "wof:name":"Gaofeng",
    "wof:placetype":"locality"
},
  "geometry": {"coordinates":[102.017,25.9566],"type":"Point"}
}