{
  "type": "Feature",
  "properties": {
    "gn:admin1_code":"03",
    "gn:asciiname":"Tanxi",
    "gn:country_code":"CN",
    "gn:dem":34,
    "gn:feature_class":"P",
    "gn:feature_code":"PPLA4",
    "gn:name":"Tanxi",
    "gn:population":0,
    "gn:timezone":"Asia/Shanghai",
    "iso:country":"CN",
    "name:und_x_variant":[
        "T\u2019an-ch\u2019i",
        "T\u2019an-hsi",
        "Tanxi",
        "\u6ee9\u6eaa",
        "Tanxi Zhen",
        "\u6ee9\u6eaa\u9547"
    ],
    "wof:name":"Tanxi",
    "wof:placetype":"locality"
},
  "geometry": {"coordinates":[115.63477,28.98396],"type":"Point"}
}