{
  "type": "Feature",
  "properties": {
    "gn:admin1_code":"2.0",
    "gn:asciiname":"Qingshi",
    "gn:country_code":"CN",
    "gn:dem":7,
    "gn:feature_class":"P",
    "gn:feature_code":"PPL",
    "gn:name":"Qingshi",
    "gn:population":0,
    "gn:timezone":"Asia/Shanghai",
    "iso:country":"CN",
    "name:und_x_variant":[
        "\u9752\u77f3",
        "Qingshixiang",
        "\u9752\u77f3\u4e61"
    ],
    "wof:name":"Qingshi",
    "wof:placetype":"locality"
},
  "geometry": {"coordinates":[120.38207,30.58103],"type":"Point"}
}