{
  "type": "Feature",
  "properties": {
    "gn:admin1_code":"29.0",
    "gn:asciiname":"Guoditang",
    "gn:country_code":"CN",
    "gn:dem":1956,
    "gn:feature_class":"P",
    "gn:feature_code":"PPL",
    "gn:name":"Guoditang",
    "gn:population":0,
    "gn:timezone":"Asia/Shanghai",
    "iso:country":"CN",
    "name:zho_x_preferred":[
        "\u9505\u5e95\u5858"
    ],
    "wof:name":"Guoditang",
    "wof:placetype":"locality"
},
  "geometry": {"coordinates":[99.502,24.0117],"type":"Point"}
}