{
  "type": "Feature",
  "properties": {
    "gn:admin1_code":"5.0",
    "gn:asciiname":"Jianshegou",
    "gn:country_code":"CN",
    "gn:dem":829,
    "gn:feature_class":"P",
    "gn:feature_code":"PPL",
    "gn:name":"Jianshegou",
    "gn:population":0,
    "gn:timezone":"Asia/Shanghai",
    "iso:country":"CN",
    "name:und_x_variant":[
        "\u5efa\u8bbe\u6c9f"
    ],
    "wof:name":"Jianshegou",
    "wof:placetype":"locality"
},
  "geometry": {"coordinates":[126.66524,42.00534],"type":"Point"}
}