{
  "type": "Feature",
  "properties": {
    "gn:admin1_code":"19.0",
    "gn:asciiname":"Hongcaogoucun",
    "gn:country_code":"CN",
    "gn:dem":287,
    "gn:feature_class":"P",
    "gn:feature_code":"PPL",
    "gn:name":"Hongcaogoucun",
    "gn:population":0,
    "gn:timezone":"Asia/Shanghai",
    "iso:country":"CN",
    "name:zho_x_preferred":[
        "\u7ea2\u8349\u6c9f\u6751"
    ],
    "wof:name":"Hongcaogoucun",
    "wof:placetype":"locality"
},
  "geometry": {"coordinates":[119.92100000000001,40.90608],"type":"Point"}
}