{
  "type": "Feature",
  "properties": {
    "gn:admin1_code":"29.0",
    "gn:asciiname":"Ajia",
    "gn:country_code":"CN",
    "gn:dem":1158,
    "gn:feature_class":"P",
    "gn:feature_code":"PPL",
    "gn:name":"Ajia",
    "gn:population":0,
    "gn:timezone":"Asia/Shanghai",
    "iso:country":"CN",
    "name:zho_x_preferred":[
        "\u963f\u621b"
    ],
    "wof:name":"Ajia",
    "wof:placetype":"locality"
},
  "geometry": {"coordinates":[101.71899999999999,23.2022],"type":"Point"}
}