{
  "type": "Feature",
  "properties": {
    "gn:admin1_code":"9.0",
    "gn:asciiname":"Yingqiancun",
    "gn:country_code":"CN",
    "gn:dem":630,
    "gn:feature_class":"P",
    "gn:feature_code":"PPL",
    "gn:name":"Yingqiancun",
    "gn:population":0,
    "gn:timezone":"Asia/Shanghai",
    "iso:country":"CN",
    "name:zho_x_preferred":[
        "\u8425\u524d\u6751"
    ],
    "wof:name":"Yingqiancun",
    "wof:placetype":"locality"
},
  "geometry": {"coordinates":[111.22696000000001,34.68295],"type":"Point"}
}