{
  "type": "Feature",
  "properties": {
    "gn:admin1_code":"04",
    "gn:asciiname":"Guozhuangmiao",
    "gn:country_code":"CN",
    "gn:dem":14,
    "gn:feature_class":"P",
    "gn:feature_code":"PPL",
    "gn:name":"Guozhuangmiao",
    "gn:population":0,
    "gn:timezone":"Asia/Shanghai",
    "iso:country":"CN",
    "name:und_x_variant":[
        "Kuo-chuang-miao",
        "Guozhuangmiao"
    ],
    "wof:name":"Guozhuangmiao",
    "wof:placetype":"locality"
},
  "geometry": {"coordinates":[119.03485000000001,31.81656],"type":"Point"}
}