{
  "type": "Feature",
  "properties": {
    "gn:admin1_code":"25",
    "gn:asciiname":"Zoujiazhuang",
    "gn:country_code":"CN",
    "gn:dem":123,
    "gn:feature_class":"P",
    "gn:feature_code":"PPL",
    "gn:name":"Zoujiazhuang",
    "gn:population":0,
    "gn:timezone":"Asia/Shanghai",
    "iso:country":"CN",
    "name:zho_x_preferred":[
        "\u90b9\u5bb6\u5e84"
    ],
    "wof:name":"Zoujiazhuang",
    "wof:placetype":"locality"
},
  "geometry": {"coordinates":[119.002,35.8855],"type":"Point"}
}