{
  "type": "Feature",
  "properties": {
    "gn:country":"CN",
    "gn:fcode":"PPLA3",
    "gn:pop":113609,
    "iso:country":"CN",
    "name:ara_x_preferred":[
        "\u0645\u0627\u0628\u0627"
    ],
    "name:ben_x_preferred":[
        "\u09ae\u09be\u09ac\u09be"
    ],
    "name:chi_x_preferred":[
        "\u9a6c\u575d\u9547"
    ],
    "name:dan_x_preferred":[
        "Maba"
    ],
    "name:dut_x_preferred":[
        "Maba"
    ],
    "name:eng_x_preferred":[
        "Maba"
    ],
    "name:fin_x_preferred":[
        "Maba"
    ],
    "name:fre_x_preferred":[
        "Maba"
    ],
    "name:gre_x_preferred":[
        "\u039c\u03ac\u03bc\u03c0\u03b1"
    ],
    "name:guj_x_preferred":[
        "\u0aae\u0abe\u0aac\u0abe"
    ],
    "name:hin_x_preferred":[
        "\u092e\u093e\u092c\u093e"
    ],
    "name:ind_x_preferred":[
        "Maba"
    ],
    "name:ita_x_preferred":[
        "Maba"
    ],
    "name:kan_x_preferred":[
        "\u0cae\u0cbe\u0cac"
    ],
    "name:kor_x_preferred":[
        "\ub9c8\ubc14"
    ],
    "name:lav_x_preferred":[
        "Maba"
    ],
    "name:lit_x_preferred":[
        "Maba"
    ],
    "name:mar_x_preferred":[
        "\u092e\u093e\u092c\u093e"
    ],
    "name:may_x_preferred":[
        "Maba"
    ],
    "name:nob_x_preferred":[
        "Maba"
    ],
    "name:pol_x_preferred":[
        "Maba"
    ],
    "name:por_x_preferred":[
        "Maba"
    ],
    "name:rus_x_preferred":[
        "\u041c\u0430\u0431\u0430"
    ],
    "name:sin_x_preferred":[
        "\u0db8\u0db6\u0dcf"
    ],
    "name:spa_x_preferred":[
        "Maba"
    ],
    "name:swe_x_preferred":[
        "Maba"
    ],
    "name:tam_x_preferred":[
        "\u0bae\u0bbe\u0baa\u0bbe"
    ],
    "name:tel_x_preferred":[
        "\u0c2e\u0c3e\u0c2c\u0c3e"
    ],
    "name:tha_x_preferred":[
        "\u0e21\u0e32\u0e41\u0e1a\u0e07\u0e04\u0e4c"
    ],
    "name:tur_x_preferred":[
        "Maba"
    ],
    "name:ukr_x_preferred":[
        "\u041c\u0430\u0431\u0430"
    ],
    "name:unk_x_variant":[
        "Ch\u2019\u00fc-chiang"
    ],
    "name:urd_x_preferred":[
        "\u0645\u0627\u0628\u0627"
    ],
    "name:vie_x_preferred":[
        "Maba"
    ],
    "qs:name":"Maba",
    "qs:photos_9r":0,
    "qs:photos_sr":0,
    "qs:pop_sr":"9",
    "wof:name":"Maba",
    "wof:placetype":"locality",
    "wof:population":113609
},
  "geometry": {"coordinates":[113.59838999999999,24.68412],"type":"Point"}
}