{
  "type": "Feature",
  "properties": {
    "gn:admin1_code":"12",
    "gn:asciiname":"Tanlinhe",
    "gn:country_code":"CN",
    "gn:dem":361,
    "gn:feature_class":"P",
    "gn:feature_code":"PPL",
    "gn:name":"Tanlinhe",
    "gn:population":0,
    "gn:timezone":"Asia/Shanghai",
    "iso:country":"CN",
    "wof:name":"Tanlinhe",
    "wof:placetype":"locality"
},
  "geometry": {"coordinates":[115.84999999999999,30.48333],"type":"Point"}
}