{
  "type": "Feature",
  "properties": {
    "gn:admin1_code":"12.0",
    "gn:asciiname":"Shinanping",
    "gn:country_code":"CN",
    "gn:dem":466,
    "gn:feature_class":"P",
    "gn:feature_code":"PPL",
    "gn:name":"Shinanping",
    "gn:population":0,
    "gn:timezone":"Asia/Shanghai",
    "iso:country":"CN",
    "name:zho_x_preferred":[
        "Shinanping"
    ],
    "name:zho_x_variant":[
        "\u65bd\u5357\u576a"
    ],
    "wof:name":"Shinanping",
    "wof:placetype":"locality"
},
  "geometry": {"coordinates":[109.37267,29.38947000000001],"type":"Point"}
}