{
  "type": "Feature",
  "properties": {
    "gn:admin1_code":"6.0",
    "gn:asciiname":"Yushan",
    "gn:country_code":"CN",
    "gn:dem":2992,
    "gn:feature_class":"P",
    "gn:feature_code":"PPL",
    "gn:name":"Yushan",
    "gn:population":0,
    "gn:timezone":"Asia/Shanghai",
    "iso:country":"CN",
    "name:ceb_x_preferred":[
        "Yushan"
    ],
    "name:deu_x_preferred":[
        "Yushan"
    ],
    "name:fra_x_preferred":[
        "Yushan"
    ],
    "name:nld_x_preferred":[
        "Yushan"
    ],
    "name:nor_x_preferred":[
        "Yushan"
    ],
    "name:zho_x_preferred":[
        "\u9c7c\u5c71"
    ],
    "wof:name":"Yushan",
    "wof:placetype":"locality"
},
  "geometry": {"coordinates":[101.37235,35.69047],"type":"Point"}
}