{
  "type": "Feature",
  "properties": {
    "gn:admin1_code":"32.0",
    "gn:asciiname":"Fubuzhai",
    "gn:country_code":"CN",
    "gn:dem":2792,
    "gn:feature_class":"P",
    "gn:feature_code":"PPL",
    "gn:name":"Fubuzhai",
    "gn:population":0,
    "gn:timezone":"Asia/Shanghai",
    "iso:country":"CN",
    "name:zho_x_preferred":[
        "\u5bcc\u5e03\u5be8"
    ],
    "wof:name":"Fubuzhai",
    "wof:placetype":"locality"
},
  "geometry": {"coordinates":[103.58499999999999,31.8409],"type":"Point"}
}