{
  "type": "Feature",
  "properties": {
    "gn:admin1_code":"2.0",
    "gn:asciiname":"Hetian",
    "gn:country_code":"CN",
    "gn:dem":194,
    "gn:feature_class":"P",
    "gn:feature_code":"PPL",
    "gn:name":"Hetian",
    "gn:population":0,
    "gn:timezone":"Asia/Shanghai",
    "iso:country":"CN",
    "name:zho_x_preferred":[
        "\u8d3a\u7530"
    ],
    "wof:name":"Hetian",
    "wof:placetype":"locality"
},
  "geometry": {"coordinates":[119.22985,28.83499],"type":"Point"}
}