{
  "type": "Feature",
  "properties": {
    "gn:admin1_code":"14.0",
    "gn:asciiname":"Lagui",
    "gn:country_code":"CN",
    "gn:dem":4197,
    "gn:feature_class":"P",
    "gn:feature_code":"PPL",
    "gn:name":"Lagui",
    "gn:population":0,
    "gn:timezone":"Asia/Urumqi",
    "iso:country":"CN",
    "name:zho_x_preferred":[
        "\u62c9\u8d35"
    ],
    "wof:name":"Lagui",
    "wof:placetype":"locality"
},
  "geometry": {"coordinates":[87.8712,28.4656],"type":"Point"}
}