{
  "type": "Feature",
  "properties": {
    "gn:admin1_code":"30",
    "gn:asciiname":"He'an",
    "gn:country_code":"CN",
    "gn:dem":0,
    "gn:feature_class":"P",
    "gn:feature_code":"PPLA4",
    "gn:name":"He\u2019an",
    "gn:population":0,
    "gn:timezone":"Asia/Urumqi",
    "iso:country":"CN",
    "name:und_x_variant":[
        "He\u2019an Zhen",
        "\u548c\u5b89\u9547"
    ],
    "name:zho_x_preferred":[
        "\u548c\u5b89"
    ],
    "name:zho_x_variant":[
        "He\u2019an"
    ],
    "wof:name":"He'an",
    "wof:placetype":"locality"
},
  "geometry": {"coordinates":[110.3698,20.62951],"type":"Point"}
}