{
  "type": "Feature",
  "properties": {
    "gn:admin1_code":"10",
    "gn:asciiname":"Beihedong",
    "gn:country_code":"CN",
    "gn:dem":617,
    "gn:feature_class":"P",
    "gn:feature_code":"PPL",
    "gn:name":"Beihedong",
    "gn:population":0,
    "gn:timezone":"Asia/Shanghai",
    "iso:country":"CN",
    "name:zho_x_preferred":[
        "\u5317\u6cb3\u4e1c"
    ],
    "wof:name":"Beihedong",
    "wof:placetype":"locality"
},
  "geometry": {"coordinates":[118.83177000000001,41.36419],"type":"Point"}
}