{
  "type": "Feature",
  "properties": {
    "gn:admin1_code":"29.0",
    "gn:asciiname":"Maji",
    "gn:country_code":"CN",
    "gn:dem":1453,
    "gn:feature_class":"P",
    "gn:feature_code":"PPL",
    "gn:name":"Maji",
    "gn:population":0,
    "gn:timezone":"Asia/Shanghai",
    "iso:country":"CN",
    "name:ceb_x_preferred":[
        "Maji"
    ],
    "name:deu_x_preferred":[
        "Maji"
    ],
    "name:swe_x_preferred":[
        "Maji"
    ],
    "name:zho_x_preferred":[
        "\u9ebb\u9e21"
    ],
    "wof:name":"Maji",
    "wof:placetype":"locality"
},
  "geometry": {"coordinates":[103.181,23.0279],"type":"Point"}
}