{
  "type": "Feature",
  "properties": {
    "gn:admin1_code":"26.0",
    "gn:asciiname":"Zhoucheng",
    "gn:country_code":"CN",
    "gn:dem":572,
    "gn:feature_class":"P",
    "gn:feature_code":"PPLA4",
    "gn:name":"Zhoucheng",
    "gn:population":0,
    "gn:timezone":"Asia/Shanghai",
    "iso:country":"CN",
    "name:und_x_variant":[
        "Chou-ch\u2019eng",
        "Chou-ch\u2019eng-fu",
        "Zhoucheng"
    ],
    "name:zho_x_preferred":[
        "\u5468\u57ce"
    ],
    "wof:name":"Zhoucheng",
    "wof:placetype":"locality"
},
  "geometry": {"coordinates":[108.12111000000002,34.43639],"type":"Point"}
}