{
  "type": "Feature",
  "properties": {
    "gn:admin1_code":"11.0",
    "gn:asciiname":"Shadaowan",
    "gn:country_code":"CN",
    "gn:dem":422,
    "gn:feature_class":"P",
    "gn:feature_code":"PPL",
    "gn:name":"Shadaowan",
    "gn:population":0,
    "gn:timezone":"Asia/Shanghai",
    "iso:country":"CN",
    "name:zho_x_preferred":[
        "\u6c99\u5c9b\u6e7e"
    ],
    "wof:name":"Shadaowan",
    "wof:placetype":"locality"
},
  "geometry": {"coordinates":[109.9117,29.12762],"type":"Point"}
}