{
  "type": "Feature",
  "properties": {
    "gn:admin1_code":"29.0",
    "gn:asciiname":"Bakansao",
    "gn:country_code":"CN",
    "gn:dem":1148,
    "gn:feature_class":"P",
    "gn:feature_code":"PPL",
    "gn:name":"Bakansao",
    "gn:population":0,
    "gn:timezone":"Asia/Shanghai",
    "iso:country":"CN",
    "name:zho_x_preferred":[
        "\u53ed\u574e\u626b"
    ],
    "wof:name":"Bakansao",
    "wof:placetype":"locality"
},
  "geometry": {"coordinates":[101.417,21.5024],"type":"Point"}
}