{
  "type": "Feature",
  "properties": {
    "gn:admin1_code":"30.0",
    "gn:asciiname":"Niumeng",
    "gn:country_code":"CN",
    "gn:dem":197,
    "gn:feature_class":"P",
    "gn:feature_code":"PPL",
    "gn:name":"Niumeng",
    "gn:population":0,
    "gn:timezone":"Asia/Shanghai",
    "iso:country":"CN",
    "name:zho_x_preferred":[
        "\u626d\u8499"
    ],
    "wof:name":"Niumeng",
    "wof:placetype":"locality"
},
  "geometry": {"coordinates":[112.08727,23.544],"type":"Point"}
}