{
  "type": "Feature",
  "properties": {
    "gn:admin1_code":"32.0",
    "gn:asciiname":"Yujiaba",
    "gn:country_code":"CN",
    "gn:dem":311,
    "gn:feature_class":"P",
    "gn:feature_code":"PPL",
    "gn:name":"Yujiaba",
    "gn:population":0,
    "gn:timezone":"Asia/Shanghai",
    "iso:country":"CN",
    "name:zho_x_preferred":[
        "\u4fde\u5bb6\u575d"
    ],
    "wof:name":"Yujiaba",
    "wof:placetype":"locality"
},
  "geometry": {"coordinates":[106.363,31.1067],"type":"Point"}
}