{
  "type": "Feature",
  "properties": {
    "gn:admin1_code":"7.0",
    "gn:asciiname":"Hengli",
    "gn:country_code":"CN",
    "gn:dem":232,
    "gn:feature_class":"P",
    "gn:feature_code":"PPL",
    "gn:name":"Hengli",
    "gn:population":0,
    "gn:timezone":"Asia/Shanghai",
    "iso:country":"CN",
    "name:zho_x_preferred":[
        "\u4ea8\u91cc"
    ],
    "wof:name":"Hengli",
    "wof:placetype":"locality"
},
  "geometry": {"coordinates":[119.67571,26.80091],"type":"Point"}
}