{
  "type": "Feature",
  "properties": {
    "gn:admin1_code":"1.0",
    "gn:asciiname":"Yudaicun",
    "gn:country_code":"CN",
    "gn:dem":39,
    "gn:feature_class":"P",
    "gn:feature_code":"PPL",
    "gn:name":"Yudaicun",
    "gn:population":0,
    "gn:timezone":"Asia/Shanghai",
    "iso:country":"CN",
    "name:zho_x_preferred":[
        "\u7389\u4ee3\u6751"
    ],
    "wof:name":"Yudaicun",
    "wof:placetype":"locality"
},
  "geometry": {"coordinates":[118.4701,32.47405999999999],"type":"Point"}
}