{
  "type": "Feature",
  "properties": {
    "gn:admin1_code":"11",
    "gn:asciiname":"Lusijing",
    "gn:country_code":"CN",
    "gn:dem":289,
    "gn:feature_class":"P",
    "gn:feature_code":"PPL",
    "gn:name":"Lusijing",
    "gn:population":0,
    "gn:timezone":"Asia/Shanghai",
    "iso:country":"CN",
    "name:zho_x_preferred":[
        "\u9e6d\u9e36\u4e95"
    ],
    "wof:name":"Lusijing",
    "wof:placetype":"locality"
},
  "geometry": {"coordinates":[111.19167,27.305],"type":"Point"}
}