{
  "type": "Feature",
  "properties": {
    "gn:admin1_code":"29.0",
    "gn:asciiname":"Sagudong",
    "gn:country_code":"CN",
    "gn:dem":1369,
    "gn:feature_class":"P",
    "gn:feature_code":"PPL",
    "gn:name":"Sagudong",
    "gn:population":0,
    "gn:timezone":"Asia/Shanghai",
    "iso:country":"CN",
    "name:zho_x_preferred":[
        "\u6d12\u8c37\u6d1e"
    ],
    "wof:name":"Sagudong",
    "wof:placetype":"locality"
},
  "geometry": {"coordinates":[98.4901,24.7768],"type":"Point"}
}