{
  "type": "Feature",
  "properties": {
    "gn:admin1_code":"30.0",
    "gn:asciiname":"Paisha",
    "gn:country_code":"CN",
    "gn:dem":5,
    "gn:feature_class":"P",
    "gn:feature_code":"PPL",
    "gn:name":"Paisha",
    "gn:population":0,
    "gn:timezone":"Asia/Shanghai",
    "iso:country":"CN",
    "name:zho_x_preferred":[
        "\u6392\u6c99"
    ],
    "wof:name":"Paisha",
    "wof:placetype":"locality"
},
  "geometry": {"coordinates":[113.03695999999999,22.84871],"type":"Point"}
}