{
  "type": "Feature",
  "properties": {
    "gn:admin1_code":"15.0",
    "gn:asciiname":"Shangshilei",
    "gn:country_code":"CN",
    "gn:dem":2194,
    "gn:feature_class":"P",
    "gn:feature_code":"PPL",
    "gn:name":"Shangshilei",
    "gn:population":0,
    "gn:timezone":"Asia/Shanghai",
    "iso:country":"CN",
    "name:zho_x_preferred":[
        "\u4e0a\u77f3\u78ca"
    ],
    "wof:name":"Shangshilei",
    "wof:placetype":"locality"
},
  "geometry": {"coordinates":[103.462,35.4262],"type":"Point"}
}