{
  "type": "Feature",
  "properties": {
    "gn:admin1_code":"7.0",
    "gn:asciiname":"Yingtaoling",
    "gn:country_code":"CN",
    "gn:dem":853,
    "gn:feature_class":"P",
    "gn:feature_code":"PPL",
    "gn:name":"Yingtaoling",
    "gn:population":0,
    "gn:timezone":"Asia/Shanghai",
    "iso:country":"CN",
    "name:und_x_variant":[
        "\u6a31\u6843\u5cad"
    ],
    "name:zho_x_preferred":[
        "\u6a31\u6843\u5cad"
    ],
    "wof:name":"Yingtaoling",
    "wof:placetype":"locality"
},
  "geometry": {"coordinates":[116.91432,26.778],"type":"Point"}
}