{
  "type": "Feature",
  "properties": {
    "gn:admin1_code":"10",
    "gn:asciiname":"Dashimen",
    "gn:country_code":"CN",
    "gn:dem":824,
    "gn:feature_class":"P",
    "gn:feature_code":"PPL",
    "gn:name":"Dashimen",
    "gn:population":0,
    "gn:timezone":"Asia/Shanghai",
    "iso:country":"CN",
    "name:zho_x_preferred":[
        "\u5927\u77f3\u95e8"
    ],
    "wof:name":"Dashimen",
    "wof:placetype":"locality"
},
  "geometry": {"coordinates":[117.84938,41.7431],"type":"Point"}
}