{
  "type": "Feature",
  "properties": {
    "gn:admin1_code":"4.0",
    "gn:asciiname":"Liuqiandang",
    "gn:country_code":"CN",
    "gn:dem":7,
    "gn:feature_class":"P",
    "gn:feature_code":"PPL",
    "gn:name":"Liuqiandang",
    "gn:population":0,
    "gn:timezone":"Asia/Shanghai",
    "iso:country":"CN",
    "name:zho_x_preferred":[
        "\u516d\u5343\u8361"
    ],
    "wof:name":"Liuqiandang",
    "wof:placetype":"locality"
},
  "geometry": {"coordinates":[120.83432000000001,32.1208],"type":"Point"}
}