{
  "type": "Feature",
  "properties": {
    "gn:admin1_code":"1.0",
    "gn:asciiname":"Badouchencun",
    "gn:country_code":"CN",
    "gn:dem":58,
    "gn:feature_class":"P",
    "gn:feature_code":"PPL",
    "gn:name":"Badouchencun",
    "gn:population":0,
    "gn:timezone":"Asia/Shanghai",
    "iso:country":"CN",
    "name:zho_x_preferred":[
        "\u7b06\u6597\u9648\u6751"
    ],
    "wof:name":"Badouchencun",
    "wof:placetype":"locality"
},
  "geometry": {"coordinates":[117.87231,32.81692],"type":"Point"}
}