{
  "type": "Feature",
  "properties": {
    "gn:admin1_code":"29.0",
    "gn:asciiname":"Lewai",
    "gn:country_code":"CN",
    "gn:dem":2029,
    "gn:feature_class":"P",
    "gn:feature_code":"PPL",
    "gn:name":"Lewai",
    "gn:population":0,
    "gn:timezone":"Asia/Shanghai",
    "iso:country":"CN",
    "name:zho_x_preferred":[
        "\u52d2\u5916"
    ],
    "wof:name":"Lewai",
    "wof:placetype":"locality"
},
  "geometry": {"coordinates":[102.17700000000001,25.5713],"type":"Point"}
}