{
  "type": "Feature",
  "properties": {
    "gn:admin1_code":"32.0",
    "gn:asciiname":"Luowu'amo",
    "gn:country_code":"CN",
    "gn:dem":2469,
    "gn:feature_class":"P",
    "gn:feature_code":"PPL",
    "gn:name":"Luowu\u2019amo",
    "gn:population":0,
    "gn:timezone":"Asia/Shanghai",
    "iso:country":"CN",
    "name:und_x_variant":[
        "Luowu\u2019amo"
    ],
    "name:zho_x_preferred":[
        "\u6d1b\u4e94\u963f\u83ab"
    ],
    "wof:name":"Luowu'amo",
    "wof:placetype":"locality"
},
  "geometry": {"coordinates":[102.91800000000001,28.0103],"type":"Point"}
}