{
  "type": "Feature",
  "properties": {
    "gn:admin1_code":"11.0",
    "gn:asciiname":"Longwei",
    "gn:country_code":"CN",
    "gn:dem":915,
    "gn:feature_class":"P",
    "gn:feature_code":"PPL",
    "gn:name":"Longwei",
    "gn:population":0,
    "gn:timezone":"Asia/Shanghai",
    "iso:country":"CN",
    "name:zho_x_preferred":[
        "\u5785\u5c3e"
    ],
    "wof:name":"Longwei",
    "wof:placetype":"locality"
},
  "geometry": {"coordinates":[113.41288,25.56489],"type":"Point"}
}