{
  "type": "Feature",
  "properties": {
    "gn:admin1_code":"23.0",
    "gn:asciiname":"Donghai",
    "gn:country_code":"CN",
    "gn:dem":3,
    "gn:feature_class":"P",
    "gn:feature_code":"PPL",
    "gn:name":"Donghai",
    "gn:population":0,
    "gn:timezone":"Asia/Shanghai",
    "iso:country":"CN",
    "name:ceb_x_preferred":[
        "Donghai"
    ],
    "name:deu_x_preferred":[
        "Donghai"
    ],
    "name:mlg_x_preferred":[
        "Donghai"
    ],
    "name:nor_x_preferred":[
        "Donghai"
    ],
    "name:vie_x_preferred":[
        "\u0110\u00f4ng H\u1ea3i"
    ],
    "name:zho_x_preferred":[
        "Donghai"
    ],
    "name:zho_x_variant":[
        "\u4e1c\u6d77"
    ],
    "wof:name":"Donghai",
    "wof:placetype":"locality"
},
  "geometry": {"coordinates":[121.83279,31.48181],"type":"Point"}
}