{
  "type": "Feature",
  "properties": {
    "gn:admin1_code":"03",
    "gn:asciiname":"Gucun",
    "gn:cc2":"CN",
    "gn:country_code":"CN",
    "gn:dem":41,
    "gn:feature_class":"P",
    "gn:feature_code":"PPL",
    "gn:name":"Gucun",
    "gn:population":0,
    "gn:timezone":"Asia/Shanghai",
    "iso:country":"CN",
    "name:und_x_variant":[
        "Ku-ts\u2019un",
        "Gucun"
    ],
    "wof:name":"Gucun",
    "wof:placetype":"locality"
},
  "geometry": {"coordinates":[115.01667,27.43333],"type":"Point"}
}