{
  "type": "Feature",
  "properties": {
    "gn:admin1_code":"30",
    "gn:asciiname":"Shijiao",
    "gn:country_code":"CN",
    "gn:dem":34,
    "gn:feature_class":"P",
    "gn:feature_code":"PPL",
    "gn:name":"Shijiao",
    "gn:population":0,
    "gn:timezone":"Asia/Urumqi",
    "iso:country":"CN",
    "name:zho_x_preferred":[
        "\u77f3\u89d2"
    ],
    "wof:name":"Shijiao",
    "wof:placetype":"locality"
},
  "geometry": {"coordinates":[111.20065,21.79126],"type":"Point"}
}