{
  "type": "Feature",
  "properties": {
    "gn:admin1_code":"10.0",
    "gn:asciiname":"Huangzhangtou",
    "gn:country_code":"CN",
    "gn:dem":212,
    "gn:feature_class":"P",
    "gn:feature_code":"PPL",
    "gn:name":"Huangzhangtou",
    "gn:population":0,
    "gn:timezone":"Asia/Shanghai",
    "iso:country":"CN",
    "name:und_x_variant":[
        "\u9ec4\u638c\u5934"
    ],
    "wof:name":"Huangzhangtou",
    "wof:placetype":"locality"
},
  "geometry": {"coordinates":[114.33005,38.59342],"type":"Point"}
}