{
  "type": "Feature",
  "properties": {
    "gn:admin1_code":"2",
    "gn:asciiname":"Shangcun",
    "gn:country_code":"CN",
    "gn:dem":313,
    "gn:feature_class":"P",
    "gn:feature_code":"PPL",
    "gn:name":"Shangcun",
    "gn:population":0,
    "gn:timezone":"Asia/Shanghai",
    "iso:country":"CN",
    "name:und_x_variant":[
        "\u4e0a\u6751"
    ],
    "name:zho_x_preferred":[
        "\u4e0a\u6751"
    ],
    "wof:name":"Shangcun",
    "wof:placetype":"locality"
},
  "geometry": {"coordinates":[120.52198,29.2883],"type":"Point"}
}