{
  "type": "Feature",
  "properties": {
    "gn:admin1_code":"32.0",
    "gn:asciiname":"Tongmashu",
    "gn:country_code":"CN",
    "gn:dem":1337,
    "gn:feature_class":"P",
    "gn:feature_code":"PPL",
    "gn:name":"Tongmashu",
    "gn:population":0,
    "gn:timezone":"Asia/Shanghai",
    "iso:country":"CN",
    "name:zho_x_preferred":[
        "\u6850\u9ebb\u6811"
    ],
    "wof:name":"Tongmashu",
    "wof:placetype":"locality"
},
  "geometry": {"coordinates":[104.52978,31.92905],"type":"Point"}
}