{
  "type": "Feature",
  "properties": {
    "gn:admin1_code":"6.0",
    "gn:asciiname":"Ningrui",
    "gn:country_code":"CN",
    "gn:dem":4429,
    "gn:feature_class":"P",
    "gn:feature_code":"PPL",
    "gn:name":"Ningrui",
    "gn:population":0,
    "gn:timezone":"Asia/Urumqi",
    "iso:country":"CN",
    "name:zho_x_preferred":[
        "\u5b81\u745e"
    ],
    "wof:name":"Ningrui",
    "wof:placetype":"locality"
},
  "geometry": {"coordinates":[95.56632,32.99587],"type":"Point"}
}