{
  "type": "Feature",
  "properties": {
    "gn:admin1_code":"18",
    "gn:asciiname":"Dajuegou",
    "gn:country_code":"CN",
    "gn:dem":1920,
    "gn:feature_class":"P",
    "gn:feature_code":"PPL",
    "gn:name":"Dajuegou",
    "gn:population":0,
    "gn:timezone":"Asia/Shanghai",
    "iso:country":"CN",
    "name:zho_x_preferred":[
        "\u6253\u8568\u6c9f"
    ],
    "wof:name":"Dajuegou",
    "wof:placetype":"locality"
},
  "geometry": {"coordinates":[104.613,27.1227],"type":"Point"}
}