{
  "type": "Feature",
  "properties": {
    "gn:admin1_code":"30.0",
    "gn:asciiname":"Zhekoulou",
    "gn:country_code":"CN",
    "gn:dem":188,
    "gn:feature_class":"P",
    "gn:feature_code":"PPL",
    "gn:name":"Zhekoulou",
    "gn:population":0,
    "gn:timezone":"Asia/Shanghai",
    "iso:country":"CN",
    "name:zho_x_preferred":[
        "\u67d8\u53e3\u697c"
    ],
    "wof:name":"Zhekoulou",
    "wof:placetype":"locality"
},
  "geometry": {"coordinates":[115.38213,23.43882],"type":"Point"}
}