{
  "type": "Feature",
  "properties": {
    "gn:admin1_code":"05",
    "gn:asciiname":"Niuxin",
    "gn:cc2":"CN",
    "gn:country_code":"CN",
    "gn:dem":318,
    "gn:feature_class":"P",
    "gn:feature_code":"PPL",
    "gn:name":"Niuxin",
    "gn:population":0,
    "gn:timezone":"Asia/Shanghai",
    "iso:country":"CN",
    "name:und_x_variant":[
        "Niu-hsin-ting-t\u2019un",
        "Niu-hsin",
        "Nan-niu-hsin-ting",
        "Niuxin"
    ],
    "wof:name":"Niuxin",
    "wof:placetype":"locality"
},
  "geometry": {"coordinates":[126.14556,42.87417],"type":"Point"}
}