{
  "type": "Feature",
  "properties": {
    "gn:admin1_code":"18",
    "gn:asciiname":"Naqiao",
    "gn:country_code":"CN",
    "gn:dem":1229,
    "gn:feature_class":"P",
    "gn:feature_code":"PPL",
    "gn:name":"Naqiao",
    "gn:population":0,
    "gn:timezone":"Asia/Shanghai",
    "iso:country":"CN",
    "name:zho_x_preferred":[
        "\u7eb3\u6865"
    ],
    "wof:name":"Naqiao",
    "wof:placetype":"locality"
},
  "geometry": {"coordinates":[105.434,25.229],"type":"Point"}
}