{
  "type": "Feature",
  "properties": {
    "gn:admin1_code":"02",
    "gn:asciiname":"Macheyucun",
    "gn:country_code":"CN",
    "gn:dem":6,
    "gn:feature_class":"P",
    "gn:feature_code":"PPL",
    "gn:name":"Macheyucun",
    "gn:population":0,
    "gn:timezone":"Asia/Shanghai",
    "iso:country":"CN",
    "name:und_x_variant":[
        "Macheyu",
        "Macheyucun"
    ],
    "name:zho_x_preferred":[
        "\u9ebb\u8f66\u5c7f"
    ],
    "name:zho_x_variant":[
        "\u9ebb\u8f66\u5c7f\u6751"
    ],
    "wof:name":"Macheyucun",
    "wof:placetype":"locality"
},
  "geometry": {"coordinates":[121.27081,28.4531],"type":"Point"}
}