{
  "type": "Feature",
  "properties": {
    "gn:admin1_code":"29.0",
    "gn:asciiname":"Simuduo",
    "gn:country_code":"CN",
    "gn:dem":2157,
    "gn:feature_class":"P",
    "gn:feature_code":"PPL",
    "gn:name":"Simuduo",
    "gn:population":0,
    "gn:timezone":"Asia/Shanghai",
    "iso:country":"CN",
    "name:zho_x_preferred":[
        "\u601d\u6728\u591a"
    ],
    "wof:name":"Simuduo",
    "wof:placetype":"locality"
},
  "geometry": {"coordinates":[101.13,26.8696],"type":"Point"}
}