{
  "type": "Feature",
  "properties": {
    "gn:admin1_code":"23",
    "gn:asciiname":"Chunshen",
    "gn:country_code":"CN",
    "gn:dem":7,
    "gn:feature_class":"P",
    "gn:feature_code":"PPL",
    "gn:name":"Chunshen",
    "gn:population":0,
    "gn:timezone":"Asia/Shanghai",
    "iso:country":"CN",
    "name:und_x_variant":[
        "\u6625\u7533"
    ],
    "wof:name":"Chunshen",
    "wof:placetype":"locality"
},
  "geometry": {"coordinates":[121.35679,31.08473],"type":"Point"}
}