{
  "type": "Feature",
  "properties": {
    "gn:admin1_code":"29.0",
    "gn:asciiname":"Menglangtian",
    "gn:country_code":"CN",
    "gn:dem":1371,
    "gn:feature_class":"P",
    "gn:feature_code":"PPL",
    "gn:name":"Menglangtian",
    "gn:population":0,
    "gn:timezone":"Asia/Shanghai",
    "iso:country":"CN",
    "name:zho_x_preferred":[
        "\u52d0\u6d6a\u7530"
    ],
    "wof:name":"Menglangtian",
    "wof:placetype":"locality"
},
  "geometry": {"coordinates":[99.03279999999999,24.0847],"type":"Point"}
}