{
  "type": "Feature",
  "properties": {
    "gn:admin1_code":"30",
    "gn:asciiname":"Fuzhou",
    "gn:country_code":"CN",
    "gn:dem":70,
    "gn:feature_class":"P",
    "gn:feature_code":"PPL",
    "gn:name":"Fuzhou",
    "gn:population":0,
    "gn:timezone":"Asia/Shanghai",
    "iso:country":"CN",
    "name:rus_x_preferred":[
        "\u0424\u0443\u0447\u0436\u043e\u0443"
    ],
    "name:zho_x_preferred":[
        "\u5bcc\u5dde"
    ],
    "wof:name":"Fuzhou",
    "wof:placetype":"locality"
},
  "geometry": {"coordinates":[116.59932999999999,24.17034],"type":"Point"}
}