{
  "type": "Feature",
  "properties": {
    "gn:admin1_code":"12.0",
    "gn:asciiname":"Lihua",
    "gn:country_code":"CN",
    "gn:dem":167,
    "gn:feature_class":"P",
    "gn:feature_code":"PPL",
    "gn:name":"Lihua",
    "gn:population":0,
    "gn:timezone":"Asia/Shanghai",
    "iso:country":"CN",
    "name:zho_x_preferred":[
        "Lihua"
    ],
    "name:zho_x_variant":[
        "\u674e\u534e"
    ],
    "wof:name":"Lihua",
    "wof:placetype":"locality"
},
  "geometry": {"coordinates":[114.66347,29.75669000000001],"type":"Point"}
}