{
  "type": "Feature",
  "properties": {
    "gn:admin1_code":"25.0",
    "gn:asciiname":"Houdicun",
    "gn:country_code":"CN",
    "gn:dem":54,
    "gn:feature_class":"P",
    "gn:feature_code":"PPL",
    "gn:name":"Houdicun",
    "gn:population":0,
    "gn:timezone":"Asia/Shanghai",
    "iso:country":"CN",
    "name:zho_x_preferred":[
        "\u540e\u5824\u6751"
    ],
    "wof:name":"Houdicun",
    "wof:placetype":"locality"
},
  "geometry": {"coordinates":[120.47653,36.77399000000001],"type":"Point"}
}