{
  "type": "Feature",
  "properties": {
    "gn:admin1_code":"12.0",
    "gn:asciiname":"Fangjia Yazi",
    "gn:country_code":"CN",
    "gn:dem":597,
    "gn:feature_class":"P",
    "gn:feature_code":"PPL",
    "gn:name":"Fangjia Yazi",
    "gn:population":0,
    "gn:timezone":"Asia/Shanghai",
    "iso:country":"CN",
    "name:zho_x_preferred":[
        "\u65b9\u5bb6\u57ad\u5b50"
    ],
    "wof:name":"Fangjia Yazi",
    "wof:placetype":"locality"
},
  "geometry": {"coordinates":[110.04894,32.21055],"type":"Point"}
}