{
  "type": "Feature",
  "properties": {
    "gn:admin1_code":"33.0",
    "gn:asciiname":"Zhejinzi",
    "gn:country_code":"CN",
    "gn:dem":474,
    "gn:feature_class":"P",
    "gn:feature_code":"PPL",
    "gn:name":"Zhejinzi",
    "gn:population":0,
    "gn:timezone":"Asia/Shanghai",
    "iso:country":"CN",
    "name:zho_x_preferred":[
        "\u6298\u91d1\u5b50"
    ],
    "wof:name":"Zhejinzi",
    "wof:placetype":"locality"
},
  "geometry": {"coordinates":[107.96427,30.95982],"type":"Point"}
}