{
  "type": "Feature",
  "properties": {
    "gn:admin1_code":"29.0",
    "gn:asciiname":"Huangjia",
    "gn:country_code":"CN",
    "gn:dem":1338,
    "gn:feature_class":"P",
    "gn:feature_code":"PPL",
    "gn:name":"Huangjia",
    "gn:population":0,
    "gn:timezone":"Asia/Shanghai",
    "iso:country":"CN",
    "name:zho_x_preferred":[
        "\u9ec4\u5bb6"
    ],
    "wof:name":"Huangjia",
    "wof:placetype":"locality"
},
  "geometry": {"coordinates":[100.31,24.4665],"type":"Point"}
}