{
  "type": "Feature",
  "properties": {
    "gn:admin1_code":"3.0",
    "gn:asciiname":"Zichaping",
    "gn:country_code":"CN",
    "gn:dem":642,
    "gn:feature_class":"P",
    "gn:feature_code":"PPL",
    "gn:name":"Zichaping",
    "gn:population":0,
    "gn:timezone":"Asia/Shanghai",
    "iso:country":"CN",
    "name:zho_x_preferred":[
        "\u7d2b\u8336\u576a"
    ],
    "wof:name":"Zichaping",
    "wof:placetype":"locality"
},
  "geometry": {"coordinates":[114.22499999999999,28.5018],"type":"Point"}
}