{
  "type": "Feature",
  "properties": {
    "gn:admin1_code":"15.0",
    "gn:asciiname":"Haochuan",
    "gn:country_code":"CN",
    "gn:dem":1417,
    "gn:feature_class":"P",
    "gn:feature_code":"PPL",
    "gn:name":"Haochuan",
    "gn:population":0,
    "gn:timezone":"Asia/Shanghai",
    "iso:country":"CN",
    "name:zho_x_preferred":[
        "\u84bf\u5ddd"
    ],
    "wof:name":"Haochuan",
    "wof:placetype":"locality"
},
  "geometry": {"coordinates":[106.256,34.0222],"type":"Point"}
}