{
  "type": "Feature",
  "properties": {
    "gn:admin1_code":"16.0",
    "gn:asciiname":"Baihuachong",
    "gn:country_code":"CN",
    "gn:dem":288,
    "gn:feature_class":"P",
    "gn:feature_code":"PPL",
    "gn:name":"Baihuachong",
    "gn:population":0,
    "gn:timezone":"Asia/Shanghai",
    "iso:country":"CN",
    "name:zho_x_preferred":[
        "\u767d\u82b1\u51b2"
    ],
    "wof:name":"Baihuachong",
    "wof:placetype":"locality"
},
  "geometry": {"coordinates":[110.247,23.0054],"type":"Point"}
}