{
  "type": "Feature",
  "properties": {
    "gn:admin1_code":"29.0",
    "gn:asciiname":"Tianchongzi",
    "gn:country_code":"CN",
    "gn:dem":1882,
    "gn:feature_class":"P",
    "gn:feature_code":"PPL",
    "gn:name":"Tianchongzi",
    "gn:population":0,
    "gn:timezone":"Asia/Shanghai",
    "iso:country":"CN",
    "name:zho_x_preferred":[
        "\u7530\u51b2\u5b50"
    ],
    "wof:name":"Tianchongzi",
    "wof:placetype":"locality"
},
  "geometry": {"coordinates":[103.72799999999999,24.0404],"type":"Point"}
}