{
  "type": "Feature",
  "properties": {
    "gn:admin1_code":"5.0",
    "gn:asciiname":"Suojuli",
    "gn:country_code":"CN",
    "gn:dem":330,
    "gn:feature_class":"P",
    "gn:feature_code":"PPL",
    "gn:name":"Suojuli",
    "gn:population":0,
    "gn:timezone":"Asia/Shanghai",
    "iso:country":"CN",
    "name:und_x_variant":[
        "So-ch\u00fc-li"
    ],
    "wof:name":"Suojuli",
    "wof:placetype":"locality"
},
  "geometry": {"coordinates":[129.66262,42.43941],"type":"Point"}
}