{
  "type": "Feature",
  "properties": {
    "gn:admin1_code":"30",
    "gn:asciiname":"Hengshan",
    "gn:country_code":"CN",
    "gn:dem":35,
    "gn:feature_class":"P",
    "gn:feature_code":"PPLA4",
    "gn:name":"Hengshan",
    "gn:population":0,
    "gn:timezone":"Asia/Urumqi",
    "iso:country":"CN",
    "name:und_x_variant":[
        "Hang-shan-hsu",
        "Heng-shan-hs\u00fc",
        "Hengshan",
        "Hengshan Zhen",
        "\u6a2a\u5c71\u9547"
    ],
    "name:zho_x_preferred":[
        "\u6a2a\u5c71"
    ],
    "wof:name":"Hengshan",
    "wof:placetype":"locality"
},
  "geometry": {"coordinates":[110.06422000000001,21.4748],"type":"Point"}
}