{
  "type": "Feature",
  "properties": {
    "gn:admin1_code":"11",
    "gn:asciiname":"Fengshiyan",
    "gn:cc2":"CN",
    "gn:country_code":"CN",
    "gn:dem":137,
    "gn:feature_class":"P",
    "gn:feature_code":"PPL",
    "gn:name":"Fengshiyan",
    "gn:population":0,
    "gn:timezone":"Asia/Shanghai",
    "iso:country":"CN",
    "name:und_x_variant":[
        "Feng-shih-yen",
        "Fengshiyan"
    ],
    "wof:name":"Fengshiyan",
    "wof:placetype":"locality"
},
  "geometry": {"coordinates":[111.99111000000001,26.79861],"type":"Point"}
}