{
  "type": "Feature",
  "properties": {
    "gn:admin1_code":"8.0",
    "gn:asciiname":"Banzifang",
    "gn:country_code":"CN",
    "gn:dem":349,
    "gn:feature_class":"P",
    "gn:feature_code":"PPL",
    "gn:name":"Banzifang",
    "gn:population":0,
    "gn:timezone":"Asia/Shanghai",
    "iso:country":"CN",
    "name:zho_x_preferred":[
        "\u677f\u5b50\u623f"
    ],
    "wof:name":"Banzifang",
    "wof:placetype":"locality"
},
  "geometry": {"coordinates":[127.61152,45.595],"type":"Point"}
}