{
  "type": "Feature",
  "properties": {
    "gn:admin1_code":"08",
    "gn:asciiname":"Sung-chia-t'un",
    "gn:country_code":"CN",
    "gn:dem":186,
    "gn:feature_class":"P",
    "gn:feature_code":"PPL",
    "gn:name":"Sung-chia-t\u2019un",
    "gn:population":0,
    "gn:timezone":"Asia/Shanghai",
    "iso:country":"CN",
    "wof:name":"Sung-chia-t'un",
    "wof:placetype":"locality"
},
  "geometry": {"coordinates":[124.53806000000002,47.92417],"type":"Point"}
}