{
  "type": "Feature",
  "properties": {
    "gn:admin1_code":"14.0",
    "gn:asciiname":"Jiaomai",
    "gn:country_code":"CN",
    "gn:dem":4720,
    "gn:feature_class":"P",
    "gn:feature_code":"PPL",
    "gn:name":"Jiaomai",
    "gn:population":0,
    "gn:timezone":"Asia/Urumqi",
    "iso:country":"CN",
    "name:zho_x_preferred":[
        "\u811a\u9ea6"
    ],
    "wof:name":"Jiaomai",
    "wof:placetype":"locality"
},
  "geometry": {"coordinates":[88.1369,29.4604],"type":"Point"}
}