{
  "type": "Feature",
  "properties": {
    "gn:admin1_code":"19",
    "gn:asciiname":"Xiahecun",
    "gn:country_code":"CN",
    "gn:dem":191,
    "gn:feature_class":"P",
    "gn:feature_code":"PPL",
    "gn:name":"Xiahecun",
    "gn:population":0,
    "gn:timezone":"Asia/Shanghai",
    "iso:country":"CN",
    "name:und_x_variant":[
        "Xiahe"
    ],
    "name:zho_x_preferred":[
        "\u5ce1\u6cb3\u6751"
    ],
    "wof:name":"Xiahecun",
    "wof:placetype":"locality"
},
  "geometry": {"coordinates":[123.97915999999999,41.64772],"type":"Point"}
}