{
  "type": "Feature",
  "properties": {
    "gn:admin1_code":"9.0",
    "gn:asciiname":"Wogou",
    "gn:country_code":"CN",
    "gn:dem":225,
    "gn:feature_class":"P",
    "gn:feature_code":"PPL",
    "gn:name":"Wogou",
    "gn:population":0,
    "gn:timezone":"Asia/Shanghai",
    "iso:country":"CN",
    "name:und_x_variant":[
        "\u6c83\u6c9f",
        "Wogou"
    ],
    "wof:name":"Wogou",
    "wof:placetype":"locality"
},
  "geometry": {"coordinates":[112.5938,33.66498],"type":"Point"}
}