{
  "type": "Feature",
  "properties": {
    "gn:admin1_code":"16.0",
    "gn:asciiname":"Chayuan",
    "gn:country_code":"CN",
    "gn:dem":278,
    "gn:feature_class":"P",
    "gn:feature_code":"PPL",
    "gn:name":"Chayuan",
    "gn:population":0,
    "gn:timezone":"Asia/Shanghai",
    "iso:country":"CN",
    "name:zho_x_preferred":[
        "\u8336\u6e90"
    ],
    "wof:name":"Chayuan",
    "wof:placetype":"locality"
},
  "geometry": {"coordinates":[111.20699999999999,24.6367],"type":"Point"}
}