{
  "type": "Feature",
  "properties": {
    "gn:admin1_code":"9.0",
    "gn:asciiname":"Jiaoyuan",
    "gn:country_code":"CN",
    "gn:dem":847,
    "gn:feature_class":"P",
    "gn:feature_code":"PPL",
    "gn:name":"Jiaoyuan",
    "gn:population":0,
    "gn:timezone":"Asia/Shanghai",
    "iso:country":"CN",
    "name:und_x_variant":[
        "\u7126\u56ed",
        "Jiaoyuan"
    ],
    "wof:name":"Jiaoyuan",
    "wof:placetype":"locality"
},
  "geometry": {"coordinates":[112.16105,33.67719],"type":"Point"}
}