{
  "type": "Feature",
  "properties": {
    "gn:admin1_code":"12.0",
    "gn:asciiname":"Hejiaxiang",
    "gn:country_code":"CN",
    "gn:dem":31,
    "gn:feature_class":"P",
    "gn:feature_code":"PPL",
    "gn:name":"Hejiaxiang",
    "gn:population":0,
    "gn:timezone":"Asia/Shanghai",
    "iso:country":"CN",
    "name:zho_x_preferred":[
        "\u8d3a\u5bb6\u5df7"
    ],
    "wof:name":"Hejiaxiang",
    "wof:placetype":"locality"
},
  "geometry": {"coordinates":[113.01243999999998,30.6072],"type":"Point"}
}