{
  "type": "Feature",
  "properties": {
    "gn:admin1_code":"15.0",
    "gn:asciiname":"Zhuojiagou",
    "gn:country_code":"CN",
    "gn:dem":1883,
    "gn:feature_class":"P",
    "gn:feature_code":"PPL",
    "gn:name":"Zhuojiagou",
    "gn:population":0,
    "gn:timezone":"Asia/Shanghai",
    "iso:country":"CN",
    "name:zho_x_preferred":[
        "\u5353\u5bb6\u6c9f"
    ],
    "wof:name":"Zhuojiagou",
    "wof:placetype":"locality"
},
  "geometry": {"coordinates":[103.85899999999999,36.012],"type":"Point"}
}