{
  "type": "Feature",
  "properties": {
    "gn:admin1_code":"24",
    "gn:asciiname":"Zhangxihe",
    "gn:cc2":"CN",
    "gn:country_code":"CN",
    "gn:dem":1095,
    "gn:feature_class":"P",
    "gn:feature_code":"PPL",
    "gn:name":"Zhangxihe",
    "gn:population":0,
    "gn:timezone":"Asia/Shanghai",
    "iso:country":"CN",
    "name:und_x_variant":[
        "Chang-hsi-ho-ts\u2019un",
        "Chang-hsi-ho",
        "Zhangxihe"
    ],
    "wof:name":"Zhangxihe",
    "wof:placetype":"locality"
},
  "geometry": {"coordinates":[114.22750000000001,40.4375],"type":"Point"}
}