{
  "type": "Feature",
  "properties": {
    "gn:admin1_code":"25",
    "gn:asciiname":"Erqilou",
    "gn:country_code":"CN",
    "gn:dem":242,
    "gn:feature_class":"P",
    "gn:feature_code":"PPL",
    "gn:name":"Erqilou",
    "gn:population":0,
    "gn:timezone":"Asia/Shanghai",
    "iso:country":"CN",
    "name:zho_x_preferred":[
        "\u4e8c\u8d77\u697c"
    ],
    "wof:name":"Erqilou",
    "wof:placetype":"locality"
},
  "geometry": {"coordinates":[116.86499999999999,36.1501],"type":"Point"}
}