{
  "type": "Feature",
  "properties": {
    "gn:admin1_code":"12.0",
    "gn:asciiname":"Xixiba",
    "gn:country_code":"CN",
    "gn:dem":786,
    "gn:feature_class":"P",
    "gn:feature_code":"PPL",
    "gn:name":"Xixiba",
    "gn:population":0,
    "gn:timezone":"Asia/Shanghai",
    "iso:country":"CN",
    "name:zho_x_preferred":[
        "\u897f\u6eaa\u575d"
    ],
    "wof:name":"Xixiba",
    "wof:placetype":"locality"
},
  "geometry": {"coordinates":[110.20385,31.08943],"type":"Point"}
}