{
  "type": "Feature",
  "properties": {
    "gn:admin1_code":"14.0",
    "gn:asciiname":"Sangkyi",
    "gn:country_code":"CN",
    "gn:dem":3537,
    "gn:feature_class":"P",
    "gn:feature_code":"PPLF",
    "gn:name":"Sangkyi",
    "gn:population":0,
    "gn:timezone":"Asia/Urumqi",
    "iso:country":"CN",
    "name:bod_x_preferred":[
        "Sangkyi"
    ],
    "name:zho_x_preferred":[
        "Songxi"
    ],
    "name:zho_x_variant":[
        "\u5b8b\u897f"
    ],
    "wof:name":"Sangkyi",
    "wof:placetype":"locality"
},
  "geometry": {"coordinates":[98.35111999999999,30.98465],"type":"Point"}
}