{
  "type": "Feature",
  "properties": {
    "gn:admin1_code":"18.0",
    "gn:asciiname":"Huangpao Shangzhai",
    "gn:country_code":"CN",
    "gn:dem":631,
    "gn:feature_class":"P",
    "gn:feature_code":"PPL",
    "gn:name":"Huangpao Shangzhai",
    "gn:population":0,
    "gn:timezone":"Asia/Shanghai",
    "iso:country":"CN",
    "name:zho_x_preferred":[
        "\u9ec4\u6ce1\u4e0a\u5be8"
    ],
    "wof:name":"Huangpao Shangzhai",
    "wof:placetype":"locality"
},
  "geometry": {"coordinates":[108.253,26.7964],"type":"Point"}
}