{
  "type": "Feature",
  "properties": {
    "gn:admin1_code":"18",
    "gn:asciiname":"Randa",
    "gn:country_code":"CN",
    "gn:dem":1016,
    "gn:feature_class":"P",
    "gn:feature_code":"PPL",
    "gn:name":"Randa",
    "gn:population":0,
    "gn:timezone":"Asia/Shanghai",
    "iso:country":"CN",
    "name:zho_x_preferred":[
        "\u7136\u8fbe"
    ],
    "wof:name":"Randa",
    "wof:placetype":"locality"
},
  "geometry": {"coordinates":[106.265,25.2794],"type":"Point"}
}