{
  "type": "Feature",
  "properties": {
    "gn:admin1_code":"18",
    "gn:asciiname":"Randa",
    "gn:country_code":"CN",
    "gn:dem":1016,
    "gn:feature_class":"P",
    "gn:feature_code":"PPL",
    "gn:name":"Randa",
    "gn:population":0,
    "gn:timezone":"Asia/Shanghai",
    "iso:country":"CN",
    "name:cat_x_preferred":[
        "Randa"
    ],
    "name:ceb_x_preferred":[
        "Randa"
    ],
    "name:ces_x_preferred":[
        "Randa"
    ],
    "name:deu_x_preferred":[
        "Randa"
    ],
    "name:fra_x_preferred":[
        "Randa"
    ],
    "name:hun_x_preferred":[
        "Randa"
    ],
    "name:nor_x_preferred":[
        "Randa"
    ],
    "name:rus_x_preferred":[
        "\u0420\u0430\u043d\u0434\u0430"
    ],
    "name:spa_x_preferred":[
        "Randa"
    ],
    "name:swe_x_preferred":[
        "Randa"
    ],
    "name:zho_x_preferred":[
        "\u7136\u8fbe"
    ],
    "wof:name":"Randa",
    "wof:placetype":"locality"
},
  "geometry": {"coordinates":[106.265,25.2794],"type":"Point"}
}