{
  "type": "Feature",
  "properties": {
    "gn:admin1_code":"7.0",
    "gn:asciiname":"Dikengyang",
    "gn:country_code":"CN",
    "gn:dem":441,
    "gn:feature_class":"P",
    "gn:feature_code":"PPL",
    "gn:name":"Dikengyang",
    "gn:population":0,
    "gn:timezone":"Asia/Shanghai",
    "iso:country":"CN",
    "name:zho_x_preferred":[
        "\u5730\u5751\u6d0b"
    ],
    "wof:name":"Dikengyang",
    "wof:placetype":"locality"
},
  "geometry": {"coordinates":[117.60842,26.17883],"type":"Point"}
}