{
  "type": "Feature",
  "properties": {
    "gn:admin1_code":"5.0",
    "gn:asciiname":"Wufeng",
    "gn:country_code":"CN",
    "gn:dem":276,
    "gn:feature_class":"P",
    "gn:feature_code":"PPL",
    "gn:name":"Wufeng",
    "gn:population":0,
    "gn:timezone":"Asia/Shanghai",
    "iso:country":"CN",
    "name:ceb_x_preferred":[
        "Wufeng"
    ],
    "name:deu_x_preferred":[
        "Wufeng"
    ],
    "name:fra_x_preferred":[
        "Wufeng"
    ],
    "name:pol_x_preferred":[
        "Wufeng"
    ],
    "name:und_x_variant":[
        "\u4e94\u51e4"
    ],
    "wof:name":"Wufeng",
    "wof:placetype":"locality"
},
  "geometry": {"coordinates":[129.30000000000001,43.0356],"type":"Point"}
}