{
  "type": "Feature",
  "properties": {
    "gn:admin1_code":"12.0",
    "gn:asciiname":"Shuitianba",
    "gn:country_code":"CN",
    "gn:dem":677,
    "gn:feature_class":"P",
    "gn:feature_code":"PPL",
    "gn:name":"Shuitianba",
    "gn:population":0,
    "gn:timezone":"Asia/Shanghai",
    "iso:country":"CN",
    "name:zho_x_preferred":[
        "\u6c34\u7530\u575d"
    ],
    "wof:name":"Shuitianba",
    "wof:placetype":"locality"
},
  "geometry": {"coordinates":[109.40272,30.02652],"type":"Point"}
}