{
  "type": "Feature",
  "properties": {
    "gn:admin1_code":"9.0",
    "gn:asciiname":"Dachenying",
    "gn:country_code":"CN",
    "gn:dem":161,
    "gn:feature_class":"P",
    "gn:feature_code":"PPL",
    "gn:name":"Dachenying",
    "gn:population":0,
    "gn:timezone":"Asia/Shanghai",
    "iso:country":"CN",
    "name:zho_x_preferred":[
        "\u5927\u9648\u8425"
    ],
    "wof:name":"Dachenying",
    "wof:placetype":"locality"
},
  "geometry": {"coordinates":[112.12887000000001,32.96766],"type":"Point"}
}