{
  "type": "Feature",
  "properties": {
    "gn:admin1_code":"8.0",
    "gn:asciiname":"Xinhaicun",
    "gn:country_code":"CN",
    "gn:dem":42,
    "gn:feature_class":"P",
    "gn:feature_code":"PPL",
    "gn:name":"Xinhaicun",
    "gn:population":0,
    "gn:timezone":"Asia/Shanghai",
    "iso:country":"CN",
    "name:zho_x_preferred":[
        "\u65b0\u6d77\u6751"
    ],
    "wof:name":"Xinhaicun",
    "wof:placetype":"locality"
},
  "geometry": {"coordinates":[134.11964,48.19465],"type":"Point"}
}