{
  "type": "Feature",
  "properties": {
    "gn:admin1_code":"1.0",
    "gn:asciiname":"Sanguaidiancun",
    "gn:country_code":"CN",
    "gn:dem":50,
    "gn:feature_class":"P",
    "gn:feature_code":"PPL",
    "gn:name":"Sanguaidiancun",
    "gn:population":0,
    "gn:timezone":"Asia/Shanghai",
    "iso:country":"CN",
    "name:zho_x_preferred":[
        "\u4e09\u62d0\u5e97\u6751"
    ],
    "wof:name":"Sanguaidiancun",
    "wof:placetype":"locality"
},
  "geometry": {"coordinates":[116.3479,31.67133],"type":"Point"}
}