{
  "type": "Feature",
  "properties": {
    "gn:admin1_code":"5.0",
    "gn:asciiname":"Mengjia Wobu",
    "gn:country_code":"CN",
    "gn:dem":172,
    "gn:feature_class":"P",
    "gn:feature_code":"PPL",
    "gn:name":"Mengjia Wobu",
    "gn:population":0,
    "gn:timezone":"Asia/Shanghai",
    "iso:country":"CN",
    "name:zho_x_preferred":[
        "\u5b5f\u5bb6\u7a9d\u5821"
    ],
    "wof:name":"Mengjia Wobu",
    "wof:placetype":"locality"
},
  "geometry": {"coordinates":[125.06988,44.21556],"type":"Point"}
}