{
  "type": "Feature",
  "properties": {
    "gn:admin1_code":"8.0",
    "gn:asciiname":"Baoquanling Jiudui",
    "gn:country_code":"CN",
    "gn:dem":76,
    "gn:feature_class":"P",
    "gn:feature_code":"PPLF",
    "gn:name":"Baoquanling Jiudui",
    "gn:population":0,
    "gn:timezone":"Asia/Shanghai",
    "iso:country":"CN",
    "name:zho_x_preferred":[
        "\u5b9d\u6cc9\u5cad\u4e5d\u961f"
    ],
    "wof:name":"Baoquanling Jiudui",
    "wof:placetype":"locality"
},
  "geometry": {"coordinates":[130.75273999999999,47.36508],"type":"Point"}
}