{
  "type": "Feature",
  "properties": {
    "gn:admin1_code":"16.0",
    "gn:asciiname":"Gengdan",
    "gn:country_code":"CN",
    "gn:dem":357,
    "gn:feature_class":"P",
    "gn:feature_code":"PPL",
    "gn:name":"Gengdan",
    "gn:population":0,
    "gn:timezone":"Asia/Shanghai",
    "iso:country":"CN",
    "name:zho_x_preferred":[
        "\u66f4\u4e39"
    ],
    "wof:name":"Gengdan",
    "wof:placetype":"locality"
},
  "geometry": {"coordinates":[108.08799999999999,24.3639],"type":"Point"}
}