{
  "type": "Feature",
  "properties": {
    "gn:admin1_code":"19.0",
    "gn:asciiname":"Shangsongshangou",
    "gn:country_code":"CN",
    "gn:dem":93,
    "gn:feature_class":"P",
    "gn:feature_code":"PPL",
    "gn:name":"Shangsongshangou",
    "gn:population":0,
    "gn:timezone":"Asia/Shanghai",
    "iso:country":"CN",
    "name:und_x_variant":[
        "\u4e0a\u677e\u5c71\u6c9f"
    ],
    "name:zho_x_preferred":[
        "\u4e0a\u677e\u5c71\u6c9f"
    ],
    "wof:name":"Shangsongshangou",
    "wof:placetype":"locality"
},
  "geometry": {"coordinates":[121.53213,41.41853],"type":"Point"}
}