{
  "type": "Feature",
  "properties": {
    "gn:admin1_code":"10",
    "gn:asciiname":"Zhanghuaiying",
    "gn:country_code":"CN",
    "gn:dem":694,
    "gn:feature_class":"P",
    "gn:feature_code":"PPL",
    "gn:name":"Zhanghuaiying",
    "gn:population":0,
    "gn:timezone":"Asia/Shanghai",
    "iso:country":"CN",
    "name:zho_x_preferred":[
        "\u5f20\u6000\u8425"
    ],
    "wof:name":"Zhanghuaiying",
    "wof:placetype":"locality"
},
  "geometry": {"coordinates":[117.056,41.31175],"type":"Point"}
}