{
  "type": "Feature",
  "properties": {
    "gn:admin1_code":"32.0",
    "gn:asciiname":"Pipashu",
    "gn:country_code":"CN",
    "gn:dem":791,
    "gn:feature_class":"P",
    "gn:feature_code":"PPL",
    "gn:name":"Pipashu",
    "gn:population":0,
    "gn:timezone":"Asia/Shanghai",
    "iso:country":"CN",
    "name:zho_x_preferred":[
        "\u6787\u6777\u6811"
    ],
    "wof:name":"Pipashu",
    "wof:placetype":"locality"
},
  "geometry": {"coordinates":[102.605,29.3231],"type":"Point"}
}