{
  "type": "Feature",
  "properties": {
    "gn:admin1_code":"30",
    "gn:asciiname":"Guanqiao",
    "gn:country_code":"CN",
    "gn:dem":19,
    "gn:feature_class":"P",
    "gn:feature_code":"PPLA4",
    "gn:name":"Guanqiao",
    "gn:population":0,
    "gn:timezone":"Asia/Urumqi",
    "iso:country":"CN",
    "name:ceb_x_preferred":[
        "Guanqiao"
    ],
    "name:deu_x_preferred":[
        "Guanqiao"
    ],
    "name:swe_x_preferred":[
        "Guanqiao"
    ],
    "name:und_x_variant":[
        "Guanqiao Zhen",
        "\u5b98\u6865\u9547"
    ],
    "name:zho_x_preferred":[
        "\u5b98\u6865"
    ],
    "wof:name":"Guanqiao",
    "wof:placetype":"locality"
},
  "geometry": {"coordinates":[110.49526000000002,21.73468],"type":"Point"}
}