{
  "type": "Feature",
  "properties": {
    "gn:admin1_code":"1.0",
    "gn:asciiname":"Hengbucun",
    "gn:country_code":"CN",
    "gn:dem":9,
    "gn:feature_class":"P",
    "gn:feature_code":"PPL",
    "gn:name":"Hengbucun",
    "gn:population":0,
    "gn:timezone":"Asia/Shanghai",
    "iso:country":"CN",
    "name:zho_x_preferred":[
        "\u6a2a\u57e0\u6751"
    ],
    "wof:name":"Hengbucun",
    "wof:placetype":"locality"
},
  "geometry": {"coordinates":[117.48372000000001,30.88827],"type":"Point"}
}