{
  "type": "Feature",
  "properties": {
    "gn:admin1_code":"9.0",
    "gn:asciiname":"Yanggangcun",
    "gn:country_code":"CN",
    "gn:dem":131,
    "gn:feature_class":"P",
    "gn:feature_code":"PPL",
    "gn:name":"Yanggangcun",
    "gn:population":0,
    "gn:timezone":"Asia/Shanghai",
    "iso:country":"CN",
    "name:zho_x_preferred":[
        "\u6768\u5c97\u6751"
    ],
    "wof:name":"Yanggangcun",
    "wof:placetype":"locality"
},
  "geometry": {"coordinates":[113.12067999999999,33.8435],"type":"Point"}
}