{
  "type": "Feature",
  "properties": {
    "gn:admin1_code":"8.0",
    "gn:asciiname":"Liangbantun",
    "gn:country_code":"CN",
    "gn:dem":133,
    "gn:feature_class":"P",
    "gn:feature_code":"PPL",
    "gn:name":"Liangbantun",
    "gn:population":0,
    "gn:timezone":"Asia/Shanghai",
    "iso:country":"CN",
    "name:zho_x_preferred":[
        "\u4e24\u534a\u5c6f"
    ],
    "wof:name":"Liangbantun",
    "wof:placetype":"locality"
},
  "geometry": {"coordinates":[124.79002,46.03679],"type":"Point"}
}