{
  "type": "Feature",
  "properties": {
    "gn:admin1_code":"15.0",
    "gn:asciiname":"Liuzhongbu",
    "gn:country_code":"CN",
    "gn:dem":1515,
    "gn:feature_class":"P",
    "gn:feature_code":"PPL",
    "gn:name":"Liuzhongbu",
    "gn:population":0,
    "gn:timezone":"Asia/Shanghai",
    "iso:country":"CN",
    "name:und_x_variant":[
        "\u5218\u4e2d\u5821"
    ],
    "wof:name":"Liuzhongbu",
    "wof:placetype":"locality"
},
  "geometry": {"coordinates":[106.98493000000001,36.59875],"type":"Point"}
}