{
  "type": "Feature",
  "properties": {
    "gn:admin1_code":"7.0",
    "gn:asciiname":"Liaofang",
    "gn:country_code":"CN",
    "gn:dem":221,
    "gn:feature_class":"P",
    "gn:feature_code":"PPL",
    "gn:name":"Liaofang",
    "gn:population":0,
    "gn:timezone":"Asia/Shanghai",
    "iso:country":"CN",
    "name:und_x_variant":[
        "\u5ed6\u574a"
    ],
    "name:zho_x_preferred":[
        "\u5ed6\u574a"
    ],
    "wof:name":"Liaofang",
    "wof:placetype":"locality"
},
  "geometry": {"coordinates":[117.63539,26.77155],"type":"Point"}
}