{
  "type": "Feature",
  "properties": {
    "gn:admin1_code":"4.0",
    "gn:asciiname":"Simo",
    "gn:country_code":"CN",
    "gn:dem":5,
    "gn:feature_class":"P",
    "gn:feature_code":"PPL",
    "gn:name":"Simo",
    "gn:population":0,
    "gn:timezone":"Asia/Shanghai",
    "iso:country":"CN",
    "name:ceb_x_preferred":[
        "Simo"
    ],
    "name:deu_x_preferred":[
        "Simo"
    ],
    "name:fin_x_preferred":[
        "Simo"
    ],
    "name:fra_x_preferred":[
        "Simo"
    ],
    "name:ind_x_preferred":[
        "Simo"
    ],
    "name:ita_x_preferred":[
        "Simo"
    ],
    "name:lit_x_preferred":[
        "Simas"
    ],
    "name:nld_x_preferred":[
        "Simo"
    ],
    "name:pol_x_preferred":[
        "Simo"
    ],
    "name:spa_x_preferred":[
        "Simo"
    ],
    "name:swe_x_preferred":[
        "Simo"
    ],
    "name:zho_x_preferred":[
        "\u601d\u6a21"
    ],
    "wof:name":"Simo",
    "wof:placetype":"locality"
},
  "geometry": {"coordinates":[118.85763,32.188],"type":"Point"}
}