{
  "type": "Feature",
  "properties": {
    "gn:admin1_code":"24.0",
    "gn:asciiname":"Eshigou",
    "gn:country_code":"CN",
    "gn:dem":1489,
    "gn:feature_class":"P",
    "gn:feature_code":"PPL",
    "gn:name":"Eshigou",
    "gn:population":0,
    "gn:timezone":"Asia/Shanghai",
    "iso:country":"CN",
    "name:zho_x_preferred":[
        "\u6076\u77f3\u6c9f"
    ],
    "wof:name":"Eshigou",
    "wof:placetype":"locality"
},
  "geometry": {"coordinates":[111.92374,35.47257000000001],"type":"Point"}
}