{
  "type": "Feature",
  "properties": {
    "gn:admin1_code":"25",
    "gn:asciiname":"Hetouwangzhuang",
    "gn:country_code":"CN",
    "gn:dem":36,
    "gn:feature_class":"P",
    "gn:feature_code":"PPL",
    "gn:name":"Hetouwangzhuang",
    "gn:population":0,
    "gn:timezone":"Asia/Shanghai",
    "iso:country":"CN",
    "name:zho_x_preferred":[
        "\u6cb3\u5934\u738b\u5e84"
    ],
    "wof:name":"Hetouwangzhuang",
    "wof:placetype":"locality"
},
  "geometry": {"coordinates":[116.84999999999999,36.6413],"type":"Point"}
}