{
  "type": "Feature",
  "properties": {
    "gn:admin1_code":"30",
    "gn:asciiname":"Kejia",
    "gn:country_code":"CN",
    "gn:dem":12,
    "gn:feature_class":"P",
    "gn:feature_code":"PPL",
    "gn:name":"Kejia",
    "gn:population":0,
    "gn:timezone":"Asia/Urumqi",
    "iso:country":"CN",
    "name:und_x_variant":[
        "\u79d1\u5bb6"
    ],
    "name:zho_x_preferred":[
        "\u79d1\u5bb6"
    ],
    "wof:name":"Kejia",
    "wof:placetype":"locality"
},
  "geometry": {"coordinates":[110.45806,20.38361],"type":"Point"}
}