{
  "type": "Feature",
  "properties": {
    "gn:admin1_code":"13.0",
    "gn:asciiname":"Santanghu",
    "gn:cc2":"CN",
    "gn:country_code":"CN",
    "gn:dem":1023,
    "gn:feature_class":"P",
    "gn:feature_code":"PPL",
    "gn:name":"Santanghu",
    "gn:population":0,
    "gn:timezone":"Asia/Urumqi",
    "iso:country":"CN",
    "name:kaz_x_preferred":[
        "\u0633\u0627\u0646\u062a\u0627\u06ad\u062d\u06cb \u0627\u06cb\u0649\u0644\u0649"
    ],
    "name:uig_x_preferred":[
        "\u0633\u06d5\u0646\u062a\u0627\u06ad\u062e\u06c7 \u064a\u06d0\u0632\u0649\u0633\u0649"
    ],
    "name:und_x_variant":[
        "San-t\u2019ang-hu-ti",
        "Santokhe",
        "Santanghu",
        "Santanghu Xiang"
    ],
    "name:zho_x_preferred":[
        "\u4e09\u5858\u6e56\u4e61"
    ],
    "wof:name":"Santanghu",
    "wof:placetype":"locality"
},
  "geometry": {"coordinates":[93.33333,44.23333],"type":"Point"}
}