{
  "type": "Feature",
  "properties": {
    "gn:admin1_code":"19.0",
    "gn:asciiname":"Dawangou",
    "gn:country_code":"CN",
    "gn:dem":312,
    "gn:feature_class":"P",
    "gn:feature_code":"PPL",
    "gn:name":"Dawangou",
    "gn:population":0,
    "gn:timezone":"Asia/Shanghai",
    "iso:country":"CN",
    "name:und_x_variant":[
        "\u5927\u6e7e\u6c9f"
    ],
    "wof:name":"Dawangou",
    "wof:placetype":"locality"
},
  "geometry": {"coordinates":[123.13835,40.54476],"type":"Point"}
}