{
  "type": "Feature",
  "properties": {
    "gn:admin1_code":"10",
    "gn:asciiname":"Tuoguonai Goumen",
    "gn:country_code":"CN",
    "gn:dem":999,
    "gn:feature_class":"P",
    "gn:feature_code":"PPL",
    "gn:name":"Tuoguonai Goumen",
    "gn:population":0,
    "gn:timezone":"Asia/Shanghai",
    "iso:country":"CN",
    "name:zho_x_preferred":[
        "\u6258\u679c\u5948\u6c9f\u95e8"
    ],
    "wof:name":"Tuoguonai Goumen",
    "wof:placetype":"locality"
},
  "geometry": {"coordinates":[117.50444,41.88338],"type":"Point"}
}