{
  "type": "Feature",
  "properties": {
    "gn:admin1_code":"24.0",
    "gn:asciiname":"Caocuncun",
    "gn:country_code":"CN",
    "gn:dem":1116,
    "gn:feature_class":"P",
    "gn:feature_code":"PPL",
    "gn:name":"Caocuncun",
    "gn:population":0,
    "gn:timezone":"Asia/Shanghai",
    "iso:country":"CN",
    "name:zho_x_preferred":[
        "\u66f9\u6751\u6751"
    ],
    "wof:name":"Caocuncun",
    "wof:placetype":"locality"
},
  "geometry": {"coordinates":[110.92695000000001,36.96767],"type":"Point"}
}