{
  "type": "Feature",
  "properties": {
    "gn:admin1_code":"15.0",
    "gn:asciiname":"Mohewan",
    "gn:country_code":"CN",
    "gn:dem":2519,
    "gn:feature_class":"P",
    "gn:feature_code":"PPL",
    "gn:name":"Mohewan",
    "gn:population":0,
    "gn:timezone":"Asia/Shanghai",
    "iso:country":"CN",
    "name:zho_x_preferred":[
        "\u78e8\u6cb3\u6e7e"
    ],
    "wof:name":"Mohewan",
    "wof:placetype":"locality"
},
  "geometry": {"coordinates":[102.89100000000001,37.2854],"type":"Point"}
}