{
  "type": "Feature",
  "properties": {
    "gn:admin1_code":"11",
    "gn:asciiname":"Xiang Linchang",
    "gn:country_code":"CN",
    "gn:dem":865,
    "gn:feature_class":"P",
    "gn:feature_code":"PPLF",
    "gn:name":"Xiang Linchang",
    "gn:population":0,
    "gn:timezone":"Asia/Shanghai",
    "iso:country":"CN",
    "wof:name":"Xiang Linchang",
    "wof:placetype":"locality"
},
  "geometry": {"coordinates":[110.63306,27.61722],"type":"Point"}
}