{
  "type": "Feature",
  "properties": {
    "gn:admin1_code":"3.0",
    "gn:asciiname":"Heqiu",
    "gn:country_code":"CN",
    "gn:dem":227,
    "gn:feature_class":"P",
    "gn:feature_code":"PPL",
    "gn:name":"Heqiu",
    "gn:population":0,
    "gn:timezone":"Asia/Shanghai",
    "iso:country":"CN",
    "name:und_x_variant":[
        "\u6cb3\u79cb"
    ],
    "wof:name":"Heqiu",
    "wof:placetype":"locality"
},
  "geometry": {"coordinates":[115.45699999999999,25.5188],"type":"Point"}
}