{
  "type": "Feature",
  "properties": {
    "gn:admin1_code":"8.0",
    "gn:asciiname":"Mawanniantun",
    "gn:country_code":"CN",
    "gn:dem":158,
    "gn:feature_class":"P",
    "gn:feature_code":"PPL",
    "gn:name":"Mawanniantun",
    "gn:population":0,
    "gn:timezone":"Asia/Shanghai",
    "iso:country":"CN",
    "name:zho_x_preferred":[
        "\u9a6c\u4e07\u5e74\u5c6f"
    ],
    "wof:name":"Mawanniantun",
    "wof:placetype":"locality"
},
  "geometry": {"coordinates":[127.39509,45.88154],"type":"Point"}
}