{
  "type": "Feature",
  "properties": {
    "gn:admin1_code":"5.0",
    "gn:asciiname":"Linjiagou",
    "gn:country_code":"CN",
    "gn:dem":592,
    "gn:feature_class":"P",
    "gn:feature_code":"PPL",
    "gn:name":"Linjiagou",
    "gn:population":0,
    "gn:timezone":"Asia/Shanghai",
    "iso:country":"CN",
    "name:zho_x_preferred":[
        "\u6797\u5bb6\u6c9f"
    ],
    "wof:name":"Linjiagou",
    "wof:placetype":"locality"
},
  "geometry": {"coordinates":[126.24317000000001,41.96893],"type":"Point"}
}