{
  "type": "Feature",
  "properties": {
    "gn:admin1_code":"32.0",
    "gn:asciiname":"Dijiansi",
    "gn:country_code":"CN",
    "gn:dem":3539,
    "gn:feature_class":"P",
    "gn:feature_code":"PPL",
    "gn:name":"Dijiansi",
    "gn:population":0,
    "gn:timezone":"Asia/Shanghai",
    "iso:country":"CN",
    "name:zho_x_preferred":[
        "\u5730\u5c16\u5bfa"
    ],
    "wof:name":"Dijiansi",
    "wof:placetype":"locality"
},
  "geometry": {"coordinates":[99.46589,32.10839],"type":"Point"}
}