{
  "type": "Feature",
  "properties": {
    "gn:admin1_code":"26.0",
    "gn:asciiname":"Huangpingcun",
    "gn:country_code":"CN",
    "gn:dem":811,
    "gn:feature_class":"P",
    "gn:feature_code":"PPL",
    "gn:name":"Huangpingcun",
    "gn:population":0,
    "gn:timezone":"Asia/Shanghai",
    "iso:country":"CN",
    "name:zho_x_preferred":[
        "\u9ec4\u576a\u6751"
    ],
    "wof:name":"Huangpingcun",
    "wof:placetype":"locality"
},
  "geometry": {"coordinates":[110.41115000000001,34.11914],"type":"Point"}
}