{
  "type": "Feature",
  "properties": {
    "gn:admin1_code":"19.0",
    "gn:asciiname":"Tangtugouli",
    "gn:country_code":"CN",
    "gn:dem":678,
    "gn:feature_class":"P",
    "gn:feature_code":"PPL",
    "gn:name":"Tangtugouli",
    "gn:population":0,
    "gn:timezone":"Asia/Shanghai",
    "iso:country":"CN",
    "name:zho_x_preferred":[
        "\u6c64\u571f\u6c9f\u91cc"
    ],
    "wof:name":"Tangtugouli",
    "wof:placetype":"locality"
},
  "geometry": {"coordinates":[119.81836,42.07542],"type":"Point"}
}