{
  "type": "Feature",
  "properties": {
    "gn:admin1_code":"6.0",
    "gn:asciiname":"Duimei",
    "gn:country_code":"CN",
    "gn:dem":3952,
    "gn:feature_class":"P",
    "gn:feature_code":"PPL",
    "gn:name":"Duimei",
    "gn:population":0,
    "gn:timezone":"Asia/Urumqi",
    "iso:country":"CN",
    "name:zho_x_preferred":[
        "\u5806\u7164"
    ],
    "wof:name":"Duimei",
    "wof:placetype":"locality"
},
  "geometry": {"coordinates":[96.72145999999999,31.96834],"type":"Point"}
}