{
  "type": "Feature",
  "properties": {
    "gn:admin1_code":"19.0",
    "gn:asciiname":"Guangmingshancun",
    "gn:country_code":"CN",
    "gn:dem":22,
    "gn:feature_class":"P",
    "gn:feature_code":"PPL",
    "gn:name":"Guangmingshancun",
    "gn:population":0,
    "gn:timezone":"Asia/Shanghai",
    "iso:country":"CN",
    "name:zho_x_preferred":[
        "\u5149\u660e\u5c71\u6751"
    ],
    "wof:name":"Guangmingshancun",
    "wof:placetype":"locality"
},
  "geometry": {"coordinates":[122.80459999999999,39.78526],"type":"Point"}
}