{
  "type": "Feature",
  "properties": {
    "gn:admin1_code":"7.0",
    "gn:asciiname":"Xizhoupu",
    "gn:country_code":"CN",
    "gn:dem":293,
    "gn:feature_class":"P",
    "gn:feature_code":"PPL",
    "gn:name":"Xizhoupu",
    "gn:population":0,
    "gn:timezone":"Asia/Shanghai",
    "iso:country":"CN",
    "name:zho_x_preferred":[
        "\u6eaa\u6d32\u94fa"
    ],
    "wof:name":"Xizhoupu",
    "wof:placetype":"locality"
},
  "geometry": {"coordinates":[118.3648,27.83887],"type":"Point"}
}