{
  "type": "Feature",
  "properties": {
    "gn:admin1_code":"15.0",
    "gn:asciiname":"Huanghua Nongchang Wudui",
    "gn:country_code":"CN",
    "gn:dem":1349,
    "gn:feature_class":"P",
    "gn:feature_code":"PPLF",
    "gn:name":"Huanghua Nongchang Wudui",
    "gn:population":0,
    "gn:timezone":"Asia/Shanghai",
    "iso:country":"CN",
    "name:eng_x_preferred":[
        "Huanghua Nongchang Fifth Dui"
    ],
    "name:zho_x_preferred":[
        "\u9ec4\u82b1\u519c\u573a\u4e94\u961f"
    ],
    "wof:name":"Huanghua Nongchang Wudui",
    "wof:placetype":"locality"
},
  "geometry": {"coordinates":[97.26154,40.43679],"type":"Point"}
}