{
  "type": "Feature",
  "properties": {
    "gn:admin1_code":"32.0",
    "gn:asciiname":"Li'erkezi Wuji",
    "gn:country_code":"CN",
    "gn:dem":1974,
    "gn:feature_class":"P",
    "gn:feature_code":"PPL",
    "gn:name":"Li\u2019erkezi Wuji",
    "gn:population":0,
    "gn:timezone":"Asia/Shanghai",
    "iso:country":"CN",
    "name:und_x_variant":[
        "Li\u2019erkezi Wuji"
    ],
    "name:zho_x_preferred":[
        "\u674e\u4e8c\u58f3\u5b50\u5c4b\u57fa"
    ],
    "wof:name":"Li'erkezi Wuji",
    "wof:placetype":"locality"
},
  "geometry": {"coordinates":[104.282,32.2992],"type":"Point"}
}