{
  "type": "Feature",
  "properties": {
    "gn:admin1_code":"14.0",
    "gn:asciiname":"Jizhongcun",
    "gn:country_code":"CN",
    "gn:dem":4470,
    "gn:feature_class":"P",
    "gn:feature_code":"PPL",
    "gn:name":"Jizhongcun",
    "gn:population":0,
    "gn:timezone":"Asia/Urumqi",
    "iso:country":"CN",
    "name:zho_x_preferred":[
        "\u5409\u4e2d\u6751"
    ],
    "wof:name":"Jizhongcun",
    "wof:placetype":"locality"
},
  "geometry": {"coordinates":[97.32911,30.40998],"type":"Point"}
}