{
  "type": "Feature",
  "properties": {
    "gn:admin1_code":"4.0",
    "gn:asciiname":"Dawangzhuang",
    "gn:country_code":"CN",
    "gn:dem":3,
    "gn:feature_class":"P",
    "gn:feature_code":"PPL",
    "gn:name":"Dawangzhuang",
    "gn:population":0,
    "gn:timezone":"Asia/Shanghai",
    "iso:country":"CN",
    "name:zho_x_preferred":[
        "Dawangzhuang"
    ],
    "name:zho_x_variant":[
        "\u5927\u738b\u5e84"
    ],
    "wof:name":"Dawangzhuang",
    "wof:placetype":"locality"
},
  "geometry": {"coordinates":[119.09422000000001,34.16493],"type":"Point"}
}