{
  "type": "Feature",
  "properties": {
    "gn:admin1_code":"29.0",
    "gn:asciiname":"Lengmi",
    "gn:country_code":"CN",
    "gn:dem":2096,
    "gn:feature_class":"P",
    "gn:feature_code":"PPL",
    "gn:name":"Lengmi",
    "gn:population":0,
    "gn:timezone":"Asia/Shanghai",
    "iso:country":"CN",
    "name:und_x_variant":[
        "\u51b7\u7c73"
    ],
    "wof:name":"Lengmi",
    "wof:placetype":"locality"
},
  "geometry": {"coordinates":[103.70166,27.66814],"type":"Point"}
}