{
  "type": "Feature",
  "properties": {
    "gn:admin1_code":"4.0",
    "gn:asciiname":"Qiaolinzhen",
    "gn:country_code":"CN",
    "gn:dem":12,
    "gn:feature_class":"P",
    "gn:feature_code":"PPL",
    "gn:name":"Qiaolinzhen",
    "gn:population":0,
    "gn:timezone":"Asia/Shanghai",
    "iso:country":"CN",
    "wof:name":"Qiaolinzhen",
    "wof:placetype":"locality"
},
  "geometry": {"coordinates":[118.50833,31.94583],"type":"Point"}
}