{
  "type": "Feature",
  "properties": {
    "gn:admin1_code":"8.0",
    "gn:asciiname":"Tongshengcun",
    "gn:country_code":"CN",
    "gn:dem":57,
    "gn:feature_class":"P",
    "gn:feature_code":"PPL",
    "gn:name":"Tongshengcun",
    "gn:population":0,
    "gn:timezone":"Asia/Shanghai",
    "iso:country":"CN",
    "name:zho_x_preferred":[
        "\u540c\u80dc\u6751"
    ],
    "wof:name":"Tongshengcun",
    "wof:placetype":"locality"
},
  "geometry": {"coordinates":[132.77663000000001,46.93443],"type":"Point"}
}