{
  "type": "Feature",
  "properties": {
    "gn:admin1_code":"12.0",
    "gn:asciiname":"Wengjiawan",
    "gn:country_code":"CN",
    "gn:dem":53,
    "gn:feature_class":"P",
    "gn:feature_code":"PPL",
    "gn:name":"Wengjiawan",
    "gn:population":0,
    "gn:timezone":"Asia/Shanghai",
    "iso:country":"CN",
    "name:zho_x_preferred":[
        "\u7fc1\u5bb6\u6e7e"
    ],
    "wof:name":"Wengjiawan",
    "wof:placetype":"locality"
},
  "geometry": {"coordinates":[112.52354,31.30713],"type":"Point"}
}