{
  "type": "Feature",
  "properties": {
    "gn:admin1_code":"30.0",
    "gn:asciiname":"Hengdong",
    "gn:country_code":"CN",
    "gn:dem":38,
    "gn:feature_class":"P",
    "gn:feature_code":"PPL",
    "gn:name":"Hengdong",
    "gn:population":0,
    "gn:timezone":"Asia/Shanghai",
    "iso:country":"CN",
    "name:zho_x_preferred":[
        "\u6a6b\u6d1e"
    ],
    "wof:name":"Hengdong",
    "wof:placetype":"locality"
},
  "geometry": {"coordinates":[112.59589,22.01151],"type":"Point"}
}