{
  "type": "Feature",
  "properties": {
    "gn:admin1_code":"4.0",
    "gn:asciiname":"Heshangxu",
    "gn:country_code":"CN",
    "gn:dem":4,
    "gn:feature_class":"P",
    "gn:feature_code":"PPL",
    "gn:name":"Heshangxu",
    "gn:population":0,
    "gn:timezone":"Asia/Shanghai",
    "iso:country":"CN",
    "name:zho_x_preferred":[
        "Heshangxu"
    ],
    "name:zho_x_variant":[
        "\u548c\u5c1a\u5729"
    ],
    "wof:name":"Heshangxu",
    "wof:placetype":"locality"
},
  "geometry": {"coordinates":[119.48242,33.91449],"type":"Point"}
}