{
  "type": "Feature",
  "properties": {
    "gn:admin1_code":"15.0",
    "gn:asciiname":"Lujiashan",
    "gn:country_code":"CN",
    "gn:dem":2390,
    "gn:feature_class":"P",
    "gn:feature_code":"PPL",
    "gn:name":"Lujiashan",
    "gn:population":0,
    "gn:timezone":"Asia/Shanghai",
    "iso:country":"CN",
    "name:zho_x_preferred":[
        "\u82a6\u5bb6\u5c71"
    ],
    "wof:name":"Lujiashan",
    "wof:placetype":"locality"
},
  "geometry": {"coordinates":[103.542,37.3682],"type":"Point"}
}