{
  "type": "Feature",
  "properties": {
    "gn:admin1_code":"32.0",
    "gn:asciiname":"Sudijigu",
    "gn:country_code":"CN",
    "gn:dem":2155,
    "gn:feature_class":"P",
    "gn:feature_code":"PPL",
    "gn:name":"Sudijigu",
    "gn:population":0,
    "gn:timezone":"Asia/Shanghai",
    "iso:country":"CN",
    "name:zho_x_preferred":[
        "\u7d20\u5e95\u57fa\u59d1"
    ],
    "wof:name":"Sudijigu",
    "wof:placetype":"locality"
},
  "geometry": {"coordinates":[103.196,28.7091],"type":"Point"}
}