{
  "type": "Feature",
  "properties": {
    "gn:admin1_code":"30",
    "gn:asciiname":"Luofu",
    "gn:country_code":"CN",
    "gn:dem":269,
    "gn:feature_class":"P",
    "gn:feature_code":"PPLA4",
    "gn:name":"Luofu",
    "gn:population":0,
    "gn:timezone":"Asia/Shanghai",
    "iso:country":"CN",
    "name:und_x_variant":[
        "Lo-fu",
        "Luofu",
        "Luofu Zhen"
    ],
    "name:zho_x_preferred":[
        "\u7f57\u6d6e\u9547"
    ],
    "wof:name":"Luofu",
    "wof:placetype":"locality"
},
  "geometry": {"coordinates":[115.57926,24.52711],"type":"Point"}
}