{
  "type": "Feature",
  "properties": {
    "gn:admin1_code":"7.0",
    "gn:asciiname":"Banluyang",
    "gn:country_code":"CN",
    "gn:dem":163,
    "gn:feature_class":"P",
    "gn:feature_code":"PPL",
    "gn:name":"Banluyang",
    "gn:population":0,
    "gn:timezone":"Asia/Shanghai",
    "iso:country":"CN",
    "name:zho_x_preferred":[
        "\u534a\u8def\u6d0b"
    ],
    "wof:name":"Banluyang",
    "wof:placetype":"locality"
},
  "geometry": {"coordinates":[117.70707,26.30305],"type":"Point"}
}