{
  "type": "Feature",
  "properties": {
    "gn:admin1_code":"24.0",
    "gn:asciiname":"Daohuiyu",
    "gn:country_code":"CN",
    "gn:dem":1742,
    "gn:feature_class":"P",
    "gn:feature_code":"PPL",
    "gn:name":"Daohuiyu",
    "gn:population":0,
    "gn:timezone":"Asia/Shanghai",
    "iso:country":"CN",
    "name:und_x_variant":[
        "\u9053\u56de\u5cea"
    ],
    "wof:name":"Daohuiyu",
    "wof:placetype":"locality"
},
  "geometry": {"coordinates":[113.4093,39.37843],"type":"Point"}
}