{
  "type": "Feature",
  "properties": {
    "gn:admin1_code":"3.0",
    "gn:asciiname":"Sanwangyuan",
    "gn:country_code":"CN",
    "gn:dem":114,
    "gn:feature_class":"P",
    "gn:feature_code":"PPL",
    "gn:name":"Sanwangyuan",
    "gn:population":0,
    "gn:timezone":"Asia/Shanghai",
    "iso:country":"CN",
    "name:zho_x_preferred":[
        "\u4e09\u671b\u6e90"
    ],
    "wof:name":"Sanwangyuan",
    "wof:placetype":"locality"
},
  "geometry": {"coordinates":[117.4983,28.53962000000001],"type":"Point"}
}