{
  "type": "Feature",
  "properties": {
    "gn:admin1_code":"11",
    "gn:asciiname":"Manghuaping",
    "gn:country_code":"CN",
    "gn:dem":1310,
    "gn:feature_class":"P",
    "gn:feature_code":"PPL",
    "gn:name":"Manghuaping",
    "gn:population":0,
    "gn:timezone":"Asia/Shanghai",
    "iso:country":"CN",
    "name:und_x_variant":[
        "Wanghuaping"
    ],
    "name:zho_x_preferred":[
        "\u8292\u82b1\u576a"
    ],
    "wof:name":"Manghuaping",
    "wof:placetype":"locality"
},
  "geometry": {"coordinates":[110.78917,27.52889],"type":"Point"}
}