{
  "type": "Feature",
  "properties": {
    "gn:admin1_code":"15.0",
    "gn:asciiname":"Heigangchuan",
    "gn:country_code":"CN",
    "gn:dem":1988,
    "gn:feature_class":"P",
    "gn:feature_code":"PPL",
    "gn:name":"Heigangchuan",
    "gn:population":0,
    "gn:timezone":"Asia/Shanghai",
    "iso:country":"CN",
    "name:zho_x_preferred":[
        "\u9ed1\u5c97\u5ddd"
    ],
    "wof:name":"Heigangchuan",
    "wof:placetype":"locality"
},
  "geometry": {"coordinates":[104.85299999999999,35.4529],"type":"Point"}
}