{
  "type": "Feature",
  "properties": {
    "gn:admin1_code":"11.0",
    "gn:asciiname":"Gouping",
    "gn:country_code":"CN",
    "gn:dem":429,
    "gn:feature_class":"P",
    "gn:feature_code":"PPL",
    "gn:name":"Gouping",
    "gn:population":0,
    "gn:timezone":"Asia/Shanghai",
    "iso:country":"CN",
    "name:zho_x_preferred":[
        "\u94a9\u576a"
    ],
    "wof:name":"Gouping",
    "wof:placetype":"locality"
},
  "geometry": {"coordinates":[113.38593,26.16231],"type":"Point"}
}