{
  "type": "Feature",
  "properties": {
    "gn:admin1_code":"29",
    "gn:asciiname":"Baohong",
    "gn:country_code":"CN",
    "gn:dem":1541,
    "gn:feature_class":"P",
    "gn:feature_code":"PPL",
    "gn:name":"Baohong",
    "gn:population":0,
    "gn:timezone":"Asia/Shanghai",
    "iso:country":"CN",
    "name:zho_x_preferred":[
        "\u5b9d\u6d2a"
    ],
    "wof:name":"Baohong",
    "wof:placetype":"locality"
},
  "geometry": {"coordinates":[103.14126,24.96678],"type":"Point"}
}