{
  "type": "Feature",
  "properties": {
    "gn:admin1_code":"29",
    "gn:asciiname":"Niujiaozhai",
    "gn:cc2":"CN",
    "gn:country_code":"CN",
    "gn:dem":1404,
    "gn:feature_class":"P",
    "gn:feature_code":"PPL",
    "gn:name":"Niujiaozhai",
    "gn:population":0,
    "gn:timezone":"Asia/Shanghai",
    "iso:country":"CN",
    "name:und_x_variant":[
        "Niu-chiao-chai",
        "Niujiaozhai"
    ],
    "wof:name":"Niujiaozhai",
    "wof:placetype":"locality"
},
  "geometry": {"coordinates":[102.65833000000001,23.12167],"type":"Point"}
}