{
  "type": "Feature",
  "properties": {
    "gn:admin1_code":"3.0",
    "gn:asciiname":"Miaozuishang",
    "gn:country_code":"CN",
    "gn:dem":33,
    "gn:feature_class":"P",
    "gn:feature_code":"PPL",
    "gn:name":"Miaozuishang",
    "gn:population":0,
    "gn:timezone":"Asia/Shanghai",
    "iso:country":"CN",
    "name:und_x_variant":[
        "\u5e99\u5634\u4e0a"
    ],
    "wof:name":"Miaozuishang",
    "wof:placetype":"locality"
},
  "geometry": {"coordinates":[116.94474,29.17078],"type":"Point"}
}