{
  "type": "Feature",
  "properties": {
    "gn:admin1_code":"2.0",
    "gn:asciiname":"Shakeng",
    "gn:country_code":"CN",
    "gn:dem":206,
    "gn:feature_class":"P",
    "gn:feature_code":"PPL",
    "gn:name":"Shakeng",
    "gn:population":0,
    "gn:timezone":"Asia/Shanghai",
    "iso:country":"CN",
    "name:zho_x_preferred":[
        "\u6c99\u5751"
    ],
    "wof:name":"Shakeng",
    "wof:placetype":"locality"
},
  "geometry": {"coordinates":[120.03909,28.41653],"type":"Point"}
}