{
  "type": "Feature",
  "properties": {
    "gn:admin1_code":"13",
    "gn:asciiname":"Yituan Yiqilian",
    "gn:country_code":"CN",
    "gn:dem":1048,
    "gn:feature_class":"P",
    "gn:feature_code":"PPL",
    "gn:name":"Yituan Yiqilian",
    "gn:population":0,
    "gn:timezone":"Asia/Shanghai",
    "iso:country":"CN",
    "name:und_x_variant":[
        "\u4e00\u56e2\u4e00\u4e03\u8fde"
    ],
    "wof:name":"Yituan Yiqilian",
    "wof:placetype":"locality"
},
  "geometry": {"coordinates":[79.89716,40.64146],"type":"Point"}
}