{
  "type": "Feature",
  "properties": {
    "gn:admin1_code":"15.0",
    "gn:asciiname":"Shangguohe",
    "gn:country_code":"CN",
    "gn:dem":2433,
    "gn:feature_class":"P",
    "gn:feature_code":"PPL",
    "gn:name":"Shangguohe",
    "gn:population":0,
    "gn:timezone":"Asia/Shanghai",
    "iso:country":"CN",
    "name:zho_x_preferred":[
        "\u4e0a\u90ed\u6cb3"
    ],
    "wof:name":"Shangguohe",
    "wof:placetype":"locality"
},
  "geometry": {"coordinates":[103.39100000000001,35.2733],"type":"Point"}
}