{
  "type": "Feature",
  "properties": {
    "gn:admin1_code":"12.0",
    "gn:asciiname":"Guanfangping",
    "gn:country_code":"CN",
    "gn:dem":1580,
    "gn:feature_class":"P",
    "gn:feature_code":"PPL",
    "gn:name":"Guanfangping",
    "gn:population":0,
    "gn:timezone":"Asia/Shanghai",
    "iso:country":"CN",
    "name:zho_x_preferred":[
        "Guanfangping"
    ],
    "name:zho_x_variant":[
        "\u5b98\u623f\u576a"
    ],
    "wof:name":"Guanfangping",
    "wof:placetype":"locality"
},
  "geometry": {"coordinates":[110.19186999999999,30.0063],"type":"Point"}
}