{
  "type": "Feature",
  "properties": {
    "gn:admin1_code":"24.0",
    "gn:asciiname":"Chengjiazhuang",
    "gn:country_code":"CN",
    "gn:dem":781,
    "gn:feature_class":"P",
    "gn:feature_code":"PPL",
    "gn:name":"Chengjiazhuang",
    "gn:population":0,
    "gn:timezone":"Asia/Shanghai",
    "iso:country":"CN",
    "name:zho_x_preferred":[
        "\u7a0b\u5bb6\u5e84"
    ],
    "wof:name":"Chengjiazhuang",
    "wof:placetype":"locality"
},
  "geometry": {"coordinates":[112.51663000000001,37.42663],"type":"Point"}
}