{
  "type": "Feature",
  "properties": {
    "gn:admin1_code":"5.0",
    "gn:asciiname":"Chenjia Gangzi",
    "gn:country_code":"CN",
    "gn:dem":185,
    "gn:feature_class":"P",
    "gn:feature_code":"PPL",
    "gn:name":"Chenjia Gangzi",
    "gn:population":0,
    "gn:timezone":"Asia/Shanghai",
    "iso:country":"CN",
    "name:zho_x_preferred":[
        "\u9648\u5bb6\u5c97\u5b50"
    ],
    "wof:name":"Chenjia Gangzi",
    "wof:placetype":"locality"
},
  "geometry": {"coordinates":[125.17638999999998,44.48882],"type":"Point"}
}