{
  "type": "Feature",
  "properties": {
    "gn:admin1_code":"29.0",
    "gn:asciiname":"Maguizha",
    "gn:country_code":"CN",
    "gn:dem":1927,
    "gn:feature_class":"P",
    "gn:feature_code":"PPL",
    "gn:name":"Maguizha",
    "gn:population":0,
    "gn:timezone":"Asia/Shanghai",
    "iso:country":"CN",
    "name:zho_x_preferred":[
        "\u9a6c\u8d35\u95f8"
    ],
    "wof:name":"Maguizha",
    "wof:placetype":"locality"
},
  "geometry": {"coordinates":[103.711,27.2945],"type":"Point"}
}