{
  "type": "Feature",
  "properties": {
    "gn:admin1_code":"4.0",
    "gn:asciiname":"Guandimiaocun",
    "gn:country_code":"CN",
    "gn:dem":38,
    "gn:feature_class":"P",
    "gn:feature_code":"PPL",
    "gn:name":"Guandimiaocun",
    "gn:population":0,
    "gn:timezone":"Asia/Shanghai",
    "iso:country":"CN",
    "name:zho_x_preferred":[
        "\u5173\u5e1d\u5e99\u6751"
    ],
    "wof:name":"Guandimiaocun",
    "wof:placetype":"locality"
},
  "geometry": {"coordinates":[116.93689000000001,34.66229000000001],"type":"Point"}
}