{
  "type": "Feature",
  "properties": {
    "gn:admin1_code":"07",
    "gn:asciiname":"Shangcuoping",
    "gn:country_code":"CN",
    "gn:dem":1078,
    "gn:feature_class":"P",
    "gn:feature_code":"PPL",
    "gn:name":"Shangcuoping",
    "gn:population":0,
    "gn:timezone":"Asia/Shanghai",
    "iso:country":"CN",
    "name:zho_x_preferred":[
        "\u4e0a\u539d\u576a"
    ],
    "wof:name":"Shangcuoping",
    "wof:placetype":"locality"
},
  "geometry": {"coordinates":[118.68962999999999,26.80093],"type":"Point"}
}