{
  "type": "Feature",
  "properties": {
    "gn:admin1_code":"12",
    "gn:asciiname":"Baoxia",
    "gn:country_code":"CN",
    "gn:dem":313,
    "gn:feature_class":"P",
    "gn:feature_code":"PPLA4",
    "gn:name":"Baoxia",
    "gn:population":0,
    "gn:timezone":"Asia/Shanghai",
    "iso:country":"CN",
    "name:und_x_variant":[
        "Pao-hsia",
        "Baoxia",
        "Baoxia Zhen"
    ],
    "name:zho_x_preferred":[
        "\u9c8d\u5ce1"
    ],
    "name:zho_x_variant":[
        "\u9c8d\u5ce1\u9547"
    ],
    "wof:name":"Baoxia",
    "wof:placetype":"locality"
},
  "geometry": {"coordinates":[110.33034000000001,32.70746],"type":"Point"}
}