{
  "type": "Feature",
  "properties": {
    "gn:admin1_code":"11.0",
    "gn:asciiname":"Nanyuemiao",
    "gn:country_code":"CN",
    "gn:dem":73,
    "gn:feature_class":"P",
    "gn:feature_code":"PPL",
    "gn:name":"Nanyuemiao",
    "gn:population":0,
    "gn:timezone":"Asia/Shanghai",
    "iso:country":"CN",
    "name:zho_x_preferred":[
        "\u5357\u5cb3\u5e99"
    ],
    "wof:name":"Nanyuemiao",
    "wof:placetype":"locality"
},
  "geometry": {"coordinates":[111.40536000000002,28.84542],"type":"Point"}
}