{
  "type": "Feature",
  "properties": {
    "gn:admin1_code":"32.0",
    "gn:asciiname":"Chongtianlou",
    "gn:country_code":"CN",
    "gn:dem":741,
    "gn:feature_class":"P",
    "gn:feature_code":"PPL",
    "gn:name":"Chongtianlou",
    "gn:population":0,
    "gn:timezone":"Asia/Shanghai",
    "iso:country":"CN",
    "name:zho_x_preferred":[
        "\u51b2\u5929\u697c"
    ],
    "wof:name":"Chongtianlou",
    "wof:placetype":"locality"
},
  "geometry": {"coordinates":[103.52085,29.23401],"type":"Point"}
}