{
  "type": "Feature",
  "properties": {
    "gn:admin1_code":"29.0",
    "gn:asciiname":"Kemu Shangzhai",
    "gn:country_code":"CN",
    "gn:dem":1588,
    "gn:feature_class":"P",
    "gn:feature_code":"PPL",
    "gn:name":"Kemu Shangzhai",
    "gn:population":0,
    "gn:timezone":"Asia/Shanghai",
    "iso:country":"CN",
    "name:zho_x_preferred":[
        "\u79d1\u6728\u4e0a\u5be8"
    ],
    "wof:name":"Kemu Shangzhai",
    "wof:placetype":"locality"
},
  "geometry": {"coordinates":[104.494,23.7588],"type":"Point"}
}