{
  "type": "Feature",
  "properties": {
    "gn:admin1_code":"18.0",
    "gn:asciiname":"Qingjiang",
    "gn:country_code":"CN",
    "gn:dem":675,
    "gn:feature_class":"P",
    "gn:feature_code":"PPL",
    "gn:name":"Qingjiang",
    "gn:population":0,
    "gn:timezone":"Asia/Shanghai",
    "iso:country":"CN",
    "name:ceb_x_preferred":[
        "Qingjiang"
    ],
    "name:swe_x_preferred":[
        "Qingjiang"
    ],
    "name:zho_x_preferred":[
        "\u6e05\u6c5f"
    ],
    "wof:name":"Qingjiang",
    "wof:placetype":"locality"
},
  "geometry": {"coordinates":[107.82299999999999,26.4079],"type":"Point"}
}