{
  "type": "Feature",
  "properties": {
    "gn:admin1_code":"7",
    "gn:asciiname":"Huangdankeng",
    "gn:country_code":"CN",
    "gn:dem":874,
    "gn:feature_class":"P",
    "gn:feature_code":"PPL",
    "gn:name":"Huangdankeng",
    "gn:population":0,
    "gn:timezone":"Asia/Shanghai",
    "iso:country":"CN",
    "name:und_x_variant":[
        "\u9ec4\u6de1\u5751",
        "Huangdankeng"
    ],
    "wof:name":"Huangdankeng",
    "wof:placetype":"locality"
},
  "geometry": {"coordinates":[119.0247,27.13234000000001],"type":"Point"}
}