{
  "type": "Feature",
  "properties": {
    "gn:admin1_code":"12.0",
    "gn:asciiname":"Youzhaling",
    "gn:country_code":"CN",
    "gn:dem":1073,
    "gn:feature_class":"P",
    "gn:feature_code":"PPL",
    "gn:name":"Youzhaling",
    "gn:population":0,
    "gn:timezone":"Asia/Shanghai",
    "iso:country":"CN",
    "name:zho_x_preferred":[
        "\u6cb9\u70b8\u5cad"
    ],
    "wof:name":"Youzhaling",
    "wof:placetype":"locality"
},
  "geometry": {"coordinates":[109.58557,33.15292],"type":"Point"}
}