{
  "type": "Feature",
  "properties": {
    "gn:admin1_code":"26.0",
    "gn:asciiname":"Lijiaheba",
    "gn:country_code":"CN",
    "gn:dem":611,
    "gn:feature_class":"P",
    "gn:feature_code":"PPL",
    "gn:name":"Lijiaheba",
    "gn:population":0,
    "gn:timezone":"Asia/Shanghai",
    "iso:country":"CN",
    "name:und_x_variant":[
        "\u9ece\u5bb6\u6cb3\u575d"
    ],
    "wof:name":"Lijiaheba",
    "wof:placetype":"locality"
},
  "geometry": {"coordinates":[107.04028999999998,33.1981],"type":"Point"}
}