{
  "type": "Feature",
  "properties": {
    "gn:admin1_code":"3",
    "gn:asciiname":"Xiaozhu",
    "gn:country_code":"CN",
    "gn:dem":146,
    "gn:feature_class":"P",
    "gn:feature_code":"PPL",
    "gn:name":"Xiaozhu",
    "gn:population":0,
    "gn:timezone":"Asia/Shanghai",
    "iso:country":"CN",
    "name:und_x_variant":[
        "\u5c0f\u7afa"
    ],
    "wof:name":"Xiaozhu",
    "wof:placetype":"locality"
},
  "geometry": {"coordinates":[116.84659000000001,27.56696],"type":"Point"}
}