{
  "type": "Feature",
  "properties": {
    "gn:admin1_code":"8.0",
    "gn:asciiname":"Xuricun",
    "gn:country_code":"CN",
    "gn:dem":187,
    "gn:feature_class":"P",
    "gn:feature_code":"PPL",
    "gn:name":"Xuricun",
    "gn:population":0,
    "gn:timezone":"Asia/Shanghai",
    "iso:country":"CN",
    "name:zho_x_preferred":[
        "\u65ed\u65e5\u6751"
    ],
    "wof:name":"Xuricun",
    "wof:placetype":"locality"
},
  "geometry": {"coordinates":[125.43376000000001,47.33978],"type":"Point"}
}