{
  "type": "Feature",
  "properties": {
    "gn:admin1_code":"11.0",
    "gn:asciiname":"Lijiali",
    "gn:country_code":"CN",
    "gn:dem":145,
    "gn:feature_class":"P",
    "gn:feature_code":"PPL",
    "gn:name":"Lijiali",
    "gn:population":0,
    "gn:timezone":"Asia/Shanghai",
    "iso:country":"CN",
    "name:zho_x_preferred":[
        "\u674e\u5bb6\u91cc"
    ],
    "wof:name":"Lijiali",
    "wof:placetype":"locality"
},
  "geometry": {"coordinates":[113.64346999999999,26.76059],"type":"Point"}
}