{
  "type": "Feature",
  "properties": {
    "gn:admin1_code":"29",
    "gn:asciiname":"Boluo",
    "gn:country_code":"CN",
    "gn:dem":2209,
    "gn:feature_class":"P",
    "gn:feature_code":"PPL",
    "gn:name":"Boluo",
    "gn:population":0,
    "gn:timezone":"Asia/Shanghai",
    "iso:country":"CN",
    "name:zho_x_preferred":[
        "\u6ce2\u7f57"
    ],
    "wof:name":"Boluo",
    "wof:placetype":"locality"
},
  "geometry": {"coordinates":[101.015,24.8645],"type":"Point"}
}