{
  "type": "Feature",
  "properties": {
    "gn:admin1_code":"4.0",
    "gn:asciiname":"Baiqianzhuang",
    "gn:country_code":"CN",
    "gn:dem":5,
    "gn:feature_class":"P",
    "gn:feature_code":"PPL",
    "gn:name":"Baiqianzhuang",
    "gn:population":0,
    "gn:timezone":"Asia/Shanghai",
    "iso:country":"CN",
    "name:zho_x_preferred":[
        "\u767d\u8fc1\u5e84"
    ],
    "wof:name":"Baiqianzhuang",
    "wof:placetype":"locality"
},
  "geometry": {"coordinates":[119.70999999999999,32.6649],"type":"Point"}
}