{
  "type": "Feature",
  "properties": {
    "gn:admin1_code":"3.0",
    "gn:asciiname":"Zhihe",
    "gn:country_code":"CN",
    "gn:dem":350,
    "gn:feature_class":"P",
    "gn:feature_code":"PPL",
    "gn:name":"Zhihe",
    "gn:population":0,
    "gn:timezone":"Asia/Shanghai",
    "iso:country":"CN",
    "name:und_x_variant":[
        "\u81f4\u548c"
    ],
    "wof:name":"Zhihe",
    "wof:placetype":"locality"
},
  "geometry": {"coordinates":[117.04405,29.57504],"type":"Point"}
}