{
  "type": "Feature",
  "properties": {
    "gn:admin1_code":"15.0",
    "gn:asciiname":"Dongzipo",
    "gn:country_code":"CN",
    "gn:dem":2030,
    "gn:feature_class":"P",
    "gn:feature_code":"PPL",
    "gn:name":"Dongzipo",
    "gn:population":0,
    "gn:timezone":"Asia/Shanghai",
    "iso:country":"CN",
    "name:zho_x_preferred":[
        "\u6d1e\u5b50\u5761"
    ],
    "wof:name":"Dongzipo",
    "wof:placetype":"locality"
},
  "geometry": {"coordinates":[103.578,36.5869],"type":"Point"}
}