{
  "type": "Feature",
  "properties": {
    "gn:admin1_code":"25",
    "gn:asciiname":"Hangtou Dongcun",
    "gn:country_code":"CN",
    "gn:dem":35,
    "gn:feature_class":"P",
    "gn:feature_code":"PPL",
    "gn:name":"Hangtou Dongcun",
    "gn:population":0,
    "gn:timezone":"Asia/Shanghai",
    "iso:country":"CN",
    "name:zho_x_preferred":[
        "\u73e9\u5934\u4e1c\u6751"
    ],
    "wof:name":"Hangtou Dongcun",
    "wof:placetype":"locality"
},
  "geometry": {"coordinates":[118.19,34.593],"type":"Point"}
}