{
  "type": "Feature",
  "properties": {
    "gn:admin1_code":"7",
    "gn:asciiname":"Changta",
    "gn:country_code":"CN",
    "gn:dem":742,
    "gn:feature_class":"P",
    "gn:feature_code":"PPL",
    "gn:name":"Changta",
    "gn:population":0,
    "gn:timezone":"Asia/Shanghai",
    "iso:country":"CN",
    "name:zho_x_preferred":[
        "\u957f\u5854"
    ],
    "wof:name":"Changta",
    "wof:placetype":"locality"
},
  "geometry": {"coordinates":[117.05508,24.82217],"type":"Point"}
}