{
  "type": "Feature",
  "properties": {
    "gn:admin1_code":"9.0",
    "gn:asciiname":"Kedi",
    "gn:country_code":"CN",
    "gn:dem":78,
    "gn:feature_class":"P",
    "gn:feature_code":"PPL",
    "gn:name":"Kedi",
    "gn:population":0,
    "gn:timezone":"Asia/Shanghai",
    "iso:country":"CN",
    "name:zho_x_preferred":[
        "\u79d1\u5824"
    ],
    "wof:name":"Kedi",
    "wof:placetype":"locality"
},
  "geometry": {"coordinates":[113.93259999999999,35.09477],"type":"Point"}
}