{
  "type": "Feature",
  "properties": {
    "gn:admin1_code":"32.0",
    "gn:asciiname":"Nimading",
    "gn:country_code":"CN",
    "gn:dem":3167,
    "gn:feature_class":"P",
    "gn:feature_code":"PPL",
    "gn:name":"Nimading",
    "gn:population":0,
    "gn:timezone":"Asia/Shanghai",
    "iso:country":"CN",
    "name:zho_x_preferred":[
        "\u5c3c\u9a6c\u4e01"
    ],
    "wof:name":"Nimading",
    "wof:placetype":"locality"
},
  "geometry": {"coordinates":[100.934,28.3415],"type":"Point"}
}