{
  "type": "Feature",
  "properties": {
    "gn:admin1_code":"29.0",
    "gn:asciiname":"Yangchangcun",
    "gn:country_code":"CN",
    "gn:dem":2582,
    "gn:feature_class":"P",
    "gn:feature_code":"PPLF",
    "gn:name":"Yangchangcun",
    "gn:population":0,
    "gn:timezone":"Asia/Shanghai",
    "iso:country":"CN",
    "name:zho_x_preferred":[
        "\u7f8a\u573a\u6751"
    ],
    "wof:name":"Yangchangcun",
    "wof:placetype":"locality"
},
  "geometry": {"coordinates":[103.03,27.0273],"type":"Point"}
}