{
  "type": "Feature",
  "properties": {
    "gn:admin1_code":"3",
    "gn:asciiname":"Shuikengli",
    "gn:country_code":"CN",
    "gn:dem":220,
    "gn:feature_class":"P",
    "gn:feature_code":"PPL",
    "gn:name":"Shuikengli",
    "gn:population":0,
    "gn:timezone":"Asia/Shanghai",
    "iso:country":"CN",
    "name:zho_x_preferred":[
        "\u6c34\u5751\u91cc"
    ],
    "wof:name":"Shuikengli",
    "wof:placetype":"locality"
},
  "geometry": {"coordinates":[114.611,25.58],"type":"Point"}
}