{
  "type": "Feature",
  "properties": {
    "gn:admin1_code":"24.0",
    "gn:asciiname":"Xishagou",
    "gn:country_code":"CN",
    "gn:dem":1342,
    "gn:feature_class":"P",
    "gn:feature_code":"PPL",
    "gn:name":"Xishagou",
    "gn:population":0,
    "gn:timezone":"Asia/Shanghai",
    "iso:country":"CN",
    "name:zho_x_preferred":[
        "\u897f\u6c99\u6c9f"
    ],
    "wof:name":"Xishagou",
    "wof:placetype":"locality"
},
  "geometry": {"coordinates":[112.51681000000001,38.93084],"type":"Point"}
}