{
  "type": "Feature",
  "properties": {
    "gn:admin1_code":"30.0",
    "gn:asciiname":"Zaige",
    "gn:country_code":"CN",
    "gn:dem":418,
    "gn:feature_class":"P",
    "gn:feature_code":"PPL",
    "gn:name":"Zaige",
    "gn:population":0,
    "gn:timezone":"Asia/Shanghai",
    "iso:country":"CN",
    "name:zho_x_preferred":[
        "\u518d\u5404"
    ],
    "wof:name":"Zaige",
    "wof:placetype":"locality"
},
  "geometry": {"coordinates":[114.91194,23.27462],"type":"Point"}
}