{
  "type": "Feature",
  "properties": {
    "gn:admin1_code":"18.0",
    "gn:asciiname":"Yangneng",
    "gn:country_code":"CN",
    "gn:dem":579,
    "gn:feature_class":"P",
    "gn:feature_code":"PPL",
    "gn:name":"Yangneng",
    "gn:population":0,
    "gn:timezone":"Asia/Shanghai",
    "iso:country":"CN",
    "name:zho_x_preferred":[
        "\u517b\u80fd"
    ],
    "wof:name":"Yangneng",
    "wof:placetype":"locality"
},
  "geometry": {"coordinates":[108.504,25.8177],"type":"Point"}
}