{
  "type": "Feature",
  "properties": {
    "gn:admin1_code":"4.0",
    "gn:asciiname":"Lieshicun",
    "gn:country_code":"CN",
    "gn:dem":1,
    "gn:feature_class":"P",
    "gn:feature_code":"PPL",
    "gn:name":"Lieshicun",
    "gn:population":0,
    "gn:timezone":"Asia/Shanghai",
    "iso:country":"CN",
    "name:zho_x_preferred":[
        "\u70c8\u58eb\u6751"
    ],
    "wof:name":"Lieshicun",
    "wof:placetype":"locality"
},
  "geometry": {"coordinates":[120.04546999999999,33.75049],"type":"Point"}
}