{
  "type": "Feature",
  "properties": {
    "gn:country":"CN",
    "gn:fcode":"PPL",
    "gn:pop":4702,
    "iso:country":"CN",
    "name:unk_x_variant":[
        "Kou-t\u2019ou"
    ],
    "qs:name":"Goutou",
    "qs:photos_9r":0,
    "qs:photos_sr":0,
    "qs:pop_sr":"4",
    "wof:name":"Goutou",
    "wof:placetype":"locality",
    "wof:population":4702
},
  "geometry": {"coordinates":[117.19917,39.805],"type":"Point"}
}