{
  "type": "Feature",
  "properties": {
    "gn:admin1_code":"2.0",
    "gn:asciiname":"Yafan",
    "gn:country_code":"CN",
    "gn:dem":49,
    "gn:feature_class":"P",
    "gn:feature_code":"PPLA4",
    "gn:name":"Yafan",
    "gn:population":0,
    "gn:timezone":"Asia/Shanghai",
    "iso:country":"CN",
    "name:und_x_variant":[
        "\u96c5\u7548",
        "Yafan Zhen"
    ],
    "name:zho_x_preferred":[
        "\u96c5\u7548\u9547"
    ],
    "wof:name":"Yafan",
    "wof:placetype":"locality"
},
  "geometry": {"coordinates":[119.67534999999999,29.03657],"type":"Point"}
}