{
  "type": "Feature",
  "properties": {
    "gn:admin1_code":"33.0",
    "gn:asciiname":"Ganxi",
    "gn:country_code":"CN",
    "gn:dem":671,
    "gn:feature_class":"P",
    "gn:feature_code":"PPL",
    "gn:name":"Ganxi",
    "gn:population":0,
    "gn:timezone":"Asia/Shanghai",
    "iso:country":"CN",
    "name:zho_x_preferred":[
        "\u7518\u6eaa"
    ],
    "wof:name":"Ganxi",
    "wof:placetype":"locality"
},
  "geometry": {"coordinates":[108.61295,28.35535],"type":"Point"}
}