{
  "type": "Feature",
  "properties": {
    "gn:admin1_code":"10",
    "gn:asciiname":"Xiyangshu Goumen",
    "gn:country_code":"CN",
    "gn:dem":485,
    "gn:feature_class":"P",
    "gn:feature_code":"PPL",
    "gn:name":"Xiyangshu Goumen",
    "gn:population":0,
    "gn:timezone":"Asia/Shanghai",
    "iso:country":"CN",
    "name:zho_x_preferred":[
        "\u897f\u6768\u6811\u6c9f\u95e8"
    ],
    "wof:name":"Xiyangshu Goumen",
    "wof:placetype":"locality"
},
  "geometry": {"coordinates":[117.2102,40.88726],"type":"Point"}
}