{
  "type": "Feature",
  "properties": {
    "gn:admin1_code":"10",
    "gn:asciiname":"Gaogongzhuang",
    "gn:cc2":"CN",
    "gn:country_code":"CN",
    "gn:dem":32,
    "gn:feature_class":"P",
    "gn:feature_code":"PPL",
    "gn:name":"Gaogongzhuang",
    "gn:population":0,
    "gn:timezone":"Asia/Shanghai",
    "iso:country":"CN",
    "name:und_x_variant":[
        "Kao-kung-chuang",
        "Gaogongzhuang"
    ],
    "wof:name":"Gaogongzhuang",
    "wof:placetype":"locality"
},
  "geometry": {"coordinates":[115.34999999999999,37.21667],"type":"Point"}
}