{
  "type": "Feature",
  "properties": {
    "gn:admin1_code":"4.0",
    "gn:asciiname":"Feng Huang Shan",
    "gn:country_code":"CN",
    "gn:dem":29,
    "gn:feature_class":"P",
    "gn:feature_code":"PPL",
    "gn:name":"Feng Huang Shan",
    "gn:population":0,
    "gn:timezone":"Asia/Shanghai",
    "iso:country":"CN",
    "wof:name":"Feng Huang Shan",
    "wof:placetype":"locality"
},
  "geometry": {"coordinates":[118.76667,31.79167],"type":"Point"}
}