{
  "type": "Feature",
  "properties": {
    "gn:admin1_code":"30.0",
    "gn:asciiname":"Jiangping",
    "gn:country_code":"CN",
    "gn:dem":131,
    "gn:feature_class":"P",
    "gn:feature_code":"PPL",
    "gn:name":"Jiangping",
    "gn:population":0,
    "gn:timezone":"Asia/Shanghai",
    "iso:country":"CN",
    "name:zho_x_preferred":[
        "Jiangping"
    ],
    "name:zho_x_variant":[
        "\u6c5f\u576a"
    ],
    "wof:name":"Jiangping",
    "wof:placetype":"locality"
},
  "geometry": {"coordinates":[114.07589,24.31956],"type":"Point"}
}