{
  "type": "Feature",
  "properties": {
    "gn:admin1_code":"4.0",
    "gn:asciiname":"Xiaozhakou",
    "gn:country_code":"CN",
    "gn:dem":2,
    "gn:feature_class":"P",
    "gn:feature_code":"PPL",
    "gn:name":"Xiaozhakou",
    "gn:population":0,
    "gn:timezone":"Asia/Shanghai",
    "iso:country":"CN",
    "name:zho_x_preferred":[
        "\u5c0f\u95f8\u53e3"
    ],
    "wof:name":"Xiaozhakou",
    "wof:placetype":"locality"
},
  "geometry": {"coordinates":[120.16309,33.68872],"type":"Point"}
}