{
  "type": "Feature",
  "properties": {
    "gn:admin1_code":"10",
    "gn:asciiname":"Houlangzhong",
    "gn:country_code":"CN",
    "gn:dem":31,
    "gn:feature_class":"P",
    "gn:feature_code":"PPL",
    "gn:name":"Houlangzhong",
    "gn:population":0,
    "gn:timezone":"Asia/Shanghai",
    "iso:country":"CN",
    "name:zho_x_preferred":[
        "\u4faf\u72fc\u51a2"
    ],
    "wof:name":"Houlangzhong",
    "wof:placetype":"locality"
},
  "geometry": {"coordinates":[115.53400000000001,37.2416],"type":"Point"}
}