{
  "type": "Feature",
  "properties": {
    "gn:admin1_code":"01",
    "gn:asciiname":"Shuichipu",
    "gn:cc2":"CN",
    "gn:country_code":"CN",
    "gn:dem":23,
    "gn:feature_class":"P",
    "gn:feature_code":"PPL",
    "gn:name":"Shuichipu",
    "gn:population":0,
    "gn:timezone":"Asia/Shanghai",
    "iso:country":"CN",
    "name:und_x_variant":[
        "Shui-ch\u2019ih-p\u2019u",
        "Shuichipu"
    ],
    "wof:name":"Shuichipu",
    "wof:placetype":"locality"
},
  "geometry": {"coordinates":[117.11667,33.53333],"type":"Point"}
}