{
  "type": "Feature",
  "properties": {
    "gn:admin1_code":"16.0",
    "gn:asciiname":"Youjiling",
    "gn:country_code":"CN",
    "gn:dem":7,
    "gn:feature_class":"P",
    "gn:feature_code":"PPL",
    "gn:name":"Youjiling",
    "gn:population":0,
    "gn:timezone":"Asia/Shanghai",
    "iso:country":"CN",
    "name:zho_x_preferred":[
        "\u6709\u8ba1\u5cad"
    ],
    "wof:name":"Youjiling",
    "wof:placetype":"locality"
},
  "geometry": {"coordinates":[108.497,21.8124],"type":"Point"}
}