{
  "type": "Feature",
  "properties": {
    "gn:admin1_code":"29",
    "gn:asciiname":"Zeda",
    "gn:country_code":"CN",
    "gn:dem":1822,
    "gn:feature_class":"P",
    "gn:feature_code":"PPL",
    "gn:name":"Zeda",
    "gn:population":0,
    "gn:timezone":"Asia/Shanghai",
    "iso:country":"CN",
    "name:zho_x_preferred":[
        "\u5219\u8fbe"
    ],
    "wof:name":"Zeda",
    "wof:placetype":"locality"
},
  "geometry": {"coordinates":[101.956,24.4933],"type":"Point"}
}