{
  "type": "Feature",
  "properties": {
    "gn:admin1_code":"4.0",
    "gn:asciiname":"Wuhan Qingdai",
    "gn:country_code":"CN",
    "gn:dem":6,
    "gn:feature_class":"P",
    "gn:feature_code":"PPL",
    "gn:name":"Wuhan Qingdai",
    "gn:population":0,
    "gn:timezone":"Asia/Shanghai",
    "iso:country":"CN",
    "name:zho_x_preferred":[
        "\u5434\u6c49\u5e86\u5788"
    ],
    "wof:name":"Wuhan Qingdai",
    "wof:placetype":"locality"
},
  "geometry": {"coordinates":[120.34172,32.07975],"type":"Point"}
}