{
  "type": "Feature",
  "properties": {
    "gn:admin1_code":"4.0",
    "gn:asciiname":"Caoye",
    "gn:country_code":"CN",
    "gn:dem":10,
    "gn:feature_class":"P",
    "gn:feature_code":"PPL",
    "gn:name":"Caoye",
    "gn:population":0,
    "gn:timezone":"Asia/Shanghai",
    "iso:country":"CN",
    "name:zho_x_preferred":[
        "Caoye"
    ],
    "name:zho_x_variant":[
        "\u66f9\u53f6"
    ],
    "wof:name":"Caoye",
    "wof:placetype":"locality"
},
  "geometry": {"coordinates":[119.33095,33.87944],"type":"Point"}
}