{
  "type": "Feature",
  "properties": {
    "gn:admin1_code":"25.0",
    "gn:asciiname":"Beicheng",
    "gn:country_code":"CN",
    "gn:dem":7,
    "gn:feature_class":"P",
    "gn:feature_code":"PPL",
    "gn:name":"Beicheng",
    "gn:population":0,
    "gn:timezone":"Asia/Shanghai",
    "iso:country":"CN",
    "name:zho_x_preferred":[
        "\u5317\u57ce"
    ],
    "wof:name":"Beicheng",
    "wof:placetype":"locality"
},
  "geometry": {"coordinates":[122.43398000000001,37.39079],"type":"Point"}
}