{
  "type": "Feature",
  "properties": {
    "gn:admin1_code":"11.0",
    "gn:asciiname":"Maoping",
    "gn:country_code":"CN",
    "gn:dem":461,
    "gn:feature_class":"P",
    "gn:feature_code":"PPL",
    "gn:name":"Maoping",
    "gn:population":0,
    "gn:timezone":"Asia/Shanghai",
    "iso:country":"CN",
    "name:ceb_x_preferred":[
        "Maoping"
    ],
    "name:deu_x_preferred":[
        "Maoping"
    ],
    "name:swe_x_preferred":[
        "Maoping"
    ],
    "name:zho_x_preferred":[
        "\u6bdb\u576a"
    ],
    "wof:name":"Maoping",
    "wof:placetype":"locality"
},
  "geometry": {"coordinates":[109.60742,27.82265],"type":"Point"}
}