{
  "type": "Feature",
  "properties": {
    "gn:admin1_code":"21.0",
    "gn:asciiname":"Huojiagou",
    "gn:country_code":"CN",
    "gn:dem":1869,
    "gn:feature_class":"P",
    "gn:feature_code":"PPL",
    "gn:name":"Huojiagou",
    "gn:population":0,
    "gn:timezone":"Asia/Shanghai",
    "iso:country":"CN",
    "name:zho_x_preferred":[
        "\u706b\u5bb6\u6c9f"
    ],
    "wof:name":"Huojiagou",
    "wof:placetype":"locality"
},
  "geometry": {"coordinates":[105.87578999999999,35.80472],"type":"Point"}
}