{
  "type": "Feature",
  "properties": {
    "gn:admin1_code":"12.0",
    "gn:asciiname":"Laijiawenping",
    "gn:country_code":"CN",
    "gn:dem":792,
    "gn:feature_class":"P",
    "gn:feature_code":"PPL",
    "gn:name":"Laijiawenping",
    "gn:population":0,
    "gn:timezone":"Asia/Shanghai",
    "iso:country":"CN",
    "name:zho_x_preferred":[
        "\u8d56\u5bb6\u95ee\u576a"
    ],
    "wof:name":"Laijiawenping",
    "wof:placetype":"locality"
},
  "geometry": {"coordinates":[110.25802,31.36468],"type":"Point"}
}