{
  "type": "Feature",
  "properties": {
    "gn:admin1_code":"11.0",
    "gn:asciiname":"Yangjiawan",
    "gn:country_code":"CN",
    "gn:dem":449,
    "gn:feature_class":"P",
    "gn:feature_code":"PPL",
    "gn:name":"Yangjiawan",
    "gn:population":0,
    "gn:timezone":"Asia/Shanghai",
    "iso:country":"CN",
    "name:und_x_variant":[
        "Yangjiaxi",
        "Yangjiawan",
        "\u6768\u5bb6\u6e7e"
    ],
    "name:zho_x_preferred":[
        "\u6768\u5bb6\u6eaa"
    ],
    "wof:name":"Yangjiawan",
    "wof:placetype":"locality"
},
  "geometry": {"coordinates":[109.99003,29.22309000000001],"type":"Point"}
}