{
  "type": "Feature",
  "properties": {
    "gn:admin1_code":"5.0",
    "gn:asciiname":"Xiuyan Wobu",
    "gn:country_code":"CN",
    "gn:dem":181,
    "gn:feature_class":"P",
    "gn:feature_code":"PPL",
    "gn:name":"Xiuyan Wobu",
    "gn:population":0,
    "gn:timezone":"Asia/Shanghai",
    "iso:country":"CN",
    "name:zho_x_preferred":[
        "\u5cab\u5ca9\u7a9d\u5821"
    ],
    "wof:name":"Xiuyan Wobu",
    "wof:placetype":"locality"
},
  "geometry": {"coordinates":[125.61941000000002,44.4486],"type":"Point"}
}