{
  "type": "Feature",
  "properties": {
    "gn:admin1_code":"8.0",
    "gn:asciiname":"Heitongcun",
    "gn:country_code":"CN",
    "gn:dem":84,
    "gn:feature_class":"P",
    "gn:feature_code":"PPL",
    "gn:name":"Heitongcun",
    "gn:population":0,
    "gn:timezone":"Asia/Shanghai",
    "iso:country":"CN",
    "name:zho_x_preferred":[
        "\u9ed1\u901a\u6751"
    ],
    "wof:name":"Heitongcun",
    "wof:placetype":"locality"
},
  "geometry": {"coordinates":[130.17681999999999,46.79629],"type":"Point"}
}