{
  "type": "Feature",
  "properties": {
    "gn:admin1_code":"02",
    "gn:asciiname":"Yanmen",
    "gn:country_code":"CN",
    "gn:dem":482,
    "gn:feature_class":"P",
    "gn:feature_code":"PPL",
    "gn:name":"Yanmen",
    "gn:population":0,
    "gn:timezone":"Asia/Shanghai",
    "iso:country":"CN",
    "name:zho_x_preferred":[
        "\u5ca9\u95e8"
    ],
    "wof:name":"Yanmen",
    "wof:placetype":"locality"
},
  "geometry": {"coordinates":[120.42898999999998,27.99144],"type":"Point"}
}