{
  "type": "Feature",
  "properties": {
    "gn:admin1_code":"32.0",
    "gn:asciiname":"Sigan Qiancun",
    "gn:country_code":"CN",
    "gn:dem":2117,
    "gn:feature_class":"P",
    "gn:feature_code":"PPL",
    "gn:name":"Sigan Qiancun",
    "gn:population":0,
    "gn:timezone":"Asia/Shanghai",
    "iso:country":"CN",
    "name:zho_x_preferred":[
        "\u65af\u5e72\u5343\u6751"
    ],
    "wof:name":"Sigan Qiancun",
    "wof:placetype":"locality"
},
  "geometry": {"coordinates":[103.04000000000001,28.2967],"type":"Point"}
}