{
  "type": "Feature",
  "properties": {
    "gn:admin1_code":"12.0",
    "gn:asciiname":"Nanmaozhuang",
    "gn:country_code":"CN",
    "gn:dem":91,
    "gn:feature_class":"P",
    "gn:feature_code":"PPL",
    "gn:name":"Nanmaozhuang",
    "gn:population":0,
    "gn:timezone":"Asia/Shanghai",
    "iso:country":"CN",
    "name:zho_x_preferred":[
        "\u5357\u6bdb\u5e84"
    ],
    "wof:name":"Nanmaozhuang",
    "wof:placetype":"locality"
},
  "geometry": {"coordinates":[112.62745,32.0322],"type":"Point"}
}