{
  "type": "Feature",
  "properties": {
    "gn:admin1_code":"32.0",
    "gn:asciiname":"Xialuo",
    "gn:country_code":"CN",
    "gn:dem":2637,
    "gn:feature_class":"P",
    "gn:feature_code":"PPL",
    "gn:name":"Xialuo",
    "gn:population":0,
    "gn:timezone":"Asia/Shanghai",
    "iso:country":"CN",
    "name:zho_x_preferred":[
        "\u5477\u6d1b"
    ],
    "wof:name":"Xialuo",
    "wof:placetype":"locality"
},
  "geometry": {"coordinates":[102.86199999999999,28.2587],"type":"Point"}
}