{
  "type": "Feature",
  "properties": {
    "gn:admin1_code":"16.0",
    "gn:asciiname":"Yaohe",
    "gn:country_code":"CN",
    "gn:dem":493,
    "gn:feature_class":"P",
    "gn:feature_code":"PPL",
    "gn:name":"Yaohe",
    "gn:population":0,
    "gn:timezone":"Asia/Shanghai",
    "iso:country":"CN",
    "name:zho_x_preferred":[
        "\u5c27\u6cb3"
    ],
    "wof:name":"Yaohe",
    "wof:placetype":"locality"
},
  "geometry": {"coordinates":[108.592,24.8924],"type":"Point"}
}