{
  "type": "Feature",
  "properties": {
    "gn:admin1_code":"15.0",
    "gn:asciiname":"Yejiabu",
    "gn:country_code":"CN",
    "gn:dem":1374,
    "gn:feature_class":"P",
    "gn:feature_code":"PPL",
    "gn:name":"Yejiabu",
    "gn:population":0,
    "gn:timezone":"Asia/Shanghai",
    "iso:country":"CN",
    "name:zho_x_preferred":[
        "\u53f6\u5bb6\u5821"
    ],
    "wof:name":"Yejiabu",
    "wof:placetype":"locality"
},
  "geometry": {"coordinates":[106.694,35.5546],"type":"Point"}
}