{
  "type": "Feature",
  "properties": {
    "gn:admin1_code":"1.0",
    "gn:asciiname":"Yuanzhuangcun",
    "gn:country_code":"CN",
    "gn:dem":37,
    "gn:feature_class":"P",
    "gn:feature_code":"PPL",
    "gn:name":"Yuanzhuangcun",
    "gn:population":0,
    "gn:timezone":"Asia/Shanghai",
    "iso:country":"CN",
    "name:zho_x_preferred":[
        "\u82d1\u5e84\u6751"
    ],
    "wof:name":"Yuanzhuangcun",
    "wof:placetype":"locality"
},
  "geometry": {"coordinates":[116.03917,33.81136],"type":"Point"}
}