{
  "type": "Feature",
  "properties": {
    "gn:admin1_code":"29.0",
    "gn:asciiname":"Maosupo",
    "gn:country_code":"CN",
    "gn:dem":2429,
    "gn:feature_class":"P",
    "gn:feature_code":"PPL",
    "gn:name":"Maosupo",
    "gn:population":0,
    "gn:timezone":"Asia/Shanghai",
    "iso:country":"CN",
    "name:zho_x_preferred":[
        "\u6bdb\u7c9f\u5761"
    ],
    "wof:name":"Maosupo",
    "wof:placetype":"locality"
},
  "geometry": {"coordinates":[100.461,25.5554],"type":"Point"}
}