{
  "type": "Feature",
  "properties": {
    "gn:admin1_code":"4.0",
    "gn:asciiname":"Nanzao Qizu",
    "gn:country_code":"CN",
    "gn:dem":1,
    "gn:feature_class":"P",
    "gn:feature_code":"PPLF",
    "gn:name":"Nanzao Qizu",
    "gn:population":0,
    "gn:timezone":"Asia/Shanghai",
    "iso:country":"CN",
    "name:zho_x_preferred":[
        "\u5357\u7076\u4e03\u7ec4"
    ],
    "wof:name":"Nanzao Qizu",
    "wof:placetype":"locality"
},
  "geometry": {"coordinates":[120.36799999999999,33.6447],"type":"Point"}
}