{
  "type": "Feature",
  "properties": {
    "gn:admin1_code":"6.0",
    "gn:asciiname":"Charanning",
    "gn:country_code":"CN",
    "gn:dem":4297,
    "gn:feature_class":"P",
    "gn:feature_code":"PPL",
    "gn:name":"Charanning",
    "gn:population":0,
    "gn:timezone":"Asia/Urumqi",
    "iso:country":"CN",
    "name:zho_x_preferred":[
        "\u67e5\u7136\u5b81"
    ],
    "wof:name":"Charanning",
    "wof:placetype":"locality"
},
  "geometry": {"coordinates":[96.14726,32.09127],"type":"Point"}
}