{
  "type": "Feature",
  "properties": {
    "gn:admin1_code":"07",
    "gn:asciiname":"Hengbeigang",
    "gn:country_code":"CN",
    "gn:dem":603,
    "gn:feature_class":"P",
    "gn:feature_code":"PPL",
    "gn:name":"Hengbeigang",
    "gn:population":0,
    "gn:timezone":"Asia/Shanghai",
    "iso:country":"CN",
    "name:zho_x_preferred":[
        "\u6a2a\u80cc\u5c97"
    ],
    "wof:name":"Hengbeigang",
    "wof:placetype":"locality"
},
  "geometry": {"coordinates":[116.4796,24.73233],"type":"Point"}
}