{
  "type": "Feature",
  "properties": {
    "gn:admin1_code":"19.0",
    "gn:asciiname":"Erdaofangcun",
    "gn:country_code":"CN",
    "gn:dem":42,
    "gn:feature_class":"P",
    "gn:feature_code":"PPL",
    "gn:name":"Erdaofangcun",
    "gn:population":0,
    "gn:timezone":"Asia/Shanghai",
    "iso:country":"CN",
    "name:zho_x_preferred":[
        "\u4e8c\u9053\u623f\u6751"
    ],
    "wof:name":"Erdaofangcun",
    "wof:placetype":"locality"
},
  "geometry": {"coordinates":[123.274,42.1392],"type":"Point"}
}