{
  "type": "Feature",
  "properties": {
    "gn:admin1_code":"16.0",
    "gn:asciiname":"Guotai",
    "gn:country_code":"CN",
    "gn:dem":115,
    "gn:feature_class":"P",
    "gn:feature_code":"PPL",
    "gn:name":"Guotai",
    "gn:population":0,
    "gn:timezone":"Asia/Shanghai",
    "iso:country":"CN",
    "name:zho_x_preferred":[
        "\u56fd\u6cf0"
    ],
    "wof:name":"Guotai",
    "wof:placetype":"locality"
},
  "geometry": {"coordinates":[108.846,23.2102],"type":"Point"}
}