{
  "type": "Feature",
  "properties": {
    "gn:admin1_code":"32.0",
    "gn:asciiname":"Shilingsi",
    "gn:country_code":"CN",
    "gn:dem":504,
    "gn:feature_class":"P",
    "gn:feature_code":"PPL",
    "gn:name":"Shilingsi",
    "gn:population":0,
    "gn:timezone":"Asia/Shanghai",
    "iso:country":"CN",
    "name:zho_x_preferred":[
        "\u77f3\u7075\u5bfa"
    ],
    "wof:name":"Shilingsi",
    "wof:placetype":"locality"
},
  "geometry": {"coordinates":[104.17831,30.65213],"type":"Point"}
}