{
  "type": "Feature",
  "properties": {
    "gn:admin1_code":"18",
    "gn:asciiname":"Chetanggou",
    "gn:country_code":"CN",
    "gn:dem":1220,
    "gn:feature_class":"P",
    "gn:feature_code":"PPL",
    "gn:name":"Chetanggou",
    "gn:population":0,
    "gn:timezone":"Asia/Shanghai",
    "iso:country":"CN",
    "name:zho_x_preferred":[
        "\u8f66\u5858\u6c9f"
    ],
    "wof:name":"Chetanggou",
    "wof:placetype":"locality"
},
  "geometry": {"coordinates":[108.09699999999999,28.6554],"type":"Point"}
}