{
  "type": "Feature",
  "properties": {
    "gn:admin1_code":"16",
    "gn:asciiname":"Shazixi",
    "gn:country_code":"CN",
    "gn:dem":169,
    "gn:feature_class":"P",
    "gn:feature_code":"PPL",
    "gn:name":"Shazixi",
    "gn:population":0,
    "gn:timezone":"Asia/Shanghai",
    "iso:country":"CN",
    "name:zho_x_preferred":[
        "\u6c99\u5b50\u6eaa"
    ],
    "wof:name":"Shazixi",
    "wof:placetype":"locality"
},
  "geometry": {"coordinates":[110.51900000000001,24.6919],"type":"Point"}
}