{
  "type": "Feature",
  "properties": {
    "gn:admin1_code":"15.0",
    "gn:asciiname":"Yaoshui",
    "gn:country_code":"CN",
    "gn:dem":1911,
    "gn:feature_class":"P",
    "gn:feature_code":"PPL",
    "gn:name":"Yaoshui",
    "gn:population":0,
    "gn:timezone":"Asia/Shanghai",
    "iso:country":"CN",
    "name:zho_x_preferred":[
        "\u8170\u6c34"
    ],
    "wof:name":"Yaoshui",
    "wof:placetype":"locality"
},
  "geometry": {"coordinates":[104.62,36.9195],"type":"Point"}
}