{
  "type": "Feature",
  "properties": {
    "gn:admin1_code":"14.0",
    "gn:asciiname":"Pamasi",
    "gn:country_code":"CN",
    "gn:dem":4615,
    "gn:feature_class":"P",
    "gn:feature_code":"PPL",
    "gn:name":"Pamasi",
    "gn:population":0,
    "gn:timezone":"Asia/Urumqi",
    "iso:country":"CN",
    "name:zho_x_preferred":[
        "\u6015\u739b\u5bfa"
    ],
    "wof:name":"Pamasi",
    "wof:placetype":"locality"
},
  "geometry": {"coordinates":[93.90345000000001,31.45773],"type":"Point"}
}