{
  "type": "Feature",
  "properties": {
    "gn:admin1_code":"19.0",
    "gn:asciiname":"Xibeijia",
    "gn:country_code":"CN",
    "gn:dem":39,
    "gn:feature_class":"P",
    "gn:feature_code":"PPL",
    "gn:name":"Xibeijia",
    "gn:population":0,
    "gn:timezone":"Asia/Shanghai",
    "iso:country":"CN",
    "name:und_x_variant":[
        "\u897f\u8d1d\u5bb6"
    ],
    "name:zho_x_preferred":[
        "\u897f\u8d1d\u5bb6"
    ],
    "wof:name":"Xibeijia",
    "wof:placetype":"locality"
},
  "geometry": {"coordinates":[120.35250000000001,40.42583],"type":"Point"}
}