{
  "type": "Feature",
  "properties": {
    "gn:admin1_code":"30",
    "gn:asciiname":"Liuneicun",
    "gn:country_code":"CN",
    "gn:dem":30,
    "gn:feature_class":"P",
    "gn:feature_code":"PPL",
    "gn:name":"Liuneicun",
    "gn:population":0,
    "gn:timezone":"Asia/Urumqi",
    "iso:country":"CN",
    "name:zho_x_preferred":[
        "\u516d\u5185\u6751"
    ],
    "wof:name":"Liuneicun",
    "wof:placetype":"locality"
},
  "geometry": {"coordinates":[109.97609,21.11737],"type":"Point"}
}