{
  "type": "Feature",
  "properties": {
    "gn:admin1_code":"25",
    "gn:asciiname":"Jiejiabu",
    "gn:country_code":"CN",
    "gn:dem":188,
    "gn:feature_class":"P",
    "gn:feature_code":"PPL",
    "gn:name":"Jiejiabu",
    "gn:population":0,
    "gn:timezone":"Asia/Shanghai",
    "iso:country":"CN",
    "name:zho_x_preferred":[
        "\u63a5\u9a7e\u57e0"
    ],
    "wof:name":"Jiejiabu",
    "wof:placetype":"locality"
},
  "geometry": {"coordinates":[117.48699999999999,36.3443],"type":"Point"}
}