{
  "type": "Feature",
  "properties": {
    "gn:admin1_code":"1.0",
    "gn:asciiname":"Yujiayao",
    "gn:country_code":"CN",
    "gn:dem":59,
    "gn:feature_class":"P",
    "gn:feature_code":"PPL",
    "gn:name":"Yujiayao",
    "gn:population":0,
    "gn:timezone":"Asia/Shanghai",
    "iso:country":"CN",
    "name:zho_x_preferred":[
        "\u4fde\u5bb6\u7a91"
    ],
    "wof:name":"Yujiayao",
    "wof:placetype":"locality"
},
  "geometry": {"coordinates":[118.59072999999999,31.05294],"type":"Point"}
}