{
  "type": "Feature",
  "properties": {
    "gn:admin1_code":"11.0",
    "gn:asciiname":"Chuanxi",
    "gn:country_code":"CN",
    "gn:dem":505,
    "gn:feature_class":"P",
    "gn:feature_code":"PPL",
    "gn:name":"Chuanxi",
    "gn:population":0,
    "gn:timezone":"Asia/Shanghai",
    "iso:country":"CN",
    "name:zho_x_preferred":[
        "\u8239\u6eaa"
    ],
    "wof:name":"Chuanxi",
    "wof:placetype":"locality"
},
  "geometry": {"coordinates":[110.79774999999999,28.33549],"type":"Point"}
}