{
  "type": "Feature",
  "properties": {
    "gn:admin1_code":"15.0",
    "gn:asciiname":"Qingyangshuliang",
    "gn:country_code":"CN",
    "gn:dem":1321,
    "gn:feature_class":"P",
    "gn:feature_code":"PPL",
    "gn:name":"Qingyangshuliang",
    "gn:population":0,
    "gn:timezone":"Asia/Shanghai",
    "iso:country":"CN",
    "name:und_x_variant":[
        "\u9752\u6768\u6811\u6881"
    ],
    "wof:name":"Qingyangshuliang",
    "wof:placetype":"locality"
},
  "geometry": {"coordinates":[107.62430000000001,36.15784],"type":"Point"}
}