{
  "type": "Feature",
  "properties": {
    "gn:admin1_code":"30",
    "gn:asciiname":"Tianwang",
    "gn:country_code":"CN",
    "gn:dem":148,
    "gn:feature_class":"P",
    "gn:feature_code":"PPL",
    "gn:name":"Tianwang",
    "gn:population":0,
    "gn:timezone":"Asia/Shanghai",
    "iso:country":"CN",
    "name:und_x_variant":[
        "\u5929\u738b"
    ],
    "name:zho_x_preferred":[
        "\u5929\u738b"
    ],
    "wof:name":"Tianwang",
    "wof:placetype":"locality"
},
  "geometry": {"coordinates":[113.95222,23.36972],"type":"Point"}
}