{
  "type": "Feature",
  "properties": {
    "gn:admin1_code":"32.0",
    "gn:asciiname":"Erdamaiba Ercun",
    "gn:country_code":"CN",
    "gn:dem":3987,
    "gn:feature_class":"P",
    "gn:feature_code":"PPL",
    "gn:name":"Erdamaiba Ercun",
    "gn:population":0,
    "gn:timezone":"Asia/Shanghai",
    "iso:country":"CN",
    "name:zho_x_preferred":[
        "\u4fc4\u8fbe\u9ea6\u5df4\u4e8c\u6751"
    ],
    "wof:name":"Erdamaiba Ercun",
    "wof:placetype":"locality"
},
  "geometry": {"coordinates":[101.75,29.9759],"type":"Point"}
}