{
  "type": "Feature",
  "properties": {
    "gn:admin1_code":"2.0",
    "gn:asciiname":"Tongwamen",
    "gn:country_code":"CN",
    "gn:dem":46,
    "gn:feature_class":"P",
    "gn:feature_code":"PPL",
    "gn:name":"Tongwamen",
    "gn:population":0,
    "gn:timezone":"Asia/Shanghai",
    "iso:country":"CN",
    "name:zho_x_preferred":[
        "\u94dc\u74e6\u95e8"
    ],
    "wof:name":"Tongwamen",
    "wof:placetype":"locality"
},
  "geometry": {"coordinates":[121.33711,28.21349],"type":"Point"}
}