{
  "type": "Feature",
  "properties": {
    "gn:admin1_code":"14.0",
    "gn:asciiname":"Tingcun",
    "gn:country_code":"CN",
    "gn:dem":3620,
    "gn:feature_class":"P",
    "gn:feature_code":"PPL",
    "gn:name":"Tingcun",
    "gn:population":0,
    "gn:timezone":"Asia/Urumqi",
    "iso:country":"CN",
    "name:bod_x_preferred":[
        "T\u00eangcun"
    ],
    "name:zho_x_preferred":[
        "\u4ead\u6751"
    ],
    "wof:name":"Tingcun",
    "wof:placetype":"locality"
},
  "geometry": {"coordinates":[91.08429,28.11458],"type":"Point"}
}