{
  "type": "Feature",
  "properties": {
    "gn:admin1_code":"2.0",
    "gn:asciiname":"Fenshui",
    "gn:country_code":"CN",
    "gn:dem":359,
    "gn:feature_class":"P",
    "gn:feature_code":"PPL",
    "gn:name":"Fenshui",
    "gn:population":0,
    "gn:timezone":"Asia/Shanghai",
    "iso:country":"CN",
    "name:zho_x_preferred":[
        "\u5206\u6c34"
    ],
    "wof:name":"Fenshui",
    "wof:placetype":"locality"
},
  "geometry": {"coordinates":[120.69847,28.39409],"type":"Point"}
}