{
  "type": "Feature",
  "properties": {
    "gn:admin1_code":"30.0",
    "gn:asciiname":"Tianxingcun",
    "gn:country_code":"CN",
    "gn:dem":173,
    "gn:feature_class":"P",
    "gn:feature_code":"PPL",
    "gn:name":"Tianxingcun",
    "gn:population":0,
    "gn:timezone":"Asia/Shanghai",
    "iso:country":"CN",
    "name:zho_x_preferred":[
        "\u7530\u5174\u6751"
    ],
    "wof:name":"Tianxingcun",
    "wof:placetype":"locality"
},
  "geometry": {"coordinates":[115.86669999999999,24.53141],"type":"Point"}
}