{
  "type": "Feature",
  "properties": {
    "gn:admin1_code":"24.0",
    "gn:asciiname":"Beixinyao",
    "gn:country_code":"CN",
    "gn:dem":1559,
    "gn:feature_class":"P",
    "gn:feature_code":"PPL",
    "gn:name":"Beixinyao",
    "gn:population":0,
    "gn:timezone":"Asia/Shanghai",
    "iso:country":"CN",
    "name:und_x_variant":[
        "\u5317\u8f9b\u7a91"
    ],
    "wof:name":"Beixinyao",
    "wof:placetype":"locality"
},
  "geometry": {"coordinates":[112.22033999999999,39.794],"type":"Point"}
}