{
  "type": "Feature",
  "properties": {
    "gn:admin1_code":"29.0",
    "gn:asciiname":"Shuimo",
    "gn:country_code":"CN",
    "gn:dem":2556,
    "gn:feature_class":"P",
    "gn:feature_code":"PPL",
    "gn:name":"Shuimo",
    "gn:population":0,
    "gn:timezone":"Asia/Shanghai",
    "iso:country":"CN",
    "name:und_x_variant":[
        "\u6c34\u78e8"
    ],
    "wof:name":"Shuimo",
    "wof:placetype":"locality"
},
  "geometry": {"coordinates":[103.25075,26.67983],"type":"Point"}
}