{
  "type": "Feature",
  "properties": {
    "gn:admin1_code":"26.0",
    "gn:asciiname":"Wangyuangou",
    "gn:country_code":"CN",
    "gn:dem":1158,
    "gn:feature_class":"P",
    "gn:feature_code":"PPL",
    "gn:name":"Wangyuangou",
    "gn:population":0,
    "gn:timezone":"Asia/Shanghai",
    "iso:country":"CN",
    "name:zho_x_preferred":[
        "\u738b\u9662\u6c9f"
    ],
    "wof:name":"Wangyuangou",
    "wof:placetype":"locality"
},
  "geometry": {"coordinates":[110.27779,33.94383],"type":"Point"}
}