{
  "type": "Feature",
  "properties": {
    "gn:admin1_code":"7",
    "gn:asciiname":"Licun",
    "gn:country_code":"CN",
    "gn:dem":722,
    "gn:feature_class":"P",
    "gn:feature_code":"PPL",
    "gn:name":"Licun",
    "gn:population":0,
    "gn:timezone":"Asia/Shanghai",
    "iso:country":"CN",
    "name:und_x_variant":[
        "\u91cc\u6751",
        "Licun"
    ],
    "wof:name":"Licun",
    "wof:placetype":"locality"
},
  "geometry": {"coordinates":[119.50962,27.13757],"type":"Point"}
}