{
  "type": "Feature",
  "properties": {
    "gn:admin1_code":"18",
    "gn:asciiname":"Ganheba",
    "gn:country_code":"CN",
    "gn:dem":908,
    "gn:feature_class":"P",
    "gn:feature_code":"PPL",
    "gn:name":"Ganheba",
    "gn:population":0,
    "gn:timezone":"Asia/Shanghai",
    "iso:country":"CN",
    "name:zho_x_preferred":[
        "\u5e72\u6cb3\u575d"
    ],
    "wof:name":"Ganheba",
    "wof:placetype":"locality"
},
  "geometry": {"coordinates":[106.494,27.3855],"type":"Point"}
}