{
  "type": "Feature",
  "properties": {
    "gn:admin1_code":"32.0",
    "gn:asciiname":"Mupa",
    "gn:country_code":"CN",
    "gn:dem":2953,
    "gn:feature_class":"P",
    "gn:feature_code":"PPL",
    "gn:name":"Mupa",
    "gn:population":0,
    "gn:timezone":"Asia/Shanghai",
    "iso:country":"CN",
    "name:msa_x_preferred":[
        "Mupa"
    ],
    "name:por_x_preferred":[
        "Mupa"
    ],
    "name:zho_x_preferred":[
        "\u6728\u6015"
    ],
    "wof:name":"Mupa",
    "wof:placetype":"locality"
},
  "geometry": {"coordinates":[100.962,27.8917],"type":"Point"}
}