{
  "type": "Feature",
  "properties": {
    "gn:admin1_code":"32",
    "gn:asciiname":"Guihua",
    "gn:country_code":"CN",
    "gn:dem":821,
    "gn:feature_class":"P",
    "gn:feature_code":"PPL",
    "gn:name":"Guihua",
    "gn:population":0,
    "gn:timezone":"Asia/Shanghai",
    "iso:country":"CN",
    "name:und_x_variant":[
        "Guihuachang",
        "Guihua"
    ],
    "name:zho_x_preferred":[
        "\u6842\u82b1"
    ],
    "wof:name":"Guihua",
    "wof:placetype":"locality"
},
  "geometry": {"coordinates":[105.68482,28.18553],"type":"Point"}
}