{
  "type": "Feature",
  "properties": {
    "gn:admin1_code":"29.0",
    "gn:asciiname":"Jinjia Pingzi",
    "gn:country_code":"CN",
    "gn:dem":1725,
    "gn:feature_class":"P",
    "gn:feature_code":"PPL",
    "gn:name":"Jinjia Pingzi",
    "gn:population":0,
    "gn:timezone":"Asia/Shanghai",
    "iso:country":"CN",
    "name:zho_x_preferred":[
        "\u91d1\u5bb6\u576a\u5b50"
    ],
    "wof:name":"Jinjia Pingzi",
    "wof:placetype":"locality"
},
  "geometry": {"coordinates":[99.5752,25.3723],"type":"Point"}
}