{
  "type": "Feature",
  "properties": {
    "gn:admin1_code":"29",
    "gn:asciiname":"Shiyi",
    "gn:country_code":"CN",
    "gn:dem":1548,
    "gn:feature_class":"P",
    "gn:feature_code":"PPL",
    "gn:name":"Shiyi",
    "gn:population":0,
    "gn:timezone":"Asia/Shanghai",
    "iso:country":"CN",
    "name:zho_x_preferred":[
        "\u77f3\u9091"
    ],
    "wof:name":"Shiyi",
    "wof:placetype":"locality"
},
  "geometry": {"coordinates":[102.46671000000001,24.17407],"type":"Point"}
}