{
  "type": "Feature",
  "properties": {
    "gn:admin1_code":"29",
    "gn:asciiname":"Damu",
    "gn:country_code":"CN",
    "gn:dem":1341,
    "gn:feature_class":"P",
    "gn:feature_code":"PPL",
    "gn:name":"Damu",
    "gn:population":0,
    "gn:timezone":"Asia/Shanghai",
    "iso:country":"CN",
    "name:deu_x_preferred":[
        "Damu"
    ],
    "name:eus_x_preferred":[
        "Damu"
    ],
    "name:fra_x_preferred":[
        "Damu"
    ],
    "name:hrv_x_preferred":[
        "Damu"
    ],
    "name:kur_x_preferred":[
        "Damu"
    ],
    "name:spa_x_preferred":[
        "Damu"
    ],
    "name:tur_x_preferred":[
        "Damu"
    ],
    "name:zho_x_preferred":[
        "\u8fbe\u6728"
    ],
    "wof:name":"Damu",
    "wof:placetype":"locality"
},
  "geometry": {"coordinates":[105.60599999999999,23.7509],"type":"Point"}
}