{
  "type": "Feature",
  "properties": {
    "gn:admin1_code":"25",
    "gn:asciiname":"Beiwangzhuang",
    "gn:country_code":"CN",
    "gn:dem":34,
    "gn:feature_class":"P",
    "gn:feature_code":"PPL",
    "gn:name":"Beiwangzhuang",
    "gn:population":0,
    "gn:timezone":"Asia/Shanghai",
    "iso:country":"CN",
    "name:zho_x_preferred":[
        "\u5317\u738b\u5e84"
    ],
    "wof:name":"Beiwangzhuang",
    "wof:placetype":"locality"
},
  "geometry": {"coordinates":[116.068,36.8816],"type":"Point"}
}