{
  "type": "Feature",
  "properties": {
    "gn:admin1_code":"15.0",
    "gn:asciiname":"Tanglubu",
    "gn:country_code":"CN",
    "gn:dem":1499,
    "gn:feature_class":"P",
    "gn:feature_code":"PPL",
    "gn:name":"Tangl\u00fcbu",
    "gn:population":0,
    "gn:timezone":"Asia/Shanghai",
    "iso:country":"CN",
    "name:und_x_variant":[
        "Tangl\u00fcbu"
    ],
    "name:zho_x_preferred":[
        "\u6c64\u5415\u5821"
    ],
    "wof:name":"Tanglubu",
    "wof:placetype":"locality"
},
  "geometry": {"coordinates":[102.57599999999999,38.2118],"type":"Point"}
}