{
  "type": "Feature",
  "properties": {
    "gn:admin1_code":"29.0",
    "gn:asciiname":"Meijing",
    "gn:country_code":"CN",
    "gn:dem":1429,
    "gn:feature_class":"P",
    "gn:feature_code":"PPL",
    "gn:name":"Meijing",
    "gn:population":0,
    "gn:timezone":"Asia/Shanghai",
    "iso:country":"CN",
    "name:und_x_variant":[
        "\u7164\u4e95"
    ],
    "wof:name":"Meijing",
    "wof:placetype":"locality"
},
  "geometry": {"coordinates":[103.94408,28.42145],"type":"Point"}
}