{
  "type": "Feature",
  "properties": {
    "gn:admin1_code":"7.0",
    "gn:asciiname":"Shazuiping",
    "gn:country_code":"CN",
    "gn:dem":167,
    "gn:feature_class":"P",
    "gn:feature_code":"PPL",
    "gn:name":"Shazuiping",
    "gn:population":0,
    "gn:timezone":"Asia/Shanghai",
    "iso:country":"CN",
    "name:zho_x_preferred":[
        "\u6c99\u5480\u576a"
    ],
    "wof:name":"Shazuiping",
    "wof:placetype":"locality"
},
  "geometry": {"coordinates":[116.64915999999999,24.72425],"type":"Point"}
}