{
  "type": "Feature",
  "properties": {
    "gn:admin1_code":"7.0",
    "gn:asciiname":"Jingke",
    "gn:country_code":"CN",
    "gn:dem":125,
    "gn:feature_class":"P",
    "gn:feature_code":"PPL",
    "gn:name":"Jingke",
    "gn:population":0,
    "gn:timezone":"Asia/Shanghai",
    "iso:country":"CN",
    "name:zho_x_preferred":[
        "\u4e95\u7aa0"
    ],
    "wof:name":"Jingke",
    "wof:placetype":"locality"
},
  "geometry": {"coordinates":[117.91894000000001,26.63326],"type":"Point"}
}