{
  "type": "Feature",
  "properties": {
    "gn:admin1_code":"2.0",
    "gn:asciiname":"Xianli",
    "gn:country_code":"CN",
    "gn:dem":64,
    "gn:feature_class":"P",
    "gn:feature_code":"PPL",
    "gn:name":"Xianli",
    "gn:population":0,
    "gn:timezone":"Asia/Shanghai",
    "iso:country":"CN",
    "name:und_x_variant":[
        "\u4ed9\u91cc"
    ],
    "wof:name":"Xianli",
    "wof:placetype":"locality"
},
  "geometry": {"coordinates":[119.68940000000001,30.03909],"type":"Point"}
}