{
  "type": "Feature",
  "properties": {
    "gn:admin1_code":"8.0",
    "gn:asciiname":"Ji'ergele Teguoleng",
    "gn:country_code":"CN",
    "gn:dem":502,
    "gn:feature_class":"P",
    "gn:feature_code":"PPLA4",
    "gn:name":"Ji\u2019ergele Teguoleng",
    "gn:population":0,
    "gn:timezone":"Asia/Urumqi",
    "iso:country":"CN",
    "name:und_x_variant":[
        "Ji\u2019ergele Teguoleng",
        "Ji\u2019ergele Teguoleng Xiang",
        "Ji\u2019ergele Teguoleng Mengguzu Xiang"
    ],
    "name:zho_x_preferred":[
        "\u5409\u5c14\u683c\u52d2\u7279\u90ed\u695e"
    ],
    "name:zho_x_variant":[
        "\u5409\u5c14\u683c\u52d2\u7279\u90ed\u695e\u4e61",
        "\u5409\u5c14\u683c\u52d2\u7279\u90ed\u695e\u8499\u53e4\u65cf\u4e61"
    ],
    "wof:name":"Ji'ergele Teguoleng",
    "wof:placetype":"locality"
},
  "geometry": {"coordinates":[84.17916,44.35542],"type":"Point"}
}