{
  "type": "Feature",
  "properties": {
    "gn:admin1_code":"8.0",
    "gn:asciiname":"Lanxin Jingjisuo",
    "gn:country_code":"CN",
    "gn:dem":302,
    "gn:feature_class":"P",
    "gn:feature_code":"PPLF",
    "gn:name":"Lanxin Jingjisuo",
    "gn:population":0,
    "gn:timezone":"Asia/Shanghai",
    "iso:country":"CN",
    "name:zho_x_preferred":[
        "\u5170\u65b0\u7ecf\u6d4e\u6240"
    ],
    "wof:name":"Lanxin Jingjisuo",
    "wof:placetype":"locality"
},
  "geometry": {"coordinates":[129.10238000000001,47.57655],"type":"Point"}
}