{
  "type": "Feature",
  "properties": {
    "gn:admin1_code":"18.0",
    "gn:asciiname":"Dalai",
    "gn:country_code":"CN",
    "gn:dem":885,
    "gn:feature_class":"P",
    "gn:feature_code":"PPL",
    "gn:name":"Dalai",
    "gn:population":0,
    "gn:timezone":"Asia/Shanghai",
    "iso:country":"CN",
    "name:ceb_x_preferred":[
        "Dalai"
    ],
    "name:deu_x_preferred":[
        "Dalai"
    ],
    "name:fra_x_preferred":[
        "Dala\u00ef"
    ],
    "name:mlg_x_preferred":[
        "Dalai"
    ],
    "name:swe_x_preferred":[
        "Dalai"
    ],
    "name:zho_x_preferred":[
        "\u6253\u8d56"
    ],
    "wof:name":"Dalai",
    "wof:placetype":"locality"
},
  "geometry": {"coordinates":[107.315,25.9544],"type":"Point"}
}