{
  "type": "Feature",
  "properties": {
    "gn:admin1_code":"10.0",
    "gn:asciiname":"Hugezhuang",
    "gn:country_code":"CN",
    "gn:dem":12,
    "gn:feature_class":"P",
    "gn:feature_code":"PPL",
    "gn:name":"Hugezhuang",
    "gn:population":0,
    "gn:timezone":"Asia/Shanghai",
    "iso:country":"CN",
    "name:zho_x_preferred":[
        "\u80e1\u5404\u5e84"
    ],
    "wof:name":"Hugezhuang",
    "wof:placetype":"locality"
},
  "geometry": {"coordinates":[116.19544999999999,38.97024],"type":"Point"}
}