{
  "type": "Feature",
  "properties": {
    "gn:admin1_code":"8.0",
    "gn:asciiname":"Halahuxue",
    "gn:country_code":"CN",
    "gn:dem":128,
    "gn:feature_class":"P",
    "gn:feature_code":"PPL",
    "gn:name":"Halahuxue",
    "gn:population":0,
    "gn:timezone":"Asia/Shanghai",
    "iso:country":"CN",
    "name:zho_x_preferred":[
        "\u54c8\u62c9\u80e1\u8840"
    ],
    "wof:name":"Halahuxue",
    "wof:placetype":"locality"
},
  "geometry": {"coordinates":[125.64185000000001,45.59192],"type":"Point"}
}