{
  "type": "Feature",
  "properties": {
    "gn:admin1_code":"4.0",
    "gn:asciiname":"Yujiaba",
    "gn:country_code":"CN",
    "gn:dem":5,
    "gn:feature_class":"P",
    "gn:feature_code":"PPL",
    "gn:name":"Yujiaba",
    "gn:population":0,
    "gn:timezone":"Asia/Shanghai",
    "iso:country":"CN",
    "name:und_x_variant":[
        "\u4e8e\u5bb6\u575d"
    ],
    "wof:name":"Yujiaba",
    "wof:placetype":"locality"
},
  "geometry": {"coordinates":[120.96811,32.12988],"type":"Point"}
}