{
  "type": "Feature",
  "properties": {
    "gn:admin1_code":"1.0",
    "gn:asciiname":"Wangzhaocun",
    "gn:country_code":"CN",
    "gn:dem":23,
    "gn:feature_class":"P",
    "gn:feature_code":"PPL",
    "gn:name":"Wangzhaocun",
    "gn:population":0,
    "gn:timezone":"Asia/Shanghai",
    "iso:country":"CN",
    "name:zho_x_preferred":[
        "\u738b\u8d75\u6751"
    ],
    "wof:name":"Wangzhaocun",
    "wof:placetype":"locality"
},
  "geometry": {"coordinates":[117.93088,33.66333],"type":"Point"}
}