{
  "type": "Feature",
  "properties": {
    "gn:admin1_code":"30.0",
    "gn:asciiname":"Majing",
    "gn:country_code":"CN",
    "gn:dem":98,
    "gn:feature_class":"P",
    "gn:feature_code":"PPL",
    "gn:name":"Majing",
    "gn:population":0,
    "gn:timezone":"Asia/Shanghai",
    "iso:country":"CN",
    "name:zho_x_preferred":[
        "Majing"
    ],
    "name:zho_x_variant":[
        "\u9a6c\u60ca"
    ],
    "wof:name":"Majing",
    "wof:placetype":"locality"
},
  "geometry": {"coordinates":[112.42528,24.57833],"type":"Point"}
}