{
  "type": "Feature",
  "properties": {
    "gn:admin1_code":"33.0",
    "gn:asciiname":"Shenjiping",
    "gn:country_code":"CN",
    "gn:dem":414,
    "gn:feature_class":"P",
    "gn:feature_code":"PPL",
    "gn:name":"Shenjiping",
    "gn:population":0,
    "gn:timezone":"Asia/Shanghai",
    "iso:country":"CN",
    "name:zho_x_preferred":[
        "\u795e\u57fa\u576a"
    ],
    "wof:name":"Shenjiping",
    "wof:placetype":"locality"
},
  "geometry": {"coordinates":[109.66119999999999,31.57968],"type":"Point"}
}