{
  "type": "Feature",
  "properties": {
    "gn:admin1_code":"29.0",
    "gn:asciiname":"Shangziyaguan",
    "gn:country_code":"CN",
    "gn:dem":1504,
    "gn:feature_class":"P",
    "gn:feature_code":"PPL",
    "gn:name":"Shangziyaguan",
    "gn:population":0,
    "gn:timezone":"Asia/Shanghai",
    "iso:country":"CN",
    "name:zho_x_preferred":[
        "\u4e0a\u5b50\u7259\u5173"
    ],
    "wof:name":"Shangziyaguan",
    "wof:placetype":"locality"
},
  "geometry": {"coordinates":[100.261,26.0521],"type":"Point"}
}