{
  "type": "Feature",
  "properties": {
    "gn:admin1_code":"32.0",
    "gn:asciiname":"Tao'en",
    "gn:country_code":"CN",
    "gn:dem":3069,
    "gn:feature_class":"P",
    "gn:feature_code":"PPL",
    "gn:name":"Tao\u2019en",
    "gn:population":0,
    "gn:timezone":"Asia/Shanghai",
    "iso:country":"CN",
    "name:und_x_variant":[
        "Tao\u2019en"
    ],
    "name:zho_x_preferred":[
        "\u6843\u6069"
    ],
    "wof:name":"Tao'en",
    "wof:placetype":"locality"
},
  "geometry": {"coordinates":[103.233,33.6181],"type":"Point"}
}