{
  "type": "Feature",
  "properties": {
    "gn:admin1_code":"10",
    "gn:asciiname":"Yingbiyao",
    "gn:country_code":"CN",
    "gn:dem":1358,
    "gn:feature_class":"P",
    "gn:feature_code":"PPL",
    "gn:name":"Yingbiyao",
    "gn:population":0,
    "gn:timezone":"Asia/Shanghai",
    "iso:country":"CN",
    "name:zho_x_preferred":[
        "\u5f71\u58c1\u7a91"
    ],
    "wof:name":"Yingbiyao",
    "wof:placetype":"locality"
},
  "geometry": {"coordinates":[115.75633999999999,41.33195],"type":"Point"}
}