{
  "type": "Feature",
  "properties": {
    "gn:admin1_code":"12.0",
    "gn:asciiname":"Niupihu",
    "gn:country_code":"CN",
    "gn:dem":28,
    "gn:feature_class":"P",
    "gn:feature_code":"PPL",
    "gn:name":"Niupihu",
    "gn:population":0,
    "gn:timezone":"Asia/Shanghai",
    "iso:country":"CN",
    "name:zho_x_preferred":[
        "\u725b\u76ae\u6e56"
    ],
    "wof:name":"Niupihu",
    "wof:placetype":"locality"
},
  "geometry": {"coordinates":[112.64473,29.90172],"type":"Point"}
}