{
  "type": "Feature",
  "properties": {
    "gn:admin1_code":"2.0",
    "gn:asciiname":"Dunfu",
    "gn:country_code":"CN",
    "gn:dem":374,
    "gn:feature_class":"P",
    "gn:feature_code":"PPL",
    "gn:name":"Dunfu",
    "gn:population":0,
    "gn:timezone":"Asia/Shanghai",
    "iso:country":"CN",
    "name:zho_x_preferred":[
        "\u58a9\u798f"
    ],
    "wof:name":"Dunfu",
    "wof:placetype":"locality"
},
  "geometry": {"coordinates":[118.48238000000001,29.20276],"type":"Point"}
}