{
  "type": "Feature",
  "properties": {
    "gn:admin1_code":"3.0",
    "gn:asciiname":"Wunikeng",
    "gn:country_code":"CN",
    "gn:dem":86,
    "gn:feature_class":"P",
    "gn:feature_code":"PPL",
    "gn:name":"Wunikeng",
    "gn:population":0,
    "gn:timezone":"Asia/Shanghai",
    "iso:country":"CN",
    "name:und_x_variant":[
        "\u4e4c\u6ce5\u5751"
    ],
    "wof:name":"Wunikeng",
    "wof:placetype":"locality"
},
  "geometry": {"coordinates":[114.90004999999999,27.36172],"type":"Point"}
}