{
  "type": "Feature",
  "properties": {
    "gn:admin1_code":"2.0",
    "gn:asciiname":"Lanpeng",
    "gn:country_code":"CN",
    "gn:dem":379,
    "gn:feature_class":"P",
    "gn:feature_code":"PPL",
    "gn:name":"Lanpeng",
    "gn:population":0,
    "gn:timezone":"Asia/Shanghai",
    "iso:country":"CN",
    "name:zho_x_preferred":[
        "\u5170\u84ec"
    ],
    "wof:name":"Lanpeng",
    "wof:placetype":"locality"
},
  "geometry": {"coordinates":[119.06319999999999,28.59148],"type":"Point"}
}