{
  "type": "Feature",
  "properties": {
    "gn:admin1_code":"8.0",
    "gn:asciiname":"Xinqing",
    "gn:country_code":"CN",
    "gn:dem":679,
    "gn:feature_class":"P",
    "gn:feature_code":"PPL",
    "gn:name":"Xinqing",
    "gn:population":0,
    "gn:timezone":"Asia/Shanghai",
    "iso:country":"CN",
    "name:zho_x_preferred":[
        "\u65b0\u9752"
    ],
    "wof:name":"Xinqing",
    "wof:placetype":"locality"
},
  "geometry": {"coordinates":[130.52757,44.42583],"type":"Point"}
}