{
  "type": "Feature",
  "properties": {
    "gn:admin1_code":"4.0",
    "gn:asciiname":"Suijia",
    "gn:country_code":"CN",
    "gn:dem":6,
    "gn:feature_class":"P",
    "gn:feature_code":"PPL",
    "gn:name":"Suijia",
    "gn:population":0,
    "gn:timezone":"Asia/Shanghai",
    "iso:country":"CN",
    "name:zho_x_preferred":[
        "\u772d\u5bb6"
    ],
    "wof:name":"Suijia",
    "wof:placetype":"locality"
},
  "geometry": {"coordinates":[119.66287,31.93384],"type":"Point"}
}