{
  "type": "Feature",
  "properties": {
    "gn:admin1_code":"32.0",
    "gn:asciiname":"Xiaodongkou",
    "gn:country_code":"CN",
    "gn:dem":2303,
    "gn:feature_class":"P",
    "gn:feature_code":"PPL",
    "gn:name":"Xiaodongkou",
    "gn:population":0,
    "gn:timezone":"Asia/Shanghai",
    "iso:country":"CN",
    "name:zho_x_preferred":[
        "\u5c0f\u6d1e\u53e3"
    ],
    "wof:name":"Xiaodongkou",
    "wof:placetype":"locality"
},
  "geometry": {"coordinates":[103.20999999999999,31.0337],"type":"Point"}
}