{
  "type": "Feature",
  "properties": {
    "gn:admin1_code":"1.0",
    "gn:asciiname":"Sunjicun",
    "gn:country_code":"CN",
    "gn:dem":62,
    "gn:feature_class":"P",
    "gn:feature_code":"PPL",
    "gn:name":"Sunjicun",
    "gn:population":0,
    "gn:timezone":"Asia/Shanghai",
    "iso:country":"CN",
    "name:zho_x_preferred":[
        "\u5b59\u96c6\u6751"
    ],
    "wof:name":"Sunjicun",
    "wof:placetype":"locality"
},
  "geometry": {"coordinates":[117.41951,32.2445],"type":"Point"}
}