{
  "type": "Feature",
  "properties": {
    "gn:admin1_code":"20.0",
    "gn:asciiname":"Yanjiatongge",
    "gn:country_code":"CN",
    "gn:dem":1012,
    "gn:feature_class":"P",
    "gn:feature_code":"PPL",
    "gn:name":"Yanjiatongge",
    "gn:population":0,
    "gn:timezone":"Asia/Shanghai",
    "iso:country":"CN",
    "name:zho_x_preferred":[
        "\u960e\u5bb6\u901a\u683c"
    ],
    "wof:name":"Yanjiatongge",
    "wof:placetype":"locality"
},
  "geometry": {"coordinates":[100.44746000000001,41.46526],"type":"Point"}
}