{
  "type": "Feature",
  "properties": {
    "gn:admin1_code":"1.0",
    "gn:asciiname":"Taoyuanqiao",
    "gn:country_code":"CN",
    "gn:dem":33,
    "gn:feature_class":"P",
    "gn:feature_code":"PPL",
    "gn:name":"Taoyuanqiao",
    "gn:population":0,
    "gn:timezone":"Asia/Shanghai",
    "iso:country":"CN",
    "name:zho_x_preferred":[
        "\u6843\u6e90\u6865"
    ],
    "wof:name":"Taoyuanqiao",
    "wof:placetype":"locality"
},
  "geometry": {"coordinates":[116.96465000000001,30.32583],"type":"Point"}
}