{
  "type": "Feature",
  "properties": {
    "gn:admin1_code":"10.0",
    "gn:asciiname":"Wen'an",
    "gn:country_code":"CN",
    "gn:dem":12,
    "gn:feature_class":"P",
    "gn:feature_code":"PPL",
    "gn:name":"Wen\u2019an",
    "gn:population":0,
    "gn:timezone":"Asia/Shanghai",
    "iso:country":"CN",
    "name:und_x_variant":[
        "Ven\u2019an",
        "Wen-an-hsien",
        "Wen-an-ch\u2019eng-kuan",
        "Wen\u2019an"
    ],
    "wof:name":"Wen'an",
    "wof:placetype":"locality"
},
  "geometry": {"coordinates":[116.46666999999999,38.86667],"type":"Point"}
}