{
  "type": "Feature",
  "properties": {
    "gn:admin1_code":"18",
    "gn:asciiname":"Bosong",
    "gn:country_code":"CN",
    "gn:dem":840,
    "gn:feature_class":"P",
    "gn:feature_code":"PPL",
    "gn:name":"Bosong",
    "gn:population":0,
    "gn:timezone":"Asia/Shanghai",
    "iso:country":"CN",
    "name:zho_x_preferred":[
        "\u64ad\u9001"
    ],
    "wof:name":"Bosong",
    "wof:placetype":"locality"
},
  "geometry": {"coordinates":[106.806,25.7142],"type":"Point"}
}