{
  "type": "Feature",
  "properties": {
    "gn:admin1_code":"3.0",
    "gn:asciiname":"Dapingnao",
    "gn:country_code":"CN",
    "gn:dem":138,
    "gn:feature_class":"P",
    "gn:feature_code":"PPL",
    "gn:name":"Dapingnao",
    "gn:population":0,
    "gn:timezone":"Asia/Shanghai",
    "iso:country":"CN",
    "name:und_x_variant":[
        "\u5927\u576a\u8111"
    ],
    "wof:name":"Dapingnao",
    "wof:placetype":"locality"
},
  "geometry": {"coordinates":[115.34232,25.84245],"type":"Point"}
}