{
  "type": "Feature",
  "properties": {
    "gn:admin1_code":"16",
    "gn:asciiname":"Nizhuling",
    "gn:country_code":"CN",
    "gn:dem":247,
    "gn:feature_class":"P",
    "gn:feature_code":"PPL",
    "gn:name":"Nizhuling",
    "gn:population":0,
    "gn:timezone":"Asia/Shanghai",
    "iso:country":"CN",
    "name:zho_x_preferred":[
        "\u6ce5\u7af9\u5cad"
    ],
    "wof:name":"Nizhuling",
    "wof:placetype":"locality"
},
  "geometry": {"coordinates":[110.229,25.5748],"type":"Point"}
}