{
  "type": "Feature",
  "properties": {
    "gn:admin1_code":"9.0",
    "gn:asciiname":"Huoshaozhao",
    "gn:country_code":"CN",
    "gn:dem":62,
    "gn:feature_class":"P",
    "gn:feature_code":"PPL",
    "gn:name":"Huoshaozhao",
    "gn:population":0,
    "gn:timezone":"Asia/Shanghai",
    "iso:country":"CN",
    "name:zho_x_preferred":[
        "\u4f19\u90b5\u8d75"
    ],
    "wof:name":"Huoshaozhao",
    "wof:placetype":"locality"
},
  "geometry": {"coordinates":[114.04007,33.72729],"type":"Point"}
}