{
  "type": "Feature",
  "properties": {
    "gn:admin1_code":"8.0",
    "gn:asciiname":"Tainongcun",
    "gn:country_code":"CN",
    "gn:dem":190,
    "gn:feature_class":"P",
    "gn:feature_code":"PPL",
    "gn:name":"Tainongcun",
    "gn:population":0,
    "gn:timezone":"Asia/Shanghai",
    "iso:country":"CN",
    "name:zho_x_preferred":[
        "\u592a\u519c\u6751"
    ],
    "wof:name":"Tainongcun",
    "wof:placetype":"locality"
},
  "geometry": {"coordinates":[125.33277,47.80688],"type":"Point"}
}