{
  "type": "Feature",
  "properties": {
    "gn:admin1_code":"30",
    "gn:asciiname":"Xianfeng",
    "gn:country_code":"CN",
    "gn:dem":135,
    "gn:feature_class":"P",
    "gn:feature_code":"PPL",
    "gn:name":"Xianfeng",
    "gn:population":0,
    "gn:timezone":"Asia/Shanghai",
    "iso:country":"CN",
    "name:ceb_x_preferred":[
        "Xianfeng"
    ],
    "name:deu_x_preferred":[
        "Xianfeng"
    ],
    "name:fra_x_preferred":[
        "Xianfeng"
    ],
    "name:nor_x_preferred":[
        "Xianfeng"
    ],
    "name:zho_x_preferred":[
        "\u4ed9\u4e30"
    ],
    "wof:name":"Xianfeng",
    "wof:placetype":"locality"
},
  "geometry": {"coordinates":[116.50377,23.93559],"type":"Point"}
}