{
  "type": "Feature",
  "properties": {
    "gn:admin1_code":"16.0",
    "gn:asciiname":"Banni",
    "gn:country_code":"CN",
    "gn:dem":144,
    "gn:feature_class":"P",
    "gn:feature_code":"PPL",
    "gn:name":"Banni",
    "gn:population":0,
    "gn:timezone":"Asia/Shanghai",
    "iso:country":"CN",
    "name:deu_x_preferred":[
        "Banni"
    ],
    "name:zho_x_preferred":[
        "\u677f\u576d"
    ],
    "wof:name":"Banni",
    "wof:placetype":"locality"
},
  "geometry": {"coordinates":[106.702,22.1889],"type":"Point"}
}