{
  "type": "Feature",
  "properties": {
    "gn:admin1_code":"30.0",
    "gn:asciiname":"Niling",
    "gn:country_code":"CN",
    "gn:dem":131,
    "gn:feature_class":"P",
    "gn:feature_code":"PPL",
    "gn:name":"Niling",
    "gn:population":0,
    "gn:timezone":"Asia/Shanghai",
    "iso:country":"CN",
    "name:zho_x_preferred":[
        "\u576d\u5cad"
    ],
    "wof:name":"Niling",
    "wof:placetype":"locality"
},
  "geometry": {"coordinates":[114.43331999999999,23.70485],"type":"Point"}
}