{
  "type": "Feature",
  "properties": {
    "gn:admin1_code":"32.0",
    "gn:asciiname":"Dengjia Danian",
    "gn:country_code":"CN",
    "gn:dem":451,
    "gn:feature_class":"P",
    "gn:feature_code":"PPL",
    "gn:name":"Dengjia Danian",
    "gn:population":0,
    "gn:timezone":"Asia/Shanghai",
    "iso:country":"CN",
    "name:zho_x_preferred":[
        "\u9093\u5bb6\u5927\u57dd"
    ],
    "wof:name":"Dengjia Danian",
    "wof:placetype":"locality"
},
  "geometry": {"coordinates":[104.34699999999999,30.4538],"type":"Point"}
}