{
  "type": "Feature",
  "properties": {
    "gn:admin1_code":"7.0",
    "gn:asciiname":"Wushangce",
    "gn:country_code":"CN",
    "gn:dem":631,
    "gn:feature_class":"P",
    "gn:feature_code":"PPL",
    "gn:name":"Wushangce",
    "gn:population":0,
    "gn:timezone":"Asia/Shanghai",
    "iso:country":"CN",
    "name:zho_x_preferred":[
        "\u5434\u4e0a\u518a"
    ],
    "wof:name":"Wushangce",
    "wof:placetype":"locality"
},
  "geometry": {"coordinates":[117.53180999999999,27.49614],"type":"Point"}
}