{
  "type": "Feature",
  "properties": {
    "gn:admin1_code":"15.0",
    "gn:asciiname":"Badui Yuanzi",
    "gn:country_code":"CN",
    "gn:dem":1632,
    "gn:feature_class":"P",
    "gn:feature_code":"PPLF",
    "gn:name":"Badui Yuanzi",
    "gn:population":0,
    "gn:timezone":"Asia/Shanghai",
    "iso:country":"CN",
    "name:zho_x_preferred":[
        "\u516b\u961f\u56ed\u5b50"
    ],
    "wof:name":"Badui Yuanzi",
    "wof:placetype":"locality"
},
  "geometry": {"coordinates":[104.50700000000001,37.1239],"type":"Point"}
}