{
  "type": "Feature",
  "properties": {
    "gn:admin1_code":"10.0",
    "gn:asciiname":"Beigang Matou",
    "gn:country_code":"CN",
    "gn:dem":-1,
    "gn:feature_class":"P",
    "gn:feature_code":"PPL",
    "gn:name":"Beigang Matou",
    "gn:population":0,
    "gn:timezone":"Asia/Shanghai",
    "iso:country":"CN",
    "name:zho_x_preferred":[
        "\u5317\u6e2f\u7801\u5934"
    ],
    "wof:name":"Beigang Matou",
    "wof:placetype":"locality"
},
  "geometry": {"coordinates":[118.85089000000001,39.1814],"type":"Point"}
}