{
  "type": "Feature",
  "properties": {
    "gn:admin1_code":"26.0",
    "gn:asciiname":"Yuyuanta",
    "gn:country_code":"CN",
    "gn:dem":1192,
    "gn:feature_class":"P",
    "gn:feature_code":"PPL",
    "gn:name":"Yuyuanta",
    "gn:population":0,
    "gn:timezone":"Asia/Shanghai",
    "iso:country":"CN",
    "name:zho_x_preferred":[
        "\u79b9\u586c\u5854"
    ],
    "wof:name":"Yuyuanta",
    "wof:placetype":"locality"
},
  "geometry": {"coordinates":[109.19117,35.32261],"type":"Point"}
}