{
  "type": "Feature",
  "properties": {
    "gn:admin1_code":"18",
    "gn:asciiname":"Botun",
    "gn:country_code":"CN",
    "gn:dem":1684,
    "gn:feature_class":"P",
    "gn:feature_code":"PPL",
    "gn:name":"Botun",
    "gn:population":0,
    "gn:timezone":"Asia/Shanghai",
    "iso:country":"CN",
    "name:bul_x_preferred":[
        "\u0411\u043e\u0442\u0443\u043d"
    ],
    "name:fra_x_preferred":[
        "Botoun"
    ],
    "name:hun_x_preferred":[
        "Botun"
    ],
    "name:mkd_x_preferred":[
        "\u0411\u043e\u0442\u0443\u043d"
    ],
    "name:sqi_x_preferred":[
        "Botuni"
    ],
    "name:srp_x_preferred":[
        "\u0411\u043e\u0442\u0443\u043d"
    ],
    "name:zho_x_preferred":[
        "\u6ce2\u6c3d"
    ],
    "wof:name":"Botun",
    "wof:placetype":"locality"
},
  "geometry": {"coordinates":[105.012,25.6491],"type":"Point"}
}