{
  "type": "Feature",
  "properties": {
    "gn:admin1_code":"16.0",
    "gn:asciiname":"Futaichong",
    "gn:country_code":"CN",
    "gn:dem":544,
    "gn:feature_class":"P",
    "gn:feature_code":"PPL",
    "gn:name":"Futaichong",
    "gn:population":0,
    "gn:timezone":"Asia/Shanghai",
    "iso:country":"CN",
    "name:zho_x_preferred":[
        "\u798f\u592a\u51b2"
    ],
    "wof:name":"Futaichong",
    "wof:placetype":"locality"
},
  "geometry": {"coordinates":[110.22499999999999,22.9025],"type":"Point"}
}