{
  "type": "Feature",
  "properties": {
    "gn:admin1_code":"12.0",
    "gn:asciiname":"Lujiazui",
    "gn:country_code":"CN",
    "gn:dem":61,
    "gn:feature_class":"P",
    "gn:feature_code":"PPL",
    "gn:name":"L\u00fcjiazui",
    "gn:population":0,
    "gn:timezone":"Asia/Shanghai",
    "iso:country":"CN",
    "name:und_x_variant":[
        "L\u00fcjiazui"
    ],
    "name:zho_x_preferred":[
        "\u5415\u5bb6\u5480"
    ],
    "wof:name":"Lujiazui",
    "wof:placetype":"locality"
},
  "geometry": {"coordinates":[114.44194,31.22584],"type":"Point"}
}