{
  "type": "Feature",
  "properties": {
    "gn:admin1_code":"32.0",
    "gn:asciiname":"Maiqiong",
    "gn:country_code":"CN",
    "gn:dem":3574,
    "gn:feature_class":"P",
    "gn:feature_code":"PPL",
    "gn:name":"Maiqiong",
    "gn:population":0,
    "gn:timezone":"Asia/Shanghai",
    "iso:country":"CN",
    "name:zho_x_preferred":[
        "\u9ea6\u7a77"
    ],
    "wof:name":"Maiqiong",
    "wof:placetype":"locality"
},
  "geometry": {"coordinates":[101.643,33.005],"type":"Point"}
}