{
  "type": "Feature",
  "properties": {
    "gn:admin1_code":"7",
    "gn:asciiname":"Zhuziye",
    "gn:country_code":"CN",
    "gn:dem":172,
    "gn:feature_class":"P",
    "gn:feature_code":"PPL",
    "gn:name":"Zhuziye",
    "gn:population":0,
    "gn:timezone":"Asia/Shanghai",
    "iso:country":"CN",
    "name:zho_x_preferred":[
        "\u7af9\u5b50\u53f6"
    ],
    "wof:name":"Zhuziye",
    "wof:placetype":"locality"
},
  "geometry": {"coordinates":[118.11152,25.00144],"type":"Point"}
}