{
  "type": "Feature",
  "properties": {
    "gn:admin1_code":"04",
    "gn:asciiname":"Baimi",
    "gn:country_code":"CN",
    "gn:dem":6,
    "gn:feature_class":"P",
    "gn:feature_code":"PPLA4",
    "gn:name":"Baimi",
    "gn:population":0,
    "gn:timezone":"Asia/Shanghai",
    "iso:country":"CN",
    "name:und_x_variant":[
        "Ta-pai-mi-chen",
        "Pai-mi",
        "Ta-pai-mi",
        "Pai-mi-chen",
        "Baimi",
        "\u767d\u7c73",
        "Baimi Zhen",
        "\u767d\u7c73\u9547"
    ],
    "wof:name":"Baimi",
    "wof:placetype":"locality"
},
  "geometry": {"coordinates":[120.25184,32.50660999999999],"type":"Point"}
}