{
  "type": "Feature",
  "properties": {
    "gn:admin1_code":"18.0",
    "gn:asciiname":"Xiarongdian",
    "gn:country_code":"CN",
    "gn:dem":982,
    "gn:feature_class":"P",
    "gn:feature_code":"PPL",
    "gn:name":"Xiarongdian",
    "gn:population":0,
    "gn:timezone":"Asia/Shanghai",
    "iso:country":"CN",
    "name:zho_x_preferred":[
        "\u4e0b\u5197\u70b9"
    ],
    "wof:name":"Xiarongdian",
    "wof:placetype":"locality"
},
  "geometry": {"coordinates":[107.43899999999999,25.6683],"type":"Point"}
}