{
  "type": "Feature",
  "properties": {
    "gn:admin1_code":"30.0",
    "gn:asciiname":"Yingfengcun",
    "gn:country_code":"CN",
    "gn:dem":8,
    "gn:feature_class":"P",
    "gn:feature_code":"PPL",
    "gn:name":"Yingfengcun",
    "gn:population":0,
    "gn:timezone":"Asia/Shanghai",
    "iso:country":"CN",
    "name:zho_x_preferred":[
        "\u82f1\u51e4\u6751"
    ],
    "wof:name":"Yingfengcun",
    "wof:placetype":"locality"
},
  "geometry": {"coordinates":[116.54815000000001,23.59428],"type":"Point"}
}