{
  "type": "Feature",
  "properties": {
    "gn:admin1_code":"14.0",
    "gn:asciiname":"Saigoi",
    "gn:country_code":"CN",
    "gn:dem":4125,
    "gn:feature_class":"P",
    "gn:feature_code":"PPL",
    "gn:name":"Saigoi",
    "gn:population":0,
    "gn:timezone":"Asia/Urumqi",
    "iso:country":"CN",
    "name:bod_x_preferred":[
        "Saigoi"
    ],
    "name:zho_x_preferred":[
        "Sagui"
    ],
    "name:zho_x_variant":[
        "\u8428\u5f52"
    ],
    "wof:name":"Saigoi",
    "wof:placetype":"locality"
},
  "geometry": {"coordinates":[88.50399999999998,29.104],"type":"Point"}
}