{
  "type": "Feature",
  "properties": {
    "gn:admin1_code":"04",
    "gn:asciiname":"Shiji",
    "gn:cc2":"CN",
    "gn:country_code":"CN",
    "gn:dem":14,
    "gn:feature_class":"P",
    "gn:feature_code":"PPL",
    "gn:name":"Shiji",
    "gn:population":0,
    "gn:timezone":"Asia/Shanghai",
    "iso:country":"CN",
    "name:und_x_variant":[
        "Shih-chi",
        "Shiji"
    ],
    "wof:name":"Shiji",
    "wof:placetype":"locality"
},
  "geometry": {"coordinates":[118.24666999999999,33.36722],"type":"Point"}
}