{
  "type": "Feature",
  "properties": {
    "gn:admin1_code":"29.0",
    "gn:asciiname":"Houzidi",
    "gn:country_code":"CN",
    "gn:dem":2039,
    "gn:feature_class":"P",
    "gn:feature_code":"PPL",
    "gn:name":"Houzidi",
    "gn:population":0,
    "gn:timezone":"Asia/Shanghai",
    "iso:country":"CN",
    "name:zho_x_preferred":[
        "\u7334\u5b50\u5730"
    ],
    "wof:name":"Houzidi",
    "wof:placetype":"locality"
},
  "geometry": {"coordinates":[103.89,26.1217],"type":"Point"}
}