{
  "type": "Feature",
  "properties": {
    "gn:admin1_code":"31",
    "gn:asciiname":"Xianchang",
    "gn:country_code":"CN",
    "gn:dem":17,
    "gn:feature_class":"P",
    "gn:feature_code":"PPL",
    "gn:name":"Xianchang",
    "gn:population":0,
    "gn:timezone":"Asia/Shanghai",
    "iso:country":"CN",
    "name:und_x_variant":[
        "\u4ed9\u660c",
        "Yuyin"
    ],
    "wof:name":"Xianchang",
    "wof:placetype":"locality"
},
  "geometry": {"coordinates":[110.66139,19.46444],"type":"Point"}
}