{
  "type": "Feature",
  "properties": {
    "gn:admin1_code":"33.0",
    "gn:asciiname":"Hucheng",
    "gn:country_code":"CN",
    "gn:dem":517,
    "gn:feature_class":"P",
    "gn:feature_code":"PPLA4",
    "gn:name":"Hucheng",
    "gn:population":0,
    "gn:timezone":"Asia/Shanghai",
    "iso:country":"CN",
    "name:und_x_variant":[
        "Hucheng Zhen"
    ],
    "name:zho_x_preferred":[
        "\u864e\u57ce"
    ],
    "name:zho_x_variant":[
        "\u864e\u57ce\u9547"
    ],
    "wof:name":"Hucheng",
    "wof:placetype":"locality"
},
  "geometry": {"coordinates":[107.54179999999999,30.81479],"type":"Point"}
}