{
  "type": "Feature",
  "properties": {
    "gn:admin1_code":"15.0",
    "gn:asciiname":"Zengjiashan",
    "gn:country_code":"CN",
    "gn:dem":2207,
    "gn:feature_class":"P",
    "gn:feature_code":"PPL",
    "gn:name":"Zengjiashan",
    "gn:population":0,
    "gn:timezone":"Asia/Shanghai",
    "iso:country":"CN",
    "name:und_x_variant":[
        "\u66fe\u5bb6\u5c71"
    ],
    "wof:name":"Zengjiashan",
    "wof:placetype":"locality"
},
  "geometry": {"coordinates":[104.39209,34.11288],"type":"Point"}
}