{
  "type": "Feature",
  "properties": {
    "gn:admin1_code":"11.0",
    "gn:asciiname":"Zhaigongtang",
    "gn:country_code":"CN",
    "gn:dem":190,
    "gn:feature_class":"P",
    "gn:feature_code":"PPL",
    "gn:name":"Zhaigongtang",
    "gn:population":0,
    "gn:timezone":"Asia/Shanghai",
    "iso:country":"CN",
    "name:zho_x_preferred":[
        "\u658b\u516c\u5858"
    ],
    "wof:name":"Zhaigongtang",
    "wof:placetype":"locality"
},
  "geometry": {"coordinates":[111.82083,26.90871],"type":"Point"}
}