{
  "type": "Feature",
  "properties": {
    "gn:admin1_code":"19.0",
    "gn:asciiname":"Sumataicun",
    "gn:country_code":"CN",
    "gn:dem":36,
    "gn:feature_class":"P",
    "gn:feature_code":"PPL",
    "gn:name":"Sumataicun",
    "gn:population":0,
    "gn:timezone":"Asia/Shanghai",
    "iso:country":"CN",
    "name:zho_x_preferred":[
        "\u82cf\u9a6c\u53f0\u6751"
    ],
    "wof:name":"Sumataicun",
    "wof:placetype":"locality"
},
  "geometry": {"coordinates":[122.82277000000001,41.00917000000001],"type":"Point"}
}