{
  "type": "Feature",
  "properties": {
    "gn:admin1_code":"32.0",
    "gn:asciiname":"Jinzhuwan",
    "gn:country_code":"CN",
    "gn:dem":745,
    "gn:feature_class":"P",
    "gn:feature_code":"PPL",
    "gn:name":"Jinzhuwan",
    "gn:population":0,
    "gn:timezone":"Asia/Shanghai",
    "iso:country":"CN",
    "name:zho_x_preferred":[
        "\u91d1\u7af9\u6e7e"
    ],
    "wof:name":"Jinzhuwan",
    "wof:placetype":"locality"
},
  "geometry": {"coordinates":[105.81100000000001,28.6402],"type":"Point"}
}