{
  "type": "Feature",
  "properties": {
    "gn:admin1_code":"24.0",
    "gn:asciiname":"Baliushu",
    "gn:country_code":"CN",
    "gn:dem":1208,
    "gn:feature_class":"P",
    "gn:feature_code":"PPL",
    "gn:name":"Baliushu",
    "gn:population":0,
    "gn:timezone":"Asia/Shanghai",
    "iso:country":"CN",
    "name:zho_x_preferred":[
        "\u516b\u67f3\u6811"
    ],
    "wof:name":"Baliushu",
    "wof:placetype":"locality"
},
  "geometry": {"coordinates":[111.71339999999999,39.49256],"type":"Point"}
}