{
  "type": "Feature",
  "properties": {
    "gn:admin1_code":"15.0",
    "gn:asciiname":"Shanglijia",
    "gn:country_code":"CN",
    "gn:dem":1335,
    "gn:feature_class":"P",
    "gn:feature_code":"PPL",
    "gn:name":"Shanglijia",
    "gn:population":0,
    "gn:timezone":"Asia/Shanghai",
    "iso:country":"CN",
    "name:zho_x_preferred":[
        "\u4e0a\u674e\u5bb6"
    ],
    "wof:name":"Shanglijia",
    "wof:placetype":"locality"
},
  "geometry": {"coordinates":[103.503,38.7711],"type":"Point"}
}