{
  "type": "Feature",
  "properties": {
    "gn:admin1_code":"8.0",
    "gn:asciiname":"Xifucun",
    "gn:country_code":"CN",
    "gn:dem":156,
    "gn:feature_class":"P",
    "gn:feature_code":"PPL",
    "gn:name":"Xifucun",
    "gn:population":0,
    "gn:timezone":"Asia/Shanghai",
    "iso:country":"CN",
    "name:zho_x_preferred":[
        "\u5e0c\u5bcc\u6751"
    ],
    "wof:name":"Xifucun",
    "wof:placetype":"locality"
},
  "geometry": {"coordinates":[126.08937,45.32055],"type":"Point"}
}