{
  "type": "Feature",
  "properties": {
    "gn:admin1_code":"29.0",
    "gn:asciiname":"Chuxiwan",
    "gn:country_code":"CN",
    "gn:dem":1234,
    "gn:feature_class":"P",
    "gn:feature_code":"PPL",
    "gn:name":"Chuxiwan",
    "gn:population":0,
    "gn:timezone":"Asia/Shanghai",
    "iso:country":"CN",
    "name:zho_x_preferred":[
        "\u96cf\u6eaa\u6e7e"
    ],
    "wof:name":"Chuxiwan",
    "wof:placetype":"locality"
},
  "geometry": {"coordinates":[104.13200000000001,28.1113],"type":"Point"}
}