{
  "type": "Feature",
  "properties": {
    "gn:country":"CN",
    "gn:fcode":"PPL",
    "gn:population":3120,
    "iso:country":"CN",
    "name:eng_x_historical":[
        "Feloon"
    ],
    "name:eng_x_preferred":[
        "Feloon"
    ],
    "name:eng_x_variant":[
        "Feiluan"
    ],
    "name:gan_x_preferred":[
        "\u98de\u9e3e\u9547"
    ],
    "name:jpn_x_preferred":[
        "\u98db\u9e1e\u93ae"
    ],
    "name:wuu_x_preferred":[
        "\u98de\u9e3e\u9547"
    ],
    "name:zho_x_preferred":[
        "\u98de\u9e3e\u9547"
    ],
    "qs:name":"Feiluan",
    "qs:photos_9r":0,
    "qs:photos_sr":0,
    "qs:pop_sr":"4",
    "wd:wordcount":268,
    "wof:name":"Feiluan",
    "wof:placetype":"locality",
    "wof:population":3120
},
  "geometry": {"coordinates":[119.5975,26.5625],"type":"Point"}
}