{
  "type": "Feature",
  "properties": {
    "gn:admin1_code":"16.0",
    "gn:asciiname":"Boluotang",
    "gn:country_code":"CN",
    "gn:dem":48,
    "gn:feature_class":"P",
    "gn:feature_code":"PPL",
    "gn:name":"Boluotang",
    "gn:population":0,
    "gn:timezone":"Asia/Shanghai",
    "iso:country":"CN",
    "name:zho_x_preferred":[
        "\u83e0\u841d\u5858"
    ],
    "wof:name":"Boluotang",
    "wof:placetype":"locality"
},
  "geometry": {"coordinates":[109.139,22.3403],"type":"Point"}
}