{
  "type": "Feature",
  "properties": {
    "gn:admin1_code":"15.0",
    "gn:asciiname":"Maquangou",
    "gn:country_code":"CN",
    "gn:dem":1757,
    "gn:feature_class":"P",
    "gn:feature_code":"PPL",
    "gn:name":"Maquangou",
    "gn:population":0,
    "gn:timezone":"Asia/Shanghai",
    "iso:country":"CN",
    "name:und_x_variant":[
        "\u9a6c\u6cc9\u6c9f"
    ],
    "wof:name":"Maquangou",
    "wof:placetype":"locality"
},
  "geometry": {"coordinates":[106.82925,36.64255],"type":"Point"}
}