{
  "type": "Feature",
  "properties": {
    "gn:admin1_code":"26.0",
    "gn:asciiname":"Ma'anshan",
    "gn:country_code":"CN",
    "gn:dem":1407,
    "gn:feature_class":"P",
    "gn:feature_code":"PPL",
    "gn:name":"Ma\u2019anshan",
    "gn:population":0,
    "gn:timezone":"Asia/Shanghai",
    "iso:country":"CN",
    "name:und_x_variant":[
        "Ma\u2019anshan",
        "\u9a6c\u5b89\u5c71"
    ],
    "wof:name":"Ma'anshan",
    "wof:placetype":"locality"
},
  "geometry": {"coordinates":[107.23963000000001,34.71054],"type":"Point"}
}