{
  "type": "Feature",
  "properties": {
    "gn:admin1_code":"4.0",
    "gn:asciiname":"Erduo Sizu",
    "gn:country_code":"CN",
    "gn:dem":-1,
    "gn:feature_class":"P",
    "gn:feature_code":"PPLF",
    "gn:name":"Erduo Sizu",
    "gn:population":0,
    "gn:timezone":"Asia/Shanghai",
    "iso:country":"CN",
    "name:zho_x_preferred":[
        "Erduo Sizu"
    ],
    "name:zho_x_variant":[
        "\u4e8c\u579b\u56db\u7ec4"
    ],
    "wof:name":"Erduo Sizu",
    "wof:placetype":"locality"
},
  "geometry": {"coordinates":[120.2512,34.04838],"type":"Point"}
}