{
  "type": "Feature",
  "properties": {
    "gn:admin1_code":"12.0",
    "gn:asciiname":"Erfenwan",
    "gn:country_code":"CN",
    "gn:dem":20,
    "gn:feature_class":"P",
    "gn:feature_code":"PPL",
    "gn:name":"Erfenwan",
    "gn:population":0,
    "gn:timezone":"Asia/Shanghai",
    "iso:country":"CN",
    "name:und_x_variant":[
        "\u4e8c\u4efd\u5846"
    ],
    "wof:name":"Erfenwan",
    "wof:placetype":"locality"
},
  "geometry": {"coordinates":[114.80286,30.77091],"type":"Point"}
}