{
  "type": "Feature",
  "properties": {
    "gn:admin1_code":"12",
    "gn:asciiname":"Qingshuiwan",
    "gn:country_code":"CN",
    "gn:dem":860,
    "gn:feature_class":"P",
    "gn:feature_code":"PPL",
    "gn:name":"Qingshuiwan",
    "gn:population":0,
    "gn:timezone":"Asia/Shanghai",
    "iso:country":"CN",
    "name:und_x_variant":[
        "Ch\u2019ing-shui-wan",
        "Qingshuiwan"
    ],
    "name:zho_x_preferred":[
        "\u6e05\u6c34\u6e7e"
    ],
    "wof:name":"Qingshuiwan",
    "wof:placetype":"locality"
},
  "geometry": {"coordinates":[111.0514,30.10718],"type":"Point"}
}