{
  "type": "Feature",
  "properties": {
    "gn:admin1_code":"2.0",
    "gn:asciiname":"Jiandoumen",
    "gn:country_code":"CN",
    "gn:dem":67,
    "gn:feature_class":"P",
    "gn:feature_code":"PPL",
    "gn:name":"Jiandoumen",
    "gn:population":0,
    "gn:timezone":"Asia/Shanghai",
    "iso:country":"CN",
    "name:zho_x_preferred":[
        "\u6da7\u9661\u95e8"
    ],
    "wof:name":"Jiandoumen",
    "wof:placetype":"locality"
},
  "geometry": {"coordinates":[120.33754,27.65526],"type":"Point"}
}