{
  "type": "Feature",
  "properties": {
    "gn:admin1_code":"12.0",
    "gn:asciiname":"Dayouyuan",
    "gn:country_code":"CN",
    "gn:dem":28,
    "gn:feature_class":"P",
    "gn:feature_code":"PPL",
    "gn:name":"Dayouyuan",
    "gn:population":0,
    "gn:timezone":"Asia/Shanghai",
    "iso:country":"CN",
    "name:zho_x_preferred":[
        "\u5927\u6709\u57b8"
    ],
    "wof:name":"Dayouyuan",
    "wof:placetype":"locality"
},
  "geometry": {"coordinates":[113.62009999999999,30.31229],"type":"Point"}
}