{
  "type": "Feature",
  "properties": {
    "gn:admin1_code":"1.0",
    "gn:asciiname":"Pailouwu",
    "gn:country_code":"CN",
    "gn:dem":60,
    "gn:feature_class":"P",
    "gn:feature_code":"PPL",
    "gn:name":"Pailouwu",
    "gn:population":0,
    "gn:timezone":"Asia/Shanghai",
    "iso:country":"CN",
    "name:zho_x_preferred":[
        "\u724c\u697c\u5c4b"
    ],
    "wof:name":"Pailouwu",
    "wof:placetype":"locality"
},
  "geometry": {"coordinates":[116.74075999999999,29.69682],"type":"Point"}
}