{
  "type": "Feature",
  "properties": {
    "gn:admin1_code":"5.0",
    "gn:asciiname":"Huiziying",
    "gn:country_code":"CN",
    "gn:dem":217,
    "gn:feature_class":"P",
    "gn:feature_code":"PPL",
    "gn:name":"Huiziying",
    "gn:population":0,
    "gn:timezone":"Asia/Shanghai",
    "iso:country":"CN",
    "name:zho_x_preferred":[
        "\u56de\u5b50\u8425"
    ],
    "wof:name":"Huiziying",
    "wof:placetype":"locality"
},
  "geometry": {"coordinates":[126.81632999999999,44.49093],"type":"Point"}
}