{
  "type": "Feature",
  "properties": {
    "gn:admin1_code":"10.0",
    "gn:asciiname":"Bafenchang",
    "gn:country_code":"CN",
    "gn:dem":6,
    "gn:feature_class":"P",
    "gn:feature_code":"PPL",
    "gn:name":"Bafenchang",
    "gn:population":0,
    "gn:timezone":"Asia/Shanghai",
    "iso:country":"CN",
    "name:zho_x_preferred":[
        "\u516b\u5206\u573a"
    ],
    "wof:name":"Bafenchang",
    "wof:placetype":"locality"
},
  "geometry": {"coordinates":[118.28355999999999,39.38848],"type":"Point"}
}