{
  "type": "Feature",
  "properties": {
    "gn:admin1_code":"21.0",
    "gn:asciiname":"Changfeng",
    "gn:country_code":"CN",
    "gn:dem":1114,
    "gn:feature_class":"P",
    "gn:feature_code":"PPL",
    "gn:name":"Changfeng",
    "gn:population":0,
    "gn:timezone":"Asia/Shanghai",
    "iso:country":"CN",
    "name:zho_x_preferred":[
        "\u957f\u4e30"
    ],
    "wof:name":"Changfeng",
    "wof:placetype":"locality"
},
  "geometry": {"coordinates":[106.33799999999999,38.3963],"type":"Point"}
}