{
  "type": "Feature",
  "properties": {
    "gn:admin1_code":"10.0",
    "gn:asciiname":"Fushankou",
    "gn:country_code":"CN",
    "gn:dem":356,
    "gn:feature_class":"P",
    "gn:feature_code":"PPL",
    "gn:name":"Fushankou",
    "gn:population":0,
    "gn:timezone":"Asia/Shanghai",
    "iso:country":"CN",
    "name:zho_x_preferred":[
        "\u798f\u5c71\u53e3"
    ],
    "wof:name":"Fushankou",
    "wof:placetype":"locality"
},
  "geometry": {"coordinates":[115.32971999999999,39.67858],"type":"Point"}
}