{
  "type": "Feature",
  "properties": {
    "gn:admin1_code":"24",
    "gn:asciiname":"Lanyi",
    "gn:country_code":"CN",
    "gn:dem":1460,
    "gn:feature_class":"P",
    "gn:feature_code":"PPLA3",
    "gn:name":"Lanyi",
    "gn:population":0,
    "gn:timezone":"Asia/Shanghai",
    "iso:country":"CN",
    "name:und_x_variant":[
        "Kolanchow",
        "Kelan",
        "Lanyi",
        "Kelan Xian",
        "Lanyi Zhen",
        "\u5ca2\u5c9a\u53bf",
        "\u5c9a\u6f2a\u9547"
    ],
    "name:zho_x_preferred":[
        "K\u2019o-lan"
    ],
    "name:zho_x_variant":[
        "K\u2019o-lan-hsien",
        "\u5c9a\u6f2a",
        "K\u2019o-lan-hsien-ch\u2019eng"
    ],
    "wof:name":"Lanyi",
    "wof:placetype":"locality"
},
  "geometry": {"coordinates":[111.59783,38.71983],"type":"Point"}
}