{
  "type": "Feature",
  "properties": {
    "gn:admin1_code":"24.0",
    "gn:asciiname":"Yanjiazhuang",
    "gn:country_code":"CN",
    "gn:dem":1184,
    "gn:feature_class":"P",
    "gn:feature_code":"PPL",
    "gn:name":"Yanjiazhuang",
    "gn:population":0,
    "gn:timezone":"Asia/Shanghai",
    "iso:country":"CN",
    "name:zho_x_preferred":[
        "\u960e\u5bb6\u5e84"
    ],
    "wof:name":"Yanjiazhuang",
    "wof:placetype":"locality"
},
  "geometry": {"coordinates":[113.29474999999999,37.8058],"type":"Point"}
}