{
  "type": "Feature",
  "properties": {
    "gn:admin1_code":"25",
    "gn:asciiname":"Hujiashihe",
    "gn:country_code":"CN",
    "gn:dem":97,
    "gn:feature_class":"P",
    "gn:feature_code":"PPL",
    "gn:name":"Hujiashihe",
    "gn:population":0,
    "gn:timezone":"Asia/Shanghai",
    "iso:country":"CN",
    "name:zho_x_preferred":[
        "\u80e1\u5bb6\u77f3\u6cb3"
    ],
    "wof:name":"Hujiashihe",
    "wof:placetype":"locality"
},
  "geometry": {"coordinates":[118.777,35.0202],"type":"Point"}
}