{
  "type": "Feature",
  "properties": {
    "gn:admin1_code":"03",
    "gn:asciiname":"Tieshan",
    "gn:country_code":"CN",
    "gn:dem":306,
    "gn:feature_class":"P",
    "gn:feature_code":"PPL",
    "gn:name":"Tieshan",
    "gn:population":0,
    "gn:timezone":"Asia/Shanghai",
    "iso:country":"CN",
    "name:und_x_variant":[
        "\u94c1\u5c71"
    ],
    "wof:name":"Tieshan",
    "wof:placetype":"locality"
},
  "geometry": {"coordinates":[115.42874999999999,25.23697],"type":"Point"}
}