{
  "type": "Feature",
  "properties": {
    "gn:admin1_code":"07",
    "gn:asciiname":"Xiamenyang",
    "gn:country_code":"CN",
    "gn:dem":371,
    "gn:feature_class":"P",
    "gn:feature_code":"PPL",
    "gn:name":"Xiamenyang",
    "gn:population":0,
    "gn:timezone":"Asia/Shanghai",
    "iso:country":"CN",
    "name:zho_x_preferred":[
        "\u4e0b\u95e8\u6d0b"
    ],
    "wof:name":"Xiamenyang",
    "wof:placetype":"locality"
},
  "geometry": {"coordinates":[117.89082999999999,25.70056],"type":"Point"}
}