{
  "type": "Feature",
  "properties": {
    "gn:admin1_code":"32.0",
    "gn:asciiname":"Yujiaguan",
    "gn:country_code":"CN",
    "gn:dem":543,
    "gn:feature_class":"P",
    "gn:feature_code":"PPL",
    "gn:name":"Yujiaguan",
    "gn:population":0,
    "gn:timezone":"Asia/Shanghai",
    "iso:country":"CN",
    "name:zho_x_preferred":[
        "\u55bb\u5bb6\u89c2"
    ],
    "wof:name":"Yujiaguan",
    "wof:placetype":"locality"
},
  "geometry": {"coordinates":[104.78400000000001,31.7878],"type":"Point"}
}