{
  "type": "Feature",
  "properties": {
    "gn:admin1_code":"11",
    "gn:asciiname":"Leidashi",
    "gn:cc2":"CN",
    "gn:country_code":"CN",
    "gn:dem":76,
    "gn:feature_class":"P",
    "gn:feature_code":"PPL",
    "gn:name":"Leidashi",
    "gn:population":0,
    "gn:timezone":"Asia/Shanghai",
    "iso:country":"CN",
    "name:und_x_variant":[
        "Lei-ta-shih",
        "Leidashi"
    ],
    "wof:name":"Leidashi",
    "wof:placetype":"locality"
},
  "geometry": {"coordinates":[113.05583,27.67944],"type":"Point"}
}