{
  "type": "Feature",
  "properties": {
    "gn:admin1_code":"29",
    "gn:asciiname":"Yutade",
    "gn:country_code":"CN",
    "gn:dem":1540,
    "gn:feature_class":"P",
    "gn:feature_code":"PPL",
    "gn:name":"Yutade",
    "gn:population":0,
    "gn:timezone":"Asia/Shanghai",
    "iso:country":"CN",
    "name:zho_x_preferred":[
        "\u9c7c\u4ed6\u5f97"
    ],
    "wof:name":"Yutade",
    "wof:placetype":"locality"
},
  "geometry": {"coordinates":[103.146,24.2741],"type":"Point"}
}