{
  "type": "Feature",
  "properties": {
    "gn:admin1_code":"5.0",
    "gn:asciiname":"Fengshu",
    "gn:country_code":"CN",
    "gn:dem":471,
    "gn:feature_class":"P",
    "gn:feature_code":"PPL",
    "gn:name":"Fengshu",
    "gn:population":0,
    "gn:timezone":"Asia/Shanghai",
    "iso:country":"CN",
    "name:und_x_variant":[
        "\u51e4\u6811"
    ],
    "wof:name":"Fengshu",
    "wof:placetype":"locality"
},
  "geometry": {"coordinates":[128.75689,43.16512],"type":"Point"}
}