{
  "type": "Feature",
  "properties": {
    "gn:admin1_code":"15.0",
    "gn:asciiname":"Nanyaoxia",
    "gn:country_code":"CN",
    "gn:dem":1732,
    "gn:feature_class":"P",
    "gn:feature_code":"PPL",
    "gn:name":"Nanyaoxia",
    "gn:population":0,
    "gn:timezone":"Asia/Shanghai",
    "iso:country":"CN",
    "name:zho_x_preferred":[
        "\u5357\u7a91\u5ce1"
    ],
    "wof:name":"Nanyaoxia",
    "wof:placetype":"locality"
},
  "geometry": {"coordinates":[106.56699999999999,35.5051],"type":"Point"}
}