{
  "type": "Feature",
  "properties": {
    "gn:admin1_code":"32.0",
    "gn:asciiname":"Yanping",
    "gn:country_code":"CN",
    "gn:dem":950,
    "gn:feature_class":"P",
    "gn:feature_code":"PPL",
    "gn:name":"Yanping",
    "gn:population":0,
    "gn:timezone":"Asia/Shanghai",
    "iso:country":"CN",
    "name:zho_x_preferred":[
        "\u5830\u576a"
    ],
    "wof:name":"Yanping",
    "wof:placetype":"locality"
},
  "geometry": {"coordinates":[104.86499999999999,32.4443],"type":"Point"}
}