{
  "type": "Feature",
  "properties": {
    "gn:admin1_code":"05",
    "gn:asciiname":"Dafengman",
    "gn:cc2":"CN",
    "gn:country_code":"CN",
    "gn:dem":224,
    "gn:feature_class":"P",
    "gn:feature_code":"PPL",
    "gn:name":"Dafengman",
    "gn:population":0,
    "gn:timezone":"Asia/Shanghai",
    "iso:country":"CN",
    "name:und_x_variant":[
        "Ta-feng-man",
        "Feng-man",
        "Ta-feng-men",
        "Hsiao-feng-man",
        "Ta-feng-kou",
        "Dafengman"
    ],
    "wof:name":"Dafengman",
    "wof:placetype":"locality"
},
  "geometry": {"coordinates":[126.69083000000001,43.72167],"type":"Point"}
}