{
  "type": "Feature",
  "properties": {
    "gn:admin1_code":"16",
    "gn:asciiname":"Sanhuang",
    "gn:cc2":"CN",
    "gn:country_code":"CN",
    "gn:dem":249,
    "gn:feature_class":"P",
    "gn:feature_code":"PPL",
    "gn:name":"Sanhuang",
    "gn:population":0,
    "gn:timezone":"Asia/Shanghai",
    "iso:country":"CN",
    "name:und_x_variant":[
        "Sanhwangh\u00fc",
        "San-huang-hs\u00fc",
        "Sanhuang"
    ],
    "wof:name":"Sanhuang",
    "wof:placetype":"locality"
},
  "geometry": {"coordinates":[109.65361,24.9325],"type":"Point"}
}