{
  "type": "Feature",
  "properties": {
    "gn:admin1_code":"3.0",
    "gn:asciiname":"Chengtoucun",
    "gn:country_code":"CN",
    "gn:dem":194,
    "gn:feature_class":"P",
    "gn:feature_code":"PPL",
    "gn:name":"Chengtoucun",
    "gn:population":0,
    "gn:timezone":"Asia/Shanghai",
    "iso:country":"CN",
    "name:und_x_variant":[
        "\u57ce\u5934\u6751"
    ],
    "wof:name":"Chengtoucun",
    "wof:placetype":"locality"
},
  "geometry": {"coordinates":[116.03882,26.55235],"type":"Point"}
}