{
  "type": "Feature",
  "properties": {
    "gn:admin1_code":"7",
    "gn:asciiname":"Longqian",
    "gn:country_code":"CN",
    "gn:dem":15,
    "gn:feature_class":"P",
    "gn:feature_code":"PPL",
    "gn:name":"Longqian",
    "gn:population":0,
    "gn:timezone":"Asia/Shanghai",
    "iso:country":"CN",
    "wof:name":"Longqian",
    "wof:placetype":"locality"
},
  "geometry": {"coordinates":[117.60944000000001,24.63139],"type":"Point"}
}