{
  "type": "Feature",
  "properties": {
    "gn:admin1_code":"14.0",
    "gn:asciiname":"Chaquka",
    "gn:country_code":"CN",
    "gn:dem":2818,
    "gn:feature_class":"P",
    "gn:feature_code":"PPL",
    "gn:name":"Chaquka",
    "gn:population":0,
    "gn:timezone":"Asia/Urumqi",
    "iso:country":"CN",
    "name:zho_x_preferred":[
        "\u67e5\u53bb\u5361"
    ],
    "wof:name":"Chaquka",
    "wof:placetype":"locality"
},
  "geometry": {"coordinates":[95.73983,29.55439],"type":"Point"}
}