{
  "type": "Feature",
  "properties": {
    "gn:admin1_code":"29",
    "gn:asciiname":"Goubian",
    "gn:country_code":"CN",
    "gn:dem":2040,
    "gn:feature_class":"P",
    "gn:feature_code":"PPL",
    "gn:name":"Goubian",
    "gn:population":0,
    "gn:timezone":"Asia/Shanghai",
    "iso:country":"CN",
    "name:zho_x_preferred":[
        "\u6c9f\u8fb9"
    ],
    "wof:name":"Goubian",
    "wof:placetype":"locality"
},
  "geometry": {"coordinates":[102.48832,24.8393],"type":"Point"}
}