{
  "type": "Feature",
  "properties": {
    "gn:admin1_code":"25.0",
    "gn:asciiname":"Bujia",
    "gn:country_code":"CN",
    "gn:dem":102,
    "gn:feature_class":"P",
    "gn:feature_code":"PPL",
    "gn:name":"Bujia",
    "gn:population":0,
    "gn:timezone":"Asia/Shanghai",
    "iso:country":"CN",
    "name:zho_x_preferred":[
        "\u6b65\u5bb6"
    ],
    "wof:name":"Bujia",
    "wof:placetype":"locality"
},
  "geometry": {"coordinates":[120.67519,37.08994000000001],"type":"Point"}
}