{
  "type": "Feature",
  "properties": {
    "gn:admin1_code":"1.0",
    "gn:asciiname":"Tuanshan Erzhongdui",
    "gn:country_code":"CN",
    "gn:dem":41,
    "gn:feature_class":"P",
    "gn:feature_code":"PPLF",
    "gn:name":"Tuanshan Erzhongdui",
    "gn:population":0,
    "gn:timezone":"Asia/Shanghai",
    "iso:country":"CN",
    "name:zho_x_preferred":[
        "Tuanshan Erzhongdui"
    ],
    "name:zho_x_variant":[
        "\u56e2\u5c71\u4e8c\u4e2d\u961f"
    ],
    "wof:name":"Tuanshan Erzhongdui",
    "wof:placetype":"locality"
},
  "geometry": {"coordinates":[119.35066999999999,30.95317],"type":"Point"}
}