{
  "type": "Feature",
  "properties": {
    "gn:admin1_code":"3.0",
    "gn:asciiname":"Majibei",
    "gn:country_code":"CN",
    "gn:dem":220,
    "gn:feature_class":"P",
    "gn:feature_code":"PPL",
    "gn:name":"Majibei",
    "gn:population":0,
    "gn:timezone":"Asia/Shanghai",
    "iso:country":"CN",
    "name:zho_x_preferred":[
        "\u9a6c\u8ff9\u80cc"
    ],
    "wof:name":"Majibei",
    "wof:placetype":"locality"
},
  "geometry": {"coordinates":[115.245,25.3486],"type":"Point"}
}