{
  "type": "Feature",
  "properties": {
    "gn:admin1_code":"2.0",
    "gn:asciiname":"Zhifeng",
    "gn:country_code":"CN",
    "gn:dem":85,
    "gn:feature_class":"P",
    "gn:feature_code":"PPL",
    "gn:name":"Zhifeng",
    "gn:population":0,
    "gn:timezone":"Asia/Shanghai",
    "iso:country":"CN",
    "name:zho_x_preferred":[
        "\u829d\u5cf0"
    ],
    "wof:name":"Zhifeng",
    "wof:placetype":"locality"
},
  "geometry": {"coordinates":[119.54206000000001,29.66108],"type":"Point"}
}