{
  "type": "Feature",
  "properties": {
    "gn:admin1_code":"16.0",
    "gn:asciiname":"Dabo",
    "gn:country_code":"CN",
    "gn:dem":164,
    "gn:feature_class":"P",
    "gn:feature_code":"PPL",
    "gn:name":"Dabo",
    "gn:population":0,
    "gn:timezone":"Asia/Shanghai",
    "iso:country":"CN",
    "name:fra_x_preferred":[
        "Dabo"
    ],
    "name:zho_x_preferred":[
        "\u5927\u52c3"
    ],
    "wof:name":"Dabo",
    "wof:placetype":"locality"
},
  "geometry": {"coordinates":[110.313,24.5129],"type":"Point"}
}