{
  "type": "Feature",
  "properties": {
    "gn:admin1_code":"30",
    "gn:asciiname":"Nankou",
    "gn:country_code":"CN",
    "gn:dem":111,
    "gn:feature_class":"P",
    "gn:feature_code":"PPLA4",
    "gn:name":"Nankou",
    "gn:population":0,
    "gn:timezone":"Asia/Shanghai",
    "iso:country":"CN",
    "name:und_x_variant":[
        "Nankou Zhen",
        "\u5357\u53e3\u9547"
    ],
    "name:zho_x_preferred":[
        "Nan-k\u2019ou-hs\u00fc"
    ],
    "name:zho_x_variant":[
        "\u5357\u53e3"
    ],
    "wof:name":"Nankou",
    "wof:placetype":"locality"
},
  "geometry": {"coordinates":[115.98753000000001,24.27437],"type":"Point"}
}