{
  "type": "Feature",
  "properties": {
    "gn:admin1_code":"18.0",
    "gn:asciiname":"Tongziping",
    "gn:country_code":"CN",
    "gn:dem":883,
    "gn:feature_class":"P",
    "gn:feature_code":"PPL",
    "gn:name":"Tongziping",
    "gn:population":0,
    "gn:timezone":"Asia/Shanghai",
    "iso:country":"CN",
    "name:zho_x_preferred":[
        "\u6850\u5b50\u576a"
    ],
    "wof:name":"Tongziping",
    "wof:placetype":"locality"
},
  "geometry": {"coordinates":[108.50700000000001,27.9753],"type":"Point"}
}