{
  "type": "Feature",
  "properties": {
    "gn:admin1_code":"24.0",
    "gn:asciiname":"Dongbaishui",
    "gn:country_code":"CN",
    "gn:dem":944,
    "gn:feature_class":"P",
    "gn:feature_code":"PPL",
    "gn:name":"Dongbaishui",
    "gn:population":0,
    "gn:timezone":"Asia/Shanghai",
    "iso:country":"CN",
    "name:zho_x_preferred":[
        "\u4e1c\u767d\u6c34"
    ],
    "wof:name":"Dongbaishui",
    "wof:placetype":"locality"
},
  "geometry": {"coordinates":[113.38581000000001,38.09619],"type":"Point"}
}