{
  "type": "Feature",
  "properties": {
    "gn:admin1_code":"11.0",
    "gn:asciiname":"Raojiabang",
    "gn:country_code":"CN",
    "gn:dem":624,
    "gn:feature_class":"P",
    "gn:feature_code":"PPL",
    "gn:name":"Raojiabang",
    "gn:population":0,
    "gn:timezone":"Asia/Shanghai",
    "iso:country":"CN",
    "name:zho_x_preferred":[
        "\u9976\u5bb6\u699c"
    ],
    "wof:name":"Raojiabang",
    "wof:placetype":"locality"
},
  "geometry": {"coordinates":[111.13463,29.91815],"type":"Point"}
}