{
  "type": "Feature",
  "properties": {
    "gn:admin1_code":"18",
    "gn:asciiname":"Qingliushui",
    "gn:country_code":"CN",
    "gn:dem":1073,
    "gn:feature_class":"P",
    "gn:feature_code":"PPL",
    "gn:name":"Qingliushui",
    "gn:population":0,
    "gn:timezone":"Asia/Shanghai",
    "iso:country":"CN",
    "name:zho_x_preferred":[
        "\u6e05\u6d41\u6c34"
    ],
    "wof:name":"Qingliushui",
    "wof:placetype":"locality"
},
  "geometry": {"coordinates":[107.986,28.8946],"type":"Point"}
}