{
  "type": "Feature",
  "properties": {
    "gn:admin1_code":"3.0",
    "gn:asciiname":"Jiaxiantou",
    "gn:country_code":"CN",
    "gn:dem":81,
    "gn:feature_class":"P",
    "gn:feature_code":"PPL",
    "gn:name":"Jiaxiantou",
    "gn:population":0,
    "gn:timezone":"Asia/Shanghai",
    "iso:country":"CN",
    "name:und_x_variant":[
        "\u7532\u5148\u5934"
    ],
    "wof:name":"Jiaxiantou",
    "wof:placetype":"locality"
},
  "geometry": {"coordinates":[115.08597,26.92925],"type":"Point"}
}