{
  "type": "Feature",
  "properties": {
    "gn:admin1_code":"26.0",
    "gn:asciiname":"Qinggangping",
    "gn:country_code":"CN",
    "gn:dem":1546,
    "gn:feature_class":"P",
    "gn:feature_code":"PPL",
    "gn:name":"Qinggangping",
    "gn:population":0,
    "gn:timezone":"Asia/Shanghai",
    "iso:country":"CN",
    "name:zho_x_preferred":[
        "\u9752\u5c97\u576a"
    ],
    "wof:name":"Qinggangping",
    "wof:placetype":"locality"
},
  "geometry": {"coordinates":[109.70762999999999,34.19953],"type":"Point"}
}