{
  "type": "Feature",
  "properties": {
    "gn:admin1_code":"7.0",
    "gn:asciiname":"Pancuokou",
    "gn:country_code":"CN",
    "gn:dem":31,
    "gn:feature_class":"P",
    "gn:feature_code":"PPL",
    "gn:name":"Pancuokou",
    "gn:population":0,
    "gn:timezone":"Asia/Shanghai",
    "iso:country":"CN",
    "name:zho_x_preferred":[
        "\u6f58\u539d\u53e3"
    ],
    "wof:name":"Pancuokou",
    "wof:placetype":"locality"
},
  "geometry": {"coordinates":[118.43592,25.01854],"type":"Point"}
}