{
  "type": "Feature",
  "properties": {
    "gn:admin1_code":"12.0",
    "gn:asciiname":"Fujiaping",
    "gn:country_code":"CN",
    "gn:dem":514,
    "gn:feature_class":"P",
    "gn:feature_code":"PPL",
    "gn:name":"Fujiaping",
    "gn:population":0,
    "gn:timezone":"Asia/Shanghai",
    "iso:country":"CN",
    "name:zho_x_preferred":[
        "Fujiaping"
    ],
    "name:zho_x_variant":[
        "\u5bcc\u5bb6\u576a"
    ],
    "wof:name":"Fujiaping",
    "wof:placetype":"locality"
},
  "geometry": {"coordinates":[114.43762,29.43395],"type":"Point"}
}