{
  "type": "Feature",
  "properties": {
    "gn:admin1_code":"26.0",
    "gn:asciiname":"Fanjiadong",
    "gn:country_code":"CN",
    "gn:dem":1129,
    "gn:feature_class":"P",
    "gn:feature_code":"PPL",
    "gn:name":"Fanjiadong",
    "gn:population":0,
    "gn:timezone":"Asia/Shanghai",
    "iso:country":"CN",
    "name:zho_x_preferred":[
        "\u6a0a\u5bb6\u6d1e"
    ],
    "wof:name":"Fanjiadong",
    "wof:placetype":"locality"
},
  "geometry": {"coordinates":[108.51188999999999,35.22166],"type":"Point"}
}