{
  "type": "Feature",
  "properties": {
    "gn:admin1_code":"25",
    "gn:asciiname":"Wanghai",
    "gn:country_code":"CN",
    "gn:dem":58,
    "gn:feature_class":"P",
    "gn:feature_code":"PPL",
    "gn:name":"Wanghai",
    "gn:population":0,
    "gn:timezone":"Asia/Shanghai",
    "iso:country":"CN",
    "name:zho_x_preferred":[
        "\u738b\u6d77"
    ],
    "wof:name":"Wanghai",
    "wof:placetype":"locality"
},
  "geometry": {"coordinates":[116.70699999999999,35.6608],"type":"Point"}
}