{
  "type": "Feature",
  "properties": {
    "gn:country":"CN",
    "gn:fcode":"PPLA3",
    "gn:population":0,
    "iso:country":"CN",
    "name:und_x_variant":[
        "Ch\u2019eng-hsien"
    ],
    "name:zho_x_preferred":[
        "\u5d4a\u5dde\u5e02"
    ],
    "name:zho_x_variant":[
        "\u5261\u6e56",
        "\u5261\u6e56\u8857\u9053"
    ],
    "qs:name":"Shengzhou Shi",
    "qs:photos_9r":0,
    "qs:photos_sr":0,
    "qs:pop_sr":"0",
    "wof:name":"Shengzhou Shi",
    "wof:placetype":"locality",
    "wof:population":0
},
  "geometry": {"coordinates":[120.81667,29.59583],"type":"Point"}
}