{
  "type": "Feature",
  "properties": {
    "gn:admin1_code":"26.0",
    "gn:asciiname":"Celi",
    "gn:country_code":"CN",
    "gn:dem":988,
    "gn:feature_class":"P",
    "gn:feature_code":"PPL",
    "gn:name":"Celi",
    "gn:population":0,
    "gn:timezone":"Asia/Shanghai",
    "iso:country":"CN",
    "name:cat_x_preferred":[
        "Celi"
    ],
    "name:deu_x_preferred":[
        "Celi"
    ],
    "name:fra_x_preferred":[
        "Celi"
    ],
    "name:nds_x_preferred":[
        "Celi"
    ],
    "name:zho_x_preferred":[
        "\u4fa7\u91cc"
    ],
    "wof:name":"Celi",
    "wof:placetype":"locality"
},
  "geometry": {"coordinates":[110.32444,36.33193],"type":"Point"}
}