{
  "type": "Feature",
  "properties": {
    "gn:admin1_code":"18",
    "gn:asciiname":"Dinagou",
    "gn:country_code":"CN",
    "gn:dem":2270,
    "gn:feature_class":"P",
    "gn:feature_code":"PPL",
    "gn:name":"Dinagou",
    "gn:population":0,
    "gn:timezone":"Asia/Shanghai",
    "iso:country":"CN",
    "name:zho_x_preferred":[
        "\u5e95\u90a3\u6c9f"
    ],
    "wof:name":"Dinagou",
    "wof:placetype":"locality"
},
  "geometry": {"coordinates":[104.583,26.7194],"type":"Point"}
}