{
  "type": "Feature",
  "properties": {
    "gn:admin1_code":"11.0",
    "gn:asciiname":"Bashui",
    "gn:country_code":"CN",
    "gn:dem":532,
    "gn:feature_class":"P",
    "gn:feature_code":"PPL",
    "gn:name":"Bashui",
    "gn:population":0,
    "gn:timezone":"Asia/Shanghai",
    "iso:country":"CN",
    "name:zho_x_preferred":[
        "\u516b\u6c34"
    ],
    "wof:name":"Bashui",
    "wof:placetype":"locality"
},
  "geometry": {"coordinates":[110.15141,28.63206],"type":"Point"}
}