{
  "type": "Feature",
  "properties": {
    "gn:admin1_code":"9.0",
    "gn:asciiname":"Santan",
    "gn:country_code":"CN",
    "gn:dem":492,
    "gn:feature_class":"P",
    "gn:feature_code":"PPL",
    "gn:name":"Santan",
    "gn:population":0,
    "gn:timezone":"Asia/Shanghai",
    "iso:country":"CN",
    "name:und_x_variant":[
        "\u4e09\u6f6d",
        "Santan"
    ],
    "wof:name":"Santan",
    "wof:placetype":"locality"
},
  "geometry": {"coordinates":[112.20665,33.27774],"type":"Point"}
}