{
  "type": "Feature",
  "properties": {
    "gn:admin1_code":"2",
    "gn:asciiname":"Daitouyang",
    "gn:country_code":"CN",
    "gn:dem":587,
    "gn:feature_class":"P",
    "gn:feature_code":"PPL",
    "gn:name":"Daitouyang",
    "gn:population":0,
    "gn:timezone":"Asia/Shanghai",
    "iso:country":"CN",
    "name:zho_x_preferred":[
        "\u5cb1\u5934\u579f"
    ],
    "wof:name":"Daitouyang",
    "wof:placetype":"locality"
},
  "geometry": {"coordinates":[119.45889,27.87139],"type":"Point"}
}