{
  "type": "Feature",
  "properties": {
    "gn:admin1_code":"29",
    "gn:asciiname":"Yafengzhai",
    "gn:country_code":"CN",
    "gn:dem":1532,
    "gn:feature_class":"P",
    "gn:feature_code":"PPL",
    "gn:name":"Yafengzhai",
    "gn:population":0,
    "gn:timezone":"Asia/Shanghai",
    "iso:country":"CN",
    "name:zho_x_preferred":[
        "\u4e2b\u5c01\u5be8"
    ],
    "wof:name":"Yafengzhai",
    "wof:placetype":"locality"
},
  "geometry": {"coordinates":[104.664,23.3903],"type":"Point"}
}