{
  "type": "Feature",
  "properties": {
    "gn:admin1_code":"29.0",
    "gn:asciiname":"Qingmen",
    "gn:country_code":"CN",
    "gn:dem":2263,
    "gn:feature_class":"P",
    "gn:feature_code":"PPL",
    "gn:name":"Qingmen",
    "gn:population":0,
    "gn:timezone":"Asia/Shanghai",
    "iso:country":"CN",
    "name:zho_x_preferred":[
        "\u7b90\u95e8"
    ],
    "wof:name":"Qingmen",
    "wof:placetype":"locality"
},
  "geometry": {"coordinates":[99.3785,26.3614],"type":"Point"}
}