{
  "type": "Feature",
  "properties": {
    "gn:admin1_code":"15.0",
    "gn:asciiname":"Caohugou",
    "gn:country_code":"CN",
    "gn:dem":1419,
    "gn:feature_class":"P",
    "gn:feature_code":"PPL",
    "gn:name":"Caohugou",
    "gn:population":0,
    "gn:timezone":"Asia/Urumqi",
    "iso:country":"CN",
    "name:zho_x_preferred":[
        "\u8349\u6e56\u6c9f"
    ],
    "wof:name":"Caohugou",
    "wof:placetype":"locality"
},
  "geometry": {"coordinates":[96.7187,40.4593],"type":"Point"}
}