{
  "type": "Feature",
  "properties": {
    "gn:admin1_code":"32.0",
    "gn:asciiname":"Zhongfengsi",
    "gn:country_code":"CN",
    "gn:dem":589,
    "gn:feature_class":"P",
    "gn:feature_code":"PPL",
    "gn:name":"Zhongfengsi",
    "gn:population":0,
    "gn:timezone":"Asia/Shanghai",
    "iso:country":"CN",
    "name:zho_x_preferred":[
        "\u4e2d\u5cf0\u5bfa"
    ],
    "wof:name":"Zhongfengsi",
    "wof:placetype":"locality"
},
  "geometry": {"coordinates":[106.875,31.5903],"type":"Point"}
}