{
  "type": "Feature",
  "properties": {
    "gn:admin1_code":"29.0",
    "gn:asciiname":"Bojia",
    "gn:country_code":"CN",
    "gn:dem":529,
    "gn:feature_class":"P",
    "gn:feature_code":"PPL",
    "gn:name":"Bojia",
    "gn:population":0,
    "gn:timezone":"Asia/Shanghai",
    "iso:country":"CN",
    "name:zho_x_preferred":[
        "\u535a\u5939"
    ],
    "wof:name":"Bojia",
    "wof:placetype":"locality"
},
  "geometry": {"coordinates":[103.977,22.7241],"type":"Point"}
}