{
  "type": "Feature",
  "properties": {
    "gn:admin1_code":"7",
    "gn:asciiname":"Shuileitou",
    "gn:country_code":"CN",
    "gn:dem":579,
    "gn:feature_class":"P",
    "gn:feature_code":"PPL",
    "gn:name":"Shuileitou",
    "gn:population":0,
    "gn:timezone":"Asia/Shanghai",
    "iso:country":"CN",
    "name:und_x_variant":[
        "\u6c34\u78ca\u5934"
    ],
    "wof:name":"Shuileitou",
    "wof:placetype":"locality"
},
  "geometry": {"coordinates":[118.78722,27.44222],"type":"Point"}
}