{
  "type": "Feature",
  "properties": {
    "gn:admin1_code":"11.0",
    "gn:asciiname":"Luobutang",
    "gn:country_code":"CN",
    "gn:dem":277,
    "gn:feature_class":"P",
    "gn:feature_code":"PPL",
    "gn:name":"Luobutang",
    "gn:population":0,
    "gn:timezone":"Asia/Shanghai",
    "iso:country":"CN",
    "name:zho_x_preferred":[
        "\u841d\u535c\u5858"
    ],
    "wof:name":"Luobutang",
    "wof:placetype":"locality"
},
  "geometry": {"coordinates":[112.82312,25.99135],"type":"Point"}
}