{
  "type": "Feature",
  "properties": {
    "gn:admin1_code":"30",
    "gn:asciiname":"Xuetangxia",
    "gn:country_code":"CN",
    "gn:dem":220,
    "gn:feature_class":"P",
    "gn:feature_code":"PPL",
    "gn:name":"Xuetangxia",
    "gn:population":0,
    "gn:timezone":"Asia/Shanghai",
    "iso:country":"CN",
    "name:zho_x_preferred":[
        "\u5b66\u5802\u4e0b"
    ],
    "wof:name":"Xuetangxia",
    "wof:placetype":"locality"
},
  "geometry": {"coordinates":[115.85857,24.59804],"type":"Point"}
}