{
  "type": "Feature",
  "properties": {
    "gn:admin1_code":"07",
    "gn:asciiname":"Kengweilin",
    "gn:country_code":"CN",
    "gn:dem":270,
    "gn:feature_class":"P",
    "gn:feature_code":"PPL",
    "gn:name":"Kengweilin",
    "gn:population":0,
    "gn:timezone":"Asia/Shanghai",
    "iso:country":"CN",
    "name:zho_x_preferred":[
        "\u5751\u5c3e\u6797"
    ],
    "wof:name":"Kengweilin",
    "wof:placetype":"locality"
},
  "geometry": {"coordinates":[118.18389000000001,25.16778],"type":"Point"}
}