{
  "type": "Feature",
  "properties": {
    "gn:admin1_code":"12.0",
    "gn:asciiname":"Chezhan",
    "gn:country_code":"CN",
    "gn:dem":33,
    "gn:feature_class":"P",
    "gn:feature_code":"PPLA4",
    "gn:name":"Chezhan",
    "gn:population":0,
    "gn:timezone":"Asia/Shanghai",
    "iso:country":"CN",
    "name:und_x_variant":[
        "Chezhan Jiedao"
    ],
    "name:zho_x_preferred":[
        "\u8f66\u7ad9"
    ],
    "name:zho_x_variant":[
        "\u8f66\u7ad9\u8857\u9053"
    ],
    "wof:name":"Chezhan",
    "wof:placetype":"locality"
},
  "geometry": {"coordinates":[113.92104999999999,30.95146],"type":"Point"}
}