{
  "type": "Feature",
  "properties": {
    "gn:admin1_code":"8.0",
    "gn:asciiname":"Taipinggang",
    "gn:country_code":"CN",
    "gn:dem":176,
    "gn:feature_class":"P",
    "gn:feature_code":"PPL",
    "gn:name":"Taipinggang",
    "gn:population":0,
    "gn:timezone":"Asia/Shanghai",
    "iso:country":"CN",
    "name:zho_x_preferred":[
        "\u592a\u5e73\u5c97"
    ],
    "wof:name":"Taipinggang",
    "wof:placetype":"locality"
},
  "geometry": {"coordinates":[126.97368,46.61239000000001],"type":"Point"}
}