{
  "type": "Feature",
  "properties": {
    "gn:admin1_code":"15.0",
    "gn:asciiname":"You'ai",
    "gn:country_code":"CN",
    "gn:dem":2306,
    "gn:feature_class":"P",
    "gn:feature_code":"PPL",
    "gn:name":"You\u2019ai",
    "gn:population":0,
    "gn:timezone":"Asia/Shanghai",
    "iso:country":"CN",
    "name:und_x_variant":[
        "You\u2019ai"
    ],
    "name:zho_x_preferred":[
        "\u53cb\u7231"
    ],
    "wof:name":"You'ai",
    "wof:placetype":"locality"
},
  "geometry": {"coordinates":[100.753,38.4435],"type":"Point"}
}