{
  "type": "Feature",
  "properties": {
    "gn:admin1_code":"24.0",
    "gn:asciiname":"Taoyuancun",
    "gn:country_code":"CN",
    "gn:dem":500,
    "gn:feature_class":"P",
    "gn:feature_code":"PPL",
    "gn:name":"Taoyuancun",
    "gn:population":0,
    "gn:timezone":"Asia/Shanghai",
    "iso:country":"CN",
    "name:zho_x_preferred":[
        "\u6843\u56ed\u6751"
    ],
    "wof:name":"Taoyuancun",
    "wof:placetype":"locality"
},
  "geometry": {"coordinates":[110.71599000000001,34.69557],"type":"Point"}
}