{
  "type": "Feature",
  "properties": {
    "gn:admin1_code":"4.0",
    "gn:asciiname":"Fandao",
    "gn:country_code":"CN",
    "gn:dem":6,
    "gn:feature_class":"P",
    "gn:feature_code":"PPL",
    "gn:name":"Fandao",
    "gn:population":0,
    "gn:timezone":"Asia/Shanghai",
    "iso:country":"CN",
    "name:zho_x_preferred":[
        "\u8303\u9053"
    ],
    "wof:name":"Fandao",
    "wof:placetype":"locality"
},
  "geometry": {"coordinates":[119.74863000000001,31.45445],"type":"Point"}
}