{
  "type": "Feature",
  "properties": {
    "gn:admin1_code":"15.0",
    "gn:asciiname":"Huangcaogou",
    "gn:country_code":"CN",
    "gn:dem":1643,
    "gn:feature_class":"P",
    "gn:feature_code":"PPL",
    "gn:name":"Huangcaogou",
    "gn:population":0,
    "gn:timezone":"Asia/Shanghai",
    "iso:country":"CN",
    "name:zho_x_preferred":[
        "\u9ec4\u8349\u6c9f"
    ],
    "wof:name":"Huangcaogou",
    "wof:placetype":"locality"
},
  "geometry": {"coordinates":[100.126,38.9975],"type":"Point"}
}