{
  "type": "Feature",
  "properties": {
    "gn:admin1_code":"4.0",
    "gn:asciiname":"Jinshacun",
    "gn:country_code":"CN",
    "gn:dem":6,
    "gn:feature_class":"P",
    "gn:feature_code":"PPL",
    "gn:name":"Jinshacun",
    "gn:population":0,
    "gn:timezone":"Asia/Shanghai",
    "iso:country":"CN",
    "name:zho_x_preferred":[
        "\u91d1\u6c99\u6751"
    ],
    "wof:name":"Jinshacun",
    "wof:placetype":"locality"
},
  "geometry": {"coordinates":[119.34350999999999,33.95892],"type":"Point"}
}