{
  "type": "Feature",
  "properties": {
    "gn:admin1_code":"25",
    "gn:asciiname":"Nanmenlou",
    "gn:country_code":"CN",
    "gn:dem":185,
    "gn:feature_class":"P",
    "gn:feature_code":"PPL",
    "gn:name":"Nanmenlou",
    "gn:population":0,
    "gn:timezone":"Asia/Shanghai",
    "iso:country":"CN",
    "name:zho_x_preferred":[
        "\u5357\u95e8\u697c"
    ],
    "wof:name":"Nanmenlou",
    "wof:placetype":"locality"
},
  "geometry": {"coordinates":[118.622,35.9419],"type":"Point"}
}