{
  "type": "Feature",
  "properties": {
    "gn:country":"CN",
    "gn:fcode":"ADM3",
    "gn:pop":489439,
    "iso:country":"CN",
    "name:unk_x_variant":[
        "Shijingshan"
    ],
    "name:zho_x_preferred":[
        "\u77f3\u666f\u5c71\u533a"
    ],
    "name:zho_x_variant":[
        "\u77f3\u666f\u5c71"
    ],
    "qs:name":"Shijingshan Qu",
    "qs:photos_9r":0,
    "qs:photos_sr":0,
    "qs:pop_sr":"10",
    "wd:wordcount":433,
    "wof:name":"Shijingshan Qu",
    "wof:placetype":"localadmin",
    "wof:population":489439
},
  "geometry": {"coordinates":[116.16987,39.93324],"type":"Point"}
}