{
  "type": "Feature",
  "properties": {
    "gn:country":"CN",
    "gn:fcode":"ADM3",
    "gn:pop":489439,
    "iso:country":"CN",
    "name:ara_x_preferred":[
        "\u0634\u064a\u062c\u064a\u0646\u063a\u0634\u0627\u0646"
    ],
    "name:ceb_x_preferred":[
        "Shijingshan Qu"
    ],
    "name:ces_x_preferred":[
        "\u0160'-\u0165ing-\u0161an"
    ],
    "name:cym_x_preferred":[
        "Ardal Shijingshan"
    ],
    "name:deu_x_preferred":[
        "Shijingshan"
    ],
    "name:eng_x_preferred":[
        "Shijingshan District"
    ],
    "name:eus_x_preferred":[
        "Shijingshan barrutia"
    ],
    "name:fas_x_preferred":[
        "\u0634\u06cc\u062c\u06cc\u0646\u06af\u0634\u0627\u0646"
    ],
    "name:gan_x_preferred":[
        "\u77f3\u666f\u5c71\u533a"
    ],
    "name:heb_x_preferred":[
        "\u05d1\u05d9\u05d9\u05d2'\u05d9\u05e0\u05d2/\u05e8\u05d5\u05d1\u05e2 \u05e9\u05d9\u05d9\u05e0\u05d2\u05e9\u05d0\u05df"
    ],
    "name:jpn_x_preferred":[
        "\u77f3\u666f\u5c71\u533a"
    ],
    "name:kor_x_preferred":[
        "\uc2a4\uc9d5\uc0b0\uad6c"
    ],
    "name:lit_x_preferred":[
        "\u0160idzing\u0161anas"
    ],
    "name:lzh_x_preferred":[
        "\u77f3\u666f\u5c71\u5340"
    ],
    "name:mwl_x_preferred":[
        "Shijingshan"
    ],
    "name:nan_x_preferred":[
        "Chio\u030dh-k\u00e9ng-san-khu"
    ],
    "name:nld_x_preferred":[
        "Shijingshan-district"
    ],
    "name:nob_x_preferred":[
        "Shijingshan"
    ],
    "name:pol_x_preferred":[
        "Shijingshan"
    ],
    "name:rus_x_preferred":[
        "\u0428\u0438\u0446\u0437\u0438\u043d\u0448\u0430\u043d\u044c"
    ],
    "name:sco_x_preferred":[
        "Shijingshan Destrict"
    ],
    "name:spa_x_preferred":[
        "Shijingshan"
    ],
    "name:swe_x_preferred":[
        "Shijingshan"
    ],
    "name:tur_x_preferred":[
        "Shijingshan"
    ],
    "name:unk_x_variant":[
        "Shijingshan"
    ],
    "name:urd_x_preferred":[
        "\u0634\u06cc\u062c\u0646\u06af\u0634\u0627\u0646 \u0636\u0644\u0639"
    ],
    "name:vie_x_preferred":[
        "Th\u1ea1ch C\u1ea3nh S\u01a1n"
    ],
    "name:wuu_x_preferred":[
        "\u77f3\u666f\u5c71\u533a"
    ],
    "name:yue_x_preferred":[
        "\u77f3\u666f\u5c71\u5340"
    ],
    "name:zho_x_preferred":[
        "\u77f3\u666f\u5c71\u533a"
    ],
    "name:zho_x_variant":[
        "\u77f3\u666f\u5c71",
        "\u77f3\u666f\u5c71\u5340"
    ],
    "qs:name":"Shijingshan Qu",
    "qs:photos_9r":0,
    "qs:photos_sr":0,
    "qs:pop_sr":"10",
    "wd:wordcount":433,
    "wof:name":"Shijingshan Qu",
    "wof:placetype":"localadmin",
    "wof:population":489439
},
  "geometry": {"coordinates":[116.16987,39.93324],"type":"Point"}
}