{
  "type": "Feature",
  "properties": {
    "gn:admin1_code":"3.0",
    "gn:asciiname":"Leijiacun",
    "gn:country_code":"CN",
    "gn:dem":51,
    "gn:feature_class":"P",
    "gn:feature_code":"PPL",
    "gn:name":"Leijiacun",
    "gn:population":0,
    "gn:timezone":"Asia/Shanghai",
    "iso:country":"CN",
    "name:und_x_variant":[
        "\u96f7\u5bb6\u6751"
    ],
    "wof:name":"Leijiacun",
    "wof:placetype":"locality"
},
  "geometry": {"coordinates":[115.43977,28.85985],"type":"Point"}
}