{
  "type": "Feature",
  "properties": {
    "gn:admin1_code":"24.0",
    "gn:asciiname":"Longbicun",
    "gn:country_code":"CN",
    "gn:dem":1101,
    "gn:feature_class":"P",
    "gn:feature_code":"PPL",
    "gn:name":"Longbicun",
    "gn:population":0,
    "gn:timezone":"Asia/Shanghai",
    "iso:country":"CN",
    "name:zho_x_preferred":[
        "\u9f99\u9f3b\u6751"
    ],
    "wof:name":"Longbicun",
    "wof:placetype":"locality"
},
  "geometry": {"coordinates":[110.77134,35.96872000000001],"type":"Point"}
}