{
  "type": "Feature",
  "properties": {
    "gn:admin1_code":"8.0",
    "gn:asciiname":"Shenghuacun",
    "gn:country_code":"CN",
    "gn:dem":155,
    "gn:feature_class":"P",
    "gn:feature_code":"PPL",
    "gn:name":"Shenghuacun",
    "gn:population":0,
    "gn:timezone":"Asia/Shanghai",
    "iso:country":"CN",
    "name:zho_x_preferred":[
        "\u80dc\u534e\u6751"
    ],
    "wof:name":"Shenghuacun",
    "wof:placetype":"locality"
},
  "geometry": {"coordinates":[126.28003,45.2238],"type":"Point"}
}