{
  "type": "Feature",
  "properties": {
    "gn:admin1_code":"1.0",
    "gn:asciiname":"Gutaicun",
    "gn:country_code":"CN",
    "gn:dem":24,
    "gn:feature_class":"P",
    "gn:feature_code":"PPL",
    "gn:name":"Gutaicun",
    "gn:population":0,
    "gn:timezone":"Asia/Shanghai",
    "iso:country":"CN",
    "name:zho_x_preferred":[
        "\u987e\u53f0\u6751"
    ],
    "wof:name":"Gutaicun",
    "wof:placetype":"locality"
},
  "geometry": {"coordinates":[116.25208000000001,32.47449],"type":"Point"}
}