{
  "type": "Feature",
  "properties": {
    "gn:admin1_code":"1.0",
    "gn:asciiname":"Dulongcun",
    "gn:country_code":"CN",
    "gn:dem":67,
    "gn:feature_class":"P",
    "gn:feature_code":"PPL",
    "gn:name":"Dulongcun",
    "gn:population":0,
    "gn:timezone":"Asia/Shanghai",
    "iso:country":"CN",
    "name:zho_x_preferred":[
        "\u72ec\u9f99\u6751"
    ],
    "wof:name":"Dulongcun",
    "wof:placetype":"locality"
},
  "geometry": {"coordinates":[117.94541,30.79321],"type":"Point"}
}