{
  "type": "Feature",
  "properties": {
    "gn:admin1_code":"3.0",
    "gn:asciiname":"Bengshandi",
    "gn:country_code":"CN",
    "gn:dem":143,
    "gn:feature_class":"P",
    "gn:feature_code":"PPL",
    "gn:name":"Bengshandi",
    "gn:population":0,
    "gn:timezone":"Asia/Shanghai",
    "iso:country":"CN",
    "name:zho_x_preferred":[
        "\u5d29\u5c71\u5e95"
    ],
    "wof:name":"Bengshandi",
    "wof:placetype":"locality"
},
  "geometry": {"coordinates":[118.27172,28.54085],"type":"Point"}
}