{
  "type": "Feature",
  "properties": {
    "gn:admin1_code":"24.0",
    "gn:asciiname":"Hejiazhuangcun",
    "gn:country_code":"CN",
    "gn:dem":407,
    "gn:feature_class":"P",
    "gn:feature_code":"PPL",
    "gn:name":"Hejiazhuangcun",
    "gn:population":0,
    "gn:timezone":"Asia/Shanghai",
    "iso:country":"CN",
    "name:zho_x_preferred":[
        "\u4f55\u5bb6\u5e84\u6751"
    ],
    "wof:name":"Hejiazhuangcun",
    "wof:placetype":"locality"
},
  "geometry": {"coordinates":[110.66036,35.67237],"type":"Point"}
}