{
  "type": "Feature",
  "properties": {
    "gn:admin1_code":"29.0",
    "gn:asciiname":"Shangzhongluo",
    "gn:country_code":"CN",
    "gn:dem":2486,
    "gn:feature_class":"P",
    "gn:feature_code":"PPL",
    "gn:name":"Shangzhongluo",
    "gn:population":0,
    "gn:timezone":"Asia/Shanghai",
    "iso:country":"CN",
    "name:zho_x_preferred":[
        "\u4e0a\u4e2d\u843d"
    ],
    "wof:name":"Shangzhongluo",
    "wof:placetype":"locality"
},
  "geometry": {"coordinates":[100.334,27.2312],"type":"Point"}
}