{
  "type": "Feature",
  "properties": {
    "gn:admin1_code":"10.0",
    "gn:asciiname":"Zhongheliu",
    "gn:country_code":"CN",
    "gn:dem":46,
    "gn:feature_class":"P",
    "gn:feature_code":"PPL",
    "gn:name":"Zhongheliu",
    "gn:population":0,
    "gn:timezone":"Asia/Shanghai",
    "iso:country":"CN",
    "name:zho_x_preferred":[
        "\u4e2d\u5408\u6d41"
    ],
    "wof:name":"Zhongheliu",
    "wof:placetype":"locality"
},
  "geometry": {"coordinates":[115.021,38.1431],"type":"Point"}
}