{
  "type": "Feature",
  "properties": {
    "gn:admin1_code":"9.0",
    "gn:asciiname":"Diligou",
    "gn:country_code":"CN",
    "gn:dem":820,
    "gn:feature_class":"P",
    "gn:feature_code":"PPL",
    "gn:name":"Diligou",
    "gn:population":0,
    "gn:timezone":"Asia/Shanghai",
    "iso:country":"CN",
    "name:zho_x_preferred":[
        "\u72c4\u91cc\u6c9f"
    ],
    "wof:name":"Diligou",
    "wof:placetype":"locality"
},
  "geometry": {"coordinates":[112.34146,33.97734000000001],"type":"Point"}
}