{
  "type": "Feature",
  "properties": {
    "gn:admin1_code":"14.0",
    "gn:asciiname":"Dezhong",
    "gn:country_code":"CN",
    "gn:dem":4339,
    "gn:feature_class":"P",
    "gn:feature_code":"PPLF",
    "gn:name":"Dezhong",
    "gn:population":0,
    "gn:timezone":"Asia/Urumqi",
    "iso:country":"CN",
    "name:bod_x_preferred":[
        "D\u00earzhom"
    ],
    "name:bod_x_variant":[
        "\u0f42\u0f4f\u0f7a\u0f62\u0f0b\u0f66\u0f92\u0fb2\u0f7c\u0f58"
    ],
    "name:zho_x_preferred":[
        "Dezhong"
    ],
    "name:zho_x_variant":[
        "\u5fb7\u5fe0"
    ],
    "wof:name":"Dezhong",
    "wof:placetype":"locality"
},
  "geometry": {"coordinates":[92.17066,30.138],"type":"Point"}
}