{
  "type": "Feature",
  "properties": {
    "gn:admin1_code":"5.0",
    "gn:asciiname":"Guoshu",
    "gn:country_code":"CN",
    "gn:dem":241,
    "gn:feature_class":"P",
    "gn:feature_code":"PPL",
    "gn:name":"Guoshu",
    "gn:population":0,
    "gn:timezone":"Asia/Shanghai",
    "iso:country":"CN",
    "name:und_x_variant":[
        "\u679c\u6811"
    ],
    "wof:name":"Guoshu",
    "wof:placetype":"locality"
},
  "geometry": {"coordinates":[126.20553999999998,41.14952],"type":"Point"}
}