{
  "type": "Feature",
  "properties": {
    "gn:admin1_code":"1.0",
    "gn:asciiname":"Weizhoucun",
    "gn:country_code":"CN",
    "gn:dem":41,
    "gn:feature_class":"P",
    "gn:feature_code":"PPL",
    "gn:name":"Weizhoucun",
    "gn:population":0,
    "gn:timezone":"Asia/Shanghai",
    "iso:country":"CN",
    "name:und_x_variant":[
        "Weizhou"
    ],
    "name:zho_x_preferred":[
        "\u97e6\u5468\u6751"
    ],
    "wof:name":"Weizhoucun",
    "wof:placetype":"locality"
},
  "geometry": {"coordinates":[115.19629,32.9563],"type":"Point"}
}