{
  "type": "Feature",
  "properties": {
    "gn:admin1_code":"15.0",
    "gn:asciiname":"Sujiayuan",
    "gn:country_code":"CN",
    "gn:dem":1538,
    "gn:feature_class":"P",
    "gn:feature_code":"PPL",
    "gn:name":"Sujiayuan",
    "gn:population":0,
    "gn:timezone":"Asia/Shanghai",
    "iso:country":"CN",
    "name:und_x_variant":[
        "\u82cf\u5bb6\u586c"
    ],
    "wof:name":"Sujiayuan",
    "wof:placetype":"locality"
},
  "geometry": {"coordinates":[107.13299000000001,36.70185],"type":"Point"}
}