{
  "type": "Feature",
  "properties": {
    "gn:admin1_code":"32.0",
    "gn:asciiname":"Yueyan",
    "gn:country_code":"CN",
    "gn:dem":446,
    "gn:feature_class":"P",
    "gn:feature_code":"PPL",
    "gn:name":"Yueyan",
    "gn:population":0,
    "gn:timezone":"Asia/Shanghai",
    "iso:country":"CN",
    "name:zho_x_preferred":[
        "\u5cb3\u5830"
    ],
    "wof:name":"Yueyan",
    "wof:placetype":"locality"
},
  "geometry": {"coordinates":[103.67100000000001,30.0976],"type":"Point"}
}