{
  "type": "Feature",
  "properties": {
    "gn:admin1_code":"18",
    "gn:asciiname":"Rongyan",
    "gn:country_code":"CN",
    "gn:dem":1146,
    "gn:feature_class":"P",
    "gn:feature_code":"PPL",
    "gn:name":"Rongyan",
    "gn:population":0,
    "gn:timezone":"Asia/Shanghai",
    "iso:country":"CN",
    "name:zho_x_preferred":[
        "\u5197\u5ca9"
    ],
    "wof:name":"Rongyan",
    "wof:placetype":"locality"
},
  "geometry": {"coordinates":[106.27500000000001,25.3855],"type":"Point"}
}