{
  "type": "Feature",
  "properties": {
    "gn:admin1_code":"26.0",
    "gn:asciiname":"Huizuizi",
    "gn:country_code":"CN",
    "gn:dem":1292,
    "gn:feature_class":"P",
    "gn:feature_code":"PPL",
    "gn:name":"Huizuizi",
    "gn:population":0,
    "gn:timezone":"Asia/Shanghai",
    "iso:country":"CN",
    "name:zho_x_preferred":[
        "\u7070\u5480\u5b50"
    ],
    "wof:name":"Huizuizi",
    "wof:placetype":"locality"
},
  "geometry": {"coordinates":[109.19431000000002,35.25863],"type":"Point"}
}