{
  "type": "Feature",
  "properties": {
    "gn:admin1_code":"1.0",
    "gn:asciiname":"Yangyoudao",
    "gn:country_code":"CN",
    "gn:dem":12,
    "gn:feature_class":"P",
    "gn:feature_code":"PPL",
    "gn:name":"Yangyoudao",
    "gn:population":0,
    "gn:timezone":"Asia/Shanghai",
    "iso:country":"CN",
    "name:zho_x_preferred":[
        "\u6768\u53cb\u9053"
    ],
    "wof:name":"Yangyoudao",
    "wof:placetype":"locality"
},
  "geometry": {"coordinates":[118.36355,31.87087],"type":"Point"}
}