{
  "type": "Feature",
  "properties": {
    "gn:admin1_code":"7",
    "gn:asciiname":"Yangmeizhou",
    "gn:country_code":"CN",
    "gn:dem":501,
    "gn:feature_class":"P",
    "gn:feature_code":"PPL",
    "gn:name":"Yangmeizhou",
    "gn:population":0,
    "gn:timezone":"Asia/Shanghai",
    "iso:country":"CN",
    "name:und_x_variant":[
        "\u6768\u6885\u5dde",
        "Yangmeizhou"
    ],
    "wof:name":"Yangmeizhou",
    "wof:placetype":"locality"
},
  "geometry": {"coordinates":[119.62972000000001,27.54872],"type":"Point"}
}