{
  "type": "Feature",
  "properties": {
    "gn:admin1_code":"24.0",
    "gn:asciiname":"Xiachangle",
    "gn:country_code":"CN",
    "gn:dem":901,
    "gn:feature_class":"P",
    "gn:feature_code":"PPL",
    "gn:name":"Xiachangle",
    "gn:population":0,
    "gn:timezone":"Asia/Shanghai",
    "iso:country":"CN",
    "name:und_x_variant":[
        "Hsia-ch\u2019ang-le",
        "Hsia-ch\u2019ang-lo",
        "Xiachangle"
    ],
    "name:zho_x_preferred":[
        "\u4e0b\u957f\u4e50"
    ],
    "wof:name":"Xiachangle",
    "wof:placetype":"locality"
},
  "geometry": {"coordinates":[112.86402,38.91395],"type":"Point"}
}