{
  "type": "Feature",
  "properties": {
    "gn:admin1_code":"1.0",
    "gn:asciiname":"Caozuicun",
    "gn:country_code":"CN",
    "gn:dem":26,
    "gn:feature_class":"P",
    "gn:feature_code":"PPL",
    "gn:name":"Caozuicun",
    "gn:population":0,
    "gn:timezone":"Asia/Shanghai",
    "iso:country":"CN",
    "name:zho_x_preferred":[
        "\u66f9\u5634\u6751"
    ],
    "wof:name":"Caozuicun",
    "wof:placetype":"locality"
},
  "geometry": {"coordinates":[116.99252,32.6592],"type":"Point"}
}