{
  "type": "Feature",
  "properties": {
    "gn:admin1_code":"10.0",
    "gn:asciiname":"Beishimen",
    "gn:country_code":"CN",
    "gn:dem":75,
    "gn:feature_class":"P",
    "gn:feature_code":"PPL",
    "gn:name":"Beishimen",
    "gn:population":0,
    "gn:timezone":"Asia/Shanghai",
    "iso:country":"CN",
    "name:zho_x_preferred":[
        "\u5317\u77f3\u95e8"
    ],
    "wof:name":"Beishimen",
    "wof:placetype":"locality"
},
  "geometry": {"coordinates":[115.42862,39.38041],"type":"Point"}
}