{
  "type": "Feature",
  "properties": {
    "gn:admin1_code":"8.0",
    "gn:asciiname":"Qixin",
    "gn:country_code":"CN",
    "gn:dem":143,
    "gn:feature_class":"P",
    "gn:feature_code":"PPL",
    "gn:name":"Qixin",
    "gn:population":0,
    "gn:timezone":"Asia/Shanghai",
    "iso:country":"CN",
    "name:zho_x_preferred":[
        "\u542f\u65b0"
    ],
    "wof:name":"Qixin",
    "wof:placetype":"locality"
},
  "geometry": {"coordinates":[125.10966999999999,46.27442],"type":"Point"}
}