{
  "type": "Feature",
  "properties": {
    "gn:admin1_code":"31.0",
    "gn:asciiname":"Donghong Ershibadui",
    "gn:country_code":"CN",
    "gn:dem":104,
    "gn:feature_class":"P",
    "gn:feature_code":"PPLF",
    "gn:name":"Donghong Ershibadui",
    "gn:population":0,
    "gn:timezone":"Asia/Shanghai",
    "iso:country":"CN",
    "name:und_x_variant":[
        "\u4e1c\u7ea2\u4e8c\u5341\u516b\u961f"
    ],
    "wof:name":"Donghong Ershibadui",
    "wof:placetype":"locality"
},
  "geometry": {"coordinates":[110.56213,19.43987000000001],"type":"Point"}
}