{
  "type": "Feature",
  "properties": {
    "gn:admin1_code":"30.0",
    "gn:admin2_code":"1784313",
    "gn:asciiname":"Xiqu",
    "gn:country_code":"CN",
    "gn:dem":1,
    "gn:feature_class":"P",
    "gn:feature_code":"PPLA4",
    "gn:name":"Xiqu",
    "gn:population":0,
    "gn:timezone":"Asia/Shanghai",
    "iso:country":"CN",
    "name:deu_x_preferred":[
        "Xiqu"
    ],
    "name:und_x_variant":[
        "Xiqu Jiedao"
    ],
    "name:zho_x_preferred":[
        "\u897f\u533a"
    ],
    "name:zho_x_variant":[
        "\u897f\u533a\u8857\u9053"
    ],
    "wof:name":"Xiqu",
    "wof:placetype":"locality"
},
  "geometry": {"coordinates":[113.35659,22.52098],"type":"Point"}
}