{
  "type": "Feature",
  "properties": {
    "gn:admin1_code":"8.0",
    "gn:asciiname":"Qinxiancun",
    "gn:country_code":"CN",
    "gn:dem":172,
    "gn:feature_class":"P",
    "gn:feature_code":"PPL",
    "gn:name":"Qinxiancun",
    "gn:population":0,
    "gn:timezone":"Asia/Shanghai",
    "iso:country":"CN",
    "name:zho_x_preferred":[
        "\u52e4\u9c9c\u6751"
    ],
    "wof:name":"Qinxiancun",
    "wof:placetype":"locality"
},
  "geometry": {"coordinates":[127.46802,46.98792],"type":"Point"}
}