{
  "type": "Feature",
  "properties": {
    "gn:admin1_code":"14.0",
    "gn:asciiname":"Qusencun",
    "gn:country_code":"CN",
    "gn:dem":4793,
    "gn:feature_class":"P",
    "gn:feature_code":"PPL",
    "gn:name":"Qusencun",
    "gn:population":0,
    "gn:timezone":"Asia/Urumqi",
    "iso:country":"CN",
    "name:zho_x_preferred":[
        "\u66f2\u68ee\u6751"
    ],
    "wof:name":"Qusencun",
    "wof:placetype":"locality"
},
  "geometry": {"coordinates":[89.90363000000001,30.76846],"type":"Point"}
}