{
  "type": "Feature",
  "properties": {
    "gn:admin1_code":"04",
    "gn:asciiname":"Daxin",
    "gn:country_code":"CN",
    "gn:dem":4,
    "gn:feature_class":"P",
    "gn:feature_code":"PPL",
    "gn:name":"Daxin",
    "gn:population":0,
    "gn:timezone":"Asia/Shanghai",
    "iso:country":"CN",
    "name:ceb_x_preferred":[
        "Daxin"
    ],
    "name:deu_x_preferred":[
        "Daxin"
    ],
    "name:und_x_variant":[
        "\u5927\u65b0",
        "Daxinzhen",
        "\u5927\u65b0\u9547"
    ],
    "wof:name":"Daxin",
    "wof:placetype":"locality"
},
  "geometry": {"coordinates":[121.34397,31.88944],"type":"Point"}
}