{
  "type": "Feature",
  "properties": {
    "gn:admin1_code":"6.0",
    "gn:asciiname":"Zaiqiong Gema",
    "gn:country_code":"CN",
    "gn:dem":3877,
    "gn:feature_class":"P",
    "gn:feature_code":"PPL",
    "gn:name":"Zaiqiong Gema",
    "gn:population":0,
    "gn:timezone":"Asia/Urumqi",
    "iso:country":"CN",
    "name:zho_x_preferred":[
        "\u683d\u743c\u5404\u739b"
    ],
    "wof:name":"Zaiqiong Gema",
    "wof:placetype":"locality"
},
  "geometry": {"coordinates":[97.02835,32.96887],"type":"Point"}
}