{
  "type": "Feature",
  "properties": {
    "gn:admin1_code":"32.0",
    "gn:asciiname":"A'erwajue",
    "gn:country_code":"CN",
    "gn:dem":2207,
    "gn:feature_class":"P",
    "gn:feature_code":"PPL",
    "gn:name":"A\u2019erwajue",
    "gn:population":0,
    "gn:timezone":"Asia/Shanghai",
    "iso:country":"CN",
    "name:und_x_variant":[
        "A\u2019erwajue"
    ],
    "name:zho_x_preferred":[
        "\u963f\u5c14\u74e6\u89c9"
    ],
    "wof:name":"A'erwajue",
    "wof:placetype":"locality"
},
  "geometry": {"coordinates":[102.97499999999999,28.3657],"type":"Point"}
}