{
  "type": "Feature",
  "properties": {
    "gn:admin1_code":"2.0",
    "gn:asciiname":"Batuan",
    "gn:country_code":"CN",
    "gn:dem":6,
    "gn:feature_class":"P",
    "gn:feature_code":"PPL",
    "gn:name":"Batuan",
    "gn:population":0,
    "gn:timezone":"Asia/Shanghai",
    "iso:country":"CN",
    "name:ceb_x_preferred":[
        "Batuan"
    ],
    "name:deu_x_preferred":[
        "Batuan"
    ],
    "name:fra_x_preferred":[
        "Batuan"
    ],
    "name:ind_x_preferred":[
        "Batuan"
    ],
    "name:ita_x_preferred":[
        "Batuan"
    ],
    "name:nld_x_preferred":[
        "Batuan"
    ],
    "name:nor_x_preferred":[
        "Batuan"
    ],
    "name:swe_x_preferred":[
        "Batuan"
    ],
    "name:und_x_variant":[
        "\u516b\u56e2"
    ],
    "name:war_x_preferred":[
        "Batuan"
    ],
    "wof:name":"Batuan",
    "wof:placetype":"locality"
},
  "geometry": {"coordinates":[120.99178000000001,30.57008],"type":"Point"}
}