{
  "type": "Feature",
  "properties": {
    "gn:admin1_code":"12.0",
    "gn:asciiname":"Hou'aoguan",
    "gn:country_code":"CN",
    "gn:dem":28,
    "gn:feature_class":"P",
    "gn:feature_code":"PPL",
    "gn:name":"Hou\u2019aoguan",
    "gn:population":0,
    "gn:timezone":"Asia/Shanghai",
    "iso:country":"CN",
    "name:und_x_variant":[
        "Hou\u2019aoguan"
    ],
    "name:zho_x_preferred":[
        "\u540e\u6556\u5173"
    ],
    "wof:name":"Hou'aoguan",
    "wof:placetype":"locality"
},
  "geometry": {"coordinates":[113.12147,29.91758],"type":"Point"}
}