{
  "type": "Feature",
  "properties": {
    "gn:admin1_code":"8.0",
    "gn:asciiname":"Liangkesong",
    "gn:country_code":"CN",
    "gn:dem":217,
    "gn:feature_class":"P",
    "gn:feature_code":"PPL",
    "gn:name":"Liangkesong",
    "gn:population":0,
    "gn:timezone":"Asia/Shanghai",
    "iso:country":"CN",
    "name:zho_x_preferred":[
        "\u4e24\u68f5\u677e"
    ],
    "wof:name":"Liangkesong",
    "wof:placetype":"locality"
},
  "geometry": {"coordinates":[127.70169,44.86803],"type":"Point"}
}