{
  "type": "Feature",
  "properties": {
    "gn:admin1_code":"11.0",
    "gn:asciiname":"Yangjiarong",
    "gn:country_code":"CN",
    "gn:dem":100,
    "gn:feature_class":"P",
    "gn:feature_code":"PPL",
    "gn:name":"Yangjiarong",
    "gn:population":0,
    "gn:timezone":"Asia/Shanghai",
    "iso:country":"CN",
    "name:zho_x_preferred":[
        "Yangjiarong"
    ],
    "name:zho_x_variant":[
        "\u6768\u5bb6\u6eb6"
    ],
    "wof:name":"Yangjiarong",
    "wof:placetype":"locality"
},
  "geometry": {"coordinates":[111.27767,29.13765],"type":"Point"}
}