{
  "type": "Feature",
  "properties": {
    "gn:admin1_code":"14",
    "gn:asciiname":"Gyixong",
    "gn:country_code":"CN",
    "gn:dem":3570,
    "gn:feature_class":"P",
    "gn:feature_code":"PPL",
    "gn:name":"Gyixong",
    "gn:population":0,
    "gn:timezone":"Asia/Urumqi",
    "iso:country":"CN",
    "name:bod_x_preferred":[
        "\u0f66\u0f90\u0fb1\u0f72\u0f51\u0f0b\u0f42\u0f64\u0f7c\u0f44\u0f66"
    ],
    "name:und_x_variant":[
        "Jixiong"
    ],
    "name:zho_x_preferred":[
        "\u5409\u96c4"
    ],
    "wof:name":"Gyixong",
    "wof:placetype":"locality"
},
  "geometry": {"coordinates":[90.9819,29.29299],"type":"Point"}
}