{
  "type": "Feature",
  "properties": {
    "gn:admin1_code":"19.0",
    "gn:asciiname":"Shipianzicun",
    "gn:country_code":"CN",
    "gn:dem":444,
    "gn:feature_class":"P",
    "gn:feature_code":"PPL",
    "gn:name":"Shipianzicun",
    "gn:population":0,
    "gn:timezone":"Asia/Shanghai",
    "iso:country":"CN",
    "name:zho_x_preferred":[
        "\u77f3\u7247\u5b50\u6751"
    ],
    "wof:name":"Shipianzicun",
    "wof:placetype":"locality"
},
  "geometry": {"coordinates":[120.20208999999998,41.61266],"type":"Point"}
}