{
  "type": "Feature",
  "properties": {
    "gn:admin1_code":"29.0",
    "gn:asciiname":"Xiajiashan",
    "gn:country_code":"CN",
    "gn:dem":2015,
    "gn:feature_class":"P",
    "gn:feature_code":"PPL",
    "gn:name":"Xiajiashan",
    "gn:population":0,
    "gn:timezone":"Asia/Shanghai",
    "iso:country":"CN",
    "name:zho_x_preferred":[
        "\u590f\u5bb6\u5c71"
    ],
    "wof:name":"Xiajiashan",
    "wof:placetype":"locality"
},
  "geometry": {"coordinates":[100.75,25.3896],"type":"Point"}
}