{
  "type": "Feature",
  "properties": {
    "gn:admin1_code":"29.0",
    "gn:asciiname":"Manguang",
    "gn:country_code":"CN",
    "gn:dem":1264,
    "gn:feature_class":"P",
    "gn:feature_code":"PPL",
    "gn:name":"Manguang",
    "gn:population":0,
    "gn:timezone":"Asia/Shanghai",
    "iso:country":"CN",
    "name:zho_x_preferred":[
        "\u66fc\u5e7f"
    ],
    "wof:name":"Manguang",
    "wof:placetype":"locality"
},
  "geometry": {"coordinates":[99.2606,23.2188],"type":"Point"}
}