{
  "type": "Feature",
  "properties": {
    "gn:admin1_code":"33.0",
    "gn:asciiname":"Mahe",
    "gn:country_code":"CN",
    "gn:dem":513,
    "gn:feature_class":"P",
    "gn:feature_code":"PPL",
    "gn:name":"Mahe",
    "gn:population":0,
    "gn:timezone":"Asia/Shanghai",
    "iso:country":"CN",
    "name:cat_x_preferred":[
        "Mahe"
    ],
    "name:ceb_x_preferred":[
        "Mahe"
    ],
    "name:dan_x_preferred":[
        "Mahe"
    ],
    "name:deu_x_preferred":[
        "Mahe"
    ],
    "name:ita_x_preferred":[
        "Mahe"
    ],
    "name:mal_x_preferred":[
        "\u0d2e\u0d3e\u0d39\u0d3f"
    ],
    "name:rus_x_preferred":[
        "\u041c\u0430\u044d"
    ],
    "name:spa_x_preferred":[
        "Mahe"
    ],
    "name:ukr_x_preferred":[
        "\u041c\u0430\u0435"
    ],
    "name:zho_x_preferred":[
        "\u9a6c\u5408"
    ],
    "wof:name":"Mahe",
    "wof:placetype":"locality"
},
  "geometry": {"coordinates":[109.1939,31.02629],"type":"Point"}
}