{
  "type": "Feature",
  "properties": {
    "gn:admin1_code":"31.0",
    "gn:asciiname":"Datoupo",
    "gn:country_code":"CN",
    "gn:dem":92,
    "gn:feature_class":"P",
    "gn:feature_code":"PPL",
    "gn:name":"Datoupo",
    "gn:population":0,
    "gn:timezone":"Asia/Shanghai",
    "iso:country":"CN",
    "name:zho_x_preferred":[
        "\u5927\u5934\u5761"
    ],
    "wof:name":"Datoupo",
    "wof:placetype":"locality"
},
  "geometry": {"coordinates":[110.50196,19.44353],"type":"Point"}
}