{
  "type": "Feature",
  "properties": {
    "gn:admin1_code":"18",
    "gn:asciiname":"Shejiagou",
    "gn:country_code":"CN",
    "gn:dem":1259,
    "gn:feature_class":"P",
    "gn:feature_code":"PPL",
    "gn:name":"Shejiagou",
    "gn:population":0,
    "gn:timezone":"Asia/Shanghai",
    "iso:country":"CN",
    "name:zho_x_preferred":[
        "\u4f58\u5bb6\u6c9f"
    ],
    "wof:name":"Shejiagou",
    "wof:placetype":"locality"
},
  "geometry": {"coordinates":[107.761,27.555],"type":"Point"}
}