{
  "type": "Feature",
  "properties": {
    "gn:admin1_code":"22.0",
    "gn:asciiname":"Fenshuilingcun",
    "gn:country_code":"CN",
    "gn:dem":428,
    "gn:feature_class":"P",
    "gn:feature_code":"PPL",
    "gn:name":"Fenshuilingcun",
    "gn:population":0,
    "gn:timezone":"Asia/Shanghai",
    "iso:country":"CN",
    "name:zho_x_preferred":[
        "\u5206\u6c34\u5cad\u6751"
    ],
    "wof:name":"Fenshuilingcun",
    "wof:placetype":"locality"
},
  "geometry": {"coordinates":[116.27563000000001,40.36201],"type":"Point"}
}