{
  "type": "Feature",
  "properties": {
    "gn:admin1_code":"26.0",
    "gn:asciiname":"Huoshao'an",
    "gn:country_code":"CN",
    "gn:dem":1998,
    "gn:feature_class":"P",
    "gn:feature_code":"PPL",
    "gn:name":"Huoshao\u2019an",
    "gn:population":0,
    "gn:timezone":"Asia/Shanghai",
    "iso:country":"CN",
    "name:und_x_variant":[
        "\u706b\u70e7\u5eb5"
    ],
    "name:zho_x_preferred":[
        "Huoshao\u2019an"
    ],
    "wof:name":"Huoshao'an",
    "wof:placetype":"locality"
},
  "geometry": {"coordinates":[106.72889000000001,33.46754],"type":"Point"}
}