{
  "type": "Feature",
  "properties": {
    "gn:admin1_code":"19.0",
    "gn:asciiname":"Longtaihao",
    "gn:country_code":"CN",
    "gn:dem":614,
    "gn:feature_class":"P",
    "gn:feature_code":"PPL",
    "gn:name":"Longtaihao",
    "gn:population":0,
    "gn:timezone":"Asia/Shanghai",
    "iso:country":"CN",
    "name:zho_x_preferred":[
        "\u9f99\u53f0\u53f7"
    ],
    "wof:name":"Longtaihao",
    "wof:placetype":"locality"
},
  "geometry": {"coordinates":[119.45699999999999,41.8935],"type":"Point"}
}