{
  "type": "Feature",
  "properties": {
    "gn:admin1_code":"14",
    "gn:asciiname":"Ziba",
    "gn:country_code":"CN",
    "gn:dem":4644,
    "gn:feature_class":"P",
    "gn:feature_code":"PPL",
    "gn:name":"Ziba",
    "gn:population":0,
    "gn:timezone":"Asia/Urumqi",
    "iso:country":"CN",
    "name:zho_x_preferred":[
        "\u5b5c\u5df4"
    ],
    "wof:name":"Ziba",
    "wof:placetype":"locality"
},
  "geometry": {"coordinates":[89.6836,29.2832],"type":"Point"}
}