{
  "type": "Feature",
  "properties": {
    "gn:admin1_code":"26.0",
    "gn:asciiname":"Shuiquanwan",
    "gn:country_code":"CN",
    "gn:dem":1615,
    "gn:feature_class":"P",
    "gn:feature_code":"PPL",
    "gn:name":"Shuiquanwan",
    "gn:population":0,
    "gn:timezone":"Asia/Shanghai",
    "iso:country":"CN",
    "name:und_x_variant":[
        "\u6c34\u6cc9\u6e7e"
    ],
    "wof:name":"Shuiquanwan",
    "wof:placetype":"locality"
},
  "geometry": {"coordinates":[106.60127,33.85297],"type":"Point"}
}