{
  "type": "Feature",
  "properties": {
    "gn:admin1_code":"20.0",
    "gn:asciiname":"Bayan Chagan",
    "gn:country_code":"CN",
    "gn:dem":734,
    "gn:feature_class":"P",
    "gn:feature_code":"PPL",
    "gn:name":"Bayan Chagan",
    "gn:population":0,
    "gn:timezone":"Asia/Shanghai",
    "iso:country":"CN",
    "name:zho_x_preferred":[
        "\u5df4\u5f66\u67e5\u5e72"
    ],
    "wof:name":"Bayan Chagan",
    "wof:placetype":"locality"
},
  "geometry": {"coordinates":[115.99655,48.07505],"type":"Point"}
}