{
  "type": "Feature",
  "properties": {
    "gn:admin1_code":"4.0",
    "gn:asciiname":"Feiyaocun",
    "gn:country_code":"CN",
    "gn:dem":8,
    "gn:feature_class":"P",
    "gn:feature_code":"PPL",
    "gn:name":"Feiyaocun",
    "gn:population":0,
    "gn:timezone":"Asia/Shanghai",
    "iso:country":"CN",
    "name:zho_x_preferred":[
        "\u8d39\u7a91\u6751"
    ],
    "wof:name":"Feiyaocun",
    "wof:placetype":"locality"
},
  "geometry": {"coordinates":[119.59448,33.87909000000001],"type":"Point"}
}