{
  "type": "Feature",
  "properties": {
    "gn:admin1_code":"8.0",
    "gn:asciiname":"Wanxingcun",
    "gn:country_code":"CN",
    "gn:dem":224,
    "gn:feature_class":"P",
    "gn:feature_code":"PPL",
    "gn:name":"Wanxingcun",
    "gn:population":0,
    "gn:timezone":"Asia/Shanghai",
    "iso:country":"CN",
    "name:zho_x_preferred":[
        "\u4e07\u5174\u6751"
    ],
    "wof:name":"Wanxingcun",
    "wof:placetype":"locality"
},
  "geometry": {"coordinates":[124.79376999999999,48.5193],"type":"Point"}
}