{
  "type": "Feature",
  "properties": {
    "gn:admin1_code":"18",
    "gn:asciiname":"Pingzitou",
    "gn:country_code":"CN",
    "gn:dem":1795,
    "gn:feature_class":"P",
    "gn:feature_code":"PPL",
    "gn:name":"Pingzitou",
    "gn:population":0,
    "gn:timezone":"Asia/Shanghai",
    "iso:country":"CN",
    "name:zho_x_preferred":[
        "\u5e73\u5b50\u5934"
    ],
    "wof:name":"Pingzitou",
    "wof:placetype":"locality"
},
  "geometry": {"coordinates":[104.57899999999999,26.2728],"type":"Point"}
}