{
  "type": "Feature",
  "properties": {
    "gn:admin1_code":"3.0",
    "gn:asciiname":"Lixu",
    "gn:country_code":"CN",
    "gn:dem":43,
    "gn:feature_class":"P",
    "gn:feature_code":"PPL",
    "gn:name":"Lixu",
    "gn:population":0,
    "gn:timezone":"Asia/Shanghai",
    "iso:country":"CN",
    "name:fas_x_preferred":[
        "\u0644\u06cc\u0634\u0648"
    ],
    "name:und_x_variant":[
        "\u9ece\u5729"
    ],
    "name:zho_x_preferred":[
        "\u9ece\u5729\u9547"
    ],
    "wof:name":"Lixu",
    "wof:placetype":"locality"
},
  "geometry": {"coordinates":[115.13778000000001,27.98986],"type":"Point"}
}