{
  "type": "Feature",
  "properties": {
    "gn:admin1_code":"9.0",
    "gn:asciiname":"Mingzhang",
    "gn:country_code":"CN",
    "gn:dem":140,
    "gn:feature_class":"P",
    "gn:feature_code":"PPL",
    "gn:name":"Mingzhang",
    "gn:population":0,
    "gn:timezone":"Asia/Shanghai",
    "iso:country":"CN",
    "name:und_x_variant":[
        "\u660e\u5f20",
        "Mingzhang"
    ],
    "wof:name":"Mingzhang",
    "wof:placetype":"locality"
},
  "geometry": {"coordinates":[112.8351,33.10097],"type":"Point"}
}