{
  "type": "Feature",
  "properties": {
    "gn:admin1_code":"29.0",
    "gn:asciiname":"Pingzhangjie",
    "gn:country_code":"CN",
    "gn:dem":1710,
    "gn:feature_class":"P",
    "gn:feature_code":"PPL",
    "gn:name":"Pingzhangjie",
    "gn:population":0,
    "gn:timezone":"Asia/Shanghai",
    "iso:country":"CN",
    "name:zho_x_preferred":[
        "\u5e73\u638c\u8857"
    ],
    "wof:name":"Pingzhangjie",
    "wof:placetype":"locality"
},
  "geometry": {"coordinates":[102.107,23.0122],"type":"Point"}
}