{
  "type": "Feature",
  "properties": {
    "gn:admin1_code":"19.0",
    "gn:asciiname":"Xinqiu",
    "gn:country_code":"CN",
    "gn:dem":183,
    "gn:feature_class":"P",
    "gn:feature_code":"PPL",
    "gn:name":"Xinqiu",
    "gn:population":0,
    "gn:timezone":"Asia/Shanghai",
    "iso:country":"CN",
    "name:und_x_variant":[
        "\u65b0\u79cb"
    ],
    "name:zho_x_preferred":[
        "\u65b0\u79cb"
    ],
    "wof:name":"Xinqiu",
    "wof:placetype":"locality"
},
  "geometry": {"coordinates":[121.0493,41.91217],"type":"Point"}
}