{
  "type": "Feature",
  "properties": {
    "gn:admin1_code":"7.0",
    "gn:asciiname":"Zhuyang",
    "gn:country_code":"CN",
    "gn:dem":606,
    "gn:feature_class":"P",
    "gn:feature_code":"PPL",
    "gn:name":"Zhuyang",
    "gn:population":0,
    "gn:timezone":"Asia/Shanghai",
    "iso:country":"CN",
    "name:zho_x_preferred":[
        "Zhuyang"
    ],
    "name:zho_x_variant":[
        "\u73e0\u6d0b"
    ],
    "wof:name":"Zhuyang",
    "wof:placetype":"locality"
},
  "geometry": {"coordinates":[118.67861000000001,26.58167000000001],"type":"Point"}
}