{
  "type": "Feature",
  "properties": {
    "gn:admin1_code":"16.0",
    "gn:asciiname":"Guili",
    "gn:country_code":"CN",
    "gn:dem":641,
    "gn:feature_class":"P",
    "gn:feature_code":"PPL",
    "gn:name":"Guili",
    "gn:population":0,
    "gn:timezone":"Asia/Shanghai",
    "iso:country":"CN",
    "name:zho_x_preferred":[
        "\u7688\u91cc"
    ],
    "wof:name":"Guili",
    "wof:placetype":"locality"
},
  "geometry": {"coordinates":[106.61199999999999,24.6679],"type":"Point"}
}