{
  "type": "Feature",
  "properties": {
    "gn:admin1_code":"10.0",
    "gn:asciiname":"Xiyangcheng",
    "gn:country_code":"CN",
    "gn:dem":1127,
    "gn:feature_class":"P",
    "gn:feature_code":"PPL",
    "gn:name":"Xiyangcheng",
    "gn:population":0,
    "gn:timezone":"Asia/Shanghai",
    "iso:country":"CN",
    "name:zho_x_preferred":[
        "\u897f\u9633\u57ce"
    ],
    "wof:name":"Xiyangcheng",
    "wof:placetype":"locality"
},
  "geometry": {"coordinates":[114.88254999999999,40.38177],"type":"Point"}
}