{
  "type": "Feature",
  "properties": {
    "gn:admin1_code":"32.0",
    "gn:asciiname":"Nimu",
    "gn:country_code":"CN",
    "gn:dem":3838,
    "gn:feature_class":"P",
    "gn:feature_code":"PPL",
    "gn:name":"Nimu",
    "gn:population":0,
    "gn:timezone":"Asia/Shanghai",
    "iso:country":"CN",
    "name:zho_x_preferred":[
        "\u5c3c\u6728"
    ],
    "wof:name":"Nimu",
    "wof:placetype":"locality"
},
  "geometry": {"coordinates":[98.74719,31.51249],"type":"Point"}
}