{
  "type": "Feature",
  "properties": {
    "gn:admin1_code":"1.0",
    "gn:asciiname":"Lichangcun",
    "gn:country_code":"CN",
    "gn:dem":28,
    "gn:feature_class":"P",
    "gn:feature_code":"PPL",
    "gn:name":"Lichangcun",
    "gn:population":0,
    "gn:timezone":"Asia/Shanghai",
    "iso:country":"CN",
    "name:und_x_variant":[
        "Lichang"
    ],
    "name:zho_x_preferred":[
        "\u674e\u573a\u6751"
    ],
    "wof:name":"Lichangcun",
    "wof:placetype":"locality"
},
  "geometry": {"coordinates":[117.44849000000001,33.9115],"type":"Point"}
}