{
  "type": "Feature",
  "properties": {
    "gn:admin1_code":"10.0",
    "gn:asciiname":"Zhaojiaquan",
    "gn:cc2":"CN",
    "gn:country_code":"CN",
    "gn:dem":24,
    "gn:feature_class":"P",
    "gn:feature_code":"PPL",
    "gn:name":"Zhaojiaquan",
    "gn:population":0,
    "gn:timezone":"Asia/Shanghai",
    "iso:country":"CN",
    "name:und_x_variant":[
        "Chao-chia-ch\u2019\u00fcan",
        "Zhaojiajuan",
        "Zhaojiaquan"
    ],
    "wof:name":"Zhaojiaquan",
    "wof:placetype":"locality"
},
  "geometry": {"coordinates":[115.50888999999999,37.73306],"type":"Point"}
}