{
  "type": "Feature",
  "properties": {
    "gn:admin1_code":"32.0",
    "gn:asciiname":"Jinyin'ao",
    "gn:country_code":"CN",
    "gn:dem":385,
    "gn:feature_class":"P",
    "gn:feature_code":"PPL",
    "gn:name":"Jinyin\u2019ao",
    "gn:population":0,
    "gn:timezone":"Asia/Shanghai",
    "iso:country":"CN",
    "name:zho_x_preferred":[
        "\u91d1\u94f6\u5773"
    ],
    "name:zho_x_variant":[
        "Jinyin\u2019ao"
    ],
    "wof:name":"Jinyin'ao",
    "wof:placetype":"locality"
},
  "geometry": {"coordinates":[105.35724,29.85312],"type":"Point"}
}