{
  "type": "Feature",
  "properties": {
    "gn:admin1_code":"02",
    "gn:asciiname":"Zhongcun",
    "gn:country_code":"CN",
    "gn:dem":8,
    "gn:feature_class":"P",
    "gn:feature_code":"PPL",
    "gn:name":"Zhongcun",
    "gn:population":0,
    "gn:timezone":"Asia/Shanghai",
    "iso:country":"CN",
    "name:und_x_variant":[
        "\u4e2d\u6751",
        "Zhongcun"
    ],
    "wof:name":"Zhongcun",
    "wof:placetype":"locality"
},
  "geometry": {"coordinates":[121.35791,28.64789],"type":"Point"}
}