{
  "type": "Feature",
  "properties": {
    "gn:admin1_code":"13",
    "gn:asciiname":"Kuowei",
    "gn:country_code":"CN",
    "gn:dem":1052,
    "gn:feature_class":"P",
    "gn:feature_code":"PPL",
    "gn:name":"Kuowei",
    "gn:population":0,
    "gn:timezone":"Asia/Shanghai",
    "iso:country":"CN",
    "name:und_x_variant":[
        "\u9614\u7ef4"
    ],
    "wof:name":"Kuowei",
    "wof:placetype":"locality"
},
  "geometry": {"coordinates":[80.28168000000002,40.69879],"type":"Point"}
}