{
  "type": "Feature",
  "properties": {
    "gn:admin1_code":"4.0",
    "gn:asciiname":"Wutang",
    "gn:country_code":"CN",
    "gn:dem":47,
    "gn:feature_class":"P",
    "gn:feature_code":"PPL",
    "gn:name":"Wutang",
    "gn:population":0,
    "gn:timezone":"Asia/Shanghai",
    "iso:country":"CN",
    "name:deu_x_preferred":[
        "Wudang"
    ],
    "name:eus_x_preferred":[
        "Wudang"
    ],
    "name:fra_x_preferred":[
        "Wudang"
    ],
    "name:swe_x_preferred":[
        "Wudang"
    ],
    "name:zho_x_preferred":[
        "\u4e94\u5858"
    ],
    "wof:name":"Wutang",
    "wof:placetype":"locality"
},
  "geometry": {"coordinates":[119.35939999999999,32.07066],"type":"Point"}
}