{
  "type": "Feature",
  "properties": {
    "gn:admin1_code":"7.0",
    "gn:asciiname":"Songbaigeng",
    "gn:country_code":"CN",
    "gn:dem":210,
    "gn:feature_class":"P",
    "gn:feature_code":"PPL",
    "gn:name":"Songbaigeng",
    "gn:population":0,
    "gn:timezone":"Asia/Shanghai",
    "iso:country":"CN",
    "name:zho_x_preferred":[
        "\u677e\u67cf\u57c2"
    ],
    "wof:name":"Songbaigeng",
    "wof:placetype":"locality"
},
  "geometry": {"coordinates":[118.04581,27.45605],"type":"Point"}
}