{
  "type": "Feature",
  "properties": {
    "gn:admin1_code":"7.0",
    "gn:asciiname":"Xiaji",
    "gn:country_code":"CN",
    "gn:dem":615,
    "gn:feature_class":"P",
    "gn:feature_code":"PPL",
    "gn:name":"Xiaji",
    "gn:population":0,
    "gn:timezone":"Asia/Shanghai",
    "iso:country":"CN",
    "name:zho_x_preferred":[
        "Xiaji"
    ],
    "name:zho_x_variant":[
        "\u4e0b\u9645"
    ],
    "wof:name":"Xiaji",
    "wof:placetype":"locality"
},
  "geometry": {"coordinates":[118.76167,26.80139],"type":"Point"}
}