{
  "type": "Feature",
  "properties": {
    "gn:admin1_code":"22",
    "gn:asciiname":"Fumazhuang",
    "gn:country_code":"CN",
    "gn:dem":51,
    "gn:feature_class":"P",
    "gn:feature_code":"PPL",
    "gn:name":"Fumazhuang",
    "gn:population":0,
    "gn:timezone":"Asia/Shanghai",
    "iso:country":"CN",
    "name:zho_x_preferred":[
        "\u9a78\u9a6c\u5e84"
    ],
    "wof:name":"Fumazhuang",
    "wof:placetype":"locality"
},
  "geometry": {"coordinates":[116.70872,40.32367],"type":"Point"}
}