{
  "type": "Feature",
  "properties": {
    "gn:admin1_code":"33.0",
    "gn:asciiname":"Shangzhichang",
    "gn:country_code":"CN",
    "gn:dem":638,
    "gn:feature_class":"P",
    "gn:feature_code":"PPL",
    "gn:name":"Shangzhichang",
    "gn:population":0,
    "gn:timezone":"Asia/Shanghai",
    "iso:country":"CN",
    "name:zho_x_preferred":[
        "\u4e0a\u7eb8\u5382"
    ],
    "wof:name":"Shangzhichang",
    "wof:placetype":"locality"
},
  "geometry": {"coordinates":[108.67983,28.8887],"type":"Point"}
}