{
  "type": "Feature",
  "properties": {
    "gn:admin1_code":"29",
    "gn:asciiname":"Ajian",
    "gn:country_code":"CN",
    "gn:dem":1928,
    "gn:feature_class":"P",
    "gn:feature_code":"PPL",
    "gn:name":"Ajian",
    "gn:population":0,
    "gn:timezone":"Asia/Shanghai",
    "iso:country":"CN",
    "name:zho_x_preferred":[
        "\u963f\u5c16"
    ],
    "wof:name":"Ajian",
    "wof:placetype":"locality"
},
  "geometry": {"coordinates":[103.044,24.4964],"type":"Point"}
}