{
  "type": "Feature",
  "properties": {
    "gn:admin1_code":"9",
    "gn:asciiname":"Liwangzhuang",
    "gn:country_code":"CN",
    "gn:dem":38,
    "gn:feature_class":"P",
    "gn:feature_code":"PPL",
    "gn:name":"Liwangzhuang",
    "gn:population":0,
    "gn:timezone":"Asia/Shanghai",
    "iso:country":"CN",
    "name:zho_x_preferred":[
        "\u674e\u738b\u5e84"
    ],
    "wof:name":"Liwangzhuang",
    "wof:placetype":"locality"
},
  "geometry": {"coordinates":[116.179,34.1691],"type":"Point"}
}