{
  "type": "Feature",
  "properties": {
    "gn:admin1_code":"3.0",
    "gn:asciiname":"Gangshang Jiangjia",
    "gn:country_code":"CN",
    "gn:dem":36,
    "gn:feature_class":"P",
    "gn:feature_code":"PPL",
    "gn:name":"Gangshang Jiangjia",
    "gn:population":0,
    "gn:timezone":"Asia/Shanghai",
    "iso:country":"CN",
    "name:zho_x_preferred":[
        "\u5c97\u4e0a\u59dc\u5bb6"
    ],
    "wof:name":"Gangshang Jiangjia",
    "wof:placetype":"locality"
},
  "geometry": {"coordinates":[117.01600000000001,28.2808],"type":"Point"}
}