{
  "type": "Feature",
  "properties": {
    "gn:admin1_code":"9",
    "gn:asciiname":"Heilisi",
    "gn:country_code":"CN",
    "gn:dem":53,
    "gn:feature_class":"P",
    "gn:feature_code":"PPL",
    "gn:name":"Heilisi",
    "gn:population":0,
    "gn:timezone":"Asia/Shanghai",
    "iso:country":"CN",
    "name:zho_x_preferred":[
        "\u9ed1\u91cc\u5bfa"
    ],
    "wof:name":"Heilisi",
    "wof:placetype":"locality"
},
  "geometry": {"coordinates":[115.128,34.1112],"type":"Point"}
}