{
  "type": "Feature",
  "properties": {
    "gn:admin1_code":"31.0",
    "gn:asciiname":"Shanglitian",
    "gn:country_code":"CN",
    "gn:dem":27,
    "gn:feature_class":"P",
    "gn:feature_code":"PPL",
    "gn:name":"Shanglitian",
    "gn:population":0,
    "gn:timezone":"Asia/Shanghai",
    "iso:country":"CN",
    "name:und_x_variant":[
        "\u4e0a\u91cc\u7530"
    ],
    "wof:name":"Shanglitian",
    "wof:placetype":"locality"
},
  "geometry": {"coordinates":[109.64458,18.33405],"type":"Point"}
}