{
  "type": "Feature",
  "properties": {
    "gn:admin1_code":"19.0",
    "gn:asciiname":"Dazhangjiagou",
    "gn:country_code":"CN",
    "gn:dem":50,
    "gn:feature_class":"P",
    "gn:feature_code":"PPL",
    "gn:name":"Dazhangjiagou",
    "gn:population":0,
    "gn:timezone":"Asia/Shanghai",
    "iso:country":"CN",
    "name:und_x_variant":[
        "\u5927\u5f20\u5bb6\u6c9f"
    ],
    "name:zho_x_preferred":[
        "\u5927\u5f20\u5bb6\u6c9f"
    ],
    "wof:name":"Dazhangjiagou",
    "wof:placetype":"locality"
},
  "geometry": {"coordinates":[122.02736000000002,39.3225],"type":"Point"}
}