{
  "type": "Feature",
  "properties": {
    "gn:admin1_code":"10",
    "gn:asciiname":"Mahatu",
    "gn:country_code":"CN",
    "gn:dem":1147,
    "gn:feature_class":"P",
    "gn:feature_code":"PPL",
    "gn:name":"Mahatu",
    "gn:population":0,
    "gn:timezone":"Asia/Shanghai",
    "iso:country":"CN",
    "name:zho_x_preferred":[
        "\u5417\u54c8\u5410"
    ],
    "wof:name":"Mahatu",
    "wof:placetype":"locality"
},
  "geometry": {"coordinates":[117.41386,42.03556],"type":"Point"}
}