{
  "type": "Feature",
  "properties": {
    "gn:admin1_code":"8.0",
    "gn:asciiname":"Zhangxiangtun",
    "gn:country_code":"CN",
    "gn:dem":162,
    "gn:feature_class":"P",
    "gn:feature_code":"PPL",
    "gn:name":"Zhangxiangtun",
    "gn:population":0,
    "gn:timezone":"Asia/Shanghai",
    "iso:country":"CN",
    "name:zho_x_preferred":[
        "\u5f20\u7965\u5c6f"
    ],
    "wof:name":"Zhangxiangtun",
    "wof:placetype":"locality"
},
  "geometry": {"coordinates":[127.16126,45.88003],"type":"Point"}
}