{
  "type": "Feature",
  "properties": {
    "gn:admin1_code":"16.0",
    "gn:asciiname":"Cenbao",
    "gn:country_code":"CN",
    "gn:dem":555,
    "gn:feature_class":"P",
    "gn:feature_code":"PPL",
    "gn:name":"Cenbao",
    "gn:population":0,
    "gn:timezone":"Asia/Shanghai",
    "iso:country":"CN",
    "name:zho_x_preferred":[
        "\u5c91\u62a5"
    ],
    "wof:name":"Cenbao",
    "wof:placetype":"locality"
},
  "geometry": {"coordinates":[108.90900000000001,25.5115],"type":"Point"}
}