{
  "type": "Feature",
  "properties": {
    "gn:admin1_code":"26.0",
    "gn:asciiname":"Guojiacao",
    "gn:country_code":"CN",
    "gn:dem":1434,
    "gn:feature_class":"P",
    "gn:feature_code":"PPL",
    "gn:name":"Guojiacao",
    "gn:population":0,
    "gn:timezone":"Asia/Shanghai",
    "iso:country":"CN",
    "name:zho_x_preferred":[
        "\u90ed\u5bb6\u69fd"
    ],
    "wof:name":"Guojiacao",
    "wof:placetype":"locality"
},
  "geometry": {"coordinates":[106.75149,35.06212],"type":"Point"}
}