{
  "type": "Feature",
  "properties": {
    "gn:admin1_code":"26.0",
    "gn:asciiname":"Zhenjicun",
    "gn:country_code":"CN",
    "gn:dem":673,
    "gn:feature_class":"P",
    "gn:feature_code":"PPL",
    "gn:name":"Zhenjicun",
    "gn:population":0,
    "gn:timezone":"Asia/Shanghai",
    "iso:country":"CN",
    "name:zho_x_preferred":[
        "\u9547\u57fa\u6751"
    ],
    "wof:name":"Zhenjicun",
    "wof:placetype":"locality"
},
  "geometry": {"coordinates":[109.90904999999999,35.14847],"type":"Point"}
}