{
  "type": "Feature",
  "properties": {
    "gn:admin1_code":"1.0",
    "gn:asciiname":"Wangshencun",
    "gn:country_code":"CN",
    "gn:dem":67,
    "gn:feature_class":"P",
    "gn:feature_code":"PPL",
    "gn:name":"Wangshencun",
    "gn:population":0,
    "gn:timezone":"Asia/Shanghai",
    "iso:country":"CN",
    "name:zho_x_preferred":[
        "\u6c6a\u795e\u6751"
    ],
    "wof:name":"Wangshencun",
    "wof:placetype":"locality"
},
  "geometry": {"coordinates":[116.47161,31.58281],"type":"Point"}
}