{
  "type": "Feature",
  "properties": {
    "gn:admin1_code":"19.0",
    "gn:asciiname":"Huangqibucun",
    "gn:country_code":"CN",
    "gn:dem":17,
    "gn:feature_class":"P",
    "gn:feature_code":"PPL",
    "gn:name":"Huangqibucun",
    "gn:population":0,
    "gn:timezone":"Asia/Shanghai",
    "iso:country":"CN",
    "name:zho_x_preferred":[
        "\u9ec4\u65d7\u5821\u6751"
    ],
    "wof:name":"Huangqibucun",
    "wof:placetype":"locality"
},
  "geometry": {"coordinates":[122.82256,41.58052],"type":"Point"}
}