{
  "type": "Feature",
  "properties": {
    "gn:admin1_code":"32.0",
    "gn:asciiname":"Dongjiang",
    "gn:country_code":"CN",
    "gn:dem":3733,
    "gn:feature_class":"P",
    "gn:feature_code":"PPL",
    "gn:name":"Dongjiang",
    "gn:population":0,
    "gn:timezone":"Asia/Shanghai",
    "iso:country":"CN",
    "name:zho_x_preferred":[
        "\u4e1c\u6c5f"
    ],
    "wof:name":"Dongjiang",
    "wof:placetype":"locality"
},
  "geometry": {"coordinates":[99.03106,30.83661],"type":"Point"}
}