{
  "type": "Feature",
  "properties": {
    "gn:admin1_code":"19.0",
    "gn:asciiname":"Dongtianjiafangshen",
    "gn:country_code":"CN",
    "gn:dem":14,
    "gn:feature_class":"P",
    "gn:feature_code":"PPL",
    "gn:name":"Dongtianjiafangshen",
    "gn:population":0,
    "gn:timezone":"Asia/Shanghai",
    "iso:country":"CN",
    "name:und_x_variant":[
        "\u4e1c\u7530\u5bb6\u623f\u8eab"
    ],
    "name:zho_x_preferred":[
        "\u4e1c\u7530\u5bb6\u623f\u8eab"
    ],
    "wof:name":"Dongtianjiafangshen",
    "wof:placetype":"locality"
},
  "geometry": {"coordinates":[121.66925999999999,39.19458],"type":"Point"}
}