{
  "type": "Feature",
  "properties": {
    "gn:admin1_code":"30",
    "gn:asciiname":"Sanjia",
    "gn:country_code":"CN",
    "gn:dem":792,
    "gn:feature_class":"P",
    "gn:feature_code":"PPL",
    "gn:name":"Sanjia",
    "gn:population":0,
    "gn:timezone":"Asia/Urumqi",
    "iso:country":"CN",
    "name:ceb_x_preferred":[
        "Sanjia"
    ],
    "name:swe_x_preferred":[
        "Sanjia"
    ],
    "wof:name":"Sanjia",
    "wof:placetype":"locality"
},
  "geometry": {"coordinates":[111.41443999999998,21.83444],"type":"Point"}
}