{
  "type": "Feature",
  "properties": {
    "gn:admin1_code":"7.0",
    "gn:asciiname":"Shiyang",
    "gn:country_code":"CN",
    "gn:dem":563,
    "gn:feature_class":"P",
    "gn:feature_code":"PPL",
    "gn:name":"Shiyang",
    "gn:population":0,
    "gn:timezone":"Asia/Shanghai",
    "iso:country":"CN",
    "name:zho_x_preferred":[
        "\u72ee\u6d0b"
    ],
    "wof:name":"Shiyang",
    "wof:placetype":"locality"
},
  "geometry": {"coordinates":[118.81185000000001,25.58791],"type":"Point"}
}