{
  "type": "Feature",
  "properties": {
    "gn:admin1_code":"30.0",
    "gn:asciiname":"Guanglizui",
    "gn:country_code":"CN",
    "gn:dem":169,
    "gn:feature_class":"P",
    "gn:feature_code":"PPL",
    "gn:name":"Guanglizui",
    "gn:population":0,
    "gn:timezone":"Asia/Shanghai",
    "iso:country":"CN",
    "name:zho_x_preferred":[
        "Guanglizui"
    ],
    "name:zho_x_variant":[
        "\u5149\u91cc\u5480"
    ],
    "wof:name":"Guanglizui",
    "wof:placetype":"locality"
},
  "geometry": {"coordinates":[115.03194000000001,24.42472],"type":"Point"}
}