{
  "type": "Feature",
  "properties": {
    "gn:admin1_code":"2.0",
    "gn:asciiname":"Anling",
    "gn:country_code":"CN",
    "gn:dem":447,
    "gn:feature_class":"P",
    "gn:feature_code":"PPLA4",
    "gn:name":"Anling",
    "gn:population":0,
    "gn:timezone":"Asia/Shanghai",
    "iso:country":"CN",
    "name:und_x_variant":[
        "Anling Xiang",
        "Shangmenlou"
    ],
    "name:zho_x_preferred":[
        "\u5b89\u5cad"
    ],
    "name:zho_x_variant":[
        "\u5b89\u5cad\u4e61",
        "\u4e0a\u95e8\u697c"
    ],
    "wof:name":"Anling",
    "wof:placetype":"locality"
},
  "geometry": {"coordinates":[120.34763999999998,28.56463],"type":"Point"}
}