{
  "type": "Feature",
  "properties": {
    "gn:admin1_code":"24.0",
    "gn:asciiname":"Taizicun",
    "gn:country_code":"CN",
    "gn:dem":1411,
    "gn:feature_class":"P",
    "gn:feature_code":"PPL",
    "gn:name":"Taizicun",
    "gn:population":0,
    "gn:timezone":"Asia/Shanghai",
    "iso:country":"CN",
    "name:zho_x_preferred":[
        "\u53f0\u5b50\u6751"
    ],
    "wof:name":"Taizicun",
    "wof:placetype":"locality"
},
  "geometry": {"coordinates":[112.23895,39.86985],"type":"Point"}
}