{
  "type": "Feature",
  "properties": {
    "gn:admin1_code":"9.0",
    "gn:asciiname":"Niejiaying",
    "gn:country_code":"CN",
    "gn:dem":71,
    "gn:feature_class":"P",
    "gn:feature_code":"PPL",
    "gn:name":"Niejiaying",
    "gn:population":0,
    "gn:timezone":"Asia/Shanghai",
    "iso:country":"CN",
    "name:zho_x_preferred":[
        "\u8042\u5bb6\u8425"
    ],
    "wof:name":"Niejiaying",
    "wof:placetype":"locality"
},
  "geometry": {"coordinates":[114.45876,35.27489],"type":"Point"}
}