{
  "type": "Feature",
  "properties": {
    "gn:admin1_code":"30.0",
    "gn:asciiname":"Shuguiling",
    "gn:country_code":"CN",
    "gn:dem":574,
    "gn:feature_class":"P",
    "gn:feature_code":"PPL",
    "gn:name":"Shuguiling",
    "gn:population":0,
    "gn:timezone":"Asia/Shanghai",
    "iso:country":"CN",
    "name:zho_x_preferred":[
        "\u4e66\u67dc\u5cad"
    ],
    "wof:name":"Shuguiling",
    "wof:placetype":"locality"
},
  "geometry": {"coordinates":[113.94616000000001,25.04336],"type":"Point"}
}