{
  "type": "Feature",
  "properties": {
    "gn:admin1_code":"29.0",
    "gn:asciiname":"Shijikuai",
    "gn:country_code":"CN",
    "gn:dem":2204,
    "gn:feature_class":"P",
    "gn:feature_code":"PPL",
    "gn:name":"Shijikuai",
    "gn:population":0,
    "gn:timezone":"Asia/Shanghai",
    "iso:country":"CN",
    "name:zho_x_preferred":[
        "\u65bd\u6d4e\u5757"
    ],
    "wof:name":"Shijikuai",
    "wof:placetype":"locality"
},
  "geometry": {"coordinates":[102.765,25.8371],"type":"Point"}
}