{
  "type": "Feature",
  "properties": {
    "gn:admin1_code":"9.0",
    "gn:asciiname":"Houxianchi",
    "gn:country_code":"CN",
    "gn:dem":803,
    "gn:feature_class":"P",
    "gn:feature_code":"PPL",
    "gn:name":"Houxianchi",
    "gn:population":0,
    "gn:timezone":"Asia/Shanghai",
    "iso:country":"CN",
    "name:zho_x_preferred":[
        "\u540e\u54b8\u6c60"
    ],
    "wof:name":"Houxianchi",
    "wof:placetype":"locality"
},
  "geometry": {"coordinates":[111.75379,33.76498],"type":"Point"}
}