{
  "type": "Feature",
  "properties": {
    "gn:admin1_code":"1.0",
    "gn:asciiname":"Guomiaocun",
    "gn:country_code":"CN",
    "gn:dem":34,
    "gn:feature_class":"P",
    "gn:feature_code":"PPL",
    "gn:name":"Guomiaocun",
    "gn:population":0,
    "gn:timezone":"Asia/Shanghai",
    "iso:country":"CN",
    "name:zho_x_preferred":[
        "\u90ed\u5e99\u6751"
    ],
    "wof:name":"Guomiaocun",
    "wof:placetype":"locality"
},
  "geometry": {"coordinates":[115.79510999999999,33.2511],"type":"Point"}
}