{
  "type": "Feature",
  "properties": {
    "gn:admin1_code":"4.0",
    "gn:asciiname":"Tonghai",
    "gn:country_code":"CN",
    "gn:dem":3,
    "gn:feature_class":"P",
    "gn:feature_code":"PPL",
    "gn:name":"Tonghai",
    "gn:population":0,
    "gn:timezone":"Asia/Shanghai",
    "iso:country":"CN",
    "name:und_x_variant":[
        "\u901a\u6d77"
    ],
    "wof:name":"Tonghai",
    "wof:placetype":"locality"
},
  "geometry": {"coordinates":[121.42028000000001,32.02239],"type":"Point"}
}