{
  "type": "Feature",
  "properties": {
    "gn:admin1_code":"4.0",
    "gn:asciiname":"Bangqun",
    "gn:country_code":"CN",
    "gn:dem":3,
    "gn:feature_class":"P",
    "gn:feature_code":"PPL",
    "gn:name":"Bangqun",
    "gn:population":0,
    "gn:timezone":"Asia/Shanghai",
    "iso:country":"CN",
    "name:zho_x_preferred":[
        "Bangqun"
    ],
    "name:zho_x_variant":[
        "\u5e2e\u7fa4"
    ],
    "wof:name":"Bangqun",
    "wof:placetype":"locality"
},
  "geometry": {"coordinates":[121.85236,31.69275],"type":"Point"}
}