{
  "type": "Feature",
  "properties": {
    "gn:admin1_code":"14.0",
    "gn:asciiname":"Chading",
    "gn:country_code":"CN",
    "gn:dem":3718,
    "gn:feature_class":"P",
    "gn:feature_code":"PPL",
    "gn:name":"Chading",
    "gn:population":0,
    "gn:timezone":"Asia/Urumqi",
    "iso:country":"CN",
    "name:zho_x_preferred":[
        "\u67e5\u5b9a"
    ],
    "wof:name":"Chading",
    "wof:placetype":"locality"
},
  "geometry": {"coordinates":[97.98041000000001,29.4032],"type":"Point"}
}