{
  "type": "Feature",
  "properties": {
    "gn:admin1_code":"24.0",
    "gn:asciiname":"Xiaodaibu",
    "gn:country_code":"CN",
    "gn:dem":1056,
    "gn:feature_class":"P",
    "gn:feature_code":"PPL",
    "gn:name":"Xiaodaibu",
    "gn:population":0,
    "gn:timezone":"Asia/Shanghai",
    "iso:country":"CN",
    "name:und_x_variant":[
        "\u5c0f\u5cb1\u5821"
    ],
    "name:zho_x_preferred":[
        "\u5c0f\u5cb1\u5821"
    ],
    "wof:name":"Xiaodaibu",
    "wof:placetype":"locality"
},
  "geometry": {"coordinates":[112.60853,39.22955],"type":"Point"}
}