{
  "type": "Feature",
  "properties": {
    "gn:admin1_code":"12.0",
    "gn:asciiname":"Dongshanping",
    "gn:country_code":"CN",
    "gn:dem":540,
    "gn:feature_class":"P",
    "gn:feature_code":"PPL",
    "gn:name":"Dongshanping",
    "gn:population":0,
    "gn:timezone":"Asia/Shanghai",
    "iso:country":"CN",
    "name:zho_x_preferred":[
        "\u4e1c\u5c71\u576a"
    ],
    "wof:name":"Dongshanping",
    "wof:placetype":"locality"
},
  "geometry": {"coordinates":[115.755,30.58882],"type":"Point"}
}