{
  "type": "Feature",
  "properties": {
    "gn:admin1_code":"29.0",
    "gn:asciiname":"Yusandi",
    "gn:country_code":"CN",
    "gn:dem":2136,
    "gn:feature_class":"P",
    "gn:feature_code":"PPL",
    "gn:name":"Yusandi",
    "gn:population":0,
    "gn:timezone":"Asia/Shanghai",
    "iso:country":"CN",
    "name:zho_x_preferred":[
        "\u4f59\u4e09\u5730"
    ],
    "wof:name":"Yusandi",
    "wof:placetype":"locality"
},
  "geometry": {"coordinates":[98.9111,24.5866],"type":"Point"}
}