{
  "type": "Feature",
  "properties": {
    "gn:admin1_code":"25",
    "gn:asciiname":"Xilujialin",
    "gn:country_code":"CN",
    "gn:dem":118,
    "gn:feature_class":"P",
    "gn:feature_code":"PPL",
    "gn:name":"Xilujialin",
    "gn:population":0,
    "gn:timezone":"Asia/Shanghai",
    "iso:country":"CN",
    "name:zho_x_preferred":[
        "\u897f\u82a6\u5bb6\u6797"
    ],
    "wof:name":"Xilujialin",
    "wof:placetype":"locality"
},
  "geometry": {"coordinates":[118.88500000000001,35.1872],"type":"Point"}
}