{
  "type": "Feature",
  "properties": {
    "iso:country":"CN",
    "name:deu_x_preferred":[
        "Luan"
    ],
    "name:fra_x_preferred":[
        "Luan"
    ],
    "name:ita_x_preferred":[
        "Luan"
    ],
    "name:nor_x_preferred":[
        "Luan"
    ],
    "name:por_x_preferred":[
        "Luan"
    ],
    "name:swe_x_preferred":[
        "Luan"
    ],
    "ne:ADM0CAP":0.0,
    "ne:ADM0NAME":"China",
    "ne:ADM0_A3":"CHN",
    "ne:ADM1NAME":"Anhui",
    "ne:ADMIN1_COD":0,
    "ne:CAPALT":0,
    "ne:CHANGED":0,
    "ne:CHECKME":0,
    "ne:COMPARE":0,
    "ne:DIFFASCII":0,
    "ne:ELEVATION":0.0,
    "ne:FEATURECLA":"Populated place",
    "ne:GEONAMEID":1802206,
    "ne:GEONAMESNO":"Manual GeoNames match, this large town missing from populated place export.",
    "ne:GN_POP":0,
    "ne:GTOPO30":0.0,
    "ne:ISO_A2":"CN",
    "ne:LABELRANK":1,
    "ne:LATITUDE":31.750348,
    "ne:LONGITUDE":116.480011,
    "ne:LS_MATCH":1,
    "ne:LS_NAME":"Luan",
    "ne:MAX_AREAKM":874.0,
    "ne:MAX_AREAMI":338.0,
    "ne:MAX_BBXMAX":116.846646,
    "ne:MAX_BBXMIN":116.408333,
    "ne:MAX_BBYMAX":32.353791,
    "ne:MAX_BBYMIN":31.441667,
    "ne:MAX_NATSCA":20.0,
    "ne:MAX_PERKM":1237.0,
    "ne:MAX_PERMI":769.0,
    "ne:MAX_POP10":1126455,
    "ne:MAX_POP20":1126455,
    "ne:MAX_POP300":0,
    "ne:MAX_POP310":0,
    "ne:MAX_POP50":0,
    "ne:MEAN_BBXC":116.606534,
    "ne:MEAN_BBYC":31.846699,
    "ne:MEGACITY":1,
    "ne:MEGANAME":"Liuan",
    "ne:MIN_AREAKM":874.0,
    "ne:MIN_AREAMI":338.0,
    "ne:MIN_BBXMAX":116.846646,
    "ne:MIN_BBXMIN":116.408333,
    "ne:MIN_BBYMAX":32.353791,
    "ne:MIN_BBYMIN":31.441667,
    "ne:MIN_PERKM":1237.0,
    "ne:MIN_PERMI":769.0,
    "ne:NAME":"Luan",
    "ne:NAMEALT":"Liuan",
    "ne:NAMEASCII":"Luan",
    "ne:NAMEDIFF":0,
    "ne:NATSCALE":30,
    "ne:POP1950":861,
    "ne:POP1955":914,
    "ne:POP1960":969,
    "ne:POP1965":1028,
    "ne:POP1970":1090,
    "ne:POP1975":1157,
    "ne:POP1980":1227,
    "ne:POP1985":1301,
    "ne:POP1990":1380,
    "ne:POP1995":1464,
    "ne:POP2000":1553,
    "ne:POP2005":1647,
    "ne:POP2010":1690,
    "ne:POP2015":1771,
    "ne:POP2020":1946,
    "ne:POP2025":2120,
    "ne:POP2050":2263,
    "ne:POP_MAX":1690000,
    "ne:POP_MIN":1126455,
    "ne:POP_OTHER":1734491,
    "ne:RANK_MAX":12,
    "ne:RANK_MIN":12,
    "ne:SCALERANK":6,
    "ne:SOV0NAME":"China",
    "ne:SOV_A3":"CHN",
    "ne:UN_ADM0":"China",
    "ne:UN_FID":77,
    "ne:UN_LAT":31.73,
    "ne:UN_LONG":116.46,
    "ne:WORLDCITY":0,
    "ne:min_zoom":6.0,
    "wof:name":"Luan",
    "wof:placetype":"locality"
},
  "geometry": {"coordinates":[116.47806549297775,31.75229337145186],"type":"Point"}
}