{
  "type": "Feature",
  "properties": {
    "gn:admin1_code":"26.0",
    "gn:asciiname":"Erdishaocun",
    "gn:country_code":"CN",
    "gn:dem":1173,
    "gn:feature_class":"P",
    "gn:feature_code":"PPL",
    "gn:name":"Erdishaocun",
    "gn:population":0,
    "gn:timezone":"Asia/Shanghai",
    "iso:country":"CN",
    "name:zho_x_preferred":[
        "\u4e8c\u6ef4\u54e8\u6751"
    ],
    "wof:name":"Erdishaocun",
    "wof:placetype":"locality"
},
  "geometry": {"coordinates":[109.59233,37.45425],"type":"Point"}
}