{
  "type": "Feature",
  "properties": {
    "gn:admin1_code":"19.0",
    "gn:asciiname":"Shuangjingzicun",
    "gn:country_code":"CN",
    "gn:dem":6,
    "gn:feature_class":"P",
    "gn:feature_code":"PPL",
    "gn:name":"Shuangjingzicun",
    "gn:population":0,
    "gn:timezone":"Asia/Shanghai",
    "iso:country":"CN",
    "name:zho_x_preferred":[
        "\u53cc\u4e95\u5b50\u6751"
    ],
    "wof:name":"Shuangjingzicun",
    "wof:placetype":"locality"
},
  "geometry": {"coordinates":[122.55773000000001,40.74385],"type":"Point"}
}