{
  "type": "Feature",
  "properties": {
    "gn:admin1_code":"25.0",
    "gn:asciiname":"Mulicun",
    "gn:country_code":"CN",
    "gn:dem":32,
    "gn:feature_class":"P",
    "gn:feature_code":"PPL",
    "gn:name":"Mulicun",
    "gn:population":0,
    "gn:timezone":"Asia/Shanghai",
    "iso:country":"CN",
    "name:zho_x_preferred":[
        "\u7766\u91cc\u6751"
    ],
    "wof:name":"Mulicun",
    "wof:placetype":"locality"
},
  "geometry": {"coordinates":[116.83255,36.66533],"type":"Point"}
}