{
  "type": "Feature",
  "properties": {
    "gn:admin1_code":"26.0",
    "gn:asciiname":"Banfangou",
    "gn:country_code":"CN",
    "gn:dem":1924,
    "gn:feature_class":"P",
    "gn:feature_code":"PPL",
    "gn:name":"Banfangou",
    "gn:population":0,
    "gn:timezone":"Asia/Shanghai",
    "iso:country":"CN",
    "name:und_x_variant":[
        "\u677f\u756a\u6c9f"
    ],
    "wof:name":"Banfangou",
    "wof:placetype":"locality"
},
  "geometry": {"coordinates":[107.37228,34.13088],"type":"Point"}
}