{
  "type": "Feature",
  "properties": {
    "gn:admin1_code":"3.0",
    "gn:asciiname":"Citang Jiangjia",
    "gn:country_code":"CN",
    "gn:dem":47,
    "gn:feature_class":"P",
    "gn:feature_code":"PPL",
    "gn:name":"Citang Jiangjia",
    "gn:population":0,
    "gn:timezone":"Asia/Shanghai",
    "iso:country":"CN",
    "name:zho_x_preferred":[
        "\u7960\u5802\u6c5f\u5bb6"
    ],
    "wof:name":"Citang Jiangjia",
    "wof:placetype":"locality"
},
  "geometry": {"coordinates":[117.41500000000001,28.3946],"type":"Point"}
}