{
  "type": "Feature",
  "properties": {
    "gn:admin1_code":"15.0",
    "gn:asciiname":"Gaochang",
    "gn:country_code":"CN",
    "gn:dem":1835,
    "gn:feature_class":"P",
    "gn:feature_code":"PPL",
    "gn:name":"Gaochang",
    "gn:population":0,
    "gn:timezone":"Asia/Shanghai",
    "iso:country":"CN",
    "name:aze_x_preferred":[
        "Qaraxoca"
    ],
    "name:bul_x_preferred":[
        "\u041a\u043e\u0447\u043e"
    ],
    "name:cat_x_preferred":[
        "Gaochang"
    ],
    "name:deu_x_preferred":[
        "Kocho"
    ],
    "name:fas_x_preferred":[
        "\u0642\u0631\u0647\u200c\u062e\u0648\u0627\u062c\u0647"
    ],
    "name:fra_x_preferred":[
        "Gaochang"
    ],
    "name:ind_x_preferred":[
        "Gaochang"
    ],
    "name:ita_x_preferred":[
        "Gaochang"
    ],
    "name:kir_x_preferred":[
        "\u0413\u0430\u043e\u0447\u0430\u043d"
    ],
    "name:kor_x_preferred":[
        "\uace0\ucc3d"
    ],
    "name:lit_x_preferred":[
        "Gao\u010dangas"
    ],
    "name:nor_x_preferred":[
        "Gaochang"
    ],
    "name:pol_x_preferred":[
        "Gaochang"
    ],
    "name:rus_x_preferred":[
        "\u0413\u0430\u043e\u0447\u0430\u043d"
    ],
    "name:tur_x_preferred":[
        "Karahoca"
    ],
    "name:uig_x_preferred":[
        "\u0642\u0626\u0627\u0631\u0626\u0627\u0647\u0648\u062c\u0626\u0627"
    ],
    "name:ukr_x_preferred":[
        "\u0413\u0430\u043e\u0447\u0430\u043d"
    ],
    "name:vie_x_preferred":[
        "Cao X\u01b0\u01a1ng"
    ],
    "name:zho_x_preferred":[
        "\u9ad8\u573a"
    ],
    "wof:name":"Gaochang",
    "wof:placetype":"locality"
},
  "geometry": {"coordinates":[103.373,36.4619],"type":"Point"}
}