{
  "type": "Feature",
  "properties": {
    "gn:admin1_code":"33.0",
    "gn:asciiname":"Shitiba",
    "gn:country_code":"CN",
    "gn:dem":769,
    "gn:feature_class":"P",
    "gn:feature_code":"PPL",
    "gn:name":"Shitiba",
    "gn:population":0,
    "gn:timezone":"Asia/Shanghai",
    "iso:country":"CN",
    "name:zho_x_preferred":[
        "\u77f3\u68af\u575d"
    ],
    "wof:name":"Shitiba",
    "wof:placetype":"locality"
},
  "geometry": {"coordinates":[108.51226,28.91404],"type":"Point"}
}