{
  "type": "Feature",
  "properties": {
    "gn:admin1_code":"25",
    "gn:asciiname":"Zhangjiayang",
    "gn:country_code":"CN",
    "gn:dem":55,
    "gn:feature_class":"P",
    "gn:feature_code":"PPL",
    "gn:name":"Zhangjiayang",
    "gn:population":0,
    "gn:timezone":"Asia/Shanghai",
    "iso:country":"CN",
    "name:zho_x_preferred":[
        "\u5f20\u5bb6\u7f8a"
    ],
    "wof:name":"Zhangjiayang",
    "wof:placetype":"locality"
},
  "geometry": {"coordinates":[118.694,36.6735],"type":"Point"}
}