{
  "type": "Feature",
  "properties": {
    "gn:admin1_code":"26.0",
    "gn:asciiname":"Yanjia Pancun",
    "gn:country_code":"CN",
    "gn:dem":1137,
    "gn:feature_class":"P",
    "gn:feature_code":"PPL",
    "gn:name":"Yanjia Pancun",
    "gn:population":0,
    "gn:timezone":"Asia/Shanghai",
    "iso:country":"CN",
    "name:zho_x_preferred":[
        "\u95eb\u5bb6\u7554\u6751"
    ],
    "wof:name":"Yanjia Pancun",
    "wof:placetype":"locality"
},
  "geometry": {"coordinates":[109.98699999999999,37.7211],"type":"Point"}
}