{
  "type": "Feature",
  "properties": {
    "gn:admin1_code":"8.0",
    "gn:asciiname":"Hengshengcun",
    "gn:country_code":"CN",
    "gn:dem":198,
    "gn:feature_class":"P",
    "gn:feature_code":"PPL",
    "gn:name":"Hengshengcun",
    "gn:population":0,
    "gn:timezone":"Asia/Shanghai",
    "iso:country":"CN",
    "name:zho_x_preferred":[
        "\u6052\u751f\u6751"
    ],
    "wof:name":"Hengshengcun",
    "wof:placetype":"locality"
},
  "geometry": {"coordinates":[126.16813,46.97187],"type":"Point"}
}