{
  "type": "Feature",
  "properties": {
    "gn:admin1_code":"1.0",
    "gn:asciiname":"Fenghucun",
    "gn:country_code":"CN",
    "gn:dem":23,
    "gn:feature_class":"P",
    "gn:feature_code":"PPL",
    "gn:name":"Fenghucun",
    "gn:population":0,
    "gn:timezone":"Asia/Shanghai",
    "iso:country":"CN",
    "name:zho_x_preferred":[
        "\u6ca3\u6e56\u6751"
    ],
    "wof:name":"Fenghucun",
    "wof:placetype":"locality"
},
  "geometry": {"coordinates":[116.07583,32.44609000000001],"type":"Point"}
}