{
  "type": "Feature",
  "properties": {
    "gn:admin1_code":"29",
    "gn:asciiname":"Hongshiyan",
    "gn:country_code":"CN",
    "gn:dem":1304,
    "gn:feature_class":"P",
    "gn:feature_code":"PPL",
    "gn:name":"Hongshiyan",
    "gn:population":0,
    "gn:timezone":"Asia/Shanghai",
    "iso:country":"CN",
    "name:zho_x_preferred":[
        "\u7ea2\u77f3\u5ca9"
    ],
    "wof:name":"Hongshiyan",
    "wof:placetype":"locality"
},
  "geometry": {"coordinates":[103.069,24.1869],"type":"Point"}
}