{
  "type": "Feature",
  "properties": {
    "gn:admin1_code":"24.0",
    "gn:asciiname":"Haiziwan",
    "gn:country_code":"CN",
    "gn:dem":1275,
    "gn:feature_class":"P",
    "gn:feature_code":"PPL",
    "gn:name":"Haiziwan",
    "gn:population":0,
    "gn:timezone":"Asia/Shanghai",
    "iso:country":"CN",
    "name:zho_x_preferred":[
        "\u6d77\u5b50\u6e7e"
    ],
    "wof:name":"Haiziwan",
    "wof:placetype":"locality"
},
  "geometry": {"coordinates":[112.30817999999999,40.21631],"type":"Point"}
}