{
  "type": "Feature",
  "properties": {
    "gn:admin1_code":"25",
    "gn:asciiname":"Denggezhuang",
    "gn:country_code":"CN",
    "gn:dem":147,
    "gn:feature_class":"P",
    "gn:feature_code":"PPL",
    "gn:name":"Denggezhuang",
    "gn:population":0,
    "gn:timezone":"Asia/Shanghai",
    "iso:country":"CN",
    "name:zho_x_preferred":[
        "\u9093\u683c\u5e84"
    ],
    "wof:name":"Denggezhuang",
    "wof:placetype":"locality"
},
  "geometry": {"coordinates":[120.79600000000001,37.4788],"type":"Point"}
}