{
  "type": "Feature",
  "properties": {
    "gn:admin1_code":"3.0",
    "gn:asciiname":"Yanzui",
    "gn:country_code":"CN",
    "gn:dem":309,
    "gn:feature_class":"P",
    "gn:feature_code":"PPL",
    "gn:name":"Yanzui",
    "gn:population":0,
    "gn:timezone":"Asia/Shanghai",
    "iso:country":"CN",
    "name:und_x_variant":[
        "\u96c1\u5480"
    ],
    "wof:name":"Yanzui",
    "wof:placetype":"locality"
},
  "geometry": {"coordinates":[115.80718,28.80091],"type":"Point"}
}