{
  "type": "Feature",
  "properties": {
    "gn:admin1_code":"32.0",
    "gn:asciiname":"Erzaizhu",
    "gn:country_code":"CN",
    "gn:dem":2755,
    "gn:feature_class":"P",
    "gn:feature_code":"PPL",
    "gn:name":"Erzaizhu",
    "gn:population":0,
    "gn:timezone":"Asia/Shanghai",
    "iso:country":"CN",
    "name:zho_x_preferred":[
        "\u5c14\u518d\u73e0"
    ],
    "wof:name":"Erzaizhu",
    "wof:placetype":"locality"
},
  "geometry": {"coordinates":[102.822,28.424],"type":"Point"}
}