{
  "type": "Feature",
  "properties": {
    "gn:admin1_code":"16.0",
    "gn:asciiname":"Shabu",
    "gn:country_code":"CN",
    "gn:dem":99,
    "gn:feature_class":"P",
    "gn:feature_code":"PPL",
    "gn:name":"Shabu",
    "gn:population":0,
    "gn:timezone":"Asia/Shanghai",
    "iso:country":"CN",
    "name:ceb_x_preferred":[
        "Shabu"
    ],
    "name:swe_x_preferred":[
        "Shabu"
    ],
    "name:zho_x_preferred":[
        "\u6c99\u57e0"
    ],
    "wof:name":"Shabu",
    "wof:placetype":"locality"
},
  "geometry": {"coordinates":[108.985,23.1307],"type":"Point"}
}