{
  "type": "Feature",
  "properties": {
    "gn:admin1_code":"16.0",
    "gn:asciiname":"Qijiabu",
    "gn:country_code":"CN",
    "gn:dem":136,
    "gn:feature_class":"P",
    "gn:feature_code":"PPL",
    "gn:name":"Qijiabu",
    "gn:population":0,
    "gn:timezone":"Asia/Shanghai",
    "iso:country":"CN",
    "name:zho_x_preferred":[
        "\u621a\u5bb6\u5821"
    ],
    "wof:name":"Qijiabu",
    "wof:placetype":"locality"
},
  "geometry": {"coordinates":[108.70399999999999,24.482],"type":"Point"}
}