{
  "type": "Feature",
  "properties": {
    "gn:admin1_code":"22.0",
    "gn:asciiname":"Sishangcun",
    "gn:country_code":"CN",
    "gn:dem":1177,
    "gn:feature_class":"P",
    "gn:feature_code":"PPL",
    "gn:name":"Sishangcun",
    "gn:population":0,
    "gn:timezone":"Asia/Shanghai",
    "iso:country":"CN",
    "name:zho_x_preferred":[
        "\u5bfa\u4e0a\u6751"
    ],
    "wof:name":"Sishangcun",
    "wof:placetype":"locality"
},
  "geometry": {"coordinates":[115.54979,40.05995],"type":"Point"}
}