{
  "type": "Feature",
  "properties": {
    "gn:admin1_code":"3.0",
    "gn:asciiname":"Ruokeng",
    "gn:country_code":"CN",
    "gn:dem":235,
    "gn:feature_class":"P",
    "gn:feature_code":"PPL",
    "gn:name":"Ruokeng",
    "gn:population":0,
    "gn:timezone":"Asia/Shanghai",
    "iso:country":"CN",
    "name:zho_x_preferred":[
        "\u7bac\u5751"
    ],
    "wof:name":"Ruokeng",
    "wof:placetype":"locality"
},
  "geometry": {"coordinates":[114.74299999999999,25.1306],"type":"Point"}
}