{
  "type": "Feature",
  "properties": {
    "gn:admin1_code":"25",
    "gn:asciiname":"Dongchengzhuang",
    "gn:country_code":"CN",
    "gn:dem":130,
    "gn:feature_class":"P",
    "gn:feature_code":"PPL",
    "gn:name":"Dongchengzhuang",
    "gn:population":0,
    "gn:timezone":"Asia/Shanghai",
    "iso:country":"CN",
    "name:zho_x_preferred":[
        "\u4e1c\u7a0b\u5e84"
    ],
    "wof:name":"Dongchengzhuang",
    "wof:placetype":"locality"
},
  "geometry": {"coordinates":[118.008,35.0884],"type":"Point"}
}