{
  "type": "Feature",
  "properties": {
    "gn:admin1_code":"3.0",
    "gn:asciiname":"Jijiang",
    "gn:country_code":"CN",
    "gn:dem":102,
    "gn:feature_class":"P",
    "gn:feature_code":"PPL",
    "gn:name":"Jijiang",
    "gn:population":0,
    "gn:timezone":"Asia/Shanghai",
    "iso:country":"CN",
    "name:und_x_variant":[
        "\u5409\u6c5f"
    ],
    "wof:name":"Jijiang",
    "wof:placetype":"locality"
},
  "geometry": {"coordinates":[115.58256000000002,27.44952],"type":"Point"}
}