{
  "type": "Feature",
  "properties": {
    "gn:admin1_code":"15.0",
    "gn:asciiname":"Zhangjiamen",
    "gn:country_code":"CN",
    "gn:dem":1873,
    "gn:feature_class":"P",
    "gn:feature_code":"PPL",
    "gn:name":"Zhangjiamen",
    "gn:population":0,
    "gn:timezone":"Asia/Shanghai",
    "iso:country":"CN",
    "name:zho_x_preferred":[
        "\u5f20\u5bb6\u95e8"
    ],
    "wof:name":"Zhangjiamen",
    "wof:placetype":"locality"
},
  "geometry": {"coordinates":[105.264,36.1116],"type":"Point"}
}