{
  "type": "Feature",
  "properties": {
    "gn:admin1_code":"32.0",
    "gn:asciiname":"Zhuzhen",
    "gn:country_code":"CN",
    "gn:dem":954,
    "gn:feature_class":"P",
    "gn:feature_code":"PPL",
    "gn:name":"Zhuzhen",
    "gn:population":0,
    "gn:timezone":"Asia/Shanghai",
    "iso:country":"CN",
    "name:zho_x_preferred":[
        "\u73e0\u73cd"
    ],
    "wof:name":"Zhuzhen",
    "wof:placetype":"locality"
},
  "geometry": {"coordinates":[105.767,32.0652],"type":"Point"}
}