{
  "type": "Feature",
  "properties": {
    "gn:admin1_code":"22",
    "gn:asciiname":"Lugezhuang",
    "gn:country_code":"CN",
    "gn:dem":30,
    "gn:feature_class":"P",
    "gn:feature_code":"PPL",
    "gn:name":"Lugezhuang",
    "gn:population":0,
    "gn:timezone":"Asia/Shanghai",
    "iso:country":"CN",
    "name:zho_x_preferred":[
        "\u82a6\u5404\u5e84"
    ],
    "wof:name":"Lugezhuang",
    "wof:placetype":"locality"
},
  "geometry": {"coordinates":[116.45562,39.61556],"type":"Point"}
}