{
  "type": "Feature",
  "properties": {
    "gn:admin1_code":"32.0",
    "gn:asciiname":"Daolin",
    "gn:country_code":"CN",
    "gn:dem":485,
    "gn:feature_class":"P",
    "gn:feature_code":"PPL",
    "gn:name":"Daolin",
    "gn:population":0,
    "gn:timezone":"Asia/Shanghai",
    "iso:country":"CN",
    "name:fra_x_preferred":[
        "Daolin"
    ],
    "name:jpn_x_preferred":[
        "\u9053\u6797\u93ae"
    ],
    "name:zho_x_preferred":[
        "\u9053\u6797"
    ],
    "name:zho_x_variant":[
        "\u9053\u6797\u9547"
    ],
    "wof:name":"Daolin",
    "wof:placetype":"locality"
},
  "geometry": {"coordinates":[106.58,31.0163],"type":"Point"}
}