{
  "type": "Feature",
  "properties": {
    "gn:admin1_code":"16.0",
    "gn:asciiname":"Suhetang",
    "gn:country_code":"CN",
    "gn:dem":38,
    "gn:feature_class":"P",
    "gn:feature_code":"PPL",
    "gn:name":"Suhetang",
    "gn:population":0,
    "gn:timezone":"Asia/Shanghai",
    "iso:country":"CN",
    "name:zho_x_preferred":[
        "\u82cf\u5408\u5858"
    ],
    "wof:name":"Suhetang",
    "wof:placetype":"locality"
},
  "geometry": {"coordinates":[110.41,23.527],"type":"Point"}
}