{
  "type": "Feature",
  "properties": {
    "gn:admin1_code":"16.0",
    "gn:asciiname":"Ping'anshan",
    "gn:country_code":"CN",
    "gn:dem":104,
    "gn:feature_class":"P",
    "gn:feature_code":"PPL",
    "gn:name":"Ping\u2019anshan",
    "gn:population":0,
    "gn:timezone":"Asia/Shanghai",
    "iso:country":"CN",
    "name:und_x_variant":[
        "Ping\u2019anshan"
    ],
    "name:zho_x_preferred":[
        "\u5e73\u5b89\u5c71"
    ],
    "wof:name":"Ping'anshan",
    "wof:placetype":"locality"
},
  "geometry": {"coordinates":[109.81100000000001,22.3308],"type":"Point"}
}