{
  "type": "Feature",
  "properties": {
    "gn:admin1_code":"32.0",
    "gn:asciiname":"Xuetang",
    "gn:country_code":"CN",
    "gn:dem":904,
    "gn:feature_class":"P",
    "gn:feature_code":"PPL",
    "gn:name":"Xuetang",
    "gn:population":0,
    "gn:timezone":"Asia/Shanghai",
    "iso:country":"CN",
    "name:und_x_variant":[
        "\u5b66\u5802"
    ],
    "wof:name":"Xuetang",
    "wof:placetype":"locality"
},
  "geometry": {"coordinates":[106.43526,32.43389000000001],"type":"Point"}
}