{
  "type": "Feature",
  "properties": {
    "gn:admin1_code":"2.0",
    "gn:asciiname":"Zhuangbang",
    "gn:country_code":"CN",
    "gn:dem":7,
    "gn:feature_class":"P",
    "gn:feature_code":"PPL",
    "gn:name":"Zhuangbang",
    "gn:population":0,
    "gn:timezone":"Asia/Shanghai",
    "iso:country":"CN",
    "name:und_x_variant":[
        "\u5e84\u6d5c"
    ],
    "wof:name":"Zhuangbang",
    "wof:placetype":"locality"
},
  "geometry": {"coordinates":[120.12819,30.91589],"type":"Point"}
}