{
  "type": "Feature",
  "properties": {
    "gn:admin1_code":"10",
    "gn:asciiname":"Xijianshanzi",
    "gn:country_code":"CN",
    "gn:dem":479,
    "gn:feature_class":"P",
    "gn:feature_code":"PPL",
    "gn:name":"Xijianshanzi",
    "gn:population":0,
    "gn:timezone":"Asia/Shanghai",
    "iso:country":"CN",
    "name:zho_x_preferred":[
        "\u897f\u5c16\u5c71\u5b50"
    ],
    "wof:name":"Xijianshanzi",
    "wof:placetype":"locality"
},
  "geometry": {"coordinates":[118.6574,40.4846],"type":"Point"}
}