{
  "type": "Feature",
  "properties": {
    "gn:admin1_code":"26.0",
    "gn:asciiname":"Kangjiagoucun",
    "gn:country_code":"CN",
    "gn:dem":1259,
    "gn:feature_class":"P",
    "gn:feature_code":"PPL",
    "gn:name":"Kangjiagoucun",
    "gn:population":0,
    "gn:timezone":"Asia/Shanghai",
    "iso:country":"CN",
    "name:zho_x_preferred":[
        "\u5eb7\u5bb6\u6c9f\u6751"
    ],
    "wof:name":"Kangjiagoucun",
    "wof:placetype":"locality"
},
  "geometry": {"coordinates":[106.76849,34.57346],"type":"Point"}
}