{
  "type": "Feature",
  "properties": {
    "gn:admin1_code":"19.0",
    "gn:asciiname":"Mijia Wopucun",
    "gn:country_code":"CN",
    "gn:dem":224,
    "gn:feature_class":"P",
    "gn:feature_code":"PPL",
    "gn:name":"Mijia Wopucun",
    "gn:population":0,
    "gn:timezone":"Asia/Shanghai",
    "iso:country":"CN",
    "name:und_x_variant":[
        "Mijiawopucun",
        "Mijia Wopucun"
    ],
    "name:zho_x_preferred":[
        "\u7c73\u5bb6\u7a9d\u94fa\u6751"
    ],
    "wof:name":"Mijia Wopucun",
    "wof:placetype":"locality"
},
  "geometry": {"coordinates":[120.98429,42.11787],"type":"Point"}
}