{
  "type": "Feature",
  "properties": {
    "gn:admin1_code":"19.0",
    "gn:asciiname":"Ximajiazi",
    "gn:country_code":"CN",
    "gn:dem":97,
    "gn:feature_class":"P",
    "gn:feature_code":"PPL",
    "gn:name":"Ximajiazi",
    "gn:population":0,
    "gn:timezone":"Asia/Shanghai",
    "iso:country":"CN",
    "name:zho_x_preferred":[
        "\u897f\u9a6c\u67b6\u5b50"
    ],
    "wof:name":"Ximajiazi",
    "wof:placetype":"locality"
},
  "geometry": {"coordinates":[122.61545,42.48615],"type":"Point"}
}