{
  "type": "Feature",
  "properties": {
    "gn:admin1_code":"05",
    "gn:asciiname":"An-lo-t'ing",
    "gn:country_code":"CN",
    "gn:dem":584,
    "gn:feature_class":"P",
    "gn:feature_code":"PPL",
    "gn:name":"An-lo-t\u2019ing",
    "gn:population":0,
    "gn:timezone":"Asia/Shanghai",
    "iso:country":"CN",
    "wof:name":"An-lo-t'ing",
    "wof:placetype":"locality"
},
  "geometry": {"coordinates":[127.825,41.40806],"type":"Point"}
}