{
  "type": "Feature",
  "properties": {
    "iso:country":"CN",
    "name:ceb_x_preferred":[
        "Nanyue Qu"
    ],
    "name:cym_x_preferred":[
        "Ardal Nanyue"
    ],
    "name:deu_x_preferred":[
        "Nanyue"
    ],
    "name:eng_x_preferred":[
        "Nanyue District"
    ],
    "name:gan_x_preferred":[
        "\u5357\u5cb3\u533a"
    ],
    "name:hak_x_preferred":[
        "N\u00e0m-ngo\u030dk-kh\u00ee"
    ],
    "name:jpn_x_preferred":[
        "\u5357\u5dbd\u533a"
    ],
    "name:kor_x_preferred":[
        "\ub09c\uc6e8\uad6c"
    ],
    "name:nan_x_preferred":[
        "L\u00e2m-ga\u030dk-khu"
    ],
    "name:nld_x_preferred":[
        "Nanyue"
    ],
    "name:nob_x_preferred":[
        "Nanyue"
    ],
    "name:swe_x_preferred":[
        "Nanyue"
    ],
    "name:vie_x_preferred":[
        "Nam Nh\u1ea1c"
    ],
    "name:wuu_x_preferred":[
        "\u5357\u5cb3\u533a"
    ],
    "name:yue_x_preferred":[
        "\u5357\u5dbd\u5340"
    ],
    "name:zho_x_preferred":[
        "\u5357\u5cb3\u533a"
    ],
    "qs:name":"\u5357\u5cb3\u533a",
    "qs:name_adm0":"\u4e2d\u570b",
    "qs:name_adm1":"\u6e56\u5357\u7701",
    "qs:photos":68,
    "qs:photos_1k":14,
    "qs:photos_9k":1,
    "qs:photos_9r":5,
    "qs:photos_all":316,
    "qs:photos_sr":2,
    "qs:placetype":"LocalAdmin",
    "qs:pop_sr":"0",
    "wd:wordcount":39,
    "wof:name":"\u5357\u5cb3\u533a",
    "wof:placetype":"localadmin"
},
  "geometry": {"coordinates":[112.69774949999999,27.274166],"type":"Point"}
}