{
  "type": "Feature",
  "properties": {
    "gn:admin1_code":"25",
    "gn:asciiname":"Qianxunfeng",
    "gn:country_code":"CN",
    "gn:dem":118,
    "gn:feature_class":"P",
    "gn:feature_code":"PPL",
    "gn:name":"Qianxunfeng",
    "gn:population":0,
    "gn:timezone":"Asia/Shanghai",
    "iso:country":"CN",
    "name:zho_x_preferred":[
        "\u524d\u900a\u5cf0"
    ],
    "wof:name":"Qianxunfeng",
    "wof:placetype":"locality"
},
  "geometry": {"coordinates":[119.071,35.8764],"type":"Point"}
}