{
  "type": "Feature",
  "properties": {
    "gn:admin1_code":"30",
    "gn:asciiname":"Caogangwu Nongchang",
    "gn:country_code":"CN",
    "gn:dem":457,
    "gn:feature_class":"P",
    "gn:feature_code":"PPLF",
    "gn:name":"Caogangwu Nongchang",
    "gn:population":0,
    "gn:timezone":"Asia/Shanghai",
    "iso:country":"CN",
    "name:zho_x_preferred":[
        "\u8349\u5c97\u6b66\u519c\u573a"
    ],
    "wof:name":"Caogangwu Nongchang",
    "wof:placetype":"locality"
},
  "geometry": {"coordinates":[116.75055,23.76162],"type":"Point"}
}