{
  "type": "Feature",
  "properties": {
    "gn:admin1_code":"32.0",
    "gn:asciiname":"Yanyansi",
    "gn:country_code":"CN",
    "gn:dem":592,
    "gn:feature_class":"P",
    "gn:feature_code":"PPL",
    "gn:name":"Yanyansi",
    "gn:population":0,
    "gn:timezone":"Asia/Shanghai",
    "iso:country":"CN",
    "name:zho_x_preferred":[
        "\u4e25\u989c\u5bfa"
    ],
    "wof:name":"Yanyansi",
    "wof:placetype":"locality"
},
  "geometry": {"coordinates":[106.303,31.7941],"type":"Point"}
}