{
  "type": "Feature",
  "properties": {
    "gn:admin1_code":"24.0",
    "gn:asciiname":"Nanxuejiayuancun",
    "gn:country_code":"CN",
    "gn:dem":1023,
    "gn:feature_class":"P",
    "gn:feature_code":"PPL",
    "gn:name":"Nanxuejiayuancun",
    "gn:population":0,
    "gn:timezone":"Asia/Shanghai",
    "iso:country":"CN",
    "name:zho_x_preferred":[
        "\u5357\u859b\u5bb6\u57a3\u6751"
    ],
    "wof:name":"Nanxuejiayuancun",
    "wof:placetype":"locality"
},
  "geometry": {"coordinates":[110.81241,37.35989],"type":"Point"}
}