{
  "type": "Feature",
  "properties": {
    "gn:admin1_code":"32",
    "gn:asciiname":"Linnong",
    "gn:country_code":"CN",
    "gn:dem":421,
    "gn:feature_class":"P",
    "gn:feature_code":"PPL",
    "gn:name":"Linnong",
    "gn:population":0,
    "gn:timezone":"Asia/Shanghai",
    "iso:country":"CN",
    "name:und_x_variant":[
        "Linyi",
        "Linnong"
    ],
    "name:zho_x_preferred":[
        "\u6797\u519c"
    ],
    "wof:name":"Linnong",
    "wof:placetype":"locality"
},
  "geometry": {"coordinates":[105.58783,31.24695],"type":"Point"}
}