{
  "type": "Feature",
  "properties": {
    "gn:admin1_code":"19.0",
    "gn:asciiname":"Nangoucun",
    "gn:country_code":"CN",
    "gn:dem":381,
    "gn:feature_class":"P",
    "gn:feature_code":"PPL",
    "gn:name":"Nangoucun",
    "gn:population":0,
    "gn:timezone":"Asia/Shanghai",
    "iso:country":"CN",
    "name:zho_x_preferred":[
        "\u5357\u6c9f\u6751"
    ],
    "wof:name":"Nangoucun",
    "wof:placetype":"locality"
},
  "geometry": {"coordinates":[121.22199999999999,42.3537],"type":"Point"}
}