{
  "type": "Feature",
  "properties": {
    "gn:admin1_code":"1.0",
    "gn:asciiname":"Hanzhaicun",
    "gn:country_code":"CN",
    "gn:dem":31,
    "gn:feature_class":"P",
    "gn:feature_code":"PPL",
    "gn:name":"Hanzhaicun",
    "gn:population":0,
    "gn:timezone":"Asia/Shanghai",
    "iso:country":"CN",
    "name:zho_x_preferred":[
        "\u97e9\u5be8\u6751"
    ],
    "wof:name":"Hanzhaicun",
    "wof:placetype":"locality"
},
  "geometry": {"coordinates":[116.64121000000002,33.41718],"type":"Point"}
}