{
  "type": "Feature",
  "properties": {
    "gn:admin1_code":"11.0",
    "gn:asciiname":"Shaizitang",
    "gn:country_code":"CN",
    "gn:dem":200,
    "gn:feature_class":"P",
    "gn:feature_code":"PPL",
    "gn:name":"Shaizitang",
    "gn:population":0,
    "gn:timezone":"Asia/Shanghai",
    "iso:country":"CN",
    "name:zho_x_preferred":[
        "\u7b5b\u5b50\u5858"
    ],
    "wof:name":"Shaizitang",
    "wof:placetype":"locality"
},
  "geometry": {"coordinates":[111.60588,25.33503],"type":"Point"}
}