{
  "type": "Feature",
  "properties": {
    "gn:admin1_code":"14.0",
    "gn:asciiname":"Qiepu",
    "gn:country_code":"CN",
    "gn:dem":4416,
    "gn:feature_class":"P",
    "gn:feature_code":"PPL",
    "gn:name":"Qiepu",
    "gn:population":0,
    "gn:timezone":"Asia/Urumqi",
    "iso:country":"CN",
    "name:zho_x_preferred":[
        "\u5207\u666e"
    ],
    "wof:name":"Qiepu",
    "wof:placetype":"locality"
},
  "geometry": {"coordinates":[87.7081,29.6475],"type":"Point"}
}