{
  "type": "Feature",
  "properties": {
    "gn:admin1_code":"16.0",
    "gn:asciiname":"Longliao",
    "gn:country_code":"CN",
    "gn:dem":559,
    "gn:feature_class":"P",
    "gn:feature_code":"PPL",
    "gn:name":"Longliao",
    "gn:population":0,
    "gn:timezone":"Asia/Shanghai",
    "iso:country":"CN",
    "name:zho_x_preferred":[
        "\u9647\u6599"
    ],
    "wof:name":"Longliao",
    "wof:placetype":"locality"
},
  "geometry": {"coordinates":[107.536,23.8636],"type":"Point"}
}