{
  "type": "Feature",
  "properties": {
    "gn:admin1_code":"19.0",
    "gn:asciiname":"Xiangfangcun",
    "gn:country_code":"CN",
    "gn:dem":324,
    "gn:feature_class":"P",
    "gn:feature_code":"PPL",
    "gn:name":"Xiangfangcun",
    "gn:population":0,
    "gn:timezone":"Asia/Shanghai",
    "iso:country":"CN",
    "name:zho_x_preferred":[
        "\u53a2\u623f\u6751"
    ],
    "wof:name":"Xiangfangcun",
    "wof:placetype":"locality"
},
  "geometry": {"coordinates":[122.91855,40.51103],"type":"Point"}
}