{
  "type": "Feature",
  "properties": {
    "gn:admin1_code":"32.0",
    "gn:asciiname":"Niula",
    "gn:country_code":"CN",
    "gn:dem":3182,
    "gn:feature_class":"P",
    "gn:feature_code":"PPL",
    "gn:name":"Niula",
    "gn:population":0,
    "gn:timezone":"Asia/Shanghai",
    "iso:country":"CN",
    "name:zho_x_preferred":[
        "\u725b\u62c9"
    ],
    "wof:name":"Niula",
    "wof:placetype":"locality"
},
  "geometry": {"coordinates":[103.69376,32.53722],"type":"Point"}
}