{
  "type": "Feature",
  "properties": {
    "gn:admin1_code":"26.0",
    "gn:asciiname":"Dawangmiaogou",
    "gn:country_code":"CN",
    "gn:dem":1261,
    "gn:feature_class":"P",
    "gn:feature_code":"PPL",
    "gn:name":"Dawangmiaogou",
    "gn:population":0,
    "gn:timezone":"Asia/Shanghai",
    "iso:country":"CN",
    "name:zho_x_preferred":[
        "\u5927\u738b\u5e99\u6c9f"
    ],
    "wof:name":"Dawangmiaogou",
    "wof:placetype":"locality"
},
  "geometry": {"coordinates":[109.13283,36.82902],"type":"Point"}
}