{
  "type": "Feature",
  "properties": {
    "gn:admin1_code":"30.0",
    "gn:asciiname":"Liubian",
    "gn:country_code":"CN",
    "gn:dem":78,
    "gn:feature_class":"P",
    "gn:feature_code":"PPL",
    "gn:name":"Liubian",
    "gn:population":0,
    "gn:timezone":"Asia/Shanghai",
    "iso:country":"CN",
    "name:zho_x_preferred":[
        "\u7559\u8fb9"
    ],
    "wof:name":"Liubian",
    "wof:placetype":"locality"
},
  "geometry": {"coordinates":[113.42610999999999,24.68115],"type":"Point"}
}