{
  "type": "Feature",
  "properties": {
    "gn:country":"CN",
    "gn:fcode":"PPLA4",
    "gn:pop":880,
    "iso:country":"CN",
    "name:unk_x_variant":[
        "\u6cee\u6d0b"
    ],
    "qs:name":"Panyang",
    "qs:photos_9r":0,
    "qs:photos_sr":0,
    "qs:pop_sr":"2",
    "wof:name":"Panyang",
    "wof:placetype":"locality",
    "wof:population":880
},
  "geometry": {"coordinates":[118.8313,26.5495],"type":"Point"}
}