{
  "type": "Feature",
  "properties": {
    "gn:admin1_code":"11.0",
    "gn:asciiname":"Shizhukeng",
    "gn:country_code":"CN",
    "gn:dem":222,
    "gn:feature_class":"P",
    "gn:feature_code":"PPL",
    "gn:name":"Shizhukeng",
    "gn:population":0,
    "gn:timezone":"Asia/Shanghai",
    "iso:country":"CN",
    "name:zho_x_preferred":[
        "Shizhukeng"
    ],
    "name:zho_x_variant":[
        "\u5b9e\u7af9\u5751"
    ],
    "wof:name":"Shizhukeng",
    "wof:placetype":"locality"
},
  "geometry": {"coordinates":[114.04364,28.6749],"type":"Point"}
}