{
  "type": "Feature",
  "properties": {
    "gn:admin1_code":"7.0",
    "gn:asciiname":"Luxiacuo",
    "gn:country_code":"CN",
    "gn:dem":188,
    "gn:feature_class":"P",
    "gn:feature_code":"PPL",
    "gn:name":"Luxiacuo",
    "gn:population":0,
    "gn:timezone":"Asia/Shanghai",
    "iso:country":"CN",
    "name:und_x_variant":[
        "\u8def\u4e0b\u539d"
    ],
    "name:zho_x_preferred":[
        "Luxiacuo"
    ],
    "wof:name":"Luxiacuo",
    "wof:placetype":"locality"
},
  "geometry": {"coordinates":[119.23441,26.14523],"type":"Point"}
}