{
  "type": "Feature",
  "properties": {
    "gn:admin1_code":"26",
    "gn:asciiname":"Zhilan",
    "gn:country_code":"CN",
    "gn:dem":602,
    "gn:feature_class":"P",
    "gn:feature_code":"PPL",
    "gn:name":"Zhilan",
    "gn:population":0,
    "gn:timezone":"Asia/Shanghai",
    "iso:country":"CN",
    "name:zho_x_preferred":[
        "\u829d\u5170"
    ],
    "wof:name":"Zhilan",
    "wof:placetype":"locality"
},
  "geometry": {"coordinates":[108.20444000000001,34.46167],"type":"Point"}
}