{
  "type": "Feature",
  "properties": {
    "gn:admin1_code":"1.0",
    "gn:asciiname":"Mulinghou",
    "gn:country_code":"CN",
    "gn:dem":470,
    "gn:feature_class":"P",
    "gn:feature_code":"PPL",
    "gn:name":"Mulinghou",
    "gn:population":0,
    "gn:timezone":"Asia/Shanghai",
    "iso:country":"CN",
    "name:zho_x_preferred":[
        "\u6728\u5cad\u540e"
    ],
    "wof:name":"Mulinghou",
    "wof:placetype":"locality"
},
  "geometry": {"coordinates":[118.39654,30.06891],"type":"Point"}
}