{
  "type": "Feature",
  "properties": {
    "gn:admin1_code":"24.0",
    "gn:asciiname":"Woyanggou",
    "gn:country_code":"CN",
    "gn:dem":886,
    "gn:feature_class":"P",
    "gn:feature_code":"PPL",
    "gn:name":"Woyanggou",
    "gn:population":0,
    "gn:timezone":"Asia/Shanghai",
    "iso:country":"CN",
    "name:zho_x_preferred":[
        "\u5367\u7f8a\u6c9f"
    ],
    "wof:name":"Woyanggou",
    "wof:placetype":"locality"
},
  "geometry": {"coordinates":[112.7525,35.20872],"type":"Point"}
}