{
  "type": "Feature",
  "properties": {
    "gn:admin1_code":"29.0",
    "gn:asciiname":"Xiaoshuiqiao",
    "gn:country_code":"CN",
    "gn:dem":1727,
    "gn:feature_class":"P",
    "gn:feature_code":"PPL",
    "gn:name":"Xiaoshuiqiao",
    "gn:population":0,
    "gn:timezone":"Asia/Shanghai",
    "iso:country":"CN",
    "name:zho_x_preferred":[
        "\u5c0f\u6c34\u6865"
    ],
    "wof:name":"Xiaoshuiqiao",
    "wof:placetype":"locality"
},
  "geometry": {"coordinates":[101.70999999999999,25.6236],"type":"Point"}
}