{
  "type": "Feature",
  "properties": {
    "gn:admin1_code":"12.0",
    "gn:asciiname":"Yanmaoling",
    "gn:country_code":"CN",
    "gn:dem":30,
    "gn:feature_class":"P",
    "gn:feature_code":"PPL",
    "gn:name":"Yanmaoling",
    "gn:population":0,
    "gn:timezone":"Asia/Shanghai",
    "iso:country":"CN",
    "name:zho_x_preferred":[
        "Yanmaoling"
    ],
    "name:zho_x_variant":[
        "\u4e25\u6bdb\u5cad"
    ],
    "wof:name":"Yanmaoling",
    "wof:placetype":"locality"
},
  "geometry": {"coordinates":[112.74088,30.18388],"type":"Point"}
}