{
  "type": "Feature",
  "properties": {
    "gn:admin1_code":"19.0",
    "gn:asciiname":"Xinbaicun",
    "gn:country_code":"CN",
    "gn:dem":15,
    "gn:feature_class":"P",
    "gn:feature_code":"PPL",
    "gn:name":"Xinbaicun",
    "gn:population":0,
    "gn:timezone":"Asia/Shanghai",
    "iso:country":"CN",
    "name:zho_x_preferred":[
        "\u65b0\u767d\u6751"
    ],
    "wof:name":"Xinbaicun",
    "wof:placetype":"locality"
},
  "geometry": {"coordinates":[120.46615,40.4907],"type":"Point"}
}