{
  "type": "Feature",
  "properties": {
    "gn:admin1_code":"7.0",
    "gn:asciiname":"Xikengli",
    "gn:country_code":"CN",
    "gn:dem":731,
    "gn:feature_class":"P",
    "gn:feature_code":"PPL",
    "gn:name":"Xikengli",
    "gn:population":0,
    "gn:timezone":"Asia/Shanghai",
    "iso:country":"CN",
    "name:zho_x_preferred":[
        "\u897f\u5751\u91cc"
    ],
    "wof:name":"Xikengli",
    "wof:placetype":"locality"
},
  "geometry": {"coordinates":[118.76705,25.88751],"type":"Point"}
}