{
  "type": "Feature",
  "properties": {
    "gn:admin1_code":"14.0",
    "gn:asciiname":"Chakulecun",
    "gn:country_code":"CN",
    "gn:dem":4711,
    "gn:feature_class":"P",
    "gn:feature_code":"PPL",
    "gn:name":"Chakulecun",
    "gn:population":0,
    "gn:timezone":"Asia/Urumqi",
    "iso:country":"CN",
    "name:zho_x_preferred":[
        "\u67e5\u5e93\u52d2\u6751"
    ],
    "wof:name":"Chakulecun",
    "wof:placetype":"locality"
},
  "geometry": {"coordinates":[93.22501,31.30186],"type":"Point"}
}