{
  "type": "Feature",
  "properties": {
    "gn:admin1_code":"11.0",
    "gn:asciiname":"Daowoli",
    "gn:country_code":"CN",
    "gn:dem":946,
    "gn:feature_class":"P",
    "gn:feature_code":"PPL",
    "gn:name":"Daowoli",
    "gn:population":0,
    "gn:timezone":"Asia/Shanghai",
    "iso:country":"CN",
    "name:zho_x_preferred":[
        "\u5012\u7a9d\u91cc"
    ],
    "wof:name":"Daowoli",
    "wof:placetype":"locality"
},
  "geometry": {"coordinates":[113.97973,26.40216],"type":"Point"}
}