{
  "type": "Feature",
  "properties": {
    "gn:admin1_code":"25.0",
    "gn:asciiname":"Yangqilingcun",
    "gn:country_code":"CN",
    "gn:dem":125,
    "gn:feature_class":"P",
    "gn:feature_code":"PPL",
    "gn:name":"Yangqilingcun",
    "gn:population":0,
    "gn:timezone":"Asia/Shanghai",
    "iso:country":"CN",
    "name:zho_x_preferred":[
        "\u6768\u4e03\u5cad\u6751"
    ],
    "wof:name":"Yangqilingcun",
    "wof:placetype":"locality"
},
  "geometry": {"coordinates":[120.11271000000001,35.9568],"type":"Point"}
}