{
  "type": "Feature",
  "properties": {
    "gn:admin1_code":"29.0",
    "gn:asciiname":"Chengzishan",
    "gn:country_code":"CN",
    "gn:dem":2100,
    "gn:feature_class":"P",
    "gn:feature_code":"PPL",
    "gn:name":"Chengzishan",
    "gn:population":0,
    "gn:timezone":"Asia/Shanghai",
    "iso:country":"CN",
    "name:zho_x_preferred":[
        "\u6210\u5b50\u5c71"
    ],
    "wof:name":"Chengzishan",
    "wof:placetype":"locality"
},
  "geometry": {"coordinates":[103.73699999999999,23.5035],"type":"Point"}
}