{
  "type": "Feature",
  "properties": {
    "gn:admin1_code":"15.0",
    "gn:asciiname":"Wanghuzhuang",
    "gn:country_code":"CN",
    "gn:dem":1474,
    "gn:feature_class":"P",
    "gn:feature_code":"PPL",
    "gn:name":"Wanghuzhuang",
    "gn:population":0,
    "gn:timezone":"Asia/Shanghai",
    "iso:country":"CN",
    "name:zho_x_preferred":[
        "\u738b\u6237\u5e84"
    ],
    "wof:name":"Wanghuzhuang",
    "wof:placetype":"locality"
},
  "geometry": {"coordinates":[102.65000000000001,38.1299],"type":"Point"}
}