{
  "type": "Feature",
  "properties": {
    "gn:admin1_code":"32.0",
    "gn:asciiname":"Zhangmugou",
    "gn:country_code":"CN",
    "gn:dem":537,
    "gn:feature_class":"P",
    "gn:feature_code":"PPL",
    "gn:name":"Zhangmugou",
    "gn:population":0,
    "gn:timezone":"Asia/Shanghai",
    "iso:country":"CN",
    "name:zho_x_preferred":[
        "\u6a1f\u6728\u6c9f"
    ],
    "wof:name":"Zhangmugou",
    "wof:placetype":"locality"
},
  "geometry": {"coordinates":[107.82299999999999,31.3479],"type":"Point"}
}