{
  "type": "Feature",
  "properties": {
    "gn:admin1_code":"28",
    "gn:asciiname":"Yangchengzhuang",
    "gn:country_code":"CN",
    "gn:dem":5,
    "gn:feature_class":"P",
    "gn:feature_code":"PPLA4",
    "gn:name":"Yangchengzhuang",
    "gn:population":0,
    "gn:timezone":"Asia/Shanghai",
    "iso:country":"CN",
    "name:und_x_variant":[
        "Yangchengzhuang Zhen"
    ],
    "name:zho_x_preferred":[
        "\u6768\u6210\u5e84"
    ],
    "name:zho_x_variant":[
        "\u6768\u6210\u5e84\u9547"
    ],
    "wof:name":"Yangchengzhuang",
    "wof:placetype":"locality"
},
  "geometry": {"coordinates":[117.04917,38.94167],"type":"Point"}
}