{
  "type": "Feature",
  "properties": {
    "gn:admin1_code":"7.0",
    "gn:asciiname":"Xingchen",
    "gn:country_code":"CN",
    "gn:dem":15,
    "gn:feature_class":"P",
    "gn:feature_code":"PPL",
    "gn:name":"Xingchen",
    "gn:population":0,
    "gn:timezone":"Asia/Shanghai",
    "iso:country":"CN",
    "name:und_x_variant":[
        "Chengyingcun",
        "Hsing-ch\u2019en",
        "Xingchen"
    ],
    "wof:name":"Xingchen",
    "wof:placetype":"locality"
},
  "geometry": {"coordinates":[117.38964,23.75416],"type":"Point"}
}