{
  "type": "Feature",
  "properties": {
    "gn:admin1_code":"29.0",
    "gn:asciiname":"Qingshuitang",
    "gn:country_code":"CN",
    "gn:dem":2136,
    "gn:feature_class":"P",
    "gn:feature_code":"PPL",
    "gn:name":"Qingshuitang",
    "gn:population":0,
    "gn:timezone":"Asia/Shanghai",
    "iso:country":"CN",
    "name:zho_x_preferred":[
        "\u6e05\u6c34\u5858"
    ],
    "wof:name":"Qingshuitang",
    "wof:placetype":"locality"
},
  "geometry": {"coordinates":[103.49299999999999,25.699],"type":"Point"}
}