{
  "type": "Feature",
  "properties": {
    "gn:admin1_code":"11.0",
    "gn:asciiname":"Daliuhong",
    "gn:country_code":"CN",
    "gn:dem":348,
    "gn:feature_class":"P",
    "gn:feature_code":"PPL",
    "gn:name":"Daliuhong",
    "gn:population":0,
    "gn:timezone":"Asia/Shanghai",
    "iso:country":"CN",
    "name:zho_x_preferred":[
        "\u5927\u6d41\u6d2a"
    ],
    "wof:name":"Daliuhong",
    "wof:placetype":"locality"
},
  "geometry": {"coordinates":[110.72926,28.25924],"type":"Point"}
}