{
  "type": "Feature",
  "properties": {
    "gn:admin1_code":"3.0",
    "gn:asciiname":"Xinzecai",
    "gn:country_code":"CN",
    "gn:dem":19,
    "gn:feature_class":"P",
    "gn:feature_code":"PPL",
    "gn:name":"Xinzecai",
    "gn:population":0,
    "gn:timezone":"Asia/Shanghai",
    "iso:country":"CN",
    "name:und_x_variant":[
        "\u65b0\u6cfd\u8521"
    ],
    "wof:name":"Xinzecai",
    "wof:placetype":"locality"
},
  "geometry": {"coordinates":[115.97259,28.97966],"type":"Point"}
}