{
  "type": "Feature",
  "properties": {
    "gn:admin1_code":"30",
    "gn:asciiname":"Huoshaoling",
    "gn:country_code":"CN",
    "gn:dem":33,
    "gn:feature_class":"P",
    "gn:feature_code":"PPL",
    "gn:name":"Huoshaoling",
    "gn:population":0,
    "gn:timezone":"Asia/Urumqi",
    "iso:country":"CN",
    "name:zho_x_preferred":[
        "\u706b\u70e7\u5cad"
    ],
    "wof:name":"Huoshaoling",
    "wof:placetype":"locality"
},
  "geometry": {"coordinates":[110.13457,21.67007000000001],"type":"Point"}
}