{
  "type": "Feature",
  "properties": {
    "gn:admin1_code":"15.0",
    "gn:asciiname":"Xujia Heishuzhuang",
    "gn:country_code":"CN",
    "gn:dem":1721,
    "gn:feature_class":"P",
    "gn:feature_code":"PPL",
    "gn:name":"Xujia Heishuzhuang",
    "gn:population":0,
    "gn:timezone":"Asia/Shanghai",
    "iso:country":"CN",
    "name:zho_x_preferred":[
        "\u8bb8\u5bb6\u9ed1\u6811\u5e84"
    ],
    "wof:name":"Xujia Heishuzhuang",
    "wof:placetype":"locality"
},
  "geometry": {"coordinates":[102.437,38.0084],"type":"Point"}
}