{
  "type": "Feature",
  "properties": {
    "gn:admin1_code":"19.0",
    "gn:asciiname":"Gaojia Beigou",
    "gn:country_code":"CN",
    "gn:dem":282,
    "gn:feature_class":"P",
    "gn:feature_code":"PPL",
    "gn:name":"Gaojia Beigou",
    "gn:population":0,
    "gn:timezone":"Asia/Shanghai",
    "iso:country":"CN",
    "name:zho_x_preferred":[
        "\u9ad8\u5bb6\u5317\u6c9f"
    ],
    "wof:name":"Gaojia Beigou",
    "wof:placetype":"locality"
},
  "geometry": {"coordinates":[123.12291,40.82391],"type":"Point"}
}