{
  "type": "Feature",
  "properties": {
    "gn:admin1_code":"32.0",
    "gn:asciiname":"Honggongqiao",
    "gn:country_code":"CN",
    "gn:dem":541,
    "gn:feature_class":"P",
    "gn:feature_code":"PPL",
    "gn:name":"Honggongqiao",
    "gn:population":0,
    "gn:timezone":"Asia/Shanghai",
    "iso:country":"CN",
    "name:zho_x_preferred":[
        "\u6d2a\u62f1\u6865"
    ],
    "wof:name":"Honggongqiao",
    "wof:placetype":"locality"
},
  "geometry": {"coordinates":[104.244,31.2559],"type":"Point"}
}