{
  "type": "Feature",
  "properties": {
    "gn:admin1_code":"12.0",
    "gn:asciiname":"Ertaiping",
    "gn:country_code":"CN",
    "gn:dem":678,
    "gn:feature_class":"P",
    "gn:feature_code":"PPL",
    "gn:name":"Ertaiping",
    "gn:population":0,
    "gn:timezone":"Asia/Shanghai",
    "iso:country":"CN",
    "name:zho_x_preferred":[
        "\u4e8c\u53f0\u576a"
    ],
    "wof:name":"Ertaiping",
    "wof:placetype":"locality"
},
  "geometry": {"coordinates":[109.54688,30.39652],"type":"Point"}
}