{
  "type": "Feature",
  "properties": {
    "gn:admin1_code":"18",
    "gn:asciiname":"Gaotian",
    "gn:country_code":"CN",
    "gn:dem":1868,
    "gn:feature_class":"P",
    "gn:feature_code":"PPL",
    "gn:name":"Gaotian",
    "gn:population":0,
    "gn:timezone":"Asia/Shanghai",
    "iso:country":"CN",
    "name:zho_x_preferred":[
        "\u9ad8\u7530"
    ],
    "wof:name":"Gaotian",
    "wof:placetype":"locality"
},
  "geometry": {"coordinates":[104.319,26.6346],"type":"Point"}
}