{
  "type": "Feature",
  "properties": {
    "gn:admin1_code":"10.0",
    "gn:asciiname":"Gaojiazhuang",
    "gn:country_code":"CN",
    "gn:dem":204,
    "gn:feature_class":"P",
    "gn:feature_code":"PPL",
    "gn:name":"Gaojiazhuang",
    "gn:population":0,
    "gn:timezone":"Asia/Shanghai",
    "iso:country":"CN",
    "name:und_x_variant":[
        "\u9ad8\u5bb6\u5e84"
    ],
    "wof:name":"Gaojiazhuang",
    "wof:placetype":"locality"
},
  "geometry": {"coordinates":[114.07922000000001,38.22535],"type":"Point"}
}