{
  "type": "Feature",
  "properties": {
    "gn:admin1_code":"8.0",
    "gn:asciiname":"Sijiashan Yidui",
    "gn:country_code":"CN",
    "gn:dem":281,
    "gn:feature_class":"P",
    "gn:feature_code":"PPLF",
    "gn:name":"Sijiashan Yidui",
    "gn:population":0,
    "gn:timezone":"Asia/Shanghai",
    "iso:country":"CN",
    "name:zho_x_preferred":[
        "\u56db\u67b6\u5c71\u4e00\u961f"
    ],
    "wof:name":"Sijiashan Yidui",
    "wof:placetype":"locality"
},
  "geometry": {"coordinates":[122.80159999999999,47.3814],"type":"Point"}
}