{
  "type": "Feature",
  "properties": {
    "gn:admin1_code":"26.0",
    "gn:asciiname":"Gaoqiaopu",
    "gn:country_code":"CN",
    "gn:dem":1398,
    "gn:feature_class":"P",
    "gn:feature_code":"PPL",
    "gn:name":"Gaoqiaopu",
    "gn:population":0,
    "gn:timezone":"Asia/Shanghai",
    "iso:country":"CN",
    "name:und_x_variant":[
        "\u9ad8\u6865\u94fa"
    ],
    "wof:name":"Gaoqiaopu",
    "wof:placetype":"locality"
},
  "geometry": {"coordinates":[106.768,33.72886],"type":"Point"}
}