{
  "type": "Feature",
  "properties": {
    "gn:admin1_code":"16",
    "gn:asciiname":"Bainan",
    "gn:cc2":"CN",
    "gn:country_code":"CN",
    "gn:dem":297,
    "gn:feature_class":"P",
    "gn:feature_code":"PPL",
    "gn:name":"Bainan",
    "gn:population":0,
    "gn:timezone":"Asia/Shanghai",
    "iso:country":"CN",
    "name:und_x_variant":[
        "Pai-nan",
        "Pai-nan-hs\u00fc",
        "Bainan"
    ],
    "wof:name":"Bainan",
    "wof:placetype":"locality"
},
  "geometry": {"coordinates":[105.81139,23.05611],"type":"Point"}
}