{
  "type": "Feature",
  "properties": {
    "gn:admin1_code":"13",
    "gn:asciiname":"Bo'ergasu",
    "gn:country_code":"CN",
    "gn:dem":1228,
    "gn:feature_class":"P",
    "gn:feature_code":"PPL",
    "gn:name":"Bo\u2019ergasu",
    "gn:population":0,
    "gn:timezone":"Asia/Urumqi",
    "iso:country":"CN",
    "name:und_x_variant":[
        "Bo\u2019ergasu",
        "\u535a\u5c14\u5c15\u82cf"
    ],
    "wof:name":"Bo'ergasu",
    "wof:placetype":"locality"
},
  "geometry": {"coordinates":[95.32212,43.0424],"type":"Point"}
}