{
  "type": "Feature",
  "properties": {
    "gn:admin1_code":"7.0",
    "gn:asciiname":"Tashan",
    "gn:country_code":"CN",
    "gn:dem":18,
    "gn:feature_class":"P",
    "gn:feature_code":"PPL",
    "gn:name":"Tashan",
    "gn:population":0,
    "gn:timezone":"Asia/Shanghai",
    "iso:country":"CN",
    "name:ceb_x_preferred":[
        "Tashan"
    ],
    "name:deu_x_preferred":[
        "Tashan"
    ],
    "name:swe_x_preferred":[
        "Tashan"
    ],
    "name:zho_x_preferred":[
        "\u5854\u5c71"
    ],
    "wof:name":"Tashan",
    "wof:placetype":"locality"
},
  "geometry": {"coordinates":[119.13276,25.46273],"type":"Point"}
}