{
  "type": "Feature",
  "properties": {
    "gn:admin1_code":"5.0",
    "gn:asciiname":"Sangedingzi Qidui",
    "gn:country_code":"CN",
    "gn:dem":381,
    "gn:feature_class":"P",
    "gn:feature_code":"PPLF",
    "gn:name":"Sangedingzi Qidui",
    "gn:population":0,
    "gn:timezone":"Asia/Shanghai",
    "iso:country":"CN",
    "name:zho_x_preferred":[
        "\u4e09\u4e2a\u9876\u5b50\u4e03\u961f"
    ],
    "wof:name":"Sangedingzi Qidui",
    "wof:placetype":"locality"
},
  "geometry": {"coordinates":[127.01969,44.08258],"type":"Point"}
}