{
  "type": "Feature",
  "properties": {
    "gn:admin1_code":"32.0",
    "gn:asciiname":"Laoyoufang",
    "gn:country_code":"CN",
    "gn:dem":509,
    "gn:feature_class":"P",
    "gn:feature_code":"PPL",
    "gn:name":"Laoyoufang",
    "gn:population":0,
    "gn:timezone":"Asia/Shanghai",
    "iso:country":"CN",
    "name:zho_x_preferred":[
        "\u8001\u6cb9\u574a"
    ],
    "wof:name":"Laoyoufang",
    "wof:placetype":"locality"
},
  "geometry": {"coordinates":[104.42888000000001,31.1856],"type":"Point"}
}