{
  "type": "Feature",
  "properties": {
    "gn:admin1_code":"24",
    "gn:asciiname":"Qiangeduocun",
    "gn:country_code":"CN",
    "gn:dem":1074,
    "gn:feature_class":"P",
    "gn:feature_code":"PPL",
    "gn:name":"Qiangeduocun",
    "gn:population":0,
    "gn:timezone":"Asia/Shanghai",
    "iso:country":"CN",
    "name:und_x_variant":[
        "Ch\u2019ien-ko-to",
        "Qiangeduo",
        "Qiangeduocun"
    ],
    "name:zho_x_preferred":[
        "\u524d\u572a\u579b\u6751"
    ],
    "wof:name":"Qiangeduocun",
    "wof:placetype":"locality"
},
  "geometry": {"coordinates":[110.89053,37.0378],"type":"Point"}
}