{
  "type": "Feature",
  "properties": {
    "gn:admin1_code":"32.0",
    "gn:asciiname":"Luoduo",
    "gn:country_code":"CN",
    "gn:dem":2639,
    "gn:feature_class":"P",
    "gn:feature_code":"PPL",
    "gn:name":"Luoduo",
    "gn:population":0,
    "gn:timezone":"Asia/Shanghai",
    "iso:country":"CN",
    "name:zho_x_preferred":[
        "\u6d1b\u591a"
    ],
    "wof:name":"Luoduo",
    "wof:placetype":"locality"
},
  "geometry": {"coordinates":[103.34108999999999,32.04935],"type":"Point"}
}