{
  "type": "Feature",
  "properties": {
    "gn:admin1_code":"15.0",
    "gn:asciiname":"Yangjia Taizi",
    "gn:country_code":"CN",
    "gn:dem":1546,
    "gn:feature_class":"P",
    "gn:feature_code":"PPL",
    "gn:name":"Yangjia Taizi",
    "gn:population":0,
    "gn:timezone":"Asia/Shanghai",
    "iso:country":"CN",
    "name:zho_x_preferred":[
        "\u6768\u5bb6\u53f0\u5b50"
    ],
    "wof:name":"Yangjia Taizi",
    "wof:placetype":"locality"
},
  "geometry": {"coordinates":[105.815,34.1137],"type":"Point"}
}