{
  "type": "Feature",
  "properties": {
    "gn:admin1_code":"25",
    "gn:asciiname":"Dalingcun",
    "gn:country_code":"CN",
    "gn:dem":74,
    "gn:feature_class":"P",
    "gn:feature_code":"PPL",
    "gn:name":"Dalingcun",
    "gn:population":0,
    "gn:timezone":"Asia/Shanghai",
    "iso:country":"CN",
    "name:und_x_variant":[
        "Daling",
        "Dalingcun"
    ],
    "name:zho_x_preferred":[
        "\u5927\u5cad"
    ],
    "name:zho_x_variant":[
        "\u5927\u5cad\u6751"
    ],
    "wof:name":"Dalingcun",
    "wof:placetype":"locality"
},
  "geometry": {"coordinates":[118.2777,35.10573],"type":"Point"}
}