{
  "type": "Feature",
  "properties": {
    "gn:admin1_code":"30.0",
    "gn:asciiname":"Shangdong",
    "gn:country_code":"CN",
    "gn:dem":417,
    "gn:feature_class":"P",
    "gn:feature_code":"PPL",
    "gn:name":"Shangdong",
    "gn:population":0,
    "gn:timezone":"Asia/Shanghai",
    "iso:country":"CN",
    "name:zho_x_preferred":[
        "Shangdong"
    ],
    "name:zho_x_variant":[
        "\u4e0a\u6d1e"
    ],
    "wof:name":"Shangdong",
    "wof:placetype":"locality"
},
  "geometry": {"coordinates":[114.96966,24.59882],"type":"Point"}
}