{
  "type": "Feature",
  "properties": {
    "gn:admin1_code":"18",
    "gn:asciiname":"Xiabantun",
    "gn:country_code":"CN",
    "gn:dem":850,
    "gn:feature_class":"P",
    "gn:feature_code":"PPL",
    "gn:name":"Xiabantun",
    "gn:population":0,
    "gn:timezone":"Asia/Shanghai",
    "iso:country":"CN",
    "name:zho_x_preferred":[
        "\u4e0b\u534a\u5c6f"
    ],
    "wof:name":"Xiabantun",
    "wof:placetype":"locality"
},
  "geometry": {"coordinates":[108.36799999999999,27.1072],"type":"Point"}
}