{
  "type": "Feature",
  "properties": {
    "gn:admin1_code":"30",
    "gn:asciiname":"Mazhuwo",
    "gn:country_code":"CN",
    "gn:dem":391,
    "gn:feature_class":"P",
    "gn:feature_code":"PPL",
    "gn:name":"Mazhuwo",
    "gn:population":0,
    "gn:timezone":"Asia/Shanghai",
    "iso:country":"CN",
    "name:zho_x_preferred":[
        "\u9ebb\u7af9\u7a9d"
    ],
    "wof:name":"Mazhuwo",
    "wof:placetype":"locality"
},
  "geometry": {"coordinates":[116.55488,24.10008],"type":"Point"}
}