{
  "type": "Feature",
  "properties": {
    "gn:admin1_code":"26",
    "gn:asciiname":"Xishiyuan",
    "gn:country_code":"CN",
    "gn:dem":900,
    "gn:feature_class":"P",
    "gn:feature_code":"PPL",
    "gn:name":"Xishiyuan",
    "gn:population":0,
    "gn:timezone":"Asia/Shanghai",
    "iso:country":"CN",
    "name:und_x_variant":[
        "\u897f\u67ff\u56ed"
    ],
    "name:zho_x_preferred":[
        "\u897f\u67ff\u56ed"
    ],
    "wof:name":"Xishiyuan",
    "wof:placetype":"locality"
},
  "geometry": {"coordinates":[108.09056,34.6325],"type":"Point"}
}