{
  "type": "Feature",
  "properties": {
    "gn:admin1_code":"29",
    "gn:asciiname":"Shangjiedai",
    "gn:country_code":"CN",
    "gn:dem":2230,
    "gn:feature_class":"P",
    "gn:feature_code":"PPL",
    "gn:name":"Shangjiedai",
    "gn:population":0,
    "gn:timezone":"Asia/Shanghai",
    "iso:country":"CN",
    "name:zho_x_preferred":[
        "\u4e0a\u501f\u4ee3"
    ],
    "wof:name":"Shangjiedai",
    "wof:placetype":"locality"
},
  "geometry": {"coordinates":[101.95999999999999,24.2107],"type":"Point"}
}