{
  "type": "Feature",
  "properties": {
    "gn:country":"CN",
    "gn:fcode":"PPL",
    "gn:pop":1850,
    "iso:country":"CN",
    "name:unk_x_variant":[
        "Hung-yang"
    ],
    "qs:name":"Hongyang",
    "qs:photos_9r":0,
    "qs:photos_sr":0,
    "qs:pop_sr":"3",
    "wd:wordcount":17,
    "wof:name":"Hongyang",
    "wof:placetype":"locality",
    "wof:population":1850
},
  "geometry": {"coordinates":[119.46250000000001,26.52861],"type":"Point"}
}