{
  "type": "Feature",
  "properties": {
    "gn:admin1_code":"4.0",
    "gn:asciiname":"Nicitangcun",
    "gn:country_code":"CN",
    "gn:dem":13,
    "gn:feature_class":"P",
    "gn:feature_code":"PPL",
    "gn:name":"Nicitangcun",
    "gn:population":0,
    "gn:timezone":"Asia/Shanghai",
    "iso:country":"CN",
    "name:zho_x_preferred":[
        "\u502a\u7960\u5802\u6751"
    ],
    "wof:name":"Nicitangcun",
    "wof:placetype":"locality"
},
  "geometry": {"coordinates":[118.79791000000002,33.74811],"type":"Point"}
}