{
  "type": "Feature",
  "properties": {
    "gn:admin1_code":"19.0",
    "gn:asciiname":"Yanggoumenzi",
    "gn:country_code":"CN",
    "gn:dem":350,
    "gn:feature_class":"P",
    "gn:feature_code":"PPL",
    "gn:name":"Yanggoumenzi",
    "gn:population":0,
    "gn:timezone":"Asia/Shanghai",
    "iso:country":"CN",
    "name:und_x_variant":[
        "\u9633\u6c9f\u95e8\u5b50"
    ],
    "name:zho_x_preferred":[
        "\u9633\u6c9f\u95e8\u5b50"
    ],
    "wof:name":"Yanggoumenzi",
    "wof:placetype":"locality"
},
  "geometry": {"coordinates":[123.43575,40.89955],"type":"Point"}
}