{
  "type": "Feature",
  "properties": {
    "gn:admin1_code":"9.0",
    "gn:asciiname":"Wangjiaying",
    "gn:country_code":"CN",
    "gn:dem":209,
    "gn:feature_class":"P",
    "gn:feature_code":"PPL",
    "gn:name":"Wangjiaying",
    "gn:population":0,
    "gn:timezone":"Asia/Shanghai",
    "iso:country":"CN",
    "name:und_x_variant":[
        "\u738b\u5bb6\u8425",
        "Wangjiaying"
    ],
    "wof:name":"Wangjiaying",
    "wof:placetype":"locality"
},
  "geometry": {"coordinates":[112.96893,33.43287],"type":"Point"}
}