{
  "type": "Feature",
  "properties": {
    "gn:admin1_code":"20.0",
    "gn:asciiname":"Liujia Shisanhao",
    "gn:country_code":"CN",
    "gn:dem":1136,
    "gn:feature_class":"P",
    "gn:feature_code":"PPL",
    "gn:name":"Liujia Shisanhao",
    "gn:population":0,
    "gn:timezone":"Asia/Shanghai",
    "iso:country":"CN",
    "name:und_x_variant":[
        "\u5218\u5bb6\u5341\u4e09\u53f7"
    ],
    "wof:name":"Liujia Shisanhao",
    "wof:placetype":"locality"
},
  "geometry": {"coordinates":[111.69248,40.08603],"type":"Point"}
}