{
  "type": "Feature",
  "properties": {
    "gn:admin1_code":"9.0",
    "gn:asciiname":"Yaodi",
    "gn:country_code":"CN",
    "gn:dem":190,
    "gn:feature_class":"P",
    "gn:feature_code":"PPL",
    "gn:name":"Yaodi",
    "gn:population":0,
    "gn:timezone":"Asia/Shanghai",
    "iso:country":"CN",
    "name:zho_x_preferred":[
        "\u7a91\u5e95"
    ],
    "wof:name":"Yaodi",
    "wof:placetype":"locality"
},
  "geometry": {"coordinates":[112.44571000000001,34.48264],"type":"Point"}
}