{
  "type": "Feature",
  "properties": {
    "gn:admin1_code":"11.0",
    "gn:asciiname":"Luzhu",
    "gn:country_code":"CN",
    "gn:dem":57,
    "gn:feature_class":"P",
    "gn:feature_code":"PPL",
    "gn:name":"Luzhu",
    "gn:population":0,
    "gn:timezone":"Asia/Shanghai",
    "iso:country":"CN",
    "name:zho_x_preferred":[
        "\u6cf8\u6e1a"
    ],
    "wof:name":"Luzhu",
    "wof:placetype":"locality"
},
  "geometry": {"coordinates":[113.3907,28.23758],"type":"Point"}
}