{
  "type": "Feature",
  "properties": {
    "gn:admin1_code":"15.0",
    "gn:asciiname":"Dongding",
    "gn:country_code":"CN",
    "gn:dem":2358,
    "gn:feature_class":"P",
    "gn:feature_code":"PPL",
    "gn:name":"Dongding",
    "gn:population":0,
    "gn:timezone":"Asia/Shanghai",
    "iso:country":"CN",
    "name:zho_x_preferred":[
        "\u4e1c\u9876"
    ],
    "wof:name":"Dongding",
    "wof:placetype":"locality"
},
  "geometry": {"coordinates":[101.955,38.0029],"type":"Point"}
}