{
  "type": "Feature",
  "properties": {
    "gn:admin1_code":"02",
    "gn:asciiname":"Tianyang",
    "gn:cc2":"CN",
    "gn:country_code":"CN",
    "gn:dem":4,
    "gn:feature_class":"P",
    "gn:feature_code":"PPL",
    "gn:name":"Tianyang",
    "gn:population":0,
    "gn:timezone":"Asia/Shanghai",
    "iso:country":"CN",
    "name:und_x_variant":[
        "T\u2019ien-yang",
        "Tianyang"
    ],
    "wof:name":"Tianyang",
    "wof:placetype":"locality"
},
  "geometry": {"coordinates":[121.36778,28.42028],"type":"Point"}
}