{
  "type": "Feature",
  "properties": {
    "gn:admin1_code":"14.0",
    "gn:asciiname":"Dongru",
    "gn:country_code":"CN",
    "gn:dem":3562,
    "gn:feature_class":"P",
    "gn:feature_code":"PPL",
    "gn:name":"Dongru",
    "gn:population":0,
    "gn:timezone":"Asia/Urumqi",
    "iso:country":"CN",
    "name:zho_x_preferred":[
        "\u8463\u5165"
    ],
    "wof:name":"Dongru",
    "wof:placetype":"locality"
},
  "geometry": {"coordinates":[94.01685999999999,30.06575],"type":"Point"}
}