{
  "type": "Feature",
  "properties": {
    "gn:admin1_code":"22",
    "gn:asciiname":"Duiyingzi",
    "gn:cc2":"CN",
    "gn:country_code":"CN",
    "gn:dem":206,
    "gn:feature_class":"P",
    "gn:feature_code":"PPL",
    "gn:name":"Duiyingzi",
    "gn:population":0,
    "gn:timezone":"Asia/Shanghai",
    "iso:country":"CN",
    "name:und_x_variant":[
        "Tui-ying-tzu",
        "Duiyingzi"
    ],
    "wof:name":"Duiyingzi",
    "wof:placetype":"locality"
},
  "geometry": {"coordinates":[116.74194,40.63417000000001],"type":"Point"}
}