{
  "type": "Feature",
  "properties": {
    "gn:admin1_code":"12.0",
    "gn:asciiname":"Xinwuwan",
    "gn:country_code":"CN",
    "gn:dem":436,
    "gn:feature_class":"P",
    "gn:feature_code":"PPL",
    "gn:name":"Xinwuwan",
    "gn:population":0,
    "gn:timezone":"Asia/Shanghai",
    "iso:country":"CN",
    "name:und_x_variant":[
        "\u65b0\u5c4b\u5846"
    ],
    "wof:name":"Xinwuwan",
    "wof:placetype":"locality"
},
  "geometry": {"coordinates":[115.46966,30.98352],"type":"Point"}
}