{
  "type": "Feature",
  "properties": {
    "gn:admin1_code":"16.0",
    "gn:asciiname":"Shijitang",
    "gn:country_code":"CN",
    "gn:dem":81,
    "gn:feature_class":"P",
    "gn:feature_code":"PPL",
    "gn:name":"Shijitang",
    "gn:population":0,
    "gn:timezone":"Asia/Shanghai",
    "iso:country":"CN",
    "name:zho_x_preferred":[
        "\u77f3\u57fa\u5858"
    ],
    "wof:name":"Shijitang",
    "wof:placetype":"locality"
},
  "geometry": {"coordinates":[110.00700000000001,22.4048],"type":"Point"}
}