{
  "type": "Feature",
  "properties": {
    "gn:admin1_code":"14",
    "gn:asciiname":"Qulong",
    "gn:country_code":"CN",
    "gn:dem":4167,
    "gn:feature_class":"P",
    "gn:feature_code":"PPL",
    "gn:name":"Qulong",
    "gn:population":0,
    "gn:timezone":"Asia/Urumqi",
    "iso:country":"CN",
    "name:zho_x_preferred":[
        "\u66f2\u9f99"
    ],
    "wof:name":"Qulong",
    "wof:placetype":"locality"
},
  "geometry": {"coordinates":[89.3591,29.4351],"type":"Point"}
}