{
  "type": "Feature",
  "properties": {
    "gn:admin1_code":"26.0",
    "gn:asciiname":"Xiahongduanqiao",
    "gn:country_code":"CN",
    "gn:dem":1037,
    "gn:feature_class":"P",
    "gn:feature_code":"PPL",
    "gn:name":"Xiahongduanqiao",
    "gn:population":0,
    "gn:timezone":"Asia/Shanghai",
    "iso:country":"CN",
    "name:zho_x_preferred":[
        "\u4e0b\u7ea2\u65ad\u6865"
    ],
    "wof:name":"Xiahongduanqiao",
    "wof:placetype":"locality"
},
  "geometry": {"coordinates":[111.00848999999999,39.42112],"type":"Point"}
}