{
  "type": "Feature",
  "properties": {
    "gn:admin1_code":"8.0",
    "gn:asciiname":"Dongdahucun",
    "gn:country_code":"CN",
    "gn:dem":137,
    "gn:feature_class":"P",
    "gn:feature_code":"PPL",
    "gn:name":"Dongdahucun",
    "gn:population":0,
    "gn:timezone":"Asia/Shanghai",
    "iso:country":"CN",
    "name:zho_x_preferred":[
        "\u4e1c\u8fbe\u80e1\u6751"
    ],
    "wof:name":"Dongdahucun",
    "wof:placetype":"locality"
},
  "geometry": {"coordinates":[126.63545999999999,46.34591],"type":"Point"}
}