{
  "type": "Feature",
  "properties": {
    "gn:admin1_code":"8.0",
    "gn:asciiname":"Banyuancun",
    "gn:country_code":"CN",
    "gn:dem":276,
    "gn:feature_class":"P",
    "gn:feature_code":"PPL",
    "gn:name":"Banyuancun",
    "gn:population":0,
    "gn:timezone":"Asia/Shanghai",
    "iso:country":"CN",
    "name:zho_x_preferred":[
        "\u677f\u9662\u6751"
    ],
    "wof:name":"Banyuancun",
    "wof:placetype":"locality"
},
  "geometry": {"coordinates":[129.82414,44.71667],"type":"Point"}
}