{
  "type": "Feature",
  "properties": {
    "gn:admin1_code":"18",
    "gn:asciiname":"Yejizhai",
    "gn:country_code":"CN",
    "gn:dem":1023,
    "gn:feature_class":"P",
    "gn:feature_code":"PPL",
    "gn:name":"Yejizhai",
    "gn:population":0,
    "gn:timezone":"Asia/Shanghai",
    "iso:country":"CN",
    "name:zho_x_preferred":[
        "\u91ce\u9e21\u5be8"
    ],
    "wof:name":"Yejizhai",
    "wof:placetype":"locality"
},
  "geometry": {"coordinates":[106.509,25.8258],"type":"Point"}
}