{
  "type": "Feature",
  "properties": {
    "gn:admin1_code":"1.0",
    "gn:asciiname":"Gaoloucun",
    "gn:country_code":"CN",
    "gn:dem":31,
    "gn:feature_class":"P",
    "gn:feature_code":"PPL",
    "gn:name":"Gaoloucun",
    "gn:population":0,
    "gn:timezone":"Asia/Shanghai",
    "iso:country":"CN",
    "name:zho_x_preferred":[
        "\u9ad8\u697c\u6751"
    ],
    "wof:name":"Gaoloucun",
    "wof:placetype":"locality"
},
  "geometry": {"coordinates":[116.42108,33.68768],"type":"Point"}
}