{
  "type": "Feature",
  "properties": {
    "gn:admin1_code":"32.0",
    "gn:asciiname":"Baohe",
    "gn:country_code":"CN",
    "gn:dem":421,
    "gn:feature_class":"P",
    "gn:feature_code":"PPL",
    "gn:name":"Baohe",
    "gn:population":0,
    "gn:timezone":"Asia/Shanghai",
    "iso:country":"CN",
    "name:zho_x_preferred":[
        "\u4fdd\u548c"
    ],
    "wof:name":"Baohe",
    "wof:placetype":"locality"
},
  "geometry": {"coordinates":[105.51900000000001,31.1389],"type":"Point"}
}