{
  "type": "Feature",
  "properties": {
    "gn:admin1_code":"18",
    "gn:asciiname":"Baguzhai",
    "gn:country_code":"CN",
    "gn:dem":1863,
    "gn:feature_class":"P",
    "gn:feature_code":"PPL",
    "gn:name":"Baguzhai",
    "gn:population":0,
    "gn:timezone":"Asia/Shanghai",
    "iso:country":"CN",
    "name:zho_x_preferred":[
        "\u6252\u8c37\u5be8"
    ],
    "wof:name":"Baguzhai",
    "wof:placetype":"locality"
},
  "geometry": {"coordinates":[104.916,26.6291],"type":"Point"}
}