{
  "type": "Feature",
  "properties": {
    "gn:admin1_code":"8.0",
    "gn:asciiname":"Sanrenbancun",
    "gn:country_code":"CN",
    "gn:dem":111,
    "gn:feature_class":"P",
    "gn:feature_code":"PPL",
    "gn:name":"Sanrenbancun",
    "gn:population":0,
    "gn:timezone":"Asia/Shanghai",
    "iso:country":"CN",
    "name:zho_x_preferred":[
        "\u4e09\u4eba\u73ed\u6751"
    ],
    "wof:name":"Sanrenbancun",
    "wof:placetype":"locality"
},
  "geometry": {"coordinates":[132.02115000000001,45.60742],"type":"Point"}
}