{
  "type": "Feature",
  "properties": {
    "gn:admin1_code":"11.0",
    "gn:asciiname":"Zoujiawan",
    "gn:country_code":"CN",
    "gn:dem":281,
    "gn:feature_class":"P",
    "gn:feature_code":"PPL",
    "gn:name":"Zoujiawan",
    "gn:population":0,
    "gn:timezone":"Asia/Shanghai",
    "iso:country":"CN",
    "name:zho_x_preferred":[
        "\u90b9\u5bb6\u6e7e"
    ],
    "wof:name":"Zoujiawan",
    "wof:placetype":"locality"
},
  "geometry": {"coordinates":[113.49657000000001,27.79517],"type":"Point"}
}