{
  "type": "Feature",
  "properties": {
    "gn:admin1_code":"29.0",
    "gn:asciiname":"Muda",
    "gn:country_code":"CN",
    "gn:dem":1435,
    "gn:feature_class":"P",
    "gn:feature_code":"PPL",
    "gn:name":"Muda",
    "gn:population":0,
    "gn:timezone":"Asia/Shanghai",
    "iso:country":"CN",
    "name:ceb_x_preferred":[
        "Muda"
    ],
    "name:fra_x_preferred":[
        "Muda"
    ],
    "name:ita_x_preferred":[
        "Muda"
    ],
    "name:nld_x_preferred":[
        "Muda"
    ],
    "name:pol_x_preferred":[
        "Muda"
    ],
    "name:por_x_preferred":[
        "Muda"
    ],
    "name:spa_x_preferred":[
        "Muda"
    ],
    "name:swa_x_preferred":[
        "Muda"
    ],
    "name:swe_x_preferred":[
        "Muda"
    ],
    "name:zho_x_preferred":[
        "\u6728\u5927"
    ],
    "wof:name":"Muda",
    "wof:placetype":"locality"
},
  "geometry": {"coordinates":[103.93600000000001,24.3167],"type":"Point"}
}