{
  "type": "Feature",
  "properties": {
    "gn:admin1_code":"7.0",
    "gn:asciiname":"Peishe",
    "gn:country_code":"CN",
    "gn:dem":327,
    "gn:feature_class":"P",
    "gn:feature_code":"PPL",
    "gn:name":"Peishe",
    "gn:population":0,
    "gn:timezone":"Asia/Shanghai",
    "iso:country":"CN",
    "name:zho_x_preferred":[
        "\u57f9\u7572"
    ],
    "wof:name":"Peishe",
    "wof:placetype":"locality"
},
  "geometry": {"coordinates":[118.09528,27.67255],"type":"Point"}
}