{
  "type": "Feature",
  "properties": {
    "gn:admin1_code":"15.0",
    "gn:asciiname":"Sanlidun",
    "gn:country_code":"CN",
    "gn:dem":2168,
    "gn:feature_class":"P",
    "gn:feature_code":"PPL",
    "gn:name":"Sanlidun",
    "gn:population":0,
    "gn:timezone":"Asia/Shanghai",
    "iso:country":"CN",
    "name:zho_x_preferred":[
        "\u4e09\u91cc\u58a9"
    ],
    "wof:name":"Sanlidun",
    "wof:placetype":"locality"
},
  "geometry": {"coordinates":[104.996,35.3118],"type":"Point"}
}