{
  "type": "Feature",
  "properties": {
    "gn:admin1_code":"10.0",
    "gn:asciiname":"Yinzishan",
    "gn:country_code":"CN",
    "gn:dem":69,
    "gn:feature_class":"P",
    "gn:feature_code":"PPL",
    "gn:name":"Yinzishan",
    "gn:population":0,
    "gn:timezone":"Asia/Shanghai",
    "iso:country":"CN",
    "name:zho_x_preferred":[
        "\u94f6\u5b50\u5c71"
    ],
    "wof:name":"Yinzishan",
    "wof:placetype":"locality"
},
  "geometry": {"coordinates":[118.18749,39.92414],"type":"Point"}
}