{
  "type": "Feature",
  "properties": {
    "gn:admin1_code":"14.0",
    "gn:asciiname":"Nanma",
    "gn:country_code":"CN",
    "gn:dem":4339,
    "gn:feature_class":"P",
    "gn:feature_code":"PPL",
    "gn:name":"Nanma",
    "gn:population":0,
    "gn:timezone":"Asia/Urumqi",
    "iso:country":"CN",
    "name:mlg_x_preferred":[
        "Nanma"
    ],
    "name:zho_x_preferred":[
        "\u5357\u739b"
    ],
    "wof:name":"Nanma",
    "wof:placetype":"locality"
},
  "geometry": {"coordinates":[87.3561,29.2026],"type":"Point"}
}