{
  "type": "Feature",
  "properties": {
    "gn:admin1_code":"25",
    "gn:asciiname":"Bei'anyang",
    "gn:country_code":"CN",
    "gn:dem":82,
    "gn:feature_class":"P",
    "gn:feature_code":"PPL",
    "gn:name":"Bei\u2019anyang",
    "gn:population":0,
    "gn:timezone":"Asia/Shanghai",
    "iso:country":"CN",
    "name:und_x_variant":[
        "Bei\u2019anyang"
    ],
    "name:zho_x_preferred":[
        "\u5317\u5b89\u9633"
    ],
    "wof:name":"Bei'anyang",
    "wof:placetype":"locality"
},
  "geometry": {"coordinates":[117.43000000000001,34.8919],"type":"Point"}
}