{
  "type": "Feature",
  "properties": {
    "gn:admin1_code":"8.0",
    "gn:asciiname":"Zhongxin Miaopu",
    "gn:country_code":"CN",
    "gn:dem":445,
    "gn:feature_class":"P",
    "gn:feature_code":"PPLF",
    "gn:name":"Zhongxin Miaopu",
    "gn:population":0,
    "gn:timezone":"Asia/Shanghai",
    "iso:country":"CN",
    "name:zho_x_preferred":[
        "\u4e2d\u5fc3\u82d7\u5703"
    ],
    "wof:name":"Zhongxin Miaopu",
    "wof:placetype":"locality"
},
  "geometry": {"coordinates":[129.50155000000001,48.46727],"type":"Point"}
}