{
  "type": "Feature",
  "properties": {
    "gn:admin1_code":"16.0",
    "gn:asciiname":"Fengmu'ao",
    "gn:country_code":"CN",
    "gn:dem":501,
    "gn:feature_class":"P",
    "gn:feature_code":"PPL",
    "gn:name":"Fengmu\u2019ao",
    "gn:population":0,
    "gn:timezone":"Asia/Shanghai",
    "iso:country":"CN",
    "name:und_x_variant":[
        "Fengmu\u2019ao"
    ],
    "name:zho_x_preferred":[
        "\u67ab\u6728\u5773"
    ],
    "wof:name":"Fengmu'ao",
    "wof:placetype":"locality"
},
  "geometry": {"coordinates":[108.78700000000001,25.1009],"type":"Point"}
}