{
  "type": "Feature",
  "properties": {
    "gn:admin1_code":"15.0",
    "gn:asciiname":"Yahuo Xiacun",
    "gn:country_code":"CN",
    "gn:dem":2229,
    "gn:feature_class":"P",
    "gn:feature_code":"PPL",
    "gn:name":"Yahuo Xiacun",
    "gn:population":0,
    "gn:timezone":"Asia/Shanghai",
    "iso:country":"CN",
    "name:zho_x_preferred":[
        "\u57ad\u8c41\u4e0b\u6751"
    ],
    "wof:name":"Yahuo Xiacun",
    "wof:placetype":"locality"
},
  "geometry": {"coordinates":[105.15600000000001,34.5033],"type":"Point"}
}