{
  "type": "Feature",
  "properties": {
    "gn:admin1_code":"4.0",
    "gn:asciiname":"Yanhua Huayuan",
    "gn:country_code":"CN",
    "gn:dem":1,
    "gn:feature_class":"P",
    "gn:feature_code":"PPL",
    "gn:name":"Yanhua Huayuan",
    "gn:population":0,
    "gn:timezone":"Asia/Shanghai",
    "iso:country":"CN",
    "name:zho_x_preferred":[
        "\u71d5\u534e\u82b1\u56ed"
    ],
    "wof:name":"Yanhua Huayuan",
    "wof:placetype":"locality"
},
  "geometry": {"coordinates":[118.81506,32.15274],"type":"Point"}
}