{
  "type": "Feature",
  "properties": {
    "gn:admin1_code":"25",
    "gn:asciiname":"Ertun",
    "gn:country_code":"CN",
    "gn:dem":34,
    "gn:feature_class":"P",
    "gn:feature_code":"PPL",
    "gn:name":"Ertun",
    "gn:population":0,
    "gn:timezone":"Asia/Shanghai",
    "iso:country":"CN",
    "name:zho_x_preferred":[
        "\u4e8c\u5c6f"
    ],
    "name:zho_x_variant":[
        "\u4e8c\u5c6f\u9547"
    ],
    "wof:name":"Ertun",
    "wof:placetype":"locality"
},
  "geometry": {"coordinates":[115.91500000000001,37.0395],"type":"Point"}
}