{
  "type": "Feature",
  "properties": {
    "gn:admin1_code":"24.0",
    "gn:asciiname":"Liudongcun",
    "gn:country_code":"CN",
    "gn:dem":970,
    "gn:feature_class":"P",
    "gn:feature_code":"PPL",
    "gn:name":"Liudongcun",
    "gn:population":0,
    "gn:timezone":"Asia/Shanghai",
    "iso:country":"CN",
    "name:zho_x_preferred":[
        "\u516d\u6d1e\u6751"
    ],
    "wof:name":"Liudongcun",
    "wof:placetype":"locality"
},
  "geometry": {"coordinates":[113.28183,36.54539000000001],"type":"Point"}
}