{
  "type": "Feature",
  "properties": {
    "gn:admin1_code":"02",
    "gn:asciiname":"Hongtang",
    "gn:country_code":"CN",
    "gn:dem":7,
    "gn:feature_class":"P",
    "gn:feature_code":"PPLA4",
    "gn:name":"Hongtang",
    "gn:population":0,
    "gn:timezone":"Asia/Shanghai",
    "iso:country":"CN",
    "name:und_x_variant":[
        "Hung-t\u2019ang-hsiang",
        "Hongtangxiang",
        "Hongtang Zhen",
        "Hongtang"
    ],
    "name:zho_x_preferred":[
        "\u6d2a\u5858"
    ],
    "name:zho_x_variant":[
        "\u6d2a\u5858\u9547"
    ],
    "wof:name":"Hongtang",
    "wof:placetype":"locality"
},
  "geometry": {"coordinates":[121.50606999999999,29.95175],"type":"Point"}
}