{
  "type": "Feature",
  "properties": {
    "gn:admin1_code":"10.0",
    "gn:asciiname":"Dabalizhuang",
    "gn:country_code":"CN",
    "gn:dem":17,
    "gn:feature_class":"P",
    "gn:feature_code":"PPL",
    "gn:name":"Dabalizhuang",
    "gn:population":0,
    "gn:timezone":"Asia/Shanghai",
    "iso:country":"CN",
    "name:zho_x_preferred":[
        "\u5927\u516b\u91cc\u5e84"
    ],
    "wof:name":"Dabalizhuang",
    "wof:placetype":"locality"
},
  "geometry": {"coordinates":[116.065,38.1985],"type":"Point"}
}