{
  "type": "Feature",
  "properties": {
    "gn:admin1_code":"11",
    "gn:asciiname":"Shuangjiangkou",
    "gn:country_code":"CN",
    "gn:dem":105,
    "gn:feature_class":"P",
    "gn:feature_code":"PPL",
    "gn:name":"Shuangjiangkou",
    "gn:population":0,
    "gn:timezone":"Asia/Shanghai",
    "iso:country":"CN",
    "name:zho_x_preferred":[
        "\u53cc\u6c5f\u53e3"
    ],
    "wof:name":"Shuangjiangkou",
    "wof:placetype":"locality"
},
  "geometry": {"coordinates":[113.46899000000001,28.6372],"type":"Point"}
}