{
  "type": "Feature",
  "properties": {
    "gn:admin1_code":"24.0",
    "gn:asciiname":"Chugoucun",
    "gn:country_code":"CN",
    "gn:dem":795,
    "gn:feature_class":"P",
    "gn:feature_code":"PPL",
    "gn:name":"Chugoucun",
    "gn:population":0,
    "gn:timezone":"Asia/Shanghai",
    "iso:country":"CN",
    "name:zho_x_preferred":[
        "\u9504\u6c9f\u6751"
    ],
    "wof:name":"Chugoucun",
    "wof:placetype":"locality"
},
  "geometry": {"coordinates":[110.90322999999999,37.42956],"type":"Point"}
}