{
  "type": "Feature",
  "properties": {
    "gn:admin1_code":"16.0",
    "gn:asciiname":"Shangnanwa",
    "gn:country_code":"CN",
    "gn:dem":1155,
    "gn:feature_class":"P",
    "gn:feature_code":"PPL",
    "gn:name":"Shangnanwa",
    "gn:population":0,
    "gn:timezone":"Asia/Shanghai",
    "iso:country":"CN",
    "name:zho_x_preferred":[
        "\u4e0a\u5357\u74e6"
    ],
    "wof:name":"Shangnanwa",
    "wof:placetype":"locality"
},
  "geometry": {"coordinates":[106.292,24.6019],"type":"Point"}
}