{
  "type": "Feature",
  "properties": {
    "gn:admin1_code":"18",
    "gn:asciiname":"Wanlitou",
    "gn:country_code":"CN",
    "gn:dem":1035,
    "gn:feature_class":"P",
    "gn:feature_code":"PPL",
    "gn:name":"Wanlitou",
    "gn:population":0,
    "gn:timezone":"Asia/Shanghai",
    "iso:country":"CN",
    "name:zho_x_preferred":[
        "\u6e7e\u91cc\u5934"
    ],
    "wof:name":"Wanlitou",
    "wof:placetype":"locality"
},
  "geometry": {"coordinates":[106.718,28.0861],"type":"Point"}
}