{
  "type": "Feature",
  "properties": {
    "gn:admin1_code":"6.0",
    "gn:asciiname":"Beizuoka",
    "gn:country_code":"CN",
    "gn:dem":3739,
    "gn:feature_class":"P",
    "gn:feature_code":"PPL",
    "gn:name":"Beizuoka",
    "gn:population":0,
    "gn:timezone":"Asia/Urumqi",
    "iso:country":"CN",
    "name:zho_x_preferred":[
        "\u80cc\u4f5c\u5361"
    ],
    "wof:name":"Beizuoka",
    "wof:placetype":"locality"
},
  "geometry": {"coordinates":[96.91132,32.28692],"type":"Point"}
}