{
  "type": "Feature",
  "properties": {
    "gn:admin1_code":"11.0",
    "gn:asciiname":"Youdatou",
    "gn:country_code":"CN",
    "gn:dem":155,
    "gn:feature_class":"P",
    "gn:feature_code":"PPL",
    "gn:name":"Youdatou",
    "gn:population":0,
    "gn:timezone":"Asia/Shanghai",
    "iso:country":"CN",
    "name:zho_x_preferred":[
        "\u5c24\u5927\u5934"
    ],
    "wof:name":"Youdatou",
    "wof:placetype":"locality"
},
  "geometry": {"coordinates":[111.90915,27.75084],"type":"Point"}
}