{
  "type": "Feature",
  "properties": {
    "gn:admin1_code":"16.0",
    "gn:asciiname":"Jin'e",
    "gn:country_code":"CN",
    "gn:dem":274,
    "gn:feature_class":"P",
    "gn:feature_code":"PPL",
    "gn:name":"Jin\u2019e",
    "gn:population":0,
    "gn:timezone":"Asia/Shanghai",
    "iso:country":"CN",
    "name:und_x_variant":[
        "Jin\u2019e"
    ],
    "name:zho_x_preferred":[
        "\u91d1\u9e45"
    ],
    "wof:name":"Jin'e",
    "wof:placetype":"locality"
},
  "geometry": {"coordinates":[111.379,24.3202],"type":"Point"}
}