{
  "type": "Feature",
  "properties": {
    "gn:admin1_code":"12.0",
    "gn:asciiname":"Chenghe",
    "gn:country_code":"CN",
    "gn:dem":42,
    "gn:feature_class":"P",
    "gn:feature_code":"PPL",
    "gn:name":"Chenghe",
    "gn:population":0,
    "gn:timezone":"Asia/Shanghai",
    "iso:country":"CN",
    "name:zho_x_preferred":[
        "\u57ce\u6cb3"
    ],
    "wof:name":"Chenghe",
    "wof:placetype":"locality"
},
  "geometry": {"coordinates":[112.42028000000001,30.58488],"type":"Point"}
}