{
  "type": "Feature",
  "properties": {
    "gn:admin1_code":"19.0",
    "gn:asciiname":"Hahushuocun",
    "gn:country_code":"CN",
    "gn:dem":73,
    "gn:feature_class":"P",
    "gn:feature_code":"PPL",
    "gn:name":"Hahushuocun",
    "gn:population":0,
    "gn:timezone":"Asia/Shanghai",
    "iso:country":"CN",
    "name:zho_x_preferred":[
        "\u54c8\u6237\u7855\u6751"
    ],
    "wof:name":"Hahushuocun",
    "wof:placetype":"locality"
},
  "geometry": {"coordinates":[123.02889,42.55526],"type":"Point"}
}