{
  "type": "Feature",
  "properties": {
    "gn:admin1_code":"20",
    "gn:asciiname":"Xianfeng Linchang",
    "gn:country_code":"CN",
    "gn:dem":767,
    "gn:feature_class":"P",
    "gn:feature_code":"PPLF",
    "gn:name":"Xianfeng Linchang",
    "gn:population":0,
    "gn:timezone":"Asia/Shanghai",
    "iso:country":"CN",
    "wof:name":"Xianfeng Linchang",
    "wof:placetype":"locality"
},
  "geometry": {"coordinates":[122.18416999999999,51.79306],"type":"Point"}
}