{
  "type": "Feature",
  "properties": {
    "gn:admin1_code":"15.0",
    "gn:asciiname":"Cuijiashan",
    "gn:country_code":"CN",
    "gn:dem":1835,
    "gn:feature_class":"P",
    "gn:feature_code":"PPL",
    "gn:name":"Cuijiashan",
    "gn:population":0,
    "gn:timezone":"Asia/Shanghai",
    "iso:country":"CN",
    "name:und_x_variant":[
        "\u5d14\u5bb6\u5c71"
    ],
    "wof:name":"Cuijiashan",
    "wof:placetype":"locality"
},
  "geometry": {"coordinates":[105.13101,35.10873],"type":"Point"}
}