{
  "type": "Feature",
  "properties": {
    "gn:admin1_code":"30",
    "gn:asciiname":"Hengjiang",
    "gn:country_code":"CN",
    "gn:dem":151,
    "gn:feature_class":"P",
    "gn:feature_code":"PPL",
    "gn:name":"Hengjiang",
    "gn:population":0,
    "gn:timezone":"Asia/Shanghai",
    "iso:country":"CN",
    "name:und_x_variant":[
        "\u6a2a\u6c5f"
    ],
    "name:zho_x_preferred":[
        "\u6a2a\u6c5f"
    ],
    "wof:name":"Hengjiang",
    "wof:placetype":"locality"
},
  "geometry": {"coordinates":[113.60193999999998,23.98833],"type":"Point"}
}