{
  "type": "Feature",
  "properties": {
    "gn:admin1_code":"29.0",
    "gn:asciiname":"Andi",
    "gn:country_code":"CN",
    "gn:dem":2059,
    "gn:feature_class":"P",
    "gn:feature_code":"PPL",
    "gn:name":"Andi",
    "gn:population":0,
    "gn:timezone":"Asia/Shanghai",
    "iso:country":"CN",
    "name:und_x_variant":[
        "\u5b89\u8fea"
    ],
    "wof:name":"Andi",
    "wof:placetype":"locality"
},
  "geometry": {"coordinates":[104.185,26.1143],"type":"Point"}
}