{
  "type": "Feature",
  "properties": {
    "gn:admin1_code":"14.0",
    "gn:asciiname":"Sela",
    "gn:country_code":"CN",
    "gn:dem":4369,
    "gn:feature_class":"P",
    "gn:feature_code":"PPL",
    "gn:name":"Sela",
    "gn:population":0,
    "gn:timezone":"Asia/Urumqi",
    "iso:country":"CN",
    "name:bod_x_preferred":[
        "S\u00ealhag"
    ],
    "name:zho_x_preferred":[
        "Sela"
    ],
    "name:zho_x_variant":[
        "\u8272\u62c9",
        "Jilipu Gongshe",
        "\u5409\u91cc\u666e\u516c\u793e"
    ],
    "wof:name":"Sela",
    "wof:placetype":"locality"
},
  "geometry": {"coordinates":[92.60899999999999,29.009],"type":"Point"}
}