{
  "type": "Feature",
  "properties": {
    "gn:admin1_code":"26.0",
    "gn:asciiname":"Luosigou",
    "gn:country_code":"CN",
    "gn:dem":1216,
    "gn:feature_class":"P",
    "gn:feature_code":"PPL",
    "gn:name":"Luosigou",
    "gn:population":0,
    "gn:timezone":"Asia/Shanghai",
    "iso:country":"CN",
    "name:zho_x_preferred":[
        "\u87ba\u4e1d\u6c9f"
    ],
    "wof:name":"Luosigou",
    "wof:placetype":"locality"
},
  "geometry": {"coordinates":[110.29325,33.37195999999999],"type":"Point"}
}