{
  "type": "Feature",
  "properties": {
    "gn:admin1_code":"10",
    "gn:asciiname":"Wan'an",
    "gn:country_code":"CN",
    "gn:dem":17,
    "gn:feature_class":"P",
    "gn:feature_code":"PPL",
    "gn:name":"Wan\u2019an",
    "gn:population":0,
    "gn:timezone":"Asia/Shanghai",
    "iso:country":"CN",
    "name:ceb_x_preferred":[
        "Wan\u2019an"
    ],
    "name:deu_x_preferred":[
        "Wan\u2019an"
    ],
    "name:swe_x_preferred":[
        "Wan\u2019an"
    ],
    "wof:name":"Wan'an",
    "wof:placetype":"locality"
},
  "geometry": {"coordinates":[115.65056,38.64056],"type":"Point"}
}