{
  "type": "Feature",
  "properties": {
    "gn:admin1_code":"26",
    "gn:asciiname":"Nandan",
    "gn:country_code":"CN",
    "gn:dem":1034,
    "gn:feature_class":"P",
    "gn:feature_code":"PPL",
    "gn:name":"Nandan",
    "gn:population":0,
    "gn:timezone":"Asia/Shanghai",
    "iso:country":"CN",
    "name:und_x_variant":[
        "\u5357\u4e39"
    ],
    "name:zho_x_preferred":[
        "\u5357\u4e39"
    ],
    "wof:name":"Nandan",
    "wof:placetype":"locality"
},
  "geometry": {"coordinates":[108.43805999999999,34.75472],"type":"Point"}
}