{
  "type": "Feature",
  "properties": {
    "gn:admin1_code":"12.0",
    "gn:asciiname":"Jiangjia Liangting",
    "gn:country_code":"CN",
    "gn:dem":51,
    "gn:feature_class":"P",
    "gn:feature_code":"PPL",
    "gn:name":"Jiangjia Liangting",
    "gn:population":0,
    "gn:timezone":"Asia/Shanghai",
    "iso:country":"CN",
    "name:zho_x_preferred":[
        "Jiangjia Liangting"
    ],
    "name:zho_x_variant":[
        "\u6c5f\u5bb6\u51c9\u4ead"
    ],
    "wof:name":"Jiangjia Liangting",
    "wof:placetype":"locality"
},
  "geometry": {"coordinates":[115.32796999999999,30.23265],"type":"Point"}
}