{
  "type": "Feature",
  "properties": {
    "gn:admin1_code":"4.0",
    "gn:asciiname":"Tiaohecun",
    "gn:country_code":"CN",
    "gn:dem":5,
    "gn:feature_class":"P",
    "gn:feature_code":"PPL",
    "gn:name":"Tiaohecun",
    "gn:population":0,
    "gn:timezone":"Asia/Shanghai",
    "iso:country":"CN",
    "name:zho_x_preferred":[
        "\u6761\u6cb3\u6751"
    ],
    "wof:name":"Tiaohecun",
    "wof:placetype":"locality"
},
  "geometry": {"coordinates":[119.58533,34.08148],"type":"Point"}
}