{
  "type": "Feature",
  "properties": {
    "gn:admin1_code":"26",
    "gn:asciiname":"Tongguan",
    "gn:cc2":"CN",
    "gn:country_code":"CN",
    "gn:dem":577,
    "gn:feature_class":"P",
    "gn:feature_code":"PPL",
    "gn:name":"Tongguan",
    "gn:population":0,
    "gn:timezone":"Asia/Shanghai",
    "iso:country":"CN",
    "name:deu_x_preferred":[
        "Tongguan"
    ],
    "name:und_x_variant":[
        "T\u2019ung-kuan",
        "Wucun",
        "Tung-hsieh-chia",
        "Wu-ts\u2019un",
        "Tongguan"
    ],
    "wof:name":"Tongguan",
    "wof:placetype":"locality"
},
  "geometry": {"coordinates":[110.2375,34.54361],"type":"Point"}
}