{
  "type": "Feature",
  "properties": {
    "gn:admin1_code":"32.0",
    "gn:asciiname":"Shabazi",
    "gn:country_code":"CN",
    "gn:dem":553,
    "gn:feature_class":"P",
    "gn:feature_code":"PPL",
    "gn:name":"Shabazi",
    "gn:population":0,
    "gn:timezone":"Asia/Shanghai",
    "iso:country":"CN",
    "name:zho_x_preferred":[
        "\u6c99\u575d\u5b50"
    ],
    "wof:name":"Shabazi",
    "wof:placetype":"locality"
},
  "geometry": {"coordinates":[104.572,29.7543],"type":"Point"}
}