{
  "type": "Feature",
  "properties": {
    "gn:admin1_code":"26.0",
    "gn:asciiname":"Yinchanggou",
    "gn:country_code":"CN",
    "gn:dem":848,
    "gn:feature_class":"P",
    "gn:feature_code":"PPL",
    "gn:name":"Yinchanggou",
    "gn:population":0,
    "gn:timezone":"Asia/Shanghai",
    "iso:country":"CN",
    "name:und_x_variant":[
        "\u94f6\u5382\u6c9f"
    ],
    "wof:name":"Yinchanggou",
    "wof:placetype":"locality"
},
  "geometry": {"coordinates":[107.59113000000001,33.3938],"type":"Point"}
}