{
  "type": "Feature",
  "properties": {
    "gn:admin1_code":"03",
    "gn:asciiname":"Chongxian",
    "gn:country_code":"CN",
    "gn:dem":238,
    "gn:feature_class":"P",
    "gn:feature_code":"PPLA4",
    "gn:name":"Chongxian",
    "gn:population":0,
    "gn:timezone":"Asia/Shanghai",
    "iso:country":"CN",
    "name:und_x_variant":[
        "Ch\u2019ung-hsien",
        "Ch\u2019ung-hsien-hs\u00fc",
        "Chongxian",
        "\u5d07\u8d24",
        "Chongxian Xiang",
        "\u5d07\u8d24\u4e61"
    ],
    "wof:name":"Chongxian",
    "wof:placetype":"locality"
},
  "geometry": {"coordinates":[115.34389,26.54889],"type":"Point"}
}