{
  "type": "Feature",
  "properties": {
    "gn:admin1_code":"24.0",
    "gn:asciiname":"Xialiuqi",
    "gn:country_code":"CN",
    "gn:dem":907,
    "gn:feature_class":"P",
    "gn:feature_code":"PPL",
    "gn:name":"Xialiuqi",
    "gn:population":0,
    "gn:timezone":"Asia/Shanghai",
    "iso:country":"CN",
    "name:zho_x_preferred":[
        "\u4e0b\u6d41\u789b"
    ],
    "wof:name":"Xialiuqi",
    "wof:placetype":"locality"
},
  "geometry": {"coordinates":[111.09851,38.95062],"type":"Point"}
}