{
  "type": "Feature",
  "properties": {
    "gn:admin1_code":"18.0",
    "gn:asciiname":"Qiedong",
    "gn:country_code":"CN",
    "gn:dem":813,
    "gn:feature_class":"P",
    "gn:feature_code":"PPL",
    "gn:name":"Qiedong",
    "gn:population":0,
    "gn:timezone":"Asia/Shanghai",
    "iso:country":"CN",
    "name:zho_x_preferred":[
        "\u8304\u6d1e"
    ],
    "wof:name":"Qiedong",
    "wof:placetype":"locality"
},
  "geometry": {"coordinates":[108.517,26.9587],"type":"Point"}
}