{
  "type": "Feature",
  "properties": {
    "gn:admin1_code":"29.0",
    "gn:asciiname":"Shaowachong",
    "gn:country_code":"CN",
    "gn:dem":1612,
    "gn:feature_class":"P",
    "gn:feature_code":"PPL",
    "gn:name":"Shaowachong",
    "gn:population":0,
    "gn:timezone":"Asia/Shanghai",
    "iso:country":"CN",
    "name:zho_x_preferred":[
        "\u70e7\u74e6\u51b2"
    ],
    "wof:name":"Shaowachong",
    "wof:placetype":"locality"
},
  "geometry": {"coordinates":[103.77800000000001,23.5905],"type":"Point"}
}