{
  "type": "Feature",
  "properties": {
    "gn:admin1_code":"29.0",
    "gn:asciiname":"Liujia",
    "gn:country_code":"CN",
    "gn:dem":2029,
    "gn:feature_class":"P",
    "gn:feature_code":"PPL",
    "gn:name":"Liujia",
    "gn:population":0,
    "gn:timezone":"Asia/Shanghai",
    "iso:country":"CN",
    "name:ceb_x_preferred":[
        "Liujia"
    ],
    "name:deu_x_preferred":[
        "Liujia"
    ],
    "name:swe_x_preferred":[
        "Liujia"
    ],
    "name:zho_x_preferred":[
        "\u5218\u5bb6"
    ],
    "wof:name":"Liujia",
    "wof:placetype":"locality"
},
  "geometry": {"coordinates":[100.131,25.0937],"type":"Point"}
}