{
  "type": "Feature",
  "properties": {
    "gn:admin1_code":"14.0",
    "gn:asciiname":"Ranggulie",
    "gn:country_code":"CN",
    "gn:dem":4694,
    "gn:feature_class":"P",
    "gn:feature_code":"PPL",
    "gn:name":"Ranggulie",
    "gn:population":0,
    "gn:timezone":"Asia/Urumqi",
    "iso:country":"CN",
    "name:zho_x_preferred":[
        "\u8ba9\u53e4\u52a3"
    ],
    "wof:name":"Ranggulie",
    "wof:placetype":"locality"
},
  "geometry": {"coordinates":[92.19893999999999,27.92799],"type":"Point"}
}