{
  "type": "Feature",
  "properties": {
    "gn:admin1_code":"30",
    "gn:asciiname":"Dongyang",
    "gn:country_code":"CN",
    "gn:dem":6,
    "gn:feature_class":"P",
    "gn:feature_code":"PPL",
    "gn:name":"Dongyang",
    "gn:population":0,
    "gn:timezone":"Asia/Shanghai",
    "iso:country":"CN",
    "name:ara_x_preferred":[
        "\u062f\u0648\u0646\u063a \u064a\u0627\u0646\u063a"
    ],
    "name:ceb_x_preferred":[
        "Dongyang"
    ],
    "name:ces_x_preferred":[
        "Tung-jang"
    ],
    "name:deu_x_preferred":[
        "Dongyang"
    ],
    "name:fas_x_preferred":[
        "\u062f\u0648\u0646\u06af\u200c\u06cc\u0627\u0646\u06af"
    ],
    "name:fra_x_preferred":[
        "Dongyang"
    ],
    "name:ita_x_preferred":[
        "Dongyang"
    ],
    "name:jpn_x_preferred":[
        "\u6771\u967d\u5e02"
    ],
    "name:kik_x_preferred":[
        "Dongyang"
    ],
    "name:kor_x_preferred":[
        "\ub465\uc591\uc2dc"
    ],
    "name:mlg_x_preferred":[
        "Dongyang"
    ],
    "name:nld_x_preferred":[
        "Dongyang"
    ],
    "name:nor_x_preferred":[
        "Dongyang"
    ],
    "name:pol_x_preferred":[
        "Dongyang"
    ],
    "name:swe_x_preferred":[
        "Dongyang"
    ],
    "name:tgl_x_preferred":[
        "Dongyang"
    ],
    "name:ukr_x_preferred":[
        "\u0414\u043e\u043d\u044f\u043d"
    ],
    "name:urd_x_preferred":[
        "\u0688\u0648\u0646\u06af\u06cc\u0627\u0646\u06af"
    ],
    "name:vie_x_preferred":[
        "\u0110\u00f4ng D\u01b0\u01a1ng"
    ],
    "name:war_x_preferred":[
        "Dongyang"
    ],
    "name:wuu_x_preferred":[
        "\u4e1c\u9633\u5e02"
    ],
    "name:zho_x_preferred":[
        "\u4e1c\u9633"
    ],
    "name:zho_x_variant":[
        "\u4e1c\u9633\u5e02"
    ],
    "wof:name":"Dongyang",
    "wof:placetype":"locality"
},
  "geometry": {"coordinates":[112.95793999999999,22.10498],"type":"Point"}
}