{
  "type": "Feature",
  "properties": {
    "gn:admin1_code":"32.0",
    "gn:asciiname":"Laoxia",
    "gn:country_code":"CN",
    "gn:dem":2588,
    "gn:feature_class":"P",
    "gn:feature_code":"PPL",
    "gn:name":"Laoxia",
    "gn:population":0,
    "gn:timezone":"Asia/Shanghai",
    "iso:country":"CN",
    "name:zho_x_preferred":[
        "\u8001\u5477"
    ],
    "wof:name":"Laoxia",
    "wof:placetype":"locality"
},
  "geometry": {"coordinates":[102.69157,27.86903],"type":"Point"}
}