{
  "type": "Feature",
  "properties": {
    "gn:admin1_code":"14.0",
    "gn:asciiname":"Baguocun",
    "gn:country_code":"CN",
    "gn:dem":4698,
    "gn:feature_class":"P",
    "gn:feature_code":"PPL",
    "gn:name":"Baguocun",
    "gn:population":0,
    "gn:timezone":"Asia/Urumqi",
    "iso:country":"CN",
    "name:zho_x_preferred":[
        "\u5df4\u679c\u6751"
    ],
    "wof:name":"Baguocun",
    "wof:placetype":"locality"
},
  "geometry": {"coordinates":[92.76767,32.204],"type":"Point"}
}