{
  "type": "Feature",
  "properties": {
    "gn:admin1_code":"4.0",
    "gn:asciiname":"Yixingsha",
    "gn:country_code":"CN",
    "gn:dem":4,
    "gn:feature_class":"P",
    "gn:feature_code":"PPL",
    "gn:name":"Yixingsha",
    "gn:population":0,
    "gn:timezone":"Asia/Shanghai",
    "iso:country":"CN",
    "name:zho_x_preferred":[
        "\u4e49\u5174\u6c99"
    ],
    "wof:name":"Yixingsha",
    "wof:placetype":"locality"
},
  "geometry": {"coordinates":[120.4802,32.08752],"type":"Point"}
}