{
  "type": "Feature",
  "properties": {
    "gn:admin1_code":"16.0",
    "gn:asciiname":"Luosichong",
    "gn:country_code":"CN",
    "gn:dem":1131,
    "gn:feature_class":"P",
    "gn:feature_code":"PPL",
    "gn:name":"Luosichong",
    "gn:population":0,
    "gn:timezone":"Asia/Shanghai",
    "iso:country":"CN",
    "name:zho_x_preferred":[
        "\u87ba\u86f3\u51b2"
    ],
    "wof:name":"Luosichong",
    "wof:placetype":"locality"
},
  "geometry": {"coordinates":[108.649,25.5202],"type":"Point"}
}