{
  "type": "Feature",
  "properties": {
    "gn:admin1_code":"25.0",
    "gn:asciiname":"Lugezhuang",
    "gn:country_code":"CN",
    "gn:dem":140,
    "gn:feature_class":"P",
    "gn:feature_code":"PPL",
    "gn:name":"Lugezhuang",
    "gn:population":0,
    "gn:timezone":"Asia/Shanghai",
    "iso:country":"CN",
    "name:zho_x_preferred":[
        "\u8def\u683c\u5e84"
    ],
    "wof:name":"Lugezhuang",
    "wof:placetype":"locality"
},
  "geometry": {"coordinates":[120.22826000000001,37.32644000000001],"type":"Point"}
}