{
  "type": "Feature",
  "properties": {
    "gn:admin1_code":"11",
    "gn:asciiname":"Silihe",
    "gn:country_code":"CN",
    "gn:dem":117,
    "gn:feature_class":"P",
    "gn:feature_code":"PPLA4",
    "gn:name":"Silihe",
    "gn:population":0,
    "gn:timezone":"Asia/Shanghai",
    "iso:country":"CN",
    "name:und_x_variant":[
        "Silihe Xiang"
    ],
    "name:zho_x_preferred":[
        "\u6cd7\u91cc\u6cb3"
    ],
    "name:zho_x_variant":[
        "\u6cd7\u91cc\u6cb3\u4e61"
    ],
    "wof:name":"Silihe",
    "wof:placetype":"locality"
},
  "geometry": {"coordinates":[111.82277999999999,28.41194],"type":"Point"}
}