{
  "type": "Feature",
  "properties": {
    "gn:asciiname":"Shamu",
    "gn:country_code":"CN",
    "gn:dem":73,
    "gn:feature_class":"P",
    "gn:feature_code":"PPL",
    "gn:name":"Shamu",
    "gn:population":0,
    "gn:timezone":"Asia/Shanghai",
    "iso:country":"CN",
    "name:fra_x_preferred":[
        "Shamu"
    ],
    "name:heb_x_preferred":[
        "\u05e9\u05d0\u05de\u05d5"
    ],
    "wof:name":"Shamu",
    "wof:placetype":"locality"
},
  "geometry": {"coordinates":[108.79546000000001,18.68418],"type":"Point"}
}