{
  "type": "Feature",
  "properties": {
    "gn:admin1_code":"11",
    "gn:asciiname":"Dilangping",
    "gn:country_code":"CN",
    "gn:dem":345,
    "gn:feature_class":"P",
    "gn:feature_code":"PPL",
    "gn:name":"Dilangping",
    "gn:population":0,
    "gn:timezone":"Asia/Shanghai",
    "iso:country":"CN",
    "name:zho_x_preferred":[
        "\u5730\u6717\u576a"
    ],
    "wof:name":"Dilangping",
    "wof:placetype":"locality"
},
  "geometry": {"coordinates":[109.73958,26.25218],"type":"Point"}
}