{
  "type": "Feature",
  "properties": {
    "gn:admin1_code":"16.0",
    "gn:asciiname":"Tangbianwu",
    "gn:country_code":"CN",
    "gn:dem":170,
    "gn:feature_class":"P",
    "gn:feature_code":"PPL",
    "gn:name":"Tangbianwu",
    "gn:population":0,
    "gn:timezone":"Asia/Shanghai",
    "iso:country":"CN",
    "name:zho_x_preferred":[
        "\u5858\u8fb9\u5c4b"
    ],
    "wof:name":"Tangbianwu",
    "wof:placetype":"locality"
},
  "geometry": {"coordinates":[110.626,22.9342],"type":"Point"}
}