{
  "type": "Feature",
  "properties": {
    "gn:admin1_code":"19.0",
    "gn:asciiname":"Heihuyingzi",
    "gn:country_code":"CN",
    "gn:dem":289,
    "gn:feature_class":"P",
    "gn:feature_code":"PPL",
    "gn:name":"Heihuyingzi",
    "gn:population":0,
    "gn:timezone":"Asia/Shanghai",
    "iso:country":"CN",
    "name:zho_x_preferred":[
        "\u9ed1\u864e\u8425\u5b50"
    ],
    "wof:name":"Heihuyingzi",
    "wof:placetype":"locality"
},
  "geometry": {"coordinates":[120.37989,40.99532],"type":"Point"}
}