{
  "type": "Feature",
  "properties": {
    "gn:admin1_code":"26.0",
    "gn:asciiname":"Longweimao",
    "gn:country_code":"CN",
    "gn:dem":1137,
    "gn:feature_class":"P",
    "gn:feature_code":"PPL",
    "gn:name":"Longweimao",
    "gn:population":0,
    "gn:timezone":"Asia/Shanghai",
    "iso:country":"CN",
    "name:zho_x_preferred":[
        "\u9f99\u5c3e\u5cc1"
    ],
    "wof:name":"Longweimao",
    "wof:placetype":"locality"
},
  "geometry": {"coordinates":[109.61181000000001,37.61653],"type":"Point"}
}