{
  "type": "Feature",
  "properties": {
    "gn:admin1_code":"7.0",
    "gn:asciiname":"Lifang",
    "gn:country_code":"CN",
    "gn:dem":634,
    "gn:feature_class":"P",
    "gn:feature_code":"PPL",
    "gn:name":"Lifang",
    "gn:population":0,
    "gn:timezone":"Asia/Shanghai",
    "iso:country":"CN",
    "name:und_x_variant":[
        "\u9ece\u574a"
    ],
    "name:zho_x_preferred":[
        "\u9ece\u574a"
    ],
    "wof:name":"Lifang",
    "wof:placetype":"locality"
},
  "geometry": {"coordinates":[116.62518,26.19887],"type":"Point"}
}