{
  "type": "Feature",
  "properties": {
    "gn:admin1_code":"07",
    "gn:asciiname":"Sanshan",
    "gn:country_code":"CN",
    "gn:dem":31,
    "gn:feature_class":"P",
    "gn:feature_code":"PPLA4",
    "gn:name":"Sanshan",
    "gn:population":0,
    "gn:timezone":"Asia/Shanghai",
    "iso:country":"CN",
    "name:und_x_variant":[
        "San Shah",
        "Sanshan",
        "Sanshan Zhen"
    ],
    "name:zho_x_preferred":[
        "\u4e09\u5c71"
    ],
    "name:zho_x_variant":[
        "\u4e09\u5c71\u9547"
    ],
    "wof:name":"Sanshan",
    "wof:placetype":"locality"
},
  "geometry": {"coordinates":[119.51675,25.53475],"type":"Point"}
}