{
  "type": "Feature",
  "properties": {
    "gn:admin1_code":"4.0",
    "gn:asciiname":"Fangzhuangcun",
    "gn:country_code":"CN",
    "gn:dem":31,
    "gn:feature_class":"P",
    "gn:feature_code":"PPL",
    "gn:name":"Fangzhuangcun",
    "gn:population":0,
    "gn:timezone":"Asia/Shanghai",
    "iso:country":"CN",
    "name:zho_x_preferred":[
        "\u623f\u5e84\u6751"
    ],
    "wof:name":"Fangzhuangcun",
    "wof:placetype":"locality"
},
  "geometry": {"coordinates":[118.24811,34.40051],"type":"Point"}
}