{
  "type": "Feature",
  "properties": {
    "gn:admin1_code":"25",
    "gn:asciiname":"Gongjia Zhuangzi",
    "gn:country_code":"CN",
    "gn:dem":213,
    "gn:feature_class":"P",
    "gn:feature_code":"PPL",
    "gn:name":"Gongjia Zhuangzi",
    "gn:population":0,
    "gn:timezone":"Asia/Shanghai",
    "iso:country":"CN",
    "name:zho_x_preferred":[
        "\u9f9a\u5bb6\u5e84\u5b50"
    ],
    "wof:name":"Gongjia Zhuangzi",
    "wof:placetype":"locality"
},
  "geometry": {"coordinates":[118.152,35.7609],"type":"Point"}
}