{
  "type": "Feature",
  "properties": {
    "gn:admin1_code":"29.0",
    "gn:asciiname":"Xiaxincun",
    "gn:country_code":"CN",
    "gn:dem":2340,
    "gn:feature_class":"P",
    "gn:feature_code":"PPL",
    "gn:name":"Xiaxincun",
    "gn:population":0,
    "gn:timezone":"Asia/Shanghai",
    "iso:country":"CN",
    "name:zho_x_preferred":[
        "\u4e0b\u65b0\u6751"
    ],
    "wof:name":"Xiaxincun",
    "wof:placetype":"locality"
},
  "geometry": {"coordinates":[102.267,26.0054],"type":"Point"}
}