{
  "type": "Feature",
  "properties": {
    "gn:admin1_code":"14.0",
    "gn:asciiname":"Dashaguo",
    "gn:country_code":"CN",
    "gn:dem":4354,
    "gn:feature_class":"P",
    "gn:feature_code":"PPL",
    "gn:name":"Dashaguo",
    "gn:population":0,
    "gn:timezone":"Asia/Urumqi",
    "iso:country":"CN",
    "name:zho_x_preferred":[
        "\u6253\u6c99\u679c"
    ],
    "wof:name":"Dashaguo",
    "wof:placetype":"locality"
},
  "geometry": {"coordinates":[94.05725,31.24872],"type":"Point"}
}