{
  "type": "Feature",
  "properties": {
    "gn:admin1_code":"32.0",
    "gn:asciiname":"Quanshantian",
    "gn:country_code":"CN",
    "gn:dem":561,
    "gn:feature_class":"P",
    "gn:feature_code":"PPL",
    "gn:name":"Quanshantian",
    "gn:population":0,
    "gn:timezone":"Asia/Shanghai",
    "iso:country":"CN",
    "name:zho_x_preferred":[
        "\u5708\u5c71\u7530"
    ],
    "wof:name":"Quanshantian",
    "wof:placetype":"locality"
},
  "geometry": {"coordinates":[104.758,28.2263],"type":"Point"}
}