{
  "type": "Feature",
  "properties": {
    "gn:admin1_code":"3",
    "gn:asciiname":"Taipinggang",
    "gn:country_code":"CN",
    "gn:dem":168,
    "gn:feature_class":"P",
    "gn:feature_code":"PPL",
    "gn:name":"Taipinggang",
    "gn:population":0,
    "gn:timezone":"Asia/Shanghai",
    "iso:country":"CN",
    "wof:name":"Taipinggang",
    "wof:placetype":"locality"
},
  "geometry": {"coordinates":[116.30777999999999,26.72306],"type":"Point"}
}