{
  "type": "Feature",
  "properties": {
    "gn:admin1_code":"22.0",
    "gn:asciiname":"Huanglouyuancun",
    "gn:country_code":"CN",
    "gn:dem":728,
    "gn:feature_class":"P",
    "gn:feature_code":"PPL",
    "gn:name":"Huanglouyuancun",
    "gn:population":0,
    "gn:timezone":"Asia/Shanghai",
    "iso:country":"CN",
    "name:zho_x_preferred":[
        "\u9ec4\u697c\u9662\u6751"
    ],
    "wof:name":"Huanglouyuancun",
    "wof:placetype":"locality"
},
  "geometry": {"coordinates":[115.93313000000001,40.2417],"type":"Point"}
}