{
  "type": "Feature",
  "properties": {
    "gn:admin1_code":"15.0",
    "gn:asciiname":"Nanzhuangyuan",
    "gn:country_code":"CN",
    "gn:dem":1520,
    "gn:feature_class":"P",
    "gn:feature_code":"PPL",
    "gn:name":"Nanzhuangyuan",
    "gn:population":0,
    "gn:timezone":"Asia/Shanghai",
    "iso:country":"CN",
    "name:und_x_variant":[
        "\u5357\u5e84\u586c"
    ],
    "wof:name":"Nanzhuangyuan",
    "wof:placetype":"locality"
},
  "geometry": {"coordinates":[107.55157,36.50321],"type":"Point"}
}