{
  "type": "Feature",
  "properties": {
    "gn:admin1_code":"1.0",
    "gn:asciiname":"Qilongcun",
    "gn:country_code":"CN",
    "gn:dem":7,
    "gn:feature_class":"P",
    "gn:feature_code":"PPL",
    "gn:name":"Qilongcun",
    "gn:population":0,
    "gn:timezone":"Asia/Shanghai",
    "iso:country":"CN",
    "name:zho_x_preferred":[
        "\u8d77\u5784\u6751"
    ],
    "wof:name":"Qilongcun",
    "wof:placetype":"locality"
},
  "geometry": {"coordinates":[118.60827999999999,31.4209],"type":"Point"}
}