{
  "type": "Feature",
  "properties": {
    "gn:admin1_code":"32.0",
    "gn:asciiname":"Resipu",
    "gn:country_code":"CN",
    "gn:dem":3307,
    "gn:feature_class":"P",
    "gn:feature_code":"PPL",
    "gn:name":"Resipu",
    "gn:population":0,
    "gn:timezone":"Asia/Shanghai",
    "iso:country":"CN",
    "name:zho_x_preferred":[
        "\u70ed\u601d\u666e"
    ],
    "wof:name":"Resipu",
    "wof:placetype":"locality"
},
  "geometry": {"coordinates":[99.1885,29.095],"type":"Point"}
}