{
  "type": "Feature",
  "properties": {
    "gn:admin1_code":"30.0",
    "gn:asciiname":"Xinlian",
    "gn:country_code":"CN",
    "gn:dem":369,
    "gn:feature_class":"P",
    "gn:feature_code":"PPL",
    "gn:name":"Xinlian",
    "gn:population":0,
    "gn:timezone":"Asia/Shanghai",
    "iso:country":"CN",
    "name:zho_x_preferred":[
        "Xinlian"
    ],
    "name:zho_x_variant":[
        "\u65b0\u8054"
    ],
    "wof:name":"Xinlian",
    "wof:placetype":"locality"
},
  "geometry": {"coordinates":[112.05944,24.5625],"type":"Point"}
}