{
  "type": "Feature",
  "properties": {
    "gn:admin1_code":"14.0",
    "gn:asciiname":"Zhanagong",
    "gn:country_code":"CN",
    "gn:dem":4001,
    "gn:feature_class":"P",
    "gn:feature_code":"PPL",
    "gn:name":"Zhanagong",
    "gn:population":0,
    "gn:timezone":"Asia/Urumqi",
    "iso:country":"CN",
    "name:zho_x_preferred":[
        "\u672d\u7eb3\u8d21"
    ],
    "wof:name":"Zhanagong",
    "wof:placetype":"locality"
},
  "geometry": {"coordinates":[98.00745999999999,31.17249],"type":"Point"}
}