{
  "type": "Feature",
  "properties": {
    "gn:admin1_code":"10",
    "gn:asciiname":"Woniupanliudui",
    "gn:country_code":"CN",
    "gn:dem":1328,
    "gn:feature_class":"P",
    "gn:feature_code":"PPL",
    "gn:name":"Woniupanliudui",
    "gn:population":0,
    "gn:timezone":"Asia/Shanghai",
    "iso:country":"CN",
    "wof:name":"Woniupanliudui",
    "wof:placetype":"locality"
},
  "geometry": {"coordinates":[116.87389,42.19694000000001],"type":"Point"}
}