{
  "type": "Feature",
  "properties": {
    "gn:admin1_code":"25.0",
    "gn:asciiname":"Wenqiaobo",
    "gn:country_code":"CN",
    "gn:dem":37,
    "gn:feature_class":"P",
    "gn:feature_code":"PPL",
    "gn:name":"Wenqiaobo",
    "gn:population":0,
    "gn:timezone":"Asia/Shanghai",
    "iso:country":"CN",
    "name:zho_x_preferred":[
        "\u6587\u7fd8\u6cca"
    ],
    "wof:name":"Wenqiaobo",
    "wof:placetype":"locality"
},
  "geometry": {"coordinates":[120.74507,36.95224],"type":"Point"}
}