{
  "type": "Feature",
  "properties": {
    "gn:admin1_code":"2.0",
    "gn:asciiname":"Huimin",
    "gn:country_code":"CN",
    "gn:dem":6,
    "gn:feature_class":"P",
    "gn:feature_code":"PPLA4",
    "gn:name":"Huimin",
    "gn:population":0,
    "gn:timezone":"Asia/Shanghai",
    "iso:country":"CN",
    "name:und_x_variant":[
        "\u60e0\u6c11",
        "Huimin Zhen",
        "\u60e0\u6c11\u9547"
    ],
    "wof:name":"Huimin",
    "wof:placetype":"locality"
},
  "geometry": {"coordinates":[120.96989000000001,30.83909],"type":"Point"}
}