{
  "type": "Feature",
  "properties": {
    "gn:admin1_code":"2.0",
    "gn:asciiname":"Huimin",
    "gn:country_code":"CN",
    "gn:dem":6,
    "gn:feature_class":"P",
    "gn:feature_code":"PPLA4",
    "gn:name":"Huimin",
    "gn:population":0,
    "gn:timezone":"Asia/Shanghai",
    "iso:country":"CN",
    "name:ceb_x_preferred":[
        "Huimin"
    ],
    "name:deu_x_preferred":[
        "Huimin"
    ],
    "name:fra_x_preferred":[
        "Huimin"
    ],
    "name:nor_x_preferred":[
        "Huimin"
    ],
    "name:rus_x_preferred":[
        "\u0425\u0443\u044d\u0439\u043c\u0438\u043d\u044c"
    ],
    "name:swe_x_preferred":[
        "Huimin"
    ],
    "name:und_x_variant":[
        "\u60e0\u6c11",
        "Huimin Zhen",
        "\u60e0\u6c11\u9547"
    ],
    "wof:name":"Huimin",
    "wof:placetype":"locality"
},
  "geometry": {"coordinates":[120.96989000000001,30.83909],"type":"Point"}
}