{
  "type": "Feature",
  "properties": {
    "gn:admin1_code":"25.0",
    "gn:asciiname":"Liujiataocun",
    "gn:country_code":"CN",
    "gn:dem":16,
    "gn:feature_class":"P",
    "gn:feature_code":"PPL",
    "gn:name":"Liujiataocun",
    "gn:population":0,
    "gn:timezone":"Asia/Shanghai",
    "iso:country":"CN",
    "name:und_x_variant":[
        "Liujiatao"
    ],
    "name:zho_x_preferred":[
        "\u5218\u5bb6\u5957\u6751"
    ],
    "name:zho_x_variant":[
        "\u5218\u5bb6\u5957"
    ],
    "wof:name":"Liujiataocun",
    "wof:placetype":"locality"
},
  "geometry": {"coordinates":[117.80783,37.04468],"type":"Point"}
}