{
  "type": "Feature",
  "properties": {
    "gn:admin1_code":"29.0",
    "gn:asciiname":"Yuzepo",
    "gn:country_code":"CN",
    "gn:dem":1835,
    "gn:feature_class":"P",
    "gn:feature_code":"PPL",
    "gn:name":"Yuzepo",
    "gn:population":0,
    "gn:timezone":"Asia/Shanghai",
    "iso:country":"CN",
    "name:zho_x_preferred":[
        "\u9c7c\u6cfd\u5761"
    ],
    "wof:name":"Yuzepo",
    "wof:placetype":"locality"
},
  "geometry": {"coordinates":[103.65000000000001,23.6347],"type":"Point"}
}