{
  "type": "Feature",
  "properties": {
    "gn:admin1_code":"1.0",
    "gn:asciiname":"Jiangdiancun",
    "gn:country_code":"CN",
    "gn:dem":78,
    "gn:feature_class":"P",
    "gn:feature_code":"PPL",
    "gn:name":"Jiangdiancun",
    "gn:population":0,
    "gn:timezone":"Asia/Shanghai",
    "iso:country":"CN",
    "name:zho_x_preferred":[
        "\u6c5f\u5e97\u6751"
    ],
    "wof:name":"Jiangdiancun",
    "wof:placetype":"locality"
},
  "geometry": {"coordinates":[116.30907999999999,31.57349],"type":"Point"}
}