{
  "type": "Feature",
  "properties": {
    "gn:admin1_code":"14.0",
    "gn:asciiname":"Lamenxia",
    "gn:country_code":"CN",
    "gn:dem":4286,
    "gn:feature_class":"P",
    "gn:feature_code":"PPL",
    "gn:name":"Lamenxia",
    "gn:population":0,
    "gn:timezone":"Asia/Urumqi",
    "iso:country":"CN",
    "name:zho_x_preferred":[
        "\u62c9\u95e8\u4e0b"
    ],
    "wof:name":"Lamenxia",
    "wof:placetype":"locality"
},
  "geometry": {"coordinates":[93.78713,31.4469],"type":"Point"}
}