{
  "type": "Feature",
  "properties": {
    "gn:admin1_code":"18.0",
    "gn:asciiname":"Mazhuyuan",
    "gn:country_code":"CN",
    "gn:dem":963,
    "gn:feature_class":"P",
    "gn:feature_code":"PPL",
    "gn:name":"Mazhuyuan",
    "gn:population":0,
    "gn:timezone":"Asia/Shanghai",
    "iso:country":"CN",
    "name:zho_x_preferred":[
        "\u9ebb\u7af9\u56ed"
    ],
    "wof:name":"Mazhuyuan",
    "wof:placetype":"locality"
},
  "geometry": {"coordinates":[108.461,28.2028],"type":"Point"}
}