{
  "type": "Feature",
  "properties": {
    "gn:admin1_code":"26.0",
    "gn:asciiname":"Chunshutancun",
    "gn:country_code":"CN",
    "gn:dem":1362,
    "gn:feature_class":"P",
    "gn:feature_code":"PPL",
    "gn:name":"Chunshutancun",
    "gn:population":0,
    "gn:timezone":"Asia/Shanghai",
    "iso:country":"CN",
    "name:zho_x_preferred":[
        "\u693f\u6811\u6ee9\u6751"
    ],
    "wof:name":"Chunshutancun",
    "wof:placetype":"locality"
},
  "geometry": {"coordinates":[106.66593,34.80101],"type":"Point"}
}