{
  "type": "Feature",
  "properties": {
    "gn:admin1_code":"32.0",
    "gn:asciiname":"Miaoxiang",
    "gn:country_code":"CN",
    "gn:dem":544,
    "gn:feature_class":"P",
    "gn:feature_code":"PPL",
    "gn:name":"Miaoxiang",
    "gn:population":0,
    "gn:timezone":"Asia/Shanghai",
    "iso:country":"CN",
    "name:zho_x_preferred":[
        "\u5999\u76f8"
    ],
    "wof:name":"Miaoxiang",
    "wof:placetype":"locality"
},
  "geometry": {"coordinates":[104.226,31.2687],"type":"Point"}
}