{
  "type": "Feature",
  "properties": {
    "gn:admin1_code":"18.0",
    "gn:asciiname":"Yangtuping",
    "gn:country_code":"CN",
    "gn:dem":873,
    "gn:feature_class":"P",
    "gn:feature_code":"PPL",
    "gn:name":"Yangtuping",
    "gn:population":0,
    "gn:timezone":"Asia/Shanghai",
    "iso:country":"CN",
    "name:zho_x_preferred":[
        "\u7f8a\u571f\u576a"
    ],
    "wof:name":"Yangtuping",
    "wof:placetype":"locality"
},
  "geometry": {"coordinates":[107.598,26.629],"type":"Point"}
}