{
  "type": "Feature",
  "properties": {
    "gn:admin1_code":"16.0",
    "gn:asciiname":"Bawancun",
    "gn:country_code":"CN",
    "gn:dem":339,
    "gn:feature_class":"P",
    "gn:feature_code":"PPL",
    "gn:name":"Bawancun",
    "gn:population":0,
    "gn:timezone":"Asia/Shanghai",
    "iso:country":"CN",
    "name:zho_x_preferred":[
        "\u5df4\u4e07\u6751"
    ],
    "wof:name":"Bawancun",
    "wof:placetype":"locality"
},
  "geometry": {"coordinates":[107.233,24.0289],"type":"Point"}
}