{
  "type": "Feature",
  "properties": {
    "gn:admin1_code":"19.0",
    "gn:asciiname":"Sandaofang",
    "gn:country_code":"CN",
    "gn:dem":5,
    "gn:feature_class":"P",
    "gn:feature_code":"PPL",
    "gn:name":"Sandaofang",
    "gn:population":0,
    "gn:timezone":"Asia/Shanghai",
    "iso:country":"CN",
    "name:und_x_variant":[
        "\u4e09\u9053\u623f"
    ],
    "name:zho_x_preferred":[
        "\u4e09\u9053\u623f"
    ],
    "wof:name":"Sandaofang",
    "wof:placetype":"locality"
},
  "geometry": {"coordinates":[121.51845,39.73211],"type":"Point"}
}