{
  "type": "Feature",
  "properties": {
    "gn:admin1_code":"22.0",
    "gn:asciiname":"Qilianzhuangcun",
    "gn:country_code":"CN",
    "gn:dem":50,
    "gn:feature_class":"P",
    "gn:feature_code":"PPL",
    "gn:name":"Qilianzhuangcun",
    "gn:population":0,
    "gn:timezone":"Asia/Shanghai",
    "iso:country":"CN",
    "name:zho_x_preferred":[
        "\u4e03\u8fde\u5e84\u6751"
    ],
    "wof:name":"Qilianzhuangcun",
    "wof:placetype":"locality"
},
  "geometry": {"coordinates":[116.87854,40.20353],"type":"Point"}
}