{
  "type": "Feature",
  "properties": {
    "gn:admin1_code":"29.0",
    "gn:asciiname":"Shipuli",
    "gn:country_code":"CN",
    "gn:dem":2242,
    "gn:feature_class":"P",
    "gn:feature_code":"PPL",
    "gn:name":"Shipuli",
    "gn:population":0,
    "gn:timezone":"Asia/Shanghai",
    "iso:country":"CN",
    "name:zho_x_preferred":[
        "\u53f2\u666e\u529b"
    ],
    "wof:name":"Shipuli",
    "wof:placetype":"locality"
},
  "geometry": {"coordinates":[99.1058,26.8987],"type":"Point"}
}