{
  "type": "Feature",
  "properties": {
    "gn:admin1_code":"11.0",
    "gn:asciiname":"Kangjitang",
    "gn:country_code":"CN",
    "gn:dem":157,
    "gn:feature_class":"P",
    "gn:feature_code":"PPL",
    "gn:name":"Kangjitang",
    "gn:population":0,
    "gn:timezone":"Asia/Shanghai",
    "iso:country":"CN",
    "name:zho_x_preferred":[
        "\u5eb7\u7ee7\u5802"
    ],
    "wof:name":"Kangjitang",
    "wof:placetype":"locality"
},
  "geometry": {"coordinates":[111.95001999999999,27.09415],"type":"Point"}
}