{
  "type": "Feature",
  "properties": {
    "gn:admin1_code":"26.0",
    "gn:asciiname":"Chenjia Shancun",
    "gn:country_code":"CN",
    "gn:dem":1170,
    "gn:feature_class":"P",
    "gn:feature_code":"PPL",
    "gn:name":"Chenjia Shancun",
    "gn:population":0,
    "gn:timezone":"Asia/Shanghai",
    "iso:country":"CN",
    "name:zho_x_preferred":[
        "\u9648\u5bb6\u5c71\u6751"
    ],
    "wof:name":"Chenjia Shancun",
    "wof:placetype":"locality"
},
  "geometry": {"coordinates":[110.212,38.0983],"type":"Point"}
}