{
  "type": "Feature",
  "properties": {
    "gn:admin1_code":"11.0",
    "gn:asciiname":"Dinghejia",
    "gn:country_code":"CN",
    "gn:dem":42,
    "gn:feature_class":"P",
    "gn:feature_code":"PPL",
    "gn:name":"Dinghejia",
    "gn:population":0,
    "gn:timezone":"Asia/Shanghai",
    "iso:country":"CN",
    "name:zho_x_preferred":[
        "\u4e01\u6cb3\u5bb6"
    ],
    "wof:name":"Dinghejia",
    "wof:placetype":"locality"
},
  "geometry": {"coordinates":[113.24684999999999,29.44002],"type":"Point"}
}