{
  "type": "Feature",
  "properties": {
    "gn:admin1_code":"16.0",
    "gn:asciiname":"Neiliu'en",
    "gn:country_code":"CN",
    "gn:dem":146,
    "gn:feature_class":"P",
    "gn:feature_code":"PPL",
    "gn:name":"Neiliu\u2019en",
    "gn:population":0,
    "gn:timezone":"Asia/Shanghai",
    "iso:country":"CN",
    "name:und_x_variant":[
        "Neiliu\u2019en"
    ],
    "name:zho_x_preferred":[
        "\u5185\u516d\u6069"
    ],
    "wof:name":"Neiliu'en",
    "wof:placetype":"locality"
},
  "geometry": {"coordinates":[108.979,22.7637],"type":"Point"}
}