{
  "type": "Feature",
  "properties": {
    "gn:admin1_code":"29.0",
    "gn:asciiname":"Shanhou",
    "gn:country_code":"CN",
    "gn:dem":2126,
    "gn:feature_class":"P",
    "gn:feature_code":"PPL",
    "gn:name":"Shanhou",
    "gn:population":0,
    "gn:timezone":"Asia/Shanghai",
    "iso:country":"CN",
    "name:zho_x_preferred":[
        "\u5c71\u540e"
    ],
    "wof:name":"Shanhou",
    "wof:placetype":"locality"
},
  "geometry": {"coordinates":[102.096,25.7343],"type":"Point"}
}