{
  "type": "Feature",
  "properties": {
    "gn:admin1_code":"15.0",
    "gn:asciiname":"Dase'er",
    "gn:country_code":"CN",
    "gn:dem":3003,
    "gn:feature_class":"P",
    "gn:feature_code":"PPL",
    "gn:name":"Dase\u2019er",
    "gn:population":0,
    "gn:timezone":"Asia/Shanghai",
    "iso:country":"CN",
    "name:und_x_variant":[
        "Dase\u2019er"
    ],
    "name:zho_x_preferred":[
        "\u8fbe\u8272\u5c14"
    ],
    "wof:name":"Dase'er",
    "wof:placetype":"locality"
},
  "geometry": {"coordinates":[102.86499999999999,34.9501],"type":"Point"}
}