{
  "type": "Feature",
  "properties": {
    "gn:admin1_code":"26.0",
    "gn:asciiname":"Chanxi",
    "gn:country_code":"CN",
    "gn:dem":642,
    "gn:feature_class":"P",
    "gn:feature_code":"PPL",
    "gn:name":"Chanxi",
    "gn:population":0,
    "gn:timezone":"Asia/Shanghai",
    "iso:country":"CN",
    "name:und_x_variant":[
        "\u4ea7\u897f"
    ],
    "wof:name":"Chanxi",
    "wof:placetype":"locality"
},
  "geometry": {"coordinates":[107.27357000000001,34.43653],"type":"Point"}
}