{
  "type": "Feature",
  "properties": {
    "gn:admin1_code":"11",
    "gn:asciiname":"Chengdujiang",
    "gn:country_code":"CN",
    "gn:dem":197,
    "gn:feature_class":"P",
    "gn:feature_code":"PPL",
    "gn:name":"Chengdujiang",
    "gn:population":0,
    "gn:timezone":"Asia/Shanghai",
    "iso:country":"CN",
    "name:zho_x_preferred":[
        "\u6f84\u6e21\u6c5f"
    ],
    "wof:name":"Chengdujiang",
    "wof:placetype":"locality"
},
  "geometry": {"coordinates":[110.24706999999999,27.44493],"type":"Point"}
}