{
  "type": "Feature",
  "properties": {
    "gn:admin1_code":"10",
    "gn:asciiname":"Zhangmanzigou",
    "gn:country_code":"CN",
    "gn:dem":733,
    "gn:feature_class":"P",
    "gn:feature_code":"PPL",
    "gn:name":"Zhangmanzigou",
    "gn:population":0,
    "gn:timezone":"Asia/Shanghai",
    "iso:country":"CN",
    "name:zho_x_preferred":[
        "\u5f20\u86ee\u5b50\u6c9f"
    ],
    "wof:name":"Zhangmanzigou",
    "wof:placetype":"locality"
},
  "geometry": {"coordinates":[117.59818,41.43837],"type":"Point"}
}