{
  "type": "Feature",
  "properties": {
    "gn:admin1_code":"26.0",
    "gn:asciiname":"Zhaizeliang",
    "gn:country_code":"CN",
    "gn:dem":1128,
    "gn:feature_class":"P",
    "gn:feature_code":"PPL",
    "gn:name":"Zhaizeliang",
    "gn:population":0,
    "gn:timezone":"Asia/Shanghai",
    "iso:country":"CN",
    "name:zho_x_preferred":[
        "\u5be8\u5219\u6881"
    ],
    "wof:name":"Zhaizeliang",
    "wof:placetype":"locality"
},
  "geometry": {"coordinates":[110.51470999999999,38.64827],"type":"Point"}
}