{
  "type": "Feature",
  "properties": {
    "gn:admin1_code":"02",
    "gn:asciiname":"Yujialong",
    "gn:country_code":"CN",
    "gn:dem":11,
    "gn:feature_class":"P",
    "gn:feature_code":"PPL",
    "gn:name":"Yujialong",
    "gn:population":0,
    "gn:timezone":"Asia/Shanghai",
    "iso:country":"CN",
    "name:und_x_variant":[
        "\u4fde\u5bb6\u5f04",
        "Y\u00fc-chia-lung"
    ],
    "wof:name":"Yujialong",
    "wof:placetype":"locality"
},
  "geometry": {"coordinates":[120.53565,30.47434],"type":"Point"}
}