{
  "type": "Feature",
  "properties": {
    "gn:admin1_code":"12.0",
    "gn:asciiname":"Miaozitou",
    "gn:country_code":"CN",
    "gn:dem":176,
    "gn:feature_class":"P",
    "gn:feature_code":"PPL",
    "gn:name":"Miaozitou",
    "gn:population":0,
    "gn:timezone":"Asia/Shanghai",
    "iso:country":"CN",
    "name:zho_x_preferred":[
        "\u5e99\u5b50\u5934"
    ],
    "wof:name":"Miaozitou",
    "wof:placetype":"locality"
},
  "geometry": {"coordinates":[113.13934999999999,31.43043],"type":"Point"}
}