{
  "type": "Feature",
  "properties": {
    "gn:admin1_code":"30.0",
    "gn:asciiname":"Gaotianji",
    "gn:country_code":"CN",
    "gn:dem":184,
    "gn:feature_class":"P",
    "gn:feature_code":"PPL",
    "gn:name":"Gaotianji",
    "gn:population":0,
    "gn:timezone":"Asia/Shanghai",
    "iso:country":"CN",
    "name:zho_x_preferred":[
        "\u9ad8\u7530\u57fa"
    ],
    "wof:name":"Gaotianji",
    "wof:placetype":"locality"
},
  "geometry": {"coordinates":[113.09472,23.98583],"type":"Point"}
}