{
  "type": "Feature",
  "properties": {
    "gn:admin1_code":"12.0",
    "gn:asciiname":"Zhujiayuan",
    "gn:country_code":"CN",
    "gn:dem":838,
    "gn:feature_class":"P",
    "gn:feature_code":"PPL",
    "gn:name":"Zhujiayuan",
    "gn:population":0,
    "gn:timezone":"Asia/Shanghai",
    "iso:country":"CN",
    "name:zho_x_preferred":[
        "\u6731\u5bb6\u9662"
    ],
    "wof:name":"Zhujiayuan",
    "wof:placetype":"locality"
},
  "geometry": {"coordinates":[110.5168,32.55843],"type":"Point"}
}