{
  "type": "Feature",
  "properties": {
    "gn:admin1_code":"20.0",
    "gn:asciiname":"Baicaigou",
    "gn:country_code":"CN",
    "gn:dem":1503,
    "gn:feature_class":"P",
    "gn:feature_code":"PPL",
    "gn:name":"Baicaigou",
    "gn:population":0,
    "gn:timezone":"Asia/Shanghai",
    "iso:country":"CN",
    "name:und_x_variant":[
        "\u767d\u83dc\u6c9f"
    ],
    "wof:name":"Baicaigou",
    "wof:placetype":"locality"
},
  "geometry": {"coordinates":[110.37626000000002,40.75615],"type":"Point"}
}