{
  "type": "Feature",
  "properties": {
    "gn:admin1_code":"12.0",
    "gn:asciiname":"Fujia Xiaozhuang",
    "gn:country_code":"CN",
    "gn:dem":211,
    "gn:feature_class":"P",
    "gn:feature_code":"PPL",
    "gn:name":"Fujia Xiaozhuang",
    "gn:population":0,
    "gn:timezone":"Asia/Shanghai",
    "iso:country":"CN",
    "name:zho_x_preferred":[
        "\u5085\u5bb6\u5c0f\u5e84"
    ],
    "wof:name":"Fujia Xiaozhuang",
    "wof:placetype":"locality"
},
  "geometry": {"coordinates":[113.02303999999999,32.30475999999999],"type":"Point"}
}