{
  "type": "Feature",
  "properties": {
    "gn:admin1_code":"4.0",
    "gn:asciiname":"Xiaolincun",
    "gn:country_code":"CN",
    "gn:dem":3,
    "gn:feature_class":"P",
    "gn:feature_code":"PPL",
    "gn:name":"Xiaolincun",
    "gn:population":0,
    "gn:timezone":"Asia/Shanghai",
    "iso:country":"CN",
    "name:zho_x_preferred":[
        "\u6821\u6797\u6751"
    ],
    "wof:name":"Xiaolincun",
    "wof:placetype":"locality"
},
  "geometry": {"coordinates":[120.31152,32.61108],"type":"Point"}
}