{
  "type": "Feature",
  "properties": {
    "gn:admin1_code":"02",
    "gn:asciiname":"Qianshancun",
    "gn:country_code":"CN",
    "gn:dem":18,
    "gn:feature_class":"P",
    "gn:feature_code":"PPL",
    "gn:name":"Qianshancun",
    "gn:population":0,
    "gn:timezone":"Asia/Shanghai",
    "iso:country":"CN",
    "name:und_x_variant":[
        "Qianshan",
        "Qianshancun"
    ],
    "name:zho_x_preferred":[
        "Ch\u2019ien-shan"
    ],
    "name:zho_x_variant":[
        "\u524d\u5c71",
        "\u524d\u5c71\u6751"
    ],
    "wof:name":"Qianshancun",
    "wof:placetype":"locality"
},
  "geometry": {"coordinates":[121.66163,29.00607],"type":"Point"}
}