{
  "type": "Feature",
  "properties": {
    "gn:admin1_code":"11",
    "gn:asciiname":"Jiudaoping",
    "gn:country_code":"CN",
    "gn:dem":1182,
    "gn:feature_class":"P",
    "gn:feature_code":"PPL",
    "gn:name":"Jiudaoping",
    "gn:population":0,
    "gn:timezone":"Asia/Shanghai",
    "iso:country":"CN",
    "name:zho_x_preferred":[
        "\u4e5d\u9053\u576a"
    ],
    "wof:name":"Jiudaoping",
    "wof:placetype":"locality"
},
  "geometry": {"coordinates":[110.65056,27.38139],"type":"Point"}
}