{
  "type": "Feature",
  "properties": {
    "gn:admin1_code":"25",
    "gn:asciiname":"Liulou",
    "gn:country_code":"CN",
    "gn:dem":52,
    "gn:feature_class":"P",
    "gn:feature_code":"PPL",
    "gn:name":"Liulou",
    "gn:population":0,
    "gn:timezone":"Asia/Shanghai",
    "iso:country":"CN",
    "name:zho_x_preferred":[
        "\u5218\u697c"
    ],
    "wof:name":"Liulou",
    "wof:placetype":"locality"
},
  "geometry": {"coordinates":[115.68000000000001,35.3165],"type":"Point"}
}