{
  "type": "Feature",
  "properties": {
    "gn:admin1_code":"15.0",
    "gn:asciiname":"Yingtan",
    "gn:country_code":"CN",
    "gn:dem":2201,
    "gn:feature_class":"P",
    "gn:feature_code":"PPLA4",
    "gn:name":"Yingtan",
    "gn:population":0,
    "gn:timezone":"Asia/Shanghai",
    "iso:country":"CN",
    "name:und_x_variant":[
        "\u8425\u6ee9"
    ],
    "wof:name":"Yingtan",
    "wof:placetype":"locality"
},
  "geometry": {"coordinates":[102.97118,35.57347],"type":"Point"}
}