{
  "type": "Feature",
  "properties": {
    "gn:admin1_code":"15.0",
    "gn:asciiname":"Yingtan",
    "gn:country_code":"CN",
    "gn:dem":2201,
    "gn:feature_class":"P",
    "gn:feature_code":"PPLA4",
    "gn:name":"Yingtan",
    "gn:population":0,
    "gn:timezone":"Asia/Shanghai",
    "iso:country":"CN",
    "name:ara_x_preferred":[
        "\u064a\u0646\u063a\u062a\u0627\u0646"
    ],
    "name:cdo_x_preferred":[
        "\u012cng-t\u00e0ng"
    ],
    "name:ces_x_preferred":[
        "Jing-tchan"
    ],
    "name:dan_x_preferred":[
        "Yingtan"
    ],
    "name:deu_x_preferred":[
        "Yingtan"
    ],
    "name:eus_x_preferred":[
        "Yingtan"
    ],
    "name:fas_x_preferred":[
        "\u06cc\u06cc\u0646\u06af\u062a\u0627\u0646"
    ],
    "name:fin_x_preferred":[
        "Yingtan"
    ],
    "name:fra_x_preferred":[
        "Yingtan"
    ],
    "name:hak_x_preferred":[
        "Y\u00een-th\u00e0m-s\u1e73"
    ],
    "name:ita_x_preferred":[
        "Yingtan"
    ],
    "name:jpn_x_preferred":[
        "\u9df9\u6f6d\u5e02"
    ],
    "name:kik_x_preferred":[
        "Yingtan"
    ],
    "name:kor_x_preferred":[
        "\uc789\ud0c4\uc2dc"
    ],
    "name:mlg_x_preferred":[
        "Yingtan"
    ],
    "name:nld_x_preferred":[
        "Yingtan"
    ],
    "name:nno_x_preferred":[
        "Yingtan"
    ],
    "name:nor_x_preferred":[
        "Yingtan"
    ],
    "name:pol_x_preferred":[
        "Yingtan"
    ],
    "name:rus_x_preferred":[
        "\u0418\u043d\u0442\u0430\u043d\u044c"
    ],
    "name:spa_x_preferred":[
        "Yingtan"
    ],
    "name:swe_x_preferred":[
        "Yingtan"
    ],
    "name:tur_x_preferred":[
        "Yingtan"
    ],
    "name:und_x_variant":[
        "\u8425\u6ee9"
    ],
    "name:urd_x_preferred":[
        "\u06cc\u0646\u06af\u062a\u0627\u0646"
    ],
    "name:vie_x_preferred":[
        "\u01afng \u0110\u00e0m"
    ],
    "name:war_x_preferred":[
        "Yingtan"
    ],
    "name:wuu_x_preferred":[
        "\u9e70\u6f6d\u5e02"
    ],
    "name:zho_x_preferred":[
        "\u9e70\u6f6d\u5e02"
    ],
    "wof:name":"Yingtan",
    "wof:placetype":"locality"
},
  "geometry": {"coordinates":[102.97118,35.57347],"type":"Point"}
}