{
  "type": "Feature",
  "properties": {
    "gn:admin1_code":"15.0",
    "gn:asciiname":"Banzi",
    "gn:country_code":"CN",
    "gn:dem":2252,
    "gn:feature_class":"P",
    "gn:feature_code":"PPL",
    "gn:name":"Banzi",
    "gn:population":0,
    "gn:timezone":"Asia/Shanghai",
    "iso:country":"CN",
    "name:und_x_variant":[
        "\u73ed\u5b50"
    ],
    "name:zho_x_preferred":[
        "\u73ed\u5b50"
    ],
    "wof:name":"Banzi",
    "wof:placetype":"locality"
},
  "geometry": {"coordinates":[104.05416,33.82208],"type":"Point"}
}