{
  "type": "Feature",
  "properties": {
    "gn:admin1_code":"15.0",
    "gn:asciiname":"Banzi",
    "gn:country_code":"CN",
    "gn:dem":2252,
    "gn:feature_class":"P",
    "gn:feature_code":"PPL",
    "gn:name":"Banzi",
    "gn:population":0,
    "gn:timezone":"Asia/Shanghai",
    "iso:country":"CN",
    "name:ara_x_preferred":[
        "\u0628\u0627\u0646\u0632\u064a"
    ],
    "name:azb_x_preferred":[
        "\u0628\u0627\u0646\u062a\u0632\u06cc"
    ],
    "name:bul_x_preferred":[
        "\u0411\u0430\u043d\u0446\u0438"
    ],
    "name:cat_x_preferred":[
        "Banzi"
    ],
    "name:ceb_x_preferred":[
        "Banzi"
    ],
    "name:deu_x_preferred":[
        "Banzi"
    ],
    "name:epo_x_preferred":[
        "Banzi"
    ],
    "name:eus_x_preferred":[
        "Banzi"
    ],
    "name:fas_x_preferred":[
        "\u0628\u0627\u0646\u062a\u0632\u06cc"
    ],
    "name:fra_x_preferred":[
        "Banzi"
    ],
    "name:hun_x_preferred":[
        "Banzi"
    ],
    "name:hye_x_preferred":[
        "\u0532\u0561\u0576\u0581\u056b"
    ],
    "name:ina_x_preferred":[
        "Banzi"
    ],
    "name:ita_x_preferred":[
        "Banzi"
    ],
    "name:jpn_x_preferred":[
        "\u30d0\u30f3\u30c4\u30a3"
    ],
    "name:kaz_x_preferred":[
        "\u0411\u0430\u043d\u0446\u0438"
    ],
    "name:lat_x_preferred":[
        "Bantium"
    ],
    "name:lmo_x_preferred":[
        "Banzi"
    ],
    "name:msa_x_preferred":[
        "Banzi"
    ],
    "name:nap_x_preferred":[
        "Banzi"
    ],
    "name:nld_x_preferred":[
        "Banzi"
    ],
    "name:pms_x_preferred":[
        "Banzi"
    ],
    "name:pol_x_preferred":[
        "Banzi"
    ],
    "name:por_x_preferred":[
        "Banzi"
    ],
    "name:ron_x_preferred":[
        "Banzi"
    ],
    "name:rus_x_preferred":[
        "\u0411\u0430\u043d\u0446\u0438"
    ],
    "name:scn_x_preferred":[
        "Banzi"
    ],
    "name:spa_x_preferred":[
        "Banzi"
    ],
    "name:srp_x_preferred":[
        "\u0411\u0430\u043d\u0446\u0438"
    ],
    "name:ukr_x_preferred":[
        "\u0411\u0430\u043d\u0446\u0456"
    ],
    "name:uzb_x_preferred":[
        "Banzi"
    ],
    "name:vol_x_preferred":[
        "Banzi"
    ],
    "name:war_x_preferred":[
        "Banzi"
    ],
    "name:zho_x_preferred":[
        "\u73ed\u5b50"
    ],
    "wof:name":"Banzi",
    "wof:placetype":"locality"
},
  "geometry": {"coordinates":[104.05416,33.82208],"type":"Point"}
}