{
  "type": "Feature",
  "properties": {
    "gn:admin1_code":"31.0",
    "gn:asciiname":"Hongli",
    "gn:country_code":"CN",
    "gn:dem":147,
    "gn:feature_class":"P",
    "gn:feature_code":"PPL",
    "gn:name":"Hongli",
    "gn:population":0,
    "gn:timezone":"Asia/Shanghai",
    "iso:country":"CN",
    "name:und_x_variant":[
        "\u7ea2\u529b"
    ],
    "name:zho_x_preferred":[
        "\u7ea2\u529b"
    ],
    "wof:name":"Hongli",
    "wof:placetype":"locality"
},
  "geometry": {"coordinates":[110.02967,18.92426],"type":"Point"}
}