{
  "type": "Feature",
  "properties": {
    "gn:admin1_code":"7.0",
    "gn:asciiname":"Xiapanyang",
    "gn:country_code":"CN",
    "gn:dem":526,
    "gn:feature_class":"P",
    "gn:feature_code":"PPL",
    "gn:name":"Xiapanyang",
    "gn:population":0,
    "gn:timezone":"Asia/Shanghai",
    "iso:country":"CN",
    "name:zho_x_preferred":[
        "Xiapanyang"
    ],
    "name:zho_x_variant":[
        "\u4e0b\u6f58\u6d0b"
    ],
    "wof:name":"Xiapanyang",
    "wof:placetype":"locality"
},
  "geometry": {"coordinates":[119.30110999999999,26.60861],"type":"Point"}
}