{
  "type": "Feature",
  "properties": {
    "gn:admin1_code":"30",
    "gn:asciiname":"Maotang",
    "gn:country_code":"CN",
    "gn:dem":29,
    "gn:feature_class":"P",
    "gn:feature_code":"PPL",
    "gn:name":"Maotang",
    "gn:population":0,
    "gn:timezone":"Asia/Urumqi",
    "iso:country":"CN",
    "name:zho_x_preferred":[
        "\u8305\u5858"
    ],
    "wof:name":"Maotang",
    "wof:placetype":"locality"
},
  "geometry": {"coordinates":[109.78024000000001,21.18925],"type":"Point"}
}