{
  "type": "Feature",
  "properties": {
    "gn:admin1_code":"12.0",
    "gn:asciiname":"Xuewuwan",
    "gn:country_code":"CN",
    "gn:dem":268,
    "gn:feature_class":"P",
    "gn:feature_code":"PPL",
    "gn:name":"Xuewuwan",
    "gn:population":0,
    "gn:timezone":"Asia/Shanghai",
    "iso:country":"CN",
    "name:zho_x_preferred":[
        "\u5b66\u5c4b\u6e7e"
    ],
    "wof:name":"Xuewuwan",
    "wof:placetype":"locality"
},
  "geometry": {"coordinates":[113.73007,31.91715],"type":"Point"}
}