{
  "type": "Feature",
  "properties": {
    "gn:admin1_code":"11.0",
    "gn:asciiname":"Chushuidong",
    "gn:country_code":"CN",
    "gn:dem":316,
    "gn:feature_class":"P",
    "gn:feature_code":"PPL",
    "gn:name":"Chushuidong",
    "gn:population":0,
    "gn:timezone":"Asia/Shanghai",
    "iso:country":"CN",
    "name:zho_x_preferred":[
        "Chushuidong"
    ],
    "name:zho_x_variant":[
        "\u51fa\u6c34\u6d1e"
    ],
    "wof:name":"Chushuidong",
    "wof:placetype":"locality"
},
  "geometry": {"coordinates":[111.26134999999999,29.71359],"type":"Point"}
}