{
  "type": "Feature",
  "properties": {
    "gn:admin1_code":"7.0",
    "gn:asciiname":"Cao'an",
    "gn:country_code":"CN",
    "gn:dem":38,
    "gn:feature_class":"P",
    "gn:feature_code":"PPL",
    "gn:name":"Cao\u2019an",
    "gn:population":0,
    "gn:timezone":"Asia/Shanghai",
    "iso:country":"CN",
    "name:fra_x_preferred":[
        "Cao'an"
    ],
    "name:und_x_variant":[
        "Cao\u2019an"
    ],
    "name:zho_x_preferred":[
        "\u8349\u57b5"
    ],
    "wof:name":"Cao'an",
    "wof:placetype":"locality"
},
  "geometry": {"coordinates":[118.44364,25.0271],"type":"Point"}
}