{
  "type": "Feature",
  "properties": {
    "gn:admin1_code":"32.0",
    "gn:asciiname":"Gaoziku",
    "gn:country_code":"CN",
    "gn:dem":529,
    "gn:feature_class":"P",
    "gn:feature_code":"PPL",
    "gn:name":"Gaoziku",
    "gn:population":0,
    "gn:timezone":"Asia/Shanghai",
    "iso:country":"CN",
    "name:zho_x_preferred":[
        "\u9ad8\u5b57\u5e93"
    ],
    "wof:name":"Gaoziku",
    "wof:placetype":"locality"
},
  "geometry": {"coordinates":[104.44277,30.71353],"type":"Point"}
}