{
  "type": "Feature",
  "properties": {
    "gn:admin1_code":"10.0",
    "gn:asciiname":"Manshan",
    "gn:country_code":"CN",
    "gn:dem":747,
    "gn:feature_class":"P",
    "gn:feature_code":"PPL",
    "gn:name":"Manshan",
    "gn:population":0,
    "gn:timezone":"Asia/Shanghai",
    "iso:country":"CN",
    "name:zho_x_preferred":[
        "\u6f2b\u5c71"
    ],
    "wof:name":"Manshan",
    "wof:placetype":"locality"
},
  "geometry": {"coordinates":[113.87685,38.68319],"type":"Point"}
}