{
  "type": "Feature",
  "properties": {
    "gn:admin1_code":"14.0",
    "gn:asciiname":"Gongjiao",
    "gn:country_code":"CN",
    "gn:dem":4169,
    "gn:feature_class":"P",
    "gn:feature_code":"PPL",
    "gn:name":"Gongjiao",
    "gn:population":0,
    "gn:timezone":"Asia/Urumqi",
    "iso:country":"CN",
    "name:zho_x_preferred":[
        "\u516c\u811a"
    ],
    "wof:name":"Gongjiao",
    "wof:placetype":"locality"
},
  "geometry": {"coordinates":[94.00081,31.92531],"type":"Point"}
}