{
  "type": "Feature",
  "properties": {
    "gn:admin1_code":"24.0",
    "gn:asciiname":"Fengshouling",
    "gn:country_code":"CN",
    "gn:dem":1174,
    "gn:feature_class":"P",
    "gn:feature_code":"PPL",
    "gn:name":"Fengshouling",
    "gn:population":0,
    "gn:timezone":"Asia/Shanghai",
    "iso:country":"CN",
    "name:zho_x_preferred":[
        "\u4e30\u6536\u5cad"
    ],
    "wof:name":"Fengshouling",
    "wof:placetype":"locality"
},
  "geometry": {"coordinates":[110.76165,36.2176],"type":"Point"}
}