{
  "type": "Feature",
  "properties": {
    "gn:admin1_code":"6.0",
    "gn:asciiname":"Quecanda",
    "gn:country_code":"CN",
    "gn:dem":3926,
    "gn:feature_class":"P",
    "gn:feature_code":"PPL",
    "gn:name":"Quecanda",
    "gn:population":0,
    "gn:timezone":"Asia/Urumqi",
    "iso:country":"CN",
    "name:zho_x_preferred":[
        "\u5374\u53c2\u8fbe"
    ],
    "wof:name":"Quecanda",
    "wof:placetype":"locality"
},
  "geometry": {"coordinates":[96.8526,33.07719],"type":"Point"}
}