{
  "type": "Feature",
  "properties": {
    "gn:admin1_code":"30",
    "gn:asciiname":"Shiliukeng",
    "gn:country_code":"CN",
    "gn:dem":237,
    "gn:feature_class":"P",
    "gn:feature_code":"PPL",
    "gn:name":"Shiliukeng",
    "gn:population":0,
    "gn:timezone":"Asia/Shanghai",
    "iso:country":"CN",
    "name:und_x_variant":[
        "\u77f3\u69b4\u5751"
    ],
    "wof:name":"Shiliukeng",
    "wof:placetype":"locality"
},
  "geometry": {"coordinates":[112.79778,23.84083],"type":"Point"}
}