{
  "type": "Feature",
  "properties": {
    "gn:admin1_code":"14.0",
    "gn:asciiname":"Ba'erdeng",
    "gn:country_code":"CN",
    "gn:dem":4493,
    "gn:feature_class":"P",
    "gn:feature_code":"PPL",
    "gn:name":"Ba\u2019erdeng",
    "gn:population":0,
    "gn:timezone":"Asia/Urumqi",
    "iso:country":"CN",
    "name:und_x_variant":[
        "Ba\u2019erdeng"
    ],
    "name:zho_x_preferred":[
        "\u5df4\u5c14\u767b"
    ],
    "wof:name":"Ba'erdeng",
    "wof:placetype":"locality"
},
  "geometry": {"coordinates":[93.92556999999999,31.4628],"type":"Point"}
}