{
  "type": "Feature",
  "properties": {
    "gn:admin1_code":"19.0",
    "gn:asciiname":"Taihuatun",
    "gn:country_code":"CN",
    "gn:dem":223,
    "gn:feature_class":"P",
    "gn:feature_code":"PPL",
    "gn:name":"Taihuatun",
    "gn:population":0,
    "gn:timezone":"Asia/Shanghai",
    "iso:country":"CN",
    "name:und_x_variant":[
        "\u592a\u534e\u5c6f"
    ],
    "name:zho_x_preferred":[
        "\u592a\u534e\u5c6f"
    ],
    "wof:name":"Taihuatun",
    "wof:placetype":"locality"
},
  "geometry": {"coordinates":[124.871,43.1095],"type":"Point"}
}