{
  "type": "Feature",
  "properties": {
    "gn:admin1_code":"12.0",
    "gn:asciiname":"Tanqiao",
    "gn:country_code":"CN",
    "gn:dem":47,
    "gn:feature_class":"P",
    "gn:feature_code":"PPL",
    "gn:name":"Tanqiao",
    "gn:population":0,
    "gn:timezone":"Asia/Shanghai",
    "iso:country":"CN",
    "name:zho_x_preferred":[
        "Tanqiao"
    ],
    "name:zho_x_variant":[
        "\u8c08\u6865"
    ],
    "wof:name":"Tanqiao",
    "wof:placetype":"locality"
},
  "geometry": {"coordinates":[114.7512,29.99108],"type":"Point"}
}