{
  "type": "Feature",
  "properties": {
    "gn:admin1_code":"5.0",
    "gn:asciiname":"Weijiabucun",
    "gn:country_code":"CN",
    "gn:dem":338,
    "gn:feature_class":"P",
    "gn:feature_code":"PPL",
    "gn:name":"Weijiabucun",
    "gn:population":0,
    "gn:timezone":"Asia/Shanghai",
    "iso:country":"CN",
    "name:zho_x_preferred":[
        "\u5a01\u5bb6\u5821\u6751"
    ],
    "wof:name":"Weijiabucun",
    "wof:placetype":"locality"
},
  "geometry": {"coordinates":[126.13637,42.39938],"type":"Point"}
}