{
  "type": "Feature",
  "properties": {
    "gn:admin1_code":"03",
    "gn:asciiname":"Dongguan",
    "gn:country_code":"CN",
    "gn:dem":53,
    "gn:feature_class":"P",
    "gn:feature_code":"PPLA4",
    "gn:name":"Dongguan",
    "gn:population":0,
    "gn:timezone":"Asia/Shanghai",
    "iso:country":"CN",
    "name:und_x_variant":[
        "Tung-kuan",
        "Dongguan",
        "\u4e1c\u9986",
        "Dongguan Zhen",
        "\u4e1c\u9986\u9547"
    ],
    "wof:name":"Dongguan",
    "wof:placetype":"locality"
},
  "geometry": {"coordinates":[116.46032,27.8272],"type":"Point"}
}