{
  "type": "Feature",
  "properties": {
    "gn:admin1_code":"30",
    "gn:asciiname":"Shigu",
    "gn:country_code":"CN",
    "gn:dem":42,
    "gn:feature_class":"P",
    "gn:feature_code":"PPL",
    "gn:name":"Shigu",
    "gn:population":0,
    "gn:timezone":"Asia/Shanghai",
    "iso:country":"CN",
    "name:ceb_x_preferred":[
        "Shigu"
    ],
    "name:deu_x_preferred":[
        "Shigu"
    ],
    "name:zho_x_preferred":[
        "\u77f3\u53e4"
    ],
    "wof:name":"Shigu",
    "wof:placetype":"locality"
},
  "geometry": {"coordinates":[116.21647,23.08289],"type":"Point"}
}