{
  "type": "Feature",
  "properties": {
    "gn:admin1_code":"10.0",
    "gn:asciiname":"Wangjiazuo",
    "gn:country_code":"CN",
    "gn:dem":16,
    "gn:feature_class":"P",
    "gn:feature_code":"PPL",
    "gn:name":"Wangjiazuo",
    "gn:population":0,
    "gn:timezone":"Asia/Shanghai",
    "iso:country":"CN",
    "name:zho_x_preferred":[
        "\u738b\u5bb6\u4f50"
    ],
    "wof:name":"Wangjiazuo",
    "wof:placetype":"locality"
},
  "geometry": {"coordinates":[115.88500000000001,38.4685],"type":"Point"}
}