{
  "type": "Feature",
  "properties": {
    "gn:admin1_code":"32.0",
    "gn:asciiname":"Jianganlin",
    "gn:country_code":"CN",
    "gn:dem":1243,
    "gn:feature_class":"P",
    "gn:feature_code":"PPL",
    "gn:name":"Jianganlin",
    "gn:population":0,
    "gn:timezone":"Asia/Shanghai",
    "iso:country":"CN",
    "name:zho_x_preferred":[
        "\u7bad\u6746\u6797"
    ],
    "wof:name":"Jianganlin",
    "wof:placetype":"locality"
},
  "geometry": {"coordinates":[103.032,30.2059],"type":"Point"}
}