{
  "type": "Feature",
  "properties": {
    "gn:admin1_code":"15.0",
    "gn:asciiname":"Panlong",
    "gn:country_code":"CN",
    "gn:dem":1501,
    "gn:feature_class":"P",
    "gn:feature_code":"PPL",
    "gn:name":"Panlong",
    "gn:population":0,
    "gn:timezone":"Asia/Shanghai",
    "iso:country":"CN",
    "name:ceb_x_preferred":[
        "Panlong"
    ],
    "name:deu_x_preferred":[
        "Panlong"
    ],
    "name:fra_x_preferred":[
        "Panlong"
    ],
    "name:nor_x_preferred":[
        "Panlong"
    ],
    "name:zho_x_preferred":[
        "\u76d8\u9f99"
    ],
    "wof:name":"Panlong",
    "wof:placetype":"locality"
},
  "geometry": {"coordinates":[106.578,34.4273],"type":"Point"}
}