{
  "type": "Feature",
  "properties": {
    "gn:admin1_code":"24.0",
    "gn:asciiname":"Sijiazhuang",
    "gn:country_code":"CN",
    "gn:dem":733,
    "gn:feature_class":"P",
    "gn:feature_code":"PPL",
    "gn:name":"Sijiazhuang",
    "gn:population":0,
    "gn:timezone":"Asia/Shanghai",
    "iso:country":"CN",
    "name:zho_x_preferred":[
        "\u5bfa\u5bb6\u5e84"
    ],
    "wof:name":"Sijiazhuang",
    "wof:placetype":"locality"
},
  "geometry": {"coordinates":[111.37599,35.27005],"type":"Point"}
}