{
  "type": "Feature",
  "properties": {
    "gn:admin1_code":"2.0",
    "gn:asciiname":"Houdinglong",
    "gn:country_code":"CN",
    "gn:dem":9,
    "gn:feature_class":"P",
    "gn:feature_code":"PPL",
    "gn:name":"Houdinglong",
    "gn:population":0,
    "gn:timezone":"Asia/Shanghai",
    "iso:country":"CN",
    "name:zho_x_preferred":[
        "\u540e\u5b9a\u5784"
    ],
    "wof:name":"Houdinglong",
    "wof:placetype":"locality"
},
  "geometry": {"coordinates":[120.37499,29.84488],"type":"Point"}
}