{
  "type": "Feature",
  "properties": {
    "gn:admin1_code":"19.0",
    "gn:asciiname":"Xiawujiazicun",
    "gn:country_code":"CN",
    "gn:dem":196,
    "gn:feature_class":"P",
    "gn:feature_code":"PPL",
    "gn:name":"Xiawujiazicun",
    "gn:population":0,
    "gn:timezone":"Asia/Shanghai",
    "iso:country":"CN",
    "name:zho_x_preferred":[
        "\u4e0b\u4e94\u5bb6\u5b50\u6751"
    ],
    "wof:name":"Xiawujiazicun",
    "wof:placetype":"locality"
},
  "geometry": {"coordinates":[120.56273,41.09183],"type":"Point"}
}