{
  "type": "Feature",
  "properties": {
    "gn:admin1_code":"30.0",
    "gn:asciiname":"Zhenzhutou",
    "gn:country_code":"CN",
    "gn:dem":337,
    "gn:feature_class":"P",
    "gn:feature_code":"PPL",
    "gn:name":"Zhenzhutou",
    "gn:population":0,
    "gn:timezone":"Asia/Shanghai",
    "iso:country":"CN",
    "name:zho_x_preferred":[
        "\u632f\u7af9\u5934"
    ],
    "wof:name":"Zhenzhutou",
    "wof:placetype":"locality"
},
  "geometry": {"coordinates":[112.19105999999999,23.46536],"type":"Point"}
}