{
  "type": "Feature",
  "properties": {
    "gn:admin1_code":"04",
    "gn:asciiname":"Dongchangzhencun",
    "gn:country_code":"CN",
    "gn:dem":6,
    "gn:feature_class":"P",
    "gn:feature_code":"PPL",
    "gn:name":"Dongchangzhencun",
    "gn:population":0,
    "gn:timezone":"Asia/Shanghai",
    "iso:country":"CN",
    "name:und_x_variant":[
        "Tung-ch\u2019ang-chen",
        "Dongchangzhen",
        "Dongchang",
        "\u4e1c\u660c",
        "\u4e1c\u660c\u9547",
        "Dongchangzhencun"
    ],
    "name:zho_x_preferred":[
        "\u4e1c\u660c\u9547\u6751"
    ],
    "wof:name":"Dongchangzhencun",
    "wof:placetype":"locality"
},
  "geometry": {"coordinates":[121.66556,31.8992],"type":"Point"}
}