{
  "type": "Feature",
  "properties": {
    "gn:admin1_code":"30",
    "gn:asciiname":"Dafapo",
    "gn:country_code":"CN",
    "gn:dem":40,
    "gn:feature_class":"P",
    "gn:feature_code":"PPL",
    "gn:name":"Dafapo",
    "gn:population":0,
    "gn:timezone":"Asia/Urumqi",
    "iso:country":"CN",
    "name:zho_x_preferred":[
        "\u5927\u53d1\u5761"
    ],
    "wof:name":"Dafapo",
    "wof:placetype":"locality"
},
  "geometry": {"coordinates":[111.33396,21.60811],"type":"Point"}
}