{
  "type": "Feature",
  "properties": {
    "gn:admin1_code":"3",
    "gn:asciiname":"Tongluozhou",
    "gn:country_code":"CN",
    "gn:dem":99,
    "gn:feature_class":"P",
    "gn:feature_code":"PPL",
    "gn:name":"Tongluozhou",
    "gn:population":0,
    "gn:timezone":"Asia/Shanghai",
    "iso:country":"CN",
    "name:zho_x_preferred":[
        "\u94dc\u9523\u6d32"
    ],
    "wof:name":"Tongluozhou",
    "wof:placetype":"locality"
},
  "geometry": {"coordinates":[114.554,26.8891],"type":"Point"}
}