{
  "type": "Feature",
  "properties": {
    "gn:admin1_code":"24.0",
    "gn:asciiname":"Nandubi",
    "gn:country_code":"CN",
    "gn:dem":804,
    "gn:feature_class":"P",
    "gn:feature_code":"PPL",
    "gn:name":"Nandubi",
    "gn:population":0,
    "gn:timezone":"Asia/Shanghai",
    "iso:country":"CN",
    "name:und_x_variant":[
        "Tu-pi-chuang",
        "Nan-tu-pi",
        "Yen-chia-chuang",
        "Tu-pi-ts\u2019un",
        "Yanjiazhuang"
    ],
    "name:zho_x_preferred":[
        "\u5357\u675c\u58c1"
    ],
    "wof:name":"Nandubi",
    "wof:placetype":"locality"
},
  "geometry": {"coordinates":[111.76227,36.48782],"type":"Point"}
}