{
  "type": "Feature",
  "properties": {
    "gn:admin1_code":"32.0",
    "gn:asciiname":"Xiaocun",
    "gn:country_code":"CN",
    "gn:dem":1718,
    "gn:feature_class":"P",
    "gn:feature_code":"PPL",
    "gn:name":"Xiaocun",
    "gn:population":0,
    "gn:timezone":"Asia/Shanghai",
    "iso:country":"CN",
    "name:zho_x_preferred":[
        "\u5c0f\u6751"
    ],
    "wof:name":"Xiaocun",
    "wof:placetype":"locality"
},
  "geometry": {"coordinates":[102.012,26.1767],"type":"Point"}
}