{
  "type": "Feature",
  "properties": {
    "gn:admin1_code":"26.0",
    "gn:asciiname":"Shuigugou",
    "gn:country_code":"CN",
    "gn:dem":1077,
    "gn:feature_class":"P",
    "gn:feature_code":"PPL",
    "gn:name":"Shuigugou",
    "gn:population":0,
    "gn:timezone":"Asia/Shanghai",
    "iso:country":"CN",
    "name:und_x_variant":[
        "\u6c34\u987e\u6c9f"
    ],
    "wof:name":"Shuigugou",
    "wof:placetype":"locality"
},
  "geometry": {"coordinates":[106.99768,33.84642],"type":"Point"}
}