{
  "type": "Feature",
  "properties": {
    "gn:admin1_code":"25.0",
    "gn:asciiname":"Nansucun",
    "gn:country_code":"CN",
    "gn:dem":137,
    "gn:feature_class":"P",
    "gn:feature_code":"PPL",
    "gn:name":"Nansucun",
    "gn:population":0,
    "gn:timezone":"Asia/Shanghai",
    "iso:country":"CN",
    "name:zho_x_preferred":[
        "\u5357\u5bbf\u6751"
    ],
    "wof:name":"Nansucun",
    "wof:placetype":"locality"
},
  "geometry": {"coordinates":[120.10089000000001,37.15279],"type":"Point"}
}