{
  "type": "Feature",
  "properties": {
    "gn:admin1_code":"8.0",
    "gn:asciiname":"Nenjiang Sifenchang Sidui",
    "gn:country_code":"CN",
    "gn:dem":277,
    "gn:feature_class":"P",
    "gn:feature_code":"PPLF",
    "gn:name":"Nenjiang Sifenchang Sidui",
    "gn:population":0,
    "gn:timezone":"Asia/Shanghai",
    "iso:country":"CN",
    "name:zho_x_preferred":[
        "\u5ae9\u6c5f\u56db\u5206\u573a\u56db\u961f"
    ],
    "wof:name":"Nenjiang Sifenchang Sidui",
    "wof:placetype":"locality"
},
  "geometry": {"coordinates":[125.81868,49.17352],"type":"Point"}
}