{
  "type": "Feature",
  "properties": {
    "gn:admin1_code":"31.0",
    "gn:asciiname":"Junkou",
    "gn:country_code":"CN",
    "gn:dem":45,
    "gn:feature_class":"P",
    "gn:feature_code":"PPL",
    "gn:name":"Junkou",
    "gn:population":0,
    "gn:timezone":"Asia/Shanghai",
    "iso:country":"CN",
    "name:zho_x_preferred":[
        "Junkou"
    ],
    "name:zho_x_variant":[
        "\u519b\u53e3"
    ],
    "wof:name":"Junkou",
    "wof:placetype":"locality"
},
  "geometry": {"coordinates":[110.04581,19.68794],"type":"Point"}
}