{
  "type": "Feature",
  "properties": {
    "gn:admin1_code":"30.0",
    "gn:asciiname":"Sanlewucun",
    "gn:country_code":"CN",
    "gn:dem":96,
    "gn:feature_class":"P",
    "gn:feature_code":"PPL",
    "gn:name":"Sanlewucun",
    "gn:population":0,
    "gn:timezone":"Asia/Shanghai",
    "iso:country":"CN",
    "name:zho_x_preferred":[
        "\u4e09\u4e50\u5c4b\u6751"
    ],
    "wof:name":"Sanlewucun",
    "wof:placetype":"locality"
},
  "geometry": {"coordinates":[116.86638000000001,24.10422],"type":"Point"}
}