{
  "type": "Feature",
  "properties": {
    "gn:admin1_code":"9.0",
    "gn:asciiname":"Wangtangzhuang",
    "gn:country_code":"CN",
    "gn:dem":106,
    "gn:feature_class":"P",
    "gn:feature_code":"PPL",
    "gn:name":"Wangtangzhuang",
    "gn:population":0,
    "gn:timezone":"Asia/Shanghai",
    "iso:country":"CN",
    "name:zho_x_preferred":[
        "\u738b\u5858\u5e84"
    ],
    "wof:name":"Wangtangzhuang",
    "wof:placetype":"locality"
},
  "geometry": {"coordinates":[112.46655,32.75593],"type":"Point"}
}