{
  "type": "Feature",
  "properties": {
    "gn:admin1_code":"11.0",
    "gn:asciiname":"Quejiachong",
    "gn:country_code":"CN",
    "gn:dem":261,
    "gn:feature_class":"P",
    "gn:feature_code":"PPL",
    "gn:name":"Quejiachong",
    "gn:population":0,
    "gn:timezone":"Asia/Shanghai",
    "iso:country":"CN",
    "name:zho_x_preferred":[
        "\u7f3a\u5bb6\u51b2"
    ],
    "wof:name":"Quejiachong",
    "wof:placetype":"locality"
},
  "geometry": {"coordinates":[110.02191999999999,27.20028],"type":"Point"}
}