{
  "type": "Feature",
  "properties": {
    "gn:admin1_code":"18",
    "gn:asciiname":"Pucun",
    "gn:country_code":"CN",
    "gn:dem":822,
    "gn:feature_class":"P",
    "gn:feature_code":"PPL",
    "gn:name":"Pucun",
    "gn:population":0,
    "gn:timezone":"Asia/Shanghai",
    "iso:country":"CN",
    "name:zho_x_preferred":[
        "\u84b2\u6751"
    ],
    "wof:name":"Pucun",
    "wof:placetype":"locality"
},
  "geometry": {"coordinates":[107.63,27.9025],"type":"Point"}
}