{
  "type": "Feature",
  "properties": {
    "gn:admin1_code":"8.0",
    "gn:asciiname":"Guodianchentun",
    "gn:country_code":"CN",
    "gn:dem":238,
    "gn:feature_class":"P",
    "gn:feature_code":"PPL",
    "gn:name":"Guodianchentun",
    "gn:population":0,
    "gn:timezone":"Asia/Shanghai",
    "iso:country":"CN",
    "name:zho_x_preferred":[
        "\u90ed\u6bbf\u81e3\u5c6f"
    ],
    "wof:name":"Guodianchentun",
    "wof:placetype":"locality"
},
  "geometry": {"coordinates":[124.77731,48.53671],"type":"Point"}
}