{
  "type": "Feature",
  "properties": {
    "gn:admin1_code":"11.0",
    "gn:asciiname":"Shanjiakou",
    "gn:country_code":"CN",
    "gn:dem":437,
    "gn:feature_class":"P",
    "gn:feature_code":"PPL",
    "gn:name":"Shanjiakou",
    "gn:population":0,
    "gn:timezone":"Asia/Shanghai",
    "iso:country":"CN",
    "name:zho_x_preferred":[
        "\u5c71\u7532\u53e3"
    ],
    "wof:name":"Shanjiakou",
    "wof:placetype":"locality"
},
  "geometry": {"coordinates":[111.70166999999999,24.80055],"type":"Point"}
}