{
  "type": "Feature",
  "properties": {
    "gn:admin1_code":"24",
    "gn:asciiname":"Baquan",
    "gn:country_code":"CN",
    "gn:dem":1090,
    "gn:feature_class":"P",
    "gn:feature_code":"PPL",
    "gn:name":"Baquan",
    "gn:population":0,
    "gn:timezone":"Asia/Shanghai",
    "iso:country":"CN",
    "name:und_x_variant":[
        "Pa-ch\u2019\u00fcan",
        "Baquan"
    ],
    "name:zho_x_preferred":[
        "\u516b\u6cc9"
    ],
    "wof:name":"Baquan",
    "wof:placetype":"locality"
},
  "geometry": {"coordinates":[112.5017,36.29145],"type":"Point"}
}