{
  "type": "Feature",
  "properties": {
    "gn:admin1_code":"5.0",
    "gn:asciiname":"Jingfacun",
    "gn:country_code":"CN",
    "gn:dem":128,
    "gn:feature_class":"P",
    "gn:feature_code":"PPL",
    "gn:name":"Jingfacun",
    "gn:population":0,
    "gn:timezone":"Asia/Shanghai",
    "iso:country":"CN",
    "name:zho_x_preferred":[
        "\u4e95\u53d1\u6751"
    ],
    "wof:name":"Jingfacun",
    "wof:placetype":"locality"
},
  "geometry": {"coordinates":[124.82881999999999,45.41371],"type":"Point"}
}