{
  "type": "Feature",
  "properties": {
    "gn:admin1_code":"16",
    "gn:asciiname":"Shibachong",
    "gn:country_code":"CN",
    "gn:dem":304,
    "gn:feature_class":"P",
    "gn:feature_code":"PPL",
    "gn:name":"Shibachong",
    "gn:population":0,
    "gn:timezone":"Asia/Shanghai",
    "iso:country":"CN",
    "name:zho_x_preferred":[
        "\u5341\u516b\u51b2"
    ],
    "wof:name":"Shibachong",
    "wof:placetype":"locality"
},
  "geometry": {"coordinates":[110.711,24.6572],"type":"Point"}
}