{
  "type": "Feature",
  "properties": {
    "gn:admin1_code":"30.0",
    "gn:asciiname":"Shangshishe",
    "gn:country_code":"CN",
    "gn:dem":520,
    "gn:feature_class":"P",
    "gn:feature_code":"PPL",
    "gn:name":"Shangshishe",
    "gn:population":0,
    "gn:timezone":"Asia/Shanghai",
    "iso:country":"CN",
    "name:zho_x_preferred":[
        "Shangshishe"
    ],
    "name:zho_x_variant":[
        "\u4e0a\u77f3\u820d"
    ],
    "wof:name":"Shangshishe",
    "wof:placetype":"locality"
},
  "geometry": {"coordinates":[114.76056,24.50028],"type":"Point"}
}