{
  "type": "Feature",
  "properties": {
    "gn:admin1_code":"11",
    "gn:asciiname":"Xiafenghuangshan",
    "gn:country_code":"CN",
    "gn:dem":227,
    "gn:feature_class":"P",
    "gn:feature_code":"PPL",
    "gn:name":"Xiafenghuangshan",
    "gn:population":0,
    "gn:timezone":"Asia/Shanghai",
    "iso:country":"CN",
    "name:zho_x_preferred":[
        "\u4e0b\u51e4\u51f0\u5c71"
    ],
    "wof:name":"Xiafenghuangshan",
    "wof:placetype":"locality"
},
  "geometry": {"coordinates":[111.24323,26.03116],"type":"Point"}
}