{
  "type": "Feature",
  "properties": {
    "gn:admin1_code":"18",
    "gn:asciiname":"Heyinba",
    "gn:country_code":"CN",
    "gn:dem":1311,
    "gn:feature_class":"P",
    "gn:feature_code":"PPL",
    "gn:name":"Heyinba",
    "gn:population":0,
    "gn:timezone":"Asia/Shanghai",
    "iso:country":"CN",
    "name:zho_x_preferred":[
        "\u6cb3\u9634\u575d"
    ],
    "wof:name":"Heyinba",
    "wof:placetype":"locality"
},
  "geometry": {"coordinates":[108.074,28.5643],"type":"Point"}
}