{
  "type": "Feature",
  "properties": {
    "gn:admin1_code":"32.0",
    "gn:asciiname":"Niulanbang",
    "gn:country_code":"CN",
    "gn:dem":769,
    "gn:feature_class":"P",
    "gn:feature_code":"PPL",
    "gn:name":"Niulanbang",
    "gn:population":0,
    "gn:timezone":"Asia/Shanghai",
    "iso:country":"CN",
    "name:zho_x_preferred":[
        "\u725b\u680f\u585d"
    ],
    "wof:name":"Niulanbang",
    "wof:placetype":"locality"
},
  "geometry": {"coordinates":[104.88491999999999,28.12934000000001],"type":"Point"}
}