{
  "type": "Feature",
  "properties": {
    "gn:admin1_code":"22.0",
    "gn:asciiname":"Tongjiawucun",
    "gn:country_code":"CN",
    "gn:dem":33,
    "gn:feature_class":"P",
    "gn:feature_code":"PPL",
    "gn:name":"Tongjiawucun",
    "gn:population":0,
    "gn:timezone":"Asia/Shanghai",
    "iso:country":"CN",
    "name:zho_x_preferred":[
        "\u4f5f\u5bb6\u52a1\u6751"
    ],
    "wof:name":"Tongjiawucun",
    "wof:placetype":"locality"
},
  "geometry": {"coordinates":[116.42304,39.59173],"type":"Point"}
}