{
  "type": "Feature",
  "properties": {
    "gn:admin1_code":"12.0",
    "gn:asciiname":"Wufangwan",
    "gn:country_code":"CN",
    "gn:dem":62,
    "gn:feature_class":"P",
    "gn:feature_code":"PPL",
    "gn:name":"Wufangwan",
    "gn:population":0,
    "gn:timezone":"Asia/Shanghai",
    "iso:country":"CN",
    "name:und_x_variant":[
        "\u4e94\u623f\u5846"
    ],
    "wof:name":"Wufangwan",
    "wof:placetype":"locality"
},
  "geometry": {"coordinates":[115.45749000000001,30.36463],"type":"Point"}
}