{
  "type": "Feature",
  "properties": {
    "gn:admin1_code":"7.0",
    "gn:asciiname":"Jinkengcun",
    "gn:country_code":"CN",
    "gn:dem":556,
    "gn:feature_class":"P",
    "gn:feature_code":"PPL",
    "gn:name":"Jinkengcun",
    "gn:population":0,
    "gn:timezone":"Asia/Shanghai",
    "iso:country":"CN",
    "name:zho_x_preferred":[
        "\u91d1\u5751\u6751"
    ],
    "wof:name":"Jinkengcun",
    "wof:placetype":"locality"
},
  "geometry": {"coordinates":[117.04201,26.89435],"type":"Point"}
}