{
  "type": "Feature",
  "properties": {
    "gn:admin1_code":"18.0",
    "gn:asciiname":"Bajiucun",
    "gn:country_code":"CN",
    "gn:dem":789,
    "gn:feature_class":"P",
    "gn:feature_code":"PPL",
    "gn:name":"Bajiucun",
    "gn:population":0,
    "gn:timezone":"Asia/Shanghai",
    "iso:country":"CN",
    "name:zho_x_preferred":[
        "\u516b\u4e5d\u6751"
    ],
    "wof:name":"Bajiucun",
    "wof:placetype":"locality"
},
  "geometry": {"coordinates":[108.586,26.3606],"type":"Point"}
}