{
  "type": "Feature",
  "properties": {
    "gn:admin1_code":"30",
    "gn:asciiname":"Baxin",
    "gn:country_code":"CN",
    "gn:dem":93,
    "gn:feature_class":"P",
    "gn:feature_code":"PPL",
    "gn:name":"Baxin",
    "gn:population":0,
    "gn:timezone":"Asia/Shanghai",
    "iso:country":"CN",
    "name:ita_x_preferred":[
        "Baxin d'Albenga"
    ],
    "wof:name":"Baxin",
    "wof:placetype":"locality"
},
  "geometry": {"coordinates":[115.85472,23.9775],"type":"Point"}
}