{
  "type": "Feature",
  "properties": {
    "gn:admin1_code":"30",
    "gn:asciiname":"Longhua",
    "gn:country_code":"CN",
    "gn:dem":71,
    "gn:feature_class":"P",
    "gn:feature_code":"PPLA4",
    "gn:name":"Longhua",
    "gn:population":0,
    "gn:timezone":"Asia/Shanghai",
    "iso:country":"CN",
    "name:nld_x_preferred":[
        "Longhua"
    ],
    "name:und_x_variant":[
        "Lung-hua",
        "Lung Wa",
        "Lung-hua-hs\u00fc",
        "Longhua",
        "Longhua Jiedao",
        "\u9f99\u534e\u8857\u9053"
    ],
    "name:zho_x_preferred":[
        "\u9f99\u534e\u8857\u9053"
    ],
    "wof:name":"Longhua",
    "wof:placetype":"locality"
},
  "geometry": {"coordinates":[114.00893000000001,22.65784],"type":"Point"}
}