{
  "type": "Feature",
  "properties": {
    "gn:admin1_code":"15.0",
    "gn:asciiname":"Yangpozhuang",
    "gn:country_code":"CN",
    "gn:dem":1405,
    "gn:feature_class":"P",
    "gn:feature_code":"PPL",
    "gn:name":"Yangpozhuang",
    "gn:population":0,
    "gn:timezone":"Asia/Shanghai",
    "iso:country":"CN",
    "name:zho_x_preferred":[
        "\u9633\u5761\u5e84"
    ],
    "wof:name":"Yangpozhuang",
    "wof:placetype":"locality"
},
  "geometry": {"coordinates":[105.44199999999999,34.6024],"type":"Point"}
}