{
  "type": "Feature",
  "properties": {
    "gn:admin1_code":"16.0",
    "gn:asciiname":"Dachuntian",
    "gn:country_code":"CN",
    "gn:dem":230,
    "gn:feature_class":"P",
    "gn:feature_code":"PPL",
    "gn:name":"Dachuntian",
    "gn:population":0,
    "gn:timezone":"Asia/Shanghai",
    "iso:country":"CN",
    "name:zho_x_preferred":[
        "\u5927\u6625\u7530"
    ],
    "wof:name":"Dachuntian",
    "wof:placetype":"locality"
},
  "geometry": {"coordinates":[110.73099999999999,24.2012],"type":"Point"}
}