{
  "type": "Feature",
  "properties": {
    "gn:admin1_code":"32.0",
    "gn:asciiname":"Shihezui",
    "gn:country_code":"CN",
    "gn:dem":393,
    "gn:feature_class":"P",
    "gn:feature_code":"PPL",
    "gn:name":"Shihezui",
    "gn:population":0,
    "gn:timezone":"Asia/Shanghai",
    "iso:country":"CN",
    "name:zho_x_preferred":[
        "\u77f3\u9e64\u5634"
    ],
    "wof:name":"Shihezui",
    "wof:placetype":"locality"
},
  "geometry": {"coordinates":[106.482,30.641],"type":"Point"}
}