{
  "type": "Feature",
  "properties": {
    "gn:admin1_code":"8.0",
    "gn:asciiname":"Jianhuacun",
    "gn:country_code":"CN",
    "gn:dem":198,
    "gn:feature_class":"P",
    "gn:feature_code":"PPL",
    "gn:name":"Jianhuacun",
    "gn:population":0,
    "gn:timezone":"Asia/Shanghai",
    "iso:country":"CN",
    "name:zho_x_preferred":[
        "\u5efa\u534e\u6751"
    ],
    "wof:name":"Jianhuacun",
    "wof:placetype":"locality"
},
  "geometry": {"coordinates":[127.78758999999999,47.00423],"type":"Point"}
}