{
  "type": "Feature",
  "properties": {
    "gn:admin1_code":"19.0",
    "gn:asciiname":"Xibeigou",
    "gn:country_code":"CN",
    "gn:dem":105,
    "gn:feature_class":"P",
    "gn:feature_code":"PPL",
    "gn:name":"Xibeigou",
    "gn:population":0,
    "gn:timezone":"Asia/Shanghai",
    "iso:country":"CN",
    "name:zho_x_preferred":[
        "\u897f\u5317\u6c9f"
    ],
    "wof:name":"Xibeigou",
    "wof:placetype":"locality"
},
  "geometry": {"coordinates":[122.51900000000001,39.9869],"type":"Point"}
}