{
  "type": "Feature",
  "properties": {
    "gn:admin1_code":"26.0",
    "gn:asciiname":"Linbianzicun",
    "gn:country_code":"CN",
    "gn:dem":1333,
    "gn:feature_class":"P",
    "gn:feature_code":"PPL",
    "gn:name":"Linbianzicun",
    "gn:population":0,
    "gn:timezone":"Asia/Shanghai",
    "iso:country":"CN",
    "name:zho_x_preferred":[
        "\u853a\u782d\u5b50\u6751"
    ],
    "wof:name":"Linbianzicun",
    "wof:placetype":"locality"
},
  "geometry": {"coordinates":[108.11673999999999,36.88007],"type":"Point"}
}