{
  "type": "Feature",
  "properties": {
    "gn:admin1_code":"29.0",
    "gn:asciiname":"Baimahe",
    "gn:country_code":"CN",
    "gn:dem":1140,
    "gn:feature_class":"P",
    "gn:feature_code":"PPL",
    "gn:name":"Baimahe",
    "gn:population":0,
    "gn:timezone":"Asia/Shanghai",
    "iso:country":"CN",
    "name:zho_x_preferred":[
        "\u767d\u9a6c\u6cb3"
    ],
    "wof:name":"Baimahe",
    "wof:placetype":"locality"
},
  "geometry": {"coordinates":[101.494,26.4341],"type":"Point"}
}