{
  "type": "Feature",
  "properties": {
    "gn:admin1_code":"29",
    "gn:asciiname":"Naba",
    "gn:country_code":"CN",
    "gn:dem":1504,
    "gn:feature_class":"P",
    "gn:feature_code":"PPL",
    "gn:name":"Naba",
    "gn:population":0,
    "gn:timezone":"Asia/Shanghai",
    "iso:country":"CN",
    "name:ceb_x_preferred":[
        "Naba"
    ],
    "name:fra_x_preferred":[
        "Naba"
    ],
    "name:spa_x_preferred":[
        "Naba"
    ],
    "name:swe_x_preferred":[
        "Naba"
    ],
    "name:zho_x_preferred":[
        "\u90a3\u5c9c"
    ],
    "wof:name":"Naba",
    "wof:placetype":"locality"
},
  "geometry": {"coordinates":[104.96299999999999,24.093],"type":"Point"}
}