{
  "type": "Feature",
  "properties": {
    "gn:admin1_code":"30",
    "gn:asciiname":"Maitan",
    "gn:country_code":"CN",
    "gn:dem":33,
    "gn:feature_class":"P",
    "gn:feature_code":"PPL",
    "gn:name":"Maitan",
    "gn:population":0,
    "gn:timezone":"Asia/Urumqi",
    "iso:country":"CN",
    "name:zho_x_preferred":[
        "\u8fc8\u70ad"
    ],
    "wof:name":"Maitan",
    "wof:placetype":"locality"
},
  "geometry": {"coordinates":[109.95856999999999,20.47961],"type":"Point"}
}