{
  "type": "Feature",
  "properties": {
    "gn:admin1_code":"15.0",
    "gn:asciiname":"Zhalin",
    "gn:country_code":"CN",
    "gn:dem":920,
    "gn:feature_class":"P",
    "gn:feature_code":"PPL",
    "gn:name":"Zhalin",
    "gn:population":0,
    "gn:timezone":"Asia/Shanghai",
    "iso:country":"CN",
    "name:zho_x_preferred":[
        "\u4e4d\u6797"
    ],
    "wof:name":"Zhalin",
    "wof:placetype":"locality"
},
  "geometry": {"coordinates":[106.63200000000001,34.3927],"type":"Point"}
}