{
  "type": "Feature",
  "properties": {
    "gn:admin1_code":"09",
    "gn:asciiname":"Jialing",
    "gn:country_code":"CN",
    "gn:dem":39,
    "gn:feature_class":"P",
    "gn:feature_code":"PPL",
    "gn:name":"Jialing",
    "gn:population":0,
    "gn:timezone":"Asia/Shanghai",
    "iso:country":"CN",
    "name:ceb_x_preferred":[
        "Jialing"
    ],
    "name:deu_x_preferred":[
        "Jialing"
    ],
    "name:fra_x_preferred":[
        "Jialing"
    ],
    "name:nor_x_preferred":[
        "Jialing"
    ],
    "wof:name":"Jialing",
    "wof:placetype":"locality"
},
  "geometry": {"coordinates":[114.83333,33.13333],"type":"Point"}
}