{
  "type": "Feature",
  "properties": {
    "gn:admin1_code":"7.0",
    "gn:asciiname":"Wangmaochang",
    "gn:country_code":"CN",
    "gn:dem":211,
    "gn:feature_class":"P",
    "gn:feature_code":"PPL",
    "gn:name":"Wangmaochang",
    "gn:population":0,
    "gn:timezone":"Asia/Shanghai",
    "iso:country":"CN",
    "name:zho_x_preferred":[
        "\u738b\u6bdb\u5382"
    ],
    "wof:name":"Wangmaochang",
    "wof:placetype":"locality"
},
  "geometry": {"coordinates":[117.62899,27.17128],"type":"Point"}
}