{
  "type": "Feature",
  "properties": {
    "gn:admin1_code":"19.0",
    "gn:asciiname":"Xiawaziyu",
    "gn:country_code":"CN",
    "gn:dem":106,
    "gn:feature_class":"P",
    "gn:feature_code":"PPL",
    "gn:name":"Xiawaziyu",
    "gn:population":0,
    "gn:timezone":"Asia/Shanghai",
    "iso:country":"CN",
    "name:und_x_variant":[
        "\u4e0b\u74e6\u5b50\u5cea"
    ],
    "name:zho_x_preferred":[
        "\u4e0b\u74e6\u5b50\u5cea"
    ],
    "wof:name":"Xiawaziyu",
    "wof:placetype":"locality"
},
  "geometry": {"coordinates":[123.64117,41.26104],"type":"Point"}
}