{
  "type": "Feature",
  "properties": {
    "gn:admin1_code":"4.0",
    "gn:asciiname":"Xinduqiao",
    "gn:country_code":"CN",
    "gn:dem":6,
    "gn:feature_class":"P",
    "gn:feature_code":"PPL",
    "gn:name":"Xinduqiao",
    "gn:population":0,
    "gn:timezone":"Asia/Shanghai",
    "iso:country":"CN",
    "name:und_x_variant":[
        "Hsin-tu-ch\u2019iao",
        "Xinduqiao"
    ],
    "name:zho_x_preferred":[
        "\u65b0\u6e21\u6865"
    ],
    "wof:name":"Xinduqiao",
    "wof:placetype":"locality"
},
  "geometry": {"coordinates":[120.1234,31.59904],"type":"Point"}
}