{
  "type": "Feature",
  "properties": {
    "gn:admin1_code":"8.0",
    "gn:asciiname":"Donghecun",
    "gn:country_code":"CN",
    "gn:dem":118,
    "gn:feature_class":"P",
    "gn:feature_code":"PPL",
    "gn:name":"Donghecun",
    "gn:population":0,
    "gn:timezone":"Asia/Shanghai",
    "iso:country":"CN",
    "name:zho_x_preferred":[
        "\u4e1c\u6cb3\u6751"
    ],
    "wof:name":"Donghecun",
    "wof:placetype":"locality"
},
  "geometry": {"coordinates":[130.08760000000001,46.18388],"type":"Point"}
}