{
  "type": "Feature",
  "properties": {
    "gn:admin1_code":"32.0",
    "gn:asciiname":"Yizi'amu",
    "gn:country_code":"CN",
    "gn:dem":2220,
    "gn:feature_class":"P",
    "gn:feature_code":"PPL",
    "gn:name":"Yizi\u2019amu",
    "gn:population":0,
    "gn:timezone":"Asia/Shanghai",
    "iso:country":"CN",
    "name:und_x_variant":[
        "Yizi\u2019amu"
    ],
    "name:zho_x_preferred":[
        "\u8863\u5b50\u963f\u6728"
    ],
    "wof:name":"Yizi'amu",
    "wof:placetype":"locality"
},
  "geometry": {"coordinates":[102.756,28.7454],"type":"Point"}
}