{
  "type": "Feature",
  "properties": {
    "gn:admin1_code":"2.0",
    "gn:asciiname":"Xiao'an",
    "gn:country_code":"CN",
    "gn:dem":113,
    "gn:feature_class":"P",
    "gn:feature_code":"PPL",
    "gn:name":"Xiao\u2019an",
    "gn:population":0,
    "gn:timezone":"Asia/Shanghai",
    "iso:country":"CN",
    "name:zho_x_preferred":[
        "\u5c0f\u5b89"
    ],
    "name:zho_x_variant":[
        "Xiao\u2019an"
    ],
    "wof:name":"Xiao'an",
    "wof:placetype":"locality"
},
  "geometry": {"coordinates":[119.85885,28.55876],"type":"Point"}
}