{
  "type": "Feature",
  "properties": {
    "gn:admin1_code":"16.0",
    "gn:asciiname":"Namu",
    "gn:country_code":"CN",
    "gn:dem":300,
    "gn:feature_class":"P",
    "gn:feature_code":"PPL",
    "gn:name":"Namu",
    "gn:population":0,
    "gn:timezone":"Asia/Shanghai",
    "iso:country":"CN",
    "name:ceb_x_preferred":[
        "Namu"
    ],
    "name:swe_x_preferred":[
        "Namu"
    ],
    "name:zho_x_preferred":[
        "\u7eb3\u6bcd"
    ],
    "wof:name":"Namu",
    "wof:placetype":"locality"
},
  "geometry": {"coordinates":[107.372,24.7294],"type":"Point"}
}