{
  "type": "Feature",
  "properties": {
    "gn:admin1_code":"1.0",
    "gn:asciiname":"Qingbufancun",
    "gn:country_code":"CN",
    "gn:dem":103,
    "gn:feature_class":"P",
    "gn:feature_code":"PPL",
    "gn:name":"Qingbufancun",
    "gn:population":0,
    "gn:timezone":"Asia/Shanghai",
    "iso:country":"CN",
    "name:zho_x_preferred":[
        "\u9752\u57e0\u7548\u6751"
    ],
    "wof:name":"Qingbufancun",
    "wof:placetype":"locality"
},
  "geometry": {"coordinates":[116.48376,31.40476],"type":"Point"}
}