{
  "type": "Feature",
  "properties": {
    "gn:admin1_code":"29",
    "gn:asciiname":"Xiadouyue",
    "gn:country_code":"CN",
    "gn:dem":1450,
    "gn:feature_class":"P",
    "gn:feature_code":"PPL",
    "gn:name":"Xiadouyue",
    "gn:population":0,
    "gn:timezone":"Asia/Shanghai",
    "iso:country":"CN",
    "name:zho_x_preferred":[
        "\u4e0b\u6597\u6708"
    ],
    "wof:name":"Xiadouyue",
    "wof:placetype":"locality"
},
  "geometry": {"coordinates":[104.705,24.1645],"type":"Point"}
}