{
  "type": "Feature",
  "properties": {
    "gn:admin1_code":"30",
    "gn:asciiname":"Shegangshang",
    "gn:country_code":"CN",
    "gn:dem":326,
    "gn:feature_class":"P",
    "gn:feature_code":"PPL",
    "gn:name":"Shegangshang",
    "gn:population":0,
    "gn:timezone":"Asia/Shanghai",
    "iso:country":"CN",
    "name:zho_x_preferred":[
        "\u793e\u5c97\u4e0a"
    ],
    "wof:name":"Shegangshang",
    "wof:placetype":"locality"
},
  "geometry": {"coordinates":[115.85012999999999,24.77569],"type":"Point"}
}