{
  "type": "Feature",
  "properties": {
    "gn:admin1_code":"4.0",
    "gn:asciiname":"Suwa",
    "gn:country_code":"CN",
    "gn:dem":20,
    "gn:feature_class":"P",
    "gn:feature_code":"PPL",
    "gn:name":"Suwa",
    "gn:population":0,
    "gn:timezone":"Asia/Shanghai",
    "iso:country":"CN",
    "name:ceb_x_preferred":[
        "Suwa"
    ],
    "name:deu_x_preferred":[
        "Suwa"
    ],
    "name:epo_x_preferred":[
        "Su\u016da"
    ],
    "name:fra_x_preferred":[
        "Suwa"
    ],
    "name:mlg_x_preferred":[
        "Suwa"
    ],
    "name:pol_x_preferred":[
        "Suwa"
    ],
    "name:por_x_preferred":[
        "Suwa"
    ],
    "name:swe_x_preferred":[
        "Suwa"
    ],
    "name:ukr_x_preferred":[
        "\u0421\u0443\u0432\u0430"
    ],
    "name:zho_x_preferred":[
        "\u82cf\u6d3c"
    ],
    "wof:name":"Suwa",
    "wof:placetype":"locality"
},
  "geometry": {"coordinates":[118.17400000000001,33.6864],"type":"Point"}
}