{
  "type": "Feature",
  "properties": {
    "gn:admin1_code":"4.0",
    "gn:asciiname":"Suwa",
    "gn:country_code":"CN",
    "gn:dem":20,
    "gn:feature_class":"P",
    "gn:feature_code":"PPL",
    "gn:name":"Suwa",
    "gn:population":0,
    "gn:timezone":"Asia/Shanghai",
    "iso:country":"CN",
    "name:zho_x_preferred":[
        "\u82cf\u6d3c"
    ],
    "wof:name":"Suwa",
    "wof:placetype":"locality"
},
  "geometry": {"coordinates":[118.17400000000001,33.6864],"type":"Point"}
}