{
  "type": "Feature",
  "properties": {
    "gn:admin1_code":"22.0",
    "gn:asciiname":"Dazhou Gezhuangcun",
    "gn:country_code":"CN",
    "gn:dem":47,
    "gn:feature_class":"P",
    "gn:feature_code":"PPL",
    "gn:name":"Dazhou Gezhuangcun",
    "gn:population":0,
    "gn:timezone":"Asia/Shanghai",
    "iso:country":"CN",
    "name:zho_x_preferred":[
        "\u5927\u5468\u5404\u5e84\u6751"
    ],
    "wof:name":"Dazhou Gezhuangcun",
    "wof:placetype":"locality"
},
  "geometry": {"coordinates":[116.71048,40.3031],"type":"Point"}
}