{
  "type": "Feature",
  "properties": {
    "gn:admin1_code":"4.0",
    "gn:asciiname":"Xiaodongzhuang",
    "gn:country_code":"CN",
    "gn:dem":8,
    "gn:feature_class":"P",
    "gn:feature_code":"PPL",
    "gn:name":"Xiaodongzhuang",
    "gn:population":0,
    "gn:timezone":"Asia/Shanghai",
    "iso:country":"CN",
    "name:zho_x_preferred":[
        "Xiaodongzhuang"
    ],
    "name:zho_x_variant":[
        "\u5c0f\u8463\u5e84"
    ],
    "wof:name":"Xiaodongzhuang",
    "wof:placetype":"locality"
},
  "geometry": {"coordinates":[119.00861999999999,33.43475],"type":"Point"}
}