{
  "type": "Feature",
  "properties": {
    "gn:admin1_code":"16.0",
    "gn:asciiname":"Shitangjiao",
    "gn:country_code":"CN",
    "gn:dem":165,
    "gn:feature_class":"P",
    "gn:feature_code":"PPL",
    "gn:name":"Shitangjiao",
    "gn:population":0,
    "gn:timezone":"Asia/Shanghai",
    "iso:country":"CN",
    "name:zho_x_preferred":[
        "\u77f3\u5858\u89d2"
    ],
    "wof:name":"Shitangjiao",
    "wof:placetype":"locality"
},
  "geometry": {"coordinates":[110.166,23.0574],"type":"Point"}
}