{
  "type": "Feature",
  "properties": {
    "gn:admin1_code":"15.0",
    "gn:asciiname":"Shandi Xiacun",
    "gn:country_code":"CN",
    "gn:dem":1064,
    "gn:feature_class":"P",
    "gn:feature_code":"PPL",
    "gn:name":"Shandi Xiacun",
    "gn:population":0,
    "gn:timezone":"Asia/Shanghai",
    "iso:country":"CN",
    "name:zho_x_preferred":[
        "\u5c71\u5e95\u4e0b\u6751"
    ],
    "wof:name":"Shandi Xiacun",
    "wof:placetype":"locality"
},
  "geometry": {"coordinates":[107.721,35.3371],"type":"Point"}
}