{
  "type": "Feature",
  "properties": {
    "gn:admin1_code":"24.0",
    "gn:asciiname":"Gezhengou",
    "gn:country_code":"CN",
    "gn:dem":984,
    "gn:feature_class":"P",
    "gn:feature_code":"PPL",
    "gn:name":"Gezhengou",
    "gn:population":0,
    "gn:timezone":"Asia/Shanghai",
    "iso:country":"CN",
    "name:zho_x_preferred":[
        "\u572a\u9488\u6c9f"
    ],
    "wof:name":"Gezhengou",
    "wof:placetype":"locality"
},
  "geometry": {"coordinates":[110.94746000000001,36.66039],"type":"Point"}
}