{
  "type": "Feature",
  "properties": {
    "gn:admin1_code":"05",
    "gn:asciiname":"Xiaosidong",
    "gn:country_code":"CN",
    "gn:dem":760,
    "gn:feature_class":"P",
    "gn:feature_code":"PPL",
    "gn:name":"Xiaosidong",
    "gn:population":0,
    "gn:timezone":"Asia/Shanghai",
    "iso:country":"CN",
    "name:und_x_variant":[
        "Hsiao-ssu-tung"
    ],
    "wof:name":"Xiaosidong",
    "wof:placetype":"locality"
},
  "geometry": {"coordinates":[128.15194,41.40056],"type":"Point"}
}