{
  "type": "Feature",
  "properties": {
    "gn:admin1_code":"4.0",
    "gn:asciiname":"Antangcun",
    "gn:country_code":"CN",
    "gn:dem":4,
    "gn:feature_class":"P",
    "gn:feature_code":"PPL",
    "gn:name":"Antangcun",
    "gn:population":0,
    "gn:timezone":"Asia/Shanghai",
    "iso:country":"CN",
    "name:zho_x_preferred":[
        "\u5b89\u5858\u6751"
    ],
    "wof:name":"Antangcun",
    "wof:placetype":"locality"
},
  "geometry": {"coordinates":[119.99487000000001,32.79071],"type":"Point"}
}