{
  "type": "Feature",
  "properties": {
    "gn:admin1_code":"7.0",
    "gn:asciiname":"Yangcheng",
    "gn:country_code":"CN",
    "gn:dem":649,
    "gn:feature_class":"P",
    "gn:feature_code":"PPL",
    "gn:name":"Yangcheng",
    "gn:population":0,
    "gn:timezone":"Asia/Shanghai",
    "iso:country":"CN",
    "name:ceb_x_preferred":[
        "Yangcheng"
    ],
    "name:deu_x_preferred":[
        "Yangcheng"
    ],
    "name:zho_x_preferred":[
        "\u6d0b\u57ce"
    ],
    "wof:name":"Yangcheng",
    "wof:placetype":"locality"
},
  "geometry": {"coordinates":[118.26802000000001,26.39501],"type":"Point"}
}