{
  "type": "Feature",
  "properties": {
    "gn:admin1_code":"26.0",
    "gn:asciiname":"Xiaomajia Shancun",
    "gn:country_code":"CN",
    "gn:dem":919,
    "gn:feature_class":"P",
    "gn:feature_code":"PPL",
    "gn:name":"Xiaomajia Shancun",
    "gn:population":0,
    "gn:timezone":"Asia/Shanghai",
    "iso:country":"CN",
    "name:zho_x_preferred":[
        "\u5c0f\u9a6c\u5bb6\u5c71\u6751"
    ],
    "wof:name":"Xiaomajia Shancun",
    "wof:placetype":"locality"
},
  "geometry": {"coordinates":[110.529,37.2134],"type":"Point"}
}