{
  "type": "Feature",
  "properties": {
    "gn:admin1_code":"29.0",
    "gn:asciiname":"Xiaonaobao",
    "gn:country_code":"CN",
    "gn:dem":1649,
    "gn:feature_class":"P",
    "gn:feature_code":"PPL",
    "gn:name":"Xiaonaobao",
    "gn:population":0,
    "gn:timezone":"Asia/Shanghai",
    "iso:country":"CN",
    "name:zho_x_preferred":[
        "\u5c0f\u8111\u5305"
    ],
    "wof:name":"Xiaonaobao",
    "wof:placetype":"locality"
},
  "geometry": {"coordinates":[103.09699999999999,26.5372],"type":"Point"}
}