{
  "type": "Feature",
  "properties": {
    "gn:admin1_code":"18",
    "gn:asciiname":"Yanfengkou",
    "gn:country_code":"CN",
    "gn:dem":1368,
    "gn:feature_class":"P",
    "gn:feature_code":"PPL",
    "gn:name":"Yanfengkou",
    "gn:population":0,
    "gn:timezone":"Asia/Shanghai",
    "iso:country":"CN",
    "name:zho_x_preferred":[
        "\u5ca9\u5cf0\u53e3"
    ],
    "wof:name":"Yanfengkou",
    "wof:placetype":"locality"
},
  "geometry": {"coordinates":[105.867,27.0644],"type":"Point"}
}