{
  "type": "Feature",
  "properties": {
    "gn:admin1_code":"5.0",
    "gn:asciiname":"Kuajiangtun",
    "gn:country_code":"CN",
    "gn:dem":213,
    "gn:feature_class":"P",
    "gn:feature_code":"PPL",
    "gn:name":"Kuajiangtun",
    "gn:population":0,
    "gn:timezone":"Asia/Shanghai",
    "iso:country":"CN",
    "name:zho_x_preferred":[
        "\u5938\u5c06\u5c6f"
    ],
    "wof:name":"Kuajiangtun",
    "wof:placetype":"locality"
},
  "geometry": {"coordinates":[125.62966000000002,43.73295],"type":"Point"}
}