{
  "type": "Feature",
  "properties": {
    "gn:admin1_code":"19.0",
    "gn:asciiname":"Dongbu",
    "gn:country_code":"CN",
    "gn:dem":299,
    "gn:feature_class":"P",
    "gn:feature_code":"PPL",
    "gn:name":"Dongbu",
    "gn:population":0,
    "gn:timezone":"Asia/Shanghai",
    "iso:country":"CN",
    "name:und_x_variant":[
        "Dongbao",
        "Dongbu"
    ],
    "name:zho_x_preferred":[
        "\u4e1c\u5821"
    ],
    "wof:name":"Dongbu",
    "wof:placetype":"locality"
},
  "geometry": {"coordinates":[124.3665,40.91303],"type":"Point"}
}