{
  "type": "Feature",
  "properties": {
    "gn:admin1_code":"29.0",
    "gn:asciiname":"Shangwei Beicun",
    "gn:country_code":"CN",
    "gn:dem":2080,
    "gn:feature_class":"P",
    "gn:feature_code":"PPL",
    "gn:name":"Shangwei Beicun",
    "gn:population":0,
    "gn:timezone":"Asia/Shanghai",
    "iso:country":"CN",
    "name:zho_x_preferred":[
        "\u4e0a\u672a\u5317\u6751"
    ],
    "wof:name":"Shangwei Beicun",
    "wof:placetype":"locality"
},
  "geometry": {"coordinates":[100.17700000000001,25.659],"type":"Point"}
}