{
  "type": "Feature",
  "properties": {
    "gn:admin1_code":"30.0",
    "gn:asciiname":"Liaoxingcun",
    "gn:country_code":"CN",
    "gn:dem":129,
    "gn:feature_class":"P",
    "gn:feature_code":"PPL",
    "gn:name":"Liaoxingcun",
    "gn:population":0,
    "gn:timezone":"Asia/Shanghai",
    "iso:country":"CN",
    "name:zho_x_preferred":[
        "\u5bee\u661f\u6751"
    ],
    "wof:name":"Liaoxingcun",
    "wof:placetype":"locality"
},
  "geometry": {"coordinates":[116.98529000000001,23.84678],"type":"Point"}
}