{
  "type": "Feature",
  "properties": {
    "gn:admin1_code":"26.0",
    "gn:asciiname":"Zhaize Goucun",
    "gn:country_code":"CN",
    "gn:dem":895,
    "gn:feature_class":"P",
    "gn:feature_code":"PPL",
    "gn:name":"Zhaize Goucun",
    "gn:population":0,
    "gn:timezone":"Asia/Shanghai",
    "iso:country":"CN",
    "name:zho_x_preferred":[
        "\u5be8\u5219\u6c9f\u6751"
    ],
    "wof:name":"Zhaize Goucun",
    "wof:placetype":"locality"
},
  "geometry": {"coordinates":[110.893,38.55],"type":"Point"}
}