{
  "type": "Feature",
  "properties": {
    "gn:admin1_code":"3.0",
    "gn:asciiname":"Dabuqiao",
    "gn:country_code":"CN",
    "gn:dem":781,
    "gn:feature_class":"P",
    "gn:feature_code":"PPL",
    "gn:name":"Dabuqiao",
    "gn:population":0,
    "gn:timezone":"Asia/Shanghai",
    "iso:country":"CN",
    "name:jpn_x_preferred":[
        "\u5927\u57e0\u6a4b\u8857\u9053"
    ],
    "name:und_x_variant":[
        "\u5927\u57e0\u6865"
    ],
    "name:zho_x_preferred":[
        "\u5927\u57e0\u6865\u8857\u9053"
    ],
    "wof:name":"Dabuqiao",
    "wof:placetype":"locality"
},
  "geometry": {"coordinates":[114.98184999999999,28.79655],"type":"Point"}
}