{
  "type": "Feature",
  "properties": {
    "gn:admin1_code":"10",
    "gn:asciiname":"Tufanzhuang",
    "gn:cc2":"CN",
    "gn:country_code":"CN",
    "gn:dem":16,
    "gn:feature_class":"P",
    "gn:feature_code":"PPL",
    "gn:name":"Tufanzhuang",
    "gn:population":0,
    "gn:timezone":"Asia/Shanghai",
    "iso:country":"CN",
    "name:und_x_variant":[
        "T\u2019u-fan-chuang",
        "Tufanzhuang"
    ],
    "wof:name":"Tufanzhuang",
    "wof:placetype":"locality"
},
  "geometry": {"coordinates":[116.40000000000001,37.81667],"type":"Point"}
}