{
  "type": "Feature",
  "properties": {
    "gn:admin1_code":"16.0",
    "gn:asciiname":"Gaoling Xincun",
    "gn:country_code":"CN",
    "gn:dem":77,
    "gn:feature_class":"P",
    "gn:feature_code":"PPL",
    "gn:name":"Gaoling Xincun",
    "gn:population":0,
    "gn:timezone":"Asia/Shanghai",
    "iso:country":"CN",
    "name:zho_x_preferred":[
        "\u9ad8\u5cad\u65b0\u6751"
    ],
    "wof:name":"Gaoling Xincun",
    "wof:placetype":"locality"
},
  "geometry": {"coordinates":[109.51600000000001,23.1335],"type":"Point"}
}