{
  "type": "Feature",
  "properties": {
    "iso:country":"CN",
    "name:ceb_x_preferred":[
        "Huaiyin Qu"
    ],
    "name:ces_x_preferred":[
        "Chuaj-jin"
    ],
    "name:cym_x_preferred":[
        "Ardal Huaiyin"
    ],
    "name:deu_x_preferred":[
        "Huaiyin"
    ],
    "name:eng_x_preferred":[
        "Huaiyin District"
    ],
    "name:gan_x_preferred":[
        "\u6dee\u9634\u533a"
    ],
    "name:jpn_x_preferred":[
        "\u6dee\u9670\u533a"
    ],
    "name:kor_x_preferred":[
        "\ud654\uc774\uc778\uad6c"
    ],
    "name:nan_x_preferred":[
        "Ho\u00e2i-im-khu"
    ],
    "name:nld_x_preferred":[
        "Huaiyin"
    ],
    "name:nob_x_preferred":[
        "Huaiyin"
    ],
    "name:rus_x_preferred":[
        "\u0425\u0443\u0430\u0439\u0438\u043d\u044c"
    ],
    "name:swe_x_preferred":[
        "Huaiyin"
    ],
    "name:vie_x_preferred":[
        "Ho\u00e0i \u00c2m"
    ],
    "name:wuu_x_preferred":[
        "\u6dee\u9634\u533a"
    ],
    "name:yue_x_preferred":[
        "\u6dee\u9670\u5340"
    ],
    "name:zho_x_preferred":[
        "\u6dee\u9634\u533a"
    ],
    "qs:name":"\u6dee\u9634\u533a",
    "qs:name_adm0":"\u4e2d\u570b",
    "qs:name_adm1":"\u6c5f\u82cf\u7701",
    "qs:photos":6,
    "qs:photos_1k":1,
    "qs:photos_9k":1,
    "qs:photos_9r":1,
    "qs:photos_all":24,
    "qs:photos_sr":1,
    "qs:placetype":"LocalAdmin",
    "qs:pop_sr":"0",
    "wd:wordcount":42,
    "wof:name":"\u6dee\u9634\u533a",
    "wof:placetype":"localadmin"
},
  "geometry": {"coordinates":[119.02399,33.600322],"type":"Point"}
}