{
  "type": "Feature",
  "properties": {
    "gn:admin1_code":"15.0",
    "gn:asciiname":"Zhangwan",
    "gn:country_code":"CN",
    "gn:dem":1497,
    "gn:feature_class":"P",
    "gn:feature_code":"PPL",
    "gn:name":"Zhangwan",
    "gn:population":0,
    "gn:timezone":"Asia/Shanghai",
    "iso:country":"CN",
    "name:ceb_x_preferred":[
        "Zhangwan"
    ],
    "name:deu_x_preferred":[
        "Zhangwan"
    ],
    "name:zho_x_preferred":[
        "\u638c\u6e7e"
    ],
    "wof:name":"Zhangwan",
    "wof:placetype":"locality"
},
  "geometry": {"coordinates":[108.00700000000001,36.522],"type":"Point"}
}