{
  "type": "Feature",
  "properties": {
    "gn:admin1_code":"9.0",
    "gn:asciiname":"Sunjiacha",
    "gn:country_code":"CN",
    "gn:dem":1113,
    "gn:feature_class":"P",
    "gn:feature_code":"PPL",
    "gn:name":"Sunjiacha",
    "gn:population":0,
    "gn:timezone":"Asia/Shanghai",
    "iso:country":"CN",
    "name:zho_x_preferred":[
        "\u5b59\u5bb6\u5c94"
    ],
    "wof:name":"Sunjiacha",
    "wof:placetype":"locality"
},
  "geometry": {"coordinates":[111.129,34.19919],"type":"Point"}
}