{
  "type": "Feature",
  "properties": {
    "gn:admin1_code":"32.0",
    "gn:asciiname":"Changshuidong",
    "gn:country_code":"CN",
    "gn:dem":579,
    "gn:feature_class":"P",
    "gn:feature_code":"PPL",
    "gn:name":"Changshuidong",
    "gn:population":0,
    "gn:timezone":"Asia/Shanghai",
    "iso:country":"CN",
    "name:zho_x_preferred":[
        "\u660c\u6c34\u6d1e"
    ],
    "wof:name":"Changshuidong",
    "wof:placetype":"locality"
},
  "geometry": {"coordinates":[103.47554,30.20353],"type":"Point"}
}