{
  "type": "Feature",
  "properties": {
    "gn:admin1_code":"14.0",
    "gn:asciiname":"Gouduo",
    "gn:country_code":"CN",
    "gn:dem":4104,
    "gn:feature_class":"P",
    "gn:feature_code":"PPL",
    "gn:name":"Gouduo",
    "gn:population":0,
    "gn:timezone":"Asia/Urumqi",
    "iso:country":"CN",
    "name:zho_x_preferred":[
        "\u6c9f\u591a"
    ],
    "wof:name":"Gouduo",
    "wof:placetype":"locality"
},
  "geometry": {"coordinates":[97.59381999999999,30.92017],"type":"Point"}
}