{
  "type": "Feature",
  "properties": {
    "gn:admin1_code":"16.0",
    "gn:asciiname":"Jia'ang",
    "gn:country_code":"CN",
    "gn:dem":476,
    "gn:feature_class":"P",
    "gn:feature_code":"PPL",
    "gn:name":"Jia\u2019ang",
    "gn:population":0,
    "gn:timezone":"Asia/Shanghai",
    "iso:country":"CN",
    "name:und_x_variant":[
        "Jia\u2019ang"
    ],
    "name:zho_x_preferred":[
        "\u7532\u6602"
    ],
    "wof:name":"Jia'ang",
    "wof:placetype":"locality"
},
  "geometry": {"coordinates":[109.092,25.3339],"type":"Point"}
}