{
  "type": "Feature",
  "properties": {
    "gn:admin1_code":"29.0",
    "gn:asciiname":"Datangzi",
    "gn:country_code":"CN",
    "gn:dem":1884,
    "gn:feature_class":"P",
    "gn:feature_code":"PPL",
    "gn:name":"Datangzi",
    "gn:population":0,
    "gn:timezone":"Asia/Shanghai",
    "iso:country":"CN",
    "name:zho_x_preferred":[
        "\u5927\u5858\u5b50"
    ],
    "wof:name":"Datangzi",
    "wof:placetype":"locality"
},
  "geometry": {"coordinates":[103.565,24.3904],"type":"Point"}
}