{
  "type": "Feature",
  "properties": {
    "gn:admin1_code":"12.0",
    "gn:asciiname":"Lianjiepeng",
    "gn:country_code":"CN",
    "gn:dem":72,
    "gn:feature_class":"P",
    "gn:feature_code":"PPL",
    "gn:name":"Lianjiepeng",
    "gn:population":0,
    "gn:timezone":"Asia/Shanghai",
    "iso:country":"CN",
    "name:zho_x_preferred":[
        "\u8fde\u754c\u68da"
    ],
    "wof:name":"Lianjiepeng",
    "wof:placetype":"locality"
},
  "geometry": {"coordinates":[113.77555,31.24076],"type":"Point"}
}