{
  "type": "Feature",
  "properties": {
    "gn:admin1_code":"24.0",
    "gn:asciiname":"Qinghedian",
    "gn:country_code":"CN",
    "gn:dem":1305,
    "gn:feature_class":"P",
    "gn:feature_code":"PPL",
    "gn:name":"Qinghedian",
    "gn:population":0,
    "gn:timezone":"Asia/Shanghai",
    "iso:country":"CN",
    "name:zho_x_preferred":[
        "\u6e05\u6cb3\u5e97"
    ],
    "wof:name":"Qinghedian",
    "wof:placetype":"locality"
},
  "geometry": {"coordinates":[113.44812,37.1873],"type":"Point"}
}