{
  "type": "Feature",
  "properties": {
    "gn:admin1_code":"19.0",
    "gn:asciiname":"Lamayingzicun",
    "gn:country_code":"CN",
    "gn:dem":112,
    "gn:feature_class":"P",
    "gn:feature_code":"PPL",
    "gn:name":"Lamayingzicun",
    "gn:population":0,
    "gn:timezone":"Asia/Shanghai",
    "iso:country":"CN",
    "name:zho_x_preferred":[
        "\u5587\u561b\u8425\u5b50\u6751"
    ],
    "wof:name":"Lamayingzicun",
    "wof:placetype":"locality"
},
  "geometry": {"coordinates":[121.962,41.9553],"type":"Point"}
}