{
  "type": "Feature",
  "properties": {
    "gn:admin1_code":"16.0",
    "gn:asciiname":"Pushuitan",
    "gn:country_code":"CN",
    "gn:dem":21,
    "gn:feature_class":"P",
    "gn:feature_code":"PPL",
    "gn:name":"Pushuitan",
    "gn:population":0,
    "gn:timezone":"Asia/Shanghai",
    "iso:country":"CN",
    "name:zho_x_preferred":[
        "\u7011\u6c34\u6ee9"
    ],
    "wof:name":"Pushuitan",
    "wof:placetype":"locality"
},
  "geometry": {"coordinates":[108.976,21.7345],"type":"Point"}
}