{
  "type": "Feature",
  "properties": {
    "gn:admin1_code":"19.0",
    "gn:asciiname":"Huangjiazhangzi",
    "gn:country_code":"CN",
    "gn:dem":283,
    "gn:feature_class":"P",
    "gn:feature_code":"PPL",
    "gn:name":"Huangjiazhangzi",
    "gn:population":0,
    "gn:timezone":"Asia/Shanghai",
    "iso:country":"CN",
    "name:zho_x_preferred":[
        "\u9ec4\u5bb6\u6756\u5b50"
    ],
    "wof:name":"Huangjiazhangzi",
    "wof:placetype":"locality"
},
  "geometry": {"coordinates":[120.25011000000001,40.75134],"type":"Point"}
}