{
  "type": "Feature",
  "properties": {
    "gn:admin1_code":"1.0",
    "gn:asciiname":"Gongchangyuan",
    "gn:country_code":"CN",
    "gn:dem":550,
    "gn:feature_class":"P",
    "gn:feature_code":"PPL",
    "gn:name":"Gongchangyuan",
    "gn:population":0,
    "gn:timezone":"Asia/Shanghai",
    "iso:country":"CN",
    "name:zho_x_preferred":[
        "\u5bab\u957f\u6e90"
    ],
    "wof:name":"Gongchangyuan",
    "wof:placetype":"locality"
},
  "geometry": {"coordinates":[117.64107,29.63888],"type":"Point"}
}