{
  "type": "Feature",
  "properties": {
    "gn:admin1_code":"2.0",
    "gn:asciiname":"Bawujia",
    "gn:country_code":"CN",
    "gn:dem":148,
    "gn:feature_class":"P",
    "gn:feature_code":"PPL",
    "gn:name":"Bawujia",
    "gn:population":0,
    "gn:timezone":"Asia/Shanghai",
    "iso:country":"CN",
    "name:zho_x_preferred":[
        "\u8019\u575e\u5bb6"
    ],
    "wof:name":"Bawujia",
    "wof:placetype":"locality"
},
  "geometry": {"coordinates":[118.913,29.64403],"type":"Point"}
}