{
  "type": "Feature",
  "properties": {
    "gn:admin1_code":"5.0",
    "gn:asciiname":"Xing'ancun",
    "gn:country_code":"CN",
    "gn:dem":195,
    "gn:feature_class":"P",
    "gn:feature_code":"PPL",
    "gn:name":"Xing\u2019ancun",
    "gn:population":0,
    "gn:timezone":"Asia/Shanghai",
    "iso:country":"CN",
    "name:und_x_variant":[
        "Xing\u2019ancun",
        "Xing\u2019an",
        "\u5174\u5b89"
    ],
    "name:zho_x_preferred":[
        "\u5174\u5b89\u6751"
    ],
    "wof:name":"Xing'ancun",
    "wof:placetype":"locality"
},
  "geometry": {"coordinates":[129.4906,42.93837],"type":"Point"}
}