{
  "type": "Feature",
  "properties": {
    "gn:admin1_code":"19.0",
    "gn:asciiname":"Huaishugoucun",
    "gn:country_code":"CN",
    "gn:dem":124,
    "gn:feature_class":"P",
    "gn:feature_code":"PPL",
    "gn:name":"Huaishugoucun",
    "gn:population":0,
    "gn:timezone":"Asia/Shanghai",
    "iso:country":"CN",
    "name:zho_x_preferred":[
        "\u69d0\u6811\u6c9f\u6751"
    ],
    "wof:name":"Huaishugoucun",
    "wof:placetype":"locality"
},
  "geometry": {"coordinates":[120.77,40.8835],"type":"Point"}
}