{
  "type": "Feature",
  "properties": {
    "gn:admin1_code":"20.0",
    "gn:asciiname":"Xiaobeitun",
    "gn:country_code":"CN",
    "gn:dem":634,
    "gn:feature_class":"P",
    "gn:feature_code":"PPL",
    "gn:name":"Xiaobeitun",
    "gn:population":0,
    "gn:timezone":"Asia/Shanghai",
    "iso:country":"CN",
    "name:und_x_variant":[
        "\u5c0f\u5317\u5c6f"
    ],
    "wof:name":"Xiaobeitun",
    "wof:placetype":"locality"
},
  "geometry": {"coordinates":[117.456,49.5985],"type":"Point"}
}