{
  "type": "Feature",
  "properties": {
    "gn:admin1_code":"9.0",
    "gn:asciiname":"Qianshao",
    "gn:country_code":"CN",
    "gn:dem":59,
    "gn:feature_class":"P",
    "gn:feature_code":"PPL",
    "gn:name":"Qianshao",
    "gn:population":0,
    "gn:timezone":"Asia/Shanghai",
    "iso:country":"CN",
    "name:zho_x_preferred":[
        "\u524d\u90b5"
    ],
    "wof:name":"Qianshao",
    "wof:placetype":"locality"
},
  "geometry": {"coordinates":[114.14409000000001,33.77715999999999],"type":"Point"}
}