{
  "type": "Feature",
  "properties": {
    "gn:admin1_code":"10",
    "gn:asciiname":"Qiandufeng",
    "gn:country_code":"CN",
    "gn:dem":113,
    "gn:feature_class":"P",
    "gn:feature_code":"PPL",
    "gn:name":"Qiandufeng",
    "gn:population":0,
    "gn:timezone":"Asia/Shanghai",
    "iso:country":"CN",
    "name:zho_x_preferred":[
        "\u524d\u90fd\u4e30"
    ],
    "wof:name":"Qiandufeng",
    "wof:placetype":"locality"
},
  "geometry": {"coordinates":[114.50700000000001,37.4936],"type":"Point"}
}