{
  "type": "Feature",
  "properties": {
    "gn:admin1_code":"29.0",
    "gn:asciiname":"Dahaizi",
    "gn:country_code":"CN",
    "gn:dem":2248,
    "gn:feature_class":"P",
    "gn:feature_code":"PPL",
    "gn:name":"Dahaizi",
    "gn:population":0,
    "gn:timezone":"Asia/Shanghai",
    "iso:country":"CN",
    "name:zho_x_preferred":[
        "\u5927\u6d77\u5b50"
    ],
    "wof:name":"Dahaizi",
    "wof:placetype":"locality"
},
  "geometry": {"coordinates":[100.65000000000001,25.3154],"type":"Point"}
}