{
  "type": "Feature",
  "properties": {
    "gn:admin1_code":"29.0",
    "gn:asciiname":"Dianwei",
    "gn:country_code":"CN",
    "gn:dem":1899,
    "gn:feature_class":"P",
    "gn:feature_code":"PPL",
    "gn:name":"Dianwei",
    "gn:population":0,
    "gn:timezone":"Asia/Shanghai",
    "iso:country":"CN",
    "name:zho_x_preferred":[
        "\u7538\u5c3e"
    ],
    "wof:name":"Dianwei",
    "wof:placetype":"locality"
},
  "geometry": {"coordinates":[103.102,25.2996],"type":"Point"}
}