{
  "type": "Feature",
  "properties": {
    "gn:admin1_code":"2.0",
    "gn:asciiname":"Huochabang",
    "gn:country_code":"CN",
    "gn:dem":5,
    "gn:feature_class":"P",
    "gn:feature_code":"PPL",
    "gn:name":"Huochabang",
    "gn:population":0,
    "gn:timezone":"Asia/Shanghai",
    "iso:country":"CN",
    "name:und_x_variant":[
        "\u706b\u53c9\u6d5c"
    ],
    "wof:name":"Huochabang",
    "wof:placetype":"locality"
},
  "geometry": {"coordinates":[120.8484,30.93392],"type":"Point"}
}