{
  "type": "Feature",
  "properties": {
    "gn:admin1_code":"6.0",
    "gn:asciiname":"Duoxige",
    "gn:country_code":"CN",
    "gn:dem":3900,
    "gn:feature_class":"P",
    "gn:feature_code":"PPL",
    "gn:name":"Duoxige",
    "gn:population":0,
    "gn:timezone":"Asia/Urumqi",
    "iso:country":"CN",
    "name:zho_x_preferred":[
        "\u591a\u5e0c\u683c"
    ],
    "wof:name":"Duoxige",
    "wof:placetype":"locality"
},
  "geometry": {"coordinates":[97.12555,32.10163],"type":"Point"}
}