{
  "type": "Feature",
  "properties": {
    "gn:admin1_code":"1.0",
    "gn:asciiname":"Zhimacun",
    "gn:country_code":"CN",
    "gn:dem":70,
    "gn:feature_class":"P",
    "gn:feature_code":"PPL",
    "gn:name":"Zhimacun",
    "gn:population":0,
    "gn:timezone":"Asia/Shanghai",
    "iso:country":"CN",
    "name:zho_x_preferred":[
        "\u829d\u9ebb\u6751"
    ],
    "wof:name":"Zhimacun",
    "wof:placetype":"locality"
},
  "geometry": {"coordinates":[117.43134000000001,32.5627],"type":"Point"}
}