{
  "type": "Feature",
  "properties": {
    "gn:admin1_code":"8.0",
    "gn:asciiname":"Shanhoucun",
    "gn:country_code":"CN",
    "gn:dem":312,
    "gn:feature_class":"P",
    "gn:feature_code":"PPL",
    "gn:name":"Shanhoucun",
    "gn:population":0,
    "gn:timezone":"Asia/Shanghai",
    "iso:country":"CN",
    "name:zho_x_preferred":[
        "\u5c71\u540e\u6751"
    ],
    "wof:name":"Shanhoucun",
    "wof:placetype":"locality"
},
  "geometry": {"coordinates":[129.16231999999999,44.31375],"type":"Point"}
}