{
  "type": "Feature",
  "properties": {
    "gn:admin1_code":"9.0",
    "gn:asciiname":"Shangliuzhuang",
    "gn:country_code":"CN",
    "gn:dem":129,
    "gn:feature_class":"P",
    "gn:feature_code":"PPL",
    "gn:name":"Shangliuzhuang",
    "gn:population":0,
    "gn:timezone":"Asia/Shanghai",
    "iso:country":"CN",
    "name:zho_x_preferred":[
        "\u4e0a\u5218\u5e84"
    ],
    "wof:name":"Shangliuzhuang",
    "wof:placetype":"locality"
},
  "geometry": {"coordinates":[112.91065999999999,32.52617],"type":"Point"}
}