{
  "type": "Feature",
  "properties": {
    "gn:admin1_code":"8.0",
    "gn:asciiname":"Rongwangcun",
    "gn:country_code":"CN",
    "gn:dem":169,
    "gn:feature_class":"P",
    "gn:feature_code":"PPL",
    "gn:name":"Rongwangcun",
    "gn:population":0,
    "gn:timezone":"Asia/Shanghai",
    "iso:country":"CN",
    "name:zho_x_preferred":[
        "\u8363\u65fa\u6751"
    ],
    "wof:name":"Rongwangcun",
    "wof:placetype":"locality"
},
  "geometry": {"coordinates":[126.1476,46.11265],"type":"Point"}
}