{
  "type": "Feature",
  "properties": {
    "gn:admin1_code":"12.0",
    "gn:asciiname":"Beijishi",
    "gn:country_code":"CN",
    "gn:dem":295,
    "gn:feature_class":"P",
    "gn:feature_code":"PPL",
    "gn:name":"Beijishi",
    "gn:population":0,
    "gn:timezone":"Asia/Shanghai",
    "iso:country":"CN",
    "name:zho_x_preferred":[
        "\u7891\u8bb0\u77f3"
    ],
    "wof:name":"Beijishi",
    "wof:placetype":"locality"
},
  "geometry": {"coordinates":[110.47329999999999,32.86976],"type":"Point"}
}