{
  "type": "Feature",
  "properties": {
    "gn:admin1_code":"1.0",
    "gn:asciiname":"Xiaowuying",
    "gn:country_code":"CN",
    "gn:dem":31,
    "gn:feature_class":"P",
    "gn:feature_code":"PPL",
    "gn:name":"Xiaowuying",
    "gn:population":0,
    "gn:timezone":"Asia/Shanghai",
    "iso:country":"CN",
    "name:zho_x_preferred":[
        "\u5c0f\u6b66\u90e2"
    ],
    "wof:name":"Xiaowuying",
    "wof:placetype":"locality"
},
  "geometry": {"coordinates":[118.68013999999999,32.59672],"type":"Point"}
}