{
  "type": "Feature",
  "properties": {
    "gn:admin1_code":"26.0",
    "gn:asciiname":"Luoquanyacun",
    "gn:country_code":"CN",
    "gn:dem":530,
    "gn:feature_class":"P",
    "gn:feature_code":"PPL",
    "gn:name":"Luoquanyacun",
    "gn:population":0,
    "gn:timezone":"Asia/Shanghai",
    "iso:country":"CN",
    "name:zho_x_preferred":[
        "\u7f57\u5708\u5d16\u6751"
    ],
    "wof:name":"Luoquanyacun",
    "wof:placetype":"locality"
},
  "geometry": {"coordinates":[108.80628,34.69183],"type":"Point"}
}