{
  "type": "Feature",
  "properties": {
    "gn:admin1_code":"11.0",
    "gn:asciiname":"Pengjiapo",
    "gn:country_code":"CN",
    "gn:dem":169,
    "gn:feature_class":"P",
    "gn:feature_code":"PPL",
    "gn:name":"Pengjiapo",
    "gn:population":0,
    "gn:timezone":"Asia/Shanghai",
    "iso:country":"CN",
    "name:zho_x_preferred":[
        "Pengjiapo"
    ],
    "name:zho_x_variant":[
        "\u5f6d\u5bb6\u5761"
    ],
    "wof:name":"Pengjiapo",
    "wof:placetype":"locality"
},
  "geometry": {"coordinates":[110.47367,29.11337],"type":"Point"}
}