{
  "type": "Feature",
  "properties": {
    "gn:admin1_code":"3.0",
    "gn:asciiname":"Yechong",
    "gn:country_code":"CN",
    "gn:dem":152,
    "gn:feature_class":"P",
    "gn:feature_code":"PPL",
    "gn:name":"Yechong",
    "gn:population":0,
    "gn:timezone":"Asia/Shanghai",
    "iso:country":"CN",
    "name:zho_x_preferred":[
        "\u91ce\u51b2"
    ],
    "wof:name":"Yechong",
    "wof:placetype":"locality"
},
  "geometry": {"coordinates":[113.828,27.7562],"type":"Point"}
}