{
  "type": "Feature",
  "properties": {
    "gn:admin1_code":"3.0",
    "gn:asciiname":"Henglishan",
    "gn:country_code":"CN",
    "gn:dem":260,
    "gn:feature_class":"P",
    "gn:feature_code":"PPLA4",
    "gn:name":"Henglishan",
    "gn:population":0,
    "gn:timezone":"Asia/Shanghai",
    "iso:country":"CN",
    "name:und_x_variant":[
        "\u6a2a\u7acb\u5c71",
        "Henglishan Xiang",
        "\u6a2a\u7acb\u5c71\u4e61"
    ],
    "wof:name":"Henglishan",
    "wof:placetype":"locality"
},
  "geometry": {"coordinates":[115.43453999999998,29.70042],"type":"Point"}
}