{
  "type": "Feature",
  "properties": {
    "gn:admin1_code":"29.0",
    "gn:asciiname":"Panguli",
    "gn:country_code":"CN",
    "gn:dem":1455,
    "gn:feature_class":"P",
    "gn:feature_code":"PPL",
    "gn:name":"Panguli",
    "gn:population":0,
    "gn:timezone":"Asia/Shanghai",
    "iso:country":"CN",
    "name:zho_x_preferred":[
        "\u6f58\u53e4\u91cc"
    ],
    "wof:name":"Panguli",
    "wof:placetype":"locality"
},
  "geometry": {"coordinates":[101.59399999999999,25.8842],"type":"Point"}
}