{
  "type": "Feature",
  "properties": {
    "gn:admin1_code":"29.0",
    "gn:asciiname":"Duoyi Shangzhai",
    "gn:country_code":"CN",
    "gn:dem":1715,
    "gn:feature_class":"P",
    "gn:feature_code":"PPL",
    "gn:name":"Duoyi Shangzhai",
    "gn:population":0,
    "gn:timezone":"Asia/Shanghai",
    "iso:country":"CN",
    "name:zho_x_preferred":[
        "\u591a\u4f9d\u4e0a\u5be8"
    ],
    "wof:name":"Duoyi Shangzhai",
    "wof:placetype":"locality"
},
  "geometry": {"coordinates":[103.276,23.1716],"type":"Point"}
}