{
  "type": "Feature",
  "properties": {
    "gn:admin1_code":"3",
    "gn:asciiname":"Duntou Pingshang",
    "gn:country_code":"CN",
    "gn:dem":191,
    "gn:feature_class":"P",
    "gn:feature_code":"PPL",
    "gn:name":"Duntou Pingshang",
    "gn:population":0,
    "gn:timezone":"Asia/Shanghai",
    "iso:country":"CN",
    "name:und_x_variant":[
        "\u58a9\u5934\u576a\u4e0a",
        "Dunshang"
    ],
    "wof:name":"Duntou Pingshang",
    "wof:placetype":"locality"
},
  "geometry": {"coordinates":[116.74871,27.58887],"type":"Point"}
}