{
  "type": "Feature",
  "properties": {
    "gn:admin1_code":"25",
    "gn:asciiname":"Baimacun",
    "gn:country_code":"CN",
    "gn:dem":18,
    "gn:feature_class":"P",
    "gn:feature_code":"PPL",
    "gn:name":"Baimacun",
    "gn:population":0,
    "gn:timezone":"Asia/Shanghai",
    "iso:country":"CN",
    "name:und_x_variant":[
        "Baima",
        "Baimacun"
    ],
    "name:zho_x_preferred":[
        "\u767d\u9a6c\u6751"
    ],
    "wof:name":"Baimacun",
    "wof:placetype":"locality"
},
  "geometry": {"coordinates":[122.31014999999999,37.35233],"type":"Point"}
}