{
  "type": "Feature",
  "properties": {
    "gn:admin1_code":"13.0",
    "gn:asciiname":"Qiaolake",
    "gn:country_code":"CN",
    "gn:dem":1208,
    "gn:feature_class":"P",
    "gn:feature_code":"PPL",
    "gn:name":"Qiaolake",
    "gn:population":0,
    "gn:timezone":"Asia/Shanghai",
    "iso:country":"CN",
    "name:zho_x_preferred":[
        "\u4e54\u62c9\u514b"
    ],
    "wof:name":"Qiaolake",
    "wof:placetype":"locality"
},
  "geometry": {"coordinates":[76.74414,39.3849],"type":"Point"}
}