{
  "type": "Feature",
  "properties": {
    "gn:admin1_code":"25",
    "gn:asciiname":"Dabu",
    "gn:country_code":"CN",
    "gn:dem":98,
    "gn:feature_class":"P",
    "gn:feature_code":"PPL",
    "gn:name":"Dabu",
    "gn:population":0,
    "gn:timezone":"Asia/Shanghai",
    "iso:country":"CN",
    "name:ceb_x_preferred":[
        "Dabu"
    ],
    "name:deu_x_preferred":[
        "Dabu"
    ],
    "name:fra_x_preferred":[
        "Dabu"
    ],
    "name:ita_x_preferred":[
        "Dabu"
    ],
    "name:zho_x_preferred":[
        "\u5927\u57e0"
    ],
    "wof:name":"Dabu",
    "wof:placetype":"locality"
},
  "geometry": {"coordinates":[120.697,37.1657],"type":"Point"}
}