{
  "type": "Feature",
  "properties": {
    "gn:admin1_code":"26.0",
    "gn:asciiname":"Zhaizi'ao",
    "gn:country_code":"CN",
    "gn:dem":832,
    "gn:feature_class":"P",
    "gn:feature_code":"PPL",
    "gn:name":"Zhaizi\u2019ao",
    "gn:population":0,
    "gn:timezone":"Asia/Shanghai",
    "iso:country":"CN",
    "name:und_x_variant":[
        "Zhaizi\u2019ao"
    ],
    "name:zho_x_preferred":[
        "\u5be8\u5b50\u51f9"
    ],
    "wof:name":"Zhaizi'ao",
    "wof:placetype":"locality"
},
  "geometry": {"coordinates":[109.87366000000002,33.62952],"type":"Point"}
}