{
  "type": "Feature",
  "properties": {
    "gn:admin1_code":"32.0",
    "gn:asciiname":"Erha",
    "gn:country_code":"CN",
    "gn:dem":2287,
    "gn:feature_class":"P",
    "gn:feature_code":"PPL",
    "gn:name":"Erha",
    "gn:population":0,
    "gn:timezone":"Asia/Shanghai",
    "iso:country":"CN",
    "name:zho_x_preferred":[
        "\u5c14\u54c8"
    ],
    "wof:name":"Erha",
    "wof:placetype":"locality"
},
  "geometry": {"coordinates":[103.005,28.3482],"type":"Point"}
}