{
  "type": "Feature",
  "properties": {
    "gn:admin1_code":"30",
    "gn:asciiname":"Nanshanzhai",
    "gn:country_code":"CN",
    "gn:dem":157,
    "gn:feature_class":"P",
    "gn:feature_code":"PPL",
    "gn:name":"Nanshanzhai",
    "gn:population":0,
    "gn:timezone":"Asia/Shanghai",
    "iso:country":"CN",
    "name:zho_x_preferred":[
        "\u5357\u5c71\u5be8"
    ],
    "wof:name":"Nanshanzhai",
    "wof:placetype":"locality"
},
  "geometry": {"coordinates":[111.66316999999999,22.37151],"type":"Point"}
}