{
  "type": "Feature",
  "properties": {
    "gn:admin1_code":"11.0",
    "gn:asciiname":"Hechangzui",
    "gn:country_code":"CN",
    "gn:dem":47,
    "gn:feature_class":"P",
    "gn:feature_code":"PPL",
    "gn:name":"Hechangzui",
    "gn:population":0,
    "gn:timezone":"Asia/Shanghai",
    "iso:country":"CN",
    "name:zho_x_preferred":[
        "\u79be\u573a\u5634"
    ],
    "wof:name":"Hechangzui",
    "wof:placetype":"locality"
},
  "geometry": {"coordinates":[112.86165,28.10404],"type":"Point"}
}