{
  "type": "Feature",
  "properties": {
    "gn:admin1_code":"12.0",
    "gn:asciiname":"Hekoushang",
    "gn:country_code":"CN",
    "gn:dem":1076,
    "gn:feature_class":"P",
    "gn:feature_code":"PPL",
    "gn:name":"Hekoushang",
    "gn:population":0,
    "gn:timezone":"Asia/Shanghai",
    "iso:country":"CN",
    "name:zho_x_preferred":[
        "\u6cb3\u53e3\u4e0a"
    ],
    "wof:name":"Hekoushang",
    "wof:placetype":"locality"
},
  "geometry": {"coordinates":[109.08978999999999,30.37137],"type":"Point"}
}