{
  "type": "Feature",
  "properties": {
    "gn:admin1_code":"5.0",
    "gn:asciiname":"Xixingtun",
    "gn:country_code":"CN",
    "gn:dem":274,
    "gn:feature_class":"P",
    "gn:feature_code":"PPL",
    "gn:name":"Xixingtun",
    "gn:population":0,
    "gn:timezone":"Asia/Shanghai",
    "iso:country":"CN",
    "name:zho_x_preferred":[
        "\u897f\u5174\u5c6f"
    ],
    "wof:name":"Xixingtun",
    "wof:placetype":"locality"
},
  "geometry": {"coordinates":[126.94215,43.36268],"type":"Point"}
}