{
  "type": "Feature",
  "properties": {
    "gn:admin1_code":"2.0",
    "gn:asciiname":"Yeyabang",
    "gn:country_code":"CN",
    "gn:dem":8,
    "gn:feature_class":"P",
    "gn:feature_code":"PPL",
    "gn:name":"Yeyabang",
    "gn:population":0,
    "gn:timezone":"Asia/Shanghai",
    "iso:country":"CN",
    "name:und_x_variant":[
        "\u91ce\u9e2d\u6d5c"
    ],
    "wof:name":"Yeyabang",
    "wof:placetype":"locality"
},
  "geometry": {"coordinates":[120.33154999999999,30.55645],"type":"Point"}
}