{
  "type": "Feature",
  "properties": {
    "gn:admin1_code":"20",
    "gn:asciiname":"Ching-t'ung-tzu-kou",
    "gn:country_code":"CN",
    "gn:dem":787,
    "gn:feature_class":"P",
    "gn:feature_code":"PPL",
    "gn:name":"Ching-t\u2019ung-tzu-kou",
    "gn:population":0,
    "gn:timezone":"Asia/Shanghai",
    "iso:country":"CN",
    "wof:name":"Ching-t'ung-tzu-kou",
    "wof:placetype":"locality"
},
  "geometry": {"coordinates":[118.91833,42.79889],"type":"Point"}
}