{
  "type": "Feature",
  "properties": {
    "gn:admin1_code":"14.0",
    "gn:asciiname":"Sadoi",
    "gn:country_code":"CN",
    "gn:dem":4408,
    "gn:feature_class":"P",
    "gn:feature_code":"PPLF",
    "gn:name":"Sadoi",
    "gn:population":0,
    "gn:timezone":"Asia/Urumqi",
    "iso:country":"CN",
    "name:bod_x_preferred":[
        "Sadoi"
    ],
    "name:zho_x_preferred":[
        "Sedui"
    ],
    "name:zho_x_variant":[
        "\u8272\u5806",
        "Niesa",
        "\u6d85\u8428"
    ],
    "wof:name":"Sadoi",
    "wof:placetype":"locality"
},
  "geometry": {"coordinates":[87.904,28.904],"type":"Point"}
}