{
  "type": "Feature",
  "properties": {
    "gn:admin1_code":"5.0",
    "gn:asciiname":"Wangdou Fufang",
    "gn:country_code":"CN",
    "gn:dem":133,
    "gn:feature_class":"P",
    "gn:feature_code":"PPL",
    "gn:name":"Wangdou Fufang",
    "gn:population":0,
    "gn:timezone":"Asia/Shanghai",
    "iso:country":"CN",
    "name:zho_x_preferred":[
        "\u738b\u8c46\u8150\u623f"
    ],
    "wof:name":"Wangdou Fufang",
    "wof:placetype":"locality"
},
  "geometry": {"coordinates":[124.64903,45.27511],"type":"Point"}
}