{
  "type": "Feature",
  "properties": {
    "gn:admin1_code":"12.0",
    "gn:asciiname":"Zhuangjiahe",
    "gn:country_code":"CN",
    "gn:dem":972,
    "gn:feature_class":"P",
    "gn:feature_code":"PPL",
    "gn:name":"Zhuangjiahe",
    "gn:population":0,
    "gn:timezone":"Asia/Shanghai",
    "iso:country":"CN",
    "name:zho_x_preferred":[
        "\u6869\u5bb6\u6cb3"
    ],
    "wof:name":"Zhuangjiahe",
    "wof:placetype":"locality"
},
  "geometry": {"coordinates":[110.66079000000001,32.34500999999999],"type":"Point"}
}