{
  "type": "Feature",
  "properties": {
    "gn:admin1_code":"32.0",
    "gn:asciiname":"Sandaocheng",
    "gn:country_code":"CN",
    "gn:dem":2020,
    "gn:feature_class":"P",
    "gn:feature_code":"PPL",
    "gn:name":"Sandaocheng",
    "gn:population":0,
    "gn:timezone":"Asia/Shanghai",
    "iso:country":"CN",
    "name:zho_x_preferred":[
        "\u4e09\u9053\u57ce"
    ],
    "wof:name":"Sandaocheng",
    "wof:placetype":"locality"
},
  "geometry": {"coordinates":[103.93322000000001,33.54526],"type":"Point"}
}