{
  "type": "Feature",
  "properties": {
    "gn:admin1_code":"29.0",
    "gn:asciiname":"Da'ede",
    "gn:country_code":"CN",
    "gn:dem":1950,
    "gn:feature_class":"P",
    "gn:feature_code":"PPL",
    "gn:name":"Da\u2019ede",
    "gn:population":0,
    "gn:timezone":"Asia/Shanghai",
    "iso:country":"CN",
    "name:und_x_variant":[
        "Da\u2019ede"
    ],
    "name:zho_x_preferred":[
        "\u5927\u4fc4\u5f97"
    ],
    "wof:name":"Da'ede",
    "wof:placetype":"locality"
},
  "geometry": {"coordinates":[104.128,25.018],"type":"Point"}
}