{
  "type": "Feature",
  "properties": {
    "gn:admin1_code":"22",
    "gn:asciiname":"Wanggezhuang",
    "gn:country_code":"CN",
    "gn:dem":21,
    "gn:feature_class":"P",
    "gn:feature_code":"PPL",
    "gn:name":"Wanggezhuang",
    "gn:population":0,
    "gn:timezone":"Asia/Shanghai",
    "iso:country":"CN",
    "name:zho_x_preferred":[
        "\u738b\u5404\u5e84"
    ],
    "name:zho_x_variant":[
        "\u738b\u683c\u5e84\u9547"
    ],
    "wof:name":"Wanggezhuang",
    "wof:placetype":"locality"
},
  "geometry": {"coordinates":[116.72490999999999,39.69912],"type":"Point"}
}