{
  "type": "Feature",
  "properties": {
    "gn:country":"CN",
    "gn:fcode":"PPL",
    "gn:population":74725,
    "iso:country":"CN",
    "name:cat_x_preferred":[
        "Yanggu"
    ],
    "name:ceb_x_preferred":[
        "Yanggu Xian"
    ],
    "name:deu_x_preferred":[
        "Yanggu"
    ],
    "name:eng_x_preferred":[
        "Yanggu County"
    ],
    "name:fas_x_preferred":[
        "\u06cc\u0627\u0646\u06af\u0648"
    ],
    "name:gan_x_preferred":[
        "\u9633\u8c37\u53bf"
    ],
    "name:jpn_x_preferred":[
        "\u967d\u8c37\u770c"
    ],
    "name:kor_x_preferred":[
        "\uc591\uad6c\ud604"
    ],
    "name:nan_x_preferred":[
        "I\u00f4ng-kok-ko\u0101n"
    ],
    "name:nld_x_preferred":[
        "Yanggu"
    ],
    "name:nob_x_preferred":[
        "Yanggu"
    ],
    "name:rus_x_preferred":[
        "\u042f\u043d\u0433"
    ],
    "name:rus_x_variant":[
        "\u042f\u043d\u0433\u0443"
    ],
    "name:swe_x_preferred":[
        "Yanggu"
    ],
    "name:und_x_variant":[
        "Yang-ku"
    ],
    "name:urd_x_preferred":[
        "\u06cc\u0646\u06af\u06af\u0648 \u06a9\u0627\u0624\u0646\u0679\u06cc"
    ],
    "name:vie_x_preferred":[
        "D\u01b0\u01a1ng C\u1ed1c"
    ],
    "name:wuu_x_preferred":[
        "\u9633\u8c37\u53bf"
    ],
    "name:yue_x_preferred":[
        "\u967d\u7a40"
    ],
    "name:zho_x_preferred":[
        "\u9633\u8c37\u53bf"
    ],
    "qs:name":"\u9633\u8c37",
    "qs:name_adm0":"\u4e2d\u570b",
    "qs:name_adm1":"\u5c71\u4e1c\u7701",
    "qs:photos_9r":0,
    "qs:photos_sr":0,
    "qs:placetype":"Town",
    "qs:pop_sr":"8",
    "wd:wordcount":71,
    "wof:name":"\u9633\u8c37",
    "wof:placetype":"locality",
    "wof:population":74725
},
  "geometry": {"coordinates":[115.77528,36.11056],"type":"Point"}
}