{
  "type": "Feature",
  "properties": {
    "gn:country":"CN",
    "gn:fcode":"PPL",
    "gn:pop":74725,
    "iso:country":"CN",
    "name:rus_x_preferred":[
        "\u042f\u043d\u0433"
    ],
    "name:unk_x_variant":[
        "Yang-ku"
    ],
    "qs:name":"\u9633\u8c37",
    "qs:name_adm0":"\u4e2d\u570b",
    "qs:name_adm1":"\u5c71\u4e1c\u7701",
    "qs:photos_9r":0,
    "qs:photos_sr":0,
    "qs:placetype":"Town",
    "qs:pop_sr":"8",
    "wd:wordcount":71,
    "wof:name":"\u9633\u8c37",
    "wof:placetype":"locality",
    "wof:population":74725
},
  "geometry": {"coordinates":[115.77528,36.11056],"type":"Point"}
}