{
  "type": "Feature",
  "properties": {
    "gn:admin1_code":"13.0",
    "gn:asciiname":"Sanshichang",
    "gn:cc2":"CN",
    "gn:country_code":"CN",
    "gn:dem":366,
    "gn:feature_class":"P",
    "gn:feature_code":"PPL",
    "gn:name":"Sanshichang",
    "gn:population":0,
    "gn:timezone":"Asia/Urumqi",
    "iso:country":"CN",
    "name:und_x_variant":[
        "San-shih-ch\u2019ang",
        "Sanshichang"
    ],
    "wof:name":"Sanshichang",
    "wof:placetype":"locality"
},
  "geometry": {"coordinates":[86.34999999999999,44.73333],"type":"Point"}
}