{
  "type": "Feature",
  "properties": {
    "gn:admin1_code":"29.0",
    "gn:asciiname":"Banchengshang",
    "gn:country_code":"CN",
    "gn:dem":1850,
    "gn:feature_class":"P",
    "gn:feature_code":"PPL",
    "gn:name":"Banchengshang",
    "gn:population":0,
    "gn:timezone":"Asia/Shanghai",
    "iso:country":"CN",
    "name:zho_x_preferred":[
        "\u677f\u6a59\u4e0a"
    ],
    "wof:name":"Banchengshang",
    "wof:placetype":"locality"
},
  "geometry": {"coordinates":[104.577,25.313],"type":"Point"}
}