{
  "type": "Feature",
  "properties": {
    "gn:admin1_code":"14.0",
    "gn:asciiname":"Xinben",
    "gn:country_code":"CN",
    "gn:dem":3979,
    "gn:feature_class":"P",
    "gn:feature_code":"PPL",
    "gn:name":"Xinben",
    "gn:population":0,
    "gn:timezone":"Asia/Urumqi",
    "iso:country":"CN",
    "name:zho_x_preferred":[
        "\u4fe1\u672c"
    ],
    "wof:name":"Xinben",
    "wof:placetype":"locality"
},
  "geometry": {"coordinates":[96.08034000000001,30.42786],"type":"Point"}
}