{
  "type": "Feature",
  "properties": {
    "gn:admin1_code":"19",
    "gn:asciiname":"Yingyinggou",
    "gn:country_code":"CN",
    "gn:dem":347,
    "gn:feature_class":"P",
    "gn:feature_code":"PPL",
    "gn:name":"Yingyinggou",
    "gn:population":0,
    "gn:timezone":"Asia/Shanghai",
    "iso:country":"CN",
    "wof:name":"Yingyinggou",
    "wof:placetype":"locality"
},
  "geometry": {"coordinates":[125.52722,41.37],"type":"Point"}
}