{
  "type": "Feature",
  "properties": {
    "gn:admin1_code":"29.0",
    "gn:asciiname":"Xitaqu",
    "gn:country_code":"CN",
    "gn:dem":2366,
    "gn:feature_class":"P",
    "gn:feature_code":"PPL",
    "gn:name":"Xitaqu",
    "gn:population":0,
    "gn:timezone":"Asia/Shanghai",
    "iso:country":"CN",
    "name:zho_x_preferred":[
        "\u897f\u5854\u66f2"
    ],
    "wof:name":"Xitaqu",
    "wof:placetype":"locality"
},
  "geometry": {"coordinates":[99.62609999999999,26.4451],"type":"Point"}
}