{
  "type": "Feature",
  "properties": {
    "gn:admin1_code":"12.0",
    "gn:asciiname":"Dongliuhe",
    "gn:country_code":"CN",
    "gn:dem":77,
    "gn:feature_class":"P",
    "gn:feature_code":"PPL",
    "gn:name":"Dongliuhe",
    "gn:population":0,
    "gn:timezone":"Asia/Shanghai",
    "iso:country":"CN",
    "name:zho_x_preferred":[
        "\u4e1c\u6d41\u6cb3"
    ],
    "wof:name":"Dongliuhe",
    "wof:placetype":"locality"
},
  "geometry": {"coordinates":[114.67337000000001,31.42346],"type":"Point"}
}