{
  "type": "Feature",
  "properties": {
    "gn:admin1_code":"32.0",
    "gn:asciiname":"Cizhu",
    "gn:country_code":"CN",
    "gn:dem":631,
    "gn:feature_class":"P",
    "gn:feature_code":"PPL",
    "gn:name":"Cizhu",
    "gn:population":0,
    "gn:timezone":"Asia/Shanghai",
    "iso:country":"CN",
    "name:zho_x_preferred":[
        "\u8328\u7af9"
    ],
    "wof:name":"Cizhu",
    "wof:placetype":"locality"
},
  "geometry": {"coordinates":[103.63694,29.15783],"type":"Point"}
}