{
  "type": "Feature",
  "properties": {
    "gn:admin1_code":"2.0",
    "gn:asciiname":"Dama",
    "gn:country_code":"CN",
    "gn:dem":62,
    "gn:feature_class":"P",
    "gn:feature_code":"PPL",
    "gn:name":"Dama",
    "gn:population":0,
    "gn:timezone":"Asia/Shanghai",
    "iso:country":"CN",
    "name:und_x_variant":[
        "\u5927\u9a6c"
    ],
    "wof:name":"Dama",
    "wof:placetype":"locality"
},
  "geometry": {"coordinates":[119.69377,30.28304],"type":"Point"}
}