{
  "type": "Feature",
  "properties": {
    "gn:admin1_code":"1.0",
    "gn:asciiname":"Shixiangcun",
    "gn:country_code":"CN",
    "gn:dem":62,
    "gn:feature_class":"P",
    "gn:feature_code":"PPL",
    "gn:name":"Shixiangcun",
    "gn:population":0,
    "gn:timezone":"Asia/Shanghai",
    "iso:country":"CN",
    "name:zho_x_preferred":[
        "\u72ee\u8c61\u6751"
    ],
    "wof:name":"Shixiangcun",
    "wof:placetype":"locality"
},
  "geometry": {"coordinates":[116.84717999999999,31.00562],"type":"Point"}
}