{
  "type": "Feature",
  "properties": {
    "gn:admin1_code":"8.0",
    "gn:asciiname":"Hamatang",
    "gn:country_code":"CN",
    "gn:dem":614,
    "gn:feature_class":"P",
    "gn:feature_code":"PPL",
    "gn:name":"Hamatang",
    "gn:population":0,
    "gn:timezone":"Asia/Shanghai",
    "iso:country":"CN",
    "name:zho_x_preferred":[
        "\u54c8\u87c6\u5858"
    ],
    "wof:name":"Hamatang",
    "wof:placetype":"locality"
},
  "geometry": {"coordinates":[128.69396,44.26],"type":"Point"}
}