{
  "type": "Feature",
  "properties": {
    "gn:admin1_code":"2.0",
    "gn:asciiname":"Tianshidian",
    "gn:country_code":"CN",
    "gn:dem":1119,
    "gn:feature_class":"P",
    "gn:feature_code":"PPL",
    "gn:name":"Tianshidian",
    "gn:population":0,
    "gn:timezone":"Asia/Shanghai",
    "iso:country":"CN",
    "name:zho_x_preferred":[
        "\u5929\u5e08\u6bbf"
    ],
    "wof:name":"Tianshidian",
    "wof:placetype":"locality"
},
  "geometry": {"coordinates":[119.74768,28.23304000000001],"type":"Point"}
}