{
  "type": "Feature",
  "properties": {
    "gn:admin1_code":"29.0",
    "gn:asciiname":"Dadang",
    "gn:country_code":"CN",
    "gn:dem":1778,
    "gn:feature_class":"P",
    "gn:feature_code":"PPL",
    "gn:name":"Dadang",
    "gn:population":0,
    "gn:timezone":"Asia/Shanghai",
    "iso:country":"CN",
    "name:zho_x_preferred":[
        "\u6253\u5f53"
    ],
    "wof:name":"Dadang",
    "wof:placetype":"locality"
},
  "geometry": {"coordinates":[102.116,23.3694],"type":"Point"}
}