{
  "type": "Feature",
  "properties": {
    "gn:admin1_code":"18.0",
    "gn:asciiname":"Shanglang",
    "gn:country_code":"CN",
    "gn:dem":918,
    "gn:feature_class":"P",
    "gn:feature_code":"PPL",
    "gn:name":"Shanglang",
    "gn:population":0,
    "gn:timezone":"Asia/Shanghai",
    "iso:country":"CN",
    "name:zho_x_preferred":[
        "\u8d4f\u90ce"
    ],
    "wof:name":"Shanglang",
    "wof:placetype":"locality"
},
  "geometry": {"coordinates":[108.059,26.6128],"type":"Point"}
}