{
  "type": "Feature",
  "properties": {
    "gn:admin1_code":"10",
    "gn:asciiname":"Zhongwula Hada",
    "gn:country_code":"CN",
    "gn:dem":1128,
    "gn:feature_class":"P",
    "gn:feature_code":"PPL",
    "gn:name":"Zhongwula Hada",
    "gn:population":0,
    "gn:timezone":"Asia/Shanghai",
    "iso:country":"CN",
    "name:zho_x_preferred":[
        "\u4e2d\u4e4c\u62c9\u54c8\u8fbe"
    ],
    "wof:name":"Zhongwula Hada",
    "wof:placetype":"locality"
},
  "geometry": {"coordinates":[114.23033,40.93651],"type":"Point"}
}