{
  "type": "Feature",
  "properties": {
    "gn:admin1_code":"18",
    "gn:asciiname":"Xiaochangba",
    "gn:country_code":"CN",
    "gn:dem":1187,
    "gn:feature_class":"P",
    "gn:feature_code":"PPL",
    "gn:name":"Xiaochangba",
    "gn:population":0,
    "gn:timezone":"Asia/Shanghai",
    "iso:country":"CN",
    "name:zho_x_preferred":[
        "\u5c0f\u573a\u575d"
    ],
    "wof:name":"Xiaochangba",
    "wof:placetype":"locality"
},
  "geometry": {"coordinates":[105.16800000000001,25.0979],"type":"Point"}
}