{
  "type": "Feature",
  "properties": {
    "gn:admin1_code":"26.0",
    "gn:asciiname":"Wulipu",
    "gn:country_code":"CN",
    "gn:dem":797,
    "gn:feature_class":"P",
    "gn:feature_code":"PPL",
    "gn:name":"Wulipu",
    "gn:population":0,
    "gn:timezone":"Asia/Shanghai",
    "iso:country":"CN",
    "name:und_x_variant":[
        "\u4e94\u91cc\u94fa"
    ],
    "name:zho_x_preferred":[
        "\u4e94\u91cc\u94fa\u9547"
    ],
    "wof:name":"Wulipu",
    "wof:placetype":"locality"
},
  "geometry": {"coordinates":[107.00346,33.50414],"type":"Point"}
}