{
  "type": "Feature",
  "properties": {
    "gn:admin1_code":"30",
    "gn:asciiname":"Bengxi",
    "gn:cc2":"CN",
    "gn:country_code":"CN",
    "gn:dem":31,
    "gn:feature_class":"P",
    "gn:feature_code":"PPL",
    "gn:name":"Bengxi",
    "gn:population":0,
    "gn:timezone":"Asia/Urumqi",
    "iso:country":"CN",
    "name:zho_x_preferred":[
        "Peng-ch\u2019i"
    ],
    "wof:name":"Bengxi",
    "wof:placetype":"locality"
},
  "geometry": {"coordinates":[109.80694,21.01083],"type":"Point"}
}