{
  "type": "Feature",
  "properties": {
    "gn:admin1_code":"26.0",
    "gn:asciiname":"Nanyaoxian",
    "gn:country_code":"CN",
    "gn:dem":1362,
    "gn:feature_class":"P",
    "gn:feature_code":"PPL",
    "gn:name":"Nanyaoxian",
    "gn:population":0,
    "gn:timezone":"Asia/Shanghai",
    "iso:country":"CN",
    "name:zho_x_preferred":[
        "\u5357\u5d3e\u5c98"
    ],
    "wof:name":"Nanyaoxian",
    "wof:placetype":"locality"
},
  "geometry": {"coordinates":[108.98445,36.87183],"type":"Point"}
}