{
  "type": "Feature",
  "properties": {
    "gn:admin1_code":"30.0",
    "gn:asciiname":"Tutang",
    "gn:country_code":"CN",
    "gn:dem":11,
    "gn:feature_class":"P",
    "gn:feature_code":"PPL",
    "gn:name":"Tutang",
    "gn:population":0,
    "gn:timezone":"Asia/Shanghai",
    "iso:country":"CN",
    "name:ara_x_preferred":[
        "\u062a\u0648 \u062a\u0646\u063a"
    ],
    "name:ceb_x_preferred":[
        "T\u016btang"
    ],
    "name:fas_x_preferred":[
        "\u062a\u0648\u062a\u0646\u06af"
    ],
    "name:msa_x_preferred":[
        "Tutang"
    ],
    "name:swe_x_preferred":[
        "T\u016btang"
    ],
    "name:urd_x_preferred":[
        "\u062a\u0648\u062a\u0646\u06af"
    ],
    "name:zho_x_preferred":[
        "\u571f\u5858"
    ],
    "wof:name":"Tutang",
    "wof:placetype":"locality"
},
  "geometry": {"coordinates":[114.02401999999999,22.96075],"type":"Point"}
}