{
  "type": "Feature",
  "properties": {
    "gn:admin1_code":"16.0",
    "gn:asciiname":"Zudi",
    "gn:country_code":"CN",
    "gn:dem":703,
    "gn:feature_class":"P",
    "gn:feature_code":"PPL",
    "gn:name":"Zudi",
    "gn:population":0,
    "gn:timezone":"Asia/Shanghai",
    "iso:country":"CN",
    "name:zho_x_preferred":[
        "\u8db3\u8fea"
    ],
    "wof:name":"Zudi",
    "wof:placetype":"locality"
},
  "geometry": {"coordinates":[106.56100000000001,23.3876],"type":"Point"}
}