{
  "type": "Feature",
  "properties": {
    "gn:admin1_code":"5.0",
    "gn:asciiname":"Wujia Tuozicun",
    "gn:country_code":"CN",
    "gn:dem":116,
    "gn:feature_class":"P",
    "gn:feature_code":"PPL",
    "gn:name":"Wujia Tuozicun",
    "gn:population":0,
    "gn:timezone":"Asia/Shanghai",
    "iso:country":"CN",
    "name:zho_x_preferred":[
        "\u5434\u5bb6\u5768\u5b50\u6751"
    ],
    "wof:name":"Wujia Tuozicun",
    "wof:placetype":"locality"
},
  "geometry": {"coordinates":[123.79937,43.52556],"type":"Point"}
}