{
  "type": "Feature",
  "properties": {
    "gn:admin1_code":"19.0",
    "gn:asciiname":"Xiabuzi",
    "gn:country_code":"CN",
    "gn:dem":10,
    "gn:feature_class":"P",
    "gn:feature_code":"PPL",
    "gn:name":"Xiabuzi",
    "gn:population":0,
    "gn:timezone":"Asia/Shanghai",
    "iso:country":"CN",
    "name:und_x_variant":[
        "Xiapuzi",
        "\u4e0b\u5821\u5b50",
        "Xiabuzi"
    ],
    "wof:name":"Xiabuzi",
    "wof:placetype":"locality"
},
  "geometry": {"coordinates":[122.50179,40.9007],"type":"Point"}
}