{
  "type": "Feature",
  "properties": {
    "gn:admin1_code":"11.0",
    "gn:asciiname":"Wuma Pocao",
    "gn:country_code":"CN",
    "gn:dem":1405,
    "gn:feature_class":"P",
    "gn:feature_code":"PPL",
    "gn:name":"Wuma Pocao",
    "gn:population":0,
    "gn:timezone":"Asia/Shanghai",
    "iso:country":"CN",
    "name:zho_x_preferred":[
        "\u4e94\u9a6c\u7834\u69fd"
    ],
    "wof:name":"Wuma Pocao",
    "wof:placetype":"locality"
},
  "geometry": {"coordinates":[110.82116000000001,27.67257],"type":"Point"}
}