{
  "type": "Feature",
  "properties": {
    "gn:admin1_code":"29.0",
    "gn:asciiname":"Mitie",
    "gn:country_code":"CN",
    "gn:dem":1481,
    "gn:feature_class":"P",
    "gn:feature_code":"PPL",
    "gn:name":"Mitie",
    "gn:population":0,
    "gn:timezone":"Asia/Shanghai",
    "iso:country":"CN",
    "name:und_x_variant":[
        "\u7c73\u8d34"
    ],
    "wof:name":"Mitie",
    "wof:placetype":"locality"
},
  "geometry": {"coordinates":[103.52894999999999,28.04623],"type":"Point"}
}