{
  "type": "Feature",
  "properties": {
    "gn:admin1_code":"3.0",
    "gn:asciiname":"Henglongbei",
    "gn:country_code":"CN",
    "gn:dem":165,
    "gn:feature_class":"P",
    "gn:feature_code":"PPL",
    "gn:name":"Henglongbei",
    "gn:population":0,
    "gn:timezone":"Asia/Shanghai",
    "iso:country":"CN",
    "name:und_x_variant":[
        "\u6a2a\u9f99\u80cc"
    ],
    "wof:name":"Henglongbei",
    "wof:placetype":"locality"
},
  "geometry": {"coordinates":[114.79572,28.07364],"type":"Point"}
}