{
  "type": "Feature",
  "properties": {
    "gn:admin1_code":"26.0",
    "gn:asciiname":"Xiahedui",
    "gn:country_code":"CN",
    "gn:dem":1057,
    "gn:feature_class":"P",
    "gn:feature_code":"PPL",
    "gn:name":"Xiahedui",
    "gn:population":0,
    "gn:timezone":"Asia/Shanghai",
    "iso:country":"CN",
    "name:zho_x_preferred":[
        "\u4e0b\u5408\u5151"
    ],
    "wof:name":"Xiahedui",
    "wof:placetype":"locality"
},
  "geometry": {"coordinates":[110.31775,36.13002],"type":"Point"}
}