{
  "type": "Feature",
  "properties": {
    "gn:admin1_code":"12.0",
    "gn:asciiname":"Dingzijie",
    "gn:country_code":"CN",
    "gn:dem":14,
    "gn:feature_class":"P",
    "gn:feature_code":"PPL",
    "gn:name":"Dingzijie",
    "gn:population":0,
    "gn:timezone":"Asia/Shanghai",
    "iso:country":"CN",
    "name:zho_x_preferred":[
        "\u4e01\u5b57\u8857"
    ],
    "wof:name":"Dingzijie",
    "wof:placetype":"locality"
},
  "geometry": {"coordinates":[115.87184000000001,29.9869],"type":"Point"}
}