{
  "type": "Feature",
  "properties": {
    "gn:admin1_code":"3.0",
    "gn:asciiname":"Dalingbei",
    "gn:country_code":"CN",
    "gn:dem":259,
    "gn:feature_class":"P",
    "gn:feature_code":"PPL",
    "gn:name":"Dalingbei",
    "gn:population":0,
    "gn:timezone":"Asia/Shanghai",
    "iso:country":"CN",
    "name:und_x_variant":[
        "\u5927\u5cad\u80cc"
    ],
    "wof:name":"Dalingbei",
    "wof:placetype":"locality"
},
  "geometry": {"coordinates":[115.83065000000001,26.30447],"type":"Point"}
}