{
  "type": "Feature",
  "properties": {
    "gn:admin1_code":"5.0",
    "gn:asciiname":"Xiwatonggou",
    "gn:country_code":"CN",
    "gn:dem":215,
    "gn:feature_class":"P",
    "gn:feature_code":"PPL",
    "gn:name":"Xiwatonggou",
    "gn:population":0,
    "gn:timezone":"Asia/Shanghai",
    "iso:country":"CN",
    "name:zho_x_preferred":[
        "\u897f\u6316\u94dc\u6c9f"
    ],
    "wof:name":"Xiwatonggou",
    "wof:placetype":"locality"
},
  "geometry": {"coordinates":[125.65902,44.14805],"type":"Point"}
}