{
  "type": "Feature",
  "properties": {
    "gn:admin1_code":"01",
    "gn:asciiname":"Caishi",
    "gn:country_code":"CN",
    "gn:dem":7,
    "gn:feature_class":"P",
    "gn:feature_code":"PPLA4",
    "gn:name":"Caishi",
    "gn:population":0,
    "gn:timezone":"Asia/Shanghai",
    "iso:country":"CN",
    "name:eng_x_historical":[
        "Tsai Shih"
    ],
    "name:eng_x_preferred":[
        "Tsai Shih"
    ],
    "name:und_x_variant":[
        "Ts\u2019ai-shih-chen",
        "Ts\u2019ai-shih",
        "Caishi Jiedao",
        "\u91c7\u77f3\u8857\u9053",
        "Caishi"
    ],
    "wof:name":"Caishi",
    "wof:placetype":"locality"
},
  "geometry": {"coordinates":[118.46189,31.64842],"type":"Point"}
}