{
  "type": "Feature",
  "properties": {
    "gn:admin1_code":"4.0",
    "gn:asciiname":"Jiudadui",
    "gn:country_code":"CN",
    "gn:dem":3,
    "gn:feature_class":"P",
    "gn:feature_code":"PPLF",
    "gn:name":"Jiudadui",
    "gn:population":0,
    "gn:timezone":"Asia/Shanghai",
    "iso:country":"CN",
    "name:und_x_variant":[
        "\u4e5d\u5927\u961f"
    ],
    "wof:name":"Jiudadui",
    "wof:placetype":"locality"
},
  "geometry": {"coordinates":[120.70954,32.99498],"type":"Point"}
}