{
  "type": "Feature",
  "properties": {
    "gn:admin1_code":"14.0",
    "gn:asciiname":"Jiaxiao",
    "gn:country_code":"CN",
    "gn:dem":4790,
    "gn:feature_class":"P",
    "gn:feature_code":"PPL",
    "gn:name":"Jiaxiao",
    "gn:population":0,
    "gn:timezone":"Asia/Urumqi",
    "iso:country":"CN",
    "name:zho_x_preferred":[
        "\u52a0\u9500"
    ],
    "wof:name":"Jiaxiao",
    "wof:placetype":"locality"
},
  "geometry": {"coordinates":[93.27731,30.0448],"type":"Point"}
}