{
  "type": "Feature",
  "properties": {
    "gn:admin1_code":"16.0",
    "gn:asciiname":"Shuangmatang",
    "gn:country_code":"CN",
    "gn:dem":320,
    "gn:feature_class":"P",
    "gn:feature_code":"PPL",
    "gn:name":"Shuangmatang",
    "gn:population":0,
    "gn:timezone":"Asia/Shanghai",
    "iso:country":"CN",
    "name:zho_x_preferred":[
        "\u53cc\u9a6c\u5858"
    ],
    "wof:name":"Shuangmatang",
    "wof:placetype":"locality"
},
  "geometry": {"coordinates":[111.40600000000001,24.9543],"type":"Point"}
}