{
  "type": "Feature",
  "properties": {
    "gn:admin1_code":"9.0",
    "gn:asciiname":"Dazhaozhuang",
    "gn:country_code":"CN",
    "gn:dem":42,
    "gn:feature_class":"P",
    "gn:feature_code":"PPL",
    "gn:name":"Dazhaozhuang",
    "gn:population":0,
    "gn:timezone":"Asia/Shanghai",
    "iso:country":"CN",
    "name:zho_x_preferred":[
        "\u5927\u8d75\u5e84"
    ],
    "wof:name":"Dazhaozhuang",
    "wof:placetype":"locality"
},
  "geometry": {"coordinates":[114.67852000000001,32.70381],"type":"Point"}
}