{
  "type": "Feature",
  "properties": {
    "gn:admin1_code":"11.0",
    "gn:asciiname":"Guchangchong",
    "gn:country_code":"CN",
    "gn:dem":436,
    "gn:feature_class":"P",
    "gn:feature_code":"PPL",
    "gn:name":"Guchangchong",
    "gn:population":0,
    "gn:timezone":"Asia/Shanghai",
    "iso:country":"CN",
    "name:zho_x_preferred":[
        "\u53e4\u957f\u51b2"
    ],
    "wof:name":"Guchangchong",
    "wof:placetype":"locality"
},
  "geometry": {"coordinates":[110.02285999999999,26.47633],"type":"Point"}
}