{
  "type": "Feature",
  "properties": {
    "gn:admin1_code":"19.0",
    "gn:asciiname":"Dongchangtai",
    "gn:country_code":"CN",
    "gn:dem":383,
    "gn:feature_class":"P",
    "gn:feature_code":"PPL",
    "gn:name":"Dongchangtai",
    "gn:population":0,
    "gn:timezone":"Asia/Shanghai",
    "iso:country":"CN",
    "name:zho_x_preferred":[
        "\u4e1c\u660c\u53f0"
    ],
    "wof:name":"Dongchangtai",
    "wof:placetype":"locality"
},
  "geometry": {"coordinates":[125.169,41.6945],"type":"Point"}
}