{
  "type": "Feature",
  "properties": {
    "gn:admin1_code":"29.0",
    "gn:asciiname":"Qiutun",
    "gn:country_code":"CN",
    "gn:dem":1981,
    "gn:feature_class":"P",
    "gn:feature_code":"PPL",
    "gn:name":"Qiutun",
    "gn:population":0,
    "gn:timezone":"Asia/Shanghai",
    "iso:country":"CN",
    "name:zho_x_preferred":[
        "\u4e18\u5c6f"
    ],
    "wof:name":"Qiutun",
    "wof:placetype":"locality"
},
  "geometry": {"coordinates":[104.086,26.0775],"type":"Point"}
}