{
  "type": "Feature",
  "properties": {
    "gn:admin1_code":"29.0",
    "gn:asciiname":"Anxincao",
    "gn:country_code":"CN",
    "gn:dem":1829,
    "gn:feature_class":"P",
    "gn:feature_code":"PPL",
    "gn:name":"Anxincao",
    "gn:population":0,
    "gn:timezone":"Asia/Shanghai",
    "iso:country":"CN",
    "name:zho_x_preferred":[
        "\u5b89\u4fe1\u69fd"
    ],
    "wof:name":"Anxincao",
    "wof:placetype":"locality"
},
  "geometry": {"coordinates":[99.49379999999999,23.9819],"type":"Point"}
}