{
  "type": "Feature",
  "properties": {
    "gn:admin1_code":"11.0",
    "gn:asciiname":"Xinpuli",
    "gn:country_code":"CN",
    "gn:dem":149,
    "gn:feature_class":"P",
    "gn:feature_code":"PPL",
    "gn:name":"Xinpuli",
    "gn:population":0,
    "gn:timezone":"Asia/Shanghai",
    "iso:country":"CN",
    "name:zho_x_preferred":[
        "\u65b0\u94fa\u91cc"
    ],
    "wof:name":"Xinpuli",
    "wof:placetype":"locality"
},
  "geometry": {"coordinates":[113.17973000000001,26.33994],"type":"Point"}
}