{
  "type": "Feature",
  "properties": {
    "gn:admin1_code":"19",
    "gn:asciiname":"Xintaizi",
    "gn:cc2":"CN",
    "gn:country_code":"CN",
    "gn:dem":60,
    "gn:feature_class":"P",
    "gn:feature_code":"PPL",
    "gn:name":"Xintaizi",
    "gn:population":0,
    "gn:timezone":"Asia/Shanghai",
    "iso:country":"CN",
    "name:und_x_variant":[
        "Hsin-t\u2019ai-tzu",
        "Xintaizi"
    ],
    "wof:name":"Xintaizi",
    "wof:placetype":"locality"
},
  "geometry": {"coordinates":[123.59999999999999,42.11667],"type":"Point"}
}