{
  "type": "Feature",
  "properties": {
    "gn:admin1_code":"02",
    "gn:asciiname":"Lubu",
    "gn:country_code":"CN",
    "gn:dem":9,
    "gn:feature_class":"P",
    "gn:feature_code":"PPLA4",
    "gn:name":"Lubu",
    "gn:population":0,
    "gn:timezone":"Asia/Shanghai",
    "iso:country":"CN",
    "name:und_x_variant":[
        "Lujiabu",
        "Lu-chia-pu",
        "Lubu",
        "Lubu Zhen",
        "\u9646\u57e0\u9547"
    ],
    "name:zho_x_preferred":[
        "\u9646\u57e0"
    ],
    "name:zho_x_variant":[
        "\u9646\u57e0\u9547"
    ],
    "wof:name":"Lubu",
    "wof:placetype":"locality"
},
  "geometry": {"coordinates":[121.23033999999998,29.99052],"type":"Point"}
}