{
  "type": "Feature",
  "properties": {
    "gn:admin1_code":"30.0",
    "gn:asciiname":"Dongtou",
    "gn:country_code":"CN",
    "gn:dem":52,
    "gn:feature_class":"P",
    "gn:feature_code":"PPL",
    "gn:name":"Dongtou",
    "gn:population":0,
    "gn:timezone":"Asia/Shanghai",
    "iso:country":"CN",
    "name:zho_x_preferred":[
        "\u578c\u5934"
    ],
    "wof:name":"Dongtou",
    "wof:placetype":"locality"
},
  "geometry": {"coordinates":[112.53673000000001,22.02693],"type":"Point"}
}