{
  "type": "Feature",
  "properties": {
    "gn:admin1_code":"29.0",
    "gn:asciiname":"Yankoujiao",
    "gn:country_code":"CN",
    "gn:dem":1238,
    "gn:feature_class":"P",
    "gn:feature_code":"PPL",
    "gn:name":"Yankoujiao",
    "gn:population":0,
    "gn:timezone":"Asia/Shanghai",
    "iso:country":"CN",
    "name:zho_x_preferred":[
        "\u5ca9\u53e3\u811a"
    ],
    "wof:name":"Yankoujiao",
    "wof:placetype":"locality"
},
  "geometry": {"coordinates":[98.9328,23.9686],"type":"Point"}
}