{
  "type": "Feature",
  "properties": {
    "gn:admin1_code":"32.0",
    "gn:asciiname":"Muyi",
    "gn:country_code":"CN",
    "gn:dem":2798,
    "gn:feature_class":"P",
    "gn:feature_code":"PPL",
    "gn:name":"Muyi",
    "gn:population":0,
    "gn:timezone":"Asia/Shanghai",
    "iso:country":"CN",
    "name:zho_x_preferred":[
        "\u6728\u8863"
    ],
    "wof:name":"Muyi",
    "wof:placetype":"locality"
},
  "geometry": {"coordinates":[103.163,32.2039],"type":"Point"}
}