{
  "type": "Feature",
  "properties": {
    "gn:admin1_code":"26.0",
    "gn:asciiname":"Dangjiazhuang",
    "gn:country_code":"CN",
    "gn:dem":516,
    "gn:feature_class":"P",
    "gn:feature_code":"PPL",
    "gn:name":"Dangjiazhuang",
    "gn:population":0,
    "gn:timezone":"Asia/Shanghai",
    "iso:country":"CN",
    "name:zho_x_preferred":[
        "\u515a\u5bb6\u5e84"
    ],
    "wof:name":"Dangjiazhuang",
    "wof:placetype":"locality"
},
  "geometry": {"coordinates":[110.08016000000001,35.01675],"type":"Point"}
}