{
  "type": "Feature",
  "properties": {
    "gn:admin1_code":"26.0",
    "gn:asciiname":"Houdujia Goucun",
    "gn:country_code":"CN",
    "gn:dem":1111,
    "gn:feature_class":"P",
    "gn:feature_code":"PPL",
    "gn:name":"Houdujia Goucun",
    "gn:population":0,
    "gn:timezone":"Asia/Shanghai",
    "iso:country":"CN",
    "name:zho_x_preferred":[
        "\u540e\u675c\u5bb6\u6c9f\u6751"
    ],
    "wof:name":"Houdujia Goucun",
    "wof:placetype":"locality"
},
  "geometry": {"coordinates":[110.20099999999999,38.4278],"type":"Point"}
}