{
  "type": "Feature",
  "properties": {
    "gn:admin1_code":"18",
    "gn:asciiname":"Mowo",
    "gn:country_code":"CN",
    "gn:dem":1064,
    "gn:feature_class":"P",
    "gn:feature_code":"PPL",
    "gn:name":"Mowo",
    "gn:population":0,
    "gn:timezone":"Asia/Shanghai",
    "iso:country":"CN",
    "name:zho_x_preferred":[
        "\u78e8\u7a9d"
    ],
    "wof:name":"Mowo",
    "wof:placetype":"locality"
},
  "geometry": {"coordinates":[106.81699999999999,25.7553],"type":"Point"}
}