{
  "type": "Feature",
  "properties": {
    "gn:admin1_code":"1.0",
    "gn:asciiname":"Zhouliucun",
    "gn:country_code":"CN",
    "gn:dem":33,
    "gn:feature_class":"P",
    "gn:feature_code":"PPL",
    "gn:name":"Zhouliucun",
    "gn:population":0,
    "gn:timezone":"Asia/Shanghai",
    "iso:country":"CN",
    "name:zho_x_preferred":[
        "\u5468\u5218\u6751"
    ],
    "wof:name":"Zhouliucun",
    "wof:placetype":"locality"
},
  "geometry": {"coordinates":[115.84911,33.49333],"type":"Point"}
}