{
  "type": "Feature",
  "properties": {
    "gn:admin1_code":"12",
    "gn:asciiname":"Baojialou",
    "gn:country_code":"CN",
    "gn:dem":99,
    "gn:feature_class":"P",
    "gn:feature_code":"PPL",
    "gn:name":"Baojialou",
    "gn:population":0,
    "gn:timezone":"Asia/Shanghai",
    "iso:country":"CN",
    "name:und_x_variant":[
        "\u9c8d\u5bb6\u697c"
    ],
    "wof:name":"Baojialou",
    "wof:placetype":"locality"
},
  "geometry": {"coordinates":[115.15649999999999,30.9671],"type":"Point"}
}