{
  "type": "Feature",
  "properties": {
    "gn:admin1_code":"7",
    "gn:asciiname":"Tangnei",
    "gn:country_code":"CN",
    "gn:dem":179,
    "gn:feature_class":"P",
    "gn:feature_code":"PPL",
    "gn:name":"Tangnei",
    "gn:population":0,
    "gn:timezone":"Asia/Shanghai",
    "iso:country":"CN",
    "name:zho_x_preferred":[
        "\u6c64\u5185"
    ],
    "wof:name":"Tangnei",
    "wof:placetype":"locality"
},
  "geometry": {"coordinates":[117.87444000000001,24.84556],"type":"Point"}
}