{
  "type": "Feature",
  "properties": {
    "gn:admin1_code":"32.0",
    "gn:asciiname":"Dajue",
    "gn:country_code":"CN",
    "gn:dem":2296,
    "gn:feature_class":"P",
    "gn:feature_code":"PPL",
    "gn:name":"Dajue",
    "gn:population":0,
    "gn:timezone":"Asia/Shanghai",
    "iso:country":"CN",
    "name:zho_x_preferred":[
        "\u8fbe\u89c9"
    ],
    "wof:name":"Dajue",
    "wof:placetype":"locality"
},
  "geometry": {"coordinates":[103.354,28.0807],"type":"Point"}
}