{
  "type": "Feature",
  "properties": {
    "gn:admin1_code":"12.0",
    "gn:asciiname":"Jinshui",
    "gn:country_code":"CN",
    "gn:dem":48,
    "gn:feature_class":"P",
    "gn:feature_code":"PPL",
    "gn:name":"Jinshui",
    "gn:population":0,
    "gn:timezone":"Asia/Shanghai",
    "iso:country":"CN",
    "name:und_x_variant":[
        "\u91d1\u6c34"
    ],
    "name:zho_x_preferred":[
        "Jinshui"
    ],
    "wof:name":"Jinshui",
    "wof:placetype":"locality"
},
  "geometry": {"coordinates":[114.13253,30.3447],"type":"Point"}
}