{
  "type": "Feature",
  "properties": {
    "gn:admin1_code":"26.0",
    "gn:asciiname":"Jianwangcun",
    "gn:country_code":"CN",
    "gn:dem":380,
    "gn:feature_class":"P",
    "gn:feature_code":"PPL",
    "gn:name":"Jianwangcun",
    "gn:population":0,
    "gn:timezone":"Asia/Shanghai",
    "iso:country":"CN",
    "name:zho_x_preferred":[
        "\u7bad\u738b\u6751"
    ],
    "wof:name":"Jianwangcun",
    "wof:placetype":"locality"
},
  "geometry": {"coordinates":[109.21289,34.62725],"type":"Point"}
}