{
  "type": "Feature",
  "properties": {
    "gn:admin1_code":"33.0",
    "gn:asciiname":"Sanxi",
    "gn:country_code":"CN",
    "gn:dem":339,
    "gn:feature_class":"P",
    "gn:feature_code":"PPLA4",
    "gn:name":"Sanxi",
    "gn:population":0,
    "gn:timezone":"Asia/Shanghai",
    "iso:country":"CN",
    "name:und_x_variant":[
        "Sanxi Xiang"
    ],
    "name:zho_x_preferred":[
        "\u4e09\u6eaa"
    ],
    "name:zho_x_variant":[
        "\u4e09\u6eaa\u4e61"
    ],
    "wof:name":"Sanxi",
    "wof:placetype":"locality"
},
  "geometry": {"coordinates":[107.45359000000001,30.06387],"type":"Point"}
}