{
  "type": "Feature",
  "properties": {
    "gn:admin1_code":"29.0",
    "gn:asciiname":"Songshuzhai",
    "gn:country_code":"CN",
    "gn:dem":961,
    "gn:feature_class":"P",
    "gn:feature_code":"PPL",
    "gn:name":"Songshuzhai",
    "gn:population":0,
    "gn:timezone":"Asia/Shanghai",
    "iso:country":"CN",
    "name:zho_x_preferred":[
        "\u677e\u6811\u5be8"
    ],
    "wof:name":"Songshuzhai",
    "wof:placetype":"locality"
},
  "geometry": {"coordinates":[98.5994,24.44],"type":"Point"}
}