{
  "type": "Feature",
  "properties": {
    "gn:admin1_code":"15.0",
    "gn:asciiname":"Xieyangwan",
    "gn:country_code":"CN",
    "gn:dem":1562,
    "gn:feature_class":"P",
    "gn:feature_code":"PPL",
    "gn:name":"Xieyangwan",
    "gn:population":0,
    "gn:timezone":"Asia/Shanghai",
    "iso:country":"CN",
    "name:und_x_variant":[
        "\u8c22\u9633\u6e7e"
    ],
    "wof:name":"Xieyangwan",
    "wof:placetype":"locality"
},
  "geometry": {"coordinates":[106.97716,36.48168],"type":"Point"}
}