{
  "type": "Feature",
  "properties": {
    "gn:admin1_code":"19.0",
    "gn:asciiname":"Dashalitu",
    "gn:country_code":"CN",
    "gn:dem":113,
    "gn:feature_class":"P",
    "gn:feature_code":"PPL",
    "gn:name":"Dashalitu",
    "gn:population":0,
    "gn:timezone":"Asia/Shanghai",
    "iso:country":"CN",
    "name:und_x_variant":[
        "\u5927\u6c99\u529b\u571f"
    ],
    "name:zho_x_preferred":[
        "\u5927\u6c99\u529b\u571f"
    ],
    "wof:name":"Dashalitu",
    "wof:placetype":"locality"
},
  "geometry": {"coordinates":[122.51953,42.50389000000001],"type":"Point"}
}