{
  "type": "Feature",
  "properties": {
    "gn:admin1_code":"1.0",
    "gn:asciiname":"Liuyaocun",
    "gn:country_code":"CN",
    "gn:dem":43,
    "gn:feature_class":"P",
    "gn:feature_code":"PPL",
    "gn:name":"Liuyaocun",
    "gn:population":0,
    "gn:timezone":"Asia/Shanghai",
    "iso:country":"CN",
    "name:zho_x_preferred":[
        "\u5218\u5c27\u6751"
    ],
    "wof:name":"Liuyaocun",
    "wof:placetype":"locality"
},
  "geometry": {"coordinates":[115.09354999999999,32.93567],"type":"Point"}
}