{
  "type": "Feature",
  "properties": {
    "gn:admin1_code":"26.0",
    "gn:asciiname":"Xipotou",
    "gn:country_code":"CN",
    "gn:dem":1307,
    "gn:feature_class":"P",
    "gn:feature_code":"PPL",
    "gn:name":"Xipotou",
    "gn:population":0,
    "gn:timezone":"Asia/Shanghai",
    "iso:country":"CN",
    "name:zho_x_preferred":[
        "\u897f\u5761\u5934"
    ],
    "wof:name":"Xipotou",
    "wof:placetype":"locality"
},
  "geometry": {"coordinates":[108.73163999999998,35.08909],"type":"Point"}
}