{
  "type": "Feature",
  "properties": {
    "gn:admin1_code":"1.0",
    "gn:asciiname":"Changlongcun",
    "gn:country_code":"CN",
    "gn:dem":16,
    "gn:feature_class":"P",
    "gn:feature_code":"PPL",
    "gn:name":"Changlongcun",
    "gn:population":0,
    "gn:timezone":"Asia/Shanghai",
    "iso:country":"CN",
    "name:zho_x_preferred":[
        "\u957f\u9f99\u6751"
    ],
    "wof:name":"Changlongcun",
    "wof:placetype":"locality"
},
  "geometry": {"coordinates":[117.90743000000001,30.93189000000001],"type":"Point"}
}