{
  "type": "Feature",
  "properties": {
    "gn:admin1_code":"8.0",
    "gn:asciiname":"Dongtaipingcun",
    "gn:country_code":"CN",
    "gn:dem":173,
    "gn:feature_class":"P",
    "gn:feature_code":"PPL",
    "gn:name":"Dongtaipingcun",
    "gn:population":0,
    "gn:timezone":"Asia/Shanghai",
    "iso:country":"CN",
    "name:zho_x_preferred":[
        "\u4e1c\u592a\u5e73\u6751"
    ],
    "wof:name":"Dongtaipingcun",
    "wof:placetype":"locality"
},
  "geometry": {"coordinates":[125.0386,47.71283],"type":"Point"}
}