{
  "type": "Feature",
  "properties": {
    "gn:admin1_code":"10",
    "gn:asciiname":"Zhonggao",
    "gn:country_code":"CN",
    "gn:dem":52,
    "gn:feature_class":"P",
    "gn:feature_code":"PPL",
    "gn:name":"Zhonggao",
    "gn:population":0,
    "gn:timezone":"Asia/Shanghai",
    "iso:country":"CN",
    "name:zho_x_preferred":[
        "\u4e2d\u9ad8"
    ],
    "wof:name":"Zhonggao",
    "wof:placetype":"locality"
},
  "geometry": {"coordinates":[115.03187,36.2475],"type":"Point"}
}