{
  "type": "Feature",
  "properties": {
    "gn:admin1_code":"24.0",
    "gn:asciiname":"Baijiashancun",
    "gn:country_code":"CN",
    "gn:dem":739,
    "gn:feature_class":"P",
    "gn:feature_code":"PPL",
    "gn:name":"Baijiashancun",
    "gn:population":0,
    "gn:timezone":"Asia/Shanghai",
    "iso:country":"CN",
    "name:zho_x_preferred":[
        "\u767d\u5bb6\u5c71\u6751"
    ],
    "wof:name":"Baijiashancun",
    "wof:placetype":"locality"
},
  "geometry": {"coordinates":[110.71735,37.34864],"type":"Point"}
}