{
  "type": "Feature",
  "properties": {
    "gn:admin1_code":"8.0",
    "gn:asciiname":"Xianghuang Wucun",
    "gn:country_code":"CN",
    "gn:dem":149,
    "gn:feature_class":"P",
    "gn:feature_code":"PPL",
    "gn:name":"Xianghuang Wucun",
    "gn:population":0,
    "gn:timezone":"Asia/Shanghai",
    "iso:country":"CN",
    "name:zho_x_preferred":[
        "\u53a2\u9ec4\u4e94\u6751"
    ],
    "wof:name":"Xianghuang Wucun",
    "wof:placetype":"locality"
},
  "geometry": {"coordinates":[126.68808,46.56563],"type":"Point"}
}