{
  "type": "Feature",
  "properties": {
    "gn:admin1_code":"26.0",
    "gn:asciiname":"Xiangjialing",
    "gn:country_code":"CN",
    "gn:dem":764,
    "gn:feature_class":"P",
    "gn:feature_code":"PPL",
    "gn:name":"Xiangjialing",
    "gn:population":0,
    "gn:timezone":"Asia/Shanghai",
    "iso:country":"CN",
    "name:zho_x_preferred":[
        "\u5411\u5bb6\u5cad"
    ],
    "wof:name":"Xiangjialing",
    "wof:placetype":"locality"
},
  "geometry": {"coordinates":[109.58331,32.93781],"type":"Point"}
}