{
  "type": "Feature",
  "properties": {
    "gn:admin1_code":"29.0",
    "gn:asciiname":"Sajiaodang",
    "gn:country_code":"CN",
    "gn:dem":1410,
    "gn:feature_class":"P",
    "gn:feature_code":"PPL",
    "gn:name":"Sajiaodang",
    "gn:population":0,
    "gn:timezone":"Asia/Shanghai",
    "iso:country":"CN",
    "name:zho_x_preferred":[
        "\u6d12\u80f6\u5f53"
    ],
    "wof:name":"Sajiaodang",
    "wof:placetype":"locality"
},
  "geometry": {"coordinates":[104.79300000000001,25.2084],"type":"Point"}
}