{
  "type": "Feature",
  "properties": {
    "gn:admin1_code":"32.0",
    "gn:asciiname":"Long'erjia",
    "gn:country_code":"CN",
    "gn:dem":2996,
    "gn:feature_class":"P",
    "gn:feature_code":"PPL",
    "gn:name":"Long\u2019erjia",
    "gn:population":0,
    "gn:timezone":"Asia/Shanghai",
    "iso:country":"CN",
    "name:zho_x_preferred":[
        "\u9f99\u5c14\u7532"
    ],
    "name:zho_x_variant":[
        "Long\u2019erjia"
    ],
    "wof:name":"Long'erjia",
    "wof:placetype":"locality"
},
  "geometry": {"coordinates":[102.0326,32.25073],"type":"Point"}
}