{
  "type": "Feature",
  "properties": {
    "gn:admin1_code":"1.0",
    "gn:asciiname":"Huangcangyu Guoying Linchang",
    "gn:country_code":"CN",
    "gn:dem":248,
    "gn:feature_class":"P",
    "gn:feature_code":"PPLF",
    "gn:name":"Huangcangyu Guoying Linchang",
    "gn:population":0,
    "gn:timezone":"Asia/Shanghai",
    "iso:country":"CN",
    "name:zho_x_preferred":[
        "\u7687\u85cf\u5cea\u56fd\u8425\u6797\u573a"
    ],
    "wof:name":"Huangcangyu Guoying Linchang",
    "wof:placetype":"locality"
},
  "geometry": {"coordinates":[117.04733,34.02698],"type":"Point"}
}