{
  "type": "Feature",
  "properties": {
    "gn:admin1_code":"4.0",
    "gn:asciiname":"Hezhuangcun",
    "gn:country_code":"CN",
    "gn:dem":29,
    "gn:feature_class":"P",
    "gn:feature_code":"PPL",
    "gn:name":"Hezhuangcun",
    "gn:population":0,
    "gn:timezone":"Asia/Shanghai",
    "iso:country":"CN",
    "name:zho_x_preferred":[
        "\u8d3a\u5e84\u6751"
    ],
    "wof:name":"Hezhuangcun",
    "wof:placetype":"locality"
},
  "geometry": {"coordinates":[117.62188999999999,34.17493],"type":"Point"}
}