{
  "type": "Feature",
  "properties": {
    "gn:admin1_code":"33.0",
    "gn:asciiname":"Guanyindong",
    "gn:country_code":"CN",
    "gn:dem":1081,
    "gn:feature_class":"P",
    "gn:feature_code":"PPL",
    "gn:name":"Guanyindong",
    "gn:population":0,
    "gn:timezone":"Asia/Shanghai",
    "iso:country":"CN",
    "name:deu_x_preferred":[
        "Guanyindong"
    ],
    "name:zho_x_preferred":[
        "\u89c2\u97f3\u6d1e"
    ],
    "wof:name":"Guanyindong",
    "wof:placetype":"locality"
},
  "geometry": {"coordinates":[107.97055,29.96982],"type":"Point"}
}