{
  "type": "Feature",
  "properties": {
    "gn:admin1_code":"15.0",
    "gn:asciiname":"Gejiahao",
    "gn:country_code":"CN",
    "gn:dem":1412,
    "gn:feature_class":"P",
    "gn:feature_code":"PPL",
    "gn:name":"Gejiahao",
    "gn:population":0,
    "gn:timezone":"Asia/Shanghai",
    "iso:country":"CN",
    "name:zho_x_preferred":[
        "\u845b\u5bb6\u58d5"
    ],
    "wof:name":"Gejiahao",
    "wof:placetype":"locality"
},
  "geometry": {"coordinates":[98.6623,39.6966],"type":"Point"}
}