{
  "type": "Feature",
  "properties": {
    "gn:admin1_code":"3.0",
    "gn:asciiname":"Tanli",
    "gn:country_code":"CN",
    "gn:dem":552,
    "gn:feature_class":"P",
    "gn:feature_code":"PPL",
    "gn:name":"Tanli",
    "gn:population":0,
    "gn:timezone":"Asia/Shanghai",
    "iso:country":"CN",
    "name:zho_x_preferred":[
        "\u8c2d\u91cc"
    ],
    "wof:name":"Tanli",
    "wof:placetype":"locality"
},
  "geometry": {"coordinates":[114.09699999999999,27.4048],"type":"Point"}
}