{
  "type": "Feature",
  "properties": {
    "gn:admin1_code":"1.0",
    "gn:asciiname":"Yeyingcun",
    "gn:country_code":"CN",
    "gn:dem":24,
    "gn:feature_class":"P",
    "gn:feature_code":"PPL",
    "gn:name":"Yeyingcun",
    "gn:population":0,
    "gn:timezone":"Asia/Shanghai",
    "iso:country":"CN",
    "name:zho_x_preferred":[
        "\u53f6\u8425\u6751"
    ],
    "wof:name":"Yeyingcun",
    "wof:placetype":"locality"
},
  "geometry": {"coordinates":[118.79468,32.63647],"type":"Point"}
}