{
  "type": "Feature",
  "properties": {
    "gn:admin1_code":"30.0",
    "gn:asciiname":"Pipakeng",
    "gn:country_code":"CN",
    "gn:dem":658,
    "gn:feature_class":"P",
    "gn:feature_code":"PPL",
    "gn:name":"Pipakeng",
    "gn:population":0,
    "gn:timezone":"Asia/Shanghai",
    "iso:country":"CN",
    "name:zho_x_preferred":[
        "Pipakeng"
    ],
    "name:zho_x_variant":[
        "\u7435\u7436\u5751"
    ],
    "wof:name":"Pipakeng",
    "wof:placetype":"locality"
},
  "geometry": {"coordinates":[113.24444,25.13333],"type":"Point"}
}