{
  "type": "Feature",
  "properties": {
    "gn:admin1_code":"15.0",
    "gn:asciiname":"Gaojiahe",
    "gn:country_code":"CN",
    "gn:dem":1662,
    "gn:feature_class":"P",
    "gn:feature_code":"PPL",
    "gn:name":"Gaojiahe",
    "gn:population":0,
    "gn:timezone":"Asia/Shanghai",
    "iso:country":"CN",
    "name:zho_x_preferred":[
        "\u9ad8\u5bb6\u6cb3"
    ],
    "wof:name":"Gaojiahe",
    "wof:placetype":"locality"
},
  "geometry": {"coordinates":[105.101,36.1482],"type":"Point"}
}