{
  "type": "Feature",
  "properties": {
    "gn:admin1_code":"8.0",
    "gn:asciiname":"Qianzhenbangtun",
    "gn:country_code":"CN",
    "gn:dem":255,
    "gn:feature_class":"P",
    "gn:feature_code":"PPL",
    "gn:name":"Qianzhenbangtun",
    "gn:population":0,
    "gn:timezone":"Asia/Shanghai",
    "iso:country":"CN",
    "name:zho_x_preferred":[
        "\u94b1\u632f\u5e2e\u5c6f"
    ],
    "wof:name":"Qianzhenbangtun",
    "wof:placetype":"locality"
},
  "geometry": {"coordinates":[125.93781,47.07224],"type":"Point"}
}