{
  "type": "Feature",
  "properties": {
    "gn:admin1_code":"14",
    "gn:asciiname":"Rending",
    "gn:country_code":"CN",
    "gn:dem":4225,
    "gn:feature_class":"P",
    "gn:feature_code":"PPL",
    "gn:name":"Rending",
    "gn:population":0,
    "gn:timezone":"Asia/Urumqi",
    "iso:country":"CN",
    "name:zho_x_preferred":[
        "\u4ec1\u5b9a"
    ],
    "wof:name":"Rending",
    "wof:placetype":"locality"
},
  "geometry": {"coordinates":[89.4258,28.9808],"type":"Point"}
}