{
  "type": "Feature",
  "properties": {
    "gn:admin1_code":"18",
    "gn:asciiname":"Bajiaogou",
    "gn:country_code":"CN",
    "gn:dem":933,
    "gn:feature_class":"P",
    "gn:feature_code":"PPL",
    "gn:name":"Bajiaogou",
    "gn:population":0,
    "gn:timezone":"Asia/Shanghai",
    "iso:country":"CN",
    "name:zho_x_preferred":[
        "\u82ad\u8549\u6c9f"
    ],
    "wof:name":"Bajiaogou",
    "wof:placetype":"locality"
},
  "geometry": {"coordinates":[106.36799999999999,27.6289],"type":"Point"}
}