{
  "type": "Feature",
  "properties": {
    "gn:admin1_code":"32.0",
    "gn:asciiname":"Xiajiawa",
    "gn:country_code":"CN",
    "gn:dem":3655,
    "gn:feature_class":"P",
    "gn:feature_code":"PPL",
    "gn:name":"Xiajiawa",
    "gn:population":0,
    "gn:timezone":"Asia/Shanghai",
    "iso:country":"CN",
    "name:zho_x_preferred":[
        "\u4e0b\u7532\u6d3c"
    ],
    "wof:name":"Xiajiawa",
    "wof:placetype":"locality"
},
  "geometry": {"coordinates":[100.402,29.7585],"type":"Point"}
}