{
  "type": "Feature",
  "properties": {
    "gn:admin1_code":"4.0",
    "gn:asciiname":"Guoqiaocun",
    "gn:country_code":"CN",
    "gn:dem":43,
    "gn:feature_class":"P",
    "gn:feature_code":"PPL",
    "gn:name":"Guoqiaocun",
    "gn:population":0,
    "gn:timezone":"Asia/Shanghai",
    "iso:country":"CN",
    "name:zho_x_preferred":[
        "\u90ed\u6865\u6751"
    ],
    "wof:name":"Guoqiaocun",
    "wof:placetype":"locality"
},
  "geometry": {"coordinates":[117.04388,34.34350999999999],"type":"Point"}
}