{
  "type": "Feature",
  "properties": {
    "gn:admin1_code":"2.0",
    "gn:asciiname":"Gaobatang",
    "gn:country_code":"CN",
    "gn:dem":106,
    "gn:feature_class":"P",
    "gn:feature_code":"PPL",
    "gn:name":"Gaobatang",
    "gn:population":0,
    "gn:timezone":"Asia/Shanghai",
    "iso:country":"CN",
    "name:und_x_variant":[
        "\u9ad8\u62d4\u5858",
        "Gaoba",
        "\u9ad8\u62d4"
    ],
    "wof:name":"Gaobatang",
    "wof:placetype":"locality"
},
  "geometry": {"coordinates":[119.30706000000001,30.17559],"type":"Point"}
}