{
  "type": "Feature",
  "properties": {
    "gn:admin1_code":"11.0",
    "gn:asciiname":"Mawangdong",
    "gn:country_code":"CN",
    "gn:dem":45,
    "gn:feature_class":"P",
    "gn:feature_code":"PPL",
    "gn:name":"Mawangdong",
    "gn:population":0,
    "gn:timezone":"Asia/Shanghai",
    "iso:country":"CN",
    "name:zho_x_preferred":[
        "Mawangdong"
    ],
    "name:zho_x_variant":[
        "\u9ebb\u738b\u6d1e"
    ],
    "wof:name":"Mawangdong",
    "wof:placetype":"locality"
},
  "geometry": {"coordinates":[111.51412000000001,28.9064],"type":"Point"}
}