{
  "type": "Feature",
  "properties": {
    "gn:admin1_code":"26.0",
    "gn:asciiname":"Zhenbao",
    "gn:country_code":"CN",
    "gn:dem":520,
    "gn:feature_class":"P",
    "gn:feature_code":"PPL",
    "gn:name":"Zhenbao",
    "gn:population":0,
    "gn:timezone":"Asia/Shanghai",
    "iso:country":"CN",
    "name:und_x_variant":[
        "\u73cd\u5b9d"
    ],
    "wof:name":"Zhenbao",
    "wof:placetype":"locality"
},
  "geometry": {"coordinates":[106.92453999999999,33.11907],"type":"Point"}
}