{
  "type": "Feature",
  "properties": {
    "gn:admin1_code":"5.0",
    "gn:asciiname":"Jianmincun",
    "gn:country_code":"CN",
    "gn:dem":197,
    "gn:feature_class":"P",
    "gn:feature_code":"PPL",
    "gn:name":"Jianmincun",
    "gn:population":0,
    "gn:timezone":"Asia/Shanghai",
    "iso:country":"CN",
    "name:zho_x_preferred":[
        "\u5065\u6c11\u6751"
    ],
    "wof:name":"Jianmincun",
    "wof:placetype":"locality"
},
  "geometry": {"coordinates":[126.45269999999999,45.09235],"type":"Point"}
}