{
  "type": "Feature",
  "properties": {
    "gn:admin1_code":"18",
    "gn:asciiname":"Wangjiaqiao",
    "gn:country_code":"CN",
    "gn:dem":820,
    "gn:feature_class":"P",
    "gn:feature_code":"PPL",
    "gn:name":"Wangjiaqiao",
    "gn:population":0,
    "gn:timezone":"Asia/Shanghai",
    "iso:country":"CN",
    "name:zho_x_preferred":[
        "\u6c6a\u5bb6\u6865"
    ],
    "wof:name":"Wangjiaqiao",
    "wof:placetype":"locality"
},
  "geometry": {"coordinates":[107.559,27.2961],"type":"Point"}
}