{
  "type": "Feature",
  "properties": {
    "gn:admin1_code":"25",
    "gn:asciiname":"Shengcai Yicun",
    "gn:country_code":"CN",
    "gn:dem":2,
    "gn:feature_class":"P",
    "gn:feature_code":"PPL",
    "gn:name":"Shengcai Yicun",
    "gn:population":0,
    "gn:timezone":"Asia/Shanghai",
    "iso:country":"CN",
    "name:zho_x_preferred":[
        "\u80dc\u91c7\u4e00\u6751"
    ],
    "wof:name":"Shengcai Yicun",
    "wof:placetype":"locality"
},
  "geometry": {"coordinates":[118.69703,37.45552],"type":"Point"}
}