{
  "type": "Feature",
  "properties": {
    "gn:admin1_code":"26.0",
    "gn:asciiname":"Qipan",
    "gn:country_code":"CN",
    "gn:dem":688,
    "gn:feature_class":"P",
    "gn:feature_code":"PPL",
    "gn:name":"Qipan",
    "gn:population":0,
    "gn:timezone":"Asia/Shanghai",
    "iso:country":"CN",
    "name:und_x_variant":[
        "\u68cb\u76d8"
    ],
    "wof:name":"Qipan",
    "wof:placetype":"locality"
},
  "geometry": {"coordinates":[106.61286,33.04651],"type":"Point"}
}