{
  "type": "Feature",
  "properties": {
    "gn:admin1_code":"19.0",
    "gn:asciiname":"Yaohuajia",
    "gn:country_code":"CN",
    "gn:dem":87,
    "gn:feature_class":"P",
    "gn:feature_code":"PPL",
    "gn:name":"Yaohuajia",
    "gn:population":0,
    "gn:timezone":"Asia/Shanghai",
    "iso:country":"CN",
    "name:und_x_variant":[
        "\u8170\u82b1\u5bb6"
    ],
    "name:zho_x_preferred":[
        "\u8170\u82b1\u5bb6"
    ],
    "wof:name":"Yaohuajia",
    "wof:placetype":"locality"
},
  "geometry": {"coordinates":[122.52301,42.4178],"type":"Point"}
}