{
  "type": "Feature",
  "properties": {
    "gn:admin1_code":"02",
    "gn:asciiname":"Shandongcun",
    "gn:country_code":"CN",
    "gn:dem":32,
    "gn:feature_class":"P",
    "gn:feature_code":"PPL",
    "gn:name":"Shandongcun",
    "gn:population":0,
    "gn:timezone":"Asia/Shanghai",
    "iso:country":"CN",
    "name:rus_x_preferred":[
        "\u0428\u0430\u043d\u044c\u0434\u0443\u043d"
    ],
    "name:und_x_variant":[
        "Shan-chen-ts\u2019un",
        "Shandong",
        "Shandongcun"
    ],
    "name:zho_x_preferred":[
        "\u5c71\u8463"
    ],
    "name:zho_x_variant":[
        "\u5c71\u8463\u6751"
    ],
    "wof:name":"Shandongcun",
    "wof:placetype":"locality"
},
  "geometry": {"coordinates":[121.35741000000002,29.10006],"type":"Point"}
}