{
  "type": "Feature",
  "properties": {
    "gn:admin1_code":"3.0",
    "gn:asciiname":"Xiaohan",
    "gn:country_code":"CN",
    "gn:dem":46,
    "gn:feature_class":"P",
    "gn:feature_code":"PPL",
    "gn:name":"Xiaohan",
    "gn:population":0,
    "gn:timezone":"Asia/Shanghai",
    "iso:country":"CN",
    "name:afr_x_preferred":[
        "Xiaohan"
    ],
    "name:cdo_x_preferred":[
        "Si\u0113u-h\u00e0ng"
    ],
    "name:fra_x_preferred":[
        "Xiaohan"
    ],
    "name:hak_x_preferred":[
        "S\u00e9u-h\u00f2n"
    ],
    "name:swe_x_preferred":[
        "Xiaohan"
    ],
    "name:und_x_variant":[
        "\u5c0f\u97e9"
    ],
    "name:vie_x_preferred":[
        "Ti\u1ec3u h\u00e0n"
    ],
    "name:zha_x_preferred":[
        "Siujhanz"
    ],
    "wof:name":"Xiaohan",
    "wof:placetype":"locality"
},
  "geometry": {"coordinates":[116.82814,29.56391],"type":"Point"}
}