{
  "type": "Feature",
  "properties": {
    "gn:admin1_code":"8.0",
    "gn:asciiname":"Ercuncun",
    "gn:country_code":"CN",
    "gn:dem":190,
    "gn:feature_class":"P",
    "gn:feature_code":"PPL",
    "gn:name":"Ercuncun",
    "gn:population":0,
    "gn:timezone":"Asia/Shanghai",
    "iso:country":"CN",
    "name:zho_x_preferred":[
        "\u4e8c\u6751\u6751"
    ],
    "wof:name":"Ercuncun",
    "wof:placetype":"locality"
},
  "geometry": {"coordinates":[127.02688000000001,47.07263],"type":"Point"}
}