{
  "type": "Feature",
  "properties": {
    "gn:admin1_code":"11",
    "gn:asciiname":"Dongtian",
    "gn:country_code":"CN",
    "gn:dem":239,
    "gn:feature_class":"P",
    "gn:feature_code":"PPLA4",
    "gn:name":"Dongtian",
    "gn:population":0,
    "gn:timezone":"Asia/Shanghai",
    "iso:country":"CN",
    "name:und_x_variant":[
        "Dongtian Zhen",
        "\u4e1c\u7530\u9547",
        "Dongtian"
    ],
    "name:zho_x_preferred":[
        "\u4e1c\u7530"
    ],
    "wof:name":"Dongtian",
    "wof:placetype":"locality"
},
  "geometry": {"coordinates":[111.64943999999998,25.14944],"type":"Point"}
}