{
  "type": "Feature",
  "properties": {
    "gn:admin1_code":"25.0",
    "gn:asciiname":"Xiaohezicun",
    "gn:country_code":"CN",
    "gn:dem":76,
    "gn:feature_class":"P",
    "gn:feature_code":"PPL",
    "gn:name":"Xiaohezicun",
    "gn:population":0,
    "gn:timezone":"Asia/Shanghai",
    "iso:country":"CN",
    "name:zho_x_preferred":[
        "\u5c0f\u6cb3\u5b50\u6751"
    ],
    "wof:name":"Xiaohezicun",
    "wof:placetype":"locality"
},
  "geometry": {"coordinates":[121.15242000000001,37.4927],"type":"Point"}
}