{
  "type": "Feature",
  "properties": {
    "gn:admin1_code":"19.0",
    "gn:asciiname":"Fakuxian Zhongxuchang",
    "gn:country_code":"CN",
    "gn:dem":141,
    "gn:feature_class":"P",
    "gn:feature_code":"PPLF",
    "gn:name":"Fakuxian Zhongxuchang",
    "gn:population":0,
    "gn:timezone":"Asia/Shanghai",
    "iso:country":"CN",
    "name:und_x_variant":[
        "\u6cd5\u5e93\u53bf\u79cd\u755c\u573a"
    ],
    "name:zho_x_preferred":[
        "\u6cd5\u5e93\u53bf\u79cd\u755c\u573a"
    ],
    "wof:name":"Fakuxian Zhongxuchang",
    "wof:placetype":"locality"
},
  "geometry": {"coordinates":[123.48293,42.47896],"type":"Point"}
}