{
  "type": "Feature",
  "properties": {
    "gn:admin1_code":"18.0",
    "gn:asciiname":"Longfeng",
    "gn:country_code":"CN",
    "gn:dem":1120,
    "gn:feature_class":"P",
    "gn:feature_code":"PPL",
    "gn:name":"Longfeng",
    "gn:population":0,
    "gn:timezone":"Asia/Shanghai",
    "iso:country":"CN",
    "name:ceb_x_preferred":[
        "Longfeng"
    ],
    "name:deu_x_preferred":[
        "Longfeng"
    ],
    "name:mlg_x_preferred":[
        "Longfeng"
    ],
    "wof:name":"Longfeng",
    "wof:placetype":"locality"
},
  "geometry": {"coordinates":[106.18056,27.3975],"type":"Point"}
}