{
  "type": "Feature",
  "properties": {
    "gn:admin1_code":"26",
    "gn:asciiname":"Longwanggou",
    "gn:country_code":"CN",
    "gn:dem":693,
    "gn:feature_class":"P",
    "gn:feature_code":"PPL",
    "gn:name":"Longwanggou",
    "gn:population":0,
    "gn:timezone":"Asia/Shanghai",
    "iso:country":"CN",
    "name:und_x_variant":[
        "Lung-wang-chieh",
        "Longwangjie",
        "Longwanggou"
    ],
    "name:zho_x_preferred":[
        "\u9f99\u738b\u6c9f"
    ],
    "wof:name":"Longwanggou",
    "wof:placetype":"locality"
},
  "geometry": {"coordinates":[108.17269,33.36789],"type":"Point"}
}