{
  "type": "Feature",
  "properties": {
    "gn:admin1_code":"13.0",
    "gn:asciiname":"Kunqi",
    "gn:country_code":"CN",
    "gn:dem":1300,
    "gn:feature_class":"P",
    "gn:feature_code":"PPL",
    "gn:name":"Kunqi",
    "gn:population":0,
    "gn:timezone":"Asia/Shanghai",
    "iso:country":"CN",
    "name:zho_x_preferred":[
        "\u6606\u5176"
    ],
    "wof:name":"Kunqi",
    "wof:placetype":"locality"
},
  "geometry": {"coordinates":[79.58702,37.46639],"type":"Point"}
}