{
  "type": "Feature",
  "properties": {
    "gn:admin1_code":"18.0",
    "gn:asciiname":"Jianping",
    "gn:country_code":"CN",
    "gn:dem":751,
    "gn:feature_class":"P",
    "gn:feature_code":"PPLA4",
    "gn:name":"Jianping",
    "gn:population":0,
    "gn:timezone":"Asia/Shanghai",
    "iso:country":"CN",
    "name:deu_x_preferred":[
        "Jianping"
    ],
    "name:und_x_variant":[
        "Jianping Xiang"
    ],
    "name:zho_x_preferred":[
        "\u4fed\u5e73"
    ],
    "name:zho_x_variant":[
        "\u4fed\u5e73\u4e61"
    ],
    "wof:name":"Jianping",
    "wof:placetype":"locality"
},
  "geometry": {"coordinates":[107.49062000000001,28.51726],"type":"Point"}
}