{
  "type": "Feature",
  "properties": {
    "gn:admin1_code":"2.0",
    "gn:asciiname":"Xumu",
    "gn:country_code":"CN",
    "gn:dem":430,
    "gn:feature_class":"P",
    "gn:feature_code":"PPL",
    "gn:name":"Xumu",
    "gn:population":0,
    "gn:timezone":"Asia/Shanghai",
    "iso:country":"CN",
    "name:und_x_variant":[
        "\u7eed\u76ee"
    ],
    "wof:name":"Xumu",
    "wof:placetype":"locality"
},
  "geometry": {"coordinates":[119.66231999999999,30.44119],"type":"Point"}
}