{
  "type": "Feature",
  "properties": {
    "gn:admin1_code":"11.0",
    "gn:asciiname":"Mao'anshang",
    "gn:country_code":"CN",
    "gn:dem":833,
    "gn:feature_class":"P",
    "gn:feature_code":"PPL",
    "gn:name":"Mao\u2019anshang",
    "gn:population":0,
    "gn:timezone":"Asia/Shanghai",
    "iso:country":"CN",
    "name:zho_x_preferred":[
        "\u6bdb\u5b89\u4e0a"
    ],
    "name:zho_x_variant":[
        "Mao\u2019anshang"
    ],
    "wof:name":"Mao'anshang",
    "wof:placetype":"locality"
},
  "geometry": {"coordinates":[110.81635,29.39993],"type":"Point"}
}