{
  "type": "Feature",
  "properties": {
    "gn:admin1_code":"13.0",
    "gn:asciiname":"Korgas",
    "gn:cc2":"CN",
    "gn:country_code":"CN",
    "gn:dem":648,
    "gn:feature_class":"P",
    "gn:feature_code":"PPL",
    "gn:name":"Korgas",
    "gn:population":0,
    "gn:timezone":"Asia/Shanghai",
    "iso:country":"CN",
    "name:uig_x_preferred":[
        "K\u0329or\u01a3as"
    ],
    "name:uig_x_variant":[
        "Qorghas",
        "\u0642\u0648\u0631\u063a\u0627\u0633",
        "\u049a\u043e\u0440\u0493\u0430\u0441"
    ],
    "name:und_x_variant":[
        "Huo-ch\u2019eng",
        "Ho-ch\u2019eng",
        "Kung-ch\u2019en",
        "Chorgos",
        "Huo-erh-kuo-ssu",
        "Gorgos",
        "Ho-erh-kuo-ssu",
        "Khorgos",
        "Khorges",
        "Kung-ch\u2019en-ch\u2019eng",
        "Horgos",
        "Kurgash",
        "Hoerkwosze",
        "Ho-ch\u2019eng-chen",
        "Ho-ch\u2019eng-hsien",
        "Korgas"
    ],
    "wof:name":"Korgas",
    "wof:placetype":"locality"
},
  "geometry": {"coordinates":[80.41444,44.12556],"type":"Point"}
}