{
  "type": "Feature",
  "properties": {
    "gn:admin1_code":"13.0",
    "gn:asciiname":"Korgas",
    "gn:cc2":"CN",
    "gn:country_code":"CN",
    "gn:dem":648,
    "gn:feature_class":"P",
    "gn:feature_code":"PPL",
    "gn:name":"Korgas",
    "gn:population":0,
    "gn:timezone":"Asia/Shanghai",
    "iso:country":"CN",
    "name:deu_x_preferred":[
        "Korgas"
    ],
    "name:fas_x_preferred":[
        "\u0642\u0648\u0631\u063a\u0627\u0633"
    ],
    "name:fra_x_preferred":[
        "Khorgos"
    ],
    "name:jpn_x_preferred":[
        "\u30b3\u30eb\u30ac\u30b9\u5e02"
    ],
    "name:kik_x_preferred":[
        "Khorgas"
    ],
    "name:nld_x_preferred":[
        "Khorgos"
    ],
    "name:rus_x_preferred":[
        "\u0425\u043e\u0440\u0433\u043e\u0441"
    ],
    "name:spa_x_preferred":[
        "Horgos"
    ],
    "name:tur_x_preferred":[
        "Korgas"
    ],
    "name:uig_x_preferred":[
        "K\u0329or\u01a3as"
    ],
    "name:uig_x_variant":[
        "Qorghas",
        "\u0642\u0648\u0631\u063a\u0627\u0633",
        "\u049a\u043e\u0440\u0493\u0430\u0441",
        "\u0642\u0648\u0631\u063a\u0627\u0633 \u0634\u06d5\u06be\u0649\u0631\u0649"
    ],
    "name:und_x_variant":[
        "Huo-ch\u2019eng",
        "Ho-ch\u2019eng",
        "Kung-ch\u2019en",
        "Chorgos",
        "Huo-erh-kuo-ssu",
        "Gorgos",
        "Ho-erh-kuo-ssu",
        "Khorgos",
        "Khorges",
        "Kung-ch\u2019en-ch\u2019eng",
        "Horgos",
        "Kurgash",
        "Hoerkwosze",
        "Ho-ch\u2019eng-chen",
        "Ho-ch\u2019eng-hsien",
        "Korgas"
    ],
    "name:urd_x_preferred":[
        "\u0642\u0648\u0631\u063a\u0627\u0633"
    ],
    "name:vie_x_preferred":[
        "Khorgas"
    ],
    "name:zho_x_preferred":[
        "\u970d\u5c14\u679c\u65af\u5e02"
    ],
    "wof:name":"Korgas",
    "wof:placetype":"locality"
},
  "geometry": {"coordinates":[80.41444,44.12556],"type":"Point"}
}