{
  "type": "Feature",
  "properties": {
    "gn:admin1_code":"16.0",
    "gn:asciiname":"Ding'e",
    "gn:country_code":"CN",
    "gn:dem":174,
    "gn:feature_class":"P",
    "gn:feature_code":"PPL",
    "gn:name":"Ding\u2019e",
    "gn:population":0,
    "gn:timezone":"Asia/Shanghai",
    "iso:country":"CN",
    "name:und_x_variant":[
        "Ding\u2019e"
    ],
    "name:zho_x_preferred":[
        "\u5b9a\u4fc4"
    ],
    "wof:name":"Ding'e",
    "wof:placetype":"locality"
},
  "geometry": {"coordinates":[107.91,23.6676],"type":"Point"}
}