{
  "type": "Feature",
  "properties": {
    "gn:admin1_code":"1.0",
    "gn:asciiname":"Jianghucun",
    "gn:country_code":"CN",
    "gn:dem":27,
    "gn:feature_class":"P",
    "gn:feature_code":"PPL",
    "gn:name":"Jianghucun",
    "gn:population":0,
    "gn:timezone":"Asia/Shanghai",
    "iso:country":"CN",
    "name:und_x_variant":[
        "Jianghu"
    ],
    "name:zho_x_preferred":[
        "\u848b\u6e56\u6751"
    ],
    "wof:name":"Jianghucun",
    "wof:placetype":"locality"
},
  "geometry": {"coordinates":[116.82246000000001,33.51234],"type":"Point"}
}