{
  "type": "Feature",
  "properties": {
    "gn:admin1_code":"6.0",
    "gn:asciiname":"Yanadong",
    "gn:country_code":"CN",
    "gn:dem":2044,
    "gn:feature_class":"P",
    "gn:feature_code":"PPL",
    "gn:name":"Yanadong",
    "gn:population":0,
    "gn:timezone":"Asia/Shanghai",
    "iso:country":"CN",
    "name:und_x_variant":[
        "\u7259\u90a3\u6d1e"
    ],
    "wof:name":"Yanadong",
    "wof:placetype":"locality"
},
  "geometry": {"coordinates":[102.05481,35.90136],"type":"Point"}
}