{
  "type": "Feature",
  "properties": {
    "gn:admin1_code":"5.0",
    "gn:asciiname":"Xiaojiacun",
    "gn:country_code":"CN",
    "gn:dem":129,
    "gn:feature_class":"P",
    "gn:feature_code":"PPL",
    "gn:name":"Xiaojiacun",
    "gn:population":0,
    "gn:timezone":"Asia/Shanghai",
    "iso:country":"CN",
    "name:zho_x_preferred":[
        "\u8096\u5bb6\u6751"
    ],
    "wof:name":"Xiaojiacun",
    "wof:placetype":"locality"
},
  "geometry": {"coordinates":[125.62763,45.41293],"type":"Point"}
}