{
  "type": "Feature",
  "properties": {
    "gn:admin1_code":"14.0",
    "gn:asciiname":"Niexiegong",
    "gn:country_code":"CN",
    "gn:dem":3843,
    "gn:feature_class":"P",
    "gn:feature_code":"PPL",
    "gn:name":"Niexiegong",
    "gn:population":0,
    "gn:timezone":"Asia/Urumqi",
    "iso:country":"CN",
    "name:zho_x_preferred":[
        "\u8042\u8c22\u5de5"
    ],
    "wof:name":"Niexiegong",
    "wof:placetype":"locality"
},
  "geometry": {"coordinates":[97.84891,32.47521],"type":"Point"}
}