{
  "type": "Feature",
  "properties": {
    "gn:admin1_code":"6.0",
    "gn:asciiname":"Gamaoqi",
    "gn:country_code":"CN",
    "gn:dem":2832,
    "gn:feature_class":"P",
    "gn:feature_code":"PPL",
    "gn:name":"Gamaoqi",
    "gn:population":0,
    "gn:timezone":"Asia/Shanghai",
    "iso:country":"CN",
    "name:und_x_variant":[
        "\u5c15\u6bdb\u5176"
    ],
    "wof:name":"Gamaoqi",
    "wof:placetype":"locality"
},
  "geometry": {"coordinates":[100.31955000000001,35.30238],"type":"Point"}
}