{
  "type": "Feature",
  "properties": {
    "gn:admin1_code":"26.0",
    "gn:asciiname":"Songjia Shancun",
    "gn:country_code":"CN",
    "gn:dem":1034,
    "gn:feature_class":"P",
    "gn:feature_code":"PPL",
    "gn:name":"Songjia Shancun",
    "gn:population":0,
    "gn:timezone":"Asia/Shanghai",
    "iso:country":"CN",
    "name:zho_x_preferred":[
        "\u5b8b\u5bb6\u5c71\u6751"
    ],
    "wof:name":"Songjia Shancun",
    "wof:placetype":"locality"
},
  "geometry": {"coordinates":[110.438,37.8456],"type":"Point"}
}