{
  "type": "Feature",
  "properties": {
    "gn:admin1_code":"29",
    "gn:asciiname":"Huangdoudi",
    "gn:country_code":"CN",
    "gn:dem":1453,
    "gn:feature_class":"P",
    "gn:feature_code":"PPL",
    "gn:name":"Huangdoudi",
    "gn:population":0,
    "gn:timezone":"Asia/Shanghai",
    "iso:country":"CN",
    "name:zho_x_preferred":[
        "\u9ec4\u8c46\u5730"
    ],
    "wof:name":"Huangdoudi",
    "wof:placetype":"locality"
},
  "geometry": {"coordinates":[102.883,24.0557],"type":"Point"}
}