{
  "type": "Feature",
  "properties": {
    "gn:admin1_code":"20.0",
    "gn:asciiname":"Quanzhangzi",
    "gn:country_code":"CN",
    "gn:dem":1636,
    "gn:feature_class":"P",
    "gn:feature_code":"PPL",
    "gn:name":"Quanzhangzi",
    "gn:population":0,
    "gn:timezone":"Asia/Shanghai",
    "iso:country":"CN",
    "name:und_x_variant":[
        "\u6cc9\u638c\u5b50"
    ],
    "wof:name":"Quanzhangzi",
    "wof:placetype":"locality"
},
  "geometry": {"coordinates":[111.60525,41.26028],"type":"Point"}
}