{
  "type": "Feature",
  "properties": {
    "gn:admin1_code":"30.0",
    "gn:asciiname":"Baimangba",
    "gn:country_code":"CN",
    "gn:dem":104,
    "gn:feature_class":"P",
    "gn:feature_code":"PPL",
    "gn:name":"Baimangba",
    "gn:population":0,
    "gn:timezone":"Asia/Shanghai",
    "iso:country":"CN",
    "name:zho_x_preferred":[
        "\u767d\u8292\u575d"
    ],
    "wof:name":"Baimangba",
    "wof:placetype":"locality"
},
  "geometry": {"coordinates":[113.47591,23.88978],"type":"Point"}
}