{
  "type": "Feature",
  "properties": {
    "gn:admin1_code":"18",
    "gn:asciiname":"Banchang",
    "gn:country_code":"CN",
    "gn:dem":645,
    "gn:feature_class":"P",
    "gn:feature_code":"PPL",
    "gn:name":"Banchang",
    "gn:population":0,
    "gn:timezone":"Asia/Shanghai",
    "iso:country":"CN",
    "name:zho_x_preferred":[
        "\u677f\u660c"
    ],
    "wof:name":"Banchang",
    "wof:placetype":"locality"
},
  "geometry": {"coordinates":[105.846,25.2298],"type":"Point"}
}