{
  "type": "Feature",
  "properties": {
    "gn:admin1_code":"15.0",
    "gn:asciiname":"Heping Shangcun",
    "gn:country_code":"CN",
    "gn:dem":1935,
    "gn:feature_class":"P",
    "gn:feature_code":"PPL",
    "gn:name":"Heping Shangcun",
    "gn:population":0,
    "gn:timezone":"Asia/Shanghai",
    "iso:country":"CN",
    "name:zho_x_preferred":[
        "\u6cb3\u576a\u4e0a\u6751"
    ],
    "wof:name":"Heping Shangcun",
    "wof:placetype":"locality"
},
  "geometry": {"coordinates":[104.643,35.582],"type":"Point"}
}