{
  "type": "Feature",
  "properties": {
    "gn:admin1_code":"4.0",
    "gn:asciiname":"Xiapicun",
    "gn:country_code":"CN",
    "gn:dem":28,
    "gn:feature_class":"P",
    "gn:feature_code":"PPL",
    "gn:name":"Xiapicun",
    "gn:population":0,
    "gn:timezone":"Asia/Shanghai",
    "iso:country":"CN",
    "name:zho_x_preferred":[
        "\u4e0b\u90b3\u6751"
    ],
    "wof:name":"Xiapicun",
    "wof:placetype":"locality"
},
  "geometry": {"coordinates":[117.90869000000001,34.14392],"type":"Point"}
}