{
  "type": "Feature",
  "properties": {
    "gn:admin1_code":"16.0",
    "gn:asciiname":"Shamu",
    "gn:country_code":"CN",
    "gn:dem":265,
    "gn:feature_class":"P",
    "gn:feature_code":"PPL",
    "gn:name":"Shamu",
    "gn:population":0,
    "gn:timezone":"Asia/Shanghai",
    "iso:country":"CN",
    "name:fra_x_preferred":[
        "Shamu"
    ],
    "name:heb_x_preferred":[
        "\u05e9\u05d0\u05de\u05d5"
    ],
    "name:zho_x_preferred":[
        "\u6749\u6728"
    ],
    "wof:name":"Shamu",
    "wof:placetype":"locality"
},
  "geometry": {"coordinates":[109.756,25.07],"type":"Point"}
}