{
  "type": "Feature",
  "properties": {
    "gn:admin1_code":"16",
    "gn:asciiname":"Pola",
    "gn:country_code":"CN",
    "gn:dem":364,
    "gn:feature_class":"P",
    "gn:feature_code":"PPL",
    "gn:name":"Pola",
    "gn:population":0,
    "gn:timezone":"Asia/Shanghai",
    "iso:country":"CN",
    "name:bul_x_preferred":[
        "\u041f\u043e\u043b\u0430"
    ],
    "name:cat_x_preferred":[
        "Pola"
    ],
    "name:ceb_x_preferred":[
        "Pola"
    ],
    "name:ces_x_preferred":[
        "Pola"
    ],
    "name:deu_x_preferred":[
        "Pola"
    ],
    "name:fin_x_preferred":[
        "Pola"
    ],
    "name:fra_x_preferred":[
        "Pola"
    ],
    "name:glg_x_preferred":[
        "Pola"
    ],
    "name:hrv_x_preferred":[
        "Pola"
    ],
    "name:hun_x_preferred":[
        "Pola"
    ],
    "name:ita_x_preferred":[
        "Pola"
    ],
    "name:nld_x_preferred":[
        "Pola"
    ],
    "name:pol_x_preferred":[
        "Pola"
    ],
    "name:spa_x_preferred":[
        "Pola"
    ],
    "name:swe_x_preferred":[
        "Pola"
    ],
    "wof:name":"Pola",
    "wof:placetype":"locality"
},
  "geometry": {"coordinates":[109.58861,25.10833],"type":"Point"}
}