{
  "type": "Feature",
  "properties": {
    "gn:admin1_code":"10",
    "gn:asciiname":"Huangzhuangzi",
    "gn:country_code":"CN",
    "gn:dem":46,
    "gn:feature_class":"P",
    "gn:feature_code":"PPL",
    "gn:name":"Huangzhuangzi",
    "gn:population":0,
    "gn:timezone":"Asia/Shanghai",
    "iso:country":"CN",
    "name:und_x_variant":[
        "Huang-chuang-tzu",
        "Huangzhuangzi"
    ],
    "name:zho_x_preferred":[
        "\u9ec4\u5e84\u5b50"
    ],
    "wof:name":"Huangzhuangzi",
    "wof:placetype":"locality"
},
  "geometry": {"coordinates":[117.92829,40.18093],"type":"Point"}
}