{
  "type": "Feature",
  "properties": {
    "gn:admin1_code":"18.0",
    "gn:asciiname":"Zhelou",
    "gn:cc2":"CN",
    "gn:country_code":"CN",
    "gn:dem":701,
    "gn:feature_class":"P",
    "gn:feature_code":"PPL",
    "gn:name":"Zhelou",
    "gn:population":0,
    "gn:timezone":"Asia/Shanghai",
    "iso:country":"CN",
    "name:und_x_variant":[
        "Ts\u2019e-heng-pu-i-tsu-tzu-chih-hsien",
        "Ceheng",
        "Ts\u2019e-heng",
        "Che-lou",
        "Ts\u2019e-heng-hsien",
        "Che-fu",
        "Che-shu",
        "Che-lou-chen",
        "Zhelou"
    ],
    "wof:name":"Zhelou",
    "wof:placetype":"locality"
},
  "geometry": {"coordinates":[105.81667,24.96667],"type":"Point"}
}