{
  "type": "Feature",
  "properties": {
    "gn:admin1_code":"30.0",
    "gn:asciiname":"Kengdongcun",
    "gn:country_code":"CN",
    "gn:dem":76,
    "gn:feature_class":"P",
    "gn:feature_code":"PPL",
    "gn:name":"Kengdongcun",
    "gn:population":0,
    "gn:timezone":"Asia/Urumqi",
    "iso:country":"CN",
    "name:zho_x_preferred":[
        "\u5751\u4e1c\u6751"
    ],
    "wof:name":"Kengdongcun",
    "wof:placetype":"locality"
},
  "geometry": {"coordinates":[110.08710000000001,20.46898],"type":"Point"}
}