{
  "type": "Feature",
  "properties": {
    "gn:admin1_code":"4.0",
    "gn:asciiname":"Qiancheng",
    "gn:country_code":"CN",
    "gn:dem":-4,
    "gn:feature_class":"P",
    "gn:feature_code":"PPL",
    "gn:name":"Qiancheng",
    "gn:population":0,
    "gn:timezone":"Asia/Shanghai",
    "iso:country":"CN",
    "name:swe_x_preferred":[
        "Qiancheng"
    ],
    "name:zho_x_preferred":[
        "Qiancheng"
    ],
    "name:zho_x_variant":[
        "\u524d\u7a0b",
        "\u9ed4\u57ce\u9547"
    ],
    "wof:name":"Qiancheng",
    "wof:placetype":"locality"
},
  "geometry": {"coordinates":[119.83645,33.85993],"type":"Point"}
}