{
  "type": "Feature",
  "properties": {
    "gn:admin1_code":"10",
    "gn:asciiname":"Shimenqiao",
    "gn:cc2":"CN",
    "gn:country_code":"CN",
    "gn:dem":10,
    "gn:feature_class":"P",
    "gn:feature_code":"PPL",
    "gn:name":"Shimenqiao",
    "gn:population":0,
    "gn:timezone":"Asia/Shanghai",
    "iso:country":"CN",
    "name:und_x_variant":[
        "Shih-men-ch\u2019iao",
        "Shih-men-ch\u2019iao-chen",
        "Shih-men-ku-chen",
        "Shimenqiao"
    ],
    "wof:name":"Shimenqiao",
    "wof:placetype":"locality"
},
  "geometry": {"coordinates":[116.05,38.63333],"type":"Point"}
}