{
  "type": "Feature",
  "properties": {
    "gn:admin1_code":"5.0",
    "gn:asciiname":"Xiaoduling Gouli",
    "gn:country_code":"CN",
    "gn:dem":530,
    "gn:feature_class":"P",
    "gn:feature_code":"PPL",
    "gn:name":"Xiaoduling Gouli",
    "gn:population":0,
    "gn:timezone":"Asia/Shanghai",
    "iso:country":"CN",
    "name:und_x_variant":[
        "\u5c0f\u90fd\u5cad\u6c9f\u91cc"
    ],
    "wof:name":"Xiaoduling Gouli",
    "wof:placetype":"locality"
},
  "geometry": {"coordinates":[125.5313,41.66207],"type":"Point"}
}