{
  "type": "Feature",
  "properties": {
    "gn:admin1_code":"26.0",
    "gn:asciiname":"Erxitai",
    "gn:country_code":"CN",
    "gn:dem":1540,
    "gn:feature_class":"P",
    "gn:feature_code":"PPL",
    "gn:name":"Erxitai",
    "gn:population":0,
    "gn:timezone":"Asia/Shanghai",
    "iso:country":"CN",
    "name:zho_x_preferred":[
        "\u4e8c\u559c\u53f0"
    ],
    "wof:name":"Erxitai",
    "wof:placetype":"locality"
},
  "geometry": {"coordinates":[108.79492999999999,37.41992],"type":"Point"}
}