{
  "type": "Feature",
  "properties": {
    "gn:admin1_code":"15.0",
    "gn:asciiname":"Dongtan",
    "gn:country_code":"CN",
    "gn:dem":1727,
    "gn:feature_class":"P",
    "gn:feature_code":"PPL",
    "gn:name":"Dongtan",
    "gn:population":0,
    "gn:timezone":"Asia/Shanghai",
    "iso:country":"CN",
    "name:deu_x_preferred":[
        "Dongtan"
    ],
    "name:zho_x_preferred":[
        "\u4e1c\u6ee9"
    ],
    "wof:name":"Dongtan",
    "wof:placetype":"locality"
},
  "geometry": {"coordinates":[102.928,37.6816],"type":"Point"}
}