{
  "type": "Feature",
  "properties": {
    "gn:admin1_code":"16.0",
    "gn:asciiname":"Si'ou",
    "gn:country_code":"CN",
    "gn:dem":217,
    "gn:feature_class":"P",
    "gn:feature_code":"PPL",
    "gn:name":"Si\u2019ou",
    "gn:population":0,
    "gn:timezone":"Asia/Shanghai",
    "iso:country":"CN",
    "name:und_x_variant":[
        "Si\u2019ou"
    ],
    "name:zho_x_preferred":[
        "\u6cd7\u6b27"
    ],
    "wof:name":"Si'ou",
    "wof:placetype":"locality"
},
  "geometry": {"coordinates":[109.333,25.3438],"type":"Point"}
}