{
  "type": "Feature",
  "properties": {
    "gn:admin1_code":"26",
    "gn:asciiname":"Dujiabu",
    "gn:country_code":"CN",
    "gn:dem":419,
    "gn:feature_class":"P",
    "gn:feature_code":"PPL",
    "gn:name":"Dujiabu",
    "gn:population":0,
    "gn:timezone":"Asia/Shanghai",
    "iso:country":"CN",
    "name:zho_x_preferred":[
        "\u675c\u5bb6\u5821"
    ],
    "wof:name":"Dujiabu",
    "wof:placetype":"locality"
},
  "geometry": {"coordinates":[108.2821,34.21764],"type":"Point"}
}