{
  "type": "Feature",
  "properties": {
    "gn:admin1_code":"32.0",
    "gn:asciiname":"Gongyantuo",
    "gn:country_code":"CN",
    "gn:dem":507,
    "gn:feature_class":"P",
    "gn:feature_code":"PPL",
    "gn:name":"Gongyantuo",
    "gn:population":0,
    "gn:timezone":"Asia/Shanghai",
    "iso:country":"CN",
    "name:zho_x_preferred":[
        "\u516c\u5830\u6cb1"
    ],
    "wof:name":"Gongyantuo",
    "wof:placetype":"locality"
},
  "geometry": {"coordinates":[103.559,30.5205],"type":"Point"}
}