{
  "type": "Feature",
  "properties": {
    "gn:admin1_code":"13",
    "gn:asciiname":"Tieti'er",
    "gn:country_code":"CN",
    "gn:dem":1270,
    "gn:feature_class":"P",
    "gn:feature_code":"PPL",
    "gn:name":"Tieti\u2019er",
    "gn:population":0,
    "gn:timezone":"Asia/Shanghai",
    "iso:country":"CN",
    "name:und_x_variant":[
        "Tieti\u2019er",
        "\u94c1\u63d0\u5c14"
    ],
    "wof:name":"Tieti'er",
    "wof:placetype":"locality"
},
  "geometry": {"coordinates":[77.35420999999999,38.11214],"type":"Point"}
}