{
  "type": "Feature",
  "properties": {
    "gn:admin1_code":"19.0",
    "gn:asciiname":"Zhuanjiaocun",
    "gn:country_code":"CN",
    "gn:dem":82,
    "gn:feature_class":"P",
    "gn:feature_code":"PPL",
    "gn:name":"Zhuanjiaocun",
    "gn:population":0,
    "gn:timezone":"Asia/Shanghai",
    "iso:country":"CN",
    "name:zho_x_preferred":[
        "\u8f6c\u89d2\u6751"
    ],
    "wof:name":"Zhuanjiaocun",
    "wof:placetype":"locality"
},
  "geometry": {"coordinates":[122.01658999999999,39.63427],"type":"Point"}
}