{
  "type": "Feature",
  "properties": {
    "gn:admin1_code":"18",
    "gn:asciiname":"Bojizhai",
    "gn:country_code":"CN",
    "gn:dem":1350,
    "gn:feature_class":"P",
    "gn:feature_code":"PPL",
    "gn:name":"Bojizhai",
    "gn:population":0,
    "gn:timezone":"Asia/Shanghai",
    "iso:country":"CN",
    "name:zho_x_preferred":[
        "\u7c38\u7b95\u5be8"
    ],
    "wof:name":"Bojizhai",
    "wof:placetype":"locality"
},
  "geometry": {"coordinates":[105.56399999999999,25.5202],"type":"Point"}
}