{
  "type": "Feature",
  "properties": {
    "gn:admin1_code":"6.0",
    "gn:asciiname":"Tangjiakatan",
    "gn:country_code":"CN",
    "gn:dem":1930,
    "gn:feature_class":"P",
    "gn:feature_code":"PPL",
    "gn:name":"Tangjiakatan",
    "gn:population":0,
    "gn:timezone":"Asia/Shanghai",
    "iso:country":"CN",
    "name:und_x_variant":[
        "\u5510\u52a0\u5361\u6ee9"
    ],
    "wof:name":"Tangjiakatan",
    "wof:placetype":"locality"
},
  "geometry": {"coordinates":[102.23554,35.88357],"type":"Point"}
}