{
  "type": "Feature",
  "properties": {
    "gn:admin1_code":"3.0",
    "gn:asciiname":"Niulingdi",
    "gn:country_code":"CN",
    "gn:dem":429,
    "gn:feature_class":"P",
    "gn:feature_code":"PPL",
    "gn:name":"Niulingdi",
    "gn:population":0,
    "gn:timezone":"Asia/Shanghai",
    "iso:country":"CN",
    "name:zho_x_preferred":[
        "\u725b\u5cad\u5e95"
    ],
    "wof:name":"Niulingdi",
    "wof:placetype":"locality"
},
  "geometry": {"coordinates":[118.30513999999999,28.13452],"type":"Point"}
}