{
  "type": "Feature",
  "properties": {
    "gn:admin1_code":"5.0",
    "gn:asciiname":"Guozijing",
    "gn:country_code":"CN",
    "gn:dem":138,
    "gn:feature_class":"P",
    "gn:feature_code":"PPL",
    "gn:name":"Guozijing",
    "gn:population":0,
    "gn:timezone":"Asia/Shanghai",
    "iso:country":"CN",
    "name:zho_x_preferred":[
        "\u8fc7\u5b57\u4e95"
    ],
    "wof:name":"Guozijing",
    "wof:placetype":"locality"
},
  "geometry": {"coordinates":[123.66903000000001,44.88815],"type":"Point"}
}