{
  "type": "Feature",
  "properties": {
    "gn:admin1_code":"15.0",
    "gn:asciiname":"Si'erzhang",
    "gn:country_code":"CN",
    "gn:dem":1470,
    "gn:feature_class":"P",
    "gn:feature_code":"PPL",
    "gn:name":"Si\u2019erzhang",
    "gn:population":0,
    "gn:timezone":"Asia/Shanghai",
    "iso:country":"CN",
    "name:und_x_variant":[
        "Si\u2019erzhang",
        "\u5bfa\u513f\u638c"
    ],
    "wof:name":"Si'erzhang",
    "wof:placetype":"locality"
},
  "geometry": {"coordinates":[107.54964,36.75148],"type":"Point"}
}