{
  "type": "Feature",
  "properties": {
    "gn:admin1_code":"32.0",
    "gn:asciiname":"Dingjiacun",
    "gn:country_code":"CN",
    "gn:dem":2276,
    "gn:feature_class":"P",
    "gn:feature_code":"PPL",
    "gn:name":"Dingjiacun",
    "gn:population":0,
    "gn:timezone":"Asia/Shanghai",
    "iso:country":"CN",
    "name:zho_x_preferred":[
        "\u4e01\u5bb6\u6751"
    ],
    "wof:name":"Dingjiacun",
    "wof:placetype":"locality"
},
  "geometry": {"coordinates":[102.12466999999999,27.15476],"type":"Point"}
}