{
  "type": "Feature",
  "properties": {
    "gn:admin1_code":"20.0",
    "gn:asciiname":"Yihaojing",
    "gn:country_code":"CN",
    "gn:dem":748,
    "gn:feature_class":"P",
    "gn:feature_code":"PPL",
    "gn:name":"Yihaojing",
    "gn:population":0,
    "gn:timezone":"Asia/Shanghai",
    "iso:country":"CN",
    "name:zho_x_preferred":[
        "\u4e00\u53f7\u4e95"
    ],
    "wof:name":"Yihaojing",
    "wof:placetype":"locality"
},
  "geometry": {"coordinates":[119.51998,48.56738],"type":"Point"}
}