{
  "type": "Feature",
  "properties": {
    "gn:admin1_code":"32.0",
    "gn:asciiname":"Pingdong",
    "gn:country_code":"CN",
    "gn:dem":366,
    "gn:feature_class":"P",
    "gn:feature_code":"PPL",
    "gn:name":"Pingdong",
    "gn:population":0,
    "gn:timezone":"Asia/Shanghai",
    "iso:country":"CN",
    "name:ceb_x_preferred":[
        "Pingdong"
    ],
    "name:swe_x_preferred":[
        "Pingdong"
    ],
    "name:zho_x_preferred":[
        "\u5e73\u6d1e"
    ],
    "wof:name":"Pingdong",
    "wof:placetype":"locality"
},
  "geometry": {"coordinates":[107.38500000000001,31.1748],"type":"Point"}
}