{
  "type": "Feature",
  "properties": {
    "gn:admin1_code":"1.0",
    "gn:asciiname":"Tuloucun",
    "gn:country_code":"CN",
    "gn:dem":37,
    "gn:feature_class":"P",
    "gn:feature_code":"PPL",
    "gn:name":"Tuloucun",
    "gn:population":0,
    "gn:timezone":"Asia/Shanghai",
    "iso:country":"CN",
    "name:zho_x_preferred":[
        "\u571f\u697c\u6751"
    ],
    "wof:name":"Tuloucun",
    "wof:placetype":"locality"
},
  "geometry": {"coordinates":[116.03149999999999,33.75192],"type":"Point"}
}