{
  "type": "Feature",
  "properties": {
    "gn:admin1_code":"12.0",
    "gn:asciiname":"Laotanjiachang",
    "gn:country_code":"CN",
    "gn:dem":31,
    "gn:feature_class":"P",
    "gn:feature_code":"PPL",
    "gn:name":"Laotanjiachang",
    "gn:population":0,
    "gn:timezone":"Asia/Shanghai",
    "iso:country":"CN",
    "name:zho_x_preferred":[
        "Laotanjiachang"
    ],
    "name:zho_x_variant":[
        "\u8001\u8c2d\u5bb6\u573a"
    ],
    "wof:name":"Laotanjiachang",
    "wof:placetype":"locality"
},
  "geometry": {"coordinates":[112.98791,30.20421],"type":"Point"}
}