{
  "type": "Feature",
  "properties": {
    "gn:admin1_code":"32.0",
    "gn:asciiname":"Youzhaping",
    "gn:country_code":"CN",
    "gn:dem":822,
    "gn:feature_class":"P",
    "gn:feature_code":"PPL",
    "gn:name":"Youzhaping",
    "gn:population":0,
    "gn:timezone":"Asia/Shanghai",
    "iso:country":"CN",
    "name:zho_x_preferred":[
        "\u6cb9\u70b8\u576a"
    ],
    "wof:name":"Youzhaping",
    "wof:placetype":"locality"
},
  "geometry": {"coordinates":[104.86799999999999,28.0671],"type":"Point"}
}