{
  "type": "Feature",
  "properties": {
    "gn:admin1_code":"15.0",
    "gn:asciiname":"Luojiabu",
    "gn:country_code":"CN",
    "gn:dem":1928,
    "gn:feature_class":"P",
    "gn:feature_code":"PPL",
    "gn:name":"Luojiabu",
    "gn:population":0,
    "gn:timezone":"Asia/Shanghai",
    "iso:country":"CN",
    "name:zho_x_preferred":[
        "\u7f57\u5bb6\u5821"
    ],
    "wof:name":"Luojiabu",
    "wof:placetype":"locality"
},
  "geometry": {"coordinates":[103.173,35.5669],"type":"Point"}
}