{
  "type": "Feature",
  "properties": {
    "gn:admin1_code":"11.0",
    "gn:asciiname":"Xingongqiao",
    "gn:country_code":"CN",
    "gn:dem":873,
    "gn:feature_class":"P",
    "gn:feature_code":"PPL",
    "gn:name":"Xingongqiao",
    "gn:population":0,
    "gn:timezone":"Asia/Shanghai",
    "iso:country":"CN",
    "name:zho_x_preferred":[
        "\u65b0\u62f1\u6865"
    ],
    "wof:name":"Xingongqiao",
    "wof:placetype":"locality"
},
  "geometry": {"coordinates":[109.62469,29.43641],"type":"Point"}
}