{
  "type": "Feature",
  "properties": {
    "gn:admin1_code":"5.0",
    "gn:asciiname":"Pianliantun",
    "gn:country_code":"CN",
    "gn:dem":256,
    "gn:feature_class":"P",
    "gn:feature_code":"PPL",
    "gn:name":"Pianliantun",
    "gn:population":0,
    "gn:timezone":"Asia/Shanghai",
    "iso:country":"CN",
    "name:zho_x_preferred":[
        "\u504f\u8138\u5c6f"
    ],
    "wof:name":"Pianliantun",
    "wof:placetype":"locality"
},
  "geometry": {"coordinates":[125.44946000000002,43.36394],"type":"Point"}
}