{
  "type": "Feature",
  "properties": {
    "gn:admin1_code":"3.0",
    "gn:asciiname":"Longshang",
    "gn:country_code":"CN",
    "gn:dem":183,
    "gn:feature_class":"P",
    "gn:feature_code":"PPL",
    "gn:name":"Longshang",
    "gn:population":0,
    "gn:timezone":"Asia/Shanghai",
    "iso:country":"CN",
    "name:und_x_variant":[
        "\u9f99\u4e0a"
    ],
    "wof:name":"Longshang",
    "wof:placetype":"locality"
},
  "geometry": {"coordinates":[115.50405000000001,25.82296],"type":"Point"}
}