{
  "type": "Feature",
  "properties": {
    "gn:admin1_code":"32.0",
    "gn:asciiname":"Huanglianshan",
    "gn:country_code":"CN",
    "gn:dem":1348,
    "gn:feature_class":"P",
    "gn:feature_code":"PPL",
    "gn:name":"Huanglianshan",
    "gn:population":0,
    "gn:timezone":"Asia/Shanghai",
    "iso:country":"CN",
    "name:zho_x_preferred":[
        "\u9ec4\u8fde\u5c71"
    ],
    "wof:name":"Huanglianshan",
    "wof:placetype":"locality"
},
  "geometry": {"coordinates":[103.62795,28.84678],"type":"Point"}
}