{
  "type": "Feature",
  "properties": {
    "gn:admin1_code":"14",
    "gn:asciiname":"Zonggaqiunu",
    "gn:country_code":"CN",
    "gn:dem":3873,
    "gn:feature_class":"P",
    "gn:feature_code":"PPL",
    "gn:name":"Zonggaqiunu",
    "gn:population":0,
    "gn:timezone":"Asia/Urumqi",
    "iso:country":"CN",
    "name:zho_x_preferred":[
        "\u5b97\u560e\u6c42\u5974"
    ],
    "wof:name":"Zonggaqiunu",
    "wof:placetype":"locality"
},
  "geometry": {"coordinates":[89.85339999999999,29.3263],"type":"Point"}
}