{
  "type": "Feature",
  "properties": {
    "gn:admin1_code":"25.0",
    "gn:asciiname":"Zhongbuhou",
    "gn:country_code":"CN",
    "gn:dem":51,
    "gn:feature_class":"P",
    "gn:feature_code":"PPL",
    "gn:name":"Zhongbuhou",
    "gn:population":0,
    "gn:timezone":"Asia/Shanghai",
    "iso:country":"CN",
    "name:zho_x_preferred":[
        "\u4e2d\u57e0\u540e"
    ],
    "wof:name":"Zhongbuhou",
    "wof:placetype":"locality"
},
  "geometry": {"coordinates":[120.6264,36.78989],"type":"Point"}
}