{
  "type": "Feature",
  "properties": {
    "gn:admin1_code":"30.0",
    "gn:asciiname":"Tanggangcun",
    "gn:country_code":"CN",
    "gn:dem":76,
    "gn:feature_class":"P",
    "gn:feature_code":"PPL",
    "gn:name":"Tanggangcun",
    "gn:population":0,
    "gn:timezone":"Asia/Shanghai",
    "iso:country":"CN",
    "name:zho_x_preferred":[
        "\u5858\u5c97\u6751"
    ],
    "wof:name":"Tanggangcun",
    "wof:placetype":"locality"
},
  "geometry": {"coordinates":[111.99823000000001,24.01627],"type":"Point"}
}