{
  "type": "Feature",
  "properties": {
    "gn:admin1_code":"11",
    "gn:asciiname":"Kuaixi",
    "gn:country_code":"CN",
    "gn:dem":175,
    "gn:feature_class":"P",
    "gn:feature_code":"PPL",
    "gn:name":"Kuaixi",
    "gn:population":0,
    "gn:timezone":"Asia/Shanghai",
    "iso:country":"CN",
    "name:zho_x_preferred":[
        "\u5feb\u6eaa"
    ],
    "wof:name":"Kuaixi",
    "wof:placetype":"locality"
},
  "geometry": {"coordinates":[111.84058,27.56181],"type":"Point"}
}