{
  "type": "Feature",
  "properties": {
    "gn:admin1_code":"15.0",
    "gn:asciiname":"Luojiahe",
    "gn:country_code":"CN",
    "gn:dem":1156,
    "gn:feature_class":"P",
    "gn:feature_code":"PPL",
    "gn:name":"Luojiahe",
    "gn:population":0,
    "gn:timezone":"Asia/Shanghai",
    "iso:country":"CN",
    "name:und_x_variant":[
        "\u7f57\u5bb6\u6cb3"
    ],
    "wof:name":"Luojiahe",
    "wof:placetype":"locality"
},
  "geometry": {"coordinates":[105.68671000000001,33.46674],"type":"Point"}
}