{
  "type": "Feature",
  "properties": {
    "gn:admin1_code":"11.0",
    "gn:asciiname":"Xinpu",
    "gn:country_code":"CN",
    "gn:dem":179,
    "gn:feature_class":"P",
    "gn:feature_code":"PPLA4",
    "gn:name":"Xinpu",
    "gn:population":0,
    "gn:timezone":"Asia/Shanghai",
    "iso:country":"CN",
    "name:ceb_x_preferred":[
        "Xinpu"
    ],
    "name:deu_x_preferred":[
        "Xinpu"
    ],
    "name:fra_x_preferred":[
        "Xinpu"
    ],
    "name:swe_x_preferred":[
        "Xinpu"
    ],
    "name:und_x_variant":[
        "\u65b0\u94fa",
        "Xinpu Xiang",
        "\u65b0\u94fa\u4e61"
    ],
    "wof:name":"Xinpu",
    "wof:placetype":"locality"
},
  "geometry": {"coordinates":[111.37815000000001,29.68135],"type":"Point"}
}