{
  "type": "Feature",
  "properties": {
    "gn:country":"CN",
    "gn:fcode":"PPLA3",
    "gn:pop":55186,
    "iso:country":"CN",
    "name:rus_x_preferred":[
        "\u0411\u0430\u044f\u043d"
    ],
    "name:unk_x_variant":[
        "Pa-yen-su-su"
    ],
    "name:zho_x_preferred":[
        "\u5df4\u5f66"
    ],
    "name:zho_x_variant":[
        "\u5df4\u5f66\u9547"
    ],
    "qs:name":"Bayan",
    "qs:photos_9r":0,
    "qs:photos_sr":0,
    "qs:pop_sr":"8",
    "wd:wordcount":488,
    "wof:name":"Bayan",
    "wof:placetype":"locality",
    "wof:population":55186
},
  "geometry": {"coordinates":[127.40000000000001,46.08333],"type":"Point"}
}