{
  "type": "Feature",
  "properties": {
    "gn:country":"CN",
    "gn:fcode":"PPLA3",
    "gn:population":55186,
    "iso:country":"CN",
    "name:ara_x_preferred":[
        "\u0627\u0644\u0628\u064a\u0627\u0646"
    ],
    "name:aze_x_preferred":[
        "Bayan"
    ],
    "name:cat_x_preferred":[
        "Bayan"
    ],
    "name:ceb_x_preferred":[
        "Bayan"
    ],
    "name:deu_x_preferred":[
        "Bayan"
    ],
    "name:fra_x_preferred":[
        "Bayan"
    ],
    "name:glg_x_preferred":[
        "Baian"
    ],
    "name:ind_x_preferred":[
        "Bayan"
    ],
    "name:ita_x_preferred":[
        "Bayan"
    ],
    "name:jpn_x_preferred":[
        "\u30d0\u30e4\u30f3"
    ],
    "name:kat_x_preferred":[
        "\u10d1\u10d0\u10d8\u10d0\u10dc\u10d8"
    ],
    "name:kaz_x_preferred":[
        "\u0411\u0430\u044f\u043d"
    ],
    "name:mlg_x_preferred":[
        "Bayan"
    ],
    "name:nld_x_preferred":[
        "Bayan"
    ],
    "name:nor_x_preferred":[
        "Bayan"
    ],
    "name:rus_x_preferred":[
        "\u0411\u0430\u044f\u043d"
    ],
    "name:swe_x_preferred":[
        "Bayan"
    ],
    "name:tgl_x_preferred":[
        "Bayan"
    ],
    "name:tur_x_preferred":[
        "Bayan"
    ],
    "name:ukr_x_preferred":[
        "\u0411\u0430\u044f\u043d"
    ],
    "name:und_x_variant":[
        "Pa-yen-su-su"
    ],
    "name:zho_x_preferred":[
        "\u5df4\u5f66"
    ],
    "name:zho_x_variant":[
        "\u5df4\u5f66\u9547"
    ],
    "qs:name":"Bayan",
    "qs:photos_9r":0,
    "qs:photos_sr":0,
    "qs:pop_sr":"8",
    "wd:wordcount":488,
    "wof:name":"Bayan",
    "wof:placetype":"locality",
    "wof:population":55186
},
  "geometry": {"coordinates":[127.40000000000001,46.08333],"type":"Point"}
}