{
  "type": "Feature",
  "properties": {
    "gn:admin1_code":"29.0",
    "gn:asciiname":"Jinwu",
    "gn:country_code":"CN",
    "gn:dem":2118,
    "gn:feature_class":"P",
    "gn:feature_code":"PPL",
    "gn:name":"Jinwu",
    "gn:population":0,
    "gn:timezone":"Asia/Shanghai",
    "iso:country":"CN",
    "name:und_x_variant":[
        "\u91d1\u4e4c"
    ],
    "wof:name":"Jinwu",
    "wof:placetype":"locality"
},
  "geometry": {"coordinates":[102.36792,25.87726],"type":"Point"}
}