{
  "type": "Feature",
  "properties": {
    "gn:admin1_code":"25.0",
    "gn:asciiname":"Daxucun",
    "gn:country_code":"CN",
    "gn:dem":12,
    "gn:feature_class":"P",
    "gn:feature_code":"PPL",
    "gn:name":"Daxucun",
    "gn:population":0,
    "gn:timezone":"Asia/Shanghai",
    "iso:country":"CN",
    "name:und_x_variant":[
        "Daxu"
    ],
    "name:zho_x_preferred":[
        "\u5927\u5f90\u6751"
    ],
    "name:zho_x_variant":[
        "\u5927\u5f90"
    ],
    "wof:name":"Daxucun",
    "wof:placetype":"locality"
},
  "geometry": {"coordinates":[117.29992,37.81908],"type":"Point"}
}