{
  "type": "Feature",
  "properties": {
    "gn:admin1_code":"7.0",
    "gn:asciiname":"Shantou",
    "gn:country_code":"CN",
    "gn:dem":402,
    "gn:feature_class":"P",
    "gn:feature_code":"PPL",
    "gn:name":"Shantou",
    "gn:population":0,
    "gn:timezone":"Asia/Shanghai",
    "iso:country":"CN",
    "name:rus_x_preferred":[
        "\u0428\u0430\u043d\u044c\u0442\u043e\u0443"
    ],
    "name:zho_x_preferred":[
        "\u5c71\u5934"
    ],
    "wof:name":"Shantou",
    "wof:placetype":"locality"
},
  "geometry": {"coordinates":[118.26708000000001,27.19101],"type":"Point"}
}