{
  "type": "Feature",
  "properties": {
    "gn:admin1_code":"33.0",
    "gn:asciiname":"Laolingou",
    "gn:country_code":"CN",
    "gn:dem":1466,
    "gn:feature_class":"P",
    "gn:feature_code":"PPL",
    "gn:name":"Laolingou",
    "gn:population":0,
    "gn:timezone":"Asia/Shanghai",
    "iso:country":"CN",
    "name:zho_x_preferred":[
        "\u8001\u6797\u6c9f"
    ],
    "wof:name":"Laolingou",
    "wof:placetype":"locality"
},
  "geometry": {"coordinates":[109.60679,31.70592000000001],"type":"Point"}
}