{
  "type": "Feature",
  "properties": {
    "gn:admin1_code":"4.0",
    "gn:asciiname":"Litangcun",
    "gn:country_code":"CN",
    "gn:dem":18,
    "gn:feature_class":"P",
    "gn:feature_code":"PPL",
    "gn:name":"Litangcun",
    "gn:population":0,
    "gn:timezone":"Asia/Shanghai",
    "iso:country":"CN",
    "name:zho_x_preferred":[
        "\u674e\u5858\u6751"
    ],
    "wof:name":"Litangcun",
    "wof:placetype":"locality"
},
  "geometry": {"coordinates":[118.40271,33.54431],"type":"Point"}
}