{
  "type": "Feature",
  "properties": {
    "gn:admin1_code":"7",
    "gn:asciiname":"Xinyang",
    "gn:country_code":"CN",
    "gn:dem":298,
    "gn:feature_class":"P",
    "gn:feature_code":"PPLA4",
    "gn:name":"Xinyang",
    "gn:population":0,
    "gn:timezone":"Asia/Shanghai",
    "iso:country":"CN",
    "name:und_x_variant":[
        "Xinyang Zhen"
    ],
    "name:zho_x_preferred":[
        "\u65b0\u9633"
    ],
    "name:zho_x_variant":[
        "\u65b0\u9633\u9547"
    ],
    "wof:name":"Xinyang",
    "wof:placetype":"locality"
},
  "geometry": {"coordinates":[117.94488,26.05119],"type":"Point"}
}