{
  "type": "Feature",
  "properties": {
    "gn:admin1_code":"19.0",
    "gn:asciiname":"Chijiazhangzi",
    "gn:country_code":"CN",
    "gn:dem":523,
    "gn:feature_class":"P",
    "gn:feature_code":"PPL",
    "gn:name":"Chijiazhangzi",
    "gn:population":0,
    "gn:timezone":"Asia/Shanghai",
    "iso:country":"CN",
    "name:zho_x_preferred":[
        "\u8fdf\u5bb6\u6756\u5b50"
    ],
    "wof:name":"Chijiazhangzi",
    "wof:placetype":"locality"
},
  "geometry": {"coordinates":[119.94342,41.76168],"type":"Point"}
}