{
  "type": "Feature",
  "properties": {
    "gn:admin1_code":"18.0",
    "gn:asciiname":"Wengbao",
    "gn:country_code":"CN",
    "gn:dem":691,
    "gn:feature_class":"P",
    "gn:feature_code":"PPL",
    "gn:name":"Wengbao",
    "gn:population":0,
    "gn:timezone":"Asia/Shanghai",
    "iso:country":"CN",
    "name:zho_x_preferred":[
        "\u7fc1\u4fdd"
    ],
    "wof:name":"Wengbao",
    "wof:placetype":"locality"
},
  "geometry": {"coordinates":[107.756,26.3882],"type":"Point"}
}