{
  "type": "Feature",
  "properties": {
    "gn:admin1_code":"15.0",
    "gn:asciiname":"Huangjiashan",
    "gn:country_code":"CN",
    "gn:dem":1273,
    "gn:feature_class":"P",
    "gn:feature_code":"PPL",
    "gn:name":"Huangjiashan",
    "gn:population":0,
    "gn:timezone":"Asia/Shanghai",
    "iso:country":"CN",
    "name:und_x_variant":[
        "\u9ec4\u5bb6\u5c71"
    ],
    "wof:name":"Huangjiashan",
    "wof:placetype":"locality"
},
  "geometry": {"coordinates":[105.74298,33.83828],"type":"Point"}
}