{
  "type": "Feature",
  "properties": {
    "gn:admin1_code":"11.0",
    "gn:asciiname":"Shijiagou",
    "gn:country_code":"CN",
    "gn:dem":543,
    "gn:feature_class":"P",
    "gn:feature_code":"PPL",
    "gn:name":"Shijiagou",
    "gn:population":0,
    "gn:timezone":"Asia/Shanghai",
    "iso:country":"CN",
    "name:zho_x_preferred":[
        "Shijiagou"
    ],
    "name:zho_x_variant":[
        "\u53f2\u5bb6\u6c9f"
    ],
    "wof:name":"Shijiagou",
    "wof:placetype":"locality"
},
  "geometry": {"coordinates":[111.01452999999999,29.6164],"type":"Point"}
}