{
  "type": "Feature",
  "properties": {
    "gn:admin1_code":"30",
    "gn:asciiname":"Longhua",
    "gn:country_code":"CN",
    "gn:dem":26,
    "gn:feature_class":"P",
    "gn:feature_code":"PPLA4",
    "gn:name":"Longhua",
    "gn:population":0,
    "gn:timezone":"Asia/Shanghai",
    "iso:country":"CN",
    "name:und_x_variant":[
        "Lung-hua",
        "Longhua",
        "Longhua Zhen",
        "\u9f99\u534e\u9547"
    ],
    "name:zho_x_preferred":[
        "\u9f99\u534e"
    ],
    "wof:name":"Longhua",
    "wof:placetype":"locality"
},
  "geometry": {"coordinates":[114.10176,23.19187],"type":"Point"}
}