{
  "type": "Feature",
  "properties": {
    "gn:admin1_code":"3",
    "gn:asciiname":"Yuanfengbei",
    "gn:country_code":"CN",
    "gn:dem":243,
    "gn:feature_class":"P",
    "gn:feature_code":"PPL",
    "gn:name":"Yuanfengbei",
    "gn:population":0,
    "gn:timezone":"Asia/Shanghai",
    "iso:country":"CN",
    "name:zho_x_preferred":[
        "\u82ab\u4e30\u80cc"
    ],
    "wof:name":"Yuanfengbei",
    "wof:placetype":"locality"
},
  "geometry": {"coordinates":[114.995,25.6557],"type":"Point"}
}