{
  "type": "Feature",
  "properties": {
    "gn:admin1_code":"8.0",
    "gn:asciiname":"Yonghengcun",
    "gn:country_code":"CN",
    "gn:dem":162,
    "gn:feature_class":"P",
    "gn:feature_code":"PPL",
    "gn:name":"Yonghengcun",
    "gn:population":0,
    "gn:timezone":"Asia/Shanghai",
    "iso:country":"CN",
    "name:zho_x_preferred":[
        "\u6c38\u6052\u6751"
    ],
    "wof:name":"Yonghengcun",
    "wof:placetype":"locality"
},
  "geometry": {"coordinates":[127.12233999999999,46.84892],"type":"Point"}
}