{
  "type": "Feature",
  "properties": {
    "gn:admin1_code":"32.0",
    "gn:asciiname":"Youhuajing",
    "gn:country_code":"CN",
    "gn:dem":471,
    "gn:feature_class":"P",
    "gn:feature_code":"PPL",
    "gn:name":"Youhuajing",
    "gn:population":0,
    "gn:timezone":"Asia/Shanghai",
    "iso:country":"CN",
    "name:zho_x_preferred":[
        "\u6cb9\u82b1\u4e95"
    ],
    "wof:name":"Youhuajing",
    "wof:placetype":"locality"
},
  "geometry": {"coordinates":[104.31443,28.74194],"type":"Point"}
}