{
  "type": "Feature",
  "properties": {
    "gn:admin1_code":"32",
    "gn:asciiname":"Fentingzi",
    "gn:country_code":"CN",
    "gn:dem":1280,
    "gn:feature_class":"P",
    "gn:feature_code":"PPL",
    "gn:name":"Fentingzi",
    "gn:population":0,
    "gn:timezone":"Asia/Shanghai",
    "iso:country":"CN",
    "name:zho_x_preferred":[
        "\u575f\u4ead\u5b50"
    ],
    "wof:name":"Fentingzi",
    "wof:placetype":"locality"
},
  "geometry": {"coordinates":[107.59,32.2408],"type":"Point"}
}