{
  "type": "Feature",
  "properties": {
    "gn:admin1_code":"32.0",
    "gn:asciiname":"Taojiagou",
    "gn:country_code":"CN",
    "gn:dem":1644,
    "gn:feature_class":"P",
    "gn:feature_code":"PPL",
    "gn:name":"Taojiagou",
    "gn:population":0,
    "gn:timezone":"Asia/Shanghai",
    "iso:country":"CN",
    "name:zho_x_preferred":[
        "\u6843\u5bb6\u6c9f"
    ],
    "wof:name":"Taojiagou",
    "wof:placetype":"locality"
},
  "geometry": {"coordinates":[103.434,27.9934],"type":"Point"}
}