{
  "type": "Feature",
  "properties": {
    "gn:admin1_code":"3",
    "gn:asciiname":"Shangping",
    "gn:country_code":"CN",
    "gn:dem":258,
    "gn:feature_class":"P",
    "gn:feature_code":"PPL",
    "gn:name":"Shangping",
    "gn:population":0,
    "gn:timezone":"Asia/Shanghai",
    "iso:country":"CN",
    "wof:name":"Shangping",
    "wof:placetype":"locality"
},
  "geometry": {"coordinates":[114.06999999999999,25.64611],"type":"Point"}
}