{
  "type": "Feature",
  "properties": {
    "gn:admin1_code":"30",
    "gn:asciiname":"Liangcunzai",
    "gn:country_code":"CN",
    "gn:dem":51,
    "gn:feature_class":"P",
    "gn:feature_code":"PPL",
    "gn:name":"Liangcunzai",
    "gn:population":0,
    "gn:timezone":"Asia/Urumqi",
    "iso:country":"CN",
    "name:zho_x_preferred":[
        "\u6881\u6751\u4ed4"
    ],
    "wof:name":"Liangcunzai",
    "wof:placetype":"locality"
},
  "geometry": {"coordinates":[110.43131,20.49864],"type":"Point"}
}