{
  "type": "Feature",
  "properties": {
    "gn:admin1_code":"15.0",
    "gn:asciiname":"Chibali",
    "gn:country_code":"CN",
    "gn:dem":2210,
    "gn:feature_class":"P",
    "gn:feature_code":"PPL",
    "gn:name":"Chibali",
    "gn:population":0,
    "gn:timezone":"Asia/Shanghai",
    "iso:country":"CN",
    "name:und_x_variant":[
        "\u6c60\u575d\u91cc"
    ],
    "wof:name":"Chibali",
    "wof:placetype":"locality"
},
  "geometry": {"coordinates":[105.26326,33.56231],"type":"Point"}
}