{
  "type": "Feature",
  "properties": {
    "gn:admin1_code":"11.0",
    "gn:asciiname":"Dazhouyan",
    "gn:country_code":"CN",
    "gn:dem":692,
    "gn:feature_class":"P",
    "gn:feature_code":"PPL",
    "gn:name":"Dazhouyan",
    "gn:population":0,
    "gn:timezone":"Asia/Shanghai",
    "iso:country":"CN",
    "name:zho_x_preferred":[
        "\u5927\u6d32\u5830"
    ],
    "wof:name":"Dazhouyan",
    "wof:placetype":"locality"
},
  "geometry": {"coordinates":[110.62168,29.20315],"type":"Point"}
}