{
  "type": "Feature",
  "properties": {
    "gn:admin1_code":"3.0",
    "gn:asciiname":"Fengmujiang",
    "gn:country_code":"CN",
    "gn:dem":191,
    "gn:feature_class":"P",
    "gn:feature_code":"PPL",
    "gn:name":"Fengmujiang",
    "gn:population":0,
    "gn:timezone":"Asia/Shanghai",
    "iso:country":"CN",
    "name:und_x_variant":[
        "\u67ab\u6728\u6c5f"
    ],
    "wof:name":"Fengmujiang",
    "wof:placetype":"locality"
},
  "geometry": {"coordinates":[114.15951,27.93317],"type":"Point"}
}