{
  "type": "Feature",
  "properties": {
    "gn:admin1_code":"26",
    "gn:asciiname":"Hetouli",
    "gn:country_code":"CN",
    "gn:dem":379,
    "gn:feature_class":"P",
    "gn:feature_code":"PPL",
    "gn:name":"Hetouli",
    "gn:population":0,
    "gn:timezone":"Asia/Shanghai",
    "iso:country":"CN",
    "name:zho_x_preferred":[
        "\u6cb3\u5934\u674e"
    ],
    "name:zho_x_variant":[
        "\u6cb3\u5934\u91cc"
    ],
    "wof:name":"Hetouli",
    "wof:placetype":"locality"
},
  "geometry": {"coordinates":[108.90204,34.49910999999999],"type":"Point"}
}