{
  "type": "Feature",
  "properties": {
    "gn:admin1_code":"30",
    "gn:asciiname":"Shuangyucheng",
    "gn:country_code":"CN",
    "gn:dem":12,
    "gn:feature_class":"P",
    "gn:feature_code":"PPL",
    "gn:name":"Shuangyucheng",
    "gn:population":0,
    "gn:timezone":"Asia/Shanghai",
    "iso:country":"CN",
    "name:zho_x_preferred":[
        "\u53cc\u9c7c\u57ce"
    ],
    "wof:name":"Shuangyucheng",
    "wof:placetype":"locality"
},
  "geometry": {"coordinates":[111.61306,21.56944],"type":"Point"}
}