{
  "type": "Feature",
  "properties": {
    "gn:admin1_code":"7.0",
    "gn:asciiname":"Shiliuyang",
    "gn:country_code":"CN",
    "gn:dem":699,
    "gn:feature_class":"P",
    "gn:feature_code":"PPL",
    "gn:name":"Shiliuyang",
    "gn:population":0,
    "gn:timezone":"Asia/Shanghai",
    "iso:country":"CN",
    "name:zho_x_preferred":[
        "\u77f3\u69b4\u6d0b"
    ],
    "wof:name":"Shiliuyang",
    "wof:placetype":"locality"
},
  "geometry": {"coordinates":[118.94304,26.25231],"type":"Point"}
}