{
  "type": "Feature",
  "properties": {
    "gn:admin1_code":"30",
    "gn:asciiname":"Jinpancun",
    "gn:country_code":"CN",
    "gn:dem":28,
    "gn:feature_class":"P",
    "gn:feature_code":"PPL",
    "gn:name":"Jinpancun",
    "gn:population":0,
    "gn:timezone":"Asia/Urumqi",
    "iso:country":"CN",
    "name:und_x_variant":[
        "Jinpan",
        "Jinpancun"
    ],
    "name:zho_x_preferred":[
        "Chin-p\u2019an"
    ],
    "name:zho_x_variant":[
        "\u9526\u76d8\u6751"
    ],
    "wof:name":"Jinpancun",
    "wof:placetype":"locality"
},
  "geometry": {"coordinates":[109.77218000000001,20.93209],"type":"Point"}
}