{
  "type": "Feature",
  "properties": {
    "gn:admin1_code":"29.0",
    "gn:asciiname":"Baimuku",
    "gn:country_code":"CN",
    "gn:dem":2214,
    "gn:feature_class":"P",
    "gn:feature_code":"PPL",
    "gn:name":"Baimuku",
    "gn:population":0,
    "gn:timezone":"Asia/Shanghai",
    "iso:country":"CN",
    "name:zho_x_preferred":[
        "\u67cf\u6728\u5e93"
    ],
    "wof:name":"Baimuku",
    "wof:placetype":"locality"
},
  "geometry": {"coordinates":[100.11499999999999,25.3203],"type":"Point"}
}