{
  "type": "Feature",
  "properties": {
    "gn:admin1_code":"19",
    "gn:asciiname":"Fu'an",
    "gn:country_code":"CN",
    "gn:dem":15,
    "gn:feature_class":"P",
    "gn:feature_code":"PPLA4",
    "gn:name":"Fu\u2019an",
    "gn:population":0,
    "gn:timezone":"Asia/Shanghai",
    "iso:country":"CN",
    "name:ara_x_preferred":[
        "\u0641\u0648\u0627\u0646"
    ],
    "name:cdo_x_preferred":[
        "H\u00f3k-\u0103ng"
    ],
    "name:deu_x_preferred":[
        "Fu\u2019an"
    ],
    "name:fas_x_preferred":[
        "\u0641\u0648\u0627\u0646"
    ],
    "name:fra_x_preferred":[
        "Fu'an"
    ],
    "name:hak_x_preferred":[
        "Fuk-\u00f4n-s\u1e73"
    ],
    "name:ita_x_preferred":[
        "Fu'an"
    ],
    "name:jpn_x_preferred":[
        "\u798f\u5b89\u5e02"
    ],
    "name:kik_x_preferred":[
        "Fu'an"
    ],
    "name:kor_x_preferred":[
        "\ud478\uc548\uc2dc"
    ],
    "name:mwl_x_preferred":[
        "Fu'an"
    ],
    "name:nor_x_preferred":[
        "Fu'an"
    ],
    "name:pam_x_preferred":[
        "Fu'an"
    ],
    "name:pnb_x_preferred":[
        "\u0641\u0648\u0622\u0646"
    ],
    "name:rus_x_preferred":[
        "\u0424\u0443\u0430\u043d\u044c"
    ],
    "name:spa_x_preferred":[
        "Fu'an"
    ],
    "name:swe_x_preferred":[
        "Fu'an"
    ],
    "name:und_x_variant":[
        "Teng-ao-tao",
        "T\u2019eng-ao-p\u2019u-ts\u2019un",
        "T\u2019eng-ao-chen",
        "Teng\u2019aopu",
        "T\u2019eng-ao-pao",
        "Teng\u2019ao"
    ],
    "name:urd_x_preferred":[
        "\u0641\u0648\u0622\u0646"
    ],
    "name:vie_x_preferred":[
        "Ph\u00fac An"
    ],
    "name:war_x_preferred":[
        "Fu'an"
    ],
    "name:zho_x_preferred":[
        "\u798f\u5b89"
    ],
    "name:zho_x_variant":[
        "Teng\u2019ao Zhen",
        "\u817e\u9ccc\u9547",
        "Fu\u2019an",
        "\u798f\u5b89\u5e02"
    ],
    "wof:name":"Fu'an",
    "wof:placetype":"locality"
},
  "geometry": {"coordinates":[122.83056000000001,41.075],"type":"Point"}
}