{
  "type": "Feature",
  "properties": {
    "gn:admin1_code":"19",
    "gn:asciiname":"Fu'an",
    "gn:country_code":"CN",
    "gn:dem":15,
    "gn:feature_class":"P",
    "gn:feature_code":"PPLA4",
    "gn:name":"Fu\u2019an",
    "gn:population":0,
    "gn:timezone":"Asia/Shanghai",
    "iso:country":"CN",
    "name:und_x_variant":[
        "Teng-ao-tao",
        "T\u2019eng-ao-p\u2019u-ts\u2019un",
        "T\u2019eng-ao-chen",
        "Teng\u2019aopu",
        "T\u2019eng-ao-pao",
        "Teng\u2019ao"
    ],
    "name:zho_x_preferred":[
        "\u798f\u5b89"
    ],
    "name:zho_x_variant":[
        "Teng\u2019ao Zhen",
        "\u817e\u9ccc\u9547",
        "Fu\u2019an"
    ],
    "wof:name":"Fu'an",
    "wof:placetype":"locality"
},
  "geometry": {"coordinates":[122.83056000000001,41.075],"type":"Point"}
}