{
  "type": "Feature",
  "properties": {
    "gn:admin1_code":"26",
    "gn:asciiname":"Yingli",
    "gn:country_code":"CN",
    "gn:dem":924,
    "gn:feature_class":"P",
    "gn:feature_code":"PPL",
    "gn:name":"Yingli",
    "gn:population":0,
    "gn:timezone":"Asia/Shanghai",
    "iso:country":"CN",
    "name:und_x_variant":[
        "\u8425\u91cc"
    ],
    "name:zho_x_preferred":[
        "\u8425\u91cc"
    ],
    "wof:name":"Yingli",
    "wof:placetype":"locality"
},
  "geometry": {"coordinates":[108.18889,34.75360999999999],"type":"Point"}
}