{
  "type": "Feature",
  "properties": {
    "gn:admin1_code":"31.0",
    "gn:asciiname":"Ergongdui",
    "gn:country_code":"CN",
    "gn:dem":17,
    "gn:feature_class":"P",
    "gn:feature_code":"PPL",
    "gn:name":"Ergongdui",
    "gn:population":0,
    "gn:timezone":"Asia/Shanghai",
    "iso:country":"CN",
    "name:zho_x_preferred":[
        "Ergongdui"
    ],
    "name:zho_x_variant":[
        "\u4e8c\u516c\u5806"
    ],
    "wof:name":"Ergongdui",
    "wof:placetype":"locality"
},
  "geometry": {"coordinates":[110.71827,19.76099],"type":"Point"}
}