{
  "type": "Feature",
  "properties": {
    "gn:admin1_code":"9.0",
    "gn:asciiname":"Xiaoyanghe",
    "gn:country_code":"CN",
    "gn:dem":569,
    "gn:feature_class":"P",
    "gn:feature_code":"PPL",
    "gn:name":"Xiaoyanghe",
    "gn:population":0,
    "gn:timezone":"Asia/Shanghai",
    "iso:country":"CN",
    "name:zho_x_preferred":[
        "\u5c0f\u9633\u6cb3"
    ],
    "wof:name":"Xiaoyanghe",
    "wof:placetype":"locality"
},
  "geometry": {"coordinates":[111.62701,34.86384],"type":"Point"}
}