{
  "type": "Feature",
  "properties": {
    "gn:admin1_code":"10.0",
    "gn:asciiname":"Baozipu",
    "gn:country_code":"CN",
    "gn:dem":36,
    "gn:feature_class":"P",
    "gn:feature_code":"PPL",
    "gn:name":"Baozipu",
    "gn:population":0,
    "gn:timezone":"Asia/Shanghai",
    "iso:country":"CN",
    "name:zho_x_preferred":[
        "\u5305\u5b50\u94fa"
    ],
    "wof:name":"Baozipu",
    "wof:placetype":"locality"
},
  "geometry": {"coordinates":[115.95532,39.45768],"type":"Point"}
}