{
  "type": "Feature",
  "properties": {
    "gn:admin1_code":"19.0",
    "gn:asciiname":"Hulutougou",
    "gn:country_code":"CN",
    "gn:dem":452,
    "gn:feature_class":"P",
    "gn:feature_code":"PPL",
    "gn:name":"Hulutougou",
    "gn:population":0,
    "gn:timezone":"Asia/Shanghai",
    "iso:country":"CN",
    "name:und_x_variant":[
        "\u846b\u82a6\u5934\u6c9f"
    ],
    "wof:name":"Hulutougou",
    "wof:placetype":"locality"
},
  "geometry": {"coordinates":[124.90096,41.99561],"type":"Point"}
}