{
  "type": "Feature",
  "properties": {
    "gn:admin1_code":"11.0",
    "gn:asciiname":"Meichong'ao",
    "gn:country_code":"CN",
    "gn:dem":235,
    "gn:feature_class":"P",
    "gn:feature_code":"PPL",
    "gn:name":"Meichong\u2019ao",
    "gn:population":0,
    "gn:timezone":"Asia/Shanghai",
    "iso:country":"CN",
    "name:und_x_variant":[
        "Meichong\u2019ao"
    ],
    "name:zho_x_preferred":[
        "\u6885\u51b2\u5773"
    ],
    "wof:name":"Meichong'ao",
    "wof:placetype":"locality"
},
  "geometry": {"coordinates":[109.73887999999999,27.17816],"type":"Point"}
}