{
  "type": "Feature",
  "properties": {
    "gn:admin1_code":"02",
    "gn:asciiname":"Shiliang",
    "gn:country_code":"CN",
    "gn:dem":119,
    "gn:feature_class":"P",
    "gn:feature_code":"PPLA4",
    "gn:name":"Shiliang",
    "gn:population":0,
    "gn:timezone":"Asia/Shanghai",
    "iso:country":"CN",
    "name:und_x_variant":[
        "Shih-liang",
        "Shih-liang-shih",
        "Shiliang Zhen",
        "Shiliang"
    ],
    "name:zho_x_preferred":[
        "\u77f3\u6881"
    ],
    "name:zho_x_variant":[
        "\u77f3\u6881\u9547"
    ],
    "wof:name":"Shiliang",
    "wof:placetype":"locality"
},
  "geometry": {"coordinates":[118.78288999999999,29.0203],"type":"Point"}
}