{
  "type": "Feature",
  "properties": {
    "gn:admin1_code":"12.0",
    "gn:asciiname":"Luzigou",
    "gn:country_code":"CN",
    "gn:dem":633,
    "gn:feature_class":"P",
    "gn:feature_code":"PPL",
    "gn:name":"Luzigou",
    "gn:population":0,
    "gn:timezone":"Asia/Shanghai",
    "iso:country":"CN",
    "name:zho_x_preferred":[
        "\u5362\u5b57\u6c9f"
    ],
    "wof:name":"Luzigou",
    "wof:placetype":"locality"
},
  "geometry": {"coordinates":[110.15218,31.99594],"type":"Point"}
}