{
  "type": "Feature",
  "properties": {
    "gn:admin1_code":"13.0",
    "gn:asciiname":"Shanshan",
    "gn:country_code":"CN",
    "gn:dem":367,
    "gn:feature_class":"P",
    "gn:feature_code":"PPLA3",
    "gn:name":"Shanshan",
    "gn:population":0,
    "gn:timezone":"Asia/Urumqi",
    "iso:country":"CN",
    "name:uig_x_preferred":[
        "Pichan"
    ],
    "name:uig_x_variant":[
        "\u067e\u0649\u0686\u0627\u0646",
        "\u041f\u0438\u0447\u0430\u043d"
    ],
    "name:und_x_variant":[
        "Pichang",
        "Pitschuang",
        "P\u2019i-chan",
        "Piqan",
        "Shan-shan-chen",
        "Shan-shan-ch\u2019eng",
        "Shan-shan-hsien",
        "Shanshar",
        "Shanshan",
        "Shanshan Xian"
    ],
    "name:zho_x_preferred":[
        "\u912f\u5584"
    ],
    "name:zho_x_variant":[
        "\u912f\u5584\u53bf"
    ],
    "wof:name":"Shanshan",
    "wof:placetype":"locality"
},
  "geometry": {"coordinates":[90.20462999999999,42.8675],"type":"Point"}
}