{
  "type": "Feature",
  "properties": {
    "gn:admin1_code":"11.0",
    "gn:asciiname":"Dushidong",
    "gn:country_code":"CN",
    "gn:dem":344,
    "gn:feature_class":"P",
    "gn:feature_code":"PPL",
    "gn:name":"Dushidong",
    "gn:population":0,
    "gn:timezone":"Asia/Shanghai",
    "iso:country":"CN",
    "name:zho_x_preferred":[
        "\u72ec\u77f3\u6d1e"
    ],
    "wof:name":"Dushidong",
    "wof:placetype":"locality"
},
  "geometry": {"coordinates":[113.72028,29.10119000000001],"type":"Point"}
}