{
  "type": "Feature",
  "properties": {
    "gn:admin1_code":"6.0",
    "gn:asciiname":"Ranggouji",
    "gn:country_code":"CN",
    "gn:dem":4078,
    "gn:feature_class":"P",
    "gn:feature_code":"PPL",
    "gn:name":"Ranggouji",
    "gn:population":0,
    "gn:timezone":"Asia/Urumqi",
    "iso:country":"CN",
    "name:zho_x_preferred":[
        "\u8ba9\u52fe\u7ed9"
    ],
    "wof:name":"Ranggouji",
    "wof:placetype":"locality"
},
  "geometry": {"coordinates":[96.86705000000001,32.15274],"type":"Point"}
}