{
  "type": "Feature",
  "properties": {
    "gn:admin1_code":"32.0",
    "gn:asciiname":"Texibu",
    "gn:country_code":"CN",
    "gn:dem":1943,
    "gn:feature_class":"P",
    "gn:feature_code":"PPL",
    "gn:name":"Texibu",
    "gn:population":0,
    "gn:timezone":"Asia/Shanghai",
    "iso:country":"CN",
    "name:zho_x_preferred":[
        "\u7279\u897f\u5e03"
    ],
    "wof:name":"Texibu",
    "wof:placetype":"locality"
},
  "geometry": {"coordinates":[103.033,28.1585],"type":"Point"}
}