{
  "type": "Feature",
  "properties": {
    "gn:admin1_code":"1.0",
    "gn:asciiname":"Heshe",
    "gn:country_code":"CN",
    "gn:dem":210,
    "gn:feature_class":"P",
    "gn:feature_code":"PPL",
    "gn:name":"Heshe",
    "gn:population":0,
    "gn:timezone":"Asia/Shanghai",
    "iso:country":"CN",
    "name:zho_x_preferred":[
        "\u9e64\u820d"
    ],
    "wof:name":"Heshe",
    "wof:placetype":"locality"
},
  "geometry": {"coordinates":[118.13263999999999,29.89049],"type":"Point"}
}