{
  "type": "Feature",
  "properties": {
    "gn:admin1_code":"26.0",
    "gn:asciiname":"Liushanjia Guacun",
    "gn:country_code":"CN",
    "gn:dem":1063,
    "gn:feature_class":"P",
    "gn:feature_code":"PPL",
    "gn:name":"Liushanjia Guacun",
    "gn:population":0,
    "gn:timezone":"Asia/Shanghai",
    "iso:country":"CN",
    "name:zho_x_preferred":[
        "\u5218\u5c71\u5bb6\u576c\u6751"
    ],
    "wof:name":"Liushanjia Guacun",
    "wof:placetype":"locality"
},
  "geometry": {"coordinates":[110.851,38.7119],"type":"Point"}
}