{
  "type": "Feature",
  "properties": {
    "gn:admin1_code":"3.0",
    "gn:asciiname":"Qijiaoshan",
    "gn:country_code":"CN",
    "gn:dem":468,
    "gn:feature_class":"P",
    "gn:feature_code":"PPL",
    "gn:name":"Qijiaoshan",
    "gn:population":0,
    "gn:timezone":"Asia/Shanghai",
    "iso:country":"CN",
    "name:und_x_variant":[
        "\u4f01\u811a\u5c71"
    ],
    "wof:name":"Qijiaoshan",
    "wof:placetype":"locality"
},
  "geometry": {"coordinates":[115.18707999999999,26.53483],"type":"Point"}
}