{
  "type": "Feature",
  "properties": {
    "gn:admin1_code":"11",
    "gn:asciiname":"Dazhai",
    "gn:country_code":"CN",
    "gn:dem":200,
    "gn:feature_class":"P",
    "gn:feature_code":"PPL",
    "gn:name":"Dazhai",
    "gn:population":0,
    "gn:timezone":"Asia/Shanghai",
    "iso:country":"CN",
    "name:fra_x_preferred":[
        "Dazhai"
    ],
    "name:jpn_x_preferred":[
        "\u5927\u5be8\u6751"
    ],
    "name:zho_x_preferred":[
        "\u5927\u5be8\u6751"
    ],
    "wof:name":"Dazhai",
    "wof:placetype":"locality"
},
  "geometry": {"coordinates":[110.23639,28.70944],"type":"Point"}
}