{
  "type": "Feature",
  "properties": {
    "gn:admin1_code":"4.0",
    "gn:asciiname":"Sunzhuang",
    "gn:country_code":"CN",
    "gn:dem":12,
    "gn:feature_class":"P",
    "gn:feature_code":"PPL",
    "gn:name":"Sunzhuang",
    "gn:population":0,
    "gn:timezone":"Asia/Shanghai",
    "iso:country":"CN",
    "name:ceb_x_preferred":[
        "Sunzhuang"
    ],
    "name:swe_x_preferred":[
        "Sunzhuang"
    ],
    "wof:name":"Sunzhuang",
    "wof:placetype":"locality"
},
  "geometry": {"coordinates":[118.82917,33.99583],"type":"Point"}
}