{
  "type": "Feature",
  "properties": {
    "gn:admin1_code":"3.0",
    "gn:asciiname":"Tangzhongjian",
    "gn:country_code":"CN",
    "gn:dem":22,
    "gn:feature_class":"P",
    "gn:feature_code":"PPL",
    "gn:name":"Tangzhongjian",
    "gn:population":0,
    "gn:timezone":"Asia/Shanghai",
    "iso:country":"CN",
    "name:und_x_variant":[
        "\u5858\u4e2d\u95f4"
    ],
    "wof:name":"Tangzhongjian",
    "wof:placetype":"locality"
},
  "geometry": {"coordinates":[116.03758999999999,28.44836],"type":"Point"}
}