{
  "type": "Feature",
  "properties": {
    "gn:admin1_code":"30.0",
    "gn:asciiname":"Lantangmian",
    "gn:country_code":"CN",
    "gn:dem":165,
    "gn:feature_class":"P",
    "gn:feature_code":"PPL",
    "gn:name":"Lantangmian",
    "gn:population":0,
    "gn:timezone":"Asia/Shanghai",
    "iso:country":"CN",
    "name:zho_x_preferred":[
        "Lantangmian"
    ],
    "name:zho_x_variant":[
        "\u5170\u5858\u9762"
    ],
    "wof:name":"Lantangmian",
    "wof:placetype":"locality"
},
  "geometry": {"coordinates":[115.43472,24.19667],"type":"Point"}
}