{
  "type": "Feature",
  "properties": {
    "gn:admin1_code":"19.0",
    "gn:asciiname":"Fuyu",
    "gn:country_code":"CN",
    "gn:dem":2,
    "gn:feature_class":"P",
    "gn:feature_code":"PPL",
    "gn:name":"Fuyu",
    "gn:population":0,
    "gn:timezone":"Asia/Shanghai",
    "iso:country":"CN",
    "name:ceb_x_preferred":[
        "Fuyu"
    ],
    "name:deu_x_preferred":[
        "Fuyu"
    ],
    "name:eus_x_preferred":[
        "Fuyu"
    ],
    "name:fra_x_preferred":[
        "Fuyu"
    ],
    "name:mlg_x_preferred":[
        "Fuyu"
    ],
    "name:nor_x_preferred":[
        "Fuyu"
    ],
    "name:swe_x_preferred":[
        "Fuyu"
    ],
    "name:und_x_variant":[
        "\u5bcc\u88d5"
    ],
    "wof:name":"Fuyu",
    "wof:placetype":"locality"
},
  "geometry": {"coordinates":[122.11586,40.74477],"type":"Point"}
}