{
  "type": "Feature",
  "properties": {
    "gn:admin1_code":"09",
    "gn:asciiname":"Gaocun",
    "gn:cc2":"CN",
    "gn:country_code":"CN",
    "gn:dem":79,
    "gn:feature_class":"P",
    "gn:feature_code":"PPL",
    "gn:name":"Gaocun",
    "gn:population":0,
    "gn:timezone":"Asia/Shanghai",
    "iso:country":"CN",
    "name:und_x_variant":[
        "Kao-ts\u2019un-ch\u2019iao",
        "Gaocunqiao",
        "Gaocun"
    ],
    "name:zho_x_preferred":[
        "\u9ad8\u6751\u9547"
    ],
    "wof:name":"Gaocun",
    "wof:placetype":"locality"
},
  "geometry": {"coordinates":[114.22194,35.66944],"type":"Point"}
}