{
  "type": "Feature",
  "properties": {
    "gn:admin1_code":"24.0",
    "gn:asciiname":"Shanggaoshicun",
    "gn:country_code":"CN",
    "gn:dem":379,
    "gn:feature_class":"P",
    "gn:feature_code":"PPL",
    "gn:name":"Shanggaoshicun",
    "gn:population":0,
    "gn:timezone":"Asia/Shanghai",
    "iso:country":"CN",
    "name:zho_x_preferred":[
        "\u4e0a\u9ad8\u5e02\u6751"
    ],
    "wof:name":"Shanggaoshicun",
    "wof:placetype":"locality"
},
  "geometry": {"coordinates":[110.43742,34.92188],"type":"Point"}
}