{
  "type": "Feature",
  "properties": {
    "gn:admin1_code":"10.0",
    "gn:asciiname":"Silipu",
    "gn:country_code":"CN",
    "gn:dem":26,
    "gn:feature_class":"P",
    "gn:feature_code":"PPL",
    "gn:name":"Silipu",
    "gn:population":0,
    "gn:timezone":"Asia/Shanghai",
    "iso:country":"CN",
    "name:zho_x_preferred":[
        "\u56db\u91cc\u94fa"
    ],
    "wof:name":"Silipu",
    "wof:placetype":"locality"
},
  "geometry": {"coordinates":[116.27916,39.37373],"type":"Point"}
}