{
  "type": "Feature",
  "properties": {
    "gn:admin1_code":"29.0",
    "gn:asciiname":"Yanjiucun",
    "gn:country_code":"CN",
    "gn:dem":2006,
    "gn:feature_class":"P",
    "gn:feature_code":"PPL",
    "gn:name":"Yanjiucun",
    "gn:population":0,
    "gn:timezone":"Asia/Shanghai",
    "iso:country":"CN",
    "name:zho_x_preferred":[
        "\u7814\u7a76\u6751"
    ],
    "wof:name":"Yanjiucun",
    "wof:placetype":"locality"
},
  "geometry": {"coordinates":[102.95999999999999,25.4895],"type":"Point"}
}