{
  "type": "Feature",
  "properties": {
    "gn:admin1_code":"2.0",
    "gn:asciiname":"Kejia",
    "gn:country_code":"CN",
    "gn:dem":81,
    "gn:feature_class":"P",
    "gn:feature_code":"PPL",
    "gn:name":"Kejia",
    "gn:population":0,
    "gn:timezone":"Asia/Shanghai",
    "iso:country":"CN",
    "name:und_x_variant":[
        "\u67ef\u5bb6",
        "Kejia"
    ],
    "wof:name":"Kejia",
    "wof:placetype":"locality"
},
  "geometry": {"coordinates":[119.10344000000001,29.13656],"type":"Point"}
}