{
  "type": "Feature",
  "properties": {
    "gn:admin1_code":"29.0",
    "gn:asciiname":"Longjinggou",
    "gn:country_code":"CN",
    "gn:dem":1791,
    "gn:feature_class":"P",
    "gn:feature_code":"PPL",
    "gn:name":"Longjinggou",
    "gn:population":0,
    "gn:timezone":"Asia/Shanghai",
    "iso:country":"CN",
    "name:zho_x_preferred":[
        "\u9f99\u4e95\u6c9f"
    ],
    "wof:name":"Longjinggou",
    "wof:placetype":"locality"
},
  "geometry": {"coordinates":[103.48,27.2344],"type":"Point"}
}