{
  "type": "Feature",
  "properties": {
    "gn:admin1_code":"2",
    "gn:asciiname":"Culong",
    "gn:country_code":"CN",
    "gn:dem":652,
    "gn:feature_class":"P",
    "gn:feature_code":"PPL",
    "gn:name":"Culong",
    "gn:population":0,
    "gn:timezone":"Asia/Shanghai",
    "iso:country":"CN",
    "name:zho_x_preferred":[
        "\u7c97\u9686"
    ],
    "wof:name":"Culong",
    "wof:placetype":"locality"
},
  "geometry": {"coordinates":[119.03471999999999,27.50944],"type":"Point"}
}