{
  "type": "Feature",
  "properties": {
    "gn:admin1_code":"3.0",
    "gn:asciiname":"Tangjiaqiao",
    "gn:country_code":"CN",
    "gn:dem":40,
    "gn:feature_class":"P",
    "gn:feature_code":"PPL",
    "gn:name":"Tangjiaqiao",
    "gn:population":0,
    "gn:timezone":"Asia/Shanghai",
    "iso:country":"CN",
    "name:und_x_variant":[
        "\u5510\u5bb6\u6865"
    ],
    "wof:name":"Tangjiaqiao",
    "wof:placetype":"locality"
},
  "geometry": {"coordinates":[115.28489999999999,27.82594000000001],"type":"Point"}
}