{
  "type": "Feature",
  "properties": {
    "gn:admin1_code":"20.0",
    "gn:asciiname":"Mo'erdeng",
    "gn:country_code":"CN",
    "gn:dem":262,
    "gn:feature_class":"P",
    "gn:feature_code":"PPL",
    "gn:name":"Mo\u2019erdeng",
    "gn:population":0,
    "gn:timezone":"Asia/Shanghai",
    "iso:country":"CN",
    "name:und_x_variant":[
        "Mo\u2019erdeng"
    ],
    "name:zho_x_preferred":[
        "\u83ab\u5c14\u767b"
    ],
    "wof:name":"Mo'erdeng",
    "wof:placetype":"locality"
},
  "geometry": {"coordinates":[123.78028,48.99264],"type":"Point"}
}