{
  "type": "Feature",
  "properties": {
    "gn:admin1_code":"19",
    "gn:asciiname":"Yong'anbeitun",
    "gn:country_code":"CN",
    "gn:dem":5,
    "gn:feature_class":"P",
    "gn:feature_code":"PPL",
    "gn:name":"Yong\u2019anbeitun",
    "gn:population":0,
    "gn:timezone":"Asia/Shanghai",
    "iso:country":"CN",
    "name:und_x_variant":[
        "Yung-an-pei-t\u2019un",
        "Yong\u2019anbeitun"
    ],
    "wof:name":"Yong'anbeitun",
    "wof:placetype":"locality"
},
  "geometry": {"coordinates":[124.21361,39.95889],"type":"Point"}
}