{
  "type": "Feature",
  "properties": {
    "gn:admin1_code":"32.0",
    "gn:asciiname":"Zhawushe",
    "gn:country_code":"CN",
    "gn:dem":3189,
    "gn:feature_class":"P",
    "gn:feature_code":"PPL",
    "gn:name":"Zhawushe",
    "gn:population":0,
    "gn:timezone":"Asia/Shanghai",
    "iso:country":"CN",
    "name:zho_x_preferred":[
        "\u624e\u52ff\u793e"
    ],
    "wof:name":"Zhawushe",
    "wof:placetype":"locality"
},
  "geometry": {"coordinates":[102.74177,34.08746],"type":"Point"}
}