{
  "type": "Feature",
  "properties": {
    "gn:admin1_code":"32.0",
    "gn:asciiname":"Rudoi",
    "gn:country_code":"CN",
    "gn:dem":3565,
    "gn:feature_class":"P",
    "gn:feature_code":"PPL",
    "gn:name":"Rudoi",
    "gn:population":0,
    "gn:timezone":"Asia/Shanghai",
    "iso:country":"CN",
    "wof:name":"Rudoi",
    "wof:placetype":"locality"
},
  "geometry": {"coordinates":[99.18333,28.66667],"type":"Point"}
}