{
  "type": "Feature",
  "properties": {
    "gn:admin1_code":"5.0",
    "gn:asciiname":"Longhai",
    "gn:country_code":"CN",
    "gn:dem":344,
    "gn:feature_class":"P",
    "gn:feature_code":"PPL",
    "gn:name":"Longhai",
    "gn:population":0,
    "gn:timezone":"Asia/Shanghai",
    "iso:country":"CN",
    "name:ceb_x_preferred":[
        "Longhai"
    ],
    "name:deu_x_preferred":[
        "Longhai"
    ],
    "name:und_x_variant":[
        "\u9f99\u6d77",
        "Longhaicun",
        "\u9f99\u6d77\u6751"
    ],
    "wof:name":"Longhai",
    "wof:placetype":"locality"
},
  "geometry": {"coordinates":[129.21501999999998,42.67542],"type":"Point"}
}