{
  "type": "Feature",
  "properties": {
    "gn:admin1_code":"12.0",
    "gn:asciiname":"Longjiatan",
    "gn:country_code":"CN",
    "gn:dem":36,
    "gn:feature_class":"P",
    "gn:feature_code":"PPL",
    "gn:name":"Longjiatan",
    "gn:population":0,
    "gn:timezone":"Asia/Shanghai",
    "iso:country":"CN",
    "name:zho_x_preferred":[
        "Longjiatan"
    ],
    "name:zho_x_variant":[
        "\u9f99\u5bb6\u6f6d"
    ],
    "wof:name":"Longjiatan",
    "wof:placetype":"locality"
},
  "geometry": {"coordinates":[111.95978999999998,30.12579],"type":"Point"}
}