{
  "type": "Feature",
  "properties": {
    "gn:admin1_code":"0.0",
    "gn:asciiname":"Banbianjiedaoban",
    "gn:country_code":"CN",
    "gn:dem":1510,
    "gn:feature_class":"P",
    "gn:feature_code":"PPL",
    "gn:name":"Banbianjiedaoban",
    "gn:population":0,
    "gn:timezone":"Asia/Shanghai",
    "iso:country":"CN",
    "name:zho_x_preferred":[
        "\u534a\u8fb9\u8857\u9053\u73ed"
    ],
    "wof:name":"Banbianjiedaoban",
    "wof:placetype":"locality"
},
  "geometry": {"coordinates":[102.33108,29.05492000000001],"type":"Point"}
}