{
  "type": "Feature",
  "properties": {
    "gn:admin1_code":"12.0",
    "gn:asciiname":"Changyanwu",
    "gn:country_code":"CN",
    "gn:dem":2418,
    "gn:feature_class":"P",
    "gn:feature_code":"PPL",
    "gn:name":"Changyanwu",
    "gn:population":0,
    "gn:timezone":"Asia/Shanghai",
    "iso:country":"CN",
    "name:zho_x_preferred":[
        "\u957f\u5ca9\u5c4b"
    ],
    "wof:name":"Changyanwu",
    "wof:placetype":"locality"
},
  "geometry": {"coordinates":[110.28852000000001,31.46482],"type":"Point"}
}