{
  "type": "Feature",
  "properties": {
    "gn:admin1_code":"25.0",
    "gn:asciiname":"Zhangzhaocun",
    "gn:country_code":"CN",
    "gn:dem":45,
    "gn:feature_class":"P",
    "gn:feature_code":"PPL",
    "gn:name":"Zhangzhaocun",
    "gn:population":0,
    "gn:timezone":"Asia/Shanghai",
    "iso:country":"CN",
    "name:zho_x_preferred":[
        "\u5f20\u8d75\u6751"
    ],
    "wof:name":"Zhangzhaocun",
    "wof:placetype":"locality"
},
  "geometry": {"coordinates":[120.71319,37.79823],"type":"Point"}
}