{
  "type": "Feature",
  "properties": {
    "gn:admin1_code":"32.0",
    "gn:asciiname":"Zhimajia",
    "gn:country_code":"CN",
    "gn:dem":2132,
    "gn:feature_class":"P",
    "gn:feature_code":"PPL",
    "gn:name":"Zhimajia",
    "gn:population":0,
    "gn:timezone":"Asia/Shanghai",
    "iso:country":"CN",
    "name:zho_x_preferred":[
        "\u829d\u9ebb\u5bb6"
    ],
    "wof:name":"Zhimajia",
    "wof:placetype":"locality"
},
  "geometry": {"coordinates":[104.121,33.3396],"type":"Point"}
}