{
  "type": "Feature",
  "properties": {
    "gn:admin1_code":"14.0",
    "gn:asciiname":"Duoduicun",
    "gn:country_code":"CN",
    "gn:dem":4335,
    "gn:feature_class":"P",
    "gn:feature_code":"PPL",
    "gn:name":"Duoduicun",
    "gn:population":0,
    "gn:timezone":"Asia/Urumqi",
    "iso:country":"CN",
    "name:zho_x_preferred":[
        "\u591a\u5806\u6751"
    ],
    "wof:name":"Duoduicun",
    "wof:placetype":"locality"
},
  "geometry": {"coordinates":[97.94358,32.01672],"type":"Point"}
}