{
  "type": "Feature",
  "properties": {
    "gn:admin1_code":"11.0",
    "gn:asciiname":"Gaopojie",
    "gn:country_code":"CN",
    "gn:dem":381,
    "gn:feature_class":"P",
    "gn:feature_code":"PPL",
    "gn:name":"Gaopojie",
    "gn:population":0,
    "gn:timezone":"Asia/Shanghai",
    "iso:country":"CN",
    "name:zho_x_preferred":[
        "\u9ad8\u5761\u754c"
    ],
    "wof:name":"Gaopojie",
    "wof:placetype":"locality"
},
  "geometry": {"coordinates":[109.74751000000001,27.33601],"type":"Point"}
}