{
  "type": "Feature",
  "properties": {
    "gn:admin1_code":"20",
    "gn:asciiname":"Uliastai",
    "gn:country_code":"CN",
    "gn:dem":868,
    "gn:feature_class":"P",
    "gn:feature_code":"PPLA3",
    "gn:name":"Uliastai",
    "gn:population":0,
    "gn:timezone":"Asia/Shanghai",
    "iso:country":"CN",
    "name:ara_x_preferred":[
        "\u0623\u0644\u064a\u0627\u0633\u062a\u0627\u064a"
    ],
    "name:bul_x_preferred":[
        "\u0423\u043b\u044f\u0441\u0442\u0430\u0439"
    ],
    "name:cat_x_preferred":[
        "Uliastai"
    ],
    "name:ceb_x_preferred":[
        "Uliastay"
    ],
    "name:ces_x_preferred":[
        "Uliastaj"
    ],
    "name:deu_x_preferred":[
        "Uliastai"
    ],
    "name:eus_x_preferred":[
        "Uliastai"
    ],
    "name:fas_x_preferred":[
        "\u0627\u0648\u0644\u06cc\u0627\u0633\u062a\u06cc"
    ],
    "name:fin_x_preferred":[
        "Uliastai"
    ],
    "name:fra_x_preferred":[
        "Uliastay"
    ],
    "name:hin_x_preferred":[
        "\u0909\u0932\u093f\u092f\u093e\u0938\u094d\u0924\u093e\u0907"
    ],
    "name:ita_x_preferred":[
        "Uliastaj"
    ],
    "name:jpn_x_preferred":[
        "\u30a6\u30ea\u30e4\u30b9\u30bf\u30a4"
    ],
    "name:kat_x_preferred":[
        "\u10e3\u10da\u10d8\u10d0\u10e1\u10e3\u10e2\u10d0\u10d8"
    ],
    "name:kor_x_preferred":[
        "\uc62c\ub9ac\uc544\uc2a4\ud0c0\uc774"
    ],
    "name:lit_x_preferred":[
        "Ulijastajus"
    ],
    "name:lmo_x_preferred":[
        "Uliastaj"
    ],
    "name:mkd_x_preferred":[
        "\u0423\u043b\u0438\u0458\u0430\u0441\u0442\u0430\u0458"
    ],
    "name:mon_x_preferred":[
        "Uliastai"
    ],
    "name:mon_x_variant":[
        "\u0423\u043b\u0438\u0430\u0441\u0442\u0430\u0439"
    ],
    "name:nld_x_preferred":[
        "Uliastaj"
    ],
    "name:pol_x_preferred":[
        "Uliastaj"
    ],
    "name:rus_x_preferred":[
        "\u0423\u043b\u0438\u0430\u0441\u0442\u0430\u0439"
    ],
    "name:spa_x_preferred":[
        "Uliastay"
    ],
    "name:swe_x_preferred":[
        "Uliastaj"
    ],
    "name:tur_x_preferred":[
        "Uliastay"
    ],
    "name:ukr_x_preferred":[
        "\u0423\u043b\u0456\u0430\u0441\u0442\u0430\u0439"
    ],
    "name:und_x_variant":[
        "Sumyyn Khuren\u2019-Sume",
        "Tung-wu-chu-mu-ch\u2019in-ch\u2019i",
        "Ramakures\u016bmu",
        "Wu-li-ya-ssu-t\u2019ai",
        "Sumoyn Khuren Sume",
        "La-ma-k\u2019u-lieh-miao",
        "Dong Ujimqin Qi",
        "Lamakulienmiay",
        "Dun\u2019uchzhumutsintsi",
        "Lamakhure Sume",
        "La-ma-k\u2019u-lien-miao",
        "La-ma-k\u2019u-lun-miao",
        "Lamakoulun",
        "\u4e4c\u91cc\u96c5\u65af\u592a",
        "Dongwuzhumuqin Qi",
        "Lamakoulunmiao",
        "Wuliyasitai Zhen",
        "\u4e1c\u4e4c\u73e0\u7a46\u6c81\u65d7",
        "\u4e4c\u91cc\u96c5\u65af\u592a\u9547",
        "\u5587\u561b\u5e93\u4f26\u5e99"
    ],
    "name:urd_x_preferred":[
        "\u0627\u0648\u0644\u06cc\u0627\u0633\u062a\u0627\u0626\u06cc"
    ],
    "name:vie_x_preferred":[
        "Uliastai"
    ],
    "name:war_x_preferred":[
        "Uliastai"
    ],
    "name:zho_x_preferred":[
        "Wuliyasitai"
    ],
    "name:zho_x_variant":[
        "\u70cf\u91cc\u96c5\u8607\u81fa\u57ce"
    ],
    "wof:name":"Uliastai",
    "wof:placetype":"locality"
},
  "geometry": {"coordinates":[116.83333,45.55],"type":"Point"}
}