{
  "type": "Feature",
  "properties": {
    "gn:admin1_code":"20",
    "gn:asciiname":"Uliastai",
    "gn:country_code":"CN",
    "gn:dem":868,
    "gn:feature_class":"P",
    "gn:feature_code":"PPLA3",
    "gn:name":"Uliastai",
    "gn:population":0,
    "gn:timezone":"Asia/Shanghai",
    "iso:country":"CN",
    "name:mon_x_preferred":[
        "Uliastai"
    ],
    "name:und_x_variant":[
        "Sumyyn Khuren\u2019-Sume",
        "Tung-wu-chu-mu-ch\u2019in-ch\u2019i",
        "Ramakures\u016bmu",
        "Wu-li-ya-ssu-t\u2019ai",
        "Sumoyn Khuren Sume",
        "La-ma-k\u2019u-lieh-miao",
        "Dong Ujimqin Qi",
        "Lamakulienmiay",
        "Dun\u2019uchzhumutsintsi",
        "Lamakhure Sume",
        "La-ma-k\u2019u-lien-miao",
        "La-ma-k\u2019u-lun-miao",
        "Lamakoulun",
        "Uliastai",
        "\u4e4c\u91cc\u96c5\u65af\u592a",
        "Dongwuzhumuqin Qi",
        "Lamakoulunmiao",
        "Wuliyasitai Zhen",
        "\u4e1c\u4e4c\u73e0\u7a46\u6c81\u65d7",
        "\u4e4c\u91cc\u96c5\u65af\u592a\u9547",
        "\u5587\u561b\u5e93\u4f26\u5e99"
    ],
    "name:zho_x_preferred":[
        "Wuliyasitai"
    ],
    "wof:name":"Uliastai",
    "wof:placetype":"locality"
},
  "geometry": {"coordinates":[116.83333,45.55],"type":"Point"}
}