{
  "type": "Feature",
  "properties": {
    "gn:admin1_code":"12.0",
    "gn:asciiname":"Baiyunao",
    "gn:country_code":"CN",
    "gn:dem":316,
    "gn:feature_class":"P",
    "gn:feature_code":"PPL",
    "gn:name":"Baiyunao",
    "gn:population":0,
    "gn:timezone":"Asia/Shanghai",
    "iso:country":"CN",
    "name:zho_x_preferred":[
        "Baiyunao"
    ],
    "name:zho_x_variant":[
        "\u767d\u7389\u57b4"
    ],
    "wof:name":"Baiyunao",
    "wof:placetype":"locality"
},
  "geometry": {"coordinates":[111.31542,30.18984],"type":"Point"}
}