{
  "type": "Feature",
  "properties": {
    "gn:admin1_code":"24",
    "gn:asciiname":"Huzhuang",
    "gn:country_code":"CN",
    "gn:dem":1122,
    "gn:feature_class":"P",
    "gn:feature_code":"PPL",
    "gn:name":"Huzhuang",
    "gn:population":0,
    "gn:timezone":"Asia/Shanghai",
    "iso:country":"CN",
    "wof:name":"Huzhuang",
    "wof:placetype":"locality"
},
  "geometry": {"coordinates":[112.66333,37.05028],"type":"Point"}
}