{
  "type": "Feature",
  "properties": {
    "gn:admin1_code":"16.0",
    "gn:asciiname":"Banba",
    "gn:country_code":"CN",
    "gn:dem":213,
    "gn:feature_class":"P",
    "gn:feature_code":"PPL",
    "gn:name":"Banba",
    "gn:population":0,
    "gn:timezone":"Asia/Shanghai",
    "iso:country":"CN",
    "name:deu_x_preferred":[
        "Banba"
    ],
    "name:fin_x_preferred":[
        "Banbha"
    ],
    "name:fra_x_preferred":[
        "Banba"
    ],
    "name:gle_x_preferred":[
        "Banbha"
    ],
    "name:ita_x_preferred":[
        "Banba"
    ],
    "name:jpn_x_preferred":[
        "\u30d0\u30f3\u30d0"
    ],
    "name:nld_x_preferred":[
        "Banba"
    ],
    "name:pol_x_preferred":[
        "Banba"
    ],
    "name:por_x_preferred":[
        "Banba"
    ],
    "name:zho_x_preferred":[
        "\u677f\u5df4"
    ],
    "wof:name":"Banba",
    "wof:placetype":"locality"
},
  "geometry": {"coordinates":[108.014,24.1257],"type":"Point"}
}