{
  "type": "Feature",
  "properties": {
    "gn:admin1_code":"10.0",
    "gn:asciiname":"Fengmansa",
    "gn:country_code":"CN",
    "gn:dem":32,
    "gn:feature_class":"P",
    "gn:feature_code":"PPL",
    "gn:name":"Fengmansa",
    "gn:population":0,
    "gn:timezone":"Asia/Shanghai",
    "iso:country":"CN",
    "name:zho_x_preferred":[
        "\u51af\u6f2b\u6492"
    ],
    "wof:name":"Fengmansa",
    "wof:placetype":"locality"
},
  "geometry": {"coordinates":[115.93328,39.32964000000001],"type":"Point"}
}