{
  "type": "Feature",
  "properties": {
    "gn:admin1_code":"1.0",
    "gn:asciiname":"Wawangcun",
    "gn:country_code":"CN",
    "gn:dem":29,
    "gn:feature_class":"P",
    "gn:feature_code":"PPL",
    "gn:name":"Wawangcun",
    "gn:population":0,
    "gn:timezone":"Asia/Shanghai",
    "iso:country":"CN",
    "name:zho_x_preferred":[
        "\u74e6\u738b\u6751"
    ],
    "wof:name":"Wawangcun",
    "wof:placetype":"locality"
},
  "geometry": {"coordinates":[117.91433000000001,32.42784],"type":"Point"}
}