{
  "type": "Feature",
  "properties": {
    "gn:admin1_code":"19.0",
    "gn:asciiname":"Yangjia Dawang",
    "gn:country_code":"CN",
    "gn:dem":116,
    "gn:feature_class":"P",
    "gn:feature_code":"PPL",
    "gn:name":"Yangjia Dawang",
    "gn:population":0,
    "gn:timezone":"Asia/Shanghai",
    "iso:country":"CN",
    "name:zho_x_preferred":[
        "\u6768\u5bb6\u5927\u65fa"
    ],
    "wof:name":"Yangjia Dawang",
    "wof:placetype":"locality"
},
  "geometry": {"coordinates":[121.345,38.9286],"type":"Point"}
}