{
  "type": "Feature",
  "properties": {
    "gn:admin1_code":"24.0",
    "gn:asciiname":"Mengbicun",
    "gn:country_code":"CN",
    "gn:dem":918,
    "gn:feature_class":"P",
    "gn:feature_code":"PPL",
    "gn:name":"Mengbicun",
    "gn:population":0,
    "gn:timezone":"Asia/Shanghai",
    "iso:country":"CN",
    "name:zho_x_preferred":[
        "\u5b5f\u58c1\u6751"
    ],
    "wof:name":"Mengbicun",
    "wof:placetype":"locality"
},
  "geometry": {"coordinates":[113.67644,37.55485],"type":"Point"}
}