{
  "type": "Feature",
  "properties": {
    "gn:admin1_code":"29.0",
    "gn:asciiname":"Longgang",
    "gn:country_code":"CN",
    "gn:dem":1329,
    "gn:feature_class":"P",
    "gn:feature_code":"PPL",
    "gn:name":"Longgang",
    "gn:population":0,
    "gn:timezone":"Asia/Shanghai",
    "iso:country":"CN",
    "name:ceb_x_preferred":[
        "Longgang"
    ],
    "name:deu_x_preferred":[
        "Longgang"
    ],
    "name:fra_x_preferred":[
        "Longgang"
    ],
    "name:kor_x_preferred":[
        "\ub8fd\uac15\uad6c"
    ],
    "name:mlg_x_preferred":[
        "Longgang"
    ],
    "name:nor_x_preferred":[
        "Longgang"
    ],
    "name:pol_x_preferred":[
        "Longgang"
    ],
    "name:zho_x_preferred":[
        "\u7b3c\u5c97"
    ],
    "wof:name":"Longgang",
    "wof:placetype":"locality"
},
  "geometry": {"coordinates":[100.84699999999999,24.4133],"type":"Point"}
}