{
  "type": "Feature",
  "properties": {
    "gn:admin1_code":"13.0",
    "gn:asciiname":"Shangqi Mugan",
    "gn:country_code":"CN",
    "gn:dem":3383,
    "gn:feature_class":"P",
    "gn:feature_code":"PPL",
    "gn:name":"Shangqi Mugan",
    "gn:population":0,
    "gn:timezone":"Asia/Shanghai",
    "iso:country":"CN",
    "name:und_x_variant":[
        "\u4e0a\u5176\u6728\u5e72"
    ],
    "wof:name":"Shangqi Mugan",
    "wof:placetype":"locality"
},
  "geometry": {"coordinates":[75.54290999999998,38.53339],"type":"Point"}
}