{
  "type": "Feature",
  "properties": {
    "gn:admin1_code":"4.0",
    "gn:asciiname":"Pubangyan",
    "gn:country_code":"CN",
    "gn:dem":4,
    "gn:feature_class":"P",
    "gn:feature_code":"PPL",
    "gn:name":"Pubangyan",
    "gn:population":0,
    "gn:timezone":"Asia/Shanghai",
    "iso:country":"CN",
    "name:zho_x_preferred":[
        "Pubangyan"
    ],
    "name:zho_x_variant":[
        "\u84b2\u6d5c\u5830"
    ],
    "wof:name":"Pubangyan",
    "wof:placetype":"locality"
},
  "geometry": {"coordinates":[121.10054,31.59929],"type":"Point"}
}