{
  "type": "Feature",
  "properties": {
    "gn:admin1_code":"29.0",
    "gn:asciiname":"Danaiba",
    "gn:country_code":"CN",
    "gn:dem":1031,
    "gn:feature_class":"P",
    "gn:feature_code":"PPL",
    "gn:name":"Danaiba",
    "gn:population":0,
    "gn:timezone":"Asia/Shanghai",
    "iso:country":"CN",
    "name:zho_x_preferred":[
        "\u5927\u4e43\u575d"
    ],
    "wof:name":"Danaiba",
    "wof:placetype":"locality"
},
  "geometry": {"coordinates":[99.5742,24.3189],"type":"Point"}
}