{
  "type": "Feature",
  "properties": {
    "gn:admin1_code":"9.0",
    "gn:asciiname":"Sunliugou",
    "gn:country_code":"CN",
    "gn:dem":326,
    "gn:feature_class":"P",
    "gn:feature_code":"PPL",
    "gn:name":"Sunliugou",
    "gn:population":0,
    "gn:timezone":"Asia/Shanghai",
    "iso:country":"CN",
    "name:zho_x_preferred":[
        "\u5b59\u7559\u6c9f"
    ],
    "wof:name":"Sunliugou",
    "wof:placetype":"locality"
},
  "geometry": {"coordinates":[112.04713,34.47601],"type":"Point"}
}