{
  "type": "Feature",
  "properties": {
    "gn:admin1_code":"16.0",
    "gn:asciiname":"Linya",
    "gn:country_code":"CN",
    "gn:dem":538,
    "gn:feature_class":"P",
    "gn:feature_code":"PPL",
    "gn:name":"Linya",
    "gn:population":0,
    "gn:timezone":"Asia/Shanghai",
    "iso:country":"CN",
    "name:zho_x_preferred":[
        "\u6797\u7259"
    ],
    "wof:name":"Linya",
    "wof:placetype":"locality"
},
  "geometry": {"coordinates":[107.43000000000001,24.6105],"type":"Point"}
}