{
  "type": "Feature",
  "properties": {
    "gn:admin1_code":"16.0",
    "gn:asciiname":"Macun",
    "gn:country_code":"CN",
    "gn:dem":127,
    "gn:feature_class":"P",
    "gn:feature_code":"PPL",
    "gn:name":"Macun",
    "gn:population":0,
    "gn:timezone":"Asia/Shanghai",
    "iso:country":"CN",
    "name:cat_x_preferred":[
        "Macun \u015fekeri"
    ],
    "name:rus_x_preferred":[
        "\u041c\u0430\u0434\u0436\u0443\u043d"
    ],
    "name:spa_x_preferred":[
        "Macun \u015fekeri"
    ],
    "name:tur_x_preferred":[
        "Macun \u015fekeri"
    ],
    "name:zho_x_preferred":[
        "\u9ebb\u6751"
    ],
    "wof:name":"Macun",
    "wof:placetype":"locality"
},
  "geometry": {"coordinates":[109.819,24.6303],"type":"Point"}
}