{
  "type": "Feature",
  "properties": {
    "gn:admin1_code":"29",
    "gn:asciiname":"Lamoke",
    "gn:country_code":"CN",
    "gn:dem":1398,
    "gn:feature_class":"P",
    "gn:feature_code":"PPL",
    "gn:name":"Lamoke",
    "gn:population":0,
    "gn:timezone":"Asia/Shanghai",
    "iso:country":"CN",
    "name:zho_x_preferred":[
        "\u62c9\u83ab\u53ef"
    ],
    "wof:name":"Lamoke",
    "wof:placetype":"locality"
},
  "geometry": {"coordinates":[101.754,24.0507],"type":"Point"}
}