{
  "type": "Feature",
  "properties": {
    "gn:admin1_code":"16.0",
    "gn:asciiname":"Xialucha",
    "gn:country_code":"CN",
    "gn:dem":106,
    "gn:feature_class":"P",
    "gn:feature_code":"PPL",
    "gn:name":"Xialucha",
    "gn:population":0,
    "gn:timezone":"Asia/Shanghai",
    "iso:country":"CN",
    "name:zho_x_preferred":[
        "\u4e0b\u8def\u5bdf"
    ],
    "wof:name":"Xialucha",
    "wof:placetype":"locality"
},
  "geometry": {"coordinates":[110.254,22.4779],"type":"Point"}
}