{
  "type": "Feature",
  "properties": {
    "gn:admin1_code":"3.0",
    "gn:asciiname":"Shangsanguan",
    "gn:country_code":"CN",
    "gn:dem":145,
    "gn:feature_class":"P",
    "gn:feature_code":"PPL",
    "gn:name":"Shangsanguan",
    "gn:population":0,
    "gn:timezone":"Asia/Shanghai",
    "iso:country":"CN",
    "name:und_x_variant":[
        "\u4e0a\u4e09\u8d2f"
    ],
    "wof:name":"Shangsanguan",
    "wof:placetype":"locality"
},
  "geometry": {"coordinates":[115.54642,26.01545],"type":"Point"}
}