{
  "type": "Feature",
  "properties": {
    "gn:admin1_code":"30",
    "gn:asciiname":"Luogang",
    "gn:country_code":"CN",
    "gn:dem":188,
    "gn:feature_class":"P",
    "gn:feature_code":"PPLA4",
    "gn:name":"Luogang",
    "gn:population":0,
    "gn:timezone":"Asia/Shanghai",
    "iso:country":"CN",
    "name:und_x_variant":[
        "Luogang Zhen",
        "\u7f57\u5c97\u9547"
    ],
    "name:zho_x_preferred":[
        "\u7f57\u5c97"
    ],
    "wof:name":"Luogang",
    "wof:placetype":"locality"
},
  "geometry": {"coordinates":[115.62972000000001,24.42664],"type":"Point"}
}