{
  "type": "Feature",
  "properties": {
    "gn:admin1_code":"7.0",
    "gn:asciiname":"Huangkeng",
    "gn:country_code":"CN",
    "gn:dem":364,
    "gn:feature_class":"P",
    "gn:feature_code":"PPL",
    "gn:name":"Huangkeng",
    "gn:population":0,
    "gn:timezone":"Asia/Shanghai",
    "iso:country":"CN",
    "name:und_x_variant":[
        "\u9ec4\u5751"
    ],
    "name:zho_x_preferred":[
        "\u9ec4\u5751"
    ],
    "wof:name":"Huangkeng",
    "wof:placetype":"locality"
},
  "geometry": {"coordinates":[117.71232999999999,26.68692],"type":"Point"}
}