{
  "type": "Feature",
  "properties": {
    "gn:admin1_code":"4.0",
    "gn:asciiname":"Honglin",
    "gn:country_code":"CN",
    "gn:dem":2,
    "gn:feature_class":"P",
    "gn:feature_code":"PPL",
    "gn:name":"Honglin",
    "gn:population":0,
    "gn:timezone":"Asia/Shanghai",
    "iso:country":"CN",
    "name:zho_x_preferred":[
        "Honglin"
    ],
    "name:zho_x_variant":[
        "\u6d2a\u6797"
    ],
    "wof:name":"Honglin",
    "wof:placetype":"locality"
},
  "geometry": {"coordinates":[119.75666,33.98179],"type":"Point"}
}