{
  "type": "Feature",
  "properties": {
    "gn:admin1_code":"26",
    "gn:asciiname":"Mucun",
    "gn:country_code":"CN",
    "gn:dem":473,
    "gn:feature_class":"P",
    "gn:feature_code":"PPL",
    "gn:name":"Mucun",
    "gn:population":0,
    "gn:timezone":"Asia/Shanghai",
    "iso:country":"CN",
    "name:und_x_variant":[
        "\u7766\u6751"
    ],
    "name:zho_x_preferred":[
        "\u7766\u6751"
    ],
    "wof:name":"Mucun",
    "wof:placetype":"locality"
},
  "geometry": {"coordinates":[108.79971999999999,34.47444],"type":"Point"}
}