{
  "type": "Feature",
  "properties": {
    "gn:admin1_code":"5.0",
    "gn:asciiname":"Gangouzhang",
    "gn:country_code":"CN",
    "gn:dem":710,
    "gn:feature_class":"P",
    "gn:feature_code":"PPL",
    "gn:name":"Gangouzhang",
    "gn:population":0,
    "gn:timezone":"Asia/Shanghai",
    "iso:country":"CN",
    "name:und_x_variant":[
        "\u5e72\u6c9f\u638c"
    ],
    "wof:name":"Gangouzhang",
    "wof:placetype":"locality"
},
  "geometry": {"coordinates":[126.14058,41.93077],"type":"Point"}
}