{
  "type": "Feature",
  "properties": {
    "gn:admin1_code":"26",
    "gn:asciiname":"Huojialing",
    "gn:country_code":"CN",
    "gn:dem":1203,
    "gn:feature_class":"P",
    "gn:feature_code":"PPL",
    "gn:name":"Huojialing",
    "gn:population":0,
    "gn:timezone":"Asia/Shanghai",
    "iso:country":"CN",
    "name:und_x_variant":[
        "\u970d\u5bb6\u5cad"
    ],
    "name:zho_x_preferred":[
        "\u970d\u5bb6\u5cad"
    ],
    "wof:name":"Huojialing",
    "wof:placetype":"locality"
},
  "geometry": {"coordinates":[108.66583,34.90417],"type":"Point"}
}