{
  "type": "Feature",
  "properties": {
    "gn:admin1_code":"15.0",
    "gn:asciiname":"Bentuo",
    "gn:country_code":"CN",
    "gn:dem":1984,
    "gn:feature_class":"P",
    "gn:feature_code":"PPL",
    "gn:name":"Bentuo",
    "gn:population":0,
    "gn:timezone":"Asia/Shanghai",
    "iso:country":"CN",
    "name:zho_x_preferred":[
        "\u672c\u9a6e"
    ],
    "wof:name":"Bentuo",
    "wof:placetype":"locality"
},
  "geometry": {"coordinates":[104.791,35.1131],"type":"Point"}
}