{
  "type": "Feature",
  "properties": {
    "gn:admin1_code":"30",
    "gn:asciiname":"Muqidong",
    "gn:country_code":"CN",
    "gn:dem":48,
    "gn:feature_class":"P",
    "gn:feature_code":"PPL",
    "gn:name":"Muqidong",
    "gn:population":0,
    "gn:timezone":"Asia/Urumqi",
    "iso:country":"CN",
    "name:zho_x_preferred":[
        "\u6728\u4e03\u578c"
    ],
    "wof:name":"Muqidong",
    "wof:placetype":"locality"
},
  "geometry": {"coordinates":[110.2655,21.76274],"type":"Point"}
}