{
  "type": "Feature",
  "properties": {
    "gn:admin1_code":"16.0",
    "gn:asciiname":"Xiapoluan",
    "gn:country_code":"CN",
    "gn:dem":720,
    "gn:feature_class":"P",
    "gn:feature_code":"PPL",
    "gn:name":"Xiapoluan",
    "gn:population":0,
    "gn:timezone":"Asia/Shanghai",
    "iso:country":"CN",
    "name:zho_x_preferred":[
        "\u4e0b\u5761\u4e71"
    ],
    "wof:name":"Xiapoluan",
    "wof:placetype":"locality"
},
  "geometry": {"coordinates":[107.20099999999999,24.3389],"type":"Point"}
}