{
  "type": "Feature",
  "properties": {
    "gn:admin1_code":"18",
    "gn:asciiname":"Laoyingdong",
    "gn:country_code":"CN",
    "gn:dem":922,
    "gn:feature_class":"P",
    "gn:feature_code":"PPL",
    "gn:name":"Laoyingdong",
    "gn:population":0,
    "gn:timezone":"Asia/Shanghai",
    "iso:country":"CN",
    "name:zho_x_preferred":[
        "\u8001\u9e70\u6d1e"
    ],
    "wof:name":"Laoyingdong",
    "wof:placetype":"locality"
},
  "geometry": {"coordinates":[107.336,28.3025],"type":"Point"}
}