{
  "type": "Feature",
  "properties": {
    "gn:admin1_code":"3.0",
    "gn:asciiname":"Heyuan Linchang",
    "gn:country_code":"CN",
    "gn:dem":294,
    "gn:feature_class":"P",
    "gn:feature_code":"PPLF",
    "gn:name":"Heyuan Linchang",
    "gn:population":0,
    "gn:timezone":"Asia/Shanghai",
    "iso:country":"CN",
    "name:und_x_variant":[
        "\u5408\u6c85\u6797\u573a"
    ],
    "wof:name":"Heyuan Linchang",
    "wof:placetype":"locality"
},
  "geometry": {"coordinates":[114.99838,29.46297],"type":"Point"}
}