{
  "type": "Feature",
  "properties": {
    "gn:admin1_code":"8.0",
    "gn:asciiname":"Sikehua",
    "gn:country_code":"CN",
    "gn:dem":239,
    "gn:feature_class":"P",
    "gn:feature_code":"PPL",
    "gn:name":"Sikehua",
    "gn:population":0,
    "gn:timezone":"Asia/Shanghai",
    "iso:country":"CN",
    "name:zho_x_preferred":[
        "\u56db\u68f5\u6866"
    ],
    "wof:name":"Sikehua",
    "wof:placetype":"locality"
},
  "geometry": {"coordinates":[126.86409999999999,47.79344],"type":"Point"}
}