{
  "type": "Feature",
  "properties": {
    "gn:admin1_code":"24",
    "gn:asciiname":"Liujiagou",
    "gn:cc2":"CN",
    "gn:country_code":"CN",
    "gn:dem":1446,
    "gn:feature_class":"P",
    "gn:feature_code":"PPL",
    "gn:name":"Liujiagou",
    "gn:population":0,
    "gn:timezone":"Asia/Shanghai",
    "iso:country":"CN",
    "name:und_x_variant":[
        "Liu-chia-kou",
        "Liujiagou"
    ],
    "wof:name":"Liujiagou",
    "wof:placetype":"locality"
},
  "geometry": {"coordinates":[111.31667,37.43333],"type":"Point"}
}