{
  "type": "Feature",
  "properties": {
    "gn:admin1_code":"8.0",
    "gn:asciiname":"Dongsheng Liudui",
    "gn:country_code":"CN",
    "gn:dem":170,
    "gn:feature_class":"P",
    "gn:feature_code":"PPLF",
    "gn:name":"Dongsheng Liudui",
    "gn:population":0,
    "gn:timezone":"Asia/Shanghai",
    "iso:country":"CN",
    "name:zho_x_preferred":[
        "\u4e1c\u80dc\u516d\u961f"
    ],
    "wof:name":"Dongsheng Liudui",
    "wof:placetype":"locality"
},
  "geometry": {"coordinates":[124.09713000000001,48.05027000000001],"type":"Point"}
}