{
  "type": "Feature",
  "properties": {
    "gn:admin1_code":"26",
    "gn:asciiname":"Xiangyanggou",
    "gn:country_code":"CN",
    "gn:dem":447,
    "gn:feature_class":"P",
    "gn:feature_code":"PPL",
    "gn:name":"Xiangyanggou",
    "gn:population":0,
    "gn:timezone":"Asia/Shanghai",
    "iso:country":"CN",
    "name:und_x_variant":[
        "\u5411\u9633\u6c9f"
    ],
    "wof:name":"Xiangyanggou",
    "wof:placetype":"locality"
},
  "geometry": {"coordinates":[109.06167000000001,34.25778],"type":"Point"}
}