{
  "type": "Feature",
  "properties": {
    "gn:admin1_code":"24",
    "gn:asciiname":"Hongshui",
    "gn:cc2":"CN",
    "gn:country_code":"CN",
    "gn:dem":1117,
    "gn:feature_class":"P",
    "gn:feature_code":"PPL",
    "gn:name":"Hongshui",
    "gn:population":0,
    "gn:timezone":"Asia/Shanghai",
    "iso:country":"CN",
    "name:ara_x_preferred":[
        "\u0647\u0648\u0646\u063a\u0634\u0648\u064a"
    ],
    "name:ben_x_preferred":[
        "\u09b9\u0982\u09b6\u09cd\u09af\u09c1\u0987"
    ],
    "name:deu_x_preferred":[
        "Hongshui"
    ],
    "name:ell_x_preferred":[
        "\u03a7\u03bf\u03bd\u03b3\u03ba\u03c3\u03bf\u03cd\u03b9"
    ],
    "name:fas_x_preferred":[
        "\u0647\u0648\u0646\u06af\u0634\u0648\u06cc"
    ],
    "name:heb_x_preferred":[
        "\u05d4\u05d5\u05e0\u05d2\u05e9\u05d5\u05d9"
    ],
    "name:hin_x_preferred":[
        "\u0939\u094b\u0902\u0917\u0936\u0941\u0908"
    ],
    "name:hun_x_preferred":[
        "Hongshui"
    ],
    "name:ind_x_preferred":[
        "Hongshui"
    ],
    "name:ita_x_preferred":[
        "Hongshui"
    ],
    "name:jpn_x_preferred":[
        "\u7d05\u6c34\u6cb3"
    ],
    "name:kor_x_preferred":[
        "\ud64d\uc218\uc774"
    ],
    "name:nld_x_preferred":[
        "Hongshui"
    ],
    "name:por_x_preferred":[
        "Hongshui"
    ],
    "name:tur_x_preferred":[
        "Hongshui"
    ],
    "name:ukr_x_preferred":[
        "\u0425\u0443\u043d\u0448\u0443\u0439\u0445\u0435"
    ],
    "name:und_x_variant":[
        "Hung-shui-chen",
        "Hung-shui",
        "Hongshui"
    ],
    "name:urd_x_preferred":[
        "\u06c1\u0627\u0646\u06af\u0634\u0648\u0626\u06cc"
    ],
    "wof:name":"Hongshui",
    "wof:placetype":"locality"
},
  "geometry": {"coordinates":[113.22278,36.86778],"type":"Point"}
}