{
  "type": "Feature",
  "properties": {
    "gn:admin1_code":"24",
    "gn:asciiname":"Hongshui",
    "gn:cc2":"CN",
    "gn:country_code":"CN",
    "gn:dem":1117,
    "gn:feature_class":"P",
    "gn:feature_code":"PPL",
    "gn:name":"Hongshui",
    "gn:population":0,
    "gn:timezone":"Asia/Shanghai",
    "iso:country":"CN",
    "name:und_x_variant":[
        "Hung-shui-chen",
        "Hung-shui",
        "Hongshui"
    ],
    "wof:name":"Hongshui",
    "wof:placetype":"locality"
},
  "geometry": {"coordinates":[113.22278,36.86778],"type":"Point"}
}