{
  "type": "Feature",
  "properties": {
    "gn:admin1_code":"2.0",
    "gn:asciiname":"Erbaiyang",
    "gn:country_code":"CN",
    "gn:dem":507,
    "gn:feature_class":"P",
    "gn:feature_code":"PPL",
    "gn:name":"Erbaiyang",
    "gn:population":0,
    "gn:timezone":"Asia/Shanghai",
    "iso:country":"CN",
    "name:zho_x_preferred":[
        "\u4e8c\u767e\u592e"
    ],
    "wof:name":"Erbaiyang",
    "wof:placetype":"locality"
},
  "geometry": {"coordinates":[121.24377,29.11603],"type":"Point"}
}