{
  "type": "Feature",
  "properties": {
    "gn:admin1_code":"9.0",
    "gn:asciiname":"Lijialou",
    "gn:country_code":"CN",
    "gn:dem":155,
    "gn:feature_class":"P",
    "gn:feature_code":"PPL",
    "gn:name":"Lijialou",
    "gn:population":0,
    "gn:timezone":"Asia/Shanghai",
    "iso:country":"CN",
    "name:zho_x_preferred":[
        "\u674e\u5bb6\u697c"
    ],
    "wof:name":"Lijialou",
    "wof:placetype":"locality"
},
  "geometry": {"coordinates":[112.69441999999999,33.19433],"type":"Point"}
}