{
  "type": "Feature",
  "properties": {
    "gn:admin1_code":"1.0",
    "gn:asciiname":"Caoqiaocun",
    "gn:country_code":"CN",
    "gn:dem":34,
    "gn:feature_class":"P",
    "gn:feature_code":"PPL",
    "gn:name":"Caoqiaocun",
    "gn:population":0,
    "gn:timezone":"Asia/Shanghai",
    "iso:country":"CN",
    "name:zho_x_preferred":[
        "\u66f9\u6865\u6751"
    ],
    "wof:name":"Caoqiaocun",
    "wof:placetype":"locality"
},
  "geometry": {"coordinates":[116.94934000000001,32.537],"type":"Point"}
}