{
  "type": "Feature",
  "properties": {
    "gn:admin1_code":"26",
    "gn:asciiname":"Maobahe",
    "gn:country_code":"CN",
    "gn:dem":914,
    "gn:feature_class":"P",
    "gn:feature_code":"PPL",
    "gn:name":"Maobahe",
    "gn:population":0,
    "gn:timezone":"Asia/Shanghai",
    "iso:country":"CN",
    "name:und_x_variant":[
        "Mao-pa-ho",
        "Maobahe",
        "\u6bdb\u575d\u6cb3",
        "Maobahezhen",
        "\u6bdb\u575d\u6cb3\u9547"
    ],
    "wof:name":"Maobahe",
    "wof:placetype":"locality"
},
  "geometry": {"coordinates":[106.33351999999999,32.68524],"type":"Point"}
}