{
  "type": "Feature",
  "properties": {
    "gn:admin1_code":"10",
    "gn:asciiname":"Chengzigou",
    "gn:country_code":"CN",
    "gn:dem":1375,
    "gn:feature_class":"P",
    "gn:feature_code":"PPL",
    "gn:name":"Chengzigou",
    "gn:population":0,
    "gn:timezone":"Asia/Shanghai",
    "iso:country":"CN",
    "name:zho_x_preferred":[
        "\u57ce\u5b50\u6c9f"
    ],
    "wof:name":"Chengzigou",
    "wof:placetype":"locality"
},
  "geometry": {"coordinates":[116.76117000000001,41.82738],"type":"Point"}
}