{
  "type": "Feature",
  "properties": {
    "gn:admin1_code":"29.0",
    "gn:asciiname":"Shangshuijing",
    "gn:country_code":"CN",
    "gn:dem":2469,
    "gn:feature_class":"P",
    "gn:feature_code":"PPL",
    "gn:name":"Shangshuijing",
    "gn:population":0,
    "gn:timezone":"Asia/Shanghai",
    "iso:country":"CN",
    "name:zho_x_preferred":[
        "\u4e0a\u6c34\u4e95"
    ],
    "wof:name":"Shangshuijing",
    "wof:placetype":"locality"
},
  "geometry": {"coordinates":[99.8481,25.658],"type":"Point"}
}