{
  "type": "Feature",
  "properties": {
    "gn:admin1_code":"24.0",
    "gn:asciiname":"Lishi",
    "gn:country_code":"CN",
    "gn:dem":1590,
    "gn:feature_class":"P",
    "gn:feature_code":"PPL",
    "gn:name":"Lishi",
    "gn:population":0,
    "gn:timezone":"Asia/Shanghai",
    "iso:country":"CN",
    "name:und_x_variant":[
        "\u7acb\u77f3"
    ],
    "name:zho_x_preferred":[
        "\u7acb\u77f3"
    ],
    "wof:name":"Lishi",
    "wof:placetype":"locality"
},
  "geometry": {"coordinates":[112.61726000000002,40.20845],"type":"Point"}
}