{
  "type": "Feature",
  "properties": {
    "gn:admin1_code":"4.0",
    "gn:asciiname":"Jiangoucun",
    "gn:country_code":"CN",
    "gn:dem":5,
    "gn:feature_class":"P",
    "gn:feature_code":"PPL",
    "gn:name":"Jiangoucun",
    "gn:population":0,
    "gn:timezone":"Asia/Shanghai",
    "iso:country":"CN",
    "name:zho_x_preferred":[
        "\u6da7\u6c9f\u6751"
    ],
    "wof:name":"Jiangoucun",
    "wof:placetype":"locality"
},
  "geometry": {"coordinates":[120.78296,31.8443],"type":"Point"}
}