{
  "type": "Feature",
  "properties": {
    "gn:admin1_code":"30.0",
    "gn:asciiname":"Bailu'ao",
    "gn:country_code":"CN",
    "gn:dem":53,
    "gn:feature_class":"P",
    "gn:feature_code":"PPL",
    "gn:name":"Bailu\u2019ao",
    "gn:population":0,
    "gn:timezone":"Asia/Shanghai",
    "iso:country":"CN",
    "name:zho_x_preferred":[
        "\u767d\u8def\u51f9"
    ],
    "name:zho_x_variant":[
        "Bailu\u2019ao"
    ],
    "wof:name":"Bailu'ao",
    "wof:placetype":"locality"
},
  "geometry": {"coordinates":[114.9436,23.07326],"type":"Point"}
}