{
  "type": "Feature",
  "properties": {
    "gn:admin1_code":"12.0",
    "gn:asciiname":"Sanguandian",
    "gn:country_code":"CN",
    "gn:dem":27,
    "gn:feature_class":"P",
    "gn:feature_code":"PPL",
    "gn:name":"Sanguandian",
    "gn:population":0,
    "gn:timezone":"Asia/Shanghai",
    "iso:country":"CN",
    "name:zho_x_preferred":[
        "\u4e09\u5b98\u6bbf"
    ],
    "wof:name":"Sanguandian",
    "wof:placetype":"locality"
},
  "geometry": {"coordinates":[113.1682,30.05526],"type":"Point"}
}