{
  "type": "Feature",
  "properties": {
    "gn:admin1_code":"12.0",
    "gn:asciiname":"Shangma Yatou",
    "gn:country_code":"CN",
    "gn:dem":545,
    "gn:feature_class":"P",
    "gn:feature_code":"PPL",
    "gn:name":"Shangma Yatou",
    "gn:population":0,
    "gn:timezone":"Asia/Shanghai",
    "iso:country":"CN",
    "name:zho_x_preferred":[
        "\u4e0a\u9ebb\u57ad\u5934"
    ],
    "wof:name":"Shangma Yatou",
    "wof:placetype":"locality"
},
  "geometry": {"coordinates":[110.42892999999999,29.68446],"type":"Point"}
}