{
  "type": "Feature",
  "properties": {
    "gn:admin1_code":"26.0",
    "gn:asciiname":"Chengze",
    "gn:country_code":"CN",
    "gn:dem":1575,
    "gn:feature_class":"P",
    "gn:feature_code":"PPL",
    "gn:name":"Chengze",
    "gn:population":0,
    "gn:timezone":"Asia/Shanghai",
    "iso:country":"CN",
    "name:zho_x_preferred":[
        "\u57ce\u5219"
    ],
    "wof:name":"Chengze",
    "wof:placetype":"locality"
},
  "geometry": {"coordinates":[108.56464,37.24105],"type":"Point"}
}