{
  "type": "Feature",
  "properties": {
    "gn:admin1_code":"32.0",
    "gn:asciiname":"Shawan",
    "gn:country_code":"CN",
    "gn:dem":3431,
    "gn:feature_class":"P",
    "gn:feature_code":"PPL",
    "gn:name":"Shawan",
    "gn:population":0,
    "gn:timezone":"Asia/Shanghai",
    "iso:country":"CN",
    "name:zho_x_preferred":[
        "\u6c99\u6e7e"
    ],
    "wof:name":"Shawan",
    "wof:placetype":"locality"
},
  "geometry": {"coordinates":[100.477,31.5322],"type":"Point"}
}