{
  "type": "Feature",
  "properties": {
    "gn:admin1_code":"19.0",
    "gn:asciiname":"Linjiafengou",
    "gn:country_code":"CN",
    "gn:dem":150,
    "gn:feature_class":"P",
    "gn:feature_code":"PPL",
    "gn:name":"Linjiafengou",
    "gn:population":0,
    "gn:timezone":"Asia/Shanghai",
    "iso:country":"CN",
    "name:zho_x_preferred":[
        "\u6797\u5bb6\u575f\u6c9f"
    ],
    "wof:name":"Linjiafengou",
    "wof:placetype":"locality"
},
  "geometry": {"coordinates":[123.765,42.0145],"type":"Point"}
}