{
  "type": "Feature",
  "properties": {
    "gn:admin1_code":"12.0",
    "gn:asciiname":"Yantangya",
    "gn:country_code":"CN",
    "gn:dem":911,
    "gn:feature_class":"P",
    "gn:feature_code":"PPL",
    "gn:name":"Yantangya",
    "gn:population":0,
    "gn:timezone":"Asia/Shanghai",
    "iso:country":"CN",
    "name:zho_x_preferred":[
        "\u5830\u5858\u57ad"
    ],
    "wof:name":"Yantangya",
    "wof:placetype":"locality"
},
  "geometry": {"coordinates":[109.68865,32.18404],"type":"Point"}
}