{
  "type": "Feature",
  "properties": {
    "gn:admin1_code":"32.0",
    "gn:asciiname":"Weijia Citang",
    "gn:country_code":"CN",
    "gn:dem":327,
    "gn:feature_class":"P",
    "gn:feature_code":"PPL",
    "gn:name":"Weijia Citang",
    "gn:population":0,
    "gn:timezone":"Asia/Shanghai",
    "iso:country":"CN",
    "name:zho_x_preferred":[
        "\u9b4f\u5bb6\u7960\u5802"
    ],
    "wof:name":"Weijia Citang",
    "wof:placetype":"locality"
},
  "geometry": {"coordinates":[104.88800000000001,29.7707],"type":"Point"}
}