{
  "type": "Feature",
  "properties": {
    "gn:admin1_code":"4.0",
    "gn:asciiname":"Luwacun",
    "gn:country_code":"CN",
    "gn:dem":25,
    "gn:feature_class":"P",
    "gn:feature_code":"PPL",
    "gn:name":"L\u00fcwacun",
    "gn:population":0,
    "gn:timezone":"Asia/Shanghai",
    "iso:country":"CN",
    "name:und_x_variant":[
        "L\u00fcwacun"
    ],
    "name:zho_x_preferred":[
        "\u5415\u6d3c\u6751"
    ],
    "wof:name":"Luwacun",
    "wof:placetype":"locality"
},
  "geometry": {"coordinates":[117.85687,33.8465],"type":"Point"}
}