{
  "type": "Feature",
  "properties": {
    "gn:admin1_code":"24.0",
    "gn:asciiname":"Xiaolijiayuancun",
    "gn:country_code":"CN",
    "gn:dem":944,
    "gn:feature_class":"P",
    "gn:feature_code":"PPL",
    "gn:name":"Xiaolijiayuancun",
    "gn:population":0,
    "gn:timezone":"Asia/Shanghai",
    "iso:country":"CN",
    "name:zho_x_preferred":[
        "\u5c0f\u674e\u5bb6\u57a3\u6751"
    ],
    "wof:name":"Xiaolijiayuancun",
    "wof:placetype":"locality"
},
  "geometry": {"coordinates":[110.79661000000002,37.43782],"type":"Point"}
}