{
  "type": "Feature",
  "properties": {
    "gn:admin1_code":"30.0",
    "gn:asciiname":"Zenggangfeng",
    "gn:country_code":"CN",
    "gn:dem":266,
    "gn:feature_class":"P",
    "gn:feature_code":"PPL",
    "gn:name":"Zenggangfeng",
    "gn:population":0,
    "gn:timezone":"Asia/Shanghai",
    "iso:country":"CN",
    "name:zho_x_preferred":[
        "\u66fe\u5c97\u5cef"
    ],
    "wof:name":"Zenggangfeng",
    "wof:placetype":"locality"
},
  "geometry": {"coordinates":[115.40978,24.0083],"type":"Point"}
}