{
  "type": "Feature",
  "properties": {
    "gn:admin1_code":"19.0",
    "gn:asciiname":"Dalishucun",
    "gn:country_code":"CN",
    "gn:dem":105,
    "gn:feature_class":"P",
    "gn:feature_code":"PPL",
    "gn:name":"Dalishucun",
    "gn:population":0,
    "gn:timezone":"Asia/Shanghai",
    "iso:country":"CN",
    "name:zho_x_preferred":[
        "\u5927\u68a8\u6811\u6751"
    ],
    "wof:name":"Dalishucun",
    "wof:placetype":"locality"
},
  "geometry": {"coordinates":[123.96102999999999,40.40463],"type":"Point"}
}