{
  "type": "Feature",
  "properties": {
    "gn:admin1_code":"32.0",
    "gn:asciiname":"Yangjia",
    "gn:country_code":"CN",
    "gn:dem":310,
    "gn:feature_class":"P",
    "gn:feature_code":"PPL",
    "gn:name":"Yangjia",
    "gn:population":0,
    "gn:timezone":"Asia/Shanghai",
    "iso:country":"CN",
    "name:und_x_variant":[
        "Yang-chia-ch\u2019ang",
        "Yangjiachang",
        "Yangjia"
    ],
    "name:zho_x_preferred":[
        "\u6768\u5bb6"
    ],
    "wof:name":"Yangjia",
    "wof:placetype":"locality"
},
  "geometry": {"coordinates":[107.22547,30.85275],"type":"Point"}
}