{
  "type": "Feature",
  "properties": {
    "gn:admin1_code":"15.0",
    "gn:asciiname":"Jianzi",
    "gn:country_code":"CN",
    "gn:dem":2587,
    "gn:feature_class":"P",
    "gn:feature_code":"PPL",
    "gn:name":"Jianzi",
    "gn:population":0,
    "gn:timezone":"Asia/Shanghai",
    "iso:country":"CN",
    "name:ces_x_preferred":[
        "Vietnamsk\u00fd badminton"
    ],
    "name:deu_x_preferred":[
        "Federfu\u00dfball"
    ],
    "name:fas_x_preferred":[
        "\u062c\u06cc\u0627\u0646\u0632\u06cc"
    ],
    "name:fra_x_preferred":[
        "Plumfoot"
    ],
    "name:ind_x_preferred":[
        "Ji\u00e0nzi"
    ],
    "name:ita_x_preferred":[
        "Shuttlecock"
    ],
    "name:jpn_x_preferred":[
        "\u30b8\u30a7\u30f3\u30ba"
    ],
    "name:por_x_preferred":[
        "Jianzi"
    ],
    "name:spa_x_preferred":[
        "Jian zi"
    ],
    "name:tur_x_preferred":[
        "Jianzi"
    ],
    "name:und_x_variant":[
        "\u5c16\u5b50"
    ],
    "name:vie_x_preferred":[
        "\u0110\u00e1 c\u1ea7u"
    ],
    "wof:name":"Jianzi",
    "wof:placetype":"locality"
},
  "geometry": {"coordinates":[104.11196,34.82227],"type":"Point"}
}