{
  "type": "Feature",
  "properties": {
    "gn:admin1_code":"15.0",
    "gn:asciiname":"Jianzi",
    "gn:country_code":"CN",
    "gn:dem":2587,
    "gn:feature_class":"P",
    "gn:feature_code":"PPL",
    "gn:name":"Jianzi",
    "gn:population":0,
    "gn:timezone":"Asia/Shanghai",
    "iso:country":"CN",
    "name:und_x_variant":[
        "\u5c16\u5b50"
    ],
    "wof:name":"Jianzi",
    "wof:placetype":"locality"
},
  "geometry": {"coordinates":[104.11196,34.82227],"type":"Point"}
}