{
  "type": "Feature",
  "properties": {
    "gn:admin1_code":"10",
    "gn:asciiname":"Seshugou",
    "gn:country_code":"CN",
    "gn:dem":1144,
    "gn:feature_class":"P",
    "gn:feature_code":"PPL",
    "gn:name":"Seshugou",
    "gn:population":0,
    "gn:timezone":"Asia/Shanghai",
    "iso:country":"CN",
    "name:zho_x_preferred":[
        "\u8272\u6811\u6c9f"
    ],
    "wof:name":"Seshugou",
    "wof:placetype":"locality"
},
  "geometry": {"coordinates":[116.92103,41.92228],"type":"Point"}
}