{
  "type": "Feature",
  "properties": {
    "gn:admin1_code":"21.0",
    "gn:asciiname":"Yang'erzhuang",
    "gn:country_code":"CN",
    "gn:dem":1509,
    "gn:feature_class":"P",
    "gn:feature_code":"PPL",
    "gn:name":"Yang\u2019erzhuang",
    "gn:population":0,
    "gn:timezone":"Asia/Shanghai",
    "iso:country":"CN",
    "name:und_x_variant":[
        "Yang\u2019erzhuang"
    ],
    "name:zho_x_preferred":[
        "\u6768\u513f\u5e84"
    ],
    "wof:name":"Yang'erzhuang",
    "wof:placetype":"locality"
},
  "geometry": {"coordinates":[106.87,37.4667],"type":"Point"}
}