{
  "type": "Feature",
  "properties": {
    "gn:admin1_code":"26.0",
    "gn:asciiname":"Houmaliangou",
    "gn:country_code":"CN",
    "gn:dem":1288,
    "gn:feature_class":"P",
    "gn:feature_code":"PPL",
    "gn:name":"Houmaliangou",
    "gn:population":0,
    "gn:timezone":"Asia/Shanghai",
    "iso:country":"CN",
    "name:zho_x_preferred":[
        "\u540e\u9a6c\u83b2\u6c9f"
    ],
    "wof:name":"Houmaliangou",
    "wof:placetype":"locality"
},
  "geometry": {"coordinates":[108.37387,36.70572],"type":"Point"}
}