{
  "type": "Feature",
  "properties": {
    "gn:admin1_code":"30.0",
    "gn:asciiname":"Xiewucun",
    "gn:country_code":"CN",
    "gn:dem":77,
    "gn:feature_class":"P",
    "gn:feature_code":"PPL",
    "gn:name":"Xiewucun",
    "gn:population":0,
    "gn:timezone":"Asia/Shanghai",
    "iso:country":"CN",
    "name:zho_x_preferred":[
        "\u8c22\u5c4b\u6751"
    ],
    "wof:name":"Xiewucun",
    "wof:placetype":"locality"
},
  "geometry": {"coordinates":[111.96679,24.01947],"type":"Point"}
}