{
  "type": "Feature",
  "properties": {
    "gn:admin1_code":"18",
    "gn:asciiname":"Tiechang",
    "gn:country_code":"CN",
    "gn:dem":842,
    "gn:feature_class":"P",
    "gn:feature_code":"PPL",
    "gn:name":"Tiechang",
    "gn:population":0,
    "gn:timezone":"Asia/Shanghai",
    "iso:country":"CN",
    "wof:name":"Tiechang",
    "wof:placetype":"locality"
},
  "geometry": {"coordinates":[107.20778,27.45722],"type":"Point"}
}