{
  "type": "Feature",
  "properties": {
    "gn:admin1_code":"4.0",
    "gn:asciiname":"Guangnancun",
    "gn:country_code":"CN",
    "gn:dem":28,
    "gn:feature_class":"P",
    "gn:feature_code":"PPL",
    "gn:name":"Guangnancun",
    "gn:population":0,
    "gn:timezone":"Asia/Shanghai",
    "iso:country":"CN",
    "name:zho_x_preferred":[
        "\u5149\u5357\u6751"
    ],
    "wof:name":"Guangnancun",
    "wof:placetype":"locality"
},
  "geometry": {"coordinates":[117.741,33.9808],"type":"Point"}
}