{
  "type": "Feature",
  "properties": {
    "gn:admin1_code":"29.0",
    "gn:asciiname":"Pendaiyang",
    "gn:country_code":"CN",
    "gn:dem":1222,
    "gn:feature_class":"P",
    "gn:feature_code":"PPL",
    "gn:name":"Pendaiyang",
    "gn:population":0,
    "gn:timezone":"Asia/Shanghai",
    "iso:country":"CN",
    "name:zho_x_preferred":[
        "\u76c6\u4ee3\u6d0b"
    ],
    "wof:name":"Pendaiyang",
    "wof:placetype":"locality"
},
  "geometry": {"coordinates":[97.7988,24.9867],"type":"Point"}
}