{
  "type": "Feature",
  "properties": {
    "gn:admin1_code":"10",
    "gn:asciiname":"Taitougou",
    "gn:country_code":"CN",
    "gn:dem":1516,
    "gn:feature_class":"P",
    "gn:feature_code":"PPL",
    "gn:name":"Taitougou",
    "gn:population":0,
    "gn:timezone":"Asia/Shanghai",
    "iso:country":"CN",
    "name:zho_x_preferred":[
        "\u62ac\u5934\u6c9f"
    ],
    "wof:name":"Taitougou",
    "wof:placetype":"locality"
},
  "geometry": {"coordinates":[116.04922000000001,41.59915],"type":"Point"}
}