{
  "type": "Feature",
  "properties": {
    "gn:admin1_code":"19.0",
    "gn:asciiname":"Luoquanbeicun",
    "gn:country_code":"CN",
    "gn:dem":200,
    "gn:feature_class":"P",
    "gn:feature_code":"PPL",
    "gn:name":"Luoquanbeicun",
    "gn:population":0,
    "gn:timezone":"Asia/Shanghai",
    "iso:country":"CN",
    "name:zho_x_preferred":[
        "\u7f57\u5708\u80cc\u6751"
    ],
    "wof:name":"Luoquanbeicun",
    "wof:placetype":"locality"
},
  "geometry": {"coordinates":[124.476,40.5133],"type":"Point"}
}