{
  "type": "Feature",
  "properties": {
    "gn:admin1_code":"30.0",
    "gn:asciiname":"Qiaoyang",
    "gn:country_code":"CN",
    "gn:dem":8,
    "gn:feature_class":"P",
    "gn:feature_code":"PPL",
    "gn:name":"Qiaoyang",
    "gn:population":0,
    "gn:timezone":"Asia/Shanghai",
    "iso:country":"CN",
    "name:zho_x_preferred":[
        "\u6a35\u9633"
    ],
    "wof:name":"Qiaoyang",
    "wof:placetype":"locality"
},
  "geometry": {"coordinates":[112.99142000000001,22.93481],"type":"Point"}
}