{
  "type": "Feature",
  "properties": {
    "gn:admin1_code":"25",
    "gn:asciiname":"Lihaoke",
    "gn:country_code":"CN",
    "gn:dem":60,
    "gn:feature_class":"P",
    "gn:feature_code":"PPL",
    "gn:name":"Lihaoke",
    "gn:population":0,
    "gn:timezone":"Asia/Shanghai",
    "iso:country":"CN",
    "name:zho_x_preferred":[
        "\u674e\u84bf\u79d1"
    ],
    "wof:name":"Lihaoke",
    "wof:placetype":"locality"
},
  "geometry": {"coordinates":[118.617,34.9079],"type":"Point"}
}