{
  "type": "Feature",
  "properties": {
    "gn:admin1_code":"31.0",
    "gn:asciiname":"Zoumayuan",
    "gn:country_code":"CN",
    "gn:dem":10,
    "gn:feature_class":"P",
    "gn:feature_code":"PPL",
    "gn:name":"Zoumayuan",
    "gn:population":0,
    "gn:timezone":"Asia/Shanghai",
    "iso:country":"CN",
    "name:zho_x_preferred":[
        "Zoumayuan"
    ],
    "name:zho_x_variant":[
        "\u8d70\u9a6c\u56ed"
    ],
    "wof:name":"Zoumayuan",
    "wof:placetype":"locality"
},
  "geometry": {"coordinates":[110.81959999999999,19.54846],"type":"Point"}
}