{
  "type": "Feature",
  "properties": {
    "gn:admin1_code":"25",
    "gn:asciiname":"Shili Beicun",
    "gn:country_code":"CN",
    "gn:dem":39,
    "gn:feature_class":"P",
    "gn:feature_code":"PPL",
    "gn:name":"Shili Beicun",
    "gn:population":0,
    "gn:timezone":"Asia/Shanghai",
    "iso:country":"CN",
    "name:zho_x_preferred":[
        "\u77f3\u91cc\u5317\u6751"
    ],
    "wof:name":"Shili Beicun",
    "wof:placetype":"locality"
},
  "geometry": {"coordinates":[116.764,35.2782],"type":"Point"}
}