{
  "type": "Feature",
  "properties": {
    "gn:admin1_code":"2.0",
    "gn:asciiname":"Guojiaqiao",
    "gn:country_code":"CN",
    "gn:dem":7,
    "gn:feature_class":"P",
    "gn:feature_code":"PPL",
    "gn:name":"Guojiaqiao",
    "gn:population":0,
    "gn:timezone":"Asia/Shanghai",
    "iso:country":"CN",
    "name:und_x_variant":[
        "\u90ed\u5bb6\u6865"
    ],
    "wof:name":"Guojiaqiao",
    "wof:placetype":"locality"
},
  "geometry": {"coordinates":[120.78998,30.74241],"type":"Point"}
}