{
  "type": "Feature",
  "properties": {
    "gn:admin1_code":"30",
    "gn:asciiname":"Bizhoucun",
    "gn:country_code":"CN",
    "gn:dem":12,
    "gn:feature_class":"P",
    "gn:feature_code":"PPL",
    "gn:name":"Bizhoucun",
    "gn:population":0,
    "gn:timezone":"Asia/Shanghai",
    "iso:country":"CN",
    "name:und_x_variant":[
        "Bizhou",
        "Bizhoucun"
    ],
    "name:zho_x_preferred":[
        "\u78a7\u6d32\u6751"
    ],
    "wof:name":"Bizhoucun",
    "wof:placetype":"locality"
},
  "geometry": {"coordinates":[117.02195,23.62003],"type":"Point"}
}