{
  "type": "Feature",
  "properties": {
    "gn:admin1_code":"15.0",
    "gn:asciiname":"Dongguan",
    "gn:country_code":"CN",
    "gn:dem":1673,
    "gn:feature_class":"P",
    "gn:feature_code":"PPL",
    "gn:name":"Dongguan",
    "gn:population":0,
    "gn:timezone":"Asia/Shanghai",
    "iso:country":"CN",
    "name:und_x_variant":[
        "\u4e1c\u5173"
    ],
    "wof:name":"Dongguan",
    "wof:placetype":"locality"
},
  "geometry": {"coordinates":[105.74175,35.52258],"type":"Point"}
}