{
  "type": "Feature",
  "properties": {
    "gn:admin1_code":"3",
    "gn:asciiname":"Miaoziqian",
    "gn:country_code":"CN",
    "gn:dem":384,
    "gn:feature_class":"P",
    "gn:feature_code":"PPL",
    "gn:name":"Miaoziqian",
    "gn:population":0,
    "gn:timezone":"Asia/Shanghai",
    "iso:country":"CN",
    "name:zho_x_preferred":[
        "\u5e99\u5b50\u524d"
    ],
    "wof:name":"Miaoziqian",
    "wof:placetype":"locality"
},
  "geometry": {"coordinates":[114.349,26.4842],"type":"Point"}
}