{
  "type": "Feature",
  "properties": {
    "gn:admin1_code":"26.0",
    "gn:asciiname":"Jiegucun",
    "gn:country_code":"CN",
    "gn:dem":514,
    "gn:feature_class":"P",
    "gn:feature_code":"PPL",
    "gn:name":"Jiegucun",
    "gn:population":0,
    "gn:timezone":"Asia/Shanghai",
    "iso:country":"CN",
    "name:zho_x_preferred":[
        "\u63a5\u9aa8\u6751"
    ],
    "wof:name":"Jiegucun",
    "wof:placetype":"locality"
},
  "geometry": {"coordinates":[108.60926000000001,34.51765],"type":"Point"}
}