{
  "type": "Feature",
  "properties": {
    "gn:admin1_code":"1.0",
    "gn:asciiname":"Luhecun",
    "gn:country_code":"CN",
    "gn:dem":179,
    "gn:feature_class":"P",
    "gn:feature_code":"PPL",
    "gn:name":"L\u00fchecun",
    "gn:population":0,
    "gn:timezone":"Asia/Shanghai",
    "iso:country":"CN",
    "name:und_x_variant":[
        "L\u00fchecun"
    ],
    "name:zho_x_preferred":[
        "\u5415\u6cb3\u6751"
    ],
    "wof:name":"Luhecun",
    "wof:placetype":"locality"
},
  "geometry": {"coordinates":[115.8819,30.6521],"type":"Point"}
}