{
  "type": "Feature",
  "properties": {
    "gn:admin1_code":"19.0",
    "gn:asciiname":"Bei'anmincun",
    "gn:country_code":"CN",
    "gn:dem":16,
    "gn:feature_class":"P",
    "gn:feature_code":"PPL",
    "gn:name":"Bei\u2019anmincun",
    "gn:population":0,
    "gn:timezone":"Asia/Shanghai",
    "iso:country":"CN",
    "name:und_x_variant":[
        "Bei\u2019anmincun"
    ],
    "name:zho_x_preferred":[
        "\u5317\u5b89\u6c11\u6751"
    ],
    "wof:name":"Bei'anmincun",
    "wof:placetype":"locality"
},
  "geometry": {"coordinates":[124.31386000000001,40.00518],"type":"Point"}
}