{
  "type": "Feature",
  "properties": {
    "gn:admin1_code":"18.0",
    "gn:asciiname":"Jiangxipo",
    "gn:country_code":"CN",
    "gn:dem":1164,
    "gn:feature_class":"P",
    "gn:feature_code":"PPL",
    "gn:name":"Jiangxipo",
    "gn:population":0,
    "gn:timezone":"Asia/Shanghai",
    "iso:country":"CN",
    "name:zho_x_preferred":[
        "\u6c5f\u897f\u5761"
    ],
    "wof:name":"Jiangxipo",
    "wof:placetype":"locality"
},
  "geometry": {"coordinates":[107.285,27.1045],"type":"Point"}
}