{
  "type": "Feature",
  "properties": {
    "gn:admin1_code":"15.0",
    "gn:asciiname":"Wushiligou",
    "gn:country_code":"CN",
    "gn:dem":1277,
    "gn:feature_class":"P",
    "gn:feature_code":"PPL",
    "gn:name":"Wushiligou",
    "gn:population":0,
    "gn:timezone":"Asia/Shanghai",
    "iso:country":"CN",
    "name:und_x_variant":[
        "\u4e94\u5341\u91cc\u6c9f"
    ],
    "wof:name":"Wushiligou",
    "wof:placetype":"locality"
},
  "geometry": {"coordinates":[107.23522,36.6289],"type":"Point"}
}