{
  "type": "Feature",
  "properties": {
    "gn:admin1_code":"30.0",
    "gn:asciiname":"Laili",
    "gn:country_code":"CN",
    "gn:dem":32,
    "gn:feature_class":"P",
    "gn:feature_code":"PPL",
    "gn:name":"Laili",
    "gn:population":0,
    "gn:timezone":"Asia/Shanghai",
    "iso:country":"CN",
    "name:fas_x_preferred":[
        "\u0644\u06cc\u0644\u06cc"
    ],
    "name:zho_x_preferred":[
        "\u6765\u5229"
    ],
    "wof:name":"Laili",
    "wof:placetype":"locality"
},
  "geometry": {"coordinates":[114.43801999999999,22.83751],"type":"Point"}
}