{
  "type": "Feature",
  "properties": {
    "gn:admin1_code":"24",
    "gn:asciiname":"Dingyang",
    "gn:country_code":"CN",
    "gn:dem":1186,
    "gn:feature_class":"P",
    "gn:feature_code":"PPL",
    "gn:name":"Dingyang",
    "gn:population":0,
    "gn:timezone":"Asia/Shanghai",
    "iso:country":"CN",
    "name:und_x_variant":[
        "Ting-yang",
        "Ting-yang-ts\u2019un",
        "Dingyang"
    ],
    "name:zho_x_preferred":[
        "\u5b9a\u9633"
    ],
    "wof:name":"Dingyang",
    "wof:placetype":"locality"
},
  "geometry": {"coordinates":[112.37867,36.72116],"type":"Point"}
}