{
  "type": "Feature",
  "properties": {
    "gn:admin1_code":"32.0",
    "gn:asciiname":"Guangqiao",
    "gn:country_code":"CN",
    "gn:dem":434,
    "gn:feature_class":"P",
    "gn:feature_code":"PPL",
    "gn:name":"Guangqiao",
    "gn:population":0,
    "gn:timezone":"Asia/Shanghai",
    "iso:country":"CN",
    "name:zho_x_preferred":[
        "\u5e7f\u6865"
    ],
    "wof:name":"Guangqiao",
    "wof:placetype":"locality"
},
  "geometry": {"coordinates":[104.12,29.9414],"type":"Point"}
}