{
  "type": "Feature",
  "properties": {
    "gn:admin1_code":"29.0",
    "gn:asciiname":"Xiayanqing",
    "gn:country_code":"CN",
    "gn:dem":1962,
    "gn:feature_class":"P",
    "gn:feature_code":"PPL",
    "gn:name":"Xiayanqing",
    "gn:population":0,
    "gn:timezone":"Asia/Shanghai",
    "iso:country":"CN",
    "name:zho_x_preferred":[
        "\u4e0b\u5ca9\u7b90"
    ],
    "wof:name":"Xiayanqing",
    "wof:placetype":"locality"
},
  "geometry": {"coordinates":[99.06950000000001,25.1194],"type":"Point"}
}