{
  "type": "Feature",
  "properties": {
    "gn:admin1_code":"29",
    "gn:asciiname":"Tso-fa",
    "gn:country_code":"CN",
    "gn:dem":935,
    "gn:feature_class":"P",
    "gn:feature_code":"PPL",
    "gn:name":"Tso-fa",
    "gn:population":0,
    "gn:timezone":"Asia/Shanghai",
    "iso:country":"CN",
    "wof:name":"Tso-fa",
    "wof:placetype":"locality"
},
  "geometry": {"coordinates":[103.96639,22.74194],"type":"Point"}
}