{
  "type": "Feature",
  "properties": {
    "gn:admin1_code":"4.0",
    "gn:asciiname":"Miaopu",
    "gn:country_code":"CN",
    "gn:dem":6,
    "gn:feature_class":"P",
    "gn:feature_code":"PPLF",
    "gn:name":"Miaopu",
    "gn:population":0,
    "gn:timezone":"Asia/Shanghai",
    "iso:country":"CN",
    "name:zho_x_preferred":[
        "Miaopu"
    ],
    "name:zho_x_variant":[
        "\u82d7\u5703"
    ],
    "wof:name":"Miaopu",
    "wof:placetype":"locality"
},
  "geometry": {"coordinates":[121.28027,31.95566],"type":"Point"}
}