{
  "type": "Feature",
  "properties": {
    "gn:admin1_code":"26",
    "gn:asciiname":"Wenjiawan",
    "gn:country_code":"CN",
    "gn:dem":504,
    "gn:feature_class":"P",
    "gn:feature_code":"PPL",
    "gn:name":"Wenjiawan",
    "gn:population":0,
    "gn:timezone":"Asia/Shanghai",
    "iso:country":"CN",
    "name:zho_x_preferred":[
        "\u6587\u5bb6\u6e7e"
    ],
    "wof:name":"Wenjiawan",
    "wof:placetype":"locality"
},
  "geometry": {"coordinates":[108.14333999999999,34.29626],"type":"Point"}
}