{
  "type": "Feature",
  "properties": {
    "gn:admin1_code":"32.0",
    "gn:asciiname":"Jinshui",
    "gn:country_code":"CN",
    "gn:dem":432,
    "gn:feature_class":"P",
    "gn:feature_code":"PPL",
    "gn:name":"Jinshui",
    "gn:population":0,
    "gn:timezone":"Asia/Shanghai",
    "iso:country":"CN",
    "name:zho_x_preferred":[
        "\u6d78\u6c34"
    ],
    "wof:name":"Jinshui",
    "wof:placetype":"locality"
},
  "geometry": {"coordinates":[104.523,30.0768],"type":"Point"}
}