{
  "type": "Feature",
  "properties": {
    "gn:admin1_code":"32.0",
    "gn:asciiname":"Mengziganya",
    "gn:country_code":"CN",
    "gn:dem":406,
    "gn:feature_class":"P",
    "gn:feature_code":"PPL",
    "gn:name":"Mengziganya",
    "gn:population":0,
    "gn:timezone":"Asia/Shanghai",
    "iso:country":"CN",
    "name:zho_x_preferred":[
        "\u8499\u5b50\u6746\u57ad"
    ],
    "wof:name":"Mengziganya",
    "wof:placetype":"locality"
},
  "geometry": {"coordinates":[105.25376,31.25618],"type":"Point"}
}