{
  "type": "Feature",
  "properties": {
    "gn:admin1_code":"29.0",
    "gn:asciiname":"Jiuhejie",
    "gn:country_code":"CN",
    "gn:dem":2295,
    "gn:feature_class":"P",
    "gn:feature_code":"PPL",
    "gn:name":"Jiuhejie",
    "gn:population":0,
    "gn:timezone":"Asia/Shanghai",
    "iso:country":"CN",
    "name:zho_x_preferred":[
        "\u4e5d\u6cb3\u8857"
    ],
    "wof:name":"Jiuhejie",
    "wof:placetype":"locality"
},
  "geometry": {"coordinates":[99.9569,26.6545],"type":"Point"}
}