{
  "type": "Feature",
  "properties": {
    "gn:admin1_code":"18",
    "gn:asciiname":"Xiapingtian",
    "gn:country_code":"CN",
    "gn:dem":1633,
    "gn:feature_class":"P",
    "gn:feature_code":"PPL",
    "gn:name":"Xiapingtian",
    "gn:population":0,
    "gn:timezone":"Asia/Shanghai",
    "iso:country":"CN",
    "name:zho_x_preferred":[
        "\u4e0b\u5e73\u7530"
    ],
    "wof:name":"Xiapingtian",
    "wof:placetype":"locality"
},
  "geometry": {"coordinates":[104.73699999999999,25.837],"type":"Point"}
}