{
  "type": "Feature",
  "properties": {
    "gn:admin1_code":"03",
    "gn:asciiname":"Qiaodong",
    "gn:country_code":"CN",
    "gn:dem":25,
    "gn:feature_class":"P",
    "gn:feature_code":"PPLA4",
    "gn:name":"Qiaodong",
    "gn:population":0,
    "gn:timezone":"Asia/Shanghai",
    "iso:country":"CN",
    "name:und_x_variant":[
        "Ch\u2019iao-tung",
        "Qiaodong",
        "\u6865\u4e1c",
        "Qiaodong Zhen",
        "\u6865\u4e1c\u9547"
    ],
    "wof:name":"Qiaodong",
    "wof:placetype":"locality"
},
  "geometry": {"coordinates":[115.81957,28.05839000000001],"type":"Point"}
}