{
  "type": "Feature",
  "properties": {
    "gn:admin1_code":"18.0",
    "gn:asciiname":"Yashantang",
    "gn:country_code":"CN",
    "gn:dem":660,
    "gn:feature_class":"P",
    "gn:feature_code":"PPL",
    "gn:name":"Yashantang",
    "gn:population":0,
    "gn:timezone":"Asia/Shanghai",
    "iso:country":"CN",
    "name:zho_x_preferred":[
        "\u9e26\u5c71\u5858"
    ],
    "wof:name":"Yashantang",
    "wof:placetype":"locality"
},
  "geometry": {"coordinates":[109.304,27.9222],"type":"Point"}
}