{
  "type": "Feature",
  "properties": {
    "gn:admin1_code":"1.0",
    "gn:asciiname":"Caoshancun",
    "gn:country_code":"CN",
    "gn:dem":26,
    "gn:feature_class":"P",
    "gn:feature_code":"PPL",
    "gn:name":"Caoshancun",
    "gn:population":0,
    "gn:timezone":"Asia/Shanghai",
    "iso:country":"CN",
    "name:zho_x_preferred":[
        "\u66f9\u5c71\u6751"
    ],
    "wof:name":"Caoshancun",
    "wof:placetype":"locality"
},
  "geometry": {"coordinates":[117.40984,33.52216],"type":"Point"}
}