{
  "type": "Feature",
  "properties": {
    "gn:admin1_code":"5.0",
    "gn:asciiname":"Lingzicun",
    "gn:country_code":"CN",
    "gn:dem":147,
    "gn:feature_class":"P",
    "gn:feature_code":"PPL",
    "gn:name":"Lingzicun",
    "gn:population":0,
    "gn:timezone":"Asia/Shanghai",
    "iso:country":"CN",
    "name:zho_x_preferred":[
        "\u4ee4\u5b57\u6751"
    ],
    "wof:name":"Lingzicun",
    "wof:placetype":"locality"
},
  "geometry": {"coordinates":[123.81364000000001,44.81851],"type":"Point"}
}