{
  "type": "Feature",
  "properties": {
    "gn:admin1_code":"33.0",
    "gn:asciiname":"Shuinian",
    "gn:country_code":"CN",
    "gn:dem":292,
    "gn:feature_class":"P",
    "gn:feature_code":"PPL",
    "gn:name":"Shuinian",
    "gn:population":0,
    "gn:timezone":"Asia/Shanghai",
    "iso:country":"CN",
    "name:zho_x_preferred":[
        "\u6c34\u78be"
    ],
    "wof:name":"Shuinian",
    "wof:placetype":"locality"
},
  "geometry": {"coordinates":[106.07926999999999,29.94185],"type":"Point"}
}