{
  "type": "Feature",
  "properties": {
    "gn:admin1_code":"6.0",
    "gn:asciiname":"Heitan",
    "gn:country_code":"CN",
    "gn:dem":1915,
    "gn:feature_class":"P",
    "gn:feature_code":"PPL",
    "gn:name":"Heitan",
    "gn:population":0,
    "gn:timezone":"Asia/Shanghai",
    "iso:country":"CN",
    "name:und_x_variant":[
        "\u9ed1\u6ee9"
    ],
    "wof:name":"Heitan",
    "wof:placetype":"locality"
},
  "geometry": {"coordinates":[102.5521,35.82497],"type":"Point"}
}