{
  "type": "Feature",
  "properties": {
    "gn:admin1_code":"30.0",
    "gn:asciiname":"Guzhoucun",
    "gn:country_code":"CN",
    "gn:dem":102,
    "gn:feature_class":"P",
    "gn:feature_code":"PPL",
    "gn:name":"Guzhoucun",
    "gn:population":0,
    "gn:timezone":"Asia/Shanghai",
    "iso:country":"CN",
    "name:zho_x_preferred":[
        "\u53e4\u5dde\u6751"
    ],
    "wof:name":"Guzhoucun",
    "wof:placetype":"locality"
},
  "geometry": {"coordinates":[112.16461,22.97839],"type":"Point"}
}