{
  "type": "Feature",
  "properties": {
    "gn:admin1_code":"9",
    "gn:asciiname":"Xidoudi",
    "gn:country_code":"CN",
    "gn:dem":56,
    "gn:feature_class":"P",
    "gn:feature_code":"PPL",
    "gn:name":"Xidoudi",
    "gn:population":0,
    "gn:timezone":"Asia/Shanghai",
    "iso:country":"CN",
    "name:zho_x_preferred":[
        "\u897f\u8c46\u5824"
    ],
    "wof:name":"Xidoudi",
    "wof:placetype":"locality"
},
  "geometry": {"coordinates":[115.05200000000001,35.7022],"type":"Point"}
}