{
  "type": "Feature",
  "properties": {
    "gn:admin1_code":"18",
    "gn:asciiname":"Matiping",
    "gn:country_code":"CN",
    "gn:dem":942,
    "gn:feature_class":"P",
    "gn:feature_code":"PPL",
    "gn:name":"Matiping",
    "gn:population":0,
    "gn:timezone":"Asia/Shanghai",
    "iso:country":"CN",
    "name:zho_x_preferred":[
        "\u9a6c\u8e44\u576a"
    ],
    "wof:name":"Matiping",
    "wof:placetype":"locality"
},
  "geometry": {"coordinates":[107.47499999999999,28.1366],"type":"Point"}
}