{
  "type": "Feature",
  "properties": {
    "gn:admin1_code":"3",
    "gn:asciiname":"Luobutian",
    "gn:country_code":"CN",
    "gn:dem":131,
    "gn:feature_class":"P",
    "gn:feature_code":"PPL",
    "gn:name":"Luobutian",
    "gn:population":0,
    "gn:timezone":"Asia/Shanghai",
    "iso:country":"CN",
    "name:zho_x_preferred":[
        "\u841d\u535c\u7530"
    ],
    "wof:name":"Luobutian",
    "wof:placetype":"locality"
},
  "geometry": {"coordinates":[114.72799999999999,25.5792],"type":"Point"}
}