{
  "type": "Feature",
  "properties": {
    "gn:admin1_code":"13.0",
    "gn:asciiname":"Chaiwopu",
    "gn:country_code":"CN",
    "gn:dem":1116,
    "gn:feature_class":"P",
    "gn:feature_code":"PPL",
    "gn:name":"Chaiwopu",
    "gn:population":0,
    "gn:timezone":"Asia/Urumqi",
    "iso:country":"CN",
    "name:und_x_variant":[
        "Ts\u2019ai-ho-p\u2019u",
        "Ch\u2019ai-o-i",
        "Ts\u2019ai-o-pao",
        "Ch\u2019ai-o-pao",
        "Tsaiopu",
        "Tsayvopu",
        "Ch\u2019ai-o-p\u2019u",
        "Tsayvotu",
        "T\u2019saiwop\u2019u",
        "Chaiwopu"
    ],
    "name:zho_x_preferred":[
        "\u67f4\u7a9d\u5821"
    ],
    "wof:name":"Chaiwopu",
    "wof:placetype":"locality"
},
  "geometry": {"coordinates":[87.94110999999999,43.53871],"type":"Point"}
}