{
  "type": "Feature",
  "properties": {
    "gn:admin1_code":"3",
    "gn:asciiname":"Shiling Hejia",
    "gn:country_code":"CN",
    "gn:dem":141,
    "gn:feature_class":"P",
    "gn:feature_code":"PPL",
    "gn:name":"Shiling Hejia",
    "gn:population":0,
    "gn:timezone":"Asia/Shanghai",
    "iso:country":"CN",
    "name:und_x_variant":[
        "\u77f3\u5cad\u4f55\u5bb6"
    ],
    "wof:name":"Shiling Hejia",
    "wof:placetype":"locality"
},
  "geometry": {"coordinates":[117.31251,28.14341],"type":"Point"}
}