{
  "type": "Feature",
  "properties": {
    "gn:admin1_code":"24",
    "gn:asciiname":"Houyancun",
    "gn:country_code":"CN",
    "gn:dem":1206,
    "gn:feature_class":"P",
    "gn:feature_code":"PPL",
    "gn:name":"Houyancun",
    "gn:population":0,
    "gn:timezone":"Asia/Shanghai",
    "iso:country":"CN",
    "name:und_x_variant":[
        "Hou-yen",
        "Hou-yen-ti",
        "Houyan",
        "Houyancun"
    ],
    "name:zho_x_preferred":[
        "\u540e\u5895\u6751"
    ],
    "wof:name":"Houyancun",
    "wof:placetype":"locality"
},
  "geometry": {"coordinates":[110.85478000000001,36.7177],"type":"Point"}
}