{
  "type": "Feature",
  "properties": {
    "gn:admin1_code":"25",
    "gn:asciiname":"Zhuwang",
    "gn:country_code":"CN",
    "gn:dem":9,
    "gn:feature_class":"P",
    "gn:feature_code":"PPL",
    "gn:name":"Zhuwang",
    "gn:population":0,
    "gn:timezone":"Asia/Shanghai",
    "iso:country":"CN",
    "name:ceb_x_preferred":[
        "Zhuwang"
    ],
    "name:fas_x_preferred":[
        "\u0698\u0648\u0627\u0646\u06af"
    ],
    "name:swe_x_preferred":[
        "Zhuwang"
    ],
    "name:zho_x_preferred":[
        "\u6731\u65fa"
    ],
    "name:zho_x_variant":[
        "\u8bf8\u5f80\u9547"
    ],
    "wof:name":"Zhuwang",
    "wof:placetype":"locality"
},
  "geometry": {"coordinates":[119.914,37.2569],"type":"Point"}
}