{
  "type": "Feature",
  "properties": {
    "gn:admin1_code":"18.0",
    "gn:asciiname":"Qiuxi",
    "gn:country_code":"CN",
    "gn:dem":392,
    "gn:feature_class":"P",
    "gn:feature_code":"PPL",
    "gn:name":"Qiuxi",
    "gn:population":0,
    "gn:timezone":"Asia/Shanghai",
    "iso:country":"CN",
    "name:zho_x_preferred":[
        "\u79cb\u6eaa"
    ],
    "wof:name":"Qiuxi",
    "wof:placetype":"locality"
},
  "geometry": {"coordinates":[108.83799999999999,27.1988],"type":"Point"}
}