{
  "type": "Feature",
  "properties": {
    "gn:admin1_code":"16.0",
    "gn:asciiname":"Yanchang",
    "gn:country_code":"CN",
    "gn:dem":918,
    "gn:feature_class":"P",
    "gn:feature_code":"PPL",
    "gn:name":"Yanchang",
    "gn:population":0,
    "gn:timezone":"Asia/Shanghai",
    "iso:country":"CN",
    "wof:name":"Yanchang",
    "wof:placetype":"locality"
},
  "geometry": {"coordinates":[105.13333,24.86667000000001],"type":"Point"}
}