{
  "type": "Feature",
  "properties": {
    "gn:admin1_code":"16.0",
    "gn:asciiname":"Kulu",
    "gn:country_code":"CN",
    "gn:dem":243,
    "gn:feature_class":"P",
    "gn:feature_code":"PPL",
    "gn:name":"Kul\u00fc",
    "gn:population":0,
    "gn:timezone":"Asia/Shanghai",
    "iso:country":"CN",
    "name:und_x_variant":[
        "Kul\u00fc"
    ],
    "name:zho_x_preferred":[
        "\u67af\u5f8b"
    ],
    "wof:name":"Kulu",
    "wof:placetype":"locality"
},
  "geometry": {"coordinates":[108.15300000000001,22.0734],"type":"Point"}
}