{
  "type": "Feature",
  "properties": {
    "gn:admin1_code":"19.0",
    "gn:asciiname":"Yaniujie",
    "gn:country_code":"CN",
    "gn:dem":15,
    "gn:feature_class":"P",
    "gn:feature_code":"PPL",
    "gn:name":"Yaniujie",
    "gn:population":0,
    "gn:timezone":"Asia/Shanghai",
    "iso:country":"CN",
    "name:zho_x_preferred":[
        "\u62bc\u725b\u8857"
    ],
    "wof:name":"Yaniujie",
    "wof:placetype":"locality"
},
  "geometry": {"coordinates":[122.62858,41.56694],"type":"Point"}
}