{
  "type": "Feature",
  "properties": {
    "gn:admin1_code":"4.0",
    "gn:asciiname":"Huanggang",
    "gn:country_code":"CN",
    "gn:dem":3,
    "gn:feature_class":"P",
    "gn:feature_code":"PPL",
    "gn:name":"Huanggang",
    "gn:population":0,
    "gn:timezone":"Asia/Shanghai",
    "iso:country":"CN",
    "name:zho_x_preferred":[
        "Huanggang"
    ],
    "name:zho_x_variant":[
        "\u9ec4\u5c97"
    ],
    "wof:name":"Huanggang",
    "wof:placetype":"locality"
},
  "geometry": {"coordinates":[119.48694999999999,33.59877],"type":"Point"}
}