{
  "type": "Feature",
  "properties": {
    "gn:admin1_code":"30.0",
    "gn:asciiname":"Nanmukeng",
    "gn:country_code":"CN",
    "gn:dem":104,
    "gn:feature_class":"P",
    "gn:feature_code":"PPL",
    "gn:name":"Nanmukeng",
    "gn:population":0,
    "gn:timezone":"Asia/Shanghai",
    "iso:country":"CN",
    "name:zho_x_preferred":[
        "\u5357\u6728\u5751"
    ],
    "wof:name":"Nanmukeng",
    "wof:placetype":"locality"
},
  "geometry": {"coordinates":[112.17794000000001,23.12522],"type":"Point"}
}