{
  "type": "Feature",
  "properties": {
    "gn:admin1_code":"16.0",
    "gn:asciiname":"Lalonglang",
    "gn:country_code":"CN",
    "gn:dem":256,
    "gn:feature_class":"P",
    "gn:feature_code":"PPL",
    "gn:name":"Lalonglang",
    "gn:population":0,
    "gn:timezone":"Asia/Shanghai",
    "iso:country":"CN",
    "name:zho_x_preferred":[
        "\u62c9\u9f99\u6d6a"
    ],
    "wof:name":"Lalonglang",
    "wof:placetype":"locality"
},
  "geometry": {"coordinates":[108.158,24.7403],"type":"Point"}
}