{
  "type": "Feature",
  "properties": {
    "gn:admin1_code":"30.0",
    "gn:asciiname":"Yingxia",
    "gn:country_code":"CN",
    "gn:dem":87,
    "gn:feature_class":"P",
    "gn:feature_code":"PPL",
    "gn:name":"Yingxia",
    "gn:population":0,
    "gn:timezone":"Asia/Shanghai",
    "iso:country":"CN",
    "name:zho_x_preferred":[
        "\u8425\u4e0b"
    ],
    "wof:name":"Yingxia",
    "wof:placetype":"locality"
},
  "geometry": {"coordinates":[115.00212000000001,23.21078],"type":"Point"}
}