{
  "type": "Feature",
  "properties": {
    "gn:admin1_code":"13",
    "gn:asciiname":"Baiyanggou Ercun",
    "gn:country_code":"CN",
    "gn:dem":1480,
    "gn:feature_class":"P",
    "gn:feature_code":"PPL",
    "gn:name":"Baiyanggou Ercun",
    "gn:population":0,
    "gn:timezone":"Asia/Urumqi",
    "iso:country":"CN",
    "name:zho_x_preferred":[
        "\u767d\u6768\u6c9f\u4e8c\u6751"
    ],
    "wof:name":"Baiyanggou Ercun",
    "wof:placetype":"locality"
},
  "geometry": {"coordinates":[87.44072,43.54807],"type":"Point"}
}