{
  "type": "Feature",
  "properties": {
    "gn:admin1_code":"25.0",
    "gn:asciiname":"Ningyang",
    "gn:country_code":"CN",
    "gn:dem":62,
    "gn:feature_class":"P",
    "gn:feature_code":"PPL",
    "gn:name":"Ningyang",
    "gn:population":0,
    "gn:timezone":"Asia/Shanghai",
    "iso:country":"CN",
    "name:zho_x_preferred":[
        "\u5b81\u9633"
    ],
    "wof:name":"Ningyang",
    "wof:placetype":"locality"
},
  "geometry": {"coordinates":[121.98873,37.19545],"type":"Point"}
}