{
  "type": "Feature",
  "properties": {
    "gn:admin1_code":"02",
    "gn:asciiname":"Feishicun",
    "gn:country_code":"CN",
    "gn:dem":13,
    "gn:feature_class":"P",
    "gn:feature_code":"PPL",
    "gn:name":"Feishicun",
    "gn:population":0,
    "gn:timezone":"Asia/Shanghai",
    "iso:country":"CN",
    "name:und_x_variant":[
        "Fei-shih-chen",
        "Feishi",
        "\u8d39\u5e02",
        "Feishicun"
    ],
    "name:zho_x_preferred":[
        "\u8d39\u5e02"
    ],
    "name:zho_x_variant":[
        "\u8d39\u5e02\u6751"
    ],
    "wof:name":"Feishicun",
    "wof:placetype":"locality"
},
  "geometry": {"coordinates":[121.53167999999999,29.96448],"type":"Point"}
}