{
  "type": "Feature",
  "properties": {
    "gn:admin1_code":"10",
    "gn:asciiname":"Hougaozhuang",
    "gn:country_code":"CN",
    "gn:dem":31,
    "gn:feature_class":"P",
    "gn:feature_code":"PPL",
    "gn:name":"Hougaozhuang",
    "gn:population":0,
    "gn:timezone":"Asia/Shanghai",
    "iso:country":"CN",
    "name:zho_x_preferred":[
        "\u540e\u9ad8\u5e84"
    ],
    "wof:name":"Hougaozhuang",
    "wof:placetype":"locality"
},
  "geometry": {"coordinates":[115.65300000000001,37.239],"type":"Point"}
}