{
  "type": "Feature",
  "properties": {
    "gn:admin1_code":"26.0",
    "gn:asciiname":"Zhuocun",
    "gn:country_code":"CN",
    "gn:dem":404,
    "gn:feature_class":"P",
    "gn:feature_code":"PPL",
    "gn:name":"Zhuocun",
    "gn:population":0,
    "gn:timezone":"Asia/Shanghai",
    "iso:country":"CN",
    "name:zho_x_preferred":[
        "\u5353\u6751"
    ],
    "wof:name":"Zhuocun",
    "wof:placetype":"locality"
},
  "geometry": {"coordinates":[108.65729,34.18081],"type":"Point"}
}