{
  "type": "Feature",
  "properties": {
    "gn:admin1_code":"13.0",
    "gn:asciiname":"Kongmusilake",
    "gn:country_code":"CN",
    "gn:dem":2290,
    "gn:feature_class":"P",
    "gn:feature_code":"PPL",
    "gn:name":"Kongmusilake",
    "gn:population":0,
    "gn:timezone":"Asia/Shanghai",
    "iso:country":"CN",
    "name:zho_x_preferred":[
        "\u7a7a\u6728\u65af\u62c9\u514b"
    ],
    "wof:name":"Kongmusilake",
    "wof:placetype":"locality"
},
  "geometry": {"coordinates":[82.24979999999999,36.60785],"type":"Point"}
}