{
  "type": "Feature",
  "properties": {
    "gn:admin1_code":"19.0",
    "gn:asciiname":"Xiaoniuquanzi",
    "gn:country_code":"CN",
    "gn:dem":1,
    "gn:feature_class":"P",
    "gn:feature_code":"PPL",
    "gn:name":"Xiaoniuquanzi",
    "gn:population":0,
    "gn:timezone":"Asia/Shanghai",
    "iso:country":"CN",
    "name:und_x_variant":[
        "\u5c0f\u725b\u5708\u5b50"
    ],
    "wof:name":"Xiaoniuquanzi",
    "wof:placetype":"locality"
},
  "geometry": {"coordinates":[122.19313,40.77031],"type":"Point"}
}