{
  "type": "Feature",
  "properties": {
    "gn:admin1_code":"8.0",
    "gn:asciiname":"Tongjia Weizi",
    "gn:country_code":"CN",
    "gn:dem":164,
    "gn:feature_class":"P",
    "gn:feature_code":"PPL",
    "gn:name":"Tongjia Weizi",
    "gn:population":0,
    "gn:timezone":"Asia/Shanghai",
    "iso:country":"CN",
    "name:zho_x_preferred":[
        "\u4f5f\u5bb6\u56f4\u5b50"
    ],
    "wof:name":"Tongjia Weizi",
    "wof:placetype":"locality"
},
  "geometry": {"coordinates":[124.77307999999999,47.6743],"type":"Point"}
}