{
  "type": "Feature",
  "properties": {
    "gn:admin1_code":"8.0",
    "gn:asciiname":"Limupu",
    "gn:country_code":"CN",
    "gn:dem":145,
    "gn:feature_class":"P",
    "gn:feature_code":"PPL",
    "gn:name":"Limupu",
    "gn:population":0,
    "gn:timezone":"Asia/Shanghai",
    "iso:country":"CN",
    "name:zho_x_preferred":[
        "\u674e\u6728\u94fa"
    ],
    "wof:name":"Limupu",
    "wof:placetype":"locality"
},
  "geometry": {"coordinates":[128.64328,45.62822],"type":"Point"}
}