{
  "type": "Feature",
  "properties": {
    "gn:admin1_code":"15.0",
    "gn:asciiname":"Sifanghe",
    "gn:country_code":"CN",
    "gn:dem":1142,
    "gn:feature_class":"P",
    "gn:feature_code":"PPL",
    "gn:name":"Sifanghe",
    "gn:population":0,
    "gn:timezone":"Asia/Shanghai",
    "iso:country":"CN",
    "name:und_x_variant":[
        "\u56db\u623f\u6cb3"
    ],
    "wof:name":"Sifanghe",
    "wof:placetype":"locality"
},
  "geometry": {"coordinates":[105.73779999999999,33.4135],"type":"Point"}
}