{
  "type": "Feature",
  "properties": {
    "gn:admin1_code":"3.0",
    "gn:asciiname":"Jiangnanxiang",
    "gn:country_code":"CN",
    "gn:dem":85,
    "gn:feature_class":"P",
    "gn:feature_code":"PPL",
    "gn:name":"Jiangnanxiang",
    "gn:population":0,
    "gn:timezone":"Asia/Shanghai",
    "iso:country":"CN",
    "name:und_x_variant":[
        "\u6c5f\u5357\u4e61"
    ],
    "wof:name":"Jiangnanxiang",
    "wof:placetype":"locality"
},
  "geometry": {"coordinates":[114.61651000000001,27.38315],"type":"Point"}
}