{
  "type": "Feature",
  "properties": {
    "gn:admin1_code":"18",
    "gn:asciiname":"Lijia Wanzi",
    "gn:country_code":"CN",
    "gn:dem":1276,
    "gn:feature_class":"P",
    "gn:feature_code":"PPL",
    "gn:name":"Lijia Wanzi",
    "gn:population":0,
    "gn:timezone":"Asia/Shanghai",
    "iso:country":"CN",
    "name:zho_x_preferred":[
        "\u674e\u5bb6\u6e7e\u5b50"
    ],
    "wof:name":"Lijia Wanzi",
    "wof:placetype":"locality"
},
  "geometry": {"coordinates":[105.56999999999999,25.6137],"type":"Point"}
}