{
  "type": "Feature",
  "properties": {
    "gn:admin1_code":"1.0",
    "gn:asciiname":"Shixiaozhuangcun",
    "gn:country_code":"CN",
    "gn:dem":33,
    "gn:feature_class":"P",
    "gn:feature_code":"PPL",
    "gn:name":"Shixiaozhuangcun",
    "gn:population":0,
    "gn:timezone":"Asia/Shanghai",
    "iso:country":"CN",
    "name:zho_x_preferred":[
        "\u77f3\u5c0f\u5e84\u6751"
    ],
    "wof:name":"Shixiaozhuangcun",
    "wof:placetype":"locality"
},
  "geometry": {"coordinates":[115.71747999999999,33.07828],"type":"Point"}
}