{
  "type": "Feature",
  "properties": {
    "gn:admin1_code":"30.0",
    "gn:asciiname":"Xinliangting",
    "gn:country_code":"CN",
    "gn:dem":271,
    "gn:feature_class":"P",
    "gn:feature_code":"PPL",
    "gn:name":"Xinliangting",
    "gn:population":0,
    "gn:timezone":"Asia/Shanghai",
    "iso:country":"CN",
    "name:zho_x_preferred":[
        "\u65b0\u51c9\u4ead"
    ],
    "wof:name":"Xinliangting",
    "wof:placetype":"locality"
},
  "geometry": {"coordinates":[113.83203,24.93533],"type":"Point"}
}