{
  "type": "Feature",
  "properties": {
    "gn:admin1_code":"25.0",
    "gn:asciiname":"Hejiazhuang",
    "gn:country_code":"CN",
    "gn:dem":122,
    "gn:feature_class":"P",
    "gn:feature_code":"PPL",
    "gn:name":"Hejiazhuang",
    "gn:population":0,
    "gn:timezone":"Asia/Shanghai",
    "iso:country":"CN",
    "name:zho_x_preferred":[
        "\u79be\u5bb6\u5e84"
    ],
    "wof:name":"Hejiazhuang",
    "wof:placetype":"locality"
},
  "geometry": {"coordinates":[120.89351000000001,37.17832],"type":"Point"}
}