{
  "type": "Feature",
  "properties": {
    "gn:admin1_code":"3.0",
    "gn:asciiname":"Xiaduan",
    "gn:country_code":"CN",
    "gn:dem":415,
    "gn:feature_class":"P",
    "gn:feature_code":"PPL",
    "gn:name":"Xiaduan",
    "gn:population":0,
    "gn:timezone":"Asia/Shanghai",
    "iso:country":"CN",
    "name:und_x_variant":[
        "\u4e0b\u5845"
    ],
    "wof:name":"Xiaduan",
    "wof:placetype":"locality"
},
  "geometry": {"coordinates":[114.04971999999999,27.93305],"type":"Point"}
}