{
  "type": "Feature",
  "properties": {
    "gn:admin1_code":"2.0",
    "gn:asciiname":"Mazhichuan",
    "gn:country_code":"CN",
    "gn:dem":53,
    "gn:feature_class":"P",
    "gn:feature_code":"PPL",
    "gn:name":"Mazhichuan",
    "gn:population":0,
    "gn:timezone":"Asia/Shanghai",
    "iso:country":"CN",
    "name:zho_x_preferred":[
        "\u9ebb\u829d\u5ddd"
    ],
    "wof:name":"Mazhichuan",
    "wof:placetype":"locality"
},
  "geometry": {"coordinates":[120.45142,28.0375],"type":"Point"}
}