{
  "type": "Feature",
  "properties": {
    "gn:admin1_code":"29.0",
    "gn:asciiname":"Fengchuishan",
    "gn:country_code":"CN",
    "gn:dem":1809,
    "gn:feature_class":"P",
    "gn:feature_code":"PPL",
    "gn:name":"Fengchuishan",
    "gn:population":0,
    "gn:timezone":"Asia/Shanghai",
    "iso:country":"CN",
    "name:zho_x_preferred":[
        "\u98ce\u5439\u5c71"
    ],
    "wof:name":"Fengchuishan",
    "wof:placetype":"locality"
},
  "geometry": {"coordinates":[99.2765,24.1132],"type":"Point"}
}