{
  "type": "Feature",
  "properties": {
    "gn:admin1_code":"16",
    "gn:asciiname":"Huwei",
    "gn:country_code":"CN",
    "gn:dem":164,
    "gn:feature_class":"P",
    "gn:feature_code":"PPL",
    "gn:name":"Huwei",
    "gn:population":0,
    "gn:timezone":"Asia/Shanghai",
    "iso:country":"CN",
    "name:zho_x_preferred":[
        "\u864e\u5c3e"
    ],
    "wof:name":"Huwei",
    "wof:placetype":"locality"
},
  "geometry": {"coordinates":[110.819,24.91800000000001],"type":"Point"}
}