{
  "type": "Feature",
  "properties": {
    "gn:admin1_code":"19.0",
    "gn:asciiname":"Gaojiabu",
    "gn:country_code":"CN",
    "gn:dem":89,
    "gn:feature_class":"P",
    "gn:feature_code":"PPL",
    "gn:name":"Gaojiabu",
    "gn:population":0,
    "gn:timezone":"Asia/Shanghai",
    "iso:country":"CN",
    "name:und_x_variant":[
        "Gaojiabao",
        "Gaojiabu"
    ],
    "name:zho_x_preferred":[
        "\u9ad8\u5bb6\u5821"
    ],
    "wof:name":"Gaojiabu",
    "wof:placetype":"locality"
},
  "geometry": {"coordinates":[124.17657,40.14291],"type":"Point"}
}