{
  "type": "Feature",
  "properties": {
    "gn:admin1_code":"26.0",
    "gn:asciiname":"Songjia Yuanzi",
    "gn:country_code":"CN",
    "gn:dem":775,
    "gn:feature_class":"P",
    "gn:feature_code":"PPL",
    "gn:name":"Songjia Yuanzi",
    "gn:population":0,
    "gn:timezone":"Asia/Shanghai",
    "iso:country":"CN",
    "name:zho_x_preferred":[
        "\u5b8b\u5bb6\u9662\u5b50"
    ],
    "wof:name":"Songjia Yuanzi",
    "wof:placetype":"locality"
},
  "geometry": {"coordinates":[109.20232,32.3249],"type":"Point"}
}