{
  "type": "Feature",
  "properties": {
    "gn:admin1_code":"31",
    "gn:asciiname":"Xinying Liudui",
    "gn:country_code":"CN",
    "gn:dem":47,
    "gn:feature_class":"P",
    "gn:feature_code":"PPLF",
    "gn:name":"Xinying Liudui",
    "gn:population":0,
    "gn:timezone":"Asia/Shanghai",
    "iso:country":"CN",
    "name:und_x_variant":[
        "\u65b0\u76c8\u516d\u961f",
        "Xinyingsidui"
    ],
    "wof:name":"Xinying Liudui",
    "wof:placetype":"locality"
},
  "geometry": {"coordinates":[109.55598000000001,19.82997],"type":"Point"}
}