{
  "type": "Feature",
  "properties": {
    "gn:admin1_code":"11.0",
    "gn:asciiname":"Shaojiwan",
    "gn:country_code":"CN",
    "gn:dem":886,
    "gn:feature_class":"P",
    "gn:feature_code":"PPL",
    "gn:name":"Shaojiwan",
    "gn:population":0,
    "gn:timezone":"Asia/Shanghai",
    "iso:country":"CN",
    "name:zho_x_preferred":[
        "\u70e7\u9e21\u6e7e"
    ],
    "wof:name":"Shaojiwan",
    "wof:placetype":"locality"
},
  "geometry": {"coordinates":[110.12748000000001,29.74204000000001],"type":"Point"}
}