{
  "type": "Feature",
  "properties": {
    "gn:admin1_code":"29.0",
    "gn:asciiname":"Yongsang",
    "gn:country_code":"CN",
    "gn:dem":822,
    "gn:feature_class":"P",
    "gn:feature_code":"PPL",
    "gn:name":"Yongsang",
    "gn:population":0,
    "gn:timezone":"Asia/Shanghai",
    "iso:country":"CN",
    "name:zho_x_preferred":[
        "\u6c38\u6851"
    ],
    "wof:name":"Yongsang",
    "wof:placetype":"locality"
},
  "geometry": {"coordinates":[98.8989,23.2123],"type":"Point"}
}