{
  "type": "Feature",
  "properties": {
    "gn:admin1_code":"29.0",
    "gn:asciiname":"Lugeman",
    "gn:country_code":"CN",
    "gn:dem":2837,
    "gn:feature_class":"P",
    "gn:feature_code":"PPL",
    "gn:name":"Lugeman",
    "gn:population":0,
    "gn:timezone":"Asia/Shanghai",
    "iso:country":"CN",
    "name:zho_x_preferred":[
        "\u9c81\u9601\u6ee1"
    ],
    "wof:name":"Lugeman",
    "wof:placetype":"locality"
},
  "geometry": {"coordinates":[100.381,27.2522],"type":"Point"}
}