{
  "type": "Feature",
  "properties": {
    "gn:admin1_code":"07",
    "gn:asciiname":"Nankou",
    "gn:country_code":"CN",
    "gn:dem":173,
    "gn:feature_class":"P",
    "gn:feature_code":"PPLA4",
    "gn:name":"Nankou",
    "gn:population":0,
    "gn:timezone":"Asia/Shanghai",
    "iso:country":"CN",
    "name:und_x_variant":[
        "\u5357\u53e3"
    ],
    "name:zho_x_preferred":[
        "\u5357\u53e3"
    ],
    "wof:name":"Nankou",
    "wof:placetype":"locality"
},
  "geometry": {"coordinates":[117.41843,26.62616],"type":"Point"}
}