{
  "type": "Feature",
  "properties": {
    "gn:admin1_code":"20.0",
    "gn:asciiname":"Dahewan",
    "gn:country_code":"CN",
    "gn:dem":258,
    "gn:feature_class":"P",
    "gn:feature_code":"PPLA4",
    "gn:name":"Dahewan",
    "gn:population":0,
    "gn:timezone":"Asia/Shanghai",
    "iso:country":"CN",
    "name:und_x_variant":[
        "Dahewan Zhen"
    ],
    "name:zho_x_preferred":[
        "\u5927\u6cb3\u6e7e"
    ],
    "name:zho_x_variant":[
        "\u5927\u6cb3\u6e7e\u9547"
    ],
    "wof:name":"Dahewan",
    "wof:placetype":"locality"
},
  "geometry": {"coordinates":[123.12774,47.84936],"type":"Point"}
}