{
  "type": "Feature",
  "properties": {
    "gn:admin1_code":"10",
    "gn:asciiname":"Sidungou",
    "gn:country_code":"CN",
    "gn:dem":1409,
    "gn:feature_class":"P",
    "gn:feature_code":"PPL",
    "gn:name":"Sidungou",
    "gn:population":0,
    "gn:timezone":"Asia/Shanghai",
    "iso:country":"CN",
    "name:zho_x_preferred":[
        "\u56db\u58a9\u6c9f"
    ],
    "wof:name":"Sidungou",
    "wof:placetype":"locality"
},
  "geometry": {"coordinates":[115.52296,41.05782],"type":"Point"}
}