{
  "type": "Feature",
  "properties": {
    "gn:admin1_code":"4.0",
    "gn:asciiname":"Zhangzhuang",
    "gn:country_code":"CN",
    "gn:dem":29,
    "gn:feature_class":"P",
    "gn:feature_code":"PPL",
    "gn:name":"Zhangzhuang",
    "gn:population":0,
    "gn:timezone":"Asia/Shanghai",
    "iso:country":"CN",
    "name:zho_x_preferred":[
        "\u5f20\u5e84"
    ],
    "wof:name":"Zhangzhuang",
    "wof:placetype":"locality"
},
  "geometry": {"coordinates":[117.20699999999999,34.1204],"type":"Point"}
}