{
  "type": "Feature",
  "properties": {
    "gn:admin1_code":"3.0",
    "gn:asciiname":"Chengjia",
    "gn:country_code":"CN",
    "gn:dem":33,
    "gn:feature_class":"P",
    "gn:feature_code":"PPL",
    "gn:name":"Chengjia",
    "gn:population":0,
    "gn:timezone":"Asia/Shanghai",
    "iso:country":"CN",
    "name:mar_x_preferred":[
        "\u091a\u0947\u0902\u0917\u094d\u091c\u093f\u092f\u093e"
    ],
    "name:tur_x_preferred":[
        "Chengjia"
    ],
    "name:und_x_variant":[
        "\u7a0b\u5bb6"
    ],
    "wof:name":"Chengjia",
    "wof:placetype":"locality"
},
  "geometry": {"coordinates":[115.44186999999999,27.92051],"type":"Point"}
}