{
  "type": "Feature",
  "properties": {
    "gn:admin1_code":"29.0",
    "gn:asciiname":"Luomaiba",
    "gn:country_code":"CN",
    "gn:dem":1224,
    "gn:feature_class":"P",
    "gn:feature_code":"PPL",
    "gn:name":"Luomaiba",
    "gn:population":0,
    "gn:timezone":"Asia/Shanghai",
    "iso:country":"CN",
    "name:zho_x_preferred":[
        "\u7f57\u5356\u5df4"
    ],
    "wof:name":"Luomaiba",
    "wof:placetype":"locality"
},
  "geometry": {"coordinates":[102.28100000000001,22.7456],"type":"Point"}
}