{
  "type": "Feature",
  "properties": {
    "gn:admin1_code":"26.0",
    "gn:asciiname":"Qinglongdian",
    "gn:country_code":"CN",
    "gn:dem":1361,
    "gn:feature_class":"P",
    "gn:feature_code":"PPL",
    "gn:name":"Qinglongdian",
    "gn:population":0,
    "gn:timezone":"Asia/Shanghai",
    "iso:country":"CN",
    "name:zho_x_preferred":[
        "\u9752\u9f99\u5e97"
    ],
    "wof:name":"Qinglongdian",
    "wof:placetype":"locality"
},
  "geometry": {"coordinates":[109.22714999999999,37.20028],"type":"Point"}
}