{
  "type": "Feature",
  "properties": {
    "gn:admin1_code":"4.0",
    "gn:asciiname":"Yun'ancun",
    "gn:country_code":"CN",
    "gn:dem":-2,
    "gn:feature_class":"P",
    "gn:feature_code":"PPL",
    "gn:name":"Yun\u2019ancun",
    "gn:population":0,
    "gn:timezone":"Asia/Shanghai",
    "iso:country":"CN",
    "name:und_x_variant":[
        "Yun\u2019ancun"
    ],
    "name:zho_x_preferred":[
        "\u4e91\u5b89\u6751"
    ],
    "wof:name":"Yun'ancun",
    "wof:placetype":"locality"
},
  "geometry": {"coordinates":[120.07232999999999,33.5401],"type":"Point"}
}