{
  "type": "Feature",
  "properties": {
    "gn:admin1_code":"2.0",
    "gn:asciiname":"Shiqiaotou",
    "gn:country_code":"CN",
    "gn:dem":77,
    "gn:feature_class":"P",
    "gn:feature_code":"PPL",
    "gn:name":"Shiqiaotou",
    "gn:population":0,
    "gn:timezone":"Asia/Shanghai",
    "iso:country":"CN",
    "name:zho_x_preferred":[
        "\u77f3\u6865\u5934"
    ],
    "wof:name":"Shiqiaotou",
    "wof:placetype":"locality"
},
  "geometry": {"coordinates":[119.85172,28.96459],"type":"Point"}
}