{
  "type": "Feature",
  "properties": {
    "gn:admin1_code":"4.0",
    "gn:asciiname":"Caoguandidian",
    "gn:country_code":"CN",
    "gn:dem":3,
    "gn:feature_class":"P",
    "gn:feature_code":"PPL",
    "gn:name":"Caoguandidian",
    "gn:population":0,
    "gn:timezone":"Asia/Shanghai",
    "iso:country":"CN",
    "name:zho_x_preferred":[
        "\u8349\u5173\u5e1d\u6bbf"
    ],
    "wof:name":"Caoguandidian",
    "wof:placetype":"locality"
},
  "geometry": {"coordinates":[120.31443,32.04296],"type":"Point"}
}