{
  "type": "Feature",
  "properties": {
    "gn:admin1_code":"1.0",
    "gn:asciiname":"Dongxuncun",
    "gn:country_code":"CN",
    "gn:dem":22,
    "gn:feature_class":"P",
    "gn:feature_code":"PPL",
    "gn:name":"Dongxuncun",
    "gn:population":0,
    "gn:timezone":"Asia/Shanghai",
    "iso:country":"CN",
    "name:und_x_variant":[
        "Dongxun"
    ],
    "name:zho_x_preferred":[
        "\u4e1c\u8340\u6751"
    ],
    "wof:name":"Dongxuncun",
    "wof:placetype":"locality"
},
  "geometry": {"coordinates":[117.58249000000001,33.29074],"type":"Point"}
}