{
  "type": "Feature",
  "properties": {
    "gn:admin1_code":"1.0",
    "gn:asciiname":"Yangyingcun",
    "gn:country_code":"CN",
    "gn:dem":22,
    "gn:feature_class":"P",
    "gn:feature_code":"PPL",
    "gn:name":"Yangyingcun",
    "gn:population":0,
    "gn:timezone":"Asia/Shanghai",
    "iso:country":"CN",
    "name:zho_x_preferred":[
        "\u6768\u8425\u6751"
    ],
    "wof:name":"Yangyingcun",
    "wof:placetype":"locality"
},
  "geometry": {"coordinates":[117.83034000000001,33.02177],"type":"Point"}
}