{
  "type": "Feature",
  "properties": {
    "gn:admin1_code":"29.0",
    "gn:asciiname":"Bachawan",
    "gn:country_code":"CN",
    "gn:dem":1830,
    "gn:feature_class":"P",
    "gn:feature_code":"PPL",
    "gn:name":"Bachawan",
    "gn:population":0,
    "gn:timezone":"Asia/Shanghai",
    "iso:country":"CN",
    "name:zho_x_preferred":[
        "\u5df4\u5c94\u6e7e"
    ],
    "wof:name":"Bachawan",
    "wof:placetype":"locality"
},
  "geometry": {"coordinates":[99.9555,26.9087],"type":"Point"}
}