{
  "type": "Feature",
  "properties": {
    "gn:admin1_code":"26.0",
    "gn:asciiname":"Yangtianwan",
    "gn:country_code":"CN",
    "gn:dem":700,
    "gn:feature_class":"P",
    "gn:feature_code":"PPL",
    "gn:name":"Yangtianwan",
    "gn:population":0,
    "gn:timezone":"Asia/Shanghai",
    "iso:country":"CN",
    "name:zho_x_preferred":[
        "\u79e7\u7530\u6e7e"
    ],
    "wof:name":"Yangtianwan",
    "wof:placetype":"locality"
},
  "geometry": {"coordinates":[109.35512,32.61025],"type":"Point"}
}