{
  "type": "Feature",
  "properties": {
    "gn:admin1_code":"25.0",
    "gn:asciiname":"Shangsunjia",
    "gn:country_code":"CN",
    "gn:dem":191,
    "gn:feature_class":"P",
    "gn:feature_code":"PPL",
    "gn:name":"Shangsunjia",
    "gn:population":0,
    "gn:timezone":"Asia/Shanghai",
    "iso:country":"CN",
    "name:zho_x_preferred":[
        "\u4e0a\u5b59\u5bb6"
    ],
    "wof:name":"Shangsunjia",
    "wof:placetype":"locality"
},
  "geometry": {"coordinates":[121.11830999999999,36.90576],"type":"Point"}
}