{
  "type": "Feature",
  "properties": {
    "gn:admin1_code":"4.0",
    "gn:asciiname":"Yuanzhuangcun",
    "gn:country_code":"CN",
    "gn:dem":1,
    "gn:feature_class":"P",
    "gn:feature_code":"PPL",
    "gn:name":"Yuanzhuangcun",
    "gn:population":0,
    "gn:timezone":"Asia/Shanghai",
    "iso:country":"CN",
    "name:zho_x_preferred":[
        "\u8881\u5e84\u6751"
    ],
    "wof:name":"Yuanzhuangcun",
    "wof:placetype":"locality"
},
  "geometry": {"coordinates":[120.10071000000001,33.42029],"type":"Point"}
}