{
  "type": "Feature",
  "properties": {
    "gn:admin1_code":"16.0",
    "gn:asciiname":"Qionggu",
    "gn:country_code":"CN",
    "gn:dem":283,
    "gn:feature_class":"P",
    "gn:feature_code":"PPL",
    "gn:name":"Qionggu",
    "gn:population":0,
    "gn:timezone":"Asia/Shanghai",
    "iso:country":"CN",
    "name:zho_x_preferred":[
        "\u743c\u53e4"
    ],
    "wof:name":"Qionggu",
    "wof:placetype":"locality"
},
  "geometry": {"coordinates":[108.517,23.9454],"type":"Point"}
}