{
  "type": "Feature",
  "properties": {
    "gn:admin1_code":"26.0",
    "gn:asciiname":"Pengshangyuan",
    "gn:country_code":"CN",
    "gn:dem":1135,
    "gn:feature_class":"P",
    "gn:feature_code":"PPL",
    "gn:name":"Pengshangyuan",
    "gn:population":0,
    "gn:timezone":"Asia/Shanghai",
    "iso:country":"CN",
    "name:zho_x_preferred":[
        "\u68da\u4e0a\u9662"
    ],
    "wof:name":"Pengshangyuan",
    "wof:placetype":"locality"
},
  "geometry": {"coordinates":[109.89604,33.76409],"type":"Point"}
}