{
  "type": "Feature",
  "properties": {
    "gn:admin1_code":"26.0",
    "gn:asciiname":"Houcuncun",
    "gn:country_code":"CN",
    "gn:dem":1252,
    "gn:feature_class":"P",
    "gn:feature_code":"PPL",
    "gn:name":"Houcuncun",
    "gn:population":0,
    "gn:timezone":"Asia/Shanghai",
    "iso:country":"CN",
    "name:zho_x_preferred":[
        "\u4faf\u6751\u6751"
    ],
    "wof:name":"Houcuncun",
    "wof:placetype":"locality"
},
  "geometry": {"coordinates":[109.25852999999999,36.03476],"type":"Point"}
}