{
  "type": "Feature",
  "properties": {
    "gn:admin1_code":"5.0",
    "gn:asciiname":"Dongyouzijing",
    "gn:country_code":"CN",
    "gn:dem":138,
    "gn:feature_class":"P",
    "gn:feature_code":"PPL",
    "gn:name":"Dongyouzijing",
    "gn:population":0,
    "gn:timezone":"Asia/Shanghai",
    "iso:country":"CN",
    "name:zho_x_preferred":[
        "\u4e1c\u6709\u5b57\u4e95"
    ],
    "wof:name":"Dongyouzijing",
    "wof:placetype":"locality"
},
  "geometry": {"coordinates":[124.21718,45.02607],"type":"Point"}
}