{
  "type": "Feature",
  "properties": {
    "gn:admin1_code":"13",
    "gn:asciiname":"Ke'erketicun",
    "gn:country_code":"CN",
    "gn:dem":2309,
    "gn:feature_class":"P",
    "gn:feature_code":"PPL",
    "gn:name":"Ke\u2019erketicun",
    "gn:population":0,
    "gn:timezone":"Asia/Urumqi",
    "iso:country":"CN",
    "name:und_x_variant":[
        "Ke\u2019erketicun",
        "\u514b\u5c14\u514b\u63d0\u6751"
    ],
    "wof:name":"Ke'erketicun",
    "wof:placetype":"locality"
},
  "geometry": {"coordinates":[86.70979,42.57304],"type":"Point"}
}