{
  "type": "Feature",
  "properties": {
    "gn:admin1_code":"15.0",
    "gn:asciiname":"Congzhuang",
    "gn:country_code":"CN",
    "gn:dem":1796,
    "gn:feature_class":"P",
    "gn:feature_code":"PPL",
    "gn:name":"Congzhuang",
    "gn:population":0,
    "gn:timezone":"Asia/Shanghai",
    "iso:country":"CN",
    "name:und_x_variant":[
        "\u4e1b\u5e84"
    ],
    "wof:name":"Congzhuang",
    "wof:placetype":"locality"
},
  "geometry": {"coordinates":[104.80165,34.96416],"type":"Point"}
}