{
  "type": "Feature",
  "properties": {
    "gn:admin1_code":"5.0",
    "gn:asciiname":"Ershiwu Gongli",
    "gn:country_code":"CN",
    "gn:dem":347,
    "gn:feature_class":"P",
    "gn:feature_code":"PPL",
    "gn:name":"Ershiwu Gongli",
    "gn:population":0,
    "gn:timezone":"Asia/Shanghai",
    "iso:country":"CN",
    "name:und_x_variant":[
        "\u4e8c\u5341\u4e94\u516c\u91cc"
    ],
    "wof:name":"Ershiwu Gongli",
    "wof:placetype":"locality"
},
  "geometry": {"coordinates":[129.94828999999999,43.20553],"type":"Point"}
}