{
  "type": "Feature",
  "properties": {
    "gn:admin1_code":"10.0",
    "gn:asciiname":"Huangyantou",
    "gn:country_code":"CN",
    "gn:dem":410,
    "gn:feature_class":"P",
    "gn:feature_code":"PPL",
    "gn:name":"Huangyantou",
    "gn:population":0,
    "gn:timezone":"Asia/Shanghai",
    "iso:country":"CN",
    "name:zho_x_preferred":[
        "\u9ec4\u5ca9\u5934"
    ],
    "wof:name":"Huangyantou",
    "wof:placetype":"locality"
},
  "geometry": {"coordinates":[114.96563999999999,39.25277],"type":"Point"}
}