{
  "type": "Feature",
  "properties": {
    "gn:admin1_code":"15.0",
    "gn:asciiname":"Caoposhan",
    "gn:country_code":"CN",
    "gn:dem":1915,
    "gn:feature_class":"P",
    "gn:feature_code":"PPL",
    "gn:name":"Caoposhan",
    "gn:population":0,
    "gn:timezone":"Asia/Shanghai",
    "iso:country":"CN",
    "name:zho_x_preferred":[
        "\u8349\u5761\u5c71"
    ],
    "wof:name":"Caoposhan",
    "wof:placetype":"locality"
},
  "geometry": {"coordinates":[104.53216,33.02329],"type":"Point"}
}