{
  "type": "Feature",
  "properties": {
    "gn:admin1_code":"21.0",
    "gn:asciiname":"Xishanwa",
    "gn:country_code":"CN",
    "gn:dem":1499,
    "gn:feature_class":"P",
    "gn:feature_code":"PPL",
    "gn:name":"Xishanwa",
    "gn:population":0,
    "gn:timezone":"Asia/Shanghai",
    "iso:country":"CN",
    "name:zho_x_preferred":[
        "\u897f\u5c71\u6d3c"
    ],
    "wof:name":"Xishanwa",
    "wof:placetype":"locality"
},
  "geometry": {"coordinates":[105.88200000000001,36.8732],"type":"Point"}
}