{
  "type": "Feature",
  "properties": {
    "gn:admin1_code":"10.0",
    "gn:asciiname":"Beidongzhuang",
    "gn:country_code":"CN",
    "gn:dem":215,
    "gn:feature_class":"P",
    "gn:feature_code":"PPL",
    "gn:name":"Beidongzhuang",
    "gn:population":0,
    "gn:timezone":"Asia/Shanghai",
    "iso:country":"CN",
    "name:und_x_variant":[
        "\u5317\u8463\u5e84"
    ],
    "wof:name":"Beidongzhuang",
    "wof:placetype":"locality"
},
  "geometry": {"coordinates":[114.28113999999999,38.58281],"type":"Point"}
}