{
  "type": "Feature",
  "properties": {
    "gn:admin1_code":"26.0",
    "gn:asciiname":"Banshangshi",
    "gn:country_code":"CN",
    "gn:dem":1137,
    "gn:feature_class":"P",
    "gn:feature_code":"PPL",
    "gn:name":"Banshangshi",
    "gn:population":0,
    "gn:timezone":"Asia/Shanghai",
    "iso:country":"CN",
    "name:und_x_variant":[
        "\u677f\u4e0a\u77f3"
    ],
    "wof:name":"Banshangshi",
    "wof:placetype":"locality"
},
  "geometry": {"coordinates":[106.25809,33.28419],"type":"Point"}
}