{
  "type": "Feature",
  "properties": {
    "gn:admin1_code":"02",
    "gn:asciiname":"Kaoshuwan",
    "gn:country_code":"CN",
    "gn:dem":9,
    "gn:feature_class":"P",
    "gn:feature_code":"PPL",
    "gn:name":"Kaoshuwan",
    "gn:population":0,
    "gn:timezone":"Asia/Shanghai",
    "iso:country":"CN",
    "name:und_x_variant":[
        "\u70e4\u6811\u6e7e"
    ],
    "wof:name":"Kaoshuwan",
    "wof:placetype":"locality"
},
  "geometry": {"coordinates":[122.22556000000002,29.83111],"type":"Point"}
}