{
  "type": "Feature",
  "properties": {
    "gn:admin1_code":"32.0",
    "gn:asciiname":"Nanwa",
    "gn:country_code":"CN",
    "gn:dem":2711,
    "gn:feature_class":"P",
    "gn:feature_code":"PPL",
    "gn:name":"Nanwa",
    "gn:population":0,
    "gn:timezone":"Asia/Shanghai",
    "iso:country":"CN",
    "name:zho_x_preferred":[
        "\u5357\u74e6"
    ],
    "wof:name":"Nanwa",
    "wof:placetype":"locality"
},
  "geometry": {"coordinates":[100.85478000000001,27.69572],"type":"Point"}
}