{
  "type": "Feature",
  "properties": {
    "gn:admin1_code":"32.0",
    "gn:asciiname":"Jinhuazhai",
    "gn:country_code":"CN",
    "gn:dem":476,
    "gn:feature_class":"P",
    "gn:feature_code":"PPL",
    "gn:name":"Jinhuazhai",
    "gn:population":0,
    "gn:timezone":"Asia/Shanghai",
    "iso:country":"CN",
    "name:zho_x_preferred":[
        "\u91d1\u82b1\u5be8"
    ],
    "wof:name":"Jinhuazhai",
    "wof:placetype":"locality"
},
  "geometry": {"coordinates":[106.70399999999999,31.4829],"type":"Point"}
}