{
  "type": "Feature",
  "properties": {
    "gn:admin1_code":"1.0",
    "gn:asciiname":"Tuanwan",
    "gn:country_code":"CN",
    "gn:dem":9,
    "gn:feature_class":"P",
    "gn:feature_code":"PPL",
    "gn:name":"Tuanwan",
    "gn:population":0,
    "gn:timezone":"Asia/Shanghai",
    "iso:country":"CN",
    "name:zho_x_preferred":[
        "\u56e2\u6e7e"
    ],
    "wof:name":"Tuanwan",
    "wof:placetype":"locality"
},
  "geometry": {"coordinates":[118.55374999999999,31.31447],"type":"Point"}
}