{
  "type": "Feature",
  "properties": {
    "gn:admin1_code":"25",
    "gn:asciiname":"Qianqukoudian",
    "gn:country_code":"CN",
    "gn:dem":137,
    "gn:feature_class":"P",
    "gn:feature_code":"PPL",
    "gn:name":"Qianqukoudian",
    "gn:population":0,
    "gn:timezone":"Asia/Shanghai",
    "iso:country":"CN",
    "name:zho_x_preferred":[
        "\u524d\u66f2\u53e3\u5e97"
    ],
    "wof:name":"Qianqukoudian",
    "wof:placetype":"locality"
},
  "geometry": {"coordinates":[117.253,36.1779],"type":"Point"}
}