{
  "type": "Feature",
  "properties": {
    "gn:admin1_code":"4.0",
    "gn:asciiname":"Zixin",
    "gn:country_code":"CN",
    "gn:dem":6,
    "gn:feature_class":"P",
    "gn:feature_code":"PPL",
    "gn:name":"Zixin",
    "gn:population":0,
    "gn:timezone":"Asia/Shanghai",
    "iso:country":"CN",
    "name:und_x_variant":[
        "\u81ea\u65b0"
    ],
    "wof:name":"Zixin",
    "wof:placetype":"locality"
},
  "geometry": {"coordinates":[121.10231,31.87886],"type":"Point"}
}