{
  "type": "Feature",
  "properties": {
    "gn:admin1_code":"32.0",
    "gn:asciiname":"Xiuguosi",
    "gn:country_code":"CN",
    "gn:dem":3672,
    "gn:feature_class":"P",
    "gn:feature_code":"PPL",
    "gn:name":"Xiuguosi",
    "gn:population":0,
    "gn:timezone":"Asia/Shanghai",
    "iso:country":"CN",
    "name:zho_x_preferred":[
        "\u4fee\u679c\u5bfa"
    ],
    "wof:name":"Xiuguosi",
    "wof:placetype":"locality"
},
  "geometry": {"coordinates":[100.375,31.8314],"type":"Point"}
}