{
  "type": "Feature",
  "properties": {
    "gn:admin1_code":"5.0",
    "gn:asciiname":"Ximozijing",
    "gn:country_code":"CN",
    "gn:dem":148,
    "gn:feature_class":"P",
    "gn:feature_code":"PPL",
    "gn:name":"Ximozijing",
    "gn:population":0,
    "gn:timezone":"Asia/Shanghai",
    "iso:country":"CN",
    "name:zho_x_preferred":[
        "\u897f\u58a8\u5b57\u4e95"
    ],
    "wof:name":"Ximozijing",
    "wof:placetype":"locality"
},
  "geometry": {"coordinates":[124.12156,44.909],"type":"Point"}
}