{
  "type": "Feature",
  "properties": {
    "gn:admin1_code":"15.0",
    "gn:asciiname":"Wangpu",
    "gn:country_code":"CN",
    "gn:dem":1916,
    "gn:feature_class":"P",
    "gn:feature_code":"PPLA4",
    "gn:name":"Wangpu",
    "gn:population":0,
    "gn:timezone":"Asia/Shanghai",
    "iso:country":"CN",
    "name:und_x_variant":[
        "\u738b\u94fa"
    ],
    "wof:name":"Wangpu",
    "wof:placetype":"locality"
},
  "geometry": {"coordinates":[105.43585,35.05712],"type":"Point"}
}