{
  "type": "Feature",
  "properties": {
    "gn:admin1_code":"32.0",
    "gn:asciiname":"Zaojiaolin",
    "gn:country_code":"CN",
    "gn:dem":1098,
    "gn:feature_class":"P",
    "gn:feature_code":"PPL",
    "gn:name":"Zaojiaolin",
    "gn:population":0,
    "gn:timezone":"Asia/Shanghai",
    "iso:country":"CN",
    "name:zho_x_preferred":[
        "\u7682\u89d2\u6797"
    ],
    "wof:name":"Zaojiaolin",
    "wof:placetype":"locality"
},
  "geometry": {"coordinates":[103.48632000000001,31.22943],"type":"Point"}
}