{
  "type": "Feature",
  "properties": {
    "gn:admin1_code":"12.0",
    "gn:asciiname":"Xiejiaping",
    "gn:country_code":"CN",
    "gn:dem":712,
    "gn:feature_class":"P",
    "gn:feature_code":"PPL",
    "gn:name":"Xiejiaping",
    "gn:population":0,
    "gn:timezone":"Asia/Shanghai",
    "iso:country":"CN",
    "name:zho_x_preferred":[
        "\u8c22\u5bb6\u576a"
    ],
    "wof:name":"Xiejiaping",
    "wof:placetype":"locality"
},
  "geometry": {"coordinates":[110.1267,32.51446],"type":"Point"}
}