{
  "type": "Feature",
  "properties": {
    "gn:admin1_code":"4.0",
    "gn:asciiname":"Qiuhazhuang",
    "gn:country_code":"CN",
    "gn:dem":58,
    "gn:feature_class":"P",
    "gn:feature_code":"PPL",
    "gn:name":"Qiuhazhuang",
    "gn:population":0,
    "gn:timezone":"Asia/Shanghai",
    "iso:country":"CN",
    "name:und_x_variant":[
        "\u90b1\u86e4\u5e84"
    ],
    "wof:name":"Qiuhazhuang",
    "wof:placetype":"locality"
},
  "geometry": {"coordinates":[118.54195,34.53069],"type":"Point"}
}