{
  "type": "Feature",
  "properties": {
    "gn:admin1_code":"11",
    "gn:asciiname":"Longkouwan",
    "gn:country_code":"CN",
    "gn:dem":425,
    "gn:feature_class":"P",
    "gn:feature_code":"PPL",
    "gn:name":"Longkouwan",
    "gn:population":0,
    "gn:timezone":"Asia/Shanghai",
    "iso:country":"CN",
    "name:zho_x_preferred":[
        "\u9f99\u53e3\u6e7e"
    ],
    "wof:name":"Longkouwan",
    "wof:placetype":"locality"
},
  "geometry": {"coordinates":[110.99083,27.65972],"type":"Point"}
}