{
  "type": "Feature",
  "properties": {
    "gn:admin1_code":"14.0",
    "gn:asciiname":"Goilunggoinba",
    "gn:country_code":"CN",
    "gn:dem":4387,
    "gn:feature_class":"P",
    "gn:feature_code":"PPL",
    "gn:name":"Goilunggoinba",
    "gn:population":0,
    "gn:timezone":"Asia/Urumqi",
    "iso:country":"CN",
    "name:bod_x_preferred":[
        "Goilunggoinba"
    ],
    "name:zho_x_preferred":[
        "Guolonggongba"
    ],
    "name:zho_x_variant":[
        "\u679c\u9f99\u8d21\u5df4",
        "Songduo Gongshe",
        "\u677e\u591a\u516c\u793e"
    ],
    "wof:name":"Goilunggoinba",
    "wof:placetype":"locality"
},
  "geometry": {"coordinates":[93.101,31.501],"type":"Point"}
}