{
  "type": "Feature",
  "properties": {
    "gn:admin1_code":"7",
    "gn:asciiname":"Huayuantou",
    "gn:country_code":"CN",
    "gn:dem":26,
    "gn:feature_class":"P",
    "gn:feature_code":"PPL",
    "gn:name":"Huayuantou",
    "gn:population":0,
    "gn:timezone":"Asia/Shanghai",
    "iso:country":"CN",
    "name:und_x_variant":[
        "\u82b1\u56ed\u5934"
    ],
    "name:zho_x_preferred":[
        "\u82b1\u56ed\u5934"
    ],
    "wof:name":"Huayuantou",
    "wof:placetype":"locality"
},
  "geometry": {"coordinates":[118.59305999999999,24.94417],"type":"Point"}
}