{
  "type": "Feature",
  "properties": {
    "gn:admin1_code":"20",
    "gn:asciiname":"Yalu",
    "gn:country_code":"CN",
    "gn:dem":533,
    "gn:feature_class":"P",
    "gn:feature_code":"PPL",
    "gn:name":"Yalu",
    "gn:population":0,
    "gn:timezone":"Asia/Shanghai",
    "iso:country":"CN",
    "name:eng_x_preferred":[
        "Yalu"
    ],
    "name:rus_x_preferred":[
        "\u042f\u043b\u0443"
    ],
    "name:und_x_variant":[
        "Ya-erh",
        "Yal",
        "Yalu"
    ],
    "name:zho_x_preferred":[
        "\u96c5\u9c81"
    ],
    "wof:name":"Yalu",
    "wof:placetype":"locality"
},
  "geometry": {"coordinates":[122.13719,48.54353],"type":"Point"}
}