{
  "type": "Feature",
  "properties": {
    "gn:admin1_code":"19.0",
    "gn:asciiname":"Baodequan",
    "gn:country_code":"CN",
    "gn:dem":600,
    "gn:feature_class":"P",
    "gn:feature_code":"PPL",
    "gn:name":"Baodequan",
    "gn:population":0,
    "gn:timezone":"Asia/Shanghai",
    "iso:country":"CN",
    "name:zho_x_preferred":[
        "\u5b9d\u5fb7\u5168"
    ],
    "wof:name":"Baodequan",
    "wof:placetype":"locality"
},
  "geometry": {"coordinates":[119.46722,41.96163],"type":"Point"}
}