{
  "type": "Feature",
  "properties": {
    "gn:admin1_code":"24.0",
    "gn:asciiname":"Dushucun",
    "gn:country_code":"CN",
    "gn:dem":1054,
    "gn:feature_class":"P",
    "gn:feature_code":"PPL",
    "gn:name":"Dushucun",
    "gn:population":0,
    "gn:timezone":"Asia/Shanghai",
    "iso:country":"CN",
    "name:zho_x_preferred":[
        "\u72ec\u6811\u6751"
    ],
    "wof:name":"Dushucun",
    "wof:placetype":"locality"
},
  "geometry": {"coordinates":[113.45262,40.07082],"type":"Point"}
}