{
  "type": "Feature",
  "properties": {
    "gn:admin1_code":"2.0",
    "gn:asciiname":"Xiadieshi",
    "gn:country_code":"CN",
    "gn:dem":293,
    "gn:feature_class":"P",
    "gn:feature_code":"PPL",
    "gn:name":"Xiadieshi",
    "gn:population":0,
    "gn:timezone":"Asia/Shanghai",
    "iso:country":"CN",
    "name:zho_x_preferred":[
        "\u4e0b\u8fed\u77f3"
    ],
    "wof:name":"Xiadieshi",
    "wof:placetype":"locality"
},
  "geometry": {"coordinates":[121.12463,29.40354],"type":"Point"}
}