{
  "type": "Feature",
  "properties": {
    "gn:admin1_code":"29.0",
    "gn:asciiname":"Lunaqing",
    "gn:country_code":"CN",
    "gn:dem":2053,
    "gn:feature_class":"P",
    "gn:feature_code":"PPL",
    "gn:name":"Lunaqing",
    "gn:population":0,
    "gn:timezone":"Asia/Shanghai",
    "iso:country":"CN",
    "name:zho_x_preferred":[
        "\u9c81\u7eb3\u7b90"
    ],
    "wof:name":"Lunaqing",
    "wof:placetype":"locality"
},
  "geometry": {"coordinates":[103.279,25.9468],"type":"Point"}
}