{
  "type": "Feature",
  "properties": {
    "gn:admin1_code":"2.0",
    "gn:asciiname":"Nanshangchen",
    "gn:country_code":"CN",
    "gn:dem":142,
    "gn:feature_class":"P",
    "gn:feature_code":"PPL",
    "gn:name":"Nanshangchen",
    "gn:population":0,
    "gn:timezone":"Asia/Shanghai",
    "iso:country":"CN",
    "name:zho_x_preferred":[
        "\u5357\u4e0a\u9648"
    ],
    "wof:name":"Nanshangchen",
    "wof:placetype":"locality"
},
  "geometry": {"coordinates":[121.20977999999999,29.92292],"type":"Point"}
}