{
  "type": "Feature",
  "properties": {
    "gn:admin1_code":"4.0",
    "gn:asciiname":"Shuixicun",
    "gn:country_code":"CN",
    "gn:dem":10,
    "gn:feature_class":"P",
    "gn:feature_code":"PPL",
    "gn:name":"Shuixicun",
    "gn:population":0,
    "gn:timezone":"Asia/Shanghai",
    "iso:country":"CN",
    "name:und_x_variant":[
        "Shuixi",
        "Shuixicun"
    ],
    "name:zho_x_preferred":[
        "\u6c34\u897f"
    ],
    "name:zho_x_variant":[
        "\u6c34\u897f\u6751"
    ],
    "wof:name":"Shuixicun",
    "wof:placetype":"locality"
},
  "geometry": {"coordinates":[119.34088,31.50971],"type":"Point"}
}