{
  "type": "Feature",
  "properties": {
    "gn:admin1_code":"4.0",
    "gn:asciiname":"Qunlicun",
    "gn:country_code":"CN",
    "gn:dem":18,
    "gn:feature_class":"P",
    "gn:feature_code":"PPL",
    "gn:name":"Qunlicun",
    "gn:population":0,
    "gn:timezone":"Asia/Shanghai",
    "iso:country":"CN",
    "name:und_x_variant":[
        "Qunli"
    ],
    "name:zho_x_preferred":[
        "\u7fa4\u529b\u6751"
    ],
    "wof:name":"Qunlicun",
    "wof:placetype":"locality"
},
  "geometry": {"coordinates":[119.00988999999998,31.74048],"type":"Point"}
}