{
  "type": "Feature",
  "properties": {
    "gn:admin1_code":"3.0",
    "gn:asciiname":"Henglujiang",
    "gn:country_code":"CN",
    "gn:dem":95,
    "gn:feature_class":"P",
    "gn:feature_code":"PPL",
    "gn:name":"Henglujiang",
    "gn:population":0,
    "gn:timezone":"Asia/Shanghai",
    "iso:country":"CN",
    "name:zho_x_preferred":[
        "\u6a2a\u8def\u6c5f"
    ],
    "wof:name":"Henglujiang",
    "wof:placetype":"locality"
},
  "geometry": {"coordinates":[117.712,29.2598],"type":"Point"}
}