{
  "type": "Feature",
  "properties": {
    "gn:admin1_code":"9",
    "gn:asciiname":"Zhangbaofu",
    "gn:country_code":"CN",
    "gn:dem":69,
    "gn:feature_class":"P",
    "gn:feature_code":"PPL",
    "gn:name":"Zhangbaofu",
    "gn:population":0,
    "gn:timezone":"Asia/Shanghai",
    "iso:country":"CN",
    "name:zho_x_preferred":[
        "\u5f20\u4fdd\u5e9c"
    ],
    "wof:name":"Zhangbaofu",
    "wof:placetype":"locality"
},
  "geometry": {"coordinates":[115.226,34.8608],"type":"Point"}
}