{
  "type": "Feature",
  "properties": {
    "gn:admin1_code":"9.0",
    "gn:asciiname":"Dongmazhuang",
    "gn:country_code":"CN",
    "gn:dem":73,
    "gn:feature_class":"P",
    "gn:feature_code":"PPL",
    "gn:name":"Dongmazhuang",
    "gn:population":0,
    "gn:timezone":"Asia/Shanghai",
    "iso:country":"CN",
    "name:zho_x_preferred":[
        "\u4e1c\u9a6c\u5e84"
    ],
    "wof:name":"Dongmazhuang",
    "wof:placetype":"locality"
},
  "geometry": {"coordinates":[114.45139,34.99695],"type":"Point"}
}