{
  "type": "Feature",
  "properties": {
    "gn:admin1_code":"16.0",
    "gn:asciiname":"Nanhe",
    "gn:country_code":"CN",
    "gn:dem":145,
    "gn:feature_class":"P",
    "gn:feature_code":"PPL",
    "gn:name":"Nanhe",
    "gn:population":0,
    "gn:timezone":"Asia/Shanghai",
    "iso:country":"CN",
    "name:deu_x_preferred":[
        "Nanhe"
    ],
    "name:fra_x_preferred":[
        "Nanhe"
    ],
    "name:zho_x_preferred":[
        "\u5357\u548c"
    ],
    "wof:name":"Nanhe",
    "wof:placetype":"locality"
},
  "geometry": {"coordinates":[110.962,22.7396],"type":"Point"}
}