{
  "type": "Feature",
  "properties": {
    "gn:admin1_code":"29.0",
    "gn:asciiname":"Huadiping",
    "gn:country_code":"CN",
    "gn:dem":1234,
    "gn:feature_class":"P",
    "gn:feature_code":"PPL",
    "gn:name":"Huadiping",
    "gn:population":0,
    "gn:timezone":"Asia/Shanghai",
    "iso:country":"CN",
    "name:zho_x_preferred":[
        "\u82b1\u5730\u576a"
    ],
    "wof:name":"Huadiping",
    "wof:placetype":"locality"
},
  "geometry": {"coordinates":[98.8904,25.7085],"type":"Point"}
}