{
  "type": "Feature",
  "properties": {
    "gn:admin1_code":"9.0",
    "gn:asciiname":"Sanlifang",
    "gn:country_code":"CN",
    "gn:dem":661,
    "gn:feature_class":"P",
    "gn:feature_code":"PPL",
    "gn:name":"Sanlifang",
    "gn:population":0,
    "gn:timezone":"Asia/Shanghai",
    "iso:country":"CN",
    "name:und_x_variant":[
        "\u4e09\u91cc\u65b9",
        "Sanlifang"
    ],
    "wof:name":"Sanlifang",
    "wof:placetype":"locality"
},
  "geometry": {"coordinates":[112.45887999999999,33.93895999999999],"type":"Point"}
}