{
  "type": "Feature",
  "properties": {
    "gn:admin1_code":"30.0",
    "gn:asciiname":"Jinyusha",
    "gn:country_code":"CN",
    "gn:dem":17,
    "gn:feature_class":"P",
    "gn:feature_code":"PPL",
    "gn:name":"Jinyusha",
    "gn:population":0,
    "gn:timezone":"Asia/Shanghai",
    "iso:country":"CN",
    "name:zho_x_preferred":[
        "\u91d1\u9c7c\u6c99"
    ],
    "wof:name":"Jinyusha",
    "wof:placetype":"locality"
},
  "geometry": {"coordinates":[112.19546,23.08444],"type":"Point"}
}