{
  "type": "Feature",
  "properties": {
    "gn:admin1_code":"33",
    "gn:asciiname":"Haitangxi",
    "gn:cc2":"CN",
    "gn:country_code":"CN",
    "gn:dem":168,
    "gn:feature_class":"P",
    "gn:feature_code":"PPL",
    "gn:name":"Haitangxi",
    "gn:population":0,
    "gn:timezone":"Asia/Shanghai",
    "iso:country":"CN",
    "name:und_x_variant":[
        "Hai-t\u2019ang-hsi",
        "Haitangxi"
    ],
    "wof:name":"Haitangxi",
    "wof:placetype":"locality"
},
  "geometry": {"coordinates":[106.58333,29.55],"type":"Point"}
}