{
  "type": "Feature",
  "properties": {
    "gn:admin1_code":"24.0",
    "gn:asciiname":"Liuwa",
    "gn:country_code":"CN",
    "gn:dem":1468,
    "gn:feature_class":"P",
    "gn:feature_code":"PPL",
    "gn:name":"Liuwa",
    "gn:population":0,
    "gn:timezone":"Asia/Shanghai",
    "iso:country":"CN",
    "name:zho_x_preferred":[
        "\u67f3\u7a8a"
    ],
    "wof:name":"Liuwa",
    "wof:placetype":"locality"
},
  "geometry": {"coordinates":[111.45285,37.26691],"type":"Point"}
}