{
  "type": "Feature",
  "properties": {
    "gn:admin1_code":"4.0",
    "gn:asciiname":"Daxing",
    "gn:country_code":"CN",
    "gn:dem":5,
    "gn:feature_class":"P",
    "gn:feature_code":"PPL",
    "gn:name":"Daxing",
    "gn:population":0,
    "gn:timezone":"Asia/Shanghai",
    "iso:country":"CN",
    "name:ceb_x_preferred":[
        "Daxing"
    ],
    "name:deu_x_preferred":[
        "Daxing"
    ],
    "name:mlg_x_preferred":[
        "Daxing"
    ],
    "name:nor_x_preferred":[
        "Daxing"
    ],
    "name:zho_x_preferred":[
        "\u5927\u5174"
    ],
    "wof:name":"Daxing",
    "wof:placetype":"locality"
},
  "geometry": {"coordinates":[120.54653999999999,32.25184],"type":"Point"}
}