{
  "type": "Feature",
  "properties": {
    "gn:admin1_code":"15.0",
    "gn:asciiname":"Miao'erzhang",
    "gn:country_code":"CN",
    "gn:dem":1812,
    "gn:feature_class":"P",
    "gn:feature_code":"PPL",
    "gn:name":"Miao\u2019erzhang",
    "gn:population":0,
    "gn:timezone":"Asia/Shanghai",
    "iso:country":"CN",
    "name:und_x_variant":[
        "Miao\u2019erzhang",
        "\u5e99\u513f\u638c"
    ],
    "wof:name":"Miao'erzhang",
    "wof:placetype":"locality"
},
  "geometry": {"coordinates":[106.56189000000001,36.32454],"type":"Point"}
}