{
  "type": "Feature",
  "properties": {
    "gn:admin1_code":"7",
    "gn:asciiname":"Xikou",
    "gn:country_code":"CN",
    "gn:dem":313,
    "gn:feature_class":"P",
    "gn:feature_code":"PPLA4",
    "gn:name":"Xikou",
    "gn:population":0,
    "gn:timezone":"Asia/Shanghai",
    "iso:country":"CN",
    "name:und_x_variant":[
        "\u6eaa\u53e3",
        "Xikou Xiang",
        "\u6eaa\u53e3\u4e61"
    ],
    "wof:name":"Xikou",
    "wof:placetype":"locality"
},
  "geometry": {"coordinates":[116.67504,25.06415],"type":"Point"}
}