{
  "type": "Feature",
  "properties": {
    "gn:admin1_code":"14.0",
    "gn:asciiname":"Xianbatang",
    "gn:country_code":"CN",
    "gn:dem":4109,
    "gn:feature_class":"P",
    "gn:feature_code":"PPL",
    "gn:name":"Xianbatang",
    "gn:population":0,
    "gn:timezone":"Asia/Urumqi",
    "iso:country":"CN",
    "name:zho_x_preferred":[
        "\u5148\u5df4\u5858"
    ],
    "wof:name":"Xianbatang",
    "wof:placetype":"locality"
},
  "geometry": {"coordinates":[92.68492999999999,29.96054],"type":"Point"}
}