{
  "type": "Feature",
  "properties": {
    "gn:admin1_code":"30",
    "gn:asciiname":"Houyuanxu",
    "gn:country_code":"CN",
    "gn:dem":521,
    "gn:feature_class":"P",
    "gn:feature_code":"PPL",
    "gn:name":"Houyuanxu",
    "gn:population":0,
    "gn:timezone":"Asia/Urumqi",
    "iso:country":"CN",
    "name:zho_x_preferred":[
        "\u539a\u5143\u5729"
    ],
    "wof:name":"Houyuanxu",
    "wof:placetype":"locality"
},
  "geometry": {"coordinates":[111.31444,22.26889],"type":"Point"}
}