{
  "type": "Feature",
  "properties": {
    "gn:admin1_code":"15.0",
    "gn:asciiname":"Hongshui",
    "gn:country_code":"CN",
    "gn:dem":2276,
    "gn:feature_class":"P",
    "gn:feature_code":"PPL",
    "gn:name":"Hongshui",
    "gn:population":0,
    "gn:timezone":"Asia/Shanghai",
    "iso:country":"CN",
    "name:und_x_variant":[
        "\u7ea2\u6c34"
    ],
    "wof:name":"Hongshui",
    "wof:placetype":"locality"
},
  "geometry": {"coordinates":[104.07332,34.52299],"type":"Point"}
}