{
  "type": "Feature",
  "properties": {
    "gn:admin1_code":"19.0",
    "gn:asciiname":"Sanjiangkou Nongchang",
    "gn:country_code":"CN",
    "gn:dem":121,
    "gn:feature_class":"P",
    "gn:feature_code":"PPLF",
    "gn:name":"Sanjiangkou Nongchang",
    "gn:population":0,
    "gn:timezone":"Asia/Shanghai",
    "iso:country":"CN",
    "name:zho_x_preferred":[
        "\u4e09\u6c5f\u53e3\u519c\u573a"
    ],
    "wof:name":"Sanjiangkou Nongchang",
    "wof:placetype":"locality"
},
  "geometry": {"coordinates":[123.76188,43.34463],"type":"Point"}
}