{
  "type": "Feature",
  "properties": {
    "gn:admin1_code":"4.0",
    "gn:asciiname":"Xichangmen",
    "gn:country_code":"CN",
    "gn:dem":23,
    "gn:feature_class":"P",
    "gn:feature_code":"PPLA4",
    "gn:name":"Xichangmen",
    "gn:population":0,
    "gn:timezone":"Asia/Shanghai",
    "iso:country":"CN",
    "name:und_x_variant":[
        "\u897f\u5382\u95e8",
        "Xichangmen Jiedao"
    ],
    "name:zho_x_preferred":[
        "\u897f\u5382\u95e8\u8857\u9053"
    ],
    "wof:name":"Xichangmen",
    "wof:placetype":"locality"
},
  "geometry": {"coordinates":[118.75807,32.22417],"type":"Point"}
}