{
  "type": "Feature",
  "properties": {
    "gn:admin1_code":"12.0",
    "gn:asciiname":"Chenyudong",
    "gn:country_code":"CN",
    "gn:dem":1004,
    "gn:feature_class":"P",
    "gn:feature_code":"PPL",
    "gn:name":"Chenyudong",
    "gn:population":0,
    "gn:timezone":"Asia/Shanghai",
    "iso:country":"CN",
    "name:zho_x_preferred":[
        "Chenyudong"
    ],
    "name:zho_x_variant":[
        "\u9648\u5b87\u6d1e"
    ],
    "wof:name":"Chenyudong",
    "wof:placetype":"locality"
},
  "geometry": {"coordinates":[111.1512,30.13238],"type":"Point"}
}