{
  "type": "Feature",
  "properties": {
    "gn:admin1_code":"8.0",
    "gn:asciiname":"Xiongweicun",
    "gn:country_code":"CN",
    "gn:dem":140,
    "gn:feature_class":"P",
    "gn:feature_code":"PPL",
    "gn:name":"Xiongweicun",
    "gn:population":0,
    "gn:timezone":"Asia/Shanghai",
    "iso:country":"CN",
    "name:zho_x_preferred":[
        "\u96c4\u4f1f\u6751"
    ],
    "wof:name":"Xiongweicun",
    "wof:placetype":"locality"
},
  "geometry": {"coordinates":[130.03756999999999,46.4975],"type":"Point"}
}