{
  "type": "Feature",
  "properties": {
    "gn:admin1_code":"01",
    "gn:asciiname":"Caicun",
    "gn:country_code":"CN",
    "gn:dem":65,
    "gn:feature_class":"P",
    "gn:feature_code":"PPLA4",
    "gn:name":"Caicun",
    "gn:population":0,
    "gn:timezone":"Asia/Shanghai",
    "iso:country":"CN",
    "name:und_x_variant":[
        "Ts\u2019ai-ts\u2019un",
        "Caicunba",
        "Ts\u2019ai-ts\u2019un-pa",
        "Caicun Zhen",
        "Ma-y\u00fcan-k\u2019ou",
        "Caicun",
        "\u8521\u6751",
        "\u8521\u6751\u9547"
    ],
    "wof:name":"Caicun",
    "wof:placetype":"locality"
},
  "geometry": {"coordinates":[118.55038999999999,30.7172],"type":"Point"}
}