{
  "type": "Feature",
  "properties": {
    "gn:admin1_code":"18",
    "gn:asciiname":"Dayantang",
    "gn:country_code":"CN",
    "gn:dem":464,
    "gn:feature_class":"P",
    "gn:feature_code":"PPL",
    "gn:name":"Dayantang",
    "gn:population":0,
    "gn:timezone":"Asia/Shanghai",
    "iso:country":"CN",
    "name:zho_x_preferred":[
        "\u5927\u5830\u5858"
    ],
    "wof:name":"Dayantang",
    "wof:placetype":"locality"
},
  "geometry": {"coordinates":[108.205,27.7051],"type":"Point"}
}