{
  "type": "Feature",
  "properties": {
    "gn:admin1_code":"11",
    "gn:asciiname":"Lianqiao",
    "gn:cc2":"CN",
    "gn:country_code":"CN",
    "gn:dem":266,
    "gn:feature_class":"P",
    "gn:feature_code":"PPL",
    "gn:name":"Lianqiao",
    "gn:population":0,
    "gn:timezone":"Asia/Shanghai",
    "iso:country":"CN",
    "name:und_x_variant":[
        "Lien-ch\u2019iao",
        "Lianqiao"
    ],
    "wof:name":"Lianqiao",
    "wof:placetype":"locality"
},
  "geometry": {"coordinates":[111.8425,27.32222],"type":"Point"}
}