{
  "type": "Feature",
  "properties": {
    "gn:admin1_code":"26.0",
    "gn:asciiname":"Zhujia Yuanzi",
    "gn:country_code":"CN",
    "gn:dem":830,
    "gn:feature_class":"P",
    "gn:feature_code":"PPL",
    "gn:name":"Zhujia Yuanzi",
    "gn:population":0,
    "gn:timezone":"Asia/Shanghai",
    "iso:country":"CN",
    "name:zho_x_preferred":[
        "\u6731\u5bb6\u9662\u5b50"
    ],
    "wof:name":"Zhujia Yuanzi",
    "wof:placetype":"locality"
},
  "geometry": {"coordinates":[108.33701000000001,33.13933],"type":"Point"}
}