{
  "type": "Feature",
  "properties": {
    "gn:admin1_code":"4.0",
    "gn:asciiname":"Chaoqiao",
    "gn:country_code":"CN",
    "gn:dem":4,
    "gn:feature_class":"P",
    "gn:feature_code":"PPLA4",
    "gn:name":"Chaoqiao",
    "gn:population":0,
    "gn:timezone":"Asia/Shanghai",
    "iso:country":"CN",
    "name:und_x_variant":[
        "\u6f6e\u6865",
        "Chaoqiao Zhen"
    ],
    "name:zho_x_preferred":[
        "\u6f6e\u6865\u9547"
    ],
    "wof:name":"Chaoqiao",
    "wof:placetype":"locality"
},
  "geometry": {"coordinates":[120.67371,32.55031],"type":"Point"}
}