{
  "type": "Feature",
  "properties": {
    "gn:admin1_code":"4.0",
    "gn:asciiname":"Xinxian",
    "gn:cc2":"CN",
    "gn:country_code":"CN",
    "gn:dem":118,
    "gn:feature_class":"P",
    "gn:feature_code":"PPL",
    "gn:name":"Xinxian",
    "gn:population":0,
    "gn:timezone":"Asia/Shanghai",
    "iso:country":"CN",
    "name:ceb_x_preferred":[
        "Xinxian"
    ],
    "name:und_x_variant":[
        "Hsin-hsien"
    ],
    "wof:name":"Xinxian",
    "wof:placetype":"locality"
},
  "geometry": {"coordinates":[119.28333000000001,34.66667],"type":"Point"}
}