{
  "type": "Feature",
  "properties": {
    "gn:admin1_code":"32.0",
    "gn:asciiname":"Baoma",
    "gn:country_code":"CN",
    "gn:dem":384,
    "gn:feature_class":"P",
    "gn:feature_code":"PPL",
    "gn:name":"Baoma",
    "gn:population":0,
    "gn:timezone":"Asia/Shanghai",
    "iso:country":"CN",
    "name:ceb_x_preferred":[
        "Baoma"
    ],
    "name:ron_x_preferred":[
        "Baoma"
    ],
    "name:zho_x_preferred":[
        "\u5b9d\u9a6c"
    ],
    "wof:name":"Baoma",
    "wof:placetype":"locality"
},
  "geometry": {"coordinates":[105.28100000000001,30.0895],"type":"Point"}
}