{
  "type": "Feature",
  "properties": {
    "gn:admin1_code":"18",
    "gn:asciiname":"Muyuchang",
    "gn:country_code":"CN",
    "gn:dem":1217,
    "gn:feature_class":"P",
    "gn:feature_code":"PPL",
    "gn:name":"Muyuchang",
    "gn:population":0,
    "gn:timezone":"Asia/Shanghai",
    "iso:country":"CN",
    "name:zho_x_preferred":[
        "\u6728\u9c7c\u5382"
    ],
    "wof:name":"Muyuchang",
    "wof:placetype":"locality"
},
  "geometry": {"coordinates":[107.986,28.5636],"type":"Point"}
}