{
  "type": "Feature",
  "properties": {
    "gn:admin1_code":"07",
    "gn:asciiname":"Hengsuo",
    "gn:cc2":"CN",
    "gn:country_code":"CN",
    "gn:dem":588,
    "gn:feature_class":"P",
    "gn:feature_code":"PPL",
    "gn:name":"Hengsuo",
    "gn:population":0,
    "gn:timezone":"Asia/Shanghai",
    "iso:country":"CN",
    "name:und_x_variant":[
        "Heng-so",
        "Hengsuo"
    ],
    "wof:name":"Hengsuo",
    "wof:placetype":"locality"
},
  "geometry": {"coordinates":[116.66667,26.16667],"type":"Point"}
}