{
  "type": "Feature",
  "properties": {
    "gn:admin1_code":"25.0",
    "gn:asciiname":"Nanbozi",
    "gn:country_code":"CN",
    "gn:dem":4,
    "gn:feature_class":"P",
    "gn:feature_code":"PPL",
    "gn:name":"Nanbozi",
    "gn:population":0,
    "gn:timezone":"Asia/Shanghai",
    "iso:country":"CN",
    "name:zho_x_preferred":[
        "\u5357\u6cca\u5b50"
    ],
    "wof:name":"Nanbozi",
    "wof:placetype":"locality"
},
  "geometry": {"coordinates":[120.66958,36.35523],"type":"Point"}
}