{
  "type": "Feature",
  "properties": {
    "gn:admin1_code":"26.0",
    "gn:asciiname":"Caibacun",
    "gn:country_code":"CN",
    "gn:dem":500,
    "gn:feature_class":"P",
    "gn:feature_code":"PPL",
    "gn:name":"Caibacun",
    "gn:population":0,
    "gn:timezone":"Asia/Shanghai",
    "iso:country":"CN",
    "name:und_x_variant":[
        "\u8521\u575d\u6751"
    ],
    "wof:name":"Caibacun",
    "wof:placetype":"locality"
},
  "geometry": {"coordinates":[107.69229,33.18423],"type":"Point"}
}