{
  "type": "Feature",
  "properties": {
    "gn:admin1_code":"11.0",
    "gn:asciiname":"Mutouzhai",
    "gn:country_code":"CN",
    "gn:dem":690,
    "gn:feature_class":"P",
    "gn:feature_code":"PPL",
    "gn:name":"Mutouzhai",
    "gn:population":0,
    "gn:timezone":"Asia/Shanghai",
    "iso:country":"CN",
    "name:zho_x_preferred":[
        "\u6728\u5934\u5be8"
    ],
    "wof:name":"Mutouzhai",
    "wof:placetype":"locality"
},
  "geometry": {"coordinates":[109.50832,28.29599],"type":"Point"}
}