{
  "type": "Feature",
  "properties": {
    "gn:admin1_code":"30.0",
    "gn:asciiname":"Guanbuli",
    "gn:country_code":"CN",
    "gn:dem":10,
    "gn:feature_class":"P",
    "gn:feature_code":"PPL",
    "gn:name":"Guanbuli",
    "gn:population":0,
    "gn:timezone":"Asia/Shanghai",
    "iso:country":"CN",
    "name:zho_x_preferred":[
        "\u5b98\u6b65\u91cc"
    ],
    "wof:name":"Guanbuli",
    "wof:placetype":"locality"
},
  "geometry": {"coordinates":[112.72374000000001,22.21242],"type":"Point"}
}