{
  "type": "Feature",
  "properties": {
    "gn:admin1_code":"30.0",
    "gn:asciiname":"Zuotongcun",
    "gn:country_code":"CN",
    "gn:dem":13,
    "gn:feature_class":"P",
    "gn:feature_code":"PPL",
    "gn:name":"Zuotongcun",
    "gn:population":0,
    "gn:timezone":"Asia/Shanghai",
    "iso:country":"CN",
    "name:zho_x_preferred":[
        "\u795a\u901a\u6751"
    ],
    "wof:name":"Zuotongcun",
    "wof:placetype":"locality"
},
  "geometry": {"coordinates":[116.29268,23.03461],"type":"Point"}
}