{
  "type": "Feature",
  "properties": {
    "gn:admin1_code":"16",
    "gn:asciiname":"Yajizhai",
    "gn:country_code":"CN",
    "gn:dem":319,
    "gn:feature_class":"P",
    "gn:feature_code":"PPL",
    "gn:name":"Yajizhai",
    "gn:population":0,
    "gn:timezone":"Asia/Shanghai",
    "iso:country":"CN",
    "name:zho_x_preferred":[
        "\u96c5\u5409\u5be8"
    ],
    "wof:name":"Yajizhai",
    "wof:placetype":"locality"
},
  "geometry": {"coordinates":[110.55500000000001,25.4514],"type":"Point"}
}