{
  "type": "Feature",
  "properties": {
    "gn:admin1_code":"20.0",
    "gn:asciiname":"Borong Xiaotun",
    "gn:country_code":"CN",
    "gn:dem":189,
    "gn:feature_class":"P",
    "gn:feature_code":"PPL",
    "gn:name":"Borong Xiaotun",
    "gn:population":0,
    "gn:timezone":"Asia/Shanghai",
    "iso:country":"CN",
    "name:zho_x_preferred":[
        "\u535a\u8363\u5c0f\u5c6f"
    ],
    "wof:name":"Borong Xiaotun",
    "wof:placetype":"locality"
},
  "geometry": {"coordinates":[124.45350000000001,48.35254000000001],"type":"Point"}
}