{
  "type": "Feature",
  "properties": {
    "gn:admin1_code":"30.0",
    "gn:asciiname":"Damiantian",
    "gn:country_code":"CN",
    "gn:dem":239,
    "gn:feature_class":"P",
    "gn:feature_code":"PPL",
    "gn:name":"Damiantian",
    "gn:population":0,
    "gn:timezone":"Asia/Shanghai",
    "iso:country":"CN",
    "name:zho_x_preferred":[
        "\u5927\u9762\u7530"
    ],
    "wof:name":"Damiantian",
    "wof:placetype":"locality"
},
  "geometry": {"coordinates":[114.8896,23.1114],"type":"Point"}
}