{
  "type": "Feature",
  "properties": {
    "gn:admin1_code":"29",
    "gn:asciiname":"Baidamo",
    "gn:country_code":"CN",
    "gn:dem":1698,
    "gn:feature_class":"P",
    "gn:feature_code":"PPL",
    "gn:name":"Baidamo",
    "gn:population":0,
    "gn:timezone":"Asia/Shanghai",
    "iso:country":"CN",
    "name:zho_x_preferred":[
        "\u767d\u6253\u83ab"
    ],
    "wof:name":"Baidamo",
    "wof:placetype":"locality"
},
  "geometry": {"coordinates":[102.06399999999999,23.6704],"type":"Point"}
}