{
  "type": "Feature",
  "properties": {
    "gn:admin1_code":"25.0",
    "gn:asciiname":"Lujiagou",
    "gn:country_code":"CN",
    "gn:dem":255,
    "gn:feature_class":"P",
    "gn:feature_code":"PPL",
    "gn:name":"Lujiagou",
    "gn:population":0,
    "gn:timezone":"Asia/Shanghai",
    "iso:country":"CN",
    "name:zho_x_preferred":[
        "\u8def\u5bb6\u6c9f"
    ],
    "wof:name":"Lujiagou",
    "wof:placetype":"locality"
},
  "geometry": {"coordinates":[120.76036000000001,37.40105],"type":"Point"}
}