{
  "type": "Feature",
  "properties": {
    "gn:admin1_code":"9",
    "gn:asciiname":"Sanliqiao",
    "gn:country_code":"CN",
    "gn:dem":48,
    "gn:feature_class":"P",
    "gn:feature_code":"PPL",
    "gn:name":"Sanliqiao",
    "gn:population":0,
    "gn:timezone":"Asia/Shanghai",
    "iso:country":"CN",
    "name:zho_x_preferred":[
        "\u4e09\u91cc\u6865"
    ],
    "wof:name":"Sanliqiao",
    "wof:placetype":"locality"
},
  "geometry": {"coordinates":[115.636,34.373],"type":"Point"}
}