{
  "type": "Feature",
  "properties": {
    "gn:admin1_code":"26.0",
    "gn:asciiname":"Quanshuigounao",
    "gn:country_code":"CN",
    "gn:dem":1244,
    "gn:feature_class":"P",
    "gn:feature_code":"PPL",
    "gn:name":"Quanshuigounao",
    "gn:population":0,
    "gn:timezone":"Asia/Shanghai",
    "iso:country":"CN",
    "name:zho_x_preferred":[
        "\u6cc9\u6c34\u6c9f\u57b4"
    ],
    "wof:name":"Quanshuigounao",
    "wof:placetype":"locality"
},
  "geometry": {"coordinates":[109.84456000000002,33.42815],"type":"Point"}
}