{
  "type": "Feature",
  "properties": {
    "gn:admin1_code":"29.0",
    "gn:asciiname":"Dubi",
    "gn:country_code":"CN",
    "gn:dem":1830,
    "gn:feature_class":"P",
    "gn:feature_code":"PPL",
    "gn:name":"Dubi",
    "gn:population":0,
    "gn:timezone":"Asia/Shanghai",
    "iso:country":"CN",
    "name:zho_x_preferred":[
        "\u90fd\u6bd4"
    ],
    "wof:name":"Dubi",
    "wof:placetype":"locality"
},
  "geometry": {"coordinates":[103.408,23.6465],"type":"Point"}
}