{
  "type": "Feature",
  "properties": {
    "gn:admin1_code":"3.0",
    "gn:asciiname":"Shi'ao",
    "gn:country_code":"CN",
    "gn:dem":371,
    "gn:feature_class":"P",
    "gn:feature_code":"PPL",
    "gn:name":"Shi\u2019ao",
    "gn:population":0,
    "gn:timezone":"Asia/Shanghai",
    "iso:country":"CN",
    "name:und_x_variant":[
        "Shi\u2019ao",
        "\u77f3\u5787"
    ],
    "wof:name":"Shi'ao",
    "wof:placetype":"locality"
},
  "geometry": {"coordinates":[115.50727999999999,26.47344],"type":"Point"}
}