{
  "type": "Feature",
  "properties": {
    "gn:admin1_code":"2.0",
    "gn:asciiname":"Kukeng",
    "gn:country_code":"CN",
    "gn:dem":469,
    "gn:feature_class":"P",
    "gn:feature_code":"PPL",
    "gn:name":"Kukeng",
    "gn:population":0,
    "gn:timezone":"Asia/Shanghai",
    "iso:country":"CN",
    "name:zho_x_preferred":[
        "\u5e93\u5751"
    ],
    "wof:name":"Kukeng",
    "wof:placetype":"locality"
},
  "geometry": {"coordinates":[118.19835999999999,29.31599000000001],"type":"Point"}
}