{
  "type": "Feature",
  "properties": {
    "gn:admin1_code":"19.0",
    "gn:asciiname":"Dongjiagoucun",
    "gn:country_code":"CN",
    "gn:dem":592,
    "gn:feature_class":"P",
    "gn:feature_code":"PPL",
    "gn:name":"Dongjiagoucun",
    "gn:population":0,
    "gn:timezone":"Asia/Shanghai",
    "iso:country":"CN",
    "name:zho_x_preferred":[
        "\u8463\u5bb6\u6c9f\u6751"
    ],
    "wof:name":"Dongjiagoucun",
    "wof:placetype":"locality"
},
  "geometry": {"coordinates":[119.36199999999999,41.9108],"type":"Point"}
}