{
  "type": "Feature",
  "properties": {
    "gn:admin1_code":"19.0",
    "gn:asciiname":"Sanduntaicun",
    "gn:country_code":"CN",
    "gn:dem":56,
    "gn:feature_class":"P",
    "gn:feature_code":"PPL",
    "gn:name":"Sanduntaicun",
    "gn:population":0,
    "gn:timezone":"Asia/Shanghai",
    "iso:country":"CN",
    "name:zho_x_preferred":[
        "\u4e09\u58a9\u53f0\u6751"
    ],
    "wof:name":"Sanduntaicun",
    "wof:placetype":"locality"
},
  "geometry": {"coordinates":[121.76412000000001,39.78567],"type":"Point"}
}