{
  "type": "Feature",
  "properties": {
    "gn:admin1_code":"18.0",
    "gn:asciiname":"Tangbianpo",
    "gn:country_code":"CN",
    "gn:dem":437,
    "gn:feature_class":"P",
    "gn:feature_code":"PPL",
    "gn:name":"Tangbianpo",
    "gn:population":0,
    "gn:timezone":"Asia/Shanghai",
    "iso:country":"CN",
    "name:zho_x_preferred":[
        "\u5858\u8fb9\u5761"
    ],
    "wof:name":"Tangbianpo",
    "wof:placetype":"locality"
},
  "geometry": {"coordinates":[109.08199999999999,27.7122],"type":"Point"}
}