{
  "type": "Feature",
  "properties": {
    "gn:admin1_code":"5.0",
    "gn:asciiname":"Longwangmiaocun",
    "gn:country_code":"CN",
    "gn:dem":355,
    "gn:feature_class":"P",
    "gn:feature_code":"PPL",
    "gn:name":"Longwangmiaocun",
    "gn:population":0,
    "gn:timezone":"Asia/Shanghai",
    "iso:country":"CN",
    "name:zho_x_preferred":[
        "\u9f99\u738b\u5e99\u6751"
    ],
    "wof:name":"Longwangmiaocun",
    "wof:placetype":"locality"
},
  "geometry": {"coordinates":[126.37957,42.9898],"type":"Point"}
}