{
  "type": "Feature",
  "properties": {
    "gn:admin1_code":"3",
    "gn:asciiname":"Penggengzi",
    "gn:country_code":"CN",
    "gn:dem":543,
    "gn:feature_class":"P",
    "gn:feature_code":"PPL",
    "gn:name":"Penggengzi",
    "gn:population":0,
    "gn:timezone":"Asia/Shanghai",
    "iso:country":"CN",
    "name:zho_x_preferred":[
        "\u68da\u57c2\u5b50"
    ],
    "wof:name":"Penggengzi",
    "wof:placetype":"locality"
},
  "geometry": {"coordinates":[114.172,25.9655],"type":"Point"}
}