{
  "type": "Feature",
  "properties": {
    "gn:admin1_code":"4.0",
    "gn:asciiname":"Xidawucun",
    "gn:country_code":"CN",
    "gn:dem":26,
    "gn:feature_class":"P",
    "gn:feature_code":"PPL",
    "gn:name":"Xidawucun",
    "gn:population":0,
    "gn:timezone":"Asia/Shanghai",
    "iso:country":"CN",
    "name:zho_x_preferred":[
        "\u897f\u5927\u5434\u6751"
    ],
    "wof:name":"Xidawucun",
    "wof:placetype":"locality"
},
  "geometry": {"coordinates":[117.39569,34.34552],"type":"Point"}
}