{
  "type": "Feature",
  "properties": {
    "gn:admin1_code":"12.0",
    "gn:asciiname":"Xiejiawan",
    "gn:country_code":"CN",
    "gn:dem":30,
    "gn:feature_class":"P",
    "gn:feature_code":"PPL",
    "gn:name":"Xiejiawan",
    "gn:population":0,
    "gn:timezone":"Asia/Shanghai",
    "iso:country":"CN",
    "name:zho_x_preferred":[
        "\u8c22\u5bb6\u6e7e"
    ],
    "wof:name":"Xiejiawan",
    "wof:placetype":"locality"
},
  "geometry": {"coordinates":[113.02301,30.15647],"type":"Point"}
}