{
  "type": "Feature",
  "properties": {
    "gn:admin1_code":"15.0",
    "gn:asciiname":"Fanjiagou",
    "gn:country_code":"CN",
    "gn:dem":1483,
    "gn:feature_class":"P",
    "gn:feature_code":"PPL",
    "gn:name":"Fanjiagou",
    "gn:population":0,
    "gn:timezone":"Asia/Shanghai",
    "iso:country":"CN",
    "name:zho_x_preferred":[
        "\u6a0a\u5bb6\u6c9f"
    ],
    "wof:name":"Fanjiagou",
    "wof:placetype":"locality"
},
  "geometry": {"coordinates":[98.4652,39.7634],"type":"Point"}
}