{
  "type": "Feature",
  "properties": {
    "gn:admin1_code":"26.0",
    "gn:asciiname":"Zhangshancun",
    "gn:country_code":"CN",
    "gn:dem":1850,
    "gn:feature_class":"P",
    "gn:feature_code":"PPL",
    "gn:name":"Zhangshancun",
    "gn:population":0,
    "gn:timezone":"Asia/Shanghai",
    "iso:country":"CN",
    "name:zho_x_preferred":[
        "\u5f20\u5c71\u6751"
    ],
    "wof:name":"Zhangshancun",
    "wof:placetype":"locality"
},
  "geometry": {"coordinates":[107.50077,37.35791],"type":"Point"}
}