{
  "type": "Feature",
  "properties": {
    "gn:admin1_code":"8.0",
    "gn:asciiname":"Xufutun",
    "gn:country_code":"CN",
    "gn:dem":131,
    "gn:feature_class":"P",
    "gn:feature_code":"PPL",
    "gn:name":"Xufutun",
    "gn:population":0,
    "gn:timezone":"Asia/Shanghai",
    "iso:country":"CN",
    "name:zho_x_preferred":[
        "\u5f90\u798f\u5c6f"
    ],
    "wof:name":"Xufutun",
    "wof:placetype":"locality"
},
  "geometry": {"coordinates":[128.63371999999998,45.82271],"type":"Point"}
}