{
  "type": "Feature",
  "properties": {
    "gn:admin1_code":"30.0",
    "gn:asciiname":"Tangpucun",
    "gn:country_code":"CN",
    "gn:dem":6,
    "gn:feature_class":"P",
    "gn:feature_code":"PPL",
    "gn:name":"Tangpucun",
    "gn:population":0,
    "gn:timezone":"Asia/Shanghai",
    "iso:country":"CN",
    "name:zho_x_preferred":[
        "\u5858\u57d4\u6751"
    ],
    "wof:name":"Tangpucun",
    "wof:placetype":"locality"
},
  "geometry": {"coordinates":[116.44529,23.52379],"type":"Point"}
}