{
  "type": "Feature",
  "properties": {
    "gn:admin1_code":"11",
    "gn:asciiname":"Shiqishi",
    "gn:cc2":"CN",
    "gn:country_code":"CN",
    "gn:dem":120,
    "gn:feature_class":"P",
    "gn:feature_code":"PPL",
    "gn:name":"Shiqishi",
    "gn:population":0,
    "gn:timezone":"Asia/Shanghai",
    "iso:country":"CN",
    "name:und_x_variant":[
        "Shih-ch\u2019i-sh\u2019ih",
        "Shih-ch\u2019i-chan",
        "Shih-ch\u2019i",
        "Shiqishi"
    ],
    "wof:name":"Shiqishi",
    "wof:placetype":"locality"
},
  "geometry": {"coordinates":[111.43361000000002,26.27528],"type":"Point"}
}