{
  "type": "Feature",
  "properties": {
    "gn:admin1_code":"1.0",
    "gn:asciiname":"Hetangcun",
    "gn:country_code":"CN",
    "gn:dem":219,
    "gn:feature_class":"P",
    "gn:feature_code":"PPL",
    "gn:name":"Hetangcun",
    "gn:population":0,
    "gn:timezone":"Asia/Shanghai",
    "iso:country":"CN",
    "name:zho_x_preferred":[
        "\u9e64\u5858\u6751"
    ],
    "wof:name":"Hetangcun",
    "wof:placetype":"locality"
},
  "geometry": {"coordinates":[115.68411999999999,31.64387],"type":"Point"}
}