{
  "type": "Feature",
  "properties": {
    "gn:admin1_code":"10",
    "gn:asciiname":"Mazhangzicun",
    "gn:country_code":"CN",
    "gn:dem":301,
    "gn:feature_class":"P",
    "gn:feature_code":"PPL",
    "gn:name":"Mazhangzicun",
    "gn:population":0,
    "gn:timezone":"Asia/Shanghai",
    "iso:country":"CN",
    "name:zho_x_preferred":[
        "\u9a6c\u6756\u5b50\u6751"
    ],
    "wof:name":"Mazhangzicun",
    "wof:placetype":"locality"
},
  "geometry": {"coordinates":[118.95728,40.37773],"type":"Point"}
}