{
  "type": "Feature",
  "properties": {
    "gn:admin1_code":"15.0",
    "gn:asciiname":"Hongyaping",
    "gn:country_code":"CN",
    "gn:dem":1281,
    "gn:feature_class":"P",
    "gn:feature_code":"PPL",
    "gn:name":"Hongyaping",
    "gn:population":0,
    "gn:timezone":"Asia/Shanghai",
    "iso:country":"CN",
    "name:und_x_variant":[
        "\u7ea2\u5d16\u576a"
    ],
    "wof:name":"Hongyaping",
    "wof:placetype":"locality"
},
  "geometry": {"coordinates":[106.40206999999999,33.86955],"type":"Point"}
}