{
  "type": "Feature",
  "properties": {
    "gn:admin1_code":"29.0",
    "gn:asciiname":"Zhujiazhai",
    "gn:country_code":"CN",
    "gn:dem":1807,
    "gn:feature_class":"P",
    "gn:feature_code":"PPL",
    "gn:name":"Zhujiazhai",
    "gn:population":0,
    "gn:timezone":"Asia/Shanghai",
    "iso:country":"CN",
    "name:zho_x_preferred":[
        "\u795d\u5bb6\u5be8"
    ],
    "wof:name":"Zhujiazhai",
    "wof:placetype":"locality"
},
  "geometry": {"coordinates":[101.509,23.9095],"type":"Point"}
}