{
  "type": "Feature",
  "properties": {
    "gn:admin1_code":"10.0",
    "gn:asciiname":"Changzuizi",
    "gn:country_code":"CN",
    "gn:dem":1450,
    "gn:feature_class":"P",
    "gn:feature_code":"PPL",
    "gn:name":"Changzuizi",
    "gn:population":0,
    "gn:timezone":"Asia/Shanghai",
    "iso:country":"CN",
    "name:zho_x_preferred":[
        "\u5e38\u5634\u5b50"
    ],
    "wof:name":"Changzuizi",
    "wof:placetype":"locality"
},
  "geometry": {"coordinates":[114.79796,39.77524],"type":"Point"}
}