{
  "type": "Feature",
  "properties": {
    "gn:admin1_code":"7.0",
    "gn:asciiname":"Henglongkeng",
    "gn:country_code":"CN",
    "gn:dem":403,
    "gn:feature_class":"P",
    "gn:feature_code":"PPL",
    "gn:name":"Henglongkeng",
    "gn:population":0,
    "gn:timezone":"Asia/Shanghai",
    "iso:country":"CN",
    "name:zho_x_preferred":[
        "\u6a2a\u9f99\u5751"
    ],
    "wof:name":"Henglongkeng",
    "wof:placetype":"locality"
},
  "geometry": {"coordinates":[119.8039,27.16585],"type":"Point"}
}