{
  "type": "Feature",
  "properties": {
    "gn:admin1_code":"1.0",
    "gn:asciiname":"Pushucun",
    "gn:country_code":"CN",
    "gn:dem":47,
    "gn:feature_class":"P",
    "gn:feature_code":"PPL",
    "gn:name":"Pushucun",
    "gn:population":0,
    "gn:timezone":"Asia/Shanghai",
    "iso:country":"CN",
    "name:zho_x_preferred":[
        "\u6734\u6811\u6751"
    ],
    "wof:name":"Pushucun",
    "wof:placetype":"locality"
},
  "geometry": {"coordinates":[117.32503,30.90092000000001],"type":"Point"}
}