{
  "type": "Feature",
  "properties": {
    "gn:admin1_code":"21",
    "gn:asciiname":"Shangzhoujia Hewan",
    "gn:country_code":"CN",
    "gn:dem":1316,
    "gn:feature_class":"P",
    "gn:feature_code":"PPL",
    "gn:name":"Shangzhoujia Hewan",
    "gn:population":0,
    "gn:timezone":"Asia/Shanghai",
    "iso:country":"CN",
    "name:und_x_variant":[
        "Xiazhoujia Hewan"
    ],
    "name:zho_x_preferred":[
        "\u4e0a\u5468\u5bb6\u6cb3\u6e7e"
    ],
    "wof:name":"Shangzhoujia Hewan",
    "wof:placetype":"locality"
},
  "geometry": {"coordinates":[105.85897,37.08275],"type":"Point"}
}