{
  "type": "Feature",
  "properties": {
    "gn:admin1_code":"30",
    "gn:asciiname":"Wulizai",
    "gn:country_code":"CN",
    "gn:dem":44,
    "gn:feature_class":"P",
    "gn:feature_code":"PPL",
    "gn:name":"Wulizai",
    "gn:population":0,
    "gn:timezone":"Asia/Urumqi",
    "iso:country":"CN",
    "name:zho_x_preferred":[
        "\u4e94\u91cc\u4ed4"
    ],
    "wof:name":"Wulizai",
    "wof:placetype":"locality"
},
  "geometry": {"coordinates":[110.19632,21.18408],"type":"Point"}
}