{
  "type": "Feature",
  "properties": {
    "gn:admin1_code":"25",
    "gn:asciiname":"Yangzao",
    "gn:country_code":"CN",
    "gn:dem":39,
    "gn:feature_class":"P",
    "gn:feature_code":"PPL",
    "gn:name":"Yangzao",
    "gn:population":0,
    "gn:timezone":"Asia/Shanghai",
    "iso:country":"CN",
    "name:zho_x_preferred":[
        "\u6768\u65e9"
    ],
    "wof:name":"Yangzao",
    "wof:placetype":"locality"
},
  "geometry": {"coordinates":[116.301,35.1275],"type":"Point"}
}