{
  "type": "Feature",
  "properties": {
    "gn:admin1_code":"11.0",
    "gn:asciiname":"Baizhangzhai",
    "gn:country_code":"CN",
    "gn:dem":418,
    "gn:feature_class":"P",
    "gn:feature_code":"PPL",
    "gn:name":"Baizhangzhai",
    "gn:population":0,
    "gn:timezone":"Asia/Shanghai",
    "iso:country":"CN",
    "name:zho_x_preferred":[
        "\u767e\u4e08\u5be8"
    ],
    "wof:name":"Baizhangzhai",
    "wof:placetype":"locality"
},
  "geometry": {"coordinates":[113.89861999999999,26.50825],"type":"Point"}
}