{
  "type": "Feature",
  "properties": {
    "gn:admin1_code":"12",
    "gn:asciiname":"Huandiqiao",
    "gn:country_code":"CN",
    "gn:dem":36,
    "gn:feature_class":"P",
    "gn:feature_code":"PPLA4",
    "gn:name":"Huandiqiao",
    "gn:population":0,
    "gn:timezone":"Asia/Shanghai",
    "iso:country":"CN",
    "name:und_x_variant":[
        "\u8fd8\u5730\u6865",
        "Huandiqiao Jiedao",
        "\u8fd8\u5730\u6865\u8857\u9053"
    ],
    "wof:name":"Huandiqiao",
    "wof:placetype":"locality"
},
  "geometry": {"coordinates":[114.82338,30.20945],"type":"Point"}
}