{
  "type": "Feature",
  "properties": {
    "gn:admin1_code":"32.0",
    "gn:asciiname":"Lengzhulin",
    "gn:country_code":"CN",
    "gn:dem":1214,
    "gn:feature_class":"P",
    "gn:feature_code":"PPL",
    "gn:name":"Lengzhulin",
    "gn:population":0,
    "gn:timezone":"Asia/Shanghai",
    "iso:country":"CN",
    "name:zho_x_preferred":[
        "\u51b7\u7af9\u6797"
    ],
    "wof:name":"Lengzhulin",
    "wof:placetype":"locality"
},
  "geometry": {"coordinates":[103.34999999999999,29.6341],"type":"Point"}
}