{
  "type": "Feature",
  "properties": {
    "gn:admin1_code":"10",
    "gn:asciiname":"Xinliuzuo",
    "gn:country_code":"CN",
    "gn:dem":15,
    "gn:feature_class":"P",
    "gn:feature_code":"PPL",
    "gn:name":"Xinliuzuo",
    "gn:population":0,
    "gn:timezone":"Asia/Shanghai",
    "iso:country":"CN",
    "name:zho_x_preferred":[
        "\u8f9b\u7559\u4f50"
    ],
    "wof:name":"Xinliuzuo",
    "wof:placetype":"locality"
},
  "geometry": {"coordinates":[115.65900000000001,38.6907],"type":"Point"}
}