{
  "type": "Feature",
  "properties": {
    "gn:admin1_code":"19.0",
    "gn:asciiname":"Xiamayingzi",
    "gn:country_code":"CN",
    "gn:dem":464,
    "gn:feature_class":"P",
    "gn:feature_code":"PPL",
    "gn:name":"Xiamayingzi",
    "gn:population":0,
    "gn:timezone":"Asia/Shanghai",
    "iso:country":"CN",
    "name:zho_x_preferred":[
        "\u4e0b\u9a6c\u8425\u5b50"
    ],
    "wof:name":"Xiamayingzi",
    "wof:placetype":"locality"
},
  "geometry": {"coordinates":[119.40900000000001,41.0352],"type":"Point"}
}