{
  "type": "Feature",
  "properties": {
    "gn:admin1_code":"16.0",
    "gn:asciiname":"Liu'anping",
    "gn:country_code":"CN",
    "gn:dem":235,
    "gn:feature_class":"P",
    "gn:feature_code":"PPL",
    "gn:name":"Liu\u2019anping",
    "gn:population":0,
    "gn:timezone":"Asia/Shanghai",
    "iso:country":"CN",
    "name:und_x_variant":[
        "Liu\u2019anping"
    ],
    "name:zho_x_preferred":[
        "\u516d\u5b89\u5e73"
    ],
    "wof:name":"Liu'anping",
    "wof:placetype":"locality"
},
  "geometry": {"coordinates":[110.343,23.7645],"type":"Point"}
}