{
  "type": "Feature",
  "properties": {
    "gn:admin1_code":"25",
    "gn:asciiname":"Tanqingwan",
    "gn:country_code":"CN",
    "gn:dem":118,
    "gn:feature_class":"P",
    "gn:feature_code":"PPL",
    "gn:name":"Tanqingwan",
    "gn:population":0,
    "gn:timezone":"Asia/Shanghai",
    "iso:country":"CN",
    "name:zho_x_preferred":[
        "\u6ee9\u6e05\u6e7e"
    ],
    "wof:name":"Tanqingwan",
    "wof:placetype":"locality"
},
  "geometry": {"coordinates":[117.032,36.0856],"type":"Point"}
}