{
  "type": "Feature",
  "properties": {
    "gn:admin1_code":"16",
    "gn:asciiname":"Lumingcun",
    "gn:country_code":"CN",
    "gn:dem":406,
    "gn:feature_class":"P",
    "gn:feature_code":"PPL",
    "gn:name":"Lumingcun",
    "gn:population":0,
    "gn:timezone":"Asia/Shanghai",
    "iso:country":"CN",
    "wof:name":"Lumingcun",
    "wof:placetype":"locality"
},
  "geometry": {"coordinates":[111.01555999999999,26.25806],"type":"Point"}
}