{
  "type": "Feature",
  "properties": {
    "gn:admin1_code":"26.0",
    "gn:asciiname":"Mengjiawan",
    "gn:country_code":"CN",
    "gn:dem":1417,
    "gn:feature_class":"P",
    "gn:feature_code":"PPL",
    "gn:name":"Mengjiawan",
    "gn:population":0,
    "gn:timezone":"Asia/Shanghai",
    "iso:country":"CN",
    "name:zho_x_preferred":[
        "\u5b5f\u5bb6\u6e7e"
    ],
    "wof:name":"Mengjiawan",
    "wof:placetype":"locality"
},
  "geometry": {"coordinates":[108.88939000000001,36.53687],"type":"Point"}
}