{
  "type": "Feature",
  "properties": {
    "gn:admin1_code":"32.0",
    "gn:asciiname":"Ganbantian",
    "gn:country_code":"CN",
    "gn:dem":1083,
    "gn:feature_class":"P",
    "gn:feature_code":"PPL",
    "gn:name":"Ganbantian",
    "gn:population":0,
    "gn:timezone":"Asia/Shanghai",
    "iso:country":"CN",
    "name:zho_x_preferred":[
        "\u5e72\u677f\u7530"
    ],
    "wof:name":"Ganbantian",
    "wof:placetype":"locality"
},
  "geometry": {"coordinates":[104.752,32.4178],"type":"Point"}
}