{
  "type": "Feature",
  "properties": {
    "gn:admin1_code":"24",
    "gn:asciiname":"Duanjiabu",
    "gn:cc2":"CN",
    "gn:country_code":"CN",
    "gn:dem":1345,
    "gn:feature_class":"P",
    "gn:feature_code":"PPL",
    "gn:name":"Duanjiabu",
    "gn:population":0,
    "gn:timezone":"Asia/Shanghai",
    "iso:country":"CN",
    "name:und_x_variant":[
        "Tuan-chia-pao",
        "Duanjiabu",
        "\u6bb5\u5bb6\u5821",
        "Duanjiabu Xiang",
        "\u6bb5\u5bb6\u5821\u4e61"
    ],
    "wof:name":"Duanjiabu",
    "wof:placetype":"locality"
},
  "geometry": {"coordinates":[112.51416999999999,38.985],"type":"Point"}
}