{
  "type": "Feature",
  "properties": {
    "gn:admin1_code":"22.0",
    "gn:asciiname":"Hongjunzhuangcun",
    "gn:country_code":"CN",
    "gn:dem":68,
    "gn:feature_class":"P",
    "gn:feature_code":"PPL",
    "gn:name":"Hongjunzhuangcun",
    "gn:population":0,
    "gn:timezone":"Asia/Shanghai",
    "iso:country":"CN",
    "name:zho_x_preferred":[
        "\u7ea2\u519b\u5e84\u6751"
    ],
    "wof:name":"Hongjunzhuangcun",
    "wof:placetype":"locality"
},
  "geometry": {"coordinates":[116.58167,40.34428],"type":"Point"}
}