{
  "type": "Feature",
  "properties": {
    "gn:admin1_code":"32.0",
    "gn:asciiname":"Dasonglin",
    "gn:country_code":"CN",
    "gn:dem":840,
    "gn:feature_class":"P",
    "gn:feature_code":"PPL",
    "gn:name":"Dasonglin",
    "gn:population":0,
    "gn:timezone":"Asia/Shanghai",
    "iso:country":"CN",
    "name:zho_x_preferred":[
        "\u5927\u677e\u6797"
    ],
    "wof:name":"Dasonglin",
    "wof:placetype":"locality"
},
  "geometry": {"coordinates":[107.54214,31.91525],"type":"Point"}
}