{
  "type": "Feature",
  "properties": {
    "gn:admin1_code":"26.0",
    "gn:asciiname":"Yang'ergou",
    "gn:country_code":"CN",
    "gn:dem":1168,
    "gn:feature_class":"P",
    "gn:feature_code":"PPL",
    "gn:name":"Yang\u2019ergou",
    "gn:population":0,
    "gn:timezone":"Asia/Shanghai",
    "iso:country":"CN",
    "name:und_x_variant":[
        "Yang\u2019ergou"
    ],
    "name:zho_x_preferred":[
        "\u7f8a\u8033\u6c9f"
    ],
    "wof:name":"Yang'ergou",
    "wof:placetype":"locality"
},
  "geometry": {"coordinates":[109.31965,33.53311],"type":"Point"}
}