{
  "type": "Feature",
  "properties": {
    "gn:admin1_code":"11",
    "gn:asciiname":"Zongguanmiao",
    "gn:country_code":"CN",
    "gn:dem":296,
    "gn:feature_class":"P",
    "gn:feature_code":"PPL",
    "gn:name":"Zongguanmiao",
    "gn:population":0,
    "gn:timezone":"Asia/Shanghai",
    "iso:country":"CN",
    "name:zho_x_preferred":[
        "\u603b\u7ba1\u5e99"
    ],
    "wof:name":"Zongguanmiao",
    "wof:placetype":"locality"
},
  "geometry": {"coordinates":[112.15478,25.46441],"type":"Point"}
}