{
  "type": "Feature",
  "properties": {
    "gn:admin1_code":"9.0",
    "gn:asciiname":"Tiejianglu",
    "gn:country_code":"CN",
    "gn:dem":220,
    "gn:feature_class":"P",
    "gn:feature_code":"PPL",
    "gn:name":"Tiejianglu",
    "gn:population":0,
    "gn:timezone":"Asia/Shanghai",
    "iso:country":"CN",
    "name:zho_x_preferred":[
        "\u94c1\u5320\u7089"
    ],
    "wof:name":"Tiejianglu",
    "wof:placetype":"locality"
},
  "geometry": {"coordinates":[112.36302999999999,33.41949],"type":"Point"}
}