{
  "type": "Feature",
  "properties": {
    "gn:admin1_code":"18.0",
    "gn:asciiname":"Houchangcun",
    "gn:country_code":"CN",
    "gn:dem":406,
    "gn:feature_class":"P",
    "gn:feature_code":"PPL",
    "gn:name":"Houchangcun",
    "gn:population":0,
    "gn:timezone":"Asia/Shanghai",
    "iso:country":"CN",
    "name:zho_x_preferred":[
        "\u7334\u573a\u6751"
    ],
    "wof:name":"Houchangcun",
    "wof:placetype":"locality"
},
  "geometry": {"coordinates":[107.84399999999999,25.9883],"type":"Point"}
}