{
  "type": "Feature",
  "properties": {
    "gn:admin1_code":"4.0",
    "gn:asciiname":"Yibei Qizu",
    "gn:country_code":"CN",
    "gn:dem":0,
    "gn:feature_class":"P",
    "gn:feature_code":"PPLF",
    "gn:name":"Yibei Qizu",
    "gn:population":0,
    "gn:timezone":"Asia/Shanghai",
    "iso:country":"CN",
    "name:zho_x_preferred":[
        "\u76ca\u5317\u4e03\u7ec4"
    ],
    "wof:name":"Yibei Qizu",
    "wof:placetype":"locality"
},
  "geometry": {"coordinates":[120.44199999999999,33.3109],"type":"Point"}
}