{
  "type": "Feature",
  "properties": {
    "gn:admin1_code":"14.0",
    "gn:asciiname":"Mokucun",
    "gn:country_code":"CN",
    "gn:dem":3944,
    "gn:feature_class":"P",
    "gn:feature_code":"PPL",
    "gn:name":"Mokucun",
    "gn:population":0,
    "gn:timezone":"Asia/Urumqi",
    "iso:country":"CN",
    "name:zho_x_preferred":[
        "\u83ab\u5e93\u6751"
    ],
    "wof:name":"Mokucun",
    "wof:placetype":"locality"
},
  "geometry": {"coordinates":[97.91146000000001,29.59865],"type":"Point"}
}