{
  "type": "Feature",
  "properties": {
    "gn:admin1_code":"4.0",
    "gn:asciiname":"Zhuzui",
    "gn:country_code":"CN",
    "gn:dem":2,
    "gn:feature_class":"P",
    "gn:feature_code":"PPL",
    "gn:name":"Zhuzui",
    "gn:population":0,
    "gn:timezone":"Asia/Shanghai",
    "iso:country":"CN",
    "name:zho_x_preferred":[
        "Zhuzui"
    ],
    "name:zho_x_variant":[
        "\u732a\u5634"
    ],
    "wof:name":"Zhuzui",
    "wof:placetype":"locality"
},
  "geometry": {"coordinates":[120.19289000000001,34.23695],"type":"Point"}
}