{
  "type": "Feature",
  "properties": {
    "gn:admin1_code":"24.0",
    "gn:asciiname":"Weijiagou",
    "gn:country_code":"CN",
    "gn:dem":1481,
    "gn:feature_class":"P",
    "gn:feature_code":"PPL",
    "gn:name":"Weijiagou",
    "gn:population":0,
    "gn:timezone":"Asia/Shanghai",
    "iso:country":"CN",
    "name:und_x_variant":[
        "\u9b4f\u5bb6\u6c9f"
    ],
    "wof:name":"Weijiagou",
    "wof:placetype":"locality"
},
  "geometry": {"coordinates":[112.79165999999999,39.76911],"type":"Point"}
}