{
  "type": "Feature",
  "properties": {
    "gn:admin1_code":"10.0",
    "gn:asciiname":"Shangliluo",
    "gn:country_code":"CN",
    "gn:dem":1610,
    "gn:feature_class":"P",
    "gn:feature_code":"PPL",
    "gn:name":"Shangliluo",
    "gn:population":0,
    "gn:timezone":"Asia/Shanghai",
    "iso:country":"CN",
    "name:zho_x_preferred":[
        "\u4e0a\u91cc\u7f57"
    ],
    "wof:name":"Shangliluo",
    "wof:placetype":"locality"
},
  "geometry": {"coordinates":[114.81318,39.64236],"type":"Point"}
}