{
  "type": "Feature",
  "properties": {
    "gn:admin1_code":"12.0",
    "gn:asciiname":"Paishang",
    "gn:country_code":"CN",
    "gn:dem":67,
    "gn:feature_class":"P",
    "gn:feature_code":"PPL",
    "gn:name":"Paishang",
    "gn:population":0,
    "gn:timezone":"Asia/Shanghai",
    "iso:country":"CN",
    "name:zho_x_preferred":[
        "Paishang"
    ],
    "name:zho_x_variant":[
        "\u6392\u4e0a"
    ],
    "wof:name":"Paishang",
    "wof:placetype":"locality"
},
  "geometry": {"coordinates":[114.02482999999999,29.49395],"type":"Point"}
}