{
  "type": "Feature",
  "properties": {
    "gn:admin1_code":"1.0",
    "gn:asciiname":"Long'ancun",
    "gn:country_code":"CN",
    "gn:dem":70,
    "gn:feature_class":"P",
    "gn:feature_code":"PPL",
    "gn:name":"Long\u2019ancun",
    "gn:population":0,
    "gn:timezone":"Asia/Shanghai",
    "iso:country":"CN",
    "name:und_x_variant":[
        "Long\u2019ancun"
    ],
    "name:zho_x_preferred":[
        "\u9f99\u5eb5\u6751"
    ],
    "wof:name":"Long'ancun",
    "wof:placetype":"locality"
},
  "geometry": {"coordinates":[117.47194,30.9595],"type":"Point"}
}