{
  "type": "Feature",
  "properties": {
    "gn:admin1_code":"11.0",
    "gn:asciiname":"Tianjiaya",
    "gn:country_code":"CN",
    "gn:dem":1059,
    "gn:feature_class":"P",
    "gn:feature_code":"PPL",
    "gn:name":"Tianjiaya",
    "gn:population":0,
    "gn:timezone":"Asia/Shanghai",
    "iso:country":"CN",
    "name:zho_x_preferred":[
        "\u7530\u5bb6\u57ad"
    ],
    "wof:name":"Tianjiaya",
    "wof:placetype":"locality"
},
  "geometry": {"coordinates":[109.70811999999999,29.49253],"type":"Point"}
}