{
  "type": "Feature",
  "properties": {
    "gn:admin1_code":"32.0",
    "gn:asciiname":"Bandengyan",
    "gn:country_code":"CN",
    "gn:dem":719,
    "gn:feature_class":"P",
    "gn:feature_code":"PPL",
    "gn:name":"Bandengyan",
    "gn:population":0,
    "gn:timezone":"Asia/Shanghai",
    "iso:country":"CN",
    "name:zho_x_preferred":[
        "\u677f\u51f3\u5ca9"
    ],
    "wof:name":"Bandengyan",
    "wof:placetype":"locality"
},
  "geometry": {"coordinates":[104.43232,28.31078],"type":"Point"}
}