{
  "type": "Feature",
  "properties": {
    "gn:admin1_code":"18",
    "gn:asciiname":"Gouliangba",
    "gn:country_code":"CN",
    "gn:dem":710,
    "gn:feature_class":"P",
    "gn:feature_code":"PPL",
    "gn:name":"Gouliangba",
    "gn:population":0,
    "gn:timezone":"Asia/Shanghai",
    "iso:country":"CN",
    "name:zho_x_preferred":[
        "\u6784\u6881\u575d"
    ],
    "wof:name":"Gouliangba",
    "wof:placetype":"locality"
},
  "geometry": {"coordinates":[107.396,28.3062],"type":"Point"}
}