{
  "type": "Feature",
  "properties": {
    "gn:admin1_code":"8.0",
    "gn:asciiname":"Guojia Shaoguo",
    "gn:country_code":"CN",
    "gn:dem":138,
    "gn:feature_class":"P",
    "gn:feature_code":"PPL",
    "gn:name":"Guojia Shaoguo",
    "gn:population":0,
    "gn:timezone":"Asia/Shanghai",
    "iso:country":"CN",
    "name:zho_x_preferred":[
        "\u90ed\u5bb6\u70e7\u9505"
    ],
    "wof:name":"Guojia Shaoguo",
    "wof:placetype":"locality"
},
  "geometry": {"coordinates":[126.56151,46.62051],"type":"Point"}
}