{
  "type": "Feature",
  "properties": {
    "gn:admin1_code":"16.0",
    "gn:asciiname":"Pengcha",
    "gn:country_code":"CN",
    "gn:dem":353,
    "gn:feature_class":"P",
    "gn:feature_code":"PPL",
    "gn:name":"Pengcha",
    "gn:population":0,
    "gn:timezone":"Asia/Shanghai",
    "iso:country":"CN",
    "name:zho_x_preferred":[
        "\u670b\u8336"
    ],
    "wof:name":"Pengcha",
    "wof:placetype":"locality"
},
  "geometry": {"coordinates":[109.10899999999999,24.275],"type":"Point"}
}