{
  "type": "Feature",
  "properties": {
    "gn:admin1_code":"32.0",
    "gn:asciiname":"Shatanzi",
    "gn:country_code":"CN",
    "gn:dem":375,
    "gn:feature_class":"P",
    "gn:feature_code":"PPL",
    "gn:name":"Shatanzi",
    "gn:population":0,
    "gn:timezone":"Asia/Shanghai",
    "iso:country":"CN",
    "name:zho_x_preferred":[
        "\u6c99\u6ee9\u5b50"
    ],
    "wof:name":"Shatanzi",
    "wof:placetype":"locality"
},
  "geometry": {"coordinates":[103.87538000000001,28.6993],"type":"Point"}
}