{
  "type": "Feature",
  "properties": {
    "gn:admin1_code":"10.0",
    "gn:asciiname":"Xianglingzi",
    "gn:country_code":"CN",
    "gn:dem":916,
    "gn:feature_class":"P",
    "gn:feature_code":"PPL",
    "gn:name":"Xianglingzi",
    "gn:population":0,
    "gn:timezone":"Asia/Shanghai",
    "iso:country":"CN",
    "name:zho_x_preferred":[
        "\u54cd\u5cad\u5b50"
    ],
    "wof:name":"Xianglingzi",
    "wof:placetype":"locality"
},
  "geometry": {"coordinates":[115.47213000000001,40.20266],"type":"Point"}
}