{
  "type": "Feature",
  "properties": {
    "gn:admin1_code":"13",
    "gn:asciiname":"Xilesayi",
    "gn:country_code":"CN",
    "gn:dem":1490,
    "gn:feature_class":"P",
    "gn:feature_code":"PPL",
    "gn:name":"Xilesayi",
    "gn:population":0,
    "gn:timezone":"Asia/Urumqi",
    "iso:country":"CN",
    "name:und_x_variant":[
        "\u5e0c\u52d2\u8428\u4f9d"
    ],
    "wof:name":"Xilesayi",
    "wof:placetype":"locality"
},
  "geometry": {"coordinates":[91.49039999999999,44.00764],"type":"Point"}
}