{
  "type": "Feature",
  "properties": {
    "gn:admin1_code":"29.0",
    "gn:asciiname":"Wanyaoshu",
    "gn:country_code":"CN",
    "gn:dem":1389,
    "gn:feature_class":"P",
    "gn:feature_code":"PPL",
    "gn:name":"Wanyaoshu",
    "gn:population":0,
    "gn:timezone":"Asia/Shanghai",
    "iso:country":"CN",
    "name:zho_x_preferred":[
        "\u5f2f\u8170\u6811"
    ],
    "wof:name":"Wanyaoshu",
    "wof:placetype":"locality"
},
  "geometry": {"coordinates":[101.533,26.4487],"type":"Point"}
}