{
  "type": "Feature",
  "properties": {
    "gn:admin1_code":"2.0",
    "gn:asciiname":"Zhanlingwu",
    "gn:country_code":"CN",
    "gn:dem":290,
    "gn:feature_class":"P",
    "gn:feature_code":"PPL",
    "gn:name":"Zhanlingwu",
    "gn:population":0,
    "gn:timezone":"Asia/Shanghai",
    "iso:country":"CN",
    "name:zho_x_preferred":[
        "\u5360\u5cad\u575e"
    ],
    "wof:name":"Zhanlingwu",
    "wof:placetype":"locality"
},
  "geometry": {"coordinates":[118.494,29.19915],"type":"Point"}
}