{
  "type": "Feature",
  "properties": {
    "gn:admin1_code":"02",
    "gn:asciiname":"Chu-k'ou-yang",
    "gn:country_code":"CN",
    "gn:dem":38,
    "gn:feature_class":"P",
    "gn:feature_code":"PPL",
    "gn:name":"Chu-k\u2019ou-yang",
    "gn:population":0,
    "gn:timezone":"Asia/Shanghai",
    "iso:country":"CN",
    "wof:name":"Chu-k'ou-yang",
    "wof:placetype":"locality"
},
  "geometry": {"coordinates":[121.44667,29.32472000000001],"type":"Point"}
}