{
  "type": "Feature",
  "properties": {
    "gn:admin1_code":"4.0",
    "gn:asciiname":"Zhenyoucun",
    "gn:country_code":"CN",
    "gn:dem":17,
    "gn:feature_class":"P",
    "gn:feature_code":"PPL",
    "gn:name":"Zhenyoucun",
    "gn:population":0,
    "gn:timezone":"Asia/Shanghai",
    "iso:country":"CN",
    "name:zho_x_preferred":[
        "\u632f\u53cb\u6751"
    ],
    "wof:name":"Zhenyoucun",
    "wof:placetype":"locality"
},
  "geometry": {"coordinates":[118.45287999999999,33.9353],"type":"Point"}
}