{
  "type": "Feature",
  "properties": {
    "gn:admin1_code":"26.0",
    "gn:asciiname":"Yayaopancun",
    "gn:country_code":"CN",
    "gn:dem":1088,
    "gn:feature_class":"P",
    "gn:feature_code":"PPL",
    "gn:name":"Yayaopancun",
    "gn:population":0,
    "gn:timezone":"Asia/Shanghai",
    "iso:country":"CN",
    "name:zho_x_preferred":[
        "\u5d16\u7a91\u7554\u6751"
    ],
    "wof:name":"Yayaopancun",
    "wof:placetype":"locality"
},
  "geometry": {"coordinates":[110.06262,38.10613],"type":"Point"}
}