{
  "type": "Feature",
  "properties": {
    "gn:admin1_code":"14.0",
    "gn:asciiname":"Keri",
    "gn:country_code":"CN",
    "gn:dem":4872,
    "gn:feature_class":"P",
    "gn:feature_code":"PPLF",
    "gn:name":"Keri",
    "gn:population":0,
    "gn:timezone":"Asia/Urumqi",
    "iso:country":"CN",
    "name:bod_x_preferred":[
        "K\u00earri"
    ],
    "name:zho_x_preferred":[
        "Keri"
    ],
    "name:zho_x_variant":[
        "\u514b\u65e5"
    ],
    "wof:name":"Keri",
    "wof:placetype":"locality"
},
  "geometry": {"coordinates":[98.80200000000001,30.702],"type":"Point"}
}