{
  "type": "Feature",
  "properties": {
    "gn:admin1_code":"23.0",
    "gn:asciiname":"Zhusifangquan",
    "gn:country_code":"CN",
    "gn:dem":8,
    "gn:feature_class":"P",
    "gn:feature_code":"PPL",
    "gn:name":"Zhusifangquan",
    "gn:population":0,
    "gn:timezone":"Asia/Shanghai",
    "iso:country":"CN",
    "name:zho_x_preferred":[
        "Zhusifangquan"
    ],
    "name:zho_x_variant":[
        "\u6731\u56db\u623f\u5708"
    ],
    "wof:name":"Zhusifangquan",
    "wof:placetype":"locality"
},
  "geometry": {"coordinates":[121.71187,31.08571],"type":"Point"}
}