{
  "type": "Feature",
  "properties": {
    "gn:admin1_code":"33.0",
    "gn:asciiname":"Wutong",
    "gn:country_code":"CN",
    "gn:dem":587,
    "gn:feature_class":"P",
    "gn:feature_code":"PPL",
    "gn:name":"Wutong",
    "gn:population":0,
    "gn:timezone":"Asia/Shanghai",
    "iso:country":"CN",
    "name:deu_x_preferred":[
        "Wutong"
    ],
    "name:zho_x_preferred":[
        "\u4e94\u540c"
    ],
    "wof:name":"Wutong",
    "wof:placetype":"locality"
},
  "geometry": {"coordinates":[108.75758,30.84246],"type":"Point"}
}