{
  "type": "Feature",
  "properties": {
    "gn:admin1_code":"21.0",
    "gn:asciiname":"Gaoxinzhuang",
    "gn:country_code":"CN",
    "gn:dem":1542,
    "gn:feature_class":"P",
    "gn:feature_code":"PPL",
    "gn:name":"Gaoxinzhuang",
    "gn:population":0,
    "gn:timezone":"Asia/Shanghai",
    "iso:country":"CN",
    "name:zho_x_preferred":[
        "\u9ad8\u65b0\u5e84"
    ],
    "wof:name":"Gaoxinzhuang",
    "wof:placetype":"locality"
},
  "geometry": {"coordinates":[106.93899999999999,37.1427],"type":"Point"}
}