{
  "type": "Feature",
  "properties": {
    "gn:admin1_code":"19.0",
    "gn:asciiname":"Zhongfantun",
    "gn:country_code":"CN",
    "gn:dem":26,
    "gn:feature_class":"P",
    "gn:feature_code":"PPL",
    "gn:name":"Zhongfantun",
    "gn:population":0,
    "gn:timezone":"Asia/Shanghai",
    "iso:country":"CN",
    "name:zho_x_preferred":[
        "\u4e2d\u8303\u5c6f"
    ],
    "wof:name":"Zhongfantun",
    "wof:placetype":"locality"
},
  "geometry": {"coordinates":[121.68600000000001,39.6082],"type":"Point"}
}