{
  "type": "Feature",
  "properties": {
    "gn:admin1_code":"29",
    "gn:asciiname":"Zanlahei",
    "gn:country_code":"CN",
    "gn:dem":1946,
    "gn:feature_class":"P",
    "gn:feature_code":"PPL",
    "gn:name":"Zanlahei",
    "gn:population":0,
    "gn:timezone":"Asia/Shanghai",
    "iso:country":"CN",
    "name:zho_x_preferred":[
        "\u54b1\u62c9\u9ed1"
    ],
    "wof:name":"Zanlahei",
    "wof:placetype":"locality"
},
  "geometry": {"coordinates":[102.071,24.367],"type":"Point"}
}