{
  "type": "Feature",
  "properties": {
    "gn:admin1_code":"21.0",
    "gn:asciiname":"Yayaomao",
    "gn:country_code":"CN",
    "gn:dem":1671,
    "gn:feature_class":"P",
    "gn:feature_code":"PPL",
    "gn:name":"Yayaomao",
    "gn:population":0,
    "gn:timezone":"Asia/Shanghai",
    "iso:country":"CN",
    "name:zho_x_preferred":[
        "\u5d16\u7a91\u5cc1"
    ],
    "wof:name":"Yayaomao",
    "wof:placetype":"locality"
},
  "geometry": {"coordinates":[107.08199999999999,37.2574],"type":"Point"}
}