{
  "type": "Feature",
  "properties": {
    "gn:admin1_code":"32.0",
    "gn:asciiname":"Laqituoka",
    "gn:country_code":"CN",
    "gn:dem":3247,
    "gn:feature_class":"P",
    "gn:feature_code":"PPL",
    "gn:name":"Laqituoka",
    "gn:population":0,
    "gn:timezone":"Asia/Shanghai",
    "iso:country":"CN",
    "name:zho_x_preferred":[
        "\u62c9\u5176\u6258\u5361"
    ],
    "wof:name":"Laqituoka",
    "wof:placetype":"locality"
},
  "geometry": {"coordinates":[101.053,29.9156],"type":"Point"}
}