{
  "type": "Feature",
  "properties": {
    "gn:admin1_code":"14.0",
    "gn:asciiname":"Gangmuchui",
    "gn:country_code":"CN",
    "gn:dem":3888,
    "gn:feature_class":"P",
    "gn:feature_code":"PPL",
    "gn:name":"Gangmuchui",
    "gn:population":0,
    "gn:timezone":"Asia/Urumqi",
    "iso:country":"CN",
    "name:zho_x_preferred":[
        "\u5c97\u6728\u5439"
    ],
    "wof:name":"Gangmuchui",
    "wof:placetype":"locality"
},
  "geometry": {"coordinates":[91.80059,29.07489],"type":"Point"}
}