{
  "type": "Feature",
  "properties": {
    "gn:admin1_code":"25",
    "gn:asciiname":"Dianzicun",
    "gn:country_code":"CN",
    "gn:dem":11,
    "gn:feature_class":"P",
    "gn:feature_code":"PPL",
    "gn:name":"Dianzicun",
    "gn:population":0,
    "gn:timezone":"Asia/Shanghai",
    "iso:country":"CN",
    "name:und_x_variant":[
        "Dianzi",
        "Dianzicun"
    ],
    "name:zho_x_preferred":[
        "\u5e97\u5b50"
    ],
    "name:zho_x_variant":[
        "\u5e97\u5b50\u6751"
    ],
    "wof:name":"Dianzicun",
    "wof:placetype":"locality"
},
  "geometry": {"coordinates":[118.21678,37.47154000000001],"type":"Point"}
}