{
  "type": "Feature",
  "properties": {
    "gn:admin1_code":"32.0",
    "gn:asciiname":"Guosi",
    "gn:country_code":"CN",
    "gn:dem":3335,
    "gn:feature_class":"P",
    "gn:feature_code":"PPL",
    "gn:name":"Guosi",
    "gn:population":0,
    "gn:timezone":"Asia/Shanghai",
    "iso:country":"CN",
    "name:zho_x_preferred":[
        "\u679c\u65af"
    ],
    "wof:name":"Guosi",
    "wof:placetype":"locality"
},
  "geometry": {"coordinates":[101.42344,32.14377],"type":"Point"}
}