{
  "type": "Feature",
  "properties": {
    "gn:admin1_code":"26.0",
    "gn:asciiname":"Yingtaoping",
    "gn:country_code":"CN",
    "gn:dem":865,
    "gn:feature_class":"P",
    "gn:feature_code":"PPL",
    "gn:name":"Yingtaoping",
    "gn:population":0,
    "gn:timezone":"Asia/Shanghai",
    "iso:country":"CN",
    "name:und_x_variant":[
        "\u6a31\u6843\u576a"
    ],
    "wof:name":"Yingtaoping",
    "wof:placetype":"locality"
},
  "geometry": {"coordinates":[105.95188,32.98697],"type":"Point"}
}