{
  "type": "Feature",
  "properties": {
    "gn:admin1_code":"13",
    "gn:asciiname":"Youkurisi",
    "gn:country_code":"CN",
    "gn:dem":1320,
    "gn:feature_class":"P",
    "gn:feature_code":"PPL",
    "gn:name":"Youkurisi",
    "gn:population":0,
    "gn:timezone":"Asia/Shanghai",
    "iso:country":"CN",
    "name:und_x_variant":[
        "\u5c24\u5e93\u65e5\u65af"
    ],
    "wof:name":"Youkurisi",
    "wof:placetype":"locality"
},
  "geometry": {"coordinates":[76.05201,39.50702],"type":"Point"}
}