{
  "type": "Feature",
  "properties": {
    "gn:admin1_code":"32.0",
    "gn:asciiname":"Lizigou",
    "gn:country_code":"CN",
    "gn:dem":408,
    "gn:feature_class":"P",
    "gn:feature_code":"PPL",
    "gn:name":"Lizigou",
    "gn:population":0,
    "gn:timezone":"Asia/Shanghai",
    "iso:country":"CN",
    "name:zho_x_preferred":[
        "\u674e\u5b50\u6c9f"
    ],
    "wof:name":"Lizigou",
    "wof:placetype":"locality"
},
  "geometry": {"coordinates":[104.979,30.0227],"type":"Point"}
}