{
  "type": "Feature",
  "properties": {
    "gn:admin1_code":"2.0",
    "gn:asciiname":"Hejiadai",
    "gn:country_code":"CN",
    "gn:dem":9,
    "gn:feature_class":"P",
    "gn:feature_code":"PPL",
    "gn:name":"Hejiadai",
    "gn:population":0,
    "gn:timezone":"Asia/Shanghai",
    "iso:country":"CN",
    "name:und_x_variant":[
        "\u4f55\u5bb6\u57ed"
    ],
    "wof:name":"Hejiadai",
    "wof:placetype":"locality"
},
  "geometry": {"coordinates":[120.43344,30.44338],"type":"Point"}
}