{
  "type": "Feature",
  "properties": {
    "gn:admin1_code":"7.0",
    "gn:asciiname":"Houlingxia",
    "gn:country_code":"CN",
    "gn:dem":225,
    "gn:feature_class":"P",
    "gn:feature_code":"PPL",
    "gn:name":"Houlingxia",
    "gn:population":0,
    "gn:timezone":"Asia/Shanghai",
    "iso:country":"CN",
    "name:und_x_variant":[
        "\u540e\u5cad\u4e0b"
    ],
    "name:zho_x_preferred":[
        "\u540e\u5cad\u4e0b"
    ],
    "wof:name":"Houlingxia",
    "wof:placetype":"locality"
},
  "geometry": {"coordinates":[118.23333999999998,26.32029],"type":"Point"}
}