{
  "type": "Feature",
  "properties": {
    "gn:admin1_code":"18",
    "gn:asciiname":"Songshujiao",
    "gn:country_code":"CN",
    "gn:dem":2512,
    "gn:feature_class":"P",
    "gn:feature_code":"PPL",
    "gn:name":"Songshujiao",
    "gn:population":0,
    "gn:timezone":"Asia/Shanghai",
    "iso:country":"CN",
    "name:zho_x_preferred":[
        "\u677e\u6811\u811a"
    ],
    "wof:name":"Songshujiao",
    "wof:placetype":"locality"
},
  "geometry": {"coordinates":[103.904,27.1539],"type":"Point"}
}