{
  "type": "Feature",
  "properties": {
    "gn:admin1_code":"30.0",
    "gn:asciiname":"Chali'ao",
    "gn:country_code":"CN",
    "gn:dem":655,
    "gn:feature_class":"P",
    "gn:feature_code":"PPL",
    "gn:name":"Chali\u2019ao",
    "gn:population":0,
    "gn:timezone":"Asia/Shanghai",
    "iso:country":"CN",
    "name:zho_x_preferred":[
        "Chali\u2019ao"
    ],
    "name:zho_x_variant":[
        "\u8336\u91cc\u5773"
    ],
    "wof:name":"Chali'ao",
    "wof:placetype":"locality"
},
  "geometry": {"coordinates":[113.235,25.22806],"type":"Point"}
}