{
  "type": "Feature",
  "properties": {
    "gn:admin1_code":"5.0",
    "gn:asciiname":"Dayao Wopeng",
    "gn:country_code":"CN",
    "gn:dem":134,
    "gn:feature_class":"P",
    "gn:feature_code":"PPL",
    "gn:name":"Dayao Wopeng",
    "gn:population":0,
    "gn:timezone":"Asia/Shanghai",
    "iso:country":"CN",
    "name:zho_x_preferred":[
        "\u5927\u8170\u7a9d\u68da"
    ],
    "wof:name":"Dayao Wopeng",
    "wof:placetype":"locality"
},
  "geometry": {"coordinates":[124.02370000000001,45.57494000000001],"type":"Point"}
}