{
  "type": "Feature",
  "properties": {
    "gn:admin1_code":"18.0",
    "gn:asciiname":"Qiangongping",
    "gn:country_code":"CN",
    "gn:dem":854,
    "gn:feature_class":"P",
    "gn:feature_code":"PPL",
    "gn:name":"Qiangongping",
    "gn:population":0,
    "gn:timezone":"Asia/Shanghai",
    "iso:country":"CN",
    "name:zho_x_preferred":[
        "\u5343\u5de5\u576a"
    ],
    "wof:name":"Qiangongping",
    "wof:placetype":"locality"
},
  "geometry": {"coordinates":[108.92400000000001,28.2105],"type":"Point"}
}