{
  "type": "Feature",
  "properties": {
    "gn:admin1_code":"15.0",
    "gn:asciiname":"Shaijing",
    "gn:country_code":"CN",
    "gn:dem":1588,
    "gn:feature_class":"P",
    "gn:feature_code":"PPLA4",
    "gn:name":"Shaijing",
    "gn:population":0,
    "gn:timezone":"Asia/Shanghai",
    "iso:country":"CN",
    "name:und_x_variant":[
        "\u6652\u7ecf"
    ],
    "wof:name":"Shaijing",
    "wof:placetype":"locality"
},
  "geometry": {"coordinates":[105.48885,33.98332],"type":"Point"}
}