{
  "type": "Feature",
  "properties": {
    "gn:admin1_code":"21.0",
    "gn:asciiname":"Gengjiawan",
    "gn:country_code":"CN",
    "gn:dem":1192,
    "gn:feature_class":"P",
    "gn:feature_code":"PPL",
    "gn:name":"Gengjiawan",
    "gn:population":0,
    "gn:timezone":"Asia/Shanghai",
    "iso:country":"CN",
    "name:zho_x_preferred":[
        "\u803f\u5bb6\u6e7e"
    ],
    "wof:name":"Gengjiawan",
    "wof:placetype":"locality"
},
  "geometry": {"coordinates":[105.71299999999999,37.4606],"type":"Point"}
}