{
  "type": "Feature",
  "properties": {
    "gn:admin1_code":"8.0",
    "gn:asciiname":"Xishidao Liangzi",
    "gn:country_code":"CN",
    "gn:dem":344,
    "gn:feature_class":"P",
    "gn:feature_code":"PPL",
    "gn:name":"Xishidao Liangzi",
    "gn:population":0,
    "gn:timezone":"Asia/Shanghai",
    "iso:country":"CN",
    "name:zho_x_preferred":[
        "\u897f\u5341\u9053\u6881\u5b50"
    ],
    "wof:name":"Xishidao Liangzi",
    "wof:placetype":"locality"
},
  "geometry": {"coordinates":[128.99265,44.30159],"type":"Point"}
}