{
  "type": "Feature",
  "properties": {
    "gn:admin1_code":"24.0",
    "gn:asciiname":"Beijiaotou",
    "gn:country_code":"CN",
    "gn:dem":923,
    "gn:feature_class":"P",
    "gn:feature_code":"PPL",
    "gn:name":"Beijiaotou",
    "gn:population":0,
    "gn:timezone":"Asia/Shanghai",
    "iso:country":"CN",
    "name:zho_x_preferred":[
        "\u5317\u89d2\u5934"
    ],
    "wof:name":"Beijiaotou",
    "wof:placetype":"locality"
},
  "geometry": {"coordinates":[110.63590000000001,35.91129],"type":"Point"}
}