{
  "type": "Feature",
  "properties": {
    "gn:admin1_code":"19.0",
    "gn:asciiname":"Dijiagou",
    "gn:country_code":"CN",
    "gn:dem":149,
    "gn:feature_class":"P",
    "gn:feature_code":"PPL",
    "gn:name":"Dijiagou",
    "gn:population":0,
    "gn:timezone":"Asia/Shanghai",
    "iso:country":"CN",
    "name:zho_x_preferred":[
        "\u5e95\u5bb6\u6c9f"
    ],
    "wof:name":"Dijiagou",
    "wof:placetype":"locality"
},
  "geometry": {"coordinates":[121.035,41.5049],"type":"Point"}
}