{
  "type": "Feature",
  "properties": {
    "gn:admin1_code":"30.0",
    "gn:asciiname":"Mashicun",
    "gn:country_code":"CN",
    "gn:dem":259,
    "gn:feature_class":"P",
    "gn:feature_code":"PPL",
    "gn:name":"Mashicun",
    "gn:population":0,
    "gn:timezone":"Asia/Shanghai",
    "iso:country":"CN",
    "name:zho_x_preferred":[
        "\u9a6c\u77f3\u6751"
    ],
    "wof:name":"Mashicun",
    "wof:placetype":"locality"
},
  "geometry": {"coordinates":[115.84014000000001,24.29212],"type":"Point"}
}