{
  "type": "Feature",
  "properties": {
    "gn:admin1_code":"29.0",
    "gn:asciiname":"Donggualin",
    "gn:country_code":"CN",
    "gn:dem":1534,
    "gn:feature_class":"P",
    "gn:feature_code":"PPL",
    "gn:name":"Donggualin",
    "gn:population":0,
    "gn:timezone":"Asia/Shanghai",
    "iso:country":"CN",
    "name:zho_x_preferred":[
        "\u4e1c\u74dc\u6797"
    ],
    "wof:name":"Donggualin",
    "wof:placetype":"locality"
},
  "geometry": {"coordinates":[104.521,22.8441],"type":"Point"}
}