{
  "type": "Feature",
  "properties": {
    "gn:admin1_code":"11.0",
    "gn:asciiname":"Guluoshan",
    "gn:country_code":"CN",
    "gn:dem":436,
    "gn:feature_class":"P",
    "gn:feature_code":"PPLA4",
    "gn:name":"Guluoshan",
    "gn:population":0,
    "gn:timezone":"Asia/Shanghai",
    "iso:country":"CN",
    "name:und_x_variant":[
        "Guluoshan Xiang",
        "Guluoshan"
    ],
    "name:zho_x_preferred":[
        "\u8c37\u7f57\u5c71"
    ],
    "name:zho_x_variant":[
        "\u8c37\u7f57\u5c71\u4e61"
    ],
    "wof:name":"Guluoshan",
    "wof:placetype":"locality"
},
  "geometry": {"coordinates":[110.19195999999999,29.58801],"type":"Point"}
}