{
  "type": "Feature",
  "properties": {
    "gn:admin1_code":"25",
    "gn:asciiname":"Fengtaishan",
    "gn:country_code":"CN",
    "gn:dem":37,
    "gn:feature_class":"P",
    "gn:feature_code":"PPL",
    "gn:name":"Fengtaishan",
    "gn:population":0,
    "gn:timezone":"Asia/Shanghai",
    "iso:country":"CN",
    "name:zho_x_preferred":[
        "\u51e4\u53f0\u5c71"
    ],
    "wof:name":"Fengtaishan",
    "wof:placetype":"locality"
},
  "geometry": {"coordinates":[121.23774,37.54949000000001],"type":"Point"}
}