{
  "type": "Feature",
  "properties": {
    "gn:admin1_code":"18",
    "gn:asciiname":"Shuitouzhai",
    "gn:country_code":"CN",
    "gn:dem":942,
    "gn:feature_class":"P",
    "gn:feature_code":"PPL",
    "gn:name":"Shuitouzhai",
    "gn:population":0,
    "gn:timezone":"Asia/Shanghai",
    "iso:country":"CN",
    "name:zho_x_preferred":[
        "\u6c34\u5934\u5be8"
    ],
    "wof:name":"Shuitouzhai",
    "wof:placetype":"locality"
},
  "geometry": {"coordinates":[106.09399999999999,26.809],"type":"Point"}
}