{
  "type": "Feature",
  "properties": {
    "gn:admin1_code":"18",
    "gn:asciiname":"Dazhanmatian",
    "gn:country_code":"CN",
    "gn:dem":1424,
    "gn:feature_class":"P",
    "gn:feature_code":"PPL",
    "gn:name":"Dazhanmatian",
    "gn:population":0,
    "gn:timezone":"Asia/Shanghai",
    "iso:country":"CN",
    "name:zho_x_preferred":[
        "\u5927\u5360\u9a6c\u7530"
    ],
    "wof:name":"Dazhanmatian",
    "wof:placetype":"locality"
},
  "geometry": {"coordinates":[105.544,25.5548],"type":"Point"}
}