{
  "type": "Feature",
  "properties": {
    "gn:admin1_code":"30.0",
    "gn:asciiname":"Kantoumian",
    "gn:country_code":"CN",
    "gn:dem":210,
    "gn:feature_class":"P",
    "gn:feature_code":"PPL",
    "gn:name":"Kantoumian",
    "gn:population":0,
    "gn:timezone":"Asia/Shanghai",
    "iso:country":"CN",
    "name:zho_x_preferred":[
        "\u574e\u5934\u9762"
    ],
    "wof:name":"Kantoumian",
    "wof:placetype":"locality"
},
  "geometry": {"coordinates":[113.06332999999999,23.97306],"type":"Point"}
}