{
  "type": "Feature",
  "properties": {
    "gn:admin1_code":"26.0",
    "gn:asciiname":"Zaomaocun",
    "gn:country_code":"CN",
    "gn:dem":902,
    "gn:feature_class":"P",
    "gn:feature_code":"PPL",
    "gn:name":"Zaomaocun",
    "gn:population":0,
    "gn:timezone":"Asia/Shanghai",
    "iso:country":"CN",
    "name:zho_x_preferred":[
        "\u67a3\u5cc1\u6751"
    ],
    "wof:name":"Zaomaocun",
    "wof:placetype":"locality"
},
  "geometry": {"coordinates":[110.33516000000002,37.35226],"type":"Point"}
}