{
  "type": "Feature",
  "properties": {
    "gn:admin1_code":"4.0",
    "gn:asciiname":"Chazi",
    "gn:country_code":"CN",
    "gn:dem":3,
    "gn:feature_class":"P",
    "gn:feature_code":"PPL",
    "gn:name":"Chazi",
    "gn:population":0,
    "gn:timezone":"Asia/Shanghai",
    "iso:country":"CN",
    "name:zho_x_preferred":[
        "Chazi"
    ],
    "name:zho_x_variant":[
        "\u5bdf\u5b57"
    ],
    "wof:name":"Chazi",
    "wof:placetype":"locality"
},
  "geometry": {"coordinates":[121.51672000000001,31.79693],"type":"Point"}
}