{
  "type": "Feature",
  "properties": {
    "gn:admin1_code":"12.0",
    "gn:asciiname":"Wangjia Caofang",
    "gn:country_code":"CN",
    "gn:dem":55,
    "gn:feature_class":"P",
    "gn:feature_code":"PPL",
    "gn:name":"Wangjia Caofang",
    "gn:population":0,
    "gn:timezone":"Asia/Shanghai",
    "iso:country":"CN",
    "name:zho_x_preferred":[
        "Wangjia Caofang"
    ],
    "name:zho_x_variant":[
        "\u738b\u5bb6\u69fd\u623f"
    ],
    "wof:name":"Wangjia Caofang",
    "wof:placetype":"locality"
},
  "geometry": {"coordinates":[111.85357,30.5498],"type":"Point"}
}