{
  "type": "Feature",
  "properties": {
    "gn:admin1_code":"10",
    "gn:asciiname":"Xichaoyang",
    "gn:country_code":"CN",
    "gn:dem":66,
    "gn:feature_class":"P",
    "gn:feature_code":"PPL",
    "gn:name":"Xichaoyang",
    "gn:population":0,
    "gn:timezone":"Asia/Shanghai",
    "iso:country":"CN",
    "name:zho_x_preferred":[
        "\u897f\u671d\u9633"
    ],
    "wof:name":"Xichaoyang",
    "wof:placetype":"locality"
},
  "geometry": {"coordinates":[115.05500000000001,38.841],"type":"Point"}
}