{
  "type": "Feature",
  "properties": {
    "gn:admin1_code":"24.0",
    "gn:asciiname":"Pingtou",
    "gn:country_code":"CN",
    "gn:dem":938,
    "gn:feature_class":"P",
    "gn:feature_code":"PPL",
    "gn:name":"Pingtou",
    "gn:population":0,
    "gn:timezone":"Asia/Shanghai",
    "iso:country":"CN",
    "name:zho_x_preferred":[
        "\u5e73\u5934"
    ],
    "wof:name":"Pingtou",
    "wof:placetype":"locality"
},
  "geometry": {"coordinates":[113.13109,35.72102],"type":"Point"}
}