{
  "type": "Feature",
  "properties": {
    "gn:admin1_code":"16",
    "gn:asciiname":"Kuangjia",
    "gn:country_code":"CN",
    "gn:dem":188,
    "gn:feature_class":"P",
    "gn:feature_code":"PPL",
    "gn:name":"Kuangjia",
    "gn:population":0,
    "gn:timezone":"Asia/Shanghai",
    "iso:country":"CN",
    "name:zho_x_preferred":[
        "\u65f7\u5bb6"
    ],
    "wof:name":"Kuangjia",
    "wof:placetype":"locality"
},
  "geometry": {"coordinates":[110.914,25.9329],"type":"Point"}
}