{
  "type": "Feature",
  "properties": {
    "gn:admin1_code":"7.0",
    "gn:asciiname":"Tongzikeng",
    "gn:country_code":"CN",
    "gn:dem":808,
    "gn:feature_class":"P",
    "gn:feature_code":"PPL",
    "gn:name":"Tongzikeng",
    "gn:population":0,
    "gn:timezone":"Asia/Shanghai",
    "iso:country":"CN",
    "name:zho_x_preferred":[
        "\u6850\u5b50\u5751"
    ],
    "wof:name":"Tongzikeng",
    "wof:placetype":"locality"
},
  "geometry": {"coordinates":[116.00773,25.32984],"type":"Point"}
}