{
  "type": "Feature",
  "properties": {
    "gn:admin1_code":"9.0",
    "gn:asciiname":"Longtanyan",
    "gn:country_code":"CN",
    "gn:dem":61,
    "gn:feature_class":"P",
    "gn:feature_code":"PPL",
    "gn:name":"Longtanyan",
    "gn:population":0,
    "gn:timezone":"Asia/Shanghai",
    "iso:country":"CN",
    "name:zho_x_preferred":[
        "\u9f99\u6f6d\u6cbf"
    ],
    "wof:name":"Longtanyan",
    "wof:placetype":"locality"
},
  "geometry": {"coordinates":[114.22139,33.11732],"type":"Point"}
}