{
  "type": "Feature",
  "properties": {
    "gn:admin1_code":"33.0",
    "gn:asciiname":"Toudao",
    "gn:country_code":"CN",
    "gn:dem":271,
    "gn:feature_class":"P",
    "gn:feature_code":"PPL",
    "gn:name":"Toudao",
    "gn:population":0,
    "gn:timezone":"Asia/Shanghai",
    "iso:country":"CN",
    "name:zho_x_preferred":[
        "\u5934\u9053"
    ],
    "wof:name":"Toudao",
    "wof:placetype":"locality"
},
  "geometry": {"coordinates":[105.96792000000001,30.16268],"type":"Point"}
}