{
  "type": "Feature",
  "properties": {
    "gn:admin1_code":"5.0",
    "gn:asciiname":"Xinfucun",
    "gn:country_code":"CN",
    "gn:dem":144,
    "gn:feature_class":"P",
    "gn:feature_code":"PPL",
    "gn:name":"Xinfucun",
    "gn:population":0,
    "gn:timezone":"Asia/Shanghai",
    "iso:country":"CN",
    "name:zho_x_preferred":[
        "\u65b0\u5bcc\u6751"
    ],
    "wof:name":"Xinfucun",
    "wof:placetype":"locality"
},
  "geometry": {"coordinates":[123.15961,44.86726],"type":"Point"}
}