{
  "type": "Feature",
  "properties": {
    "gn:admin1_code":"20.0",
    "gn:asciiname":"Yuejiajing",
    "gn:cc2":"CN",
    "gn:country_code":"CN",
    "gn:dem":1668,
    "gn:feature_class":"P",
    "gn:feature_code":"PPL",
    "gn:name":"Yuejiajing",
    "gn:population":0,
    "gn:timezone":"Asia/Shanghai",
    "iso:country":"CN",
    "name:und_x_variant":[
        "Y\u00fceh-chia-ching",
        "Yuejiajing"
    ],
    "wof:name":"Yuejiajing",
    "wof:placetype":"locality"
},
  "geometry": {"coordinates":[104.31667,37.58333],"type":"Point"}
}