{
  "type": "Feature",
  "properties": {
    "gn:admin1_code":"1.0",
    "gn:asciiname":"Sun'ancun",
    "gn:country_code":"CN",
    "gn:dem":29,
    "gn:feature_class":"P",
    "gn:feature_code":"PPL",
    "gn:name":"Sun\u2019ancun",
    "gn:population":0,
    "gn:timezone":"Asia/Shanghai",
    "iso:country":"CN",
    "name:und_x_variant":[
        "Sun\u2019ancun"
    ],
    "name:zho_x_preferred":[
        "\u5b59\u5eb5\u6751"
    ],
    "wof:name":"Sun'ancun",
    "wof:placetype":"locality"
},
  "geometry": {"coordinates":[117.21742999999999,33.82101],"type":"Point"}
}