{
  "type": "Feature",
  "properties": {
    "gn:admin1_code":"30.0",
    "gn:asciiname":"Hengxicun",
    "gn:country_code":"CN",
    "gn:dem":431,
    "gn:feature_class":"P",
    "gn:feature_code":"PPL",
    "gn:name":"Hengxicun",
    "gn:population":0,
    "gn:timezone":"Asia/Shanghai",
    "iso:country":"CN",
    "name:zho_x_preferred":[
        "\u6a2a\u6eaa\u6751"
    ],
    "wof:name":"Hengxicun",
    "wof:placetype":"locality"
},
  "geometry": {"coordinates":[116.83376,24.38722000000001],"type":"Point"}
}