{
  "type": "Feature",
  "properties": {
    "gn:admin1_code":"3.0",
    "gn:asciiname":"Tieshancun",
    "gn:country_code":"CN",
    "gn:dem":40,
    "gn:feature_class":"P",
    "gn:feature_code":"PPL",
    "gn:name":"Tieshancun",
    "gn:population":0,
    "gn:timezone":"Asia/Shanghai",
    "iso:country":"CN",
    "name:und_x_variant":[
        "\u94c1\u5c71\u6751"
    ],
    "wof:name":"Tieshancun",
    "wof:placetype":"locality"
},
  "geometry": {"coordinates":[116.97081,28.4049],"type":"Point"}
}