{
  "type": "Feature",
  "properties": {
    "gn:admin1_code":"4.0",
    "gn:asciiname":"Beitou'erfang",
    "gn:country_code":"CN",
    "gn:dem":8,
    "gn:feature_class":"P",
    "gn:feature_code":"PPL",
    "gn:name":"Beitou\u2019erfang",
    "gn:population":0,
    "gn:timezone":"Asia/Shanghai",
    "iso:country":"CN",
    "name:zho_x_preferred":[
        "Beitou\u2019erfang"
    ],
    "name:zho_x_variant":[
        "\u5317\u5934\u4e8c\u623f"
    ],
    "wof:name":"Beitou'erfang",
    "wof:placetype":"locality"
},
  "geometry": {"coordinates":[120.48737,31.58399],"type":"Point"}
}