{
  "type": "Feature",
  "properties": {
    "gn:admin1_code":"24.0",
    "gn:asciiname":"Xizhuang",
    "gn:country_code":"CN",
    "gn:dem":1010,
    "gn:feature_class":"P",
    "gn:feature_code":"PPL",
    "gn:name":"Xizhuang",
    "gn:population":0,
    "gn:timezone":"Asia/Shanghai",
    "iso:country":"CN",
    "name:und_x_variant":[
        "Ch\u00fc-chuang",
        "Hsi-chuang",
        "Xizhuang"
    ],
    "name:zho_x_preferred":[
        "\u897f\u5e84"
    ],
    "wof:name":"Xizhuang",
    "wof:placetype":"locality"
},
  "geometry": {"coordinates":[113.22047000000001,36.1563],"type":"Point"}
}