{
  "type": "Feature",
  "properties": {
    "gn:admin1_code":"20.0",
    "gn:asciiname":"Kundelin Bulege",
    "gn:country_code":"CN",
    "gn:dem":926,
    "gn:feature_class":"P",
    "gn:feature_code":"PPL",
    "gn:name":"Kundelin Bulege",
    "gn:population":0,
    "gn:timezone":"Asia/Shanghai",
    "iso:country":"CN",
    "name:zho_x_preferred":[
        "\u6606\u5fb7\u6797\u5e03\u52d2\u683c"
    ],
    "wof:name":"Kundelin Bulege",
    "wof:placetype":"locality"
},
  "geometry": {"coordinates":[101.12297,42.10848],"type":"Point"}
}