{
  "type": "Feature",
  "properties": {
    "gn:admin1_code":"25",
    "gn:asciiname":"Baiyi'an",
    "gn:country_code":"CN",
    "gn:dem":245,
    "gn:feature_class":"P",
    "gn:feature_code":"PPL",
    "gn:name":"Baiyi\u2019an",
    "gn:population":0,
    "gn:timezone":"Asia/Shanghai",
    "iso:country":"CN",
    "name:und_x_variant":[
        "Baiyi\u2019an"
    ],
    "name:zho_x_preferred":[
        "\u767d\u8863\u5b89"
    ],
    "wof:name":"Baiyi'an",
    "wof:placetype":"locality"
},
  "geometry": {"coordinates":[118.419,35.6765],"type":"Point"}
}