{
  "type": "Feature",
  "properties": {
    "gn:admin1_code":"25",
    "gn:asciiname":"Zhaogui",
    "gn:country_code":"CN",
    "gn:dem":42,
    "gn:feature_class":"P",
    "gn:feature_code":"PPL",
    "gn:name":"Zhaogui",
    "gn:population":0,
    "gn:timezone":"Asia/Shanghai",
    "iso:country":"CN",
    "name:zho_x_preferred":[
        "\u8d75\u6842"
    ],
    "wof:name":"Zhaogui",
    "wof:placetype":"locality"
},
  "geometry": {"coordinates":[115.65028999999998,36.48381],"type":"Point"}
}