{
  "type": "Feature",
  "properties": {
    "gn:admin1_code":"13.0",
    "gn:asciiname":"Erpu",
    "gn:cc2":"CN",
    "gn:country_code":"CN",
    "gn:dem":746,
    "gn:feature_class":"P",
    "gn:feature_code":"PPL",
    "gn:name":"Erpu",
    "gn:population":0,
    "gn:timezone":"Asia/Urumqi",
    "iso:country":"CN",
    "name:und_x_variant":[
        "A-ssu-t\u2019a-li-na",
        "Ast\u012bne",
        "Eru-p\u016bli",
        "Erh-pao",
        "Erh-pu",
        "Erpu"
    ],
    "wof:name":"Erpu",
    "wof:placetype":"locality"
},
  "geometry": {"coordinates":[93.13333,42.91667],"type":"Point"}
}