{
  "type": "Feature",
  "properties": {
    "gn:admin1_code":"11.0",
    "gn:asciiname":"Jiangbian Duanjia",
    "gn:country_code":"CN",
    "gn:dem":80,
    "gn:feature_class":"P",
    "gn:feature_code":"PPL",
    "gn:name":"Jiangbian Duanjia",
    "gn:population":0,
    "gn:timezone":"Asia/Shanghai",
    "iso:country":"CN",
    "name:zho_x_preferred":[
        "\u6c5f\u8fb9\u6bb5\u5bb6"
    ],
    "wof:name":"Jiangbian Duanjia",
    "wof:placetype":"locality"
},
  "geometry": {"coordinates":[112.86716,26.65829],"type":"Point"}
}