{
  "type": "Feature",
  "properties": {
    "gn:admin1_code":"15.0",
    "gn:asciiname":"Anzui",
    "gn:country_code":"CN",
    "gn:dem":1613,
    "gn:feature_class":"P",
    "gn:feature_code":"PPL",
    "gn:name":"Anzui",
    "gn:population":0,
    "gn:timezone":"Asia/Shanghai",
    "iso:country":"CN",
    "name:und_x_variant":[
        "\u5b89\u5480"
    ],
    "wof:name":"Anzui",
    "wof:placetype":"locality"
},
  "geometry": {"coordinates":[104.72935,34.74153],"type":"Point"}
}