{
  "type": "Feature",
  "properties": {
    "gn:admin1_code":"19",
    "gn:asciiname":"Chagou",
    "gn:country_code":"CN",
    "gn:dem":112,
    "gn:feature_class":"P",
    "gn:feature_code":"PPLA4",
    "gn:name":"Chagou",
    "gn:population":0,
    "gn:timezone":"Asia/Shanghai",
    "iso:country":"CN",
    "name:und_x_variant":[
        "Pa-ch\u2019a-kou",
        "Ch\u2019a-kou",
        "Chagou",
        "Chagou Zhen",
        "\u5c94\u6c9f\u9547"
    ],
    "name:zho_x_preferred":[
        "\u5c94\u6c9f"
    ],
    "wof:name":"Chagou",
    "wof:placetype":"locality"
},
  "geometry": {"coordinates":[122.86091,40.6168],"type":"Point"}
}