{
  "type": "Feature",
  "properties": {
    "gn:admin1_code":"26.0",
    "gn:asciiname":"Caiziba",
    "gn:country_code":"CN",
    "gn:dem":1027,
    "gn:feature_class":"P",
    "gn:feature_code":"PPL",
    "gn:name":"Caiziba",
    "gn:population":0,
    "gn:timezone":"Asia/Shanghai",
    "iso:country":"CN",
    "name:und_x_variant":[
        "\u8521\u5b50\u575d"
    ],
    "wof:name":"Caiziba",
    "wof:placetype":"locality"
},
  "geometry": {"coordinates":[106.34773,33.27897],"type":"Point"}
}