{
  "type": "Feature",
  "properties": {
    "gn:admin1_code":"19.0",
    "gn:asciiname":"Qiansanyihe",
    "gn:country_code":"CN",
    "gn:dem":120,
    "gn:feature_class":"P",
    "gn:feature_code":"PPL",
    "gn:name":"Qiansanyihe",
    "gn:population":0,
    "gn:timezone":"Asia/Shanghai",
    "iso:country":"CN",
    "name:zho_x_preferred":[
        "\u524d\u4e09\u4e49\u5408"
    ],
    "wof:name":"Qiansanyihe",
    "wof:placetype":"locality"
},
  "geometry": {"coordinates":[122.264,42.4938],"type":"Point"}
}