{
  "type": "Feature",
  "properties": {
    "gn:admin1_code":"30",
    "gn:asciiname":"Dalan",
    "gn:country_code":"CN",
    "gn:dem":1,
    "gn:feature_class":"P",
    "gn:feature_code":"PPL",
    "gn:name":"Dalan",
    "gn:population":0,
    "gn:timezone":"Asia/Shanghai",
    "iso:country":"CN",
    "name:ceb_x_preferred":[
        "Dalan"
    ],
    "name:swe_x_preferred":[
        "Dalan"
    ],
    "name:und_x_variant":[
        "Ta-lan"
    ],
    "name:zho_x_preferred":[
        "\u5927\u6984"
    ],
    "wof:name":"Dalan",
    "wof:placetype":"locality"
},
  "geometry": {"coordinates":[113.02406000000001,23.19485],"type":"Point"}
}