{
  "type": "Feature",
  "properties": {
    "gn:admin1_code":"12.0",
    "gn:asciiname":"Gaojiadian",
    "gn:country_code":"CN",
    "gn:dem":101,
    "gn:feature_class":"P",
    "gn:feature_code":"PPL",
    "gn:name":"Gaojiadian",
    "gn:population":0,
    "gn:timezone":"Asia/Shanghai",
    "iso:country":"CN",
    "name:zho_x_preferred":[
        "Gaojiadian"
    ],
    "name:zho_x_variant":[
        "\u9ad8\u5bb6\u5e97"
    ],
    "wof:name":"Gaojiadian",
    "wof:placetype":"locality"
},
  "geometry": {"coordinates":[111.43634,30.58954],"type":"Point"}
}