{
  "type": "Feature",
  "properties": {
    "gn:admin1_code":"32.0",
    "gn:asciiname":"Xijiaping",
    "gn:country_code":"CN",
    "gn:dem":2553,
    "gn:feature_class":"P",
    "gn:feature_code":"PPL",
    "gn:name":"Xijiaping",
    "gn:population":0,
    "gn:timezone":"Asia/Shanghai",
    "iso:country":"CN",
    "name:zho_x_preferred":[
        "\u897f\u5bb6\u576a"
    ],
    "wof:name":"Xijiaping",
    "wof:placetype":"locality"
},
  "geometry": {"coordinates":[101.43600000000001,27.4114],"type":"Point"}
}