{
  "type": "Feature",
  "properties": {
    "gn:admin1_code":"32.0",
    "gn:asciiname":"Zhaojianian",
    "gn:country_code":"CN",
    "gn:dem":538,
    "gn:feature_class":"P",
    "gn:feature_code":"PPL",
    "gn:name":"Zhaojianian",
    "gn:population":0,
    "gn:timezone":"Asia/Shanghai",
    "iso:country":"CN",
    "name:zho_x_preferred":[
        "\u8d75\u5bb6\u78be"
    ],
    "wof:name":"Zhaojianian",
    "wof:placetype":"locality"
},
  "geometry": {"coordinates":[104.069,31.0238],"type":"Point"}
}