{
  "type": "Feature",
  "properties": {
    "gn:admin1_code":"2.0",
    "gn:asciiname":"Yaowu",
    "gn:country_code":"CN",
    "gn:dem":83,
    "gn:feature_class":"P",
    "gn:feature_code":"PPL",
    "gn:name":"Yaowu",
    "gn:population":0,
    "gn:timezone":"Asia/Shanghai",
    "iso:country":"CN",
    "name:und_x_variant":[
        "\u59da\u575e",
        "Yaowu"
    ],
    "wof:name":"Yaowu",
    "wof:placetype":"locality"
},
  "geometry": {"coordinates":[119.55029999999999,29.26833],"type":"Point"}
}