{
  "type": "Feature",
  "properties": {
    "gn:admin1_code":"32.0",
    "gn:asciiname":"Eri",
    "gn:country_code":"CN",
    "gn:dem":3666,
    "gn:feature_class":"P",
    "gn:feature_code":"PPL",
    "gn:name":"Eri",
    "gn:population":0,
    "gn:timezone":"Asia/Shanghai",
    "iso:country":"CN",
    "name:ceb_x_preferred":[
        "Eri"
    ],
    "name:fra_x_preferred":[
        "Eri"
    ],
    "name:hun_x_preferred":[
        "\u00c9ri"
    ],
    "name:pol_x_preferred":[
        "Eri"
    ],
    "name:por_x_preferred":[
        "Eri"
    ],
    "name:ron_x_preferred":[
        "Eri"
    ],
    "name:swe_x_preferred":[
        "Eri"
    ],
    "name:tha_x_preferred":[
        "\u0e40\u0e2d\u0e23\u0e34"
    ],
    "name:zho_x_preferred":[
        "\u4fc4\u65e5"
    ],
    "wof:name":"Eri",
    "wof:placetype":"locality"
},
  "geometry": {"coordinates":[100.223,30.9055],"type":"Point"}
}