{
  "type": "Feature",
  "properties": {
    "gn:admin1_code":"11",
    "gn:asciiname":"Guangxingzhou",
    "gn:cc2":"CN",
    "gn:country_code":"CN",
    "gn:dem":30,
    "gn:feature_class":"P",
    "gn:feature_code":"PPL",
    "gn:name":"Guangxingzhou",
    "gn:population":0,
    "gn:timezone":"Asia/Shanghai",
    "iso:country":"CN",
    "name:und_x_variant":[
        "Kuang-hsing-chou",
        "Guangxingzhou"
    ],
    "wof:name":"Guangxingzhou",
    "wof:placetype":"locality"
},
  "geometry": {"coordinates":[112.90222,29.54306],"type":"Point"}
}