{
  "type": "Feature",
  "properties": {
    "gn:admin1_code":"3.0",
    "gn:asciiname":"Huaqiao",
    "gn:country_code":"CN",
    "gn:dem":68,
    "gn:feature_class":"P",
    "gn:feature_code":"PPL",
    "gn:name":"Huaqiao",
    "gn:population":0,
    "gn:timezone":"Asia/Shanghai",
    "iso:country":"CN",
    "name:ceb_x_preferred":[
        "Huaqiao"
    ],
    "name:deu_x_preferred":[
        "Huaqiao"
    ],
    "name:swe_x_preferred":[
        "Huaqiao"
    ],
    "name:und_x_variant":[
        "\u82b1\u6865"
    ],
    "wof:name":"Huaqiao",
    "wof:placetype":"locality"
},
  "geometry": {"coordinates":[116.0239,27.82779],"type":"Point"}
}