{
  "type": "Feature",
  "properties": {
    "gn:admin1_code":"4.0",
    "gn:asciiname":"Yaoqiao",
    "gn:country_code":"CN",
    "gn:dem":8,
    "gn:feature_class":"P",
    "gn:feature_code":"PPLA4",
    "gn:name":"Yaoqiao",
    "gn:population":0,
    "gn:timezone":"Asia/Shanghai",
    "iso:country":"CN",
    "name:und_x_variant":[
        "Yaojiaqiao",
        "Yaokiakiao",
        "Yao-chia-ch\u2019iao",
        "Yaoqiao",
        "Yaoqiao Zhen"
    ],
    "name:zho_x_preferred":[
        "\u59da\u6865"
    ],
    "name:zho_x_variant":[
        "\u59da\u6865\u9547"
    ],
    "wof:name":"Yaoqiao",
    "wof:placetype":"locality"
},
  "geometry": {"coordinates":[119.77222999999999,32.16352],"type":"Point"}
}