{
  "type": "Feature",
  "properties": {
    "gn:admin1_code":"8.0",
    "gn:asciiname":"Yangshuipiaotun",
    "gn:country_code":"CN",
    "gn:dem":153,
    "gn:feature_class":"P",
    "gn:feature_code":"PPL",
    "gn:name":"Yangshuipiaotun",
    "gn:population":0,
    "gn:timezone":"Asia/Shanghai",
    "iso:country":"CN",
    "name:zho_x_preferred":[
        "\u6768\u6c34\u98d8\u5c6f"
    ],
    "wof:name":"Yangshuipiaotun",
    "wof:placetype":"locality"
},
  "geometry": {"coordinates":[127.13487000000001,45.92119],"type":"Point"}
}