{
  "type": "Feature",
  "properties": {
    "gn:admin1_code":"14.0",
    "gn:asciiname":"Qinda",
    "gn:country_code":"CN",
    "gn:dem":4469,
    "gn:feature_class":"P",
    "gn:feature_code":"PPL",
    "gn:name":"Qinda",
    "gn:population":0,
    "gn:timezone":"Asia/Urumqi",
    "iso:country":"CN",
    "name:bod_x_preferred":[
        "Qinda"
    ],
    "name:zho_x_preferred":[
        "Qingda"
    ],
    "name:zho_x_variant":[
        "\u9752\u6253",
        "\u9752\u8fbe"
    ],
    "wof:name":"Qinda",
    "wof:placetype":"locality"
},
  "geometry": {"coordinates":[90.42791,29.04735],"type":"Point"}
}