{
  "type": "Feature",
  "properties": {
    "gn:admin1_code":"14.0",
    "gn:asciiname":"Pengre",
    "gn:country_code":"CN",
    "gn:dem":4673,
    "gn:feature_class":"P",
    "gn:feature_code":"PPL",
    "gn:name":"Pengre",
    "gn:population":0,
    "gn:timezone":"Asia/Urumqi",
    "iso:country":"CN",
    "name:zho_x_preferred":[
        "\u7bf7\u70ed"
    ],
    "wof:name":"Pengre",
    "wof:placetype":"locality"
},
  "geometry": {"coordinates":[91.92931,31.18439],"type":"Point"}
}