{
  "type": "Feature",
  "properties": {
    "gn:admin1_code":"18",
    "gn:asciiname":"Tongzipo",
    "gn:country_code":"CN",
    "gn:dem":650,
    "gn:feature_class":"P",
    "gn:feature_code":"PPL",
    "gn:name":"Tongzipo",
    "gn:population":0,
    "gn:timezone":"Asia/Shanghai",
    "iso:country":"CN",
    "name:zho_x_preferred":[
        "\u6850\u5b50\u5761"
    ],
    "wof:name":"Tongzipo",
    "wof:placetype":"locality"
},
  "geometry": {"coordinates":[105.81,28.588],"type":"Point"}
}