{
  "type": "Feature",
  "properties": {
    "gn:admin1_code":"29.0",
    "gn:asciiname":"Miaopo",
    "gn:country_code":"CN",
    "gn:dem":1774,
    "gn:feature_class":"P",
    "gn:feature_code":"PPL",
    "gn:name":"Miaopo",
    "gn:population":0,
    "gn:timezone":"Asia/Shanghai",
    "iso:country":"CN",
    "name:zho_x_preferred":[
        "\u5e99\u5761"
    ],
    "wof:name":"Miaopo",
    "wof:placetype":"locality"
},
  "geometry": {"coordinates":[104.23699999999999,27.6723],"type":"Point"}
}