{
  "type": "Feature",
  "properties": {
    "gn:admin1_code":"3",
    "gn:asciiname":"Gaotaishan Wangjia",
    "gn:country_code":"CN",
    "gn:dem":46,
    "gn:feature_class":"P",
    "gn:feature_code":"PPL",
    "gn:name":"Gaotaishan Wangjia",
    "gn:population":0,
    "gn:timezone":"Asia/Shanghai",
    "iso:country":"CN",
    "name:und_x_variant":[
        "\u9ad8\u53f0\u5c71\u6c6a\u5bb6"
    ],
    "wof:name":"Gaotaishan Wangjia",
    "wof:placetype":"locality"
},
  "geometry": {"coordinates":[117.35333,28.34833],"type":"Point"}
}