{
  "type": "Feature",
  "properties": {
    "gn:admin1_code":"7",
    "gn:asciiname":"Pandi",
    "gn:country_code":"CN",
    "gn:dem":787,
    "gn:feature_class":"P",
    "gn:feature_code":"PPL",
    "gn:name":"Pandi",
    "gn:population":0,
    "gn:timezone":"Asia/Shanghai",
    "iso:country":"CN",
    "name:ceb_x_preferred":[
        "Pandi"
    ],
    "name:deu_x_preferred":[
        "Pandi"
    ],
    "name:ita_x_preferred":[
        "Pandi"
    ],
    "name:nld_x_preferred":[
        "Pandi"
    ],
    "name:swe_x_preferred":[
        "Pandi"
    ],
    "name:und_x_variant":[
        "\u5224\u5730"
    ],
    "name:war_x_preferred":[
        "Pandi"
    ],
    "wof:name":"Pandi",
    "wof:placetype":"locality"
},
  "geometry": {"coordinates":[119.57778,27.51083],"type":"Point"}
}