{
  "type": "Feature",
  "properties": {
    "gn:admin1_code":"15.0",
    "gn:asciiname":"Wuliqiao",
    "gn:country_code":"CN",
    "gn:dem":1835,
    "gn:feature_class":"P",
    "gn:feature_code":"PPL",
    "gn:name":"Wuliqiao",
    "gn:population":0,
    "gn:timezone":"Asia/Shanghai",
    "iso:country":"CN",
    "name:und_x_variant":[
        "\u4e94\u91cc\u6865"
    ],
    "wof:name":"Wuliqiao",
    "wof:placetype":"locality"
},
  "geometry": {"coordinates":[105.23347,35.70141],"type":"Point"}
}