{
  "type": "Feature",
  "properties": {
    "gn:admin1_code":"14.0",
    "gn:asciiname":"Sadoi",
    "gn:country_code":"CN",
    "gn:dem":4669,
    "gn:feature_class":"P",
    "gn:feature_code":"PPL",
    "gn:name":"Sadoi",
    "gn:population":0,
    "gn:timezone":"Asia/Urumqi",
    "iso:country":"CN",
    "name:bod_x_preferred":[
        "Sadoi"
    ],
    "name:und_x_variant":[
        "Shadui"
    ],
    "name:zho_x_preferred":[
        "\u6c99\u5806"
    ],
    "wof:name":"Sadoi",
    "wof:placetype":"locality"
},
  "geometry": {"coordinates":[97.64022,29.15535],"type":"Point"}
}