{
  "type": "Feature",
  "properties": {
    "gn:admin1_code":"16",
    "gn:asciiname":"Ganshang",
    "gn:country_code":"CN",
    "gn:dem":160,
    "gn:feature_class":"P",
    "gn:feature_code":"PPL",
    "gn:name":"Ganshang",
    "gn:population":0,
    "gn:timezone":"Asia/Shanghai",
    "iso:country":"CN",
    "name:zho_x_preferred":[
        "\u5e72\u4e0a"
    ],
    "wof:name":"Ganshang",
    "wof:placetype":"locality"
},
  "geometry": {"coordinates":[110.22199999999999,25.0376],"type":"Point"}
}