{
  "type": "Feature",
  "properties": {
    "gn:admin1_code":"1.0",
    "gn:asciiname":"Shishancun",
    "gn:country_code":"CN",
    "gn:dem":59,
    "gn:feature_class":"P",
    "gn:feature_code":"PPL",
    "gn:name":"Shishancun",
    "gn:population":0,
    "gn:timezone":"Asia/Shanghai",
    "iso:country":"CN",
    "name:zho_x_preferred":[
        "\u77f3\u5c71\u6751"
    ],
    "wof:name":"Shishancun",
    "wof:placetype":"locality"
},
  "geometry": {"coordinates":[117.55852,30.59884000000001],"type":"Point"}
}