{
  "type": "Feature",
  "properties": {
    "gn:admin1_code":"33.0",
    "gn:asciiname":"Changchun",
    "gn:country_code":"CN",
    "gn:dem":376,
    "gn:feature_class":"P",
    "gn:feature_code":"PPL",
    "gn:name":"Changchun",
    "gn:population":0,
    "gn:timezone":"Asia/Shanghai",
    "iso:country":"CN",
    "name:zho_x_preferred":[
        "\u957f\u6625"
    ],
    "wof:name":"Changchun",
    "wof:placetype":"locality"
},
  "geometry": {"coordinates":[106.96814999999999,29.98469],"type":"Point"}
}