{
  "type": "Feature",
  "properties": {
    "gn:admin1_code":"18",
    "gn:asciiname":"Lianbacun",
    "gn:country_code":"CN",
    "gn:dem":1251,
    "gn:feature_class":"P",
    "gn:feature_code":"PPL",
    "gn:name":"Lianbacun",
    "gn:population":0,
    "gn:timezone":"Asia/Shanghai",
    "iso:country":"CN",
    "name:zho_x_preferred":[
        "\u8054\u516b\u6751"
    ],
    "wof:name":"Lianbacun",
    "wof:placetype":"locality"
},
  "geometry": {"coordinates":[106.313,25.4146],"type":"Point"}
}