{
  "type": "Feature",
  "properties": {
    "gn:admin1_code":"26.0",
    "gn:asciiname":"Yayao",
    "gn:country_code":"CN",
    "gn:dem":1186,
    "gn:feature_class":"P",
    "gn:feature_code":"PPL",
    "gn:name":"Yayao",
    "gn:population":0,
    "gn:timezone":"Asia/Shanghai",
    "iso:country":"CN",
    "name:zho_x_preferred":[
        "\u5d16\u7a91"
    ],
    "wof:name":"Yayao",
    "wof:placetype":"locality"
},
  "geometry": {"coordinates":[109.34647,36.89312],"type":"Point"}
}