{
  "type": "Feature",
  "properties": {
    "gn:admin1_code":"19.0",
    "gn:asciiname":"Shuiquan",
    "gn:country_code":"CN",
    "gn:dem":497,
    "gn:feature_class":"P",
    "gn:feature_code":"PPL",
    "gn:name":"Shuiquan",
    "gn:population":0,
    "gn:timezone":"Asia/Shanghai",
    "iso:country":"CN",
    "name:zho_x_preferred":[
        "\u6c34\u6cc9"
    ],
    "wof:name":"Shuiquan",
    "wof:placetype":"locality"
},
  "geometry": {"coordinates":[119.94779,41.68059],"type":"Point"}
}