{
  "type": "Feature",
  "properties": {
    "gn:admin1_code":"25.0",
    "gn:asciiname":"Jufeng",
    "gn:country_code":"CN",
    "gn:dem":26,
    "gn:feature_class":"P",
    "gn:feature_code":"PPL",
    "gn:name":"Jufeng",
    "gn:population":0,
    "gn:timezone":"Asia/Shanghai",
    "iso:country":"CN",
    "name:zho_x_preferred":[
        "\u5de8\u5cf0"
    ],
    "wof:name":"Jufeng",
    "wof:placetype":"locality"
},
  "geometry": {"coordinates":[121.02983,37.68491],"type":"Point"}
}