{
  "type": "Feature",
  "properties": {
    "gn:admin1_code":"32.0",
    "gn:asciiname":"Maoguanzi",
    "gn:country_code":"CN",
    "gn:dem":570,
    "gn:feature_class":"P",
    "gn:feature_code":"PPL",
    "gn:name":"Maoguanzi",
    "gn:population":0,
    "gn:timezone":"Asia/Shanghai",
    "iso:country":"CN",
    "name:zho_x_preferred":[
        "\u6bdb\u7f50\u5b50"
    ],
    "wof:name":"Maoguanzi",
    "wof:placetype":"locality"
},
  "geometry": {"coordinates":[105.848,31.5335],"type":"Point"}
}