{
  "type": "Feature",
  "properties": {
    "gn:admin1_code":"9.0",
    "gn:asciiname":"Shilingtou",
    "gn:country_code":"CN",
    "gn:dem":390,
    "gn:feature_class":"P",
    "gn:feature_code":"PPL",
    "gn:name":"Shilingtou",
    "gn:population":0,
    "gn:timezone":"Asia/Shanghai",
    "iso:country":"CN",
    "name:zho_x_preferred":[
        "\u77f3\u5cad\u5934"
    ],
    "wof:name":"Shilingtou",
    "wof:placetype":"locality"
},
  "geometry": {"coordinates":[113.23339,34.47199000000001],"type":"Point"}
}