{
  "type": "Feature",
  "properties": {
    "gn:admin1_code":"11",
    "gn:asciiname":"Wengpengchong",
    "gn:country_code":"CN",
    "gn:dem":242,
    "gn:feature_class":"P",
    "gn:feature_code":"PPL",
    "gn:name":"Wengpengchong",
    "gn:population":0,
    "gn:timezone":"Asia/Shanghai",
    "iso:country":"CN",
    "name:zho_x_preferred":[
        "\u74ee\u670b\u51b2"
    ],
    "wof:name":"Wengpengchong",
    "wof:placetype":"locality"
},
  "geometry": {"coordinates":[109.56439,27.72972],"type":"Point"}
}