{
  "type": "Feature",
  "properties": {
    "gn:admin1_code":"15.0",
    "gn:asciiname":"Chenxiazhuang",
    "gn:country_code":"CN",
    "gn:dem":1783,
    "gn:feature_class":"P",
    "gn:feature_code":"PPL",
    "gn:name":"Chenxiazhuang",
    "gn:population":0,
    "gn:timezone":"Asia/Shanghai",
    "iso:country":"CN",
    "name:zho_x_preferred":[
        "\u9648\u4e0b\u5e84"
    ],
    "wof:name":"Chenxiazhuang",
    "wof:placetype":"locality"
},
  "geometry": {"coordinates":[102.93300000000001,37.6417],"type":"Point"}
}