{
  "type": "Feature",
  "properties": {
    "gn:admin1_code":"25.0",
    "gn:asciiname":"Lujia Qiaowang",
    "gn:country_code":"CN",
    "gn:dem":39,
    "gn:feature_class":"P",
    "gn:feature_code":"PPL",
    "gn:name":"Lujia Qiaowang",
    "gn:population":0,
    "gn:timezone":"Asia/Shanghai",
    "iso:country":"CN",
    "name:zho_x_preferred":[
        "\u9c81\u5bb6\u4e54\u65fa"
    ],
    "wof:name":"Lujia Qiaowang",
    "wof:placetype":"locality"
},
  "geometry": {"coordinates":[119.02052999999999,35.09551],"type":"Point"}
}