{
  "type": "Feature",
  "properties": {
    "gn:admin1_code":"25",
    "gn:asciiname":"Zhaili",
    "gn:country_code":"CN",
    "gn:dem":51,
    "gn:feature_class":"P",
    "gn:feature_code":"PPL",
    "gn:name":"Zhaili",
    "gn:population":0,
    "gn:timezone":"Asia/Shanghai",
    "iso:country":"CN",
    "name:zho_x_preferred":[
        "\u5be8\u91cc"
    ],
    "wof:name":"Zhaili",
    "wof:placetype":"locality"
},
  "geometry": {"coordinates":[118.643,36.7147],"type":"Point"}
}