{
  "type": "Feature",
  "properties": {
    "gn:admin1_code":"6.0",
    "gn:asciiname":"Juenongga",
    "gn:country_code":"CN",
    "gn:dem":3782,
    "gn:feature_class":"P",
    "gn:feature_code":"PPL",
    "gn:name":"Juenongga",
    "gn:population":0,
    "gn:timezone":"Asia/Urumqi",
    "iso:country":"CN",
    "name:zho_x_preferred":[
        "\u89c9\u5f04\u5c15"
    ],
    "wof:name":"Juenongga",
    "wof:placetype":"locality"
},
  "geometry": {"coordinates":[96.31713000000001,32.4795],"type":"Point"}
}