{
  "type": "Feature",
  "properties": {
    "gn:admin1_code":"07",
    "gn:asciiname":"Guokeng",
    "gn:cc2":"CN",
    "gn:country_code":"CN",
    "gn:dem":7,
    "gn:feature_class":"P",
    "gn:feature_code":"PPL",
    "gn:name":"Guokeng",
    "gn:population":0,
    "gn:timezone":"Asia/Shanghai",
    "iso:country":"CN",
    "name:und_x_variant":[
        "Kuo-k\u2019eng",
        "Guokeng"
    ],
    "wof:name":"Guokeng",
    "wof:placetype":"locality"
},
  "geometry": {"coordinates":[117.73305999999999,24.55889],"type":"Point"}
}