{
  "type": "Feature",
  "properties": {
    "gn:admin1_code":"11.0",
    "gn:asciiname":"Hougongling",
    "gn:country_code":"CN",
    "gn:dem":38,
    "gn:feature_class":"P",
    "gn:feature_code":"PPL",
    "gn:name":"Hougongling",
    "gn:population":0,
    "gn:timezone":"Asia/Shanghai",
    "iso:country":"CN",
    "name:zho_x_preferred":[
        "\u4faf\u516c\u5cad"
    ],
    "wof:name":"Hougongling",
    "wof:placetype":"locality"
},
  "geometry": {"coordinates":[112.68168,28.38069],"type":"Point"}
}