{
  "type": "Feature",
  "properties": {
    "gn:admin1_code":"12",
    "gn:asciiname":"Luoji",
    "gn:country_code":"CN",
    "gn:dem":45,
    "gn:feature_class":"P",
    "gn:feature_code":"PPL",
    "gn:name":"Luoji",
    "gn:population":0,
    "gn:timezone":"Asia/Shanghai",
    "iso:country":"CN",
    "name:und_x_variant":[
        "Lo-chia-chi",
        "Luoji",
        "\u7f57\u96c6"
    ],
    "wof:name":"Luoji",
    "wof:placetype":"locality"
},
  "geometry": {"coordinates":[112.4577,30.87],"type":"Point"}
}