{
  "type": "Feature",
  "properties": {
    "gn:admin1_code":"29",
    "gn:asciiname":"Hejing",
    "gn:country_code":"CN",
    "gn:dem":1658,
    "gn:feature_class":"P",
    "gn:feature_code":"PPL",
    "gn:name":"Hejing",
    "gn:population":0,
    "gn:timezone":"Asia/Shanghai",
    "iso:country":"CN",
    "name:zho_x_preferred":[
        "\u4f55\u4e95"
    ],
    "wof:name":"Hejing",
    "wof:placetype":"locality"
},
  "geometry": {"coordinates":[102.56399999999999,24.4228],"type":"Point"}
}