{
  "type": "Feature",
  "properties": {
    "gn:admin1_code":"3.0",
    "gn:asciiname":"Fangxia",
    "gn:country_code":"CN",
    "gn:dem":83,
    "gn:feature_class":"P",
    "gn:feature_code":"PPL",
    "gn:name":"Fangxia",
    "gn:population":0,
    "gn:timezone":"Asia/Shanghai",
    "iso:country":"CN",
    "name:und_x_variant":[
        "\u574a\u4e0b"
    ],
    "wof:name":"Fangxia",
    "wof:placetype":"locality"
},
  "geometry": {"coordinates":[114.85015,27.65899000000001],"type":"Point"}
}