{
  "type": "Feature",
  "properties": {
    "gn:admin1_code":"26.0",
    "gn:asciiname":"Hongyuan",
    "gn:country_code":"CN",
    "gn:dem":480,
    "gn:feature_class":"P",
    "gn:feature_code":"PPL",
    "gn:name":"Hongyuan",
    "gn:population":0,
    "gn:timezone":"Asia/Shanghai",
    "iso:country":"CN",
    "name:ceb_x_preferred":[
        "Hongyuan"
    ],
    "name:zho_x_preferred":[
        "\u7ea2\u539f"
    ],
    "wof:name":"Hongyuan",
    "wof:placetype":"locality"
},
  "geometry": {"coordinates":[108.90260000000001,34.7216],"type":"Point"}
}