{
  "type": "Feature",
  "properties": {
    "gn:admin1_code":"20.0",
    "gn:asciiname":"Youyi Erdui Nongyedian",
    "gn:country_code":"CN",
    "gn:dem":664,
    "gn:feature_class":"P",
    "gn:feature_code":"PPL",
    "gn:name":"Youyi Erdui Nongyedian",
    "gn:population":0,
    "gn:timezone":"Asia/Shanghai",
    "iso:country":"CN",
    "name:zho_x_preferred":[
        "\u53cb\u8c0a\u4e8c\u961f\u519c\u4e1a\u70b9"
    ],
    "wof:name":"Youyi Erdui Nongyedian",
    "wof:placetype":"locality"
},
  "geometry": {"coordinates":[119.84191,49.12973],"type":"Point"}
}