{
  "type": "Feature",
  "properties": {
    "gn:admin1_code":"11.0",
    "gn:asciiname":"Bajiaotang",
    "gn:country_code":"CN",
    "gn:dem":173,
    "gn:feature_class":"P",
    "gn:feature_code":"PPL",
    "gn:name":"Bajiaotang",
    "gn:population":0,
    "gn:timezone":"Asia/Shanghai",
    "iso:country":"CN",
    "name:zho_x_preferred":[
        "\u516b\u89d2\u5802"
    ],
    "wof:name":"Bajiaotang",
    "wof:placetype":"locality"
},
  "geometry": {"coordinates":[112.4786,27.25604],"type":"Point"}
}