{
  "type": "Feature",
  "properties": {
    "gn:admin1_code":"12.0",
    "gn:asciiname":"Renjiahe",
    "gn:country_code":"CN",
    "gn:dem":89,
    "gn:feature_class":"P",
    "gn:feature_code":"PPL",
    "gn:name":"Renjiahe",
    "gn:population":0,
    "gn:timezone":"Asia/Shanghai",
    "iso:country":"CN",
    "name:zho_x_preferred":[
        "\u4efb\u5bb6\u6cb3"
    ],
    "wof:name":"Renjiahe",
    "wof:placetype":"locality"
},
  "geometry": {"coordinates":[113.45762000000001,31.50976],"type":"Point"}
}