{
  "type": "Feature",
  "properties": {
    "gn:admin1_code":"19.0",
    "gn:asciiname":"Xiadian",
    "gn:country_code":"CN",
    "gn:dem":19,
    "gn:feature_class":"P",
    "gn:feature_code":"PPL",
    "gn:name":"Xiadian",
    "gn:population":0,
    "gn:timezone":"Asia/Shanghai",
    "iso:country":"CN",
    "name:und_x_variant":[
        "\u4e0b\u5e97"
    ],
    "name:zho_x_preferred":[
        "\u4e0b\u5e97"
    ],
    "wof:name":"Xiadian",
    "wof:placetype":"locality"
},
  "geometry": {"coordinates":[122.34425,40.44673],"type":"Point"}
}