{
  "type": "Feature",
  "properties": {
    "gn:admin1_code":"29.0",
    "gn:asciiname":"Daijiaping",
    "gn:country_code":"CN",
    "gn:dem":2611,
    "gn:feature_class":"P",
    "gn:feature_code":"PPL",
    "gn:name":"Daijiaping",
    "gn:population":0,
    "gn:timezone":"Asia/Shanghai",
    "iso:country":"CN",
    "name:zho_x_preferred":[
        "\u4ee3\u5bb6\u576a"
    ],
    "wof:name":"Daijiaping",
    "wof:placetype":"locality"
},
  "geometry": {"coordinates":[102.98099999999999,26.937],"type":"Point"}
}