{
  "type": "Feature",
  "properties": {
    "gn:admin1_code":"8.0",
    "gn:asciiname":"Xinlaogou",
    "gn:country_code":"CN",
    "gn:dem":243,
    "gn:feature_class":"P",
    "gn:feature_code":"PPL",
    "gn:name":"Xinlaogou",
    "gn:population":0,
    "gn:timezone":"Asia/Shanghai",
    "iso:country":"CN",
    "name:zho_x_preferred":[
        "\u65b0\u8001\u6c9f"
    ],
    "wof:name":"Xinlaogou",
    "wof:placetype":"locality"
},
  "geometry": {"coordinates":[130.29974999999999,48.16829],"type":"Point"}
}