{
  "type": "Feature",
  "properties": {
    "gn:admin1_code":"4.0",
    "gn:asciiname":"Chenchang Yizu",
    "gn:country_code":"CN",
    "gn:dem":0,
    "gn:feature_class":"P",
    "gn:feature_code":"PPLF",
    "gn:name":"Chenchang Yizu",
    "gn:population":0,
    "gn:timezone":"Asia/Shanghai",
    "iso:country":"CN",
    "name:zho_x_preferred":[
        "\u9648\u573a\u4e00\u7ec4"
    ],
    "wof:name":"Chenchang Yizu",
    "wof:placetype":"locality"
},
  "geometry": {"coordinates":[120.059,33.9964],"type":"Point"}
}