{
  "type": "Feature",
  "properties": {
    "gn:admin1_code":"11",
    "gn:asciiname":"Jingzi",
    "gn:cc2":"CN",
    "gn:country_code":"CN",
    "gn:dem":151,
    "gn:feature_class":"P",
    "gn:feature_code":"PPL",
    "gn:name":"Jingzi",
    "gn:population":0,
    "gn:timezone":"Asia/Shanghai",
    "iso:country":"CN",
    "name:und_x_variant":[
        "Jingzijie",
        "Jingzi"
    ],
    "wof:name":"Jingzi",
    "wof:placetype":"locality"
},
  "geometry": {"coordinates":[112.41443999999998,27.46361],"type":"Point"}
}