{
  "type": "Feature",
  "properties": {
    "gn:admin1_code":"11.0",
    "gn:asciiname":"Xiniuwan",
    "gn:country_code":"CN",
    "gn:dem":119,
    "gn:feature_class":"P",
    "gn:feature_code":"PPL",
    "gn:name":"Xiniuwan",
    "gn:population":0,
    "gn:timezone":"Asia/Shanghai",
    "iso:country":"CN",
    "name:zho_x_preferred":[
        "Xiniuwan"
    ],
    "name:zho_x_variant":[
        "\u897f\u725b\u6e7e"
    ],
    "wof:name":"Xiniuwan",
    "wof:placetype":"locality"
},
  "geometry": {"coordinates":[111.49677,29.82474],"type":"Point"}
}