{
  "type": "Feature",
  "properties": {
    "gn:admin1_code":"11.0",
    "gn:asciiname":"Jiepaiwan",
    "gn:country_code":"CN",
    "gn:dem":158,
    "gn:feature_class":"P",
    "gn:feature_code":"PPL",
    "gn:name":"Jiepaiwan",
    "gn:population":0,
    "gn:timezone":"Asia/Shanghai",
    "iso:country":"CN",
    "name:zho_x_preferred":[
        "\u754c\u724c\u6e7e"
    ],
    "wof:name":"Jiepaiwan",
    "wof:placetype":"locality"
},
  "geometry": {"coordinates":[113.34358,26.42046],"type":"Point"}
}