{
  "type": "Feature",
  "properties": {
    "gn:admin1_code":"18",
    "gn:asciiname":"Haozhidian",
    "gn:country_code":"CN",
    "gn:dem":1861,
    "gn:feature_class":"P",
    "gn:feature_code":"PPL",
    "gn:name":"Haozhidian",
    "gn:population":0,
    "gn:timezone":"Asia/Shanghai",
    "iso:country":"CN",
    "name:zho_x_preferred":[
        "\u84bf\u679d\u4f43"
    ],
    "wof:name":"Haozhidian",
    "wof:placetype":"locality"
},
  "geometry": {"coordinates":[104.872,26.8335],"type":"Point"}
}