{
  "type": "Feature",
  "properties": {
    "gn:admin1_code":"15.0",
    "gn:asciiname":"Tailu",
    "gn:country_code":"CN",
    "gn:dem":950,
    "gn:feature_class":"P",
    "gn:feature_code":"PPL",
    "gn:name":"Tailu",
    "gn:population":0,
    "gn:timezone":"Asia/Shanghai",
    "iso:country":"CN",
    "name:zho_x_preferred":[
        "\u592a\u788c"
    ],
    "wof:name":"Tailu",
    "wof:placetype":"locality"
},
  "geometry": {"coordinates":[106.34,34.5165],"type":"Point"}
}