{
  "type": "Feature",
  "properties": {
    "gn:admin1_code":"11.0",
    "gn:asciiname":"Jishui",
    "gn:country_code":"CN",
    "gn:dem":154,
    "gn:feature_class":"P",
    "gn:feature_code":"PPL",
    "gn:name":"Jishui",
    "gn:population":0,
    "gn:timezone":"Asia/Shanghai",
    "iso:country":"CN",
    "name:ceb_x_preferred":[
        "Jishui"
    ],
    "name:fra_x_preferred":[
        "Jishui"
    ],
    "name:nor_x_preferred":[
        "Jishui"
    ],
    "name:pol_x_preferred":[
        "Jishui"
    ],
    "name:zho_x_preferred":[
        "\u5409\u6c34"
    ],
    "wof:name":"Jishui",
    "wof:placetype":"locality"
},
  "geometry": {"coordinates":[112.35415,28.0644],"type":"Point"}
}