{
  "type": "Feature",
  "properties": {
    "gn:admin1_code":"10.0",
    "gn:asciiname":"Chusong",
    "gn:country_code":"CN",
    "gn:dem":7,
    "gn:feature_class":"P",
    "gn:feature_code":"PPL",
    "gn:name":"Chusong",
    "gn:population":0,
    "gn:timezone":"Asia/Shanghai",
    "iso:country":"CN",
    "name:zho_x_preferred":[
        "\u891a\u5b8b"
    ],
    "wof:name":"Chusong",
    "wof:placetype":"locality"
},
  "geometry": {"coordinates":[117.456,38.0968],"type":"Point"}
}