{
  "type": "Feature",
  "properties": {
    "gn:admin1_code":"8.0",
    "gn:asciiname":"Changtingcun",
    "gn:country_code":"CN",
    "gn:dem":154,
    "gn:feature_class":"P",
    "gn:feature_code":"PPL",
    "gn:name":"Changtingcun",
    "gn:population":0,
    "gn:timezone":"Asia/Shanghai",
    "iso:country":"CN",
    "name:zho_x_preferred":[
        "\u957f\u4ead\u6751"
    ],
    "wof:name":"Changtingcun",
    "wof:placetype":"locality"
},
  "geometry": {"coordinates":[128.73979,45.49562],"type":"Point"}
}