{
  "type": "Feature",
  "properties": {
    "gn:admin1_code":"32",
    "gn:asciiname":"Jiangkou",
    "gn:country_code":"CN",
    "gn:dem":379,
    "gn:feature_class":"P",
    "gn:feature_code":"PPLA3",
    "gn:name":"Jiangkou",
    "gn:population":0,
    "gn:timezone":"Asia/Shanghai",
    "iso:country":"CN",
    "name:und_x_variant":[
        "Tszyankou",
        "Pingchang",
        "Jiangkou"
    ],
    "name:zho_x_preferred":[
        "P\u2019ing-ch\u2019ang-she-chih-ch\u00fc"
    ],
    "name:zho_x_variant":[
        "Chiang-k\u2019ou",
        "Chiang-k\u2019ou-chen",
        "\u6c5f\u53e3"
    ],
    "wof:name":"Jiangkou",
    "wof:placetype":"locality"
},
  "geometry": {"coordinates":[107.09735999999999,31.56506],"type":"Point"}
}