{
  "type": "Feature",
  "properties": {
    "gn:admin1_code":"9.0",
    "gn:asciiname":"Zhougou",
    "gn:country_code":"CN",
    "gn:dem":189,
    "gn:feature_class":"P",
    "gn:feature_code":"PPL",
    "gn:name":"Zhougou",
    "gn:population":0,
    "gn:timezone":"Asia/Shanghai",
    "iso:country":"CN",
    "name:und_x_variant":[
        "\u5468\u6c9f",
        "Zhougou"
    ],
    "wof:name":"Zhougou",
    "wof:placetype":"locality"
},
  "geometry": {"coordinates":[112.44835999999999,33.22928],"type":"Point"}
}