{
  "type": "Feature",
  "properties": {
    "gn:admin1_code":"31",
    "gn:asciiname":"Zhulin",
    "gn:country_code":"CN",
    "gn:dem":146,
    "gn:feature_class":"P",
    "gn:feature_code":"PPL",
    "gn:name":"Zhulin",
    "gn:population":0,
    "gn:timezone":"Asia/Shanghai",
    "iso:country":"CN",
    "name:und_x_variant":[
        "Chu-lin",
        "Zhulin",
        "\u7af9\u6797"
    ],
    "wof:name":"Zhulin",
    "wof:placetype":"locality"
},
  "geometry": {"coordinates":[110.53700000000001,19.4742],"type":"Point"}
}