{
  "type": "Feature",
  "properties": {
    "gn:admin1_code":"20",
    "gn:asciiname":"Hobo Hudag",
    "gn:country_code":"CN",
    "gn:dem":1267,
    "gn:feature_class":"P",
    "gn:feature_code":"PPL",
    "gn:name":"Hobo Hudag",
    "gn:population":0,
    "gn:timezone":"Asia/Shanghai",
    "iso:country":"CN",
    "wof:name":"Hobo Hudag",
    "wof:placetype":"locality"
},
  "geometry": {"coordinates":[105.34999999999999,38.98333],"type":"Point"}
}