{
  "type": "Feature",
  "properties": {
    "gn:admin1_code":"29.0",
    "gn:asciiname":"Hupa",
    "gn:country_code":"CN",
    "gn:dem":1908,
    "gn:feature_class":"P",
    "gn:feature_code":"PPL",
    "gn:name":"Hupa",
    "gn:population":0,
    "gn:timezone":"Asia/Shanghai",
    "iso:country":"CN",
    "name:ava_x_preferred":[
        "\u0425\u0443\u043f\u0430\u044f\u043b"
    ],
    "name:bel_x_preferred":[
        "\u0425\u0443\u043f\u0430"
    ],
    "name:bul_x_preferred":[
        "\u0425\u0443\u043f\u0430"
    ],
    "name:cat_x_preferred":[
        "Hupes"
    ],
    "name:deu_x_preferred":[
        "Hoopa"
    ],
    "name:fra_x_preferred":[
        "Hupas"
    ],
    "name:hrv_x_preferred":[
        "Hupa"
    ],
    "name:ita_x_preferred":[
        "Hupa"
    ],
    "name:lit_x_preferred":[
        "Hupai"
    ],
    "name:nld_x_preferred":[
        "Hupa"
    ],
    "name:nor_x_preferred":[
        "Hupa"
    ],
    "name:por_x_preferred":[
        "Hupa"
    ],
    "name:rus_x_preferred":[
        "\u0425\u0443\u043f\u0430"
    ],
    "name:spa_x_preferred":[
        "Hupa"
    ],
    "name:swe_x_preferred":[
        "Hupa"
    ],
    "name:tur_x_preferred":[
        "Hupalar"
    ],
    "name:zho_x_preferred":[
        "\u6237\u6015"
    ],
    "wof:name":"Hupa",
    "wof:placetype":"locality"
},
  "geometry": {"coordinates":[100.005,23.392],"type":"Point"}
}