{
  "type": "Feature",
  "properties": {
    "gn:admin1_code":"19.0",
    "gn:asciiname":"Wumen Wangjia",
    "gn:country_code":"CN",
    "gn:dem":140,
    "gn:feature_class":"P",
    "gn:feature_code":"PPL",
    "gn:name":"Wumen Wangjia",
    "gn:population":0,
    "gn:timezone":"Asia/Shanghai",
    "iso:country":"CN",
    "name:zho_x_preferred":[
        "\u4e94\u95e8\u738b\u5bb6"
    ],
    "wof:name":"Wumen Wangjia",
    "wof:placetype":"locality"
},
  "geometry": {"coordinates":[124.098,43.1817],"type":"Point"}
}