{
  "type": "Feature",
  "properties": {
    "gn:admin1_code":"32.0",
    "gn:asciiname":"Luojue Yizu",
    "gn:country_code":"CN",
    "gn:dem":2160,
    "gn:feature_class":"P",
    "gn:feature_code":"PPL",
    "gn:name":"Luojue Yizu",
    "gn:population":0,
    "gn:timezone":"Asia/Shanghai",
    "iso:country":"CN",
    "name:zho_x_preferred":[
        "\u6d1b\u89c9\u4f9d\u7956"
    ],
    "wof:name":"Luojue Yizu",
    "wof:placetype":"locality"
},
  "geometry": {"coordinates":[103.152,28.3371],"type":"Point"}
}