{
  "type": "Feature",
  "properties": {
    "gn:admin1_code":"10",
    "gn:asciiname":"Liushouying",
    "gn:cc2":"CN",
    "gn:country_code":"CN",
    "gn:dem":6,
    "gn:feature_class":"P",
    "gn:feature_code":"PPL",
    "gn:name":"Liushouying",
    "gn:population":0,
    "gn:timezone":"Asia/Shanghai",
    "iso:country":"CN",
    "name:und_x_variant":[
        "Liushow",
        "Liu-shou-ying-chen",
        "Liushouying"
    ],
    "wof:name":"Liushouying",
    "wof:placetype":"locality"
},
  "geometry": {"coordinates":[119.29583,39.78472],"type":"Point"}
}