{
  "type": "Feature",
  "properties": {
    "gn:admin1_code":"2.0",
    "gn:asciiname":"Lunlang",
    "gn:country_code":"CN",
    "gn:dem":341,
    "gn:feature_class":"P",
    "gn:feature_code":"PPL",
    "gn:name":"Lunlang",
    "gn:population":0,
    "gn:timezone":"Asia/Shanghai",
    "iso:country":"CN",
    "name:zho_x_preferred":[
        "\u4ed1\u5eca"
    ],
    "wof:name":"Lunlang",
    "wof:placetype":"locality"
},
  "geometry": {"coordinates":[119.06058,28.10007],"type":"Point"}
}