{
  "type": "Feature",
  "properties": {
    "gn:admin1_code":"25",
    "gn:asciiname":"Xizhaojia",
    "gn:country_code":"CN",
    "gn:dem":23,
    "gn:feature_class":"P",
    "gn:feature_code":"PPL",
    "gn:name":"Xizhaojia",
    "gn:population":0,
    "gn:timezone":"Asia/Shanghai",
    "iso:country":"CN",
    "name:zho_x_preferred":[
        "\u897f\u8d75\u5bb6"
    ],
    "wof:name":"Xizhaojia",
    "wof:placetype":"locality"
},
  "geometry": {"coordinates":[116.60662000000001,37.32958],"type":"Point"}
}