{
  "type": "Feature",
  "properties": {
    "gn:admin1_code":"30.0",
    "gn:asciiname":"Qianli",
    "gn:country_code":"CN",
    "gn:dem":193,
    "gn:feature_class":"P",
    "gn:feature_code":"PPL",
    "gn:name":"Qianli",
    "gn:population":0,
    "gn:timezone":"Asia/Shanghai",
    "iso:country":"CN",
    "name:zho_x_preferred":[
        "Qianli"
    ],
    "name:zho_x_variant":[
        "\u4e7e\u91cc"
    ],
    "wof:name":"Qianli",
    "wof:placetype":"locality"
},
  "geometry": {"coordinates":[115.44750000000001,24.22111],"type":"Point"}
}