{
  "type": "Feature",
  "properties": {
    "gn:admin1_code":"8.0",
    "gn:asciiname":"Chenggongcun",
    "gn:country_code":"CN",
    "gn:dem":165,
    "gn:feature_class":"P",
    "gn:feature_code":"PPL",
    "gn:name":"Chenggongcun",
    "gn:population":0,
    "gn:timezone":"Asia/Shanghai",
    "iso:country":"CN",
    "name:zho_x_preferred":[
        "\u6210\u529f\u6751"
    ],
    "wof:name":"Chenggongcun",
    "wof:placetype":"locality"
},
  "geometry": {"coordinates":[127.17707,46.78096],"type":"Point"}
}