{
  "type": "Feature",
  "properties": {
    "gn:admin1_code":"24.0",
    "gn:asciiname":"Guozigou",
    "gn:country_code":"CN",
    "gn:dem":1595,
    "gn:feature_class":"P",
    "gn:feature_code":"PPL",
    "gn:name":"Guozigou",
    "gn:population":0,
    "gn:timezone":"Asia/Shanghai",
    "iso:country":"CN",
    "name:zho_x_preferred":[
        "\u679c\u5b50\u6c9f"
    ],
    "wof:name":"Guozigou",
    "wof:placetype":"locality"
},
  "geometry": {"coordinates":[112.40919,37.10135],"type":"Point"}
}