{
  "type": "Feature",
  "properties": {
    "gn:admin1_code":"32.0",
    "gn:asciiname":"Zhe'eduona",
    "gn:country_code":"CN",
    "gn:dem":4157,
    "gn:feature_class":"P",
    "gn:feature_code":"PPL",
    "gn:name":"Zhe\u2019eduona",
    "gn:population":0,
    "gn:timezone":"Asia/Shanghai",
    "iso:country":"CN",
    "name:zho_x_preferred":[
        "\u54f2\u9102\u593a\u7eb3"
    ],
    "name:zho_x_variant":[
        "Zhe\u2019eduona"
    ],
    "wof:name":"Zhe'eduona",
    "wof:placetype":"locality"
},
  "geometry": {"coordinates":[100.98327,29.89619],"type":"Point"}
}