{
  "type": "Feature",
  "properties": {
    "gn:admin1_code":"11",
    "gn:asciiname":"Huishangang",
    "gn:country_code":"CN",
    "gn:dem":97,
    "gn:feature_class":"P",
    "gn:feature_code":"PPLA4",
    "gn:name":"Huishangang",
    "gn:population":0,
    "gn:timezone":"Asia/Shanghai",
    "iso:country":"CN",
    "name:und_x_variant":[
        "Hui-shan-chiang",
        "Hui-shan-kang",
        "Huishangang",
        "Huishangang Zhen"
    ],
    "name:zho_x_preferred":[
        "\u7070\u5c71\u6e2f"
    ],
    "name:zho_x_variant":[
        "\u7070\u5c71\u6e2f\u9547"
    ],
    "wof:name":"Huishangang",
    "wof:placetype":"locality"
},
  "geometry": {"coordinates":[112.23860999999999,28.28944000000001],"type":"Point"}
}