{
  "type": "Feature",
  "properties": {
    "gn:admin1_code":"3.0",
    "gn:asciiname":"Popomiao",
    "gn:country_code":"CN",
    "gn:dem":57,
    "gn:feature_class":"P",
    "gn:feature_code":"PPL",
    "gn:name":"Popomiao",
    "gn:population":0,
    "gn:timezone":"Asia/Shanghai",
    "iso:country":"CN",
    "name:und_x_variant":[
        "\u5a46\u5a46\u5e99"
    ],
    "wof:name":"Popomiao",
    "wof:placetype":"locality"
},
  "geometry": {"coordinates":[114.99652,27.04341],"type":"Point"}
}