{
  "type": "Feature",
  "properties": {
    "gn:admin1_code":"21.0",
    "gn:asciiname":"Nanwang Jiaquan",
    "gn:country_code":"CN",
    "gn:dem":1368,
    "gn:feature_class":"P",
    "gn:feature_code":"PPL",
    "gn:name":"Nanwang Jiaquan",
    "gn:population":0,
    "gn:timezone":"Asia/Shanghai",
    "iso:country":"CN",
    "name:zho_x_preferred":[
        "\u5357\u738b\u5bb6\u5708"
    ],
    "wof:name":"Nanwang Jiaquan",
    "wof:placetype":"locality"
},
  "geometry": {"coordinates":[107.44199999999999,37.846],"type":"Point"}
}