{
  "type": "Feature",
  "properties": {
    "gn:admin1_code":"9.0",
    "gn:asciiname":"Xigang",
    "gn:country_code":"CN",
    "gn:dem":346,
    "gn:feature_class":"P",
    "gn:feature_code":"PPL",
    "gn:name":"Xigang",
    "gn:population":0,
    "gn:timezone":"Asia/Shanghai",
    "iso:country":"CN",
    "name:ceb_x_preferred":[
        "Xigang"
    ],
    "name:deu_x_preferred":[
        "Xigang"
    ],
    "name:fra_x_preferred":[
        "Xigang"
    ],
    "name:zho_x_preferred":[
        "\u897f\u5c97"
    ],
    "wof:name":"Xigang",
    "wof:placetype":"locality"
},
  "geometry": {"coordinates":[112.11846,33.56899],"type":"Point"}
}