{
  "type": "Feature",
  "properties": {
    "gn:admin1_code":"19.0",
    "gn:asciiname":"Hulianzi",
    "gn:country_code":"CN",
    "gn:dem":393,
    "gn:feature_class":"P",
    "gn:feature_code":"PPL",
    "gn:name":"Hulianzi",
    "gn:population":0,
    "gn:timezone":"Asia/Shanghai",
    "iso:country":"CN",
    "name:zho_x_preferred":[
        "\u864e\u8138\u5b50"
    ],
    "wof:name":"Hulianzi",
    "wof:placetype":"locality"
},
  "geometry": {"coordinates":[125.09699999999999,42.1531],"type":"Point"}
}