{
  "type": "Feature",
  "properties": {
    "gn:admin1_code":"16.0",
    "gn:asciiname":"Jianong Xiaodong",
    "gn:country_code":"CN",
    "gn:dem":206,
    "gn:feature_class":"P",
    "gn:feature_code":"PPL",
    "gn:name":"Jianong Xiaodong",
    "gn:population":0,
    "gn:timezone":"Asia/Shanghai",
    "iso:country":"CN",
    "name:zho_x_preferred":[
        "\u52a0\u519c\u5c0f\u5cd2"
    ],
    "wof:name":"Jianong Xiaodong",
    "wof:placetype":"locality"
},
  "geometry": {"coordinates":[108.23399999999999,24.317],"type":"Point"}
}