{
  "type": "Feature",
  "properties": {
    "gn:admin1_code":"26.0",
    "gn:asciiname":"Qingshu",
    "gn:country_code":"CN",
    "gn:dem":625,
    "gn:feature_class":"P",
    "gn:feature_code":"PPLA4",
    "gn:name":"Qingshu",
    "gn:population":0,
    "gn:timezone":"Asia/Shanghai",
    "iso:country":"CN",
    "name:und_x_variant":[
        "\u9752\u6811",
        "Qingshu Zhen",
        "\u9752\u6811\u9547"
    ],
    "wof:name":"Qingshu",
    "wof:placetype":"locality"
},
  "geometry": {"coordinates":[106.90324,32.93629],"type":"Point"}
}