{
  "type": "Feature",
  "properties": {
    "gn:admin1_code":"12",
    "gn:asciiname":"Pantang",
    "gn:country_code":"CN",
    "gn:dem":64,
    "gn:feature_class":"P",
    "gn:feature_code":"PPLA4",
    "gn:name":"Pantang",
    "gn:population":0,
    "gn:timezone":"Asia/Shanghai",
    "iso:country":"CN",
    "name:und_x_variant":[
        "Pantang Jiedao",
        "\u6f58\u5858\u8857\u9053"
    ],
    "name:zho_x_preferred":[
        "\u6f58\u5858"
    ],
    "wof:name":"Pantang",
    "wof:placetype":"locality"
},
  "geometry": {"coordinates":[114.88824,30.99799],"type":"Point"}
}