{
  "type": "Feature",
  "properties": {
    "gn:admin1_code":"19.0",
    "gn:asciiname":"Mengzhangzi",
    "gn:country_code":"CN",
    "gn:dem":416,
    "gn:feature_class":"P",
    "gn:feature_code":"PPL",
    "gn:name":"Mengzhangzi",
    "gn:population":0,
    "gn:timezone":"Asia/Shanghai",
    "iso:country":"CN",
    "name:zho_x_preferred":[
        "\u5b5f\u6756\u5b50"
    ],
    "wof:name":"Mengzhangzi",
    "wof:placetype":"locality"
},
  "geometry": {"coordinates":[119.47308,41.13749],"type":"Point"}
}