{
  "type": "Feature",
  "properties": {
    "gn:admin1_code":"11.0",
    "gn:asciiname":"Fengshengjie",
    "gn:country_code":"CN",
    "gn:dem":692,
    "gn:feature_class":"P",
    "gn:feature_code":"PPL",
    "gn:name":"Fengshengjie",
    "gn:population":0,
    "gn:timezone":"Asia/Shanghai",
    "iso:country":"CN",
    "name:zho_x_preferred":[
        "\u4e30\u80dc\u754c"
    ],
    "wof:name":"Fengshengjie",
    "wof:placetype":"locality"
},
  "geometry": {"coordinates":[110.6581,27.29819],"type":"Point"}
}