{
  "type": "Feature",
  "properties": {
    "gn:admin1_code":"14.0",
    "gn:asciiname":"Gangqiongcun",
    "gn:country_code":"CN",
    "gn:dem":4349,
    "gn:feature_class":"P",
    "gn:feature_code":"PPL",
    "gn:name":"Gangqiongcun",
    "gn:population":0,
    "gn:timezone":"Asia/Urumqi",
    "iso:country":"CN",
    "name:zho_x_preferred":[
        "\u5c97\u743c\u6751"
    ],
    "wof:name":"Gangqiongcun",
    "wof:placetype":"locality"
},
  "geometry": {"coordinates":[93.66983999999999,32.24601],"type":"Point"}
}