{
  "type": "Feature",
  "properties": {
    "gn:admin1_code":"1.0",
    "gn:asciiname":"Dengducun",
    "gn:country_code":"CN",
    "gn:dem":6,
    "gn:feature_class":"P",
    "gn:feature_code":"PPL",
    "gn:name":"Dengducun",
    "gn:population":0,
    "gn:timezone":"Asia/Shanghai",
    "iso:country":"CN",
    "name:zho_x_preferred":[
        "\u9093\u6e21\u6751"
    ],
    "wof:name":"Dengducun",
    "wof:placetype":"locality"
},
  "geometry": {"coordinates":[117.37361,31.5154],"type":"Point"}
}