{
  "type": "Feature",
  "properties": {
    "gn:admin1_code":"29.0",
    "gn:asciiname":"Mengsuo",
    "gn:country_code":"CN",
    "gn:dem":1365,
    "gn:feature_class":"P",
    "gn:feature_code":"PPLA3",
    "gn:name":"Mengsuo",
    "gn:population":0,
    "gn:timezone":"Asia/Shanghai",
    "iso:country":"CN",
    "name:und_x_variant":[
        "Meng-hsaw",
        "M\u00f6ng Hsaw",
        "Mengsuo"
    ],
    "name:zho_x_preferred":[
        "\u52d0\u68ad"
    ],
    "name:zho_x_variant":[
        "M\u00f6ng Hsaw"
    ],
    "wof:name":"Mengsuo",
    "wof:placetype":"locality"
},
  "geometry": {"coordinates":[99.55137000000001,22.60199],"type":"Point"}
}