{
  "type": "Feature",
  "properties": {
    "gn:admin1_code":"14.0",
    "gn:asciiname":"Chudigongcun",
    "gn:country_code":"CN",
    "gn:dem":3821,
    "gn:feature_class":"P",
    "gn:feature_code":"PPL",
    "gn:name":"Chudigongcun",
    "gn:population":0,
    "gn:timezone":"Asia/Urumqi",
    "iso:country":"CN",
    "name:zho_x_preferred":[
        "\u695a\u5730\u8d21\u6751"
    ],
    "wof:name":"Chudigongcun",
    "wof:placetype":"locality"
},
  "geometry": {"coordinates":[98.95643,29.70446],"type":"Point"}
}