{
  "type": "Feature",
  "properties": {
    "gn:admin1_code":"14",
    "gn:asciiname":"Jinque",
    "gn:country_code":"CN",
    "gn:dem":4136,
    "gn:feature_class":"P",
    "gn:feature_code":"PPL",
    "gn:name":"Jinque",
    "gn:population":0,
    "gn:timezone":"Asia/Urumqi",
    "iso:country":"CN",
    "name:zho_x_preferred":[
        "\u91d1\u786e"
    ],
    "wof:name":"Jinque",
    "wof:placetype":"locality"
},
  "geometry": {"coordinates":[89.1388,29.0814],"type":"Point"}
}