{
  "type": "Feature",
  "properties": {
    "gn:admin1_code":"3.0",
    "gn:asciiname":"Changxia",
    "gn:country_code":"CN",
    "gn:dem":483,
    "gn:feature_class":"P",
    "gn:feature_code":"PPL",
    "gn:name":"Changxia",
    "gn:population":0,
    "gn:timezone":"Asia/Shanghai",
    "iso:country":"CN",
    "name:und_x_variant":[
        "\u660c\u4e0b"
    ],
    "wof:name":"Changxia",
    "wof:placetype":"locality"
},
  "geometry": {"coordinates":[115.50368,26.60848],"type":"Point"}
}