{
  "type": "Feature",
  "properties": {
    "date:inception_lower": "2008-07-01",
    "date:inception_upper": "2008-07-31",
    "iso:country": "CN",
    "wof:name": "Shijiazhuang Zhengding International Airport",
    "wof:placetype": "campus",
    "wof:placetype_alt": "airport"
  },
  "geometry": {"coordinates":[114.696667,38.280833],"type":"Point"}
}
