{
  "type": "Feature",
  "properties": {
    "gn:admin1_code":"29.0",
    "gn:asciiname":"Daluozhai",
    "gn:country_code":"CN",
    "gn:dem":1235,
    "gn:feature_class":"P",
    "gn:feature_code":"PPL",
    "gn:name":"Daluozhai",
    "gn:population":0,
    "gn:timezone":"Asia/Shanghai",
    "iso:country":"CN",
    "name:zho_x_preferred":[
        "\u6253\u843d\u5be8"
    ],
    "wof:name":"Daluozhai",
    "wof:placetype":"locality"
},
  "geometry": {"coordinates":[103.121,22.7564],"type":"Point"}
}