{
  "type": "Feature",
  "properties": {
    "gn:admin1_code":"15.0",
    "gn:asciiname":"Minfanggou",
    "gn:country_code":"CN",
    "gn:dem":2710,
    "gn:feature_class":"P",
    "gn:feature_code":"PPL",
    "gn:name":"Minfanggou",
    "gn:population":0,
    "gn:timezone":"Asia/Shanghai",
    "iso:country":"CN",
    "name:zho_x_preferred":[
        "\u6c11\u623f\u6c9f"
    ],
    "wof:name":"Minfanggou",
    "wof:placetype":"locality"
},
  "geometry": {"coordinates":[103.202,37.2657],"type":"Point"}
}