{
  "type": "Feature",
  "properties": {
    "gn:admin1_code":"04",
    "gn:asciiname":"Qidong Yanchang",
    "gn:country_code":"CN",
    "gn:dem":3,
    "gn:feature_class":"P",
    "gn:feature_code":"PPLF",
    "gn:name":"Qidong Yanchang",
    "gn:population":0,
    "gn:timezone":"Asia/Shanghai",
    "iso:country":"CN",
    "name:und_x_variant":[
        "\u542f\u4e1c\u76d0\u573a",
        "Qidongyanchang"
    ],
    "wof:name":"Qidong Yanchang",
    "wof:placetype":"locality"
},
  "geometry": {"coordinates":[121.83893999999999,31.91128],"type":"Point"}
}