{
  "type": "Feature",
  "properties": {
    "gn:admin1_code":"32.0",
    "gn:asciiname":"Wuxing",
    "gn:country_code":"CN",
    "gn:dem":1524,
    "gn:feature_class":"P",
    "gn:feature_code":"PPL",
    "gn:name":"Wuxing",
    "gn:population":0,
    "gn:timezone":"Asia/Shanghai",
    "iso:country":"CN",
    "name:ceb_x_preferred":[
        "Wuxing"
    ],
    "name:deu_x_preferred":[
        "Wuxing"
    ],
    "name:fra_x_preferred":[
        "Wuxing"
    ],
    "name:zho_x_preferred":[
        "\u4e94\u661f"
    ],
    "wof:name":"Wuxing",
    "wof:placetype":"locality"
},
  "geometry": {"coordinates":[102.48399999999999,29.53],"type":"Point"}
}