{
  "type": "Feature",
  "properties": {
    "gn:admin1_code":"19.0",
    "gn:asciiname":"Lujuanzigou",
    "gn:country_code":"CN",
    "gn:dem":579,
    "gn:feature_class":"P",
    "gn:feature_code":"PPL",
    "gn:name":"Lujuanzigou",
    "gn:population":0,
    "gn:timezone":"Asia/Shanghai",
    "iso:country":"CN",
    "name:zho_x_preferred":[
        "\u5362\u5377\u5b50\u6c9f"
    ],
    "wof:name":"Lujuanzigou",
    "wof:placetype":"locality"
},
  "geometry": {"coordinates":[119.90361,41.44109],"type":"Point"}
}