{
  "type": "Feature",
  "properties": {
    "gn:admin1_code":"3.0",
    "gn:asciiname":"Daiyou",
    "gn:country_code":"CN",
    "gn:dem":328,
    "gn:feature_class":"P",
    "gn:feature_code":"PPL",
    "gn:name":"Daiyou",
    "gn:population":0,
    "gn:timezone":"Asia/Shanghai",
    "iso:country":"CN",
    "name:und_x_variant":[
        "\u5cb1\u6cb9"
    ],
    "wof:name":"Daiyou",
    "wof:placetype":"locality"
},
  "geometry": {"coordinates":[114.42113000000001,24.90019],"type":"Point"}
}