{
  "type": "Feature",
  "properties": {
    "gn:admin1_code":"26.0",
    "gn:asciiname":"Qingshuihecun",
    "gn:country_code":"CN",
    "gn:dem":1518,
    "gn:feature_class":"P",
    "gn:feature_code":"PPL",
    "gn:name":"Qingshuihecun",
    "gn:population":0,
    "gn:timezone":"Asia/Shanghai",
    "iso:country":"CN",
    "name:zho_x_preferred":[
        "\u6e05\u6c34\u6cb3\u6751"
    ],
    "wof:name":"Qingshuihecun",
    "wof:placetype":"locality"
},
  "geometry": {"coordinates":[108.04785,33.83882],"type":"Point"}
}