{
  "type": "Feature",
  "properties": {
    "gn:admin1_code":"32.0",
    "gn:asciiname":"Jinfengtan",
    "gn:country_code":"CN",
    "gn:dem":427,
    "gn:feature_class":"P",
    "gn:feature_code":"PPL",
    "gn:name":"Jinfengtan",
    "gn:population":0,
    "gn:timezone":"Asia/Shanghai",
    "iso:country":"CN",
    "name:zho_x_preferred":[
        "\u91d1\u51e4\u6ee9"
    ],
    "wof:name":"Jinfengtan",
    "wof:placetype":"locality"
},
  "geometry": {"coordinates":[105.78100000000001,30.7413],"type":"Point"}
}