{
  "type": "Feature",
  "properties": {
    "gn:admin1_code":"24.0",
    "gn:asciiname":"Huaishu'ao",
    "gn:country_code":"CN",
    "gn:dem":369,
    "gn:feature_class":"P",
    "gn:feature_code":"PPL",
    "gn:name":"Huaishu\u2019ao",
    "gn:population":0,
    "gn:timezone":"Asia/Shanghai",
    "iso:country":"CN",
    "name:und_x_variant":[
        "Huaishu\u2019ao"
    ],
    "name:zho_x_preferred":[
        "\u69d0\u6811\u51f9"
    ],
    "wof:name":"Huaishu'ao",
    "wof:placetype":"locality"
},
  "geometry": {"coordinates":[111.00790000000001,35.03361],"type":"Point"}
}