{
  "type": "Feature",
  "properties": {
    "gn:admin1_code":"26",
    "gn:asciiname":"Shiquan",
    "gn:cc2":"CN",
    "gn:country_code":"CN",
    "gn:dem":1117,
    "gn:feature_class":"P",
    "gn:feature_code":"PPL",
    "gn:name":"Shiquan",
    "gn:population":0,
    "gn:timezone":"Asia/Shanghai",
    "iso:country":"CN",
    "name:und_x_variant":[
        "Shih-ch\u00fcan",
        "Shih-ch\u2019\u00fcan-ts\u2019un",
        "Shiquan"
    ],
    "wof:name":"Shiquan",
    "wof:placetype":"locality"
},
  "geometry": {"coordinates":[109.56999999999999,35.66194],"type":"Point"}
}