{
  "type": "Feature",
  "properties": {
    "gn:admin1_code":"26",
    "gn:asciiname":"Shiquan",
    "gn:cc2":"CN",
    "gn:country_code":"CN",
    "gn:dem":1117,
    "gn:feature_class":"P",
    "gn:feature_code":"PPL",
    "gn:name":"Shiquan",
    "gn:population":0,
    "gn:timezone":"Asia/Shanghai",
    "iso:country":"CN",
    "name:ara_x_preferred":[
        "\u0634\u064a\u0643\u0648\u0627\u0646"
    ],
    "name:ben_x_preferred":[
        "\u09b6\u09bf\u0995\u09be\u09a8"
    ],
    "name:deu_x_preferred":[
        "S\u00eangg\u00ea Zangbo"
    ],
    "name:ell_x_preferred":[
        "\u03a3\u03b9\u03ba\u03bf\u03c5\u03ac\u03bd"
    ],
    "name:fas_x_preferred":[
        "\u0634\u06cc\u06a9\u0648\u0627\u0646"
    ],
    "name:fra_x_preferred":[
        "Shiquan"
    ],
    "name:heb_x_preferred":[
        "\u05e9\u05d9\u05e7\u05d0\u05df"
    ],
    "name:hun_x_preferred":[
        "Shiquan"
    ],
    "name:ind_x_preferred":[
        "Shiquan"
    ],
    "name:ita_x_preferred":[
        "Shiquan"
    ],
    "name:kor_x_preferred":[
        "\uc2a4\ucd28"
    ],
    "name:pol_x_preferred":[
        "Shiquan"
    ],
    "name:por_x_preferred":[
        "Shiquan"
    ],
    "name:rus_x_preferred":[
        "\u0440\u0435\u043a\u0430 \u0428\u0438\u0446\u044e\u0430\u043d\u044c"
    ],
    "name:spa_x_preferred":[
        "Shiquan"
    ],
    "name:tur_x_preferred":[
        "Shiquan"
    ],
    "name:ukr_x_preferred":[
        "\u0428\u0456\u043a\u0432\u0430\u043d"
    ],
    "name:und_x_variant":[
        "Shih-ch\u00fcan",
        "Shih-ch\u2019\u00fcan-ts\u2019un",
        "Shiquan"
    ],
    "name:urd_x_preferred":[
        "\u0634\u06cc\u0642\u0648\u0627\u0646"
    ],
    "name:vie_x_preferred":[
        "S\u00f4ng Shiquan"
    ],
    "wof:name":"Shiquan",
    "wof:placetype":"locality"
},
  "geometry": {"coordinates":[109.56999999999999,35.66194],"type":"Point"}
}