{
  "type": "Feature",
  "properties": {
    "gn:admin1_code":"32.0",
    "gn:asciiname":"Xi'eluo",
    "gn:country_code":"CN",
    "gn:dem":3534,
    "gn:feature_class":"P",
    "gn:feature_code":"PPL",
    "gn:name":"Xi\u2019eluo",
    "gn:population":0,
    "gn:timezone":"Asia/Shanghai",
    "iso:country":"CN",
    "name:und_x_variant":[
        "Lithang Golok",
        "Hsi-o-lo",
        "Lithang Golog",
        "Sielo",
        "Singolo",
        "Xi Golog"
    ],
    "name:zho_x_preferred":[
        "\u897f\u4fc4\u6d1b"
    ],
    "name:zho_x_variant":[
        "Xi\u2019eluo"
    ],
    "wof:name":"Xi'eluo",
    "wof:placetype":"locality"
},
  "geometry": {"coordinates":[100.71425000000001,30.02508],"type":"Point"}
}