{
  "type": "Feature",
  "properties": {
    "gn:admin1_code":"16.0",
    "gn:asciiname":"Weihong",
    "gn:country_code":"CN",
    "gn:dem":525,
    "gn:feature_class":"P",
    "gn:feature_code":"PPL",
    "gn:name":"Weihong",
    "gn:population":0,
    "gn:timezone":"Asia/Shanghai",
    "iso:country":"CN",
    "name:zho_x_preferred":[
        "\u6e2d\u8f70"
    ],
    "wof:name":"Weihong",
    "wof:placetype":"locality"
},
  "geometry": {"coordinates":[106.16500000000001,24.2053],"type":"Point"}
}