{
  "type": "Feature",
  "properties": {
    "gn:admin1_code":"7.0",
    "gn:asciiname":"Neilongkou",
    "gn:country_code":"CN",
    "gn:dem":137,
    "gn:feature_class":"P",
    "gn:feature_code":"PPL",
    "gn:name":"Neilongkou",
    "gn:population":0,
    "gn:timezone":"Asia/Shanghai",
    "iso:country":"CN",
    "name:zho_x_preferred":[
        "\u5185\u5784\u53e3"
    ],
    "wof:name":"Neilongkou",
    "wof:placetype":"locality"
},
  "geometry": {"coordinates":[117.89739,24.29592],"type":"Point"}
}