{
  "type": "Feature",
  "properties": {
    "gn:admin1_code":"11.0",
    "gn:asciiname":"Erfenchang Yidui",
    "gn:country_code":"CN",
    "gn:dem":28,
    "gn:feature_class":"P",
    "gn:feature_code":"PPLF",
    "gn:name":"Erfenchang Yidui",
    "gn:population":0,
    "gn:timezone":"Asia/Shanghai",
    "iso:country":"CN",
    "name:zho_x_preferred":[
        "\u4e8c\u5206\u573a\u4e00\u961f"
    ],
    "wof:name":"Erfenchang Yidui",
    "wof:placetype":"locality"
},
  "geometry": {"coordinates":[112.60057999999999,29.14961],"type":"Point"}
}