{
  "type": "Feature",
  "properties": {
    "gn:admin1_code":"5.0",
    "gn:asciiname":"Yangmucun",
    "gn:country_code":"CN",
    "gn:dem":420,
    "gn:feature_class":"P",
    "gn:feature_code":"PPL",
    "gn:name":"Yangmucun",
    "gn:population":0,
    "gn:timezone":"Asia/Shanghai",
    "iso:country":"CN",
    "name:zho_x_preferred":[
        "\u6768\u6728\u6751"
    ],
    "wof:name":"Yangmucun",
    "wof:placetype":"locality"
},
  "geometry": {"coordinates":[128.30808999999999,43.55942],"type":"Point"}
}