{
  "type": "Feature",
  "properties": {
    "gn:admin1_code":"12.0",
    "gn:asciiname":"Tuochuangou",
    "gn:country_code":"CN",
    "gn:dem":30,
    "gn:feature_class":"P",
    "gn:feature_code":"PPL",
    "gn:name":"Tuochuangou",
    "gn:population":0,
    "gn:timezone":"Asia/Shanghai",
    "iso:country":"CN",
    "name:zho_x_preferred":[
        "\u62d6\u8239\u6c9f"
    ],
    "wof:name":"Tuochuangou",
    "wof:placetype":"locality"
},
  "geometry": {"coordinates":[112.74521,29.71814],"type":"Point"}
}