{
  "type": "Feature",
  "properties": {
    "gn:admin1_code":"3.0",
    "gn:asciiname":"Qiaotoucun",
    "gn:country_code":"CN",
    "gn:dem":24,
    "gn:feature_class":"P",
    "gn:feature_code":"PPL",
    "gn:name":"Qiaotoucun",
    "gn:population":0,
    "gn:timezone":"Asia/Shanghai",
    "iso:country":"CN",
    "name:und_x_variant":[
        "\u6865\u5934\u6751"
    ],
    "wof:name":"Qiaotoucun",
    "wof:placetype":"locality"
},
  "geometry": {"coordinates":[116.35697999999999,28.49641],"type":"Point"}
}