{
  "type": "Feature",
  "properties": {
    "gn:admin1_code":"3.0",
    "gn:asciiname":"Niubeijing",
    "gn:country_code":"CN",
    "gn:dem":323,
    "gn:feature_class":"P",
    "gn:feature_code":"PPL",
    "gn:name":"Niubeijing",
    "gn:population":0,
    "gn:timezone":"Asia/Shanghai",
    "iso:country":"CN",
    "name:zho_x_preferred":[
        "\u725b\u80cc\u9888"
    ],
    "wof:name":"Niubeijing",
    "wof:placetype":"locality"
},
  "geometry": {"coordinates":[114.68899999999999,29.3479],"type":"Point"}
}