{
  "type": "Feature",
  "properties": {
    "gn:admin1_code":"30.0",
    "gn:asciiname":"Shijieling",
    "gn:country_code":"CN",
    "gn:dem":321,
    "gn:feature_class":"P",
    "gn:feature_code":"PPL",
    "gn:name":"Shijieling",
    "gn:population":0,
    "gn:timezone":"Asia/Shanghai",
    "iso:country":"CN",
    "name:zho_x_preferred":[
        "Shijieling"
    ],
    "name:zho_x_variant":[
        "\u77f3\u8857\u5cad"
    ],
    "wof:name":"Shijieling",
    "wof:placetype":"locality"
},
  "geometry": {"coordinates":[114.21113,24.30796],"type":"Point"}
}