{
  "type": "Feature",
  "properties": {
    "gn:admin1_code":"18.0",
    "gn:asciiname":"Guanchayuan",
    "gn:country_code":"CN",
    "gn:dem":672,
    "gn:feature_class":"P",
    "gn:feature_code":"PPL",
    "gn:name":"Guanchayuan",
    "gn:population":0,
    "gn:timezone":"Asia/Shanghai",
    "iso:country":"CN",
    "name:zho_x_preferred":[
        "\u5173\u8336\u56ed"
    ],
    "wof:name":"Guanchayuan",
    "wof:placetype":"locality"
},
  "geometry": {"coordinates":[109.084,27.8931],"type":"Point"}
}