{
  "type": "Feature",
  "properties": {
    "gn:admin1_code":"32.0",
    "gn:asciiname":"Renshou Guoping",
    "gn:country_code":"CN",
    "gn:dem":3413,
    "gn:feature_class":"P",
    "gn:feature_code":"PPL",
    "gn:name":"Renshou Guoping",
    "gn:population":0,
    "gn:timezone":"Asia/Shanghai",
    "iso:country":"CN",
    "name:zho_x_preferred":[
        "\u4ec1\u5bff\u679c\u576a"
    ],
    "wof:name":"Renshou Guoping",
    "wof:placetype":"locality"
},
  "geometry": {"coordinates":[102.78304,31.05809],"type":"Point"}
}