{
  "type": "Feature",
  "properties": {
    "gn:admin1_code":"15.0",
    "gn:asciiname":"Nanguan",
    "gn:country_code":"CN",
    "gn:dem":1659,
    "gn:feature_class":"P",
    "gn:feature_code":"PPL",
    "gn:name":"Nanguan",
    "gn:population":0,
    "gn:timezone":"Asia/Shanghai",
    "iso:country":"CN",
    "name:ceb_x_preferred":[
        "Nanguan"
    ],
    "name:deu_x_preferred":[
        "Nanguan"
    ],
    "name:fra_x_preferred":[
        "Nanguan"
    ],
    "name:und_x_variant":[
        "\u5357\u5173"
    ],
    "wof:name":"Nanguan",
    "wof:placetype":"locality"
},
  "geometry": {"coordinates":[105.71681,35.51547],"type":"Point"}
}