{
  "type": "Feature",
  "properties": {
    "gn:admin1_code":"11",
    "gn:asciiname":"Shenjiaxi",
    "gn:country_code":"CN",
    "gn:dem":439,
    "gn:feature_class":"P",
    "gn:feature_code":"PPL",
    "gn:name":"Shenjiaxi",
    "gn:population":0,
    "gn:timezone":"Asia/Shanghai",
    "iso:country":"CN",
    "name:zho_x_preferred":[
        "\u6c88\u5bb6\u6eaa"
    ],
    "wof:name":"Shenjiaxi",
    "wof:placetype":"locality"
},
  "geometry": {"coordinates":[109.69705999999999,27.57333],"type":"Point"}
}