{
  "type": "Feature",
  "properties": {
    "gn:admin1_code":"07",
    "gn:asciiname":"Longjin",
    "gn:country_code":"CN",
    "gn:dem":299,
    "gn:feature_class":"P",
    "gn:feature_code":"PPLA3",
    "gn:name":"Longjin",
    "gn:population":0,
    "gn:timezone":"Asia/Shanghai",
    "iso:country":"CN",
    "name:und_x_variant":[
        "Qingliu",
        "Longjin",
        "Longjin Zhen",
        "Donghua",
        "\u6e05\u6d41",
        "\u9f99\u6d25\u9547",
        "\u4e1c\u534e"
    ],
    "name:zho_x_preferred":[
        "Ch\u2019ing-liu-hsien"
    ],
    "name:zho_x_variant":[
        "Ch\u2019ing-liu"
    ],
    "wof:name":"Longjin",
    "wof:placetype":"locality"
},
  "geometry": {"coordinates":[116.81464,26.18197],"type":"Point"}
}