{
  "type": "Feature",
  "properties": {
    "gn:admin1_code":"19.0",
    "gn:asciiname":"Yaojia Zhangzicun",
    "gn:country_code":"CN",
    "gn:dem":367,
    "gn:feature_class":"P",
    "gn:feature_code":"PPL",
    "gn:name":"Yaojia Zhangzicun",
    "gn:population":0,
    "gn:timezone":"Asia/Shanghai",
    "iso:country":"CN",
    "name:zho_x_preferred":[
        "\u59da\u5bb6\u6756\u5b50\u6751"
    ],
    "wof:name":"Yaojia Zhangzicun",
    "wof:placetype":"locality"
},
  "geometry": {"coordinates":[120.093,41.3012],"type":"Point"}
}