{
  "type": "Feature",
  "properties": {
    "gn:admin1_code":"33.0",
    "gn:asciiname":"Dangshui",
    "gn:country_code":"CN",
    "gn:dem":377,
    "gn:feature_class":"P",
    "gn:feature_code":"PPL",
    "gn:name":"Dangshui",
    "gn:population":0,
    "gn:timezone":"Asia/Shanghai",
    "iso:country":"CN",
    "name:zho_x_preferred":[
        "\u51fc\u6c34"
    ],
    "wof:name":"Dangshui",
    "wof:placetype":"locality"
},
  "geometry": {"coordinates":[107.40951,30.20299],"type":"Point"}
}