{
  "type": "Feature",
  "properties": {
    "gn:admin1_code":"05",
    "gn:asciiname":"Dongqingcun",
    "gn:country_code":"CN",
    "gn:dem":509,
    "gn:feature_class":"P",
    "gn:feature_code":"PPL",
    "gn:name":"Dongqingcun",
    "gn:population":0,
    "gn:timezone":"Asia/Shanghai",
    "iso:country":"CN",
    "name:und_x_variant":[
        "Ta-chiang-kang",
        "Dongqing",
        "\u4e1c\u6e05",
        "Dongqingcun"
    ],
    "name:zho_x_preferred":[
        "\u4e1c\u6e05\u6751"
    ],
    "wof:name":"Dongqingcun",
    "wof:placetype":"locality"
},
  "geometry": {"coordinates":[128.22193999999999,42.77944],"type":"Point"}
}