{
  "type": "Feature",
  "properties": {
    "gn:admin1_code":"8.0",
    "gn:asciiname":"Zonghecun",
    "gn:country_code":"CN",
    "gn:dem":163,
    "gn:feature_class":"P",
    "gn:feature_code":"PPL",
    "gn:name":"Zonghecun",
    "gn:population":0,
    "gn:timezone":"Asia/Shanghai",
    "iso:country":"CN",
    "name:zho_x_preferred":[
        "\u7efc\u5408\u6751"
    ],
    "wof:name":"Zonghecun",
    "wof:placetype":"locality"
},
  "geometry": {"coordinates":[131.40098999999998,45.20976],"type":"Point"}
}