{
  "type": "Feature",
  "properties": {
    "gn:admin1_code":"19.0",
    "gn:asciiname":"Loutaicun",
    "gn:country_code":"CN",
    "gn:dem":3,
    "gn:feature_class":"P",
    "gn:feature_code":"PPL",
    "gn:name":"Loutaicun",
    "gn:population":0,
    "gn:timezone":"Asia/Shanghai",
    "iso:country":"CN",
    "name:zho_x_preferred":[
        "\u697c\u53f0\u6751"
    ],
    "wof:name":"Loutaicun",
    "wof:placetype":"locality"
},
  "geometry": {"coordinates":[122.23795,41.36159],"type":"Point"}
}