{
  "type": "Feature",
  "properties": {
    "gn:admin1_code":"21.0",
    "gn:asciiname":"Pingdaogou",
    "gn:country_code":"CN",
    "gn:dem":1863,
    "gn:feature_class":"P",
    "gn:feature_code":"PPL",
    "gn:name":"Pingdaogou",
    "gn:population":0,
    "gn:timezone":"Asia/Shanghai",
    "iso:country":"CN",
    "name:zho_x_preferred":[
        "\u5e73\u9053\u6c9f"
    ],
    "wof:name":"Pingdaogou",
    "wof:placetype":"locality"
},
  "geometry": {"coordinates":[105.973,36.214],"type":"Point"}
}