{
  "type": "Feature",
  "properties": {
    "gn:admin1_code":"4.0",
    "gn:asciiname":"Changwan",
    "gn:country_code":"CN",
    "gn:dem":3,
    "gn:feature_class":"P",
    "gn:feature_code":"PPL",
    "gn:name":"Changwan",
    "gn:population":0,
    "gn:timezone":"Asia/Shanghai",
    "iso:country":"CN",
    "name:zho_x_preferred":[
        "Changwan"
    ],
    "name:zho_x_variant":[
        "\u957f\u5f2f"
    ],
    "wof:name":"Changwan",
    "wof:placetype":"locality"
},
  "geometry": {"coordinates":[121.34811999999999,31.90504],"type":"Point"}
}