{
  "type": "Feature",
  "properties": {
    "gn:admin1_code":"20.0",
    "gn:asciiname":"Jike Tengdi",
    "gn:country_code":"CN",
    "gn:dem":317,
    "gn:feature_class":"P",
    "gn:feature_code":"PPL",
    "gn:name":"Jike Tengdi",
    "gn:population":0,
    "gn:timezone":"Asia/Shanghai",
    "iso:country":"CN",
    "name:zho_x_preferred":[
        "\u5409\u514b\u817e\u5730"
    ],
    "wof:name":"Jike Tengdi",
    "wof:placetype":"locality"
},
  "geometry": {"coordinates":[123.69945,49.10869],"type":"Point"}
}