{
  "type": "Feature",
  "properties": {
    "gn:admin1_code":"26.0",
    "gn:asciiname":"Shigongping",
    "gn:country_code":"CN",
    "gn:dem":1081,
    "gn:feature_class":"P",
    "gn:feature_code":"PPL",
    "gn:name":"Shigongping",
    "gn:population":0,
    "gn:timezone":"Asia/Shanghai",
    "iso:country":"CN",
    "name:zho_x_preferred":[
        "\u77f3\u62f1\u576a"
    ],
    "wof:name":"Shigongping",
    "wof:placetype":"locality"
},
  "geometry": {"coordinates":[108.01143999999999,32.17954],"type":"Point"}
}