{
  "type": "Feature",
  "properties": {
    "gn:admin1_code":"30",
    "gn:asciiname":"Qiufengdong",
    "gn:country_code":"CN",
    "gn:dem":50,
    "gn:feature_class":"P",
    "gn:feature_code":"PPL",
    "gn:name":"Qiufengdong",
    "gn:population":0,
    "gn:timezone":"Asia/Shanghai",
    "iso:country":"CN",
    "name:zho_x_preferred":[
        "\u79cb\u98ce\u6d1e"
    ],
    "wof:name":"Qiufengdong",
    "wof:placetype":"locality"
},
  "geometry": {"coordinates":[113.54702,23.38953],"type":"Point"}
}