{
  "type": "Feature",
  "properties": {
    "gn:admin1_code":"16.0",
    "gn:asciiname":"Nanxiong",
    "gn:country_code":"CN",
    "gn:dem":1060,
    "gn:feature_class":"P",
    "gn:feature_code":"PPL",
    "gn:name":"Nanxiong",
    "gn:population":0,
    "gn:timezone":"Asia/Shanghai",
    "iso:country":"CN",
    "name:ara_x_preferred":[
        "\u0646\u0627\u0646\u0634\u064a\u0627\u0646\u063a"
    ],
    "name:ces_x_preferred":[
        "Nan-siung"
    ],
    "name:deu_x_preferred":[
        "Nanxiong"
    ],
    "name:fas_x_preferred":[
        "\u0646\u0627\u0646\u0634\u06cc\u0627\u0646\u06af"
    ],
    "name:fra_x_preferred":[
        "Nanxiong"
    ],
    "name:hak_x_preferred":[
        "N\u00e0m-hi\u00f9ng-s\u1e73"
    ],
    "name:ita_x_preferred":[
        "Nanxiong"
    ],
    "name:jpn_x_preferred":[
        "\u5357\u96c4\u5e02"
    ],
    "name:kik_x_preferred":[
        "Nanxiong"
    ],
    "name:kor_x_preferred":[
        "\ub09c\uc29d\uc2dc"
    ],
    "name:mwl_x_preferred":[
        "Nanxiong"
    ],
    "name:nld_x_preferred":[
        "Nanxiong"
    ],
    "name:nor_x_preferred":[
        "Nanxiong"
    ],
    "name:pam_x_preferred":[
        "Nanxiong"
    ],
    "name:pnb_x_preferred":[
        "\u0646\u0627\u0646\u0633\u06cc \u0627\u0648\u0646\u06af"
    ],
    "name:swe_x_preferred":[
        "Nanxiong"
    ],
    "name:urd_x_preferred":[
        "\u0646\u0627\u0646\u0634\u06cc\u0648\u0646\u06af"
    ],
    "name:vie_x_preferred":[
        "Nam H\u00f9ng"
    ],
    "name:zho_x_preferred":[
        "\u5357\u718a"
    ],
    "name:zho_x_variant":[
        "\u5357\u96c4\u5e02"
    ],
    "wof:name":"Nanxiong",
    "wof:placetype":"locality"
},
  "geometry": {"coordinates":[105.94499999999999,24.5285],"type":"Point"}
}