{
  "type": "Feature",
  "properties": {
    "gn:admin1_code":"15.0",
    "gn:asciiname":"Yaoping",
    "gn:country_code":"CN",
    "gn:dem":2083,
    "gn:feature_class":"P",
    "gn:feature_code":"PPL",
    "gn:name":"Yaoping",
    "gn:population":0,
    "gn:timezone":"Asia/Shanghai",
    "iso:country":"CN",
    "name:zho_x_preferred":[
        "\u7a91\u576a"
    ],
    "wof:name":"Yaoping",
    "wof:placetype":"locality"
},
  "geometry": {"coordinates":[104.048,35.3179],"type":"Point"}
}