{
  "type": "Feature",
  "properties": {
    "gn:admin1_code":"20.0",
    "gn:asciiname":"Chulundariga",
    "gn:country_code":"CN",
    "gn:dem":917,
    "gn:feature_class":"P",
    "gn:feature_code":"PPL",
    "gn:name":"Chulundariga",
    "gn:population":0,
    "gn:timezone":"Asia/Shanghai",
    "iso:country":"CN",
    "name:zho_x_preferred":[
        "\u695a\u4f26\u8fbe\u65e5\u5c15"
    ],
    "wof:name":"Chulundariga",
    "wof:placetype":"locality"
},
  "geometry": {"coordinates":[101.30710000000001,42.16795],"type":"Point"}
}