{
  "type": "Feature",
  "properties": {
    "gn:admin1_code":"6.0",
    "gn:asciiname":"Sairenguo",
    "gn:country_code":"CN",
    "gn:dem":3764,
    "gn:feature_class":"P",
    "gn:feature_code":"PPL",
    "gn:name":"Sairenguo",
    "gn:population":0,
    "gn:timezone":"Asia/Urumqi",
    "iso:country":"CN",
    "name:zho_x_preferred":[
        "\u8d5b\u4efb\u679c"
    ],
    "wof:name":"Sairenguo",
    "wof:placetype":"locality"
},
  "geometry": {"coordinates":[96.82383,32.24863],"type":"Point"}
}