{
  "type": "Feature",
  "properties": {
    "gn:admin1_code":"18",
    "gn:asciiname":"Zaoduwan",
    "gn:country_code":"CN",
    "gn:dem":781,
    "gn:feature_class":"P",
    "gn:feature_code":"PPL",
    "gn:name":"Zaoduwan",
    "gn:population":0,
    "gn:timezone":"Asia/Shanghai",
    "iso:country":"CN",
    "name:zho_x_preferred":[
        "\u65e9\u6e21\u6e7e"
    ],
    "wof:name":"Zaoduwan",
    "wof:placetype":"locality"
},
  "geometry": {"coordinates":[108.11199999999999,27.5998],"type":"Point"}
}