{
  "type": "Feature",
  "properties": {
    "gn:admin1_code":"18",
    "gn:asciiname":"Gamu",
    "gn:country_code":"CN",
    "gn:dem":1504,
    "gn:feature_class":"P",
    "gn:feature_code":"PPL",
    "gn:name":"Gamu",
    "gn:population":0,
    "gn:timezone":"Asia/Shanghai",
    "iso:country":"CN",
    "name:zho_x_preferred":[
        "\u560e\u6728"
    ],
    "wof:name":"Gamu",
    "wof:placetype":"locality"
},
  "geometry": {"coordinates":[106.059,27.2746],"type":"Point"}
}