{
  "type": "Feature",
  "properties": {
    "gn:admin1_code":"30.0",
    "gn:asciiname":"Leigongtian",
    "gn:country_code":"CN",
    "gn:dem":186,
    "gn:feature_class":"P",
    "gn:feature_code":"PPL",
    "gn:name":"Leigongtian",
    "gn:population":0,
    "gn:timezone":"Asia/Shanghai",
    "iso:country":"CN",
    "name:zho_x_preferred":[
        "\u96f7\u516c\u7530"
    ],
    "wof:name":"Leigongtian",
    "wof:placetype":"locality"
},
  "geometry": {"coordinates":[112.06283000000001,23.01513],"type":"Point"}
}