{
  "type": "Feature",
  "properties": {
    "gn:admin1_code":"26.0",
    "gn:asciiname":"Qunxingcun",
    "gn:country_code":"CN",
    "gn:dem":468,
    "gn:feature_class":"P",
    "gn:feature_code":"PPL",
    "gn:name":"Qunxingcun",
    "gn:population":0,
    "gn:timezone":"Asia/Shanghai",
    "iso:country":"CN",
    "name:zho_x_preferred":[
        "\u7fa4\u5174\u6751"
    ],
    "wof:name":"Qunxingcun",
    "wof:placetype":"locality"
},
  "geometry": {"coordinates":[108.18814999999999,34.1074],"type":"Point"}
}