{
  "type": "Feature",
  "properties": {
    "gn:admin1_code":"2",
    "gn:asciiname":"Zaotou",
    "gn:country_code":"CN",
    "gn:dem":536,
    "gn:feature_class":"P",
    "gn:feature_code":"PPL",
    "gn:name":"Zaotou",
    "gn:population":0,
    "gn:timezone":"Asia/Shanghai",
    "iso:country":"CN",
    "name:und_x_variant":[
        "\u7076\u5934"
    ],
    "wof:name":"Zaotou",
    "wof:placetype":"locality"
},
  "geometry": {"coordinates":[119.67889,29.20694],"type":"Point"}
}