{
  "type": "Feature",
  "properties": {
    "gn:admin1_code":"24.0",
    "gn:asciiname":"Xiqiaosi",
    "gn:country_code":"CN",
    "gn:dem":1111,
    "gn:feature_class":"P",
    "gn:feature_code":"PPL",
    "gn:name":"Xiqiaosi",
    "gn:population":0,
    "gn:timezone":"Asia/Shanghai",
    "iso:country":"CN",
    "name:zho_x_preferred":[
        "\u897f\u6865\u5bfa"
    ],
    "wof:name":"Xiqiaosi",
    "wof:placetype":"locality"
},
  "geometry": {"coordinates":[112.20504,36.4063],"type":"Point"}
}