{
  "type": "Feature",
  "properties": {
    "gn:admin1_code":"8.0",
    "gn:asciiname":"Qinjiancun",
    "gn:country_code":"CN",
    "gn:dem":228,
    "gn:feature_class":"P",
    "gn:feature_code":"PPL",
    "gn:name":"Qinjiancun",
    "gn:population":0,
    "gn:timezone":"Asia/Shanghai",
    "iso:country":"CN",
    "name:zho_x_preferred":[
        "\u52e4\u4fed\u6751"
    ],
    "wof:name":"Qinjiancun",
    "wof:placetype":"locality"
},
  "geometry": {"coordinates":[126.58174,47.73803],"type":"Point"}
}