{
  "type": "Feature",
  "properties": {
    "gn:admin1_code":"12.0",
    "gn:asciiname":"Niefan",
    "gn:country_code":"CN",
    "gn:dem":24,
    "gn:feature_class":"P",
    "gn:feature_code":"PPL",
    "gn:name":"Niefan",
    "gn:population":0,
    "gn:timezone":"Asia/Shanghai",
    "iso:country":"CN",
    "name:zho_x_preferred":[
        "Niefan"
    ],
    "name:zho_x_variant":[
        "\u8042\u6a0a"
    ],
    "wof:name":"Niefan",
    "wof:placetype":"locality"
},
  "geometry": {"coordinates":[114.27404,29.98782000000001],"type":"Point"}
}