{
  "type": "Feature",
  "properties": {
    "gn:admin1_code":"9.0",
    "gn:asciiname":"Xiangzishu",
    "gn:country_code":"CN",
    "gn:dem":107,
    "gn:feature_class":"P",
    "gn:feature_code":"PPL",
    "gn:name":"Xiangzishu",
    "gn:population":0,
    "gn:timezone":"Asia/Shanghai",
    "iso:country":"CN",
    "name:zho_x_preferred":[
        "\u6a61\u5b50\u6811"
    ],
    "wof:name":"Xiangzishu",
    "wof:placetype":"locality"
},
  "geometry": {"coordinates":[112.47320999999999,32.72799000000001],"type":"Point"}
}