{
  "type": "Feature",
  "properties": {
    "gn:admin1_code":"11.0",
    "gn:asciiname":"Huomatang",
    "gn:country_code":"CN",
    "gn:dem":257,
    "gn:feature_class":"P",
    "gn:feature_code":"PPL",
    "gn:name":"Huomatang",
    "gn:population":0,
    "gn:timezone":"Asia/Shanghai",
    "iso:country":"CN",
    "name:zho_x_preferred":[
        "\u706b\u9a6c\u5858"
    ],
    "wof:name":"Huomatang",
    "wof:placetype":"locality"
},
  "geometry": {"coordinates":[110.12796000000002,27.65559],"type":"Point"}
}