{
  "type": "Feature",
  "properties": {
    "gn:admin1_code":"2.0",
    "gn:asciiname":"Nanzhou",
    "gn:country_code":"CN",
    "gn:dem":135,
    "gn:feature_class":"P",
    "gn:feature_code":"PPL",
    "gn:name":"Nanzhou",
    "gn:population":0,
    "gn:timezone":"Asia/Shanghai",
    "iso:country":"CN",
    "name:deu_x_preferred":[
        "Nanzhou"
    ],
    "name:zho_x_preferred":[
        "\u5357\u5468"
    ],
    "wof:name":"Nanzhou",
    "wof:placetype":"locality"
},
  "geometry": {"coordinates":[118.7632,29.426],"type":"Point"}
}