{
  "type": "Feature",
  "properties": {
    "gn:admin1_code":"3.0",
    "gn:asciiname":"Jilinzui",
    "gn:country_code":"CN",
    "gn:dem":52,
    "gn:feature_class":"P",
    "gn:feature_code":"PPL",
    "gn:name":"Jilinzui",
    "gn:population":0,
    "gn:timezone":"Asia/Shanghai",
    "iso:country":"CN",
    "name:und_x_variant":[
        "\u9e21\u6797\u5480"
    ],
    "wof:name":"Jilinzui",
    "wof:placetype":"locality"
},
  "geometry": {"coordinates":[116.17619000000001,28.07218],"type":"Point"}
}