{
  "type": "Feature",
  "properties": {
    "gn:admin1_code":"26.0",
    "gn:asciiname":"Dongyangcun",
    "gn:country_code":"CN",
    "gn:dem":966,
    "gn:feature_class":"P",
    "gn:feature_code":"PPL",
    "gn:name":"Dongyangcun",
    "gn:population":0,
    "gn:timezone":"Asia/Shanghai",
    "iso:country":"CN",
    "name:zho_x_preferred":[
        "\u4e1c\u6768\u6751"
    ],
    "wof:name":"Dongyangcun",
    "wof:placetype":"locality"
},
  "geometry": {"coordinates":[110.27330000000001,34.05269000000001],"type":"Point"}
}