{
  "type": "Feature",
  "properties": {
    "gn:admin1_code":"11.0",
    "gn:asciiname":"Honghu",
    "gn:country_code":"CN",
    "gn:dem":28,
    "gn:feature_class":"P",
    "gn:feature_code":"PPL",
    "gn:name":"Honghu",
    "gn:population":0,
    "gn:timezone":"Asia/Shanghai",
    "iso:country":"CN",
    "name:ceb_x_preferred":[
        "Honghu Shi"
    ],
    "name:deu_x_preferred":[
        "Honghu"
    ],
    "name:fas_x_preferred":[
        "\u0647\u0627\u0646\u06af\u0647\u0648"
    ],
    "name:fra_x_preferred":[
        "Honghu"
    ],
    "name:ita_x_preferred":[
        "Honghu"
    ],
    "name:jpn_x_preferred":[
        "\u6d2a\u6e56\u5e02"
    ],
    "name:kik_x_preferred":[
        "Honghu"
    ],
    "name:kor_x_preferred":[
        "\ud6d9\ud6c4\uc2dc"
    ],
    "name:mlg_x_preferred":[
        "Honghu"
    ],
    "name:nor_x_preferred":[
        "Honghu"
    ],
    "name:pam_x_preferred":[
        "Honghu"
    ],
    "name:pol_x_preferred":[
        "Honghu"
    ],
    "name:swe_x_preferred":[
        "Honghu"
    ],
    "name:vie_x_preferred":[
        "H\u1ed3ng H\u1ed3"
    ],
    "name:war_x_preferred":[
        "Honghu"
    ],
    "name:zho_x_preferred":[
        "\u7ea2\u6e56"
    ],
    "name:zho_x_variant":[
        "\u6d2a\u6e56\u5e02"
    ],
    "wof:name":"Honghu",
    "wof:placetype":"locality"
},
  "geometry": {"coordinates":[112.54742,28.78345],"type":"Point"}
}