{
  "type": "Feature",
  "properties": {
    "gn:admin1_code":"11.0",
    "gn:asciiname":"Wachangli",
    "gn:country_code":"CN",
    "gn:dem":860,
    "gn:feature_class":"P",
    "gn:feature_code":"PPL",
    "gn:name":"Wachangli",
    "gn:population":0,
    "gn:timezone":"Asia/Shanghai",
    "iso:country":"CN",
    "name:zho_x_preferred":[
        "\u74e6\u5382\u91cc"
    ],
    "wof:name":"Wachangli",
    "wof:placetype":"locality"
},
  "geometry": {"coordinates":[113.92529,26.04007],"type":"Point"}
}