{
  "type": "Feature",
  "properties": {
    "gn:admin1_code":"11.0",
    "gn:asciiname":"Luositang",
    "gn:country_code":"CN",
    "gn:dem":75,
    "gn:feature_class":"P",
    "gn:feature_code":"PPL",
    "gn:name":"Luositang",
    "gn:population":0,
    "gn:timezone":"Asia/Shanghai",
    "iso:country":"CN",
    "name:zho_x_preferred":[
        "\u87ba\u4e1d\u5858"
    ],
    "wof:name":"Luositang",
    "wof:placetype":"locality"
},
  "geometry": {"coordinates":[113.12392,28.23504],"type":"Point"}
}