{
  "type": "Feature",
  "properties": {
    "gn:admin1_code":"3.0",
    "gn:asciiname":"Zhutang",
    "gn:country_code":"CN",
    "gn:dem":60,
    "gn:feature_class":"P",
    "gn:feature_code":"PPL",
    "gn:name":"Zhutang",
    "gn:population":0,
    "gn:timezone":"Asia/Shanghai",
    "iso:country":"CN",
    "name:deu_x_preferred":[
        "Zhutang"
    ],
    "name:und_x_variant":[
        "\u6e1a\u5858"
    ],
    "wof:name":"Zhutang",
    "wof:placetype":"locality"
},
  "geometry": {"coordinates":[115.38624,27.93878],"type":"Point"}
}