{
  "type": "Feature",
  "properties": {
    "gn:admin1_code":"12.0",
    "gn:asciiname":"Shazhouyuan",
    "gn:country_code":"CN",
    "gn:dem":28,
    "gn:feature_class":"P",
    "gn:feature_code":"PPL",
    "gn:name":"Shazhouyuan",
    "gn:population":0,
    "gn:timezone":"Asia/Shanghai",
    "iso:country":"CN",
    "name:zho_x_preferred":[
        "\u6c99\u6d32\u57b8"
    ],
    "wof:name":"Shazhouyuan",
    "wof:placetype":"locality"
},
  "geometry": {"coordinates":[112.75893000000001,29.99828],"type":"Point"}
}