{
  "type": "Feature",
  "properties": {
    "gn:admin1_code":"19.0",
    "gn:asciiname":"Banlashancun",
    "gn:country_code":"CN",
    "gn:dem":92,
    "gn:feature_class":"P",
    "gn:feature_code":"PPL",
    "gn:name":"Banlashancun",
    "gn:population":0,
    "gn:timezone":"Asia/Shanghai",
    "iso:country":"CN",
    "name:und_x_variant":[
        "Banlashan"
    ],
    "name:zho_x_preferred":[
        "\u534a\u62c9\u5c71\u6751"
    ],
    "wof:name":"Banlashancun",
    "wof:placetype":"locality"
},
  "geometry": {"coordinates":[122.078,39.8118],"type":"Point"}
}