{
  "type": "Feature",
  "properties": {
    "gn:admin1_code":"25",
    "gn:asciiname":"Beibao Beicun",
    "gn:country_code":"CN",
    "gn:dem":40,
    "gn:feature_class":"P",
    "gn:feature_code":"PPL",
    "gn:name":"Beibao Beicun",
    "gn:population":0,
    "gn:timezone":"Asia/Shanghai",
    "iso:country":"CN",
    "name:zho_x_preferred":[
        "\u5317\u8584\u5317\u6751"
    ],
    "wof:name":"Beibao Beicun",
    "wof:placetype":"locality"
},
  "geometry": {"coordinates":[116.76000000000001,35.2013],"type":"Point"}
}