{
  "type": "Feature",
  "properties": {
    "gn:admin1_code":"29.0",
    "gn:asciiname":"Nuodao",
    "gn:country_code":"CN",
    "gn:dem":1258,
    "gn:feature_class":"P",
    "gn:feature_code":"PPL",
    "gn:name":"Nuodao",
    "gn:population":0,
    "gn:timezone":"Asia/Shanghai",
    "iso:country":"CN",
    "name:zho_x_preferred":[
        "\u7cef\u5c9b"
    ],
    "wof:name":"Nuodao",
    "wof:placetype":"locality"
},
  "geometry": {"coordinates":[99.7764,22.184],"type":"Point"}
}