{
  "type": "Feature",
  "properties": {
    "gn:admin1_code":"22.0",
    "gn:asciiname":"Baita Nangou",
    "gn:country_code":"CN",
    "gn:dem":595,
    "gn:feature_class":"P",
    "gn:feature_code":"PPL",
    "gn:name":"Baita Nangou",
    "gn:population":0,
    "gn:timezone":"Asia/Shanghai",
    "iso:country":"CN",
    "name:zho_x_preferred":[
        "\u767d\u5854\u5357\u6c9f"
    ],
    "wof:name":"Baita Nangou",
    "wof:placetype":"locality"
},
  "geometry": {"coordinates":[116.35982,40.67303],"type":"Point"}
}