{
  "type": "Feature",
  "properties": {
    "gn:admin1_code":"32.0",
    "gn:asciiname":"Dashiba",
    "gn:country_code":"CN",
    "gn:dem":406,
    "gn:feature_class":"P",
    "gn:feature_code":"PPL",
    "gn:name":"Dashiba",
    "gn:population":0,
    "gn:timezone":"Asia/Shanghai",
    "iso:country":"CN",
    "name:zho_x_preferred":[
        "\u6253\u77f3\u575d"
    ],
    "wof:name":"Dashiba",
    "wof:placetype":"locality"
},
  "geometry": {"coordinates":[105.34999999999999,31.0862],"type":"Point"}
}