{
  "type": "Feature",
  "properties": {
    "gn:admin1_code":"3",
    "gn:asciiname":"Luoshi",
    "gn:country_code":"CN",
    "gn:dem":37,
    "gn:feature_class":"P",
    "gn:feature_code":"PPLA4",
    "gn:name":"Luoshi",
    "gn:population":0,
    "gn:timezone":"Asia/Shanghai",
    "iso:country":"CN",
    "name:und_x_variant":[
        "\u6d1b\u5e02",
        "Luoshi Zhen",
        "\u6d1b\u5e02\u9547"
    ],
    "wof:name":"Luoshi",
    "wof:placetype":"locality"
},
  "geometry": {"coordinates":[115.82965,27.99225],"type":"Point"}
}