{
  "type": "Feature",
  "properties": {
    "gn:admin1_code":"19.0",
    "gn:asciiname":"Tuchengzicun",
    "gn:country_code":"CN",
    "gn:dem":107,
    "gn:feature_class":"P",
    "gn:feature_code":"PPL",
    "gn:name":"Tuchengzicun",
    "gn:population":0,
    "gn:timezone":"Asia/Shanghai",
    "iso:country":"CN",
    "name:zho_x_preferred":[
        "\u571f\u57ce\u5b50\u6751"
    ],
    "wof:name":"Tuchengzicun",
    "wof:placetype":"locality"
},
  "geometry": {"coordinates":[124.61005,40.54575],"type":"Point"}
}