{
  "type": "Feature",
  "properties": {
    "gn:admin1_code":"15.0",
    "gn:asciiname":"Youfangping",
    "gn:country_code":"CN",
    "gn:dem":2061,
    "gn:feature_class":"P",
    "gn:feature_code":"PPL",
    "gn:name":"Youfangping",
    "gn:population":0,
    "gn:timezone":"Asia/Shanghai",
    "iso:country":"CN",
    "name:zho_x_preferred":[
        "\u6cb9\u574a\u576a"
    ],
    "wof:name":"Youfangping",
    "wof:placetype":"locality"
},
  "geometry": {"coordinates":[104.61,35.4089],"type":"Point"}
}