{
  "type": "Feature",
  "properties": {
    "gn:admin1_code":"8.0",
    "gn:asciiname":"Shiwulidi Houdu",
    "gn:country_code":"CN",
    "gn:dem":351,
    "gn:feature_class":"P",
    "gn:feature_code":"PPL",
    "gn:name":"Shiwulidi Houdu",
    "gn:population":0,
    "gn:timezone":"Asia/Shanghai",
    "iso:country":"CN",
    "name:zho_x_preferred":[
        "\u5341\u4e94\u91cc\u5730\u540e\u5835"
    ],
    "wof:name":"Shiwulidi Houdu",
    "wof:placetype":"locality"
},
  "geometry": {"coordinates":[128.13631000000001,44.90019],"type":"Point"}
}