{
  "type": "Feature",
  "properties": {
    "gn:admin1_code":"19.0",
    "gn:asciiname":"Donghuitong",
    "gn:country_code":"CN",
    "gn:dem":187,
    "gn:feature_class":"P",
    "gn:feature_code":"PPL",
    "gn:name":"Donghuitong",
    "gn:population":0,
    "gn:timezone":"Asia/Shanghai",
    "iso:country":"CN",
    "name:zho_x_preferred":[
        "\u4e1c\u7070\u901a"
    ],
    "wof:name":"Donghuitong",
    "wof:placetype":"locality"
},
  "geometry": {"coordinates":[121.57544,42.06442],"type":"Point"}
}