{
  "type": "Feature",
  "properties": {
    "gn:admin1_code":"22.0",
    "gn:asciiname":"Chanfangcun",
    "gn:country_code":"CN",
    "gn:dem":762,
    "gn:feature_class":"P",
    "gn:feature_code":"PPL",
    "gn:name":"Chanfangcun",
    "gn:population":0,
    "gn:timezone":"Asia/Shanghai",
    "iso:country":"CN",
    "name:zho_x_preferred":[
        "\u7985\u623f\u6751"
    ],
    "wof:name":"Chanfangcun",
    "wof:placetype":"locality"
},
  "geometry": {"coordinates":[115.99386,40.07592],"type":"Point"}
}