{
  "type": "Feature",
  "properties": {
    "gn:admin1_code":"24.0",
    "gn:asciiname":"Yong'an",
    "gn:country_code":"CN",
    "gn:dem":674,
    "gn:feature_class":"P",
    "gn:feature_code":"PPL",
    "gn:name":"Yong\u2019an",
    "gn:population":0,
    "gn:timezone":"Asia/Shanghai",
    "iso:country":"CN",
    "name:und_x_variant":[
        "Yung-an",
        "Yong\u2019an"
    ],
    "wof:name":"Yong'an",
    "wof:placetype":"locality"
},
  "geometry": {"coordinates":[112.47221999999999,35.56],"type":"Point"}
}