{
  "type": "Feature",
  "properties": {
    "gn:admin1_code":"30",
    "gn:asciiname":"Yangpocun",
    "gn:country_code":"CN",
    "gn:dem":20,
    "gn:feature_class":"P",
    "gn:feature_code":"PPL",
    "gn:name":"Yangpocun",
    "gn:population":0,
    "gn:timezone":"Asia/Urumqi",
    "iso:country":"CN",
    "name:zho_x_preferred":[
        "\u9633\u5761\u6751"
    ],
    "wof:name":"Yangpocun",
    "wof:placetype":"locality"
},
  "geometry": {"coordinates":[110.01531,20.78028],"type":"Point"}
}