{
  "type": "Feature",
  "properties": {
    "gn:admin1_code":"14.0",
    "gn:asciiname":"Chenba",
    "gn:country_code":"CN",
    "gn:dem":3995,
    "gn:feature_class":"P",
    "gn:feature_code":"PPL",
    "gn:name":"Chenba",
    "gn:population":0,
    "gn:timezone":"Asia/Urumqi",
    "iso:country":"CN",
    "name:zho_x_preferred":[
        "\u9648\u5df4"
    ],
    "wof:name":"Chenba",
    "wof:placetype":"locality"
},
  "geometry": {"coordinates":[90.4541,29.21842],"type":"Point"}
}