{
  "type": "Feature",
  "properties": {
    "gn:admin1_code":"16.0",
    "gn:asciiname":"Longyanshan",
    "gn:country_code":"CN",
    "gn:dem":21,
    "gn:feature_class":"P",
    "gn:feature_code":"PPL",
    "gn:name":"Longyanshan",
    "gn:population":0,
    "gn:timezone":"Asia/Shanghai",
    "iso:country":"CN",
    "name:zho_x_preferred":[
        "\u9f99\u773c\u5c71"
    ],
    "wof:name":"Longyanshan",
    "wof:placetype":"locality"
},
  "geometry": {"coordinates":[108.761,21.7078],"type":"Point"}
}