{
  "type": "Feature",
  "properties": {
    "gn:admin1_code":"32.0",
    "gn:asciiname":"Amipu",
    "gn:country_code":"CN",
    "gn:dem":1836,
    "gn:feature_class":"P",
    "gn:feature_code":"PPL",
    "gn:name":"Amipu",
    "gn:population":0,
    "gn:timezone":"Asia/Shanghai",
    "iso:country":"CN",
    "name:zho_x_preferred":[
        "\u963f\u7c73\u666e"
    ],
    "wof:name":"Amipu",
    "wof:placetype":"locality"
},
  "geometry": {"coordinates":[103.38500000000001,28.3072],"type":"Point"}
}