{
  "type": "Feature",
  "properties": {
    "gn:admin1_code":"18.0",
    "gn:asciiname":"Shulinpo",
    "gn:country_code":"CN",
    "gn:dem":742,
    "gn:feature_class":"P",
    "gn:feature_code":"PPL",
    "gn:name":"Shulinpo",
    "gn:population":0,
    "gn:timezone":"Asia/Shanghai",
    "iso:country":"CN",
    "name:zho_x_preferred":[
        "\u6811\u6797\u5761"
    ],
    "wof:name":"Shulinpo",
    "wof:placetype":"locality"
},
  "geometry": {"coordinates":[108.45399999999999,27.5248],"type":"Point"}
}