{
  "type": "Feature",
  "properties": {
    "gn:admin1_code":"7.0",
    "gn:asciiname":"Hongliao",
    "gn:country_code":"CN",
    "gn:dem":678,
    "gn:feature_class":"P",
    "gn:feature_code":"PPL",
    "gn:name":"Hongliao",
    "gn:population":0,
    "gn:timezone":"Asia/Shanghai",
    "iso:country":"CN",
    "name:zho_x_preferred":[
        "\u7ea2\u5bee"
    ],
    "wof:name":"Hongliao",
    "wof:placetype":"locality"
},
  "geometry": {"coordinates":[116.05410999999999,25.62164],"type":"Point"}
}