{
  "type": "Feature",
  "properties": {
    "gn:admin1_code":"26.0",
    "gn:asciiname":"Gaobangjincun",
    "gn:country_code":"CN",
    "gn:dem":1146,
    "gn:feature_class":"P",
    "gn:feature_code":"PPL",
    "gn:name":"Gaobangjincun",
    "gn:population":0,
    "gn:timezone":"Asia/Shanghai",
    "iso:country":"CN",
    "name:zho_x_preferred":[
        "\u9ad8\u90a6\u8fdb\u6751"
    ],
    "wof:name":"Gaobangjincun",
    "wof:placetype":"locality"
},
  "geometry": {"coordinates":[110.18940000000001,38.06684],"type":"Point"}
}