{
  "type": "Feature",
  "properties": {
    "gn:admin1_code":"3.0",
    "gn:asciiname":"Xuexing",
    "gn:country_code":"CN",
    "gn:dem":426,
    "gn:feature_class":"P",
    "gn:feature_code":"PPL",
    "gn:name":"Xuexing",
    "gn:population":0,
    "gn:timezone":"Asia/Shanghai",
    "iso:country":"CN",
    "name:und_x_variant":[
        "\u5b66\u5f62"
    ],
    "wof:name":"Xuexing",
    "wof:placetype":"locality"
},
  "geometry": {"coordinates":[115.84201000000002,25.24006],"type":"Point"}
}