{
  "type": "Feature",
  "properties": {
    "gn:admin1_code":"29.0",
    "gn:asciiname":"Shagouyan",
    "gn:country_code":"CN",
    "gn:dem":1833,
    "gn:feature_class":"P",
    "gn:feature_code":"PPL",
    "gn:name":"Shagouyan",
    "gn:population":0,
    "gn:timezone":"Asia/Shanghai",
    "iso:country":"CN",
    "name:zho_x_preferred":[
        "\u6c99\u6c9f\u5ca9"
    ],
    "wof:name":"Shagouyan",
    "wof:placetype":"locality"
},
  "geometry": {"coordinates":[103.767,25.065],"type":"Point"}
}