{
  "type": "Feature",
  "properties": {
    "gn:admin1_code":"3.0",
    "gn:asciiname":"Tianbei",
    "gn:country_code":"CN",
    "gn:dem":220,
    "gn:feature_class":"P",
    "gn:feature_code":"PPL",
    "gn:name":"Tianbei",
    "gn:population":0,
    "gn:timezone":"Asia/Shanghai",
    "iso:country":"CN",
    "name:und_x_variant":[
        "\u7530\u80cc"
    ],
    "wof:name":"Tianbei",
    "wof:placetype":"locality"
},
  "geometry": {"coordinates":[116.12137,26.00832],"type":"Point"}
}