{
  "type": "Feature",
  "properties": {
    "gn:admin1_code":"16.0",
    "gn:asciiname":"Neiqin",
    "gn:country_code":"CN",
    "gn:dem":410,
    "gn:feature_class":"P",
    "gn:feature_code":"PPL",
    "gn:name":"Neiqin",
    "gn:population":0,
    "gn:timezone":"Asia/Shanghai",
    "iso:country":"CN",
    "name:zho_x_preferred":[
        "\u5185\u94a6"
    ],
    "wof:name":"Neiqin",
    "wof:placetype":"locality"
},
  "geometry": {"coordinates":[107.40300000000001,23.1259],"type":"Point"}
}