{
  "type": "Feature",
  "properties": {
    "gn:admin1_code":"8.0",
    "gn:asciiname":"Majiajiecun",
    "gn:country_code":"CN",
    "gn:dem":75,
    "gn:feature_class":"P",
    "gn:feature_code":"PPL",
    "gn:name":"Majiajiecun",
    "gn:population":0,
    "gn:timezone":"Asia/Shanghai",
    "iso:country":"CN",
    "name:zho_x_preferred":[
        "\u9a6c\u5bb6\u8857\u6751"
    ],
    "wof:name":"Majiajiecun",
    "wof:placetype":"locality"
},
  "geometry": {"coordinates":[131.75892999999999,46.68599],"type":"Point"}
}