{
  "type": "Feature",
  "properties": {
    "gn:admin1_code":"29.0",
    "gn:asciiname":"Pujiazhai",
    "gn:country_code":"CN",
    "gn:dem":2072,
    "gn:feature_class":"P",
    "gn:feature_code":"PPL",
    "gn:name":"Pujiazhai",
    "gn:population":0,
    "gn:timezone":"Asia/Shanghai",
    "iso:country":"CN",
    "name:zho_x_preferred":[
        "\u666e\u5bb6\u5be8"
    ],
    "wof:name":"Pujiazhai",
    "wof:placetype":"locality"
},
  "geometry": {"coordinates":[99.7976,24.7238],"type":"Point"}
}