{
  "type": "Feature",
  "properties": {
    "gn:admin1_code":"4.0",
    "gn:asciiname":"Wangtuan",
    "gn:country_code":"CN",
    "gn:dem":4,
    "gn:feature_class":"P",
    "gn:feature_code":"PPL",
    "gn:name":"Wangtuan",
    "gn:population":0,
    "gn:timezone":"Asia/Shanghai",
    "iso:country":"CN",
    "name:zho_x_preferred":[
        "Wangtuan"
    ],
    "name:zho_x_variant":[
        "\u738b\u7583"
    ],
    "wof:name":"Wangtuan",
    "wof:placetype":"locality"
},
  "geometry": {"coordinates":[119.07904000000001,34.71593],"type":"Point"}
}