{
  "type": "Feature",
  "properties": {
    "gn:admin1_code":"32.0",
    "gn:asciiname":"Ezhai",
    "gn:country_code":"CN",
    "gn:dem":3271,
    "gn:feature_class":"P",
    "gn:feature_code":"PPL",
    "gn:name":"Ezhai",
    "gn:population":0,
    "gn:timezone":"Asia/Shanghai",
    "iso:country":"CN",
    "name:zho_x_preferred":[
        "\u4fc4\u5be8"
    ],
    "wof:name":"Ezhai",
    "wof:placetype":"locality"
},
  "geometry": {"coordinates":[103.30500000000001,32.3233],"type":"Point"}
}