{
  "type": "Feature",
  "properties": {
    "gn:admin1_code":"16.0",
    "gn:asciiname":"Qilinling",
    "gn:country_code":"CN",
    "gn:dem":35,
    "gn:feature_class":"P",
    "gn:feature_code":"PPL",
    "gn:name":"Qilinling",
    "gn:population":0,
    "gn:timezone":"Asia/Shanghai",
    "iso:country":"CN",
    "name:zho_x_preferred":[
        "\u9e92\u9e9f\u5cad"
    ],
    "wof:name":"Qilinling",
    "wof:placetype":"locality"
},
  "geometry": {"coordinates":[110.182,23.6064],"type":"Point"}
}