{
  "type": "Feature",
  "properties": {
    "gn:admin1_code":"32.0",
    "gn:asciiname":"Jiashikou",
    "gn:country_code":"CN",
    "gn:dem":2131,
    "gn:feature_class":"P",
    "gn:feature_code":"PPL",
    "gn:name":"Jiashikou",
    "gn:population":0,
    "gn:timezone":"Asia/Shanghai",
    "iso:country":"CN",
    "name:zho_x_preferred":[
        "\u7532\u77f3\u53e3"
    ],
    "wof:name":"Jiashikou",
    "wof:placetype":"locality"
},
  "geometry": {"coordinates":[103.084,31.3887],"type":"Point"}
}