{
  "type": "Feature",
  "properties": {
    "gn:admin1_code":"4.0",
    "gn:asciiname":"Xiyan",
    "gn:country_code":"CN",
    "gn:dem":4,
    "gn:feature_class":"P",
    "gn:feature_code":"PPL",
    "gn:name":"Xiyan",
    "gn:population":0,
    "gn:timezone":"Asia/Shanghai",
    "iso:country":"CN",
    "name:ceb_x_preferred":[
        "Xiyan"
    ],
    "name:swe_x_preferred":[
        "Xiyan"
    ],
    "name:zho_x_preferred":[
        "\u897f\u95eb"
    ],
    "wof:name":"Xiyan",
    "wof:placetype":"locality"
},
  "geometry": {"coordinates":[119.63942,32.60483],"type":"Point"}
}