{
  "type": "Feature",
  "properties": {
    "gn:admin1_code":"1.0",
    "gn:asciiname":"Dawancun",
    "gn:country_code":"CN",
    "gn:dem":450,
    "gn:feature_class":"P",
    "gn:feature_code":"PPL",
    "gn:name":"Dawancun",
    "gn:population":0,
    "gn:timezone":"Asia/Shanghai",
    "iso:country":"CN",
    "name:und_x_variant":[
        "Dawan"
    ],
    "name:zho_x_preferred":[
        "\u5927\u6e7e\u6751"
    ],
    "wof:name":"Dawancun",
    "wof:placetype":"locality"
},
  "geometry": {"coordinates":[115.68057,31.33856],"type":"Point"}
}