{
  "type": "Feature",
  "properties": {
    "gn:admin1_code":"32.0",
    "gn:asciiname":"Chenyanshan",
    "gn:country_code":"CN",
    "gn:dem":1171,
    "gn:feature_class":"P",
    "gn:feature_code":"PPL",
    "gn:name":"Chenyanshan",
    "gn:population":0,
    "gn:timezone":"Asia/Shanghai",
    "iso:country":"CN",
    "name:zho_x_preferred":[
        "\u9648\u5ca9\u5c71"
    ],
    "wof:name":"Chenyanshan",
    "wof:placetype":"locality"
},
  "geometry": {"coordinates":[104.768,32.0018],"type":"Point"}
}