{
  "type": "Feature",
  "properties": {
    "gn:admin1_code":"9.0",
    "gn:asciiname":"Gedawang",
    "gn:country_code":"CN",
    "gn:dem":118,
    "gn:feature_class":"P",
    "gn:feature_code":"PPL",
    "gn:name":"Gedawang",
    "gn:population":0,
    "gn:timezone":"Asia/Shanghai",
    "iso:country":"CN",
    "name:zho_x_preferred":[
        "\u572a\u57af\u738b"
    ],
    "wof:name":"Gedawang",
    "wof:placetype":"locality"
},
  "geometry": {"coordinates":[113.37623000000001,34.03379],"type":"Point"}
}