{
  "type": "Feature",
  "properties": {
    "gn:admin1_code":"21.0",
    "gn:asciiname":"Qingshawo",
    "gn:country_code":"CN",
    "gn:dem":1103,
    "gn:feature_class":"P",
    "gn:feature_code":"PPL",
    "gn:name":"Qingshawo",
    "gn:population":0,
    "gn:timezone":"Asia/Shanghai",
    "iso:country":"CN",
    "name:zho_x_preferred":[
        "\u9752\u6c99\u7a9d"
    ],
    "wof:name":"Qingshawo",
    "wof:placetype":"locality"
},
  "geometry": {"coordinates":[106.66,38.796],"type":"Point"}
}