{
  "type": "Feature",
  "properties": {
    "gn:admin1_code":"33.0",
    "gn:asciiname":"Pengdong",
    "gn:country_code":"CN",
    "gn:dem":767,
    "gn:feature_class":"P",
    "gn:feature_code":"PPLA4",
    "gn:name":"Pengdong",
    "gn:population":0,
    "gn:timezone":"Asia/Shanghai",
    "iso:country":"CN",
    "name:und_x_variant":[
        "Pengdong Xiang",
        "Huocaoba"
    ],
    "name:zho_x_preferred":[
        "\u84ec\u4e1c"
    ],
    "name:zho_x_variant":[
        "\u84ec\u4e1c\u4e61",
        "\u706b\u8349\u575d"
    ],
    "wof:name":"Pengdong",
    "wof:placetype":"locality"
},
  "geometry": {"coordinates":[108.82304999999999,29.38621],"type":"Point"}
}