{
  "type": "Feature",
  "properties": {
    "gn:admin1_code":"07",
    "gn:asciiname":"Qiling",
    "gn:country_code":"CN",
    "gn:dem":296,
    "gn:feature_class":"P",
    "gn:feature_code":"PPLA4",
    "gn:name":"Qiling",
    "gn:population":0,
    "gn:timezone":"Asia/Shanghai",
    "iso:country":"CN",
    "name:und_x_variant":[
        "Jingxia",
        "Qiling",
        "Qiling Xiang"
    ],
    "name:zho_x_preferred":[
        "Ch\u2019i-ling"
    ],
    "name:zho_x_variant":[
        "\u5c90\u5cad",
        "\u4e95\u4e0b",
        "\u5c90\u5cad\u4e61",
        "\u5c90\u5cad\u9547"
    ],
    "wof:name":"Qiling",
    "wof:placetype":"locality"
},
  "geometry": {"coordinates":[116.88773999999999,24.67555],"type":"Point"}
}