{
  "type": "Feature",
  "properties": {
    "gn:admin1_code":"4.0",
    "gn:asciiname":"Maowucun",
    "gn:country_code":"CN",
    "gn:dem":0,
    "gn:feature_class":"P",
    "gn:feature_code":"PPL",
    "gn:name":"Maowucun",
    "gn:population":0,
    "gn:timezone":"Asia/Shanghai",
    "iso:country":"CN",
    "name:zho_x_preferred":[
        "\u8306\u5434\u6751"
    ],
    "wof:name":"Maowucun",
    "wof:placetype":"locality"
},
  "geometry": {"coordinates":[119.64471,32.82788],"type":"Point"}
}