{
  "type": "Feature",
  "properties": {
    "gn:admin1_code":"26.0",
    "gn:asciiname":"Shimen",
    "gn:country_code":"CN",
    "gn:dem":1272,
    "gn:feature_class":"P",
    "gn:feature_code":"PPL",
    "gn:name":"Shimen",
    "gn:population":0,
    "gn:timezone":"Asia/Shanghai",
    "iso:country":"CN",
    "name:und_x_variant":[
        "\u77f3\u95e8"
    ],
    "wof:name":"Shimen",
    "wof:placetype":"locality"
},
  "geometry": {"coordinates":[106.85205999999999,33.30279],"type":"Point"}
}