{
  "type": "Feature",
  "properties": {
    "gn:admin1_code":"32.0",
    "gn:asciiname":"Yutai",
    "gn:country_code":"CN",
    "gn:dem":831,
    "gn:feature_class":"P",
    "gn:feature_code":"PPL",
    "gn:name":"Yutai",
    "gn:population":0,
    "gn:timezone":"Asia/Shanghai",
    "iso:country":"CN",
    "name:zho_x_preferred":[
        "\u96e8\u53f0"
    ],
    "wof:name":"Yutai",
    "wof:placetype":"locality"
},
  "geometry": {"coordinates":[108.155,31.6074],"type":"Point"}
}