{
  "type": "Feature",
  "properties": {
    "gn:admin1_code":"26.0",
    "gn:asciiname":"Guojiaping",
    "gn:country_code":"CN",
    "gn:dem":1644,
    "gn:feature_class":"P",
    "gn:feature_code":"PPL",
    "gn:name":"Guojiaping",
    "gn:population":0,
    "gn:timezone":"Asia/Shanghai",
    "iso:country":"CN",
    "name:und_x_variant":[
        "\u90ed\u5bb6\u576a"
    ],
    "wof:name":"Guojiaping",
    "wof:placetype":"locality"
},
  "geometry": {"coordinates":[106.92207000000001,34.0427],"type":"Point"}
}