{
  "type": "Feature",
  "properties": {
    "gn:admin1_code":"14.0",
    "gn:asciiname":"Zhowagoin",
    "gn:country_code":"CN",
    "gn:dem":2654,
    "gn:feature_class":"P",
    "gn:feature_code":"PPLA3",
    "gn:name":"Zhowagoin",
    "gn:population":0,
    "gn:timezone":"Asia/Urumqi",
    "iso:country":"CN",
    "name:ara_x_preferred":[
        "\u062c\u0648\u0627\u063a\u0648\u0627\u0646"
    ],
    "name:bod_x_preferred":[
        "Zhowagoin"
    ],
    "name:fas_x_preferred":[
        "\u0698\u0648\u0627\u06af\u0648\u06cc\u0646"
    ],
    "name:msa_x_preferred":[
        "Zhowagoin"
    ],
    "name:und_x_variant":[
        "Zhuwagen Zhen"
    ],
    "name:zho_x_preferred":[
        "Zhuwagen"
    ],
    "name:zho_x_variant":[
        "\u7af9\u74e6\u6839",
        "Jigong",
        "\u5409\u516c",
        "\u7af9\u74e6\u6839\u9547"
    ],
    "wof:name":"Zhowagoin",
    "wof:placetype":"locality"
},
  "geometry": {"coordinates":[97.45065,28.6591],"type":"Point"}
}