{
  "type": "Feature",
  "properties": {
    "gn:admin1_code":"2",
    "gn:asciiname":"Huangduantou",
    "gn:country_code":"CN",
    "gn:dem":257,
    "gn:feature_class":"P",
    "gn:feature_code":"PPL",
    "gn:name":"Huangduantou",
    "gn:population":0,
    "gn:timezone":"Asia/Shanghai",
    "iso:country":"CN",
    "name:zho_x_preferred":[
        "\u9ec4\u7aef\u5934"
    ],
    "wof:name":"Huangduantou",
    "wof:placetype":"locality"
},
  "geometry": {"coordinates":[119.05667,27.97333],"type":"Point"}
}