{
  "type": "Feature",
  "properties": {
    "gn:admin1_code":"15.0",
    "gn:asciiname":"Songjiachuan",
    "gn:country_code":"CN",
    "gn:dem":1952,
    "gn:feature_class":"P",
    "gn:feature_code":"PPL",
    "gn:name":"Songjiachuan",
    "gn:population":0,
    "gn:timezone":"Asia/Shanghai",
    "iso:country":"CN",
    "name:zho_x_preferred":[
        "\u5b8b\u5bb6\u5ddd"
    ],
    "wof:name":"Songjiachuan",
    "wof:placetype":"locality"
},
  "geometry": {"coordinates":[104.371,35.7208],"type":"Point"}
}