{
  "type": "Feature",
  "properties": {
    "gn:admin1_code":"5.0",
    "gn:asciiname":"Dongfanghongcun",
    "gn:country_code":"CN",
    "gn:dem":208,
    "gn:feature_class":"P",
    "gn:feature_code":"PPL",
    "gn:name":"Dongfanghongcun",
    "gn:population":0,
    "gn:timezone":"Asia/Shanghai",
    "iso:country":"CN",
    "name:zho_x_preferred":[
        "\u4e1c\u65b9\u7ea2\u6751"
    ],
    "wof:name":"Dongfanghongcun",
    "wof:placetype":"locality"
},
  "geometry": {"coordinates":[125.17837,44.53826],"type":"Point"}
}