{
  "type": "Feature",
  "properties": {
    "gn:admin1_code":"19.0",
    "gn:asciiname":"Dongzhangzi",
    "gn:country_code":"CN",
    "gn:dem":524,
    "gn:feature_class":"P",
    "gn:feature_code":"PPL",
    "gn:name":"Dongzhangzi",
    "gn:population":0,
    "gn:timezone":"Asia/Shanghai",
    "iso:country":"CN",
    "name:zho_x_preferred":[
        "\u8463\u6756\u5b50"
    ],
    "wof:name":"Dongzhangzi",
    "wof:placetype":"locality"
},
  "geometry": {"coordinates":[119.48506999999999,40.76959],"type":"Point"}
}