{
  "type": "Feature",
  "properties": {
    "gn:admin1_code":"05",
    "gn:asciiname":"Chaluhe",
    "gn:cc2":"CN",
    "gn:country_code":"CN",
    "gn:dem":208,
    "gn:feature_class":"P",
    "gn:feature_code":"PPL",
    "gn:name":"Chaluhe",
    "gn:population":0,
    "gn:timezone":"Asia/Shanghai",
    "iso:country":"CN",
    "name:und_x_variant":[
        "Ch\u2019a-lu-ho",
        "Ch\u2019a-lu",
        "Ch\u2019a-lu-ho-ts\u2019un",
        "Chaluhe"
    ],
    "wof:name":"Chaluhe",
    "wof:placetype":"locality"
},
  "geometry": {"coordinates":[125.97528,43.70083],"type":"Point"}
}