{
  "type": "Feature",
  "properties": {
    "gn:admin1_code":"19.0",
    "gn:asciiname":"Dayujiatun",
    "gn:country_code":"CN",
    "gn:dem":13,
    "gn:feature_class":"P",
    "gn:feature_code":"PPL",
    "gn:name":"Dayujiatun",
    "gn:population":0,
    "gn:timezone":"Asia/Shanghai",
    "iso:country":"CN",
    "name:und_x_variant":[
        "\u5927\u4e8e\u5bb6\u5c6f"
    ],
    "name:zho_x_preferred":[
        "\u5927\u4e8e\u5bb6\u5c6f"
    ],
    "wof:name":"Dayujiatun",
    "wof:placetype":"locality"
},
  "geometry": {"coordinates":[123.12443,39.68078],"type":"Point"}
}