{
  "type": "Feature",
  "properties": {
    "gn:admin1_code":"32.0",
    "gn:asciiname":"Yongluo",
    "gn:country_code":"CN",
    "gn:dem":2461,
    "gn:feature_class":"P",
    "gn:feature_code":"PPL",
    "gn:name":"Yongluo",
    "gn:population":0,
    "gn:timezone":"Asia/Shanghai",
    "iso:country":"CN",
    "name:zho_x_preferred":[
        "\u6c38\u6d1b"
    ],
    "wof:name":"Yongluo",
    "wof:placetype":"locality"
},
  "geometry": {"coordinates":[102.86308,28.23707000000001],"type":"Point"}
}