{
  "type": "Feature",
  "properties": {
    "gn:admin1_code":"24.0",
    "gn:asciiname":"Fucun",
    "gn:country_code":"CN",
    "gn:dem":359,
    "gn:feature_class":"P",
    "gn:feature_code":"PPL",
    "gn:name":"Fucun",
    "gn:population":0,
    "gn:timezone":"Asia/Shanghai",
    "iso:country":"CN",
    "name:zho_x_preferred":[
        "\u4ed8\u6751"
    ],
    "wof:name":"Fucun",
    "wof:placetype":"locality"
},
  "geometry": {"coordinates":[111.14868,35.07327],"type":"Point"}
}