{
  "type": "Feature",
  "properties": {
    "gn:admin1_code":"9.0",
    "gn:asciiname":"Yelaozhuang",
    "gn:country_code":"CN",
    "gn:dem":182,
    "gn:feature_class":"P",
    "gn:feature_code":"PPL",
    "gn:name":"Yelaozhuang",
    "gn:population":0,
    "gn:timezone":"Asia/Shanghai",
    "iso:country":"CN",
    "name:zho_x_preferred":[
        "\u53f6\u8001\u5e84"
    ],
    "wof:name":"Yelaozhuang",
    "wof:placetype":"locality"
},
  "geometry": {"coordinates":[113.81442,32.81169000000001],"type":"Point"}
}