{
  "type": "Feature",
  "properties": {
    "gn:admin1_code":"9.0",
    "gn:asciiname":"Lianzhuangpu",
    "gn:country_code":"CN",
    "gn:dem":80,
    "gn:feature_class":"P",
    "gn:feature_code":"PPL",
    "gn:name":"Lianzhuangpu",
    "gn:population":0,
    "gn:timezone":"Asia/Shanghai",
    "iso:country":"CN",
    "name:zho_x_preferred":[
        "\u8fde\u5e84\u94fa"
    ],
    "wof:name":"Lianzhuangpu",
    "wof:placetype":"locality"
},
  "geometry": {"coordinates":[113.91261000000002,34.19589000000001],"type":"Point"}
}