{
  "type": "Feature",
  "properties": {
    "gn:admin1_code":"32.0",
    "gn:asciiname":"Zhuangziba",
    "gn:country_code":"CN",
    "gn:dem":1441,
    "gn:feature_class":"P",
    "gn:feature_code":"PPL",
    "gn:name":"Zhuangziba",
    "gn:population":0,
    "gn:timezone":"Asia/Shanghai",
    "iso:country":"CN",
    "name:und_x_variant":[
        "\u5e84\u5b50\u575d"
    ],
    "wof:name":"Zhuangziba",
    "wof:placetype":"locality"
},
  "geometry": {"coordinates":[106.18801000000001,32.52789],"type":"Point"}
}