{
  "type": "Feature",
  "properties": {
    "gn:country":"CN",
    "gn:fcode":"PPLA4",
    "gn:pop":125427,
    "iso:country":"CN",
    "name:chi_x_preferred":[
        "\u6d77\u95e8\u9547"
    ],
    "name:eng_x_preferred":[
        "Haimen"
    ],
    "name:jpn_x_preferred":[
        "\u6d77\u9580\u93ae"
    ],
    "name:swe_x_preferred":[
        "Haimen"
    ],
    "name:unk_x_variant":[
        "Hoimoon"
    ],
    "qs:name":"Haimen",
    "qs:photos_9r":0,
    "qs:photos_sr":0,
    "qs:pop_sr":"9",
    "wd:wordcount":699,
    "wof:name":"Haimen",
    "wof:placetype":"locality",
    "wof:population":125427
},
  "geometry": {"coordinates":[116.61219,23.19346],"type":"Point"}
}