{
  "type": "Feature",
  "properties": {
    "gn:admin1_code":"14.0",
    "gn:asciiname":"Duoqiannong",
    "gn:country_code":"CN",
    "gn:dem":4419,
    "gn:feature_class":"P",
    "gn:feature_code":"PPL",
    "gn:name":"Duoqiannong",
    "gn:population":0,
    "gn:timezone":"Asia/Urumqi",
    "iso:country":"CN",
    "name:zho_x_preferred":[
        "\u593a\u5343\u5f04"
    ],
    "wof:name":"Duoqiannong",
    "wof:placetype":"locality"
},
  "geometry": {"coordinates":[94.32792999999999,31.77803],"type":"Point"}
}