{
  "type": "Feature",
  "properties": {
    "gn:admin1_code":"30.0",
    "gn:asciiname":"Zhanchencun",
    "gn:country_code":"CN",
    "gn:dem":13,
    "gn:feature_class":"P",
    "gn:feature_code":"PPL",
    "gn:name":"Zhanchencun",
    "gn:population":0,
    "gn:timezone":"Asia/Shanghai",
    "iso:country":"CN",
    "name:zho_x_preferred":[
        "\u5360\u9648\u6751"
    ],
    "wof:name":"Zhanchencun",
    "wof:placetype":"locality"
},
  "geometry": {"coordinates":[116.2595,23.29043],"type":"Point"}
}