{
  "type": "Feature",
  "properties": {
    "gn:admin1_code":"18.0",
    "gn:asciiname":"Shanglamei",
    "gn:country_code":"CN",
    "gn:dem":860,
    "gn:feature_class":"P",
    "gn:feature_code":"PPL",
    "gn:name":"Shanglamei",
    "gn:population":0,
    "gn:timezone":"Asia/Shanghai",
    "iso:country":"CN",
    "name:zho_x_preferred":[
        "\u4e0a\u62c9\u7f8e"
    ],
    "wof:name":"Shanglamei",
    "wof:placetype":"locality"
},
  "geometry": {"coordinates":[107.699,25.3512],"type":"Point"}
}