{
  "type": "Feature",
  "properties": {
    "gn:admin1_code":"19.0",
    "gn:asciiname":"Qiantaipingzhuang",
    "gn:country_code":"CN",
    "gn:dem":126,
    "gn:feature_class":"P",
    "gn:feature_code":"PPL",
    "gn:name":"Qiantaipingzhuang",
    "gn:population":0,
    "gn:timezone":"Asia/Shanghai",
    "iso:country":"CN",
    "name:zho_x_preferred":[
        "\u524d\u592a\u5e73\u5e84"
    ],
    "wof:name":"Qiantaipingzhuang",
    "wof:placetype":"locality"
},
  "geometry": {"coordinates":[122.91759999999999,42.7625],"type":"Point"}
}