{
  "type": "Feature",
  "properties": {
    "gn:admin1_code":"16.0",
    "gn:asciiname":"Deming",
    "gn:country_code":"CN",
    "gn:dem":203,
    "gn:feature_class":"P",
    "gn:feature_code":"PPL",
    "gn:name":"Deming",
    "gn:population":0,
    "gn:timezone":"Asia/Shanghai",
    "iso:country":"CN",
    "name:ben_x_preferred":[
        "\u09a1\u09c7\u09ae\u09bf\u0982"
    ],
    "name:cat_x_preferred":[
        "Deming"
    ],
    "name:ceb_x_preferred":[
        "Deming"
    ],
    "name:deu_x_preferred":[
        "Deming"
    ],
    "name:ell_x_preferred":[
        "\u039d\u03c4\u03ad\u03bc\u03b9\u03bd\u03b3\u03ba"
    ],
    "name:fra_x_preferred":[
        "Deming"
    ],
    "name:heb_x_preferred":[
        "\u05d3\u05de\u05d9\u05e0\u05d2"
    ],
    "name:hin_x_preferred":[
        "\u0921\u0947\u092e\u093f\u0902\u0917"
    ],
    "name:ind_x_preferred":[
        "Deming"
    ],
    "name:ita_x_preferred":[
        "Deming"
    ],
    "name:jpn_x_preferred":[
        "\u30c7\u30df\u30f3\u30b0"
    ],
    "name:kor_x_preferred":[
        "\ub370\ubc0d"
    ],
    "name:nld_x_preferred":[
        "Deming"
    ],
    "name:por_x_preferred":[
        "Deming"
    ],
    "name:rus_x_preferred":[
        "\u0414\u0435\u043c\u0438\u043d\u0433"
    ],
    "name:srp_x_preferred":[
        "\u0414\u0435\u043c\u0438\u043d\u0433"
    ],
    "name:swe_x_preferred":[
        "Deming"
    ],
    "name:ukr_x_preferred":[
        "\u0414\u0435\u043c\u0456\u043d\u0433"
    ],
    "name:vie_x_preferred":[
        "Deming"
    ],
    "name:vol_x_preferred":[
        "Deming"
    ],
    "name:zho_x_preferred":[
        "\u5fb7\u660e"
    ],
    "wof:name":"Deming",
    "wof:placetype":"locality"
},
  "geometry": {"coordinates":[108.738,23.1377],"type":"Point"}
}