{
  "type": "Feature",
  "properties": {
    "gn:admin1_code":"12.0",
    "gn:asciiname":"Dongzhoujiawan",
    "gn:country_code":"CN",
    "gn:dem":50,
    "gn:feature_class":"P",
    "gn:feature_code":"PPL",
    "gn:name":"Dongzhoujiawan",
    "gn:population":0,
    "gn:timezone":"Asia/Shanghai",
    "iso:country":"CN",
    "name:zho_x_preferred":[
        "\u4e1c\u5468\u5bb6\u6e7e"
    ],
    "wof:name":"Dongzhoujiawan",
    "wof:placetype":"locality"
},
  "geometry": {"coordinates":[112.30922,30.5758],"type":"Point"}
}