{
  "type": "Feature",
  "properties": {
    "gn:admin1_code":"18",
    "gn:asciiname":"Yangtongtai",
    "gn:country_code":"CN",
    "gn:dem":1144,
    "gn:feature_class":"P",
    "gn:feature_code":"PPL",
    "gn:name":"Yangtongtai",
    "gn:population":0,
    "gn:timezone":"Asia/Shanghai",
    "iso:country":"CN",
    "name:zho_x_preferred":[
        "\u6768\u901a\u53f0"
    ],
    "wof:name":"Yangtongtai",
    "wof:placetype":"locality"
},
  "geometry": {"coordinates":[106.601,28.2619],"type":"Point"}
}