{
  "type": "Feature",
  "properties": {
    "gn:admin1_code":"16",
    "gn:asciiname":"Liang'an",
    "gn:country_code":"CN",
    "gn:dem":149,
    "gn:feature_class":"P",
    "gn:feature_code":"PPL",
    "gn:name":"Liang\u2019an",
    "gn:population":0,
    "gn:timezone":"Asia/Shanghai",
    "iso:country":"CN",
    "name:und_x_variant":[
        "Liang-an-ts\u2019un",
        "Liang\u2019an"
    ],
    "name:zho_x_preferred":[
        "\u826f\u5b89"
    ],
    "wof:name":"Liang'an",
    "wof:placetype":"locality"
},
  "geometry": {"coordinates":[107.36,22.1042],"type":"Point"}
}