{
  "type": "Feature",
  "properties": {
    "gn:admin1_code":"3.0",
    "gn:asciiname":"Yujiang",
    "gn:country_code":"CN",
    "gn:dem":448,
    "gn:feature_class":"P",
    "gn:feature_code":"PPL",
    "gn:name":"Yujiang",
    "gn:population":0,
    "gn:timezone":"Asia/Shanghai",
    "iso:country":"CN",
    "name:und_x_variant":[
        "\u4f59\u6c5f"
    ],
    "wof:name":"Yujiang",
    "wof:placetype":"locality"
},
  "geometry": {"coordinates":[114.16468999999999,27.63978],"type":"Point"}
}