{
  "type": "Feature",
  "properties": {
    "gn:admin1_code":"16",
    "gn:asciiname":"Juhe",
    "gn:country_code":"CN",
    "gn:dem":332,
    "gn:feature_class":"P",
    "gn:feature_code":"PPL",
    "gn:name":"Juhe",
    "gn:population":0,
    "gn:timezone":"Asia/Shanghai",
    "iso:country":"CN",
    "name:zho_x_preferred":[
        "\u5177\u6cb3"
    ],
    "wof:name":"Juhe",
    "wof:placetype":"locality"
},
  "geometry": {"coordinates":[109.465,25.9386],"type":"Point"}
}