{
  "type": "Feature",
  "properties": {
    "gn:admin1_code":"14.0",
    "gn:asciiname":"Sewucun",
    "gn:country_code":"CN",
    "gn:dem":4178,
    "gn:feature_class":"P",
    "gn:feature_code":"PPL",
    "gn:name":"Sewucun",
    "gn:population":0,
    "gn:timezone":"Asia/Urumqi",
    "iso:country":"CN",
    "name:zho_x_preferred":[
        "\u8272\u543e\u6751"
    ],
    "wof:name":"Sewucun",
    "wof:placetype":"locality"
},
  "geometry": {"coordinates":[92.17627,28.94368],"type":"Point"}
}