{
  "type": "Feature",
  "properties": {
    "gn:admin1_code":"8.0",
    "gn:asciiname":"Huangzhanshantun",
    "gn:country_code":"CN",
    "gn:dem":303,
    "gn:feature_class":"P",
    "gn:feature_code":"PPL",
    "gn:name":"Huangzhanshantun",
    "gn:population":0,
    "gn:timezone":"Asia/Shanghai",
    "iso:country":"CN",
    "name:zho_x_preferred":[
        "\u9ec4\u5360\u5c71\u5c6f"
    ],
    "wof:name":"Huangzhanshantun",
    "wof:placetype":"locality"
},
  "geometry": {"coordinates":[125.29067999999999,48.1441],"type":"Point"}
}