{
  "type": "Feature",
  "properties": {
    "gn:admin1_code":"24",
    "gn:asciiname":"Hebei",
    "gn:cc2":"CN",
    "gn:country_code":"CN",
    "gn:dem":1082,
    "gn:feature_class":"P",
    "gn:feature_code":"PPL",
    "gn:name":"Hebei",
    "gn:population":0,
    "gn:timezone":"Asia/Shanghai",
    "iso:country":"CN",
    "name:rus_x_preferred":[
        "\u0425\u044d\u0431\u044d\u0439"
    ],
    "name:und_x_variant":[
        "Ho-pei-ts\u2019un",
        "Ho-pei",
        "Hebei"
    ],
    "wof:name":"Hebei",
    "wof:placetype":"locality"
},
  "geometry": {"coordinates":[113.55,38.70611],"type":"Point"}
}