{
  "type": "Feature",
  "properties": {
    "gn:admin1_code":"29.0",
    "gn:asciiname":"Shiziping",
    "gn:country_code":"CN",
    "gn:dem":2095,
    "gn:feature_class":"P",
    "gn:feature_code":"PPL",
    "gn:name":"Shiziping",
    "gn:population":0,
    "gn:timezone":"Asia/Shanghai",
    "iso:country":"CN",
    "name:zho_x_preferred":[
        "\u67ff\u5b50\u576a"
    ],
    "wof:name":"Shiziping",
    "wof:placetype":"locality"
},
  "geometry": {"coordinates":[99.8565,25.2712],"type":"Point"}
}