{
  "type": "Feature",
  "properties": {
    "gn:admin1_code":"2.0",
    "gn:asciiname":"Xiajiamen",
    "gn:country_code":"CN",
    "gn:dem":164,
    "gn:feature_class":"P",
    "gn:feature_code":"PPL",
    "gn:name":"Xiajiamen",
    "gn:population":0,
    "gn:timezone":"Asia/Shanghai",
    "iso:country":"CN",
    "name:und_x_variant":[
        "\u590f\u5bb6\u95e8"
    ],
    "name:zho_x_preferred":[
        "Xiajiamen"
    ],
    "wof:name":"Xiajiamen",
    "wof:placetype":"locality"
},
  "geometry": {"coordinates":[120.08647999999999,30.01644000000001],"type":"Point"}
}