{
  "type": "Feature",
  "properties": {
    "gn:admin1_code":"19.0",
    "gn:asciiname":"Changgangzi",
    "gn:country_code":"CN",
    "gn:dem":67,
    "gn:feature_class":"P",
    "gn:feature_code":"PPL",
    "gn:name":"Changgangzi",
    "gn:population":0,
    "gn:timezone":"Asia/Shanghai",
    "iso:country":"CN",
    "name:und_x_variant":[
        "\u957f\u5c97\u5b50"
    ],
    "name:zho_x_preferred":[
        "\u957f\u5c97\u5b50"
    ],
    "wof:name":"Changgangzi",
    "wof:placetype":"locality"
},
  "geometry": {"coordinates":[123.03315000000001,42.43613],"type":"Point"}
}