{
  "type": "Feature",
  "properties": {
    "gn:admin1_code":"12.0",
    "gn:asciiname":"Daheping",
    "gn:country_code":"CN",
    "gn:dem":759,
    "gn:feature_class":"P",
    "gn:feature_code":"PPL",
    "gn:name":"Daheping",
    "gn:population":0,
    "gn:timezone":"Asia/Shanghai",
    "iso:country":"CN",
    "name:zho_x_preferred":[
        "Daheping"
    ],
    "name:zho_x_variant":[
        "\u5927\u6cb3\u576a"
    ],
    "wof:name":"Daheping",
    "wof:placetype":"locality"
},
  "geometry": {"coordinates":[110.03954,30.00746],"type":"Point"}
}