{
  "type": "Feature",
  "properties": {
    "gn:admin1_code":"24.0",
    "gn:asciiname":"Zhoujiazhuangcun",
    "gn:country_code":"CN",
    "gn:dem":539,
    "gn:feature_class":"P",
    "gn:feature_code":"PPL",
    "gn:name":"Zhoujiazhuangcun",
    "gn:population":0,
    "gn:timezone":"Asia/Shanghai",
    "iso:country":"CN",
    "name:zho_x_preferred":[
        "\u5468\u5bb6\u5e84\u6751"
    ],
    "wof:name":"Zhoujiazhuangcun",
    "wof:placetype":"locality"
},
  "geometry": {"coordinates":[110.87357,35.25725999999999],"type":"Point"}
}