{
  "type": "Feature",
  "properties": {
    "gn:admin1_code":"02",
    "gn:asciiname":"Zhanghancun",
    "gn:country_code":"CN",
    "gn:dem":58,
    "gn:feature_class":"P",
    "gn:feature_code":"PPL",
    "gn:name":"Zhanghancun",
    "gn:population":0,
    "gn:timezone":"Asia/Shanghai",
    "iso:country":"CN",
    "name:und_x_variant":[
        "Chang-han-ts\u2019un",
        "Zhanghan",
        "\u5f20\u97e9",
        "Zhanghancun"
    ],
    "name:zho_x_preferred":[
        "\u5f20\u97e9"
    ],
    "name:zho_x_variant":[
        "\u5f20\u97e9\u6751"
    ],
    "wof:name":"Zhanghancun",
    "wof:placetype":"locality"
},
  "geometry": {"coordinates":[121.69410999999999,29.37812000000001],"type":"Point"}
}