{
  "type": "Feature",
  "properties": {
    "gn:admin1_code":"02",
    "gn:asciiname":"Xiazhuangcun",
    "gn:country_code":"CN",
    "gn:dem":8,
    "gn:feature_class":"P",
    "gn:feature_code":"PPL",
    "gn:name":"Xiazhuangcun",
    "gn:population":0,
    "gn:timezone":"Asia/Shanghai",
    "iso:country":"CN",
    "name:und_x_variant":[
        "Hsia-shan-chuang",
        "Xiazhuang",
        "Xiazhuangcun"
    ],
    "name:zho_x_preferred":[
        "\u4e0b\u5e84\u6751"
    ],
    "wof:name":"Xiazhuangcun",
    "wof:placetype":"locality"
},
  "geometry": {"coordinates":[121.29979,28.68992],"type":"Point"}
}