{
  "type": "Feature",
  "properties": {
    "gn:admin1_code":"3.0",
    "gn:asciiname":"Jiangxi Gangchang Jiashu Nongchang",
    "gn:country_code":"CN",
    "gn:dem":107,
    "gn:feature_class":"P",
    "gn:feature_code":"PPLF",
    "gn:name":"Jiangxi Gangchang Jiashu Nongchang",
    "gn:population":0,
    "gn:timezone":"Asia/Shanghai",
    "iso:country":"CN",
    "name:und_x_variant":[
        "\u6c5f\u897f\u94a2\u5382\u5bb6\u5c5e\u519c\u573a"
    ],
    "wof:name":"Jiangxi Gangchang Jiashu Nongchang",
    "wof:placetype":"locality"
},
  "geometry": {"coordinates":[115.00758999999999,27.73017],"type":"Point"}
}