{
  "type": "Feature",
  "properties": {
    "gn:admin1_code":"1.0",
    "gn:asciiname":"Yupingcun",
    "gn:country_code":"CN",
    "gn:dem":54,
    "gn:feature_class":"P",
    "gn:feature_code":"PPL",
    "gn:name":"Yupingcun",
    "gn:population":0,
    "gn:timezone":"Asia/Shanghai",
    "iso:country":"CN",
    "name:zho_x_preferred":[
        "\u7389\u5c4f\u6751"
    ],
    "wof:name":"Yupingcun",
    "wof:placetype":"locality"
},
  "geometry": {"coordinates":[117.22601,30.8591],"type":"Point"}
}