{
  "type": "Feature",
  "properties": {
    "gn:admin1_code":"15.0",
    "gn:asciiname":"Yinshui",
    "gn:country_code":"CN",
    "gn:dem":1379,
    "gn:feature_class":"P",
    "gn:feature_code":"PPL",
    "gn:name":"Yinshui",
    "gn:population":0,
    "gn:timezone":"Asia/Shanghai",
    "iso:country":"CN",
    "name:und_x_variant":[
        "\u5c39\u6c34"
    ],
    "wof:name":"Yinshui",
    "wof:placetype":"locality"
},
  "geometry": {"coordinates":[105.44405999999999,33.70119],"type":"Point"}
}