{
  "type": "Feature",
  "properties": {
    "gn:admin1_code":"30.0",
    "gn:asciiname":"Raonancun",
    "gn:country_code":"CN",
    "gn:dem":285,
    "gn:feature_class":"P",
    "gn:feature_code":"PPL",
    "gn:name":"Raonancun",
    "gn:population":0,
    "gn:timezone":"Asia/Shanghai",
    "iso:country":"CN",
    "name:zho_x_preferred":[
        "\u9976\u5357\u6751"
    ],
    "wof:name":"Raonancun",
    "wof:placetype":"locality"
},
  "geometry": {"coordinates":[116.907,24.00302000000001],"type":"Point"}
}