{
  "type": "Feature",
  "properties": {
    "gn:admin1_code":"25.0",
    "gn:asciiname":"Dingjiazhaicun",
    "gn:country_code":"CN",
    "gn:dem":118,
    "gn:feature_class":"P",
    "gn:feature_code":"PPL",
    "gn:name":"Dingjiazhaicun",
    "gn:population":0,
    "gn:timezone":"Asia/Shanghai",
    "iso:country":"CN",
    "name:zho_x_preferred":[
        "\u4e01\u5bb6\u5be8\u6751"
    ],
    "wof:name":"Dingjiazhaicun",
    "wof:placetype":"locality"
},
  "geometry": {"coordinates":[120.82868000000001,37.19288],"type":"Point"}
}