{
  "type": "Feature",
  "properties": {
    "gn:admin1_code":"26.0",
    "gn:asciiname":"Wamiangou",
    "gn:country_code":"CN",
    "gn:dem":1047,
    "gn:feature_class":"P",
    "gn:feature_code":"PPL",
    "gn:name":"Wamiangou",
    "gn:population":0,
    "gn:timezone":"Asia/Shanghai",
    "iso:country":"CN",
    "name:zho_x_preferred":[
        "\u74e6\u9762\u6c9f"
    ],
    "wof:name":"Wamiangou",
    "wof:placetype":"locality"
},
  "geometry": {"coordinates":[110.09365,33.71434],"type":"Point"}
}