{
  "type": "Feature",
  "properties": {
    "gn:admin1_code":"8.0",
    "gn:asciiname":"Wulian",
    "gn:country_code":"CN",
    "gn:dem":124,
    "gn:feature_class":"P",
    "gn:feature_code":"PPL",
    "gn:name":"Wulian",
    "gn:population":0,
    "gn:timezone":"Asia/Shanghai",
    "iso:country":"CN",
    "name:zho_x_preferred":[
        "\u4e94\u8fde"
    ],
    "wof:name":"Wulian",
    "wof:placetype":"locality"
},
  "geometry": {"coordinates":[129.46108000000001,46.39109000000001],"type":"Point"}
}