{
  "type": "Feature",
  "properties": {
    "gn:admin1_code":"15.0",
    "gn:asciiname":"Chunshuyuan",
    "gn:country_code":"CN",
    "gn:dem":1557,
    "gn:feature_class":"P",
    "gn:feature_code":"PPL",
    "gn:name":"Chunshuyuan",
    "gn:population":0,
    "gn:timezone":"Asia/Shanghai",
    "iso:country":"CN",
    "name:und_x_variant":[
        "\u693f\u6811\u586c"
    ],
    "wof:name":"Chunshuyuan",
    "wof:placetype":"locality"
},
  "geometry": {"coordinates":[107.86901,36.54859],"type":"Point"}
}