{
  "type": "Feature",
  "properties": {
    "gn:admin1_code":"5.0",
    "gn:asciiname":"Changchunbu",
    "gn:country_code":"CN",
    "gn:dem":190,
    "gn:feature_class":"P",
    "gn:feature_code":"PPL",
    "gn:name":"Changchunbu",
    "gn:population":0,
    "gn:timezone":"Asia/Shanghai",
    "iso:country":"CN",
    "name:zho_x_preferred":[
        "\u957f\u6625\u5821"
    ],
    "wof:name":"Changchunbu",
    "wof:placetype":"locality"
},
  "geometry": {"coordinates":[126.91305,44.93362],"type":"Point"}
}