{
  "type": "Feature",
  "properties": {
    "gn:admin1_code":"11.0",
    "gn:asciiname":"Fangmochong",
    "gn:country_code":"CN",
    "gn:dem":408,
    "gn:feature_class":"P",
    "gn:feature_code":"PPL",
    "gn:name":"Fangmochong",
    "gn:population":0,
    "gn:timezone":"Asia/Shanghai",
    "iso:country":"CN",
    "name:zho_x_preferred":[
        "\u65b9\u78e8\u51b2"
    ],
    "wof:name":"Fangmochong",
    "wof:placetype":"locality"
},
  "geometry": {"coordinates":[110.01073,26.71782],"type":"Point"}
}