{
  "type": "Feature",
  "properties": {
    "gn:admin1_code":"11",
    "gn:asciiname":"Jielong",
    "gn:cc2":"CN",
    "gn:country_code":"CN",
    "gn:dem":334,
    "gn:feature_class":"P",
    "gn:feature_code":"PPL",
    "gn:name":"Jielong",
    "gn:population":0,
    "gn:timezone":"Asia/Shanghai",
    "iso:country":"CN",
    "name:und_x_variant":[
        "Wolong",
        "Jielong"
    ],
    "wof:name":"Jielong",
    "wof:placetype":"locality"
},
  "geometry": {"coordinates":[110.35222,27.54028],"type":"Point"}
}