{
  "type": "Feature",
  "properties": {
    "gn:admin1_code":"3.0",
    "gn:asciiname":"Lujiaokeng",
    "gn:country_code":"CN",
    "gn:dem":855,
    "gn:feature_class":"P",
    "gn:feature_code":"PPL",
    "gn:name":"Lujiaokeng",
    "gn:population":0,
    "gn:timezone":"Asia/Shanghai",
    "iso:country":"CN",
    "name:zho_x_preferred":[
        "\u9e7f\u89d2\u5751"
    ],
    "wof:name":"Lujiaokeng",
    "wof:placetype":"locality"
},
  "geometry": {"coordinates":[118.27572000000001,28.14738],"type":"Point"}
}