{
  "type": "Feature",
  "properties": {
    "gn:admin1_code":"13.0",
    "gn:asciiname":"Maimaitimila Founiwuyi",
    "gn:country_code":"CN",
    "gn:dem":908,
    "gn:feature_class":"P",
    "gn:feature_code":"PPL",
    "gn:name":"Maimaitimila Founiwuyi",
    "gn:population":0,
    "gn:timezone":"Asia/Urumqi",
    "iso:country":"CN",
    "name:zho_x_preferred":[
        "\u4e70\u4e70\u63d0\u7c73\u814a\u5426\u5c3c\u4e4c\u4f9d"
    ],
    "wof:name":"Maimaitimila Founiwuyi",
    "wof:placetype":"locality"
},
  "geometry": {"coordinates":[85.31701,40.69986],"type":"Point"}
}