{
  "type": "Feature",
  "properties": {
    "gn:admin1_code":"15.0",
    "gn:asciiname":"Kashaoka",
    "gn:country_code":"CN",
    "gn:dem":3019,
    "gn:feature_class":"P",
    "gn:feature_code":"PPL",
    "gn:name":"Kashaoka",
    "gn:population":0,
    "gn:timezone":"Asia/Shanghai",
    "iso:country":"CN",
    "name:und_x_variant":[
        "\u5361\u52fa\u5361"
    ],
    "wof:name":"Kashaoka",
    "wof:placetype":"locality"
},
  "geometry": {"coordinates":[103.3133,34.65523],"type":"Point"}
}