{
  "type": "Feature",
  "properties": {
    "gn:admin1_code":"3.0",
    "gn:asciiname":"Dongcun",
    "gn:country_code":"CN",
    "gn:dem":87,
    "gn:feature_class":"P",
    "gn:feature_code":"PPLA4",
    "gn:name":"Dongcun",
    "gn:population":0,
    "gn:timezone":"Asia/Shanghai",
    "iso:country":"CN",
    "name:und_x_variant":[
        "\u6d1e\u6751",
        "Dongcun Xiang",
        "\u6d1e\u6751\u4e61"
    ],
    "wof:name":"Dongcun",
    "wof:placetype":"locality"
},
  "geometry": {"coordinates":[114.81485000000001,28.01448],"type":"Point"}
}