{
  "type": "Feature",
  "properties": {
    "gn:admin1_code":"2.0",
    "gn:asciiname":"Dongboyang",
    "gn:country_code":"CN",
    "gn:dem":22,
    "gn:feature_class":"P",
    "gn:feature_code":"PPL",
    "gn:name":"Dongboyang",
    "gn:population":0,
    "gn:timezone":"Asia/Shanghai",
    "iso:country":"CN",
    "name:zho_x_preferred":[
        "\u4e1c\u6cca\u6f3e"
    ],
    "wof:name":"Dongboyang",
    "wof:placetype":"locality"
},
  "geometry": {"coordinates":[121.1109,28.59326],"type":"Point"}
}