{
  "type": "Feature",
  "properties": {
    "gn:admin1_code":"24.0",
    "gn:asciiname":"Baidaogou",
    "gn:country_code":"CN",
    "gn:dem":1545,
    "gn:feature_class":"P",
    "gn:feature_code":"PPL",
    "gn:name":"Baidaogou",
    "gn:population":0,
    "gn:timezone":"Asia/Shanghai",
    "iso:country":"CN",
    "name:und_x_variant":[
        "\u767d\u9053\u6c9f"
    ],
    "name:zho_x_preferred":[
        "\u767d\u9053\u6c9f"
    ],
    "wof:name":"Baidaogou",
    "wof:placetype":"locality"
},
  "geometry": {"coordinates":[112.01452,39.43595],"type":"Point"}
}