{
  "type": "Feature",
  "properties": {
    "gn:admin1_code":"12",
    "gn:asciiname":"Heshengqiao",
    "gn:country_code":"CN",
    "gn:dem":36,
    "gn:feature_class":"P",
    "gn:feature_code":"PPL",
    "gn:name":"Heshengqiao",
    "gn:population":0,
    "gn:timezone":"Asia/Shanghai",
    "iso:country":"CN",
    "name:und_x_variant":[
        "Ho-sheng-ch\u2019iao",
        "Heshengqiao"
    ],
    "name:zho_x_preferred":[
        "\u8d3a\u80dc\u6865"
    ],
    "wof:name":"Heshengqiao",
    "wof:placetype":"locality"
},
  "geometry": {"coordinates":[114.35596,30.03839],"type":"Point"}
}