{
  "type": "Feature",
  "properties": {
    "gn:admin1_code":"18.0",
    "gn:asciiname":"Labasa",
    "gn:country_code":"CN",
    "gn:dem":1035,
    "gn:feature_class":"P",
    "gn:feature_code":"PPL",
    "gn:name":"Labasa",
    "gn:population":0,
    "gn:timezone":"Asia/Shanghai",
    "iso:country":"CN",
    "name:ara_x_preferred":[
        "\u0644\u0627\u0628\u0627\u0633\u0627"
    ],
    "name:ceb_x_preferred":[
        "Lambasa"
    ],
    "name:deu_x_preferred":[
        "Labasa"
    ],
    "name:fij_x_preferred":[
        "Labasa"
    ],
    "name:fin_x_preferred":[
        "Labasa"
    ],
    "name:fra_x_preferred":[
        "Labasa"
    ],
    "name:heb_x_preferred":[
        "\u05dc\u05d0\u05de\u05d1\u05d0\u05e1\u05d4"
    ],
    "name:hif_x_preferred":[
        "Labasa"
    ],
    "name:hin_x_preferred":[
        "\u0932\u092e\u094d\u092c\u093e\u0938\u093e"
    ],
    "name:ita_x_preferred":[
        "Labasa"
    ],
    "name:jpn_x_preferred":[
        "\u30e9\u30f3\u30d0\u30b5"
    ],
    "name:kor_x_preferred":[
        "\ub78c\ubc14\uc0ac"
    ],
    "name:lit_x_preferred":[
        "Labasa"
    ],
    "name:nld_x_preferred":[
        "Labasa"
    ],
    "name:nor_x_preferred":[
        "Labasa"
    ],
    "name:pol_x_preferred":[
        "Labasa"
    ],
    "name:por_x_preferred":[
        "Labasa"
    ],
    "name:rus_x_preferred":[
        "\u041b\u0430\u043c\u0431\u0430\u0441\u0430"
    ],
    "name:spa_x_preferred":[
        "Labasa"
    ],
    "name:swe_x_preferred":[
        "Labasa"
    ],
    "name:tam_x_preferred":[
        "\u0bb2\u0bae\u0bcd\u0baa\u0bbe\u0b9a\u0bbe"
    ],
    "name:zho_x_preferred":[
        "\u62c9\u575d\u6d12"
    ],
    "name:zho_x_variant":[
        "\u62c9\u5df4\u8428"
    ],
    "wof:name":"Labasa",
    "wof:placetype":"locality"
},
  "geometry": {"coordinates":[107.583,25.8887],"type":"Point"}
}