{
  "type": "Feature",
  "properties": {
    "gn:admin1_code":"18.0",
    "gn:asciiname":"Labasa",
    "gn:country_code":"CN",
    "gn:dem":1035,
    "gn:feature_class":"P",
    "gn:feature_code":"PPL",
    "gn:name":"Labasa",
    "gn:population":0,
    "gn:timezone":"Asia/Shanghai",
    "iso:country":"CN",
    "name:zho_x_preferred":[
        "\u62c9\u575d\u6d12"
    ],
    "wof:name":"Labasa",
    "wof:placetype":"locality"
},
  "geometry": {"coordinates":[107.583,25.8887],"type":"Point"}
}