{
  "type": "Feature",
  "properties": {
    "gn:admin1_code":"8.0",
    "gn:asciiname":"Beigongcun",
    "gn:country_code":"CN",
    "gn:dem":184,
    "gn:feature_class":"P",
    "gn:feature_code":"PPL",
    "gn:name":"Beigongcun",
    "gn:population":0,
    "gn:timezone":"Asia/Shanghai",
    "iso:country":"CN",
    "name:zho_x_preferred":[
        "\u5317\u8d21\u6751"
    ],
    "wof:name":"Beigongcun",
    "wof:placetype":"locality"
},
  "geometry": {"coordinates":[127.06896999999999,44.85586],"type":"Point"}
}