{
  "type": "Feature",
  "properties": {
    "gn:admin1_code":"19.0",
    "gn:asciiname":"Chaizhangzi Beizhuang",
    "gn:country_code":"CN",
    "gn:dem":376,
    "gn:feature_class":"P",
    "gn:feature_code":"PPL",
    "gn:name":"Chaizhangzi Beizhuang",
    "gn:population":0,
    "gn:timezone":"Asia/Shanghai",
    "iso:country":"CN",
    "name:zho_x_preferred":[
        "\u67f4\u6756\u5b50\u5317\u5e84"
    ],
    "wof:name":"Chaizhangzi Beizhuang",
    "wof:placetype":"locality"
},
  "geometry": {"coordinates":[119.16397000000001,40.75968],"type":"Point"}
}