{
  "type": "Feature",
  "properties": {
    "gn:admin1_code":"11.0",
    "gn:asciiname":"Maxicun",
    "gn:country_code":"CN",
    "gn:dem":138,
    "gn:feature_class":"P",
    "gn:feature_code":"PPL",
    "gn:name":"Maxicun",
    "gn:population":0,
    "gn:timezone":"Asia/Shanghai",
    "iso:country":"CN",
    "name:zho_x_preferred":[
        "\u9a6c\u897f\u6751"
    ],
    "wof:name":"Maxicun",
    "wof:placetype":"locality"
},
  "geometry": {"coordinates":[113.96665,28.68064],"type":"Point"}
}