{
  "type": "Feature",
  "properties": {
    "gn:admin1_code":"2.0",
    "gn:asciiname":"Lixia",
    "gn:country_code":"CN",
    "gn:dem":762,
    "gn:feature_class":"P",
    "gn:feature_code":"PPL",
    "gn:name":"Lixia",
    "gn:population":0,
    "gn:timezone":"Asia/Shanghai",
    "iso:country":"CN",
    "name:afr_x_preferred":[
        "Lixia"
    ],
    "name:cdo_x_preferred":[
        "L\u012dk-h\u00e2"
    ],
    "name:hak_x_preferred":[
        "Li\u030dp-ha"
    ],
    "name:ind_x_preferred":[
        "Lixia"
    ],
    "name:swe_x_preferred":[
        "Lixia"
    ],
    "name:vie_x_preferred":[
        "L\u1eadp h\u1ea1"
    ],
    "name:zha_x_preferred":[
        "Laebhah"
    ],
    "name:zho_x_preferred":[
        "\u783e\u4e0b"
    ],
    "wof:name":"Lixia",
    "wof:placetype":"locality"
},
  "geometry": {"coordinates":[118.72138,28.30821],"type":"Point"}
}