{
  "type": "Feature",
  "properties": {
    "gn:admin1_code":"2.0",
    "gn:asciiname":"Lixia",
    "gn:country_code":"CN",
    "gn:dem":762,
    "gn:feature_class":"P",
    "gn:feature_code":"PPL",
    "gn:name":"Lixia",
    "gn:population":0,
    "gn:timezone":"Asia/Shanghai",
    "iso:country":"CN",
    "name:zho_x_preferred":[
        "\u783e\u4e0b"
    ],
    "wof:name":"Lixia",
    "wof:placetype":"locality"
},
  "geometry": {"coordinates":[118.72138,28.30821],"type":"Point"}
}