{
  "type": "Feature",
  "properties": {
    "gn:admin1_code":"33.0",
    "gn:asciiname":"Zaojiaoping",
    "gn:country_code":"CN",
    "gn:dem":285,
    "gn:feature_class":"P",
    "gn:feature_code":"PPL",
    "gn:name":"Zaojiaoping",
    "gn:population":0,
    "gn:timezone":"Asia/Shanghai",
    "iso:country":"CN",
    "name:zho_x_preferred":[
        "\u7682\u89d2\u576a"
    ],
    "wof:name":"Zaojiaoping",
    "wof:placetype":"locality"
},
  "geometry": {"coordinates":[105.80525,30.12133],"type":"Point"}
}