{
  "type": "Feature",
  "properties": {
    "gn:admin1_code":"2.0",
    "gn:asciiname":"Tiaojiabang",
    "gn:country_code":"CN",
    "gn:dem":8,
    "gn:feature_class":"P",
    "gn:feature_code":"PPL",
    "gn:name":"Tiaojiabang",
    "gn:population":0,
    "gn:timezone":"Asia/Shanghai",
    "iso:country":"CN",
    "name:und_x_variant":[
        "\u773a\u5bb6\u6d5c"
    ],
    "wof:name":"Tiaojiabang",
    "wof:placetype":"locality"
},
  "geometry": {"coordinates":[120.59739999999999,30.76729000000001],"type":"Point"}
}