{
  "type": "Feature",
  "properties": {
    "gn:admin1_code":"18",
    "gn:asciiname":"Yanjiao",
    "gn:country_code":"CN",
    "gn:dem":2015,
    "gn:feature_class":"P",
    "gn:feature_code":"PPL",
    "gn:name":"Yanjiao",
    "gn:population":0,
    "gn:timezone":"Asia/Shanghai",
    "iso:country":"CN",
    "name:zho_x_preferred":[
        "\u5ca9\u811a"
    ],
    "name:zho_x_variant":[
        "\u71d5\u90ca\u9547"
    ],
    "wof:name":"Yanjiao",
    "wof:placetype":"locality"
},
  "geometry": {"coordinates":[104.88,26.9559],"type":"Point"}
}