{
  "type": "Feature",
  "properties": {
    "gn:admin1_code":"18.0",
    "gn:asciiname":"Datangshao",
    "gn:country_code":"CN",
    "gn:dem":945,
    "gn:feature_class":"P",
    "gn:feature_code":"PPL",
    "gn:name":"Datangshao",
    "gn:population":0,
    "gn:timezone":"Asia/Shanghai",
    "iso:country":"CN",
    "name:zho_x_preferred":[
        "\u5927\u5858\u54e8"
    ],
    "wof:name":"Datangshao",
    "wof:placetype":"locality"
},
  "geometry": {"coordinates":[108.28400000000001,26.9347],"type":"Point"}
}