{
  "type": "Feature",
  "properties": {
    "gn:admin1_code":"32.0",
    "gn:asciiname":"Maixi",
    "gn:country_code":"CN",
    "gn:dem":3439,
    "gn:feature_class":"P",
    "gn:feature_code":"PPL",
    "gn:name":"Maixi",
    "gn:population":0,
    "gn:timezone":"Asia/Shanghai",
    "iso:country":"CN",
    "name:zho_x_preferred":[
        "\u9ea6\u6eaa"
    ],
    "wof:name":"Maixi",
    "wof:placetype":"locality"
},
  "geometry": {"coordinates":[102.45996,34.01999],"type":"Point"}
}