{
  "type": "Feature",
  "properties": {
    "gn:admin1_code":"1.0",
    "gn:asciiname":"Jieloucun",
    "gn:country_code":"CN",
    "gn:dem":50,
    "gn:feature_class":"P",
    "gn:feature_code":"PPL",
    "gn:name":"Jieloucun",
    "gn:population":0,
    "gn:timezone":"Asia/Shanghai",
    "iso:country":"CN",
    "name:zho_x_preferred":[
        "\u89e3\u697c\u6751"
    ],
    "wof:name":"Jieloucun",
    "wof:placetype":"locality"
},
  "geometry": {"coordinates":[116.35402000000001,34.60305],"type":"Point"}
}