{
  "type": "Feature",
  "properties": {
    "gn:admin1_code":"30",
    "gn:asciiname":"Chashan",
    "gn:country_code":"CN",
    "gn:dem":44,
    "gn:feature_class":"P",
    "gn:feature_code":"PPL",
    "gn:name":"Chashan",
    "gn:population":0,
    "gn:timezone":"Asia/Urumqi",
    "iso:country":"CN",
    "name:fas_x_preferred":[
        "\u0686\u0627\u0634\u0627\u0646"
    ],
    "name:mlg_x_preferred":[
        "Chashan"
    ],
    "name:zho_x_preferred":[
        "\u8336\u5c71"
    ],
    "name:zho_x_variant":[
        "\u8336\u5c71\u9547"
    ],
    "wof:name":"Chashan",
    "wof:placetype":"locality"
},
  "geometry": {"coordinates":[110.33656000000001,21.64763],"type":"Point"}
}