{
  "type": "Feature",
  "properties": {
    "gn:admin1_code":"14.0",
    "gn:asciiname":"Qiga",
    "gn:country_code":"CN",
    "gn:dem":4487,
    "gn:feature_class":"P",
    "gn:feature_code":"PPL",
    "gn:name":"Qiga",
    "gn:population":0,
    "gn:timezone":"Asia/Urumqi",
    "iso:country":"CN",
    "name:zho_x_preferred":[
        "\u65d7\u560e"
    ],
    "wof:name":"Qiga",
    "wof:placetype":"locality"
},
  "geometry": {"coordinates":[90.09111,29.61359],"type":"Point"}
}