{
  "type": "Feature",
  "properties": {
    "gn:admin1_code":"7.0",
    "gn:asciiname":"Laocheng",
    "gn:country_code":"CN",
    "gn:dem":265,
    "gn:feature_class":"P",
    "gn:feature_code":"PPLA4",
    "gn:name":"Laocheng",
    "gn:population":0,
    "gn:timezone":"Asia/Shanghai",
    "iso:country":"CN",
    "name:und_x_variant":[
        "Zhongshan",
        "Laocheng",
        "\u8001\u57ce",
        "Zhongshan Zhen",
        "\u4e2d\u5c71\u9547"
    ],
    "name:zho_x_preferred":[
        "\u4e2d\u5c71"
    ],
    "wof:name":"Laocheng",
    "wof:placetype":"locality"
},
  "geometry": {"coordinates":[116.03578,25.02737],"type":"Point"}
}