{
  "type": "Feature",
  "properties": {
    "gn:admin1_code":"12.0",
    "gn:asciiname":"Tanwozi",
    "gn:country_code":"CN",
    "gn:dem":124,
    "gn:feature_class":"P",
    "gn:feature_code":"PPL",
    "gn:name":"Tanwozi",
    "gn:population":0,
    "gn:timezone":"Asia/Shanghai",
    "iso:country":"CN",
    "name:zho_x_preferred":[
        "\u6f6d\u7a9d\u5b50"
    ],
    "wof:name":"Tanwozi",
    "wof:placetype":"locality"
},
  "geometry": {"coordinates":[111.60702000000001,32.20774],"type":"Point"}
}