{
  "type": "Feature",
  "properties": {
    "gn:admin1_code":"30",
    "gn:asciiname":"Huohu",
    "gn:cc2":"CN",
    "gn:country_code":"CN",
    "gn:dem":27,
    "gn:feature_class":"P",
    "gn:feature_code":"PPL",
    "gn:name":"Huohu",
    "gn:population":0,
    "gn:timezone":"Asia/Urumqi",
    "iso:country":"CN",
    "name:und_x_variant":[
        "Huo-hu-hs\u00fc",
        "Huohu"
    ],
    "wof:name":"Huohu",
    "wof:placetype":"locality"
},
  "geometry": {"coordinates":[109.84778,21.24917],"type":"Point"}
}