{
  "type": "Feature",
  "properties": {
    "gn:admin1_code":"4.0",
    "gn:asciiname":"Jiukougang",
    "gn:country_code":"CN",
    "gn:dem":0,
    "gn:feature_class":"P",
    "gn:feature_code":"PPL",
    "gn:name":"Jiukougang",
    "gn:population":0,
    "gn:timezone":"Asia/Shanghai",
    "iso:country":"CN",
    "name:zho_x_preferred":[
        "Jiukougang"
    ],
    "name:zho_x_variant":[
        "\u4e5d\u53e3\u7f38"
    ],
    "wof:name":"Jiukougang",
    "wof:placetype":"locality"
},
  "geometry": {"coordinates":[120.25557000000001,34.0247],"type":"Point"}
}