{
  "type": "Feature",
  "properties": {
    "gn:admin1_code":"13",
    "gn:asciiname":"Kashi Airike",
    "gn:country_code":"CN",
    "gn:dem":1237,
    "gn:feature_class":"P",
    "gn:feature_code":"PPL",
    "gn:name":"Kashi Airike",
    "gn:population":0,
    "gn:timezone":"Asia/Shanghai",
    "iso:country":"CN",
    "name:zho_x_preferred":[
        "\u5580\u4ec0\u827e\u65e5\u514b"
    ],
    "wof:name":"Kashi Airike",
    "wof:placetype":"locality"
},
  "geometry": {"coordinates":[76.40911,39.10672],"type":"Point"}
}