{
  "type": "Feature",
  "properties": {
    "gn:admin1_code":"16.0",
    "gn:asciiname":"Jixinpo",
    "gn:country_code":"CN",
    "gn:dem":75,
    "gn:feature_class":"P",
    "gn:feature_code":"PPL",
    "gn:name":"Jixinpo",
    "gn:population":0,
    "gn:timezone":"Asia/Shanghai",
    "iso:country":"CN",
    "name:zho_x_preferred":[
        "\u9e21\u5fc3\u5761"
    ],
    "wof:name":"Jixinpo",
    "wof:placetype":"locality"
},
  "geometry": {"coordinates":[109.383,22.1208],"type":"Point"}
}