{
  "type": "Feature",
  "properties": {
    "gn:admin1_code":"18",
    "gn:asciiname":"Manidong",
    "gn:country_code":"CN",
    "gn:dem":731,
    "gn:feature_class":"P",
    "gn:feature_code":"PPL",
    "gn:name":"Manidong",
    "gn:population":0,
    "gn:timezone":"Asia/Shanghai",
    "iso:country":"CN",
    "name:zho_x_preferred":[
        "\u9a6c\u5c3f\u6d1e"
    ],
    "wof:name":"Manidong",
    "wof:placetype":"locality"
},
  "geometry": {"coordinates":[107.845,27.7548],"type":"Point"}
}