{
  "type": "Feature",
  "properties": {
    "gn:admin1_code":"5.0",
    "gn:asciiname":"Sanbuluo",
    "gn:country_code":"CN",
    "gn:dem":192,
    "gn:feature_class":"P",
    "gn:feature_code":"PPL",
    "gn:name":"Sanbuluo",
    "gn:population":0,
    "gn:timezone":"Asia/Shanghai",
    "iso:country":"CN",
    "name:zho_x_preferred":[
        "\u4e09\u90e8\u843d"
    ],
    "wof:name":"Sanbuluo",
    "wof:placetype":"locality"
},
  "geometry": {"coordinates":[124.98558,44.96919000000001],"type":"Point"}
}