{
  "type": "Feature",
  "properties": {
    "gn:admin1_code":"14.0",
    "gn:asciiname":"Baribu",
    "gn:country_code":"CN",
    "gn:dem":4922,
    "gn:feature_class":"P",
    "gn:feature_code":"PPL",
    "gn:name":"Baribu",
    "gn:population":0,
    "gn:timezone":"Asia/Urumqi",
    "iso:country":"CN",
    "name:zho_x_preferred":[
        "\u5df4\u65e5\u5e03"
    ],
    "wof:name":"Baribu",
    "wof:placetype":"locality"
},
  "geometry": {"coordinates":[92.99695,31.16009],"type":"Point"}
}