{
  "type": "Feature",
  "properties": {
    "gn:admin1_code":"9",
    "gn:asciiname":"Jianchangdian",
    "gn:country_code":"CN",
    "gn:dem":52,
    "gn:feature_class":"P",
    "gn:feature_code":"PPL",
    "gn:name":"Jianchangdian",
    "gn:population":0,
    "gn:timezone":"Asia/Shanghai",
    "iso:country":"CN",
    "name:zho_x_preferred":[
        "\u51cf\u573a\u5e97"
    ],
    "wof:name":"Jianchangdian",
    "wof:placetype":"locality"
},
  "geometry": {"coordinates":[115.13894999999999,36.16561],"type":"Point"}
}