{
  "type": "Feature",
  "properties": {
    "gn:admin1_code":"4.0",
    "gn:asciiname":"Huashen",
    "gn:country_code":"CN",
    "gn:dem":5,
    "gn:feature_class":"P",
    "gn:feature_code":"PPL",
    "gn:name":"Huashen",
    "gn:population":0,
    "gn:timezone":"Asia/Shanghai",
    "iso:country":"CN",
    "name:zho_x_preferred":[
        "\u82b1\u6c88"
    ],
    "wof:name":"Huashen",
    "wof:placetype":"locality"
},
  "geometry": {"coordinates":[119.89127000000001,32.83586],"type":"Point"}
}