{
  "type": "Feature",
  "properties": {
    "gn:admin1_code":"10",
    "gn:asciiname":"Luzhuangzi",
    "gn:country_code":"CN",
    "gn:dem":284,
    "gn:feature_class":"P",
    "gn:feature_code":"PPL",
    "gn:name":"Luzhuangzi",
    "gn:population":0,
    "gn:timezone":"Asia/Shanghai",
    "iso:country":"CN",
    "name:zho_x_preferred":[
        "\u9646\u5e84\u5b50"
    ],
    "wof:name":"Luzhuangzi",
    "wof:placetype":"locality"
},
  "geometry": {"coordinates":[118.44148,40.60039],"type":"Point"}
}