{
  "type": "Feature",
  "properties": {
    "gn:admin1_code":"8.0",
    "gn:asciiname":"Baoli Erdui",
    "gn:country_code":"CN",
    "gn:dem":175,
    "gn:feature_class":"P",
    "gn:feature_code":"PPLF",
    "gn:name":"Baoli Erdui",
    "gn:population":0,
    "gn:timezone":"Asia/Shanghai",
    "iso:country":"CN",
    "name:zho_x_preferred":[
        "\u4fdd\u5229\u4e8c\u961f"
    ],
    "wof:name":"Baoli Erdui",
    "wof:placetype":"locality"
},
  "geometry": {"coordinates":[125.65657,46.73803],"type":"Point"}
}