{
  "type": "Feature",
  "properties": {
    "gn:admin1_code":"19.0",
    "gn:asciiname":"Laopingtuo",
    "gn:country_code":"CN",
    "gn:dem":350,
    "gn:feature_class":"P",
    "gn:feature_code":"PPL",
    "gn:name":"Laopingtuo",
    "gn:population":0,
    "gn:timezone":"Asia/Shanghai",
    "iso:country":"CN",
    "name:und_x_variant":[
        "\u8001\u5e73\u5768"
    ],
    "name:zho_x_preferred":[
        "\u8001\u5e73\u5768"
    ],
    "wof:name":"Laopingtuo",
    "wof:placetype":"locality"
},
  "geometry": {"coordinates":[124.51414,40.69845],"type":"Point"}
}