{
  "type": "Feature",
  "properties": {
    "gn:admin1_code":"4.0",
    "gn:asciiname":"Hongzhuang",
    "gn:country_code":"CN",
    "gn:dem":4,
    "gn:feature_class":"P",
    "gn:feature_code":"PPL",
    "gn:name":"Hongzhuang",
    "gn:population":0,
    "gn:timezone":"Asia/Shanghai",
    "iso:country":"CN",
    "name:und_x_variant":[
        "\u6d2a\u5e84"
    ],
    "name:zho_x_preferred":[
        "\u6d2a\u5e84"
    ],
    "wof:name":"Hongzhuang",
    "wof:placetype":"locality"
},
  "geometry": {"coordinates":[120.68071999999999,32.10764],"type":"Point"}
}