{
  "type": "Feature",
  "properties": {
    "gn:admin1_code":"29.0",
    "gn:asciiname":"Pahe",
    "gn:country_code":"CN",
    "gn:dem":1298,
    "gn:feature_class":"P",
    "gn:feature_code":"PPL",
    "gn:name":"Pahe",
    "gn:population":0,
    "gn:timezone":"Asia/Shanghai",
    "iso:country":"CN",
    "name:zho_x_preferred":[
        "\u6015\u6cb3"
    ],
    "wof:name":"Pahe",
    "wof:placetype":"locality"
},
  "geometry": {"coordinates":[98.1773,24.3809],"type":"Point"}
}