{
  "type": "Feature",
  "properties": {
    "gn:admin1_code":"10",
    "gn:asciiname":"Gushan Xigou",
    "gn:country_code":"CN",
    "gn:dem":408,
    "gn:feature_class":"P",
    "gn:feature_code":"PPL",
    "gn:name":"Gushan Xigou",
    "gn:population":0,
    "gn:timezone":"Asia/Shanghai",
    "iso:country":"CN",
    "name:zho_x_preferred":[
        "\u5b64\u5c71\u897f\u6c9f"
    ],
    "wof:name":"Gushan Xigou",
    "wof:placetype":"locality"
},
  "geometry": {"coordinates":[118.20994,40.95331],"type":"Point"}
}