{
  "type": "Feature",
  "properties": {
    "gn:admin1_code":"30.0",
    "gn:asciiname":"Yanggongkeng",
    "gn:country_code":"CN",
    "gn:dem":465,
    "gn:feature_class":"P",
    "gn:feature_code":"PPL",
    "gn:name":"Yanggongkeng",
    "gn:population":0,
    "gn:timezone":"Asia/Shanghai",
    "iso:country":"CN",
    "name:zho_x_preferred":[
        "Yanggongkeng"
    ],
    "name:zho_x_variant":[
        "\u517b\u516c\u5751"
    ],
    "wof:name":"Yanggongkeng",
    "wof:placetype":"locality"
},
  "geometry": {"coordinates":[112.81056,23.73972],"type":"Point"}
}