{
  "type": "Feature",
  "properties": {
    "gn:admin1_code":"18",
    "gn:asciiname":"Lujiabao",
    "gn:country_code":"CN",
    "gn:dem":1128,
    "gn:feature_class":"P",
    "gn:feature_code":"PPL",
    "gn:name":"Lujiabao",
    "gn:population":0,
    "gn:timezone":"Asia/Shanghai",
    "iso:country":"CN",
    "name:zho_x_preferred":[
        "\u9646\u5bb6\u5305"
    ],
    "wof:name":"Lujiabao",
    "wof:placetype":"locality"
},
  "geometry": {"coordinates":[105.19799999999999,26.2583],"type":"Point"}
}