{
  "type": "Feature",
  "properties": {
    "gn:admin1_code":"16.0",
    "gn:asciiname":"Yixing",
    "gn:country_code":"CN",
    "gn:dem":695,
    "gn:feature_class":"P",
    "gn:feature_code":"PPL",
    "gn:name":"Yixing",
    "gn:population":0,
    "gn:timezone":"Asia/Shanghai",
    "iso:country":"CN",
    "name:bel_x_preferred":[
        "\u0406\u0441\u0456\u043d"
    ],
    "name:deu_x_preferred":[
        "Yixing"
    ],
    "name:fra_x_preferred":[
        "Yixing"
    ],
    "name:ita_x_preferred":[
        "Yixing"
    ],
    "name:jpn_x_preferred":[
        "\u5b9c\u8208\u5e02"
    ],
    "name:kik_x_preferred":[
        "Yixing"
    ],
    "name:kor_x_preferred":[
        "\uc774\uc2f1\uc2dc"
    ],
    "name:nld_x_preferred":[
        "Yixing"
    ],
    "name:nno_x_preferred":[
        "Yixing"
    ],
    "name:nor_x_preferred":[
        "Yixing"
    ],
    "name:por_x_preferred":[
        "Yixing"
    ],
    "name:rus_x_preferred":[
        "\u0418\u0441\u0438\u043d"
    ],
    "name:swe_x_preferred":[
        "Yixing"
    ],
    "name:tgl_x_preferred":[
        "Yixing"
    ],
    "name:tur_x_preferred":[
        "Yixing"
    ],
    "name:ukr_x_preferred":[
        "\u0406\u0441\u0438\u043d"
    ],
    "name:urd_x_preferred":[
        "\u06cc\u06cc\u0634\u06cc\u0646\u06af"
    ],
    "name:vie_x_preferred":[
        "Nghi H\u01b0ng"
    ],
    "name:war_x_preferred":[
        "Yixing"
    ],
    "name:wuu_x_preferred":[
        "\u5b9c\u5174\u5e02"
    ],
    "name:zho_x_preferred":[
        "\u4e49\u5174"
    ],
    "name:zho_x_variant":[
        "\u5b9c\u5174\u5e02"
    ],
    "wof:name":"Yixing",
    "wof:placetype":"locality"
},
  "geometry": {"coordinates":[106.584,23.1604],"type":"Point"}
}