{
  "type": "Feature",
  "properties": {
    "gn:admin1_code":"3",
    "gn:asciiname":"Zhenbei",
    "gn:country_code":"CN",
    "gn:dem":174,
    "gn:feature_class":"P",
    "gn:feature_code":"PPL",
    "gn:name":"Zhenbei",
    "gn:population":0,
    "gn:timezone":"Asia/Shanghai",
    "iso:country":"CN",
    "name:zho_x_preferred":[
        "\u9547\u80cc"
    ],
    "wof:name":"Zhenbei",
    "wof:placetype":"locality"
},
  "geometry": {"coordinates":[113.92561000000001,27.0104],"type":"Point"}
}