{
  "type": "Feature",
  "properties": {
    "gn:admin1_code":"15.0",
    "gn:asciiname":"Xiaojiachuan",
    "gn:country_code":"CN",
    "gn:dem":1307,
    "gn:feature_class":"P",
    "gn:feature_code":"PPL",
    "gn:name":"Xiaojiachuan",
    "gn:population":0,
    "gn:timezone":"Asia/Shanghai",
    "iso:country":"CN",
    "name:und_x_variant":[
        "\u8427\u5bb6\u5ddd"
    ],
    "wof:name":"Xiaojiachuan",
    "wof:placetype":"locality"
},
  "geometry": {"coordinates":[107.17271,36.51201],"type":"Point"}
}