{
  "type": "Feature",
  "properties": {
    "gn:admin1_code":"9.0",
    "gn:asciiname":"Langliuji",
    "gn:country_code":"CN",
    "gn:dem":68,
    "gn:feature_class":"P",
    "gn:feature_code":"PPL",
    "gn:name":"Langliuji",
    "gn:population":0,
    "gn:timezone":"Asia/Shanghai",
    "iso:country":"CN",
    "name:zho_x_preferred":[
        "\u90ce\u67f3\u96c6"
    ],
    "wof:name":"Langliuji",
    "wof:placetype":"locality"
},
  "geometry": {"coordinates":[114.48111000000002,35.45800999999999],"type":"Point"}
}