{
  "type": "Feature",
  "properties": {
    "gn:admin1_code":"12.0",
    "gn:asciiname":"Changjiazhou",
    "gn:country_code":"CN",
    "gn:dem":41,
    "gn:feature_class":"P",
    "gn:feature_code":"PPL",
    "gn:name":"Changjiazhou",
    "gn:population":0,
    "gn:timezone":"Asia/Shanghai",
    "iso:country":"CN",
    "name:zho_x_preferred":[
        "Changjiazhou"
    ],
    "name:zho_x_variant":[
        "\u5e38\u5bb6\u5dde"
    ],
    "wof:name":"Changjiazhou",
    "wof:placetype":"locality"
},
  "geometry": {"coordinates":[111.91939000000001,30.48149],"type":"Point"}
}