{
  "type": "Feature",
  "properties": {
    "gn:admin1_code":"2.0",
    "gn:asciiname":"Gaoshanwan",
    "gn:country_code":"CN",
    "gn:dem":736,
    "gn:feature_class":"P",
    "gn:feature_code":"PPL",
    "gn:name":"Gaoshanwan",
    "gn:population":0,
    "gn:timezone":"Asia/Shanghai",
    "iso:country":"CN",
    "name:zho_x_preferred":[
        "\u9ad8\u5c71\u6e7e"
    ],
    "wof:name":"Gaoshanwan",
    "wof:placetype":"locality"
},
  "geometry": {"coordinates":[118.95583999999999,27.55105],"type":"Point"}
}