{
  "type": "Feature",
  "properties": {
    "gn:admin1_code":"7.0",
    "gn:asciiname":"Qianpai",
    "gn:country_code":"CN",
    "gn:dem":903,
    "gn:feature_class":"P",
    "gn:feature_code":"PPL",
    "gn:name":"Qianpai",
    "gn:population":0,
    "gn:timezone":"Asia/Shanghai",
    "iso:country":"CN",
    "name:zho_x_preferred":[
        "\u524d\u6392"
    ],
    "wof:name":"Qianpai",
    "wof:placetype":"locality"
},
  "geometry": {"coordinates":[118.38406999999999,28.01606],"type":"Point"}
}