{
  "type": "Feature",
  "properties": {
    "gn:admin1_code":"3.0",
    "gn:asciiname":"Wangjingpai",
    "gn:country_code":"CN",
    "gn:dem":41,
    "gn:feature_class":"P",
    "gn:feature_code":"PPL",
    "gn:name":"Wangjingpai",
    "gn:population":0,
    "gn:timezone":"Asia/Shanghai",
    "iso:country":"CN",
    "name:und_x_variant":[
        "\u738b\u7cbe\u6392"
    ],
    "wof:name":"Wangjingpai",
    "wof:placetype":"locality"
},
  "geometry": {"coordinates":[115.55972,28.34006],"type":"Point"}
}