{
  "type": "Feature",
  "properties": {
    "gn:admin1_code":"10.0",
    "gn:asciiname":"Yecaowan",
    "gn:cc2":"CN",
    "gn:country_code":"CN",
    "gn:dem":282,
    "gn:feature_class":"P",
    "gn:feature_code":"PPL",
    "gn:name":"Yecaowan",
    "gn:population":0,
    "gn:timezone":"Asia/Shanghai",
    "iso:country":"CN",
    "name:und_x_variant":[
        "Yeh-ts\u2019ao-wan",
        "Yecaowan"
    ],
    "wof:name":"Yecaowan",
    "wof:placetype":"locality"
},
  "geometry": {"coordinates":[114.22861,37.635],"type":"Point"}
}