{
  "type": "Feature",
  "properties": {
    "gn:admin1_code":"29.0",
    "gn:asciiname":"Shatian",
    "gn:country_code":"CN",
    "gn:dem":1270,
    "gn:feature_class":"P",
    "gn:feature_code":"PPL",
    "gn:name":"Shatian",
    "gn:population":0,
    "gn:timezone":"Asia/Shanghai",
    "iso:country":"CN",
    "name:ceb_x_preferred":[
        "Shatian"
    ],
    "name:deu_x_preferred":[
        "Shatian"
    ],
    "name:jpn_x_preferred":[
        "\u6c99\u7530"
    ],
    "name:swe_x_preferred":[
        "Shatian"
    ],
    "name:zho_x_preferred":[
        "\u6c99\u7530"
    ],
    "wof:name":"Shatian",
    "wof:placetype":"locality"
},
  "geometry": {"coordinates":[100.417,26.6202],"type":"Point"}
}