{
  "type": "Feature",
  "properties": {
    "gn:admin1_code":"18.0",
    "gn:asciiname":"Biyou",
    "gn:country_code":"CN",
    "gn:dem":775,
    "gn:feature_class":"P",
    "gn:feature_code":"PPL",
    "gn:name":"Biyou",
    "gn:population":0,
    "gn:timezone":"Asia/Shanghai",
    "iso:country":"CN",
    "name:zho_x_preferred":[
        "\u5e87\u4f51"
    ],
    "wof:name":"Biyou",
    "wof:placetype":"locality"
},
  "geometry": {"coordinates":[108.95699999999999,26.7438],"type":"Point"}
}