{
  "type": "Feature",
  "properties": {
    "gn:admin1_code":"18",
    "gn:asciiname":"Gujiao Laojie",
    "gn:country_code":"CN",
    "gn:dem":1279,
    "gn:feature_class":"P",
    "gn:feature_code":"PPL",
    "gn:name":"Gujiao Laojie",
    "gn:population":0,
    "gn:timezone":"Asia/Shanghai",
    "iso:country":"CN",
    "name:zho_x_preferred":[
        "\u8c37\u811a\u8001\u8857"
    ],
    "wof:name":"Gujiao Laojie",
    "wof:placetype":"locality"
},
  "geometry": {"coordinates":[106.866,26.516],"type":"Point"}
}