{
  "type": "Feature",
  "properties": {
    "gn:admin1_code":"33.0",
    "gn:asciiname":"Jinyinao",
    "gn:country_code":"CN",
    "gn:dem":556,
    "gn:feature_class":"P",
    "gn:feature_code":"PPL",
    "gn:name":"Jinyinao",
    "gn:population":0,
    "gn:timezone":"Asia/Shanghai",
    "iso:country":"CN",
    "name:zho_x_preferred":[
        "\u91d1\u94f6\u5773"
    ],
    "wof:name":"Jinyinao",
    "wof:placetype":"locality"
},
  "geometry": {"coordinates":[105.76975,29.36239],"type":"Point"}
}