{
  "type": "Feature",
  "properties": {
    "gn:admin1_code":"32.0",
    "gn:asciiname":"Ride",
    "gn:country_code":"CN",
    "gn:dem":3519,
    "gn:feature_class":"P",
    "gn:feature_code":"PPL",
    "gn:name":"Ride",
    "gn:population":0,
    "gn:timezone":"Asia/Shanghai",
    "iso:country":"CN",
    "name:ces_x_preferred":[
        "Ride"
    ],
    "name:dan_x_preferred":[
        "Ride"
    ],
    "name:deu_x_preferred":[
        "Ride"
    ],
    "name:fra_x_preferred":[
        "Ride"
    ],
    "name:heb_x_preferred":[
        "\u05e8\u05d9\u05d9\u05d3"
    ],
    "name:ita_x_preferred":[
        "Ride"
    ],
    "name:jpn_x_preferred":[
        "\u30e9\u30a4\u30c9"
    ],
    "name:kor_x_preferred":[
        "\ub77c\uc774\ub4dc"
    ],
    "name:nld_x_preferred":[
        "Ride"
    ],
    "name:pol_x_preferred":[
        "Ride"
    ],
    "name:por_x_preferred":[
        "Ride"
    ],
    "name:rus_x_preferred":[
        "Ride"
    ],
    "name:swe_x_preferred":[
        "Ride"
    ],
    "name:tur_x_preferred":[
        "Ride"
    ],
    "name:zho_x_preferred":[
        "\u65e5\u5fb7"
    ],
    "name:zho_x_variant":[
        "Ride"
    ],
    "wof:name":"Ride",
    "wof:placetype":"locality"
},
  "geometry": {"coordinates":[101.009,31.9726],"type":"Point"}
}