{
  "type": "Feature",
  "properties": {
    "gn:admin1_code":"11.0",
    "gn:asciiname":"Yanjiating",
    "gn:country_code":"CN",
    "gn:dem":153,
    "gn:feature_class":"P",
    "gn:feature_code":"PPL",
    "gn:name":"Yanjiating",
    "gn:population":0,
    "gn:timezone":"Asia/Shanghai",
    "iso:country":"CN",
    "name:zho_x_preferred":[
        "\u989c\u5bb6\u753a"
    ],
    "wof:name":"Yanjiating",
    "wof:placetype":"locality"
},
  "geometry": {"coordinates":[113.02279,26.94411],"type":"Point"}
}