{
  "type": "Feature",
  "properties": {
    "gn:admin1_code":"18",
    "gn:asciiname":"Lantian",
    "gn:country_code":"CN",
    "gn:dem":938,
    "gn:feature_class":"P",
    "gn:feature_code":"PPL",
    "gn:name":"Lantian",
    "gn:population":0,
    "gn:timezone":"Asia/Shanghai",
    "iso:country":"CN",
    "name:zho_x_preferred":[
        "\u5170\u7530"
    ],
    "wof:name":"Lantian",
    "wof:placetype":"locality"
},
  "geometry": {"coordinates":[105.178,26.0955],"type":"Point"}
}