{
  "type": "Feature",
  "properties": {
    "gn:admin1_code":"30",
    "gn:asciiname":"Xiangshan",
    "gn:country_code":"CN",
    "gn:dem":41,
    "gn:feature_class":"P",
    "gn:feature_code":"PPL",
    "gn:name":"Xiangshan",
    "gn:population":0,
    "gn:timezone":"Asia/Shanghai",
    "iso:country":"CN",
    "name:und_x_variant":[
        "Xiangshanshi",
        "\u9999\u5c71\u5e02",
        "Xiangshan",
        "\u9999\u5c71"
    ],
    "name:zho_x_preferred":[
        "\u9999\u5c71\u5e02"
    ],
    "wof:name":"Xiangshan",
    "wof:placetype":"locality"
},
  "geometry": {"coordinates":[112.45652,22.753],"type":"Point"}
}