{
  "type": "Feature",
  "properties": {
    "gn:admin1_code":"25.0",
    "gn:asciiname":"Lujia",
    "gn:country_code":"CN",
    "gn:dem":16,
    "gn:feature_class":"P",
    "gn:feature_code":"PPL",
    "gn:name":"L\u00fcjia",
    "gn:population":0,
    "gn:timezone":"Asia/Shanghai",
    "iso:country":"CN",
    "name:und_x_variant":[
        "L\u00fcjia"
    ],
    "name:zho_x_preferred":[
        "\u5415\u5bb6"
    ],
    "wof:name":"Lujia",
    "wof:placetype":"locality"
},
  "geometry": {"coordinates":[119.99151000000001,37.33337],"type":"Point"}
}