{
  "type": "Feature",
  "properties": {
    "gn:admin1_code":"29.0",
    "gn:asciiname":"Liujiacun",
    "gn:country_code":"CN",
    "gn:dem":2076,
    "gn:feature_class":"P",
    "gn:feature_code":"PPL",
    "gn:name":"Liujiacun",
    "gn:population":0,
    "gn:timezone":"Asia/Shanghai",
    "iso:country":"CN",
    "name:zho_x_preferred":[
        "\u5218\u5bb6\u6751"
    ],
    "wof:name":"Liujiacun",
    "wof:placetype":"locality"
},
  "geometry": {"coordinates":[103.14700000000001,26.3234],"type":"Point"}
}