{
  "type": "Feature",
  "properties": {
    "gn:admin1_code":"32.0",
    "gn:asciiname":"Liangchahe",
    "gn:country_code":"CN",
    "gn:dem":1065,
    "gn:feature_class":"P",
    "gn:feature_code":"PPL",
    "gn:name":"Liangchahe",
    "gn:population":0,
    "gn:timezone":"Asia/Shanghai",
    "iso:country":"CN",
    "name:zho_x_preferred":[
        "\u4e24\u5c94\u6cb3"
    ],
    "wof:name":"Liangchahe",
    "wof:placetype":"locality"
},
  "geometry": {"coordinates":[104.496,32.3996],"type":"Point"}
}