{
  "type": "Feature",
  "properties": {
    "gn:admin1_code":"10.0",
    "gn:asciiname":"Xiguojiazhuang",
    "gn:country_code":"CN",
    "gn:dem":18,
    "gn:feature_class":"P",
    "gn:feature_code":"PPL",
    "gn:name":"Xiguojiazhuang",
    "gn:population":0,
    "gn:timezone":"Asia/Shanghai",
    "iso:country":"CN",
    "name:zho_x_preferred":[
        "\u897f\u90ed\u5bb6\u5e84"
    ],
    "wof:name":"Xiguojiazhuang",
    "wof:placetype":"locality"
},
  "geometry": {"coordinates":[115.786,38.4253],"type":"Point"}
}