{
  "type": "Feature",
  "properties": {
    "gn:admin1_code":"25.0",
    "gn:asciiname":"Daoxizhuangcun",
    "gn:country_code":"CN",
    "gn:dem":15,
    "gn:feature_class":"P",
    "gn:feature_code":"PPL",
    "gn:name":"Daoxizhuangcun",
    "gn:population":0,
    "gn:timezone":"Asia/Shanghai",
    "iso:country":"CN",
    "name:zho_x_preferred":[
        "\u5c9b\u897f\u5e84\u6751"
    ],
    "wof:name":"Daoxizhuangcun",
    "wof:placetype":"locality"
},
  "geometry": {"coordinates":[122.50568,36.90259],"type":"Point"}
}