{
  "type": "Feature",
  "properties": {
    "gn:admin1_code":"24.0",
    "gn:asciiname":"Luoyun",
    "gn:country_code":"CN",
    "gn:dem":956,
    "gn:feature_class":"P",
    "gn:feature_code":"PPL",
    "gn:name":"Luoyun",
    "gn:population":0,
    "gn:timezone":"Asia/Shanghai",
    "iso:country":"CN",
    "name:zho_x_preferred":[
        "\u7f57\u4e91"
    ],
    "wof:name":"Luoyun",
    "wof:placetype":"locality"
},
  "geometry": {"coordinates":[111.48806,36.40955],"type":"Point"}
}