{
  "type": "Feature",
  "properties": {
    "gn:admin1_code":"7",
    "gn:asciiname":"Qingliuxinken Nongchang",
    "gn:country_code":"CN",
    "gn:dem":512,
    "gn:feature_class":"P",
    "gn:feature_code":"PPLF",
    "gn:name":"Qingliuxinken Nongchang",
    "gn:population":0,
    "gn:timezone":"Asia/Shanghai",
    "iso:country":"CN",
    "name:zho_x_preferred":[
        "\u6e05\u6d41\u65b0\u57a6\u519c\u573a"
    ],
    "wof:name":"Qingliuxinken Nongchang",
    "wof:placetype":"locality"
},
  "geometry": {"coordinates":[117.07420999999999,26.30422],"type":"Point"}
}