{
  "type": "Feature",
  "properties": {
    "gn:admin1_code":"02",
    "gn:asciiname":"Yiwu,Zhejiang",
    "gn:country_code":"CN",
    "gn:dem":72,
    "gn:feature_class":"P",
    "gn:feature_code":"PPL",
    "gn:name":"Yiwu,Zhejiang",
    "gn:population":0,
    "gn:timezone":"Asia/Shanghai",
    "iso:country":"CN",
    "wof:name":"Yiwu,Zhejiang",
    "wof:placetype":"locality"
},
  "geometry": {"coordinates":[120.04761000000001,29.40611],"type":"Point"}
}