{
  "type": "Feature",
  "properties": {
    "gn:admin1_code":"10",
    "gn:asciiname":"Deyanqingmiao",
    "gn:country_code":"CN",
    "gn:dem":1335,
    "gn:feature_class":"P",
    "gn:feature_code":"PPL",
    "gn:name":"Deyanqingmiao",
    "gn:population":0,
    "gn:timezone":"Asia/Shanghai",
    "iso:country":"CN",
    "name:und_x_variant":[
        "Te-yen-chi-miao",
        "Deyanqingmiao"
    ],
    "name:zho_x_preferred":[
        "\u5fb7\u8a00\u5e86\u5e99"
    ],
    "wof:name":"Deyanqingmiao",
    "wof:placetype":"locality"
},
  "geometry": {"coordinates":[114.37645000000001,41.5549],"type":"Point"}
}