{
  "type": "Feature",
  "properties": {
    "gn:admin1_code":"7.0",
    "gn:asciiname":"Yandou",
    "gn:country_code":"CN",
    "gn:dem":549,
    "gn:feature_class":"P",
    "gn:feature_code":"PPL",
    "gn:name":"Yandou",
    "gn:population":0,
    "gn:timezone":"Asia/Shanghai",
    "iso:country":"CN",
    "name:und_x_variant":[
        "\u5ca9\u515c"
    ],
    "name:zho_x_preferred":[
        "\u5ca9\u515c"
    ],
    "wof:name":"Yandou",
    "wof:placetype":"locality"
},
  "geometry": {"coordinates":[118.15877999999999,26.42082000000001],"type":"Point"}
}