{
  "type": "Feature",
  "properties": {
    "gn:admin1_code":"08",
    "gn:asciiname":"Duibaoshan Dongtun",
    "gn:country_code":"CN",
    "gn:dem":201,
    "gn:feature_class":"P",
    "gn:feature_code":"PPL",
    "gn:name":"Duibaoshan Dongtun",
    "gn:population":0,
    "gn:timezone":"Asia/Shanghai",
    "iso:country":"CN",
    "name:und_x_variant":[
        "Duibaoshan"
    ],
    "name:zho_x_preferred":[
        "\u5bf9\u5b9d\u5c71\u4e1c\u5c6f"
    ],
    "wof:name":"Duibaoshan Dongtun",
    "wof:placetype":"locality"
},
  "geometry": {"coordinates":[123.07039,47.23921],"type":"Point"}
}