{
  "type": "Feature",
  "properties": {
    "gn:admin1_code":"12.0",
    "gn:asciiname":"Lao tsei (historical)",
    "gn:country_code":"CN",
    "gn:dem":29,
    "gn:feature_class":"P",
    "gn:feature_code":"PPL",
    "gn:name":"Lao tsei (historical)",
    "gn:population":0,
    "gn:timezone":"Asia/Shanghai",
    "iso:country":"CN",
    "wof:name":"Lao tsei (historical)",
    "wof:placetype":"locality"
},
  "geometry": {"coordinates":[113.54301,30.46369],"type":"Point"}
}