{
  "type": "Feature",
  "properties": {
    "gn:admin1_code":"30",
    "gn:asciiname":"Yongzengcun",
    "gn:country_code":"CN",
    "gn:dem":13,
    "gn:feature_class":"P",
    "gn:feature_code":"PPL",
    "gn:name":"Yongzengcun",
    "gn:population":0,
    "gn:timezone":"Asia/Urumqi",
    "iso:country":"CN",
    "name:zho_x_preferred":[
        "\u96cd\u589e\u6751"
    ],
    "wof:name":"Yongzengcun",
    "wof:placetype":"locality"
},
  "geometry": {"coordinates":[110.84914999999999,21.64042],"type":"Point"}
}