{
  "type": "Feature",
  "properties": {
    "gn:admin1_code":"3",
    "gn:asciiname":"Luojiang",
    "gn:country_code":"CN",
    "gn:dem":127,
    "gn:feature_class":"P",
    "gn:feature_code":"PPLA4",
    "gn:name":"Luojiang",
    "gn:population":0,
    "gn:timezone":"Asia/Shanghai",
    "iso:country":"CN",
    "name:und_x_variant":[
        "\u7f57\u6c5f",
        "Luojiangxu",
        "Luojiang Xiang",
        "\u7f57\u6c5f\u4e61",
        "\u7f57\u6c5f\u5729"
    ],
    "wof:name":"Luojiang",
    "wof:placetype":"locality"
},
  "geometry": {"coordinates":[115.25255,25.88001],"type":"Point"}
}