{
  "type": "Feature",
  "properties": {
    "gn:admin1_code":"9",
    "gn:asciiname":"Taofeng",
    "gn:country_code":"CN",
    "gn:dem":78,
    "gn:feature_class":"P",
    "gn:feature_code":"PPL",
    "gn:name":"Taofeng",
    "gn:population":0,
    "gn:timezone":"Asia/Shanghai",
    "iso:country":"CN",
    "name:zho_x_preferred":[
        "\u6843\u4e30"
    ],
    "wof:name":"Taofeng",
    "wof:placetype":"locality"
},
  "geometry": {"coordinates":[113.58969,33.62701],"type":"Point"}
}