{
  "type": "Feature",
  "properties": {
    "gn:admin1_code":"32.0",
    "gn:asciiname":"Yadong",
    "gn:country_code":"CN",
    "gn:dem":3754,
    "gn:feature_class":"P",
    "gn:feature_code":"PPL",
    "gn:name":"Yadong",
    "gn:population":0,
    "gn:timezone":"Asia/Shanghai",
    "iso:country":"CN",
    "name:zho_x_preferred":[
        "\u4e9a\u51bb"
    ],
    "name:zho_x_variant":[
        "\u4e9a\u51ac"
    ],
    "wof:name":"Yadong",
    "wof:placetype":"locality"
},
  "geometry": {"coordinates":[98.98439999999999,32.3653],"type":"Point"}
}