{
  "type": "Feature",
  "properties": {
    "gn:admin1_code":"29.0",
    "gn:asciiname":"Youdian",
    "gn:country_code":"CN",
    "gn:dem":1822,
    "gn:feature_class":"P",
    "gn:feature_code":"PPLA3",
    "gn:name":"Youdian",
    "gn:population":0,
    "gn:timezone":"Asia/Shanghai",
    "iso:country":"CN",
    "name:und_x_variant":[
        "Yu-tien",
        "Yu-tien-hsien-tso",
        "Changning",
        "Youdian"
    ],
    "name:zho_x_preferred":[
        "\u53f3\u7538"
    ],
    "wof:name":"Youdian",
    "wof:placetype":"locality"
},
  "geometry": {"coordinates":[99.59232,24.82894],"type":"Point"}
}