{
  "type": "Feature",
  "properties": {
    "gn:admin1_code":"26.0",
    "gn:asciiname":"Qilin Goucun",
    "gn:country_code":"CN",
    "gn:dem":1017,
    "gn:feature_class":"P",
    "gn:feature_code":"PPL",
    "gn:name":"Qilin Goucun",
    "gn:population":0,
    "gn:timezone":"Asia/Shanghai",
    "iso:country":"CN",
    "name:zho_x_preferred":[
        "\u9e92\u9e9f\u6c9f\u6751"
    ],
    "wof:name":"Qilin Goucun",
    "wof:placetype":"locality"
},
  "geometry": {"coordinates":[109.566,37.5631],"type":"Point"}
}