{
  "type": "Feature",
  "properties": {
    "gn:admin1_code":"32.0",
    "gn:asciiname":"Sanyuanmiao",
    "gn:country_code":"CN",
    "gn:dem":442,
    "gn:feature_class":"P",
    "gn:feature_code":"PPL",
    "gn:name":"Sanyuanmiao",
    "gn:population":0,
    "gn:timezone":"Asia/Shanghai",
    "iso:country":"CN",
    "name:zho_x_preferred":[
        "\u4e09\u5143\u5e99"
    ],
    "wof:name":"Sanyuanmiao",
    "wof:placetype":"locality"
},
  "geometry": {"coordinates":[105.107,30.2152],"type":"Point"}
}