{
  "type": "Feature",
  "properties": {
    "gn:admin1_code":"25",
    "gn:asciiname":"Guobotang",
    "gn:country_code":"CN",
    "gn:dem":51,
    "gn:feature_class":"P",
    "gn:feature_code":"PPL",
    "gn:name":"Guobotang",
    "gn:population":0,
    "gn:timezone":"Asia/Shanghai",
    "iso:country":"CN",
    "name:zho_x_preferred":[
        "\u90ed\u4f2f\u5802"
    ],
    "wof:name":"Guobotang",
    "wof:placetype":"locality"
},
  "geometry": {"coordinates":[115.50409999999999,35.03233],"type":"Point"}
}