{
  "type": "Feature",
  "properties": {
    "gn:admin1_code":"29.0",
    "gn:asciiname":"Banzhamo",
    "gn:country_code":"CN",
    "gn:dem":1344,
    "gn:feature_class":"P",
    "gn:feature_code":"PPL",
    "gn:name":"Banzhamo",
    "gn:population":0,
    "gn:timezone":"Asia/Shanghai",
    "iso:country":"CN",
    "name:zho_x_preferred":[
        "\u73ed\u624e\u6469"
    ],
    "wof:name":"Banzhamo",
    "wof:placetype":"locality"
},
  "geometry": {"coordinates":[99.67,22.322],"type":"Point"}
}