{
  "type": "Feature",
  "properties": {
    "gn:admin1_code":"9.0",
    "gn:asciiname":"Sunzhuang",
    "gn:country_code":"CN",
    "gn:dem":216,
    "gn:feature_class":"P",
    "gn:feature_code":"PPL",
    "gn:name":"Sunzhuang",
    "gn:population":0,
    "gn:timezone":"Asia/Shanghai",
    "iso:country":"CN",
    "name:ceb_x_preferred":[
        "Sunzhuang"
    ],
    "name:swe_x_preferred":[
        "Sunzhuang"
    ],
    "name:zho_x_preferred":[
        "\u5b59\u5e84"
    ],
    "wof:name":"Sunzhuang",
    "wof:placetype":"locality"
},
  "geometry": {"coordinates":[113.71519000000001,32.81398],"type":"Point"}
}