{
  "type": "Feature",
  "properties": {
    "gn:admin1_code":"19.0",
    "gn:asciiname":"Wangjiagoucun",
    "gn:country_code":"CN",
    "gn:dem":253,
    "gn:feature_class":"P",
    "gn:feature_code":"PPL",
    "gn:name":"Wangjiagoucun",
    "gn:population":0,
    "gn:timezone":"Asia/Shanghai",
    "iso:country":"CN",
    "name:und_x_variant":[
        "Wang-chia-t\u2019un"
    ],
    "name:zho_x_preferred":[
        "\u6c6a\u5bb6\u6c9f\u6751"
    ],
    "wof:name":"Wangjiagoucun",
    "wof:placetype":"locality"
},
  "geometry": {"coordinates":[125.00700000000001,42.3387],"type":"Point"}
}