{
  "type": "Feature",
  "properties": {
    "gn:admin1_code":"15.0",
    "gn:asciiname":"Dalijia",
    "gn:country_code":"CN",
    "gn:dem":1833,
    "gn:feature_class":"P",
    "gn:feature_code":"PPL",
    "gn:name":"Dalijia",
    "gn:population":0,
    "gn:timezone":"Asia/Shanghai",
    "iso:country":"CN",
    "name:und_x_variant":[
        "\u5927\u674e\u5bb6"
    ],
    "wof:name":"Dalijia",
    "wof:placetype":"locality"
},
  "geometry": {"coordinates":[105.102,35.8779],"type":"Point"}
}