{
  "type": "Feature",
  "properties": {
    "gn:admin1_code":"19.0",
    "gn:asciiname":"Hongtudicun",
    "gn:country_code":"CN",
    "gn:dem":62,
    "gn:feature_class":"P",
    "gn:feature_code":"PPL",
    "gn:name":"Hongtudicun",
    "gn:population":0,
    "gn:timezone":"Asia/Shanghai",
    "iso:country":"CN",
    "name:zho_x_preferred":[
        "\u7ea2\u571f\u5730\u6751"
    ],
    "wof:name":"Hongtudicun",
    "wof:placetype":"locality"
},
  "geometry": {"coordinates":[121.31699999999999,41.5636],"type":"Point"}
}