{
  "type": "Feature",
  "properties": {
    "gn:admin1_code":"25.0",
    "gn:asciiname":"Dongjiacun",
    "gn:cc2":"CN",
    "gn:country_code":"CN",
    "gn:dem":3,
    "gn:feature_class":"P",
    "gn:feature_code":"PPL",
    "gn:name":"Dongjiacun",
    "gn:population":0,
    "gn:timezone":"Asia/Shanghai",
    "iso:country":"CN",
    "name:zho_x_preferred":[
        "\u8463\u5bb6\u6751"
    ],
    "wof:name":"Dongjiacun",
    "wof:placetype":"locality"
},
  "geometry": {"coordinates":[119.64964000000001,35.62901],"type":"Point"}
}