{
  "type": "Feature",
  "properties": {
    "gn:admin1_code":"5.0",
    "gn:asciiname":"Qianliuhao",
    "gn:country_code":"CN",
    "gn:dem":167,
    "gn:feature_class":"P",
    "gn:feature_code":"PPL",
    "gn:name":"Qianliuhao",
    "gn:population":0,
    "gn:timezone":"Asia/Shanghai",
    "iso:country":"CN",
    "name:zho_x_preferred":[
        "\u524d\u516d\u53f7"
    ],
    "wof:name":"Qianliuhao",
    "wof:placetype":"locality"
},
  "geometry": {"coordinates":[123.76663000000001,44.22237],"type":"Point"}
}