{
  "type": "Feature",
  "properties": {
    "gn:admin1_code":"20",
    "gn:asciiname":"San-tao-ying-tzu",
    "gn:country_code":"CN",
    "gn:dem":582,
    "gn:feature_class":"P",
    "gn:feature_code":"PPL",
    "gn:name":"San-tao-ying-tzu",
    "gn:population":0,
    "gn:timezone":"Asia/Shanghai",
    "iso:country":"CN",
    "wof:name":"San-tao-ying-tzu",
    "wof:placetype":"locality"
},
  "geometry": {"coordinates":[119.15111,42.00194000000001],"type":"Point"}
}