{
  "type": "Feature",
  "properties": {
    "gn:admin1_code":"10.0",
    "gn:asciiname":"Anxia",
    "gn:country_code":"CN",
    "gn:dem":77,
    "gn:feature_class":"P",
    "gn:feature_code":"PPL",
    "gn:name":"Anxia",
    "gn:population":0,
    "gn:timezone":"Asia/Shanghai",
    "iso:country":"CN",
    "name:und_x_variant":[
        "\u5cb8\u4e0b"
    ],
    "wof:name":"Anxia",
    "wof:placetype":"locality"
},
  "geometry": {"coordinates":[114.57571000000002,38.19101],"type":"Point"}
}