{
  "type": "Feature",
  "properties": {
    "gn:admin1_code":"25.0",
    "gn:asciiname":"Wulizhuangcun",
    "gn:country_code":"CN",
    "gn:dem":52,
    "gn:feature_class":"P",
    "gn:feature_code":"PPL",
    "gn:name":"Wulizhuangcun",
    "gn:population":0,
    "gn:timezone":"Asia/Shanghai",
    "iso:country":"CN",
    "name:zho_x_preferred":[
        "\u4e94\u91cc\u5e84\u6751"
    ],
    "wof:name":"Wulizhuangcun",
    "wof:placetype":"locality"
},
  "geometry": {"coordinates":[120.22023,36.75865],"type":"Point"}
}