{
  "type": "Feature",
  "properties": {
    "gn:admin1_code":"26.0",
    "gn:asciiname":"Temagou",
    "gn:country_code":"CN",
    "gn:dem":1114,
    "gn:feature_class":"P",
    "gn:feature_code":"PPL",
    "gn:name":"Temagou",
    "gn:population":0,
    "gn:timezone":"Asia/Shanghai",
    "iso:country":"CN",
    "name:zho_x_preferred":[
        "\u7279\u9ebb\u6c9f"
    ],
    "wof:name":"Temagou",
    "wof:placetype":"locality"
},
  "geometry": {"coordinates":[110.37832,39.27145],"type":"Point"}
}