{
  "type": "Feature",
  "properties": {
    "gn:admin1_code":"14",
    "gn:asciiname":"Guobushu",
    "gn:country_code":"CN",
    "gn:dem":4769,
    "gn:feature_class":"P",
    "gn:feature_code":"PPL",
    "gn:name":"Guobushu",
    "gn:population":0,
    "gn:timezone":"Asia/Urumqi",
    "iso:country":"CN",
    "name:zho_x_preferred":[
        "\u679c\u5e03\u6570"
    ],
    "wof:name":"Guobushu",
    "wof:placetype":"locality"
},
  "geometry": {"coordinates":[89.0107,28.8699],"type":"Point"}
}