{
  "type": "Feature",
  "properties": {
    "gn:admin1_code":"32",
    "gn:asciiname":"Heling",
    "gn:country_code":"CN",
    "gn:dem":782,
    "gn:feature_class":"P",
    "gn:feature_code":"PPL",
    "gn:name":"Heling",
    "gn:population":0,
    "gn:timezone":"Asia/Shanghai",
    "iso:country":"CN",
    "name:und_x_variant":[
        "Helin",
        "Heling"
    ],
    "name:zho_x_preferred":[
        "\u9e64\u9f84"
    ],
    "wof:name":"Heling",
    "wof:placetype":"locality"
},
  "geometry": {"coordinates":[105.7516,31.86002],"type":"Point"}
}