{
  "type": "Feature",
  "properties": {
    "gn:admin1_code":"19.0",
    "gn:asciiname":"Wangmangou",
    "gn:country_code":"CN",
    "gn:dem":53,
    "gn:feature_class":"P",
    "gn:feature_code":"PPL",
    "gn:name":"Wangmangou",
    "gn:population":0,
    "gn:timezone":"Asia/Shanghai",
    "iso:country":"CN",
    "name:und_x_variant":[
        "\u738b\u6ee1\u6c9f"
    ],
    "name:zho_x_preferred":[
        "\u738b\u6ee1\u6c9f"
    ],
    "wof:name":"Wangmangou",
    "wof:placetype":"locality"
},
  "geometry": {"coordinates":[121.26913,41.16634000000001],"type":"Point"}
}