{
  "type": "Feature",
  "properties": {
    "gn:admin1_code":"32.0",
    "gn:asciiname":"Liujiao",
    "gn:country_code":"CN",
    "gn:dem":361,
    "gn:feature_class":"P",
    "gn:feature_code":"PPL",
    "gn:name":"Liujiao",
    "gn:population":0,
    "gn:timezone":"Asia/Shanghai",
    "iso:country":"CN",
    "name:zho_x_preferred":[
        "\u516d\u89d2"
    ],
    "wof:name":"Liujiao",
    "wof:placetype":"locality"
},
  "geometry": {"coordinates":[105.41500000000001,30.0056],"type":"Point"}
}