{
  "type": "Feature",
  "properties": {
    "gn:admin1_code":"32.0",
    "gn:asciiname":"Liujiao",
    "gn:country_code":"CN",
    "gn:dem":361,
    "gn:feature_class":"P",
    "gn:feature_code":"PPL",
    "gn:name":"Liujiao",
    "gn:population":0,
    "gn:timezone":"Asia/Shanghai",
    "iso:country":"CN",
    "name:hak_x_preferred":[
        "Liuk-kiok-hi\u00f4ng"
    ],
    "name:jpn_x_preferred":[
        "\u516d\u811a\u90f7"
    ],
    "name:kor_x_preferred":[
        "\ub958\uc790\uc624\ud5a5"
    ],
    "name:pol_x_preferred":[
        "Liujiao"
    ],
    "name:vie_x_preferred":[
        "L\u1ee5c C\u01b0\u1edbc"
    ],
    "name:zho_x_preferred":[
        "\u516d\u89d2"
    ],
    "name:zho_x_variant":[
        "\u516d\u8173\u9109"
    ],
    "wof:name":"Liujiao",
    "wof:placetype":"locality"
},
  "geometry": {"coordinates":[105.41500000000001,30.0056],"type":"Point"}
}