{
  "type": "Feature",
  "properties": {
    "gn:country":"CN",
    "iso:country":"CN",
    "name:cdo_x_preferred":[
        "\u971e\u6d66\u7e23"
    ],
    "name:deu_x_preferred":[
        "Xiapu"
    ],
    "name:eng_x_preferred":[
        "Xiapu County"
    ],
    "name:fas_x_preferred":[
        "\u0634\u0647\u0631\u0633\u062a\u0627\u0646 \u0634\u06cc\u0627\u067e\u0648"
    ],
    "name:gan_x_preferred":[
        "\u971e\u6d66\u53bf"
    ],
    "name:hak_x_preferred":[
        "H\u00e2-ph\u00fa-yen"
    ],
    "name:jpn_x_preferred":[
        "\u971e\u6d66\u770c"
    ],
    "name:kor_x_preferred":[
        "\uc0e4\ud478\ud604"
    ],
    "name:mwl_x_preferred":[
        "Xiapu"
    ],
    "name:nan_x_preferred":[
        "H\u00e2-ph\u00f3\u0358-ko\u0101n"
    ],
    "name:nld_x_preferred":[
        "Xiapu"
    ],
    "name:nob_x_preferred":[
        "Xiapu"
    ],
    "name:spa_x_preferred":[
        "Xi\u00e1p\u016d Xi\u00e0n"
    ],
    "name:swe_x_preferred":[
        "Xiapu"
    ],
    "name:vie_x_preferred":[
        "H\u00e0 Ph\u1ed1"
    ],
    "name:wuu_x_preferred":[
        "\u971e\u6d66\u53bf"
    ],
    "name:yue_x_preferred":[
        "\u971e\u6d66"
    ],
    "name:zho_x_preferred":[
        "\u971e\u6d66\u53bf"
    ],
    "qs:name":"\u971e\u6d66\u53bf",
    "qs:name_adm0":"\u4e2d\u570b",
    "qs:name_adm1":"\u798f\u5efa\u7701",
    "qs:photos":219,
    "qs:photos_1k":44,
    "qs:photos_9k":1,
    "qs:photos_9r":4,
    "qs:photos_all":281,
    "qs:photos_sr":4,
    "qs:placetype":"LocalAdmin",
    "qs:pop_sr":"0",
    "wd:wordcount":255,
    "wof:name":"\u971e\u6d66\u53bf",
    "wof:placetype":"localadmin"
},
  "geometry": {"coordinates":[120.050354,26.885636],"type":"Point"}
}