{
  "type": "Feature",
  "properties": {
    "gn:country":"CN",
    "iso:country":"CN",
    "qs:name":"\u971e\u6d66\u53bf",
    "qs:name_adm0":"\u4e2d\u570b",
    "qs:name_adm1":"\u798f\u5efa\u7701",
    "qs:photos":219,
    "qs:photos_1k":44,
    "qs:photos_9k":1,
    "qs:photos_9r":4,
    "qs:photos_all":281,
    "qs:photos_sr":4,
    "qs:placetype":"LocalAdmin",
    "qs:pop_sr":"0",
    "wd:wordcount":255,
    "wof:name":"\u971e\u6d66\u53bf",
    "wof:placetype":"localadmin"
},
  "geometry": {"coordinates":[120.050354,26.885636],"type":"Point"}
}