{
  "type": "Feature",
  "properties": {
    "gn:admin1_code":"18",
    "gn:asciiname":"Wenchangmiao",
    "gn:country_code":"CN",
    "gn:dem":445,
    "gn:feature_class":"P",
    "gn:feature_code":"PPL",
    "gn:name":"Wenchangmiao",
    "gn:population":0,
    "gn:timezone":"Asia/Shanghai",
    "iso:country":"CN",
    "name:zho_x_preferred":[
        "\u6587\u660c\u5e99"
    ],
    "wof:name":"Wenchangmiao",
    "wof:placetype":"locality"
},
  "geometry": {"coordinates":[106.08199999999999,28.5961],"type":"Point"}
}