{
  "type": "Feature",
  "properties": {
    "gn:admin1_code":"12.0",
    "gn:asciiname":"Shitouya",
    "gn:country_code":"CN",
    "gn:dem":1249,
    "gn:feature_class":"P",
    "gn:feature_code":"PPL",
    "gn:name":"Shitouya",
    "gn:population":0,
    "gn:timezone":"Asia/Shanghai",
    "iso:country":"CN",
    "name:zho_x_preferred":[
        "\u77f3\u5934\u57ad"
    ],
    "wof:name":"Shitouya",
    "wof:placetype":"locality"
},
  "geometry": {"coordinates":[110.58122,31.09066],"type":"Point"}
}