{
  "type": "Feature",
  "properties": {
    "gn:admin1_code":"5.0",
    "gn:asciiname":"Yushu Linzicun",
    "gn:country_code":"CN",
    "gn:dem":248,
    "gn:feature_class":"P",
    "gn:feature_code":"PPL",
    "gn:name":"Yushu Linzicun",
    "gn:population":0,
    "gn:timezone":"Asia/Shanghai",
    "iso:country":"CN",
    "name:zho_x_preferred":[
        "\u6986\u6811\u6797\u5b50\u6751"
    ],
    "wof:name":"Yushu Linzicun",
    "wof:placetype":"locality"
},
  "geometry": {"coordinates":[125.08644,43.30067],"type":"Point"}
}