{
  "type": "Feature",
  "properties": {
    "gn:admin1_code":"32.0",
    "gn:asciiname":"Xiyandong",
    "gn:country_code":"CN",
    "gn:dem":2112,
    "gn:feature_class":"P",
    "gn:feature_code":"PPL",
    "gn:name":"Xiyandong",
    "gn:population":0,
    "gn:timezone":"Asia/Shanghai",
    "iso:country":"CN",
    "name:zho_x_preferred":[
        "\u897f\u71d5\u6d1e"
    ],
    "wof:name":"Xiyandong",
    "wof:placetype":"locality"
},
  "geometry": {"coordinates":[102.60899999999999,29.2889],"type":"Point"}
}