{
  "type": "Feature",
  "properties": {
    "gn:admin1_code":"7",
    "gn:asciiname":"Qinyang",
    "gn:country_code":"CN",
    "gn:dem":560,
    "gn:feature_class":"P",
    "gn:feature_code":"PPL",
    "gn:name":"Qinyang",
    "gn:population":0,
    "gn:timezone":"Asia/Shanghai",
    "iso:country":"CN",
    "name:zho_x_preferred":[
        "\u82b9\u6d0b"
    ],
    "wof:name":"Qinyang",
    "wof:placetype":"locality"
},
  "geometry": {"coordinates":[118.95950000000001,25.93897],"type":"Point"}
}