{
  "type": "Feature",
  "properties": {
    "gn:admin1_code":"24.0",
    "gn:asciiname":"Zhuangcheping",
    "gn:country_code":"CN",
    "gn:dem":1493,
    "gn:feature_class":"P",
    "gn:feature_code":"PPL",
    "gn:name":"Zhuangcheping",
    "gn:population":0,
    "gn:timezone":"Asia/Shanghai",
    "iso:country":"CN",
    "name:zho_x_preferred":[
        "\u5e84\u8f66\u576a"
    ],
    "wof:name":"Zhuangcheping",
    "wof:placetype":"locality"
},
  "geometry": {"coordinates":[112.12662,38.61422],"type":"Point"}
}