{
  "type": "Feature",
  "properties": {
    "gn:admin1_code":"3.0",
    "gn:asciiname":"Zuojiazhuang",
    "gn:country_code":"CN",
    "gn:dem":46,
    "gn:feature_class":"P",
    "gn:feature_code":"PPL",
    "gn:name":"Zuojiazhuang",
    "gn:population":0,
    "gn:timezone":"Asia/Shanghai",
    "iso:country":"CN",
    "name:und_x_variant":[
        "\u5de6\u5bb6\u5e84"
    ],
    "wof:name":"Zuojiazhuang",
    "wof:placetype":"locality"
},
  "geometry": {"coordinates":[115.51803999999998,28.69012],"type":"Point"}
}