{
  "type": "Feature",
  "properties": {
    "gn:admin1_code":"29.0",
    "gn:asciiname":"Baozipo",
    "gn:country_code":"CN",
    "gn:dem":1454,
    "gn:feature_class":"P",
    "gn:feature_code":"PPL",
    "gn:name":"Baozipo",
    "gn:population":0,
    "gn:timezone":"Asia/Shanghai",
    "iso:country":"CN",
    "name:zho_x_preferred":[
        "\u8c79\u5b50\u5761"
    ],
    "wof:name":"Baozipo",
    "wof:placetype":"locality"
},
  "geometry": {"coordinates":[104.098,24.1198],"type":"Point"}
}