{
  "type": "Feature",
  "properties": {
    "gn:admin1_code":"12.0",
    "gn:asciiname":"Yawugou",
    "gn:country_code":"CN",
    "gn:dem":1305,
    "gn:feature_class":"P",
    "gn:feature_code":"PPL",
    "gn:name":"Yawugou",
    "gn:population":0,
    "gn:timezone":"Asia/Shanghai",
    "iso:country":"CN",
    "name:zho_x_preferred":[
        "\u5d16\u5c4b\u6c9f"
    ],
    "wof:name":"Yawugou",
    "wof:placetype":"locality"
},
  "geometry": {"coordinates":[110.73056,31.85819],"type":"Point"}
}