{
  "type": "Feature",
  "properties": {
    "gn:admin1_code":"10",
    "gn:asciiname":"Dule",
    "gn:cc2":"CN",
    "gn:country_code":"CN",
    "gn:dem":143,
    "gn:feature_class":"P",
    "gn:feature_code":"PPL",
    "gn:name":"Dule",
    "gn:population":0,
    "gn:timezone":"Asia/Shanghai",
    "iso:country":"CN",
    "name:bos_x_preferred":[
        "Dule"
    ],
    "name:ceb_x_preferred":[
        "Dule"
    ],
    "name:hrv_x_preferred":[
        "Dule"
    ],
    "name:nld_x_preferred":[
        "Dule"
    ],
    "name:pol_x_preferred":[
        "Dule"
    ],
    "name:slv_x_preferred":[
        "Dule"
    ],
    "name:srp_x_preferred":[
        "\u0414\u0443\u043b\u0435"
    ],
    "name:swe_x_preferred":[
        "Dule"
    ],
    "name:und_x_variant":[
        "Tung-tu-lo",
        "Tu-le",
        "Dule"
    ],
    "wof:name":"Dule",
    "wof:placetype":"locality"
},
  "geometry": {"coordinates":[115.21111000000001,39.08056],"type":"Point"}
}