{
  "type": "Feature",
  "properties": {
    "gn:admin1_code":"29",
    "gn:asciiname":"Yangcaotian",
    "gn:country_code":"CN",
    "gn:dem":1622,
    "gn:feature_class":"P",
    "gn:feature_code":"PPL",
    "gn:name":"Yangcaotian",
    "gn:population":0,
    "gn:timezone":"Asia/Shanghai",
    "iso:country":"CN",
    "name:zho_x_preferred":[
        "\u79e7\u8349\u7530"
    ],
    "wof:name":"Yangcaotian",
    "wof:placetype":"locality"
},
  "geometry": {"coordinates":[103.203,24.9541],"type":"Point"}
}