{
  "type": "Feature",
  "properties": {
    "gn:admin1_code":"11.0",
    "gn:asciiname":"Gongjiaping",
    "gn:country_code":"CN",
    "gn:dem":39,
    "gn:feature_class":"P",
    "gn:feature_code":"PPL",
    "gn:name":"Gongjiaping",
    "gn:population":0,
    "gn:timezone":"Asia/Shanghai",
    "iso:country":"CN",
    "name:zho_x_preferred":[
        "\u9f9a\u5bb6\u576a"
    ],
    "wof:name":"Gongjiaping",
    "wof:placetype":"locality"
},
  "geometry": {"coordinates":[112.22824,28.60538],"type":"Point"}
}