{
  "type": "Feature",
  "properties": {
    "gn:admin1_code":"4.0",
    "gn:asciiname":"Xiasanhe",
    "gn:country_code":"CN",
    "gn:dem":4,
    "gn:feature_class":"P",
    "gn:feature_code":"PPLA4",
    "gn:name":"Xiasanhe",
    "gn:population":0,
    "gn:timezone":"Asia/Shanghai",
    "iso:country":"CN",
    "name:und_x_variant":[
        "Wan-sheng-sha",
        "Xiasanhe",
        "\u4e0b\u4e09\u548c",
        "Wannian",
        "Wannian Zhen",
        "\u4e07\u5e74",
        "\u4e07\u5e74\u9547"
    ],
    "wof:name":"Xiasanhe",
    "wof:placetype":"locality"
},
  "geometry": {"coordinates":[121.41929,31.98228],"type":"Point"}
}