{
  "type": "Feature",
  "properties": {
    "gn:admin1_code":"25",
    "gn:asciiname":"Songjia Zhuangzi",
    "gn:country_code":"CN",
    "gn:dem":6,
    "gn:feature_class":"P",
    "gn:feature_code":"PPL",
    "gn:name":"Songjia Zhuangzi",
    "gn:population":0,
    "gn:timezone":"Asia/Shanghai",
    "iso:country":"CN",
    "name:zho_x_preferred":[
        "\u5b8b\u5bb6\u5e84\u5b50"
    ],
    "wof:name":"Songjia Zhuangzi",
    "wof:placetype":"locality"
},
  "geometry": {"coordinates":[118.15300000000001,37.7786],"type":"Point"}
}