{
  "type": "Feature",
  "properties": {
    "gn:admin1_code":"26.0",
    "gn:asciiname":"Luanshijiaocun",
    "gn:country_code":"CN",
    "gn:dem":813,
    "gn:feature_class":"P",
    "gn:feature_code":"PPL",
    "gn:name":"Luanshijiaocun",
    "gn:population":0,
    "gn:timezone":"Asia/Shanghai",
    "iso:country":"CN",
    "name:zho_x_preferred":[
        "\u4e71\u77f3\u7a96\u6751"
    ],
    "wof:name":"Luanshijiaocun",
    "wof:placetype":"locality"
},
  "geometry": {"coordinates":[109.44483,33.31586],"type":"Point"}
}