{
  "type": "Feature",
  "properties": {
    "gn:admin1_code":"14.0",
    "gn:asciiname":"Jiabuneiri'a",
    "gn:country_code":"CN",
    "gn:dem":5017,
    "gn:feature_class":"P",
    "gn:feature_code":"PPL",
    "gn:name":"Jiabuneiri\u2019a",
    "gn:population":0,
    "gn:timezone":"Asia/Urumqi",
    "iso:country":"CN",
    "name:und_x_variant":[
        "Jiabuneiri\u2019a"
    ],
    "name:zho_x_preferred":[
        "\u52a0\u5e03\u5185\u65e5\u963f"
    ],
    "wof:name":"Jiabuneiri'a",
    "wof:placetype":"locality"
},
  "geometry": {"coordinates":[85.8175,31.7549],"type":"Point"}
}