{
  "type": "Feature",
  "properties": {
    "gn:admin1_code":"32.0",
    "gn:asciiname":"Zhongzuishang",
    "gn:country_code":"CN",
    "gn:dem":318,
    "gn:feature_class":"P",
    "gn:feature_code":"PPL",
    "gn:name":"Zhongzuishang",
    "gn:population":0,
    "gn:timezone":"Asia/Shanghai",
    "iso:country":"CN",
    "name:zho_x_preferred":[
        "\u4e2d\u5480\u4e0a"
    ],
    "wof:name":"Zhongzuishang",
    "wof:placetype":"locality"
},
  "geometry": {"coordinates":[104.57599999999999,28.876],"type":"Point"}
}