{
  "type": "Feature",
  "properties": {
    "gn:admin1_code":"16.0",
    "gn:asciiname":"Huili",
    "gn:country_code":"CN",
    "gn:dem":430,
    "gn:feature_class":"P",
    "gn:feature_code":"PPL",
    "gn:name":"Huili",
    "gn:population":0,
    "gn:timezone":"Asia/Shanghai",
    "iso:country":"CN",
    "name:zho_x_preferred":[
        "\u8334\u5229"
    ],
    "wof:name":"Huili",
    "wof:placetype":"locality"
},
  "geometry": {"coordinates":[107.34699999999999,23.2415],"type":"Point"}
}