{
  "type": "Feature",
  "properties": {
    "gn:admin1_code":"26.0",
    "gn:asciiname":"Baijia Pancun",
    "gn:country_code":"CN",
    "gn:dem":1108,
    "gn:feature_class":"P",
    "gn:feature_code":"PPL",
    "gn:name":"Baijia Pancun",
    "gn:population":0,
    "gn:timezone":"Asia/Shanghai",
    "iso:country":"CN",
    "name:zho_x_preferred":[
        "\u767d\u5bb6\u7554\u6751"
    ],
    "wof:name":"Baijia Pancun",
    "wof:placetype":"locality"
},
  "geometry": {"coordinates":[110.443,38.7329],"type":"Point"}
}