{
  "type": "Feature",
  "properties": {
    "gn:admin1_code":"14",
    "gn:asciiname":"Yidadui",
    "gn:country_code":"CN",
    "gn:dem":4540,
    "gn:feature_class":"P",
    "gn:feature_code":"PPLF",
    "gn:name":"Yidadui",
    "gn:population":0,
    "gn:timezone":"Asia/Urumqi",
    "iso:country":"CN",
    "name:zho_x_preferred":[
        "\u4e00\u5927\u961f"
    ],
    "wof:name":"Yidadui",
    "wof:placetype":"locality"
},
  "geometry": {"coordinates":[88.7299,31.9849],"type":"Point"}
}