{
  "type": "Feature",
  "properties": {
    "gn:admin1_code":"3.0",
    "gn:asciiname":"Chuanlongke",
    "gn:country_code":"CN",
    "gn:dem":328,
    "gn:feature_class":"P",
    "gn:feature_code":"PPL",
    "gn:name":"Chuanlongke",
    "gn:population":0,
    "gn:timezone":"Asia/Shanghai",
    "iso:country":"CN",
    "name:und_x_variant":[
        "\u5ddd\u9f99\u7aa0"
    ],
    "wof:name":"Chuanlongke",
    "wof:placetype":"locality"
},
  "geometry": {"coordinates":[115.65293,24.68896],"type":"Point"}
}