{
  "type": "Feature",
  "properties": {
    "gn:admin1_code":"2.0",
    "gn:asciiname":"Puquan",
    "gn:country_code":"CN",
    "gn:dem":243,
    "gn:feature_class":"P",
    "gn:feature_code":"PPL",
    "gn:name":"Puquan",
    "gn:population":0,
    "gn:timezone":"Asia/Shanghai",
    "iso:country":"CN",
    "name:zho_x_preferred":[
        "\u7011\u6cc9"
    ],
    "wof:name":"Puquan",
    "wof:placetype":"locality"
},
  "geometry": {"coordinates":[120.00502,28.42841],"type":"Point"}
}