{
  "type": "Feature",
  "properties": {
    "gn:admin1_code":"9.0",
    "gn:asciiname":"Madian",
    "gn:country_code":"CN",
    "gn:dem":109,
    "gn:feature_class":"P",
    "gn:feature_code":"PPL",
    "gn:name":"Madian",
    "gn:population":0,
    "gn:timezone":"Asia/Shanghai",
    "iso:country":"CN",
    "name:ceb_x_preferred":[
        "Madian"
    ],
    "name:swe_x_preferred":[
        "Madian"
    ],
    "name:zho_x_preferred":[
        "\u9ebb\u5e97"
    ],
    "wof:name":"Madian",
    "wof:placetype":"locality"
},
  "geometry": {"coordinates":[113.75142,34.30284],"type":"Point"}
}