{
  "type": "Feature",
  "properties": {
    "gn:admin1_code":"32.0",
    "gn:asciiname":"Zhoujia Yakou",
    "gn:country_code":"CN",
    "gn:dem":356,
    "gn:feature_class":"P",
    "gn:feature_code":"PPL",
    "gn:name":"Zhoujia Yakou",
    "gn:population":0,
    "gn:timezone":"Asia/Shanghai",
    "iso:country":"CN",
    "name:zho_x_preferred":[
        "\u5468\u5bb6\u54d1\u53e3"
    ],
    "wof:name":"Zhoujia Yakou",
    "wof:placetype":"locality"
},
  "geometry": {"coordinates":[106.65433,30.4415],"type":"Point"}
}