{
  "type": "Feature",
  "properties": {
    "gn:admin1_code":"12.0",
    "gn:asciiname":"Shangliugu",
    "gn:country_code":"CN",
    "gn:dem":27,
    "gn:feature_class":"P",
    "gn:feature_code":"PPL",
    "gn:name":"Shangliugu",
    "gn:population":0,
    "gn:timezone":"Asia/Shanghai",
    "iso:country":"CN",
    "name:und_x_variant":[
        "\u4e0a\u516d\u80a1"
    ],
    "wof:name":"Shangliugu",
    "wof:placetype":"locality"
},
  "geometry": {"coordinates":[114.16343999999999,30.13461],"type":"Point"}
}