{
  "type": "Feature",
  "properties": {
    "gn:admin1_code":"11.0",
    "gn:asciiname":"Laowu Tangjia",
    "gn:country_code":"CN",
    "gn:dem":230,
    "gn:feature_class":"P",
    "gn:feature_code":"PPL",
    "gn:name":"Laowu Tangjia",
    "gn:population":0,
    "gn:timezone":"Asia/Shanghai",
    "iso:country":"CN",
    "name:zho_x_preferred":[
        "\u8001\u5c4b\u5510\u5bb6"
    ],
    "wof:name":"Laowu Tangjia",
    "wof:placetype":"locality"
},
  "geometry": {"coordinates":[111.3164,27.1464],"type":"Point"}
}