{
  "type": "Feature",
  "properties": {
    "gn:admin1_code":"15.0",
    "gn:asciiname":"Zecha",
    "gn:country_code":"CN",
    "gn:dem":3238,
    "gn:feature_class":"P",
    "gn:feature_code":"PPL",
    "gn:name":"Zecha",
    "gn:population":0,
    "gn:timezone":"Asia/Shanghai",
    "iso:country":"CN",
    "name:zho_x_preferred":[
        "\u5219\u5c94"
    ],
    "wof:name":"Zecha",
    "wof:placetype":"locality"
},
  "geometry": {"coordinates":[102.68600000000001,34.3528],"type":"Point"}
}