{
  "type": "Feature",
  "properties": {
    "gn:admin1_code":"11.0",
    "gn:asciiname":"Youmachong",
    "gn:country_code":"CN",
    "gn:dem":315,
    "gn:feature_class":"P",
    "gn:feature_code":"PPL",
    "gn:name":"Youmachong",
    "gn:population":0,
    "gn:timezone":"Asia/Shanghai",
    "iso:country":"CN",
    "name:zho_x_preferred":[
        "\u6cb9\u9ebb\u51b2"
    ],
    "wof:name":"Youmachong",
    "wof:placetype":"locality"
},
  "geometry": {"coordinates":[109.58723999999999,27.26556],"type":"Point"}
}