{
  "type": "Feature",
  "properties": {
    "gn:admin1_code":"32.0",
    "gn:asciiname":"Beidou",
    "gn:country_code":"CN",
    "gn:dem":306,
    "gn:feature_class":"P",
    "gn:feature_code":"PPL",
    "gn:name":"Beidou",
    "gn:population":0,
    "gn:timezone":"Asia/Shanghai",
    "iso:country":"CN",
    "name:zho_x_preferred":[
        "\u5317\u6597"
    ],
    "wof:name":"Beidou",
    "wof:placetype":"locality"
},
  "geometry": {"coordinates":[105.616,30.0038],"type":"Point"}
}