{
  "type": "Feature",
  "properties": {
    "gn:admin1_code":"18.0",
    "gn:asciiname":"Gunlongpo",
    "gn:country_code":"CN",
    "gn:dem":724,
    "gn:feature_class":"P",
    "gn:feature_code":"PPL",
    "gn:name":"Gunlongpo",
    "gn:population":0,
    "gn:timezone":"Asia/Shanghai",
    "iso:country":"CN",
    "name:zho_x_preferred":[
        "\u6eda\u9f99\u5761"
    ],
    "wof:name":"Gunlongpo",
    "wof:placetype":"locality"
},
  "geometry": {"coordinates":[107.80500000000001,27.0406],"type":"Point"}
}