{
  "type": "Feature",
  "properties": {
    "gn:admin1_code":"23",
    "gn:asciiname":"Pengsancun",
    "gn:country_code":"CN",
    "gn:dem":5,
    "gn:feature_class":"P",
    "gn:feature_code":"PPL",
    "gn:name":"Pengsancun",
    "gn:population":0,
    "gn:timezone":"Asia/Shanghai",
    "iso:country":"CN",
    "name:zho_x_preferred":[
        "\u5f6d\u4e09\u6751"
    ],
    "wof:name":"Pengsancun",
    "wof:placetype":"locality"
},
  "geometry": {"coordinates":[121.77785,30.87958],"type":"Point"}
}