{
  "type": "Feature",
  "properties": {
    "gn:admin1_code":"30.0",
    "gn:asciiname":"Litou",
    "gn:country_code":"CN",
    "gn:dem":660,
    "gn:feature_class":"P",
    "gn:feature_code":"PPL",
    "gn:name":"Litou",
    "gn:population":0,
    "gn:timezone":"Asia/Shanghai",
    "iso:country":"CN",
    "name:zho_x_preferred":[
        "\u783e\u5934"
    ],
    "wof:name":"Litou",
    "wof:placetype":"locality"
},
  "geometry": {"coordinates":[113.52542,25.29628],"type":"Point"}
}