{
  "type": "Feature",
  "properties": {
    "gn:admin1_code":"3",
    "gn:asciiname":"Ducheng",
    "gn:country_code":"CN",
    "gn:dem":52,
    "gn:feature_class":"P",
    "gn:feature_code":"PPLA4",
    "gn:name":"Ducheng",
    "gn:population":0,
    "gn:timezone":"Asia/Shanghai",
    "iso:country":"CN",
    "name:und_x_variant":[
        "\u72ec\u57ce",
        "Duchengxu",
        "Ducheng Zhen",
        "\u72ec\u57ce\u9547"
    ],
    "wof:name":"Ducheng",
    "wof:placetype":"locality"
},
  "geometry": {"coordinates":[115.49153,28.23346],"type":"Point"}
}