{
  "type": "Feature",
  "properties": {
    "gn:admin1_code":"5.0",
    "gn:asciiname":"Huangni Hezi",
    "gn:country_code":"CN",
    "gn:dem":313,
    "gn:feature_class":"P",
    "gn:feature_code":"PPL",
    "gn:name":"Huangni Hezi",
    "gn:population":0,
    "gn:timezone":"Asia/Shanghai",
    "iso:country":"CN",
    "name:zho_x_preferred":[
        "\u9ec4\u6ce5\u6cb3\u5b50"
    ],
    "wof:name":"Huangni Hezi",
    "wof:placetype":"locality"
},
  "geometry": {"coordinates":[127.09045,44.17764],"type":"Point"}
}