{
  "type": "Feature",
  "properties": {
    "gn:admin1_code":"25",
    "gn:asciiname":"Jieshou Yicun",
    "gn:country_code":"CN",
    "gn:dem":48,
    "gn:feature_class":"P",
    "gn:feature_code":"PPL",
    "gn:name":"Jieshou Yicun",
    "gn:population":0,
    "gn:timezone":"Asia/Shanghai",
    "iso:country":"CN",
    "name:zho_x_preferred":[
        "\u754c\u9996\u4e00\u6751"
    ],
    "wof:name":"Jieshou Yicun",
    "wof:placetype":"locality"
},
  "geometry": {"coordinates":[118.869,35.0584],"type":"Point"}
}