{
  "type": "Feature",
  "properties": {
    "gn:admin1_code":"29.0",
    "gn:asciiname":"Boluoling",
    "gn:country_code":"CN",
    "gn:dem":1467,
    "gn:feature_class":"P",
    "gn:feature_code":"PPL",
    "gn:name":"Boluoling",
    "gn:population":0,
    "gn:timezone":"Asia/Shanghai",
    "iso:country":"CN",
    "name:zho_x_preferred":[
        "\u83e0\u841d\u5cad"
    ],
    "wof:name":"Boluoling",
    "wof:placetype":"locality"
},
  "geometry": {"coordinates":[100.328,23.0732],"type":"Point"}
}