{
  "type": "Feature",
  "properties": {
    "gn:admin1_code":"1.0",
    "gn:asciiname":"Leiyang",
    "gn:country_code":"CN",
    "gn:dem":15,
    "gn:feature_class":"P",
    "gn:feature_code":"PPLA3",
    "gn:name":"Leiyang",
    "gn:population":0,
    "gn:timezone":"Asia/Shanghai",
    "iso:country":"CN",
    "name:und_x_variant":[
        "Wang-chiang",
        "Wangkiang-hsien",
        "Wang-chiang-hsien",
        "Wangkiang",
        "Wangjiang",
        "Leiyang",
        "Wangjiang Xian"
    ],
    "name:zho_x_preferred":[
        "\u671b\u6c5f"
    ],
    "name:zho_x_variant":[
        "\u96f7\u9633",
        "\u671b\u6c5f\u53bf"
    ],
    "wof:name":"Leiyang",
    "wof:placetype":"locality"
},
  "geometry": {"coordinates":[116.68292,30.12043],"type":"Point"}
}