{
  "type": "Feature",
  "properties": {
    "gn:admin1_code":"1.0",
    "gn:asciiname":"Leiyang",
    "gn:country_code":"CN",
    "gn:dem":15,
    "gn:feature_class":"P",
    "gn:feature_code":"PPLA3",
    "gn:name":"Leiyang",
    "gn:population":0,
    "gn:timezone":"Asia/Shanghai",
    "iso:country":"CN",
    "name:ceb_x_preferred":[
        "Leiyang"
    ],
    "name:deu_x_preferred":[
        "Leiyang"
    ],
    "name:fra_x_preferred":[
        "Leiyang"
    ],
    "name:hak_x_preferred":[
        "L\u00f3i-y\u00f2ng-s\u1e73"
    ],
    "name:ita_x_preferred":[
        "Leiyang"
    ],
    "name:jpn_x_preferred":[
        "\u8012\u967d\u5e02"
    ],
    "name:kik_x_preferred":[
        "Leiyang"
    ],
    "name:kor_x_preferred":[
        "\ub808\uc774\uc591\uc2dc"
    ],
    "name:mlg_x_preferred":[
        "Leiyang"
    ],
    "name:nor_x_preferred":[
        "Leiyang"
    ],
    "name:pam_x_preferred":[
        "Leiyang"
    ],
    "name:rus_x_preferred":[
        "\u041b\u044d\u0439\u044f\u043d"
    ],
    "name:swe_x_preferred":[
        "Leiyang"
    ],
    "name:und_x_variant":[
        "Wang-chiang",
        "Wangkiang-hsien",
        "Wang-chiang-hsien",
        "Wangkiang",
        "Wangjiang",
        "Wangjiang Xian"
    ],
    "name:vie_x_preferred":[
        "L\u1ed7i D\u01b0\u01a1ng"
    ],
    "name:war_x_preferred":[
        "Leiyang"
    ],
    "name:zho_x_preferred":[
        "\u671b\u6c5f"
    ],
    "name:zho_x_variant":[
        "\u96f7\u9633",
        "\u671b\u6c5f\u53bf",
        "\u8012\u9633\u5e02"
    ],
    "wof:name":"Leiyang",
    "wof:placetype":"locality"
},
  "geometry": {"coordinates":[116.68292,30.12043],"type":"Point"}
}