{
  "type": "Feature",
  "properties": {
    "iso:country":"CN",
    "qs:name":"\u5609\u5584\u53bf",
    "qs:name_adm0":"\u4e2d\u570b",
    "qs:name_adm1":"\u6d59\u6c5f\u7701",
    "qs:photos":2,
    "qs:photos_1k":1,
    "qs:photos_9k":15,
    "qs:photos_9r":11,
    "qs:photos_all":3399,
    "qs:photos_sr":1,
    "qs:placetype":"LocalAdmin",
    "qs:pop_sr":"0",
    "wd:wordcount":188,
    "wof:name":"\u5609\u5584\u53bf",
    "wof:placetype":"localadmin"
},
  "geometry": {"coordinates":[120.88888900000001,30.947647],"type":"Point"}
}