{
  "type": "Feature",
  "properties": {
    "iso:country":"CN",
    "name:ceb_x_preferred":[
        "Jiashan Xian"
    ],
    "name:deu_x_preferred":[
        "Jiashan"
    ],
    "name:eng_x_preferred":[
        "Jiashan County"
    ],
    "name:fas_x_preferred":[
        "\u0634\u0647\u0631\u0633\u062a\u0627\u0646 \u062c\u06cc\u0627\u0634\u0627\u0646"
    ],
    "name:gan_x_preferred":[
        "\u5609\u5584\u53bf"
    ],
    "name:jpn_x_preferred":[
        "\u5609\u5584\u770c"
    ],
    "name:kor_x_preferred":[
        "\uc790\uc0b0\ud604"
    ],
    "name:nan_x_preferred":[
        "Ka-si\u0101n-ko\u0101n"
    ],
    "name:nld_x_preferred":[
        "Jiashan"
    ],
    "name:nob_x_preferred":[
        "Jiashan"
    ],
    "name:swe_x_preferred":[
        "Jiashan"
    ],
    "name:vie_x_preferred":[
        "Gia Thi\u1ec7n"
    ],
    "name:wuu_x_preferred":[
        "\u5609\u5584"
    ],
    "name:yue_x_preferred":[
        "\u5609\u5584"
    ],
    "name:zho_x_preferred":[
        "\u5609\u5584\u53bf"
    ],
    "qs:name":"\u5609\u5584\u53bf",
    "qs:name_adm0":"\u4e2d\u570b",
    "qs:name_adm1":"\u6d59\u6c5f\u7701",
    "qs:photos":2,
    "qs:photos_1k":1,
    "qs:photos_9k":15,
    "qs:photos_9r":11,
    "qs:photos_all":3399,
    "qs:photos_sr":1,
    "qs:placetype":"LocalAdmin",
    "qs:pop_sr":"0",
    "wd:wordcount":188,
    "wof:name":"\u5609\u5584\u53bf",
    "wof:placetype":"localadmin"
},
  "geometry": {"coordinates":[120.88888900000001,30.947647],"type":"Point"}
}