{
  "type": "Feature",
  "properties": {
    "gn:admin1_code":"2.0",
    "gn:asciiname":"Huilingjiao",
    "gn:country_code":"CN",
    "gn:dem":478,
    "gn:feature_class":"P",
    "gn:feature_code":"PPL",
    "gn:name":"Huilingjiao",
    "gn:population":0,
    "gn:timezone":"Asia/Shanghai",
    "iso:country":"CN",
    "name:und_x_variant":[
        "\u7070\u5cad\u811a",
        "Huilingjiao"
    ],
    "wof:name":"Huilingjiao",
    "wof:placetype":"locality"
},
  "geometry": {"coordinates":[119.18038,29.97126],"type":"Point"}
}