{
  "type": "Feature",
  "properties": {
    "gn:admin1_code":"29.0",
    "gn:asciiname":"Diaojing",
    "gn:country_code":"CN",
    "gn:dem":1453,
    "gn:feature_class":"P",
    "gn:feature_code":"PPL",
    "gn:name":"Diaojing",
    "gn:population":0,
    "gn:timezone":"Asia/Shanghai",
    "iso:country":"CN",
    "name:zho_x_preferred":[
        "\u540a\u4e95"
    ],
    "wof:name":"Diaojing",
    "wof:placetype":"locality"
},
  "geometry": {"coordinates":[101.18899999999999,22.3881],"type":"Point"}
}