{
  "type": "Feature",
  "properties": {
    "gn:admin1_code":"26.0",
    "gn:asciiname":"Laoshicun",
    "gn:country_code":"CN",
    "gn:dem":898,
    "gn:feature_class":"P",
    "gn:feature_code":"PPL",
    "gn:name":"Laoshicun",
    "gn:population":0,
    "gn:timezone":"Asia/Shanghai",
    "iso:country":"CN",
    "name:zho_x_preferred":[
        "\u8001\u77f3\u6751"
    ],
    "wof:name":"Laoshicun",
    "wof:placetype":"locality"
},
  "geometry": {"coordinates":[110.39066,36.41924],"type":"Point"}
}