{
  "type": "Feature",
  "properties": {
    "gn:admin1_code":"9.0",
    "gn:asciiname":"Shangqiao",
    "gn:country_code":"CN",
    "gn:dem":63,
    "gn:feature_class":"P",
    "gn:feature_code":"PPLA4",
    "gn:name":"Shangqiao",
    "gn:population":0,
    "gn:timezone":"Asia/Shanghai",
    "iso:country":"CN",
    "name:und_x_variant":[
        "Hsiao-shang-ch\u2019iao-pei-chai",
        "Hsiao-shang-ch\u2019iao",
        "Xiaoshangqiao",
        "Shangqiao",
        "\u5546\u6865",
        "Shangqiao Zhen",
        "\u5546\u6865\u9547"
    ],
    "wof:name":"Shangqiao",
    "wof:placetype":"locality"
},
  "geometry": {"coordinates":[113.95667,33.70598],"type":"Point"}
}