{
  "type": "Feature",
  "properties": {
    "gn:admin1_code":"3.0",
    "gn:asciiname":"Lujimian",
    "gn:country_code":"CN",
    "gn:dem":187,
    "gn:feature_class":"P",
    "gn:feature_code":"PPL",
    "gn:name":"Lujimian",
    "gn:population":0,
    "gn:timezone":"Asia/Shanghai",
    "iso:country":"CN",
    "name:und_x_variant":[
        "\u82a6\u7b95\u9762"
    ],
    "wof:name":"Lujimian",
    "wof:placetype":"locality"
},
  "geometry": {"coordinates":[115.1413,26.16207],"type":"Point"}
}