{
  "type": "Feature",
  "properties": {
    "gn:admin1_code":"7",
    "gn:asciiname":"Zhuxiacun",
    "gn:country_code":"CN",
    "gn:dem":764,
    "gn:feature_class":"P",
    "gn:feature_code":"PPL",
    "gn:name":"Zhuxiacun",
    "gn:population":0,
    "gn:timezone":"Asia/Shanghai",
    "iso:country":"CN",
    "name:zho_x_preferred":[
        "\u7af9\u4e0b\u6751"
    ],
    "wof:name":"Zhuxiacun",
    "wof:placetype":"locality"
},
  "geometry": {"coordinates":[119.29288,27.07233],"type":"Point"}
}