{
  "type": "Feature",
  "properties": {
    "gn:admin1_code":"32.0",
    "gn:asciiname":"Fujiang",
    "gn:country_code":"CN",
    "gn:dem":277,
    "gn:feature_class":"P",
    "gn:feature_code":"PPL",
    "gn:name":"Fujiang",
    "gn:population":0,
    "gn:timezone":"Asia/Shanghai",
    "iso:country":"CN",
    "name:zho_x_preferred":[
        "\u6daa\u6c5f"
    ],
    "wof:name":"Fujiang",
    "wof:placetype":"locality"
},
  "geometry": {"coordinates":[105.62,30.4654],"type":"Point"}
}