{
  "type": "Feature",
  "properties": {
    "gn:admin1_code":"11",
    "gn:asciiname":"Yueyanlinchangcaifadui",
    "gn:country_code":"CN",
    "gn:dem":781,
    "gn:feature_class":"P",
    "gn:feature_code":"PPL",
    "gn:name":"Yueyanlinchangcaifadui",
    "gn:population":0,
    "gn:timezone":"Asia/Shanghai",
    "iso:country":"CN",
    "wof:name":"Yueyanlinchangcaifadui",
    "wof:placetype":"locality"
},
  "geometry": {"coordinates":[111.35361,25.52028],"type":"Point"}
}