{
  "type": "Feature",
  "properties": {
    "gn:admin1_code":"14.0",
    "gn:asciiname":"Nairucun",
    "gn:country_code":"CN",
    "gn:dem":3968,
    "gn:feature_class":"P",
    "gn:feature_code":"PPL",
    "gn:name":"Nairucun",
    "gn:population":0,
    "gn:timezone":"Asia/Urumqi",
    "iso:country":"CN",
    "name:zho_x_preferred":[
        "\u4e43\u5982\u6751"
    ],
    "wof:name":"Nairucun",
    "wof:placetype":"locality"
},
  "geometry": {"coordinates":[92.85795,28.5898],"type":"Point"}
}