{
  "type": "Feature",
  "properties": {
    "gn:admin1_code":"15.0",
    "gn:asciiname":"Jing'ergou",
    "gn:country_code":"CN",
    "gn:dem":2400,
    "gn:feature_class":"P",
    "gn:feature_code":"PPL",
    "gn:name":"Jing\u2019ergou",
    "gn:population":0,
    "gn:timezone":"Asia/Shanghai",
    "iso:country":"CN",
    "name:und_x_variant":[
        "Jing\u2019ergou"
    ],
    "name:zho_x_preferred":[
        "\u4e95\u513f\u6c9f"
    ],
    "wof:name":"Jing'ergou",
    "wof:placetype":"locality"
},
  "geometry": {"coordinates":[103.169,37.4484],"type":"Point"}
}