{
  "type": "Feature",
  "properties": {
    "gn:admin1_code":"10",
    "gn:asciiname":"Xiaotai Goumen",
    "gn:country_code":"CN",
    "gn:dem":741,
    "gn:feature_class":"P",
    "gn:feature_code":"PPL",
    "gn:name":"Xiaotai Goumen",
    "gn:population":0,
    "gn:timezone":"Asia/Shanghai",
    "iso:country":"CN",
    "name:zho_x_preferred":[
        "\u5c0f\u53f0\u6c9f\u95e8"
    ],
    "wof:name":"Xiaotai Goumen",
    "wof:placetype":"locality"
},
  "geometry": {"coordinates":[117.83467,41.55482],"type":"Point"}
}