{
  "type": "Feature",
  "properties": {
    "gn:admin1_code":"12.0",
    "gn:asciiname":"Fuchi",
    "gn:country_code":"CN",
    "gn:dem":28,
    "gn:feature_class":"P",
    "gn:feature_code":"PPLA4",
    "gn:name":"Fuchi",
    "gn:population":0,
    "gn:timezone":"Asia/Shanghai",
    "iso:country":"CN",
    "name:eng_x_historical":[
        "Fuchihkow"
    ],
    "name:eng_x_preferred":[
        "Fuchihkow"
    ],
    "name:und_x_variant":[
        "\u5bcc\u6c60",
        "Fuchi Zhen",
        "\u5bcc\u6c60\u9547"
    ],
    "wof:name":"Fuchi",
    "wof:placetype":"locality"
},
  "geometry": {"coordinates":[115.43795,29.85505],"type":"Point"}
}