{
  "type": "Feature",
  "properties": {
    "gn:admin1_code":"4.0",
    "gn:asciiname":"Laomiaocun",
    "gn:country_code":"CN",
    "gn:dem":35,
    "gn:feature_class":"P",
    "gn:feature_code":"PPL",
    "gn:name":"Laomiaocun",
    "gn:population":0,
    "gn:timezone":"Asia/Shanghai",
    "iso:country":"CN",
    "name:zho_x_preferred":[
        "\u59e5\u5e99\u6751"
    ],
    "wof:name":"Laomiaocun",
    "wof:placetype":"locality"
},
  "geometry": {"coordinates":[117.40393,34.23712],"type":"Point"}
}