{
  "type": "Feature",
  "properties": {
    "gn:admin1_code":"12.0",
    "gn:asciiname":"Qifang",
    "gn:country_code":"CN",
    "gn:dem":141,
    "gn:feature_class":"P",
    "gn:feature_code":"PPLA4",
    "gn:name":"Qifang",
    "gn:population":0,
    "gn:timezone":"Asia/Shanghai",
    "iso:country":"CN",
    "name:und_x_variant":[
        "Qifang Zhen"
    ],
    "name:zho_x_preferred":[
        "\u4e03\u65b9"
    ],
    "name:zho_x_variant":[
        "\u4e03\u65b9\u9547"
    ],
    "wof:name":"Qifang",
    "wof:placetype":"locality"
},
  "geometry": {"coordinates":[112.56283999999999,32.20368],"type":"Point"}
}