{
  "type": "Feature",
  "properties": {
    "gn:admin1_code":"18.0",
    "gn:asciiname":"Bazhe",
    "gn:country_code":"CN",
    "gn:dem":930,
    "gn:feature_class":"P",
    "gn:feature_code":"PPL",
    "gn:name":"Bazhe",
    "gn:population":0,
    "gn:timezone":"Asia/Shanghai",
    "iso:country":"CN",
    "name:zho_x_preferred":[
        "\u575d\u8005"
    ],
    "wof:name":"Bazhe",
    "wof:placetype":"locality"
},
  "geometry": {"coordinates":[107.36199999999999,25.5323],"type":"Point"}
}