{
  "type": "Feature",
  "properties": {
    "gn:admin1_code":"9.0",
    "gn:asciiname":"Guandimiao",
    "gn:country_code":"CN",
    "gn:dem":445,
    "gn:feature_class":"P",
    "gn:feature_code":"PPL",
    "gn:name":"Guandimiao",
    "gn:population":0,
    "gn:timezone":"Asia/Shanghai",
    "iso:country":"CN",
    "name:und_x_variant":[
        "\u5173\u5e1d\u5e99",
        "Guandimiao"
    ],
    "wof:name":"Guandimiao",
    "wof:placetype":"locality"
},
  "geometry": {"coordinates":[112.38720000000001,33.78611],"type":"Point"}
}