{
  "type": "Feature",
  "properties": {
    "gn:admin1_code":"02",
    "gn:asciiname":"Zhuoyiting",
    "gn:cc2":"CN",
    "gn:country_code":"CN",
    "gn:dem":10,
    "gn:feature_class":"P",
    "gn:feature_code":"PPL",
    "gn:name":"Zhuoyiting",
    "gn:population":0,
    "gn:timezone":"Asia/Shanghai",
    "iso:country":"CN",
    "name:und_x_variant":[
        "Cho-i-t\u2019ing",
        "Zhuoyiting"
    ],
    "wof:name":"Zhuoyiting",
    "wof:placetype":"locality"
},
  "geometry": {"coordinates":[121.86583,29.57361],"type":"Point"}
}