{
  "type": "Feature",
  "properties": {
    "gn:admin1_code":"19.0",
    "gn:asciiname":"Houwangtun",
    "gn:country_code":"CN",
    "gn:dem":31,
    "gn:feature_class":"P",
    "gn:feature_code":"PPL",
    "gn:name":"Houwangtun",
    "gn:population":0,
    "gn:timezone":"Asia/Shanghai",
    "iso:country":"CN",
    "name:zho_x_preferred":[
        "\u540e\u738b\u5c6f"
    ],
    "wof:name":"Houwangtun",
    "wof:placetype":"locality"
},
  "geometry": {"coordinates":[122.074,39.1454],"type":"Point"}
}