{
  "type": "Feature",
  "properties": {
    "gn:admin1_code":"7.0",
    "gn:asciiname":"Youshan",
    "gn:country_code":"CN",
    "gn:dem":535,
    "gn:feature_class":"P",
    "gn:feature_code":"PPL",
    "gn:name":"Youshan",
    "gn:population":0,
    "gn:timezone":"Asia/Shanghai",
    "iso:country":"CN",
    "name:zho_x_preferred":[
        "\u4f18\u5c71"
    ],
    "wof:name":"Youshan",
    "wof:placetype":"locality"
},
  "geometry": {"coordinates":[119.19644,26.2619],"type":"Point"}
}