{
  "type": "Feature",
  "properties": {
    "gn:admin1_code":"12.0",
    "gn:asciiname":"Tongshugou",
    "gn:country_code":"CN",
    "gn:dem":182,
    "gn:feature_class":"P",
    "gn:feature_code":"PPL",
    "gn:name":"Tongshugou",
    "gn:population":0,
    "gn:timezone":"Asia/Shanghai",
    "iso:country":"CN",
    "name:zho_x_preferred":[
        "\u6850\u6811\u6c9f"
    ],
    "wof:name":"Tongshugou",
    "wof:placetype":"locality"
},
  "geometry": {"coordinates":[111.36225,32.63405],"type":"Point"}
}