{
  "type": "Feature",
  "properties": {
    "gn:admin1_code":"16",
    "gn:asciiname":"Zhonghua",
    "gn:country_code":"CN",
    "gn:dem":156,
    "gn:feature_class":"P",
    "gn:feature_code":"PPL",
    "gn:name":"Zhonghua",
    "gn:population":0,
    "gn:timezone":"Asia/Shanghai",
    "iso:country":"CN",
    "name:cdo_x_preferred":[
        "D\u1e73\u0306ng-hu\u00e0"
    ],
    "name:deu_x_preferred":[
        "Zhonghua"
    ],
    "name:hak_x_preferred":[
        "Ch\u00fbng-f\u00e0"
    ],
    "name:zho_x_preferred":[
        "\u4e2d\u534e"
    ],
    "name:zho_x_variant":[
        "\u4e2d\u83ef"
    ],
    "wof:name":"Zhonghua",
    "wof:placetype":"locality"
},
  "geometry": {"coordinates":[110.592,24.593],"type":"Point"}
}