{
  "type": "Feature",
  "properties": {
    "gn:admin1_code":"3.0",
    "gn:asciiname":"Yaqian",
    "gn:country_code":"CN",
    "gn:dem":125,
    "gn:feature_class":"P",
    "gn:feature_code":"PPL",
    "gn:name":"Yaqian",
    "gn:population":0,
    "gn:timezone":"Asia/Shanghai",
    "iso:country":"CN",
    "name:und_x_variant":[
        "\u96c5\u524d"
    ],
    "wof:name":"Yaqian",
    "wof:placetype":"locality"
},
  "geometry": {"coordinates":[116.55265,27.17601],"type":"Point"}
}