{
  "type": "Feature",
  "properties": {
    "gn:admin1_code":"10.0",
    "gn:asciiname":"Xiamajiayu",
    "gn:country_code":"CN",
    "gn:dem":97,
    "gn:feature_class":"P",
    "gn:feature_code":"PPL",
    "gn:name":"Xiamajiayu",
    "gn:population":0,
    "gn:timezone":"Asia/Shanghai",
    "iso:country":"CN",
    "name:zho_x_preferred":[
        "\u4e0b\u9a6c\u5bb6\u5cea"
    ],
    "wof:name":"Xiamajiayu",
    "wof:placetype":"locality"
},
  "geometry": {"coordinates":[118.06827,39.98088],"type":"Point"}
}