{
  "type": "Feature",
  "properties": {
    "gn:admin1_code":"29.0",
    "gn:asciiname":"Lengdu",
    "gn:country_code":"CN",
    "gn:dem":3150,
    "gn:feature_class":"P",
    "gn:feature_code":"PPL",
    "gn:name":"Lengdu",
    "gn:population":0,
    "gn:timezone":"Asia/Shanghai",
    "iso:country":"CN",
    "name:zho_x_preferred":[
        "\u51b7\u90fd"
    ],
    "wof:name":"Lengdu",
    "wof:placetype":"locality"
},
  "geometry": {"coordinates":[99.8954,27.4677],"type":"Point"}
}