{
  "type": "Feature",
  "properties": {
    "gn:admin1_code":"14.0",
    "gn:asciiname":"Gongbapu",
    "gn:country_code":"CN",
    "gn:dem":4395,
    "gn:feature_class":"P",
    "gn:feature_code":"PPL",
    "gn:name":"Gongbapu",
    "gn:population":0,
    "gn:timezone":"Asia/Urumqi",
    "iso:country":"CN",
    "name:zho_x_preferred":[
        "\u8d21\u5df4\u666e"
    ],
    "wof:name":"Gongbapu",
    "wof:placetype":"locality"
},
  "geometry": {"coordinates":[86.6142,28.5253],"type":"Point"}
}