{
  "type": "Feature",
  "properties": {
    "gn:admin1_code":"16",
    "gn:asciiname":"Shuangzaoping",
    "gn:country_code":"CN",
    "gn:dem":469,
    "gn:feature_class":"P",
    "gn:feature_code":"PPL",
    "gn:name":"Shuangzaoping",
    "gn:population":0,
    "gn:timezone":"Asia/Shanghai",
    "iso:country":"CN",
    "name:zho_x_preferred":[
        "\u53cc\u67a3\u576a"
    ],
    "wof:name":"Shuangzaoping",
    "wof:placetype":"locality"
},
  "geometry": {"coordinates":[110.80800000000001,25.0397],"type":"Point"}
}