{
  "type": "Feature",
  "properties": {
    "gn:admin1_code":"11.0",
    "gn:asciiname":"Huatianpu",
    "gn:country_code":"CN",
    "gn:dem":89,
    "gn:feature_class":"P",
    "gn:feature_code":"PPL",
    "gn:name":"Huatianpu",
    "gn:population":0,
    "gn:timezone":"Asia/Shanghai",
    "iso:country":"CN",
    "name:zho_x_preferred":[
        "\u82b1\u7530\u94fa"
    ],
    "wof:name":"Huatianpu",
    "wof:placetype":"locality"
},
  "geometry": {"coordinates":[113.13136000000002,27.34095],"type":"Point"}
}