{
  "type": "Feature",
  "properties": {
    "gn:admin1_code":"24.0",
    "gn:asciiname":"Xiabocheng",
    "gn:cc2":"CN",
    "gn:country_code":"CN",
    "gn:dem":265,
    "gn:feature_class":"P",
    "gn:feature_code":"PPL",
    "gn:name":"Xiabocheng",
    "gn:population":0,
    "gn:timezone":"Asia/Shanghai",
    "iso:country":"CN",
    "name:und_x_variant":[
        "Hsia-po-ch\u2019eng",
        "Hsia-po-ch\u2019eng-ts\u2019un",
        "Xiabocheng"
    ],
    "wof:name":"Xiabocheng",
    "wof:placetype":"locality"
},
  "geometry": {"coordinates":[111.83028,35.1175],"type":"Point"}
}