{
  "type": "Feature",
  "properties": {
    "gn:admin1_code":"29",
    "gn:asciiname":"Heishuwo",
    "gn:country_code":"CN",
    "gn:dem":2006,
    "gn:feature_class":"P",
    "gn:feature_code":"PPL",
    "gn:name":"Heishuwo",
    "gn:population":0,
    "gn:timezone":"Asia/Shanghai",
    "iso:country":"CN",
    "name:zho_x_preferred":[
        "\u9ed1\u6811\u7a9d"
    ],
    "wof:name":"Heishuwo",
    "wof:placetype":"locality"
},
  "geometry": {"coordinates":[102.12514,24.83995],"type":"Point"}
}