{
  "type": "Feature",
  "properties": {
    "gn:admin1_code":"2.0",
    "gn:asciiname":"Jiu'ercun",
    "gn:country_code":"CN",
    "gn:dem":10,
    "gn:feature_class":"P",
    "gn:feature_code":"PPL",
    "gn:name":"Jiu\u2019ercun",
    "gn:population":0,
    "gn:timezone":"Asia/Shanghai",
    "iso:country":"CN",
    "name:und_x_variant":[
        "Jiu\u2019ercun"
    ],
    "name:zho_x_preferred":[
        "\u4e5d\u4e8c\u6751"
    ],
    "wof:name":"Jiu'ercun",
    "wof:placetype":"locality"
},
  "geometry": {"coordinates":[120.38717,30.09416],"type":"Point"}
}