{
  "type": "Feature",
  "properties": {
    "gn:admin1_code":"9.0",
    "gn:asciiname":"Zhenggou",
    "gn:country_code":"CN",
    "gn:dem":1379,
    "gn:feature_class":"P",
    "gn:feature_code":"PPL",
    "gn:name":"Zhenggou",
    "gn:population":0,
    "gn:timezone":"Asia/Shanghai",
    "iso:country":"CN",
    "name:zho_x_preferred":[
        "\u6b63\u6c9f"
    ],
    "wof:name":"Zhenggou",
    "wof:placetype":"locality"
},
  "geometry": {"coordinates":[111.27432,34.00232],"type":"Point"}
}