{
  "type": "Feature",
  "properties": {
    "gn:admin1_code":"26.0",
    "gn:asciiname":"Hengshuigoukou",
    "gn:country_code":"CN",
    "gn:dem":769,
    "gn:feature_class":"P",
    "gn:feature_code":"PPL",
    "gn:name":"Hengshuigoukou",
    "gn:population":0,
    "gn:timezone":"Asia/Shanghai",
    "iso:country":"CN",
    "name:zho_x_preferred":[
        "\u6a2a\u6c34\u6c9f\u53e3"
    ],
    "wof:name":"Hengshuigoukou",
    "wof:placetype":"locality"
},
  "geometry": {"coordinates":[109.48148999999999,33.56665],"type":"Point"}
}