{
  "type": "Feature",
  "properties": {
    "gn:admin1_code":"16",
    "gn:asciiname":"Luoyun",
    "gn:country_code":"CN",
    "gn:dem":622,
    "gn:feature_class":"P",
    "gn:feature_code":"PPL",
    "gn:name":"Luoyun",
    "gn:population":0,
    "gn:timezone":"Asia/Shanghai",
    "iso:country":"CN",
    "name:und_x_variant":[
        "Lo-y\u00fcn",
        "Luoyun"
    ],
    "name:zho_x_preferred":[
        "\u7f57\u8fd0"
    ],
    "wof:name":"Luoyun",
    "wof:placetype":"locality"
},
  "geometry": {"coordinates":[110.188,23.9504],"type":"Point"}
}