{
  "type": "Feature",
  "properties": {
    "gn:admin1_code":"7.0",
    "gn:asciiname":"Shuihe",
    "gn:country_code":"CN",
    "gn:dem":318,
    "gn:feature_class":"P",
    "gn:feature_code":"PPL",
    "gn:name":"Shuihe",
    "gn:population":0,
    "gn:timezone":"Asia/Shanghai",
    "iso:country":"CN",
    "name:und_x_variant":[
        "\u6c34\u58d1"
    ],
    "name:zho_x_preferred":[
        "Shuihe"
    ],
    "wof:name":"Shuihe",
    "wof:placetype":"locality"
},
  "geometry": {"coordinates":[119.2555,26.14236],"type":"Point"}
}