{
  "type": "Feature",
  "properties": {
    "gn:country":"CN",
    "gn:fcode":"ADM3",
    "gn:pop":0,
    "iso:country":"CN",
    "name:unk_x_variant":[
        "Ch\u00fc Hsien"
    ],
    "name:zho_x_preferred":[
        "\u8392\u53bf"
    ],
    "qs:name":"Ju Xian",
    "qs:photos_9r":0,
    "qs:photos_sr":0,
    "qs:pop_sr":"0",
    "wd:wordcount":245,
    "wof:name":"Ju Xian",
    "wof:placetype":"localadmin",
    "wof:population":0
},
  "geometry": {"coordinates":[118.90306,35.62694],"type":"Point"}
}