{
  "type": "Feature",
  "properties": {
    "gn:country":"CN",
    "gn:fcode":"ADM3",
    "gn:pop":0,
    "iso:country":"CN",
    "name:ceb_x_preferred":[
        "Ju Xian"
    ],
    "name:deu_x_preferred":[
        "Ju"
    ],
    "name:eng_x_preferred":[
        "Ju County"
    ],
    "name:fas_x_preferred":[
        "\u0634\u0647\u0631\u0633\u062a\u0627\u0646 \u062c\u0648"
    ],
    "name:gan_x_preferred":[
        "\u8392\u53bf"
    ],
    "name:jpn_x_preferred":[
        "\u8392\u770c"
    ],
    "name:kor_x_preferred":[
        "\uc950\ud604"
    ],
    "name:nan_x_preferred":[
        "K\u00fa-ko\u0101n"
    ],
    "name:nld_x_preferred":[
        "Ju"
    ],
    "name:nob_x_preferred":[
        "Ju"
    ],
    "name:rus_x_preferred":[
        "\u0426\u0437\u044e\u0439\u0441\u044f\u043d\u044c"
    ],
    "name:swe_x_preferred":[
        "Ju"
    ],
    "name:unk_x_variant":[
        "Ch\u00fc Hsien"
    ],
    "name:vie_x_preferred":[
        "C\u1eed"
    ],
    "name:wuu_x_preferred":[
        "\u8392\u53bf"
    ],
    "name:yue_x_preferred":[
        "\u8392\u7e23"
    ],
    "name:zho_x_preferred":[
        "\u8392\u53bf"
    ],
    "qs:name":"Ju Xian",
    "qs:photos_9r":0,
    "qs:photos_sr":0,
    "qs:pop_sr":"0",
    "wd:wordcount":245,
    "wof:name":"Ju Xian",
    "wof:placetype":"localadmin",
    "wof:population":0
},
  "geometry": {"coordinates":[118.90306,35.62694],"type":"Point"}
}