{
  "type": "Feature",
  "properties": {
    "gn:admin1_code":"32.0",
    "gn:asciiname":"Yueshuiyan",
    "gn:country_code":"CN",
    "gn:dem":1324,
    "gn:feature_class":"P",
    "gn:feature_code":"PPL",
    "gn:name":"Yueshuiyan",
    "gn:population":0,
    "gn:timezone":"Asia/Shanghai",
    "iso:country":"CN",
    "name:zho_x_preferred":[
        "\u8dc3\u6c34\u5ca9"
    ],
    "wof:name":"Yueshuiyan",
    "wof:placetype":"locality"
},
  "geometry": {"coordinates":[104.62072999999999,32.20034],"type":"Point"}
}