{
  "type": "Feature",
  "properties": {
    "gn:admin1_code":"12.0",
    "gn:asciiname":"Jiegounao",
    "gn:country_code":"CN",
    "gn:dem":799,
    "gn:feature_class":"P",
    "gn:feature_code":"PPL",
    "gn:name":"Jiegounao",
    "gn:population":0,
    "gn:timezone":"Asia/Shanghai",
    "iso:country":"CN",
    "name:zho_x_preferred":[
        "\u622a\u6c9f\u8111"
    ],
    "wof:name":"Jiegounao",
    "wof:placetype":"locality"
},
  "geometry": {"coordinates":[110.08277,32.92890999999999],"type":"Point"}
}