{
  "type": "Feature",
  "properties": {
    "gn:admin1_code":"21.0",
    "gn:asciiname":"Jizhong Sandui",
    "gn:country_code":"CN",
    "gn:dem":1103,
    "gn:feature_class":"P",
    "gn:feature_code":"PPLF",
    "gn:name":"Jizhong Sandui",
    "gn:population":0,
    "gn:timezone":"Asia/Shanghai",
    "iso:country":"CN",
    "name:zho_x_preferred":[
        "\u96c6\u4e2d\u4e09\u961f"
    ],
    "wof:name":"Jizhong Sandui",
    "wof:placetype":"locality"
},
  "geometry": {"coordinates":[106.509,38.7048],"type":"Point"}
}