{
  "type": "Feature",
  "properties": {
    "gn:admin1_code":"24.0",
    "gn:asciiname":"Liaojiang Hutong",
    "gn:country_code":"CN",
    "gn:dem":1117,
    "gn:feature_class":"P",
    "gn:feature_code":"PPL",
    "gn:name":"Liaojiang Hutong",
    "gn:population":0,
    "gn:timezone":"Asia/Shanghai",
    "iso:country":"CN",
    "name:zho_x_preferred":[
        "\u6599\u6c5f\u80e1\u540c"
    ],
    "wof:name":"Liaojiang Hutong",
    "wof:placetype":"locality"
},
  "geometry": {"coordinates":[111.41991000000002,36.27592],"type":"Point"}
}