{
  "type": "Feature",
  "properties": {
    "gn:admin1_code":"10.0",
    "gn:asciiname":"Taolinping",
    "gn:country_code":"CN",
    "gn:dem":323,
    "gn:feature_class":"P",
    "gn:feature_code":"PPL",
    "gn:name":"Taolinping",
    "gn:population":0,
    "gn:timezone":"Asia/Shanghai",
    "iso:country":"CN",
    "name:zho_x_preferred":[
        "\u6843\u6797\u576a"
    ],
    "wof:name":"Taolinping",
    "wof:placetype":"locality"
},
  "geometry": {"coordinates":[113.98941000000001,38.12104],"type":"Point"}
}