{
  "type": "Feature",
  "properties": {
    "gn:admin1_code":"14.0",
    "gn:asciiname":"Saikang",
    "gn:country_code":"CN",
    "gn:dem":3664,
    "gn:feature_class":"P",
    "gn:feature_code":"PPL",
    "gn:name":"Saikang",
    "gn:population":0,
    "gn:timezone":"Asia/Urumqi",
    "iso:country":"CN",
    "name:bod_x_preferred":[
        "Saikang"
    ],
    "name:zho_x_preferred":[
        "Segang"
    ],
    "name:zho_x_variant":[
        "\u8272\u5c97",
        "Kaduo Gongshe",
        "\u5361\u591a\u516c\u793e"
    ],
    "wof:name":"Saikang",
    "wof:placetype":"locality"
},
  "geometry": {"coordinates":[91.708,29.108],"type":"Point"}
}