{
  "type": "Feature",
  "properties": {
    "gn:admin1_code":"9.0",
    "gn:asciiname":"Xiajijiazhuang",
    "gn:country_code":"CN",
    "gn:dem":421,
    "gn:feature_class":"P",
    "gn:feature_code":"PPL",
    "gn:name":"Xiajijiazhuang",
    "gn:population":0,
    "gn:timezone":"Asia/Shanghai",
    "iso:country":"CN",
    "name:zho_x_preferred":[
        "\u4e0b\u59ec\u5bb6\u5e84"
    ],
    "wof:name":"Xiajijiazhuang",
    "wof:placetype":"locality"
},
  "geometry": {"coordinates":[112.05367,33.59076],"type":"Point"}
}