{
  "type": "Feature",
  "properties": {
    "gn:admin1_code":"13",
    "gn:asciiname":"Keshilake",
    "gn:country_code":"CN",
    "gn:dem":1238,
    "gn:feature_class":"P",
    "gn:feature_code":"PPL",
    "gn:name":"Keshilake",
    "gn:population":0,
    "gn:timezone":"Asia/Shanghai",
    "iso:country":"CN",
    "name:zho_x_preferred":[
        "\u514b\u4ec0\u62c9\u514b"
    ],
    "wof:name":"Keshilake",
    "wof:placetype":"locality"
},
  "geometry": {"coordinates":[76.41206,39.09763],"type":"Point"}
}