{
  "type": "Feature",
  "properties": {
    "gn:admin1_code":"15.0",
    "gn:asciiname":"Shangchencha",
    "gn:country_code":"CN",
    "gn:dem":1700,
    "gn:feature_class":"P",
    "gn:feature_code":"PPL",
    "gn:name":"Shangchencha",
    "gn:population":0,
    "gn:timezone":"Asia/Shanghai",
    "iso:country":"CN",
    "name:zho_x_preferred":[
        "\u4e0a\u9648\u5c94"
    ],
    "wof:name":"Shangchencha",
    "wof:placetype":"locality"
},
  "geometry": {"coordinates":[104.84399999999999,37.0222],"type":"Point"}
}