{
  "type": "Feature",
  "properties": {
    "gn:admin1_code":"19.0",
    "gn:asciiname":"Hulitao",
    "gn:country_code":"CN",
    "gn:dem":6,
    "gn:feature_class":"P",
    "gn:feature_code":"PPL",
    "gn:name":"Hulitao",
    "gn:population":0,
    "gn:timezone":"Asia/Shanghai",
    "iso:country":"CN",
    "name:und_x_variant":[
        "\u72d0\u72f8\u5957"
    ],
    "name:zho_x_preferred":[
        "\u72d0\u72f8\u5957"
    ],
    "wof:name":"Hulitao",
    "wof:placetype":"locality"
},
  "geometry": {"coordinates":[120.58314,40.44374000000001],"type":"Point"}
}