{
  "type": "Feature",
  "properties": {
    "gn:admin1_code":"25",
    "gn:asciiname":"Fangzhuang",
    "gn:country_code":"CN",
    "gn:dem":59,
    "gn:feature_class":"P",
    "gn:feature_code":"PPL",
    "gn:name":"Fangzhuang",
    "gn:population":0,
    "gn:timezone":"Asia/Shanghai",
    "iso:country":"CN",
    "name:zho_x_preferred":[
        "\u623f\u5e84"
    ],
    "name:zho_x_variant":[
        "\u65b9\u5e84\u5730\u533a"
    ],
    "wof:name":"Fangzhuang",
    "wof:placetype":"locality"
},
  "geometry": {"coordinates":[118.333,34.9397],"type":"Point"}
}