{
  "type": "Feature",
  "properties": {
    "gn:admin1_code":"15.0",
    "gn:asciiname":"Ranzi",
    "gn:country_code":"CN",
    "gn:dem":2674,
    "gn:feature_class":"P",
    "gn:feature_code":"PPL",
    "gn:name":"Ranzi",
    "gn:population":0,
    "gn:timezone":"Asia/Shanghai",
    "iso:country":"CN",
    "name:deu_x_preferred":[
        "Ranzi"
    ],
    "name:srp_x_preferred":[
        "Ranzi"
    ],
    "name:zho_x_preferred":[
        "\u7136\u5b50"
    ],
    "wof:name":"Ranzi",
    "wof:placetype":"locality"
},
  "geometry": {"coordinates":[103.88500000000001,33.792],"type":"Point"}
}