{
  "type": "Feature",
  "properties": {
    "gn:admin1_code":"7.0",
    "gn:asciiname":"Linyangtou",
    "gn:country_code":"CN",
    "gn:dem":364,
    "gn:feature_class":"P",
    "gn:feature_code":"PPL",
    "gn:name":"Linyangtou",
    "gn:population":0,
    "gn:timezone":"Asia/Shanghai",
    "iso:country":"CN",
    "name:zho_x_preferred":[
        "\u6797\u6d0b\u5934"
    ],
    "wof:name":"Linyangtou",
    "wof:placetype":"locality"
},
  "geometry": {"coordinates":[119.62318,26.83093],"type":"Point"}
}