{
  "type": "Feature",
  "properties": {
    "gn:admin1_code":"08",
    "gn:asciiname":"Hougaotou",
    "gn:country_code":"CN",
    "gn:dem":150,
    "gn:feature_class":"P",
    "gn:feature_code":"PPL",
    "gn:name":"Hougaotou",
    "gn:population":0,
    "gn:timezone":"Asia/Shanghai",
    "iso:country":"CN",
    "name:und_x_variant":[
        "Hou-kao-t\u2019un",
        "Hougaotou"
    ],
    "name:zho_x_preferred":[
        "\u540e\u9ad8\u5934"
    ],
    "wof:name":"Hougaotou",
    "wof:placetype":"locality"
},
  "geometry": {"coordinates":[124.06502,47.42828],"type":"Point"}
}