{
  "type": "Feature",
  "properties": {
    "gn:admin1_code":"19.0",
    "gn:asciiname":"Erdaogou Buzi",
    "gn:country_code":"CN",
    "gn:dem":296,
    "gn:feature_class":"P",
    "gn:feature_code":"PPL",
    "gn:name":"Erdaogou Buzi",
    "gn:population":0,
    "gn:timezone":"Asia/Shanghai",
    "iso:country":"CN",
    "name:und_x_variant":[
        "Erdaogou Puzi",
        "\u4e8c\u9053\u6c9f\u5821\u5b50",
        "Erdaogou Buzi"
    ],
    "wof:name":"Erdaogou Buzi",
    "wof:placetype":"locality"
},
  "geometry": {"coordinates":[122.87824000000001,40.39281],"type":"Point"}
}