{
  "type": "Feature",
  "properties": {
    "gn:admin1_code":"19.0",
    "gn:asciiname":"Gujiazhangzi",
    "gn:country_code":"CN",
    "gn:dem":304,
    "gn:feature_class":"P",
    "gn:feature_code":"PPL",
    "gn:name":"Gujiazhangzi",
    "gn:population":0,
    "gn:timezone":"Asia/Shanghai",
    "iso:country":"CN",
    "name:und_x_variant":[
        "\u987e\u5bb6\u6756\u5b50"
    ],
    "name:zho_x_preferred":[
        "\u987e\u5bb6\u6756\u5b50"
    ],
    "wof:name":"Gujiazhangzi",
    "wof:placetype":"locality"
},
  "geometry": {"coordinates":[120.54092,41.53454],"type":"Point"}
}