{
  "type": "Feature",
  "properties": {
    "gn:admin1_code":"30.0",
    "gn:asciiname":"Weiganping",
    "gn:country_code":"CN",
    "gn:dem":309,
    "gn:feature_class":"P",
    "gn:feature_code":"PPL",
    "gn:name":"Weiganping",
    "gn:population":0,
    "gn:timezone":"Asia/Shanghai",
    "iso:country":"CN",
    "name:zho_x_preferred":[
        "Weiganping"
    ],
    "name:zho_x_variant":[
        "\u56f4\u6746\u576a"
    ],
    "wof:name":"Weiganping",
    "wof:placetype":"locality"
},
  "geometry": {"coordinates":[112.48721999999999,24.70833],"type":"Point"}
}