{
  "type": "Feature",
  "properties": {
    "gn:admin1_code":"29",
    "gn:asciiname":"Zhongdouda",
    "gn:country_code":"CN",
    "gn:dem":1626,
    "gn:feature_class":"P",
    "gn:feature_code":"PPL",
    "gn:name":"Zhongdouda",
    "gn:population":0,
    "gn:timezone":"Asia/Shanghai",
    "iso:country":"CN",
    "name:zho_x_preferred":[
        "\u4e2d\u8c46\u8fbe"
    ],
    "wof:name":"Zhongdouda",
    "wof:placetype":"locality"
},
  "geometry": {"coordinates":[103.121,24.6204],"type":"Point"}
}