{
  "type": "Feature",
  "properties": {
    "gn:admin1_code":"32.0",
    "gn:asciiname":"Malihong",
    "gn:country_code":"CN",
    "gn:dem":3063,
    "gn:feature_class":"P",
    "gn:feature_code":"PPL",
    "gn:name":"Malihong",
    "gn:population":0,
    "gn:timezone":"Asia/Shanghai",
    "iso:country":"CN",
    "name:zho_x_preferred":[
        "\u9a6c\u91cc\u54c4"
    ],
    "wof:name":"Malihong",
    "wof:placetype":"locality"
},
  "geometry": {"coordinates":[102.48699999999999,27.7804],"type":"Point"}
}