{
  "type": "Feature",
  "properties": {
    "gn:country":"CN",
    "gn:fcode":"PPLA4",
    "gn:population":0,
    "iso:country":"CN",
    "name:ceb_x_preferred":[
        "Nanqiao Qu"
    ],
    "name:deu_x_preferred":[
        "Nanqiao"
    ],
    "name:jpn_x_preferred":[
        "\u5357\u30b7\u30e7\u30a6\u533a"
    ],
    "name:kor_x_preferred":[
        "\ub09c\ucc28\uc624\uad6c"
    ],
    "name:mwl_x_preferred":[
        "Nanqiao"
    ],
    "name:nor_x_preferred":[
        "Nanqiao"
    ],
    "name:pol_x_preferred":[
        "Nanqiao"
    ],
    "name:spa_x_preferred":[
        "N\u00e1nqi\u00e1o Q\u016b"
    ],
    "name:swe_x_preferred":[
        "Nanqiao"
    ],
    "name:und_x_variant":[
        "Nanqiao Zhen"
    ],
    "name:urd_x_preferred":[
        "\u0646\u0627\u0646\u0686\u06cc\u0627\u0648 \u0636\u0644\u0639"
    ],
    "name:vie_x_preferred":[
        "Nam Ti\u1ebfu"
    ],
    "name:zho_x_preferred":[
        "\u5357\u6865"
    ],
    "name:zho_x_variant":[
        "\u5357\u6865\u9547",
        "\u5357\u8c2f\u533a"
    ],
    "qs:name":"Nanqiao",
    "qs:photos_9r":0,
    "qs:photos_sr":0,
    "qs:pop_sr":"0",
    "wd:wordcount":79,
    "wof:name":"Nanqiao",
    "wof:placetype":"locality",
    "wof:population":0
},
  "geometry": {"coordinates":[115.71478,24.79441],"type":"Point"}
}