{
  "type": "Feature",
  "properties": {
    "gn:country":"CN",
    "gn:fcode":"PPLA4",
    "gn:pop":0,
    "iso:country":"CN",
    "name:unk_x_variant":[
        "Nanqiao Zhen"
    ],
    "name:zho_x_preferred":[
        "\u5357\u6865"
    ],
    "name:zho_x_variant":[
        "\u5357\u6865\u9547"
    ],
    "qs:name":"Nanqiao",
    "qs:photos_9r":0,
    "qs:photos_sr":0,
    "qs:pop_sr":"0",
    "wd:wordcount":79,
    "wof:name":"Nanqiao",
    "wof:placetype":"locality",
    "wof:population":0
},
  "geometry": {"coordinates":[115.71478,24.79441],"type":"Point"}
}