{
  "type": "Feature",
  "properties": {
    "gn:admin1_code":"19.0",
    "gn:asciiname":"Xiaoyingpan",
    "gn:country_code":"CN",
    "gn:dem":129,
    "gn:feature_class":"P",
    "gn:feature_code":"PPL",
    "gn:name":"Xiaoyingpan",
    "gn:population":0,
    "gn:timezone":"Asia/Shanghai",
    "iso:country":"CN",
    "name:zho_x_preferred":[
        "\u5c0f\u8425\u76d8"
    ],
    "wof:name":"Xiaoyingpan",
    "wof:placetype":"locality"
},
  "geometry": {"coordinates":[124.10299999999999,42.2228],"type":"Point"}
}