{
  "type": "Feature",
  "properties": {
    "gn:admin1_code":"12.0",
    "gn:asciiname":"Badouwo",
    "gn:country_code":"CN",
    "gn:dem":257,
    "gn:feature_class":"P",
    "gn:feature_code":"PPL",
    "gn:name":"Badouwo",
    "gn:population":0,
    "gn:timezone":"Asia/Shanghai",
    "iso:country":"CN",
    "name:zho_x_preferred":[
        "Badouwo"
    ],
    "name:zho_x_variant":[
        "\u516b\u6597\u7a9d"
    ],
    "wof:name":"Badouwo",
    "wof:placetype":"locality"
},
  "geometry": {"coordinates":[111.22677,30.37163],"type":"Point"}
}