{
  "type": "Feature",
  "properties": {
    "gn:admin1_code":"12.0",
    "gn:asciiname":"Xiaojiapu",
    "gn:country_code":"CN",
    "gn:dem":36,
    "gn:feature_class":"P",
    "gn:feature_code":"PPL",
    "gn:name":"Xiaojiapu",
    "gn:population":0,
    "gn:timezone":"Asia/Shanghai",
    "iso:country":"CN",
    "name:zho_x_preferred":[
        "Xiaojiapu"
    ],
    "name:zho_x_variant":[
        "\u8096\u5bb6\u94fa"
    ],
    "wof:name":"Xiaojiapu",
    "wof:placetype":"locality"
},
  "geometry": {"coordinates":[114.99894999999999,30.19758],"type":"Point"}
}