{
  "type": "Feature",
  "properties": {
    "gn:admin1_code":"4.0",
    "gn:asciiname":"Mengcaobu",
    "gn:country_code":"CN",
    "gn:dem":27,
    "gn:feature_class":"P",
    "gn:feature_code":"PPL",
    "gn:name":"Mengcaobu",
    "gn:population":0,
    "gn:timezone":"Asia/Shanghai",
    "iso:country":"CN",
    "name:zho_x_preferred":[
        "\u5b5f\u66f9\u57e0"
    ],
    "wof:name":"Mengcaobu",
    "wof:placetype":"locality"
},
  "geometry": {"coordinates":[118.879,34.7864],"type":"Point"}
}