{
  "type": "Feature",
  "properties": {
    "gn:admin1_code":"3.0",
    "gn:asciiname":"Gutian",
    "gn:country_code":"CN",
    "gn:dem":30,
    "gn:feature_class":"P",
    "gn:feature_code":"PPL",
    "gn:name":"Gutian",
    "gn:population":0,
    "gn:timezone":"Asia/Shanghai",
    "iso:country":"CN",
    "name:deu_x_preferred":[
        "Gutian"
    ],
    "name:zho_x_preferred":[
        "\u53e4\u7530"
    ],
    "wof:name":"Gutian",
    "wof:placetype":"locality"
},
  "geometry": {"coordinates":[117.282,29.0084],"type":"Point"}
}