{
  "type": "Feature",
  "properties": {
    "gn:admin1_code":"29.0",
    "gn:asciiname":"Tangshanlin",
    "gn:country_code":"CN",
    "gn:dem":1845,
    "gn:feature_class":"P",
    "gn:feature_code":"PPL",
    "gn:name":"Tangshanlin",
    "gn:population":0,
    "gn:timezone":"Asia/Shanghai",
    "iso:country":"CN",
    "name:zho_x_preferred":[
        "\u5510\u5c71\u6797"
    ],
    "wof:name":"Tangshanlin",
    "wof:placetype":"locality"
},
  "geometry": {"coordinates":[99.70569999999999,23.762],"type":"Point"}
}