{
  "type": "Feature",
  "properties": {
    "gn:admin1_code":"11.0",
    "gn:asciiname":"Xianchaqiao",
    "gn:cc2":"CN",
    "gn:country_code":"CN",
    "gn:dem":259,
    "gn:feature_class":"P",
    "gn:feature_code":"PPL",
    "gn:name":"Xianchaqiao",
    "gn:population":0,
    "gn:timezone":"Asia/Shanghai",
    "iso:country":"CN",
    "name:und_x_variant":[
        "Hsien-ch\u2019a-ch\u2019iao",
        "Xianchaqiao"
    ],
    "wof:name":"Xianchaqiao",
    "wof:placetype":"locality"
},
  "geometry": {"coordinates":[111.70056,27.17167],"type":"Point"}
}