{
  "type": "Feature",
  "properties": {
    "gn:admin1_code":"30",
    "gn:asciiname":"Wushijing",
    "gn:country_code":"CN",
    "gn:dem":160,
    "gn:feature_class":"P",
    "gn:feature_code":"PPL",
    "gn:name":"Wushijing",
    "gn:population":0,
    "gn:timezone":"Asia/Shanghai",
    "iso:country":"CN",
    "name:zho_x_preferred":[
        "\u4e4c\u77f3\u8ff3"
    ],
    "wof:name":"Wushijing",
    "wof:placetype":"locality"
},
  "geometry": {"coordinates":[111.91719000000001,22.17433],"type":"Point"}
}