{
  "type": "Feature",
  "properties": {
    "gn:admin1_code":"7",
    "gn:asciiname":"Budoulou",
    "gn:country_code":"CN",
    "gn:dem":359,
    "gn:feature_class":"P",
    "gn:feature_code":"PPL",
    "gn:name":"Budoulou",
    "gn:population":0,
    "gn:timezone":"Asia/Shanghai",
    "iso:country":"CN",
    "name:und_x_variant":[
        "\u6b65\u515c\u697c",
        "Budoulou"
    ],
    "wof:name":"Budoulou",
    "wof:placetype":"locality"
},
  "geometry": {"coordinates":[119.73316,27.06161],"type":"Point"}
}