{
  "type": "Feature",
  "properties": {
    "gn:admin1_code":"7",
    "gn:asciiname":"Chimaxi",
    "gn:country_code":"CN",
    "gn:dem":158,
    "gn:feature_class":"P",
    "gn:feature_code":"PPL",
    "gn:name":"Chimaxi",
    "gn:population":0,
    "gn:timezone":"Asia/Shanghai",
    "iso:country":"CN",
    "name:zho_x_preferred":[
        "\u8d64\u9ebb\u6eaa"
    ],
    "wof:name":"Chimaxi",
    "wof:placetype":"locality"
},
  "geometry": {"coordinates":[117.43517,24.02611],"type":"Point"}
}