{
  "type": "Feature",
  "properties": {
    "gn:admin1_code":"30",
    "gn:asciiname":"Chadong",
    "gn:country_code":"CN",
    "gn:dem":186,
    "gn:feature_class":"P",
    "gn:feature_code":"PPL",
    "gn:name":"Chadong",
    "gn:population":0,
    "gn:timezone":"Asia/Shanghai",
    "iso:country":"CN",
    "name:zho_x_preferred":[
        "Ch\u2019a-tung"
    ],
    "name:zho_x_variant":[
        "\u8336\u6d1e"
    ],
    "wof:name":"Chadong",
    "wof:placetype":"locality"
},
  "geometry": {"coordinates":[111.98333,22.83999],"type":"Point"}
}