{
  "type": "Feature",
  "properties": {
    "gn:admin1_code":"19.0",
    "gn:asciiname":"Zonghuangdicun",
    "gn:country_code":"CN",
    "gn:dem":60,
    "gn:feature_class":"P",
    "gn:feature_code":"PPL",
    "gn:name":"Zonghuangdicun",
    "gn:population":0,
    "gn:timezone":"Asia/Shanghai",
    "iso:country":"CN",
    "name:zho_x_preferred":[
        "\u5b97\u8352\u5730\u6751"
    ],
    "wof:name":"Zonghuangdicun",
    "wof:placetype":"locality"
},
  "geometry": {"coordinates":[123.651,42.3587],"type":"Point"}
}