{
  "type": "Feature",
  "properties": {
    "gn:admin1_code":"32.0",
    "gn:asciiname":"Xifan",
    "gn:country_code":"CN",
    "gn:dem":1190,
    "gn:feature_class":"P",
    "gn:feature_code":"PPL",
    "gn:name":"Xifan",
    "gn:population":0,
    "gn:timezone":"Asia/Shanghai",
    "iso:country":"CN",
    "name:zho_x_preferred":[
        "\u897f\u756a"
    ],
    "wof:name":"Xifan",
    "wof:placetype":"locality"
},
  "geometry": {"coordinates":[101.586,26.94],"type":"Point"}
}