{
  "type": "Feature",
  "properties": {
    "gn:admin1_code":"13",
    "gn:asciiname":"Huqiaxia",
    "gn:country_code":"CN",
    "gn:dem":1307,
    "gn:feature_class":"P",
    "gn:feature_code":"PPL",
    "gn:name":"Huqiaxia",
    "gn:population":0,
    "gn:timezone":"Asia/Urumqi",
    "iso:country":"CN",
    "name:und_x_variant":[
        "\u80e1\u6070\u590f"
    ],
    "wof:name":"Huqiaxia",
    "wof:placetype":"locality"
},
  "geometry": {"coordinates":[91.40260000000001,44.09936],"type":"Point"}
}