{
  "type": "Feature",
  "properties": {
    "gn:admin1_code":"29.0",
    "gn:asciiname":"Weizuicun",
    "gn:country_code":"CN",
    "gn:dem":1561,
    "gn:feature_class":"P",
    "gn:feature_code":"PPL",
    "gn:name":"Weizuicun",
    "gn:population":0,
    "gn:timezone":"Asia/Shanghai",
    "iso:country":"CN",
    "name:zho_x_preferred":[
        "\u5c3e\u5634\u6751"
    ],
    "wof:name":"Weizuicun",
    "wof:placetype":"locality"
},
  "geometry": {"coordinates":[105.18300000000001,27.4727],"type":"Point"}
}