{
  "type": "Feature",
  "properties": {
    "gn:admin1_code":"10.0",
    "gn:asciiname":"Xiage'er",
    "gn:country_code":"CN",
    "gn:dem":289,
    "gn:feature_class":"P",
    "gn:feature_code":"PPL",
    "gn:name":"Xiage\u2019er",
    "gn:population":0,
    "gn:timezone":"Asia/Shanghai",
    "iso:country":"CN",
    "name:und_x_variant":[
        "Xiage\u2019er",
        "\u4e0b\u9601\u5c14"
    ],
    "wof:name":"Xiage'er",
    "wof:placetype":"locality"
},
  "geometry": {"coordinates":[114.58150000000001,38.89324000000001],"type":"Point"}
}