{
  "type": "Feature",
  "properties": {
    "gn:admin1_code":"14.0",
    "gn:asciiname":"Dengmengda",
    "gn:country_code":"CN",
    "gn:dem":4165,
    "gn:feature_class":"P",
    "gn:feature_code":"PPL",
    "gn:name":"Dengmengda",
    "gn:population":0,
    "gn:timezone":"Asia/Urumqi",
    "iso:country":"CN",
    "name:zho_x_preferred":[
        "\u9093\u8499\u8fbe"
    ],
    "wof:name":"Dengmengda",
    "wof:placetype":"locality"
},
  "geometry": {"coordinates":[96.01586,30.73124],"type":"Point"}
}