{
  "type": "Feature",
  "properties": {
    "gn:admin1_code":"8.0",
    "gn:asciiname":"Xinnongcun",
    "gn:country_code":"CN",
    "gn:dem":648,
    "gn:feature_class":"P",
    "gn:feature_code":"PPL",
    "gn:name":"Xinnongcun",
    "gn:population":0,
    "gn:timezone":"Asia/Shanghai",
    "iso:country":"CN",
    "name:zho_x_preferred":[
        "\u65b0\u519c\u6751"
    ],
    "wof:name":"Xinnongcun",
    "wof:placetype":"locality"
},
  "geometry": {"coordinates":[130.89651000000001,45.02203],"type":"Point"}
}