{
  "type": "Feature",
  "properties": {
    "gn:admin1_code":"29",
    "gn:asciiname":"Liujiacaozi",
    "gn:country_code":"CN",
    "gn:dem":1852,
    "gn:feature_class":"P",
    "gn:feature_code":"PPL",
    "gn:name":"Liujiacaozi",
    "gn:population":0,
    "gn:timezone":"Asia/Shanghai",
    "iso:country":"CN",
    "name:zho_x_preferred":[
        "\u5218\u5bb6\u69fd\u5b50"
    ],
    "wof:name":"Liujiacaozi",
    "wof:placetype":"locality"
},
  "geometry": {"coordinates":[101.541,25.0876],"type":"Point"}
}