{
  "type": "Feature",
  "properties": {
    "gn:admin1_code":"24",
    "gn:asciiname":"Baimu",
    "gn:country_code":"CN",
    "gn:dem":1061,
    "gn:feature_class":"P",
    "gn:feature_code":"PPL",
    "gn:name":"Baimu",
    "gn:population":0,
    "gn:timezone":"Asia/Shanghai",
    "iso:country":"CN",
    "name:und_x_variant":[
        "Pai-mu",
        "Pai-mu-kou",
        "Baimu"
    ],
    "name:zho_x_preferred":[
        "\u67cf\u6728"
    ],
    "wof:name":"Baimu",
    "wof:placetype":"locality"
},
  "geometry": {"coordinates":[112.35047,36.36225],"type":"Point"}
}