{
  "type": "Feature",
  "properties": {
    "gn:admin1_code":"32.0",
    "gn:asciiname":"Luo'ergou",
    "gn:country_code":"CN",
    "gn:dem":2165,
    "gn:feature_class":"P",
    "gn:feature_code":"PPL",
    "gn:name":"Luo\u2019ergou",
    "gn:population":0,
    "gn:timezone":"Asia/Shanghai",
    "iso:country":"CN",
    "name:zho_x_preferred":[
        "\u6d1b\u5c14\u6c9f"
    ],
    "name:zho_x_variant":[
        "Luo\u2019ergou"
    ],
    "wof:name":"Luo'ergou",
    "wof:placetype":"locality"
},
  "geometry": {"coordinates":[102.63957000000001,28.78059],"type":"Point"}
}