{
  "type": "Feature",
  "properties": {
    "gn:admin1_code":"4.0",
    "gn:asciiname":"Wufenchang",
    "gn:country_code":"CN",
    "gn:dem":2,
    "gn:feature_class":"P",
    "gn:feature_code":"PPLF",
    "gn:name":"Wufenchang",
    "gn:population":0,
    "gn:timezone":"Asia/Shanghai",
    "iso:country":"CN",
    "name:und_x_variant":[
        "\u4e94\u5206\u573a"
    ],
    "wof:name":"Wufenchang",
    "wof:placetype":"locality"
},
  "geometry": {"coordinates":[120.31541,33.89015999999999],"type":"Point"}
}