{
  "type": "Feature",
  "properties": {
    "gn:admin1_code":"15.0",
    "gn:asciiname":"Chidi",
    "gn:country_code":"CN",
    "gn:dem":2734,
    "gn:feature_class":"P",
    "gn:feature_code":"PPL",
    "gn:name":"Chidi",
    "gn:population":0,
    "gn:timezone":"Asia/Shanghai",
    "iso:country":"CN",
    "name:und_x_variant":[
        "\u6c60\u5730"
    ],
    "wof:name":"Chidi",
    "wof:placetype":"locality"
},
  "geometry": {"coordinates":[103.33821,34.56144],"type":"Point"}
}