{
  "type": "Feature",
  "properties": {
    "gn:admin1_code":"1.0",
    "gn:asciiname":"Dianqiancun",
    "gn:country_code":"CN",
    "gn:dem":127,
    "gn:feature_class":"P",
    "gn:feature_code":"PPL",
    "gn:name":"Dianqiancun",
    "gn:population":0,
    "gn:timezone":"Asia/Shanghai",
    "iso:country":"CN",
    "name:zho_x_preferred":[
        "\u5e97\u524d\u6751"
    ],
    "wof:name":"Dianqiancun",
    "wof:placetype":"locality"
},
  "geometry": {"coordinates":[116.00837,30.72867],"type":"Point"}
}