{
  "type": "Feature",
  "properties": {
    "gn:admin1_code":"30",
    "gn:asciiname":"Yanggan",
    "gn:country_code":"CN",
    "gn:dem":21,
    "gn:feature_class":"P",
    "gn:feature_code":"PPLA4",
    "gn:name":"Yanggan",
    "gn:population":0,
    "gn:timezone":"Asia/Urumqi",
    "iso:country":"CN",
    "name:und_x_variant":[
        "\u6768\u67d1",
        "Yanggan",
        "Yanggan Zhen",
        "\u6768\u67d1\u9547"
    ],
    "wof:name":"Yanggan",
    "wof:placetype":"locality"
},
  "geometry": {"coordinates":[109.91845000000001,21.32189],"type":"Point"}
}