{
  "type": "Feature",
  "properties": {
    "gn:admin1_code":"29.0",
    "gn:asciiname":"Tuolaping",
    "gn:country_code":"CN",
    "gn:dem":2795,
    "gn:feature_class":"P",
    "gn:feature_code":"PPL",
    "gn:name":"Tuolaping",
    "gn:population":0,
    "gn:timezone":"Asia/Shanghai",
    "iso:country":"CN",
    "name:zho_x_preferred":[
        "\u62d6\u62c9\u576a"
    ],
    "wof:name":"Tuolaping",
    "wof:placetype":"locality"
},
  "geometry": {"coordinates":[100.66,27.2195],"type":"Point"}
}