{
  "type": "Feature",
  "properties": {
    "gn:admin1_code":"29.0",
    "gn:asciiname":"Yangcaotang",
    "gn:country_code":"CN",
    "gn:dem":2257,
    "gn:feature_class":"P",
    "gn:feature_code":"PPL",
    "gn:name":"Yangcaotang",
    "gn:population":0,
    "gn:timezone":"Asia/Shanghai",
    "iso:country":"CN",
    "name:zho_x_preferred":[
        "\u79e7\u8349\u5858"
    ],
    "wof:name":"Yangcaotang",
    "wof:placetype":"locality"
},
  "geometry": {"coordinates":[103.06999999999999,25.9702],"type":"Point"}
}