{
  "type": "Feature",
  "properties": {
    "gn:admin1_code":"11",
    "gn:asciiname":"Dachongping",
    "gn:country_code":"CN",
    "gn:dem":189,
    "gn:feature_class":"P",
    "gn:feature_code":"PPL",
    "gn:name":"Dachongping",
    "gn:population":0,
    "gn:timezone":"Asia/Shanghai",
    "iso:country":"CN",
    "name:zho_x_preferred":[
        "\u5927\u51b2\u576a"
    ],
    "wof:name":"Dachongping",
    "wof:placetype":"locality"
},
  "geometry": {"coordinates":[111.76973999999998,27.74417],"type":"Point"}
}