{
  "type": "Feature",
  "properties": {
    "gn:admin1_code":"19.0",
    "gn:asciiname":"Tianguantun",
    "gn:country_code":"CN",
    "gn:dem":119,
    "gn:feature_class":"P",
    "gn:feature_code":"PPL",
    "gn:name":"Tianguantun",
    "gn:population":0,
    "gn:timezone":"Asia/Shanghai",
    "iso:country":"CN",
    "name:und_x_variant":[
        "\u7530\u5b98\u5c6f"
    ],
    "name:zho_x_preferred":[
        "\u7530\u5b98\u5c6f"
    ],
    "wof:name":"Tianguantun",
    "wof:placetype":"locality"
},
  "geometry": {"coordinates":[123.53,41.304],"type":"Point"}
}