{
  "type": "Feature",
  "properties": {
    "gn:admin1_code":"7",
    "gn:asciiname":"Lunan",
    "gn:country_code":"CN",
    "gn:dem":7,
    "gn:feature_class":"P",
    "gn:feature_code":"PPL",
    "gn:name":"Lunan",
    "gn:population":0,
    "gn:timezone":"Asia/Shanghai",
    "iso:country":"CN",
    "name:ceb_x_preferred":[
        "Lunan"
    ],
    "name:deu_x_preferred":[
        "Lunan"
    ],
    "name:nld_x_preferred":[
        "Lunan"
    ],
    "name:swe_x_preferred":[
        "Lunan"
    ],
    "wof:name":"Lunan",
    "wof:placetype":"locality"
},
  "geometry": {"coordinates":[119.73,25.53944],"type":"Point"}
}