{
  "type": "Feature",
  "properties": {
    "gn:admin1_code":"14.0",
    "gn:asciiname":"Xiaobubo",
    "gn:country_code":"CN",
    "gn:dem":4784,
    "gn:feature_class":"P",
    "gn:feature_code":"PPL",
    "gn:name":"Xiaobubo",
    "gn:population":0,
    "gn:timezone":"Asia/Urumqi",
    "iso:country":"CN",
    "name:zho_x_preferred":[
        "\u524a\u5e03\u6ce2"
    ],
    "wof:name":"Xiaobubo",
    "wof:placetype":"locality"
},
  "geometry": {"coordinates":[90.09645999999999,30.90401],"type":"Point"}
}