{
  "type": "Feature",
  "properties": {
    "gn:admin1_code":"4.0",
    "gn:asciiname":"Nanguzhai",
    "gn:country_code":"CN",
    "gn:dem":45,
    "gn:feature_class":"P",
    "gn:feature_code":"PPL",
    "gn:name":"Nanguzhai",
    "gn:population":0,
    "gn:timezone":"Asia/Shanghai",
    "iso:country":"CN",
    "name:und_x_variant":[
        "\u5357\u53e4\u5be8"
    ],
    "wof:name":"Nanguzhai",
    "wof:placetype":"locality"
},
  "geometry": {"coordinates":[118.4426,34.61148],"type":"Point"}
}