{
  "type": "Feature",
  "properties": {
    "gn:admin1_code":"07",
    "gn:asciiname":"Liexi",
    "gn:cc2":"CN",
    "gn:country_code":"CN",
    "gn:dem":137,
    "gn:feature_class":"P",
    "gn:feature_code":"PPL",
    "gn:name":"Liexi",
    "gn:population":0,
    "gn:timezone":"Asia/Shanghai",
    "iso:country":"CN",
    "name:und_x_variant":[
        "Lieh-hsi",
        "Liexi"
    ],
    "wof:name":"Liexi",
    "wof:placetype":"locality"
},
  "geometry": {"coordinates":[117.63833,26.28861],"type":"Point"}
}