{
  "type": "Feature",
  "properties": {
    "gn:admin1_code":"04",
    "gn:asciiname":"Hengjian",
    "gn:country_code":"CN",
    "gn:dem":48,
    "gn:feature_class":"P",
    "gn:feature_code":"PPL",
    "gn:name":"Hengjian",
    "gn:population":0,
    "gn:timezone":"Asia/Shanghai",
    "iso:country":"CN",
    "name:und_x_variant":[
        "Huengchien",
        "Heng-chieh",
        "Heng-chien",
        "Hengjian"
    ],
    "name:zho_x_preferred":[
        "\u6a2a\u6da7"
    ],
    "wof:name":"Hengjian",
    "wof:placetype":"locality"
},
  "geometry": {"coordinates":[119.49963,31.22031],"type":"Point"}
}