{
  "type": "Feature",
  "properties": {
    "gn:admin1_code":"3.0",
    "gn:asciiname":"Wuji",
    "gn:country_code":"CN",
    "gn:dem":535,
    "gn:feature_class":"P",
    "gn:feature_code":"PPL",
    "gn:name":"Wuji",
    "gn:population":0,
    "gn:timezone":"Asia/Shanghai",
    "iso:country":"CN",
    "name:ceb_x_preferred":[
        "Wuji"
    ],
    "name:deu_x_preferred":[
        "Wuji"
    ],
    "name:ita_x_preferred":[
        "Wuji"
    ],
    "name:und_x_variant":[
        "\u5c4b\u8ff9"
    ],
    "wof:name":"Wuji",
    "wof:placetype":"locality"
},
  "geometry": {"coordinates":[115.24079,29.54037000000001],"type":"Point"}
}