{
  "type": "Feature",
  "properties": {
    "gn:admin1_code":"16",
    "gn:asciiname":"Shuiyanba",
    "gn:cc2":"CN",
    "gn:country_code":"CN",
    "gn:dem":443,
    "gn:feature_class":"P",
    "gn:feature_code":"PPL",
    "gn:name":"Shuiyanba",
    "gn:population":0,
    "gn:timezone":"Asia/Shanghai",
    "iso:country":"CN",
    "name:und_x_variant":[
        "Shui-yen-pa",
        "Shuiyanba"
    ],
    "wof:name":"Shuiyanba",
    "wof:placetype":"locality"
},
  "geometry": {"coordinates":[111.56667,24.55],"type":"Point"}
}