{
  "type": "Feature",
  "properties": {
    "gn:admin1_code":"11.0",
    "gn:asciiname":"Nanjiawan",
    "gn:country_code":"CN",
    "gn:dem":172,
    "gn:feature_class":"P",
    "gn:feature_code":"PPL",
    "gn:name":"Nanjiawan",
    "gn:population":0,
    "gn:timezone":"Asia/Shanghai",
    "iso:country":"CN",
    "name:zho_x_preferred":[
        "Nanjiawan"
    ],
    "name:zho_x_variant":[
        "\u5357\u5bb6\u6e7e"
    ],
    "wof:name":"Nanjiawan",
    "wof:placetype":"locality"
},
  "geometry": {"coordinates":[111.28413999999999,29.36718],"type":"Point"}
}