{
  "type": "Feature",
  "properties": {
    "gn:admin1_code":"10.0",
    "gn:asciiname":"Dashiyu",
    "gn:country_code":"CN",
    "gn:dem":449,
    "gn:feature_class":"P",
    "gn:feature_code":"PPL",
    "gn:name":"Dashiyu",
    "gn:population":0,
    "gn:timezone":"Asia/Shanghai",
    "iso:country":"CN",
    "name:zho_x_preferred":[
        "\u5927\u77f3\u5cea"
    ],
    "wof:name":"Dashiyu",
    "wof:placetype":"locality"
},
  "geometry": {"coordinates":[114.60363999999998,39.09781],"type":"Point"}
}