{
  "type": "Feature",
  "properties": {
    "gn:admin1_code":"30.0",
    "gn:asciiname":"Lihuaping",
    "gn:country_code":"CN",
    "gn:dem":163,
    "gn:feature_class":"P",
    "gn:feature_code":"PPL",
    "gn:name":"Lihuaping",
    "gn:population":0,
    "gn:timezone":"Asia/Shanghai",
    "iso:country":"CN",
    "name:zho_x_preferred":[
        "\u674e\u82b1\u576a"
    ],
    "wof:name":"Lihuaping",
    "wof:placetype":"locality"
},
  "geometry": {"coordinates":[114.04634,25.03455],"type":"Point"}
}