{
  "type": "Feature",
  "properties": {
    "gn:admin1_code":"10",
    "gn:asciiname":"Xiasandaogou",
    "gn:country_code":"CN",
    "gn:dem":1603,
    "gn:feature_class":"P",
    "gn:feature_code":"PPL",
    "gn:name":"Xiasandaogou",
    "gn:population":0,
    "gn:timezone":"Asia/Shanghai",
    "iso:country":"CN",
    "name:zho_x_preferred":[
        "\u4e0b\u4e09\u9053\u6c9f"
    ],
    "wof:name":"Xiasandaogou",
    "wof:placetype":"locality"
},
  "geometry": {"coordinates":[114.40197000000001,41.01269],"type":"Point"}
}