{
  "type": "Feature",
  "properties": {
    "gn:admin1_code":"26.0",
    "gn:asciiname":"Liujiahe",
    "gn:country_code":"CN",
    "gn:dem":1320,
    "gn:feature_class":"P",
    "gn:feature_code":"PPL",
    "gn:name":"Liujiahe",
    "gn:population":0,
    "gn:timezone":"Asia/Shanghai",
    "iso:country":"CN",
    "name:zho_x_preferred":[
        "\u5218\u5bb6\u6cb3"
    ],
    "wof:name":"Liujiahe",
    "wof:placetype":"locality"
},
  "geometry": {"coordinates":[108.52748,36.59741],"type":"Point"}
}