{
  "type": "Feature",
  "properties": {
    "gn:admin1_code":"19.0",
    "gn:asciiname":"Dabu Beigou",
    "gn:country_code":"CN",
    "gn:dem":402,
    "gn:feature_class":"P",
    "gn:feature_code":"PPL",
    "gn:name":"Dabu Beigou",
    "gn:population":0,
    "gn:timezone":"Asia/Shanghai",
    "iso:country":"CN",
    "name:und_x_variant":[
        "\u5927\u535c\u5317\u6c9f"
    ],
    "wof:name":"Dabu Beigou",
    "wof:placetype":"locality"
},
  "geometry": {"coordinates":[124.93004999999999,41.67251],"type":"Point"}
}