{
  "type": "Feature",
  "properties": {
    "gn:admin1_code":"2.0",
    "gn:asciiname":"Zoumaling",
    "gn:country_code":"CN",
    "gn:dem":266,
    "gn:feature_class":"P",
    "gn:feature_code":"PPL",
    "gn:name":"Zoumaling",
    "gn:population":0,
    "gn:timezone":"Asia/Shanghai",
    "iso:country":"CN",
    "name:und_x_variant":[
        "\u8d70\u9a6c\u5cad"
    ],
    "wof:name":"Zoumaling",
    "wof:placetype":"locality"
},
  "geometry": {"coordinates":[119.51955,30.72824],"type":"Point"}
}