{
  "type": "Feature",
  "properties": {
    "gn:admin1_code":"21.0",
    "gn:asciiname":"Mamaokeng",
    "gn:country_code":"CN",
    "gn:dem":1413,
    "gn:feature_class":"P",
    "gn:feature_code":"PPL",
    "gn:name":"Mamaokeng",
    "gn:population":0,
    "gn:timezone":"Asia/Shanghai",
    "iso:country":"CN",
    "name:zho_x_preferred":[
        "\u9a6c\u6bdb\u5751"
    ],
    "wof:name":"Mamaokeng",
    "wof:placetype":"locality"
},
  "geometry": {"coordinates":[106.553,37.5045],"type":"Point"}
}