{
  "type": "Feature",
  "properties": {
    "gn:admin1_code":"9.0",
    "gn:asciiname":"Laozhangzhuang",
    "gn:country_code":"CN",
    "gn:dem":132,
    "gn:feature_class":"P",
    "gn:feature_code":"PPL",
    "gn:name":"Laozhangzhuang",
    "gn:population":0,
    "gn:timezone":"Asia/Shanghai",
    "iso:country":"CN",
    "name:zho_x_preferred":[
        "\u8001\u5f20\u5e84"
    ],
    "wof:name":"Laozhangzhuang",
    "wof:placetype":"locality"
},
  "geometry": {"coordinates":[113.8091,34.61718],"type":"Point"}
}