{
  "type": "Feature",
  "properties": {
    "gn:admin1_code":"1.0",
    "gn:asciiname":"Banqiaocun",
    "gn:country_code":"CN",
    "gn:dem":25,
    "gn:feature_class":"P",
    "gn:feature_code":"PPL",
    "gn:name":"Banqiaocun",
    "gn:population":0,
    "gn:timezone":"Asia/Shanghai",
    "iso:country":"CN",
    "name:zho_x_preferred":[
        "\u677f\u6865\u6751"
    ],
    "wof:name":"Banqiaocun",
    "wof:placetype":"locality"
},
  "geometry": {"coordinates":[117.17950999999999,30.86197],"type":"Point"}
}