{
  "type": "Feature",
  "properties": {
    "gn:admin1_code":"4.0",
    "gn:asciiname":"Yangqiao",
    "gn:country_code":"CN",
    "gn:dem":3,
    "gn:feature_class":"P",
    "gn:feature_code":"PPL",
    "gn:name":"Yangqiao",
    "gn:population":0,
    "gn:timezone":"Asia/Shanghai",
    "iso:country":"CN",
    "name:ceb_x_preferred":[
        "Yangqiao"
    ],
    "name:deu_x_preferred":[
        "Yangqiao"
    ],
    "name:swe_x_preferred":[
        "Yangqiao"
    ],
    "name:zho_x_preferred":[
        "\u6768\u6865"
    ],
    "wof:name":"Yangqiao",
    "wof:placetype":"locality"
},
  "geometry": {"coordinates":[119.50593000000001,31.70595],"type":"Point"}
}