{
  "type": "Feature",
  "properties": {
    "gn:admin1_code":"25",
    "gn:asciiname":"Donggouliu",
    "gn:country_code":"CN",
    "gn:dem":98,
    "gn:feature_class":"P",
    "gn:feature_code":"PPL",
    "gn:name":"Donggouliu",
    "gn:population":0,
    "gn:timezone":"Asia/Shanghai",
    "iso:country":"CN",
    "name:zho_x_preferred":[
        "\u4e1c\u6c9f\u6d41"
    ],
    "wof:name":"Donggouliu",
    "wof:placetype":"locality"
},
  "geometry": {"coordinates":[116.34099999999999,36.0429],"type":"Point"}
}