{
  "type": "Feature",
  "properties": {
    "gn:admin1_code":"18",
    "gn:asciiname":"Hejia Wanzi",
    "gn:country_code":"CN",
    "gn:dem":1860,
    "gn:feature_class":"P",
    "gn:feature_code":"PPL",
    "gn:name":"Hejia Wanzi",
    "gn:population":0,
    "gn:timezone":"Asia/Shanghai",
    "iso:country":"CN",
    "name:zho_x_preferred":[
        "\u4f55\u5bb6\u5f2f\u5b50"
    ],
    "wof:name":"Hejia Wanzi",
    "wof:placetype":"locality"
},
  "geometry": {"coordinates":[104.592,27.1595],"type":"Point"}
}