{
  "type": "Feature",
  "properties": {
    "gn:admin1_code":"8.0",
    "gn:asciiname":"Laoqilian",
    "gn:country_code":"CN",
    "gn:dem":367,
    "gn:feature_class":"P",
    "gn:feature_code":"PPL",
    "gn:name":"Laoqilian",
    "gn:population":0,
    "gn:timezone":"Asia/Shanghai",
    "iso:country":"CN",
    "name:zho_x_preferred":[
        "\u8001\u4e03\u8fde"
    ],
    "wof:name":"Laoqilian",
    "wof:placetype":"locality"
},
  "geometry": {"coordinates":[125.44835,49.00707],"type":"Point"}
}