{
  "type": "Feature",
  "properties": {
    "gn:admin1_code":"18",
    "gn:asciiname":"Yansangxi",
    "gn:country_code":"CN",
    "gn:dem":648,
    "gn:feature_class":"P",
    "gn:feature_code":"PPL",
    "gn:name":"Yansangxi",
    "gn:population":0,
    "gn:timezone":"Asia/Shanghai",
    "iso:country":"CN",
    "name:zho_x_preferred":[
        "\u5ca9\u6851\u6eaa"
    ],
    "wof:name":"Yansangxi",
    "wof:placetype":"locality"
},
  "geometry": {"coordinates":[106.233,27.7676],"type":"Point"}
}