{
  "type": "Feature",
  "properties": {
    "gn:admin1_code":"8.0",
    "gn:asciiname":"Guozhan Chentun",
    "gn:country_code":"CN",
    "gn:dem":169,
    "gn:feature_class":"P",
    "gn:feature_code":"PPL",
    "gn:name":"Guozhan Chentun",
    "gn:population":0,
    "gn:timezone":"Asia/Shanghai",
    "iso:country":"CN",
    "name:zho_x_preferred":[
        "\u90ed\u5360\u81e3\u5c6f"
    ],
    "wof:name":"Guozhan Chentun",
    "wof:placetype":"locality"
},
  "geometry": {"coordinates":[124.16789,47.98935],"type":"Point"}
}