{
  "type": "Feature",
  "properties": {
    "gn:admin1_code":"19.0",
    "gn:asciiname":"Dongsidaoling",
    "gn:country_code":"CN",
    "gn:dem":161,
    "gn:feature_class":"P",
    "gn:feature_code":"PPL",
    "gn:name":"Dongsidaoling",
    "gn:population":0,
    "gn:timezone":"Asia/Shanghai",
    "iso:country":"CN",
    "name:zho_x_preferred":[
        "\u4e1c\u56db\u9053\u5cad"
    ],
    "wof:name":"Dongsidaoling",
    "wof:placetype":"locality"
},
  "geometry": {"coordinates":[121.53400000000001,41.9541],"type":"Point"}
}