{
  "type": "Feature",
  "properties": {
    "gn:admin1_code":"5.0",
    "gn:asciiname":"Houguozijing",
    "gn:country_code":"CN",
    "gn:dem":147,
    "gn:feature_class":"P",
    "gn:feature_code":"PPL",
    "gn:name":"Houguozijing",
    "gn:population":0,
    "gn:timezone":"Asia/Shanghai",
    "iso:country":"CN",
    "name:zho_x_preferred":[
        "\u540e\u8fc7\u5b57\u4e95"
    ],
    "wof:name":"Houguozijing",
    "wof:placetype":"locality"
},
  "geometry": {"coordinates":[123.66775,44.90584000000001],"type":"Point"}
}