{
  "type": "Feature",
  "properties": {
    "gn:admin1_code":"21.0",
    "gn:asciiname":"Nanwan",
    "gn:country_code":"CN",
    "gn:dem":1998,
    "gn:feature_class":"P",
    "gn:feature_code":"PPL",
    "gn:name":"Nanwan",
    "gn:population":0,
    "gn:timezone":"Asia/Shanghai",
    "iso:country":"CN",
    "name:und_x_variant":[
        "\u5357\u6e7e"
    ],
    "name:zho_x_preferred":[
        "\u5357\u6e7e"
    ],
    "wof:name":"Nanwan",
    "wof:placetype":"locality"
},
  "geometry": {"coordinates":[105.84763999999998,35.54068],"type":"Point"}
}