{
  "type": "Feature",
  "properties": {
    "gn:admin1_code":"29.0",
    "gn:asciiname":"Shijiuzi",
    "gn:country_code":"CN",
    "gn:dem":1586,
    "gn:feature_class":"P",
    "gn:feature_code":"PPL",
    "gn:name":"Shijiuzi",
    "gn:population":0,
    "gn:timezone":"Asia/Shanghai",
    "iso:country":"CN",
    "name:zho_x_preferred":[
        "\u5b9e\u4e5d\u5b50"
    ],
    "wof:name":"Shijiuzi",
    "wof:placetype":"locality"
},
  "geometry": {"coordinates":[98.8549,26.9964],"type":"Point"}
}