{
  "type": "Feature",
  "properties": {
    "gn:admin1_code":"25",
    "gn:asciiname":"Pozi",
    "gn:country_code":"CN",
    "gn:dem":79,
    "gn:feature_class":"P",
    "gn:feature_code":"PPL",
    "gn:name":"Pozi",
    "gn:population":0,
    "gn:timezone":"Asia/Shanghai",
    "iso:country":"CN",
    "name:zho_x_preferred":[
        "\u5761\u5b50"
    ],
    "wof:name":"Pozi",
    "wof:placetype":"locality"
},
  "geometry": {"coordinates":[118.518,36.6841],"type":"Point"}
}