{
  "type": "Feature",
  "properties": {
    "gn:admin1_code":"12.0",
    "gn:asciiname":"Dagangou",
    "gn:country_code":"CN",
    "gn:dem":805,
    "gn:feature_class":"P",
    "gn:feature_code":"PPL",
    "gn:name":"Dagangou",
    "gn:population":0,
    "gn:timezone":"Asia/Shanghai",
    "iso:country":"CN",
    "name:zho_x_preferred":[
        "\u5927\u5e72\u6c9f"
    ],
    "wof:name":"Dagangou",
    "wof:placetype":"locality"
},
  "geometry": {"coordinates":[110.88512,33.01829],"type":"Point"}
}