{
  "type": "Feature",
  "properties": {
    "gn:admin1_code":"12.0",
    "gn:asciiname":"Dashengmiao",
    "gn:country_code":"CN",
    "gn:dem":959,
    "gn:feature_class":"P",
    "gn:feature_code":"PPL",
    "gn:name":"Dashengmiao",
    "gn:population":0,
    "gn:timezone":"Asia/Shanghai",
    "iso:country":"CN",
    "name:zho_x_preferred":[
        "\u5927\u5723\u5e99"
    ],
    "wof:name":"Dashengmiao",
    "wof:placetype":"locality"
},
  "geometry": {"coordinates":[109.66509000000001,32.05013],"type":"Point"}
}