{
  "type": "Feature",
  "properties": {
    "gn:admin1_code":"25",
    "gn:asciiname":"Canglin",
    "gn:country_code":"CN",
    "gn:dem":16,
    "gn:feature_class":"P",
    "gn:feature_code":"PPL",
    "gn:name":"Canglin",
    "gn:population":0,
    "gn:timezone":"Asia/Shanghai",
    "iso:country":"CN",
    "name:zho_x_preferred":[
        "\u4ed3\u6797"
    ],
    "wof:name":"Canglin",
    "wof:placetype":"locality"
},
  "geometry": {"coordinates":[117.67100000000001,36.957],"type":"Point"}
}