{
  "type": "Feature",
  "properties": {
    "gn:admin1_code":"7.0",
    "gn:asciiname":"Xiakelun",
    "gn:country_code":"CN",
    "gn:dem":374,
    "gn:feature_class":"P",
    "gn:feature_code":"PPL",
    "gn:name":"Xiakelun",
    "gn:population":0,
    "gn:timezone":"Asia/Shanghai",
    "iso:country":"CN",
    "name:zho_x_preferred":[
        "\u971e\u7aa0\u4ed1"
    ],
    "wof:name":"Xiakelun",
    "wof:placetype":"locality"
},
  "geometry": {"coordinates":[117.90258,26.32912],"type":"Point"}
}