{
  "type": "Feature",
  "properties": {
    "gn:admin1_code":"24.0",
    "gn:asciiname":"Zhangcuncun",
    "gn:country_code":"CN",
    "gn:dem":514,
    "gn:feature_class":"P",
    "gn:feature_code":"PPL",
    "gn:name":"Zhangcuncun",
    "gn:population":0,
    "gn:timezone":"Asia/Shanghai",
    "iso:country":"CN",
    "name:zho_x_preferred":[
        "\u5f20\u6751\u6751"
    ],
    "wof:name":"Zhangcuncun",
    "wof:placetype":"locality"
},
  "geometry": {"coordinates":[110.76298,35.21874000000001],"type":"Point"}
}