{
  "type": "Feature",
  "properties": {
    "gn:admin1_code":"29",
    "gn:asciiname":"Yidukou",
    "gn:country_code":"CN",
    "gn:dem":1670,
    "gn:feature_class":"P",
    "gn:feature_code":"PPL",
    "gn:name":"Yidukou",
    "gn:population":0,
    "gn:timezone":"Asia/Shanghai",
    "iso:country":"CN",
    "name:zho_x_preferred":[
        "\u77e3\u90fd\u53e3"
    ],
    "wof:name":"Yidukou",
    "wof:placetype":"locality"
},
  "geometry": {"coordinates":[101.94199999999999,24.368],"type":"Point"}
}