{
  "type": "Feature",
  "properties": {
    "gn:admin1_code":"9",
    "gn:asciiname":"Louzhuang",
    "gn:country_code":"CN",
    "gn:dem":88,
    "gn:feature_class":"P",
    "gn:feature_code":"PPL",
    "gn:name":"Louzhuang",
    "gn:population":0,
    "gn:timezone":"Asia/Shanghai",
    "iso:country":"CN",
    "name:zho_x_preferred":[
        "\u5a04\u5e84"
    ],
    "wof:name":"Louzhuang",
    "wof:placetype":"locality"
},
  "geometry": {"coordinates":[113.40546999999999,33.57678],"type":"Point"}
}