{
  "type": "Feature",
  "properties": {
    "gn:admin1_code":"32",
    "gn:asciiname":"Yanwu",
    "gn:country_code":"CN",
    "gn:dem":703,
    "gn:feature_class":"P",
    "gn:feature_code":"PPL",
    "gn:name":"Yanwu",
    "gn:population":0,
    "gn:timezone":"Asia/Shanghai",
    "iso:country":"CN",
    "name:zho_x_preferred":[
        "\u6f14\u6b66"
    ],
    "wof:name":"Yanwu",
    "wof:placetype":"locality"
},
  "geometry": {"coordinates":[105.24393000000001,31.81677],"type":"Point"}
}