{
  "type": "Feature",
  "properties": {
    "gn:admin1_code":"16",
    "gn:asciiname":"Hekouli",
    "gn:country_code":"CN",
    "gn:dem":165,
    "gn:feature_class":"P",
    "gn:feature_code":"PPL",
    "gn:name":"Hekouli",
    "gn:population":0,
    "gn:timezone":"Asia/Shanghai",
    "iso:country":"CN",
    "name:zho_x_preferred":[
        "\u6cb3\u53e3\u91cc"
    ],
    "wof:name":"Hekouli",
    "wof:placetype":"locality"
},
  "geometry": {"coordinates":[111.004,25.9639],"type":"Point"}
}