{
  "type": "Feature",
  "properties": {
    "gn:admin1_code":"26.0",
    "gn:asciiname":"Xiong'ergou",
    "gn:country_code":"CN",
    "gn:dem":1388,
    "gn:feature_class":"P",
    "gn:feature_code":"PPL",
    "gn:name":"Xiong\u2019ergou",
    "gn:population":0,
    "gn:timezone":"Asia/Shanghai",
    "iso:country":"CN",
    "name:und_x_variant":[
        "Xiong\u2019ergou"
    ],
    "name:zho_x_preferred":[
        "\u718a\u8033\u6c9f"
    ],
    "wof:name":"Xiong'ergou",
    "wof:placetype":"locality"
},
  "geometry": {"coordinates":[110.05997000000001,34.28249],"type":"Point"}
}