{
  "type": "Feature",
  "properties": {
    "gn:admin1_code":"16.0",
    "gn:asciiname":"Zhaimen",
    "gn:country_code":"CN",
    "gn:dem":102,
    "gn:feature_class":"P",
    "gn:feature_code":"PPL",
    "gn:name":"Zhaimen",
    "gn:population":0,
    "gn:timezone":"Asia/Shanghai",
    "iso:country":"CN",
    "name:zho_x_preferred":[
        "\u5be8\u95e8"
    ],
    "wof:name":"Zhaimen",
    "wof:placetype":"locality"
},
  "geometry": {"coordinates":[109.84999999999999,22.822],"type":"Point"}
}