{
  "type": "Feature",
  "properties": {
    "gn:admin1_code":"32.0",
    "gn:asciiname":"Ludigou",
    "gn:country_code":"CN",
    "gn:dem":452,
    "gn:feature_class":"P",
    "gn:feature_code":"PPL",
    "gn:name":"L\u00fcdigou",
    "gn:population":0,
    "gn:timezone":"Asia/Shanghai",
    "iso:country":"CN",
    "name:und_x_variant":[
        "L\u00fcdigou"
    ],
    "name:zho_x_preferred":[
        "\u7eff\u5e95\u6c9f"
    ],
    "wof:name":"Ludigou",
    "wof:placetype":"locality"
},
  "geometry": {"coordinates":[104.551,30.6181],"type":"Point"}
}