{
  "type": "Feature",
  "properties": {
    "gn:admin1_code":"29.0",
    "gn:asciiname":"Manman",
    "gn:country_code":"CN",
    "gn:dem":1313,
    "gn:feature_class":"P",
    "gn:feature_code":"PPL",
    "gn:name":"Manman",
    "gn:population":0,
    "gn:timezone":"Asia/Shanghai",
    "iso:country":"CN",
    "name:zho_x_preferred":[
        "\u66fc\u6ee1"
    ],
    "wof:name":"Manman",
    "wof:placetype":"locality"
},
  "geometry": {"coordinates":[100.20699999999999,21.881],"type":"Point"}
}