{
  "type": "Feature",
  "properties": {
    "gn:admin1_code":"24.0",
    "gn:asciiname":"Houwumu",
    "gn:country_code":"CN",
    "gn:dem":1208,
    "gn:feature_class":"P",
    "gn:feature_code":"PPL",
    "gn:name":"Houwumu",
    "gn:population":0,
    "gn:timezone":"Asia/Shanghai",
    "iso:country":"CN",
    "name:zho_x_preferred":[
        "\u540e\u4e4c\u6728"
    ],
    "wof:name":"Houwumu",
    "wof:placetype":"locality"
},
  "geometry": {"coordinates":[112.27696,36.50455],"type":"Point"}
}