{
  "type": "Feature",
  "properties": {
    "gn:admin1_code":"29",
    "gn:asciiname":"Baita",
    "gn:country_code":"CN",
    "gn:dem":1828,
    "gn:feature_class":"P",
    "gn:feature_code":"PPL",
    "gn:name":"Baita",
    "gn:population":0,
    "gn:timezone":"Asia/Shanghai",
    "iso:country":"CN",
    "name:ceb_x_preferred":[
        "Baita"
    ],
    "name:deu_x_preferred":[
        "Baita"
    ],
    "name:ita_x_preferred":[
        "Baita"
    ],
    "name:swe_x_preferred":[
        "Baita"
    ],
    "name:vie_x_preferred":[
        "Baita"
    ],
    "name:zho_x_preferred":[
        "\u767d\u5854"
    ],
    "wof:name":"Baita",
    "wof:placetype":"locality"
},
  "geometry": {"coordinates":[102.34232,24.99188],"type":"Point"}
}