{
  "type": "Feature",
  "properties": {
    "gn:admin1_code":"11.0",
    "gn:asciiname":"Modaoyan",
    "gn:country_code":"CN",
    "gn:dem":275,
    "gn:feature_class":"P",
    "gn:feature_code":"PPL",
    "gn:name":"Modaoyan",
    "gn:population":0,
    "gn:timezone":"Asia/Shanghai",
    "iso:country":"CN",
    "name:zho_x_preferred":[
        "\u78e8\u5200\u5ca9"
    ],
    "wof:name":"Modaoyan",
    "wof:placetype":"locality"
},
  "geometry": {"coordinates":[110.02028,28.12576],"type":"Point"}
}