{
  "type": "Feature",
  "properties": {
    "gn:admin1_code":"15.0",
    "gn:asciiname":"Gezhiping",
    "gn:country_code":"CN",
    "gn:dem":2058,
    "gn:feature_class":"P",
    "gn:feature_code":"PPL",
    "gn:name":"Gezhiping",
    "gn:population":0,
    "gn:timezone":"Asia/Shanghai",
    "iso:country":"CN",
    "name:zho_x_preferred":[
        "\u683c\u81f4\u576a"
    ],
    "wof:name":"Gezhiping",
    "wof:placetype":"locality"
},
  "geometry": {"coordinates":[103.80200000000001,35.1436],"type":"Point"}
}