{
  "type": "Feature",
  "properties": {
    "gn:admin1_code":"25",
    "gn:asciiname":"Donghoulou",
    "gn:country_code":"CN",
    "gn:dem":53,
    "gn:feature_class":"P",
    "gn:feature_code":"PPL",
    "gn:name":"Donghoulou",
    "gn:population":0,
    "gn:timezone":"Asia/Shanghai",
    "iso:country":"CN",
    "name:zho_x_preferred":[
        "\u4e1c\u4faf\u697c"
    ],
    "wof:name":"Donghoulou",
    "wof:placetype":"locality"
},
  "geometry": {"coordinates":[115.589,35.5347],"type":"Point"}
}