{
  "type": "Feature",
  "properties": {
    "gn:admin1_code":"24.0",
    "gn:asciiname":"Toupu",
    "gn:country_code":"CN",
    "gn:dem":1517,
    "gn:feature_class":"P",
    "gn:feature_code":"PPL",
    "gn:name":"Toupu",
    "gn:population":0,
    "gn:timezone":"Asia/Shanghai",
    "iso:country":"CN",
    "name:und_x_variant":[
        "\u5934\u94fa"
    ],
    "name:zho_x_preferred":[
        "\u5934\u94fa"
    ],
    "wof:name":"Toupu",
    "wof:placetype":"locality"
},
  "geometry": {"coordinates":[112.17658,39.81102],"type":"Point"}
}