{
  "type": "Feature",
  "properties": {
    "gn:admin1_code":"4.0",
    "gn:asciiname":"Maoshecun",
    "gn:country_code":"CN",
    "gn:dem":2,
    "gn:feature_class":"P",
    "gn:feature_code":"PPL",
    "gn:name":"Maoshecun",
    "gn:population":0,
    "gn:timezone":"Asia/Shanghai",
    "iso:country":"CN",
    "name:zho_x_preferred":[
        "\u8306\u820d\u6751"
    ],
    "wof:name":"Maoshecun",
    "wof:placetype":"locality"
},
  "geometry": {"coordinates":[119.45331000000002,33.32269],"type":"Point"}
}