{
  "type": "Feature",
  "properties": {
    "gn:admin1_code":"15.0",
    "gn:asciiname":"Jianshan",
    "gn:country_code":"CN",
    "gn:dem":1653,
    "gn:feature_class":"P",
    "gn:feature_code":"PPL",
    "gn:name":"Jianshan",
    "gn:population":0,
    "gn:timezone":"Asia/Shanghai",
    "iso:country":"CN",
    "name:zho_x_preferred":[
        "\u575a\u5c71"
    ],
    "wof:name":"Jianshan",
    "wof:placetype":"locality"
},
  "geometry": {"coordinates":[105.57299999999999,34.6313],"type":"Point"}
}