{
  "type": "Feature",
  "properties": {
    "gn:admin1_code":"18",
    "gn:asciiname":"Shangbazi",
    "gn:country_code":"CN",
    "gn:dem":1845,
    "gn:feature_class":"P",
    "gn:feature_code":"PPL",
    "gn:name":"Shangbazi",
    "gn:population":0,
    "gn:timezone":"Asia/Shanghai",
    "iso:country":"CN",
    "name:zho_x_preferred":[
        "\u4e0a\u575d\u5b50"
    ],
    "wof:name":"Shangbazi",
    "wof:placetype":"locality"
},
  "geometry": {"coordinates":[105.053,26.523],"type":"Point"}
}