{
  "type": "Feature",
  "properties": {
    "gn:admin1_code":"11.0",
    "gn:asciiname":"Shangjiangchong",
    "gn:country_code":"CN",
    "gn:dem":399,
    "gn:feature_class":"P",
    "gn:feature_code":"PPL",
    "gn:name":"Shangjiangchong",
    "gn:population":0,
    "gn:timezone":"Asia/Shanghai",
    "iso:country":"CN",
    "name:zho_x_preferred":[
        "\u4e0a\u6c5f\u51b2"
    ],
    "wof:name":"Shangjiangchong",
    "wof:placetype":"locality"
},
  "geometry": {"coordinates":[109.49581000000001,26.76083],"type":"Point"}
}