{
  "type": "Feature",
  "properties": {
    "gn:admin1_code":"33.0",
    "gn:asciiname":"Hengcao",
    "gn:country_code":"CN",
    "gn:dem":1065,
    "gn:feature_class":"P",
    "gn:feature_code":"PPL",
    "gn:name":"Hengcao",
    "gn:population":0,
    "gn:timezone":"Asia/Shanghai",
    "iso:country":"CN",
    "name:zho_x_preferred":[
        "\u6a2a\u69fd"
    ],
    "wof:name":"Hengcao",
    "wof:placetype":"locality"
},
  "geometry": {"coordinates":[110.03381,30.95745],"type":"Point"}
}