{
  "type": "Feature",
  "properties": {
    "gn:admin1_code":"29.0",
    "gn:asciiname":"Niuchangshan",
    "gn:country_code":"CN",
    "gn:dem":1500,
    "gn:feature_class":"P",
    "gn:feature_code":"PPL",
    "gn:name":"Niuchangshan",
    "gn:population":0,
    "gn:timezone":"Asia/Shanghai",
    "iso:country":"CN",
    "name:zho_x_preferred":[
        "\u725b\u573a\u5c71"
    ],
    "wof:name":"Niuchangshan",
    "wof:placetype":"locality"
},
  "geometry": {"coordinates":[98.89570000000001,23.7087],"type":"Point"}
}