{
  "type": "Feature",
  "properties": {
    "gn:admin1_code":"30",
    "gn:asciiname":"Shuiweidong",
    "gn:country_code":"CN",
    "gn:dem":24,
    "gn:feature_class":"P",
    "gn:feature_code":"PPL",
    "gn:name":"Shuiweidong",
    "gn:population":0,
    "gn:timezone":"Asia/Shanghai",
    "iso:country":"CN",
    "name:zho_x_preferred":[
        "\u6c34\u5c3e\u578c"
    ],
    "wof:name":"Shuiweidong",
    "wof:placetype":"locality"
},
  "geometry": {"coordinates":[111.64012,22.15746],"type":"Point"}
}