{
  "type": "Feature",
  "properties": {
    "gn:admin1_code":"6.0",
    "gn:asciiname":"Yale Hate",
    "gn:country_code":"CN",
    "gn:dem":3234,
    "gn:feature_class":"P",
    "gn:feature_code":"PPL",
    "gn:name":"Yale Hate",
    "gn:population":0,
    "gn:timezone":"Asia/Urumqi",
    "iso:country":"CN",
    "name:zho_x_preferred":[
        "\u5440\u52d2\u54c8\u7279"
    ],
    "wof:name":"Yale Hate",
    "wof:placetype":"locality"
},
  "geometry": {"coordinates":[97.39896,35.94702],"type":"Point"}
}