{
  "type": "Feature",
  "properties": {
    "gn:admin1_code":"32.0",
    "gn:asciiname":"Jinyu",
    "gn:country_code":"CN",
    "gn:dem":1105,
    "gn:feature_class":"P",
    "gn:feature_code":"PPL",
    "gn:name":"Jinyu",
    "gn:population":0,
    "gn:timezone":"Asia/Shanghai",
    "iso:country":"CN",
    "name:zho_x_preferred":[
        "\u91d1\u9c7c"
    ],
    "wof:name":"Jinyu",
    "wof:placetype":"locality"
},
  "geometry": {"coordinates":[105.81100000000001,28.2366],"type":"Point"}
}