{
  "type": "Feature",
  "properties": {
    "gn:admin1_code":"7",
    "gn:asciiname":"Qingtou",
    "gn:cc2":"CN",
    "gn:country_code":"CN",
    "gn:dem":18,
    "gn:feature_class":"P",
    "gn:feature_code":"PPL",
    "gn:name":"Qingtou",
    "gn:population":0,
    "gn:timezone":"Asia/Shanghai",
    "iso:country":"CN",
    "name:zho_x_preferred":[
        "Ch\u2019ing-t\u2019ou"
    ],
    "name:zho_x_variant":[
        "\u6e05\u900f"
    ],
    "wof:name":"Qingtou",
    "wof:placetype":"locality"
},
  "geometry": {"coordinates":[118.52222,24.64528],"type":"Point"}
}