{
  "type": "Feature",
  "properties": {
    "gn:admin1_code":"12.0",
    "gn:asciiname":"Zhuwufeng",
    "gn:country_code":"CN",
    "gn:dem":46,
    "gn:feature_class":"P",
    "gn:feature_code":"PPL",
    "gn:name":"Zhuwufeng",
    "gn:population":0,
    "gn:timezone":"Asia/Shanghai",
    "iso:country":"CN",
    "name:und_x_variant":[
        "\u6731\u4f0d\u5cf0"
    ],
    "wof:name":"Zhuwufeng",
    "wof:placetype":"locality"
},
  "geometry": {"coordinates":[114.73206,30.91206],"type":"Point"}
}