{
  "type": "Feature",
  "properties": {
    "gn:admin1_code":"26.0",
    "gn:asciiname":"Daheigou",
    "gn:country_code":"CN",
    "gn:dem":912,
    "gn:feature_class":"P",
    "gn:feature_code":"PPL",
    "gn:name":"Daheigou",
    "gn:population":0,
    "gn:timezone":"Asia/Shanghai",
    "iso:country":"CN",
    "name:und_x_variant":[
        "\u5927\u9ed1\u6c9f"
    ],
    "wof:name":"Daheigou",
    "wof:placetype":"locality"
},
  "geometry": {"coordinates":[107.9273,34.12206],"type":"Point"}
}