{
  "type": "Feature",
  "properties": {
    "gn:admin1_code":"16.0",
    "gn:asciiname":"Jiudongli",
    "gn:country_code":"CN",
    "gn:dem":498,
    "gn:feature_class":"P",
    "gn:feature_code":"PPL",
    "gn:name":"Jiudongli",
    "gn:population":0,
    "gn:timezone":"Asia/Shanghai",
    "iso:country":"CN",
    "name:zho_x_preferred":[
        "\u65e7\u5cbd\u529b"
    ],
    "wof:name":"Jiudongli",
    "wof:placetype":"locality"
},
  "geometry": {"coordinates":[107.441,21.9561],"type":"Point"}
}