{
  "type": "Feature",
  "properties": {
    "gn:admin1_code":"14.0",
    "gn:asciiname":"Ga'er Qingpan'er",
    "gn:country_code":"CN",
    "gn:dem":4516,
    "gn:feature_class":"P",
    "gn:feature_code":"PPL",
    "gn:name":"Ga\u2019er Qingpan\u2019er",
    "gn:population":0,
    "gn:timezone":"Asia/Urumqi",
    "iso:country":"CN",
    "name:und_x_variant":[
        "Ga\u2019er Qingpan\u2019er"
    ],
    "name:zho_x_preferred":[
        "\u560e\u5c14\u9752\u76d8\u513f"
    ],
    "wof:name":"Ga'er Qingpan'er",
    "wof:placetype":"locality"
},
  "geometry": {"coordinates":[92.07367000000001,31.33681],"type":"Point"}
}