{
  "type": "Feature",
  "properties": {
    "gn:admin1_code":"3.0",
    "gn:asciiname":"Tianpu",
    "gn:country_code":"CN",
    "gn:dem":67,
    "gn:feature_class":"P",
    "gn:feature_code":"PPL",
    "gn:name":"Tianpu",
    "gn:population":0,
    "gn:timezone":"Asia/Shanghai",
    "iso:country":"CN",
    "name:und_x_variant":[
        "\u7530\u94fa"
    ],
    "wof:name":"Tianpu",
    "wof:placetype":"locality"
},
  "geometry": {"coordinates":[115.61772000000001,29.3603],"type":"Point"}
}