{
  "type": "Feature",
  "properties": {
    "gn:admin1_code":"18.0",
    "gn:asciiname":"Xilu",
    "gn:country_code":"CN",
    "gn:dem":805,
    "gn:feature_class":"P",
    "gn:feature_code":"PPL",
    "gn:name":"Xil\u00fc",
    "gn:population":0,
    "gn:timezone":"Asia/Shanghai",
    "iso:country":"CN",
    "name:und_x_variant":[
        "Xil\u00fc"
    ],
    "name:zho_x_preferred":[
        "\u7cfb\u5415"
    ],
    "wof:name":"Xilu",
    "wof:placetype":"locality"
},
  "geometry": {"coordinates":[108.129,25.6341],"type":"Point"}
}