{
  "type": "Feature",
  "properties": {
    "gn:admin1_code":"4.0",
    "gn:asciiname":"Dongxinqiaocun",
    "gn:country_code":"CN",
    "gn:dem":3,
    "gn:feature_class":"P",
    "gn:feature_code":"PPL",
    "gn:name":"Dongxinqiaocun",
    "gn:population":0,
    "gn:timezone":"Asia/Shanghai",
    "iso:country":"CN",
    "name:und_x_variant":[
        "\u4e1c\u65b0\u6865\u6751"
    ],
    "name:zho_x_preferred":[
        "\u4e1c\u65b0\u6865\u6751"
    ],
    "wof:name":"Dongxinqiaocun",
    "wof:placetype":"locality"
},
  "geometry": {"coordinates":[120.48926000000002,31.72107],"type":"Point"}
}