{
  "type": "Feature",
  "properties": {
    "gn:admin1_code":"12.0",
    "gn:asciiname":"Citangwan",
    "gn:country_code":"CN",
    "gn:dem":32,
    "gn:feature_class":"P",
    "gn:feature_code":"PPL",
    "gn:name":"Citangwan",
    "gn:population":0,
    "gn:timezone":"Asia/Shanghai",
    "iso:country":"CN",
    "name:zho_x_preferred":[
        "\u7960\u5802\u6e7e"
    ],
    "wof:name":"Citangwan",
    "wof:placetype":"locality"
},
  "geometry": {"coordinates":[113.15564000000001,30.48784],"type":"Point"}
}