{
  "type": "Feature",
  "properties": {
    "gn:admin1_code":"29.0",
    "gn:asciiname":"Fabaoqing",
    "gn:country_code":"CN",
    "gn:dem":1407,
    "gn:feature_class":"P",
    "gn:feature_code":"PPL",
    "gn:name":"Fabaoqing",
    "gn:population":0,
    "gn:timezone":"Asia/Shanghai",
    "iso:country":"CN",
    "name:zho_x_preferred":[
        "\u6cd5\u5b9d\u7b90"
    ],
    "wof:name":"Fabaoqing",
    "wof:placetype":"locality"
},
  "geometry": {"coordinates":[103.518,24.0212],"type":"Point"}
}