{
  "type": "Feature",
  "properties": {
    "gn:admin1_code":"5.0",
    "gn:asciiname":"Nanyangcun",
    "gn:country_code":"CN",
    "gn:dem":627,
    "gn:feature_class":"P",
    "gn:feature_code":"PPL",
    "gn:name":"Nanyangcun",
    "gn:population":0,
    "gn:timezone":"Asia/Shanghai",
    "iso:country":"CN",
    "name:zho_x_preferred":[
        "\u5357\u9633\u6751"
    ],
    "wof:name":"Nanyangcun",
    "wof:placetype":"locality"
},
  "geometry": {"coordinates":[126.62025,42.39886],"type":"Point"}
}