{
  "type": "Feature",
  "properties": {
    "gn:admin1_code":"32.0",
    "gn:asciiname":"Shatuo",
    "gn:country_code":"CN",
    "gn:dem":3320,
    "gn:feature_class":"P",
    "gn:feature_code":"PPL",
    "gn:name":"Shatuo",
    "gn:population":0,
    "gn:timezone":"Asia/Urumqi",
    "iso:country":"CN",
    "name:zho_x_preferred":[
        "\u6c99\u62d6"
    ],
    "wof:name":"Shatuo",
    "wof:placetype":"locality"
},
  "geometry": {"coordinates":[98.89409999999999,30.812],"type":"Point"}
}