{
  "type": "Feature",
  "properties": {
    "gn:admin1_code":"32.0",
    "gn:asciiname":"Tubagou",
    "gn:country_code":"CN",
    "gn:dem":1167,
    "gn:feature_class":"P",
    "gn:feature_code":"PPL",
    "gn:name":"Tubagou",
    "gn:population":0,
    "gn:timezone":"Asia/Shanghai",
    "iso:country":"CN",
    "name:zho_x_preferred":[
        "\u571f\u5df4\u6c9f"
    ],
    "wof:name":"Tubagou",
    "wof:placetype":"locality"
},
  "geometry": {"coordinates":[103.19208,29.59848],"type":"Point"}
}