{
  "type": "Feature",
  "properties": {
    "gn:admin1_code":"10.0",
    "gn:asciiname":"Dongnamuzhuang",
    "gn:country_code":"CN",
    "gn:dem":32,
    "gn:feature_class":"P",
    "gn:feature_code":"PPL",
    "gn:name":"Dongnamuzhuang",
    "gn:population":0,
    "gn:timezone":"Asia/Shanghai",
    "iso:country":"CN",
    "name:zho_x_preferred":[
        "\u4e1c\u90a3\u6bcd\u5e84"
    ],
    "wof:name":"Dongnamuzhuang",
    "wof:placetype":"locality"
},
  "geometry": {"coordinates":[118.10861,39.77513],"type":"Point"}
}