{
  "type": "Feature",
  "properties": {
    "gn:admin1_code":"9.0",
    "gn:asciiname":"Qianzhouzhuang",
    "gn:country_code":"CN",
    "gn:dem":59,
    "gn:feature_class":"P",
    "gn:feature_code":"PPL",
    "gn:name":"Qianzhouzhuang",
    "gn:population":0,
    "gn:timezone":"Asia/Shanghai",
    "iso:country":"CN",
    "name:zho_x_preferred":[
        "\u524d\u5468\u5e84"
    ],
    "wof:name":"Qianzhouzhuang",
    "wof:placetype":"locality"
},
  "geometry": {"coordinates":[114.63442999999999,32.45446],"type":"Point"}
}