{
  "type": "Feature",
  "properties": {
    "gn:admin1_code":"3.0",
    "gn:asciiname":"Danyang",
    "gn:country_code":"CN",
    "gn:dem":138,
    "gn:feature_class":"P",
    "gn:feature_code":"PPL",
    "gn:name":"Danyang",
    "gn:population":0,
    "gn:timezone":"Asia/Shanghai",
    "iso:country":"CN",
    "name:ceb_x_preferred":[
        "Danyang"
    ],
    "name:deu_x_preferred":[
        "Danyang"
    ],
    "name:fra_x_preferred":[
        "Danyang"
    ],
    "name:nor_x_preferred":[
        "Danyang"
    ],
    "name:pol_x_preferred":[
        "Danyang"
    ],
    "name:swe_x_preferred":[
        "Danyang"
    ],
    "name:und_x_variant":[
        "\u4e39\u9633"
    ],
    "wof:name":"Danyang",
    "wof:placetype":"locality"
},
  "geometry": {"coordinates":[116.61837,27.02076],"type":"Point"}
}