{
  "type": "Feature",
  "properties": {
    "gn:admin1_code":"2.0",
    "gn:asciiname":"Chenpo'ao",
    "gn:country_code":"CN",
    "gn:dem":91,
    "gn:feature_class":"P",
    "gn:feature_code":"PPL",
    "gn:name":"Chenpo\u2019ao",
    "gn:population":0,
    "gn:timezone":"Asia/Shanghai",
    "iso:country":"CN",
    "name:und_x_variant":[
        "Chenpo\u2019ao"
    ],
    "name:zho_x_preferred":[
        "\u9648\u5a46\u5c99"
    ],
    "wof:name":"Chenpo'ao",
    "wof:placetype":"locality"
},
  "geometry": {"coordinates":[121.0284,28.96397],"type":"Point"}
}