{
  "type": "Feature",
  "properties": {
    "gn:admin1_code":"29.0",
    "gn:asciiname":"Guzha",
    "gn:country_code":"CN",
    "gn:dem":2146,
    "gn:feature_class":"P",
    "gn:feature_code":"PPL",
    "gn:name":"Guzha",
    "gn:population":0,
    "gn:timezone":"Asia/Shanghai",
    "iso:country":"CN",
    "name:zho_x_preferred":[
        "\u8c37\u624e"
    ],
    "wof:name":"Guzha",
    "wof:placetype":"locality"
},
  "geometry": {"coordinates":[98.8814,28.1342],"type":"Point"}
}