{
  "type": "Feature",
  "properties": {
    "gn:admin1_code":"1.0",
    "gn:asciiname":"Waisongkeng",
    "gn:country_code":"CN",
    "gn:dem":347,
    "gn:feature_class":"P",
    "gn:feature_code":"PPL",
    "gn:name":"Waisongkeng",
    "gn:population":0,
    "gn:timezone":"Asia/Shanghai",
    "iso:country":"CN",
    "name:und_x_variant":[
        "\u5916\u7ae6\u5751"
    ],
    "wof:name":"Waisongkeng",
    "wof:placetype":"locality"
},
  "geometry": {"coordinates":[118.43857,30.07813],"type":"Point"}
}