{
  "type": "Feature",
  "properties": {
    "gn:admin1_code":"30",
    "gn:asciiname":"Danzhugen",
    "gn:country_code":"CN",
    "gn:dem":259,
    "gn:feature_class":"P",
    "gn:feature_code":"PPL",
    "gn:name":"Danzhugen",
    "gn:population":0,
    "gn:timezone":"Asia/Urumqi",
    "iso:country":"CN",
    "name:zho_x_preferred":[
        "\u4e39\u7af9\u6839"
    ],
    "wof:name":"Danzhugen",
    "wof:placetype":"locality"
},
  "geometry": {"coordinates":[111.20235,22.01935],"type":"Point"}
}