{
  "type": "Feature",
  "properties": {
    "gn:admin1_code":"10.0",
    "gn:asciiname":"Jingcheng",
    "gn:country_code":"CN",
    "gn:dem":13,
    "gn:feature_class":"P",
    "gn:feature_code":"PPL",
    "gn:name":"Jingcheng",
    "gn:population":0,
    "gn:timezone":"Asia/Shanghai",
    "iso:country":"CN",
    "name:deu_x_preferred":[
        "Jingcheng"
    ],
    "name:zho_x_preferred":[
        "\u666f\u57ce"
    ],
    "wof:name":"Jingcheng",
    "wof:placetype":"locality"
},
  "geometry": {"coordinates":[116.523,38.2907],"type":"Point"}
}