{
  "type": "Feature",
  "properties": {
    "gn:admin1_code":"8.0",
    "gn:asciiname":"Wanghuiwentun",
    "gn:country_code":"CN",
    "gn:dem":188,
    "gn:feature_class":"P",
    "gn:feature_code":"PPL",
    "gn:name":"Wanghuiwentun",
    "gn:population":0,
    "gn:timezone":"Asia/Shanghai",
    "iso:country":"CN",
    "name:zho_x_preferred":[
        "\u738b\u60e0\u6587\u5c6f"
    ],
    "wof:name":"Wanghuiwentun",
    "wof:placetype":"locality"
},
  "geometry": {"coordinates":[126.69884,45.52701],"type":"Point"}
}