{
  "type": "Feature",
  "properties": {
    "gn:admin1_code":"12.0",
    "gn:asciiname":"Duwan",
    "gn:country_code":"CN",
    "gn:dem":28,
    "gn:feature_class":"P",
    "gn:feature_code":"PPL",
    "gn:name":"Duwan",
    "gn:population":0,
    "gn:timezone":"Asia/Shanghai",
    "iso:country":"CN",
    "name:und_x_variant":[
        "\u72ec\u5846"
    ],
    "wof:name":"Duwan",
    "wof:placetype":"locality"
},
  "geometry": {"coordinates":[114.14081000000002,30.75472],"type":"Point"}
}