{
  "type": "Feature",
  "properties": {
    "gn:admin1_code":"29.0",
    "gn:asciiname":"Haitian",
    "gn:country_code":"CN",
    "gn:dem":1983,
    "gn:feature_class":"P",
    "gn:feature_code":"PPL",
    "gn:name":"Haitian",
    "gn:population":0,
    "gn:timezone":"Asia/Shanghai",
    "iso:country":"CN",
    "name:hat_x_preferred":[
        "Ayisyen"
    ],
    "name:zho_x_preferred":[
        "\u6d77\u7530"
    ],
    "wof:name":"Haitian",
    "wof:placetype":"locality"
},
  "geometry": {"coordinates":[104.173,25.7171],"type":"Point"}
}