{
  "type": "Feature",
  "properties": {
    "gn:admin1_code":"25",
    "gn:asciiname":"Lianghecha",
    "gn:country_code":"CN",
    "gn:dem":115,
    "gn:feature_class":"P",
    "gn:feature_code":"PPL",
    "gn:name":"Lianghecha",
    "gn:population":0,
    "gn:timezone":"Asia/Shanghai",
    "iso:country":"CN",
    "name:zho_x_preferred":[
        "\u4e24\u6cb3\u5c94"
    ],
    "wof:name":"Lianghecha",
    "wof:placetype":"locality"
},
  "geometry": {"coordinates":[117.45699999999999,34.948],"type":"Point"}
}