{
  "type": "Feature",
  "properties": {
    "gn:admin1_code":"8.0",
    "gn:asciiname":"Fuxincun",
    "gn:country_code":"CN",
    "gn:dem":196,
    "gn:feature_class":"P",
    "gn:feature_code":"PPL",
    "gn:name":"Fuxincun",
    "gn:population":0,
    "gn:timezone":"Asia/Shanghai",
    "iso:country":"CN",
    "name:zho_x_preferred":[
        "\u5bcc\u65b0\u6751"
    ],
    "wof:name":"Fuxincun",
    "wof:placetype":"locality"
},
  "geometry": {"coordinates":[125.46890999999999,47.30698],"type":"Point"}
}