{
  "type": "Feature",
  "properties": {
    "gn:admin1_code":"7",
    "gn:asciiname":"Dongshanbian",
    "gn:country_code":"CN",
    "gn:dem":72,
    "gn:feature_class":"P",
    "gn:feature_code":"PPL",
    "gn:name":"Dongshanbian",
    "gn:population":0,
    "gn:timezone":"Asia/Shanghai",
    "iso:country":"CN",
    "name:zho_x_preferred":[
        "\u4e1c\u5c71\u8fb9"
    ],
    "wof:name":"Dongshanbian",
    "wof:placetype":"locality"
},
  "geometry": {"coordinates":[119.28140999999999,25.74265],"type":"Point"}
}