{
  "type": "Feature",
  "properties": {
    "gn:admin1_code":"32.0",
    "gn:asciiname":"Huayuansi",
    "gn:country_code":"CN",
    "gn:dem":344,
    "gn:feature_class":"P",
    "gn:feature_code":"PPL",
    "gn:name":"Huayuansi",
    "gn:population":0,
    "gn:timezone":"Asia/Shanghai",
    "iso:country":"CN",
    "name:zho_x_preferred":[
        "\u82b1\u56ed\u5bfa"
    ],
    "wof:name":"Huayuansi",
    "wof:placetype":"locality"
},
  "geometry": {"coordinates":[105.729,30.9222],"type":"Point"}
}