{
  "type": "Feature",
  "properties": {
    "gn:admin1_code":"13.0",
    "gn:asciiname":"Taxmilik",
    "gn:cc2":"CN",
    "gn:country_code":"CN",
    "gn:dem":1554,
    "gn:feature_class":"P",
    "gn:feature_code":"PPL",
    "gn:name":"Taxmilik",
    "gn:population":0,
    "gn:timezone":"Asia/Shanghai",
    "iso:country":"CN",
    "name:uig_x_preferred":[
        "Taxmilik\u0329"
    ],
    "name:uig_x_variant":[
        "Tashmiliq",
        "\u062a\u0627\u0634\u0645\u0649\u0644\u0649\u0642",
        "\u0422\u0430\u0448\u043c\u0438\u043b\u044b\u049b"
    ],
    "name:und_x_variant":[
        "T\u2019a-shih-ma-li-k\u2019o",
        "Taxmilik"
    ],
    "wof:name":"Taxmilik",
    "wof:placetype":"locality"
},
  "geometry": {"coordinates":[75.63944000000002,39.10167],"type":"Point"}
}