{
  "type": "Feature",
  "properties": {
    "gn:admin1_code":"29.0",
    "gn:asciiname":"Xingyezhai",
    "gn:country_code":"CN",
    "gn:dem":1234,
    "gn:feature_class":"P",
    "gn:feature_code":"PPL",
    "gn:name":"Xingyezhai",
    "gn:population":0,
    "gn:timezone":"Asia/Shanghai",
    "iso:country":"CN",
    "name:zho_x_preferred":[
        "\u5174\u4e1a\u5be8"
    ],
    "wof:name":"Xingyezhai",
    "wof:placetype":"locality"
},
  "geometry": {"coordinates":[103.232,23.5055],"type":"Point"}
}