{
  "type": "Feature",
  "properties": {
    "gn:admin1_code":"25",
    "gn:asciiname":"Donglouzhuang",
    "gn:country_code":"CN",
    "gn:dem":42,
    "gn:feature_class":"P",
    "gn:feature_code":"PPL",
    "gn:name":"Donglouzhuang",
    "gn:population":0,
    "gn:timezone":"Asia/Shanghai",
    "iso:country":"CN",
    "name:zho_x_preferred":[
        "\u4e1c\u5a04\u5e84"
    ],
    "wof:name":"Donglouzhuang",
    "wof:placetype":"locality"
},
  "geometry": {"coordinates":[116.736,35.4143],"type":"Point"}
}