{
  "type": "Feature",
  "properties": {
    "gn:admin1_code":"9",
    "gn:asciiname":"Fengzhai",
    "gn:country_code":"CN",
    "gn:dem":57,
    "gn:feature_class":"P",
    "gn:feature_code":"PPL",
    "gn:name":"Fengzhai",
    "gn:population":0,
    "gn:timezone":"Asia/Shanghai",
    "iso:country":"CN",
    "name:zho_x_preferred":[
        "\u51af\u5be8"
    ],
    "wof:name":"Fengzhai",
    "wof:placetype":"locality"
},
  "geometry": {"coordinates":[114.96299999999999,35.7177],"type":"Point"}
}