{
  "type": "Feature",
  "properties": {
    "gn:admin1_code":"29.0",
    "gn:asciiname":"Nancun",
    "gn:country_code":"CN",
    "gn:dem":2107,
    "gn:feature_class":"P",
    "gn:feature_code":"PPL",
    "gn:name":"Nancun",
    "gn:population":0,
    "gn:timezone":"Asia/Shanghai",
    "iso:country":"CN",
    "name:zho_x_preferred":[
        "\u5357\u6751"
    ],
    "wof:name":"Nancun",
    "wof:placetype":"locality"
},
  "geometry": {"coordinates":[103.994,25.9349],"type":"Point"}
}