{
  "type": "Feature",
  "properties": {
    "gn:admin1_code":"11.0",
    "gn:asciiname":"Kuangdongshan",
    "gn:country_code":"CN",
    "gn:dem":619,
    "gn:feature_class":"P",
    "gn:feature_code":"PPL",
    "gn:name":"Kuangdongshan",
    "gn:population":0,
    "gn:timezone":"Asia/Shanghai",
    "iso:country":"CN",
    "name:zho_x_preferred":[
        "\u77ff\u6d1e\u5c71"
    ],
    "wof:name":"Kuangdongshan",
    "wof:placetype":"locality"
},
  "geometry": {"coordinates":[110.04273999999999,29.37039],"type":"Point"}
}