{
  "type": "Feature",
  "properties": {
    "gn:admin1_code":"9.0",
    "gn:asciiname":"Chexianggou",
    "gn:country_code":"CN",
    "gn:dem":497,
    "gn:feature_class":"P",
    "gn:feature_code":"PPL",
    "gn:name":"Chexianggou",
    "gn:population":0,
    "gn:timezone":"Asia/Shanghai",
    "iso:country":"CN",
    "name:zho_x_preferred":[
        "\u8f66\u7bb1\u6c9f"
    ],
    "wof:name":"Chexianggou",
    "wof:placetype":"locality"
},
  "geometry": {"coordinates":[111.45291,33.4198],"type":"Point"}
}