{
  "type": "Feature",
  "properties": {
    "gn:admin1_code":"29",
    "gn:asciiname":"Nasha",
    "gn:country_code":"CN",
    "gn:dem":759,
    "gn:feature_class":"P",
    "gn:feature_code":"PPL",
    "gn:name":"Nasha",
    "gn:population":0,
    "gn:timezone":"Asia/Shanghai",
    "iso:country":"CN",
    "name:ceb_x_preferred":[
        "Nasha"
    ],
    "name:swe_x_preferred":[
        "Nasha"
    ],
    "name:zho_x_preferred":[
        "\u90a3\u6c99"
    ],
    "wof:name":"Nasha",
    "wof:placetype":"locality"
},
  "geometry": {"coordinates":[105.777,23.8763],"type":"Point"}
}