{
  "type": "Feature",
  "properties": {
    "gn:admin1_code":"32.0",
    "gn:asciiname":"Baizhishu",
    "gn:country_code":"CN",
    "gn:dem":1526,
    "gn:feature_class":"P",
    "gn:feature_code":"PPL",
    "gn:name":"Baizhishu",
    "gn:population":0,
    "gn:timezone":"Asia/Shanghai",
    "iso:country":"CN",
    "name:zho_x_preferred":[
        "\u67cf\u679d\u6811"
    ],
    "wof:name":"Baizhishu",
    "wof:placetype":"locality"
},
  "geometry": {"coordinates":[102.16500000000001,27.9443],"type":"Point"}
}