{
  "type": "Feature",
  "properties": {
    "gn:admin1_code":"29",
    "gn:asciiname":"Lijie",
    "gn:country_code":"CN",
    "gn:dem":1278,
    "gn:feature_class":"P",
    "gn:feature_code":"PPL",
    "gn:name":"Lijie",
    "gn:population":0,
    "gn:timezone":"Asia/Shanghai",
    "iso:country":"CN",
    "name:zho_x_preferred":[
        "\u91cc\u8857"
    ],
    "wof:name":"Lijie",
    "wof:placetype":"locality"
},
  "geometry": {"coordinates":[104.953,23.9097],"type":"Point"}
}