{
  "type": "Feature",
  "properties": {
    "gn:admin1_code":"2.0",
    "gn:asciiname":"Dawuli",
    "gn:country_code":"CN",
    "gn:dem":382,
    "gn:feature_class":"P",
    "gn:feature_code":"PPL",
    "gn:name":"Dawuli",
    "gn:population":0,
    "gn:timezone":"Asia/Shanghai",
    "iso:country":"CN",
    "name:zho_x_preferred":[
        "\u5927\u575e\u91cc"
    ],
    "wof:name":"Dawuli",
    "wof:placetype":"locality"
},
  "geometry": {"coordinates":[119.36984,29.64445],"type":"Point"}
}