{
  "type": "Feature",
  "properties": {
    "gn:admin1_code":"25",
    "gn:asciiname":"Yuanzhuang",
    "gn:country_code":"CN",
    "gn:dem":41,
    "gn:feature_class":"P",
    "gn:feature_code":"PPL",
    "gn:name":"Yuanzhuang",
    "gn:population":0,
    "gn:timezone":"Asia/Shanghai",
    "iso:country":"CN",
    "name:und_x_variant":[
        "Xiyuan"
    ],
    "name:zho_x_preferred":[
        "\u8881\u5e84"
    ],
    "name:zho_x_variant":[
        "\u897f\u8881"
    ],
    "wof:name":"Yuanzhuang",
    "wof:placetype":"locality"
},
  "geometry": {"coordinates":[115.76157000000001,36.34864],"type":"Point"}
}