{
  "type": "Feature",
  "properties": {
    "gn:admin1_code":"31.0",
    "gn:asciiname":"Yaxing Xincun",
    "gn:country_code":"CN",
    "gn:dem":145,
    "gn:feature_class":"P",
    "gn:feature_code":"PPL",
    "gn:name":"Yaxing Xincun",
    "gn:population":0,
    "gn:timezone":"Asia/Shanghai",
    "iso:country":"CN",
    "name:zho_x_preferred":[
        "\u96c5\u661f\u65b0\u6751"
    ],
    "wof:name":"Yaxing Xincun",
    "wof:placetype":"locality"
},
  "geometry": {"coordinates":[109.24401,19.44144],"type":"Point"}
}