{
  "type": "Feature",
  "properties": {
    "gn:admin1_code":"29.0",
    "gn:asciiname":"Xiaozhangtian",
    "gn:country_code":"CN",
    "gn:dem":1616,
    "gn:feature_class":"P",
    "gn:feature_code":"PPL",
    "gn:name":"Xiaozhangtian",
    "gn:population":0,
    "gn:timezone":"Asia/Shanghai",
    "iso:country":"CN",
    "name:zho_x_preferred":[
        "\u5c0f\u5f20\u5929"
    ],
    "wof:name":"Xiaozhangtian",
    "wof:placetype":"locality"
},
  "geometry": {"coordinates":[99.6504,23.8389],"type":"Point"}
}