{
  "type": "Feature",
  "properties": {
    "gn:admin1_code":"26.0",
    "gn:asciiname":"Hejia Qucun",
    "gn:country_code":"CN",
    "gn:dem":1123,
    "gn:feature_class":"P",
    "gn:feature_code":"PPL",
    "gn:name":"Hejia Qucun",
    "gn:population":0,
    "gn:timezone":"Asia/Shanghai",
    "iso:country":"CN",
    "name:zho_x_preferred":[
        "\u8d3a\u5bb6\u6e20\u6751"
    ],
    "wof:name":"Hejia Qucun",
    "wof:placetype":"locality"
},
  "geometry": {"coordinates":[109.738,36.9558],"type":"Point"}
}