{
  "type": "Feature",
  "properties": {
    "gn:admin1_code":"18.0",
    "gn:asciiname":"Jiuliba",
    "gn:country_code":"CN",
    "gn:dem":1050,
    "gn:feature_class":"P",
    "gn:feature_code":"PPL",
    "gn:name":"Jiuliba",
    "gn:population":0,
    "gn:timezone":"Asia/Shanghai",
    "iso:country":"CN",
    "name:zho_x_preferred":[
        "\u4e5d\u91cc\u575d"
    ],
    "wof:name":"Jiuliba",
    "wof:placetype":"locality"
},
  "geometry": {"coordinates":[108.70399999999999,26.5873],"type":"Point"}
}