{
  "type": "Feature",
  "properties": {
    "gn:admin1_code":"10",
    "gn:asciiname":"Fucao",
    "gn:country_code":"CN",
    "gn:dem":9,
    "gn:feature_class":"P",
    "gn:feature_code":"PPL",
    "gn:name":"Fucao",
    "gn:population":0,
    "gn:timezone":"Asia/Shanghai",
    "iso:country":"CN",
    "name:und_x_variant":[
        "Fou-ts\u2019ao-ts\u2019un",
        "Fucaocun",
        "Futsao",
        "Fucao"
    ],
    "name:zho_x_preferred":[
        "\u961c\u8349"
    ],
    "wof:name":"Fucao",
    "wof:placetype":"locality"
},
  "geometry": {"coordinates":[116.44199999999999,38.7001],"type":"Point"}
}