{
  "type": "Feature",
  "properties": {
    "gn:admin1_code":"11",
    "gn:asciiname":"Longwangshi",
    "gn:country_code":"CN",
    "gn:dem":170,
    "gn:feature_class":"P",
    "gn:feature_code":"PPL",
    "gn:name":"Longwangshi",
    "gn:population":0,
    "gn:timezone":"Asia/Shanghai",
    "iso:country":"CN",
    "name:zho_x_preferred":[
        "\u9f99\u738b\u5e02"
    ],
    "wof:name":"Longwangshi",
    "wof:placetype":"locality"
},
  "geometry": {"coordinates":[113.26685000000001,26.42062],"type":"Point"}
}