{
  "type": "Feature",
  "properties": {
    "gn:admin1_code":"8.0",
    "gn:asciiname":"Minyi Sansidui",
    "gn:country_code":"CN",
    "gn:dem":245,
    "gn:feature_class":"P",
    "gn:feature_code":"PPLF",
    "gn:name":"Minyi Sansidui",
    "gn:population":0,
    "gn:timezone":"Asia/Shanghai",
    "iso:country":"CN",
    "name:zho_x_preferred":[
        "\u6c11\u610f\u4e09\u56db\u961f"
    ],
    "wof:name":"Minyi Sansidui",
    "wof:placetype":"locality"
},
  "geometry": {"coordinates":[126.84074,47.81794],"type":"Point"}
}