{
  "type": "Feature",
  "properties": {
    "gn:admin1_code":"18",
    "gn:asciiname":"Sanchaoping",
    "gn:country_code":"CN",
    "gn:dem":1128,
    "gn:feature_class":"P",
    "gn:feature_code":"PPL",
    "gn:name":"Sanchaoping",
    "gn:population":0,
    "gn:timezone":"Asia/Shanghai",
    "iso:country":"CN",
    "name:zho_x_preferred":[
        "\u4e09\u8d85\u576a"
    ],
    "wof:name":"Sanchaoping",
    "wof:placetype":"locality"
},
  "geometry": {"coordinates":[107.553,27.1042],"type":"Point"}
}