{
  "type": "Feature",
  "properties": {
    "gn:admin1_code":"8.0",
    "gn:asciiname":"Liujiafenkeng",
    "gn:country_code":"CN",
    "gn:dem":276,
    "gn:feature_class":"P",
    "gn:feature_code":"PPL",
    "gn:name":"Liujiafenkeng",
    "gn:population":0,
    "gn:timezone":"Asia/Shanghai",
    "iso:country":"CN",
    "name:zho_x_preferred":[
        "\u5218\u5bb6\u7c89\u5751"
    ],
    "wof:name":"Liujiafenkeng",
    "wof:placetype":"locality"
},
  "geometry": {"coordinates":[126.31131999999999,47.93913],"type":"Point"}
}