{
  "type": "Feature",
  "properties": {
    "gn:admin1_code":"07",
    "gn:asciiname":"Kanshi",
    "gn:country_code":"CN",
    "gn:dem":272,
    "gn:feature_class":"P",
    "gn:feature_code":"PPLA4",
    "gn:name":"Kanshi",
    "gn:population":0,
    "gn:timezone":"Asia/Shanghai",
    "iso:country":"CN",
    "name:und_x_variant":[
        "Kunshih",
        "Kanshi",
        "\u574e\u5e02",
        "Kanshi Zhen"
    ],
    "name:zho_x_preferred":[
        "K\u2019an-shih"
    ],
    "name:zho_x_variant":[
        "T\u2019ai-p\u2019ing",
        "\u574e\u5e02",
        "\u574e\u5e02\u9547"
    ],
    "wof:name":"Kanshi",
    "wof:placetype":"locality"
},
  "geometry": {"coordinates":[116.88833,24.91861],"type":"Point"}
}