{
  "type": "Feature",
  "properties": {
    "gn:admin1_code":"4.0",
    "gn:asciiname":"Dingzi'an",
    "gn:country_code":"CN",
    "gn:dem":6,
    "gn:feature_class":"P",
    "gn:feature_code":"PPL",
    "gn:name":"Dingzi\u2019an",
    "gn:population":0,
    "gn:timezone":"Asia/Shanghai",
    "iso:country":"CN",
    "name:zho_x_preferred":[
        "Dingzi\u2019an"
    ],
    "name:zho_x_variant":[
        "\u4e01\u5b57\u5cb8"
    ],
    "wof:name":"Dingzi'an",
    "wof:placetype":"locality"
},
  "geometry": {"coordinates":[121.21553,32.2404],"type":"Point"}
}