{
  "type": "Feature",
  "properties": {
    "gn:admin1_code":"3.0",
    "gn:asciiname":"Nangangling",
    "gn:country_code":"CN",
    "gn:dem":282,
    "gn:feature_class":"P",
    "gn:feature_code":"PPL",
    "gn:name":"Nangangling",
    "gn:population":0,
    "gn:timezone":"Asia/Shanghai",
    "iso:country":"CN",
    "name:und_x_variant":[
        "\u5357\u5c97\u5cad"
    ],
    "wof:name":"Nangangling",
    "wof:placetype":"locality"
},
  "geometry": {"coordinates":[115.09751,26.51758],"type":"Point"}
}