{
  "type": "Feature",
  "properties": {
    "gn:admin1_code":"3.0",
    "gn:asciiname":"Honghu Fenchang",
    "gn:country_code":"CN",
    "gn:dem":31,
    "gn:feature_class":"P",
    "gn:feature_code":"PPLF",
    "gn:name":"Honghu Fenchang",
    "gn:population":0,
    "gn:timezone":"Asia/Shanghai",
    "iso:country":"CN",
    "name:und_x_variant":[
        "\u7ea2\u6e56\u5206\u573a"
    ],
    "wof:name":"Honghu Fenchang",
    "wof:placetype":"locality"
},
  "geometry": {"coordinates":[115.68076000000001,29.08999],"type":"Point"}
}