{
  "type": "Feature",
  "properties": {
    "gn:admin1_code":"9.0",
    "gn:asciiname":"Xishengying",
    "gn:country_code":"CN",
    "gn:dem":46,
    "gn:feature_class":"P",
    "gn:feature_code":"PPL",
    "gn:name":"Xishengying",
    "gn:population":0,
    "gn:timezone":"Asia/Shanghai",
    "iso:country":"CN",
    "name:zho_x_preferred":[
        "\u897f\u76db\u8425"
    ],
    "wof:name":"Xishengying",
    "wof:placetype":"locality"
},
  "geometry": {"coordinates":[114.81185000000001,33.17985],"type":"Point"}
}