{
  "type": "Feature",
  "properties": {
    "gn:admin1_code":"15.0",
    "gn:asciiname":"Yinxingshuping",
    "gn:country_code":"CN",
    "gn:dem":993,
    "gn:feature_class":"P",
    "gn:feature_code":"PPL",
    "gn:name":"Yinxingshuping",
    "gn:population":0,
    "gn:timezone":"Asia/Shanghai",
    "iso:country":"CN",
    "name:und_x_variant":[
        "\u94f6\u674f\u6811\u576a"
    ],
    "wof:name":"Yinxingshuping",
    "wof:placetype":"locality"
},
  "geometry": {"coordinates":[106.30713,33.75776],"type":"Point"}
}