{
  "type": "Feature",
  "properties": {
    "gn:admin1_code":"29.0",
    "gn:asciiname":"Xiebu",
    "gn:country_code":"CN",
    "gn:dem":1740,
    "gn:feature_class":"P",
    "gn:feature_code":"PPL",
    "gn:name":"Xiebu",
    "gn:population":0,
    "gn:timezone":"Asia/Shanghai",
    "iso:country":"CN",
    "name:zho_x_preferred":[
        "\u8c22\u8865"
    ],
    "wof:name":"Xiebu",
    "wof:placetype":"locality"
},
  "geometry": {"coordinates":[104.56399999999999,25.0143],"type":"Point"}
}