{
  "type": "Feature",
  "properties": {
    "gn:admin1_code":"29.0",
    "gn:asciiname":"Man'en",
    "gn:country_code":"CN",
    "gn:dem":1180,
    "gn:feature_class":"P",
    "gn:feature_code":"PPL",
    "gn:name":"Man\u2019en",
    "gn:population":0,
    "gn:timezone":"Asia/Shanghai",
    "iso:country":"CN",
    "name:und_x_variant":[
        "Man\u2019en"
    ],
    "name:zho_x_preferred":[
        "\u66fc\u6069"
    ],
    "wof:name":"Man'en",
    "wof:placetype":"locality"
},
  "geometry": {"coordinates":[100.36199999999999,21.9472],"type":"Point"}
}