{
  "type": "Feature",
  "properties": {
    "gn:admin1_code":"29.0",
    "gn:asciiname":"Man'en",
    "gn:country_code":"CN",
    "gn:dem":1180,
    "gn:feature_class":"P",
    "gn:feature_code":"PPL",
    "gn:name":"Man\u2019en",
    "gn:population":0,
    "gn:timezone":"Asia/Shanghai",
    "iso:country":"CN",
    "name:fas_x_preferred":[
        "\u0645\u0627\u0646\u0626\u0646"
    ],
    "name:fra_x_preferred":[
        "\u00c8re Man'en"
    ],
    "name:rus_x_preferred":[
        "\u041c\u0430\u043d\u044a\u044d\u043d"
    ],
    "name:spa_x_preferred":[
        "Man'en"
    ],
    "name:srp_x_preferred":[
        "\u041c\u0430\u043d\u0435\u043d"
    ],
    "name:swe_x_preferred":[
        "Manen"
    ],
    "name:und_x_variant":[
        "Man\u2019en"
    ],
    "name:zho_x_preferred":[
        "\u66fc\u6069"
    ],
    "wof:name":"Man'en",
    "wof:placetype":"locality"
},
  "geometry": {"coordinates":[100.36199999999999,21.9472],"type":"Point"}
}