{
  "type": "Feature",
  "properties": {
    "gn:admin1_code":"4.0",
    "gn:asciiname":"Laobacun",
    "gn:country_code":"CN",
    "gn:dem":23,
    "gn:feature_class":"P",
    "gn:feature_code":"PPL",
    "gn:name":"Laobacun",
    "gn:population":0,
    "gn:timezone":"Asia/Shanghai",
    "iso:country":"CN",
    "name:zho_x_preferred":[
        "\u8001\u575d\u6751"
    ],
    "wof:name":"Laobacun",
    "wof:placetype":"locality"
},
  "geometry": {"coordinates":[119.17010999999999,32.54132],"type":"Point"}
}