{
  "type": "Feature",
  "properties": {
    "gn:admin1_code":"24.0",
    "gn:asciiname":"Yangmosi",
    "gn:country_code":"CN",
    "gn:dem":1460,
    "gn:feature_class":"P",
    "gn:feature_code":"PPL",
    "gn:name":"Yangmosi",
    "gn:population":0,
    "gn:timezone":"Asia/Shanghai",
    "iso:country":"CN",
    "name:zho_x_preferred":[
        "\u7f8a\u6469\u5bfa"
    ],
    "wof:name":"Yangmosi",
    "wof:placetype":"locality"
},
  "geometry": {"coordinates":[113.11432000000001,38.06438],"type":"Point"}
}