{
  "type": "Feature",
  "properties": {
    "gn:admin1_code":"11",
    "gn:asciiname":"Chutouping",
    "gn:country_code":"CN",
    "gn:dem":286,
    "gn:feature_class":"P",
    "gn:feature_code":"PPL",
    "gn:name":"Chutouping",
    "gn:population":0,
    "gn:timezone":"Asia/Shanghai",
    "iso:country":"CN",
    "name:zho_x_preferred":[
        "\u9504\u5934\u576a"
    ],
    "wof:name":"Chutouping",
    "wof:placetype":"locality"
},
  "geometry": {"coordinates":[110.21185,27.74533],"type":"Point"}
}