{
  "type": "Feature",
  "properties": {
    "gn:admin1_code":"33.0",
    "gn:asciiname":"Waziba",
    "gn:country_code":"CN",
    "gn:dem":252,
    "gn:feature_class":"P",
    "gn:feature_code":"PPL",
    "gn:name":"Waziba",
    "gn:population":0,
    "gn:timezone":"Asia/Shanghai",
    "iso:country":"CN",
    "name:zho_x_preferred":[
        "\u74e6\u5b50\u575d"
    ],
    "wof:name":"Waziba",
    "wof:placetype":"locality"
},
  "geometry": {"coordinates":[106.19273,28.98059000000001],"type":"Point"}
}