{
  "type": "Feature",
  "properties": {
    "gn:admin1_code":"29",
    "gn:asciiname":"Batanqiao",
    "gn:country_code":"CN",
    "gn:dem":2187,
    "gn:feature_class":"P",
    "gn:feature_code":"PPL",
    "gn:name":"Batanqiao",
    "gn:population":0,
    "gn:timezone":"Asia/Shanghai",
    "iso:country":"CN",
    "name:zho_x_preferred":[
        "\u634c\u5766\u835e"
    ],
    "wof:name":"Batanqiao",
    "wof:placetype":"locality"
},
  "geometry": {"coordinates":[102.70014999999999,24.24899],"type":"Point"}
}