{
  "type": "Feature",
  "properties": {
    "gn:admin1_code":"7.0",
    "gn:asciiname":"Hekeng Nongchang",
    "gn:country_code":"CN",
    "gn:dem":378,
    "gn:feature_class":"P",
    "gn:feature_code":"PPLF",
    "gn:name":"Hekeng Nongchang",
    "gn:population":0,
    "gn:timezone":"Asia/Shanghai",
    "iso:country":"CN",
    "name:und_x_variant":[
        "\u6cb3\u5751\u519c\u573a"
    ],
    "wof:name":"Hekeng Nongchang",
    "wof:placetype":"locality"
},
  "geometry": {"coordinates":[116.74866000000002,26.43318],"type":"Point"}
}