{
  "type": "Feature",
  "properties": {
    "gn:admin1_code":"7",
    "gn:asciiname":"Fangguangsi",
    "gn:country_code":"CN",
    "gn:dem":929,
    "gn:feature_class":"P",
    "gn:feature_code":"PPL",
    "gn:name":"Fangguangsi",
    "gn:population":0,
    "gn:timezone":"Asia/Shanghai",
    "iso:country":"CN",
    "name:und_x_variant":[
        "\u65b9\u5e7f\u5bfa",
        "Fangguangsi"
    ],
    "wof:name":"Fangguangsi",
    "wof:placetype":"locality"
},
  "geometry": {"coordinates":[119.44289000000001,27.01273],"type":"Point"}
}