{
  "type": "Feature",
  "properties": {
    "gn:admin1_code":"11",
    "gn:asciiname":"Chayuanping",
    "gn:country_code":"CN",
    "gn:dem":977,
    "gn:feature_class":"P",
    "gn:feature_code":"PPL",
    "gn:name":"Chayuanping",
    "gn:population":0,
    "gn:timezone":"Asia/Shanghai",
    "iso:country":"CN",
    "name:und_x_variant":[
        "\u8336\u56ed\u576a"
    ],
    "wof:name":"Chayuanping",
    "wof:placetype":"locality"
},
  "geometry": {"coordinates":[110.83806,30.09361],"type":"Point"}
}