{
  "type": "Feature",
  "properties": {
    "gn:admin1_code":"30.0",
    "gn:asciiname":"Daping",
    "gn:country_code":"CN",
    "gn:dem":129,
    "gn:feature_class":"P",
    "gn:feature_code":"PPL",
    "gn:name":"Daping",
    "gn:population":0,
    "gn:timezone":"Asia/Shanghai",
    "iso:country":"CN",
    "name:ceb_x_preferred":[
        "Daping"
    ],
    "name:deu_x_preferred":[
        "Daping"
    ],
    "name:swe_x_preferred":[
        "Daping"
    ],
    "name:zho_x_preferred":[
        "\u5927\u576a"
    ],
    "wof:name":"Daping",
    "wof:placetype":"locality"
},
  "geometry": {"coordinates":[114.12092,25.04266],"type":"Point"}
}