{
  "type": "Feature",
  "properties": {
    "gn:admin1_code":"5.0",
    "gn:asciiname":"Xiaoduanzijing",
    "gn:country_code":"CN",
    "gn:dem":143,
    "gn:feature_class":"P",
    "gn:feature_code":"PPL",
    "gn:name":"Xiaoduanzijing",
    "gn:population":0,
    "gn:timezone":"Asia/Shanghai",
    "iso:country":"CN",
    "name:zho_x_preferred":[
        "\u5c0f\u7aef\u5b57\u4e95"
    ],
    "wof:name":"Xiaoduanzijing",
    "wof:placetype":"locality"
},
  "geometry": {"coordinates":[123.64452,44.89952],"type":"Point"}
}