{
  "type": "Feature",
  "properties": {
    "gn:admin1_code":"1.0",
    "gn:asciiname":"Sishancun",
    "gn:country_code":"CN",
    "gn:dem":46,
    "gn:feature_class":"P",
    "gn:feature_code":"PPL",
    "gn:name":"Sishancun",
    "gn:population":0,
    "gn:timezone":"Asia/Shanghai",
    "iso:country":"CN",
    "name:zho_x_preferred":[
        "\u5bfa\u5c71\u6751"
    ],
    "wof:name":"Sishancun",
    "wof:placetype":"locality"
},
  "geometry": {"coordinates":[117.65134999999999,32.76306],"type":"Point"}
}