{
  "type": "Feature",
  "properties": {
    "gn:admin1_code":"02",
    "gn:asciiname":"Dasong",
    "gn:country_code":"CN",
    "gn:dem":10,
    "gn:feature_class":"P",
    "gn:feature_code":"PPL",
    "gn:name":"Dasong",
    "gn:population":0,
    "gn:timezone":"Asia/Shanghai",
    "iso:country":"CN",
    "name:und_x_variant":[
        "Ta-sung-ch\u2019eng",
        "Ta-sung",
        "Dasong"
    ],
    "name:zho_x_preferred":[
        "\u5927\u5d69"
    ],
    "wof:name":"Dasong",
    "wof:placetype":"locality"
},
  "geometry": {"coordinates":[121.77909,29.71455],"type":"Point"}
}