{
  "type": "Feature",
  "properties": {
    "gn:admin1_code":"24.0",
    "gn:asciiname":"Huagedao",
    "gn:country_code":"CN",
    "gn:dem":1471,
    "gn:feature_class":"P",
    "gn:feature_code":"PPL",
    "gn:name":"Huagedao",
    "gn:population":0,
    "gn:timezone":"Asia/Shanghai",
    "iso:country":"CN",
    "name:zho_x_preferred":[
        "\u5316\u572a\u9053"
    ],
    "wof:name":"Huagedao",
    "wof:placetype":"locality"
},
  "geometry": {"coordinates":[113.50192,36.20276],"type":"Point"}
}