{
  "type": "Feature",
  "properties": {
    "gn:admin1_code":"22.0",
    "gn:asciiname":"Xichangyucun",
    "gn:country_code":"CN",
    "gn:dem":271,
    "gn:feature_class":"P",
    "gn:feature_code":"PPL",
    "gn:name":"Xichangyucun",
    "gn:population":0,
    "gn:timezone":"Asia/Shanghai",
    "iso:country":"CN",
    "name:zho_x_preferred":[
        "\u897f\u957f\u5cea\u6751"
    ],
    "wof:name":"Xichangyucun",
    "wof:placetype":"locality"
},
  "geometry": {"coordinates":[117.07292,40.33819],"type":"Point"}
}