{
  "type": "Feature",
  "properties": {
    "gn:admin1_code":"15.0",
    "gn:asciiname":"Xiawufen",
    "gn:country_code":"CN",
    "gn:dem":1162,
    "gn:feature_class":"P",
    "gn:feature_code":"PPL",
    "gn:name":"Xiawufen",
    "gn:population":0,
    "gn:timezone":"Asia/Shanghai",
    "iso:country":"CN",
    "name:zho_x_preferred":[
        "\u4e0b\u4e94\u5206"
    ],
    "wof:name":"Xiawufen",
    "wof:placetype":"locality"
},
  "geometry": {"coordinates":[99.6305,40.4227],"type":"Point"}
}