{
  "type": "Feature",
  "properties": {
    "gn:admin1_code":"15.0",
    "gn:asciiname":"Panling",
    "gn:country_code":"CN",
    "gn:dem":1703,
    "gn:feature_class":"P",
    "gn:feature_code":"PPL",
    "gn:name":"Panling",
    "gn:population":0,
    "gn:timezone":"Asia/Shanghai",
    "iso:country":"CN",
    "name:zho_x_preferred":[
        "\u6f58\u5cad"
    ],
    "wof:name":"Panling",
    "wof:placetype":"locality"
},
  "geometry": {"coordinates":[106.78100000000001,35.3533],"type":"Point"}
}