{
  "type": "Feature",
  "properties": {
    "gn:admin1_code":"32.0",
    "gn:asciiname":"Ergengmi",
    "gn:country_code":"CN",
    "gn:dem":2503,
    "gn:feature_class":"P",
    "gn:feature_code":"PPL",
    "gn:name":"Ergengmi",
    "gn:population":0,
    "gn:timezone":"Asia/Shanghai",
    "iso:country":"CN",
    "name:zho_x_preferred":[
        "\u4e8c\u5e9a\u7c73"
    ],
    "wof:name":"Ergengmi",
    "wof:placetype":"locality"
},
  "geometry": {"coordinates":[103.69199999999999,31.7551],"type":"Point"}
}