{
  "type": "Feature",
  "properties": {
    "gn:admin1_code":"19.0",
    "gn:asciiname":"Beiqinyingzi",
    "gn:country_code":"CN",
    "gn:dem":276,
    "gn:feature_class":"P",
    "gn:feature_code":"PPL",
    "gn:name":"Beiqinyingzi",
    "gn:population":0,
    "gn:timezone":"Asia/Shanghai",
    "iso:country":"CN",
    "name:zho_x_preferred":[
        "\u5317\u79e6\u8425\u5b50"
    ],
    "wof:name":"Beiqinyingzi",
    "wof:placetype":"locality"
},
  "geometry": {"coordinates":[120.41368,41.06208],"type":"Point"}
}