{
  "type": "Feature",
  "properties": {
    "gn:admin1_code":"02",
    "gn:asciiname":"Dao'antoucun",
    "gn:country_code":"CN",
    "gn:dem":8,
    "gn:feature_class":"P",
    "gn:feature_code":"PPL",
    "gn:name":"Dao\u2019antoucun",
    "gn:population":0,
    "gn:timezone":"Asia/Shanghai",
    "iso:country":"CN",
    "name:und_x_variant":[
        "T\u2019ang-an-t\u2019ou",
        "Dao\u2019antoucun"
    ],
    "name:zho_x_preferred":[
        "\u9053\u5cb8\u5934"
    ],
    "name:zho_x_variant":[
        "Dao\u2019antou",
        "\u9053\u5cb8\u5934\u6751"
    ],
    "wof:name":"Dao'antoucun",
    "wof:placetype":"locality"
},
  "geometry": {"coordinates":[121.41687,29.1535],"type":"Point"}
}