{
  "type": "Feature",
  "properties": {
    "gn:admin1_code":"24.0",
    "gn:asciiname":"Changjiagou",
    "gn:country_code":"CN",
    "gn:dem":1460,
    "gn:feature_class":"P",
    "gn:feature_code":"PPL",
    "gn:name":"Changjiagou",
    "gn:population":0,
    "gn:timezone":"Asia/Shanghai",
    "iso:country":"CN",
    "name:zho_x_preferred":[
        "\u5e38\u5bb6\u6c9f"
    ],
    "wof:name":"Changjiagou",
    "wof:placetype":"locality"
},
  "geometry": {"coordinates":[111.26286,38.35334],"type":"Point"}
}