{
  "type": "Feature",
  "properties": {
    "gn:admin1_code":"30",
    "gn:asciiname":"Zhutian",
    "gn:country_code":"CN",
    "gn:dem":130,
    "gn:feature_class":"P",
    "gn:feature_code":"PPLA4",
    "gn:name":"Zhutian",
    "gn:population":0,
    "gn:timezone":"Asia/Shanghai",
    "iso:country":"CN",
    "name:und_x_variant":[
        "Zhutian Zhen",
        "\u4e3b\u7530\u9547"
    ],
    "name:zho_x_preferred":[
        "\u4e3b\u7530"
    ],
    "wof:name":"Zhutian",
    "wof:placetype":"locality"
},
  "geometry": {"coordinates":[114.29583,25.06528],"type":"Point"}
}