{
  "type": "Feature",
  "properties": {
    "gn:admin1_code":"30",
    "gn:asciiname":"Zhutian",
    "gn:country_code":"CN",
    "gn:dem":130,
    "gn:feature_class":"P",
    "gn:feature_code":"PPLA4",
    "gn:name":"Zhutian",
    "gn:population":0,
    "gn:timezone":"Asia/Shanghai",
    "iso:country":"CN",
    "name:hak_x_preferred":[
        "Tsuk-thi\u00e8n-hi\u00f4ng"
    ],
    "name:jpn_x_preferred":[
        "\u7af9\u7530\u90f7"
    ],
    "name:kor_x_preferred":[
        "\uc8fc\ud188\ud5a5"
    ],
    "name:und_x_variant":[
        "Zhutian Zhen",
        "\u4e3b\u7530\u9547"
    ],
    "name:vie_x_preferred":[
        "Tr\u00fac \u0110i\u1ec1n"
    ],
    "name:zho_x_preferred":[
        "\u4e3b\u7530"
    ],
    "name:zho_x_variant":[
        "\u7af9\u7530\u9109"
    ],
    "wof:name":"Zhutian",
    "wof:placetype":"locality"
},
  "geometry": {"coordinates":[114.29583,25.06528],"type":"Point"}
}