{
  "type": "Feature",
  "properties": {
    "gn:admin1_code":"25",
    "gn:asciiname":"Nanbaita",
    "gn:country_code":"CN",
    "gn:dem":205,
    "gn:feature_class":"P",
    "gn:feature_code":"PPL",
    "gn:name":"Nanbaita",
    "gn:population":0,
    "gn:timezone":"Asia/Shanghai",
    "iso:country":"CN",
    "name:zho_x_preferred":[
        "\u5357\u767d\u5854"
    ],
    "wof:name":"Nanbaita",
    "wof:placetype":"locality"
},
  "geometry": {"coordinates":[117.458,36.0957],"type":"Point"}
}