{
  "type": "Feature",
  "properties": {
    "gn:admin1_code":"5.0",
    "gn:asciiname":"Yinglincun",
    "gn:country_code":"CN",
    "gn:dem":610,
    "gn:feature_class":"P",
    "gn:feature_code":"PPL",
    "gn:name":"Yinglincun",
    "gn:population":0,
    "gn:timezone":"Asia/Shanghai",
    "iso:country":"CN",
    "name:zho_x_preferred":[
        "\u8425\u6797\u6751"
    ],
    "wof:name":"Yinglincun",
    "wof:placetype":"locality"
},
  "geometry": {"coordinates":[128.33013,42.49644],"type":"Point"}
}