{
  "type": "Feature",
  "properties": {
    "gn:admin1_code":"11.0",
    "gn:asciiname":"Ganxigou",
    "gn:country_code":"CN",
    "gn:dem":157,
    "gn:feature_class":"P",
    "gn:feature_code":"PPL",
    "gn:name":"Ganxigou",
    "gn:population":0,
    "gn:timezone":"Asia/Shanghai",
    "iso:country":"CN",
    "name:zho_x_preferred":[
        "Ganxigou"
    ],
    "name:zho_x_variant":[
        "\u5e72\u6eaa\u6c9f"
    ],
    "wof:name":"Ganxigou",
    "wof:placetype":"locality"
},
  "geometry": {"coordinates":[111.34284,29.63716],"type":"Point"}
}