{
  "type": "Feature",
  "properties": {
    "gn:admin1_code":"26.0",
    "gn:asciiname":"Xinduncun",
    "gn:country_code":"CN",
    "gn:dem":1615,
    "gn:feature_class":"P",
    "gn:feature_code":"PPL",
    "gn:name":"Xinduncun",
    "gn:population":0,
    "gn:timezone":"Asia/Shanghai",
    "iso:country":"CN",
    "name:zho_x_preferred":[
        "\u65b0\u58a9\u6751"
    ],
    "wof:name":"Xinduncun",
    "wof:placetype":"locality"
},
  "geometry": {"coordinates":[107.58866,37.45675],"type":"Point"}
}