{
  "type": "Feature",
  "properties": {
    "gn:admin1_code":"16.0",
    "gn:asciiname":"Gongshi",
    "gn:country_code":"CN",
    "gn:dem":246,
    "gn:feature_class":"P",
    "gn:feature_code":"PPL",
    "gn:name":"Gongshi",
    "gn:population":0,
    "gn:timezone":"Asia/Shanghai",
    "iso:country":"CN",
    "name:epo_x_preferred":[
        "Gong\u015di"
    ],
    "name:nld_x_preferred":[
        "Gongshi"
    ],
    "name:spa_x_preferred":[
        "Gongshi"
    ],
    "name:zho_x_preferred":[
        "\u516c\u77f3"
    ],
    "wof:name":"Gongshi",
    "wof:placetype":"locality"
},
  "geometry": {"coordinates":[110.78100000000001,24.0663],"type":"Point"}
}