{
  "type": "Feature",
  "properties": {
    "gn:admin1_code":"29.0",
    "gn:asciiname":"Bangla",
    "gn:country_code":"CN",
    "gn:dem":1007,
    "gn:feature_class":"P",
    "gn:feature_code":"PPL",
    "gn:name":"Bangla",
    "gn:population":0,
    "gn:timezone":"Asia/Shanghai",
    "iso:country":"CN",
    "name:asm_x_preferred":[
        "\u09ac\u09be\u0982\u09b2\u09be"
    ],
    "name:ben_x_preferred":[
        "\u09ac\u09be\u0982\u09b2\u09be"
    ],
    "name:ceb_x_preferred":[
        "Bangla"
    ],
    "name:ita_x_preferred":[
        "Bangla"
    ],
    "name:swe_x_preferred":[
        "Bangla"
    ],
    "name:zho_x_preferred":[
        "\u90a6\u814a"
    ],
    "wof:name":"Bangla",
    "wof:placetype":"locality"
},
  "geometry": {"coordinates":[99.81619999999999,23.0945],"type":"Point"}
}