{
  "type": "Feature",
  "properties": {
    "gn:admin1_code":"18",
    "gn:asciiname":"Houbachang",
    "gn:country_code":"CN",
    "gn:dem":858,
    "gn:feature_class":"P",
    "gn:feature_code":"PPL",
    "gn:name":"Houbachang",
    "gn:population":0,
    "gn:timezone":"Asia/Shanghai",
    "iso:country":"CN",
    "name:zho_x_preferred":[
        "\u540e\u575d\u573a"
    ],
    "wof:name":"Houbachang",
    "wof:placetype":"locality"
},
  "geometry": {"coordinates":[106.883,27.3415],"type":"Point"}
}