{
  "type": "Feature",
  "properties": {
    "gn:admin1_code":"5.0",
    "gn:asciiname":"Xingfucun",
    "gn:country_code":"CN",
    "gn:dem":613,
    "gn:feature_class":"P",
    "gn:feature_code":"PPL",
    "gn:name":"Xingfucun",
    "gn:population":0,
    "gn:timezone":"Asia/Shanghai",
    "iso:country":"CN",
    "name:zho_x_preferred":[
        "\u5e78\u798f\u6751"
    ],
    "wof:name":"Xingfucun",
    "wof:placetype":"locality"
},
  "geometry": {"coordinates":[128.43861999999999,42.49965],"type":"Point"}
}