{
  "type": "Feature",
  "properties": {
    "gn:admin1_code":"1.0",
    "gn:asciiname":"Guozhuangcun",
    "gn:country_code":"CN",
    "gn:dem":26,
    "gn:feature_class":"P",
    "gn:feature_code":"PPL",
    "gn:name":"Guozhuangcun",
    "gn:population":0,
    "gn:timezone":"Asia/Shanghai",
    "iso:country":"CN",
    "name:und_x_variant":[
        "Guozhuang"
    ],
    "name:zho_x_preferred":[
        "\u90ed\u5e84\u6751"
    ],
    "wof:name":"Guozhuangcun",
    "wof:placetype":"locality"
},
  "geometry": {"coordinates":[117.65555999999999,33.85278],"type":"Point"}
}