{
  "type": "Feature",
  "properties": {
    "gn:admin1_code":"33.0",
    "gn:asciiname":"Jiaobang",
    "gn:country_code":"CN",
    "gn:dem":985,
    "gn:feature_class":"P",
    "gn:feature_code":"PPL",
    "gn:name":"Jiaobang",
    "gn:population":0,
    "gn:timezone":"Asia/Shanghai",
    "iso:country":"CN",
    "name:zho_x_preferred":[
        "\u89d2\u5e2e"
    ],
    "wof:name":"Jiaobang",
    "wof:placetype":"locality"
},
  "geometry": {"coordinates":[107.53972,29.46656],"type":"Point"}
}