{
  "type": "Feature",
  "properties": {
    "gn:admin1_code":"10",
    "gn:asciiname":"Caiputai",
    "gn:country_code":"CN",
    "gn:dem":13,
    "gn:feature_class":"P",
    "gn:feature_code":"PPL",
    "gn:name":"Caiputai",
    "gn:population":0,
    "gn:timezone":"Asia/Shanghai",
    "iso:country":"CN",
    "name:zho_x_preferred":[
        "\u91c7\u84b2\u53f0"
    ],
    "wof:name":"Caiputai",
    "wof:placetype":"locality"
},
  "geometry": {"coordinates":[116.014,38.8228],"type":"Point"}
}