{
  "type": "Feature",
  "properties": {
    "gn:admin1_code":"3.0",
    "gn:asciiname":"Yangtiankeng",
    "gn:country_code":"CN",
    "gn:dem":77,
    "gn:feature_class":"P",
    "gn:feature_code":"PPL",
    "gn:name":"Yangtiankeng",
    "gn:population":0,
    "gn:timezone":"Asia/Shanghai",
    "iso:country":"CN",
    "name:und_x_variant":[
        "\u79e7\u7530\u5751"
    ],
    "wof:name":"Yangtiankeng",
    "wof:placetype":"locality"
},
  "geometry": {"coordinates":[115.10726,27.79092],"type":"Point"}
}