{
  "type": "Feature",
  "properties": {
    "gn:admin1_code":"19",
    "gn:asciiname":"Changhanchi",
    "gn:country_code":"CN",
    "gn:dem":540,
    "gn:feature_class":"P",
    "gn:feature_code":"PPL",
    "gn:name":"Changhanchi",
    "gn:population":0,
    "gn:timezone":"Asia/Shanghai",
    "iso:country":"CN",
    "name:und_x_variant":[
        "Baishan Xiang"
    ],
    "name:zho_x_preferred":[
        "\u957f\u6c49\u6c60"
    ],
    "name:zho_x_variant":[
        "\u767d\u5c71\u4e61"
    ],
    "wof:name":"Changhanchi",
    "wof:placetype":"locality"
},
  "geometry": {"coordinates":[119.44110999999999,41.75667],"type":"Point"}
}