{
  "type": "Feature",
  "properties": {
    "gn:admin1_code":"15.0",
    "gn:asciiname":"Lujiagou",
    "gn:country_code":"CN",
    "gn:dem":1382,
    "gn:feature_class":"P",
    "gn:feature_code":"PPL",
    "gn:name":"L\u00fcjiagou",
    "gn:population":0,
    "gn:timezone":"Asia/Shanghai",
    "iso:country":"CN",
    "name:und_x_variant":[
        "L\u00fcjiagou",
        "\u5415\u5bb6\u6c9f"
    ],
    "wof:name":"Lujiagou",
    "wof:placetype":"locality"
},
  "geometry": {"coordinates":[107.70053,36.58491],"type":"Point"}
}