{
  "type": "Feature",
  "properties": {
    "gn:admin1_code":"26.0",
    "gn:asciiname":"Waliangshang",
    "gn:country_code":"CN",
    "gn:dem":1107,
    "gn:feature_class":"P",
    "gn:feature_code":"PPL",
    "gn:name":"Waliangshang",
    "gn:population":0,
    "gn:timezone":"Asia/Shanghai",
    "iso:country":"CN",
    "name:und_x_variant":[
        "\u74e6\u6881\u4e0a"
    ],
    "wof:name":"Waliangshang",
    "wof:placetype":"locality"
},
  "geometry": {"coordinates":[105.85082,32.90599],"type":"Point"}
}