{
  "type": "Feature",
  "properties": {
    "gn:admin1_code":"25.0",
    "gn:asciiname":"Yichengcun",
    "gn:country_code":"CN",
    "gn:dem":59,
    "gn:feature_class":"P",
    "gn:feature_code":"PPL",
    "gn:name":"Yichengcun",
    "gn:population":0,
    "gn:timezone":"Asia/Shanghai",
    "iso:country":"CN",
    "name:zho_x_preferred":[
        "\u8bae\u57ce\u6751"
    ],
    "wof:name":"Yichengcun",
    "wof:placetype":"locality"
},
  "geometry": {"coordinates":[121.82124,37.18099],"type":"Point"}
}