{
  "type": "Feature",
  "properties": {
    "gn:admin1_code":"15.0",
    "gn:asciiname":"Zhangqizhai",
    "gn:country_code":"CN",
    "gn:dem":993,
    "gn:feature_class":"P",
    "gn:feature_code":"PPL",
    "gn:name":"Zhangqizhai",
    "gn:population":0,
    "gn:timezone":"Asia/Shanghai",
    "iso:country":"CN",
    "name:und_x_variant":[
        "\u5f20\u65d7\u5be8"
    ],
    "wof:name":"Zhangqizhai",
    "wof:placetype":"locality"
},
  "geometry": {"coordinates":[105.73487,33.76597],"type":"Point"}
}