{
  "type": "Feature",
  "properties": {
    "gn:admin1_code":"12.0",
    "gn:asciiname":"Tangpuling",
    "gn:country_code":"CN",
    "gn:dem":61,
    "gn:feature_class":"P",
    "gn:feature_code":"PPL",
    "gn:name":"Tangpuling",
    "gn:population":0,
    "gn:timezone":"Asia/Shanghai",
    "iso:country":"CN",
    "name:und_x_variant":[
        "\u6c64\u94fa\u5cad"
    ],
    "wof:name":"Tangpuling",
    "wof:placetype":"locality"
},
  "geometry": {"coordinates":[114.96803,30.65654],"type":"Point"}
}