{
  "type": "Feature",
  "properties": {
    "gn:admin1_code":"03",
    "gn:asciiname":"Gaobu",
    "gn:cc2":"CN",
    "gn:country_code":"CN",
    "gn:dem":360,
    "gn:feature_class":"P",
    "gn:feature_code":"PPL",
    "gn:name":"Gaobu",
    "gn:population":0,
    "gn:timezone":"Asia/Shanghai",
    "iso:country":"CN",
    "name:und_x_variant":[
        "Kao-pu",
        "Gaobu"
    ],
    "wof:name":"Gaobu",
    "wof:placetype":"locality"
},
  "geometry": {"coordinates":[117.06667,27.75],"type":"Point"}
}