{
  "type": "Feature",
  "properties": {
    "gn:admin1_code":"2.0",
    "gn:asciiname":"Madian",
    "gn:country_code":"CN",
    "gn:dem":132,
    "gn:feature_class":"P",
    "gn:feature_code":"PPL",
    "gn:name":"Madian",
    "gn:population":0,
    "gn:timezone":"Asia/Shanghai",
    "iso:country":"CN",
    "name:ceb_x_preferred":[
        "Madian"
    ],
    "name:swe_x_preferred":[
        "Madian"
    ],
    "name:zho_x_preferred":[
        "\u9a6c\u5e97"
    ],
    "wof:name":"Madian",
    "wof:placetype":"locality"
},
  "geometry": {"coordinates":[120.29349999999999,29.5507],"type":"Point"}
}