{
  "type": "Feature",
  "properties": {
    "gn:admin1_code":"4.0",
    "gn:asciiname":"Dongpingcun",
    "gn:country_code":"CN",
    "gn:dem":2,
    "gn:feature_class":"P",
    "gn:feature_code":"PPL",
    "gn:name":"Dongpingcun",
    "gn:population":0,
    "gn:timezone":"Asia/Shanghai",
    "iso:country":"CN",
    "name:zho_x_preferred":[
        "\u4e1c\u5c4f\u6751"
    ],
    "wof:name":"Dongpingcun",
    "wof:placetype":"locality"
},
  "geometry": {"coordinates":[119.75629000000001,32.75372],"type":"Point"}
}