{
  "type": "Feature",
  "properties": {
    "gn:admin1_code":"5.0",
    "gn:asciiname":"Lirencun",
    "gn:country_code":"CN",
    "gn:dem":223,
    "gn:feature_class":"P",
    "gn:feature_code":"PPL",
    "gn:name":"Lirencun",
    "gn:population":0,
    "gn:timezone":"Asia/Shanghai",
    "iso:country":"CN",
    "name:zho_x_preferred":[
        "\u91cc\u4ec1\u6751"
    ],
    "wof:name":"Lirencun",
    "wof:placetype":"locality"
},
  "geometry": {"coordinates":[122.13196000000001,45.74688],"type":"Point"}
}