{
  "type": "Feature",
  "properties": {
    "gn:admin1_code":"24.0",
    "gn:asciiname":"Yuanbuzi",
    "gn:country_code":"CN",
    "gn:dem":1439,
    "gn:feature_class":"P",
    "gn:feature_code":"PPLA4",
    "gn:name":"Yuanbuzi",
    "gn:population":0,
    "gn:timezone":"Asia/Shanghai",
    "iso:country":"CN",
    "name:und_x_variant":[
        "Y\u00fcan-pao-tzu",
        "Yuanbuzi",
        "\u5143\u5821\u5b50",
        "Yuanbuzi Zhen",
        "\u5143\u5821\u5b50\u9547"
    ],
    "wof:name":"Yuanbuzi",
    "wof:placetype":"locality"
},
  "geometry": {"coordinates":[112.53434,39.8222],"type":"Point"}
}