{
  "type": "Feature",
  "properties": {
    "gn:admin1_code":"6.0",
    "gn:asciiname":"Maixue",
    "gn:country_code":"CN",
    "gn:dem":3698,
    "gn:feature_class":"P",
    "gn:feature_code":"PPL",
    "gn:name":"Maixue",
    "gn:population":0,
    "gn:timezone":"Asia/Urumqi",
    "iso:country":"CN",
    "name:zho_x_preferred":[
        "\u9ea6\u96ea"
    ],
    "wof:name":"Maixue",
    "wof:placetype":"locality"
},
  "geometry": {"coordinates":[96.97375,33.32852],"type":"Point"}
}