{
  "type": "Feature",
  "properties": {
    "gn:admin1_code":"4.0",
    "gn:asciiname":"Meiwangcun",
    "gn:country_code":"CN",
    "gn:dem":5,
    "gn:feature_class":"P",
    "gn:feature_code":"PPL",
    "gn:name":"Meiwangcun",
    "gn:population":0,
    "gn:timezone":"Asia/Shanghai",
    "iso:country":"CN",
    "name:zho_x_preferred":[
        "\u6885\u7f51\u6751"
    ],
    "wof:name":"Meiwangcun",
    "wof:placetype":"locality"
},
  "geometry": {"coordinates":[120.05226,32.43826],"type":"Point"}
}