{
  "type": "Feature",
  "properties": {
    "gn:admin1_code":"7.0",
    "gn:asciiname":"Yangchiwei",
    "gn:country_code":"CN",
    "gn:dem":337,
    "gn:feature_class":"P",
    "gn:feature_code":"PPL",
    "gn:name":"Yangchiwei",
    "gn:population":0,
    "gn:timezone":"Asia/Shanghai",
    "iso:country":"CN",
    "name:zho_x_preferred":[
        "\u79e7\u5c3a\u5c3e"
    ],
    "wof:name":"Yangchiwei",
    "wof:placetype":"locality"
},
  "geometry": {"coordinates":[118.65018000000001,26.0756],"type":"Point"}
}