{
  "type": "Feature",
  "properties": {
    "gn:admin1_code":"25.0",
    "gn:asciiname":"Pantao",
    "gn:country_code":"CN",
    "gn:dem":75,
    "gn:feature_class":"P",
    "gn:feature_code":"PPL",
    "gn:name":"Pantao",
    "gn:population":0,
    "gn:timezone":"Asia/Shanghai",
    "iso:country":"CN",
    "name:zho_x_preferred":[
        "\u87e0\u6843"
    ],
    "wof:name":"Pantao",
    "wof:placetype":"locality"
},
  "geometry": {"coordinates":[119.94566,36.83095],"type":"Point"}
}