{
  "type": "Feature",
  "properties": {
    "gn:admin1_code":"7.0",
    "gn:asciiname":"Wushiqiu",
    "gn:country_code":"CN",
    "gn:dem":564,
    "gn:feature_class":"P",
    "gn:feature_code":"PPL",
    "gn:name":"Wushiqiu",
    "gn:population":0,
    "gn:timezone":"Asia/Shanghai",
    "iso:country":"CN",
    "name:zho_x_preferred":[
        "\u4e4c\u77f3\u4e18"
    ],
    "wof:name":"Wushiqiu",
    "wof:placetype":"locality"
},
  "geometry": {"coordinates":[119.06209,26.88964],"type":"Point"}
}