{
  "type": "Feature",
  "properties": {
    "gn:admin1_code":"24.0",
    "gn:asciiname":"Danangou",
    "gn:country_code":"CN",
    "gn:dem":1550,
    "gn:feature_class":"P",
    "gn:feature_code":"PPL",
    "gn:name":"Danangou",
    "gn:population":0,
    "gn:timezone":"Asia/Shanghai",
    "iso:country":"CN",
    "name:zho_x_preferred":[
        "\u5927\u5357\u6c9f"
    ],
    "wof:name":"Danangou",
    "wof:placetype":"locality"
},
  "geometry": {"coordinates":[111.14106,37.01161],"type":"Point"}
}