{
  "type": "Feature",
  "properties": {
    "gn:admin1_code":"14.0",
    "gn:asciiname":"Gyazhong",
    "gn:country_code":"CN",
    "gn:dem":4467,
    "gn:feature_class":"P",
    "gn:feature_code":"PPLF",
    "gn:name":"Gyazhong",
    "gn:population":0,
    "gn:timezone":"Asia/Urumqi",
    "iso:country":"CN",
    "name:bod_x_preferred":[
        "Gyazhong"
    ],
    "name:zho_x_preferred":[
        "Jiazhong"
    ],
    "name:zho_x_variant":[
        "\u5939\u4e2d",
        "Zhaxixiong",
        "\u624e\u897f\u96c4"
    ],
    "wof:name":"Gyazhong",
    "wof:placetype":"locality"
},
  "geometry": {"coordinates":[89.602,28.802],"type":"Point"}
}