{
  "type": "Feature",
  "properties": {
    "gn:admin1_code":"13",
    "gn:asciiname":"Shanggou",
    "gn:country_code":"CN",
    "gn:dem":486,
    "gn:feature_class":"P",
    "gn:feature_code":"PPL",
    "gn:name":"Shanggou",
    "gn:population":0,
    "gn:timezone":"Asia/Urumqi",
    "iso:country":"CN",
    "name:zho_x_preferred":[
        "\u4e0a\u6c9f"
    ],
    "wof:name":"Shanggou",
    "wof:placetype":"locality"
},
  "geometry": {"coordinates":[87.44353000000002,44.18292],"type":"Point"}
}