{
  "type": "Feature",
  "properties": {
    "gn:admin1_code":"19.0",
    "gn:asciiname":"Liujia Caiyuan",
    "gn:country_code":"CN",
    "gn:dem":394,
    "gn:feature_class":"P",
    "gn:feature_code":"PPL",
    "gn:name":"Liujia Caiyuan",
    "gn:population":0,
    "gn:timezone":"Asia/Shanghai",
    "iso:country":"CN",
    "name:zho_x_preferred":[
        "\u5218\u5bb6\u83dc\u56ed"
    ],
    "wof:name":"Liujia Caiyuan",
    "wof:placetype":"locality"
},
  "geometry": {"coordinates":[120.39400000000001,41.908],"type":"Point"}
}