{
  "type": "Feature",
  "properties": {
    "gn:admin1_code":"11.0",
    "gn:asciiname":"Moshixi",
    "gn:country_code":"CN",
    "gn:dem":417,
    "gn:feature_class":"P",
    "gn:feature_code":"PPL",
    "gn:name":"Moshixi",
    "gn:population":0,
    "gn:timezone":"Asia/Shanghai",
    "iso:country":"CN",
    "name:zho_x_preferred":[
        "\u78e8\u77f3\u6eaa"
    ],
    "wof:name":"Moshixi",
    "wof:placetype":"locality"
},
  "geometry": {"coordinates":[110.32680999999999,27.45985],"type":"Point"}
}