{
  "type": "Feature",
  "properties": {
    "gn:admin1_code":"11.0",
    "gn:asciiname":"Yandengpo",
    "gn:country_code":"CN",
    "gn:dem":311,
    "gn:feature_class":"P",
    "gn:feature_code":"PPL",
    "gn:name":"Yandengpo",
    "gn:population":0,
    "gn:timezone":"Asia/Shanghai",
    "iso:country":"CN",
    "name:zho_x_preferred":[
        "\u70df\u706f\u5761"
    ],
    "wof:name":"Yandengpo",
    "wof:placetype":"locality"
},
  "geometry": {"coordinates":[109.71928,27.41043],"type":"Point"}
}