{
  "type": "Feature",
  "properties": {
    "gn:admin1_code":"19.0",
    "gn:asciiname":"Xiaokuanchanggou",
    "gn:country_code":"CN",
    "gn:dem":471,
    "gn:feature_class":"P",
    "gn:feature_code":"PPL",
    "gn:name":"Xiaokuanchanggou",
    "gn:population":0,
    "gn:timezone":"Asia/Shanghai",
    "iso:country":"CN",
    "name:zho_x_preferred":[
        "\u5c0f\u5bbd\u660c\u6c9f"
    ],
    "wof:name":"Xiaokuanchanggou",
    "wof:placetype":"locality"
},
  "geometry": {"coordinates":[119.724,41.5213],"type":"Point"}
}