{
  "type": "Feature",
  "properties": {
    "gn:admin1_code":"2.0",
    "gn:asciiname":"Zhangdaijie",
    "gn:country_code":"CN",
    "gn:dem":67,
    "gn:feature_class":"P",
    "gn:feature_code":"PPL",
    "gn:name":"Zhangdaijie",
    "gn:population":0,
    "gn:timezone":"Asia/Shanghai",
    "iso:country":"CN",
    "name:zho_x_preferred":[
        "\u6a1f\u6234\u8857"
    ],
    "wof:name":"Zhangdaijie",
    "wof:placetype":"locality"
},
  "geometry": {"coordinates":[118.95353,29.03836],"type":"Point"}
}