{
  "type": "Feature",
  "properties": {
    "gn:admin1_code":"5.0",
    "gn:asciiname":"Taipinggou",
    "gn:country_code":"CN",
    "gn:dem":763,
    "gn:feature_class":"P",
    "gn:feature_code":"PPL",
    "gn:name":"Taipinggou",
    "gn:population":0,
    "gn:timezone":"Asia/Shanghai",
    "iso:country":"CN",
    "name:und_x_variant":[
        "\u592a\u5e73\u6c9f"
    ],
    "wof:name":"Taipinggou",
    "wof:placetype":"locality"
},
  "geometry": {"coordinates":[128.38946999999999,42.51307],"type":"Point"}
}