{
  "type": "Feature",
  "properties": {
    "gn:admin1_code":"04",
    "gn:asciiname":"Dongduncun",
    "gn:country_code":"CN",
    "gn:dem":1,
    "gn:feature_class":"P",
    "gn:feature_code":"PPL",
    "gn:name":"Dongduncun",
    "gn:population":0,
    "gn:timezone":"Asia/Shanghai",
    "iso:country":"CN",
    "name:und_x_variant":[
        "Dongdun",
        "Dongduncun"
    ],
    "name:zho_x_preferred":[
        "\u4e1c\u58a9"
    ],
    "name:zho_x_variant":[
        "\u4e1c\u58a9\u6751"
    ],
    "wof:name":"Dongduncun",
    "wof:placetype":"locality"
},
  "geometry": {"coordinates":[119.44472,32.85145],"type":"Point"}
}