{
  "type": "Feature",
  "properties": {
    "gn:admin1_code":"4.0",
    "gn:asciiname":"Renfan",
    "gn:country_code":"CN",
    "gn:dem":-2,
    "gn:feature_class":"P",
    "gn:feature_code":"PPL",
    "gn:name":"Renfan",
    "gn:population":0,
    "gn:timezone":"Asia/Shanghai",
    "iso:country":"CN",
    "name:zho_x_preferred":[
        "Renfan"
    ],
    "name:zho_x_variant":[
        "\u4ec1\u8303"
    ],
    "wof:name":"Renfan",
    "wof:placetype":"locality"
},
  "geometry": {"coordinates":[119.93864000000001,33.74832],"type":"Point"}
}