{
  "type": "Feature",
  "properties": {
    "gn:admin1_code":"18.0",
    "gn:asciiname":"Majiang",
    "gn:country_code":"CN",
    "gn:dem":1004,
    "gn:feature_class":"P",
    "gn:feature_code":"PPL",
    "gn:name":"Majiang",
    "gn:population":0,
    "gn:timezone":"Asia/Shanghai",
    "iso:country":"CN",
    "name:ceb_x_preferred":[
        "Majiang"
    ],
    "name:deu_x_preferred":[
        "Majiang"
    ],
    "name:zho_x_preferred":[
        "\u9a6c\u964d"
    ],
    "wof:name":"Majiang",
    "wof:placetype":"locality"
},
  "geometry": {"coordinates":[107.548,25.6506],"type":"Point"}
}