{
  "type": "Feature",
  "properties": {
    "gn:admin1_code":"12.0",
    "gn:asciiname":"Longtai",
    "gn:country_code":"CN",
    "gn:dem":1062,
    "gn:feature_class":"P",
    "gn:feature_code":"PPL",
    "gn:name":"Longtai",
    "gn:population":0,
    "gn:timezone":"Asia/Shanghai",
    "iso:country":"CN",
    "name:zho_x_preferred":[
        "\u9f99\u53f0"
    ],
    "wof:name":"Longtai",
    "wof:placetype":"locality"
},
  "geometry": {"coordinates":[109.18340000000001,30.34793],"type":"Point"}
}