{
  "type": "Feature",
  "properties": {
    "gn:admin1_code":"9.0",
    "gn:asciiname":"Liangguanying",
    "gn:country_code":"CN",
    "gn:dem":100,
    "gn:feature_class":"P",
    "gn:feature_code":"PPL",
    "gn:name":"Liangguanying",
    "gn:population":0,
    "gn:timezone":"Asia/Shanghai",
    "iso:country":"CN",
    "name:und_x_variant":[
        "\u6881\u5b98\u8425"
    ],
    "name:zho_x_preferred":[
        "\u6881\u5b98\u8425"
    ],
    "wof:name":"Liangguanying",
    "wof:placetype":"locality"
},
  "geometry": {"coordinates":[113.20238999999999,33.66287],"type":"Point"}
}