{
  "type": "Feature",
  "properties": {
    "gn:admin1_code":"29.0",
    "gn:asciiname":"Dawenzhuang",
    "gn:country_code":"CN",
    "gn:dem":1526,
    "gn:feature_class":"P",
    "gn:feature_code":"PPL",
    "gn:name":"Dawenzhuang",
    "gn:population":0,
    "gn:timezone":"Asia/Shanghai",
    "iso:country":"CN",
    "name:zho_x_preferred":[
        "\u5927\u6587\u5e84"
    ],
    "wof:name":"Dawenzhuang",
    "wof:placetype":"locality"
},
  "geometry": {"coordinates":[101.09,24.2398],"type":"Point"}
}