{
  "type": "Feature",
  "properties": {
    "gn:admin1_code":"15.0",
    "gn:asciiname":"Longjiaba",
    "gn:country_code":"CN",
    "gn:dem":1063,
    "gn:feature_class":"P",
    "gn:feature_code":"PPL",
    "gn:name":"Longjiaba",
    "gn:population":0,
    "gn:timezone":"Asia/Shanghai",
    "iso:country":"CN",
    "name:und_x_variant":[
        "\u9f99\u5bb6\u575d"
    ],
    "wof:name":"Longjiaba",
    "wof:placetype":"locality"
},
  "geometry": {"coordinates":[105.38722,33.53325],"type":"Point"}
}