{
  "type": "Feature",
  "properties": {
    "gn:admin1_code":"24.0",
    "gn:asciiname":"Shiweigoucun",
    "gn:country_code":"CN",
    "gn:dem":1011,
    "gn:feature_class":"P",
    "gn:feature_code":"PPL",
    "gn:name":"Shiweigoucun",
    "gn:population":0,
    "gn:timezone":"Asia/Shanghai",
    "iso:country":"CN",
    "name:zho_x_preferred":[
        "\u72ee\u5c3e\u6c9f\u6751"
    ],
    "wof:name":"Shiweigoucun",
    "wof:placetype":"locality"
},
  "geometry": {"coordinates":[110.98933999999998,37.35206],"type":"Point"}
}