{
  "type": "Feature",
  "properties": {
    "gn:admin1_code":"4.0",
    "gn:asciiname":"Zhouqiao",
    "gn:country_code":"CN",
    "gn:dem":16,
    "gn:feature_class":"P",
    "gn:feature_code":"PPL",
    "gn:name":"Zhouqiao",
    "gn:population":0,
    "gn:timezone":"Asia/Shanghai",
    "iso:country":"CN",
    "name:zho_x_preferred":[
        "\u5468\u6865"
    ],
    "wof:name":"Zhouqiao",
    "wof:placetype":"locality"
},
  "geometry": {"coordinates":[118.18600000000001,33.381],"type":"Point"}
}