{
  "type": "Feature",
  "properties": {
    "gn:admin1_code":"32.0",
    "gn:asciiname":"Eside",
    "gn:country_code":"CN",
    "gn:dem":3345,
    "gn:feature_class":"P",
    "gn:feature_code":"PPL",
    "gn:name":"Eside",
    "gn:population":0,
    "gn:timezone":"Asia/Shanghai",
    "iso:country":"CN",
    "name:zho_x_preferred":[
        "\u989d\u65af\u5f97"
    ],
    "wof:name":"Eside",
    "wof:placetype":"locality"
},
  "geometry": {"coordinates":[101.97747,31.16656],"type":"Point"}
}