{
  "type": "Feature",
  "properties": {
    "gn:admin1_code":"20.0",
    "gn:asciiname":"Huashanzi",
    "gn:country_code":"CN",
    "gn:dem":1587,
    "gn:feature_class":"P",
    "gn:feature_code":"PPLA4",
    "gn:name":"Huashanzi",
    "gn:population":0,
    "gn:timezone":"Asia/Shanghai",
    "iso:country":"CN",
    "name:und_x_variant":[
        "\u82b1\u5c71\u5b50",
        "Xihezi",
        "\u897f\u6cb3\u5b50"
    ],
    "wof:name":"Huashanzi",
    "wof:placetype":"locality"
},
  "geometry": {"coordinates":[112.27221000000002,41.62665],"type":"Point"}
}