{
  "type": "Feature",
  "properties": {
    "gn:admin1_code":"16.0",
    "gn:asciiname":"Shangjinzhang",
    "gn:country_code":"CN",
    "gn:dem":239,
    "gn:feature_class":"P",
    "gn:feature_code":"PPL",
    "gn:name":"Shangjinzhang",
    "gn:population":0,
    "gn:timezone":"Asia/Shanghai",
    "iso:country":"CN",
    "name:zho_x_preferred":[
        "\u4e0a\u91d1\u7ae0"
    ],
    "wof:name":"Shangjinzhang",
    "wof:placetype":"locality"
},
  "geometry": {"coordinates":[109.01900000000001,23.7895],"type":"Point"}
}