{
  "type": "Feature",
  "properties": {
    "gn:admin1_code":"32.0",
    "gn:asciiname":"Maheba",
    "gn:country_code":"CN",
    "gn:dem":440,
    "gn:feature_class":"P",
    "gn:feature_code":"PPL",
    "gn:name":"Maheba",
    "gn:population":0,
    "gn:timezone":"Asia/Shanghai",
    "iso:country":"CN",
    "name:zho_x_preferred":[
        "\u9a6c\u6cb3\u575d"
    ],
    "wof:name":"Maheba",
    "wof:placetype":"locality"
},
  "geometry": {"coordinates":[103.714,30.1347],"type":"Point"}
}