{
  "type": "Feature",
  "properties": {
    "gn:admin1_code":"5.0",
    "gn:asciiname":"Gaojia Youfang",
    "gn:country_code":"CN",
    "gn:dem":179,
    "gn:feature_class":"P",
    "gn:feature_code":"PPL",
    "gn:name":"Gaojia Youfang",
    "gn:population":0,
    "gn:timezone":"Asia/Shanghai",
    "iso:country":"CN",
    "name:zho_x_preferred":[
        "\u9ad8\u5bb6\u6cb9\u574a"
    ],
    "wof:name":"Gaojia Youfang",
    "wof:placetype":"locality"
},
  "geometry": {"coordinates":[123.75861999999999,44.11523],"type":"Point"}
}