{
  "type": "Feature",
  "properties": {
    "gn:admin1_code":"29",
    "gn:asciiname":"Haiyi",
    "gn:country_code":"CN",
    "gn:dem":1579,
    "gn:feature_class":"P",
    "gn:feature_code":"PPL",
    "gn:name":"Haiyi",
    "gn:population":0,
    "gn:timezone":"Asia/Shanghai",
    "iso:country":"CN",
    "name:zho_x_preferred":[
        "\u6d77\u8fe4"
    ],
    "wof:name":"Haiyi",
    "wof:placetype":"locality"
},
  "geometry": {"coordinates":[103.023,24.4888],"type":"Point"}
}