{
  "type": "Feature",
  "properties": {
    "gn:admin1_code":"4.0",
    "gn:asciiname":"Jiangjia Yuanzi",
    "gn:country_code":"CN",
    "gn:dem":4,
    "gn:feature_class":"P",
    "gn:feature_code":"PPL",
    "gn:name":"Jiangjia Yuanzi",
    "gn:population":0,
    "gn:timezone":"Asia/Shanghai",
    "iso:country":"CN",
    "name:und_x_variant":[
        "\u848b\u5bb6\u56ed\u5b50"
    ],
    "wof:name":"Jiangjia Yuanzi",
    "wof:placetype":"locality"
},
  "geometry": {"coordinates":[119.93349000000001,32.13208],"type":"Point"}
}