{
  "type": "Feature",
  "properties": {
    "gn:admin1_code":"24",
    "gn:asciiname":"Beiban",
    "gn:country_code":"CN",
    "gn:dem":964,
    "gn:feature_class":"P",
    "gn:feature_code":"PPL",
    "gn:name":"Beiban",
    "gn:population":0,
    "gn:timezone":"Asia/Shanghai",
    "iso:country":"CN",
    "wof:name":"Beiban",
    "wof:placetype":"locality"
},
  "geometry": {"coordinates":[111.82832999999999,35.59028],"type":"Point"}
}