{
  "type": "Feature",
  "properties": {
    "gn:admin1_code":"25",
    "gn:asciiname":"Nanshagou",
    "gn:country_code":"CN",
    "gn:dem":56,
    "gn:feature_class":"P",
    "gn:feature_code":"PPL",
    "gn:name":"Nanshagou",
    "gn:population":0,
    "gn:timezone":"Asia/Shanghai",
    "iso:country":"CN",
    "name:zho_x_preferred":[
        "\u5357\u6c99\u6c9f"
    ],
    "wof:name":"Nanshagou",
    "wof:placetype":"locality"
},
  "geometry": {"coordinates":[120.489,37.5868],"type":"Point"}
}