{
  "type": "Feature",
  "properties": {
    "gn:admin1_code":"9.0",
    "gn:asciiname":"Lilou",
    "gn:country_code":"CN",
    "gn:dem":190,
    "gn:feature_class":"P",
    "gn:feature_code":"PPL",
    "gn:name":"Lilou",
    "gn:population":0,
    "gn:timezone":"Asia/Shanghai",
    "iso:country":"CN",
    "name:und_x_variant":[
        "\u674e\u697c",
        "Lilou"
    ],
    "wof:name":"Lilou",
    "wof:placetype":"locality"
},
  "geometry": {"coordinates":[112.98757999999999,33.3541],"type":"Point"}
}