{
  "type": "Feature",
  "properties": {
    "gn:admin1_code":"4.0",
    "gn:asciiname":"Beisongzhuang",
    "gn:country_code":"CN",
    "gn:dem":4,
    "gn:feature_class":"P",
    "gn:feature_code":"PPL",
    "gn:name":"Beisongzhuang",
    "gn:population":0,
    "gn:timezone":"Asia/Shanghai",
    "iso:country":"CN",
    "name:zho_x_preferred":[
        "\u5317\u5b8b\u5e84"
    ],
    "wof:name":"Beisongzhuang",
    "wof:placetype":"locality"
},
  "geometry": {"coordinates":[119.76257,32.89832],"type":"Point"}
}