{
  "type": "Feature",
  "properties": {
    "gn:admin1_code":"21.0",
    "gn:asciiname":"Wangjiaquan",
    "gn:country_code":"CN",
    "gn:dem":1429,
    "gn:feature_class":"P",
    "gn:feature_code":"PPL",
    "gn:name":"Wangjiaquan",
    "gn:population":0,
    "gn:timezone":"Asia/Shanghai",
    "iso:country":"CN",
    "name:zho_x_preferred":[
        "\u738b\u5bb6\u5708"
    ],
    "wof:name":"Wangjiaquan",
    "wof:placetype":"locality"
},
  "geometry": {"coordinates":[107.04000000000001,37.9354],"type":"Point"}
}