{
  "type": "Feature",
  "properties": {
    "gn:admin1_code":"7.0",
    "gn:asciiname":"Donghai",
    "gn:country_code":"CN",
    "gn:dem":16,
    "gn:feature_class":"P",
    "gn:feature_code":"PPLA4",
    "gn:name":"Donghai",
    "gn:population":0,
    "gn:timezone":"Asia/Shanghai",
    "iso:country":"CN",
    "name:und_x_variant":[
        "Donghai Zhen"
    ],
    "name:zho_x_preferred":[
        "\u4e1c\u6d77"
    ],
    "name:zho_x_variant":[
        "\u4e1c\u6d77\u9547"
    ],
    "wof:name":"Donghai",
    "wof:placetype":"locality"
},
  "geometry": {"coordinates":[118.91745,25.27566],"type":"Point"}
}