{
  "type": "Feature",
  "properties": {
    "gn:admin1_code":"19.0",
    "gn:asciiname":"Wukun Zhangzicun",
    "gn:country_code":"CN",
    "gn:dem":547,
    "gn:feature_class":"P",
    "gn:feature_code":"PPL",
    "gn:name":"Wukun Zhangzicun",
    "gn:population":0,
    "gn:timezone":"Asia/Shanghai",
    "iso:country":"CN",
    "name:und_x_variant":[
        "Wukunzhangzicun",
        "Wukun Zhangzicun"
    ],
    "name:zho_x_preferred":[
        "\u5434\u5764\u6756\u5b50\u6751"
    ],
    "wof:name":"Wukun Zhangzicun",
    "wof:placetype":"locality"
},
  "geometry": {"coordinates":[119.42758000000001,40.56637],"type":"Point"}
}