{
  "type": "Feature",
  "properties": {
    "gn:admin1_code":"05",
    "gn:asciiname":"Bajilei",
    "gn:cc2":"CN",
    "gn:country_code":"CN",
    "gn:dem":193,
    "gn:feature_class":"P",
    "gn:feature_code":"PPL",
    "gn:name":"Bajilei",
    "gn:population":0,
    "gn:timezone":"Asia/Shanghai",
    "iso:country":"CN",
    "name:und_x_variant":[
        "Hsiang-yang-pao",
        "Batszyaley",
        "Hsiang-yang-p\u2019u",
        "Pa-lei-chieh",
        "Hsiang-y\u00fc-pao",
        "Pa-chia-lei",
        "Pa-chia-lei-chieh",
        "Pa-chi-lei",
        "Pa-chia-lei-kai",
        "Pa-chia-lie-chieh",
        "Bajilei"
    ],
    "wof:name":"Bajilei",
    "wof:placetype":"locality"
},
  "geometry": {"coordinates":[124.81667,44.33333],"type":"Point"}
}