{
  "type": "Feature",
  "properties": {
    "gn:admin1_code":"9",
    "gn:asciiname":"Tandian",
    "gn:country_code":"CN",
    "gn:dem":68,
    "gn:feature_class":"P",
    "gn:feature_code":"PPLA4",
    "gn:name":"Tandian",
    "gn:population":0,
    "gn:timezone":"Asia/Shanghai",
    "iso:country":"CN",
    "name:und_x_variant":[
        "\u8c2d\u5e97",
        "Tandian Xiang",
        "\u8c2d\u5e97\u4e61"
    ],
    "wof:name":"Tandian",
    "wof:placetype":"locality"
},
  "geometry": {"coordinates":[113.92565,33.3759],"type":"Point"}
}