{
  "type": "Feature",
  "properties": {
    "gn:admin1_code":"4.0",
    "gn:asciiname":"Zhuji",
    "gn:country_code":"CN",
    "gn:dem":5,
    "gn:feature_class":"P",
    "gn:feature_code":"PPL",
    "gn:name":"Zhuji",
    "gn:population":0,
    "gn:timezone":"Asia/Shanghai",
    "iso:country":"CN",
    "name:cat_x_preferred":[
        "Zhuji"
    ],
    "name:ceb_x_preferred":[
        "Zhuji"
    ],
    "name:deu_x_preferred":[
        "Zhuji"
    ],
    "name:fra_x_preferred":[
        "Zhuji"
    ],
    "name:gle_x_preferred":[
        "Zhuji"
    ],
    "name:hak_x_preferred":[
        "Ch\u00fb-ki-s\u1e73"
    ],
    "name:ita_x_preferred":[
        "Zhuji"
    ],
    "name:jpn_x_preferred":[
        "\u8af8\u66c1\u5e02"
    ],
    "name:kik_x_preferred":[
        "Zhuji"
    ],
    "name:kor_x_preferred":[
        "\uc8fc\uc9c0\uc2dc"
    ],
    "name:mlg_x_preferred":[
        "Zhuji"
    ],
    "name:nor_x_preferred":[
        "Zhuji"
    ],
    "name:pol_x_preferred":[
        "Zhuji"
    ],
    "name:sco_x_preferred":[
        "Zhuji"
    ],
    "name:swe_x_preferred":[
        "Zhuji"
    ],
    "name:tgl_x_preferred":[
        "Zhuji"
    ],
    "name:urd_x_preferred":[
        "\u0698\u0648\u062c\u06cc"
    ],
    "name:vie_x_preferred":[
        "Ch\u01b0 K\u1ef5"
    ],
    "name:war_x_preferred":[
        "Zhuji"
    ],
    "name:wuu_x_preferred":[
        "\u8bf8\u66a8\u5e02"
    ],
    "name:zho_x_preferred":[
        "\u4f4f\u57fa"
    ],
    "name:zho_x_variant":[
        "\u8bf8\u66a8\u5e02"
    ],
    "wof:name":"Zhuji",
    "wof:placetype":"locality"
},
  "geometry": {"coordinates":[119.7715,31.7074],"type":"Point"}
}