{
  "type": "Feature",
  "properties": {
    "gn:admin1_code":"30",
    "gn:asciiname":"Dazhaiwei",
    "gn:country_code":"CN",
    "gn:dem":531,
    "gn:feature_class":"P",
    "gn:feature_code":"PPL",
    "gn:name":"Dazhaiwei",
    "gn:population":0,
    "gn:timezone":"Asia/Shanghai",
    "iso:country":"CN",
    "name:zho_x_preferred":[
        "\u5927\u5be8\u56f4"
    ],
    "wof:name":"Dazhaiwei",
    "wof:placetype":"locality"
},
  "geometry": {"coordinates":[116.67606000000001,23.84631],"type":"Point"}
}