{
  "type": "Feature",
  "properties": {
    "gn:admin1_code":"16",
    "gn:asciiname":"Shuanglong",
    "gn:country_code":"CN",
    "gn:dem":127,
    "gn:feature_class":"P",
    "gn:feature_code":"PPL",
    "gn:name":"Shuanglong",
    "gn:population":0,
    "gn:timezone":"Asia/Shanghai",
    "iso:country":"CN",
    "name:ceb_x_preferred":[
        "Shuanglong"
    ],
    "name:deu_x_preferred":[
        "Shuanglong"
    ],
    "name:swe_x_preferred":[
        "Shuanglong"
    ],
    "name:zho_x_preferred":[
        "\u53cc\u9f99"
    ],
    "wof:name":"Shuanglong",
    "wof:placetype":"locality"
},
  "geometry": {"coordinates":[107.149,22.0986],"type":"Point"}
}