{
  "type": "Feature",
  "properties": {
    "gn:admin1_code":"33.0",
    "gn:asciiname":"Tiecun",
    "gn:country_code":"CN",
    "gn:dem":710,
    "gn:feature_class":"P",
    "gn:feature_code":"PPLA4",
    "gn:name":"Tiecun",
    "gn:population":0,
    "gn:timezone":"Asia/Shanghai",
    "iso:country":"CN",
    "name:und_x_variant":[
        "Tiecun Xiang"
    ],
    "name:zho_x_preferred":[
        "\u94c1\u6751"
    ],
    "name:zho_x_variant":[
        "\u94c1\u6751\u4e61"
    ],
    "wof:name":"Tiecun",
    "wof:placetype":"locality"
},
  "geometry": {"coordinates":[107.18342,29.23785],"type":"Point"}
}