{
  "type": "Feature",
  "properties": {
    "gn:admin1_code":"4.0",
    "gn:asciiname":"Yuejin Nongyedui",
    "gn:country_code":"CN",
    "gn:dem":2,
    "gn:feature_class":"P",
    "gn:feature_code":"PPLF",
    "gn:name":"Yuejin Nongyedui",
    "gn:population":0,
    "gn:timezone":"Asia/Shanghai",
    "iso:country":"CN",
    "name:zho_x_preferred":[
        "\u8dc3\u8fdb\u519c\u4e1a\u961f"
    ],
    "wof:name":"Yuejin Nongyedui",
    "wof:placetype":"locality"
},
  "geometry": {"coordinates":[120.46299999999999,33.6317],"type":"Point"}
}