{
  "type": "Feature",
  "properties": {
    "gn:admin1_code":"11.0",
    "gn:asciiname":"Yanwan",
    "gn:country_code":"CN",
    "gn:dem":117,
    "gn:feature_class":"P",
    "gn:feature_code":"PPL",
    "gn:name":"Yanwan",
    "gn:population":0,
    "gn:timezone":"Asia/Shanghai",
    "iso:country":"CN",
    "name:zho_x_preferred":[
        "Yanwan"
    ],
    "name:zho_x_variant":[
        "\u5ca9\u5f2f"
    ],
    "wof:name":"Yanwan",
    "wof:placetype":"locality"
},
  "geometry": {"coordinates":[111.26379,29.63583],"type":"Point"}
}