{
  "type": "Feature",
  "properties": {
    "gn:admin1_code":"29.0",
    "gn:asciiname":"Houshaba",
    "gn:country_code":"CN",
    "gn:dem":1848,
    "gn:feature_class":"P",
    "gn:feature_code":"PPL",
    "gn:name":"Houshaba",
    "gn:population":0,
    "gn:timezone":"Asia/Shanghai",
    "iso:country":"CN",
    "name:zho_x_preferred":[
        "\u540e\u6c99\u575d"
    ],
    "wof:name":"Houshaba",
    "wof:placetype":"locality"
},
  "geometry": {"coordinates":[104.23099999999999,27.7781],"type":"Point"}
}