{
  "type": "Feature",
  "properties": {
    "gn:admin1_code":"14.0",
    "gn:asciiname":"Junmachang",
    "gn:country_code":"CN",
    "gn:dem":4308,
    "gn:feature_class":"P",
    "gn:feature_code":"PPL",
    "gn:name":"Junmachang",
    "gn:population":0,
    "gn:timezone":"Asia/Urumqi",
    "iso:country":"CN",
    "name:zho_x_preferred":[
        "\u519b\u9a6c\u573a"
    ],
    "wof:name":"Junmachang",
    "wof:placetype":"locality"
},
  "geometry": {"coordinates":[90.45192,30.04997],"type":"Point"}
}