{
  "type": "Feature",
  "properties": {
    "gn:admin1_code":"14.0",
    "gn:asciiname":"Laimeng Niuchang",
    "gn:country_code":"CN",
    "gn:dem":4464,
    "gn:feature_class":"P",
    "gn:feature_code":"PPLF",
    "gn:name":"Laimeng Niuchang",
    "gn:population":0,
    "gn:timezone":"Asia/Urumqi",
    "iso:country":"CN",
    "name:zho_x_preferred":[
        "\u6765\u8499\u725b\u573a"
    ],
    "wof:name":"Laimeng Niuchang",
    "wof:placetype":"locality"
},
  "geometry": {"coordinates":[93.8274,29.31301],"type":"Point"}
}