{
  "type": "Feature",
  "properties": {
    "gn:admin1_code":"26.0",
    "gn:asciiname":"Daguanpo",
    "gn:country_code":"CN",
    "gn:dem":1350,
    "gn:feature_class":"P",
    "gn:feature_code":"PPL",
    "gn:name":"Daguanpo",
    "gn:population":0,
    "gn:timezone":"Asia/Shanghai",
    "iso:country":"CN",
    "name:zho_x_preferred":[
        "\u5927\u5b98\u5761"
    ],
    "wof:name":"Daguanpo",
    "wof:placetype":"locality"
},
  "geometry": {"coordinates":[110.13151999999999,35.72705],"type":"Point"}
}