{
  "type": "Feature",
  "properties": {
    "gn:admin1_code":"12.0",
    "gn:asciiname":"Liuwan",
    "gn:country_code":"CN",
    "gn:dem":178,
    "gn:feature_class":"P",
    "gn:feature_code":"PPL",
    "gn:name":"Liuwan",
    "gn:population":0,
    "gn:timezone":"Asia/Shanghai",
    "iso:country":"CN",
    "name:zho_x_preferred":[
        "\u5218\u6e7e"
    ],
    "wof:name":"Liuwan",
    "wof:placetype":"locality"
},
  "geometry": {"coordinates":[111.71774000000001,32.55929],"type":"Point"}
}