{
  "type": "Feature",
  "properties": {
    "gn:admin1_code":"14.0",
    "gn:asciiname":"Chongsar",
    "gn:country_code":"CN",
    "gn:dem":4490,
    "gn:feature_class":"P",
    "gn:feature_code":"PPL",
    "gn:name":"Chongsar",
    "gn:population":0,
    "gn:timezone":"Asia/Urumqi",
    "iso:country":"CN",
    "name:bod_x_preferred":[
        "Chongsar"
    ],
    "name:msa_x_preferred":[
        "Chongsar"
    ],
    "name:zho_x_preferred":[
        "Zhongsha"
    ],
    "name:zho_x_variant":[
        "\u4e2d\u6c99"
    ],
    "wof:name":"Chongsar",
    "wof:placetype":"locality"
},
  "geometry": {"coordinates":[92.104,28.804],"type":"Point"}
}