{
  "type": "Feature",
  "properties": {
    "gn:admin1_code":"25.0",
    "gn:asciiname":"Xingjia",
    "gn:country_code":"CN",
    "gn:dem":74,
    "gn:feature_class":"P",
    "gn:feature_code":"PPL",
    "gn:name":"Xingjia",
    "gn:population":0,
    "gn:timezone":"Asia/Shanghai",
    "iso:country":"CN",
    "name:zho_x_preferred":[
        "\u5211\u5bb6"
    ],
    "wof:name":"Xingjia",
    "wof:placetype":"locality"
},
  "geometry": {"coordinates":[121.70026,37.10915],"type":"Point"}
}