{
  "type": "Feature",
  "properties": {
    "gn:admin1_code":"30.0",
    "gn:asciiname":"Liusheng",
    "gn:country_code":"CN",
    "gn:dem":213,
    "gn:feature_class":"P",
    "gn:feature_code":"PPL",
    "gn:name":"Liusheng",
    "gn:population":0,
    "gn:timezone":"Asia/Urumqi",
    "iso:country":"CN",
    "name:zho_x_preferred":[
        "\u516d\u80dc"
    ],
    "wof:name":"Liusheng",
    "wof:placetype":"locality"
},
  "geometry": {"coordinates":[110.77251,22.47158],"type":"Point"}
}