{
  "type": "Feature",
  "properties": {
    "gn:admin1_code":"32.0",
    "gn:asciiname":"Yuzhongzhan",
    "gn:country_code":"CN",
    "gn:dem":313,
    "gn:feature_class":"P",
    "gn:feature_code":"PPL",
    "gn:name":"Yuzhongzhan",
    "gn:population":0,
    "gn:timezone":"Asia/Shanghai",
    "iso:country":"CN",
    "name:zho_x_preferred":[
        "\u9c7c\u79cd\u7ad9"
    ],
    "wof:name":"Yuzhongzhan",
    "wof:placetype":"locality"
},
  "geometry": {"coordinates":[105.313,30.0732],"type":"Point"}
}