{
  "type": "Feature",
  "properties": {
    "gn:admin1_code":"10",
    "gn:asciiname":"Sankeshu",
    "gn:country_code":"CN",
    "gn:dem":1473,
    "gn:feature_class":"P",
    "gn:feature_code":"PPL",
    "gn:name":"Sankeshu",
    "gn:population":0,
    "gn:timezone":"Asia/Shanghai",
    "iso:country":"CN",
    "wof:name":"Sankeshu",
    "wof:placetype":"locality"
},
  "geometry": {"coordinates":[115.67528,41.33861],"type":"Point"}
}