{
  "type": "Feature",
  "properties": {
    "gn:admin1_code":"24.0",
    "gn:asciiname":"Anyandun",
    "gn:country_code":"CN",
    "gn:dem":1393,
    "gn:feature_class":"P",
    "gn:feature_code":"PPL",
    "gn:name":"Anyandun",
    "gn:population":0,
    "gn:timezone":"Asia/Shanghai",
    "iso:country":"CN",
    "name:und_x_variant":[
        "\u5b89\u70df\u58a9"
    ],
    "name:zho_x_preferred":[
        "\u5b89\u70df\u58a9"
    ],
    "wof:name":"Anyandun",
    "wof:placetype":"locality"
},
  "geometry": {"coordinates":[112.72964,40.1367],"type":"Point"}
}