{
  "type": "Feature",
  "properties": {
    "gn:admin1_code":"15.0",
    "gn:asciiname":"Gulaoba",
    "gn:country_code":"CN",
    "gn:dem":1778,
    "gn:feature_class":"P",
    "gn:feature_code":"PPL",
    "gn:name":"Gulaoba",
    "gn:population":0,
    "gn:timezone":"Asia/Shanghai",
    "iso:country":"CN",
    "name:zho_x_preferred":[
        "\u53e4\u6d9d\u575d"
    ],
    "wof:name":"Gulaoba",
    "wof:placetype":"locality"
},
  "geometry": {"coordinates":[105.113,36.9099],"type":"Point"}
}