{
  "type": "Feature",
  "properties": {
    "gn:admin1_code":"19.0",
    "gn:asciiname":"Matigoucun",
    "gn:country_code":"CN",
    "gn:dem":39,
    "gn:feature_class":"P",
    "gn:feature_code":"PPL",
    "gn:name":"Matigoucun",
    "gn:population":0,
    "gn:timezone":"Asia/Shanghai",
    "iso:country":"CN",
    "name:zho_x_preferred":[
        "\u9a6c\u8e44\u6c9f\u6751"
    ],
    "wof:name":"Matigoucun",
    "wof:placetype":"locality"
},
  "geometry": {"coordinates":[120.13988000000001,40.27184000000001],"type":"Point"}
}