{
  "type": "Feature",
  "properties": {
    "gn:admin1_code":"32",
    "gn:asciiname":"Zhangjiatan",
    "gn:country_code":"CN",
    "gn:dem":267,
    "gn:feature_class":"P",
    "gn:feature_code":"PPL",
    "gn:name":"Zhangjiatan",
    "gn:population":0,
    "gn:timezone":"Asia/Shanghai",
    "iso:country":"CN",
    "name:zho_x_preferred":[
        "\u5f20\u5bb6\u6ee9"
    ],
    "wof:name":"Zhangjiatan",
    "wof:placetype":"locality"
},
  "geometry": {"coordinates":[106.17894,30.45533],"type":"Point"}
}