{
  "type": "Feature",
  "properties": {
    "gn:admin1_code":"26.0",
    "gn:asciiname":"Nianmaocun",
    "gn:country_code":"CN",
    "gn:dem":1076,
    "gn:feature_class":"P",
    "gn:feature_code":"PPL",
    "gn:name":"Nianmaocun",
    "gn:population":0,
    "gn:timezone":"Asia/Shanghai",
    "iso:country":"CN",
    "name:zho_x_preferred":[
        "\u78be\u5cc1\u6751"
    ],
    "wof:name":"Nianmaocun",
    "wof:placetype":"locality"
},
  "geometry": {"coordinates":[110.54403000000001,38.44816],"type":"Point"}
}