{
  "type": "Feature",
  "properties": {
    "gn:admin1_code":"31.0",
    "gn:asciiname":"Mazhai",
    "gn:country_code":"CN",
    "gn:dem":62,
    "gn:feature_class":"P",
    "gn:feature_code":"PPL",
    "gn:name":"Mazhai",
    "gn:population":0,
    "gn:timezone":"Asia/Shanghai",
    "iso:country":"CN",
    "name:zho_x_preferred":[
        "\u9a6c\u5be8"
    ],
    "wof:name":"Mazhai",
    "wof:placetype":"locality"
},
  "geometry": {"coordinates":[110.44316000000001,19.38754],"type":"Point"}
}