{
  "type": "Feature",
  "properties": {
    "gn:admin1_code":"8.0",
    "gn:asciiname":"Lifengge",
    "gn:country_code":"CN",
    "gn:dem":174,
    "gn:feature_class":"P",
    "gn:feature_code":"PPL",
    "gn:name":"Lifengge",
    "gn:population":0,
    "gn:timezone":"Asia/Shanghai",
    "iso:country":"CN",
    "name:zho_x_preferred":[
        "\u674e\u98ce\u9601"
    ],
    "wof:name":"Lifengge",
    "wof:placetype":"locality"
},
  "geometry": {"coordinates":[127.52091,46.42205],"type":"Point"}
}