{
  "type": "Feature",
  "properties": {
    "gn:admin1_code":"26.0",
    "gn:asciiname":"Sangshuwan",
    "gn:country_code":"CN",
    "gn:dem":1553,
    "gn:feature_class":"P",
    "gn:feature_code":"PPL",
    "gn:name":"Sangshuwan",
    "gn:population":0,
    "gn:timezone":"Asia/Shanghai",
    "iso:country":"CN",
    "name:zho_x_preferred":[
        "\u6851\u6811\u6e7e"
    ],
    "wof:name":"Sangshuwan",
    "wof:placetype":"locality"
},
  "geometry": {"coordinates":[108.13406000000001,36.61873],"type":"Point"}
}