{
  "type": "Feature",
  "properties": {
    "gn:admin1_code":"18",
    "gn:asciiname":"Paomachang",
    "gn:country_code":"CN",
    "gn:dem":1077,
    "gn:feature_class":"P",
    "gn:feature_code":"PPL",
    "gn:name":"Paomachang",
    "gn:population":0,
    "gn:timezone":"Asia/Shanghai",
    "iso:country":"CN",
    "name:zho_x_preferred":[
        "\u8dd1\u9a6c\u573a"
    ],
    "wof:name":"Paomachang",
    "wof:placetype":"locality"
},
  "geometry": {"coordinates":[106.744,26.3602],"type":"Point"}
}