{
  "type": "Feature",
  "properties": {
    "gn:admin1_code":"2",
    "gn:asciiname":"Jinyancun",
    "gn:country_code":"CN",
    "gn:dem":403,
    "gn:feature_class":"P",
    "gn:feature_code":"PPL",
    "gn:name":"Jinyancun",
    "gn:population":0,
    "gn:timezone":"Asia/Shanghai",
    "iso:country":"CN",
    "name:zho_x_preferred":[
        "\u91d1\u5ca9\u6751"
    ],
    "wof:name":"Jinyancun",
    "wof:placetype":"locality"
},
  "geometry": {"coordinates":[119.77948000000001,28.65743],"type":"Point"}
}