{
  "type": "Feature",
  "properties": {
    "gn:admin1_code":"25.0",
    "gn:asciiname":"Dalongkoucun",
    "gn:country_code":"CN",
    "gn:dem":70,
    "gn:feature_class":"P",
    "gn:feature_code":"PPL",
    "gn:name":"Dalongkoucun",
    "gn:population":0,
    "gn:timezone":"Asia/Shanghai",
    "iso:country":"CN",
    "name:zho_x_preferred":[
        "\u5927\u9f99\u53e3\u6751"
    ],
    "wof:name":"Dalongkoucun",
    "wof:placetype":"locality"
},
  "geometry": {"coordinates":[121.28400000000001,36.98052],"type":"Point"}
}