{
  "type": "Feature",
  "properties": {
    "gn:admin1_code":"15.0",
    "gn:asciiname":"Xujiashan",
    "gn:country_code":"CN",
    "gn:dem":1593,
    "gn:feature_class":"P",
    "gn:feature_code":"PPL",
    "gn:name":"Xujiashan",
    "gn:population":0,
    "gn:timezone":"Asia/Shanghai",
    "iso:country":"CN",
    "name:und_x_variant":[
        "\u5f90\u5bb6\u5c71"
    ],
    "wof:name":"Xujiashan",
    "wof:placetype":"locality"
},
  "geometry": {"coordinates":[105.34220999999999,33.47364],"type":"Point"}
}