{
  "type": "Feature",
  "properties": {
    "gn:admin1_code":"18",
    "gn:asciiname":"Xiongkong",
    "gn:country_code":"CN",
    "gn:dem":1004,
    "gn:feature_class":"P",
    "gn:feature_code":"PPL",
    "gn:name":"Xiongkong",
    "gn:population":0,
    "gn:timezone":"Asia/Shanghai",
    "iso:country":"CN",
    "name:zho_x_preferred":[
        "\u718a\u5b54"
    ],
    "wof:name":"Xiongkong",
    "wof:placetype":"locality"
},
  "geometry": {"coordinates":[107.02200000000001,27.4368],"type":"Point"}
}