{
  "type": "Feature",
  "properties": {
    "gn:admin1_code":"33.0",
    "gn:asciiname":"Nancheng",
    "gn:country_code":"CN",
    "gn:dem":274,
    "gn:feature_class":"P",
    "gn:feature_code":"PPLA4",
    "gn:name":"Nancheng",
    "gn:population":0,
    "gn:timezone":"Asia/Shanghai",
    "iso:country":"CN",
    "name:und_x_variant":[
        "Nancheng Jiedao"
    ],
    "name:zho_x_preferred":[
        "\u5357\u57ce"
    ],
    "name:zho_x_variant":[
        "\u5357\u57ce\u8857\u9053"
    ],
    "wof:name":"Nancheng",
    "wof:placetype":"locality"
},
  "geometry": {"coordinates":[106.05172,29.83548],"type":"Point"}
}