{
  "type": "Feature",
  "properties": {
    "gn:admin1_code":"9.0",
    "gn:asciiname":"Tuozhuang",
    "gn:country_code":"CN",
    "gn:dem":187,
    "gn:feature_class":"P",
    "gn:feature_code":"PPL",
    "gn:name":"Tuozhuang",
    "gn:population":0,
    "gn:timezone":"Asia/Shanghai",
    "iso:country":"CN",
    "name:zho_x_preferred":[
        "\u5eb9\u5e84"
    ],
    "wof:name":"Tuozhuang",
    "wof:placetype":"locality"
},
  "geometry": {"coordinates":[112.83228,33.32448],"type":"Point"}
}