{
  "type": "Feature",
  "properties": {
    "gn:admin1_code":"8.0",
    "gn:asciiname":"Xinglong Erdui",
    "gn:country_code":"CN",
    "gn:dem":193,
    "gn:feature_class":"P",
    "gn:feature_code":"PPLF",
    "gn:name":"Xinglong Erdui",
    "gn:population":0,
    "gn:timezone":"Asia/Shanghai",
    "iso:country":"CN",
    "name:zho_x_preferred":[
        "\u5174\u9686\u4e8c\u961f"
    ],
    "wof:name":"Xinglong Erdui",
    "wof:placetype":"locality"
},
  "geometry": {"coordinates":[131.24590000000001,45.3452],"type":"Point"}
}