{
  "type": "Feature",
  "properties": {
    "gn:admin1_code":"21",
    "gn:asciiname":"Chongyicun",
    "gn:country_code":"CN",
    "gn:dem":2038,
    "gn:feature_class":"P",
    "gn:feature_code":"PPL",
    "gn:name":"Chongyicun",
    "gn:population":0,
    "gn:timezone":"Asia/Shanghai",
    "iso:country":"CN",
    "wof:name":"Chongyicun",
    "wof:placetype":"locality"
},
  "geometry": {"coordinates":[106.33333,35.55],"type":"Point"}
}