{
  "type": "Feature",
  "properties": {
    "gn:admin1_code":"18",
    "gn:asciiname":"Gaojian",
    "gn:country_code":"CN",
    "gn:dem":1835,
    "gn:feature_class":"P",
    "gn:feature_code":"PPL",
    "gn:name":"Gaojian",
    "gn:population":0,
    "gn:timezone":"Asia/Shanghai",
    "iso:country":"CN",
    "name:zho_x_preferred":[
        "\u9ad8\u7b80"
    ],
    "wof:name":"Gaojian",
    "wof:placetype":"locality"
},
  "geometry": {"coordinates":[104.319,27.1618],"type":"Point"}
}