{
  "type": "Feature",
  "properties": {
    "gn:admin1_code":"8.0",
    "gn:asciiname":"Dongnantuncun",
    "gn:country_code":"CN",
    "gn:dem":93,
    "gn:feature_class":"P",
    "gn:feature_code":"PPL",
    "gn:name":"Dongnantuncun",
    "gn:population":0,
    "gn:timezone":"Asia/Shanghai",
    "iso:country":"CN",
    "name:zho_x_preferred":[
        "\u4e1c\u5357\u5c6f\u6751"
    ],
    "wof:name":"Dongnantuncun",
    "wof:placetype":"locality"
},
  "geometry": {"coordinates":[129.70569,49.27456],"type":"Point"}
}