{
  "type": "Feature",
  "properties": {
    "gn:admin1_code":"25",
    "gn:asciiname":"Longhua",
    "gn:country_code":"CN",
    "gn:dem":129,
    "gn:feature_class":"P",
    "gn:feature_code":"PPL",
    "gn:name":"Longhua",
    "gn:population":0,
    "gn:timezone":"Asia/Shanghai",
    "iso:country":"CN",
    "name:ceb_x_preferred":[
        "Longhua"
    ],
    "name:deu_x_preferred":[
        "Longhua"
    ],
    "name:fra_x_preferred":[
        "Longhua"
    ],
    "name:nor_x_preferred":[
        "Longhua"
    ],
    "name:pol_x_preferred":[
        "Longhua"
    ],
    "name:rus_x_preferred":[
        "\u041b\u0443\u043d\u0445\u0443\u0430"
    ],
    "name:swe_x_preferred":[
        "Longhua"
    ],
    "name:zho_x_preferred":[
        "\u9f99\u534e"
    ],
    "wof:name":"Longhua",
    "wof:placetype":"locality"
},
  "geometry": {"coordinates":[117.621,36.7383],"type":"Point"}
}