{
  "type": "Feature",
  "properties": {
    "gn:admin1_code":"14.0",
    "gn:asciiname":"Xiagu",
    "gn:country_code":"CN",
    "gn:dem":4678,
    "gn:feature_class":"P",
    "gn:feature_code":"PPL",
    "gn:name":"Xiagu",
    "gn:population":0,
    "gn:timezone":"Asia/Urumqi",
    "iso:country":"CN",
    "name:zho_x_preferred":[
        "\u867e\u53e4"
    ],
    "wof:name":"Xiagu",
    "wof:placetype":"locality"
},
  "geometry": {"coordinates":[83.7607,32.1384],"type":"Point"}
}