{
  "type": "Feature",
  "properties": {
    "gn:admin1_code":"12.0",
    "gn:asciiname":"Luohanzhou",
    "gn:country_code":"CN",
    "gn:dem":24,
    "gn:feature_class":"P",
    "gn:feature_code":"PPL",
    "gn:name":"Luohanzhou",
    "gn:population":0,
    "gn:timezone":"Asia/Shanghai",
    "iso:country":"CN",
    "name:zho_x_preferred":[
        "\u7f57\u6c49\u6d32"
    ],
    "wof:name":"Luohanzhou",
    "wof:placetype":"locality"
},
  "geometry": {"coordinates":[113.8087,30.33109],"type":"Point"}
}