{
  "type": "Feature",
  "properties": {
    "gn:admin1_code":"11",
    "gn:asciiname":"Guanzhuang",
    "gn:country_code":"CN",
    "gn:dem":226,
    "gn:feature_class":"P",
    "gn:feature_code":"PPLA4",
    "gn:name":"Guanzhuang",
    "gn:population":0,
    "gn:timezone":"Asia/Shanghai",
    "iso:country":"CN",
    "name:ceb_x_preferred":[
        "Guanzhuang"
    ],
    "name:swe_x_preferred":[
        "Guanzhuang"
    ],
    "name:und_x_variant":[
        "Kuan-chuang",
        "Guanzhuang",
        "Guanzhuang Zhen"
    ],
    "name:zho_x_preferred":[
        "\u5b98\u5e84"
    ],
    "name:zho_x_variant":[
        "\u5b98\u5e84\u9547"
    ],
    "wof:name":"Guanzhuang",
    "wof:placetype":"locality"
},
  "geometry": {"coordinates":[110.90000000000001,28.53333],"type":"Point"}
}