{
  "type": "Feature",
  "properties": {
    "gn:admin1_code":"1.0",
    "gn:asciiname":"Sanyicun",
    "gn:country_code":"CN",
    "gn:dem":322,
    "gn:feature_class":"P",
    "gn:feature_code":"PPL",
    "gn:name":"Sanyicun",
    "gn:population":0,
    "gn:timezone":"Asia/Shanghai",
    "iso:country":"CN",
    "name:zho_x_preferred":[
        "\u4e09\u4e49\u6751"
    ],
    "wof:name":"Sanyicun",
    "wof:placetype":"locality"
},
  "geometry": {"coordinates":[116.81894,31.09369],"type":"Point"}
}