{
  "type": "Feature",
  "properties": {
    "gn:admin1_code":"15.0",
    "gn:asciiname":"Qujiagou",
    "gn:country_code":"CN",
    "gn:dem":959,
    "gn:feature_class":"P",
    "gn:feature_code":"PPL",
    "gn:name":"Qujiagou",
    "gn:population":0,
    "gn:timezone":"Asia/Shanghai",
    "iso:country":"CN",
    "name:und_x_variant":[
        "\u5c48\u5bb6\u6c9f"
    ],
    "wof:name":"Qujiagou",
    "wof:placetype":"locality"
},
  "geometry": {"coordinates":[106.02209000000001,33.62728],"type":"Point"}
}