{
  "type": "Feature",
  "properties": {
    "gn:admin1_code":"19.0",
    "gn:asciiname":"Qian'an Shanyu",
    "gn:country_code":"CN",
    "gn:dem":113,
    "gn:feature_class":"P",
    "gn:feature_code":"PPL",
    "gn:name":"Qian\u2019an Shanyu",
    "gn:population":0,
    "gn:timezone":"Asia/Shanghai",
    "iso:country":"CN",
    "name:und_x_variant":[
        "Qian\u2019an Shanyu",
        "\u524d\u978d\u5c71\u5cea"
    ],
    "name:zho_x_preferred":[
        "\u524d\u978d\u5c71\u5cea"
    ],
    "wof:name":"Qian'an Shanyu",
    "wof:placetype":"locality"
},
  "geometry": {"coordinates":[122.48563,40.01728],"type":"Point"}
}