{
  "type": "Feature",
  "properties": {
    "gn:admin1_code":"11",
    "gn:asciiname":"Tangtianshi",
    "gn:cc2":"CN",
    "gn:country_code":"CN",
    "gn:dem":233,
    "gn:feature_class":"P",
    "gn:feature_code":"PPL",
    "gn:name":"Tangtianshi",
    "gn:population":0,
    "gn:timezone":"Asia/Shanghai",
    "iso:country":"CN",
    "name:und_x_variant":[
        "T\u2019ang-t\u2019ien-shih",
        "Tangtianshi"
    ],
    "wof:name":"Tangtianshi",
    "wof:placetype":"locality"
},
  "geometry": {"coordinates":[111.22833,26.84917],"type":"Point"}
}