{
  "type": "Feature",
  "properties": {
    "gn:admin1_code":"8.0",
    "gn:asciiname":"Wangxingyuantun",
    "gn:country_code":"CN",
    "gn:dem":294,
    "gn:feature_class":"P",
    "gn:feature_code":"PPL",
    "gn:name":"Wangxingyuantun",
    "gn:population":0,
    "gn:timezone":"Asia/Shanghai",
    "iso:country":"CN",
    "name:zho_x_preferred":[
        "\u738b\u5174\u5143\u5c6f"
    ],
    "wof:name":"Wangxingyuantun",
    "wof:placetype":"locality"
},
  "geometry": {"coordinates":[125.92108,48.16832],"type":"Point"}
}