{
  "type": "Feature",
  "properties": {
    "gn:admin1_code":"15.0",
    "gn:asciiname":"Xiaowan",
    "gn:country_code":"CN",
    "gn:dem":2035,
    "gn:feature_class":"P",
    "gn:feature_code":"PPL",
    "gn:name":"Xiaowan",
    "gn:population":0,
    "gn:timezone":"Asia/Shanghai",
    "iso:country":"CN",
    "name:zho_x_preferred":[
        "\u5c0f\u6e7e"
    ],
    "wof:name":"Xiaowan",
    "wof:placetype":"locality"
},
  "geometry": {"coordinates":[104.73399999999999,35.3266],"type":"Point"}
}