{
  "type": "Feature",
  "properties": {
    "gn:admin1_code":"2.0",
    "gn:asciiname":"Shengtang",
    "gn:country_code":"CN",
    "gn:dem":158,
    "gn:feature_class":"P",
    "gn:feature_code":"PPL",
    "gn:name":"Shengtang",
    "gn:population":0,
    "gn:timezone":"Asia/Shanghai",
    "iso:country":"CN",
    "name:zho_x_preferred":[
        "\u5723\u5858"
    ],
    "wof:name":"Shengtang",
    "wof:placetype":"locality"
},
  "geometry": {"coordinates":[120.48869999999999,27.31366],"type":"Point"}
}