{
  "type": "Feature",
  "properties": {
    "gn:admin1_code":"11.0",
    "gn:asciiname":"Liushaxi",
    "gn:country_code":"CN",
    "gn:dem":503,
    "gn:feature_class":"P",
    "gn:feature_code":"PPL",
    "gn:name":"Liushaxi",
    "gn:population":0,
    "gn:timezone":"Asia/Shanghai",
    "iso:country":"CN",
    "name:zho_x_preferred":[
        "\u6d41\u6c99\u6eaa"
    ],
    "wof:name":"Liushaxi",
    "wof:placetype":"locality"
},
  "geometry": {"coordinates":[109.83365999999999,26.41661],"type":"Point"}
}