{
  "type": "Feature",
  "properties": {
    "gn:admin1_code":"15.0",
    "gn:asciiname":"Sanshi",
    "gn:country_code":"CN",
    "gn:dem":2822,
    "gn:feature_class":"P",
    "gn:feature_code":"PPL",
    "gn:name":"Sanshi",
    "gn:population":0,
    "gn:timezone":"Asia/Shanghai",
    "iso:country":"CN",
    "name:und_x_variant":[
        "\u4e09\u77f3",
        "Sanshicun",
        "\u4e09\u77f3\u6751"
    ],
    "wof:name":"Sanshi",
    "wof:placetype":"locality"
},
  "geometry": {"coordinates":[103.69941,34.77824],"type":"Point"}
}