{
  "type": "Feature",
  "properties": {
    "gn:admin1_code":"18",
    "gn:asciiname":"Daicunba",
    "gn:country_code":"CN",
    "gn:dem":805,
    "gn:feature_class":"P",
    "gn:feature_code":"PPL",
    "gn:name":"Daicunba",
    "gn:population":0,
    "gn:timezone":"Asia/Shanghai",
    "iso:country":"CN",
    "name:zho_x_preferred":[
        "\u4ee3\u6751\u575d"
    ],
    "wof:name":"Daicunba",
    "wof:placetype":"locality"
},
  "geometry": {"coordinates":[107.33199999999999,27.7125],"type":"Point"}
}