{
  "type": "Feature",
  "properties": {
    "gn:admin1_code":"32.0",
    "gn:asciiname":"Zhuwo",
    "gn:country_code":"CN",
    "gn:dem":3393,
    "gn:feature_class":"P",
    "gn:feature_code":"PPL",
    "gn:name":"Zhuwo",
    "gn:population":0,
    "gn:timezone":"Asia/Shanghai",
    "iso:country":"CN",
    "name:und_x_variant":[
        "Driwo",
        "Chzhue",
        "Chu-wo",
        "Chu-o",
        "Zh\u00eahor",
        "Zhuwo"
    ],
    "name:zho_x_preferred":[
        "\u6731\u502d"
    ],
    "wof:name":"Zhuwo",
    "wof:placetype":"locality"
},
  "geometry": {"coordinates":[100.30884,31.63633],"type":"Point"}
}