{
  "type": "Feature",
  "properties": {
    "gn:admin1_code":"20.0",
    "gn:asciiname":"Wuliyasi",
    "gn:country_code":"CN",
    "gn:dem":666,
    "gn:feature_class":"P",
    "gn:feature_code":"PPL",
    "gn:name":"Wuliyasi",
    "gn:population":0,
    "gn:timezone":"Asia/Shanghai",
    "iso:country":"CN",
    "name:zho_x_preferred":[
        "\u4e4c\u529b\u4e9a\u65af"
    ],
    "wof:name":"Wuliyasi",
    "wof:placetype":"locality"
},
  "geometry": {"coordinates":[120.94625000000001,49.41277],"type":"Point"}
}