{
  "type": "Feature",
  "properties": {
    "gn:admin1_code":"2.0",
    "gn:asciiname":"Shimuling",
    "gn:country_code":"CN",
    "gn:dem":92,
    "gn:feature_class":"P",
    "gn:feature_code":"PPL",
    "gn:name":"Shimuling",
    "gn:population":0,
    "gn:timezone":"Asia/Shanghai",
    "iso:country":"CN",
    "name:zho_x_preferred":[
        "\u77f3\u6728\u5cad"
    ],
    "wof:name":"Shimuling",
    "wof:placetype":"locality"
},
  "geometry": {"coordinates":[119.19696999999999,29.23783],"type":"Point"}
}