{
  "type": "Feature",
  "properties": {
    "gn:admin1_code":"9.0",
    "gn:asciiname":"Tacaomao",
    "gn:country_code":"CN",
    "gn:dem":1080,
    "gn:feature_class":"P",
    "gn:feature_code":"PPL",
    "gn:name":"Tacaomao",
    "gn:population":0,
    "gn:timezone":"Asia/Shanghai",
    "iso:country":"CN",
    "name:und_x_variant":[
        "\u5854\u8349\u5e3d",
        "Tacaomao"
    ],
    "wof:name":"Tacaomao",
    "wof:placetype":"locality"
},
  "geometry": {"coordinates":[112.02833,33.3538],"type":"Point"}
}