{
  "type": "Feature",
  "properties": {
    "gn:admin1_code":"30.0",
    "gn:asciiname":"Hengpi",
    "gn:country_code":"CN",
    "gn:dem":135,
    "gn:feature_class":"P",
    "gn:feature_code":"PPLA4",
    "gn:name":"Hengpi",
    "gn:population":0,
    "gn:timezone":"Asia/Shanghai",
    "iso:country":"CN",
    "name:und_x_variant":[
        "Hengpi Zhen"
    ],
    "name:zho_x_preferred":[
        "\u6a2a\u9642"
    ],
    "name:zho_x_variant":[
        "\u6a2a\u9642\u9547"
    ],
    "wof:name":"Hengpi",
    "wof:placetype":"locality"
},
  "geometry": {"coordinates":[115.72167,23.88916],"type":"Point"}
}