{
  "type": "Feature",
  "properties": {
    "gn:admin1_code":"19.0",
    "gn:asciiname":"Luojia Wobu",
    "gn:country_code":"CN",
    "gn:dem":62,
    "gn:feature_class":"P",
    "gn:feature_code":"PPL",
    "gn:name":"Luojia Wobu",
    "gn:population":0,
    "gn:timezone":"Asia/Shanghai",
    "iso:country":"CN",
    "name:zho_x_preferred":[
        "\u7f57\u5bb6\u7a9d\u5821"
    ],
    "wof:name":"Luojia Wobu",
    "wof:placetype":"locality"
},
  "geometry": {"coordinates":[122.509,42.1804],"type":"Point"}
}