{
  "type": "Feature",
  "properties": {
    "gn:admin1_code":"12.0",
    "gn:asciiname":"Liugang Fenchang Sidui",
    "gn:country_code":"CN",
    "gn:dem":31,
    "gn:feature_class":"P",
    "gn:feature_code":"PPLF",
    "gn:name":"Liugang Fenchang Sidui",
    "gn:population":0,
    "gn:timezone":"Asia/Shanghai",
    "iso:country":"CN",
    "name:zho_x_preferred":[
        "\u6d41\u6e2f\u5206\u573a\u56db\u961f"
    ],
    "wof:name":"Liugang Fenchang Sidui",
    "wof:placetype":"locality"
},
  "geometry": {"coordinates":[112.63896,29.83255],"type":"Point"}
}