{
  "type": "Feature",
  "properties": {
    "gn:admin1_code":"30.0",
    "gn:asciiname":"Su'ercun",
    "gn:country_code":"CN",
    "gn:dem":8,
    "gn:feature_class":"P",
    "gn:feature_code":"PPL",
    "gn:name":"Su\u2019ercun",
    "gn:population":0,
    "gn:timezone":"Asia/Shanghai",
    "iso:country":"CN",
    "name:und_x_variant":[
        "Su\u2019ercun",
        "Su\u2019er"
    ],
    "name:zho_x_preferred":[
        "\u82cf\u4e8c\u6751"
    ],
    "wof:name":"Su'ercun",
    "wof:placetype":"locality"
},
  "geometry": {"coordinates":[116.7445,23.60426],"type":"Point"}
}