{
  "type": "Feature",
  "properties": {
    "gn:admin1_code":"7.0",
    "gn:asciiname":"Shikengwo",
    "gn:country_code":"CN",
    "gn:dem":423,
    "gn:feature_class":"P",
    "gn:feature_code":"PPL",
    "gn:name":"Shikengwo",
    "gn:population":0,
    "gn:timezone":"Asia/Shanghai",
    "iso:country":"CN",
    "name:zho_x_preferred":[
        "\u77f3\u5751\u7a9d"
    ],
    "wof:name":"Shikengwo",
    "wof:placetype":"locality"
},
  "geometry": {"coordinates":[116.26331999999999,25.22427],"type":"Point"}
}