{
  "type": "Feature",
  "properties": {
    "gn:admin1_code":"11.0",
    "gn:asciiname":"Liancun",
    "gn:country_code":"CN",
    "gn:dem":268,
    "gn:feature_class":"P",
    "gn:feature_code":"PPL",
    "gn:name":"Liancun",
    "gn:population":0,
    "gn:timezone":"Asia/Shanghai",
    "iso:country":"CN",
    "name:zho_x_preferred":[
        "Liancun"
    ],
    "name:zho_x_variant":[
        "\u5ec9\u6751"
    ],
    "wof:name":"Liancun",
    "wof:placetype":"locality"
},
  "geometry": {"coordinates":[114.10148999999998,28.33847],"type":"Point"}
}