{
  "type": "Feature",
  "properties": {
    "gn:admin1_code":"5.0",
    "gn:asciiname":"Xinfengtun",
    "gn:country_code":"CN",
    "gn:dem":417,
    "gn:feature_class":"P",
    "gn:feature_code":"PPL",
    "gn:name":"Xinfengtun",
    "gn:population":0,
    "gn:timezone":"Asia/Shanghai",
    "iso:country":"CN",
    "name:und_x_variant":[
        "\u65b0\u4e30\u5c6f",
        "Xinfengcun",
        "\u65b0\u4e30\u6751"
    ],
    "wof:name":"Xinfengtun",
    "wof:placetype":"locality"
},
  "geometry": {"coordinates":[130.30154999999999,43.66399000000001],"type":"Point"}
}