{
  "type": "Feature",
  "properties": {
    "gn:admin1_code":"30.0",
    "gn:asciiname":"Yizitang",
    "gn:country_code":"CN",
    "gn:dem":67,
    "gn:feature_class":"P",
    "gn:feature_code":"PPL",
    "gn:name":"Yizitang",
    "gn:population":0,
    "gn:timezone":"Asia/Shanghai",
    "iso:country":"CN",
    "name:zho_x_preferred":[
        "\u4e49\u5b50\u5858"
    ],
    "wof:name":"Yizitang",
    "wof:placetype":"locality"
},
  "geometry": {"coordinates":[111.77307,23.59427],"type":"Point"}
}