{
  "type": "Feature",
  "properties": {
    "gn:admin1_code":"11.0",
    "gn:asciiname":"Dongjiang",
    "gn:country_code":"CN",
    "gn:dem":29,
    "gn:feature_class":"P",
    "gn:feature_code":"PPLA4",
    "gn:name":"Dongjiang",
    "gn:population":0,
    "gn:timezone":"Asia/Shanghai",
    "iso:country":"CN",
    "name:und_x_variant":[
        "\u4e1c\u6c5f",
        "Qingnian Beilu",
        "\u9752\u5e74\u5317\u8def"
    ],
    "name:zho_x_preferred":[
        "Dongjiang Xiang"
    ],
    "name:zho_x_variant":[
        "\u4e1c\u6c5f\u4e61"
    ],
    "wof:name":"Dongjiang",
    "wof:placetype":"locality"
},
  "geometry": {"coordinates":[111.74664,29.03406],"type":"Point"}
}