{
  "type": "Feature",
  "properties": {
    "gn:admin1_code":"24.0",
    "gn:asciiname":"Houlingdi",
    "gn:country_code":"CN",
    "gn:dem":1461,
    "gn:feature_class":"P",
    "gn:feature_code":"PPL",
    "gn:name":"Houlingdi",
    "gn:population":0,
    "gn:timezone":"Asia/Shanghai",
    "iso:country":"CN",
    "name:zho_x_preferred":[
        "\u540e\u5cad\u5e95"
    ],
    "wof:name":"Houlingdi",
    "wof:placetype":"locality"
},
  "geometry": {"coordinates":[112.07959,37.73548],"type":"Point"}
}