{
  "type": "Feature",
  "properties": {
    "gn:admin1_code":"14.0",
    "gn:asciiname":"Shengdacun",
    "gn:country_code":"CN",
    "gn:dem":4153,
    "gn:feature_class":"P",
    "gn:feature_code":"PPL",
    "gn:name":"Shengdacun",
    "gn:population":0,
    "gn:timezone":"Asia/Urumqi",
    "iso:country":"CN",
    "name:zho_x_preferred":[
        "\u751f\u8fbe\u6751"
    ],
    "wof:name":"Shengdacun",
    "wof:placetype":"locality"
},
  "geometry": {"coordinates":[96.1592,30.6948],"type":"Point"}
}