{
  "type": "Feature",
  "properties": {
    "gn:admin1_code":"9.0",
    "gn:asciiname":"Dafanzhuang",
    "gn:country_code":"CN",
    "gn:dem":44,
    "gn:feature_class":"P",
    "gn:feature_code":"PPL",
    "gn:name":"Dafanzhuang",
    "gn:population":0,
    "gn:timezone":"Asia/Shanghai",
    "iso:country":"CN",
    "name:zho_x_preferred":[
        "\u5927\u6a0a\u5e84"
    ],
    "wof:name":"Dafanzhuang",
    "wof:placetype":"locality"
},
  "geometry": {"coordinates":[114.87293,33.09987],"type":"Point"}
}