{
  "type": "Feature",
  "properties": {
    "gn:admin1_code":"6.0",
    "gn:asciiname":"Nantai",
    "gn:country_code":"CN",
    "gn:dem":3258,
    "gn:feature_class":"P",
    "gn:feature_code":"PPL",
    "gn:name":"Nantai",
    "gn:population":0,
    "gn:timezone":"Asia/Urumqi",
    "iso:country":"CN",
    "name:und_x_variant":[
        "\u5357\u53f0"
    ],
    "wof:name":"Nantai",
    "wof:placetype":"locality"
},
  "geometry": {"coordinates":[98.09677000000001,36.23938],"type":"Point"}
}