{
  "type": "Feature",
  "properties": {
    "gn:admin1_code":"29.0",
    "gn:asciiname":"Goumenkou",
    "gn:country_code":"CN",
    "gn:dem":1567,
    "gn:feature_class":"P",
    "gn:feature_code":"PPL",
    "gn:name":"Goumenkou",
    "gn:population":0,
    "gn:timezone":"Asia/Shanghai",
    "iso:country":"CN",
    "name:zho_x_preferred":[
        "\u6c9f\u95e8\u53e3"
    ],
    "wof:name":"Goumenkou",
    "wof:placetype":"locality"
},
  "geometry": {"coordinates":[104.85899999999999,27.5168],"type":"Point"}
}