{
  "type": "Feature",
  "properties": {
    "gn:admin1_code":"32.0",
    "gn:asciiname":"Gebudu",
    "gn:country_code":"CN",
    "gn:dem":2626,
    "gn:feature_class":"P",
    "gn:feature_code":"PPL",
    "gn:name":"Gebudu",
    "gn:population":0,
    "gn:timezone":"Asia/Shanghai",
    "iso:country":"CN",
    "name:zho_x_preferred":[
        "\u683c\u5e03\u5835"
    ],
    "wof:name":"Gebudu",
    "wof:placetype":"locality"
},
  "geometry": {"coordinates":[103.06100000000001,28.0271],"type":"Point"}
}