{
  "type": "Feature",
  "properties": {
    "gn:admin1_code":"4.0",
    "gn:asciiname":"Qiantengzhuang",
    "gn:country_code":"CN",
    "gn:dem":12,
    "gn:feature_class":"P",
    "gn:feature_code":"PPL",
    "gn:name":"Qiantengzhuang",
    "gn:population":0,
    "gn:timezone":"Asia/Shanghai",
    "iso:country":"CN",
    "name:zho_x_preferred":[
        "Qiantengzhuang"
    ],
    "name:zho_x_variant":[
        "\u524d\u6ed5\u5e84"
    ],
    "wof:name":"Qiantengzhuang",
    "wof:placetype":"locality"
},
  "geometry": {"coordinates":[119.03949,34.83773],"type":"Point"}
}