{
  "type": "Feature",
  "properties": {
    "gn:admin1_code":"16",
    "gn:asciiname":"Luo'an",
    "gn:country_code":"CN",
    "gn:dem":149,
    "gn:feature_class":"P",
    "gn:feature_code":"PPL",
    "gn:name":"Luo\u2019an",
    "gn:population":0,
    "gn:timezone":"Asia/Shanghai",
    "iso:country":"CN",
    "name:und_x_variant":[
        "Luo\u2019an"
    ],
    "name:zho_x_preferred":[
        "\u7f57\u5b89"
    ],
    "wof:name":"Luo'an",
    "wof:placetype":"locality"
},
  "geometry": {"coordinates":[110.328,25.1061],"type":"Point"}
}