{
  "type": "Feature",
  "properties": {
    "gn:admin1_code":"6.0",
    "gn:asciiname":"Keqiena",
    "gn:country_code":"CN",
    "gn:dem":4068,
    "gn:feature_class":"P",
    "gn:feature_code":"PPL",
    "gn:name":"Keqiena",
    "gn:population":0,
    "gn:timezone":"Asia/Urumqi",
    "iso:country":"CN",
    "name:zho_x_preferred":[
        "\u514b\u5207\u90a3"
    ],
    "wof:name":"Keqiena",
    "wof:placetype":"locality"
},
  "geometry": {"coordinates":[96.12302,32.42755],"type":"Point"}
}