{
  "type": "Feature",
  "properties": {
    "gn:admin1_code":"3.0",
    "gn:asciiname":"Zhoupoli",
    "gn:country_code":"CN",
    "gn:dem":178,
    "gn:feature_class":"P",
    "gn:feature_code":"PPL",
    "gn:name":"Zhoupoli",
    "gn:population":0,
    "gn:timezone":"Asia/Shanghai",
    "iso:country":"CN",
    "name:und_x_variant":[
        "\u5468\u5761\u91cc"
    ],
    "wof:name":"Zhoupoli",
    "wof:placetype":"locality"
},
  "geometry": {"coordinates":[114.94710000000001,28.59141],"type":"Point"}
}