{
  "type": "Feature",
  "properties": {
    "gn:admin1_code":"7.0",
    "gn:asciiname":"Qinyang",
    "gn:country_code":"CN",
    "gn:dem":492,
    "gn:feature_class":"P",
    "gn:feature_code":"PPL",
    "gn:name":"Qinyang",
    "gn:population":0,
    "gn:timezone":"Asia/Shanghai",
    "iso:country":"CN",
    "name:cym_x_preferred":[
        "Qinyang"
    ],
    "name:deu_x_preferred":[
        "Qinyang"
    ],
    "name:fra_x_preferred":[
        "Qinyang"
    ],
    "name:ita_x_preferred":[
        "Qinyang"
    ],
    "name:jpn_x_preferred":[
        "\u6c81\u967d\u5e02"
    ],
    "name:kik_x_preferred":[
        "Qinyang"
    ],
    "name:kor_x_preferred":[
        "\uce5c\uc591\uc2dc"
    ],
    "name:mlg_x_preferred":[
        "Qinyang"
    ],
    "name:mwl_x_preferred":[
        "Qinyang"
    ],
    "name:nld_x_preferred":[
        "Qinyang"
    ],
    "name:nor_x_preferred":[
        "Qinyang"
    ],
    "name:pam_x_preferred":[
        "Qinyang"
    ],
    "name:rus_x_preferred":[
        "\u0426\u0438\u043d\u044c\u044f\u043d"
    ],
    "name:swe_x_preferred":[
        "Qinyang"
    ],
    "name:und_x_variant":[
        "\u82b9\u6d0b"
    ],
    "name:vie_x_preferred":[
        "Th\u1ea5m D\u01b0\u01a1ng"
    ],
    "name:war_x_preferred":[
        "Qinyang"
    ],
    "name:zho_x_preferred":[
        "\u82b9\u6d0b"
    ],
    "name:zho_x_variant":[
        "\u6c81\u9633\u5e02"
    ],
    "wof:name":"Qinyang",
    "wof:placetype":"locality"
},
  "geometry": {"coordinates":[118.06779,26.00707],"type":"Point"}
}