{
  "type": "Feature",
  "properties": {
    "gn:admin1_code":"3.0",
    "gn:asciiname":"Youshui",
    "gn:country_code":"CN",
    "gn:dem":266,
    "gn:feature_class":"P",
    "gn:feature_code":"PPLA4",
    "gn:name":"Youshui",
    "gn:population":0,
    "gn:timezone":"Asia/Shanghai",
    "iso:country":"CN",
    "name:und_x_variant":[
        "Yu-shui",
        "Youshui",
        "\u53f3\u6c34",
        "Youshui Xiang",
        "\u53f3\u6c34\u4e61"
    ],
    "wof:name":"Youshui",
    "wof:placetype":"locality"
},
  "geometry": {"coordinates":[115.66974,25.44347],"type":"Point"}
}