{
  "type": "Feature",
  "properties": {
    "gn:admin1_code":"30",
    "gn:asciiname":"Chuandongcun",
    "gn:country_code":"CN",
    "gn:dem":6,
    "gn:feature_class":"P",
    "gn:feature_code":"PPL",
    "gn:name":"Chuandongcun",
    "gn:population":0,
    "gn:timezone":"Asia/Urumqi",
    "iso:country":"CN",
    "name:zho_x_preferred":[
        "\u5ddd\u4e1c\u6751"
    ],
    "wof:name":"Chuandongcun",
    "wof:placetype":"locality"
},
  "geometry": {"coordinates":[110.02932,20.8586],"type":"Point"}
}