{
  "type": "Feature",
  "properties": {
    "gn:admin1_code":"19.0",
    "gn:asciiname":"Gaochengzhai",
    "gn:country_code":"CN",
    "gn:dem":179,
    "gn:feature_class":"P",
    "gn:feature_code":"PPL",
    "gn:name":"Gaochengzhai",
    "gn:population":0,
    "gn:timezone":"Asia/Shanghai",
    "iso:country":"CN",
    "name:und_x_variant":[
        "\u9ad8\u7a0b\u5be8"
    ],
    "name:zho_x_preferred":[
        "\u9ad8\u7a0b\u5be8"
    ],
    "wof:name":"Gaochengzhai",
    "wof:placetype":"locality"
},
  "geometry": {"coordinates":[123.72199000000001,41.40181],"type":"Point"}
}