{
  "type": "Feature",
  "properties": {
    "gn:admin1_code":"18.0",
    "gn:asciiname":"Bianpozhai",
    "gn:country_code":"CN",
    "gn:dem":533,
    "gn:feature_class":"P",
    "gn:feature_code":"PPL",
    "gn:name":"Bianpozhai",
    "gn:population":0,
    "gn:timezone":"Asia/Shanghai",
    "iso:country":"CN",
    "name:zho_x_preferred":[
        "\u8fb9\u5761\u5be8"
    ],
    "wof:name":"Bianpozhai",
    "wof:placetype":"locality"
},
  "geometry": {"coordinates":[109.072,26.2408],"type":"Point"}
}