{
  "type": "Feature",
  "properties": {
    "gn:admin1_code":"19.0",
    "gn:asciiname":"Yijiayu",
    "gn:country_code":"CN",
    "gn:dem":52,
    "gn:feature_class":"P",
    "gn:feature_code":"PPL",
    "gn:name":"Yijiayu",
    "gn:population":0,
    "gn:timezone":"Asia/Shanghai",
    "iso:country":"CN",
    "name:und_x_variant":[
        "\u4e00\u5bb6\u5cea"
    ],
    "name:zho_x_preferred":[
        "\u4e00\u5bb6\u5cea"
    ],
    "wof:name":"Yijiayu",
    "wof:placetype":"locality"
},
  "geometry": {"coordinates":[121.46656000000002,41.35737],"type":"Point"}
}