{
  "type": "Feature",
  "properties": {
    "gn:admin1_code":"15.0",
    "gn:asciiname":"Xingdujia",
    "gn:country_code":"CN",
    "gn:dem":1310,
    "gn:feature_class":"P",
    "gn:feature_code":"PPL",
    "gn:name":"Xingdujia",
    "gn:population":0,
    "gn:timezone":"Asia/Shanghai",
    "iso:country":"CN",
    "name:zho_x_preferred":[
        "\u90a2\u675c\u5bb6"
    ],
    "wof:name":"Xingdujia",
    "wof:placetype":"locality"
},
  "geometry": {"coordinates":[107.502,35.5743],"type":"Point"}
}