{
  "type": "Feature",
  "properties": {
    "gn:admin1_code":"04",
    "gn:asciiname":"Daijiaxia",
    "gn:cc2":"CN",
    "gn:country_code":"CN",
    "gn:dem":3,
    "gn:feature_class":"P",
    "gn:feature_code":"PPL",
    "gn:name":"Daijiaxia",
    "gn:population":0,
    "gn:timezone":"Asia/Shanghai",
    "iso:country":"CN",
    "name:und_x_variant":[
        "Tai-chia-hsia",
        "Daijiaxia"
    ],
    "wof:name":"Daijiaxia",
    "wof:placetype":"locality"
},
  "geometry": {"coordinates":[121.19333,32.37694],"type":"Point"}
}