{
  "type": "Feature",
  "properties": {
    "gn:admin1_code":"4.0",
    "gn:asciiname":"Naizhuang",
    "gn:country_code":"CN",
    "gn:dem":5,
    "gn:feature_class":"P",
    "gn:feature_code":"PPL",
    "gn:name":"Naizhuang",
    "gn:population":0,
    "gn:timezone":"Asia/Shanghai",
    "iso:country":"CN",
    "name:zho_x_preferred":[
        "Naizhuang"
    ],
    "name:zho_x_variant":[
        "\u5948\u5e84"
    ],
    "wof:name":"Naizhuang",
    "wof:placetype":"locality"
},
  "geometry": {"coordinates":[119.46933,33.77134],"type":"Point"}
}