{
  "type": "Feature",
  "properties": {
    "gn:admin1_code":"19.0",
    "gn:asciiname":"Xiaojiangtun",
    "gn:country_code":"CN",
    "gn:dem":16,
    "gn:feature_class":"P",
    "gn:feature_code":"PPL",
    "gn:name":"Xiaojiangtun",
    "gn:population":0,
    "gn:timezone":"Asia/Shanghai",
    "iso:country":"CN",
    "name:zho_x_preferred":[
        "\u5c0f\u6c5f\u5c6f"
    ],
    "wof:name":"Xiaojiangtun",
    "wof:placetype":"locality"
},
  "geometry": {"coordinates":[122.61499999999999,39.5942],"type":"Point"}
}