{
  "type": "Feature",
  "properties": {
    "gn:admin1_code":"9.0",
    "gn:asciiname":"Duoluomu",
    "gn:country_code":"CN",
    "gn:dem":337,
    "gn:feature_class":"P",
    "gn:feature_code":"PPL",
    "gn:name":"Duoluomu",
    "gn:population":0,
    "gn:timezone":"Asia/Shanghai",
    "iso:country":"CN",
    "name:zho_x_preferred":[
        "\u88f0\u843d\u5893"
    ],
    "wof:name":"Duoluomu",
    "wof:placetype":"locality"
},
  "geometry": {"coordinates":[111.33163999999999,33.2316],"type":"Point"}
}