{
  "type": "Feature",
  "properties": {
    "gn:admin1_code":"16",
    "gn:asciiname":"Shilong",
    "gn:cc2":"CN",
    "gn:country_code":"CN",
    "gn:dem":49,
    "gn:feature_class":"P",
    "gn:feature_code":"PPL",
    "gn:name":"Shilong",
    "gn:population":0,
    "gn:timezone":"Asia/Shanghai",
    "iso:country":"CN",
    "name:und_x_variant":[
        "Shih-lung-hs\u00fc",
        "Shih-lung",
        "Shilong"
    ],
    "wof:name":"Shilong",
    "wof:placetype":"locality"
},
  "geometry": {"coordinates":[109.80194,23.31194],"type":"Point"}
}