{
  "type": "Feature",
  "properties": {
    "gn:admin1_code":"16.0",
    "gn:asciiname":"Liangbiao",
    "gn:country_code":"CN",
    "gn:dem":76,
    "gn:feature_class":"P",
    "gn:feature_code":"PPL",
    "gn:name":"Liangbiao",
    "gn:population":0,
    "gn:timezone":"Asia/Shanghai",
    "iso:country":"CN",
    "name:zho_x_preferred":[
        "\u826f\u8868"
    ],
    "wof:name":"Liangbiao",
    "wof:placetype":"locality"
},
  "geometry": {"coordinates":[110.02200000000001,22.5938],"type":"Point"}
}