{
  "type": "Feature",
  "properties": {
    "gn:admin1_code":"11.0",
    "gn:asciiname":"Zaopo",
    "gn:country_code":"CN",
    "gn:dem":367,
    "gn:feature_class":"P",
    "gn:feature_code":"PPL",
    "gn:name":"Zaopo",
    "gn:population":0,
    "gn:timezone":"Asia/Shanghai",
    "iso:country":"CN",
    "name:zho_x_preferred":[
        "\u65e9\u5761"
    ],
    "wof:name":"Zaopo",
    "wof:placetype":"locality"
},
  "geometry": {"coordinates":[110.71132,29.55185],"type":"Point"}
}