{
  "type": "Feature",
  "properties": {
    "gn:admin1_code":"15.0",
    "gn:asciiname":"Houjiashan",
    "gn:country_code":"CN",
    "gn:dem":1790,
    "gn:feature_class":"P",
    "gn:feature_code":"PPL",
    "gn:name":"Houjiashan",
    "gn:population":0,
    "gn:timezone":"Asia/Shanghai",
    "iso:country":"CN",
    "name:und_x_variant":[
        "\u4faf\u5bb6\u5c71"
    ],
    "wof:name":"Houjiashan",
    "wof:placetype":"locality"
},
  "geometry": {"coordinates":[105.66288,35.11802],"type":"Point"}
}