{
  "type": "Feature",
  "properties": {
    "gn:admin1_code":"32.0",
    "gn:asciiname":"Liangshan",
    "gn:country_code":"CN",
    "gn:dem":425,
    "gn:feature_class":"P",
    "gn:feature_code":"PPL",
    "gn:name":"Liangshan",
    "gn:population":0,
    "gn:timezone":"Asia/Shanghai",
    "iso:country":"CN",
    "name:ceb_x_preferred":[
        "Liangshan"
    ],
    "name:deu_x_preferred":[
        "Liangshan"
    ],
    "name:fra_x_preferred":[
        "Liangshan"
    ],
    "name:nor_x_preferred":[
        "Liangshan"
    ],
    "name:pol_x_preferred":[
        "Liangshan"
    ],
    "name:swe_x_preferred":[
        "Liangshan"
    ],
    "name:zho_x_preferred":[
        "\u6881\u5c71"
    ],
    "wof:name":"Liangshan",
    "wof:placetype":"locality"
},
  "geometry": {"coordinates":[106.584,31.4582],"type":"Point"}
}