{
  "type": "Feature",
  "properties": {
    "gn:admin1_code":"3.0",
    "gn:asciiname":"Liangxi Zhoujia",
    "gn:country_code":"CN",
    "gn:dem":70,
    "gn:feature_class":"P",
    "gn:feature_code":"PPL",
    "gn:name":"Liangxi Zhoujia",
    "gn:population":0,
    "gn:timezone":"Asia/Shanghai",
    "iso:country":"CN",
    "name:zho_x_preferred":[
        "\u6881\u6eaa\u5468\u5bb6"
    ],
    "wof:name":"Liangxi Zhoujia",
    "wof:placetype":"locality"
},
  "geometry": {"coordinates":[117.24332,28.15488],"type":"Point"}
}