{
  "type": "Feature",
  "properties": {
    "gn:admin1_code":"20",
    "gn:asciiname":"Hada Linchang",
    "gn:country_code":"CN",
    "gn:dem":783,
    "gn:feature_class":"P",
    "gn:feature_code":"PPLF",
    "gn:name":"Hada Linchang",
    "gn:population":0,
    "gn:timezone":"Asia/Shanghai",
    "iso:country":"CN",
    "wof:name":"Hada Linchang",
    "wof:placetype":"locality"
},
  "geometry": {"coordinates":[121.345,50.415],"type":"Point"}
}