{
  "type": "Feature",
  "properties": {
    "gn:admin1_code":"10.0",
    "gn:asciiname":"Xijiahe",
    "gn:country_code":"CN",
    "gn:dem":56,
    "gn:feature_class":"P",
    "gn:feature_code":"PPL",
    "gn:name":"Xijiahe",
    "gn:population":0,
    "gn:timezone":"Asia/Shanghai",
    "iso:country":"CN",
    "name:zho_x_preferred":[
        "\u897f\u5939\u6cb3"
    ],
    "wof:name":"Xijiahe",
    "wof:placetype":"locality"
},
  "geometry": {"coordinates":[118.63727,40.00608],"type":"Point"}
}