{
  "type": "Feature",
  "properties": {
    "gn:admin1_code":"32.0",
    "gn:asciiname":"Baila",
    "gn:country_code":"CN",
    "gn:dem":496,
    "gn:feature_class":"P",
    "gn:feature_code":"PPL",
    "gn:name":"Baila",
    "gn:population":0,
    "gn:timezone":"Asia/Shanghai",
    "iso:country":"CN",
    "name:fra_x_preferred":[
        "Baila"
    ],
    "name:zho_x_preferred":[
        "\u767d\u8721"
    ],
    "wof:name":"Baila",
    "wof:placetype":"locality"
},
  "geometry": {"coordinates":[103.98699999999999,30.15],"type":"Point"}
}