{
  "type": "Feature",
  "properties": {
    "gn:admin1_code":"33.0",
    "gn:asciiname":"Dianchanggou",
    "gn:country_code":"CN",
    "gn:dem":912,
    "gn:feature_class":"P",
    "gn:feature_code":"PPL",
    "gn:name":"Dianchanggou",
    "gn:population":0,
    "gn:timezone":"Asia/Shanghai",
    "iso:country":"CN",
    "name:zho_x_preferred":[
        "\u975b\u5382\u6c9f"
    ],
    "wof:name":"Dianchanggou",
    "wof:placetype":"locality"
},
  "geometry": {"coordinates":[107.07899999999999,29.0205],"type":"Point"}
}