{
  "type": "Feature",
  "properties": {
    "gn:admin1_code":"4.0",
    "gn:asciiname":"Zhangzhuang",
    "gn:country_code":"CN",
    "gn:dem":2,
    "gn:feature_class":"P",
    "gn:feature_code":"PPL",
    "gn:name":"Zhangzhuang",
    "gn:population":0,
    "gn:timezone":"Asia/Shanghai",
    "iso:country":"CN",
    "name:zho_x_preferred":[
        "Zhangzhuang"
    ],
    "name:zho_x_variant":[
        "\u5f20\u5e84"
    ],
    "wof:name":"Zhangzhuang",
    "wof:placetype":"locality"
},
  "geometry": {"coordinates":[119.27758,34.08871],"type":"Point"}
}