{
  "type": "Feature",
  "properties": {
    "gn:admin1_code":"10",
    "gn:asciiname":"Wulan Hudong",
    "gn:country_code":"CN",
    "gn:dem":1393,
    "gn:feature_class":"P",
    "gn:feature_code":"PPL",
    "gn:name":"Wulan Hudong",
    "gn:population":0,
    "gn:timezone":"Asia/Shanghai",
    "iso:country":"CN",
    "name:zho_x_preferred":[
        "\u4e4c\u5170\u80e1\u6d1e"
    ],
    "wof:name":"Wulan Hudong",
    "wof:placetype":"locality"
},
  "geometry": {"coordinates":[114.77572000000001,41.42992],"type":"Point"}
}