{
  "type": "Feature",
  "properties": {
    "gn:admin1_code":"21.0",
    "gn:asciiname":"Baotoushui",
    "gn:country_code":"CN",
    "gn:dem":1687,
    "gn:feature_class":"P",
    "gn:feature_code":"PPL",
    "gn:name":"Baotoushui",
    "gn:population":0,
    "gn:timezone":"Asia/Shanghai",
    "iso:country":"CN",
    "name:und_x_variant":[
        "\u5305\u5934\u6c34"
    ],
    "name:zho_x_preferred":[
        "\u5305\u5934\u6c34"
    ],
    "wof:name":"Baotoushui",
    "wof:placetype":"locality"
},
  "geometry": {"coordinates":[106.22523,36.7978],"type":"Point"}
}