{
  "type": "Feature",
  "properties": {
    "gn:admin1_code":"26.0",
    "gn:asciiname":"Fengyangzhuang",
    "gn:country_code":"CN",
    "gn:dem":1496,
    "gn:feature_class":"P",
    "gn:feature_code":"PPL",
    "gn:name":"Fengyangzhuang",
    "gn:population":0,
    "gn:timezone":"Asia/Shanghai",
    "iso:country":"CN",
    "name:und_x_variant":[
        "\u51af\u9633\u5e84"
    ],
    "wof:name":"Fengyangzhuang",
    "wof:placetype":"locality"
},
  "geometry": {"coordinates":[107.49316,36.89623],"type":"Point"}
}