{
  "type": "Feature",
  "properties": {
    "gn:admin1_code":"18",
    "gn:asciiname":"Miaogouzhai",
    "gn:country_code":"CN",
    "gn:dem":907,
    "gn:feature_class":"P",
    "gn:feature_code":"PPL",
    "gn:name":"Miaogouzhai",
    "gn:population":0,
    "gn:timezone":"Asia/Shanghai",
    "iso:country":"CN",
    "name:zho_x_preferred":[
        "\u5e99\u6c9f\u5be8"
    ],
    "wof:name":"Miaogouzhai",
    "wof:placetype":"locality"
},
  "geometry": {"coordinates":[108.41500000000001,27.1632],"type":"Point"}
}