{
  "type": "Feature",
  "properties": {
    "gn:admin1_code":"8.0",
    "gn:asciiname":"Shijia Weizi",
    "gn:country_code":"CN",
    "gn:dem":210,
    "gn:feature_class":"P",
    "gn:feature_code":"PPLF",
    "gn:name":"Shijia Weizi",
    "gn:population":0,
    "gn:timezone":"Asia/Shanghai",
    "iso:country":"CN",
    "name:zho_x_preferred":[
        "\u77f3\u5bb6\u56f4\u5b50"
    ],
    "wof:name":"Shijia Weizi",
    "wof:placetype":"locality"
},
  "geometry": {"coordinates":[126.63720000000001,47.75396],"type":"Point"}
}