{
  "type": "Feature",
  "properties": {
    "gn:admin1_code":"29.0",
    "gn:asciiname":"Zhequ",
    "gn:country_code":"CN",
    "gn:dem":1328,
    "gn:feature_class":"P",
    "gn:feature_code":"PPL",
    "gn:name":"Zhequ",
    "gn:population":0,
    "gn:timezone":"Asia/Shanghai",
    "iso:country":"CN",
    "name:zho_x_preferred":[
        "\u8005\u53bb"
    ],
    "wof:name":"Zhequ",
    "wof:placetype":"locality"
},
  "geometry": {"coordinates":[102.976,23.6693],"type":"Point"}
}