{
  "type": "Feature",
  "properties": {
    "gn:admin1_code":"20",
    "gn:asciiname":"Wufendi",
    "gn:cc2":"CN",
    "gn:country_code":"CN",
    "gn:dem":713,
    "gn:feature_class":"P",
    "gn:feature_code":"PPL",
    "gn:name":"Wufendi",
    "gn:population":0,
    "gn:timezone":"Asia/Shanghai",
    "iso:country":"CN",
    "name:und_x_variant":[
        "Wu-fen-ti",
        "Wufendi"
    ],
    "wof:name":"Wufendi",
    "wof:placetype":"locality"
},
  "geometry": {"coordinates":[118.55,43.21667],"type":"Point"}
}