{
  "type": "Feature",
  "properties": {
    "gn:admin1_code":"3.0",
    "gn:asciiname":"Shuangluo",
    "gn:country_code":"CN",
    "gn:dem":368,
    "gn:feature_class":"P",
    "gn:feature_code":"PPL",
    "gn:name":"Shuangluo",
    "gn:population":0,
    "gn:timezone":"Asia/Shanghai",
    "iso:country":"CN",
    "name:und_x_variant":[
        "\u53cc\u7f57"
    ],
    "wof:name":"Shuangluo",
    "wof:placetype":"locality"
},
  "geometry": {"coordinates":[114.60281999999999,24.71],"type":"Point"}
}