{
  "type": "Feature",
  "properties": {
    "gn:admin1_code":"4.0",
    "gn:asciiname":"Xipancun",
    "gn:country_code":"CN",
    "gn:dem":4,
    "gn:feature_class":"P",
    "gn:feature_code":"PPL",
    "gn:name":"Xipancun",
    "gn:population":0,
    "gn:timezone":"Asia/Shanghai",
    "iso:country":"CN",
    "name:zho_x_preferred":[
        "\u897f\u76d8\u6751"
    ],
    "wof:name":"Xipancun",
    "wof:placetype":"locality"
},
  "geometry": {"coordinates":[119.54608,34.26111],"type":"Point"}
}