{
  "type": "Feature",
  "properties": {
    "gn:admin1_code":"8.0",
    "gn:asciiname":"Houkanjiatun",
    "gn:country_code":"CN",
    "gn:dem":129,
    "gn:feature_class":"P",
    "gn:feature_code":"PPL",
    "gn:name":"Houkanjiatun",
    "gn:population":0,
    "gn:timezone":"Asia/Shanghai",
    "iso:country":"CN",
    "name:zho_x_preferred":[
        "\u540e\u574e\u5bb6\u5c6f"
    ],
    "wof:name":"Houkanjiatun",
    "wof:placetype":"locality"
},
  "geometry": {"coordinates":[127.42591000000002,45.99833],"type":"Point"}
}