{
  "type": "Feature",
  "properties": {
    "gn:admin1_code":"29.0",
    "gn:asciiname":"Weixiluogu",
    "gn:country_code":"CN",
    "gn:dem":2277,
    "gn:feature_class":"P",
    "gn:feature_code":"PPL",
    "gn:name":"Weixiluogu",
    "gn:population":0,
    "gn:timezone":"Asia/Shanghai",
    "iso:country":"CN",
    "name:zho_x_preferred":[
        "\u7ef4\u897f\u6d1b\u53e4"
    ],
    "wof:name":"Weixiluogu",
    "wof:placetype":"locality"
},
  "geometry": {"coordinates":[99.0861,27.4359],"type":"Point"}
}