{
  "type": "Feature",
  "properties": {
    "gn:admin1_code":"02",
    "gn:asciiname":"Aolizhao",
    "gn:cc2":"CN",
    "gn:country_code":"CN",
    "gn:dem":97,
    "gn:feature_class":"P",
    "gn:feature_code":"PPL",
    "gn:name":"Aolizhao",
    "gn:population":0,
    "gn:timezone":"Asia/Shanghai",
    "iso:country":"CN",
    "name:und_x_variant":[
        "Ao-li-chao",
        "Aolizhao",
        "\u5c99\u91cc\u8d75"
    ],
    "name:zho_x_preferred":[
        "\u5c99\u91cc\u8d75"
    ],
    "wof:name":"Aolizhao",
    "wof:placetype":"locality"
},
  "geometry": {"coordinates":[121.54083,29.30556],"type":"Point"}
}