{
  "type": "Feature",
  "properties": {
    "gn:admin1_code":"30.0",
    "gn:asciiname":"Taiping Kengkou",
    "gn:country_code":"CN",
    "gn:dem":154,
    "gn:feature_class":"P",
    "gn:feature_code":"PPL",
    "gn:name":"Taiping Kengkou",
    "gn:population":0,
    "gn:timezone":"Asia/Shanghai",
    "iso:country":"CN",
    "name:zho_x_preferred":[
        "\u592a\u5e73\u5751\u53e3"
    ],
    "wof:name":"Taiping Kengkou",
    "wof:placetype":"locality"
},
  "geometry": {"coordinates":[113.29111,25.14028],"type":"Point"}
}