{
  "type": "Feature",
  "properties": {
    "gn:admin1_code":"11.0",
    "gn:asciiname":"Shirui Yuanzi",
    "gn:country_code":"CN",
    "gn:dem":193,
    "gn:feature_class":"P",
    "gn:feature_code":"PPL",
    "gn:name":"Shirui Yuanzi",
    "gn:population":0,
    "gn:timezone":"Asia/Shanghai",
    "iso:country":"CN",
    "name:zho_x_preferred":[
        "\u77f3\u745e\u9662\u5b50"
    ],
    "wof:name":"Shirui Yuanzi",
    "wof:placetype":"locality"
},
  "geometry": {"coordinates":[111.14713,26.36997],"type":"Point"}
}