{
  "type": "Feature",
  "properties": {
    "gn:admin1_code":"6.0",
    "gn:asciiname":"Yatoutan",
    "gn:country_code":"CN",
    "gn:dem":3140,
    "gn:feature_class":"P",
    "gn:feature_code":"PPL",
    "gn:name":"Yatoutan",
    "gn:population":0,
    "gn:timezone":"Asia/Shanghai",
    "iso:country":"CN",
    "name:zho_x_preferred":[
        "\u5d16\u5934\u6ee9"
    ],
    "wof:name":"Yatoutan",
    "wof:placetype":"locality"
},
  "geometry": {"coordinates":[101.54937,36.30087],"type":"Point"}
}