{
  "type": "Feature",
  "properties": {
    "gn:admin1_code":"5.0",
    "gn:asciiname":"Dongweicun",
    "gn:country_code":"CN",
    "gn:dem":165,
    "gn:feature_class":"P",
    "gn:feature_code":"PPL",
    "gn:name":"Dongweicun",
    "gn:population":0,
    "gn:timezone":"Asia/Shanghai",
    "iso:country":"CN",
    "name:zho_x_preferred":[
        "\u4e1c\u5d34\u6751"
    ],
    "wof:name":"Dongweicun",
    "wof:placetype":"locality"
},
  "geometry": {"coordinates":[126.52258,44.41786],"type":"Point"}
}