{
  "type": "Feature",
  "properties": {
    "gn:admin1_code":"4.0",
    "gn:asciiname":"Daye",
    "gn:country_code":"CN",
    "gn:dem":3,
    "gn:feature_class":"P",
    "gn:feature_code":"PPL",
    "gn:name":"Daye",
    "gn:population":0,
    "gn:timezone":"Asia/Shanghai",
    "iso:country":"CN",
    "name:zho_x_preferred":[
        "Daye"
    ],
    "name:zho_x_variant":[
        "\u5927\u53f6"
    ],
    "wof:name":"Daye",
    "wof:placetype":"locality"
},
  "geometry": {"coordinates":[119.42877,33.56273],"type":"Point"}
}