{
  "type": "Feature",
  "properties": {
    "gn:admin1_code":"4.0",
    "gn:asciiname":"Cuizhuang",
    "gn:country_code":"CN",
    "gn:dem":-4,
    "gn:feature_class":"P",
    "gn:feature_code":"PPL",
    "gn:name":"Cuizhuang",
    "gn:population":0,
    "gn:timezone":"Asia/Shanghai",
    "iso:country":"CN",
    "name:zho_x_preferred":[
        "Cuizhuang"
    ],
    "name:zho_x_variant":[
        "\u5d14\u5e84"
    ],
    "wof:name":"Cuizhuang",
    "wof:placetype":"locality"
},
  "geometry": {"coordinates":[120.27861,34.08429],"type":"Point"}
}