{
  "type": "Feature",
  "properties": {
    "gn:admin1_code":"8.0",
    "gn:asciiname":"Anjucun",
    "gn:country_code":"CN",
    "gn:dem":145,
    "gn:feature_class":"P",
    "gn:feature_code":"PPL",
    "gn:name":"Anjucun",
    "gn:population":0,
    "gn:timezone":"Asia/Shanghai",
    "iso:country":"CN",
    "name:zho_x_preferred":[
        "\u5b89\u5c45\u6751"
    ],
    "wof:name":"Anjucun",
    "wof:placetype":"locality"
},
  "geometry": {"coordinates":[126.25577,45.91063],"type":"Point"}
}