{
  "type": "Feature",
  "properties": {
    "gn:admin1_code":"15.0",
    "gn:asciiname":"Lijiashan",
    "gn:country_code":"CN",
    "gn:dem":1423,
    "gn:feature_class":"P",
    "gn:feature_code":"PPL",
    "gn:name":"Lijiashan",
    "gn:population":0,
    "gn:timezone":"Asia/Shanghai",
    "iso:country":"CN",
    "name:und_x_variant":[
        "\u674e\u5bb6\u5c71"
    ],
    "name:zho_x_preferred":[
        "\u674e\u5bb6\u5c71"
    ],
    "wof:name":"Lijiashan",
    "wof:placetype":"locality"
},
  "geometry": {"coordinates":[104.81091000000001,33.01857],"type":"Point"}
}