{
  "type": "Feature",
  "properties": {
    "gn:admin1_code":"8.0",
    "gn:asciiname":"Kuixingcun",
    "gn:country_code":"CN",
    "gn:dem":162,
    "gn:feature_class":"P",
    "gn:feature_code":"PPL",
    "gn:name":"Kuixingcun",
    "gn:population":0,
    "gn:timezone":"Asia/Shanghai",
    "iso:country":"CN",
    "name:zho_x_preferred":[
        "\u594e\u661f\u6751"
    ],
    "wof:name":"Kuixingcun",
    "wof:placetype":"locality"
},
  "geometry": {"coordinates":[125.66352999999999,46.69447],"type":"Point"}
}