{
  "type": "Feature",
  "properties": {
    "gn:admin1_code":"19.0",
    "gn:asciiname":"Yinjiatun",
    "gn:country_code":"CN",
    "gn:dem":100,
    "gn:feature_class":"P",
    "gn:feature_code":"PPL",
    "gn:name":"Yinjiatun",
    "gn:population":0,
    "gn:timezone":"Asia/Shanghai",
    "iso:country":"CN",
    "name:zho_x_preferred":[
        "\u5c39\u5bb6\u5c6f"
    ],
    "wof:name":"Yinjiatun",
    "wof:placetype":"locality"
},
  "geometry": {"coordinates":[120.35612,40.50276],"type":"Point"}
}