{
  "type": "Feature",
  "properties": {
    "gn:admin1_code":"33.0",
    "gn:asciiname":"Baishuishan",
    "gn:country_code":"CN",
    "gn:dem":895,
    "gn:feature_class":"P",
    "gn:feature_code":"PPL",
    "gn:name":"Baishuishan",
    "gn:population":0,
    "gn:timezone":"Asia/Shanghai",
    "iso:country":"CN",
    "name:zho_x_preferred":[
        "\u767e\u6c34\u5c71"
    ],
    "wof:name":"Baishuishan",
    "wof:placetype":"locality"
},
  "geometry": {"coordinates":[110.10285,31.1625],"type":"Point"}
}