{
  "type": "Feature",
  "properties": {
    "gn:admin1_code":"3.0",
    "gn:asciiname":"Xifencun",
    "gn:country_code":"CN",
    "gn:dem":208,
    "gn:feature_class":"P",
    "gn:feature_code":"PPL",
    "gn:name":"Xifencun",
    "gn:population":0,
    "gn:timezone":"Asia/Shanghai",
    "iso:country":"CN",
    "name:und_x_variant":[
        "\u897f\u6c7e\u6751"
    ],
    "wof:name":"Xifencun",
    "wof:placetype":"locality"
},
  "geometry": {"coordinates":[115.57087,26.20083],"type":"Point"}
}