{
  "type": "Feature",
  "properties": {
    "gn:admin1_code":"32.0",
    "gn:asciiname":"Yuchigai",
    "gn:country_code":"CN",
    "gn:dem":745,
    "gn:feature_class":"P",
    "gn:feature_code":"PPL",
    "gn:name":"Yuchigai",
    "gn:population":0,
    "gn:timezone":"Asia/Shanghai",
    "iso:country":"CN",
    "name:zho_x_preferred":[
        "\u9c7c\u6c60\u76d6"
    ],
    "wof:name":"Yuchigai",
    "wof:placetype":"locality"
},
  "geometry": {"coordinates":[105.449,32.1178],"type":"Point"}
}