{
  "type": "Feature",
  "properties": {
    "gn:admin1_code":"29.0",
    "gn:asciiname":"Fatuwo",
    "gn:country_code":"CN",
    "gn:dem":1660,
    "gn:feature_class":"P",
    "gn:feature_code":"PPL",
    "gn:name":"Fatuwo",
    "gn:population":0,
    "gn:timezone":"Asia/Shanghai",
    "iso:country":"CN",
    "name:zho_x_preferred":[
        "\u6cd5\u571f\u7a9d"
    ],
    "wof:name":"Fatuwo",
    "wof:placetype":"locality"
},
  "geometry": {"coordinates":[102.952,26.9675],"type":"Point"}
}