{
  "type": "Feature",
  "properties": {
    "gn:admin1_code":"26.0",
    "gn:asciiname":"Changshacun",
    "gn:country_code":"CN",
    "gn:dem":403,
    "gn:feature_class":"P",
    "gn:feature_code":"PPL",
    "gn:name":"Changshacun",
    "gn:population":0,
    "gn:timezone":"Asia/Shanghai",
    "iso:country":"CN",
    "name:zho_x_preferred":[
        "\u957f\u6c99\u6751"
    ],
    "wof:name":"Changshacun",
    "wof:placetype":"locality"
},
  "geometry": {"coordinates":[109.46916,32.86692],"type":"Point"}
}