{
  "type": "Feature",
  "properties": {
    "gn:admin1_code":"2",
    "gn:asciiname":"Shuangkeng",
    "gn:country_code":"CN",
    "gn:dem":454,
    "gn:feature_class":"P",
    "gn:feature_code":"PPL",
    "gn:name":"Shuangkeng",
    "gn:population":0,
    "gn:timezone":"Asia/Shanghai",
    "iso:country":"CN",
    "name:und_x_variant":[
        "\u53cc\u5751",
        "Shuangkengkou",
        "\u53cc\u5751\u53e3"
    ],
    "wof:name":"Shuangkeng",
    "wof:placetype":"locality"
},
  "geometry": {"coordinates":[119.29163,29.99735],"type":"Point"}
}