{
  "type": "Feature",
  "properties": {
    "gn:admin1_code":"4.0",
    "gn:asciiname":"Sanxin Erzu",
    "gn:country_code":"CN",
    "gn:dem":2,
    "gn:feature_class":"P",
    "gn:feature_code":"PPLF",
    "gn:name":"Sanxin Erzu",
    "gn:population":0,
    "gn:timezone":"Asia/Shanghai",
    "iso:country":"CN",
    "name:zho_x_preferred":[
        "\u4e09\u65b0\u4e8c\u7ec4"
    ],
    "wof:name":"Sanxin Erzu",
    "wof:placetype":"locality"
},
  "geometry": {"coordinates":[120.438,32.9733],"type":"Point"}
}