{
  "type": "Feature",
  "properties": {
    "gn:admin1_code":"15.0",
    "gn:asciiname":"Shengouyan",
    "gn:country_code":"CN",
    "gn:dem":2390,
    "gn:feature_class":"P",
    "gn:feature_code":"PPL",
    "gn:name":"Shengouyan",
    "gn:population":0,
    "gn:timezone":"Asia/Shanghai",
    "iso:country":"CN",
    "name:zho_x_preferred":[
        "\u6df1\u6c9f\u6cbf"
    ],
    "wof:name":"Shengouyan",
    "wof:placetype":"locality"
},
  "geometry": {"coordinates":[103.41500000000001,35.2901],"type":"Point"}
}