{
  "type": "Feature",
  "properties": {
    "gn:admin1_code":"30.0",
    "gn:asciiname":"Yong'anli",
    "gn:country_code":"CN",
    "gn:dem":9,
    "gn:feature_class":"P",
    "gn:feature_code":"PPL",
    "gn:name":"Yong\u2019anli",
    "gn:population":0,
    "gn:timezone":"Asia/Shanghai",
    "iso:country":"CN",
    "name:zho_x_preferred":[
        "\u6c38\u5b89\u91cc"
    ],
    "name:zho_x_variant":[
        "Yong\u2019anli"
    ],
    "wof:name":"Yong'anli",
    "wof:placetype":"locality"
},
  "geometry": {"coordinates":[112.55749,22.32074],"type":"Point"}
}