{
  "type": "Feature",
  "properties": {
    "gn:admin1_code":"26.0",
    "gn:asciiname":"Wangtiebei",
    "gn:country_code":"CN",
    "gn:dem":368,
    "gn:feature_class":"P",
    "gn:feature_code":"PPL",
    "gn:name":"Wangtiebei",
    "gn:population":0,
    "gn:timezone":"Asia/Shanghai",
    "iso:country":"CN",
    "name:zho_x_preferred":[
        "\u738b\u94c1\u5317"
    ],
    "wof:name":"Wangtiebei",
    "wof:placetype":"locality"
},
  "geometry": {"coordinates":[109.33555,34.63061],"type":"Point"}
}