{
  "type": "Feature",
  "properties": {
    "gn:admin1_code":"31",
    "gn:asciiname":"Changzheng Nongchang",
    "gn:country_code":"CN",
    "gn:dem":352,
    "gn:feature_class":"P",
    "gn:feature_code":"PPLF",
    "gn:name":"Changzheng Nongchang",
    "gn:population":0,
    "gn:timezone":"Asia/Shanghai",
    "iso:country":"CN",
    "name:und_x_variant":[
        "\u957f\u5f81\u519c\u573a"
    ],
    "wof:name":"Changzheng Nongchang",
    "wof:placetype":"locality"
},
  "geometry": {"coordinates":[109.88284,18.96424],"type":"Point"}
}