{
  "type": "Feature",
  "properties": {
    "gn:admin1_code":"4.0",
    "gn:asciiname":"Yuhua",
    "gn:country_code":"CN",
    "gn:dem":46,
    "gn:feature_class":"P",
    "gn:feature_code":"PPL",
    "gn:name":"Yuhua",
    "gn:population":0,
    "gn:timezone":"Asia/Shanghai",
    "iso:country":"CN",
    "name:zho_x_preferred":[
        "\u96e8\u82b1"
    ],
    "wof:name":"Yuhua",
    "wof:placetype":"locality"
},
  "geometry": {"coordinates":[118.76971,31.99152],"type":"Point"}
}