{
  "type": "Feature",
  "properties": {
    "gn:admin1_code":"11",
    "gn:asciiname":"Sangongqiao",
    "gn:country_code":"CN",
    "gn:dem":215,
    "gn:feature_class":"P",
    "gn:feature_code":"PPLA4",
    "gn:name":"Sangongqiao",
    "gn:population":0,
    "gn:timezone":"Asia/Shanghai",
    "iso:country":"CN",
    "name:und_x_variant":[
        "Sangongqiao Xiang"
    ],
    "name:zho_x_preferred":[
        "\u4e09\u62f1\u6865"
    ],
    "name:zho_x_variant":[
        "\u4e09\u62f1\u6865\u4e61"
    ],
    "wof:name":"Sangongqiao",
    "wof:placetype":"locality"
},
  "geometry": {"coordinates":[109.64798999999999,28.18843],"type":"Point"}
}