{
  "type": "Feature",
  "properties": {
    "gn:admin1_code":"19.0",
    "gn:asciiname":"Wendonggoucun",
    "gn:country_code":"CN",
    "gn:dem":74,
    "gn:feature_class":"P",
    "gn:feature_code":"PPL",
    "gn:name":"Wendonggoucun",
    "gn:population":0,
    "gn:timezone":"Asia/Shanghai",
    "iso:country":"CN",
    "name:zho_x_preferred":[
        "\u6587\u6d1e\u6c9f\u6751"
    ],
    "wof:name":"Wendonggoucun",
    "wof:placetype":"locality"
},
  "geometry": {"coordinates":[122.98,41.002],"type":"Point"}
}