{
  "type": "Feature",
  "properties": {
    "gn:admin1_code":"21.0",
    "gn:asciiname":"Miao'ershan",
    "gn:country_code":"CN",
    "gn:dem":1936,
    "gn:feature_class":"P",
    "gn:feature_code":"PPL",
    "gn:name":"Miao\u2019ershan",
    "gn:population":0,
    "gn:timezone":"Asia/Shanghai",
    "iso:country":"CN",
    "name:und_x_variant":[
        "Miao\u2019ershan"
    ],
    "name:zho_x_preferred":[
        "\u5e99\u513f\u5c71"
    ],
    "wof:name":"Miao'ershan",
    "wof:placetype":"locality"
},
  "geometry": {"coordinates":[106.413,35.6197],"type":"Point"}
}