{
  "type": "Feature",
  "properties": {
    "gn:admin1_code":"15.0",
    "gn:asciiname":"Bulongji",
    "gn:country_code":"CN",
    "gn:dem":1344,
    "gn:feature_class":"P",
    "gn:feature_code":"PPLA4",
    "gn:name":"Bulongji",
    "gn:population":0,
    "gn:timezone":"Asia/Urumqi",
    "iso:country":"CN",
    "name:und_x_variant":[
        "Pu-lung-chi",
        "Bulungir",
        "Pu-lung-ch\u2019i Ch\u2019eng",
        "Pulungki",
        "Bulingar",
        "Bulongji",
        "Bulongji Xiang"
    ],
    "name:zho_x_preferred":[
        "\u5e03\u9686\u5409"
    ],
    "name:zho_x_variant":[
        "\u5e03\u9686\u5409\u4e61"
    ],
    "wof:name":"Bulongji",
    "wof:placetype":"locality"
},
  "geometry": {"coordinates":[96.54102,40.53087],"type":"Point"}
}