{
  "type": "Feature",
  "properties": {
    "gn:admin1_code":"29.0",
    "gn:asciiname":"Shuiyuan",
    "gn:country_code":"CN",
    "gn:dem":1381,
    "gn:feature_class":"P",
    "gn:feature_code":"PPL",
    "gn:name":"Shuiyuan",
    "gn:population":0,
    "gn:timezone":"Asia/Shanghai",
    "iso:country":"CN",
    "name:zho_x_preferred":[
        "\u6c34\u6e90"
    ],
    "wof:name":"Shuiyuan",
    "wof:placetype":"locality"
},
  "geometry": {"coordinates":[103.176,22.9499],"type":"Point"}
}