{
  "type": "Feature",
  "properties": {
    "gn:admin1_code":"12.0",
    "gn:asciiname":"Genminyuan",
    "gn:country_code":"CN",
    "gn:dem":34,
    "gn:feature_class":"P",
    "gn:feature_code":"PPL",
    "gn:name":"Genminyuan",
    "gn:population":0,
    "gn:timezone":"Asia/Shanghai",
    "iso:country":"CN",
    "name:zho_x_preferred":[
        "\u6839\u6c11\u57b8"
    ],
    "wof:name":"Genminyuan",
    "wof:placetype":"locality"
},
  "geometry": {"coordinates":[112.34363999999999,29.5957],"type":"Point"}
}