{
  "type": "Feature",
  "properties": {
    "gn:admin1_code":"26",
    "gn:asciiname":"Qianshizui",
    "gn:cc2":"CN",
    "gn:country_code":"CN",
    "gn:dem":1474,
    "gn:feature_class":"P",
    "gn:feature_code":"PPL",
    "gn:name":"Qianshizui",
    "gn:population":0,
    "gn:timezone":"Asia/Shanghai",
    "iso:country":"CN",
    "name:und_x_variant":[
        "Ch\u2019ien-shih-tsui",
        "Qianshizui"
    ],
    "wof:name":"Qianshizui",
    "wof:placetype":"locality"
},
  "geometry": {"coordinates":[108.76667,37.18333],"type":"Point"}
}