{
  "type": "Feature",
  "properties": {
    "gn:admin1_code":"19.0",
    "gn:asciiname":"Shangfucheng",
    "gn:country_code":"CN",
    "gn:dem":199,
    "gn:feature_class":"P",
    "gn:feature_code":"PPL",
    "gn:name":"Shangfucheng",
    "gn:population":0,
    "gn:timezone":"Asia/Shanghai",
    "iso:country":"CN",
    "name:und_x_variant":[
        "\u4e0a\u798f\u57ce"
    ],
    "wof:name":"Shangfucheng",
    "wof:placetype":"locality"
},
  "geometry": {"coordinates":[122.96243,40.11533],"type":"Point"}
}