{
  "type": "Feature",
  "properties": {
    "gn:admin1_code":"29.0",
    "gn:asciiname":"Huzhang Xiazhai",
    "gn:country_code":"CN",
    "gn:dem":1602,
    "gn:feature_class":"P",
    "gn:feature_code":"PPL",
    "gn:name":"Huzhang Xiazhai",
    "gn:population":0,
    "gn:timezone":"Asia/Shanghai",
    "iso:country":"CN",
    "name:zho_x_preferred":[
        "\u6237\u638c\u4e0b\u5be8"
    ],
    "wof:name":"Huzhang Xiazhai",
    "wof:placetype":"locality"
},
  "geometry": {"coordinates":[98.3546,24.2305],"type":"Point"}
}