{
  "type": "Feature",
  "properties": {
    "gn:admin1_code":"19",
    "gn:asciiname":"Hsing-ching-erh-tao-kou",
    "gn:country_code":"CN",
    "gn:dem":412,
    "gn:feature_class":"P",
    "gn:feature_code":"PPL",
    "gn:name":"Hsing-ching-erh-tao-kou",
    "gn:population":0,
    "gn:timezone":"Asia/Shanghai",
    "iso:country":"CN",
    "wof:name":"Hsing-ching-erh-tao-kou",
    "wof:placetype":"locality"
},
  "geometry": {"coordinates":[125.31778,41.64111],"type":"Point"}
}