{
  "type": "Feature",
  "properties": {
    "gn:admin1_code":"25.0",
    "gn:asciiname":"Wangmenzhuang",
    "gn:country_code":"CN",
    "gn:dem":76,
    "gn:feature_class":"P",
    "gn:feature_code":"PPL",
    "gn:name":"Wangmenzhuang",
    "gn:population":0,
    "gn:timezone":"Asia/Shanghai",
    "iso:country":"CN",
    "name:zho_x_preferred":[
        "\u738b\u95e8\u5e84"
    ],
    "wof:name":"Wangmenzhuang",
    "wof:placetype":"locality"
},
  "geometry": {"coordinates":[119.35254999999999,35.93955],"type":"Point"}
}