{
  "type": "Feature",
  "properties": {
    "gn:admin1_code":"2.0",
    "gn:asciiname":"Fuyuan",
    "gn:country_code":"CN",
    "gn:dem":14,
    "gn:feature_class":"P",
    "gn:feature_code":"PPL",
    "gn:name":"Fuyuan",
    "gn:population":0,
    "gn:timezone":"Asia/Shanghai",
    "iso:country":"CN",
    "name:ceb_x_preferred":[
        "Fuyuan"
    ],
    "name:deu_x_preferred":[
        "Fuyuan"
    ],
    "name:eus_x_preferred":[
        "Fuyuan"
    ],
    "name:fra_x_preferred":[
        "Fuyuan"
    ],
    "name:kor_x_preferred":[
        "\ud478\uc704\uc548"
    ],
    "name:mlg_x_preferred":[
        "Fuyuan"
    ],
    "name:nor_x_preferred":[
        "Fuyuan"
    ],
    "name:rus_x_preferred":[
        "\u0424\u0443\u044e\u0430\u043d\u044c"
    ],
    "name:swe_x_preferred":[
        "Fuyuan"
    ],
    "name:und_x_variant":[
        "\u5bcc\u6e90"
    ],
    "wof:name":"Fuyuan",
    "wof:placetype":"locality"
},
  "geometry": {"coordinates":[119.94825,30.01667],"type":"Point"}
}