{
  "type": "Feature",
  "properties": {
    "gn:admin1_code":"26.0",
    "gn:asciiname":"Fengshuping",
    "gn:country_code":"CN",
    "gn:dem":888,
    "gn:feature_class":"P",
    "gn:feature_code":"PPL",
    "gn:name":"Fengshuping",
    "gn:population":0,
    "gn:timezone":"Asia/Shanghai",
    "iso:country":"CN",
    "name:zho_x_preferred":[
        "\u67ab\u6811\u576a"
    ],
    "wof:name":"Fengshuping",
    "wof:placetype":"locality"
},
  "geometry": {"coordinates":[109.64456,32.86168],"type":"Point"}
}