{
  "type": "Feature",
  "properties": {
    "gn:admin1_code":"30.0",
    "gn:asciiname":"Qianpuchengcun",
    "gn:country_code":"CN",
    "gn:dem":20,
    "gn:feature_class":"P",
    "gn:feature_code":"PPL",
    "gn:name":"Qianpuchengcun",
    "gn:population":0,
    "gn:timezone":"Asia/Shanghai",
    "iso:country":"CN",
    "name:zho_x_preferred":[
        "\u524d\u57d4\u57d5\u6751"
    ],
    "wof:name":"Qianpuchengcun",
    "wof:placetype":"locality"
},
  "geometry": {"coordinates":[117.01934,23.4202],"type":"Point"}
}