{
  "type": "Feature",
  "properties": {
    "gn:admin1_code":"32.0",
    "gn:asciiname":"Hutousi",
    "gn:country_code":"CN",
    "gn:dem":518,
    "gn:feature_class":"P",
    "gn:feature_code":"PPL",
    "gn:name":"Hutousi",
    "gn:population":0,
    "gn:timezone":"Asia/Shanghai",
    "iso:country":"CN",
    "name:zho_x_preferred":[
        "\u864e\u5934\u5bfa"
    ],
    "wof:name":"Hutousi",
    "wof:placetype":"locality"
},
  "geometry": {"coordinates":[105.685,32.3535],"type":"Point"}
}