{
  "type": "Feature",
  "properties": {
    "gn:admin1_code":"8.0",
    "gn:asciiname":"Dahejia Wopeng",
    "gn:country_code":"CN",
    "gn:dem":132,
    "gn:feature_class":"P",
    "gn:feature_code":"PPL",
    "gn:name":"Dahejia Wopeng",
    "gn:population":0,
    "gn:timezone":"Asia/Shanghai",
    "iso:country":"CN",
    "name:zho_x_preferred":[
        "\u5927\u4f55\u5bb6\u7a9d\u68da"
    ],
    "wof:name":"Dahejia Wopeng",
    "wof:placetype":"locality"
},
  "geometry": {"coordinates":[124.62649999999999,45.94739000000001],"type":"Point"}
}