{
  "type": "Feature",
  "properties": {
    "gn:admin1_code":"4.0",
    "gn:asciiname":"Panjiazhuang",
    "gn:country_code":"CN",
    "gn:dem":8,
    "gn:feature_class":"P",
    "gn:feature_code":"PPL",
    "gn:name":"Panjiazhuang",
    "gn:population":0,
    "gn:timezone":"Asia/Shanghai",
    "iso:country":"CN",
    "name:und_x_variant":[
        "Panyuan"
    ],
    "name:zho_x_preferred":[
        "\u6f58\u5bb6\u5e84"
    ],
    "name:zho_x_variant":[
        "\u6f58\u5143"
    ],
    "wof:name":"Panjiazhuang",
    "wof:placetype":"locality"
},
  "geometry": {"coordinates":[120.20469,32.32332],"type":"Point"}
}