{
  "type": "Feature",
  "properties": {
    "gn:admin1_code":"1.0",
    "gn:asciiname":"Houshidiancun",
    "gn:country_code":"CN",
    "gn:dem":37,
    "gn:feature_class":"P",
    "gn:feature_code":"PPL",
    "gn:name":"Houshidiancun",
    "gn:population":0,
    "gn:timezone":"Asia/Shanghai",
    "iso:country":"CN",
    "name:zho_x_preferred":[
        "\u540e\u5e08\u5e97\u6751"
    ],
    "wof:name":"Houshidiancun",
    "wof:placetype":"locality"
},
  "geometry": {"coordinates":[115.86461,33.63131],"type":"Point"}
}