{
  "type": "Feature",
  "properties": {
    "gn:admin1_code":"18.0",
    "gn:asciiname":"Dabanxi",
    "gn:country_code":"CN",
    "gn:dem":836,
    "gn:feature_class":"P",
    "gn:feature_code":"PPL",
    "gn:name":"Dabanxi",
    "gn:population":0,
    "gn:timezone":"Asia/Shanghai",
    "iso:country":"CN",
    "name:zho_x_preferred":[
        "\u5927\u677f\u7ec6"
    ],
    "wof:name":"Dabanxi",
    "wof:placetype":"locality"
},
  "geometry": {"coordinates":[108.06399999999999,26.8193],"type":"Point"}
}