{
  "type": "Feature",
  "properties": {
    "gn:admin1_code":"16.0",
    "gn:asciiname":"Liuhuai",
    "gn:country_code":"CN",
    "gn:dem":192,
    "gn:feature_class":"P",
    "gn:feature_code":"PPL",
    "gn:name":"Liuhuai",
    "gn:population":0,
    "gn:timezone":"Asia/Shanghai",
    "iso:country":"CN",
    "name:zho_x_preferred":[
        "\u516d\u69d0"
    ],
    "wof:name":"Liuhuai",
    "wof:placetype":"locality"
},
  "geometry": {"coordinates":[109.35299999999999,22.5056],"type":"Point"}
}