{
  "type": "Feature",
  "properties": {
    "gn:admin1_code":"11.0",
    "gn:asciiname":"Zhongjiali",
    "gn:country_code":"CN",
    "gn:dem":183,
    "gn:feature_class":"P",
    "gn:feature_code":"PPL",
    "gn:name":"Zhongjiali",
    "gn:population":0,
    "gn:timezone":"Asia/Shanghai",
    "iso:country":"CN",
    "name:und_x_variant":[
        "Yinjiaci"
    ],
    "name:zho_x_preferred":[
        "\u949f\u5bb6\u91cc"
    ],
    "name:zho_x_variant":[
        "\u5c39\u5bb6\u7960"
    ],
    "wof:name":"Zhongjiali",
    "wof:placetype":"locality"
},
  "geometry": {"coordinates":[113.55186,26.8935],"type":"Point"}
}