{
  "type": "Feature",
  "properties": {
    "gn:admin1_code":"8.0",
    "gn:asciiname":"Linjiangcun",
    "gn:country_code":"CN",
    "gn:dem":120,
    "gn:feature_class":"P",
    "gn:feature_code":"PPL",
    "gn:name":"Linjiangcun",
    "gn:population":0,
    "gn:timezone":"Asia/Shanghai",
    "iso:country":"CN",
    "name:zho_x_preferred":[
        "\u4e34\u6c5f\u6751"
    ],
    "wof:name":"Linjiangcun",
    "wof:placetype":"locality"
},
  "geometry": {"coordinates":[126.23968000000001,45.71849],"type":"Point"}
}