{
  "type": "Feature",
  "properties": {
    "gn:admin1_code":"7.0",
    "gn:asciiname":"Daheshan",
    "gn:country_code":"CN",
    "gn:dem":508,
    "gn:feature_class":"P",
    "gn:feature_code":"PPL",
    "gn:name":"Daheshan",
    "gn:population":0,
    "gn:timezone":"Asia/Shanghai",
    "iso:country":"CN",
    "name:zho_x_preferred":[
        "\u5927\u79be\u5c71"
    ],
    "wof:name":"Daheshan",
    "wof:placetype":"locality"
},
  "geometry": {"coordinates":[117.15548,27.6009],"type":"Point"}
}