{
  "type": "Feature",
  "properties": {
    "gn:admin1_code":"03",
    "gn:asciiname":"Luxi",
    "gn:country_code":"CN",
    "gn:dem":143,
    "gn:feature_class":"P",
    "gn:feature_code":"PPLA3",
    "gn:name":"Luxi",
    "gn:population":0,
    "gn:timezone":"Asia/Shanghai",
    "iso:country":"CN",
    "name:und_x_variant":[
        "Lu-hsi",
        "Luxi",
        "\u82a6\u6eaa",
        "Luxi Zhen",
        "Luxi Xian",
        "\u82a6\u6eaa\u9547",
        "\u82a6\u6eaa\u53bf"
    ],
    "wof:name":"Luxi",
    "wof:placetype":"locality"
},
  "geometry": {"coordinates":[114.03529,27.63618],"type":"Point"}
}