{
  "type": "Feature",
  "properties": {
    "gn:admin1_code":"26.0",
    "gn:asciiname":"Dangjiacun",
    "gn:country_code":"CN",
    "gn:dem":1172,
    "gn:feature_class":"P",
    "gn:feature_code":"PPL",
    "gn:name":"Dangjiacun",
    "gn:population":0,
    "gn:timezone":"Asia/Shanghai",
    "iso:country":"CN",
    "name:zho_x_preferred":[
        "\u515a\u5bb6\u6751"
    ],
    "wof:name":"Dangjiacun",
    "wof:placetype":"locality"
},
  "geometry": {"coordinates":[108.42923,34.92412],"type":"Point"}
}