{
  "type": "Feature",
  "properties": {
    "gn:admin1_code":"29.0",
    "gn:asciiname":"Shantoujie",
    "gn:country_code":"CN",
    "gn:dem":1747,
    "gn:feature_class":"P",
    "gn:feature_code":"PPL",
    "gn:name":"Shantoujie",
    "gn:population":0,
    "gn:timezone":"Asia/Shanghai",
    "iso:country":"CN",
    "name:zho_x_preferred":[
        "\u5c71\u5934\u8857"
    ],
    "wof:name":"Shantoujie",
    "wof:placetype":"locality"
},
  "geometry": {"coordinates":[99.46259999999999,24.6874],"type":"Point"}
}