{
  "type": "Feature",
  "properties": {
    "gn:admin1_code":"8.0",
    "gn:asciiname":"Lixingcun",
    "gn:country_code":"CN",
    "gn:dem":119,
    "gn:feature_class":"P",
    "gn:feature_code":"PPL",
    "gn:name":"Lixingcun",
    "gn:population":0,
    "gn:timezone":"Asia/Shanghai",
    "iso:country":"CN",
    "name:zho_x_preferred":[
        "\u7acb\u5174\u6751"
    ],
    "wof:name":"Lixingcun",
    "wof:placetype":"locality"
},
  "geometry": {"coordinates":[127.45811999999999,45.98723],"type":"Point"}
}