{
  "type": "Feature",
  "properties": {
    "gn:admin1_code":"15.0",
    "gn:asciiname":"Chashugou",
    "gn:country_code":"CN",
    "gn:dem":2521,
    "gn:feature_class":"P",
    "gn:feature_code":"PPL",
    "gn:name":"Chashugou",
    "gn:population":0,
    "gn:timezone":"Asia/Shanghai",
    "iso:country":"CN",
    "name:zho_x_preferred":[
        "\u8336\u6811\u6c9f"
    ],
    "wof:name":"Chashugou",
    "wof:placetype":"locality"
},
  "geometry": {"coordinates":[102.988,37.3284],"type":"Point"}
}