{
  "type": "Feature",
  "properties": {
    "gn:admin1_code":"26.0",
    "gn:asciiname":"Zhaigoucun",
    "gn:country_code":"CN",
    "gn:dem":1222,
    "gn:feature_class":"P",
    "gn:feature_code":"PPL",
    "gn:name":"Zhaigoucun",
    "gn:population":0,
    "gn:timezone":"Asia/Shanghai",
    "iso:country":"CN",
    "name:zho_x_preferred":[
        "\u5be8\u6c9f\u6751"
    ],
    "wof:name":"Zhaigoucun",
    "wof:placetype":"locality"
},
  "geometry": {"coordinates":[110.00721,33.90846],"type":"Point"}
}