{
  "type": "Feature",
  "properties": {
    "gn:admin1_code":"15.0",
    "gn:asciiname":"Beidaqiao",
    "gn:country_code":"CN",
    "gn:dem":1173,
    "gn:feature_class":"P",
    "gn:feature_code":"PPL",
    "gn:name":"Beidaqiao",
    "gn:population":0,
    "gn:timezone":"Asia/Urumqi",
    "iso:country":"CN",
    "name:und_x_variant":[
        "Pei-ta-ch\u2019iao",
        "Beidaqiao"
    ],
    "name:zho_x_preferred":[
        "\u5317\u5927\u6865"
    ],
    "wof:name":"Beidaqiao",
    "wof:placetype":"locality"
},
  "geometry": {"coordinates":[95.76909999999999,40.5568],"type":"Point"}
}