{
  "type": "Feature",
  "properties": {
    "gn:admin1_code":"9.0",
    "gn:asciiname":"Kongwangzhuang",
    "gn:country_code":"CN",
    "gn:dem":54,
    "gn:feature_class":"P",
    "gn:feature_code":"PPL",
    "gn:name":"Kongwangzhuang",
    "gn:population":0,
    "gn:timezone":"Asia/Shanghai",
    "iso:country":"CN",
    "name:zho_x_preferred":[
        "\u5b54\u738b\u5e84"
    ],
    "wof:name":"Kongwangzhuang",
    "wof:placetype":"locality"
},
  "geometry": {"coordinates":[114.38639999999999,32.98443],"type":"Point"}
}