{
  "type": "Feature",
  "properties": {
    "gn:admin1_code":"2.0",
    "gn:asciiname":"Tashitou",
    "gn:country_code":"CN",
    "gn:dem":195,
    "gn:feature_class":"P",
    "gn:feature_code":"PPL",
    "gn:name":"Tashitou",
    "gn:population":0,
    "gn:timezone":"Asia/Shanghai",
    "iso:country":"CN",
    "name:zho_x_preferred":[
        "\u5854\u77f3\u5934"
    ],
    "wof:name":"Tashitou",
    "wof:placetype":"locality"
},
  "geometry": {"coordinates":[119.96731,28.98451],"type":"Point"}
}