{
  "type": "Feature",
  "properties": {
    "gn:admin1_code":"16.0",
    "gn:asciiname":"Dongxin",
    "gn:country_code":"CN",
    "gn:dem":503,
    "gn:feature_class":"P",
    "gn:feature_code":"PPL",
    "gn:name":"Dongxin",
    "gn:population":0,
    "gn:timezone":"Asia/Shanghai",
    "iso:country":"CN",
    "name:zho_x_preferred":[
        "\u61c2\u4fe1"
    ],
    "wof:name":"Dongxin",
    "wof:placetype":"locality"
},
  "geometry": {"coordinates":[107.18300000000001,25.4023],"type":"Point"}
}