{
  "type": "Feature",
  "properties": {
    "gn:admin1_code":"26",
    "gn:asciiname":"Sanqiao",
    "gn:country_code":"CN",
    "gn:dem":390,
    "gn:feature_class":"P",
    "gn:feature_code":"PPLA4",
    "gn:name":"Sanqiao",
    "gn:population":0,
    "gn:timezone":"Asia/Shanghai",
    "iso:country":"CN",
    "name:deu_x_preferred":[
        "Sanqiao"
    ],
    "name:und_x_variant":[
        "San-ch\u2019iao",
        "San-ch\u2019iao-chen",
        "Sanqiao Jieban",
        "Sanqiao"
    ],
    "name:zho_x_preferred":[
        "\u4e09\u6865"
    ],
    "name:zho_x_variant":[
        "\u4e09\u6865\u8857\u529e"
    ],
    "wof:name":"Sanqiao",
    "wof:placetype":"locality"
},
  "geometry": {"coordinates":[108.83553000000001,34.28684000000001],"type":"Point"}
}