{
  "type": "Feature",
  "properties": {
    "gn:admin1_code":"5.0",
    "gn:asciiname":"Yinshan Linchang",
    "gn:country_code":"CN",
    "gn:dem":757,
    "gn:feature_class":"P",
    "gn:feature_code":"PPLF",
    "gn:name":"Yinshan Linchang",
    "gn:population":0,
    "gn:timezone":"Asia/Shanghai",
    "iso:country":"CN",
    "name:und_x_variant":[
        "\u94f6\u5c71\u6797\u573a"
    ],
    "wof:name":"Yinshan Linchang",
    "wof:placetype":"locality"
},
  "geometry": {"coordinates":[127.26179999999999,42.04692],"type":"Point"}
}