{
  "type": "Feature",
  "properties": {
    "gn:admin1_code":"32.0",
    "gn:asciiname":"Banruo'an",
    "gn:country_code":"CN",
    "gn:dem":419,
    "gn:feature_class":"P",
    "gn:feature_code":"PPL",
    "gn:name":"Banruo\u2019an",
    "gn:population":0,
    "gn:timezone":"Asia/Shanghai",
    "iso:country":"CN",
    "name:und_x_variant":[
        "Banruo\u2019an"
    ],
    "name:zho_x_preferred":[
        "\u822c\u82e5\u5eb5"
    ],
    "wof:name":"Banruo'an",
    "wof:placetype":"locality"
},
  "geometry": {"coordinates":[106.145,31.4909],"type":"Point"}
}