{
  "type": "Feature",
  "properties": {
    "gn:admin1_code":"29.0",
    "gn:asciiname":"Maidixin",
    "gn:country_code":"CN",
    "gn:dem":2167,
    "gn:feature_class":"P",
    "gn:feature_code":"PPL",
    "gn:name":"Maidixin",
    "gn:population":0,
    "gn:timezone":"Asia/Shanghai",
    "iso:country":"CN",
    "name:zho_x_preferred":[
        "\u9ea6\u5730\u5fc3"
    ],
    "wof:name":"Maidixin",
    "wof:placetype":"locality"
},
  "geometry": {"coordinates":[103.117,25.7355],"type":"Point"}
}