{
  "type": "Feature",
  "properties": {
    "gn:admin1_code":"16.0",
    "gn:asciiname":"Tanyuan",
    "gn:country_code":"CN",
    "gn:dem":181,
    "gn:feature_class":"P",
    "gn:feature_code":"PPL",
    "gn:name":"Tanyuan",
    "gn:population":0,
    "gn:timezone":"Asia/Shanghai",
    "iso:country":"CN",
    "name:zho_x_preferred":[
        "\u575b\u5143"
    ],
    "wof:name":"Tanyuan",
    "wof:placetype":"locality"
},
  "geometry": {"coordinates":[108.426,23.1852],"type":"Point"}
}