{
  "type": "Feature",
  "properties": {
    "gn:admin1_code":"9",
    "gn:asciiname":"Zhuantan",
    "gn:country_code":"CN",
    "gn:dem":70,
    "gn:feature_class":"P",
    "gn:feature_code":"PPLA4",
    "gn:name":"Zhuantan",
    "gn:population":0,
    "gn:timezone":"Asia/Shanghai",
    "iso:country":"CN",
    "name:und_x_variant":[
        "\u4e13\u63a2",
        "Zhuantan Xiang",
        "\u4e13\u63a2\u4e61"
    ],
    "wof:name":"Zhuantan",
    "wof:placetype":"locality"
},
  "geometry": {"coordinates":[113.90334,33.33659],"type":"Point"}
}