{
  "type": "Feature",
  "properties": {
    "gn:admin1_code":"16.0",
    "gn:asciiname":"Luoma",
    "gn:country_code":"CN",
    "gn:dem":623,
    "gn:feature_class":"P",
    "gn:feature_code":"PPL",
    "gn:name":"Luoma",
    "gn:population":0,
    "gn:timezone":"Asia/Shanghai",
    "iso:country":"CN",
    "name:ceb_x_preferred":[
        "Luoma"
    ],
    "name:deu_x_preferred":[
        "Luoma"
    ],
    "name:fin_x_preferred":[
        "Luoma"
    ],
    "name:rus_x_preferred":[
        "\u041b\u0443\u043e\u043c\u0430"
    ],
    "name:swe_x_preferred":[
        "Luoma"
    ],
    "name:zho_x_preferred":[
        "\u9a86\u9a6c"
    ],
    "wof:name":"Luoma",
    "wof:placetype":"locality"
},
  "geometry": {"coordinates":[107.56100000000001,24.9036],"type":"Point"}
}