{
  "type": "Feature",
  "properties": {
    "gn:admin1_code":"16.0",
    "gn:asciiname":"Tianlao",
    "gn:country_code":"CN",
    "gn:dem":546,
    "gn:feature_class":"P",
    "gn:feature_code":"PPL",
    "gn:name":"Tianlao",
    "gn:population":0,
    "gn:timezone":"Asia/Shanghai",
    "iso:country":"CN",
    "name:zho_x_preferred":[
        "\u7530\u52b3"
    ],
    "wof:name":"Tianlao",
    "wof:placetype":"locality"
},
  "geometry": {"coordinates":[110.35899999999999,24.0788],"type":"Point"}
}