{
  "type": "Feature",
  "properties": {
    "gn:admin1_code":"15.0",
    "gn:asciiname":"Wangwan",
    "gn:country_code":"CN",
    "gn:dem":2007,
    "gn:feature_class":"P",
    "gn:feature_code":"PPL",
    "gn:name":"Wangwan",
    "gn:population":0,
    "gn:timezone":"Asia/Shanghai",
    "iso:country":"CN",
    "name:und_x_variant":[
        "\u738b\u6e7e"
    ],
    "wof:name":"Wangwan",
    "wof:placetype":"locality"
},
  "geometry": {"coordinates":[105.43322999999999,35.48998],"type":"Point"}
}