{
  "type": "Feature",
  "properties": {
    "gn:admin1_code":"19.0",
    "gn:asciiname":"Yinjianggoucun",
    "gn:country_code":"CN",
    "gn:dem":101,
    "gn:feature_class":"P",
    "gn:feature_code":"PPL",
    "gn:name":"Yinjianggoucun",
    "gn:population":0,
    "gn:timezone":"Asia/Shanghai",
    "iso:country":"CN",
    "name:zho_x_preferred":[
        "\u94f6\u5320\u6c9f\u6751"
    ],
    "wof:name":"Yinjianggoucun",
    "wof:placetype":"locality"
},
  "geometry": {"coordinates":[120.85599999999999,41.1571],"type":"Point"}
}