{
  "type": "Feature",
  "properties": {
    "gn:admin1_code":"25",
    "gn:asciiname":"Jingwangzhuang",
    "gn:country_code":"CN",
    "gn:dem":395,
    "gn:feature_class":"P",
    "gn:feature_code":"PPL",
    "gn:name":"Jingwangzhuang",
    "gn:population":0,
    "gn:timezone":"Asia/Shanghai",
    "iso:country":"CN",
    "name:zho_x_preferred":[
        "\u4e95\u65fa\u5e84"
    ],
    "wof:name":"Jingwangzhuang",
    "wof:placetype":"locality"
},
  "geometry": {"coordinates":[118.063,35.9892],"type":"Point"}
}