{
  "type": "Feature",
  "properties": {
    "gn:admin1_code":"12.0",
    "gn:asciiname":"Guoshan",
    "gn:country_code":"CN",
    "gn:dem":496,
    "gn:feature_class":"P",
    "gn:feature_code":"PPL",
    "gn:name":"Guoshan",
    "gn:population":0,
    "gn:timezone":"Asia/Shanghai",
    "iso:country":"CN",
    "name:zho_x_preferred":[
        "\u90ed\u5c71"
    ],
    "wof:name":"Guoshan",
    "wof:placetype":"locality"
},
  "geometry": {"coordinates":[111.01217,32.89041],"type":"Point"}
}