{
  "type": "Feature",
  "properties": {
    "gn:admin1_code":"24.0",
    "gn:asciiname":"Jing'ershang",
    "gn:country_code":"CN",
    "gn:dem":1515,
    "gn:feature_class":"P",
    "gn:feature_code":"PPL",
    "gn:name":"Jing\u2019ershang",
    "gn:population":0,
    "gn:timezone":"Asia/Shanghai",
    "iso:country":"CN",
    "name:und_x_variant":[
        "Jing\u2019ershang"
    ],
    "name:zho_x_preferred":[
        "\u4e95\u513f\u4e0a"
    ],
    "wof:name":"Jing'ershang",
    "wof:placetype":"locality"
},
  "geometry": {"coordinates":[111.43473,38.61166],"type":"Point"}
}