{
  "type": "Feature",
  "properties": {
    "gn:country":"CN",
    "gn:fcode":"PPL",
    "gn:population":1200,
    "iso:country":"CN",
    "name:und_x_variant":[
        "Kuo-fu"
    ],
    "qs:name":"Guofuchang",
    "qs:photos_9r":0,
    "qs:photos_sr":0,
    "qs:pop_sr":"3",
    "wof:name":"Guofuchang",
    "wof:placetype":"locality",
    "wof:population":1200
},
  "geometry": {"coordinates":[106.60138999999999,28.85],"type":"Point"}
}