{
  "type": "Feature",
  "properties": {
    "gn:admin1_code":"12.0",
    "gn:asciiname":"Lumiantang",
    "gn:country_code":"CN",
    "gn:dem":82,
    "gn:feature_class":"P",
    "gn:feature_code":"PPL",
    "gn:name":"Lumiantang",
    "gn:population":0,
    "gn:timezone":"Asia/Shanghai",
    "iso:country":"CN",
    "name:zho_x_preferred":[
        "Lumiantang"
    ],
    "name:zho_x_variant":[
        "\u9e7f\u7720\u5858"
    ],
    "wof:name":"Lumiantang",
    "wof:placetype":"locality"
},
  "geometry": {"coordinates":[114.66652000000001,29.63994000000001],"type":"Point"}
}