{
  "type": "Feature",
  "properties": {
    "gn:admin1_code":"30",
    "gn:asciiname":"Zhumashi",
    "gn:country_code":"CN",
    "gn:dem":513,
    "gn:feature_class":"P",
    "gn:feature_code":"PPL",
    "gn:name":"Zhumashi",
    "gn:population":0,
    "gn:timezone":"Asia/Shanghai",
    "iso:country":"CN",
    "name:zho_x_preferred":[
        "\u732a\u9ebb\u77f3"
    ],
    "wof:name":"Zhumashi",
    "wof:placetype":"locality"
},
  "geometry": {"coordinates":[116.12673999999998,23.85366],"type":"Point"}
}