{
  "type": "Feature",
  "properties": {
    "gn:admin1_code":"1.0",
    "gn:asciiname":"Yangxi",
    "gn:country_code":"CN",
    "gn:dem":240,
    "gn:feature_class":"P",
    "gn:feature_code":"PPLA4",
    "gn:name":"Yangxi",
    "gn:population":0,
    "gn:timezone":"Asia/Shanghai",
    "iso:country":"CN",
    "name:und_x_variant":[
        "Yang-ch\u2019i",
        "Yang-hsi",
        "Yang-ch\u2019i-chen",
        "Yangxi",
        "\u6768\u6eaa",
        "Yangxi Zhen",
        "\u6768\u6eaa\u9547"
    ],
    "wof:name":"Yangxi",
    "wof:placetype":"locality"
},
  "geometry": {"coordinates":[118.6421,30.15667],"type":"Point"}
}