{
  "type": "Feature",
  "properties": {
    "gn:admin1_code":"02",
    "gn:asciiname":"Li'aocun",
    "gn:country_code":"CN",
    "gn:dem":704,
    "gn:feature_class":"P",
    "gn:feature_code":"PPL",
    "gn:name":"Li\u2019aocun",
    "gn:population":0,
    "gn:timezone":"Asia/Shanghai",
    "iso:country":"CN",
    "name:und_x_variant":[
        "Li\u2019ao",
        "Li\u2019aocun"
    ],
    "name:zho_x_preferred":[
        "\u91cc\u5c99"
    ],
    "name:zho_x_variant":[
        "\u91cc\u5c99\u6751"
    ],
    "wof:name":"Li'aocun",
    "wof:placetype":"locality"
},
  "geometry": {"coordinates":[120.92776000000001,28.71358],"type":"Point"}
}