{
  "type": "Feature",
  "properties": {
    "gn:admin1_code":"30",
    "gn:asciiname":"Changshajie",
    "gn:country_code":"CN",
    "gn:dem":311,
    "gn:feature_class":"P",
    "gn:feature_code":"PPL",
    "gn:name":"Changshajie",
    "gn:population":0,
    "gn:timezone":"Asia/Shanghai",
    "iso:country":"CN",
    "name:zho_x_preferred":[
        "\u957f\u6c99\u8857"
    ],
    "wof:name":"Changshajie",
    "wof:placetype":"locality"
},
  "geometry": {"coordinates":[111.43814999999999,22.24916],"type":"Point"}
}