{
  "type": "Feature",
  "properties": {
    "gn:admin1_code":"14.0",
    "gn:asciiname":"Longxiagong",
    "gn:country_code":"CN",
    "gn:dem":3677,
    "gn:feature_class":"P",
    "gn:feature_code":"PPL",
    "gn:name":"Longxiagong",
    "gn:population":0,
    "gn:timezone":"Asia/Urumqi",
    "iso:country":"CN",
    "name:zho_x_preferred":[
        "\u9f99\u5477\u516c"
    ],
    "wof:name":"Longxiagong",
    "wof:placetype":"locality"
},
  "geometry": {"coordinates":[98.63749,29.45961],"type":"Point"}
}