{
  "type": "Feature",
  "properties": {
    "gn:admin1_code":"3.0",
    "gn:asciiname":"Yijiayuan",
    "gn:country_code":"CN",
    "gn:dem":130,
    "gn:feature_class":"P",
    "gn:feature_code":"PPL",
    "gn:name":"Yijiayuan",
    "gn:population":0,
    "gn:timezone":"Asia/Shanghai",
    "iso:country":"CN",
    "name:zho_x_preferred":[
        "\u6613\u5bb6\u6e90"
    ],
    "wof:name":"Yijiayuan",
    "wof:placetype":"locality"
},
  "geometry": {"coordinates":[114.81699999999999,28.417],"type":"Point"}
}