{
  "type": "Feature",
  "properties": {
    "gn:admin1_code":"4.0",
    "gn:asciiname":"Heiduntang",
    "gn:country_code":"CN",
    "gn:dem":28,
    "gn:feature_class":"P",
    "gn:feature_code":"PPL",
    "gn:name":"Heiduntang",
    "gn:population":0,
    "gn:timezone":"Asia/Shanghai",
    "iso:country":"CN",
    "name:zho_x_preferred":[
        "\u9ed1\u58a9\u5858"
    ],
    "wof:name":"Heiduntang",
    "wof:placetype":"locality"
},
  "geometry": {"coordinates":[118.491,34.3103],"type":"Point"}
}