{
  "type": "Feature",
  "properties": {
    "gn:admin1_code":"26",
    "gn:asciiname":"Taoquyuan",
    "gn:country_code":"CN",
    "gn:dem":1204,
    "gn:feature_class":"P",
    "gn:feature_code":"PPL",
    "gn:name":"Taoquyuan",
    "gn:population":0,
    "gn:timezone":"Asia/Shanghai",
    "iso:country":"CN",
    "name:und_x_variant":[
        "\u6843\u6e20\u586c"
    ],
    "name:zho_x_preferred":[
        "\u6843\u6e20\u586c"
    ],
    "wof:name":"Taoquyuan",
    "wof:placetype":"locality"
},
  "geometry": {"coordinates":[108.61056000000001,34.96361],"type":"Point"}
}