{
  "type": "Feature",
  "properties": {
    "gn:admin1_code":"30.0",
    "gn:asciiname":"Shikenglang",
    "gn:country_code":"CN",
    "gn:dem":111,
    "gn:feature_class":"P",
    "gn:feature_code":"PPL",
    "gn:name":"Shikenglang",
    "gn:population":0,
    "gn:timezone":"Asia/Shanghai",
    "iso:country":"CN",
    "name:zho_x_preferred":[
        "Shikenglang"
    ],
    "name:zho_x_variant":[
        "\u77f3\u5751\u6d6a"
    ],
    "wof:name":"Shikenglang",
    "wof:placetype":"locality"
},
  "geometry": {"coordinates":[112.36194,24.55806],"type":"Point"}
}