{
  "type": "Feature",
  "properties": {
    "gn:admin1_code":"18",
    "gn:asciiname":"Bana",
    "gn:country_code":"CN",
    "gn:dem":816,
    "gn:feature_class":"P",
    "gn:feature_code":"PPL",
    "gn:name":"Bana",
    "gn:population":0,
    "gn:timezone":"Asia/Shanghai",
    "iso:country":"CN",
    "name:zho_x_preferred":[
        "\u575d\u7eb3"
    ],
    "wof:name":"Bana",
    "wof:placetype":"locality"
},
  "geometry": {"coordinates":[106.152,24.8717],"type":"Point"}
}