{
  "type": "Feature",
  "properties": {
    "gn:admin1_code":"2",
    "gn:asciiname":"Jiangzhen",
    "gn:country_code":"CN",
    "gn:dem":28,
    "gn:feature_class":"P",
    "gn:feature_code":"PPL",
    "gn:name":"Jiangzhen",
    "gn:population":0,
    "gn:timezone":"Asia/Shanghai",
    "iso:country":"CN",
    "name:und_x_variant":[
        "\u848b\u9547"
    ],
    "name:zho_x_preferred":[
        "\u848b\u9547"
    ],
    "wof:name":"Jiangzhen",
    "wof:placetype":"locality"
},
  "geometry": {"coordinates":[120.77388999999999,29.78667],"type":"Point"}
}