{
  "type": "Feature",
  "properties": {
    "gn:admin1_code":"9.0",
    "gn:asciiname":"Dongyangzhuang",
    "gn:country_code":"CN",
    "gn:dem":145,
    "gn:feature_class":"P",
    "gn:feature_code":"PPL",
    "gn:name":"Dongyangzhuang",
    "gn:population":0,
    "gn:timezone":"Asia/Shanghai",
    "iso:country":"CN",
    "name:und_x_variant":[
        "\u4e1c\u6768\u5e84",
        "Dongyangzhuang"
    ],
    "wof:name":"Dongyangzhuang",
    "wof:placetype":"locality"
},
  "geometry": {"coordinates":[112.39857000000001,33.01412],"type":"Point"}
}