{
  "type": "Feature",
  "properties": {
    "gn:admin1_code":"7.0",
    "gn:asciiname":"Wusuo",
    "gn:cc2":"CN",
    "gn:country_code":"CN",
    "gn:dem":561,
    "gn:feature_class":"P",
    "gn:feature_code":"PPL",
    "gn:name":"Wusuo",
    "gn:population":0,
    "gn:timezone":"Asia/Shanghai",
    "iso:country":"CN",
    "name:und_x_variant":[
        "Wu-so",
        "Wusuo"
    ],
    "wof:name":"Wusuo",
    "wof:placetype":"locality"
},
  "geometry": {"coordinates":[116.03333000000001,25.06667],"type":"Point"}
}