{
  "type": "Feature",
  "properties": {
    "gn:admin1_code":"4.0",
    "gn:asciiname":"Wangzaodun",
    "gn:country_code":"CN",
    "gn:dem":6,
    "gn:feature_class":"P",
    "gn:feature_code":"PPL",
    "gn:name":"Wangzaodun",
    "gn:population":0,
    "gn:timezone":"Asia/Shanghai",
    "iso:country":"CN",
    "name:zho_x_preferred":[
        "\u738b\u7076\u58a9"
    ],
    "wof:name":"Wangzaodun",
    "wof:placetype":"locality"
},
  "geometry": {"coordinates":[121.33137000000001,32.05965],"type":"Point"}
}