{
  "type": "Feature",
  "properties": {
    "gn:admin1_code":"30",
    "gn:asciiname":"Hemen",
    "gn:country_code":"CN",
    "gn:dem":15,
    "gn:feature_class":"P",
    "gn:feature_code":"PPL",
    "gn:name":"Hemen",
    "gn:population":0,
    "gn:timezone":"Asia/Urumqi",
    "iso:country":"CN",
    "name:bul_x_preferred":[
        "\u0425\u0435\u043c\u0435\u043d"
    ],
    "name:deu_x_preferred":[
        "Hemen"
    ],
    "name:fra_x_preferred":[
        "Hemen"
    ],
    "name:rus_x_preferred":[
        "\u0425\u0435\u043c\u0435\u043d"
    ],
    "name:ukr_x_preferred":[
        "\u0425\u0435\u043c\u0435\u043d"
    ],
    "name:zho_x_preferred":[
        "\u6cb3\u95e8"
    ],
    "wof:name":"Hemen",
    "wof:placetype":"locality"
},
  "geometry": {"coordinates":[109.87949999999999,20.69593],"type":"Point"}
}