{
  "type": "Feature",
  "properties": {
    "gn:admin1_code":"26.0",
    "gn:asciiname":"Sunkengcun",
    "gn:country_code":"CN",
    "gn:dem":1434,
    "gn:feature_class":"P",
    "gn:feature_code":"PPL",
    "gn:name":"Sunkengcun",
    "gn:population":0,
    "gn:timezone":"Asia/Shanghai",
    "iso:country":"CN",
    "name:zho_x_preferred":[
        "\u5b59\u5751\u6751"
    ],
    "wof:name":"Sunkengcun",
    "wof:placetype":"locality"
},
  "geometry": {"coordinates":[107.94477999999999,37.55051],"type":"Point"}
}