{
  "type": "Feature",
  "properties": {
    "gn:admin1_code":"24.0",
    "gn:asciiname":"Wangshencun",
    "gn:country_code":"CN",
    "gn:dem":564,
    "gn:feature_class":"P",
    "gn:feature_code":"PPL",
    "gn:name":"Wangshencun",
    "gn:population":0,
    "gn:timezone":"Asia/Shanghai",
    "iso:country":"CN",
    "name:zho_x_preferred":[
        "\u738b\u7533\u6751"
    ],
    "wof:name":"Wangshencun",
    "wof:placetype":"locality"
},
  "geometry": {"coordinates":[110.59381999999999,35.24493],"type":"Point"}
}