{
  "type": "Feature",
  "properties": {
    "iso:country":"CN",
    "qs:name":"\u4e91",
    "qs:name_adm0":"\u4e2d\u570b",
    "qs:name_adm1":"\u4e91\u5357\u7701",
    "qs:photos":7,
    "qs:photos_1k":1,
    "qs:photos_9k":1,
    "qs:photos_9r":1,
    "qs:photos_all":7,
    "qs:photos_sr":1,
    "qs:placetype":"Town",
    "qs:pop_sr":"0",
    "wof:name":"\u4e91",
    "wof:placetype":"locality"
},
  "geometry": {"coordinates":[100.134973,24.449337],"type":"Point"}
}