{
  "type": "Feature",
  "properties": {
    "gn:admin1_code":"2.0",
    "gn:asciiname":"Fanwuli",
    "gn:country_code":"CN",
    "gn:dem":180,
    "gn:feature_class":"P",
    "gn:feature_code":"PPL",
    "gn:name":"Fanwuli",
    "gn:population":0,
    "gn:timezone":"Asia/Shanghai",
    "iso:country":"CN",
    "name:und_x_variant":[
        "\u7548\u575e\u91cc",
        "Fanwuli"
    ],
    "wof:name":"Fanwuli",
    "wof:placetype":"locality"
},
  "geometry": {"coordinates":[119.24142000000001,29.825],"type":"Point"}
}