{
  "type": "Feature",
  "properties": {
    "gn:admin1_code":"12.0",
    "gn:asciiname":"Laozhaixi",
    "gn:country_code":"CN",
    "gn:dem":704,
    "gn:feature_class":"P",
    "gn:feature_code":"PPL",
    "gn:name":"Laozhaixi",
    "gn:population":0,
    "gn:timezone":"Asia/Shanghai",
    "iso:country":"CN",
    "name:zho_x_preferred":[
        "\u8001\u5be8\u6eaa"
    ],
    "wof:name":"Laozhaixi",
    "wof:placetype":"locality"
},
  "geometry": {"coordinates":[109.39464,30.03968],"type":"Point"}
}