{
  "type": "Feature",
  "properties": {
    "gn:admin1_code":"32.0",
    "gn:asciiname":"Menggu",
    "gn:country_code":"CN",
    "gn:dem":3295,
    "gn:feature_class":"P",
    "gn:feature_code":"PPL",
    "gn:name":"Menggu",
    "gn:population":0,
    "gn:timezone":"Asia/Shanghai",
    "iso:country":"CN",
    "name:zho_x_preferred":[
        "\u731b\u56fa"
    ],
    "wof:name":"Menggu",
    "wof:placetype":"locality"
},
  "geometry": {"coordinates":[102.384,31.0266],"type":"Point"}
}