{
  "type": "Feature",
  "properties": {
    "gn:admin1_code":"3",
    "gn:asciiname":"Quxi",
    "gn:country_code":"CN",
    "gn:dem":392,
    "gn:feature_class":"P",
    "gn:feature_code":"PPL",
    "gn:name":"Quxi",
    "gn:population":0,
    "gn:timezone":"Asia/Shanghai",
    "iso:country":"CN",
    "name:zho_x_preferred":[
        "\u66f2\u6eaa"
    ],
    "wof:name":"Quxi",
    "wof:placetype":"locality"
},
  "geometry": {"coordinates":[114.32868000000001,26.10918],"type":"Point"}
}