{
  "type": "Feature",
  "properties": {
    "gn:admin1_code":"29.0",
    "gn:asciiname":"Wangjiaqing",
    "gn:country_code":"CN",
    "gn:dem":2374,
    "gn:feature_class":"P",
    "gn:feature_code":"PPL",
    "gn:name":"Wangjiaqing",
    "gn:population":0,
    "gn:timezone":"Asia/Shanghai",
    "iso:country":"CN",
    "name:zho_x_preferred":[
        "\u6c6a\u5bb6\u7b90"
    ],
    "wof:name":"Wangjiaqing",
    "wof:placetype":"locality"
},
  "geometry": {"coordinates":[102.95399999999999,25.4488],"type":"Point"}
}