{
  "type": "Feature",
  "properties": {
    "gn:admin1_code":"32.0",
    "gn:asciiname":"Yongping",
    "gn:country_code":"CN",
    "gn:dem":1502,
    "gn:feature_class":"P",
    "gn:feature_code":"PPL",
    "gn:name":"Yongping",
    "gn:population":0,
    "gn:timezone":"Asia/Shanghai",
    "iso:country":"CN",
    "name:deu_x_preferred":[
        "Yongping"
    ],
    "name:und_x_variant":[
        "\u6c38\u5e73"
    ],
    "name:vie_x_preferred":[
        "V\u0129nh B\u00ecnh"
    ],
    "wof:name":"Yongping",
    "wof:placetype":"locality"
},
  "geometry": {"coordinates":[106.19392999999999,32.68075],"type":"Point"}
}