{
  "type": "Feature",
  "properties": {
    "gn:admin1_code":"8.0",
    "gn:asciiname":"Dongliuhe",
    "gn:country_code":"CN",
    "gn:dem":173,
    "gn:feature_class":"P",
    "gn:feature_code":"PPL",
    "gn:name":"Dongliuhe",
    "gn:population":0,
    "gn:timezone":"Asia/Shanghai",
    "iso:country":"CN",
    "name:zho_x_preferred":[
        "\u4e1c\u516d\u5408"
    ],
    "wof:name":"Dongliuhe",
    "wof:placetype":"locality"
},
  "geometry": {"coordinates":[124.15849,48.10507],"type":"Point"}
}