{
  "type": "Feature",
  "properties": {
    "gn:admin1_code":"14.0",
    "gn:asciiname":"Guma",
    "gn:country_code":"CN",
    "gn:dem":4582,
    "gn:feature_class":"P",
    "gn:feature_code":"PPL",
    "gn:name":"Guma",
    "gn:population":0,
    "gn:timezone":"Asia/Urumqi",
    "iso:country":"CN",
    "name:zho_x_preferred":[
        "\u53e4\u9a6c"
    ],
    "wof:name":"Guma",
    "wof:placetype":"locality"
},
  "geometry": {"coordinates":[86.941,29.2927],"type":"Point"}
}