{
  "type": "Feature",
  "properties": {
    "gn:admin1_code":"32.0",
    "gn:asciiname":"Caoyuanding",
    "gn:country_code":"CN",
    "gn:dem":1657,
    "gn:feature_class":"P",
    "gn:feature_code":"PPL",
    "gn:name":"Caoyuanding",
    "gn:population":0,
    "gn:timezone":"Asia/Shanghai",
    "iso:country":"CN",
    "name:zho_x_preferred":[
        "\u8349\u5143\u9876"
    ],
    "wof:name":"Caoyuanding",
    "wof:placetype":"locality"
},
  "geometry": {"coordinates":[104.18300000000001,31.8508],"type":"Point"}
}