{
  "type": "Feature",
  "properties": {
    "gn:admin1_code":"8.0",
    "gn:asciiname":"Anchang Jintun",
    "gn:country_code":"CN",
    "gn:dem":176,
    "gn:feature_class":"P",
    "gn:feature_code":"PPL",
    "gn:name":"Anchang Jintun",
    "gn:population":0,
    "gn:timezone":"Asia/Shanghai",
    "iso:country":"CN",
    "name:zho_x_preferred":[
        "\u5b89\u957f\u91d1\u5c6f"
    ],
    "wof:name":"Anchang Jintun",
    "wof:placetype":"locality"
},
  "geometry": {"coordinates":[124.38949,48.19008],"type":"Point"}
}