{
  "type": "Feature",
  "properties": {
    "gn:admin1_code":"9.0",
    "gn:asciiname":"Sishanzhuang",
    "gn:country_code":"CN",
    "gn:dem":355,
    "gn:feature_class":"P",
    "gn:feature_code":"PPL",
    "gn:name":"Sishanzhuang",
    "gn:population":0,
    "gn:timezone":"Asia/Shanghai",
    "iso:country":"CN",
    "name:zho_x_preferred":[
        "\u56db\u5c71\u5e84"
    ],
    "wof:name":"Sishanzhuang",
    "wof:placetype":"locality"
},
  "geometry": {"coordinates":[112.15143,33.191],"type":"Point"}
}