{
  "type": "Feature",
  "properties": {
    "gn:admin1_code":"11.0",
    "gn:asciiname":"Mahuangchong",
    "gn:country_code":"CN",
    "gn:dem":122,
    "gn:feature_class":"P",
    "gn:feature_code":"PPL",
    "gn:name":"Mahuangchong",
    "gn:population":0,
    "gn:timezone":"Asia/Shanghai",
    "iso:country":"CN",
    "name:zho_x_preferred":[
        "\u8682\u8757\u51b2"
    ],
    "wof:name":"Mahuangchong",
    "wof:placetype":"locality"
},
  "geometry": {"coordinates":[112.80789,27.53803],"type":"Point"}
}