{
  "type": "Feature",
  "properties": {
    "gn:admin1_code":"9.0",
    "gn:asciiname":"Shiqiaolu",
    "gn:country_code":"CN",
    "gn:dem":185,
    "gn:feature_class":"P",
    "gn:feature_code":"PPL",
    "gn:name":"Shiqiaolu",
    "gn:population":0,
    "gn:timezone":"Asia/Shanghai",
    "iso:country":"CN",
    "name:und_x_variant":[
        "\u77f3\u6865\u8def",
        "Shiqiaolu"
    ],
    "wof:name":"Shiqiaolu",
    "wof:placetype":"locality"
},
  "geometry": {"coordinates":[112.77043,33.24886],"type":"Point"}
}