{
  "type": "Feature",
  "properties": {
    "gn:admin1_code":"14.0",
    "gn:asciiname":"Xiongduocun",
    "gn:country_code":"CN",
    "gn:dem":4639,
    "gn:feature_class":"P",
    "gn:feature_code":"PPL",
    "gn:name":"Xiongduocun",
    "gn:population":0,
    "gn:timezone":"Asia/Urumqi",
    "iso:country":"CN",
    "name:zho_x_preferred":[
        "\u96c4\u591a\u6751"
    ],
    "wof:name":"Xiongduocun",
    "wof:placetype":"locality"
},
  "geometry": {"coordinates":[90.21747999999999,31.36153],"type":"Point"}
}