{
  "type": "Feature",
  "properties": {
    "gn:admin1_code":"30.0",
    "gn:asciiname":"Daluo Ercun",
    "gn:country_code":"CN",
    "gn:dem":16,
    "gn:feature_class":"P",
    "gn:feature_code":"PPL",
    "gn:name":"Daluo Ercun",
    "gn:population":0,
    "gn:timezone":"Asia/Shanghai",
    "iso:country":"CN",
    "name:zho_x_preferred":[
        "\u5927\u7f85\u4e8c\u6751"
    ],
    "wof:name":"Daluo Ercun",
    "wof:placetype":"locality"
},
  "geometry": {"coordinates":[112.62299,22.58589],"type":"Point"}
}