{
  "type": "Feature",
  "properties": {
    "gn:admin1_code":"15.0",
    "gn:asciiname":"Ji'ang",
    "gn:country_code":"CN",
    "gn:dem":3047,
    "gn:feature_class":"P",
    "gn:feature_code":"PPL",
    "gn:name":"Ji\u2019ang",
    "gn:population":0,
    "gn:timezone":"Asia/Shanghai",
    "iso:country":"CN",
    "name:und_x_variant":[
        "Ji\u2019ang"
    ],
    "name:zho_x_preferred":[
        "\u5409\u6602"
    ],
    "wof:name":"Ji'ang",
    "wof:placetype":"locality"
},
  "geometry": {"coordinates":[102.706,34.8021],"type":"Point"}
}