{
  "type": "Feature",
  "properties": {
    "gn:admin1_code":"29.0",
    "gn:asciiname":"Manjiaolai",
    "gn:country_code":"CN",
    "gn:dem":1532,
    "gn:feature_class":"P",
    "gn:feature_code":"PPL",
    "gn:name":"Manjiaolai",
    "gn:population":0,
    "gn:timezone":"Asia/Shanghai",
    "iso:country":"CN",
    "name:zho_x_preferred":[
        "\u66fc\u811a\u6765"
    ],
    "wof:name":"Manjiaolai",
    "wof:placetype":"locality"
},
  "geometry": {"coordinates":[100.681,21.82],"type":"Point"}
}