{
  "type": "Feature",
  "properties": {
    "gn:admin1_code":"32.0",
    "gn:asciiname":"Caijia Dayuanzi",
    "gn:country_code":"CN",
    "gn:dem":419,
    "gn:feature_class":"P",
    "gn:feature_code":"PPL",
    "gn:name":"Caijia Dayuanzi",
    "gn:population":0,
    "gn:timezone":"Asia/Shanghai",
    "iso:country":"CN",
    "name:zho_x_preferred":[
        "\u8521\u5bb6\u5927\u9662\u5b50"
    ],
    "wof:name":"Caijia Dayuanzi",
    "wof:placetype":"locality"
},
  "geometry": {"coordinates":[104.211,29.813],"type":"Point"}
}