{
  "type": "Feature",
  "properties": {
    "gn:admin1_code":"19.0",
    "gn:asciiname":"Chebangou",
    "gn:country_code":"CN",
    "gn:dem":461,
    "gn:feature_class":"P",
    "gn:feature_code":"PPL",
    "gn:name":"Chebangou",
    "gn:population":0,
    "gn:timezone":"Asia/Shanghai",
    "iso:country":"CN",
    "name:und_x_variant":[
        "\u8f66\u677f\u6c9f"
    ],
    "wof:name":"Chebangou",
    "wof:placetype":"locality"
},
  "geometry": {"coordinates":[124.52809000000001,41.32853],"type":"Point"}
}