{
  "type": "Feature",
  "properties": {
    "gn:admin1_code":"9",
    "gn:asciiname":"Danxu",
    "gn:country_code":"CN",
    "gn:dem":53,
    "gn:feature_class":"P",
    "gn:feature_code":"PPL",
    "gn:name":"Danxu",
    "gn:population":0,
    "gn:timezone":"Asia/Shanghai",
    "iso:country":"CN",
    "name:zho_x_preferred":[
        "\u4e39\u5f90"
    ],
    "wof:name":"Danxu",
    "wof:placetype":"locality"
},
  "geometry": {"coordinates":[115.44025999999999,35.7031],"type":"Point"}
}