{
  "type": "Feature",
  "properties": {
    "gn:admin1_code":"25.0",
    "gn:asciiname":"Xinhu",
    "gn:cc2":"CN",
    "gn:country_code":"CN",
    "gn:dem":4,
    "gn:feature_class":"P",
    "gn:feature_code":"PPL",
    "gn:name":"Xinhu",
    "gn:population":0,
    "gn:timezone":"Asia/Shanghai",
    "iso:country":"CN",
    "name:und_x_variant":[
        "Xinqianhu",
        "Hsin-ch\u2019ien-hu",
        "Xinhu"
    ],
    "wof:name":"Xinhu",
    "wof:placetype":"locality"
},
  "geometry": {"coordinates":[118.29694000000001,37.985],"type":"Point"}
}