{
  "type": "Feature",
  "properties": {
    "gn:admin1_code":"5.0",
    "gn:asciiname":"Houxunzicun",
    "gn:country_code":"CN",
    "gn:dem":153,
    "gn:feature_class":"P",
    "gn:feature_code":"PPL",
    "gn:name":"Houxunzicun",
    "gn:population":0,
    "gn:timezone":"Asia/Shanghai",
    "iso:country":"CN",
    "name:zho_x_preferred":[
        "\u540e\u8bad\u5b57\u6751"
    ],
    "wof:name":"Houxunzicun",
    "wof:placetype":"locality"
},
  "geometry": {"coordinates":[123.77945,44.77963],"type":"Point"}
}