{
  "type": "Feature",
  "properties": {
    "gn:admin1_code":"16.0",
    "gn:asciiname":"Yandong",
    "gn:cc2":"CN",
    "gn:country_code":"CN",
    "gn:dem":613,
    "gn:feature_class":"P",
    "gn:feature_code":"PPL",
    "gn:name":"Yandong",
    "gn:population":0,
    "gn:timezone":"Asia/Shanghai",
    "iso:country":"CN",
    "name:und_x_variant":[
        "Yen-tung",
        "Yandong"
    ],
    "wof:name":"Yandong",
    "wof:placetype":"locality"
},
  "geometry": {"coordinates":[106.66667,23.16667],"type":"Point"}
}