{
  "type": "Feature",
  "properties": {
    "gn:admin1_code":"26.0",
    "gn:asciiname":"Jianqu",
    "gn:country_code":"CN",
    "gn:dem":1107,
    "gn:feature_class":"P",
    "gn:feature_code":"PPL",
    "gn:name":"Jianqu",
    "gn:population":0,
    "gn:timezone":"Asia/Shanghai",
    "iso:country":"CN",
    "name:und_x_variant":[
        "\u6da7\u6e20"
    ],
    "wof:name":"Jianqu",
    "wof:placetype":"locality"
},
  "geometry": {"coordinates":[107.58915,34.64677],"type":"Point"}
}