{
  "type": "Feature",
  "properties": {
    "gn:admin1_code":"3.0",
    "gn:asciiname":"Meizhou",
    "gn:country_code":"CN",
    "gn:dem":139,
    "gn:feature_class":"P",
    "gn:feature_code":"PPL",
    "gn:name":"Meizhou",
    "gn:population":0,
    "gn:timezone":"Asia/Shanghai",
    "iso:country":"CN",
    "name:ara_x_preferred":[
        "\u0645\u0627\u0648\u0632\u0648"
    ],
    "name:cdo_x_preferred":[
        "M\u00f9i-ci\u016d"
    ],
    "name:ceb_x_preferred":[
        "Meizhou"
    ],
    "name:ces_x_preferred":[
        "Mej-\u010dou"
    ],
    "name:cym_x_preferred":[
        "Meizhou"
    ],
    "name:dan_x_preferred":[
        "Meizhou"
    ],
    "name:deu_x_preferred":[
        "Meizhou"
    ],
    "name:eus_x_preferred":[
        "Meizhou"
    ],
    "name:fas_x_preferred":[
        "\u0645\u0627\u0648\u0698\u0648\u0627"
    ],
    "name:fin_x_preferred":[
        "Meizhou"
    ],
    "name:fra_x_preferred":[
        "Meizhou"
    ],
    "name:hak_x_preferred":[
        "M\u00f2i-ch\u00fb-s\u1e73"
    ],
    "name:ind_x_preferred":[
        "Meizhou"
    ],
    "name:ita_x_preferred":[
        "Meizhou"
    ],
    "name:jpn_x_preferred":[
        "\u6885\u5dde\u5e02"
    ],
    "name:kaz_x_preferred":[
        "\u041c\u044d\u0439\u0447\u0436\u043e\u0443"
    ],
    "name:kik_x_preferred":[
        "Meizhou"
    ],
    "name:kor_x_preferred":[
        "\uba54\uc774\uc800\uc6b0\uc2dc"
    ],
    "name:mlg_x_preferred":[
        "Meizhou"
    ],
    "name:nld_x_preferred":[
        "Meizhou"
    ],
    "name:nno_x_preferred":[
        "Meizhou"
    ],
    "name:nor_x_preferred":[
        "Meizhou"
    ],
    "name:pam_x_preferred":[
        "Meizhou"
    ],
    "name:pnb_x_preferred":[
        "\u0645\u06cc\u0626\u06cc\u0698\u0648\u0624"
    ],
    "name:pol_x_preferred":[
        "Meizhou"
    ],
    "name:por_x_preferred":[
        "Meizhou"
    ],
    "name:rus_x_preferred":[
        "\u041c\u044d\u0439\u0447\u0436\u043e\u0443"
    ],
    "name:spa_x_preferred":[
        "Meizh\u00f3u"
    ],
    "name:swa_x_preferred":[
        "Meizhou"
    ],
    "name:swe_x_preferred":[
        "Meizhou"
    ],
    "name:tgl_x_preferred":[
        "Meizhou"
    ],
    "name:tur_x_preferred":[
        "Meizhou"
    ],
    "name:und_x_variant":[
        "\u6885\u6d32"
    ],
    "name:urd_x_preferred":[
        "\u0645\u0626\u06cc\u0698\u0648"
    ],
    "name:vie_x_preferred":[
        "Mai Ch\u00e2u"
    ],
    "name:war_x_preferred":[
        "Meizhou"
    ],
    "name:zho_x_preferred":[
        "\u6885\u5dde\u5e02"
    ],
    "wof:name":"Meizhou",
    "wof:placetype":"locality"
},
  "geometry": {"coordinates":[114.23963000000001,27.09838],"type":"Point"}
}