{
  "type": "Feature",
  "properties": {
    "gn:admin1_code":"3.0",
    "gn:asciiname":"Meizhou",
    "gn:country_code":"CN",
    "gn:dem":139,
    "gn:feature_class":"P",
    "gn:feature_code":"PPL",
    "gn:name":"Meizhou",
    "gn:population":0,
    "gn:timezone":"Asia/Shanghai",
    "iso:country":"CN",
    "name:und_x_variant":[
        "\u6885\u6d32"
    ],
    "wof:name":"Meizhou",
    "wof:placetype":"locality"
},
  "geometry": {"coordinates":[114.23963000000001,27.09838],"type":"Point"}
}