{
  "type": "Feature",
  "properties": {
    "gn:admin1_code":"5.0",
    "gn:asciiname":"Donggepingfang",
    "gn:country_code":"CN",
    "gn:dem":258,
    "gn:feature_class":"P",
    "gn:feature_code":"PPL",
    "gn:name":"Donggepingfang",
    "gn:population":0,
    "gn:timezone":"Asia/Shanghai",
    "iso:country":"CN",
    "name:zho_x_preferred":[
        "\u4e1c\u845b\u5e73\u623f"
    ],
    "wof:name":"Donggepingfang",
    "wof:placetype":"locality"
},
  "geometry": {"coordinates":[124.63898,44.14867],"type":"Point"}
}