{
  "type": "Feature",
  "properties": {
    "gn:admin1_code":"32.0",
    "gn:asciiname":"Dongwantou",
    "gn:country_code":"CN",
    "gn:dem":508,
    "gn:feature_class":"P",
    "gn:feature_code":"PPL",
    "gn:name":"Dongwantou",
    "gn:population":0,
    "gn:timezone":"Asia/Shanghai",
    "iso:country":"CN",
    "name:zho_x_preferred":[
        "\u6d1e\u6e7e\u5934"
    ],
    "wof:name":"Dongwantou",
    "wof:placetype":"locality"
},
  "geometry": {"coordinates":[105.187,31.3633],"type":"Point"}
}