{
  "type": "Feature",
  "properties": {
    "gn:admin1_code":"14.0",
    "gn:asciiname":"Jueduicun",
    "gn:country_code":"CN",
    "gn:dem":3220,
    "gn:feature_class":"P",
    "gn:feature_code":"PPL",
    "gn:name":"Jueduicun",
    "gn:population":0,
    "gn:timezone":"Asia/Urumqi",
    "iso:country":"CN",
    "name:zho_x_preferred":[
        "\u51b3\u5806\u6751"
    ],
    "wof:name":"Jueduicun",
    "wof:placetype":"locality"
},
  "geometry": {"coordinates":[92.82819000000001,29.10254],"type":"Point"}
}