{
  "type": "Feature",
  "properties": {
    "gn:admin1_code":"30.0",
    "gn:asciiname":"Huangdongkou",
    "gn:country_code":"CN",
    "gn:dem":17,
    "gn:feature_class":"P",
    "gn:feature_code":"PPL",
    "gn:name":"Huangdongkou",
    "gn:population":0,
    "gn:timezone":"Asia/Shanghai",
    "iso:country":"CN",
    "name:zho_x_preferred":[
        "Huangdongkou"
    ],
    "name:zho_x_variant":[
        "\u9ec4\u6d1e\u53e3"
    ],
    "wof:name":"Huangdongkou",
    "wof:placetype":"locality"
},
  "geometry": {"coordinates":[113.24083,23.79833],"type":"Point"}
}