{
  "type": "Feature",
  "properties": {
    "gn:admin1_code":"20.0",
    "gn:asciiname":"Xing'an",
    "gn:country_code":"CN",
    "gn:dem":241,
    "gn:feature_class":"P",
    "gn:feature_code":"PPL",
    "gn:name":"Xing\u2019an",
    "gn:population":0,
    "gn:timezone":"Asia/Shanghai",
    "iso:country":"CN",
    "name:ceb_x_preferred":[
        "Xing\u2019an"
    ],
    "name:deu_x_preferred":[
        "Xing\u2019an"
    ],
    "name:fra_x_preferred":[
        "Xing'an"
    ],
    "name:nor_x_preferred":[
        "Xing'an"
    ],
    "name:swe_x_preferred":[
        "Xing\u2019an"
    ],
    "name:zho_x_preferred":[
        "\u5174\u5b89"
    ],
    "wof:name":"Xing'an",
    "wof:placetype":"locality"
},
  "geometry": {"coordinates":[124.05221,48.6405],"type":"Point"}
}