{
  "type": "Feature",
  "properties": {
    "gn:admin1_code":"25.0",
    "gn:asciiname":"Nanbucun",
    "gn:country_code":"CN",
    "gn:dem":128,
    "gn:feature_class":"P",
    "gn:feature_code":"PPL",
    "gn:name":"Nanbucun",
    "gn:population":0,
    "gn:timezone":"Asia/Shanghai",
    "iso:country":"CN",
    "name:zho_x_preferred":[
        "\u5357\u57e0\u6751"
    ],
    "wof:name":"Nanbucun",
    "wof:placetype":"locality"
},
  "geometry": {"coordinates":[120.96622000000001,37.38276],"type":"Point"}
}