{
  "type": "Feature",
  "properties": {
    "gn:admin1_code":"33.0",
    "gn:asciiname":"Yueliangtian",
    "gn:country_code":"CN",
    "gn:dem":661,
    "gn:feature_class":"P",
    "gn:feature_code":"PPL",
    "gn:name":"Yueliangtian",
    "gn:population":0,
    "gn:timezone":"Asia/Shanghai",
    "iso:country":"CN",
    "name:zho_x_preferred":[
        "\u6708\u4eae\u7530"
    ],
    "wof:name":"Yueliangtian",
    "wof:placetype":"locality"
},
  "geometry": {"coordinates":[106.40891000000001,28.74545],"type":"Point"}
}