{
  "type": "Feature",
  "properties": {
    "gn:admin1_code":"19.0",
    "gn:asciiname":"Dongshuangmiaozi",
    "gn:country_code":"CN",
    "gn:dem":7,
    "gn:feature_class":"P",
    "gn:feature_code":"PPL",
    "gn:name":"Dongshuangmiaozi",
    "gn:population":0,
    "gn:timezone":"Asia/Shanghai",
    "iso:country":"CN",
    "name:und_x_variant":[
        "\u4e1c\u53cc\u5e99\u5b50"
    ],
    "name:zho_x_preferred":[
        "\u4e1c\u53cc\u5e99\u5b50"
    ],
    "wof:name":"Dongshuangmiaozi",
    "wof:placetype":"locality"
},
  "geometry": {"coordinates":[121.69504000000001,41.33701],"type":"Point"}
}