{
  "type": "Feature",
  "properties": {
    "gn:admin1_code":"3.0",
    "gn:asciiname":"Houtuhu",
    "gn:country_code":"CN",
    "gn:dem":24,
    "gn:feature_class":"P",
    "gn:feature_code":"PPL",
    "gn:name":"Houtuhu",
    "gn:population":0,
    "gn:timezone":"Asia/Shanghai",
    "iso:country":"CN",
    "name:und_x_variant":[
        "\u540e\u571f\u6e56"
    ],
    "wof:name":"Houtuhu",
    "wof:placetype":"locality"
},
  "geometry": {"coordinates":[116.66236000000001,29.03772],"type":"Point"}
}