{
  "type": "Feature",
  "properties": {
    "gn:admin1_code":"11.0",
    "gn:asciiname":"Huluyuan",
    "gn:country_code":"CN",
    "gn:dem":318,
    "gn:feature_class":"P",
    "gn:feature_code":"PPL",
    "gn:name":"Huluyuan",
    "gn:population":0,
    "gn:timezone":"Asia/Shanghai",
    "iso:country":"CN",
    "name:zho_x_preferred":[
        "\u846b\u82a6\u56ed"
    ],
    "wof:name":"Huluyuan",
    "wof:placetype":"locality"
},
  "geometry": {"coordinates":[113.62059000000001,27.93386],"type":"Point"}
}