{
  "type": "Feature",
  "properties": {
    "gn:admin1_code":"12.0",
    "gn:asciiname":"Shuangshuijing",
    "gn:country_code":"CN",
    "gn:dem":1113,
    "gn:feature_class":"P",
    "gn:feature_code":"PPL",
    "gn:name":"Shuangshuijing",
    "gn:population":0,
    "gn:timezone":"Asia/Shanghai",
    "iso:country":"CN",
    "name:zho_x_preferred":[
        "\u53cc\u6c34\u4e95"
    ],
    "wof:name":"Shuangshuijing",
    "wof:placetype":"locality"
},
  "geometry": {"coordinates":[108.88473,30.30189],"type":"Point"}
}