{
  "type": "Feature",
  "properties": {
    "gn:admin1_code":"8.0",
    "gn:asciiname":"Fuqingcun",
    "gn:country_code":"CN",
    "gn:dem":212,
    "gn:feature_class":"P",
    "gn:feature_code":"PPL",
    "gn:name":"Fuqingcun",
    "gn:population":0,
    "gn:timezone":"Asia/Shanghai",
    "iso:country":"CN",
    "name:zho_x_preferred":[
        "\u798f\u5e86\u6751"
    ],
    "wof:name":"Fuqingcun",
    "wof:placetype":"locality"
},
  "geometry": {"coordinates":[126.01096,46.98576],"type":"Point"}
}