{
  "type": "Feature",
  "properties": {
    "gn:admin1_code":"8.0",
    "gn:asciiname":"Xinhua Nongchang Jiudui",
    "gn:country_code":"CN",
    "gn:dem":119,
    "gn:feature_class":"P",
    "gn:feature_code":"PPLF",
    "gn:name":"Xinhua Nongchang Jiudui",
    "gn:population":0,
    "gn:timezone":"Asia/Shanghai",
    "iso:country":"CN",
    "name:zho_x_preferred":[
        "\u65b0\u534e\u519c\u573a\u4e5d\u961f"
    ],
    "wof:name":"Xinhua Nongchang Jiudui",
    "wof:placetype":"locality"
},
  "geometry": {"coordinates":[130.22066000000001,47.1824],"type":"Point"}
}