{
  "type": "Feature",
  "properties": {
    "gn:admin1_code":"29.0",
    "gn:asciiname":"Laowangtian",
    "gn:country_code":"CN",
    "gn:dem":1522,
    "gn:feature_class":"P",
    "gn:feature_code":"PPL",
    "gn:name":"Laowangtian",
    "gn:population":0,
    "gn:timezone":"Asia/Shanghai",
    "iso:country":"CN",
    "name:zho_x_preferred":[
        "\u8001\u738b\u7530"
    ],
    "wof:name":"Laowangtian",
    "wof:placetype":"locality"
},
  "geometry": {"coordinates":[103.65600000000001,23.8736],"type":"Point"}
}