{
  "type": "Feature",
  "properties": {
    "gn:admin1_code":"32.0",
    "gn:asciiname":"Tangkanshang",
    "gn:country_code":"CN",
    "gn:dem":449,
    "gn:feature_class":"P",
    "gn:feature_code":"PPL",
    "gn:name":"Tangkanshang",
    "gn:population":0,
    "gn:timezone":"Asia/Shanghai",
    "iso:country":"CN",
    "name:zho_x_preferred":[
        "\u5858\u574e\u4e0a"
    ],
    "wof:name":"Tangkanshang",
    "wof:placetype":"locality"
},
  "geometry": {"coordinates":[104.52500000000001,28.8369],"type":"Point"}
}