{
  "type": "Feature",
  "properties": {
    "gn:admin1_code":"11.0",
    "gn:asciiname":"Qiangbu",
    "gn:country_code":"CN",
    "gn:dem":300,
    "gn:feature_class":"P",
    "gn:feature_code":"PPL",
    "gn:name":"Qiangbu",
    "gn:population":0,
    "gn:timezone":"Asia/Shanghai",
    "iso:country":"CN",
    "name:zho_x_preferred":[
        "\u5899\u57e0"
    ],
    "wof:name":"Qiangbu",
    "wof:placetype":"locality"
},
  "geometry": {"coordinates":[110.71511,27.00727],"type":"Point"}
}