{
  "type": "Feature",
  "properties": {
    "gn:admin1_code":"11",
    "gn:asciiname":"Gutang Liujia",
    "gn:country_code":"CN",
    "gn:dem":127,
    "gn:feature_class":"P",
    "gn:feature_code":"PPL",
    "gn:name":"Gutang Liujia",
    "gn:population":0,
    "gn:timezone":"Asia/Shanghai",
    "iso:country":"CN",
    "name:zho_x_preferred":[
        "\u53e4\u5858\u5218\u5bb6"
    ],
    "wof:name":"Gutang Liujia",
    "wof:placetype":"locality"
},
  "geometry": {"coordinates":[111.72633,26.46277000000001],"type":"Point"}
}