{
  "type": "Feature",
  "properties": {
    "gn:admin1_code":"32.0",
    "gn:asciiname":"Dafenbao",
    "gn:country_code":"CN",
    "gn:dem":393,
    "gn:feature_class":"P",
    "gn:feature_code":"PPL",
    "gn:name":"Dafenbao",
    "gn:population":0,
    "gn:timezone":"Asia/Shanghai",
    "iso:country":"CN",
    "name:zho_x_preferred":[
        "\u5927\u575f\u5305"
    ],
    "wof:name":"Dafenbao",
    "wof:placetype":"locality"
},
  "geometry": {"coordinates":[104.545,28.8815],"type":"Point"}
}