{
  "type": "Feature",
  "properties": {
    "gn:admin1_code":"18",
    "gn:asciiname":"Lagaozhai",
    "gn:country_code":"CN",
    "gn:dem":794,
    "gn:feature_class":"P",
    "gn:feature_code":"PPL",
    "gn:name":"Lagaozhai",
    "gn:population":0,
    "gn:timezone":"Asia/Shanghai",
    "iso:country":"CN",
    "name:zho_x_preferred":[
        "\u62c9\u9ad8\u5be8"
    ],
    "wof:name":"Lagaozhai",
    "wof:placetype":"locality"
},
  "geometry": {"coordinates":[106.443,25.5396],"type":"Point"}
}