{
  "type": "Feature",
  "properties": {
    "gn:admin1_code":"3.0",
    "gn:asciiname":"Buxing",
    "gn:country_code":"CN",
    "gn:dem":277,
    "gn:feature_class":"P",
    "gn:feature_code":"PPL",
    "gn:name":"Buxing",
    "gn:population":0,
    "gn:timezone":"Asia/Shanghai",
    "iso:country":"CN",
    "name:und_x_variant":[
        "\u5e03\u661f"
    ],
    "wof:name":"Buxing",
    "wof:placetype":"locality"
},
  "geometry": {"coordinates":[114.45115,27.57739],"type":"Point"}
}