{
  "type": "Feature",
  "properties": {
    "gn:admin1_code":"32.0",
    "gn:asciiname":"Zhangsigou",
    "gn:country_code":"CN",
    "gn:dem":670,
    "gn:feature_class":"P",
    "gn:feature_code":"PPL",
    "gn:name":"Zhangsigou",
    "gn:population":0,
    "gn:timezone":"Asia/Shanghai",
    "iso:country":"CN",
    "name:zho_x_preferred":[
        "\u5f20\u65af\u6c9f"
    ],
    "wof:name":"Zhangsigou",
    "wof:placetype":"locality"
},
  "geometry": {"coordinates":[103.191,30.2572],"type":"Point"}
}