{
  "type": "Feature",
  "properties": {
    "gn:admin1_code":"29",
    "gn:asciiname":"Tawude",
    "gn:country_code":"CN",
    "gn:dem":1892,
    "gn:feature_class":"P",
    "gn:feature_code":"PPL",
    "gn:name":"Tawude",
    "gn:population":0,
    "gn:timezone":"Asia/Shanghai",
    "iso:country":"CN",
    "name:zho_x_preferred":[
        "\u4ed6\u4e4c\u5fb7"
    ],
    "wof:name":"Tawude",
    "wof:placetype":"locality"
},
  "geometry": {"coordinates":[102.348,23.9452],"type":"Point"}
}