{
  "type": "Feature",
  "properties": {
    "gn:admin1_code":"32.0",
    "gn:asciiname":"Qingangdun",
    "gn:country_code":"CN",
    "gn:dem":582,
    "gn:feature_class":"P",
    "gn:feature_code":"PPL",
    "gn:name":"Qingangdun",
    "gn:population":0,
    "gn:timezone":"Asia/Shanghai",
    "iso:country":"CN",
    "name:zho_x_preferred":[
        "\u9752\u5188\u58a9"
    ],
    "wof:name":"Qingangdun",
    "wof:placetype":"locality"
},
  "geometry": {"coordinates":[103.38215,30.39534],"type":"Point"}
}