{
  "type": "Feature",
  "properties": {
    "gn:admin1_code":"32.0",
    "gn:asciiname":"Citangba",
    "gn:country_code":"CN",
    "gn:dem":529,
    "gn:feature_class":"P",
    "gn:feature_code":"PPL",
    "gn:name":"Citangba",
    "gn:population":0,
    "gn:timezone":"Asia/Shanghai",
    "iso:country":"CN",
    "name:zho_x_preferred":[
        "\u7960\u5802\u575d"
    ],
    "wof:name":"Citangba",
    "wof:placetype":"locality"
},
  "geometry": {"coordinates":[106.88079,31.44142],"type":"Point"}
}