{
  "type": "Feature",
  "properties": {
    "gn:admin1_code":"2.0",
    "gn:asciiname":"Wuyan",
    "gn:country_code":"CN",
    "gn:dem":71,
    "gn:feature_class":"P",
    "gn:feature_code":"PPL",
    "gn:name":"Wuyan",
    "gn:population":0,
    "gn:timezone":"Asia/Shanghai",
    "iso:country":"CN",
    "name:zho_x_preferred":[
        "\u4e4c\u5ca9"
    ],
    "wof:name":"Wuyan",
    "wof:placetype":"locality"
},
  "geometry": {"coordinates":[121.06846000000002,28.61822],"type":"Point"}
}