{
  "type": "Feature",
  "properties": {
    "gn:admin1_code":"1.0",
    "gn:asciiname":"Zhongtangzhanjia",
    "gn:country_code":"CN",
    "gn:dem":98,
    "gn:feature_class":"P",
    "gn:feature_code":"PPL",
    "gn:name":"Zhongtangzhanjia",
    "gn:population":0,
    "gn:timezone":"Asia/Shanghai",
    "iso:country":"CN",
    "name:zho_x_preferred":[
        "\u4e2d\u5802\u8a79\u5bb6"
    ],
    "wof:name":"Zhongtangzhanjia",
    "wof:placetype":"locality"
},
  "geometry": {"coordinates":[116.95044,29.70536],"type":"Point"}
}