{
  "type": "Feature",
  "properties": {
    "gn:admin1_code":"32.0",
    "gn:asciiname":"Rigezha",
    "gn:country_code":"CN",
    "gn:dem":3311,
    "gn:feature_class":"P",
    "gn:feature_code":"PPL",
    "gn:name":"Rigezha",
    "gn:population":0,
    "gn:timezone":"Asia/Shanghai",
    "iso:country":"CN",
    "name:zho_x_preferred":[
        "\u65e5\u683c\u624e"
    ],
    "wof:name":"Rigezha",
    "wof:placetype":"locality"
},
  "geometry": {"coordinates":[101.764,32.8883],"type":"Point"}
}