{
  "type": "Feature",
  "properties": {
    "gn:admin1_code":"16.0",
    "gn:asciiname":"Zhanjiawan",
    "gn:country_code":"CN",
    "gn:dem":976,
    "gn:feature_class":"P",
    "gn:feature_code":"PPL",
    "gn:name":"Zhanjiawan",
    "gn:population":0,
    "gn:timezone":"Asia/Shanghai",
    "iso:country":"CN",
    "name:zho_x_preferred":[
        "\u7ad9\u5bb6\u5f2f"
    ],
    "wof:name":"Zhanjiawan",
    "wof:placetype":"locality"
},
  "geometry": {"coordinates":[104.94799999999999,24.7231],"type":"Point"}
}