{
  "type": "Feature",
  "properties": {
    "gn:admin1_code":"10",
    "gn:asciiname":"Laojuzi Nangou",
    "gn:country_code":"CN",
    "gn:dem":847,
    "gn:feature_class":"P",
    "gn:feature_code":"PPL",
    "gn:name":"Laojuzi Nangou",
    "gn:population":0,
    "gn:timezone":"Asia/Shanghai",
    "iso:country":"CN",
    "name:zho_x_preferred":[
        "\u8001\u5c40\u5b50\u5357\u6c9f"
    ],
    "wof:name":"Laojuzi Nangou",
    "wof:placetype":"locality"
},
  "geometry": {"coordinates":[118.20085,41.51172],"type":"Point"}
}