{
  "type": "Feature",
  "properties": {
    "gn:admin1_code":"4.0",
    "gn:asciiname":"Qianwangzixu",
    "gn:country_code":"CN",
    "gn:dem":5,
    "gn:feature_class":"P",
    "gn:feature_code":"PPL",
    "gn:name":"Qianwangzixu",
    "gn:population":0,
    "gn:timezone":"Asia/Shanghai",
    "iso:country":"CN",
    "name:zho_x_preferred":[
        "\u524d\u5f80\u5b57\u5729"
    ],
    "wof:name":"Qianwangzixu",
    "wof:placetype":"locality"
},
  "geometry": {"coordinates":[120.75923,32.05468],"type":"Point"}
}