{
  "type": "Feature",
  "properties": {
    "gn:admin1_code":"28.0",
    "gn:asciiname":"Zhangxianzhuang",
    "gn:country_code":"CN",
    "gn:dem":8,
    "gn:feature_class":"P",
    "gn:feature_code":"PPL",
    "gn:name":"Zhangxianzhuang",
    "gn:population":0,
    "gn:timezone":"Asia/Shanghai",
    "iso:country":"CN",
    "name:zho_x_preferred":[
        "\u5f20\u732e\u5e84"
    ],
    "wof:name":"Zhangxianzhuang",
    "wof:placetype":"locality"
},
  "geometry": {"coordinates":[117.19329999999999,39.27307],"type":"Point"}
}