{
  "type": "Feature",
  "properties": {
    "gn:admin1_code":"19.0",
    "gn:asciiname":"Jiujiazi",
    "gn:country_code":"CN",
    "gn:dem":595,
    "gn:feature_class":"P",
    "gn:feature_code":"PPL",
    "gn:name":"Jiujiazi",
    "gn:population":0,
    "gn:timezone":"Asia/Shanghai",
    "iso:country":"CN",
    "name:zho_x_preferred":[
        "\u4e5d\u5bb6\u5b50"
    ],
    "wof:name":"Jiujiazi",
    "wof:placetype":"locality"
},
  "geometry": {"coordinates":[119.39400000000001,41.5345],"type":"Point"}
}