{
  "type": "Feature",
  "properties": {
    "gn:admin1_code":"10",
    "gn:asciiname":"Huangguantun",
    "gn:country_code":"CN",
    "gn:dem":31,
    "gn:feature_class":"P",
    "gn:feature_code":"PPL",
    "gn:name":"Huangguantun",
    "gn:population":0,
    "gn:timezone":"Asia/Shanghai",
    "iso:country":"CN",
    "name:zho_x_preferred":[
        "\u9ec4\u5b98\u5c6f"
    ],
    "wof:name":"Huangguantun",
    "wof:placetype":"locality"
},
  "geometry": {"coordinates":[115.883,37.3411],"type":"Point"}
}