{
  "type": "Feature",
  "properties": {
    "gn:admin1_code":"2.0",
    "gn:asciiname":"Bingfengyuan",
    "gn:country_code":"CN",
    "gn:dem":334,
    "gn:feature_class":"P",
    "gn:feature_code":"PPL",
    "gn:name":"Bingfengyuan",
    "gn:population":0,
    "gn:timezone":"Asia/Shanghai",
    "iso:country":"CN",
    "name:und_x_variant":[
        "\u5c4f\u98ce\u6e90",
        "Bingfengyuan"
    ],
    "wof:name":"Bingfengyuan",
    "wof:placetype":"locality"
},
  "geometry": {"coordinates":[119.84232,29.8047],"type":"Point"}
}