{
  "type": "Feature",
  "properties": {
    "gn:admin1_code":"5.0",
    "gn:asciiname":"Xiwangjiacun",
    "gn:country_code":"CN",
    "gn:dem":144,
    "gn:feature_class":"P",
    "gn:feature_code":"PPL",
    "gn:name":"Xiwangjiacun",
    "gn:population":0,
    "gn:timezone":"Asia/Shanghai",
    "iso:country":"CN",
    "name:zho_x_preferred":[
        "\u897f\u738b\u5bb6\u6751"
    ],
    "wof:name":"Xiwangjiacun",
    "wof:placetype":"locality"
},
  "geometry": {"coordinates":[125.31621,44.79921],"type":"Point"}
}