{
  "type": "Feature",
  "properties": {
    "gn:admin1_code":"29",
    "gn:asciiname":"Hansuo",
    "gn:country_code":"CN",
    "gn:dem":1588,
    "gn:feature_class":"P",
    "gn:feature_code":"PPL",
    "gn:name":"Hansuo",
    "gn:population":0,
    "gn:timezone":"Asia/Shanghai",
    "iso:country":"CN",
    "name:zho_x_preferred":[
        "\u97e9\u6240"
    ],
    "wof:name":"Hansuo",
    "wof:placetype":"locality"
},
  "geometry": {"coordinates":[102.19199999999999,24.7002],"type":"Point"}
}