{
  "type": "Feature",
  "properties": {
    "gn:admin1_code":"26",
    "gn:asciiname":"Mijia",
    "gn:country_code":"CN",
    "gn:dem":1070,
    "gn:feature_class":"P",
    "gn:feature_code":"PPL",
    "gn:name":"Mijia",
    "gn:population":0,
    "gn:timezone":"Asia/Shanghai",
    "iso:country":"CN",
    "name:und_x_variant":[
        "\u7c73\u5bb6"
    ],
    "name:zho_x_preferred":[
        "\u7c73\u5bb6"
    ],
    "wof:name":"Mijia",
    "wof:placetype":"locality"
},
  "geometry": {"coordinates":[108.45694,34.67028],"type":"Point"}
}