{
  "type": "Feature",
  "properties": {
    "gn:admin1_code":"19.0",
    "gn:asciiname":"Yaojiadian",
    "gn:country_code":"CN",
    "gn:dem":185,
    "gn:feature_class":"P",
    "gn:feature_code":"PPL",
    "gn:name":"Yaojiadian",
    "gn:population":0,
    "gn:timezone":"Asia/Shanghai",
    "iso:country":"CN",
    "name:zho_x_preferred":[
        "\u59da\u5bb6\u5e97"
    ],
    "wof:name":"Yaojiadian",
    "wof:placetype":"locality"
},
  "geometry": {"coordinates":[121.55283,41.56422],"type":"Point"}
}