{
  "type": "Feature",
  "properties": {
    "gn:admin1_code":"12.0",
    "gn:asciiname":"Yaoyazi",
    "gn:country_code":"CN",
    "gn:dem":1340,
    "gn:feature_class":"P",
    "gn:feature_code":"PPL",
    "gn:name":"Yaoyazi",
    "gn:population":0,
    "gn:timezone":"Asia/Shanghai",
    "iso:country":"CN",
    "name:zho_x_preferred":[
        "\u7a91\u57ad\u5b50"
    ],
    "wof:name":"Yaoyazi",
    "wof:placetype":"locality"
},
  "geometry": {"coordinates":[111.05441,31.54038],"type":"Point"}
}