{
  "type": "Feature",
  "properties": {
    "gn:admin1_code":"23.0",
    "gn:asciiname":"Gangxi Liudui",
    "gn:country_code":"CN",
    "gn:dem":5,
    "gn:feature_class":"P",
    "gn:feature_code":"PPLF",
    "gn:name":"Gangxi Liudui",
    "gn:population":0,
    "gn:timezone":"Asia/Shanghai",
    "iso:country":"CN",
    "name:zho_x_preferred":[
        "Gangxi Liudui"
    ],
    "name:zho_x_variant":[
        "\u6e2f\u897f\u516d\u961f"
    ],
    "wof:name":"Gangxi Liudui",
    "wof:placetype":"locality"
},
  "geometry": {"coordinates":[121.2012,31.78763],"type":"Point"}
}