{
  "type": "Feature",
  "properties": {
    "gn:admin1_code":"5.0",
    "gn:asciiname":"Caomiaocun",
    "gn:country_code":"CN",
    "gn:dem":357,
    "gn:feature_class":"P",
    "gn:feature_code":"PPL",
    "gn:name":"Caomiaocun",
    "gn:population":0,
    "gn:timezone":"Asia/Shanghai",
    "iso:country":"CN",
    "name:zho_x_preferred":[
        "\u8349\u5e99\u6751"
    ],
    "wof:name":"Caomiaocun",
    "wof:placetype":"locality"
},
  "geometry": {"coordinates":[125.39978000000001,42.99484],"type":"Point"}
}