{
  "type": "Feature",
  "properties": {
    "gn:admin1_code":"33.0",
    "gn:asciiname":"Liangtianwo",
    "gn:country_code":"CN",
    "gn:dem":1050,
    "gn:feature_class":"P",
    "gn:feature_code":"PPL",
    "gn:name":"Liangtianwo",
    "gn:population":0,
    "gn:timezone":"Asia/Shanghai",
    "iso:country":"CN",
    "name:zho_x_preferred":[
        "\u4e24\u5929\u7a9d"
    ],
    "wof:name":"Liangtianwo",
    "wof:placetype":"locality"
},
  "geometry": {"coordinates":[108.79947,28.95829],"type":"Point"}
}