{
  "type": "Feature",
  "properties": {
    "gn:admin1_code":"20.0",
    "gn:asciiname":"Xingshan",
    "gn:country_code":"CN",
    "gn:dem":414,
    "gn:feature_class":"P",
    "gn:feature_code":"PPL",
    "gn:name":"Xingshan",
    "gn:population":0,
    "gn:timezone":"Asia/Shanghai",
    "iso:country":"CN",
    "name:ceb_x_preferred":[
        "Xingshan"
    ],
    "name:deu_x_preferred":[
        "Xingshan"
    ],
    "name:fra_x_preferred":[
        "Xingshan"
    ],
    "name:nor_x_preferred":[
        "Xingshan"
    ],
    "name:rus_x_preferred":[
        "\u0421\u0438\u043d\u0448\u0430\u043d\u044c"
    ],
    "name:swe_x_preferred":[
        "Xingshan"
    ],
    "name:zho_x_preferred":[
        "\u674f\u5c71"
    ],
    "wof:name":"Xingshan",
    "wof:placetype":"locality"
},
  "geometry": {"coordinates":[122.20984,47.46957],"type":"Point"}
}