{
  "type": "Feature",
  "properties": {
    "gn:admin1_code":"26.0",
    "gn:asciiname":"Chaoliucun",
    "gn:country_code":"CN",
    "gn:dem":738,
    "gn:feature_class":"P",
    "gn:feature_code":"PPL",
    "gn:name":"Chaoliucun",
    "gn:population":0,
    "gn:timezone":"Asia/Shanghai",
    "iso:country":"CN",
    "name:zho_x_preferred":[
        "\u6641\u7559\u6751"
    ],
    "wof:name":"Chaoliucun",
    "wof:placetype":"locality"
},
  "geometry": {"coordinates":[107.98907,34.51714],"type":"Point"}
}