{
  "type": "Feature",
  "properties": {
    "gn:admin1_code":"10.0",
    "gn:asciiname":"Yaozhongli",
    "gn:country_code":"CN",
    "gn:dem":8,
    "gn:feature_class":"P",
    "gn:feature_code":"PPL",
    "gn:name":"Yaozhongli",
    "gn:population":0,
    "gn:timezone":"Asia/Shanghai",
    "iso:country":"CN",
    "name:zho_x_preferred":[
        "\u8000\u4e2d\u91cc"
    ],
    "wof:name":"Yaozhongli",
    "wof:placetype":"locality"
},
  "geometry": {"coordinates":[119.57704,39.91895],"type":"Point"}
}