{
  "type": "Feature",
  "properties": {
    "gn:admin1_code":"4.0",
    "gn:asciiname":"Juxing Sizu",
    "gn:country_code":"CN",
    "gn:dem":-2,
    "gn:feature_class":"P",
    "gn:feature_code":"PPLF",
    "gn:name":"Juxing Sizu",
    "gn:population":0,
    "gn:timezone":"Asia/Shanghai",
    "iso:country":"CN",
    "name:zho_x_preferred":[
        "\u5de8\u661f\u56db\u7ec4"
    ],
    "wof:name":"Juxing Sizu",
    "wof:placetype":"locality"
},
  "geometry": {"coordinates":[120.08499999999999,33.7222],"type":"Point"}
}