{
  "type": "Feature",
  "properties": {
    "gn:admin1_code":"15.0",
    "gn:asciiname":"Huangjiaquan",
    "gn:country_code":"CN",
    "gn:dem":1751,
    "gn:feature_class":"P",
    "gn:feature_code":"PPL",
    "gn:name":"Huangjiaquan",
    "gn:population":0,
    "gn:timezone":"Asia/Shanghai",
    "iso:country":"CN",
    "name:zho_x_preferred":[
        "\u9ec4\u5bb6\u6cc9"
    ],
    "wof:name":"Huangjiaquan",
    "wof:placetype":"locality"
},
  "geometry": {"coordinates":[102.148,38.3242],"type":"Point"}
}