{
  "type": "Feature",
  "properties": {
    "gn:admin1_code":"29.0",
    "gn:asciiname":"Lindu",
    "gn:country_code":"CN",
    "gn:dem":3353,
    "gn:feature_class":"P",
    "gn:feature_code":"PPL",
    "gn:name":"Lindu",
    "gn:population":0,
    "gn:timezone":"Asia/Shanghai",
    "iso:country":"CN",
    "name:zho_x_preferred":[
        "\u6797\u90fd"
    ],
    "wof:name":"Lindu",
    "wof:placetype":"locality"
},
  "geometry": {"coordinates":[99.79259999999999,27.7924],"type":"Point"}
}