{
  "type": "Feature",
  "properties": {
    "gn:admin1_code":"10.0",
    "gn:asciiname":"Beimengzhuang",
    "gn:country_code":"CN",
    "gn:dem":22,
    "gn:feature_class":"P",
    "gn:feature_code":"PPL",
    "gn:name":"Beimengzhuang",
    "gn:population":0,
    "gn:timezone":"Asia/Shanghai",
    "iso:country":"CN",
    "name:zho_x_preferred":[
        "\u5317\u5b5f\u5e84"
    ],
    "wof:name":"Beimengzhuang",
    "wof:placetype":"locality"
},
  "geometry": {"coordinates":[116.19058,37.65735],"type":"Point"}
}