{
  "type": "Feature",
  "properties": {
    "gn:admin1_code":"24.0",
    "gn:asciiname":"Wenjiazhai",
    "gn:country_code":"CN",
    "gn:dem":1081,
    "gn:feature_class":"P",
    "gn:feature_code":"PPL",
    "gn:name":"Wenjiazhai",
    "gn:population":0,
    "gn:timezone":"Asia/Shanghai",
    "iso:country":"CN",
    "name:zho_x_preferred":[
        "\u6e29\u5bb6\u5be8"
    ],
    "wof:name":"Wenjiazhai",
    "wof:placetype":"locality"
},
  "geometry": {"coordinates":[111.05634000000001,38.52509000000001],"type":"Point"}
}