{
  "type": "Feature",
  "properties": {
    "gn:admin1_code":"12.0",
    "gn:asciiname":"Xiongjiabao",
    "gn:country_code":"CN",
    "gn:dem":855,
    "gn:feature_class":"P",
    "gn:feature_code":"PPL",
    "gn:name":"Xiongjiabao",
    "gn:population":0,
    "gn:timezone":"Asia/Shanghai",
    "iso:country":"CN",
    "name:zho_x_preferred":[
        "\u718a\u5bb6\u5305"
    ],
    "wof:name":"Xiongjiabao",
    "wof:placetype":"locality"
},
  "geometry": {"coordinates":[110.31613,31.9958],"type":"Point"}
}