{
  "type": "Feature",
  "properties": {
    "gn:admin1_code":"31.0",
    "gn:asciiname":"Qibailang",
    "gn:country_code":"CN",
    "gn:dem":13,
    "gn:feature_class":"P",
    "gn:feature_code":"PPL",
    "gn:name":"Qibailang",
    "gn:population":0,
    "gn:timezone":"Asia/Shanghai",
    "iso:country":"CN",
    "name:zho_x_preferred":[
        "\u4e03\u67cf\u6994"
    ],
    "wof:name":"Qibailang",
    "wof:placetype":"locality"
},
  "geometry": {"coordinates":[109.02646,19.4675],"type":"Point"}
}