{
  "type": "Feature",
  "properties": {
    "gn:admin1_code":"32.0",
    "gn:asciiname":"Quezha",
    "gn:country_code":"CN",
    "gn:dem":3438,
    "gn:feature_class":"P",
    "gn:feature_code":"PPL",
    "gn:name":"Quezha",
    "gn:population":0,
    "gn:timezone":"Asia/Shanghai",
    "iso:country":"CN",
    "name:zho_x_preferred":[
        "\u5374\u624e"
    ],
    "wof:name":"Quezha",
    "wof:placetype":"locality"
},
  "geometry": {"coordinates":[99.40349999999999,31.5006],"type":"Point"}
}