{
  "type": "Feature",
  "properties": {
    "gn:admin1_code":"8.0",
    "gn:asciiname":"Tiancaogang",
    "gn:country_code":"CN",
    "gn:dem":145,
    "gn:feature_class":"P",
    "gn:feature_code":"PPL",
    "gn:name":"Tiancaogang",
    "gn:population":0,
    "gn:timezone":"Asia/Shanghai",
    "iso:country":"CN",
    "name:zho_x_preferred":[
        "\u751c\u8349\u5c97"
    ],
    "wof:name":"Tiancaogang",
    "wof:placetype":"locality"
},
  "geometry": {"coordinates":[124.41568999999998,47.22164],"type":"Point"}
}