{
  "type": "Feature",
  "properties": {
    "gn:admin1_code":"25",
    "gn:asciiname":"Hougu",
    "gn:country_code":"CN",
    "gn:dem":44,
    "gn:feature_class":"P",
    "gn:feature_code":"PPL",
    "gn:name":"Hougu",
    "gn:population":0,
    "gn:timezone":"Asia/Shanghai",
    "iso:country":"CN",
    "name:zho_x_preferred":[
        "\u540e\u8c37"
    ],
    "wof:name":"Hougu",
    "wof:placetype":"locality"
},
  "geometry": {"coordinates":[116.04000000000001,35.2293],"type":"Point"}
}