{
  "type": "Feature",
  "properties": {
    "gn:admin1_code":"19.0",
    "gn:asciiname":"Zhenquansi Xiagou",
    "gn:country_code":"CN",
    "gn:dem":47,
    "gn:feature_class":"P",
    "gn:feature_code":"PPL",
    "gn:name":"Zhenquansi Xiagou",
    "gn:population":0,
    "gn:timezone":"Asia/Shanghai",
    "iso:country":"CN",
    "name:zho_x_preferred":[
        "\u9547\u6cc9\u5bfa\u4e0b\u6c9f"
    ],
    "wof:name":"Zhenquansi Xiagou",
    "wof:placetype":"locality"
},
  "geometry": {"coordinates":[121.373,38.8745],"type":"Point"}
}