{
  "type": "Feature",
  "properties": {
    "gn:admin1_code":"02",
    "gn:asciiname":"Dazhangcun",
    "gn:country_code":"CN",
    "gn:dem":3,
    "gn:feature_class":"P",
    "gn:feature_code":"PPL",
    "gn:name":"Dazhangcun",
    "gn:population":0,
    "gn:timezone":"Asia/Shanghai",
    "iso:country":"CN",
    "name:und_x_variant":[
        "Ta-chiang-ts\u2019un",
        "Dazhang",
        "Dazhangcun"
    ],
    "name:zho_x_preferred":[
        "\u5927\u5f20"
    ],
    "name:zho_x_variant":[
        "\u5927\u5f20\u6751"
    ],
    "wof:name":"Dazhangcun",
    "wof:placetype":"locality"
},
  "geometry": {"coordinates":[121.3205,29.70587],"type":"Point"}
}