{
  "type": "Feature",
  "properties": {
    "gn:admin1_code":"30",
    "gn:asciiname":"Xialan",
    "gn:country_code":"CN",
    "gn:dem":4,
    "gn:feature_class":"P",
    "gn:feature_code":"PPL",
    "gn:name":"Xialan",
    "gn:population":0,
    "gn:timezone":"Asia/Urumqi",
    "iso:country":"CN",
    "name:zho_x_preferred":[
        "Hsia-lan-ts\u2019un"
    ],
    "name:zho_x_variant":[
        "\u4e0b\u5c9a"
    ],
    "wof:name":"Xialan",
    "wof:placetype":"locality"
},
  "geometry": {"coordinates":[110.15868,20.87658],"type":"Point"}
}