{
  "type": "Feature",
  "properties": {
    "gn:admin1_code":"30.0",
    "gn:asciiname":"Dongba Zhen",
    "gn:country_code":"CN",
    "gn:dem":26,
    "gn:feature_class":"P",
    "gn:feature_code":"PPL",
    "gn:name":"Dongba Zhen",
    "gn:population":0,
    "gn:timezone":"Asia/Shanghai",
    "iso:country":"CN",
    "name:zho_x_preferred":[
        "\u4e1c\u575d\u9547"
    ],
    "wof:name":"Dongba Zhen",
    "wof:placetype":"locality"
},
  "geometry": {"coordinates":[111.73761,22.93311],"type":"Point"}
}