{
  "type": "Feature",
  "properties": {
    "gn:admin1_code":"2.0",
    "gn:asciiname":"Wuliyuan",
    "gn:country_code":"CN",
    "gn:dem":75,
    "gn:feature_class":"P",
    "gn:feature_code":"PPL",
    "gn:name":"Wuliyuan",
    "gn:population":0,
    "gn:timezone":"Asia/Shanghai",
    "iso:country":"CN",
    "name:und_x_variant":[
        "\u4e94\u91cc\u6e90",
        "Wuliyuan"
    ],
    "wof:name":"Wuliyuan",
    "wof:placetype":"locality"
},
  "geometry": {"coordinates":[119.23560999999999,29.43071],"type":"Point"}
}