{
  "type": "Feature",
  "properties": {
    "gn:admin1_code":"5.0",
    "gn:asciiname":"Fanjiayao",
    "gn:country_code":"CN",
    "gn:dem":212,
    "gn:feature_class":"P",
    "gn:feature_code":"PPL",
    "gn:name":"Fanjiayao",
    "gn:population":0,
    "gn:timezone":"Asia/Shanghai",
    "iso:country":"CN",
    "name:zho_x_preferred":[
        "\u8303\u5bb6\u7a91"
    ],
    "wof:name":"Fanjiayao",
    "wof:placetype":"locality"
},
  "geometry": {"coordinates":[124.79497000000001,43.86632],"type":"Point"}
}