{
  "type": "Feature",
  "properties": {
    "gn:admin1_code":"19.0",
    "gn:asciiname":"Sandaoliangzi",
    "gn:country_code":"CN",
    "gn:dem":390,
    "gn:feature_class":"P",
    "gn:feature_code":"PPL",
    "gn:name":"Sandaoliangzi",
    "gn:population":0,
    "gn:timezone":"Asia/Shanghai",
    "iso:country":"CN",
    "name:zho_x_preferred":[
        "\u4e09\u9053\u6881\u5b50"
    ],
    "wof:name":"Sandaoliangzi",
    "wof:placetype":"locality"
},
  "geometry": {"coordinates":[119.21969,40.66957],"type":"Point"}
}