{
  "type": "Feature",
  "properties": {
    "gn:admin1_code":"31.0",
    "gn:asciiname":"Yongdong",
    "gn:country_code":"CN",
    "gn:dem":341,
    "gn:feature_class":"P",
    "gn:feature_code":"PPL",
    "gn:name":"Yongdong",
    "gn:population":0,
    "gn:timezone":"Asia/Shanghai",
    "iso:country":"CN",
    "name:und_x_variant":[
        "\u62e5\u4e1c"
    ],
    "name:zho_x_preferred":[
        "\u62e5\u4e1c"
    ],
    "wof:name":"Yongdong",
    "wof:placetype":"locality"
},
  "geometry": {"coordinates":[109.29376000000001,19.1591],"type":"Point"}
}