{
  "type": "Feature",
  "properties": {
    "gn:admin1_code":"26",
    "gn:asciiname":"Wangducun",
    "gn:country_code":"CN",
    "gn:dem":539,
    "gn:feature_class":"P",
    "gn:feature_code":"PPL",
    "gn:name":"Wangducun",
    "gn:population":0,
    "gn:timezone":"Asia/Shanghai",
    "iso:country":"CN",
    "name:und_x_variant":[
        "Wangdu",
        "Wangducun"
    ],
    "name:zho_x_preferred":[
        "\u738b\u90fd"
    ],
    "name:zho_x_variant":[
        "\u738b\u90fd\u6751"
    ],
    "wof:name":"Wangducun",
    "wof:placetype":"locality"
},
  "geometry": {"coordinates":[108.40664,34.3924],"type":"Point"}
}