{
  "type": "Feature",
  "properties": {
    "gn:admin1_code":"19.0",
    "gn:asciiname":"Fuxingdicun",
    "gn:country_code":"CN",
    "gn:dem":94,
    "gn:feature_class":"P",
    "gn:feature_code":"PPL",
    "gn:name":"Fuxingdicun",
    "gn:population":0,
    "gn:timezone":"Asia/Shanghai",
    "iso:country":"CN",
    "name:zho_x_preferred":[
        "\u798f\u5174\u5730\u6751"
    ],
    "wof:name":"Fuxingdicun",
    "wof:placetype":"locality"
},
  "geometry": {"coordinates":[121.511,41.81399999999999],"type":"Point"}
}