{
  "type": "Feature",
  "properties": {
    "gn:admin1_code":"15.0",
    "gn:asciiname":"Shanghongtu Wanzi",
    "gn:country_code":"CN",
    "gn:dem":2841,
    "gn:feature_class":"P",
    "gn:feature_code":"PPL",
    "gn:name":"Shanghongtu Wanzi",
    "gn:population":0,
    "gn:timezone":"Asia/Shanghai",
    "iso:country":"CN",
    "name:zho_x_preferred":[
        "\u4e0a\u7ea2\u571f\u6e7e\u5b50"
    ],
    "wof:name":"Shanghongtu Wanzi",
    "wof:placetype":"locality"
},
  "geometry": {"coordinates":[97.98090000000001,39.1808],"type":"Point"}
}