{
  "type": "Feature",
  "properties": {
    "gn:admin1_code":"1.0",
    "gn:asciiname":"Lianhuancun",
    "gn:country_code":"CN",
    "gn:dem":88,
    "gn:feature_class":"P",
    "gn:feature_code":"PPL",
    "gn:name":"Lianhuancun",
    "gn:population":0,
    "gn:timezone":"Asia/Shanghai",
    "iso:country":"CN",
    "name:zho_x_preferred":[
        "\u740f\u73af\u6751"
    ],
    "wof:name":"Lianhuancun",
    "wof:placetype":"locality"
},
  "geometry": {"coordinates":[117.60275,32.60074],"type":"Point"}
}