{
  "type": "Feature",
  "properties": {
    "gn:admin1_code":"7.0",
    "gn:asciiname":"Renping",
    "gn:country_code":"CN",
    "gn:dem":13,
    "gn:feature_class":"P",
    "gn:feature_code":"PPL",
    "gn:name":"Renping",
    "gn:population":0,
    "gn:timezone":"Asia/Shanghai",
    "iso:country":"CN",
    "name:zho_x_preferred":[
        "\u4eba\u576a"
    ],
    "wof:name":"Renping",
    "wof:placetype":"locality"
},
  "geometry": {"coordinates":[117.89462,24.17805],"type":"Point"}
}