{
  "type": "Feature",
  "properties": {
    "gn:admin1_code":"19.0",
    "gn:asciiname":"Sangedingzi",
    "gn:country_code":"CN",
    "gn:dem":420,
    "gn:feature_class":"P",
    "gn:feature_code":"PPL",
    "gn:name":"Sangedingzi",
    "gn:population":0,
    "gn:timezone":"Asia/Shanghai",
    "iso:country":"CN",
    "name:zho_x_preferred":[
        "\u4e09\u4e2a\u9876\u5b50"
    ],
    "wof:name":"Sangedingzi",
    "wof:placetype":"locality"
},
  "geometry": {"coordinates":[124.97078,41.37261],"type":"Point"}
}