{
  "type": "Feature",
  "properties": {
    "gn:admin1_code":"25",
    "gn:asciiname":"Qiandonglou",
    "gn:country_code":"CN",
    "gn:dem":43,
    "gn:feature_class":"P",
    "gn:feature_code":"PPL",
    "gn:name":"Qiandonglou",
    "gn:population":0,
    "gn:timezone":"Asia/Shanghai",
    "iso:country":"CN",
    "name:zho_x_preferred":[
        "\u524d\u8463\u697c"
    ],
    "wof:name":"Qiandonglou",
    "wof:placetype":"locality"
},
  "geometry": {"coordinates":[116.199,35.1638],"type":"Point"}
}