{
  "type": "Feature",
  "properties": {
    "gn:admin1_code":"06",
    "gn:asciiname":"Obo",
    "gn:country_code":"CN",
    "gn:dem":3425,
    "gn:feature_class":"P",
    "gn:feature_code":"PPLA4",
    "gn:name":"Obo",
    "gn:population":0,
    "gn:timezone":"Asia/Shanghai",
    "iso:country":"CN",
    "name:und_x_variant":[
        "Ebo",
        "O-po-ch\u2019eng",
        "O-po",
        "Obo",
        "Ebao",
        "Hongtu",
        "Ebao Zhen",
        "Hongtucheng"
    ],
    "name:zho_x_preferred":[
        "\u5ce8\u5821"
    ],
    "name:zho_x_variant":[
        "\u7ea2\u571f",
        "\u5ce8\u5821\u9547",
        "\u7ea2\u571f\u57ce"
    ],
    "wof:name":"Obo",
    "wof:placetype":"locality"
},
  "geometry": {"coordinates":[100.93299,37.96463],"type":"Point"}
}