{
  "type": "Feature",
  "properties": {
    "gn:admin1_code":"06",
    "gn:asciiname":"Obo",
    "gn:country_code":"CN",
    "gn:dem":3425,
    "gn:feature_class":"P",
    "gn:feature_code":"PPLA4",
    "gn:name":"Obo",
    "gn:population":0,
    "gn:timezone":"Asia/Shanghai",
    "iso:country":"CN",
    "name:azb_x_preferred":[
        "\u0627\u0648\u0628\u0648"
    ],
    "name:ceb_x_preferred":[
        "Obo"
    ],
    "name:deu_x_preferred":[
        "Obo"
    ],
    "name:est_x_preferred":[
        "Obo"
    ],
    "name:fas_x_preferred":[
        "\u0627\u0648\u0628\u0648"
    ],
    "name:fra_x_preferred":[
        "Obo"
    ],
    "name:frr_x_preferred":[
        "Obo"
    ],
    "name:ita_x_preferred":[
        "Obo"
    ],
    "name:jpn_x_preferred":[
        "\u30aa\u30dc"
    ],
    "name:lit_x_preferred":[
        "Obo"
    ],
    "name:nld_x_preferred":[
        "Obo"
    ],
    "name:pol_x_preferred":[
        "Obo"
    ],
    "name:ron_x_preferred":[
        "Obo"
    ],
    "name:rus_x_preferred":[
        "\u041e\u0431\u043e"
    ],
    "name:sag_x_preferred":[
        "Obo"
    ],
    "name:sqi_x_preferred":[
        "Obo"
    ],
    "name:swe_x_preferred":[
        "Obo"
    ],
    "name:tur_x_preferred":[
        "Obo"
    ],
    "name:und_x_variant":[
        "Ebo",
        "O-po-ch\u2019eng",
        "O-po",
        "Ebao",
        "Hongtu",
        "Ebao Zhen",
        "Hongtucheng"
    ],
    "name:urd_x_preferred":[
        "\u0627\u0648\u0628\u0648"
    ],
    "name:xmf_x_preferred":[
        "\u10dd\u10d1\u10dd"
    ],
    "name:zho_x_preferred":[
        "\u5ce8\u5821"
    ],
    "name:zho_x_variant":[
        "\u7ea2\u571f",
        "\u5ce8\u5821\u9547",
        "\u7ea2\u571f\u57ce"
    ],
    "wof:name":"Obo",
    "wof:placetype":"locality"
},
  "geometry": {"coordinates":[100.93299,37.96463],"type":"Point"}
}