{
  "type": "Feature",
  "properties": {
    "gn:admin1_code":"7",
    "gn:asciiname":"Houlinguo",
    "gn:country_code":"CN",
    "gn:dem":43,
    "gn:feature_class":"P",
    "gn:feature_code":"PPL",
    "gn:name":"Houlinguo",
    "gn:population":0,
    "gn:timezone":"Asia/Shanghai",
    "iso:country":"CN",
    "name:und_x_variant":[
        "\u540e\u6797\u8fc7",
        "Houlinguo"
    ],
    "wof:name":"Houlinguo",
    "wof:placetype":"locality"
},
  "geometry": {"coordinates":[118.71576,25.00371],"type":"Point"}
}