{
  "type": "Feature",
  "properties": {
    "gn:admin1_code":"30",
    "gn:asciiname":"Dongtangcun",
    "gn:country_code":"CN",
    "gn:dem":85,
    "gn:feature_class":"P",
    "gn:feature_code":"PPL",
    "gn:name":"Dongtangcun",
    "gn:population":0,
    "gn:timezone":"Asia/Urumqi",
    "iso:country":"CN",
    "name:zho_x_preferred":[
        "\u4e1c\u5858\u6751"
    ],
    "wof:name":"Dongtangcun",
    "wof:placetype":"locality"
},
  "geometry": {"coordinates":[110.15269000000001,21.27779],"type":"Point"}
}