{
  "type": "Feature",
  "properties": {
    "gn:admin1_code":"25",
    "gn:asciiname":"Qijiagou",
    "gn:country_code":"CN",
    "gn:dem":94,
    "gn:feature_class":"P",
    "gn:feature_code":"PPL",
    "gn:name":"Qijiagou",
    "gn:population":0,
    "gn:timezone":"Asia/Shanghai",
    "iso:country":"CN",
    "name:zho_x_preferred":[
        "\u9f50\u5bb6\u6c9f"
    ],
    "wof:name":"Qijiagou",
    "wof:placetype":"locality"
},
  "geometry": {"coordinates":[119.131,35.4804],"type":"Point"}
}