{
  "type": "Feature",
  "properties": {
    "gn:admin1_code":"4.0",
    "gn:asciiname":"Gaojiacun",
    "gn:country_code":"CN",
    "gn:dem":6,
    "gn:feature_class":"P",
    "gn:feature_code":"PPL",
    "gn:name":"Gaojiacun",
    "gn:population":0,
    "gn:timezone":"Asia/Shanghai",
    "iso:country":"CN",
    "name:und_x_variant":[
        "\u9ad8\u5bb6\u6751"
    ],
    "name:zho_x_preferred":[
        "\u9ad8\u5bb6\u6751"
    ],
    "wof:name":"Gaojiacun",
    "wof:placetype":"locality"
},
  "geometry": {"coordinates":[120.36789,31.7463],"type":"Point"}
}