{
  "type": "Feature",
  "properties": {
    "gn:admin1_code":"07",
    "gn:asciiname":"Shishanbei",
    "gn:country_code":"CN",
    "gn:dem":349,
    "gn:feature_class":"P",
    "gn:feature_code":"PPL",
    "gn:name":"Shishanbei",
    "gn:population":0,
    "gn:timezone":"Asia/Shanghai",
    "iso:country":"CN",
    "name:zho_x_preferred":[
        "\u77f3\u5c71\u80cc"
    ],
    "wof:name":"Shishanbei",
    "wof:placetype":"locality"
},
  "geometry": {"coordinates":[116.00648,24.98961],"type":"Point"}
}