{
  "type": "Feature",
  "properties": {
    "gn:admin1_code":"16.0",
    "gn:asciiname":"Banxie",
    "gn:country_code":"CN",
    "gn:dem":610,
    "gn:feature_class":"P",
    "gn:feature_code":"PPL",
    "gn:name":"Banxie",
    "gn:population":0,
    "gn:timezone":"Asia/Shanghai",
    "iso:country":"CN",
    "name:zho_x_preferred":[
        "\u677f\u978b"
    ],
    "wof:name":"Banxie",
    "wof:placetype":"locality"
},
  "geometry": {"coordinates":[106.893,24.7504],"type":"Point"}
}