{
  "type": "Feature",
  "properties": {
    "gn:admin1_code":"2.0",
    "gn:asciiname":"Wu'ao",
    "gn:country_code":"CN",
    "gn:dem":734,
    "gn:feature_class":"P",
    "gn:feature_code":"PPL",
    "gn:name":"Wu\u2019ao",
    "gn:population":0,
    "gn:timezone":"Asia/Shanghai",
    "iso:country":"CN",
    "name:und_x_variant":[
        "\u5434\u5773"
    ],
    "name:zho_x_preferred":[
        "Wu\u2019ao"
    ],
    "wof:name":"Wu'ao",
    "wof:placetype":"locality"
},
  "geometry": {"coordinates":[119.89529,27.86556],"type":"Point"}
}