{
  "type": "Feature",
  "properties": {
    "gn:admin1_code":"11.0",
    "gn:asciiname":"Danzhuyuan",
    "gn:country_code":"CN",
    "gn:dem":466,
    "gn:feature_class":"P",
    "gn:feature_code":"PPL",
    "gn:name":"Danzhuyuan",
    "gn:population":0,
    "gn:timezone":"Asia/Shanghai",
    "iso:country":"CN",
    "name:zho_x_preferred":[
        "\u5355\u7af9\u6e90"
    ],
    "wof:name":"Danzhuyuan",
    "wof:placetype":"locality"
},
  "geometry": {"coordinates":[110.95698,25.0404],"type":"Point"}
}