{
  "type": "Feature",
  "properties": {
    "gn:admin1_code":"21",
    "gn:asciiname":"Dongjiabu",
    "gn:cc2":"CN",
    "gn:country_code":"CN",
    "gn:dem":1629,
    "gn:feature_class":"P",
    "gn:feature_code":"PPL",
    "gn:name":"Dongjiabu",
    "gn:population":0,
    "gn:timezone":"Asia/Shanghai",
    "iso:country":"CN",
    "name:und_x_variant":[
        "Tung-chia-p\u2019u",
        "Dongjiabu"
    ],
    "wof:name":"Dongjiabu",
    "wof:placetype":"locality"
},
  "geometry": {"coordinates":[105.57944000000001,36.67861],"type":"Point"}
}