{
  "type": "Feature",
  "properties": {
    "gn:admin1_code":"32.0",
    "gn:asciiname":"Bake",
    "gn:country_code":"CN",
    "gn:dem":2290,
    "gn:feature_class":"P",
    "gn:feature_code":"PPL",
    "gn:name":"Bake",
    "gn:population":0,
    "gn:timezone":"Asia/Shanghai",
    "iso:country":"CN",
    "name:ceb_x_preferred":[
        "Bake"
    ],
    "name:deu_x_preferred":[
        "Bake"
    ],
    "name:nds_x_preferred":[
        "Bake"
    ],
    "name:nld_x_preferred":[
        "Bake"
    ],
    "name:swe_x_preferred":[
        "Bake"
    ],
    "name:zho_x_preferred":[
        "\u516b\u79d1"
    ],
    "wof:name":"Bake",
    "wof:placetype":"locality"
},
  "geometry": {"coordinates":[100.958,28.0602],"type":"Point"}
}