{
  "type": "Feature",
  "properties": {
    "gn:admin1_code":"29.0",
    "gn:asciiname":"Shangyudingzhai",
    "gn:country_code":"CN",
    "gn:dem":1334,
    "gn:feature_class":"P",
    "gn:feature_code":"PPL",
    "gn:name":"Shangyudingzhai",
    "gn:population":0,
    "gn:timezone":"Asia/Shanghai",
    "iso:country":"CN",
    "name:zho_x_preferred":[
        "\u4e0a\u9c7c\u4e01\u5be8"
    ],
    "wof:name":"Shangyudingzhai",
    "wof:placetype":"locality"
},
  "geometry": {"coordinates":[98.923,25.0957],"type":"Point"}
}