{
  "type": "Feature",
  "properties": {
    "gn:admin1_code":"29",
    "gn:asciiname":"Qijiang",
    "gn:country_code":"CN",
    "gn:dem":1574,
    "gn:feature_class":"P",
    "gn:feature_code":"PPL",
    "gn:name":"Qijiang",
    "gn:population":0,
    "gn:timezone":"Asia/Shanghai",
    "iso:country":"CN",
    "name:zho_x_preferred":[
        "\u4e03\u6c5f"
    ],
    "wof:name":"Qijiang",
    "wof:placetype":"locality"
},
  "geometry": {"coordinates":[103.05200000000001,24.7324],"type":"Point"}
}