{
  "type": "Feature",
  "properties": {
    "gn:admin1_code":"10",
    "gn:asciiname":"Huashibamu",
    "gn:country_code":"CN",
    "gn:dem":32,
    "gn:feature_class":"P",
    "gn:feature_code":"PPL",
    "gn:name":"Huashibamu",
    "gn:population":0,
    "gn:timezone":"Asia/Shanghai",
    "iso:country":"CN",
    "name:zho_x_preferred":[
        "\u82b1\u5341\u516b\u4ea9"
    ],
    "wof:name":"Huashibamu",
    "wof:placetype":"locality"
},
  "geometry": {"coordinates":[115.73399999999999,37.1818],"type":"Point"}
}