{
  "type": "Feature",
  "properties": {
    "gn:admin1_code":"1.0",
    "gn:asciiname":"Zhenxicun",
    "gn:country_code":"CN",
    "gn:dem":38,
    "gn:feature_class":"P",
    "gn:feature_code":"PPL",
    "gn:name":"Zhenxicun",
    "gn:population":0,
    "gn:timezone":"Asia/Shanghai",
    "iso:country":"CN",
    "name:und_x_variant":[
        "Zhenxi"
    ],
    "name:zho_x_preferred":[
        "\u73cd\u6eaa\u6751"
    ],
    "wof:name":"Zhenxicun",
    "wof:placetype":"locality"
},
  "geometry": {"coordinates":[117.46666999999999,30.36389],"type":"Point"}
}