{
  "type": "Feature",
  "properties": {
    "gn:admin1_code":"25",
    "gn:asciiname":"Dongbiaoshan",
    "gn:country_code":"CN",
    "gn:dem":278,
    "gn:feature_class":"P",
    "gn:feature_code":"PPL",
    "gn:name":"Dongbiaoshan",
    "gn:population":0,
    "gn:timezone":"Asia/Shanghai",
    "iso:country":"CN",
    "name:zho_x_preferred":[
        "\u4e1c\u6753\u5c71"
    ],
    "wof:name":"Dongbiaoshan",
    "wof:placetype":"locality"
},
  "geometry": {"coordinates":[117.729,36.3786],"type":"Point"}
}