{
  "type": "Feature",
  "properties": {
    "gn:admin1_code":"14.0",
    "gn:asciiname":"Chonglaguo",
    "gn:country_code":"CN",
    "gn:dem":4580,
    "gn:feature_class":"P",
    "gn:feature_code":"PPL",
    "gn:name":"Chonglaguo",
    "gn:population":0,
    "gn:timezone":"Asia/Urumqi",
    "iso:country":"CN",
    "name:zho_x_preferred":[
        "\u51b2\u62c9\u679c"
    ],
    "wof:name":"Chonglaguo",
    "wof:placetype":"locality"
},
  "geometry": {"coordinates":[94.71792000000001,31.93655],"type":"Point"}
}