{
  "type": "Feature",
  "properties": {
    "gn:admin1_code":"25",
    "gn:asciiname":"Qidong",
    "gn:country_code":"CN",
    "gn:dem":35,
    "gn:feature_class":"P",
    "gn:feature_code":"PPL",
    "gn:name":"Qidong",
    "gn:population":0,
    "gn:timezone":"Asia/Shanghai",
    "iso:country":"CN",
    "name:ceb_x_preferred":[
        "Qidong"
    ],
    "name:deu_x_preferred":[
        "Qidong"
    ],
    "name:fra_x_preferred":[
        "Qidong"
    ],
    "name:nor_x_preferred":[
        "Qidong"
    ],
    "name:rus_x_preferred":[
        "\u0426\u0438\u0434\u0443\u043d"
    ],
    "name:swe_x_preferred":[
        "Qidong"
    ],
    "name:zho_x_preferred":[
        "\u675e\u4e1c"
    ],
    "wof:name":"Qidong",
    "wof:placetype":"locality"
},
  "geometry": {"coordinates":[119.31699999999999,36.5436],"type":"Point"}
}