{
  "type": "Feature",
  "properties": {
    "gn:admin1_code":"9.0",
    "gn:asciiname":"Houwutou",
    "gn:country_code":"CN",
    "gn:dem":68,
    "gn:feature_class":"P",
    "gn:feature_code":"PPL",
    "gn:name":"Houwutou",
    "gn:population":0,
    "gn:timezone":"Asia/Shanghai",
    "iso:country":"CN",
    "name:zho_x_preferred":[
        "\u540e\u7269\u5934"
    ],
    "wof:name":"Houwutou",
    "wof:placetype":"locality"
},
  "geometry": {"coordinates":[114.48697,35.42043],"type":"Point"}
}