{
  "type": "Feature",
  "properties": {
    "gn:admin1_code":"30",
    "gn:asciiname":"Zhegushan",
    "gn:country_code":"CN",
    "gn:dem":186,
    "gn:feature_class":"P",
    "gn:feature_code":"PPL",
    "gn:name":"Zhegushan",
    "gn:population":0,
    "gn:timezone":"Asia/Shanghai",
    "iso:country":"CN",
    "name:zho_x_preferred":[
        "\u9e67\u9e2a\u5c71"
    ],
    "wof:name":"Zhegushan",
    "wof:placetype":"locality"
},
  "geometry": {"coordinates":[111.80649,22.42708],"type":"Point"}
}