{
  "type": "Feature",
  "properties": {
    "gn:admin1_code":"5.0",
    "gn:asciiname":"Ailincun",
    "gn:country_code":"CN",
    "gn:dem":433,
    "gn:feature_class":"P",
    "gn:feature_code":"PPL",
    "gn:name":"Ailincun",
    "gn:population":0,
    "gn:timezone":"Asia/Shanghai",
    "iso:country":"CN",
    "name:zho_x_preferred":[
        "\u7231\u6797\u6751"
    ],
    "wof:name":"Ailincun",
    "wof:placetype":"locality"
},
  "geometry": {"coordinates":[126.64015000000001,42.68085],"type":"Point"}
}