{
  "type": "Feature",
  "properties": {
    "gn:admin1_code":"24",
    "gn:asciiname":"Dongxiaocun",
    "gn:cc2":"CN",
    "gn:country_code":"CN",
    "gn:dem":1129,
    "gn:feature_class":"P",
    "gn:feature_code":"PPL",
    "gn:name":"Dongxiaocun",
    "gn:population":0,
    "gn:timezone":"Asia/Shanghai",
    "iso:country":"CN",
    "name:und_x_variant":[
        "Tung-hsiao-ts\u2019un",
        "Dongxiaocun"
    ],
    "wof:name":"Dongxiaocun",
    "wof:placetype":"locality"
},
  "geometry": {"coordinates":[113.84222,40.07083],"type":"Point"}
}