{
  "type": "Feature",
  "properties": {
    "gn:admin1_code":"29.0",
    "gn:asciiname":"Akaluoduo",
    "gn:country_code":"CN",
    "gn:dem":1182,
    "gn:feature_class":"P",
    "gn:feature_code":"PPL",
    "gn:name":"Akaluoduo",
    "gn:population":0,
    "gn:timezone":"Asia/Shanghai",
    "iso:country":"CN",
    "name:zho_x_preferred":[
        "\u963f\u5361\u6d1b\u593a"
    ],
    "wof:name":"Akaluoduo",
    "wof:placetype":"locality"
},
  "geometry": {"coordinates":[101.896,22.605],"type":"Point"}
}