{
  "type": "Feature",
  "properties": {
    "gn:admin1_code":"24.0",
    "gn:asciiname":"Geda",
    "gn:country_code":"CN",
    "gn:dem":845,
    "gn:feature_class":"P",
    "gn:feature_code":"PPL",
    "gn:name":"Geda",
    "gn:population":0,
    "gn:timezone":"Asia/Shanghai",
    "iso:country":"CN",
    "name:und_x_variant":[
        "\u572a\u57af"
    ],
    "wof:name":"Geda",
    "wof:placetype":"locality"
},
  "geometry": {"coordinates":[111.55047,35.26198],"type":"Point"}
}