{
  "type": "Feature",
  "properties": {
    "gn:admin1_code":"12.0",
    "gn:asciiname":"Woxiping",
    "gn:country_code":"CN",
    "gn:dem":874,
    "gn:feature_class":"P",
    "gn:feature_code":"PPL",
    "gn:name":"Woxiping",
    "gn:population":0,
    "gn:timezone":"Asia/Shanghai",
    "iso:country":"CN",
    "name:zho_x_preferred":[
        "\u5367\u897f\u576a"
    ],
    "wof:name":"Woxiping",
    "wof:placetype":"locality"
},
  "geometry": {"coordinates":[109.42310999999999,29.82013],"type":"Point"}
}