{
  "type": "Feature",
  "properties": {
    "gn:admin1_code":"1.0",
    "gn:asciiname":"Cuiloucun",
    "gn:country_code":"CN",
    "gn:dem":30,
    "gn:feature_class":"P",
    "gn:feature_code":"PPL",
    "gn:name":"Cuiloucun",
    "gn:population":0,
    "gn:timezone":"Asia/Shanghai",
    "iso:country":"CN",
    "name:und_x_variant":[
        "Cuilou"
    ],
    "name:zho_x_preferred":[
        "\u5d14\u697c\u6751"
    ],
    "wof:name":"Cuiloucun",
    "wof:placetype":"locality"
},
  "geometry": {"coordinates":[117.62130999999999,33.99896],"type":"Point"}
}