{
  "type": "Feature",
  "properties": {
    "gn:admin1_code":"01",
    "gn:asciiname":"Shuizhen",
    "gn:cc2":"CN",
    "gn:country_code":"CN",
    "gn:dem":38,
    "gn:feature_class":"P",
    "gn:feature_code":"PPL",
    "gn:name":"Shuizhen",
    "gn:population":0,
    "gn:timezone":"Asia/Shanghai",
    "iso:country":"CN",
    "name:und_x_variant":[
        "Shui-tzu-chi",
        "Shui-chen",
        "Shui-tzu-p\u2019u",
        "Shuizhen"
    ],
    "wof:name":"Shuizhen",
    "wof:placetype":"locality"
},
  "geometry": {"coordinates":[115.46666999999999,33.21667],"type":"Point"}
}