{
  "type": "Feature",
  "properties": {
    "gn:admin1_code":"11.0",
    "gn:asciiname":"Jiangdongwan",
    "gn:country_code":"CN",
    "gn:dem":238,
    "gn:feature_class":"P",
    "gn:feature_code":"PPL",
    "gn:name":"Jiangdongwan",
    "gn:population":0,
    "gn:timezone":"Asia/Shanghai",
    "iso:country":"CN",
    "name:zho_x_preferred":[
        "\u6c5f\u4e1c\u6e7e"
    ],
    "wof:name":"Jiangdongwan",
    "wof:placetype":"locality"
},
  "geometry": {"coordinates":[110.62412999999999,27.77489000000001],"type":"Point"}
}