{
  "type": "Feature",
  "properties": {
    "gn:admin1_code":"14.0",
    "gn:asciiname":"Diwusibucun",
    "gn:country_code":"CN",
    "gn:dem":4828,
    "gn:feature_class":"P",
    "gn:feature_code":"PPL",
    "gn:name":"Diwusibucun",
    "gn:population":0,
    "gn:timezone":"Asia/Urumqi",
    "iso:country":"CN",
    "name:zho_x_preferred":[
        "\u5824\u543e\u65af\u535c\u6751"
    ],
    "wof:name":"Diwusibucun",
    "wof:placetype":"locality"
},
  "geometry": {"coordinates":[91.37815999999999,31.04039],"type":"Point"}
}