{
  "type": "Feature",
  "properties": {
    "gn:admin1_code":"8.0",
    "gn:asciiname":"Pingyoutun",
    "gn:country_code":"CN",
    "gn:dem":251,
    "gn:feature_class":"P",
    "gn:feature_code":"PPL",
    "gn:name":"Pingyoutun",
    "gn:population":0,
    "gn:timezone":"Asia/Shanghai",
    "iso:country":"CN",
    "name:zho_x_preferred":[
        "\u5e73\u6709\u5c6f"
    ],
    "wof:name":"Pingyoutun",
    "wof:placetype":"locality"
},
  "geometry": {"coordinates":[127.49271,45.62356],"type":"Point"}
}