{
  "type": "Feature",
  "properties": {
    "gn:admin1_code":"30.0",
    "gn:asciiname":"Huluqiu",
    "gn:country_code":"CN",
    "gn:dem":299,
    "gn:feature_class":"P",
    "gn:feature_code":"PPL",
    "gn:name":"Huluqiu",
    "gn:population":0,
    "gn:timezone":"Asia/Shanghai",
    "iso:country":"CN",
    "name:zho_x_preferred":[
        "Huluqiu"
    ],
    "name:zho_x_variant":[
        "\u846b\u82a6\u4e18"
    ],
    "wof:name":"Huluqiu",
    "wof:placetype":"locality"
},
  "geometry": {"coordinates":[113.26528,25.23472000000001],"type":"Point"}
}