{
  "type": "Feature",
  "properties": {
    "gn:admin1_code":"32.0",
    "gn:asciiname":"Wengsong",
    "gn:country_code":"CN",
    "gn:dem":856,
    "gn:feature_class":"P",
    "gn:feature_code":"PPL",
    "gn:name":"Wengsong",
    "gn:population":0,
    "gn:timezone":"Asia/Shanghai",
    "iso:country":"CN",
    "name:zho_x_preferred":[
        "\u7fc1\u677e"
    ],
    "wof:name":"Wengsong",
    "wof:placetype":"locality"
},
  "geometry": {"coordinates":[108.08199999999999,31.7016],"type":"Point"}
}