{
  "type": "Feature",
  "properties": {
    "gn:admin1_code":"15.0",
    "gn:asciiname":"Qingjiaba",
    "gn:country_code":"CN",
    "gn:dem":1121,
    "gn:feature_class":"P",
    "gn:feature_code":"PPL",
    "gn:name":"Qingjiaba",
    "gn:population":0,
    "gn:timezone":"Asia/Shanghai",
    "iso:country":"CN",
    "name:zho_x_preferred":[
        "\u9752\u5bb6\u575d"
    ],
    "wof:name":"Qingjiaba",
    "wof:placetype":"locality"
},
  "geometry": {"coordinates":[104.70659000000001,33.50356],"type":"Point"}
}