{
  "type": "Feature",
  "properties": {
    "gn:admin1_code":"24",
    "gn:asciiname":"Beigan",
    "gn:country_code":"CN",
    "gn:dem":772,
    "gn:feature_class":"P",
    "gn:feature_code":"PPL",
    "gn:name":"Beigan",
    "gn:population":0,
    "gn:timezone":"Asia/Shanghai",
    "iso:country":"CN",
    "name:und_x_variant":[
        "Pei-kan",
        "Pei-kan-ts\u2019un",
        "Beigan"
    ],
    "name:zho_x_preferred":[
        "\u5317\u6a44"
    ],
    "wof:name":"Beigan",
    "wof:placetype":"locality"
},
  "geometry": {"coordinates":[111.82472,35.75447],"type":"Point"}
}