{
  "type": "Feature",
  "properties": {
    "gn:admin1_code":"21.0",
    "gn:asciiname":"Mengjiahoushan",
    "gn:country_code":"CN",
    "gn:dem":1777,
    "gn:feature_class":"P",
    "gn:feature_code":"PPL",
    "gn:name":"Mengjiahoushan",
    "gn:population":0,
    "gn:timezone":"Asia/Shanghai",
    "iso:country":"CN",
    "name:und_x_variant":[
        "\u5b5f\u5bb6\u540e\u5c71"
    ],
    "name:zho_x_preferred":[
        "\u5b5f\u5bb6\u540e\u5c71"
    ],
    "wof:name":"Mengjiahoushan",
    "wof:placetype":"locality"
},
  "geometry": {"coordinates":[106.64671,36.2476],"type":"Point"}
}