{
  "type": "Feature",
  "properties": {
    "gn:admin1_code":"19.0",
    "gn:asciiname":"Zhujialing",
    "gn:country_code":"CN",
    "gn:dem":57,
    "gn:feature_class":"P",
    "gn:feature_code":"PPL",
    "gn:name":"Zhujialing",
    "gn:population":0,
    "gn:timezone":"Asia/Shanghai",
    "iso:country":"CN",
    "name:und_x_variant":[
        "\u6731\u5bb6\u5cad"
    ],
    "name:zho_x_preferred":[
        "\u6731\u5bb6\u5cad"
    ],
    "wof:name":"Zhujialing",
    "wof:placetype":"locality"
},
  "geometry": {"coordinates":[123.4218,40.1632],"type":"Point"}
}