{
  "type": "Feature",
  "properties": {
    "gn:admin1_code":"29.0",
    "gn:asciiname":"Banpozhai",
    "gn:country_code":"CN",
    "gn:dem":1012,
    "gn:feature_class":"P",
    "gn:feature_code":"PPL",
    "gn:name":"Banpozhai",
    "gn:population":0,
    "gn:timezone":"Asia/Shanghai",
    "iso:country":"CN",
    "name:zho_x_preferred":[
        "\u534a\u5761\u5be8"
    ],
    "wof:name":"Banpozhai",
    "wof:placetype":"locality"
},
  "geometry": {"coordinates":[101.46299999999999,21.3146],"type":"Point"}
}