{
  "type": "Feature",
  "properties": {
    "gn:admin1_code":"29.0",
    "gn:asciiname":"Lamaluo",
    "gn:country_code":"CN",
    "gn:dem":1993,
    "gn:feature_class":"P",
    "gn:feature_code":"PPL",
    "gn:name":"Lamaluo",
    "gn:population":0,
    "gn:timezone":"Asia/Shanghai",
    "iso:country":"CN",
    "name:zho_x_preferred":[
        "\u814a\u9a6c\u6d1b"
    ],
    "wof:name":"Lamaluo",
    "wof:placetype":"locality"
},
  "geometry": {"coordinates":[98.88679999999999,27.0348],"type":"Point"}
}