{
  "type": "Feature",
  "properties": {
    "gn:admin1_code":"8.0",
    "gn:asciiname":"Guanjia Wobu",
    "gn:country_code":"CN",
    "gn:dem":161,
    "gn:feature_class":"P",
    "gn:feature_code":"PPL",
    "gn:name":"Guanjia Wobu",
    "gn:population":0,
    "gn:timezone":"Asia/Shanghai",
    "iso:country":"CN",
    "name:zho_x_preferred":[
        "\u5173\u5bb6\u7a9d\u5821"
    ],
    "wof:name":"Guanjia Wobu",
    "wof:placetype":"locality"
},
  "geometry": {"coordinates":[126.25988,45.34197],"type":"Point"}
}