{
  "type": "Feature",
  "properties": {
    "gn:admin1_code":"19.0",
    "gn:asciiname":"Shanghuo Jiadi",
    "gn:country_code":"CN",
    "gn:dem":684,
    "gn:feature_class":"P",
    "gn:feature_code":"PPL",
    "gn:name":"Shanghuo Jiadi",
    "gn:population":0,
    "gn:timezone":"Asia/Shanghai",
    "iso:country":"CN",
    "name:zho_x_preferred":[
        "\u4e0a\u970d\u5bb6\u5730"
    ],
    "wof:name":"Shanghuo Jiadi",
    "wof:placetype":"locality"
},
  "geometry": {"coordinates":[119.54145,42.17083],"type":"Point"}
}