{
  "type": "Feature",
  "properties": {
    "gn:admin1_code":"26.0",
    "gn:asciiname":"Ercenghetai",
    "gn:country_code":"CN",
    "gn:dem":1299,
    "gn:feature_class":"P",
    "gn:feature_code":"PPL",
    "gn:name":"Ercenghetai",
    "gn:population":0,
    "gn:timezone":"Asia/Shanghai",
    "iso:country":"CN",
    "name:zho_x_preferred":[
        "\u4e8c\u5c42\u6cb3\u53f0"
    ],
    "wof:name":"Ercenghetai",
    "wof:placetype":"locality"
},
  "geometry": {"coordinates":[108.48411000000002,37.67113],"type":"Point"}
}