{
  "type": "Feature",
  "properties": {
    "gn:admin1_code":"08",
    "gn:asciiname":"Xiluoqi",
    "gn:country_code":"CN",
    "gn:dem":725,
    "gn:feature_class":"P",
    "gn:feature_code":"PPL",
    "gn:name":"Xiluoqi",
    "gn:population":0,
    "gn:timezone":"Asia/Shanghai",
    "iso:country":"CN",
    "wof:name":"Xiluoqi",
    "wof:placetype":"locality"
},
  "geometry": {"coordinates":[124.40000000000001,52.58333],"type":"Point"}
}