{
  "type": "Feature",
  "properties": {
    "gn:admin1_code":"32.0",
    "gn:asciiname":"Qixinzhai",
    "gn:country_code":"CN",
    "gn:dem":389,
    "gn:feature_class":"P",
    "gn:feature_code":"PPL",
    "gn:name":"Qixinzhai",
    "gn:population":0,
    "gn:timezone":"Asia/Shanghai",
    "iso:country":"CN",
    "name:zho_x_preferred":[
        "\u4e03\u5fc3\u5be8"
    ],
    "name:zho_x_variant":[
        "\u9f50\u5fc3\u5be8"
    ],
    "wof:name":"Qixinzhai",
    "wof:placetype":"locality"
},
  "geometry": {"coordinates":[107.32899999999999,30.5899],"type":"Point"}
}