{
  "type": "Feature",
  "properties": {
    "gn:admin1_code":"32.0",
    "gn:asciiname":"Wadu Xicun",
    "gn:country_code":"CN",
    "gn:dem":2062,
    "gn:feature_class":"P",
    "gn:feature_code":"PPL",
    "gn:name":"Wadu Xicun",
    "gn:population":0,
    "gn:timezone":"Asia/Shanghai",
    "iso:country":"CN",
    "name:zho_x_preferred":[
        "\u74e6\u90fd\u897f\u6751"
    ],
    "wof:name":"Wadu Xicun",
    "wof:placetype":"locality"
},
  "geometry": {"coordinates":[102.10599999999999,27.8113],"type":"Point"}
}