{
  "type": "Feature",
  "properties": {
    "gn:admin1_code":"12.0",
    "gn:asciiname":"Liujia Laowu",
    "gn:country_code":"CN",
    "gn:dem":832,
    "gn:feature_class":"P",
    "gn:feature_code":"PPL",
    "gn:name":"Liujia Laowu",
    "gn:population":0,
    "gn:timezone":"Asia/Shanghai",
    "iso:country":"CN",
    "name:zho_x_preferred":[
        "Liujia Laowu"
    ],
    "name:zho_x_variant":[
        "\u5218\u5bb6\u8001\u5c4b"
    ],
    "wof:name":"Liujia Laowu",
    "wof:placetype":"locality"
},
  "geometry": {"coordinates":[111.14811,30.05391],"type":"Point"}
}