{
  "type": "Feature",
  "properties": {
    "gn:admin1_code":"11",
    "gn:asciiname":"Zhongjiayuan",
    "gn:country_code":"CN",
    "gn:dem":101,
    "gn:feature_class":"P",
    "gn:feature_code":"PPL",
    "gn:name":"Zhongjiayuan",
    "gn:population":0,
    "gn:timezone":"Asia/Shanghai",
    "iso:country":"CN",
    "name:zho_x_preferred":[
        "\u949f\u5bb6\u9662"
    ],
    "wof:name":"Zhongjiayuan",
    "wof:placetype":"locality"
},
  "geometry": {"coordinates":[111.73914000000001,26.57841],"type":"Point"}
}