{
  "type": "Feature",
  "properties": {
    "gn:admin1_code":"18",
    "gn:asciiname":"Luojiazhai",
    "gn:country_code":"CN",
    "gn:dem":771,
    "gn:feature_class":"P",
    "gn:feature_code":"PPL",
    "gn:name":"Luojiazhai",
    "gn:population":0,
    "gn:timezone":"Asia/Shanghai",
    "iso:country":"CN",
    "name:zho_x_preferred":[
        "\u7f57\u5bb6\u5be8"
    ],
    "wof:name":"Luojiazhai",
    "wof:placetype":"locality"
},
  "geometry": {"coordinates":[107.51000000000001,27.4067],"type":"Point"}
}