{
  "type": "Feature",
  "properties": {
    "gn:admin1_code":"16.0",
    "gn:asciiname":"Shangdi",
    "gn:country_code":"CN",
    "gn:dem":563,
    "gn:feature_class":"P",
    "gn:feature_code":"PPL",
    "gn:name":"Shangdi",
    "gn:population":0,
    "gn:timezone":"Asia/Shanghai",
    "iso:country":"CN",
    "name:zho_x_preferred":[
        "\u4e0a\u7b2c"
    ],
    "wof:name":"Shangdi",
    "wof:placetype":"locality"
},
  "geometry": {"coordinates":[108.193,24.1891],"type":"Point"}
}