{
  "type": "Feature",
  "properties": {
    "gn:admin1_code":"33.0",
    "gn:asciiname":"Deshengqiao",
    "gn:country_code":"CN",
    "gn:dem":277,
    "gn:feature_class":"P",
    "gn:feature_code":"PPL",
    "gn:name":"Deshengqiao",
    "gn:population":0,
    "gn:timezone":"Asia/Shanghai",
    "iso:country":"CN",
    "name:zho_x_preferred":[
        "\u5fb7\u80dc\u6865"
    ],
    "wof:name":"Deshengqiao",
    "wof:placetype":"locality"
},
  "geometry": {"coordinates":[106.04883999999998,29.41553],"type":"Point"}
}