{
  "type": "Feature",
  "properties": {
    "gn:admin1_code":"12.0",
    "gn:asciiname":"Xiangluyan",
    "gn:country_code":"CN",
    "gn:dem":679,
    "gn:feature_class":"P",
    "gn:feature_code":"PPL",
    "gn:name":"Xiangluyan",
    "gn:population":0,
    "gn:timezone":"Asia/Shanghai",
    "iso:country":"CN",
    "name:zho_x_preferred":[
        "Xiangluyan"
    ],
    "name:zho_x_variant":[
        "\u9999\u7089\u5ca9"
    ],
    "wof:name":"Xiangluyan",
    "wof:placetype":"locality"
},
  "geometry": {"coordinates":[111.30015,30.09973],"type":"Point"}
}