{
  "type": "Feature",
  "properties": {
    "gn:admin1_code":"25.0",
    "gn:asciiname":"Aluocun",
    "gn:country_code":"CN",
    "gn:dem":70,
    "gn:feature_class":"P",
    "gn:feature_code":"PPL",
    "gn:name":"Aluocun",
    "gn:population":0,
    "gn:timezone":"Asia/Shanghai",
    "iso:country":"CN",
    "name:zho_x_preferred":[
        "\u963f\u6d1b\u6751"
    ],
    "wof:name":"Aluocun",
    "wof:placetype":"locality"
},
  "geometry": {"coordinates":[119.30759999999999,36.35735],"type":"Point"}
}