{
  "type": "Feature",
  "properties": {
    "gn:admin1_code":"25",
    "gn:asciiname":"Wanglaoshi",
    "gn:country_code":"CN",
    "gn:dem":24,
    "gn:feature_class":"P",
    "gn:feature_code":"PPL",
    "gn:name":"Wanglaoshi",
    "gn:population":0,
    "gn:timezone":"Asia/Shanghai",
    "iso:country":"CN",
    "name:zho_x_preferred":[
        "\u738b\u8001\u5b9e"
    ],
    "wof:name":"Wanglaoshi",
    "wof:placetype":"locality"
},
  "geometry": {"coordinates":[116.786,36.8202],"type":"Point"}
}