{
  "type": "Feature",
  "properties": {
    "gn:admin1_code":"32.0",
    "gn:asciiname":"Pading",
    "gn:country_code":"CN",
    "gn:dem":2983,
    "gn:feature_class":"P",
    "gn:feature_code":"PPL",
    "gn:name":"Pading",
    "gn:population":0,
    "gn:timezone":"Asia/Shanghai",
    "iso:country":"CN",
    "name:zho_x_preferred":[
        "\u5e15\u4e01"
    ],
    "wof:name":"Pading",
    "wof:placetype":"locality"
},
  "geometry": {"coordinates":[100.23999999999999,28.4181],"type":"Point"}
}