{
  "type": "Feature",
  "properties": {
    "gn:admin1_code":"29.0",
    "gn:asciiname":"Zhaka",
    "gn:country_code":"CN",
    "gn:dem":2003,
    "gn:feature_class":"P",
    "gn:feature_code":"PPL",
    "gn:name":"Zhaka",
    "gn:population":0,
    "gn:timezone":"Asia/Shanghai",
    "iso:country":"CN",
    "name:zho_x_preferred":[
        "\u624e\u5361"
    ],
    "wof:name":"Zhaka",
    "wof:placetype":"locality"
},
  "geometry": {"coordinates":[101.283,24.1059],"type":"Point"}
}