{
  "type": "Feature",
  "properties": {
    "gn:admin1_code":"24",
    "gn:asciiname":"Dongnanbucun",
    "gn:country_code":"CN",
    "gn:dem":1088,
    "gn:feature_class":"P",
    "gn:feature_code":"PPL",
    "gn:name":"Dongnanbucun",
    "gn:population":0,
    "gn:timezone":"Asia/Shanghai",
    "iso:country":"CN",
    "name:und_x_variant":[
        "Tung-nan-pao",
        "Tung-nan-p\u2019u",
        "Dongnanbu",
        "Dongnanbucun"
    ],
    "name:zho_x_preferred":[
        "\u4e1c\u5357\u5821\u6751"
    ],
    "wof:name":"Dongnanbucun",
    "wof:placetype":"locality"
},
  "geometry": {"coordinates":[110.86109,36.37057],"type":"Point"}
}