{
  "type": "Feature",
  "properties": {
    "gn:admin1_code":"10",
    "gn:asciiname":"Jin'an",
    "gn:country_code":"CN",
    "gn:dem":47,
    "gn:feature_class":"P",
    "gn:feature_code":"PPL",
    "gn:name":"Jin\u2019an",
    "gn:population":0,
    "gn:timezone":"Asia/Shanghai",
    "iso:country":"CN",
    "name:und_x_variant":[
        "Jin\u2019an"
    ],
    "name:zho_x_preferred":[
        "\u91d1\u5b89"
    ],
    "wof:name":"Jin'an",
    "wof:placetype":"locality"
},
  "geometry": {"coordinates":[115.03212000000001,36.47667],"type":"Point"}
}