{
  "type": "Feature",
  "properties": {
    "gn:admin1_code":"21.0",
    "gn:asciiname":"Majiagou",
    "gn:country_code":"CN",
    "gn:dem":1934,
    "gn:feature_class":"P",
    "gn:feature_code":"PPL",
    "gn:name":"Majiagou",
    "gn:population":0,
    "gn:timezone":"Asia/Shanghai",
    "iso:country":"CN",
    "name:zho_x_preferred":[
        "\u9a6c\u5bb6\u6c9f"
    ],
    "wof:name":"Majiagou",
    "wof:placetype":"locality"
},
  "geometry": {"coordinates":[105.97028,35.72547],"type":"Point"}
}