{
  "type": "Feature",
  "properties": {
    "gn:admin1_code":"9",
    "gn:asciiname":"Baijiansi",
    "gn:country_code":"CN",
    "gn:dem":488,
    "gn:feature_class":"P",
    "gn:feature_code":"PPL",
    "gn:name":"Baijiansi",
    "gn:population":0,
    "gn:timezone":"Asia/Shanghai",
    "iso:country":"CN",
    "name:zho_x_preferred":[
        "\u767d\u6da7\u5bfa"
    ],
    "wof:name":"Baijiansi",
    "wof:placetype":"locality"
},
  "geometry": {"coordinates":[112.71509,35.20321],"type":"Point"}
}