{
  "type": "Feature",
  "properties": {
    "gn:admin1_code":"15.0",
    "gn:asciiname":"Chenguang",
    "gn:country_code":"CN",
    "gn:dem":1237,
    "gn:feature_class":"P",
    "gn:feature_code":"PPL",
    "gn:name":"Chenguang",
    "gn:population":0,
    "gn:timezone":"Asia/Shanghai",
    "iso:country":"CN",
    "name:zho_x_preferred":[
        "\u6668\u5149"
    ],
    "wof:name":"Chenguang",
    "wof:placetype":"locality"
},
  "geometry": {"coordinates":[98.7403,40.1895],"type":"Point"}
}