{
  "type": "Feature",
  "properties": {
    "gn:admin1_code":"11.0",
    "gn:asciiname":"Jingbianhu",
    "gn:country_code":"CN",
    "gn:dem":81,
    "gn:feature_class":"P",
    "gn:feature_code":"PPL",
    "gn:name":"Jingbianhu",
    "gn:population":0,
    "gn:timezone":"Asia/Shanghai",
    "iso:country":"CN",
    "name:zho_x_preferred":[
        "\u4e95\u8fb9\u6e56"
    ],
    "wof:name":"Jingbianhu",
    "wof:placetype":"locality"
},
  "geometry": {"coordinates":[113.14305,27.43326],"type":"Point"}
}