{
  "type": "Feature",
  "properties": {
    "gn:admin1_code":"19.0",
    "gn:asciiname":"Yayaogou",
    "gn:country_code":"CN",
    "gn:dem":54,
    "gn:feature_class":"P",
    "gn:feature_code":"PPL",
    "gn:name":"Yayaogou",
    "gn:population":0,
    "gn:timezone":"Asia/Shanghai",
    "iso:country":"CN",
    "name:zho_x_preferred":[
        "\u5d16\u7a91\u6c9f"
    ],
    "wof:name":"Yayaogou",
    "wof:placetype":"locality"
},
  "geometry": {"coordinates":[121.414,38.8544],"type":"Point"}
}