{
  "type": "Feature",
  "properties": {
    "gn:admin1_code":"3.0",
    "gn:asciiname":"Xiangxia",
    "gn:country_code":"CN",
    "gn:dem":60,
    "gn:feature_class":"P",
    "gn:feature_code":"PPL",
    "gn:name":"Xiangxia",
    "gn:population":0,
    "gn:timezone":"Asia/Shanghai",
    "iso:country":"CN",
    "name:und_x_variant":[
        "\u4eab\u4e0b"
    ],
    "wof:name":"Xiangxia",
    "wof:placetype":"locality"
},
  "geometry": {"coordinates":[114.87033999999998,27.91955],"type":"Point"}
}