{
  "type": "Feature",
  "properties": {
    "gn:admin1_code":"16.0",
    "gn:asciiname":"Mijiling",
    "gn:country_code":"CN",
    "gn:dem":90,
    "gn:feature_class":"P",
    "gn:feature_code":"PPL",
    "gn:name":"Mijiling",
    "gn:population":0,
    "gn:timezone":"Asia/Shanghai",
    "iso:country":"CN",
    "name:zho_x_preferred":[
        "\u7c73\u9e21\u5cad"
    ],
    "wof:name":"Mijiling",
    "wof:placetype":"locality"
},
  "geometry": {"coordinates":[109.251,23.8305],"type":"Point"}
}