{
  "type": "Feature",
  "properties": {
    "gn:admin1_code":"11",
    "gn:asciiname":"Yuhetian",
    "gn:country_code":"CN",
    "gn:dem":127,
    "gn:feature_class":"P",
    "gn:feature_code":"PPL",
    "gn:name":"Yuhetian",
    "gn:population":0,
    "gn:timezone":"Asia/Shanghai",
    "iso:country":"CN",
    "name:zho_x_preferred":[
        "\u7389\u79be\u7530"
    ],
    "wof:name":"Yuhetian",
    "wof:placetype":"locality"
},
  "geometry": {"coordinates":[111.52228999999998,26.22372],"type":"Point"}
}