{
  "type": "Feature",
  "properties": {
    "gn:admin1_code":"32.0",
    "gn:asciiname":"Yanjiamiao",
    "gn:country_code":"CN",
    "gn:dem":375,
    "gn:feature_class":"P",
    "gn:feature_code":"PPL",
    "gn:name":"Yanjiamiao",
    "gn:population":0,
    "gn:timezone":"Asia/Shanghai",
    "iso:country":"CN",
    "name:zho_x_preferred":[
        "\u989c\u5bb6\u5e99"
    ],
    "wof:name":"Yanjiamiao",
    "wof:placetype":"locality"
},
  "geometry": {"coordinates":[104.84567,28.57643],"type":"Point"}
}