{
  "type": "Feature",
  "properties": {
    "gn:admin1_code":"18",
    "gn:asciiname":"Hejia Yuanzi",
    "gn:country_code":"CN",
    "gn:dem":1735,
    "gn:feature_class":"P",
    "gn:feature_code":"PPL",
    "gn:name":"Hejia Yuanzi",
    "gn:population":0,
    "gn:timezone":"Asia/Shanghai",
    "iso:country":"CN",
    "name:zho_x_preferred":[
        "\u4f55\u5bb6\u9662\u5b50"
    ],
    "wof:name":"Hejia Yuanzi",
    "wof:placetype":"locality"
},
  "geometry": {"coordinates":[105.04600000000001,27.0995],"type":"Point"}
}