{
  "type": "Feature",
  "properties": {
    "gn:admin1_code":"10.0",
    "gn:asciiname":"Huanglingwa",
    "gn:country_code":"CN",
    "gn:dem":231,
    "gn:feature_class":"P",
    "gn:feature_code":"PPL",
    "gn:name":"Huanglingwa",
    "gn:population":0,
    "gn:timezone":"Asia/Shanghai",
    "iso:country":"CN",
    "name:und_x_variant":[
        "\u9ec4\u5cad\u6d3c"
    ],
    "wof:name":"Huanglingwa",
    "wof:placetype":"locality"
},
  "geometry": {"coordinates":[114.56621,38.84485],"type":"Point"}
}