{
  "type": "Feature",
  "properties": {
    "gn:admin1_code":"1.0",
    "gn:asciiname":"Dushantou",
    "gn:country_code":"CN",
    "gn:dem":309,
    "gn:feature_class":"P",
    "gn:feature_code":"PPL",
    "gn:name":"Dushantou",
    "gn:population":0,
    "gn:timezone":"Asia/Shanghai",
    "iso:country":"CN",
    "name:und_x_variant":[
        "\u72ec\u5c71\u5934"
    ],
    "name:zho_x_preferred":[
        "Dushantou"
    ],
    "wof:name":"Dushantou",
    "wof:placetype":"locality"
},
  "geometry": {"coordinates":[119.27451000000001,30.38252],"type":"Point"}
}