{
  "type": "Feature",
  "properties": {
    "gn:admin1_code":"24.0",
    "gn:asciiname":"Wuhuaying",
    "gn:country_code":"CN",
    "gn:dem":1046,
    "gn:feature_class":"P",
    "gn:feature_code":"PPL",
    "gn:name":"Wuhuaying",
    "gn:population":0,
    "gn:timezone":"Asia/Shanghai",
    "iso:country":"CN",
    "name:und_x_variant":[
        "\u4e94\u82b1\u8425"
    ],
    "name:zho_x_preferred":[
        "\u4e94\u82b1\u8425"
    ],
    "wof:name":"Wuhuaying",
    "wof:placetype":"locality"
},
  "geometry": {"coordinates":[112.75041,39.28283],"type":"Point"}
}