{
  "type": "Feature",
  "properties": {
    "gn:admin1_code":"7.0",
    "gn:asciiname":"Yunhoucun",
    "gn:country_code":"CN",
    "gn:dem":115,
    "gn:feature_class":"P",
    "gn:feature_code":"PPL",
    "gn:name":"Yunhoucun",
    "gn:population":0,
    "gn:timezone":"Asia/Shanghai",
    "iso:country":"CN",
    "name:zho_x_preferred":[
        "\u4e91\u540e\u6751"
    ],
    "wof:name":"Yunhoucun",
    "wof:placetype":"locality"
},
  "geometry": {"coordinates":[117.36948999999998,24.26013],"type":"Point"}
}