{
  "type": "Feature",
  "properties": {
    "gn:admin1_code":"10",
    "gn:asciiname":"Xinzhuangzi",
    "gn:cc2":"CN",
    "gn:country_code":"CN",
    "gn:dem":571,
    "gn:feature_class":"P",
    "gn:feature_code":"PPL",
    "gn:name":"Xinzhuangzi",
    "gn:population":0,
    "gn:timezone":"Asia/Shanghai",
    "iso:country":"CN",
    "name:und_x_variant":[
        "Hsin-chuang-tzu",
        "Xinzhuangzi"
    ],
    "wof:name":"Xinzhuangzi",
    "wof:placetype":"locality"
},
  "geometry": {"coordinates":[115.16583,40.51472],"type":"Point"}
}