{
  "type": "Feature",
  "properties": {
    "gn:admin1_code":"8.0",
    "gn:asciiname":"Xiaomandian",
    "gn:country_code":"CN",
    "gn:dem":237,
    "gn:feature_class":"P",
    "gn:feature_code":"PPL",
    "gn:name":"Xiaomandian",
    "gn:population":0,
    "gn:timezone":"Asia/Shanghai",
    "iso:country":"CN",
    "name:zho_x_preferred":[
        "\u5c0f\u6ee1\u5e97"
    ],
    "wof:name":"Xiaomandian",
    "wof:placetype":"locality"
},
  "geometry": {"coordinates":[127.28727000000001,45.67113],"type":"Point"}
}