{
  "type": "Feature",
  "properties": {
    "gn:admin1_code":"32.0",
    "gn:asciiname":"Changwushan",
    "gn:country_code":"CN",
    "gn:dem":519,
    "gn:feature_class":"P",
    "gn:feature_code":"PPL",
    "gn:name":"Changwushan",
    "gn:population":0,
    "gn:timezone":"Asia/Shanghai",
    "iso:country":"CN",
    "name:zho_x_preferred":[
        "\u957f\u5c4b\u5c71"
    ],
    "wof:name":"Changwushan",
    "wof:placetype":"locality"
},
  "geometry": {"coordinates":[104.624,28.499],"type":"Point"}
}