{
  "type": "Feature",
  "properties": {
    "gn:admin1_code":"25",
    "gn:asciiname":"Qiaojiahu",
    "gn:country_code":"CN",
    "gn:dem":73,
    "gn:feature_class":"P",
    "gn:feature_code":"PPL",
    "gn:name":"Qiaojiahu",
    "gn:population":0,
    "gn:timezone":"Asia/Shanghai",
    "iso:country":"CN",
    "name:zho_x_preferred":[
        "\u4e54\u5bb6\u6e56"
    ],
    "wof:name":"Qiaojiahu",
    "wof:placetype":"locality"
},
  "geometry": {"coordinates":[118.372,35.1888],"type":"Point"}
}