{
  "type": "Feature",
  "properties": {
    "gn:admin1_code":"11.0",
    "gn:asciiname":"Tianxingya",
    "gn:country_code":"CN",
    "gn:dem":92,
    "gn:feature_class":"P",
    "gn:feature_code":"PPL",
    "gn:name":"Tianxingya",
    "gn:population":0,
    "gn:timezone":"Asia/Shanghai",
    "iso:country":"CN",
    "name:zho_x_preferred":[
        "Tianxingya"
    ],
    "name:zho_x_variant":[
        "\u5929\u661f\u57ad"
    ],
    "wof:name":"Tianxingya",
    "wof:placetype":"locality"
},
  "geometry": {"coordinates":[111.31944,29.19923],"type":"Point"}
}