{
  "type": "Feature",
  "properties": {
    "gn:admin1_code":"15.0",
    "gn:asciiname":"Huaxian",
    "gn:country_code":"CN",
    "gn:dem":1718,
    "gn:feature_class":"P",
    "gn:feature_code":"PPL",
    "gn:name":"Huaxian",
    "gn:population":0,
    "gn:timezone":"Asia/Shanghai",
    "iso:country":"CN",
    "name:zho_x_preferred":[
        "\u82b1\u5c98"
    ],
    "wof:name":"Huaxian",
    "wof:placetype":"locality"
},
  "geometry": {"coordinates":[104.718,37.1346],"type":"Point"}
}