{
  "type": "Feature",
  "properties": {
    "gn:admin1_code":"9.0",
    "gn:asciiname":"Youfangzhuang",
    "gn:country_code":"CN",
    "gn:dem":136,
    "gn:feature_class":"P",
    "gn:feature_code":"PPL",
    "gn:name":"Youfangzhuang",
    "gn:population":0,
    "gn:timezone":"Asia/Shanghai",
    "iso:country":"CN",
    "name:zho_x_preferred":[
        "\u6cb9\u574a\u5e84"
    ],
    "wof:name":"Youfangzhuang",
    "wof:placetype":"locality"
},
  "geometry": {"coordinates":[113.17712,32.84243],"type":"Point"}
}