{
  "type": "Feature",
  "properties": {
    "gn:admin1_code":"29.0",
    "gn:asciiname":"Wenyou'ao",
    "gn:country_code":"CN",
    "gn:dem":2653,
    "gn:feature_class":"P",
    "gn:feature_code":"PPL",
    "gn:name":"Wenyou\u2019ao",
    "gn:population":0,
    "gn:timezone":"Asia/Shanghai",
    "iso:country":"CN",
    "name:und_x_variant":[
        "Wenyou\u2019ao"
    ],
    "name:zho_x_preferred":[
        "\u868a\u7531\u51f9"
    ],
    "wof:name":"Wenyou'ao",
    "wof:placetype":"locality"
},
  "geometry": {"coordinates":[100.52200000000001,26.992],"type":"Point"}
}