{
  "type": "Feature",
  "properties": {
    "gn:admin1_code":"4.0",
    "gn:asciiname":"Xiqiao",
    "gn:country_code":"CN",
    "gn:dem":6,
    "gn:feature_class":"P",
    "gn:feature_code":"PPLA4",
    "gn:name":"Xiqiao",
    "gn:population":0,
    "gn:timezone":"Asia/Shanghai",
    "iso:country":"CN",
    "name:ceb_x_preferred":[
        "Xiqiao"
    ],
    "name:swe_x_preferred":[
        "Xiqiao"
    ],
    "name:und_x_variant":[
        "\u6eaa\u6865",
        "Xiqiao Zhen",
        "\u6eaa\u6865\u9547"
    ],
    "wof:name":"Xiqiao",
    "wof:placetype":"locality"
},
  "geometry": {"coordinates":[120.18218,32.22576],"type":"Point"}
}