{
  "type": "Feature",
  "properties": {
    "gn:admin1_code":"30.0",
    "gn:asciiname":"Jianpucun",
    "gn:country_code":"CN",
    "gn:dem":7,
    "gn:feature_class":"P",
    "gn:feature_code":"PPL",
    "gn:name":"Jianpucun",
    "gn:population":0,
    "gn:timezone":"Asia/Shanghai",
    "iso:country":"CN",
    "name:und_x_variant":[
        "Jiancun",
        "Jianpo"
    ],
    "name:zho_x_preferred":[
        "\u7b80\u6734\u6751"
    ],
    "wof:name":"Jianpucun",
    "wof:placetype":"locality"
},
  "geometry": {"coordinates":[116.47384,23.17238],"type":"Point"}
}