{
  "type": "Feature",
  "properties": {
    "gn:admin1_code":"10",
    "gn:asciiname":"Lianghe",
    "gn:country_code":"CN",
    "gn:dem":132,
    "gn:feature_class":"P",
    "gn:feature_code":"PPLA4",
    "gn:name":"Lianghe",
    "gn:population":0,
    "gn:timezone":"Asia/Shanghai",
    "iso:country":"CN",
    "name:und_x_variant":[
        "Liang-ho",
        "Lianghe",
        "\u4e24\u6cb3",
        "Lianghe Xiang",
        "\u4e24\u6cb3\u4e61"
    ],
    "wof:name":"Lianghe",
    "wof:placetype":"locality"
},
  "geometry": {"coordinates":[114.15801,38.33461],"type":"Point"}
}