{
  "type": "Feature",
  "properties": {
    "gn:admin1_code":"1.0",
    "gn:asciiname":"Luoducun",
    "gn:country_code":"CN",
    "gn:dem":7,
    "gn:feature_class":"P",
    "gn:feature_code":"PPL",
    "gn:name":"Luoducun",
    "gn:population":0,
    "gn:timezone":"Asia/Shanghai",
    "iso:country":"CN",
    "name:zho_x_preferred":[
        "\u7f57\u6e21\u6751"
    ],
    "wof:name":"Luoducun",
    "wof:placetype":"locality"
},
  "geometry": {"coordinates":[118.44513000000001,31.34271],"type":"Point"}
}