{
  "type": "Feature",
  "properties": {
    "gn:admin1_code":"08",
    "gn:asciiname":"Yongsheng",
    "gn:country_code":"CN",
    "gn:dem":52,
    "gn:feature_class":"P",
    "gn:feature_code":"PPL",
    "gn:name":"Yongsheng",
    "gn:population":0,
    "gn:timezone":"Asia/Shanghai",
    "iso:country":"CN",
    "wof:name":"Yongsheng",
    "wof:placetype":"locality"
},
  "geometry": {"coordinates":[134.53638999999998,48.18472],"type":"Point"}
}