{
  "type": "Feature",
  "properties": {
    "gn:admin1_code":"3.0",
    "gn:asciiname":"Paixia",
    "gn:country_code":"CN",
    "gn:dem":101,
    "gn:feature_class":"P",
    "gn:feature_code":"PPL",
    "gn:name":"Paixia",
    "gn:population":0,
    "gn:timezone":"Asia/Shanghai",
    "iso:country":"CN",
    "name:und_x_variant":[
        "\u6392\u4e0b"
    ],
    "wof:name":"Paixia",
    "wof:placetype":"locality"
},
  "geometry": {"coordinates":[115.70793999999999,27.52288],"type":"Point"}
}