{
  "type": "Feature",
  "properties": {
    "gn:admin1_code":"9.0",
    "gn:asciiname":"Qianpo",
    "gn:country_code":"CN",
    "gn:dem":678,
    "gn:feature_class":"P",
    "gn:feature_code":"PPL",
    "gn:name":"Qianpo",
    "gn:population":0,
    "gn:timezone":"Asia/Shanghai",
    "iso:country":"CN",
    "name:und_x_variant":[
        "\u524d\u5761",
        "Qianpo"
    ],
    "wof:name":"Qianpo",
    "wof:placetype":"locality"
},
  "geometry": {"coordinates":[112.44926,33.58169],"type":"Point"}
}