{
  "type": "Feature",
  "properties": {
    "gn:admin1_code":"20.0",
    "gn:asciiname":"Sarula Tubu",
    "gn:country_code":"CN",
    "gn:dem":761,
    "gn:feature_class":"P",
    "gn:feature_code":"PPL",
    "gn:name":"Sarula Tubu",
    "gn:population":0,
    "gn:timezone":"Asia/Shanghai",
    "iso:country":"CN",
    "name:zho_x_preferred":[
        "\u8428\u5982\u62c9\u56fe\u5e03"
    ],
    "wof:name":"Sarula Tubu",
    "wof:placetype":"locality"
},
  "geometry": {"coordinates":[119.20917,47.93408],"type":"Point"}
}