{
  "type": "Feature",
  "properties": {
    "gn:admin1_code":"11",
    "gn:asciiname":"Yangjiaping",
    "gn:country_code":"CN",
    "gn:dem":1114,
    "gn:feature_class":"P",
    "gn:feature_code":"PPL",
    "gn:name":"Yangjiaping",
    "gn:population":0,
    "gn:timezone":"Asia/Shanghai",
    "iso:country":"CN",
    "name:und_x_variant":[
        "\u6768\u5bb6\u576a",
        "Yangjiaping"
    ],
    "wof:name":"Yangjiaping",
    "wof:placetype":"locality"
},
  "geometry": {"coordinates":[111.95083,25.12472],"type":"Point"}
}