{
  "type": "Feature",
  "properties": {
    "gn:admin1_code":"19.0",
    "gn:asciiname":"Toudaogoucun",
    "gn:country_code":"CN",
    "gn:dem":402,
    "gn:feature_class":"P",
    "gn:feature_code":"PPL",
    "gn:name":"Toudaogoucun",
    "gn:population":0,
    "gn:timezone":"Asia/Shanghai",
    "iso:country":"CN",
    "name:zho_x_preferred":[
        "\u5934\u9053\u6c9f\u6751"
    ],
    "wof:name":"Toudaogoucun",
    "wof:placetype":"locality"
},
  "geometry": {"coordinates":[124.86172000000001,40.86734000000001],"type":"Point"}
}