{
  "type": "Feature",
  "properties": {
    "gn:admin1_code":"25",
    "gn:asciiname":"Nuanshuihe",
    "gn:country_code":"CN",
    "gn:dem":296,
    "gn:feature_class":"P",
    "gn:feature_code":"PPL",
    "gn:name":"Nuanshuihe",
    "gn:population":0,
    "gn:timezone":"Asia/Shanghai",
    "iso:country":"CN",
    "name:zho_x_preferred":[
        "\u6696\u6c34\u6cb3"
    ],
    "wof:name":"Nuanshuihe",
    "wof:placetype":"locality"
},
  "geometry": {"coordinates":[118.298,36.3804],"type":"Point"}
}