{
  "type": "Feature",
  "properties": {
    "gn:admin1_code":"3.0",
    "gn:asciiname":"Danqiao",
    "gn:country_code":"CN",
    "gn:dem":83,
    "gn:feature_class":"P",
    "gn:feature_code":"PPL",
    "gn:name":"Danqiao",
    "gn:population":0,
    "gn:timezone":"Asia/Shanghai",
    "iso:country":"CN",
    "name:und_x_variant":[
        "\u4f46\u6865"
    ],
    "wof:name":"Danqiao",
    "wof:placetype":"locality"
},
  "geometry": {"coordinates":[115.39012,29.45946],"type":"Point"}
}