{
  "type": "Feature",
  "properties": {
    "gn:admin1_code":"30.0",
    "gn:asciiname":"Chuantan",
    "gn:country_code":"CN",
    "gn:dem":111,
    "gn:feature_class":"P",
    "gn:feature_code":"PPL",
    "gn:name":"Chuantan",
    "gn:population":0,
    "gn:timezone":"Asia/Shanghai",
    "iso:country":"CN",
    "name:zho_x_preferred":[
        "Chuantan"
    ],
    "name:zho_x_variant":[
        "\u8239\u6f6d"
    ],
    "wof:name":"Chuantan",
    "wof:placetype":"locality"
},
  "geometry": {"coordinates":[112.34193999999999,24.82944],"type":"Point"}
}