{
  "type": "Feature",
  "properties": {
    "gn:admin1_code":"32.0",
    "gn:asciiname":"Mao'erba",
    "gn:country_code":"CN",
    "gn:dem":640,
    "gn:feature_class":"P",
    "gn:feature_code":"PPL",
    "gn:name":"Mao\u2019erba",
    "gn:population":0,
    "gn:timezone":"Asia/Shanghai",
    "iso:country":"CN",
    "name:zho_x_preferred":[
        "\u732b\u513f\u575d"
    ],
    "name:zho_x_variant":[
        "Mao\u2019erba"
    ],
    "wof:name":"Mao'erba",
    "wof:placetype":"locality"
},
  "geometry": {"coordinates":[103.70251,30.87886],"type":"Point"}
}