{
  "type": "Feature",
  "properties": {
    "gn:admin1_code":"10.0",
    "gn:asciiname":"Shanghe",
    "gn:country_code":"CN",
    "gn:dem":174,
    "gn:feature_class":"P",
    "gn:feature_code":"PPL",
    "gn:name":"Shanghe",
    "gn:population":0,
    "gn:timezone":"Asia/Shanghai",
    "iso:country":"CN",
    "name:und_x_variant":[
        "\u4e0a\u6cb3"
    ],
    "wof:name":"Shanghe",
    "wof:placetype":"locality"
},
  "geometry": {"coordinates":[114.71146,38.74159],"type":"Point"}
}