{
  "type": "Feature",
  "properties": {
    "gn:admin1_code":"18.0",
    "gn:asciiname":"Wu'ai Xiazhai",
    "gn:country_code":"CN",
    "gn:dem":868,
    "gn:feature_class":"P",
    "gn:feature_code":"PPL",
    "gn:name":"Wu\u2019ai Xiazhai",
    "gn:population":0,
    "gn:timezone":"Asia/Shanghai",
    "iso:country":"CN",
    "name:und_x_variant":[
        "Wu\u2019ai Xiazhai"
    ],
    "name:zho_x_preferred":[
        "\u4e4c\u57c3\u4e0b\u5be8"
    ],
    "wof:name":"Wu'ai Xiazhai",
    "wof:placetype":"locality"
},
  "geometry": {"coordinates":[107.765,26.0825],"type":"Point"}
}