{
  "type": "Feature",
  "properties": {
    "gn:admin1_code":"1.0",
    "gn:asciiname":"Sunzhuangcun",
    "gn:country_code":"CN",
    "gn:dem":27,
    "gn:feature_class":"P",
    "gn:feature_code":"PPL",
    "gn:name":"Sunzhuangcun",
    "gn:population":0,
    "gn:timezone":"Asia/Shanghai",
    "iso:country":"CN",
    "name:zho_x_preferred":[
        "\u5b59\u5e84\u6751"
    ],
    "wof:name":"Sunzhuangcun",
    "wof:placetype":"locality"
},
  "geometry": {"coordinates":[116.47615999999999,33.61821],"type":"Point"}
}