{
  "type": "Feature",
  "properties": {
    "gn:admin1_code":"1.0",
    "gn:asciiname":"Zhaoningcun",
    "gn:country_code":"CN",
    "gn:dem":31,
    "gn:feature_class":"P",
    "gn:feature_code":"PPL",
    "gn:name":"Zhaoningcun",
    "gn:population":0,
    "gn:timezone":"Asia/Shanghai",
    "iso:country":"CN",
    "name:zho_x_preferred":[
        "\u8d75\u5b81\u6751"
    ],
    "wof:name":"Zhaoningcun",
    "wof:placetype":"locality"
},
  "geometry": {"coordinates":[115.93872,32.75669],"type":"Point"}
}