{
  "type": "Feature",
  "properties": {
    "gn:admin1_code":"3.0",
    "gn:asciiname":"Laowu Daijia",
    "gn:country_code":"CN",
    "gn:dem":75,
    "gn:feature_class":"P",
    "gn:feature_code":"PPL",
    "gn:name":"Laowu Daijia",
    "gn:population":0,
    "gn:timezone":"Asia/Shanghai",
    "iso:country":"CN",
    "name:und_x_variant":[
        "\u8001\u5c4b\u6234\u5bb6"
    ],
    "wof:name":"Laowu Daijia",
    "wof:placetype":"locality"
},
  "geometry": {"coordinates":[116.73023999999999,28.45227],"type":"Point"}
}