{
  "type": "Feature",
  "properties": {
    "gn:admin1_code":"25.0",
    "gn:asciiname":"Dazhanjia",
    "gn:country_code":"CN",
    "gn:dem":30,
    "gn:feature_class":"P",
    "gn:feature_code":"PPL",
    "gn:name":"Dazhanjia",
    "gn:population":0,
    "gn:timezone":"Asia/Shanghai",
    "iso:country":"CN",
    "name:zho_x_preferred":[
        "\u5927\u6218\u5bb6"
    ],
    "wof:name":"Dazhanjia",
    "wof:placetype":"locality"
},
  "geometry": {"coordinates":[120.11142,37.34587],"type":"Point"}
}