{
  "type": "Feature",
  "properties": {
    "gn:admin1_code":"20.0",
    "gn:asciiname":"Kelimeng",
    "gn:country_code":"CN",
    "gn:dem":1459,
    "gn:feature_class":"P",
    "gn:feature_code":"PPL",
    "gn:name":"Kelimeng",
    "gn:population":0,
    "gn:timezone":"Asia/Shanghai",
    "iso:country":"CN",
    "name:und_x_variant":[
        "\u514b\u529b\u5b5f"
    ],
    "wof:name":"Kelimeng",
    "wof:placetype":"locality"
},
  "geometry": {"coordinates":[112.84632000000001,41.56197],"type":"Point"}
}