{
  "type": "Feature",
  "properties": {
    "gn:admin1_code":"26.0",
    "gn:asciiname":"Daliangshang",
    "gn:country_code":"CN",
    "gn:dem":1182,
    "gn:feature_class":"P",
    "gn:feature_code":"PPL",
    "gn:name":"Daliangshang",
    "gn:population":0,
    "gn:timezone":"Asia/Shanghai",
    "iso:country":"CN",
    "name:und_x_variant":[
        "\u5927\u6881\u4e0a"
    ],
    "wof:name":"Daliangshang",
    "wof:placetype":"locality"
},
  "geometry": {"coordinates":[108.05897,32.97392],"type":"Point"}
}