{
  "type": "Feature",
  "properties": {
    "gn:admin1_code":"25.0",
    "gn:asciiname":"Qigezhuang",
    "gn:country_code":"CN",
    "gn:dem":32,
    "gn:feature_class":"P",
    "gn:feature_code":"PPL",
    "gn:name":"Qigezhuang",
    "gn:population":0,
    "gn:timezone":"Asia/Shanghai",
    "iso:country":"CN",
    "name:zho_x_preferred":[
        "\u8d77\u6208\u5e84"
    ],
    "wof:name":"Qigezhuang",
    "wof:placetype":"locality"
},
  "geometry": {"coordinates":[120.3389,36.57303],"type":"Point"}
}