{
  "type": "Feature",
  "properties": {
    "gn:admin1_code":"26.0",
    "gn:asciiname":"Xiayuantou",
    "gn:country_code":"CN",
    "gn:dem":857,
    "gn:feature_class":"P",
    "gn:feature_code":"PPL",
    "gn:name":"Xiayuantou",
    "gn:population":0,
    "gn:timezone":"Asia/Shanghai",
    "iso:country":"CN",
    "name:zho_x_preferred":[
        "\u4e0b\u586c\u5934"
    ],
    "wof:name":"Xiayuantou",
    "wof:placetype":"locality"
},
  "geometry": {"coordinates":[110.38079,36.17451],"type":"Point"}
}