{
  "type": "Feature",
  "properties": {
    "gn:admin1_code":"32.0",
    "gn:asciiname":"Quelangduona",
    "gn:country_code":"CN",
    "gn:dem":4267,
    "gn:feature_class":"P",
    "gn:feature_code":"PPL",
    "gn:name":"Quelangduona",
    "gn:population":0,
    "gn:timezone":"Asia/Shanghai",
    "iso:country":"CN",
    "name:zho_x_preferred":[
        "\u5374\u90ce\u593a\u7eb3"
    ],
    "wof:name":"Quelangduona",
    "wof:placetype":"locality"
},
  "geometry": {"coordinates":[100.98099999999999,29.8966],"type":"Point"}
}