{
  "type": "Feature",
  "properties": {
    "gn:admin1_code":"5.0",
    "gn:asciiname":"Dongxiajia",
    "gn:country_code":"CN",
    "gn:dem":188,
    "gn:feature_class":"P",
    "gn:feature_code":"PPL",
    "gn:name":"Dongxiajia",
    "gn:population":0,
    "gn:timezone":"Asia/Shanghai",
    "iso:country":"CN",
    "name:zho_x_preferred":[
        "\u4e1c\u590f\u5bb6"
    ],
    "wof:name":"Dongxiajia",
    "wof:placetype":"locality"
},
  "geometry": {"coordinates":[124.41386,43.12097],"type":"Point"}
}