{
  "type": "Feature",
  "properties": {
    "gn:country":"CN",
    "gn:fcode":"ADM3",
    "gn:pop":0,
    "iso:country":"CN",
    "name:eng_x_preferred":[
        "kunshan shi"
    ],
    "name:unk_x_variant":[
        "Kunshan Xian"
    ],
    "name:zho_x_preferred":[
        "\u6606\u5c71\u5e02"
    ],
    "name:zho_x_variant":[
        "\u6606\u5c71"
    ],
    "qs:name":"Kunshan Shi",
    "qs:photos_9r":0,
    "qs:photos_sr":0,
    "qs:pop_sr":"0",
    "wof:name":"Kunshan Shi",
    "wof:placetype":"localadmin",
    "wof:population":0
},
  "geometry": {"coordinates":[120.97051999999999,31.34497],"type":"Point"}
}