{
  "type": "Feature",
  "properties": {
    "gn:admin1_code":"4.0",
    "gn:asciiname":"Beisongjiadun",
    "gn:country_code":"CN",
    "gn:dem":3,
    "gn:feature_class":"P",
    "gn:feature_code":"PPL",
    "gn:name":"Beisongjiadun",
    "gn:population":0,
    "gn:timezone":"Asia/Shanghai",
    "iso:country":"CN",
    "name:zho_x_preferred":[
        "\u5317\u5b8b\u5bb6\u58a9"
    ],
    "wof:name":"Beisongjiadun",
    "wof:placetype":"locality"
},
  "geometry": {"coordinates":[120.47148,32.93577],"type":"Point"}
}