{
  "type": "Feature",
  "properties": {
    "gn:admin1_code":"02",
    "gn:asciiname":"Daji",
    "gn:country_code":"CN",
    "gn:dem":1020,
    "gn:feature_class":"P",
    "gn:feature_code":"PPLA4",
    "gn:name":"Daji",
    "gn:population":0,
    "gn:timezone":"Asia/Shanghai",
    "iso:country":"CN",
    "name:und_x_variant":[
        "Xi\u2019andi",
        "Ta-chi",
        "\u5927\u6f08",
        "Daji",
        "Daji Xiang"
    ],
    "name:zho_x_preferred":[
        "\u5927\u6f08\u4e61"
    ],
    "wof:name":"Daji",
    "wof:placetype":"locality"
},
  "geometry": {"coordinates":[119.58574,27.81409],"type":"Point"}
}