{
  "type": "Feature",
  "properties": {
    "gn:admin1_code":"10",
    "gn:asciiname":"Houwuhao",
    "gn:country_code":"CN",
    "gn:dem":1294,
    "gn:feature_class":"P",
    "gn:feature_code":"PPLF",
    "gn:name":"Houwuhao",
    "gn:population":0,
    "gn:timezone":"Asia/Shanghai",
    "iso:country":"CN",
    "name:zho_x_preferred":[
        "\u540e\u4e94\u53f7"
    ],
    "wof:name":"Houwuhao",
    "wof:placetype":"locality"
},
  "geometry": {"coordinates":[114.02057000000001,41.41714],"type":"Point"}
}