{
  "type": "Feature",
  "properties": {
    "gn:admin1_code":"19.0",
    "gn:asciiname":"Xihaidaiwan",
    "gn:country_code":"CN",
    "gn:dem":21,
    "gn:feature_class":"P",
    "gn:feature_code":"PPL",
    "gn:name":"Xihaidaiwan",
    "gn:population":0,
    "gn:timezone":"Asia/Shanghai",
    "iso:country":"CN",
    "name:zho_x_preferred":[
        "\u897f\u6d77\u5e26\u6e7e"
    ],
    "wof:name":"Xihaidaiwan",
    "wof:placetype":"locality"
},
  "geometry": {"coordinates":[122.571,39.2812],"type":"Point"}
}