{
  "type": "Feature",
  "properties": {
    "gn:admin1_code":"9",
    "gn:asciiname":"Donghangutuan",
    "gn:country_code":"CN",
    "gn:dem":48,
    "gn:feature_class":"P",
    "gn:feature_code":"PPL",
    "gn:name":"Donghangutuan",
    "gn:population":0,
    "gn:timezone":"Asia/Shanghai",
    "iso:country":"CN",
    "name:zho_x_preferred":[
        "\u4e1c\u97e9\u56fa\u7583"
    ],
    "wof:name":"Donghangutuan",
    "wof:placetype":"locality"
},
  "geometry": {"coordinates":[115.33055,36.05842],"type":"Point"}
}