{
  "type": "Feature",
  "properties": {
    "gn:admin1_code":"16.0",
    "gn:asciiname":"Lunpo",
    "gn:country_code":"CN",
    "gn:dem":293,
    "gn:feature_class":"P",
    "gn:feature_code":"PPL",
    "gn:name":"Lunpo",
    "gn:population":0,
    "gn:timezone":"Asia/Shanghai",
    "iso:country":"CN",
    "name:zho_x_preferred":[
        "\u4f26\u5761"
    ],
    "wof:name":"Lunpo",
    "wof:placetype":"locality"
},
  "geometry": {"coordinates":[107.386,22.6995],"type":"Point"}
}