{
  "type": "Feature",
  "properties": {
    "gn:admin1_code":"5.0",
    "gn:asciiname":"Dongwushibahao",
    "gn:country_code":"CN",
    "gn:dem":146,
    "gn:feature_class":"P",
    "gn:feature_code":"PPL",
    "gn:name":"Dongwushibahao",
    "gn:population":0,
    "gn:timezone":"Asia/Shanghai",
    "iso:country":"CN",
    "name:zho_x_preferred":[
        "\u4e1c\u4e94\u5341\u516b\u53f7"
    ],
    "wof:name":"Dongwushibahao",
    "wof:placetype":"locality"
},
  "geometry": {"coordinates":[123.40897,44.33095],"type":"Point"}
}