{
  "type": "Feature",
  "properties": {
    "gn:admin1_code":"32.0",
    "gn:asciiname":"Kuyaogou",
    "gn:country_code":"CN",
    "gn:dem":2172,
    "gn:feature_class":"P",
    "gn:feature_code":"PPL",
    "gn:name":"Kuyaogou",
    "gn:population":0,
    "gn:timezone":"Asia/Shanghai",
    "iso:country":"CN",
    "name:zho_x_preferred":[
        "\u82e6\u8170\u6c9f"
    ],
    "wof:name":"Kuyaogou",
    "wof:placetype":"locality"
},
  "geometry": {"coordinates":[102.285,29.7718],"type":"Point"}
}