{
  "type": "Feature",
  "properties": {
    "gn:admin1_code":"18.0",
    "gn:asciiname":"Dachong",
    "gn:country_code":"CN",
    "gn:dem":848,
    "gn:feature_class":"P",
    "gn:feature_code":"PPL",
    "gn:name":"Dachong",
    "gn:population":0,
    "gn:timezone":"Asia/Shanghai",
    "iso:country":"CN",
    "name:fas_x_preferred":[
        "\u062f\u0627\u0686\u0648\u0646\u06af"
    ],
    "name:zho_x_preferred":[
        "\u5927\u51b2"
    ],
    "name:zho_x_variant":[
        "\u5927\u6d8c\u9547"
    ],
    "wof:name":"Dachong",
    "wof:placetype":"locality"
},
  "geometry": {"coordinates":[107.346,25.89],"type":"Point"}
}