{
  "type": "Feature",
  "properties": {
    "gn:admin1_code":"25.0",
    "gn:asciiname":"Yangxinzhuangcun",
    "gn:country_code":"CN",
    "gn:dem":36,
    "gn:feature_class":"P",
    "gn:feature_code":"PPL",
    "gn:name":"Yangxinzhuangcun",
    "gn:population":0,
    "gn:timezone":"Asia/Shanghai",
    "iso:country":"CN",
    "name:zho_x_preferred":[
        "\u6768\u8f9b\u5e84\u6751"
    ],
    "wof:name":"Yangxinzhuangcun",
    "wof:placetype":"locality"
},
  "geometry": {"coordinates":[115.81870000000001,36.73821],"type":"Point"}
}