{
  "type": "Feature",
  "properties": {
    "gn:admin1_code":"11.0",
    "gn:asciiname":"Mingjiatang",
    "gn:country_code":"CN",
    "gn:dem":214,
    "gn:feature_class":"P",
    "gn:feature_code":"PPL",
    "gn:name":"Mingjiatang",
    "gn:population":0,
    "gn:timezone":"Asia/Shanghai",
    "iso:country":"CN",
    "name:zho_x_preferred":[
        "\u660e\u5bb6\u5858"
    ],
    "wof:name":"Mingjiatang",
    "wof:placetype":"locality"
},
  "geometry": {"coordinates":[110.56466,28.01563],"type":"Point"}
}