{
  "type": "Feature",
  "properties": {
    "gn:admin1_code":"29.0",
    "gn:asciiname":"Xinpaling",
    "gn:country_code":"CN",
    "gn:dem":1441,
    "gn:feature_class":"P",
    "gn:feature_code":"PPL",
    "gn:name":"Xinpaling",
    "gn:population":0,
    "gn:timezone":"Asia/Shanghai",
    "iso:country":"CN",
    "name:zho_x_preferred":[
        "\u65b0\u6015\u5cad"
    ],
    "wof:name":"Xinpaling",
    "wof:placetype":"locality"
},
  "geometry": {"coordinates":[100.047,24.1946],"type":"Point"}
}