{
  "type": "Feature",
  "properties": {
    "gn:admin1_code":"14.0",
    "gn:asciiname":"Quguo Xicun",
    "gn:country_code":"CN",
    "gn:dem":3958,
    "gn:feature_class":"P",
    "gn:feature_code":"PPL",
    "gn:name":"Quguo Xicun",
    "gn:population":0,
    "gn:timezone":"Asia/Urumqi",
    "iso:country":"CN",
    "name:zho_x_preferred":[
        "\u66f2\u679c\u897f\u6751"
    ],
    "wof:name":"Quguo Xicun",
    "wof:placetype":"locality"
},
  "geometry": {"coordinates":[94.67491,30.98581],"type":"Point"}
}