{
  "type": "Feature",
  "properties": {
    "gn:admin1_code":"23.0",
    "gn:asciiname":"Xiaokunshan",
    "gn:cc2":"CN",
    "gn:country_code":"CN",
    "gn:dem":5,
    "gn:feature_class":"P",
    "gn:feature_code":"PPL",
    "gn:name":"Xiaokunshan",
    "gn:population":0,
    "gn:timezone":"Asia/Shanghai",
    "iso:country":"CN",
    "name:und_x_variant":[
        "K\u2019un-shan-chen",
        "Hsiao-k\u2019un-shan-chen",
        "Hsiao-k\u2019un-shan",
        "Xiaokunshan",
        "\u5c0f\u6606\u5c71"
    ],
    "wof:name":"Xiaokunshan",
    "wof:placetype":"locality"
},
  "geometry": {"coordinates":[121.12389,31.04361],"type":"Point"}
}