{
  "type": "Feature",
  "properties": {
    "gn:admin1_code":"32.0",
    "gn:asciiname":"Sanyuanqiao",
    "gn:country_code":"CN",
    "gn:dem":466,
    "gn:feature_class":"P",
    "gn:feature_code":"PPL",
    "gn:name":"Sanyuanqiao",
    "gn:population":0,
    "gn:timezone":"Asia/Shanghai",
    "iso:country":"CN",
    "name:zho_x_preferred":[
        "\u4e09\u5143\u6865"
    ],
    "wof:name":"Sanyuanqiao",
    "wof:placetype":"locality"
},
  "geometry": {"coordinates":[104.61645,31.09874000000001],"type":"Point"}
}