{
  "type": "Feature",
  "properties": {
    "gn:admin1_code":"32.0",
    "gn:asciiname":"Baixiluo",
    "gn:country_code":"CN",
    "gn:dem":2084,
    "gn:feature_class":"P",
    "gn:feature_code":"PPL",
    "gn:name":"Baixiluo",
    "gn:population":0,
    "gn:timezone":"Asia/Shanghai",
    "iso:country":"CN",
    "name:zho_x_preferred":[
        "\u767d\u897f\u6d1b"
    ],
    "wof:name":"Baixiluo",
    "wof:placetype":"locality"
},
  "geometry": {"coordinates":[102.099,28.63782],"type":"Point"}
}