{
  "type": "Feature",
  "properties": {
    "gn:admin1_code":"11.0",
    "gn:asciiname":"Yanwowu",
    "gn:country_code":"CN",
    "gn:dem":49,
    "gn:feature_class":"P",
    "gn:feature_code":"PPL",
    "gn:name":"Yanwowu",
    "gn:population":0,
    "gn:timezone":"Asia/Shanghai",
    "iso:country":"CN",
    "name:zho_x_preferred":[
        "\u71d5\u7a9d\u5c4b"
    ],
    "wof:name":"Yanwowu",
    "wof:placetype":"locality"
},
  "geometry": {"coordinates":[113.17623,29.37585],"type":"Point"}
}