{
  "type": "Feature",
  "properties": {
    "gn:admin1_code":"15",
    "gn:asciiname":"Jingchuan Chengguanzhen",
    "gn:country_code":"CN",
    "gn:dem":1033,
    "gn:feature_class":"P",
    "gn:feature_code":"PPLA3",
    "gn:name":"Jingchuan Chengguanzhen",
    "gn:population":0,
    "gn:timezone":"Asia/Shanghai",
    "iso:country":"CN",
    "name:und_x_variant":[
        "Ching-ch\u2019uan",
        "Tszinchuan\u2019",
        "Ching-chou",
        "Jingchuan",
        "Jingchuan Chengguanzhen",
        "Jingchuan Xian"
    ],
    "name:zho_x_preferred":[
        "\u6cfe\u5ddd\u57ce\u5173\u9547"
    ],
    "name:zho_x_variant":[
        "\u6cfe\u5ddd\u53bf"
    ],
    "wof:name":"Jingchuan Chengguanzhen",
    "wof:placetype":"locality"
},
  "geometry": {"coordinates":[107.36111,35.33194],"type":"Point"}
}