{
  "type": "Feature",
  "properties": {
    "gn:admin1_code":"3.0",
    "gn:asciiname":"Xi'an",
    "gn:country_code":"CN",
    "gn:dem":403,
    "gn:feature_class":"P",
    "gn:feature_code":"PPL",
    "gn:name":"Xi\u2019an",
    "gn:population":0,
    "gn:timezone":"Asia/Shanghai",
    "iso:country":"CN",
    "name:und_x_variant":[
        "Xi\u2019an",
        "\u897f\u5cb8"
    ],
    "wof:name":"Xi'an",
    "wof:placetype":"locality"
},
  "geometry": {"coordinates":[114.76245,29.00915],"type":"Point"}
}