{
  "type": "Feature",
  "properties": {
    "gn:admin1_code":"10.0",
    "gn:asciiname":"Houqixingzhai",
    "gn:country_code":"CN",
    "gn:dem":28,
    "gn:feature_class":"P",
    "gn:feature_code":"PPL",
    "gn:name":"Houqixingzhai",
    "gn:population":0,
    "gn:timezone":"Asia/Shanghai",
    "iso:country":"CN",
    "name:zho_x_preferred":[
        "\u540e\u4e03\u661f\u5be8"
    ],
    "wof:name":"Houqixingzhai",
    "wof:placetype":"locality"
},
  "geometry": {"coordinates":[119.68228000000001,40.00403],"type":"Point"}
}