{
  "type": "Feature",
  "properties": {
    "gn:admin1_code":"26.0",
    "gn:asciiname":"Longwangzhuang",
    "gn:country_code":"CN",
    "gn:dem":623,
    "gn:feature_class":"P",
    "gn:feature_code":"PPL",
    "gn:name":"Longwangzhuang",
    "gn:population":0,
    "gn:timezone":"Asia/Shanghai",
    "iso:country":"CN",
    "name:und_x_variant":[
        "\u9f99\u738b\u5e84"
    ],
    "wof:name":"Longwangzhuang",
    "wof:placetype":"locality"
},
  "geometry": {"coordinates":[107.78949,33.22842],"type":"Point"}
}