{
  "type": "Feature",
  "properties": {
    "gn:admin1_code":"10.0",
    "gn:asciiname":"Woluogu",
    "gn:cc2":"CN",
    "gn:country_code":"CN",
    "gn:dem":7,
    "gn:feature_class":"P",
    "gn:feature_code":"PPL",
    "gn:name":"Woluogu",
    "gn:population":0,
    "gn:timezone":"Asia/Shanghai",
    "iso:country":"CN",
    "name:und_x_variant":[
        "Wo-lo-ku",
        "Wo-ko-ku",
        "Wo-yen-ku",
        "Woluogu"
    ],
    "wof:name":"Woluogu",
    "wof:placetype":"locality"
},
  "geometry": {"coordinates":[117.77361000000001,39.66472],"type":"Point"}
}