{
  "type": "Feature",
  "properties": {
    "iso:country":"CN",
    "name:eng_x_preferred":[
        "Gannan Tibetan Autonomous Prefecture"
    ],
    "name:zho_x_preferred":[
        "\u7518\u5357\u85cf\u65cf\u81ea\u6cbb\u5dde"
    ],
    "qs:name":"\u7518\u5357\u85cf\u65cf\u81ea\u6cbb\u5dde",
    "qs:name_adm0":"\u4e2d\u570b",
    "qs:name_adm1":"\u7518\u8083\u7701",
    "qs:photos":244,
    "qs:photos_1k":49,
    "qs:photos_9k":9,
    "qs:photos_9r":9,
    "qs:photos_all":2085,
    "qs:photos_sr":4,
    "qs:placetype":"LocalAdmin",
    "qs:pop_sr":"0",
    "wof:name":"Gannan Tibetan Autonomous Prefecture",
    "wof:placetype":"localadmin"
},
  "geometry": {"coordinates":[102.50328500000001,35.189953],"type":"Point"}
}