{
  "type": "Feature",
  "properties": {
    "gn:admin1_code":"3.0",
    "gn:asciiname":"Pingdi",
    "gn:country_code":"CN",
    "gn:dem":242,
    "gn:feature_class":"P",
    "gn:feature_code":"PPL",
    "gn:name":"Pingdi",
    "gn:population":0,
    "gn:timezone":"Asia/Shanghai",
    "iso:country":"CN",
    "name:und_x_variant":[
        "\u576a\u5730"
    ],
    "wof:name":"Pingdi",
    "wof:placetype":"locality"
},
  "geometry": {"coordinates":[116.20356,26.38907],"type":"Point"}
}