{
  "type": "Feature",
  "properties": {
    "gn:admin1_code":"31",
    "gn:asciiname":"Fuqi",
    "gn:country_code":"CN",
    "gn:dem":164,
    "gn:feature_class":"P",
    "gn:feature_code":"PPL",
    "gn:name":"Fuqi",
    "gn:population":0,
    "gn:timezone":"Asia/Shanghai",
    "iso:country":"CN",
    "name:und_x_variant":[
        "\u961c\u6c14"
    ],
    "wof:name":"Fuqi",
    "wof:placetype":"locality"
},
  "geometry": {"coordinates":[109.221,19.4589],"type":"Point"}
}