{
  "type": "Feature",
  "properties": {
    "gn:admin1_code":"15.0",
    "gn:asciiname":"Jiazui",
    "gn:country_code":"CN",
    "gn:dem":1978,
    "gn:feature_class":"P",
    "gn:feature_code":"PPL",
    "gn:name":"Jiazui",
    "gn:population":0,
    "gn:timezone":"Asia/Shanghai",
    "iso:country":"CN",
    "name:zho_x_preferred":[
        "\u8d3e\u5634"
    ],
    "wof:name":"Jiazui",
    "wof:placetype":"locality"
},
  "geometry": {"coordinates":[106.496,35.5877],"type":"Point"}
}