{
  "type": "Feature",
  "properties": {
    "gn:admin1_code":"4.0",
    "gn:asciiname":"Gongshuntouxu",
    "gn:country_code":"CN",
    "gn:dem":3,
    "gn:feature_class":"P",
    "gn:feature_code":"PPL",
    "gn:name":"Gongshuntouxu",
    "gn:population":0,
    "gn:timezone":"Asia/Shanghai",
    "iso:country":"CN",
    "name:zho_x_preferred":[
        "\u516c\u987a\u5934\u5729"
    ],
    "wof:name":"Gongshuntouxu",
    "wof:placetype":"locality"
},
  "geometry": {"coordinates":[120.68259999999999,31.92465],"type":"Point"}
}