{
  "type": "Feature",
  "properties": {
    "gn:admin1_code":"30.0",
    "gn:asciiname":"Zhoushan",
    "gn:country_code":"CN",
    "gn:dem":10,
    "gn:feature_class":"P",
    "gn:feature_code":"PPL",
    "gn:name":"Zhoushan",
    "gn:population":0,
    "gn:timezone":"Asia/Shanghai",
    "iso:country":"CN",
    "name:ara_x_preferred":[
        "\u0632\u0647\u0648\u0634\u0627\u0646"
    ],
    "name:cdo_x_preferred":[
        "Ci\u016d-s\u0103ng"
    ],
    "name:ces_x_preferred":[
        "\u010cou-\u0161an"
    ],
    "name:dan_x_preferred":[
        "Zhoushan"
    ],
    "name:deu_x_preferred":[
        "Zhoushan"
    ],
    "name:eus_x_preferred":[
        "Zhoushan"
    ],
    "name:fas_x_preferred":[
        "\u062c\u0648\u0627\u0634\u0627\u0646"
    ],
    "name:fin_x_preferred":[
        "Zhoushan"
    ],
    "name:fra_x_preferred":[
        "Zhoushan"
    ],
    "name:ind_x_preferred":[
        "Zhoushan"
    ],
    "name:ita_x_preferred":[
        "Zhoushan"
    ],
    "name:jpn_x_preferred":[
        "\u821f\u5c71\u5e02"
    ],
    "name:kik_x_preferred":[
        "Zhoushan"
    ],
    "name:kor_x_preferred":[
        "\uc800\uc6b0\uc0b0\uc2dc"
    ],
    "name:mlg_x_preferred":[
        "Zhoushan"
    ],
    "name:nld_x_preferred":[
        "Zhoushan"
    ],
    "name:nno_x_preferred":[
        "Zhoushan"
    ],
    "name:nor_x_preferred":[
        "Zhoushan"
    ],
    "name:pol_x_preferred":[
        "Zhoushan"
    ],
    "name:rus_x_preferred":[
        "\u0427\u0436\u043e\u0443\u0448\u0430\u043d\u044c"
    ],
    "name:spa_x_preferred":[
        "Zhoushan"
    ],
    "name:swe_x_preferred":[
        "Zhoushan"
    ],
    "name:tgl_x_preferred":[
        "Zhoushan"
    ],
    "name:tur_x_preferred":[
        "Zhoushan"
    ],
    "name:uig_x_preferred":[
        "\u062c\u06c7\u0634\u06d5\u0646 \u0634\u06d5\u06be\u0649\u0631\u0649"
    ],
    "name:urd_x_preferred":[
        "\u0698\u0648\u0648\u0634\u0627\u0646"
    ],
    "name:vie_x_preferred":[
        "Chu San"
    ],
    "name:war_x_preferred":[
        "Zhoushan"
    ],
    "name:wuu_x_preferred":[
        "\u821f\u5c71\u5e02"
    ],
    "name:zho_x_preferred":[
        "\u6d32\u5c71"
    ],
    "name:zho_x_variant":[
        "\u821f\u5c71\u5e02"
    ],
    "wof:name":"Zhoushan",
    "wof:placetype":"locality"
},
  "geometry": {"coordinates":[112.85624,22.00195],"type":"Point"}
}