{
  "type": "Feature",
  "properties": {
    "gn:admin1_code":"02",
    "gn:asciiname":"Lixian",
    "gn:country_code":"CN",
    "gn:dem":140,
    "gn:feature_class":"P",
    "gn:feature_code":"PPL",
    "gn:name":"Lixian",
    "gn:population":0,
    "gn:timezone":"Asia/Shanghai",
    "iso:country":"CN",
    "name:zho_x_preferred":[
        "\u793c\u8d24"
    ],
    "wof:name":"Lixian",
    "wof:placetype":"locality"
},
  "geometry": {"coordinates":[118.51743999999999,28.60541],"type":"Point"}
}