{
  "type": "Feature",
  "properties": {
    "gn:admin1_code":"4.0",
    "gn:asciiname":"Gaojicun",
    "gn:country_code":"CN",
    "gn:dem":24,
    "gn:feature_class":"P",
    "gn:feature_code":"PPL",
    "gn:name":"Gaojicun",
    "gn:population":0,
    "gn:timezone":"Asia/Shanghai",
    "iso:country":"CN",
    "name:zho_x_preferred":[
        "\u9ad8\u96c6\u6751"
    ],
    "wof:name":"Gaojicun",
    "wof:placetype":"locality"
},
  "geometry": {"coordinates":[118.65808,33.53851],"type":"Point"}
}