{
  "type": "Feature",
  "properties": {
    "gn:admin1_code":"18.0",
    "gn:asciiname":"Longxi",
    "gn:country_code":"CN",
    "gn:dem":879,
    "gn:feature_class":"P",
    "gn:feature_code":"PPL",
    "gn:name":"Longxi",
    "gn:population":0,
    "gn:timezone":"Asia/Shanghai",
    "iso:country":"CN",
    "name:ara_x_preferred":[
        "\u0644\u0648\u0646\u062c\u0643\u0633\u064a"
    ],
    "name:ben_x_preferred":[
        "\u09b2\u0982\u0997\u0995\u09cd\u09b8\u09bf"
    ],
    "name:ceb_x_preferred":[
        "Longxi"
    ],
    "name:deu_x_preferred":[
        "Longxi"
    ],
    "name:ell_x_preferred":[
        "\u039b\u03cc\u03bd\u03b3\u03ba\u03be\u03b9"
    ],
    "name:eng_x_preferred":[
        "Longxi"
    ],
    "name:fas_x_preferred":[
        "\u0644\u0646\u06af\u0634\u06cc"
    ],
    "name:fra_x_preferred":[
        "Longxi"
    ],
    "name:heb_x_preferred":[
        "\u05dc\u05d5\u05e0\u05d2\u05e7\u05e1\u05d9"
    ],
    "name:hin_x_preferred":[
        "\u0932\u093e\u0902\u0917\u0915\u094d\u0938\u0940"
    ],
    "name:hun_x_preferred":[
        "Longxi"
    ],
    "name:ind_x_preferred":[
        "Longxi"
    ],
    "name:ita_x_preferred":[
        "Longxi"
    ],
    "name:jpn_x_preferred":[
        "\u96b4\u897f"
    ],
    "name:kor_x_preferred":[
        "\ub8fd\uc2dc"
    ],
    "name:nld_x_preferred":[
        "Longxi"
    ],
    "name:pol_x_preferred":[
        "Longxi"
    ],
    "name:por_x_preferred":[
        "Longxi"
    ],
    "name:rus_x_preferred":[
        "\u041b\u0443\u043d\u0441\u0438"
    ],
    "name:spa_x_preferred":[
        "Longxi"
    ],
    "name:swe_x_preferred":[
        "Longxi"
    ],
    "name:tur_x_preferred":[
        "Longxi"
    ],
    "name:ukr_x_preferred":[
        "\u041b\u0443\u043d\u0441\u0456"
    ],
    "name:urd_x_preferred":[
        "\u0644\u0648\u0646\u06af\u0632\u06cc"
    ],
    "name:vie_x_preferred":[
        "L\u0169ng T\u00e2y"
    ],
    "name:zho_cn_x_preferred":[
        "\u9647\u897f"
    ],
    "name:zho_tw_x_preferred":[
        "\u96b4\u897f"
    ],
    "name:zho_x_preferred":[
        "\u9f99\u6eaa"
    ],
    "wof:name":"Longxi",
    "wof:placetype":"locality"
},
  "geometry": {"coordinates":[108.773,26.3192],"type":"Point"}
}