{
  "type": "Feature",
  "properties": {
    "gn:admin1_code":"26",
    "gn:asciiname":"Laodian",
    "gn:country_code":"CN",
    "gn:dem":408,
    "gn:feature_class":"P",
    "gn:feature_code":"PPLA4",
    "gn:name":"Laodian",
    "gn:population":0,
    "gn:timezone":"Asia/Shanghai",
    "iso:country":"CN",
    "name:und_x_variant":[
        "Lao-tien",
        "Laodian Zhen",
        "Laodian"
    ],
    "name:zho_x_preferred":[
        "\u6d9d\u5e97"
    ],
    "name:zho_x_variant":[
        "\u6d9d\u5e97\u9547"
    ],
    "wof:name":"Laodian",
    "wof:placetype":"locality"
},
  "geometry": {"coordinates":[108.56417999999999,34.1714],"type":"Point"}
}