{
  "type": "Feature",
  "properties": {
    "gn:admin1_code":"3.0",
    "gn:asciiname":"Baijiawo",
    "gn:country_code":"CN",
    "gn:dem":322,
    "gn:feature_class":"P",
    "gn:feature_code":"PPL",
    "gn:name":"Baijiawo",
    "gn:population":0,
    "gn:timezone":"Asia/Shanghai",
    "iso:country":"CN",
    "name:und_x_variant":[
        "\u767d\u5bb6\u7a9d"
    ],
    "wof:name":"Baijiawo",
    "wof:placetype":"locality"
},
  "geometry": {"coordinates":[115.60896,26.8414],"type":"Point"}
}