{
  "type": "Feature",
  "properties": {
    "gn:admin1_code":"8.0",
    "gn:asciiname":"Baidajiecun",
    "gn:country_code":"CN",
    "gn:dem":144,
    "gn:feature_class":"P",
    "gn:feature_code":"PPL",
    "gn:name":"Baidajiecun",
    "gn:population":0,
    "gn:timezone":"Asia/Shanghai",
    "iso:country":"CN",
    "name:zho_x_preferred":[
        "\u4f70\u5927\u8857\u6751"
    ],
    "wof:name":"Baidajiecun",
    "wof:placetype":"locality"
},
  "geometry": {"coordinates":[123.71473,46.99643],"type":"Point"}
}