{
  "type": "Feature",
  "properties": {
    "gn:admin1_code":"19.0",
    "gn:asciiname":"Qiangandao",
    "gn:country_code":"CN",
    "gn:dem":27,
    "gn:feature_class":"P",
    "gn:feature_code":"PPL",
    "gn:name":"Qiangandao",
    "gn:population":0,
    "gn:timezone":"Asia/Shanghai",
    "iso:country":"CN",
    "name:zho_x_preferred":[
        "\u524d\u5e72\u5c9b"
    ],
    "wof:name":"Qiangandao",
    "wof:placetype":"locality"
},
  "geometry": {"coordinates":[122.97,39.5014],"type":"Point"}
}