{
  "type": "Feature",
  "properties": {
    "gn:admin1_code":"26.0",
    "gn:asciiname":"Xinwanwan",
    "gn:country_code":"CN",
    "gn:dem":1500,
    "gn:feature_class":"P",
    "gn:feature_code":"PPL",
    "gn:name":"Xinwanwan",
    "gn:population":0,
    "gn:timezone":"Asia/Shanghai",
    "iso:country":"CN",
    "name:zho_x_preferred":[
        "\u8f9b\u6e7e\u6e7e"
    ],
    "wof:name":"Xinwanwan",
    "wof:placetype":"locality"
},
  "geometry": {"coordinates":[107.36691,37.20449],"type":"Point"}
}