{
  "type": "Feature",
  "properties": {
    "gn:admin1_code":"19.0",
    "gn:asciiname":"Xiaoweituncun",
    "gn:country_code":"CN",
    "gn:dem":211,
    "gn:feature_class":"P",
    "gn:feature_code":"PPL",
    "gn:name":"Xiaoweituncun",
    "gn:population":0,
    "gn:timezone":"Asia/Shanghai",
    "iso:country":"CN",
    "name:zho_x_preferred":[
        "\u5c0f\u9b4f\u5c6f\u6751"
    ],
    "wof:name":"Xiaoweituncun",
    "wof:placetype":"locality"
},
  "geometry": {"coordinates":[123.093,40.4087],"type":"Point"}
}