{
  "type": "Feature",
  "properties": {
    "gn:country":"CN",
    "gn:fcode":"ADM3",
    "gn:pop":0,
    "iso:country":"CN",
    "name:eng_x_preferred":[
        "Bijiang District"
    ],
    "name:unk_x_variant":[
        "T\u2019ung-jen Hsien"
    ],
    "name:zho_x_preferred":[
        "\u94dc\u4ec1\u5e02"
    ],
    "name:zho_x_variant":[
        "\u94dc\u4ec1"
    ],
    "qs:name":"\u94dc\u4ec1\u5e02",
    "qs:name_adm0":"\u4e2d\u570b",
    "qs:name_adm1":"\u8d35\u5dde\u7701",
    "qs:photos":286,
    "qs:photos_1k":58,
    "qs:photos_9k":1,
    "qs:photos_9r":5,
    "qs:photos_all":322,
    "qs:photos_sr":5,
    "qs:placetype":"LocalAdmin",
    "qs:pop_sr":"0",
    "wd:wordcount":125,
    "wof:name":"\u94dc\u4ec1\u5e02",
    "wof:placetype":"localadmin",
    "wof:population":0
},
  "geometry": {"coordinates":[109.12045000000001,27.68707],"type":"Point"}
}