{
  "type": "Feature",
  "properties": {
    "gn:country":"CN",
    "gn:fcode":"ADM3",
    "gn:population":0,
    "iso:country":"CN",
    "name:ceb_x_preferred":[
        "Tongren Shi"
    ],
    "name:cym_x_preferred":[
        "Ardal Bijiang"
    ],
    "name:deu_x_preferred":[
        "Bijiang"
    ],
    "name:eng_x_preferred":[
        "Bijiang District"
    ],
    "name:fra_x_preferred":[
        "Tongren"
    ],
    "name:gan_x_preferred":[
        "\u78a7\u6c5f\u533a"
    ],
    "name:jpn_x_preferred":[
        "\u78a7\u6c5f\u533a"
    ],
    "name:kor_x_preferred":[
        "\ube44\uc7a5\uad6c"
    ],
    "name:nan_x_preferred":[
        "Phek-kang-khu"
    ],
    "name:nld_x_preferred":[
        "Bijiang"
    ],
    "name:pam_x_preferred":[
        "Bijiang Distritu"
    ],
    "name:pnb_x_preferred":[
        "\u062a\u0648\u0646\u06af\u0631\u06cc\u0646"
    ],
    "name:spa_x_preferred":[
        "Bijiang"
    ],
    "name:swe_x_preferred":[
        "Bijiang"
    ],
    "name:und_x_variant":[
        "T\u2019ung-jen Hsien"
    ],
    "name:vie_x_preferred":[
        "B\u00edch Giang"
    ],
    "name:war_x_preferred":[
        "Tongren"
    ],
    "name:wuu_x_preferred":[
        "\u78a7\u6c5f\u533a"
    ],
    "name:zho_x_preferred":[
        "\u94dc\u4ec1\u5e02"
    ],
    "name:zho_x_variant":[
        "\u94dc\u4ec1",
        "\u78a7\u6c5f\u533a"
    ],
    "qs:name":"\u94dc\u4ec1\u5e02",
    "qs:name_adm0":"\u4e2d\u570b",
    "qs:name_adm1":"\u8d35\u5dde\u7701",
    "qs:photos":286,
    "qs:photos_1k":58,
    "qs:photos_9k":1,
    "qs:photos_9r":5,
    "qs:photos_all":322,
    "qs:photos_sr":5,
    "qs:placetype":"LocalAdmin",
    "qs:pop_sr":"0",
    "wd:wordcount":125,
    "wof:name":"\u94dc\u4ec1\u5e02",
    "wof:placetype":"localadmin",
    "wof:population":0
},
  "geometry": {"coordinates":[109.12045000000001,27.68707],"type":"Point"}
}