{
  "type": "Feature",
  "properties": {
    "gn:admin1_code":"4.0",
    "gn:asciiname":"Fanjia'nong",
    "gn:country_code":"CN",
    "gn:dem":5,
    "gn:feature_class":"P",
    "gn:feature_code":"PPL",
    "gn:name":"Fanjia\u2019nong",
    "gn:population":0,
    "gn:timezone":"Asia/Shanghai",
    "iso:country":"CN",
    "name:und_x_variant":[
        "Fanjia\u2019nong"
    ],
    "name:zho_x_preferred":[
        "\u8303\u5bb6\u5f04"
    ],
    "wof:name":"Fanjia'nong",
    "wof:placetype":"locality"
},
  "geometry": {"coordinates":[120.25857000000001,32.05672],"type":"Point"}
}