{
  "type": "Feature",
  "properties": {
    "gn:admin1_code":"11.0",
    "gn:asciiname":"Qinjiayao",
    "gn:country_code":"CN",
    "gn:dem":70,
    "gn:feature_class":"P",
    "gn:feature_code":"PPL",
    "gn:name":"Qinjiayao",
    "gn:population":0,
    "gn:timezone":"Asia/Shanghai",
    "iso:country":"CN",
    "name:zho_x_preferred":[
        "Qinjiayao"
    ],
    "name:zho_x_variant":[
        "\u79e6\u5bb6\u7a91"
    ],
    "wof:name":"Qinjiayao",
    "wof:placetype":"locality"
},
  "geometry": {"coordinates":[111.45811,29.086],"type":"Point"}
}