{
  "type": "Feature",
  "properties": {
    "gn:admin1_code":"29.0",
    "gn:asciiname":"Dipang",
    "gn:country_code":"CN",
    "gn:dem":2044,
    "gn:feature_class":"P",
    "gn:feature_code":"PPL",
    "gn:name":"Dipang",
    "gn:population":0,
    "gn:timezone":"Asia/Shanghai",
    "iso:country":"CN",
    "name:zho_x_preferred":[
        "\u5730\u65c1"
    ],
    "wof:name":"Dipang",
    "wof:placetype":"locality"
},
  "geometry": {"coordinates":[99.3944,25.8058],"type":"Point"}
}