{
  "type": "Feature",
  "properties": {
    "gn:admin1_code":"10",
    "gn:asciiname":"Huaizhuang",
    "gn:country_code":"CN",
    "gn:dem":69,
    "gn:feature_class":"P",
    "gn:feature_code":"PPL",
    "gn:name":"Huaizhuang",
    "gn:population":0,
    "gn:timezone":"Asia/Shanghai",
    "iso:country":"CN",
    "name:zho_x_preferred":[
        "\u6dee\u5e84"
    ],
    "wof:name":"Huaizhuang",
    "wof:placetype":"locality"
},
  "geometry": {"coordinates":[114.482,36.9054],"type":"Point"}
}