{
  "type": "Feature",
  "properties": {
    "gn:admin1_code":"3.0",
    "gn:asciiname":"Shang'an",
    "gn:country_code":"CN",
    "gn:dem":281,
    "gn:feature_class":"P",
    "gn:feature_code":"PPL",
    "gn:name":"Shang\u2019an",
    "gn:population":0,
    "gn:timezone":"Asia/Shanghai",
    "iso:country":"CN",
    "name:und_x_variant":[
        "Shang\u2019an",
        "\u4e0a\u6848"
    ],
    "wof:name":"Shang'an",
    "wof:placetype":"locality"
},
  "geometry": {"coordinates":[116.3342,26.26962],"type":"Point"}
}