{
  "type": "Feature",
  "properties": {
    "gn:admin1_code":"19.0",
    "gn:asciiname":"Beiguangfu Yingzi",
    "gn:country_code":"CN",
    "gn:dem":275,
    "gn:feature_class":"P",
    "gn:feature_code":"PPL",
    "gn:name":"Beiguangfu Yingzi",
    "gn:population":0,
    "gn:timezone":"Asia/Shanghai",
    "iso:country":"CN",
    "name:und_x_variant":[
        "\u5317\u5e7f\u5bcc\u8425\u5b50"
    ],
    "name:zho_x_preferred":[
        "\u5317\u5e7f\u5bcc\u8425\u5b50"
    ],
    "wof:name":"Beiguangfu Yingzi",
    "wof:placetype":"locality"
},
  "geometry": {"coordinates":[120.88491999999999,42.19539],"type":"Point"}
}