{
  "type": "Feature",
  "properties": {
    "gn:admin1_code":"16.0",
    "gn:asciiname":"Longjia",
    "gn:country_code":"CN",
    "gn:dem":603,
    "gn:feature_class":"P",
    "gn:feature_code":"PPL",
    "gn:name":"Longjia",
    "gn:population":0,
    "gn:timezone":"Asia/Shanghai",
    "iso:country":"CN",
    "name:deu_x_preferred":[
        "Longjia"
    ],
    "name:zho_x_preferred":[
        "\u9f99\u7532"
    ],
    "wof:name":"Longjia",
    "wof:placetype":"locality"
},
  "geometry": {"coordinates":[107.119,24.1532],"type":"Point"}
}