{
  "type": "Feature",
  "properties": {
    "gn:admin1_code":"16.0",
    "gn:asciiname":"Xinfu",
    "gn:country_code":"CN",
    "gn:dem":147,
    "gn:feature_class":"P",
    "gn:feature_code":"PPL",
    "gn:name":"Xinfu",
    "gn:population":0,
    "gn:timezone":"Asia/Shanghai",
    "iso:country":"CN",
    "name:ceb_x_preferred":[
        "Xinfu"
    ],
    "name:deu_x_preferred":[
        "Xinfu"
    ],
    "name:fra_x_preferred":[
        "Xinfu"
    ],
    "name:kor_x_preferred":[
        "\uc2e0\ud478\uad6c"
    ],
    "name:nor_x_preferred":[
        "Xinfu"
    ],
    "name:rus_x_preferred":[
        "\u0421\u0438\u043d\u044c\u0444\u0443"
    ],
    "name:swe_x_preferred":[
        "Xinfu"
    ],
    "name:zho_x_preferred":[
        "\u65b0\u752b"
    ],
    "wof:name":"Xinfu",
    "wof:placetype":"locality"
},
  "geometry": {"coordinates":[108.827,24.5743],"type":"Point"}
}