{
  "type": "Feature",
  "properties": {
    "gn:admin1_code":"15.0",
    "gn:asciiname":"Xiaobaozi",
    "gn:country_code":"CN",
    "gn:dem":1917,
    "gn:feature_class":"P",
    "gn:feature_code":"PPL",
    "gn:name":"Xiaobaozi",
    "gn:population":0,
    "gn:timezone":"Asia/Shanghai",
    "iso:country":"CN",
    "name:zho_x_preferred":[
        "\u5c0f\u5821\u5b50"
    ],
    "wof:name":"Xiaobaozi",
    "wof:placetype":"locality"
},
  "geometry": {"coordinates":[104.34193999999999,34.02826],"type":"Point"}
}