{
  "type": "Feature",
  "properties": {
    "gn:admin1_code":"16.0",
    "gn:asciiname":"Ganhong",
    "gn:country_code":"CN",
    "gn:dem":512,
    "gn:feature_class":"P",
    "gn:feature_code":"PPL",
    "gn:name":"Ganhong",
    "gn:population":0,
    "gn:timezone":"Asia/Shanghai",
    "iso:country":"CN",
    "name:zho_x_preferred":[
        "\u6562\u7ea2"
    ],
    "wof:name":"Ganhong",
    "wof:placetype":"locality"
},
  "geometry": {"coordinates":[108.468,23.8291],"type":"Point"}
}