{
  "type": "Feature",
  "properties": {
    "gn:admin1_code":"24.0",
    "gn:asciiname":"Shenshanyan",
    "gn:country_code":"CN",
    "gn:dem":1993,
    "gn:feature_class":"P",
    "gn:feature_code":"PPL",
    "gn:name":"Shenshanyan",
    "gn:population":0,
    "gn:timezone":"Asia/Shanghai",
    "iso:country":"CN",
    "name:zho_x_preferred":[
        "\u6df1\u5c71\u5895"
    ],
    "wof:name":"Shenshanyan",
    "wof:placetype":"locality"
},
  "geometry": {"coordinates":[111.82229,38.76817],"type":"Point"}
}