{
  "type": "Feature",
  "properties": {
    "gn:admin1_code":"3.0",
    "gn:asciiname":"Lihuadian",
    "gn:country_code":"CN",
    "gn:dem":31,
    "gn:feature_class":"P",
    "gn:feature_code":"PPL",
    "gn:name":"Lihuadian",
    "gn:population":0,
    "gn:timezone":"Asia/Shanghai",
    "iso:country":"CN",
    "name:und_x_variant":[
        "\u674e\u82b1\u5e97"
    ],
    "wof:name":"Lihuadian",
    "wof:placetype":"locality"
},
  "geometry": {"coordinates":[115.36404,28.0134],"type":"Point"}
}