{
  "type": "Feature",
  "properties": {
    "gn:admin1_code":"29.0",
    "gn:asciiname":"Tianfang",
    "gn:country_code":"CN",
    "gn:dem":1733,
    "gn:feature_class":"P",
    "gn:feature_code":"PPL",
    "gn:name":"Tianfang",
    "gn:population":0,
    "gn:timezone":"Asia/Shanghai",
    "iso:country":"CN",
    "name:zho_x_preferred":[
        "\u7530\u623f"
    ],
    "wof:name":"Tianfang",
    "wof:placetype":"locality"
},
  "geometry": {"coordinates":[100.702,26.1116],"type":"Point"}
}