{
  "type": "Feature",
  "properties": {
    "gn:admin1_code":"3.0",
    "gn:asciiname":"Jingzikou",
    "gn:country_code":"CN",
    "gn:dem":323,
    "gn:feature_class":"P",
    "gn:feature_code":"PPL",
    "gn:name":"Jingzikou",
    "gn:population":0,
    "gn:timezone":"Asia/Shanghai",
    "iso:country":"CN",
    "name:und_x_variant":[
        "\u5f84\u5b50\u53e3"
    ],
    "wof:name":"Jingzikou",
    "wof:placetype":"locality"
},
  "geometry": {"coordinates":[115.57057,26.3557],"type":"Point"}
}