{
  "type": "Feature",
  "properties": {
    "gn:admin1_code":"11",
    "gn:asciiname":"Yankoudong",
    "gn:country_code":"CN",
    "gn:dem":275,
    "gn:feature_class":"P",
    "gn:feature_code":"PPL",
    "gn:name":"Yankoudong",
    "gn:population":0,
    "gn:timezone":"Asia/Shanghai",
    "iso:country":"CN",
    "name:zho_x_preferred":[
        "\u5ca9\u53e3\u6d1e"
    ],
    "wof:name":"Yankoudong",
    "wof:placetype":"locality"
},
  "geometry": {"coordinates":[112.22835000000001,25.44068],"type":"Point"}
}