{
  "type": "Feature",
  "properties": {
    "gn:admin1_code":"12.0",
    "gn:asciiname":"Wangpotan",
    "gn:country_code":"CN",
    "gn:dem":35,
    "gn:feature_class":"P",
    "gn:feature_code":"PPL",
    "gn:name":"Wangpotan",
    "gn:population":0,
    "gn:timezone":"Asia/Shanghai",
    "iso:country":"CN",
    "name:zho_x_preferred":[
        "\u738b\u5a46\u6f6d"
    ],
    "wof:name":"Wangpotan",
    "wof:placetype":"locality"
},
  "geometry": {"coordinates":[112.42567,29.80725],"type":"Point"}
}