{
  "type": "Feature",
  "properties": {
    "gn:admin1_code":"15.0",
    "gn:asciiname":"Gaolouyuan",
    "gn:country_code":"CN",
    "gn:dem":1448,
    "gn:feature_class":"P",
    "gn:feature_code":"PPL",
    "gn:name":"Gaolouyuan",
    "gn:population":0,
    "gn:timezone":"Asia/Shanghai",
    "iso:country":"CN",
    "name:und_x_variant":[
        "\u9ad8\u697c\u586c"
    ],
    "wof:name":"Gaolouyuan",
    "wof:placetype":"locality"
},
  "geometry": {"coordinates":[107.48658,36.40618],"type":"Point"}
}