{
  "type": "Feature",
  "properties": {
    "gn:admin1_code":"5.0",
    "gn:asciiname":"Majia Wopeng",
    "gn:country_code":"CN",
    "gn:dem":132,
    "gn:feature_class":"P",
    "gn:feature_code":"PPL",
    "gn:name":"Majia Wopeng",
    "gn:population":0,
    "gn:timezone":"Asia/Shanghai",
    "iso:country":"CN",
    "name:zho_x_preferred":[
        "\u9a6c\u5bb6\u7a9d\u68da"
    ],
    "wof:name":"Majia Wopeng",
    "wof:placetype":"locality"
},
  "geometry": {"coordinates":[123.86693,45.26654],"type":"Point"}
}