{
  "type": "Feature",
  "properties": {
    "gn:admin1_code":"15",
    "gn:asciiname":"Dongri",
    "gn:country_code":"CN",
    "gn:dem":1313,
    "gn:feature_class":"P",
    "gn:feature_code":"PPL",
    "gn:name":"Dongri",
    "gn:population":0,
    "gn:timezone":"Asia/Shanghai",
    "iso:country":"CN",
    "name:jpn_x_preferred":[
        "\u30c9\u30f3\u30b0\u30ea"
    ],
    "name:vie_x_preferred":[
        "Dongri"
    ],
    "wof:name":"Dongri",
    "wof:placetype":"locality"
},
  "geometry": {"coordinates":[103.74694,38.98278],"type":"Point"}
}