{
  "type": "Feature",
  "properties": {
    "gn:admin1_code":"12.0",
    "gn:asciiname":"Daxiwan",
    "gn:country_code":"CN",
    "gn:dem":123,
    "gn:feature_class":"P",
    "gn:feature_code":"PPL",
    "gn:name":"Daxiwan",
    "gn:population":0,
    "gn:timezone":"Asia/Shanghai",
    "iso:country":"CN",
    "name:zho_x_preferred":[
        "\u5927\u897f\u6e7e"
    ],
    "wof:name":"Daxiwan",
    "wof:placetype":"locality"
},
  "geometry": {"coordinates":[112.48090999999999,32.00825],"type":"Point"}
}