{
  "type": "Feature",
  "properties": {
    "gn:admin1_code":"1.0",
    "gn:asciiname":"Shuanghekou",
    "gn:country_code":"CN",
    "gn:dem":431,
    "gn:feature_class":"P",
    "gn:feature_code":"PPL",
    "gn:name":"Shuanghekou",
    "gn:population":0,
    "gn:timezone":"Asia/Shanghai",
    "iso:country":"CN",
    "name:und_x_variant":[
        "\u53cc\u6cb3\u53e3"
    ],
    "wof:name":"Shuanghekou",
    "wof:placetype":"locality"
},
  "geometry": {"coordinates":[118.8511,30.60849],"type":"Point"}
}