{
  "type": "Feature",
  "properties": {
    "gn:admin1_code":"3.0",
    "gn:asciiname":"Baishuiji",
    "gn:country_code":"CN",
    "gn:dem":379,
    "gn:feature_class":"P",
    "gn:feature_code":"PPL",
    "gn:name":"Baishuiji",
    "gn:population":0,
    "gn:timezone":"Asia/Shanghai",
    "iso:country":"CN",
    "name:und_x_variant":[
        "\u767d\u6c34\u9645"
    ],
    "wof:name":"Baishuiji",
    "wof:placetype":"locality"
},
  "geometry": {"coordinates":[116.93024,27.65026],"type":"Point"}
}