{
  "type": "Feature",
  "properties": {
    "gn:admin1_code":"4.0",
    "gn:asciiname":"Xinsha'erxu",
    "gn:country_code":"CN",
    "gn:dem":2,
    "gn:feature_class":"P",
    "gn:feature_code":"PPL",
    "gn:name":"Xinsha\u2019erxu",
    "gn:population":0,
    "gn:timezone":"Asia/Shanghai",
    "iso:country":"CN",
    "name:und_x_variant":[
        "\u65b0\u6c99\u4e8c\u5729"
    ],
    "name:zho_x_preferred":[
        "Xinsha\u2019erxu"
    ],
    "name:zho_x_variant":[
        "\u65b0\u6c99\u4e8c\u5729"
    ],
    "wof:name":"Xinsha'erxu",
    "wof:placetype":"locality"
},
  "geometry": {"coordinates":[120.72815,31.843],"type":"Point"}
}