{
  "type": "Feature",
  "properties": {
    "gn:admin1_code":"10.0",
    "gn:asciiname":"Qiubudong",
    "gn:country_code":"CN",
    "gn:dem":880,
    "gn:feature_class":"P",
    "gn:feature_code":"PPL",
    "gn:name":"Qiubudong",
    "gn:population":0,
    "gn:timezone":"Asia/Shanghai",
    "iso:country":"CN",
    "name:zho_x_preferred":[
        "\u79cb\u535c\u6d1e"
    ],
    "wof:name":"Qiubudong",
    "wof:placetype":"locality"
},
  "geometry": {"coordinates":[113.84748999999999,38.61659],"type":"Point"}
}