{
  "type": "Feature",
  "properties": {
    "gn:admin1_code":"08",
    "gn:asciiname":"Qianfeng Nongchang Si Dui",
    "gn:country_code":"CN",
    "gn:dem":55,
    "gn:feature_class":"P",
    "gn:feature_code":"PPL",
    "gn:name":"Qianfeng Nongchang Si Dui",
    "gn:population":0,
    "gn:timezone":"Asia/Shanghai",
    "iso:country":"CN",
    "wof:name":"Qianfeng Nongchang Si Dui",
    "wof:placetype":"locality"
},
  "geometry": {"coordinates":[133.86000000000001,47.75083],"type":"Point"}
}