{
  "type": "Feature",
  "properties": {
    "gn:admin1_code":"12.0",
    "gn:asciiname":"Kechengjia",
    "gn:country_code":"CN",
    "gn:dem":40,
    "gn:feature_class":"P",
    "gn:feature_code":"PPL",
    "gn:name":"Kechengjia",
    "gn:population":0,
    "gn:timezone":"Asia/Shanghai",
    "iso:country":"CN",
    "name:und_x_variant":[
        "\u67ef\u7a0b\u5bb6"
    ],
    "wof:name":"Kechengjia",
    "wof:placetype":"locality"
},
  "geometry": {"coordinates":[114.95392,30.06162],"type":"Point"}
}