{
  "type": "Feature",
  "properties": {
    "gn:admin1_code":"14.0",
    "gn:asciiname":"Maxi",
    "gn:country_code":"CN",
    "gn:dem":4464,
    "gn:feature_class":"P",
    "gn:feature_code":"PPL",
    "gn:name":"Maxi",
    "gn:population":0,
    "gn:timezone":"Asia/Urumqi",
    "iso:country":"CN",
    "name:deu_x_preferred":[
        "Maxi"
    ],
    "name:fra_x_preferred":[
        "Maxi"
    ],
    "name:ita_x_preferred":[
        "Maxi"
    ],
    "name:spa_x_preferred":[
        "Maxi"
    ],
    "name:swe_x_preferred":[
        "Maxi"
    ],
    "name:zho_x_preferred":[
        "\u739b\u559c"
    ],
    "wof:name":"Maxi",
    "wof:placetype":"locality"
},
  "geometry": {"coordinates":[94.58123000000001,29.63802],"type":"Point"}
}