{
  "type": "Feature",
  "properties": {
    "gn:admin1_code":"11.0",
    "gn:asciiname":"Zhaibeilong",
    "gn:country_code":"CN",
    "gn:dem":559,
    "gn:feature_class":"P",
    "gn:feature_code":"PPL",
    "gn:name":"Zhaibeilong",
    "gn:population":0,
    "gn:timezone":"Asia/Shanghai",
    "iso:country":"CN",
    "name:zho_x_preferred":[
        "\u5be8\u80cc\u5785"
    ],
    "wof:name":"Zhaibeilong",
    "wof:placetype":"locality"
},
  "geometry": {"coordinates":[113.51157000000001,25.72949],"type":"Point"}
}