{
  "type": "Feature",
  "properties": {
    "gn:admin1_code":"12.0",
    "gn:asciiname":"Waxuedi",
    "gn:country_code":"CN",
    "gn:dem":57,
    "gn:feature_class":"P",
    "gn:feature_code":"PPL",
    "gn:name":"Waxuedi",
    "gn:population":0,
    "gn:timezone":"Asia/Shanghai",
    "iso:country":"CN",
    "name:zho_x_preferred":[
        "Waxuedi"
    ],
    "name:zho_x_variant":[
        "\u74e6\u96ea\u5730"
    ],
    "wof:name":"Waxuedi",
    "wof:placetype":"locality"
},
  "geometry": {"coordinates":[114.66896,29.96805],"type":"Point"}
}