{
  "type": "Feature",
  "properties": {
    "gn:admin1_code":"25.0",
    "gn:asciiname":"Xiaomagezhuang",
    "gn:country_code":"CN",
    "gn:dem":102,
    "gn:feature_class":"P",
    "gn:feature_code":"PPL",
    "gn:name":"Xiaomagezhuang",
    "gn:population":0,
    "gn:timezone":"Asia/Shanghai",
    "iso:country":"CN",
    "name:zho_x_preferred":[
        "\u5c0f\u9a6c\u683c\u5e84"
    ],
    "wof:name":"Xiaomagezhuang",
    "wof:placetype":"locality"
},
  "geometry": {"coordinates":[120.59598,36.84324],"type":"Point"}
}