{
  "type": "Feature",
  "properties": {
    "gn:admin1_code":"30.0",
    "gn:asciiname":"Tanzu",
    "gn:country_code":"CN",
    "gn:dem":541,
    "gn:feature_class":"P",
    "gn:feature_code":"PPL",
    "gn:name":"Tanzu",
    "gn:population":0,
    "gn:timezone":"Asia/Shanghai",
    "iso:country":"CN",
    "name:zho_x_preferred":[
        "Tanzu"
    ],
    "name:zho_x_variant":[
        "\u575b\u7956"
    ],
    "wof:name":"Tanzu",
    "wof:placetype":"locality"
},
  "geometry": {"coordinates":[113.21778,25.47],"type":"Point"}
}