{
  "type": "Feature",
  "properties": {
    "gn:admin1_code":"3.0",
    "gn:asciiname":"Zhehu",
    "gn:country_code":"CN",
    "gn:dem":17,
    "gn:feature_class":"P",
    "gn:feature_code":"PPL",
    "gn:name":"Zhehu",
    "gn:population":0,
    "gn:timezone":"Asia/Shanghai",
    "iso:country":"CN",
    "name:und_x_variant":[
        "\u8517\u6e56"
    ],
    "wof:name":"Zhehu",
    "wof:placetype":"locality"
},
  "geometry": {"coordinates":[116.46075,28.67002],"type":"Point"}
}