{
  "type": "Feature",
  "properties": {
    "gn:admin1_code":"05",
    "gn:asciiname":"Laoling Linchang",
    "gn:country_code":"CN",
    "gn:dem":944,
    "gn:feature_class":"P",
    "gn:feature_code":"PPLF",
    "gn:name":"Laoling Linchang",
    "gn:population":0,
    "gn:timezone":"Asia/Shanghai",
    "iso:country":"CN",
    "name:und_x_variant":[
        "\u8001\u5cad\u6797\u573a"
    ],
    "wof:name":"Laoling Linchang",
    "wof:placetype":"locality"
},
  "geometry": {"coordinates":[127.70623999999999,41.8991],"type":"Point"}
}