{
  "type": "Feature",
  "properties": {
    "gn:admin1_code":"7",
    "gn:asciiname":"Xiashuizai",
    "gn:country_code":"CN",
    "gn:dem":346,
    "gn:feature_class":"P",
    "gn:feature_code":"PPL",
    "gn:name":"Xiashuizai",
    "gn:population":0,
    "gn:timezone":"Asia/Shanghai",
    "iso:country":"CN",
    "name:zho_x_preferred":[
        "\u4e0b\u6c34\u4ed4"
    ],
    "wof:name":"Xiashuizai",
    "wof:placetype":"locality"
},
  "geometry": {"coordinates":[117.02643999999999,24.27783],"type":"Point"}
}