{
  "type": "Feature",
  "properties": {
    "gn:admin1_code":"3.0",
    "gn:asciiname":"Mijia",
    "gn:country_code":"CN",
    "gn:dem":58,
    "gn:feature_class":"P",
    "gn:feature_code":"PPL",
    "gn:name":"Mijia",
    "gn:population":0,
    "gn:timezone":"Asia/Shanghai",
    "iso:country":"CN",
    "name:und_x_variant":[
        "\u7c73\u5bb6"
    ],
    "wof:name":"Mijia",
    "wof:placetype":"locality"
},
  "geometry": {"coordinates":[116.70474,27.75257],"type":"Point"}
}