{
  "type": "Feature",
  "properties": {
    "gn:admin1_code":"9.0",
    "gn:asciiname":"Songzhuang",
    "gn:country_code":"CN",
    "gn:dem":392,
    "gn:feature_class":"P",
    "gn:feature_code":"PPL",
    "gn:name":"Songzhuang",
    "gn:population":0,
    "gn:timezone":"Asia/Shanghai",
    "iso:country":"CN",
    "name:zho_x_preferred":[
        "\u5b8b\u5e84"
    ],
    "wof:name":"Songzhuang",
    "wof:placetype":"locality"
},
  "geometry": {"coordinates":[111.26288999999998,33.35562],"type":"Point"}
}