{
  "type": "Feature",
  "properties": {
    "gn:admin1_code":"16.0",
    "gn:asciiname":"Fenguangda",
    "gn:country_code":"CN",
    "gn:dem":548,
    "gn:feature_class":"P",
    "gn:feature_code":"PPL",
    "gn:name":"Fenguangda",
    "gn:population":0,
    "gn:timezone":"Asia/Shanghai",
    "iso:country":"CN",
    "name:zho_x_preferred":[
        "\u575f\u5e7f\u8fbe"
    ],
    "wof:name":"Fenguangda",
    "wof:placetype":"locality"
},
  "geometry": {"coordinates":[106.79600000000001,22.197],"type":"Point"}
}