{
  "type": "Feature",
  "properties": {
    "gn:admin1_code":"11.0",
    "gn:asciiname":"Xiangjia",
    "gn:country_code":"CN",
    "gn:dem":432,
    "gn:feature_class":"P",
    "gn:feature_code":"PPL",
    "gn:name":"Xiangjia",
    "gn:population":0,
    "gn:timezone":"Asia/Shanghai",
    "iso:country":"CN",
    "name:zho_x_preferred":[
        "\u5411\u5bb6"
    ],
    "wof:name":"Xiangjia",
    "wof:placetype":"locality"
},
  "geometry": {"coordinates":[109.86887,29.10468],"type":"Point"}
}