{
  "type": "Feature",
  "properties": {
    "gn:admin1_code":"25.0",
    "gn:asciiname":"Yuejiadianzicun",
    "gn:country_code":"CN",
    "gn:dem":72,
    "gn:feature_class":"P",
    "gn:feature_code":"PPL",
    "gn:name":"Yuejiadianzicun",
    "gn:population":0,
    "gn:timezone":"Asia/Shanghai",
    "iso:country":"CN",
    "name:zho_x_preferred":[
        "\u5cb3\u5bb6\u5e97\u5b50\u6751"
    ],
    "wof:name":"Yuejiadianzicun",
    "wof:placetype":"locality"
},
  "geometry": {"coordinates":[119.28668,36.35969],"type":"Point"}
}