{
  "type": "Feature",
  "properties": {
    "gn:admin1_code":"25",
    "gn:asciiname":"Dashizhuang",
    "gn:country_code":"CN",
    "gn:dem":53,
    "gn:feature_class":"P",
    "gn:feature_code":"PPL",
    "gn:name":"Dashizhuang",
    "gn:population":0,
    "gn:timezone":"Asia/Shanghai",
    "iso:country":"CN",
    "name:zho_x_preferred":[
        "\u5927\u5e02\u5e84"
    ],
    "wof:name":"Dashizhuang",
    "wof:placetype":"locality"
},
  "geometry": {"coordinates":[117.017,35.1264],"type":"Point"}
}