{
  "type": "Feature",
  "properties": {
    "gn:admin1_code":"19.0",
    "gn:asciiname":"Beidadianzi",
    "gn:country_code":"CN",
    "gn:dem":24,
    "gn:feature_class":"P",
    "gn:feature_code":"PPL",
    "gn:name":"Beidadianzi",
    "gn:population":0,
    "gn:timezone":"Asia/Shanghai",
    "iso:country":"CN",
    "name:zho_x_preferred":[
        "\u5317\u5927\u7538\u5b50"
    ],
    "wof:name":"Beidadianzi",
    "wof:placetype":"locality"
},
  "geometry": {"coordinates":[120.11574,40.17197],"type":"Point"}
}