{
  "type": "Feature",
  "properties": {
    "gn:admin1_code":"24.0",
    "gn:asciiname":"Louziba",
    "gn:country_code":"CN",
    "gn:dem":1088,
    "gn:feature_class":"P",
    "gn:feature_code":"PPL",
    "gn:name":"Louziba",
    "gn:population":0,
    "gn:timezone":"Asia/Shanghai",
    "iso:country":"CN",
    "name:und_x_variant":[
        "\u697c\u5b50\u575d"
    ],
    "wof:name":"Louziba",
    "wof:placetype":"locality"
},
  "geometry": {"coordinates":[112.59872,39.18373],"type":"Point"}
}