{
  "type": "Feature",
  "properties": {
    "gn:admin1_code":"2.0",
    "gn:asciiname":"Moyin",
    "gn:country_code":"CN",
    "gn:dem":581,
    "gn:feature_class":"P",
    "gn:feature_code":"PPL",
    "gn:name":"Moyin",
    "gn:population":0,
    "gn:timezone":"Asia/Shanghai",
    "iso:country":"CN",
    "name:zho_x_preferred":[
        "\u58a8\u5370"
    ],
    "wof:name":"Moyin",
    "wof:placetype":"locality"
},
  "geometry": {"coordinates":[120.42832,28.37567],"type":"Point"}
}