{
  "type": "Feature",
  "properties": {
    "gn:admin1_code":"3.0",
    "gn:asciiname":"Xiahekeng",
    "gn:country_code":"CN",
    "gn:dem":255,
    "gn:feature_class":"P",
    "gn:feature_code":"PPL",
    "gn:name":"Xiahekeng",
    "gn:population":0,
    "gn:timezone":"Asia/Shanghai",
    "iso:country":"CN",
    "name:und_x_variant":[
        "\u4e0b\u6cb3\u5751"
    ],
    "wof:name":"Xiahekeng",
    "wof:placetype":"locality"
},
  "geometry": {"coordinates":[116.37069,26.19412],"type":"Point"}
}