{
  "type": "Feature",
  "properties": {
    "gn:admin1_code":"15.0",
    "gn:asciiname":"Houduipo",
    "gn:country_code":"CN",
    "gn:dem":1284,
    "gn:feature_class":"P",
    "gn:feature_code":"PPL",
    "gn:name":"Houduipo",
    "gn:population":0,
    "gn:timezone":"Asia/Shanghai",
    "iso:country":"CN",
    "name:zho_x_preferred":[
        "\u540e\u5bf9\u5761"
    ],
    "wof:name":"Houduipo",
    "wof:placetype":"locality"
},
  "geometry": {"coordinates":[107.379,35.1718],"type":"Point"}
}