{
  "type": "Feature",
  "properties": {
    "gn:admin1_code":"08",
    "gn:asciiname":"Ch'ien-ta-kang-tzu",
    "gn:country_code":"CN",
    "gn:dem":160,
    "gn:feature_class":"P",
    "gn:feature_code":"PPL",
    "gn:name":"Ch\u2019ien-ta-kang-tzu",
    "gn:population":0,
    "gn:timezone":"Asia/Shanghai",
    "iso:country":"CN",
    "wof:name":"Ch'ien-ta-kang-tzu",
    "wof:placetype":"locality"
},
  "geometry": {"coordinates":[124.145,47.82306],"type":"Point"}
}