{
  "type": "Feature",
  "properties": {
    "gn:admin1_code":"32.0",
    "gn:asciiname":"Biji",
    "gn:country_code":"CN",
    "gn:dem":3019,
    "gn:feature_class":"P",
    "gn:feature_code":"PPL",
    "gn:name":"Biji",
    "gn:population":0,
    "gn:timezone":"Asia/Shanghai",
    "iso:country":"CN",
    "name:zho_x_preferred":[
        "\u78a7\u57fa"
    ],
    "wof:name":"Biji",
    "wof:placetype":"locality"
},
  "geometry": {"coordinates":[100.992,27.6509],"type":"Point"}
}