{
  "type": "Feature",
  "properties": {
    "gn:admin1_code":"3.0",
    "gn:asciiname":"Xiaofanghu",
    "gn:country_code":"CN",
    "gn:dem":18,
    "gn:feature_class":"P",
    "gn:feature_code":"PPL",
    "gn:name":"Xiaofanghu",
    "gn:population":0,
    "gn:timezone":"Asia/Shanghai",
    "iso:country":"CN",
    "name:und_x_variant":[
        "\u5c0f\u623f\u80e1"
    ],
    "wof:name":"Xiaofanghu",
    "wof:placetype":"locality"
},
  "geometry": {"coordinates":[115.87832,29.03962000000001],"type":"Point"}
}