{
  "type": "Feature",
  "properties": {
    "gn:admin1_code":"11",
    "gn:asciiname":"Wanfuling",
    "gn:country_code":"CN",
    "gn:dem":144,
    "gn:feature_class":"P",
    "gn:feature_code":"PPL",
    "gn:name":"Wanfuling",
    "gn:population":0,
    "gn:timezone":"Asia/Shanghai",
    "iso:country":"CN",
    "name:zho_x_preferred":[
        "\u4e07\u798f\u5cad"
    ],
    "wof:name":"Wanfuling",
    "wof:placetype":"locality"
},
  "geometry": {"coordinates":[111.89422999999999,26.79772],"type":"Point"}
}