{
  "type": "Feature",
  "properties": {
    "gn:admin1_code":"26.0",
    "gn:asciiname":"Lizipingcun",
    "gn:country_code":"CN",
    "gn:dem":1218,
    "gn:feature_class":"P",
    "gn:feature_code":"PPL",
    "gn:name":"Lizipingcun",
    "gn:population":0,
    "gn:timezone":"Asia/Shanghai",
    "iso:country":"CN",
    "name:und_x_variant":[
        "\u68a8\u5b50\u576a\u6751"
    ],
    "wof:name":"Lizipingcun",
    "wof:placetype":"locality"
},
  "geometry": {"coordinates":[107.28686,33.4103],"type":"Point"}
}