{
  "type": "Feature",
  "properties": {
    "gn:admin1_code":"16.0",
    "gn:asciiname":"Wuhe",
    "gn:country_code":"CN",
    "gn:dem":96,
    "gn:feature_class":"P",
    "gn:feature_code":"PPL",
    "gn:name":"Wuhe",
    "gn:population":0,
    "gn:timezone":"Asia/Shanghai",
    "iso:country":"CN",
    "name:ceb_x_preferred":[
        "Wuhe"
    ],
    "name:deu_x_preferred":[
        "Wuhe"
    ],
    "name:zho_x_preferred":[
        "\u4e94\u5408"
    ],
    "wof:name":"Wuhe",
    "wof:placetype":"locality"
},
  "geometry": {"coordinates":[108.527,22.8193],"type":"Point"}
}