{
  "type": "Feature",
  "properties": {
    "gn:admin1_code":"18",
    "gn:asciiname":"Tongziyuan",
    "gn:country_code":"CN",
    "gn:dem":890,
    "gn:feature_class":"P",
    "gn:feature_code":"PPL",
    "gn:name":"Tongziyuan",
    "gn:population":0,
    "gn:timezone":"Asia/Shanghai",
    "iso:country":"CN",
    "name:zho_x_preferred":[
        "\u6850\u5b50\u56ed"
    ],
    "wof:name":"Tongziyuan",
    "wof:placetype":"locality"
},
  "geometry": {"coordinates":[107.002,27.296],"type":"Point"}
}