{
  "type": "Feature",
  "properties": {
    "gn:admin1_code":"19.0",
    "gn:asciiname":"Guojia Zhangzi",
    "gn:country_code":"CN",
    "gn:dem":305,
    "gn:feature_class":"P",
    "gn:feature_code":"PPL",
    "gn:name":"Guojia Zhangzi",
    "gn:population":0,
    "gn:timezone":"Asia/Shanghai",
    "iso:country":"CN",
    "name:und_x_variant":[
        "\u90ed\u5bb6\u6756\u5b50"
    ],
    "name:zho_x_preferred":[
        "\u90ed\u5bb6\u6756\u5b50"
    ],
    "wof:name":"Guojia Zhangzi",
    "wof:placetype":"locality"
},
  "geometry": {"coordinates":[119.93600000000001,40.9272],"type":"Point"}
}