{
  "type": "Feature",
  "properties": {
    "gn:admin1_code":"14.0",
    "gn:asciiname":"Aluo",
    "gn:country_code":"CN",
    "gn:dem":3744,
    "gn:feature_class":"P",
    "gn:feature_code":"PPL",
    "gn:name":"Aluo",
    "gn:population":0,
    "gn:timezone":"Asia/Urumqi",
    "iso:country":"CN",
    "name:zho_x_preferred":[
        "\u554a\u7f57"
    ],
    "wof:name":"Aluo",
    "wof:placetype":"locality"
},
  "geometry": {"coordinates":[95.60457,30.79378],"type":"Point"}
}