{
  "type": "Feature",
  "properties": {
    "gn:admin1_code":"02",
    "gn:asciiname":"Panjiali",
    "gn:country_code":"CN",
    "gn:dem":10,
    "gn:feature_class":"P",
    "gn:feature_code":"PPL",
    "gn:name":"Panjiali",
    "gn:population":0,
    "gn:timezone":"Asia/Shanghai",
    "iso:country":"CN",
    "name:und_x_variant":[
        "P\u2019an-chia",
        "Panjiali"
    ],
    "wof:name":"Panjiali",
    "wof:placetype":"locality"
},
  "geometry": {"coordinates":[121.42289,28.67982],"type":"Point"}
}