{
  "type": "Feature",
  "properties": {
    "gn:admin1_code":"20.0",
    "gn:asciiname":"Quanzigou",
    "gn:country_code":"CN",
    "gn:dem":1764,
    "gn:feature_class":"P",
    "gn:feature_code":"PPL",
    "gn:name":"Quanzigou",
    "gn:population":0,
    "gn:timezone":"Asia/Shanghai",
    "iso:country":"CN",
    "name:und_x_variant":[
        "\u6cc9\u5b50\u6c9f"
    ],
    "wof:name":"Quanzigou",
    "wof:placetype":"locality"
},
  "geometry": {"coordinates":[110.67509,41.28605],"type":"Point"}
}