{
  "type": "Feature",
  "properties": {
    "gn:admin1_code":"32.0",
    "gn:asciiname":"Maidong",
    "gn:country_code":"CN",
    "gn:dem":3435,
    "gn:feature_class":"P",
    "gn:feature_code":"PPL",
    "gn:name":"Maidong",
    "gn:population":0,
    "gn:timezone":"Asia/Shanghai",
    "iso:country":"CN",
    "name:zho_x_preferred":[
        "\u9ea6\u51ac"
    ],
    "wof:name":"Maidong",
    "wof:placetype":"locality"
},
  "geometry": {"coordinates":[102.139,32.204],"type":"Point"}
}