{
  "type": "Feature",
  "properties": {
    "gn:admin1_code":"8.0",
    "gn:asciiname":"Xinancun",
    "gn:country_code":"CN",
    "gn:dem":164,
    "gn:feature_class":"P",
    "gn:feature_code":"PPL",
    "gn:name":"Xinancun",
    "gn:population":0,
    "gn:timezone":"Asia/Shanghai",
    "iso:country":"CN",
    "name:zho_x_preferred":[
        "\u897f\u5357\u6751"
    ],
    "wof:name":"Xinancun",
    "wof:placetype":"locality"
},
  "geometry": {"coordinates":[127.17619000000001,46.86506],"type":"Point"}
}