{
  "type": "Feature",
  "properties": {
    "gn:admin1_code":"29",
    "gn:asciiname":"Baichendi",
    "gn:country_code":"CN",
    "gn:dem":1201,
    "gn:feature_class":"P",
    "gn:feature_code":"PPL",
    "gn:name":"Baichendi",
    "gn:population":0,
    "gn:timezone":"Asia/Shanghai",
    "iso:country":"CN",
    "name:zho_x_preferred":[
        "\u767d\u8fb0\u5730"
    ],
    "wof:name":"Baichendi",
    "wof:placetype":"locality"
},
  "geometry": {"coordinates":[104.786,23.3314],"type":"Point"}
}