{
  "type": "Feature",
  "properties": {
    "gn:admin1_code":"7.0",
    "gn:asciiname":"Houpingdi",
    "gn:country_code":"CN",
    "gn:dem":450,
    "gn:feature_class":"P",
    "gn:feature_code":"PPL",
    "gn:name":"Houpingdi",
    "gn:population":0,
    "gn:timezone":"Asia/Shanghai",
    "iso:country":"CN",
    "name:zho_x_preferred":[
        "\u540e\u576a\u5e95"
    ],
    "wof:name":"Houpingdi",
    "wof:placetype":"locality"
},
  "geometry": {"coordinates":[118.47138,26.565],"type":"Point"}
}