{
  "type": "Feature",
  "properties": {
    "gn:admin1_code":"22.0",
    "gn:asciiname":"Xitiejiangyingcun",
    "gn:country_code":"CN",
    "gn:dem":47,
    "gn:feature_class":"P",
    "gn:feature_code":"PPL",
    "gn:name":"Xitiejiangyingcun",
    "gn:population":0,
    "gn:timezone":"Asia/Shanghai",
    "iso:country":"CN",
    "name:zho_x_preferred":[
        "\u897f\u94c1\u5320\u8425\u6751"
    ],
    "wof:name":"Xitiejiangyingcun",
    "wof:placetype":"locality"
},
  "geometry": {"coordinates":[116.34228,39.85905],"type":"Point"}
}