{
  "type": "Feature",
  "properties": {
    "gn:admin1_code":"3.0",
    "gn:asciiname":"Yuanjiali",
    "gn:country_code":"CN",
    "gn:dem":403,
    "gn:feature_class":"P",
    "gn:feature_code":"PPL",
    "gn:name":"Yuanjiali",
    "gn:population":0,
    "gn:timezone":"Asia/Shanghai",
    "iso:country":"CN",
    "name:und_x_variant":[
        "\u8881\u5bb6\u91cc"
    ],
    "wof:name":"Yuanjiali",
    "wof:placetype":"locality"
},
  "geometry": {"coordinates":[114.16576999999999,27.17796],"type":"Point"}
}