{
  "type": "Feature",
  "properties": {
    "gn:admin1_code":"16.0",
    "gn:asciiname":"Gongshiling",
    "gn:country_code":"CN",
    "gn:dem":85,
    "gn:feature_class":"P",
    "gn:feature_code":"PPL",
    "gn:name":"Gongshiling",
    "gn:population":0,
    "gn:timezone":"Asia/Shanghai",
    "iso:country":"CN",
    "name:zho_x_preferred":[
        "\u516c\u72ee\u5cad"
    ],
    "wof:name":"Gongshiling",
    "wof:placetype":"locality"
},
  "geometry": {"coordinates":[110.20999999999999,22.568],"type":"Point"}
}