{
  "type": "Feature",
  "properties": {
    "gn:admin1_code":"6.0",
    "gn:asciiname":"Barun",
    "gn:cc2":"CN",
    "gn:country_code":"CN",
    "gn:dem":2844,
    "gn:feature_class":"P",
    "gn:feature_code":"PPL",
    "gn:name":"Barun",
    "gn:population":0,
    "gn:timezone":"Asia/Urumqi",
    "iso:country":"CN",
    "name:ceb_x_preferred":[
        "Barun"
    ],
    "name:deu_x_preferred":[
        "Barun"
    ],
    "name:fra_x_preferred":[
        "Barun"
    ],
    "name:ita_x_preferred":[
        "Barun"
    ],
    "name:jpn_x_preferred":[
        "\u30d0\u30eb\u30f3"
    ],
    "name:und_x_variant":[
        "Pa-lung",
        "Baron",
        "Baruun",
        "Baronkure",
        "Barun"
    ],
    "wof:name":"Barun",
    "wof:placetype":"locality"
},
  "geometry": {"coordinates":[97.33333,36.16667],"type":"Point"}
}