{
  "type": "Feature",
  "properties": {
    "gn:admin1_code":"15.0",
    "gn:asciiname":"Chengzhuang",
    "gn:country_code":"CN",
    "gn:dem":1126,
    "gn:feature_class":"P",
    "gn:feature_code":"PPL",
    "gn:name":"Chengzhuang",
    "gn:population":0,
    "gn:timezone":"Asia/Shanghai",
    "iso:country":"CN",
    "name:und_x_variant":[
        "\u6210\u5e84"
    ],
    "wof:name":"Chengzhuang",
    "wof:placetype":"locality"
},
  "geometry": {"coordinates":[105.86114000000001,33.83143],"type":"Point"}
}