{
  "type": "Feature",
  "properties": {
    "gn:admin1_code":"32.0",
    "gn:asciiname":"Yuejiayan",
    "gn:country_code":"CN",
    "gn:dem":326,
    "gn:feature_class":"P",
    "gn:feature_code":"PPL",
    "gn:name":"Yuejiayan",
    "gn:population":0,
    "gn:timezone":"Asia/Shanghai",
    "iso:country":"CN",
    "name:zho_x_preferred":[
        "\u5cb3\u5bb6\u5ca9"
    ],
    "wof:name":"Yuejiayan",
    "wof:placetype":"locality"
},
  "geometry": {"coordinates":[107.277,31.3791],"type":"Point"}
}