{
  "type": "Feature",
  "properties": {
    "gn:admin1_code":"07",
    "gn:asciiname":"Xiachiyuan",
    "gn:country_code":"CN",
    "gn:dem":462,
    "gn:feature_class":"P",
    "gn:feature_code":"PPL",
    "gn:name":"Xiachiyuan",
    "gn:population":0,
    "gn:timezone":"Asia/Shanghai",
    "iso:country":"CN",
    "name:zho_x_preferred":[
        "\u4e0b\u6c60\u56ed"
    ],
    "wof:name":"Xiachiyuan",
    "wof:placetype":"locality"
},
  "geometry": {"coordinates":[117.74021,25.89576],"type":"Point"}
}