{
  "type": "Feature",
  "properties": {
    "gn:admin1_code":"30",
    "gn:asciiname":"Xichang",
    "gn:country_code":"CN",
    "gn:dem":102,
    "gn:feature_class":"P",
    "gn:feature_code":"PPLA4",
    "gn:name":"Xichang",
    "gn:population":0,
    "gn:timezone":"Asia/Shanghai",
    "iso:country":"CN",
    "name:und_x_variant":[
        "\u9521\u573a",
        "Xichang Zhen",
        "\u9521\u573a\u9547"
    ],
    "wof:name":"Xichang",
    "wof:placetype":"locality"
},
  "geometry": {"coordinates":[114.45276,23.92719],"type":"Point"}
}