{
  "type": "Feature",
  "properties": {
    "gn:admin1_code":"5.0",
    "gn:asciiname":"Dahuacun",
    "gn:country_code":"CN",
    "gn:dem":615,
    "gn:feature_class":"P",
    "gn:feature_code":"PPL",
    "gn:name":"Dahuacun",
    "gn:population":0,
    "gn:timezone":"Asia/Shanghai",
    "iso:country":"CN",
    "name:zho_x_preferred":[
        "\u5927\u534e\u6751"
    ],
    "wof:name":"Dahuacun",
    "wof:placetype":"locality"
},
  "geometry": {"coordinates":[126.54412000000001,42.02124],"type":"Point"}
}