{
  "type": "Feature",
  "properties": {
    "gn:admin1_code":"3.0",
    "gn:asciiname":"Shixingli",
    "gn:country_code":"CN",
    "gn:dem":265,
    "gn:feature_class":"P",
    "gn:feature_code":"PPL",
    "gn:name":"Shixingli",
    "gn:population":0,
    "gn:timezone":"Asia/Shanghai",
    "iso:country":"CN",
    "name:und_x_variant":[
        "\u72ee\u5f62\u91cc"
    ],
    "wof:name":"Shixingli",
    "wof:placetype":"locality"
},
  "geometry": {"coordinates":[114.54373,27.46285],"type":"Point"}
}