{
  "type": "Feature",
  "properties": {
    "gn:admin1_code":"15.0",
    "gn:asciiname":"Qiaojiahe",
    "gn:country_code":"CN",
    "gn:dem":1396,
    "gn:feature_class":"P",
    "gn:feature_code":"PPL",
    "gn:name":"Qiaojiahe",
    "gn:population":0,
    "gn:timezone":"Asia/Shanghai",
    "iso:country":"CN",
    "name:zho_x_preferred":[
        "\u8c2f\u5bb6\u6cb3"
    ],
    "wof:name":"Qiaojiahe",
    "wof:placetype":"locality"
},
  "geometry": {"coordinates":[107.209,35.817],"type":"Point"}
}