{
  "type": "Feature",
  "properties": {
    "gn:admin1_code":"5.0",
    "gn:asciiname":"Tongjuyongcun",
    "gn:country_code":"CN",
    "gn:dem":159,
    "gn:feature_class":"P",
    "gn:feature_code":"PPL",
    "gn:name":"Tongjuyongcun",
    "gn:population":0,
    "gn:timezone":"Asia/Shanghai",
    "iso:country":"CN",
    "name:zho_x_preferred":[
        "\u540c\u5de8\u6c38\u6751"
    ],
    "wof:name":"Tongjuyongcun",
    "wof:placetype":"locality"
},
  "geometry": {"coordinates":[126.11507,44.58717],"type":"Point"}
}