{
  "type": "Feature",
  "properties": {
    "gn:admin1_code":"4.0",
    "gn:asciiname":"Yibei",
    "gn:country_code":"CN",
    "gn:dem":1,
    "gn:feature_class":"P",
    "gn:feature_code":"PPL",
    "gn:name":"Yibei",
    "gn:population":0,
    "gn:timezone":"Asia/Shanghai",
    "iso:country":"CN",
    "name:zho_x_preferred":[
        "Yibei"
    ],
    "name:zho_x_variant":[
        "\u4f0a\u5317"
    ],
    "wof:name":"Yibei",
    "wof:placetype":"locality"
},
  "geometry": {"coordinates":[119.18086,34.38841],"type":"Point"}
}