{
  "type": "Feature",
  "properties": {
    "gn:admin1_code":"29",
    "gn:asciiname":"Yangxiewo",
    "gn:country_code":"CN",
    "gn:dem":2002,
    "gn:feature_class":"P",
    "gn:feature_code":"PPL",
    "gn:name":"Yangxiewo",
    "gn:population":0,
    "gn:timezone":"Asia/Shanghai",
    "iso:country":"CN",
    "name:zho_x_preferred":[
        "\u7f8a\u6b47\u7a9d"
    ],
    "wof:name":"Yangxiewo",
    "wof:placetype":"locality"
},
  "geometry": {"coordinates":[102.605,24.457],"type":"Point"}
}