{
  "type": "Feature",
  "properties": {
    "gn:admin1_code":"14.0",
    "gn:asciiname":"Shenda",
    "gn:country_code":"CN",
    "gn:dem":4223,
    "gn:feature_class":"P",
    "gn:feature_code":"PPL",
    "gn:name":"Shenda",
    "gn:population":0,
    "gn:timezone":"Asia/Urumqi",
    "iso:country":"CN",
    "name:zho_x_preferred":[
        "\u4f38\u8fbe"
    ],
    "wof:name":"Shenda",
    "wof:placetype":"locality"
},
  "geometry": {"coordinates":[92.48598,28.64573],"type":"Point"}
}