{
  "type": "Feature",
  "properties": {
    "gn:admin1_code":"18.0",
    "gn:asciiname":"Huarong",
    "gn:country_code":"CN",
    "gn:dem":458,
    "gn:feature_class":"P",
    "gn:feature_code":"PPL",
    "gn:name":"Huarong",
    "gn:population":0,
    "gn:timezone":"Asia/Shanghai",
    "iso:country":"CN",
    "name:ceb_x_preferred":[
        "Huarong"
    ],
    "name:deu_x_preferred":[
        "Huarong"
    ],
    "name:fra_x_preferred":[
        "Huarong"
    ],
    "name:nor_x_preferred":[
        "Huarong"
    ],
    "name:swe_x_preferred":[
        "Huarong"
    ],
    "wof:name":"Huarong",
    "wof:placetype":"locality"
},
  "geometry": {"coordinates":[105.90000000000001,25.00417],"type":"Point"}
}