{
  "type": "Feature",
  "properties": {
    "gn:admin1_code":"32.0",
    "gn:asciiname":"Qumi",
    "gn:country_code":"CN",
    "gn:dem":2649,
    "gn:feature_class":"P",
    "gn:feature_code":"PPL",
    "gn:name":"Qumi",
    "gn:population":0,
    "gn:timezone":"Asia/Shanghai",
    "iso:country":"CN",
    "name:ara_x_preferred":[
        "\u0642\u0648\u0645\u064a"
    ],
    "name:ceb_x_preferred":[
        "Q\u016bm\u012b"
    ],
    "name:fas_x_preferred":[
        "\u0642\u0648\u0645\u06cc"
    ],
    "name:swe_x_preferred":[
        "Q\u016bm\u012b"
    ],
    "name:zho_x_preferred":[
        "\u66f2\u7c73"
    ],
    "wof:name":"Qumi",
    "wof:placetype":"locality"
},
  "geometry": {"coordinates":[101.55200000000001,27.9306],"type":"Point"}
}