{
  "type": "Feature",
  "properties": {
    "gn:admin1_code":"16.0",
    "gn:asciiname":"Dongling",
    "gn:country_code":"CN",
    "gn:dem":61,
    "gn:feature_class":"P",
    "gn:feature_code":"PPL",
    "gn:name":"Dongling",
    "gn:population":0,
    "gn:timezone":"Asia/Shanghai",
    "iso:country":"CN",
    "name:ceb_x_preferred":[
        "Dongling"
    ],
    "name:mlg_x_preferred":[
        "Dongling"
    ],
    "name:swe_x_preferred":[
        "Dongling"
    ],
    "name:zho_x_preferred":[
        "\u4e1c\u5cad"
    ],
    "wof:name":"Dongling",
    "wof:placetype":"locality"
},
  "geometry": {"coordinates":[109.86499999999999,23.0375],"type":"Point"}
}