{
  "type": "Feature",
  "properties": {
    "gn:admin1_code":"6.0",
    "gn:asciiname":"Chesuo",
    "gn:country_code":"CN",
    "gn:dem":3776,
    "gn:feature_class":"P",
    "gn:feature_code":"PPL",
    "gn:name":"Chesuo",
    "gn:population":0,
    "gn:timezone":"Asia/Urumqi",
    "iso:country":"CN",
    "name:zho_x_preferred":[
        "\u8f66\u6240"
    ],
    "wof:name":"Chesuo",
    "wof:placetype":"locality"
},
  "geometry": {"coordinates":[97.10424999999999,33.27441],"type":"Point"}
}