{
  "type": "Feature",
  "properties": {
    "gn:admin1_code":"11",
    "gn:asciiname":"Qujiang",
    "gn:country_code":"CN",
    "gn:dem":371,
    "gn:feature_class":"P",
    "gn:feature_code":"PPL",
    "gn:name":"Qujiang",
    "gn:population":0,
    "gn:timezone":"Asia/Shanghai",
    "iso:country":"CN",
    "name:ceb_x_preferred":[
        "Qujiang"
    ],
    "name:deu_x_preferred":[
        "Qujiang"
    ],
    "name:fra_x_preferred":[
        "Qujiang"
    ],
    "name:kor_x_preferred":[
        "\ucde8\uc7a5\uad6c"
    ],
    "name:nor_x_preferred":[
        "Qujiang"
    ],
    "name:swe_x_preferred":[
        "Qujiang"
    ],
    "wof:name":"Qujiang",
    "wof:placetype":"locality"
},
  "geometry": {"coordinates":[109.67722000000001,26.43611],"type":"Point"}
}