{
  "type": "Feature",
  "properties": {
    "gn:admin1_code":"32.0",
    "gn:asciiname":"Pie'erkashan",
    "gn:country_code":"CN",
    "gn:dem":3222,
    "gn:feature_class":"P",
    "gn:feature_code":"PPL",
    "gn:name":"Pie\u2019erkashan",
    "gn:population":0,
    "gn:timezone":"Asia/Shanghai",
    "iso:country":"CN",
    "name:und_x_variant":[
        "Pie\u2019erkashan"
    ],
    "name:zho_x_preferred":[
        "\u6487\u5c14\u5361\u5c71"
    ],
    "wof:name":"Pie'erkashan",
    "wof:placetype":"locality"
},
  "geometry": {"coordinates":[102.53400000000001,31.0039],"type":"Point"}
}