{
  "type": "Feature",
  "properties": {
    "gn:admin1_code":"29.0",
    "gn:asciiname":"Xiaozhezong",
    "gn:country_code":"CN",
    "gn:dem":1954,
    "gn:feature_class":"P",
    "gn:feature_code":"PPL",
    "gn:name":"Xiaozhezong",
    "gn:population":0,
    "gn:timezone":"Asia/Shanghai",
    "iso:country":"CN",
    "name:zho_x_preferred":[
        "\u5c0f\u54f2\u5b97"
    ],
    "wof:name":"Xiaozhezong",
    "wof:placetype":"locality"
},
  "geometry": {"coordinates":[103.42100000000001,25.1795],"type":"Point"}
}