{
  "type": "Feature",
  "properties": {
    "gn:admin1_code":"12.0",
    "gn:asciiname":"Damochang",
    "gn:country_code":"CN",
    "gn:dem":1751,
    "gn:feature_class":"P",
    "gn:feature_code":"PPL",
    "gn:name":"Damochang",
    "gn:population":0,
    "gn:timezone":"Asia/Shanghai",
    "iso:country":"CN",
    "name:zho_x_preferred":[
        "\u6253\u78e8\u573a"
    ],
    "wof:name":"Damochang",
    "wof:placetype":"locality"
},
  "geometry": {"coordinates":[110.69884999999999,30.52487],"type":"Point"}
}