{
  "type": "Feature",
  "properties": {
    "gn:admin1_code":"3.0",
    "gn:asciiname":"Xinkailing",
    "gn:country_code":"CN",
    "gn:dem":200,
    "gn:feature_class":"P",
    "gn:feature_code":"PPL",
    "gn:name":"Xinkailing",
    "gn:population":0,
    "gn:timezone":"Asia/Shanghai",
    "iso:country":"CN",
    "name:und_x_variant":[
        "\u65b0\u5f00\u5cad"
    ],
    "wof:name":"Xinkailing",
    "wof:placetype":"locality"
},
  "geometry": {"coordinates":[115.76288,26.18972],"type":"Point"}
}