{
  "type": "Feature",
  "properties": {
    "gn:admin1_code":"32",
    "gn:asciiname":"Suomo",
    "gn:country_code":"CN",
    "gn:dem":2945,
    "gn:feature_class":"P",
    "gn:feature_code":"PPL",
    "gn:name":"Suomo",
    "gn:population":0,
    "gn:timezone":"Asia/Shanghai",
    "iso:country":"CN",
    "name:und_x_variant":[
        "So-mo",
        "Somang",
        "Suomo"
    ],
    "name:zho_x_preferred":[
        "\u68ad\u78e8"
    ],
    "wof:name":"Suomo",
    "wof:placetype":"locality"
},
  "geometry": {"coordinates":[102.49518999999999,31.86197],"type":"Point"}
}