{
  "type": "Feature",
  "properties": {
    "gn:admin1_code":"29.0",
    "gn:asciiname":"Nanxizhai",
    "gn:country_code":"CN",
    "gn:dem":991,
    "gn:feature_class":"P",
    "gn:feature_code":"PPL",
    "gn:name":"Nanxizhai",
    "gn:population":0,
    "gn:timezone":"Asia/Shanghai",
    "iso:country":"CN",
    "name:zho_x_preferred":[
        "\u5357\u897f\u5be8"
    ],
    "wof:name":"Nanxizhai",
    "wof:placetype":"locality"
},
  "geometry": {"coordinates":[102.965,22.5166],"type":"Point"}
}