{
  "type": "Feature",
  "properties": {
    "gn:admin1_code":"12.0",
    "gn:asciiname":"Fengjia",
    "gn:country_code":"CN",
    "gn:dem":361,
    "gn:feature_class":"P",
    "gn:feature_code":"PPL",
    "gn:name":"Fengjia",
    "gn:population":0,
    "gn:timezone":"Asia/Shanghai",
    "iso:country":"CN",
    "name:zho_x_preferred":[
        "Fengjia"
    ],
    "name:zho_x_variant":[
        "\u51af\u5bb6"
    ],
    "wof:name":"Fengjia",
    "wof:placetype":"locality"
},
  "geometry": {"coordinates":[114.45807000000001,29.35093],"type":"Point"}
}