{
  "type": "Feature",
  "properties": {
    "gn:admin1_code":"19.0",
    "gn:asciiname":"Houmashi Bucun",
    "gn:country_code":"CN",
    "gn:dem":113,
    "gn:feature_class":"P",
    "gn:feature_code":"PPL",
    "gn:name":"Houmashi Bucun",
    "gn:population":0,
    "gn:timezone":"Asia/Shanghai",
    "iso:country":"CN",
    "name:und_x_variant":[
        "Houmashibucun",
        "Houmashi Bucun"
    ],
    "name:zho_x_preferred":[
        "\u540e\u9a6c\u5e02\u5821\u6751"
    ],
    "wof:name":"Houmashi Bucun",
    "wof:placetype":"locality"
},
  "geometry": {"coordinates":[124.19802,42.6654],"type":"Point"}
}