{
  "type": "Feature",
  "properties": {
    "gn:admin1_code":"11.0",
    "gn:asciiname":"Tanghualing",
    "gn:country_code":"CN",
    "gn:dem":413,
    "gn:feature_class":"P",
    "gn:feature_code":"PPL",
    "gn:name":"Tanghualing",
    "gn:population":0,
    "gn:timezone":"Asia/Shanghai",
    "iso:country":"CN",
    "name:zho_x_preferred":[
        "\u68e0\u534e\u5cad"
    ],
    "wof:name":"Tanghualing",
    "wof:placetype":"locality"
},
  "geometry": {"coordinates":[113.98430999999999,26.60848],"type":"Point"}
}