{
  "type": "Feature",
  "properties": {
    "gn:admin1_code":"10.0",
    "gn:asciiname":"Beidinan",
    "gn:country_code":"CN",
    "gn:dem":19,
    "gn:feature_class":"P",
    "gn:feature_code":"PPL",
    "gn:name":"Beidinan",
    "gn:population":0,
    "gn:timezone":"Asia/Shanghai",
    "iso:country":"CN",
    "name:zho_x_preferred":[
        "\u5317\u5824\u5357"
    ],
    "wof:name":"Beidinan",
    "wof:placetype":"locality"
},
  "geometry": {"coordinates":[115.846,38.0864],"type":"Point"}
}