{
  "type": "Feature",
  "properties": {
    "gn:admin1_code":"20.0",
    "gn:asciiname":"Chendi Yingzi",
    "gn:country_code":"CN",
    "gn:dem":408,
    "gn:feature_class":"P",
    "gn:feature_code":"PPL",
    "gn:name":"Chendi Yingzi",
    "gn:population":0,
    "gn:timezone":"Asia/Shanghai",
    "iso:country":"CN",
    "name:zho_x_preferred":[
        "\u9648\u5730\u8425\u5b50"
    ],
    "wof:name":"Chendi Yingzi",
    "wof:placetype":"locality"
},
  "geometry": {"coordinates":[122.75381000000002,48.20106],"type":"Point"}
}