{
  "type": "Feature",
  "properties": {
    "gn:admin1_code":"3.0",
    "gn:asciiname":"Zengjia",
    "gn:country_code":"CN",
    "gn:dem":114,
    "gn:feature_class":"P",
    "gn:feature_code":"PPL",
    "gn:name":"Zengjia",
    "gn:population":0,
    "gn:timezone":"Asia/Shanghai",
    "iso:country":"CN",
    "name:und_x_variant":[
        "\u66fe\u5bb6"
    ],
    "wof:name":"Zengjia",
    "wof:placetype":"locality"
},
  "geometry": {"coordinates":[115.02159,25.84045],"type":"Point"}
}