{
  "type": "Feature",
  "properties": {
    "gn:admin1_code":"16",
    "gn:asciiname":"Dazhuping",
    "gn:country_code":"CN",
    "gn:dem":549,
    "gn:feature_class":"P",
    "gn:feature_code":"PPL",
    "gn:name":"Dazhuping",
    "gn:population":0,
    "gn:timezone":"Asia/Shanghai",
    "iso:country":"CN",
    "name:zho_x_preferred":[
        "\u5927\u7af9\u576a"
    ],
    "wof:name":"Dazhuping",
    "wof:placetype":"locality"
},
  "geometry": {"coordinates":[110.42700000000001,25.8116],"type":"Point"}
}