{
  "type": "Feature",
  "properties": {
    "gn:admin1_code":"29.0",
    "gn:asciiname":"Shangzhu'en",
    "gn:country_code":"CN",
    "gn:dem":2656,
    "gn:feature_class":"P",
    "gn:feature_code":"PPL",
    "gn:name":"Shangzhu\u2019en",
    "gn:population":0,
    "gn:timezone":"Asia/Shanghai",
    "iso:country":"CN",
    "name:und_x_variant":[
        "Shangzhu\u2019en"
    ],
    "name:zho_x_preferred":[
        "\u4e0a\u7af9\u6069"
    ],
    "wof:name":"Shangzhu'en",
    "wof:placetype":"locality"
},
  "geometry": {"coordinates":[100.119,27.501],"type":"Point"}
}