{
  "type": "Feature",
  "properties": {
    "gn:admin1_code":"5.0",
    "gn:asciiname":"Zhangjia Juzi",
    "gn:country_code":"CN",
    "gn:dem":154,
    "gn:feature_class":"P",
    "gn:feature_code":"PPL",
    "gn:name":"Zhangjia Juzi",
    "gn:population":0,
    "gn:timezone":"Asia/Shanghai",
    "iso:country":"CN",
    "name:zho_x_preferred":[
        "\u5f20\u5bb6\u5c40\u5b50"
    ],
    "wof:name":"Zhangjia Juzi",
    "wof:placetype":"locality"
},
  "geometry": {"coordinates":[124.02423,43.41791],"type":"Point"}
}