{
  "type": "Feature",
  "properties": {
    "gn:admin1_code":"15.0",
    "gn:asciiname":"Xinmiao",
    "gn:country_code":"CN",
    "gn:dem":1100,
    "gn:feature_class":"P",
    "gn:feature_code":"PPL",
    "gn:name":"Xinmiao",
    "gn:population":0,
    "gn:timezone":"Asia/Urumqi",
    "iso:country":"CN",
    "name:zho_x_preferred":[
        "\u65b0\u5e99"
    ],
    "wof:name":"Xinmiao",
    "wof:placetype":"locality"
},
  "geometry": {"coordinates":[94.7808,40.2434],"type":"Point"}
}