{
  "type": "Feature",
  "properties": {
    "gn:admin1_code":"9.0",
    "gn:asciiname":"Xixianghu",
    "gn:country_code":"CN",
    "gn:dem":72,
    "gn:feature_class":"P",
    "gn:feature_code":"PPL",
    "gn:name":"Xixianghu",
    "gn:population":0,
    "gn:timezone":"Asia/Shanghai",
    "iso:country":"CN",
    "name:zho_x_preferred":[
        "\u897f\u9999\u80e1"
    ],
    "wof:name":"Xixianghu",
    "wof:placetype":"locality"
},
  "geometry": {"coordinates":[114.42319000000001,34.97166],"type":"Point"}
}