{
  "type": "Feature",
  "properties": {
    "gn:admin1_code":"5.0",
    "gn:asciiname":"Sanshijiuhu",
    "gn:country_code":"CN",
    "gn:dem":184,
    "gn:feature_class":"P",
    "gn:feature_code":"PPL",
    "gn:name":"Sanshijiuhu",
    "gn:population":0,
    "gn:timezone":"Asia/Shanghai",
    "iso:country":"CN",
    "name:zho_x_preferred":[
        "\u4e09\u5341\u4e5d\u6237"
    ],
    "wof:name":"Sanshijiuhu",
    "wof:placetype":"locality"
},
  "geometry": {"coordinates":[126.8948,45.0662],"type":"Point"}
}