{
  "type": "Feature",
  "properties": {
    "gn:admin1_code":"14.0",
    "gn:asciiname":"Zhiglung",
    "gn:country_code":"CN",
    "gn:dem":4666,
    "gn:feature_class":"P",
    "gn:feature_code":"PPL",
    "gn:name":"Zhiglung",
    "gn:population":0,
    "gn:timezone":"Asia/Urumqi",
    "iso:country":"CN",
    "name:bod_x_preferred":[
        "Zhiglung"
    ],
    "name:zho_x_preferred":[
        "Zhelong"
    ],
    "name:zho_x_variant":[
        "\u54f2\u9686"
    ],
    "wof:name":"Zhiglung",
    "wof:placetype":"locality"
},
  "geometry": {"coordinates":[91.402,32.102],"type":"Point"}
}