{
  "type": "Feature",
  "properties": {
    "gn:admin1_code":"25",
    "gn:asciiname":"Xiaobeizhuang",
    "gn:country_code":"CN",
    "gn:dem":365,
    "gn:feature_class":"P",
    "gn:feature_code":"PPL",
    "gn:name":"Xiaobeizhuang",
    "gn:population":0,
    "gn:timezone":"Asia/Shanghai",
    "iso:country":"CN",
    "name:zho_x_preferred":[
        "\u5c0f\u5317\u5e84"
    ],
    "wof:name":"Xiaobeizhuang",
    "wof:placetype":"locality"
},
  "geometry": {"coordinates":[118.048,36.2178],"type":"Point"}
}