{
  "type": "Feature",
  "properties": {
    "gn:admin1_code":"12.0",
    "gn:asciiname":"Zhengjia'ao",
    "gn:country_code":"CN",
    "gn:dem":377,
    "gn:feature_class":"P",
    "gn:feature_code":"PPL",
    "gn:name":"Zhengjia\u2019ao",
    "gn:population":0,
    "gn:timezone":"Asia/Shanghai",
    "iso:country":"CN",
    "name:und_x_variant":[
        "Zhengjia\u2019ao"
    ],
    "name:zho_x_preferred":[
        "\u90d1\u5bb6\u5773"
    ],
    "wof:name":"Zhengjia'ao",
    "wof:placetype":"locality"
},
  "geometry": {"coordinates":[115.6018,31.04358],"type":"Point"}
}