{
  "type": "Feature",
  "properties": {
    "gn:admin1_code":"29.0",
    "gn:asciiname":"Liujiazhuang",
    "gn:country_code":"CN",
    "gn:dem":2020,
    "gn:feature_class":"P",
    "gn:feature_code":"PPL",
    "gn:name":"Liujiazhuang",
    "gn:population":0,
    "gn:timezone":"Asia/Shanghai",
    "iso:country":"CN",
    "name:und_x_variant":[
        "\u5218\u5bb6\u5e84"
    ],
    "wof:name":"Liujiazhuang",
    "wof:placetype":"locality"
},
  "geometry": {"coordinates":[103.74911,25.79685],"type":"Point"}
}