{
  "type": "Feature",
  "properties": {
    "gn:admin1_code":"24.0",
    "gn:asciiname":"Shandicun",
    "gn:country_code":"CN",
    "gn:dem":553,
    "gn:feature_class":"P",
    "gn:feature_code":"PPL",
    "gn:name":"Shandicun",
    "gn:population":0,
    "gn:timezone":"Asia/Shanghai",
    "iso:country":"CN",
    "name:zho_x_preferred":[
        "\u5c71\u5e95\u6751"
    ],
    "wof:name":"Shandicun",
    "wof:placetype":"locality"
},
  "geometry": {"coordinates":[110.96202,35.67373],"type":"Point"}
}