{
  "type": "Feature",
  "properties": {
    "gn:admin1_code":"8.0",
    "gn:asciiname":"Baotiancun",
    "gn:country_code":"CN",
    "gn:dem":127,
    "gn:feature_class":"P",
    "gn:feature_code":"PPL",
    "gn:name":"Baotiancun",
    "gn:population":0,
    "gn:timezone":"Asia/Shanghai",
    "iso:country":"CN",
    "name:zho_x_preferred":[
        "\u4fdd\u7530\u6751"
    ],
    "wof:name":"Baotiancun",
    "wof:placetype":"locality"
},
  "geometry": {"coordinates":[130.0454,46.1989],"type":"Point"}
}