{
  "type": "Feature",
  "properties": {
    "gn:admin1_code":"7",
    "gn:asciiname":"Sushan",
    "gn:country_code":"CN",
    "gn:dem":508,
    "gn:feature_class":"P",
    "gn:feature_code":"PPL",
    "gn:name":"Sushan",
    "gn:population":0,
    "gn:timezone":"Asia/Shanghai",
    "iso:country":"CN",
    "wof:name":"Sushan",
    "wof:placetype":"locality"
},
  "geometry": {"coordinates":[118.56999999999999,25.26083],"type":"Point"}
}