{
  "type": "Feature",
  "properties": {
    "gn:admin1_code":"16",
    "gn:asciiname":"Daoguangzhou",
    "gn:country_code":"CN",
    "gn:dem":137,
    "gn:feature_class":"P",
    "gn:feature_code":"PPL",
    "gn:name":"Daoguangzhou",
    "gn:population":0,
    "gn:timezone":"Asia/Shanghai",
    "iso:country":"CN",
    "name:zho_x_preferred":[
        "\u9053\u5149\u6d32"
    ],
    "wof:name":"Daoguangzhou",
    "wof:placetype":"locality"
},
  "geometry": {"coordinates":[110.46299999999999,24.8084],"type":"Point"}
}