{
  "type": "Feature",
  "properties": {
    "gn:admin1_code":"26.0",
    "gn:asciiname":"Yinzhongcun",
    "gn:country_code":"CN",
    "gn:dem":850,
    "gn:feature_class":"P",
    "gn:feature_code":"PPL",
    "gn:name":"Yinzhongcun",
    "gn:population":0,
    "gn:timezone":"Asia/Shanghai",
    "iso:country":"CN",
    "name:zho_x_preferred":[
        "\u94f6\u4e2d\u6751"
    ],
    "wof:name":"Yinzhongcun",
    "wof:placetype":"locality"
},
  "geometry": {"coordinates":[110.49253,33.66129],"type":"Point"}
}