{
  "type": "Feature",
  "properties": {
    "gn:admin1_code":"4.0",
    "gn:asciiname":"Miaoxudai",
    "gn:country_code":"CN",
    "gn:dem":7,
    "gn:feature_class":"P",
    "gn:feature_code":"PPL",
    "gn:name":"Miaoxudai",
    "gn:population":0,
    "gn:timezone":"Asia/Shanghai",
    "iso:country":"CN",
    "name:zho_x_preferred":[
        "\u5e99\u5729\u57ed"
    ],
    "wof:name":"Miaoxudai",
    "wof:placetype":"locality"
},
  "geometry": {"coordinates":[119.79822,32.12904],"type":"Point"}
}