{
  "type": "Feature",
  "properties": {
    "gn:admin1_code":"29.0",
    "gn:asciiname":"Baishadong",
    "gn:country_code":"CN",
    "gn:dem":2365,
    "gn:feature_class":"P",
    "gn:feature_code":"PPL",
    "gn:name":"Baishadong",
    "gn:population":0,
    "gn:timezone":"Asia/Shanghai",
    "iso:country":"CN",
    "name:zho_x_preferred":[
        "\u767d\u6c99\u6d1e"
    ],
    "wof:name":"Baishadong",
    "wof:placetype":"locality"
},
  "geometry": {"coordinates":[100.232,26.1798],"type":"Point"}
}