{
  "type": "Feature",
  "properties": {
    "gn:admin1_code":"8.0",
    "gn:asciiname":"Luhaitun",
    "gn:country_code":"CN",
    "gn:dem":200,
    "gn:feature_class":"P",
    "gn:feature_code":"PPL",
    "gn:name":"L\u00fchaitun",
    "gn:population":0,
    "gn:timezone":"Asia/Shanghai",
    "iso:country":"CN",
    "name:und_x_variant":[
        "L\u00fchaitun"
    ],
    "name:zho_x_preferred":[
        "\u5415\u6d77\u5c6f"
    ],
    "wof:name":"Luhaitun",
    "wof:placetype":"locality"
},
  "geometry": {"coordinates":[128.14162999999999,45.45331],"type":"Point"}
}