{
  "type": "Feature",
  "properties": {
    "gn:admin1_code":"14.0",
    "gn:asciiname":"Nabug",
    "gn:country_code":"CN",
    "gn:dem":5091,
    "gn:feature_class":"P",
    "gn:feature_code":"PPLF",
    "gn:name":"Nabug",
    "gn:population":0,
    "gn:timezone":"Asia/Urumqi",
    "iso:country":"CN",
    "name:bod_x_preferred":[
        "Nabug"
    ],
    "name:zho_x_preferred":[
        "Nabu"
    ],
    "name:zho_x_variant":[
        "\u7eb3\u5e03",
        "Chajuenangma",
        "\u67e5\u89c9\u56ca\u739b"
    ],
    "wof:name":"Nabug",
    "wof:placetype":"locality"
},
  "geometry": {"coordinates":[92.101,31.001],"type":"Point"}
}