{
  "type": "Feature",
  "properties": {
    "gn:admin1_code":"1.0",
    "gn:asciiname":"Qipucun",
    "gn:country_code":"CN",
    "gn:dem":465,
    "gn:feature_class":"P",
    "gn:feature_code":"PPL",
    "gn:name":"Qipucun",
    "gn:population":0,
    "gn:timezone":"Asia/Shanghai",
    "iso:country":"CN",
    "name:zho_x_preferred":[
        "\u6f06\u94fa\u6751"
    ],
    "wof:name":"Qipucun",
    "wof:placetype":"locality"
},
  "geometry": {"coordinates":[116.51039,30.75301],"type":"Point"}
}