{
  "type": "Feature",
  "properties": {
    "gn:admin1_code":"14.0",
    "gn:asciiname":"Parongdacun",
    "gn:country_code":"CN",
    "gn:dem":3947,
    "gn:feature_class":"P",
    "gn:feature_code":"PPL",
    "gn:name":"Parongdacun",
    "gn:population":0,
    "gn:timezone":"Asia/Urumqi",
    "iso:country":"CN",
    "name:zho_x_preferred":[
        "\u5e15\u8363\u8fbe\u6751"
    ],
    "wof:name":"Parongdacun",
    "wof:placetype":"locality"
},
  "geometry": {"coordinates":[94.61201,31.58814000000001],"type":"Point"}
}