{
  "type": "Feature",
  "properties": {
    "gn:admin1_code":"19.0",
    "gn:asciiname":"Songtuncun",
    "gn:country_code":"CN",
    "gn:dem":33,
    "gn:feature_class":"P",
    "gn:feature_code":"PPL",
    "gn:name":"Songtuncun",
    "gn:population":0,
    "gn:timezone":"Asia/Shanghai",
    "iso:country":"CN",
    "name:zho_x_preferred":[
        "\u5b8b\u5c6f\u6751"
    ],
    "wof:name":"Songtuncun",
    "wof:placetype":"locality"
},
  "geometry": {"coordinates":[122.04300000000001,41.6891],"type":"Point"}
}