{
  "type": "Feature",
  "properties": {
    "gn:admin1_code":"25",
    "gn:asciiname":"Liufuzhai",
    "gn:country_code":"CN",
    "gn:dem":24,
    "gn:feature_class":"P",
    "gn:feature_code":"PPL",
    "gn:name":"Liufuzhai",
    "gn:population":0,
    "gn:timezone":"Asia/Shanghai",
    "iso:country":"CN",
    "name:zho_x_preferred":[
        "\u5218\u592b\u5be8"
    ],
    "wof:name":"Liufuzhai",
    "wof:placetype":"locality"
},
  "geometry": {"coordinates":[116.364,37.2171],"type":"Point"}
}