{
  "type": "Feature",
  "properties": {
    "gn:admin1_code":"29.0",
    "gn:asciiname":"Baimadiluo",
    "gn:country_code":"CN",
    "gn:dem":2165,
    "gn:feature_class":"P",
    "gn:feature_code":"PPL",
    "gn:name":"Baimadiluo",
    "gn:population":0,
    "gn:timezone":"Asia/Shanghai",
    "iso:country":"CN",
    "name:zho_x_preferred":[
        "\u767d\u9a6c\u8fea\u6d1b"
    ],
    "wof:name":"Baimadiluo",
    "wof:placetype":"locality"
},
  "geometry": {"coordinates":[99.0539,27.8046],"type":"Point"}
}