{
  "type": "Feature",
  "properties": {
    "gn:admin1_code":"5.0",
    "gn:asciiname":"Houjia Dayuan",
    "gn:country_code":"CN",
    "gn:dem":191,
    "gn:feature_class":"P",
    "gn:feature_code":"PPL",
    "gn:name":"Houjia Dayuan",
    "gn:population":0,
    "gn:timezone":"Asia/Shanghai",
    "iso:country":"CN",
    "name:zho_x_preferred":[
        "\u4faf\u5bb6\u5927\u9662"
    ],
    "wof:name":"Houjia Dayuan",
    "wof:placetype":"locality"
},
  "geometry": {"coordinates":[124.79233000000001,43.73484000000001],"type":"Point"}
}