{
  "type": "Feature",
  "properties": {
    "gn:admin1_code":"16.0",
    "gn:asciiname":"Huashou",
    "gn:country_code":"CN",
    "gn:dem":105,
    "gn:feature_class":"P",
    "gn:feature_code":"PPL",
    "gn:name":"Huashou",
    "gn:population":0,
    "gn:timezone":"Asia/Shanghai",
    "iso:country":"CN",
    "name:zho_x_preferred":[
        "\u5316\u5bff"
    ],
    "wof:name":"Huashou",
    "wof:placetype":"locality"
},
  "geometry": {"coordinates":[109.94199999999999,22.8493],"type":"Point"}
}