{
  "type": "Feature",
  "properties": {
    "gn:admin1_code":"11",
    "gn:asciiname":"Dingcheng",
    "gn:country_code":"CN",
    "gn:dem":39,
    "gn:feature_class":"P",
    "gn:feature_code":"PPLA3",
    "gn:name":"Dingcheng",
    "gn:population":0,
    "gn:timezone":"Asia/Shanghai",
    "iso:country":"CN",
    "name:ceb_x_preferred":[
        "Dingcheng"
    ],
    "name:und_x_variant":[
        "\u9f0e\u6210",
        "Wuling",
        "Wuling Zhen",
        "Dingcheng Qu",
        "\u6b66\u9675",
        "\u6b66\u9675\u9547",
        "\u9f0e\u6210\u533a"
    ],
    "wof:name":"Dingcheng",
    "wof:placetype":"locality"
},
  "geometry": {"coordinates":[111.67976000000002,29.01937],"type":"Point"}
}