{
  "type": "Feature",
  "properties": {
    "gn:admin1_code":"30",
    "gn:asciiname":"Maoling",
    "gn:country_code":"CN",
    "gn:dem":41,
    "gn:feature_class":"P",
    "gn:feature_code":"PPL",
    "gn:name":"Maoling",
    "gn:population":0,
    "gn:timezone":"Asia/Urumqi",
    "iso:country":"CN",
    "name:zho_x_preferred":[
        "\u8302\u5cad"
    ],
    "wof:name":"Maoling",
    "wof:placetype":"locality"
},
  "geometry": {"coordinates":[110.84502999999999,21.89111],"type":"Point"}
}