{
  "type": "Feature",
  "properties": {
    "gn:admin1_code":"11.0",
    "gn:asciiname":"Taoshu",
    "gn:country_code":"CN",
    "gn:dem":601,
    "gn:feature_class":"P",
    "gn:feature_code":"PPL",
    "gn:name":"Taoshu",
    "gn:population":0,
    "gn:timezone":"Asia/Shanghai",
    "iso:country":"CN",
    "name:zho_x_preferred":[
        "Taoshu"
    ],
    "name:zho_x_variant":[
        "\u6843\u6811"
    ],
    "wof:name":"Taoshu",
    "wof:placetype":"locality"
},
  "geometry": {"coordinates":[111.24114,29.49997],"type":"Point"}
}