{
  "type": "Feature",
  "properties": {
    "gn:admin1_code":"09",
    "gn:asciiname":"Niutunzhen",
    "gn:cc2":"CN",
    "gn:country_code":"CN",
    "gn:dem":67,
    "gn:feature_class":"P",
    "gn:feature_code":"PPL",
    "gn:name":"Niutunzhen",
    "gn:population":0,
    "gn:timezone":"Asia/Shanghai",
    "iso:country":"CN",
    "name:und_x_variant":[
        "Niu-t\u2019un-chi",
        "Niu-t\u2019un",
        "Niu-shih-t\u2019un",
        "Niushitun",
        "Niutunzhen"
    ],
    "wof:name":"Niutunzhen",
    "wof:placetype":"locality"
},
  "geometry": {"coordinates":[114.41,35.27528],"type":"Point"}
}