{
  "type": "Feature",
  "properties": {
    "gn:admin1_code":"16",
    "gn:asciiname":"Ledong",
    "gn:country_code":"CN",
    "gn:dem":231,
    "gn:feature_class":"P",
    "gn:feature_code":"PPL",
    "gn:name":"Ledong",
    "gn:population":0,
    "gn:timezone":"Asia/Shanghai",
    "iso:country":"CN",
    "name:zho_x_preferred":[
        "\u52d2\u4e1c"
    ],
    "wof:name":"Ledong",
    "wof:placetype":"locality"
},
  "geometry": {"coordinates":[110.012,25.7795],"type":"Point"}
}