{
  "type": "Feature",
  "properties": {
    "gn:admin1_code":"3.0",
    "gn:asciiname":"Sikeng",
    "gn:country_code":"CN",
    "gn:dem":302,
    "gn:feature_class":"P",
    "gn:feature_code":"PPL",
    "gn:name":"Sikeng",
    "gn:population":0,
    "gn:timezone":"Asia/Shanghai",
    "iso:country":"CN",
    "name:und_x_variant":[
        "\u5bfa\u5751"
    ],
    "wof:name":"Sikeng",
    "wof:placetype":"locality"
},
  "geometry": {"coordinates":[115.68403000000001,26.63551],"type":"Point"}
}