{
  "type": "Feature",
  "properties": {
    "gn:admin1_code":"9",
    "gn:asciiname":"Houzixiang",
    "gn:country_code":"CN",
    "gn:dem":61,
    "gn:feature_class":"P",
    "gn:feature_code":"PPL",
    "gn:name":"Houzixiang",
    "gn:population":0,
    "gn:timezone":"Asia/Shanghai",
    "iso:country":"CN",
    "name:zho_x_preferred":[
        "\u540e\u5b50\u53a2"
    ],
    "wof:name":"Houzixiang",
    "wof:placetype":"locality"
},
  "geometry": {"coordinates":[114.827,35.3867],"type":"Point"}
}