{
  "type": "Feature",
  "properties": {
    "gn:admin1_code":"16.0",
    "gn:asciiname":"Lixin",
    "gn:country_code":"CN",
    "gn:dem":145,
    "gn:feature_class":"P",
    "gn:feature_code":"PPL",
    "gn:name":"Lixin",
    "gn:population":0,
    "gn:timezone":"Asia/Shanghai",
    "iso:country":"CN",
    "name:ceb_x_preferred":[
        "Lixin"
    ],
    "name:deu_x_preferred":[
        "Lixin"
    ],
    "name:zho_x_preferred":[
        "\u7acb\u65b0"
    ],
    "wof:name":"Lixin",
    "wof:placetype":"locality"
},
  "geometry": {"coordinates":[109.91,24.22],"type":"Point"}
}