{
  "type": "Feature",
  "properties": {
    "gn:admin1_code":"19.0",
    "gn:asciiname":"Dabeishan",
    "gn:country_code":"CN",
    "gn:dem":56,
    "gn:feature_class":"P",
    "gn:feature_code":"PPL",
    "gn:name":"Dabeishan",
    "gn:population":0,
    "gn:timezone":"Asia/Shanghai",
    "iso:country":"CN",
    "name:und_x_variant":[
        "\u5927\u5317\u5c71"
    ],
    "wof:name":"Dabeishan",
    "wof:placetype":"locality"
},
  "geometry": {"coordinates":[122.25528,40.24548],"type":"Point"}
}