{
  "type": "Feature",
  "properties": {
    "gn:admin1_code":"24",
    "gn:asciiname":"Hanyang",
    "gn:cc2":"CN",
    "gn:country_code":"CN",
    "gn:dem":352,
    "gn:feature_class":"P",
    "gn:feature_code":"PPL",
    "gn:name":"Hanyang",
    "gn:population":0,
    "gn:timezone":"Asia/Shanghai",
    "iso:country":"CN",
    "name:ceb_x_preferred":[
        "Hanyang"
    ],
    "name:ces_x_preferred":[
        "Chan-jang"
    ],
    "name:deu_x_preferred":[
        "Hanyang"
    ],
    "name:kor_x_preferred":[
        "\ud55c\uc591"
    ],
    "name:nor_x_preferred":[
        "Hanyang"
    ],
    "name:swe_x_preferred":[
        "Hanyang"
    ],
    "name:und_x_variant":[
        "Hanyangzhen",
        "Han-yang-chen"
    ],
    "name:vie_x_preferred":[
        "H\u00e1n D\u01b0\u01a1ng"
    ],
    "wof:name":"Hanyang",
    "wof:placetype":"locality"
},
  "geometry": {"coordinates":[110.29917,34.76833],"type":"Point"}
}