{
  "type": "Feature",
  "properties": {
    "gn:admin1_code":"24",
    "gn:asciiname":"Hanyang",
    "gn:cc2":"CN",
    "gn:country_code":"CN",
    "gn:dem":352,
    "gn:feature_class":"P",
    "gn:feature_code":"PPL",
    "gn:name":"Hanyang",
    "gn:population":0,
    "gn:timezone":"Asia/Shanghai",
    "iso:country":"CN",
    "name:und_x_variant":[
        "Hanyangzhen",
        "Han-yang-chen",
        "Hanyang"
    ],
    "wof:name":"Hanyang",
    "wof:placetype":"locality"
},
  "geometry": {"coordinates":[110.29917,34.76833],"type":"Point"}
}