{
  "type": "Feature",
  "properties": {
    "gn:admin1_code":"3.0",
    "gn:asciiname":"Kongjia",
    "gn:country_code":"CN",
    "gn:dem":213,
    "gn:feature_class":"P",
    "gn:feature_code":"PPL",
    "gn:name":"Kongjia",
    "gn:population":0,
    "gn:timezone":"Asia/Shanghai",
    "iso:country":"CN",
    "name:zho_x_preferred":[
        "\u5b54\u5bb6"
    ],
    "wof:name":"Kongjia",
    "wof:placetype":"locality"
},
  "geometry": {"coordinates":[117.45422000000001,28.15764],"type":"Point"}
}