{
  "type": "Feature",
  "properties": {
    "gn:admin1_code":"18",
    "gn:asciiname":"Xiaofengyan",
    "gn:country_code":"CN",
    "gn:dem":963,
    "gn:feature_class":"P",
    "gn:feature_code":"PPL",
    "gn:name":"Xiaofengyan",
    "gn:population":0,
    "gn:timezone":"Asia/Shanghai",
    "iso:country":"CN",
    "name:zho_x_preferred":[
        "\u5c0f\u4e30\u5ca9"
    ],
    "wof:name":"Xiaofengyan",
    "wof:placetype":"locality"
},
  "geometry": {"coordinates":[108.032,27.9355],"type":"Point"}
}