{
  "type": "Feature",
  "properties": {
    "gn:admin1_code":"4.0",
    "gn:asciiname":"Songjiapeng",
    "gn:country_code":"CN",
    "gn:dem":7,
    "gn:feature_class":"P",
    "gn:feature_code":"PPL",
    "gn:name":"Songjiapeng",
    "gn:population":0,
    "gn:timezone":"Asia/Shanghai",
    "iso:country":"CN",
    "name:zho_x_preferred":[
        "Songjiapeng"
    ],
    "name:zho_x_variant":[
        "\u5b8b\u5bb6\u68da"
    ],
    "wof:name":"Songjiapeng",
    "wof:placetype":"locality"
},
  "geometry": {"coordinates":[119.26376,33.45425],"type":"Point"}
}