{
  "type": "Feature",
  "properties": {
    "gn:admin1_code":"24.0",
    "gn:asciiname":"Jinjialicun",
    "gn:country_code":"CN",
    "gn:dem":1193,
    "gn:feature_class":"P",
    "gn:feature_code":"PPL",
    "gn:name":"Jinjialicun",
    "gn:population":0,
    "gn:timezone":"Asia/Shanghai",
    "iso:country":"CN",
    "name:zho_x_preferred":[
        "\u9773\u5bb6\u91cc\u6751"
    ],
    "wof:name":"Jinjialicun",
    "wof:placetype":"locality"
},
  "geometry": {"coordinates":[110.79982,38.0557],"type":"Point"}
}