{
  "type": "Feature",
  "properties": {
    "gn:admin1_code":"29.0",
    "gn:asciiname":"Shangyikuayi",
    "gn:country_code":"CN",
    "gn:dem":1482,
    "gn:feature_class":"P",
    "gn:feature_code":"PPL",
    "gn:name":"Shangyikuayi",
    "gn:population":0,
    "gn:timezone":"Asia/Shanghai",
    "iso:country":"CN",
    "name:zho_x_preferred":[
        "\u4e0a\u4ee5\u57ae\u8863"
    ],
    "wof:name":"Shangyikuayi",
    "wof:placetype":"locality"
},
  "geometry": {"coordinates":[104.42100000000001,24.8948],"type":"Point"}
}