{
  "type": "Feature",
  "properties": {
    "gn:admin1_code":"24.0",
    "gn:asciiname":"Caochengcun",
    "gn:country_code":"CN",
    "gn:dem":933,
    "gn:feature_class":"P",
    "gn:feature_code":"PPL",
    "gn:name":"Caochengcun",
    "gn:population":0,
    "gn:timezone":"Asia/Shanghai",
    "iso:country":"CN",
    "name:zho_x_preferred":[
        "\u66f9\u57ce\u6751"
    ],
    "wof:name":"Caochengcun",
    "wof:placetype":"locality"
},
  "geometry": {"coordinates":[110.92513,36.62947],"type":"Point"}
}