{
  "type": "Feature",
  "properties": {
    "gn:admin1_code":"18",
    "gn:asciiname":"Datuoba",
    "gn:country_code":"CN",
    "gn:dem":449,
    "gn:feature_class":"P",
    "gn:feature_code":"PPL",
    "gn:name":"Datuoba",
    "gn:population":0,
    "gn:timezone":"Asia/Shanghai",
    "iso:country":"CN",
    "name:zho_x_preferred":[
        "\u5927\u5768\u575d"
    ],
    "wof:name":"Datuoba",
    "wof:placetype":"locality"
},
  "geometry": {"coordinates":[108.307,28.4145],"type":"Point"}
}