{
  "type": "Feature",
  "properties": {
    "gn:admin1_code":"30.0",
    "gn:asciiname":"Xiaqishan",
    "gn:country_code":"CN",
    "gn:dem":143,
    "gn:feature_class":"P",
    "gn:feature_code":"PPL",
    "gn:name":"Xiaqishan",
    "gn:population":0,
    "gn:timezone":"Asia/Shanghai",
    "iso:country":"CN",
    "name:und_x_variant":[
        "\u4e0b\u5c90\u5c71"
    ],
    "name:zho_x_preferred":[
        "\u4e0b\u5c90\u5c71"
    ],
    "wof:name":"Xiaqishan",
    "wof:placetype":"locality"
},
  "geometry": {"coordinates":[114.92703,23.47614],"type":"Point"}
}