{
  "type": "Feature",
  "properties": {
    "gn:admin1_code":"25.0",
    "gn:asciiname":"Zangjiazhuang",
    "gn:country_code":"CN",
    "gn:dem":56,
    "gn:feature_class":"P",
    "gn:feature_code":"PPLA4",
    "gn:name":"Zangjiazhuang",
    "gn:population":0,
    "gn:timezone":"Asia/Shanghai",
    "iso:country":"CN",
    "name:und_x_variant":[
        "Tsang-ko-chuang",
        "Zanggezhuang",
        "Tsang-chia-chuang",
        "Zangjiazhuang Zhen",
        "Zangjiazhuang"
    ],
    "name:zho_x_preferred":[
        "\u81e7\u5bb6\u5e84"
    ],
    "name:zho_x_variant":[
        "\u81e7\u5bb6\u5e84\u9547"
    ],
    "wof:name":"Zangjiazhuang",
    "wof:placetype":"locality"
},
  "geometry": {"coordinates":[120.98528,37.46611],"type":"Point"}
}