{
  "type": "Feature",
  "properties": {
    "gn:admin1_code":"20",
    "gn:asciiname":"Gegen Jo Sum",
    "gn:cc2":"CN",
    "gn:country_code":"CN",
    "gn:dem":1029,
    "gn:feature_class":"P",
    "gn:feature_code":"PPL",
    "gn:name":"Gegen Jo Sum",
    "gn:population":0,
    "gn:timezone":"Asia/Shanghai",
    "iso:country":"CN",
    "name:und_x_variant":[
        "Gegen Jo",
        "Gegen Jo Sum"
    ],
    "wof:name":"Gegen Jo Sum",
    "wof:placetype":"locality"
},
  "geometry": {"coordinates":[108.04861,40.81694],"type":"Point"}
}