{
  "type": "Feature",
  "properties": {
    "gn:admin1_code":"15.0",
    "gn:asciiname":"Dongjiangshui",
    "gn:country_code":"CN",
    "gn:dem":1032,
    "gn:feature_class":"P",
    "gn:feature_code":"PPL",
    "gn:name":"Dongjiangshui",
    "gn:population":0,
    "gn:timezone":"Asia/Shanghai",
    "iso:country":"CN",
    "name:zho_x_preferred":[
        "\u4e1c\u6c5f\u6c34"
    ],
    "wof:name":"Dongjiangshui",
    "wof:placetype":"locality"
},
  "geometry": {"coordinates":[104.93993,33.37717],"type":"Point"}
}