{
  "type": "Feature",
  "properties": {
    "gn:admin1_code":"5.0",
    "gn:asciiname":"Maolintun",
    "gn:country_code":"CN",
    "gn:dem":165,
    "gn:feature_class":"P",
    "gn:feature_code":"PPL",
    "gn:name":"Maolintun",
    "gn:population":0,
    "gn:timezone":"Asia/Shanghai",
    "iso:country":"CN",
    "name:zho_x_preferred":[
        "\u8302\u6797\u5c6f"
    ],
    "wof:name":"Maolintun",
    "wof:placetype":"locality"
},
  "geometry": {"coordinates":[122.33607000000001,45.25165],"type":"Point"}
}