{
  "type": "Feature",
  "properties": {
    "gn:admin1_code":"11",
    "gn:asciiname":"Jiedianzi",
    "gn:country_code":"CN",
    "gn:dem":201,
    "gn:feature_class":"P",
    "gn:feature_code":"PPL",
    "gn:name":"Jiedianzi",
    "gn:population":0,
    "gn:timezone":"Asia/Shanghai",
    "iso:country":"CN",
    "name:und_x_variant":[
        "\u8857\u5e97\u5b50"
    ],
    "wof:name":"Jiedianzi",
    "wof:placetype":"locality"
},
  "geometry": {"coordinates":[111.42892000000001,29.69862],"type":"Point"}
}