{
  "type": "Feature",
  "properties": {
    "gn:admin1_code":"12.0",
    "gn:asciiname":"Sangqiaochong",
    "gn:country_code":"CN",
    "gn:dem":196,
    "gn:feature_class":"P",
    "gn:feature_code":"PPL",
    "gn:name":"Sangqiaochong",
    "gn:population":0,
    "gn:timezone":"Asia/Shanghai",
    "iso:country":"CN",
    "name:zho_x_preferred":[
        "Sangqiaochong"
    ],
    "name:zho_x_variant":[
        "\u6851\u6865\u51b2"
    ],
    "wof:name":"Sangqiaochong",
    "wof:placetype":"locality"
},
  "geometry": {"coordinates":[111.70157,30.99613],"type":"Point"}
}