{
  "type": "Feature",
  "properties": {
    "gn:admin1_code":"2.0",
    "gn:asciiname":"Chairuowan",
    "gn:country_code":"CN",
    "gn:dem":473,
    "gn:feature_class":"P",
    "gn:feature_code":"PPL",
    "gn:name":"Chairuowan",
    "gn:population":0,
    "gn:timezone":"Asia/Shanghai",
    "iso:country":"CN",
    "name:zho_x_preferred":[
        "\u67f4\u7bac\u6e7e"
    ],
    "wof:name":"Chairuowan",
    "wof:placetype":"locality"
},
  "geometry": {"coordinates":[120.72751,29.74515],"type":"Point"}
}