{
  "type": "Feature",
  "properties": {
    "gn:admin1_code":"3.0",
    "gn:asciiname":"Guanzhou Xinnongcun",
    "gn:country_code":"CN",
    "gn:dem":22,
    "gn:feature_class":"P",
    "gn:feature_code":"PPL",
    "gn:name":"Guanzhou Xinnongcun",
    "gn:population":0,
    "gn:timezone":"Asia/Shanghai",
    "iso:country":"CN",
    "name:und_x_variant":[
        "\u89c2\u6d32\u65b0\u519c\u6751"
    ],
    "wof:name":"Guanzhou Xinnongcun",
    "wof:placetype":"locality"
},
  "geometry": {"coordinates":[115.85458,28.64049],"type":"Point"}
}