{
  "type": "Feature",
  "properties": {
    "gn:admin1_code":"18",
    "gn:asciiname":"Maocaodi",
    "gn:country_code":"CN",
    "gn:dem":1864,
    "gn:feature_class":"P",
    "gn:feature_code":"PPL",
    "gn:name":"Maocaodi",
    "gn:population":0,
    "gn:timezone":"Asia/Shanghai",
    "iso:country":"CN",
    "name:zho_x_preferred":[
        "\u8305\u8349\u5730"
    ],
    "wof:name":"Maocaodi",
    "wof:placetype":"locality"
},
  "geometry": {"coordinates":[104.684,25.4996],"type":"Point"}
}