{
  "type": "Feature",
  "properties": {
    "gn:admin1_code":"3",
    "gn:asciiname":"Qingcaozhou",
    "gn:country_code":"CN",
    "gn:dem":73,
    "gn:feature_class":"P",
    "gn:feature_code":"PPL",
    "gn:name":"Qingcaozhou",
    "gn:population":0,
    "gn:timezone":"Asia/Shanghai",
    "iso:country":"CN",
    "name:zho_x_preferred":[
        "\u9752\u8349\u6d32"
    ],
    "wof:name":"Qingcaozhou",
    "wof:placetype":"locality"
},
  "geometry": {"coordinates":[114.73699999999999,26.6121],"type":"Point"}
}