{
  "type": "Feature",
  "properties": {
    "gn:admin1_code":"19.0",
    "gn:asciiname":"Jiaogantun",
    "gn:country_code":"CN",
    "gn:dem":43,
    "gn:feature_class":"P",
    "gn:feature_code":"PPL",
    "gn:name":"Jiaogantun",
    "gn:population":0,
    "gn:timezone":"Asia/Shanghai",
    "iso:country":"CN",
    "name:und_x_variant":[
        "\u4ea4\u5e72\u5c6f"
    ],
    "wof:name":"Jiaogantun",
    "wof:placetype":"locality"
},
  "geometry": {"coordinates":[122.61658,40.74386],"type":"Point"}
}