{
  "type": "Feature",
  "properties": {
    "gn:admin1_code":"15.0",
    "gn:asciiname":"Wangjiawan",
    "gn:country_code":"CN",
    "gn:dem":2015,
    "gn:feature_class":"P",
    "gn:feature_code":"PPL",
    "gn:name":"Wangjiawan",
    "gn:population":0,
    "gn:timezone":"Asia/Shanghai",
    "iso:country":"CN",
    "name:deu_x_preferred":[
        "Wangjiawan"
    ],
    "name:und_x_variant":[
        "\u738b\u5bb6\u6e7e"
    ],
    "wof:name":"Wangjiawan",
    "wof:placetype":"locality"
},
  "geometry": {"coordinates":[105.13437,35.23573],"type":"Point"}
}