{
  "type": "Feature",
  "properties": {
    "gn:admin1_code":"15.0",
    "gn:asciiname":"Erbaihu",
    "gn:country_code":"CN",
    "gn:dem":1788,
    "gn:feature_class":"P",
    "gn:feature_code":"PPL",
    "gn:name":"Erbaihu",
    "gn:population":0,
    "gn:timezone":"Asia/Shanghai",
    "iso:country":"CN",
    "name:zho_x_preferred":[
        "\u4e8c\u767e\u6237"
    ],
    "wof:name":"Erbaihu",
    "wof:placetype":"locality"
},
  "geometry": {"coordinates":[104.991,36.1648],"type":"Point"}
}