{
  "type": "Feature",
  "properties": {
    "gn:admin1_code":"7.0",
    "gn:asciiname":"Kungang",
    "gn:country_code":"CN",
    "gn:dem":553,
    "gn:feature_class":"P",
    "gn:feature_code":"PPL",
    "gn:name":"Kungang",
    "gn:population":0,
    "gn:timezone":"Asia/Shanghai",
    "iso:country":"CN",
    "name:und_x_variant":[
        "\u6606\u5c97"
    ],
    "name:zho_x_preferred":[
        "\u6606\u5c97"
    ],
    "wof:name":"Kungang",
    "wof:placetype":"locality"
},
  "geometry": {"coordinates":[116.54286999999999,26.30293],"type":"Point"}
}