{
  "type": "Feature",
  "properties": {
    "gn:admin1_code":"11.0",
    "gn:asciiname":"Zeluo",
    "gn:country_code":"CN",
    "gn:dem":659,
    "gn:feature_class":"P",
    "gn:feature_code":"PPL",
    "gn:name":"Zeluo",
    "gn:population":0,
    "gn:timezone":"Asia/Shanghai",
    "iso:country":"CN",
    "name:zho_x_preferred":[
        "\u6cfd\u843d"
    ],
    "wof:name":"Zeluo",
    "wof:placetype":"locality"
},
  "geometry": {"coordinates":[109.58295,28.60979],"type":"Point"}
}