{
  "type": "Feature",
  "properties": {
    "gn:admin1_code":"7",
    "gn:asciiname":"Ximenli",
    "gn:country_code":"CN",
    "gn:dem":732,
    "gn:feature_class":"P",
    "gn:feature_code":"PPL",
    "gn:name":"Ximenli",
    "gn:population":0,
    "gn:timezone":"Asia/Shanghai",
    "iso:country":"CN",
    "name:und_x_variant":[
        "\u6eaa\u95e8\u91cc"
    ],
    "wof:name":"Ximenli",
    "wof:placetype":"locality"
},
  "geometry": {"coordinates":[119.91443999999998,27.20444],"type":"Point"}
}