{
  "type": "Feature",
  "properties": {
    "gn:admin1_code":"11.0",
    "gn:asciiname":"Jiaotuo",
    "gn:country_code":"CN",
    "gn:dem":64,
    "gn:feature_class":"P",
    "gn:feature_code":"PPL",
    "gn:name":"Jiaotuo",
    "gn:population":0,
    "gn:timezone":"Asia/Shanghai",
    "iso:country":"CN",
    "name:zho_x_preferred":[
        "\u86df\u6258"
    ],
    "wof:name":"Jiaotuo",
    "wof:placetype":"locality"
},
  "geometry": {"coordinates":[112.80714,27.82733],"type":"Point"}
}