{
  "type": "Feature",
  "properties": {
    "gn:admin1_code":"4.0",
    "gn:asciiname":"Shadong Yizu",
    "gn:country_code":"CN",
    "gn:dem":4,
    "gn:feature_class":"P",
    "gn:feature_code":"PPLF",
    "gn:name":"Shadong Yizu",
    "gn:population":0,
    "gn:timezone":"Asia/Shanghai",
    "iso:country":"CN",
    "name:zho_x_preferred":[
        "Shadong Yizu"
    ],
    "name:zho_x_variant":[
        "\u6c99\u4e1c\u4e00\u7ec4"
    ],
    "wof:name":"Shadong Yizu",
    "wof:placetype":"locality"
},
  "geometry": {"coordinates":[121.39485000000001,32.14245],"type":"Point"}
}