{
  "type": "Feature",
  "properties": {
    "gn:admin1_code":"12",
    "gn:asciiname":"Meichuan",
    "gn:country_code":"CN",
    "gn:dem":45,
    "gn:feature_class":"P",
    "gn:feature_code":"PPLA4",
    "gn:name":"Meichuan",
    "gn:population":0,
    "gn:timezone":"Asia/Shanghai",
    "iso:country":"CN",
    "name:und_x_variant":[
        "Kwangchi",
        "Mei-ch\u2019uan-chen",
        "Kuang-chi-hsien",
        "Kuang-chi",
        "Meichuan",
        "Meichuan Zhen",
        "\u6885\u5ddd\u9547"
    ],
    "name:zho_x_preferred":[
        "\u6885\u5ddd"
    ],
    "name:zho_x_variant":[
        "\u6885\u5ddd\u9547"
    ],
    "wof:name":"Meichuan",
    "wof:placetype":"locality"
},
  "geometry": {"coordinates":[115.59596999999999,30.12946],"type":"Point"}
}