{
  "type": "Feature",
  "properties": {
    "gn:admin1_code":"16.0",
    "gn:asciiname":"Lalu",
    "gn:country_code":"CN",
    "gn:dem":582,
    "gn:feature_class":"P",
    "gn:feature_code":"PPL",
    "gn:name":"Lalu",
    "gn:population":0,
    "gn:timezone":"Asia/Shanghai",
    "iso:country":"CN",
    "name:ceb_x_preferred":[
        "Lalu"
    ],
    "name:swe_x_preferred":[
        "Lalu"
    ],
    "name:zho_x_preferred":[
        "\u62c9\u8def"
    ],
    "wof:name":"Lalu",
    "wof:placetype":"locality"
},
  "geometry": {"coordinates":[108.501,24.798],"type":"Point"}
}