{
  "type": "Feature",
  "properties": {
    "gn:admin1_code":"32.0",
    "gn:asciiname":"Ciguwan",
    "gn:country_code":"CN",
    "gn:dem":660,
    "gn:feature_class":"P",
    "gn:feature_code":"PPL",
    "gn:name":"Ciguwan",
    "gn:population":0,
    "gn:timezone":"Asia/Shanghai",
    "iso:country":"CN",
    "name:zho_x_preferred":[
        "\u8328\u8c37\u6e7e"
    ],
    "wof:name":"Ciguwan",
    "wof:placetype":"locality"
},
  "geometry": {"coordinates":[103.991,28.9348],"type":"Point"}
}