{
  "type": "Feature",
  "properties": {
    "gn:admin1_code":"12.0",
    "gn:asciiname":"Panshici",
    "gn:country_code":"CN",
    "gn:dem":146,
    "gn:feature_class":"P",
    "gn:feature_code":"PPL",
    "gn:name":"Panshici",
    "gn:population":0,
    "gn:timezone":"Asia/Shanghai",
    "iso:country":"CN",
    "name:zho_x_preferred":[
        "\u6f58\u6c0f\u7960"
    ],
    "wof:name":"Panshici",
    "wof:placetype":"locality"
},
  "geometry": {"coordinates":[115.5595,30.96439],"type":"Point"}
}