{
  "type": "Feature",
  "properties": {
    "gn:admin1_code":"10",
    "gn:asciiname":"Pingdingshan",
    "gn:country_code":"CN",
    "gn:dem":787,
    "gn:feature_class":"P",
    "gn:feature_code":"PPL",
    "gn:name":"Pingdingshan",
    "gn:population":0,
    "gn:timezone":"Asia/Shanghai",
    "iso:country":"CN",
    "name:afr_x_preferred":[
        "Pingdingshan"
    ],
    "name:ara_x_preferred":[
        "\u0628\u064a\u0646\u063a\u062f\u064a\u0646\u063a\u0634\u0627\u0646"
    ],
    "name:bul_x_preferred":[
        "\u041f\u0438\u043d\u0434\u0438\u043d\u0448\u0430\u043d"
    ],
    "name:cdo_x_preferred":[
        "B\u00ecng-d\u012bng-s\u0103ng"
    ],
    "name:ceb_x_preferred":[
        "Pingdingshan"
    ],
    "name:ces_x_preferred":[
        "Pching-ting-\u0161an"
    ],
    "name:dan_x_preferred":[
        "Pingdingshan"
    ],
    "name:deu_x_preferred":[
        "Pingdingshan"
    ],
    "name:epo_x_preferred":[
        "Pingding\u015dano"
    ],
    "name:eus_x_preferred":[
        "Pingdingshan"
    ],
    "name:fas_x_preferred":[
        "\u067e\u06cc\u0646\u06af\u062f\u06cc\u0646\u06af\u0634\u0627\u0646"
    ],
    "name:fin_x_preferred":[
        "Pingdingshan"
    ],
    "name:fra_x_preferred":[
        "Pingdingshan"
    ],
    "name:ind_x_preferred":[
        "Pingdingshan"
    ],
    "name:ita_x_preferred":[
        "Pingdingshan"
    ],
    "name:jpn_x_preferred":[
        "\u5e73\u9802\u5c71\u5e02"
    ],
    "name:kik_x_preferred":[
        "Pingdingshan"
    ],
    "name:kor_x_preferred":[
        "\ud551\ub529\uc0b0\uc2dc"
    ],
    "name:mlg_x_preferred":[
        "Pingdingshan"
    ],
    "name:nld_x_preferred":[
        "Pingdingshan"
    ],
    "name:nno_x_preferred":[
        "Pingdingshan"
    ],
    "name:nor_x_preferred":[
        "Pingdingshan"
    ],
    "name:pam_x_preferred":[
        "Pingdingshan"
    ],
    "name:pol_x_preferred":[
        "Pingdingshan"
    ],
    "name:por_x_preferred":[
        "Pingdingshan"
    ],
    "name:rus_x_preferred":[
        "\u041f\u0438\u043d\u0434\u0438\u043d\u0448\u0430\u043d\u044c"
    ],
    "name:sco_x_preferred":[
        "Pingdingshan"
    ],
    "name:spa_x_preferred":[
        "Pingdingshan"
    ],
    "name:srp_x_preferred":[
        "\u041f\u0438\u043d\u0433\u0434\u0438\u043d\u0433\u0448\u0430\u043d"
    ],
    "name:swe_x_preferred":[
        "Pingdingshan"
    ],
    "name:tur_x_preferred":[
        "Pingdingshan"
    ],
    "name:ukr_x_preferred":[
        "\u041f\u0456\u043d\u0434\u0456\u043d\u0448\u0430\u043d\u044c"
    ],
    "name:urd_x_preferred":[
        "\u067e\u0646\u06af\u0688\u0646\u06af\u0634\u0627\u0646"
    ],
    "name:war_x_preferred":[
        "Pingdingshan"
    ],
    "name:wuu_x_preferred":[
        "\u5e73\u9876\u5c71\u5e02"
    ],
    "name:zho_x_preferred":[
        "\u5e73\u9876\u5c71"
    ],
    "name:zho_x_variant":[
        "\u5e73\u9876\u5c71\u5e02"
    ],
    "wof:name":"Pingdingshan",
    "wof:placetype":"locality"
},
  "geometry": {"coordinates":[117.9295,41.50225],"type":"Point"}
}