{
  "type": "Feature",
  "properties": {
    "gn:admin1_code":"8.0",
    "gn:asciiname":"Yingyong",
    "gn:country_code":"CN",
    "gn:dem":147,
    "gn:feature_class":"P",
    "gn:feature_code":"PPL",
    "gn:name":"Yingyong",
    "gn:population":0,
    "gn:timezone":"Asia/Shanghai",
    "iso:country":"CN",
    "name:zho_x_preferred":[
        "\u82f1\u52c7"
    ],
    "wof:name":"Yingyong",
    "wof:placetype":"locality"
},
  "geometry": {"coordinates":[125.23017,46.46229],"type":"Point"}
}