{
  "type": "Feature",
  "properties": {
    "gn:admin1_code":"15.0",
    "gn:asciiname":"Zhangjia Gouwan",
    "gn:country_code":"CN",
    "gn:dem":2538,
    "gn:feature_class":"P",
    "gn:feature_code":"PPL",
    "gn:name":"Zhangjia Gouwan",
    "gn:population":0,
    "gn:timezone":"Asia/Shanghai",
    "iso:country":"CN",
    "name:zho_x_preferred":[
        "\u5f20\u5bb6\u6c9f\u6e7e"
    ],
    "wof:name":"Zhangjia Gouwan",
    "wof:placetype":"locality"
},
  "geometry": {"coordinates":[100.88200000000001,38.3287],"type":"Point"}
}