{
  "type": "Feature",
  "properties": {
    "gn:admin1_code":"14.0",
    "gn:asciiname":"Jiaregang",
    "gn:country_code":"CN",
    "gn:dem":4322,
    "gn:feature_class":"P",
    "gn:feature_code":"PPL",
    "gn:name":"Jiaregang",
    "gn:population":0,
    "gn:timezone":"Asia/Urumqi",
    "iso:country":"CN",
    "name:zho_x_preferred":[
        "\u7532\u70ed\u5c97"
    ],
    "wof:name":"Jiaregang",
    "wof:placetype":"locality"
},
  "geometry": {"coordinates":[91.83193,30.44553],"type":"Point"}
}