{
  "type": "Feature",
  "properties": {
    "gn:admin1_code":"12.0",
    "gn:asciiname":"Laoshuidong",
    "gn:country_code":"CN",
    "gn:dem":987,
    "gn:feature_class":"P",
    "gn:feature_code":"PPL",
    "gn:name":"Laoshuidong",
    "gn:population":0,
    "gn:timezone":"Asia/Shanghai",
    "iso:country":"CN",
    "name:zho_x_preferred":[
        "\u8001\u6c34\u6d1e"
    ],
    "wof:name":"Laoshuidong",
    "wof:placetype":"locality"
},
  "geometry": {"coordinates":[110.06662,30.54599],"type":"Point"}
}