{
  "type": "Feature",
  "properties": {
    "gn:admin1_code":"2.0",
    "gn:asciiname":"Shanglinkou",
    "gn:country_code":"CN",
    "gn:dem":64,
    "gn:feature_class":"P",
    "gn:feature_code":"PPL",
    "gn:name":"Shanglinkou",
    "gn:population":0,
    "gn:timezone":"Asia/Shanghai",
    "iso:country":"CN",
    "name:zho_x_preferred":[
        "\u4e0a\u6797\u53e3"
    ],
    "wof:name":"Shanglinkou",
    "wof:placetype":"locality"
},
  "geometry": {"coordinates":[120.44381,29.97271],"type":"Point"}
}