{
  "type": "Feature",
  "properties": {
    "gn:admin1_code":"1.0",
    "gn:asciiname":"Jinshancun",
    "gn:country_code":"CN",
    "gn:dem":21,
    "gn:feature_class":"P",
    "gn:feature_code":"PPL",
    "gn:name":"Jinshancun",
    "gn:population":0,
    "gn:timezone":"Asia/Shanghai",
    "iso:country":"CN",
    "name:zho_x_preferred":[
        "\u91d1\u5c71\u6751"
    ],
    "wof:name":"Jinshancun",
    "wof:placetype":"locality"
},
  "geometry": {"coordinates":[117.63454,30.64664],"type":"Point"}
}