{
  "type": "Feature",
  "properties": {
    "gn:admin1_code":"25",
    "gn:asciiname":"Shahezi",
    "gn:country_code":"CN",
    "gn:dem":65,
    "gn:feature_class":"P",
    "gn:feature_code":"PPL",
    "gn:name":"Shahezi",
    "gn:population":0,
    "gn:timezone":"Asia/Shanghai",
    "iso:country":"CN",
    "name:zho_x_preferred":[
        "\u6c99\u6cb3\u5b50"
    ],
    "wof:name":"Shahezi",
    "wof:placetype":"locality"
},
  "geometry": {"coordinates":[117.535,34.8591],"type":"Point"}
}