{
  "type": "Feature",
  "properties": {
    "gn:admin1_code":"29.0",
    "gn:asciiname":"Modang",
    "gn:country_code":"CN",
    "gn:dem":1327,
    "gn:feature_class":"P",
    "gn:feature_code":"PPL",
    "gn:name":"Modang",
    "gn:population":0,
    "gn:timezone":"Asia/Shanghai",
    "iso:country":"CN",
    "name:zho_x_preferred":[
        "\u83ab\u515a"
    ],
    "wof:name":"Modang",
    "wof:placetype":"locality"
},
  "geometry": {"coordinates":[101.913,25.7383],"type":"Point"}
}