{
  "type": "Feature",
  "properties": {
    "gn:admin1_code":"3",
    "gn:asciiname":"Xiangxingwan",
    "gn:country_code":"CN",
    "gn:dem":278,
    "gn:feature_class":"P",
    "gn:feature_code":"PPL",
    "gn:name":"Xiangxingwan",
    "gn:population":0,
    "gn:timezone":"Asia/Shanghai",
    "iso:country":"CN",
    "name:zho_x_preferred":[
        "\u8c61\u5f62\u6e7e"
    ],
    "wof:name":"Xiangxingwan",
    "wof:placetype":"locality"
},
  "geometry": {"coordinates":[114.215,26.4176],"type":"Point"}
}