{
  "type": "Feature",
  "properties": {
    "gn:admin1_code":"10",
    "gn:asciiname":"Chadao",
    "gn:country_code":"CN",
    "gn:dem":1477,
    "gn:feature_class":"P",
    "gn:feature_code":"PPL",
    "gn:name":"Chadao",
    "gn:population":0,
    "gn:timezone":"Asia/Shanghai",
    "iso:country":"CN",
    "name:zho_x_preferred":[
        "\u5c94\u9053"
    ],
    "wof:name":"Chadao",
    "wof:placetype":"locality"
},
  "geometry": {"coordinates":[114.65644,39.63236],"type":"Point"}
}