{
  "type": "Feature",
  "properties": {
    "gn:admin1_code":"14.0",
    "gn:asciiname":"Peiyang",
    "gn:country_code":"CN",
    "gn:dem":4161,
    "gn:feature_class":"P",
    "gn:feature_code":"PPL",
    "gn:name":"Peiyang",
    "gn:population":0,
    "gn:timezone":"Asia/Shanghai",
    "iso:country":"CN",
    "name:zho_x_preferred":[
        "\u57f9\u6768"
    ],
    "wof:name":"Peiyang",
    "wof:placetype":"locality"
},
  "geometry": {"coordinates":[79.7944,31.681],"type":"Point"}
}