{
  "type": "Feature",
  "properties": {
    "gn:admin1_code":"26.0",
    "gn:asciiname":"Yuanzhuang",
    "gn:country_code":"CN",
    "gn:dem":1621,
    "gn:feature_class":"P",
    "gn:feature_code":"PPL",
    "gn:name":"Yuanzhuang",
    "gn:population":0,
    "gn:timezone":"Asia/Shanghai",
    "iso:country":"CN",
    "name:zho_x_preferred":[
        "\u5143\u5e84"
    ],
    "wof:name":"Yuanzhuang",
    "wof:placetype":"locality"
},
  "geometry": {"coordinates":[108.70921,37.22248],"type":"Point"}
}