{
  "type": "Feature",
  "properties": {
    "gn:admin1_code":"33.0",
    "gn:asciiname":"Huoguang",
    "gn:country_code":"CN",
    "gn:dem":731,
    "gn:feature_class":"P",
    "gn:feature_code":"PPL",
    "gn:name":"Huoguang",
    "gn:population":0,
    "gn:timezone":"Asia/Shanghai",
    "iso:country":"CN",
    "name:zho_x_preferred":[
        "\u706b\u5149"
    ],
    "wof:name":"Huoguang",
    "wof:placetype":"locality"
},
  "geometry": {"coordinates":[108.52893,29.15052],"type":"Point"}
}