{
  "type": "Feature",
  "properties": {
    "gn:admin1_code":"10.0",
    "gn:asciiname":"Qiji",
    "gn:country_code":"CN",
    "gn:dem":85,
    "gn:feature_class":"P",
    "gn:feature_code":"PPL",
    "gn:name":"Qiji",
    "gn:population":0,
    "gn:timezone":"Asia/Shanghai",
    "iso:country":"CN",
    "name:ceb_x_preferred":[
        "Qiji"
    ],
    "name:swe_x_preferred":[
        "Qiji"
    ],
    "name:und_x_variant":[
        "\u4e03\u5409"
    ],
    "wof:name":"Qiji",
    "wof:placetype":"locality"
},
  "geometry": {"coordinates":[114.5581,38.24395],"type":"Point"}
}