{
  "type": "Feature",
  "properties": {
    "gn:admin1_code":"29",
    "gn:asciiname":"Damanxian",
    "gn:country_code":"CN",
    "gn:dem":513,
    "gn:feature_class":"P",
    "gn:feature_code":"PPL",
    "gn:name":"Damanxian",
    "gn:population":0,
    "gn:timezone":"Asia/Shanghai",
    "iso:country":"CN",
    "name:zho_x_preferred":[
        "\u5927\u66fc\u7ebf"
    ],
    "wof:name":"Damanxian",
    "wof:placetype":"locality"
},
  "geometry": {"coordinates":[101.81,23.7584],"type":"Point"}
}