{
  "type": "Feature",
  "properties": {
    "gn:admin1_code":"11.0",
    "gn:asciiname":"Tanjia'ao",
    "gn:country_code":"CN",
    "gn:dem":133,
    "gn:feature_class":"P",
    "gn:feature_code":"PPL",
    "gn:name":"Tanjia\u2019ao",
    "gn:population":0,
    "gn:timezone":"Asia/Shanghai",
    "iso:country":"CN",
    "name:und_x_variant":[
        "Tanjia\u2019ao"
    ],
    "name:zho_x_preferred":[
        "\u8c2d\u5bb6\u5773"
    ],
    "wof:name":"Tanjia'ao",
    "wof:placetype":"locality"
},
  "geometry": {"coordinates":[113.04318000000001,27.28816],"type":"Point"}
}