{
  "type": "Feature",
  "properties": {
    "gn:admin1_code":"1.0",
    "gn:asciiname":"Wangshanwocun",
    "gn:country_code":"CN",
    "gn:dem":39,
    "gn:feature_class":"P",
    "gn:feature_code":"PPL",
    "gn:name":"Wangshanwocun",
    "gn:population":0,
    "gn:timezone":"Asia/Shanghai",
    "iso:country":"CN",
    "name:zho_x_preferred":[
        "\u738b\u5c71\u7a9d\u6751"
    ],
    "wof:name":"Wangshanwocun",
    "wof:placetype":"locality"
},
  "geometry": {"coordinates":[116.83255,34.1189],"type":"Point"}
}