{
  "type": "Feature",
  "properties": {
    "gn:admin1_code":"25",
    "gn:asciiname":"Changlizhuang",
    "gn:country_code":"CN",
    "gn:dem":45,
    "gn:feature_class":"P",
    "gn:feature_code":"PPL",
    "gn:name":"Changlizhuang",
    "gn:population":0,
    "gn:timezone":"Asia/Shanghai",
    "iso:country":"CN",
    "name:zho_x_preferred":[
        "\u5e38\u674e\u5e84"
    ],
    "wof:name":"Changlizhuang",
    "wof:placetype":"locality"
},
  "geometry": {"coordinates":[116.289,34.812],"type":"Point"}
}