{
  "type": "Feature",
  "properties": {
    "gn:admin1_code":"9.0",
    "gn:asciiname":"Yanhuai",
    "gn:country_code":"CN",
    "gn:dem":52,
    "gn:feature_class":"P",
    "gn:feature_code":"PPL",
    "gn:name":"Yanhuai",
    "gn:population":0,
    "gn:timezone":"Asia/Shanghai",
    "iso:country":"CN",
    "name:zho_x_preferred":[
        "\u6cbf\u6dee"
    ],
    "wof:name":"Yanhuai",
    "wof:placetype":"locality"
},
  "geometry": {"coordinates":[114.52301,32.30489],"type":"Point"}
}