{
  "type": "Feature",
  "properties": {
    "gn:admin1_code":"8.0",
    "gn:asciiname":"Guoyu'antun",
    "gn:country_code":"CN",
    "gn:dem":201,
    "gn:feature_class":"P",
    "gn:feature_code":"PPL",
    "gn:name":"Guoyu\u2019antun",
    "gn:population":0,
    "gn:timezone":"Asia/Shanghai",
    "iso:country":"CN",
    "name:zho_x_preferred":[
        "Guoyu\u2019antun"
    ],
    "name:zho_x_variant":[
        "\u90ed\u7389\u5b89\u5c6f"
    ],
    "wof:name":"Guoyu'antun",
    "wof:placetype":"locality"
},
  "geometry": {"coordinates":[127.38643999999999,45.70925],"type":"Point"}
}