{
  "type": "Feature",
  "properties": {
    "gn:admin1_code":"30.0",
    "gn:asciiname":"Qinghejing",
    "gn:country_code":"CN",
    "gn:dem":221,
    "gn:feature_class":"P",
    "gn:feature_code":"PPL",
    "gn:name":"Qinghejing",
    "gn:population":0,
    "gn:timezone":"Asia/Shanghai",
    "iso:country":"CN",
    "name:und_x_variant":[
        "\u9752\u6cb3\u5f84"
    ],
    "name:zho_x_preferred":[
        "\u9752\u6cb3\u5f84"
    ],
    "wof:name":"Qinghejing",
    "wof:placetype":"locality"
},
  "geometry": {"coordinates":[115.10626999999999,23.60742],"type":"Point"}
}