{
  "type": "Feature",
  "properties": {
    "gn:admin1_code":"30.0",
    "gn:asciiname":"Shegang Xiacun",
    "gn:country_code":"CN",
    "gn:dem":162,
    "gn:feature_class":"P",
    "gn:feature_code":"PPL",
    "gn:name":"Shegang Xiacun",
    "gn:population":0,
    "gn:timezone":"Asia/Shanghai",
    "iso:country":"CN",
    "name:zho_x_preferred":[
        "\u793e\u5c97\u4e0b\u6751"
    ],
    "wof:name":"Shegang Xiacun",
    "wof:placetype":"locality"
},
  "geometry": {"coordinates":[115.69618,24.05097],"type":"Point"}
}