{
  "type": "Feature",
  "properties": {
    "gn:admin1_code":"10",
    "gn:asciiname":"Caozhuang",
    "gn:country_code":"CN",
    "gn:dem":32,
    "gn:feature_class":"P",
    "gn:feature_code":"PPL",
    "gn:name":"Caozhuang",
    "gn:population":0,
    "gn:timezone":"Asia/Shanghai",
    "iso:country":"CN",
    "name:ceb_x_preferred":[
        "Caozhuang"
    ],
    "name:swe_x_preferred":[
        "Caozhuang"
    ],
    "wof:name":"Caozhuang",
    "wof:placetype":"locality"
},
  "geometry": {"coordinates":[115.25417,38.61056],"type":"Point"}
}