{
  "type": "Feature",
  "properties": {
    "gn:admin1_code":"26.0",
    "gn:asciiname":"Wanghumao",
    "gn:country_code":"CN",
    "gn:dem":1048,
    "gn:feature_class":"P",
    "gn:feature_code":"PPL",
    "gn:name":"Wanghumao",
    "gn:population":0,
    "gn:timezone":"Asia/Shanghai",
    "iso:country":"CN",
    "name:zho_x_preferred":[
        "\u738b\u80e1\u5cc1"
    ],
    "wof:name":"Wanghumao",
    "wof:placetype":"locality"
},
  "geometry": {"coordinates":[110.06417999999999,38.04775],"type":"Point"}
}