{
  "type": "Feature",
  "properties": {
    "gn:admin1_code":"26.0",
    "gn:asciiname":"Yangshanwan",
    "gn:country_code":"CN",
    "gn:dem":1794,
    "gn:feature_class":"P",
    "gn:feature_code":"PPL",
    "gn:name":"Yangshanwan",
    "gn:population":0,
    "gn:timezone":"Asia/Shanghai",
    "iso:country":"CN",
    "name:und_x_variant":[
        "\u9633\u5c71\u6e7e"
    ],
    "wof:name":"Yangshanwan",
    "wof:placetype":"locality"
},
  "geometry": {"coordinates":[106.91115000000001,33.91074],"type":"Point"}
}