{
  "type": "Feature",
  "properties": {
    "gn:admin1_code":"7",
    "gn:asciiname":"Lingdou",
    "gn:country_code":"CN",
    "gn:dem":18,
    "gn:feature_class":"P",
    "gn:feature_code":"PPL",
    "gn:name":"Lingdou",
    "gn:population":0,
    "gn:timezone":"Asia/Shanghai",
    "iso:country":"CN",
    "name:zho_x_preferred":[
        "\u5cad\u515c"
    ],
    "wof:name":"Lingdou",
    "wof:placetype":"locality"
},
  "geometry": {"coordinates":[117.95529999999999,24.35895],"type":"Point"}
}