{
  "type": "Feature",
  "properties": {
    "gn:admin1_code":"8.0",
    "gn:asciiname":"Xiaobolake",
    "gn:country_code":"CN",
    "gn:dem":208,
    "gn:feature_class":"P",
    "gn:feature_code":"PPL",
    "gn:name":"Xiaobolake",
    "gn:population":0,
    "gn:timezone":"Asia/Shanghai",
    "iso:country":"CN",
    "name:zho_x_preferred":[
        "\u5c0f\u4f2f\u62c9\u79d1"
    ],
    "wof:name":"Xiaobolake",
    "wof:placetype":"locality"
},
  "geometry": {"coordinates":[125.11788,48.50233],"type":"Point"}
}