{
  "type": "Feature",
  "properties": {
    "gn:admin1_code":"10",
    "gn:asciiname":"Beisan Chakou",
    "gn:country_code":"CN",
    "gn:dem":1422,
    "gn:feature_class":"P",
    "gn:feature_code":"PPL",
    "gn:name":"Beisan Chakou",
    "gn:population":0,
    "gn:timezone":"Asia/Shanghai",
    "iso:country":"CN",
    "name:zho_x_preferred":[
        "\u5317\u4e09\u5c94\u53e3"
    ],
    "wof:name":"Beisan Chakou",
    "wof:placetype":"locality"
},
  "geometry": {"coordinates":[115.63593,41.27054],"type":"Point"}
}