{
  "type": "Feature",
  "properties": {
    "gn:admin1_code":"24.0",
    "gn:asciiname":"Hujiashan",
    "gn:country_code":"CN",
    "gn:dem":1378,
    "gn:feature_class":"P",
    "gn:feature_code":"PPL",
    "gn:name":"Hujiashan",
    "gn:population":0,
    "gn:timezone":"Asia/Shanghai",
    "iso:country":"CN",
    "name:zho_x_preferred":[
        "\u80e1\u5bb6\u5c71"
    ],
    "wof:name":"Hujiashan",
    "wof:placetype":"locality"
},
  "geometry": {"coordinates":[111.27021000000001,37.84599],"type":"Point"}
}