{
  "type": "Feature",
  "properties": {
    "gn:admin1_code":"18.0",
    "gn:asciiname":"Wenggao",
    "gn:country_code":"CN",
    "gn:dem":319,
    "gn:feature_class":"P",
    "gn:feature_code":"PPL",
    "gn:name":"Wenggao",
    "gn:population":0,
    "gn:timezone":"Asia/Shanghai",
    "iso:country":"CN",
    "name:zho_x_preferred":[
        "\u7fc1\u7a3f"
    ],
    "wof:name":"Wenggao",
    "wof:placetype":"locality"
},
  "geometry": {"coordinates":[109.015,27.8405],"type":"Point"}
}