{
  "type": "Feature",
  "properties": {
    "gn:admin1_code":"24.0",
    "gn:asciiname":"Suancigou",
    "gn:country_code":"CN",
    "gn:dem":1673,
    "gn:feature_class":"P",
    "gn:feature_code":"PPL",
    "gn:name":"Suancigou",
    "gn:population":0,
    "gn:timezone":"Asia/Shanghai",
    "iso:country":"CN",
    "name:und_x_variant":[
        "\u9178\u523a\u6c9f"
    ],
    "name:zho_x_preferred":[
        "\u9178\u523a\u6c9f"
    ],
    "wof:name":"Suancigou",
    "wof:placetype":"locality"
},
  "geometry": {"coordinates":[113.09692,39.27097],"type":"Point"}
}