{
  "type": "Feature",
  "properties": {
    "gn:admin1_code":"16.0",
    "gn:asciiname":"Tuntie",
    "gn:country_code":"CN",
    "gn:dem":669,
    "gn:feature_class":"P",
    "gn:feature_code":"PPL",
    "gn:name":"Tuntie",
    "gn:population":0,
    "gn:timezone":"Asia/Shanghai",
    "iso:country":"CN",
    "name:zho_x_preferred":[
        "\u541e\u94c1"
    ],
    "wof:name":"Tuntie",
    "wof:placetype":"locality"
},
  "geometry": {"coordinates":[106.721,23.3011],"type":"Point"}
}