{
  "type": "Feature",
  "properties": {
    "gn:admin1_code":"26.0",
    "gn:asciiname":"Zhangjiaping",
    "gn:cc2":"CN",
    "gn:country_code":"CN",
    "gn:dem":1213,
    "gn:feature_class":"P",
    "gn:feature_code":"PPL",
    "gn:name":"Zhangjiaping",
    "gn:population":0,
    "gn:timezone":"Asia/Shanghai",
    "iso:country":"CN",
    "name:und_x_variant":[
        "Chang-chia-p\u2019ing",
        "Zhangjiaping"
    ],
    "wof:name":"Zhangjiaping",
    "wof:placetype":"locality"
},
  "geometry": {"coordinates":[109.46666999999999,36.91667],"type":"Point"}
}