{
  "type": "Feature",
  "properties": {
    "gn:admin1_code":"8.0",
    "gn:asciiname":"Xingfucun",
    "gn:country_code":"CN",
    "gn:dem":187,
    "gn:feature_class":"P",
    "gn:feature_code":"PPL",
    "gn:name":"Xingfucun",
    "gn:population":0,
    "gn:timezone":"Asia/Shanghai",
    "iso:country":"CN",
    "name:zho_x_preferred":[
        "\u5174\u5bcc\u6751"
    ],
    "wof:name":"Xingfucun",
    "wof:placetype":"locality"
},
  "geometry": {"coordinates":[126.75939,45.40779000000001],"type":"Point"}
}