{
  "type": "Feature",
  "properties": {
    "gn:admin1_code":"11.0",
    "gn:asciiname":"Leidapo",
    "gn:country_code":"CN",
    "gn:dem":881,
    "gn:feature_class":"P",
    "gn:feature_code":"PPL",
    "gn:name":"Leidapo",
    "gn:population":0,
    "gn:timezone":"Asia/Shanghai",
    "iso:country":"CN",
    "name:zho_x_preferred":[
        "\u96f7\u6253\u5761"
    ],
    "wof:name":"Leidapo",
    "wof:placetype":"locality"
},
  "geometry": {"coordinates":[110.42964000000001,26.43939],"type":"Point"}
}