{
  "type": "Feature",
  "properties": {
    "gn:admin1_code":"30.0",
    "gn:asciiname":"Miaohoucun",
    "gn:country_code":"CN",
    "gn:dem":216,
    "gn:feature_class":"P",
    "gn:feature_code":"PPL",
    "gn:name":"Miaohoucun",
    "gn:population":0,
    "gn:timezone":"Asia/Shanghai",
    "iso:country":"CN",
    "name:zho_x_preferred":[
        "\u5e99\u540e\u6751"
    ],
    "wof:name":"Miaohoucun",
    "wof:placetype":"locality"
},
  "geometry": {"coordinates":[111.65891999999999,23.31581],"type":"Point"}
}