{
  "type": "Feature",
  "properties": {
    "gn:admin1_code":"7.0",
    "gn:asciiname":"Xiajinfang",
    "gn:country_code":"CN",
    "gn:dem":475,
    "gn:feature_class":"P",
    "gn:feature_code":"PPL",
    "gn:name":"Xiajinfang",
    "gn:population":0,
    "gn:timezone":"Asia/Shanghai",
    "iso:country":"CN",
    "name:zho_x_preferred":[
        "\u4e0b\u9526\u574a"
    ],
    "wof:name":"Xiajinfang",
    "wof:placetype":"locality"
},
  "geometry": {"coordinates":[116.73459,25.024],"type":"Point"}
}