{
  "type": "Feature",
  "properties": {
    "gn:admin1_code":"18",
    "gn:asciiname":"Sanchahe",
    "gn:country_code":"CN",
    "gn:dem":1219,
    "gn:feature_class":"P",
    "gn:feature_code":"PPL",
    "gn:name":"Sanchahe",
    "gn:population":0,
    "gn:timezone":"Asia/Shanghai",
    "iso:country":"CN",
    "name:zho_x_preferred":[
        "\u4e09\u5c94\u6cb3"
    ],
    "wof:name":"Sanchahe",
    "wof:placetype":"locality"
},
  "geometry": {"coordinates":[106.104,26.0657],"type":"Point"}
}