{
  "type": "Feature",
  "properties": {
    "gn:admin1_code":"3",
    "gn:asciiname":"Nuomikeng",
    "gn:country_code":"CN",
    "gn:dem":293,
    "gn:feature_class":"P",
    "gn:feature_code":"PPL",
    "gn:name":"Nuomikeng",
    "gn:population":0,
    "gn:timezone":"Asia/Shanghai",
    "iso:country":"CN",
    "name:zho_x_preferred":[
        "\u7cef\u7c73\u5751"
    ],
    "wof:name":"Nuomikeng",
    "wof:placetype":"locality"
},
  "geometry": {"coordinates":[114.417,26.9248],"type":"Point"}
}