{
  "type": "Feature",
  "properties": {
    "gn:admin1_code":"08",
    "gn:asciiname":"Xuda Fangzi",
    "gn:country_code":"CN",
    "gn:dem":158,
    "gn:feature_class":"P",
    "gn:feature_code":"PPL",
    "gn:name":"Xuda Fangzi",
    "gn:population":0,
    "gn:timezone":"Asia/Shanghai",
    "iso:country":"CN",
    "name:und_x_variant":[
        "Hs\u00fc-ta-fang-tzu",
        "Xuda Fangzi"
    ],
    "name:zho_x_preferred":[
        "\u5f90\u5927\u623f\u5b50"
    ],
    "wof:name":"Xuda Fangzi",
    "wof:placetype":"locality"
},
  "geometry": {"coordinates":[126.76035,46.4394],"type":"Point"}
}