{
  "type": "Feature",
  "properties": {
    "gn:admin1_code":"11.0",
    "gn:asciiname":"Chaoyang",
    "gn:country_code":"CN",
    "gn:dem":187,
    "gn:feature_class":"P",
    "gn:feature_code":"PPLA4",
    "gn:name":"Chaoyang",
    "gn:population":0,
    "gn:timezone":"Asia/Shanghai",
    "iso:country":"CN",
    "name:und_x_variant":[
        "Yanping",
        "\u5ca9\u576a",
        "Chaoyang",
        "\u671d\u9633"
    ],
    "name:zho_x_preferred":[
        "Chaoyang Xiang"
    ],
    "name:zho_x_variant":[
        "\u671d\u9633\u4e61"
    ],
    "wof:name":"Chaoyang",
    "wof:placetype":"locality"
},
  "geometry": {"coordinates":[111.03073999999999,29.33515],"type":"Point"}
}