{
  "type": "Feature",
  "properties": {
    "gn:admin1_code":"19.0",
    "gn:asciiname":"Guanyingzicun",
    "gn:country_code":"CN",
    "gn:dem":222,
    "gn:feature_class":"P",
    "gn:feature_code":"PPL",
    "gn:name":"Guanyingzicun",
    "gn:population":0,
    "gn:timezone":"Asia/Shanghai",
    "iso:country":"CN",
    "name:zho_x_preferred":[
        "\u5b98\u8425\u5b50\u6751"
    ],
    "wof:name":"Guanyingzicun",
    "wof:placetype":"locality"
},
  "geometry": {"coordinates":[121.11660999999999,42.22777],"type":"Point"}
}