{
  "type": "Feature",
  "properties": {
    "gn:admin1_code":"26.0",
    "gn:asciiname":"Lanjia",
    "gn:country_code":"CN",
    "gn:dem":743,
    "gn:feature_class":"P",
    "gn:feature_code":"PPL",
    "gn:name":"Lanjia",
    "gn:population":0,
    "gn:timezone":"Asia/Shanghai",
    "iso:country":"CN",
    "name:zho_x_preferred":[
        "\u5170\u5bb6"
    ],
    "wof:name":"Lanjia",
    "wof:placetype":"locality"
},
  "geometry": {"coordinates":[108.86884999999999,34.85092],"type":"Point"}
}