{
  "type": "Feature",
  "properties": {
    "gn:admin1_code":"24.0",
    "gn:asciiname":"Fengjiabu",
    "gn:country_code":"CN",
    "gn:dem":1357,
    "gn:feature_class":"P",
    "gn:feature_code":"PPL",
    "gn:name":"Fengjiabu",
    "gn:population":0,
    "gn:timezone":"Asia/Shanghai",
    "iso:country":"CN",
    "name:und_x_variant":[
        "\u51af\u5bb6\u5821"
    ],
    "name:zho_x_preferred":[
        "\u51af\u5bb6\u5821"
    ],
    "wof:name":"Fengjiabu",
    "wof:placetype":"locality"
},
  "geometry": {"coordinates":[112.70623000000001,39.98189],"type":"Point"}
}