{
  "type": "Feature",
  "properties": {
    "gn:admin1_code":"32.0",
    "gn:asciiname":"Tijiaolaijian",
    "gn:country_code":"CN",
    "gn:dem":2280,
    "gn:feature_class":"P",
    "gn:feature_code":"PPL",
    "gn:name":"Tijiaolaijian",
    "gn:population":0,
    "gn:timezone":"Asia/Shanghai",
    "iso:country":"CN",
    "name:zho_x_preferred":[
        "\u4f53\u89d2\u6765\u5c16"
    ],
    "wof:name":"Tijiaolaijian",
    "wof:placetype":"locality"
},
  "geometry": {"coordinates":[102.931,28.3954],"type":"Point"}
}