{
  "type": "Feature",
  "properties": {
    "gn:admin1_code":"18.0",
    "gn:asciiname":"Guijiazhai",
    "gn:country_code":"CN",
    "gn:dem":1047,
    "gn:feature_class":"P",
    "gn:feature_code":"PPL",
    "gn:name":"Guijiazhai",
    "gn:population":0,
    "gn:timezone":"Asia/Shanghai",
    "iso:country":"CN",
    "name:zho_x_preferred":[
        "\u6842\u5bb6\u5be8"
    ],
    "wof:name":"Guijiazhai",
    "wof:placetype":"locality"
},
  "geometry": {"coordinates":[108.461,28.3244],"type":"Point"}
}