{
  "type": "Feature",
  "properties": {
    "gn:admin1_code":"2.0",
    "gn:asciiname":"Tongluoban",
    "gn:country_code":"CN",
    "gn:dem":419,
    "gn:feature_class":"P",
    "gn:feature_code":"PPL",
    "gn:name":"Tongluoban",
    "gn:population":0,
    "gn:timezone":"Asia/Shanghai",
    "iso:country":"CN",
    "name:und_x_variant":[
        "\u94dc\u9523\u5742"
    ],
    "wof:name":"Tongluoban",
    "wof:placetype":"locality"
},
  "geometry": {"coordinates":[119.07804,30.10927],"type":"Point"}
}