{
  "type": "Feature",
  "properties": {
    "gn:admin1_code":"29",
    "gn:asciiname":"Shidong",
    "gn:country_code":"CN",
    "gn:dem":1773,
    "gn:feature_class":"P",
    "gn:feature_code":"PPL",
    "gn:name":"Shidong",
    "gn:population":0,
    "gn:timezone":"Asia/Shanghai",
    "iso:country":"CN",
    "name:zho_x_preferred":[
        "\u77f3\u6d1e"
    ],
    "wof:name":"Shidong",
    "wof:placetype":"locality"
},
  "geometry": {"coordinates":[102.259,24.6538],"type":"Point"}
}