{
  "type": "Feature",
  "properties": {
    "gn:admin1_code":"25",
    "gn:asciiname":"Xiche",
    "gn:country_code":"CN",
    "gn:dem":28,
    "gn:feature_class":"P",
    "gn:feature_code":"PPL",
    "gn:name":"Xiche",
    "gn:population":0,
    "gn:timezone":"Asia/Shanghai",
    "iso:country":"CN",
    "name:fra_x_preferred":[
        "Xiche"
    ],
    "name:zho_x_preferred":[
        "\u897f\u8f66"
    ],
    "wof:name":"Xiche",
    "wof:placetype":"locality"
},
  "geometry": {"coordinates":[116.995,36.7952],"type":"Point"}
}