{
  "type": "Feature",
  "properties": {
    "gn:admin1_code":"14.0",
    "gn:asciiname":"Yangrigangcun",
    "gn:country_code":"CN",
    "gn:dem":3993,
    "gn:feature_class":"P",
    "gn:feature_code":"PPL",
    "gn:name":"Yangrigangcun",
    "gn:population":0,
    "gn:timezone":"Asia/Urumqi",
    "iso:country":"CN",
    "name:zho_x_preferred":[
        "\u7f8a\u65e5\u5c97\u6751"
    ],
    "wof:name":"Yangrigangcun",
    "wof:placetype":"locality"
},
  "geometry": {"coordinates":[91.98211999999999,29.99944],"type":"Point"}
}