{
  "type": "Feature",
  "properties": {
    "gn:admin1_code":"29.0",
    "gn:asciiname":"Kangle",
    "gn:country_code":"CN",
    "gn:dem":2090,
    "gn:feature_class":"P",
    "gn:feature_code":"PPL",
    "gn:name":"Kangle",
    "gn:population":0,
    "gn:timezone":"Asia/Shanghai",
    "iso:country":"CN",
    "name:zho_x_preferred":[
        "\u5eb7\u4e50"
    ],
    "wof:name":"Kangle",
    "wof:placetype":"locality"
},
  "geometry": {"coordinates":[102.435,25.8966],"type":"Point"}
}