{
  "type": "Feature",
  "properties": {
    "gn:admin1_code":"8.0",
    "gn:asciiname":"Baojiacun",
    "gn:country_code":"CN",
    "gn:dem":248,
    "gn:feature_class":"P",
    "gn:feature_code":"PPL",
    "gn:name":"Baojiacun",
    "gn:population":0,
    "gn:timezone":"Asia/Shanghai",
    "iso:country":"CN",
    "name:zho_x_preferred":[
        "\u4fdd\u5bb6\u6751"
    ],
    "wof:name":"Baojiacun",
    "wof:placetype":"locality"
},
  "geometry": {"coordinates":[125.70808,48.08213],"type":"Point"}
}