{
  "type": "Feature",
  "properties": {
    "gn:admin1_code":"31.0",
    "gn:asciiname":"Changfapo",
    "gn:country_code":"CN",
    "gn:dem":33,
    "gn:feature_class":"P",
    "gn:feature_code":"PPL",
    "gn:name":"Changfapo",
    "gn:population":0,
    "gn:timezone":"Asia/Shanghai",
    "iso:country":"CN",
    "name:zho_x_preferred":[
        "Changfapo"
    ],
    "name:zho_x_variant":[
        "\u957f\u53d1\u5761"
    ],
    "wof:name":"Changfapo",
    "wof:placetype":"locality"
},
  "geometry": {"coordinates":[110.02415000000001,19.72381],"type":"Point"}
}