{
  "type": "Feature",
  "properties": {
    "gn:admin1_code":"04",
    "gn:asciiname":"Dashishan",
    "gn:cc2":"CN",
    "gn:country_code":"CN",
    "gn:dem":10,
    "gn:feature_class":"P",
    "gn:feature_code":"PPL",
    "gn:name":"Dashishan",
    "gn:population":0,
    "gn:timezone":"Asia/Shanghai",
    "iso:country":"CN",
    "name:und_x_variant":[
        "Ta-shih-shan-chuang",
        "Dashishan"
    ],
    "wof:name":"Dashishan",
    "wof:placetype":"locality"
},
  "geometry": {"coordinates":[118.3875,32.94889000000001],"type":"Point"}
}