{
  "type": "Feature",
  "properties": {
    "gn:admin1_code":"32.0",
    "gn:asciiname":"Longjiaci",
    "gn:country_code":"CN",
    "gn:dem":476,
    "gn:feature_class":"P",
    "gn:feature_code":"PPL",
    "gn:name":"Longjiaci",
    "gn:population":0,
    "gn:timezone":"Asia/Shanghai",
    "iso:country":"CN",
    "name:zho_x_preferred":[
        "\u9f99\u5bb6\u7960"
    ],
    "wof:name":"Longjiaci",
    "wof:placetype":"locality"
},
  "geometry": {"coordinates":[103.93899999999999,29.7795],"type":"Point"}
}