{
  "type": "Feature",
  "properties": {
    "gn:admin1_code":"4.0",
    "gn:asciiname":"Dinglu",
    "gn:country_code":"CN",
    "gn:dem":5,
    "gn:feature_class":"P",
    "gn:feature_code":"PPL",
    "gn:name":"Dinglu",
    "gn:population":0,
    "gn:timezone":"Asia/Shanghai",
    "iso:country":"CN",
    "name:zho_x_preferred":[
        "Dinglu"
    ],
    "name:zho_x_variant":[
        "\u4e01\u9646"
    ],
    "wof:name":"Dinglu",
    "wof:placetype":"locality"
},
  "geometry": {"coordinates":[121.32348,31.88698],"type":"Point"}
}