{
  "type": "Feature",
  "properties": {
    "gn:admin1_code":"29.0",
    "gn:asciiname":"Zhujiawan",
    "gn:country_code":"CN",
    "gn:dem":2093,
    "gn:feature_class":"P",
    "gn:feature_code":"PPL",
    "gn:name":"Zhujiawan",
    "gn:population":0,
    "gn:timezone":"Asia/Shanghai",
    "iso:country":"CN",
    "name:zho_x_preferred":[
        "\u6731\u5bb6\u6e7e"
    ],
    "wof:name":"Zhujiawan",
    "wof:placetype":"locality"
},
  "geometry": {"coordinates":[103.054,25.8519],"type":"Point"}
}