{
  "type": "Feature",
  "properties": {
    "gn:admin1_code":"07",
    "gn:asciiname":"Duncuo",
    "gn:country_code":"CN",
    "gn:dem":56,
    "gn:feature_class":"P",
    "gn:feature_code":"PPL",
    "gn:name":"Duncuo",
    "gn:population":0,
    "gn:timezone":"Asia/Shanghai",
    "iso:country":"CN",
    "name:zho_x_preferred":[
        "\u6566\u539d"
    ],
    "wof:name":"Duncuo",
    "wof:placetype":"locality"
},
  "geometry": {"coordinates":[118.40691,25.03314],"type":"Point"}
}