{
  "type": "Feature",
  "properties": {
    "gn:admin1_code":"33.0",
    "gn:asciiname":"Shuguang",
    "gn:country_code":"CN",
    "gn:dem":697,
    "gn:feature_class":"P",
    "gn:feature_code":"PPL",
    "gn:name":"Shuguang",
    "gn:population":0,
    "gn:timezone":"Asia/Shanghai",
    "iso:country":"CN",
    "name:zho_x_preferred":[
        "\u66d9\u5149"
    ],
    "wof:name":"Shuguang",
    "wof:placetype":"locality"
},
  "geometry": {"coordinates":[107.08735,29.42765],"type":"Point"}
}