{
  "type": "Feature",
  "properties": {
    "gn:admin1_code":"32.0",
    "gn:asciiname":"Shijiahe",
    "gn:country_code":"CN",
    "gn:dem":720,
    "gn:feature_class":"P",
    "gn:feature_code":"PPL",
    "gn:name":"Shijiahe",
    "gn:population":0,
    "gn:timezone":"Asia/Shanghai",
    "iso:country":"CN",
    "name:zho_x_preferred":[
        "\u5341\u5bb6\u6cb3"
    ],
    "wof:name":"Shijiahe",
    "wof:placetype":"locality"
},
  "geometry": {"coordinates":[107.16,32.4739],"type":"Point"}
}