{
  "type": "Feature",
  "properties": {
    "gn:admin1_code":"4.0",
    "gn:asciiname":"Qixiacun",
    "gn:country_code":"CN",
    "gn:dem":19,
    "gn:feature_class":"P",
    "gn:feature_code":"PPL",
    "gn:name":"Qixiacun",
    "gn:population":0,
    "gn:timezone":"Asia/Shanghai",
    "iso:country":"CN",
    "name:zho_x_preferred":[
        "\u6816\u971e\u6751"
    ],
    "wof:name":"Qixiacun",
    "wof:placetype":"locality"
},
  "geometry": {"coordinates":[118.94873,32.14771],"type":"Point"}
}