{
  "type": "Feature",
  "properties": {
    "gn:admin1_code":"10",
    "gn:asciiname":"Jingjiazhai",
    "gn:country_code":"CN",
    "gn:dem":36,
    "gn:feature_class":"P",
    "gn:feature_code":"PPL",
    "gn:name":"Jingjiazhai",
    "gn:population":0,
    "gn:timezone":"Asia/Shanghai",
    "iso:country":"CN",
    "name:und_x_variant":[
        "\u8346\u5bb6\u5be8"
    ],
    "wof:name":"Jingjiazhai",
    "wof:placetype":"locality"
},
  "geometry": {"coordinates":[115.20331000000002,37.00878],"type":"Point"}
}