{
  "type": "Feature",
  "properties": {
    "gn:admin1_code":"14.0",
    "gn:asciiname":"Chaxiteng",
    "gn:country_code":"CN",
    "gn:dem":3938,
    "gn:feature_class":"P",
    "gn:feature_code":"PPL",
    "gn:name":"Chaxiteng",
    "gn:population":0,
    "gn:timezone":"Asia/Urumqi",
    "iso:country":"CN",
    "name:zho_x_preferred":[
        "\u5bdf\u620f\u817e"
    ],
    "wof:name":"Chaxiteng",
    "wof:placetype":"locality"
},
  "geometry": {"coordinates":[97.54406,31.96887000000001],"type":"Point"}
}