{
  "type": "Feature",
  "properties": {
    "gn:admin1_code":"12.0",
    "gn:asciiname":"Zengjia Wo",
    "gn:country_code":"CN",
    "gn:dem":315,
    "gn:feature_class":"P",
    "gn:feature_code":"PPL",
    "gn:name":"Zengjia Wo",
    "gn:population":0,
    "gn:timezone":"Asia/Shanghai",
    "iso:country":"CN",
    "name:zho_x_preferred":[
        "\u66fe\u5bb6\u7a9d"
    ],
    "wof:name":"Zengjia Wo",
    "wof:placetype":"locality"
},
  "geometry": {"coordinates":[111.05249999999999,32.03116],"type":"Point"}
}