{
  "type": "Feature",
  "properties": {
    "gn:admin1_code":"8.0",
    "gn:asciiname":"Linfucun",
    "gn:country_code":"CN",
    "gn:dem":148,
    "gn:feature_class":"P",
    "gn:feature_code":"PPL",
    "gn:name":"Linfucun",
    "gn:population":0,
    "gn:timezone":"Asia/Shanghai",
    "iso:country":"CN",
    "name:zho_x_preferred":[
        "\u6797\u5bcc\u6751"
    ],
    "wof:name":"Linfucun",
    "wof:placetype":"locality"
},
  "geometry": {"coordinates":[126.20704000000001,46.06128],"type":"Point"}
}