{
  "type": "Feature",
  "properties": {
    "gn:admin1_code":"18",
    "gn:asciiname":"Xiaqichong",
    "gn:country_code":"CN",
    "gn:dem":1558,
    "gn:feature_class":"P",
    "gn:feature_code":"PPL",
    "gn:name":"Xiaqichong",
    "gn:population":0,
    "gn:timezone":"Asia/Shanghai",
    "iso:country":"CN",
    "name:zho_x_preferred":[
        "\u4e0b\u6f06\u51b2"
    ],
    "wof:name":"Xiaqichong",
    "wof:placetype":"locality"
},
  "geometry": {"coordinates":[105.681,26.6943],"type":"Point"}
}