{
  "type": "Feature",
  "properties": {
    "gn:admin1_code":"19.0",
    "gn:asciiname":"Mopanshan",
    "gn:country_code":"CN",
    "gn:dem":17,
    "gn:feature_class":"P",
    "gn:feature_code":"PPL",
    "gn:name":"Mopanshan",
    "gn:population":0,
    "gn:timezone":"Asia/Shanghai",
    "iso:country":"CN",
    "name:und_x_variant":[
        "\u78e8\u76d8\u5c71"
    ],
    "name:zho_x_preferred":[
        "\u78e8\u76d8\u5c71"
    ],
    "wof:name":"Mopanshan",
    "wof:placetype":"locality"
},
  "geometry": {"coordinates":[123.35478999999999,39.82927],"type":"Point"}
}