{
  "type": "Feature",
  "properties": {
    "gn:admin1_code":"10",
    "gn:asciiname":"Yanjiazhuang",
    "gn:country_code":"CN",
    "gn:dem":658,
    "gn:feature_class":"P",
    "gn:feature_code":"PPL",
    "gn:name":"Yanjiazhuang",
    "gn:population":0,
    "gn:timezone":"Asia/Shanghai",
    "iso:country":"CN",
    "name:zho_x_preferred":[
        "\u960e\u5bb6\u5e84"
    ],
    "wof:name":"Yanjiazhuang",
    "wof:placetype":"locality"
},
  "geometry": {"coordinates":[118.77931,40.82368],"type":"Point"}
}