{
  "type": "Feature",
  "properties": {
    "gn:admin1_code":"4.0",
    "gn:asciiname":"Zhangguandang",
    "gn:country_code":"CN",
    "gn:dem":11,
    "gn:feature_class":"P",
    "gn:feature_code":"PPL",
    "gn:name":"Zhangguandang",
    "gn:population":0,
    "gn:timezone":"Asia/Shanghai",
    "iso:country":"CN",
    "name:zho_x_preferred":[
        "Zhangguandang"
    ],
    "name:zho_x_variant":[
        "\u5f20\u5b98\u8361"
    ],
    "wof:name":"Zhangguandang",
    "wof:placetype":"locality"
},
  "geometry": {"coordinates":[119.11344,33.75941],"type":"Point"}
}