{
  "type": "Feature",
  "properties": {
    "gn:admin1_code":"1.0",
    "gn:asciiname":"Qicaiyuancun",
    "gn:country_code":"CN",
    "gn:dem":37,
    "gn:feature_class":"P",
    "gn:feature_code":"PPL",
    "gn:name":"Qicaiyuancun",
    "gn:population":0,
    "gn:timezone":"Asia/Shanghai",
    "iso:country":"CN",
    "name:zho_x_preferred":[
        "\u9f50\u83dc\u56ed\u6751"
    ],
    "wof:name":"Qicaiyuancun",
    "wof:placetype":"locality"
},
  "geometry": {"coordinates":[115.5705,33.04749],"type":"Point"}
}