{
  "type": "Feature",
  "properties": {
    "gn:admin1_code":"2.0",
    "gn:asciiname":"Tangping",
    "gn:country_code":"CN",
    "gn:dem":515,
    "gn:feature_class":"P",
    "gn:feature_code":"PPL",
    "gn:name":"Tangping",
    "gn:population":0,
    "gn:timezone":"Asia/Shanghai",
    "iso:country":"CN",
    "name:und_x_variant":[
        "\u68e0\u576a",
        "Tangping"
    ],
    "wof:name":"Tangping",
    "wof:placetype":"locality"
},
  "geometry": {"coordinates":[119.7179,27.47139],"type":"Point"}
}