{
  "type": "Feature",
  "properties": {
    "gn:admin1_code":"12.0",
    "gn:asciiname":"Laiwan",
    "gn:country_code":"CN",
    "gn:dem":132,
    "gn:feature_class":"P",
    "gn:feature_code":"PPL",
    "gn:name":"Laiwan",
    "gn:population":0,
    "gn:timezone":"Asia/Shanghai",
    "iso:country":"CN",
    "name:por_x_preferred":[
        "Laiwan"
    ],
    "name:zho_x_preferred":[
        "\u8d56\u6e7e"
    ],
    "wof:name":"Laiwan",
    "wof:placetype":"locality"
},
  "geometry": {"coordinates":[112.10693000000001,31.41836],"type":"Point"}
}