{
  "type": "Feature",
  "properties": {
    "gn:admin1_code":"19.0",
    "gn:asciiname":"Qianmincun",
    "gn:country_code":"CN",
    "gn:dem":37,
    "gn:feature_class":"P",
    "gn:feature_code":"PPL",
    "gn:name":"Qianmincun",
    "gn:population":0,
    "gn:timezone":"Asia/Shanghai",
    "iso:country":"CN",
    "name:zho_x_preferred":[
        "\u524d\u6c11\u6751"
    ],
    "wof:name":"Qianmincun",
    "wof:placetype":"locality"
},
  "geometry": {"coordinates":[123.23699999999999,41.8068],"type":"Point"}
}