{
  "type": "Feature",
  "properties": {
    "gn:admin1_code":"29",
    "gn:asciiname":"Tianxin",
    "gn:country_code":"CN",
    "gn:dem":1717,
    "gn:feature_class":"P",
    "gn:feature_code":"PPL",
    "gn:name":"Tianxin",
    "gn:population":0,
    "gn:timezone":"Asia/Shanghai",
    "iso:country":"CN",
    "name:zho_x_preferred":[
        "\u7530\u5fc3"
    ],
    "wof:name":"Tianxin",
    "wof:placetype":"locality"
},
  "geometry": {"coordinates":[102.22799999999999,24.3355],"type":"Point"}
}