{
  "type": "Feature",
  "properties": {
    "gn:admin1_code":"8.0",
    "gn:asciiname":"Tianjincun",
    "gn:country_code":"CN",
    "gn:dem":219,
    "gn:feature_class":"P",
    "gn:feature_code":"PPL",
    "gn:name":"Tianjincun",
    "gn:population":0,
    "gn:timezone":"Asia/Shanghai",
    "iso:country":"CN",
    "name:zho_x_preferred":[
        "\u5929\u6d25\u6751"
    ],
    "wof:name":"Tianjincun",
    "wof:placetype":"locality"
},
  "geometry": {"coordinates":[124.61301,48.15009000000001],"type":"Point"}
}