{
  "type": "Feature",
  "properties": {
    "gn:admin1_code":"1.0",
    "gn:asciiname":"Zhuxiaoloucun",
    "gn:country_code":"CN",
    "gn:dem":46,
    "gn:feature_class":"P",
    "gn:feature_code":"PPL",
    "gn:name":"Zhuxiaoloucun",
    "gn:population":0,
    "gn:timezone":"Asia/Shanghai",
    "iso:country":"CN",
    "name:zho_x_preferred":[
        "\u6731\u5c0f\u697c\u6751"
    ],
    "wof:name":"Zhuxiaoloucun",
    "wof:placetype":"locality"
},
  "geometry": {"coordinates":[116.43268,34.5669],"type":"Point"}
}