{
  "type": "Feature",
  "properties": {
    "gn:admin1_code":"2.0",
    "gn:asciiname":"Panshan",
    "gn:country_code":"CN",
    "gn:dem":348,
    "gn:feature_class":"P",
    "gn:feature_code":"PPL",
    "gn:name":"Panshan",
    "gn:population":0,
    "gn:timezone":"Asia/Shanghai",
    "iso:country":"CN",
    "name:zho_x_preferred":[
        "\u87e0\u5c71"
    ],
    "wof:name":"Panshan",
    "wof:placetype":"locality"
},
  "geometry": {"coordinates":[119.44063,29.36417],"type":"Point"}
}