{
  "type": "Feature",
  "properties": {
    "gn:admin1_code":"04",
    "gn:asciiname":"Miaoqiaozhen",
    "gn:cc2":"CN",
    "gn:country_code":"CN",
    "gn:dem":4,
    "gn:feature_class":"P",
    "gn:feature_code":"PPL",
    "gn:name":"Miaoqiaozhen",
    "gn:population":0,
    "gn:timezone":"Asia/Shanghai",
    "iso:country":"CN",
    "name:und_x_variant":[
        "Miao-ch'iao-chen"
    ],
    "wof:name":"Miaoqiaozhen",
    "wof:placetype":"locality"
},
  "geometry": {"coordinates":[121.51027999999999,31.90111],"type":"Point"}
}