{
  "type": "Feature",
  "properties": {
    "gn:admin1_code":"4.0",
    "gn:asciiname":"Guanjiang",
    "gn:country_code":"CN",
    "gn:dem":54,
    "gn:feature_class":"P",
    "gn:feature_code":"PPL",
    "gn:name":"Guanjiang",
    "gn:population":0,
    "gn:timezone":"Asia/Shanghai",
    "iso:country":"CN",
    "name:und_x_variant":[
        "\u5173\u6c5f"
    ],
    "wof:name":"Guanjiang",
    "wof:placetype":"locality"
},
  "geometry": {"coordinates":[118.48350000000001,34.48307],"type":"Point"}
}