{
  "type": "Feature",
  "properties": {
    "gn:admin1_code":"25",
    "gn:asciiname":"Laoyagu",
    "gn:country_code":"CN",
    "gn:dem":161,
    "gn:feature_class":"P",
    "gn:feature_code":"PPL",
    "gn:name":"Laoyagu",
    "gn:population":0,
    "gn:timezone":"Asia/Shanghai",
    "iso:country":"CN",
    "name:zho_x_preferred":[
        "\u8001\u5d16\u5d2e"
    ],
    "wof:name":"Laoyagu",
    "wof:placetype":"locality"
},
  "geometry": {"coordinates":[118.477,36.401],"type":"Point"}
}