{
  "type": "Feature",
  "properties": {
    "gn:admin1_code":"32.0",
    "gn:asciiname":"Gengdu",
    "gn:country_code":"CN",
    "gn:dem":3681,
    "gn:feature_class":"P",
    "gn:feature_code":"PPL",
    "gn:name":"Gengdu",
    "gn:population":0,
    "gn:timezone":"Asia/Shanghai",
    "iso:country":"CN",
    "name:zho_x_preferred":[
        "\u66f4\u90fd"
    ],
    "wof:name":"Gengdu",
    "wof:placetype":"locality"
},
  "geometry": {"coordinates":[100.959,31.7688],"type":"Point"}
}