{
  "type": "Feature",
  "properties": {
    "gn:admin1_code":"29.0",
    "gn:asciiname":"Wotuozhai",
    "gn:country_code":"CN",
    "gn:dem":1215,
    "gn:feature_class":"P",
    "gn:feature_code":"PPL",
    "gn:name":"Wotuozhai",
    "gn:population":0,
    "gn:timezone":"Asia/Shanghai",
    "iso:country":"CN",
    "name:zho_x_preferred":[
        "\u7a9d\u6258\u5be8"
    ],
    "wof:name":"Wotuozhai",
    "wof:placetype":"locality"
},
  "geometry": {"coordinates":[99.9474,22.5053],"type":"Point"}
}