{
  "type": "Feature",
  "properties": {
    "gn:admin1_code":"02",
    "gn:asciiname":"Jietou",
    "gn:country_code":"CN",
    "gn:dem":97,
    "gn:feature_class":"P",
    "gn:feature_code":"PPLA4",
    "gn:name":"Jietou",
    "gn:population":0,
    "gn:timezone":"Asia/Shanghai",
    "iso:country":"CN",
    "name:und_x_variant":[
        "Chieh-t\u2019ou",
        "Chieh-t\u2019ou-chen",
        "Chiatou",
        "Jietou Zhen",
        "Jietou"
    ],
    "name:zho_x_preferred":[
        "\u8857\u5934"
    ],
    "name:zho_x_variant":[
        "\u8857\u5934\u9547"
    ],
    "wof:name":"Jietou",
    "wof:placetype":"locality"
},
  "geometry": {"coordinates":[120.80376,29.11588],"type":"Point"}
}