{
  "type": "Feature",
  "properties": {
    "gn:admin1_code":"15.0",
    "gn:asciiname":"Dalupo",
    "gn:country_code":"CN",
    "gn:dem":2244,
    "gn:feature_class":"P",
    "gn:feature_code":"PPL",
    "gn:name":"Dalupo",
    "gn:population":0,
    "gn:timezone":"Asia/Shanghai",
    "iso:country":"CN",
    "name:zho_x_preferred":[
        "\u5927\u8def\u5761"
    ],
    "wof:name":"Dalupo",
    "wof:placetype":"locality"
},
  "geometry": {"coordinates":[104.199,35.357],"type":"Point"}
}