{
  "type": "Feature",
  "properties": {
    "gn:admin1_code":"19.0",
    "gn:asciiname":"Wudaogou",
    "gn:country_code":"CN",
    "gn:dem":94,
    "gn:feature_class":"P",
    "gn:feature_code":"PPL",
    "gn:name":"Wudaogou",
    "gn:population":0,
    "gn:timezone":"Asia/Shanghai",
    "iso:country":"CN",
    "name:und_x_variant":[
        "\u4e94\u9053\u6c9f"
    ],
    "wof:name":"Wudaogou",
    "wof:placetype":"locality"
},
  "geometry": {"coordinates":[123.42,40.2068],"type":"Point"}
}