{
  "type": "Feature",
  "properties": {
    "gn:admin1_code":"25",
    "gn:asciiname":"Caomancheng",
    "gn:country_code":"CN",
    "gn:dem":65,
    "gn:feature_class":"P",
    "gn:feature_code":"PPL",
    "gn:name":"Caomancheng",
    "gn:population":0,
    "gn:timezone":"Asia/Shanghai",
    "iso:country":"CN",
    "name:zho_x_preferred":[
        "\u66f9\u6ee1\u57ce"
    ],
    "wof:name":"Caomancheng",
    "wof:placetype":"locality"
},
  "geometry": {"coordinates":[115.056,35.25199999999999],"type":"Point"}
}