{
  "type": "Feature",
  "properties": {
    "gn:admin1_code":"25",
    "gn:asciiname":"Fangtun",
    "gn:country_code":"CN",
    "gn:dem":17,
    "gn:feature_class":"P",
    "gn:feature_code":"PPL",
    "gn:name":"Fangtun",
    "gn:population":0,
    "gn:timezone":"Asia/Shanghai",
    "iso:country":"CN",
    "name:zho_x_preferred":[
        "\u623f\u5c6f"
    ],
    "wof:name":"Fangtun",
    "wof:placetype":"locality"
},
  "geometry": {"coordinates":[117.28100000000001,37.2841],"type":"Point"}
}