{
  "type": "Feature",
  "properties": {
    "gn:admin1_code":"5.0",
    "gn:asciiname":"Donggangzi",
    "gn:country_code":"CN",
    "gn:dem":251,
    "gn:feature_class":"P",
    "gn:feature_code":"PPL",
    "gn:name":"Donggangzi",
    "gn:population":0,
    "gn:timezone":"Asia/Shanghai",
    "iso:country":"CN",
    "name:zho_x_preferred":[
        "\u4e1c\u5c97\u5b50"
    ],
    "wof:name":"Donggangzi",
    "wof:placetype":"locality"
},
  "geometry": {"coordinates":[124.65667999999999,44.40208],"type":"Point"}
}