{
  "type": "Feature",
  "properties": {
    "gn:admin1_code":"7",
    "gn:asciiname":"Shangxibing",
    "gn:country_code":"CN",
    "gn:dem":666,
    "gn:feature_class":"P",
    "gn:feature_code":"PPL",
    "gn:name":"Shangxibing",
    "gn:population":0,
    "gn:timezone":"Asia/Shanghai",
    "iso:country":"CN",
    "name:zho_x_preferred":[
        "\u4e0a\u6eaa\u67c4"
    ],
    "wof:name":"Shangxibing",
    "wof:placetype":"locality"
},
  "geometry": {"coordinates":[117.15235,24.92371],"type":"Point"}
}