{
  "type": "Feature",
  "properties": {
    "gn:admin1_code":"3.0",
    "gn:asciiname":"Lujiafang",
    "gn:country_code":"CN",
    "gn:dem":167,
    "gn:feature_class":"P",
    "gn:feature_code":"PPL",
    "gn:name":"Lujiafang",
    "gn:population":0,
    "gn:timezone":"Asia/Shanghai",
    "iso:country":"CN",
    "name:und_x_variant":[
        "\u82a6\u5bb6\u574a"
    ],
    "wof:name":"Lujiafang",
    "wof:placetype":"locality"
},
  "geometry": {"coordinates":[114.1174,28.11397],"type":"Point"}
}