{
  "type": "Feature",
  "properties": {
    "gn:admin1_code":"10.0",
    "gn:asciiname":"Yaogezhuang",
    "gn:country_code":"CN",
    "gn:dem":3,
    "gn:feature_class":"P",
    "gn:feature_code":"PPL",
    "gn:name":"Yaogezhuang",
    "gn:population":0,
    "gn:timezone":"Asia/Shanghai",
    "iso:country":"CN",
    "name:zho_x_preferred":[
        "\u7476\u5404\u5e84"
    ],
    "wof:name":"Yaogezhuang",
    "wof:placetype":"locality"
},
  "geometry": {"coordinates":[119.00563,39.3602],"type":"Point"}
}