{
  "type": "Feature",
  "properties": {
    "gn:admin1_code":"19.0",
    "gn:asciiname":"Mingxutun",
    "gn:country_code":"CN",
    "gn:dem":249,
    "gn:feature_class":"P",
    "gn:feature_code":"PPL",
    "gn:name":"Mingxutun",
    "gn:population":0,
    "gn:timezone":"Asia/Shanghai",
    "iso:country":"CN",
    "name:zho_x_preferred":[
        "\u660e\u65ed\u5c6f"
    ],
    "wof:name":"Mingxutun",
    "wof:placetype":"locality"
},
  "geometry": {"coordinates":[124.59399999999999,42.5362],"type":"Point"}
}