{
  "type": "Feature",
  "properties": {
    "gn:admin1_code":"15.0",
    "gn:asciiname":"Gaolouzi",
    "gn:country_code":"CN",
    "gn:dem":2180,
    "gn:feature_class":"P",
    "gn:feature_code":"PPL",
    "gn:name":"Gaolouzi",
    "gn:population":0,
    "gn:timezone":"Asia/Shanghai",
    "iso:country":"CN",
    "name:zho_x_preferred":[
        "\u9ad8\u697c\u5b50"
    ],
    "wof:name":"Gaolouzi",
    "wof:placetype":"locality"
},
  "geometry": {"coordinates":[103.55500000000001,35.3397],"type":"Point"}
}