{
  "type": "Feature",
  "properties": {
    "gn:admin1_code":"18",
    "gn:asciiname":"Changzhongshan",
    "gn:country_code":"CN",
    "gn:dem":2229,
    "gn:feature_class":"P",
    "gn:feature_code":"PPL",
    "gn:name":"Changzhongshan",
    "gn:population":0,
    "gn:timezone":"Asia/Shanghai",
    "iso:country":"CN",
    "name:zho_x_preferred":[
        "\u957f\u91cd\u5c71"
    ],
    "wof:name":"Changzhongshan",
    "wof:placetype":"locality"
},
  "geometry": {"coordinates":[104.24299999999999,26.8076],"type":"Point"}
}