{
  "type": "Feature",
  "properties": {
    "gn:admin1_code":"5.0",
    "gn:asciiname":"Toudaomengou",
    "gn:country_code":"CN",
    "gn:dem":587,
    "gn:feature_class":"P",
    "gn:feature_code":"PPL",
    "gn:name":"Toudaomengou",
    "gn:population":0,
    "gn:timezone":"Asia/Shanghai",
    "iso:country":"CN",
    "name:und_x_variant":[
        "\u5934\u9053\u95e8\u6c9f"
    ],
    "wof:name":"Toudaomengou",
    "wof:placetype":"locality"
},
  "geometry": {"coordinates":[126.23088,41.53865],"type":"Point"}
}