{
  "type": "Feature",
  "properties": {
    "gn:admin1_code":"24.0",
    "gn:asciiname":"Zhujiatuncun",
    "gn:country_code":"CN",
    "gn:dem":1148,
    "gn:feature_class":"P",
    "gn:feature_code":"PPL",
    "gn:name":"Zhujiatuncun",
    "gn:population":0,
    "gn:timezone":"Asia/Shanghai",
    "iso:country":"CN",
    "name:zho_x_preferred":[
        "\u6731\u5bb6\u5c6f\u6751"
    ],
    "wof:name":"Zhujiatuncun",
    "wof:placetype":"locality"
},
  "geometry": {"coordinates":[114.18692,40.41435],"type":"Point"}
}