{
  "type": "Feature",
  "properties": {
    "gn:admin1_code":"30.0",
    "gn:asciiname":"Longtian",
    "gn:country_code":"CN",
    "gn:dem":101,
    "gn:feature_class":"P",
    "gn:feature_code":"PPL",
    "gn:name":"Longtian",
    "gn:population":0,
    "gn:timezone":"Asia/Shanghai",
    "iso:country":"CN",
    "name:ceb_x_preferred":[
        "Longtian"
    ],
    "name:swe_x_preferred":[
        "Longtian"
    ],
    "name:zho_x_preferred":[
        "\u5785\u7530"
    ],
    "wof:name":"Longtian",
    "wof:placetype":"locality"
},
  "geometry": {"coordinates":[113.13056,23.92167],"type":"Point"}
}