{
  "type": "Feature",
  "properties": {
    "gn:admin1_code":"19.0",
    "gn:asciiname":"Beiyingcun",
    "gn:country_code":"CN",
    "gn:dem":35,
    "gn:feature_class":"P",
    "gn:feature_code":"PPL",
    "gn:name":"Beiyingcun",
    "gn:population":0,
    "gn:timezone":"Asia/Shanghai",
    "iso:country":"CN",
    "name:zho_x_preferred":[
        "\u5317\u8425\u6751"
    ],
    "wof:name":"Beiyingcun",
    "wof:placetype":"locality"
},
  "geometry": {"coordinates":[123.309,41.6727],"type":"Point"}
}