{
  "type": "Feature",
  "properties": {
    "gn:admin1_code":"26.0",
    "gn:asciiname":"Taoshuliang",
    "gn:country_code":"CN",
    "gn:dem":1036,
    "gn:feature_class":"P",
    "gn:feature_code":"PPL",
    "gn:name":"Taoshuliang",
    "gn:population":0,
    "gn:timezone":"Asia/Shanghai",
    "iso:country":"CN",
    "name:zho_x_preferred":[
        "\u6843\u6811\u6881"
    ],
    "wof:name":"Taoshuliang",
    "wof:placetype":"locality"
},
  "geometry": {"coordinates":[109.99567,36.28211],"type":"Point"}
}