{
  "type": "Feature",
  "properties": {
    "gn:admin1_code":"07",
    "gn:asciiname":"Neiwenkeng",
    "gn:country_code":"CN",
    "gn:dem":449,
    "gn:feature_class":"P",
    "gn:feature_code":"PPL",
    "gn:name":"Neiwenkeng",
    "gn:population":0,
    "gn:timezone":"Asia/Shanghai",
    "iso:country":"CN",
    "name:zho_x_preferred":[
        "\u5185\u6e29\u5751"
    ],
    "wof:name":"Neiwenkeng",
    "wof:placetype":"locality"
},
  "geometry": {"coordinates":[117.37888999999998,25.67944],"type":"Point"}
}