{
  "type": "Feature",
  "properties": {
    "gn:admin1_code":"14.0",
    "gn:asciiname":"Wencun",
    "gn:country_code":"CN",
    "gn:dem":4214,
    "gn:feature_class":"P",
    "gn:feature_code":"PPL",
    "gn:name":"Wencun",
    "gn:population":0,
    "gn:timezone":"Asia/Urumqi",
    "iso:country":"CN",
    "name:bod_x_preferred":[
        "W\u00eancun"
    ],
    "name:und_x_variant":[
        "Reta Gongshe"
    ],
    "name:zho_x_preferred":[
        "\u6e29\u6751"
    ],
    "name:zho_x_variant":[
        "\u70ed\u5b83\u516c\u793e"
    ],
    "wof:name":"Wencun",
    "wof:placetype":"locality"
},
  "geometry": {"coordinates":[95.504,30.904],"type":"Point"}
}