{
  "type": "Feature",
  "properties": {
    "gn:admin1_code":"18.0",
    "gn:asciiname":"Yangsiping",
    "gn:country_code":"CN",
    "gn:dem":875,
    "gn:feature_class":"P",
    "gn:feature_code":"PPL",
    "gn:name":"Yangsiping",
    "gn:population":0,
    "gn:timezone":"Asia/Shanghai",
    "iso:country":"CN",
    "name:zho_x_preferred":[
        "\u6768\u56db\u576a"
    ],
    "wof:name":"Yangsiping",
    "wof:placetype":"locality"
},
  "geometry": {"coordinates":[107.932,27.0162],"type":"Point"}
}