{
  "type": "Feature",
  "properties": {
    "gn:admin1_code":"18",
    "gn:asciiname":"Na'an",
    "gn:country_code":"CN",
    "gn:dem":711,
    "gn:feature_class":"P",
    "gn:feature_code":"PPL",
    "gn:name":"Na\u2019an",
    "gn:population":0,
    "gn:timezone":"Asia/Shanghai",
    "iso:country":"CN",
    "name:und_x_variant":[
        "Na\u2019an"
    ],
    "name:zho_x_preferred":[
        "\u7eb3\u5cb8"
    ],
    "wof:name":"Na'an",
    "wof:placetype":"locality"
},
  "geometry": {"coordinates":[105.94199999999999,25.4202],"type":"Point"}
}