{
  "type": "Feature",
  "properties": {
    "gn:admin1_code":"30.0",
    "gn:asciiname":"Zhegutang",
    "gn:country_code":"CN",
    "gn:dem":540,
    "gn:feature_class":"P",
    "gn:feature_code":"PPL",
    "gn:name":"Zhegutang",
    "gn:population":0,
    "gn:timezone":"Asia/Shanghai",
    "iso:country":"CN",
    "name:zho_x_preferred":[
        "Zhegutang"
    ],
    "name:zho_x_variant":[
        "\u9e67\u9e2a\u5858"
    ],
    "wof:name":"Zhegutang",
    "wof:placetype":"locality"
},
  "geometry": {"coordinates":[113.07361000000002,25.15556],"type":"Point"}
}