{
  "type": "Feature",
  "properties": {
    "gn:admin1_code":"4.0",
    "gn:asciiname":"Tuofengcun",
    "gn:country_code":"CN",
    "gn:dem":13,
    "gn:feature_class":"P",
    "gn:feature_code":"PPL",
    "gn:name":"Tuofengcun",
    "gn:population":0,
    "gn:timezone":"Asia/Shanghai",
    "iso:country":"CN",
    "name:zho_x_preferred":[
        "\u9a7c\u5cf0\u6751"
    ],
    "wof:name":"Tuofengcun",
    "wof:placetype":"locality"
},
  "geometry": {"coordinates":[118.85669,34.57489],"type":"Point"}
}