{
  "type": "Feature",
  "properties": {
    "gn:admin1_code":"3.0",
    "gn:asciiname":"Dianxia",
    "gn:country_code":"CN",
    "gn:dem":50,
    "gn:feature_class":"P",
    "gn:feature_code":"PPLA4",
    "gn:name":"Dianxia",
    "gn:population":0,
    "gn:timezone":"Asia/Shanghai",
    "iso:country":"CN",
    "name:und_x_variant":[
        "\u5e97\u4e0b",
        "Dianxia Zhen",
        "\u5e97\u4e0b\u9547"
    ],
    "wof:name":"Dianxia",
    "wof:placetype":"locality"
},
  "geometry": {"coordinates":[115.60026000000001,27.93557],"type":"Point"}
}