{
  "type": "Feature",
  "properties": {
    "gn:admin1_code":"9.0",
    "gn:asciiname":"Liudaqiao",
    "gn:country_code":"CN",
    "gn:dem":89,
    "gn:feature_class":"P",
    "gn:feature_code":"PPL",
    "gn:name":"Liudaqiao",
    "gn:population":0,
    "gn:timezone":"Asia/Shanghai",
    "iso:country":"CN",
    "name:zho_x_preferred":[
        "\u5218\u5927\u6865"
    ],
    "wof:name":"Liudaqiao",
    "wof:placetype":"locality"
},
  "geometry": {"coordinates":[114.10848,32.63729],"type":"Point"}
}