{
  "type": "Feature",
  "properties": {
    "gn:admin1_code":"4.0",
    "gn:asciiname":"Fenghuacun",
    "gn:country_code":"CN",
    "gn:dem":5,
    "gn:feature_class":"P",
    "gn:feature_code":"PPL",
    "gn:name":"Fenghuacun",
    "gn:population":0,
    "gn:timezone":"Asia/Shanghai",
    "iso:country":"CN",
    "name:zho_x_preferred":[
        "\u4e30\u534e\u6751"
    ],
    "wof:name":"Fenghuacun",
    "wof:placetype":"locality"
},
  "geometry": {"coordinates":[119.52191000000001,33.91669],"type":"Point"}
}