{
  "type": "Feature",
  "properties": {
    "gn:admin1_code":"29",
    "gn:asciiname":"Fengguanqiao",
    "gn:country_code":"CN",
    "gn:dem":1872,
    "gn:feature_class":"P",
    "gn:feature_code":"PPL",
    "gn:name":"Fengguanqiao",
    "gn:population":0,
    "gn:timezone":"Asia/Shanghai",
    "iso:country":"CN",
    "name:und_x_variant":[
        "\u51af\u5b98\u6865"
    ],
    "wof:name":"Fengguanqiao",
    "wof:placetype":"locality"
},
  "geometry": {"coordinates":[103.75143,25.51611],"type":"Point"}
}