{
  "type": "Feature",
  "properties": {
    "gn:admin1_code":"14",
    "gn:asciiname":"Caiqiong",
    "gn:country_code":"CN",
    "gn:dem":4894,
    "gn:feature_class":"P",
    "gn:feature_code":"PPL",
    "gn:name":"Caiqiong",
    "gn:population":0,
    "gn:timezone":"Asia/Urumqi",
    "iso:country":"CN",
    "name:zho_x_preferred":[
        "\u91c7\u743c"
    ],
    "wof:name":"Caiqiong",
    "wof:placetype":"locality"
},
  "geometry": {"coordinates":[89.4816,29.9256],"type":"Point"}
}