{
  "type": "Feature",
  "properties": {
    "gn:admin1_code":"14.0",
    "gn:asciiname":"Rouxue",
    "gn:country_code":"CN",
    "gn:dem":3981,
    "gn:feature_class":"P",
    "gn:feature_code":"PPL",
    "gn:name":"Rouxue",
    "gn:population":0,
    "gn:timezone":"Asia/Urumqi",
    "iso:country":"CN",
    "name:zho_x_preferred":[
        "\u8089\u8840"
    ],
    "wof:name":"Rouxue",
    "wof:placetype":"locality"
},
  "geometry": {"coordinates":[96.87788999999999,31.75788],"type":"Point"}
}