{
  "type": "Feature",
  "properties": {
    "gn:admin1_code":"1.0",
    "gn:asciiname":"Zhumiaocun",
    "gn:country_code":"CN",
    "gn:dem":33,
    "gn:feature_class":"P",
    "gn:feature_code":"PPL",
    "gn:name":"Zhumiaocun",
    "gn:population":0,
    "gn:timezone":"Asia/Shanghai",
    "iso:country":"CN",
    "name:und_x_variant":[
        "Zhumiao"
    ],
    "name:zho_x_preferred":[
        "\u6731\u5e99\u6751"
    ],
    "wof:name":"Zhumiaocun",
    "wof:placetype":"locality"
},
  "geometry": {"coordinates":[116.45065,33.77629],"type":"Point"}
}