{
  "type": "Feature",
  "properties": {
    "gn:admin1_code":"29.0",
    "gn:asciiname":"Niutangyao",
    "gn:country_code":"CN",
    "gn:dem":1430,
    "gn:feature_class":"P",
    "gn:feature_code":"PPL",
    "gn:name":"Niutangyao",
    "gn:population":0,
    "gn:timezone":"Asia/Shanghai",
    "iso:country":"CN",
    "name:zho_x_preferred":[
        "\u725b\u5858\u7476"
    ],
    "wof:name":"Niutangyao",
    "wof:placetype":"locality"
},
  "geometry": {"coordinates":[102.88500000000001,22.688],"type":"Point"}
}