{
  "type": "Feature",
  "properties": {
    "gn:admin1_code":"19.0",
    "gn:asciiname":"Shangu",
    "gn:country_code":"CN",
    "gn:dem":42,
    "gn:feature_class":"P",
    "gn:feature_code":"PPL",
    "gn:name":"Shangu",
    "gn:population":0,
    "gn:timezone":"Asia/Shanghai",
    "iso:country":"CN",
    "name:und_x_variant":[
        "\u5c71\u8c37"
    ],
    "name:zho_x_preferred":[
        "\u5c71\u8c37"
    ],
    "wof:name":"Shangu",
    "wof:placetype":"locality"
},
  "geometry": {"coordinates":[124.26087,40.11396],"type":"Point"}
}