{
  "type": "Feature",
  "properties": {
    "gn:admin1_code":"18",
    "gn:asciiname":"Zibaigou",
    "gn:country_code":"CN",
    "gn:dem":946,
    "gn:feature_class":"P",
    "gn:feature_code":"PPL",
    "gn:name":"Zibaigou",
    "gn:population":0,
    "gn:timezone":"Asia/Shanghai",
    "iso:country":"CN",
    "name:zho_x_preferred":[
        "\u6893\u67cf\u6c9f"
    ],
    "wof:name":"Zibaigou",
    "wof:placetype":"locality"
},
  "geometry": {"coordinates":[107.81100000000001,27.6318],"type":"Point"}
}