{
  "type": "Feature",
  "properties": {
    "gn:admin1_code":"24.0",
    "gn:asciiname":"Longchitou",
    "gn:country_code":"CN",
    "gn:dem":1075,
    "gn:feature_class":"P",
    "gn:feature_code":"PPL",
    "gn:name":"Longchitou",
    "gn:population":0,
    "gn:timezone":"Asia/Shanghai",
    "iso:country":"CN",
    "name:zho_x_preferred":[
        "\u9f99\u6c60\u5934"
    ],
    "wof:name":"Longchitou",
    "wof:placetype":"locality"
},
  "geometry": {"coordinates":[111.55601,37.2089],"type":"Point"}
}