{
  "type": "Feature",
  "properties": {
    "gn:admin1_code":"33.0",
    "gn:asciiname":"Banbiancheng",
    "gn:country_code":"CN",
    "gn:dem":721,
    "gn:feature_class":"P",
    "gn:feature_code":"PPL",
    "gn:name":"Banbiancheng",
    "gn:population":0,
    "gn:timezone":"Asia/Shanghai",
    "iso:country":"CN",
    "name:zho_x_preferred":[
        "\u534a\u8fb9\u57ce"
    ],
    "wof:name":"Banbiancheng",
    "wof:placetype":"locality"
},
  "geometry": {"coordinates":[108.91585000000001,28.94391],"type":"Point"}
}