{
  "type": "Feature",
  "properties": {
    "gn:admin1_code":"14.0",
    "gn:asciiname":"Naqog",
    "gn:country_code":"CN",
    "gn:dem":4585,
    "gn:feature_class":"P",
    "gn:feature_code":"PPL",
    "gn:name":"Naqog",
    "gn:population":0,
    "gn:timezone":"Asia/Urumqi",
    "iso:country":"CN",
    "name:bod_x_preferred":[
        "Naqog"
    ],
    "name:zho_x_preferred":[
        "Nanmuque"
    ],
    "name:zho_x_variant":[
        "\u5357\u6728\u5374",
        "Honghai Gongshe",
        "\u7ea2\u6d77\u516c\u793e"
    ],
    "wof:name":"Naqog",
    "wof:placetype":"locality"
},
  "geometry": {"coordinates":[91.502,32.102],"type":"Point"}
}