{
  "type": "Feature",
  "properties": {
    "gn:admin1_code":"23.0",
    "gn:asciiname":"Wangjiaxiang",
    "gn:country_code":"CN",
    "gn:dem":4,
    "gn:feature_class":"P",
    "gn:feature_code":"PPL",
    "gn:name":"Wangjiaxiang",
    "gn:population":0,
    "gn:timezone":"Asia/Shanghai",
    "iso:country":"CN",
    "name:zho_x_preferred":[
        "Wangjiaxiang"
    ],
    "name:zho_x_variant":[
        "\u738b\u5bb6\u5df7"
    ],
    "wof:name":"Wangjiaxiang",
    "wof:placetype":"locality"
},
  "geometry": {"coordinates":[121.18728,31.44085],"type":"Point"}
}