{
  "type": "Feature",
  "properties": {
    "gn:admin1_code":"14",
    "gn:asciiname":"Heibu",
    "gn:country_code":"CN",
    "gn:dem":5018,
    "gn:feature_class":"P",
    "gn:feature_code":"PPL",
    "gn:name":"Heibu",
    "gn:population":0,
    "gn:timezone":"Asia/Urumqi",
    "iso:country":"CN",
    "name:zho_x_preferred":[
        "\u9ed1\u5e03"
    ],
    "wof:name":"Heibu",
    "wof:placetype":"locality"
},
  "geometry": {"coordinates":[89.4883,30.0249],"type":"Point"}
}