{
  "type": "Feature",
  "properties": {
    "gn:admin1_code":"18.0",
    "gn:asciiname":"Luhua",
    "gn:country_code":"CN",
    "gn:dem":1253,
    "gn:feature_class":"P",
    "gn:feature_code":"PPL",
    "gn:name":"L\u00fchua",
    "gn:population":0,
    "gn:timezone":"Asia/Shanghai",
    "iso:country":"CN",
    "wof:name":"Luhua",
    "wof:placetype":"locality"
},
  "geometry": {"coordinates":[106.09999999999999,26.94167],"type":"Point"}
}