{
  "type": "Feature",
  "properties": {
    "gn:admin1_code":"11.0",
    "gn:asciiname":"Taoliwan",
    "gn:country_code":"CN",
    "gn:dem":571,
    "gn:feature_class":"P",
    "gn:feature_code":"PPL",
    "gn:name":"Taoliwan",
    "gn:population":0,
    "gn:timezone":"Asia/Shanghai",
    "iso:country":"CN",
    "name:zho_x_preferred":[
        "\u6843\u674e\u6e7e"
    ],
    "wof:name":"Taoliwan",
    "wof:placetype":"locality"
},
  "geometry": {"coordinates":[110.96857,27.97405],"type":"Point"}
}