{
  "type": "Feature",
  "properties": {
    "gn:admin1_code":"19.0",
    "gn:asciiname":"Shuangyanjing",
    "gn:country_code":"CN",
    "gn:dem":49,
    "gn:feature_class":"P",
    "gn:feature_code":"PPL",
    "gn:name":"Shuangyanjing",
    "gn:population":0,
    "gn:timezone":"Asia/Shanghai",
    "iso:country":"CN",
    "name:zho_x_preferred":[
        "\u53cc\u773c\u4e95"
    ],
    "wof:name":"Shuangyanjing",
    "wof:placetype":"locality"
},
  "geometry": {"coordinates":[121.9431,39.79792],"type":"Point"}
}