{
  "type": "Feature",
  "properties": {
    "gn:admin1_code":"10",
    "gn:asciiname":"Majiazi",
    "gn:country_code":"CN",
    "gn:dem":833,
    "gn:feature_class":"P",
    "gn:feature_code":"PPL",
    "gn:name":"Majiazi",
    "gn:population":0,
    "gn:timezone":"Asia/Shanghai",
    "iso:country":"CN",
    "name:zho_x_preferred":[
        "\u9a6c\u67b6\u5b50"
    ],
    "wof:name":"Majiazi",
    "wof:placetype":"locality"
},
  "geometry": {"coordinates":[118.56271,41.26002],"type":"Point"}
}