{
  "type": "Feature",
  "properties": {
    "gn:admin1_code":"14.0",
    "gn:asciiname":"Samen",
    "gn:country_code":"CN",
    "gn:dem":4609,
    "gn:feature_class":"P",
    "gn:feature_code":"PPL",
    "gn:name":"Samen",
    "gn:population":0,
    "gn:timezone":"Asia/Urumqi",
    "iso:country":"CN",
    "name:bod_x_preferred":[
        "Samai"
    ],
    "name:zho_x_preferred":[
        "\u8428\u95e8"
    ],
    "wof:name":"Samen",
    "wof:placetype":"locality"
},
  "geometry": {"coordinates":[83.7937,33.23699999999999],"type":"Point"}
}