{
  "type": "Feature",
  "properties": {
    "gn:admin1_code":"29.0",
    "gn:asciiname":"Jiuneng",
    "gn:country_code":"CN",
    "gn:dem":1340,
    "gn:feature_class":"P",
    "gn:feature_code":"PPL",
    "gn:name":"Jiuneng",
    "gn:population":0,
    "gn:timezone":"Asia/Shanghai",
    "iso:country":"CN",
    "name:zho_x_preferred":[
        "\u5c31\u80fd"
    ],
    "wof:name":"Jiuneng",
    "wof:placetype":"locality"
},
  "geometry": {"coordinates":[103.313,23.5186],"type":"Point"}
}