{
  "type": "Feature",
  "properties": {
    "gn:admin1_code":"25",
    "gn:asciiname":"Jiangjiazhuang",
    "gn:country_code":"CN",
    "gn:dem":77,
    "gn:feature_class":"P",
    "gn:feature_code":"PPL",
    "gn:name":"Jiangjiazhuang",
    "gn:population":0,
    "gn:timezone":"Asia/Shanghai",
    "iso:country":"CN",
    "name:und_x_variant":[
        "\u848b\u5bb6\u5e84"
    ],
    "wof:name":"Jiangjiazhuang",
    "wof:placetype":"locality"
},
  "geometry": {"coordinates":[119.23963000000001,35.93602],"type":"Point"}
}