{
  "type": "Feature",
  "properties": {
    "gn:admin1_code":"30.0",
    "gn:asciiname":"Sihecun",
    "gn:country_code":"CN",
    "gn:dem":4,
    "gn:feature_class":"P",
    "gn:feature_code":"PPL",
    "gn:name":"Sihecun",
    "gn:population":0,
    "gn:timezone":"Asia/Shanghai",
    "iso:country":"CN",
    "name:zho_x_preferred":[
        "\u6cd7\u548c\u6751"
    ],
    "wof:name":"Sihecun",
    "wof:placetype":"locality"
},
  "geometry": {"coordinates":[116.43685000000001,23.23147],"type":"Point"}
}