{
  "type": "Feature",
  "properties": {
    "gn:admin1_code":"32.0",
    "gn:asciiname":"Bietuo",
    "gn:country_code":"CN",
    "gn:dem":2216,
    "gn:feature_class":"P",
    "gn:feature_code":"PPL",
    "gn:name":"Bietuo",
    "gn:population":0,
    "gn:timezone":"Asia/Shanghai",
    "iso:country":"CN",
    "name:zho_x_preferred":[
        "\u522b\u6258"
    ],
    "wof:name":"Bietuo",
    "wof:placetype":"locality"
},
  "geometry": {"coordinates":[102.254,29.8405],"type":"Point"}
}