{
  "type": "Feature",
  "properties": {
    "gn:admin1_code":"15.0",
    "gn:asciiname":"Guanjiagou",
    "gn:country_code":"CN",
    "gn:dem":1516,
    "gn:feature_class":"P",
    "gn:feature_code":"PPL",
    "gn:name":"Guanjiagou",
    "gn:population":0,
    "gn:timezone":"Asia/Shanghai",
    "iso:country":"CN",
    "name:zho_x_preferred":[
        "\u5173\u5bb6\u6c9f"
    ],
    "wof:name":"Guanjiagou",
    "wof:placetype":"locality"
},
  "geometry": {"coordinates":[104.154,36.3387],"type":"Point"}
}