{
  "type": "Feature",
  "properties": {
    "gn:admin1_code":"26.0",
    "gn:asciiname":"Tianxincun",
    "gn:country_code":"CN",
    "gn:dem":695,
    "gn:feature_class":"P",
    "gn:feature_code":"PPL",
    "gn:name":"Tianxincun",
    "gn:population":0,
    "gn:timezone":"Asia/Shanghai",
    "iso:country":"CN",
    "name:zho_x_preferred":[
        "\u7530\u5fc3\u6751"
    ],
    "wof:name":"Tianxincun",
    "wof:placetype":"locality"
},
  "geometry": {"coordinates":[108.30683000000001,32.86528],"type":"Point"}
}