{
  "type": "Feature",
  "properties": {
    "gn:admin1_code":"15.0",
    "gn:asciiname":"Mahuangcha",
    "gn:country_code":"CN",
    "gn:dem":2063,
    "gn:feature_class":"P",
    "gn:feature_code":"PPL",
    "gn:name":"Mahuangcha",
    "gn:population":0,
    "gn:timezone":"Asia/Shanghai",
    "iso:country":"CN",
    "name:zho_x_preferred":[
        "\u9a6c\u9ec4\u5c94"
    ],
    "wof:name":"Mahuangcha",
    "wof:placetype":"locality"
},
  "geometry": {"coordinates":[104.883,35.2123],"type":"Point"}
}