{
  "type": "Feature",
  "properties": {
    "gn:admin1_code":"12.0",
    "gn:asciiname":"Zhenjiakeng",
    "gn:country_code":"CN",
    "gn:dem":1044,
    "gn:feature_class":"P",
    "gn:feature_code":"PPL",
    "gn:name":"Zhenjiakeng",
    "gn:population":0,
    "gn:timezone":"Asia/Shanghai",
    "iso:country":"CN",
    "name:zho_x_preferred":[
        "\u771f\u5047\u5751"
    ],
    "wof:name":"Zhenjiakeng",
    "wof:placetype":"locality"
},
  "geometry": {"coordinates":[108.87635,29.48317],"type":"Point"}
}