{
  "type": "Feature",
  "properties": {
    "gn:admin1_code":"12.0",
    "gn:asciiname":"Meitangou",
    "gn:country_code":"CN",
    "gn:dem":820,
    "gn:feature_class":"P",
    "gn:feature_code":"PPL",
    "gn:name":"Meitangou",
    "gn:population":0,
    "gn:timezone":"Asia/Shanghai",
    "iso:country":"CN",
    "name:zho_x_preferred":[
        "\u7164\u70ad\u6c9f"
    ],
    "wof:name":"Meitangou",
    "wof:placetype":"locality"
},
  "geometry": {"coordinates":[109.85105,30.6344],"type":"Point"}
}