{
  "type": "Feature",
  "properties": {
    "gn:admin1_code":"19.0",
    "gn:asciiname":"Goumenzicun",
    "gn:country_code":"CN",
    "gn:dem":240,
    "gn:feature_class":"P",
    "gn:feature_code":"PPL",
    "gn:name":"Goumenzicun",
    "gn:population":0,
    "gn:timezone":"Asia/Shanghai",
    "iso:country":"CN",
    "name:zho_x_preferred":[
        "\u6c9f\u95e8\u5b50\u6751"
    ],
    "wof:name":"Goumenzicun",
    "wof:placetype":"locality"
},
  "geometry": {"coordinates":[120.31966,41.51305],"type":"Point"}
}