{
  "type": "Feature",
  "properties": {
    "gn:admin1_code":"30",
    "gn:asciiname":"Cunxin",
    "gn:country_code":"CN",
    "gn:dem":47,
    "gn:feature_class":"P",
    "gn:feature_code":"PPL",
    "gn:name":"Cunxin",
    "gn:population":0,
    "gn:timezone":"Asia/Urumqi",
    "iso:country":"CN",
    "name:zho_x_preferred":[
        "\u5b58\u5fc3"
    ],
    "wof:name":"Cunxin",
    "wof:placetype":"locality"
},
  "geometry": {"coordinates":[110.67549,22.00324],"type":"Point"}
}