{
  "type": "Feature",
  "properties": {
    "gn:admin1_code":"4.0",
    "gn:asciiname":"Baidian",
    "gn:country_code":"CN",
    "gn:dem":3,
    "gn:feature_class":"P",
    "gn:feature_code":"PPLA4",
    "gn:name":"Baidian",
    "gn:population":0,
    "gn:timezone":"Asia/Shanghai",
    "iso:country":"CN",
    "name:und_x_variant":[
        "\u767d\u7538",
        "Baidian Zhen",
        "\u767d\u7538\u9547"
    ],
    "wof:name":"Baidian",
    "wof:placetype":"locality"
},
  "geometry": {"coordinates":[120.25700000000001,32.67087],"type":"Point"}
}