{
  "type": "Feature",
  "properties": {
    "gn:admin1_code":"15.0",
    "gn:asciiname":"Wangjiashan",
    "gn:country_code":"CN",
    "gn:dem":2648,
    "gn:feature_class":"P",
    "gn:feature_code":"PPL",
    "gn:name":"Wangjiashan",
    "gn:population":0,
    "gn:timezone":"Asia/Shanghai",
    "iso:country":"CN",
    "name:und_x_variant":[
        "\u738b\u5bb6\u5c71"
    ],
    "wof:name":"Wangjiashan",
    "wof:placetype":"locality"
},
  "geometry": {"coordinates":[104.54156,34.36718],"type":"Point"}
}