{
  "type": "Feature",
  "properties": {
    "gn:admin1_code":"10",
    "gn:asciiname":"Douzhuangzi",
    "gn:cc2":"CN",
    "gn:country_code":"CN",
    "gn:dem":5,
    "gn:feature_class":"P",
    "gn:feature_code":"PPL",
    "gn:name":"Douzhuangzi",
    "gn:population":0,
    "gn:timezone":"Asia/Shanghai",
    "iso:country":"CN",
    "name:und_x_variant":[
        "Tou-chuang-tzu",
        "Tou-chia-chuang",
        "Douzhuangzi"
    ],
    "wof:name":"Douzhuangzi",
    "wof:placetype":"locality"
},
  "geometry": {"coordinates":[117.32389000000001,38.57917],"type":"Point"}
}