{
  "type": "Feature",
  "properties": {
    "gn:admin1_code":"32.0",
    "gn:asciiname":"Rongcharong",
    "gn:country_code":"CN",
    "gn:dem":2441,
    "gn:feature_class":"P",
    "gn:feature_code":"PPL",
    "gn:name":"Rongcharong",
    "gn:population":0,
    "gn:timezone":"Asia/Shanghai",
    "iso:country":"CN",
    "name:zho_x_preferred":[
        "\u7ed2\u5c94\u7ed2"
    ],
    "wof:name":"Rongcharong",
    "wof:placetype":"locality"
},
  "geometry": {"coordinates":[99.0658,29.3969],"type":"Point"}
}