{
  "type": "Feature",
  "properties": {
    "gn:admin1_code":"15.0",
    "gn:asciiname":"Sherengou",
    "gn:country_code":"CN",
    "gn:dem":3176,
    "gn:feature_class":"P",
    "gn:feature_code":"PPL",
    "gn:name":"Sherengou",
    "gn:population":0,
    "gn:timezone":"Asia/Shanghai",
    "iso:country":"CN",
    "name:und_x_variant":[
        "\u6d89\u4ec1\u6c9f"
    ],
    "wof:name":"Sherengou",
    "wof:placetype":"locality"
},
  "geometry": {"coordinates":[104.00054,34.79917],"type":"Point"}
}