{
  "type": "Feature",
  "properties": {
    "gn:admin1_code":"5.0",
    "gn:asciiname":"Defacun",
    "gn:country_code":"CN",
    "gn:dem":353,
    "gn:feature_class":"P",
    "gn:feature_code":"PPL",
    "gn:name":"Defacun",
    "gn:population":0,
    "gn:timezone":"Asia/Shanghai",
    "iso:country":"CN",
    "name:zho_x_preferred":[
        "\u5fb7\u53d1\u6751"
    ],
    "wof:name":"Defacun",
    "wof:placetype":"locality"
},
  "geometry": {"coordinates":[121.77551,45.82403],"type":"Point"}
}