{
  "type": "Feature",
  "properties": {
    "gn:admin1_code":"24.0",
    "gn:asciiname":"Ximotan",
    "gn:country_code":"CN",
    "gn:dem":455,
    "gn:feature_class":"P",
    "gn:feature_code":"PPL",
    "gn:name":"Ximotan",
    "gn:population":0,
    "gn:timezone":"Asia/Shanghai",
    "iso:country":"CN",
    "name:zho_x_preferred":[
        "\u897f\u78e8\u6ee9"
    ],
    "wof:name":"Ximotan",
    "wof:placetype":"locality"
},
  "geometry": {"coordinates":[112.58750999999999,35.33793],"type":"Point"}
}