{
  "type": "Feature",
  "properties": {
    "gn:admin1_code":"20.0",
    "gn:asciiname":"Dabagou",
    "gn:country_code":"CN",
    "gn:dem":309,
    "gn:feature_class":"P",
    "gn:feature_code":"PPLA3",
    "gn:name":"Dabagou",
    "gn:population":0,
    "gn:timezone":"Asia/Shanghai",
    "iso:country":"CN",
    "name:und_x_variant":[
        "\u5927\u575d\u6c9f",
        "Dabagou Zhen",
        "Ke\u2019erqin Youyi Qianqi",
        "Horqin Youyi Qianqi",
        "\u5927\u575d\u6c9f\u9547",
        "\u79d1\u5c14\u6c81\u53f3\u7ffc\u524d\u65d7"
    ],
    "name:zho_x_preferred":[
        "Dabagou"
    ],
    "wof:name":"Dabagou",
    "wof:placetype":"locality"
},
  "geometry": {"coordinates":[121.91632,46.06946],"type":"Point"}
}