{
  "type": "Feature",
  "properties": {
    "gn:admin1_code":"32.0",
    "gn:asciiname":"Leibojing",
    "gn:country_code":"CN",
    "gn:dem":548,
    "gn:feature_class":"P",
    "gn:feature_code":"PPL",
    "gn:name":"Leibojing",
    "gn:population":0,
    "gn:timezone":"Asia/Shanghai",
    "iso:country":"CN",
    "name:zho_x_preferred":[
        "\u96f7\u8584\u4e95"
    ],
    "wof:name":"Leibojing",
    "wof:placetype":"locality"
},
  "geometry": {"coordinates":[104.87702,30.47692],"type":"Point"}
}