{
  "type": "Feature",
  "properties": {
    "gn:admin1_code":"18",
    "gn:asciiname":"Xiaozhuchang",
    "gn:country_code":"CN",
    "gn:dem":1589,
    "gn:feature_class":"P",
    "gn:feature_code":"PPL",
    "gn:name":"Xiaozhuchang",
    "gn:population":0,
    "gn:timezone":"Asia/Shanghai",
    "iso:country":"CN",
    "name:zho_x_preferred":[
        "\u5c0f\u732a\u573a"
    ],
    "wof:name":"Xiaozhuchang",
    "wof:placetype":"locality"
},
  "geometry": {"coordinates":[105.855,26.6326],"type":"Point"}
}