{
  "type": "Feature",
  "properties": {
    "gn:admin1_code":"32.0",
    "gn:asciiname":"Dushu",
    "gn:country_code":"CN",
    "gn:dem":1727,
    "gn:feature_class":"P",
    "gn:feature_code":"PPL",
    "gn:name":"Dushu",
    "gn:population":0,
    "gn:timezone":"Asia/Shanghai",
    "iso:country":"CN",
    "name:nor_x_preferred":[
        "Dushu"
    ],
    "name:spa_x_preferred":[
        "Dushu"
    ],
    "name:zho_x_preferred":[
        "\u72ec\u6811"
    ],
    "name:zho_x_variant":[
        "\u8bfb\u4e66"
    ],
    "wof:name":"Dushu",
    "wof:placetype":"locality"
},
  "geometry": {"coordinates":[101.96899999999999,27.0304],"type":"Point"}
}