{
  "type": "Feature",
  "properties": {
    "gn:admin1_code":"02",
    "gn:asciiname":"Yang-chia-ti",
    "gn:country_code":"CN",
    "gn:dem":417,
    "gn:feature_class":"P",
    "gn:feature_code":"PPL",
    "gn:name":"Yang-chia-ti",
    "gn:population":0,
    "gn:timezone":"Asia/Shanghai",
    "iso:country":"CN",
    "wof:name":"Yang-chia-ti",
    "wof:placetype":"locality"
},
  "geometry": {"coordinates":[120.92638999999998,28.28389],"type":"Point"}
}