{
  "type": "Feature",
  "properties": {
    "gn:admin1_code":"2.0",
    "gn:asciiname":"Dongxucun",
    "gn:country_code":"CN",
    "gn:dem":156,
    "gn:feature_class":"P",
    "gn:feature_code":"PPL",
    "gn:name":"Dongxucun",
    "gn:population":0,
    "gn:timezone":"Asia/Shanghai",
    "iso:country":"CN",
    "name:und_x_variant":[
        "Dongxu",
        "\u4e1c\u53d9",
        "\u4e1c\u53d9\u6751",
        "Dongxucun"
    ],
    "wof:name":"Dongxucun",
    "wof:placetype":"locality"
},
  "geometry": {"coordinates":[119.56882,30.18659],"type":"Point"}
}