{
  "type": "Feature",
  "properties": {
    "gn:admin1_code":"5.0",
    "gn:asciiname":"Suijiagou",
    "gn:country_code":"CN",
    "gn:dem":480,
    "gn:feature_class":"P",
    "gn:feature_code":"PPL",
    "gn:name":"Suijiagou",
    "gn:population":0,
    "gn:timezone":"Asia/Shanghai",
    "iso:country":"CN",
    "name:zho_x_preferred":[
        "\u968b\u5bb6\u6c9f"
    ],
    "wof:name":"Suijiagou",
    "wof:placetype":"locality"
},
  "geometry": {"coordinates":[125.10448,42.49307],"type":"Point"}
}