{
  "type": "Feature",
  "properties": {
    "gn:admin1_code":"19.0",
    "gn:asciiname":"Shoubingtaicun",
    "gn:country_code":"CN",
    "gn:dem":68,
    "gn:feature_class":"P",
    "gn:feature_code":"PPL",
    "gn:name":"Shoubingtaicun",
    "gn:population":0,
    "gn:timezone":"Asia/Shanghai",
    "iso:country":"CN",
    "name:zho_x_preferred":[
        "\u6536\u5175\u53f0\u6751"
    ],
    "wof:name":"Shoubingtaicun",
    "wof:placetype":"locality"
},
  "geometry": {"coordinates":[123.599,41.7173],"type":"Point"}
}