{
  "type": "Feature",
  "properties": {
    "gn:admin1_code":"14.0",
    "gn:asciiname":"Jiyacun",
    "gn:country_code":"CN",
    "gn:dem":3676,
    "gn:feature_class":"P",
    "gn:feature_code":"PPL",
    "gn:name":"Jiyacun",
    "gn:population":0,
    "gn:timezone":"Asia/Urumqi",
    "iso:country":"CN",
    "name:zho_x_preferred":[
        "\u5409\u4e9a\u6751"
    ],
    "wof:name":"Jiyacun",
    "wof:placetype":"locality"
},
  "geometry": {"coordinates":[96.31551,31.7765],"type":"Point"}
}