{
  "type": "Feature",
  "properties": {
    "gn:admin1_code":"24.0",
    "gn:asciiname":"Baitupo",
    "gn:country_code":"CN",
    "gn:dem":1052,
    "gn:feature_class":"P",
    "gn:feature_code":"PPL",
    "gn:name":"Baitupo",
    "gn:population":0,
    "gn:timezone":"Asia/Shanghai",
    "iso:country":"CN",
    "name:zho_x_preferred":[
        "\u767d\u571f\u5761"
    ],
    "wof:name":"Baitupo",
    "wof:placetype":"locality"
},
  "geometry": {"coordinates":[113.57210000000001,38.08543],"type":"Point"}
}