{
  "type": "Feature",
  "properties": {
    "gn:admin1_code":"8.0",
    "gn:asciiname":"Chengzihoutun",
    "gn:country_code":"CN",
    "gn:dem":106,
    "gn:feature_class":"P",
    "gn:feature_code":"PPL",
    "gn:name":"Chengzihoutun",
    "gn:population":0,
    "gn:timezone":"Asia/Shanghai",
    "iso:country":"CN",
    "name:zho_x_preferred":[
        "\u57ce\u5b50\u540e\u5c6f"
    ],
    "wof:name":"Chengzihoutun",
    "wof:placetype":"locality"
},
  "geometry": {"coordinates":[127.7724,45.91454],"type":"Point"}
}