{
  "type": "Feature",
  "properties": {
    "gn:admin1_code":"9.0",
    "gn:asciiname":"Wudadian",
    "gn:country_code":"CN",
    "gn:dem":54,
    "gn:feature_class":"P",
    "gn:feature_code":"PPL",
    "gn:name":"Wudadian",
    "gn:population":0,
    "gn:timezone":"Asia/Shanghai",
    "iso:country":"CN",
    "name:zho_x_preferred":[
        "\u5434\u5927\u5e97"
    ],
    "wof:name":"Wudadian",
    "wof:placetype":"locality"
},
  "geometry": {"coordinates":[114.88836999999999,31.9759],"type":"Point"}
}