{
  "type": "Feature",
  "properties": {
    "gn:admin1_code":"3.0",
    "gn:asciiname":"Dapengxia",
    "gn:country_code":"CN",
    "gn:dem":454,
    "gn:feature_class":"P",
    "gn:feature_code":"PPL",
    "gn:name":"Dapengxia",
    "gn:population":0,
    "gn:timezone":"Asia/Shanghai",
    "iso:country":"CN",
    "name:und_x_variant":[
        "\u5927\u68da\u4e0b"
    ],
    "wof:name":"Dapengxia",
    "wof:placetype":"locality"
},
  "geometry": {"coordinates":[114.33153,28.55661],"type":"Point"}
}