{
  "type": "Feature",
  "properties": {
    "gn:admin1_code":"13.0",
    "gn:asciiname":"Kurti",
    "gn:country_code":"CN",
    "gn:dem":1003,
    "gn:feature_class":"P",
    "gn:feature_code":"PPLA4",
    "gn:name":"K\u00fcrti",
    "gn:population":0,
    "gn:timezone":"Asia/Urumqi",
    "iso:country":"CN",
    "name:ceb_x_preferred":[
        "Kurti"
    ],
    "name:deu_x_preferred":[
        "Kurti"
    ],
    "name:swe_x_preferred":[
        "Kurti"
    ],
    "name:uig_x_preferred":[
        "\u0643\u06c8\u0631\u062a\u0649"
    ],
    "name:uig_x_variant":[
        "\u041a\u04af\u0440\u0442\u0438"
    ],
    "name:und_x_variant":[
        "K\u00fcrti",
        "Ku\u2019er Te",
        "Ku\u2019erte Xiang"
    ],
    "name:zho_x_preferred":[
        "\u5e93\u5c14\u7279"
    ],
    "name:zho_x_variant":[
        "\u5e93\u5c14\u7279\u4e61"
    ],
    "wof:name":"Kurti",
    "wof:placetype":"locality"
},
  "geometry": {"coordinates":[89.30530999999998,47.20003],"type":"Point"}
}