{
  "type": "Feature",
  "properties": {
    "gn:admin1_code":"10",
    "gn:asciiname":"Lugezhai",
    "gn:cc2":"CN",
    "gn:country_code":"CN",
    "gn:dem":72,
    "gn:feature_class":"P",
    "gn:feature_code":"PPL",
    "gn:name":"Lugezhai",
    "gn:population":0,
    "gn:timezone":"Asia/Shanghai",
    "iso:country":"CN",
    "name:und_x_variant":[
        "Lu-kou-chai",
        "Lu-ko-chai",
        "Lugezhai"
    ],
    "wof:name":"Lugezhai",
    "wof:placetype":"locality"
},
  "geometry": {"coordinates":[118.08333,40.01667],"type":"Point"}
}