{
  "type": "Feature",
  "properties": {
    "gn:admin1_code":"29.0",
    "gn:asciiname":"Xiaomeng'e",
    "gn:country_code":"CN",
    "gn:dem":1027,
    "gn:feature_class":"P",
    "gn:feature_code":"PPL",
    "gn:name":"Xiaomeng\u2019e",
    "gn:population":0,
    "gn:timezone":"Asia/Shanghai",
    "iso:country":"CN",
    "name:und_x_variant":[
        "Xiaomeng\u2019e"
    ],
    "name:zho_x_preferred":[
        "\u5c0f\u52d0\u5ce8"
    ],
    "wof:name":"Xiaomeng'e",
    "wof:placetype":"locality"
},
  "geometry": {"coordinates":[99.79130000000001,23.4621],"type":"Point"}
}