{
  "type": "Feature",
  "properties": {
    "gn:admin1_code":"29",
    "gn:asciiname":"Mitangchong",
    "gn:country_code":"CN",
    "gn:dem":1300,
    "gn:feature_class":"P",
    "gn:feature_code":"PPL",
    "gn:name":"Mitangchong",
    "gn:population":0,
    "gn:timezone":"Asia/Shanghai",
    "iso:country":"CN",
    "name:zho_x_preferred":[
        "\u7c73\u6c64\u51b2"
    ],
    "wof:name":"Mitangchong",
    "wof:placetype":"locality"
},
  "geometry": {"coordinates":[105.26600000000001,23.9583],"type":"Point"}
}