{
  "type": "Feature",
  "properties": {
    "gn:admin1_code":"30",
    "gn:asciiname":"Xianting",
    "gn:country_code":"CN",
    "gn:dem":9,
    "gn:feature_class":"P",
    "gn:feature_code":"PPL",
    "gn:name":"Xianting",
    "gn:population":0,
    "gn:timezone":"Asia/Shanghai",
    "iso:country":"CN",
    "name:zho_x_preferred":[
        "\u4ed9\u5ead"
    ],
    "wof:name":"Xianting",
    "wof:placetype":"locality"
},
  "geometry": {"coordinates":[116.56775,23.57624],"type":"Point"}
}