{
  "type": "Feature",
  "properties": {
    "gn:admin1_code":"26.0",
    "gn:asciiname":"Wangyuan",
    "gn:country_code":"CN",
    "gn:dem":1719,
    "gn:feature_class":"P",
    "gn:feature_code":"PPL",
    "gn:name":"Wangyuan",
    "gn:population":0,
    "gn:timezone":"Asia/Shanghai",
    "iso:country":"CN",
    "name:zho_x_preferred":[
        "\u738b\u586c"
    ],
    "wof:name":"Wangyuan",
    "wof:placetype":"locality"
},
  "geometry": {"coordinates":[107.66956999999999,37.384],"type":"Point"}
}