{
  "type": "Feature",
  "properties": {
    "gn:admin1_code":"12.0",
    "gn:asciiname":"Laoshan",
    "gn:country_code":"CN",
    "gn:dem":67,
    "gn:feature_class":"P",
    "gn:feature_code":"PPL",
    "gn:name":"Laoshan",
    "gn:population":0,
    "gn:timezone":"Asia/Shanghai",
    "iso:country":"CN",
    "name:ceb_x_preferred":[
        "Laoshan"
    ],
    "name:deu_x_preferred":[
        "Laoshan"
    ],
    "name:zho_x_preferred":[
        "\u8001\u5c71"
    ],
    "wof:name":"Laoshan",
    "wof:placetype":"locality"
},
  "geometry": {"coordinates":[112.24290999999999,30.64576],"type":"Point"}
}