{
  "type": "Feature",
  "properties": {
    "gn:country":"CN",
    "gn:fcode":"EST",
    "gn:pop":1000,
    "iso:country":"CN",
    "qs:name":"Changan Xin yi hao",
    "qs:photos_9r":0,
    "qs:photos_sr":0,
    "qs:pop_sr":"2",
    "wof:name":"Changan Xin yi hao",
    "wof:placetype":"locality",
    "wof:population":1000
},
  "geometry": {"coordinates":[113.80074,22.81642],"type":"Point"}
}