{
  "type": "Feature",
  "properties": {
    "gn:admin1_code":"18",
    "gn:asciiname":"Shangtangzhang",
    "gn:country_code":"CN",
    "gn:dem":1545,
    "gn:feature_class":"P",
    "gn:feature_code":"PPL",
    "gn:name":"Shangtangzhang",
    "gn:population":0,
    "gn:timezone":"Asia/Shanghai",
    "iso:country":"CN",
    "name:zho_x_preferred":[
        "\u4e0a\u6c64\u7ae0"
    ],
    "wof:name":"Shangtangzhang",
    "wof:placetype":"locality"
},
  "geometry": {"coordinates":[104.58,25.4911],"type":"Point"}
}