{
  "type": "Feature",
  "properties": {
    "gn:admin1_code":"7.0",
    "gn:asciiname":"Banlingli",
    "gn:country_code":"CN",
    "gn:dem":508,
    "gn:feature_class":"P",
    "gn:feature_code":"PPL",
    "gn:name":"Banlingli",
    "gn:population":0,
    "gn:timezone":"Asia/Shanghai",
    "iso:country":"CN",
    "name:zho_x_preferred":[
        "\u534a\u5cad\u91cc"
    ],
    "wof:name":"Banlingli",
    "wof:placetype":"locality"
},
  "geometry": {"coordinates":[118.55632,26.35444],"type":"Point"}
}