{
  "type": "Feature",
  "properties": {
    "gn:admin1_code":"29",
    "gn:asciiname":"Caihuaping",
    "gn:country_code":"CN",
    "gn:dem":2428,
    "gn:feature_class":"P",
    "gn:feature_code":"PPL",
    "gn:name":"Caihuaping",
    "gn:population":0,
    "gn:timezone":"Asia/Shanghai",
    "iso:country":"CN",
    "name:zho_x_preferred":[
        "\u83dc\u82b1\u576a"
    ],
    "name:zho_x_variant":[
        "\u83dc\u82b1\u576a\u9547"
    ],
    "wof:name":"Caihuaping",
    "wof:placetype":"locality"
},
  "geometry": {"coordinates":[102.90300000000001,24.7521],"type":"Point"}
}