{
  "type": "Feature",
  "properties": {
    "gn:admin1_code":"3.0",
    "gn:asciiname":"Dakengwei",
    "gn:country_code":"CN",
    "gn:dem":370,
    "gn:feature_class":"P",
    "gn:feature_code":"PPL",
    "gn:name":"Dakengwei",
    "gn:population":0,
    "gn:timezone":"Asia/Shanghai",
    "iso:country":"CN",
    "name:und_x_variant":[
        "\u5927\u5751\u5c3e"
    ],
    "wof:name":"Dakengwei",
    "wof:placetype":"locality"
},
  "geometry": {"coordinates":[114.46622000000001,24.72742],"type":"Point"}
}