{
  "type": "Feature",
  "properties": {
    "gn:admin1_code":"16.0",
    "gn:asciiname":"Jiandao'ai",
    "gn:country_code":"CN",
    "gn:dem":269,
    "gn:feature_class":"P",
    "gn:feature_code":"PPL",
    "gn:name":"Jiandao\u2019ai",
    "gn:population":0,
    "gn:timezone":"Asia/Shanghai",
    "iso:country":"CN",
    "name:und_x_variant":[
        "Jiandao\u2019ai"
    ],
    "name:zho_x_preferred":[
        "\u526a\u5200\u9698"
    ],
    "wof:name":"Jiandao'ai",
    "wof:placetype":"locality"
},
  "geometry": {"coordinates":[108.73099999999999,24.6082],"type":"Point"}
}