{
  "type": "Feature",
  "properties": {
    "gn:admin1_code":"19.0",
    "gn:asciiname":"Cuijia Buzi",
    "gn:country_code":"CN",
    "gn:dem":7,
    "gn:feature_class":"P",
    "gn:feature_code":"PPL",
    "gn:name":"Cuijia Buzi",
    "gn:population":0,
    "gn:timezone":"Asia/Shanghai",
    "iso:country":"CN",
    "name:und_x_variant":[
        "Cuijia Puzi",
        "Cuijia Buzi"
    ],
    "name:zho_x_preferred":[
        "\u5d14\u5bb6\u5821\u5b50"
    ],
    "wof:name":"Cuijia Buzi",
    "wof:placetype":"locality"
},
  "geometry": {"coordinates":[122.46171,40.72647],"type":"Point"}
}