{
  "type": "Feature",
  "properties": {
    "gn:admin1_code":"32.0",
    "gn:asciiname":"Zhangbangsi",
    "gn:country_code":"CN",
    "gn:dem":433,
    "gn:feature_class":"P",
    "gn:feature_code":"PPL",
    "gn:name":"Zhangbangsi",
    "gn:population":0,
    "gn:timezone":"Asia/Shanghai",
    "iso:country":"CN",
    "name:zho_x_preferred":[
        "\u7ae0\u5e2e\u5bfa"
    ],
    "wof:name":"Zhangbangsi",
    "wof:placetype":"locality"
},
  "geometry": {"coordinates":[105.32662999999999,31.2552],"type":"Point"}
}