{
  "type": "Feature",
  "properties": {
    "gn:admin1_code":"25.0",
    "gn:asciiname":"Xinjiayaocun",
    "gn:country_code":"CN",
    "gn:dem":72,
    "gn:feature_class":"P",
    "gn:feature_code":"PPL",
    "gn:name":"Xinjiayaocun",
    "gn:population":0,
    "gn:timezone":"Asia/Shanghai",
    "iso:country":"CN",
    "name:zho_x_preferred":[
        "\u8f9b\u5bb6\u5c27\u6751"
    ],
    "wof:name":"Xinjiayaocun",
    "wof:placetype":"locality"
},
  "geometry": {"coordinates":[119.40727,35.95105],"type":"Point"}
}