{
  "type": "Feature",
  "properties": {
    "gn:admin1_code":"29.0",
    "gn:asciiname":"Wulucun",
    "gn:country_code":"CN",
    "gn:dem":1392,
    "gn:feature_class":"P",
    "gn:feature_code":"PPL",
    "gn:name":"Wulucun",
    "gn:population":0,
    "gn:timezone":"Asia/Shanghai",
    "iso:country":"CN",
    "name:zho_x_preferred":[
        "\u52a1\u8def\u6751"
    ],
    "wof:name":"Wulucun",
    "wof:placetype":"locality"
},
  "geometry": {"coordinates":[104.032,23.601],"type":"Point"}
}