{
  "type": "Feature",
  "properties": {
    "gn:admin1_code":"18",
    "gn:asciiname":"Wengkong",
    "gn:country_code":"CN",
    "gn:dem":523,
    "gn:feature_class":"P",
    "gn:feature_code":"PPL",
    "gn:name":"Wengkong",
    "gn:population":0,
    "gn:timezone":"Asia/Shanghai",
    "iso:country":"CN",
    "name:zho_x_preferred":[
        "\u74ee\u5b54"
    ],
    "wof:name":"Wengkong",
    "wof:placetype":"locality"
},
  "geometry": {"coordinates":[107.39,27.3078],"type":"Point"}
}