{
  "type": "Feature",
  "properties": {
    "gn:admin1_code":"7",
    "gn:asciiname":"Zuoba",
    "gn:country_code":"CN",
    "gn:dem":511,
    "gn:feature_class":"P",
    "gn:feature_code":"PPL",
    "gn:name":"Zuoba",
    "gn:population":0,
    "gn:timezone":"Asia/Shanghai",
    "iso:country":"CN",
    "name:zho_x_preferred":[
        "\u5de6\u62d4"
    ],
    "wof:name":"Zuoba",
    "wof:placetype":"locality"
},
  "geometry": {"coordinates":[117.06139,25.88694],"type":"Point"}
}