{
  "type": "Feature",
  "properties": {
    "gn:admin1_code":"13",
    "gn:asciiname":"Ereryituan Chang",
    "gn:country_code":"CN",
    "gn:dem":131,
    "gn:feature_class":"P",
    "gn:feature_code":"PPLF",
    "gn:name":"Ereryituan Chang",
    "gn:population":0,
    "gn:timezone":"Asia/Urumqi",
    "iso:country":"CN",
    "name:und_x_variant":[
        "\u4e8c\u4e8c\u4e00\u56e2\u573a"
    ],
    "wof:name":"Ereryituan Chang",
    "wof:placetype":"locality"
},
  "geometry": {"coordinates":[89.00391,42.97113],"type":"Point"}
}