{
  "type": "Feature",
  "properties": {
    "gn:admin1_code":"1.0",
    "gn:asciiname":"Daxingsicun",
    "gn:country_code":"CN",
    "gn:dem":87,
    "gn:feature_class":"P",
    "gn:feature_code":"PPL",
    "gn:name":"Daxingsicun",
    "gn:population":0,
    "gn:timezone":"Asia/Shanghai",
    "iso:country":"CN",
    "name:zho_x_preferred":[
        "\u5927\u5174\u5bfa\u6751"
    ],
    "wof:name":"Daxingsicun",
    "wof:placetype":"locality"
},
  "geometry": {"coordinates":[115.96195,31.77962],"type":"Point"}
}