{
  "type": "Feature",
  "properties": {
    "gn:admin1_code":"9",
    "gn:asciiname":"Tangdi",
    "gn:country_code":"CN",
    "gn:dem":49,
    "gn:feature_class":"P",
    "gn:feature_code":"PPL",
    "gn:name":"Tangdi",
    "gn:population":0,
    "gn:timezone":"Asia/Shanghai",
    "iso:country":"CN",
    "name:zho_x_preferred":[
        "\u68e0\u68e3"
    ],
    "wof:name":"Tangdi",
    "wof:placetype":"locality"
},
  "geometry": {"coordinates":[115.002,33.8692],"type":"Point"}
}