{
  "type": "Feature",
  "properties": {
    "gn:admin1_code":"8.0",
    "gn:asciiname":"Hongxiancun",
    "gn:country_code":"CN",
    "gn:dem":130,
    "gn:feature_class":"P",
    "gn:feature_code":"PPL",
    "gn:name":"Hongxiancun",
    "gn:population":0,
    "gn:timezone":"Asia/Shanghai",
    "iso:country":"CN",
    "name:zho_x_preferred":[
        "\u7ea2\u9c9c\u6751"
    ],
    "wof:name":"Hongxiancun",
    "wof:placetype":"locality"
},
  "geometry": {"coordinates":[126.88525,45.70513],"type":"Point"}
}