{
  "type": "Feature",
  "properties": {
    "gn:admin1_code":"02",
    "gn:asciiname":"Kuangyan",
    "gn:country_code":"CN",
    "gn:dem":8,
    "gn:feature_class":"P",
    "gn:feature_code":"PPLA4",
    "gn:name":"Kuangyan",
    "gn:population":0,
    "gn:timezone":"Asia/Shanghai",
    "iso:country":"CN",
    "name:und_x_variant":[
        "K\u2019uang-yen-shih",
        "K\u2019uang-yen",
        "Kuangyan",
        "\u5321\u5830",
        "Kuangyan Zhen",
        "\u5321\u5830\u9547"
    ],
    "wof:name":"Kuangyan",
    "wof:placetype":"locality"
},
  "geometry": {"coordinates":[121.29586,30.15127],"type":"Point"}
}