{
  "type": "Feature",
  "properties": {
    "gn:admin1_code":"15",
    "gn:asciiname":"Sanshilipu",
    "gn:country_code":"CN",
    "gn:dem":1101,
    "gn:feature_class":"P",
    "gn:feature_code":"PPLA4",
    "gn:name":"Sanshilipu",
    "gn:population":0,
    "gn:timezone":"Asia/Shanghai",
    "iso:country":"CN",
    "name:und_x_variant":[
        "Shilipu",
        "Sanshilipu",
        "\u4e09\u5341\u91cc\u94fa",
        "Sanshilipu Zhen",
        "\u4e09\u5341\u91cc\u94fa\u9547"
    ],
    "wof:name":"Sanshilipu",
    "wof:placetype":"locality"
},
  "geometry": {"coordinates":[107.77839,36.09755],"type":"Point"}
}