{
  "type": "Feature",
  "properties": {
    "gn:admin1_code":"1.0",
    "gn:asciiname":"Wangpoloucun",
    "gn:country_code":"CN",
    "gn:dem":44,
    "gn:feature_class":"P",
    "gn:feature_code":"PPL",
    "gn:name":"Wangpoloucun",
    "gn:population":0,
    "gn:timezone":"Asia/Shanghai",
    "iso:country":"CN",
    "name:und_x_variant":[
        "Wangpolou"
    ],
    "name:zho_x_preferred":[
        "\u738b\u7834\u697c\u6751"
    ],
    "wof:name":"Wangpoloucun",
    "wof:placetype":"locality"
},
  "geometry": {"coordinates":[115.72682,34.03736],"type":"Point"}
}