{
  "type": "Feature",
  "properties": {
    "gn:admin1_code":"32",
    "gn:asciiname":"Muguaping",
    "gn:country_code":"CN",
    "gn:dem":1350,
    "gn:feature_class":"P",
    "gn:feature_code":"PPL",
    "gn:name":"Muguaping",
    "gn:population":0,
    "gn:timezone":"Asia/Shanghai",
    "iso:country":"CN",
    "name:und_x_variant":[
        "Mu-kua-p\u2019ing",
        "Muguaping"
    ],
    "name:zho_x_preferred":[
        "\u6728\u74dc\u576a"
    ],
    "wof:name":"Muguaping",
    "wof:placetype":"locality"
},
  "geometry": {"coordinates":[103.998,31.4446],"type":"Point"}
}