{
  "type": "Feature",
  "properties": {
    "gn:admin1_code":"11.0",
    "gn:asciiname":"Nandaohe",
    "gn:country_code":"CN",
    "gn:dem":29,
    "gn:feature_class":"P",
    "gn:feature_code":"PPL",
    "gn:name":"Nandaohe",
    "gn:population":0,
    "gn:timezone":"Asia/Shanghai",
    "iso:country":"CN",
    "name:zho_x_preferred":[
        "\u5357\u9053\u6cb3"
    ],
    "wof:name":"Nandaohe",
    "wof:placetype":"locality"
},
  "geometry": {"coordinates":[112.71982,29.14589],"type":"Point"}
}