{
  "type": "Feature",
  "properties": {
    "gn:admin1_code":"25",
    "gn:asciiname":"Taishanmiao",
    "gn:country_code":"CN",
    "gn:dem":467,
    "gn:feature_class":"P",
    "gn:feature_code":"PPL",
    "gn:name":"Taishanmiao",
    "gn:population":0,
    "gn:timezone":"Asia/Shanghai",
    "iso:country":"CN",
    "name:zho_x_preferred":[
        "\u6cf0\u5c71\u5e99"
    ],
    "wof:name":"Taishanmiao",
    "wof:placetype":"locality"
},
  "geometry": {"coordinates":[117.246,36.6136],"type":"Point"}
}