{
  "type": "Feature",
  "properties": {
    "gn:admin1_code":"9.0",
    "gn:asciiname":"Dongqingkou",
    "gn:country_code":"CN",
    "gn:dem":427,
    "gn:feature_class":"P",
    "gn:feature_code":"PPL",
    "gn:name":"Dongqingkou",
    "gn:population":0,
    "gn:timezone":"Asia/Shanghai",
    "iso:country":"CN",
    "name:zho_x_preferred":[
        "\u51bb\u6e05\u53e3"
    ],
    "wof:name":"Dongqingkou",
    "wof:placetype":"locality"
},
  "geometry": {"coordinates":[112.24594,33.38079],"type":"Point"}
}