{
  "type": "Feature",
  "properties": {
    "gn:admin1_code":"3.0",
    "gn:asciiname":"Xiayuan",
    "gn:country_code":"CN",
    "gn:dem":102,
    "gn:feature_class":"P",
    "gn:feature_code":"PPL",
    "gn:name":"Xiayuan",
    "gn:population":0,
    "gn:timezone":"Asia/Shanghai",
    "iso:country":"CN",
    "name:und_x_variant":[
        "\u7856\u6e90"
    ],
    "wof:name":"Xiayuan",
    "wof:placetype":"locality"
},
  "geometry": {"coordinates":[116.04433,27.93445],"type":"Point"}
}