{
  "type": "Feature",
  "properties": {
    "gn:admin1_code":"3.0",
    "gn:asciiname":"Anshan",
    "gn:country_code":"CN",
    "gn:dem":43,
    "gn:feature_class":"P",
    "gn:feature_code":"PPL",
    "gn:name":"Anshan",
    "gn:population":0,
    "gn:timezone":"Asia/Shanghai",
    "iso:country":"CN",
    "name:und_x_variant":[
        "\u6697\u5c71"
    ],
    "wof:name":"Anshan",
    "wof:placetype":"locality"
},
  "geometry": {"coordinates":[115.40883999999998,28.5184],"type":"Point"}
}