{
  "type": "Feature",
  "properties": {
    "gn:admin1_code":"25",
    "gn:asciiname":"Dazhangzhuang",
    "gn:country_code":"CN",
    "gn:dem":26,
    "gn:feature_class":"P",
    "gn:feature_code":"PPL",
    "gn:name":"Dazhangzhuang",
    "gn:population":0,
    "gn:timezone":"Asia/Shanghai",
    "iso:country":"CN",
    "name:zho_x_preferred":[
        "\u5927\u5f20\u5e84"
    ],
    "wof:name":"Dazhangzhuang",
    "wof:placetype":"locality"
},
  "geometry": {"coordinates":[117.232,36.7882],"type":"Point"}
}