{
  "type": "Feature",
  "properties": {
    "gn:admin1_code":"32.0",
    "gn:asciiname":"Dilong",
    "gn:country_code":"CN",
    "gn:dem":3607,
    "gn:feature_class":"P",
    "gn:feature_code":"PPL",
    "gn:name":"Dilong",
    "gn:population":0,
    "gn:timezone":"Asia/Shanghai",
    "iso:country":"CN",
    "name:msa_x_preferred":[
        "Dilong"
    ],
    "name:spa_x_preferred":[
        "Dilong"
    ],
    "name:zho_x_preferred":[
        "\u5730\u9f99"
    ],
    "wof:name":"Dilong",
    "wof:placetype":"locality"
},
  "geometry": {"coordinates":[99.46169999999999,32.1412],"type":"Point"}
}