{
  "type": "Feature",
  "properties": {
    "gn:admin1_code":"3",
    "gn:asciiname":"Dandi",
    "gn:country_code":"CN",
    "gn:dem":703,
    "gn:feature_class":"P",
    "gn:feature_code":"PPL",
    "gn:name":"Dandi",
    "gn:population":0,
    "gn:timezone":"Asia/Shanghai",
    "iso:country":"CN",
    "name:ceb_x_preferred":[
        "Dandi"
    ],
    "name:deu_x_preferred":[
        "Dandi"
    ],
    "name:ita_x_preferred":[
        "Dandi"
    ],
    "name:por_x_preferred":[
        "Dandi"
    ],
    "name:swe_x_preferred":[
        "Dandi"
    ],
    "name:tam_x_preferred":[
        "\u0ba4\u0ba3\u0bcd\u0b9f\u0bbf"
    ],
    "name:und_x_variant":[
        "Handi",
        "Dandi"
    ],
    "name:zho_x_preferred":[
        "\u6de1\u5730"
    ],
    "wof:name":"Dandi",
    "wof:placetype":"locality"
},
  "geometry": {"coordinates":[115.83041,24.98893],"type":"Point"}
}