{
  "type": "Feature",
  "properties": {
    "gn:admin1_code":"18",
    "gn:asciiname":"Shuihongyin",
    "gn:country_code":"CN",
    "gn:dem":775,
    "gn:feature_class":"P",
    "gn:feature_code":"PPL",
    "gn:name":"Shuihongyin",
    "gn:population":0,
    "gn:timezone":"Asia/Shanghai",
    "iso:country":"CN",
    "name:zho_x_preferred":[
        "\u6c34\u7ea2\u94f6"
    ],
    "wof:name":"Shuihongyin",
    "wof:placetype":"locality"
},
  "geometry": {"coordinates":[107.86799999999999,28.7196],"type":"Point"}
}