{
  "type": "Feature",
  "properties": {
    "gn:admin1_code":"07",
    "gn:asciiname":"Malunzhai",
    "gn:country_code":"CN",
    "gn:dem":235,
    "gn:feature_class":"P",
    "gn:feature_code":"PPL",
    "gn:name":"Malunzhai",
    "gn:population":0,
    "gn:timezone":"Asia/Shanghai",
    "iso:country":"CN",
    "name:zho_x_preferred":[
        "\u9a6c\u4ed1\u5be8"
    ],
    "wof:name":"Malunzhai",
    "wof:placetype":"locality"
},
  "geometry": {"coordinates":[118.46526,25.31604],"type":"Point"}
}