{
  "type": "Feature",
  "properties": {
    "gn:admin1_code":"31.0",
    "gn:asciiname":"Nanchou",
    "gn:country_code":"CN",
    "gn:dem":48,
    "gn:feature_class":"P",
    "gn:feature_code":"PPL",
    "gn:name":"Nanchou",
    "gn:population":0,
    "gn:timezone":"Asia/Shanghai",
    "iso:country":"CN",
    "name:zho_x_preferred":[
        "Nanchou"
    ],
    "name:zho_x_variant":[
        "\u5357\u4e11"
    ],
    "wof:name":"Nanchou",
    "wof:placetype":"locality"
},
  "geometry": {"coordinates":[110.54423,19.80189],"type":"Point"}
}