{
  "type": "Feature",
  "properties": {
    "gn:admin1_code":"7",
    "gn:asciiname":"Nuanxikeng",
    "gn:country_code":"CN",
    "gn:dem":963,
    "gn:feature_class":"P",
    "gn:feature_code":"PPL",
    "gn:name":"Nuanxikeng",
    "gn:population":0,
    "gn:timezone":"Asia/Shanghai",
    "iso:country":"CN",
    "name:und_x_variant":[
        "\u6696\u6eaa\u5751"
    ],
    "wof:name":"Nuanxikeng",
    "wof:placetype":"locality"
},
  "geometry": {"coordinates":[119.16777999999999,27.3425],"type":"Point"}
}