{
  "type": "Feature",
  "properties": {
    "gn:admin1_code":"18.0",
    "gn:asciiname":"Taoyuan",
    "gn:country_code":"CN",
    "gn:dem":823,
    "gn:feature_class":"P",
    "gn:feature_code":"PPLA4",
    "gn:name":"Taoyuan",
    "gn:population":0,
    "gn:timezone":"Asia/Shanghai",
    "iso:country":"CN",
    "name:ceb_x_preferred":[
        "Taoyuan"
    ],
    "name:deu_x_preferred":[
        "Taoyuan"
    ],
    "name:fra_x_preferred":[
        "Taoyuan"
    ],
    "name:kor_x_preferred":[
        "\ud0c0\uc624\uc704\uc548"
    ],
    "name:lit_x_preferred":[
        "Taojuanas"
    ],
    "name:nld_x_preferred":[
        "Taoyuan"
    ],
    "name:nor_x_preferred":[
        "Taoyuan"
    ],
    "name:por_x_preferred":[
        "Taoyuan"
    ],
    "name:und_x_variant":[
        "Taoyuan Xiang"
    ],
    "name:vie_x_preferred":[
        "\u0110\u00e0o Vi\u00ean"
    ],
    "name:zho_x_preferred":[
        "\u6843\u6e90"
    ],
    "name:zho_x_variant":[
        "\u6843\u6e90\u4e61",
        "\u6843\u5712"
    ],
    "wof:name":"Taoyuan",
    "wof:placetype":"locality"
},
  "geometry": {"coordinates":[107.75623,28.88353],"type":"Point"}
}