{
  "type": "Feature",
  "properties": {
    "gn:admin1_code":"29.0",
    "gn:asciiname":"Liumatan",
    "gn:country_code":"CN",
    "gn:dem":279,
    "gn:feature_class":"P",
    "gn:feature_code":"PPL",
    "gn:name":"Liumatan",
    "gn:population":0,
    "gn:timezone":"Asia/Shanghai",
    "iso:country":"CN",
    "name:zho_x_preferred":[
        "\u6e9c\u9a6c\u6ee9"
    ],
    "wof:name":"Liumatan",
    "wof:placetype":"locality"
},
  "geometry": {"coordinates":[103.91,22.9105],"type":"Point"}
}