{
  "type": "Feature",
  "properties": {
    "gn:admin1_code":"31",
    "gn:asciiname":"Shicha",
    "gn:country_code":"CN",
    "gn:dem":268,
    "gn:feature_class":"P",
    "gn:feature_code":"PPL",
    "gn:name":"Shicha",
    "gn:population":0,
    "gn:timezone":"Asia/Shanghai",
    "iso:country":"CN",
    "name:und_x_variant":[
        "\u4ec0\u63d2"
    ],
    "wof:name":"Shicha",
    "wof:placetype":"locality"
},
  "geometry": {"coordinates":[109.94799999999999,18.825],"type":"Point"}
}