{
  "type": "Feature",
  "properties": {
    "gn:admin1_code":"4.0",
    "gn:asciiname":"Panzhuang Yizu",
    "gn:country_code":"CN",
    "gn:dem":15,
    "gn:feature_class":"P",
    "gn:feature_code":"PPLF",
    "gn:name":"Panzhuang Yizu",
    "gn:population":0,
    "gn:timezone":"Asia/Shanghai",
    "iso:country":"CN",
    "name:zho_x_preferred":[
        "\u6f58\u5e84\u4e00\u7ec4"
    ],
    "wof:name":"Panzhuang Yizu",
    "wof:placetype":"locality"
},
  "geometry": {"coordinates":[118.652,33.0698],"type":"Point"}
}