{
  "type": "Feature",
  "properties": {
    "gn:admin1_code":"25",
    "gn:asciiname":"Xiashuilianyu",
    "gn:country_code":"CN",
    "gn:dem":187,
    "gn:feature_class":"P",
    "gn:feature_code":"PPL",
    "gn:name":"Xiashuilianyu",
    "gn:population":0,
    "gn:timezone":"Asia/Shanghai",
    "iso:country":"CN",
    "name:zho_x_preferred":[
        "\u4e0b\u6c34\u8fde\u5cea"
    ],
    "wof:name":"Xiashuilianyu",
    "wof:placetype":"locality"
},
  "geometry": {"coordinates":[117.749,35.2352],"type":"Point"}
}