{
  "type": "Feature",
  "properties": {
    "gn:admin1_code":"1.0",
    "gn:asciiname":"Beiwangzhaicun",
    "gn:country_code":"CN",
    "gn:dem":27,
    "gn:feature_class":"P",
    "gn:feature_code":"PPL",
    "gn:name":"Beiwangzhaicun",
    "gn:population":0,
    "gn:timezone":"Asia/Shanghai",
    "iso:country":"CN",
    "name:zho_x_preferred":[
        "\u5317\u738b\u5be8\u6751"
    ],
    "wof:name":"Beiwangzhaicun",
    "wof:placetype":"locality"
},
  "geometry": {"coordinates":[117.17968999999999,33.5639],"type":"Point"}
}