{
  "type": "Feature",
  "properties": {
    "gn:admin1_code":"16.0",
    "gn:asciiname":"Longhong",
    "gn:country_code":"CN",
    "gn:dem":857,
    "gn:feature_class":"P",
    "gn:feature_code":"PPL",
    "gn:name":"Longhong",
    "gn:population":0,
    "gn:timezone":"Asia/Shanghai",
    "iso:country":"CN",
    "name:zho_x_preferred":[
        "\u9647\u7ea2"
    ],
    "wof:name":"Longhong",
    "wof:placetype":"locality"
},
  "geometry": {"coordinates":[107.774,24.2698],"type":"Point"}
}