{
  "type": "Feature",
  "properties": {
    "gn:admin1_code":"14.0",
    "gn:asciiname":"Zaring",
    "gn:country_code":"CN",
    "gn:dem":4633,
    "gn:feature_class":"P",
    "gn:feature_code":"PPLA4",
    "gn:name":"Zaring",
    "gn:population":0,
    "gn:timezone":"Asia/Urumqi",
    "iso:country":"CN",
    "name:bod_x_preferred":[
        "Zaring"
    ],
    "name:und_x_variant":[
        "Liangdaohe",
        "Zaring",
        "Zaren Xiang"
    ],
    "name:zho_x_preferred":[
        "Zaren"
    ],
    "name:zho_x_variant":[
        "\u624e\u4ec1",
        "Chaqin Gongshe",
        "\u67e5\u52e4\u516c\u793e",
        "\u624e\u4ec1\u4e61"
    ],
    "wof:name":"Zaring",
    "wof:placetype":"locality"
},
  "geometry": {"coordinates":[91.70784999999999,31.98568],"type":"Point"}
}