{
  "type": "Feature",
  "properties": {
    "gn:admin1_code":"26.0",
    "gn:asciiname":"Yangguo",
    "gn:country_code":"CN",
    "gn:dem":638,
    "gn:feature_class":"P",
    "gn:feature_code":"PPLA4",
    "gn:name":"Yangguo",
    "gn:population":0,
    "gn:timezone":"Asia/Shanghai",
    "iso:country":"CN",
    "name:und_x_variant":[
        "Yang-kuo-chen",
        "Yang-kuo",
        "Yangguo",
        "Yangguo Zhen"
    ],
    "name:zho_x_preferred":[
        "\u9633\u90ed"
    ],
    "wof:name":"Yangguo",
    "wof:placetype":"locality"
},
  "geometry": {"coordinates":[109.51963000000001,34.35588],"type":"Point"}
}