{
  "type": "Feature",
  "properties": {
    "gn:admin1_code":"30.0",
    "gn:asciiname":"Yangkengwei",
    "gn:country_code":"CN",
    "gn:dem":98,
    "gn:feature_class":"P",
    "gn:feature_code":"PPL",
    "gn:name":"Yangkengwei",
    "gn:population":0,
    "gn:timezone":"Asia/Shanghai",
    "iso:country":"CN",
    "name:zho_x_preferred":[
        "Yangkengwei"
    ],
    "name:zho_x_variant":[
        "\u6768\u5751\u5c3e"
    ],
    "wof:name":"Yangkengwei",
    "wof:placetype":"locality"
},
  "geometry": {"coordinates":[113.15917,23.81611],"type":"Point"}
}