{
  "type": "Feature",
  "properties": {
    "gn:admin1_code":"18.0",
    "gn:asciiname":"Mianhuachong",
    "gn:country_code":"CN",
    "gn:dem":778,
    "gn:feature_class":"P",
    "gn:feature_code":"PPL",
    "gn:name":"Mianhuachong",
    "gn:population":0,
    "gn:timezone":"Asia/Shanghai",
    "iso:country":"CN",
    "name:zho_x_preferred":[
        "\u68c9\u82b1\u51b2"
    ],
    "wof:name":"Mianhuachong",
    "wof:placetype":"locality"
},
  "geometry": {"coordinates":[107.631,26.2419],"type":"Point"}
}