{
  "type": "Feature",
  "properties": {
    "gn:admin1_code":"16",
    "gn:asciiname":"Shangchanggang",
    "gn:country_code":"CN",
    "gn:dem":385,
    "gn:feature_class":"P",
    "gn:feature_code":"PPL",
    "gn:name":"Shangchanggang",
    "gn:population":0,
    "gn:timezone":"Asia/Shanghai",
    "iso:country":"CN",
    "name:zho_x_preferred":[
        "\u4e0a\u957f\u5c97"
    ],
    "wof:name":"Shangchanggang",
    "wof:placetype":"locality"
},
  "geometry": {"coordinates":[110.491,25.3957],"type":"Point"}
}