{
  "type": "Feature",
  "properties": {
    "gn:admin1_code":"9.0",
    "gn:asciiname":"Lijia Xilou",
    "gn:country_code":"CN",
    "gn:dem":143,
    "gn:feature_class":"P",
    "gn:feature_code":"PPL",
    "gn:name":"Lijia Xilou",
    "gn:population":0,
    "gn:timezone":"Asia/Shanghai",
    "iso:country":"CN",
    "name:zho_x_preferred":[
        "\u9ece\u5bb6\u897f\u697c"
    ],
    "wof:name":"Lijia Xilou",
    "wof:placetype":"locality"
},
  "geometry": {"coordinates":[114.32016000000002,31.94125],"type":"Point"}
}