{
  "type": "Feature",
  "properties": {
    "gn:admin1_code":"21.0",
    "gn:asciiname":"Tongjin",
    "gn:country_code":"CN",
    "gn:dem":1096,
    "gn:feature_class":"P",
    "gn:feature_code":"PPL",
    "gn:name":"Tongjin",
    "gn:population":0,
    "gn:timezone":"Asia/Shanghai",
    "iso:country":"CN",
    "name:zho_x_preferred":[
        "\u540c\u8fdb"
    ],
    "wof:name":"Tongjin",
    "wof:placetype":"locality"
},
  "geometry": {"coordinates":[106.55800000000001,39.0094],"type":"Point"}
}