{
  "type": "Feature",
  "properties": {
    "gn:admin1_code":"32.0",
    "gn:asciiname":"Laisu",
    "gn:country_code":"CN",
    "gn:dem":551,
    "gn:feature_class":"P",
    "gn:feature_code":"PPL",
    "gn:name":"Laisu",
    "gn:population":0,
    "gn:timezone":"Asia/Shanghai",
    "iso:country":"CN",
    "name:zho_x_preferred":[
        "\u6765\u82cf"
    ],
    "wof:name":"Laisu",
    "wof:placetype":"locality"
},
  "geometry": {"coordinates":[106.27901,31.51803],"type":"Point"}
}