{
  "type": "Feature",
  "properties": {
    "gn:admin1_code":"26.0",
    "gn:asciiname":"Laozhuang Licun",
    "gn:country_code":"CN",
    "gn:dem":1115,
    "gn:feature_class":"P",
    "gn:feature_code":"PPL",
    "gn:name":"Laozhuang Licun",
    "gn:population":0,
    "gn:timezone":"Asia/Shanghai",
    "iso:country":"CN",
    "name:zho_x_preferred":[
        "\u8001\u5e84\u91cc\u6751"
    ],
    "wof:name":"Laozhuang Licun",
    "wof:placetype":"locality"
},
  "geometry": {"coordinates":[110.19199999999999,37.2921],"type":"Point"}
}