{
  "type": "Feature",
  "properties": {
    "gn:admin1_code":"10.0",
    "gn:asciiname":"Guanyintang",
    "gn:country_code":"CN",
    "gn:dem":617,
    "gn:feature_class":"P",
    "gn:feature_code":"PPL",
    "gn:name":"Guanyintang",
    "gn:population":0,
    "gn:timezone":"Asia/Shanghai",
    "iso:country":"CN",
    "name:und_x_variant":[
        "\u89c2\u97f3\u5802"
    ],
    "wof:name":"Guanyintang",
    "wof:placetype":"locality"
},
  "geometry": {"coordinates":[114.03582,38.50422],"type":"Point"}
}