{
  "type": "Feature",
  "properties": {
    "gn:admin1_code":"29.0",
    "gn:asciiname":"Yangzhuchang",
    "gn:country_code":"CN",
    "gn:dem":2840,
    "gn:feature_class":"P",
    "gn:feature_code":"PPLF",
    "gn:name":"Yangzhuchang",
    "gn:population":0,
    "gn:timezone":"Asia/Shanghai",
    "iso:country":"CN",
    "name:zho_x_preferred":[
        "\u517b\u732a\u573a"
    ],
    "wof:name":"Yangzhuchang",
    "wof:placetype":"locality"
},
  "geometry": {"coordinates":[102.55500000000001,26.1726],"type":"Point"}
}