{
  "type": "Feature",
  "properties": {
    "gn:admin1_code":"26",
    "gn:asciiname":"Liping",
    "gn:country_code":"CN",
    "gn:dem":1585,
    "gn:feature_class":"P",
    "gn:feature_code":"PPL",
    "gn:name":"Liping",
    "gn:population":0,
    "gn:timezone":"Asia/Shanghai",
    "iso:country":"CN",
    "name:und_x_variant":[
        "Chapin",
        "Laoliping",
        "Cha-p\u2019ing",
        "Liping",
        "\u9ece\u576a",
        "Lipingxiang",
        "\u9ece\u576a\u4e61"
    ],
    "wof:name":"Liping",
    "wof:placetype":"locality"
},
  "geometry": {"coordinates":[106.61149,32.74281],"type":"Point"}
}