{
  "type": "Feature",
  "properties": {
    "gn:admin1_code":"30",
    "gn:asciiname":"Huangcaolang",
    "gn:country_code":"CN",
    "gn:dem":30,
    "gn:feature_class":"P",
    "gn:feature_code":"PPL",
    "gn:name":"Huangcaolang",
    "gn:population":0,
    "gn:timezone":"Asia/Shanghai",
    "iso:country":"CN",
    "name:und_x_variant":[
        "Huangcaolang"
    ],
    "name:zho_x_preferred":[
        "\u9ec4\u8349\u6717"
    ],
    "wof:name":"Huangcaolang",
    "wof:placetype":"locality"
},
  "geometry": {"coordinates":[113.91034999999999,22.91801],"type":"Point"}
}