{
  "type": "Feature",
  "properties": {
    "gn:admin1_code":"1.0",
    "gn:asciiname":"Haozhuangcun",
    "gn:country_code":"CN",
    "gn:dem":38,
    "gn:feature_class":"P",
    "gn:feature_code":"PPL",
    "gn:name":"Haozhuangcun",
    "gn:population":0,
    "gn:timezone":"Asia/Shanghai",
    "iso:country":"CN",
    "name:zho_x_preferred":[
        "\u90dd\u5e84\u6751"
    ],
    "wof:name":"Haozhuangcun",
    "wof:placetype":"locality"
},
  "geometry": {"coordinates":[115.39136000000001,33.10652],"type":"Point"}
}