{
  "type": "Feature",
  "properties": {
    "gn:admin1_code":"22.0",
    "gn:asciiname":"Dianzicun",
    "gn:country_code":"CN",
    "gn:dem":31,
    "gn:feature_class":"P",
    "gn:feature_code":"PPL",
    "gn:name":"Dianzicun",
    "gn:population":0,
    "gn:timezone":"Asia/Shanghai",
    "iso:country":"CN",
    "name:zho_x_preferred":[
        "\u4f43\u5b50\u6751"
    ],
    "wof:name":"Dianzicun",
    "wof:placetype":"locality"
},
  "geometry": {"coordinates":[116.47459000000001,39.56474],"type":"Point"}
}