{
  "type": "Feature",
  "properties": {
    "gn:admin1_code":"32.0",
    "gn:asciiname":"Jiangda",
    "gn:country_code":"CN",
    "gn:dem":3417,
    "gn:feature_class":"P",
    "gn:feature_code":"PPL",
    "gn:name":"Jiangda",
    "gn:population":0,
    "gn:timezone":"Asia/Shanghai",
    "iso:country":"CN",
    "name:zho_x_preferred":[
        "\u5c06\u8fbe"
    ],
    "name:zho_x_variant":[
        "\u964d\u8fbe"
    ],
    "wof:name":"Jiangda",
    "wof:placetype":"locality"
},
  "geometry": {"coordinates":[100.574,31.6572],"type":"Point"}
}