{
  "type": "Feature",
  "properties": {
    "gn:admin1_code":"14.0",
    "gn:asciiname":"Yongguogang",
    "gn:country_code":"CN",
    "gn:dem":4022,
    "gn:feature_class":"P",
    "gn:feature_code":"PPL",
    "gn:name":"Yongguogang",
    "gn:population":0,
    "gn:timezone":"Asia/Urumqi",
    "iso:country":"CN",
    "name:zho_x_preferred":[
        "\u62e5\u679c\u5c97"
    ],
    "wof:name":"Yongguogang",
    "wof:placetype":"locality"
},
  "geometry": {"coordinates":[92.32641,28.23983],"type":"Point"}
}