{
  "type": "Feature",
  "properties": {
    "gn:admin1_code":"4.0",
    "gn:asciiname":"Songjiadian",
    "gn:country_code":"CN",
    "gn:dem":5,
    "gn:feature_class":"P",
    "gn:feature_code":"PPL",
    "gn:name":"Songjiadian",
    "gn:population":0,
    "gn:timezone":"Asia/Shanghai",
    "iso:country":"CN",
    "name:zho_x_preferred":[
        "Songjiadian"
    ],
    "name:zho_x_variant":[
        "\u5b8b\u5bb6\u5e97"
    ],
    "wof:name":"Songjiadian",
    "wof:placetype":"locality"
},
  "geometry": {"coordinates":[121.33497,32.36139],"type":"Point"}
}