{
  "type": "Feature",
  "properties": {
    "gn:admin1_code":"18",
    "gn:asciiname":"Jiupuzi",
    "gn:country_code":"CN",
    "gn:dem":1253,
    "gn:feature_class":"P",
    "gn:feature_code":"PPL",
    "gn:name":"Jiupuzi",
    "gn:population":0,
    "gn:timezone":"Asia/Shanghai",
    "iso:country":"CN",
    "name:zho_x_preferred":[
        "\u65e7\u94fa\u5b50"
    ],
    "wof:name":"Jiupuzi",
    "wof:placetype":"locality"
},
  "geometry": {"coordinates":[106.374,26.5291],"type":"Point"}
}