{
  "type": "Feature",
  "properties": {
    "gn:admin1_code":"11.0",
    "gn:asciiname":"Xigutian",
    "gn:country_code":"CN",
    "gn:dem":472,
    "gn:feature_class":"P",
    "gn:feature_code":"PPL",
    "gn:name":"Xigutian",
    "gn:population":0,
    "gn:timezone":"Asia/Shanghai",
    "iso:country":"CN",
    "name:zho_x_preferred":[
        "Xigutian"
    ],
    "name:zho_x_variant":[
        "\u897f\u8c37\u7530"
    ],
    "wof:name":"Xigutian",
    "wof:placetype":"locality"
},
  "geometry": {"coordinates":[110.72857999999999,28.99199],"type":"Point"}
}