{
  "type": "Feature",
  "properties": {
    "gn:admin1_code":"30.0",
    "gn:asciiname":"Jiezhou",
    "gn:country_code":"CN",
    "gn:dem":7,
    "gn:feature_class":"P",
    "gn:feature_code":"PPL",
    "gn:name":"Jiezhou",
    "gn:population":0,
    "gn:timezone":"Asia/Shanghai",
    "iso:country":"CN",
    "name:zho_x_preferred":[
        "\u6770\u5dde"
    ],
    "wof:name":"Jiezhou",
    "wof:placetype":"locality"
},
  "geometry": {"coordinates":[113.03381,22.79972],"type":"Point"}
}