{
  "type": "Feature",
  "properties": {
    "gn:admin1_code":"18",
    "gn:asciiname":"Dabaisha",
    "gn:country_code":"CN",
    "gn:dem":917,
    "gn:feature_class":"P",
    "gn:feature_code":"PPL",
    "gn:name":"Dabaisha",
    "gn:population":0,
    "gn:timezone":"Asia/Shanghai",
    "iso:country":"CN",
    "name:zho_x_preferred":[
        "\u5927\u767d\u6c99"
    ],
    "wof:name":"Dabaisha",
    "wof:placetype":"locality"
},
  "geometry": {"coordinates":[107.974,27.2167],"type":"Point"}
}