{
  "type": "Feature",
  "properties": {
    "gn:admin1_code":"8.0",
    "gn:asciiname":"Hanjialou",
    "gn:country_code":"CN",
    "gn:dem":165,
    "gn:feature_class":"P",
    "gn:feature_code":"PPL",
    "gn:name":"Hanjialou",
    "gn:population":0,
    "gn:timezone":"Asia/Shanghai",
    "iso:country":"CN",
    "name:zho_x_preferred":[
        "\u97e9\u5bb6\u697c"
    ],
    "wof:name":"Hanjialou",
    "wof:placetype":"locality"
},
  "geometry": {"coordinates":[126.88018999999998,46.54568],"type":"Point"}
}