{
  "type": "Feature",
  "properties": {
    "gn:admin1_code":"16",
    "gn:asciiname":"Songchuan",
    "gn:country_code":"CN",
    "gn:dem":219,
    "gn:feature_class":"P",
    "gn:feature_code":"PPL",
    "gn:name":"Songchuan",
    "gn:population":0,
    "gn:timezone":"Asia/Shanghai",
    "iso:country":"CN",
    "name:zho_x_preferred":[
        "\u677e\u5ddd"
    ],
    "wof:name":"Songchuan",
    "wof:placetype":"locality"
},
  "geometry": {"coordinates":[110.79900000000001,25.8698],"type":"Point"}
}