{
  "type": "Feature",
  "properties": {
    "gn:admin1_code":"33.0",
    "gn:asciiname":"Langjia",
    "gn:country_code":"CN",
    "gn:dem":1000,
    "gn:feature_class":"P",
    "gn:feature_code":"PPL",
    "gn:name":"Langjia",
    "gn:population":0,
    "gn:timezone":"Asia/Shanghai",
    "iso:country":"CN",
    "name:zho_x_preferred":[
        "\u90ce\u5bb6"
    ],
    "wof:name":"Langjia",
    "wof:placetype":"locality"
},
  "geometry": {"coordinates":[108.48313,29.40071],"type":"Point"}
}