{
  "type": "Feature",
  "properties": {
    "gn:admin1_code":"2.0",
    "gn:asciiname":"Tingziqiao",
    "gn:country_code":"CN",
    "gn:dem":6,
    "gn:feature_class":"P",
    "gn:feature_code":"PPL",
    "gn:name":"Tingziqiao",
    "gn:population":0,
    "gn:timezone":"Asia/Shanghai",
    "iso:country":"CN",
    "name:und_x_variant":[
        "\u4ead\u5b50\u6865"
    ],
    "wof:name":"Tingziqiao",
    "wof:placetype":"locality"
},
  "geometry": {"coordinates":[120.71474000000001,30.77717],"type":"Point"}
}