{
  "type": "Feature",
  "properties": {
    "gn:admin1_code":"5.0",
    "gn:asciiname":"Baqiangzi",
    "gn:country_code":"CN",
    "gn:dem":188,
    "gn:feature_class":"P",
    "gn:feature_code":"PPL",
    "gn:name":"Baqiangzi",
    "gn:population":0,
    "gn:timezone":"Asia/Shanghai",
    "iso:country":"CN",
    "name:zho_x_preferred":[
        "\u575d\u5899\u5b50"
    ],
    "wof:name":"Baqiangzi",
    "wof:placetype":"locality"
},
  "geometry": {"coordinates":[126.02771,45.06771],"type":"Point"}
}