{
  "type": "Feature",
  "properties": {
    "gn:admin1_code":"5.0",
    "gn:asciiname":"Nanwaibozigou",
    "gn:country_code":"CN",
    "gn:dem":295,
    "gn:feature_class":"P",
    "gn:feature_code":"PPL",
    "gn:name":"Nanwaibozigou",
    "gn:population":0,
    "gn:timezone":"Asia/Shanghai",
    "iso:country":"CN",
    "name:zho_x_preferred":[
        "\u5357\u6b6a\u8116\u5b50\u6c9f"
    ],
    "wof:name":"Nanwaibozigou",
    "wof:placetype":"locality"
},
  "geometry": {"coordinates":[126.71063999999998,44.06533],"type":"Point"}
}