{
  "type": "Feature",
  "properties": {
    "gn:admin1_code":"2.0",
    "gn:asciiname":"Chengxi",
    "gn:country_code":"CN",
    "gn:dem":5,
    "gn:feature_class":"P",
    "gn:feature_code":"PPLA4",
    "gn:name":"Chengxi",
    "gn:population":0,
    "gn:timezone":"Asia/Shanghai",
    "iso:country":"CN",
    "name:und_x_variant":[
        "Chengxi Jiedao"
    ],
    "name:zho_x_preferred":[
        "\u57ce\u897f"
    ],
    "name:zho_x_variant":[
        "\u57ce\u897f\u8857\u9053"
    ],
    "wof:name":"Chengxi",
    "wof:placetype":"locality"
},
  "geometry": {"coordinates":[121.35411000000001,28.38425],"type":"Point"}
}