{
  "type": "Feature",
  "properties": {
    "gn:admin1_code":"3.0",
    "gn:asciiname":"Shebucun",
    "gn:country_code":"CN",
    "gn:dem":21,
    "gn:feature_class":"P",
    "gn:feature_code":"PPL",
    "gn:name":"Shebucun",
    "gn:population":0,
    "gn:timezone":"Asia/Shanghai",
    "iso:country":"CN",
    "name:und_x_variant":[
        "\u7572\u57e0\u6751"
    ],
    "wof:name":"Shebucun",
    "wof:placetype":"locality"
},
  "geometry": {"coordinates":[116.95634,28.85916],"type":"Point"}
}