{
  "type": "Feature",
  "properties": {
    "gn:admin1_code":"26.0",
    "gn:asciiname":"Baoshicun",
    "gn:country_code":"CN",
    "gn:dem":863,
    "gn:feature_class":"P",
    "gn:feature_code":"PPL",
    "gn:name":"Baoshicun",
    "gn:population":0,
    "gn:timezone":"Asia/Shanghai",
    "iso:country":"CN",
    "name:zho_x_preferred":[
        "\u5b9d\u77f3\u6751"
    ],
    "wof:name":"Baoshicun",
    "wof:placetype":"locality"
},
  "geometry": {"coordinates":[109.27737999999999,33.1855],"type":"Point"}
}