{
  "type": "Feature",
  "properties": {
    "gn:admin1_code":"8.0",
    "gn:asciiname":"Shuanghe Jiudui",
    "gn:country_code":"CN",
    "gn:dem":102,
    "gn:feature_class":"P",
    "gn:feature_code":"PPLF",
    "gn:name":"Shuanghe Jiudui",
    "gn:population":0,
    "gn:timezone":"Asia/Shanghai",
    "iso:country":"CN",
    "name:zho_x_preferred":[
        "\u53cc\u6cb3\u4e5d\u961f"
    ],
    "wof:name":"Shuanghe Jiudui",
    "wof:placetype":"locality"
},
  "geometry": {"coordinates":[128.65871000000001,45.96393],"type":"Point"}
}