{
  "type": "Feature",
  "properties": {
    "gn:admin1_code":"11",
    "gn:asciiname":"Tangtianxu",
    "gn:cc2":"CN",
    "gn:country_code":"CN",
    "gn:dem":194,
    "gn:feature_class":"P",
    "gn:feature_code":"PPL",
    "gn:name":"Tangtianxu",
    "gn:population":0,
    "gn:timezone":"Asia/Shanghai",
    "iso:country":"CN",
    "name:und_x_variant":[
        "T\u2019ang-t\u2019ien",
        "Tangtian",
        "Tangtianxu"
    ],
    "wof:name":"Tangtianxu",
    "wof:placetype":"locality"
},
  "geometry": {"coordinates":[113.66694,26.40611],"type":"Point"}
}