{
  "type": "Feature",
  "properties": {
    "gn:admin1_code":"19.0",
    "gn:asciiname":"Luofenggou",
    "gn:country_code":"CN",
    "gn:dem":94,
    "gn:feature_class":"P",
    "gn:feature_code":"PPL",
    "gn:name":"Luofenggou",
    "gn:population":0,
    "gn:timezone":"Asia/Shanghai",
    "iso:country":"CN",
    "name:zho_x_preferred":[
        "\u843d\u51e4\u6c9f"
    ],
    "wof:name":"Luofenggou",
    "wof:placetype":"locality"
},
  "geometry": {"coordinates":[121.48699999999999,38.9139],"type":"Point"}
}