{
  "type": "Feature",
  "properties": {
    "gn:admin1_code":"4.0",
    "gn:asciiname":"Huaqicun",
    "gn:country_code":"CN",
    "gn:dem":19,
    "gn:feature_class":"P",
    "gn:feature_code":"PPL",
    "gn:name":"Huaqicun",
    "gn:population":0,
    "gn:timezone":"Asia/Shanghai",
    "iso:country":"CN",
    "name:und_x_variant":[
        "Hua-ch\u2019i-ying",
        "Huaqi",
        "Huaqicun"
    ],
    "name:zho_x_preferred":[
        "\u82b1\u65d7"
    ],
    "name:zho_x_variant":[
        "\u82b1\u65d7\u6751"
    ],
    "wof:name":"Huaqicun",
    "wof:placetype":"locality"
},
  "geometry": {"coordinates":[118.64191,32.16467],"type":"Point"}
}