{
  "type": "Feature",
  "properties": {
    "gn:admin1_code":"8.0",
    "gn:asciiname":"Zhengfacun",
    "gn:country_code":"CN",
    "gn:dem":153,
    "gn:feature_class":"P",
    "gn:feature_code":"PPL",
    "gn:name":"Zhengfacun",
    "gn:population":0,
    "gn:timezone":"Asia/Shanghai",
    "iso:country":"CN",
    "name:zho_x_preferred":[
        "\u653f\u53d1\u6751"
    ],
    "wof:name":"Zhengfacun",
    "wof:placetype":"locality"
},
  "geometry": {"coordinates":[126.43698000000001,45.26477],"type":"Point"}
}