{
  "type": "Feature",
  "properties": {
    "gn:admin1_code":"10.0",
    "gn:asciiname":"Wangguanying",
    "gn:country_code":"CN",
    "gn:dem":60,
    "gn:feature_class":"P",
    "gn:feature_code":"PPL",
    "gn:name":"Wangguanying",
    "gn:population":0,
    "gn:timezone":"Asia/Shanghai",
    "iso:country":"CN",
    "name:zho_x_preferred":[
        "\u738b\u5b98\u8425"
    ],
    "wof:name":"Wangguanying",
    "wof:placetype":"locality"
},
  "geometry": {"coordinates":[118.7428,39.89538],"type":"Point"}
}