{
  "type": "Feature",
  "properties": {
    "gn:admin1_code":"29.0",
    "gn:asciiname":"Qingbudong",
    "gn:country_code":"CN",
    "gn:dem":1699,
    "gn:feature_class":"P",
    "gn:feature_code":"PPL",
    "gn:name":"Qingbudong",
    "gn:population":0,
    "gn:timezone":"Asia/Shanghai",
    "iso:country":"CN",
    "name:zho_x_preferred":[
        "\u7b90\u8865\u8463"
    ],
    "wof:name":"Qingbudong",
    "wof:placetype":"locality"
},
  "geometry": {"coordinates":[104.346,24.774],"type":"Point"}
}