{
  "type": "Feature",
  "properties": {
    "gn:admin1_code":"4.0",
    "gn:asciiname":"Xiaotangcun",
    "gn:country_code":"CN",
    "gn:dem":3,
    "gn:feature_class":"P",
    "gn:feature_code":"PPL",
    "gn:name":"Xiaotangcun",
    "gn:population":0,
    "gn:timezone":"Asia/Shanghai",
    "iso:country":"CN",
    "name:zho_x_preferred":[
        "\u5c0f\u8361\u6751"
    ],
    "wof:name":"Xiaotangcun",
    "wof:placetype":"locality"
},
  "geometry": {"coordinates":[119.1955,34.49573],"type":"Point"}
}