{
  "type": "Feature",
  "properties": {
    "gn:admin1_code":"14.0",
    "gn:asciiname":"Kaburuka",
    "gn:country_code":"CN",
    "gn:dem":4710,
    "gn:feature_class":"P",
    "gn:feature_code":"PPL",
    "gn:name":"Kaburuka",
    "gn:population":0,
    "gn:timezone":"Asia/Urumqi",
    "iso:country":"CN",
    "name:zho_x_preferred":[
        "\u5361\u5e03\u5982\u5361"
    ],
    "wof:name":"Kaburuka",
    "wof:placetype":"locality"
},
  "geometry": {"coordinates":[91.32615,31.44325],"type":"Point"}
}