{
  "type": "Feature",
  "properties": {
    "gn:admin1_code":"1.0",
    "gn:asciiname":"Wuxiao",
    "gn:country_code":"CN",
    "gn:dem":8,
    "gn:feature_class":"P",
    "gn:feature_code":"PPL",
    "gn:name":"Wuxiao",
    "gn:population":0,
    "gn:timezone":"Asia/Shanghai",
    "iso:country":"CN",
    "name:zho_x_preferred":[
        "\u5434\u5c0f"
    ],
    "wof:name":"Wuxiao",
    "wof:placetype":"locality"
},
  "geometry": {"coordinates":[118.47411,31.41858],"type":"Point"}
}