{
  "type": "Feature",
  "properties": {
    "gn:admin1_code":"29.0",
    "gn:asciiname":"Huangmu",
    "gn:country_code":"CN",
    "gn:dem":2541,
    "gn:feature_class":"P",
    "gn:feature_code":"PPL",
    "gn:name":"Huangmu",
    "gn:population":0,
    "gn:timezone":"Asia/Shanghai",
    "iso:country":"CN",
    "name:zho_x_preferred":[
        "\u9ec4\u6728"
    ],
    "wof:name":"Huangmu",
    "wof:placetype":"locality"
},
  "geometry": {"coordinates":[99.54770000000001,26.6272],"type":"Point"}
}