{
  "type": "Feature",
  "properties": {
    "gn:admin1_code":"29.0",
    "gn:asciiname":"Chixi",
    "gn:country_code":"CN",
    "gn:dem":2321,
    "gn:feature_class":"P",
    "gn:feature_code":"PPL",
    "gn:name":"Chixi",
    "gn:population":0,
    "gn:timezone":"Asia/Shanghai",
    "iso:country":"CN",
    "name:zho_x_preferred":[
        "\u6c60\u897f"
    ],
    "wof:name":"Chixi",
    "wof:placetype":"locality"
},
  "geometry": {"coordinates":[103.797,24.3973],"type":"Point"}
}