{
  "type": "Feature",
  "properties": {
    "gn:admin1_code":"30",
    "gn:asciiname":"Dongcheng",
    "gn:country_code":"CN",
    "gn:dem":23,
    "gn:feature_class":"P",
    "gn:feature_code":"PPL",
    "gn:name":"Dongcheng",
    "gn:population":0,
    "gn:timezone":"Asia/Urumqi",
    "iso:country":"CN",
    "name:ceb_x_preferred":[
        "Dongcheng"
    ],
    "name:deu_x_preferred":[
        "Dongcheng"
    ],
    "name:eus_x_preferred":[
        "Dongcheng"
    ],
    "name:nld_x_preferred":[
        "Dongcheng"
    ],
    "name:zho_x_preferred":[
        "\u578c\u57ce"
    ],
    "wof:name":"Dongcheng",
    "wof:placetype":"locality"
},
  "geometry": {"coordinates":[109.78368,21.16731],"type":"Point"}
}