{
  "type": "Feature",
  "properties": {
    "gn:admin1_code":"19.0",
    "gn:asciiname":"Langdongzi",
    "gn:country_code":"CN",
    "gn:dem":74,
    "gn:feature_class":"P",
    "gn:feature_code":"PPL",
    "gn:name":"Langdongzi",
    "gn:population":0,
    "gn:timezone":"Asia/Shanghai",
    "iso:country":"CN",
    "name:zho_x_preferred":[
        "\u72fc\u6d1e\u5b50"
    ],
    "wof:name":"Langdongzi",
    "wof:placetype":"locality"
},
  "geometry": {"coordinates":[122.941,42.306],"type":"Point"}
}