{
  "type": "Feature",
  "properties": {
    "gn:admin1_code":"18.0",
    "gn:asciiname":"Song'e",
    "gn:country_code":"CN",
    "gn:dem":819,
    "gn:feature_class":"P",
    "gn:feature_code":"PPL",
    "gn:name":"Song\u2019e",
    "gn:population":0,
    "gn:timezone":"Asia/Shanghai",
    "iso:country":"CN",
    "name:und_x_variant":[
        "Song\u2019e"
    ],
    "name:zho_x_preferred":[
        "\u9001\u4fc4"
    ],
    "wof:name":"Song'e",
    "wof:placetype":"locality"
},
  "geometry": {"coordinates":[108.04300000000001,26.16],"type":"Point"}
}