{
  "type": "Feature",
  "properties": {
    "gn:admin1_code":"11",
    "gn:asciiname":"Ejingbei",
    "gn:country_code":"CN",
    "gn:dem":1244,
    "gn:feature_class":"P",
    "gn:feature_code":"PPL",
    "gn:name":"Ejingbei",
    "gn:population":0,
    "gn:timezone":"Asia/Shanghai",
    "iso:country":"CN",
    "wof:name":"Ejingbei",
    "wof:placetype":"locality"
},
  "geometry": {"coordinates":[113.94083000000001,26.42833],"type":"Point"}
}