{
  "type": "Feature",
  "properties": {
    "gn:admin1_code":"5.0",
    "gn:asciiname":"Xiaodonggoucun",
    "gn:country_code":"CN",
    "gn:dem":409,
    "gn:feature_class":"P",
    "gn:feature_code":"PPL",
    "gn:name":"Xiaodonggoucun",
    "gn:population":0,
    "gn:timezone":"Asia/Shanghai",
    "iso:country":"CN",
    "name:zho_x_preferred":[
        "\u5c0f\u4e1c\u6c9f\u6751"
    ],
    "wof:name":"Xiaodonggoucun",
    "wof:placetype":"locality"
},
  "geometry": {"coordinates":[128.75458999999998,43.71097],"type":"Point"}
}