{
  "type": "Feature",
  "properties": {
    "gn:admin1_code":"15.0",
    "gn:asciiname":"Xiapuzi",
    "gn:country_code":"CN",
    "gn:dem":2041,
    "gn:feature_class":"P",
    "gn:feature_code":"PPL",
    "gn:name":"Xiapuzi",
    "gn:population":0,
    "gn:timezone":"Asia/Shanghai",
    "iso:country":"CN",
    "name:zho_x_preferred":[
        "\u4e0b\u94fa\u5b50"
    ],
    "wof:name":"Xiapuzi",
    "wof:placetype":"locality"
},
  "geometry": {"coordinates":[104.363,35.6535],"type":"Point"}
}