{
  "type": "Feature",
  "properties": {
    "gn:admin1_code":"3.0",
    "gn:asciiname":"Jinzhucun",
    "gn:country_code":"CN",
    "gn:dem":415,
    "gn:feature_class":"P",
    "gn:feature_code":"PPL",
    "gn:name":"Jinzhucun",
    "gn:population":0,
    "gn:timezone":"Asia/Shanghai",
    "iso:country":"CN",
    "name:und_x_variant":[
        "\u91d1\u7af9\u6751"
    ],
    "wof:name":"Jinzhucun",
    "wof:placetype":"locality"
},
  "geometry": {"coordinates":[115.893,26.8359],"type":"Point"}
}