{
  "type": "Feature",
  "properties": {
    "gn:admin1_code":"19.0",
    "gn:asciiname":"Xiagu",
    "gn:country_code":"CN",
    "gn:dem":220,
    "gn:feature_class":"P",
    "gn:feature_code":"PPL",
    "gn:name":"Xiagu",
    "gn:population":0,
    "gn:timezone":"Asia/Shanghai",
    "iso:country":"CN",
    "name:und_x_variant":[
        "\u4e0b\u53e4"
    ],
    "wof:name":"Xiagu",
    "wof:placetype":"locality"
},
  "geometry": {"coordinates":[124.22414999999999,41.67972],"type":"Point"}
}