{
  "type": "Feature",
  "properties": {
    "gn:admin1_code":"16.0",
    "gn:asciiname":"Waibei",
    "gn:country_code":"CN",
    "gn:dem":251,
    "gn:feature_class":"P",
    "gn:feature_code":"PPL",
    "gn:name":"Waibei",
    "gn:population":0,
    "gn:timezone":"Asia/Shanghai",
    "iso:country":"CN",
    "name:zho_x_preferred":[
        "\u6b6a\u8d1d"
    ],
    "wof:name":"Waibei",
    "wof:placetype":"locality"
},
  "geometry": {"coordinates":[108.98099999999999,23.8371],"type":"Point"}
}