{
  "type": "Feature",
  "properties": {
    "gn:admin1_code":"30",
    "gn:asciiname":"Yangweiliao",
    "gn:country_code":"CN",
    "gn:dem":5,
    "gn:feature_class":"P",
    "gn:feature_code":"PPL",
    "gn:name":"Yangweiliao",
    "gn:population":0,
    "gn:timezone":"Asia/Shanghai",
    "iso:country":"CN",
    "name:zho_x_preferred":[
        "\u6d0b\u5c3e\u5bee"
    ],
    "wof:name":"Yangweiliao",
    "wof:placetype":"locality"
},
  "geometry": {"coordinates":[116.42719,23.3016],"type":"Point"}
}