{
  "type": "Feature",
  "properties": {
    "gn:admin1_code":"07",
    "gn:asciiname":"Fugui",
    "gn:country_code":"CN",
    "gn:dem":131,
    "gn:feature_class":"P",
    "gn:feature_code":"PPL",
    "gn:name":"Fugui",
    "gn:population":0,
    "gn:timezone":"Asia/Shanghai",
    "iso:country":"CN",
    "name:zho_x_preferred":[
        "\u6d6e\u9f9f"
    ],
    "wof:name":"Fugui",
    "wof:placetype":"locality"
},
  "geometry": {"coordinates":[118.22056000000001,25.10083],"type":"Point"}
}