{
  "type": "Feature",
  "properties": {
    "gn:admin1_code":"18.0",
    "gn:asciiname":"Dayan",
    "gn:country_code":"CN",
    "gn:dem":1288,
    "gn:feature_class":"P",
    "gn:feature_code":"PPL",
    "gn:name":"Dayan",
    "gn:population":0,
    "gn:timezone":"Asia/Shanghai",
    "iso:country":"CN",
    "name:deu_x_preferred":[
        "Dayan"
    ],
    "name:fra_x_preferred":[
        "Dayan"
    ],
    "name:heb_x_preferred":[
        "\u05d3\u05d9\u05d9\u05df"
    ],
    "name:ita_x_preferred":[
        "Dayan"
    ],
    "name:jpn_x_preferred":[
        "\u30c0\u30e4\u30f3"
    ],
    "name:nds_x_preferred":[
        "Dayan"
    ],
    "name:rus_x_preferred":[
        "\u0414\u0430\u044f\u043d"
    ],
    "wof:name":"Dayan",
    "wof:placetype":"locality"
},
  "geometry": {"coordinates":[106.04167,25.31667],"type":"Point"}
}