{
  "type": "Feature",
  "properties": {
    "gn:admin1_code":"11.0",
    "gn:asciiname":"Potehu",
    "gn:country_code":"CN",
    "gn:dem":387,
    "gn:feature_class":"P",
    "gn:feature_code":"PPL",
    "gn:name":"Potehu",
    "gn:population":0,
    "gn:timezone":"Asia/Shanghai",
    "iso:country":"CN",
    "name:zho_x_preferred":[
        "\u8feb\u7279\u6e56"
    ],
    "wof:name":"Potehu",
    "wof:placetype":"locality"
},
  "geometry": {"coordinates":[109.6452,28.92735],"type":"Point"}
}