{
  "type": "Feature",
  "properties": {
    "gn:admin1_code":"10",
    "gn:asciiname":"Suyi",
    "gn:country_code":"CN",
    "gn:dem":23,
    "gn:feature_class":"P",
    "gn:feature_code":"PPL",
    "gn:name":"Suyi",
    "gn:population":0,
    "gn:timezone":"Asia/Shanghai",
    "iso:country":"CN",
    "name:ara_x_preferred":[
        "\u0633\u0627\u064a\u064a"
    ],
    "name:fas_x_preferred":[
        "\u0633\u0648\u06cc"
    ],
    "name:zho_x_preferred":[
        "\u82cf\u4e49"
    ],
    "wof:name":"Suyi",
    "wof:placetype":"locality"
},
  "geometry": {"coordinates":[115.825,37.793],"type":"Point"}
}