{
  "type": "Feature",
  "properties": {
    "gn:admin1_code":"14.0",
    "gn:asciiname":"Nianzhuo",
    "gn:country_code":"CN",
    "gn:dem":4346,
    "gn:feature_class":"P",
    "gn:feature_code":"PPL",
    "gn:name":"Nianzhuo",
    "gn:population":0,
    "gn:timezone":"Asia/Urumqi",
    "iso:country":"CN",
    "name:zho_x_preferred":[
        "\u917f\u5353"
    ],
    "wof:name":"Nianzhuo",
    "wof:placetype":"locality"
},
  "geometry": {"coordinates":[86.462,29.1946],"type":"Point"}
}