{
  "type": "Feature",
  "properties": {
    "gn:admin1_code":"7.0",
    "gn:asciiname":"Dongyali",
    "gn:country_code":"CN",
    "gn:dem":458,
    "gn:feature_class":"P",
    "gn:feature_code":"PPL",
    "gn:name":"Dongyali",
    "gn:population":0,
    "gn:timezone":"Asia/Shanghai",
    "iso:country":"CN",
    "name:zho_x_preferred":[
        "\u4e1c\u7259\u91cc"
    ],
    "wof:name":"Dongyali",
    "wof:placetype":"locality"
},
  "geometry": {"coordinates":[116.63211,26.00384],"type":"Point"}
}