{
  "type": "Feature",
  "properties": {
    "gn:admin1_code":"12.0",
    "gn:asciiname":"Aijiaci",
    "gn:country_code":"CN",
    "gn:dem":105,
    "gn:feature_class":"P",
    "gn:feature_code":"PPL",
    "gn:name":"Aijiaci",
    "gn:population":0,
    "gn:timezone":"Asia/Shanghai",
    "iso:country":"CN",
    "name:zho_x_preferred":[
        "Aijiaci"
    ],
    "name:zho_x_variant":[
        "\u827e\u5bb6\u7960"
    ],
    "wof:name":"Aijiaci",
    "wof:placetype":"locality"
},
  "geometry": {"coordinates":[114.73904,29.81847],"type":"Point"}
}