{
  "type": "Feature",
  "properties": {
    "gn:admin1_code":"11.0",
    "gn:asciiname":"Bashangpu",
    "gn:country_code":"CN",
    "gn:dem":38,
    "gn:feature_class":"P",
    "gn:feature_code":"PPL",
    "gn:name":"Bashangpu",
    "gn:population":0,
    "gn:timezone":"Asia/Shanghai",
    "iso:country":"CN",
    "name:zho_x_preferred":[
        "\u575d\u4e0a\u94fa"
    ],
    "wof:name":"Bashangpu",
    "wof:placetype":"locality"
},
  "geometry": {"coordinates":[111.90765,28.79958],"type":"Point"}
}