{
  "type": "Feature",
  "properties": {
    "gn:admin1_code":"30.0",
    "gn:asciiname":"Pinggongcun",
    "gn:country_code":"CN",
    "gn:dem":281,
    "gn:feature_class":"P",
    "gn:feature_code":"PPL",
    "gn:name":"Pinggongcun",
    "gn:population":0,
    "gn:timezone":"Asia/Shanghai",
    "iso:country":"CN",
    "name:zho_x_preferred":[
        "\u576a\u5bae\u6751"
    ],
    "wof:name":"Pinggongcun",
    "wof:placetype":"locality"
},
  "geometry": {"coordinates":[115.90655,24.22809],"type":"Point"}
}