{
  "type": "Feature",
  "properties": {
    "gn:admin1_code":"10.0",
    "gn:asciiname":"Guxinzhuang",
    "gn:country_code":"CN",
    "gn:dem":14,
    "gn:feature_class":"P",
    "gn:feature_code":"PPL",
    "gn:name":"Guxinzhuang",
    "gn:population":0,
    "gn:timezone":"Asia/Shanghai",
    "iso:country":"CN",
    "name:zho_x_preferred":[
        "\u987e\u8f9b\u5e84"
    ],
    "wof:name":"Guxinzhuang",
    "wof:placetype":"locality"
},
  "geometry": {"coordinates":[116.648,38.1442],"type":"Point"}
}