{
  "type": "Feature",
  "properties": {
    "gn:admin1_code":"3.0",
    "gn:asciiname":"Qupai",
    "gn:country_code":"CN",
    "gn:dem":155,
    "gn:feature_class":"P",
    "gn:feature_code":"PPL",
    "gn:name":"Qupai",
    "gn:population":0,
    "gn:timezone":"Asia/Shanghai",
    "iso:country":"CN",
    "name:und_x_variant":[
        "\u66f2\u6392"
    ],
    "name:zho_x_preferred":[
        "\u5143\u4ee3\u66f2\u724c\u540d\u5217\u8868"
    ],
    "wof:name":"Qupai",
    "wof:placetype":"locality"
},
  "geometry": {"coordinates":[114.29375,29.00577],"type":"Point"}
}