{
  "type": "Feature",
  "properties": {
    "gn:admin1_code":"14.0",
    "gn:asciiname":"Shengzika",
    "gn:country_code":"CN",
    "gn:dem":4059,
    "gn:feature_class":"P",
    "gn:feature_code":"PPL",
    "gn:name":"Shengzika",
    "gn:population":0,
    "gn:timezone":"Asia/Urumqi",
    "iso:country":"CN",
    "name:zho_x_preferred":[
        "\u5347\u5b50\u5361"
    ],
    "wof:name":"Shengzika",
    "wof:placetype":"locality"
},
  "geometry": {"coordinates":[95.23502000000001,30.92771],"type":"Point"}
}