{
  "type": "Feature",
  "properties": {
    "gn:admin1_code":"16.0",
    "gn:asciiname":"Changtun",
    "gn:country_code":"CN",
    "gn:dem":406,
    "gn:feature_class":"P",
    "gn:feature_code":"PPL",
    "gn:name":"Changtun",
    "gn:population":0,
    "gn:timezone":"Asia/Shanghai",
    "iso:country":"CN",
    "name:zho_x_preferred":[
        "\u5e38\u5c6f"
    ],
    "wof:name":"Changtun",
    "wof:placetype":"locality"
},
  "geometry": {"coordinates":[107.277,23.1081],"type":"Point"}
}