{
  "type": "Feature",
  "properties": {
    "gn:admin1_code":"29",
    "gn:asciiname":"Azezuo",
    "gn:country_code":"CN",
    "gn:dem":1924,
    "gn:feature_class":"P",
    "gn:feature_code":"PPL",
    "gn:name":"Azezuo",
    "gn:population":0,
    "gn:timezone":"Asia/Shanghai",
    "iso:country":"CN",
    "name:zho_x_preferred":[
        "\u963f\u5219\u5de6"
    ],
    "wof:name":"Azezuo",
    "wof:placetype":"locality"
},
  "geometry": {"coordinates":[101.76000000000001,24.2158],"type":"Point"}
}