{
  "type": "Feature",
  "properties": {
    "gn:admin1_code":"9.0",
    "gn:asciiname":"Fengdian",
    "gn:country_code":"CN",
    "gn:dem":229,
    "gn:feature_class":"P",
    "gn:feature_code":"PPL",
    "gn:name":"Fengdian",
    "gn:population":0,
    "gn:timezone":"Asia/Shanghai",
    "iso:country":"CN",
    "name:zho_x_preferred":[
        "\u5c01\u5e97"
    ],
    "wof:name":"Fengdian",
    "wof:placetype":"locality"
},
  "geometry": {"coordinates":[111.45795,33.32779],"type":"Point"}
}