{
  "type": "Feature",
  "properties": {
    "gn:admin1_code":"9.0",
    "gn:asciiname":"Ershilipu",
    "gn:country_code":"CN",
    "gn:dem":110,
    "gn:feature_class":"P",
    "gn:feature_code":"PPL",
    "gn:name":"Ershilipu",
    "gn:population":0,
    "gn:timezone":"Asia/Shanghai",
    "iso:country":"CN",
    "name:zho_x_preferred":[
        "\u4e8c\u5341\u91cc\u94fa"
    ],
    "wof:name":"Ershilipu",
    "wof:placetype":"locality"
},
  "geometry": {"coordinates":[112.90711,32.64541],"type":"Point"}
}