{
  "type": "Feature",
  "properties": {
    "gn:admin1_code":"32.0",
    "gn:asciiname":"Cuoba",
    "gn:country_code":"CN",
    "gn:dem":4276,
    "gn:feature_class":"P",
    "gn:feature_code":"PPL",
    "gn:name":"Cuoba",
    "gn:population":0,
    "gn:timezone":"Asia/Shanghai",
    "iso:country":"CN",
    "name:zho_x_preferred":[
        "\u9519\u575d"
    ],
    "wof:name":"Cuoba",
    "wof:placetype":"locality"
},
  "geometry": {"coordinates":[99.06740000000001,31.8797],"type":"Point"}
}