{
  "type": "Feature",
  "properties": {
    "gn:admin1_code":"10",
    "gn:asciiname":"Lazi Goumen",
    "gn:country_code":"CN",
    "gn:dem":1014,
    "gn:feature_class":"P",
    "gn:feature_code":"PPL",
    "gn:name":"Lazi Goumen",
    "gn:population":0,
    "gn:timezone":"Asia/Shanghai",
    "iso:country":"CN",
    "name:zho_x_preferred":[
        "\u782c\u5b50\u6c9f\u95e8"
    ],
    "wof:name":"Lazi Goumen",
    "wof:placetype":"locality"
},
  "geometry": {"coordinates":[117.16033,41.66116],"type":"Point"}
}