{
  "type": "Feature",
  "properties": {
    "gn:admin1_code":"4.0",
    "gn:asciiname":"Chengjia",
    "gn:country_code":"CN",
    "gn:dem":6,
    "gn:feature_class":"P",
    "gn:feature_code":"PPL",
    "gn:name":"Chengjia",
    "gn:population":0,
    "gn:timezone":"Asia/Shanghai",
    "iso:country":"CN",
    "name:zho_x_preferred":[
        "\u627f\u5bb6"
    ],
    "wof:name":"Chengjia",
    "wof:placetype":"locality"
},
  "geometry": {"coordinates":[120.09426000000001,31.83132],"type":"Point"}
}