{
  "type": "Feature",
  "properties": {
    "gn:admin1_code":"18",
    "gn:asciiname":"Yongkang",
    "gn:country_code":"CN",
    "gn:dem":746,
    "gn:feature_class":"P",
    "gn:feature_code":"PPL",
    "gn:name":"Yongkang",
    "gn:population":0,
    "gn:timezone":"Asia/Shanghai",
    "iso:country":"CN",
    "wof:name":"Yongkang",
    "wof:placetype":"locality"
},
  "geometry": {"coordinates":[107.94638999999999,25.34833],"type":"Point"}
}