{
  "type": "Feature",
  "properties": {
    "gn:admin1_code":"18",
    "gn:asciiname":"Yongkang",
    "gn:country_code":"CN",
    "gn:dem":746,
    "gn:feature_class":"P",
    "gn:feature_code":"PPL",
    "gn:name":"Yongkang",
    "gn:population":0,
    "gn:timezone":"Asia/Shanghai",
    "iso:country":"CN",
    "name:ceb_x_preferred":[
        "Yongkang"
    ],
    "name:deu_x_preferred":[
        "Yongkang"
    ],
    "name:fra_x_preferred":[
        "Yongkang"
    ],
    "name:kor_x_preferred":[
        "\uc735\uce89\uc2dc"
    ],
    "name:swe_x_preferred":[
        "Yongkang"
    ],
    "name:ukr_x_preferred":[
        "\u042e\u043d\u043a\u0430\u043d"
    ],
    "name:zho_x_preferred":[
        "\u6c38\u5eb7\u5e02"
    ],
    "wof:name":"Yongkang",
    "wof:placetype":"locality"
},
  "geometry": {"coordinates":[107.94638999999999,25.34833],"type":"Point"}
}