{
  "type": "Feature",
  "properties": {
    "gn:admin1_code":"21.0",
    "gn:asciiname":"Caijia Houhe",
    "gn:country_code":"CN",
    "gn:dem":1939,
    "gn:feature_class":"P",
    "gn:feature_code":"PPL",
    "gn:name":"Caijia Houhe",
    "gn:population":0,
    "gn:timezone":"Asia/Shanghai",
    "iso:country":"CN",
    "name:zho_x_preferred":[
        "\u8521\u5bb6\u540e\u6cb3"
    ],
    "wof:name":"Caijia Houhe",
    "wof:placetype":"locality"
},
  "geometry": {"coordinates":[105.378,36.6475],"type":"Point"}
}