{
  "type": "Feature",
  "properties": {
    "gn:admin1_code":"14.0",
    "gn:asciiname":"Dianxuecun",
    "gn:country_code":"CN",
    "gn:dem":3506,
    "gn:feature_class":"P",
    "gn:feature_code":"PPL",
    "gn:name":"Dianxuecun",
    "gn:population":0,
    "gn:timezone":"Asia/Urumqi",
    "iso:country":"CN",
    "name:zho_x_preferred":[
        "\u5178\u5b66\u6751"
    ],
    "wof:name":"Dianxuecun",
    "wof:placetype":"locality"
},
  "geometry": {"coordinates":[97.17871,29.26308],"type":"Point"}
}