{
  "type": "Feature",
  "properties": {
    "gn:admin1_code":"26.0",
    "gn:asciiname":"Wujiancun",
    "gn:country_code":"CN",
    "gn:dem":485,
    "gn:feature_class":"P",
    "gn:feature_code":"PPL",
    "gn:name":"Wujiancun",
    "gn:population":0,
    "gn:timezone":"Asia/Shanghai",
    "iso:country":"CN",
    "name:und_x_variant":[
        "\u4e94\u95f4\u6751"
    ],
    "wof:name":"Wujiancun",
    "wof:placetype":"locality"
},
  "geometry": {"coordinates":[107.39628999999999,33.19428],"type":"Point"}
}