{
  "type": "Feature",
  "properties": {
    "gn:admin1_code":"3.0",
    "gn:asciiname":"Xuanjiashan",
    "gn:country_code":"CN",
    "gn:dem":146,
    "gn:feature_class":"P",
    "gn:feature_code":"PPL",
    "gn:name":"Xuanjiashan",
    "gn:population":0,
    "gn:timezone":"Asia/Shanghai",
    "iso:country":"CN",
    "name:und_x_variant":[
        "\u8f69\u5bb6\u5c71"
    ],
    "wof:name":"Xuanjiashan",
    "wof:placetype":"locality"
},
  "geometry": {"coordinates":[116.86629000000001,29.93773],"type":"Point"}
}