{
  "type": "Feature",
  "properties": {
    "gn:admin1_code":"24.0",
    "gn:asciiname":"Yeli",
    "gn:cc2":"CN",
    "gn:country_code":"CN",
    "gn:dem":1415,
    "gn:feature_class":"P",
    "gn:feature_code":"PPL",
    "gn:name":"Yeli",
    "gn:population":0,
    "gn:timezone":"Asia/Shanghai",
    "iso:country":"CN",
    "name:ceb_x_preferred":[
        "Yeli"
    ],
    "name:swe_x_preferred":[
        "Yeli"
    ],
    "name:und_x_variant":[
        "Yeh-li",
        "Yeli"
    ],
    "wof:name":"Yeli",
    "wof:placetype":"locality"
},
  "geometry": {"coordinates":[114.10250000000001,39.32028],"type":"Point"}
}