{
  "type": "Feature",
  "properties": {
    "gn:admin1_code":"26.0",
    "gn:asciiname":"Mazuicun",
    "gn:country_code":"CN",
    "gn:dem":928,
    "gn:feature_class":"P",
    "gn:feature_code":"PPL",
    "gn:name":"Mazuicun",
    "gn:population":0,
    "gn:timezone":"Asia/Shanghai",
    "iso:country":"CN",
    "name:zho_x_preferred":[
        "\u9a6c\u5480\u6751"
    ],
    "wof:name":"Mazuicun",
    "wof:placetype":"locality"
},
  "geometry": {"coordinates":[108.91236000000001,34.98845],"type":"Point"}
}