{
  "type": "Feature",
  "properties": {
    "gn:admin1_code":"19.0",
    "gn:asciiname":"Lengtang",
    "gn:country_code":"CN",
    "gn:dem":268,
    "gn:feature_class":"P",
    "gn:feature_code":"PPL",
    "gn:name":"Lengtang",
    "gn:population":0,
    "gn:timezone":"Asia/Shanghai",
    "iso:country":"CN",
    "name:und_x_variant":[
        "\u51b7\u6c64"
    ],
    "name:zho_x_preferred":[
        "\u51b7\u6c64"
    ],
    "wof:name":"Lengtang",
    "wof:placetype":"locality"
},
  "geometry": {"coordinates":[121.274,42.1879],"type":"Point"}
}