{
  "type": "Feature",
  "properties": {
    "gn:admin1_code":"4.0",
    "gn:asciiname":"Jigengcun",
    "gn:country_code":"CN",
    "gn:dem":2,
    "gn:feature_class":"P",
    "gn:feature_code":"PPL",
    "gn:name":"Jigengcun",
    "gn:population":0,
    "gn:timezone":"Asia/Shanghai",
    "iso:country":"CN",
    "name:zho_x_preferred":[
        "\u5409\u803f\u6751"
    ],
    "wof:name":"Jigengcun",
    "wof:placetype":"locality"
},
  "geometry": {"coordinates":[119.88988999999999,33.14252],"type":"Point"}
}