{
  "type": "Feature",
  "properties": {
    "gn:admin1_code":"30.0",
    "gn:asciiname":"Changqiao",
    "gn:country_code":"CN",
    "gn:dem":236,
    "gn:feature_class":"P",
    "gn:feature_code":"PPL",
    "gn:name":"Changqiao",
    "gn:population":0,
    "gn:timezone":"Asia/Shanghai",
    "iso:country":"CN",
    "name:zho_x_preferred":[
        "Changqiao"
    ],
    "name:zho_x_variant":[
        "\u957f\u6865"
    ],
    "wof:name":"Changqiao",
    "wof:placetype":"locality"
},
  "geometry": {"coordinates":[114.04334,24.41603],"type":"Point"}
}