{
  "type": "Feature",
  "properties": {
    "gn:admin1_code":"5.0",
    "gn:asciiname":"Taojia Wobu",
    "gn:country_code":"CN",
    "gn:dem":198,
    "gn:feature_class":"P",
    "gn:feature_code":"PPL",
    "gn:name":"Taojia Wobu",
    "gn:population":0,
    "gn:timezone":"Asia/Shanghai",
    "iso:country":"CN",
    "name:zho_x_preferred":[
        "\u9676\u5bb6\u7a9d\u5821"
    ],
    "wof:name":"Taojia Wobu",
    "wof:placetype":"locality"
},
  "geometry": {"coordinates":[124.90415,44.11088],"type":"Point"}
}