{
  "type": "Feature",
  "properties": {
    "gn:admin1_code":"30.0",
    "gn:asciiname":"Chongdong",
    "gn:country_code":"CN",
    "gn:dem":303,
    "gn:feature_class":"P",
    "gn:feature_code":"PPL",
    "gn:name":"Chongdong",
    "gn:population":0,
    "gn:timezone":"Asia/Shanghai",
    "iso:country":"CN",
    "name:zho_x_preferred":[
        "\u5ba0\u6d1e"
    ],
    "wof:name":"Chongdong",
    "wof:placetype":"locality"
},
  "geometry": {"coordinates":[112.17699,22.39505],"type":"Point"}
}