{
  "type": "Feature",
  "properties": {
    "gn:admin1_code":"03",
    "gn:asciiname":"Shandang",
    "gn:country_code":"CN",
    "gn:dem":87,
    "gn:feature_class":"P",
    "gn:feature_code":"PPLA4",
    "gn:name":"Shandang",
    "gn:population":0,
    "gn:timezone":"Asia/Shanghai",
    "iso:country":"CN",
    "name:und_x_variant":[
        "Shan-tang",
        "Shandang",
        "\u5c71\u7800",
        "Shandang Zhen",
        "\u5c71\u7800\u9547"
    ],
    "wof:name":"Shandang",
    "wof:placetype":"locality"
},
  "geometry": {"coordinates":[115.79719,27.63188],"type":"Point"}
}