{
  "type": "Feature",
  "properties": {
    "gn:admin1_code":"29",
    "gn:asciiname":"Shangbenyakou",
    "gn:country_code":"CN",
    "gn:dem":1900,
    "gn:feature_class":"P",
    "gn:feature_code":"PPL",
    "gn:name":"Shangbenyakou",
    "gn:population":0,
    "gn:timezone":"Asia/Shanghai",
    "iso:country":"CN",
    "name:zho_x_preferred":[
        "\u4e0a\u672c\u4e2b\u53e3"
    ],
    "wof:name":"Shangbenyakou",
    "wof:placetype":"locality"
},
  "geometry": {"coordinates":[101.53700000000001,24.9567],"type":"Point"}
}