{
  "type": "Feature",
  "properties": {
    "gn:admin1_code":"3.0",
    "gn:asciiname":"Yanghuang Fengjia",
    "gn:country_code":"CN",
    "gn:dem":33,
    "gn:feature_class":"P",
    "gn:feature_code":"PPL",
    "gn:name":"Yanghuang Fengjia",
    "gn:population":0,
    "gn:timezone":"Asia/Shanghai",
    "iso:country":"CN",
    "name:und_x_variant":[
        "\u6768\u9ec4\u5c01\u5bb6"
    ],
    "wof:name":"Yanghuang Fengjia",
    "wof:placetype":"locality"
},
  "geometry": {"coordinates":[116.44712,28.11293],"type":"Point"}
}