{
  "type": "Feature",
  "properties": {
    "gn:admin1_code":"3.0",
    "gn:asciiname":"Daijia",
    "gn:country_code":"CN",
    "gn:dem":53,
    "gn:feature_class":"P",
    "gn:feature_code":"PPL",
    "gn:name":"Daijia",
    "gn:population":0,
    "gn:timezone":"Asia/Shanghai",
    "iso:country":"CN",
    "name:und_x_variant":[
        "\u6234\u5bb6"
    ],
    "wof:name":"Daijia",
    "wof:placetype":"locality"
},
  "geometry": {"coordinates":[115.01723,28.34048],"type":"Point"}
}