{
  "type": "Feature",
  "properties": {
    "gn:admin1_code":"12.0",
    "gn:asciiname":"Yuekou",
    "gn:cc2":"CN",
    "gn:country_code":"CN",
    "gn:dem":35,
    "gn:feature_class":"P",
    "gn:feature_code":"PPL",
    "gn:name":"Yuekou",
    "gn:population":0,
    "gn:timezone":"Asia/Shanghai",
    "iso:country":"CN",
    "name:eng_x_historical":[
        "Yokiakow"
    ],
    "name:eng_x_preferred":[
        "Yokiakow"
    ],
    "name:und_x_variant":[
        "Yo-k\u2019ou-chen",
        "Y\u00fceh-k\u2019ou-chen",
        "Y\u00fceh-k\u2019ou-shih",
        "Y\u00fceh-k\u2019ou",
        "Yokow",
        "Yuekou",
        "Yuekou Jiedao"
    ],
    "name:zho_x_preferred":[
        "\u5cb3\u53e3"
    ],
    "name:zho_x_variant":[
        "\u5cb3\u53e3\u8857\u9053"
    ],
    "wof:name":"Yuekou",
    "wof:placetype":"locality"
},
  "geometry": {"coordinates":[113.07764,30.51414],"type":"Point"}
}