{
  "type": "Feature",
  "properties": {
    "gn:admin1_code":"26.0",
    "gn:asciiname":"Hougoucun",
    "gn:country_code":"CN",
    "gn:dem":1349,
    "gn:feature_class":"P",
    "gn:feature_code":"PPL",
    "gn:name":"Hougoucun",
    "gn:population":0,
    "gn:timezone":"Asia/Shanghai",
    "iso:country":"CN",
    "name:zho_x_preferred":[
        "\u540e\u6c9f\u6751"
    ],
    "wof:name":"Hougoucun",
    "wof:placetype":"locality"
},
  "geometry": {"coordinates":[109.10346,35.23285],"type":"Point"}
}