{
  "type": "Feature",
  "properties": {
    "gn:admin1_code":"18.0",
    "gn:asciiname":"Sanbei",
    "gn:country_code":"CN",
    "gn:dem":815,
    "gn:feature_class":"P",
    "gn:feature_code":"PPL",
    "gn:name":"Sanbei",
    "gn:population":0,
    "gn:timezone":"Asia/Shanghai",
    "iso:country":"CN",
    "name:zho_x_preferred":[
        "\u4e09\u80cc"
    ],
    "wof:name":"Sanbei",
    "wof:placetype":"locality"
},
  "geometry": {"coordinates":[108.536,27.2029],"type":"Point"}
}