{
  "type": "Feature",
  "properties": {
    "gn:admin1_code":"2.0",
    "gn:asciiname":"Linkeng",
    "gn:country_code":"CN",
    "gn:dem":254,
    "gn:feature_class":"P",
    "gn:feature_code":"PPL",
    "gn:name":"Linkeng",
    "gn:population":0,
    "gn:timezone":"Asia/Shanghai",
    "iso:country":"CN",
    "name:und_x_variant":[
        "\u6797\u5751",
        "Linkeng"
    ],
    "wof:name":"Linkeng",
    "wof:placetype":"locality"
},
  "geometry": {"coordinates":[119.89265,27.97309000000001],"type":"Point"}
}