{
  "type": "Feature",
  "properties": {
    "gn:admin1_code":"20.0",
    "gn:asciiname":"Bayintala",
    "gn:country_code":"CN",
    "gn:dem":582,
    "gn:feature_class":"P",
    "gn:feature_code":"PPL",
    "gn:name":"Bayintala",
    "gn:population":0,
    "gn:timezone":"Asia/Shanghai",
    "iso:country":"CN",
    "name:zho_x_preferred":[
        "\u5df4\u97f3\u5854\u62c9"
    ],
    "wof:name":"Bayintala",
    "wof:placetype":"locality"
},
  "geometry": {"coordinates":[117.80146000000001,48.06174],"type":"Point"}
}