{
  "type": "Feature",
  "properties": {
    "gn:admin1_code":"5.0",
    "gn:asciiname":"Dongjixiangcun",
    "gn:country_code":"CN",
    "gn:dem":542,
    "gn:feature_class":"P",
    "gn:feature_code":"PPL",
    "gn:name":"Dongjixiangcun",
    "gn:population":0,
    "gn:timezone":"Asia/Shanghai",
    "iso:country":"CN",
    "name:zho_x_preferred":[
        "\u4e1c\u5409\u7965\u6751"
    ],
    "wof:name":"Dongjixiangcun",
    "wof:placetype":"locality"
},
  "geometry": {"coordinates":[128.29023999999998,43.26773],"type":"Point"}
}