{
  "type": "Feature",
  "properties": {
    "gn:admin1_code":"08",
    "gn:asciiname":"Yang-chia-t'un",
    "gn:country_code":"CN",
    "gn:dem":137,
    "gn:feature_class":"P",
    "gn:feature_code":"PPL",
    "gn:name":"Yang-chia-t\u2019un",
    "gn:population":0,
    "gn:timezone":"Asia/Shanghai",
    "iso:country":"CN",
    "wof:name":"Yang-chia-t'un",
    "wof:placetype":"locality"
},
  "geometry": {"coordinates":[126.3325,46.67972],"type":"Point"}
}