{
  "type": "Feature",
  "properties": {
    "gn:admin1_code":"32.0",
    "gn:asciiname":"Yongjia Yuanzi",
    "gn:country_code":"CN",
    "gn:dem":299,
    "gn:feature_class":"P",
    "gn:feature_code":"PPL",
    "gn:name":"Yongjia Yuanzi",
    "gn:population":0,
    "gn:timezone":"Asia/Shanghai",
    "iso:country":"CN",
    "name:zho_x_preferred":[
        "\u96cd\u5bb6\u9662\u5b50"
    ],
    "wof:name":"Yongjia Yuanzi",
    "wof:placetype":"locality"
},
  "geometry": {"coordinates":[106.151,30.9096],"type":"Point"}
}