{
  "type": "Feature",
  "properties": {
    "gn:admin1_code":"11.0",
    "gn:asciiname":"Huangjiatan",
    "gn:country_code":"CN",
    "gn:dem":34,
    "gn:feature_class":"P",
    "gn:feature_code":"PPL",
    "gn:name":"Huangjiatan",
    "gn:population":0,
    "gn:timezone":"Asia/Shanghai",
    "iso:country":"CN",
    "name:zho_x_preferred":[
        "\u9ec4\u5bb6\u6f6d"
    ],
    "wof:name":"Huangjiatan",
    "wof:placetype":"locality"
},
  "geometry": {"coordinates":[112.91209000000001,29.68701],"type":"Point"}
}