{
  "type": "Feature",
  "properties": {
    "gn:admin1_code":"7.0",
    "gn:asciiname":"Jiancun",
    "gn:country_code":"CN",
    "gn:dem":265,
    "gn:feature_class":"P",
    "gn:feature_code":"PPL",
    "gn:name":"Jiancun",
    "gn:population":0,
    "gn:timezone":"Asia/Shanghai",
    "iso:country":"CN",
    "name:zho_x_preferred":[
        "\u575a\u6751"
    ],
    "wof:name":"Jiancun",
    "wof:placetype":"locality"
},
  "geometry": {"coordinates":[117.15649999999999,25.77383],"type":"Point"}
}