{
  "type": "Feature",
  "properties": {
    "gn:admin1_code":"12.0",
    "gn:asciiname":"Shangzhoujiahe",
    "gn:country_code":"CN",
    "gn:dem":55,
    "gn:feature_class":"P",
    "gn:feature_code":"PPL",
    "gn:name":"Shangzhoujiahe",
    "gn:population":0,
    "gn:timezone":"Asia/Shanghai",
    "iso:country":"CN",
    "name:zho_x_preferred":[
        "\u4e0a\u5468\u5bb6\u6cb3"
    ],
    "wof:name":"Shangzhoujiahe",
    "wof:placetype":"locality"
},
  "geometry": {"coordinates":[113.35983,31.11679],"type":"Point"}
}