{
  "type": "Feature",
  "properties": {
    "gn:admin1_code":"15.0",
    "gn:asciiname":"Zuozhuang",
    "gn:country_code":"CN",
    "gn:dem":1901,
    "gn:feature_class":"P",
    "gn:feature_code":"PPL",
    "gn:name":"Zuozhuang",
    "gn:population":0,
    "gn:timezone":"Asia/Shanghai",
    "iso:country":"CN",
    "name:zho_x_preferred":[
        "\u5de6\u5e84"
    ],
    "wof:name":"Zuozhuang",
    "wof:placetype":"locality"
},
  "geometry": {"coordinates":[102.18600000000001,38.1405],"type":"Point"}
}