{
  "type": "Feature",
  "properties": {
    "gn:admin1_code":"26.0",
    "gn:asciiname":"Huwonanliang",
    "gn:country_code":"CN",
    "gn:dem":1617,
    "gn:feature_class":"P",
    "gn:feature_code":"PPL",
    "gn:name":"Huwonanliang",
    "gn:population":0,
    "gn:timezone":"Asia/Shanghai",
    "iso:country":"CN",
    "name:zho_x_preferred":[
        "\u864e\u7a9d\u5357\u6881"
    ],
    "wof:name":"Huwonanliang",
    "wof:placetype":"locality"
},
  "geometry": {"coordinates":[108.12022,33.89329],"type":"Point"}
}