{
  "type": "Feature",
  "properties": {
    "gn:admin1_code":"4.0",
    "gn:asciiname":"Zhengsuncun",
    "gn:country_code":"CN",
    "gn:dem":3,
    "gn:feature_class":"P",
    "gn:feature_code":"PPL",
    "gn:name":"Zhengsuncun",
    "gn:population":0,
    "gn:timezone":"Asia/Shanghai",
    "iso:country":"CN",
    "name:zho_x_preferred":[
        "\u5f81\u5b59\u6751"
    ],
    "wof:name":"Zhengsuncun",
    "wof:placetype":"locality"
},
  "geometry": {"coordinates":[120.20287999999999,32.98169],"type":"Point"}
}