{
  "type": "Feature",
  "properties": {
    "gn:admin1_code":"02",
    "gn:asciiname":"Shiqiucun",
    "gn:country_code":"CN",
    "gn:dem":5,
    "gn:feature_class":"P",
    "gn:feature_code":"PPL",
    "gn:name":"Shiqiucun",
    "gn:population":0,
    "gn:timezone":"Asia/Shanghai",
    "iso:country":"CN",
    "name:und_x_variant":[
        "Shih-ch\u2019iu-shih",
        "Shiqiu",
        "\u77f3\u6e6b",
        "Shiqiucun"
    ],
    "name:zho_x_preferred":[
        "\u77f3\u6e6b"
    ],
    "name:zho_x_variant":[
        "\u77f3\u6e6b\u6751"
    ],
    "wof:name":"Shiqiucun",
    "wof:placetype":"locality"
},
  "geometry": {"coordinates":[121.79207,29.88219],"type":"Point"}
}