{
  "type": "Feature",
  "properties": {
    "gn:admin1_code":"32.0",
    "gn:asciiname":"Huashuwan",
    "gn:country_code":"CN",
    "gn:dem":747,
    "gn:feature_class":"P",
    "gn:feature_code":"PPL",
    "gn:name":"Huashuwan",
    "gn:population":0,
    "gn:timezone":"Asia/Shanghai",
    "iso:country":"CN",
    "name:zho_x_preferred":[
        "\u82b1\u6811\u6e7e"
    ],
    "wof:name":"Huashuwan",
    "wof:placetype":"locality"
},
  "geometry": {"coordinates":[104.84901000000001,27.95066],"type":"Point"}
}