{
  "type": "Feature",
  "properties": {
    "gn:admin1_code":"7.0",
    "gn:asciiname":"Dazhongcun",
    "gn:country_code":"CN",
    "gn:dem":241,
    "gn:feature_class":"P",
    "gn:feature_code":"PPL",
    "gn:name":"Dazhongcun",
    "gn:population":0,
    "gn:timezone":"Asia/Shanghai",
    "iso:country":"CN",
    "name:zho_x_preferred":[
        "\u8fbe\u4e2d\u6751"
    ],
    "wof:name":"Dazhongcun",
    "wof:placetype":"locality"
},
  "geometry": {"coordinates":[118.1446,25.31805],"type":"Point"}
}