{
  "type": "Feature",
  "properties": {
    "gn:admin1_code":"12.0",
    "gn:asciiname":"Diping",
    "gn:country_code":"CN",
    "gn:dem":273,
    "gn:feature_class":"P",
    "gn:feature_code":"PPL",
    "gn:name":"Diping",
    "gn:population":0,
    "gn:timezone":"Asia/Shanghai",
    "iso:country":"CN",
    "name:zho_x_preferred":[
        "Diping"
    ],
    "name:zho_x_variant":[
        "\u5730\u576a"
    ],
    "wof:name":"Diping",
    "wof:placetype":"locality"
},
  "geometry": {"coordinates":[114.85930999999999,29.66185],"type":"Point"}
}