{
  "type": "Feature",
  "properties": {
    "gn:admin1_code":"15.0",
    "gn:asciiname":"Yidui",
    "gn:country_code":"CN",
    "gn:dem":1251,
    "gn:feature_class":"P",
    "gn:feature_code":"PPLF",
    "gn:name":"Yidui",
    "gn:population":0,
    "gn:timezone":"Asia/Urumqi",
    "iso:country":"CN",
    "name:zho_x_preferred":[
        "\u4e00\u961f"
    ],
    "wof:name":"Yidui",
    "wof:placetype":"locality"
},
  "geometry": {"coordinates":[96.16330000000001,40.532],"type":"Point"}
}