{
  "type": "Feature",
  "properties": {
    "gn:admin1_code":"12",
    "gn:asciiname":"Daji",
    "gn:country_code":"CN",
    "gn:dem":35,
    "gn:feature_class":"P",
    "gn:feature_code":"PPLA4",
    "gn:name":"Daji",
    "gn:population":0,
    "gn:timezone":"Asia/Shanghai",
    "iso:country":"CN",
    "name:cat_x_preferred":[
        "Daji"
    ],
    "name:deu_x_preferred":[
        "Daji"
    ],
    "name:fra_x_preferred":[
        "Daji"
    ],
    "name:ind_x_preferred":[
        "Daji"
    ],
    "name:por_x_preferred":[
        "Daji"
    ],
    "name:spa_x_preferred":[
        "Daji"
    ],
    "name:tha_x_preferred":[
        "\u0e15\u0e4b\u0e32\u0e08\u0e35\u0e48"
    ],
    "name:und_x_variant":[
        "\u5927\u96c6",
        "Daji Jiedao",
        "\u5927\u96c6\u8857\u9053"
    ],
    "name:vie_x_preferred":[
        "\u0110\u00e1t K\u1ef7"
    ],
    "wof:name":"Daji",
    "wof:placetype":"locality"
},
  "geometry": {"coordinates":[114.04281,30.50887],"type":"Point"}
}