{
  "type": "Feature",
  "properties": {
    "gn:admin1_code":"12",
    "gn:asciiname":"Daji",
    "gn:country_code":"CN",
    "gn:dem":35,
    "gn:feature_class":"P",
    "gn:feature_code":"PPLA4",
    "gn:name":"Daji",
    "gn:population":0,
    "gn:timezone":"Asia/Shanghai",
    "iso:country":"CN",
    "name:und_x_variant":[
        "\u5927\u96c6",
        "Daji Jiedao",
        "\u5927\u96c6\u8857\u9053"
    ],
    "wof:name":"Daji",
    "wof:placetype":"locality"
},
  "geometry": {"coordinates":[114.04281,30.50887],"type":"Point"}
}