{
  "type": "Feature",
  "properties": {
    "gn:admin1_code":"26",
    "gn:asciiname":"Hengshan",
    "gn:cc2":"CN",
    "gn:country_code":"CN",
    "gn:dem":1039,
    "gn:feature_class":"P",
    "gn:feature_code":"PPL",
    "gn:name":"Hengshan",
    "gn:population":0,
    "gn:timezone":"Asia/Shanghai",
    "iso:country":"CN",
    "name:ceb_x_preferred":[
        "Hengshan"
    ],
    "name:deu_x_preferred":[
        "Hengshan"
    ],
    "name:fra_x_preferred":[
        "Hengshan"
    ],
    "name:nor_x_preferred":[
        "Hengshan"
    ],
    "name:pol_x_preferred":[
        "Heng Shan"
    ],
    "name:rus_x_preferred":[
        "\u0425\u044d\u043d\u0448\u0430\u043d\u044c"
    ],
    "name:swe_x_preferred":[
        "Hengshan"
    ],
    "name:und_x_variant":[
        "Haiy\u00fcanhsien",
        "Heng-shan-hsien",
        "Huai-y\u00fcan",
        "Heng-shan-hsien-ch\u2019eng"
    ],
    "wof:name":"Hengshan",
    "wof:placetype":"locality"
},
  "geometry": {"coordinates":[109.28167000000001,37.95833],"type":"Point"}
}