{
  "type": "Feature",
  "properties": {
    "gn:admin1_code":"32.0",
    "gn:asciiname":"Jizilin",
    "gn:country_code":"CN",
    "gn:dem":804,
    "gn:feature_class":"P",
    "gn:feature_code":"PPL",
    "gn:name":"Jizilin",
    "gn:population":0,
    "gn:timezone":"Asia/Shanghai",
    "iso:country":"CN",
    "name:zho_x_preferred":[
        "\u68d8\u5b50\u6797"
    ],
    "wof:name":"Jizilin",
    "wof:placetype":"locality"
},
  "geometry": {"coordinates":[104.3188,30.50969000000001],"type":"Point"}
}