{
  "type": "Feature",
  "properties": {
    "gn:admin1_code":"18.0",
    "gn:asciiname":"Pangxiexi",
    "gn:country_code":"CN",
    "gn:dem":657,
    "gn:feature_class":"P",
    "gn:feature_code":"PPL",
    "gn:name":"Pangxiexi",
    "gn:population":0,
    "gn:timezone":"Asia/Shanghai",
    "iso:country":"CN",
    "name:zho_x_preferred":[
        "\u8783\u87f9\u6eaa"
    ],
    "wof:name":"Pangxiexi",
    "wof:placetype":"locality"
},
  "geometry": {"coordinates":[109.334,27.7504],"type":"Point"}
}