{
  "type": "Feature",
  "properties": {
    "gn:admin1_code":"11.0",
    "gn:asciiname":"Tulongshan",
    "gn:country_code":"CN",
    "gn:dem":679,
    "gn:feature_class":"P",
    "gn:feature_code":"PPL",
    "gn:name":"Tulongshan",
    "gn:population":0,
    "gn:timezone":"Asia/Shanghai",
    "iso:country":"CN",
    "name:zho_x_preferred":[
        "\u51f8\u9f99\u5c71"
    ],
    "wof:name":"Tulongshan",
    "wof:placetype":"locality"
},
  "geometry": {"coordinates":[109.1533,27.08489],"type":"Point"}
}