{
  "type": "Feature",
  "properties": {
    "gn:admin1_code":"20.0",
    "gn:asciiname":"Hongqimiao",
    "gn:country_code":"CN",
    "gn:dem":1679,
    "gn:feature_class":"P",
    "gn:feature_code":"PPL",
    "gn:name":"Hongqimiao",
    "gn:population":0,
    "gn:timezone":"Asia/Shanghai",
    "iso:country":"CN",
    "name:und_x_variant":[
        "\u7ea2\u65d7\u5e99"
    ],
    "wof:name":"Hongqimiao",
    "wof:placetype":"locality"
},
  "geometry": {"coordinates":[112.88544,41.35507],"type":"Point"}
}