{
  "type": "Feature",
  "properties": {
    "gn:admin1_code":"30",
    "gn:asciiname":"Tiantang",
    "gn:country_code":"CN",
    "gn:dem":109,
    "gn:feature_class":"P",
    "gn:feature_code":"PPL",
    "gn:name":"Tiantang",
    "gn:population":0,
    "gn:timezone":"Asia/Urumqi",
    "iso:country":"CN",
    "name:zho_x_preferred":[
        "\u5929\u5802"
    ],
    "wof:name":"Tiantang",
    "wof:placetype":"locality"
},
  "geometry": {"coordinates":[110.9083,22.06647],"type":"Point"}
}