{
  "type": "Feature",
  "properties": {
    "gn:admin1_code":"8.0",
    "gn:asciiname":"Liuzhendong",
    "gn:country_code":"CN",
    "gn:dem":188,
    "gn:feature_class":"P",
    "gn:feature_code":"PPL",
    "gn:name":"Liuzhendong",
    "gn:population":0,
    "gn:timezone":"Asia/Shanghai",
    "iso:country":"CN",
    "name:zho_x_preferred":[
        "\u5218\u632f\u4e1c"
    ],
    "wof:name":"Liuzhendong",
    "wof:placetype":"locality"
},
  "geometry": {"coordinates":[125.88916,46.65744],"type":"Point"}
}