{
  "type": "Feature",
  "properties": {
    "gn:admin1_code":"18",
    "gn:asciiname":"Youshigang",
    "gn:country_code":"CN",
    "gn:dem":970,
    "gn:feature_class":"P",
    "gn:feature_code":"PPL",
    "gn:name":"Youshigang",
    "gn:population":0,
    "gn:timezone":"Asia/Shanghai",
    "iso:country":"CN",
    "name:zho_x_preferred":[
        "\u72b9\u72ee\u5c97"
    ],
    "wof:name":"Youshigang",
    "wof:placetype":"locality"
},
  "geometry": {"coordinates":[106.812,28.5511],"type":"Point"}
}