{
  "type": "Feature",
  "properties": {
    "gn:admin1_code":"14.0",
    "gn:asciiname":"Yueqing",
    "gn:country_code":"CN",
    "gn:dem":4955,
    "gn:feature_class":"P",
    "gn:feature_code":"PPL",
    "gn:name":"Yueqing",
    "gn:population":0,
    "gn:timezone":"Asia/Urumqi",
    "iso:country":"CN",
    "name:zho_x_preferred":[
        "\u8d8a\u9752"
    ],
    "wof:name":"Yueqing",
    "wof:placetype":"locality"
},
  "geometry": {"coordinates":[85.13249999999999,28.8303],"type":"Point"}
}