{
  "type": "Feature",
  "properties": {
    "gn:admin1_code":"14.0",
    "gn:asciiname":"Yueqing",
    "gn:country_code":"CN",
    "gn:dem":4955,
    "gn:feature_class":"P",
    "gn:feature_code":"PPL",
    "gn:name":"Yueqing",
    "gn:population":0,
    "gn:timezone":"Asia/Urumqi",
    "iso:country":"CN",
    "name:deu_x_preferred":[
        "Yueqing"
    ],
    "name:fra_x_preferred":[
        "Yueqing"
    ],
    "name:hak_x_preferred":[
        "Ngo\u030dk-chh\u00een-s\u1e73"
    ],
    "name:ita_x_preferred":[
        "Yueqing"
    ],
    "name:jpn_x_preferred":[
        "\u697d\u6e05\u5e02"
    ],
    "name:kik_x_preferred":[
        "Yueqing"
    ],
    "name:kor_x_preferred":[
        "\uc6e8\uce6d\uc2dc"
    ],
    "name:mlg_x_preferred":[
        "Yueqing"
    ],
    "name:nld_x_preferred":[
        "Yueqing"
    ],
    "name:nor_x_preferred":[
        "Yueqing"
    ],
    "name:swe_x_preferred":[
        "Yueqing"
    ],
    "name:tgl_x_preferred":[
        "Yueqing"
    ],
    "name:tur_x_preferred":[
        "Yueqing"
    ],
    "name:urd_x_preferred":[
        "\u06cc\u0648\u0626\u0686\u0646\u06af"
    ],
    "name:vie_x_preferred":[
        "Nh\u1ea1c Thanh"
    ],
    "name:war_x_preferred":[
        "Yueqing"
    ],
    "name:wuu_x_preferred":[
        "\u4e50\u6e05\u5e02"
    ],
    "name:zho_x_preferred":[
        "\u8d8a\u9752"
    ],
    "name:zho_x_variant":[
        "\u4e50\u6e05\u5e02"
    ],
    "wof:name":"Yueqing",
    "wof:placetype":"locality"
},
  "geometry": {"coordinates":[85.13249999999999,28.8303],"type":"Point"}
}