{
  "type": "Feature",
  "properties": {
    "gn:admin1_code":"24",
    "gn:asciiname":"Longwangchan",
    "gn:cc2":"CN",
    "gn:country_code":"CN",
    "gn:dem":666,
    "gn:feature_class":"P",
    "gn:feature_code":"PPL",
    "gn:name":"Longwangchan",
    "gn:population":0,
    "gn:timezone":"Asia/Shanghai",
    "iso:country":"CN",
    "name:und_x_variant":[
        "Lung-wang-hsien",
        "Lung-wang-yen",
        "Longwangchan"
    ],
    "wof:name":"Longwangchan",
    "wof:placetype":"locality"
},
  "geometry": {"coordinates":[110.45,36.16667],"type":"Point"}
}