{
  "type": "Feature",
  "properties": {
    "gn:admin1_code":"11.0",
    "gn:asciiname":"Cangxi",
    "gn:country_code":"CN",
    "gn:dem":419,
    "gn:feature_class":"P",
    "gn:feature_code":"PPL",
    "gn:name":"Cangxi",
    "gn:population":0,
    "gn:timezone":"Asia/Shanghai",
    "iso:country":"CN",
    "name:zho_x_preferred":[
        "Cangxi"
    ],
    "name:zho_x_variant":[
        "\u6ca7\u6eaa"
    ],
    "wof:name":"Cangxi",
    "wof:placetype":"locality"
},
  "geometry": {"coordinates":[114.06793,28.37142],"type":"Point"}
}