{
  "type": "Feature",
  "properties": {
    "gn:admin1_code":"11.0",
    "gn:asciiname":"Daozigang",
    "gn:country_code":"CN",
    "gn:dem":60,
    "gn:feature_class":"P",
    "gn:feature_code":"PPL",
    "gn:name":"Daozigang",
    "gn:population":0,
    "gn:timezone":"Asia/Shanghai",
    "iso:country":"CN",
    "name:zho_x_preferred":[
        "\u7a3b\u5b50\u5c97"
    ],
    "wof:name":"Daozigang",
    "wof:placetype":"locality"
},
  "geometry": {"coordinates":[111.37575,28.75876],"type":"Point"}
}