{
  "type": "Feature",
  "properties": {
    "gn:admin1_code":"25.0",
    "gn:asciiname":"Yanjia",
    "gn:country_code":"CN",
    "gn:dem":100,
    "gn:feature_class":"P",
    "gn:feature_code":"PPL",
    "gn:name":"Yanjia",
    "gn:population":0,
    "gn:timezone":"Asia/Shanghai",
    "iso:country":"CN",
    "name:zho_x_preferred":[
        "\u960e\u5bb6"
    ],
    "wof:name":"Yanjia",
    "wof:placetype":"locality"
},
  "geometry": {"coordinates":[120.39315999999999,37.0877],"type":"Point"}
}