{
  "type": "Feature",
  "properties": {
    "gn:admin1_code":"16",
    "gn:asciiname":"Ejing",
    "gn:country_code":"CN",
    "gn:dem":106,
    "gn:feature_class":"P",
    "gn:feature_code":"PPL",
    "gn:name":"Ejing",
    "gn:population":0,
    "gn:timezone":"Asia/Shanghai",
    "iso:country":"CN",
    "name:zho_x_preferred":[
        "\u4fc4\u5883"
    ],
    "wof:name":"Ejing",
    "wof:placetype":"locality"
},
  "geometry": {"coordinates":[109.459,22.5733],"type":"Point"}
}