{
  "type": "Feature",
  "properties": {
    "gn:admin1_code":"19.0",
    "gn:asciiname":"Caodaogou",
    "gn:country_code":"CN",
    "gn:dem":64,
    "gn:feature_class":"P",
    "gn:feature_code":"PPL",
    "gn:name":"Caodaogou",
    "gn:population":0,
    "gn:timezone":"Asia/Shanghai",
    "iso:country":"CN",
    "name:zho_x_preferred":[
        "\u8349\u9053\u6c9f"
    ],
    "wof:name":"Caodaogou",
    "wof:placetype":"locality"
},
  "geometry": {"coordinates":[121.95699999999999,40.0188],"type":"Point"}
}