{
  "type": "Feature",
  "properties": {
    "gn:admin1_code":"4.0",
    "gn:asciiname":"Huangdacun",
    "gn:country_code":"CN",
    "gn:dem":7,
    "gn:feature_class":"P",
    "gn:feature_code":"PPL",
    "gn:name":"Huangdacun",
    "gn:population":0,
    "gn:timezone":"Asia/Shanghai",
    "iso:country":"CN",
    "name:und_x_variant":[
        "\u749c\u5927\u6751"
    ],
    "name:zho_x_preferred":[
        "\u749c\u5927\u6751"
    ],
    "wof:name":"Huangdacun",
    "wof:placetype":"locality"
},
  "geometry": {"coordinates":[120.29866,31.88676],"type":"Point"}
}