{
  "type": "Feature",
  "properties": {
    "gn:admin1_code":"24",
    "gn:asciiname":"Houshiyu",
    "gn:country_code":"CN",
    "gn:dem":1594,
    "gn:feature_class":"P",
    "gn:feature_code":"PPL",
    "gn:name":"Houshiyu",
    "gn:population":0,
    "gn:timezone":"Asia/Shanghai",
    "iso:country":"CN",
    "wof:name":"Houshiyu",
    "wof:placetype":"locality"
},
  "geometry": {"coordinates":[111.39194000000001,37.26972],"type":"Point"}
}