{
  "type": "Feature",
  "properties": {
    "gn:admin1_code":"4.0",
    "gn:asciiname":"Xiawangcun",
    "gn:country_code":"CN",
    "gn:dem":4,
    "gn:feature_class":"P",
    "gn:feature_code":"PPL",
    "gn:name":"Xiawangcun",
    "gn:population":0,
    "gn:timezone":"Asia/Shanghai",
    "iso:country":"CN",
    "name:und_x_variant":[
        "\u590f\u738b\u6751"
    ],
    "name:zho_x_preferred":[
        "\u590f\u738b\u6751"
    ],
    "wof:name":"Xiawangcun",
    "wof:placetype":"locality"
},
  "geometry": {"coordinates":[120.07865,31.93645],"type":"Point"}
}