{
  "type": "Feature",
  "properties": {
    "gn:admin1_code":"5.0",
    "gn:asciiname":"Toupengdianzi",
    "gn:country_code":"CN",
    "gn:dem":566,
    "gn:feature_class":"P",
    "gn:feature_code":"PPL",
    "gn:name":"Toupengdianzi",
    "gn:population":0,
    "gn:timezone":"Asia/Shanghai",
    "iso:country":"CN",
    "name:und_x_variant":[
        "\u5934\u68da\u7538\u5b50"
    ],
    "wof:name":"Toupengdianzi",
    "wof:placetype":"locality"
},
  "geometry": {"coordinates":[125.48783,41.90411],"type":"Point"}
}