{
  "type": "Feature",
  "properties": {
    "gn:admin1_code":"32.0",
    "gn:asciiname":"Yangang",
    "gn:country_code":"CN",
    "gn:dem":656,
    "gn:feature_class":"P",
    "gn:feature_code":"PPL",
    "gn:name":"Yangang",
    "gn:population":0,
    "gn:timezone":"Asia/Shanghai",
    "iso:country":"CN",
    "name:ukr_x_preferred":[
        "\u042f\u043d\u0491\u0430\u043d\u0491"
    ],
    "name:urd_x_preferred":[
        "\u06cc\u0627\u0646\u06af \u06af\u0627\u0646\u06af"
    ],
    "name:zho_x_preferred":[
        "\u70df\u5c97"
    ],
    "wof:name":"Yangang",
    "wof:placetype":"locality"
},
  "geometry": {"coordinates":[103.375,30.0203],"type":"Point"}
}