{
  "type": "Feature",
  "properties": {
    "gn:admin1_code":"8.0",
    "gn:asciiname":"Zhanglama Wopeng",
    "gn:country_code":"CN",
    "gn:dem":139,
    "gn:feature_class":"P",
    "gn:feature_code":"PPL",
    "gn:name":"Zhanglama Wopeng",
    "gn:population":0,
    "gn:timezone":"Asia/Shanghai",
    "iso:country":"CN",
    "name:zho_x_preferred":[
        "\u5f20\u5587\u561b\u7a9d\u68da"
    ],
    "wof:name":"Zhanglama Wopeng",
    "wof:placetype":"locality"
},
  "geometry": {"coordinates":[123.47279,46.48601],"type":"Point"}
}