{
  "type": "Feature",
  "properties": {
    "gn:admin1_code":"24.0",
    "gn:asciiname":"Zhongjie",
    "gn:country_code":"CN",
    "gn:dem":905,
    "gn:feature_class":"P",
    "gn:feature_code":"PPL",
    "gn:name":"Zhongjie",
    "gn:population":0,
    "gn:timezone":"Asia/Shanghai",
    "iso:country":"CN",
    "name:rus_x_preferred":[
        "\u0427\u0436\u0443\u043d\u0446\u0437\u0435"
    ],
    "name:zho_x_preferred":[
        "\u4e2d\u8857"
    ],
    "wof:name":"Zhongjie",
    "wof:placetype":"locality"
},
  "geometry": {"coordinates":[112.66540000000001,35.59621],"type":"Point"}
}