{
  "type": "Feature",
  "properties": {
    "gn:admin1_code":"5.0",
    "gn:asciiname":"Wulantalacunniu Wobu",
    "gn:country_code":"CN",
    "gn:dem":166,
    "gn:feature_class":"P",
    "gn:feature_code":"PPL",
    "gn:name":"Wulantalacunniu Wobu",
    "gn:population":0,
    "gn:timezone":"Asia/Shanghai",
    "iso:country":"CN",
    "name:zho_x_preferred":[
        "\u4e4c\u5170\u5854\u62c9\u6751\u725b\u7a9d\u5821"
    ],
    "wof:name":"Wulantalacunniu Wobu",
    "wof:placetype":"locality"
},
  "geometry": {"coordinates":[122.29883999999998,45.18454000000001],"type":"Point"}
}