{
  "type": "Feature",
  "properties": {
    "gn:admin1_code":"5.0",
    "gn:asciiname":"Chengdongcun",
    "gn:country_code":"CN",
    "gn:dem":188,
    "gn:feature_class":"P",
    "gn:feature_code":"PPL",
    "gn:name":"Chengdongcun",
    "gn:population":0,
    "gn:timezone":"Asia/Shanghai",
    "iso:country":"CN",
    "name:zho_x_preferred":[
        "\u57ce\u4e1c\u6751"
    ],
    "wof:name":"Chengdongcun",
    "wof:placetype":"locality"
},
  "geometry": {"coordinates":[126.03267,44.37205],"type":"Point"}
}