{
  "type": "Feature",
  "properties": {
    "gn:admin1_code":"19.0",
    "gn:asciiname":"Dengjiatai",
    "gn:country_code":"CN",
    "gn:dem":32,
    "gn:feature_class":"P",
    "gn:feature_code":"PPL",
    "gn:name":"Dengjiatai",
    "gn:population":0,
    "gn:timezone":"Asia/Shanghai",
    "iso:country":"CN",
    "name:und_x_variant":[
        "\u9093\u5bb6\u53f0"
    ],
    "wof:name":"Dengjiatai",
    "wof:placetype":"locality"
},
  "geometry": {"coordinates":[122.82093999999999,40.98361],"type":"Point"}
}