{
  "type": "Feature",
  "properties": {
    "gn:admin1_code":"18",
    "gn:asciiname":"Rangshuiwan",
    "gn:country_code":"CN",
    "gn:dem":1185,
    "gn:feature_class":"P",
    "gn:feature_code":"PPL",
    "gn:name":"Rangshuiwan",
    "gn:population":0,
    "gn:timezone":"Asia/Shanghai",
    "iso:country":"CN",
    "name:zho_x_preferred":[
        "\u8ba9\u6c34\u6e7e"
    ],
    "wof:name":"Rangshuiwan",
    "wof:placetype":"locality"
},
  "geometry": {"coordinates":[107.492,28.4423],"type":"Point"}
}