{
  "type": "Feature",
  "properties": {
    "gn:admin1_code":"4.0",
    "gn:asciiname":"Longtang",
    "gn:country_code":"CN",
    "gn:dem":4,
    "gn:feature_class":"P",
    "gn:feature_code":"PPL",
    "gn:name":"Longtang",
    "gn:population":0,
    "gn:timezone":"Asia/Shanghai",
    "iso:country":"CN",
    "name:zho_x_preferred":[
        "Longtang"
    ],
    "name:zho_x_variant":[
        "\u9f99\u5858"
    ],
    "wof:name":"Longtang",
    "wof:placetype":"locality"
},
  "geometry": {"coordinates":[121.26909000000001,32.24133],"type":"Point"}
}