{
  "type": "Feature",
  "properties": {
    "gn:admin1_code":"1.0",
    "gn:asciiname":"Guantangcun",
    "gn:country_code":"CN",
    "gn:dem":58,
    "gn:feature_class":"P",
    "gn:feature_code":"PPL",
    "gn:name":"Guantangcun",
    "gn:population":0,
    "gn:timezone":"Asia/Shanghai",
    "iso:country":"CN",
    "name:zho_x_preferred":[
        "\u5b98\u5858\u6751"
    ],
    "wof:name":"Guantangcun",
    "wof:placetype":"locality"
},
  "geometry": {"coordinates":[116.27958999999998,31.5633],"type":"Point"}
}