{
  "type": "Feature",
  "properties": {
    "gn:admin1_code":"16.0",
    "gn:asciiname":"Qingjiangwei",
    "gn:country_code":"CN",
    "gn:dem":446,
    "gn:feature_class":"P",
    "gn:feature_code":"PPL",
    "gn:name":"Qingjiangwei",
    "gn:population":0,
    "gn:timezone":"Asia/Shanghai",
    "iso:country":"CN",
    "name:zho_x_preferred":[
        "\u9752\u6c5f\u5c3e"
    ],
    "wof:name":"Qingjiangwei",
    "wof:placetype":"locality"
},
  "geometry": {"coordinates":[110.658,24.2076],"type":"Point"}
}