{
  "type": "Feature",
  "properties": {
    "gn:admin1_code":"29.0",
    "gn:asciiname":"Erpingzi",
    "gn:country_code":"CN",
    "gn:dem":2141,
    "gn:feature_class":"P",
    "gn:feature_code":"PPL",
    "gn:name":"Erpingzi",
    "gn:population":0,
    "gn:timezone":"Asia/Shanghai",
    "iso:country":"CN",
    "name:zho_x_preferred":[
        "\u4e8c\u576a\u5b50"
    ],
    "wof:name":"Erpingzi",
    "wof:placetype":"locality"
},
  "geometry": {"coordinates":[103.042,26.08],"type":"Point"}
}