{
  "type": "Feature",
  "properties": {
    "gn:admin1_code":"16.0",
    "gn:asciiname":"Menshui",
    "gn:country_code":"CN",
    "gn:dem":461,
    "gn:feature_class":"P",
    "gn:feature_code":"PPL",
    "gn:name":"Menshui",
    "gn:population":0,
    "gn:timezone":"Asia/Shanghai",
    "iso:country":"CN",
    "name:zho_x_preferred":[
        "\u95f7\u6c34"
    ],
    "wof:name":"Menshui",
    "wof:placetype":"locality"
},
  "geometry": {"coordinates":[109.288,25.4566],"type":"Point"}
}