{
  "type": "Feature",
  "properties": {
    "gn:admin1_code":"20.0",
    "gn:asciiname":"Ailin",
    "gn:country_code":"CN",
    "gn:dem":388,
    "gn:feature_class":"P",
    "gn:feature_code":"PPL",
    "gn:name":"Ailin",
    "gn:population":0,
    "gn:timezone":"Asia/Shanghai",
    "iso:country":"CN",
    "name:zho_x_preferred":[
        "\u7231\u6797"
    ],
    "wof:name":"Ailin",
    "wof:placetype":"locality"
},
  "geometry": {"coordinates":[124.17626,48.85191],"type":"Point"}
}