{
  "type": "Feature",
  "properties": {
    "gn:admin1_code":"24",
    "gn:asciiname":"Shaojiazhuang",
    "gn:cc2":"CN",
    "gn:country_code":"CN",
    "gn:dem":1176,
    "gn:feature_class":"P",
    "gn:feature_code":"PPL",
    "gn:name":"Shaojiazhuang",
    "gn:population":0,
    "gn:timezone":"Asia/Shanghai",
    "iso:country":"CN",
    "name:und_x_variant":[
        "Shao-chia-chuang",
        "Shaojiazhuang"
    ],
    "name:zho_x_preferred":[
        "\u90b5\u5bb6\u5e84"
    ],
    "wof:name":"Shaojiazhuang",
    "wof:placetype":"locality"
},
  "geometry": {"coordinates":[114.26167,39.6625],"type":"Point"}
}