{
  "type": "Feature",
  "properties": {
    "gn:admin1_code":"4",
    "gn:asciiname":"Weizhuang",
    "gn:country_code":"CN",
    "gn:dem":21,
    "gn:feature_class":"P",
    "gn:feature_code":"PPL",
    "gn:name":"Weizhuang",
    "gn:population":0,
    "gn:timezone":"Asia/Shanghai",
    "iso:country":"CN",
    "name:zho_x_preferred":[
        "\u97e6\u5e84"
    ],
    "wof:name":"Weizhuang",
    "wof:placetype":"locality"
},
  "geometry": {"coordinates":[118.97107,32.99111],"type":"Point"}
}