{
  "type": "Feature",
  "properties": {
    "gn:admin1_code":"14.0",
    "gn:asciiname":"Danduo",
    "gn:country_code":"CN",
    "gn:dem":4419,
    "gn:feature_class":"P",
    "gn:feature_code":"PPL",
    "gn:name":"Danduo",
    "gn:population":0,
    "gn:timezone":"Asia/Urumqi",
    "iso:country":"CN",
    "name:zho_x_preferred":[
        "\u65e6\u591a"
    ],
    "wof:name":"Danduo",
    "wof:placetype":"locality"
},
  "geometry": {"coordinates":[93.87860000000001,31.62635],"type":"Point"}
}