{
  "type": "Feature",
  "properties": {
    "gn:admin1_code":"32",
    "gn:asciiname":"Hanpo'ao",
    "gn:country_code":"CN",
    "gn:dem":331,
    "gn:feature_class":"P",
    "gn:feature_code":"PPL",
    "gn:name":"Hanpo\u2019ao",
    "gn:population":0,
    "gn:timezone":"Asia/Shanghai",
    "iso:country":"CN",
    "name:zho_x_preferred":[
        "\u97e9\u5761\u5773"
    ],
    "name:zho_x_variant":[
        "Hanpo\u2019ao"
    ],
    "wof:name":"Hanpo'ao",
    "wof:placetype":"locality"
},
  "geometry": {"coordinates":[106.21611,30.63511],"type":"Point"}
}