{
  "type": "Feature",
  "properties": {
    "gn:admin1_code":"2.0",
    "gn:asciiname":"Qunlian",
    "gn:country_code":"CN",
    "gn:dem":10,
    "gn:feature_class":"P",
    "gn:feature_code":"PPL",
    "gn:name":"Qunlian",
    "gn:population":0,
    "gn:timezone":"Asia/Shanghai",
    "iso:country":"CN",
    "name:und_x_variant":[
        "\u7fa4\u8054"
    ],
    "wof:name":"Qunlian",
    "wof:placetype":"locality"
},
  "geometry": {"coordinates":[121.10957000000001,30.05985],"type":"Point"}
}