{
  "type": "Feature",
  "properties": {
    "gn:admin1_code":"18",
    "gn:asciiname":"Taozitai",
    "gn:country_code":"CN",
    "gn:dem":1199,
    "gn:feature_class":"P",
    "gn:feature_code":"PPL",
    "gn:name":"Taozitai",
    "gn:population":0,
    "gn:timezone":"Asia/Shanghai",
    "iso:country":"CN",
    "name:zho_x_preferred":[
        "\u6843\u5b50\u53f0"
    ],
    "wof:name":"Taozitai",
    "wof:placetype":"locality"
},
  "geometry": {"coordinates":[106.95099999999999,28.2789],"type":"Point"}
}