{
  "type": "Feature",
  "properties": {
    "gn:admin1_code":"15.0",
    "gn:asciiname":"Xiaoma",
    "gn:country_code":"CN",
    "gn:dem":1312,
    "gn:feature_class":"P",
    "gn:feature_code":"PPL",
    "gn:name":"Xiaoma",
    "gn:population":0,
    "gn:timezone":"Asia/Shanghai",
    "iso:country":"CN",
    "name:zho_x_preferred":[
        "\u5c0f\u9a6c"
    ],
    "wof:name":"Xiaoma",
    "wof:placetype":"locality"
},
  "geometry": {"coordinates":[106.89700000000001,35.3854],"type":"Point"}
}