{
  "type": "Feature",
  "properties": {
    "gn:admin1_code":"16.0",
    "gn:asciiname":"Xiaoliuliang",
    "gn:country_code":"CN",
    "gn:dem":219,
    "gn:feature_class":"P",
    "gn:feature_code":"PPL",
    "gn:name":"Xiaoliuliang",
    "gn:population":0,
    "gn:timezone":"Asia/Shanghai",
    "iso:country":"CN",
    "name:zho_x_preferred":[
        "\u5c0f\u516d\u826f"
    ],
    "wof:name":"Xiaoliuliang",
    "wof:placetype":"locality"
},
  "geometry": {"coordinates":[110.554,22.6277],"type":"Point"}
}