{
  "type": "Feature",
  "properties": {
    "gn:admin1_code":"7",
    "gn:asciiname":"Gaozhaiban",
    "gn:country_code":"CN",
    "gn:dem":42,
    "gn:feature_class":"P",
    "gn:feature_code":"PPL",
    "gn:name":"Gaozhaiban",
    "gn:population":0,
    "gn:timezone":"Asia/Shanghai",
    "iso:country":"CN",
    "name:zho_x_preferred":[
        "\u9ad8\u5be8\u5742"
    ],
    "wof:name":"Gaozhaiban",
    "wof:placetype":"locality"
},
  "geometry": {"coordinates":[117.37298,24.59192],"type":"Point"}
}