{
  "type": "Feature",
  "properties": {
    "gn:admin1_code":"24.0",
    "gn:asciiname":"Shangxian",
    "gn:country_code":"CN",
    "gn:dem":938,
    "gn:feature_class":"P",
    "gn:feature_code":"PPL",
    "gn:name":"Shangxian",
    "gn:population":0,
    "gn:timezone":"Asia/Shanghai",
    "iso:country":"CN",
    "name:zho_x_preferred":[
        "\u4e0a\u53bf"
    ],
    "wof:name":"Shangxian",
    "wof:placetype":"locality"
},
  "geometry": {"coordinates":[112.21559000000001,36.29353],"type":"Point"}
}