{
  "type": "Feature",
  "properties": {
    "gn:admin1_code":"15.0",
    "gn:asciiname":"Changchuangzui",
    "gn:country_code":"CN",
    "gn:dem":1365,
    "gn:feature_class":"P",
    "gn:feature_code":"PPL",
    "gn:name":"Changchuangzui",
    "gn:population":0,
    "gn:timezone":"Asia/Shanghai",
    "iso:country":"CN",
    "name:zho_x_preferred":[
        "\u957f\u5e8a\u5480"
    ],
    "wof:name":"Changchuangzui",
    "wof:placetype":"locality"
},
  "geometry": {"coordinates":[108.185,35.7975],"type":"Point"}
}