{
  "type": "Feature",
  "properties": {
    "gn:admin1_code":"4.0",
    "gn:asciiname":"Balidian",
    "gn:country_code":"CN",
    "gn:dem":3,
    "gn:feature_class":"P",
    "gn:feature_code":"PPL",
    "gn:name":"Balidian",
    "gn:population":0,
    "gn:timezone":"Asia/Shanghai",
    "iso:country":"CN",
    "name:und_x_variant":[
        "\u516b\u91cc\u5e97"
    ],
    "wof:name":"Balidian",
    "wof:placetype":"locality"
},
  "geometry": {"coordinates":[120.92787,32.40221],"type":"Point"}
}