{
  "type": "Feature",
  "properties": {
    "gn:admin1_code":"19.0",
    "gn:asciiname":"Daidonggou",
    "gn:country_code":"CN",
    "gn:dem":529,
    "gn:feature_class":"P",
    "gn:feature_code":"PPL",
    "gn:name":"Daidonggou",
    "gn:population":0,
    "gn:timezone":"Asia/Shanghai",
    "iso:country":"CN",
    "name:und_x_variant":[
        "\u4ee3\u4e1c\u6c9f"
    ],
    "wof:name":"Daidonggou",
    "wof:placetype":"locality"
},
  "geometry": {"coordinates":[124.79234,41.95015],"type":"Point"}
}