{
  "type": "Feature",
  "properties": {
    "gn:admin1_code":"3.0",
    "gn:asciiname":"Bajiaoli",
    "gn:country_code":"CN",
    "gn:dem":339,
    "gn:feature_class":"P",
    "gn:feature_code":"PPL",
    "gn:name":"Bajiaoli",
    "gn:population":0,
    "gn:timezone":"Asia/Shanghai",
    "iso:country":"CN",
    "name:und_x_variant":[
        "\u575d\u89d2\u91cc"
    ],
    "wof:name":"Bajiaoli",
    "wof:placetype":"locality"
},
  "geometry": {"coordinates":[114.26582999999999,28.60446],"type":"Point"}
}