{
  "type": "Feature",
  "properties": {
    "gn:admin1_code":"19.0",
    "gn:asciiname":"Chagudao",
    "gn:country_code":"CN",
    "gn:dem":254,
    "gn:feature_class":"P",
    "gn:feature_code":"PPL",
    "gn:name":"Chagudao",
    "gn:population":0,
    "gn:timezone":"Asia/Shanghai",
    "iso:country":"CN",
    "name:zho_x_preferred":[
        "\u5c94\u80a1\u9053"
    ],
    "wof:name":"Chagudao",
    "wof:placetype":"locality"
},
  "geometry": {"coordinates":[124.3207,42.35007],"type":"Point"}
}