{
  "type": "Feature",
  "properties": {
    "gn:admin1_code":"3.0",
    "gn:asciiname":"Hetouwei",
    "gn:country_code":"CN",
    "gn:dem":48,
    "gn:feature_class":"P",
    "gn:feature_code":"PPL",
    "gn:name":"Hetouwei",
    "gn:population":0,
    "gn:timezone":"Asia/Shanghai",
    "iso:country":"CN",
    "name:und_x_variant":[
        "\u6cb3\u5934\u56f4"
    ],
    "wof:name":"Hetouwei",
    "wof:placetype":"locality"
},
  "geometry": {"coordinates":[115.45402,28.6452],"type":"Point"}
}