{
  "type": "Feature",
  "properties": {
    "gn:admin1_code":"2.0",
    "gn:asciiname":"Yangkoushi",
    "gn:cc2":"CN",
    "gn:country_code":"CN",
    "gn:dem":231,
    "gn:feature_class":"P",
    "gn:feature_code":"PPL",
    "gn:name":"Yangkoushi",
    "gn:population":0,
    "gn:timezone":"Asia/Shanghai",
    "iso:country":"CN",
    "name:und_x_variant":[
        "Yang-K\u2019ou-shih",
        "Yangkoushi"
    ],
    "wof:name":"Yangkoushi",
    "wof:placetype":"locality"
},
  "geometry": {"coordinates":[118.90000000000001,28.65],"type":"Point"}
}