{
  "type": "Feature",
  "properties": {
    "gn:admin1_code":"11",
    "gn:asciiname":"Baitian",
    "gn:cc2":"CN",
    "gn:country_code":"CN",
    "gn:dem":117,
    "gn:feature_class":"P",
    "gn:feature_code":"PPL",
    "gn:name":"Baitian",
    "gn:population":0,
    "gn:timezone":"Asia/Shanghai",
    "iso:country":"CN",
    "name:und_x_variant":[
        "Baitianwan",
        "Baitian"
    ],
    "wof:name":"Baitian",
    "wof:placetype":"locality"
},
  "geometry": {"coordinates":[112.39306000000001,27.92639],"type":"Point"}
}