{
  "type": "Feature",
  "properties": {
    "gn:admin1_code":"16.0",
    "gn:asciiname":"Donggua",
    "gn:country_code":"CN",
    "gn:dem":497,
    "gn:feature_class":"P",
    "gn:feature_code":"PPL",
    "gn:name":"Donggua",
    "gn:population":0,
    "gn:timezone":"Asia/Shanghai",
    "iso:country":"CN",
    "name:zho_x_preferred":[
        "\u5cd2\u74dc"
    ],
    "wof:name":"Donggua",
    "wof:placetype":"locality"
},
  "geometry": {"coordinates":[107.846,24.9507],"type":"Point"}
}