{
  "type": "Feature",
  "properties": {
    "gn:admin1_code":"2.0",
    "gn:asciiname":"Fantou",
    "gn:country_code":"CN",
    "gn:dem":155,
    "gn:feature_class":"P",
    "gn:feature_code":"PPL",
    "gn:name":"Fantou",
    "gn:population":0,
    "gn:timezone":"Asia/Shanghai",
    "iso:country":"CN",
    "name:zho_x_preferred":[
        "\u7548\u5934"
    ],
    "wof:name":"Fantou",
    "wof:placetype":"locality"
},
  "geometry": {"coordinates":[118.4906,29.43298],"type":"Point"}
}