{
  "type": "Feature",
  "properties": {
    "gn:admin1_code":"06",
    "gn:asciiname":"Zhongtie",
    "gn:country_code":"CN",
    "gn:dem":3363,
    "gn:feature_class":"P",
    "gn:feature_code":"PPLA4",
    "gn:name":"Zhongtie",
    "gn:population":0,
    "gn:timezone":"Asia/Shanghai",
    "iso:country":"CN",
    "name:bod_x_preferred":[
        "Kyiling"
    ],
    "name:und_x_variant":[
        "Jilang",
        "Zhongtie Xiang",
        "\u4e2d\u94c1\u4e61",
        "Zhongtie"
    ],
    "name:zho_x_preferred":[
        "\u5409\u6d6a"
    ],
    "name:zho_x_variant":[
        "\u4e2d\u94c1"
    ],
    "wof:name":"Zhongtie",
    "wof:placetype":"locality"
},
  "geometry": {"coordinates":[100.13290000000001,35.24481],"type":"Point"}
}