{
  "type": "Feature",
  "properties": {
    "gn:admin1_code":"15.0",
    "gn:asciiname":"Chenghua",
    "gn:country_code":"CN",
    "gn:dem":1696,
    "gn:feature_class":"P",
    "gn:feature_code":"PPL",
    "gn:name":"Chenghua",
    "gn:population":0,
    "gn:timezone":"Asia/Shanghai",
    "iso:country":"CN",
    "name:ceb_x_preferred":[
        "Chenghua"
    ],
    "name:deu_x_preferred":[
        "Chenghua"
    ],
    "name:fra_x_preferred":[
        "Chenghua"
    ],
    "name:nor_x_preferred":[
        "Chenghua"
    ],
    "name:zho_x_preferred":[
        "\u57ce\u534e"
    ],
    "wof:name":"Chenghua",
    "wof:placetype":"locality"
},
  "geometry": {"coordinates":[103.929,37.5209],"type":"Point"}
}