{
  "type": "Feature",
  "properties": {
    "gn:admin1_code":"11",
    "gn:asciiname":"Huanglinggang",
    "gn:country_code":"CN",
    "gn:dem":42,
    "gn:feature_class":"P",
    "gn:feature_code":"PPL",
    "gn:name":"Huanglinggang",
    "gn:population":0,
    "gn:timezone":"Asia/Shanghai",
    "iso:country":"CN",
    "name:zho_x_preferred":[
        "\u9ec4\u5cad\u5c97"
    ],
    "wof:name":"Huanglinggang",
    "wof:placetype":"locality"
},
  "geometry": {"coordinates":[111.88551,28.80958],"type":"Point"}
}