{
  "type": "Feature",
  "properties": {
    "gn:admin1_code":"30",
    "gn:asciiname":"Xincuobei",
    "gn:country_code":"CN",
    "gn:dem":5,
    "gn:feature_class":"P",
    "gn:feature_code":"PPL",
    "gn:name":"Xincuobei",
    "gn:population":0,
    "gn:timezone":"Asia/Shanghai",
    "iso:country":"CN",
    "name:zho_x_preferred":[
        "\u65b0\u539d\u9642"
    ],
    "wof:name":"Xincuobei",
    "wof:placetype":"locality"
},
  "geometry": {"coordinates":[116.15491000000002,23.47073],"type":"Point"}
}