{
  "type": "Feature",
  "properties": {
    "gn:admin1_code":"18.0",
    "gn:asciiname":"Mengzhai",
    "gn:country_code":"CN",
    "gn:dem":671,
    "gn:feature_class":"P",
    "gn:feature_code":"PPL",
    "gn:name":"Mengzhai",
    "gn:population":0,
    "gn:timezone":"Asia/Shanghai",
    "iso:country":"CN",
    "name:zho_x_preferred":[
        "\u8499\u5be8"
    ],
    "wof:name":"Mengzhai",
    "wof:placetype":"locality"
},
  "geometry": {"coordinates":[107.994,25.8508],"type":"Point"}
}