{
  "type": "Feature",
  "properties": {
    "gn:admin1_code":"24.0",
    "gn:asciiname":"Lijiayan",
    "gn:country_code":"CN",
    "gn:dem":1467,
    "gn:feature_class":"P",
    "gn:feature_code":"PPL",
    "gn:name":"Lijiayan",
    "gn:population":0,
    "gn:timezone":"Asia/Shanghai",
    "iso:country":"CN",
    "name:zho_x_preferred":[
        "\u674e\u5bb6\u5ca9"
    ],
    "wof:name":"Lijiayan",
    "wof:placetype":"locality"
},
  "geometry": {"coordinates":[112.06139,38.37451],"type":"Point"}
}