{
  "type": "Feature",
  "properties": {
    "gn:admin1_code":"3.0",
    "gn:asciiname":"Pingnao",
    "gn:country_code":"CN",
    "gn:dem":285,
    "gn:feature_class":"P",
    "gn:feature_code":"PPL",
    "gn:name":"Pingnao",
    "gn:population":0,
    "gn:timezone":"Asia/Shanghai",
    "iso:country":"CN",
    "name:und_x_variant":[
        "\u576a\u8111"
    ],
    "wof:name":"Pingnao",
    "wof:placetype":"locality"
},
  "geometry": {"coordinates":[114.634,24.7204],"type":"Point"}
}