{
  "type": "Feature",
  "properties": {
    "gn:admin1_code":"5.0",
    "gn:asciiname":"Yaocha",
    "gn:country_code":"CN",
    "gn:dem":593,
    "gn:feature_class":"P",
    "gn:feature_code":"PPL",
    "gn:name":"Yaocha",
    "gn:population":0,
    "gn:timezone":"Asia/Shanghai",
    "iso:country":"CN",
    "name:und_x_variant":[
        "\u8170\u5c94"
    ],
    "wof:name":"Yaocha",
    "wof:placetype":"locality"
},
  "geometry": {"coordinates":[128.04536999999999,42.93503],"type":"Point"}
}