{
  "type": "Feature",
  "properties": {
    "gn:admin1_code":"30",
    "gn:asciiname":"Cangxia",
    "gn:country_code":"CN",
    "gn:dem":223,
    "gn:feature_class":"P",
    "gn:feature_code":"PPL",
    "gn:name":"Cangxia",
    "gn:population":0,
    "gn:timezone":"Asia/Shanghai",
    "iso:country":"CN",
    "name:zho_x_preferred":[
        "\u4ed3\u4e0b"
    ],
    "wof:name":"Cangxia",
    "wof:placetype":"locality"
},
  "geometry": {"coordinates":[115.75602000000001,23.70207000000001],"type":"Point"}
}