{
  "type": "Feature",
  "properties": {
    "gn:admin1_code":"32.0",
    "gn:asciiname":"Huangjiawan",
    "gn:country_code":"CN",
    "gn:dem":2573,
    "gn:feature_class":"P",
    "gn:feature_code":"PPL",
    "gn:name":"Huangjiawan",
    "gn:population":0,
    "gn:timezone":"Asia/Shanghai",
    "iso:country":"CN",
    "name:zho_x_preferred":[
        "\u9ec4\u5bb6\u6e7e"
    ],
    "wof:name":"Huangjiawan",
    "wof:placetype":"locality"
},
  "geometry": {"coordinates":[104.62573,32.59569],"type":"Point"}
}