{
  "type": "Feature",
  "properties": {
    "gn:admin1_code":"29.0",
    "gn:asciiname":"Nizhang",
    "gn:country_code":"CN",
    "gn:dem":2239,
    "gn:feature_class":"P",
    "gn:feature_code":"PPL",
    "gn:name":"Nizhang",
    "gn:population":0,
    "gn:timezone":"Asia/Shanghai",
    "iso:country":"CN",
    "name:zho_x_preferred":[
        "\u817b\u638c"
    ],
    "wof:name":"Nizhang",
    "wof:placetype":"locality"
},
  "geometry": {"coordinates":[100.901,25.0762],"type":"Point"}
}