{
  "type": "Feature",
  "properties": {
    "gn:admin1_code":"3.0",
    "gn:asciiname":"Tieluxia",
    "gn:country_code":"CN",
    "gn:dem":44,
    "gn:feature_class":"P",
    "gn:feature_code":"PPL",
    "gn:name":"Tieluxia",
    "gn:population":0,
    "gn:timezone":"Asia/Shanghai",
    "iso:country":"CN",
    "name:und_x_variant":[
        "\u94c1\u7089\u4e0b"
    ],
    "wof:name":"Tieluxia",
    "wof:placetype":"locality"
},
  "geometry": {"coordinates":[115.61544000000001,28.5098],"type":"Point"}
}