{
  "type": "Feature",
  "properties": {
    "gn:admin1_code":"26.0",
    "gn:asciiname":"Xiyaogou",
    "gn:country_code":"CN",
    "gn:dem":1234,
    "gn:feature_class":"P",
    "gn:feature_code":"PPL",
    "gn:name":"Xiyaogou",
    "gn:population":0,
    "gn:timezone":"Asia/Shanghai",
    "iso:country":"CN",
    "name:zho_x_preferred":[
        "\u897f\u5c27\u6c9f"
    ],
    "wof:name":"Xiyaogou",
    "wof:placetype":"locality"
},
  "geometry": {"coordinates":[110.64903,39.23632],"type":"Point"}
}