{
  "type": "Feature",
  "properties": {
    "gn:admin1_code":"30.0",
    "gn:asciiname":"Jiaokengping",
    "gn:country_code":"CN",
    "gn:dem":103,
    "gn:feature_class":"P",
    "gn:feature_code":"PPL",
    "gn:name":"Jiaokengping",
    "gn:population":0,
    "gn:timezone":"Asia/Shanghai",
    "iso:country":"CN",
    "name:und_x_variant":[
        "\u89d2\u5751\u576a"
    ],
    "name:zho_x_preferred":[
        "\u89d2\u5751\u576a"
    ],
    "wof:name":"Jiaokengping",
    "wof:placetype":"locality"
},
  "geometry": {"coordinates":[114.9777,23.49931],"type":"Point"}
}