{
  "type": "Feature",
  "properties": {
    "gn:admin1_code":"8.0",
    "gn:asciiname":"Wangquan Wopeng",
    "gn:country_code":"CN",
    "gn:dem":142,
    "gn:feature_class":"P",
    "gn:feature_code":"PPL",
    "gn:name":"Wangquan Wopeng",
    "gn:population":0,
    "gn:timezone":"Asia/Shanghai",
    "iso:country":"CN",
    "name:zho_x_preferred":[
        "\u738b\u5168\u7a9d\u68da"
    ],
    "wof:name":"Wangquan Wopeng",
    "wof:placetype":"locality"
},
  "geometry": {"coordinates":[124.48994,47.02858],"type":"Point"}
}