{
  "type": "Feature",
  "properties": {
    "gn:admin1_code":"8.0",
    "gn:asciiname":"Xiaosunjia Weizi",
    "gn:country_code":"CN",
    "gn:dem":136,
    "gn:feature_class":"P",
    "gn:feature_code":"PPL",
    "gn:name":"Xiaosunjia Weizi",
    "gn:population":0,
    "gn:timezone":"Asia/Shanghai",
    "iso:country":"CN",
    "name:zho_x_preferred":[
        "\u5c0f\u5b59\u5bb6\u56f4\u5b50"
    ],
    "wof:name":"Xiaosunjia Weizi",
    "wof:placetype":"locality"
},
  "geometry": {"coordinates":[123.62103,46.61253],"type":"Point"}
}