{
  "type": "Feature",
  "properties": {
    "gn:admin1_code":"3.0",
    "gn:asciiname":"Jinpen",
    "gn:country_code":"CN",
    "gn:dem":492,
    "gn:feature_class":"P",
    "gn:feature_code":"PPL",
    "gn:name":"Jinpen",
    "gn:population":0,
    "gn:timezone":"Asia/Shanghai",
    "iso:country":"CN",
    "name:und_x_variant":[
        "\u91d1\u76c6"
    ],
    "name:zho_x_preferred":[
        "\u91d1\u76c6\u9547"
    ],
    "wof:name":"Jinpen",
    "wof:placetype":"locality"
},
  "geometry": {"coordinates":[114.17332,29.16321],"type":"Point"}
}