{
  "type": "Feature",
  "properties": {
    "gn:admin1_code":"13",
    "gn:asciiname":"Yilingsantuan Jiulian",
    "gn:country_code":"CN",
    "gn:dem":433,
    "gn:feature_class":"P",
    "gn:feature_code":"PPL",
    "gn:name":"Yilingsantuan Jiulian",
    "gn:population":0,
    "gn:timezone":"Asia/Urumqi",
    "iso:country":"CN",
    "name:zho_x_preferred":[
        "\u4e00\u96f6\u4e09\u56e2\u4e5d\u8fde"
    ],
    "wof:name":"Yilingsantuan Jiulian",
    "wof:placetype":"locality"
},
  "geometry": {"coordinates":[87.50660000000001,44.46545],"type":"Point"}
}