{
  "type": "Feature",
  "properties": {
    "gn:admin1_code":"19.0",
    "gn:asciiname":"Xiaolongwancun",
    "gn:country_code":"CN",
    "gn:dem":5,
    "gn:feature_class":"P",
    "gn:feature_code":"PPL",
    "gn:name":"Xiaolongwancun",
    "gn:population":0,
    "gn:timezone":"Asia/Shanghai",
    "iso:country":"CN",
    "name:zho_x_preferred":[
        "\u5c0f\u9f99\u6e7e\u6751"
    ],
    "name:zho_x_variant":[
        "\u5c0f\u9f99\u5f2f\u6751"
    ],
    "wof:name":"Xiaolongwancun",
    "wof:placetype":"locality"
},
  "geometry": {"coordinates":[122.53509,41.23558],"type":"Point"}
}