{
  "type": "Feature",
  "properties": {
    "gn:admin1_code":"32.0",
    "gn:asciiname":"Wenchang",
    "gn:country_code":"CN",
    "gn:dem":666,
    "gn:feature_class":"P",
    "gn:feature_code":"PPL",
    "gn:name":"Wenchang",
    "gn:population":0,
    "gn:timezone":"Asia/Shanghai",
    "iso:country":"CN",
    "name:und_x_variant":[
        "\u6587\u660c"
    ],
    "wof:name":"Wenchang",
    "wof:placetype":"locality"
},
  "geometry": {"coordinates":[106.73971,32.10361],"type":"Point"}
}