{
  "type": "Feature",
  "properties": {
    "gn:admin1_code":"18",
    "gn:asciiname":"Maota",
    "gn:country_code":"CN",
    "gn:dem":1136,
    "gn:feature_class":"P",
    "gn:feature_code":"PPL",
    "gn:name":"Maota",
    "gn:population":0,
    "gn:timezone":"Asia/Shanghai",
    "iso:country":"CN",
    "name:zho_x_preferred":[
        "\u6bdb\u5854"
    ],
    "wof:name":"Maota",
    "wof:placetype":"locality"
},
  "geometry": {"coordinates":[105.748,25.9668],"type":"Point"}
}