{
  "type": "Feature",
  "properties": {
    "gn:admin1_code":"29.0",
    "gn:asciiname":"Wadai",
    "gn:country_code":"CN",
    "gn:dem":2339,
    "gn:feature_class":"P",
    "gn:feature_code":"PPL",
    "gn:name":"Wadai",
    "gn:population":0,
    "gn:timezone":"Asia/Shanghai",
    "iso:country":"CN",
    "name:zho_x_preferred":[
        "\u74e6\u4ee3"
    ],
    "wof:name":"Wadai",
    "wof:placetype":"locality"
},
  "geometry": {"coordinates":[100.871,26.1879],"type":"Point"}
}