{
  "type": "Feature",
  "properties": {
    "gn:admin1_code":"02",
    "gn:asciiname":"Tianqiancun",
    "gn:country_code":"CN",
    "gn:dem":11,
    "gn:feature_class":"P",
    "gn:feature_code":"PPL",
    "gn:name":"Tianqiancun",
    "gn:population":0,
    "gn:timezone":"Asia/Shanghai",
    "iso:country":"CN",
    "name:und_x_variant":[
        "Tianqian",
        "Tianqiancun"
    ],
    "name:zho_x_preferred":[
        "\u7530\u5898\u6751"
    ],
    "wof:name":"Tianqiancun",
    "wof:placetype":"locality"
},
  "geometry": {"coordinates":[120.34743,27.48705],"type":"Point"}
}