{
  "type": "Feature",
  "properties": {
    "gn:admin1_code":"30.0",
    "gn:asciiname":"Luchangxia",
    "gn:country_code":"CN",
    "gn:dem":389,
    "gn:feature_class":"P",
    "gn:feature_code":"PPL",
    "gn:name":"Luchangxia",
    "gn:population":0,
    "gn:timezone":"Asia/Shanghai",
    "iso:country":"CN",
    "name:zho_x_preferred":[
        "\u7089\u5382\u4e0b"
    ],
    "wof:name":"Luchangxia",
    "wof:placetype":"locality"
},
  "geometry": {"coordinates":[115.11429,23.20349],"type":"Point"}
}