{
  "type": "Feature",
  "properties": {
    "gn:admin1_code":"10.0",
    "gn:asciiname":"Xichengli",
    "gn:country_code":"CN",
    "gn:dem":10,
    "gn:feature_class":"P",
    "gn:feature_code":"PPL",
    "gn:name":"Xichengli",
    "gn:population":0,
    "gn:timezone":"Asia/Shanghai",
    "iso:country":"CN",
    "name:zho_x_preferred":[
        "\u897f\u57ce\u91cc"
    ],
    "wof:name":"Xichengli",
    "wof:placetype":"locality"
},
  "geometry": {"coordinates":[119.56588000000001,39.95328],"type":"Point"}
}