{
  "type": "Feature",
  "properties": {
    "gn:admin1_code":"31",
    "gn:asciiname":"Xinshi",
    "gn:country_code":"CN",
    "gn:dem":58,
    "gn:feature_class":"P",
    "gn:feature_code":"PPL",
    "gn:name":"Xinshi",
    "gn:population":0,
    "gn:timezone":"Asia/Shanghai",
    "iso:country":"CN",
    "name:und_x_variant":[
        "\u65b0\u5e02"
    ],
    "wof:name":"Xinshi",
    "wof:placetype":"locality"
},
  "geometry": {"coordinates":[110.38451000000001,19.33598],"type":"Point"}
}