{
  "type": "Feature",
  "properties": {
    "gn:admin1_code":"30.0",
    "gn:asciiname":"Xiangshui",
    "gn:country_code":"CN",
    "gn:dem":195,
    "gn:feature_class":"P",
    "gn:feature_code":"PPL",
    "gn:name":"Xiangshui",
    "gn:population":0,
    "gn:timezone":"Asia/Urumqi",
    "iso:country":"CN",
    "name:zho_x_preferred":[
        "\u54cd\u6c34"
    ],
    "wof:name":"Xiangshui",
    "wof:placetype":"locality"
},
  "geometry": {"coordinates":[110.96787,22.63581],"type":"Point"}
}