{
  "type": "Feature",
  "properties": {
    "gn:admin1_code":"16.0",
    "gn:asciiname":"Xinmalai",
    "gn:country_code":"CN",
    "gn:dem":124,
    "gn:feature_class":"P",
    "gn:feature_code":"PPL",
    "gn:name":"Xinmalai",
    "gn:population":0,
    "gn:timezone":"Asia/Shanghai",
    "iso:country":"CN",
    "name:zho_x_preferred":[
        "\u65b0\u9a6c\u8d56"
    ],
    "wof:name":"Xinmalai",
    "wof:placetype":"locality"
},
  "geometry": {"coordinates":[109.41200000000001,23.3247],"type":"Point"}
}