{
  "type": "Feature",
  "properties": {
    "gn:admin1_code":"3.0",
    "gn:asciiname":"Songshanpai",
    "gn:country_code":"CN",
    "gn:dem":192,
    "gn:feature_class":"P",
    "gn:feature_code":"PPL",
    "gn:name":"Songshanpai",
    "gn:population":0,
    "gn:timezone":"Asia/Shanghai",
    "iso:country":"CN",
    "name:und_x_variant":[
        "\u677e\u5c71\u6392"
    ],
    "wof:name":"Songshanpai",
    "wof:placetype":"locality"
},
  "geometry": {"coordinates":[115.7916,26.32381],"type":"Point"}
}