{
  "type": "Feature",
  "properties": {
    "gn:admin1_code":"30",
    "gn:asciiname":"Jijiacun",
    "gn:country_code":"CN",
    "gn:dem":32,
    "gn:feature_class":"P",
    "gn:feature_code":"PPL",
    "gn:name":"Jijiacun",
    "gn:population":0,
    "gn:timezone":"Asia/Urumqi",
    "iso:country":"CN",
    "name:zho_x_preferred":[
        "\u7eaa\u5bb6\u6751"
    ],
    "wof:name":"Jijiacun",
    "wof:placetype":"locality"
},
  "geometry": {"coordinates":[109.79078,20.93841],"type":"Point"}
}