{
  "type": "Feature",
  "properties": {
    "gn:admin1_code":"8.0",
    "gn:asciiname":"Xijie Yidui",
    "gn:country_code":"CN",
    "gn:dem":386,
    "gn:feature_class":"P",
    "gn:feature_code":"PPLF",
    "gn:name":"Xijie Yidui",
    "gn:population":0,
    "gn:timezone":"Asia/Shanghai",
    "iso:country":"CN",
    "name:zho_x_preferred":[
        "\u897f\u8857\u4e00\u961f"
    ],
    "wof:name":"Xijie Yidui",
    "wof:placetype":"locality"
},
  "geometry": {"coordinates":[129.05403000000001,44.56555],"type":"Point"}
}