{
  "type": "Feature",
  "properties": {
    "gn:admin1_code":"30",
    "gn:asciiname":"Fengshutang",
    "gn:country_code":"CN",
    "gn:dem":30,
    "gn:feature_class":"P",
    "gn:feature_code":"PPL",
    "gn:name":"Fengshutang",
    "gn:population":0,
    "gn:timezone":"Asia/Urumqi",
    "iso:country":"CN",
    "name:zho_x_preferred":[
        "\u67ab\u6811\u5858"
    ],
    "wof:name":"Fengshutang",
    "wof:placetype":"locality"
},
  "geometry": {"coordinates":[109.80062,20.97006],"type":"Point"}
}