{
  "type": "Feature",
  "properties": {
    "gn:admin1_code":"14.0",
    "gn:asciiname":"Qiangpaile",
    "gn:country_code":"CN",
    "gn:dem":4612,
    "gn:feature_class":"P",
    "gn:feature_code":"PPL",
    "gn:name":"Qiangpaile",
    "gn:population":0,
    "gn:timezone":"Asia/Urumqi",
    "iso:country":"CN",
    "name:zho_x_preferred":[
        "\u5f3a\u62cd\u52d2"
    ],
    "wof:name":"Qiangpaile",
    "wof:placetype":"locality"
},
  "geometry": {"coordinates":[86.4186,29.0017],"type":"Point"}
}