{
  "type": "Feature",
  "properties": {
    "gn:admin1_code":"3.0",
    "gn:asciiname":"Yanqiao",
    "gn:country_code":"CN",
    "gn:dem":17,
    "gn:feature_class":"P",
    "gn:feature_code":"PPL",
    "gn:name":"Yanqiao",
    "gn:population":0,
    "gn:timezone":"Asia/Shanghai",
    "iso:country":"CN",
    "name:und_x_variant":[
        "\u664f\u6865"
    ],
    "wof:name":"Yanqiao",
    "wof:placetype":"locality"
},
  "geometry": {"coordinates":[116.62165,29.42826],"type":"Point"}
}