{
  "type": "Feature",
  "properties": {
    "gn:admin1_code":"5.0",
    "gn:asciiname":"Zhengbeigou",
    "gn:country_code":"CN",
    "gn:dem":225,
    "gn:feature_class":"P",
    "gn:feature_code":"PPL",
    "gn:name":"Zhengbeigou",
    "gn:population":0,
    "gn:timezone":"Asia/Shanghai",
    "iso:country":"CN",
    "name:zho_x_preferred":[
        "\u6b63\u5317\u6c9f"
    ],
    "wof:name":"Zhengbeigou",
    "wof:placetype":"locality"
},
  "geometry": {"coordinates":[124.41983999999999,42.91754],"type":"Point"}
}