{
  "type": "Feature",
  "properties": {
    "gn:admin1_code":"32.0",
    "gn:asciiname":"Aotianjiao",
    "gn:country_code":"CN",
    "gn:dem":342,
    "gn:feature_class":"P",
    "gn:feature_code":"PPL",
    "gn:name":"Aotianjiao",
    "gn:population":0,
    "gn:timezone":"Asia/Shanghai",
    "iso:country":"CN",
    "name:zho_x_preferred":[
        "\u5773\u7530\u89d2"
    ],
    "wof:name":"Aotianjiao",
    "wof:placetype":"locality"
},
  "geometry": {"coordinates":[105.30064,29.01538],"type":"Point"}
}