{
  "type": "Feature",
  "properties": {
    "gn:admin1_code":"1.0",
    "gn:asciiname":"Dingchengcun",
    "gn:country_code":"CN",
    "gn:dem":48,
    "gn:feature_class":"P",
    "gn:feature_code":"PPL",
    "gn:name":"Dingchengcun",
    "gn:population":0,
    "gn:timezone":"Asia/Shanghai",
    "iso:country":"CN",
    "name:zho_x_preferred":[
        "\u4e01\u57ce\u6751"
    ],
    "wof:name":"Dingchengcun",
    "wof:placetype":"locality"
},
  "geometry": {"coordinates":[118.59332000000001,32.65192],"type":"Point"}
}