{
  "type": "Feature",
  "properties": {
    "gn:admin1_code":"11.0",
    "gn:asciiname":"Wujia Citang",
    "gn:country_code":"CN",
    "gn:dem":439,
    "gn:feature_class":"P",
    "gn:feature_code":"PPL",
    "gn:name":"Wujia Citang",
    "gn:population":0,
    "gn:timezone":"Asia/Shanghai",
    "iso:country":"CN",
    "name:zho_x_preferred":[
        "\u5434\u5bb6\u7960\u5802"
    ],
    "wof:name":"Wujia Citang",
    "wof:placetype":"locality"
},
  "geometry": {"coordinates":[110.4864,26.70757],"type":"Point"}
}