{
  "type": "Feature",
  "properties": {
    "gn:admin1_code":"10.0",
    "gn:asciiname":"Zhaofanzhuang",
    "gn:country_code":"CN",
    "gn:dem":11,
    "gn:feature_class":"P",
    "gn:feature_code":"PPL",
    "gn:name":"Zhaofanzhuang",
    "gn:population":0,
    "gn:timezone":"Asia/Shanghai",
    "iso:country":"CN",
    "name:zho_x_preferred":[
        "\u8d75\u8303\u5e84"
    ],
    "wof:name":"Zhaofanzhuang",
    "wof:placetype":"locality"
},
  "geometry": {"coordinates":[116.128,38.5951],"type":"Point"}
}