{
  "type": "Feature",
  "properties": {
    "gn:admin1_code":"20.0",
    "gn:asciiname":"Dayan Zhiqingdui",
    "gn:country_code":"CN",
    "gn:dem":673,
    "gn:feature_class":"P",
    "gn:feature_code":"PPLF",
    "gn:name":"Dayan Zhiqingdui",
    "gn:population":0,
    "gn:timezone":"Asia/Shanghai",
    "iso:country":"CN",
    "name:zho_x_preferred":[
        "\u5927\u96c1\u77e5\u9752\u961f"
    ],
    "wof:name":"Dayan Zhiqingdui",
    "wof:placetype":"locality"
},
  "geometry": {"coordinates":[120.57737,49.20272],"type":"Point"}
}