{
  "type": "Feature",
  "properties": {
    "gn:admin1_code":"10.0",
    "gn:asciiname":"Fugezhuangcun",
    "gn:country_code":"CN",
    "gn:dem":29,
    "gn:feature_class":"P",
    "gn:feature_code":"PPL",
    "gn:name":"Fugezhuangcun",
    "gn:population":0,
    "gn:timezone":"Asia/Shanghai",
    "iso:country":"CN",
    "name:zho_x_preferred":[
        "\u5085\u5404\u5e84\u6751"
    ],
    "wof:name":"Fugezhuangcun",
    "wof:placetype":"locality"
},
  "geometry": {"coordinates":[115.542,38.3036],"type":"Point"}
}