{
  "type": "Feature",
  "properties": {
    "gn:admin1_code":"5.0",
    "gn:asciiname":"Jianguotun",
    "gn:country_code":"CN",
    "gn:dem":172,
    "gn:feature_class":"P",
    "gn:feature_code":"PPL",
    "gn:name":"Jianguotun",
    "gn:population":0,
    "gn:timezone":"Asia/Shanghai",
    "iso:country":"CN",
    "name:zho_x_preferred":[
        "\u5efa\u56fd\u5c6f"
    ],
    "wof:name":"Jianguotun",
    "wof:placetype":"locality"
},
  "geometry": {"coordinates":[122.3309,44.92663],"type":"Point"}
}