{
  "type": "Feature",
  "properties": {
    "gn:admin1_code":"29.0",
    "gn:asciiname":"Niaogu",
    "gn:country_code":"CN",
    "gn:dem":1709,
    "gn:feature_class":"P",
    "gn:feature_code":"PPL",
    "gn:name":"Niaogu",
    "gn:population":0,
    "gn:timezone":"Asia/Shanghai",
    "iso:country":"CN",
    "name:zho_x_preferred":[
        "\u9e1f\u59d1"
    ],
    "wof:name":"Niaogu",
    "wof:placetype":"locality"
},
  "geometry": {"coordinates":[101.917,25.9651],"type":"Point"}
}