{
  "type": "Feature",
  "properties": {
    "gn:admin1_code":"32.0",
    "gn:asciiname":"Shuichiya",
    "gn:country_code":"CN",
    "gn:dem":1208,
    "gn:feature_class":"P",
    "gn:feature_code":"PPL",
    "gn:name":"Shuichiya",
    "gn:population":0,
    "gn:timezone":"Asia/Shanghai",
    "iso:country":"CN",
    "name:und_x_variant":[
        "\u6c34\u6c60\u57ad"
    ],
    "wof:name":"Shuichiya",
    "wof:placetype":"locality"
},
  "geometry": {"coordinates":[106.42619000000001,32.3287],"type":"Point"}
}