{
  "type": "Feature",
  "properties": {
    "gn:admin1_code":"19.0",
    "gn:asciiname":"Gaojiadong",
    "gn:country_code":"CN",
    "gn:dem":308,
    "gn:feature_class":"P",
    "gn:feature_code":"PPL",
    "gn:name":"Gaojiadong",
    "gn:population":0,
    "gn:timezone":"Asia/Shanghai",
    "iso:country":"CN",
    "name:und_x_variant":[
        "\u9ad8\u5bb6\u6d1e"
    ],
    "name:zho_x_preferred":[
        "\u9ad8\u5bb6\u6d1e"
    ],
    "wof:name":"Gaojiadong",
    "wof:placetype":"locality"
},
  "geometry": {"coordinates":[119.66840999999999,41.05297],"type":"Point"}
}