{
  "type": "Feature",
  "properties": {
    "gn:admin1_code":"20.0",
    "gn:asciiname":"Sidaogou",
    "gn:country_code":"CN",
    "gn:dem":358,
    "gn:feature_class":"P",
    "gn:feature_code":"PPL",
    "gn:name":"Sidaogou",
    "gn:population":0,
    "gn:timezone":"Asia/Shanghai",
    "iso:country":"CN",
    "name:zho_x_preferred":[
        "\u56db\u9053\u6c9f"
    ],
    "wof:name":"Sidaogou",
    "wof:placetype":"locality"
},
  "geometry": {"coordinates":[122.52567000000001,47.79854],"type":"Point"}
}