{
  "type": "Feature",
  "properties": {
    "gn:admin1_code":"11.0",
    "gn:asciiname":"Quanjing",
    "gn:country_code":"CN",
    "gn:dem":213,
    "gn:feature_class":"P",
    "gn:feature_code":"PPL",
    "gn:name":"Quanjing",
    "gn:population":0,
    "gn:timezone":"Asia/Shanghai",
    "iso:country":"CN",
    "name:zho_x_preferred":[
        "Quanjing"
    ],
    "name:zho_x_variant":[
        "\u6cc9\u4e95"
    ],
    "wof:name":"Quanjing",
    "wof:placetype":"locality"
},
  "geometry": {"coordinates":[114.01737,28.07323],"type":"Point"}
}