{
  "type": "Feature",
  "properties": {
    "gn:admin1_code":"31",
    "gn:asciiname":"Guigen",
    "gn:country_code":"CN",
    "gn:dem":92,
    "gn:feature_class":"P",
    "gn:feature_code":"PPL",
    "gn:name":"Guigen",
    "gn:population":0,
    "gn:timezone":"Asia/Shanghai",
    "iso:country":"CN",
    "name:und_x_variant":[
        "Kuei-ken-ts\u2019un",
        "Guigen",
        "\u6842\u6839"
    ],
    "wof:name":"Guigen",
    "wof:placetype":"locality"
},
  "geometry": {"coordinates":[110.07599999999999,19.5578],"type":"Point"}
}