{
  "type": "Feature",
  "properties": {
    "gn:admin1_code":"25.0",
    "gn:asciiname":"Qiaozigou",
    "gn:country_code":"CN",
    "gn:dem":126,
    "gn:feature_class":"P",
    "gn:feature_code":"PPL",
    "gn:name":"Qiaozigou",
    "gn:population":0,
    "gn:timezone":"Asia/Shanghai",
    "iso:country":"CN",
    "name:zho_x_preferred":[
        "\u6865\u5b50\u6c9f"
    ],
    "wof:name":"Qiaozigou",
    "wof:placetype":"locality"
},
  "geometry": {"coordinates":[121.15062,37.28111],"type":"Point"}
}