{
  "type": "Feature",
  "properties": {
    "gn:admin1_code":"18",
    "gn:asciiname":"Gouchangzhai",
    "gn:country_code":"CN",
    "gn:dem":1077,
    "gn:feature_class":"P",
    "gn:feature_code":"PPL",
    "gn:name":"Gouchangzhai",
    "gn:population":0,
    "gn:timezone":"Asia/Shanghai",
    "iso:country":"CN",
    "name:zho_x_preferred":[
        "\u72d7\u573a\u5be8"
    ],
    "wof:name":"Gouchangzhai",
    "wof:placetype":"locality"
},
  "geometry": {"coordinates":[106.774,26.639],"type":"Point"}
}