{
  "type": "Feature",
  "properties": {
    "gn:admin1_code":"2.0",
    "gn:asciiname":"Sangshumen",
    "gn:country_code":"CN",
    "gn:dem":52,
    "gn:feature_class":"P",
    "gn:feature_code":"PPL",
    "gn:name":"Sangshumen",
    "gn:population":0,
    "gn:timezone":"Asia/Shanghai",
    "iso:country":"CN",
    "name:zho_x_preferred":[
        "\u6851\u6811\u95e8"
    ],
    "wof:name":"Sangshumen",
    "wof:placetype":"locality"
},
  "geometry": {"coordinates":[120.57781,29.84463],"type":"Point"}
}