{
  "type": "Feature",
  "properties": {
    "gn:admin1_code":"24.0",
    "gn:asciiname":"Chuangou",
    "gn:country_code":"CN",
    "gn:dem":1631,
    "gn:feature_class":"P",
    "gn:feature_code":"PPL",
    "gn:name":"Chuangou",
    "gn:population":0,
    "gn:timezone":"Asia/Shanghai",
    "iso:country":"CN",
    "name:zho_x_preferred":[
        "\u5ddd\u6c9f"
    ],
    "wof:name":"Chuangou",
    "wof:placetype":"locality"
},
  "geometry": {"coordinates":[113.79640000000001,38.83683],"type":"Point"}
}