{
  "type": "Feature",
  "properties": {
    "gn:admin1_code":"29.0",
    "gn:asciiname":"Abuhou",
    "gn:country_code":"CN",
    "gn:dem":2111,
    "gn:feature_class":"P",
    "gn:feature_code":"PPL",
    "gn:name":"Abuhou",
    "gn:population":0,
    "gn:timezone":"Asia/Shanghai",
    "iso:country":"CN",
    "name:zho_x_preferred":[
        "\u963f\u5e03\u5019"
    ],
    "wof:name":"Abuhou",
    "wof:placetype":"locality"
},
  "geometry": {"coordinates":[104.211,27.3443],"type":"Point"}
}