{
  "type": "Feature",
  "properties": {
    "gn:admin1_code":"24.0",
    "gn:asciiname":"Donggucheng",
    "gn:country_code":"CN",
    "gn:dem":1421,
    "gn:feature_class":"P",
    "gn:feature_code":"PPL",
    "gn:name":"Donggucheng",
    "gn:population":0,
    "gn:timezone":"Asia/Shanghai",
    "iso:country":"CN",
    "name:und_x_variant":[
        "\u4e1c\u53e4\u57ce"
    ],
    "name:zho_x_preferred":[
        "\u4e1c\u53e4\u57ce"
    ],
    "wof:name":"Donggucheng",
    "wof:placetype":"locality"
},
  "geometry": {"coordinates":[112.61485999999999,39.82585],"type":"Point"}
}