{
  "type": "Feature",
  "properties": {
    "gn:admin1_code":"30.0",
    "gn:asciiname":"Panhushui",
    "gn:country_code":"CN",
    "gn:dem":54,
    "gn:feature_class":"P",
    "gn:feature_code":"PPL",
    "gn:name":"Panhushui",
    "gn:population":0,
    "gn:timezone":"Asia/Shanghai",
    "iso:country":"CN",
    "name:zho_x_preferred":[
        "\u76d8\u6237\u6c34"
    ],
    "wof:name":"Panhushui",
    "wof:placetype":"locality"
},
  "geometry": {"coordinates":[114.83199999999999,23.85877],"type":"Point"}
}