{
  "type": "Feature",
  "properties": {
    "gn:admin1_code":"11.0",
    "gn:asciiname":"Majiayuan",
    "gn:country_code":"CN",
    "gn:dem":31,
    "gn:feature_class":"P",
    "gn:feature_code":"PPL",
    "gn:name":"Majiayuan",
    "gn:population":0,
    "gn:timezone":"Asia/Shanghai",
    "iso:country":"CN",
    "name:zho_x_preferred":[
        "Majiayuan"
    ],
    "name:zho_x_variant":[
        "\u9a6c\u5bb6\u57b8"
    ],
    "wof:name":"Majiayuan",
    "wof:placetype":"locality"
},
  "geometry": {"coordinates":[112.07848,29.45949],"type":"Point"}
}