{
  "type": "Feature",
  "properties": {
    "gn:admin1_code":"10",
    "gn:asciiname":"Banmaozhazi Goumen",
    "gn:country_code":"CN",
    "gn:dem":1077,
    "gn:feature_class":"P",
    "gn:feature_code":"PPL",
    "gn:name":"Banmaozhazi Goumen",
    "gn:population":0,
    "gn:timezone":"Asia/Shanghai",
    "iso:country":"CN",
    "name:zho_x_preferred":[
        "\u534a\u8305\u624e\u5b50\u6c9f\u95e8"
    ],
    "wof:name":"Banmaozhazi Goumen",
    "wof:placetype":"locality"
},
  "geometry": {"coordinates":[118.29958999999999,41.51686],"type":"Point"}
}