{
  "type": "Feature",
  "properties": {
    "gn:admin1_code":"29.0",
    "gn:asciiname":"Dawanzi",
    "gn:country_code":"CN",
    "gn:dem":1849,
    "gn:feature_class":"P",
    "gn:feature_code":"PPL",
    "gn:name":"Dawanzi",
    "gn:population":0,
    "gn:timezone":"Asia/Shanghai",
    "iso:country":"CN",
    "name:zho_x_preferred":[
        "\u5927\u6e7e\u5b50"
    ],
    "wof:name":"Dawanzi",
    "wof:placetype":"locality"
},
  "geometry": {"coordinates":[103.14100000000001,27.3775],"type":"Point"}
}