{
  "type": "Feature",
  "properties": {
    "gn:admin1_code":"12.0",
    "gn:asciiname":"Zhanghuang Chang",
    "gn:country_code":"CN",
    "gn:dem":33,
    "gn:feature_class":"P",
    "gn:feature_code":"PPL",
    "gn:name":"Zhanghuang Chang",
    "gn:population":0,
    "gn:timezone":"Asia/Shanghai",
    "iso:country":"CN",
    "name:zho_x_preferred":[
        "\u5f20\u9ec4\u573a"
    ],
    "wof:name":"Zhanghuang Chang",
    "wof:placetype":"locality"
},
  "geometry": {"coordinates":[112.23627999999999,30.12452],"type":"Point"}
}