{
  "type": "Feature",
  "properties": {
    "gn:admin1_code":"29.0",
    "gn:asciiname":"Shuimoshang",
    "gn:country_code":"CN",
    "gn:dem":2549,
    "gn:feature_class":"P",
    "gn:feature_code":"PPL",
    "gn:name":"Shuimoshang",
    "gn:population":0,
    "gn:timezone":"Asia/Shanghai",
    "iso:country":"CN",
    "name:zho_x_preferred":[
        "\u6c34\u78e8\u4e0a"
    ],
    "wof:name":"Shuimoshang",
    "wof:placetype":"locality"
},
  "geometry": {"coordinates":[103.251,26.6794],"type":"Point"}
}