{
  "type": "Feature",
  "properties": {
    "gn:admin1_code":"30.0",
    "gn:asciiname":"Daochong",
    "gn:country_code":"CN",
    "gn:dem":482,
    "gn:feature_class":"P",
    "gn:feature_code":"PPL",
    "gn:name":"Daochong",
    "gn:population":0,
    "gn:timezone":"Asia/Shanghai",
    "iso:country":"CN",
    "name:zho_x_preferred":[
        "Daochong"
    ],
    "name:zho_x_variant":[
        "\u5230\u51b2"
    ],
    "wof:name":"Daochong",
    "wof:placetype":"locality"
},
  "geometry": {"coordinates":[113.23083,25.48361],"type":"Point"}
}