{
  "type": "Feature",
  "properties": {
    "gn:admin1_code":"26.0",
    "gn:asciiname":"Dasugou",
    "gn:country_code":"CN",
    "gn:dem":781,
    "gn:feature_class":"P",
    "gn:feature_code":"PPL",
    "gn:name":"Dasugou",
    "gn:population":0,
    "gn:timezone":"Asia/Shanghai",
    "iso:country":"CN",
    "name:zho_x_preferred":[
        "\u5927\u82cf\u6c9f"
    ],
    "wof:name":"Dasugou",
    "wof:placetype":"locality"
},
  "geometry": {"coordinates":[110.46531,33.59321],"type":"Point"}
}