{
  "type": "Feature",
  "properties": {
    "gn:admin1_code":"32.0",
    "gn:asciiname":"Luyong",
    "gn:country_code":"CN",
    "gn:dem":426,
    "gn:feature_class":"P",
    "gn:feature_code":"PPL",
    "gn:name":"Luyong",
    "gn:population":0,
    "gn:timezone":"Asia/Shanghai",
    "iso:country":"CN",
    "name:zho_x_preferred":[
        "\u82a6\u6c38"
    ],
    "wof:name":"Luyong",
    "wof:placetype":"locality"
},
  "geometry": {"coordinates":[104.455,30.3535],"type":"Point"}
}