{
  "type": "Feature",
  "properties": {
    "gn:admin1_code":"4.0",
    "gn:asciiname":"Nongye Erdadui",
    "gn:country_code":"CN",
    "gn:dem":1,
    "gn:feature_class":"P",
    "gn:feature_code":"PPLF",
    "gn:name":"Nongye Erdadui",
    "gn:population":0,
    "gn:timezone":"Asia/Shanghai",
    "iso:country":"CN",
    "name:zho_x_preferred":[
        "\u519c\u4e1a\u4e8c\u5927\u961f"
    ],
    "wof:name":"Nongye Erdadui",
    "wof:placetype":"locality"
},
  "geometry": {"coordinates":[120.4953,33.51572],"type":"Point"}
}