{
  "type": "Feature",
  "properties": {
    "gn:admin1_code":"14.0",
    "gn:asciiname":"Puqiong",
    "gn:country_code":"CN",
    "gn:dem":4601,
    "gn:feature_class":"P",
    "gn:feature_code":"PPL",
    "gn:name":"Puqiong",
    "gn:population":0,
    "gn:timezone":"Asia/Urumqi",
    "iso:country":"CN",
    "name:und_x_variant":[
        "Puqiongcun"
    ],
    "name:zho_x_preferred":[
        "\u666e\u7a77"
    ],
    "name:zho_x_variant":[
        "\u666e\u743c",
        "\u666e\u743c\u6751"
    ],
    "wof:name":"Puqiong",
    "wof:placetype":"locality"
},
  "geometry": {"coordinates":[83.13290000000001,30.116],"type":"Point"}
}