{
  "type": "Feature",
  "properties": {
    "gn:admin1_code":"25.0",
    "gn:asciiname":"Beihenggou",
    "gn:country_code":"CN",
    "gn:dem":155,
    "gn:feature_class":"P",
    "gn:feature_code":"PPL",
    "gn:name":"Beihenggou",
    "gn:population":0,
    "gn:timezone":"Asia/Shanghai",
    "iso:country":"CN",
    "name:zho_x_preferred":[
        "\u5317\u6a2a\u6c9f"
    ],
    "wof:name":"Beihenggou",
    "wof:placetype":"locality"
},
  "geometry": {"coordinates":[120.6041,37.35899000000001],"type":"Point"}
}