{
  "type": "Feature",
  "properties": {
    "gn:admin1_code":"24.0",
    "gn:asciiname":"Shaling",
    "gn:country_code":"CN",
    "gn:dem":975,
    "gn:feature_class":"P",
    "gn:feature_code":"PPL",
    "gn:name":"Shaling",
    "gn:population":0,
    "gn:timezone":"Asia/Shanghai",
    "iso:country":"CN",
    "name:und_x_variant":[
        "\u6c99\u5cad"
    ],
    "name:zho_x_preferred":[
        "\u6c99\u5cad"
    ],
    "wof:name":"Shaling",
    "wof:placetype":"locality"
},
  "geometry": {"coordinates":[113.52697999999999,39.88858],"type":"Point"}
}