{
  "type": "Feature",
  "properties": {
    "gn:admin1_code":"29.0",
    "gn:asciiname":"Yumie",
    "gn:country_code":"CN",
    "gn:dem":1929,
    "gn:feature_class":"P",
    "gn:feature_code":"PPL",
    "gn:name":"Yumie",
    "gn:population":0,
    "gn:timezone":"Asia/Shanghai",
    "iso:country":"CN",
    "name:zho_x_preferred":[
        "\u96e8\u54a9"
    ],
    "wof:name":"Yumie",
    "wof:placetype":"locality"
},
  "geometry": {"coordinates":[103.767,24.45],"type":"Point"}
}