{
  "type": "Feature",
  "properties": {
    "gn:admin1_code":"3.0",
    "gn:asciiname":"Yongchun",
    "gn:country_code":"CN",
    "gn:dem":48,
    "gn:feature_class":"P",
    "gn:feature_code":"PPL",
    "gn:name":"Yongchun",
    "gn:population":0,
    "gn:timezone":"Asia/Shanghai",
    "iso:country":"CN",
    "name:ceb_x_preferred":[
        "Yongchun"
    ],
    "name:deu_x_preferred":[
        "Yongchun"
    ],
    "name:zho_x_preferred":[
        "\u6c38\u6625"
    ],
    "wof:name":"Yongchun",
    "wof:placetype":"locality"
},
  "geometry": {"coordinates":[114.907,27.4232],"type":"Point"}
}