{
  "type": "Feature",
  "properties": {
    "gn:admin1_code":"23.0",
    "gn:asciiname":"Jianqiang",
    "gn:country_code":"CN",
    "gn:dem":2,
    "gn:feature_class":"P",
    "gn:feature_code":"PPL",
    "gn:name":"Jianqiang",
    "gn:population":0,
    "gn:timezone":"Asia/Shanghai",
    "iso:country":"CN",
    "name:und_x_variant":[
        "\u575a\u5f3a"
    ],
    "wof:name":"Jianqiang",
    "wof:placetype":"locality"
},
  "geometry": {"coordinates":[121.23181,31.19385],"type":"Point"}
}