{
  "type": "Feature",
  "properties": {
    "gn:admin1_code":"30.0",
    "gn:asciiname":"Dongning",
    "gn:country_code":"CN",
    "gn:dem":27,
    "gn:feature_class":"P",
    "gn:feature_code":"PPL",
    "gn:name":"Dongning",
    "gn:population":0,
    "gn:timezone":"Asia/Shanghai",
    "iso:country":"CN",
    "name:deu_x_preferred":[
        "Dongning"
    ],
    "name:zho_x_preferred":[
        "\u6d1e\u5b81"
    ],
    "wof:name":"Dongning",
    "wof:placetype":"locality"
},
  "geometry": {"coordinates":[112.83129,22.20229],"type":"Point"}
}