{
  "type": "Feature",
  "properties": {
    "gn:admin1_code":"29.0",
    "gn:asciiname":"Yakoushang",
    "gn:country_code":"CN",
    "gn:dem":2180,
    "gn:feature_class":"P",
    "gn:feature_code":"PPL",
    "gn:name":"Yakoushang",
    "gn:population":0,
    "gn:timezone":"Asia/Shanghai",
    "iso:country":"CN",
    "name:zho_x_preferred":[
        "\u57ad\u53e3\u4e0a"
    ],
    "wof:name":"Yakoushang",
    "wof:placetype":"locality"
},
  "geometry": {"coordinates":[103.377,27.6074],"type":"Point"}
}