{
  "type": "Feature",
  "properties": {
    "gn:admin1_code":"29.0",
    "gn:asciiname":"Yizhi",
    "gn:country_code":"CN",
    "gn:dem":2645,
    "gn:feature_class":"P",
    "gn:feature_code":"PPL",
    "gn:name":"Yizhi",
    "gn:population":0,
    "gn:timezone":"Asia/Shanghai",
    "iso:country":"CN",
    "name:zho_x_preferred":[
        "\u4f9d\u652f"
    ],
    "wof:name":"Yizhi",
    "wof:placetype":"locality"
},
  "geometry": {"coordinates":[99.4684,27.4286],"type":"Point"}
}