{
  "type": "Feature",
  "properties": {
    "gn:admin1_code":"19.0",
    "gn:asciiname":"Beidi Laozhoujia",
    "gn:country_code":"CN",
    "gn:dem":17,
    "gn:feature_class":"P",
    "gn:feature_code":"PPL",
    "gn:name":"Beidi Laozhoujia",
    "gn:population":0,
    "gn:timezone":"Asia/Shanghai",
    "iso:country":"CN",
    "name:zho_x_preferred":[
        "\u5317\u5730\u8001\u5468\u5bb6"
    ],
    "wof:name":"Beidi Laozhoujia",
    "wof:placetype":"locality"
},
  "geometry": {"coordinates":[120.31999999999999,40.348],"type":"Point"}
}