{
  "type": "Feature",
  "properties": {
    "gn:admin1_code":"21.0",
    "gn:asciiname":"Huanghaocha",
    "gn:country_code":"CN",
    "gn:dem":1872,
    "gn:feature_class":"P",
    "gn:feature_code":"PPL",
    "gn:name":"Huanghaocha",
    "gn:population":0,
    "gn:timezone":"Asia/Shanghai",
    "iso:country":"CN",
    "name:und_x_variant":[
        "\u9ec4\u58d5\u5c94"
    ],
    "name:zho_x_preferred":[
        "\u9ec4\u58d5\u5c94"
    ],
    "wof:name":"Huanghaocha",
    "wof:placetype":"locality"
},
  "geometry": {"coordinates":[106.4926,36.45738],"type":"Point"}
}