{
  "type": "Feature",
  "properties": {
    "gn:admin1_code":"13.0",
    "gn:asciiname":"Pao-la-su-mu",
    "gn:country_code":"CN",
    "gn:dem":1055,
    "gn:feature_class":"P",
    "gn:feature_code":"PPL",
    "gn:name":"Pao-la-su-mu",
    "gn:population":0,
    "gn:timezone":"Asia/Urumqi",
    "iso:country":"CN",
    "wof:name":"Pao-la-su-mu",
    "wof:placetype":"locality"
},
  "geometry": {"coordinates":[86.6675,42.02528],"type":"Point"}
}