{
  "type": "Feature",
  "properties": {
    "gn:country":"CN",
    "gn:fcode":"PPL",
    "gn:pop":108883,
    "iso:country":"CN",
    "name:eng_x_historical":[
        "Anlu"
    ],
    "name:eng_x_preferred":[
        "Anlu"
    ],
    "name:unk_x_variant":[
        "Anlufu"
    ],
    "qs:name":"Zhongxiang",
    "qs:photos_9r":0,
    "qs:photos_sr":0,
    "qs:pop_sr":"9",
    "wd:wordcount":1133,
    "wof:name":"Zhongxiang",
    "wof:placetype":"locality",
    "wof:population":108883
},
  "geometry": {"coordinates":[112.58306,31.16611],"type":"Point"}
}