{
  "type": "Feature",
  "properties": {
    "gn:admin1_code":"26.0",
    "gn:asciiname":"Lujiashancun",
    "gn:country_code":"CN",
    "gn:dem":1039,
    "gn:feature_class":"P",
    "gn:feature_code":"PPL",
    "gn:name":"L\u00fcjiashancun",
    "gn:population":0,
    "gn:timezone":"Asia/Shanghai",
    "iso:country":"CN",
    "name:und_x_variant":[
        "L\u00fcjiashancun"
    ],
    "name:zho_x_preferred":[
        "\u5415\u5bb6\u5c71\u6751"
    ],
    "wof:name":"Lujiashancun",
    "wof:placetype":"locality"
},
  "geometry": {"coordinates":[109.66173999999999,35.43808],"type":"Point"}
}