{
  "type": "Feature",
  "properties": {
    "gn:admin1_code":"16.0",
    "gn:asciiname":"Liangjiazhai",
    "gn:country_code":"CN",
    "gn:dem":177,
    "gn:feature_class":"P",
    "gn:feature_code":"PPL",
    "gn:name":"Liangjiazhai",
    "gn:population":0,
    "gn:timezone":"Asia/Shanghai",
    "iso:country":"CN",
    "name:zho_x_preferred":[
        "\u826f\u4f73\u5be8"
    ],
    "wof:name":"Liangjiazhai",
    "wof:placetype":"locality"
},
  "geometry": {"coordinates":[109.967,24.7986],"type":"Point"}
}