{
  "type": "Feature",
  "properties": {
    "gn:admin1_code":"15.0",
    "gn:asciiname":"Heduipotan",
    "gn:country_code":"CN",
    "gn:dem":1363,
    "gn:feature_class":"P",
    "gn:feature_code":"PPL",
    "gn:name":"Heduipotan",
    "gn:population":0,
    "gn:timezone":"Asia/Shanghai",
    "iso:country":"CN",
    "name:zho_x_preferred":[
        "\u6cb3\u5bf9\u5761\u6ee9"
    ],
    "wof:name":"Heduipotan",
    "wof:placetype":"locality"
},
  "geometry": {"coordinates":[104.30200000000001,37.0355],"type":"Point"}
}