{
  "type": "Feature",
  "properties": {
    "gn:admin1_code":"20.0",
    "gn:asciiname":"Damen Zhuang",
    "gn:country_code":"CN",
    "gn:dem":259,
    "gn:feature_class":"P",
    "gn:feature_code":"PPL",
    "gn:name":"Damen Zhuang",
    "gn:population":0,
    "gn:timezone":"Asia/Shanghai",
    "iso:country":"CN",
    "name:zho_x_preferred":[
        "\u5927\u95e8\u5e84"
    ],
    "wof:name":"Damen Zhuang",
    "wof:placetype":"locality"
},
  "geometry": {"coordinates":[124.30561000000002,48.99099],"type":"Point"}
}