{
  "type": "Feature",
  "properties": {
    "gn:admin1_code":"25.0",
    "gn:asciiname":"Xilingxi",
    "gn:country_code":"CN",
    "gn:dem":59,
    "gn:feature_class":"P",
    "gn:feature_code":"PPL",
    "gn:name":"Xilingxi",
    "gn:population":0,
    "gn:timezone":"Asia/Shanghai",
    "iso:country":"CN",
    "name:zho_x_preferred":[
        "\u897f\u5cad\u897f"
    ],
    "wof:name":"Xilingxi",
    "wof:placetype":"locality"
},
  "geometry": {"coordinates":[121.88623,37.32426],"type":"Point"}
}