{
  "type": "Feature",
  "properties": {
    "gn:admin1_code":"7.0",
    "gn:asciiname":"Lianwugang",
    "gn:country_code":"CN",
    "gn:dem":596,
    "gn:feature_class":"P",
    "gn:feature_code":"PPL",
    "gn:name":"Lianwugang",
    "gn:population":0,
    "gn:timezone":"Asia/Shanghai",
    "iso:country":"CN",
    "name:zho_x_preferred":[
        "\u8fde\u5c4b\u5c97"
    ],
    "wof:name":"Lianwugang",
    "wof:placetype":"locality"
},
  "geometry": {"coordinates":[116.56135,25.64651],"type":"Point"}
}