{
  "type": "Feature",
  "properties": {
    "gn:admin1_code":"19.0",
    "gn:asciiname":"Litanggou",
    "gn:country_code":"CN",
    "gn:dem":106,
    "gn:feature_class":"P",
    "gn:feature_code":"PPL",
    "gn:name":"Litanggou",
    "gn:population":0,
    "gn:timezone":"Asia/Shanghai",
    "iso:country":"CN",
    "name:zho_x_preferred":[
        "\u674e\u5858\u6c9f"
    ],
    "wof:name":"Litanggou",
    "wof:placetype":"locality"
},
  "geometry": {"coordinates":[121.38,38.8489],"type":"Point"}
}