{
  "type": "Feature",
  "properties": {
    "gn:admin1_code":"33.0",
    "gn:asciiname":"Tuchengba",
    "gn:country_code":"CN",
    "gn:dem":649,
    "gn:feature_class":"P",
    "gn:feature_code":"PPL",
    "gn:name":"Tuchengba",
    "gn:population":0,
    "gn:timezone":"Asia/Shanghai",
    "iso:country":"CN",
    "name:zho_x_preferred":[
        "\u571f\u57ce\u575d"
    ],
    "wof:name":"Tuchengba",
    "wof:placetype":"locality"
},
  "geometry": {"coordinates":[108.7441,28.66815],"type":"Point"}
}