{
  "type": "Feature",
  "properties": {
    "gn:admin1_code":"32.0",
    "gn:asciiname":"Baruo",
    "gn:country_code":"CN",
    "gn:dem":4334,
    "gn:feature_class":"P",
    "gn:feature_code":"PPL",
    "gn:name":"Baruo",
    "gn:population":0,
    "gn:timezone":"Asia/Shanghai",
    "iso:country":"CN",
    "name:zho_x_preferred":[
        "\u516b\u82e5"
    ],
    "wof:name":"Baruo",
    "wof:placetype":"locality"
},
  "geometry": {"coordinates":[97.7196,33.4545],"type":"Point"}
}