{
  "type": "Feature",
  "properties": {
    "gn:admin1_code":"3.0",
    "gn:asciiname":"Xiawanshi",
    "gn:country_code":"CN",
    "gn:dem":84,
    "gn:feature_class":"P",
    "gn:feature_code":"PPL",
    "gn:name":"Xiawanshi",
    "gn:population":0,
    "gn:timezone":"Asia/Shanghai",
    "iso:country":"CN",
    "name:zho_x_preferred":[
        "\u4e0b\u4e07\u77f3"
    ],
    "wof:name":"Xiawanshi",
    "wof:placetype":"locality"
},
  "geometry": {"coordinates":[114.843,27.7752],"type":"Point"}
}