{
  "type": "Feature",
  "properties": {
    "gn:admin1_code":"7",
    "gn:asciiname":"Zhuling",
    "gn:country_code":"CN",
    "gn:dem":713,
    "gn:feature_class":"P",
    "gn:feature_code":"PPL",
    "gn:name":"Zhuling",
    "gn:population":0,
    "gn:timezone":"Asia/Shanghai",
    "iso:country":"CN",
    "name:und_x_variant":[
        "\u7af9\u5cad",
        "Zhuling"
    ],
    "wof:name":"Zhuling",
    "wof:placetype":"locality"
},
  "geometry": {"coordinates":[119.84636,27.16252],"type":"Point"}
}