{
  "type": "Feature",
  "properties": {
    "gn:admin1_code":"19.0",
    "gn:asciiname":"Hujialing",
    "gn:country_code":"CN",
    "gn:dem":400,
    "gn:feature_class":"P",
    "gn:feature_code":"PPL",
    "gn:name":"Hujialing",
    "gn:population":0,
    "gn:timezone":"Asia/Shanghai",
    "iso:country":"CN",
    "name:und_x_variant":[
        "\u80e1\u5bb6\u5cad"
    ],
    "name:zho_x_preferred":[
        "\u80e1\u5bb6\u5cad"
    ],
    "wof:name":"Hujialing",
    "wof:placetype":"locality"
},
  "geometry": {"coordinates":[121.768,41.9362],"type":"Point"}
}