{
  "type": "Feature",
  "properties": {
    "gn:admin1_code":"14.0",
    "gn:asciiname":"Kajunguo",
    "gn:country_code":"CN",
    "gn:dem":4213,
    "gn:feature_class":"P",
    "gn:feature_code":"PPL",
    "gn:name":"Kajunguo",
    "gn:population":0,
    "gn:timezone":"Asia/Urumqi",
    "iso:country":"CN",
    "name:zho_x_preferred":[
        "\u5361\u519b\u679c"
    ],
    "wof:name":"Kajunguo",
    "wof:placetype":"locality"
},
  "geometry": {"coordinates":[91.85028,29.70147],"type":"Point"}
}