{
  "type": "Feature",
  "properties": {
    "gn:admin1_code":"05",
    "gn:asciiname":"Henglucun",
    "gn:country_code":"CN",
    "gn:dem":390,
    "gn:feature_class":"P",
    "gn:feature_code":"PPL",
    "gn:name":"Henglucun",
    "gn:population":0,
    "gn:timezone":"Asia/Shanghai",
    "iso:country":"CN",
    "name:und_x_variant":[
        "Henglu",
        "\u6a2a\u8def",
        "Henglucun"
    ],
    "name:zho_x_preferred":[
        "\u6a2a\u8def\u6751"
    ],
    "wof:name":"Henglucun",
    "wof:placetype":"locality"
},
  "geometry": {"coordinates":[125.80745,41.34359],"type":"Point"}
}