{
  "type": "Feature",
  "properties": {
    "gn:admin1_code":"11",
    "gn:asciiname":"Cangdongyuan",
    "gn:country_code":"CN",
    "gn:dem":91,
    "gn:feature_class":"P",
    "gn:feature_code":"PPL",
    "gn:name":"Cangdongyuan",
    "gn:population":0,
    "gn:timezone":"Asia/Shanghai",
    "iso:country":"CN",
    "name:zho_x_preferred":[
        "\u82cd\u6d1e\u6e90"
    ],
    "wof:name":"Cangdongyuan",
    "wof:placetype":"locality"
},
  "geometry": {"coordinates":[112.12907,26.61303],"type":"Point"}
}