{
  "type": "Feature",
  "properties": {
    "gn:admin1_code":"13.0",
    "gn:asciiname":"Bextograk",
    "gn:country_code":"CN",
    "gn:dem":1050,
    "gn:feature_class":"P",
    "gn:feature_code":"PPL",
    "gn:name":"Bextograk",
    "gn:population":0,
    "gn:timezone":"Asia/Urumqi",
    "iso:country":"CN",
    "name:uig_x_preferred":[
        "B\u0259xto\u01a3rak\u0329"
    ],
    "name:uig_x_variant":[
        "Beshtoghraq",
        "\u0628\u06d5\u0634\u062a\u0648\u063a\u0631\u0627\u0642",
        "\u0411\u04d9\u0448\u0442\u043e\u0493\u0440\u0430\u049b"
    ],
    "name:und_x_variant":[
        "Pai-shih-t\u2019o-ko-la-k\u2019o",
        "Bextograk",
        "Baishituo Gelake"
    ],
    "name:zho_x_preferred":[
        "\u62dc\u4ec0\u6258\u683c\u814a\u514b"
    ],
    "wof:name":"Bextograk",
    "wof:placetype":"locality"
},
  "geometry": {"coordinates":[86.95732,38.607],"type":"Point"}
}