{
  "type": "Feature",
  "properties": {
    "gn:admin1_code":"8.0",
    "gn:asciiname":"Zhangquandiantun",
    "gn:country_code":"CN",
    "gn:dem":146,
    "gn:feature_class":"P",
    "gn:feature_code":"PPL",
    "gn:name":"Zhangquandiantun",
    "gn:population":0,
    "gn:timezone":"Asia/Shanghai",
    "iso:country":"CN",
    "name:zho_x_preferred":[
        "\u5f20\u5168\u5e97\u5c6f"
    ],
    "wof:name":"Zhangquandiantun",
    "wof:placetype":"locality"
},
  "geometry": {"coordinates":[126.23565000000001,46.94505],"type":"Point"}
}