{
  "type": "Feature",
  "properties": {
    "gn:admin1_code":"11.0",
    "gn:asciiname":"Wujia Wuchang",
    "gn:country_code":"CN",
    "gn:dem":968,
    "gn:feature_class":"P",
    "gn:feature_code":"PPL",
    "gn:name":"Wujia Wuchang",
    "gn:population":0,
    "gn:timezone":"Asia/Shanghai",
    "iso:country":"CN",
    "name:zho_x_preferred":[
        "\u4f0d\u5bb6\u5c4b\u573a"
    ],
    "wof:name":"Wujia Wuchang",
    "wof:placetype":"locality"
},
  "geometry": {"coordinates":[110.86418,27.73865],"type":"Point"}
}