{
  "type": "Feature",
  "properties": {
    "gn:admin1_code":"4.0",
    "gn:asciiname":"Xinglongzhuang",
    "gn:country_code":"CN",
    "gn:dem":3,
    "gn:feature_class":"P",
    "gn:feature_code":"PPL",
    "gn:name":"Xinglongzhuang",
    "gn:population":0,
    "gn:timezone":"Asia/Shanghai",
    "iso:country":"CN",
    "name:zho_x_preferred":[
        "\u5174\u9686\u5e84"
    ],
    "wof:name":"Xinglongzhuang",
    "wof:placetype":"locality"
},
  "geometry": {"coordinates":[119.59958,32.66477],"type":"Point"}
}