{
  "type": "Feature",
  "properties": {
    "gn:admin1_code":"19.0",
    "gn:asciiname":"Meihualing",
    "gn:country_code":"CN",
    "gn:dem":41,
    "gn:feature_class":"P",
    "gn:feature_code":"PPL",
    "gn:name":"Meihualing",
    "gn:population":0,
    "gn:timezone":"Asia/Shanghai",
    "iso:country":"CN",
    "name:zho_x_preferred":[
        "\u6885\u82b1\u5cad"
    ],
    "wof:name":"Meihualing",
    "wof:placetype":"locality"
},
  "geometry": {"coordinates":[123.381,41.2561],"type":"Point"}
}