{
  "type": "Feature",
  "properties": {
    "gn:admin1_code":"24.0",
    "gn:asciiname":"Houqingyanggou",
    "gn:country_code":"CN",
    "gn:dem":1664,
    "gn:feature_class":"P",
    "gn:feature_code":"PPL",
    "gn:name":"Houqingyanggou",
    "gn:population":0,
    "gn:timezone":"Asia/Shanghai",
    "iso:country":"CN",
    "name:zho_x_preferred":[
        "\u540e\u9752\u6768\u6c9f"
    ],
    "wof:name":"Houqingyanggou",
    "wof:placetype":"locality"
},
  "geometry": {"coordinates":[111.60477,37.94441],"type":"Point"}
}