{
  "type": "Feature",
  "properties": {
    "gn:admin1_code":"25",
    "gn:asciiname":"Shijiacun",
    "gn:country_code":"CN",
    "gn:dem":136,
    "gn:feature_class":"P",
    "gn:feature_code":"PPL",
    "gn:name":"Shijiacun",
    "gn:population":0,
    "gn:timezone":"Asia/Shanghai",
    "iso:country":"CN",
    "name:zho_x_preferred":[
        "\u65f6\u5bb6\u6751"
    ],
    "wof:name":"Shijiacun",
    "wof:placetype":"locality"
},
  "geometry": {"coordinates":[117.88200000000001,35.44],"type":"Point"}
}