{
  "type": "Feature",
  "properties": {
    "gn:admin1_code":"15.0",
    "gn:asciiname":"Pujiawan",
    "gn:country_code":"CN",
    "gn:dem":1103,
    "gn:feature_class":"P",
    "gn:feature_code":"PPL",
    "gn:name":"Pujiawan",
    "gn:population":0,
    "gn:timezone":"Asia/Shanghai",
    "iso:country":"CN",
    "name:und_x_variant":[
        "\u84b2\u5bb6\u6e7e"
    ],
    "wof:name":"Pujiawan",
    "wof:placetype":"locality"
},
  "geometry": {"coordinates":[106.28406,33.84274],"type":"Point"}
}