{
  "type": "Feature",
  "properties": {
    "gn:admin1_code":"14.0",
    "gn:asciiname":"Agangcun",
    "gn:country_code":"CN",
    "gn:dem":3453,
    "gn:feature_class":"P",
    "gn:feature_code":"PPL",
    "gn:name":"Agangcun",
    "gn:population":0,
    "gn:timezone":"Asia/Urumqi",
    "iso:country":"CN",
    "name:zho_x_preferred":[
        "\u963f\u5c97\u6751"
    ],
    "wof:name":"Agangcun",
    "wof:placetype":"locality"
},
  "geometry": {"coordinates":[92.79066,29.10834],"type":"Point"}
}