{
  "type": "Feature",
  "properties": {
    "gn:admin1_code":"11",
    "gn:asciiname":"Shiyangtang",
    "gn:country_code":"CN",
    "gn:dem":90,
    "gn:feature_class":"P",
    "gn:feature_code":"PPL",
    "gn:name":"Shiyangtang",
    "gn:population":0,
    "gn:timezone":"Asia/Shanghai",
    "iso:country":"CN",
    "name:zho_x_preferred":[
        "\u77f3\u7f8a\u5858\u9547"
    ],
    "wof:name":"Shiyangtang",
    "wof:placetype":"locality"
},
  "geometry": {"coordinates":[113.30361000000001,27.08972],"type":"Point"}
}