{
  "type": "Feature",
  "properties": {
    "gn:admin1_code":"7",
    "gn:asciiname":"Hutunzai",
    "gn:country_code":"CN",
    "gn:dem":491,
    "gn:feature_class":"P",
    "gn:feature_code":"PPL",
    "gn:name":"Hutunzai",
    "gn:population":0,
    "gn:timezone":"Asia/Shanghai",
    "iso:country":"CN",
    "name:und_x_variant":[
        "\u80e1\u5c6f\u4ed4",
        "Hutunzai"
    ],
    "wof:name":"Hutunzai",
    "wof:placetype":"locality"
},
  "geometry": {"coordinates":[118.99844,27.47779],"type":"Point"}
}