{
  "type": "Feature",
  "properties": {
    "gn:admin1_code":"4.0",
    "gn:asciiname":"Mingyinsi",
    "gn:country_code":"CN",
    "gn:dem":15,
    "gn:feature_class":"P",
    "gn:feature_code":"PPL",
    "gn:name":"Mingyinsi",
    "gn:population":0,
    "gn:timezone":"Asia/Shanghai",
    "iso:country":"CN",
    "name:zho_x_preferred":[
        "\u660e\u56e0\u5bfa"
    ],
    "wof:name":"Mingyinsi",
    "wof:placetype":"locality"
},
  "geometry": {"coordinates":[118.52808,31.9613],"type":"Point"}
}