{
  "type": "Feature",
  "properties": {
    "gn:admin1_code":"8.0",
    "gn:asciiname":"Shuangfeng",
    "gn:country_code":"CN",
    "gn:dem":238,
    "gn:feature_class":"P",
    "gn:feature_code":"PPL",
    "gn:name":"Shuangfeng",
    "gn:population":0,
    "gn:timezone":"Asia/Shanghai",
    "iso:country":"CN",
    "name:ceb_x_preferred":[
        "Shuangfeng"
    ],
    "name:deu_x_preferred":[
        "Shuangfeng"
    ],
    "name:zho_x_preferred":[
        "\u53cc\u4e30"
    ],
    "wof:name":"Shuangfeng",
    "wof:placetype":"locality"
},
  "geometry": {"coordinates":[130.02891,48.36998],"type":"Point"}
}