{
  "type": "Feature",
  "properties": {
    "gn:admin1_code":"12.0",
    "gn:asciiname":"Tangjiafan",
    "gn:country_code":"CN",
    "gn:dem":155,
    "gn:feature_class":"P",
    "gn:feature_code":"PPL",
    "gn:name":"Tangjiafan",
    "gn:population":0,
    "gn:timezone":"Asia/Shanghai",
    "iso:country":"CN",
    "name:zho_x_preferred":[
        "\u6c64\u5bb6\u7548"
    ],
    "wof:name":"Tangjiafan",
    "wof:placetype":"locality"
},
  "geometry": {"coordinates":[113.39948,31.35549],"type":"Point"}
}