{
  "type": "Feature",
  "properties": {
    "gn:admin1_code":"32.0",
    "gn:asciiname":"Dasongshu",
    "gn:country_code":"CN",
    "gn:dem":1867,
    "gn:feature_class":"P",
    "gn:feature_code":"PPL",
    "gn:name":"Dasongshu",
    "gn:population":0,
    "gn:timezone":"Asia/Shanghai",
    "iso:country":"CN",
    "name:zho_x_preferred":[
        "\u5927\u677e\u6811"
    ],
    "wof:name":"Dasongshu",
    "wof:placetype":"locality"
},
  "geometry": {"coordinates":[102.55188,26.69592],"type":"Point"}
}