{
  "type": "Feature",
  "properties": {
    "gn:admin1_code":"29.0",
    "gn:asciiname":"Da'edi",
    "gn:country_code":"CN",
    "gn:dem":2001,
    "gn:feature_class":"P",
    "gn:feature_code":"PPL",
    "gn:name":"Da\u2019edi",
    "gn:population":0,
    "gn:timezone":"Asia/Shanghai",
    "iso:country":"CN",
    "name:und_x_variant":[
        "Da\u2019edi"
    ],
    "name:zho_x_preferred":[
        "\u6253\u4fc4\u5e95"
    ],
    "wof:name":"Da'edi",
    "wof:placetype":"locality"
},
  "geometry": {"coordinates":[98.90519999999999,26.7643],"type":"Point"}
}