{
  "type": "Feature",
  "properties": {
    "gn:admin1_code":"25",
    "gn:asciiname":"Heituwa",
    "gn:country_code":"CN",
    "gn:dem":368,
    "gn:feature_class":"P",
    "gn:feature_code":"PPL",
    "gn:name":"Heituwa",
    "gn:population":0,
    "gn:timezone":"Asia/Shanghai",
    "iso:country":"CN",
    "name:zho_x_preferred":[
        "\u9ed1\u571f\u6d3c"
    ],
    "wof:name":"Heituwa",
    "wof:placetype":"locality"
},
  "geometry": {"coordinates":[118.223,35.941],"type":"Point"}
}