{
  "type": "Feature",
  "properties": {
    "gn:admin1_code":"32.0",
    "gn:asciiname":"Seweng",
    "gn:country_code":"CN",
    "gn:dem":3475,
    "gn:feature_class":"P",
    "gn:feature_code":"PPL",
    "gn:name":"Seweng",
    "gn:population":0,
    "gn:timezone":"Asia/Shanghai",
    "iso:country":"CN",
    "name:zho_x_preferred":[
        "\u8272\u7fc1"
    ],
    "wof:name":"Seweng",
    "wof:placetype":"locality"
},
  "geometry": {"coordinates":[100.629,29.0732],"type":"Point"}
}