{
  "type": "Feature",
  "properties": {
    "gn:admin1_code":"20",
    "gn:asciiname":"Marain Sum",
    "gn:cc2":"CN",
    "gn:country_code":"CN",
    "gn:dem":293,
    "gn:feature_class":"P",
    "gn:feature_code":"PPL",
    "gn:name":"Marain Sum",
    "gn:population":0,
    "gn:timezone":"Asia/Shanghai",
    "iso:country":"CN",
    "name:und_x_variant":[
        "Mei-lin-miao",
        "Marain Sum"
    ],
    "wof:name":"Marain Sum",
    "wof:placetype":"locality"
},
  "geometry": {"coordinates":[120.86667,44.03333],"type":"Point"}
}