{
  "type": "Feature",
  "properties": {
    "gn:admin1_code":"2.0",
    "gn:asciiname":"Daqiaotou",
    "gn:country_code":"CN",
    "gn:dem":190,
    "gn:feature_class":"P",
    "gn:feature_code":"PPL",
    "gn:name":"Daqiaotou",
    "gn:population":0,
    "gn:timezone":"Asia/Shanghai",
    "iso:country":"CN",
    "name:zho_x_preferred":[
        "\u5927\u6865\u5934"
    ],
    "wof:name":"Daqiaotou",
    "wof:placetype":"locality"
},
  "geometry": {"coordinates":[120.62488999999999,29.67313],"type":"Point"}
}