{
  "type": "Feature",
  "properties": {
    "gn:admin1_code":"02",
    "gn:asciiname":"Tiantongcun",
    "gn:country_code":"CN",
    "gn:dem":153,
    "gn:feature_class":"P",
    "gn:feature_code":"PPL",
    "gn:name":"Tiantongcun",
    "gn:population":0,
    "gn:timezone":"Asia/Shanghai",
    "iso:country":"CN",
    "name:und_x_variant":[
        "T\u2019ai-t\u2019ung-chieh",
        "T\u2019ien-t\u2019ung-chieh",
        "T\u2019ien-t\u2019ung",
        "Tiantong",
        "Tiantongcun"
    ],
    "name:zho_x_preferred":[
        "\u5929\u7ae5"
    ],
    "name:zho_x_variant":[
        "\u5929\u7ae5\u6751"
    ],
    "wof:name":"Tiantongcun",
    "wof:placetype":"locality"
},
  "geometry": {"coordinates":[121.77498,29.79188],"type":"Point"}
}