{
  "type": "Feature",
  "properties": {
    "gn:admin1_code":"9",
    "gn:asciiname":"Dafuzhuang",
    "gn:country_code":"CN",
    "gn:dem":61,
    "gn:feature_class":"P",
    "gn:feature_code":"PPL",
    "gn:name":"Dafuzhuang",
    "gn:population":0,
    "gn:timezone":"Asia/Shanghai",
    "iso:country":"CN",
    "name:zho_x_preferred":[
        "\u5927\u4ed8\u5e84"
    ],
    "wof:name":"Dafuzhuang",
    "wof:placetype":"locality"
},
  "geometry": {"coordinates":[115.111,34.4589],"type":"Point"}
}