{
  "type": "Feature",
  "properties": {
    "gn:admin1_code":"3.0",
    "gn:asciiname":"Laoyanlong",
    "gn:country_code":"CN",
    "gn:dem":24,
    "gn:feature_class":"P",
    "gn:feature_code":"PPL",
    "gn:name":"Laoyanlong",
    "gn:population":0,
    "gn:timezone":"Asia/Shanghai",
    "iso:country":"CN",
    "name:und_x_variant":[
        "\u8001\u4e25\u5784"
    ],
    "wof:name":"Laoyanlong",
    "wof:placetype":"locality"
},
  "geometry": {"coordinates":[115.85599000000001,29.16282],"type":"Point"}
}