{
  "type": "Feature",
  "properties": {
    "gn:admin1_code":"32.0",
    "gn:asciiname":"Hexuangou",
    "gn:country_code":"CN",
    "gn:dem":1222,
    "gn:feature_class":"P",
    "gn:feature_code":"PPL",
    "gn:name":"Hexuangou",
    "gn:population":0,
    "gn:timezone":"Asia/Shanghai",
    "iso:country":"CN",
    "name:zho_x_preferred":[
        "\u6cb3\u65cb\u6c9f"
    ],
    "wof:name":"Hexuangou",
    "wof:placetype":"locality"
},
  "geometry": {"coordinates":[105.30023,32.46463],"type":"Point"}
}