{
  "type": "Feature",
  "properties": {
    "gn:admin1_code":"30.0",
    "gn:asciiname":"Dansa",
    "gn:country_code":"CN",
    "gn:dem":81,
    "gn:feature_class":"P",
    "gn:feature_code":"PPL",
    "gn:name":"Dansa",
    "gn:population":0,
    "gn:timezone":"Asia/Shanghai",
    "iso:country":"CN",
    "name:cat_x_preferred":[
        "Dansa"
    ],
    "name:ita_x_preferred":[
        "Dansa"
    ],
    "name:zho_x_preferred":[
        "\u62c5\u6492"
    ],
    "wof:name":"Dansa",
    "wof:placetype":"locality"
},
  "geometry": {"coordinates":[112.15040999999999,23.87097],"type":"Point"}
}