{
  "type": "Feature",
  "properties": {
    "gn:admin1_code":"3.0",
    "gn:asciiname":"Houzinao",
    "gn:country_code":"CN",
    "gn:dem":343,
    "gn:feature_class":"P",
    "gn:feature_code":"PPL",
    "gn:name":"Houzinao",
    "gn:population":0,
    "gn:timezone":"Asia/Shanghai",
    "iso:country":"CN",
    "name:und_x_variant":[
        "\u7334\u5b50\u8111"
    ],
    "wof:name":"Houzinao",
    "wof:placetype":"locality"
},
  "geometry": {"coordinates":[114.50508000000001,28.56189],"type":"Point"}
}