{
  "type": "Feature",
  "properties": {
    "gn:admin1_code":"3.0",
    "gn:asciiname":"Fenggangcun",
    "gn:country_code":"CN",
    "gn:dem":21,
    "gn:feature_class":"P",
    "gn:feature_code":"PPL",
    "gn:name":"Fenggangcun",
    "gn:population":0,
    "gn:timezone":"Asia/Shanghai",
    "iso:country":"CN",
    "name:und_x_variant":[
        "\u51e4\u5c97\u6751"
    ],
    "wof:name":"Fenggangcun",
    "wof:placetype":"locality"
},
  "geometry": {"coordinates":[116.10406,28.49353],"type":"Point"}
}