{
  "type": "Feature",
  "properties": {
    "gn:admin1_code":"25",
    "gn:asciiname":"Pengjia",
    "gn:country_code":"CN",
    "gn:dem":12,
    "gn:feature_class":"P",
    "gn:feature_code":"PPL",
    "gn:name":"Pengjia",
    "gn:population":0,
    "gn:timezone":"Asia/Shanghai",
    "iso:country":"CN",
    "name:zho_x_preferred":[
        "\u5f6d\u5bb6"
    ],
    "wof:name":"Pengjia",
    "wof:placetype":"locality"
},
  "geometry": {"coordinates":[117.967,37.2118],"type":"Point"}
}