{
  "type": "Feature",
  "properties": {
    "gn:admin1_code":"25.0",
    "gn:asciiname":"Caozhuangcun",
    "gn:country_code":"CN",
    "gn:dem":34,
    "gn:feature_class":"P",
    "gn:feature_code":"PPL",
    "gn:name":"Caozhuangcun",
    "gn:population":0,
    "gn:timezone":"Asia/Shanghai",
    "iso:country":"CN",
    "name:zho_x_preferred":[
        "\u66f9\u5e84\u6751"
    ],
    "wof:name":"Caozhuangcun",
    "wof:placetype":"locality"
},
  "geometry": {"coordinates":[115.89696000000001,36.9536],"type":"Point"}
}