{
  "type": "Feature",
  "properties": {
    "gn:admin1_code":"1.0",
    "gn:asciiname":"Xinhuacun",
    "gn:country_code":"CN",
    "gn:dem":25,
    "gn:feature_class":"P",
    "gn:feature_code":"PPL",
    "gn:name":"Xinhuacun",
    "gn:population":0,
    "gn:timezone":"Asia/Shanghai",
    "iso:country":"CN",
    "name:zho_x_preferred":[
        "\u65b0\u5316\u6751"
    ],
    "wof:name":"Xinhuacun",
    "wof:placetype":"locality"
},
  "geometry": {"coordinates":[117.22188,31.00438],"type":"Point"}
}