{
  "type": "Feature",
  "properties": {
    "gn:admin1_code":"14.0",
    "gn:asciiname":"Zazhong",
    "gn:country_code":"CN",
    "gn:dem":3741,
    "gn:feature_class":"P",
    "gn:feature_code":"PPL",
    "gn:name":"Zazhong",
    "gn:population":0,
    "gn:timezone":"Asia/Urumqi",
    "iso:country":"CN",
    "name:bod_x_preferred":[
        "Zazhong"
    ],
    "name:zho_x_preferred":[
        "Zhazhong"
    ],
    "name:zho_x_variant":[
        "\u624e\u4e2d"
    ],
    "wof:name":"Zazhong",
    "wof:placetype":"locality"
},
  "geometry": {"coordinates":[96.80200000000001,31.102],"type":"Point"}
}