{
  "type": "Feature",
  "properties": {
    "gn:admin1_code":"2.0",
    "gn:asciiname":"Machuan",
    "gn:country_code":"CN",
    "gn:dem":560,
    "gn:feature_class":"P",
    "gn:feature_code":"PPL",
    "gn:name":"Machuan",
    "gn:population":0,
    "gn:timezone":"Asia/Shanghai",
    "iso:country":"CN",
    "name:und_x_variant":[
        "\u9a6c\u5ddd"
    ],
    "wof:name":"Machuan",
    "wof:placetype":"locality"
},
  "geometry": {"coordinates":[118.99199,30.32691],"type":"Point"}
}