{
  "type": "Feature",
  "properties": {
    "gn:admin1_code":"29",
    "gn:asciiname":"Wafang",
    "gn:country_code":"CN",
    "gn:dem":1973,
    "gn:feature_class":"P",
    "gn:feature_code":"PPL",
    "gn:name":"Wafang",
    "gn:population":0,
    "gn:timezone":"Asia/Shanghai",
    "iso:country":"CN",
    "wof:name":"Wafang",
    "wof:placetype":"locality"
},
  "geometry": {"coordinates":[101.27388999999999,25.81222],"type":"Point"}
}