{
  "type": "Feature",
  "properties": {
    "gn:admin1_code":"13.0",
    "gn:asciiname":"Nagereqialedi",
    "gn:country_code":"CN",
    "gn:dem":1223,
    "gn:feature_class":"P",
    "gn:feature_code":"PPL",
    "gn:name":"Nagereqialedi",
    "gn:population":0,
    "gn:timezone":"Asia/Shanghai",
    "iso:country":"CN",
    "name:zho_x_preferred":[
        "\u7eb3\u683c\u70ed\u6070\u52d2\u8fea"
    ],
    "wof:name":"Nagereqialedi",
    "wof:placetype":"locality"
},
  "geometry": {"coordinates":[76.54829000000002,39.15957],"type":"Point"}
}