{
  "type": "Feature",
  "properties": {
    "gn:admin1_code":"7",
    "gn:asciiname":"Shangfengshan",
    "gn:country_code":"CN",
    "gn:dem":826,
    "gn:feature_class":"P",
    "gn:feature_code":"PPL",
    "gn:name":"Shangfengshan",
    "gn:population":0,
    "gn:timezone":"Asia/Shanghai",
    "iso:country":"CN",
    "wof:name":"Shangfengshan",
    "wof:placetype":"locality"
},
  "geometry": {"coordinates":[117.64111,25.62472],"type":"Point"}
}