{
  "type": "Feature",
  "properties": {
    "gn:admin1_code":"26.0",
    "gn:asciiname":"Youfanggou",
    "gn:country_code":"CN",
    "gn:dem":1963,
    "gn:feature_class":"P",
    "gn:feature_code":"PPL",
    "gn:name":"Youfanggou",
    "gn:population":0,
    "gn:timezone":"Asia/Shanghai",
    "iso:country":"CN",
    "name:und_x_variant":[
        "\u6cb9\u623f\u6c9f"
    ],
    "wof:name":"Youfanggou",
    "wof:placetype":"locality"
},
  "geometry": {"coordinates":[106.77909,33.4166],"type":"Point"}
}