{
  "type": "Feature",
  "properties": {
    "gn:admin1_code":"33.0",
    "gn:asciiname":"Yanwan",
    "gn:country_code":"CN",
    "gn:dem":803,
    "gn:feature_class":"P",
    "gn:feature_code":"PPLA4",
    "gn:name":"Yanwan",
    "gn:population":0,
    "gn:timezone":"Asia/Shanghai",
    "iso:country":"CN",
    "name:und_x_variant":[
        "Yanwan Xiang",
        "Congmuling"
    ],
    "name:zho_x_preferred":[
        "\u5ca9\u6e7e"
    ],
    "name:zho_x_variant":[
        "\u5ca9\u6e7e\u4e61",
        "\u4e1b\u6728\u5cad"
    ],
    "wof:name":"Yanwan",
    "wof:placetype":"locality"
},
  "geometry": {"coordinates":[109.5301,31.1957],"type":"Point"}
}