{
  "type": "Feature",
  "properties": {
    "gn:admin1_code":"26.0",
    "gn:asciiname":"Yanyaobian",
    "gn:country_code":"CN",
    "gn:dem":1080,
    "gn:feature_class":"P",
    "gn:feature_code":"PPL",
    "gn:name":"Yanyaobian",
    "gn:population":0,
    "gn:timezone":"Asia/Shanghai",
    "iso:country":"CN",
    "name:und_x_variant":[
        "Yen-yao-pien",
        "Yanyaobian"
    ],
    "wof:name":"Yanyaobian",
    "wof:placetype":"locality"
},
  "geometry": {"coordinates":[108.91694,35.92083],"type":"Point"}
}