{
  "type": "Feature",
  "properties": {
    "gn:admin1_code":"15.0",
    "gn:asciiname":"Shangsuoluo",
    "gn:country_code":"CN",
    "gn:dem":1019,
    "gn:feature_class":"P",
    "gn:feature_code":"PPL",
    "gn:name":"Shangsuoluo",
    "gn:population":0,
    "gn:timezone":"Asia/Shanghai",
    "iso:country":"CN",
    "name:und_x_variant":[
        "\u4e0a\u5a11\u7f57"
    ],
    "wof:name":"Shangsuoluo",
    "wof:placetype":"locality"
},
  "geometry": {"coordinates":[105.64376,33.70746],"type":"Point"}
}