{
  "type": "Feature",
  "properties": {
    "gn:admin1_code":"15.0",
    "gn:asciiname":"Yubaijia",
    "gn:country_code":"CN",
    "gn:dem":1962,
    "gn:feature_class":"P",
    "gn:feature_code":"PPL",
    "gn:name":"Yubaijia",
    "gn:population":0,
    "gn:timezone":"Asia/Shanghai",
    "iso:country":"CN",
    "name:zho_x_preferred":[
        "\u4fde\u767d\u5bb6"
    ],
    "wof:name":"Yubaijia",
    "wof:placetype":"locality"
},
  "geometry": {"coordinates":[102.95399999999999,36.3827],"type":"Point"}
}