{
  "type": "Feature",
  "properties": {
    "gn:admin1_code":"5.0",
    "gn:asciiname":"Kanchuangoucun",
    "gn:country_code":"CN",
    "gn:dem":360,
    "gn:feature_class":"P",
    "gn:feature_code":"PPL",
    "gn:name":"Kanchuangoucun",
    "gn:population":0,
    "gn:timezone":"Asia/Shanghai",
    "iso:country":"CN",
    "name:zho_x_preferred":[
        "\u780d\u693d\u6c9f\u6751"
    ],
    "wof:name":"Kanchuangoucun",
    "wof:placetype":"locality"
},
  "geometry": {"coordinates":[126.47947000000001,43.17752],"type":"Point"}
}