{
  "type": "Feature",
  "properties": {
    "gn:admin1_code":"14.0",
    "gn:asciiname":"Mabja",
    "gn:country_code":"CN",
    "gn:dem":4101,
    "gn:feature_class":"P",
    "gn:feature_code":"PPL",
    "gn:name":"Mabja",
    "gn:population":0,
    "gn:timezone":"Asia/Urumqi",
    "iso:country":"CN",
    "name:bod_x_preferred":[
        "Mabja"
    ],
    "name:zho_x_preferred":[
        "Maya"
    ],
    "name:zho_x_variant":[
        "\u9a6c\u4e9a",
        "Wuxing Gongshe",
        "\u4e94\u661f\u516c\u793e"
    ],
    "wof:name":"Mabja",
    "wof:placetype":"locality"
},
  "geometry": {"coordinates":[89.40100000000002,29.101],"type":"Point"}
}