{
  "type": "Feature",
  "properties": {
    "gn:admin1_code":"26",
    "gn:asciiname":"Hezhuangping",
    "gn:cc2":"CN",
    "gn:country_code":"CN",
    "gn:dem":987,
    "gn:feature_class":"P",
    "gn:feature_code":"PPL",
    "gn:name":"Hezhuangping",
    "gn:population":0,
    "gn:timezone":"Asia/Shanghai",
    "iso:country":"CN",
    "name:und_x_variant":[
        "Ho-chuang-p\u2019ing",
        "Hezhuangping"
    ],
    "wof:name":"Hezhuangping",
    "wof:placetype":"locality"
},
  "geometry": {"coordinates":[109.43333,36.66667],"type":"Point"}
}