{
  "type": "Feature",
  "properties": {
    "gn:admin1_code":"29.0",
    "gn:asciiname":"Chengfeng",
    "gn:country_code":"CN",
    "gn:dem":479,
    "gn:feature_class":"P",
    "gn:feature_code":"PPL",
    "gn:name":"Chengfeng",
    "gn:population":0,
    "gn:timezone":"Asia/Shanghai",
    "iso:country":"CN",
    "name:und_x_variant":[
        "\u6210\u51e4"
    ],
    "wof:name":"Chengfeng",
    "wof:placetype":"locality"
},
  "geometry": {"coordinates":[104.24429000000001,28.39474],"type":"Point"}
}