{
  "type": "Feature",
  "properties": {
    "gn:admin1_code":"7.0",
    "gn:asciiname":"Duiyang",
    "gn:country_code":"CN",
    "gn:dem":699,
    "gn:feature_class":"P",
    "gn:feature_code":"PPL",
    "gn:name":"Duiyang",
    "gn:population":0,
    "gn:timezone":"Asia/Shanghai",
    "iso:country":"CN",
    "name:zho_x_preferred":[
        "\u5806\u6d0b"
    ],
    "wof:name":"Duiyang",
    "wof:placetype":"locality"
},
  "geometry": {"coordinates":[117.88919,26.16046],"type":"Point"}
}