{
  "type": "Feature",
  "properties": {
    "gn:admin1_code":"06",
    "gn:asciiname":"Moduo",
    "gn:country_code":"CN",
    "gn:dem":2831,
    "gn:feature_class":"P",
    "gn:feature_code":"PPL",
    "gn:name":"Moduo",
    "gn:population":0,
    "gn:timezone":"Asia/Shanghai",
    "iso:country":"CN",
    "name:und_x_variant":[
        "Maoduo",
        "\u6bdb\u591a"
    ],
    "name:zho_x_preferred":[
        "\u83ab\u591a"
    ],
    "wof:name":"Moduo",
    "wof:placetype":"locality"
},
  "geometry": {"coordinates":[100.13308000000001,35.32553],"type":"Point"}
}