{
  "type": "Feature",
  "properties": {
    "gn:admin1_code":"18.0",
    "gn:asciiname":"Bingxi",
    "gn:country_code":"CN",
    "gn:dem":675,
    "gn:feature_class":"P",
    "gn:feature_code":"PPL",
    "gn:name":"Bingxi",
    "gn:population":0,
    "gn:timezone":"Asia/Shanghai",
    "iso:country":"CN",
    "name:zho_x_preferred":[
        "\u51b0\u6eaa"
    ],
    "wof:name":"Bingxi",
    "wof:placetype":"locality"
},
  "geometry": {"coordinates":[108.429,26.864],"type":"Point"}
}