{
  "type": "Feature",
  "properties": {
    "gn:admin1_code":"11.0",
    "gn:asciiname":"Yanziwan",
    "gn:country_code":"CN",
    "gn:dem":443,
    "gn:feature_class":"P",
    "gn:feature_code":"PPL",
    "gn:name":"Yanziwan",
    "gn:population":0,
    "gn:timezone":"Asia/Shanghai",
    "iso:country":"CN",
    "name:zho_x_preferred":[
        "\u71d5\u5b50\u6e7e"
    ],
    "wof:name":"Yanziwan",
    "wof:placetype":"locality"
},
  "geometry": {"coordinates":[109.50601,26.37434],"type":"Point"}
}