{
  "type": "Feature",
  "properties": {
    "gn:admin1_code":"30.0",
    "gn:asciiname":"Niuwei",
    "gn:country_code":"CN",
    "gn:dem":22,
    "gn:feature_class":"P",
    "gn:feature_code":"PPL",
    "gn:name":"Niuwei",
    "gn:population":0,
    "gn:timezone":"Asia/Shanghai",
    "iso:country":"CN",
    "name:zho_x_preferred":[
        "\u725b\u56f4"
    ],
    "wof:name":"Niuwei",
    "wof:placetype":"locality"
},
  "geometry": {"coordinates":[112.40206999999999,22.89653],"type":"Point"}
}