{
  "type": "Feature",
  "properties": {
    "gn:admin1_code":"2.0",
    "gn:asciiname":"Shilangjiao",
    "gn:country_code":"CN",
    "gn:dem":444,
    "gn:feature_class":"P",
    "gn:feature_code":"PPL",
    "gn:name":"Shilangjiao",
    "gn:population":0,
    "gn:timezone":"Asia/Shanghai",
    "iso:country":"CN",
    "name:zho_x_preferred":[
        "\u77f3\u6d6a\u811a"
    ],
    "wof:name":"Shilangjiao",
    "wof:placetype":"locality"
},
  "geometry": {"coordinates":[120.86018,29.09484],"type":"Point"}
}