{
  "type": "Feature",
  "properties": {
    "gn:admin1_code":"15.0",
    "gn:asciiname":"Xiaoyingpanshui",
    "gn:country_code":"CN",
    "gn:dem":1922,
    "gn:feature_class":"P",
    "gn:feature_code":"PPL",
    "gn:name":"Xiaoyingpanshui",
    "gn:population":0,
    "gn:timezone":"Asia/Shanghai",
    "iso:country":"CN",
    "name:zho_x_preferred":[
        "\u5c0f\u8425\u76d8\u6c34"
    ],
    "wof:name":"Xiaoyingpanshui",
    "wof:placetype":"locality"
},
  "geometry": {"coordinates":[103.904,37.3576],"type":"Point"}
}