{
  "type": "Feature",
  "properties": {
    "gn:admin1_code":"5.0",
    "gn:asciiname":"Yixingcun",
    "gn:country_code":"CN",
    "gn:dem":246,
    "gn:feature_class":"P",
    "gn:feature_code":"PPL",
    "gn:name":"Yixingcun",
    "gn:population":0,
    "gn:timezone":"Asia/Shanghai",
    "iso:country":"CN",
    "name:zho_x_preferred":[
        "\u76ca\u5174\u6751"
    ],
    "wof:name":"Yixingcun",
    "wof:placetype":"locality"
},
  "geometry": {"coordinates":[127.26714,44.35156],"type":"Point"}
}