{
  "type": "Feature",
  "properties": {
    "gn:admin1_code":"12.0",
    "gn:asciiname":"Baiguoyuan",
    "gn:country_code":"CN",
    "gn:dem":68,
    "gn:feature_class":"P",
    "gn:feature_code":"PPL",
    "gn:name":"Baiguoyuan",
    "gn:population":0,
    "gn:timezone":"Asia/Shanghai",
    "iso:country":"CN",
    "name:zho_x_preferred":[
        "\u767d\u679c\u56ed"
    ],
    "wof:name":"Baiguoyuan",
    "wof:placetype":"locality"
},
  "geometry": {"coordinates":[113.7848,31.35849],"type":"Point"}
}