{
  "type": "Feature",
  "properties": {
    "gn:admin1_code":"10",
    "gn:asciiname":"Dagou'e",
    "gn:country_code":"CN",
    "gn:dem":994,
    "gn:feature_class":"P",
    "gn:feature_code":"PPL",
    "gn:name":"Dagou\u2019e",
    "gn:population":0,
    "gn:timezone":"Asia/Shanghai",
    "iso:country":"CN",
    "name:und_x_variant":[
        "Ta-kou-o",
        "Dagou\u2019e"
    ],
    "wof:name":"Dagou'e",
    "wof:placetype":"locality"
},
  "geometry": {"coordinates":[114.58778,40.14194000000001],"type":"Point"}
}