{
  "type": "Feature",
  "properties": {
    "gn:admin1_code":"7.0",
    "gn:asciiname":"Chunleiyun",
    "gn:country_code":"CN",
    "gn:dem":112,
    "gn:feature_class":"P",
    "gn:feature_code":"PPL",
    "gn:name":"Chunleiyun",
    "gn:population":0,
    "gn:timezone":"Asia/Shanghai",
    "iso:country":"CN",
    "name:zho_x_preferred":[
        "\u6625\u96f7\u4e91"
    ],
    "wof:name":"Chunleiyun",
    "wof:placetype":"locality"
},
  "geometry": {"coordinates":[119.63827999999999,26.89162],"type":"Point"}
}