{
  "type": "Feature",
  "properties": {
    "gn:admin1_code":"4.0",
    "gn:asciiname":"Youyi Yizu",
    "gn:country_code":"CN",
    "gn:dem":3,
    "gn:feature_class":"P",
    "gn:feature_code":"PPL",
    "gn:name":"Youyi Yizu",
    "gn:population":0,
    "gn:timezone":"Asia/Shanghai",
    "iso:country":"CN",
    "name:zho_x_preferred":[
        "\u53cb\u8c0a\u4e00\u7ec4"
    ],
    "wof:name":"Youyi Yizu",
    "wof:placetype":"locality"
},
  "geometry": {"coordinates":[120.42716,32.65528],"type":"Point"}
}