{
  "type": "Feature",
  "properties": {
    "gn:admin1_code":"29.0",
    "gn:asciiname":"Heishitou",
    "gn:country_code":"CN",
    "gn:dem":2138,
    "gn:feature_class":"P",
    "gn:feature_code":"PPL",
    "gn:name":"Heishitou",
    "gn:population":0,
    "gn:timezone":"Asia/Shanghai",
    "iso:country":"CN",
    "name:zho_x_preferred":[
        "\u9ed1\u77f3\u5934"
    ],
    "wof:name":"Heishitou",
    "wof:placetype":"locality"
},
  "geometry": {"coordinates":[103.45699999999999,25.5567],"type":"Point"}
}