{
  "type": "Feature",
  "properties": {
    "gn:admin1_code":"26.0",
    "gn:asciiname":"Chentuangoucun",
    "gn:country_code":"CN",
    "gn:dem":1049,
    "gn:feature_class":"P",
    "gn:feature_code":"PPL",
    "gn:name":"Chentuangoucun",
    "gn:population":0,
    "gn:timezone":"Asia/Shanghai",
    "iso:country":"CN",
    "name:zho_x_preferred":[
        "\u9648\u56e2\u6c9f\u6751"
    ],
    "wof:name":"Chentuangoucun",
    "wof:placetype":"locality"
},
  "geometry": {"coordinates":[109.44897,36.67757],"type":"Point"}
}