{
  "type": "Feature",
  "properties": {
    "gn:admin1_code":"15.0",
    "gn:asciiname":"Liujiabu",
    "gn:country_code":"CN",
    "gn:dem":1127,
    "gn:feature_class":"P",
    "gn:feature_code":"PPL",
    "gn:name":"Liujiabu",
    "gn:population":0,
    "gn:timezone":"Asia/Urumqi",
    "iso:country":"CN",
    "name:zho_x_preferred":[
        "\u5218\u5bb6\u5821"
    ],
    "wof:name":"Liujiabu",
    "wof:placetype":"locality"
},
  "geometry": {"coordinates":[94.6692,40.1823],"type":"Point"}
}