{
  "type": "Feature",
  "properties": {
    "gn:admin1_code":"26.0",
    "gn:asciiname":"Guandimiao",
    "gn:country_code":"CN",
    "gn:dem":1239,
    "gn:feature_class":"P",
    "gn:feature_code":"PPL",
    "gn:name":"Guandimiao",
    "gn:population":0,
    "gn:timezone":"Asia/Shanghai",
    "iso:country":"CN",
    "name:und_x_variant":[
        "\u5173\u5e1d\u5e99"
    ],
    "wof:name":"Guandimiao",
    "wof:placetype":"locality"
},
  "geometry": {"coordinates":[107.49972,33.61707],"type":"Point"}
}