{
  "type": "Feature",
  "properties": {
    "gn:admin1_code":"20.0",
    "gn:asciiname":"Dongtai",
    "gn:country_code":"CN",
    "gn:dem":334,
    "gn:feature_class":"P",
    "gn:feature_code":"PPL",
    "gn:name":"Dongtai",
    "gn:population":0,
    "gn:timezone":"Asia/Shanghai",
    "iso:country":"CN",
    "name:zho_x_preferred":[
        "\u4e1c\u6cf0"
    ],
    "wof:name":"Dongtai",
    "wof:placetype":"locality"
},
  "geometry": {"coordinates":[122.59444000000001,47.55549],"type":"Point"}
}