{
  "type": "Feature",
  "properties": {
    "gn:admin1_code":"15.0",
    "gn:asciiname":"Hadiha",
    "gn:country_code":"CN",
    "gn:dem":2486,
    "gn:feature_class":"P",
    "gn:feature_code":"PPL",
    "gn:name":"Hadiha",
    "gn:population":0,
    "gn:timezone":"Asia/Shanghai",
    "iso:country":"CN",
    "name:und_x_variant":[
        "\u54c8\u5730\u54c8"
    ],
    "wof:name":"Hadiha",
    "wof:placetype":"locality"
},
  "geometry": {"coordinates":[104.1992,34.46719],"type":"Point"}
}