{
  "type": "Feature",
  "properties": {
    "gn:admin1_code":"24",
    "gn:asciiname":"Kaihuacun",
    "gn:country_code":"CN",
    "gn:dem":1042,
    "gn:feature_class":"P",
    "gn:feature_code":"PPL",
    "gn:name":"Kaihuacun",
    "gn:population":0,
    "gn:timezone":"Asia/Shanghai",
    "iso:country":"CN",
    "name:und_x_variant":[
        "Ho-ti-ts\u2019un",
        "Kaihua",
        "Kaihuacun"
    ],
    "name:zho_x_preferred":[
        "\u5f00\u5316\u6751"
    ],
    "wof:name":"Kaihuacun",
    "wof:placetype":"locality"
},
  "geometry": {"coordinates":[110.71256,38.1473],"type":"Point"}
}