{
  "type": "Feature",
  "properties": {
    "gn:admin1_code":"3.0",
    "gn:asciiname":"Jianchong",
    "gn:country_code":"CN",
    "gn:dem":253,
    "gn:feature_class":"P",
    "gn:feature_code":"PPL",
    "gn:name":"Jianchong",
    "gn:population":0,
    "gn:timezone":"Asia/Shanghai",
    "iso:country":"CN",
    "name:und_x_variant":[
        "\u67a7\u51b2"
    ],
    "wof:name":"Jianchong",
    "wof:placetype":"locality"
},
  "geometry": {"coordinates":[114.16069,27.65726],"type":"Point"}
}