{
  "type": "Feature",
  "properties": {
    "gn:admin1_code":"14.0",
    "gn:asciiname":"Cuo'aka",
    "gn:country_code":"CN",
    "gn:dem":4283,
    "gn:feature_class":"P",
    "gn:feature_code":"PPL",
    "gn:name":"Cuo\u2019aka",
    "gn:population":0,
    "gn:timezone":"Asia/Urumqi",
    "iso:country":"CN",
    "name:und_x_variant":[
        "Cuo\u2019aka"
    ],
    "name:zho_x_preferred":[
        "\u9519\u963f\u5361"
    ],
    "wof:name":"Cuo'aka",
    "wof:placetype":"locality"
},
  "geometry": {"coordinates":[94.49075000000001,31.20461],"type":"Point"}
}