{
  "type": "Feature",
  "properties": {
    "gn:admin1_code":"8.0",
    "gn:asciiname":"Zhenghuangcun",
    "gn:country_code":"CN",
    "gn:dem":192,
    "gn:feature_class":"P",
    "gn:feature_code":"PPL",
    "gn:name":"Zhenghuangcun",
    "gn:population":0,
    "gn:timezone":"Asia/Shanghai",
    "iso:country":"CN",
    "name:zho_x_preferred":[
        "\u6b63\u9ec4\u6751"
    ],
    "wof:name":"Zhenghuangcun",
    "wof:placetype":"locality"
},
  "geometry": {"coordinates":[126.81489999999999,45.36054],"type":"Point"}
}