{
  "type": "Feature",
  "properties": {
    "gn:admin1_code":"30.0",
    "gn:asciiname":"Guoxingcun",
    "gn:country_code":"CN",
    "gn:dem":86,
    "gn:feature_class":"P",
    "gn:feature_code":"PPL",
    "gn:name":"Guoxingcun",
    "gn:population":0,
    "gn:timezone":"Asia/Shanghai",
    "iso:country":"CN",
    "name:zho_x_preferred":[
        "\u9505\u5f62\u6751"
    ],
    "wof:name":"Guoxingcun",
    "wof:placetype":"locality"
},
  "geometry": {"coordinates":[116.10431,24.29301],"type":"Point"}
}