{
  "type": "Feature",
  "properties": {
    "gn:admin1_code":"18.0",
    "gn:asciiname":"Pipazhai",
    "gn:country_code":"CN",
    "gn:dem":871,
    "gn:feature_class":"P",
    "gn:feature_code":"PPL",
    "gn:name":"Pipazhai",
    "gn:population":0,
    "gn:timezone":"Asia/Shanghai",
    "iso:country":"CN",
    "name:zho_x_preferred":[
        "\u7435\u7436\u5be8"
    ],
    "wof:name":"Pipazhai",
    "wof:placetype":"locality"
},
  "geometry": {"coordinates":[108.377,26.9208],"type":"Point"}
}