{
  "type": "Feature",
  "properties": {
    "gn:admin1_code":"5.0",
    "gn:asciiname":"Dongxinlitun",
    "gn:country_code":"CN",
    "gn:dem":684,
    "gn:feature_class":"P",
    "gn:feature_code":"PPL",
    "gn:name":"Dongxinlitun",
    "gn:population":0,
    "gn:timezone":"Asia/Shanghai",
    "iso:country":"CN",
    "name:zho_x_preferred":[
        "\u4e1c\u65b0\u7acb\u5c6f"
    ],
    "wof:name":"Dongxinlitun",
    "wof:placetype":"locality"
},
  "geometry": {"coordinates":[126.83262999999999,42.34393],"type":"Point"}
}