{
  "type": "Feature",
  "properties": {
    "gn:admin1_code":"18",
    "gn:asciiname":"Hetoushang",
    "gn:country_code":"CN",
    "gn:dem":1529,
    "gn:feature_class":"P",
    "gn:feature_code":"PPL",
    "gn:name":"Hetoushang",
    "gn:population":0,
    "gn:timezone":"Asia/Shanghai",
    "iso:country":"CN",
    "name:zho_x_preferred":[
        "\u6cb3\u5934\u4e0a"
    ],
    "wof:name":"Hetoushang",
    "wof:placetype":"locality"
},
  "geometry": {"coordinates":[105.87,26.4795],"type":"Point"}
}