{
  "type": "Feature",
  "properties": {
    "gn:admin1_code":"30",
    "gn:asciiname":"Liangtang",
    "gn:country_code":"CN",
    "gn:dem":153,
    "gn:feature_class":"P",
    "gn:feature_code":"PPL",
    "gn:name":"Liangtang",
    "gn:population":0,
    "gn:timezone":"Asia/Urumqi",
    "iso:country":"CN",
    "name:zho_x_preferred":[
        "\u826f\u5858"
    ],
    "wof:name":"Liangtang",
    "wof:placetype":"locality"
},
  "geometry": {"coordinates":[110.75814,22.271],"type":"Point"}
}