{
  "type": "Feature",
  "properties": {
    "gn:admin1_code":"29.0",
    "gn:asciiname":"Shangwenqu",
    "gn:country_code":"CN",
    "gn:dem":2169,
    "gn:feature_class":"P",
    "gn:feature_code":"PPL",
    "gn:name":"Shangwenqu",
    "gn:population":0,
    "gn:timezone":"Asia/Shanghai",
    "iso:country":"CN",
    "name:zho_x_preferred":[
        "\u4e0a\u6587\u66f2"
    ],
    "wof:name":"Shangwenqu",
    "wof:placetype":"locality"
},
  "geometry": {"coordinates":[99.9811,26.2725],"type":"Point"}
}