{
  "type": "Feature",
  "properties": {
    "gn:admin1_code":"14.0",
    "gn:asciiname":"Danacun",
    "gn:country_code":"CN",
    "gn:dem":3879,
    "gn:feature_class":"P",
    "gn:feature_code":"PPL",
    "gn:name":"Danacun",
    "gn:population":0,
    "gn:timezone":"Asia/Urumqi",
    "iso:country":"CN",
    "name:zho_x_preferred":[
        "\u8fbe\u90a3\u6751"
    ],
    "wof:name":"Danacun",
    "wof:placetype":"locality"
},
  "geometry": {"coordinates":[96.92614,31.70435],"type":"Point"}
}