{
  "type": "Feature",
  "properties": {
    "gn:admin1_code":"18",
    "gn:asciiname":"Zhongheba",
    "gn:country_code":"CN",
    "gn:dem":1967,
    "gn:feature_class":"P",
    "gn:feature_code":"PPL",
    "gn:name":"Zhongheba",
    "gn:population":0,
    "gn:timezone":"Asia/Shanghai",
    "iso:country":"CN",
    "name:zho_x_preferred":[
        "\u4e2d\u6cb3\u575d"
    ],
    "wof:name":"Zhongheba",
    "wof:placetype":"locality"
},
  "geometry": {"coordinates":[104.437,27.4094],"type":"Point"}
}