{
  "type": "Feature",
  "properties": {
    "gn:admin1_code":"30.0",
    "gn:asciiname":"Pengdongcun",
    "gn:country_code":"CN",
    "gn:dem":12,
    "gn:feature_class":"P",
    "gn:feature_code":"PPL",
    "gn:name":"Pengdongcun",
    "gn:population":0,
    "gn:timezone":"Asia/Shanghai",
    "iso:country":"CN",
    "name:zho_x_preferred":[
        "\u84ec\u6d1e\u6751"
    ],
    "wof:name":"Pengdongcun",
    "wof:placetype":"locality"
},
  "geometry": {"coordinates":[116.70296999999999,23.565],"type":"Point"}
}