{
  "type": "Feature",
  "properties": {
    "gn:admin1_code":"2.0",
    "gn:asciiname":"Chanzhi",
    "gn:country_code":"CN",
    "gn:dem":243,
    "gn:feature_class":"P",
    "gn:feature_code":"PPL",
    "gn:name":"Chanzhi",
    "gn:population":0,
    "gn:timezone":"Asia/Shanghai",
    "iso:country":"CN",
    "name:zho_x_preferred":[
        "\u4ea7\u829d"
    ],
    "wof:name":"Chanzhi",
    "wof:placetype":"locality"
},
  "geometry": {"coordinates":[120.84748,29.44094],"type":"Point"}
}