{
  "type": "Feature",
  "properties": {
    "gn:admin1_code":"26.0",
    "gn:asciiname":"Huangzhoukui",
    "gn:country_code":"CN",
    "gn:dem":259,
    "gn:feature_class":"P",
    "gn:feature_code":"PPL",
    "gn:name":"Huangzhoukui",
    "gn:population":0,
    "gn:timezone":"Asia/Shanghai",
    "iso:country":"CN",
    "name:zho_x_preferred":[
        "\u9ec4\u6d32\u594e"
    ],
    "wof:name":"Huangzhoukui",
    "wof:placetype":"locality"
},
  "geometry": {"coordinates":[110.88124999999999,33.34370999999999],"type":"Point"}
}