{
  "type": "Feature",
  "properties": {
    "gn:admin1_code":"32.0",
    "gn:asciiname":"Wenchanggong",
    "gn:country_code":"CN",
    "gn:dem":378,
    "gn:feature_class":"P",
    "gn:feature_code":"PPL",
    "gn:name":"Wenchanggong",
    "gn:population":0,
    "gn:timezone":"Asia/Shanghai",
    "iso:country":"CN",
    "name:zho_x_preferred":[
        "\u6587\u660c\u5bab"
    ],
    "wof:name":"Wenchanggong",
    "wof:placetype":"locality"
},
  "geometry": {"coordinates":[107.051,31.2528],"type":"Point"}
}