{
  "type": "Feature",
  "properties": {
    "gn:admin1_code":"3.0",
    "gn:asciiname":"Yingyuan",
    "gn:country_code":"CN",
    "gn:dem":204,
    "gn:feature_class":"P",
    "gn:feature_code":"PPL",
    "gn:name":"Yingyuan",
    "gn:population":0,
    "gn:timezone":"Asia/Shanghai",
    "iso:country":"CN",
    "name:und_x_variant":[
        "\u76c8\u6e90"
    ],
    "wof:name":"Yingyuan",
    "wof:placetype":"locality"
},
  "geometry": {"coordinates":[115.16058999999998,26.21161],"type":"Point"}
}