{
  "type": "Feature",
  "properties": {
    "gn:admin1_code":"19.0",
    "gn:asciiname":"Qianlinzi",
    "gn:country_code":"CN",
    "gn:dem":19,
    "gn:feature_class":"P",
    "gn:feature_code":"PPL",
    "gn:name":"Qianlinzi",
    "gn:population":0,
    "gn:timezone":"Asia/Shanghai",
    "iso:country":"CN",
    "name:und_x_variant":[
        "\u524d\u6797\u5b50"
    ],
    "wof:name":"Qianlinzi",
    "wof:placetype":"locality"
},
  "geometry": {"coordinates":[122.50660000000001,40.68411],"type":"Point"}
}