{
  "type": "Feature",
  "properties": {
    "gn:admin1_code":"14.0",
    "gn:asciiname":"Guodianguo",
    "gn:country_code":"CN",
    "gn:dem":4614,
    "gn:feature_class":"P",
    "gn:feature_code":"PPL",
    "gn:name":"Guodianguo",
    "gn:population":0,
    "gn:timezone":"Asia/Shanghai",
    "iso:country":"CN",
    "name:bod_x_preferred":[
        "God\u00eango"
    ],
    "name:und_x_variant":[
        "Bacuo Gongshe",
        "Guodianguocun"
    ],
    "name:zho_x_preferred":[
        "\u679c\u70b9\u679c"
    ],
    "name:zho_x_variant":[
        "\u5df4\u63aa\u516c\u793e",
        "\u679c\u70b9\u679c\u6751"
    ],
    "wof:name":"Guodianguo",
    "wof:placetype":"locality"
},
  "geometry": {"coordinates":[82.4166,32.1669],"type":"Point"}
}