{
  "type": "Feature",
  "properties": {
    "gn:admin1_code":"1.0",
    "gn:asciiname":"Kanhecun",
    "gn:country_code":"CN",
    "gn:dem":31,
    "gn:feature_class":"P",
    "gn:feature_code":"PPL",
    "gn:name":"Kanhecun",
    "gn:population":0,
    "gn:timezone":"Asia/Shanghai",
    "iso:country":"CN",
    "name:zho_x_preferred":[
        "\u574e\u6cb3\u6751"
    ],
    "wof:name":"Kanhecun",
    "wof:placetype":"locality"
},
  "geometry": {"coordinates":[115.72886,32.94993],"type":"Point"}
}