{
  "type": "Feature",
  "properties": {
    "gn:admin1_code":"15.0",
    "gn:asciiname":"Wangjia Yangshan",
    "gn:country_code":"CN",
    "gn:dem":2373,
    "gn:feature_class":"P",
    "gn:feature_code":"PPL",
    "gn:name":"Wangjia Yangshan",
    "gn:population":0,
    "gn:timezone":"Asia/Shanghai",
    "iso:country":"CN",
    "name:zho_x_preferred":[
        "\u6c6a\u5bb6\u9633\u5c71"
    ],
    "wof:name":"Wangjia Yangshan",
    "wof:placetype":"locality"
},
  "geometry": {"coordinates":[104.465,35.328],"type":"Point"}
}