{
  "type": "Feature",
  "properties": {
    "gn:admin1_code":"29.0",
    "gn:asciiname":"Pingzhang",
    "gn:country_code":"CN",
    "gn:dem":1815,
    "gn:feature_class":"P",
    "gn:feature_code":"PPL",
    "gn:name":"Pingzhang",
    "gn:population":0,
    "gn:timezone":"Asia/Shanghai",
    "iso:country":"CN",
    "name:zho_x_preferred":[
        "\u5e73\u638c"
    ],
    "wof:name":"Pingzhang",
    "wof:placetype":"locality"
},
  "geometry": {"coordinates":[100.873,24.1353],"type":"Point"}
}