{
  "type": "Feature",
  "properties": {
    "gn:admin1_code":"8.0",
    "gn:asciiname":"Baoquanling Shiliudui",
    "gn:country_code":"CN",
    "gn:dem":117,
    "gn:feature_class":"P",
    "gn:feature_code":"PPLF",
    "gn:name":"Baoquanling Shiliudui",
    "gn:population":0,
    "gn:timezone":"Asia/Shanghai",
    "iso:country":"CN",
    "name:zho_x_preferred":[
        "\u5b9d\u6cc9\u5cad\u5341\u516d\u961f"
    ],
    "wof:name":"Baoquanling Shiliudui",
    "wof:placetype":"locality"
},
  "geometry": {"coordinates":[130.48974999999999,47.59873],"type":"Point"}
}