{
  "type": "Feature",
  "properties": {
    "gn:admin1_code":"32.0",
    "gn:asciiname":"Wenzhenguan",
    "gn:cc2":"CN",
    "gn:country_code":"CN",
    "gn:dem":1421,
    "gn:feature_class":"P",
    "gn:feature_code":"PPL",
    "gn:name":"Wenzhenguan",
    "gn:population":0,
    "gn:timezone":"Asia/Shanghai",
    "iso:country":"CN",
    "name:und_x_variant":[
        "Wen-chen-kuan",
        "Wenzhenguan"
    ],
    "wof:name":"Wenzhenguan",
    "wof:placetype":"locality"
},
  "geometry": {"coordinates":[103.68333,31.53333],"type":"Point"}
}