{
  "type": "Feature",
  "properties": {
    "iso:country":"CN",
    "name:bar_x_preferred":[
        "Xiangtan"
    ],
    "name:ceb_x_preferred":[
        "Xiangtan Xian"
    ],
    "name:deu_x_preferred":[
        "Xiangtan"
    ],
    "name:eng_x_preferred":[
        "Xiangtan County"
    ],
    "name:fas_x_preferred":[
        "\u0634\u0647\u0631\u0633\u062a\u0627\u0646 \u0634\u06cc\u0627\u0646\u06af\u062a\u0627\u0646"
    ],
    "name:gan_x_preferred":[
        "\u6e58\u6f6d\u53bf"
    ],
    "name:hak_x_preferred":[
        "Siong-th\u00e2m-yen"
    ],
    "name:jpn_x_preferred":[
        "\u6e58\u6f6d\u770c"
    ],
    "name:kor_x_preferred":[
        "\uc0f9\ud0c4\ud604"
    ],
    "name:nan_x_preferred":[
        "Siong-th\u00e2m-ko\u0101n"
    ],
    "name:nld_x_preferred":[
        "Xiangtan"
    ],
    "name:nob_x_preferred":[
        "Xiangtan"
    ],
    "name:slv_x_preferred":[
        "Xiangtan"
    ],
    "name:swe_x_preferred":[
        "Xiangtan"
    ],
    "name:vie_x_preferred":[
        "T\u01b0\u01a1ng \u0110\u00e0m"
    ],
    "name:wuu_x_preferred":[
        "\u6e58\u6f6d\u53bf"
    ],
    "name:yue_x_preferred":[
        "\u6e58\u6f6d"
    ],
    "name:zho_x_preferred":[
        "\u6e58\u6f6d\u53bf"
    ],
    "qs:name":"\u6e58\u6f6d\u53bf",
    "qs:name_adm0":"\u4e2d\u570b",
    "qs:name_adm1":"\u6e56\u5357\u7701",
    "qs:photos":7,
    "qs:photos_1k":1,
    "qs:photos_9k":1,
    "qs:photos_9r":3,
    "qs:photos_all":103,
    "qs:photos_sr":1,
    "qs:placetype":"LocalAdmin",
    "qs:pop_sr":"0",
    "wd:wordcount":28,
    "wof:name":"\u6e58\u6f6d\u53bf",
    "wof:placetype":"localadmin"
},
  "geometry": {"coordinates":[112.891902,27.861842],"type":"Point"}
}