{
  "type": "Feature",
  "properties": {
    "iso:country":"CN",
    "qs:name":"\u6e58\u6f6d\u53bf",
    "qs:name_adm0":"\u4e2d\u570b",
    "qs:name_adm1":"\u6e56\u5357\u7701",
    "qs:photos":7,
    "qs:photos_1k":1,
    "qs:photos_9k":1,
    "qs:photos_9r":3,
    "qs:photos_all":103,
    "qs:photos_sr":1,
    "qs:placetype":"LocalAdmin",
    "qs:pop_sr":"0",
    "wd:wordcount":28,
    "wof:name":"\u6e58\u6f6d\u53bf",
    "wof:placetype":"localadmin"
},
  "geometry": {"coordinates":[112.891902,27.861842],"type":"Point"}
}