{
  "type": "Feature",
  "properties": {
    "gn:admin1_code":"10",
    "gn:asciiname":"Liubaizhi",
    "gn:country_code":"CN",
    "gn:dem":330,
    "gn:feature_class":"P",
    "gn:feature_code":"PPL",
    "gn:name":"Liubaizhi",
    "gn:population":0,
    "gn:timezone":"Asia/Shanghai",
    "iso:country":"CN",
    "name:zho_x_preferred":[
        "\u5218\u767d\u82b7"
    ],
    "wof:name":"Liubaizhi",
    "wof:placetype":"locality"
},
  "geometry": {"coordinates":[114.255,37.3765],"type":"Point"}
}