{
  "type": "Feature",
  "properties": {
    "gn:admin1_code":"19.0",
    "gn:asciiname":"Lousha",
    "gn:country_code":"CN",
    "gn:dem":30,
    "gn:feature_class":"P",
    "gn:feature_code":"PPL",
    "gn:name":"Lousha",
    "gn:population":0,
    "gn:timezone":"Asia/Shanghai",
    "iso:country":"CN",
    "name:zho_x_preferred":[
        "\u6f0f\u6c99"
    ],
    "wof:name":"Lousha",
    "wof:placetype":"locality"
},
  "geometry": {"coordinates":[123.27383,39.70016],"type":"Point"}
}