{
  "type": "Feature",
  "properties": {
    "gn:admin1_code":"7.0",
    "gn:asciiname":"Julin",
    "gn:country_code":"CN",
    "gn:dem":293,
    "gn:feature_class":"P",
    "gn:feature_code":"PPL",
    "gn:name":"Julin",
    "gn:population":0,
    "gn:timezone":"Asia/Shanghai",
    "iso:country":"CN",
    "name:deu_x_preferred":[
        "Julin"
    ],
    "name:fin_x_preferred":[
        "Julin"
    ],
    "name:pol_x_preferred":[
        "Julin"
    ],
    "name:rus_x_preferred":[
        "\u042e\u043b\u0438\u043d"
    ],
    "name:zho_x_preferred":[
        "\u6854\u6797"
    ],
    "wof:name":"Julin",
    "wof:placetype":"locality"
},
  "geometry": {"coordinates":[118.77889,26.39219000000001],"type":"Point"}
}