{
  "type": "Feature",
  "properties": {
    "gn:admin1_code":"12.0",
    "gn:asciiname":"Yanzhongdi",
    "gn:country_code":"CN",
    "gn:dem":29,
    "gn:feature_class":"P",
    "gn:feature_code":"PPL",
    "gn:name":"Yanzhongdi",
    "gn:population":0,
    "gn:timezone":"Asia/Shanghai",
    "iso:country":"CN",
    "name:zho_x_preferred":[
        "\u4e25\u4e2d\u5824"
    ],
    "wof:name":"Yanzhongdi",
    "wof:placetype":"locality"
},
  "geometry": {"coordinates":[112.51940999999999,29.97187000000001],"type":"Point"}
}