{
  "type": "Feature",
  "properties": {
    "gn:admin1_code":"32.0",
    "gn:asciiname":"Bolunzi",
    "gn:country_code":"CN",
    "gn:dem":1450,
    "gn:feature_class":"P",
    "gn:feature_code":"PPL",
    "gn:name":"Bolunzi",
    "gn:population":0,
    "gn:timezone":"Asia/Shanghai",
    "iso:country":"CN",
    "name:zho_x_preferred":[
        "\u535a\u4ed1\u5b5c"
    ],
    "wof:name":"Bolunzi",
    "wof:placetype":"locality"
},
  "geometry": {"coordinates":[103.408,28.0351],"type":"Point"}
}