{
  "type": "Feature",
  "properties": {
    "gn:admin1_code":"10",
    "gn:asciiname":"Dongyingzi",
    "gn:country_code":"CN",
    "gn:dem":638,
    "gn:feature_class":"P",
    "gn:feature_code":"PPL",
    "gn:name":"Dongyingzi",
    "gn:population":0,
    "gn:timezone":"Asia/Shanghai",
    "iso:country":"CN",
    "name:und_x_variant":[
        "Tung-ying-tzu",
        "Dongying",
        "Dongyingzi"
    ],
    "name:zho_x_preferred":[
        "\u4e1c\u8425\u5b50"
    ],
    "wof:name":"Dongyingzi",
    "wof:placetype":"locality"
},
  "geometry": {"coordinates":[117.38606,40.82414],"type":"Point"}
}