{
  "type": "Feature",
  "properties": {
    "gn:admin1_code":"10.0",
    "gn:asciiname":"Xiayulin",
    "gn:country_code":"CN",
    "gn:dem":759,
    "gn:feature_class":"P",
    "gn:feature_code":"PPL",
    "gn:name":"Xiayulin",
    "gn:population":0,
    "gn:timezone":"Asia/Shanghai",
    "iso:country":"CN",
    "name:zho_x_preferred":[
        "\u4e0b\u6986\u6797"
    ],
    "wof:name":"Xiayulin",
    "wof:placetype":"locality"
},
  "geometry": {"coordinates":[115.36533,40.23978],"type":"Point"}
}