{
  "type": "Feature",
  "properties": {
    "gn:admin1_code":"7.0",
    "gn:asciiname":"Zhengfang",
    "gn:country_code":"CN",
    "gn:dem":362,
    "gn:feature_class":"P",
    "gn:feature_code":"PPL",
    "gn:name":"Zhengfang",
    "gn:population":0,
    "gn:timezone":"Asia/Shanghai",
    "iso:country":"CN",
    "name:und_x_variant":[
        "\u90d1\u574a"
    ],
    "name:zho_x_preferred":[
        "\u90d1\u574a"
    ],
    "wof:name":"Zhengfang",
    "wof:placetype":"locality"
},
  "geometry": {"coordinates":[116.33976,25.8836],"type":"Point"}
}