{
  "type": "Feature",
  "properties": {
    "gn:admin1_code":"24.0",
    "gn:asciiname":"Wohuzhuang",
    "gn:country_code":"CN",
    "gn:dem":1331,
    "gn:feature_class":"P",
    "gn:feature_code":"PPL",
    "gn:name":"Wohuzhuang",
    "gn:population":0,
    "gn:timezone":"Asia/Shanghai",
    "iso:country":"CN",
    "name:zho_x_preferred":[
        "\u5367\u864e\u5e84"
    ],
    "wof:name":"Wohuzhuang",
    "wof:placetype":"locality"
},
  "geometry": {"coordinates":[112.08481,36.43616],"type":"Point"}
}