{
  "type": "Feature",
  "properties": {
    "gn:admin1_code":"32.0",
    "gn:asciiname":"Guaizao",
    "gn:country_code":"CN",
    "gn:dem":501,
    "gn:feature_class":"P",
    "gn:feature_code":"PPL",
    "gn:name":"Guaizao",
    "gn:population":0,
    "gn:timezone":"Asia/Shanghai",
    "iso:country":"CN",
    "name:zho_x_preferred":[
        "\u62d0\u67a3"
    ],
    "wof:name":"Guaizao",
    "wof:placetype":"locality"
},
  "geometry": {"coordinates":[105.526,32.3008],"type":"Point"}
}