{
  "type": "Feature",
  "properties": {
    "gn:admin1_code":"16.0",
    "gn:asciiname":"Xiangkou",
    "gn:country_code":"CN",
    "gn:dem":238,
    "gn:feature_class":"P",
    "gn:feature_code":"PPL",
    "gn:name":"Xiangkou",
    "gn:population":0,
    "gn:timezone":"Asia/Shanghai",
    "iso:country":"CN",
    "name:zho_x_preferred":[
        "\u5df7\u53e3"
    ],
    "wof:name":"Xiangkou",
    "wof:placetype":"locality"
},
  "geometry": {"coordinates":[106.81399999999999,22.8755],"type":"Point"}
}