{
  "type": "Feature",
  "properties": {
    "gn:admin1_code":"26.0",
    "gn:asciiname":"Zhongtaicun",
    "gn:country_code":"CN",
    "gn:dem":1387,
    "gn:feature_class":"P",
    "gn:feature_code":"PPL",
    "gn:name":"Zhongtaicun",
    "gn:population":0,
    "gn:timezone":"Asia/Shanghai",
    "iso:country":"CN",
    "name:zho_x_preferred":[
        "\u4e2d\u53f0\u6751"
    ],
    "wof:name":"Zhongtaicun",
    "wof:placetype":"locality"
},
  "geometry": {"coordinates":[108.05641,36.88463],"type":"Point"}
}