{
  "type": "Feature",
  "properties": {
    "gn:admin1_code":"16.0",
    "gn:asciiname":"Bucheng",
    "gn:country_code":"CN",
    "gn:dem":476,
    "gn:feature_class":"P",
    "gn:feature_code":"PPL",
    "gn:name":"Bucheng",
    "gn:population":0,
    "gn:timezone":"Asia/Shanghai",
    "iso:country":"CN",
    "name:zho_x_preferred":[
        "\u5e03\u57ce"
    ],
    "wof:name":"Bucheng",
    "wof:placetype":"locality"
},
  "geometry": {"coordinates":[107.714,21.8535],"type":"Point"}
}