{
  "type": "Feature",
  "properties": {
    "gn:admin1_code":"4.0",
    "gn:asciiname":"Yuanzhong",
    "gn:country_code":"CN",
    "gn:dem":4,
    "gn:feature_class":"P",
    "gn:feature_code":"PPL",
    "gn:name":"Yuanzhong",
    "gn:population":0,
    "gn:timezone":"Asia/Shanghai",
    "iso:country":"CN",
    "name:zho_x_preferred":[
        "Yuanzhong"
    ],
    "name:zho_x_variant":[
        "\u5143\u4e2d"
    ],
    "wof:name":"Yuanzhong",
    "wof:placetype":"locality"
},
  "geometry": {"coordinates":[121.46185,31.88525],"type":"Point"}
}