{
  "type": "Feature",
  "properties": {
    "gn:admin1_code":"18",
    "gn:asciiname":"Heyang",
    "gn:country_code":"CN",
    "gn:dem":946,
    "gn:feature_class":"P",
    "gn:feature_code":"PPL",
    "gn:name":"Heyang",
    "gn:population":0,
    "gn:timezone":"Asia/Shanghai",
    "iso:country":"CN",
    "name:ceb_x_preferred":[
        "Heyang"
    ],
    "wof:name":"Heyang",
    "wof:placetype":"locality"
},
  "geometry": {"coordinates":[107.46028,26.10944],"type":"Point"}
}