{
  "type": "Feature",
  "properties": {
    "gn:admin1_code":"14.0",
    "gn:asciiname":"Ga'erdong",
    "gn:country_code":"CN",
    "gn:dem":4190,
    "gn:feature_class":"P",
    "gn:feature_code":"PPL",
    "gn:name":"Ga\u2019erdong",
    "gn:population":0,
    "gn:timezone":"Asia/Shanghai",
    "iso:country":"CN",
    "name:und_x_variant":[
        "Ga\u2019erdong"
    ],
    "name:zho_x_preferred":[
        "\u560e\u5c14\u4e1c"
    ],
    "wof:name":"Ga'erdong",
    "wof:placetype":"locality"
},
  "geometry": {"coordinates":[81.0996,30.5009],"type":"Point"}
}