{
  "type": "Feature",
  "properties": {
    "gn:admin1_code":"32.0",
    "gn:asciiname":"Ede",
    "gn:country_code":"CN",
    "gn:dem":3316,
    "gn:feature_class":"P",
    "gn:feature_code":"PPL",
    "gn:name":"Ede",
    "gn:population":0,
    "gn:timezone":"Asia/Shanghai",
    "iso:country":"CN",
    "name:cat_x_preferred":[
        "Ede"
    ],
    "name:ceb_x_preferred":[
        "Ede"
    ],
    "name:deu_x_preferred":[
        "Ede"
    ],
    "name:fra_x_preferred":[
        "Ede"
    ],
    "name:hun_x_preferred":[
        "Ede"
    ],
    "name:lit_x_preferred":[
        "Ed\u0117"
    ],
    "name:nld_x_preferred":[
        "Ede"
    ],
    "name:pol_x_preferred":[
        "Ede"
    ],
    "name:rus_x_preferred":[
        "\u042d\u0434\u0435"
    ],
    "name:spa_x_preferred":[
        "Ede"
    ],
    "name:swe_x_preferred":[
        "Ede"
    ],
    "name:tur_x_preferred":[
        "Ede"
    ],
    "name:zho_x_preferred":[
        "\u9102\u5fb7"
    ],
    "wof:name":"Ede",
    "wof:placetype":"locality"
},
  "geometry": {"coordinates":[100.11691999999999,31.45841],"type":"Point"}
}