{
  "type": "Feature",
  "properties": {
    "gn:admin1_code":"32.0",
    "gn:asciiname":"Ede",
    "gn:country_code":"CN",
    "gn:dem":3316,
    "gn:feature_class":"P",
    "gn:feature_code":"PPL",
    "gn:name":"Ede",
    "gn:population":0,
    "gn:timezone":"Asia/Shanghai",
    "iso:country":"CN",
    "name:zho_x_preferred":[
        "\u9102\u5fb7"
    ],
    "wof:name":"Ede",
    "wof:placetype":"locality"
},
  "geometry": {"coordinates":[100.11691999999999,31.45841],"type":"Point"}
}