{
  "type": "Feature",
  "properties": {
    "gn:admin1_code":"16.0",
    "gn:asciiname":"Zhushanzui",
    "gn:country_code":"CN",
    "gn:dem":207,
    "gn:feature_class":"P",
    "gn:feature_code":"PPL",
    "gn:name":"Zhushanzui",
    "gn:population":0,
    "gn:timezone":"Asia/Shanghai",
    "iso:country":"CN",
    "name:zho_x_preferred":[
        "\u7af9\u5c71\u5480"
    ],
    "wof:name":"Zhushanzui",
    "wof:placetype":"locality"
},
  "geometry": {"coordinates":[110.324,23.0789],"type":"Point"}
}