{
  "type": "Feature",
  "properties": {
    "gn:admin1_code":"33.0",
    "gn:asciiname":"Duiwoyan",
    "gn:country_code":"CN",
    "gn:dem":998,
    "gn:feature_class":"P",
    "gn:feature_code":"PPL",
    "gn:name":"Duiwoyan",
    "gn:population":0,
    "gn:timezone":"Asia/Shanghai",
    "iso:country":"CN",
    "name:zho_x_preferred":[
        "\u5bf9\u7a9d\u5ca9"
    ],
    "wof:name":"Duiwoyan",
    "wof:placetype":"locality"
},
  "geometry": {"coordinates":[106.37564,28.58938],"type":"Point"}
}