{
  "type": "Feature",
  "properties": {
    "gn:admin1_code":"32.0",
    "gn:asciiname":"Angu",
    "gn:country_code":"CN",
    "gn:dem":353,
    "gn:feature_class":"P",
    "gn:feature_code":"PPL",
    "gn:name":"Angu",
    "gn:population":0,
    "gn:timezone":"Asia/Shanghai",
    "iso:country":"CN",
    "name:fra_x_preferred":[
        "Kukukukus"
    ],
    "name:hrv_x_preferred":[
        "Kukukuku"
    ],
    "name:hun_x_preferred":[
        "Kukukukuk"
    ],
    "name:jpn_x_preferred":[
        "\u30af\u30ab\u30af\u30ab\u65cf"
    ],
    "name:kat_x_preferred":[
        "\u10d0\u10dc\u10d2\u10e3"
    ],
    "name:rus_x_preferred":[
        "\u0410\u043d\u0433\u0443"
    ],
    "name:zho_x_preferred":[
        "\u5b89\u56fa"
    ],
    "name:zho_x_variant":[
        "\u5eab\u5361\u5eab\u5361\u4eba"
    ],
    "wof:name":"Angu",
    "wof:placetype":"locality"
},
  "geometry": {"coordinates":[106.60482,31.22],"type":"Point"}
}