{
  "type": "Feature",
  "properties": {
    "gn:admin1_code":"18.0",
    "gn:asciiname":"Danao",
    "gn:country_code":"CN",
    "gn:dem":797,
    "gn:feature_class":"P",
    "gn:feature_code":"PPL",
    "gn:name":"Danao",
    "gn:population":0,
    "gn:timezone":"Asia/Shanghai",
    "iso:country":"CN",
    "name:ceb_x_preferred":[
        "Danao"
    ],
    "name:ell_x_preferred":[
        "\u0394\u03b1\u03bd\u03b1\u03cc\u03c2"
    ],
    "name:fra_x_preferred":[
        "Danao"
    ],
    "name:ita_x_preferred":[
        "Danao"
    ],
    "name:msa_x_preferred":[
        "Danao"
    ],
    "name:nld_x_preferred":[
        "Danao"
    ],
    "name:spa_x_preferred":[
        "Danao"
    ],
    "name:war_x_preferred":[
        "Danao"
    ],
    "name:zho_x_preferred":[
        "\u5927\u8111"
    ],
    "wof:name":"Danao",
    "wof:placetype":"locality"
},
  "geometry": {"coordinates":[108.19799999999999,25.9973],"type":"Point"}
}