{
  "type": "Feature",
  "properties": {
    "gn:admin1_code":"18.0",
    "gn:asciiname":"Danao",
    "gn:country_code":"CN",
    "gn:dem":797,
    "gn:feature_class":"P",
    "gn:feature_code":"PPL",
    "gn:name":"Danao",
    "gn:population":0,
    "gn:timezone":"Asia/Shanghai",
    "iso:country":"CN",
    "name:zho_x_preferred":[
        "\u5927\u8111"
    ],
    "wof:name":"Danao",
    "wof:placetype":"locality"
},
  "geometry": {"coordinates":[108.19799999999999,25.9973],"type":"Point"}
}