{
  "type": "Feature",
  "properties": {
    "gn:admin1_code":"02",
    "gn:asciiname":"Gexiang",
    "gn:country_code":"CN",
    "gn:dem":9,
    "gn:feature_class":"P",
    "gn:feature_code":"PPL",
    "gn:name":"Gexiang",
    "gn:population":0,
    "gn:timezone":"Asia/Shanghai",
    "iso:country":"CN",
    "name:und_x_variant":[
        "Kuo-hsiang",
        "Gexiang"
    ],
    "name:zho_x_preferred":[
        "\u9601\u5df7"
    ],
    "wof:name":"Gexiang",
    "wof:placetype":"locality"
},
  "geometry": {"coordinates":[120.64592,27.70187],"type":"Point"}
}