{
  "type": "Feature",
  "properties": {
    "gn:admin1_code":"24.0",
    "gn:asciiname":"Shanggoukou",
    "gn:country_code":"CN",
    "gn:dem":1377,
    "gn:feature_class":"P",
    "gn:feature_code":"PPL",
    "gn:name":"Shanggoukou",
    "gn:population":0,
    "gn:timezone":"Asia/Shanghai",
    "iso:country":"CN",
    "name:zho_x_preferred":[
        "\u4e0a\u6c9f\u53e3"
    ],
    "wof:name":"Shanggoukou",
    "wof:placetype":"locality"
},
  "geometry": {"coordinates":[111.06153,36.19501],"type":"Point"}
}