{
  "type": "Feature",
  "properties": {
    "gn:admin1_code":"3.0",
    "gn:asciiname":"Liantangbei",
    "gn:country_code":"CN",
    "gn:dem":162,
    "gn:feature_class":"P",
    "gn:feature_code":"PPL",
    "gn:name":"Liantangbei",
    "gn:population":0,
    "gn:timezone":"Asia/Shanghai",
    "iso:country":"CN",
    "name:und_x_variant":[
        "\u8fde\u5858\u80cc"
    ],
    "wof:name":"Liantangbei",
    "wof:placetype":"locality"
},
  "geometry": {"coordinates":[115.24517,25.8827],"type":"Point"}
}