{
  "type": "Feature",
  "properties": {
    "gn:admin1_code":"9.0",
    "gn:asciiname":"Xiaoxuzhuang",
    "gn:country_code":"CN",
    "gn:dem":47,
    "gn:feature_class":"P",
    "gn:feature_code":"PPL",
    "gn:name":"Xiaoxuzhuang",
    "gn:population":0,
    "gn:timezone":"Asia/Shanghai",
    "iso:country":"CN",
    "name:zho_x_preferred":[
        "\u5c0f\u5f90\u5e84"
    ],
    "wof:name":"Xiaoxuzhuang",
    "wof:placetype":"locality"
},
  "geometry": {"coordinates":[114.73481,32.80303],"type":"Point"}
}