{
  "type": "Feature",
  "properties": {
    "gn:admin1_code":"15.0",
    "gn:asciiname":"Taxian",
    "gn:country_code":"CN",
    "gn:dem":1361,
    "gn:feature_class":"P",
    "gn:feature_code":"PPL",
    "gn:name":"Taxian",
    "gn:population":0,
    "gn:timezone":"Asia/Shanghai",
    "iso:country":"CN",
    "name:und_x_variant":[
        "\u5854\u8d24"
    ],
    "wof:name":"Taxian",
    "wof:placetype":"locality"
},
  "geometry": {"coordinates":[107.48971,34.96542],"type":"Point"}
}