{
  "type": "Feature",
  "properties": {
    "gn:admin1_code":"04",
    "gn:asciiname":"Chenji",
    "gn:cc2":"CN",
    "gn:country_code":"CN",
    "gn:dem":21,
    "gn:feature_class":"P",
    "gn:feature_code":"PPL",
    "gn:name":"Chenji",
    "gn:population":0,
    "gn:timezone":"Asia/Shanghai",
    "iso:country":"CN",
    "name:und_x_variant":[
        "Ch\u2019en-chi",
        "Chenji"
    ],
    "wof:name":"Chenji",
    "wof:placetype":"locality"
},
  "geometry": {"coordinates":[118.15000000000001,33.55],"type":"Point"}
}