{
  "type": "Feature",
  "properties": {
    "gn:admin1_code":"15.0",
    "gn:asciiname":"Luo'erping",
    "gn:country_code":"CN",
    "gn:dem":2043,
    "gn:feature_class":"P",
    "gn:feature_code":"PPL",
    "gn:name":"Luo\u2019erping",
    "gn:population":0,
    "gn:timezone":"Asia/Shanghai",
    "iso:country":"CN",
    "name:und_x_variant":[
        "Luo\u2019erping"
    ],
    "name:zho_x_preferred":[
        "\u7f57\u513f\u576a"
    ],
    "wof:name":"Luo'erping",
    "wof:placetype":"locality"
},
  "geometry": {"coordinates":[104.42100000000001,35.2066],"type":"Point"}
}