{
  "type": "Feature",
  "properties": {
    "gn:admin1_code":"02",
    "gn:asciiname":"Linshan",
    "gn:cc2":"CN",
    "gn:country_code":"CN",
    "gn:dem":489,
    "gn:feature_class":"P",
    "gn:feature_code":"PPL",
    "gn:name":"Linshan",
    "gn:population":0,
    "gn:timezone":"Asia/Shanghai",
    "iso:country":"CN",
    "name:und_x_variant":[
        "Lin-shan-ts\u2019un",
        "Linshan"
    ],
    "wof:name":"Linshan",
    "wof:placetype":"locality"
},
  "geometry": {"coordinates":[120.54056,28.24417],"type":"Point"}
}