{
  "type": "Feature",
  "properties": {
    "gn:admin1_code":"15.0",
    "gn:asciiname":"Xiaxiding",
    "gn:country_code":"CN",
    "gn:dem":2915,
    "gn:feature_class":"P",
    "gn:feature_code":"PPL",
    "gn:name":"Xiaxiding",
    "gn:population":0,
    "gn:timezone":"Asia/Shanghai",
    "iso:country":"CN",
    "name:zho_x_preferred":[
        "\u4e0b\u897f\u9876"
    ],
    "wof:name":"Xiaxiding",
    "wof:placetype":"locality"
},
  "geometry": {"coordinates":[102.661,37.614],"type":"Point"}
}