{
  "type": "Feature",
  "properties": {
    "gn:admin1_code":"29.0",
    "gn:asciiname":"Bogali",
    "gn:country_code":"CN",
    "gn:dem":1694,
    "gn:feature_class":"P",
    "gn:feature_code":"PPL",
    "gn:name":"Bogali",
    "gn:population":0,
    "gn:timezone":"Asia/Shanghai",
    "iso:country":"CN",
    "name:zho_x_preferred":[
        "\u62e8\u560e\u91cc"
    ],
    "wof:name":"Bogali",
    "wof:placetype":"locality"
},
  "geometry": {"coordinates":[102.48999999999999,26.3047],"type":"Point"}
}