{
  "type": "Feature",
  "properties": {
    "gn:admin1_code":"32.0",
    "gn:asciiname":"Aoxiading",
    "gn:country_code":"CN",
    "gn:dem":2088,
    "gn:feature_class":"P",
    "gn:feature_code":"PPL",
    "gn:name":"Aoxiading",
    "gn:population":0,
    "gn:timezone":"Asia/Shanghai",
    "iso:country":"CN",
    "name:zho_x_preferred":[
        "\u51f9\u5477\u4e01"
    ],
    "wof:name":"Aoxiading",
    "wof:placetype":"locality"
},
  "geometry": {"coordinates":[100.675,28.3079],"type":"Point"}
}