{
  "type": "Feature",
  "properties": {
    "gn:admin1_code":"1.0",
    "gn:asciiname":"Donglizhaicun",
    "gn:country_code":"CN",
    "gn:dem":41,
    "gn:feature_class":"P",
    "gn:feature_code":"PPL",
    "gn:name":"Donglizhaicun",
    "gn:population":0,
    "gn:timezone":"Asia/Shanghai",
    "iso:country":"CN",
    "name:zho_x_preferred":[
        "\u4e1c\u674e\u5be8\u6751"
    ],
    "wof:name":"Donglizhaicun",
    "wof:placetype":"locality"
},
  "geometry": {"coordinates":[115.2234,32.93691],"type":"Point"}
}