{
  "type": "Feature",
  "properties": {
    "gn:admin1_code":"11.0",
    "gn:asciiname":"Qingjiachong",
    "gn:country_code":"CN",
    "gn:dem":274,
    "gn:feature_class":"P",
    "gn:feature_code":"PPL",
    "gn:name":"Qingjiachong",
    "gn:population":0,
    "gn:timezone":"Asia/Shanghai",
    "iso:country":"CN",
    "name:zho_x_preferred":[
        "\u9752\u5bb6\u51b2"
    ],
    "wof:name":"Qingjiachong",
    "wof:placetype":"locality"
},
  "geometry": {"coordinates":[109.9216,27.6482],"type":"Point"}
}