{
  "type": "Feature",
  "properties": {
    "gn:admin1_code":"10.0",
    "gn:asciiname":"Nanjiazhuang",
    "gn:country_code":"CN",
    "gn:dem":60,
    "gn:feature_class":"P",
    "gn:feature_code":"PPL",
    "gn:name":"Nanjiazhuang",
    "gn:population":0,
    "gn:timezone":"Asia/Shanghai",
    "iso:country":"CN",
    "name:und_x_variant":[
        "\u5357\u8d3e\u5e84"
    ],
    "wof:name":"Nanjiazhuang",
    "wof:placetype":"locality"
},
  "geometry": {"coordinates":[114.89678000000001,38.39882],"type":"Point"}
}