{
  "type": "Feature",
  "properties": {
    "gn:admin1_code":"12.0",
    "gn:asciiname":"Dongjiatian",
    "gn:country_code":"CN",
    "gn:dem":31,
    "gn:feature_class":"P",
    "gn:feature_code":"PPL",
    "gn:name":"Dongjiatian",
    "gn:population":0,
    "gn:timezone":"Asia/Shanghai",
    "iso:country":"CN",
    "name:und_x_variant":[
        "\u8463\u5bb6\u7530"
    ],
    "wof:name":"Dongjiatian",
    "wof:placetype":"locality"
},
  "geometry": {"coordinates":[114.69091,30.89273],"type":"Point"}
}