{
  "type": "Feature",
  "properties": {
    "gn:admin1_code":"4.0",
    "gn:asciiname":"Wuxing Liuzu",
    "gn:country_code":"CN",
    "gn:dem":6,
    "gn:feature_class":"P",
    "gn:feature_code":"PPL",
    "gn:name":"Wuxing Liuzu",
    "gn:population":0,
    "gn:timezone":"Asia/Shanghai",
    "iso:country":"CN",
    "name:zho_x_preferred":[
        "Wuxing Liuzu"
    ],
    "name:zho_x_variant":[
        "\u4e94\u661f\u516d\u7ec4"
    ],
    "wof:name":"Wuxing Liuzu",
    "wof:placetype":"locality"
},
  "geometry": {"coordinates":[120.98717000000001,32.15268],"type":"Point"}
}