{
  "type": "Feature",
  "properties": {
    "gn:admin1_code":"13",
    "gn:asciiname":"Gongqingtuan Nongchang Jiudui",
    "gn:country_code":"CN",
    "gn:dem":451,
    "gn:feature_class":"P",
    "gn:feature_code":"PPLF",
    "gn:name":"Gongqingtuan Nongchang Jiudui",
    "gn:population":0,
    "gn:timezone":"Asia/Urumqi",
    "iso:country":"CN",
    "name:zho_x_preferred":[
        "\u5171\u9752\u56e2\u519c\u573a\u4e5d\u961f"
    ],
    "wof:name":"Gongqingtuan Nongchang Jiudui",
    "wof:placetype":"locality"
},
  "geometry": {"coordinates":[87.41504999999999,44.33264000000001],"type":"Point"}
}