{
  "type": "Feature",
  "properties": {
    "gn:admin1_code":"12.0",
    "gn:asciiname":"Xiaocun",
    "gn:country_code":"CN",
    "gn:dem":697,
    "gn:feature_class":"P",
    "gn:feature_code":"PPLA4",
    "gn:name":"Xiaocun",
    "gn:population":0,
    "gn:timezone":"Asia/Shanghai",
    "iso:country":"CN",
    "name:und_x_variant":[
        "Hsiao-ts\u2019un",
        "Xiaocun",
        "Xiaocun Xiang"
    ],
    "name:zho_x_preferred":[
        "\u5c0f\u6751"
    ],
    "name:zho_x_variant":[
        "\u5c0f\u6751\u4e61"
    ],
    "wof:name":"Xiaocun",
    "wof:placetype":"locality"
},
  "geometry": {"coordinates":[108.9568,29.91191],"type":"Point"}
}