{
  "type": "Feature",
  "properties": {
    "gn:admin1_code":"24.0",
    "gn:asciiname":"Beiduwu",
    "gn:country_code":"CN",
    "gn:dem":486,
    "gn:feature_class":"P",
    "gn:feature_code":"PPL",
    "gn:name":"Beiduwu",
    "gn:population":0,
    "gn:timezone":"Asia/Shanghai",
    "iso:country":"CN",
    "name:und_x_variant":[
        "\u5317\u675c\u575e"
    ],
    "wof:name":"Beiduwu",
    "wof:placetype":"locality"
},
  "geometry": {"coordinates":[111.1172,35.72805],"type":"Point"}
}