{
  "type": "Feature",
  "properties": {
    "gn:admin1_code":"11.0",
    "gn:asciiname":"Zhangshuxia",
    "gn:cc2":"CN",
    "gn:country_code":"CN",
    "gn:dem":187,
    "gn:feature_class":"P",
    "gn:feature_code":"PPL",
    "gn:name":"Zhangshuxia",
    "gn:population":0,
    "gn:timezone":"Asia/Shanghai",
    "iso:country":"CN",
    "name:und_x_variant":[
        "Chang-shu-hsia",
        "Chang-shu",
        "Chang-shu-hsia-hs\u00fc",
        "Zhangshuxia"
    ],
    "wof:name":"Zhangshuxia",
    "wof:placetype":"locality"
},
  "geometry": {"coordinates":[112.76667,25.85],"type":"Point"}
}