{
  "type": "Feature",
  "properties": {
    "gn:admin1_code":"4.0",
    "gn:asciiname":"Nancaozhuangcun",
    "gn:country_code":"CN",
    "gn:dem":4,
    "gn:feature_class":"P",
    "gn:feature_code":"PPL",
    "gn:name":"Nancaozhuangcun",
    "gn:population":0,
    "gn:timezone":"Asia/Shanghai",
    "iso:country":"CN",
    "name:zho_x_preferred":[
        "\u5357\u66f9\u5e84\u6751"
    ],
    "wof:name":"Nancaozhuangcun",
    "wof:placetype":"locality"
},
  "geometry": {"coordinates":[120.5545,31.7655],"type":"Point"}
}