{
  "type": "Feature",
  "properties": {
    "gn:admin1_code":"15.0",
    "gn:asciiname":"Touniu'er",
    "gn:country_code":"CN",
    "gn:dem":1497,
    "gn:feature_class":"P",
    "gn:feature_code":"PPL",
    "gn:name":"Touniu\u2019er",
    "gn:population":0,
    "gn:timezone":"Asia/Shanghai",
    "iso:country":"CN",
    "name:und_x_variant":[
        "Touniu\u2019er",
        "\u900f\u725b\u513f"
    ],
    "wof:name":"Touniu'er",
    "wof:placetype":"locality"
},
  "geometry": {"coordinates":[105.36241,33.43531],"type":"Point"}
}