{
  "type": "Feature",
  "properties": {
    "gn:admin1_code":"29.0",
    "gn:asciiname":"Kongdang",
    "gn:country_code":"CN",
    "gn:dem":1615,
    "gn:feature_class":"P",
    "gn:feature_code":"PPL",
    "gn:name":"Kongdang",
    "gn:population":0,
    "gn:timezone":"Asia/Shanghai",
    "iso:country":"CN",
    "name:zho_x_preferred":[
        "\u5b54\u5f53"
    ],
    "wof:name":"Kongdang",
    "wof:placetype":"locality"
},
  "geometry": {"coordinates":[98.3382,27.8744],"type":"Point"}
}