{
  "type": "Feature",
  "properties": {
    "gn:admin1_code":"9",
    "gn:asciiname":"Houyuelian",
    "gn:country_code":"CN",
    "gn:dem":50,
    "gn:feature_class":"P",
    "gn:feature_code":"PPL",
    "gn:name":"Houyuelian",
    "gn:population":0,
    "gn:timezone":"Asia/Shanghai",
    "iso:country":"CN",
    "name:zho_x_preferred":[
        "\u540e\u5cb3\u8fde"
    ],
    "wof:name":"Houyuelian",
    "wof:placetype":"locality"
},
  "geometry": {"coordinates":[115.25697,36.11406],"type":"Point"}
}