{
  "type": "Feature",
  "properties": {
    "gn:admin1_code":"4.0",
    "gn:asciiname":"Shengfeng",
    "gn:country_code":"CN",
    "gn:dem":3,
    "gn:feature_class":"P",
    "gn:feature_code":"PPL",
    "gn:name":"Shengfeng",
    "gn:population":0,
    "gn:timezone":"Asia/Shanghai",
    "iso:country":"CN",
    "name:zho_x_preferred":[
        "Shengfeng"
    ],
    "name:zho_x_variant":[
        "\u80dc\u4e30"
    ],
    "wof:name":"Shengfeng",
    "wof:placetype":"locality"
},
  "geometry": {"coordinates":[121.87495,31.72633],"type":"Point"}
}