{
  "type": "Feature",
  "properties": {
    "gn:admin1_code":"30.0",
    "gn:asciiname":"Dajiao",
    "gn:country_code":"CN",
    "gn:dem":12,
    "gn:feature_class":"P",
    "gn:feature_code":"PPL",
    "gn:name":"Dajiao",
    "gn:population":0,
    "gn:timezone":"Asia/Shanghai",
    "iso:country":"CN",
    "name:hak_x_preferred":[
        "Thaai-phin-cang-ziu"
    ],
    "name:nld_x_preferred":[
        "Taipingqingjiao"
    ],
    "name:zho_x_preferred":[
        "\u5927\u89d2"
    ],
    "name:zho_x_variant":[
        "\u7948\u5b89\u91ae"
    ],
    "wof:name":"Dajiao",
    "wof:placetype":"locality"
},
  "geometry": {"coordinates":[112.97457,23.64573],"type":"Point"}
}