{
  "type": "Feature",
  "properties": {
    "gn:admin1_code":"2.0",
    "gn:asciiname":"Bujiachang",
    "gn:country_code":"CN",
    "gn:dem":6,
    "gn:feature_class":"P",
    "gn:feature_code":"PPL",
    "gn:name":"Bujiachang",
    "gn:population":0,
    "gn:timezone":"Asia/Shanghai",
    "iso:country":"CN",
    "name:und_x_variant":[
        "\u535c\u5bb6\u573a"
    ],
    "wof:name":"Bujiachang",
    "wof:placetype":"locality"
},
  "geometry": {"coordinates":[120.62736,30.50854],"type":"Point"}
}