{
  "type": "Feature",
  "properties": {
    "gn:admin1_code":"3",
    "gn:asciiname":"Pengjiasheng",
    "gn:country_code":"CN",
    "gn:dem":705,
    "gn:feature_class":"P",
    "gn:feature_code":"PPL",
    "gn:name":"Pengjiasheng",
    "gn:population":0,
    "gn:timezone":"Asia/Shanghai",
    "iso:country":"CN",
    "wof:name":"Pengjiasheng",
    "wof:placetype":"locality"
},
  "geometry": {"coordinates":[117.05249999999999,27.51083],"type":"Point"}
}