{
  "type": "Feature",
  "properties": {
    "gn:admin1_code":"14.0",
    "gn:asciiname":"Shadatong",
    "gn:country_code":"CN",
    "gn:dem":3637,
    "gn:feature_class":"P",
    "gn:feature_code":"PPL",
    "gn:name":"Shadatong",
    "gn:population":0,
    "gn:timezone":"Asia/Urumqi",
    "iso:country":"CN",
    "name:zho_x_preferred":[
        "\u6c99\u6253\u540c"
    ],
    "wof:name":"Shadatong",
    "wof:placetype":"locality"
},
  "geometry": {"coordinates":[98.67837,29.36852],"type":"Point"}
}