{
  "type": "Feature",
  "properties": {
    "gn:admin1_code":"1.0",
    "gn:asciiname":"Fuchengcun",
    "gn:country_code":"CN",
    "gn:dem":15,
    "gn:feature_class":"P",
    "gn:feature_code":"PPL",
    "gn:name":"Fuchengcun",
    "gn:population":0,
    "gn:timezone":"Asia/Shanghai",
    "iso:country":"CN",
    "name:zho_x_preferred":[
        "\u9644\u57ce\u6751"
    ],
    "wof:name":"Fuchengcun",
    "wof:placetype":"locality"
},
  "geometry": {"coordinates":[117.28436000000001,31.23368],"type":"Point"}
}