{
  "type": "Feature",
  "properties": {
    "gn:admin1_code":"8.0",
    "gn:asciiname":"Donghuicun",
    "gn:country_code":"CN",
    "gn:dem":38,
    "gn:feature_class":"P",
    "gn:feature_code":"PPL",
    "gn:name":"Donghuicun",
    "gn:population":0,
    "gn:timezone":"Asia/Shanghai",
    "iso:country":"CN",
    "name:und_x_variant":[
        "Donghui Xumuchang"
    ],
    "name:zho_x_preferred":[
        "\u4e1c\u8f89\u6751"
    ],
    "wof:name":"Donghuicun",
    "wof:placetype":"locality"
},
  "geometry": {"coordinates":[134.53336999999999,48.3291],"type":"Point"}
}