{
  "type": "Feature",
  "properties": {
    "gn:admin1_code":"11.0",
    "gn:asciiname":"Pu'anqiao",
    "gn:country_code":"CN",
    "gn:dem":113,
    "gn:feature_class":"P",
    "gn:feature_code":"PPL",
    "gn:name":"Pu\u2019anqiao",
    "gn:population":0,
    "gn:timezone":"Asia/Shanghai",
    "iso:country":"CN",
    "name:und_x_variant":[
        "Pu\u2019anqiao"
    ],
    "name:zho_x_preferred":[
        "\u666e\u5b89\u6865"
    ],
    "wof:name":"Pu'anqiao",
    "wof:placetype":"locality"
},
  "geometry": {"coordinates":[113.51115,27.21591],"type":"Point"}
}