{
  "type": "Feature",
  "properties": {
    "gn:admin1_code":"30",
    "gn:asciiname":"Magong",
    "gn:country_code":"CN",
    "gn:dem":7,
    "gn:feature_class":"P",
    "gn:feature_code":"PPLA4",
    "gn:name":"Magong",
    "gn:population":0,
    "gn:timezone":"Asia/Shanghai",
    "iso:country":"CN",
    "name:ara_x_preferred":[
        "\u0645\u0627\u063a\u0648\u0646\u063a"
    ],
    "name:ces_x_preferred":[
        "Ma-kung"
    ],
    "name:deu_x_preferred":[
        "Magong"
    ],
    "name:fas_x_preferred":[
        "\u0645\u0627\u06af\u0648\u0646\u06af"
    ],
    "name:fra_x_preferred":[
        "Magong"
    ],
    "name:hak_x_preferred":[
        "M\u00e2-k\u00fbng-s\u1e73"
    ],
    "name:ita_x_preferred":[
        "Magong"
    ],
    "name:jpn_x_preferred":[
        "\u99ac\u516c\u5e02"
    ],
    "name:kor_x_preferred":[
        "\ub9c8\uad81\uc2dc"
    ],
    "name:lit_x_preferred":[
        "Magongas"
    ],
    "name:nld_x_preferred":[
        "Magong"
    ],
    "name:pol_x_preferred":[
        "Magong"
    ],
    "name:rus_x_preferred":[
        "\u041c\u0430\u0433\u0443\u043d"
    ],
    "name:tur_x_preferred":[
        "Magong"
    ],
    "name:und_x_variant":[
        "Ma-tsung",
        "Ma-kung",
        "Magong"
    ],
    "name:vie_x_preferred":[
        "M\u00e3 C\u00f4ng"
    ],
    "name:zho_x_preferred":[
        "\u9a6c\u5bab"
    ],
    "name:zho_x_variant":[
        "\u99ac\u516c\u5e02"
    ],
    "wof:name":"Magong",
    "wof:placetype":"locality"
},
  "geometry": {"coordinates":[115.23853,22.79019],"type":"Point"}
}