{
  "type": "Feature",
  "properties": {
    "gn:admin1_code":"30",
    "gn:asciiname":"Magong",
    "gn:country_code":"CN",
    "gn:dem":7,
    "gn:feature_class":"P",
    "gn:feature_code":"PPLA4",
    "gn:name":"Magong",
    "gn:population":0,
    "gn:timezone":"Asia/Shanghai",
    "iso:country":"CN",
    "name:und_x_variant":[
        "Ma-tsung",
        "Ma-kung",
        "Magong"
    ],
    "name:zho_x_preferred":[
        "\u9a6c\u5bab"
    ],
    "wof:name":"Magong",
    "wof:placetype":"locality"
},
  "geometry": {"coordinates":[115.23853,22.79019],"type":"Point"}
}