{
  "type": "Feature",
  "properties": {
    "gn:admin1_code":"19.0",
    "gn:asciiname":"Xinanwopeng",
    "gn:country_code":"CN",
    "gn:dem":92,
    "gn:feature_class":"P",
    "gn:feature_code":"PPL",
    "gn:name":"Xinanwopeng",
    "gn:population":0,
    "gn:timezone":"Asia/Shanghai",
    "iso:country":"CN",
    "name:zho_x_preferred":[
        "\u897f\u5357\u7a9d\u68da"
    ],
    "wof:name":"Xinanwopeng",
    "wof:placetype":"locality"
},
  "geometry": {"coordinates":[123.76600000000001,42.9455],"type":"Point"}
}