{
  "type": "Feature",
  "properties": {
    "gn:admin1_code":"16.0",
    "gn:asciiname":"Panwu",
    "gn:country_code":"CN",
    "gn:dem":59,
    "gn:feature_class":"P",
    "gn:feature_code":"PPL",
    "gn:name":"Panwu",
    "gn:population":0,
    "gn:timezone":"Asia/Shanghai",
    "iso:country":"CN",
    "name:zho_x_preferred":[
        "\u6f58\u5c4b"
    ],
    "wof:name":"Panwu",
    "wof:placetype":"locality"
},
  "geometry": {"coordinates":[109.13200000000001,22.1133],"type":"Point"}
}