{
  "type": "Feature",
  "properties": {
    "gn:admin1_code":"10",
    "gn:asciiname":"Dasangyuan",
    "gn:country_code":"CN",
    "gn:dem":226,
    "gn:feature_class":"P",
    "gn:feature_code":"PPL",
    "gn:name":"Dasangyuan",
    "gn:population":0,
    "gn:timezone":"Asia/Shanghai",
    "iso:country":"CN",
    "name:zho_x_preferred":[
        "\u5927\u6851\u56ed"
    ],
    "wof:name":"Dasangyuan",
    "wof:placetype":"locality"
},
  "geometry": {"coordinates":[118.37175000000001,40.55735],"type":"Point"}
}