{
  "type": "Feature",
  "properties": {
    "gn:admin1_code":"18.0",
    "gn:asciiname":"Yonghe",
    "gn:country_code":"CN",
    "gn:dem":967,
    "gn:feature_class":"P",
    "gn:feature_code":"PPL",
    "gn:name":"Yonghe",
    "gn:population":0,
    "gn:timezone":"Asia/Shanghai",
    "iso:country":"CN",
    "wof:name":"Yonghe",
    "wof:placetype":"locality"
},
  "geometry": {"coordinates":[106.47444,27.45694],"type":"Point"}
}