{
  "type": "Feature",
  "properties": {
    "gn:admin1_code":"25.0",
    "gn:asciiname":"Songjiashuipo",
    "gn:country_code":"CN",
    "gn:dem":32,
    "gn:feature_class":"P",
    "gn:feature_code":"PPL",
    "gn:name":"Songjiashuipo",
    "gn:population":0,
    "gn:timezone":"Asia/Shanghai",
    "iso:country":"CN",
    "name:zho_x_preferred":[
        "\u5b8b\u5bb6\u6c34\u6cca"
    ],
    "wof:name":"Songjiashuipo",
    "wof:placetype":"locality"
},
  "geometry": {"coordinates":[120.10362000000001,36.69411],"type":"Point"}
}