{
  "type": "Feature",
  "properties": {
    "gn:admin1_code":"04",
    "gn:asciiname":"Shengze",
    "gn:country_code":"CN",
    "gn:dem":7,
    "gn:feature_class":"P",
    "gn:feature_code":"PPLA4",
    "gn:name":"Shengze",
    "gn:population":0,
    "gn:timezone":"Asia/Shanghai",
    "iso:country":"CN",
    "name:und_x_variant":[
        "Sheng-tse-chen",
        "Sheng-tse",
        "Shengze",
        "\u76db\u6cfd",
        "Shengze Zhen",
        "\u76db\u6cfd\u9547"
    ],
    "name:zho_x_preferred":[
        "\u76db\u6cfd\u9547"
    ],
    "wof:name":"Shengze",
    "wof:placetype":"locality"
},
  "geometry": {"coordinates":[120.66931,30.90884],"type":"Point"}
}