{
  "type": "Feature",
  "properties": {
    "gn:admin1_code":"3.0",
    "gn:asciiname":"Lianhuatang",
    "gn:country_code":"CN",
    "gn:dem":248,
    "gn:feature_class":"P",
    "gn:feature_code":"PPL",
    "gn:name":"Lianhuatang",
    "gn:population":0,
    "gn:timezone":"Asia/Shanghai",
    "iso:country":"CN",
    "name:und_x_variant":[
        "\u83b2\u82b1\u5858"
    ],
    "wof:name":"Lianhuatang",
    "wof:placetype":"locality"
},
  "geometry": {"coordinates":[114.0132,27.16481],"type":"Point"}
}