{
  "type": "Feature",
  "properties": {
    "gn:admin1_code":"5.0",
    "gn:asciiname":"Shuangtaicun",
    "gn:country_code":"CN",
    "gn:dem":192,
    "gn:feature_class":"P",
    "gn:feature_code":"PPL",
    "gn:name":"Shuangtaicun",
    "gn:population":0,
    "gn:timezone":"Asia/Shanghai",
    "iso:country":"CN",
    "name:zho_x_preferred":[
        "\u53cc\u592a\u6751"
    ],
    "wof:name":"Shuangtaicun",
    "wof:placetype":"locality"
},
  "geometry": {"coordinates":[126.25059,45.01802],"type":"Point"}
}