{
  "type": "Feature",
  "properties": {
    "gn:admin1_code":"16.0",
    "gn:asciiname":"Wangmeng",
    "gn:country_code":"CN",
    "gn:dem":39,
    "gn:feature_class":"P",
    "gn:feature_code":"PPL",
    "gn:name":"Wangmeng",
    "gn:population":0,
    "gn:timezone":"Asia/Shanghai",
    "iso:country":"CN",
    "name:zho_x_preferred":[
        "\u738b\u5b5f"
    ],
    "wof:name":"Wangmeng",
    "wof:placetype":"locality"
},
  "geometry": {"coordinates":[108.97799999999999,22.2412],"type":"Point"}
}