{
  "type": "Feature",
  "properties": {
    "gn:admin1_code":"19.0",
    "gn:asciiname":"Songshugou",
    "gn:country_code":"CN",
    "gn:dem":185,
    "gn:feature_class":"P",
    "gn:feature_code":"PPL",
    "gn:name":"Songshugou",
    "gn:population":0,
    "gn:timezone":"Asia/Shanghai",
    "iso:country":"CN",
    "name:zho_x_preferred":[
        "\u677e\u6811\u6c9f"
    ],
    "wof:name":"Songshugou",
    "wof:placetype":"locality"
},
  "geometry": {"coordinates":[124.47255,42.42934],"type":"Point"}
}