{
  "type": "Feature",
  "properties": {
    "gn:admin1_code":"11.0",
    "gn:asciiname":"Wawu Zhoujia",
    "gn:country_code":"CN",
    "gn:dem":140,
    "gn:feature_class":"P",
    "gn:feature_code":"PPL",
    "gn:name":"Wawu Zhoujia",
    "gn:population":0,
    "gn:timezone":"Asia/Shanghai",
    "iso:country":"CN",
    "name:zho_x_preferred":[
        "\u74e6\u5c4b\u5468\u5bb6"
    ],
    "wof:name":"Wawu Zhoujia",
    "wof:placetype":"locality"
},
  "geometry": {"coordinates":[112.50108,26.35128],"type":"Point"}
}