{
  "type": "Feature",
  "properties": {
    "gn:admin1_code":"10",
    "gn:asciiname":"Cujiangfang",
    "gn:country_code":"CN",
    "gn:dem":1408,
    "gn:feature_class":"P",
    "gn:feature_code":"PPL",
    "gn:name":"Cujiangfang",
    "gn:population":0,
    "gn:timezone":"Asia/Shanghai",
    "iso:country":"CN",
    "name:zho_x_preferred":[
        "\u918b\u9171\u574a"
    ],
    "wof:name":"Cujiangfang",
    "wof:placetype":"locality"
},
  "geometry": {"coordinates":[114.82465999999999,41.727],"type":"Point"}
}