{
  "type": "Feature",
  "properties": {
    "gn:admin1_code":"16.0",
    "gn:asciiname":"Suoxi",
    "gn:country_code":"CN",
    "gn:dem":437,
    "gn:feature_class":"P",
    "gn:feature_code":"PPL",
    "gn:name":"Suoxi",
    "gn:population":0,
    "gn:timezone":"Asia/Shanghai",
    "iso:country":"CN",
    "name:zho_x_preferred":[
        "\u6240\u7ec6"
    ],
    "wof:name":"Suoxi",
    "wof:placetype":"locality"
},
  "geometry": {"coordinates":[106.64400000000001,25.057],"type":"Point"}
}