{
  "type": "Feature",
  "properties": {
    "gn:admin1_code":"22",
    "gn:asciiname":"Beiyanfa",
    "gn:country_code":"CN",
    "gn:dem":34,
    "gn:feature_class":"P",
    "gn:feature_code":"PPL",
    "gn:name":"Beiyanfa",
    "gn:population":0,
    "gn:timezone":"Asia/Shanghai",
    "iso:country":"CN",
    "name:zho_x_preferred":[
        "\u5317\u7814\u57a1"
    ],
    "wof:name":"Beiyanfa",
    "wof:placetype":"locality"
},
  "geometry": {"coordinates":[116.395,39.6644],"type":"Point"}
}