{
  "type": "Feature",
  "properties": {
    "gn:admin1_code":"24.0",
    "gn:asciiname":"Renliucun",
    "gn:country_code":"CN",
    "gn:dem":365,
    "gn:feature_class":"P",
    "gn:feature_code":"PPL",
    "gn:name":"Renliucun",
    "gn:population":0,
    "gn:timezone":"Asia/Shanghai",
    "iso:country":"CN",
    "name:zho_x_preferred":[
        "\u4efb\u67f3\u6751"
    ],
    "wof:name":"Renliucun",
    "wof:placetype":"locality"
},
  "geometry": {"coordinates":[110.69022,35.04528],"type":"Point"}
}