{
  "type": "Feature",
  "properties": {
    "gn:admin1_code":"14.0",
    "gn:asciiname":"Zegucun",
    "gn:country_code":"CN",
    "gn:dem":4292,
    "gn:feature_class":"P",
    "gn:feature_code":"PPL",
    "gn:name":"Zegucun",
    "gn:population":0,
    "gn:timezone":"Asia/Urumqi",
    "iso:country":"CN",
    "name:zho_x_preferred":[
        "\u5219\u53e4\u6751"
    ],
    "wof:name":"Zegucun",
    "wof:placetype":"locality"
},
  "geometry": {"coordinates":[97.19327,30.29104],"type":"Point"}
}