{
  "type": "Feature",
  "properties": {
    "gn:admin1_code":"26",
    "gn:asciiname":"Xinjia",
    "gn:country_code":"CN",
    "gn:dem":521,
    "gn:feature_class":"P",
    "gn:feature_code":"PPL",
    "gn:name":"Xinjia",
    "gn:population":0,
    "gn:timezone":"Asia/Shanghai",
    "iso:country":"CN",
    "name:zho_x_preferred":[
        "\u5e78\u5bb6"
    ],
    "wof:name":"Xinjia",
    "wof:placetype":"locality"
},
  "geometry": {"coordinates":[109.32068,34.92142],"type":"Point"}
}