{
  "type": "Feature",
  "properties": {
    "gn:admin1_code":"30.0",
    "gn:asciiname":"Wuxingcun",
    "gn:country_code":"CN",
    "gn:dem":88,
    "gn:feature_class":"P",
    "gn:feature_code":"PPL",
    "gn:name":"Wuxingcun",
    "gn:population":0,
    "gn:timezone":"Asia/Shanghai",
    "iso:country":"CN",
    "name:zho_x_preferred":[
        "\u4e94\u661f\u6751"
    ],
    "wof:name":"Wuxingcun",
    "wof:placetype":"locality"
},
  "geometry": {"coordinates":[112.02191000000001,24.04703],"type":"Point"}
}