{
  "type": "Feature",
  "properties": {
    "gn:admin1_code":"14.0",
    "gn:asciiname":"Rimoin",
    "gn:country_code":"CN",
    "gn:dem":4268,
    "gn:feature_class":"P",
    "gn:feature_code":"PPLF",
    "gn:name":"Rimoin",
    "gn:population":0,
    "gn:timezone":"Asia/Urumqi",
    "iso:country":"CN",
    "name:bod_x_preferred":[
        "Rimoin"
    ],
    "name:zho_x_preferred":[
        "Rimu"
    ],
    "name:zho_x_variant":[
        "\u65e5\u6728",
        "Zhamei",
        "\u624e\u7f8e"
    ],
    "wof:name":"Rimoin",
    "wof:placetype":"locality"
},
  "geometry": {"coordinates":[97.63507,31.83975],"type":"Point"}
}