{
  "type": "Feature",
  "properties": {
    "gn:admin1_code":"2.0",
    "gn:asciiname":"Jiqingqiao",
    "gn:country_code":"CN",
    "gn:dem":15,
    "gn:feature_class":"P",
    "gn:feature_code":"PPL",
    "gn:name":"Jiqingqiao",
    "gn:population":0,
    "gn:timezone":"Asia/Shanghai",
    "iso:country":"CN",
    "name:und_x_variant":[
        "\u5409\u5e86\u6865"
    ],
    "wof:name":"Jiqingqiao",
    "wof:placetype":"locality"
},
  "geometry": {"coordinates":[119.67234000000001,30.65328],"type":"Point"}
}