{
  "type": "Feature",
  "properties": {
    "gn:admin1_code":"9.0",
    "gn:asciiname":"Meiqianlou",
    "gn:country_code":"CN",
    "gn:dem":101,
    "gn:feature_class":"P",
    "gn:feature_code":"PPL",
    "gn:name":"Meiqianlou",
    "gn:population":0,
    "gn:timezone":"Asia/Shanghai",
    "iso:country":"CN",
    "name:zho_x_preferred":[
        "\u6885\u524d\u697c"
    ],
    "wof:name":"Meiqianlou",
    "wof:placetype":"locality"
},
  "geometry": {"coordinates":[115.30267000000001,31.89473],"type":"Point"}
}