{
  "type": "Feature",
  "properties": {
    "gn:admin1_code":"19.0",
    "gn:asciiname":"Mahuangdi",
    "gn:country_code":"CN",
    "gn:dem":46,
    "gn:feature_class":"P",
    "gn:feature_code":"PPL",
    "gn:name":"Mahuangdi",
    "gn:population":0,
    "gn:timezone":"Asia/Shanghai",
    "iso:country":"CN",
    "name:und_x_variant":[
        "\u9a6c\u8352\u5730"
    ],
    "name:zho_x_preferred":[
        "\u9a6c\u8352\u5730"
    ],
    "wof:name":"Mahuangdi",
    "wof:placetype":"locality"
},
  "geometry": {"coordinates":[123.39117,42.17242],"type":"Point"}
}