{
  "type": "Feature",
  "properties": {
    "gn:admin1_code":"10.0",
    "gn:asciiname":"Dakunliu",
    "gn:country_code":"CN",
    "gn:dem":42,
    "gn:feature_class":"P",
    "gn:feature_code":"PPL",
    "gn:name":"Dakunliu",
    "gn:population":0,
    "gn:timezone":"Asia/Shanghai",
    "iso:country":"CN",
    "name:zho_x_preferred":[
        "\u5927\u6346 \u67f3"
    ],
    "wof:name":"Dakunliu",
    "wof:placetype":"locality"
},
  "geometry": {"coordinates":[115.8793,39.44492],"type":"Point"}
}