{
  "type": "Feature",
  "properties": {
    "gn:admin1_code":"2.0",
    "gn:asciiname":"Wanyaolong",
    "gn:country_code":"CN",
    "gn:dem":695,
    "gn:feature_class":"P",
    "gn:feature_code":"PPL",
    "gn:name":"Wanyaolong",
    "gn:population":0,
    "gn:timezone":"Asia/Shanghai",
    "iso:country":"CN",
    "name:zho_x_preferred":[
        "\u7897\u7a91\u5784"
    ],
    "wof:name":"Wanyaolong",
    "wof:placetype":"locality"
},
  "geometry": {"coordinates":[120.07874,27.42707],"type":"Point"}
}