{
  "type": "Feature",
  "properties": {
    "gn:admin1_code":"13.0",
    "gn:asciiname":"Ha-la-wei-ssu-te",
    "gn:country_code":"CN",
    "gn:dem":859,
    "gn:feature_class":"P",
    "gn:feature_code":"PPL",
    "gn:name":"Ha-la-wei-ssu-te",
    "gn:population":0,
    "gn:timezone":"Asia/Urumqi",
    "iso:country":"CN",
    "wof:name":"Ha-la-wei-ssu-te",
    "wof:placetype":"locality"
},
  "geometry": {"coordinates":[87.33139,40.62972],"type":"Point"}
}