{
  "type": "Feature",
  "properties": {
    "gn:admin1_code":"7.0",
    "gn:asciiname":"Wuchen",
    "gn:country_code":"CN",
    "gn:dem":48,
    "gn:feature_class":"P",
    "gn:feature_code":"PPL",
    "gn:name":"Wuchen",
    "gn:population":0,
    "gn:timezone":"Asia/Shanghai",
    "iso:country":"CN",
    "name:zho_x_preferred":[
        "\u620a\u8fb0"
    ],
    "wof:name":"Wuchen",
    "wof:placetype":"locality"
},
  "geometry": {"coordinates":[119.32281,25.84939],"type":"Point"}
}