{
  "type": "Feature",
  "properties": {
    "gn:admin1_code":"32.0",
    "gn:asciiname":"Zhaojiaping",
    "gn:country_code":"CN",
    "gn:dem":692,
    "gn:feature_class":"P",
    "gn:feature_code":"PPL",
    "gn:name":"Zhaojiaping",
    "gn:population":0,
    "gn:timezone":"Asia/Shanghai",
    "iso:country":"CN",
    "name:zho_x_preferred":[
        "\u8d75\u5bb6\u576a"
    ],
    "wof:name":"Zhaojiaping",
    "wof:placetype":"locality"
},
  "geometry": {"coordinates":[105.22803,31.62943],"type":"Point"}
}