{
  "type": "Feature",
  "properties": {
    "gn:admin1_code":"5.0",
    "gn:asciiname":"Jingyingchang",
    "gn:country_code":"CN",
    "gn:dem":471,
    "gn:feature_class":"P",
    "gn:feature_code":"PPL",
    "gn:name":"Jingyingchang",
    "gn:population":0,
    "gn:timezone":"Asia/Shanghai",
    "iso:country":"CN",
    "name:zho_x_preferred":[
        "\u7ecf\u8425\u573a"
    ],
    "wof:name":"Jingyingchang",
    "wof:placetype":"locality"
},
  "geometry": {"coordinates":[126.44747,43.36612],"type":"Point"}
}