{
  "type": "Feature",
  "properties": {
    "gn:admin1_code":"02",
    "gn:asciiname":"Yangzhuangcun",
    "gn:country_code":"CN",
    "gn:dem":741,
    "gn:feature_class":"P",
    "gn:feature_code":"PPL",
    "gn:name":"Yangzhuangcun",
    "gn:population":0,
    "gn:timezone":"Asia/Shanghai",
    "iso:country":"CN",
    "name:und_x_variant":[
        "Yang-chuang",
        "Yangzhuang",
        "Yangzhuangcun"
    ],
    "name:zho_x_preferred":[
        "\u6768\u5e84"
    ],
    "name:zho_x_variant":[
        "\u6768\u5e84\u6751"
    ],
    "wof:name":"Yangzhuangcun",
    "wof:placetype":"locality"
},
  "geometry": {"coordinates":[120.43467,28.48318],"type":"Point"}
}