{
  "type": "Feature",
  "properties": {
    "gn:admin1_code":"18.0",
    "gn:asciiname":"Xinbie",
    "gn:country_code":"CN",
    "gn:dem":664,
    "gn:feature_class":"P",
    "gn:feature_code":"PPL",
    "gn:name":"Xinbie",
    "gn:population":0,
    "gn:timezone":"Asia/Shanghai",
    "iso:country":"CN",
    "name:zho_x_preferred":[
        "\u65b0\u9cd6"
    ],
    "wof:name":"Xinbie",
    "wof:placetype":"locality"
},
  "geometry": {"coordinates":[108.56,28.0122],"type":"Point"}
}