{
  "type": "Feature",
  "properties": {
    "gn:admin1_code":"29.0",
    "gn:asciiname":"Guoluo",
    "gn:country_code":"CN",
    "gn:dem":1962,
    "gn:feature_class":"P",
    "gn:feature_code":"PPL",
    "gn:name":"Guoluo",
    "gn:population":0,
    "gn:timezone":"Asia/Shanghai",
    "iso:country":"CN",
    "name:zho_x_preferred":[
        "\u679c\u7f57"
    ],
    "wof:name":"Guoluo",
    "wof:placetype":"locality"
},
  "geometry": {"coordinates":[101.26300000000001,25.0914],"type":"Point"}
}