{
  "type": "Feature",
  "properties": {
    "gn:admin1_code":"21",
    "gn:asciiname":"Majiawan",
    "gn:country_code":"CN",
    "gn:dem":1599,
    "gn:feature_class":"P",
    "gn:feature_code":"PPL",
    "gn:name":"Majiawan",
    "gn:population":0,
    "gn:timezone":"Asia/Shanghai",
    "iso:country":"CN",
    "wof:name":"Majiawan",
    "wof:placetype":"locality"
},
  "geometry": {"coordinates":[105.73472,36.71611],"type":"Point"}
}