{
  "type": "Feature",
  "properties": {
    "gn:admin1_code":"25",
    "gn:asciiname":"Houzhanjiachakou",
    "gn:country_code":"CN",
    "gn:dem":152,
    "gn:feature_class":"P",
    "gn:feature_code":"PPL",
    "gn:name":"Houzhanjiachakou",
    "gn:population":0,
    "gn:timezone":"Asia/Shanghai",
    "iso:country":"CN",
    "name:zho_x_preferred":[
        "\u540e\u6218\u5bb6\u5c94\u53e3"
    ],
    "wof:name":"Houzhanjiachakou",
    "wof:placetype":"locality"
},
  "geometry": {"coordinates":[118.874,35.8018],"type":"Point"}
}