{
  "type": "Feature",
  "properties": {
    "gn:admin1_code":"16.0",
    "gn:asciiname":"Langfu",
    "gn:country_code":"CN",
    "gn:dem":342,
    "gn:feature_class":"P",
    "gn:feature_code":"PPL",
    "gn:name":"Langfu",
    "gn:population":0,
    "gn:timezone":"Asia/Shanghai",
    "iso:country":"CN",
    "name:zho_x_preferred":[
        "\u90ce\u4f0f"
    ],
    "wof:name":"Langfu",
    "wof:placetype":"locality"
},
  "geometry": {"coordinates":[107.32899999999999,24.115],"type":"Point"}
}