{
  "type": "Feature",
  "properties": {
    "gn:admin1_code":"1.0",
    "gn:asciiname":"Huantangcun",
    "gn:country_code":"CN",
    "gn:dem":13,
    "gn:feature_class":"P",
    "gn:feature_code":"PPL",
    "gn:name":"Huantangcun",
    "gn:population":0,
    "gn:timezone":"Asia/Shanghai",
    "iso:country":"CN",
    "name:zho_x_preferred":[
        "\u73af\u5858\u6751"
    ],
    "wof:name":"Huantangcun",
    "wof:placetype":"locality"
},
  "geometry": {"coordinates":[118.15195,31.7426],"type":"Point"}
}