{
  "type": "Feature",
  "properties": {
    "gn:admin1_code":"26.0",
    "gn:asciiname":"Huayuancun",
    "gn:country_code":"CN",
    "gn:dem":1111,
    "gn:feature_class":"P",
    "gn:feature_code":"PPL",
    "gn:name":"Huayuancun",
    "gn:population":0,
    "gn:timezone":"Asia/Shanghai",
    "iso:country":"CN",
    "name:zho_x_preferred":[
        "\u5316\u586c\u6751"
    ],
    "wof:name":"Huayuancun",
    "wof:placetype":"locality"
},
  "geometry": {"coordinates":[110.17238999999999,36.16351],"type":"Point"}
}