{
  "type": "Feature",
  "properties": {
    "gn:admin1_code":"14.0",
    "gn:asciiname":"Zasib",
    "gn:country_code":"CN",
    "gn:dem":4365,
    "gn:feature_class":"P",
    "gn:feature_code":"PPLF",
    "gn:name":"Zasib",
    "gn:population":0,
    "gn:timezone":"Asia/Urumqi",
    "iso:country":"CN",
    "name:bod_x_preferred":[
        "Zasib"
    ],
    "name:zho_x_preferred":[
        "Zhasai"
    ],
    "name:zho_x_variant":[
        "\u624e\u8d5b",
        "Pengdatang",
        "\u5f6d\u8fbe\u5858"
    ],
    "wof:name":"Zasib",
    "wof:placetype":"locality"
},
  "geometry": {"coordinates":[93.508,32.008],"type":"Point"}
}