{
  "type": "Feature",
  "properties": {
    "gn:admin1_code":"18",
    "gn:asciiname":"Zhuchanghe",
    "gn:country_code":"CN",
    "gn:dem":1543,
    "gn:feature_class":"P",
    "gn:feature_code":"PPL",
    "gn:name":"Zhuchanghe",
    "gn:population":0,
    "gn:timezone":"Asia/Shanghai",
    "iso:country":"CN",
    "name:zho_x_preferred":[
        "\u732a\u573a\u6cb3"
    ],
    "wof:name":"Zhuchanghe",
    "wof:placetype":"locality"
},
  "geometry": {"coordinates":[104.875,25.552],"type":"Point"}
}