{
  "type": "Feature",
  "properties": {
    "gn:admin1_code":"7",
    "gn:asciiname":"Yuanlou",
    "gn:country_code":"CN",
    "gn:dem":131,
    "gn:feature_class":"P",
    "gn:feature_code":"PPL",
    "gn:name":"Yuanlou",
    "gn:population":0,
    "gn:timezone":"Asia/Shanghai",
    "iso:country":"CN",
    "name:zho_x_preferred":[
        "\u56ed\u697c"
    ],
    "wof:name":"Yuanlou",
    "wof:placetype":"locality"
},
  "geometry": {"coordinates":[117.59404000000001,24.77383],"type":"Point"}
}