{
  "type": "Feature",
  "properties": {
    "gn:admin1_code":"24.0",
    "gn:asciiname":"Chengjiagou",
    "gn:country_code":"CN",
    "gn:dem":1174,
    "gn:feature_class":"P",
    "gn:feature_code":"PPL",
    "gn:name":"Chengjiagou",
    "gn:population":0,
    "gn:timezone":"Asia/Shanghai",
    "iso:country":"CN",
    "name:zho_x_preferred":[
        "\u6210\u5bb6\u6c9f"
    ],
    "wof:name":"Chengjiagou",
    "wof:placetype":"locality"
},
  "geometry": {"coordinates":[110.95524,36.99032],"type":"Point"}
}