{
  "type": "Feature",
  "properties": {
    "gn:admin1_code":"32.0",
    "gn:asciiname":"Lanchang",
    "gn:country_code":"CN",
    "gn:dem":448,
    "gn:feature_class":"P",
    "gn:feature_code":"PPL",
    "gn:name":"Lanchang",
    "gn:population":0,
    "gn:timezone":"Asia/Shanghai",
    "iso:country":"CN",
    "name:msa_x_preferred":[
        "Lanchang"
    ],
    "name:zho_x_preferred":[
        "\u84dd\u5382"
    ],
    "wof:name":"Lanchang",
    "wof:placetype":"locality"
},
  "geometry": {"coordinates":[105.22499999999999,28.1411],"type":"Point"}
}