{
  "type": "Feature",
  "properties": {
    "gn:admin1_code":"16.0",
    "gn:asciiname":"Juanpeng",
    "gn:country_code":"CN",
    "gn:dem":116,
    "gn:feature_class":"P",
    "gn:feature_code":"PPL",
    "gn:name":"Juanpeng",
    "gn:population":0,
    "gn:timezone":"Asia/Shanghai",
    "iso:country":"CN",
    "name:zho_x_preferred":[
        "\u5377\u84ec"
    ],
    "wof:name":"Juanpeng",
    "wof:placetype":"locality"
},
  "geometry": {"coordinates":[107.072,22.3744],"type":"Point"}
}