{
  "type": "Feature",
  "properties": {
    "gn:admin1_code":"3.0",
    "gn:asciiname":"Taqian",
    "gn:country_code":"CN",
    "gn:dem":62,
    "gn:feature_class":"P",
    "gn:feature_code":"PPL",
    "gn:name":"Taqian",
    "gn:population":0,
    "gn:timezone":"Asia/Shanghai",
    "iso:country":"CN",
    "name:und_x_variant":[
        "\u5854\u524d"
    ],
    "wof:name":"Taqian",
    "wof:placetype":"locality"
},
  "geometry": {"coordinates":[115.48842,28.78071],"type":"Point"}
}