{
  "type": "Feature",
  "properties": {
    "gn:admin1_code":"6.0",
    "gn:asciiname":"Shawo",
    "gn:country_code":"CN",
    "gn:dem":3042,
    "gn:feature_class":"P",
    "gn:feature_code":"PPL",
    "gn:name":"Shawo",
    "gn:population":0,
    "gn:timezone":"Asia/Urumqi",
    "iso:country":"CN",
    "name:zho_x_preferred":[
        "\u6c99\u7a9d"
    ],
    "wof:name":"Shawo",
    "wof:placetype":"locality"
},
  "geometry": {"coordinates":[97.80587,36.01267],"type":"Point"}
}