{
  "type": "Feature",
  "properties": {
    "gn:admin1_code":"1.0",
    "gn:asciiname":"Cangxicun",
    "gn:country_code":"CN",
    "gn:dem":67,
    "gn:feature_class":"P",
    "gn:feature_code":"PPL",
    "gn:name":"Cangxicun",
    "gn:population":0,
    "gn:timezone":"Asia/Shanghai",
    "iso:country":"CN",
    "name:zho_x_preferred":[
        "\u4ed3\u897f\u6751"
    ],
    "wof:name":"Cangxicun",
    "wof:placetype":"locality"
},
  "geometry": {"coordinates":[117.73882999999999,32.40803],"type":"Point"}
}