{
  "type": "Feature",
  "properties": {
    "gn:admin1_code":"25.0",
    "gn:asciiname":"Zhailixujiacun",
    "gn:country_code":"CN",
    "gn:dem":10,
    "gn:feature_class":"P",
    "gn:feature_code":"PPL",
    "gn:name":"Zhailixujiacun",
    "gn:population":0,
    "gn:timezone":"Asia/Shanghai",
    "iso:country":"CN",
    "name:zho_x_preferred":[
        "\u5be8\u91cc\u5f90\u5bb6\u6751"
    ],
    "wof:name":"Zhailixujiacun",
    "wof:placetype":"locality"
},
  "geometry": {"coordinates":[119.71120000000001,37.03381],"type":"Point"}
}