{
  "type": "Feature",
  "properties": {
    "gn:admin1_code":"10.0",
    "gn:asciiname":"Simazhuang",
    "gn:country_code":"CN",
    "gn:dem":9,
    "gn:feature_class":"P",
    "gn:feature_code":"PPL",
    "gn:name":"Simazhuang",
    "gn:population":0,
    "gn:timezone":"Asia/Shanghai",
    "iso:country":"CN",
    "name:zho_x_preferred":[
        "\u53f8\u9a6c\u5e84"
    ],
    "wof:name":"Simazhuang",
    "wof:placetype":"locality"
},
  "geometry": {"coordinates":[116.80800000000001,38.6195],"type":"Point"}
}