{
  "type": "Feature",
  "properties": {
    "gn:admin1_code":"4.0",
    "gn:asciiname":"Lixucun",
    "gn:country_code":"CN",
    "gn:dem":4,
    "gn:feature_class":"P",
    "gn:feature_code":"PPL",
    "gn:name":"Lixucun",
    "gn:population":0,
    "gn:timezone":"Asia/Shanghai",
    "iso:country":"CN",
    "name:zho_x_preferred":[
        "\u674e\u5729\u6751"
    ],
    "wof:name":"Lixucun",
    "wof:placetype":"locality"
},
  "geometry": {"coordinates":[119.38988999999999,33.91309],"type":"Point"}
}