{
  "type": "Feature",
  "properties": {
    "gn:admin1_code":"14",
    "gn:asciiname":"Zhaxibuba",
    "gn:country_code":"CN",
    "gn:dem":5059,
    "gn:feature_class":"P",
    "gn:feature_code":"PPL",
    "gn:name":"Zhaxibuba",
    "gn:population":0,
    "gn:timezone":"Asia/Urumqi",
    "iso:country":"CN",
    "name:zho_x_preferred":[
        "\u624e\u897f\u5e03\u5df4"
    ],
    "wof:name":"Zhaxibuba",
    "wof:placetype":"locality"
},
  "geometry": {"coordinates":[89.53440000000001,29.5108],"type":"Point"}
}