{
  "type": "Feature",
  "properties": {
    "gn:admin1_code":"29.0",
    "gn:asciiname":"Hetouzhai",
    "gn:country_code":"CN",
    "gn:dem":1885,
    "gn:feature_class":"P",
    "gn:feature_code":"PPL",
    "gn:name":"Hetouzhai",
    "gn:population":0,
    "gn:timezone":"Asia/Shanghai",
    "iso:country":"CN",
    "name:zho_x_preferred":[
        "\u6cb3\u5934\u5be8"
    ],
    "wof:name":"Hetouzhai",
    "wof:placetype":"locality"
},
  "geometry": {"coordinates":[100.191,23.8667],"type":"Point"}
}