{
  "type": "Feature",
  "properties": {
    "gn:admin1_code":"9.0",
    "gn:asciiname":"Liufangzhuang",
    "gn:country_code":"CN",
    "gn:dem":214,
    "gn:feature_class":"P",
    "gn:feature_code":"PPL",
    "gn:name":"Liufangzhuang",
    "gn:population":0,
    "gn:timezone":"Asia/Shanghai",
    "iso:country":"CN",
    "name:und_x_variant":[
        "\u5218\u82b3\u5e84",
        "Liufangzhuang"
    ],
    "wof:name":"Liufangzhuang",
    "wof:placetype":"locality"
},
  "geometry": {"coordinates":[112.80276000000001,33.84818],"type":"Point"}
}