{
  "type": "Feature",
  "properties": {
    "gn:admin1_code":"8.0",
    "gn:asciiname":"Xianghuicun",
    "gn:country_code":"CN",
    "gn:dem":192,
    "gn:feature_class":"P",
    "gn:feature_code":"PPL",
    "gn:name":"Xianghuicun",
    "gn:population":0,
    "gn:timezone":"Asia/Shanghai",
    "iso:country":"CN",
    "name:zho_x_preferred":[
        "\u5411\u8f89\u6751"
    ],
    "wof:name":"Xianghuicun",
    "wof:placetype":"locality"
},
  "geometry": {"coordinates":[126.70638,47.51939],"type":"Point"}
}