{
  "type": "Feature",
  "properties": {
    "gn:admin1_code":"12.0",
    "gn:asciiname":"Xiangjiachong",
    "gn:country_code":"CN",
    "gn:dem":364,
    "gn:feature_class":"P",
    "gn:feature_code":"PPL",
    "gn:name":"Xiangjiachong",
    "gn:population":0,
    "gn:timezone":"Asia/Shanghai",
    "iso:country":"CN",
    "name:zho_x_preferred":[
        "Xiangjiachong"
    ],
    "name:zho_x_variant":[
        "\u5411\u5bb6\u51b2"
    ],
    "wof:name":"Xiangjiachong",
    "wof:placetype":"locality"
},
  "geometry": {"coordinates":[111.13916,30.20659],"type":"Point"}
}