{
  "type": "Feature",
  "properties": {
    "gn:admin1_code":"4.0",
    "gn:asciiname":"Xingjiancun",
    "gn:country_code":"CN",
    "gn:dem":1,
    "gn:feature_class":"P",
    "gn:feature_code":"PPL",
    "gn:name":"Xingjiancun",
    "gn:population":0,
    "gn:timezone":"Asia/Shanghai",
    "iso:country":"CN",
    "name:und_x_variant":[
        "\u5174\u5efa\u6751"
    ],
    "name:zho_x_preferred":[
        "\u5174\u5efa\u6751"
    ],
    "wof:name":"Xingjiancun",
    "wof:placetype":"locality"
},
  "geometry": {"coordinates":[120.49071000000001,31.15131],"type":"Point"}
}