{
  "type": "Feature",
  "properties": {
    "gn:admin1_code":"18.0",
    "gn:asciiname":"Luowangtian",
    "gn:country_code":"CN",
    "gn:dem":449,
    "gn:feature_class":"P",
    "gn:feature_code":"PPL",
    "gn:name":"Luowangtian",
    "gn:population":0,
    "gn:timezone":"Asia/Shanghai",
    "iso:country":"CN",
    "name:zho_x_preferred":[
        "\u7f57\u65fa\u7530"
    ],
    "wof:name":"Luowangtian",
    "wof:placetype":"locality"
},
  "geometry": {"coordinates":[109.408,26.9103],"type":"Point"}
}