{
  "type": "Feature",
  "properties": {
    "gn:admin1_code":"11.0",
    "gn:asciiname":"Binjiawan",
    "gn:country_code":"CN",
    "gn:dem":189,
    "gn:feature_class":"P",
    "gn:feature_code":"PPL",
    "gn:name":"Binjiawan",
    "gn:population":0,
    "gn:timezone":"Asia/Shanghai",
    "iso:country":"CN",
    "name:zho_x_preferred":[
        "\u5bbe\u5bb6\u6e7e"
    ],
    "wof:name":"Binjiawan",
    "wof:placetype":"locality"
},
  "geometry": {"coordinates":[109.98751,27.90614],"type":"Point"}
}