{
  "type": "Feature",
  "properties": {
    "gn:admin1_code":"26.0",
    "gn:asciiname":"Haojiawan",
    "gn:country_code":"CN",
    "gn:dem":769,
    "gn:feature_class":"P",
    "gn:feature_code":"PPL",
    "gn:name":"Haojiawan",
    "gn:population":0,
    "gn:timezone":"Asia/Shanghai",
    "iso:country":"CN",
    "name:und_x_variant":[
        "\u90dd\u5bb6\u6e7e"
    ],
    "wof:name":"Haojiawan",
    "wof:placetype":"locality"
},
  "geometry": {"coordinates":[107.75099,34.14684],"type":"Point"}
}