{
  "type": "Feature",
  "properties": {
    "gn:admin1_code":"12.0",
    "gn:asciiname":"Houli",
    "gn:country_code":"CN",
    "gn:dem":513,
    "gn:feature_class":"P",
    "gn:feature_code":"PPL",
    "gn:name":"Houli",
    "gn:population":0,
    "gn:timezone":"Asia/Shanghai",
    "iso:country":"CN",
    "name:zho_x_preferred":[
        "Houli"
    ],
    "name:zho_x_variant":[
        "\u7334\u6817"
    ],
    "wof:name":"Houli",
    "wof:placetype":"locality"
},
  "geometry": {"coordinates":[109.35025,29.52307],"type":"Point"}
}