{
  "type": "Feature",
  "properties": {
    "gn:admin1_code":"32.0",
    "gn:asciiname":"Xiaohanxi",
    "gn:country_code":"CN",
    "gn:dem":1046,
    "gn:feature_class":"P",
    "gn:feature_code":"PPL",
    "gn:name":"Xiaohanxi",
    "gn:population":0,
    "gn:timezone":"Asia/Shanghai",
    "iso:country":"CN",
    "name:zho_x_preferred":[
        "\u5c0f\u6c49\u6eaa"
    ],
    "wof:name":"Xiaohanxi",
    "wof:placetype":"locality"
},
  "geometry": {"coordinates":[103.782,28.6446],"type":"Point"}
}