{
  "type": "Feature",
  "properties": {
    "gn:admin1_code":"9.0",
    "gn:asciiname":"Damengzhuang",
    "gn:country_code":"CN",
    "gn:dem":168,
    "gn:feature_class":"P",
    "gn:feature_code":"PPL",
    "gn:name":"Damengzhuang",
    "gn:population":0,
    "gn:timezone":"Asia/Shanghai",
    "iso:country":"CN",
    "name:zho_x_preferred":[
        "\u5927\u5b5f\u5e84"
    ],
    "wof:name":"Damengzhuang",
    "wof:placetype":"locality"
},
  "geometry": {"coordinates":[112.96684,33.2726],"type":"Point"}
}