{
  "type": "Feature",
  "properties": {
    "gn:admin1_code":"18",
    "gn:asciiname":"Bangguang",
    "gn:country_code":"CN",
    "gn:dem":1076,
    "gn:feature_class":"P",
    "gn:feature_code":"PPL",
    "gn:name":"Bangguang",
    "gn:population":0,
    "gn:timezone":"Asia/Shanghai",
    "iso:country":"CN",
    "name:zho_x_preferred":[
        "\u699c\u5e7f"
    ],
    "wof:name":"Bangguang",
    "wof:placetype":"locality"
},
  "geometry": {"coordinates":[107.16800000000001,25.91800000000001],"type":"Point"}
}