{
  "type": "Feature",
  "properties": {
    "gn:admin1_code":"24.0",
    "gn:asciiname":"Liuyu",
    "gn:country_code":"CN",
    "gn:dem":1165,
    "gn:feature_class":"P",
    "gn:feature_code":"PPL",
    "gn:name":"Liuyu",
    "gn:population":0,
    "gn:timezone":"Asia/Shanghai",
    "iso:country":"CN",
    "name:zho_x_preferred":[
        "\u7559\u5cea"
    ],
    "wof:name":"Liuyu",
    "wof:placetype":"locality"
},
  "geometry": {"coordinates":[111.39552999999999,36.60621],"type":"Point"}
}