{
  "type": "Feature",
  "properties": {
    "gn:admin1_code":"32.0",
    "gn:asciiname":"Esema",
    "gn:country_code":"CN",
    "gn:dem":3521,
    "gn:feature_class":"P",
    "gn:feature_code":"PPL",
    "gn:name":"Esema",
    "gn:population":0,
    "gn:timezone":"Asia/Shanghai",
    "iso:country":"CN",
    "name:zho_x_preferred":[
        "\u989d\u8272\u739b"
    ],
    "wof:name":"Esema",
    "wof:placetype":"locality"
},
  "geometry": {"coordinates":[102.092,32.6567],"type":"Point"}
}