{
  "type": "Feature",
  "properties": {
    "gn:admin1_code":"2.0",
    "gn:asciiname":"Lutan",
    "gn:country_code":"CN",
    "gn:dem":133,
    "gn:feature_class":"P",
    "gn:feature_code":"PPL",
    "gn:name":"L\u00fctan",
    "gn:population":0,
    "gn:timezone":"Asia/Shanghai",
    "iso:country":"CN",
    "name:zho_x_preferred":[
        "\u5415\u6f6d"
    ],
    "name:zho_x_variant":[
        "L\u00fctan"
    ],
    "wof:name":"Lutan",
    "wof:placetype":"locality"
},
  "geometry": {"coordinates":[119.54048,28.38401],"type":"Point"}
}