{
  "type": "Feature",
  "properties": {
    "gn:admin1_code":"19.0",
    "gn:asciiname":"Wangdazhai",
    "gn:country_code":"CN",
    "gn:dem":79,
    "gn:feature_class":"P",
    "gn:feature_code":"PPL",
    "gn:name":"Wangdazhai",
    "gn:population":0,
    "gn:timezone":"Asia/Shanghai",
    "iso:country":"CN",
    "name:und_x_variant":[
        "\u738b\u5927\u5be8"
    ],
    "wof:name":"Wangdazhai",
    "wof:placetype":"locality"
},
  "geometry": {"coordinates":[122.65501999999999,40.43521],"type":"Point"}
}