{
  "type": "Feature",
  "properties": {
    "gn:admin1_code":"15.0",
    "gn:asciiname":"Daiba",
    "gn:country_code":"CN",
    "gn:dem":3150,
    "gn:feature_class":"P",
    "gn:feature_code":"PPL",
    "gn:name":"Daiba",
    "gn:population":0,
    "gn:timezone":"Asia/Shanghai",
    "iso:country":"CN",
    "name:und_x_variant":[
        "\u4ee3\u5df4"
    ],
    "wof:name":"Daiba",
    "wof:placetype":"locality"
},
  "geometry": {"coordinates":[103.16692,34.23769],"type":"Point"}
}