{
  "type": "Feature",
  "properties": {
    "gn:admin1_code":"32.0",
    "gn:asciiname":"Longwo",
    "gn:country_code":"CN",
    "gn:dem":2459,
    "gn:feature_class":"P",
    "gn:feature_code":"PPL",
    "gn:name":"Longwo",
    "gn:population":0,
    "gn:timezone":"Asia/Shanghai",
    "iso:country":"CN",
    "name:zho_x_preferred":[
        "\u9f99\u7a9d"
    ],
    "wof:name":"Longwo",
    "wof:placetype":"locality"
},
  "geometry": {"coordinates":[103.61,31.8001],"type":"Point"}
}