{
  "type": "Feature",
  "properties": {
    "gn:admin1_code":"7.0",
    "gn:asciiname":"Wuge",
    "gn:cc2":"CN",
    "gn:country_code":"CN",
    "gn:dem":575,
    "gn:feature_class":"P",
    "gn:feature_code":"PPL",
    "gn:name":"Wuge",
    "gn:population":0,
    "gn:timezone":"Asia/Shanghai",
    "iso:country":"CN",
    "name:und_x_variant":[
        "Wu-ko",
        "Wuge"
    ],
    "wof:name":"Wuge",
    "wof:placetype":"locality"
},
  "geometry": {"coordinates":[116.71666999999999,25.88333],"type":"Point"}
}