{
  "type": "Feature",
  "properties": {
    "gn:admin1_code":"33.0",
    "gn:asciiname":"Baolongsi",
    "gn:country_code":"CN",
    "gn:dem":502,
    "gn:feature_class":"P",
    "gn:feature_code":"PPL",
    "gn:name":"Baolongsi",
    "gn:population":0,
    "gn:timezone":"Asia/Shanghai",
    "iso:country":"CN",
    "name:zho_x_preferred":[
        "\u5821\u9f99\u5bfa"
    ],
    "wof:name":"Baolongsi",
    "wof:placetype":"locality"
},
  "geometry": {"coordinates":[109.19370000000001,28.9784],"type":"Point"}
}