{
  "type": "Feature",
  "properties": {
    "gn:admin1_code":"30.0",
    "gn:asciiname":"Langwei",
    "gn:country_code":"CN",
    "gn:dem":66,
    "gn:feature_class":"P",
    "gn:feature_code":"PPL",
    "gn:name":"Langwei",
    "gn:population":0,
    "gn:timezone":"Asia/Shanghai",
    "iso:country":"CN",
    "name:zho_x_preferred":[
        "\u6d6a\u5c3e"
    ],
    "wof:name":"Langwei",
    "wof:placetype":"locality"
},
  "geometry": {"coordinates":[112.05464000000001,23.88459],"type":"Point"}
}