{
  "type": "Feature",
  "properties": {
    "gn:admin1_code":"5.0",
    "gn:asciiname":"Mianxicun",
    "gn:country_code":"CN",
    "gn:dem":136,
    "gn:feature_class":"P",
    "gn:feature_code":"PPL",
    "gn:name":"Mianxicun",
    "gn:population":0,
    "gn:timezone":"Asia/Shanghai",
    "iso:country":"CN",
    "name:zho_x_preferred":[
        "\u68c9\u897f\u6751"
    ],
    "wof:name":"Mianxicun",
    "wof:placetype":"locality"
},
  "geometry": {"coordinates":[123.49692,45.77176],"type":"Point"}
}