{
  "type": "Feature",
  "properties": {
    "gn:admin1_code":"29",
    "gn:asciiname":"Dabaizai",
    "gn:country_code":"CN",
    "gn:dem":1926,
    "gn:feature_class":"P",
    "gn:feature_code":"PPL",
    "gn:name":"Dabaizai",
    "gn:population":0,
    "gn:timezone":"Asia/Shanghai",
    "iso:country":"CN",
    "name:zho_x_preferred":[
        "\u5927\u767e\u5bb0"
    ],
    "wof:name":"Dabaizai",
    "wof:placetype":"locality"
},
  "geometry": {"coordinates":[101.45999999999999,24.9638],"type":"Point"}
}