{
  "type": "Feature",
  "properties": {
    "gn:admin1_code":"30",
    "gn:asciiname":"Jiangwu",
    "gn:country_code":"CN",
    "gn:dem":107,
    "gn:feature_class":"P",
    "gn:feature_code":"PPL",
    "gn:name":"Jiangwu",
    "gn:population":0,
    "gn:timezone":"Asia/Shanghai",
    "iso:country":"CN",
    "name:zho_x_preferred":[
        "\u6c5f\u5c4b"
    ],
    "wof:name":"Jiangwu",
    "wof:placetype":"locality"
},
  "geometry": {"coordinates":[116.33307000000001,24.37291],"type":"Point"}
}