{
  "type": "Feature",
  "properties": {
    "gn:admin1_code":"7",
    "gn:asciiname":"Daping Houcun",
    "gn:country_code":"CN",
    "gn:dem":390,
    "gn:feature_class":"P",
    "gn:feature_code":"PPL",
    "gn:name":"Daping Houcun",
    "gn:population":0,
    "gn:timezone":"Asia/Shanghai",
    "iso:country":"CN",
    "name:zho_x_preferred":[
        "\u5927\u576a\u540e\u6751"
    ],
    "wof:name":"Daping Houcun",
    "wof:placetype":"locality"
},
  "geometry": {"coordinates":[117.41624,24.85504],"type":"Point"}
}