{
  "type": "Feature",
  "properties": {
    "gn:admin1_code":"8.0",
    "gn:asciiname":"Duishan",
    "gn:country_code":"CN",
    "gn:dem":148,
    "gn:feature_class":"P",
    "gn:feature_code":"PPL",
    "gn:name":"Duishan",
    "gn:population":0,
    "gn:timezone":"Asia/Shanghai",
    "iso:country":"CN",
    "name:zho_x_preferred":[
        "\u5bf9\u5c71"
    ],
    "wof:name":"Duishan",
    "wof:placetype":"locality"
},
  "geometry": {"coordinates":[124.85059,46.82038],"type":"Point"}
}