{
  "type": "Feature",
  "properties": {
    "gn:admin1_code":"7.0",
    "gn:asciiname":"Dujiayang",
    "gn:country_code":"CN",
    "gn:dem":463,
    "gn:feature_class":"P",
    "gn:feature_code":"PPL",
    "gn:name":"Dujiayang",
    "gn:population":0,
    "gn:timezone":"Asia/Shanghai",
    "iso:country":"CN",
    "name:zho_x_preferred":[
        "\u6e21\u5bb6\u6d0b"
    ],
    "wof:name":"Dujiayang",
    "wof:placetype":"locality"
},
  "geometry": {"coordinates":[119.67305,27.44446],"type":"Point"}
}