{
  "type": "Feature",
  "properties": {
    "gn:admin1_code":"9.0",
    "gn:asciiname":"Dongwa",
    "gn:country_code":"CN",
    "gn:dem":795,
    "gn:feature_class":"P",
    "gn:feature_code":"PPL",
    "gn:name":"Dongwa",
    "gn:population":0,
    "gn:timezone":"Asia/Shanghai",
    "iso:country":"CN",
    "name:und_x_variant":[
        "\u4e1c\u6d3c",
        "Dongwa"
    ],
    "wof:name":"Dongwa",
    "wof:placetype":"locality"
},
  "geometry": {"coordinates":[112.35754,33.91097],"type":"Point"}
}