{
  "type": "Feature",
  "properties": {
    "gn:admin1_code":"25",
    "gn:asciiname":"Xiciyao",
    "gn:country_code":"CN",
    "gn:dem":120,
    "gn:feature_class":"P",
    "gn:feature_code":"PPL",
    "gn:name":"Xiciyao",
    "gn:population":0,
    "gn:timezone":"Asia/Shanghai",
    "iso:country":"CN",
    "name:zho_x_preferred":[
        "\u897f\u78c1\u7a91"
    ],
    "wof:name":"Xiciyao",
    "wof:placetype":"locality"
},
  "geometry": {"coordinates":[117.126,35.8901],"type":"Point"}
}