{
  "type": "Feature",
  "properties": {
    "gn:admin1_code":"9.0",
    "gn:asciiname":"Beimengwan",
    "gn:country_code":"CN",
    "gn:dem":76,
    "gn:feature_class":"P",
    "gn:feature_code":"PPL",
    "gn:name":"Beimengwan",
    "gn:population":0,
    "gn:timezone":"Asia/Shanghai",
    "iso:country":"CN",
    "name:zho_x_preferred":[
        "\u5317\u5b5f\u6e7e"
    ],
    "wof:name":"Beimengwan",
    "wof:placetype":"locality"
},
  "geometry": {"coordinates":[114.13181000000002,35.27200999999999],"type":"Point"}
}