{
  "type": "Feature",
  "properties": {
    "gn:admin1_code":"11",
    "gn:asciiname":"Suocheng",
    "gn:country_code":"CN",
    "gn:dem":421,
    "gn:feature_class":"P",
    "gn:feature_code":"PPLA4",
    "gn:name":"Suocheng",
    "gn:population":0,
    "gn:timezone":"Asia/Shanghai",
    "iso:country":"CN",
    "name:und_x_variant":[
        "So-ch\u2019eng",
        "Suocheng",
        "Suocheng Zhen",
        "\u6240\u57ce\u9547"
    ],
    "name:zho_x_preferred":[
        "\u6240\u57ce"
    ],
    "wof:name":"Suocheng",
    "wof:placetype":"locality"
},
  "geometry": {"coordinates":[112.14388999999998,25.2675],"type":"Point"}
}