{
  "type": "Feature",
  "properties": {
    "gn:admin1_code":"11.0",
    "gn:asciiname":"Yaojiatang",
    "gn:country_code":"CN",
    "gn:dem":59,
    "gn:feature_class":"P",
    "gn:feature_code":"PPL",
    "gn:name":"Yaojiatang",
    "gn:population":0,
    "gn:timezone":"Asia/Shanghai",
    "iso:country":"CN",
    "name:zho_x_preferred":[
        "\u5c27\u5bb6\u5858"
    ],
    "wof:name":"Yaojiatang",
    "wof:placetype":"locality"
},
  "geometry": {"coordinates":[112.71332,27.85406],"type":"Point"}
}