{
  "type": "Feature",
  "properties": {
    "gn:admin1_code":"8.0",
    "gn:asciiname":"Xinhecun",
    "gn:country_code":"CN",
    "gn:dem":70,
    "gn:feature_class":"P",
    "gn:feature_code":"PPL",
    "gn:name":"Xinhecun",
    "gn:population":0,
    "gn:timezone":"Asia/Shanghai",
    "iso:country":"CN",
    "name:zho_x_preferred":[
        "\u65b0\u5408\u6751"
    ],
    "wof:name":"Xinhecun",
    "wof:placetype":"locality"
},
  "geometry": {"coordinates":[131.36358000000001,46.91872],"type":"Point"}
}