{
  "type": "Feature",
  "properties": {
    "gn:admin1_code":"32.0",
    "gn:asciiname":"Haozi",
    "gn:country_code":"CN",
    "gn:dem":613,
    "gn:feature_class":"P",
    "gn:feature_code":"PPL",
    "gn:name":"Haozi",
    "gn:population":0,
    "gn:timezone":"Asia/Shanghai",
    "iso:country":"CN",
    "name:zho_x_preferred":[
        "\u8017\u5b50"
    ],
    "wof:name":"Haozi",
    "wof:placetype":"locality"
},
  "geometry": {"coordinates":[103.72199999999999,29.2889],"type":"Point"}
}