{
  "type": "Feature",
  "properties": {
    "gn:admin1_code":"26.0",
    "gn:asciiname":"Tuojiamaozi",
    "gn:country_code":"CN",
    "gn:dem":1215,
    "gn:feature_class":"P",
    "gn:feature_code":"PPL",
    "gn:name":"Tuojiamaozi",
    "gn:population":0,
    "gn:timezone":"Asia/Shanghai",
    "iso:country":"CN",
    "name:zho_x_preferred":[
        "\u62d3\u5bb6\u5cc1\u5b50"
    ],
    "wof:name":"Tuojiamaozi",
    "wof:placetype":"locality"
},
  "geometry": {"coordinates":[109.31261000000001,36.99455],"type":"Point"}
}