{
  "type": "Feature",
  "properties": {
    "gn:admin1_code":"14",
    "gn:asciiname":"Zhuopu",
    "gn:country_code":"CN",
    "gn:dem":4561,
    "gn:feature_class":"P",
    "gn:feature_code":"PPL",
    "gn:name":"Zhuopu",
    "gn:population":0,
    "gn:timezone":"Asia/Urumqi",
    "iso:country":"CN",
    "name:zho_x_preferred":[
        "\u5353\u666e"
    ],
    "wof:name":"Zhuopu",
    "wof:placetype":"locality"
},
  "geometry": {"coordinates":[89.38809999999999,28.8954],"type":"Point"}
}