{
  "type": "Feature",
  "properties": {
    "gn:admin1_code":"19",
    "gn:asciiname":"Yuanzhangzicun",
    "gn:country_code":"CN",
    "gn:dem":308,
    "gn:feature_class":"P",
    "gn:feature_code":"PPL",
    "gn:name":"Yuanzhangzicun",
    "gn:population":0,
    "gn:timezone":"Asia/Shanghai",
    "iso:country":"CN",
    "name:und_x_variant":[
        "Yuanzhangzi"
    ],
    "name:zho_x_preferred":[
        "\u82d1\u6756\u5b50\u6751"
    ],
    "wof:name":"Yuanzhangzicun",
    "wof:placetype":"locality"
},
  "geometry": {"coordinates":[119.88037,41.34182],"type":"Point"}
}