{
  "type": "Feature",
  "properties": {
    "gn:admin1_code":"32.0",
    "gn:asciiname":"Abuhuo",
    "gn:country_code":"CN",
    "gn:dem":2452,
    "gn:feature_class":"P",
    "gn:feature_code":"PPL",
    "gn:name":"Abuhuo",
    "gn:population":0,
    "gn:timezone":"Asia/Shanghai",
    "iso:country":"CN",
    "name:zho_x_preferred":[
        "\u963f\u5e03\u8c41"
    ],
    "wof:name":"Abuhuo",
    "wof:placetype":"locality"
},
  "geometry": {"coordinates":[103.137,27.6837],"type":"Point"}
}