{
  "type": "Feature",
  "properties": {
    "gn:admin1_code":"12.0",
    "gn:asciiname":"Shijiahe",
    "gn:country_code":"CN",
    "gn:dem":861,
    "gn:feature_class":"P",
    "gn:feature_code":"PPL",
    "gn:name":"Shijiahe",
    "gn:population":0,
    "gn:timezone":"Asia/Shanghai",
    "iso:country":"CN",
    "name:zho_x_preferred":[
        "\u77f3\u5bb6\u6cb3"
    ],
    "wof:name":"Shijiahe",
    "wof:placetype":"locality"
},
  "geometry": {"coordinates":[110.66736000000002,31.70567],"type":"Point"}
}