{
  "type": "Feature",
  "properties": {
    "gn:admin1_code":"16",
    "gn:asciiname":"Huangnigu",
    "gn:country_code":"CN",
    "gn:dem":227,
    "gn:feature_class":"P",
    "gn:feature_code":"PPL",
    "gn:name":"Huangnigu",
    "gn:population":0,
    "gn:timezone":"Asia/Shanghai",
    "iso:country":"CN",
    "name:zho_x_preferred":[
        "\u9ec4\u5c3c\u53e4"
    ],
    "wof:name":"Huangnigu",
    "wof:placetype":"locality"
},
  "geometry": {"coordinates":[110.74299999999999,25.7687],"type":"Point"}
}