{
  "type": "Feature",
  "properties": {
    "gn:admin1_code":"31.0",
    "gn:asciiname":"Jiaoding",
    "gn:country_code":"CN",
    "gn:dem":221,
    "gn:feature_class":"P",
    "gn:feature_code":"PPL",
    "gn:name":"Jiaoding",
    "gn:population":0,
    "gn:timezone":"Asia/Shanghai",
    "iso:country":"CN",
    "name:und_x_variant":[
        "\u811a\u9876"
    ],
    "wof:name":"Jiaoding",
    "wof:placetype":"locality"
},
  "geometry": {"coordinates":[109.27948000000001,18.64451],"type":"Point"}
}