{
  "type": "Feature",
  "properties": {
    "gn:admin1_code":"8.0",
    "gn:asciiname":"Liulancun",
    "gn:country_code":"CN",
    "gn:dem":110,
    "gn:feature_class":"P",
    "gn:feature_code":"PPL",
    "gn:name":"Liulancun",
    "gn:population":0,
    "gn:timezone":"Asia/Shanghai",
    "iso:country":"CN",
    "name:zho_x_preferred":[
        "\u67f3\u5170\u6751"
    ],
    "wof:name":"Liulancun",
    "wof:placetype":"locality"
},
  "geometry": {"coordinates":[133.86646000000002,47.00789],"type":"Point"}
}