{
  "type": "Feature",
  "properties": {
    "gn:admin1_code":"18",
    "gn:asciiname":"Tengqiaobian",
    "gn:country_code":"CN",
    "gn:dem":1446,
    "gn:feature_class":"P",
    "gn:feature_code":"PPL",
    "gn:name":"Tengqiaobian",
    "gn:population":0,
    "gn:timezone":"Asia/Shanghai",
    "iso:country":"CN",
    "name:zho_x_preferred":[
        "\u85e4\u6865\u8fb9"
    ],
    "wof:name":"Tengqiaobian",
    "wof:placetype":"locality"
},
  "geometry": {"coordinates":[105.08499999999999,26.8717],"type":"Point"}
}