{
  "type": "Feature",
  "properties": {
    "gn:admin1_code":"9",
    "gn:asciiname":"Lipaikou",
    "gn:country_code":"CN",
    "gn:dem":41,
    "gn:feature_class":"P",
    "gn:feature_code":"PPL",
    "gn:name":"Lipaikou",
    "gn:population":0,
    "gn:timezone":"Asia/Shanghai",
    "iso:country":"CN",
    "name:zho_x_preferred":[
        "\u674e\u724c\u53e3"
    ],
    "wof:name":"Lipaikou",
    "wof:placetype":"locality"
},
  "geometry": {"coordinates":[115.48099999999999,33.8092],"type":"Point"}
}