{
  "type": "Feature",
  "properties": {
    "gn:admin1_code":"26.0",
    "gn:asciiname":"Zhangshuikou",
    "gn:country_code":"CN",
    "gn:dem":1374,
    "gn:feature_class":"P",
    "gn:feature_code":"PPL",
    "gn:name":"Zhangshuikou",
    "gn:population":0,
    "gn:timezone":"Asia/Shanghai",
    "iso:country":"CN",
    "name:zho_x_preferred":[
        "\u5f20\u6c34\u53e3"
    ],
    "wof:name":"Zhangshuikou",
    "wof:placetype":"locality"
},
  "geometry": {"coordinates":[108.00376,36.90598],"type":"Point"}
}