{
  "type": "Feature",
  "properties": {
    "gn:admin1_code":"8.0",
    "gn:asciiname":"Shuanghe",
    "gn:country_code":"CN",
    "gn:dem":226,
    "gn:feature_class":"P",
    "gn:feature_code":"PPL",
    "gn:name":"Shuanghe",
    "gn:population":0,
    "gn:timezone":"Asia/Shanghai",
    "iso:country":"CN",
    "name:cdo_x_preferred":[
        "S\u0115\u0324ng-\u00f2\u0324"
    ],
    "name:deu_x_preferred":[
        "Shuanghe"
    ],
    "name:ell_x_preferred":[
        "\u03a3\u03bf\u03c5\u03b1\u03bd\u03b3\u03ba\u03c7\u03ad"
    ],
    "name:ita_x_preferred":[
        "Shuanghe"
    ],
    "name:jpn_x_preferred":[
        "\u53cc\u6cb3\u5e02"
    ],
    "name:kik_x_preferred":[
        "Shuanghe"
    ],
    "name:kor_x_preferred":[
        "\uc1bd\ud5c8\uc2dc"
    ],
    "name:rus_x_preferred":[
        "\u0428\u0443\u0430\u043d\u0445\u044d"
    ],
    "name:tur_x_preferred":[
        "Ko\u015f\u00f6k\u00fcz"
    ],
    "name:uig_x_preferred":[
        "\u0642\u0648\u0634\u0626\u06c6\u06af\u06c8\u0632 \u0634\u06d5\u06be\u0649\u0631\u0649"
    ],
    "name:urd_x_preferred":[
        "\u0634\u0648\u0627\u0646\u06af\u06c1\u06d2"
    ],
    "name:vie_x_preferred":[
        "Song H\u00e0"
    ],
    "name:zho_x_preferred":[
        "\u53cc\u5408"
    ],
    "name:zho_x_variant":[
        "\u96d9\u6cb3\u5e02"
    ],
    "wof:name":"Shuanghe",
    "wof:placetype":"locality"
},
  "geometry": {"coordinates":[125.89021,47.1361],"type":"Point"}
}