{
  "type": "Feature",
  "properties": {
    "gn:admin1_code":"5.0",
    "gn:asciiname":"Houyongsheng",
    "gn:country_code":"CN",
    "gn:dem":478,
    "gn:feature_class":"P",
    "gn:feature_code":"PPL",
    "gn:name":"Houyongsheng",
    "gn:population":0,
    "gn:timezone":"Asia/Shanghai",
    "iso:country":"CN",
    "name:und_x_variant":[
        "\u540e\u6c38\u80dc"
    ],
    "wof:name":"Houyongsheng",
    "wof:placetype":"locality"
},
  "geometry": {"coordinates":[130.27271999999999,43.84004],"type":"Point"}
}