{
  "type": "Feature",
  "properties": {
    "gn:admin1_code":"29.0",
    "gn:asciiname":"Jinhua",
    "gn:country_code":"CN",
    "gn:dem":2201,
    "gn:feature_class":"P",
    "gn:feature_code":"PPLA3",
    "gn:name":"Jinhua",
    "gn:population":0,
    "gn:timezone":"Asia/Shanghai",
    "iso:country":"CN",
    "name:und_x_variant":[
        "Jianchuan",
        "Kienchwan-hsien",
        "Kienchwanchow",
        "Jinhua"
    ],
    "name:zho_x_preferred":[
        "Chien-ch\u2019uan"
    ],
    "name:zho_x_variant":[
        "Chien-ch\u2019uan-hsien",
        "\u91d1\u534e"
    ],
    "wof:name":"Jinhua",
    "wof:placetype":"locality"
},
  "geometry": {"coordinates":[99.91715000000001,26.538],"type":"Point"}
}