{
  "type": "Feature",
  "properties": {
    "gn:admin1_code":"29.0",
    "gn:asciiname":"Jinhua",
    "gn:country_code":"CN",
    "gn:dem":2201,
    "gn:feature_class":"P",
    "gn:feature_code":"PPLA3",
    "gn:name":"Jinhua",
    "gn:population":0,
    "gn:timezone":"Asia/Shanghai",
    "iso:country":"CN",
    "name:afr_x_preferred":[
        "Jinhua"
    ],
    "name:ara_x_preferred":[
        "\u062c\u064a\u0646\u0647\u0648\u0627"
    ],
    "name:cdo_x_preferred":[
        "G\u012dng-hu\u00e0"
    ],
    "name:ceb_x_preferred":[
        "Jinhua"
    ],
    "name:ces_x_preferred":[
        "\u0164in-chua"
    ],
    "name:dan_x_preferred":[
        "Jinhua"
    ],
    "name:deu_x_preferred":[
        "Jinhua"
    ],
    "name:est_x_preferred":[
        "Jinhua"
    ],
    "name:eus_x_preferred":[
        "Jinhua"
    ],
    "name:fas_x_preferred":[
        "\u062c\u06cc\u0646\u0647\u0648\u0627"
    ],
    "name:fin_x_preferred":[
        "Jinhua"
    ],
    "name:fra_x_preferred":[
        "Jinhua"
    ],
    "name:hak_x_preferred":[
        "K\u00eem-f\u00e0-s\u1e73"
    ],
    "name:ind_x_preferred":[
        "Jinhua"
    ],
    "name:ita_x_preferred":[
        "Jinhua"
    ],
    "name:jpn_x_preferred":[
        "\u91d1\u83ef\u5e02"
    ],
    "name:kik_x_preferred":[
        "Jinhua"
    ],
    "name:kor_x_preferred":[
        "\uc9c4\ud654\uc2dc"
    ],
    "name:mlg_x_preferred":[
        "Jinhua"
    ],
    "name:nld_x_preferred":[
        "Jinhua"
    ],
    "name:nno_x_preferred":[
        "Jinhua"
    ],
    "name:nor_x_preferred":[
        "Jinhua"
    ],
    "name:pol_x_preferred":[
        "Jinhua"
    ],
    "name:rus_x_preferred":[
        "\u0426\u0437\u0438\u043d\u044c\u0445\u0443\u0430"
    ],
    "name:spa_x_preferred":[
        "Jinhua"
    ],
    "name:swe_x_preferred":[
        "Jinhua"
    ],
    "name:tgl_x_preferred":[
        "Jinhua"
    ],
    "name:tur_x_preferred":[
        "Jinhua"
    ],
    "name:und_x_variant":[
        "Jianchuan",
        "Kienchwan-hsien",
        "Kienchwanchow"
    ],
    "name:urd_x_preferred":[
        "\u062c\u0646\u06c1\u0648\u0627"
    ],
    "name:vie_x_preferred":[
        "Kim Hoa"
    ],
    "name:war_x_preferred":[
        "Jinhua"
    ],
    "name:wuu_x_preferred":[
        "\u91d1\u83ef\u5e02"
    ],
    "name:zho_x_preferred":[
        "Chien-ch\u2019uan"
    ],
    "name:zho_x_variant":[
        "Chien-ch\u2019uan-hsien",
        "\u91d1\u534e",
        "\u91d1\u534e\u5e02"
    ],
    "wof:name":"Jinhua",
    "wof:placetype":"locality"
},
  "geometry": {"coordinates":[99.91715000000001,26.538],"type":"Point"}
}