{
  "type": "Feature",
  "properties": {
    "gn:admin1_code":"4.0",
    "gn:asciiname":"Dongliuzhuang",
    "gn:country_code":"CN",
    "gn:dem":4,
    "gn:feature_class":"P",
    "gn:feature_code":"PPL",
    "gn:name":"Dongliuzhuang",
    "gn:population":0,
    "gn:timezone":"Asia/Shanghai",
    "iso:country":"CN",
    "name:zho_x_preferred":[
        "Dongliuzhuang"
    ],
    "name:zho_x_variant":[
        "\u4e1c\u5218\u5e84"
    ],
    "wof:name":"Dongliuzhuang",
    "wof:placetype":"locality"
},
  "geometry": {"coordinates":[119.87747,34.17471],"type":"Point"}
}