{
  "type": "Feature",
  "properties": {
    "gn:admin1_code":"11.0",
    "gn:asciiname":"Fengjiaping",
    "gn:country_code":"CN",
    "gn:dem":208,
    "gn:feature_class":"P",
    "gn:feature_code":"PPL",
    "gn:name":"Fengjiaping",
    "gn:population":0,
    "gn:timezone":"Asia/Shanghai",
    "iso:country":"CN",
    "name:zho_x_preferred":[
        "Fengjiaping"
    ],
    "name:zho_x_variant":[
        "\u51af\u5bb6\u576a"
    ],
    "wof:name":"Fengjiaping",
    "wof:placetype":"locality"
},
  "geometry": {"coordinates":[111.331,29.40897],"type":"Point"}
}