{
  "type": "Feature",
  "properties": {
    "gn:admin1_code":"19.0",
    "gn:asciiname":"Guandaogoucun",
    "gn:country_code":"CN",
    "gn:dem":188,
    "gn:feature_class":"P",
    "gn:feature_code":"PPL",
    "gn:name":"Guandaogoucun",
    "gn:population":0,
    "gn:timezone":"Asia/Shanghai",
    "iso:country":"CN",
    "name:zho_x_preferred":[
        "\u5b98\u9053\u6c9f\u6751"
    ],
    "wof:name":"Guandaogoucun",
    "wof:placetype":"locality"
},
  "geometry": {"coordinates":[125.09335,40.69745],"type":"Point"}
}