{
  "type": "Feature",
  "properties": {
    "gn:admin1_code":"24.0",
    "gn:asciiname":"Xiaoshan",
    "gn:cc2":"CN",
    "gn:country_code":"CN",
    "gn:dem":1003,
    "gn:feature_class":"P",
    "gn:feature_code":"PPL",
    "gn:name":"Xiaoshan",
    "gn:population":0,
    "gn:timezone":"Asia/Shanghai",
    "iso:country":"CN",
    "name:und_x_variant":[
        "Hsiao-shan-ts\u2019un",
        "Hsiao-shan",
        "Xiaoshan"
    ],
    "wof:name":"Xiaoshan",
    "wof:placetype":"locality"
},
  "geometry": {"coordinates":[110.96666999999999,38.43333],"type":"Point"}
}