{
  "type": "Feature",
  "properties": {
    "gn:admin1_code":"19.0",
    "gn:asciiname":"Banlashanzicun",
    "gn:country_code":"CN",
    "gn:dem":163,
    "gn:feature_class":"P",
    "gn:feature_code":"PPL",
    "gn:name":"Banlashanzicun",
    "gn:population":0,
    "gn:timezone":"Asia/Shanghai",
    "iso:country":"CN",
    "name:zho_x_preferred":[
        "\u534a\u62c9\u5c71\u5b50\u6751"
    ],
    "wof:name":"Banlashanzicun",
    "wof:placetype":"locality"
},
  "geometry": {"coordinates":[124.19799999999999,42.4064],"type":"Point"}
}