{
  "type": "Feature",
  "properties": {
    "gn:admin1_code":"11.0",
    "gn:asciiname":"Gaodoupo",
    "gn:country_code":"CN",
    "gn:dem":706,
    "gn:feature_class":"P",
    "gn:feature_code":"PPL",
    "gn:name":"Gaodoupo",
    "gn:population":0,
    "gn:timezone":"Asia/Shanghai",
    "iso:country":"CN",
    "name:zho_x_preferred":[
        "\u9ad8\u6597\u5761"
    ],
    "wof:name":"Gaodoupo",
    "wof:placetype":"locality"
},
  "geometry": {"coordinates":[109.55377,28.14675],"type":"Point"}
}