{
  "type": "Feature",
  "properties": {
    "gn:admin1_code":"4.0",
    "gn:asciiname":"Shijia Cangqiao",
    "gn:country_code":"CN",
    "gn:dem":4,
    "gn:feature_class":"P",
    "gn:feature_code":"PPL",
    "gn:name":"Shijia Cangqiao",
    "gn:population":0,
    "gn:timezone":"Asia/Shanghai",
    "iso:country":"CN",
    "name:zho_x_preferred":[
        "Shijia Cangqiao"
    ],
    "name:zho_x_variant":[
        "\u65bd\u5bb6\u4ed3\u6865"
    ],
    "wof:name":"Shijia Cangqiao",
    "wof:placetype":"locality"
},
  "geometry": {"coordinates":[121.46257,31.96003],"type":"Point"}
}