{
  "type": "Feature",
  "properties": {
    "gn:admin1_code":"10",
    "gn:asciiname":"Boluotai",
    "gn:country_code":"CN",
    "gn:dem":256,
    "gn:feature_class":"P",
    "gn:feature_code":"PPL",
    "gn:name":"Boluotai",
    "gn:population":0,
    "gn:timezone":"Asia/Shanghai",
    "iso:country":"CN",
    "name:zho_x_preferred":[
        "\u6872\u6924\u53f0"
    ],
    "wof:name":"Boluotai",
    "wof:placetype":"locality"
},
  "geometry": {"coordinates":[117.9567,40.37706],"type":"Point"}
}