{
  "type": "Feature",
  "properties": {
    "gn:admin1_code":"32.0",
    "gn:asciiname":"Huguosi",
    "gn:country_code":"CN",
    "gn:dem":558,
    "gn:feature_class":"P",
    "gn:feature_code":"PPL",
    "gn:name":"Huguosi",
    "gn:population":0,
    "gn:timezone":"Asia/Shanghai",
    "iso:country":"CN",
    "name:zho_x_preferred":[
        "\u62a4\u56fd\u5bfa"
    ],
    "wof:name":"Huguosi",
    "wof:placetype":"locality"
},
  "geometry": {"coordinates":[103.90492999999999,30.82797],"type":"Point"}
}