{
  "type": "Feature",
  "properties": {
    "gn:admin1_code":"2.0",
    "gn:asciiname":"Xizhang",
    "gn:country_code":"CN",
    "gn:dem":98,
    "gn:feature_class":"P",
    "gn:feature_code":"PPL",
    "gn:name":"Xizhang",
    "gn:population":0,
    "gn:timezone":"Asia/Shanghai",
    "iso:country":"CN",
    "name:und_x_variant":[
        "\u897f\u5f20",
        "Xizhang"
    ],
    "wof:name":"Xizhang",
    "wof:placetype":"locality"
},
  "geometry": {"coordinates":[119.92643,29.41367],"type":"Point"}
}