{
  "type": "Feature",
  "properties": {
    "gn:admin1_code":"32.0",
    "gn:asciiname":"Changwujian",
    "gn:country_code":"CN",
    "gn:dem":320,
    "gn:feature_class":"P",
    "gn:feature_code":"PPL",
    "gn:name":"Changwujian",
    "gn:population":0,
    "gn:timezone":"Asia/Shanghai",
    "iso:country":"CN",
    "name:zho_x_preferred":[
        "\u957f\u4e94\u95f4"
    ],
    "wof:name":"Changwujian",
    "wof:placetype":"locality"
},
  "geometry": {"coordinates":[104.901,29.1635],"type":"Point"}
}