{
  "type": "Feature",
  "properties": {
    "gn:admin1_code":"20",
    "gn:asciiname":"San-chia-pei-kou",
    "gn:country_code":"CN",
    "gn:dem":819,
    "gn:feature_class":"P",
    "gn:feature_code":"PPL",
    "gn:name":"San-chia-pei-kou",
    "gn:population":0,
    "gn:timezone":"Asia/Shanghai",
    "iso:country":"CN",
    "wof:name":"San-chia-pei-kou",
    "wof:placetype":"locality"
},
  "geometry": {"coordinates":[119.01582999999999,42.57167000000001],"type":"Point"}
}