{
  "type": "Feature",
  "properties": {
    "gn:admin1_code":"19.0",
    "gn:asciiname":"Zhangjiayaocun",
    "gn:country_code":"CN",
    "gn:dem":320,
    "gn:feature_class":"P",
    "gn:feature_code":"PPL",
    "gn:name":"Zhangjiayaocun",
    "gn:population":0,
    "gn:timezone":"Asia/Shanghai",
    "iso:country":"CN",
    "name:zho_x_preferred":[
        "\u5f20\u5bb6\u7a91\u6751"
    ],
    "wof:name":"Zhangjiayaocun",
    "wof:placetype":"locality"
},
  "geometry": {"coordinates":[119.60878,41.11627],"type":"Point"}
}