{
  "type": "Feature",
  "properties": {
    "gn:admin1_code":"1.0",
    "gn:asciiname":"Yaoxucun",
    "gn:country_code":"CN",
    "gn:dem":32,
    "gn:feature_class":"P",
    "gn:feature_code":"PPL",
    "gn:name":"Yaoxucun",
    "gn:population":0,
    "gn:timezone":"Asia/Shanghai",
    "iso:country":"CN",
    "name:zho_x_preferred":[
        "\u59da\u5729\u6751"
    ],
    "wof:name":"Yaoxucun",
    "wof:placetype":"locality"
},
  "geometry": {"coordinates":[116.28304,30.25295],"type":"Point"}
}