{
  "type": "Feature",
  "properties": {
    "gn:admin1_code":"32.0",
    "gn:asciiname":"Wunanbian",
    "gn:country_code":"CN",
    "gn:dem":360,
    "gn:feature_class":"P",
    "gn:feature_code":"PPL",
    "gn:name":"Wunanbian",
    "gn:population":0,
    "gn:timezone":"Asia/Shanghai",
    "iso:country":"CN",
    "name:zho_x_preferred":[
        "\u6b66\u5357\u78a5"
    ],
    "wof:name":"Wunanbian",
    "wof:placetype":"locality"
},
  "geometry": {"coordinates":[105.29234,30.94323],"type":"Point"}
}