{
  "type": "Feature",
  "properties": {
    "gn:admin1_code":"12.0",
    "gn:asciiname":"Ludichong",
    "gn:country_code":"CN",
    "gn:dem":656,
    "gn:feature_class":"P",
    "gn:feature_code":"PPL",
    "gn:name":"Ludichong",
    "gn:population":0,
    "gn:timezone":"Asia/Shanghai",
    "iso:country":"CN",
    "name:zho_x_preferred":[
        "Ludichong"
    ],
    "name:zho_x_variant":[
        "\u82a6\u837b\u51b2"
    ],
    "wof:name":"Ludichong",
    "wof:placetype":"locality"
},
  "geometry": {"coordinates":[111.10684000000001,30.26493],"type":"Point"}
}