{
  "type": "Feature",
  "properties": {
    "gn:admin1_code":"32.0",
    "gn:asciiname":"Shiyuan Bazi",
    "gn:country_code":"CN",
    "gn:dem":524,
    "gn:feature_class":"P",
    "gn:feature_code":"PPL",
    "gn:name":"Shiyuan Bazi",
    "gn:population":0,
    "gn:timezone":"Asia/Shanghai",
    "iso:country":"CN",
    "name:zho_x_preferred":[
        "\u77f3\u9662\u575d\u5b50"
    ],
    "wof:name":"Shiyuan Bazi",
    "wof:placetype":"locality"
},
  "geometry": {"coordinates":[104.69499999999999,31.5895],"type":"Point"}
}