{
  "type": "Feature",
  "properties": {
    "gn:admin1_code":"0.0",
    "gn:asciiname":"Nan-ching-wa",
    "gn:country_code":"CN",
    "gn:dem":1431,
    "gn:feature_class":"P",
    "gn:feature_code":"PPL",
    "gn:name":"Nan-ching-wa",
    "gn:population":0,
    "gn:timezone":"Asia/Shanghai",
    "iso:country":"CN",
    "wof:name":"Nan-ching-wa",
    "wof:placetype":"locality"
},
  "geometry": {"coordinates":[100.03973000000001,22.7862],"type":"Point"}
}