{
  "type": "Feature",
  "properties": {
    "gn:admin1_code":"2.0",
    "gn:asciiname":"Xianiqiao",
    "gn:country_code":"CN",
    "gn:dem":842,
    "gn:feature_class":"P",
    "gn:feature_code":"PPL",
    "gn:name":"Xianiqiao",
    "gn:population":0,
    "gn:timezone":"Asia/Shanghai",
    "iso:country":"CN",
    "name:zho_x_preferred":[
        "\u4e0b\u502a\u6865"
    ],
    "wof:name":"Xianiqiao",
    "wof:placetype":"locality"
},
  "geometry": {"coordinates":[119.91334000000001,27.49129000000001],"type":"Point"}
}