{
  "type": "Feature",
  "properties": {
    "gn:admin1_code":"26.0",
    "gn:asciiname":"Xiaochuancun",
    "gn:country_code":"CN",
    "gn:dem":745,
    "gn:feature_class":"P",
    "gn:feature_code":"PPL",
    "gn:name":"Xiaochuancun",
    "gn:population":0,
    "gn:timezone":"Asia/Shanghai",
    "iso:country":"CN",
    "name:und_x_variant":[
        "Hsiao-ch\u2019uan",
        "Xiaochuanjie",
        "Hsiao-ch\u2019uan-chieh",
        "Xiaochuan",
        "Xiaochuancun"
    ],
    "name:zho_x_preferred":[
        "\u5c0f\u5ddd\u6751"
    ],
    "wof:name":"Xiaochuancun",
    "wof:placetype":"locality"
},
  "geometry": {"coordinates":[108.7625,33.57167],"type":"Point"}
}