{
  "type": "Feature",
  "properties": {
    "gn:admin1_code":"5.0",
    "gn:asciiname":"Malugou",
    "gn:country_code":"CN",
    "gn:dem":296,
    "gn:feature_class":"P",
    "gn:feature_code":"PPL",
    "gn:name":"Malugou",
    "gn:population":0,
    "gn:timezone":"Asia/Shanghai",
    "iso:country":"CN",
    "name:und_x_variant":[
        "\u9a6c\u9e7f\u6c9f"
    ],
    "wof:name":"Malugou",
    "wof:placetype":"locality"
},
  "geometry": {"coordinates":[129.25128999999998,42.82396],"type":"Point"}
}