{
  "type": "Feature",
  "properties": {
    "gn:admin1_code":"29",
    "gn:asciiname":"Longping",
    "gn:country_code":"CN",
    "gn:dem":1276,
    "gn:feature_class":"P",
    "gn:feature_code":"PPL",
    "gn:name":"Longping",
    "gn:population":0,
    "gn:timezone":"Asia/Shanghai",
    "iso:country":"CN",
    "name:zho_x_preferred":[
        "\u9f99\u5e73"
    ],
    "wof:name":"Longping",
    "wof:placetype":"locality"
},
  "geometry": {"coordinates":[105.73099999999999,23.4828],"type":"Point"}
}