{
  "type": "Feature",
  "properties": {
    "gn:admin1_code":"25",
    "gn:asciiname":"Lizhangcun",
    "gn:country_code":"CN",
    "gn:dem":72,
    "gn:feature_class":"P",
    "gn:feature_code":"PPL",
    "gn:name":"Lizhangcun",
    "gn:population":0,
    "gn:timezone":"Asia/Shanghai",
    "iso:country":"CN",
    "name:und_x_variant":[
        "Lizhang",
        "Lizhangcun"
    ],
    "name:zho_x_preferred":[
        "\u91cc\u4e08"
    ],
    "name:zho_x_variant":[
        "\u91cc\u4e08\u6751"
    ],
    "wof:name":"Lizhangcun",
    "wof:placetype":"locality"
},
  "geometry": {"coordinates":[119.22648,36.19519],"type":"Point"}
}