{
  "type": "Feature",
  "properties": {
    "gn:admin1_code":"25",
    "gn:asciiname":"Dongyujia",
    "gn:country_code":"CN",
    "gn:dem":130,
    "gn:feature_class":"P",
    "gn:feature_code":"PPL",
    "gn:name":"Dongyujia",
    "gn:population":0,
    "gn:timezone":"Asia/Shanghai",
    "iso:country":"CN",
    "name:zho_x_preferred":[
        "\u4e1c\u4e8e\u5bb6"
    ],
    "wof:name":"Dongyujia",
    "wof:placetype":"locality"
},
  "geometry": {"coordinates":[121.429,37.2268],"type":"Point"}
}