{
  "type": "Feature",
  "properties": {
    "gn:admin1_code":"16.0",
    "gn:asciiname":"Dusongbai",
    "gn:country_code":"CN",
    "gn:dem":37,
    "gn:feature_class":"P",
    "gn:feature_code":"PPL",
    "gn:name":"Dusongbai",
    "gn:population":0,
    "gn:timezone":"Asia/Shanghai",
    "iso:country":"CN",
    "name:zho_x_preferred":[
        "\u72ec\u677e\u67cf"
    ],
    "wof:name":"Dusongbai",
    "wof:placetype":"locality"
},
  "geometry": {"coordinates":[109.021,21.8209],"type":"Point"}
}