{
  "type": "Feature",
  "properties": {
    "gn:admin1_code":"16.0",
    "gn:asciiname":"Kuli'ao",
    "gn:country_code":"CN",
    "gn:dem":804,
    "gn:feature_class":"P",
    "gn:feature_code":"PPL",
    "gn:name":"Kuli\u2019ao",
    "gn:population":0,
    "gn:timezone":"Asia/Shanghai",
    "iso:country":"CN",
    "name:und_x_variant":[
        "Kuli\u2019ao"
    ],
    "name:zho_x_preferred":[
        "\u82e6\u674e\u5773"
    ],
    "wof:name":"Kuli'ao",
    "wof:placetype":"locality"
},
  "geometry": {"coordinates":[107.697,24.9823],"type":"Point"}
}