{
  "type": "Feature",
  "properties": {
    "gn:admin1_code":"19.0",
    "gn:asciiname":"Badaolingcun",
    "gn:country_code":"CN",
    "gn:dem":138,
    "gn:feature_class":"P",
    "gn:feature_code":"PPL",
    "gn:name":"Badaolingcun",
    "gn:population":0,
    "gn:timezone":"Asia/Shanghai",
    "iso:country":"CN",
    "name:zho_x_preferred":[
        "\u516b\u9053\u5cad\u6751"
    ],
    "wof:name":"Badaolingcun",
    "wof:placetype":"locality"
},
  "geometry": {"coordinates":[122.985,39.9859],"type":"Point"}
}