{
  "type": "Feature",
  "properties": {
    "gn:admin1_code":"32.0",
    "gn:asciiname":"Chaipo",
    "gn:country_code":"CN",
    "gn:dem":851,
    "gn:feature_class":"P",
    "gn:feature_code":"PPL",
    "gn:name":"Chaipo",
    "gn:population":0,
    "gn:timezone":"Asia/Shanghai",
    "iso:country":"CN",
    "name:und_x_variant":[
        "\u67f4\u5761"
    ],
    "wof:name":"Chaipo",
    "wof:placetype":"locality"
},
  "geometry": {"coordinates":[106.29364,32.04187],"type":"Point"}
}