{
  "type": "Feature",
  "properties": {
    "gn:admin1_code":"10.0",
    "gn:asciiname":"Ransanjiao",
    "gn:country_code":"CN",
    "gn:dem":23,
    "gn:feature_class":"P",
    "gn:feature_code":"PPL",
    "gn:name":"Ransanjiao",
    "gn:population":0,
    "gn:timezone":"Asia/Shanghai",
    "iso:country":"CN",
    "name:zho_x_preferred":[
        "\u5189\u4e09\u89d2"
    ],
    "wof:name":"Ransanjiao",
    "wof:placetype":"locality"
},
  "geometry": {"coordinates":[115.884,38.2363],"type":"Point"}
}