{
  "type": "Feature",
  "properties": {
    "gn:admin1_code":"1.0",
    "gn:asciiname":"Songshengcun",
    "gn:country_code":"CN",
    "gn:dem":64,
    "gn:feature_class":"P",
    "gn:feature_code":"PPL",
    "gn:name":"Songshengcun",
    "gn:population":0,
    "gn:timezone":"Asia/Shanghai",
    "iso:country":"CN",
    "name:zho_x_preferred":[
        "\u5b8b\u76db\u6751"
    ],
    "wof:name":"Songshengcun",
    "wof:placetype":"locality"
},
  "geometry": {"coordinates":[117.64936000000002,32.19777],"type":"Point"}
}