{
  "type": "Feature",
  "properties": {
    "gn:admin1_code":"25",
    "gn:asciiname":"Dongba",
    "gn:country_code":"CN",
    "gn:dem":8,
    "gn:feature_class":"P",
    "gn:feature_code":"PPL",
    "gn:name":"Dongba",
    "gn:population":0,
    "gn:timezone":"Asia/Shanghai",
    "iso:country":"CN",
    "name:deu_x_preferred":[
        "Dongba"
    ],
    "name:fra_x_preferred":[
        "Dongba"
    ],
    "name:ita_x_preferred":[
        "Dongba"
    ],
    "name:pol_x_preferred":[
        "Dongba"
    ],
    "name:por_x_preferred":[
        "Dongba"
    ],
    "name:tha_x_preferred":[
        "\u0e25\u0e31\u0e17\u0e18\u0e34\u0e15\u0e07\u0e1b\u0e32"
    ],
    "name:vie_x_preferred":[
        "Dongba"
    ],
    "name:zho_x_preferred":[
        "\u4e1c\u575d"
    ],
    "name:zho_x_variant":[
        "\u6771\u5df4\u6559"
    ],
    "wof:name":"Dongba",
    "wof:placetype":"locality"
},
  "geometry": {"coordinates":[118.44199999999999,37.6382],"type":"Point"}
}