{
  "type": "Feature",
  "properties": {
    "gn:admin1_code":"29.0",
    "gn:asciiname":"Ganhaizi Dacun",
    "gn:country_code":"CN",
    "gn:dem":2208,
    "gn:feature_class":"P",
    "gn:feature_code":"PPL",
    "gn:name":"Ganhaizi Dacun",
    "gn:population":0,
    "gn:timezone":"Asia/Shanghai",
    "iso:country":"CN",
    "name:zho_x_preferred":[
        "\u5e72\u6d77\u5b50\u5927\u6751"
    ],
    "wof:name":"Ganhaizi Dacun",
    "wof:placetype":"locality"
},
  "geometry": {"coordinates":[102.137,25.6601],"type":"Point"}
}