{
  "type": "Feature",
  "properties": {
    "gn:admin1_code":"26.0",
    "gn:asciiname":"Libaisi",
    "gn:country_code":"CN",
    "gn:dem":1463,
    "gn:feature_class":"P",
    "gn:feature_code":"PPL",
    "gn:name":"Libaisi",
    "gn:population":0,
    "gn:timezone":"Asia/Shanghai",
    "iso:country":"CN",
    "name:zho_x_preferred":[
        "\u674e\u62dc\u5bfa"
    ],
    "wof:name":"Libaisi",
    "wof:placetype":"locality"
},
  "geometry": {"coordinates":[108.35266,36.91633],"type":"Point"}
}