{
  "type": "Feature",
  "properties": {
    "gn:admin1_code":"1.0",
    "gn:asciiname":"Songqiaocun",
    "gn:country_code":"CN",
    "gn:dem":46,
    "gn:feature_class":"P",
    "gn:feature_code":"PPL",
    "gn:name":"Songqiaocun",
    "gn:population":0,
    "gn:timezone":"Asia/Shanghai",
    "iso:country":"CN",
    "name:zho_x_preferred":[
        "\u5b8b\u6865\u6751"
    ],
    "wof:name":"Songqiaocun",
    "wof:placetype":"locality"
},
  "geometry": {"coordinates":[116.26322999999999,32.21899000000001],"type":"Point"}
}