{
  "type": "Feature",
  "properties": {
    "gn:admin1_code":"16",
    "gn:asciiname":"Yatoushui",
    "gn:country_code":"CN",
    "gn:dem":886,
    "gn:feature_class":"P",
    "gn:feature_code":"PPL",
    "gn:name":"Yatoushui",
    "gn:population":0,
    "gn:timezone":"Asia/Shanghai",
    "iso:country":"CN",
    "name:zho_x_preferred":[
        "\u9e2d\u5934\u6c34"
    ],
    "wof:name":"Yatoushui",
    "wof:placetype":"locality"
},
  "geometry": {"coordinates":[110.52800000000001,26.099],"type":"Point"}
}