{
  "type": "Feature",
  "properties": {
    "gn:admin1_code":"21.0",
    "gn:asciiname":"Xuegouyang",
    "gn:country_code":"CN",
    "gn:dem":1862,
    "gn:feature_class":"P",
    "gn:feature_code":"PPL",
    "gn:name":"Xuegouyang",
    "gn:population":0,
    "gn:timezone":"Asia/Shanghai",
    "iso:country":"CN",
    "name:zho_x_preferred":[
        "\u5b66\u6c9f\u6768"
    ],
    "wof:name":"Xuegouyang",
    "wof:placetype":"locality"
},
  "geometry": {"coordinates":[105.6896,35.74357],"type":"Point"}
}