{
  "type": "Feature",
  "properties": {
    "gn:admin1_code":"26",
    "gn:asciiname":"Nanliangcun",
    "gn:country_code":"CN",
    "gn:dem":373,
    "gn:feature_class":"P",
    "gn:feature_code":"PPL",
    "gn:name":"Nanliangcun",
    "gn:population":0,
    "gn:timezone":"Asia/Shanghai",
    "iso:country":"CN",
    "name:zho_x_preferred":[
        "\u5357\u6881\u6751"
    ],
    "wof:name":"Nanliangcun",
    "wof:placetype":"locality"
},
  "geometry": {"coordinates":[109.40697,34.69492],"type":"Point"}
}