{
  "type": "Feature",
  "properties": {
    "gn:admin1_code":"19.0",
    "gn:asciiname":"Haizhouwobao",
    "gn:country_code":"CN",
    "gn:dem":105,
    "gn:feature_class":"P",
    "gn:feature_code":"PPLA4",
    "gn:name":"Haizhouwobao",
    "gn:population":0,
    "gn:timezone":"Asia/Shanghai",
    "iso:country":"CN",
    "name:und_x_variant":[
        "Haizhouwobao Xiang",
        "Haizhouwobao"
    ],
    "name:zho_x_preferred":[
        "\u6d77\u5dde\u7a9d\u5821"
    ],
    "name:zho_x_variant":[
        "\u6d77\u5dde\u7a9d\u5821\u4e61"
    ],
    "wof:name":"Haizhouwobao",
    "wof:placetype":"locality"
},
  "geometry": {"coordinates":[123.37081000000001,42.93823],"type":"Point"}
}