{
  "type": "Feature",
  "properties": {
    "gn:admin1_code":"10",
    "gn:asciiname":"Sidaowanzi",
    "gn:country_code":"CN",
    "gn:dem":1082,
    "gn:feature_class":"P",
    "gn:feature_code":"PPL",
    "gn:name":"Sidaowanzi",
    "gn:population":0,
    "gn:timezone":"Asia/Shanghai",
    "iso:country":"CN",
    "name:zho_x_preferred":[
        "\u56db\u9053\u6e7e\u5b50"
    ],
    "wof:name":"Sidaowanzi",
    "wof:placetype":"locality"
},
  "geometry": {"coordinates":[117.50601,41.97583],"type":"Point"}
}