{
  "type": "Feature",
  "properties": {
    "gn:admin1_code":"4.0",
    "gn:asciiname":"Sizhou",
    "gn:country_code":"CN",
    "gn:dem":7,
    "gn:feature_class":"P",
    "gn:feature_code":"PPL",
    "gn:name":"Sizhou",
    "gn:population":0,
    "gn:timezone":"Asia/Shanghai",
    "iso:country":"CN",
    "name:und_x_variant":[
        "Anzhou"
    ],
    "name:zho_x_preferred":[
        "\u6cd7\u6d32"
    ],
    "name:zho_x_variant":[
        "\u5b89\u6d32"
    ],
    "wof:name":"Sizhou",
    "wof:placetype":"locality"
},
  "geometry": {"coordinates":[119.75122,32.91095],"type":"Point"}
}