{
  "type": "Feature",
  "properties": {
    "gn:admin1_code":"31.0",
    "gn:asciiname":"Gaoshanling",
    "gn:country_code":"CN",
    "gn:dem":60,
    "gn:feature_class":"P",
    "gn:feature_code":"PPL",
    "gn:name":"Gaoshanling",
    "gn:population":0,
    "gn:timezone":"Asia/Shanghai",
    "iso:country":"CN",
    "name:und_x_variant":[
        "\u9ad8\u5c71\u5cad"
    ],
    "wof:name":"Gaoshanling",
    "wof:placetype":"locality"
},
  "geometry": {"coordinates":[110.55106000000001,19.38621],"type":"Point"}
}