{
  "type": "Feature",
  "properties": {
    "gn:admin1_code":"0.0",
    "gn:asciiname":"Xixi",
    "gn:country_code":"CN",
    "gn:dem":1778,
    "gn:feature_class":"P",
    "gn:feature_code":"PPL",
    "gn:name":"Xixi",
    "gn:population":0,
    "gn:timezone":"Asia/Shanghai",
    "iso:country":"CN",
    "name:ceb_x_preferred":[
        "Xixi"
    ],
    "name:deu_x_preferred":[
        "Xixi"
    ],
    "name:swe_x_preferred":[
        "Xixi"
    ],
    "name:zho_x_preferred":[
        "\u897f\u6eaa"
    ],
    "wof:name":"Xixi",
    "wof:placetype":"locality"
},
  "geometry": {"coordinates":[102.55028,29.60102],"type":"Point"}
}