{
  "type": "Feature",
  "properties": {
    "gn:admin1_code":"26.0",
    "gn:asciiname":"Xiaojieze Daoban",
    "gn:country_code":"CN",
    "gn:dem":1272,
    "gn:feature_class":"P",
    "gn:feature_code":"PPL",
    "gn:name":"Xiaojieze Daoban",
    "gn:population":0,
    "gn:timezone":"Asia/Shanghai",
    "iso:country":"CN",
    "name:zho_x_preferred":[
        "\u5c0f\u754c\u5219\u9053\u73ed"
    ],
    "wof:name":"Xiaojieze Daoban",
    "wof:placetype":"locality"
},
  "geometry": {"coordinates":[109.242,37.7187],"type":"Point"}
}