{
  "type": "Feature",
  "properties": {
    "gn:admin1_code":"30",
    "gn:asciiname":"Zhukehu",
    "gn:country_code":"CN",
    "gn:dem":42,
    "gn:feature_class":"P",
    "gn:feature_code":"PPL",
    "gn:name":"Zhukehu",
    "gn:population":0,
    "gn:timezone":"Asia/Shanghai",
    "iso:country":"CN",
    "name:zho_x_preferred":[
        "\u7af9\u58f3\u6e56"
    ],
    "wof:name":"Zhukehu",
    "wof:placetype":"locality"
},
  "geometry": {"coordinates":[111.86353,22.42495],"type":"Point"}
}