{
  "type": "Feature",
  "properties": {
    "gn:admin1_code":"5.0",
    "gn:asciiname":"Jiayi",
    "gn:country_code":"CN",
    "gn:dem":320,
    "gn:feature_class":"P",
    "gn:feature_code":"PPL",
    "gn:name":"Jiayi",
    "gn:population":0,
    "gn:timezone":"Asia/Shanghai",
    "iso:country":"CN",
    "name:und_x_variant":[
        "\u7532\u4e59"
    ],
    "wof:name":"Jiayi",
    "wof:placetype":"locality"
},
  "geometry": {"coordinates":[125.65461999999999,41.36379],"type":"Point"}
}