{
  "type": "Feature",
  "properties": {
    "gn:admin1_code":"25",
    "gn:asciiname":"Ningjia",
    "gn:country_code":"CN",
    "gn:dem":148,
    "gn:feature_class":"P",
    "gn:feature_code":"PPL",
    "gn:name":"Ningjia",
    "gn:population":0,
    "gn:timezone":"Asia/Shanghai",
    "iso:country":"CN",
    "name:zho_x_preferred":[
        "\u5b81\u5bb6"
    ],
    "wof:name":"Ningjia",
    "wof:placetype":"locality"
},
  "geometry": {"coordinates":[116.995,35.8302],"type":"Point"}
}