{
  "type": "Feature",
  "properties": {
    "gn:admin1_code":"8.0",
    "gn:asciiname":"Sentie Jingyingdian",
    "gn:country_code":"CN",
    "gn:dem":302,
    "gn:feature_class":"P",
    "gn:feature_code":"PPL",
    "gn:name":"Sentie Jingyingdian",
    "gn:population":0,
    "gn:timezone":"Asia/Shanghai",
    "iso:country":"CN",
    "name:und_x_variant":[
        "\u68ee\u94c1\u7ecf\u8425\u70b9"
    ],
    "wof:name":"Sentie Jingyingdian",
    "wof:placetype":"locality"
},
  "geometry": {"coordinates":[130.72357,44.20849000000001],"type":"Point"}
}