{
  "type": "Feature",
  "properties": {
    "gn:admin1_code":"3.0",
    "gn:asciiname":"Liaojia",
    "gn:country_code":"CN",
    "gn:dem":335,
    "gn:feature_class":"P",
    "gn:feature_code":"PPL",
    "gn:name":"Liaojia",
    "gn:population":0,
    "gn:timezone":"Asia/Shanghai",
    "iso:country":"CN",
    "name:und_x_variant":[
        "\u5ed6\u5bb6"
    ],
    "wof:name":"Liaojia",
    "wof:placetype":"locality"
},
  "geometry": {"coordinates":[115.93853,27.58715],"type":"Point"}
}