{
  "type": "Feature",
  "properties": {
    "gn:admin1_code":"18",
    "gn:asciiname":"Anichong",
    "gn:country_code":"CN",
    "gn:dem":2021,
    "gn:feature_class":"P",
    "gn:feature_code":"PPL",
    "gn:name":"Anichong",
    "gn:population":0,
    "gn:timezone":"Asia/Shanghai",
    "iso:country":"CN",
    "name:zho_x_preferred":[
        "\u963f\u6ce5\u51b2"
    ],
    "wof:name":"Anichong",
    "wof:placetype":"locality"
},
  "geometry": {"coordinates":[104.777,26.4233],"type":"Point"}
}