{
  "type": "Feature",
  "properties": {
    "gn:admin1_code":"15.0",
    "gn:asciiname":"Daocang",
    "gn:country_code":"CN",
    "gn:dem":2715,
    "gn:feature_class":"P",
    "gn:feature_code":"PPL",
    "gn:name":"Daocang",
    "gn:population":0,
    "gn:timezone":"Asia/Shanghai",
    "iso:country":"CN",
    "name:und_x_variant":[
        "\u9053\u85cf"
    ],
    "name:zho_x_preferred":[
        "\u9053\u85cf"
    ],
    "wof:name":"Daocang",
    "wof:placetype":"locality"
},
  "geometry": {"coordinates":[103.83087999999999,34.02778],"type":"Point"}
}