{
  "type": "Feature",
  "properties": {
    "gn:admin1_code":"19.0",
    "gn:asciiname":"Yangjiawopu",
    "gn:country_code":"CN",
    "gn:dem":379,
    "gn:feature_class":"P",
    "gn:feature_code":"PPL",
    "gn:name":"Yangjiawopu",
    "gn:population":0,
    "gn:timezone":"Asia/Shanghai",
    "iso:country":"CN",
    "name:zho_x_preferred":[
        "\u6768\u5bb6\u7a9d\u94fa"
    ],
    "wof:name":"Yangjiawopu",
    "wof:placetype":"locality"
},
  "geometry": {"coordinates":[121.73699999999999,42.2384],"type":"Point"}
}