{
  "type": "Feature",
  "properties": {
    "gn:admin1_code":"11.0",
    "gn:asciiname":"Laodukou",
    "gn:country_code":"CN",
    "gn:dem":35,
    "gn:feature_class":"P",
    "gn:feature_code":"PPL",
    "gn:name":"Laodukou",
    "gn:population":0,
    "gn:timezone":"Asia/Shanghai",
    "iso:country":"CN",
    "name:zho_x_preferred":[
        "Laodukou"
    ],
    "name:zho_x_variant":[
        "\u8001\u6e21\u53e3"
    ],
    "wof:name":"Laodukou",
    "wof:placetype":"locality"
},
  "geometry": {"coordinates":[111.7998,28.91965],"type":"Point"}
}