{
  "type": "Feature",
  "properties": {
    "gn:admin1_code":"5.0",
    "gn:asciiname":"Gangyaotun",
    "gn:country_code":"CN",
    "gn:dem":301,
    "gn:feature_class":"P",
    "gn:feature_code":"PPL",
    "gn:name":"Gangyaotun",
    "gn:population":0,
    "gn:timezone":"Asia/Shanghai",
    "iso:country":"CN",
    "name:zho_x_preferred":[
        "\u7f38\u7a91\u5c6f"
    ],
    "wof:name":"Gangyaotun",
    "wof:placetype":"locality"
},
  "geometry": {"coordinates":[125.46075999999999,43.2666],"type":"Point"}
}