{
  "type": "Feature",
  "properties": {
    "gn:admin1_code":"18",
    "gn:asciiname":"Maweigou",
    "gn:country_code":"CN",
    "gn:dem":924,
    "gn:feature_class":"P",
    "gn:feature_code":"PPL",
    "gn:name":"Maweigou",
    "gn:population":0,
    "gn:timezone":"Asia/Shanghai",
    "iso:country":"CN",
    "name:zho_x_preferred":[
        "\u9a6c\u5c3e\u6c9f"
    ],
    "wof:name":"Maweigou",
    "wof:placetype":"locality"
},
  "geometry": {"coordinates":[106.947,27.4342],"type":"Point"}
}