{
  "type": "Feature",
  "properties": {
    "gn:admin1_code":"4.0",
    "gn:asciiname":"Xinmin Liuzu",
    "gn:country_code":"CN",
    "gn:dem":3,
    "gn:feature_class":"P",
    "gn:feature_code":"PPLF",
    "gn:name":"Xinmin Liuzu",
    "gn:population":0,
    "gn:timezone":"Asia/Shanghai",
    "iso:country":"CN",
    "name:und_x_variant":[
        "\u65b0\u6c11\u516d\u7ec4"
    ],
    "name:zho_x_preferred":[
        "\u65b0\u6c11\u516d\u7ec4"
    ],
    "wof:name":"Xinmin Liuzu",
    "wof:placetype":"locality"
},
  "geometry": {"coordinates":[120.30038999999999,32.03768],"type":"Point"}
}