{
  "type": "Feature",
  "properties": {
    "gn:admin1_code":"11.0",
    "gn:asciiname":"Pengjiazhou",
    "gn:country_code":"CN",
    "gn:dem":512,
    "gn:feature_class":"P",
    "gn:feature_code":"PPL",
    "gn:name":"Pengjiazhou",
    "gn:population":0,
    "gn:timezone":"Asia/Shanghai",
    "iso:country":"CN",
    "name:zho_x_preferred":[
        "\u5f6d\u5bb6\u6d32"
    ],
    "wof:name":"Pengjiazhou",
    "wof:placetype":"locality"
},
  "geometry": {"coordinates":[109.87591999999999,29.6874],"type":"Point"}
}