{
  "type": "Feature",
  "properties": {
    "gn:admin1_code":"7.0",
    "gn:asciiname":"Qianyuan",
    "gn:country_code":"CN",
    "gn:dem":369,
    "gn:feature_class":"P",
    "gn:feature_code":"PPL",
    "gn:name":"Qianyuan",
    "gn:population":0,
    "gn:timezone":"Asia/Shanghai",
    "iso:country":"CN",
    "name:zho_x_preferred":[
        "\u524d\u6e90"
    ],
    "wof:name":"Qianyuan",
    "wof:placetype":"locality"
},
  "geometry": {"coordinates":[118.20752,27.88991],"type":"Point"}
}