{
  "type": "Feature",
  "properties": {
    "gn:admin1_code":"8.0",
    "gn:asciiname":"Haitangpao",
    "gn:country_code":"CN",
    "gn:dem":177,
    "gn:feature_class":"P",
    "gn:feature_code":"PPL",
    "gn:name":"Haitangpao",
    "gn:population":0,
    "gn:timezone":"Asia/Shanghai",
    "iso:country":"CN",
    "name:zho_x_preferred":[
        "\u6d77\u68e0\u6ce1"
    ],
    "wof:name":"Haitangpao",
    "wof:placetype":"locality"
},
  "geometry": {"coordinates":[124.58692000000001,48.33072],"type":"Point"}
}