{
  "type": "Feature",
  "properties": {
    "gn:admin1_code":"25",
    "gn:asciiname":"Xiajia Xiaohe",
    "gn:country_code":"CN",
    "gn:dem":119,
    "gn:feature_class":"P",
    "gn:feature_code":"PPL",
    "gn:name":"Xiajia Xiaohe",
    "gn:population":0,
    "gn:timezone":"Asia/Shanghai",
    "iso:country":"CN",
    "name:zho_x_preferred":[
        "\u590f\u5bb6\u5c0f\u6cb3"
    ],
    "wof:name":"Xiajia Xiaohe",
    "wof:placetype":"locality"
},
  "geometry": {"coordinates":[118.599,35.6389],"type":"Point"}
}