{
  "type": "Feature",
  "properties": {
    "gn:admin1_code":"19.0",
    "gn:asciiname":"Wazigoucun",
    "gn:country_code":"CN",
    "gn:dem":276,
    "gn:feature_class":"P",
    "gn:feature_code":"PPL",
    "gn:name":"Wazigoucun",
    "gn:population":0,
    "gn:timezone":"Asia/Shanghai",
    "iso:country":"CN",
    "name:zho_x_preferred":[
        "\u74e6\u5b50\u6c9f\u6751"
    ],
    "wof:name":"Wazigoucun",
    "wof:placetype":"locality"
},
  "geometry": {"coordinates":[122.98639,40.53037],"type":"Point"}
}