{
  "type": "Feature",
  "properties": {
    "gn:admin1_code":"19.0",
    "gn:asciiname":"Ciyu Gangzicun",
    "gn:country_code":"CN",
    "gn:dem":9,
    "gn:feature_class":"P",
    "gn:feature_code":"PPL",
    "gn:name":"Ciyu Gangzicun",
    "gn:population":0,
    "gn:timezone":"Asia/Shanghai",
    "iso:country":"CN",
    "name:zho_x_preferred":[
        "\u8328\u6986\u5c97\u5b50\u6751"
    ],
    "wof:name":"Ciyu Gangzicun",
    "wof:placetype":"locality"
},
  "geometry": {"coordinates":[122.569,41.348],"type":"Point"}
}