{
  "type": "Feature",
  "properties": {
    "gn:admin1_code":"15.0",
    "gn:asciiname":"Zhangzhuangzi",
    "gn:country_code":"CN",
    "gn:dem":1289,
    "gn:feature_class":"P",
    "gn:feature_code":"PPL",
    "gn:name":"Zhangzhuangzi",
    "gn:population":0,
    "gn:timezone":"Asia/Shanghai",
    "iso:country":"CN",
    "name:zho_x_preferred":[
        "\u5f20\u5e84\u5b50"
    ],
    "wof:name":"Zhangzhuangzi",
    "wof:placetype":"locality"
},
  "geometry": {"coordinates":[107.02500000000001,35.7909],"type":"Point"}
}