{
  "type": "Feature",
  "properties": {
    "gn:admin1_code":"0.0",
    "gn:asciiname":"Shih-hui-yao",
    "gn:country_code":"CN",
    "gn:dem":1802,
    "gn:feature_class":"P",
    "gn:feature_code":"PPL",
    "gn:name":"Shih-hui-yao",
    "gn:population":0,
    "gn:timezone":"Asia/Shanghai",
    "iso:country":"CN",
    "wof:name":"Shih-hui-yao",
    "wof:placetype":"locality"
},
  "geometry": {"coordinates":[104.97263,23.74277],"type":"Point"}
}