{
  "type": "Feature",
  "properties": {
    "gn:admin1_code":"29.0",
    "gn:asciiname":"Dingguan",
    "gn:country_code":"CN",
    "gn:dem":1589,
    "gn:feature_class":"P",
    "gn:feature_code":"PPL",
    "gn:name":"Dingguan",
    "gn:population":0,
    "gn:timezone":"Asia/Shanghai",
    "iso:country":"CN",
    "name:zho_x_preferred":[
        "\u9876\u5b98"
    ],
    "wof:name":"Dingguan",
    "wof:placetype":"locality"
},
  "geometry": {"coordinates":[100.68000000000001,26.7494],"type":"Point"}
}