{
  "type": "Feature",
  "properties": {
    "gn:admin1_code":"29.0",
    "gn:asciiname":"Bijiashan",
    "gn:country_code":"CN",
    "gn:dem":1838,
    "gn:feature_class":"P",
    "gn:feature_code":"PPL",
    "gn:name":"Bijiashan",
    "gn:population":0,
    "gn:timezone":"Asia/Shanghai",
    "iso:country":"CN",
    "name:zho_x_preferred":[
        "\u7b14\u67b6\u5c71"
    ],
    "wof:name":"Bijiashan",
    "wof:placetype":"locality"
},
  "geometry": {"coordinates":[104.03,24.8343],"type":"Point"}
}