{
  "type": "Feature",
  "properties": {
    "gn:admin1_code":"32.0",
    "gn:asciiname":"Wanmatang",
    "gn:country_code":"CN",
    "gn:dem":3197,
    "gn:feature_class":"P",
    "gn:feature_code":"PPL",
    "gn:name":"Wanmatang",
    "gn:population":0,
    "gn:timezone":"Asia/Shanghai",
    "iso:country":"CN",
    "name:zho_x_preferred":[
        "\u4e07\u9a6c\u5858"
    ],
    "wof:name":"Wanmatang",
    "wof:placetype":"locality"
},
  "geometry": {"coordinates":[101.88433999999999,32.60762],"type":"Point"}
}