{
  "type": "Feature",
  "properties": {
    "gn:admin1_code":"23.0",
    "gn:asciiname":"Hongqi Yidui",
    "gn:country_code":"CN",
    "gn:dem":4,
    "gn:feature_class":"P",
    "gn:feature_code":"PPLF",
    "gn:name":"Hongqi Yidui",
    "gn:population":0,
    "gn:timezone":"Asia/Shanghai",
    "iso:country":"CN",
    "name:zho_x_preferred":[
        "Hongqi Yidui"
    ],
    "name:zho_x_variant":[
        "\u7ea2\u65d7\u4e00\u961f"
    ],
    "wof:name":"Hongqi Yidui",
    "wof:placetype":"locality"
},
  "geometry": {"coordinates":[121.75713,31.49939],"type":"Point"}
}