{
  "type": "Feature",
  "properties": {
    "gn:admin1_code":"15.0",
    "gn:asciiname":"Wujiao",
    "gn:country_code":"CN",
    "gn:dem":1216,
    "gn:feature_class":"P",
    "gn:feature_code":"PPLA4",
    "gn:name":"Wujiao",
    "gn:population":0,
    "gn:timezone":"Asia/Shanghai",
    "iso:country":"CN",
    "name:und_x_variant":[
        "\u4e94\u86df",
        "Wujiao Xiang",
        "\u4e94\u86df\u4e61"
    ],
    "wof:name":"Wujiao",
    "wof:placetype":"locality"
},
  "geometry": {"coordinates":[107.80542,36.44979],"type":"Point"}
}