{
  "type": "Feature",
  "properties": {
    "gn:admin1_code":"9.0",
    "gn:asciiname":"Chuandian",
    "gn:country_code":"CN",
    "gn:dem":222,
    "gn:feature_class":"P",
    "gn:feature_code":"PPL",
    "gn:name":"Chuandian",
    "gn:population":0,
    "gn:timezone":"Asia/Shanghai",
    "iso:country":"CN",
    "name:und_x_variant":[
        "\u5ddd\u5e97",
        "Chuandian"
    ],
    "wof:name":"Chuandian",
    "wof:placetype":"locality"
},
  "geometry": {"coordinates":[112.62081999999999,33.46458],"type":"Point"}
}