{
  "type": "Feature",
  "properties": {
    "gn:admin1_code":"14",
    "gn:asciiname":"Jang",
    "gn:country_code":"CN",
    "gn:dem":3597,
    "gn:feature_class":"P",
    "gn:feature_code":"PPL",
    "gn:name":"Jang",
    "gn:population":0,
    "gn:timezone":"Asia/Urumqi",
    "iso:country":"CN",
    "name:bod_x_preferred":[
        "\u0f63\u0f97\u0f44"
    ],
    "name:bul_x_preferred":[
        "\u0427\u0430\u043d"
    ],
    "name:ceb_x_preferred":[
        "Jang"
    ],
    "name:ces_x_preferred":[
        "Jang"
    ],
    "name:deu_x_preferred":[
        "Jang"
    ],
    "name:fin_x_preferred":[
        "Jang"
    ],
    "name:rus_x_preferred":[
        "\u0427\u0430\u043d"
    ],
    "name:swe_x_preferred":[
        "Jang"
    ],
    "name:ukr_x_preferred":[
        "\u0427\u0430\u043d"
    ],
    "wof:name":"Jang",
    "wof:placetype":"locality"
},
  "geometry": {"coordinates":[90.89577,29.39838],"type":"Point"}
}