{
  "type": "Feature",
  "properties": {
    "gn:admin1_code":"30.0",
    "gn:asciiname":"Dongkeng",
    "gn:country_code":"CN",
    "gn:dem":125,
    "gn:feature_class":"P",
    "gn:feature_code":"PPL",
    "gn:name":"Dongkeng",
    "gn:population":0,
    "gn:timezone":"Asia/Shanghai",
    "iso:country":"CN",
    "name:fas_x_preferred":[
        "\u062f\u0648\u0646\u06af\u06a9\u0646\u06af"
    ],
    "name:sco_x_preferred":[
        "Dongkeng"
    ],
    "name:zho_x_preferred":[
        "\u4e1c\u5751"
    ],
    "name:zho_x_variant":[
        "\u4e1c\u5751\u9547"
    ],
    "wof:name":"Dongkeng",
    "wof:placetype":"locality"
},
  "geometry": {"coordinates":[113.60205000000001,23.97088],"type":"Point"}
}