{
  "type": "Feature",
  "properties": {
    "gn:admin1_code":"19.0",
    "gn:asciiname":"Sunjia Wopeng",
    "gn:country_code":"CN",
    "gn:dem":4,
    "gn:feature_class":"P",
    "gn:feature_code":"PPL",
    "gn:name":"Sunjia Wopeng",
    "gn:population":0,
    "gn:timezone":"Asia/Shanghai",
    "iso:country":"CN",
    "name:und_x_variant":[
        "\u5b59\u5bb6\u7a9d\u68da"
    ],
    "name:zho_x_preferred":[
        "\u5b59\u5bb6\u7a9d\u68da"
    ],
    "wof:name":"Sunjia Wopeng",
    "wof:placetype":"locality"
},
  "geometry": {"coordinates":[123.75024000000001,39.84688],"type":"Point"}
}