{
  "type": "Feature",
  "properties": {
    "gn:admin1_code":"25",
    "gn:asciiname":"Xuezhuang Yicun",
    "gn:country_code":"CN",
    "gn:dem":50,
    "gn:feature_class":"P",
    "gn:feature_code":"PPL",
    "gn:name":"Xuezhuang Yicun",
    "gn:population":0,
    "gn:timezone":"Asia/Shanghai",
    "iso:country":"CN",
    "name:zho_x_preferred":[
        "\u859b\u5e84\u4e00\u6751"
    ],
    "wof:name":"Xuezhuang Yicun",
    "wof:placetype":"locality"
},
  "geometry": {"coordinates":[118.31999999999999,34.7877],"type":"Point"}
}