{
  "type": "Feature",
  "properties": {
    "gn:admin1_code":"7",
    "gn:asciiname":"Jiangdang",
    "gn:country_code":"CN",
    "gn:dem":367,
    "gn:feature_class":"P",
    "gn:feature_code":"PPL",
    "gn:name":"Jiangdang",
    "gn:population":0,
    "gn:timezone":"Asia/Shanghai",
    "iso:country":"CN",
    "name:und_x_variant":[
        "\u6c5f\u57b1"
    ],
    "wof:name":"Jiangdang",
    "wof:placetype":"locality"
},
  "geometry": {"coordinates":[118.6125,27.05972],"type":"Point"}
}