{
  "type": "Feature",
  "properties": {
    "gn:admin1_code":"18",
    "gn:asciiname":"Tianchitang",
    "gn:country_code":"CN",
    "gn:dem":873,
    "gn:feature_class":"P",
    "gn:feature_code":"PPL",
    "gn:name":"Tianchitang",
    "gn:population":0,
    "gn:timezone":"Asia/Shanghai",
    "iso:country":"CN",
    "name:zho_x_preferred":[
        "\u5929\u6c60\u5858"
    ],
    "wof:name":"Tianchitang",
    "wof:placetype":"locality"
},
  "geometry": {"coordinates":[107.095,28.3148],"type":"Point"}
}