{
  "type": "Feature",
  "properties": {
    "gn:admin1_code":"6.0",
    "gn:asciiname":"Shangmanggou",
    "gn:country_code":"CN",
    "gn:dem":2872,
    "gn:feature_class":"P",
    "gn:feature_code":"PPL",
    "gn:name":"Shangmanggou",
    "gn:population":0,
    "gn:timezone":"Asia/Shanghai",
    "iso:country":"CN",
    "name:zho_x_preferred":[
        "\u4e0a\u5fd9\u6c9f"
    ],
    "wof:name":"Shangmanggou",
    "wof:placetype":"locality"
},
  "geometry": {"coordinates":[101.47578,35.75694],"type":"Point"}
}