{
  "type": "Feature",
  "properties": {
    "gn:admin1_code":"3",
    "gn:asciiname":"Wudoukengkou",
    "gn:country_code":"CN",
    "gn:dem":197,
    "gn:feature_class":"P",
    "gn:feature_code":"PPL",
    "gn:name":"Wudoukengkou",
    "gn:population":0,
    "gn:timezone":"Asia/Shanghai",
    "iso:country":"CN",
    "name:zho_x_preferred":[
        "\u4e94\u6597\u5751\u53e3"
    ],
    "wof:name":"Wudoukengkou",
    "wof:placetype":"locality"
},
  "geometry": {"coordinates":[114.80500000000001,26.3345],"type":"Point"}
}