{
  "type": "Feature",
  "properties": {
    "gn:admin1_code":"32.0",
    "gn:asciiname":"Kayacun",
    "gn:country_code":"CN",
    "gn:dem":2017,
    "gn:feature_class":"P",
    "gn:feature_code":"PPL",
    "gn:name":"Kayacun",
    "gn:population":0,
    "gn:timezone":"Asia/Shanghai",
    "iso:country":"CN",
    "name:zho_x_preferred":[
        "\u5361\u57ad\u6751"
    ],
    "wof:name":"Kayacun",
    "wof:placetype":"locality"
},
  "geometry": {"coordinates":[101.98694,30.95237],"type":"Point"}
}