{
  "type": "Feature",
  "properties": {
    "gn:admin1_code":"25",
    "gn:asciiname":"Beisunzhuang",
    "gn:country_code":"CN",
    "gn:dem":74,
    "gn:feature_class":"P",
    "gn:feature_code":"PPL",
    "gn:name":"Beisunzhuang",
    "gn:population":0,
    "gn:timezone":"Asia/Shanghai",
    "iso:country":"CN",
    "name:zho_x_preferred":[
        "\u5317\u5b59\u5e84"
    ],
    "wof:name":"Beisunzhuang",
    "wof:placetype":"locality"
},
  "geometry": {"coordinates":[117.45699999999999,34.7659],"type":"Point"}
}