{
  "type": "Feature",
  "properties": {
    "gn:admin1_code":"19.0",
    "gn:asciiname":"Wanzigou",
    "gn:country_code":"CN",
    "gn:dem":284,
    "gn:feature_class":"P",
    "gn:feature_code":"PPL",
    "gn:name":"Wanzigou",
    "gn:population":0,
    "gn:timezone":"Asia/Shanghai",
    "iso:country":"CN",
    "name:zho_x_preferred":[
        "\u6e7e\u5b50\u6c9f"
    ],
    "wof:name":"Wanzigou",
    "wof:placetype":"locality"
},
  "geometry": {"coordinates":[124.7924,42.42372],"type":"Point"}
}