{
  "type": "Feature",
  "properties": {
    "gn:admin1_code":"25",
    "gn:asciiname":"Suntang",
    "gn:country_code":"CN",
    "gn:dem":48,
    "gn:feature_class":"P",
    "gn:feature_code":"PPL",
    "gn:name":"Suntang",
    "gn:population":0,
    "gn:timezone":"Asia/Shanghai",
    "iso:country":"CN",
    "name:zho_x_preferred":[
        "\u5b59\u5802"
    ],
    "wof:name":"Suntang",
    "wof:placetype":"locality"
},
  "geometry": {"coordinates":[115.73994999999999,35.35612000000001],"type":"Point"}
}