{
  "type": "Feature",
  "properties": {
    "gn:admin1_code":"26.0",
    "gn:asciiname":"Houwan",
    "gn:country_code":"CN",
    "gn:dem":1093,
    "gn:feature_class":"P",
    "gn:feature_code":"PPL",
    "gn:name":"Houwan",
    "gn:population":0,
    "gn:timezone":"Asia/Shanghai",
    "iso:country":"CN",
    "name:und_x_variant":[
        "\u540e\u6e7e"
    ],
    "wof:name":"Houwan",
    "wof:placetype":"locality"
},
  "geometry": {"coordinates":[107.80259,33.35159],"type":"Point"}
}