{
  "type": "Feature",
  "properties": {
    "gn:admin1_code":"19.0",
    "gn:asciiname":"Dongda Ling",
    "gn:country_code":"CN",
    "gn:dem":443,
    "gn:feature_class":"P",
    "gn:feature_code":"PPL",
    "gn:name":"Dongda Ling",
    "gn:population":0,
    "gn:timezone":"Asia/Shanghai",
    "iso:country":"CN",
    "name:und_x_variant":[
        "\u4e1c\u5927\u5cad"
    ],
    "wof:name":"Dongda Ling",
    "wof:placetype":"locality"
},
  "geometry": {"coordinates":[122.98121,40.4372],"type":"Point"}
}