{
  "type": "Feature",
  "properties": {
    "gn:admin1_code":"4.0",
    "gn:asciiname":"Nanchenjiagang",
    "gn:country_code":"CN",
    "gn:dem":1,
    "gn:feature_class":"P",
    "gn:feature_code":"PPL",
    "gn:name":"Nanchenjiagang",
    "gn:population":0,
    "gn:timezone":"Asia/Shanghai",
    "iso:country":"CN",
    "name:zho_x_preferred":[
        "\u5357\u9648\u5bb6\u6e2f"
    ],
    "wof:name":"Nanchenjiagang",
    "wof:placetype":"locality"
},
  "geometry": {"coordinates":[120.035,33.5854],"type":"Point"}
}