{
  "type": "Feature",
  "properties": {
    "gn:admin1_code":"18",
    "gn:asciiname":"Guanfang Pingzi",
    "gn:country_code":"CN",
    "gn:dem":1473,
    "gn:feature_class":"P",
    "gn:feature_code":"PPL",
    "gn:name":"Guanfang Pingzi",
    "gn:population":0,
    "gn:timezone":"Asia/Shanghai",
    "iso:country":"CN",
    "name:zho_x_preferred":[
        "\u5b98\u65b9\u576a\u5b50"
    ],
    "wof:name":"Guanfang Pingzi",
    "wof:placetype":"locality"
},
  "geometry": {"coordinates":[104.892,27.2764],"type":"Point"}
}