{
  "type": "Feature",
  "properties": {
    "gn:admin1_code":"30.0",
    "gn:asciiname":"Zhaigangjiao",
    "gn:country_code":"CN",
    "gn:dem":255,
    "gn:feature_class":"P",
    "gn:feature_code":"PPL",
    "gn:name":"Zhaigangjiao",
    "gn:population":0,
    "gn:timezone":"Asia/Shanghai",
    "iso:country":"CN",
    "name:zho_x_preferred":[
        "\u5be8\u5c97\u811a"
    ],
    "wof:name":"Zhaigangjiao",
    "wof:placetype":"locality"
},
  "geometry": {"coordinates":[112.6739,23.73694],"type":"Point"}
}