{
  "type": "Feature",
  "properties": {
    "gn:admin1_code":"16",
    "gn:asciiname":"Mugui",
    "gn:cc2":"CN",
    "gn:country_code":"CN",
    "gn:dem":40,
    "gn:feature_class":"P",
    "gn:feature_code":"PPL",
    "gn:name":"Mugui",
    "gn:population":0,
    "gn:timezone":"Asia/Shanghai",
    "iso:country":"CN",
    "name:und_x_variant":[
        "Ch\u2019\u00fcan-huang",
        "Mu-kuei",
        "Mu-kuei-hs\u00fc",
        "Mugui"
    ],
    "wof:name":"Mugui",
    "wof:placetype":"locality"
},
  "geometry": {"coordinates":[110.29667000000001,23.535],"type":"Point"}
}