{
  "type": "Feature",
  "properties": {
    "gn:admin1_code":"11.0",
    "gn:asciiname":"Zhangongtang",
    "gn:country_code":"CN",
    "gn:dem":128,
    "gn:feature_class":"P",
    "gn:feature_code":"PPL",
    "gn:name":"Zhangongtang",
    "gn:population":0,
    "gn:timezone":"Asia/Shanghai",
    "iso:country":"CN",
    "name:zho_x_preferred":[
        "\u6e5b\u516c\u5858"
    ],
    "wof:name":"Zhangongtang",
    "wof:placetype":"locality"
},
  "geometry": {"coordinates":[113.48577,28.87105],"type":"Point"}
}