{
  "type": "Feature",
  "properties": {
    "gn:admin1_code":"8.0",
    "gn:asciiname":"Houhuangheyan",
    "gn:country_code":"CN",
    "gn:dem":128,
    "gn:feature_class":"P",
    "gn:feature_code":"PPL",
    "gn:name":"Houhuangheyan",
    "gn:population":0,
    "gn:timezone":"Asia/Shanghai",
    "iso:country":"CN",
    "name:zho_x_preferred":[
        "\u540e\u9ec4\u6cb3\u6cbf"
    ],
    "wof:name":"Houhuangheyan",
    "wof:placetype":"locality"
},
  "geometry": {"coordinates":[126.90268,45.69722],"type":"Point"}
}