{
  "type": "Feature",
  "properties": {
    "gn:admin1_code":"30.0",
    "gn:asciiname":"Goutoushan",
    "gn:country_code":"CN",
    "gn:dem":243,
    "gn:feature_class":"P",
    "gn:feature_code":"PPL",
    "gn:name":"Goutoushan",
    "gn:population":0,
    "gn:timezone":"Asia/Shanghai",
    "iso:country":"CN",
    "name:zho_x_preferred":[
        "\u72d7\u5934\u5c71"
    ],
    "wof:name":"Goutoushan",
    "wof:placetype":"locality"
},
  "geometry": {"coordinates":[113.83496,25.10805],"type":"Point"}
}