{
  "type": "Feature",
  "properties": {
    "gn:admin1_code":"8.0",
    "gn:asciiname":"Nenbei Shi'erdui",
    "gn:country_code":"CN",
    "gn:dem":324,
    "gn:feature_class":"P",
    "gn:feature_code":"PPLF",
    "gn:name":"Nenbei Shi\u2019erdui",
    "gn:population":0,
    "gn:timezone":"Asia/Shanghai",
    "iso:country":"CN",
    "name:und_x_variant":[
        "Nenbei Shi\u2019erdui"
    ],
    "name:zho_x_preferred":[
        "\u5ae9\u5317\u5341\u4e8c\u961f"
    ],
    "wof:name":"Nenbei Shi'erdui",
    "wof:placetype":"locality"
},
  "geometry": {"coordinates":[125.62111000000002,49.5273],"type":"Point"}
}