{
  "type": "Feature",
  "properties": {
    "gn:admin1_code":"11.0",
    "gn:asciiname":"Yangmeijiang Jiangjia",
    "gn:country_code":"CN",
    "gn:dem":122,
    "gn:feature_class":"P",
    "gn:feature_code":"PPL",
    "gn:name":"Yangmeijiang Jiangjia",
    "gn:population":0,
    "gn:timezone":"Asia/Shanghai",
    "iso:country":"CN",
    "name:zho_x_preferred":[
        "\u6f3e\u679a\u6c5f\u848b\u5bb6"
    ],
    "wof:name":"Yangmeijiang Jiangjia",
    "wof:placetype":"locality"
},
  "geometry": {"coordinates":[111.83051,26.31786],"type":"Point"}
}