{
  "type": "Feature",
  "properties": {
    "gn:admin1_code":"19.0",
    "gn:asciiname":"Dabaimiaozi",
    "gn:country_code":"CN",
    "gn:dem":379,
    "gn:feature_class":"P",
    "gn:feature_code":"PPL",
    "gn:name":"Dabaimiaozi",
    "gn:population":0,
    "gn:timezone":"Asia/Shanghai",
    "iso:country":"CN",
    "name:und_x_variant":[
        "\u5927\u767d\u5e99\u5b50"
    ],
    "name:zho_x_preferred":[
        "\u5927\u767d\u5e99\u5b50"
    ],
    "wof:name":"Dabaimiaozi",
    "wof:placetype":"locality"
},
  "geometry": {"coordinates":[119.917,40.9925],"type":"Point"}
}