{
  "type": "Feature",
  "properties": {
    "gn:admin1_code":"32.0",
    "gn:asciiname":"Xiaochi",
    "gn:country_code":"CN",
    "gn:dem":1092,
    "gn:feature_class":"P",
    "gn:feature_code":"PPL",
    "gn:name":"Xiaochi",
    "gn:population":0,
    "gn:timezone":"Asia/Shanghai",
    "iso:country":"CN",
    "name:ind_x_preferred":[
        "Xiaochi"
    ],
    "name:ita_x_preferred":[
        "Xiaochi"
    ],
    "name:rus_x_preferred":[
        "\u0421\u044f\u043e\u0447\u0438"
    ],
    "name:zho_x_preferred":[
        "\u5c0f\u6c60"
    ],
    "name:zho_x_variant":[
        "\u4e2d\u5f0f\u5c0f\u5403"
    ],
    "wof:name":"Xiaochi",
    "wof:placetype":"locality"
},
  "geometry": {"coordinates":[105.06,32.1857],"type":"Point"}
}