{
  "type": "Feature",
  "properties": {
    "gn:admin1_code":"4.0",
    "gn:asciiname":"Kuanghu",
    "gn:country_code":"CN",
    "gn:dem":10,
    "gn:feature_class":"P",
    "gn:feature_code":"PPL",
    "gn:name":"Kuanghu",
    "gn:population":0,
    "gn:timezone":"Asia/Shanghai",
    "iso:country":"CN",
    "name:zho_x_preferred":[
        "\u5321\u6e56"
    ],
    "wof:name":"Kuanghu",
    "wof:placetype":"locality"
},
  "geometry": {"coordinates":[119.59863,31.45204],"type":"Point"}
}