{
  "type": "Feature",
  "properties": {
    "gn:admin1_code":"29.0",
    "gn:asciiname":"Haozhiqing",
    "gn:country_code":"CN",
    "gn:dem":1451,
    "gn:feature_class":"P",
    "gn:feature_code":"PPL",
    "gn:name":"Haozhiqing",
    "gn:population":0,
    "gn:timezone":"Asia/Shanghai",
    "iso:country":"CN",
    "name:zho_x_preferred":[
        "\u84bf\u679d\u7b90"
    ],
    "wof:name":"Haozhiqing",
    "wof:placetype":"locality"
},
  "geometry": {"coordinates":[100.43000000000001,26.5134],"type":"Point"}
}