{
  "type": "Feature",
  "properties": {
    "gn:admin1_code":"31.0",
    "gn:asciiname":"Hongtu",
    "gn:country_code":"CN",
    "gn:dem":72,
    "gn:feature_class":"P",
    "gn:feature_code":"PPL",
    "gn:name":"Hongtu",
    "gn:population":0,
    "gn:timezone":"Asia/Shanghai",
    "iso:country":"CN",
    "name:und_x_variant":[
        "\u7ea2\u571f"
    ],
    "wof:name":"Hongtu",
    "wof:placetype":"locality"
},
  "geometry": {"coordinates":[109.88229,18.52279],"type":"Point"}
}