{
  "type": "Feature",
  "properties": {
    "gn:admin1_code":"19.0",
    "gn:asciiname":"Yaopingfangcun",
    "gn:country_code":"CN",
    "gn:dem":306,
    "gn:feature_class":"P",
    "gn:feature_code":"PPL",
    "gn:name":"Yaopingfangcun",
    "gn:population":0,
    "gn:timezone":"Asia/Shanghai",
    "iso:country":"CN",
    "name:zho_x_preferred":[
        "\u8170\u5e73\u623f\u6751"
    ],
    "wof:name":"Yaopingfangcun",
    "wof:placetype":"locality"
},
  "geometry": {"coordinates":[120.184,40.9789],"type":"Point"}
}