{
  "type": "Feature",
  "properties": {
    "gn:admin1_code":"26.0",
    "gn:asciiname":"Huangying",
    "gn:country_code":"CN",
    "gn:dem":255,
    "gn:feature_class":"P",
    "gn:feature_code":"PPL",
    "gn:name":"Huangying",
    "gn:population":0,
    "gn:timezone":"Asia/Shanghai",
    "iso:country":"CN",
    "name:zho_x_preferred":[
        "\u9ec4\u8425"
    ],
    "wof:name":"Huangying",
    "wof:placetype":"locality"
},
  "geometry": {"coordinates":[108.94289000000001,32.70658],"type":"Point"}
}