{
  "type": "Feature",
  "properties": {
    "gn:admin1_code":"32.0",
    "gn:asciiname":"Niutanggou",
    "gn:country_code":"CN",
    "gn:dem":1360,
    "gn:feature_class":"P",
    "gn:feature_code":"PPL",
    "gn:name":"Niutanggou",
    "gn:population":0,
    "gn:timezone":"Asia/Shanghai",
    "iso:country":"CN",
    "name:zho_x_preferred":[
        "\u725b\u5858\u6c9f"
    ],
    "wof:name":"Niutanggou",
    "wof:placetype":"locality"
},
  "geometry": {"coordinates":[103.404,30.962],"type":"Point"}
}