{
  "type": "Feature",
  "properties": {
    "gn:admin1_code":"31.0",
    "gn:asciiname":"Baoya Laocun",
    "gn:country_code":"CN",
    "gn:dem":246,
    "gn:feature_class":"P",
    "gn:feature_code":"PPL",
    "gn:name":"Baoya Laocun",
    "gn:population":0,
    "gn:timezone":"Asia/Shanghai",
    "iso:country":"CN",
    "name:und_x_variant":[
        "Baoya",
        "Baoya Laocun",
        "\u4fdd\u96c5\u8001\u6751"
    ],
    "name:zho_x_preferred":[
        "\u4fdd\u96c5"
    ],
    "wof:name":"Baoya Laocun",
    "wof:placetype":"locality"
},
  "geometry": {"coordinates":[109.32144,18.59954],"type":"Point"}
}