{
  "type": "Feature",
  "properties": {
    "gn:admin1_code":"2.0",
    "gn:asciiname":"Lidachen",
    "gn:country_code":"CN",
    "gn:dem":625,
    "gn:feature_class":"P",
    "gn:feature_code":"PPL",
    "gn:name":"Lidachen",
    "gn:population":0,
    "gn:timezone":"Asia/Shanghai",
    "iso:country":"CN",
    "name:zho_x_preferred":[
        "\u91cc\u5927\u9648"
    ],
    "wof:name":"Lidachen",
    "wof:placetype":"locality"
},
  "geometry": {"coordinates":[121.22565,29.2716],"type":"Point"}
}