{
  "type": "Feature",
  "properties": {
    "gn:admin1_code":"18.0",
    "gn:asciiname":"Kulichong",
    "gn:country_code":"CN",
    "gn:dem":1154,
    "gn:feature_class":"P",
    "gn:feature_code":"PPL",
    "gn:name":"Kulichong",
    "gn:population":0,
    "gn:timezone":"Asia/Shanghai",
    "iso:country":"CN",
    "name:zho_x_preferred":[
        "\u82e6\u674e\u51b2"
    ],
    "wof:name":"Kulichong",
    "wof:placetype":"locality"
},
  "geometry": {"coordinates":[108.172,26.2774],"type":"Point"}
}