{
  "type": "Feature",
  "properties": {
    "gn:admin1_code":"5.0",
    "gn:asciiname":"Yizhouwangtun",
    "gn:country_code":"CN",
    "gn:dem":194,
    "gn:feature_class":"P",
    "gn:feature_code":"PPL",
    "gn:name":"Yizhouwangtun",
    "gn:population":0,
    "gn:timezone":"Asia/Shanghai",
    "iso:country":"CN",
    "name:zho_x_preferred":[
        "\u4e49\u6d32\u738b\u5c6f"
    ],
    "wof:name":"Yizhouwangtun",
    "wof:placetype":"locality"
},
  "geometry": {"coordinates":[126.59486,44.64785],"type":"Point"}
}