{
  "type": "Feature",
  "properties": {
    "gn:admin1_code":"32.0",
    "gn:asciiname":"Touka",
    "gn:country_code":"CN",
    "gn:dem":3103,
    "gn:feature_class":"P",
    "gn:feature_code":"PPL",
    "gn:name":"Touka",
    "gn:population":0,
    "gn:timezone":"Asia/Shanghai",
    "iso:country":"CN",
    "name:zho_x_preferred":[
        "\u5934\u5361"
    ],
    "wof:name":"Touka",
    "wof:placetype":"locality"
},
  "geometry": {"coordinates":[102.303,31.0716],"type":"Point"}
}