{
  "type": "Feature",
  "properties": {
    "gn:admin1_code":"19.0",
    "gn:asciiname":"Andeyingzi",
    "gn:country_code":"CN",
    "gn:dem":139,
    "gn:feature_class":"P",
    "gn:feature_code":"PPL",
    "gn:name":"Andeyingzi",
    "gn:population":0,
    "gn:timezone":"Asia/Shanghai",
    "iso:country":"CN",
    "name:zho_x_preferred":[
        "\u5b89\u5fb7\u8425\u5b50"
    ],
    "wof:name":"Andeyingzi",
    "wof:placetype":"locality"
},
  "geometry": {"coordinates":[121.98724,41.98606],"type":"Point"}
}