{
  "type": "Feature",
  "properties": {
    "gn:admin1_code":"19.0",
    "gn:asciiname":"Sanjiabanzi",
    "gn:country_code":"CN",
    "gn:dem":57,
    "gn:feature_class":"P",
    "gn:feature_code":"PPL",
    "gn:name":"Sanjiabanzi",
    "gn:population":0,
    "gn:timezone":"Asia/Shanghai",
    "iso:country":"CN",
    "name:zho_x_preferred":[
        "\u4e09\u5bb6\u534a\u5b50"
    ],
    "wof:name":"Sanjiabanzi",
    "wof:placetype":"locality"
},
  "geometry": {"coordinates":[122.49337,42.13171],"type":"Point"}
}