{
  "type": "Feature",
  "properties": {
    "gn:admin1_code":"32.0",
    "gn:asciiname":"Tangjia Yuanzi",
    "gn:country_code":"CN",
    "gn:dem":332,
    "gn:feature_class":"P",
    "gn:feature_code":"PPL",
    "gn:name":"Tangjia Yuanzi",
    "gn:population":0,
    "gn:timezone":"Asia/Shanghai",
    "iso:country":"CN",
    "name:zho_x_preferred":[
        "\u5510\u5bb6\u9662\u5b50"
    ],
    "wof:name":"Tangjia Yuanzi",
    "wof:placetype":"locality"
},
  "geometry": {"coordinates":[106.70963999999999,30.26133],"type":"Point"}
}