{
  "type": "Feature",
  "properties": {
    "gn:admin1_code":"29.0",
    "gn:asciiname":"Xinghuoshan",
    "gn:country_code":"CN",
    "gn:dem":1421,
    "gn:feature_class":"P",
    "gn:feature_code":"PPL",
    "gn:name":"Xinghuoshan",
    "gn:population":0,
    "gn:timezone":"Asia/Shanghai",
    "iso:country":"CN",
    "name:zho_x_preferred":[
        "\u661f\u706b\u5c71"
    ],
    "wof:name":"Xinghuoshan",
    "wof:placetype":"locality"
},
  "geometry": {"coordinates":[100.443,22.5199],"type":"Point"}
}