{
  "type": "Feature",
  "properties": {
    "gn:admin1_code":"4.0",
    "gn:asciiname":"Zhengdu",
    "gn:country_code":"CN",
    "gn:dem":4,
    "gn:feature_class":"P",
    "gn:feature_code":"PPL",
    "gn:name":"Zhengdu",
    "gn:population":0,
    "gn:timezone":"Asia/Shanghai",
    "iso:country":"CN",
    "name:zho_x_preferred":[
        "Zhengdu"
    ],
    "name:zho_x_variant":[
        "\u90d1\u6e21"
    ],
    "wof:name":"Zhengdu",
    "wof:placetype":"locality"
},
  "geometry": {"coordinates":[119.58735,33.1517],"type":"Point"}
}