{
  "type": "Feature",
  "properties": {
    "gn:admin1_code":"9.0",
    "gn:asciiname":"Guanliu",
    "gn:country_code":"CN",
    "gn:dem":132,
    "gn:feature_class":"P",
    "gn:feature_code":"PPL",
    "gn:name":"Guanliu",
    "gn:population":0,
    "gn:timezone":"Asia/Shanghai",
    "iso:country":"CN",
    "name:zho_x_preferred":[
        "\u7f50\u5218"
    ],
    "wof:name":"Guanliu",
    "wof:placetype":"locality"
},
  "geometry": {"coordinates":[112.08052000000001,32.47292],"type":"Point"}
}