{
  "type": "Feature",
  "properties": {
    "gn:admin1_code":"29.0",
    "gn:asciiname":"Zehei",
    "gn:country_code":"CN",
    "gn:dem":1998,
    "gn:feature_class":"P",
    "gn:feature_code":"PPL",
    "gn:name":"Zehei",
    "gn:population":0,
    "gn:timezone":"Asia/Shanghai",
    "iso:country":"CN",
    "wof:name":"Zehei",
    "wof:placetype":"locality"
},
  "geometry": {"coordinates":[104.05,24.66667],"type":"Point"}
}