{
  "type": "Feature",
  "properties": {
    "gn:admin1_code":"26.0",
    "gn:asciiname":"Linghuicun",
    "gn:country_code":"CN",
    "gn:dem":945,
    "gn:feature_class":"P",
    "gn:feature_code":"PPL",
    "gn:name":"Linghuicun",
    "gn:population":0,
    "gn:timezone":"Asia/Shanghai",
    "iso:country":"CN",
    "name:zho_x_preferred":[
        "\u9675\u8f89\u6751"
    ],
    "wof:name":"Linghuicun",
    "wof:placetype":"locality"
},
  "geometry": {"coordinates":[107.12182,34.42187],"type":"Point"}
}