{
  "type": "Feature",
  "properties": {
    "gn:admin1_code":"18",
    "gn:asciiname":"Zhezhutun",
    "gn:country_code":"CN",
    "gn:dem":1180,
    "gn:feature_class":"P",
    "gn:feature_code":"PPL",
    "gn:name":"Zhezhutun",
    "gn:population":0,
    "gn:timezone":"Asia/Shanghai",
    "iso:country":"CN",
    "name:zho_x_preferred":[
        "\u8005\u732a\u5c6f"
    ],
    "wof:name":"Zhezhutun",
    "wof:placetype":"locality"
},
  "geometry": {"coordinates":[106.038,25.722],"type":"Point"}
}