{
  "type": "Feature",
  "properties": {
    "gn:admin1_code":"4.0",
    "gn:asciiname":"Chuannan",
    "gn:country_code":"CN",
    "gn:dem":2,
    "gn:feature_class":"P",
    "gn:feature_code":"PPL",
    "gn:name":"Chuannan",
    "gn:population":0,
    "gn:timezone":"Asia/Shanghai",
    "iso:country":"CN",
    "name:zho_x_preferred":[
        "\u5ddd\u5357"
    ],
    "wof:name":"Chuannan",
    "wof:placetype":"locality"
},
  "geometry": {"coordinates":[120.68668,32.99534],"type":"Point"}
}