{
  "type": "Feature",
  "properties": {
    "gn:admin1_code":"30.0",
    "gn:asciiname":"Beiliancun",
    "gn:country_code":"CN",
    "gn:dem":173,
    "gn:feature_class":"P",
    "gn:feature_code":"PPL",
    "gn:name":"Beiliancun",
    "gn:population":0,
    "gn:timezone":"Asia/Shanghai",
    "iso:country":"CN",
    "name:zho_x_preferred":[
        "\u5317\u8054\u6751"
    ],
    "wof:name":"Beiliancun",
    "wof:placetype":"locality"
},
  "geometry": {"coordinates":[116.20851999999999,24.3397],"type":"Point"}
}