{
  "type": "Feature",
  "properties": {
    "gn:admin1_code":"30.0",
    "gn:asciiname":"Dancun",
    "gn:country_code":"CN",
    "gn:dem":0,
    "gn:feature_class":"P",
    "gn:feature_code":"PPL",
    "gn:name":"Dancun",
    "gn:population":0,
    "gn:timezone":"Asia/Shanghai",
    "iso:country":"CN",
    "name:zho_x_preferred":[
        "\u6de1\u6751"
    ],
    "wof:name":"Dancun",
    "wof:placetype":"locality"
},
  "geometry": {"coordinates":[112.72423999999999,22.27851],"type":"Point"}
}