{
  "type": "Feature",
  "properties": {
    "gn:admin1_code":"5.0",
    "gn:asciiname":"Yufengcun",
    "gn:country_code":"CN",
    "gn:dem":171,
    "gn:feature_class":"P",
    "gn:feature_code":"PPL",
    "gn:name":"Yufengcun",
    "gn:population":0,
    "gn:timezone":"Asia/Shanghai",
    "iso:country":"CN",
    "name:zho_x_preferred":[
        "\u7389\u4e30\u6751"
    ],
    "wof:name":"Yufengcun",
    "wof:placetype":"locality"
},
  "geometry": {"coordinates":[126.37103,44.47373],"type":"Point"}
}