{
  "type": "Feature",
  "properties": {
    "gn:admin1_code":"29.0",
    "gn:asciiname":"Songmaolin",
    "gn:country_code":"CN",
    "gn:dem":1422,
    "gn:feature_class":"P",
    "gn:feature_code":"PPL",
    "gn:name":"Songmaolin",
    "gn:population":0,
    "gn:timezone":"Asia/Shanghai",
    "iso:country":"CN",
    "name:zho_x_preferred":[
        "\u677e\u6bdb\u6797"
    ],
    "wof:name":"Songmaolin",
    "wof:placetype":"locality"
},
  "geometry": {"coordinates":[100.84699999999999,23.0074],"type":"Point"}
}