{
  "type": "Feature",
  "properties": {
    "gn:admin1_code":"7.0",
    "gn:asciiname":"Kukeng",
    "gn:country_code":"CN",
    "gn:dem":241,
    "gn:feature_class":"P",
    "gn:feature_code":"PPL",
    "gn:name":"Kukeng",
    "gn:population":0,
    "gn:timezone":"Asia/Shanghai",
    "iso:country":"CN",
    "name:und_x_variant":[
        "\u67af\u5751",
        "Kukeng"
    ],
    "wof:name":"Kukeng",
    "wof:placetype":"locality"
},
  "geometry": {"coordinates":[118.50279999999999,27.48879],"type":"Point"}
}