{
  "type": "Feature",
  "properties": {
    "gn:admin1_code":"12.0",
    "gn:asciiname":"Hongxing Dadui",
    "gn:country_code":"CN",
    "gn:dem":48,
    "gn:feature_class":"P",
    "gn:feature_code":"PPLF",
    "gn:name":"Hongxing Dadui",
    "gn:population":0,
    "gn:timezone":"Asia/Shanghai",
    "iso:country":"CN",
    "name:zho_x_preferred":[
        "Hongxing Dadui"
    ],
    "name:zho_x_variant":[
        "\u7ea2\u661f\u5927\u961f"
    ],
    "wof:name":"Hongxing Dadui",
    "wof:placetype":"locality"
},
  "geometry": {"coordinates":[114.27135,29.80615],"type":"Point"}
}