{
  "type": "Feature",
  "properties": {
    "gn:admin1_code":"12.0",
    "gn:asciiname":"Huawuji",
    "gn:country_code":"CN",
    "gn:dem":152,
    "gn:feature_class":"P",
    "gn:feature_code":"PPL",
    "gn:name":"Huawuji",
    "gn:population":0,
    "gn:timezone":"Asia/Shanghai",
    "iso:country":"CN",
    "name:zho_x_preferred":[
        "\u82b1\u5c4b\u810a"
    ],
    "wof:name":"Huawuji",
    "wof:placetype":"locality"
},
  "geometry": {"coordinates":[112.77558000000001,31.83234],"type":"Point"}
}