{
  "type": "Feature",
  "properties": {
    "gn:admin1_code":"3.0",
    "gn:asciiname":"Shipi Xiawu",
    "gn:country_code":"CN",
    "gn:dem":208,
    "gn:feature_class":"P",
    "gn:feature_code":"PPL",
    "gn:name":"Shipi Xiawu",
    "gn:population":0,
    "gn:timezone":"Asia/Shanghai",
    "iso:country":"CN",
    "name:zho_x_preferred":[
        "\u77f3\u76ae\u4e0b\u5c4b"
    ],
    "wof:name":"Shipi Xiawu",
    "wof:placetype":"locality"
},
  "geometry": {"coordinates":[114.078,29.0706],"type":"Point"}
}