{
  "type": "Feature",
  "properties": {
    "gn:admin1_code":"10",
    "gn:asciiname":"Zhitun",
    "gn:country_code":"CN",
    "gn:dem":79,
    "gn:feature_class":"P",
    "gn:feature_code":"PPL",
    "gn:name":"Zhitun",
    "gn:population":0,
    "gn:timezone":"Asia/Shanghai",
    "iso:country":"CN",
    "name:zho_x_preferred":[
        "\u7eb8\u5c6f"
    ],
    "wof:name":"Zhitun",
    "wof:placetype":"locality"
},
  "geometry": {"coordinates":[114.476,37.7367],"type":"Point"}
}