{
  "type": "Feature",
  "properties": {
    "gn:admin1_code":"11.0",
    "gn:asciiname":"Liangxi",
    "gn:country_code":"CN",
    "gn:dem":176,
    "gn:feature_class":"P",
    "gn:feature_code":"PPL",
    "gn:name":"Liangxi",
    "gn:population":0,
    "gn:timezone":"Asia/Shanghai",
    "iso:country":"CN",
    "name:zho_x_preferred":[
        "\u826f\u6eaa"
    ],
    "wof:name":"Liangxi",
    "wof:placetype":"locality"
},
  "geometry": {"coordinates":[111.61781999999999,27.67537],"type":"Point"}
}