{
  "type": "Feature",
  "properties": {
    "gn:admin1_code":"11.0",
    "gn:asciiname":"Shetian",
    "gn:country_code":"CN",
    "gn:dem":43,
    "gn:feature_class":"P",
    "gn:feature_code":"PPL",
    "gn:name":"Shetian",
    "gn:population":0,
    "gn:timezone":"Asia/Shanghai",
    "iso:country":"CN",
    "name:und_x_variant":[
        "\u756c\u7530"
    ],
    "wof:name":"Shetian",
    "wof:placetype":"locality"
},
  "geometry": {"coordinates":[111.52789,29.08918],"type":"Point"}
}