{
  "type": "Feature",
  "properties": {
    "gn:admin1_code":"29.0",
    "gn:asciiname":"Yanguojike",
    "gn:country_code":"CN",
    "gn:dem":2116,
    "gn:feature_class":"P",
    "gn:feature_code":"PPL",
    "gn:name":"Yanguojike",
    "gn:population":0,
    "gn:timezone":"Asia/Shanghai",
    "iso:country":"CN",
    "name:zho_x_preferred":[
        "\u5ca9\u8fc7\u5409\u53ef"
    ],
    "wof:name":"Yanguojike",
    "wof:placetype":"locality"
},
  "geometry": {"coordinates":[100.08199999999999,27.0706],"type":"Point"}
}