{
  "type": "Feature",
  "properties": {
    "gn:admin1_code":"24.0",
    "gn:asciiname":"Shihedi",
    "gn:country_code":"CN",
    "gn:dem":932,
    "gn:feature_class":"P",
    "gn:feature_code":"PPL",
    "gn:name":"Shihedi",
    "gn:population":0,
    "gn:timezone":"Asia/Shanghai",
    "iso:country":"CN",
    "name:zho_x_preferred":[
        "\u5e08\u6cb3\u5e95"
    ],
    "wof:name":"Shihedi",
    "wof:placetype":"locality"
},
  "geometry": {"coordinates":[111.71234,37.05727],"type":"Point"}
}