{
  "type": "Feature",
  "properties": {
    "gn:admin1_code":"16",
    "gn:asciiname":"Qianjia",
    "gn:country_code":"CN",
    "gn:dem":189,
    "gn:feature_class":"P",
    "gn:feature_code":"PPL",
    "gn:name":"Qianjia",
    "gn:population":0,
    "gn:timezone":"Asia/Shanghai",
    "iso:country":"CN",
    "name:zho_x_preferred":[
        "\u5343\u5bb6"
    ],
    "wof:name":"Qianjia",
    "wof:placetype":"locality"
},
  "geometry": {"coordinates":[110.45699999999999,25.5648],"type":"Point"}
}