{
  "type": "Feature",
  "properties": {
    "gn:admin1_code":"19.0",
    "gn:asciiname":"Baihuyingzi",
    "gn:country_code":"CN",
    "gn:dem":259,
    "gn:feature_class":"P",
    "gn:feature_code":"PPL",
    "gn:name":"Baihuyingzi",
    "gn:population":0,
    "gn:timezone":"Asia/Shanghai",
    "iso:country":"CN",
    "name:und_x_variant":[
        "\u767e\u6237\u8425\u5b50"
    ],
    "name:zho_x_preferred":[
        "\u767e\u6237\u8425\u5b50"
    ],
    "wof:name":"Baihuyingzi",
    "wof:placetype":"locality"
},
  "geometry": {"coordinates":[120.33251,41.0113],"type":"Point"}
}