{
  "type": "Feature",
  "properties": {
    "gn:admin1_code":"8.0",
    "gn:asciiname":"Zhaoxiangtun",
    "gn:country_code":"CN",
    "gn:dem":246,
    "gn:feature_class":"P",
    "gn:feature_code":"PPL",
    "gn:name":"Zhaoxiangtun",
    "gn:population":0,
    "gn:timezone":"Asia/Shanghai",
    "iso:country":"CN",
    "name:zho_x_preferred":[
        "\u5146\u7965\u5c6f"
    ],
    "wof:name":"Zhaoxiangtun",
    "wof:placetype":"locality"
},
  "geometry": {"coordinates":[125.16141,47.96713],"type":"Point"}
}