{
  "type": "Feature",
  "properties": {
    "gn:admin1_code":"18",
    "gn:asciiname":"Miaoyasi",
    "gn:country_code":"CN",
    "gn:dem":902,
    "gn:feature_class":"P",
    "gn:feature_code":"PPL",
    "gn:name":"Miaoyasi",
    "gn:population":0,
    "gn:timezone":"Asia/Shanghai",
    "iso:country":"CN",
    "name:zho_x_preferred":[
        "\u5e99\u57ad\u5bfa"
    ],
    "wof:name":"Miaoyasi",
    "wof:placetype":"locality"
},
  "geometry": {"coordinates":[108.211,28.6194],"type":"Point"}
}