{
  "type": "Feature",
  "properties": {
    "gn:admin1_code":"2.0",
    "gn:asciiname":"Xiyangtou",
    "gn:country_code":"CN",
    "gn:dem":133,
    "gn:feature_class":"P",
    "gn:feature_code":"PPL",
    "gn:name":"Xiyangtou",
    "gn:population":0,
    "gn:timezone":"Asia/Shanghai",
    "iso:country":"CN",
    "name:zho_x_preferred":[
        "\u897f\u6d0b\u5934"
    ],
    "wof:name":"Xiyangtou",
    "wof:placetype":"locality"
},
  "geometry": {"coordinates":[120.91148,29.54839],"type":"Point"}
}