{
  "type": "Feature",
  "properties": {
    "gn:admin1_code":"9.0",
    "gn:asciiname":"Liuxuezhuang",
    "gn:country_code":"CN",
    "gn:dem":196,
    "gn:feature_class":"P",
    "gn:feature_code":"PPL",
    "gn:name":"Liuxuezhuang",
    "gn:population":0,
    "gn:timezone":"Asia/Shanghai",
    "iso:country":"CN",
    "name:und_x_variant":[
        "\u5218\u5b66\u5e84",
        "Liuxuezhuang"
    ],
    "wof:name":"Liuxuezhuang",
    "wof:placetype":"locality"
},
  "geometry": {"coordinates":[112.94015,33.28683],"type":"Point"}
}