{
  "type": "Feature",
  "properties": {
    "gn:admin1_code":"19.0",
    "gn:asciiname":"Xiaobaicaidi",
    "gn:country_code":"CN",
    "gn:dem":133,
    "gn:feature_class":"P",
    "gn:feature_code":"PPL",
    "gn:name":"Xiaobaicaidi",
    "gn:population":0,
    "gn:timezone":"Asia/Shanghai",
    "iso:country":"CN",
    "name:und_x_variant":[
        "\u5c0f\u767d\u83dc\u5730"
    ],
    "name:zho_x_preferred":[
        "\u5c0f\u767d\u83dc\u5730"
    ],
    "wof:name":"Xiaobaicaidi",
    "wof:placetype":"locality"
},
  "geometry": {"coordinates":[125.22163999999999,40.64052],"type":"Point"}
}