{
  "type": "Feature",
  "properties": {
    "gn:admin1_code":"11.0",
    "gn:asciiname":"Yanpiqiao",
    "gn:cc2":"CN",
    "gn:country_code":"CN",
    "gn:dem":126,
    "gn:feature_class":"P",
    "gn:feature_code":"PPL",
    "gn:name":"Yanpiqiao",
    "gn:population":0,
    "gn:timezone":"Asia/Shanghai",
    "iso:country":"CN",
    "name:und_x_variant":[
        "Yen-p\u2019i-ch\u2019iao",
        "Yanpiqiao"
    ],
    "wof:name":"Yanpiqiao",
    "wof:placetype":"locality"
},
  "geometry": {"coordinates":[112.28333000000001,27.05],"type":"Point"}
}