{
  "type": "Feature",
  "properties": {
    "gn:admin1_code":"14.0",
    "gn:asciiname":"Yazha",
    "gn:country_code":"CN",
    "gn:dem":4437,
    "gn:feature_class":"P",
    "gn:feature_code":"PPL",
    "gn:name":"Yazha",
    "gn:population":0,
    "gn:timezone":"Asia/Urumqi",
    "iso:country":"CN",
    "name:zho_x_preferred":[
        "\u4e9a\u70b8"
    ],
    "wof:name":"Yazha",
    "wof:placetype":"locality"
},
  "geometry": {"coordinates":[94.949,31.49346],"type":"Point"}
}