{
  "type": "Feature",
  "properties": {
    "gn:admin1_code":"15.0",
    "gn:asciiname":"Hanpingshan",
    "gn:country_code":"CN",
    "gn:dem":1485,
    "gn:feature_class":"P",
    "gn:feature_code":"PPL",
    "gn:name":"Hanpingshan",
    "gn:population":0,
    "gn:timezone":"Asia/Shanghai",
    "iso:country":"CN",
    "name:zho_x_preferred":[
        "\u7ff0\u576a\u5c71"
    ],
    "wof:name":"Hanpingshan",
    "wof:placetype":"locality"
},
  "geometry": {"coordinates":[105.001,32.8584],"type":"Point"}
}