{
  "type": "Feature",
  "properties": {
    "gn:admin1_code":"02",
    "gn:asciiname":"Gaocun",
    "gn:country_code":"CN",
    "gn:dem":186,
    "gn:feature_class":"P",
    "gn:feature_code":"PPL",
    "gn:name":"Gaocun",
    "gn:population":0,
    "gn:timezone":"Asia/Shanghai",
    "iso:country":"CN",
    "name:und_x_variant":[
        "Kao-ts\u2019un",
        "Gaocun"
    ],
    "name:zho_x_preferred":[
        "\u9ad8\u6751"
    ],
    "name:zho_x_variant":[
        "\u9ad8\u6751\u9547"
    ],
    "wof:name":"Gaocun",
    "wof:placetype":"locality"
},
  "geometry": {"coordinates":[119.27368,30.54835],"type":"Point"}
}