{
  "type": "Feature",
  "properties": {
    "gn:admin1_code":"32",
    "gn:asciiname":"Jiapuzi",
    "gn:country_code":"CN",
    "gn:dem":2840,
    "gn:feature_class":"P",
    "gn:feature_code":"PPL",
    "gn:name":"Jiapuzi",
    "gn:population":0,
    "gn:timezone":"Asia/Shanghai",
    "iso:country":"CN",
    "name:zho_x_preferred":[
        "\u5939\u94fa\u5b50"
    ],
    "wof:name":"Jiapuzi",
    "wof:placetype":"locality"
},
  "geometry": {"coordinates":[101.82599999999999,28.8063],"type":"Point"}
}