{
  "type": "Feature",
  "properties": {
    "gn:admin1_code":"14.0",
    "gn:asciiname":"Dongco",
    "gn:country_code":"CN",
    "gn:dem":4433,
    "gn:feature_class":"P",
    "gn:feature_code":"PPLF",
    "gn:name":"Dongco",
    "gn:population":0,
    "gn:timezone":"Asia/Urumqi",
    "iso:country":"CN",
    "name:bod_x_preferred":[
        "Dongco"
    ],
    "name:ceb_x_preferred":[
        "Dongcuo"
    ],
    "name:msa_x_preferred":[
        "Dongco"
    ],
    "name:swe_x_preferred":[
        "Dongcuo"
    ],
    "name:und_x_variant":[
        "Dongcuo",
        "Cuoqiong"
    ],
    "name:zho_x_preferred":[
        "\u6d1e\u63aa"
    ],
    "name:zho_x_variant":[
        "\u63aa\u7a77",
        "\u6d1e\u63aa\u4e61"
    ],
    "wof:name":"Dongco",
    "wof:placetype":"locality"
},
  "geometry": {"coordinates":[84.801,32.101],"type":"Point"}
}