{
  "type": "Feature",
  "properties": {
    "gn:admin1_code":"7.0",
    "gn:asciiname":"Xiafengzhai",
    "gn:country_code":"CN",
    "gn:dem":776,
    "gn:feature_class":"P",
    "gn:feature_code":"PPL",
    "gn:name":"Xiafengzhai",
    "gn:population":0,
    "gn:timezone":"Asia/Shanghai",
    "iso:country":"CN",
    "name:zho_x_preferred":[
        "\u971e\u5cf0\u5be8"
    ],
    "wof:name":"Xiafengzhai",
    "wof:placetype":"locality"
},
  "geometry": {"coordinates":[118.54881,26.05785],"type":"Point"}
}