{
  "type": "Feature",
  "properties": {
    "gn:admin1_code":"28.0",
    "gn:asciiname":"Daliubu",
    "gn:country_code":"CN",
    "gn:dem":13,
    "gn:feature_class":"P",
    "gn:feature_code":"PPL",
    "gn:name":"Daliubu",
    "gn:population":0,
    "gn:timezone":"Asia/Shanghai",
    "iso:country":"CN",
    "name:zho_x_preferred":[
        "\u5927\u5218\u5821"
    ],
    "wof:name":"Daliubu",
    "wof:placetype":"locality"
},
  "geometry": {"coordinates":[116.89991999999999,39.22711],"type":"Point"}
}