{
  "type": "Feature",
  "properties": {
    "gn:admin1_code":"9",
    "gn:asciiname":"Zhuxiaolou",
    "gn:country_code":"CN",
    "gn:dem":67,
    "gn:feature_class":"P",
    "gn:feature_code":"PPL",
    "gn:name":"Zhuxiaolou",
    "gn:population":0,
    "gn:timezone":"Asia/Shanghai",
    "iso:country":"CN",
    "name:zho_x_preferred":[
        "\u6731\u5c0f\u697c"
    ],
    "wof:name":"Zhuxiaolou",
    "wof:placetype":"locality"
},
  "geometry": {"coordinates":[115.462,34.5741],"type":"Point"}
}