{
  "type": "Feature",
  "properties": {
    "gn:admin1_code":"26",
    "gn:asciiname":"Nanxiang",
    "gn:country_code":"CN",
    "gn:dem":931,
    "gn:feature_class":"P",
    "gn:feature_code":"PPL",
    "gn:name":"Nanxiang",
    "gn:population":0,
    "gn:timezone":"Asia/Shanghai",
    "iso:country":"CN",
    "name:deu_x_preferred":[
        "Nanxiang"
    ],
    "name:jpn_x_preferred":[
        "\u5357\u7fd4\u93ae"
    ],
    "name:nor_x_preferred":[
        "Nanxiang"
    ],
    "name:wuu_x_preferred":[
        "\u5357\u7fd4\u9547"
    ],
    "name:zho_x_preferred":[
        "\u5357\u4e61"
    ],
    "name:zho_x_variant":[
        "\u5357\u7fd4\u9547"
    ],
    "wof:name":"Nanxiang",
    "wof:placetype":"locality"
},
  "geometry": {"coordinates":[108.43722,34.80472],"type":"Point"}
}