{
  "type": "Feature",
  "properties": {
    "gn:admin1_code":"1.0",
    "gn:asciiname":"Taolingcun",
    "gn:country_code":"CN",
    "gn:dem":346,
    "gn:feature_class":"P",
    "gn:feature_code":"PPL",
    "gn:name":"Taolingcun",
    "gn:population":0,
    "gn:timezone":"Asia/Shanghai",
    "iso:country":"CN",
    "name:zho_x_preferred":[
        "\u6843\u5cad\u6751"
    ],
    "wof:name":"Taolingcun",
    "wof:placetype":"locality"
},
  "geometry": {"coordinates":[118.61450000000001,30.52112],"type":"Point"}
}