{
  "type": "Feature",
  "properties": {
    "gn:admin1_code":"32.0",
    "gn:asciiname":"Zhangping",
    "gn:country_code":"CN",
    "gn:dem":1124,
    "gn:feature_class":"P",
    "gn:feature_code":"PPL",
    "gn:name":"Zhangping",
    "gn:population":0,
    "gn:timezone":"Asia/Shanghai",
    "iso:country":"CN",
    "name:ara_x_preferred":[
        "\u0632\u0647\u0627\u0646\u063a\u0628\u064a\u0646\u063a"
    ],
    "name:cdo_x_preferred":[
        "Ci\u014fng-b\u00ecng"
    ],
    "name:deu_x_preferred":[
        "Zhangping"
    ],
    "name:fas_x_preferred":[
        "\u062c\u0627\u0646\u06af\u067e\u06cc\u0646\u06af"
    ],
    "name:fra_x_preferred":[
        "Zhangping"
    ],
    "name:hak_x_preferred":[
        "Ch\u00f4ng-ph\u00ecn-s\u1e73"
    ],
    "name:ita_x_preferred":[
        "Zhangping"
    ],
    "name:jpn_x_preferred":[
        "\u30b7\u30e7\u30a6\u5e73\u5e02"
    ],
    "name:kik_x_preferred":[
        "Zhangping"
    ],
    "name:kor_x_preferred":[
        "\uc7a5\ud551\uc2dc"
    ],
    "name:mlg_x_preferred":[
        "Zhangping"
    ],
    "name:mwl_x_preferred":[
        "Zhangping"
    ],
    "name:nor_x_preferred":[
        "Zhangping"
    ],
    "name:pam_x_preferred":[
        "Zhangping"
    ],
    "name:pnb_x_preferred":[
        "\u0698\u0627\u0646\u06af \u067e\u06cc\u0646\u06af"
    ],
    "name:spa_x_preferred":[
        "Zh\u0101ngp\u00edng Sh\u00ec"
    ],
    "name:swe_x_preferred":[
        "Zhangping"
    ],
    "name:urd_x_preferred":[
        "\u0698\u0627\u0646\u06af\u067e\u0646\u06af"
    ],
    "name:vie_x_preferred":[
        "Ch\u01b0\u01a1ng B\u00ecnh"
    ],
    "name:zho_x_preferred":[
        "\u5f20\u576a"
    ],
    "name:zho_x_variant":[
        "\u6f33\u5e73\u5e02"
    ],
    "wof:name":"Zhangping",
    "wof:placetype":"locality"
},
  "geometry": {"coordinates":[103.068,29.6208],"type":"Point"}
}