{
  "type": "Feature",
  "properties": {
    "gn:admin1_code":"2.0",
    "gn:asciiname":"Jinsiniangqiao",
    "gn:country_code":"CN",
    "gn:dem":242,
    "gn:feature_class":"P",
    "gn:feature_code":"PPL",
    "gn:name":"Jinsiniangqiao",
    "gn:population":0,
    "gn:timezone":"Asia/Shanghai",
    "iso:country":"CN",
    "name:zho_x_preferred":[
        "\u91d1\u4e1d\u5a18\u6865"
    ],
    "wof:name":"Jinsiniangqiao",
    "wof:placetype":"locality"
},
  "geometry": {"coordinates":[121.27029,29.59653],"type":"Point"}
}