{
  "type": "Feature",
  "properties": {
    "gn:admin1_code":"11",
    "gn:asciiname":"Lishanping",
    "gn:country_code":"CN",
    "gn:dem":126,
    "gn:feature_class":"P",
    "gn:feature_code":"PPL",
    "gn:name":"Lishanping",
    "gn:population":0,
    "gn:timezone":"Asia/Shanghai",
    "iso:country":"CN",
    "name:zho_x_preferred":[
        "\u6817\u5c71\u576a"
    ],
    "wof:name":"Lishanping",
    "wof:placetype":"locality"
},
  "geometry": {"coordinates":[112.49148,27.40505],"type":"Point"}
}