{
  "type": "Feature",
  "properties": {
    "gn:admin1_code":"25.0",
    "gn:asciiname":"Huangsicun",
    "gn:country_code":"CN",
    "gn:dem":44,
    "gn:feature_class":"P",
    "gn:feature_code":"PPL",
    "gn:name":"Huangsicun",
    "gn:population":0,
    "gn:timezone":"Asia/Shanghai",
    "iso:country":"CN",
    "name:zho_x_preferred":[
        "\u9ec4\u5bfa\u6751"
    ],
    "wof:name":"Huangsicun",
    "wof:placetype":"locality"
},
  "geometry": {"coordinates":[116.07395,34.87447],"type":"Point"}
}