{
  "type": "Feature",
  "properties": {
    "gn:admin1_code":"24.0",
    "gn:asciiname":"Jijiayingcun",
    "gn:country_code":"CN",
    "gn:dem":537,
    "gn:feature_class":"P",
    "gn:feature_code":"PPL",
    "gn:name":"Jijiayingcun",
    "gn:population":0,
    "gn:timezone":"Asia/Shanghai",
    "iso:country":"CN",
    "name:zho_x_preferred":[
        "\u5409\u5bb6\u8425\u6751"
    ],
    "wof:name":"Jijiayingcun",
    "wof:placetype":"locality"
},
  "geometry": {"coordinates":[110.46684,35.13957],"type":"Point"}
}