{
  "type": "Feature",
  "properties": {
    "gn:admin1_code":"11.0",
    "gn:asciiname":"Bailixi",
    "gn:country_code":"CN",
    "gn:dem":220,
    "gn:feature_class":"P",
    "gn:feature_code":"PPL",
    "gn:name":"Bailixi",
    "gn:population":0,
    "gn:timezone":"Asia/Shanghai",
    "iso:country":"CN",
    "name:zho_x_preferred":[
        "\u767d\u6817\u6eaa"
    ],
    "wof:name":"Bailixi",
    "wof:placetype":"locality"
},
  "geometry": {"coordinates":[109.80394,27.27084],"type":"Point"}
}