{
  "type": "Feature",
  "properties": {
    "gn:admin1_code":"7",
    "gn:asciiname":"Tiechanglan",
    "gn:country_code":"CN",
    "gn:dem":863,
    "gn:feature_class":"P",
    "gn:feature_code":"PPL",
    "gn:name":"Tiechanglan",
    "gn:population":0,
    "gn:timezone":"Asia/Shanghai",
    "iso:country":"CN",
    "name:zho_x_preferred":[
        "\u94c1\u573a\u5170"
    ],
    "wof:name":"Tiechanglan",
    "wof:placetype":"locality"
},
  "geometry": {"coordinates":[118.8193,25.94259],"type":"Point"}
}