{
  "type": "Feature",
  "properties": {
    "gn:admin1_code":"24.0",
    "gn:asciiname":"Haijiayao",
    "gn:country_code":"CN",
    "gn:dem":1353,
    "gn:feature_class":"P",
    "gn:feature_code":"PPL",
    "gn:name":"Haijiayao",
    "gn:population":0,
    "gn:timezone":"Asia/Shanghai",
    "iso:country":"CN",
    "name:zho_x_preferred":[
        "\u6d77\u5bb6\u7a91"
    ],
    "wof:name":"Haijiayao",
    "wof:placetype":"locality"
},
  "geometry": {"coordinates":[112.86327,40.15393],"type":"Point"}
}