{
  "type": "Feature",
  "properties": {
    "gn:admin1_code":"4.0",
    "gn:asciiname":"Baqiaocun",
    "gn:country_code":"CN",
    "gn:dem":5,
    "gn:feature_class":"P",
    "gn:feature_code":"PPL",
    "gn:name":"Baqiaocun",
    "gn:population":0,
    "gn:timezone":"Asia/Shanghai",
    "iso:country":"CN",
    "name:zho_x_preferred":[
        "\u516b\u6865\u6751"
    ],
    "wof:name":"Baqiaocun",
    "wof:placetype":"locality"
},
  "geometry": {"coordinates":[119.31408999999999,32.32568],"type":"Point"}
}