{
  "type": "Feature",
  "properties": {
    "gn:admin1_code":"3.0",
    "gn:asciiname":"Henggangzi",
    "gn:country_code":"CN",
    "gn:dem":317,
    "gn:feature_class":"P",
    "gn:feature_code":"PPL",
    "gn:name":"Henggangzi",
    "gn:population":0,
    "gn:timezone":"Asia/Shanghai",
    "iso:country":"CN",
    "name:zho_x_preferred":[
        "\u6a2a\u5c97\u5b50"
    ],
    "wof:name":"Henggangzi",
    "wof:placetype":"locality"
},
  "geometry": {"coordinates":[115.72726000000002,24.96972],"type":"Point"}
}