{
  "type": "Feature",
  "properties": {
    "gn:admin1_code":"19.0",
    "gn:asciiname":"Zhanghuajiang",
    "gn:country_code":"CN",
    "gn:dem":104,
    "gn:feature_class":"P",
    "gn:feature_code":"PPL",
    "gn:name":"Zhanghuajiang",
    "gn:population":0,
    "gn:timezone":"Asia/Shanghai",
    "iso:country":"CN",
    "name:zho_x_preferred":[
        "\u5f20\u753b\u5320"
    ],
    "wof:name":"Zhanghuajiang",
    "wof:placetype":"locality"
},
  "geometry": {"coordinates":[123.91831999999999,42.96131],"type":"Point"}
}