{
  "type": "Feature",
  "properties": {
    "gn:admin1_code":"26.0",
    "gn:asciiname":"Yazhuang",
    "gn:country_code":"CN",
    "gn:dem":1217,
    "gn:feature_class":"P",
    "gn:feature_code":"PPL",
    "gn:name":"Yazhuang",
    "gn:population":0,
    "gn:timezone":"Asia/Shanghai",
    "iso:country":"CN",
    "name:zho_x_preferred":[
        "\u82bd\u5e84"
    ],
    "wof:name":"Yazhuang",
    "wof:placetype":"locality"
},
  "geometry": {"coordinates":[108.94414999999999,35.45702],"type":"Point"}
}