{
  "type": "Feature",
  "properties": {
    "gn:admin1_code":"12.0",
    "gn:asciiname":"Hongwa Wuzhuang",
    "gn:country_code":"CN",
    "gn:dem":173,
    "gn:feature_class":"P",
    "gn:feature_code":"PPL",
    "gn:name":"Hongwa Wuzhuang",
    "gn:population":0,
    "gn:timezone":"Asia/Shanghai",
    "iso:country":"CN",
    "name:zho_x_preferred":[
        "\u7ea2\u74e6\u5c4b\u5e84"
    ],
    "wof:name":"Hongwa Wuzhuang",
    "wof:placetype":"locality"
},
  "geometry": {"coordinates":[113.59863,32.33130999999999],"type":"Point"}
}