{
  "type": "Feature",
  "properties": {
    "gn:admin1_code":"25",
    "gn:asciiname":"Houjushangmiao",
    "gn:country_code":"CN",
    "gn:dem":45,
    "gn:feature_class":"P",
    "gn:feature_code":"PPL",
    "gn:name":"Houjushangmiao",
    "gn:population":0,
    "gn:timezone":"Asia/Shanghai",
    "iso:country":"CN",
    "name:und_x_variant":[
        "Shangmiao"
    ],
    "name:zho_x_preferred":[
        "\u540e\u5de8\u5c1a\u5e99"
    ],
    "name:zho_x_variant":[
        "\u5c1a\u5e99"
    ],
    "wof:name":"Houjushangmiao",
    "wof:placetype":"locality"
},
  "geometry": {"coordinates":[115.50615999999999,36.10061],"type":"Point"}
}