{
  "type": "Feature",
  "properties": {
    "gn:admin1_code":"32",
    "gn:asciiname":"Hepingyizu",
    "gn:country_code":"CN",
    "gn:dem":827,
    "gn:feature_class":"P",
    "gn:feature_code":"PPLA3",
    "gn:name":"Hepingyizu",
    "gn:population":0,
    "gn:timezone":"Asia/Shanghai",
    "iso:country":"CN",
    "name:und_x_variant":[
        "Jinkouhe",
        "Kinkowho",
        "Chin-k\u2019ou-ho",
        "Heping",
        "Hepingyizu"
    ],
    "name:zho_x_preferred":[
        "\u548c\u5e73\u5f5d\u65cf"
    ],
    "wof:name":"Hepingyizu",
    "wof:placetype":"locality"
},
  "geometry": {"coordinates":[103.08249000000001,29.24693],"type":"Point"}
}