{
  "type": "Feature",
  "properties": {
    "gn:admin1_code":"2.0",
    "gn:asciiname":"Wan'anting",
    "gn:country_code":"CN",
    "gn:dem":9,
    "gn:feature_class":"P",
    "gn:feature_code":"PPL",
    "gn:name":"Wan\u2019anting",
    "gn:population":0,
    "gn:timezone":"Asia/Shanghai",
    "iso:country":"CN",
    "name:und_x_variant":[
        "Wan\u2019anting"
    ],
    "name:zho_x_preferred":[
        "\u4e07\u5b89\u4ead"
    ],
    "wof:name":"Wan'anting",
    "wof:placetype":"locality"
},
  "geometry": {"coordinates":[121.17529999999999,30.18186],"type":"Point"}
}