{
  "type": "Feature",
  "properties": {
    "gn:admin1_code":"16.0",
    "gn:asciiname":"Wangyao",
    "gn:country_code":"CN",
    "gn:dem":79,
    "gn:feature_class":"P",
    "gn:feature_code":"PPL",
    "gn:name":"Wangyao",
    "gn:population":0,
    "gn:timezone":"Asia/Shanghai",
    "iso:country":"CN",
    "name:zho_x_preferred":[
        "\u65fa\u7476"
    ],
    "wof:name":"Wangyao",
    "wof:placetype":"locality"
},
  "geometry": {"coordinates":[110.17700000000001,22.6341],"type":"Point"}
}