{
  "type": "Feature",
  "properties": {
    "gn:admin1_code":"32.0",
    "gn:asciiname":"Mutan",
    "gn:country_code":"CN",
    "gn:dem":447,
    "gn:feature_class":"P",
    "gn:feature_code":"PPL",
    "gn:name":"Mutan",
    "gn:population":0,
    "gn:timezone":"Asia/Shanghai",
    "iso:country":"CN",
    "name:zho_x_preferred":[
        "\u6c90\u6ee9"
    ],
    "wof:name":"Mutan",
    "wof:placetype":"locality"
},
  "geometry": {"coordinates":[104.66744,28.21052],"type":"Point"}
}