{
  "type": "Feature",
  "properties": {
    "gn:admin1_code":"18",
    "gn:asciiname":"Dingmu",
    "gn:country_code":"CN",
    "gn:dem":1200,
    "gn:feature_class":"P",
    "gn:feature_code":"PPL",
    "gn:name":"Dingmu",
    "gn:population":0,
    "gn:timezone":"Asia/Shanghai",
    "iso:country":"CN",
    "name:zho_x_preferred":[
        "\u4e01\u6728"
    ],
    "wof:name":"Dingmu",
    "wof:placetype":"locality"
},
  "geometry": {"coordinates":[105.572,24.8957],"type":"Point"}
}