{
  "type": "Feature",
  "properties": {
    "gn:admin1_code":"4.0",
    "gn:asciiname":"Tangzhong",
    "gn:country_code":"CN",
    "gn:dem":3,
    "gn:feature_class":"P",
    "gn:feature_code":"PPL",
    "gn:name":"Tangzhong",
    "gn:population":0,
    "gn:timezone":"Asia/Shanghai",
    "iso:country":"CN",
    "name:und_x_variant":[
        "\u5510\u4e2d"
    ],
    "wof:name":"Tangzhong",
    "wof:placetype":"locality"
},
  "geometry": {"coordinates":[120.44934000000001,33.00804],"type":"Point"}
}