{
  "type": "Feature",
  "properties": {
    "gn:admin1_code":"8.0",
    "gn:asciiname":"Hongshancun",
    "gn:country_code":"CN",
    "gn:dem":163,
    "gn:feature_class":"P",
    "gn:feature_code":"PPL",
    "gn:name":"Hongshancun",
    "gn:population":0,
    "gn:timezone":"Asia/Shanghai",
    "iso:country":"CN",
    "name:zho_x_preferred":[
        "\u7ea2\u5c71\u6751"
    ],
    "wof:name":"Hongshancun",
    "wof:placetype":"locality"
},
  "geometry": {"coordinates":[130.35669999999999,46.46689],"type":"Point"}
}