{
  "type": "Feature",
  "properties": {
    "gn:admin1_code":"11.0",
    "gn:asciiname":"Wulongwei",
    "gn:country_code":"CN",
    "gn:dem":29,
    "gn:feature_class":"P",
    "gn:feature_code":"PPL",
    "gn:name":"Wulongwei",
    "gn:population":0,
    "gn:timezone":"Asia/Shanghai",
    "iso:country":"CN",
    "name:zho_x_preferred":[
        "\u4e4c\u9f99\u5c3e"
    ],
    "wof:name":"Wulongwei",
    "wof:placetype":"locality"
},
  "geometry": {"coordinates":[112.62452,28.65613],"type":"Point"}
}