{
  "type": "Feature",
  "properties": {
    "gn:admin1_code":"24.0",
    "gn:asciiname":"Shencun",
    "gn:country_code":"CN",
    "gn:dem":799,
    "gn:feature_class":"P",
    "gn:feature_code":"PPL",
    "gn:name":"Shencun",
    "gn:population":0,
    "gn:timezone":"Asia/Shanghai",
    "iso:country":"CN",
    "name:zho_x_preferred":[
        "\u7533\u6751"
    ],
    "wof:name":"Shencun",
    "wof:placetype":"locality"
},
  "geometry": {"coordinates":[111.58887,36.47174],"type":"Point"}
}