{
  "type": "Feature",
  "properties": {
    "gn:admin1_code":"30.0",
    "gn:asciiname":"Danzhuba",
    "gn:country_code":"CN",
    "gn:dem":183,
    "gn:feature_class":"P",
    "gn:feature_code":"PPL",
    "gn:name":"Danzhuba",
    "gn:population":0,
    "gn:timezone":"Asia/Shanghai",
    "iso:country":"CN",
    "name:zho_x_preferred":[
        "\u4e39\u7af9\u575d"
    ],
    "wof:name":"Danzhuba",
    "wof:placetype":"locality"
},
  "geometry": {"coordinates":[113.21856,23.56298],"type":"Point"}
}