{
  "type": "Feature",
  "properties": {
    "gn:admin1_code":"11.0",
    "gn:asciiname":"Chayuanchong",
    "gn:country_code":"CN",
    "gn:dem":303,
    "gn:feature_class":"P",
    "gn:feature_code":"PPL",
    "gn:name":"Chayuanchong",
    "gn:population":0,
    "gn:timezone":"Asia/Shanghai",
    "iso:country":"CN",
    "name:zho_x_preferred":[
        "\u8336\u56ed\u51b2"
    ],
    "wof:name":"Chayuanchong",
    "wof:placetype":"locality"
},
  "geometry": {"coordinates":[112.28474,27.28303],"type":"Point"}
}