{
  "type": "Feature",
  "properties": {
    "gn:admin1_code":"15.0",
    "gn:asciiname":"Zhaizigou",
    "gn:country_code":"CN",
    "gn:dem":1469,
    "gn:feature_class":"P",
    "gn:feature_code":"PPL",
    "gn:name":"Zhaizigou",
    "gn:population":0,
    "gn:timezone":"Asia/Shanghai",
    "iso:country":"CN",
    "name:zho_x_preferred":[
        "\u5be8\u5b50\u6c9f"
    ],
    "wof:name":"Zhaizigou",
    "wof:placetype":"locality"
},
  "geometry": {"coordinates":[108.006,36.5482],"type":"Point"}
}