{
  "type": "Feature",
  "properties": {
    "gn:admin1_code":"33.0",
    "gn:asciiname":"Yicheng",
    "gn:country_code":"CN",
    "gn:dem":299,
    "gn:feature_class":"P",
    "gn:feature_code":"PPL",
    "gn:name":"Yicheng",
    "gn:population":0,
    "gn:timezone":"Asia/Shanghai",
    "iso:country":"CN",
    "name:ceb_x_preferred":[
        "Yicheng"
    ],
    "name:deu_x_preferred":[
        "Yicheng"
    ],
    "name:fra_x_preferred":[
        "Yicheng"
    ],
    "name:kor_x_preferred":[
        "\uc774\uccad\uad6c"
    ],
    "name:mlg_x_preferred":[
        "Yicheng"
    ],
    "name:nor_x_preferred":[
        "Yicheng"
    ],
    "name:rus_x_preferred":[
        "\u0418\u0447\u044d\u043d"
    ],
    "name:swe_x_preferred":[
        "Yicheng"
    ],
    "name:zho_x_preferred":[
        "\u6905\u57ce"
    ],
    "wof:name":"Yicheng",
    "wof:placetype":"locality"
},
  "geometry": {"coordinates":[108.2436,30.51209],"type":"Point"}
}