{
  "type": "Feature",
  "properties": {
    "gn:admin1_code":"30.0",
    "gn:asciiname":"Qiaohucun",
    "gn:country_code":"CN",
    "gn:dem":8,
    "gn:feature_class":"P",
    "gn:feature_code":"PPL",
    "gn:name":"Qiaohucun",
    "gn:population":0,
    "gn:timezone":"Asia/Shanghai",
    "iso:country":"CN",
    "name:zho_x_preferred":[
        "\u6865\u6e56\u6751"
    ],
    "wof:name":"Qiaohucun",
    "wof:placetype":"locality"
},
  "geometry": {"coordinates":[116.5827,23.59815],"type":"Point"}
}