{
  "type": "Feature",
  "properties": {
    "gn:admin1_code":"25.0",
    "gn:asciiname":"Zuocun",
    "gn:country_code":"CN",
    "gn:dem":82,
    "gn:feature_class":"P",
    "gn:feature_code":"PPLA4",
    "gn:name":"Zuocun",
    "gn:population":0,
    "gn:timezone":"Asia/Shanghai",
    "iso:country":"CN",
    "name:und_x_variant":[
        "Zuocun Zhen"
    ],
    "name:zho_x_preferred":[
        "\u67de\u6751"
    ],
    "name:zho_x_variant":[
        "\u67de\u6751\u9547"
    ],
    "wof:name":"Zuocun",
    "wof:placetype":"locality"
},
  "geometry": {"coordinates":[119.94177000000001,37.06039000000001],"type":"Point"}
}