{
  "type": "Feature",
  "properties": {
    "gn:admin1_code":"19.0",
    "gn:asciiname":"Liujiazi",
    "gn:country_code":"CN",
    "gn:dem":172,
    "gn:feature_class":"P",
    "gn:feature_code":"PPL",
    "gn:name":"Liujiazi",
    "gn:population":0,
    "gn:timezone":"Asia/Shanghai",
    "iso:country":"CN",
    "name:zho_x_preferred":[
        "\u516d\u5bb6\u5b50"
    ],
    "wof:name":"Liujiazi",
    "wof:placetype":"locality"
},
  "geometry": {"coordinates":[122.744,42.7227],"type":"Point"}
}