{
  "type": "Feature",
  "properties": {
    "gn:admin1_code":"32.0",
    "gn:asciiname":"Zhuchang",
    "gn:country_code":"CN",
    "gn:dem":660,
    "gn:feature_class":"P",
    "gn:feature_code":"PPL",
    "gn:name":"Zhuchang",
    "gn:population":0,
    "gn:timezone":"Asia/Shanghai",
    "iso:country":"CN",
    "name:zho_x_preferred":[
        "\u6731\u573a"
    ],
    "wof:name":"Zhuchang",
    "wof:placetype":"locality"
},
  "geometry": {"coordinates":[103.17467000000001,30.21084],"type":"Point"}
}