{
  "type": "Feature",
  "properties": {
    "gn:admin1_code":"16.0",
    "gn:asciiname":"Yaguang",
    "gn:country_code":"CN",
    "gn:dem":381,
    "gn:feature_class":"P",
    "gn:feature_code":"PPL",
    "gn:name":"Yaguang",
    "gn:population":0,
    "gn:timezone":"Asia/Shanghai",
    "iso:country":"CN",
    "name:zho_x_preferred":[
        "\u96c5\u5e7f"
    ],
    "wof:name":"Yaguang",
    "wof:placetype":"locality"
},
  "geometry": {"coordinates":[109.13800000000001,25.6918],"type":"Point"}
}