{
  "type": "Feature",
  "properties": {
    "gn:admin1_code":"16",
    "gn:asciiname":"Yangniaojiang",
    "gn:country_code":"CN",
    "gn:dem":771,
    "gn:feature_class":"P",
    "gn:feature_code":"PPL",
    "gn:name":"Yangniaojiang",
    "gn:population":0,
    "gn:timezone":"Asia/Shanghai",
    "iso:country":"CN",
    "name:zho_x_preferred":[
        "\u9633\u9e1f\u6c5f"
    ],
    "wof:name":"Yangniaojiang",
    "wof:placetype":"locality"
},
  "geometry": {"coordinates":[110.52800000000001,25.9094],"type":"Point"}
}