{
  "type": "Feature",
  "properties": {
    "gn:admin1_code":"2.0",
    "gn:asciiname":"Houdaishan",
    "gn:country_code":"CN",
    "gn:dem":611,
    "gn:feature_class":"P",
    "gn:feature_code":"PPL",
    "gn:name":"Houdaishan",
    "gn:population":0,
    "gn:timezone":"Asia/Shanghai",
    "iso:country":"CN",
    "name:zho_x_preferred":[
        "\u540e\u5cb1\u5c71"
    ],
    "wof:name":"Houdaishan",
    "wof:placetype":"locality"
},
  "geometry": {"coordinates":[119.41088999999999,28.34209],"type":"Point"}
}