{
  "type": "Feature",
  "properties": {
    "gn:admin1_code":"32.0",
    "gn:asciiname":"Hualong",
    "gn:country_code":"CN",
    "gn:dem":2433,
    "gn:feature_class":"P",
    "gn:feature_code":"PPL",
    "gn:name":"Hualong",
    "gn:population":0,
    "gn:timezone":"Asia/Shanghai",
    "iso:country":"CN",
    "name:ceb_x_preferred":[
        "Hualong"
    ],
    "name:deu_x_preferred":[
        "Hualong"
    ],
    "name:fra_x_preferred":[
        "Hualong"
    ],
    "name:nor_x_preferred":[
        "Hualong"
    ],
    "name:swe_x_preferred":[
        "Hualong"
    ],
    "name:zho_x_preferred":[
        "\u82b1\u9f99"
    ],
    "wof:name":"Hualong",
    "wof:placetype":"locality"
},
  "geometry": {"coordinates":[101.11,27.2318],"type":"Point"}
}