{
  "type": "Feature",
  "properties": {
    "gn:admin1_code":"28",
    "gn:asciiname":"Chaomidian",
    "gn:country_code":"CN",
    "gn:dem":4,
    "gn:feature_class":"P",
    "gn:feature_code":"PPL",
    "gn:name":"Chaomidian",
    "gn:population":0,
    "gn:timezone":"Asia/Shanghai",
    "iso:country":"CN",
    "name:und_x_variant":[
        "Ch\u2019ao-mi-chuang",
        "Ch\u2019ao-mi-tien",
        "Chaomidian"
    ],
    "name:zho_x_preferred":[
        "\u7092\u7c73\u5e97"
    ],
    "wof:name":"Chaomidian",
    "wof:placetype":"locality"
},
  "geometry": {"coordinates":[117.02023,39.06976],"type":"Point"}
}