{
  "type": "Feature",
  "properties": {
    "gn:admin1_code":"15.0",
    "gn:asciiname":"Dunshang",
    "gn:country_code":"CN",
    "gn:dem":1562,
    "gn:feature_class":"P",
    "gn:feature_code":"PPL",
    "gn:name":"Dunshang",
    "gn:population":0,
    "gn:timezone":"Asia/Shanghai",
    "iso:country":"CN",
    "name:und_x_variant":[
        "\u58a9\u4e0a"
    ],
    "name:zho_x_preferred":[
        "\u58a9\u4e0a"
    ],
    "wof:name":"Dunshang",
    "wof:placetype":"locality"
},
  "geometry": {"coordinates":[104.39973000000001,33.2426],"type":"Point"}
}