{
  "type": "Feature",
  "properties": {
    "gn:admin1_code":"16",
    "gn:asciiname":"Wujia",
    "gn:country_code":"CN",
    "gn:dem":175,
    "gn:feature_class":"P",
    "gn:feature_code":"PPL",
    "gn:name":"Wujia",
    "gn:population":0,
    "gn:timezone":"Asia/Shanghai",
    "iso:country":"CN",
    "name:zho_x_preferred":[
        "\u4f0d\u5bb6"
    ],
    "wof:name":"Wujia",
    "wof:placetype":"locality"
},
  "geometry": {"coordinates":[110.026,25.3251],"type":"Point"}
}