{
  "type": "Feature",
  "properties": {
    "gn:admin1_code":"3.0",
    "gn:asciiname":"Tongzishuxia",
    "gn:country_code":"CN",
    "gn:dem":180,
    "gn:feature_class":"P",
    "gn:feature_code":"PPL",
    "gn:name":"Tongzishuxia",
    "gn:population":0,
    "gn:timezone":"Asia/Shanghai",
    "iso:country":"CN",
    "name:zho_x_preferred":[
        "\u6850\u6893\u6811\u4e0b"
    ],
    "wof:name":"Tongzishuxia",
    "wof:placetype":"locality"
},
  "geometry": {"coordinates":[115.08499999999999,25.2427],"type":"Point"}
}