{
  "type": "Feature",
  "properties": {
    "gn:admin1_code":"1.0",
    "gn:asciiname":"Dongyancun",
    "gn:country_code":"CN",
    "gn:dem":48,
    "gn:feature_class":"P",
    "gn:feature_code":"PPL",
    "gn:name":"Dongyancun",
    "gn:population":0,
    "gn:timezone":"Asia/Shanghai",
    "iso:country":"CN",
    "name:zho_x_preferred":[
        "\u4e1c\u5830\u6751"
    ],
    "wof:name":"Dongyancun",
    "wof:placetype":"locality"
},
  "geometry": {"coordinates":[116.69802,31.6287],"type":"Point"}
}