{
  "type": "Feature",
  "properties": {
    "gn:admin1_code":"14.0",
    "gn:asciiname":"Dedacun",
    "gn:country_code":"CN",
    "gn:dem":3997,
    "gn:feature_class":"P",
    "gn:feature_code":"PPL",
    "gn:name":"Dedacun",
    "gn:population":0,
    "gn:timezone":"Asia/Urumqi",
    "iso:country":"CN",
    "name:zho_x_preferred":[
        "\u5fb7\u8fbe\u6751"
    ],
    "wof:name":"Dedacun",
    "wof:placetype":"locality"
},
  "geometry": {"coordinates":[97.51027000000001,29.9562],"type":"Point"}
}