{
  "type": "Feature",
  "properties": {
    "gn:admin1_code":"12.0",
    "gn:asciiname":"Xiaoshi",
    "gn:country_code":"CN",
    "gn:dem":31,
    "gn:feature_class":"P",
    "gn:feature_code":"PPL",
    "gn:name":"Xiaoshi",
    "gn:population":0,
    "gn:timezone":"Asia/Shanghai",
    "iso:country":"CN",
    "name:ceb_x_preferred":[
        "Xiaoshi"
    ],
    "name:swe_x_preferred":[
        "Xiaoshi"
    ],
    "name:zho_x_preferred":[
        "\u8096\u5e02"
    ],
    "wof:name":"Xiaoshi",
    "wof:placetype":"locality"
},
  "geometry": {"coordinates":[113.51184000000001,30.43388],"type":"Point"}
}