{
  "type": "Feature",
  "properties": {
    "gn:admin1_code":"26.0",
    "gn:asciiname":"Jiataizicun",
    "gn:country_code":"CN",
    "gn:dem":1440,
    "gn:feature_class":"P",
    "gn:feature_code":"PPL",
    "gn:name":"Jiataizicun",
    "gn:population":0,
    "gn:timezone":"Asia/Shanghai",
    "iso:country":"CN",
    "name:zho_x_preferred":[
        "\u8d3e\u53f0\u5b50\u6751"
    ],
    "wof:name":"Jiataizicun",
    "wof:placetype":"locality"
},
  "geometry": {"coordinates":[107.79680999999999,37.03631],"type":"Point"}
}