{
  "type": "Feature",
  "properties": {
    "gn:admin1_code":"16.0",
    "gn:asciiname":"Gaojiatian",
    "gn:country_code":"CN",
    "gn:dem":41,
    "gn:feature_class":"P",
    "gn:feature_code":"PPL",
    "gn:name":"Gaojiatian",
    "gn:population":0,
    "gn:timezone":"Asia/Shanghai",
    "iso:country":"CN",
    "name:zho_x_preferred":[
        "\u9ad8\u67b6\u7530"
    ],
    "wof:name":"Gaojiatian",
    "wof:placetype":"locality"
},
  "geometry": {"coordinates":[109.185,21.8213],"type":"Point"}
}