{
  "type": "Feature",
  "properties": {
    "gn:admin1_code":"32.0",
    "gn:asciiname":"Xuxu",
    "gn:country_code":"CN",
    "gn:dem":3340,
    "gn:feature_class":"P",
    "gn:feature_code":"PPL",
    "gn:name":"Xuxu",
    "gn:population":0,
    "gn:timezone":"Asia/Shanghai",
    "iso:country":"CN",
    "name:zho_x_preferred":[
        "\u987b\u987b"
    ],
    "wof:name":"Xuxu",
    "wof:placetype":"locality"
},
  "geometry": {"coordinates":[100.57299999999999,31.4497],"type":"Point"}
}