{
  "type": "Feature",
  "properties": {
    "gn:admin1_code":"26.0",
    "gn:asciiname":"Changhanmao",
    "gn:country_code":"CN",
    "gn:dem":1269,
    "gn:feature_class":"P",
    "gn:feature_code":"PPL",
    "gn:name":"Changhanmao",
    "gn:population":0,
    "gn:timezone":"Asia/Shanghai",
    "iso:country":"CN",
    "name:zho_x_preferred":[
        "\u660c\u6c57\u5cc1"
    ],
    "wof:name":"Changhanmao",
    "wof:placetype":"locality"
},
  "geometry": {"coordinates":[109.30807,38.46015],"type":"Point"}
}