{
  "type": "Feature",
  "properties": {
    "gn:admin1_code":"19",
    "gn:asciiname":"Chiao-ho-ying-tzu",
    "gn:country_code":"CN",
    "gn:dem":638,
    "gn:feature_class":"P",
    "gn:feature_code":"PPL",
    "gn:name":"Chiao-ho-ying-tzu",
    "gn:population":0,
    "gn:timezone":"Asia/Shanghai",
    "iso:country":"CN",
    "wof:name":"Chiao-ho-ying-tzu",
    "wof:placetype":"locality"
},
  "geometry": {"coordinates":[119.71056000000002,42.13167],"type":"Point"}
}