{
  "type": "Feature",
  "properties": {
    "gn:admin1_code":"8.0",
    "gn:asciiname":"Yongpingcun",
    "gn:country_code":"CN",
    "gn:dem":254,
    "gn:feature_class":"P",
    "gn:feature_code":"PPL",
    "gn:name":"Yongpingcun",
    "gn:population":0,
    "gn:timezone":"Asia/Shanghai",
    "iso:country":"CN",
    "name:zho_x_preferred":[
        "\u6c38\u5e73\u6751"
    ],
    "wof:name":"Yongpingcun",
    "wof:placetype":"locality"
},
  "geometry": {"coordinates":[126.14445000000001,48.14138],"type":"Point"}
}