{
  "type": "Feature",
  "properties": {
    "gn:admin1_code":"14",
    "gn:asciiname":"Sanglin",
    "gn:country_code":"CN",
    "gn:dem":4206,
    "gn:feature_class":"P",
    "gn:feature_code":"PPL",
    "gn:name":"Sanglin",
    "gn:population":0,
    "gn:timezone":"Asia/Urumqi",
    "iso:country":"CN",
    "name:zho_x_preferred":[
        "\u6851\u6797"
    ],
    "wof:name":"Sanglin",
    "wof:placetype":"locality"
},
  "geometry": {"coordinates":[89.17149999999999,29.0285],"type":"Point"}
}