{
  "type": "Feature",
  "properties": {
    "gn:admin1_code":"5.0",
    "gn:asciiname":"Heigoucun",
    "gn:country_code":"CN",
    "gn:dem":516,
    "gn:feature_class":"P",
    "gn:feature_code":"PPL",
    "gn:name":"Heigoucun",
    "gn:population":0,
    "gn:timezone":"Asia/Shanghai",
    "iso:country":"CN",
    "name:zho_x_preferred":[
        "\u9ed1\u6c9f\u6751"
    ],
    "wof:name":"Heigoucun",
    "wof:placetype":"locality"
},
  "geometry": {"coordinates":[126.27115000000001,41.95818],"type":"Point"}
}