{
  "type": "Feature",
  "properties": {
    "gn:admin1_code":"29.0",
    "gn:asciiname":"Bilazha Dacun",
    "gn:country_code":"CN",
    "gn:dem":1939,
    "gn:feature_class":"P",
    "gn:feature_code":"PPL",
    "gn:name":"Bilazha Dacun",
    "gn:population":0,
    "gn:timezone":"Asia/Shanghai",
    "iso:country":"CN",
    "name:zho_x_preferred":[
        "\u78a7\u62c9\u4e4d\u5927\u6751"
    ],
    "wof:name":"Bilazha Dacun",
    "wof:placetype":"locality"
},
  "geometry": {"coordinates":[101.202,26.2231],"type":"Point"}
}