{
  "type": "Feature",
  "properties": {
    "gn:admin1_code":"18.0",
    "gn:asciiname":"Chenqitun",
    "gn:country_code":"CN",
    "gn:dem":565,
    "gn:feature_class":"P",
    "gn:feature_code":"PPL",
    "gn:name":"Chenqitun",
    "gn:population":0,
    "gn:timezone":"Asia/Shanghai",
    "iso:country":"CN",
    "name:zho_x_preferred":[
        "\u9648\u5176\u5c6f"
    ],
    "wof:name":"Chenqitun",
    "wof:placetype":"locality"
},
  "geometry": {"coordinates":[108.982,27.4967],"type":"Point"}
}