{
  "type": "Feature",
  "properties": {
    "gn:admin1_code":"29.0",
    "gn:asciiname":"Laoduoge",
    "gn:country_code":"CN",
    "gn:dem":1753,
    "gn:feature_class":"P",
    "gn:feature_code":"PPL",
    "gn:name":"Laoduoge",
    "gn:population":0,
    "gn:timezone":"Asia/Shanghai",
    "iso:country":"CN",
    "name:zho_x_preferred":[
        "\u8001\u6735\u683c"
    ],
    "wof:name":"Laoduoge",
    "wof:placetype":"locality"
},
  "geometry": {"coordinates":[103.608,26.947],"type":"Point"}
}