{
  "type": "Feature",
  "properties": {
    "gn:admin1_code":"24.0",
    "gn:asciiname":"Zhongwoquan",
    "gn:country_code":"CN",
    "gn:dem":961,
    "gn:feature_class":"P",
    "gn:feature_code":"PPL",
    "gn:name":"Zhongwoquan",
    "gn:population":0,
    "gn:timezone":"Asia/Shanghai",
    "iso:country":"CN",
    "name:zho_x_preferred":[
        "\u4e2d\u6c83\u6cc9"
    ],
    "wof:name":"Zhongwoquan",
    "wof:placetype":"locality"
},
  "geometry": {"coordinates":[112.07908,35.57339],"type":"Point"}
}