{
  "type": "Feature",
  "properties": {
    "gn:admin1_code":"16.0",
    "gn:asciiname":"Guogan",
    "gn:country_code":"CN",
    "gn:dem":237,
    "gn:feature_class":"P",
    "gn:feature_code":"PPL",
    "gn:name":"Guogan",
    "gn:population":0,
    "gn:timezone":"Asia/Shanghai",
    "iso:country":"CN",
    "name:zho_x_preferred":[
        "\u679c\u7518"
    ],
    "wof:name":"Guogan",
    "wof:placetype":"locality"
},
  "geometry": {"coordinates":[108.09999999999999,24.5976],"type":"Point"}
}