{
  "type": "Feature",
  "properties": {
    "gn:admin1_code":"29.0",
    "gn:asciiname":"Maizhuangpo",
    "gn:country_code":"CN",
    "gn:dem":2295,
    "gn:feature_class":"P",
    "gn:feature_code":"PPL",
    "gn:name":"Maizhuangpo",
    "gn:population":0,
    "gn:timezone":"Asia/Shanghai",
    "iso:country":"CN",
    "name:zho_x_preferred":[
        "\u9ea6\u5e84\u5761"
    ],
    "wof:name":"Maizhuangpo",
    "wof:placetype":"locality"
},
  "geometry": {"coordinates":[99.4462,25.6154],"type":"Point"}
}