{
  "type": "Feature",
  "properties": {
    "gn:admin1_code":"12.0",
    "gn:asciiname":"Xiahupan",
    "gn:country_code":"CN",
    "gn:dem":68,
    "gn:feature_class":"P",
    "gn:feature_code":"PPL",
    "gn:name":"Xiahupan",
    "gn:population":0,
    "gn:timezone":"Asia/Shanghai",
    "iso:country":"CN",
    "name:zho_x_preferred":[
        "Xiahupan"
    ],
    "name:zho_x_variant":[
        "\u4e0b\u6e56\u7554"
    ],
    "wof:name":"Xiahupan",
    "wof:placetype":"locality"
},
  "geometry": {"coordinates":[114.81708999999999,29.55432],"type":"Point"}
}