{
  "type": "Feature",
  "properties": {
    "gn:admin1_code":"03",
    "gn:asciiname":"Chezi'ao",
    "gn:country_code":"CN",
    "gn:dem":1002,
    "gn:feature_class":"P",
    "gn:feature_code":"PPL",
    "gn:name":"Chezi\u2019ao",
    "gn:population":0,
    "gn:timezone":"Asia/Shanghai",
    "iso:country":"CN",
    "wof:name":"Chezi'ao",
    "wof:placetype":"locality"
},
  "geometry": {"coordinates":[114.05,26.06667],"type":"Point"}
}