{
  "type": "Feature",
  "properties": {
    "gn:admin1_code":"30.0",
    "gn:asciiname":"Panjialiu",
    "gn:country_code":"CN",
    "gn:dem":687,
    "gn:feature_class":"P",
    "gn:feature_code":"PPL",
    "gn:name":"Panjialiu",
    "gn:population":0,
    "gn:timezone":"Asia/Shanghai",
    "iso:country":"CN",
    "name:zho_x_preferred":[
        "Panjialiu"
    ],
    "name:zho_x_variant":[
        "\u76d8\u5bb6\u6d41"
    ],
    "wof:name":"Panjialiu",
    "wof:placetype":"locality"
},
  "geometry": {"coordinates":[112.50861,25.11028],"type":"Point"}
}