{
  "type": "Feature",
  "properties": {
    "gn:admin1_code":"10",
    "gn:asciiname":"Jiangzhangzi",
    "gn:country_code":"CN",
    "gn:dem":626,
    "gn:feature_class":"P",
    "gn:feature_code":"PPL",
    "gn:name":"Jiangzhangzi",
    "gn:population":0,
    "gn:timezone":"Asia/Shanghai",
    "iso:country":"CN",
    "name:zho_x_preferred":[
        "\u59dc\u6756\u5b50"
    ],
    "wof:name":"Jiangzhangzi",
    "wof:placetype":"locality"
},
  "geometry": {"coordinates":[118.5322,40.98399000000001],"type":"Point"}
}