{
  "type": "Feature",
  "properties": {
    "gn:admin1_code":"5.0",
    "gn:asciiname":"Sentiechu Jitihu",
    "gn:country_code":"CN",
    "gn:dem":781,
    "gn:feature_class":"P",
    "gn:feature_code":"PPLF",
    "gn:name":"Sentiechu Jitihu",
    "gn:population":0,
    "gn:timezone":"Asia/Shanghai",
    "iso:country":"CN",
    "name:und_x_variant":[
        "\u68ee\u94c1\u5904\u96c6\u4f53\u6237"
    ],
    "wof:name":"Sentiechu Jitihu",
    "wof:placetype":"locality"
},
  "geometry": {"coordinates":[127.59622,42.37689],"type":"Point"}
}