{
  "type": "Feature",
  "properties": {
    "gn:admin1_code":"19.0",
    "gn:asciiname":"Duanjiawopucun",
    "gn:country_code":"CN",
    "gn:dem":27,
    "gn:feature_class":"P",
    "gn:feature_code":"PPL",
    "gn:name":"Duanjiawopucun",
    "gn:population":0,
    "gn:timezone":"Asia/Shanghai",
    "iso:country":"CN",
    "name:zho_x_preferred":[
        "\u6bb5\u5bb6\u7a9d\u94fa\u6751"
    ],
    "wof:name":"Duanjiawopucun",
    "wof:placetype":"locality"
},
  "geometry": {"coordinates":[122.355,41.8098],"type":"Point"}
}