{
  "type": "Feature",
  "properties": {
    "gn:admin1_code":"4.0",
    "gn:asciiname":"Fufeng Liuzu",
    "gn:country_code":"CN",
    "gn:dem":5,
    "gn:feature_class":"P",
    "gn:feature_code":"PPLF",
    "gn:name":"Fufeng Liuzu",
    "gn:population":0,
    "gn:timezone":"Asia/Shanghai",
    "iso:country":"CN",
    "name:zho_x_preferred":[
        "Fufeng Liuzu"
    ],
    "name:zho_x_variant":[
        "\u961c\u4e30\u516d\u7ec4"
    ],
    "wof:name":"Fufeng Liuzu",
    "wof:placetype":"locality"
},
  "geometry": {"coordinates":[120.96536999999999,32.12971],"type":"Point"}
}