{
  "type": "Feature",
  "properties": {
    "gn:admin1_code":"10",
    "gn:asciiname":"Liyipai",
    "gn:country_code":"CN",
    "gn:dem":47,
    "gn:feature_class":"P",
    "gn:feature_code":"PPL",
    "gn:name":"Liyipai",
    "gn:population":0,
    "gn:timezone":"Asia/Shanghai",
    "iso:country":"CN",
    "name:zho_x_preferred":[
        "\u674e\u4e00\u724c"
    ],
    "wof:name":"Liyipai",
    "wof:placetype":"locality"
},
  "geometry": {"coordinates":[115.197,36.2377],"type":"Point"}
}