{
  "type": "Feature",
  "properties": {
    "gn:admin1_code":"15.0",
    "gn:asciiname":"Wangjiaying",
    "gn:country_code":"CN",
    "gn:dem":1820,
    "gn:feature_class":"P",
    "gn:feature_code":"PPL",
    "gn:name":"Wangjiaying",
    "gn:population":0,
    "gn:timezone":"Asia/Shanghai",
    "iso:country":"CN",
    "name:zho_x_preferred":[
        "\u738b\u5bb6\u8425"
    ],
    "wof:name":"Wangjiaying",
    "wof:placetype":"locality"
},
  "geometry": {"coordinates":[104.542,35.058],"type":"Point"}
}