{
  "type": "Feature",
  "properties": {
    "gn:admin1_code":"25",
    "gn:asciiname":"Dianji",
    "gn:cc2":"CN",
    "gn:country_code":"CN",
    "gn:dem":8,
    "gn:feature_class":"P",
    "gn:feature_code":"PPL",
    "gn:name":"Dianji",
    "gn:population":0,
    "gn:timezone":"Asia/Shanghai",
    "iso:country":"CN",
    "name:und_x_variant":[
        "Tien-chi",
        "Chi-tung",
        "Dianji"
    ],
    "name:zho_x_preferred":[
        "\u5e97\u96c6\u9547"
    ],
    "wof:name":"Dianji",
    "wof:placetype":"locality"
},
  "geometry": {"coordinates":[120.70056,36.54806],"type":"Point"}
}