{
  "type": "Feature",
  "properties": {
    "gn:admin1_code":"19.0",
    "gn:asciiname":"Xinjieji",
    "gn:country_code":"CN",
    "gn:dem":265,
    "gn:feature_class":"P",
    "gn:feature_code":"PPL",
    "gn:name":"Xinjieji",
    "gn:population":0,
    "gn:timezone":"Asia/Shanghai",
    "iso:country":"CN",
    "name:zho_x_preferred":[
        "\u65b0\u8857\u57fa"
    ],
    "wof:name":"Xinjieji",
    "wof:placetype":"locality"
},
  "geometry": {"coordinates":[124.565,42.5187],"type":"Point"}
}