{
  "type": "Feature",
  "properties": {
    "gn:admin1_code":"9.0",
    "gn:asciiname":"Sangshuping",
    "gn:country_code":"CN",
    "gn:dem":846,
    "gn:feature_class":"P",
    "gn:feature_code":"PPL",
    "gn:name":"Sangshuping",
    "gn:population":0,
    "gn:timezone":"Asia/Shanghai",
    "iso:country":"CN",
    "name:zho_x_preferred":[
        "\u6851\u6811\u576a"
    ],
    "wof:name":"Sangshuping",
    "wof:placetype":"locality"
},
  "geometry": {"coordinates":[111.36306,34.54327],"type":"Point"}
}