{
  "type": "Feature",
  "properties": {
    "gn:admin1_code":"15.0",
    "gn:asciiname":"Jiangjia Shizi",
    "gn:country_code":"CN",
    "gn:dem":1193,
    "gn:feature_class":"P",
    "gn:feature_code":"PPL",
    "gn:name":"Jiangjia Shizi",
    "gn:population":0,
    "gn:timezone":"Asia/Shanghai",
    "iso:country":"CN",
    "name:zho_x_preferred":[
        "\u59dc\u5bb6\u4ec0\u5b57"
    ],
    "wof:name":"Jiangjia Shizi",
    "wof:placetype":"locality"
},
  "geometry": {"coordinates":[107.834,35.3504],"type":"Point"}
}