{
  "type": "Feature",
  "properties": {
    "gn:admin1_code":"25.0",
    "gn:asciiname":"Nanzhao",
    "gn:country_code":"CN",
    "gn:dem":114,
    "gn:feature_class":"P",
    "gn:feature_code":"PPL",
    "gn:name":"Nanzhao",
    "gn:population":0,
    "gn:timezone":"Asia/Shanghai",
    "iso:country":"CN",
    "name:ben_x_preferred":[
        "\u09a8\u09be\u09a8\u099d\u09be\u0993 \u09b0\u09be\u099c\u09cd\u09af"
    ],
    "name:bul_x_preferred":[
        "\u041d\u0430\u043d\u0434\u0436\u0430\u043e"
    ],
    "name:cat_x_preferred":[
        "Nan Chao"
    ],
    "name:deu_x_preferred":[
        "Nanzhao"
    ],
    "name:epo_x_preferred":[
        "Nanchao"
    ],
    "name:hin_x_preferred":[
        "\u0928\u093e\u0928\u091d\u093e\u0913 \u0930\u093e\u091c\u094d\u092f"
    ],
    "name:kat_x_preferred":[
        "\u10dc\u10d0\u10dc\u10ef\u10d0\u10dd"
    ],
    "name:kor_x_preferred":[
        "\ub0a8\uc870"
    ],
    "name:lat_x_preferred":[
        "Nanzhao"
    ],
    "name:lit_x_preferred":[
        "Nanzhao"
    ],
    "name:nld_x_preferred":[
        "Nan Chao"
    ],
    "name:nor_x_preferred":[
        "Nanzhao"
    ],
    "name:pol_x_preferred":[
        "Nanzhao"
    ],
    "name:rus_x_preferred":[
        "\u041d\u0430\u043d\u044c\u0447\u0436\u0430\u043e"
    ],
    "name:sco_x_preferred":[
        "Nanzhao"
    ],
    "name:swe_x_preferred":[
        "Nanzhaoriket"
    ],
    "name:tha_x_preferred":[
        "\u0e2d\u0e32\u0e13\u0e32\u0e08\u0e31\u0e01\u0e23\u0e19\u0e48\u0e32\u0e19\u0e40\u0e08\u0e49\u0e32"
    ],
    "name:ukr_x_preferred":[
        "\u041d\u0430\u043d\u044c\u0447\u0436\u0430\u043e"
    ],
    "name:vie_x_preferred":[
        "Nam Chi\u1ebfu"
    ],
    "name:zho_x_preferred":[
        "\u5357\u7167"
    ],
    "wof:name":"Nanzhao",
    "wof:placetype":"locality"
},
  "geometry": {"coordinates":[120.63276999999999,37.16589000000001],"type":"Point"}
}