{
  "type": "Feature",
  "properties": {
    "gn:admin1_code":"25.0",
    "gn:asciiname":"Nanzhao",
    "gn:country_code":"CN",
    "gn:dem":114,
    "gn:feature_class":"P",
    "gn:feature_code":"PPL",
    "gn:name":"Nanzhao",
    "gn:population":0,
    "gn:timezone":"Asia/Shanghai",
    "iso:country":"CN",
    "name:zho_x_preferred":[
        "\u5357\u7167"
    ],
    "wof:name":"Nanzhao",
    "wof:placetype":"locality"
},
  "geometry": {"coordinates":[120.63276999999999,37.16589000000001],"type":"Point"}
}