{
  "type": "Feature",
  "properties": {
    "gn:admin1_code":"5.0",
    "gn:asciiname":"Nanchanggoucun",
    "gn:country_code":"CN",
    "gn:dem":158,
    "gn:feature_class":"P",
    "gn:feature_code":"PPL",
    "gn:name":"Nanchanggoucun",
    "gn:population":0,
    "gn:timezone":"Asia/Shanghai",
    "iso:country":"CN",
    "name:zho_x_preferred":[
        "\u5357\u957f\u6c9f\u6751"
    ],
    "wof:name":"Nanchanggoucun",
    "wof:placetype":"locality"
},
  "geometry": {"coordinates":[126.14372,44.65869],"type":"Point"}
}