{
  "type": "Feature",
  "properties": {
    "gn:admin1_code":"10",
    "gn:asciiname":"Shanggoumen",
    "gn:country_code":"CN",
    "gn:dem":1127,
    "gn:feature_class":"P",
    "gn:feature_code":"PPL",
    "gn:name":"Shanggoumen",
    "gn:population":0,
    "gn:timezone":"Asia/Shanghai",
    "iso:country":"CN",
    "name:zho_x_preferred":[
        "\u4e0a\u6c9f\u95e8"
    ],
    "wof:name":"Shanggoumen",
    "wof:placetype":"locality"
},
  "geometry": {"coordinates":[116.75299,41.50755],"type":"Point"}
}