{
  "type": "Feature",
  "properties": {
    "gn:admin1_code":"14.0",
    "gn:asciiname":"Exue",
    "gn:country_code":"CN",
    "gn:dem":3349,
    "gn:feature_class":"P",
    "gn:feature_code":"PPL",
    "gn:name":"Exue",
    "gn:population":0,
    "gn:timezone":"Asia/Urumqi",
    "iso:country":"CN",
    "name:zho_x_preferred":[
        "\u4fc4\u5b66"
    ],
    "wof:name":"Exue",
    "wof:placetype":"locality"
},
  "geometry": {"coordinates":[96.67335,30.48369000000001],"type":"Point"}
}