{
  "type": "Feature",
  "properties": {
    "gn:admin1_code":"4.0",
    "gn:asciiname":"Baoshengcun",
    "gn:country_code":"CN",
    "gn:dem":52,
    "gn:feature_class":"P",
    "gn:feature_code":"PPL",
    "gn:name":"Baoshengcun",
    "gn:population":0,
    "gn:timezone":"Asia/Shanghai",
    "iso:country":"CN",
    "name:zho_x_preferred":[
        "\u5b9d\u5723\u6751"
    ],
    "wof:name":"Baoshengcun",
    "wof:placetype":"locality"
},
  "geometry": {"coordinates":[118.84668000000001,32.48889],"type":"Point"}
}