{
  "type": "Feature",
  "properties": {
    "gn:admin1_code":"18",
    "gn:asciiname":"Dayangou",
    "gn:country_code":"CN",
    "gn:dem":675,
    "gn:feature_class":"P",
    "gn:feature_code":"PPL",
    "gn:name":"Dayangou",
    "gn:population":0,
    "gn:timezone":"Asia/Shanghai",
    "iso:country":"CN",
    "name:zho_x_preferred":[
        "\u5927\u5ca9\u6c9f"
    ],
    "wof:name":"Dayangou",
    "wof:placetype":"locality"
},
  "geometry": {"coordinates":[107.374,28.4586],"type":"Point"}
}