{
  "type": "Feature",
  "properties": {
    "gn:admin1_code":"4.0",
    "gn:asciiname":"Jiwangzhuang",
    "gn:country_code":"CN",
    "gn:dem":3,
    "gn:feature_class":"P",
    "gn:feature_code":"PPL",
    "gn:name":"Jiwangzhuang",
    "gn:population":0,
    "gn:timezone":"Asia/Shanghai",
    "iso:country":"CN",
    "name:zho_x_preferred":[
        "Jiwangzhuang"
    ],
    "name:zho_x_variant":[
        "\u5b63\u738b\u5e84"
    ],
    "wof:name":"Jiwangzhuang",
    "wof:placetype":"locality"
},
  "geometry": {"coordinates":[119.28919,34.01797],"type":"Point"}
}