{
  "type": "Feature",
  "properties": {
    "gn:admin1_code":"14",
    "gn:asciiname":"De'gyi",
    "gn:country_code":"CN",
    "gn:dem":3636,
    "gn:feature_class":"P",
    "gn:feature_code":"PPL",
    "gn:name":"D\u00ea'gyi",
    "gn:population":0,
    "gn:timezone":"Asia/Urumqi",
    "iso:country":"CN",
    "name:bod_x_preferred":[
        "\u0f66\u0fa1\u0f7a\u0f0b\u0f51\u0f40\u0fb1\u0f72\u0f63"
    ],
    "wof:name":"De'gyi",
    "wof:placetype":"locality"
},
  "geometry": {"coordinates":[92.46866,28.23862],"type":"Point"}
}