{
  "type": "Feature",
  "properties": {
    "gn:admin1_code":"29.0",
    "gn:asciiname":"Panzhihua",
    "gn:country_code":"CN",
    "gn:dem":592,
    "gn:feature_class":"P",
    "gn:feature_code":"PPL",
    "gn:name":"Panzhihua",
    "gn:population":0,
    "gn:timezone":"Asia/Shanghai",
    "iso:country":"CN",
    "name:ara_x_preferred":[
        "\u0628\u0627\u0646\u062a\u0634\u064a\u0647\u0648\u0627"
    ],
    "name:bul_x_preferred":[
        "\u041f\u0430\u043d\u0434\u0436\u0438\u0445\u0443\u0430"
    ],
    "name:cdo_x_preferred":[
        "P\u0103ng-ci\u0115-hu\u0103"
    ],
    "name:ces_x_preferred":[
        "Pchan-\u010d\u2019-chua"
    ],
    "name:dan_x_preferred":[
        "Panzhihua"
    ],
    "name:deu_x_preferred":[
        "Panzhihua"
    ],
    "name:est_x_preferred":[
        "Panzhihua Shi"
    ],
    "name:eus_x_preferred":[
        "Panzhihua"
    ],
    "name:fas_x_preferred":[
        "\u067e\u0646\u0698\u06cc\u0647\u0648\u0627"
    ],
    "name:fin_x_preferred":[
        "Panzhihua"
    ],
    "name:fra_x_preferred":[
        "Panzhihua"
    ],
    "name:hak_x_preferred":[
        "P\u00e2n-k\u00ee-f\u00e2-s\u1e73"
    ],
    "name:ita_x_preferred":[
        "Panzhihua"
    ],
    "name:jpn_x_preferred":[
        "\u6500\u679d\u82b1\u5e02"
    ],
    "name:kik_x_preferred":[
        "Panzhihua"
    ],
    "name:kor_x_preferred":[
        "\ud310\uc988\ud654\uc2dc"
    ],
    "name:nld_x_preferred":[
        "Panzhihua"
    ],
    "name:nno_x_preferred":[
        "Panzhihua"
    ],
    "name:nor_x_preferred":[
        "Panzhihua"
    ],
    "name:pol_x_preferred":[
        "Panzhihua"
    ],
    "name:rus_x_preferred":[
        "\u041f\u0430\u043d\u044c\u0447\u0436\u0438\u0445\u0443\u0430"
    ],
    "name:spa_x_preferred":[
        "Panzhihua"
    ],
    "name:srp_x_preferred":[
        "\u041f\u0430\u043d\u045f\u0438\u0445\u0443\u0430"
    ],
    "name:swe_x_preferred":[
        "Panzhihua"
    ],
    "name:tur_x_preferred":[
        "Panzhihua"
    ],
    "name:urd_x_preferred":[
        "\u067e\u0627\u0646\u0698\u06cc\u06c1\u0648\u0627"
    ],
    "name:war_x_preferred":[
        "Panzhihua"
    ],
    "name:wuu_x_preferred":[
        "\u6500\u679d\u82b1\u5e02"
    ],
    "name:zho_x_preferred":[
        "\u6500\u652f\u82b1"
    ],
    "name:zho_x_variant":[
        "\u6500\u679d\u82b1\u5e02"
    ],
    "wof:name":"Panzhihua",
    "wof:placetype":"locality"
},
  "geometry": {"coordinates":[103.23399999999999,23.0591],"type":"Point"}
}