{
  "type": "Feature",
  "properties": {
    "gn:admin1_code":"29.0",
    "gn:asciiname":"Panzhihua",
    "gn:country_code":"CN",
    "gn:dem":592,
    "gn:feature_class":"P",
    "gn:feature_code":"PPL",
    "gn:name":"Panzhihua",
    "gn:population":0,
    "gn:timezone":"Asia/Shanghai",
    "iso:country":"CN",
    "name:zho_x_preferred":[
        "\u6500\u652f\u82b1"
    ],
    "wof:name":"Panzhihua",
    "wof:placetype":"locality"
},
  "geometry": {"coordinates":[103.23399999999999,23.0591],"type":"Point"}
}