{
  "type": "Feature",
  "properties": {
    "gn:admin1_code":"15.0",
    "gn:asciiname":"Gaomiao",
    "gn:country_code":"CN",
    "gn:dem":1790,
    "gn:feature_class":"P",
    "gn:feature_code":"PPL",
    "gn:name":"Gaomiao",
    "gn:population":0,
    "gn:timezone":"Asia/Shanghai",
    "iso:country":"CN",
    "name:und_x_variant":[
        "\u9ad8\u5e99"
    ],
    "wof:name":"Gaomiao",
    "wof:placetype":"locality"
},
  "geometry": {"coordinates":[105.07545,35.56426],"type":"Point"}
}