{
  "type": "Feature",
  "properties": {
    "gn:admin1_code":"5.0",
    "gn:asciiname":"Zhangcai Wopeng",
    "gn:country_code":"CN",
    "gn:dem":144,
    "gn:feature_class":"P",
    "gn:feature_code":"PPL",
    "gn:name":"Zhangcai Wopeng",
    "gn:population":0,
    "gn:timezone":"Asia/Shanghai",
    "iso:country":"CN",
    "name:zho_x_preferred":[
        "\u5f20\u624d\u7a9d\u68da"
    ],
    "wof:name":"Zhangcai Wopeng",
    "wof:placetype":"locality"
},
  "geometry": {"coordinates":[123.56474,43.98274],"type":"Point"}
}