{
  "type": "Feature",
  "properties": {
    "gn:admin1_code":"02",
    "gn:asciiname":"Zhuyucun",
    "gn:country_code":"CN",
    "gn:dem":9,
    "gn:feature_class":"P",
    "gn:feature_code":"PPL",
    "gn:name":"Zhuyucun",
    "gn:population":0,
    "gn:timezone":"Asia/Shanghai",
    "iso:country":"CN",
    "name:und_x_variant":[
        "Chu-yu",
        "Zhuyu",
        "Zhuyucun"
    ],
    "name:zho_x_preferred":[
        "\u7af9\u5c7f"
    ],
    "name:zho_x_variant":[
        "\u7af9\u5c7f\u6751"
    ],
    "wof:name":"Zhuyucun",
    "wof:placetype":"locality"
},
  "geometry": {"coordinates":[121.01251000000001,28.16916],"type":"Point"}
}