{
  "type": "Feature",
  "properties": {
    "gn:admin1_code":"26.0",
    "gn:asciiname":"Haimingcun",
    "gn:country_code":"CN",
    "gn:dem":788,
    "gn:feature_class":"P",
    "gn:feature_code":"PPL",
    "gn:name":"Haimingcun",
    "gn:population":0,
    "gn:timezone":"Asia/Shanghai",
    "iso:country":"CN",
    "name:und_x_variant":[
        "\u6d77\u660e\u6751"
    ],
    "wof:name":"Haimingcun",
    "wof:placetype":"locality"
},
  "geometry": {"coordinates":[107.13041,32.95893],"type":"Point"}
}