{
  "type": "Feature",
  "properties": {
    "gn:admin1_code":"15.0",
    "gn:asciiname":"Guanzikou",
    "gn:country_code":"CN",
    "gn:dem":2189,
    "gn:feature_class":"P",
    "gn:feature_code":"PPL",
    "gn:name":"Guanzikou",
    "gn:population":0,
    "gn:timezone":"Asia/Shanghai",
    "iso:country":"CN",
    "name:zho_x_preferred":[
        "\u7f50\u5b50\u53e3"
    ],
    "wof:name":"Guanzikou",
    "wof:placetype":"locality"
},
  "geometry": {"coordinates":[104.203,35.072],"type":"Point"}
}