{
  "type": "Feature",
  "properties": {
    "gn:admin1_code":"20.0",
    "gn:asciiname":"Xiaodashi",
    "gn:country_code":"CN",
    "gn:dem":1432,
    "gn:feature_class":"P",
    "gn:feature_code":"PPL",
    "gn:name":"Xiaodashi",
    "gn:population":0,
    "gn:timezone":"Asia/Shanghai",
    "iso:country":"CN",
    "name:und_x_variant":[
        "\u5c0f\u4e01\u4ec0"
    ],
    "wof:name":"Xiaodashi",
    "wof:placetype":"locality"
},
  "geometry": {"coordinates":[112.58467,41.68159],"type":"Point"}
}