{
  "type": "Feature",
  "properties": {
    "gn:admin1_code":"10",
    "gn:asciiname":"Beijianshan",
    "gn:country_code":"CN",
    "gn:dem":408,
    "gn:feature_class":"P",
    "gn:feature_code":"PPL",
    "gn:name":"Beijianshan",
    "gn:population":0,
    "gn:timezone":"Asia/Shanghai",
    "iso:country":"CN",
    "name:zho_x_preferred":[
        "\u5317\u5c16\u5c71"
    ],
    "wof:name":"Beijianshan",
    "wof:placetype":"locality"
},
  "geometry": {"coordinates":[114.129,36.7962],"type":"Point"}
}