{
  "type": "Feature",
  "properties": {
    "gn:admin1_code":"7",
    "gn:asciiname":"Dongshanwei",
    "gn:country_code":"CN",
    "gn:dem":478,
    "gn:feature_class":"P",
    "gn:feature_code":"PPL",
    "gn:name":"Dongshanwei",
    "gn:population":0,
    "gn:timezone":"Asia/Shanghai",
    "iso:country":"CN",
    "name:zho_x_preferred":[
        "\u4e1c\u5c71\u5c3e"
    ],
    "wof:name":"Dongshanwei",
    "wof:placetype":"locality"
},
  "geometry": {"coordinates":[117.79277999999999,24.95278],"type":"Point"}
}