{
  "type": "Feature",
  "properties": {
    "gn:admin1_code":"30",
    "gn:asciiname":"Huoxing Nongchang",
    "gn:country_code":"CN",
    "gn:dem":71,
    "gn:feature_class":"P",
    "gn:feature_code":"PPLF",
    "gn:name":"Huoxing Nongchang",
    "gn:population":0,
    "gn:timezone":"Asia/Urumqi",
    "iso:country":"CN",
    "name:und_x_variant":[
        "Houxing Nongchang",
        "Huoxing Nongchang"
    ],
    "name:zho_x_preferred":[
        "\u706b\u661f\u519c\u573a"
    ],
    "wof:name":"Huoxing Nongchang",
    "wof:placetype":"locality"
},
  "geometry": {"coordinates":[110.90278000000001,21.9125],"type":"Point"}
}