{
  "type": "Feature",
  "properties": {
    "gn:admin1_code":"11",
    "gn:asciiname":"Huangjiangwan",
    "gn:country_code":"CN",
    "gn:dem":443,
    "gn:feature_class":"P",
    "gn:feature_code":"PPL",
    "gn:name":"Huangjiangwan",
    "gn:population":0,
    "gn:timezone":"Asia/Shanghai",
    "iso:country":"CN",
    "name:zho_x_preferred":[
        "\u7687\u6c5f\u6e7e"
    ],
    "wof:name":"Huangjiangwan",
    "wof:placetype":"locality"
},
  "geometry": {"coordinates":[111.61394,27.99134],"type":"Point"}
}