{
  "type": "Feature",
  "properties": {
    "gn:admin1_code":"32.0",
    "gn:asciiname":"Changshenggou",
    "gn:country_code":"CN",
    "gn:dem":499,
    "gn:feature_class":"P",
    "gn:feature_code":"PPL",
    "gn:name":"Changshenggou",
    "gn:population":0,
    "gn:timezone":"Asia/Shanghai",
    "iso:country":"CN",
    "name:zho_x_preferred":[
        "\u957f\u751f\u6c9f"
    ],
    "wof:name":"Changshenggou",
    "wof:placetype":"locality"
},
  "geometry": {"coordinates":[104.13978,30.65575],"type":"Point"}
}