{
  "type": "Feature",
  "properties": {
    "gn:admin1_code":"19.0",
    "gn:asciiname":"Beiqinggoucun",
    "gn:country_code":"CN",
    "gn:dem":281,
    "gn:feature_class":"P",
    "gn:feature_code":"PPL",
    "gn:name":"Beiqinggoucun",
    "gn:population":0,
    "gn:timezone":"Asia/Shanghai",
    "iso:country":"CN",
    "name:zho_x_preferred":[
        "\u5317\u9752\u6c9f\u6751"
    ],
    "wof:name":"Beiqinggoucun",
    "wof:placetype":"locality"
},
  "geometry": {"coordinates":[124.68901,40.97317],"type":"Point"}
}