{
  "type": "Feature",
  "properties": {
    "gn:admin1_code":"25",
    "gn:asciiname":"Luzhuang",
    "gn:country_code":"CN",
    "gn:dem":35,
    "gn:feature_class":"P",
    "gn:feature_code":"PPL",
    "gn:name":"Luzhuang",
    "gn:population":0,
    "gn:timezone":"Asia/Shanghai",
    "iso:country":"CN",
    "name:und_x_variant":[
        "Ludong"
    ],
    "name:zho_x_preferred":[
        "\u8def\u5e84"
    ],
    "name:zho_x_variant":[
        "\u8def\u4e1c"
    ],
    "wof:name":"Luzhuang",
    "wof:placetype":"locality"
},
  "geometry": {"coordinates":[115.79935,36.52694],"type":"Point"}
}