{
  "type": "Feature",
  "properties": {
    "gn:admin1_code":"32.0",
    "gn:asciiname":"Aizigou",
    "gn:country_code":"CN",
    "gn:dem":1731,
    "gn:feature_class":"P",
    "gn:feature_code":"PPL",
    "gn:name":"Aizigou",
    "gn:population":0,
    "gn:timezone":"Asia/Shanghai",
    "iso:country":"CN",
    "name:zho_x_preferred":[
        "\u77ee\u5b50\u6c9f"
    ],
    "wof:name":"Aizigou",
    "wof:placetype":"locality"
},
  "geometry": {"coordinates":[101.583,28.1246],"type":"Point"}
}