{
  "type": "Feature",
  "properties": {
    "gn:admin1_code":"2.0",
    "gn:asciiname":"Daguixi",
    "gn:country_code":"CN",
    "gn:dem":84,
    "gn:feature_class":"P",
    "gn:feature_code":"PPL",
    "gn:name":"Daguixi",
    "gn:population":0,
    "gn:timezone":"Asia/Shanghai",
    "iso:country":"CN",
    "name:zho_x_preferred":[
        "\u5927\u8d35\u6eaa"
    ],
    "wof:name":"Daguixi",
    "wof:placetype":"locality"
},
  "geometry": {"coordinates":[121.52697999999999,29.33718],"type":"Point"}
}