{
  "type": "Feature",
  "properties": {
    "gn:admin1_code":"25",
    "gn:asciiname":"Donggucheng",
    "gn:country_code":"CN",
    "gn:dem":144,
    "gn:feature_class":"P",
    "gn:feature_code":"PPL",
    "gn:name":"Donggucheng",
    "gn:population":0,
    "gn:timezone":"Asia/Shanghai",
    "iso:country":"CN",
    "name:zho_x_preferred":[
        "\u4e1c\u580c\u57ce"
    ],
    "name:zho_x_variant":[
        "\u4e1c\u53e4\u57ce\u9547"
    ],
    "wof:name":"Donggucheng",
    "wof:placetype":"locality"
},
  "geometry": {"coordinates":[117.379,35.1621],"type":"Point"}
}