{
  "type": "Feature",
  "properties": {
    "gn:admin1_code":"22",
    "gn:asciiname":"Dadong",
    "gn:country_code":"CN",
    "gn:dem":64,
    "gn:feature_class":"P",
    "gn:feature_code":"PPL",
    "gn:name":"Dadong",
    "gn:population":0,
    "gn:timezone":"Asia/Shanghai",
    "iso:country":"CN",
    "name:zho_x_preferred":[
        "\u5927\u8463"
    ],
    "wof:name":"Dadong",
    "wof:placetype":"locality"
},
  "geometry": {"coordinates":[116.05306000000002,39.71559],"type":"Point"}
}