{
  "type": "Feature",
  "properties": {
    "gn:admin1_code":"29.0",
    "gn:asciiname":"Ouzhu",
    "gn:country_code":"CN",
    "gn:dem":1058,
    "gn:feature_class":"P",
    "gn:feature_code":"PPL",
    "gn:name":"Ouzhu",
    "gn:population":0,
    "gn:timezone":"Asia/Shanghai",
    "iso:country":"CN",
    "name:zho_x_preferred":[
        "\u6b27\u6731"
    ],
    "wof:name":"Ouzhu",
    "wof:placetype":"locality"
},
  "geometry": {"coordinates":[102.30500000000001,22.5965],"type":"Point"}
}