{
  "type": "Feature",
  "properties": {
    "gn:admin1_code":"15.0",
    "gn:asciiname":"Doujialiang",
    "gn:country_code":"CN",
    "gn:dem":1386,
    "gn:feature_class":"P",
    "gn:feature_code":"PPL",
    "gn:name":"Doujialiang",
    "gn:population":0,
    "gn:timezone":"Asia/Shanghai",
    "iso:country":"CN",
    "name:zho_x_preferred":[
        "\u8c46\u5bb6\u826f"
    ],
    "wof:name":"Doujialiang",
    "wof:placetype":"locality"
},
  "geometry": {"coordinates":[108.327,35.6809],"type":"Point"}
}