{
  "type": "Feature",
  "properties": {
    "gn:admin1_code":"29.0",
    "gn:asciiname":"Xianandong",
    "gn:country_code":"CN",
    "gn:dem":972,
    "gn:feature_class":"P",
    "gn:feature_code":"PPL",
    "gn:name":"Xianandong",
    "gn:population":0,
    "gn:timezone":"Asia/Shanghai",
    "iso:country":"CN",
    "name:zho_x_preferred":[
        "\u4e0b\u5357\u4e1c"
    ],
    "wof:name":"Xianandong",
    "wof:placetype":"locality"
},
  "geometry": {"coordinates":[97.8428,24.5474],"type":"Point"}
}