{
  "type": "Feature",
  "properties": {
    "gn:admin1_code":"4.0",
    "gn:asciiname":"Sanjucun",
    "gn:country_code":"CN",
    "gn:dem":4,
    "gn:feature_class":"P",
    "gn:feature_code":"PPL",
    "gn:name":"Sanjucun",
    "gn:population":0,
    "gn:timezone":"Asia/Shanghai",
    "iso:country":"CN",
    "name:zho_x_preferred":[
        "\u4e09\u82f4\u6751"
    ],
    "wof:name":"Sanjucun",
    "wof:placetype":"locality"
},
  "geometry": {"coordinates":[120.73291,32.72113],"type":"Point"}
}