{
  "type": "Feature",
  "properties": {
    "gn:admin1_code":"30.0",
    "gn:asciiname":"Datang",
    "gn:country_code":"CN",
    "gn:dem":56,
    "gn:feature_class":"P",
    "gn:feature_code":"PPL",
    "gn:name":"Datang",
    "gn:population":0,
    "gn:timezone":"Asia/Shanghai",
    "iso:country":"CN",
    "name:ceb_x_preferred":[
        "Datang"
    ],
    "name:ces_x_preferred":[
        "Ta-tchang"
    ],
    "name:deu_x_preferred":[
        "Datang"
    ],
    "name:nor_x_preferred":[
        "Datang"
    ],
    "name:swe_x_preferred":[
        "Datang"
    ],
    "name:zho_x_preferred":[
        "\u5927\u5858"
    ],
    "wof:name":"Datang",
    "wof:placetype":"locality"
},
  "geometry": {"coordinates":[112.37008,22.5159],"type":"Point"}
}