{
  "type": "Feature",
  "properties": {
    "gn:admin1_code":"29.0",
    "gn:asciiname":"Maliping Dazhai",
    "gn:country_code":"CN",
    "gn:dem":1706,
    "gn:feature_class":"P",
    "gn:feature_code":"PPL",
    "gn:name":"Maliping Dazhai",
    "gn:population":0,
    "gn:timezone":"Asia/Shanghai",
    "iso:country":"CN",
    "name:zho_x_preferred":[
        "\u9ebb\u6817\u576a\u5927\u5be8"
    ],
    "wof:name":"Maliping Dazhai",
    "wof:placetype":"locality"
},
  "geometry": {"coordinates":[99.76220000000001,22.9786],"type":"Point"}
}