{
  "type": "Feature",
  "properties": {
    "gn:admin1_code":"9.0",
    "gn:asciiname":"Diaotan",
    "gn:country_code":"CN",
    "gn:dem":251,
    "gn:feature_class":"P",
    "gn:feature_code":"PPL",
    "gn:name":"Diaotan",
    "gn:population":0,
    "gn:timezone":"Asia/Shanghai",
    "iso:country":"CN",
    "name:zho_x_preferred":[
        "\u540a\u6ee9"
    ],
    "wof:name":"Diaotan",
    "wof:placetype":"locality"
},
  "geometry": {"coordinates":[111.64503000000001,34.93829],"type":"Point"}
}