{
  "type": "Feature",
  "properties": {
    "gn:admin1_code":"29.0",
    "gn:asciiname":"Xinzhai",
    "gn:country_code":"CN",
    "gn:dem":1435,
    "gn:feature_class":"P",
    "gn:feature_code":"PPL",
    "gn:name":"Xinzhai",
    "gn:population":0,
    "gn:timezone":"Asia/Shanghai",
    "iso:country":"CN",
    "name:nor_x_preferred":[
        "Xinzhai"
    ],
    "name:swe_x_preferred":[
        "Xinzhai"
    ],
    "name:zho_x_preferred":[
        "\u65b0\u5be8"
    ],
    "name:zho_x_variant":[
        "\u65b0\u7826\u9057\u5740"
    ],
    "wof:name":"Xinzhai",
    "wof:placetype":"locality"
},
  "geometry": {"coordinates":[104.387,24.8527],"type":"Point"}
}