{
  "type": "Feature",
  "properties": {
    "gn:admin1_code":"29.0",
    "gn:asciiname":"Dawolong",
    "gn:country_code":"CN",
    "gn:dem":1305,
    "gn:feature_class":"P",
    "gn:feature_code":"PPL",
    "gn:name":"Dawolong",
    "gn:population":0,
    "gn:timezone":"Asia/Shanghai",
    "iso:country":"CN",
    "name:zho_x_preferred":[
        "\u5927\u5367\u9f99"
    ],
    "wof:name":"Dawolong",
    "wof:placetype":"locality"
},
  "geometry": {"coordinates":[101.65000000000001,23.5488],"type":"Point"}
}