{
  "type": "Feature",
  "properties": {
    "gn:admin1_code":"15.0",
    "gn:asciiname":"Linziba",
    "gn:country_code":"CN",
    "gn:dem":1344,
    "gn:feature_class":"P",
    "gn:feature_code":"PPL",
    "gn:name":"Linziba",
    "gn:population":0,
    "gn:timezone":"Asia/Shanghai",
    "iso:country":"CN",
    "name:und_x_variant":[
        "\u541d\u5b50\u575d"
    ],
    "name:zho_x_preferred":[
        "\u541d\u5b50\u575d"
    ],
    "wof:name":"Linziba",
    "wof:placetype":"locality"
},
  "geometry": {"coordinates":[104.59873,32.93119],"type":"Point"}
}