{
  "type": "Feature",
  "properties": {
    "gn:admin1_code":"02",
    "gn:asciiname":"Huajiadou",
    "gn:country_code":"CN",
    "gn:dem":6,
    "gn:feature_class":"P",
    "gn:feature_code":"PPL",
    "gn:name":"Huajiadou",
    "gn:population":0,
    "gn:timezone":"Asia/Shanghai",
    "iso:country":"CN",
    "name:und_x_variant":[
        "\u534e\u5bb6\u515c",
        "Wan-li"
    ],
    "wof:name":"Huajiadou",
    "wof:placetype":"locality"
},
  "geometry": {"coordinates":[120.72389,30.41278],"type":"Point"}
}