{
  "type": "Feature",
  "properties": {
    "gn:admin1_code":"26.0",
    "gn:asciiname":"Yindonggou",
    "gn:country_code":"CN",
    "gn:dem":558,
    "gn:feature_class":"P",
    "gn:feature_code":"PPL",
    "gn:name":"Yindonggou",
    "gn:population":0,
    "gn:timezone":"Asia/Shanghai",
    "iso:country":"CN",
    "name:und_x_variant":[
        "\u94f6\u6d1e\u6c9f"
    ],
    "wof:name":"Yindonggou",
    "wof:placetype":"locality"
},
  "geometry": {"coordinates":[107.54076000000001,32.91892],"type":"Point"}
}