{
  "type": "Feature",
  "properties": {
    "gn:admin1_code":"33.0",
    "gn:asciiname":"Mengzi",
    "gn:country_code":"CN",
    "gn:dem":186,
    "gn:feature_class":"P",
    "gn:feature_code":"PPL",
    "gn:name":"Mengzi",
    "gn:population":0,
    "gn:timezone":"Asia/Shanghai",
    "iso:country":"CN",
    "name:ceb_x_preferred":[
        "Mengzi"
    ],
    "name:deu_x_preferred":[
        "Mengzi"
    ],
    "name:fra_x_preferred":[
        "Mengzi"
    ],
    "name:nld_x_preferred":[
        "Mengzi"
    ],
    "name:nor_x_preferred":[
        "Mengzi"
    ],
    "name:swe_x_preferred":[
        "Mengzi"
    ],
    "name:zho_x_preferred":[
        "\u6aac\u5b50"
    ],
    "wof:name":"Mengzi",
    "wof:placetype":"locality"
},
  "geometry": {"coordinates":[106.3865,29.20552],"type":"Point"}
}