{
  "type": "Feature",
  "properties": {
    "gn:admin1_code":"18",
    "gn:asciiname":"Jichang",
    "gn:cc2":"CN",
    "gn:country_code":"CN",
    "gn:dem":1265,
    "gn:feature_class":"P",
    "gn:feature_code":"PPL",
    "gn:name":"Jichang",
    "gn:population":0,
    "gn:timezone":"Asia/Shanghai",
    "iso:country":"CN",
    "name:und_x_variant":[
        "Chi-ch\u2019ang",
        "Jichang"
    ],
    "wof:name":"Jichang",
    "wof:placetype":"locality"
},
  "geometry": {"coordinates":[106.06667,26.06667],"type":"Point"}
}