{
  "type": "Feature",
  "properties": {
    "gn:admin1_code":"16.0",
    "gn:asciiname":"Douya",
    "gn:country_code":"CN",
    "gn:dem":711,
    "gn:feature_class":"P",
    "gn:feature_code":"PPL",
    "gn:name":"Douya",
    "gn:population":0,
    "gn:timezone":"Asia/Shanghai",
    "iso:country":"CN",
    "name:zho_x_preferred":[
        "\u8c46\u7259"
    ],
    "wof:name":"Douya",
    "wof:placetype":"locality"
},
  "geometry": {"coordinates":[107.01300000000001,25.2597],"type":"Point"}
}