{
  "type": "Feature",
  "properties": {
    "gn:admin1_code":"04",
    "gn:asciiname":"Qiqiao",
    "gn:country_code":"CN",
    "gn:dem":25,
    "gn:feature_class":"P",
    "gn:feature_code":"PPLA4",
    "gn:name":"Qiqiao",
    "gn:population":0,
    "gn:timezone":"Asia/Shanghai",
    "iso:country":"CN",
    "name:und_x_variant":[
        "Ch\u2019i-ch\u2019iao",
        "Qiqiao",
        "Qiqiao Zhen"
    ],
    "name:zho_x_preferred":[
        "\u6f06\u6865"
    ],
    "name:zho_x_variant":[
        "\u6f06\u6865\u9547"
    ],
    "wof:name":"Qiqiao",
    "wof:placetype":"locality"
},
  "geometry": {"coordinates":[118.9871,31.38798],"type":"Point"}
}