{
  "type": "Feature",
  "properties": {
    "gn:admin1_code":"20.0",
    "gn:asciiname":"Guihuanan",
    "gn:country_code":"CN",
    "gn:dem":424,
    "gn:feature_class":"P",
    "gn:feature_code":"PPL",
    "gn:name":"Guihuanan",
    "gn:population":0,
    "gn:timezone":"Asia/Shanghai",
    "iso:country":"CN",
    "name:zho_x_preferred":[
        "\u6842\u82b1\u5357"
    ],
    "wof:name":"Guihuanan",
    "wof:placetype":"locality"
},
  "geometry": {"coordinates":[122.08889000000001,47.53774],"type":"Point"}
}