{
  "type": "Feature",
  "properties": {
    "gn:admin1_code":"16",
    "gn:asciiname":"Daliang",
    "gn:cc2":"CN",
    "gn:country_code":"CN",
    "gn:dem":191,
    "gn:feature_class":"P",
    "gn:feature_code":"PPL",
    "gn:name":"Daliang",
    "gn:population":0,
    "gn:timezone":"Asia/Shanghai",
    "iso:country":"CN",
    "name:ceb_x_preferred":[
        "Daliang"
    ],
    "name:swe_x_preferred":[
        "Daliang"
    ],
    "name:und_x_variant":[
        "Ta-liang"
    ],
    "wof:name":"Daliang",
    "wof:placetype":"locality"
},
  "geometry": {"coordinates":[109.33194,24.83333],"type":"Point"}
}