{
  "type": "Feature",
  "properties": {
    "gn:admin1_code":"3.0",
    "gn:asciiname":"Xiaoyang Zhoujia",
    "gn:country_code":"CN",
    "gn:dem":41,
    "gn:feature_class":"P",
    "gn:feature_code":"PPL",
    "gn:name":"Xiaoyang Zhoujia",
    "gn:population":0,
    "gn:timezone":"Asia/Shanghai",
    "iso:country":"CN",
    "name:und_x_variant":[
        "\u5c0f\u6d0b\u5468\u5bb6"
    ],
    "wof:name":"Xiaoyang Zhoujia",
    "wof:placetype":"locality"
},
  "geometry": {"coordinates":[115.39221999999999,28.05814],"type":"Point"}
}