{
  "type": "Feature",
  "properties": {
    "gn:admin1_code":"14",
    "gn:asciiname":"Qumuduonuba",
    "gn:country_code":"CN",
    "gn:dem":3469,
    "gn:feature_class":"P",
    "gn:feature_code":"PPL",
    "gn:name":"Qumuduonuba",
    "gn:population":0,
    "gn:timezone":"Asia/Urumqi",
    "iso:country":"CN",
    "name:zho_x_preferred":[
        "\u66f2\u59c6\u591a\u5974\u5df4"
    ],
    "wof:name":"Qumuduonuba",
    "wof:placetype":"locality"
},
  "geometry": {"coordinates":[88.8844,27.4523],"type":"Point"}
}