{
  "type": "Feature",
  "properties": {
    "gn:admin1_code":"4.0",
    "gn:asciiname":"Beizhuang",
    "gn:country_code":"CN",
    "gn:dem":12,
    "gn:feature_class":"P",
    "gn:feature_code":"PPL",
    "gn:name":"Beizhuang",
    "gn:population":0,
    "gn:timezone":"Asia/Shanghai",
    "iso:country":"CN",
    "name:zho_x_preferred":[
        "\u8d1d\u5e84"
    ],
    "name:zho_x_variant":[
        "\u5317\u5e84\u9547"
    ],
    "wof:name":"Beizhuang",
    "wof:placetype":"locality"
},
  "geometry": {"coordinates":[118.92100000000001,33.2276],"type":"Point"}
}