{
  "type": "Feature",
  "properties": {
    "gn:admin1_code":"18",
    "gn:asciiname":"Dahuashao",
    "gn:country_code":"CN",
    "gn:dem":1009,
    "gn:feature_class":"P",
    "gn:feature_code":"PPL",
    "gn:name":"Dahuashao",
    "gn:population":0,
    "gn:timezone":"Asia/Shanghai",
    "iso:country":"CN",
    "name:zho_x_preferred":[
        "\u5927\u82b1\u54e8"
    ],
    "wof:name":"Dahuashao",
    "wof:placetype":"locality"
},
  "geometry": {"coordinates":[105.64,25.9627],"type":"Point"}
}