{
  "type": "Feature",
  "properties": {
    "gn:admin1_code":"4.0",
    "gn:asciiname":"Gaolou",
    "gn:country_code":"CN",
    "gn:dem":6,
    "gn:feature_class":"P",
    "gn:feature_code":"PPL",
    "gn:name":"Gaolou",
    "gn:population":0,
    "gn:timezone":"Asia/Shanghai",
    "iso:country":"CN",
    "name:ceb_x_preferred":[
        "Gaolou"
    ],
    "name:swe_x_preferred":[
        "Gaolou"
    ],
    "name:zho_x_preferred":[
        "\u9ad8\u697c"
    ],
    "name:zho_x_variant":[
        "\u9ad8\u697c\u9547"
    ],
    "wof:name":"Gaolou",
    "wof:placetype":"locality"
},
  "geometry": {"coordinates":[119.59636,32.03357],"type":"Point"}
}