{
  "type": "Feature",
  "properties": {
    "gn:admin1_code":"25.0",
    "gn:asciiname":"Lagezhuangcun",
    "gn:country_code":"CN",
    "gn:dem":100,
    "gn:feature_class":"P",
    "gn:feature_code":"PPL",
    "gn:name":"Lagezhuangcun",
    "gn:population":0,
    "gn:timezone":"Asia/Shanghai",
    "iso:country":"CN",
    "name:zho_x_preferred":[
        "\u62c9\u683c\u5e84\u6751"
    ],
    "wof:name":"Lagezhuangcun",
    "wof:placetype":"locality"
},
  "geometry": {"coordinates":[120.20057,37.38045],"type":"Point"}
}