{
  "type": "Feature",
  "properties": {
    "gn:admin1_code":"1.0",
    "gn:asciiname":"Xinghongcun",
    "gn:country_code":"CN",
    "gn:dem":165,
    "gn:feature_class":"P",
    "gn:feature_code":"PPL",
    "gn:name":"Xinghongcun",
    "gn:population":0,
    "gn:timezone":"Asia/Shanghai",
    "iso:country":"CN",
    "name:zho_x_preferred":[
        "\u661f\u7ea2\u6751"
    ],
    "wof:name":"Xinghongcun",
    "wof:placetype":"locality"
},
  "geometry": {"coordinates":[118.15339,29.60176],"type":"Point"}
}