{
  "type": "Feature",
  "properties": {
    "gn:admin1_code":"18",
    "gn:asciiname":"Yejiapo",
    "gn:country_code":"CN",
    "gn:dem":1356,
    "gn:feature_class":"P",
    "gn:feature_code":"PPL",
    "gn:name":"Yejiapo",
    "gn:population":0,
    "gn:timezone":"Asia/Shanghai",
    "iso:country":"CN",
    "name:zho_x_preferred":[
        "\u53f6\u5bb6\u5761"
    ],
    "wof:name":"Yejiapo",
    "wof:placetype":"locality"
},
  "geometry": {"coordinates":[106.934,26.8238],"type":"Point"}
}