{
  "type": "Feature",
  "properties": {
    "gn:admin1_code":"19.0",
    "gn:asciiname":"Majiadiancun",
    "gn:country_code":"CN",
    "gn:dem":114,
    "gn:feature_class":"P",
    "gn:feature_code":"PPL",
    "gn:name":"Majiadiancun",
    "gn:population":0,
    "gn:timezone":"Asia/Shanghai",
    "iso:country":"CN",
    "name:zho_x_preferred":[
        "\u9a6c\u5bb6\u5e97\u6751"
    ],
    "wof:name":"Majiadiancun",
    "wof:placetype":"locality"
},
  "geometry": {"coordinates":[124.14107,43.08308],"type":"Point"}
}