{
  "type": "Feature",
  "properties": {
    "gn:admin1_code":"4.0",
    "gn:asciiname":"Liuxiaoyingcun",
    "gn:country_code":"CN",
    "gn:dem":36,
    "gn:feature_class":"P",
    "gn:feature_code":"PPL",
    "gn:name":"Liuxiaoyingcun",
    "gn:population":0,
    "gn:timezone":"Asia/Shanghai",
    "iso:country":"CN",
    "name:zho_x_preferred":[
        "\u5218\u5c0f\u8425\u6751"
    ],
    "wof:name":"Liuxiaoyingcun",
    "wof:placetype":"locality"
},
  "geometry": {"coordinates":[116.62152,34.8443],"type":"Point"}
}