{
  "type": "Feature",
  "properties": {
    "gn:admin1_code":"29",
    "gn:asciiname":"Nabai",
    "gn:country_code":"CN",
    "gn:dem":811,
    "gn:feature_class":"P",
    "gn:feature_code":"PPL",
    "gn:name":"Nabai",
    "gn:population":0,
    "gn:timezone":"Asia/Shanghai",
    "iso:country":"CN",
    "name:zho_x_preferred":[
        "\u90a3\u62dc"
    ],
    "wof:name":"Nabai",
    "wof:placetype":"locality"
},
  "geometry": {"coordinates":[105.76300000000001,24.0655],"type":"Point"}
}