{
  "type": "Feature",
  "properties": {
    "gn:admin1_code":"3",
    "gn:asciiname":"Fenshui'ao",
    "gn:country_code":"CN",
    "gn:dem":141,
    "gn:feature_class":"P",
    "gn:feature_code":"PPL",
    "gn:name":"Fenshui\u2019ao",
    "gn:population":0,
    "gn:timezone":"Asia/Shanghai",
    "iso:country":"CN",
    "name:und_x_variant":[
        "Fenshui\u2019ao"
    ],
    "name:zho_x_preferred":[
        "\u5206\u6c34\u5773"
    ],
    "wof:name":"Fenshui'ao",
    "wof:placetype":"locality"
},
  "geometry": {"coordinates":[114.645,25.549],"type":"Point"}
}