{
  "type": "Feature",
  "properties": {
    "gn:admin1_code":"10",
    "gn:asciiname":"Baodi",
    "gn:country_code":"CN",
    "gn:dem":548,
    "gn:feature_class":"P",
    "gn:feature_code":"PPL",
    "gn:name":"Baodi",
    "gn:population":0,
    "gn:timezone":"Asia/Shanghai",
    "iso:country":"CN",
    "name:und_x_variant":[
        "Pao-ti"
    ],
    "name:zho_x_preferred":[
        "\u5b9d\u5730"
    ],
    "wof:name":"Baodi",
    "wof:placetype":"locality"
},
  "geometry": {"coordinates":[117.72221999999999,40.43583],"type":"Point"}
}