{
  "type": "Feature",
  "properties": {
    "gn:admin1_code":"08",
    "gn:asciiname":"Lianjiangkou",
    "gn:country_code":"CN",
    "gn:dem":81,
    "gn:feature_class":"P",
    "gn:feature_code":"PPLA4",
    "gn:name":"Lianjiangkou",
    "gn:population":0,
    "gn:timezone":"Asia/Shanghai",
    "iso:country":"CN",
    "name:und_x_variant":[
        "Ud\u0101gan",
        "Lien-chiang-k\u2019ou-chen",
        "Lien-chiang-k\u2019ou",
        "Lianjiangkou",
        "Lianjiangkou Zhen"
    ],
    "name:zho_x_preferred":[
        "\u83b2\u6c5f\u53e3"
    ],
    "name:zho_x_variant":[
        "\u83b2\u6c5f\u53e3\u9547"
    ],
    "wof:name":"Lianjiangkou",
    "wof:placetype":"locality"
},
  "geometry": {"coordinates":[130.30756,46.86185],"type":"Point"}
}