{
  "type": "Feature",
  "properties": {
    "gn:admin1_code":"15",
    "gn:asciiname":"Maojing",
    "gn:country_code":"CN",
    "gn:dem":1765,
    "gn:feature_class":"P",
    "gn:feature_code":"PPLA4",
    "gn:name":"Maojing",
    "gn:population":0,
    "gn:timezone":"Asia/Shanghai",
    "iso:country":"CN",
    "name:und_x_variant":[
        "Mao-ching",
        "Maojing",
        "\u6bdb\u4e95",
        "Maojing Xiang",
        "\u6bdb\u4e95\u4e61"
    ],
    "wof:name":"Maojing",
    "wof:placetype":"locality"
},
  "geometry": {"coordinates":[106.60656000000002,36.46448],"type":"Point"}
}