{
  "type": "Feature",
  "properties": {
    "gn:admin1_code":"9.0",
    "gn:asciiname":"Dinggang",
    "gn:country_code":"CN",
    "gn:dem":59,
    "gn:feature_class":"P",
    "gn:feature_code":"PPL",
    "gn:name":"Dinggang",
    "gn:population":0,
    "gn:timezone":"Asia/Shanghai",
    "iso:country":"CN",
    "name:zho_x_preferred":[
        "\u4e01\u5c97"
    ],
    "wof:name":"Dinggang",
    "wof:placetype":"locality"
},
  "geometry": {"coordinates":[114.22132999999999,34.00291],"type":"Point"}
}