{
  "type": "Feature",
  "properties": {
    "gn:admin1_code":"11.0",
    "gn:asciiname":"Chengxialong",
    "gn:country_code":"CN",
    "gn:dem":78,
    "gn:feature_class":"P",
    "gn:feature_code":"PPL",
    "gn:name":"Chengxialong",
    "gn:population":0,
    "gn:timezone":"Asia/Shanghai",
    "iso:country":"CN",
    "name:zho_x_preferred":[
        "\u4e58\u971e\u5785"
    ],
    "wof:name":"Chengxialong",
    "wof:placetype":"locality"
},
  "geometry": {"coordinates":[113.19152,27.65799],"type":"Point"}
}