{
  "type": "Feature",
  "properties": {
    "gn:admin1_code":"29.0",
    "gn:asciiname":"Longlaza",
    "gn:country_code":"CN",
    "gn:dem":1779,
    "gn:feature_class":"P",
    "gn:feature_code":"PPL",
    "gn:name":"Longlaza",
    "gn:population":0,
    "gn:timezone":"Asia/Shanghai",
    "iso:country":"CN",
    "name:zho_x_preferred":[
        "\u9f99\u5587\u6742"
    ],
    "wof:name":"Longlaza",
    "wof:placetype":"locality"
},
  "geometry": {"coordinates":[102.095,25.279],"type":"Point"}
}