{
  "type": "Feature",
  "properties": {
    "gn:admin1_code":"07",
    "gn:asciiname":"Licuo",
    "gn:country_code":"CN",
    "gn:dem":539,
    "gn:feature_class":"P",
    "gn:feature_code":"PPL",
    "gn:name":"Licuo",
    "gn:population":0,
    "gn:timezone":"Asia/Shanghai",
    "iso:country":"CN",
    "name:zho_x_preferred":[
        "\u674e\u539d"
    ],
    "wof:name":"Licuo",
    "wof:placetype":"locality"
},
  "geometry": {"coordinates":[118.20417,25.51111],"type":"Point"}
}