{
  "type": "Feature",
  "properties": {
    "gn:admin1_code":"2.0",
    "gn:asciiname":"Dongzhubang",
    "gn:country_code":"CN",
    "gn:dem":7,
    "gn:feature_class":"P",
    "gn:feature_code":"PPL",
    "gn:name":"Dongzhubang",
    "gn:population":0,
    "gn:timezone":"Asia/Shanghai",
    "iso:country":"CN",
    "name:und_x_variant":[
        "\u4e1c\u73e0\u6d5c"
    ],
    "wof:name":"Dongzhubang",
    "wof:placetype":"locality"
},
  "geometry": {"coordinates":[120.79145,30.94839],"type":"Point"}
}