{
  "type": "Feature",
  "properties": {
    "gn:admin1_code":"26.0",
    "gn:asciiname":"Heihe",
    "gn:country_code":"CN",
    "gn:dem":1095,
    "gn:feature_class":"P",
    "gn:feature_code":"PPL",
    "gn:name":"Heihe",
    "gn:population":0,
    "gn:timezone":"Asia/Shanghai",
    "iso:country":"CN",
    "name:ara_x_preferred":[
        "\u062e\u064a\u062e\u0647"
    ],
    "name:bak_x_preferred":[
        "\u0425\u044d\u0439\u0445\u044d"
    ],
    "name:cdo_x_preferred":[
        "H\u00e1ik-\u00f2\u0324"
    ],
    "name:ceb_x_preferred":[
        "Heihe"
    ],
    "name:ces_x_preferred":[
        "Chej-che"
    ],
    "name:dan_x_preferred":[
        "Heihe"
    ],
    "name:deu_x_preferred":[
        "Heihe"
    ],
    "name:ell_x_preferred":[
        "\u03a7\u03ad\u03b9\u03c7\u03b5"
    ],
    "name:epo_x_preferred":[
        "Heihe"
    ],
    "name:est_x_preferred":[
        "Heihe Shi"
    ],
    "name:eus_x_preferred":[
        "Heihe"
    ],
    "name:fas_x_preferred":[
        "\u0647\u0627\u06cc\u0647\u06cc"
    ],
    "name:fin_x_preferred":[
        "Heihe"
    ],
    "name:fra_x_preferred":[
        "Heihe"
    ],
    "name:hin_x_preferred":[
        "\u0939\u0947\u0907\u0939\u0947"
    ],
    "name:ind_x_preferred":[
        "Heihe"
    ],
    "name:ita_x_preferred":[
        "Heihe"
    ],
    "name:jpn_x_preferred":[
        "\u9ed2\u6cb3"
    ],
    "name:jpn_x_variant":[
        "\u9ed2\u6cb3\u5e02"
    ],
    "name:kik_x_preferred":[
        "Heihe"
    ],
    "name:kor_x_preferred":[
        "\ud5e4\uc774\ud5c8\uc2dc"
    ],
    "name:mlg_x_preferred":[
        "Heihe"
    ],
    "name:nld_x_preferred":[
        "Heihe"
    ],
    "name:nno_x_preferred":[
        "Heihe"
    ],
    "name:nor_x_preferred":[
        "Heihe"
    ],
    "name:pam_x_preferred":[
        "Heihe"
    ],
    "name:pol_x_preferred":[
        "Heihe"
    ],
    "name:por_x_preferred":[
        "Heihe"
    ],
    "name:rus_x_preferred":[
        "\u0425\u044d\u0439\u0445\u044d"
    ],
    "name:sah_x_preferred":[
        "\u0425\u044d\u0439\u0445\u044d"
    ],
    "name:spa_x_preferred":[
        "Heihe"
    ],
    "name:swe_x_preferred":[
        "Heihe"
    ],
    "name:tgl_x_preferred":[
        "Heihe"
    ],
    "name:tur_x_preferred":[
        "Heihe"
    ],
    "name:urd_x_preferred":[
        "\u06c1\u0626\u06cc\u06c1\u06d2"
    ],
    "name:vie_x_preferred":[
        "H\u1eafc H\u00e0"
    ],
    "name:war_x_preferred":[
        "Heihe"
    ],
    "name:wuu_x_preferred":[
        "\u9ed1\u6cb3\u5e02"
    ],
    "name:zho_x_preferred":[
        "\u9ed1\u6cb3"
    ],
    "name:zho_x_variant":[
        "\u9ed1\u6cb3\u5e02"
    ],
    "wof:name":"Heihe",
    "wof:placetype":"locality"
},
  "geometry": {"coordinates":[109.05588,38.01232],"type":"Point"}
}