{
  "type": "Feature",
  "properties": {
    "gn:admin1_code":"18.0",
    "gn:asciiname":"Xiamaoliping",
    "gn:country_code":"CN",
    "gn:dem":1105,
    "gn:feature_class":"P",
    "gn:feature_code":"PPL",
    "gn:name":"Xiamaoliping",
    "gn:population":0,
    "gn:timezone":"Asia/Shanghai",
    "iso:country":"CN",
    "name:zho_x_preferred":[
        "\u4e0b\u6bdb\u6817\u576a"
    ],
    "wof:name":"Xiamaoliping",
    "wof:placetype":"locality"
},
  "geometry": {"coordinates":[108.486,27.478],"type":"Point"}
}