{
  "type": "Feature",
  "properties": {
    "gn:admin1_code":"25.0",
    "gn:asciiname":"Guangchenjia",
    "gn:country_code":"CN",
    "gn:dem":79,
    "gn:feature_class":"P",
    "gn:feature_code":"PPL",
    "gn:name":"Guangchenjia",
    "gn:population":0,
    "gn:timezone":"Asia/Shanghai",
    "iso:country":"CN",
    "name:zho_x_preferred":[
        "\u5149\u9648\u5bb6"
    ],
    "wof:name":"Guangchenjia",
    "wof:placetype":"locality"
},
  "geometry": {"coordinates":[119.91798,37.11445],"type":"Point"}
}