{
  "type": "Feature",
  "properties": {
    "gn:admin1_code":"33.0",
    "gn:asciiname":"Yuxing",
    "gn:country_code":"CN",
    "gn:dem":462,
    "gn:feature_class":"P",
    "gn:feature_code":"PPL",
    "gn:name":"Yuxing",
    "gn:population":0,
    "gn:timezone":"Asia/Shanghai",
    "iso:country":"CN",
    "name:zho_x_preferred":[
        "\u6109\u5e78"
    ],
    "wof:name":"Yuxing",
    "wof:placetype":"locality"
},
  "geometry": {"coordinates":[108.10099,30.58105],"type":"Point"}
}