{
  "type": "Feature",
  "properties": {
    "gn:admin1_code":"9.0",
    "gn:asciiname":"Tangwangqiao",
    "gn:country_code":"CN",
    "gn:dem":135,
    "gn:feature_class":"P",
    "gn:feature_code":"PPL",
    "gn:name":"Tangwangqiao",
    "gn:population":0,
    "gn:timezone":"Asia/Shanghai",
    "iso:country":"CN",
    "name:zho_x_preferred":[
        "\u5510\u738b\u6865"
    ],
    "wof:name":"Tangwangqiao",
    "wof:placetype":"locality"
},
  "geometry": {"coordinates":[111.86127,32.70385],"type":"Point"}
}