{
  "type": "Feature",
  "properties": {
    "gn:admin1_code":"29.0",
    "gn:asciiname":"Anhejie",
    "gn:country_code":"CN",
    "gn:dem":2155,
    "gn:feature_class":"P",
    "gn:feature_code":"PPL",
    "gn:name":"Anhejie",
    "gn:population":0,
    "gn:timezone":"Asia/Shanghai",
    "iso:country":"CN",
    "name:zho_x_preferred":[
        "\u5b89\u548c\u8857"
    ],
    "wof:name":"Anhejie",
    "wof:placetype":"locality"
},
  "geometry": {"coordinates":[99.37139999999999,25.1911],"type":"Point"}
}