{
  "type": "Feature",
  "properties": {
    "gn:admin1_code":"5.0",
    "gn:asciiname":"Zhongyingcun",
    "gn:country_code":"CN",
    "gn:dem":329,
    "gn:feature_class":"P",
    "gn:feature_code":"PPL",
    "gn:name":"Zhongyingcun",
    "gn:population":0,
    "gn:timezone":"Asia/Shanghai",
    "iso:country":"CN",
    "name:zho_x_preferred":[
        "\u4e2d\u8425\u6751"
    ],
    "wof:name":"Zhongyingcun",
    "wof:placetype":"locality"
},
  "geometry": {"coordinates":[127.23425,44.15572],"type":"Point"}
}