{
  "type": "Feature",
  "properties": {
    "gn:admin1_code":"5.0",
    "gn:asciiname":"Fuyucun",
    "gn:country_code":"CN",
    "gn:dem":136,
    "gn:feature_class":"P",
    "gn:feature_code":"PPL",
    "gn:name":"Fuyucun",
    "gn:population":0,
    "gn:timezone":"Asia/Shanghai",
    "iso:country":"CN",
    "name:zho_x_preferred":[
        "\u9644\u4f59\u6751"
    ],
    "wof:name":"Fuyucun",
    "wof:placetype":"locality"
},
  "geometry": {"coordinates":[124.10311000000002,45.14386],"type":"Point"}
}