{
  "type": "Feature",
  "properties": {
    "gn:admin1_code":"3.0",
    "gn:asciiname":"Zhongfan",
    "gn:country_code":"CN",
    "gn:dem":65,
    "gn:feature_class":"P",
    "gn:feature_code":"PPLA4",
    "gn:name":"Zhongfan",
    "gn:population":0,
    "gn:timezone":"Asia/Shanghai",
    "iso:country":"CN",
    "name:und_x_variant":[
        "Zhongfan Xiang",
        "\u4e2d\u7548\u4e61",
        "Zhongfan"
    ],
    "name:zho_x_preferred":[
        "\u4e2d\u7548"
    ],
    "wof:name":"Zhongfan",
    "wof:placetype":"locality"
},
  "geometry": {"coordinates":[117.37820000000001,28.54038],"type":"Point"}
}