{
  "type": "Feature",
  "properties": {
    "gn:admin1_code":"1.0",
    "gn:asciiname":"Laozhangmiaocun",
    "gn:country_code":"CN",
    "gn:dem":30,
    "gn:feature_class":"P",
    "gn:feature_code":"PPL",
    "gn:name":"Laozhangmiaocun",
    "gn:population":0,
    "gn:timezone":"Asia/Shanghai",
    "iso:country":"CN",
    "name:zho_x_preferred":[
        "\u8001\u5f20\u5e99\u6751"
    ],
    "wof:name":"Laozhangmiaocun",
    "wof:placetype":"locality"
},
  "geometry": {"coordinates":[115.86346,32.95401],"type":"Point"}
}