{
  "type": "Feature",
  "properties": {
    "gn:admin1_code":"2.0",
    "gn:asciiname":"Muchengyuan",
    "gn:country_code":"CN",
    "gn:dem":157,
    "gn:feature_class":"P",
    "gn:feature_code":"PPL",
    "gn:name":"Muchengyuan",
    "gn:population":0,
    "gn:timezone":"Asia/Shanghai",
    "iso:country":"CN",
    "name:und_x_variant":[
        "\u7a46\u6f84\u6e90",
        "Muchengyuan"
    ],
    "wof:name":"Muchengyuan",
    "wof:placetype":"locality"
},
  "geometry": {"coordinates":[119.58886,29.25548],"type":"Point"}
}