{
  "type": "Feature",
  "properties": {
    "gn:admin1_code":"7",
    "gn:asciiname":"Shuangdihuaqiao Nongchang",
    "gn:country_code":"CN",
    "gn:dem":60,
    "gn:feature_class":"P",
    "gn:feature_code":"PPLF",
    "gn:name":"Shuangdihuaqiao Nongchang",
    "gn:population":0,
    "gn:timezone":"Asia/Shanghai",
    "iso:country":"CN",
    "wof:name":"Shuangdihuaqiao Nongchang",
    "wof:placetype":"locality"
},
  "geometry": {"coordinates":[117.71138999999999,24.40194],"type":"Point"}
}