{
  "type": "Feature",
  "properties": {
    "gn:admin1_code":"24.0",
    "gn:asciiname":"Shenjiazhuang",
    "gn:country_code":"CN",
    "gn:dem":747,
    "gn:feature_class":"P",
    "gn:feature_code":"PPL",
    "gn:name":"Shenjiazhuang",
    "gn:population":0,
    "gn:timezone":"Asia/Shanghai",
    "iso:country":"CN",
    "name:zho_x_preferred":[
        "\u7533\u5bb6\u5e84"
    ],
    "wof:name":"Shenjiazhuang",
    "wof:placetype":"locality"
},
  "geometry": {"coordinates":[112.56869,35.67129],"type":"Point"}
}