{
  "type": "Feature",
  "properties": {
    "gn:admin1_code":"5.0",
    "gn:asciiname":"Songjia Weizi",
    "gn:country_code":"CN",
    "gn:dem":178,
    "gn:feature_class":"P",
    "gn:feature_code":"PPL",
    "gn:name":"Songjia Weizi",
    "gn:population":0,
    "gn:timezone":"Asia/Shanghai",
    "iso:country":"CN",
    "name:zho_x_preferred":[
        "\u5b8b\u5bb6\u56f4\u5b50"
    ],
    "wof:name":"Songjia Weizi",
    "wof:placetype":"locality"
},
  "geometry": {"coordinates":[122.44455000000001,45.62045],"type":"Point"}
}