{
  "type": "Feature",
  "properties": {
    "gn:admin1_code":"18.0",
    "gn:asciiname":"Lantou",
    "gn:country_code":"CN",
    "gn:dem":934,
    "gn:feature_class":"P",
    "gn:feature_code":"PPL",
    "gn:name":"Lantou",
    "gn:population":0,
    "gn:timezone":"Asia/Shanghai",
    "iso:country":"CN",
    "wof:name":"Lantou",
    "wof:placetype":"locality"
},
  "geometry": {"coordinates":[106.49889,27.41333],"type":"Point"}
}