{
  "type": "Feature",
  "properties": {
    "gn:admin1_code":"30.0",
    "gn:asciiname":"Shangshixia",
    "gn:country_code":"CN",
    "gn:dem":342,
    "gn:feature_class":"P",
    "gn:feature_code":"PPL",
    "gn:name":"Shangshixia",
    "gn:population":0,
    "gn:timezone":"Asia/Shanghai",
    "iso:country":"CN",
    "name:zho_x_preferred":[
        "Shangshixia"
    ],
    "name:zho_x_variant":[
        "\u4e0a\u77f3\u4e0b"
    ],
    "wof:name":"Shangshixia",
    "wof:placetype":"locality"
},
  "geometry": {"coordinates":[114.65192,24.12837],"type":"Point"}
}