{
  "type": "Feature",
  "properties": {
    "gn:admin1_code":"12.0",
    "gn:asciiname":"Liaowujia",
    "gn:country_code":"CN",
    "gn:dem":27,
    "gn:feature_class":"P",
    "gn:feature_code":"PPL",
    "gn:name":"Liaowujia",
    "gn:population":0,
    "gn:timezone":"Asia/Shanghai",
    "iso:country":"CN",
    "name:zho_x_preferred":[
        "Liaowujia"
    ],
    "name:zho_x_variant":[
        "\u5ed6\u4e94\u5bb6"
    ],
    "wof:name":"Liaowujia",
    "wof:placetype":"locality"
},
  "geometry": {"coordinates":[112.84119,30.15185],"type":"Point"}
}