{
  "type": "Feature",
  "properties": {
    "gn:admin1_code":"19",
    "gn:asciiname":"Pailou",
    "gn:country_code":"CN",
    "gn:dem":61,
    "gn:feature_class":"P",
    "gn:feature_code":"PPLA4",
    "gn:name":"Pailou",
    "gn:population":0,
    "gn:timezone":"Asia/Shanghai",
    "iso:country":"CN",
    "name:und_x_variant":[
        "Pailou Zhen",
        "Pailou"
    ],
    "name:zho_x_preferred":[
        "\u724c\u697c"
    ],
    "name:zho_x_variant":[
        "\u724c\u697c\u9547"
    ],
    "wof:name":"Pailou",
    "wof:placetype":"locality"
},
  "geometry": {"coordinates":[122.81654,40.73294],"type":"Point"}
}