{
  "type": "Feature",
  "properties": {
    "gn:admin1_code":"16",
    "gn:asciiname":"De'e",
    "gn:country_code":"CN",
    "gn:dem":1526,
    "gn:feature_class":"P",
    "gn:feature_code":"PPL",
    "gn:name":"De\u2019e",
    "gn:population":0,
    "gn:timezone":"Asia/Shanghai",
    "iso:country":"CN",
    "name:und_x_variant":[
        "De\u2019e"
    ],
    "name:zho_x_preferred":[
        "\u5fb7\u5ce8\u4e61"
    ],
    "wof:name":"De'e",
    "wof:placetype":"locality"
},
  "geometry": {"coordinates":[105.16667,24.65],"type":"Point"}
}