{
  "type": "Feature",
  "properties": {
    "gn:admin1_code":"15",
    "gn:asciiname":"Shunhua",
    "gn:country_code":"CN",
    "gn:dem":2315,
    "gn:feature_class":"P",
    "gn:feature_code":"PPLA4",
    "gn:name":"Shunhua",
    "gn:population":0,
    "gn:timezone":"Asia/Shanghai",
    "iso:country":"CN",
    "name:und_x_variant":[
        "Shunhua Xiang"
    ],
    "name:zho_x_preferred":[
        "\u987a\u5316"
    ],
    "name:zho_x_variant":[
        "\u987a\u5316\u4e61"
    ],
    "wof:name":"Shunhua",
    "wof:placetype":"locality"
},
  "geometry": {"coordinates":[100.71417,38.46861],"type":"Point"}
}