{
  "type": "Feature",
  "properties": {
    "gn:admin1_code":"23.0",
    "gn:asciiname":"Quanmin Yidui",
    "gn:country_code":"CN",
    "gn:dem":4,
    "gn:feature_class":"P",
    "gn:feature_code":"PPLF",
    "gn:name":"Quanmin Yidui",
    "gn:population":0,
    "gn:timezone":"Asia/Shanghai",
    "iso:country":"CN",
    "name:zho_x_preferred":[
        "Quanmin Yidui"
    ],
    "name:zho_x_variant":[
        "\u5168\u6c11\u4e00\u961f"
    ],
    "wof:name":"Quanmin Yidui",
    "wof:placetype":"locality"
},
  "geometry": {"coordinates":[121.80613999999998,31.47128],"type":"Point"}
}