{
  "type": "Feature",
  "properties": {
    "gn:admin1_code":"16.0",
    "gn:asciiname":"Guda",
    "gn:country_code":"CN",
    "gn:dem":325,
    "gn:feature_class":"P",
    "gn:feature_code":"PPL",
    "gn:name":"Guda",
    "gn:population":0,
    "gn:timezone":"Asia/Shanghai",
    "iso:country":"CN",
    "name:cat_x_preferred":[
        "Guda"
    ],
    "name:fra_x_preferred":[
        "Guda"
    ],
    "name:ltz_x_preferred":[
        "Guda"
    ],
    "name:nld_x_preferred":[
        "Guda"
    ],
    "name:rus_x_preferred":[
        "\u0413\u0443\u0434\u0430"
    ],
    "name:zho_x_preferred":[
        "\u53e4\u8fbe"
    ],
    "wof:name":"Guda",
    "wof:placetype":"locality"
},
  "geometry": {"coordinates":[107.986,24.0403],"type":"Point"}
}