{
  "type": "Feature",
  "properties": {
    "gn:admin1_code":"26.0",
    "gn:asciiname":"Jiangouliang",
    "gn:country_code":"CN",
    "gn:dem":1644,
    "gn:feature_class":"P",
    "gn:feature_code":"PPL",
    "gn:name":"Jiangouliang",
    "gn:population":0,
    "gn:timezone":"Asia/Shanghai",
    "iso:country":"CN",
    "name:und_x_variant":[
        "\u89c1\u6c9f\u6881"
    ],
    "wof:name":"Jiangouliang",
    "wof:placetype":"locality"
},
  "geometry": {"coordinates":[107.58468000000001,34.07559000000001],"type":"Point"}
}