{
  "type": "Feature",
  "properties": {
    "gn:admin1_code":"26.0",
    "gn:asciiname":"Zhangyaozi",
    "gn:country_code":"CN",
    "gn:dem":1477,
    "gn:feature_class":"P",
    "gn:feature_code":"PPL",
    "gn:name":"Zhangyaozi",
    "gn:population":0,
    "gn:timezone":"Asia/Shanghai",
    "iso:country":"CN",
    "name:zho_x_preferred":[
        "\u5f20\u7a91\u5b50"
    ],
    "wof:name":"Zhangyaozi",
    "wof:placetype":"locality"
},
  "geometry": {"coordinates":[108.33114,36.92983],"type":"Point"}
}