{
  "type": "Feature",
  "properties": {
    "gn:admin1_code":"30.0",
    "gn:asciiname":"Heliaokou",
    "gn:country_code":"CN",
    "gn:dem":343,
    "gn:feature_class":"P",
    "gn:feature_code":"PPL",
    "gn:name":"Heliaokou",
    "gn:population":0,
    "gn:timezone":"Asia/Shanghai",
    "iso:country":"CN",
    "name:und_x_variant":[
        "\u79be\u5bee\u53e3"
    ],
    "name:zho_x_preferred":[
        "\u79be\u5bee\u53e3"
    ],
    "wof:name":"Heliaokou",
    "wof:placetype":"locality"
},
  "geometry": {"coordinates":[115.3614,23.88728],"type":"Point"}
}