{
  "type": "Feature",
  "properties": {
    "gn:admin1_code":"32.0",
    "gn:asciiname":"Caoyuanzi",
    "gn:country_code":"CN",
    "gn:dem":3645,
    "gn:feature_class":"P",
    "gn:feature_code":"PPL",
    "gn:name":"Caoyuanzi",
    "gn:population":0,
    "gn:timezone":"Asia/Shanghai",
    "iso:country":"CN",
    "name:zho_x_preferred":[
        "\u8349\u539f\u5b50"
    ],
    "wof:name":"Caoyuanzi",
    "wof:placetype":"locality"
},
  "geometry": {"coordinates":[101.39256,29.14252],"type":"Point"}
}