{
  "type": "Feature",
  "properties": {
    "gn:admin1_code":"24.0",
    "gn:asciiname":"Baijiazhuangcun",
    "gn:country_code":"CN",
    "gn:dem":967,
    "gn:feature_class":"P",
    "gn:feature_code":"PPL",
    "gn:name":"Baijiazhuangcun",
    "gn:population":0,
    "gn:timezone":"Asia/Shanghai",
    "iso:country":"CN",
    "name:zho_x_preferred":[
        "\u767d\u5bb6\u5e84\u6751"
    ],
    "wof:name":"Baijiazhuangcun",
    "wof:placetype":"locality"
},
  "geometry": {"coordinates":[110.63906,38.15002],"type":"Point"}
}