{
  "type": "Feature",
  "properties": {
    "gn:admin1_code":"4.0",
    "gn:asciiname":"Jiangzhuang",
    "gn:country_code":"CN",
    "gn:dem":3,
    "gn:feature_class":"P",
    "gn:feature_code":"PPL",
    "gn:name":"Jiangzhuang",
    "gn:population":0,
    "gn:timezone":"Asia/Shanghai",
    "iso:country":"CN",
    "name:und_x_variant":[
        "\u848b\u5e84"
    ],
    "name:zho_x_preferred":[
        "\u848b\u5e84"
    ],
    "wof:name":"Jiangzhuang",
    "wof:placetype":"locality"
},
  "geometry": {"coordinates":[120.18745,32.75068],"type":"Point"}
}