{
  "type": "Feature",
  "properties": {
    "gn:admin1_code":"19.0",
    "gn:asciiname":"Shangpaishanlou",
    "gn:country_code":"CN",
    "gn:dem":275,
    "gn:feature_class":"P",
    "gn:feature_code":"PPL",
    "gn:name":"Shangpaishanlou",
    "gn:population":0,
    "gn:timezone":"Asia/Shanghai",
    "iso:country":"CN",
    "name:zho_x_preferred":[
        "\u4e0a\u6392\u5c71\u697c"
    ],
    "wof:name":"Shangpaishanlou",
    "wof:placetype":"locality"
},
  "geometry": {"coordinates":[121.73697,41.87797],"type":"Point"}
}