{
  "type": "Feature",
  "properties": {
    "gn:admin1_code":"7.0",
    "gn:asciiname":"Huangditang",
    "gn:country_code":"CN",
    "gn:dem":502,
    "gn:feature_class":"P",
    "gn:feature_code":"PPL",
    "gn:name":"Huangditang",
    "gn:population":0,
    "gn:timezone":"Asia/Shanghai",
    "iso:country":"CN",
    "name:und_x_variant":[
        "\u9ec4\u5730\u5858"
    ],
    "name:zho_x_preferred":[
        "\u9ec4\u5730\u5858"
    ],
    "wof:name":"Huangditang",
    "wof:placetype":"locality"
},
  "geometry": {"coordinates":[116.96956000000002,26.57688],"type":"Point"}
}