{
  "type": "Feature",
  "properties": {
    "gn:admin1_code":"08",
    "gn:asciiname":"Xilinji",
    "gn:cc2":"CN",
    "gn:country_code":"CN",
    "gn:dem":440,
    "gn:feature_class":"P",
    "gn:feature_code":"PPL",
    "gn:name":"Xilinji",
    "gn:population":0,
    "gn:timezone":"Asia/Shanghai",
    "iso:country":"CN",
    "name:und_x_variant":[
        "Ch\u2019i-lin-chi",
        "Hsi-lin-chi",
        "Xilinji"
    ],
    "wof:name":"Xilinji",
    "wof:placetype":"locality"
},
  "geometry": {"coordinates":[122.48333,53.01667],"type":"Point"}
}