{
  "type": "Feature",
  "properties": {
    "gn:admin1_code":"02",
    "gn:asciiname":"Chaoyang",
    "gn:country_code":"CN",
    "gn:dem":428,
    "gn:feature_class":"P",
    "gn:feature_code":"PPL",
    "gn:name":"Chaoyang",
    "gn:population":0,
    "gn:timezone":"Asia/Shanghai",
    "iso:country":"CN",
    "name:und_x_variant":[
        "Fengmenge",
        "Chaoyang"
    ],
    "name:zho_x_preferred":[
        "\u671d\u9633"
    ],
    "wof:name":"Chaoyang",
    "wof:placetype":"locality"
},
  "geometry": {"coordinates":[120.34827,27.57301],"type":"Point"}
}