{
  "type": "Feature",
  "properties": {
    "gn:admin1_code":"02",
    "gn:asciiname":"Chaoyang",
    "gn:country_code":"CN",
    "gn:dem":428,
    "gn:feature_class":"P",
    "gn:feature_code":"PPL",
    "gn:name":"Chaoyang",
    "gn:population":0,
    "gn:timezone":"Asia/Shanghai",
    "iso:country":"CN",
    "name:ceb_x_preferred":[
        "Chaoyang"
    ],
    "name:ces_x_preferred":[
        "\u010cchao-jang"
    ],
    "name:deu_x_preferred":[
        "Chaoyang"
    ],
    "name:eus_x_preferred":[
        "Chaoyang"
    ],
    "name:fra_x_preferred":[
        "Chaoyang"
    ],
    "name:heb_x_preferred":[
        "\u05e6'\u05d0\u05d5\u05d9\u05d0\u05e0\u05d2"
    ],
    "name:hun_x_preferred":[
        "Chaoyang"
    ],
    "name:mlg_x_preferred":[
        "Chaoyang"
    ],
    "name:nld_x_preferred":[
        "Chaoyang"
    ],
    "name:nor_x_preferred":[
        "Chaoyang"
    ],
    "name:pol_x_preferred":[
        "Chaoyang"
    ],
    "name:rus_x_preferred":[
        "\u0427\u0430\u043e\u044f\u043d"
    ],
    "name:spa_x_preferred":[
        "Chaoyang"
    ],
    "name:swe_x_preferred":[
        "Chaoyang"
    ],
    "name:tur_x_preferred":[
        "Chaoyang"
    ],
    "name:und_x_variant":[
        "Fengmenge"
    ],
    "name:zho_x_preferred":[
        "\u671d\u9633"
    ],
    "wof:name":"Chaoyang",
    "wof:placetype":"locality"
},
  "geometry": {"coordinates":[120.34827,27.57301],"type":"Point"}
}