{
  "type": "Feature",
  "properties": {
    "gn:admin1_code":"16.0",
    "gn:asciiname":"Xialiuxia",
    "gn:country_code":"CN",
    "gn:dem":227,
    "gn:feature_class":"P",
    "gn:feature_code":"PPL",
    "gn:name":"Xialiuxia",
    "gn:population":0,
    "gn:timezone":"Asia/Shanghai",
    "iso:country":"CN",
    "name:zho_x_preferred":[
        "\u4e0b\u516d\u590f"
    ],
    "wof:name":"Xialiuxia",
    "wof:placetype":"locality"
},
  "geometry": {"coordinates":[110.29000000000001,23.0238],"type":"Point"}
}