{
  "type": "Feature",
  "properties": {
    "gn:admin1_code":"24",
    "gn:asciiname":"Nanfan",
    "gn:cc2":"CN",
    "gn:country_code":"CN",
    "gn:dem":533,
    "gn:feature_class":"P",
    "gn:feature_code":"PPL",
    "gn:name":"Nanfan",
    "gn:population":0,
    "gn:timezone":"Asia/Shanghai",
    "iso:country":"CN",
    "name:und_x_variant":[
        "Nan-fan-chen",
        "Nanfan"
    ],
    "wof:name":"Nanfan",
    "wof:placetype":"locality"
},
  "geometry": {"coordinates":[111.60361,35.60389],"type":"Point"}
}