{
  "type": "Feature",
  "properties": {
    "gn:admin1_code":"29.0",
    "gn:asciiname":"Mu'erping",
    "gn:country_code":"CN",
    "gn:dem":2695,
    "gn:feature_class":"P",
    "gn:feature_code":"PPL",
    "gn:name":"Mu\u2019erping",
    "gn:population":0,
    "gn:timezone":"Asia/Shanghai",
    "iso:country":"CN",
    "name:und_x_variant":[
        "Mu\u2019erping"
    ],
    "name:zho_x_preferred":[
        "\u6728\u8033\u576a"
    ],
    "wof:name":"Mu'erping",
    "wof:placetype":"locality"
},
  "geometry": {"coordinates":[100.773,26.8352],"type":"Point"}
}