{
  "type": "Feature",
  "properties": {
    "gn:admin1_code":"11.0",
    "gn:asciiname":"Si'erguo",
    "gn:country_code":"CN",
    "gn:dem":759,
    "gn:feature_class":"P",
    "gn:feature_code":"PPL",
    "gn:name":"Si\u2019erguo",
    "gn:population":0,
    "gn:timezone":"Asia/Shanghai",
    "iso:country":"CN",
    "name:und_x_variant":[
        "Si\u2019erguo"
    ],
    "name:zho_x_preferred":[
        "\u56db\u8033\u9505"
    ],
    "wof:name":"Si'erguo",
    "wof:placetype":"locality"
},
  "geometry": {"coordinates":[113.92717,26.49728],"type":"Point"}
}