{
  "type": "Feature",
  "properties": {
    "gn:admin1_code":"10.0",
    "gn:asciiname":"Lujingzhuang",
    "gn:country_code":"CN",
    "gn:dem":5,
    "gn:feature_class":"P",
    "gn:feature_code":"PPL",
    "gn:name":"Lujingzhuang",
    "gn:population":0,
    "gn:timezone":"Asia/Shanghai",
    "iso:country":"CN",
    "name:zho_x_preferred":[
        "\u82a6\u4e95\u5e84"
    ],
    "wof:name":"Lujingzhuang",
    "wof:placetype":"locality"
},
  "geometry": {"coordinates":[118.44626,39.30826],"type":"Point"}
}