{
  "type": "Feature",
  "properties": {
    "gn:admin1_code":"12.0",
    "gn:asciiname":"Shangqigan",
    "gn:country_code":"CN",
    "gn:dem":17,
    "gn:feature_class":"P",
    "gn:feature_code":"PPL",
    "gn:name":"Shangqigan",
    "gn:population":0,
    "gn:timezone":"Asia/Shanghai",
    "iso:country":"CN",
    "name:zho_x_preferred":[
        "\u5546\u65d7\u6746"
    ],
    "wof:name":"Shangqigan",
    "wof:placetype":"locality"
},
  "geometry": {"coordinates":[115.86194999999999,29.94388],"type":"Point"}
}