{
  "type": "Feature",
  "properties": {
    "gn:admin1_code":"02",
    "gn:asciiname":"Hsia-yu-yeh",
    "gn:country_code":"CN",
    "gn:dem":3,
    "gn:feature_class":"P",
    "gn:feature_code":"PPL",
    "gn:name":"Hsia-yu-yeh",
    "gn:population":0,
    "gn:timezone":"Asia/Shanghai",
    "iso:country":"CN",
    "wof:name":"Hsia-yu-yeh",
    "wof:placetype":"locality"
},
  "geometry": {"coordinates":[122.19499999999999,30.29667],"type":"Point"}
}