{
  "type": "Feature",
  "properties": {
    "gn:admin1_code":"30.0",
    "gn:asciiname":"Dandong",
    "gn:country_code":"CN",
    "gn:dem":61,
    "gn:feature_class":"P",
    "gn:feature_code":"PPL",
    "gn:name":"Dandong",
    "gn:population":0,
    "gn:timezone":"Asia/Shanghai",
    "iso:country":"CN",
    "name:zho_x_preferred":[
        "\u62c5\u578c"
    ],
    "wof:name":"Dandong",
    "wof:placetype":"locality"
},
  "geometry": {"coordinates":[111.77137999999999,22.93332],"type":"Point"}
}