{
  "type": "Feature",
  "properties": {
    "gn:admin1_code":"24.0",
    "gn:asciiname":"Gaochecun",
    "gn:country_code":"CN",
    "gn:dem":754,
    "gn:feature_class":"P",
    "gn:feature_code":"PPL",
    "gn:name":"Gaochecun",
    "gn:population":0,
    "gn:timezone":"Asia/Shanghai",
    "iso:country":"CN",
    "name:zho_x_preferred":[
        "\u9ad8\u8f66\u6751"
    ],
    "wof:name":"Gaochecun",
    "wof:placetype":"locality"
},
  "geometry": {"coordinates":[112.25517000000001,37.43488],"type":"Point"}
}