{
  "type": "Feature",
  "properties": {
    "gn:admin1_code":"26",
    "gn:asciiname":"Xiangyu",
    "gn:country_code":"CN",
    "gn:dem":474,
    "gn:feature_class":"P",
    "gn:feature_code":"PPL",
    "gn:name":"Xiangyu",
    "gn:population":0,
    "gn:timezone":"Asia/Shanghai",
    "iso:country":"CN",
    "wof:name":"Xiangyu",
    "wof:placetype":"locality"
},
  "geometry": {"coordinates":[108.78306000000001,34.02611],"type":"Point"}
}