{
  "type": "Feature",
  "properties": {
    "gn:admin1_code":"30",
    "gn:asciiname":"Fuwan",
    "gn:country_code":"CN",
    "gn:dem":-2,
    "gn:feature_class":"P",
    "gn:feature_code":"PPL",
    "gn:name":"Fuwan",
    "gn:population":0,
    "gn:timezone":"Asia/Shanghai",
    "iso:country":"CN",
    "name:und_x_variant":[
        "Fu-wun",
        "Fuwan"
    ],
    "name:zho_x_preferred":[
        "\u8299\u6e7e"
    ],
    "wof:name":"Fuwan",
    "wof:placetype":"locality"
},
  "geometry": {"coordinates":[112.56983,21.66274],"type":"Point"}
}