{
  "type": "Feature",
  "properties": {
    "gn:admin1_code":"14.0",
    "gn:asciiname":"Gamacun",
    "gn:country_code":"CN",
    "gn:dem":3410,
    "gn:feature_class":"P",
    "gn:feature_code":"PPL",
    "gn:name":"Gamacun",
    "gn:population":0,
    "gn:timezone":"Asia/Urumqi",
    "iso:country":"CN",
    "name:zho_x_preferred":[
        "\u560e\u739b\u6751"
    ],
    "wof:name":"Gamacun",
    "wof:placetype":"locality"
},
  "geometry": {"coordinates":[97.30484,30.09965],"type":"Point"}
}