{
  "type": "Feature",
  "properties": {
    "gn:admin1_code":"12.0",
    "gn:asciiname":"Gaosuntang",
    "gn:country_code":"CN",
    "gn:dem":798,
    "gn:feature_class":"P",
    "gn:feature_code":"PPL",
    "gn:name":"Gaosuntang",
    "gn:population":0,
    "gn:timezone":"Asia/Shanghai",
    "iso:country":"CN",
    "name:zho_x_preferred":[
        "Gaosuntang"
    ],
    "name:zho_x_variant":[
        "\u9ad8\u7b0b\u5858"
    ],
    "wof:name":"Gaosuntang",
    "wof:placetype":"locality"
},
  "geometry": {"coordinates":[109.30906,29.68087],"type":"Point"}
}