{
  "type": "Feature",
  "properties": {
    "gn:admin1_code":"02",
    "gn:asciiname":"Bilingjiao",
    "gn:country_code":"CN",
    "gn:dem":563,
    "gn:feature_class":"P",
    "gn:feature_code":"PPL",
    "gn:name":"Bilingjiao",
    "gn:population":0,
    "gn:timezone":"Asia/Shanghai",
    "iso:country":"CN",
    "wof:name":"Bilingjiao",
    "wof:placetype":"locality"
},
  "geometry": {"coordinates":[120.28888999999999,27.42667],"type":"Point"}
}