{
  "type": "Feature",
  "properties": {
    "gn:admin1_code":"29.0",
    "gn:asciiname":"Dakukeng",
    "gn:country_code":"CN",
    "gn:dem":2061,
    "gn:feature_class":"P",
    "gn:feature_code":"PPL",
    "gn:name":"Dakukeng",
    "gn:population":0,
    "gn:timezone":"Asia/Shanghai",
    "iso:country":"CN",
    "name:zho_x_preferred":[
        "\u5927\u67af\u5751"
    ],
    "wof:name":"Dakukeng",
    "wof:placetype":"locality"
},
  "geometry": {"coordinates":[104.509,25.2397],"type":"Point"}
}