{
  "type": "Feature",
  "properties": {
    "gn:admin1_code":"26.0",
    "gn:asciiname":"Changjiagoucun",
    "gn:country_code":"CN",
    "gn:dem":530,
    "gn:feature_class":"P",
    "gn:feature_code":"PPL",
    "gn:name":"Changjiagoucun",
    "gn:population":0,
    "gn:timezone":"Asia/Shanghai",
    "iso:country":"CN",
    "name:und_x_variant":[
        "\u5e38\u5bb6\u6c9f\u6751"
    ],
    "wof:name":"Changjiagoucun",
    "wof:placetype":"locality"
},
  "geometry": {"coordinates":[107.30941,33.23304],"type":"Point"}
}