{
  "type": "Feature",
  "properties": {
    "gn:admin1_code":"11.0",
    "gn:asciiname":"Jibutang",
    "gn:country_code":"CN",
    "gn:dem":514,
    "gn:feature_class":"P",
    "gn:feature_code":"PPL",
    "gn:name":"Jibutang",
    "gn:population":0,
    "gn:timezone":"Asia/Shanghai",
    "iso:country":"CN",
    "name:zho_x_preferred":[
        "\u9e21\u535c\u5858"
    ],
    "wof:name":"Jibutang",
    "wof:placetype":"locality"
},
  "geometry": {"coordinates":[110.6892,28.16962],"type":"Point"}
}