{
  "type": "Feature",
  "properties": {
    "gn:admin1_code":"21.0",
    "gn:asciiname":"Zhangjiaquan",
    "gn:country_code":"CN",
    "gn:dem":1414,
    "gn:feature_class":"P",
    "gn:feature_code":"PPL",
    "gn:name":"Zhangjiaquan",
    "gn:population":0,
    "gn:timezone":"Asia/Shanghai",
    "iso:country":"CN",
    "name:zho_x_preferred":[
        "\u5f20\u5bb6\u5708"
    ],
    "wof:name":"Zhangjiaquan",
    "wof:placetype":"locality"
},
  "geometry": {"coordinates":[106.80800000000001,37.8904],"type":"Point"}
}