{
  "type": "Feature",
  "properties": {
    "gn:admin1_code":"18.0",
    "gn:asciiname":"Panmushu",
    "gn:country_code":"CN",
    "gn:dem":757,
    "gn:feature_class":"P",
    "gn:feature_code":"PPL",
    "gn:name":"Panmushu",
    "gn:population":0,
    "gn:timezone":"Asia/Shanghai",
    "iso:country":"CN",
    "name:zho_x_preferred":[
        "\u76d8\u6728\u6811"
    ],
    "wof:name":"Panmushu",
    "wof:placetype":"locality"
},
  "geometry": {"coordinates":[108.89,27.8956],"type":"Point"}
}