{
  "type": "Feature",
  "properties": {
    "gn:admin1_code":"1.0",
    "gn:asciiname":"Tongzhuangcun",
    "gn:country_code":"CN",
    "gn:dem":40,
    "gn:feature_class":"P",
    "gn:feature_code":"PPL",
    "gn:name":"Tongzhuangcun",
    "gn:population":0,
    "gn:timezone":"Asia/Shanghai",
    "iso:country":"CN",
    "name:zho_x_preferred":[
        "\u6850\u5e84\u6751"
    ],
    "wof:name":"Tongzhuangcun",
    "wof:placetype":"locality"
},
  "geometry": {"coordinates":[115.3523,32.94744],"type":"Point"}
}