{
  "type": "Feature",
  "properties": {
    "gn:admin1_code":"14.0",
    "gn:asciiname":"Limanduo",
    "gn:country_code":"CN",
    "gn:dem":4308,
    "gn:feature_class":"P",
    "gn:feature_code":"PPL",
    "gn:name":"Limanduo",
    "gn:population":0,
    "gn:timezone":"Asia/Urumqi",
    "iso:country":"CN",
    "name:zho_x_preferred":[
        "\u91cc\u6f2b\u591a"
    ],
    "wof:name":"Limanduo",
    "wof:placetype":"locality"
},
  "geometry": {"coordinates":[94.03677999999999,31.14202],"type":"Point"}
}