{
  "type": "Feature",
  "properties": {
    "gn:admin1_code":"4.0",
    "gn:asciiname":"Xiaojia Wanzi",
    "gn:country_code":"CN",
    "gn:dem":6,
    "gn:feature_class":"P",
    "gn:feature_code":"PPL",
    "gn:name":"Xiaojia Wanzi",
    "gn:population":0,
    "gn:timezone":"Asia/Shanghai",
    "iso:country":"CN",
    "name:zho_x_preferred":[
        "\u8096\u5bb6\u6e7e\u5b50"
    ],
    "wof:name":"Xiaojia Wanzi",
    "wof:placetype":"locality"
},
  "geometry": {"coordinates":[119.85201000000001,32.18563],"type":"Point"}
}