{
  "type": "Feature",
  "properties": {
    "gn:admin1_code":"33.0",
    "gn:asciiname":"Tangrong",
    "gn:country_code":"CN",
    "gn:dem":737,
    "gn:feature_class":"P",
    "gn:feature_code":"PPL",
    "gn:name":"Tangrong",
    "gn:population":0,
    "gn:timezone":"Asia/Shanghai",
    "iso:country":"CN",
    "name:zho_x_preferred":[
        "\u5858\u8363"
    ],
    "wof:name":"Tangrong",
    "wof:placetype":"locality"
},
  "geometry": {"coordinates":[108.00248999999999,29.50162000000001],"type":"Point"}
}