{
  "type": "Feature",
  "properties": {
    "gn:admin1_code":"19.0",
    "gn:asciiname":"Yudiantun",
    "gn:country_code":"CN",
    "gn:dem":200,
    "gn:feature_class":"P",
    "gn:feature_code":"PPL",
    "gn:name":"Yudiantun",
    "gn:population":0,
    "gn:timezone":"Asia/Shanghai",
    "iso:country":"CN",
    "name:zho_x_preferred":[
        "\u79b9\u7538\u5c6f"
    ],
    "wof:name":"Yudiantun",
    "wof:placetype":"locality"
},
  "geometry": {"coordinates":[124.66098999999998,42.57387],"type":"Point"}
}