{
  "type": "Feature",
  "properties": {
    "gn:admin1_code":"19.0",
    "gn:asciiname":"Cuiqitun",
    "gn:country_code":"CN",
    "gn:dem":8,
    "gn:feature_class":"P",
    "gn:feature_code":"PPL",
    "gn:name":"Cuiqitun",
    "gn:population":0,
    "gn:timezone":"Asia/Shanghai",
    "iso:country":"CN",
    "name:zho_x_preferred":[
        "\u5d14\u8d77\u5c6f"
    ],
    "wof:name":"Cuiqitun",
    "wof:placetype":"locality"
},
  "geometry": {"coordinates":[120.33029999999999,40.27143],"type":"Point"}
}