{
  "type": "Feature",
  "properties": {
    "gn:admin1_code":"16.0",
    "gn:asciiname":"Bieling",
    "gn:country_code":"CN",
    "gn:dem":211,
    "gn:feature_class":"P",
    "gn:feature_code":"PPL",
    "gn:name":"Bieling",
    "gn:population":0,
    "gn:timezone":"Asia/Shanghai",
    "iso:country":"CN",
    "name:zho_x_preferred":[
        "\u9cd6\u5cad"
    ],
    "wof:name":"Bieling",
    "wof:placetype":"locality"
},
  "geometry": {"coordinates":[111.149,24.5395],"type":"Point"}
}