{
  "type": "Feature",
  "properties": {
    "gn:admin1_code":"26.0",
    "gn:asciiname":"Songjiapo",
    "gn:country_code":"CN",
    "gn:dem":743,
    "gn:feature_class":"P",
    "gn:feature_code":"PPL",
    "gn:name":"Songjiapo",
    "gn:population":0,
    "gn:timezone":"Asia/Shanghai",
    "iso:country":"CN",
    "name:zho_x_preferred":[
        "\u5b8b\u5bb6\u5761"
    ],
    "wof:name":"Songjiapo",
    "wof:placetype":"locality"
},
  "geometry": {"coordinates":[108.05515,34.60001],"type":"Point"}
}