{
  "type": "Feature",
  "properties": {
    "gn:admin1_code":"12.0",
    "gn:asciiname":"Dongguang",
    "gn:country_code":"CN",
    "gn:dem":1228,
    "gn:feature_class":"P",
    "gn:feature_code":"PPL",
    "gn:name":"Dongguang",
    "gn:population":0,
    "gn:timezone":"Asia/Shanghai",
    "iso:country":"CN",
    "name:zho_x_preferred":[
        "\u4e1c\u5149"
    ],
    "wof:name":"Dongguang",
    "wof:placetype":"locality"
},
  "geometry": {"coordinates":[108.89451,30.43432],"type":"Point"}
}