{
  "type": "Feature",
  "properties": {
    "gn:admin1_code":"3.0",
    "gn:asciiname":"Huolongshan",
    "gn:country_code":"CN",
    "gn:dem":41,
    "gn:feature_class":"P",
    "gn:feature_code":"PPL",
    "gn:name":"Huolongshan",
    "gn:population":0,
    "gn:timezone":"Asia/Shanghai",
    "iso:country":"CN",
    "name:und_x_variant":[
        "\u706b\u9f99\u5c71"
    ],
    "wof:name":"Huolongshan",
    "wof:placetype":"locality"
},
  "geometry": {"coordinates":[116.09524,29.37916],"type":"Point"}
}