{
  "type": "Feature",
  "properties": {
    "gn:admin1_code":"11.0",
    "gn:asciiname":"Yuanjia",
    "gn:country_code":"CN",
    "gn:dem":1035,
    "gn:feature_class":"P",
    "gn:feature_code":"PPL",
    "gn:name":"Yuanjia",
    "gn:population":0,
    "gn:timezone":"Asia/Shanghai",
    "iso:country":"CN",
    "name:und_x_variant":[
        "\u539f\u5bb6"
    ],
    "wof:name":"Yuanjia",
    "wof:placetype":"locality"
},
  "geometry": {"coordinates":[110.34911,29.04154],"type":"Point"}
}