{
  "type": "Feature",
  "properties": {
    "gn:admin1_code":"11.0",
    "gn:asciiname":"Fengxiangquan",
    "gn:country_code":"CN",
    "gn:dem":761,
    "gn:feature_class":"P",
    "gn:feature_code":"PPL",
    "gn:name":"Fengxiangquan",
    "gn:population":0,
    "gn:timezone":"Asia/Shanghai",
    "iso:country":"CN",
    "name:zho_x_preferred":[
        "\u98ce\u9999\u6cc9"
    ],
    "wof:name":"Fengxiangquan",
    "wof:placetype":"locality"
},
  "geometry": {"coordinates":[110.46222,29.43482],"type":"Point"}
}