{
  "type": "Feature",
  "properties": {
    "gn:admin1_code":"16",
    "gn:asciiname":"Tantou",
    "gn:country_code":"CN",
    "gn:dem":168,
    "gn:feature_class":"P",
    "gn:feature_code":"PPL",
    "gn:name":"Tantou",
    "gn:population":0,
    "gn:timezone":"Asia/Shanghai",
    "iso:country":"CN",
    "name:ceb_x_preferred":[
        "Tantou"
    ],
    "name:deu_x_preferred":[
        "Tantou"
    ],
    "name:fra_x_preferred":[
        "Tantou"
    ],
    "name:swe_x_preferred":[
        "Tantou"
    ],
    "wof:name":"Tantou",
    "wof:placetype":"locality"
},
  "geometry": {"coordinates":[109.29028,24.83472],"type":"Point"}
}