{
  "type": "Feature",
  "properties": {
    "gn:admin1_code":"9.0",
    "gn:asciiname":"Liying",
    "gn:country_code":"CN",
    "gn:dem":218,
    "gn:feature_class":"P",
    "gn:feature_code":"PPL",
    "gn:name":"Liying",
    "gn:population":0,
    "gn:timezone":"Asia/Shanghai",
    "iso:country":"CN",
    "name:zho_x_preferred":[
        "\u674e\u8425"
    ],
    "wof:name":"Liying",
    "wof:placetype":"locality"
},
  "geometry": {"coordinates":[111.71073,33.20362],"type":"Point"}
}