{
  "type": "Feature",
  "properties": {
    "gn:admin1_code":"1.0",
    "gn:asciiname":"Niuyingcun",
    "gn:country_code":"CN",
    "gn:dem":22,
    "gn:feature_class":"P",
    "gn:feature_code":"PPL",
    "gn:name":"Niuyingcun",
    "gn:population":0,
    "gn:timezone":"Asia/Shanghai",
    "iso:country":"CN",
    "name:zho_x_preferred":[
        "\u725b\u90e2\u6751"
    ],
    "wof:name":"Niuyingcun",
    "wof:placetype":"locality"
},
  "geometry": {"coordinates":[118.14216999999999,32.90339],"type":"Point"}
}