{
  "type": "Feature",
  "properties": {
    "gn:admin1_code":"11.0",
    "gn:asciiname":"Mengshanwang",
    "gn:country_code":"CN",
    "gn:dem":67,
    "gn:feature_class":"P",
    "gn:feature_code":"PPL",
    "gn:name":"Mengshanwang",
    "gn:population":0,
    "gn:timezone":"Asia/Shanghai",
    "iso:country":"CN",
    "name:zho_x_preferred":[
        "\u76df\u5c71\u738b"
    ],
    "wof:name":"Mengshanwang",
    "wof:placetype":"locality"
},
  "geometry": {"coordinates":[112.59338,26.84032],"type":"Point"}
}