{
  "type": "Feature",
  "properties": {
    "gn:admin1_code":"4.0",
    "gn:asciiname":"Luo'ercun",
    "gn:country_code":"CN",
    "gn:dem":3,
    "gn:feature_class":"P",
    "gn:feature_code":"PPL",
    "gn:name":"Luo\u2019ercun",
    "gn:population":0,
    "gn:timezone":"Asia/Shanghai",
    "iso:country":"CN",
    "name:und_x_variant":[
        "Luo\u2019ercun"
    ],
    "name:zho_x_preferred":[
        "\u7f57\u4e8c\u6751"
    ],
    "wof:name":"Luo'ercun",
    "wof:placetype":"locality"
},
  "geometry": {"coordinates":[120.15373,32.64842],"type":"Point"}
}