{
  "type": "Feature",
  "properties": {
    "gn:admin1_code":"1.0",
    "gn:asciiname":"Zhufancun",
    "gn:country_code":"CN",
    "gn:dem":191,
    "gn:feature_class":"P",
    "gn:feature_code":"PPL",
    "gn:name":"Zhufancun",
    "gn:population":0,
    "gn:timezone":"Asia/Shanghai",
    "iso:country":"CN",
    "name:zho_x_preferred":[
        "\u7af9\u7548\u6751"
    ],
    "wof:name":"Zhufancun",
    "wof:placetype":"locality"
},
  "geometry": {"coordinates":[115.59578,31.57893],"type":"Point"}
}