{
  "type": "Feature",
  "properties": {
    "gn:admin1_code":"2.0",
    "gn:asciiname":"Dabang",
    "gn:country_code":"CN",
    "gn:dem":6,
    "gn:feature_class":"P",
    "gn:feature_code":"PPL",
    "gn:name":"Dabang",
    "gn:population":0,
    "gn:timezone":"Asia/Shanghai",
    "iso:country":"CN",
    "name:por_x_preferred":[
        "Dabang"
    ],
    "name:zho_x_preferred":[
        "\u5927\u6d5c"
    ],
    "wof:name":"Dabang",
    "wof:placetype":"locality"
},
  "geometry": {"coordinates":[121.09078,30.77065],"type":"Point"}
}