{
  "type": "Feature",
  "properties": {
    "gn:admin1_code":"18",
    "gn:asciiname":"Dadi Liangzi",
    "gn:country_code":"CN",
    "gn:dem":1929,
    "gn:feature_class":"P",
    "gn:feature_code":"PPL",
    "gn:name":"Dadi Liangzi",
    "gn:population":0,
    "gn:timezone":"Asia/Shanghai",
    "iso:country":"CN",
    "name:zho_x_preferred":[
        "\u5927\u5730\u6881\u5b50"
    ],
    "wof:name":"Dadi Liangzi",
    "wof:placetype":"locality"
},
  "geometry": {"coordinates":[104.601,26.3159],"type":"Point"}
}