{
  "type": "Feature",
  "properties": {
    "gn:admin1_code":"7.0",
    "gn:asciiname":"Yuancuoqian",
    "gn:country_code":"CN",
    "gn:dem":67,
    "gn:feature_class":"P",
    "gn:feature_code":"PPL",
    "gn:name":"Yuancuoqian",
    "gn:population":0,
    "gn:timezone":"Asia/Shanghai",
    "iso:country":"CN",
    "name:zho_x_preferred":[
        "\u56ed\u539d\u524d"
    ],
    "wof:name":"Yuancuoqian",
    "wof:placetype":"locality"
},
  "geometry": {"coordinates":[119.06869,26.16008],"type":"Point"}
}