{
  "type": "Feature",
  "properties": {
    "gn:admin1_code":"8.0",
    "gn:asciiname":"Tongkencun",
    "gn:country_code":"CN",
    "gn:dem":222,
    "gn:feature_class":"P",
    "gn:feature_code":"PPL",
    "gn:name":"Tongkencun",
    "gn:population":0,
    "gn:timezone":"Asia/Shanghai",
    "iso:country":"CN",
    "name:zho_x_preferred":[
        "\u901a\u80af\u6751"
    ],
    "wof:name":"Tongkencun",
    "wof:placetype":"locality"
},
  "geometry": {"coordinates":[126.50199000000001,47.60965],"type":"Point"}
}