{
  "type": "Feature",
  "properties": {
    "gn:admin1_code":"29",
    "gn:asciiname":"Mubanglang",
    "gn:country_code":"CN",
    "gn:dem":1359,
    "gn:feature_class":"P",
    "gn:feature_code":"PPL",
    "gn:name":"Mubanglang",
    "gn:population":0,
    "gn:timezone":"Asia/Shanghai",
    "iso:country":"CN",
    "name:zho_x_preferred":[
        "\u6728\u90a6\u90ce"
    ],
    "wof:name":"Mubanglang",
    "wof:placetype":"locality"
},
  "geometry": {"coordinates":[101.59099999999999,24.2318],"type":"Point"}
}