{
  "type": "Feature",
  "properties": {
    "gn:admin1_code":"14.0",
    "gn:asciiname":"Kuoda Wucun",
    "gn:country_code":"CN",
    "gn:dem":4261,
    "gn:feature_class":"P",
    "gn:feature_code":"PPL",
    "gn:name":"Kuoda Wucun",
    "gn:population":0,
    "gn:timezone":"Asia/Urumqi",
    "iso:country":"CN",
    "name:zho_x_preferred":[
        "\u6269\u8fbe\u4e94\u6751"
    ],
    "wof:name":"Kuoda Wucun",
    "wof:placetype":"locality"
},
  "geometry": {"coordinates":[97.92427000000001,30.82201],"type":"Point"}
}