{
  "type": "Feature",
  "properties": {
    "gn:admin1_code":"07",
    "gn:asciiname":"Yuansi",
    "gn:country_code":"CN",
    "gn:dem":380,
    "gn:feature_class":"P",
    "gn:feature_code":"PPL",
    "gn:name":"Yuansi",
    "gn:population":0,
    "gn:timezone":"Asia/Shanghai",
    "iso:country":"CN",
    "name:zho_x_preferred":[
        "\u5458\u5bfa"
    ],
    "wof:name":"Yuansi",
    "wof:placetype":"locality"
},
  "geometry": {"coordinates":[120.06273,27.30283],"type":"Point"}
}