{
  "type": "Feature",
  "properties": {
    "gn:admin1_code":"16.0",
    "gn:asciiname":"Nage",
    "gn:country_code":"CN",
    "gn:dem":130,
    "gn:feature_class":"P",
    "gn:feature_code":"PPL",
    "gn:name":"Nage",
    "gn:population":0,
    "gn:timezone":"Asia/Shanghai",
    "iso:country":"CN",
    "name:ind_x_preferred":[
        "Nage"
    ],
    "name:rus_x_preferred":[
        "\u041d\u0430\u0433\u0435"
    ],
    "name:ukr_x_preferred":[
        "\u041d\u0430\u0433\u0435"
    ],
    "name:zho_x_preferred":[
        "\u90a3\u4e2a"
    ],
    "wof:name":"Nage",
    "wof:placetype":"locality"
},
  "geometry": {"coordinates":[108.595,22.5164],"type":"Point"}
}