{
  "type": "Feature",
  "properties": {
    "gn:admin1_code":"7.0",
    "gn:asciiname":"Chengyuan",
    "gn:country_code":"CN",
    "gn:dem":152,
    "gn:feature_class":"P",
    "gn:feature_code":"PPL",
    "gn:name":"Chengyuan",
    "gn:population":0,
    "gn:timezone":"Asia/Shanghai",
    "iso:country":"CN",
    "name:und_x_variant":[
        "\u6f84\u6e90"
    ],
    "name:zho_x_preferred":[
        "\u6f84\u6e90"
    ],
    "wof:name":"Chengyuan",
    "wof:placetype":"locality"
},
  "geometry": {"coordinates":[118.28795,26.61183],"type":"Point"}
}