{
  "type": "Feature",
  "properties": {
    "gn:admin1_code":"15.0",
    "gn:asciiname":"Shengou",
    "gn:country_code":"CN",
    "gn:dem":1656,
    "gn:feature_class":"P",
    "gn:feature_code":"PPL",
    "gn:name":"Shengou",
    "gn:population":0,
    "gn:timezone":"Asia/Shanghai",
    "iso:country":"CN",
    "name:zho_x_preferred":[
        "\u6df1\u6c9f"
    ],
    "wof:name":"Shengou",
    "wof:placetype":"locality"
},
  "geometry": {"coordinates":[105.346,34.1325],"type":"Point"}
}