{
  "type": "Feature",
  "properties": {
    "gn:admin1_code":"32.0",
    "gn:asciiname":"Dengbuluo",
    "gn:country_code":"CN",
    "gn:dem":2824,
    "gn:feature_class":"P",
    "gn:feature_code":"PPL",
    "gn:name":"Dengbuluo",
    "gn:population":0,
    "gn:timezone":"Asia/Shanghai",
    "iso:country":"CN",
    "name:zho_x_preferred":[
        "\u9093\u5e03\u502e"
    ],
    "wof:name":"Dengbuluo",
    "wof:placetype":"locality"
},
  "geometry": {"coordinates":[101.922,27.9379],"type":"Point"}
}