{
  "type": "Feature",
  "properties": {
    "gn:admin1_code":"3.0",
    "gn:asciiname":"Simazui",
    "gn:country_code":"CN",
    "gn:dem":17,
    "gn:feature_class":"P",
    "gn:feature_code":"PPL",
    "gn:name":"Simazui",
    "gn:population":0,
    "gn:timezone":"Asia/Shanghai",
    "iso:country":"CN",
    "name:und_x_variant":[
        "\u53f8\u9a6c\u5634"
    ],
    "wof:name":"Simazui",
    "wof:placetype":"locality"
},
  "geometry": {"coordinates":[116.64788,29.26459],"type":"Point"}
}