{
  "type": "Feature",
  "properties": {
    "gn:admin1_code":"30",
    "gn:asciiname":"Daqiao",
    "gn:country_code":"CN",
    "gn:dem":43,
    "gn:feature_class":"P",
    "gn:feature_code":"PPL",
    "gn:name":"Daqiao",
    "gn:population":0,
    "gn:timezone":"Asia/Urumqi",
    "iso:country":"CN",
    "name:ceb_x_preferred":[
        "Daqiao"
    ],
    "name:deu_x_preferred":[
        "Daqiao"
    ],
    "name:swe_x_preferred":[
        "Daqiao"
    ],
    "name:zho_x_preferred":[
        "\u8fbe\u6865"
    ],
    "wof:name":"Daqiao",
    "wof:placetype":"locality"
},
  "geometry": {"coordinates":[110.67934,21.79638],"type":"Point"}
}