{
  "type": "Feature",
  "properties": {
    "gn:admin1_code":"1.0",
    "gn:asciiname":"Nanjincun",
    "gn:country_code":"CN",
    "gn:dem":23,
    "gn:feature_class":"P",
    "gn:feature_code":"PPL",
    "gn:name":"Nanjincun",
    "gn:population":0,
    "gn:timezone":"Asia/Shanghai",
    "iso:country":"CN",
    "name:zho_x_preferred":[
        "\u5357\u91d1\u6751"
    ],
    "wof:name":"Nanjincun",
    "wof:placetype":"locality"
},
  "geometry": {"coordinates":[116.73283000000001,32.76484],"type":"Point"}
}