{
  "type": "Feature",
  "properties": {
    "gn:admin1_code":"15.0",
    "gn:asciiname":"Dongshamen",
    "gn:country_code":"CN",
    "gn:dem":1092,
    "gn:feature_class":"P",
    "gn:feature_code":"PPL",
    "gn:name":"Dongshamen",
    "gn:population":0,
    "gn:timezone":"Asia/Urumqi",
    "iso:country":"CN",
    "name:zho_x_preferred":[
        "\u4e1c\u6c99\u95e8"
    ],
    "wof:name":"Dongshamen",
    "wof:placetype":"locality"
},
  "geometry": {"coordinates":[94.7723,40.269],"type":"Point"}
}