{
  "type": "Feature",
  "properties": {
    "gn:admin1_code":"29.0",
    "gn:asciiname":"Alanghe",
    "gn:country_code":"CN",
    "gn:dem":2209,
    "gn:feature_class":"P",
    "gn:feature_code":"PPL",
    "gn:name":"Alanghe",
    "gn:population":0,
    "gn:timezone":"Asia/Shanghai",
    "iso:country":"CN",
    "name:zho_x_preferred":[
        "\u963f\u6d6a\u6cb3"
    ],
    "wof:name":"Alanghe",
    "wof:placetype":"locality"
},
  "geometry": {"coordinates":[103.83,25.9962],"type":"Point"}
}