{
  "type": "Feature",
  "properties": {
    "gn:admin1_code":"11.0",
    "gn:asciiname":"Laolukoupu",
    "gn:country_code":"CN",
    "gn:dem":81,
    "gn:feature_class":"P",
    "gn:feature_code":"PPL",
    "gn:name":"Laolukoupu",
    "gn:population":0,
    "gn:timezone":"Asia/Shanghai",
    "iso:country":"CN",
    "name:zho_x_preferred":[
        "\u8001\u8def\u53e3\u94fa"
    ],
    "wof:name":"Laolukoupu",
    "wof:placetype":"locality"
},
  "geometry": {"coordinates":[113.38848,29.50238],"type":"Point"}
}