{
  "type": "Feature",
  "properties": {
    "gn:admin1_code":"15.0",
    "gn:asciiname":"Xiaolingouxiangen",
    "gn:country_code":"CN",
    "gn:dem":2811,
    "gn:feature_class":"P",
    "gn:feature_code":"PPL",
    "gn:name":"Xiaolingouxiangen",
    "gn:population":0,
    "gn:timezone":"Asia/Shanghai",
    "iso:country":"CN",
    "name:und_x_variant":[
        "\u5c0f\u6797\u6c9f\u7ebf\u6839"
    ],
    "wof:name":"Xiaolingouxiangen",
    "wof:placetype":"locality"
},
  "geometry": {"coordinates":[104.18805,34.66516],"type":"Point"}
}