{
  "type": "Feature",
  "properties": {
    "gn:admin1_code":"18",
    "gn:asciiname":"Baiziwan",
    "gn:country_code":"CN",
    "gn:dem":1270,
    "gn:feature_class":"P",
    "gn:feature_code":"PPL",
    "gn:name":"Baiziwan",
    "gn:population":0,
    "gn:timezone":"Asia/Shanghai",
    "iso:country":"CN",
    "name:zho_x_preferred":[
        "\u7a17\u5b50\u6e7e"
    ],
    "wof:name":"Baiziwan",
    "wof:placetype":"locality"
},
  "geometry": {"coordinates":[107.03,28.0072],"type":"Point"}
}