{
  "type": "Feature",
  "properties": {
    "gn:admin1_code":"21",
    "gn:asciiname":"Sutai",
    "gn:country_code":"CN",
    "gn:dem":2320,
    "gn:feature_class":"P",
    "gn:feature_code":"PPL",
    "gn:name":"Sutai",
    "gn:population":0,
    "gn:timezone":"Asia/Shanghai",
    "iso:country":"CN",
    "wof:name":"Sutai",
    "wof:placetype":"locality"
},
  "geometry": {"coordinates":[106.18333,35.48333],"type":"Point"}
}