{
  "type": "Feature",
  "properties": {
    "gn:admin1_code":"29",
    "gn:asciiname":"Longbang",
    "gn:country_code":"CN",
    "gn:dem":1113,
    "gn:feature_class":"P",
    "gn:feature_code":"PPL",
    "gn:name":"Longbang",
    "gn:population":0,
    "gn:timezone":"Asia/Shanghai",
    "iso:country":"CN",
    "name:zho_x_preferred":[
        "\u9f99\u699c"
    ],
    "name:zho_x_variant":[
        "\u9f99\u90a6\u9547"
    ],
    "wof:name":"Longbang",
    "wof:placetype":"locality"
},
  "geometry": {"coordinates":[104.601,23.2687],"type":"Point"}
}