{
  "type": "Feature",
  "properties": {
    "gn:admin1_code":"11.0",
    "gn:asciiname":"Jindangwan",
    "gn:country_code":"CN",
    "gn:dem":350,
    "gn:feature_class":"P",
    "gn:feature_code":"PPL",
    "gn:name":"Jindangwan",
    "gn:population":0,
    "gn:timezone":"Asia/Shanghai",
    "iso:country":"CN",
    "name:zho_x_preferred":[
        "\u91d1\u5f53\u6e7e"
    ],
    "wof:name":"Jindangwan",
    "wof:placetype":"locality"
},
  "geometry": {"coordinates":[110.17433,29.1686],"type":"Point"}
}