{
  "type": "Feature",
  "properties": {
    "gn:admin1_code":"8.0",
    "gn:asciiname":"Kuntou Houcun",
    "gn:country_code":"CN",
    "gn:dem":136,
    "gn:feature_class":"P",
    "gn:feature_code":"PPL",
    "gn:name":"Kuntou Houcun",
    "gn:population":0,
    "gn:timezone":"Asia/Shanghai",
    "iso:country":"CN",
    "name:zho_x_preferred":[
        "\u5764\u5934\u540e\u6751"
    ],
    "wof:name":"Kuntou Houcun",
    "wof:placetype":"locality"
},
  "geometry": {"coordinates":[126.32326,46.64077],"type":"Point"}
}