{
  "type": "Feature",
  "properties": {
    "gn:admin1_code":"4.0",
    "gn:asciiname":"Shijiu Xudai",
    "gn:country_code":"CN",
    "gn:dem":4,
    "gn:feature_class":"P",
    "gn:feature_code":"PPL",
    "gn:name":"Shijiu Xudai",
    "gn:population":0,
    "gn:timezone":"Asia/Shanghai",
    "iso:country":"CN",
    "name:zho_x_preferred":[
        "\u5341\u4e5d\u5729\u57ed"
    ],
    "wof:name":"Shijiu Xudai",
    "wof:placetype":"locality"
},
  "geometry": {"coordinates":[119.834,32.06354],"type":"Point"}
}