{
  "type": "Feature",
  "properties": {
    "gn:admin1_code":"3",
    "gn:asciiname":"Yapokeng",
    "gn:country_code":"CN",
    "gn:dem":198,
    "gn:feature_class":"P",
    "gn:feature_code":"PPL",
    "gn:name":"Yapokeng",
    "gn:population":0,
    "gn:timezone":"Asia/Shanghai",
    "iso:country":"CN",
    "name:zho_x_preferred":[
        "\u9e2d\u5a46\u5751"
    ],
    "wof:name":"Yapokeng",
    "wof:placetype":"locality"
},
  "geometry": {"coordinates":[114.57599999999999,25.9097],"type":"Point"}
}