{
  "type": "Feature",
  "properties": {
    "gn:admin1_code":"16.0",
    "gn:asciiname":"Dadongtian",
    "gn:country_code":"CN",
    "gn:dem":77,
    "gn:feature_class":"P",
    "gn:feature_code":"PPL",
    "gn:name":"Dadongtian",
    "gn:population":0,
    "gn:timezone":"Asia/Shanghai",
    "iso:country":"CN",
    "name:zho_x_preferred":[
        "\u5927\u578c\u7530"
    ],
    "wof:name":"Dadongtian",
    "wof:placetype":"locality"
},
  "geometry": {"coordinates":[109.22199999999999,22.2737],"type":"Point"}
}