{
  "type": "Feature",
  "properties": {
    "gn:admin1_code":"29.0",
    "gn:asciiname":"Youzha",
    "gn:country_code":"CN",
    "gn:dem":1996,
    "gn:feature_class":"P",
    "gn:feature_code":"PPLA4",
    "gn:name":"Youzha",
    "gn:population":0,
    "gn:timezone":"Asia/Shanghai",
    "iso:country":"CN",
    "name:und_x_variant":[
        "Xiyi",
        "Xiyi Zhen",
        "\u897f\u4e00\u9547",
        "Youzha"
    ],
    "name:zho_x_preferred":[
        "\u6cb9\u69a8"
    ],
    "wof:name":"Youzha",
    "wof:placetype":"locality"
},
  "geometry": {"coordinates":[103.27472,24.46611],"type":"Point"}
}