{
  "type": "Feature",
  "properties": {
    "gn:admin1_code":"3.0",
    "gn:asciiname":"Tianpengban",
    "gn:country_code":"CN",
    "gn:dem":335,
    "gn:feature_class":"P",
    "gn:feature_code":"PPL",
    "gn:name":"Tianpengban",
    "gn:population":0,
    "gn:timezone":"Asia/Shanghai",
    "iso:country":"CN",
    "name:zho_x_preferred":[
        "\u7530\u68da\u5742"
    ],
    "wof:name":"Tianpengban",
    "wof:placetype":"locality"
},
  "geometry": {"coordinates":[118.02513,28.15153],"type":"Point"}
}