{
  "type": "Feature",
  "properties": {
    "gn:admin1_code":"2.0",
    "gn:asciiname":"Longmenling",
    "gn:country_code":"CN",
    "gn:dem":556,
    "gn:feature_class":"P",
    "gn:feature_code":"PPL",
    "gn:name":"Longmenling",
    "gn:population":0,
    "gn:timezone":"Asia/Shanghai",
    "iso:country":"CN",
    "name:und_x_variant":[
        "\u9f99\u95e8\u5cad"
    ],
    "wof:name":"Longmenling",
    "wof:placetype":"locality"
},
  "geometry": {"coordinates":[119.23206999999999,30.28503],"type":"Point"}
}