{
  "type": "Feature",
  "properties": {
    "gn:admin1_code":"24.0",
    "gn:asciiname":"Shangdongliu",
    "gn:country_code":"CN",
    "gn:dem":777,
    "gn:feature_class":"P",
    "gn:feature_code":"PPL",
    "gn:name":"Shangdongliu",
    "gn:population":0,
    "gn:timezone":"Asia/Shanghai",
    "iso:country":"CN",
    "name:zho_x_preferred":[
        "\u4e0a\u4e1c\u7559"
    ],
    "wof:name":"Shangdongliu",
    "wof:placetype":"locality"
},
  "geometry": {"coordinates":[113.02876000000001,38.4984],"type":"Point"}
}