{
  "type": "Feature",
  "properties": {
    "gn:admin1_code":"4.0",
    "gn:asciiname":"Yinnan",
    "gn:country_code":"CN",
    "gn:dem":6,
    "gn:feature_class":"P",
    "gn:feature_code":"PPL",
    "gn:name":"Yinnan",
    "gn:population":0,
    "gn:timezone":"Asia/Shanghai",
    "iso:country":"CN",
    "name:zho_x_preferred":[
        "Yinnan"
    ],
    "name:zho_x_variant":[
        "\u996e\u5357"
    ],
    "wof:name":"Yinnan",
    "wof:placetype":"locality"
},
  "geometry": {"coordinates":[121.34643,32.38894000000001],"type":"Point"}
}