{
  "type": "Feature",
  "properties": {
    "gn:admin1_code":"2.0",
    "gn:asciiname":"Gaoyaoshan",
    "gn:country_code":"CN",
    "gn:dem":153,
    "gn:feature_class":"P",
    "gn:feature_code":"PPL",
    "gn:name":"Gaoyaoshan",
    "gn:population":0,
    "gn:timezone":"Asia/Shanghai",
    "iso:country":"CN",
    "name:zho_x_preferred":[
        "\u9ad8\u7476\u5c71"
    ],
    "wof:name":"Gaoyaoshan",
    "wof:placetype":"locality"
},
  "geometry": {"coordinates":[120.24169000000001,29.17366],"type":"Point"}
}