{
  "type": "Feature",
  "properties": {
    "gn:admin1_code":"16.0",
    "gn:asciiname":"Dalongdong",
    "gn:country_code":"CN",
    "gn:dem":154,
    "gn:feature_class":"P",
    "gn:feature_code":"PPL",
    "gn:name":"Dalongdong",
    "gn:population":0,
    "gn:timezone":"Asia/Shanghai",
    "iso:country":"CN",
    "name:deu_x_preferred":[
        "Dalongdong"
    ],
    "name:zho_x_preferred":[
        "\u5927\u9f99\u6d1e"
    ],
    "name:zho_x_variant":[
        "\u5927\u9f8d\u5cd2"
    ],
    "wof:name":"Dalongdong",
    "wof:placetype":"locality"
},
  "geometry": {"coordinates":[108.57599999999999,23.5792],"type":"Point"}
}