{
  "type": "Feature",
  "properties": {
    "gn:admin1_code":"15.0",
    "gn:asciiname":"Heimayuan",
    "gn:country_code":"CN",
    "gn:dem":1828,
    "gn:feature_class":"P",
    "gn:feature_code":"PPL",
    "gn:name":"Heimayuan",
    "gn:population":0,
    "gn:timezone":"Asia/Shanghai",
    "iso:country":"CN",
    "name:zho_x_preferred":[
        "\u9ed1\u9a6c\u586c"
    ],
    "wof:name":"Heimayuan",
    "wof:placetype":"locality"
},
  "geometry": {"coordinates":[104.90900000000001,36.0838],"type":"Point"}
}