{
  "type": "Feature",
  "properties": {
    "gn:admin1_code":"5.0",
    "gn:asciiname":"Pengjia Weizi",
    "gn:country_code":"CN",
    "gn:dem":137,
    "gn:feature_class":"P",
    "gn:feature_code":"PPL",
    "gn:name":"Pengjia Weizi",
    "gn:population":0,
    "gn:timezone":"Asia/Shanghai",
    "iso:country":"CN",
    "name:zho_x_preferred":[
        "\u5f6d\u5bb6\u5d34\u5b50"
    ],
    "wof:name":"Pengjia Weizi",
    "wof:placetype":"locality"
},
  "geometry": {"coordinates":[125.79617,45.2158],"type":"Point"}
}