{
  "type": "Feature",
  "properties": {
    "gn:admin1_code":"18.0",
    "gn:asciiname":"Guolushan",
    "gn:country_code":"CN",
    "gn:dem":1474,
    "gn:feature_class":"P",
    "gn:feature_code":"PPL",
    "gn:name":"Guolushan",
    "gn:population":0,
    "gn:timezone":"Asia/Shanghai",
    "iso:country":"CN",
    "name:zho_x_preferred":[
        "\u8fc7\u8def\u5c71"
    ],
    "wof:name":"Guolushan",
    "wof:placetype":"locality"
},
  "geometry": {"coordinates":[107.29000000000001,26.4586],"type":"Point"}
}