{
  "type": "Feature",
  "properties": {
    "gn:admin1_code":"2.0",
    "gn:asciiname":"Changchao",
    "gn:country_code":"CN",
    "gn:dem":72,
    "gn:feature_class":"P",
    "gn:feature_code":"PPL",
    "gn:name":"Changchao",
    "gn:population":0,
    "gn:timezone":"Asia/Shanghai",
    "iso:country":"CN",
    "name:und_x_variant":[
        "\u957f\u6f6e",
        "Changchaoxiang",
        "\u957f\u6f6e\u4e61"
    ],
    "wof:name":"Changchao",
    "wof:placetype":"locality"
},
  "geometry": {"coordinates":[119.66264,30.95492],"type":"Point"}
}