{
  "type": "Feature",
  "properties": {
    "gn:admin1_code":"20.0",
    "gn:asciiname":"Huweizihao",
    "gn:country_code":"CN",
    "gn:dem":1613,
    "gn:feature_class":"P",
    "gn:feature_code":"PPL",
    "gn:name":"Huweizihao",
    "gn:population":0,
    "gn:timezone":"Asia/Shanghai",
    "iso:country":"CN",
    "name:und_x_variant":[
        "\u864e\u5a01\u5b50\u58d5"
    ],
    "wof:name":"Huweizihao",
    "wof:placetype":"locality"
},
  "geometry": {"coordinates":[110.05482000000001,41.18453],"type":"Point"}
}