{
  "type": "Feature",
  "properties": {
    "gn:admin1_code":"7",
    "gn:asciiname":"Gaogang",
    "gn:country_code":"CN",
    "gn:dem":14,
    "gn:feature_class":"P",
    "gn:feature_code":"PPL",
    "gn:name":"Gaogang",
    "gn:population":0,
    "gn:timezone":"Asia/Shanghai",
    "iso:country":"CN",
    "name:und_x_variant":[
        "\u9ad8\u6e2f"
    ],
    "wof:name":"Gaogang",
    "wof:placetype":"locality"
},
  "geometry": {"coordinates":[118.00694,24.39861],"type":"Point"}
}