{
  "type": "Feature",
  "properties": {
    "gn:admin1_code":"7.0",
    "gn:asciiname":"Laoshushan",
    "gn:country_code":"CN",
    "gn:dem":261,
    "gn:feature_class":"P",
    "gn:feature_code":"PPL",
    "gn:name":"Laoshushan",
    "gn:population":0,
    "gn:timezone":"Asia/Shanghai",
    "iso:country":"CN",
    "name:zho_x_preferred":[
        "\u8001\u9f20\u5c71"
    ],
    "wof:name":"Laoshushan",
    "wof:placetype":"locality"
},
  "geometry": {"coordinates":[117.85907,27.36659],"type":"Point"}
}