{
  "type": "Feature",
  "properties": {
    "gn:admin1_code":"14.0",
    "gn:asciiname":"Wuyag",
    "gn:country_code":"CN",
    "gn:dem":3837,
    "gn:feature_class":"P",
    "gn:feature_code":"PPLF",
    "gn:name":"Wuyag",
    "gn:population":0,
    "gn:timezone":"Asia/Urumqi",
    "iso:country":"CN",
    "name:bod_x_preferred":[
        "Wuyag"
    ],
    "name:zho_x_preferred":[
        "Wuya"
    ],
    "name:zho_x_variant":[
        "\u4e4c\u96c5"
    ],
    "wof:name":"Wuyag",
    "wof:placetype":"locality"
},
  "geometry": {"coordinates":[97.78771999999999,29.7186],"type":"Point"}
}