{
  "type": "Feature",
  "properties": {
    "gn:admin1_code":"26.0",
    "gn:asciiname":"Yatoucun",
    "gn:country_code":"CN",
    "gn:dem":1146,
    "gn:feature_class":"P",
    "gn:feature_code":"PPL",
    "gn:name":"Yatoucun",
    "gn:population":0,
    "gn:timezone":"Asia/Shanghai",
    "iso:country":"CN",
    "name:zho_x_preferred":[
        "\u5d16\u5934\u6751"
    ],
    "wof:name":"Yatoucun",
    "wof:placetype":"locality"
},
  "geometry": {"coordinates":[110.08778,36.64735],"type":"Point"}
}