{
  "type": "Feature",
  "properties": {
    "gn:admin1_code":"33.0",
    "gn:asciiname":"Ganlongdong",
    "gn:country_code":"CN",
    "gn:dem":472,
    "gn:feature_class":"P",
    "gn:feature_code":"PPL",
    "gn:name":"Ganlongdong",
    "gn:population":0,
    "gn:timezone":"Asia/Shanghai",
    "iso:country":"CN",
    "name:zho_x_preferred":[
        "\u5e72\u9f99\u6d1e"
    ],
    "wof:name":"Ganlongdong",
    "wof:placetype":"locality"
},
  "geometry": {"coordinates":[106.61921,30.00618],"type":"Point"}
}