{
  "type": "Feature",
  "properties": {
    "gn:admin1_code":"12.0",
    "gn:asciiname":"Santiaoling",
    "gn:country_code":"CN",
    "gn:dem":1187,
    "gn:feature_class":"P",
    "gn:feature_code":"PPL",
    "gn:name":"Santiaoling",
    "gn:population":0,
    "gn:timezone":"Asia/Shanghai",
    "iso:country":"CN",
    "name:zho_x_preferred":[
        "\u4e09\u6761\u5cad"
    ],
    "wof:name":"Santiaoling",
    "wof:placetype":"locality"
},
  "geometry": {"coordinates":[110.46003,31.85973],"type":"Point"}
}