{
  "type": "Feature",
  "properties": {
    "gn:admin1_code":"29.0",
    "gn:asciiname":"Jimu",
    "gn:country_code":"CN",
    "gn:dem":2123,
    "gn:feature_class":"P",
    "gn:feature_code":"PPL",
    "gn:name":"Jimu",
    "gn:population":0,
    "gn:timezone":"Asia/Shanghai",
    "iso:country":"CN",
    "name:und_x_variant":[
        "\u57fa\u6bcd"
    ],
    "wof:name":"Jimu",
    "wof:placetype":"locality"
},
  "geometry": {"coordinates":[104.02451000000001,25.72166],"type":"Point"}
}