{
  "type": "Feature",
  "properties": {
    "gn:admin1_code":"15.0",
    "gn:asciiname":"Machangtan",
    "gn:country_code":"CN",
    "gn:dem":1706,
    "gn:feature_class":"P",
    "gn:feature_code":"PPL",
    "gn:name":"Machangtan",
    "gn:population":0,
    "gn:timezone":"Asia/Shanghai",
    "iso:country":"CN",
    "name:zho_x_preferred":[
        "\u9a6c\u573a\u6ee9"
    ],
    "wof:name":"Machangtan",
    "wof:placetype":"locality"
},
  "geometry": {"coordinates":[103.643,37.588],"type":"Point"}
}