{
  "type": "Feature",
  "properties": {
    "gn:admin1_code":"19.0",
    "gn:asciiname":"Langjiacun",
    "gn:country_code":"CN",
    "gn:dem":3,
    "gn:feature_class":"P",
    "gn:feature_code":"PPL",
    "gn:name":"Langjiacun",
    "gn:population":0,
    "gn:timezone":"Asia/Shanghai",
    "iso:country":"CN",
    "name:und_x_variant":[
        "Langjiawobao",
        "Langjia Wobu"
    ],
    "name:zho_x_preferred":[
        "\u90ce\u5bb6\u6751"
    ],
    "name:zho_x_variant":[
        "\u90ce\u5bb6\u7a9d\u5821"
    ],
    "wof:name":"Langjiacun",
    "wof:placetype":"locality"
},
  "geometry": {"coordinates":[122.17007,41.25809],"type":"Point"}
}