{
  "type": "Feature",
  "properties": {
    "gn:admin1_code":"10",
    "gn:asciiname":"Koucun",
    "gn:country_code":"CN",
    "gn:dem":61,
    "gn:feature_class":"P",
    "gn:feature_code":"PPL",
    "gn:name":"Koucun",
    "gn:population":0,
    "gn:timezone":"Asia/Shanghai",
    "iso:country":"CN",
    "name:und_x_variant":[
        "K\u2019ou-ts\u2019un",
        "Koucun"
    ],
    "name:zho_x_preferred":[
        "\u53e9\u6751"
    ],
    "wof:name":"Koucun",
    "wof:placetype":"locality"
},
  "geometry": {"coordinates":[114.578,37.7666],"type":"Point"}
}