{
  "type": "Feature",
  "properties": {
    "gn:admin1_code":"7.0",
    "gn:asciiname":"Wanyang",
    "gn:country_code":"CN",
    "gn:dem":429,
    "gn:feature_class":"P",
    "gn:feature_code":"PPL",
    "gn:name":"Wanyang",
    "gn:population":0,
    "gn:timezone":"Asia/Shanghai",
    "iso:country":"CN",
    "name:zho_x_preferred":[
        "\u4e07\u6d0b"
    ],
    "wof:name":"Wanyang",
    "wof:placetype":"locality"
},
  "geometry": {"coordinates":[119.22217000000001,26.3296],"type":"Point"}
}