{
  "type": "Feature",
  "properties": {
    "gn:admin1_code":"3.0",
    "gn:asciiname":"Luoxiancun",
    "gn:country_code":"CN",
    "gn:dem":54,
    "gn:feature_class":"P",
    "gn:feature_code":"PPL",
    "gn:name":"Luoxiancun",
    "gn:population":0,
    "gn:timezone":"Asia/Shanghai",
    "iso:country":"CN",
    "name:und_x_variant":[
        "\u9a86\u4ed9"
    ],
    "wof:name":"Luoxiancun",
    "wof:placetype":"locality"
},
  "geometry": {"coordinates":[116.35553,28.1731],"type":"Point"}
}