{
  "type": "Feature",
  "properties": {
    "gn:admin1_code":"3",
    "gn:asciiname":"Lingmeigang Fenchang",
    "gn:country_code":"CN",
    "gn:dem":73,
    "gn:feature_class":"P",
    "gn:feature_code":"PPL",
    "gn:name":"Lingmeigang Fenchang",
    "gn:population":0,
    "gn:timezone":"Asia/Shanghai",
    "iso:country":"CN",
    "name:und_x_variant":[
        "\u5cad\u7f8e\u5c97\u5206\u573a",
        "Lingmeigang"
    ],
    "wof:name":"Lingmeigang Fenchang",
    "wof:placetype":"locality"
},
  "geometry": {"coordinates":[116.65957,28.07758],"type":"Point"}
}