{
  "type": "Feature",
  "properties": {
    "gn:admin1_code":"5.0",
    "gn:asciiname":"Huojiatuncun",
    "gn:country_code":"CN",
    "gn:dem":195,
    "gn:feature_class":"P",
    "gn:feature_code":"PPL",
    "gn:name":"Huojiatuncun",
    "gn:population":0,
    "gn:timezone":"Asia/Shanghai",
    "iso:country":"CN",
    "name:zho_x_preferred":[
        "\u970d\u5bb6\u5c6f\u6751"
    ],
    "wof:name":"Huojiatuncun",
    "wof:placetype":"locality"
},
  "geometry": {"coordinates":[124.85052,43.88804],"type":"Point"}
}