{
  "type": "Feature",
  "properties": {
    "gn:admin1_code":"16.0",
    "gn:asciiname":"Genbu",
    "gn:country_code":"CN",
    "gn:dem":697,
    "gn:feature_class":"P",
    "gn:feature_code":"PPL",
    "gn:name":"Genbu",
    "gn:population":0,
    "gn:timezone":"Asia/Shanghai",
    "iso:country":"CN",
    "name:zho_x_preferred":[
        "\u6839\u535c"
    ],
    "wof:name":"Genbu",
    "wof:placetype":"locality"
},
  "geometry": {"coordinates":[106.983,24.2493],"type":"Point"}
}