{
  "type": "Feature",
  "properties": {
    "gn:admin1_code":"4.0",
    "gn:asciiname":"Xinshicun",
    "gn:cc2":"CN",
    "gn:country_code":"CN",
    "gn:dem":1,
    "gn:feature_class":"P",
    "gn:feature_code":"PPL",
    "gn:name":"Xinshicun",
    "gn:population":0,
    "gn:timezone":"Asia/Shanghai",
    "iso:country":"CN",
    "name:und_x_variant":[
        "Hsin-shih-ts\u2019un",
        "Xinshicun"
    ],
    "wof:name":"Xinshicun",
    "wof:placetype":"locality"
},
  "geometry": {"coordinates":[120.04443999999999,34.30361],"type":"Point"}
}