{
  "type": "Feature",
  "properties": {
    "gn:admin1_code":"26.0",
    "gn:asciiname":"Siheyuan",
    "gn:country_code":"CN",
    "gn:dem":1214,
    "gn:feature_class":"P",
    "gn:feature_code":"PPL",
    "gn:name":"Siheyuan",
    "gn:population":0,
    "gn:timezone":"Asia/Shanghai",
    "iso:country":"CN",
    "name:deu_x_preferred":[
        "Siheyuan"
    ],
    "name:fra_x_preferred":[
        "Siheyuan"
    ],
    "name:jpn_x_preferred":[
        "\u56db\u5408\u9662"
    ],
    "name:kor_x_preferred":[
        "\uc4f0\ud5c8\uc704\uc548"
    ],
    "name:msa_x_preferred":[
        "Siheyuan"
    ],
    "name:nld_x_preferred":[
        "Siheyuan"
    ],
    "name:nor_x_preferred":[
        "Siheyuan"
    ],
    "name:pol_x_preferred":[
        "Siheyuan"
    ],
    "name:rus_x_preferred":[
        "\u0421\u044b\u0445\u044d\u044e\u0430\u043d\u044c"
    ],
    "name:spa_x_preferred":[
        "Siheyuan"
    ],
    "name:swe_x_preferred":[
        "Siheyuan"
    ],
    "name:ukr_x_preferred":[
        "\u0421\u0438\u0445\u0435\u044e\u0430\u043d\u044c"
    ],
    "name:und_x_variant":[
        "\u56db\u5408\u9662"
    ],
    "name:zho_x_preferred":[
        "\u56db\u5408\u9662"
    ],
    "wof:name":"Siheyuan",
    "wof:placetype":"locality"
},
  "geometry": {"coordinates":[106.79537000000001,32.74897],"type":"Point"}
}