{
  "type": "Feature",
  "properties": {
    "gn:admin1_code":"12.0",
    "gn:asciiname":"Mazhaling",
    "gn:country_code":"CN",
    "gn:dem":349,
    "gn:feature_class":"P",
    "gn:feature_code":"PPL",
    "gn:name":"Mazhaling",
    "gn:population":0,
    "gn:timezone":"Asia/Shanghai",
    "iso:country":"CN",
    "name:zho_x_preferred":[
        "\u8682\u86b1\u5cad"
    ],
    "wof:name":"Mazhaling",
    "wof:placetype":"locality"
},
  "geometry": {"coordinates":[110.36054,32.88129],"type":"Point"}
}