{
  "type": "Feature",
  "properties": {
    "gn:admin1_code":"19.0",
    "gn:asciiname":"Xujia Kanzi",
    "gn:country_code":"CN",
    "gn:dem":76,
    "gn:feature_class":"P",
    "gn:feature_code":"PPL",
    "gn:name":"Xujia Kanzi",
    "gn:population":0,
    "gn:timezone":"Asia/Shanghai",
    "iso:country":"CN",
    "name:zho_x_preferred":[
        "\u5f90\u5bb6\u574e\u5b50"
    ],
    "wof:name":"Xujia Kanzi",
    "wof:placetype":"locality"
},
  "geometry": {"coordinates":[122.753,39.9038],"type":"Point"}
}