{
  "type": "Feature",
  "properties": {
    "gn:admin1_code":"16.0",
    "gn:asciiname":"Nayi",
    "gn:country_code":"CN",
    "gn:dem":1131,
    "gn:feature_class":"P",
    "gn:feature_code":"PPL",
    "gn:name":"Nayi",
    "gn:population":0,
    "gn:timezone":"Asia/Shanghai",
    "iso:country":"CN",
    "name:zho_x_preferred":[
        "\u90a3\u4e49"
    ],
    "wof:name":"Nayi",
    "wof:placetype":"locality"
},
  "geometry": {"coordinates":[105.027,24.6551],"type":"Point"}
}