{
  "type": "Feature",
  "properties": {
    "gn:admin1_code":"30.0",
    "gn:asciiname":"Yangshanling",
    "gn:country_code":"CN",
    "gn:dem":382,
    "gn:feature_class":"P",
    "gn:feature_code":"PPL",
    "gn:name":"Yangshanling",
    "gn:population":0,
    "gn:timezone":"Asia/Shanghai",
    "iso:country":"CN",
    "name:zho_x_preferred":[
        "\u6768\u5c71\u5cad"
    ],
    "wof:name":"Yangshanling",
    "wof:placetype":"locality"
},
  "geometry": {"coordinates":[112.50302000000001,24.20026],"type":"Point"}
}