{
  "type": "Feature",
  "properties": {
    "gn:admin1_code":"8.0",
    "gn:asciiname":"Shizhongcun",
    "gn:country_code":"CN",
    "gn:dem":156,
    "gn:feature_class":"P",
    "gn:feature_code":"PPL",
    "gn:name":"Shizhongcun",
    "gn:population":0,
    "gn:timezone":"Asia/Shanghai",
    "iso:country":"CN",
    "name:zho_x_preferred":[
        "\u9002\u4e2d\u6751"
    ],
    "wof:name":"Shizhongcun",
    "wof:placetype":"locality"
},
  "geometry": {"coordinates":[128.54011,45.54],"type":"Point"}
}