{
  "type": "Feature",
  "properties": {
    "gn:admin1_code":"33.0",
    "gn:asciiname":"Baiyangjing",
    "gn:country_code":"CN",
    "gn:dem":752,
    "gn:feature_class":"P",
    "gn:feature_code":"PPL",
    "gn:name":"Baiyangjing",
    "gn:population":0,
    "gn:timezone":"Asia/Shanghai",
    "iso:country":"CN",
    "name:zho_x_preferred":[
        "\u767d\u6768\u4e95"
    ],
    "wof:name":"Baiyangjing",
    "wof:placetype":"locality"
},
  "geometry": {"coordinates":[108.68147,28.76502],"type":"Point"}
}