{
  "type": "Feature",
  "properties": {
    "gn:admin1_code":"20.0",
    "gn:asciiname":"Dongxing",
    "gn:country_code":"CN",
    "gn:dem":295,
    "gn:feature_class":"P",
    "gn:feature_code":"PPL",
    "gn:name":"Dongxing",
    "gn:population":0,
    "gn:timezone":"Asia/Shanghai",
    "iso:country":"CN",
    "name:ceb_x_preferred":[
        "Dongxing"
    ],
    "name:deu_x_preferred":[
        "Dongxing"
    ],
    "name:fra_x_preferred":[
        "Dongxing"
    ],
    "name:mlg_x_preferred":[
        "Dongxing"
    ],
    "name:nor_x_preferred":[
        "Dongxing"
    ],
    "name:pnb_x_preferred":[
        "\u0688\u0648\u0646\u06af\u0634\u06cc\u0646\u06af"
    ],
    "name:rus_x_preferred":[
        "\u0414\u0443\u043d\u0441\u0438\u043d"
    ],
    "name:swe_x_preferred":[
        "Dongxing"
    ],
    "name:vie_x_preferred":[
        "\u0110\u00f4ng H\u01b0ng"
    ],
    "name:zho_x_preferred":[
        "\u4e1c\u5174"
    ],
    "wof:name":"Dongxing",
    "wof:placetype":"locality"
},
  "geometry": {"coordinates":[123.51481,48.49041],"type":"Point"}
}