{
  "type": "Feature",
  "properties": {
    "gn:admin1_code":"8.0",
    "gn:asciiname":"Sanqinggong",
    "gn:country_code":"CN",
    "gn:dem":254,
    "gn:feature_class":"P",
    "gn:feature_code":"PPL",
    "gn:name":"Sanqinggong",
    "gn:population":0,
    "gn:timezone":"Asia/Shanghai",
    "iso:country":"CN",
    "name:zho_x_preferred":[
        "\u4e09\u6e05\u5bab"
    ],
    "wof:name":"Sanqinggong",
    "wof:placetype":"locality"
},
  "geometry": {"coordinates":[127.40335,45.40011],"type":"Point"}
}