{
  "type": "Feature",
  "properties": {
    "gn:admin1_code":"19.0",
    "gn:asciiname":"Houhuangjia",
    "gn:country_code":"CN",
    "gn:dem":114,
    "gn:feature_class":"P",
    "gn:feature_code":"PPL",
    "gn:name":"Houhuangjia",
    "gn:population":0,
    "gn:timezone":"Asia/Shanghai",
    "iso:country":"CN",
    "name:zho_x_preferred":[
        "\u540e\u9ec4\u5bb6"
    ],
    "wof:name":"Houhuangjia",
    "wof:placetype":"locality"
},
  "geometry": {"coordinates":[124.027,43.0425],"type":"Point"}
}