{
  "type": "Feature",
  "properties": {
    "gn:admin1_code":"11.0",
    "gn:asciiname":"Tangbachong",
    "gn:country_code":"CN",
    "gn:dem":306,
    "gn:feature_class":"P",
    "gn:feature_code":"PPL",
    "gn:name":"Tangbachong",
    "gn:population":0,
    "gn:timezone":"Asia/Shanghai",
    "iso:country":"CN",
    "name:zho_x_preferred":[
        "\u5858\u575d\u51b2"
    ],
    "wof:name":"Tangbachong",
    "wof:placetype":"locality"
},
  "geometry": {"coordinates":[109.6678,28.28725],"type":"Point"}
}