{
  "type": "Feature",
  "properties": {
    "gn:admin1_code":"4.0",
    "gn:asciiname":"Xinyuan Erzu",
    "gn:country_code":"CN",
    "gn:dem":0,
    "gn:feature_class":"P",
    "gn:feature_code":"PPLF",
    "gn:name":"Xinyuan Erzu",
    "gn:population":0,
    "gn:timezone":"Asia/Shanghai",
    "iso:country":"CN",
    "name:zho_x_preferred":[
        "\u65b0\u56ed\u4e8c\u7ec4"
    ],
    "wof:name":"Xinyuan Erzu",
    "wof:placetype":"locality"
},
  "geometry": {"coordinates":[120.41,33.482],"type":"Point"}
}