{
  "type": "Feature",
  "properties": {
    "gn:admin1_code":"20.0",
    "gn:asciiname":"Dongfeng Jiudui",
    "gn:country_code":"CN",
    "gn:dem":297,
    "gn:feature_class":"P",
    "gn:feature_code":"PPLF",
    "gn:name":"Dongfeng Jiudui",
    "gn:population":0,
    "gn:timezone":"Asia/Shanghai",
    "iso:country":"CN",
    "name:zho_x_preferred":[
        "\u4e1c\u98ce\u4e5d\u961f"
    ],
    "wof:name":"Dongfeng Jiudui",
    "wof:placetype":"locality"
},
  "geometry": {"coordinates":[122.55146999999999,47.52756],"type":"Point"}
}