{
  "type": "Feature",
  "properties": {
    "gn:admin1_code":"32.0",
    "gn:asciiname":"Huachaomen",
    "gn:country_code":"CN",
    "gn:dem":362,
    "gn:feature_class":"P",
    "gn:feature_code":"PPL",
    "gn:name":"Huachaomen",
    "gn:population":0,
    "gn:timezone":"Asia/Shanghai",
    "iso:country":"CN",
    "name:zho_x_preferred":[
        "\u82b1\u671d\u95e8"
    ],
    "wof:name":"Huachaomen",
    "wof:placetype":"locality"
},
  "geometry": {"coordinates":[104.301,29.3817],"type":"Point"}
}