{
  "type": "Feature",
  "properties": {
    "gn:admin1_code":"29",
    "gn:asciiname":"Xiahanjia",
    "gn:country_code":"CN",
    "gn:dem":1741,
    "gn:feature_class":"P",
    "gn:feature_code":"PPL",
    "gn:name":"Xiahanjia",
    "gn:population":0,
    "gn:timezone":"Asia/Shanghai",
    "iso:country":"CN",
    "name:zho_x_preferred":[
        "\u4e0b\u97e9\u5bb6"
    ],
    "wof:name":"Xiahanjia",
    "wof:placetype":"locality"
},
  "geometry": {"coordinates":[101.70699999999999,24.7646],"type":"Point"}
}