{
  "type": "Feature",
  "properties": {
    "gn:admin1_code":"32.0",
    "gn:asciiname":"Chenjia Wanzi",
    "gn:country_code":"CN",
    "gn:dem":357,
    "gn:feature_class":"P",
    "gn:feature_code":"PPL",
    "gn:name":"Chenjia Wanzi",
    "gn:population":0,
    "gn:timezone":"Asia/Shanghai",
    "iso:country":"CN",
    "name:zho_x_preferred":[
        "\u9648\u5bb6\u6e7e\u5b50"
    ],
    "wof:name":"Chenjia Wanzi",
    "wof:placetype":"locality"
},
  "geometry": {"coordinates":[105.10565,29.31145],"type":"Point"}
}