{
  "type": "Feature",
  "properties": {
    "gn:admin1_code":"14.0",
    "gn:asciiname":"Mayeyajie",
    "gn:country_code":"CN",
    "gn:dem":4803,
    "gn:feature_class":"P",
    "gn:feature_code":"PPL",
    "gn:name":"Mayeyajie",
    "gn:population":0,
    "gn:timezone":"Asia/Urumqi",
    "iso:country":"CN",
    "name:zho_x_preferred":[
        "\u9ebb\u53f6\u4e9a\u59d0"
    ],
    "wof:name":"Mayeyajie",
    "wof:placetype":"locality"
},
  "geometry": {"coordinates":[87.0557,31.2395],"type":"Point"}
}