{
  "type": "Feature",
  "properties": {
    "gn:admin1_code":"7.0",
    "gn:asciiname":"Xiyuanli",
    "gn:country_code":"CN",
    "gn:dem":550,
    "gn:feature_class":"P",
    "gn:feature_code":"PPL",
    "gn:name":"Xiyuanli",
    "gn:population":0,
    "gn:timezone":"Asia/Shanghai",
    "iso:country":"CN",
    "name:zho_x_preferred":[
        "Xiyuanli"
    ],
    "name:zho_x_variant":[
        "\u6eaa\u6e90\u91cc"
    ],
    "wof:name":"Xiyuanli",
    "wof:placetype":"locality"
},
  "geometry": {"coordinates":[118.93277999999999,26.555],"type":"Point"}
}