{
  "type": "Feature",
  "properties": {
    "gn:admin1_code":"7.0",
    "gn:asciiname":"Xiayangpai",
    "gn:country_code":"CN",
    "gn:dem":670,
    "gn:feature_class":"P",
    "gn:feature_code":"PPL",
    "gn:name":"Xiayangpai",
    "gn:population":0,
    "gn:timezone":"Asia/Shanghai",
    "iso:country":"CN",
    "name:zho_x_preferred":[
        "\u4e0b\u6d0b\u6392"
    ],
    "wof:name":"Xiayangpai",
    "wof:placetype":"locality"
},
  "geometry": {"coordinates":[117.5478,27.08782],"type":"Point"}
}