{
  "type": "Feature",
  "properties": {
    "gn:admin1_code":"29.0",
    "gn:asciiname":"Mili",
    "gn:country_code":"CN",
    "gn:dem":2402,
    "gn:feature_class":"P",
    "gn:feature_code":"PPL",
    "gn:name":"Mili",
    "gn:population":0,
    "gn:timezone":"Asia/Shanghai",
    "iso:country":"CN",
    "name:ceb_x_preferred":[
        "Mili"
    ],
    "name:glg_x_preferred":[
        "Mili"
    ],
    "name:hye_x_preferred":[
        "\u0544\u056b\u056c\u056b"
    ],
    "name:ita_x_preferred":[
        "Mili"
    ],
    "name:por_x_preferred":[
        "Mili"
    ],
    "name:rus_x_preferred":[
        "\u041c\u0438\u043b\u043b\u0438"
    ],
    "name:spa_x_preferred":[
        "Mili"
    ],
    "name:srp_x_preferred":[
        "\u041c\u0438\u043b\u0438"
    ],
    "name:swe_x_preferred":[
        "Mili"
    ],
    "name:zho_x_preferred":[
        "\u54aa\u91cc"
    ],
    "name:zho_x_variant":[
        "Mili"
    ],
    "wof:name":"Mili",
    "wof:placetype":"locality"
},
  "geometry": {"coordinates":[99.20140000000001,27.0468],"type":"Point"}
}