{
  "type": "Feature",
  "properties": {
    "gn:admin1_code":"30.0",
    "gn:asciiname":"Guankengtou",
    "gn:country_code":"CN",
    "gn:dem":175,
    "gn:feature_class":"P",
    "gn:feature_code":"PPL",
    "gn:name":"Guankengtou",
    "gn:population":0,
    "gn:timezone":"Asia/Shanghai",
    "iso:country":"CN",
    "name:zho_x_preferred":[
        "Guankengtou"
    ],
    "name:zho_x_variant":[
        "\u89c2\u5751\u5934"
    ],
    "wof:name":"Guankengtou",
    "wof:placetype":"locality"
},
  "geometry": {"coordinates":[114.14823,24.88546],"type":"Point"}
}