{
  "type": "Feature",
  "properties": {
    "gn:admin1_code":"25.0",
    "gn:asciiname":"Nanbu",
    "gn:country_code":"CN",
    "gn:dem":101,
    "gn:feature_class":"P",
    "gn:feature_code":"PPL",
    "gn:name":"Nanbu",
    "gn:population":0,
    "gn:timezone":"Asia/Shanghai",
    "iso:country":"CN",
    "name:zho_x_preferred":[
        "\u5357\u57e0"
    ],
    "wof:name":"Nanbu",
    "wof:placetype":"locality"
},
  "geometry": {"coordinates":[120.696,37.17278],"type":"Point"}
}