{
  "type": "Feature",
  "properties": {
    "gn:admin1_code":"04",
    "gn:asciiname":"Xuejiayao",
    "gn:country_code":"CN",
    "gn:dem":7,
    "gn:feature_class":"P",
    "gn:feature_code":"PPL",
    "gn:name":"Xuejiayao",
    "gn:population":0,
    "gn:timezone":"Asia/Shanghai",
    "iso:country":"CN",
    "name:und_x_variant":[
        "Hsueh-chia-yao",
        "Xuejiayao"
    ],
    "wof:name":"Xuejiayao",
    "wof:placetype":"locality"
},
  "geometry": {"coordinates":[120.63972,32.14278],"type":"Point"}
}