{
  "type": "Feature",
  "properties": {
    "gn:admin1_code":"2",
    "gn:asciiname":"Fujiayang",
    "gn:country_code":"CN",
    "gn:dem":609,
    "gn:feature_class":"P",
    "gn:feature_code":"PPL",
    "gn:name":"Fujiayang",
    "gn:population":0,
    "gn:timezone":"Asia/Shanghai",
    "iso:country":"CN",
    "name:zho_x_preferred":[
        "\u5bcc\u5bb6\u579f"
    ],
    "wof:name":"Fujiayang",
    "wof:placetype":"locality"
},
  "geometry": {"coordinates":[119.78333000000001,27.40667],"type":"Point"}
}