{
  "type": "Feature",
  "properties": {
    "gn:admin1_code":"8.0",
    "gn:asciiname":"Jiangbing Shierdui",
    "gn:country_code":"CN",
    "gn:dem":65,
    "gn:feature_class":"P",
    "gn:feature_code":"PPLF",
    "gn:name":"Jiangbing Shierdui",
    "gn:population":0,
    "gn:timezone":"Asia/Shanghai",
    "iso:country":"CN",
    "name:zho_x_preferred":[
        "\u6c5f\u6ee8\u5341\u4e8c\u961f"
    ],
    "wof:name":"Jiangbing Shierdui",
    "wof:placetype":"locality"
},
  "geometry": {"coordinates":[131.23515,47.64761],"type":"Point"}
}