{
  "type": "Feature",
  "properties": {
    "gn:admin1_code":"18",
    "gn:asciiname":"Liujiaxiang",
    "gn:country_code":"CN",
    "gn:dem":2179,
    "gn:feature_class":"P",
    "gn:feature_code":"PPL",
    "gn:name":"Liujiaxiang",
    "gn:population":0,
    "gn:timezone":"Asia/Shanghai",
    "iso:country":"CN",
    "name:zho_x_preferred":[
        "\u5218\u5bb6\u5df7"
    ],
    "wof:name":"Liujiaxiang",
    "wof:placetype":"locality"
},
  "geometry": {"coordinates":[104.288,26.8353],"type":"Point"}
}