{
  "type": "Feature",
  "properties": {
    "gn:admin1_code":"4.0",
    "gn:asciiname":"Tiangou",
    "gn:country_code":"CN",
    "gn:dem":0,
    "gn:feature_class":"P",
    "gn:feature_code":"PPL",
    "gn:name":"Tiangou",
    "gn:population":0,
    "gn:timezone":"Asia/Shanghai",
    "iso:country":"CN",
    "name:deu_x_preferred":[
        "Tiangou"
    ],
    "name:fra_x_preferred":[
        "Ti\u0101ng\u01d2u"
    ],
    "name:ind_x_preferred":[
        "Tiangou"
    ],
    "name:por_x_preferred":[
        "Tien-koan"
    ],
    "name:rus_x_preferred":[
        "\u0422\u044f\u043d\u044c\u0433\u043e\u0443"
    ],
    "name:spa_x_preferred":[
        "Tiangou"
    ],
    "name:zho_x_preferred":[
        "Tiangou"
    ],
    "name:zho_x_variant":[
        "\u5929\u6c9f",
        "\u5929\u72d7"
    ],
    "wof:name":"Tiangou",
    "wof:placetype":"locality"
},
  "geometry": {"coordinates":[119.72826999999999,33.89228],"type":"Point"}
}