{
  "type": "Feature",
  "properties": {
    "gn:admin1_code":"14.0",
    "gn:asciiname":"Suodingkacun",
    "gn:country_code":"CN",
    "gn:dem":3937,
    "gn:feature_class":"P",
    "gn:feature_code":"PPL",
    "gn:name":"Suodingkacun",
    "gn:population":0,
    "gn:timezone":"Asia/Urumqi",
    "iso:country":"CN",
    "name:zho_x_preferred":[
        "\u7d22\u5b9a\u5494\u6751"
    ],
    "wof:name":"Suodingkacun",
    "wof:placetype":"locality"
},
  "geometry": {"coordinates":[94.65260000000001,31.56193],"type":"Point"}
}