{
  "type": "Feature",
  "properties": {
    "gn:admin1_code":"13",
    "gn:asciiname":"Xilu",
    "gn:country_code":"CN",
    "gn:dem":1694,
    "gn:feature_class":"P",
    "gn:feature_code":"PPL",
    "gn:name":"Xilu",
    "gn:population":0,
    "gn:timezone":"Asia/Urumqi",
    "iso:country":"CN",
    "name:zho_x_preferred":[
        "\u897f\u8def"
    ],
    "wof:name":"Xilu",
    "wof:placetype":"locality"
},
  "geometry": {"coordinates":[94.46948999999999,42.80459000000001],"type":"Point"}
}