{
  "type": "Feature",
  "properties": {
    "gn:admin1_code":"11.0",
    "gn:asciiname":"Weizi'ao",
    "gn:country_code":"CN",
    "gn:dem":466,
    "gn:feature_class":"P",
    "gn:feature_code":"PPL",
    "gn:name":"Weizi\u2019ao",
    "gn:population":0,
    "gn:timezone":"Asia/Shanghai",
    "iso:country":"CN",
    "name:und_x_variant":[
        "Weizi\u2019ao"
    ],
    "name:zho_x_preferred":[
        "\u56f4\u5b50\u5773"
    ],
    "wof:name":"Weizi'ao",
    "wof:placetype":"locality"
},
  "geometry": {"coordinates":[111.31019999999999,28.54619000000001],"type":"Point"}
}