{
  "type": "Feature",
  "properties": {
    "gn:admin1_code":"29.0",
    "gn:asciiname":"Shanjiao",
    "gn:country_code":"CN",
    "gn:dem":1803,
    "gn:feature_class":"P",
    "gn:feature_code":"PPLA4",
    "gn:name":"Shanjiao",
    "gn:population":0,
    "gn:timezone":"Asia/Shanghai",
    "iso:country":"CN",
    "name:und_x_variant":[
        "\u5c71\u811a",
        "Dongping",
        "Dongping Xiang",
        "\u4e1c\u576a",
        "\u4e1c\u576a\u4e61"
    ],
    "wof:name":"Shanjiao",
    "wof:placetype":"locality"
},
  "geometry": {"coordinates":[103.06844,27.3223],"type":"Point"}
}