{
  "type": "Feature",
  "properties": {
    "gn:admin1_code":"25.0",
    "gn:asciiname":"Hehujia",
    "gn:country_code":"CN",
    "gn:dem":72,
    "gn:feature_class":"P",
    "gn:feature_code":"PPL",
    "gn:name":"Hehujia",
    "gn:population":0,
    "gn:timezone":"Asia/Shanghai",
    "iso:country":"CN",
    "name:zho_x_preferred":[
        "\u6cb3\u80e1\u5bb6"
    ],
    "wof:name":"Hehujia",
    "wof:placetype":"locality"
},
  "geometry": {"coordinates":[122.06549,37.1251],"type":"Point"}
}