{
  "type": "Feature",
  "properties": {
    "gn:admin1_code":"25",
    "gn:asciiname":"Yijiaquan",
    "gn:country_code":"CN",
    "gn:dem":279,
    "gn:feature_class":"P",
    "gn:feature_code":"PPL",
    "gn:name":"Yijiaquan",
    "gn:population":0,
    "gn:timezone":"Asia/Shanghai",
    "iso:country":"CN",
    "name:zho_x_preferred":[
        "\u4f0a\u5bb6\u5708"
    ],
    "wof:name":"Yijiaquan",
    "wof:placetype":"locality"
},
  "geometry": {"coordinates":[118.06399999999999,35.8659],"type":"Point"}
}