{
  "type": "Feature",
  "properties": {
    "gn:admin1_code":"12.0",
    "gn:asciiname":"Songshuping",
    "gn:country_code":"CN",
    "gn:dem":601,
    "gn:feature_class":"P",
    "gn:feature_code":"PPL",
    "gn:name":"Songshuping",
    "gn:population":0,
    "gn:timezone":"Asia/Shanghai",
    "iso:country":"CN",
    "name:zho_x_preferred":[
        "Songshuping"
    ],
    "name:zho_x_variant":[
        "\u677e\u6811\u576a"
    ],
    "wof:name":"Songshuping",
    "wof:placetype":"locality"
},
  "geometry": {"coordinates":[109.57584,29.71213],"type":"Point"}
}