{
  "type": "Feature",
  "properties": {
    "gn:admin1_code":"7.0",
    "gn:asciiname":"Nongchang",
    "gn:country_code":"CN",
    "gn:dem":342,
    "gn:feature_class":"P",
    "gn:feature_code":"PPLF",
    "gn:name":"Nongchang",
    "gn:population":0,
    "gn:timezone":"Asia/Shanghai",
    "iso:country":"CN",
    "name:zho_x_preferred":[
        "\u519c\u573a"
    ],
    "wof:name":"Nongchang",
    "wof:placetype":"locality"
},
  "geometry": {"coordinates":[118.24509,25.26732],"type":"Point"}
}