{
  "type": "Feature",
  "properties": {
    "gn:admin1_code":"3.0",
    "gn:asciiname":"Tianlongli",
    "gn:country_code":"CN",
    "gn:dem":80,
    "gn:feature_class":"P",
    "gn:feature_code":"PPL",
    "gn:name":"Tianlongli",
    "gn:population":0,
    "gn:timezone":"Asia/Shanghai",
    "iso:country":"CN",
    "name:und_x_variant":[
        "\u7530\u5784\u91cc"
    ],
    "wof:name":"Tianlongli",
    "wof:placetype":"locality"
},
  "geometry": {"coordinates":[114.86863999999998,27.46309],"type":"Point"}
}