{
  "type": "Feature",
  "properties": {
    "gn:admin1_code":"25",
    "gn:asciiname":"Youlan",
    "gn:country_code":"CN",
    "gn:dem":156,
    "gn:feature_class":"P",
    "gn:feature_code":"PPL",
    "gn:name":"Youlan",
    "gn:population":0,
    "gn:timezone":"Asia/Shanghai",
    "iso:country":"CN",
    "name:nld_x_preferred":[
        "Youlan"
    ],
    "name:zho_x_preferred":[
        "\u53cb\u5170"
    ],
    "wof:name":"Youlan",
    "wof:placetype":"locality"
},
  "geometry": {"coordinates":[118.617,35.8575],"type":"Point"}
}