{
  "type": "Feature",
  "properties": {
    "gn:admin1_code":"16.0",
    "gn:asciiname":"Baibi",
    "gn:country_code":"CN",
    "gn:dem":618,
    "gn:feature_class":"P",
    "gn:feature_code":"PPL",
    "gn:name":"Baibi",
    "gn:population":0,
    "gn:timezone":"Asia/Shanghai",
    "iso:country":"CN",
    "name:zho_x_preferred":[
        "\u767e\u5fc5"
    ],
    "wof:name":"Baibi",
    "wof:placetype":"locality"
},
  "geometry": {"coordinates":[106.55800000000001,24.2432],"type":"Point"}
}