{
  "type": "Feature",
  "properties": {
    "gn:admin1_code":"1.0",
    "gn:asciiname":"Zhangzhancun",
    "gn:country_code":"CN",
    "gn:dem":28,
    "gn:feature_class":"P",
    "gn:feature_code":"PPL",
    "gn:name":"Zhangzhancun",
    "gn:population":0,
    "gn:timezone":"Asia/Shanghai",
    "iso:country":"CN",
    "name:zho_x_preferred":[
        "\u5f20\u7ad9\u6751"
    ],
    "wof:name":"Zhangzhancun",
    "wof:placetype":"locality"
},
  "geometry": {"coordinates":[116.91325999999999,33.50321],"type":"Point"}
}