{
  "type": "Feature",
  "properties": {
    "gn:admin1_code":"13",
    "gn:asciiname":"Tafusa",
    "gn:country_code":"CN",
    "gn:dem":1069,
    "gn:feature_class":"P",
    "gn:feature_code":"PPL",
    "gn:name":"Tafusa",
    "gn:population":0,
    "gn:timezone":"Asia/Shanghai",
    "iso:country":"CN",
    "name:und_x_variant":[
        "\u5854\u752b\u8428"
    ],
    "wof:name":"Tafusa",
    "wof:placetype":"locality"
},
  "geometry": {"coordinates":[79.77401,39.89073],"type":"Point"}
}