{
  "type": "Feature",
  "properties": {
    "gn:admin1_code":"14.0",
    "gn:asciiname":"Wangpazhao",
    "gn:country_code":"CN",
    "gn:dem":3644,
    "gn:feature_class":"P",
    "gn:feature_code":"PPL",
    "gn:name":"Wangpazhao",
    "gn:population":0,
    "gn:timezone":"Asia/Urumqi",
    "iso:country":"CN",
    "name:zho_x_preferred":[
        "\u738b\u6015\u62db"
    ],
    "wof:name":"Wangpazhao",
    "wof:placetype":"locality"
},
  "geometry": {"coordinates":[97.31984,31.5053],"type":"Point"}
}