{
  "type": "Feature",
  "properties": {
    "gn:admin1_code":"7",
    "gn:asciiname":"Shilipai",
    "gn:country_code":"CN",
    "gn:dem":233,
    "gn:feature_class":"P",
    "gn:feature_code":"PPL",
    "gn:name":"Shilipai",
    "gn:population":0,
    "gn:timezone":"Asia/Shanghai",
    "iso:country":"CN",
    "name:und_x_variant":[
        "\u5341\u91cc\u6e90"
    ],
    "wof:name":"Shilipai",
    "wof:placetype":"locality"
},
  "geometry": {"coordinates":[118.51416999999999,27.88194],"type":"Point"}
}