{
  "type": "Feature",
  "properties": {
    "gn:admin1_code":"9.0",
    "gn:asciiname":"Beiyuzhuang",
    "gn:country_code":"CN",
    "gn:dem":70,
    "gn:feature_class":"P",
    "gn:feature_code":"PPL",
    "gn:name":"Beiyuzhuang",
    "gn:population":0,
    "gn:timezone":"Asia/Shanghai",
    "iso:country":"CN",
    "name:zho_x_preferred":[
        "\u5317\u4e8e\u5e84"
    ],
    "wof:name":"Beiyuzhuang",
    "wof:placetype":"locality"
},
  "geometry": {"coordinates":[114.34267,35.39704000000001],"type":"Point"}
}