{
  "type": "Feature",
  "properties": {
    "gn:admin1_code":"32.0",
    "gn:asciiname":"Kumo",
    "gn:country_code":"CN",
    "gn:dem":2570,
    "gn:feature_class":"P",
    "gn:feature_code":"PPL",
    "gn:name":"Kumo",
    "gn:population":0,
    "gn:timezone":"Asia/Shanghai",
    "iso:country":"CN",
    "name:zho_x_preferred":[
        "\u5e93\u83ab"
    ],
    "wof:name":"Kumo",
    "wof:placetype":"locality"
},
  "geometry": {"coordinates":[102.837,28.2756],"type":"Point"}
}