{
  "type": "Feature",
  "properties": {
    "gn:admin1_code":"32.0",
    "gn:asciiname":"Kumo",
    "gn:country_code":"CN",
    "gn:dem":2570,
    "gn:feature_class":"P",
    "gn:feature_code":"PPL",
    "gn:name":"Kumo",
    "gn:population":0,
    "gn:timezone":"Asia/Shanghai",
    "iso:country":"CN",
    "name:ara_x_preferred":[
        "\u0643\u0648\u0645\u0648"
    ],
    "name:ben_x_preferred":[
        "\u0995\u09c1\u09ae\u09cb"
    ],
    "name:ceb_x_preferred":[
        "Kumo"
    ],
    "name:deu_x_preferred":[
        "Kumo"
    ],
    "name:ell_x_preferred":[
        "\u039a\u03bf\u03cd\u03bc\u03bf"
    ],
    "name:fas_x_preferred":[
        "\u06a9\u0648\u0645\u0648"
    ],
    "name:fra_x_preferred":[
        "Kumo"
    ],
    "name:heb_x_preferred":[
        "\u05e7\u05d5\u05de\u05d5"
    ],
    "name:hin_x_preferred":[
        "\u0915\u0942\u092e\u094b"
    ],
    "name:hun_x_preferred":[
        "Kumo"
    ],
    "name:ind_x_preferred":[
        "Kumo"
    ],
    "name:ita_x_preferred":[
        "Kumo"
    ],
    "name:jpn_x_preferred":[
        "\u30af\u30e2"
    ],
    "name:kor_x_preferred":[
        "\ucfe0\ubaa8"
    ],
    "name:nld_x_preferred":[
        "Kumo"
    ],
    "name:pol_x_preferred":[
        "Kumo"
    ],
    "name:por_x_preferred":[
        "Kumo"
    ],
    "name:rus_x_preferred":[
        "\u041a\u0443\u043c\u043e"
    ],
    "name:spa_x_preferred":[
        "Kumo"
    ],
    "name:swe_x_preferred":[
        "Kumo"
    ],
    "name:tur_x_preferred":[
        "Kumo"
    ],
    "name:ukr_x_preferred":[
        "\u041a\u0443\u043c\u043e"
    ],
    "name:urd_x_preferred":[
        "\u06a9\u0648\u0645\u0648"
    ],
    "name:vie_x_preferred":[
        "Kumo"
    ],
    "name:zho_cn_x_preferred":[
        "\u5e93\u83ab"
    ],
    "name:zho_tw_x_preferred":[
        "\u5eab\u6469"
    ],
    "name:zho_x_preferred":[
        "\u5e93\u83ab"
    ],
    "wof:name":"Kumo",
    "wof:placetype":"locality"
},
  "geometry": {"coordinates":[102.837,28.2756],"type":"Point"}
}