{
  "type": "Feature",
  "properties": {
    "gn:admin1_code":"24.0",
    "gn:asciiname":"Tudijiao",
    "gn:country_code":"CN",
    "gn:dem":1210,
    "gn:feature_class":"P",
    "gn:feature_code":"PPL",
    "gn:name":"Tudijiao",
    "gn:population":0,
    "gn:timezone":"Asia/Shanghai",
    "iso:country":"CN",
    "name:zho_x_preferred":[
        "\u571f\u5730\u89d2"
    ],
    "wof:name":"Tudijiao",
    "wof:placetype":"locality"
},
  "geometry": {"coordinates":[111.03636000000002,36.55804000000001],"type":"Point"}
}