{
  "type": "Feature",
  "properties": {
    "gn:admin1_code":"2.0",
    "gn:asciiname":"Shangxilong",
    "gn:country_code":"CN",
    "gn:dem":113,
    "gn:feature_class":"P",
    "gn:feature_code":"PPL",
    "gn:name":"Shangxilong",
    "gn:population":0,
    "gn:timezone":"Asia/Shanghai",
    "iso:country":"CN",
    "name:zho_x_preferred":[
        "\u4e0a\u897f\u5784"
    ],
    "wof:name":"Shangxilong",
    "wof:placetype":"locality"
},
  "geometry": {"coordinates":[118.97026,28.91241],"type":"Point"}
}