{
  "type": "Feature",
  "properties": {
    "gn:admin1_code":"25",
    "gn:asciiname":"Sanbulijia",
    "gn:country_code":"CN",
    "gn:dem":8,
    "gn:feature_class":"P",
    "gn:feature_code":"PPL",
    "gn:name":"Sanbulijia",
    "gn:population":0,
    "gn:timezone":"Asia/Shanghai",
    "iso:country":"CN",
    "name:zho_x_preferred":[
        "\u4e09\u57e0\u674e\u5bb6"
    ],
    "wof:name":"Sanbulijia",
    "wof:placetype":"locality"
},
  "geometry": {"coordinates":[119.65600000000001,36.9716],"type":"Point"}
}