{
  "type": "Feature",
  "properties": {
    "gn:admin1_code":"19.0",
    "gn:asciiname":"Zhaohugou Yidui",
    "gn:country_code":"CN",
    "gn:dem":329,
    "gn:feature_class":"P",
    "gn:feature_code":"PPLF",
    "gn:name":"Zhaohugou Yidui",
    "gn:population":0,
    "gn:timezone":"Asia/Shanghai",
    "iso:country":"CN",
    "name:zho_x_preferred":[
        "\u8d75\u6237\u6c9f\u4e00\u961f"
    ],
    "wof:name":"Zhaohugou Yidui",
    "wof:placetype":"locality"
},
  "geometry": {"coordinates":[120.724,41.9863],"type":"Point"}
}