{
  "type": "Feature",
  "properties": {
    "gn:admin1_code":"02",
    "gn:asciiname":"Yuandicun",
    "gn:country_code":"CN",
    "gn:dem":7,
    "gn:feature_class":"P",
    "gn:feature_code":"PPL",
    "gn:name":"Yuandicun",
    "gn:population":0,
    "gn:timezone":"Asia/Shanghai",
    "iso:country":"CN",
    "name:und_x_variant":[
        "Y\u00fcan-ti",
        "Yuandi",
        "Yuandicun"
    ],
    "name:zho_x_preferred":[
        "Y\u00fcan-ti"
    ],
    "name:zho_x_variant":[
        "\u56ed\u5e95\u6751"
    ],
    "wof:name":"Yuandicun",
    "wof:placetype":"locality"
},
  "geometry": {"coordinates":[120.69432999999999,27.95243],"type":"Point"}
}