{
  "type": "Feature",
  "properties": {
    "gn:admin1_code":"32.0",
    "gn:asciiname":"Hanwan",
    "gn:country_code":"CN",
    "gn:dem":378,
    "gn:feature_class":"P",
    "gn:feature_code":"PPL",
    "gn:name":"Hanwan",
    "gn:population":0,
    "gn:timezone":"Asia/Shanghai",
    "iso:country":"CN",
    "name:zho_x_preferred":[
        "\u6c57\u6e7e"
    ],
    "wof:name":"Hanwan",
    "wof:placetype":"locality"
},
  "geometry": {"coordinates":[104.95757,30.78282],"type":"Point"}
}