{
  "type": "Feature",
  "properties": {
    "gn:admin1_code":"7",
    "gn:asciiname":"Duping",
    "gn:country_code":"CN",
    "gn:dem":581,
    "gn:feature_class":"P",
    "gn:feature_code":"PPL",
    "gn:name":"Duping",
    "gn:population":0,
    "gn:timezone":"Asia/Shanghai",
    "iso:country":"CN",
    "name:und_x_variant":[
        "\u5835\u576a"
    ],
    "wof:name":"Duping",
    "wof:placetype":"locality"
},
  "geometry": {"coordinates":[119.75749999999999,27.09],"type":"Point"}
}