{
  "type": "Feature",
  "properties": {
    "gn:admin1_code":"32.0",
    "gn:asciiname":"Laoniu Yuanzi",
    "gn:country_code":"CN",
    "gn:dem":3752,
    "gn:feature_class":"P",
    "gn:feature_code":"PPL",
    "gn:name":"Laoniu Yuanzi",
    "gn:population":0,
    "gn:timezone":"Asia/Shanghai",
    "iso:country":"CN",
    "name:zho_x_preferred":[
        "\u8001\u725b\u56ed\u5b50"
    ],
    "wof:name":"Laoniu Yuanzi",
    "wof:placetype":"locality"
},
  "geometry": {"coordinates":[102.91592,31.02496],"type":"Point"}
}