{
  "type": "Feature",
  "properties": {
    "gn:admin1_code":"25.0",
    "gn:asciiname":"Wangjia Tiegou",
    "gn:country_code":"CN",
    "gn:dem":76,
    "gn:feature_class":"P",
    "gn:feature_code":"PPL",
    "gn:name":"Wangjia Tiegou",
    "gn:population":0,
    "gn:timezone":"Asia/Shanghai",
    "iso:country":"CN",
    "name:zho_x_preferred":[
        "\u738b\u5bb6\u94c1\u6c9f"
    ],
    "wof:name":"Wangjia Tiegou",
    "wof:placetype":"locality"
},
  "geometry": {"coordinates":[119.43434999999999,35.97793],"type":"Point"}
}