{
  "type": "Feature",
  "properties": {
    "gn:admin1_code":"11",
    "gn:asciiname":"Qiaotou",
    "gn:country_code":"CN",
    "gn:dem":619,
    "gn:feature_class":"P",
    "gn:feature_code":"PPL",
    "gn:name":"Qiaotou",
    "gn:population":0,
    "gn:timezone":"Asia/Shanghai",
    "iso:country":"CN",
    "name:ceb_x_preferred":[
        "Qiaotou"
    ],
    "name:deu_x_preferred":[
        "Qiaotou"
    ],
    "name:swe_x_preferred":[
        "Qiaotou"
    ],
    "name:zho_x_preferred":[
        "\u6865\u5934\u9547"
    ],
    "wof:name":"Qiaotou",
    "wof:placetype":"locality"
},
  "geometry": {"coordinates":[110.54361000000002,29.46278],"type":"Point"}
}