{
  "type": "Feature",
  "properties": {
    "gn:admin1_code":"10",
    "gn:asciiname":"Dapuhe",
    "gn:cc2":"CN",
    "gn:country_code":"CN",
    "gn:dem":0,
    "gn:feature_class":"P",
    "gn:feature_code":"PPL",
    "gn:name":"Dapuhe",
    "gn:population":0,
    "gn:timezone":"Asia/Shanghai",
    "iso:country":"CN",
    "name:und_x_variant":[
        "Ta-p\u2019u-ho",
        "Dapuhe"
    ],
    "wof:name":"Dapuhe",
    "wof:placetype":"locality"
},
  "geometry": {"coordinates":[119.28778,39.67583],"type":"Point"}
}