{
  "type": "Feature",
  "properties": {
    "gn:admin1_code":"19",
    "gn:asciiname":"Gaokanwancun",
    "gn:country_code":"CN",
    "gn:dem":6,
    "gn:feature_class":"P",
    "gn:feature_code":"PPL",
    "gn:name":"Gaokanwancun",
    "gn:population":0,
    "gn:timezone":"Asia/Shanghai",
    "iso:country":"CN",
    "name:und_x_variant":[
        "Kao-k\u2019an",
        "Gaokan",
        "Gaokanwan",
        "\u9ad8\u574e\u6e7e",
        "Gaokanwancun"
    ],
    "name:zho_x_preferred":[
        "\u9ad8\u574e\u6e7e\u6751"
    ],
    "wof:name":"Gaokanwancun",
    "wof:placetype":"locality"
},
  "geometry": {"coordinates":[122.26218,40.89026],"type":"Point"}
}