{
  "type": "Feature",
  "properties": {
    "gn:country":"CN",
    "gn:fcode":"PPL",
    "gn:pop":147,
    "iso:country":"CN",
    "name:unk_x_variant":[
        "Shuanglong"
    ],
    "qs:name":"Shuanglongchang",
    "qs:photos_9r":0,
    "qs:photos_sr":0,
    "qs:pop_sr":"1",
    "wof:name":"Shuanglongchang",
    "wof:placetype":"locality",
    "wof:population":147
},
  "geometry": {"coordinates":[106.56361,28.32028],"type":"Point"}
}