{
  "type": "Feature",
  "properties": {
    "gn:admin1_code":"12.0",
    "gn:asciiname":"Houbeixu",
    "gn:country_code":"CN",
    "gn:dem":28,
    "gn:feature_class":"P",
    "gn:feature_code":"PPL",
    "gn:name":"Houbeixu",
    "gn:population":0,
    "gn:timezone":"Asia/Shanghai",
    "iso:country":"CN",
    "name:zho_x_preferred":[
        "Houbeixu"
    ],
    "name:zho_x_variant":[
        "\u540e\u80cc\u5f90"
    ],
    "wof:name":"Houbeixu",
    "wof:placetype":"locality"
},
  "geometry": {"coordinates":[115.20335,30.04921],"type":"Point"}
}