{
  "type": "Feature",
  "properties": {
    "gn:admin1_code":"02",
    "gn:asciiname":"Lengshui",
    "gn:country_code":"CN",
    "gn:dem":267,
    "gn:feature_class":"P",
    "gn:feature_code":"PPLA4",
    "gn:name":"Lengshui",
    "gn:population":0,
    "gn:timezone":"Asia/Shanghai",
    "iso:country":"CN",
    "name:und_x_variant":[
        "Lengshui Zhen"
    ],
    "name:zho_x_preferred":[
        "\u51b7\u6c34"
    ],
    "name:zho_x_variant":[
        "\u51b7\u6c34\u9547"
    ],
    "wof:name":"Lengshui",
    "wof:placetype":"locality"
},
  "geometry": {"coordinates":[120.34614999999999,28.89994],"type":"Point"}
}