{
  "type": "Feature",
  "properties": {
    "gn:admin1_code":"33.0",
    "gn:asciiname":"Suntianping",
    "gn:country_code":"CN",
    "gn:dem":932,
    "gn:feature_class":"P",
    "gn:feature_code":"PPL",
    "gn:name":"Suntianping",
    "gn:population":0,
    "gn:timezone":"Asia/Shanghai",
    "iso:country":"CN",
    "name:zho_x_preferred":[
        "\u7b0b\u5929\u576a"
    ],
    "wof:name":"Suntianping",
    "wof:placetype":"locality"
},
  "geometry": {"coordinates":[106.40168,28.67777],"type":"Point"}
}