{
  "type": "Feature",
  "properties": {
    "gn:admin1_code":"3",
    "gn:asciiname":"Wokeng",
    "gn:country_code":"CN",
    "gn:dem":168,
    "gn:feature_class":"P",
    "gn:feature_code":"PPL",
    "gn:name":"Wokeng",
    "gn:population":0,
    "gn:timezone":"Asia/Shanghai",
    "iso:country":"CN",
    "name:zho_x_preferred":[
        "\u7a9d\u5751"
    ],
    "wof:name":"Wokeng",
    "wof:placetype":"locality"
},
  "geometry": {"coordinates":[114.68543,25.52542],"type":"Point"}
}