{
  "type": "Feature",
  "properties": {
    "gn:admin1_code":"12.0",
    "gn:asciiname":"Yangjiapo",
    "gn:country_code":"CN",
    "gn:dem":467,
    "gn:feature_class":"P",
    "gn:feature_code":"PPL",
    "gn:name":"Yangjiapo",
    "gn:population":0,
    "gn:timezone":"Asia/Shanghai",
    "iso:country":"CN",
    "name:zho_x_preferred":[
        "Yangjiapo"
    ],
    "name:zho_x_variant":[
        "\u6768\u5bb6\u5761"
    ],
    "wof:name":"Yangjiapo",
    "wof:placetype":"locality"
},
  "geometry": {"coordinates":[111.41307999999999,30.14643],"type":"Point"}
}