{
  "type": "Feature",
  "properties": {
    "gn:admin1_code":"12.0",
    "gn:asciiname":"Mianhualing",
    "gn:country_code":"CN",
    "gn:dem":762,
    "gn:feature_class":"P",
    "gn:feature_code":"PPL",
    "gn:name":"Mianhualing",
    "gn:population":0,
    "gn:timezone":"Asia/Shanghai",
    "iso:country":"CN",
    "name:zho_x_preferred":[
        "\u68c9\u82b1\u5cad"
    ],
    "wof:name":"Mianhualing",
    "wof:placetype":"locality"
},
  "geometry": {"coordinates":[109.89641,33.09018],"type":"Point"}
}