{
  "type": "Feature",
  "properties": {
    "gn:admin1_code":"30.0",
    "gn:asciiname":"Panlongcun",
    "gn:country_code":"CN",
    "gn:dem":64,
    "gn:feature_class":"P",
    "gn:feature_code":"PPL",
    "gn:name":"Panlongcun",
    "gn:population":0,
    "gn:timezone":"Asia/Urumqi",
    "iso:country":"CN",
    "name:zho_x_preferred":[
        "\u6f58\u9f99\u6751"
    ],
    "wof:name":"Panlongcun",
    "wof:placetype":"locality"
},
  "geometry": {"coordinates":[110.6874,22.20866],"type":"Point"}
}