{
  "type": "Feature",
  "properties": {
    "gn:admin1_code":"19.0",
    "gn:asciiname":"Lianjiangcun",
    "gn:country_code":"CN",
    "gn:dem":159,
    "gn:feature_class":"P",
    "gn:feature_code":"PPL",
    "gn:name":"Lianjiangcun",
    "gn:population":0,
    "gn:timezone":"Asia/Shanghai",
    "iso:country":"CN",
    "name:zho_x_preferred":[
        "\u8fde\u6c5f\u6751"
    ],
    "wof:name":"Lianjiangcun",
    "wof:placetype":"locality"
},
  "geometry": {"coordinates":[125.50342000000001,40.95026],"type":"Point"}
}