{
  "type": "Feature",
  "properties": {
    "gn:admin1_code":"11.0",
    "gn:asciiname":"Wulangmiao",
    "gn:country_code":"CN",
    "gn:dem":415,
    "gn:feature_class":"P",
    "gn:feature_code":"PPL",
    "gn:name":"Wulangmiao",
    "gn:population":0,
    "gn:timezone":"Asia/Shanghai",
    "iso:country":"CN",
    "name:zho_x_preferred":[
        "\u4e94\u90ce\u5e99"
    ],
    "wof:name":"Wulangmiao",
    "wof:placetype":"locality"
},
  "geometry": {"coordinates":[113.87021,26.53103],"type":"Point"}
}