{
  "type": "Feature",
  "properties": {
    "gn:admin1_code":"19.0",
    "gn:asciiname":"Shangwuchilou",
    "gn:country_code":"CN",
    "gn:dem":303,
    "gn:feature_class":"P",
    "gn:feature_code":"PPL",
    "gn:name":"Shangwuchilou",
    "gn:population":0,
    "gn:timezone":"Asia/Shanghai",
    "iso:country":"CN",
    "name:zho_x_preferred":[
        "\u4e0a\u52ff\u6c60\u697c"
    ],
    "wof:name":"Shangwuchilou",
    "wof:placetype":"locality"
},
  "geometry": {"coordinates":[120.77982,41.98146],"type":"Point"}
}