{
  "type": "Feature",
  "properties": {
    "gn:admin1_code":"32.0",
    "gn:asciiname":"Mutang",
    "gn:country_code":"CN",
    "gn:dem":2445,
    "gn:feature_class":"P",
    "gn:feature_code":"PPL",
    "gn:name":"Mutang",
    "gn:population":0,
    "gn:timezone":"Asia/Shanghai",
    "iso:country":"CN",
    "name:zho_x_preferred":[
        "\u6728\u5858"
    ],
    "wof:name":"Mutang",
    "wof:placetype":"locality"
},
  "geometry": {"coordinates":[103.142,34.0943],"type":"Point"}
}