{
  "type": "Feature",
  "properties": {
    "gn:admin1_code":"30.0",
    "gn:asciiname":"Zhongjianyong",
    "gn:country_code":"CN",
    "gn:dem":4,
    "gn:feature_class":"P",
    "gn:feature_code":"PPL",
    "gn:name":"Zhongjianyong",
    "gn:population":0,
    "gn:timezone":"Asia/Shanghai",
    "iso:country":"CN",
    "name:zho_x_preferred":[
        "\u4e2d\u95f4\u6d8c"
    ],
    "wof:name":"Zhongjianyong",
    "wof:placetype":"locality"
},
  "geometry": {"coordinates":[113.13148,22.84357],"type":"Point"}
}