{
  "type": "Feature",
  "properties": {
    "gn:admin1_code":"13",
    "gn:asciiname":"Kaisike'er",
    "gn:country_code":"CN",
    "gn:dem":18,
    "gn:feature_class":"P",
    "gn:feature_code":"PPL",
    "gn:name":"Kaisike\u2019er",
    "gn:population":0,
    "gn:timezone":"Asia/Urumqi",
    "iso:country":"CN",
    "name:und_x_variant":[
        "Kaisike\u2019er",
        "\u5f00\u65af\u514b\u5c14"
    ],
    "wof:name":"Kaisike'er",
    "wof:placetype":"locality"
},
  "geometry": {"coordinates":[88.62828,42.82482],"type":"Point"}
}