{
  "type": "Feature",
  "properties": {
    "gn:admin1_code":"26.0",
    "gn:asciiname":"Hujia Maocun",
    "gn:country_code":"CN",
    "gn:dem":1174,
    "gn:feature_class":"P",
    "gn:feature_code":"PPL",
    "gn:name":"Hujia Maocun",
    "gn:population":0,
    "gn:timezone":"Asia/Shanghai",
    "iso:country":"CN",
    "name:zho_x_preferred":[
        "\u80e1\u5bb6\u5cc1\u6751"
    ],
    "wof:name":"Hujia Maocun",
    "wof:placetype":"locality"
},
  "geometry": {"coordinates":[110.119,38.097],"type":"Point"}
}