{
  "type": "Feature",
  "properties": {
    "gn:admin1_code":"8.0",
    "gn:asciiname":"Fushengcun",
    "gn:country_code":"CN",
    "gn:dem":109,
    "gn:feature_class":"P",
    "gn:feature_code":"PPL",
    "gn:name":"Fushengcun",
    "gn:population":0,
    "gn:timezone":"Asia/Shanghai",
    "iso:country":"CN",
    "name:zho_x_preferred":[
        "\u5bcc\u76db\u6751"
    ],
    "wof:name":"Fushengcun",
    "wof:placetype":"locality"
},
  "geometry": {"coordinates":[130.20469,47.06121],"type":"Point"}
}