{
  "type": "Feature",
  "properties": {
    "gn:admin1_code":"12.0",
    "gn:asciiname":"Wujiashan",
    "gn:country_code":"CN",
    "gn:dem":26,
    "gn:feature_class":"P",
    "gn:feature_code":"PPLA3",
    "gn:name":"Wujiashan",
    "gn:population":0,
    "gn:timezone":"Asia/Shanghai",
    "iso:country":"CN",
    "name:deu_x_preferred":[
        "Dongxihu"
    ],
    "name:eus_x_preferred":[
        "Dongxihu Barrutia"
    ],
    "name:jpn_x_preferred":[
        "\u6771\u897f\u6e56\u533a"
    ],
    "name:kor_x_preferred":[
        "\ub465\uc2dc\ud6c4\uad6c"
    ],
    "name:nor_x_preferred":[
        "Dongxihu"
    ],
    "name:swe_x_preferred":[
        "Dongxihu"
    ],
    "name:und_x_variant":[
        "\u5434\u5bb6\u5c71",
        "Wujiashan Jiedao",
        "Dongxihu Qu",
        "\u4e1c\u897f\u6e56"
    ],
    "name:zho_x_preferred":[
        "\u4e1c\u897f\u6e56\u533a"
    ],
    "wof:name":"Wujiashan",
    "wof:placetype":"locality"
},
  "geometry": {"coordinates":[114.13166,30.61702],"type":"Point"}
}