{
  "type": "Feature",
  "properties": {
    "gn:admin1_code":"12.0",
    "gn:asciiname":"Wujiashan",
    "gn:country_code":"CN",
    "gn:dem":26,
    "gn:feature_class":"P",
    "gn:feature_code":"PPLA3",
    "gn:name":"Wujiashan",
    "gn:population":0,
    "gn:timezone":"Asia/Shanghai",
    "iso:country":"CN",
    "name:und_x_variant":[
        "\u5434\u5bb6\u5c71",
        "Wujiashan Jiedao",
        "Dongxihu",
        "Dongxihu Qu",
        "\u4e1c\u897f\u6e56"
    ],
    "wof:name":"Wujiashan",
    "wof:placetype":"locality"
},
  "geometry": {"coordinates":[114.13166,30.61702],"type":"Point"}
}