{
  "type": "Feature",
  "properties": {
    "gn:admin1_code":"14.0",
    "gn:asciiname":"Meisha Muchang",
    "gn:country_code":"CN",
    "gn:dem":4508,
    "gn:feature_class":"P",
    "gn:feature_code":"PPLF",
    "gn:name":"Meisha Muchang",
    "gn:population":0,
    "gn:timezone":"Asia/Urumqi",
    "iso:country":"CN",
    "name:zho_x_preferred":[
        "\u6ca1\u6c99\u7267\u573a"
    ],
    "wof:name":"Meisha Muchang",
    "wof:placetype":"locality"
},
  "geometry": {"coordinates":[98.43351,29.86472],"type":"Point"}
}