{
  "type": "Feature",
  "properties": {
    "gn:admin1_code":"19.0",
    "gn:asciiname":"Dalaohucun",
    "gn:country_code":"CN",
    "gn:dem":61,
    "gn:feature_class":"P",
    "gn:feature_code":"PPL",
    "gn:name":"Dalaohucun",
    "gn:population":0,
    "gn:timezone":"Asia/Shanghai",
    "iso:country":"CN",
    "name:zho_x_preferred":[
        "\u5927\u8001\u864e\u6751"
    ],
    "wof:name":"Dalaohucun",
    "wof:placetype":"locality"
},
  "geometry": {"coordinates":[121.83,39.6505],"type":"Point"}
}