{
  "type": "Feature",
  "properties": {
    "gn:admin1_code":"14.0",
    "gn:asciiname":"Wadicun",
    "gn:country_code":"CN",
    "gn:dem":3883,
    "gn:feature_class":"P",
    "gn:feature_code":"PPL",
    "gn:name":"Wadicun",
    "gn:population":0,
    "gn:timezone":"Asia/Urumqi",
    "iso:country":"CN",
    "name:zho_x_preferred":[
        "\u74e6\u5730\u6751"
    ],
    "wof:name":"Wadicun",
    "wof:placetype":"locality"
},
  "geometry": {"coordinates":[95.01124,31.15079],"type":"Point"}
}