{
  "type": "Feature",
  "properties": {
    "gn:admin1_code":"11",
    "gn:asciiname":"Taolingxu",
    "gn:country_code":"CN",
    "gn:dem":321,
    "gn:feature_class":"P",
    "gn:feature_code":"PPL",
    "gn:name":"Taolingxu",
    "gn:population":0,
    "gn:timezone":"Asia/Shanghai",
    "iso:country":"CN",
    "name:zho_x_preferred":[
        "\u9676\u73b2\u5729"
    ],
    "wof:name":"Taolingxu",
    "wof:placetype":"locality"
},
  "geometry": {"coordinates":[112.31861000000001,25.74194],"type":"Point"}
}