{
  "type": "Feature",
  "properties": {
    "gn:admin1_code":"16.0",
    "gn:asciiname":"Qiaonancun",
    "gn:country_code":"CN",
    "gn:dem":478,
    "gn:feature_class":"P",
    "gn:feature_code":"PPL",
    "gn:name":"Qiaonancun",
    "gn:population":0,
    "gn:timezone":"Asia/Shanghai",
    "iso:country":"CN",
    "name:zho_x_preferred":[
        "\u6865\u5357\u6751"
    ],
    "wof:name":"Qiaonancun",
    "wof:placetype":"locality"
},
  "geometry": {"coordinates":[106.848,23.4642],"type":"Point"}
}