{
  "type": "Feature",
  "properties": {
    "gn:admin1_code":"15.0",
    "gn:asciiname":"Zinishui",
    "gn:country_code":"CN",
    "gn:dem":1429,
    "gn:feature_class":"P",
    "gn:feature_code":"PPL",
    "gn:name":"Zinishui",
    "gn:population":0,
    "gn:timezone":"Asia/Shanghai",
    "iso:country":"CN",
    "name:zho_x_preferred":[
        "\u6ecb\u6ce5\u6c34"
    ],
    "wof:name":"Zinishui",
    "wof:placetype":"locality"
},
  "geometry": {"coordinates":[104.72499999999999,36.7271],"type":"Point"}
}