{
  "type": "Feature",
  "properties": {
    "gn:admin1_code":"3.0",
    "gn:asciiname":"Jiuzhoucun",
    "gn:country_code":"CN",
    "gn:dem":24,
    "gn:feature_class":"P",
    "gn:feature_code":"PPL",
    "gn:name":"Jiuzhoucun",
    "gn:population":0,
    "gn:timezone":"Asia/Shanghai",
    "iso:country":"CN",
    "name:und_x_variant":[
        "\u4e5d\u6d32\u6751"
    ],
    "wof:name":"Jiuzhoucun",
    "wof:placetype":"locality"
},
  "geometry": {"coordinates":[116.25479,28.48182000000001],"type":"Point"}
}