{
  "type": "Feature",
  "properties": {
    "gn:admin1_code":"10.0",
    "gn:asciiname":"Beiyangma",
    "gn:country_code":"CN",
    "gn:dem":95,
    "gn:feature_class":"P",
    "gn:feature_code":"PPL",
    "gn:name":"Beiyangma",
    "gn:population":0,
    "gn:timezone":"Asia/Shanghai",
    "iso:country":"CN",
    "name:und_x_variant":[
        "\u5317\u517b\u9a6c"
    ],
    "wof:name":"Beiyangma",
    "wof:placetype":"locality"
},
  "geometry": {"coordinates":[114.66471,38.51814],"type":"Point"}
}