{
  "type": "Feature",
  "properties": {
    "gn:admin1_code":"32.0",
    "gn:asciiname":"Yongxing",
    "gn:country_code":"CN",
    "gn:dem":1212,
    "gn:feature_class":"P",
    "gn:feature_code":"PPL",
    "gn:name":"Yongxing",
    "gn:population":0,
    "gn:timezone":"Asia/Shanghai",
    "iso:country":"CN",
    "name:ceb_x_preferred":[
        "Yongxing"
    ],
    "name:deu_x_preferred":[
        "Yongxing"
    ],
    "name:gan_x_preferred":[
        "\u6c38\u8208"
    ],
    "name:zho_x_preferred":[
        "\u6c38\u5174"
    ],
    "wof:name":"Yongxing",
    "wof:placetype":"locality"
},
  "geometry": {"coordinates":[101.44683000000001,26.93689],"type":"Point"}
}