{
  "type": "Feature",
  "properties": {
    "gn:admin1_code":"8.0",
    "gn:asciiname":"Changshoucun",
    "gn:country_code":"CN",
    "gn:dem":86,
    "gn:feature_class":"P",
    "gn:feature_code":"PPL",
    "gn:name":"Changshoucun",
    "gn:population":0,
    "gn:timezone":"Asia/Shanghai",
    "iso:country":"CN",
    "name:zho_x_preferred":[
        "\u957f\u5bff\u6751"
    ],
    "wof:name":"Changshoucun",
    "wof:placetype":"locality"
},
  "geometry": {"coordinates":[130.03110000000001,46.75205],"type":"Point"}
}