{
  "type": "Feature",
  "properties": {
    "gn:admin1_code":"26",
    "gn:asciiname":"Yaozicun",
    "gn:country_code":"CN",
    "gn:dem":1053,
    "gn:feature_class":"P",
    "gn:feature_code":"PPL",
    "gn:name":"Yaozicun",
    "gn:population":0,
    "gn:timezone":"Asia/Shanghai",
    "iso:country":"CN",
    "name:und_x_variant":[
        "Yaozi",
        "\u9e5e\u5b50",
        "Yaozicun"
    ],
    "name:zho_x_preferred":[
        "\u9e5e\u5b50"
    ],
    "name:zho_x_variant":[
        "\u9e5e\u5b50\u6751"
    ],
    "wof:name":"Yaozicun",
    "wof:placetype":"locality"
},
  "geometry": {"coordinates":[108.04143999999999,34.67395],"type":"Point"}
}