{
  "type": "Feature",
  "properties": {
    "gn:admin1_code":"18",
    "gn:asciiname":"Taitoujing",
    "gn:country_code":"CN",
    "gn:dem":1048,
    "gn:feature_class":"P",
    "gn:feature_code":"PPL",
    "gn:name":"Taitoujing",
    "gn:population":0,
    "gn:timezone":"Asia/Shanghai",
    "iso:country":"CN",
    "name:zho_x_preferred":[
        "\u62ac\u5934\u4e95"
    ],
    "wof:name":"Taitoujing",
    "wof:placetype":"locality"
},
  "geometry": {"coordinates":[108.42100000000001,28.2884],"type":"Point"}
}