{
  "type": "Feature",
  "properties": {
    "gn:admin1_code":"07",
    "gn:asciiname":"Dahe",
    "gn:country_code":"CN",
    "gn:dem":547,
    "gn:feature_class":"P",
    "gn:feature_code":"PPL",
    "gn:name":"Dahe",
    "gn:population":0,
    "gn:timezone":"Asia/Shanghai",
    "iso:country":"CN",
    "name:ceb_x_preferred":[
        "Dahe"
    ],
    "name:deu_x_preferred":[
        "Dahe"
    ],
    "name:swe_x_preferred":[
        "Dahe"
    ],
    "name:zho_x_preferred":[
        "\u5927\u5408"
    ],
    "wof:name":"Dahe",
    "wof:placetype":"locality"
},
  "geometry": {"coordinates":[117.7925,25.82778],"type":"Point"}
}