{
  "type": "Feature",
  "properties": {
    "gn:admin1_code":"10",
    "gn:asciiname":"Dongxinghe",
    "gn:country_code":"CN",
    "gn:dem":1609,
    "gn:feature_class":"P",
    "gn:feature_code":"PPL",
    "gn:name":"Dongxinghe",
    "gn:population":0,
    "gn:timezone":"Asia/Shanghai",
    "iso:country":"CN",
    "name:zho_x_preferred":[
        "\u4e1c\u674f\u6cb3"
    ],
    "wof:name":"Dongxinghe",
    "wof:placetype":"locality"
},
  "geometry": {"coordinates":[114.8185,39.75383],"type":"Point"}
}