{
  "type": "Feature",
  "properties": {
    "gn:admin1_code":"5.0",
    "gn:asciiname":"Jiudehaocun",
    "gn:country_code":"CN",
    "gn:dem":215,
    "gn:feature_class":"P",
    "gn:feature_code":"PPL",
    "gn:name":"Jiudehaocun",
    "gn:population":0,
    "gn:timezone":"Asia/Shanghai",
    "iso:country":"CN",
    "name:zho_x_preferred":[
        "\u4e5d\u5fb7\u53f7\u6751"
    ],
    "wof:name":"Jiudehaocun",
    "wof:placetype":"locality"
},
  "geometry": {"coordinates":[125.29264999999999,44.67088],"type":"Point"}
}