{
  "type": "Feature",
  "properties": {
    "gn:admin1_code":"32.0",
    "gn:asciiname":"Chenjia Bubu",
    "gn:country_code":"CN",
    "gn:dem":2375,
    "gn:feature_class":"P",
    "gn:feature_code":"PPL",
    "gn:name":"Chenjia Bubu",
    "gn:population":0,
    "gn:timezone":"Asia/Shanghai",
    "iso:country":"CN",
    "name:zho_x_preferred":[
        "\u9648\u5bb6\u5821\u5821"
    ],
    "wof:name":"Chenjia Bubu",
    "wof:placetype":"locality"
},
  "geometry": {"coordinates":[102.242,26.9496],"type":"Point"}
}