{
  "type": "Feature",
  "properties": {
    "gn:admin1_code":"10.0",
    "gn:asciiname":"Dalinggongzhuang",
    "gn:country_code":"CN",
    "gn:dem":23,
    "gn:feature_class":"P",
    "gn:feature_code":"PPL",
    "gn:name":"Dalinggongzhuang",
    "gn:population":0,
    "gn:timezone":"Asia/Shanghai",
    "iso:country":"CN",
    "name:zho_x_preferred":[
        "\u5927\u4ee4\u516c\u5e84"
    ],
    "wof:name":"Dalinggongzhuang",
    "wof:placetype":"locality"
},
  "geometry": {"coordinates":[118.02481,39.81501],"type":"Point"}
}