{
  "type": "Feature",
  "properties": {
    "gn:admin1_code":"18",
    "gn:asciiname":"Qinike",
    "gn:country_code":"CN",
    "gn:dem":1863,
    "gn:feature_class":"P",
    "gn:feature_code":"PPL",
    "gn:name":"Qinike",
    "gn:population":0,
    "gn:timezone":"Asia/Shanghai",
    "iso:country":"CN",
    "name:zho_x_preferred":[
        "\u5176\u6ce5\u514b"
    ],
    "wof:name":"Qinike",
    "wof:placetype":"locality"
},
  "geometry": {"coordinates":[104.727,26.035],"type":"Point"}
}