{
  "type": "Feature",
  "properties": {
    "gn:admin1_code":"15.0",
    "gn:asciiname":"Sizuishan",
    "gn:country_code":"CN",
    "gn:dem":1344,
    "gn:feature_class":"P",
    "gn:feature_code":"PPL",
    "gn:name":"Sizuishan",
    "gn:population":0,
    "gn:timezone":"Asia/Shanghai",
    "iso:country":"CN",
    "name:und_x_variant":[
        "\u56db\u5480\u5c71"
    ],
    "wof:name":"Sizuishan",
    "wof:placetype":"locality"
},
  "geometry": {"coordinates":[107.54348,36.37658],"type":"Point"}
}