{
  "type": "Feature",
  "properties": {
    "gn:admin1_code":"6.0",
    "gn:asciiname":"Shengli Dadui",
    "gn:country_code":"CN",
    "gn:dem":3284,
    "gn:feature_class":"P",
    "gn:feature_code":"PPL",
    "gn:name":"Shengli Dadui",
    "gn:population":0,
    "gn:timezone":"Asia/Shanghai",
    "iso:country":"CN",
    "name:und_x_variant":[
        "\u80dc\u5229\u5927\u961f"
    ],
    "wof:name":"Shengli Dadui",
    "wof:placetype":"locality"
},
  "geometry": {"coordinates":[100.45747,37.23696],"type":"Point"}
}