{
  "type": "Feature",
  "properties": {
    "gn:admin1_code":"26.0",
    "gn:asciiname":"Majiacun",
    "gn:country_code":"CN",
    "gn:dem":868,
    "gn:feature_class":"P",
    "gn:feature_code":"PPL",
    "gn:name":"Majiacun",
    "gn:population":0,
    "gn:timezone":"Asia/Shanghai",
    "iso:country":"CN",
    "name:zho_x_preferred":[
        "\u9ebb\u5bb6\u6751"
    ],
    "wof:name":"Majiacun",
    "wof:placetype":"locality"
},
  "geometry": {"coordinates":[109.55118,35.26275],"type":"Point"}
}