{
  "type": "Feature",
  "properties": {
    "gn:admin1_code":"26.0",
    "gn:asciiname":"Heibaisheng",
    "gn:country_code":"CN",
    "gn:dem":931,
    "gn:feature_class":"P",
    "gn:feature_code":"PPL",
    "gn:name":"Heibaisheng",
    "gn:population":0,
    "gn:timezone":"Asia/Shanghai",
    "iso:country":"CN",
    "name:zho_x_preferred":[
        "\u9ed1\u767d\u80dc"
    ],
    "wof:name":"Heibaisheng",
    "wof:placetype":"locality"
},
  "geometry": {"coordinates":[110.34742,36.73073],"type":"Point"}
}