{
  "type": "Feature",
  "properties": {
    "gn:admin1_code":"4.0",
    "gn:asciiname":"Hongtu",
    "gn:country_code":"CN",
    "gn:dem":7,
    "gn:feature_class":"P",
    "gn:feature_code":"PPL",
    "gn:name":"Hongtu",
    "gn:population":0,
    "gn:timezone":"Asia/Shanghai",
    "iso:country":"CN",
    "name:zho_x_preferred":[
        "Hongtu"
    ],
    "name:zho_x_variant":[
        "\u5b8f\u56fe"
    ],
    "wof:name":"Hongtu",
    "wof:placetype":"locality"
},
  "geometry": {"coordinates":[119.32391,33.12085],"type":"Point"}
}