{
  "type": "Feature",
  "properties": {
    "gn:admin1_code":"26",
    "gn:asciiname":"Taojiazhuang",
    "gn:country_code":"CN",
    "gn:dem":1277,
    "gn:feature_class":"P",
    "gn:feature_code":"PPL",
    "gn:name":"Taojiazhuang",
    "gn:population":0,
    "gn:timezone":"Asia/Shanghai",
    "iso:country":"CN",
    "wof:name":"Taojiazhuang",
    "wof:placetype":"locality"
},
  "geometry": {"coordinates":[108.68639,34.87694],"type":"Point"}
}