{
  "type": "Feature",
  "properties": {
    "gn:admin1_code":"29.0",
    "gn:asciiname":"Wuhuazhai",
    "gn:country_code":"CN",
    "gn:dem":781,
    "gn:feature_class":"P",
    "gn:feature_code":"PPL",
    "gn:name":"Wuhuazhai",
    "gn:population":0,
    "gn:timezone":"Asia/Shanghai",
    "iso:country":"CN",
    "name:zho_x_preferred":[
        "\u4e94\u82b1\u5be8"
    ],
    "wof:name":"Wuhuazhai",
    "wof:placetype":"locality"
},
  "geometry": {"coordinates":[100.23099999999999,22.6609],"type":"Point"}
}