{
  "type": "Feature",
  "properties": {
    "gn:admin1_code":"8.0",
    "gn:asciiname":"Nianzigoucun",
    "gn:country_code":"CN",
    "gn:dem":441,
    "gn:feature_class":"P",
    "gn:feature_code":"PPL",
    "gn:name":"Nianzigoucun",
    "gn:population":0,
    "gn:timezone":"Asia/Shanghai",
    "iso:country":"CN",
    "name:zho_x_preferred":[
        "\u78be\u5b50\u6c9f\u6751"
    ],
    "wof:name":"Nianzigoucun",
    "wof:placetype":"locality"
},
  "geometry": {"coordinates":[130.15597,44.83646],"type":"Point"}
}