{
  "type": "Feature",
  "properties": {
    "gn:admin1_code":"9.0",
    "gn:asciiname":"Liudianshi",
    "gn:country_code":"CN",
    "gn:dem":214,
    "gn:feature_class":"P",
    "gn:feature_code":"PPL",
    "gn:name":"Liudianshi",
    "gn:population":0,
    "gn:timezone":"Asia/Shanghai",
    "iso:country":"CN",
    "name:zho_x_preferred":[
        "\u5218\u5960\u77f3"
    ],
    "wof:name":"Liudianshi",
    "wof:placetype":"locality"
},
  "geometry": {"coordinates":[112.50387000000001,33.12318],"type":"Point"}
}