{
  "type": "Feature",
  "properties": {
    "gn:admin1_code":"3",
    "gn:asciiname":"Xinxiaowu",
    "gn:country_code":"CN",
    "gn:dem":278,
    "gn:feature_class":"P",
    "gn:feature_code":"PPL",
    "gn:name":"Xinxiaowu",
    "gn:population":0,
    "gn:timezone":"Asia/Shanghai",
    "iso:country":"CN",
    "name:zho_x_preferred":[
        "\u65b0\u8096\u5c4b"
    ],
    "wof:name":"Xinxiaowu",
    "wof:placetype":"locality"
},
  "geometry": {"coordinates":[114.157,25.4064],"type":"Point"}
}