{
  "type": "Feature",
  "properties": {
    "gn:admin1_code":"9",
    "gn:asciiname":"Bizhuang",
    "gn:country_code":"CN",
    "gn:dem":434,
    "gn:feature_class":"P",
    "gn:feature_code":"PPL",
    "gn:name":"Bizhuang",
    "gn:population":0,
    "gn:timezone":"Asia/Shanghai",
    "iso:country":"CN",
    "wof:name":"Bizhuang",
    "wof:placetype":"locality"
},
  "geometry": {"coordinates":[112.36221999999999,35.02861],"type":"Point"}
}