{
  "type": "Feature",
  "properties": {
    "gn:admin1_code":"5.0",
    "gn:asciiname":"Yibuluocun",
    "gn:country_code":"CN",
    "gn:dem":196,
    "gn:feature_class":"P",
    "gn:feature_code":"PPL",
    "gn:name":"Yibuluocun",
    "gn:population":0,
    "gn:timezone":"Asia/Shanghai",
    "iso:country":"CN",
    "name:zho_x_preferred":[
        "\u4e00\u90e8\u843d\u6751"
    ],
    "wof:name":"Yibuluocun",
    "wof:placetype":"locality"
},
  "geometry": {"coordinates":[125.04174999999999,44.96766],"type":"Point"}
}