{
  "type": "Feature",
  "properties": {
    "gn:admin1_code":"13",
    "gn:asciiname":"Gulebage",
    "gn:country_code":"CN",
    "gn:dem":1252,
    "gn:feature_class":"P",
    "gn:feature_code":"PPL",
    "gn:name":"Gulebage",
    "gn:population":0,
    "gn:timezone":"Asia/Shanghai",
    "iso:country":"CN",
    "name:und_x_variant":[
        "\u53e4\u52d2\u5df4\u683c"
    ],
    "wof:name":"Gulebage",
    "wof:placetype":"locality"
},
  "geometry": {"coordinates":[77.27518000000001,38.26495],"type":"Point"}
}