{
  "type": "Feature",
  "properties": {
    "gn:admin1_code":"14.0",
    "gn:asciiname":"Donpanglung",
    "gn:country_code":"CN",
    "gn:dem":4590,
    "gn:feature_class":"P",
    "gn:feature_code":"PPL",
    "gn:name":"Donpanglung",
    "gn:population":0,
    "gn:timezone":"Asia/Urumqi",
    "iso:country":"CN",
    "name:bod_x_preferred":[
        "Donpanglung"
    ],
    "name:zho_x_preferred":[
        "Dunpenglong"
    ],
    "name:zho_x_variant":[
        "\u6566\u6367\u9686"
    ],
    "wof:name":"Donpanglung",
    "wof:placetype":"locality"
},
  "geometry": {"coordinates":[93.601,32.101],"type":"Point"}
}