{
  "type": "Feature",
  "properties": {
    "gn:admin1_code":"02",
    "gn:asciiname":"Shangxi",
    "gn:country_code":"CN",
    "gn:dem":91,
    "gn:feature_class":"P",
    "gn:feature_code":"PPLA4",
    "gn:name":"Shangxi",
    "gn:population":0,
    "gn:timezone":"Asia/Shanghai",
    "iso:country":"CN",
    "name:fas_x_preferred":[
        "\u0634\u0627\u0646\u06af\u0634\u06cc"
    ],
    "name:und_x_variant":[
        "Shang-hsi",
        "\u4e0a\u6eaa",
        "Shangxi",
        "Shangxi Zhen"
    ],
    "name:zho_x_preferred":[
        "\u4e0a\u6eaa\u9547"
    ],
    "wof:name":"Shangxi",
    "wof:placetype":"locality"
},
  "geometry": {"coordinates":[119.93205,29.28489],"type":"Point"}
}