{
  "type": "Feature",
  "properties": {
    "gn:admin1_code":"26.0",
    "gn:asciiname":"Qianzuishang",
    "gn:country_code":"CN",
    "gn:dem":1403,
    "gn:feature_class":"P",
    "gn:feature_code":"PPL",
    "gn:name":"Qianzuishang",
    "gn:population":0,
    "gn:timezone":"Asia/Shanghai",
    "iso:country":"CN",
    "name:zho_x_preferred":[
        "\u524d\u5480\u4e0a"
    ],
    "wof:name":"Qianzuishang",
    "wof:placetype":"locality"
},
  "geometry": {"coordinates":[108.03903,33.86564],"type":"Point"}
}