{
  "type": "Feature",
  "properties": {
    "gn:admin1_code":"26.0",
    "gn:asciiname":"Yadicun",
    "gn:country_code":"CN",
    "gn:dem":1186,
    "gn:feature_class":"P",
    "gn:feature_code":"PPL",
    "gn:name":"Yadicun",
    "gn:population":0,
    "gn:timezone":"Asia/Shanghai",
    "iso:country":"CN",
    "name:zho_x_preferred":[
        "\u5d16\u5824\u6751"
    ],
    "wof:name":"Yadicun",
    "wof:placetype":"locality"
},
  "geometry": {"coordinates":[109.43593,37.20228],"type":"Point"}
}