{
  "type": "Feature",
  "properties": {
    "gn:admin1_code":"29.0",
    "gn:asciiname":"Mijiawan",
    "gn:country_code":"CN",
    "gn:dem":1907,
    "gn:feature_class":"P",
    "gn:feature_code":"PPL",
    "gn:name":"Mijiawan",
    "gn:population":0,
    "gn:timezone":"Asia/Shanghai",
    "iso:country":"CN",
    "name:zho_x_preferred":[
        "\u7c73\u5bb6\u6e7e"
    ],
    "wof:name":"Mijiawan",
    "wof:placetype":"locality"
},
  "geometry": {"coordinates":[103.583,27.2279],"type":"Point"}
}