{
  "type": "Feature",
  "properties": {
    "gn:admin1_code":"4.0",
    "gn:asciiname":"Liangzhuangcun",
    "gn:country_code":"CN",
    "gn:dem":14,
    "gn:feature_class":"P",
    "gn:feature_code":"PPL",
    "gn:name":"Liangzhuangcun",
    "gn:population":0,
    "gn:timezone":"Asia/Shanghai",
    "iso:country":"CN",
    "name:zho_x_preferred":[
        "\u6881\u5e84\u6751"
    ],
    "wof:name":"Liangzhuangcun",
    "wof:placetype":"locality"
},
  "geometry": {"coordinates":[118.55486999999999,34.1535],"type":"Point"}
}