{
  "type": "Feature",
  "properties": {
    "gn:admin1_code":"9.0",
    "gn:asciiname":"Huanglianshupo",
    "gn:country_code":"CN",
    "gn:dem":204,
    "gn:feature_class":"P",
    "gn:feature_code":"PPL",
    "gn:name":"Huanglianshupo",
    "gn:population":0,
    "gn:timezone":"Asia/Shanghai",
    "iso:country":"CN",
    "name:zho_x_preferred":[
        "\u9ec4\u695d\u6811\u5761"
    ],
    "wof:name":"Huanglianshupo",
    "wof:placetype":"locality"
},
  "geometry": {"coordinates":[111.83999,33.16166],"type":"Point"}
}