{
  "type": "Feature",
  "properties": {
    "gn:admin1_code":"29.0",
    "gn:asciiname":"Daluchang",
    "gn:country_code":"CN",
    "gn:dem":2214,
    "gn:feature_class":"P",
    "gn:feature_code":"PPL",
    "gn:name":"Daluchang",
    "gn:population":0,
    "gn:timezone":"Asia/Shanghai",
    "iso:country":"CN",
    "name:zho_x_preferred":[
        "\u5927\u7089\u5382"
    ],
    "wof:name":"Daluchang",
    "wof:placetype":"locality"
},
  "geometry": {"coordinates":[99.5744,24.0026],"type":"Point"}
}