{
  "type": "Feature",
  "properties": {
    "gn:admin1_code":"10",
    "gn:asciiname":"Fanjiazhuang",
    "gn:country_code":"CN",
    "gn:dem":39,
    "gn:feature_class":"P",
    "gn:feature_code":"PPL",
    "gn:name":"Fanjiazhuang",
    "gn:population":0,
    "gn:timezone":"Asia/Shanghai",
    "iso:country":"CN",
    "name:und_x_variant":[
        "Fan-chia-chuang",
        "Fanjiazhuang"
    ],
    "name:zho_x_preferred":[
        "\u8303\u5bb6\u5e84"
    ],
    "wof:name":"Fanjiazhuang",
    "wof:placetype":"locality"
},
  "geometry": {"coordinates":[115.253,37.9855],"type":"Point"}
}