{
  "type": "Feature",
  "properties": {
    "gn:admin1_code":"8.0",
    "gn:asciiname":"Daxiangfangtun",
    "gn:country_code":"CN",
    "gn:dem":124,
    "gn:feature_class":"P",
    "gn:feature_code":"PPL",
    "gn:name":"Daxiangfangtun",
    "gn:population":0,
    "gn:timezone":"Asia/Shanghai",
    "iso:country":"CN",
    "name:zho_x_preferred":[
        "\u5927\u53a2\u623f\u5c6f"
    ],
    "wof:name":"Daxiangfangtun",
    "wof:placetype":"locality"
},
  "geometry": {"coordinates":[128.18759,45.98909],"type":"Point"}
}