{
  "type": "Feature",
  "properties": {
    "gn:admin1_code":"11.0",
    "gn:asciiname":"Daliangshan",
    "gn:country_code":"CN",
    "gn:dem":656,
    "gn:feature_class":"P",
    "gn:feature_code":"PPL",
    "gn:name":"Daliangshan",
    "gn:population":0,
    "gn:timezone":"Asia/Shanghai",
    "iso:country":"CN",
    "name:zho_x_preferred":[
        "\u5927\u51c9\u5c71"
    ],
    "wof:name":"Daliangshan",
    "wof:placetype":"locality"
},
  "geometry": {"coordinates":[110.46052,27.17356],"type":"Point"}
}