{
  "type": "Feature",
  "properties": {
    "gn:admin1_code":"10",
    "gn:asciiname":"Zhongxingtuan",
    "gn:country_code":"CN",
    "gn:dem":25,
    "gn:feature_class":"P",
    "gn:feature_code":"PPL",
    "gn:name":"Zhongxingtuan",
    "gn:population":0,
    "gn:timezone":"Asia/Shanghai",
    "iso:country":"CN",
    "name:zho_x_preferred":[
        "\u4e2d\u90a2\u7583"
    ],
    "wof:name":"Zhongxingtuan",
    "wof:placetype":"locality"
},
  "geometry": {"coordinates":[115.78,37.6834],"type":"Point"}
}