{
  "type": "Feature",
  "properties": {
    "gn:admin1_code":"15.0",
    "gn:asciiname":"Sigou",
    "gn:country_code":"CN",
    "gn:dem":1955,
    "gn:feature_class":"P",
    "gn:feature_code":"PPL",
    "gn:name":"Sigou",
    "gn:population":0,
    "gn:timezone":"Asia/Shanghai",
    "iso:country":"CN",
    "name:zho_x_preferred":[
        "\u5bfa\u6c9f"
    ],
    "wof:name":"Sigou",
    "wof:placetype":"locality"
},
  "geometry": {"coordinates":[106.021,35.3805],"type":"Point"}
}