{
  "type": "Feature",
  "properties": {
    "gn:admin1_code":"4.0",
    "gn:asciiname":"Liuxushe",
    "gn:country_code":"CN",
    "gn:dem":5,
    "gn:feature_class":"P",
    "gn:feature_code":"PPL",
    "gn:name":"Liuxushe",
    "gn:population":0,
    "gn:timezone":"Asia/Shanghai",
    "iso:country":"CN",
    "name:zho_x_preferred":[
        "\u5218\u5729\u820d"
    ],
    "wof:name":"Liuxushe",
    "wof:placetype":"locality"
},
  "geometry": {"coordinates":[120.00292,33.1052],"type":"Point"}
}