{
  "type": "Feature",
  "properties": {
    "gn:admin1_code":"8.0",
    "gn:asciiname":"Dasujia Wobu",
    "gn:country_code":"CN",
    "gn:dem":148,
    "gn:feature_class":"P",
    "gn:feature_code":"PPL",
    "gn:name":"Dasujia Wobu",
    "gn:population":0,
    "gn:timezone":"Asia/Shanghai",
    "iso:country":"CN",
    "name:zho_x_preferred":[
        "\u5927\u82cf\u5bb6\u7a9d\u5821"
    ],
    "wof:name":"Dasujia Wobu",
    "wof:placetype":"locality"
},
  "geometry": {"coordinates":[126.08243,45.52004],"type":"Point"}
}