{
  "type": "Feature",
  "properties": {
    "gn:admin1_code":"14",
    "gn:asciiname":"Comai",
    "gn:country_code":"CN",
    "gn:dem":3902,
    "gn:feature_class":"P",
    "gn:feature_code":"PPL",
    "gn:name":"Comai",
    "gn:population":0,
    "gn:timezone":"Asia/Urumqi",
    "iso:country":"CN",
    "name:bod_x_preferred":[
        "\u0f58\u0f5a\u0f7c\u0f0b\u0f66\u0fa8\u0f51"
    ],
    "wof:name":"Comai",
    "wof:placetype":"locality"
},
  "geometry": {"coordinates":[90.73814,29.82143],"type":"Point"}
}