{
  "type": "Feature",
  "properties": {
    "gn:admin1_code":"30.0",
    "gn:asciiname":"Huadongcun",
    "gn:country_code":"CN",
    "gn:dem":12,
    "gn:feature_class":"P",
    "gn:feature_code":"PPL",
    "gn:name":"Huadongcun",
    "gn:population":0,
    "gn:timezone":"Asia/Shanghai",
    "iso:country":"CN",
    "name:und_x_variant":[
        "Huadong"
    ],
    "name:zho_x_preferred":[
        "\u534e\u4e1c\u6751"
    ],
    "name:zho_x_variant":[
        "\u534e\u6d1e"
    ],
    "wof:name":"Huadongcun",
    "wof:placetype":"locality"
},
  "geometry": {"coordinates":[116.13308000000001,23.40652],"type":"Point"}
}