{
  "type": "Feature",
  "properties": {
    "gn:admin1_code":"15.0",
    "gn:asciiname":"Hongtuzui",
    "gn:country_code":"CN",
    "gn:dem":2786,
    "gn:feature_class":"P",
    "gn:feature_code":"PPL",
    "gn:name":"Hongtuzui",
    "gn:population":0,
    "gn:timezone":"Asia/Shanghai",
    "iso:country":"CN",
    "name:zho_x_preferred":[
        "\u7ea2\u571f\u5634"
    ],
    "wof:name":"Hongtuzui",
    "wof:placetype":"locality"
},
  "geometry": {"coordinates":[104.006,35.6522],"type":"Point"}
}