{
  "type": "Feature",
  "properties": {
    "gn:admin1_code":"32.0",
    "gn:asciiname":"Musha",
    "gn:country_code":"CN",
    "gn:dem":3007,
    "gn:feature_class":"P",
    "gn:feature_code":"PPL",
    "gn:name":"Musha",
    "gn:population":0,
    "gn:timezone":"Asia/Shanghai",
    "iso:country":"CN",
    "name:zho_x_preferred":[
        "\u6728\u6c99"
    ],
    "wof:name":"Musha",
    "wof:placetype":"locality"
},
  "geometry": {"coordinates":[99.17140000000001,28.9364],"type":"Point"}
}