{
  "type": "Feature",
  "properties": {
    "gn:admin1_code":"3.0",
    "gn:asciiname":"Huguanglong",
    "gn:country_code":"CN",
    "gn:dem":39,
    "gn:feature_class":"P",
    "gn:feature_code":"PPL",
    "gn:name":"Huguanglong",
    "gn:population":0,
    "gn:timezone":"Asia/Shanghai",
    "iso:country":"CN",
    "name:und_x_variant":[
        "\u6e56\u5e7f\u5784"
    ],
    "wof:name":"Huguanglong",
    "wof:placetype":"locality"
},
  "geometry": {"coordinates":[116.00400999999999,29.31002],"type":"Point"}
}