{
  "type": "Feature",
  "properties": {
    "gn:admin1_code":"12.0",
    "gn:asciiname":"Huangjia Shuizhai",
    "gn:country_code":"CN",
    "gn:dem":62,
    "gn:feature_class":"P",
    "gn:feature_code":"PPL",
    "gn:name":"Huangjia Shuizhai",
    "gn:population":0,
    "gn:timezone":"Asia/Shanghai",
    "iso:country":"CN",
    "name:zho_x_preferred":[
        "\u9ec4\u5bb6\u6c34\u5be8"
    ],
    "wof:name":"Huangjia Shuizhai",
    "wof:placetype":"locality"
},
  "geometry": {"coordinates":[113.45535,31.71148],"type":"Point"}
}