{
  "type": "Feature",
  "properties": {
    "gn:admin1_code":"11.0",
    "gn:asciiname":"Baijia'ao",
    "gn:country_code":"CN",
    "gn:dem":1337,
    "gn:feature_class":"P",
    "gn:feature_code":"PPL",
    "gn:name":"Baijia\u2019ao",
    "gn:population":0,
    "gn:timezone":"Asia/Shanghai",
    "iso:country":"CN",
    "name:und_x_variant":[
        "Baijia\u2019ao"
    ],
    "name:zho_x_preferred":[
        "\u767d\u5bb6\u5773"
    ],
    "wof:name":"Baijia'ao",
    "wof:placetype":"locality"
},
  "geometry": {"coordinates":[110.53037999999999,26.46237],"type":"Point"}
}