{
  "type": "Feature",
  "properties": {
    "gn:admin1_code":"19.0",
    "gn:asciiname":"Baijiagou",
    "gn:country_code":"CN",
    "gn:dem":39,
    "gn:feature_class":"P",
    "gn:feature_code":"PPL",
    "gn:name":"Baijiagou",
    "gn:population":0,
    "gn:timezone":"Asia/Shanghai",
    "iso:country":"CN",
    "name:zho_x_preferred":[
        "\u767d\u5bb6\u6c9f"
    ],
    "wof:name":"Baijiagou",
    "wof:placetype":"locality"
},
  "geometry": {"coordinates":[120.52,40.497],"type":"Point"}
}