{
  "type": "Feature",
  "properties": {
    "gn:admin1_code":"1.0",
    "gn:asciiname":"Quexiangcun",
    "gn:country_code":"CN",
    "gn:dem":36,
    "gn:feature_class":"P",
    "gn:feature_code":"PPL",
    "gn:name":"Quexiangcun",
    "gn:population":0,
    "gn:timezone":"Asia/Shanghai",
    "iso:country":"CN",
    "name:zho_x_preferred":[
        "\u5374\u5df7\u6751"
    ],
    "wof:name":"Quexiangcun",
    "wof:placetype":"locality"
},
  "geometry": {"coordinates":[117.28034,32.66004],"type":"Point"}
}