{
  "type": "Feature",
  "properties": {
    "gn:admin1_code":"09",
    "gn:asciiname":"Taipingzhen",
    "gn:cc2":"CN",
    "gn:country_code":"CN",
    "gn:dem":830,
    "gn:feature_class":"P",
    "gn:feature_code":"PPL",
    "gn:name":"Taipingzhen",
    "gn:population":0,
    "gn:timezone":"Asia/Shanghai",
    "iso:country":"CN",
    "name:und_x_variant":[
        "T\u2019ai-p\u2019ing-chen",
        "T\u2019ai-p\u2019ing-t\u2019ou",
        "Taipingzhen"
    ],
    "wof:name":"Taipingzhen",
    "wof:placetype":"locality"
},
  "geometry": {"coordinates":[111.72861,33.61389],"type":"Point"}
}