{
  "type": "Feature",
  "properties": {
    "gn:admin1_code":"11",
    "gn:asciiname":"Jiugongqiao",
    "gn:cc2":"CN",
    "gn:country_code":"CN",
    "gn:dem":236,
    "gn:feature_class":"P",
    "gn:feature_code":"PPL",
    "gn:name":"Jiugongqiao",
    "gn:population":0,
    "gn:timezone":"Asia/Shanghai",
    "iso:country":"CN",
    "name:und_x_variant":[
        "Chiu-kung-ch\u2019iao",
        "Jiugongqiao"
    ],
    "wof:name":"Jiugongqiao",
    "wof:placetype":"locality"
},
  "geometry": {"coordinates":[111.36056000000001,27.12556],"type":"Point"}
}