{
  "type": "Feature",
  "properties": {
    "gn:admin1_code":"12.0",
    "gn:asciiname":"Pengtan",
    "gn:country_code":"CN",
    "gn:dem":37,
    "gn:feature_class":"P",
    "gn:feature_code":"PPL",
    "gn:name":"Pengtan",
    "gn:population":0,
    "gn:timezone":"Asia/Shanghai",
    "iso:country":"CN",
    "name:zho_x_preferred":[
        "\u670b\u6ee9"
    ],
    "wof:name":"Pengtan",
    "wof:placetype":"locality"
},
  "geometry": {"coordinates":[112.73614999999999,30.56543],"type":"Point"}
}