{
  "type": "Feature",
  "properties": {
    "gn:admin1_code":"5.0",
    "gn:asciiname":"Wangdayuan",
    "gn:country_code":"CN",
    "gn:dem":291,
    "gn:feature_class":"P",
    "gn:feature_code":"PPL",
    "gn:name":"Wangdayuan",
    "gn:population":0,
    "gn:timezone":"Asia/Shanghai",
    "iso:country":"CN",
    "name:zho_x_preferred":[
        "\u738b\u5927\u9662"
    ],
    "wof:name":"Wangdayuan",
    "wof:placetype":"locality"
},
  "geometry": {"coordinates":[125.2409,42.96586],"type":"Point"}
}