{
  "type": "Feature",
  "properties": {
    "gn:admin1_code":"10",
    "gn:asciiname":"Mancheng",
    "gn:cc2":"CN",
    "gn:country_code":"CN",
    "gn:dem":47,
    "gn:feature_class":"P",
    "gn:feature_code":"PPL",
    "gn:name":"Mancheng",
    "gn:population":0,
    "gn:timezone":"Asia/Shanghai",
    "iso:country":"CN",
    "name:und_x_variant":[
        "Man\u2019chen",
        "Man-ch\u2019eng-ch\u2019eng-kuan",
        "Man-ch\u2019eng-hsien",
        "Man-ch\u2019eng-hsien-ch\u2019eng",
        "Mancheng"
    ],
    "wof:name":"Mancheng",
    "wof:placetype":"locality"
},
  "geometry": {"coordinates":[115.31083,38.94611],"type":"Point"}
}