{
  "type": "Feature",
  "properties": {
    "gn:admin1_code":"30",
    "gn:asciiname":"Huanglouli",
    "gn:country_code":"CN",
    "gn:dem":166,
    "gn:feature_class":"P",
    "gn:feature_code":"PPL",
    "gn:name":"Huanglouli",
    "gn:population":0,
    "gn:timezone":"Asia/Shanghai",
    "iso:country":"CN",
    "name:zho_x_preferred":[
        "\u9ec4\u697c\u91cc"
    ],
    "wof:name":"Huanglouli",
    "wof:placetype":"locality"
},
  "geometry": {"coordinates":[115.52943999999999,23.63675],"type":"Point"}
}