{
  "type": "Feature",
  "properties": {
    "gn:admin1_code":"6.0",
    "gn:asciiname":"Balai",
    "gn:country_code":"CN",
    "gn:dem":3631,
    "gn:feature_class":"P",
    "gn:feature_code":"PPL",
    "gn:name":"Balai",
    "gn:population":0,
    "gn:timezone":"Asia/Urumqi",
    "iso:country":"CN",
    "name:mar_x_preferred":[
        "\u092c\u0932\u093e\u0908"
    ],
    "name:zho_x_preferred":[
        "\u5df4\u83b1"
    ],
    "wof:name":"Balai",
    "wof:placetype":"locality"
},
  "geometry": {"coordinates":[97.0577,33.17332],"type":"Point"}
}