{
  "type": "Feature",
  "properties": {
    "gn:admin1_code":"32.0",
    "gn:asciiname":"Hejiawan",
    "gn:country_code":"CN",
    "gn:dem":571,
    "gn:feature_class":"P",
    "gn:feature_code":"PPL",
    "gn:name":"Hejiawan",
    "gn:population":0,
    "gn:timezone":"Asia/Shanghai",
    "iso:country":"CN",
    "name:zho_x_preferred":[
        "\u4f55\u5bb6\u6e7e"
    ],
    "wof:name":"Hejiawan",
    "wof:placetype":"locality"
},
  "geometry": {"coordinates":[104.41500000000001,31.4167],"type":"Point"}
}