{
  "type": "Feature",
  "properties": {
    "gn:admin1_code":"5.0",
    "gn:asciiname":"Xinjian",
    "gn:country_code":"CN",
    "gn:dem":396,
    "gn:feature_class":"P",
    "gn:feature_code":"PPL",
    "gn:name":"Xinjian",
    "gn:population":0,
    "gn:timezone":"Asia/Shanghai",
    "iso:country":"CN",
    "name:ceb_x_preferred":[
        "Xinjian"
    ],
    "name:deu_x_preferred":[
        "Xinjian"
    ],
    "name:und_x_variant":[
        "\u65b0\u5efa"
    ],
    "wof:name":"Xinjian",
    "wof:placetype":"locality"
},
  "geometry": {"coordinates":[125.66507,41.31219],"type":"Point"}
}