{
  "type": "Feature",
  "properties": {
    "gn:admin1_code":"31.0",
    "gn:asciiname":"Tufuwan",
    "gn:country_code":"CN",
    "gn:dem":10,
    "gn:feature_class":"P",
    "gn:feature_code":"PPL",
    "gn:name":"Tufuwan",
    "gn:population":0,
    "gn:timezone":"Asia/Shanghai",
    "iso:country":"CN",
    "name:zho_x_preferred":[
        "\u571f\u798f\u6e7e"
    ],
    "wof:name":"Tufuwan",
    "wof:placetype":"locality"
},
  "geometry": {"coordinates":[109.78885,18.40347],"type":"Point"}
}