{
  "type": "Feature",
  "properties": {
    "gn:admin1_code":"19.0",
    "gn:asciiname":"Majia Goushang",
    "gn:country_code":"CN",
    "gn:dem":332,
    "gn:feature_class":"P",
    "gn:feature_code":"PPL",
    "gn:name":"Majia Goushang",
    "gn:population":0,
    "gn:timezone":"Asia/Shanghai",
    "iso:country":"CN",
    "name:und_x_variant":[
        "\u9a6c\u5bb6\u6c9f\u4e0a"
    ],
    "wof:name":"Majia Goushang",
    "wof:placetype":"locality"
},
  "geometry": {"coordinates":[123.30976,40.71463],"type":"Point"}
}