{
  "type": "Feature",
  "properties": {
    "gn:admin1_code":"3.0",
    "gn:asciiname":"Zhenshang Hongjia",
    "gn:country_code":"CN",
    "gn:dem":51,
    "gn:feature_class":"P",
    "gn:feature_code":"PPL",
    "gn:name":"Zhenshang Hongjia",
    "gn:population":0,
    "gn:timezone":"Asia/Shanghai",
    "iso:country":"CN",
    "name:und_x_variant":[
        "\u5733\u4e0a\u6d2a\u5bb6"
    ],
    "wof:name":"Zhenshang Hongjia",
    "wof:placetype":"locality"
},
  "geometry": {"coordinates":[116.39585,28.06639],"type":"Point"}
}