{
  "type": "Feature",
  "properties": {
    "gn:admin1_code":"29.0",
    "gn:asciiname":"Changpoling",
    "gn:country_code":"CN",
    "gn:dem":1860,
    "gn:feature_class":"P",
    "gn:feature_code":"PPL",
    "gn:name":"Changpoling",
    "gn:population":0,
    "gn:timezone":"Asia/Shanghai",
    "iso:country":"CN",
    "name:zho_x_preferred":[
        "\u957f\u5761\u5cad"
    ],
    "wof:name":"Changpoling",
    "wof:placetype":"locality"
},
  "geometry": {"coordinates":[100.51900000000001,26.3726],"type":"Point"}
}