{
  "type": "Feature",
  "properties": {
    "gn:admin1_code":"9",
    "gn:asciiname":"Simaji",
    "gn:country_code":"CN",
    "gn:dem":65,
    "gn:feature_class":"P",
    "gn:feature_code":"PPL",
    "gn:name":"Simaji",
    "gn:population":0,
    "gn:timezone":"Asia/Shanghai",
    "iso:country":"CN",
    "name:zho_x_preferred":[
        "\u53f8\u9a6c\u96c6"
    ],
    "wof:name":"Simaji",
    "wof:placetype":"locality"
},
  "geometry": {"coordinates":[115.07104,35.41921],"type":"Point"}
}