{
  "type": "Feature",
  "properties": {
    "gn:admin1_code":"9.0",
    "gn:asciiname":"Hengpocun",
    "gn:country_code":"CN",
    "gn:dem":68,
    "gn:feature_class":"P",
    "gn:feature_code":"PPL",
    "gn:name":"Hengpocun",
    "gn:population":0,
    "gn:timezone":"Asia/Shanghai",
    "iso:country":"CN",
    "name:und_x_variant":[
        "\u8861\u5761\u6751"
    ],
    "name:zho_x_preferred":[
        "\u8861\u5761\u6751"
    ],
    "wof:name":"Hengpocun",
    "wof:placetype":"locality"
},
  "geometry": {"coordinates":[113.93481,33.32096],"type":"Point"}
}