{
  "type": "Feature",
  "properties": {
    "gn:admin1_code":"23.0",
    "gn:asciiname":"Mindong",
    "gn:country_code":"CN",
    "gn:dem":2,
    "gn:feature_class":"P",
    "gn:feature_code":"PPL",
    "gn:name":"Mindong",
    "gn:population":0,
    "gn:timezone":"Asia/Shanghai",
    "iso:country":"CN",
    "name:zho_x_preferred":[
        "Mindong"
    ],
    "name:zho_x_variant":[
        "\u6c11\u4e1c"
    ],
    "wof:name":"Mindong",
    "wof:placetype":"locality"
},
  "geometry": {"coordinates":[121.85198,31.3572],"type":"Point"}
}