{
  "type": "Feature",
  "properties": {
    "gn:admin1_code":"32.0",
    "gn:asciiname":"Waba",
    "gn:country_code":"CN",
    "gn:dem":3592,
    "gn:feature_class":"P",
    "gn:feature_code":"PPL",
    "gn:name":"Waba",
    "gn:population":0,
    "gn:timezone":"Asia/Shanghai",
    "iso:country":"CN",
    "name:zho_x_preferred":[
        "\u5a03\u5df4"
    ],
    "wof:name":"Waba",
    "wof:placetype":"locality"
},
  "geometry": {"coordinates":[99.47150000000001,32.0894],"type":"Point"}
}