{
  "type": "Feature",
  "properties": {
    "gn:admin1_code":"14.0",
    "gn:asciiname":"Zharengencai",
    "gn:country_code":"CN",
    "gn:dem":4810,
    "gn:feature_class":"P",
    "gn:feature_code":"PPL",
    "gn:name":"Zharengencai",
    "gn:population":0,
    "gn:timezone":"Asia/Urumqi",
    "iso:country":"CN",
    "name:zho_x_preferred":[
        "\u624e\u4ec1\u6839\u624d"
    ],
    "wof:name":"Zharengencai",
    "wof:placetype":"locality"
},
  "geometry": {"coordinates":[94.37090000000001,32.47232],"type":"Point"}
}