{
  "type": "Feature",
  "properties": {
    "gn:admin1_code":"1.0",
    "gn:asciiname":"Daliucun",
    "gn:country_code":"CN",
    "gn:dem":54,
    "gn:feature_class":"P",
    "gn:feature_code":"PPL",
    "gn:name":"Daliucun",
    "gn:population":0,
    "gn:timezone":"Asia/Shanghai",
    "iso:country":"CN",
    "name:zho_x_preferred":[
        "\u5927\u5218\u6751"
    ],
    "wof:name":"Daliucun",
    "wof:placetype":"locality"
},
  "geometry": {"coordinates":[117.25833,32.31847],"type":"Point"}
}