{
  "type": "Feature",
  "properties": {
    "gn:admin1_code":"29.0",
    "gn:asciiname":"Wamaizuo",
    "gn:country_code":"CN",
    "gn:dem":1688,
    "gn:feature_class":"P",
    "gn:feature_code":"PPL",
    "gn:name":"Wamaizuo",
    "gn:population":0,
    "gn:timezone":"Asia/Shanghai",
    "iso:country":"CN",
    "name:zho_x_preferred":[
        "\u74e6\u8109\u4f50"
    ],
    "wof:name":"Wamaizuo",
    "wof:placetype":"locality"
},
  "geometry": {"coordinates":[100.167,25.0072],"type":"Point"}
}