{
  "type": "Feature",
  "properties": {
    "gn:admin1_code":"18",
    "gn:asciiname":"Houtai",
    "gn:country_code":"CN",
    "gn:dem":723,
    "gn:feature_class":"P",
    "gn:feature_code":"PPL",
    "gn:name":"Houtai",
    "gn:population":0,
    "gn:timezone":"Asia/Shanghai",
    "iso:country":"CN",
    "name:zho_x_preferred":[
        "\u540e\u53f0"
    ],
    "wof:name":"Houtai",
    "wof:placetype":"locality"
},
  "geometry": {"coordinates":[106.84399999999999,28.7715],"type":"Point"}
}