{
  "type": "Feature",
  "properties": {
    "gn:admin1_code":"32.0",
    "gn:asciiname":"Chunyaping",
    "gn:country_code":"CN",
    "gn:dem":1637,
    "gn:feature_class":"P",
    "gn:feature_code":"PPL",
    "gn:name":"Chunyaping",
    "gn:population":0,
    "gn:timezone":"Asia/Shanghai",
    "iso:country":"CN",
    "name:zho_x_preferred":[
        "\u6625\u82bd\u576a"
    ],
    "wof:name":"Chunyaping",
    "wof:placetype":"locality"
},
  "geometry": {"coordinates":[103.742,31.229],"type":"Point"}
}