{
  "type": "Feature",
  "properties": {
    "gn:admin1_code":"25",
    "gn:asciiname":"Dagaozhuang",
    "gn:country_code":"CN",
    "gn:dem":44,
    "gn:feature_class":"P",
    "gn:feature_code":"PPL",
    "gn:name":"Dagaozhuang",
    "gn:population":0,
    "gn:timezone":"Asia/Shanghai",
    "iso:country":"CN",
    "name:zho_x_preferred":[
        "\u5927\u9ad8\u5e84"
    ],
    "wof:name":"Dagaozhuang",
    "wof:placetype":"locality"
},
  "geometry": {"coordinates":[116.02800000000001,35.4974],"type":"Point"}
}