{
  "type": "Feature",
  "properties": {
    "gn:admin1_code":"12",
    "gn:asciiname":"Qingtaiping",
    "gn:country_code":"CN",
    "gn:dem":1143,
    "gn:feature_class":"P",
    "gn:feature_code":"PPLA4",
    "gn:name":"Qingtaiping",
    "gn:population":0,
    "gn:timezone":"Asia/Shanghai",
    "iso:country":"CN",
    "name:und_x_variant":[
        "Ch\u2019ing-t\u2019ai-p\u2019ing",
        "Qingtaiping",
        "Qingtaiping Zhen"
    ],
    "name:zho_x_preferred":[
        "\u6e05\u592a\u576a"
    ],
    "name:zho_x_variant":[
        "\u6e05\u592a\u576a\u9547"
    ],
    "wof:name":"Qingtaiping",
    "wof:placetype":"locality"
},
  "geometry": {"coordinates":[110.21720000000001,30.48335],"type":"Point"}
}