{
  "type": "Feature",
  "properties": {
    "gn:admin1_code":"19.0",
    "gn:asciiname":"Nanguan",
    "gn:country_code":"CN",
    "gn:dem":153,
    "gn:feature_class":"P",
    "gn:feature_code":"PPL",
    "gn:name":"Nanguan",
    "gn:population":0,
    "gn:timezone":"Asia/Shanghai",
    "iso:country":"CN",
    "name:ceb_x_preferred":[
        "Nanguan"
    ],
    "name:deu_x_preferred":[
        "Nanguan"
    ],
    "name:fra_x_preferred":[
        "Nanguan"
    ],
    "name:zho_x_preferred":[
        "\u5357\u5173"
    ],
    "wof:name":"Nanguan",
    "wof:placetype":"locality"
},
  "geometry": {"coordinates":[120.55013999999998,41.3114],"type":"Point"}
}