{
  "type": "Feature",
  "properties": {
    "gn:admin1_code":"5.0",
    "gn:asciiname":"Xiangfanggoucun",
    "gn:country_code":"CN",
    "gn:dem":476,
    "gn:feature_class":"P",
    "gn:feature_code":"PPL",
    "gn:name":"Xiangfanggoucun",
    "gn:population":0,
    "gn:timezone":"Asia/Shanghai",
    "iso:country":"CN",
    "name:zho_x_preferred":[
        "\u9999\u623f\u6c9f\u6751"
    ],
    "wof:name":"Xiangfanggoucun",
    "wof:placetype":"locality"
},
  "geometry": {"coordinates":[128.56533000000002,43.58024],"type":"Point"}
}