{
  "type": "Feature",
  "properties": {
    "gn:admin1_code":"18.0",
    "gn:asciiname":"Ganlongtian",
    "gn:country_code":"CN",
    "gn:dem":631,
    "gn:feature_class":"P",
    "gn:feature_code":"PPL",
    "gn:name":"Ganlongtian",
    "gn:population":0,
    "gn:timezone":"Asia/Shanghai",
    "iso:country":"CN",
    "name:zho_x_preferred":[
        "\u7518\u9f99\u7530"
    ],
    "wof:name":"Ganlongtian",
    "wof:placetype":"locality"
},
  "geometry": {"coordinates":[108.85599999999999,27.4894],"type":"Point"}
}