{
  "type": "Feature",
  "properties": {
    "gn:admin1_code":"13",
    "gn:asciiname":"Bugedayili Kejianggale",
    "gn:country_code":"CN",
    "gn:dem":1202,
    "gn:feature_class":"P",
    "gn:feature_code":"PPL",
    "gn:name":"Bugedayili Kejianggale",
    "gn:population":0,
    "gn:timezone":"Asia/Shanghai",
    "iso:country":"CN",
    "name:zho_x_preferred":[
        "\u5e03\u683c\u8fbe\u4f9d\u91cc\u514b\u6c5f\u5c15\u52d2"
    ],
    "wof:name":"Bugedayili Kejianggale",
    "wof:placetype":"locality"
},
  "geometry": {"coordinates":[76.76175000000001,39.04796],"type":"Point"}
}