{
  "type": "Feature",
  "properties": {
    "gn:admin1_code":"30.0",
    "gn:asciiname":"Yangzitang",
    "gn:country_code":"CN",
    "gn:dem":207,
    "gn:feature_class":"P",
    "gn:feature_code":"PPL",
    "gn:name":"Yangzitang",
    "gn:population":0,
    "gn:timezone":"Asia/Shanghai",
    "iso:country":"CN",
    "name:zho_x_preferred":[
        "\u7f8a\u5b50\u5858"
    ],
    "wof:name":"Yangzitang",
    "wof:placetype":"locality"
},
  "geometry": {"coordinates":[113.67476000000001,23.73642000000001],"type":"Point"}
}