{
  "type": "Feature",
  "properties": {
    "gn:admin1_code":"15.0",
    "gn:asciiname":"Danjiagou",
    "gn:country_code":"CN",
    "gn:dem":1360,
    "gn:feature_class":"P",
    "gn:feature_code":"PPL",
    "gn:name":"Danjiagou",
    "gn:population":0,
    "gn:timezone":"Asia/Shanghai",
    "iso:country":"CN",
    "name:und_x_variant":[
        "\u5355\u5bb6\u6c9f"
    ],
    "wof:name":"Danjiagou",
    "wof:placetype":"locality"
},
  "geometry": {"coordinates":[105.59434,33.78669],"type":"Point"}
}