{
  "type": "Feature",
  "properties": {
    "gn:admin1_code":"29",
    "gn:asciiname":"Batang",
    "gn:country_code":"CN",
    "gn:dem":1437,
    "gn:feature_class":"P",
    "gn:feature_code":"PPL",
    "gn:name":"Batang",
    "gn:population":0,
    "gn:timezone":"Asia/Shanghai",
    "iso:country":"CN",
    "name:ceb_x_preferred":[
        "Batang"
    ],
    "name:deu_x_preferred":[
        "Batang"
    ],
    "name:fra_x_preferred":[
        "Batang"
    ],
    "name:jpn_x_preferred":[
        "\u30d0\u30bf\u30f3"
    ],
    "name:mlg_x_preferred":[
        "Batang"
    ],
    "name:nld_x_preferred":[
        "Batang"
    ],
    "name:nor_x_preferred":[
        "Batang"
    ],
    "name:sun_x_preferred":[
        "Batang"
    ],
    "name:swe_x_preferred":[
        "Batang"
    ],
    "name:zho_x_preferred":[
        "\u516b\u6c64"
    ],
    "wof:name":"Batang",
    "wof:placetype":"locality"
},
  "geometry": {"coordinates":[105.086,23.8747],"type":"Point"}
}