{
  "type": "Feature",
  "properties": {
    "gn:admin1_code":"08",
    "gn:asciiname":"Zhonghe",
    "gn:country_code":"CN",
    "gn:dem":155,
    "gn:feature_class":"P",
    "gn:feature_code":"PPLA4",
    "gn:name":"Zhonghe",
    "gn:population":0,
    "gn:timezone":"Asia/Shanghai",
    "iso:country":"CN",
    "name:ceb_x_preferred":[
        "Zhonghe"
    ],
    "name:deu_x_preferred":[
        "Zhonghe"
    ],
    "name:swe_x_preferred":[
        "Zhonghe"
    ],
    "name:und_x_variant":[
        "Chung-ho",
        "Zhonghe",
        "Zhonghe Zhen"
    ],
    "name:zho_x_preferred":[
        "\u4e2d\u548c"
    ],
    "name:zho_x_variant":[
        "\u4e2d\u548c\u9547"
    ],
    "wof:name":"Zhonghe",
    "wof:placetype":"locality"
},
  "geometry": {"coordinates":[128.77168999999998,45.50523],"type":"Point"}
}