{
  "type": "Feature",
  "properties": {
    "gn:admin1_code":"29.0",
    "gn:asciiname":"Dalubian",
    "gn:country_code":"CN",
    "gn:dem":1911,
    "gn:feature_class":"P",
    "gn:feature_code":"PPL",
    "gn:name":"Dalubian",
    "gn:population":0,
    "gn:timezone":"Asia/Shanghai",
    "iso:country":"CN",
    "name:zho_x_preferred":[
        "\u5927\u8def\u8fb9"
    ],
    "wof:name":"Dalubian",
    "wof:placetype":"locality"
},
  "geometry": {"coordinates":[104.295,26.178],"type":"Point"}
}