{
  "type": "Feature",
  "properties": {
    "gn:admin1_code":"15.0",
    "gn:asciiname":"Miaobei Houcun",
    "gn:country_code":"CN",
    "gn:dem":1775,
    "gn:feature_class":"P",
    "gn:feature_code":"PPL",
    "gn:name":"Miaobei Houcun",
    "gn:population":0,
    "gn:timezone":"Asia/Shanghai",
    "iso:country":"CN",
    "name:zho_x_preferred":[
        "\u5e99\u80cc\u540e\u6751"
    ],
    "wof:name":"Miaobei Houcun",
    "wof:placetype":"locality"
},
  "geometry": {"coordinates":[104.696,33.0038],"type":"Point"}
}