{
  "type": "Feature",
  "properties": {
    "gn:admin1_code":"18",
    "gn:asciiname":"Mentouya",
    "gn:country_code":"CN",
    "gn:dem":1017,
    "gn:feature_class":"P",
    "gn:feature_code":"PPL",
    "gn:name":"Mentouya",
    "gn:population":0,
    "gn:timezone":"Asia/Shanghai",
    "iso:country":"CN",
    "name:zho_x_preferred":[
        "\u95f7\u5934\u4e2b"
    ],
    "wof:name":"Mentouya",
    "wof:placetype":"locality"
},
  "geometry": {"coordinates":[107.301,27.5741],"type":"Point"}
}