{
  "type": "Feature",
  "properties": {
    "gn:admin1_code":"20",
    "gn:asciiname":"Hsia-chu-ts'ai-kou",
    "gn:country_code":"CN",
    "gn:dem":645,
    "gn:feature_class":"P",
    "gn:feature_code":"PPL",
    "gn:name":"Hsia-chu-ts\u2019ai-kou",
    "gn:population":0,
    "gn:timezone":"Asia/Shanghai",
    "iso:country":"CN",
    "wof:name":"Hsia-chu-ts'ai-kou",
    "wof:placetype":"locality"
},
  "geometry": {"coordinates":[119.26833000000001,42.76917],"type":"Point"}
}