{
  "type": "Feature",
  "properties": {
    "gn:admin1_code":"7",
    "gn:asciiname":"Dongzaiwei",
    "gn:country_code":"CN",
    "gn:dem":255,
    "gn:feature_class":"P",
    "gn:feature_code":"PPL",
    "gn:name":"Dongzaiwei",
    "gn:population":0,
    "gn:timezone":"Asia/Shanghai",
    "iso:country":"CN",
    "name:zho_x_preferred":[
        "\u6d1e\u4ed4\u5c3e"
    ],
    "wof:name":"Dongzaiwei",
    "wof:placetype":"locality"
},
  "geometry": {"coordinates":[117.455,24.37385],"type":"Point"}
}