{
  "type": "Feature",
  "properties": {
    "gn:admin1_code":"9.0",
    "gn:asciiname":"Zhulinzui",
    "gn:country_code":"CN",
    "gn:dem":87,
    "gn:feature_class":"P",
    "gn:feature_code":"PPL",
    "gn:name":"Zhulinzui",
    "gn:population":0,
    "gn:timezone":"Asia/Shanghai",
    "iso:country":"CN",
    "name:zho_x_preferred":[
        "\u7af9\u6797\u5480"
    ],
    "wof:name":"Zhulinzui",
    "wof:placetype":"locality"
},
  "geometry": {"coordinates":[114.87888999999998,31.64235],"type":"Point"}
}