{
  "type": "Feature",
  "properties": {
    "gn:admin1_code":"30",
    "gn:asciiname":"Liwu",
    "gn:country_code":"CN",
    "gn:dem":8,
    "gn:feature_class":"P",
    "gn:feature_code":"PPL",
    "gn:name":"Liwu",
    "gn:population":0,
    "gn:timezone":"Asia/Urumqi",
    "iso:country":"CN",
    "name:zho_x_preferred":[
        "\u674e\u5c4b"
    ],
    "wof:name":"Liwu",
    "wof:placetype":"locality"
},
  "geometry": {"coordinates":[110.70346000000001,21.38098],"type":"Point"}
}