{
  "type": "Feature",
  "properties": {
    "gn:admin1_code":"26.0",
    "gn:asciiname":"Zhaiziwan",
    "gn:country_code":"CN",
    "gn:dem":1501,
    "gn:feature_class":"P",
    "gn:feature_code":"PPL",
    "gn:name":"Zhaiziwan",
    "gn:population":0,
    "gn:timezone":"Asia/Shanghai",
    "iso:country":"CN",
    "name:zho_x_preferred":[
        "\u5be8\u5b50\u6e7e"
    ],
    "wof:name":"Zhaiziwan",
    "wof:placetype":"locality"
},
  "geometry": {"coordinates":[110.11373,35.71632],"type":"Point"}
}