{
  "type": "Feature",
  "properties": {
    "gn:admin1_code":"32.0",
    "gn:asciiname":"Qie'erma",
    "gn:country_code":"CN",
    "gn:dem":2529,
    "gn:feature_class":"P",
    "gn:feature_code":"PPL",
    "gn:name":"Qie\u2019erma",
    "gn:population":0,
    "gn:timezone":"Asia/Shanghai",
    "iso:country":"CN",
    "name:und_x_variant":[
        "Qie\u2019erma"
    ],
    "name:zho_x_preferred":[
        "\u4e14\u5c14\u739b"
    ],
    "wof:name":"Qie'erma",
    "wof:placetype":"locality"
},
  "geometry": {"coordinates":[101.946,31.7906],"type":"Point"}
}