{
  "type": "Feature",
  "properties": {
    "gn:admin1_code":"22.0",
    "gn:asciiname":"Tumencun",
    "gn:country_code":"CN",
    "gn:dem":88,
    "gn:feature_class":"P",
    "gn:feature_code":"PPL",
    "gn:name":"Tumencun",
    "gn:population":0,
    "gn:timezone":"Asia/Shanghai",
    "iso:country":"CN",
    "name:zho_x_preferred":[
        "\u571f\u95e8\u6751"
    ],
    "wof:name":"Tumencun",
    "wof:placetype":"locality"
},
  "geometry": {"coordinates":[117.26347,40.18868],"type":"Point"}
}