{
  "type": "Feature",
  "properties": {
    "iso:country":"CN",
    "name:cym_x_preferred":[
        "Ardal Wujin"
    ],
    "name:deu_x_preferred":[
        "Wujin"
    ],
    "name:eng_x_preferred":[
        "Wujin District"
    ],
    "name:fas_x_preferred":[
        "\u0628\u062e\u0634 \u0648\u0648\u062c\u06cc\u0646"
    ],
    "name:gan_x_preferred":[
        "\u6b66\u8fdb\u533a"
    ],
    "name:heb_x_preferred":[
        "\u05d7\u05d5\u05d0\u05d5 \u05d9\u05d5\u05e0\u05d3\u05d4"
    ],
    "name:jpn_x_preferred":[
        "\u6b66\u9032\u533a"
    ],
    "name:kor_x_preferred":[
        "\uc6b0\uc9c4\uad6c"
    ],
    "name:nan_x_preferred":[
        "B\u00fa-ch\u00ecn-khu"
    ],
    "name:nld_x_preferred":[
        "Wujin"
    ],
    "name:nob_x_preferred":[
        "Wujin"
    ],
    "name:rus_x_preferred":[
        "\u0423\u0446\u0437\u0438\u043d\u044c"
    ],
    "name:swe_x_preferred":[
        "Wujin"
    ],
    "name:urd_x_preferred":[
        "\u0648\u0648\u062c\u06cc\u0646 \u0636\u0644\u0639"
    ],
    "name:vie_x_preferred":[
        "V\u0169 Ti\u1ebfn"
    ],
    "name:wuu_x_preferred":[
        "\u6b66\u9032\u5340"
    ],
    "name:yue_x_preferred":[
        "\u6b66\u9032\u5340"
    ],
    "name:zho_x_preferred":[
        "\u6b66\u8fdb\u533a"
    ],
    "qs:name":"\u6b66\u8fdb\u533a",
    "qs:name_adm0":"\u4e2d\u570b",
    "qs:name_adm1":"\u6c5f\u82cf\u7701",
    "qs:photos":395,
    "qs:photos_1k":80,
    "qs:photos_9k":2,
    "qs:photos_9r":5,
    "qs:photos_all":395,
    "qs:photos_sr":6,
    "qs:placetype":"LocalAdmin",
    "qs:pop_sr":"0",
    "wd:wordcount":360,
    "wof:name":"\u6b66\u8fdb\u533a",
    "wof:placetype":"localadmin"
},
  "geometry": {"coordinates":[119.93671399999999,31.754736],"type":"Point"}
}