{
  "type": "Feature",
  "properties": {
    "iso:country":"CN",
    "qs:name":"\u6b66\u8fdb\u533a",
    "qs:name_adm0":"\u4e2d\u570b",
    "qs:name_adm1":"\u6c5f\u82cf\u7701",
    "qs:photos":395,
    "qs:photos_1k":80,
    "qs:photos_9k":2,
    "qs:photos_9r":5,
    "qs:photos_all":395,
    "qs:photos_sr":6,
    "qs:placetype":"LocalAdmin",
    "qs:pop_sr":"0",
    "wd:wordcount":360,
    "wof:name":"\u6b66\u8fdb\u533a",
    "wof:placetype":"localadmin"
},
  "geometry": {"coordinates":[119.93671399999999,31.754736],"type":"Point"}
}