{
  "type": "Feature",
  "properties": {
    "gn:admin1_code":"32",
    "gn:asciiname":"Dafeng",
    "gn:country_code":"CN",
    "gn:dem":389,
    "gn:feature_class":"P",
    "gn:feature_code":"PPL",
    "gn:name":"Dafeng",
    "gn:population":0,
    "gn:timezone":"Asia/Shanghai",
    "iso:country":"CN",
    "name:zho_x_preferred":[
        "\u5927\u98ce"
    ],
    "wof:name":"Dafeng",
    "wof:placetype":"locality"
},
  "geometry": {"coordinates":[107.65763,31.0645],"type":"Point"}
}