{
  "type": "Feature",
  "properties": {
    "gn:country":"CN",
    "gn:fcode":"PPL",
    "gn:population":2950,
    "iso:country":"CN",
    "name:und_x_variant":[
        "\u5218\u4e94\u5e97"
    ],
    "qs:name":"Liuwudian",
    "qs:photos_9r":0,
    "qs:photos_sr":0,
    "qs:pop_sr":"4",
    "wof:name":"Liuwudian",
    "wof:placetype":"locality",
    "wof:population":2950
},
  "geometry": {"coordinates":[118.19558000000001,24.55552],"type":"Point"}
}