{
  "type": "Feature",
  "properties": {
    "gn:admin1_code":"12.0",
    "gn:asciiname":"Yangjiachang",
    "gn:country_code":"CN",
    "gn:dem":45,
    "gn:feature_class":"P",
    "gn:feature_code":"PPL",
    "gn:name":"Yangjiachang",
    "gn:population":0,
    "gn:timezone":"Asia/Shanghai",
    "iso:country":"CN",
    "name:zho_x_preferred":[
        "Yangjiachang"
    ],
    "name:zho_x_variant":[
        "\u6768\u5bb6\u573a"
    ],
    "wof:name":"Yangjiachang",
    "wof:placetype":"locality"
},
  "geometry": {"coordinates":[111.76121999999999,30.37626],"type":"Point"}
}