{
  "type": "Feature",
  "properties": {
    "gn:admin1_code":"21.0",
    "gn:asciiname":"Wujianao",
    "gn:country_code":"CN",
    "gn:dem":1235,
    "gn:feature_class":"P",
    "gn:feature_code":"PPL",
    "gn:name":"Wujianao",
    "gn:population":0,
    "gn:timezone":"Asia/Shanghai",
    "iso:country":"CN",
    "name:zho_x_preferred":[
        "\u5434\u5bb6\u8111"
    ],
    "wof:name":"Wujianao",
    "wof:placetype":"locality"
},
  "geometry": {"coordinates":[105.119,37.4922],"type":"Point"}
}