{
  "type": "Feature",
  "properties": {
    "gn:admin1_code":"26.0",
    "gn:asciiname":"Gongjia Yuanzi",
    "gn:country_code":"CN",
    "gn:dem":1614,
    "gn:feature_class":"P",
    "gn:feature_code":"PPL",
    "gn:name":"Gongjia Yuanzi",
    "gn:population":0,
    "gn:timezone":"Asia/Shanghai",
    "iso:country":"CN",
    "name:zho_x_preferred":[
        "\u9f9a\u5bb6\u9662\u5b50"
    ],
    "wof:name":"Gongjia Yuanzi",
    "wof:placetype":"locality"
},
  "geometry": {"coordinates":[109.39451,33.85626],"type":"Point"}
}