{
  "type": "Feature",
  "properties": {
    "gn:admin1_code":"4.0",
    "gn:asciiname":"Qibucun",
    "gn:country_code":"CN",
    "gn:dem":0,
    "gn:feature_class":"P",
    "gn:feature_code":"PPL",
    "gn:name":"Qibucun",
    "gn:population":0,
    "gn:timezone":"Asia/Shanghai",
    "iso:country":"CN",
    "name:zho_x_preferred":[
        "\u4e03\u57e0\u6751"
    ],
    "wof:name":"Qibucun",
    "wof:placetype":"locality"
},
  "geometry": {"coordinates":[120.1131,33.7085],"type":"Point"}
}