{
  "type": "Feature",
  "properties": {
    "gn:admin1_code":"02",
    "gn:asciiname":"Huangpu",
    "gn:country_code":"CN",
    "gn:dem":13,
    "gn:feature_class":"P",
    "gn:feature_code":"PPL",
    "gn:name":"Huangpu",
    "gn:population":0,
    "gn:timezone":"Asia/Shanghai",
    "iso:country":"CN",
    "name:und_x_variant":[
        "Huang-p\u2019u-chuang",
        "Huangpuzhuang",
        "Huangpu",
        "\u7687\u6d66"
    ],
    "wof:name":"Huangpu",
    "wof:placetype":"locality"
},
  "geometry": {"coordinates":[120.70657,30.04219],"type":"Point"}
}