{
  "type": "Feature",
  "properties": {
    "gn:admin1_code":"02",
    "gn:asciiname":"Huangpu",
    "gn:country_code":"CN",
    "gn:dem":13,
    "gn:feature_class":"P",
    "gn:feature_code":"PPL",
    "gn:name":"Huangpu",
    "gn:population":0,
    "gn:timezone":"Asia/Shanghai",
    "iso:country":"CN",
    "name:ceb_x_preferred":[
        "Huangpu"
    ],
    "name:deu_x_preferred":[
        "Huangpu"
    ],
    "name:eus_x_preferred":[
        "Huangpu"
    ],
    "name:fra_x_preferred":[
        "Huangpu"
    ],
    "name:kor_x_preferred":[
        "\ud669\ud478\uad6c"
    ],
    "name:nor_x_preferred":[
        "Huangpu"
    ],
    "name:pol_x_preferred":[
        "Huangpu"
    ],
    "name:ron_x_preferred":[
        "Huangpu"
    ],
    "name:swe_x_preferred":[
        "Huangpu"
    ],
    "name:und_x_variant":[
        "Huang-p\u2019u-chuang",
        "Huangpuzhuang",
        "\u7687\u6d66"
    ],
    "name:vie_x_preferred":[
        "Ho\u00e0ng Ph\u1ed1"
    ],
    "wof:name":"Huangpu",
    "wof:placetype":"locality"
},
  "geometry": {"coordinates":[120.70657,30.04219],"type":"Point"}
}