{
  "type": "Feature",
  "properties": {
    "gn:admin1_code":"19.0",
    "gn:asciiname":"Xiaogaizhoucun",
    "gn:country_code":"CN",
    "gn:dem":98,
    "gn:feature_class":"P",
    "gn:feature_code":"PPL",
    "gn:name":"Xiaogaizhoucun",
    "gn:population":0,
    "gn:timezone":"Asia/Shanghai",
    "iso:country":"CN",
    "name:zho_x_preferred":[
        "\u5c0f\u76d6\u5dde\u6751"
    ],
    "wof:name":"Xiaogaizhoucun",
    "wof:placetype":"locality"
},
  "geometry": {"coordinates":[120.70999999999999,40.7525],"type":"Point"}
}