{
  "type": "Feature",
  "properties": {
    "gn:admin1_code":"7",
    "gn:asciiname":"Guiyangtou",
    "gn:country_code":"CN",
    "gn:dem":804,
    "gn:feature_class":"P",
    "gn:feature_code":"PPL",
    "gn:name":"Guiyangtou",
    "gn:population":0,
    "gn:timezone":"Asia/Shanghai",
    "iso:country":"CN",
    "name:und_x_variant":[
        "\u9f9f\u6d0b\u5934"
    ],
    "wof:name":"Guiyangtou",
    "wof:placetype":"locality"
},
  "geometry": {"coordinates":[119.96972,27.13694000000001],"type":"Point"}
}