{
  "type": "Feature",
  "properties": {
    "gn:admin1_code":"30.0",
    "gn:asciiname":"Youcaotang",
    "gn:country_code":"CN",
    "gn:dem":205,
    "gn:feature_class":"P",
    "gn:feature_code":"PPL",
    "gn:name":"Youcaotang",
    "gn:population":0,
    "gn:timezone":"Asia/Shanghai",
    "iso:country":"CN",
    "name:zho_x_preferred":[
        "Youcaotang"
    ],
    "name:zho_x_variant":[
        "\u6cb9\u8349\u5858"
    ],
    "wof:name":"Youcaotang",
    "wof:placetype":"locality"
},
  "geometry": {"coordinates":[114.96639,24.40222],"type":"Point"}
}