{
  "type": "Feature",
  "properties": {
    "gn:admin1_code":"16.0",
    "gn:asciiname":"Na'ao",
    "gn:country_code":"CN",
    "gn:dem":173,
    "gn:feature_class":"P",
    "gn:feature_code":"PPL",
    "gn:name":"Na\u2019ao",
    "gn:population":0,
    "gn:timezone":"Asia/Shanghai",
    "iso:country":"CN",
    "name:und_x_variant":[
        "Na\u2019ao"
    ],
    "name:zho_x_preferred":[
        "\u90a3\u6556"
    ],
    "wof:name":"Na'ao",
    "wof:placetype":"locality"
},
  "geometry": {"coordinates":[107.658,23.1058],"type":"Point"}
}