{
  "type": "Feature",
  "properties": {
    "gn:admin1_code":"25",
    "gn:asciiname":"Wudikou",
    "gn:country_code":"CN",
    "gn:dem":40,
    "gn:feature_class":"P",
    "gn:feature_code":"PPL",
    "gn:name":"Wudikou",
    "gn:population":0,
    "gn:timezone":"Asia/Shanghai",
    "iso:country":"CN",
    "name:zho_x_preferred":[
        "\u6b66\u5824\u53e3"
    ],
    "wof:name":"Wudikou",
    "wof:placetype":"locality"
},
  "geometry": {"coordinates":[115.79243,36.25567],"type":"Point"}
}