{
  "type": "Feature",
  "properties": {
    "gn:admin1_code":"26.0",
    "gn:asciiname":"Yandicun",
    "gn:country_code":"CN",
    "gn:dem":1136,
    "gn:feature_class":"P",
    "gn:feature_code":"PPL",
    "gn:name":"Yandicun",
    "gn:population":0,
    "gn:timezone":"Asia/Shanghai",
    "iso:country":"CN",
    "name:zho_x_preferred":[
        "\u5ca9\u5e95\u6751"
    ],
    "wof:name":"Yandicun",
    "wof:placetype":"locality"
},
  "geometry": {"coordinates":[110.044,33.97945],"type":"Point"}
}