{
  "type": "Feature",
  "properties": {
    "gn:admin1_code":"30.0",
    "gn:asciiname":"Shikengcun",
    "gn:country_code":"CN",
    "gn:dem":152,
    "gn:feature_class":"P",
    "gn:feature_code":"PPL",
    "gn:name":"Shikengcun",
    "gn:population":0,
    "gn:timezone":"Asia/Shanghai",
    "iso:country":"CN",
    "name:zho_x_preferred":[
        "\u77f3\u5751\u6751"
    ],
    "wof:name":"Shikengcun",
    "wof:placetype":"locality"
},
  "geometry": {"coordinates":[114.38267,25.20609],"type":"Point"}
}