{
  "type": "Feature",
  "properties": {
    "gn:admin1_code":"18",
    "gn:asciiname":"Fengxiangba",
    "gn:country_code":"CN",
    "gn:dem":767,
    "gn:feature_class":"P",
    "gn:feature_code":"PPL",
    "gn:name":"Fengxiangba",
    "gn:population":0,
    "gn:timezone":"Asia/Shanghai",
    "iso:country":"CN",
    "name:zho_x_preferred":[
        "\u67ab\u9999\u575d"
    ],
    "wof:name":"Fengxiangba",
    "wof:placetype":"locality"
},
  "geometry": {"coordinates":[107.96299999999999,27.6865],"type":"Point"}
}