{
  "type": "Feature",
  "properties": {
    "gn:admin1_code":"21.0",
    "gn:asciiname":"Xinduncao",
    "gn:country_code":"CN",
    "gn:dem":1231,
    "gn:feature_class":"P",
    "gn:feature_code":"PPL",
    "gn:name":"Xinduncao",
    "gn:population":0,
    "gn:timezone":"Asia/Shanghai",
    "iso:country":"CN",
    "name:zho_x_preferred":[
        "\u65b0\u58a9\u69fd"
    ],
    "wof:name":"Xinduncao",
    "wof:placetype":"locality"
},
  "geometry": {"coordinates":[105.15300000000001,37.489],"type":"Point"}
}