{
  "type": "Feature",
  "properties": {
    "gn:admin1_code":"7.0",
    "gn:asciiname":"Tangbeike",
    "gn:country_code":"CN",
    "gn:dem":339,
    "gn:feature_class":"P",
    "gn:feature_code":"PPL",
    "gn:name":"Tangbeike",
    "gn:population":0,
    "gn:timezone":"Asia/Shanghai",
    "iso:country":"CN",
    "name:zho_x_preferred":[
        "\u5858\u80cc\u79d1"
    ],
    "wof:name":"Tangbeike",
    "wof:placetype":"locality"
},
  "geometry": {"coordinates":[116.98945000000001,24.3147],"type":"Point"}
}