{
  "type": "Feature",
  "properties": {
    "gn:admin1_code":"15",
    "gn:asciiname":"Ganjun",
    "gn:country_code":"CN",
    "gn:dem":1587,
    "gn:feature_class":"P",
    "gn:feature_code":"PPLA4",
    "gn:name":"Ganjun",
    "gn:population":0,
    "gn:timezone":"Asia/Shanghai",
    "iso:country":"CN",
    "name:und_x_variant":[
        "Ganjunpu",
        "Ganjun Zhen"
    ],
    "name:zho_x_preferred":[
        "\u7518\u6d5a"
    ],
    "name:zho_x_variant":[
        "\u7518\u6d5a\u9547"
    ],
    "wof:name":"Ganjun",
    "wof:placetype":"locality"
},
  "geometry": {"coordinates":[100.16972,38.96583],"type":"Point"}
}