{
  "type": "Feature",
  "properties": {
    "gn:admin1_code":"29.0",
    "gn:asciiname":"Dagouqiao",
    "gn:country_code":"CN",
    "gn:dem":1702,
    "gn:feature_class":"P",
    "gn:feature_code":"PPL",
    "gn:name":"Dagouqiao",
    "gn:population":0,
    "gn:timezone":"Asia/Shanghai",
    "iso:country":"CN",
    "name:zho_x_preferred":[
        "\u5927\u6c9f\u6865"
    ],
    "wof:name":"Dagouqiao",
    "wof:placetype":"locality"
},
  "geometry": {"coordinates":[98.5014,25.3145],"type":"Point"}
}