{
  "type": "Feature",
  "properties": {
    "gn:admin1_code":"15.0",
    "gn:asciiname":"Yuanpan",
    "gn:country_code":"CN",
    "gn:dem":1386,
    "gn:feature_class":"P",
    "gn:feature_code":"PPL",
    "gn:name":"Yuanpan",
    "gn:population":0,
    "gn:timezone":"Asia/Shanghai",
    "iso:country":"CN",
    "name:zho_x_preferred":[
        "\u586c\u7554"
    ],
    "wof:name":"Yuanpan",
    "wof:placetype":"locality"
},
  "geometry": {"coordinates":[107.304,35.7294],"type":"Point"}
}