{
  "type": "Feature",
  "properties": {
    "gn:admin1_code":"25",
    "gn:asciiname":"Chenjiahu",
    "gn:country_code":"CN",
    "gn:dem":60,
    "gn:feature_class":"P",
    "gn:feature_code":"PPL",
    "gn:name":"Chenjiahu",
    "gn:population":0,
    "gn:timezone":"Asia/Shanghai",
    "iso:country":"CN",
    "name:zho_x_preferred":[
        "\u9648\u5bb6\u6e56"
    ],
    "wof:name":"Chenjiahu",
    "wof:placetype":"locality"
},
  "geometry": {"coordinates":[118.47199999999999,34.9741],"type":"Point"}
}