{
  "type": "Feature",
  "properties": {
    "gn:admin1_code":"13",
    "gn:asciiname":"Sanshili",
    "gn:country_code":"CN",
    "gn:dem":468,
    "gn:feature_class":"P",
    "gn:feature_code":"PPL",
    "gn:name":"Sanshili",
    "gn:population":0,
    "gn:timezone":"Asia/Urumqi",
    "iso:country":"CN",
    "name:und_x_variant":[
        "\u4e09\u5341\u91cc"
    ],
    "wof:name":"Sanshili",
    "wof:placetype":"locality"
},
  "geometry": {"coordinates":[90.33154999999999,42.92598],"type":"Point"}
}