{
  "type": "Feature",
  "properties": {
    "gn:admin1_code":"33.0",
    "gn:asciiname":"Shangping",
    "gn:country_code":"CN",
    "gn:dem":561,
    "gn:feature_class":"P",
    "gn:feature_code":"PPL",
    "gn:name":"Shangping",
    "gn:population":0,
    "gn:timezone":"Asia/Shanghai",
    "iso:country":"CN",
    "name:zho_x_preferred":[
        "\u4e0a\u576a"
    ],
    "wof:name":"Shangping",
    "wof:placetype":"locality"
},
  "geometry": {"coordinates":[107.85133,30.2278],"type":"Point"}
}