{
  "type": "Feature",
  "properties": {
    "gn:admin1_code":"4.0",
    "gn:asciiname":"Aishan Xicun",
    "gn:country_code":"CN",
    "gn:dem":35,
    "gn:feature_class":"P",
    "gn:feature_code":"PPL",
    "gn:name":"Aishan Xicun",
    "gn:population":0,
    "gn:timezone":"Asia/Shanghai",
    "iso:country":"CN",
    "name:zho_x_preferred":[
        "\u827e\u5c71\u897f\u6751"
    ],
    "wof:name":"Aishan Xicun",
    "wof:placetype":"locality"
},
  "geometry": {"coordinates":[117.94971,34.51709],"type":"Point"}
}