{
  "type": "Feature",
  "properties": {
    "gn:admin1_code":"11",
    "gn:asciiname":"Jinlongshan",
    "gn:country_code":"CN",
    "gn:dem":309,
    "gn:feature_class":"P",
    "gn:feature_code":"PPL",
    "gn:name":"Jinlongshan",
    "gn:population":0,
    "gn:timezone":"Asia/Shanghai",
    "iso:country":"CN",
    "name:zho_x_preferred":[
        "\u91d1\u9f99\u5c71\u9547"
    ],
    "wof:name":"Jinlongshan",
    "wof:placetype":"locality"
},
  "geometry": {"coordinates":[110.99944000000001,26.69889],"type":"Point"}
}