{
  "type": "Feature",
  "properties": {
    "gn:admin1_code":"2.0",
    "gn:asciiname":"Sanfangli",
    "gn:country_code":"CN",
    "gn:dem":148,
    "gn:feature_class":"P",
    "gn:feature_code":"PPL",
    "gn:name":"Sanfangli",
    "gn:population":0,
    "gn:timezone":"Asia/Shanghai",
    "iso:country":"CN",
    "name:und_x_variant":[
        "\u4e09\u623f\u91cc"
    ],
    "wof:name":"Sanfangli",
    "wof:placetype":"locality"
},
  "geometry": {"coordinates":[119.62452,30.05877000000001],"type":"Point"}
}