{
  "type": "Feature",
  "properties": {
    "gn:admin1_code":"26.0",
    "gn:asciiname":"Wuxing",
    "gn:country_code":"CN",
    "gn:dem":730,
    "gn:feature_class":"P",
    "gn:feature_code":"PPL",
    "gn:name":"Wuxing",
    "gn:population":0,
    "gn:timezone":"Asia/Shanghai",
    "iso:country":"CN",
    "name:ceb_x_preferred":[
        "Wuxing"
    ],
    "name:deu_x_preferred":[
        "Wuxing"
    ],
    "name:fra_x_preferred":[
        "Wuxing"
    ],
    "name:und_x_variant":[
        "\u4e94\u661f"
    ],
    "wof:name":"Wuxing",
    "wof:placetype":"locality"
},
  "geometry": {"coordinates":[107.44947000000001,34.41518],"type":"Point"}
}