{
  "type": "Feature",
  "properties": {
    "gn:admin1_code":"3.0",
    "gn:asciiname":"Changling",
    "gn:country_code":"CN",
    "gn:dem":428,
    "gn:feature_class":"P",
    "gn:feature_code":"PPL",
    "gn:name":"Changling",
    "gn:population":0,
    "gn:timezone":"Asia/Shanghai",
    "iso:country":"CN",
    "name:ceb_x_preferred":[
        "Changling"
    ],
    "name:deu_x_preferred":[
        "Changling"
    ],
    "name:mlg_x_preferred":[
        "Changling"
    ],
    "name:swe_x_preferred":[
        "Changling"
    ],
    "name:ukr_x_preferred":[
        "\u0427\u0430\u043d\u043b\u0456\u043d"
    ],
    "name:zho_x_preferred":[
        "\u957f\u5cad"
    ],
    "wof:name":"Changling",
    "wof:placetype":"locality"
},
  "geometry": {"coordinates":[114.196,27.6179],"type":"Point"}
}