{
  "type": "Feature",
  "properties": {
    "gn:admin1_code":"19.0",
    "gn:asciiname":"Baishangou",
    "gn:country_code":"CN",
    "gn:dem":185,
    "gn:feature_class":"P",
    "gn:feature_code":"PPL",
    "gn:name":"Baishangou",
    "gn:population":0,
    "gn:timezone":"Asia/Shanghai",
    "iso:country":"CN",
    "name:und_x_variant":[
        "\u67cf\u5c71\u6c9f"
    ],
    "name:zho_x_preferred":[
        "\u67cf\u5c71\u6c9f"
    ],
    "wof:name":"Baishangou",
    "wof:placetype":"locality"
},
  "geometry": {"coordinates":[120.532,41.1578],"type":"Point"}
}