{
  "type": "Feature",
  "properties": {
    "gn:admin1_code":"8.0",
    "gn:asciiname":"Guodikengcun",
    "gn:country_code":"CN",
    "gn:dem":276,
    "gn:feature_class":"P",
    "gn:feature_code":"PPL",
    "gn:name":"Guodikengcun",
    "gn:population":0,
    "gn:timezone":"Asia/Shanghai",
    "iso:country":"CN",
    "name:zho_x_preferred":[
        "\u90ed\u72c4\u5751\u6751"
    ],
    "wof:name":"Guodikengcun",
    "wof:placetype":"locality"
},
  "geometry": {"coordinates":[123.05649,47.59956],"type":"Point"}
}