{
  "type": "Feature",
  "properties": {
    "gn:admin1_code":"19.0",
    "gn:asciiname":"Huajiacun",
    "gn:country_code":"CN",
    "gn:dem":88,
    "gn:feature_class":"P",
    "gn:feature_code":"PPL",
    "gn:name":"Huajiacun",
    "gn:population":0,
    "gn:timezone":"Asia/Shanghai",
    "iso:country":"CN",
    "name:zho_x_preferred":[
        "\u82b1\u5bb6\u6751"
    ],
    "wof:name":"Huajiacun",
    "wof:placetype":"locality"
},
  "geometry": {"coordinates":[122.52200000000001,42.4207],"type":"Point"}
}