{
  "type": "Feature",
  "properties": {
    "gn:admin1_code":"15.0",
    "gn:asciiname":"Sigoujie",
    "gn:country_code":"CN",
    "gn:dem":1283,
    "gn:feature_class":"P",
    "gn:feature_code":"PPL",
    "gn:name":"Sigoujie",
    "gn:population":0,
    "gn:timezone":"Asia/Shanghai",
    "iso:country":"CN",
    "name:zho_x_preferred":[
        "\u5bfa\u6c9f\u8857"
    ],
    "wof:name":"Sigoujie",
    "wof:placetype":"locality"
},
  "geometry": {"coordinates":[106.18899999999999,34.1854],"type":"Point"}
}