{
  "type": "Feature",
  "properties": {
    "gn:admin1_code":"16.0",
    "gn:asciiname":"Jiajin",
    "gn:country_code":"CN",
    "gn:dem":575,
    "gn:feature_class":"P",
    "gn:feature_code":"PPL",
    "gn:name":"Jiajin",
    "gn:population":0,
    "gn:timezone":"Asia/Shanghai",
    "iso:country":"CN",
    "name:zho_x_preferred":[
        "\u52a0\u8fdb"
    ],
    "wof:name":"Jiajin",
    "wof:placetype":"locality"
},
  "geometry": {"coordinates":[107.925,24.2138],"type":"Point"}
}