{
  "type": "Feature",
  "properties": {
    "gn:admin1_code":"9.0",
    "gn:asciiname":"Zhanglinzhuang",
    "gn:country_code":"CN",
    "gn:dem":59,
    "gn:feature_class":"P",
    "gn:feature_code":"PPL",
    "gn:name":"Zhanglinzhuang",
    "gn:population":0,
    "gn:timezone":"Asia/Shanghai",
    "iso:country":"CN",
    "name:zho_x_preferred":[
        "\u5f20\u6797\u5e84"
    ],
    "wof:name":"Zhanglinzhuang",
    "wof:placetype":"locality"
},
  "geometry": {"coordinates":[114.68758,35.6357],"type":"Point"}
}