{
  "type": "Feature",
  "properties": {
    "gn:admin1_code":"32.0",
    "gn:asciiname":"Xiaojincun",
    "gn:country_code":"CN",
    "gn:dem":2497,
    "gn:feature_class":"P",
    "gn:feature_code":"PPL",
    "gn:name":"Xiaojincun",
    "gn:population":0,
    "gn:timezone":"Asia/Shanghai",
    "iso:country":"CN",
    "name:zho_x_preferred":[
        "\u5c0f\u91d1\u6751"
    ],
    "wof:name":"Xiaojincun",
    "wof:placetype":"locality"
},
  "geometry": {"coordinates":[101.93274,28.66053],"type":"Point"}
}