{
  "type": "Feature",
  "properties": {
    "gn:admin1_code":"8.0",
    "gn:asciiname":"Fengshantun",
    "gn:country_code":"CN",
    "gn:dem":188,
    "gn:feature_class":"P",
    "gn:feature_code":"PPL",
    "gn:name":"Fengshantun",
    "gn:population":0,
    "gn:timezone":"Asia/Shanghai",
    "iso:country":"CN",
    "name:zho_x_preferred":[
        "\u51e4\u5c71\u5c6f"
    ],
    "wof:name":"Fengshantun",
    "wof:placetype":"locality"
},
  "geometry": {"coordinates":[128.49589,46.39668],"type":"Point"}
}