{
  "type": "Feature",
  "properties": {
    "gn:admin1_code":"19.0",
    "gn:asciiname":"Houdianzi",
    "gn:country_code":"CN",
    "gn:dem":73,
    "gn:feature_class":"P",
    "gn:feature_code":"PPL",
    "gn:name":"Houdianzi",
    "gn:population":0,
    "gn:timezone":"Asia/Shanghai",
    "iso:country":"CN",
    "name:und_x_variant":[
        "\u4faf\u7538\u5b50"
    ],
    "name:zho_x_preferred":[
        "\u4faf\u7538\u5b50"
    ],
    "wof:name":"Houdianzi",
    "wof:placetype":"locality"
},
  "geometry": {"coordinates":[122.12170999999999,39.6092],"type":"Point"}
}