{
  "type": "Feature",
  "properties": {
    "gn:admin1_code":"16.0",
    "gn:asciiname":"Bai'an",
    "gn:country_code":"CN",
    "gn:dem":277,
    "gn:feature_class":"P",
    "gn:feature_code":"PPL",
    "gn:name":"Bai\u2019an",
    "gn:population":0,
    "gn:timezone":"Asia/Shanghai",
    "iso:country":"CN",
    "name:und_x_variant":[
        "Bai\u2019an"
    ],
    "name:zho_x_preferred":[
        "\u767e\u5535"
    ],
    "wof:name":"Bai'an",
    "wof:placetype":"locality"
},
  "geometry": {"coordinates":[107.51300000000001,22.9678],"type":"Point"}
}