{
  "type": "Feature",
  "properties": {
    "gn:admin1_code":"4.0",
    "gn:asciiname":"Louzizhang",
    "gn:country_code":"CN",
    "gn:dem":6,
    "gn:feature_class":"P",
    "gn:feature_code":"PPL",
    "gn:name":"Louzizhang",
    "gn:population":0,
    "gn:timezone":"Asia/Shanghai",
    "iso:country":"CN",
    "name:und_x_variant":[
        "\u697c\u5b50\u5f20"
    ],
    "name:zho_x_preferred":[
        "\u697c\u5b50\u5f20"
    ],
    "wof:name":"Louzizhang",
    "wof:placetype":"locality"
},
  "geometry": {"coordinates":[120.88551,32.21921],"type":"Point"}
}