{
  "type": "Feature",
  "properties": {
    "gn:admin1_code":"7.0",
    "gn:asciiname":"Changhoukeng",
    "gn:country_code":"CN",
    "gn:dem":173,
    "gn:feature_class":"P",
    "gn:feature_code":"PPL",
    "gn:name":"Changhoukeng",
    "gn:population":0,
    "gn:timezone":"Asia/Shanghai",
    "iso:country":"CN",
    "name:zho_x_preferred":[
        "\u957f\u540e\u5751"
    ],
    "wof:name":"Changhoukeng",
    "wof:placetype":"locality"
},
  "geometry": {"coordinates":[118.48533,27.03399000000001],"type":"Point"}
}