{
  "type": "Feature",
  "properties": {
    "gn:admin1_code":"32.0",
    "gn:asciiname":"Kawa",
    "gn:country_code":"CN",
    "gn:dem":1992,
    "gn:feature_class":"P",
    "gn:feature_code":"PPL",
    "gn:name":"Kawa",
    "gn:population":0,
    "gn:timezone":"Asia/Shanghai",
    "iso:country":"CN",
    "name:ceb_x_preferred":[
        "Kawa"
    ],
    "name:deu_x_preferred":[
        "Kawa"
    ],
    "name:fra_x_preferred":[
        "Kawa"
    ],
    "name:kur_x_preferred":[
        "Kawa"
    ],
    "name:pol_x_preferred":[
        "Kawa"
    ],
    "name:swe_x_preferred":[
        "Kawa"
    ],
    "name:zho_x_preferred":[
        "\u5361\u74e6"
    ],
    "wof:name":"Kawa",
    "wof:placetype":"locality"
},
  "geometry": {"coordinates":[100.447,27.9407],"type":"Point"}
}