{
  "type": "Feature",
  "properties": {
    "gn:admin1_code":"04",
    "gn:asciiname":"Jiusiyang",
    "gn:cc2":"CN",
    "gn:country_code":"CN",
    "gn:dem":14,
    "gn:feature_class":"P",
    "gn:feature_code":"PPL",
    "gn:name":"Jiusiyang",
    "gn:population":0,
    "gn:timezone":"Asia/Shanghai",
    "iso:country":"CN",
    "name:und_x_variant":[
        "Lao-ssu-yang",
        "T\u2019ao-y\u00fcan",
        "Ssu-yang",
        "Chiu-ssu-yang",
        "Ssu-yang-ch\u2019eng",
        "Szeyang",
        "Ssu-yang-hsien",
        "Jiusiyang"
    ],
    "wof:name":"Jiusiyang",
    "wof:placetype":"locality"
},
  "geometry": {"coordinates":[118.65000000000001,33.68333],"type":"Point"}
}