{
  "type": "Feature",
  "properties": {
    "gn:admin1_code":"10",
    "gn:asciiname":"Nianziwan",
    "gn:country_code":"CN",
    "gn:dem":722,
    "gn:feature_class":"P",
    "gn:feature_code":"PPL",
    "gn:name":"Nianziwan",
    "gn:population":0,
    "gn:timezone":"Asia/Shanghai",
    "iso:country":"CN",
    "name:zho_x_preferred":[
        "\u78be\u5b50\u6e7e"
    ],
    "wof:name":"Nianziwan",
    "wof:placetype":"locality"
},
  "geometry": {"coordinates":[116.16173999999999,40.90901],"type":"Point"}
}