{
  "type": "Feature",
  "properties": {
    "gn:admin1_code":"16.0",
    "gn:asciiname":"Tangshang",
    "gn:country_code":"CN",
    "gn:dem":83,
    "gn:feature_class":"P",
    "gn:feature_code":"PPL",
    "gn:name":"Tangshang",
    "gn:population":0,
    "gn:timezone":"Asia/Shanghai",
    "iso:country":"CN",
    "name:zho_x_preferred":[
        "\u5802\u4e0a"
    ],
    "wof:name":"Tangshang",
    "wof:placetype":"locality"
},
  "geometry": {"coordinates":[109.721,24.1628],"type":"Point"}
}