{
  "type": "Feature",
  "properties": {
    "gn:admin1_code":"25",
    "gn:asciiname":"Donghebei",
    "gn:country_code":"CN",
    "gn:dem":112,
    "gn:feature_class":"P",
    "gn:feature_code":"PPL",
    "gn:name":"Donghebei",
    "gn:population":0,
    "gn:timezone":"Asia/Shanghai",
    "iso:country":"CN",
    "name:zho_x_preferred":[
        "\u4e1c\u6cb3\u5317"
    ],
    "wof:name":"Donghebei",
    "wof:placetype":"locality"
},
  "geometry": {"coordinates":[120.34,37.1092],"type":"Point"}
}