{
  "type": "Feature",
  "properties": {
    "gn:admin1_code":"11.0",
    "gn:asciiname":"Dayuwan",
    "gn:country_code":"CN",
    "gn:dem":51,
    "gn:feature_class":"P",
    "gn:feature_code":"PPL",
    "gn:name":"Dayuwan",
    "gn:population":0,
    "gn:timezone":"Asia/Shanghai",
    "iso:country":"CN",
    "name:zho_x_preferred":[
        "\u5927\u9c7c\u6e7e"
    ],
    "wof:name":"Dayuwan",
    "wof:placetype":"locality"
},
  "geometry": {"coordinates":[112.53567,26.57201],"type":"Point"}
}