{
  "type": "Feature",
  "properties": {
    "gn:admin1_code":"19.0",
    "gn:asciiname":"Shangnandi",
    "gn:country_code":"CN",
    "gn:dem":721,
    "gn:feature_class":"P",
    "gn:feature_code":"PPL",
    "gn:name":"Shangnandi",
    "gn:population":0,
    "gn:timezone":"Asia/Shanghai",
    "iso:country":"CN",
    "name:zho_x_preferred":[
        "\u4e0a\u5357\u5730"
    ],
    "wof:name":"Shangnandi",
    "wof:placetype":"locality"
},
  "geometry": {"coordinates":[119.71878,41.84183],"type":"Point"}
}