{
  "type": "Feature",
  "properties": {
    "gn:admin1_code":"20",
    "gn:asciiname":"Guantunpu",
    "gn:cc2":"CN",
    "gn:country_code":"CN",
    "gn:dem":1358,
    "gn:feature_class":"P",
    "gn:feature_code":"PPL",
    "gn:name":"Guantunpu",
    "gn:population":0,
    "gn:timezone":"Asia/Shanghai",
    "iso:country":"CN",
    "name:und_x_variant":[
        "Kuan-t\u2019un-p\u2019u",
        "Guantunpu"
    ],
    "wof:name":"Guantunpu",
    "wof:placetype":"locality"
},
  "geometry": {"coordinates":[113.38500000000001,40.38833],"type":"Point"}
}