{
  "type": "Feature",
  "properties": {
    "gn:admin1_code":"19.0",
    "gn:asciiname":"Angbangniucun",
    "gn:country_code":"CN",
    "gn:dem":32,
    "gn:feature_class":"P",
    "gn:feature_code":"PPL",
    "gn:name":"Angbangniucun",
    "gn:population":0,
    "gn:timezone":"Asia/Shanghai",
    "iso:country":"CN",
    "name:zho_x_preferred":[
        "\u6602\u5e2e\u725b\u6751"
    ],
    "wof:name":"Angbangniucun",
    "wof:placetype":"locality"
},
  "geometry": {"coordinates":[123.10299999999999,41.9123],"type":"Point"}
}