{
  "type": "Feature",
  "properties": {
    "gn:admin1_code":"7",
    "gn:asciiname":"Dongshantou",
    "gn:country_code":"CN",
    "gn:dem":640,
    "gn:feature_class":"P",
    "gn:feature_code":"PPL",
    "gn:name":"Dongshantou",
    "gn:population":0,
    "gn:timezone":"Asia/Shanghai",
    "iso:country":"CN",
    "name:und_x_variant":[
        "\u4e1c\u5c71\u5934",
        "Dongshantou"
    ],
    "wof:name":"Dongshantou",
    "wof:placetype":"locality"
},
  "geometry": {"coordinates":[118.98057,27.45687],"type":"Point"}
}