{
  "type": "Feature",
  "properties": {
    "gn:admin1_code":"3",
    "gn:asciiname":"Datang Yangjia",
    "gn:country_code":"CN",
    "gn:dem":93,
    "gn:feature_class":"P",
    "gn:feature_code":"PPL",
    "gn:name":"Datang Yangjia",
    "gn:population":0,
    "gn:timezone":"Asia/Shanghai",
    "iso:country":"CN",
    "name:und_x_variant":[
        "\u5927\u5858\u6768\u5bb6"
    ],
    "wof:name":"Datang Yangjia",
    "wof:placetype":"locality"
},
  "geometry": {"coordinates":[116.76921000000002,27.86524],"type":"Point"}
}