{
  "type": "Feature",
  "properties": {
    "gn:admin1_code":"26.0",
    "gn:asciiname":"Xuyingtacun",
    "gn:country_code":"CN",
    "gn:dem":1020,
    "gn:feature_class":"P",
    "gn:feature_code":"PPL",
    "gn:name":"Xuyingtacun",
    "gn:population":0,
    "gn:timezone":"Asia/Shanghai",
    "iso:country":"CN",
    "name:zho_x_preferred":[
        "\u5f90\u5e94\u5854\u6751"
    ],
    "wof:name":"Xuyingtacun",
    "wof:placetype":"locality"
},
  "geometry": {"coordinates":[110.49473999999999,38.76674000000001],"type":"Point"}
}