{
  "type": "Feature",
  "properties": {
    "gn:admin1_code":"14.0",
    "gn:asciiname":"Locun",
    "gn:country_code":"CN",
    "gn:dem":4614,
    "gn:feature_class":"P",
    "gn:feature_code":"PPLF",
    "gn:name":"Locun",
    "gn:population":0,
    "gn:timezone":"Asia/Urumqi",
    "iso:country":"CN",
    "name:bod_x_preferred":[
        "Locun"
    ],
    "name:und_x_variant":[
        "Luocun"
    ],
    "name:zho_x_preferred":[
        "\u6d1b\u6751"
    ],
    "wof:name":"Locun",
    "wof:placetype":"locality"
},
  "geometry": {"coordinates":[91.602,29.202],"type":"Point"}
}