{
  "type": "Feature",
  "properties": {
    "gn:admin1_code":"32.0",
    "gn:asciiname":"Jiancao",
    "gn:country_code":"CN",
    "gn:dem":3337,
    "gn:feature_class":"P",
    "gn:feature_code":"PPL",
    "gn:name":"Jiancao",
    "gn:population":0,
    "gn:timezone":"Asia/Shanghai",
    "iso:country":"CN",
    "name:zho_x_preferred":[
        "\u7b80\u69fd"
    ],
    "wof:name":"Jiancao",
    "wof:placetype":"locality"
},
  "geometry": {"coordinates":[102.61199999999999,30.9942],"type":"Point"}
}