{
  "type": "Feature",
  "properties": {
    "gn:admin1_code":"29.0",
    "gn:asciiname":"Weiqiangtou",
    "gn:country_code":"CN",
    "gn:dem":1173,
    "gn:feature_class":"P",
    "gn:feature_code":"PPL",
    "gn:name":"Weiqiangtou",
    "gn:population":0,
    "gn:timezone":"Asia/Shanghai",
    "iso:country":"CN",
    "name:zho_x_preferred":[
        "\u56f4\u5899\u5934"
    ],
    "wof:name":"Weiqiangtou",
    "wof:placetype":"locality"
},
  "geometry": {"coordinates":[104.05200000000001,28.3355],"type":"Point"}
}