{
  "type": "Feature",
  "properties": {
    "gn:admin1_code":"3.0",
    "gn:asciiname":"Tanxi",
    "gn:country_code":"CN",
    "gn:dem":111,
    "gn:feature_class":"P",
    "gn:feature_code":"PPLA4",
    "gn:name":"Tanxi",
    "gn:population":0,
    "gn:timezone":"Asia/Shanghai",
    "iso:country":"CN",
    "name:und_x_variant":[
        "\u6f6d\u6eaa",
        "Tanxi Xiang",
        "\u6f6d\u6eaa\u4e61"
    ],
    "wof:name":"Tanxi",
    "wof:placetype":"locality"
},
  "geometry": {"coordinates":[116.93749,27.28913],"type":"Point"}
}