{
  "type": "Feature",
  "properties": {
    "gn:admin1_code":"9.0",
    "gn:asciiname":"Shizishu",
    "gn:country_code":"CN",
    "gn:dem":121,
    "gn:feature_class":"P",
    "gn:feature_code":"PPL",
    "gn:name":"Shizishu",
    "gn:population":0,
    "gn:timezone":"Asia/Shanghai",
    "iso:country":"CN",
    "name:zho_x_preferred":[
        "\u67ff\u5b50\u6811"
    ],
    "wof:name":"Shizishu",
    "wof:placetype":"locality"
},
  "geometry": {"coordinates":[115.21162,31.74849],"type":"Point"}
}