{
  "type": "Feature",
  "properties": {
    "gn:admin1_code":"2.0",
    "gn:asciiname":"Bamengang",
    "gn:country_code":"CN",
    "gn:dem":604,
    "gn:feature_class":"P",
    "gn:feature_code":"PPL",
    "gn:name":"Bamengang",
    "gn:population":0,
    "gn:timezone":"Asia/Shanghai",
    "iso:country":"CN",
    "name:zho_x_preferred":[
        "\u516b\u95e8\u5c97"
    ],
    "wof:name":"Bamengang",
    "wof:placetype":"locality"
},
  "geometry": {"coordinates":[119.3533,28.70878],"type":"Point"}
}