{
  "type": "Feature",
  "properties": {
    "gn:admin1_code":"12.0",
    "gn:asciiname":"Shuiyankeng",
    "gn:country_code":"CN",
    "gn:dem":858,
    "gn:feature_class":"P",
    "gn:feature_code":"PPL",
    "gn:name":"Shuiyankeng",
    "gn:population":0,
    "gn:timezone":"Asia/Shanghai",
    "iso:country":"CN",
    "name:zho_x_preferred":[
        "\u6c34\u6df9\u5751"
    ],
    "wof:name":"Shuiyankeng",
    "wof:placetype":"locality"
},
  "geometry": {"coordinates":[111.64336000000002,31.686],"type":"Point"}
}