{
  "type": "Feature",
  "properties": {
    "gn:admin1_code":"11.0",
    "gn:asciiname":"Miaogangshang",
    "gn:country_code":"CN",
    "gn:dem":196,
    "gn:feature_class":"P",
    "gn:feature_code":"PPL",
    "gn:name":"Miaogangshang",
    "gn:population":0,
    "gn:timezone":"Asia/Shanghai",
    "iso:country":"CN",
    "name:zho_x_preferred":[
        "\u5e99\u5c97\u4e0a"
    ],
    "wof:name":"Miaogangshang",
    "wof:placetype":"locality"
},
  "geometry": {"coordinates":[110.3524,29.07078],"type":"Point"}
}