{
  "type": "Feature",
  "properties": {
    "gn:admin1_code":"14.0",
    "gn:asciiname":"Nankor",
    "gn:country_code":"CN",
    "gn:dem":4939,
    "gn:feature_class":"P",
    "gn:feature_code":"PPL",
    "gn:name":"Nankor",
    "gn:population":0,
    "gn:timezone":"Asia/Urumqi",
    "iso:country":"CN",
    "name:bod_x_preferred":[
        "Nankor"
    ],
    "name:zho_x_preferred":[
        "Naguo"
    ],
    "name:zho_x_variant":[
        "\u7eb3\u679c",
        "Nanmuqie Qu",
        "\u5357\u6728\u5207\u533a"
    ],
    "wof:name":"Nankor",
    "wof:placetype":"locality"
},
  "geometry": {"coordinates":[88.30200000000001,29.702],"type":"Point"}
}