{
  "type": "Feature",
  "properties": {
    "gn:admin1_code":"10.0",
    "gn:asciiname":"Songpengsi",
    "gn:country_code":"CN",
    "gn:dem":907,
    "gn:feature_class":"P",
    "gn:feature_code":"PPL",
    "gn:name":"Songpengsi",
    "gn:population":0,
    "gn:timezone":"Asia/Shanghai",
    "iso:country":"CN",
    "name:zho_x_preferred":[
        "\u677e\u84ec\u5bfa"
    ],
    "wof:name":"Songpengsi",
    "wof:placetype":"locality"
},
  "geometry": {"coordinates":[115.72602999999999,40.25181],"type":"Point"}
}