{
  "type": "Feature",
  "properties": {
    "gn:admin1_code":"3.0",
    "gn:asciiname":"Zhouwei",
    "gn:country_code":"CN",
    "gn:dem":562,
    "gn:feature_class":"P",
    "gn:feature_code":"PPL",
    "gn:name":"Zhouwei",
    "gn:population":0,
    "gn:timezone":"Asia/Shanghai",
    "iso:country":"CN",
    "name:zho_x_preferred":[
        "\u5468\u5c3e"
    ],
    "wof:name":"Zhouwei",
    "wof:placetype":"locality"
},
  "geometry": {"coordinates":[115.523,25.2022],"type":"Point"}
}