{
  "type": "Feature",
  "properties": {
    "gn:admin1_code":"13.0",
    "gn:asciiname":"Tasayi",
    "gn:country_code":"CN",
    "gn:dem":3013,
    "gn:feature_class":"P",
    "gn:feature_code":"PPL",
    "gn:name":"Tasayi",
    "gn:population":0,
    "gn:timezone":"Asia/Shanghai",
    "iso:country":"CN",
    "name:zho_x_preferred":[
        "\u5854\u8428\u4f9d"
    ],
    "wof:name":"Tasayi",
    "wof:placetype":"locality"
},
  "geometry": {"coordinates":[79.95489000000001,36.24952],"type":"Point"}
}