{
  "type": "Feature",
  "properties": {
    "gn:admin1_code":"4.0",
    "gn:asciiname":"Jinsucun",
    "gn:country_code":"CN",
    "gn:dem":8,
    "gn:feature_class":"P",
    "gn:feature_code":"PPL",
    "gn:name":"Jinsucun",
    "gn:population":0,
    "gn:timezone":"Asia/Shanghai",
    "iso:country":"CN",
    "name:zho_x_preferred":[
        "\u91d1\u82cf\u6751"
    ],
    "wof:name":"Jinsucun",
    "wof:placetype":"locality"
},
  "geometry": {"coordinates":[119.34869,34.67290999999999],"type":"Point"}
}