{
  "type": "Feature",
  "properties": {
    "gn:admin1_code":"4.0",
    "gn:asciiname":"Nanfengchangcun",
    "gn:country_code":"CN",
    "gn:dem":35,
    "gn:feature_class":"P",
    "gn:feature_code":"PPL",
    "gn:name":"Nanfengchangcun",
    "gn:population":0,
    "gn:timezone":"Asia/Shanghai",
    "iso:country":"CN",
    "name:zho_x_preferred":[
        "\u5357\u51af\u573a\u6751"
    ],
    "wof:name":"Nanfengchangcun",
    "wof:placetype":"locality"
},
  "geometry": {"coordinates":[118.04730000000001,34.50409000000001],"type":"Point"}
}