{
  "type": "Feature",
  "properties": {
    "gn:admin1_code":"25",
    "gn:asciiname":"Shuanglongyu",
    "gn:country_code":"CN",
    "gn:dem":288,
    "gn:feature_class":"P",
    "gn:feature_code":"PPL",
    "gn:name":"Shuanglongyu",
    "gn:population":0,
    "gn:timezone":"Asia/Shanghai",
    "iso:country":"CN",
    "name:zho_x_preferred":[
        "\u53cc\u9f99\u5cea"
    ],
    "wof:name":"Shuanglongyu",
    "wof:placetype":"locality"
},
  "geometry": {"coordinates":[117.85899999999999,36.1582],"type":"Point"}
}