{
  "type": "Feature",
  "properties": {
    "gn:admin1_code":"32.0",
    "gn:asciiname":"Malatixi",
    "gn:country_code":"CN",
    "gn:dem":4197,
    "gn:feature_class":"P",
    "gn:feature_code":"PPL",
    "gn:name":"Malatixi",
    "gn:population":0,
    "gn:timezone":"Asia/Shanghai",
    "iso:country":"CN",
    "name:zho_x_preferred":[
        "\u739b\u62c9\u63d0\u5e0c"
    ],
    "wof:name":"Malatixi",
    "wof:placetype":"locality"
},
  "geometry": {"coordinates":[100.82752000000001,29.7793],"type":"Point"}
}