{
  "type": "Feature",
  "properties": {
    "gn:admin1_code":"5.0",
    "gn:asciiname":"Shengli Linchang",
    "gn:country_code":"CN",
    "gn:dem":917,
    "gn:feature_class":"P",
    "gn:feature_code":"PPLF",
    "gn:name":"Shengli Linchang",
    "gn:population":0,
    "gn:timezone":"Asia/Shanghai",
    "iso:country":"CN",
    "name:und_x_variant":[
        "\u80dc\u5229\u6797\u573a"
    ],
    "wof:name":"Shengli Linchang",
    "wof:placetype":"locality"
},
  "geometry": {"coordinates":[127.76452,42.32505],"type":"Point"}
}