{
  "type": "Feature",
  "properties": {
    "gn:admin1_code":"2.0",
    "gn:asciiname":"Xia'aofang",
    "gn:country_code":"CN",
    "gn:dem":20,
    "gn:feature_class":"P",
    "gn:feature_code":"PPL",
    "gn:name":"Xia\u2019aofang",
    "gn:population":0,
    "gn:timezone":"Asia/Shanghai",
    "iso:country":"CN",
    "name:und_x_variant":[
        "Xia\u2019aofang"
    ],
    "name:zho_x_preferred":[
        "\u4e0b\u5c99\u65b9"
    ],
    "wof:name":"Xia'aofang",
    "wof:placetype":"locality"
},
  "geometry": {"coordinates":[121.503,28.93025],"type":"Point"}
}