{
  "type": "Feature",
  "properties": {
    "gn:admin1_code":"31",
    "gn:asciiname":"Buxiao",
    "gn:country_code":"CN",
    "gn:dem":67,
    "gn:feature_class":"P",
    "gn:feature_code":"PPL",
    "gn:name":"Buxiao",
    "gn:population":0,
    "gn:timezone":"Asia/Shanghai",
    "iso:country":"CN",
    "name:und_x_variant":[
        "\u535c\u6548"
    ],
    "wof:name":"Buxiao",
    "wof:placetype":"locality"
},
  "geometry": {"coordinates":[110.166,19.6406],"type":"Point"}
}