{
  "type": "Feature",
  "properties": {
    "gn:admin1_code":"26.0",
    "gn:asciiname":"Tianchizi",
    "gn:country_code":"CN",
    "gn:dem":1406,
    "gn:feature_class":"P",
    "gn:feature_code":"PPL",
    "gn:name":"Tianchizi",
    "gn:population":0,
    "gn:timezone":"Asia/Shanghai",
    "iso:country":"CN",
    "name:und_x_variant":[
        "\u5929\u6c60\u5b50"
    ],
    "wof:name":"Tianchizi",
    "wof:placetype":"locality"
},
  "geometry": {"coordinates":[105.97637,33.1149],"type":"Point"}
}