{
  "type": "Feature",
  "properties": {
    "gn:admin1_code":"25.0",
    "gn:asciiname":"Liangjiazhuang",
    "gn:country_code":"CN",
    "gn:dem":23,
    "gn:feature_class":"P",
    "gn:feature_code":"PPL",
    "gn:name":"Liangjiazhuang",
    "gn:population":0,
    "gn:timezone":"Asia/Shanghai",
    "iso:country":"CN",
    "name:zho_x_preferred":[
        "\u4e24\u7532\u5e84"
    ],
    "wof:name":"Liangjiazhuang",
    "wof:placetype":"locality"
},
  "geometry": {"coordinates":[121.25932,37.44192],"type":"Point"}
}