{
  "type": "Feature",
  "properties": {
    "gn:admin1_code":"02",
    "gn:asciiname":"Xujiachang",
    "gn:country_code":"CN",
    "gn:dem":7,
    "gn:feature_class":"P",
    "gn:feature_code":"PPL",
    "gn:name":"Xujiachang",
    "gn:population":0,
    "gn:timezone":"Asia/Shanghai",
    "iso:country":"CN",
    "name:und_x_variant":[
        "\u8bb8\u5bb6\u573a",
        "Hsu-chia"
    ],
    "wof:name":"Xujiachang",
    "wof:placetype":"locality"
},
  "geometry": {"coordinates":[120.60693999999999,30.41115],"type":"Point"}
}