{
  "type": "Feature",
  "properties": {
    "gn:admin1_code":"3",
    "gn:asciiname":"Jiangkeng",
    "gn:country_code":"CN",
    "gn:dem":281,
    "gn:feature_class":"P",
    "gn:feature_code":"PPL",
    "gn:name":"Jiangkeng",
    "gn:population":0,
    "gn:timezone":"Asia/Shanghai",
    "iso:country":"CN",
    "name:zho_x_preferred":[
        "\u6d46\u5751"
    ],
    "wof:name":"Jiangkeng",
    "wof:placetype":"locality"
},
  "geometry": {"coordinates":[114.343,26.8165],"type":"Point"}
}