{
  "type": "Feature",
  "properties": {
    "gn:admin1_code":"15.0",
    "gn:asciiname":"Liuyangba",
    "gn:country_code":"CN",
    "gn:dem":2210,
    "gn:feature_class":"P",
    "gn:feature_code":"PPL",
    "gn:name":"Liuyangba",
    "gn:population":0,
    "gn:timezone":"Asia/Shanghai",
    "iso:country":"CN",
    "name:zho_x_preferred":[
        "\u516d\u6d0b\u575d"
    ],
    "wof:name":"Liuyangba",
    "wof:placetype":"locality"
},
  "geometry": {"coordinates":[99.34139999999999,39.1391],"type":"Point"}
}