{
  "type": "Feature",
  "properties": {
    "gn:admin1_code":"16.0",
    "gn:asciiname":"Gu'ao",
    "gn:country_code":"CN",
    "gn:dem":351,
    "gn:feature_class":"P",
    "gn:feature_code":"PPL",
    "gn:name":"Gu\u2019ao",
    "gn:population":0,
    "gn:timezone":"Asia/Shanghai",
    "iso:country":"CN",
    "name:und_x_variant":[
        "Gu\u2019ao"
    ],
    "name:zho_x_preferred":[
        "\u53e4\u6556"
    ],
    "wof:name":"Gu'ao",
    "wof:placetype":"locality"
},
  "geometry": {"coordinates":[108.883,23.9704],"type":"Point"}
}