{
  "type": "Feature",
  "properties": {
    "gn:admin1_code":"4.0",
    "gn:asciiname":"Haojiacun",
    "gn:country_code":"CN",
    "gn:dem":43,
    "gn:feature_class":"P",
    "gn:feature_code":"PPL",
    "gn:name":"Haojiacun",
    "gn:population":0,
    "gn:timezone":"Asia/Shanghai",
    "iso:country":"CN",
    "name:zho_x_preferred":[
        "\u90dd\u5bb6\u6751"
    ],
    "wof:name":"Haojiacun",
    "wof:placetype":"locality"
},
  "geometry": {"coordinates":[117.3681,34.54413],"type":"Point"}
}