{
  "type": "Feature",
  "properties": {
    "gn:admin1_code":"12.0",
    "gn:asciiname":"Chijia Zuizi",
    "gn:country_code":"CN",
    "gn:dem":28,
    "gn:feature_class":"P",
    "gn:feature_code":"PPL",
    "gn:name":"Chijia Zuizi",
    "gn:population":0,
    "gn:timezone":"Asia/Shanghai",
    "iso:country":"CN",
    "name:zho_x_preferred":[
        "\u6c60\u5bb6\u5480\u5b50"
    ],
    "wof:name":"Chijia Zuizi",
    "wof:placetype":"locality"
},
  "geometry": {"coordinates":[113.83457,31.01159],"type":"Point"}
}