{
  "type": "Feature",
  "properties": {
    "gn:admin1_code":"4.0",
    "gn:asciiname":"Cishandian",
    "gn:country_code":"CN",
    "gn:dem":5,
    "gn:feature_class":"P",
    "gn:feature_code":"PPL",
    "gn:name":"Cishandian",
    "gn:population":0,
    "gn:timezone":"Asia/Shanghai",
    "iso:country":"CN",
    "name:zho_x_preferred":[
        "\u7960\u5c71\u6bbf"
    ],
    "wof:name":"Cishandian",
    "wof:placetype":"locality"
},
  "geometry": {"coordinates":[120.25569,32.09049],"type":"Point"}
}