{
  "type": "Feature",
  "properties": {
    "gn:admin1_code":"30.0",
    "gn:asciiname":"Yaojingli",
    "gn:country_code":"CN",
    "gn:dem":31,
    "gn:feature_class":"P",
    "gn:feature_code":"PPL",
    "gn:name":"Yaojingli",
    "gn:population":0,
    "gn:timezone":"Asia/Shanghai",
    "iso:country":"CN",
    "name:zho_x_preferred":[
        "\u9065\u5f84\u91cc"
    ],
    "wof:name":"Yaojingli",
    "wof:placetype":"locality"
},
  "geometry": {"coordinates":[112.64655,22.19975],"type":"Point"}
}