{
  "type": "Feature",
  "properties": {
    "gn:admin1_code":"31.0",
    "gn:asciiname":"Wenchangxi",
    "gn:country_code":"CN",
    "gn:dem":54,
    "gn:feature_class":"P",
    "gn:feature_code":"PPL",
    "gn:name":"Wenchangxi",
    "gn:population":0,
    "gn:timezone":"Asia/Shanghai",
    "iso:country":"CN",
    "name:zho_x_preferred":[
        "\u6587\u660c\u6eaa"
    ],
    "wof:name":"Wenchangxi",
    "wof:placetype":"locality"
},
  "geometry": {"coordinates":[110.51751000000002,19.61258],"type":"Point"}
}