{
  "type": "Feature",
  "properties": {
    "gn:admin1_code":"32.0",
    "gn:asciiname":"Daluping",
    "gn:country_code":"CN",
    "gn:dem":1051,
    "gn:feature_class":"P",
    "gn:feature_code":"PPL",
    "gn:name":"Daluping",
    "gn:population":0,
    "gn:timezone":"Asia/Shanghai",
    "iso:country":"CN",
    "name:zho_x_preferred":[
        "\u5927\u8def\u576a"
    ],
    "wof:name":"Daluping",
    "wof:placetype":"locality"
},
  "geometry": {"coordinates":[108.104,32.0647],"type":"Point"}
}