{
  "type": "Feature",
  "properties": {
    "gn:admin1_code":"09",
    "gn:asciiname":"Tuodian",
    "gn:country_code":"CN",
    "gn:dem":108,
    "gn:feature_class":"P",
    "gn:feature_code":"PPL",
    "gn:name":"Tuodian",
    "gn:population":0,
    "gn:timezone":"Asia/Shanghai",
    "iso:country":"CN",
    "name:und_x_variant":[
        "Lo-t\u2019o-tien",
        "Luotuodian",
        "Tuodian"
    ],
    "name:zho_x_preferred":[
        "\u9a7c\u5e97"
    ],
    "wof:name":"Tuodian",
    "wof:placetype":"locality"
},
  "geometry": {"coordinates":[113.83113,32.20632],"type":"Point"}
}