{
  "type": "Feature",
  "properties": {
    "gn:admin1_code":"13.0",
    "gn:asciiname":"Sayileke",
    "gn:country_code":"CN",
    "gn:dem":4296,
    "gn:feature_class":"P",
    "gn:feature_code":"PPL",
    "gn:name":"Sayileke",
    "gn:population":0,
    "gn:timezone":"Asia/Urumqi",
    "iso:country":"CN",
    "name:zho_x_preferred":[
        "\u8428\u4f9d\u52d2\u514b"
    ],
    "wof:name":"Sayileke",
    "wof:placetype":"locality"
},
  "geometry": {"coordinates":[84.87964000000002,37.0174],"type":"Point"}
}