{
  "type": "Feature",
  "properties": {
    "gn:admin1_code":"8.0",
    "gn:asciiname":"Fengwangcun",
    "gn:country_code":"CN",
    "gn:dem":167,
    "gn:feature_class":"P",
    "gn:feature_code":"PPL",
    "gn:name":"Fengwangcun",
    "gn:population":0,
    "gn:timezone":"Asia/Shanghai",
    "iso:country":"CN",
    "name:zho_x_preferred":[
        "\u4e30\u671b\u6751"
    ],
    "wof:name":"Fengwangcun",
    "wof:placetype":"locality"
},
  "geometry": {"coordinates":[126.93414,46.46523],"type":"Point"}
}