{
  "type": "Feature",
  "properties": {
    "gn:admin1_code":"2.0",
    "gn:asciiname":"Lingjue",
    "gn:country_code":"CN",
    "gn:dem":178,
    "gn:feature_class":"P",
    "gn:feature_code":"PPL",
    "gn:name":"Lingjue",
    "gn:population":0,
    "gn:timezone":"Asia/Shanghai",
    "iso:country":"CN",
    "name:zho_x_preferred":[
        "\u9886\u8bc0"
    ],
    "wof:name":"Lingjue",
    "wof:placetype":"locality"
},
  "geometry": {"coordinates":[120.4657,29.40658],"type":"Point"}
}