{
  "type": "Feature",
  "properties": {
    "gn:admin1_code":"32.0",
    "gn:asciiname":"Ma'er",
    "gn:country_code":"CN",
    "gn:dem":2885,
    "gn:feature_class":"P",
    "gn:feature_code":"PPL",
    "gn:name":"Ma\u2019er",
    "gn:population":0,
    "gn:timezone":"Asia/Shanghai",
    "iso:country":"CN",
    "name:und_x_variant":[
        "Ma\u2019er"
    ],
    "name:zho_x_preferred":[
        "\u9a6c\u5c14"
    ],
    "wof:name":"Ma'er",
    "wof:placetype":"locality"
},
  "geometry": {"coordinates":[102.215,31.0193],"type":"Point"}
}