{
  "type": "Feature",
  "properties": {
    "gn:admin1_code":"3.0",
    "gn:asciiname":"Gongjiaqiao",
    "gn:country_code":"CN",
    "gn:dem":56,
    "gn:feature_class":"P",
    "gn:feature_code":"PPL",
    "gn:name":"Gongjiaqiao",
    "gn:population":0,
    "gn:timezone":"Asia/Shanghai",
    "iso:country":"CN",
    "name:und_x_variant":[
        "\u9f9a\u5bb6\u6865"
    ],
    "wof:name":"Gongjiaqiao",
    "wof:placetype":"locality"
},
  "geometry": {"coordinates":[115.37242999999999,28.23284],"type":"Point"}
}