{
  "type": "Feature",
  "properties": {
    "gn:admin1_code":"30.0",
    "gn:asciiname":"Beitang Jiejiao",
    "gn:country_code":"CN",
    "gn:dem":153,
    "gn:feature_class":"P",
    "gn:feature_code":"PPL",
    "gn:name":"Beitang Jiejiao",
    "gn:population":0,
    "gn:timezone":"Asia/Shanghai",
    "iso:country":"CN",
    "name:zho_x_preferred":[
        "\u5317\u5858\u754c\u811a"
    ],
    "wof:name":"Beitang Jiejiao",
    "wof:placetype":"locality"
},
  "geometry": {"coordinates":[111.64296000000002,23.79683],"type":"Point"}
}