{
  "type": "Feature",
  "properties": {
    "gn:admin1_code":"18",
    "gn:asciiname":"Shuihezi",
    "gn:country_code":"CN",
    "gn:dem":927,
    "gn:feature_class":"P",
    "gn:feature_code":"PPL",
    "gn:name":"Shuihezi",
    "gn:population":0,
    "gn:timezone":"Asia/Shanghai",
    "iso:country":"CN",
    "name:zho_x_preferred":[
        "\u6c34\u6cb3\u5b50"
    ],
    "wof:name":"Shuihezi",
    "wof:placetype":"locality"
},
  "geometry": {"coordinates":[107.586,28.1347],"type":"Point"}
}