{
  "type": "Feature",
  "properties": {
    "gn:admin1_code":"26.0",
    "gn:asciiname":"Zhangjia Qucun",
    "gn:country_code":"CN",
    "gn:dem":1076,
    "gn:feature_class":"P",
    "gn:feature_code":"PPL",
    "gn:name":"Zhangjia Qucun",
    "gn:population":0,
    "gn:timezone":"Asia/Shanghai",
    "iso:country":"CN",
    "name:zho_x_preferred":[
        "\u5f20\u5bb6\u6e20\u6751"
    ],
    "wof:name":"Zhangjia Qucun",
    "wof:placetype":"locality"
},
  "geometry": {"coordinates":[109.95999999999999,37.3405],"type":"Point"}
}