{
  "type": "Feature",
  "properties": {
    "gn:admin1_code":"23.0",
    "gn:asciiname":"Min'an",
    "gn:country_code":"CN",
    "gn:dem":6,
    "gn:feature_class":"P",
    "gn:feature_code":"PPL",
    "gn:name":"Min\u2019an",
    "gn:population":0,
    "gn:timezone":"Asia/Shanghai",
    "iso:country":"CN",
    "name:und_x_variant":[
        "\u6c11\u5b89"
    ],
    "name:zho_x_preferred":[
        "Min\u2019an"
    ],
    "wof:name":"Min'an",
    "wof:placetype":"locality"
},
  "geometry": {"coordinates":[121.57472,30.94835],"type":"Point"}
}