{
  "type": "Feature",
  "properties": {
    "gn:admin1_code":"15.0",
    "gn:asciiname":"Lishanbu",
    "gn:country_code":"CN",
    "gn:dem":2079,
    "gn:feature_class":"P",
    "gn:feature_code":"PPL",
    "gn:name":"Lishanbu",
    "gn:population":0,
    "gn:timezone":"Asia/Shanghai",
    "iso:country":"CN",
    "name:zho_x_preferred":[
        "\u674e\u5584\u5821"
    ],
    "wof:name":"Lishanbu",
    "wof:placetype":"locality"
},
  "geometry": {"coordinates":[105.206,36.2733],"type":"Point"}
}