{
  "type": "Feature",
  "properties": {
    "gn:admin1_code":"29.0",
    "gn:asciiname":"Alangshan",
    "gn:country_code":"CN",
    "gn:dem":2051,
    "gn:feature_class":"P",
    "gn:feature_code":"PPL",
    "gn:name":"Alangshan",
    "gn:population":0,
    "gn:timezone":"Asia/Shanghai",
    "iso:country":"CN",
    "name:zho_x_preferred":[
        "\u963f\u6717\u5c71"
    ],
    "wof:name":"Alangshan",
    "wof:placetype":"locality"
},
  "geometry": {"coordinates":[99.71339999999999,25.1101],"type":"Point"}
}