{
  "type": "Feature",
  "properties": {
    "gn:admin1_code":"15.0",
    "gn:asciiname":"Xinying",
    "gn:cc2":"CN",
    "gn:country_code":"CN",
    "gn:dem":2213,
    "gn:feature_class":"P",
    "gn:feature_code":"PPL",
    "gn:name":"Xinying",
    "gn:population":0,
    "gn:timezone":"Asia/Shanghai",
    "iso:country":"CN",
    "name:und_x_variant":[
        "Hsin-ying-chen",
        "Xinying"
    ],
    "wof:name":"Xinying",
    "wof:placetype":"locality"
},
  "geometry": {"coordinates":[104.17833,35.70389],"type":"Point"}
}