{
  "type": "Feature",
  "properties": {
    "gn:admin1_code":"13.0",
    "gn:asciiname":"Bore Mailixin",
    "gn:country_code":"CN",
    "gn:dem":1704,
    "gn:feature_class":"P",
    "gn:feature_code":"PPL",
    "gn:name":"Bore Mailixin",
    "gn:population":0,
    "gn:timezone":"Asia/Shanghai",
    "iso:country":"CN",
    "name:und_x_variant":[
        "\u535a\u70ed\u4e70\u91cc\u65b0"
    ],
    "wof:name":"Bore Mailixin",
    "wof:placetype":"locality"
},
  "geometry": {"coordinates":[76.20352,38.65634],"type":"Point"}
}