{
  "type": "Feature",
  "properties": {
    "gn:admin1_code":"10",
    "gn:asciiname":"Nantou",
    "gn:country_code":"CN",
    "gn:dem":585,
    "gn:feature_class":"P",
    "gn:feature_code":"PPL",
    "gn:name":"Nantou",
    "gn:population":0,
    "gn:timezone":"Asia/Shanghai",
    "iso:country":"CN",
    "name:ben_x_preferred":[
        "\u09a8\u09be\u09a8\u09cd\u09a4\u09cc"
    ],
    "name:ceb_x_preferred":[
        "Nantou"
    ],
    "name:deu_x_preferred":[
        "Nantou"
    ],
    "name:ell_x_preferred":[
        "\u039d\u03ac\u03bd\u03c4\u03bf\u03c5"
    ],
    "name:fas_x_preferred":[
        "\u0646\u0627\u0646\u062a\u0648"
    ],
    "name:heb_x_preferred":[
        "\u05e0\u05d0\u05e0\u05d8\u05d5"
    ],
    "name:hin_x_preferred":[
        "\u0928\u0902\u0924\u093e\u090a"
    ],
    "name:hun_x_preferred":[
        "Nantou"
    ],
    "name:ind_x_preferred":[
        "Nantou"
    ],
    "name:kor_x_preferred":[
        "\ub09c\ud130\uc6b0"
    ],
    "name:nld_x_preferred":[
        "Nantou"
    ],
    "name:por_x_preferred":[
        "Nantou"
    ],
    "name:swe_x_preferred":[
        "Nantou"
    ],
    "name:ukr_x_preferred":[
        "\u041d\u0430\u043d\u044c\u0442\u043e\u0443"
    ],
    "name:urd_x_preferred":[
        "\u0646\u0627\u0646\u062a\u0648"
    ],
    "name:zho_x_preferred":[
        "\u5357\u5934"
    ],
    "wof:name":"Nantou",
    "wof:placetype":"locality"
},
  "geometry": {"coordinates":[117.46425000000001,40.93715],"type":"Point"}
}