{
  "type": "Feature",
  "properties": {
    "gn:admin1_code":"33.0",
    "gn:asciiname":"Dabailin",
    "gn:country_code":"CN",
    "gn:dem":914,
    "gn:feature_class":"P",
    "gn:feature_code":"PPL",
    "gn:name":"Dabailin",
    "gn:population":0,
    "gn:timezone":"Asia/Shanghai",
    "iso:country":"CN",
    "name:zho_x_preferred":[
        "\u5927\u67cf\u6797"
    ],
    "wof:name":"Dabailin",
    "wof:placetype":"locality"
},
  "geometry": {"coordinates":[109.50409000000001,31.15647],"type":"Point"}
}