{
  "type": "Feature",
  "properties": {
    "gn:admin1_code":"15.0",
    "gn:asciiname":"Yaojiamen",
    "gn:country_code":"CN",
    "gn:dem":2086,
    "gn:feature_class":"P",
    "gn:feature_code":"PPL",
    "gn:name":"Yaojiamen",
    "gn:population":0,
    "gn:timezone":"Asia/Shanghai",
    "iso:country":"CN",
    "name:zho_x_preferred":[
        "\u59da\u5bb6\u95e8"
    ],
    "wof:name":"Yaojiamen",
    "wof:placetype":"locality"
},
  "geometry": {"coordinates":[104.758,35.3348],"type":"Point"}
}