{
  "type": "Feature",
  "properties": {
    "gn:admin1_code":"30.0",
    "gn:asciiname":"Zhaoyang",
    "gn:country_code":"CN",
    "gn:dem":3,
    "gn:feature_class":"P",
    "gn:feature_code":"PPL",
    "gn:name":"Zhaoyang",
    "gn:population":0,
    "gn:timezone":"Asia/Shanghai",
    "iso:country":"CN",
    "name:zho_x_preferred":[
        "\u671d\u967d"
    ],
    "wof:name":"Zhaoyang",
    "wof:placetype":"locality"
},
  "geometry": {"coordinates":[113.11208999999999,22.93702],"type":"Point"}
}