{
  "type": "Feature",
  "properties": {
    "gn:admin1_code":"3.0",
    "gn:asciiname":"Laohejing",
    "gn:country_code":"CN",
    "gn:dem":300,
    "gn:feature_class":"P",
    "gn:feature_code":"PPL",
    "gn:name":"Laohejing",
    "gn:population":0,
    "gn:timezone":"Asia/Shanghai",
    "iso:country":"CN",
    "name:zho_x_preferred":[
        "\u8001\u6cb3\u8ff3"
    ],
    "wof:name":"Laohejing",
    "wof:placetype":"locality"
},
  "geometry": {"coordinates":[115.307,24.9826],"type":"Point"}
}