{
  "type": "Feature",
  "properties": {
    "gn:admin1_code":"30.0",
    "gn:asciiname":"Dongliaocun",
    "gn:country_code":"CN",
    "gn:dem":23,
    "gn:feature_class":"P",
    "gn:feature_code":"PPL",
    "gn:name":"Dongliaocun",
    "gn:population":0,
    "gn:timezone":"Asia/Shanghai",
    "iso:country":"CN",
    "name:zho_x_preferred":[
        "\u578c\u5bee\u6751"
    ],
    "wof:name":"Dongliaocun",
    "wof:placetype":"locality"
},
  "geometry": {"coordinates":[112.02334999999999,23.10908],"type":"Point"}
}