{
  "type": "Feature",
  "properties": {
    "gn:admin1_code":"14.0",
    "gn:asciiname":"Goinba",
    "gn:country_code":"CN",
    "gn:dem":3028,
    "gn:feature_class":"P",
    "gn:feature_code":"PPL",
    "gn:name":"Goinba",
    "gn:population":0,
    "gn:timezone":"Asia/Urumqi",
    "iso:country":"CN",
    "name:bod_x_preferred":[
        "Goinba"
    ],
    "name:zho_x_preferred":[
        "Gongba"
    ],
    "name:zho_x_variant":[
        "\u8d21\u5df4",
        "Gula Qu",
        "\u53e4\u62c9\u533a"
    ],
    "wof:name":"Goinba",
    "wof:placetype":"locality"
},
  "geometry": {"coordinates":[97.90300000000001,29.003],"type":"Point"}
}