{
  "type": "Feature",
  "properties": {
    "gn:admin1_code":"11",
    "gn:asciiname":"Dongzhou",
    "gn:country_code":"CN",
    "gn:dem":305,
    "gn:feature_class":"P",
    "gn:feature_code":"PPL",
    "gn:name":"Dongzhou",
    "gn:population":0,
    "gn:timezone":"Asia/Shanghai",
    "iso:country":"CN",
    "name:zho_x_preferred":[
        "\u52a8\u5468"
    ],
    "wof:name":"Dongzhou",
    "wof:placetype":"locality"
},
  "geometry": {"coordinates":[111.20358,25.13679],"type":"Point"}
}