{
  "type": "Feature",
  "properties": {
    "gn:admin1_code":"05",
    "gn:asciiname":"Hsin-an-p'ing",
    "gn:country_code":"CN",
    "gn:dem":73,
    "gn:feature_class":"P",
    "gn:feature_code":"PPL",
    "gn:name":"Hsin-an-p\u2019ing",
    "gn:population":0,
    "gn:timezone":"Asia/Shanghai",
    "iso:country":"CN",
    "wof:name":"Hsin-an-p'ing",
    "wof:placetype":"locality"
},
  "geometry": {"coordinates":[130.43556000000001,42.93556],"type":"Point"}
}