{
  "type": "Feature",
  "properties": {
    "gn:admin1_code":"15.0",
    "gn:asciiname":"Baiyangshu",
    "gn:country_code":"CN",
    "gn:dem":2108,
    "gn:feature_class":"P",
    "gn:feature_code":"PPL",
    "gn:name":"Baiyangshu",
    "gn:population":0,
    "gn:timezone":"Asia/Shanghai",
    "iso:country":"CN",
    "name:zho_x_preferred":[
        "\u67cf\u6768\u6811"
    ],
    "wof:name":"Baiyangshu",
    "wof:placetype":"locality"
},
  "geometry": {"coordinates":[100.34399999999999,38.6442],"type":"Point"}
}