{
  "type": "Feature",
  "properties": {
    "gn:admin1_code":"12.0",
    "gn:asciiname":"Wanjiachong",
    "gn:country_code":"CN",
    "gn:dem":42,
    "gn:feature_class":"P",
    "gn:feature_code":"PPL",
    "gn:name":"Wanjiachong",
    "gn:population":0,
    "gn:timezone":"Asia/Shanghai",
    "iso:country":"CN",
    "name:zho_x_preferred":[
        "Wanjiachong"
    ],
    "name:zho_x_variant":[
        "\u4e07\u5bb6\u51b2"
    ],
    "wof:name":"Wanjiachong",
    "wof:placetype":"locality"
},
  "geometry": {"coordinates":[111.87164,30.46891],"type":"Point"}
}