{
  "type": "Feature",
  "properties": {
    "gn:admin1_code":"25",
    "gn:asciiname":"Xialiyuan",
    "gn:country_code":"CN",
    "gn:dem":64,
    "gn:feature_class":"P",
    "gn:feature_code":"PPL",
    "gn:name":"Xialiyuan",
    "gn:population":0,
    "gn:timezone":"Asia/Shanghai",
    "iso:country":"CN",
    "name:zho_x_preferred":[
        "\u4e0b\u674e\u5143"
    ],
    "wof:name":"Xialiyuan",
    "wof:placetype":"locality"
},
  "geometry": {"coordinates":[119.965,36.8053],"type":"Point"}
}