{
  "type": "Feature",
  "properties": {
    "gn:admin1_code":"32.0",
    "gn:asciiname":"Na'er",
    "gn:country_code":"CN",
    "gn:dem":2523,
    "gn:feature_class":"P",
    "gn:feature_code":"PPL",
    "gn:name":"Na\u2019er",
    "gn:population":0,
    "gn:timezone":"Asia/Shanghai",
    "iso:country":"CN",
    "name:und_x_variant":[
        "Na\u2019er"
    ],
    "name:zho_x_preferred":[
        "\u7eb3\u5c14"
    ],
    "wof:name":"Na'er",
    "wof:placetype":"locality"
},
  "geometry": {"coordinates":[101.968,28.5205],"type":"Point"}
}