{
  "type": "Feature",
  "properties": {
    "gn:country":"CN",
    "gn:fcode":"ADM3",
    "gn:pop":0,
    "iso:country":"CN",
    "name:deu_x_preferred":[
        "Xunke"
    ],
    "name:eng_x_preferred":[
        "Xunke County"
    ],
    "name:fas_x_preferred":[
        "\u0634\u0647\u0631\u0633\u062a\u0627\u0646 \u0634\u0648\u0646\u06a9\u0647"
    ],
    "name:gan_x_preferred":[
        "\u900a\u514b\u53bf"
    ],
    "name:jpn_x_preferred":[
        "\u905c\u514b\u770c"
    ],
    "name:kor_x_preferred":[
        "\uc270\ucee4\ud604"
    ],
    "name:nan_x_preferred":[
        "S\u00f9n-khek-ko\u0101n"
    ],
    "name:nld_x_preferred":[
        "Xunke"
    ],
    "name:nob_x_preferred":[
        "Xunke"
    ],
    "name:rus_x_preferred":[
        "\u0421\u044e\u043d\u044c\u043a\u044d"
    ],
    "name:swe_x_preferred":[
        "Xunke"
    ],
    "name:unk_x_variant":[
        "Hs\u00fcn-k\u2019o Hsien"
    ],
    "name:vie_x_preferred":[
        "T\u1ed1n Kh\u1eafc"
    ],
    "name:wuu_x_preferred":[
        "\u900a\u514b\u53bf"
    ],
    "name:zho_x_preferred":[
        "\u900a\u514b\u53bf"
    ],
    "name:zho_x_variant":[
        "\u900a\u514b"
    ],
    "qs:name":"Xunke Xian",
    "qs:photos_9r":0,
    "qs:photos_sr":0,
    "qs:pop_sr":"0",
    "wd:wordcount":71,
    "wof:name":"Xunke Xian",
    "wof:placetype":"localadmin",
    "wof:population":0
},
  "geometry": {"coordinates":[128.35773,48.79716],"type":"Point"}
}