{
  "type": "Feature",
  "properties": {
    "gn:country":"CN",
    "gn:fcode":"ADM3",
    "gn:pop":0,
    "iso:country":"CN",
    "name:unk_x_variant":[
        "Hs\u00fcn-k\u2019o Hsien"
    ],
    "name:zho_x_preferred":[
        "\u900a\u514b\u53bf"
    ],
    "name:zho_x_variant":[
        "\u900a\u514b"
    ],
    "qs:name":"Xunke Xian",
    "qs:photos_9r":0,
    "qs:photos_sr":0,
    "qs:pop_sr":"0",
    "wd:wordcount":71,
    "wof:name":"Xunke Xian",
    "wof:placetype":"localadmin",
    "wof:population":0
},
  "geometry": {"coordinates":[128.35773,48.79716],"type":"Point"}
}