{
  "type": "Feature",
  "properties": {
    "gn:admin1_code":"24.0",
    "gn:asciiname":"Jiuloufan",
    "gn:country_code":"CN",
    "gn:dem":1182,
    "gn:feature_class":"P",
    "gn:feature_code":"PPL",
    "gn:name":"Jiuloufan",
    "gn:population":0,
    "gn:timezone":"Asia/Shanghai",
    "iso:country":"CN",
    "name:zho_x_preferred":[
        "\u65e7\u5a04\u70e6"
    ],
    "wof:name":"Jiuloufan",
    "wof:placetype":"locality"
},
  "geometry": {"coordinates":[111.84368000000001,38.09688],"type":"Point"}
}