{
  "type": "Feature",
  "properties": {
    "gn:admin1_code":"24.0",
    "gn:asciiname":"Shansanggou",
    "gn:country_code":"CN",
    "gn:dem":1093,
    "gn:feature_class":"P",
    "gn:feature_code":"PPL",
    "gn:name":"Shansanggou",
    "gn:population":0,
    "gn:timezone":"Asia/Shanghai",
    "iso:country":"CN",
    "name:zho_x_preferred":[
        "\u5c71\u6851\u6c9f"
    ],
    "wof:name":"Shansanggou",
    "wof:placetype":"locality"
},
  "geometry": {"coordinates":[111.90053,35.4339],"type":"Point"}
}