{
  "type": "Feature",
  "properties": {
    "gn:admin1_code":"12.0",
    "gn:asciiname":"Laowuwan",
    "gn:country_code":"CN",
    "gn:dem":58,
    "gn:feature_class":"P",
    "gn:feature_code":"PPL",
    "gn:name":"Laowuwan",
    "gn:population":0,
    "gn:timezone":"Asia/Shanghai",
    "iso:country":"CN",
    "name:und_x_variant":[
        "\u8001\u5c4b\u5846"
    ],
    "wof:name":"Laowuwan",
    "wof:placetype":"locality"
},
  "geometry": {"coordinates":[115.17709000000001,30.80765],"type":"Point"}
}