{
  "type": "Feature",
  "properties": {
    "gn:admin1_code":"2.0",
    "gn:asciiname":"Dujiaqiao",
    "gn:country_code":"CN",
    "gn:dem":6,
    "gn:feature_class":"P",
    "gn:feature_code":"PPL",
    "gn:name":"Dujiaqiao",
    "gn:population":0,
    "gn:timezone":"Asia/Shanghai",
    "iso:country":"CN",
    "name:und_x_variant":[
        "\u675c\u5bb6\u6865"
    ],
    "name:zho_x_preferred":[
        "Dujiaqiao"
    ],
    "wof:name":"Dujiaqiao",
    "wof:placetype":"locality"
},
  "geometry": {"coordinates":[119.98219,30.30567000000001],"type":"Point"}
}