{
  "type": "Feature",
  "properties": {
    "gn:admin1_code":"8.0",
    "gn:asciiname":"Dongshengcun",
    "gn:country_code":"CN",
    "gn:dem":228,
    "gn:feature_class":"P",
    "gn:feature_code":"PPL",
    "gn:name":"Dongshengcun",
    "gn:population":0,
    "gn:timezone":"Asia/Shanghai",
    "iso:country":"CN",
    "name:zho_x_preferred":[
        "\u4e1c\u5347\u6751"
    ],
    "wof:name":"Dongshengcun",
    "wof:placetype":"locality"
},
  "geometry": {"coordinates":[125.21305,47.9594],"type":"Point"}
}