{
  "type": "Feature",
  "properties": {
    "gn:admin1_code":"8.0",
    "gn:asciiname":"Qianhaitang",
    "gn:country_code":"CN",
    "gn:dem":187,
    "gn:feature_class":"P",
    "gn:feature_code":"PPL",
    "gn:name":"Qianhaitang",
    "gn:population":0,
    "gn:timezone":"Asia/Shanghai",
    "iso:country":"CN",
    "name:zho_x_preferred":[
        "\u524d\u6d77\u5858"
    ],
    "wof:name":"Qianhaitang",
    "wof:placetype":"locality"
},
  "geometry": {"coordinates":[124.69238,48.43436],"type":"Point"}
}