{
  "type": "Feature",
  "properties": {
    "gn:admin1_code":"9.0",
    "gn:asciiname":"Zhangpeng",
    "gn:country_code":"CN",
    "gn:dem":77,
    "gn:feature_class":"P",
    "gn:feature_code":"PPL",
    "gn:name":"Zhangpeng",
    "gn:population":0,
    "gn:timezone":"Asia/Shanghai",
    "iso:country":"CN",
    "name:zho_x_preferred":[
        "\u5f20\u68da"
    ],
    "wof:name":"Zhangpeng",
    "wof:placetype":"locality"
},
  "geometry": {"coordinates":[114.98224999999999,31.92966],"type":"Point"}
}