{
  "type": "Feature",
  "properties": {
    "gn:admin1_code":"7",
    "gn:asciiname":"Fengtou",
    "gn:country_code":"CN",
    "gn:dem":286,
    "gn:feature_class":"P",
    "gn:feature_code":"PPL",
    "gn:name":"Fengtou",
    "gn:population":0,
    "gn:timezone":"Asia/Shanghai",
    "iso:country":"CN",
    "name:und_x_variant":[
        "\u51e4\u5934"
    ],
    "wof:name":"Fengtou",
    "wof:placetype":"locality"
},
  "geometry": {"coordinates":[118.61248999999999,27.43969],"type":"Point"}
}