{
  "type": "Feature",
  "properties": {
    "gn:admin1_code":"15.0",
    "gn:asciiname":"Sihetai",
    "gn:country_code":"CN",
    "gn:dem":1434,
    "gn:feature_class":"P",
    "gn:feature_code":"PPL",
    "gn:name":"Sihetai",
    "gn:population":0,
    "gn:timezone":"Asia/Shanghai",
    "iso:country":"CN",
    "name:zho_x_preferred":[
        "\u56db\u5408\u53f0"
    ],
    "wof:name":"Sihetai",
    "wof:placetype":"locality"
},
  "geometry": {"coordinates":[108.41800000000001,36.3622],"type":"Point"}
}