{
  "type": "Feature",
  "properties": {
    "gn:admin1_code":"11.0",
    "gn:asciiname":"Wanzikou",
    "gn:country_code":"CN",
    "gn:dem":124,
    "gn:feature_class":"P",
    "gn:feature_code":"PPL",
    "gn:name":"Wanzikou",
    "gn:population":0,
    "gn:timezone":"Asia/Shanghai",
    "iso:country":"CN",
    "name:zho_x_preferred":[
        "\u6e7e\u5b50\u53e3"
    ],
    "wof:name":"Wanzikou",
    "wof:placetype":"locality"
},
  "geometry": {"coordinates":[113.59201000000002,26.77562],"type":"Point"}
}