{
  "type": "Feature",
  "properties": {
    "gn:admin1_code":"15.0",
    "gn:asciiname":"Yikeshu",
    "gn:country_code":"CN",
    "gn:dem":1383,
    "gn:feature_class":"P",
    "gn:feature_code":"PPL",
    "gn:name":"Yikeshu",
    "gn:population":0,
    "gn:timezone":"Asia/Shanghai",
    "iso:country":"CN",
    "name:zho_x_preferred":[
        "\u4e00\u68f5\u6811"
    ],
    "wof:name":"Yikeshu",
    "wof:placetype":"locality"
},
  "geometry": {"coordinates":[99.0091,39.649],"type":"Point"}
}