{
  "type": "Feature",
  "properties": {
    "gn:admin1_code":"19.0",
    "gn:asciiname":"Xiajingshi",
    "gn:country_code":"CN",
    "gn:dem":111,
    "gn:feature_class":"P",
    "gn:feature_code":"PPL",
    "gn:name":"Xiajingshi",
    "gn:population":0,
    "gn:timezone":"Asia/Shanghai",
    "iso:country":"CN",
    "name:zho_x_preferred":[
        "\u4e0b\u4e95\u77f3"
    ],
    "wof:name":"Xiajingshi",
    "wof:placetype":"locality"
},
  "geometry": {"coordinates":[123.986,43.0093],"type":"Point"}
}