{
  "type": "Feature",
  "properties": {
    "gn:admin1_code":"12.0",
    "gn:asciiname":"Kengshangyang",
    "gn:country_code":"CN",
    "gn:dem":34,
    "gn:feature_class":"P",
    "gn:feature_code":"PPL",
    "gn:name":"Kengshangyang",
    "gn:population":0,
    "gn:timezone":"Asia/Shanghai",
    "iso:country":"CN",
    "name:und_x_variant":[
        "\u5751\u4e0a\u6768"
    ],
    "wof:name":"Kengshangyang",
    "wof:placetype":"locality"
},
  "geometry": {"coordinates":[114.41417,30.37026],"type":"Point"}
}