{
  "type": "Feature",
  "properties": {
    "gn:admin1_code":"30.0",
    "gn:asciiname":"Jiazitang",
    "gn:country_code":"CN",
    "gn:dem":17,
    "gn:feature_class":"P",
    "gn:feature_code":"PPL",
    "gn:name":"Jiazitang",
    "gn:population":0,
    "gn:timezone":"Asia/Shanghai",
    "iso:country":"CN",
    "name:zho_x_preferred":[
        "\u7532\u5b50\u5858"
    ],
    "wof:name":"Jiazitang",
    "wof:placetype":"locality"
},
  "geometry": {"coordinates":[113.91316,22.73593],"type":"Point"}
}