{
  "type": "Feature",
  "properties": {
    "gn:admin1_code":"25",
    "gn:asciiname":"Wangxiangzhai",
    "gn:country_code":"CN",
    "gn:dem":62,
    "gn:feature_class":"P",
    "gn:feature_code":"PPL",
    "gn:name":"Wangxiangzhai",
    "gn:population":0,
    "gn:timezone":"Asia/Shanghai",
    "iso:country":"CN",
    "name:zho_x_preferred":[
        "\u738b\u7965\u5be8"
    ],
    "wof:name":"Wangxiangzhai",
    "wof:placetype":"locality"
},
  "geometry": {"coordinates":[115.13,35.0192],"type":"Point"}
}