{
  "type": "Feature",
  "properties": {
    "gn:admin1_code":"29.0",
    "gn:asciiname":"Hongmen",
    "gn:country_code":"CN",
    "gn:dem":1553,
    "gn:feature_class":"P",
    "gn:feature_code":"PPL",
    "gn:name":"Hongmen",
    "gn:population":0,
    "gn:timezone":"Asia/Shanghai",
    "iso:country":"CN",
    "name:zho_x_preferred":[
        "\u6d2a\u95e8"
    ],
    "wof:name":"Hongmen",
    "wof:placetype":"locality"
},
  "geometry": {"coordinates":[100.51900000000001,27.1993],"type":"Point"}
}