{
  "type": "Feature",
  "properties": {
    "gn:admin1_code":"3.0",
    "gn:asciiname":"Zhongxintang",
    "gn:country_code":"CN",
    "gn:dem":363,
    "gn:feature_class":"P",
    "gn:feature_code":"PPL",
    "gn:name":"Zhongxintang",
    "gn:population":0,
    "gn:timezone":"Asia/Shanghai",
    "iso:country":"CN",
    "name:und_x_variant":[
        "\u4e2d\u5fc3\u5858"
    ],
    "wof:name":"Zhongxintang",
    "wof:placetype":"locality"
},
  "geometry": {"coordinates":[115.75493,25.03004],"type":"Point"}
}