{
  "type": "Feature",
  "properties": {
    "gn:admin1_code":"12.0",
    "gn:asciiname":"Bailigang",
    "gn:country_code":"CN",
    "gn:dem":52,
    "gn:feature_class":"P",
    "gn:feature_code":"PPL",
    "gn:name":"Bailigang",
    "gn:population":0,
    "gn:timezone":"Asia/Shanghai",
    "iso:country":"CN",
    "name:zho_x_preferred":[
        "Bailigang"
    ],
    "name:zho_x_variant":[
        "\u767e\u91cc\u5c97"
    ],
    "wof:name":"Bailigang",
    "wof:placetype":"locality"
},
  "geometry": {"coordinates":[115.0788,30.58207],"type":"Point"}
}