{
  "type": "Feature",
  "properties": {
    "gn:admin1_code":"7.0",
    "gn:asciiname":"Xinfeng",
    "gn:country_code":"CN",
    "gn:dem":485,
    "gn:feature_class":"P",
    "gn:feature_code":"PPL",
    "gn:name":"Xinfeng",
    "gn:population":0,
    "gn:timezone":"Asia/Shanghai",
    "iso:country":"CN",
    "name:ceb_x_preferred":[
        "Xinfeng"
    ],
    "name:deu_x_preferred":[
        "Xinfeng"
    ],
    "name:fra_x_preferred":[
        "Xinfeng"
    ],
    "name:kor_x_preferred":[
        "\uc2e0\ud391\ud604"
    ],
    "name:nor_x_preferred":[
        "Xinfeng"
    ],
    "name:swe_x_preferred":[
        "Xinfeng"
    ],
    "name:zho_x_preferred":[
        "\u65b0\u5cf0"
    ],
    "wof:name":"Xinfeng",
    "wof:placetype":"locality"
},
  "geometry": {"coordinates":[116.28227,25.8951],"type":"Point"}
}