{
  "type": "Feature",
  "properties": {
    "gn:admin1_code":"30",
    "gn:asciiname":"Shishuikeng",
    "gn:country_code":"CN",
    "gn:dem":523,
    "gn:feature_class":"P",
    "gn:feature_code":"PPL",
    "gn:name":"Shishuikeng",
    "gn:population":0,
    "gn:timezone":"Asia/Shanghai",
    "iso:country":"CN",
    "name:zho_x_preferred":[
        "\u98df\u6c34\u5751"
    ],
    "wof:name":"Shishuikeng",
    "wof:placetype":"locality"
},
  "geometry": {"coordinates":[116.09967,23.97756],"type":"Point"}
}