{
  "type": "Feature",
  "properties": {
    "gn:admin1_code":"5.0",
    "gn:asciiname":"Shuanggangshan",
    "gn:country_code":"CN",
    "gn:dem":136,
    "gn:feature_class":"P",
    "gn:feature_code":"PPL",
    "gn:name":"Shuanggangshan",
    "gn:population":0,
    "gn:timezone":"Asia/Shanghai",
    "iso:country":"CN",
    "name:zho_x_preferred":[
        "\u53cc\u5c97\u5c71"
    ],
    "wof:name":"Shuanggangshan",
    "wof:placetype":"locality"
},
  "geometry": {"coordinates":[123.56596999999999,45.2598],"type":"Point"}
}