{
  "type": "Feature",
  "properties": {
    "gn:admin1_code":"33.0",
    "gn:asciiname":"Folingsi",
    "gn:country_code":"CN",
    "gn:dem":366,
    "gn:feature_class":"P",
    "gn:feature_code":"PPL",
    "gn:name":"Folingsi",
    "gn:population":0,
    "gn:timezone":"Asia/Shanghai",
    "iso:country":"CN",
    "name:zho_x_preferred":[
        "\u4f5b\u7075\u5bfa"
    ],
    "wof:name":"Folingsi",
    "wof:placetype":"locality"
},
  "geometry": {"coordinates":[105.4858,29.44571],"type":"Point"}
}