{
  "type": "Feature",
  "properties": {
    "gn:admin1_code":"19.0",
    "gn:asciiname":"Yangjia Wazicun",
    "gn:country_code":"CN",
    "gn:dem":39,
    "gn:feature_class":"P",
    "gn:feature_code":"PPL",
    "gn:name":"Yangjia Wazicun",
    "gn:population":0,
    "gn:timezone":"Asia/Shanghai",
    "iso:country":"CN",
    "name:zho_x_preferred":[
        "\u6768\u5bb6\u6d3c\u5b50\u6751"
    ],
    "wof:name":"Yangjia Wazicun",
    "wof:placetype":"locality"
},
  "geometry": {"coordinates":[120.869,40.8314],"type":"Point"}
}