{
  "type": "Feature",
  "properties": {
    "gn:admin1_code":"7.0",
    "gn:asciiname":"Zhuancang",
    "gn:country_code":"CN",
    "gn:dem":393,
    "gn:feature_class":"P",
    "gn:feature_code":"PPL",
    "gn:name":"Zhuancang",
    "gn:population":0,
    "gn:timezone":"Asia/Shanghai",
    "iso:country":"CN",
    "name:zho_x_preferred":[
        "\u7816\u4ed3"
    ],
    "wof:name":"Zhuancang",
    "wof:placetype":"locality"
},
  "geometry": {"coordinates":[119.42453999999999,26.28826],"type":"Point"}
}