{
  "type": "Feature",
  "properties": {
    "gn:admin1_code":"29.0",
    "gn:asciiname":"Hebatou",
    "gn:country_code":"CN",
    "gn:dem":813,
    "gn:feature_class":"P",
    "gn:feature_code":"PPL",
    "gn:name":"Hebatou",
    "gn:population":0,
    "gn:timezone":"Asia/Shanghai",
    "iso:country":"CN",
    "name:zho_x_preferred":[
        "\u6cb3\u575d\u5934"
    ],
    "wof:name":"Hebatou",
    "wof:placetype":"locality"
},
  "geometry": {"coordinates":[104.286,28.0095],"type":"Point"}
}