{
  "type": "Feature",
  "properties": {
    "gn:admin1_code":"19.0",
    "gn:asciiname":"Hansanjiacun",
    "gn:country_code":"CN",
    "gn:dem":12,
    "gn:feature_class":"P",
    "gn:feature_code":"PPL",
    "gn:name":"Hansanjiacun",
    "gn:population":0,
    "gn:timezone":"Asia/Shanghai",
    "iso:country":"CN",
    "name:zho_x_preferred":[
        "\u97e9\u4e09\u5bb6\u6751"
    ],
    "wof:name":"Hansanjiacun",
    "wof:placetype":"locality"
},
  "geometry": {"coordinates":[122.96212,41.73563],"type":"Point"}
}