{
  "type": "Feature",
  "properties": {
    "gn:admin1_code":"11",
    "gn:asciiname":"Muzhou",
    "gn:country_code":"CN",
    "gn:dem":133,
    "gn:feature_class":"P",
    "gn:feature_code":"PPL",
    "gn:name":"Muzhou",
    "gn:population":0,
    "gn:timezone":"Asia/Shanghai",
    "iso:country":"CN",
    "name:zho_x_preferred":[
        "\u6728\u6d32"
    ],
    "wof:name":"Muzhou",
    "wof:placetype":"locality"
},
  "geometry": {"coordinates":[110.26174,27.98391],"type":"Point"}
}