{
  "type": "Feature",
  "properties": {
    "gn:admin1_code":"25",
    "gn:asciiname":"Qingshui",
    "gn:cc2":"CN",
    "gn:country_code":"CN",
    "gn:dem":41,
    "gn:feature_class":"P",
    "gn:feature_code":"PPL",
    "gn:name":"Qingshui",
    "gn:population":0,
    "gn:timezone":"Asia/Shanghai",
    "iso:country":"CN",
    "name:ceb_x_preferred":[
        "Qingshui"
    ],
    "name:deu_x_preferred":[
        "Qingshui"
    ],
    "name:und_x_variant":[
        "Ch\u2019ing-shui",
        "Ch\u2019ing-shui-chi",
        "Chingshuipu"
    ],
    "wof:name":"Qingshui",
    "wof:placetype":"locality"
},
  "geometry": {"coordinates":[115.52167,36.61861],"type":"Point"}
}