{
  "type": "Feature",
  "properties": {
    "gn:admin1_code":"10.0",
    "gn:asciiname":"Dadijiu",
    "gn:country_code":"CN",
    "gn:dem":22,
    "gn:feature_class":"P",
    "gn:feature_code":"PPL",
    "gn:name":"Dadijiu",
    "gn:population":0,
    "gn:timezone":"Asia/Shanghai",
    "iso:country":"CN",
    "name:zho_x_preferred":[
        "\u5927\u7b2c\u4e5d"
    ],
    "wof:name":"Dadijiu",
    "wof:placetype":"locality"
},
  "geometry": {"coordinates":[116.37318999999999,37.63963],"type":"Point"}
}