{
  "type": "Feature",
  "properties": {
    "gn:admin1_code":"11.0",
    "gn:asciiname":"Jianglaowu",
    "gn:country_code":"CN",
    "gn:dem":82,
    "gn:feature_class":"P",
    "gn:feature_code":"PPL",
    "gn:name":"Jianglaowu",
    "gn:population":0,
    "gn:timezone":"Asia/Shanghai",
    "iso:country":"CN",
    "name:zho_x_preferred":[
        "\u848b\u8001\u5c4b"
    ],
    "wof:name":"Jianglaowu",
    "wof:placetype":"locality"
},
  "geometry": {"coordinates":[112.40798999999998,26.98526],"type":"Point"}
}