{
  "type": "Feature",
  "properties": {
    "gn:admin1_code":"14.0",
    "gn:asciiname":"Yatangcun",
    "gn:country_code":"CN",
    "gn:dem":4193,
    "gn:feature_class":"P",
    "gn:feature_code":"PPL",
    "gn:name":"Yatangcun",
    "gn:population":0,
    "gn:timezone":"Asia/Urumqi",
    "iso:country":"CN",
    "name:zho_x_preferred":[
        "\u4e9a\u5858\u6751"
    ],
    "wof:name":"Yatangcun",
    "wof:placetype":"locality"
},
  "geometry": {"coordinates":[92.8227,31.68291],"type":"Point"}
}