{
  "type": "Feature",
  "properties": {
    "gn:admin1_code":"26.0",
    "gn:asciiname":"Dalumaoliang",
    "gn:country_code":"CN",
    "gn:dem":1110,
    "gn:feature_class":"P",
    "gn:feature_code":"PPL",
    "gn:name":"Dalumaoliang",
    "gn:population":0,
    "gn:timezone":"Asia/Shanghai",
    "iso:country":"CN",
    "name:zho_x_preferred":[
        "\u5927\u8def\u5cc1\u6881"
    ],
    "wof:name":"Dalumaoliang",
    "wof:placetype":"locality"
},
  "geometry": {"coordinates":[110.98784999999999,39.41765],"type":"Point"}
}