{
  "type": "Feature",
  "properties": {
    "gn:admin1_code":"30",
    "gn:asciiname":"Tanmu Kuzai",
    "gn:country_code":"CN",
    "gn:dem":74,
    "gn:feature_class":"P",
    "gn:feature_code":"PPL",
    "gn:name":"Tanmu Kuzai",
    "gn:population":0,
    "gn:timezone":"Asia/Urumqi",
    "iso:country":"CN",
    "name:zho_x_preferred":[
        "\u6f6d\u76ee\u5800\u4ed4"
    ],
    "wof:name":"Tanmu Kuzai",
    "wof:placetype":"locality"
},
  "geometry": {"coordinates":[110.27536000000001,20.71618],"type":"Point"}
}