{
  "type": "Feature",
  "properties": {
    "gn:admin1_code":"30.0",
    "gn:asciiname":"Yuanguangcun",
    "gn:country_code":"CN",
    "gn:dem":9,
    "gn:feature_class":"P",
    "gn:feature_code":"PPL",
    "gn:name":"Yuanguangcun",
    "gn:population":0,
    "gn:timezone":"Asia/Shanghai",
    "iso:country":"CN",
    "name:zho_x_preferred":[
        "\u8fdc\u5149\u6751"
    ],
    "wof:name":"Yuanguangcun",
    "wof:placetype":"locality"
},
  "geometry": {"coordinates":[116.61493,23.54042],"type":"Point"}
}