{
  "type": "Feature",
  "properties": {
    "gn:admin1_code":"10",
    "gn:asciiname":"Jiecun",
    "gn:country_code":"CN",
    "gn:dem":87,
    "gn:feature_class":"P",
    "gn:feature_code":"PPL",
    "gn:name":"Jiecun",
    "gn:population":0,
    "gn:timezone":"Asia/Shanghai",
    "iso:country":"CN",
    "name:zho_x_preferred":[
        "\u89e3\u6751"
    ],
    "wof:name":"Jiecun",
    "wof:placetype":"locality"
},
  "geometry": {"coordinates":[114.51600000000001,37.4066],"type":"Point"}
}