{
  "type": "Feature",
  "properties": {
    "gn:admin1_code":"4.0",
    "gn:asciiname":"Chaoxing",
    "gn:country_code":"CN",
    "gn:dem":5,
    "gn:feature_class":"P",
    "gn:feature_code":"PPL",
    "gn:name":"Chaoxing",
    "gn:population":0,
    "gn:timezone":"Asia/Shanghai",
    "iso:country":"CN",
    "name:zho_x_preferred":[
        "\u8d85\u5e78"
    ],
    "wof:name":"Chaoxing",
    "wof:placetype":"locality"
},
  "geometry": {"coordinates":[120.1367,32.55751],"type":"Point"}
}