{
  "type": "Feature",
  "properties": {
    "gn:admin1_code":"12.0",
    "gn:asciiname":"Wangjia Laowu",
    "gn:country_code":"CN",
    "gn:dem":617,
    "gn:feature_class":"P",
    "gn:feature_code":"PPL",
    "gn:name":"Wangjia Laowu",
    "gn:population":0,
    "gn:timezone":"Asia/Shanghai",
    "iso:country":"CN",
    "name:zho_x_preferred":[
        "\u738b\u5bb6\u8001\u5c4b"
    ],
    "wof:name":"Wangjia Laowu",
    "wof:placetype":"locality"
},
  "geometry": {"coordinates":[111.27439,31.98008],"type":"Point"}
}