{
  "type": "Feature",
  "properties": {
    "gn:admin1_code":"32.0",
    "gn:asciiname":"Jiaba",
    "gn:country_code":"CN",
    "gn:dem":3092,
    "gn:feature_class":"P",
    "gn:feature_code":"PPL",
    "gn:name":"Jiaba",
    "gn:population":0,
    "gn:timezone":"Asia/Shanghai",
    "iso:country":"CN",
    "name:zho_x_preferred":[
        "\u7532\u575d"
    ],
    "wof:name":"Jiaba",
    "wof:placetype":"locality"
},
  "geometry": {"coordinates":[101.676,28.3995],"type":"Point"}
}