{
  "type": "Feature",
  "properties": {
    "gn:admin1_code":"30.0",
    "gn:asciiname":"Zhuzaibu",
    "gn:country_code":"CN",
    "gn:dem":164,
    "gn:feature_class":"P",
    "gn:feature_code":"PPL",
    "gn:name":"Zhuzaibu",
    "gn:population":0,
    "gn:timezone":"Asia/Shanghai",
    "iso:country":"CN",
    "name:zho_x_preferred":[
        "\u7af9\u4ed4\u5e03"
    ],
    "wof:name":"Zhuzaibu",
    "wof:placetype":"locality"
},
  "geometry": {"coordinates":[115.18264000000001,23.23831],"type":"Point"}
}