{
  "type": "Feature",
  "properties": {
    "gn:admin1_code":"29.0",
    "gn:asciiname":"Panxinlong",
    "gn:country_code":"CN",
    "gn:dem":1168,
    "gn:feature_class":"P",
    "gn:feature_code":"PPL",
    "gn:name":"Panxinlong",
    "gn:population":0,
    "gn:timezone":"Asia/Shanghai",
    "iso:country":"CN",
    "name:zho_x_preferred":[
        "\u76d8\u65b0\u9f99"
    ],
    "wof:name":"Panxinlong",
    "wof:placetype":"locality"
},
  "geometry": {"coordinates":[101.235,21.7161],"type":"Point"}
}