{
  "type": "Feature",
  "properties": {
    "gn:admin1_code":"19.0",
    "gn:asciiname":"Panjiadi",
    "gn:country_code":"CN",
    "gn:dem":119,
    "gn:feature_class":"P",
    "gn:feature_code":"PPL",
    "gn:name":"Panjiadi",
    "gn:population":0,
    "gn:timezone":"Asia/Shanghai",
    "iso:country":"CN",
    "name:und_x_variant":[
        "\u6f58\u5bb6\u5730"
    ],
    "wof:name":"Panjiadi",
    "wof:placetype":"locality"
},
  "geometry": {"coordinates":[123.96259000000001,40.63142],"type":"Point"}
}