{
  "type": "Feature",
  "properties": {
    "gn:admin1_code":"9.0",
    "gn:asciiname":"Weizhuang",
    "gn:country_code":"CN",
    "gn:dem":91,
    "gn:feature_class":"P",
    "gn:feature_code":"PPL",
    "gn:name":"Weizhuang",
    "gn:population":0,
    "gn:timezone":"Asia/Shanghai",
    "iso:country":"CN",
    "name:zho_x_preferred":[
        "\u9b4f\u5e84"
    ],
    "wof:name":"Weizhuang",
    "wof:placetype":"locality"
},
  "geometry": {"coordinates":[112.47651999999999,32.53811],"type":"Point"}
}