{
  "type": "Feature",
  "properties": {
    "gn:admin1_code":"14.0",
    "gn:asciiname":"Baseke",
    "gn:country_code":"CN",
    "gn:dem":3840,
    "gn:feature_class":"P",
    "gn:feature_code":"PPL",
    "gn:name":"Baseke",
    "gn:population":0,
    "gn:timezone":"Asia/Urumqi",
    "iso:country":"CN",
    "name:zho_x_preferred":[
        "\u5df4\u8272\u53ef"
    ],
    "wof:name":"Baseke",
    "wof:placetype":"locality"
},
  "geometry": {"coordinates":[97.37092,32.07986],"type":"Point"}
}