{
  "type": "Feature",
  "properties": {
    "gn:admin1_code":"14.0",
    "gn:asciiname":"Genongna",
    "gn:country_code":"CN",
    "gn:dem":4687,
    "gn:feature_class":"P",
    "gn:feature_code":"PPL",
    "gn:name":"Genongna",
    "gn:population":0,
    "gn:timezone":"Asia/Urumqi",
    "iso:country":"CN",
    "name:zho_x_preferred":[
        "\u683c\u5f04\u90a3"
    ],
    "wof:name":"Genongna",
    "wof:placetype":"locality"
},
  "geometry": {"coordinates":[93.521,31.85143],"type":"Point"}
}