{
  "type": "Feature",
  "properties": {
    "gn:admin1_code":"9.0",
    "gn:asciiname":"Xiaoyangzhuang",
    "gn:country_code":"CN",
    "gn:dem":216,
    "gn:feature_class":"P",
    "gn:feature_code":"PPL",
    "gn:name":"Xiaoyangzhuang",
    "gn:population":0,
    "gn:timezone":"Asia/Shanghai",
    "iso:country":"CN",
    "name:und_x_variant":[
        "\u5c0f\u6768\u5e84",
        "Xiaoyangzhuang"
    ],
    "wof:name":"Xiaoyangzhuang",
    "wof:placetype":"locality"
},
  "geometry": {"coordinates":[112.19794,33.06869],"type":"Point"}
}