{
  "type": "Feature",
  "properties": {
    "gn:admin1_code":"14.0",
    "gn:asciiname":"Shannan Nongchang",
    "gn:country_code":"CN",
    "gn:dem":3565,
    "gn:feature_class":"P",
    "gn:feature_code":"PPLF",
    "gn:name":"Shannan Nongchang",
    "gn:population":0,
    "gn:timezone":"Asia/Urumqi",
    "iso:country":"CN",
    "name:zho_x_preferred":[
        "\u5c71\u5357\u519c\u573a"
    ],
    "wof:name":"Shannan Nongchang",
    "wof:placetype":"locality"
},
  "geometry": {"coordinates":[91.52061999999999,29.31945],"type":"Point"}
}