{
  "type": "Feature",
  "properties": {
    "gn:admin1_code":"5.0",
    "gn:asciiname":"Wujiayingcun",
    "gn:country_code":"CN",
    "gn:dem":825,
    "gn:feature_class":"P",
    "gn:feature_code":"PPL",
    "gn:name":"Wujiayingcun",
    "gn:population":0,
    "gn:timezone":"Asia/Shanghai",
    "iso:country":"CN",
    "name:zho_x_preferred":[
        "\u5434\u5bb6\u8425\u6751"
    ],
    "wof:name":"Wujiayingcun",
    "wof:placetype":"locality"
},
  "geometry": {"coordinates":[127.21854,41.75088],"type":"Point"}
}