{
  "type": "Feature",
  "properties": {
    "gn:admin1_code":"15.0",
    "gn:asciiname":"Lijiatai",
    "gn:country_code":"CN",
    "gn:dem":1973,
    "gn:feature_class":"P",
    "gn:feature_code":"PPL",
    "gn:name":"Lijiatai",
    "gn:population":0,
    "gn:timezone":"Asia/Shanghai",
    "iso:country":"CN",
    "name:zho_x_preferred":[
        "\u674e\u5bb6\u53f0"
    ],
    "wof:name":"Lijiatai",
    "wof:placetype":"locality"
},
  "geometry": {"coordinates":[103.408,37.4554],"type":"Point"}
}