{
  "type": "Feature",
  "properties": {
    "gn:admin1_code":"8.0",
    "gn:asciiname":"Laogaitun",
    "gn:country_code":"CN",
    "gn:dem":210,
    "gn:feature_class":"P",
    "gn:feature_code":"PPL",
    "gn:name":"Laogaitun",
    "gn:population":0,
    "gn:timezone":"Asia/Shanghai",
    "iso:country":"CN",
    "name:zho_x_preferred":[
        "\u8001\u76d6\u5c6f"
    ],
    "wof:name":"Laogaitun",
    "wof:placetype":"locality"
},
  "geometry": {"coordinates":[127.61506,47.07845],"type":"Point"}
}