{
  "type": "Feature",
  "properties": {
    "gn:admin1_code":"29.0",
    "gn:asciiname":"Akedi",
    "gn:country_code":"CN",
    "gn:dem":1874,
    "gn:feature_class":"P",
    "gn:feature_code":"PPL",
    "gn:name":"Akedi",
    "gn:population":0,
    "gn:timezone":"Asia/Shanghai",
    "iso:country":"CN",
    "name:zho_x_preferred":[
        "\u963f\u514b\u5730"
    ],
    "wof:name":"Akedi",
    "wof:placetype":"locality"
},
  "geometry": {"coordinates":[100.47799999999999,24.9497],"type":"Point"}
}