{
  "type": "Feature",
  "properties": {
    "gn:admin1_code":"30.0",
    "gn:asciiname":"Liaoqian",
    "gn:country_code":"CN",
    "gn:dem":321,
    "gn:feature_class":"P",
    "gn:feature_code":"PPL",
    "gn:name":"Liaoqian",
    "gn:population":0,
    "gn:timezone":"Asia/Shanghai",
    "iso:country":"CN",
    "name:zho_x_preferred":[
        "\u5ed6\u524d"
    ],
    "wof:name":"Liaoqian",
    "wof:placetype":"locality"
},
  "geometry": {"coordinates":[112.55226999999999,23.74232],"type":"Point"}
}