{
  "type": "Feature",
  "properties": {
    "gn:admin1_code":"8.0",
    "gn:asciiname":"Juchengcun",
    "gn:country_code":"CN",
    "gn:dem":175,
    "gn:feature_class":"P",
    "gn:feature_code":"PPL",
    "gn:name":"Juchengcun",
    "gn:population":0,
    "gn:timezone":"Asia/Shanghai",
    "iso:country":"CN",
    "name:zho_x_preferred":[
        "\u5de8\u6210\u6751"
    ],
    "wof:name":"Juchengcun",
    "wof:placetype":"locality"
},
  "geometry": {"coordinates":[125.80328,45.99042],"type":"Point"}
}