{
  "type": "Feature",
  "properties": {
    "gn:admin1_code":"32.0",
    "gn:asciiname":"Anhuai",
    "gn:country_code":"CN",
    "gn:dem":283,
    "gn:feature_class":"P",
    "gn:feature_code":"PPL",
    "gn:name":"Anhuai",
    "gn:population":0,
    "gn:timezone":"Asia/Shanghai",
    "iso:country":"CN",
    "name:zho_x_preferred":[
        "\u5b89\u6000"
    ],
    "wof:name":"Anhuai",
    "wof:placetype":"locality"
},
  "geometry": {"coordinates":[105.21899999999999,29.0161],"type":"Point"}
}