{
  "type": "Feature",
  "properties": {
    "gn:admin1_code":"16.0",
    "gn:asciiname":"Xiaodafa",
    "gn:country_code":"CN",
    "gn:dem":434,
    "gn:feature_class":"P",
    "gn:feature_code":"PPL",
    "gn:name":"Xiaodafa",
    "gn:population":0,
    "gn:timezone":"Asia/Shanghai",
    "iso:country":"CN",
    "name:zho_x_preferred":[
        "\u5c0f\u8fbe\u53d1"
    ],
    "wof:name":"Xiaodafa",
    "wof:placetype":"locality"
},
  "geometry": {"coordinates":[106.849,24.7089],"type":"Point"}
}