{
  "type": "Feature",
  "properties": {
    "gn:admin1_code":"30",
    "gn:asciiname":"Mukengdong",
    "gn:country_code":"CN",
    "gn:dem":62,
    "gn:feature_class":"P",
    "gn:feature_code":"PPL",
    "gn:name":"Mukengdong",
    "gn:population":0,
    "gn:timezone":"Asia/Urumqi",
    "iso:country":"CN",
    "name:zho_x_preferred":[
        "\u6728\u5751\u578c"
    ],
    "wof:name":"Mukengdong",
    "wof:placetype":"locality"
},
  "geometry": {"coordinates":[110.66654,22.06973],"type":"Point"}
}