{
  "type": "Feature",
  "properties": {
    "gn:admin1_code":"19.0",
    "gn:asciiname":"Sunjiatuncun",
    "gn:country_code":"CN",
    "gn:dem":93,
    "gn:feature_class":"P",
    "gn:feature_code":"PPL",
    "gn:name":"Sunjiatuncun",
    "gn:population":0,
    "gn:timezone":"Asia/Shanghai",
    "iso:country":"CN",
    "name:zho_x_preferred":[
        "\u5b59\u5bb6\u5c6f\u6751"
    ],
    "wof:name":"Sunjiatuncun",
    "wof:placetype":"locality"
},
  "geometry": {"coordinates":[123.45208,42.63451],"type":"Point"}
}