{
  "type": "Feature",
  "properties": {
    "gn:admin1_code":"9.0",
    "gn:asciiname":"Yulin",
    "gn:country_code":"CN",
    "gn:dem":105,
    "gn:feature_class":"P",
    "gn:feature_code":"PPL",
    "gn:name":"Yulin",
    "gn:population":0,
    "gn:timezone":"Asia/Shanghai",
    "iso:country":"CN",
    "name:ceb_x_preferred":[
        "Yulin"
    ],
    "name:deu_x_preferred":[
        "Yulin"
    ],
    "name:eus_x_preferred":[
        "Yulin"
    ],
    "name:fin_x_preferred":[
        "Yulin"
    ],
    "name:fra_x_preferred":[
        "Yulin"
    ],
    "name:heb_x_preferred":[
        "\u05d9\u05d5\u05dc\u05d9\u05df"
    ],
    "name:hun_x_preferred":[
        "J\u00fclin"
    ],
    "name:kor_x_preferred":[
        "\uc704\ub9b0\uc2dc"
    ],
    "name:nld_x_preferred":[
        "Yulin"
    ],
    "name:nor_x_preferred":[
        "Yulin"
    ],
    "name:pol_x_preferred":[
        "Yulin"
    ],
    "name:por_x_preferred":[
        "Yulin"
    ],
    "name:rus_x_preferred":[
        "\u042e\u0439\u043b\u0438\u043d\u044c"
    ],
    "name:spa_x_preferred":[
        "Yulin"
    ],
    "name:swe_x_preferred":[
        "Yulin"
    ],
    "name:tur_x_preferred":[
        "Yulin"
    ],
    "name:zho_x_preferred":[
        "\u6986\u6797"
    ],
    "wof:name":"Yulin",
    "wof:placetype":"locality"
},
  "geometry": {"coordinates":[112.13946,32.64762],"type":"Point"}
}