{
  "type": "Feature",
  "properties": {
    "gn:admin1_code":"18.0",
    "gn:asciiname":"Yinguo",
    "gn:country_code":"CN",
    "gn:dem":469,
    "gn:feature_class":"P",
    "gn:feature_code":"PPL",
    "gn:name":"Yinguo",
    "gn:population":0,
    "gn:timezone":"Asia/Shanghai",
    "iso:country":"CN",
    "name:zho_x_preferred":[
        "\u5f15\u679c"
    ],
    "wof:name":"Yinguo",
    "wof:placetype":"locality"
},
  "geometry": {"coordinates":[108.601,25.6873],"type":"Point"}
}