{
  "type": "Feature",
  "properties": {
    "gn:admin1_code":"02",
    "gn:asciiname":"Zhongjiashacun",
    "gn:country_code":"CN",
    "gn:dem":26,
    "gn:feature_class":"P",
    "gn:feature_code":"PPL",
    "gn:name":"Zhongjiashacun",
    "gn:population":0,
    "gn:timezone":"Asia/Shanghai",
    "iso:country":"CN",
    "name:und_x_variant":[
        "Chung-chia-sha",
        "Zhongjiasha",
        "Zhongjiashacun"
    ],
    "name:zho_x_preferred":[
        "\u949f\u5bb6\u6c99\u6751"
    ],
    "wof:name":"Zhongjiashacun",
    "wof:placetype":"locality"
},
  "geometry": {"coordinates":[121.67572,29.83148],"type":"Point"}
}