{
  "type": "Feature",
  "properties": {
    "gn:admin1_code":"19.0",
    "gn:asciiname":"Beishangcun",
    "gn:country_code":"CN",
    "gn:dem":61,
    "gn:feature_class":"P",
    "gn:feature_code":"PPL",
    "gn:name":"Beishangcun",
    "gn:population":0,
    "gn:timezone":"Asia/Shanghai",
    "iso:country":"CN",
    "name:zho_x_preferred":[
        "\u7891\u4e0a\u6751"
    ],
    "wof:name":"Beishangcun",
    "wof:placetype":"locality"
},
  "geometry": {"coordinates":[123.032,39.8994],"type":"Point"}
}