{
  "type": "Feature",
  "properties": {
    "gn:admin1_code":"19.0",
    "gn:asciiname":"Mengjia Pozi",
    "gn:country_code":"CN",
    "gn:dem":24,
    "gn:feature_class":"P",
    "gn:feature_code":"PPL",
    "gn:name":"Mengjia Pozi",
    "gn:population":0,
    "gn:timezone":"Asia/Shanghai",
    "iso:country":"CN",
    "name:zho_x_preferred":[
        "\u5b5f\u5bb6\u5761\u5b50"
    ],
    "wof:name":"Mengjia Pozi",
    "wof:placetype":"locality"
},
  "geometry": {"coordinates":[123.19193,39.7912],"type":"Point"}
}