{
  "type": "Feature",
  "properties": {
    "gn:admin1_code":"9.0",
    "gn:asciiname":"Heihumiao",
    "gn:country_code":"CN",
    "gn:dem":237,
    "gn:feature_class":"P",
    "gn:feature_code":"PPL",
    "gn:name":"Heihumiao",
    "gn:population":0,
    "gn:timezone":"Asia/Shanghai",
    "iso:country":"CN",
    "name:und_x_variant":[
        "\u9ed1\u864e\u5e99",
        "Heihumiao"
    ],
    "wof:name":"Heihumiao",
    "wof:placetype":"locality"
},
  "geometry": {"coordinates":[112.3222,33.38737],"type":"Point"}
}