{
  "type": "Feature",
  "properties": {
    "gn:admin1_code":"7.0",
    "gn:asciiname":"Yinkeng",
    "gn:country_code":"CN",
    "gn:dem":524,
    "gn:feature_class":"P",
    "gn:feature_code":"PPL",
    "gn:name":"Yinkeng",
    "gn:population":0,
    "gn:timezone":"Asia/Shanghai",
    "iso:country":"CN",
    "name:zho_x_preferred":[
        "\u94f6\u5751"
    ],
    "wof:name":"Yinkeng",
    "wof:placetype":"locality"
},
  "geometry": {"coordinates":[117.16413,27.2417],"type":"Point"}
}