{
  "type": "Feature",
  "properties": {
    "gn:admin1_code":"32.0",
    "gn:asciiname":"Maliushan",
    "gn:country_code":"CN",
    "gn:dem":1363,
    "gn:feature_class":"P",
    "gn:feature_code":"PPL",
    "gn:name":"Maliushan",
    "gn:population":0,
    "gn:timezone":"Asia/Shanghai",
    "iso:country":"CN",
    "name:zho_x_preferred":[
        "\u9ebb\u67f3\u5c71"
    ],
    "wof:name":"Maliushan",
    "wof:placetype":"locality"
},
  "geometry": {"coordinates":[104.4332,32.44902],"type":"Point"}
}