{
  "type": "Feature",
  "properties": {
    "gn:admin1_code":"31.0",
    "gn:asciiname":"Lin'e",
    "gn:country_code":"CN",
    "gn:dem":63,
    "gn:feature_class":"P",
    "gn:feature_code":"PPL",
    "gn:name":"Lin\u2019e",
    "gn:population":0,
    "gn:timezone":"Asia/Shanghai",
    "iso:country":"CN",
    "name:zho_x_preferred":[
        "Lin\u2019e"
    ],
    "name:zho_x_variant":[
        "\u6797\u5ce8"
    ],
    "wof:name":"Lin'e",
    "wof:placetype":"locality"
},
  "geometry": {"coordinates":[109.95886000000002,19.64412],"type":"Point"}
}