{
  "type": "Feature",
  "properties": {
    "gn:admin1_code":"7",
    "gn:asciiname":"Dapingshui",
    "gn:country_code":"CN",
    "gn:dem":368,
    "gn:feature_class":"P",
    "gn:feature_code":"PPL",
    "gn:name":"Dapingshui",
    "gn:population":0,
    "gn:timezone":"Asia/Shanghai",
    "iso:country":"CN",
    "name:zho_x_preferred":[
        "\u5927\u576a\u6c34"
    ],
    "wof:name":"Dapingshui",
    "wof:placetype":"locality"
},
  "geometry": {"coordinates":[117.32832999999999,24.11778],"type":"Point"}
}