{
  "type": "Feature",
  "properties": {
    "gn:admin1_code":"5.0",
    "gn:asciiname":"Angelaicun",
    "gn:country_code":"CN",
    "gn:dem":161,
    "gn:feature_class":"P",
    "gn:feature_code":"PPL",
    "gn:name":"Angelaicun",
    "gn:population":0,
    "gn:timezone":"Asia/Shanghai",
    "iso:country":"CN",
    "name:zho_x_preferred":[
        "\u6602\u683c\u8d49\u6751"
    ],
    "wof:name":"Angelaicun",
    "wof:placetype":"locality"
},
  "geometry": {"coordinates":[123.96319,44.51425],"type":"Point"}
}