{
  "type": "Feature",
  "properties": {
    "gn:admin1_code":"21.0",
    "gn:asciiname":"Xijiao",
    "gn:country_code":"CN",
    "gn:dem":1744,
    "gn:feature_class":"P",
    "gn:feature_code":"PPLA4",
    "gn:name":"Xijiao",
    "gn:population":0,
    "gn:timezone":"Asia/Shanghai",
    "iso:country":"CN",
    "name:und_x_variant":[
        "\u897f\u90ca",
        "Xijiao Xiang",
        "\u897f\u90ca\u4e61"
    ],
    "wof:name":"Xijiao",
    "wof:placetype":"locality"
},
  "geometry": {"coordinates":[106.27613999999998,36.00958],"type":"Point"}
}