{
  "type": "Feature",
  "properties": {
    "gn:admin1_code":"8.0",
    "gn:asciiname":"Zhuchangtun",
    "gn:country_code":"CN",
    "gn:dem":136,
    "gn:feature_class":"P",
    "gn:feature_code":"PPLF",
    "gn:name":"Zhuchangtun",
    "gn:population":0,
    "gn:timezone":"Asia/Shanghai",
    "iso:country":"CN",
    "name:zho_x_preferred":[
        "\u732a\u573a\u5c6f"
    ],
    "wof:name":"Zhuchangtun",
    "wof:placetype":"locality"
},
  "geometry": {"coordinates":[123.51648,46.28441],"type":"Point"}
}