{
  "type": "Feature",
  "properties": {
    "gn:admin1_code":"19.0",
    "gn:asciiname":"Jiajiabu",
    "gn:country_code":"CN",
    "gn:dem":28,
    "gn:feature_class":"P",
    "gn:feature_code":"PPL",
    "gn:name":"Jiajiabu",
    "gn:population":0,
    "gn:timezone":"Asia/Shanghai",
    "iso:country":"CN",
    "name:und_x_variant":[
        "Jiajiabao",
        "Jiajiabu"
    ],
    "name:zho_x_preferred":[
        "\u8d3e\u5bb6\u5821"
    ],
    "wof:name":"Jiajiabu",
    "wof:placetype":"locality"
},
  "geometry": {"coordinates":[123.65805,40.04414000000001],"type":"Point"}
}