{
  "type": "Feature",
  "properties": {
    "gn:admin1_code":"24.0",
    "gn:asciiname":"Wufengcun",
    "gn:country_code":"CN",
    "gn:dem":1552,
    "gn:feature_class":"P",
    "gn:feature_code":"PPL",
    "gn:name":"Wufengcun",
    "gn:population":0,
    "gn:timezone":"Asia/Shanghai",
    "iso:country":"CN",
    "name:zho_x_preferred":[
        "\u4e94\u5c01\u6751"
    ],
    "wof:name":"Wufengcun",
    "wof:placetype":"locality"
},
  "geometry": {"coordinates":[112.45001000000001,37.00897],"type":"Point"}
}