{
  "type": "Feature",
  "properties": {
    "gn:admin1_code":"1.0",
    "gn:asciiname":"Gao'ancun",
    "gn:country_code":"CN",
    "gn:dem":8,
    "gn:feature_class":"P",
    "gn:feature_code":"PPL",
    "gn:name":"Gao\u2019ancun",
    "gn:population":0,
    "gn:timezone":"Asia/Shanghai",
    "iso:country":"CN",
    "name:und_x_variant":[
        "Gao\u2019ancun"
    ],
    "name:zho_x_preferred":[
        "\u9ad8\u5b89\u6751"
    ],
    "wof:name":"Gao'ancun",
    "wof:placetype":"locality"
},
  "geometry": {"coordinates":[118.10509,31.21512],"type":"Point"}
}