{
  "type": "Feature",
  "properties": {
    "gn:admin1_code":"2.0",
    "gn:asciiname":"Gendixian",
    "gn:country_code":"CN",
    "gn:dem":711,
    "gn:feature_class":"P",
    "gn:feature_code":"PPL",
    "gn:name":"Gendixian",
    "gn:population":0,
    "gn:timezone":"Asia/Shanghai",
    "iso:country":"CN",
    "name:zho_x_preferred":[
        "\u6839\u5e95\u5c98"
    ],
    "wof:name":"Gendixian",
    "wof:placetype":"locality"
},
  "geometry": {"coordinates":[119.65093,27.81256],"type":"Point"}
}