{
  "type": "Feature",
  "properties": {
    "gn:admin1_code":"6.0",
    "gn:asciiname":"Yaoluo",
    "gn:country_code":"CN",
    "gn:dem":2730,
    "gn:feature_class":"P",
    "gn:feature_code":"PPL",
    "gn:name":"Yaoluo",
    "gn:population":0,
    "gn:timezone":"Asia/Shanghai",
    "iso:country":"CN",
    "name:und_x_variant":[
        "\u8981\u6d1b"
    ],
    "wof:name":"Yaoluo",
    "wof:placetype":"locality"
},
  "geometry": {"coordinates":[100.5099,35.88487],"type":"Point"}
}