{
  "type": "Feature",
  "properties": {
    "gn:admin1_code":"25",
    "gn:asciiname":"Xiangchengmiao",
    "gn:country_code":"CN",
    "gn:dem":22,
    "gn:feature_class":"P",
    "gn:feature_code":"PPL",
    "gn:name":"Xiangchengmiao",
    "gn:population":0,
    "gn:timezone":"Asia/Shanghai",
    "iso:country":"CN",
    "name:zho_x_preferred":[
        "\u4e61\u57ce\u5e99"
    ],
    "wof:name":"Xiangchengmiao",
    "wof:placetype":"locality"
},
  "geometry": {"coordinates":[120.47,37.6713],"type":"Point"}
}