{
  "type": "Feature",
  "properties": {
    "gn:admin1_code":"32.0",
    "gn:asciiname":"Chunshu",
    "gn:country_code":"CN",
    "gn:dem":573,
    "gn:feature_class":"P",
    "gn:feature_code":"PPL",
    "gn:name":"Chunshu",
    "gn:population":0,
    "gn:timezone":"Asia/Shanghai",
    "iso:country":"CN",
    "name:zho_x_preferred":[
        "\u693f\u6811"
    ],
    "wof:name":"Chunshu",
    "wof:placetype":"locality"
},
  "geometry": {"coordinates":[106.87,31.7991],"type":"Point"}
}