{
  "type": "Feature",
  "properties": {
    "gn:admin1_code":"29.0",
    "gn:asciiname":"Maguan",
    "gn:country_code":"CN",
    "gn:dem":2646,
    "gn:feature_class":"P",
    "gn:feature_code":"PPL",
    "gn:name":"Maguan",
    "gn:population":0,
    "gn:timezone":"Asia/Shanghai",
    "iso:country":"CN",
    "name:zho_x_preferred":[
        "\u9ebb\u5b98"
    ],
    "wof:name":"Maguan",
    "wof:placetype":"locality"
},
  "geometry": {"coordinates":[99.8908,26.9728],"type":"Point"}
}