{
  "type": "Feature",
  "properties": {
    "gn:admin1_code":"16.0",
    "gn:asciiname":"Dahebei",
    "gn:country_code":"CN",
    "gn:dem":245,
    "gn:feature_class":"P",
    "gn:feature_code":"PPL",
    "gn:name":"Dahebei",
    "gn:population":0,
    "gn:timezone":"Asia/Shanghai",
    "iso:country":"CN",
    "name:zho_x_preferred":[
        "\u5927\u4f55\u80cc"
    ],
    "wof:name":"Dahebei",
    "wof:placetype":"locality"
},
  "geometry": {"coordinates":[110.961,24.0688],"type":"Point"}
}