{
  "type": "Feature",
  "properties": {
    "gn:admin1_code":"12.0",
    "gn:asciiname":"Sanhe Chang",
    "gn:country_code":"CN",
    "gn:dem":44,
    "gn:feature_class":"P",
    "gn:feature_code":"PPL",
    "gn:name":"Sanhe Chang",
    "gn:population":0,
    "gn:timezone":"Asia/Shanghai",
    "iso:country":"CN",
    "name:zho_x_preferred":[
        "\u4e09\u5408\u573a"
    ],
    "wof:name":"Sanhe Chang",
    "wof:placetype":"locality"
},
  "geometry": {"coordinates":[112.62994999999999,30.63822],"type":"Point"}
}