{
  "type": "Feature",
  "properties": {
    "gn:admin1_code":"29.0",
    "gn:asciiname":"Duoguo",
    "gn:country_code":"CN",
    "gn:dem":1840,
    "gn:feature_class":"P",
    "gn:feature_code":"PPL",
    "gn:name":"Duoguo",
    "gn:population":0,
    "gn:timezone":"Asia/Shanghai",
    "iso:country":"CN",
    "name:zho_x_preferred":[
        "\u6735\u679c"
    ],
    "wof:name":"Duoguo",
    "wof:placetype":"locality"
},
  "geometry": {"coordinates":[100.613,26.4282],"type":"Point"}
}