{
  "type": "Feature",
  "properties": {
    "gn:admin1_code":"6.0",
    "gn:asciiname":"Qingquan",
    "gn:country_code":"CN",
    "gn:dem":3222,
    "gn:feature_class":"P",
    "gn:feature_code":"PPL",
    "gn:name":"Qingquan",
    "gn:population":0,
    "gn:timezone":"Asia/Urumqi",
    "iso:country":"CN",
    "name:zho_x_preferred":[
        "\u6e05\u6cc9"
    ],
    "wof:name":"Qingquan",
    "wof:placetype":"locality"
},
  "geometry": {"coordinates":[97.41982,35.95043],"type":"Point"}
}