{
  "type": "Feature",
  "properties": {
    "gn:admin1_code":"30",
    "gn:asciiname":"Shijizui",
    "gn:country_code":"CN",
    "gn:dem":21,
    "gn:feature_class":"P",
    "gn:feature_code":"PPL",
    "gn:name":"Shijizui",
    "gn:population":0,
    "gn:timezone":"Asia/Shanghai",
    "iso:country":"CN",
    "name:zho_x_preferred":[
        "\u77f3\u57fa\u5480"
    ],
    "wof:name":"Shijizui",
    "wof:placetype":"locality"
},
  "geometry": {"coordinates":[112.40539,21.74184],"type":"Point"}
}