{
  "type": "Feature",
  "properties": {
    "gn:admin1_code":"32.0",
    "gn:asciiname":"Yingshuiba",
    "gn:country_code":"CN",
    "gn:dem":1718,
    "gn:feature_class":"P",
    "gn:feature_code":"PPL",
    "gn:name":"Yingshuiba",
    "gn:population":0,
    "gn:timezone":"Asia/Shanghai",
    "iso:country":"CN",
    "name:zho_x_preferred":[
        "\u6620\u6c34\u575d"
    ],
    "wof:name":"Yingshuiba",
    "wof:placetype":"locality"
},
  "geometry": {"coordinates":[106.999,32.7059],"type":"Point"}
}