{
  "type": "Feature",
  "properties": {
    "gn:admin1_code":"10.0",
    "gn:asciiname":"Xinjing",
    "gn:cc2":"CN",
    "gn:country_code":"CN",
    "gn:dem":284,
    "gn:feature_class":"P",
    "gn:feature_code":"PPL",
    "gn:name":"Xinjing",
    "gn:population":0,
    "gn:timezone":"Asia/Shanghai",
    "iso:country":"CN",
    "name:deu_x_preferred":[
        "Xinjing"
    ],
    "name:und_x_variant":[
        "Hsin-ch\u2019ing"
    ],
    "wof:name":"Xinjing",
    "wof:placetype":"locality"
},
  "geometry": {"coordinates":[114.05,38.13333],"type":"Point"}
}