{
  "type": "Feature",
  "properties": {
    "gn:admin1_code":"16.0",
    "gn:asciiname":"Dingguanjing",
    "gn:country_code":"CN",
    "gn:dem":6,
    "gn:feature_class":"P",
    "gn:feature_code":"PPL",
    "gn:name":"Dingguanjing",
    "gn:population":0,
    "gn:timezone":"Asia/Shanghai",
    "iso:country":"CN",
    "name:zho_x_preferred":[
        "\u4e01\u5173\u4e95"
    ],
    "wof:name":"Dingguanjing",
    "wof:placetype":"locality"
},
  "geometry": {"coordinates":[109.218,21.4702],"type":"Point"}
}