{
  "type": "Feature",
  "properties": {
    "gn:admin1_code":"12.0",
    "gn:asciiname":"Xinwu",
    "gn:country_code":"CN",
    "gn:dem":602,
    "gn:feature_class":"P",
    "gn:feature_code":"PPL",
    "gn:name":"Xinwu",
    "gn:population":0,
    "gn:timezone":"Asia/Shanghai",
    "iso:country":"CN",
    "name:zho_x_preferred":[
        "Xinwu"
    ],
    "name:zho_x_variant":[
        "\u65b0\u5c4b"
    ],
    "wof:name":"Xinwu",
    "wof:placetype":"locality"
},
  "geometry": {"coordinates":[114.13460000000001,29.39634],"type":"Point"}
}