{
  "type": "Feature",
  "properties": {
    "gn:admin1_code":"18",
    "gn:asciiname":"Lengshui",
    "gn:country_code":"CN",
    "gn:dem":1103,
    "gn:feature_class":"P",
    "gn:feature_code":"PPL",
    "gn:name":"Lengshui",
    "gn:population":0,
    "gn:timezone":"Asia/Shanghai",
    "iso:country":"CN",
    "name:zho_x_preferred":[
        "\u51b7\u6c34"
    ],
    "wof:name":"Lengshui",
    "wof:placetype":"locality"
},
  "geometry": {"coordinates":[106.83199999999999,25.9192],"type":"Point"}
}