{
  "type": "Feature",
  "properties": {
    "gn:admin1_code":"10",
    "gn:asciiname":"Zhangkuan",
    "gn:country_code":"CN",
    "gn:dem":81,
    "gn:feature_class":"P",
    "gn:feature_code":"PPL",
    "gn:name":"Zhangkuan",
    "gn:population":0,
    "gn:timezone":"Asia/Shanghai",
    "iso:country":"CN",
    "name:zho_x_preferred":[
        "\u5f20\u5bbd"
    ],
    "wof:name":"Zhangkuan",
    "wof:placetype":"locality"
},
  "geometry": {"coordinates":[114.473,36.9965],"type":"Point"}
}