{
  "type": "Feature",
  "properties": {
    "gn:admin1_code":"9.0",
    "gn:asciiname":"Baizhongcun",
    "gn:country_code":"CN",
    "gn:dem":81,
    "gn:feature_class":"P",
    "gn:feature_code":"PPL",
    "gn:name":"Baizhongcun",
    "gn:population":0,
    "gn:timezone":"Asia/Shanghai",
    "iso:country":"CN",
    "name:und_x_variant":[
        "\u67cf\u51a2\u6751"
    ],
    "name:zho_x_preferred":[
        "\u67cf\u51a2\u6751"
    ],
    "wof:name":"Baizhongcun",
    "wof:placetype":"locality"
},
  "geometry": {"coordinates":[113.72881,33.87923],"type":"Point"}
}