{
  "type": "Feature",
  "properties": {
    "gn:admin1_code":"1.0",
    "gn:asciiname":"Zouwangcun",
    "gn:country_code":"CN",
    "gn:dem":32,
    "gn:feature_class":"P",
    "gn:feature_code":"PPL",
    "gn:name":"Zouwangcun",
    "gn:population":0,
    "gn:timezone":"Asia/Shanghai",
    "iso:country":"CN",
    "name:zho_x_preferred":[
        "\u90b9\u738b\u6751"
    ],
    "wof:name":"Zouwangcun",
    "wof:placetype":"locality"
},
  "geometry": {"coordinates":[116.23033999999998,32.77143],"type":"Point"}
}