{
  "type": "Feature",
  "properties": {
    "gn:admin1_code":"29.0",
    "gn:asciiname":"Xiaoshui",
    "gn:country_code":"CN",
    "gn:dem":2680,
    "gn:feature_class":"P",
    "gn:feature_code":"PPL",
    "gn:name":"Xiaoshui",
    "gn:population":0,
    "gn:timezone":"Asia/Shanghai",
    "iso:country":"CN",
    "name:und_x_variant":[
        "\u5c0f\u6c34"
    ],
    "wof:name":"Xiaoshui",
    "wof:placetype":"locality"
},
  "geometry": {"coordinates":[103.36068,25.96348],"type":"Point"}
}