{
  "type": "Feature",
  "properties": {
    "gn:admin1_code":"1.0",
    "gn:asciiname":"Yangliu",
    "gn:cc2":"CN",
    "gn:country_code":"CN",
    "gn:dem":30,
    "gn:feature_class":"P",
    "gn:feature_code":"PPL",
    "gn:name":"Yangliu",
    "gn:population":0,
    "gn:timezone":"Asia/Shanghai",
    "iso:country":"CN",
    "name:und_x_variant":[
        "Yangliuji",
        "Yang-liu-chi",
        "Yangliu"
    ],
    "wof:name":"Yangliu",
    "wof:placetype":"locality"
},
  "geometry": {"coordinates":[116.7625,33.6225],"type":"Point"}
}