{
  "type": "Feature",
  "properties": {
    "gn:admin1_code":"1.0",
    "gn:asciiname":"Qizhaicun",
    "gn:country_code":"CN",
    "gn:dem":32,
    "gn:feature_class":"P",
    "gn:feature_code":"PPL",
    "gn:name":"Qizhaicun",
    "gn:population":0,
    "gn:timezone":"Asia/Shanghai",
    "iso:country":"CN",
    "name:zho_x_preferred":[
        "\u9f50\u5be8\u6751"
    ],
    "wof:name":"Qizhaicun",
    "wof:placetype":"locality"
},
  "geometry": {"coordinates":[116.08323,33.00559000000001],"type":"Point"}
}