{
  "type": "Feature",
  "properties": {
    "gn:admin1_code":"32.0",
    "gn:asciiname":"Songjiang",
    "gn:country_code":"CN",
    "gn:dem":405,
    "gn:feature_class":"P",
    "gn:feature_code":"PPL",
    "gn:name":"Songjiang",
    "gn:population":0,
    "gn:timezone":"Asia/Shanghai",
    "iso:country":"CN",
    "name:ceb_x_preferred":[
        "Songjiang"
    ],
    "name:deu_x_preferred":[
        "Songjiang"
    ],
    "name:mlg_x_preferred":[
        "Songjiang"
    ],
    "name:nor_x_preferred":[
        "Songjiang"
    ],
    "name:pol_x_preferred":[
        "Songjiang"
    ],
    "name:rus_x_preferred":[
        "\u0421\u0443\u043d\u0446\u0437\u044f\u043d"
    ],
    "name:swe_x_preferred":[
        "Songjiang"
    ],
    "name:zho_x_preferred":[
        "\u677e\u6c5f"
    ],
    "wof:name":"Songjiang",
    "wof:placetype":"locality"
},
  "geometry": {"coordinates":[103.79931999999999,29.99795],"type":"Point"}
}