{
  "type": "Feature",
  "properties": {
    "gn:admin1_code":"24.0",
    "gn:asciiname":"Daijiabu",
    "gn:country_code":"CN",
    "gn:dem":766,
    "gn:feature_class":"P",
    "gn:feature_code":"PPL",
    "gn:name":"Daijiabu",
    "gn:population":0,
    "gn:timezone":"Asia/Shanghai",
    "iso:country":"CN",
    "name:zho_x_preferred":[
        "\u4ee3\u5bb6\u5821"
    ],
    "wof:name":"Daijiabu",
    "wof:placetype":"locality"
},
  "geometry": {"coordinates":[112.48612,37.62629],"type":"Point"}
}