{
  "type": "Feature",
  "properties": {
    "gn:admin1_code":"30.0",
    "gn:asciiname":"Yujiaocun",
    "gn:country_code":"CN",
    "gn:dem":17,
    "gn:feature_class":"P",
    "gn:feature_code":"PPL",
    "gn:name":"Yujiaocun",
    "gn:population":0,
    "gn:timezone":"Asia/Shanghai",
    "iso:country":"CN",
    "name:zho_x_preferred":[
        "\u5729\u811a\u6751"
    ],
    "wof:name":"Yujiaocun",
    "wof:placetype":"locality"
},
  "geometry": {"coordinates":[116.29036000000001,23.35128],"type":"Point"}
}