{
  "type": "Feature",
  "properties": {
    "gn:admin1_code":"10",
    "gn:asciiname":"Tougou",
    "gn:cc2":"CN",
    "gn:country_code":"CN",
    "gn:dem":453,
    "gn:feature_class":"P",
    "gn:feature_code":"PPL",
    "gn:name":"Tougou",
    "gn:population":0,
    "gn:timezone":"Asia/Shanghai",
    "iso:country":"CN",
    "name:und_x_variant":[
        "T\u2019ou-kou",
        "Tougou"
    ],
    "wof:name":"Tougou",
    "wof:placetype":"locality"
},
  "geometry": {"coordinates":[118.06216999999999,41.15488],"type":"Point"}
}