{
  "type": "Feature",
  "properties": {
    "gn:admin1_code":"29.0",
    "gn:asciiname":"Zuna",
    "gn:country_code":"CN",
    "gn:dem":1879,
    "gn:feature_class":"P",
    "gn:feature_code":"PPL",
    "gn:name":"Zuna",
    "gn:population":0,
    "gn:timezone":"Asia/Shanghai",
    "iso:country":"CN",
    "name:ces_x_preferred":[
        "Zuna"
    ],
    "name:zho_x_preferred":[
        "\u7956\u90a3"
    ],
    "wof:name":"Zuna",
    "wof:placetype":"locality"
},
  "geometry": {"coordinates":[104.30500000000001,25.4411],"type":"Point"}
}