{
  "type": "Feature",
  "properties": {
    "gn:admin1_code":"8.0",
    "gn:asciiname":"Dazhengjia Weizi",
    "gn:country_code":"CN",
    "gn:dem":200,
    "gn:feature_class":"P",
    "gn:feature_code":"PPL",
    "gn:name":"Dazhengjia Weizi",
    "gn:population":0,
    "gn:timezone":"Asia/Shanghai",
    "iso:country":"CN",
    "name:zho_x_preferred":[
        "\u5927\u90d1\u5bb6\u56f4\u5b50"
    ],
    "wof:name":"Dazhengjia Weizi",
    "wof:placetype":"locality"
},
  "geometry": {"coordinates":[125.22683000000001,47.73194],"type":"Point"}
}