{
  "type": "Feature",
  "properties": {
    "gn:admin1_code":"29",
    "gn:asciiname":"Zhongtongchang",
    "gn:country_code":"CN",
    "gn:dem":748,
    "gn:feature_class":"P",
    "gn:feature_code":"PPL",
    "gn:name":"Zhongtongchang",
    "gn:population":0,
    "gn:timezone":"Asia/Shanghai",
    "iso:country":"CN",
    "name:zho_x_preferred":[
        "\u4e2d\u94dc\u5382"
    ],
    "wof:name":"Zhongtongchang",
    "wof:placetype":"locality"
},
  "geometry": {"coordinates":[104.976,23.2537],"type":"Point"}
}