{
  "type": "Feature",
  "properties": {
    "gn:admin1_code":"12.0",
    "gn:asciiname":"Bainiaoping",
    "gn:country_code":"CN",
    "gn:dem":890,
    "gn:feature_class":"P",
    "gn:feature_code":"PPL",
    "gn:name":"Bainiaoping",
    "gn:population":0,
    "gn:timezone":"Asia/Shanghai",
    "iso:country":"CN",
    "name:zho_x_preferred":[
        "\u767e\u9e1f\u576a"
    ],
    "wof:name":"Bainiaoping",
    "wof:placetype":"locality"
},
  "geometry": {"coordinates":[110.1759,30.13291],"type":"Point"}
}