{
  "type": "Feature",
  "properties": {
    "gn:admin1_code":"19.0",
    "gn:asciiname":"Houshicun",
    "gn:country_code":"CN",
    "gn:dem":13,
    "gn:feature_class":"P",
    "gn:feature_code":"PPL",
    "gn:name":"Houshicun",
    "gn:population":0,
    "gn:timezone":"Asia/Shanghai",
    "iso:country":"CN",
    "name:zho_x_preferred":[
        "\u7334\u77f3\u6751"
    ],
    "wof:name":"Houshicun",
    "wof:placetype":"locality"
},
  "geometry": {"coordinates":[122.23699999999999,39.2844],"type":"Point"}
}