{
  "type": "Feature",
  "properties": {
    "gn:admin1_code":"10.0",
    "gn:asciiname":"Juliushu",
    "gn:country_code":"CN",
    "gn:dem":836,
    "gn:feature_class":"P",
    "gn:feature_code":"PPL",
    "gn:name":"Juliushu",
    "gn:population":0,
    "gn:timezone":"Asia/Shanghai",
    "iso:country":"CN",
    "name:zho_x_preferred":[
        "\u8d84\u67f3\u6811"
    ],
    "wof:name":"Juliushu",
    "wof:placetype":"locality"
},
  "geometry": {"coordinates":[115.28045,40.67896],"type":"Point"}
}