{
  "type": "Feature",
  "properties": {
    "gn:country":"CN",
    "gn:fcode":"ADM3",
    "gn:pop":0,
    "iso:country":"CN",
    "name:ceb_x_preferred":[
        "Qidong Xian"
    ],
    "name:deu_x_preferred":[
        "Qidong"
    ],
    "name:eng_x_preferred":[
        "Qidong County"
    ],
    "name:fas_x_preferred":[
        "\u0634\u0647\u0631\u0633\u062a\u0627\u0646 \u0686\u06cc\u062f\u0648\u0646\u06af"
    ],
    "name:gan_x_preferred":[
        "\u7941\u4e1c\u53bf"
    ],
    "name:hak_x_preferred":[
        "Kh\u00ee-t\u00fbng-yen"
    ],
    "name:jpn_x_preferred":[
        "\u7941\u6771\u770c"
    ],
    "name:kor_x_preferred":[
        "\uce58\ub465\ud604"
    ],
    "name:nan_x_preferred":[
        "K\u00ee-tang-ko\u0101n"
    ],
    "name:nld_x_preferred":[
        "Qidong"
    ],
    "name:nob_x_preferred":[
        "Qidong"
    ],
    "name:swe_x_preferred":[
        "Qidong"
    ],
    "name:unk_x_variant":[
        "Ch\u2019i-tung Hsien"
    ],
    "name:vie_x_preferred":[
        "K\u1ef3 \u0110\u00f4ng"
    ],
    "name:wuu_x_preferred":[
        "\u7941\u4e1c\u53bf"
    ],
    "name:yue_x_preferred":[
        "\u7941\u6771"
    ],
    "name:zho_x_preferred":[
        "\u7941\u4e1c\u53bf"
    ],
    "name:zho_x_variant":[
        "\u7941\u4e1c"
    ],
    "qs:name":"Qidong Xian",
    "qs:photos_9r":0,
    "qs:photos_sr":0,
    "qs:pop_sr":"0",
    "wd:wordcount":51,
    "wof:name":"Qidong Xian",
    "wof:placetype":"localadmin",
    "wof:population":0
},
  "geometry": {"coordinates":[112.01286,26.74283],"type":"Point"}
}