{
  "type": "Feature",
  "properties": {
    "gn:country":"CN",
    "gn:fcode":"ADM3",
    "gn:pop":0,
    "iso:country":"CN",
    "name:unk_x_variant":[
        "Ch\u2019i-tung Hsien"
    ],
    "name:zho_x_preferred":[
        "\u7941\u4e1c\u53bf"
    ],
    "name:zho_x_variant":[
        "\u7941\u4e1c"
    ],
    "qs:name":"Qidong Xian",
    "qs:photos_9r":0,
    "qs:photos_sr":0,
    "qs:pop_sr":"0",
    "wd:wordcount":51,
    "wof:name":"Qidong Xian",
    "wof:placetype":"localadmin",
    "wof:population":0
},
  "geometry": {"coordinates":[112.01286,26.74283],"type":"Point"}
}