{
  "type": "Feature",
  "properties": {
    "gn:admin1_code":"1.0",
    "gn:asciiname":"Zhouzhaicun",
    "gn:country_code":"CN",
    "gn:dem":32,
    "gn:feature_class":"P",
    "gn:feature_code":"PPL",
    "gn:name":"Zhouzhaicun",
    "gn:population":0,
    "gn:timezone":"Asia/Shanghai",
    "iso:country":"CN",
    "name:zho_x_preferred":[
        "\u5468\u5be8\u6751"
    ],
    "wof:name":"Zhouzhaicun",
    "wof:placetype":"locality"
},
  "geometry": {"coordinates":[116.00915000000001,33.19875],"type":"Point"}
}