{
  "type": "Feature",
  "properties": {
    "gn:admin1_code":"07",
    "gn:asciiname":"Jingxi",
    "gn:country_code":"CN",
    "gn:dem":184,
    "gn:feature_class":"P",
    "gn:feature_code":"PPLA4",
    "gn:name":"Jingxi",
    "gn:population":0,
    "gn:timezone":"Asia/Shanghai",
    "iso:country":"CN",
    "name:und_x_variant":[
        "Ching-hsi",
        "Jingxi",
        "\u8346\u897f",
        "Jingxi Jiedao",
        "\u8346\u897f\u8857\u9053"
    ],
    "name:zho_x_preferred":[
        "\u8346\u897f"
    ],
    "wof:name":"Jingxi",
    "wof:placetype":"locality"
},
  "geometry": {"coordinates":[117.54526,26.19454],"type":"Point"}
}