{
  "type": "Feature",
  "properties": {
    "gn:admin1_code":"4.0",
    "gn:asciiname":"Zhangbaduo",
    "gn:country_code":"CN",
    "gn:dem":2,
    "gn:feature_class":"P",
    "gn:feature_code":"PPL",
    "gn:name":"Zhangbaduo",
    "gn:population":0,
    "gn:timezone":"Asia/Shanghai",
    "iso:country":"CN",
    "name:zho_x_preferred":[
        "Zhangbaduo"
    ],
    "name:zho_x_variant":[
        "\u5f20\u516b\u579b"
    ],
    "wof:name":"Zhangbaduo",
    "wof:placetype":"locality"
},
  "geometry": {"coordinates":[119.81501000000002,33.34734],"type":"Point"}
}