{
  "type": "Feature",
  "properties": {
    "gn:admin1_code":"9",
    "gn:asciiname":"Hou'an",
    "gn:country_code":"CN",
    "gn:dem":62,
    "gn:feature_class":"P",
    "gn:feature_code":"PPL",
    "gn:name":"Hou\u2019an",
    "gn:population":0,
    "gn:timezone":"Asia/Shanghai",
    "iso:country":"CN",
    "name:und_x_variant":[
        "Hou\u2019an"
    ],
    "name:zho_x_preferred":[
        "\u540e\u5b89"
    ],
    "wof:name":"Hou'an",
    "wof:placetype":"locality"
},
  "geometry": {"coordinates":[114.65056,35.82389000000001],"type":"Point"}
}