{
  "type": "Feature",
  "properties": {
    "gn:admin1_code":"30.0",
    "gn:asciiname":"Genghe",
    "gn:country_code":"CN",
    "gn:dem":26,
    "gn:feature_class":"P",
    "gn:feature_code":"PPLA4",
    "gn:name":"Genghe",
    "gn:population":0,
    "gn:timezone":"Asia/Shanghai",
    "iso:country":"CN",
    "name:und_x_variant":[
        "Genghe Zhen"
    ],
    "name:zho_x_preferred":[
        "\u66f4\u5408"
    ],
    "name:zho_x_variant":[
        "\u66f4\u5408\u9547"
    ],
    "wof:name":"Genghe",
    "wof:placetype":"locality"
},
  "geometry": {"coordinates":[112.57831000000002,22.78354],"type":"Point"}
}