{
  "type": "Feature",
  "properties": {
    "gn:admin1_code":"06",
    "gn:asciiname":"Quedantang",
    "gn:country_code":"CN",
    "gn:dem":2945,
    "gn:feature_class":"P",
    "gn:feature_code":"PPLA4",
    "gn:name":"Quedantang",
    "gn:population":0,
    "gn:timezone":"Asia/Shanghai",
    "iso:country":"CN",
    "name:bod_x_preferred":[
        "Mangra"
    ],
    "name:msa_x_preferred":[
        "Mangra"
    ],
    "name:und_x_variant":[
        "Guynan\u2019",
        "Mang-la",
        "Kuei-nan",
        "Guinan",
        "Quedantang",
        "\u5374\u65e6\u5858",
        "Mangla Xiang"
    ],
    "name:zho_x_preferred":[
        "\u832b\u62c9\u4e61"
    ],
    "wof:name":"Quedantang",
    "wof:placetype":"locality"
},
  "geometry": {"coordinates":[100.60006,35.65022000000001],"type":"Point"}
}