{
  "type": "Feature",
  "properties": {
    "gn:admin1_code":"26.0",
    "gn:asciiname":"Jujiawan",
    "gn:country_code":"CN",
    "gn:dem":479,
    "gn:feature_class":"P",
    "gn:feature_code":"PPL",
    "gn:name":"Jujiawan",
    "gn:population":0,
    "gn:timezone":"Asia/Shanghai",
    "iso:country":"CN",
    "name:und_x_variant":[
        "\u5de8\u5bb6\u6e7e"
    ],
    "wof:name":"Jujiawan",
    "wof:placetype":"locality"
},
  "geometry": {"coordinates":[107.28569,33.12407],"type":"Point"}
}