{
  "type": "Feature",
  "properties": {
    "gn:admin1_code":"22.0",
    "gn:asciiname":"Shangwopucun",
    "gn:country_code":"CN",
    "gn:dem":493,
    "gn:feature_class":"P",
    "gn:feature_code":"PPL",
    "gn:name":"Shangwopucun",
    "gn:population":0,
    "gn:timezone":"Asia/Shanghai",
    "iso:country":"CN",
    "name:zho_x_preferred":[
        "\u4e0a\u7a9d\u94fa\u6751"
    ],
    "wof:name":"Shangwopucun",
    "wof:placetype":"locality"
},
  "geometry": {"coordinates":[116.86199000000001,40.80885],"type":"Point"}
}