{
  "type": "Feature",
  "properties": {
    "gn:admin1_code":"4.0",
    "gn:asciiname":"Shebincun",
    "gn:country_code":"CN",
    "gn:dem":3,
    "gn:feature_class":"P",
    "gn:feature_code":"PPL",
    "gn:name":"Shebincun",
    "gn:population":0,
    "gn:timezone":"Asia/Shanghai",
    "iso:country":"CN",
    "name:zho_x_preferred":[
        "\u5c04\u6ee8\u6751"
    ],
    "wof:name":"Shebincun",
    "wof:placetype":"locality"
},
  "geometry": {"coordinates":[119.53088,33.51929000000001],"type":"Point"}
}