{
  "type": "Feature",
  "properties": {
    "gn:admin1_code":"20.0",
    "gn:asciiname":"Liemindui",
    "gn:country_code":"CN",
    "gn:dem":289,
    "gn:feature_class":"P",
    "gn:feature_code":"PPLF",
    "gn:name":"Liemindui",
    "gn:population":0,
    "gn:timezone":"Asia/Shanghai",
    "iso:country":"CN",
    "name:zho_x_preferred":[
        "\u730e\u6c11\u961f"
    ],
    "wof:name":"Liemindui",
    "wof:placetype":"locality"
},
  "geometry": {"coordinates":[124.89969000000001,50.07192],"type":"Point"}
}