{
  "type": "Feature",
  "properties": {
    "gn:admin1_code":"21.0",
    "gn:asciiname":"Jiangkou",
    "gn:country_code":"CN",
    "gn:dem":1708,
    "gn:feature_class":"P",
    "gn:feature_code":"PPL",
    "gn:name":"Jiangkou",
    "gn:population":0,
    "gn:timezone":"Asia/Shanghai",
    "iso:country":"CN",
    "name:und_x_variant":[
        "\u848b\u53e3"
    ],
    "name:zho_x_preferred":[
        "\u848b\u53e3"
    ],
    "wof:name":"Jiangkou",
    "wof:placetype":"locality"
},
  "geometry": {"coordinates":[106.11612,36.09592],"type":"Point"}
}