{
  "type": "Feature",
  "properties": {
    "gn:admin1_code":"30",
    "gn:asciiname":"Bolong'ao",
    "gn:country_code":"CN",
    "gn:dem":371,
    "gn:feature_class":"P",
    "gn:feature_code":"PPL",
    "gn:name":"Bolong\u2019ao",
    "gn:population":0,
    "gn:timezone":"Asia/Shanghai",
    "iso:country":"CN",
    "name:zho_x_preferred":[
        "\u9a73\u9f99\u51f9"
    ],
    "name:zho_x_variant":[
        "Bolong\u2019ao"
    ],
    "wof:name":"Bolong'ao",
    "wof:placetype":"locality"
},
  "geometry": {"coordinates":[115.88106000000001,24.38218],"type":"Point"}
}