{
  "type": "Feature",
  "properties": {
    "gn:admin1_code":"2",
    "gn:asciiname":"Xiatang",
    "gn:country_code":"CN",
    "gn:dem":77,
    "gn:feature_class":"P",
    "gn:feature_code":"PPL",
    "gn:name":"Xiatang",
    "gn:population":0,
    "gn:timezone":"Asia/Shanghai",
    "iso:country":"CN",
    "name:und_x_variant":[
        "\u4e0b\u6c64"
    ],
    "wof:name":"Xiatang",
    "wof:placetype":"locality"
},
  "geometry": {"coordinates":[119.50278,30.55722],"type":"Point"}
}