{
  "type": "Feature",
  "properties": {
    "gn:admin1_code":"8.0",
    "gn:asciiname":"Baishuncun",
    "gn:country_code":"CN",
    "gn:dem":181,
    "gn:feature_class":"P",
    "gn:feature_code":"PPL",
    "gn:name":"Baishuncun",
    "gn:population":0,
    "gn:timezone":"Asia/Shanghai",
    "iso:country":"CN",
    "name:zho_x_preferred":[
        "\u767e\u987a\u6751"
    ],
    "wof:name":"Baishuncun",
    "wof:placetype":"locality"
},
  "geometry": {"coordinates":[126.50579,47.26709],"type":"Point"}
}