{
  "type": "Feature",
  "properties": {
    "gn:admin1_code":"30.0",
    "gn:asciiname":"Zumiao",
    "gn:country_code":"CN",
    "gn:dem":1,
    "gn:feature_class":"P",
    "gn:feature_code":"PPLA4",
    "gn:name":"Zumiao",
    "gn:population":0,
    "gn:timezone":"Asia/Shanghai",
    "iso:country":"CN",
    "name:und_x_variant":[
        "Zumiao Jiedao"
    ],
    "name:zho_x_preferred":[
        "\u7956\u5e99"
    ],
    "name:zho_x_variant":[
        "\u7956\u5e99\u8857\u9053"
    ],
    "wof:name":"Zumiao",
    "wof:placetype":"locality"
},
  "geometry": {"coordinates":[113.13026000000001,23.02544],"type":"Point"}
}