{
  "type": "Feature",
  "properties": {
    "gn:admin1_code":"25.0",
    "gn:asciiname":"Lunanbucun",
    "gn:country_code":"CN",
    "gn:dem":93,
    "gn:feature_class":"P",
    "gn:feature_code":"PPL",
    "gn:name":"Lunanbucun",
    "gn:population":0,
    "gn:timezone":"Asia/Shanghai",
    "iso:country":"CN",
    "name:zho_x_preferred":[
        "\u8def\u5357\u57e0\u6751"
    ],
    "wof:name":"Lunanbucun",
    "wof:placetype":"locality"
},
  "geometry": {"coordinates":[120.34233,36.94938],"type":"Point"}
}