{
  "type": "Feature",
  "properties": {
    "gn:admin1_code":"19",
    "gn:asciiname":"Ganquan",
    "gn:country_code":"CN",
    "gn:dem":53,
    "gn:feature_class":"P",
    "gn:feature_code":"PPLA4",
    "gn:name":"Ganquan",
    "gn:population":0,
    "gn:timezone":"Asia/Shanghai",
    "iso:country":"CN",
    "name:und_x_variant":[
        "Ganquan Zhen",
        "Ganquan"
    ],
    "name:zho_x_preferred":[
        "\u7518\u6cc9"
    ],
    "name:zho_x_variant":[
        "\u7518\u6cc9\u9547"
    ],
    "wof:name":"Ganquan",
    "wof:placetype":"locality"
},
  "geometry": {"coordinates":[122.85418,40.96426],"type":"Point"}
}