{
  "type": "Feature",
  "properties": {
    "gn:admin1_code":"14.0",
    "gn:asciiname":"Riqiongduo",
    "gn:country_code":"CN",
    "gn:dem":4415,
    "gn:feature_class":"P",
    "gn:feature_code":"PPL",
    "gn:name":"Riqiongduo",
    "gn:population":0,
    "gn:timezone":"Asia/Urumqi",
    "iso:country":"CN",
    "name:zho_x_preferred":[
        "\u65e5\u909b\u6735"
    ],
    "wof:name":"Riqiongduo",
    "wof:placetype":"locality"
},
  "geometry": {"coordinates":[92.06713000000001,30.41375],"type":"Point"}
}