{
  "type": "Feature",
  "properties": {
    "gn:admin1_code":"7.0",
    "gn:asciiname":"Kunban",
    "gn:country_code":"CN",
    "gn:dem":876,
    "gn:feature_class":"P",
    "gn:feature_code":"PPL",
    "gn:name":"Kunban",
    "gn:population":0,
    "gn:timezone":"Asia/Shanghai",
    "iso:country":"CN",
    "name:zho_x_preferred":[
        "\u6606\u5742"
    ],
    "wof:name":"Kunban",
    "wof:placetype":"locality"
},
  "geometry": {"coordinates":[118.4888,25.65767],"type":"Point"}
}