{
  "type": "Feature",
  "properties": {
    "gn:admin1_code":"0.0",
    "gn:asciiname":"Mu-sang",
    "gn:country_code":"CN",
    "gn:dem":1036,
    "gn:feature_class":"P",
    "gn:feature_code":"PPL",
    "gn:name":"Mu-sang",
    "gn:population":0,
    "gn:timezone":"Asia/Shanghai",
    "iso:country":"CN",
    "wof:name":"Mu-sang",
    "wof:placetype":"locality"
},
  "geometry": {"coordinates":[105.66419,23.96305],"type":"Point"}
}