{
  "type": "Feature",
  "properties": {
    "gn:admin1_code":"7.0",
    "gn:asciiname":"Huaguoxia",
    "gn:country_code":"CN",
    "gn:dem":461,
    "gn:feature_class":"P",
    "gn:feature_code":"PPL",
    "gn:name":"Huaguoxia",
    "gn:population":0,
    "gn:timezone":"Asia/Shanghai",
    "iso:country":"CN",
    "name:zho_x_preferred":[
        "\u534e\u56fd\u4e0b"
    ],
    "wof:name":"Huaguoxia",
    "wof:placetype":"locality"
},
  "geometry": {"coordinates":[116.71234,24.7951],"type":"Point"}
}