{
  "type": "Feature",
  "properties": {
    "gn:admin1_code":"25.0",
    "gn:asciiname":"Sungezhuang",
    "gn:country_code":"CN",
    "gn:dem":76,
    "gn:feature_class":"P",
    "gn:feature_code":"PPL",
    "gn:name":"Sungezhuang",
    "gn:population":0,
    "gn:timezone":"Asia/Shanghai",
    "iso:country":"CN",
    "name:zho_x_preferred":[
        "\u5b59\u6208\u5e84"
    ],
    "wof:name":"Sungezhuang",
    "wof:placetype":"locality"
},
  "geometry": {"coordinates":[119.38214000000001,36.12238],"type":"Point"}
}