{
  "type": "Feature",
  "properties": {
    "gn:admin1_code":"11",
    "gn:asciiname":"Lianhua",
    "gn:country_code":"CN",
    "gn:dem":94,
    "gn:feature_class":"P",
    "gn:feature_code":"PPLA4",
    "gn:name":"Lianhua",
    "gn:population":0,
    "gn:timezone":"Asia/Shanghai",
    "iso:country":"CN",
    "name:ceb_x_preferred":[
        "Lianhua"
    ],
    "name:deu_x_preferred":[
        "Lianhua"
    ],
    "name:nor_x_preferred":[
        "Lianhua"
    ],
    "name:und_x_variant":[
        "Lianhua Zhen"
    ],
    "name:zho_x_preferred":[
        "\u83b2\u82b1"
    ],
    "name:zho_x_variant":[
        "\u83b2\u82b1\u9547"
    ],
    "wof:name":"Lianhua",
    "wof:placetype":"locality"
},
  "geometry": {"coordinates":[112.76639,28.11694],"type":"Point"}
}