{
  "type": "Feature",
  "properties": {
    "gn:admin1_code":"29.0",
    "gn:asciiname":"Epu Shangzhai",
    "gn:country_code":"CN",
    "gn:dem":1550,
    "gn:feature_class":"P",
    "gn:feature_code":"PPL",
    "gn:name":"Epu Shangzhai",
    "gn:population":0,
    "gn:timezone":"Asia/Shanghai",
    "iso:country":"CN",
    "name:zho_x_preferred":[
        "\u4fc4\u94fa\u4e0a\u5be8"
    ],
    "wof:name":"Epu Shangzhai",
    "wof:placetype":"locality"
},
  "geometry": {"coordinates":[102.569,23.0158],"type":"Point"}
}