{
  "type": "Feature",
  "properties": {
    "gn:admin1_code":"10",
    "gn:asciiname":"Daposhang",
    "gn:country_code":"CN",
    "gn:dem":369,
    "gn:feature_class":"P",
    "gn:feature_code":"PPL",
    "gn:name":"Daposhang",
    "gn:population":0,
    "gn:timezone":"Asia/Shanghai",
    "iso:country":"CN",
    "name:zho_x_preferred":[
        "\u5927\u5761\u4e0a"
    ],
    "wof:name":"Daposhang",
    "wof:placetype":"locality"
},
  "geometry": {"coordinates":[118.32172,40.57617],"type":"Point"}
}