{
  "type": "Feature",
  "properties": {
    "gn:admin1_code":"26.0",
    "gn:asciiname":"Heshuyuan",
    "gn:country_code":"CN",
    "gn:dem":1161,
    "gn:feature_class":"P",
    "gn:feature_code":"PPL",
    "gn:name":"Heshuyuan",
    "gn:population":0,
    "gn:timezone":"Asia/Shanghai",
    "iso:country":"CN",
    "name:zho_x_preferred":[
        "\u4f55\u6811\u586c"
    ],
    "wof:name":"Heshuyuan",
    "wof:placetype":"locality"
},
  "geometry": {"coordinates":[109.08238,35.59115999999999],"type":"Point"}
}