{
  "type": "Feature",
  "properties": {
    "gn:admin1_code":"31.0",
    "gn:asciiname":"Dianliao",
    "gn:country_code":"CN",
    "gn:dem":33,
    "gn:feature_class":"P",
    "gn:feature_code":"PPL",
    "gn:name":"Dianliao",
    "gn:population":0,
    "gn:timezone":"Asia/Shanghai",
    "iso:country":"CN",
    "name:zho_x_preferred":[
        "\u5178\u5bee"
    ],
    "wof:name":"Dianliao",
    "wof:placetype":"locality"
},
  "geometry": {"coordinates":[110.29655,18.81359],"type":"Point"}
}