{
  "type": "Feature",
  "properties": {
    "gn:admin1_code":"30.0",
    "gn:asciiname":"Shilonggang",
    "gn:country_code":"CN",
    "gn:dem":59,
    "gn:feature_class":"P",
    "gn:feature_code":"PPL",
    "gn:name":"Shilonggang",
    "gn:population":0,
    "gn:timezone":"Asia/Shanghai",
    "iso:country":"CN",
    "name:zho_x_preferred":[
        "\u77f3\u9f99\u5c97"
    ],
    "wof:name":"Shilonggang",
    "wof:placetype":"locality"
},
  "geometry": {"coordinates":[112.45789000000001,22.69912],"type":"Point"}
}