{
  "type": "Feature",
  "properties": {
    "gn:admin1_code":"26.0",
    "gn:asciiname":"Shaguagoucun",
    "gn:country_code":"CN",
    "gn:dem":1514,
    "gn:feature_class":"P",
    "gn:feature_code":"PPL",
    "gn:name":"Shaguagoucun",
    "gn:population":0,
    "gn:timezone":"Asia/Shanghai",
    "iso:country":"CN",
    "name:zho_x_preferred":[
        "\u6c99\u576c\u6c9f\u6751"
    ],
    "wof:name":"Shaguagoucun",
    "wof:placetype":"locality"
},
  "geometry": {"coordinates":[108.54398999999999,37.23628],"type":"Point"}
}