{
  "type": "Feature",
  "properties": {
    "gn:admin1_code":"3.0",
    "gn:asciiname":"Qiexia",
    "gn:country_code":"CN",
    "gn:dem":41,
    "gn:feature_class":"P",
    "gn:feature_code":"PPL",
    "gn:name":"Qiexia",
    "gn:population":0,
    "gn:timezone":"Asia/Shanghai",
    "iso:country":"CN",
    "name:und_x_variant":[
        "\u4e14\u4e0b"
    ],
    "wof:name":"Qiexia",
    "wof:placetype":"locality"
},
  "geometry": {"coordinates":[115.76392,27.94583],"type":"Point"}
}