{
  "type": "Feature",
  "properties": {
    "gn:admin1_code":"19.0",
    "gn:asciiname":"Lujia Fangzi",
    "gn:country_code":"CN",
    "gn:dem":140,
    "gn:feature_class":"P",
    "gn:feature_code":"PPL",
    "gn:name":"Lujia Fangzi",
    "gn:population":0,
    "gn:timezone":"Asia/Shanghai",
    "iso:country":"CN",
    "name:zho_x_preferred":[
        "\u5362\u5bb6\u623f\u5b50"
    ],
    "wof:name":"Lujia Fangzi",
    "wof:placetype":"locality"
},
  "geometry": {"coordinates":[119.895,40.2586],"type":"Point"}
}