{
  "type": "Feature",
  "properties": {
    "gn:admin1_code":"19.0",
    "gn:asciiname":"Donglalajie",
    "gn:country_code":"CN",
    "gn:dem":105,
    "gn:feature_class":"P",
    "gn:feature_code":"PPL",
    "gn:name":"Donglalajie",
    "gn:population":0,
    "gn:timezone":"Asia/Shanghai",
    "iso:country":"CN",
    "name:zho_x_preferred":[
        "\u4e1c\u62c9\u62c9\u8857"
    ],
    "wof:name":"Donglalajie",
    "wof:placetype":"locality"
},
  "geometry": {"coordinates":[122.57599999999999,42.5038],"type":"Point"}
}