{
  "type": "Feature",
  "properties": {
    "gn:admin1_code":"21.0",
    "gn:asciiname":"Donggouwan",
    "gn:country_code":"CN",
    "gn:dem":1133,
    "gn:feature_class":"P",
    "gn:feature_code":"PPL",
    "gn:name":"Donggouwan",
    "gn:population":0,
    "gn:timezone":"Asia/Shanghai",
    "iso:country":"CN",
    "name:zho_x_preferred":[
        "\u4e1c\u6c9f\u6e7e"
    ],
    "wof:name":"Donggouwan",
    "wof:placetype":"locality"
},
  "geometry": {"coordinates":[106.265,37.949],"type":"Point"}
}