{
  "type": "Feature",
  "properties": {
    "gn:admin1_code":"12.0",
    "gn:asciiname":"Xinleiwan",
    "gn:country_code":"CN",
    "gn:dem":30,
    "gn:feature_class":"P",
    "gn:feature_code":"PPL",
    "gn:name":"Xinleiwan",
    "gn:population":0,
    "gn:timezone":"Asia/Shanghai",
    "iso:country":"CN",
    "name:zho_x_preferred":[
        "\u65b0\u96f7\u6e7e"
    ],
    "wof:name":"Xinleiwan",
    "wof:placetype":"locality"
},
  "geometry": {"coordinates":[112.95207000000001,30.25807],"type":"Point"}
}