{
  "type": "Feature",
  "properties": {
    "gn:admin1_code":"2.0",
    "gn:asciiname":"Fandong",
    "gn:country_code":"CN",
    "gn:dem":78,
    "gn:feature_class":"P",
    "gn:feature_code":"PPL",
    "gn:name":"Fandong",
    "gn:population":0,
    "gn:timezone":"Asia/Shanghai",
    "iso:country":"CN",
    "name:zho_x_preferred":[
        "\u7548\u4e1c"
    ],
    "wof:name":"Fandong",
    "wof:placetype":"locality"
},
  "geometry": {"coordinates":[120.02413,29.31957],"type":"Point"}
}