{
  "type": "Feature",
  "properties": {
    "gn:admin1_code":"12.0",
    "gn:asciiname":"Fengjiawan",
    "gn:country_code":"CN",
    "gn:dem":102,
    "gn:feature_class":"P",
    "gn:feature_code":"PPL",
    "gn:name":"Fengjiawan",
    "gn:population":0,
    "gn:timezone":"Asia/Shanghai",
    "iso:country":"CN",
    "name:und_x_variant":[
        "\u51af\u5bb6\u5846"
    ],
    "wof:name":"Fengjiawan",
    "wof:placetype":"locality"
},
  "geometry": {"coordinates":[115.17036,30.01542],"type":"Point"}
}