{
  "type": "Feature",
  "properties": {
    "gn:admin1_code":"4.0",
    "gn:asciiname":"Dannan",
    "gn:country_code":"CN",
    "gn:dem":6,
    "gn:feature_class":"P",
    "gn:feature_code":"PPL",
    "gn:name":"Dannan",
    "gn:population":0,
    "gn:timezone":"Asia/Shanghai",
    "iso:country":"CN",
    "name:zho_x_preferred":[
        "Dannan"
    ],
    "name:zho_x_variant":[
        "\u5355\u5357"
    ],
    "wof:name":"Dannan",
    "wof:placetype":"locality"
},
  "geometry": {"coordinates":[119.16388999999999,34.96371],"type":"Point"}
}