{
  "type": "Feature",
  "properties": {
    "gn:admin1_code":"2.0",
    "gn:asciiname":"Yuan'ao",
    "gn:country_code":"CN",
    "gn:dem":93,
    "gn:feature_class":"P",
    "gn:feature_code":"PPL",
    "gn:name":"Yuan\u2019ao",
    "gn:population":0,
    "gn:timezone":"Asia/Shanghai",
    "iso:country":"CN",
    "name:zho_x_preferred":[
        "\u5143\u5c99"
    ],
    "name:zho_x_variant":[
        "Yuan\u2019ao"
    ],
    "wof:name":"Yuan'ao",
    "wof:placetype":"locality"
},
  "geometry": {"coordinates":[120.86879999999999,29.47997],"type":"Point"}
}