{
  "type": "Feature",
  "properties": {
    "gn:admin1_code":"16",
    "gn:asciiname":"Changhe",
    "gn:cc2":"CN",
    "gn:country_code":"CN",
    "gn:dem":131,
    "gn:feature_class":"P",
    "gn:feature_code":"PPL",
    "gn:name":"Changhe",
    "gn:population":0,
    "gn:timezone":"Asia/Shanghai",
    "iso:country":"CN",
    "name:deu_x_preferred":[
        "Changhe"
    ],
    "name:fra_x_preferred":[
        "Changhe"
    ],
    "name:pol_x_preferred":[
        "Changhe"
    ],
    "name:por_x_preferred":[
        "Changhe"
    ],
    "name:sco_x_preferred":[
        "Changhe"
    ],
    "name:spa_x_preferred":[
        "Changhe"
    ],
    "name:und_x_variant":[
        "Ch\u2019ang-ho-chieh",
        "Ch\u2019ang-ho-shieh",
        "Ch\u2019ang-ho"
    ],
    "name:zho_x_preferred":[
        "\u660c\u6cb3\u6c7d\u8f66"
    ],
    "wof:name":"Changhe",
    "wof:placetype":"locality"
},
  "geometry": {"coordinates":[110.66056,22.9525],"type":"Point"}
}