{
  "type": "Feature",
  "properties": {
    "gn:admin1_code":"29.0",
    "gn:asciiname":"Shidongmen",
    "gn:country_code":"CN",
    "gn:dem":1512,
    "gn:feature_class":"P",
    "gn:feature_code":"PPL",
    "gn:name":"Shidongmen",
    "gn:population":0,
    "gn:timezone":"Asia/Shanghai",
    "iso:country":"CN",
    "name:zho_x_preferred":[
        "\u77f3\u6d1e\u95e8"
    ],
    "wof:name":"Shidongmen",
    "wof:placetype":"locality"
},
  "geometry": {"coordinates":[104.08799999999999,23.6701],"type":"Point"}
}