{
  "type": "Feature",
  "properties": {
    "gn:admin1_code":"8.0",
    "gn:asciiname":"Qingfengtun",
    "gn:country_code":"CN",
    "gn:dem":105,
    "gn:feature_class":"P",
    "gn:feature_code":"PPL",
    "gn:name":"Qingfengtun",
    "gn:population":0,
    "gn:timezone":"Asia/Shanghai",
    "iso:country":"CN",
    "name:zho_x_preferred":[
        "\u5e86\u4e30\u5c6f"
    ],
    "wof:name":"Qingfengtun",
    "wof:placetype":"locality"
},
  "geometry": {"coordinates":[132.12469999999999,45.56196],"type":"Point"}
}