{
  "type": "Feature",
  "properties": {
    "gn:admin1_code":"3.0",
    "gn:asciiname":"Muxicun",
    "gn:country_code":"CN",
    "gn:dem":18,
    "gn:feature_class":"P",
    "gn:feature_code":"PPL",
    "gn:name":"Muxicun",
    "gn:population":0,
    "gn:timezone":"Asia/Shanghai",
    "iso:country":"CN",
    "name:und_x_variant":[
        "\u6728\u897f\u6751"
    ],
    "wof:name":"Muxicun",
    "wof:placetype":"locality"
},
  "geometry": {"coordinates":[116.50458,28.6466],"type":"Point"}
}