{
  "type": "Feature",
  "properties": {
    "gn:admin1_code":"01",
    "gn:asciiname":"Guraoji",
    "gn:cc2":"CN",
    "gn:country_code":"CN",
    "gn:dem":34,
    "gn:feature_class":"P",
    "gn:feature_code":"PPL",
    "gn:name":"Guraoji",
    "gn:population":0,
    "gn:timezone":"Asia/Shanghai",
    "iso:country":"CN",
    "name:und_x_variant":[
        "Ku-jao-chi",
        "Ku-jao",
        "Guraoji"
    ],
    "wof:name":"Guraoji",
    "wof:placetype":"locality"
},
  "geometry": {"coordinates":[116.91667,33.83333],"type":"Point"}
}