{
  "type": "Feature",
  "properties": {
    "gn:admin1_code":"32.0",
    "gn:asciiname":"Xujia Pingzi",
    "gn:country_code":"CN",
    "gn:dem":1996,
    "gn:feature_class":"P",
    "gn:feature_code":"PPL",
    "gn:name":"Xujia Pingzi",
    "gn:population":0,
    "gn:timezone":"Asia/Shanghai",
    "iso:country":"CN",
    "name:zho_x_preferred":[
        "\u8bb8\u5bb6\u576a\u5b50"
    ],
    "wof:name":"Xujia Pingzi",
    "wof:placetype":"locality"
},
  "geometry": {"coordinates":[102.79601,26.82166],"type":"Point"}
}