{
  "type": "Feature",
  "properties": {
    "gn:admin1_code":"24.0",
    "gn:asciiname":"Donglishang",
    "gn:country_code":"CN",
    "gn:dem":1369,
    "gn:feature_class":"P",
    "gn:feature_code":"PPL",
    "gn:name":"Donglishang",
    "gn:population":0,
    "gn:timezone":"Asia/Shanghai",
    "iso:country":"CN",
    "name:zho_x_preferred":[
        "\u4e1c\u91cc\u4e0a"
    ],
    "wof:name":"Donglishang",
    "wof:placetype":"locality"
},
  "geometry": {"coordinates":[112.12257,38.32951],"type":"Point"}
}