{
  "type": "Feature",
  "properties": {
    "gn:admin1_code":"1.0",
    "gn:asciiname":"Gushan",
    "gn:country_code":"CN",
    "gn:dem":144,
    "gn:feature_class":"P",
    "gn:feature_code":"PPL",
    "gn:name":"Gushan",
    "gn:population":0,
    "gn:timezone":"Asia/Shanghai",
    "iso:country":"CN",
    "name:ceb_x_preferred":[
        "Gushan"
    ],
    "name:deu_x_preferred":[
        "Gushan"
    ],
    "name:swe_x_preferred":[
        "Gushan"
    ],
    "name:zho_x_preferred":[
        "\u8c37\u5c71"
    ],
    "wof:name":"Gushan",
    "wof:placetype":"locality"
},
  "geometry": {"coordinates":[118.25432000000001,29.85785],"type":"Point"}
}