{
  "type": "Feature",
  "properties": {
    "gn:admin1_code":"19.0",
    "gn:asciiname":"Tujiatun",
    "gn:country_code":"CN",
    "gn:dem":201,
    "gn:feature_class":"P",
    "gn:feature_code":"PPL",
    "gn:name":"Tujiatun",
    "gn:population":0,
    "gn:timezone":"Asia/Shanghai",
    "iso:country":"CN",
    "name:zho_x_preferred":[
        "\u6d82\u5bb6\u5c6f"
    ],
    "wof:name":"Tujiatun",
    "wof:placetype":"locality"
},
  "geometry": {"coordinates":[120.41661999999999,40.89614],"type":"Point"}
}