{
  "type": "Feature",
  "properties": {
    "gn:admin1_code":"9.0",
    "gn:asciiname":"Dongjingzhuang",
    "gn:country_code":"CN",
    "gn:dem":96,
    "gn:feature_class":"P",
    "gn:feature_code":"PPL",
    "gn:name":"Dongjingzhuang",
    "gn:population":0,
    "gn:timezone":"Asia/Shanghai",
    "iso:country":"CN",
    "name:zho_x_preferred":[
        "\u4e1c\u4e95\u5e84"
    ],
    "wof:name":"Dongjingzhuang",
    "wof:placetype":"locality"
},
  "geometry": {"coordinates":[113.98963000000001,32.39899],"type":"Point"}
}