{
  "type": "Feature",
  "properties": {
    "gn:admin1_code":"11.0",
    "gn:asciiname":"Baiguojiao",
    "gn:country_code":"CN",
    "gn:dem":480,
    "gn:feature_class":"P",
    "gn:feature_code":"PPL",
    "gn:name":"Baiguojiao",
    "gn:population":0,
    "gn:timezone":"Asia/Shanghai",
    "iso:country":"CN",
    "name:zho_x_preferred":[
        "\u767d\u679c\u811a"
    ],
    "wof:name":"Baiguojiao",
    "wof:placetype":"locality"
},
  "geometry": {"coordinates":[111.75019,26.05879],"type":"Point"}
}