{
  "type": "Feature",
  "properties": {
    "gn:admin1_code":"19.0",
    "gn:asciiname":"Xialiuzhangzi",
    "gn:country_code":"CN",
    "gn:dem":430,
    "gn:feature_class":"P",
    "gn:feature_code":"PPL",
    "gn:name":"Xialiuzhangzi",
    "gn:population":0,
    "gn:timezone":"Asia/Shanghai",
    "iso:country":"CN",
    "name:zho_x_preferred":[
        "\u4e0b\u67f3\u6756\u5b50"
    ],
    "wof:name":"Xialiuzhangzi",
    "wof:placetype":"locality"
},
  "geometry": {"coordinates":[120.05758,41.05737],"type":"Point"}
}