{
  "type": "Feature",
  "properties": {
    "gn:admin1_code":"19",
    "gn:asciiname":"Songzigou",
    "gn:country_code":"CN",
    "gn:dem":477,
    "gn:feature_class":"P",
    "gn:feature_code":"PPL",
    "gn:name":"Songzigou",
    "gn:population":0,
    "gn:timezone":"Asia/Shanghai",
    "iso:country":"CN",
    "name:und_x_variant":[
        "\u5b8b\u5bb6\u6c9f"
    ],
    "wof:name":"Songzigou",
    "wof:placetype":"locality"
},
  "geometry": {"coordinates":[124.96975,41.56829000000001],"type":"Point"}
}