{
  "type": "Feature",
  "properties": {
    "gn:admin1_code":"29.0",
    "gn:asciiname":"Dajishu",
    "gn:country_code":"CN",
    "gn:dem":2369,
    "gn:feature_class":"P",
    "gn:feature_code":"PPL",
    "gn:name":"Dajishu",
    "gn:population":0,
    "gn:timezone":"Asia/Shanghai",
    "iso:country":"CN",
    "name:zho_x_preferred":[
        "\u5927\u5b63\u6811"
    ],
    "wof:name":"Dajishu",
    "wof:placetype":"locality"
},
  "geometry": {"coordinates":[102.777,25.438],"type":"Point"}
}