{
  "type": "Feature",
  "properties": {
    "gn:admin1_code":"29.0",
    "gn:asciiname":"Ciguzhai",
    "gn:country_code":"CN",
    "gn:dem":2090,
    "gn:feature_class":"P",
    "gn:feature_code":"PPL",
    "gn:name":"Ciguzhai",
    "gn:population":0,
    "gn:timezone":"Asia/Shanghai",
    "iso:country":"CN",
    "name:zho_x_preferred":[
        "\u8328\u83c7\u5be8"
    ],
    "wof:name":"Ciguzhai",
    "wof:placetype":"locality"
},
  "geometry": {"coordinates":[99.244,24.8017],"type":"Point"}
}