{
  "type": "Feature",
  "properties": {
    "gn:admin1_code":"26.0",
    "gn:asciiname":"Sujia Getai",
    "gn:country_code":"CN",
    "gn:dem":1226,
    "gn:feature_class":"P",
    "gn:feature_code":"PPL",
    "gn:name":"Sujia Getai",
    "gn:population":0,
    "gn:timezone":"Asia/Shanghai",
    "iso:country":"CN",
    "name:zho_x_preferred":[
        "\u82cf\u5bb6\u7599\u53f0"
    ],
    "wof:name":"Sujia Getai",
    "wof:placetype":"locality"
},
  "geometry": {"coordinates":[110.688,38.8741],"type":"Point"}
}