{
  "type": "Feature",
  "properties": {
    "gn:admin1_code":"6.0",
    "gn:asciiname":"Kugri",
    "gn:country_code":"CN",
    "gn:dem":3706,
    "gn:feature_class":"P",
    "gn:feature_code":"PPLA4",
    "gn:name":"Kugri",
    "gn:population":0,
    "gn:timezone":"Asia/Urumqi",
    "iso:country":"CN",
    "name:mon_x_preferred":[
        "Kugri"
    ],
    "name:und_x_variant":[
        "Gouli",
        "Gouli Xiang",
        "Qurina"
    ],
    "name:zho_x_preferred":[
        "\u6c9f\u91cc"
    ],
    "name:zho_x_variant":[
        "\u6c9f\u91cc\u4e61",
        "\u66f2\u65e5\u7eb3"
    ],
    "wof:name":"Kugri",
    "wof:placetype":"locality"
},
  "geometry": {"coordinates":[98.40985999999999,35.65924000000001],"type":"Point"}
}