{
  "type": "Feature",
  "properties": {
    "gn:admin1_code":"11.0",
    "gn:asciiname":"Luogongchong",
    "gn:country_code":"CN",
    "gn:dem":434,
    "gn:feature_class":"P",
    "gn:feature_code":"PPL",
    "gn:name":"Luogongchong",
    "gn:population":0,
    "gn:timezone":"Asia/Shanghai",
    "iso:country":"CN",
    "name:zho_x_preferred":[
        "\u7f57\u516c\u51b2"
    ],
    "wof:name":"Luogongchong",
    "wof:placetype":"locality"
},
  "geometry": {"coordinates":[109.75591,26.31119],"type":"Point"}
}