{
  "type": "Feature",
  "properties": {
    "gn:admin1_code":"11.0",
    "gn:asciiname":"Yangshu",
    "gn:country_code":"CN",
    "gn:dem":128,
    "gn:feature_class":"P",
    "gn:feature_code":"PPL",
    "gn:name":"Yangshu",
    "gn:population":0,
    "gn:timezone":"Asia/Shanghai",
    "iso:country":"CN",
    "name:zho_x_preferred":[
        "Yangshu"
    ],
    "name:zho_x_variant":[
        "\u6768\u6811"
    ],
    "wof:name":"Yangshu",
    "wof:placetype":"locality"
},
  "geometry": {"coordinates":[114.03317,28.83733],"type":"Point"}
}