{
  "type": "Feature",
  "properties": {
    "gn:admin1_code":"14.0",
    "gn:asciiname":"Kyingo",
    "gn:country_code":"CN",
    "gn:dem":4322,
    "gn:feature_class":"P",
    "gn:feature_code":"PPL",
    "gn:name":"Kyingo",
    "gn:population":0,
    "gn:timezone":"Asia/Urumqi",
    "iso:country":"CN",
    "name:bod_x_preferred":[
        "Kyingo"
    ],
    "name:zho_x_preferred":[
        "Qigu"
    ],
    "name:zho_x_variant":[
        "\u8d77\u8c37"
    ],
    "wof:name":"Kyingo",
    "wof:placetype":"locality"
},
  "geometry": {"coordinates":[96.30200000000001,31.302],"type":"Point"}
}