{
  "type": "Feature",
  "properties": {
    "gn:admin1_code":"32.0",
    "gn:asciiname":"Chengzhengong",
    "gn:country_code":"CN",
    "gn:dem":411,
    "gn:feature_class":"P",
    "gn:feature_code":"PPL",
    "gn:name":"Chengzhengong",
    "gn:population":0,
    "gn:timezone":"Asia/Shanghai",
    "iso:country":"CN",
    "name:zho_x_preferred":[
        "\u7a0b\u771f\u5bab"
    ],
    "wof:name":"Chengzhengong",
    "wof:placetype":"locality"
},
  "geometry": {"coordinates":[105.879,31.0374],"type":"Point"}
}