{
  "type": "Feature",
  "properties": {
    "gn:admin1_code":"7.0",
    "gn:asciiname":"Houfeng",
    "gn:country_code":"CN",
    "gn:dem":884,
    "gn:feature_class":"P",
    "gn:feature_code":"PPL",
    "gn:name":"Houfeng",
    "gn:population":0,
    "gn:timezone":"Asia/Shanghai",
    "iso:country":"CN",
    "name:zho_x_preferred":[
        "\u540e\u5cf0"
    ],
    "wof:name":"Houfeng",
    "wof:placetype":"locality"
},
  "geometry": {"coordinates":[118.93107999999999,26.44262],"type":"Point"}
}