{
  "type": "Feature",
  "properties": {
    "gn:admin1_code":"29.0",
    "gn:asciiname":"Shigangping",
    "gn:country_code":"CN",
    "gn:dem":809,
    "gn:feature_class":"P",
    "gn:feature_code":"PPL",
    "gn:name":"Shigangping",
    "gn:population":0,
    "gn:timezone":"Asia/Shanghai",
    "iso:country":"CN",
    "name:und_x_variant":[
        "\u77f3\u7f38\u576a"
    ],
    "wof:name":"Shigangping",
    "wof:placetype":"locality"
},
  "geometry": {"coordinates":[104.17683,28.5061],"type":"Point"}
}