{
  "type": "Feature",
  "properties": {
    "gn:admin1_code":"8.0",
    "gn:asciiname":"Changxing Sidui",
    "gn:country_code":"CN",
    "gn:dem":183,
    "gn:feature_class":"P",
    "gn:feature_code":"PPLF",
    "gn:name":"Changxing Sidui",
    "gn:population":0,
    "gn:timezone":"Asia/Shanghai",
    "iso:country":"CN",
    "name:zho_x_preferred":[
        "\u957f\u5174\u56db\u961f"
    ],
    "wof:name":"Changxing Sidui",
    "wof:placetype":"locality"
},
  "geometry": {"coordinates":[130.86734999999999,45.8968],"type":"Point"}
}