{
  "type": "Feature",
  "properties": {
    "gn:admin1_code":"24.0",
    "gn:asciiname":"Cuijiaya",
    "gn:country_code":"CN",
    "gn:dem":1033,
    "gn:feature_class":"P",
    "gn:feature_code":"PPL",
    "gn:name":"Cuijiaya",
    "gn:population":0,
    "gn:timezone":"Asia/Shanghai",
    "iso:country":"CN",
    "name:zho_x_preferred":[
        "\u5d14\u5bb6\u5d16"
    ],
    "wof:name":"Cuijiaya",
    "wof:placetype":"locality"
},
  "geometry": {"coordinates":[111.10563,37.52276],"type":"Point"}
}