{
  "type": "Feature",
  "properties": {
    "gn:admin1_code":"21.0",
    "gn:asciiname":"Lujia Yingzi",
    "gn:country_code":"CN",
    "gn:dem":1094,
    "gn:feature_class":"P",
    "gn:feature_code":"PPL",
    "gn:name":"Lujia Yingzi",
    "gn:population":0,
    "gn:timezone":"Asia/Shanghai",
    "iso:country":"CN",
    "name:zho_x_preferred":[
        "\u8def\u5bb6\u8425\u5b50"
    ],
    "wof:name":"Lujia Yingzi",
    "wof:placetype":"locality"
},
  "geometry": {"coordinates":[106.56,39.0334],"type":"Point"}
}