{
  "type": "Feature",
  "properties": {
    "gn:admin1_code":"7",
    "gn:asciiname":"Liyang",
    "gn:country_code":"CN",
    "gn:dem":851,
    "gn:feature_class":"P",
    "gn:feature_code":"PPL",
    "gn:name":"Liyang",
    "gn:population":0,
    "gn:timezone":"Asia/Shanghai",
    "iso:country":"CN",
    "name:cym_x_preferred":[
        "Liyang"
    ],
    "name:deu_x_preferred":[
        "Liyang"
    ],
    "name:fra_x_preferred":[
        "Liyang"
    ],
    "name:ita_x_preferred":[
        "Liyang"
    ],
    "name:jpn_x_preferred":[
        "\u30ea\u30c4\u967d\u5e02"
    ],
    "name:kik_x_preferred":[
        "Liyang"
    ],
    "name:kor_x_preferred":[
        "\ub9ac\uc591\uc2dc"
    ],
    "name:nld_x_preferred":[
        "Liyang"
    ],
    "name:nor_x_preferred":[
        "Liyang"
    ],
    "name:rus_x_preferred":[
        "\u041b\u0438\u044f\u043d"
    ],
    "name:swe_x_preferred":[
        "Liyang"
    ],
    "name:tgl_x_preferred":[
        "Liyang"
    ],
    "name:urd_x_preferred":[
        "\u0644\u06cc\u0626\u0627\u0646\u06af"
    ],
    "name:vie_x_preferred":[
        "L\u1eadt D\u01b0\u01a1ng"
    ],
    "name:wuu_x_preferred":[
        "\u6ea7\u9633\u5e02"
    ],
    "name:zho_x_preferred":[
        "\u91cc\u6d0b"
    ],
    "name:zho_x_variant":[
        "\u6ea7\u9633\u5e02"
    ],
    "wof:name":"Liyang",
    "wof:placetype":"locality"
},
  "geometry": {"coordinates":[118.59159,25.71743],"type":"Point"}
}