{
  "type": "Feature",
  "properties": {
    "gn:admin1_code":"7",
    "gn:asciiname":"Liyang",
    "gn:country_code":"CN",
    "gn:dem":851,
    "gn:feature_class":"P",
    "gn:feature_code":"PPL",
    "gn:name":"Liyang",
    "gn:population":0,
    "gn:timezone":"Asia/Shanghai",
    "iso:country":"CN",
    "name:zho_x_preferred":[
        "\u91cc\u6d0b"
    ],
    "wof:name":"Liyang",
    "wof:placetype":"locality"
},
  "geometry": {"coordinates":[118.59159,25.71743],"type":"Point"}
}