{
  "type": "Feature",
  "properties": {
    "gn:admin1_code":"12.0",
    "gn:asciiname":"Pingkeng",
    "gn:country_code":"CN",
    "gn:dem":703,
    "gn:feature_class":"P",
    "gn:feature_code":"PPL",
    "gn:name":"Pingkeng",
    "gn:population":0,
    "gn:timezone":"Asia/Shanghai",
    "iso:country":"CN",
    "name:zho_x_preferred":[
        "Pingkeng"
    ],
    "name:zho_x_variant":[
        "\u576a\u5751"
    ],
    "wof:name":"Pingkeng",
    "wof:placetype":"locality"
},
  "geometry": {"coordinates":[114.50339,29.39637],"type":"Point"}
}