{
  "type": "Feature",
  "properties": {
    "gn:admin1_code":"14.0",
    "gn:asciiname":"Lingdui",
    "gn:country_code":"CN",
    "gn:dem":3676,
    "gn:feature_class":"P",
    "gn:feature_code":"PPL",
    "gn:name":"Lingdui",
    "gn:population":0,
    "gn:timezone":"Asia/Urumqi",
    "iso:country":"CN",
    "name:zho_x_preferred":[
        "\u5cad\u5806"
    ],
    "wof:name":"Lingdui",
    "wof:placetype":"locality"
},
  "geometry": {"coordinates":[92.75691999999999,29.11981],"type":"Point"}
}