{
  "type": "Feature",
  "properties": {
    "gn:admin1_code":"11.0",
    "gn:asciiname":"Bajiaoting",
    "gn:country_code":"CN",
    "gn:dem":328,
    "gn:feature_class":"P",
    "gn:feature_code":"PPL",
    "gn:name":"Bajiaoting",
    "gn:population":0,
    "gn:timezone":"Asia/Shanghai",
    "iso:country":"CN",
    "name:zho_x_preferred":[
        "\u516b\u89d2\u4ead"
    ],
    "wof:name":"Bajiaoting",
    "wof:placetype":"locality"
},
  "geometry": {"coordinates":[110.98123,27.01123],"type":"Point"}
}