{
  "type": "Feature",
  "properties": {
    "gn:admin1_code":"18.0",
    "gn:asciiname":"Doushan",
    "gn:country_code":"CN",
    "gn:dem":1293,
    "gn:feature_class":"P",
    "gn:feature_code":"PPL",
    "gn:name":"Doushan",
    "gn:population":0,
    "gn:timezone":"Asia/Shanghai",
    "iso:country":"CN",
    "name:fas_x_preferred":[
        "\u062f\u0648\u06cc\u0634\u0627\u0646"
    ],
    "name:zho_x_preferred":[
        "\u9661\u5c71"
    ],
    "name:zho_x_variant":[
        "\u6597\u5c71\u9547"
    ],
    "wof:name":"Doushan",
    "wof:placetype":"locality"
},
  "geometry": {"coordinates":[107.345,26.8476],"type":"Point"}
}