{
  "type": "Feature",
  "properties": {
    "gn:admin1_code":"11.0",
    "gn:asciiname":"Zhaojiawan",
    "gn:country_code":"CN",
    "gn:dem":99,
    "gn:feature_class":"P",
    "gn:feature_code":"PPL",
    "gn:name":"Zhaojiawan",
    "gn:population":0,
    "gn:timezone":"Asia/Shanghai",
    "iso:country":"CN",
    "name:zho_x_preferred":[
        "Zhaojiawan"
    ],
    "name:zho_x_variant":[
        "\u8d75\u5bb6\u6e7e"
    ],
    "wof:name":"Zhaojiawan",
    "wof:placetype":"locality"
},
  "geometry": {"coordinates":[111.23515,28.9573],"type":"Point"}
}