{
  "type": "Feature",
  "properties": {
    "gn:admin1_code":"6.0",
    "gn:asciiname":"Moingar",
    "gn:country_code":"CN",
    "gn:dem":4494,
    "gn:feature_class":"P",
    "gn:feature_code":"PPL",
    "gn:name":"Moingar",
    "gn:population":0,
    "gn:timezone":"Asia/Urumqi",
    "iso:country":"CN",
    "name:bod_x_preferred":[
        "Moingar"
    ],
    "name:zho_x_preferred":[
        "Menga"
    ],
    "name:zho_x_variant":[
        "\u95e8\u560e",
        "Seduo Gongshe",
        "\u8272\u591a\u516c\u793e"
    ],
    "wof:name":"Moingar",
    "wof:placetype":"locality"
},
  "geometry": {"coordinates":[96.20099999999999,31.701],"type":"Point"}
}