{
  "type": "Feature",
  "properties": {
    "gn:admin1_code":"1.0",
    "gn:asciiname":"Zhaoyingcun",
    "gn:country_code":"CN",
    "gn:dem":25,
    "gn:feature_class":"P",
    "gn:feature_code":"PPL",
    "gn:name":"Zhaoyingcun",
    "gn:population":0,
    "gn:timezone":"Asia/Shanghai",
    "iso:country":"CN",
    "name:zho_x_preferred":[
        "\u627e\u8425\u6751"
    ],
    "wof:name":"Zhaoyingcun",
    "wof:placetype":"locality"
},
  "geometry": {"coordinates":[117.65148000000001,33.76653],"type":"Point"}
}