{
  "type": "Feature",
  "properties": {
    "gn:admin1_code":"14",
    "gn:asciiname":"Zongcun",
    "gn:country_code":"CN",
    "gn:dem":4598,
    "gn:feature_class":"P",
    "gn:feature_code":"PPL",
    "gn:name":"Zongcun",
    "gn:population":0,
    "gn:timezone":"Asia/Urumqi",
    "iso:country":"CN",
    "name:zho_x_preferred":[
        "\u5b97\u6751"
    ],
    "wof:name":"Zongcun",
    "wof:placetype":"locality"
},
  "geometry": {"coordinates":[89.0517,29.8346],"type":"Point"}
}