{
  "type": "Feature",
  "properties": {
    "gn:admin1_code":"11.0",
    "gn:asciiname":"Bazikeng",
    "gn:country_code":"CN",
    "gn:dem":458,
    "gn:feature_class":"P",
    "gn:feature_code":"PPL",
    "gn:name":"Bazikeng",
    "gn:population":0,
    "gn:timezone":"Asia/Shanghai",
    "iso:country":"CN",
    "name:zho_x_preferred":[
        "\u516b\u5b57\u5751"
    ],
    "wof:name":"Bazikeng",
    "wof:placetype":"locality"
},
  "geometry": {"coordinates":[113.76063000000001,26.18942],"type":"Point"}
}