{
  "type": "Feature",
  "properties": {
    "gn:admin1_code":"11.0",
    "gn:asciiname":"Shangshutouxi",
    "gn:country_code":"CN",
    "gn:dem":493,
    "gn:feature_class":"P",
    "gn:feature_code":"PPL",
    "gn:name":"Shangshutouxi",
    "gn:population":0,
    "gn:timezone":"Asia/Shanghai",
    "iso:country":"CN",
    "name:zho_x_preferred":[
        "\u4e0a\u68b3\u5934\u6eaa"
    ],
    "wof:name":"Shangshutouxi",
    "wof:placetype":"locality"
},
  "geometry": {"coordinates":[109.85576,28.63162],"type":"Point"}
}