{
  "type": "Feature",
  "properties": {
    "gn:admin1_code":"29.0",
    "gn:asciiname":"Zhejiatian Mafengcun",
    "gn:country_code":"CN",
    "gn:dem":1932,
    "gn:feature_class":"P",
    "gn:feature_code":"PPL",
    "gn:name":"Zhejiatian Mafengcun",
    "gn:population":0,
    "gn:timezone":"Asia/Shanghai",
    "iso:country":"CN",
    "name:zho_x_preferred":[
        "\u8005\u5bb6\u7530\u9ebb\u75af\u6751"
    ],
    "wof:name":"Zhejiatian Mafengcun",
    "wof:placetype":"locality"
},
  "geometry": {"coordinates":[101.968,25.2199],"type":"Point"}
}