{
  "type": "Feature",
  "properties": {
    "gn:admin1_code":"18",
    "gn:asciiname":"Meizichong",
    "gn:country_code":"CN",
    "gn:dem":1184,
    "gn:feature_class":"P",
    "gn:feature_code":"PPL",
    "gn:name":"Meizichong",
    "gn:population":0,
    "gn:timezone":"Asia/Shanghai",
    "iso:country":"CN",
    "name:zho_x_preferred":[
        "\u6885\u5b50\u51b2"
    ],
    "wof:name":"Meizichong",
    "wof:placetype":"locality"
},
  "geometry": {"coordinates":[105.959,25.835],"type":"Point"}
}