{
  "type": "Feature",
  "properties": {
    "gn:admin1_code":"9.0",
    "gn:asciiname":"Miaozhuang",
    "gn:country_code":"CN",
    "gn:dem":143,
    "gn:feature_class":"P",
    "gn:feature_code":"PPL",
    "gn:name":"Miaozhuang",
    "gn:population":0,
    "gn:timezone":"Asia/Shanghai",
    "iso:country":"CN",
    "name:zho_x_preferred":[
        "\u82d7\u5e84"
    ],
    "wof:name":"Miaozhuang",
    "wof:placetype":"locality"
},
  "geometry": {"coordinates":[112.51352,33.03005],"type":"Point"}
}