{
  "type": "Feature",
  "properties": {
    "gn:admin1_code":"31.0",
    "gn:asciiname":"Lezhong Nongchang Shi'erdui",
    "gn:country_code":"CN",
    "gn:dem":188,
    "gn:feature_class":"P",
    "gn:feature_code":"PPLF",
    "gn:name":"Lezhong Nongchang Shi\u2019erdui",
    "gn:population":0,
    "gn:timezone":"Asia/Shanghai",
    "iso:country":"CN",
    "name:und_x_variant":[
        "Lezhong Nongchang Shi\u2019erdui",
        "\u4e50\u4e2d\u519c\u573a\u5341\u4e8c\u961f"
    ],
    "wof:name":"Lezhong Nongchang Shi'erdui",
    "wof:placetype":"locality"
},
  "geometry": {"coordinates":[109.27717,18.73937],"type":"Point"}
}