{
  "type": "Feature",
  "properties": {
    "gn:admin1_code":"33.0",
    "gn:asciiname":"Yuhe",
    "gn:country_code":"CN",
    "gn:dem":624,
    "gn:feature_class":"P",
    "gn:feature_code":"PPL",
    "gn:name":"Yuhe",
    "gn:population":0,
    "gn:timezone":"Asia/Shanghai",
    "iso:country":"CN",
    "name:zho_x_preferred":[
        "\u7389\u5408"
    ],
    "wof:name":"Yuhe",
    "wof:placetype":"locality"
},
  "geometry": {"coordinates":[107.82846000000001,29.76372000000001],"type":"Point"}
}