{
  "type": "Feature",
  "properties": {
    "gn:admin1_code":"19.0",
    "gn:asciiname":"Bei'anjia Buzi",
    "gn:country_code":"CN",
    "gn:dem":126,
    "gn:feature_class":"P",
    "gn:feature_code":"PPL",
    "gn:name":"Bei\u2019anjia Buzi",
    "gn:population":0,
    "gn:timezone":"Asia/Shanghai",
    "iso:country":"CN",
    "name:und_x_variant":[
        "Bei\u2019anjia Buzi"
    ],
    "name:zho_x_preferred":[
        "\u5317\u5b89\u5bb6\u5821\u5b50"
    ],
    "wof:name":"Bei'anjia Buzi",
    "wof:placetype":"locality"
},
  "geometry": {"coordinates":[124.012,40.4676],"type":"Point"}
}