{
  "type": "Feature",
  "properties": {
    "gn:admin1_code":"26",
    "gn:asciiname":"Hongmiao",
    "gn:country_code":"CN",
    "gn:dem":639,
    "gn:feature_class":"P",
    "gn:feature_code":"PPLA4",
    "gn:name":"Hongmiao",
    "gn:population":0,
    "gn:timezone":"Asia/Shanghai",
    "iso:country":"CN",
    "name:und_x_variant":[
        "Hung-miao",
        "Hung-miao-t\u2019ang",
        "Hongmiaotang",
        "Hongmiao",
        "\u7ea2\u5e99",
        "Hongmiao Zhen",
        "\u7ea2\u5e99\u9547"
    ],
    "wof:name":"Hongmiao",
    "wof:placetype":"locality"
},
  "geometry": {"coordinates":[106.91358,32.86439],"type":"Point"}
}