{
  "type": "Feature",
  "properties": {
    "gn:admin1_code":"2.0",
    "gn:asciiname":"Zhongguan",
    "gn:country_code":"CN",
    "gn:dem":9,
    "gn:feature_class":"P",
    "gn:feature_code":"PPLA4",
    "gn:name":"Zhongguan",
    "gn:population":0,
    "gn:timezone":"Asia/Shanghai",
    "iso:country":"CN",
    "name:und_x_variant":[
        "Chung-kuan-chen",
        "Chung-kuan",
        "Zhongguan",
        "\u949f\u7ba1",
        "Zhongguan Zhen",
        "\u949f\u7ba1\u9547"
    ],
    "wof:name":"Zhongguan",
    "wof:placetype":"locality"
},
  "geometry": {"coordinates":[120.18451,30.64958],"type":"Point"}
}