{
  "type": "Feature",
  "properties": {
    "gn:admin1_code":"24.0",
    "gn:asciiname":"Xishuiquan",
    "gn:country_code":"CN",
    "gn:dem":1086,
    "gn:feature_class":"P",
    "gn:feature_code":"PPL",
    "gn:name":"Xishuiquan",
    "gn:population":0,
    "gn:timezone":"Asia/Shanghai",
    "iso:country":"CN",
    "name:und_x_variant":[
        "\u897f\u6c34\u6cc9"
    ],
    "name:zho_x_preferred":[
        "\u897f\u6c34\u6cc9"
    ],
    "wof:name":"Xishuiquan",
    "wof:placetype":"locality"
},
  "geometry": {"coordinates":[113.40976999999999,39.24161],"type":"Point"}
}