{
  "type": "Feature",
  "properties": {
    "gn:admin1_code":"32.0",
    "gn:asciiname":"Shigongsi",
    "gn:country_code":"CN",
    "gn:dem":317,
    "gn:feature_class":"P",
    "gn:feature_code":"PPL",
    "gn:name":"Shigongsi",
    "gn:population":0,
    "gn:timezone":"Asia/Shanghai",
    "iso:country":"CN",
    "name:zho_x_preferred":[
        "\u77f3\u8d21\u5bfa"
    ],
    "wof:name":"Shigongsi",
    "wof:placetype":"locality"
},
  "geometry": {"coordinates":[105.03498,29.13936],"type":"Point"}
}