{
  "type": "Feature",
  "properties": {
    "gn:admin1_code":"12.0",
    "gn:asciiname":"Baguamiao",
    "gn:country_code":"CN",
    "gn:dem":1299,
    "gn:feature_class":"P",
    "gn:feature_code":"PPL",
    "gn:name":"Baguamiao",
    "gn:population":0,
    "gn:timezone":"Asia/Shanghai",
    "iso:country":"CN",
    "name:zho_x_preferred":[
        "\u516b\u5366\u5e99"
    ],
    "wof:name":"Baguamiao",
    "wof:placetype":"locality"
},
  "geometry": {"coordinates":[110.55683999999999,31.76142],"type":"Point"}
}