{
  "type": "Feature",
  "properties": {
    "gn:admin1_code":"04",
    "gn:asciiname":"Yaojiatan",
    "gn:cc2":"CN",
    "gn:country_code":"CN",
    "gn:dem":4,
    "gn:feature_class":"P",
    "gn:feature_code":"PPL",
    "gn:name":"Yaojiatan",
    "gn:population":0,
    "gn:timezone":"Asia/Shanghai",
    "iso:country":"CN",
    "name:und_x_variant":[
        "Ni-chia-t\u2019an",
        "Yaojiatan"
    ],
    "wof:name":"Yaojiatan",
    "wof:placetype":"locality"
},
  "geometry": {"coordinates":[121.06111,31.72694000000001],"type":"Point"}
}