{
  "type": "Feature",
  "properties": {
    "gn:admin1_code":"24.0",
    "gn:asciiname":"Yaozhuang",
    "gn:country_code":"CN",
    "gn:dem":919,
    "gn:feature_class":"P",
    "gn:feature_code":"PPL",
    "gn:name":"Yaozhuang",
    "gn:population":0,
    "gn:timezone":"Asia/Shanghai",
    "iso:country":"CN",
    "name:und_x_variant":[
        "\u8170\u5e84"
    ],
    "wof:name":"Yaozhuang",
    "wof:placetype":"locality"
},
  "geometry": {"coordinates":[111.48165,35.2133],"type":"Point"}
}