{
  "type": "Feature",
  "properties": {
    "gn:admin1_code":"19.0",
    "gn:asciiname":"Yanjiabu",
    "gn:country_code":"CN",
    "gn:dem":120,
    "gn:feature_class":"P",
    "gn:feature_code":"PPL",
    "gn:name":"Yanjiabu",
    "gn:population":0,
    "gn:timezone":"Asia/Shanghai",
    "iso:country":"CN",
    "name:und_x_variant":[
        "Yanjiabao",
        "Yanjiabu"
    ],
    "name:zho_x_preferred":[
        "\u960e\u5bb6\u5821"
    ],
    "wof:name":"Yanjiabu",
    "wof:placetype":"locality"
},
  "geometry": {"coordinates":[123.86998,40.42454],"type":"Point"}
}