{
  "type": "Feature",
  "properties": {
    "gn:admin1_code":"29.0",
    "gn:asciiname":"Xishacun",
    "gn:country_code":"CN",
    "gn:dem":1374,
    "gn:feature_class":"P",
    "gn:feature_code":"PPL",
    "gn:name":"Xishacun",
    "gn:population":0,
    "gn:timezone":"Asia/Shanghai",
    "iso:country":"CN",
    "name:zho_x_preferred":[
        "\u7ec6\u6c99\u6751"
    ],
    "wof:name":"Xishacun",
    "wof:placetype":"locality"
},
  "geometry": {"coordinates":[103.986,28.0796],"type":"Point"}
}