{
  "type": "Feature",
  "properties": {
    "gn:admin1_code":"29.0",
    "gn:asciiname":"Xiawenpo",
    "gn:country_code":"CN",
    "gn:dem":2266,
    "gn:feature_class":"P",
    "gn:feature_code":"PPL",
    "gn:name":"Xiawenpo",
    "gn:population":0,
    "gn:timezone":"Asia/Shanghai",
    "iso:country":"CN",
    "name:zho_x_preferred":[
        "\u4e0b\u6e29\u5761"
    ],
    "wof:name":"Xiawenpo",
    "wof:placetype":"locality"
},
  "geometry": {"coordinates":[99.7098,25.9605],"type":"Point"}
}