{
  "type": "Feature",
  "properties": {
    "gn:admin1_code":"30.0",
    "gn:asciiname":"Liangxicun",
    "gn:country_code":"CN",
    "gn:dem":180,
    "gn:feature_class":"P",
    "gn:feature_code":"PPL",
    "gn:name":"Liangxicun",
    "gn:population":0,
    "gn:timezone":"Asia/Shanghai",
    "iso:country":"CN",
    "name:zho_x_preferred":[
        "\u826f\u897f\u6751"
    ],
    "wof:name":"Liangxicun",
    "wof:placetype":"locality"
},
  "geometry": {"coordinates":[114.07890999999999,24.30319],"type":"Point"}
}