{
  "type": "Feature",
  "properties": {
    "gn:admin1_code":"9.0",
    "gn:asciiname":"Yaozhuang",
    "gn:country_code":"CN",
    "gn:dem":57,
    "gn:feature_class":"P",
    "gn:feature_code":"PPL",
    "gn:name":"Yaozhuang",
    "gn:population":0,
    "gn:timezone":"Asia/Shanghai",
    "iso:country":"CN",
    "name:zho_x_preferred":[
        "\u59da\u5e84"
    ],
    "wof:name":"Yaozhuang",
    "wof:placetype":"locality"
},
  "geometry": {"coordinates":[114.33327,33.0922],"type":"Point"}
}