{
  "type": "Feature",
  "properties": {
    "gn:admin1_code":"18",
    "gn:asciiname":"Tuochuanya",
    "gn:country_code":"CN",
    "gn:dem":607,
    "gn:feature_class":"P",
    "gn:feature_code":"PPL",
    "gn:name":"Tuochuanya",
    "gn:population":0,
    "gn:timezone":"Asia/Shanghai",
    "iso:country":"CN",
    "name:zho_x_preferred":[
        "\u62d6\u8239\u57ad"
    ],
    "wof:name":"Tuochuanya",
    "wof:placetype":"locality"
},
  "geometry": {"coordinates":[108.158,28.2995],"type":"Point"}
}