{
  "type": "Feature",
  "properties": {
    "gn:admin1_code":"32.0",
    "gn:asciiname":"Tongche",
    "gn:country_code":"CN",
    "gn:dem":290,
    "gn:feature_class":"P",
    "gn:feature_code":"PPL",
    "gn:name":"Tongche",
    "gn:population":0,
    "gn:timezone":"Asia/Shanghai",
    "iso:country":"CN",
    "name:zho_x_preferred":[
        "\u7b52\u8f66"
    ],
    "wof:name":"Tongche",
    "wof:placetype":"locality"
},
  "geometry": {"coordinates":[105.54000000000001,30.024],"type":"Point"}
}