{
  "type": "Feature",
  "properties": {
    "gn:admin1_code":"16.0",
    "gn:asciiname":"Likou",
    "gn:country_code":"CN",
    "gn:dem":164,
    "gn:feature_class":"P",
    "gn:feature_code":"PPL",
    "gn:name":"Likou",
    "gn:population":0,
    "gn:timezone":"Asia/Shanghai",
    "iso:country":"CN",
    "name:zho_x_preferred":[
        "\u529b\u53e3"
    ],
    "wof:name":"Likou",
    "wof:placetype":"locality"
},
  "geometry": {"coordinates":[108.44499999999999,24.1202],"type":"Point"}
}