{
  "type": "Feature",
  "properties": {
    "gn:country":"CN",
    "gn:fcode":"ADM3",
    "gn:pop":0,
    "iso:country":"CN",
    "name:unk_x_variant":[
        "Ch\u2019ing-chen Hsien"
    ],
    "name:zho_x_preferred":[
        "\u6e05\u9547\u5e02"
    ],
    "name:zho_x_variant":[
        "\u6e05\u9547"
    ],
    "qs:name":"Qingzhen Shi",
    "qs:photos_9r":0,
    "qs:photos_sr":0,
    "qs:pop_sr":"0",
    "wof:name":"Qingzhen Shi",
    "wof:placetype":"localadmin",
    "wof:population":0
},
  "geometry": {"coordinates":[106.34832,26.73267],"type":"Point"}
}