{
  "type": "Feature",
  "properties": {
    "gn:admin1_code":"30.0",
    "gn:asciiname":"Huangdong",
    "gn:country_code":"CN",
    "gn:dem":600,
    "gn:feature_class":"P",
    "gn:feature_code":"PPL",
    "gn:name":"Huangdong",
    "gn:population":0,
    "gn:timezone":"Asia/Shanghai",
    "iso:country":"CN",
    "name:zho_x_preferred":[
        "Huangdong"
    ],
    "name:zho_x_variant":[
        "\u9ec4\u6d1e"
    ],
    "wof:name":"Huangdong",
    "wof:placetype":"locality"
},
  "geometry": {"coordinates":[113.6675,25.25778],"type":"Point"}
}