{
  "type": "Feature",
  "properties": {
    "gn:admin1_code":"19.0",
    "gn:asciiname":"Liushanzuizi",
    "gn:country_code":"CN",
    "gn:dem":36,
    "gn:feature_class":"P",
    "gn:feature_code":"PPL",
    "gn:name":"Liushanzuizi",
    "gn:population":0,
    "gn:timezone":"Asia/Shanghai",
    "iso:country":"CN",
    "name:zho_x_preferred":[
        "\u5218\u5c71\u5634\u5b50"
    ],
    "wof:name":"Liushanzuizi",
    "wof:placetype":"locality"
},
  "geometry": {"coordinates":[121.41901,41.3347],"type":"Point"}
}