{
  "type": "Feature",
  "properties": {
    "gn:admin1_code":"33.0",
    "gn:asciiname":"Dongzikou",
    "gn:country_code":"CN",
    "gn:dem":305,
    "gn:feature_class":"P",
    "gn:feature_code":"PPL",
    "gn:name":"Dongzikou",
    "gn:population":0,
    "gn:timezone":"Asia/Shanghai",
    "iso:country":"CN",
    "name:zho_x_preferred":[
        "\u6d1e\u5b50\u53e3"
    ],
    "wof:name":"Dongzikou",
    "wof:placetype":"locality"
},
  "geometry": {"coordinates":[106.03008,29.43589],"type":"Point"}
}