{
  "type": "Feature",
  "properties": {
    "gn:admin1_code":"26.0",
    "gn:asciiname":"Baishubian",
    "gn:country_code":"CN",
    "gn:dem":1174,
    "gn:feature_class":"P",
    "gn:feature_code":"PPL",
    "gn:name":"Baishubian",
    "gn:population":0,
    "gn:timezone":"Asia/Shanghai",
    "iso:country":"CN",
    "name:zho_x_preferred":[
        "\u67cf\u6811\u782d"
    ],
    "wof:name":"Baishubian",
    "wof:placetype":"locality"
},
  "geometry": {"coordinates":[109.25811000000002,36.14573],"type":"Point"}
}