{
  "type": "Feature",
  "properties": {
    "gn:admin1_code":"18",
    "gn:asciiname":"Baiyantou",
    "gn:country_code":"CN",
    "gn:dem":1205,
    "gn:feature_class":"P",
    "gn:feature_code":"PPL",
    "gn:name":"Baiyantou",
    "gn:population":0,
    "gn:timezone":"Asia/Shanghai",
    "iso:country":"CN",
    "name:zho_x_preferred":[
        "\u767d\u5ca9\u5934"
    ],
    "wof:name":"Baiyantou",
    "wof:placetype":"locality"
},
  "geometry": {"coordinates":[106.264,26.8669],"type":"Point"}
}