{
  "type": "Feature",
  "properties": {
    "gn:admin1_code":"29.0",
    "gn:asciiname":"Qikeshu",
    "gn:country_code":"CN",
    "gn:dem":1151,
    "gn:feature_class":"P",
    "gn:feature_code":"PPL",
    "gn:name":"Qikeshu",
    "gn:population":0,
    "gn:timezone":"Asia/Shanghai",
    "iso:country":"CN",
    "name:zho_x_preferred":[
        "\u4e03\u68f5\u6811"
    ],
    "wof:name":"Qikeshu",
    "wof:placetype":"locality"
},
  "geometry": {"coordinates":[100.923,26.1893],"type":"Point"}
}