{
  "type": "Feature",
  "properties": {
    "gn:admin1_code":"1.0",
    "gn:asciiname":"Yangzixucun",
    "gn:country_code":"CN",
    "gn:dem":6,
    "gn:feature_class":"P",
    "gn:feature_code":"PPL",
    "gn:name":"Yangzixucun",
    "gn:population":0,
    "gn:timezone":"Asia/Shanghai",
    "iso:country":"CN",
    "name:zho_x_preferred":[
        "\u6d0b\u5b50\u5729\u6751"
    ],
    "wof:name":"Yangzixucun",
    "wof:placetype":"locality"
},
  "geometry": {"coordinates":[117.9074,31.17094],"type":"Point"}
}