{
  "type": "Feature",
  "properties": {
    "gn:admin1_code":"30",
    "gn:asciiname":"Baishuiqi",
    "gn:country_code":"CN",
    "gn:dem":639,
    "gn:feature_class":"P",
    "gn:feature_code":"PPL",
    "gn:name":"Baishuiqi",
    "gn:population":0,
    "gn:timezone":"Asia/Shanghai",
    "iso:country":"CN",
    "name:zho_x_preferred":[
        "\u767d\u6c34\u78dc"
    ],
    "wof:name":"Baishuiqi",
    "wof:placetype":"locality"
},
  "geometry": {"coordinates":[116.83161,24.1953],"type":"Point"}
}