{
  "type": "Feature",
  "properties": {
    "gn:admin1_code":"12.0",
    "gn:asciiname":"Changtanzi",
    "gn:country_code":"CN",
    "gn:dem":364,
    "gn:feature_class":"P",
    "gn:feature_code":"PPL",
    "gn:name":"Changtanzi",
    "gn:population":0,
    "gn:timezone":"Asia/Shanghai",
    "iso:country":"CN",
    "name:zho_x_preferred":[
        "\u957f\u6ee9\u5b50"
    ],
    "wof:name":"Changtanzi",
    "wof:placetype":"locality"
},
  "geometry": {"coordinates":[109.92574,32.89259000000001],"type":"Point"}
}