{
  "type": "Feature",
  "properties": {
    "gn:admin1_code":"06",
    "gn:asciiname":"Qumarleb",
    "gn:country_code":"CN",
    "gn:dem":4296,
    "gn:feature_class":"P",
    "gn:feature_code":"PPL",
    "gn:name":"Qumarl\u00eab",
    "gn:population":0,
    "gn:timezone":"Asia/Urumqi",
    "iso:country":"CN",
    "name:bod_x_preferred":[
        "\u0f46\u0f74\u0f0b\u0f51\u0f58\u0f62\u0f0b\u0f63\u0f7a\u0f56"
    ],
    "name:und_x_variant":[
        "Shaiwugou"
    ],
    "name:zho_x_preferred":[
        "\u8272\u543e\u6c9f"
    ],
    "wof:name":"Qumarleb",
    "wof:placetype":"locality"
},
  "geometry": {"coordinates":[95.61976,34.55068],"type":"Point"}
}