{
  "type": "Feature",
  "properties": {
    "gn:admin1_code":"18.0",
    "gn:asciiname":"Yuxi",
    "gn:country_code":"CN",
    "gn:dem":686,
    "gn:feature_class":"P",
    "gn:feature_code":"PPLA3",
    "gn:name":"Yuxi",
    "gn:population":0,
    "gn:timezone":"Asia/Shanghai",
    "iso:country":"CN",
    "name:und_x_variant":[
        "Tao-chen-hsien",
        "Tukichang",
        "Y\u00fc-ch\u2019i-chen",
        "Daozhen",
        "Tao-chen",
        "T\u2019u-ch\u2019i-ch\u2019ang",
        "Y\u00fc-ch\u2019i",
        "Y\u00fc-hsi",
        "Yuxi",
        "Daozhen Gelaozu Miaozu Zizhixian",
        "Yuxi Zhen"
    ],
    "name:zho_x_preferred":[
        "\u7389\u6eaa"
    ],
    "name:zho_x_variant":[
        "\u9053\u771f\u4ee1\u4f6c\u65cf\u82d7\u65cf\u81ea\u6cbb\u53bf",
        "\u7389\u6eaa\u9547"
    ],
    "wof:name":"Yuxi",
    "wof:placetype":"locality"
},
  "geometry": {"coordinates":[107.59399999999999,28.889],"type":"Point"}
}