{
  "type": "Feature",
  "properties": {
    "gn:admin1_code":"2.0",
    "gn:asciiname":"Baishuiji",
    "gn:country_code":"CN",
    "gn:dem":883,
    "gn:feature_class":"P",
    "gn:feature_code":"PPL",
    "gn:name":"Baishuiji",
    "gn:population":0,
    "gn:timezone":"Asia/Shanghai",
    "iso:country":"CN",
    "name:zho_x_preferred":[
        "\u767d\u6c34\u6d4e"
    ],
    "wof:name":"Baishuiji",
    "wof:placetype":"locality"
},
  "geometry": {"coordinates":[120.13477,27.98635],"type":"Point"}
}