{
  "type": "Feature",
  "properties": {
    "gn:admin1_code":"7.0",
    "gn:asciiname":"Shaxi",
    "gn:country_code":"CN",
    "gn:dem":720,
    "gn:feature_class":"P",
    "gn:feature_code":"PPL",
    "gn:name":"Shaxi",
    "gn:population":0,
    "gn:timezone":"Asia/Shanghai",
    "iso:country":"CN",
    "name:ceb_x_preferred":[
        "Shaxi"
    ],
    "name:deu_x_preferred":[
        "Shaxi"
    ],
    "name:fra_x_preferred":[
        "Shaxi"
    ],
    "name:swe_x_preferred":[
        "Shaxi"
    ],
    "name:und_x_variant":[
        "\u6749\u6eaa"
    ],
    "name:zho_x_preferred":[
        "\u6749\u6eaa"
    ],
    "wof:name":"Shaxi",
    "wof:placetype":"locality"
},
  "geometry": {"coordinates":[118.07989999999999,26.32425],"type":"Point"}
}