{
  "type": "Feature",
  "properties": {
    "gn:admin1_code":"26.0",
    "gn:asciiname":"Shangjiagou",
    "gn:country_code":"CN",
    "gn:dem":1140,
    "gn:feature_class":"P",
    "gn:feature_code":"PPL",
    "gn:name":"Shangjiagou",
    "gn:population":0,
    "gn:timezone":"Asia/Shanghai",
    "iso:country":"CN",
    "name:zho_x_preferred":[
        "\u5546\u5bb6\u6c9f"
    ],
    "wof:name":"Shangjiagou",
    "wof:placetype":"locality"
},
  "geometry": {"coordinates":[109.65822,33.94146],"type":"Point"}
}