{
  "type": "Feature",
  "properties": {
    "gn:admin1_code":"19.0",
    "gn:asciiname":"Lijiazhangzi",
    "gn:country_code":"CN",
    "gn:dem":297,
    "gn:feature_class":"P",
    "gn:feature_code":"PPL",
    "gn:name":"Lijiazhangzi",
    "gn:population":0,
    "gn:timezone":"Asia/Shanghai",
    "iso:country":"CN",
    "name:zho_x_preferred":[
        "\u674e\u5bb6\u6756\u5b50"
    ],
    "wof:name":"Lijiazhangzi",
    "wof:placetype":"locality"
},
  "geometry": {"coordinates":[120.52187000000001,41.43189],"type":"Point"}
}