{
  "type": "Feature",
  "properties": {
    "gn:admin1_code":"26.0",
    "gn:asciiname":"Yuanjia Chacun",
    "gn:country_code":"CN",
    "gn:dem":1051,
    "gn:feature_class":"P",
    "gn:feature_code":"PPL",
    "gn:name":"Yuanjia Chacun",
    "gn:population":0,
    "gn:timezone":"Asia/Shanghai",
    "iso:country":"CN",
    "name:zho_x_preferred":[
        "\u8881\u5bb6\u5c94\u6751"
    ],
    "wof:name":"Yuanjia Chacun",
    "wof:placetype":"locality"
},
  "geometry": {"coordinates":[110.297,38.0489],"type":"Point"}
}