{
  "type": "Feature",
  "properties": {
    "gn:admin1_code":"12.0",
    "gn:asciiname":"Guanmenshi",
    "gn:country_code":"CN",
    "gn:dem":131,
    "gn:feature_class":"P",
    "gn:feature_code":"PPL",
    "gn:name":"Guanmenshi",
    "gn:population":0,
    "gn:timezone":"Asia/Shanghai",
    "iso:country":"CN",
    "name:zho_x_preferred":[
        "Guanmenshi"
    ],
    "name:zho_x_variant":[
        "\u5173\u95e8\u77f3"
    ],
    "wof:name":"Guanmenshi",
    "wof:placetype":"locality"
},
  "geometry": {"coordinates":[111.36568,30.37889],"type":"Point"}
}