{
  "type": "Feature",
  "properties": {
    "gn:admin1_code":"16.0",
    "gn:asciiname":"Youqi",
    "gn:country_code":"CN",
    "gn:dem":839,
    "gn:feature_class":"P",
    "gn:feature_code":"PPL",
    "gn:name":"Youqi",
    "gn:population":0,
    "gn:timezone":"Asia/Shanghai",
    "iso:country":"CN",
    "name:zho_x_preferred":[
        "\u5c24\u9f50"
    ],
    "wof:name":"Youqi",
    "wof:placetype":"locality"
},
  "geometry": {"coordinates":[107.721,24.0588],"type":"Point"}
}