{
  "type": "Feature",
  "properties": {
    "gn:admin1_code":"4.0",
    "gn:asciiname":"Gongqing",
    "gn:country_code":"CN",
    "gn:dem":6,
    "gn:feature_class":"P",
    "gn:feature_code":"PPL",
    "gn:name":"Gongqing",
    "gn:population":0,
    "gn:timezone":"Asia/Shanghai",
    "iso:country":"CN",
    "name:zho_x_preferred":[
        "\u5171\u5e86"
    ],
    "wof:name":"Gongqing",
    "wof:placetype":"locality"
},
  "geometry": {"coordinates":[120.13030999999999,31.71348],"type":"Point"}
}