{
  "type": "Feature",
  "properties": {
    "gn:admin1_code":"1.0",
    "gn:asciiname":"Kantingcun",
    "gn:country_code":"CN",
    "gn:dem":28,
    "gn:feature_class":"P",
    "gn:feature_code":"PPL",
    "gn:name":"Kantingcun",
    "gn:population":0,
    "gn:timezone":"Asia/Shanghai",
    "iso:country":"CN",
    "name:zho_x_preferred":[
        "\u961a\u753a\u6751"
    ],
    "wof:name":"Kantingcun",
    "wof:placetype":"locality"
},
  "geometry": {"coordinates":[117.21294,33.92612],"type":"Point"}
}