{
  "type": "Feature",
  "properties": {
    "gn:admin1_code":"20",
    "gn:asciiname":"Charbaqi",
    "gn:cc2":"CN",
    "gn:country_code":"CN",
    "gn:dem":387,
    "gn:feature_class":"P",
    "gn:feature_code":"PPL",
    "gn:name":"Charbaqi",
    "gn:population":0,
    "gn:timezone":"Asia/Shanghai",
    "iso:country":"CN",
    "name:eng_x_preferred":[
        "Charbaqi"
    ],
    "name:rus_x_preferred":[
        "\u0427\u0430\u0440\u0431\u0430\u0446\u0438"
    ],
    "name:und_x_variant":[
        "Ch\u2019a-erh-pa-ch\u2019i",
        "Charbaqi"
    ],
    "wof:name":"Charbaqi",
    "wof:placetype":"locality"
},
  "geometry": {"coordinates":[123.09999999999999,48.58333],"type":"Point"}
}