{
  "type": "Feature",
  "properties": {
    "gn:admin1_code":"30.0",
    "gn:asciiname":"Taofengcun",
    "gn:country_code":"CN",
    "gn:dem":242,
    "gn:feature_class":"P",
    "gn:feature_code":"PPL",
    "gn:name":"Taofengcun",
    "gn:population":0,
    "gn:timezone":"Asia/Shanghai",
    "iso:country":"CN",
    "name:zho_x_preferred":[
        "\u6843\u950b\u6751"
    ],
    "wof:name":"Taofengcun",
    "wof:placetype":"locality"
},
  "geometry": {"coordinates":[116.63906,24.07757],"type":"Point"}
}