{
  "type": "Feature",
  "properties": {
    "gn:admin1_code":"33.0",
    "gn:asciiname":"Leizhuang",
    "gn:country_code":"CN",
    "gn:dem":864,
    "gn:feature_class":"P",
    "gn:feature_code":"PPL",
    "gn:name":"Leizhuang",
    "gn:population":0,
    "gn:timezone":"Asia/Shanghai",
    "iso:country":"CN",
    "name:zho_x_preferred":[
        "\u96f7\u5e84"
    ],
    "wof:name":"Leizhuang",
    "wof:placetype":"locality"
},
  "geometry": {"coordinates":[108.10048,29.91107],"type":"Point"}
}