{
  "type": "Feature",
  "properties": {
    "gn:admin1_code":"26",
    "gn:asciiname":"Tiancheng",
    "gn:cc2":"CN",
    "gn:country_code":"CN",
    "gn:dem":1049,
    "gn:feature_class":"P",
    "gn:feature_code":"PPL",
    "gn:name":"Tiancheng",
    "gn:population":0,
    "gn:timezone":"Asia/Shanghai",
    "iso:country":"CN",
    "name:und_x_variant":[
        "T\u2019ien-ch\u2019eng",
        "Tianchengbu",
        "T\u2019ien-ch\u2019eng-pao",
        "Tiancheng"
    ],
    "wof:name":"Tiancheng",
    "wof:placetype":"locality"
},
  "geometry": {"coordinates":[106.73806,34.87583],"type":"Point"}
}