{
  "type": "Feature",
  "properties": {
    "gn:admin1_code":"19.0",
    "gn:asciiname":"Dalongyaozi",
    "gn:country_code":"CN",
    "gn:dem":286,
    "gn:feature_class":"P",
    "gn:feature_code":"PPL",
    "gn:name":"Dalongyaozi",
    "gn:population":0,
    "gn:timezone":"Asia/Shanghai",
    "iso:country":"CN",
    "name:zho_x_preferred":[
        "\u5927\u9f99\u8170\u5b50"
    ],
    "wof:name":"Dalongyaozi",
    "wof:placetype":"locality"
},
  "geometry": {"coordinates":[120.491,41.5054],"type":"Point"}
}