{
  "type": "Feature",
  "properties": {
    "gn:admin1_code":"05",
    "gn:asciiname":"Fangchuancun",
    "gn:country_code":"CN",
    "gn:dem":17,
    "gn:feature_class":"P",
    "gn:feature_code":"PPL",
    "gn:name":"Fangchuancun",
    "gn:population":0,
    "gn:timezone":"Asia/Shanghai",
    "iso:country":"CN",
    "name:und_x_variant":[
        "Fang-ch\u2019uan-ting",
        "Fangchuancun",
        "\u9632\u5ddd\u6751",
        "Hs\u00fc-ting",
        "Xuding",
        "Fangchuanding"
    ],
    "wof:name":"Fangchuancun",
    "wof:placetype":"locality"
},
  "geometry": {"coordinates":[130.58819,42.43716],"type":"Point"}
}