{
  "type": "Feature",
  "properties": {
    "gn:admin1_code":"4.0",
    "gn:asciiname":"Donghuacun",
    "gn:country_code":"CN",
    "gn:dem":4,
    "gn:feature_class":"P",
    "gn:feature_code":"PPL",
    "gn:name":"Donghuacun",
    "gn:population":0,
    "gn:timezone":"Asia/Shanghai",
    "iso:country":"CN",
    "name:und_x_variant":[
        "\u4e1c\u534e\u6751"
    ],
    "name:zho_x_preferred":[
        "\u4e1c\u534e\u6751"
    ],
    "wof:name":"Donghuacun",
    "wof:placetype":"locality"
},
  "geometry": {"coordinates":[120.74634,31.85479],"type":"Point"}
}