{
  "type": "Feature",
  "properties": {
    "gn:admin1_code":"33.0",
    "gn:asciiname":"Ma'an",
    "gn:country_code":"CN",
    "gn:dem":1646,
    "gn:feature_class":"P",
    "gn:feature_code":"PPL",
    "gn:name":"Ma\u2019an",
    "gn:population":0,
    "gn:timezone":"Asia/Shanghai",
    "iso:country":"CN",
    "name:und_x_variant":[
        "Ma\u2019an"
    ],
    "name:zho_x_preferred":[
        "\u9a6c\u978d"
    ],
    "wof:name":"Ma'an",
    "wof:placetype":"locality"
},
  "geometry": {"coordinates":[108.38735,29.98412],"type":"Point"}
}