{
  "type": "Feature",
  "properties": {
    "gn:admin1_code":"32.0",
    "gn:asciiname":"Laolinpo",
    "gn:country_code":"CN",
    "gn:dem":797,
    "gn:feature_class":"P",
    "gn:feature_code":"PPL",
    "gn:name":"Laolinpo",
    "gn:population":0,
    "gn:timezone":"Asia/Shanghai",
    "iso:country":"CN",
    "name:zho_x_preferred":[
        "\u8001\u6797\u5761"
    ],
    "wof:name":"Laolinpo",
    "wof:placetype":"locality"
},
  "geometry": {"coordinates":[107.828,31.6444],"type":"Point"}
}