{
  "type": "Feature",
  "properties": {
    "gn:admin1_code":"29.0",
    "gn:asciiname":"Tongjige",
    "gn:country_code":"CN",
    "gn:dem":3394,
    "gn:feature_class":"P",
    "gn:feature_code":"PPL",
    "gn:name":"Tongjige",
    "gn:population":0,
    "gn:timezone":"Asia/Shanghai",
    "iso:country":"CN",
    "name:zho_x_preferred":[
        "\u901a\u5409\u683c"
    ],
    "wof:name":"Tongjige",
    "wof:placetype":"locality"
},
  "geometry": {"coordinates":[99.0659,28.83],"type":"Point"}
}