{
  "type": "Feature",
  "properties": {
    "gn:admin1_code":"10",
    "gn:asciiname":"Zhaoyi",
    "gn:country_code":"CN",
    "gn:dem":418,
    "gn:feature_class":"P",
    "gn:feature_code":"PPL",
    "gn:name":"Zhaoyi",
    "gn:population":0,
    "gn:timezone":"Asia/Shanghai",
    "iso:country":"CN",
    "name:zho_x_preferred":[
        "\u662d\u4e49"
    ],
    "wof:name":"Zhaoyi",
    "wof:placetype":"locality"
},
  "geometry": {"coordinates":[113.767,36.4463],"type":"Point"}
}