{
  "type": "Feature",
  "properties": {
    "gn:admin1_code":"2.0",
    "gn:asciiname":"Gouwuling",
    "gn:country_code":"CN",
    "gn:dem":302,
    "gn:feature_class":"P",
    "gn:feature_code":"PPL",
    "gn:name":"Gouwuling",
    "gn:population":0,
    "gn:timezone":"Asia/Shanghai",
    "iso:country":"CN",
    "name:zho_x_preferred":[
        "\u72d7\u575e\u5cad"
    ],
    "wof:name":"Gouwuling",
    "wof:placetype":"locality"
},
  "geometry": {"coordinates":[119.41786,28.94469],"type":"Point"}
}