{
  "type": "Feature",
  "properties": {
    "gn:admin1_code":"14.0",
    "gn:asciiname":"Gyixong",
    "gn:country_code":"CN",
    "gn:dem":5682,
    "gn:feature_class":"P",
    "gn:feature_code":"PPLF",
    "gn:name":"Gyixong",
    "gn:population":0,
    "gn:timezone":"Asia/Urumqi",
    "iso:country":"CN",
    "name:bod_x_preferred":[
        "Gyixong"
    ],
    "name:zho_x_preferred":[
        "Jixiong"
    ],
    "name:zho_x_variant":[
        "\u5409\u96c4",
        "Banjiugang",
        "\u73ed\u4e45\u5c97"
    ],
    "wof:name":"Gyixong",
    "wof:placetype":"locality"
},
  "geometry": {"coordinates":[87.301,28.501],"type":"Point"}
}