{
  "type": "Feature",
  "properties": {
    "gn:admin1_code":"29.0",
    "gn:asciiname":"Enjiu",
    "gn:country_code":"CN",
    "gn:dem":1639,
    "gn:feature_class":"P",
    "gn:feature_code":"PPL",
    "gn:name":"Enjiu",
    "gn:population":0,
    "gn:timezone":"Asia/Shanghai",
    "iso:country":"CN",
    "name:zho_x_preferred":[
        "\u6069\u5c31"
    ],
    "wof:name":"Enjiu",
    "wof:placetype":"locality"
},
  "geometry": {"coordinates":[101.71599999999999,26.1517],"type":"Point"}
}