{
  "type": "Feature",
  "properties": {
    "gn:admin1_code":"7.0",
    "gn:asciiname":"Shangwangwen",
    "gn:country_code":"CN",
    "gn:dem":263,
    "gn:feature_class":"P",
    "gn:feature_code":"PPL",
    "gn:name":"Shangwangwen",
    "gn:population":0,
    "gn:timezone":"Asia/Shanghai",
    "iso:country":"CN",
    "name:zho_x_preferred":[
        "\u4e0a\u738b\u6587"
    ],
    "wof:name":"Shangwangwen",
    "wof:placetype":"locality"
},
  "geometry": {"coordinates":[117.36765,27.64151],"type":"Point"}
}