{
  "type": "Feature",
  "properties": {
    "gn:admin1_code":"26.0",
    "gn:asciiname":"Kangjialing",
    "gn:country_code":"CN",
    "gn:dem":1177,
    "gn:feature_class":"P",
    "gn:feature_code":"PPL",
    "gn:name":"Kangjialing",
    "gn:population":0,
    "gn:timezone":"Asia/Shanghai",
    "iso:country":"CN",
    "name:zho_x_preferred":[
        "\u5eb7\u5bb6\u5cad"
    ],
    "wof:name":"Kangjialing",
    "wof:placetype":"locality"
},
  "geometry": {"coordinates":[110.70605,33.77358],"type":"Point"}
}