{
  "type": "Feature",
  "properties": {
    "gn:admin1_code":"30",
    "gn:asciiname":"Tielilang",
    "gn:country_code":"CN",
    "gn:dem":72,
    "gn:feature_class":"P",
    "gn:feature_code":"PPL",
    "gn:name":"Tielilang",
    "gn:population":0,
    "gn:timezone":"Asia/Urumqi",
    "iso:country":"CN",
    "name:zho_x_preferred":[
        "\u94c1\u91cc\u7405"
    ],
    "wof:name":"Tielilang",
    "wof:placetype":"locality"
},
  "geometry": {"coordinates":[111.29476,21.7196],"type":"Point"}
}