{
  "type": "Feature",
  "properties": {
    "gn:admin1_code":"12.0",
    "gn:asciiname":"Magujian",
    "gn:country_code":"CN",
    "gn:dem":184,
    "gn:feature_class":"P",
    "gn:feature_code":"PPL",
    "gn:name":"Magujian",
    "gn:population":0,
    "gn:timezone":"Asia/Shanghai",
    "iso:country":"CN",
    "name:zho_x_preferred":[
        "Magujian"
    ],
    "name:zho_x_variant":[
        "\u9ebb\u9aa8\u5c16"
    ],
    "wof:name":"Magujian",
    "wof:placetype":"locality"
},
  "geometry": {"coordinates":[115.10133999999999,30.77901],"type":"Point"}
}