{
  "type": "Feature",
  "properties": {
    "gn:admin1_code":"29.0",
    "gn:asciiname":"Shiyatian",
    "gn:country_code":"CN",
    "gn:dem":1379,
    "gn:feature_class":"P",
    "gn:feature_code":"PPL",
    "gn:name":"Shiyatian",
    "gn:population":0,
    "gn:timezone":"Asia/Shanghai",
    "iso:country":"CN",
    "name:zho_x_preferred":[
        "\u77f3\u4e2b\u7530"
    ],
    "wof:name":"Shiyatian",
    "wof:placetype":"locality"
},
  "geometry": {"coordinates":[101.17400000000001,22.6958],"type":"Point"}
}