{
  "type": "Feature",
  "properties": {
    "gn:admin1_code":"10.0",
    "gn:asciiname":"Xizhijia",
    "gn:country_code":"CN",
    "gn:dem":64,
    "gn:feature_class":"P",
    "gn:feature_code":"PPL",
    "gn:name":"Xizhijia",
    "gn:population":0,
    "gn:timezone":"Asia/Shanghai",
    "iso:country":"CN",
    "name:und_x_variant":[
        "\u897f\u53ea\u7532"
    ],
    "wof:name":"Xizhijia",
    "wof:placetype":"locality"
},
  "geometry": {"coordinates":[114.73427,38.14827],"type":"Point"}
}