{
  "type": "Feature",
  "properties": {
    "gn:admin1_code":"2.0",
    "gn:asciiname":"Yushiqiao",
    "gn:country_code":"CN",
    "gn:dem":9,
    "gn:feature_class":"P",
    "gn:feature_code":"PPL",
    "gn:name":"Yushiqiao",
    "gn:population":0,
    "gn:timezone":"Asia/Shanghai",
    "iso:country":"CN",
    "name:und_x_variant":[
        "\u9047\u4e16\u6865"
    ],
    "wof:name":"Yushiqiao",
    "wof:placetype":"locality"
},
  "geometry": {"coordinates":[120.84828,30.83137],"type":"Point"}
}