{
  "type": "Feature",
  "properties": {
    "gn:admin1_code":"13.0",
    "gn:asciiname":"Kaletie Shimazha",
    "gn:country_code":"CN",
    "gn:dem":1409,
    "gn:feature_class":"P",
    "gn:feature_code":"PPL",
    "gn:name":"Kaletie Shimazha",
    "gn:population":0,
    "gn:timezone":"Asia/Shanghai",
    "iso:country":"CN",
    "name:zho_x_preferred":[
        "\u5580\u52d2\u94c1\u4ec0\u9ebb\u624e"
    ],
    "wof:name":"Kaletie Shimazha",
    "wof:placetype":"locality"
},
  "geometry": {"coordinates":[81.08551,36.91165],"type":"Point"}
}