{
  "type": "Feature",
  "properties": {
    "gn:admin1_code":"30.0",
    "gn:asciiname":"Yangshuikeng",
    "gn:country_code":"CN",
    "gn:dem":487,
    "gn:feature_class":"P",
    "gn:feature_code":"PPL",
    "gn:name":"Yangshuikeng",
    "gn:population":0,
    "gn:timezone":"Asia/Shanghai",
    "iso:country":"CN",
    "name:zho_x_preferred":[
        "\u7f8a\u6c34\u5751"
    ],
    "wof:name":"Yangshuikeng",
    "wof:placetype":"locality"
},
  "geometry": {"coordinates":[112.42945,24.21722],"type":"Point"}
}