{
  "type": "Feature",
  "properties": {
    "gn:admin1_code":"16",
    "gn:asciiname":"Huapichong",
    "gn:country_code":"CN",
    "gn:dem":909,
    "gn:feature_class":"P",
    "gn:feature_code":"PPL",
    "gn:name":"Huapichong",
    "gn:population":0,
    "gn:timezone":"Asia/Shanghai",
    "iso:country":"CN",
    "name:zho_x_preferred":[
        "\u534e\u76ae\u51b2"
    ],
    "wof:name":"Huapichong",
    "wof:placetype":"locality"
},
  "geometry": {"coordinates":[110.71599999999999,26.0696],"type":"Point"}
}