{
  "type": "Feature",
  "properties": {
    "gn:admin1_code":"16.0",
    "gn:asciiname":"Yaopan",
    "gn:country_code":"CN",
    "gn:dem":441,
    "gn:feature_class":"P",
    "gn:feature_code":"PPL",
    "gn:name":"Yaopan",
    "gn:population":0,
    "gn:timezone":"Asia/Shanghai",
    "iso:country":"CN",
    "name:und_x_variant":[
        "Mepan",
        "Yaopan"
    ],
    "name:zho_x_preferred":[
        "\u4e48\u76d8"
    ],
    "wof:name":"Yaopan",
    "wof:placetype":"locality"
},
  "geometry": {"coordinates":[107.711,24.7786],"type":"Point"}
}