{
  "type": "Feature",
  "properties": {
    "gn:admin1_code":"9",
    "gn:asciiname":"Wangqiao",
    "gn:country_code":"CN",
    "gn:dem":66,
    "gn:feature_class":"P",
    "gn:feature_code":"PPL",
    "gn:name":"Wangqiao",
    "gn:population":0,
    "gn:timezone":"Asia/Shanghai",
    "iso:country":"CN",
    "name:und_x_variant":[
        "\u738b\u6865"
    ],
    "name:zho_x_preferred":[
        "\u738b\u6865"
    ],
    "wof:name":"Wangqiao",
    "wof:placetype":"locality"
},
  "geometry": {"coordinates":[113.78111,33.51361],"type":"Point"}
}