{
  "type": "Feature",
  "properties": {
    "gn:admin1_code":"29.0",
    "gn:asciiname":"Tuochecun",
    "gn:country_code":"CN",
    "gn:dem":1636,
    "gn:feature_class":"P",
    "gn:feature_code":"PPL",
    "gn:name":"Tuochecun",
    "gn:population":0,
    "gn:timezone":"Asia/Shanghai",
    "iso:country":"CN",
    "name:zho_x_preferred":[
        "\u62d6\u8f66\u6751"
    ],
    "wof:name":"Tuochecun",
    "wof:placetype":"locality"
},
  "geometry": {"coordinates":[103.197,27.2522],"type":"Point"}
}