{
  "type": "Feature",
  "properties": {
    "gn:admin1_code":"3.0",
    "gn:asciiname":"Beikeng",
    "gn:country_code":"CN",
    "gn:dem":415,
    "gn:feature_class":"P",
    "gn:feature_code":"PPL",
    "gn:name":"Beikeng",
    "gn:population":0,
    "gn:timezone":"Asia/Shanghai",
    "iso:country":"CN",
    "name:und_x_variant":[
        "\u5317\u5751"
    ],
    "wof:name":"Beikeng",
    "wof:placetype":"locality"
},
  "geometry": {"coordinates":[115.92497,25.56655],"type":"Point"}
}