{
  "type": "Feature",
  "properties": {
    "gn:admin1_code":"29.0",
    "gn:asciiname":"Danuobai",
    "gn:country_code":"CN",
    "gn:dem":1957,
    "gn:feature_class":"P",
    "gn:feature_code":"PPL",
    "gn:name":"Danuobai",
    "gn:population":0,
    "gn:timezone":"Asia/Shanghai",
    "iso:country":"CN",
    "name:zho_x_preferred":[
        "\u5927\u7cef\u767d"
    ],
    "wof:name":"Danuobai",
    "wof:placetype":"locality"
},
  "geometry": {"coordinates":[104.066,24.7215],"type":"Point"}
}