{
  "type": "Feature",
  "properties": {
    "gn:admin1_code":"14.0",
    "gn:asciiname":"Bangmozui",
    "gn:country_code":"CN",
    "gn:dem":3488,
    "gn:feature_class":"P",
    "gn:feature_code":"PPL",
    "gn:name":"Bangmozui",
    "gn:population":0,
    "gn:timezone":"Asia/Urumqi",
    "iso:country":"CN",
    "name:zho_x_preferred":[
        "\u90a6\u83ab\u5480"
    ],
    "wof:name":"Bangmozui",
    "wof:placetype":"locality"
},
  "geometry": {"coordinates":[93.75038000000001,28.92197],"type":"Point"}
}