{
  "type": "Feature",
  "properties": {
    "gn:admin1_code":"20.0",
    "gn:asciiname":"Wangwugou",
    "gn:country_code":"CN",
    "gn:dem":1334,
    "gn:feature_class":"P",
    "gn:feature_code":"PPL",
    "gn:name":"Wangwugou",
    "gn:population":0,
    "gn:timezone":"Asia/Shanghai",
    "iso:country":"CN",
    "name:und_x_variant":[
        "\u738b\u4e94\u6c9f"
    ],
    "wof:name":"Wangwugou",
    "wof:placetype":"locality"
},
  "geometry": {"coordinates":[109.96521,40.92989],"type":"Point"}
}