{
  "type": "Feature",
  "properties": {
    "gn:admin1_code":"30",
    "gn:asciiname":"Zhenziwei",
    "gn:country_code":"CN",
    "gn:dem":32,
    "gn:feature_class":"P",
    "gn:feature_code":"PPL",
    "gn:name":"Zhenziwei",
    "gn:population":0,
    "gn:timezone":"Asia/Shanghai",
    "iso:country":"CN",
    "name:zho_x_preferred":[
        "\u771f\u5b50\u56f4"
    ],
    "wof:name":"Zhenziwei",
    "wof:placetype":"locality"
},
  "geometry": {"coordinates":[116.05521,23.57557000000001],"type":"Point"}
}