{
  "type": "Feature",
  "properties": {
    "gn:admin1_code":"2.0",
    "gn:asciiname":"Jieba",
    "gn:country_code":"CN",
    "gn:dem":10,
    "gn:feature_class":"P",
    "gn:feature_code":"PPL",
    "gn:name":"Jieba",
    "gn:population":0,
    "gn:timezone":"Asia/Shanghai",
    "iso:country":"CN",
    "name:zho_x_preferred":[
        "\u89e3\u516b"
    ],
    "wof:name":"Jieba",
    "wof:placetype":"locality"
},
  "geometry": {"coordinates":[121.58907000000001,29.04337],"type":"Point"}
}