{
  "type": "Feature",
  "properties": {
    "gn:admin1_code":"5.0",
    "gn:asciiname":"Tangjia Weizi",
    "gn:country_code":"CN",
    "gn:dem":270,
    "gn:feature_class":"P",
    "gn:feature_code":"PPL",
    "gn:name":"Tangjia Weizi",
    "gn:population":0,
    "gn:timezone":"Asia/Shanghai",
    "iso:country":"CN",
    "name:zho_x_preferred":[
        "\u5510\u5bb6\u5d34\u5b50"
    ],
    "wof:name":"Tangjia Weizi",
    "wof:placetype":"locality"
},
  "geometry": {"coordinates":[126.78888000000001,43.73239],"type":"Point"}
}