{
  "type": "Feature",
  "properties": {
    "gn:admin1_code":"10.0",
    "gn:asciiname":"Shangmingyu",
    "gn:country_code":"CN",
    "gn:dem":684,
    "gn:feature_class":"P",
    "gn:feature_code":"PPL",
    "gn:name":"Shangmingyu",
    "gn:population":0,
    "gn:timezone":"Asia/Shanghai",
    "iso:country":"CN",
    "name:zho_x_preferred":[
        "\u4e0a\u660e\u5cea"
    ],
    "wof:name":"Shangmingyu",
    "wof:placetype":"locality"
},
  "geometry": {"coordinates":[115.19255,39.7168],"type":"Point"}
}