{
  "type": "Feature",
  "properties": {
    "gn:admin1_code":"12.0",
    "gn:asciiname":"Fujia Dayuan",
    "gn:country_code":"CN",
    "gn:dem":581,
    "gn:feature_class":"P",
    "gn:feature_code":"PPL",
    "gn:name":"Fujia Dayuan",
    "gn:population":0,
    "gn:timezone":"Asia/Shanghai",
    "iso:country":"CN",
    "name:zho_x_preferred":[
        "\u5085\u5bb6\u5927\u9662"
    ],
    "wof:name":"Fujia Dayuan",
    "wof:placetype":"locality"
},
  "geometry": {"coordinates":[110.3862,33.11448],"type":"Point"}
}