{
  "type": "Feature",
  "properties": {
    "gn:admin1_code":"03",
    "gn:asciiname":"Jinkouxiang",
    "gn:country_code":"CN",
    "gn:dem":100,
    "gn:feature_class":"P",
    "gn:feature_code":"PPL",
    "gn:name":"Jinkouxiang",
    "gn:population":0,
    "gn:timezone":"Asia/Shanghai",
    "iso:country":"CN",
    "name:und_x_variant":[
        "Ching-k\u2019ou",
        "Chin-k\u2019ou",
        "Jinkouxiang",
        "\u5dfe\u53e3\u4e61"
    ],
    "wof:name":"Jinkouxiang",
    "wof:placetype":"locality"
},
  "geometry": {"coordinates":[115.27751000000001,29.32321],"type":"Point"}
}