{
  "type": "Feature",
  "properties": {
    "gn:admin1_code":"32.0",
    "gn:asciiname":"Shuiyachi",
    "gn:country_code":"CN",
    "gn:dem":414,
    "gn:feature_class":"P",
    "gn:feature_code":"PPL",
    "gn:name":"Shuiyachi",
    "gn:population":0,
    "gn:timezone":"Asia/Shanghai",
    "iso:country":"CN",
    "name:zho_x_preferred":[
        "\u6c34\u9e2d\u6c60"
    ],
    "wof:name":"Shuiyachi",
    "wof:placetype":"locality"
},
  "geometry": {"coordinates":[104.53803000000001,28.47244],"type":"Point"}
}