{
  "type": "Feature",
  "properties": {
    "gn:admin1_code":"30.0",
    "gn:asciiname":"Jinggang",
    "gn:country_code":"CN",
    "gn:dem":16,
    "gn:feature_class":"P",
    "gn:feature_code":"PPL",
    "gn:name":"Jinggang",
    "gn:population":0,
    "gn:timezone":"Asia/Shanghai",
    "iso:country":"CN",
    "name:zho_x_preferred":[
        "\u4e95\u5d17"
    ],
    "wof:name":"Jinggang",
    "wof:placetype":"locality"
},
  "geometry": {"coordinates":[112.83437000000001,22.33432],"type":"Point"}
}