{
  "type": "Feature",
  "properties": {
    "gn:admin1_code":"30.0",
    "gn:asciiname":"Jinglian",
    "gn:country_code":"CN",
    "gn:dem":603,
    "gn:feature_class":"P",
    "gn:feature_code":"PPL",
    "gn:name":"Jinglian",
    "gn:population":0,
    "gn:timezone":"Asia/Shanghai",
    "iso:country":"CN",
    "name:zho_x_preferred":[
        "Jinglian"
    ],
    "name:zho_x_variant":[
        "\u656c\u8054"
    ],
    "wof:name":"Jinglian",
    "wof:placetype":"locality"
},
  "geometry": {"coordinates":[112.53417,25.12417],"type":"Point"}
}