{
  "type": "Feature",
  "properties": {
    "gn:admin1_code":"7.0",
    "gn:asciiname":"Lianfeng",
    "gn:country_code":"CN",
    "gn:dem":19,
    "gn:feature_class":"P",
    "gn:feature_code":"PPL",
    "gn:name":"Lianfeng",
    "gn:population":0,
    "gn:timezone":"Asia/Shanghai",
    "iso:country":"CN",
    "name:zho_x_preferred":[
        "\u83b2\u5cf0"
    ],
    "wof:name":"Lianfeng",
    "wof:placetype":"locality"
},
  "geometry": {"coordinates":[118.95434,24.96965],"type":"Point"}
}