{
  "type": "Feature",
  "properties": {
    "gn:admin1_code":"7.0",
    "gn:asciiname":"Yucuodun",
    "gn:country_code":"CN",
    "gn:dem":256,
    "gn:feature_class":"P",
    "gn:feature_code":"PPL",
    "gn:name":"Yucuodun",
    "gn:population":0,
    "gn:timezone":"Asia/Shanghai",
    "iso:country":"CN",
    "name:zho_x_preferred":[
        "\u4fde\u539d\u58a9"
    ],
    "wof:name":"Yucuodun",
    "wof:placetype":"locality"
},
  "geometry": {"coordinates":[117.57293,27.07916],"type":"Point"}
}