{
  "type": "Feature",
  "properties": {
    "gn:admin1_code":"6.0",
    "gn:asciiname":"Shali Kete",
    "gn:country_code":"CN",
    "gn:dem":3172,
    "gn:feature_class":"P",
    "gn:feature_code":"PPL",
    "gn:name":"Shali Kete",
    "gn:population":0,
    "gn:timezone":"Asia/Urumqi",
    "iso:country":"CN",
    "name:zho_x_preferred":[
        "\u6c99\u7acb\u514b\u7279"
    ],
    "wof:name":"Shali Kete",
    "wof:placetype":"locality"
},
  "geometry": {"coordinates":[97.95578999999999,35.92463],"type":"Point"}
}