{
  "type": "Feature",
  "properties": {
    "gn:admin1_code":"11.0",
    "gn:asciiname":"Lijiawu",
    "gn:country_code":"CN",
    "gn:dem":81,
    "gn:feature_class":"P",
    "gn:feature_code":"PPL",
    "gn:name":"Lijiawu",
    "gn:population":0,
    "gn:timezone":"Asia/Shanghai",
    "iso:country":"CN",
    "name:zho_x_preferred":[
        "\u674e\u5bb6\u5c4b"
    ],
    "wof:name":"Lijiawu",
    "wof:placetype":"locality"
},
  "geometry": {"coordinates":[113.10617999999999,28.9188],"type":"Point"}
}