{
  "type": "Feature",
  "properties": {
    "gn:admin1_code":"14.0",
    "gn:asciiname":"Wolongnong",
    "gn:country_code":"CN",
    "gn:dem":3667,
    "gn:feature_class":"P",
    "gn:feature_code":"PPL",
    "gn:name":"Wolongnong",
    "gn:population":0,
    "gn:timezone":"Asia/Urumqi",
    "iso:country":"CN",
    "name:zho_x_preferred":[
        "\u7a9d\u9f99\u519c"
    ],
    "wof:name":"Wolongnong",
    "wof:placetype":"locality"
},
  "geometry": {"coordinates":[98.73067,29.93104000000001],"type":"Point"}
}