{
  "type": "Feature",
  "properties": {
    "gn:admin1_code":"11",
    "gn:asciiname":"Beishibian",
    "gn:country_code":"CN",
    "gn:dem":151,
    "gn:feature_class":"P",
    "gn:feature_code":"PPL",
    "gn:name":"Beishibian",
    "gn:population":0,
    "gn:timezone":"Asia/Shanghai",
    "iso:country":"CN",
    "name:zho_x_preferred":[
        "\u7891\u77f3\u8fb9"
    ],
    "wof:name":"Beishibian",
    "wof:placetype":"locality"
},
  "geometry": {"coordinates":[112.49618999999998,26.7444],"type":"Point"}
}