{
  "type": "Feature",
  "properties": {
    "gn:admin1_code":"33.0",
    "gn:asciiname":"Longbaotang",
    "gn:country_code":"CN",
    "gn:dem":1259,
    "gn:feature_class":"P",
    "gn:feature_code":"PPL",
    "gn:name":"Longbaotang",
    "gn:population":0,
    "gn:timezone":"Asia/Shanghai",
    "iso:country":"CN",
    "name:zho_x_preferred":[
        "\u9f99\u5b9d\u5858"
    ],
    "wof:name":"Longbaotang",
    "wof:placetype":"locality"
},
  "geometry": {"coordinates":[107.76035,29.44895],"type":"Point"}
}