{
  "type": "Feature",
  "properties": {
    "gn:admin1_code":"11",
    "gn:asciiname":"Dabatou",
    "gn:country_code":"CN",
    "gn:dem":610,
    "gn:feature_class":"P",
    "gn:feature_code":"PPL",
    "gn:name":"Dabatou",
    "gn:population":0,
    "gn:timezone":"Asia/Shanghai",
    "iso:country":"CN",
    "name:zho_x_preferred":[
        "\u5927\u575d\u5934"
    ],
    "wof:name":"Dabatou",
    "wof:placetype":"locality"
},
  "geometry": {"coordinates":[112.01622,26.14651],"type":"Point"}
}