{
  "type": "Feature",
  "properties": {
    "gn:admin1_code":"30.0",
    "gn:asciiname":"Yangqikeng",
    "gn:country_code":"CN",
    "gn:dem":270,
    "gn:feature_class":"P",
    "gn:feature_code":"PPL",
    "gn:name":"Yangqikeng",
    "gn:population":0,
    "gn:timezone":"Asia/Shanghai",
    "iso:country":"CN",
    "name:zho_x_preferred":[
        "\u6768\u6816\u5751"
    ],
    "wof:name":"Yangqikeng",
    "wof:placetype":"locality"
},
  "geometry": {"coordinates":[115.51843,23.46239],"type":"Point"}
}