{
  "type": "Feature",
  "properties": {
    "gn:admin1_code":"5.0",
    "gn:asciiname":"Xinsheng Gongqu",
    "gn:country_code":"CN",
    "gn:dem":921,
    "gn:feature_class":"P",
    "gn:feature_code":"PPLF",
    "gn:name":"Xinsheng Gongqu",
    "gn:population":0,
    "gn:timezone":"Asia/Shanghai",
    "iso:country":"CN",
    "name:und_x_variant":[
        "\u65b0\u80dc\u5de5\u533a"
    ],
    "wof:name":"Xinsheng Gongqu",
    "wof:placetype":"locality"
},
  "geometry": {"coordinates":[127.35012999999999,41.93935],"type":"Point"}
}