{
  "type": "Feature",
  "properties": {
    "gn:admin1_code":"8.0",
    "gn:asciiname":"Wangchunyang",
    "gn:country_code":"CN",
    "gn:dem":236,
    "gn:feature_class":"P",
    "gn:feature_code":"PPL",
    "gn:name":"Wangchunyang",
    "gn:population":0,
    "gn:timezone":"Asia/Shanghai",
    "iso:country":"CN",
    "name:zho_x_preferred":[
        "\u738b\u6625\u9633"
    ],
    "wof:name":"Wangchunyang",
    "wof:placetype":"locality"
},
  "geometry": {"coordinates":[125.82483999999999,47.75982],"type":"Point"}
}