{
  "type": "Feature",
  "properties": {
    "gn:admin1_code":"18",
    "gn:asciiname":"Dahuoshan",
    "gn:country_code":"CN",
    "gn:dem":853,
    "gn:feature_class":"P",
    "gn:feature_code":"PPL",
    "gn:name":"Dahuoshan",
    "gn:population":0,
    "gn:timezone":"Asia/Shanghai",
    "iso:country":"CN",
    "name:zho_x_preferred":[
        "\u5927\u706b\u5c71"
    ],
    "wof:name":"Dahuoshan",
    "wof:placetype":"locality"
},
  "geometry": {"coordinates":[107.732,27.1477],"type":"Point"}
}