{
  "type": "Feature",
  "properties": {
    "gn:admin1_code":"29.0",
    "gn:asciiname":"Damadi",
    "gn:country_code":"CN",
    "gn:dem":1895,
    "gn:feature_class":"P",
    "gn:feature_code":"PPL",
    "gn:name":"Damadi",
    "gn:population":0,
    "gn:timezone":"Asia/Shanghai",
    "iso:country":"CN",
    "name:zho_x_preferred":[
        "\u5927\u9ebb\u5730"
    ],
    "wof:name":"Damadi",
    "wof:placetype":"locality"
},
  "geometry": {"coordinates":[104.03700000000001,23.2311],"type":"Point"}
}