{
  "type": "Feature",
  "properties": {
    "gn:admin1_code":"14.0",
    "gn:asciiname":"Zonggo",
    "gn:country_code":"CN",
    "gn:dem":2112,
    "gn:feature_class":"P",
    "gn:feature_code":"PPL",
    "gn:name":"Zonggo",
    "gn:population":0,
    "gn:timezone":"Asia/Urumqi",
    "iso:country":"CN",
    "name:bod_x_preferred":[
        "Zonggo"
    ],
    "name:zho_x_preferred":[
        "Zonggu"
    ],
    "name:zho_x_variant":[
        "\u5b97\u53e4"
    ],
    "wof:name":"Zonggo",
    "wof:placetype":"locality"
},
  "geometry": {"coordinates":[97.08136,28.40403],"type":"Point"}
}