{
  "type": "Feature",
  "properties": {
    "gn:admin1_code":"26",
    "gn:asciiname":"Dongwang",
    "gn:cc2":"CN",
    "gn:country_code":"CN",
    "gn:dem":397,
    "gn:feature_class":"P",
    "gn:feature_code":"PPL",
    "gn:name":"Dongwang",
    "gn:population":0,
    "gn:timezone":"Asia/Shanghai",
    "iso:country":"CN",
    "name:und_x_variant":[
        "Tung-wang",
        "Dongwang"
    ],
    "wof:name":"Dongwang",
    "wof:placetype":"locality"
},
  "geometry": {"coordinates":[110.32444,35.17333],"type":"Point"}
}