{
  "type": "Feature",
  "properties": {
    "gn:admin1_code":"5.0",
    "gn:asciiname":"Chuangyecun",
    "gn:country_code":"CN",
    "gn:dem":150,
    "gn:feature_class":"P",
    "gn:feature_code":"PPL",
    "gn:name":"Chuangyecun",
    "gn:population":0,
    "gn:timezone":"Asia/Shanghai",
    "iso:country":"CN",
    "name:zho_x_preferred":[
        "\u521b\u4e1a\u6751"
    ],
    "wof:name":"Chuangyecun",
    "wof:placetype":"locality"
},
  "geometry": {"coordinates":[125.11848000000001,45.23082],"type":"Point"}
}