{
  "type": "Feature",
  "properties": {
    "gn:admin1_code":"2.0",
    "gn:asciiname":"Houchuwu",
    "gn:country_code":"CN",
    "gn:dem":166,
    "gn:feature_class":"P",
    "gn:feature_code":"PPL",
    "gn:name":"Houchuwu",
    "gn:population":0,
    "gn:timezone":"Asia/Shanghai",
    "iso:country":"CN",
    "name:und_x_variant":[
        "\u540e\u521d\u575e"
    ],
    "wof:name":"Houchuwu",
    "wof:placetype":"locality"
},
  "geometry": {"coordinates":[119.40039,29.9296],"type":"Point"}
}