{
  "type": "Feature",
  "properties": {
    "gn:admin1_code":"16.0",
    "gn:asciiname":"Liuyishan",
    "gn:country_code":"CN",
    "gn:dem":175,
    "gn:feature_class":"P",
    "gn:feature_code":"PPL",
    "gn:name":"Liuyishan",
    "gn:population":0,
    "gn:timezone":"Asia/Shanghai",
    "iso:country":"CN",
    "name:zho_x_preferred":[
        "\u516d\u5b9c\u5c71"
    ],
    "wof:name":"Liuyishan",
    "wof:placetype":"locality"
},
  "geometry": {"coordinates":[110.255,23.6793],"type":"Point"}
}