{
  "type": "Feature",
  "properties": {
    "gn:admin1_code":"25",
    "gn:asciiname":"Bocun",
    "gn:country_code":"CN",
    "gn:dem":11,
    "gn:feature_class":"P",
    "gn:feature_code":"PPL",
    "gn:name":"Bocun",
    "gn:population":0,
    "gn:timezone":"Asia/Shanghai",
    "iso:country":"CN",
    "name:zho_x_preferred":[
        "\u8584\u6751"
    ],
    "wof:name":"Bocun",
    "wof:placetype":"locality"
},
  "geometry": {"coordinates":[118.37384,37.66632],"type":"Point"}
}