{
  "type": "Feature",
  "properties": {
    "gn:admin1_code":"24.0",
    "gn:asciiname":"Yanfengying",
    "gn:country_code":"CN",
    "gn:dem":1058,
    "gn:feature_class":"P",
    "gn:feature_code":"PPL",
    "gn:name":"Yanfengying",
    "gn:population":0,
    "gn:timezone":"Asia/Shanghai",
    "iso:country":"CN",
    "name:und_x_variant":[
        "\u76d0\u4e30\u8425"
    ],
    "name:zho_x_preferred":[
        "\u76d0\u4e30\u8425"
    ],
    "wof:name":"Yanfengying",
    "wof:placetype":"locality"
},
  "geometry": {"coordinates":[112.88375000000001,39.66089],"type":"Point"}
}