{
  "type": "Feature",
  "properties": {
    "gn:admin1_code":"1.0",
    "gn:asciiname":"Hwang Yuen Chin (historical)",
    "gn:country_code":"CN",
    "gn:dem":18,
    "gn:feature_class":"P",
    "gn:feature_code":"PPL",
    "gn:name":"Hwang Yuen Chin (historical)",
    "gn:population":0,
    "gn:timezone":"Asia/Shanghai",
    "iso:country":"CN",
    "wof:name":"Hwang Yuen Chin (historical)",
    "wof:placetype":"locality"
},
  "geometry": {"coordinates":[116.75617,30.09138],"type":"Point"}
}