{
  "type": "Feature",
  "properties": {
    "gn:admin1_code":"4.0",
    "gn:asciiname":"Fengjia Xiaoqiao",
    "gn:country_code":"CN",
    "gn:dem":6,
    "gn:feature_class":"P",
    "gn:feature_code":"PPL",
    "gn:name":"Fengjia Xiaoqiao",
    "gn:population":0,
    "gn:timezone":"Asia/Shanghai",
    "iso:country":"CN",
    "name:zho_x_preferred":[
        "\u51af\u5bb6\u5c0f\u6865"
    ],
    "wof:name":"Fengjia Xiaoqiao",
    "wof:placetype":"locality"
},
  "geometry": {"coordinates":[120.8578,32.09726],"type":"Point"}
}