{
  "type": "Feature",
  "properties": {
    "gn:admin1_code":"10",
    "gn:asciiname":"Qixinzhai",
    "gn:country_code":"CN",
    "gn:dem":48,
    "gn:feature_class":"P",
    "gn:feature_code":"PPL",
    "gn:name":"Qixinzhai",
    "gn:population":0,
    "gn:timezone":"Asia/Shanghai",
    "iso:country":"CN",
    "name:zho_x_preferred":[
        "\u5c90\u8f9b\u5be8"
    ],
    "wof:name":"Qixinzhai",
    "wof:placetype":"locality"
},
  "geometry": {"coordinates":[114.697,36.858],"type":"Point"}
}