{
  "type": "Feature",
  "properties": {
    "gn:admin1_code":"9.0",
    "gn:asciiname":"Linghe",
    "gn:country_code":"CN",
    "gn:dem":71,
    "gn:feature_class":"P",
    "gn:feature_code":"PPL",
    "gn:name":"Linghe",
    "gn:population":0,
    "gn:timezone":"Asia/Shanghai",
    "iso:country":"CN",
    "name:zho_x_preferred":[
        "\u96f6\u6cb3"
    ],
    "wof:name":"Linghe",
    "wof:placetype":"locality"
},
  "geometry": {"coordinates":[114.45423999999998,35.40613],"type":"Point"}
}