{
  "type": "Feature",
  "properties": {
    "gn:admin1_code":"32.0",
    "gn:asciiname":"Zhoushigou",
    "gn:country_code":"CN",
    "gn:dem":409,
    "gn:feature_class":"P",
    "gn:feature_code":"PPL",
    "gn:name":"Zhoushigou",
    "gn:population":0,
    "gn:timezone":"Asia/Shanghai",
    "iso:country":"CN",
    "name:zho_x_preferred":[
        "\u5468\u72ee\u6c9f"
    ],
    "wof:name":"Zhoushigou",
    "wof:placetype":"locality"
},
  "geometry": {"coordinates":[104.17189999999999,29.67462],"type":"Point"}
}