{
  "type": "Feature",
  "properties": {
    "gn:admin1_code":"26.0",
    "gn:asciiname":"Gongliucun",
    "gn:country_code":"CN",
    "gn:dem":503,
    "gn:feature_class":"P",
    "gn:feature_code":"PPL",
    "gn:name":"Gongliucun",
    "gn:population":0,
    "gn:timezone":"Asia/Shanghai",
    "iso:country":"CN",
    "name:zho_x_preferred":[
        "\u9f9a\u5218\u6751"
    ],
    "wof:name":"Gongliucun",
    "wof:placetype":"locality"
},
  "geometry": {"coordinates":[107.6661,34.31699],"type":"Point"}
}