{
  "type": "Feature",
  "properties": {
    "gn:admin1_code":"31",
    "gn:asciiname":"Xianggen Yidui",
    "gn:country_code":"CN",
    "gn:dem":125,
    "gn:feature_class":"P",
    "gn:feature_code":"PPLF",
    "gn:name":"Xianggen Yidui",
    "gn:population":0,
    "gn:timezone":"Asia/Shanghai",
    "iso:country":"CN",
    "name:und_x_variant":[
        "\u9999\u6839\u4e00\u961f"
    ],
    "wof:name":"Xianggen Yidui",
    "wof:placetype":"locality"
},
  "geometry": {"coordinates":[110.1985,18.97571],"type":"Point"}
}