{
  "type": "Feature",
  "properties": {
    "gn:admin1_code":"10",
    "gn:asciiname":"Zhongjing",
    "gn:country_code":"CN",
    "gn:dem":24,
    "gn:feature_class":"P",
    "gn:feature_code":"PPL",
    "gn:name":"Zhongjing",
    "gn:population":0,
    "gn:timezone":"Asia/Shanghai",
    "iso:country":"CN",
    "name:zho_x_preferred":[
        "\u4ef2\u666f"
    ],
    "wof:name":"Zhongjing",
    "wof:placetype":"locality"
},
  "geometry": {"coordinates":[115.693,37.6113],"type":"Point"}
}