{
  "type": "Feature",
  "properties": {
    "gn:admin1_code":"11",
    "gn:asciiname":"Shengqiao",
    "gn:cc2":"CN",
    "gn:country_code":"CN",
    "gn:dem":93,
    "gn:feature_class":"P",
    "gn:feature_code":"PPL",
    "gn:name":"Shengqiao",
    "gn:population":0,
    "gn:timezone":"Asia/Shanghai",
    "iso:country":"CN",
    "name:und_x_variant":[
        "Dashengjiang",
        "Shengqiao"
    ],
    "wof:name":"Shengqiao",
    "wof:placetype":"locality"
},
  "geometry": {"coordinates":[112.32472,26.30167],"type":"Point"}
}