{
  "type": "Feature",
  "properties": {
    "gn:admin1_code":"11.0",
    "gn:asciiname":"Qingmingdong",
    "gn:country_code":"CN",
    "gn:dem":284,
    "gn:feature_class":"P",
    "gn:feature_code":"PPL",
    "gn:name":"Qingmingdong",
    "gn:population":0,
    "gn:timezone":"Asia/Shanghai",
    "iso:country":"CN",
    "name:zho_x_preferred":[
        "\u6e05\u660e\u6d1e"
    ],
    "wof:name":"Qingmingdong",
    "wof:placetype":"locality"
},
  "geometry": {"coordinates":[109.69127,27.68544],"type":"Point"}
}