{
  "type": "Feature",
  "properties": {
    "gn:admin1_code":"22.0",
    "gn:asciiname":"Xibailianyucun",
    "gn:country_code":"CN",
    "gn:dem":299,
    "gn:feature_class":"P",
    "gn:feature_code":"PPL",
    "gn:name":"Xibailianyucun",
    "gn:population":0,
    "gn:timezone":"Asia/Shanghai",
    "iso:country":"CN",
    "name:zho_x_preferred":[
        "\u897f\u767d\u83b2\u5cea\u6751"
    ],
    "wof:name":"Xibailianyucun",
    "wof:placetype":"locality"
},
  "geometry": {"coordinates":[116.88191,40.65367],"type":"Point"}
}