{
  "type": "Feature",
  "properties": {
    "gn:admin1_code":"06",
    "gn:asciiname":"Daxia",
    "gn:cc2":"CN",
    "gn:country_code":"CN",
    "gn:dem":2082,
    "gn:feature_class":"P",
    "gn:feature_code":"PPL",
    "gn:name":"Daxia",
    "gn:population":0,
    "gn:timezone":"Asia/Shanghai",
    "iso:country":"CN",
    "name:fra_x_preferred":[
        "Daxia"
    ],
    "name:ind_x_preferred":[
        "Daxia"
    ],
    "name:ita_x_preferred":[
        "Da Xia"
    ],
    "name:kor_x_preferred":[
        "\ub300\ud558"
    ],
    "name:und_x_variant":[
        "Ta-hsia",
        "Dasya"
    ],
    "name:zho_x_preferred":[
        "\u5927\u590f"
    ],
    "wof:name":"Daxia",
    "wof:placetype":"locality"
},
  "geometry": {"coordinates":[102.19917,36.48],"type":"Point"}
}