{
  "type": "Feature",
  "properties": {
    "gn:admin1_code":"16.0",
    "gn:asciiname":"Paiban",
    "gn:country_code":"CN",
    "gn:dem":137,
    "gn:feature_class":"P",
    "gn:feature_code":"PPL",
    "gn:name":"Paiban",
    "gn:population":0,
    "gn:timezone":"Asia/Shanghai",
    "iso:country":"CN",
    "name:zho_x_preferred":[
        "\u6d3e\u73ed"
    ],
    "wof:name":"Paiban",
    "wof:placetype":"locality"
},
  "geometry": {"coordinates":[107.357,23.4241],"type":"Point"}
}