{
  "type": "Feature",
  "properties": {
    "gn:admin1_code":"1.0",
    "gn:asciiname":"Waitakeng",
    "gn:country_code":"CN",
    "gn:dem":282,
    "gn:feature_class":"P",
    "gn:feature_code":"PPL",
    "gn:name":"Waitakeng",
    "gn:population":0,
    "gn:timezone":"Asia/Shanghai",
    "iso:country":"CN",
    "name:zho_x_preferred":[
        "\u5916\u5854\u5751"
    ],
    "wof:name":"Waitakeng",
    "wof:placetype":"locality"
},
  "geometry": {"coordinates":[118.14388,29.48335],"type":"Point"}
}