{
  "type": "Feature",
  "properties": {
    "gn:admin1_code":"16",
    "gn:asciiname":"Gao'an",
    "gn:country_code":"CN",
    "gn:dem":246,
    "gn:feature_class":"P",
    "gn:feature_code":"PPL",
    "gn:name":"Gao\u2019an",
    "gn:population":0,
    "gn:timezone":"Asia/Shanghai",
    "iso:country":"CN",
    "name:ces_x_preferred":[
        "Kao-an"
    ],
    "name:cym_x_preferred":[
        "Gao'an"
    ],
    "name:deu_x_preferred":[
        "Gao\u2019an"
    ],
    "name:fra_x_preferred":[
        "Gao'an"
    ],
    "name:ita_x_preferred":[
        "Gao'an"
    ],
    "name:jpn_x_preferred":[
        "\u9ad8\u5b89\u5e02"
    ],
    "name:kik_x_preferred":[
        "Gao'an"
    ],
    "name:kor_x_preferred":[
        "\uac00\uc624\uc548\uc2dc"
    ],
    "name:mlg_x_preferred":[
        "Gao'an"
    ],
    "name:nld_x_preferred":[
        "Gao'an"
    ],
    "name:nor_x_preferred":[
        "Gao'an"
    ],
    "name:swe_x_preferred":[
        "Gao'an"
    ],
    "name:vie_x_preferred":[
        "Cao An"
    ],
    "name:zho_x_preferred":[
        "\u9ad8\u5cb8"
    ],
    "name:zho_x_variant":[
        "\u9ad8\u5b89\u5e02"
    ],
    "wof:name":"Gao'an",
    "wof:placetype":"locality"
},
  "geometry": {"coordinates":[110.28100000000001,24.5777],"type":"Point"}
}