{
  "type": "Feature",
  "properties": {
    "gn:admin1_code":"3.0",
    "gn:asciiname":"Heshuxia",
    "gn:country_code":"CN",
    "gn:dem":252,
    "gn:feature_class":"P",
    "gn:feature_code":"PPL",
    "gn:name":"Heshuxia",
    "gn:population":0,
    "gn:timezone":"Asia/Shanghai",
    "iso:country":"CN",
    "name:und_x_variant":[
        "\u8377\u6811\u4e0b"
    ],
    "wof:name":"Heshuxia",
    "wof:placetype":"locality"
},
  "geometry": {"coordinates":[115.59992,24.7937],"type":"Point"}
}