{
  "type": "Feature",
  "properties": {
    "gn:admin1_code":"9.0",
    "gn:asciiname":"Runancun",
    "gn:country_code":"CN",
    "gn:dem":332,
    "gn:feature_class":"P",
    "gn:feature_code":"PPL",
    "gn:name":"Runancun",
    "gn:population":0,
    "gn:timezone":"Asia/Shanghai",
    "iso:country":"CN",
    "name:zho_x_preferred":[
        "\u6c5d\u5357\u6751"
    ],
    "wof:name":"Runancun",
    "wof:placetype":"locality"
},
  "geometry": {"coordinates":[112.43098000000001,34.12674000000001],"type":"Point"}
}