{
  "type": "Feature",
  "properties": {
    "gn:admin1_code":"2.0",
    "gn:asciiname":"Xiba",
    "gn:country_code":"CN",
    "gn:dem":5,
    "gn:feature_class":"P",
    "gn:feature_code":"PPL",
    "gn:name":"Xiba",
    "gn:population":0,
    "gn:timezone":"Asia/Shanghai",
    "iso:country":"CN",
    "name:und_x_variant":[
        "\u897f\u575d"
    ],
    "wof:name":"Xiba",
    "wof:placetype":"locality"
},
  "geometry": {"coordinates":[119.97517999999999,30.97659],"type":"Point"}
}