{
  "type": "Feature",
  "properties": {
    "gn:admin1_code":"18",
    "gn:asciiname":"Machishui",
    "gn:country_code":"CN",
    "gn:dem":1535,
    "gn:feature_class":"P",
    "gn:feature_code":"PPL",
    "gn:name":"Machishui",
    "gn:population":0,
    "gn:timezone":"Asia/Shanghai",
    "iso:country":"CN",
    "name:zho_x_preferred":[
        "\u9a6c\u5403\u6c34"
    ],
    "wof:name":"Machishui",
    "wof:placetype":"locality"
},
  "geometry": {"coordinates":[105.914,27.1299],"type":"Point"}
}