{
  "type": "Feature",
  "properties": {
    "gn:admin1_code":"12.0",
    "gn:asciiname":"Chenke",
    "gn:country_code":"CN",
    "gn:dem":29,
    "gn:feature_class":"P",
    "gn:feature_code":"PPL",
    "gn:name":"Chenke",
    "gn:population":0,
    "gn:timezone":"Asia/Shanghai",
    "iso:country":"CN",
    "name:und_x_variant":[
        "\u9648\u53ef"
    ],
    "wof:name":"Chenke",
    "wof:placetype":"locality"
},
  "geometry": {"coordinates":[114.35525,30.13694000000001],"type":"Point"}
}