{
  "type": "Feature",
  "properties": {
    "gn:admin1_code":"12.0",
    "gn:asciiname":"Xiangtan",
    "gn:country_code":"CN",
    "gn:dem":1159,
    "gn:feature_class":"P",
    "gn:feature_code":"PPL",
    "gn:name":"Xiangtan",
    "gn:population":0,
    "gn:timezone":"Asia/Shanghai",
    "iso:country":"CN",
    "name:zho_x_preferred":[
        "\u54cd\u6ee9"
    ],
    "wof:name":"Xiangtan",
    "wof:placetype":"locality"
},
  "geometry": {"coordinates":[108.85075000000001,30.46817],"type":"Point"}
}