{
  "type": "Feature",
  "properties": {
    "gn:admin1_code":"2.0",
    "gn:asciiname":"Zhuhong",
    "gn:country_code":"CN",
    "gn:dem":362,
    "gn:feature_class":"P",
    "gn:feature_code":"PPL",
    "gn:name":"Zhuhong",
    "gn:population":0,
    "gn:timezone":"Asia/Shanghai",
    "iso:country":"CN",
    "name:zho_x_preferred":[
        "\u795d\u6d2a"
    ],
    "wof:name":"Zhuhong",
    "wof:placetype":"locality"
},
  "geometry": {"coordinates":[119.62425,28.78175],"type":"Point"}
}