{
  "type": "Feature",
  "properties": {
    "gn:admin1_code":"19.0",
    "gn:asciiname":"Lindayuan",
    "gn:country_code":"CN",
    "gn:dem":127,
    "gn:feature_class":"P",
    "gn:feature_code":"PPL",
    "gn:name":"Lindayuan",
    "gn:population":0,
    "gn:timezone":"Asia/Shanghai",
    "iso:country":"CN",
    "name:und_x_variant":[
        "\u6797\u5927\u9662"
    ],
    "wof:name":"Lindayuan",
    "wof:placetype":"locality"
},
  "geometry": {"coordinates":[123.43116000000001,40.07424],"type":"Point"}
}