{
  "type": "Feature",
  "properties": {
    "gn:admin1_code":"24",
    "gn:asciiname":"Qinquan",
    "gn:cc2":"CN",
    "gn:country_code":"CN",
    "gn:dem":900,
    "gn:feature_class":"P",
    "gn:feature_code":"PPL",
    "gn:name":"Qinquan",
    "gn:population":0,
    "gn:timezone":"Asia/Shanghai",
    "iso:country":"CN",
    "name:und_x_variant":[
        "Ch\u2019in-ch\u2019\u00fcan",
        "Ch\u2019in-ch\u2019\u00fcan-chen",
        "Qinquan"
    ],
    "wof:name":"Qinquan",
    "wof:placetype":"locality"
},
  "geometry": {"coordinates":[113.60389000000001,36.97861],"type":"Point"}
}