{
  "type": "Feature",
  "properties": {
    "gn:admin1_code":"12.0",
    "gn:asciiname":"Guizhou",
    "gn:country_code":"CN",
    "gn:dem":99,
    "gn:feature_class":"P",
    "gn:feature_code":"PPLA4",
    "gn:name":"Guizhou",
    "gn:population":0,
    "gn:timezone":"Asia/Shanghai",
    "iso:country":"CN",
    "name:und_x_variant":[
        "Guizhou Zhen"
    ],
    "name:zho_x_preferred":[
        "\u5f52\u5dde"
    ],
    "name:zho_x_variant":[
        "\u5f52\u5dde\u9547"
    ],
    "wof:name":"Guizhou",
    "wof:placetype":"locality"
},
  "geometry": {"coordinates":[110.68975,30.99695],"type":"Point"}
}