{
  "type": "Feature",
  "properties": {
    "gn:admin1_code":"32.0",
    "gn:asciiname":"Chadianzi",
    "gn:country_code":"CN",
    "gn:dem":960,
    "gn:feature_class":"P",
    "gn:feature_code":"PPL",
    "gn:name":"Chadianzi",
    "gn:population":0,
    "gn:timezone":"Asia/Shanghai",
    "iso:country":"CN",
    "name:zho_x_preferred":[
        "\u8336\u5e97\u5b50"
    ],
    "wof:name":"Chadianzi",
    "wof:placetype":"locality"
},
  "geometry": {"coordinates":[103.54582000000001,29.19061],"type":"Point"}
}