{
  "type": "Feature",
  "properties": {
    "gn:admin1_code":"32.0",
    "gn:asciiname":"Duori'a",
    "gn:country_code":"CN",
    "gn:dem":4013,
    "gn:feature_class":"P",
    "gn:feature_code":"PPL",
    "gn:name":"Duori\u2019a",
    "gn:population":0,
    "gn:timezone":"Asia/Shanghai",
    "iso:country":"CN",
    "name:und_x_variant":[
        "Duori\u2019a"
    ],
    "name:zho_x_preferred":[
        "\u591a\u65e5\u963f"
    ],
    "wof:name":"Duori'a",
    "wof:placetype":"locality"
},
  "geometry": {"coordinates":[98.3579,33.0109],"type":"Point"}
}