{
  "type": "Feature",
  "properties": {
    "gn:admin1_code":"29",
    "gn:asciiname":"Dawazi",
    "gn:country_code":"CN",
    "gn:dem":1762,
    "gn:feature_class":"P",
    "gn:feature_code":"PPL",
    "gn:name":"Dawazi",
    "gn:population":0,
    "gn:timezone":"Asia/Shanghai",
    "iso:country":"CN",
    "name:zho_x_preferred":[
        "\u5927\u6d3c\u5b50"
    ],
    "wof:name":"Dawazi",
    "wof:placetype":"locality"
},
  "geometry": {"coordinates":[104.81999999999999,23.8329],"type":"Point"}
}