{
  "type": "Feature",
  "properties": {
    "gn:admin1_code":"13.0",
    "gn:asciiname":"Dahe",
    "gn:country_code":"CN",
    "gn:dem":1633,
    "gn:feature_class":"P",
    "gn:feature_code":"PPL",
    "gn:name":"Dahe",
    "gn:population":0,
    "gn:timezone":"Asia/Urumqi",
    "iso:country":"CN",
    "name:ceb_x_preferred":[
        "Dahe"
    ],
    "name:deu_x_preferred":[
        "Dahe"
    ],
    "name:kaz_x_preferred":[
        "\u062f\u0627\u062d\u0649 \u0642\u0627\u0644\u0627\u0634\u0649\u0639\u0649"
    ],
    "name:swe_x_preferred":[
        "Dahe"
    ],
    "name:uig_x_preferred":[
        "\u062f\u0627\u062e\u06d0 \u0628\u0627\u0632\u0649\u0631\u0649"
    ],
    "name:und_x_variant":[
        "Dahe Zhen"
    ],
    "name:zho_x_preferred":[
        "\u5927\u6cb3\u9547"
    ],
    "wof:name":"Dahe",
    "wof:placetype":"locality"
},
  "geometry": {"coordinates":[93.10603999999999,43.71107],"type":"Point"}
}