{
  "type": "Feature",
  "properties": {
    "gn:admin1_code":"02",
    "gn:asciiname":"Shanqian",
    "gn:country_code":"CN",
    "gn:dem":10,
    "gn:feature_class":"P",
    "gn:feature_code":"PPL",
    "gn:name":"Shanqian",
    "gn:population":0,
    "gn:timezone":"Asia/Shanghai",
    "iso:country":"CN",
    "name:zho_x_preferred":[
        "Shan-ch\u2019ien"
    ],
    "name:zho_x_variant":[
        "\u5c71\u524d"
    ],
    "wof:name":"Shanqian",
    "wof:placetype":"locality"
},
  "geometry": {"coordinates":[120.93040999999999,28.0022],"type":"Point"}
}