{
  "type": "Feature",
  "properties": {
    "gn:admin1_code":"26.0",
    "gn:asciiname":"Tuhuangshan",
    "gn:country_code":"CN",
    "gn:dem":1423,
    "gn:feature_class":"P",
    "gn:feature_code":"PPL",
    "gn:name":"Tuhuangshan",
    "gn:population":0,
    "gn:timezone":"Asia/Shanghai",
    "iso:country":"CN",
    "name:zho_x_preferred":[
        "\u571f\u9ec4\u5c71"
    ],
    "wof:name":"Tuhuangshan",
    "wof:placetype":"locality"
},
  "geometry": {"coordinates":[106.49661999999999,34.54085],"type":"Point"}
}