{
  "type": "Feature",
  "properties": {
    "gn:admin1_code":"29.0",
    "gn:asciiname":"Gazhu",
    "gn:country_code":"CN",
    "gn:dem":1582,
    "gn:feature_class":"P",
    "gn:feature_code":"PPL",
    "gn:name":"Gazhu",
    "gn:population":0,
    "gn:timezone":"Asia/Shanghai",
    "iso:country":"CN",
    "name:zho_x_preferred":[
        "\u560e\u67f1"
    ],
    "wof:name":"Gazhu",
    "wof:placetype":"locality"
},
  "geometry": {"coordinates":[100.43899999999999,27.4829],"type":"Point"}
}