{
  "type": "Feature",
  "properties": {
    "gn:admin1_code":"14.0",
    "gn:asciiname":"Yonggalecun",
    "gn:country_code":"CN",
    "gn:dem":4453,
    "gn:feature_class":"P",
    "gn:feature_code":"PPL",
    "gn:name":"Yonggalecun",
    "gn:population":0,
    "gn:timezone":"Asia/Urumqi",
    "iso:country":"CN",
    "name:zho_x_preferred":[
        "\u6c38\u560e\u52d2\u6751"
    ],
    "wof:name":"Yonggalecun",
    "wof:placetype":"locality"
},
  "geometry": {"coordinates":[93.07983,31.93131],"type":"Point"}
}