{
  "type": "Feature",
  "properties": {
    "gn:admin1_code":"10",
    "gn:asciiname":"Mojiatun",
    "gn:country_code":"CN",
    "gn:dem":104,
    "gn:feature_class":"P",
    "gn:feature_code":"PPL",
    "gn:name":"Mojiatun",
    "gn:population":0,
    "gn:timezone":"Asia/Shanghai",
    "iso:country":"CN",
    "name:zho_x_preferred":[
        "\u83ab\u5bb6\u5c6f"
    ],
    "wof:name":"Mojiatun",
    "wof:placetype":"locality"
},
  "geometry": {"coordinates":[118.15192999999999,40.08227],"type":"Point"}
}