{
  "type": "Feature",
  "properties": {
    "gn:admin1_code":"32.0",
    "gn:asciiname":"Lubanhui",
    "gn:country_code":"CN",
    "gn:dem":293,
    "gn:feature_class":"P",
    "gn:feature_code":"PPL",
    "gn:name":"Lubanhui",
    "gn:population":0,
    "gn:timezone":"Asia/Shanghai",
    "iso:country":"CN",
    "name:zho_x_preferred":[
        "\u9c81\u73ed\u4f1a"
    ],
    "wof:name":"Lubanhui",
    "wof:placetype":"locality"
},
  "geometry": {"coordinates":[105.55797,30.26002],"type":"Point"}
}