{
  "type": "Feature",
  "properties": {
    "gn:admin1_code":"16.0",
    "gn:asciiname":"Guihou",
    "gn:country_code":"CN",
    "gn:dem":918,
    "gn:feature_class":"P",
    "gn:feature_code":"PPL",
    "gn:name":"Guihou",
    "gn:population":0,
    "gn:timezone":"Asia/Shanghai",
    "iso:country":"CN",
    "name:zho_x_preferred":[
        "\u89c4\u540e"
    ],
    "wof:name":"Guihou",
    "wof:placetype":"locality"
},
  "geometry": {"coordinates":[105.955,23.1503],"type":"Point"}
}