{
  "type": "Feature",
  "properties": {
    "gn:admin1_code":"8.0",
    "gn:asciiname":"Shuanghongcun",
    "gn:country_code":"CN",
    "gn:dem":172,
    "gn:feature_class":"P",
    "gn:feature_code":"PPL",
    "gn:name":"Shuanghongcun",
    "gn:population":0,
    "gn:timezone":"Asia/Shanghai",
    "iso:country":"CN",
    "name:zho_x_preferred":[
        "\u53cc\u7ea2\u6751"
    ],
    "wof:name":"Shuanghongcun",
    "wof:placetype":"locality"
},
  "geometry": {"coordinates":[126.16619,45.4858],"type":"Point"}
}