{
  "type": "Feature",
  "properties": {
    "gn:admin1_code":"19.0",
    "gn:asciiname":"Liujia Wopucun",
    "gn:country_code":"CN",
    "gn:dem":165,
    "gn:feature_class":"P",
    "gn:feature_code":"PPL",
    "gn:name":"Liujia Wopucun",
    "gn:population":0,
    "gn:timezone":"Asia/Shanghai",
    "iso:country":"CN",
    "name:und_x_variant":[
        "Liujiawopucun",
        "Liujia Wopucun"
    ],
    "name:zho_x_preferred":[
        "\u516d\u5bb6\u7a9d\u94fa\u6751"
    ],
    "wof:name":"Liujia Wopucun",
    "wof:placetype":"locality"
},
  "geometry": {"coordinates":[120.58971,41.01143],"type":"Point"}
}