{
  "type": "Feature",
  "properties": {
    "gn:admin1_code":"24.0",
    "gn:asciiname":"Hejiao",
    "gn:country_code":"CN",
    "gn:dem":1873,
    "gn:feature_class":"P",
    "gn:feature_code":"PPL",
    "gn:name":"Hejiao",
    "gn:population":0,
    "gn:timezone":"Asia/Shanghai",
    "iso:country":"CN",
    "name:und_x_variant":[
        "\u6cb3\u86df"
    ],
    "name:zho_x_preferred":[
        "\u6cb3\u86df"
    ],
    "wof:name":"Hejiao",
    "wof:placetype":"locality"
},
  "geometry": {"coordinates":[113.35641,39.32339],"type":"Point"}
}