{
  "type": "Feature",
  "properties": {
    "gn:admin1_code":"25.0",
    "gn:asciiname":"Muyu",
    "gn:country_code":"CN",
    "gn:dem":34,
    "gn:feature_class":"P",
    "gn:feature_code":"PPL",
    "gn:name":"Muyu",
    "gn:population":0,
    "gn:timezone":"Asia/Shanghai",
    "iso:country":"CN",
    "name:zho_x_preferred":[
        "\u6c90\u6d74"
    ],
    "wof:name":"Muyu",
    "wof:placetype":"locality"
},
  "geometry": {"coordinates":[121.35074,37.33267],"type":"Point"}
}