{
  "type": "Feature",
  "properties": {
    "gn:admin1_code":"11.0",
    "gn:asciiname":"Jiuguanqiao",
    "gn:country_code":"CN",
    "gn:dem":132,
    "gn:feature_class":"P",
    "gn:feature_code":"PPL",
    "gn:name":"Jiuguanqiao",
    "gn:population":0,
    "gn:timezone":"Asia/Shanghai",
    "iso:country":"CN",
    "name:zho_x_preferred":[
        "\u4e5d\u89c2\u6865"
    ],
    "wof:name":"Jiuguanqiao",
    "wof:placetype":"locality"
},
  "geometry": {"coordinates":[112.69789,27.11555],"type":"Point"}
}