{
  "type": "Feature",
  "properties": {
    "gn:admin1_code":"11.0",
    "gn:asciiname":"Qishizhai",
    "gn:country_code":"CN",
    "gn:dem":319,
    "gn:feature_class":"P",
    "gn:feature_code":"PPL",
    "gn:name":"Qishizhai",
    "gn:population":0,
    "gn:timezone":"Asia/Shanghai",
    "iso:country":"CN",
    "name:zho_x_preferred":[
        "\u5c90\u77f3\u5be8"
    ],
    "wof:name":"Qishizhai",
    "wof:placetype":"locality"
},
  "geometry": {"coordinates":[110.70959000000001,27.14428],"type":"Point"}
}