{
  "type": "Feature",
  "properties": {
    "gn:admin1_code":"32.0",
    "gn:asciiname":"Nurige",
    "gn:country_code":"CN",
    "gn:dem":4269,
    "gn:feature_class":"P",
    "gn:feature_code":"PPL",
    "gn:name":"N\u00fcrige",
    "gn:population":0,
    "gn:timezone":"Asia/Shanghai",
    "iso:country":"CN",
    "name:und_x_variant":[
        "N\u00fcrige"
    ],
    "name:zho_x_preferred":[
        "\u5973\u65e5\u683c"
    ],
    "wof:name":"Nurige",
    "wof:placetype":"locality"
},
  "geometry": {"coordinates":[101.56,30.8525],"type":"Point"}
}