{
  "type": "Feature",
  "properties": {
    "gn:admin1_code":"14.0",
    "gn:asciiname":"Cuoqiongda",
    "gn:country_code":"CN",
    "gn:dem":4310,
    "gn:feature_class":"P",
    "gn:feature_code":"PPL",
    "gn:name":"Cuoqiongda",
    "gn:population":0,
    "gn:timezone":"Asia/Urumqi",
    "iso:country":"CN",
    "name:zho_x_preferred":[
        "\u9519\u7a77\u8fbe"
    ],
    "wof:name":"Cuoqiongda",
    "wof:placetype":"locality"
},
  "geometry": {"coordinates":[94.17086999999999,29.57434000000001],"type":"Point"}
}