{
  "type": "Feature",
  "properties": {
    "gn:admin1_code":"11.0",
    "gn:asciiname":"Zhenjiatuan",
    "gn:country_code":"CN",
    "gn:dem":365,
    "gn:feature_class":"P",
    "gn:feature_code":"PPL",
    "gn:name":"Zhenjiatuan",
    "gn:population":0,
    "gn:timezone":"Asia/Shanghai",
    "iso:country":"CN",
    "name:zho_x_preferred":[
        "\u7504\u5bb6\u56e2"
    ],
    "wof:name":"Zhenjiatuan",
    "wof:placetype":"locality"
},
  "geometry": {"coordinates":[109.81346000000001,26.51889000000001],"type":"Point"}
}