{
  "type": "Feature",
  "properties": {
    "gn:admin1_code":"21.0",
    "gn:asciiname":"Guanquzha",
    "gn:country_code":"CN",
    "gn:dem":1134,
    "gn:feature_class":"P",
    "gn:feature_code":"PPL",
    "gn:name":"Guanquzha",
    "gn:population":0,
    "gn:timezone":"Asia/Shanghai",
    "iso:country":"CN",
    "name:zho_x_preferred":[
        "\u5173\u6e20\u95f8"
    ],
    "wof:name":"Guanquzha",
    "wof:placetype":"locality"
},
  "geometry": {"coordinates":[106.149,37.9422],"type":"Point"}
}