{
  "type": "Feature",
  "properties": {
    "gn:admin1_code":"23.0",
    "gn:asciiname":"Lingjiazhai",
    "gn:country_code":"CN",
    "gn:dem":4,
    "gn:feature_class":"P",
    "gn:feature_code":"PPL",
    "gn:name":"Lingjiazhai",
    "gn:population":0,
    "gn:timezone":"Asia/Shanghai",
    "iso:country":"CN",
    "name:zho_x_preferred":[
        "Lingjiazhai"
    ],
    "name:zho_x_variant":[
        "\u51cc\u5bb6\u5b85"
    ],
    "wof:name":"Lingjiazhai",
    "wof:placetype":"locality"
},
  "geometry": {"coordinates":[121.58443,31.14228],"type":"Point"}
}