{
  "type": "Feature",
  "properties": {
    "gn:admin1_code":"8.0",
    "gn:asciiname":"Yingchun",
    "gn:country_code":"CN",
    "gn:dem":165,
    "gn:feature_class":"P",
    "gn:feature_code":"PPL",
    "gn:name":"Yingchun",
    "gn:population":0,
    "gn:timezone":"Asia/Shanghai",
    "iso:country":"CN",
    "name:zho_x_preferred":[
        "\u8fce\u6625"
    ],
    "wof:name":"Yingchun",
    "wof:placetype":"locality"
},
  "geometry": {"coordinates":[123.58278,47.76529],"type":"Point"}
}