{
  "type": "Feature",
  "properties": {
    "gn:admin1_code":"25",
    "gn:asciiname":"Helou",
    "gn:country_code":"CN",
    "gn:dem":53,
    "gn:feature_class":"P",
    "gn:feature_code":"PPL",
    "gn:name":"Helou",
    "gn:population":0,
    "gn:timezone":"Asia/Shanghai",
    "iso:country":"CN",
    "name:rus_x_preferred":[
        "\u042d\u043b\u0443"
    ],
    "name:zho_x_preferred":[
        "\u4f55\u697c"
    ],
    "wof:name":"Helou",
    "wof:placetype":"locality"
},
  "geometry": {"coordinates":[115.494,35.2342],"type":"Point"}
}