{
  "type": "Feature",
  "properties": {
    "gn:admin1_code":"29.0",
    "gn:asciiname":"Mange",
    "gn:country_code":"CN",
    "gn:dem":558,
    "gn:feature_class":"P",
    "gn:feature_code":"PPL",
    "gn:name":"Mange",
    "gn:population":0,
    "gn:timezone":"Asia/Shanghai",
    "iso:country":"CN",
    "name:dan_x_preferred":[
        "Skab"
    ],
    "name:deu_x_preferred":[
        "R\u00e4ude"
    ],
    "name:fin_x_preferred":[
        "Kapi"
    ],
    "name:gle_x_preferred":[
        "Claimhe"
    ],
    "name:ind_x_preferred":[
        "Mange"
    ],
    "name:ita_x_preferred":[
        "Rogna"
    ],
    "name:jpn_x_preferred":[
        "\u6bdb\u5305\u866b\u75c7"
    ],
    "name:nld_x_preferred":[
        "Schurft"
    ],
    "name:pol_x_preferred":[
        "Nu\u017cyca"
    ],
    "name:zho_x_preferred":[
        "\u66fc\u5404"
    ],
    "name:zho_x_variant":[
        "\u6bdb\u56ca\u87f2\u75c5"
    ],
    "wof:name":"Mange",
    "wof:placetype":"locality"
},
  "geometry": {"coordinates":[100.794,22.0286],"type":"Point"}
}