{
  "type": "Feature",
  "properties": {
    "gn:admin1_code":"7.0",
    "gn:asciiname":"Pushangcun",
    "gn:country_code":"CN",
    "gn:dem":133,
    "gn:feature_class":"P",
    "gn:feature_code":"PPL",
    "gn:name":"Pushangcun",
    "gn:population":0,
    "gn:timezone":"Asia/Shanghai",
    "iso:country":"CN",
    "name:und_x_variant":[
        "\u57d4\u4e0a\u6751"
    ],
    "name:zho_x_preferred":[
        "\u57d4\u4e0a\u6751"
    ],
    "wof:name":"Pushangcun",
    "wof:placetype":"locality"
},
  "geometry": {"coordinates":[117.76931,26.93122],"type":"Point"}
}