{
  "type": "Feature",
  "properties": {
    "gn:admin1_code":"9.0",
    "gn:asciiname":"Luma",
    "gn:country_code":"CN",
    "gn:dem":722,
    "gn:feature_class":"P",
    "gn:feature_code":"PPL",
    "gn:name":"Luma",
    "gn:population":0,
    "gn:timezone":"Asia/Shanghai",
    "iso:country":"CN",
    "name:ceb_x_preferred":[
        "Luma"
    ],
    "name:deu_x_preferred":[
        "Luma"
    ],
    "name:fin_x_preferred":[
        "Luma"
    ],
    "name:fra_x_preferred":[
        "Luma"
    ],
    "name:mar_x_preferred":[
        "\u0906\u0930\u094d\u092e\u0947\u0928\u093f\u092f\u0928 \u0932\u0941\u092e\u093e"
    ],
    "name:por_x_preferred":[
        "Luma"
    ],
    "name:rus_x_preferred":[
        "\u041b\u0443\u043c\u0430"
    ],
    "name:spa_x_preferred":[
        "Luma"
    ],
    "name:swe_x_preferred":[
        "Luma"
    ],
    "name:zho_x_preferred":[
        "\u9e7f\u9a6c"
    ],
    "wof:name":"Luma",
    "wof:placetype":"locality"
},
  "geometry": {"coordinates":[111.45699999999999,34.78274],"type":"Point"}
}