{
  "type": "Feature",
  "properties": {
    "gn:admin1_code":"16.0",
    "gn:asciiname":"Jianshang",
    "gn:country_code":"CN",
    "gn:dem":366,
    "gn:feature_class":"P",
    "gn:feature_code":"PPL",
    "gn:name":"Jianshang",
    "gn:population":0,
    "gn:timezone":"Asia/Shanghai",
    "iso:country":"CN",
    "name:zho_x_preferred":[
        "\u6da7\u4e0a"
    ],
    "wof:name":"Jianshang",
    "wof:placetype":"locality"
},
  "geometry": {"coordinates":[111.232,25.0998],"type":"Point"}
}