{
  "type": "Feature",
  "properties": {
    "gn:admin1_code":"4.0",
    "gn:asciiname":"Xuanxuzicun",
    "gn:country_code":"CN",
    "gn:dem":38,
    "gn:feature_class":"P",
    "gn:feature_code":"PPL",
    "gn:name":"Xuanxuzicun",
    "gn:population":0,
    "gn:timezone":"Asia/Shanghai",
    "iso:country":"CN",
    "name:zho_x_preferred":[
        "\u8881\u5729\u5b50\u6751"
    ],
    "wof:name":"Xuanxuzicun",
    "wof:placetype":"locality"
},
  "geometry": {"coordinates":[116.87927000000001,34.56628],"type":"Point"}
}