{
  "type": "Feature",
  "properties": {
    "gn:admin1_code":"16.0",
    "gn:asciiname":"Nongmei",
    "gn:country_code":"CN",
    "gn:dem":329,
    "gn:feature_class":"P",
    "gn:feature_code":"PPL",
    "gn:name":"Nongmei",
    "gn:population":0,
    "gn:timezone":"Asia/Shanghai",
    "iso:country":"CN",
    "name:zho_x_preferred":[
        "\u5f04\u7f8e"
    ],
    "wof:name":"Nongmei",
    "wof:placetype":"locality"
},
  "geometry": {"coordinates":[107.93300000000001,23.8144],"type":"Point"}
}