{
  "type": "Feature",
  "properties": {
    "gn:admin1_code":"7.0",
    "gn:asciiname":"Guikeng",
    "gn:country_code":"CN",
    "gn:dem":411,
    "gn:feature_class":"P",
    "gn:feature_code":"PPL",
    "gn:name":"Guikeng",
    "gn:population":0,
    "gn:timezone":"Asia/Shanghai",
    "iso:country":"CN",
    "name:zho_x_preferred":[
        "\u9b3c\u5751"
    ],
    "wof:name":"Guikeng",
    "wof:placetype":"locality"
},
  "geometry": {"coordinates":[116.73241000000002,25.47606],"type":"Point"}
}