{
  "type": "Feature",
  "properties": {
    "gn:admin1_code":"19.0",
    "gn:asciiname":"Yaoma Shangou",
    "gn:country_code":"CN",
    "gn:dem":126,
    "gn:feature_class":"P",
    "gn:feature_code":"PPL",
    "gn:name":"Yaoma Shangou",
    "gn:population":0,
    "gn:timezone":"Asia/Shanghai",
    "iso:country":"CN",
    "name:zho_x_preferred":[
        "\u8170\u9a6c\u5c71\u6c9f"
    ],
    "wof:name":"Yaoma Shangou",
    "wof:placetype":"locality"
},
  "geometry": {"coordinates":[121.0754,41.55651],"type":"Point"}
}