{
  "type": "Feature",
  "properties": {
    "gn:admin1_code":"25",
    "gn:asciiname":"Zhanghoutang",
    "gn:country_code":"CN",
    "gn:dem":37,
    "gn:feature_class":"P",
    "gn:feature_code":"PPL",
    "gn:name":"Zhanghoutang",
    "gn:population":0,
    "gn:timezone":"Asia/Shanghai",
    "iso:country":"CN",
    "name:und_x_variant":[
        "Zhangchen"
    ],
    "name:zho_x_preferred":[
        "\u5f20\u540e\u5802"
    ],
    "name:zho_x_variant":[
        "\u5f20\u9648"
    ],
    "wof:name":"Zhanghoutang",
    "wof:placetype":"locality"
},
  "geometry": {"coordinates":[115.94004,36.60311],"type":"Point"}
}