{
  "type": "Feature",
  "properties": {
    "gn:admin1_code":"11.0",
    "gn:asciiname":"Qijiating",
    "gn:country_code":"CN",
    "gn:dem":137,
    "gn:feature_class":"P",
    "gn:feature_code":"PPL",
    "gn:name":"Qijiating",
    "gn:population":0,
    "gn:timezone":"Asia/Shanghai",
    "iso:country":"CN",
    "name:zho_x_preferred":[
        "\u6f06\u5bb6\u4ead"
    ],
    "wof:name":"Qijiating",
    "wof:placetype":"locality"
},
  "geometry": {"coordinates":[111.78274999999999,26.65223],"type":"Point"}
}