{
  "type": "Feature",
  "properties": {
    "gn:admin1_code":"4.0",
    "gn:asciiname":"Yandi",
    "gn:country_code":"CN",
    "gn:dem":4,
    "gn:feature_class":"P",
    "gn:feature_code":"PPL",
    "gn:name":"Yandi",
    "gn:population":0,
    "gn:timezone":"Asia/Shanghai",
    "iso:country":"CN",
    "name:ceb_x_preferred":[
        "Yandi"
    ],
    "name:swe_x_preferred":[
        "Yandi"
    ],
    "name:zho_x_preferred":[
        "\u6cbf\u5824"
    ],
    "wof:name":"Yandi",
    "wof:placetype":"locality"
},
  "geometry": {"coordinates":[120.82526,32.65962],"type":"Point"}
}