{
  "type": "Feature",
  "properties": {
    "gn:admin1_code":"32.0",
    "gn:asciiname":"Choushuihe",
    "gn:country_code":"CN",
    "gn:dem":1721,
    "gn:feature_class":"P",
    "gn:feature_code":"PPL",
    "gn:name":"Choushuihe",
    "gn:population":0,
    "gn:timezone":"Asia/Shanghai",
    "iso:country":"CN",
    "name:zho_x_preferred":[
        "\u81ed\u6c34\u6cb3"
    ],
    "wof:name":"Choushuihe",
    "wof:placetype":"locality"
},
  "geometry": {"coordinates":[103.44199999999999,27.8787],"type":"Point"}
}