{
  "type": "Feature",
  "properties": {
    "gn:admin1_code":"26.0",
    "gn:asciiname":"Huangbaiyuanxiang",
    "gn:country_code":"CN",
    "gn:dem":1294,
    "gn:feature_class":"P",
    "gn:feature_code":"PPL",
    "gn:name":"Huangbaiyuanxiang",
    "gn:population":0,
    "gn:timezone":"Asia/Shanghai",
    "iso:country":"CN",
    "name:und_x_variant":[
        "\u9ec4\u67cf\u586c\u4e61"
    ],
    "wof:name":"Huangbaiyuanxiang",
    "wof:placetype":"locality"
},
  "geometry": {"coordinates":[107.51452999999999,33.81022],"type":"Point"}
}