{
  "type": "Feature",
  "properties": {
    "gn:admin1_code":"20.0",
    "gn:asciiname":"Damiangou",
    "gn:country_code":"CN",
    "gn:dem":1830,
    "gn:feature_class":"P",
    "gn:feature_code":"PPL",
    "gn:name":"Damiangou",
    "gn:population":0,
    "gn:timezone":"Asia/Shanghai",
    "iso:country":"CN",
    "name:und_x_variant":[
        "\u5927\u9762\u6c9f"
    ],
    "wof:name":"Damiangou",
    "wof:placetype":"locality"
},
  "geometry": {"coordinates":[110.76298,41.02851],"type":"Point"}
}