{
  "type": "Feature",
  "properties": {
    "gn:admin1_code":"18.0",
    "gn:asciiname":"Yizehe",
    "gn:country_code":"CN",
    "gn:dem":2201,
    "gn:feature_class":"P",
    "gn:feature_code":"PPL",
    "gn:name":"Yizehe",
    "gn:population":0,
    "gn:timezone":"Asia/Shanghai",
    "iso:country":"CN",
    "name:und_x_variant":[
        "I-tse-ho",
        "Yizehe"
    ],
    "name:zho_x_preferred":[
        "\u4ee5\u5219\u6cb3"
    ],
    "wof:name":"Yizehe",
    "wof:placetype":"locality"
},
  "geometry": {"coordinates":[104.32599999999999,27.3212],"type":"Point"}
}