{
  "type": "Feature",
  "properties": {
    "gn:admin1_code":"15.0",
    "gn:asciiname":"Yangxinbu",
    "gn:country_code":"CN",
    "gn:dem":1732,
    "gn:feature_class":"P",
    "gn:feature_code":"PPL",
    "gn:name":"Yangxinbu",
    "gn:population":0,
    "gn:timezone":"Asia/Shanghai",
    "iso:country":"CN",
    "name:und_x_variant":[
        "\u6768\u65b0\u5821"
    ],
    "wof:name":"Yangxinbu",
    "wof:placetype":"locality"
},
  "geometry": {"coordinates":[106.73273,36.81022],"type":"Point"}
}