{
  "type": "Feature",
  "properties": {
    "gn:admin1_code":"16.0",
    "gn:asciiname":"Changgailing",
    "gn:country_code":"CN",
    "gn:dem":54,
    "gn:feature_class":"P",
    "gn:feature_code":"PPL",
    "gn:name":"Changgailing",
    "gn:population":0,
    "gn:timezone":"Asia/Shanghai",
    "iso:country":"CN",
    "name:zho_x_preferred":[
        "\u9520\u76d6\u5cad"
    ],
    "wof:name":"Changgailing",
    "wof:placetype":"locality"
},
  "geometry": {"coordinates":[109.253,22.1609],"type":"Point"}
}