{
  "type": "Feature",
  "properties": {
    "gn:admin1_code":"3.0",
    "gn:asciiname":"Zhapu Kouxia",
    "gn:country_code":"CN",
    "gn:dem":16,
    "gn:feature_class":"P",
    "gn:feature_code":"PPL",
    "gn:name":"Zhapu Kouxia",
    "gn:population":0,
    "gn:timezone":"Asia/Shanghai",
    "iso:country":"CN",
    "name:und_x_variant":[
        "\u69a8\u6d66\u53e3\u4e0b"
    ],
    "wof:name":"Zhapu Kouxia",
    "wof:placetype":"locality"
},
  "geometry": {"coordinates":[116.15161000000001,28.83026],"type":"Point"}
}