{
  "type": "Feature",
  "properties": {
    "gn:admin1_code":"5.0",
    "gn:asciiname":"Qianchenjia Tangfang",
    "gn:country_code":"CN",
    "gn:dem":214,
    "gn:feature_class":"P",
    "gn:feature_code":"PPL",
    "gn:name":"Qianchenjia Tangfang",
    "gn:population":0,
    "gn:timezone":"Asia/Shanghai",
    "iso:country":"CN",
    "name:zho_x_preferred":[
        "\u524d\u9648\u5bb6\u6e8f\u623f"
    ],
    "wof:name":"Qianchenjia Tangfang",
    "wof:placetype":"locality"
},
  "geometry": {"coordinates":[126.08023,43.80061],"type":"Point"}
}