{
  "type": "Feature",
  "properties": {
    "gn:admin1_code":"19.0",
    "gn:asciiname":"Dadougouzi",
    "gn:country_code":"CN",
    "gn:dem":195,
    "gn:feature_class":"P",
    "gn:feature_code":"PPL",
    "gn:name":"Dadougouzi",
    "gn:population":0,
    "gn:timezone":"Asia/Shanghai",
    "iso:country":"CN",
    "name:zho_x_preferred":[
        "\u5927\u9661\u6c9f\u5b50"
    ],
    "wof:name":"Dadougouzi",
    "wof:placetype":"locality"
},
  "geometry": {"coordinates":[124.52235,40.84156],"type":"Point"}
}