{
  "type": "Feature",
  "properties": {
    "gn:admin1_code":"11.0",
    "gn:asciiname":"Shuixicun",
    "gn:country_code":"CN",
    "gn:dem":320,
    "gn:feature_class":"P",
    "gn:feature_code":"PPL",
    "gn:name":"Shuixicun",
    "gn:population":0,
    "gn:timezone":"Asia/Shanghai",
    "iso:country":"CN",
    "name:zho_x_preferred":[
        "\u6c34\u897f\u6751"
    ],
    "wof:name":"Shuixicun",
    "wof:placetype":"locality"
},
  "geometry": {"coordinates":[110.81089,26.31477000000001],"type":"Point"}
}