{
  "type": "Feature",
  "properties": {
    "gn:admin1_code":"14.0",
    "gn:asciiname":"Tanglaimucun",
    "gn:country_code":"CN",
    "gn:dem":3860,
    "gn:feature_class":"P",
    "gn:feature_code":"PPL",
    "gn:name":"Tanglaimucun",
    "gn:population":0,
    "gn:timezone":"Asia/Urumqi",
    "iso:country":"CN",
    "name:zho_x_preferred":[
        "\u5802\u6765\u6728\u6751"
    ],
    "wof:name":"Tanglaimucun",
    "wof:placetype":"locality"
},
  "geometry": {"coordinates":[92.71586000000001,28.35316],"type":"Point"}
}