{
  "type": "Feature",
  "properties": {
    "gn:admin1_code":"8.0",
    "gn:asciiname":"Xifengtun",
    "gn:country_code":"CN",
    "gn:dem":243,
    "gn:feature_class":"P",
    "gn:feature_code":"PPL",
    "gn:name":"Xifengtun",
    "gn:population":0,
    "gn:timezone":"Asia/Shanghai",
    "iso:country":"CN",
    "name:zho_x_preferred":[
        "\u897f\u4e30\u5c6f"
    ],
    "wof:name":"Xifengtun",
    "wof:placetype":"locality"
},
  "geometry": {"coordinates":[125.09975,48.12434],"type":"Point"}
}