{
  "type": "Feature",
  "properties": {
    "gn:admin1_code":"13.0",
    "gn:asciiname":"Tumxuk",
    "gn:country_code":"CN",
    "gn:dem":1225,
    "gn:feature_class":"P",
    "gn:feature_code":"PPLA4",
    "gn:name":"Tumxuk",
    "gn:population":0,
    "gn:timezone":"Asia/Shanghai",
    "iso:country":"CN",
    "name:uig_x_preferred":[
        "Tumxuk\u0329"
    ],
    "name:uig_x_variant":[
        "Tumshuq",
        "\u062a\u06c7\u0645\u0634\u06c7\u0642",
        "\u0422\u0443\u043c\u0448\u0443\u049b"
    ],
    "name:und_x_variant":[
        "T\u2019u-mu-hsiu-k\u2019o",
        "Tumxuk",
        "Tumuxiuke",
        "Tumuxiuke Zhen"
    ],
    "name:zho_x_preferred":[
        "\u5410\u6728\u79c0\u514b"
    ],
    "name:zho_x_variant":[
        "\u5410\u6728\u79c0\u514b\u9547"
    ],
    "wof:name":"Tumxuk",
    "wof:placetype":"locality"
},
  "geometry": {"coordinates":[79.96278000000002,41.36861],"type":"Point"}
}