{
  "type": "Feature",
  "properties": {
    "gn:admin1_code":"13.0",
    "gn:asciiname":"Tumxuk",
    "gn:country_code":"CN",
    "gn:dem":1225,
    "gn:feature_class":"P",
    "gn:feature_code":"PPLA4",
    "gn:name":"Tumxuk",
    "gn:population":0,
    "gn:timezone":"Asia/Shanghai",
    "iso:country":"CN",
    "name:ara_x_preferred":[
        "\u062a\u0648\u0645\u062a\u0634\u0648\u0643"
    ],
    "name:cdo_x_preferred":[
        "Tumxuk"
    ],
    "name:deu_x_preferred":[
        "Tumxuk"
    ],
    "name:ell_x_preferred":[
        "\u03a4\u03bf\u03c5\u03bc\u03c3\u03bf\u03cd\u03ba"
    ],
    "name:est_x_preferred":[
        "Tumxuk"
    ],
    "name:eus_x_preferred":[
        "Tumshuke"
    ],
    "name:fas_x_preferred":[
        "\u062a\u0648\u0645\u0634\u0648\u0642"
    ],
    "name:fra_x_preferred":[
        "Tumushuke"
    ],
    "name:ita_x_preferred":[
        "Tumxuk"
    ],
    "name:jpn_x_preferred":[
        "\u30c8\u30e0\u30b7\u30e5\u30af\u5e02"
    ],
    "name:kik_x_preferred":[
        "Tumxuk"
    ],
    "name:kor_x_preferred":[
        "\ud22c\ubb34\uc218\ucee4\uc2dc"
    ],
    "name:nld_x_preferred":[
        "Tumxuk"
    ],
    "name:nor_x_preferred":[
        "Tumxuk"
    ],
    "name:pol_x_preferred":[
        "Tumxuk"
    ],
    "name:rus_x_preferred":[
        "\u0422\u0443\u043c\u0448\u0443\u043a"
    ],
    "name:spa_x_preferred":[
        "Tumshuke"
    ],
    "name:swe_x_preferred":[
        "Tumshuq"
    ],
    "name:tur_x_preferred":[
        "Tom\u015fuk"
    ],
    "name:uig_x_preferred":[
        "Tumxuk\u0329"
    ],
    "name:uig_x_variant":[
        "Tumshuq",
        "\u062a\u06c7\u0645\u0634\u06c7\u0642",
        "\u0422\u0443\u043c\u0448\u0443\u049b",
        "\u062a\u06c7\u0645\u0634\u06c7\u0642 \u0634\u06d5\u06be\u0649\u0631\u0649"
    ],
    "name:und_x_variant":[
        "T\u2019u-mu-hsiu-k\u2019o",
        "Tumuxiuke",
        "Tumuxiuke Zhen"
    ],
    "name:urd_x_preferred":[
        "\u062a\u0648\u0645\u0634\u0648\u06a9"
    ],
    "name:vie_x_preferred":[
        "Tumxuk"
    ],
    "name:zho_x_preferred":[
        "\u5410\u6728\u79c0\u514b"
    ],
    "name:zho_x_variant":[
        "\u5410\u6728\u79c0\u514b\u9547",
        "\u56fe\u6728\u8212\u514b\u5e02"
    ],
    "wof:name":"Tumxuk",
    "wof:placetype":"locality"
},
  "geometry": {"coordinates":[79.96278000000002,41.36861],"type":"Point"}
}