{
  "type": "Feature",
  "properties": {
    "gn:admin1_code":"19.0",
    "gn:asciiname":"Baiyegou",
    "gn:country_code":"CN",
    "gn:dem":117,
    "gn:feature_class":"P",
    "gn:feature_code":"PPL",
    "gn:name":"Baiyegou",
    "gn:population":0,
    "gn:timezone":"Asia/Shanghai",
    "iso:country":"CN",
    "name:und_x_variant":[
        "\u67cf\u53f6\u6c9f"
    ],
    "name:zho_x_preferred":[
        "\u67cf\u53f6\u6c9f"
    ],
    "wof:name":"Baiyegou",
    "wof:placetype":"locality"
},
  "geometry": {"coordinates":[123.75142,41.72064],"type":"Point"}
}