{
  "type": "Feature",
  "properties": {
    "gn:admin1_code":"18",
    "gn:asciiname":"Youmushui",
    "gn:country_code":"CN",
    "gn:dem":662,
    "gn:feature_class":"P",
    "gn:feature_code":"PPL",
    "gn:name":"Youmushui",
    "gn:population":0,
    "gn:timezone":"Asia/Shanghai",
    "iso:country":"CN",
    "name:zho_x_preferred":[
        "\u6cb9\u6728\u6c34"
    ],
    "wof:name":"Youmushui",
    "wof:placetype":"locality"
},
  "geometry": {"coordinates":[107.931,28.4809],"type":"Point"}
}