{
  "type": "Feature",
  "properties": {
    "gn:admin1_code":"9.0",
    "gn:asciiname":"Duiwoshi",
    "gn:country_code":"CN",
    "gn:dem":342,
    "gn:feature_class":"P",
    "gn:feature_code":"PPL",
    "gn:name":"Duiwoshi",
    "gn:population":0,
    "gn:timezone":"Asia/Shanghai",
    "iso:country":"CN",
    "name:zho_x_preferred":[
        "\u7893\u7a9d\u77f3"
    ],
    "wof:name":"Duiwoshi",
    "wof:placetype":"locality"
},
  "geometry": {"coordinates":[114.82004999999999,31.62435],"type":"Point"}
}