{
  "type": "Feature",
  "properties": {
    "gn:admin1_code":"15.0",
    "gn:asciiname":"Jiadaogou",
    "gn:country_code":"CN",
    "gn:dem":2114,
    "gn:feature_class":"P",
    "gn:feature_code":"PPL",
    "gn:name":"Jiadaogou",
    "gn:population":0,
    "gn:timezone":"Asia/Shanghai",
    "iso:country":"CN",
    "name:zho_x_preferred":[
        "\u5939\u9053\u6c9f"
    ],
    "wof:name":"Jiadaogou",
    "wof:placetype":"locality"
},
  "geometry": {"coordinates":[104.32599999999999,36.2973],"type":"Point"}
}