{
  "type": "Feature",
  "properties": {
    "gn:admin1_code":"18.0",
    "gn:asciiname":"Taoziping",
    "gn:country_code":"CN",
    "gn:dem":930,
    "gn:feature_class":"P",
    "gn:feature_code":"PPL",
    "gn:name":"Taoziping",
    "gn:population":0,
    "gn:timezone":"Asia/Shanghai",
    "iso:country":"CN",
    "name:zho_x_preferred":[
        "\u6843\u5b50\u576a"
    ],
    "wof:name":"Taoziping",
    "wof:placetype":"locality"
},
  "geometry": {"coordinates":[107.84099999999999,26.88300000000001],"type":"Point"}
}