{
  "type": "Feature",
  "properties": {
    "gn:admin1_code":"29",
    "gn:asciiname":"Qianchang",
    "gn:country_code":"CN",
    "gn:dem":2207,
    "gn:feature_class":"P",
    "gn:feature_code":"PPL",
    "gn:name":"Qianchang",
    "gn:population":0,
    "gn:timezone":"Asia/Shanghai",
    "iso:country":"CN",
    "wof:name":"Qianchang",
    "wof:placetype":"locality"
},
  "geometry": {"coordinates":[101.37,25.52361],"type":"Point"}
}