{
  "type": "Feature",
  "properties": {
    "gn:admin1_code":"8.0",
    "gn:asciiname":"Xigongsi",
    "gn:country_code":"CN",
    "gn:dem":207,
    "gn:feature_class":"P",
    "gn:feature_code":"PPL",
    "gn:name":"Xigongsi",
    "gn:population":0,
    "gn:timezone":"Asia/Shanghai",
    "iso:country":"CN",
    "name:zho_x_preferred":[
        "\u897f\u516c\u53f8"
    ],
    "wof:name":"Xigongsi",
    "wof:placetype":"locality"
},
  "geometry": {"coordinates":[123.12367999999999,47.36963],"type":"Point"}
}