{
  "type": "Feature",
  "properties": {
    "gn:admin1_code":"29.0",
    "gn:asciiname":"Haizi",
    "gn:country_code":"CN",
    "gn:dem":2036,
    "gn:feature_class":"P",
    "gn:feature_code":"PPL",
    "gn:name":"Haizi",
    "gn:population":0,
    "gn:timezone":"Asia/Shanghai",
    "iso:country":"CN",
    "name:zho_x_preferred":[
        "\u6d77\u5b50"
    ],
    "wof:name":"Haizi",
    "wof:placetype":"locality"
},
  "geometry": {"coordinates":[102.907,25.7842],"type":"Point"}
}