{
  "type": "Feature",
  "properties": {
    "gn:admin1_code":"29.0",
    "gn:asciiname":"Tuobieluzhua",
    "gn:country_code":"CN",
    "gn:dem":2714,
    "gn:feature_class":"P",
    "gn:feature_code":"PPL",
    "gn:name":"Tuobieluzhua",
    "gn:population":0,
    "gn:timezone":"Asia/Shanghai",
    "iso:country":"CN",
    "name:zho_x_preferred":[
        "\u6258\u522b\u9c81\u6293"
    ],
    "wof:name":"Tuobieluzhua",
    "wof:placetype":"locality"
},
  "geometry": {"coordinates":[99.35339999999999,27.7161],"type":"Point"}
}