{
  "type": "Feature",
  "properties": {
    "gn:admin1_code":"11.0",
    "gn:asciiname":"Yanmianqian",
    "gn:country_code":"CN",
    "gn:dem":180,
    "gn:feature_class":"P",
    "gn:feature_code":"PPL",
    "gn:name":"Yanmianqian",
    "gn:population":0,
    "gn:timezone":"Asia/Shanghai",
    "iso:country":"CN",
    "name:zho_x_preferred":[
        "\u5ca9\u9762\u524d"
    ],
    "wof:name":"Yanmianqian",
    "wof:placetype":"locality"
},
  "geometry": {"coordinates":[111.91364,27.0952],"type":"Point"}
}