{
  "type": "Feature",
  "properties": {
    "gn:admin1_code":"14",
    "gn:asciiname":"Ngarrab",
    "gn:country_code":"CN",
    "gn:dem":3222,
    "gn:feature_class":"P",
    "gn:feature_code":"PPL",
    "gn:name":"Ngarrab",
    "gn:population":0,
    "gn:timezone":"Asia/Urumqi",
    "iso:country":"CN",
    "name:bod_x_preferred":[
        "\u0f44\u0f62\u0f0b\u0f62\u0f56"
    ],
    "name:und_x_variant":[
        "Anrao"
    ],
    "name:zho_x_preferred":[
        "\u5b89\u7ed5"
    ],
    "wof:name":"Ngarrab",
    "wof:placetype":"locality"
},
  "geometry": {"coordinates":[92.62461999999999,29.11288],"type":"Point"}
}