{
  "type": "Feature",
  "properties": {
    "gn:admin1_code":"24.0",
    "gn:asciiname":"Shanghuangzhuang",
    "gn:country_code":"CN",
    "gn:dem":1158,
    "gn:feature_class":"P",
    "gn:feature_code":"PPL",
    "gn:name":"Shanghuangzhuang",
    "gn:population":0,
    "gn:timezone":"Asia/Shanghai",
    "iso:country":"CN",
    "name:zho_x_preferred":[
        "\u4e0a\u7687\u5e84"
    ],
    "wof:name":"Shanghuangzhuang",
    "wof:placetype":"locality"
},
  "geometry": {"coordinates":[113.24460999999999,40.13796],"type":"Point"}
}