{
  "type": "Feature",
  "properties": {
    "gn:admin1_code":"26.0",
    "gn:asciiname":"Liujiamiaoping",
    "gn:country_code":"CN",
    "gn:dem":1155,
    "gn:feature_class":"P",
    "gn:feature_code":"PPL",
    "gn:name":"Liujiamiaoping",
    "gn:population":0,
    "gn:timezone":"Asia/Shanghai",
    "iso:country":"CN",
    "name:zho_x_preferred":[
        "\u5218\u5bb6\u5e99\u576a"
    ],
    "wof:name":"Liujiamiaoping",
    "wof:placetype":"locality"
},
  "geometry": {"coordinates":[109.28597000000001,36.9902],"type":"Point"}
}