{
  "type": "Feature",
  "properties": {
    "gn:admin1_code":"15.0",
    "gn:asciiname":"Yazou",
    "gn:country_code":"CN",
    "gn:dem":2606,
    "gn:feature_class":"P",
    "gn:feature_code":"PPL",
    "gn:name":"Yazou",
    "gn:population":0,
    "gn:timezone":"Asia/Shanghai",
    "iso:country":"CN",
    "name:und_x_variant":[
        "\u7259\u8d70"
    ],
    "wof:name":"Yazou",
    "wof:placetype":"locality"
},
  "geometry": {"coordinates":[104.49476,34.14127],"type":"Point"}
}