{
  "type": "Feature",
  "properties": {
    "gn:admin1_code":"30",
    "gn:asciiname":"Xiayanting",
    "gn:country_code":"CN",
    "gn:dem":6,
    "gn:feature_class":"P",
    "gn:feature_code":"PPL",
    "gn:name":"Xiayanting",
    "gn:population":0,
    "gn:timezone":"Asia/Shanghai",
    "iso:country":"CN",
    "name:und_x_variant":[
        "Xiayanjiang",
        "Xiayanting"
    ],
    "name:zho_x_preferred":[
        "\u4e0b\u76d0\u6c40"
    ],
    "wof:name":"Xiayanting",
    "wof:placetype":"locality"
},
  "geometry": {"coordinates":[116.48247000000001,23.20258],"type":"Point"}
}