{
  "type": "Feature",
  "properties": {
    "gn:admin1_code":"25.0",
    "gn:asciiname":"Qianjiacun",
    "gn:country_code":"CN",
    "gn:dem":20,
    "gn:feature_class":"P",
    "gn:feature_code":"PPL",
    "gn:name":"Qianjiacun",
    "gn:population":0,
    "gn:timezone":"Asia/Shanghai",
    "iso:country":"CN",
    "name:und_x_variant":[
        "Qianjia"
    ],
    "name:zho_x_preferred":[
        "\u94b1\u5bb6\u6751"
    ],
    "name:zho_x_variant":[
        "\u94b1\u5bb6"
    ],
    "wof:name":"Qianjiacun",
    "wof:placetype":"locality"
},
  "geometry": {"coordinates":[117.23921,37.14313],"type":"Point"}
}