{
  "type": "Feature",
  "properties": {
    "gn:admin1_code":"8.0",
    "gn:asciiname":"Baoquanling Sanshisandui",
    "gn:country_code":"CN",
    "gn:dem":82,
    "gn:feature_class":"P",
    "gn:feature_code":"PPLF",
    "gn:name":"Baoquanling Sanshisandui",
    "gn:population":0,
    "gn:timezone":"Asia/Shanghai",
    "iso:country":"CN",
    "name:zho_x_preferred":[
        "\u5b9d\u6cc9\u5cad\u4e09\u5341\u4e09\u961f"
    ],
    "wof:name":"Baoquanling Sanshisandui",
    "wof:placetype":"locality"
},
  "geometry": {"coordinates":[130.57013999999998,47.34423],"type":"Point"}
}