{
  "type": "Feature",
  "properties": {
    "gn:admin1_code":"12.0",
    "gn:asciiname":"Zongyangdun",
    "gn:country_code":"CN",
    "gn:dem":1842,
    "gn:feature_class":"P",
    "gn:feature_code":"PPL",
    "gn:name":"Zongyangdun",
    "gn:population":0,
    "gn:timezone":"Asia/Shanghai",
    "iso:country":"CN",
    "name:zho_x_preferred":[
        "\u9b03\u7f8a\u58a9"
    ],
    "wof:name":"Zongyangdun",
    "wof:placetype":"locality"
},
  "geometry": {"coordinates":[110.71872999999999,30.29306],"type":"Point"}
}