{
  "type": "Feature",
  "properties": {
    "gn:admin1_code":"25",
    "gn:asciiname":"Liujiahetuan",
    "gn:country_code":"CN",
    "gn:dem":103,
    "gn:feature_class":"P",
    "gn:feature_code":"PPL",
    "gn:name":"Liujiahetuan",
    "gn:population":0,
    "gn:timezone":"Asia/Shanghai",
    "iso:country":"CN",
    "name:zho_x_preferred":[
        "\u5218\u5bb6\u6cb3\u7583"
    ],
    "wof:name":"Liujiahetuan",
    "wof:placetype":"locality"
},
  "geometry": {"coordinates":[118.33,35.381],"type":"Point"}
}