{
  "type": "Feature",
  "properties": {
    "gn:admin1_code":"30.0",
    "gn:asciiname":"Zuokeng",
    "gn:country_code":"CN",
    "gn:dem":320,
    "gn:feature_class":"P",
    "gn:feature_code":"PPL",
    "gn:name":"Zuokeng",
    "gn:population":0,
    "gn:timezone":"Asia/Shanghai",
    "iso:country":"CN",
    "name:zho_x_preferred":[
        "Zuokeng"
    ],
    "name:zho_x_variant":[
        "\u5de6\u5751"
    ],
    "wof:name":"Zuokeng",
    "wof:placetype":"locality"
},
  "geometry": {"coordinates":[113.66889,25.21417000000001],"type":"Point"}
}