{
  "type": "Feature",
  "properties": {
    "gn:admin1_code":"19.0",
    "gn:asciiname":"Houniangniangmiao",
    "gn:country_code":"CN",
    "gn:dem":14,
    "gn:feature_class":"P",
    "gn:feature_code":"PPL",
    "gn:name":"Houniangniangmiao",
    "gn:population":0,
    "gn:timezone":"Asia/Shanghai",
    "iso:country":"CN",
    "name:zho_x_preferred":[
        "\u540e\u5a18\u5a18\u5e99"
    ],
    "wof:name":"Houniangniangmiao",
    "wof:placetype":"locality"
},
  "geometry": {"coordinates":[121.66800000000001,39.8991],"type":"Point"}
}