{
  "type": "Feature",
  "properties": {
    "gn:admin1_code":"11",
    "gn:asciiname":"Huaiqiling",
    "gn:country_code":"CN",
    "gn:dem":76,
    "gn:feature_class":"P",
    "gn:feature_code":"PPL",
    "gn:name":"Huaiqiling",
    "gn:population":0,
    "gn:timezone":"Asia/Shanghai",
    "iso:country":"CN",
    "name:zho_x_preferred":[
        "\u69d0\u5947\u5cad"
    ],
    "wof:name":"Huaiqiling",
    "wof:placetype":"locality"
},
  "geometry": {"coordinates":[112.46419,28.39092],"type":"Point"}
}