{
  "type": "Feature",
  "properties": {
    "gn:admin1_code":"30.0",
    "gn:asciiname":"Pingtou",
    "gn:country_code":"CN",
    "gn:dem":471,
    "gn:feature_class":"P",
    "gn:feature_code":"PPL",
    "gn:name":"Pingtou",
    "gn:population":0,
    "gn:timezone":"Asia/Shanghai",
    "iso:country":"CN",
    "name:zho_x_preferred":[
        "Pingtou"
    ],
    "name:zho_x_variant":[
        "\u576a\u5934"
    ],
    "wof:name":"Pingtou",
    "wof:placetype":"locality"
},
  "geometry": {"coordinates":[112.05638999999999,24.69056],"type":"Point"}
}