{
  "type": "Feature",
  "properties": {
    "gn:admin1_code":"8.0",
    "gn:asciiname":"Shuguang Sidui",
    "gn:country_code":"CN",
    "gn:dem":147,
    "gn:feature_class":"P",
    "gn:feature_code":"PPLF",
    "gn:name":"Shuguang Sidui",
    "gn:population":0,
    "gn:timezone":"Asia/Shanghai",
    "iso:country":"CN",
    "name:zho_x_preferred":[
        "\u66d9\u5149\u56db\u961f"
    ],
    "wof:name":"Shuguang Sidui",
    "wof:placetype":"locality"
},
  "geometry": {"coordinates":[123.98287000000001,47.40643],"type":"Point"}
}