{
  "type": "Feature",
  "properties": {
    "gn:admin1_code":"29.0",
    "gn:asciiname":"Layueqing",
    "gn:country_code":"CN",
    "gn:dem":1898,
    "gn:feature_class":"P",
    "gn:feature_code":"PPL",
    "gn:name":"Layueqing",
    "gn:population":0,
    "gn:timezone":"Asia/Shanghai",
    "iso:country":"CN",
    "name:zho_x_preferred":[
        "\u814a\u6708\u7b90"
    ],
    "wof:name":"Layueqing",
    "wof:placetype":"locality"
},
  "geometry": {"coordinates":[102.566,25.2662],"type":"Point"}
}