{
  "type": "Feature",
  "properties": {
    "gn:admin1_code":"7",
    "gn:asciiname":"Xiban",
    "gn:country_code":"CN",
    "gn:dem":23,
    "gn:feature_class":"P",
    "gn:feature_code":"PPL",
    "gn:name":"Xiban",
    "gn:population":0,
    "gn:timezone":"Asia/Shanghai",
    "iso:country":"CN",
    "name:und_x_variant":[
        "\u897f\u5742",
        "Xiban"
    ],
    "wof:name":"Xiban",
    "wof:placetype":"locality"
},
  "geometry": {"coordinates":[118.36718,24.75146],"type":"Point"}
}