{
  "type": "Feature",
  "properties": {
    "gn:admin1_code":"4.0",
    "gn:asciiname":"Xitaiyang",
    "gn:country_code":"CN",
    "gn:dem":33,
    "gn:feature_class":"P",
    "gn:feature_code":"PPL",
    "gn:name":"Xitaiyang",
    "gn:population":0,
    "gn:timezone":"Asia/Shanghai",
    "iso:country":"CN",
    "name:zho_x_preferred":[
        "\u897f\u592a\u9633"
    ],
    "wof:name":"Xitaiyang",
    "wof:placetype":"locality"
},
  "geometry": {"coordinates":[119.26792,31.80205],"type":"Point"}
}