{
  "type": "Feature",
  "properties": {
    "gn:admin1_code":"24.0",
    "gn:asciiname":"Sanyizhuang",
    "gn:country_code":"CN",
    "gn:dem":1553,
    "gn:feature_class":"P",
    "gn:feature_code":"PPL",
    "gn:name":"Sanyizhuang",
    "gn:population":0,
    "gn:timezone":"Asia/Shanghai",
    "iso:country":"CN",
    "name:zho_x_preferred":[
        "\u4e09\u4e49\u5e84"
    ],
    "wof:name":"Sanyizhuang",
    "wof:placetype":"locality"
},
  "geometry": {"coordinates":[111.4524,38.76404],"type":"Point"}
}