{
  "type": "Feature",
  "properties": {
    "gn:admin1_code":"10",
    "gn:asciiname":"Houliangmianjing",
    "gn:country_code":"CN",
    "gn:dem":1441,
    "gn:feature_class":"P",
    "gn:feature_code":"PPL",
    "gn:name":"Houliangmianjing",
    "gn:population":0,
    "gn:timezone":"Asia/Shanghai",
    "iso:country":"CN",
    "name:zho_x_preferred":[
        "\u540e\u4e24\u9762\u4e95"
    ],
    "wof:name":"Houliangmianjing",
    "wof:placetype":"locality"
},
  "geometry": {"coordinates":[114.74051,41.64845],"type":"Point"}
}