{
  "type": "Feature",
  "properties": {
    "gn:admin1_code":"30",
    "gn:asciiname":"Potouqiao",
    "gn:country_code":"CN",
    "gn:dem":28,
    "gn:feature_class":"P",
    "gn:feature_code":"PPL",
    "gn:name":"Potouqiao",
    "gn:population":0,
    "gn:timezone":"Asia/Urumqi",
    "iso:country":"CN",
    "name:zho_x_preferred":[
        "\u5761\u5934\u6865"
    ],
    "wof:name":"Potouqiao",
    "wof:placetype":"locality"
},
  "geometry": {"coordinates":[110.00899,21.21331],"type":"Point"}
}