{
  "type": "Feature",
  "properties": {
    "gn:admin1_code":"25",
    "gn:asciiname":"Dongniujiazhuang",
    "gn:country_code":"CN",
    "gn:dem":260,
    "gn:feature_class":"P",
    "gn:feature_code":"PPL",
    "gn:name":"Dongniujiazhuang",
    "gn:population":0,
    "gn:timezone":"Asia/Shanghai",
    "iso:country":"CN",
    "name:zho_x_preferred":[
        "\u4e1c\u725b\u5bb6\u5e84"
    ],
    "wof:name":"Dongniujiazhuang",
    "wof:placetype":"locality"
},
  "geometry": {"coordinates":[117.694,35.7851],"type":"Point"}
}