{
  "type": "Feature",
  "properties": {
    "gn:admin1_code":"12.0",
    "gn:asciiname":"Huajiatai",
    "gn:country_code":"CN",
    "gn:dem":22,
    "gn:feature_class":"P",
    "gn:feature_code":"PPL",
    "gn:name":"Huajiatai",
    "gn:population":0,
    "gn:timezone":"Asia/Shanghai",
    "iso:country":"CN",
    "name:und_x_variant":[
        "\u534e\u5bb6\u62ac"
    ],
    "wof:name":"Huajiatai",
    "wof:placetype":"locality"
},
  "geometry": {"coordinates":[114.01164,30.5355],"type":"Point"}
}