{
  "type": "Feature",
  "properties": {
    "gn:admin1_code":"1.0",
    "gn:asciiname":"Fangdiancun",
    "gn:country_code":"CN",
    "gn:dem":31,
    "gn:feature_class":"P",
    "gn:feature_code":"PPL",
    "gn:name":"Fangdiancun",
    "gn:population":0,
    "gn:timezone":"Asia/Shanghai",
    "iso:country":"CN",
    "name:zho_x_preferred":[
        "\u65b9\u5e97\u6751"
    ],
    "wof:name":"Fangdiancun",
    "wof:placetype":"locality"
},
  "geometry": {"coordinates":[117.28005,31.28246],"type":"Point"}
}