{
  "type": "Feature",
  "properties": {
    "gn:admin1_code":"22.0",
    "gn:asciiname":"Jiezhouying",
    "gn:country_code":"CN",
    "gn:dem":26,
    "gn:feature_class":"P",
    "gn:feature_code":"PPL",
    "gn:name":"Jiezhouying",
    "gn:population":0,
    "gn:timezone":"Asia/Shanghai",
    "iso:country":"CN",
    "name:zho_x_preferred":[
        "\u89e3\u5dde\u8425"
    ],
    "wof:name":"Jiezhouying",
    "wof:placetype":"locality"
},
  "geometry": {"coordinates":[116.55289,39.68921],"type":"Point"}
}