{
  "type": "Feature",
  "properties": {
    "gn:admin1_code":"9",
    "gn:asciiname":"Shihuangji",
    "gn:country_code":"CN",
    "gn:dem":48,
    "gn:feature_class":"P",
    "gn:feature_code":"PPL",
    "gn:name":"Shihuangji",
    "gn:population":0,
    "gn:timezone":"Asia/Shanghai",
    "iso:country":"CN",
    "name:zho_x_preferred":[
        "\u67ff\u9ec4\u96c6"
    ],
    "wof:name":"Shihuangji",
    "wof:placetype":"locality"
},
  "geometry": {"coordinates":[115.42700000000001,34.06],"type":"Point"}
}