{
  "type": "Feature",
  "properties": {
    "gn:admin1_code":"9.0",
    "gn:asciiname":"Shaozhuang",
    "gn:country_code":"CN",
    "gn:dem":58,
    "gn:feature_class":"P",
    "gn:feature_code":"PPL",
    "gn:name":"Shaozhuang",
    "gn:population":0,
    "gn:timezone":"Asia/Shanghai",
    "iso:country":"CN",
    "name:zho_x_preferred":[
        "\u90b5\u5e84"
    ],
    "wof:name":"Shaozhuang",
    "wof:placetype":"locality"
},
  "geometry": {"coordinates":[114.22499999999999,33.59416],"type":"Point"}
}