{
  "type": "Feature",
  "properties": {
    "gn:admin1_code":"24.0",
    "gn:asciiname":"Zhanglukou",
    "gn:country_code":"CN",
    "gn:dem":993,
    "gn:feature_class":"P",
    "gn:feature_code":"PPL",
    "gn:name":"Zhanglukou",
    "gn:population":0,
    "gn:timezone":"Asia/Shanghai",
    "iso:country":"CN",
    "name:und_x_variant":[
        "Chang-lu-k\u2019ou",
        "Zhanglukou"
    ],
    "name:zho_x_preferred":[
        "\u5f20\u8def\u53e3"
    ],
    "wof:name":"Zhanglukou",
    "wof:placetype":"locality"
},
  "geometry": {"coordinates":[113.06632,35.35759],"type":"Point"}
}