{
  "type": "Feature",
  "properties": {
    "gn:admin1_code":"9.0",
    "gn:asciiname":"Liangjiagou",
    "gn:country_code":"CN",
    "gn:dem":307,
    "gn:feature_class":"P",
    "gn:feature_code":"PPL",
    "gn:name":"Liangjiagou",
    "gn:population":0,
    "gn:timezone":"Asia/Shanghai",
    "iso:country":"CN",
    "name:zho_x_preferred":[
        "\u6881\u5bb6\u6c9f"
    ],
    "wof:name":"Liangjiagou",
    "wof:placetype":"locality"
},
  "geometry": {"coordinates":[111.7547,33.2812],"type":"Point"}
}