{
  "type": "Feature",
  "properties": {
    "gn:admin1_code":"02",
    "gn:asciiname":"Da'ao",
    "gn:country_code":"CN",
    "gn:dem":6,
    "gn:feature_class":"P",
    "gn:feature_code":"PPL",
    "gn:name":"Da\u2019ao",
    "gn:population":0,
    "gn:timezone":"Asia/Shanghai",
    "iso:country":"CN",
    "name:zho_x_preferred":[
        "\u5927\u5c99"
    ],
    "name:zho_x_variant":[
        "Da\u2019ao"
    ],
    "wof:name":"Da'ao",
    "wof:placetype":"locality"
},
  "geometry": {"coordinates":[121.59101,28.94652],"type":"Point"}
}