{
  "type": "Feature",
  "properties": {
    "gn:admin1_code":"5.0",
    "gn:asciiname":"Pingfangtun",
    "gn:country_code":"CN",
    "gn:dem":252,
    "gn:feature_class":"P",
    "gn:feature_code":"PPL",
    "gn:name":"Pingfangtun",
    "gn:population":0,
    "gn:timezone":"Asia/Shanghai",
    "iso:country":"CN",
    "name:zho_x_preferred":[
        "\u5e73\u623f\u5c6f"
    ],
    "wof:name":"Pingfangtun",
    "wof:placetype":"locality"
},
  "geometry": {"coordinates":[124.5658,43.15085],"type":"Point"}
}