{
  "type": "Feature",
  "properties": {
    "gn:admin1_code":"30",
    "gn:asciiname":"Shuitoukeng",
    "gn:country_code":"CN",
    "gn:dem":110,
    "gn:feature_class":"P",
    "gn:feature_code":"PPL",
    "gn:name":"Shuitoukeng",
    "gn:population":0,
    "gn:timezone":"Asia/Urumqi",
    "iso:country":"CN",
    "name:zho_x_preferred":[
        "\u6c34\u5934\u5751"
    ],
    "wof:name":"Shuitoukeng",
    "wof:placetype":"locality"
},
  "geometry": {"coordinates":[111.05215,22.0934],"type":"Point"}
}