{
  "type": "Feature",
  "properties": {
    "gn:admin1_code":"19.0",
    "gn:asciiname":"Laoheshen",
    "gn:country_code":"CN",
    "gn:dem":72,
    "gn:feature_class":"P",
    "gn:feature_code":"PPL",
    "gn:name":"Laoheshen",
    "gn:population":0,
    "gn:timezone":"Asia/Shanghai",
    "iso:country":"CN",
    "name:und_x_variant":[
        "\u8001\u6cb3\u6df1"
    ],
    "name:zho_x_preferred":[
        "\u8001\u6cb3\u6df1"
    ],
    "wof:name":"Laoheshen",
    "wof:placetype":"locality"
},
  "geometry": {"coordinates":[122.01734,41.88149],"type":"Point"}
}