{
  "type": "Feature",
  "properties": {
    "gn:admin1_code":"32.0",
    "gn:asciiname":"Zhongzi",
    "gn:country_code":"CN",
    "gn:dem":2505,
    "gn:feature_class":"P",
    "gn:feature_code":"PPL",
    "gn:name":"Zhongzi",
    "gn:population":0,
    "gn:timezone":"Asia/Shanghai",
    "iso:country":"CN",
    "name:zho_x_preferred":[
        "\u4ef2\u5b50"
    ],
    "wof:name":"Zhongzi",
    "wof:placetype":"locality"
},
  "geometry": {"coordinates":[103.089,27.785],"type":"Point"}
}