{
  "type": "Feature",
  "properties": {
    "gn:admin1_code":"19.0",
    "gn:asciiname":"Xutuncun",
    "gn:country_code":"CN",
    "gn:dem":69,
    "gn:feature_class":"P",
    "gn:feature_code":"PPL",
    "gn:name":"Xutuncun",
    "gn:population":0,
    "gn:timezone":"Asia/Shanghai",
    "iso:country":"CN",
    "name:zho_x_preferred":[
        "\u5f90\u5c6f\u6751"
    ],
    "wof:name":"Xutuncun",
    "wof:placetype":"locality"
},
  "geometry": {"coordinates":[122.039,39.6708],"type":"Point"}
}