{
  "type": "Feature",
  "properties": {
    "gn:admin1_code":"3",
    "gn:asciiname":"Lingzishang",
    "gn:country_code":"CN",
    "gn:dem":222,
    "gn:feature_class":"P",
    "gn:feature_code":"PPL",
    "gn:name":"Lingzishang",
    "gn:population":0,
    "gn:timezone":"Asia/Shanghai",
    "iso:country":"CN",
    "name:zho_x_preferred":[
        "\u5cad\u5b5c\u4e0a"
    ],
    "wof:name":"Lingzishang",
    "wof:placetype":"locality"
},
  "geometry": {"coordinates":[114.80200000000001,25.4954],"type":"Point"}
}