{
  "type": "Feature",
  "properties": {
    "gn:admin1_code":"02",
    "gn:asciiname":"Hengfan",
    "gn:country_code":"CN",
    "gn:dem":46,
    "gn:feature_class":"P",
    "gn:feature_code":"PPLA4",
    "gn:name":"Hengfan",
    "gn:population":0,
    "gn:timezone":"Asia/Shanghai",
    "iso:country":"CN",
    "name:und_x_variant":[
        "Hueng-pan",
        "Hengpan",
        "Heng-fan-chen",
        "Hengfan",
        "\u6a2a\u7548"
    ],
    "wof:name":"Hengfan",
    "wof:placetype":"locality"
},
  "geometry": {"coordinates":[119.75123000000001,30.33074],"type":"Point"}
}