{
  "type": "Feature",
  "properties": {
    "gn:admin1_code":"04",
    "gn:asciiname":"Xinqiaocun",
    "gn:country_code":"CN",
    "gn:dem":4,
    "gn:feature_class":"P",
    "gn:feature_code":"PPL",
    "gn:name":"Xinqiaocun",
    "gn:population":0,
    "gn:timezone":"Asia/Shanghai",
    "iso:country":"CN",
    "name:und_x_variant":[
        "Hsin-ch\u2019iao-chen",
        "Xinqiaozhen",
        "Xinqiao",
        "\u65b0\u6865",
        "\u65b0\u6865\u9547",
        "Xinqiaocun"
    ],
    "name:zho_x_preferred":[
        "\u65b0\u6865\u6751"
    ],
    "wof:name":"Xinqiaocun",
    "wof:placetype":"locality"
},
  "geometry": {"coordinates":[121.51593,31.88733],"type":"Point"}
}