{
  "type": "Feature",
  "properties": {
    "gn:admin1_code":"12",
    "gn:asciiname":"Ditianqiao",
    "gn:country_code":"CN",
    "gn:dem":33,
    "gn:feature_class":"P",
    "gn:feature_code":"PPL",
    "gn:name":"Ditianqiao",
    "gn:population":0,
    "gn:timezone":"Asia/Shanghai",
    "iso:country":"CN",
    "name:und_x_variant":[
        "\u837b\u7530\u6865"
    ],
    "wof:name":"Ditianqiao",
    "wof:placetype":"locality"
},
  "geometry": {"coordinates":[115.13002,29.86966],"type":"Point"}
}