{
  "type": "Feature",
  "properties": {
    "gn:admin1_code":"8.0",
    "gn:asciiname":"Guchengdian",
    "gn:country_code":"CN",
    "gn:dem":170,
    "gn:feature_class":"P",
    "gn:feature_code":"PPL",
    "gn:name":"Guchengdian",
    "gn:population":0,
    "gn:timezone":"Asia/Shanghai",
    "iso:country":"CN",
    "name:zho_x_preferred":[
        "\u53e4\u57ce\u5e97"
    ],
    "wof:name":"Guchengdian",
    "wof:placetype":"locality"
},
  "geometry": {"coordinates":[126.94243,45.35784],"type":"Point"}
}