{
  "type": "Feature",
  "properties": {
    "gn:admin1_code":"07",
    "gn:asciiname":"Changkengtian",
    "gn:country_code":"CN",
    "gn:dem":1039,
    "gn:feature_class":"P",
    "gn:feature_code":"PPL",
    "gn:name":"Changkengtian",
    "gn:population":0,
    "gn:timezone":"Asia/Shanghai",
    "iso:country":"CN",
    "name:zho_x_preferred":[
        "\u957f\u5751\u7530"
    ],
    "wof:name":"Changkengtian",
    "wof:placetype":"locality"
},
  "geometry": {"coordinates":[117.08634000000001,25.30649],"type":"Point"}
}