{
  "type": "Feature",
  "properties": {
    "gn:admin1_code":"12.0",
    "gn:asciiname":"Songlingang",
    "gn:country_code":"CN",
    "gn:dem":68,
    "gn:feature_class":"P",
    "gn:feature_code":"PPL",
    "gn:name":"Songlingang",
    "gn:population":0,
    "gn:timezone":"Asia/Shanghai",
    "iso:country":"CN",
    "name:zho_x_preferred":[
        "\u677e\u6797\u5c97"
    ],
    "wof:name":"Songlingang",
    "wof:placetype":"locality"
},
  "geometry": {"coordinates":[113.47472999999999,30.98147],"type":"Point"}
}