{
  "type": "Feature",
  "properties": {
    "gn:admin1_code":"7.0",
    "gn:asciiname":"Xiakengyuan",
    "gn:country_code":"CN",
    "gn:dem":436,
    "gn:feature_class":"P",
    "gn:feature_code":"PPL",
    "gn:name":"Xiakengyuan",
    "gn:population":0,
    "gn:timezone":"Asia/Shanghai",
    "iso:country":"CN",
    "name:und_x_variant":[
        "\u4e0b\u5751\u6e90"
    ],
    "name:zho_x_preferred":[
        "\u4e0b\u5751\u6e90"
    ],
    "wof:name":"Xiakengyuan",
    "wof:placetype":"locality"
},
  "geometry": {"coordinates":[117.61488,26.38129],"type":"Point"}
}