{
  "type": "Feature",
  "properties": {
    "gn:admin1_code":"29.0",
    "gn:asciiname":"Xiushan",
    "gn:country_code":"CN",
    "gn:dem":1829,
    "gn:feature_class":"P",
    "gn:feature_code":"PPLA3",
    "gn:name":"Xiushan",
    "gn:population":0,
    "gn:timezone":"Asia/Shanghai",
    "iso:country":"CN",
    "name:und_x_variant":[
        "Tonghai",
        "Tonghai Xian",
        "Xiushan Zhen",
        "\u79c0\u5c71\u9547",
        "Xiushan"
    ],
    "name:zho_x_preferred":[
        "T\u2019ung-hai-hsien"
    ],
    "name:zho_x_variant":[
        "Ch\u2019i-lu",
        "T\u2019ung-hai",
        "\u79c0\u5c71",
        "\u901a\u6d77\u53bf"
    ],
    "wof:name":"Xiushan",
    "wof:placetype":"locality"
},
  "geometry": {"coordinates":[102.76152999999999,24.10999],"type":"Point"}
}