{
  "type": "Feature",
  "properties": {
    "gn:admin1_code":"19.0",
    "gn:asciiname":"Caituncun",
    "gn:country_code":"CN",
    "gn:dem":28,
    "gn:feature_class":"P",
    "gn:feature_code":"PPL",
    "gn:name":"Caituncun",
    "gn:population":0,
    "gn:timezone":"Asia/Shanghai",
    "iso:country":"CN",
    "name:zho_x_preferred":[
        "\u8521\u5c6f\u6751"
    ],
    "wof:name":"Caituncun",
    "wof:placetype":"locality"
},
  "geometry": {"coordinates":[122.358,39.5875],"type":"Point"}
}