{
  "type": "Feature",
  "properties": {
    "gn:admin1_code":"18",
    "gn:asciiname":"Chagou",
    "gn:country_code":"CN",
    "gn:dem":971,
    "gn:feature_class":"P",
    "gn:feature_code":"PPL",
    "gn:name":"Chagou",
    "gn:population":0,
    "gn:timezone":"Asia/Shanghai",
    "iso:country":"CN",
    "name:zho_x_preferred":[
        "\u8336\u6c9f"
    ],
    "wof:name":"Chagou",
    "wof:placetype":"locality"
},
  "geometry": {"coordinates":[107.68000000000001,28.9568],"type":"Point"}
}