{
  "type": "Feature",
  "properties": {
    "gn:admin1_code":"11.0",
    "gn:asciiname":"Shunlinyi",
    "gn:country_code":"CN",
    "gn:dem":37,
    "gn:feature_class":"P",
    "gn:feature_code":"PPL",
    "gn:name":"Shunlinyi",
    "gn:population":0,
    "gn:timezone":"Asia/Shanghai",
    "iso:country":"CN",
    "name:zho_x_preferred":[
        "Shunlinyi"
    ],
    "name:zho_x_variant":[
        "\u987a\u6797\u9a7f"
    ],
    "wof:name":"Shunlinyi",
    "wof:placetype":"locality"
},
  "geometry": {"coordinates":[111.88424000000001,29.76737],"type":"Point"}
}