{
  "type": "Feature",
  "properties": {
    "gn:admin1_code":"07",
    "gn:asciiname":"Jieshang",
    "gn:country_code":"CN",
    "gn:dem":336,
    "gn:feature_class":"P",
    "gn:feature_code":"PPL",
    "gn:name":"Jieshang",
    "gn:population":0,
    "gn:timezone":"Asia/Shanghai",
    "iso:country":"CN",
    "name:zho_x_preferred":[
        "\u8857\u4e0a"
    ],
    "wof:name":"Jieshang",
    "wof:placetype":"locality"
},
  "geometry": {"coordinates":[116.24545999999999,24.99117],"type":"Point"}
}