{
  "type": "Feature",
  "properties": {
    "gn:admin1_code":"19.0",
    "gn:asciiname":"Shijiang Wopeng",
    "gn:country_code":"CN",
    "gn:dem":85,
    "gn:feature_class":"P",
    "gn:feature_code":"PPL",
    "gn:name":"Shijiang Wopeng",
    "gn:population":0,
    "gn:timezone":"Asia/Shanghai",
    "iso:country":"CN",
    "name:zho_x_preferred":[
        "\u77f3\u5320\u7a9d\u68da"
    ],
    "wof:name":"Shijiang Wopeng",
    "wof:placetype":"locality"
},
  "geometry": {"coordinates":[122.39,39.7009],"type":"Point"}
}