{
  "type": "Feature",
  "properties": {
    "gn:admin1_code":"11.0",
    "gn:asciiname":"Jianche",
    "gn:country_code":"CN",
    "gn:dem":166,
    "gn:feature_class":"P",
    "gn:feature_code":"PPL",
    "gn:name":"Jianche",
    "gn:population":0,
    "gn:timezone":"Asia/Shanghai",
    "iso:country":"CN",
    "name:zho_x_preferred":[
        "\u7b80\u8f66"
    ],
    "wof:name":"Jianche",
    "wof:placetype":"locality"
},
  "geometry": {"coordinates":[110.42553999999998,28.2699],"type":"Point"}
}