{
  "type": "Feature",
  "properties": {
    "gn:admin1_code":"19.0",
    "gn:asciiname":"Baijiakouzi",
    "gn:country_code":"CN",
    "gn:dem":5,
    "gn:feature_class":"P",
    "gn:feature_code":"PPL",
    "gn:name":"Baijiakouzi",
    "gn:population":0,
    "gn:timezone":"Asia/Shanghai",
    "iso:country":"CN",
    "name:zho_x_preferred":[
        "\u767d\u5bb6\u53e3\u5b50"
    ],
    "wof:name":"Baijiakouzi",
    "wof:placetype":"locality"
},
  "geometry": {"coordinates":[121.66,39.4379],"type":"Point"}
}