{
  "type": "Feature",
  "properties": {
    "gn:admin1_code":"29.0",
    "gn:asciiname":"Nanlang",
    "gn:country_code":"CN",
    "gn:dem":1592,
    "gn:feature_class":"P",
    "gn:feature_code":"PPL",
    "gn:name":"Nanlang",
    "gn:population":0,
    "gn:timezone":"Asia/Shanghai",
    "iso:country":"CN",
    "name:fas_x_preferred":[
        "\u0646\u0627\u0646\u0644\u0627\u0646\u06af"
    ],
    "name:mlg_x_preferred":[
        "Nanlang"
    ],
    "name:nld_x_preferred":[
        "Nanlang"
    ],
    "name:swe_x_preferred":[
        "Nanlang"
    ],
    "name:zho_x_preferred":[
        "\u5357\u6994"
    ],
    "name:zho_x_variant":[
        "\u5357\u6717\u9547"
    ],
    "wof:name":"Nanlang",
    "wof:placetype":"locality"
},
  "geometry": {"coordinates":[99.8409,23.3025],"type":"Point"}
}