{
  "type": "Feature",
  "properties": {
    "gn:admin1_code":"16.0",
    "gn:asciiname":"Xingengyang",
    "gn:country_code":"CN",
    "gn:dem":117,
    "gn:feature_class":"P",
    "gn:feature_code":"PPL",
    "gn:name":"Xingengyang",
    "gn:population":0,
    "gn:timezone":"Asia/Shanghai",
    "iso:country":"CN",
    "name:zho_x_preferred":[
        "\u65b0\u66f4\u6768"
    ],
    "wof:name":"Xingengyang",
    "wof:placetype":"locality"
},
  "geometry": {"coordinates":[107.91800000000001,22.4747],"type":"Point"}
}