{
  "type": "Feature",
  "properties": {
    "gn:admin1_code":"18",
    "gn:asciiname":"Chaoyangba",
    "gn:country_code":"CN",
    "gn:dem":1310,
    "gn:feature_class":"P",
    "gn:feature_code":"PPL",
    "gn:name":"Chaoyangba",
    "gn:population":0,
    "gn:timezone":"Asia/Shanghai",
    "iso:country":"CN",
    "name:zho_x_preferred":[
        "\u671d\u9633\u575d"
    ],
    "wof:name":"Chaoyangba",
    "wof:placetype":"locality"
},
  "geometry": {"coordinates":[106.071,27.1516],"type":"Point"}
}