{
  "type": "Feature",
  "properties": {
    "gn:admin1_code":"20",
    "gn:asciiname":"P'ang-chia-ying-tzu",
    "gn:country_code":"CN",
    "gn:dem":687,
    "gn:feature_class":"P",
    "gn:feature_code":"PPL",
    "gn:name":"P\u2019ang-chia-ying-tzu",
    "gn:population":0,
    "gn:timezone":"Asia/Shanghai",
    "iso:country":"CN",
    "wof:name":"P'ang-chia-ying-tzu",
    "wof:placetype":"locality"
},
  "geometry": {"coordinates":[118.84528,42.48639],"type":"Point"}
}