{
  "type": "Feature",
  "properties": {
    "gn:admin1_code":"11",
    "gn:asciiname":"Daoguajingou",
    "gn:country_code":"CN",
    "gn:dem":108,
    "gn:feature_class":"P",
    "gn:feature_code":"PPL",
    "gn:name":"Daoguajingou",
    "gn:population":0,
    "gn:timezone":"Asia/Shanghai",
    "iso:country":"CN",
    "name:zho_x_preferred":[
        "\u5012\u6302\u91d1\u94a9"
    ],
    "wof:name":"Daoguajingou",
    "wof:placetype":"locality"
},
  "geometry": {"coordinates":[112.47931,27.60805],"type":"Point"}
}