{
  "type": "Feature",
  "properties": {
    "gn:admin1_code":"26.0",
    "gn:asciiname":"Jidanmaocun",
    "gn:country_code":"CN",
    "gn:dem":1221,
    "gn:feature_class":"P",
    "gn:feature_code":"PPL",
    "gn:name":"Jidanmaocun",
    "gn:population":0,
    "gn:timezone":"Asia/Shanghai",
    "iso:country":"CN",
    "name:zho_x_preferred":[
        "\u9e21\u86cb\u5cc1\u6751"
    ],
    "wof:name":"Jidanmaocun",
    "wof:placetype":"locality"
},
  "geometry": {"coordinates":[109.53852999999999,36.51223],"type":"Point"}
}