{
  "type": "Feature",
  "properties": {
    "gn:admin1_code":"18.0",
    "gn:asciiname":"Lidong",
    "gn:country_code":"CN",
    "gn:dem":739,
    "gn:feature_class":"P",
    "gn:feature_code":"PPL",
    "gn:name":"Lidong",
    "gn:population":0,
    "gn:timezone":"Asia/Shanghai",
    "iso:country":"CN",
    "name:afr_x_preferred":[
        "Lidong"
    ],
    "name:cdo_x_preferred":[
        "L\u012dk-d\u0115\u0324ng"
    ],
    "name:hak_x_preferred":[
        "Li\u030dp-t\u00fbng"
    ],
    "name:swe_x_preferred":[
        "Lidong"
    ],
    "name:vie_x_preferred":[
        "L\u1eadp \u0111\u00f4ng"
    ],
    "name:zha_x_preferred":[
        "Laebdoeng"
    ],
    "name:zho_x_preferred":[
        "\u5229\u6d1e"
    ],
    "wof:name":"Lidong",
    "wof:placetype":"locality"
},
  "geometry": {"coordinates":[108.63800000000001,26.0412],"type":"Point"}
}