{
  "type": "Feature",
  "properties": {
    "gn:admin1_code":"32.0",
    "gn:asciiname":"Wangdian",
    "gn:country_code":"CN",
    "gn:dem":589,
    "gn:feature_class":"P",
    "gn:feature_code":"PPL",
    "gn:name":"Wangdian",
    "gn:population":0,
    "gn:timezone":"Asia/Shanghai",
    "iso:country":"CN",
    "name:ceb_x_preferred":[
        "Wangdian"
    ],
    "name:swe_x_preferred":[
        "Wangdian"
    ],
    "name:zho_x_preferred":[
        "\u738b\u5e97"
    ],
    "wof:name":"Wangdian",
    "wof:placetype":"locality"
},
  "geometry": {"coordinates":[103.25612,30.27567],"type":"Point"}
}