{
  "type": "Feature",
  "properties": {
    "gn:admin1_code":"32.0",
    "gn:asciiname":"Heluo",
    "gn:country_code":"CN",
    "gn:dem":3325,
    "gn:feature_class":"P",
    "gn:feature_code":"PPL",
    "gn:name":"Heluo",
    "gn:population":0,
    "gn:timezone":"Asia/Shanghai",
    "iso:country":"CN",
    "name:zho_x_preferred":[
        "\u8d3a\u6d1b"
    ],
    "wof:name":"Heluo",
    "wof:placetype":"locality"
},
  "geometry": {"coordinates":[100.363,30.9393],"type":"Point"}
}