{
  "type": "Feature",
  "properties": {
    "gn:admin1_code":"7.0",
    "gn:asciiname":"Longxia",
    "gn:country_code":"CN",
    "gn:dem":373,
    "gn:feature_class":"P",
    "gn:feature_code":"PPL",
    "gn:name":"Longxia",
    "gn:population":0,
    "gn:timezone":"Asia/Shanghai",
    "iso:country":"CN",
    "name:und_x_variant":[
        "\u9686\u4e0b"
    ],
    "name:zho_x_preferred":[
        "\u9686\u4e0b"
    ],
    "wof:name":"Longxia",
    "wof:placetype":"locality"
},
  "geometry": {"coordinates":[116.77256,26.63577],"type":"Point"}
}