{
  "type": "Feature",
  "properties": {
    "gn:admin1_code":"6.0",
    "gn:asciiname":"Qianhu",
    "gn:country_code":"CN",
    "gn:dem":3063,
    "gn:feature_class":"P",
    "gn:feature_code":"PPL",
    "gn:name":"Qianhu",
    "gn:population":0,
    "gn:timezone":"Asia/Shanghai",
    "iso:country":"CN",
    "name:zho_x_preferred":[
        "\u5343\u6237"
    ],
    "wof:name":"Qianhu",
    "wof:placetype":"locality"
},
  "geometry": {"coordinates":[101.54228000000001,36.29506],"type":"Point"}
}