{
  "type": "Feature",
  "properties": {
    "gn:admin1_code":"11.0",
    "gn:asciiname":"Diaozitang",
    "gn:country_code":"CN",
    "gn:dem":58,
    "gn:feature_class":"P",
    "gn:feature_code":"PPL",
    "gn:name":"Diaozitang",
    "gn:population":0,
    "gn:timezone":"Asia/Shanghai",
    "iso:country":"CN",
    "name:zho_x_preferred":[
        "\u5201\u5b50\u5858"
    ],
    "wof:name":"Diaozitang",
    "wof:placetype":"locality"
},
  "geometry": {"coordinates":[112.7118,27.83766],"type":"Point"}
}