{
  "type": "Feature",
  "properties": {
    "gn:admin1_code":"02",
    "gn:asciiname":"Chenyangshan",
    "gn:country_code":"CN",
    "gn:dem":21,
    "gn:feature_class":"P",
    "gn:feature_code":"PPL",
    "gn:name":"Chenyangshan",
    "gn:population":0,
    "gn:timezone":"Asia/Shanghai",
    "iso:country":"CN",
    "name:zho_x_preferred":[
        "\u9648\u579f\u5c71"
    ],
    "wof:name":"Chenyangshan",
    "wof:placetype":"locality"
},
  "geometry": {"coordinates":[120.47999,28.03454],"type":"Point"}
}