{
  "type": "Feature",
  "properties": {
    "gn:admin1_code":"3.0",
    "gn:asciiname":"Dashanpai",
    "gn:country_code":"CN",
    "gn:dem":62,
    "gn:feature_class":"P",
    "gn:feature_code":"PPL",
    "gn:name":"Dashanpai",
    "gn:population":0,
    "gn:timezone":"Asia/Shanghai",
    "iso:country":"CN",
    "name:und_x_variant":[
        "\u5927\u5c71\u6392"
    ],
    "wof:name":"Dashanpai",
    "wof:placetype":"locality"
},
  "geometry": {"coordinates":[115.86481000000001,27.95685],"type":"Point"}
}