{
  "type": "Feature",
  "properties": {
    "gn:admin1_code":"30.0",
    "gn:asciiname":"Xiajiao",
    "gn:country_code":"CN",
    "gn:dem":43,
    "gn:feature_class":"P",
    "gn:feature_code":"PPL",
    "gn:name":"Xiajiao",
    "gn:population":0,
    "gn:timezone":"Asia/Shanghai",
    "iso:country":"CN",
    "name:zho_x_preferred":[
        "\u5413\u89d2"
    ],
    "wof:name":"Xiajiao",
    "wof:placetype":"locality"
},
  "geometry": {"coordinates":[114.2392,22.68863],"type":"Point"}
}