{
  "type": "Feature",
  "properties": {
    "gn:admin1_code":"25",
    "gn:asciiname":"Rendezhuang",
    "gn:country_code":"CN",
    "gn:dem":29,
    "gn:feature_class":"P",
    "gn:feature_code":"PPL",
    "gn:name":"Rendezhuang",
    "gn:population":0,
    "gn:timezone":"Asia/Shanghai",
    "iso:country":"CN",
    "name:zho_x_preferred":[
        "\u4ec1\u5fb7\u5e84"
    ],
    "wof:name":"Rendezhuang",
    "wof:placetype":"locality"
},
  "geometry": {"coordinates":[116.242,37.2319],"type":"Point"}
}