{
  "type": "Feature",
  "properties": {
    "gn:admin1_code":"19.0",
    "gn:asciiname":"Shanzui",
    "gn:country_code":"CN",
    "gn:dem":528,
    "gn:feature_class":"P",
    "gn:feature_code":"PPL",
    "gn:name":"Shanzui",
    "gn:population":0,
    "gn:timezone":"Asia/Shanghai",
    "iso:country":"CN",
    "name:und_x_variant":[
        "\u5c71\u5480"
    ],
    "name:zho_x_preferred":[
        "\u5c71\u5480"
    ],
    "wof:name":"Shanzui",
    "wof:placetype":"locality"
},
  "geometry": {"coordinates":[119.77893,41.49197],"type":"Point"}
}