{
  "type": "Feature",
  "properties": {
    "gn:admin1_code":"32.0",
    "gn:asciiname":"Tuogou",
    "gn:country_code":"CN",
    "gn:dem":2146,
    "gn:feature_class":"P",
    "gn:feature_code":"PPL",
    "gn:name":"Tuogou",
    "gn:population":0,
    "gn:timezone":"Asia/Shanghai",
    "iso:country":"CN",
    "name:zho_x_preferred":[
        "\u62d6\u6c9f"
    ],
    "wof:name":"Tuogou",
    "wof:placetype":"locality"
},
  "geometry": {"coordinates":[101.45699999999999,28.077],"type":"Point"}
}