{
  "type": "Feature",
  "properties": {
    "gn:admin1_code":"8.0",
    "gn:asciiname":"Shuangfubeitun",
    "gn:country_code":"CN",
    "gn:dem":169,
    "gn:feature_class":"P",
    "gn:feature_code":"PPL",
    "gn:name":"Shuangfubeitun",
    "gn:population":0,
    "gn:timezone":"Asia/Shanghai",
    "iso:country":"CN",
    "name:zho_x_preferred":[
        "\u53cc\u5bcc\u5317\u5c6f"
    ],
    "wof:name":"Shuangfubeitun",
    "wof:placetype":"locality"
},
  "geometry": {"coordinates":[131.20769000000001,46.66138],"type":"Point"}
}