{
  "type": "Feature",
  "properties": {
    "gn:admin1_code":"3",
    "gn:asciiname":"Dongli",
    "gn:country_code":"CN",
    "gn:dem":120,
    "gn:feature_class":"P",
    "gn:feature_code":"PPL",
    "gn:name":"Dongli",
    "gn:population":0,
    "gn:timezone":"Asia/Shanghai",
    "iso:country":"CN",
    "name:zho_x_preferred":[
        "\u4e1c\u91cc"
    ],
    "wof:name":"Dongli",
    "wof:placetype":"locality"
},
  "geometry": {"coordinates":[114.24918999999998,26.94972000000001],"type":"Point"}
}