{
  "type": "Feature",
  "properties": {
    "gn:admin1_code":"31.0",
    "gn:asciiname":"Pomatian",
    "gn:country_code":"CN",
    "gn:dem":162,
    "gn:feature_class":"P",
    "gn:feature_code":"PPL",
    "gn:name":"Pomatian",
    "gn:population":0,
    "gn:timezone":"Asia/Shanghai",
    "iso:country":"CN",
    "name:und_x_variant":[
        "\u5761\u9ebb\u7530"
    ],
    "wof:name":"Pomatian",
    "wof:placetype":"locality"
},
  "geometry": {"coordinates":[110.27902,18.97996],"type":"Point"}
}