{
  "type": "Feature",
  "properties": {
    "gn:admin1_code":"25",
    "gn:asciiname":"Yunshan",
    "gn:country_code":"CN",
    "gn:dem":306,
    "gn:feature_class":"P",
    "gn:feature_code":"PPL",
    "gn:name":"Yunshan",
    "gn:population":0,
    "gn:timezone":"Asia/Shanghai",
    "iso:country":"CN",
    "name:zho_x_preferred":[
        "\u4e91\u5c71"
    ],
    "wof:name":"Yunshan",
    "wof:placetype":"locality"
},
  "geometry": {"coordinates":[117.67100000000001,35.8405],"type":"Point"}
}