{
  "type": "Feature",
  "properties": {
    "gn:admin1_code":"31.0",
    "gn:asciiname":"Fengshoupo",
    "gn:country_code":"CN",
    "gn:dem":38,
    "gn:feature_class":"P",
    "gn:feature_code":"PPL",
    "gn:name":"Fengshoupo",
    "gn:population":0,
    "gn:timezone":"Asia/Shanghai",
    "iso:country":"CN",
    "name:zho_x_preferred":[
        "\u4e30\u6536\u5761"
    ],
    "wof:name":"Fengshoupo",
    "wof:placetype":"locality"
},
  "geometry": {"coordinates":[110.27759,18.90434],"type":"Point"}
}