{
  "type": "Feature",
  "properties": {
    "gn:admin1_code":"15.0",
    "gn:asciiname":"Hejiaba",
    "gn:country_code":"CN",
    "gn:dem":1528,
    "gn:feature_class":"P",
    "gn:feature_code":"PPL",
    "gn:name":"Hejiaba",
    "gn:population":0,
    "gn:timezone":"Asia/Shanghai",
    "iso:country":"CN",
    "name:und_x_variant":[
        "\u8d3a\u5bb6\u575d"
    ],
    "wof:name":"Hejiaba",
    "wof:placetype":"locality"
},
  "geometry": {"coordinates":[106.55531000000001,33.61832],"type":"Point"}
}