{
  "type": "Feature",
  "properties": {
    "gn:admin1_code":"12.0",
    "gn:asciiname":"Zhouhuangdun",
    "gn:country_code":"CN",
    "gn:dem":28,
    "gn:feature_class":"P",
    "gn:feature_code":"PPL",
    "gn:name":"Zhouhuangdun",
    "gn:population":0,
    "gn:timezone":"Asia/Shanghai",
    "iso:country":"CN",
    "name:zho_x_preferred":[
        "\u5468\u9ec4\u58a9"
    ],
    "wof:name":"Zhouhuangdun",
    "wof:placetype":"locality"
},
  "geometry": {"coordinates":[113.13630000000001,29.61008],"type":"Point"}
}