{
  "type": "Feature",
  "properties": {
    "gn:admin1_code":"02",
    "gn:asciiname":"Cengang",
    "gn:cc2":"CN",
    "gn:country_code":"CN",
    "gn:dem":1,
    "gn:feature_class":"P",
    "gn:feature_code":"PPL",
    "gn:name":"Cengang",
    "gn:population":0,
    "gn:timezone":"Asia/Shanghai",
    "iso:country":"CN",
    "name:und_x_variant":[
        "Ts\u2019en-kang-chen",
        "Ling-chiang",
        "Cengangzhen",
        "Cengang"
    ],
    "wof:name":"Cengang",
    "wof:placetype":"locality"
},
  "geometry": {"coordinates":[121.99167,30.07722],"type":"Point"}
}