{
  "type": "Feature",
  "properties": {
    "gn:admin1_code":"10.0",
    "gn:asciiname":"Chitushan",
    "gn:country_code":"CN",
    "gn:dem":8,
    "gn:feature_class":"P",
    "gn:feature_code":"PPL",
    "gn:name":"Chitushan",
    "gn:population":0,
    "gn:timezone":"Asia/Shanghai",
    "iso:country":"CN",
    "name:zho_x_preferred":[
        "\u8d64\u571f\u5c71"
    ],
    "wof:name":"Chitushan",
    "wof:placetype":"locality"
},
  "geometry": {"coordinates":[119.50439,39.83323],"type":"Point"}
}