{
  "type": "Feature",
  "properties": {
    "gn:admin1_code":"19.0",
    "gn:asciiname":"Gaijiagou",
    "gn:country_code":"CN",
    "gn:dem":232,
    "gn:feature_class":"P",
    "gn:feature_code":"PPL",
    "gn:name":"Gaijiagou",
    "gn:population":0,
    "gn:timezone":"Asia/Shanghai",
    "iso:country":"CN",
    "name:zho_x_preferred":[
        "\u76d6\u5bb6\u6c9f"
    ],
    "wof:name":"Gaijiagou",
    "wof:placetype":"locality"
},
  "geometry": {"coordinates":[120.52800000000001,41.37600000000001],"type":"Point"}
}