{
  "type": "Feature",
  "properties": {
    "gn:admin1_code":"16.0",
    "gn:asciiname":"Hewu",
    "gn:country_code":"CN",
    "gn:dem":44,
    "gn:feature_class":"P",
    "gn:feature_code":"PPL",
    "gn:name":"Hewu",
    "gn:population":0,
    "gn:timezone":"Asia/Shanghai",
    "iso:country":"CN",
    "name:zho_x_preferred":[
        "\u4f55\u5c4b"
    ],
    "wof:name":"Hewu",
    "wof:placetype":"locality"
},
  "geometry": {"coordinates":[109.794,23.2712],"type":"Point"}
}