{
  "type": "Feature",
  "properties": {
    "gn:admin1_code":"1.0",
    "gn:asciiname":"Xiaogutan",
    "gn:country_code":"CN",
    "gn:dem":143,
    "gn:feature_class":"P",
    "gn:feature_code":"PPL",
    "gn:name":"Xiaogutan",
    "gn:population":0,
    "gn:timezone":"Asia/Shanghai",
    "iso:country":"CN",
    "name:zho_x_preferred":[
        "\u5c0f\u59d1\u6f6d"
    ],
    "wof:name":"Xiaogutan",
    "wof:placetype":"locality"
},
  "geometry": {"coordinates":[118.34211000000001,29.6834],"type":"Point"}
}