{
  "type": "Feature",
  "properties": {
    "gn:admin1_code":"32.0",
    "gn:asciiname":"Citangbao",
    "gn:country_code":"CN",
    "gn:dem":534,
    "gn:feature_class":"P",
    "gn:feature_code":"PPL",
    "gn:name":"Citangbao",
    "gn:population":0,
    "gn:timezone":"Asia/Shanghai",
    "iso:country":"CN",
    "name:zho_x_preferred":[
        "\u7960\u5802\u5305"
    ],
    "wof:name":"Citangbao",
    "wof:placetype":"locality"
},
  "geometry": {"coordinates":[104.27500000000001,28.7854],"type":"Point"}
}