{
  "type": "Feature",
  "properties": {
    "gn:admin1_code":"7.0",
    "gn:asciiname":"Wuyang",
    "gn:country_code":"CN",
    "gn:dem":270,
    "gn:feature_class":"P",
    "gn:feature_code":"PPL",
    "gn:name":"Wuyang",
    "gn:population":0,
    "gn:timezone":"Asia/Shanghai",
    "iso:country":"CN",
    "name:ceb_x_preferred":[
        "Wuyang"
    ],
    "name:deu_x_preferred":[
        "Wuyang"
    ],
    "name:nor_x_preferred":[
        "Wuyang"
    ],
    "name:zho_x_preferred":[
        "\u4e4c\u7f8a"
    ],
    "wof:name":"Wuyang",
    "wof:placetype":"locality"
},
  "geometry": {"coordinates":[117.38347,27.65382],"type":"Point"}
}