{
  "type": "Feature",
  "properties": {
    "gn:admin1_code":"14.0",
    "gn:asciiname":"Jingzhu",
    "gn:country_code":"CN",
    "gn:dem":4713,
    "gn:feature_class":"P",
    "gn:feature_code":"PPL",
    "gn:name":"Jingzhu",
    "gn:population":0,
    "gn:timezone":"Asia/Urumqi",
    "iso:country":"CN",
    "name:zho_x_preferred":[
        "\u4eac\u73e0"
    ],
    "wof:name":"Jingzhu",
    "wof:placetype":"locality"
},
  "geometry": {"coordinates":[84.7778,31.0981],"type":"Point"}
}