{
  "type": "Feature",
  "properties": {
    "gn:admin1_code":"1.0",
    "gn:asciiname":"Laozhouweizi",
    "gn:country_code":"CN",
    "gn:dem":21,
    "gn:feature_class":"P",
    "gn:feature_code":"PPL",
    "gn:name":"Laozhouweizi",
    "gn:population":0,
    "gn:timezone":"Asia/Shanghai",
    "iso:country":"CN",
    "wof:name":"Laozhouweizi",
    "wof:placetype":"locality"
},
  "geometry": {"coordinates":[118.03333000000001,33.65833],"type":"Point"}
}