{
  "type": "Feature",
  "properties": {
    "gn:admin1_code":"16.0",
    "gn:asciiname":"Xinxiasi",
    "gn:country_code":"CN",
    "gn:dem":132,
    "gn:feature_class":"P",
    "gn:feature_code":"PPL",
    "gn:name":"Xinxiasi",
    "gn:population":0,
    "gn:timezone":"Asia/Shanghai",
    "iso:country":"CN",
    "name:zho_x_preferred":[
        "\u65b0\u4e0b\u5bfa"
    ],
    "wof:name":"Xinxiasi",
    "wof:placetype":"locality"
},
  "geometry": {"coordinates":[109.435,23.5883],"type":"Point"}
}