{
  "type": "Feature",
  "properties": {
    "gn:admin1_code":"33.0",
    "gn:asciiname":"Dabayi",
    "gn:country_code":"CN",
    "gn:dem":779,
    "gn:feature_class":"P",
    "gn:feature_code":"PPL",
    "gn:name":"Dabayi",
    "gn:population":0,
    "gn:timezone":"Asia/Shanghai",
    "iso:country":"CN",
    "name:zho_x_preferred":[
        "\u5927\u575d\u9091"
    ],
    "wof:name":"Dabayi",
    "wof:placetype":"locality"
},
  "geometry": {"coordinates":[108.57241999999999,28.88086],"type":"Point"}
}