{
  "type": "Feature",
  "properties": {
    "gn:admin1_code":"26.0",
    "gn:asciiname":"Zhangxinyao",
    "gn:country_code":"CN",
    "gn:dem":1112,
    "gn:feature_class":"P",
    "gn:feature_code":"PPL",
    "gn:name":"Zhangxinyao",
    "gn:population":0,
    "gn:timezone":"Asia/Shanghai",
    "iso:country":"CN",
    "name:zho_x_preferred":[
        "\u5f20\u65b0\u7a91"
    ],
    "wof:name":"Zhangxinyao",
    "wof:placetype":"locality"
},
  "geometry": {"coordinates":[109.50684,37.92133],"type":"Point"}
}