{
  "type": "Feature",
  "properties": {
    "gn:admin1_code":"9",
    "gn:asciiname":"Dongdiandang",
    "gn:country_code":"CN",
    "gn:dem":55,
    "gn:feature_class":"P",
    "gn:feature_code":"PPL",
    "gn:name":"Dongdiandang",
    "gn:population":0,
    "gn:timezone":"Asia/Shanghai",
    "iso:country":"CN",
    "name:zho_x_preferred":[
        "\u4e1c\u5e97\u5f53"
    ],
    "wof:name":"Dongdiandang",
    "wof:placetype":"locality"
},
  "geometry": {"coordinates":[115.015,35.61052],"type":"Point"}
}