{
  "type": "Feature",
  "properties": {
    "gn:admin1_code":"1.0",
    "gn:asciiname":"Houfancun",
    "gn:country_code":"CN",
    "gn:dem":625,
    "gn:feature_class":"P",
    "gn:feature_code":"PPL",
    "gn:name":"Houfancun",
    "gn:population":0,
    "gn:timezone":"Asia/Shanghai",
    "iso:country":"CN",
    "name:zho_x_preferred":[
        "\u540e\u7548\u6751"
    ],
    "wof:name":"Houfancun",
    "wof:placetype":"locality"
},
  "geometry": {"coordinates":[115.74473999999999,31.21128],"type":"Point"}
}