{
  "type": "Feature",
  "properties": {
    "gn:admin1_code":"8.0",
    "gn:asciiname":"Huiqiqiancun",
    "gn:country_code":"CN",
    "gn:dem":190,
    "gn:feature_class":"P",
    "gn:feature_code":"PPL",
    "gn:name":"Huiqiqiancun",
    "gn:population":0,
    "gn:timezone":"Asia/Shanghai",
    "iso:country":"CN",
    "name:zho_x_preferred":[
        "\u60e0\u4e03\u524d\u6751"
    ],
    "wof:name":"Huiqiqiancun",
    "wof:placetype":"locality"
},
  "geometry": {"coordinates":[126.64583,47.06167],"type":"Point"}
}