{
  "type": "Feature",
  "properties": {
    "gn:admin1_code":"12.0",
    "gn:asciiname":"Wujiapeng",
    "gn:country_code":"CN",
    "gn:dem":21,
    "gn:feature_class":"P",
    "gn:feature_code":"PPL",
    "gn:name":"Wujiapeng",
    "gn:population":0,
    "gn:timezone":"Asia/Shanghai",
    "iso:country":"CN",
    "name:und_x_variant":[
        "\u4e94\u5bb6\u68da"
    ],
    "wof:name":"Wujiapeng",
    "wof:placetype":"locality"
},
  "geometry": {"coordinates":[114.69596,30.32857000000001],"type":"Point"}
}