{
  "type": "Feature",
  "properties": {
    "gn:admin1_code":"25",
    "gn:asciiname":"Xixiazhai",
    "gn:country_code":"CN",
    "gn:dem":19,
    "gn:feature_class":"P",
    "gn:feature_code":"PPL",
    "gn:name":"Xixiazhai",
    "gn:population":0,
    "gn:timezone":"Asia/Shanghai",
    "iso:country":"CN",
    "name:zho_x_preferred":[
        "\u897f\u590f\u5be8"
    ],
    "wof:name":"Xixiazhai",
    "wof:placetype":"locality"
},
  "geometry": {"coordinates":[117.83199999999999,36.9738],"type":"Point"}
}