{
  "type": "Feature",
  "properties": {
    "gn:admin1_code":"26.0",
    "gn:asciiname":"Fengducun",
    "gn:country_code":"CN",
    "gn:dem":604,
    "gn:feature_class":"P",
    "gn:feature_code":"PPL",
    "gn:name":"Fengducun",
    "gn:population":0,
    "gn:timezone":"Asia/Shanghai",
    "iso:country":"CN",
    "name:zho_x_preferred":[
        "\u51af\u675c\u6751"
    ],
    "wof:name":"Fengducun",
    "wof:placetype":"locality"
},
  "geometry": {"coordinates":[109.44023,34.37852],"type":"Point"}
}