{
  "type": "Feature",
  "properties": {
    "gn:admin1_code":"16",
    "gn:asciiname":"Guiya",
    "gn:country_code":"CN",
    "gn:dem":440,
    "gn:feature_class":"P",
    "gn:feature_code":"PPL",
    "gn:name":"Guiya",
    "gn:population":0,
    "gn:timezone":"Asia/Shanghai",
    "iso:country":"CN",
    "name:zho_x_preferred":[
        "\u5f52\u4e9a"
    ],
    "wof:name":"Guiya",
    "wof:placetype":"locality"
},
  "geometry": {"coordinates":[109.35599999999999,25.7929],"type":"Point"}
}