{
  "type": "Feature",
  "properties": {
    "gn:admin1_code":"16.0",
    "gn:asciiname":"Changkun",
    "gn:country_code":"CN",
    "gn:dem":266,
    "gn:feature_class":"P",
    "gn:feature_code":"PPL",
    "gn:name":"Changkun",
    "gn:population":0,
    "gn:timezone":"Asia/Shanghai",
    "iso:country":"CN",
    "name:zho_x_preferred":[
        "\u957f\u6606"
    ],
    "wof:name":"Changkun",
    "wof:placetype":"locality"
},
  "geometry": {"coordinates":[109.523,22.4799],"type":"Point"}
}