{
  "type": "Feature",
  "properties": {
    "gn:admin1_code":"14.0",
    "gn:asciiname":"Rubacun",
    "gn:country_code":"CN",
    "gn:dem":4029,
    "gn:feature_class":"P",
    "gn:feature_code":"PPL",
    "gn:name":"Rubacun",
    "gn:population":0,
    "gn:timezone":"Asia/Urumqi",
    "iso:country":"CN",
    "name:zho_x_preferred":[
        "\u5982\u5df4\u6751"
    ],
    "wof:name":"Rubacun",
    "wof:placetype":"locality"
},
  "geometry": {"coordinates":[91.36744,30.1666],"type":"Point"}
}