{
  "type": "Feature",
  "properties": {
    "gn:admin1_code":"3.0",
    "gn:asciiname":"Dongfeng Zonghe Kenzhichang",
    "gn:country_code":"CN",
    "gn:dem":106,
    "gn:feature_class":"P",
    "gn:feature_code":"PPLF",
    "gn:name":"Dongfeng Zonghe Kenzhichang",
    "gn:population":0,
    "gn:timezone":"Asia/Shanghai",
    "iso:country":"CN",
    "name:und_x_variant":[
        "\u4e1c\u98ce\u7efc\u5408\u57a6\u6b96\u573a"
    ],
    "wof:name":"Dongfeng Zonghe Kenzhichang",
    "wof:placetype":"locality"
},
  "geometry": {"coordinates":[114.99271,28.67721],"type":"Point"}
}