{
  "type": "Feature",
  "properties": {
    "gn:admin1_code":"24",
    "gn:asciiname":"Weilu",
    "gn:country_code":"CN",
    "gn:dem":1397,
    "gn:feature_class":"P",
    "gn:feature_code":"PPL",
    "gn:name":"Weilu",
    "gn:population":0,
    "gn:timezone":"Asia/Shanghai",
    "iso:country":"CN",
    "name:und_x_variant":[
        "Wei-lu-pao",
        "Weilu",
        "\u5a01\u9c81"
    ],
    "wof:name":"Weilu",
    "wof:placetype":"locality"
},
  "geometry": {"coordinates":[112.78328999999999,40.17241],"type":"Point"}
}