{
  "type": "Feature",
  "properties": {
    "gn:admin1_code":"29",
    "gn:asciiname":"Daicun",
    "gn:country_code":"CN",
    "gn:dem":1738,
    "gn:feature_class":"P",
    "gn:feature_code":"PPL",
    "gn:name":"Daicun",
    "gn:population":0,
    "gn:timezone":"Asia/Shanghai",
    "iso:country":"CN",
    "name:zho_x_preferred":[
        "\u6234\u6751"
    ],
    "wof:name":"Daicun",
    "wof:placetype":"locality"
},
  "geometry": {"coordinates":[102.95099999999999,24.6245],"type":"Point"}
}