{
  "type": "Feature",
  "properties": {
    "gn:admin1_code":"5.0",
    "gn:asciiname":"Mengjiatun",
    "gn:country_code":"CN",
    "gn:dem":193,
    "gn:feature_class":"P",
    "gn:feature_code":"PPL",
    "gn:name":"Mengjiatun",
    "gn:population":0,
    "gn:timezone":"Asia/Shanghai",
    "iso:country":"CN",
    "name:zho_x_preferred":[
        "\u5b5f\u5bb6\u5c6f"
    ],
    "wof:name":"Mengjiatun",
    "wof:placetype":"locality"
},
  "geometry": {"coordinates":[125.63505000000001,44.64379],"type":"Point"}
}