{
  "type": "Feature",
  "properties": {
    "gn:admin1_code":"15.0",
    "gn:asciiname":"Huoshao",
    "gn:country_code":"CN",
    "gn:dem":1204,
    "gn:feature_class":"P",
    "gn:feature_code":"PPL",
    "gn:name":"Huoshao",
    "gn:population":0,
    "gn:timezone":"Asia/Shanghai",
    "iso:country":"CN",
    "name:zho_x_preferred":[
        "\u706b\u70e7"
    ],
    "wof:name":"Huoshao",
    "wof:placetype":"locality"
},
  "geometry": {"coordinates":[99.1961,40.2585],"type":"Point"}
}