{
  "type": "Feature",
  "properties": {
    "gn:admin1_code":"19.0",
    "gn:asciiname":"Ershanggou",
    "gn:country_code":"CN",
    "gn:dem":86,
    "gn:feature_class":"P",
    "gn:feature_code":"PPL",
    "gn:name":"Ershanggou",
    "gn:population":0,
    "gn:timezone":"Asia/Shanghai",
    "iso:country":"CN",
    "name:zho_x_preferred":[
        "\u4e8c\u57eb\u6c9f"
    ],
    "wof:name":"Ershanggou",
    "wof:placetype":"locality"
},
  "geometry": {"coordinates":[121.825,39.2069],"type":"Point"}
}