{
  "type": "Feature",
  "properties": {
    "gn:admin1_code":"16.0",
    "gn:asciiname":"Ganpan",
    "gn:country_code":"CN",
    "gn:dem":356,
    "gn:feature_class":"P",
    "gn:feature_code":"PPL",
    "gn:name":"Ganpan",
    "gn:population":0,
    "gn:timezone":"Asia/Shanghai",
    "iso:country":"CN",
    "name:zho_x_preferred":[
        "\u5e72\u76d8"
    ],
    "wof:name":"Ganpan",
    "wof:placetype":"locality"
},
  "geometry": {"coordinates":[108.745,24.6751],"type":"Point"}
}