{
  "type": "Feature",
  "properties": {
    "gn:admin1_code":"6.0",
    "gn:asciiname":"Gaorao",
    "gn:country_code":"CN",
    "gn:dem":3647,
    "gn:feature_class":"P",
    "gn:feature_code":"PPL",
    "gn:name":"Gaorao",
    "gn:population":0,
    "gn:timezone":"Asia/Urumqi",
    "iso:country":"CN",
    "name:zho_x_preferred":[
        "\u9ad8\u7ed5"
    ],
    "wof:name":"Gaorao",
    "wof:placetype":"locality"
},
  "geometry": {"coordinates":[96.80775,32.03558],"type":"Point"}
}