{
  "type": "Feature",
  "properties": {
    "gn:admin1_code":"7",
    "gn:asciiname":"Taxiacun",
    "gn:country_code":"CN",
    "gn:dem":570,
    "gn:feature_class":"P",
    "gn:feature_code":"PPL",
    "gn:name":"Taxiacun",
    "gn:population":0,
    "gn:timezone":"Asia/Shanghai",
    "iso:country":"CN",
    "name:zho_x_preferred":[
        "\u5854\u4e0b\u6751"
    ],
    "wof:name":"Taxiacun",
    "wof:placetype":"locality"
},
  "geometry": {"coordinates":[117.04474,24.62107],"type":"Point"}
}