{
  "type": "Feature",
  "properties": {
    "gn:admin1_code":"13.0",
    "gn:asciiname":"Bor Tungge",
    "gn:country_code":"CN",
    "gn:dem":1191,
    "gn:feature_class":"P",
    "gn:feature_code":"PPLA4",
    "gn:name":"Bor Tungge",
    "gn:population":0,
    "gn:timezone":"Asia/Urumqi",
    "iso:country":"CN",
    "name:uig_x_preferred":[
        "Bort\u00fcnggi"
    ],
    "name:uig_x_variant":[
        "\u0628\u0648\u0631\u062a\u06c8\u06ad\u06af\u0649",
        "\u0411\u043e\u0440\u0442\u04af\u04a3\u0433\u0438"
    ],
    "name:und_x_variant":[
        "Bo\u2019ertonggu",
        "Bo\u2019ertonggu Xiang"
    ],
    "name:zho_x_preferred":[
        "\u535a\u5c14\u901a\u53e4"
    ],
    "name:zho_x_variant":[
        "\u535a\u5c14\u901a\u53e4\u4e61"
    ],
    "wof:name":"Bor Tungge",
    "wof:placetype":"locality"
},
  "geometry": {"coordinates":[85.37747,44.05317],"type":"Point"}
}