{
  "type": "Feature",
  "properties": {
    "gn:admin1_code":"12.0",
    "gn:asciiname":"Xiaxujiatai",
    "gn:country_code":"CN",
    "gn:dem":30,
    "gn:feature_class":"P",
    "gn:feature_code":"PPL",
    "gn:name":"Xiaxujiatai",
    "gn:population":0,
    "gn:timezone":"Asia/Shanghai",
    "iso:country":"CN",
    "name:zho_x_preferred":[
        "\u4e0b\u5f90\u5bb6\u53f0"
    ],
    "wof:name":"Xiaxujiatai",
    "wof:placetype":"locality"
},
  "geometry": {"coordinates":[113.15815000000001,30.36586],"type":"Point"}
}