{
  "type": "Feature",
  "properties": {
    "gn:admin1_code":"8.0",
    "gn:asciiname":"Beidamiao",
    "gn:country_code":"CN",
    "gn:dem":220,
    "gn:feature_class":"P",
    "gn:feature_code":"PPL",
    "gn:name":"Beidamiao",
    "gn:population":0,
    "gn:timezone":"Asia/Shanghai",
    "iso:country":"CN",
    "name:zho_x_preferred":[
        "\u5317\u5927\u5e99"
    ],
    "wof:name":"Beidamiao",
    "wof:placetype":"locality"
},
  "geometry": {"coordinates":[128.07069999999999,45.09042],"type":"Point"}
}