{
  "type": "Feature",
  "properties": {
    "gn:admin1_code":"12.0",
    "gn:asciiname":"Dabujie",
    "gn:country_code":"CN",
    "gn:dem":82,
    "gn:feature_class":"P",
    "gn:feature_code":"PPL",
    "gn:name":"Dabujie",
    "gn:population":0,
    "gn:timezone":"Asia/Shanghai",
    "iso:country":"CN",
    "name:zho_x_preferred":[
        "\u5927\u57e0\u8857"
    ],
    "wof:name":"Dabujie",
    "wof:placetype":"locality"
},
  "geometry": {"coordinates":[112.30355,32.0286],"type":"Point"}
}