{
  "type": "Feature",
  "properties": {
    "gn:admin1_code":"29.0",
    "gn:asciiname":"Wanhuzhuang",
    "gn:country_code":"CN",
    "gn:dem":1585,
    "gn:feature_class":"P",
    "gn:feature_code":"PPL",
    "gn:name":"Wanhuzhuang",
    "gn:population":0,
    "gn:timezone":"Asia/Shanghai",
    "iso:country":"CN",
    "name:zho_x_preferred":[
        "\u4e07\u6237\u5e84"
    ],
    "wof:name":"Wanhuzhuang",
    "wof:placetype":"locality"
},
  "geometry": {"coordinates":[103.145,24.9875],"type":"Point"}
}