{
  "type": "Feature",
  "properties": {
    "gn:admin1_code":"33.0",
    "gn:asciiname":"Pingxi",
    "gn:country_code":"CN",
    "gn:dem":1252,
    "gn:feature_class":"P",
    "gn:feature_code":"PPL",
    "gn:name":"Pingxi",
    "gn:population":0,
    "gn:timezone":"Asia/Shanghai",
    "iso:country":"CN",
    "name:zho_x_preferred":[
        "\u5e73\u6eaa"
    ],
    "wof:name":"Pingxi",
    "wof:placetype":"locality"
},
  "geometry": {"coordinates":[108.94346000000002,31.89386],"type":"Point"}
}