{
  "type": "Feature",
  "properties": {
    "gn:admin1_code":"16.0",
    "gn:asciiname":"Leida",
    "gn:country_code":"CN",
    "gn:dem":112,
    "gn:feature_class":"P",
    "gn:feature_code":"PPL",
    "gn:name":"Leida",
    "gn:population":0,
    "gn:timezone":"Asia/Shanghai",
    "iso:country":"CN",
    "name:vie_x_preferred":[
        "Leida"
    ],
    "name:zho_x_preferred":[
        "\u96f7\u5927"
    ],
    "wof:name":"Leida",
    "wof:placetype":"locality"
},
  "geometry": {"coordinates":[108.238,23.1176],"type":"Point"}
}