{
  "type": "Feature",
  "properties": {
    "gn:admin1_code":"31",
    "gn:asciiname":"Bianwen",
    "gn:country_code":"CN",
    "gn:dem":445,
    "gn:feature_class":"P",
    "gn:feature_code":"PPL",
    "gn:name":"Bianwen",
    "gn:population":0,
    "gn:timezone":"Asia/Shanghai",
    "iso:country":"CN",
    "name:deu_x_preferred":[
        "Bianwen"
    ],
    "name:fra_x_preferred":[
        "Bianwen"
    ],
    "name:ind_x_preferred":[
        "Bianwen"
    ],
    "name:ita_x_preferred":[
        "Bianwen"
    ],
    "name:kat_x_preferred":[
        "\u10d1\u10d8\u10d0\u10dc\u10d5\u10d4\u10dc\u10d8"
    ],
    "name:pol_x_preferred":[
        "Bianwen"
    ],
    "name:und_x_variant":[
        "\u4fbf\u6587"
    ],
    "wof:name":"Bianwen",
    "wof:placetype":"locality"
},
  "geometry": {"coordinates":[109.548,18.9936],"type":"Point"}
}