{
  "type": "Feature",
  "properties": {
    "gn:admin1_code":"4.0",
    "gn:asciiname":"Shengoucun",
    "gn:country_code":"CN",
    "gn:dem":15,
    "gn:feature_class":"P",
    "gn:feature_code":"PPL",
    "gn:name":"Shengoucun",
    "gn:population":0,
    "gn:timezone":"Asia/Shanghai",
    "iso:country":"CN",
    "name:und_x_variant":[
        "Shengou"
    ],
    "name:zho_x_preferred":[
        "\u6df1\u6c9f\u6751"
    ],
    "wof:name":"Shengoucun",
    "wof:placetype":"locality"
},
  "geometry": {"coordinates":[119.13549999999999,34.32129],"type":"Point"}
}