{
  "type": "Feature",
  "properties": {
    "gn:admin1_code":"19.0",
    "gn:asciiname":"Xiatouzi",
    "gn:country_code":"CN",
    "gn:dem":106,
    "gn:feature_class":"P",
    "gn:feature_code":"PPL",
    "gn:name":"Xiatouzi",
    "gn:population":0,
    "gn:timezone":"Asia/Shanghai",
    "iso:country":"CN",
    "name:zho_x_preferred":[
        "\u4e0b\u5934\u5b50"
    ],
    "wof:name":"Xiatouzi",
    "wof:placetype":"locality"
},
  "geometry": {"coordinates":[123.782,42.6681],"type":"Point"}
}