{
  "type": "Feature",
  "properties": {
    "gn:admin1_code":"10.0",
    "gn:asciiname":"Dongli",
    "gn:country_code":"CN",
    "gn:dem":56,
    "gn:feature_class":"P",
    "gn:feature_code":"PPL",
    "gn:name":"Dongli",
    "gn:population":0,
    "gn:timezone":"Asia/Shanghai",
    "iso:country":"CN",
    "name:ceb_x_preferred":[
        "Dongli"
    ],
    "name:und_x_variant":[
        "\u4e1c\u91cc"
    ],
    "wof:name":"Dongli",
    "wof:placetype":"locality"
},
  "geometry": {"coordinates":[114.92759,38.3357],"type":"Point"}
}