{
  "type": "Feature",
  "properties": {
    "gn:admin1_code":"11.0",
    "gn:asciiname":"Matuwu",
    "gn:country_code":"CN",
    "gn:dem":140,
    "gn:feature_class":"P",
    "gn:feature_code":"PPL",
    "gn:name":"Matuwu",
    "gn:population":0,
    "gn:timezone":"Asia/Shanghai",
    "iso:country":"CN",
    "name:zho_x_preferred":[
        "\u9ebb\u571f\u5c4b"
    ],
    "wof:name":"Matuwu",
    "wof:placetype":"locality"
},
  "geometry": {"coordinates":[113.74984000000001,26.94844],"type":"Point"}
}