{
  "type": "Feature",
  "properties": {
    "gn:admin1_code":"29.0",
    "gn:asciiname":"Qixinggang",
    "gn:country_code":"CN",
    "gn:dem":2591,
    "gn:feature_class":"P",
    "gn:feature_code":"PPL",
    "gn:name":"Qixinggang",
    "gn:population":0,
    "gn:timezone":"Asia/Shanghai",
    "iso:country":"CN",
    "name:zho_x_preferred":[
        "\u4e03\u661f\u5c97"
    ],
    "wof:name":"Qixinggang",
    "wof:placetype":"locality"
},
  "geometry": {"coordinates":[100.51600000000001,26.7592],"type":"Point"}
}