{
  "type": "Feature",
  "properties": {
    "gn:admin1_code":"04",
    "gn:asciiname":"Erling",
    "gn:country_code":"CN",
    "gn:dem":9,
    "gn:feature_class":"P",
    "gn:feature_code":"PPLA4",
    "gn:name":"Erling",
    "gn:population":0,
    "gn:timezone":"Asia/Shanghai",
    "iso:country":"CN",
    "name:deu_x_preferred":[
        "Erling"
    ],
    "name:und_x_variant":[
        "Erh-ling",
        "Erh-ling-chen",
        "Erling Zhen"
    ],
    "name:zho_x_preferred":[
        "\u73e5\u9675"
    ],
    "name:zho_x_variant":[
        "\u73e5\u9675\u9547"
    ],
    "wof:name":"Erling",
    "wof:placetype":"locality"
},
  "geometry": {"coordinates":[119.59558,31.87974],"type":"Point"}
}