{
  "type": "Feature",
  "properties": {
    "gn:admin1_code":"16.0",
    "gn:asciiname":"Gouge",
    "gn:country_code":"CN",
    "gn:dem":210,
    "gn:feature_class":"P",
    "gn:feature_code":"PPL",
    "gn:name":"Gouge",
    "gn:population":0,
    "gn:timezone":"Asia/Shanghai",
    "iso:country":"CN",
    "name:fra_x_preferred":[
        "Gouge"
    ],
    "name:rus_x_preferred":[
        "\u0413\u0443\u0436"
    ],
    "name:tgl_x_preferred":[
        "Pait"
    ],
    "name:ukr_x_preferred":[
        "\u0413\u0443\u0436"
    ],
    "name:zho_x_preferred":[
        "\u52fe\u5272"
    ],
    "wof:name":"Gouge",
    "wof:placetype":"locality"
},
  "geometry": {"coordinates":[107.92400000000001,23.9422],"type":"Point"}
}