{
  "type": "Feature",
  "properties": {
    "gn:admin1_code":"18",
    "gn:asciiname":"Paifang",
    "gn:country_code":"CN",
    "gn:dem":1237,
    "gn:feature_class":"P",
    "gn:feature_code":"PPL",
    "gn:name":"Paifang",
    "gn:population":0,
    "gn:timezone":"Asia/Shanghai",
    "iso:country":"CN",
    "name:deu_x_preferred":[
        "Pailou"
    ],
    "name:fra_x_preferred":[
        "Pa\u00effang"
    ],
    "name:ita_x_preferred":[
        "Paifang"
    ],
    "name:msa_x_preferred":[
        "Paifang"
    ],
    "name:nld_x_preferred":[
        "Chinese poort"
    ],
    "name:nor_x_preferred":[
        "Pailou"
    ],
    "name:pol_x_preferred":[
        "Paifang"
    ],
    "name:rus_x_preferred":[
        "\u041f\u0430\u0439\u043b\u043e\u0443"
    ],
    "name:spa_x_preferred":[
        "Paifang"
    ],
    "name:swe_x_preferred":[
        "Paifang"
    ],
    "name:ukr_x_preferred":[
        "\u041f\u0430\u0439\u043b\u043e\u0443"
    ],
    "name:zho_x_preferred":[
        "\u724c\u574a"
    ],
    "wof:name":"Paifang",
    "wof:placetype":"locality"
},
  "geometry": {"coordinates":[104.914,25.8521],"type":"Point"}
}