{
  "type": "Feature",
  "properties": {
    "gn:admin1_code":"32.0",
    "gn:asciiname":"Mujue",
    "gn:country_code":"CN",
    "gn:dem":2257,
    "gn:feature_class":"P",
    "gn:feature_code":"PPL",
    "gn:name":"Mujue",
    "gn:population":0,
    "gn:timezone":"Asia/Shanghai",
    "iso:country":"CN",
    "name:zho_x_preferred":[
        "\u7261\u89c9"
    ],
    "wof:name":"Mujue",
    "wof:placetype":"locality"
},
  "geometry": {"coordinates":[103.07899999999999,28.2674],"type":"Point"}
}