{
  "type": "Feature",
  "properties": {
    "gn:admin1_code":"26.0",
    "gn:asciiname":"Houliulingou",
    "gn:country_code":"CN",
    "gn:dem":1225,
    "gn:feature_class":"P",
    "gn:feature_code":"PPL",
    "gn:name":"Houliulingou",
    "gn:population":0,
    "gn:timezone":"Asia/Shanghai",
    "iso:country":"CN",
    "name:zho_x_preferred":[
        "\u540e\u67f3\u6797\u6c9f"
    ],
    "wof:name":"Houliulingou",
    "wof:placetype":"locality"
},
  "geometry": {"coordinates":[109.20587999999999,36.35104000000001],"type":"Point"}
}