{
  "type": "Feature",
  "properties": {
    "gn:admin1_code":"16.0",
    "gn:asciiname":"Tongjiang",
    "gn:country_code":"CN",
    "gn:dem":144,
    "gn:feature_class":"P",
    "gn:feature_code":"PPL",
    "gn:name":"Tongjiang",
    "gn:population":0,
    "gn:timezone":"Asia/Shanghai",
    "iso:country":"CN",
    "name:ceb_x_preferred":[
        "Tongjiang"
    ],
    "name:deu_x_preferred":[
        "Tongjiang"
    ],
    "name:fra_x_preferred":[
        "Tongjiang"
    ],
    "name:nor_x_preferred":[
        "Tongjiang"
    ],
    "name:rus_x_preferred":[
        "\u0422\u0443\u043d\u0446\u0437\u044f\u043d"
    ],
    "name:swe_x_preferred":[
        "Tongjiang"
    ],
    "name:zho_x_preferred":[
        "\u540c\u964d"
    ],
    "wof:name":"Tongjiang",
    "wof:placetype":"locality"
},
  "geometry": {"coordinates":[110.557,23.8317],"type":"Point"}
}