{
  "type": "Feature",
  "properties": {
    "gn:admin1_code":"4.0",
    "gn:asciiname":"Xuxu",
    "gn:country_code":"CN",
    "gn:dem":0,
    "gn:feature_class":"P",
    "gn:feature_code":"PPL",
    "gn:name":"Xuxu",
    "gn:population":0,
    "gn:timezone":"Asia/Shanghai",
    "iso:country":"CN",
    "name:zho_x_preferred":[
        "Xuxu"
    ],
    "name:zho_x_variant":[
        "\u5f90\u5729"
    ],
    "wof:name":"Xuxu",
    "wof:placetype":"locality"
},
  "geometry": {"coordinates":[119.75342999999999,33.95235],"type":"Point"}
}