{
  "type": "Feature",
  "properties": {
    "gn:admin1_code":"31.0",
    "gn:asciiname":"Hulutian",
    "gn:country_code":"CN",
    "gn:dem":36,
    "gn:feature_class":"P",
    "gn:feature_code":"PPL",
    "gn:name":"Hulutian",
    "gn:population":0,
    "gn:timezone":"Asia/Shanghai",
    "iso:country":"CN",
    "name:und_x_variant":[
        "\u846b\u82a6\u7530"
    ],
    "wof:name":"Hulutian",
    "wof:placetype":"locality"
},
  "geometry": {"coordinates":[108.74294999999999,19.08421],"type":"Point"}
}