{
  "type": "Feature",
  "properties": {
    "gn:admin1_code":"31.0",
    "gn:asciiname":"Niuxincun",
    "gn:country_code":"CN",
    "gn:dem":315,
    "gn:feature_class":"P",
    "gn:feature_code":"PPL",
    "gn:name":"Niuxincun",
    "gn:population":0,
    "gn:timezone":"Asia/Shanghai",
    "iso:country":"CN",
    "name:zho_x_preferred":[
        "\u725b\u65b0\u6751"
    ],
    "wof:name":"Niuxincun",
    "wof:placetype":"locality"
},
  "geometry": {"coordinates":[109.94114999999999,18.96372],"type":"Point"}
}