{
  "type": "Feature",
  "properties": {
    "gn:admin1_code":"18",
    "gn:asciiname":"Haijiaying",
    "gn:country_code":"CN",
    "gn:dem":2303,
    "gn:feature_class":"P",
    "gn:feature_code":"PPL",
    "gn:name":"Haijiaying",
    "gn:population":0,
    "gn:timezone":"Asia/Shanghai",
    "iso:country":"CN",
    "name:zho_x_preferred":[
        "\u6d77\u5bb6\u8425"
    ],
    "wof:name":"Haijiaying",
    "wof:placetype":"locality"
},
  "geometry": {"coordinates":[104.51300000000001,26.7497],"type":"Point"}
}