{
  "type": "Feature",
  "properties": {
    "gn:admin1_code":"1.0",
    "gn:asciiname":"Wangchengcun",
    "gn:country_code":"CN",
    "gn:dem":36,
    "gn:feature_class":"P",
    "gn:feature_code":"PPL",
    "gn:name":"Wangchengcun",
    "gn:population":0,
    "gn:timezone":"Asia/Shanghai",
    "iso:country":"CN",
    "name:zho_x_preferred":[
        "\u671b\u57ce\u6751"
    ],
    "wof:name":"Wangchengcun",
    "wof:placetype":"locality"
},
  "geometry": {"coordinates":[116.97976,31.00538],"type":"Point"}
}