{
  "type": "Feature",
  "properties": {
    "gn:admin1_code":"18",
    "gn:asciiname":"Zhuyingshao",
    "gn:country_code":"CN",
    "gn:dem":1265,
    "gn:feature_class":"P",
    "gn:feature_code":"PPL",
    "gn:name":"Zhuyingshao",
    "gn:population":0,
    "gn:timezone":"Asia/Shanghai",
    "iso:country":"CN",
    "name:zho_x_preferred":[
        "\u795d\u82f1\u54e8"
    ],
    "wof:name":"Zhuyingshao",
    "wof:placetype":"locality"
},
  "geometry": {"coordinates":[105.715,26.0361],"type":"Point"}
}