{
  "type": "Feature",
  "properties": {
    "gn:admin1_code":"26.0",
    "gn:asciiname":"Pojiagou",
    "gn:country_code":"CN",
    "gn:dem":1261,
    "gn:feature_class":"P",
    "gn:feature_code":"PPL",
    "gn:name":"Pojiagou",
    "gn:population":0,
    "gn:timezone":"Asia/Shanghai",
    "iso:country":"CN",
    "name:zho_x_preferred":[
        "\u5761\u5bb6\u6c9f"
    ],
    "wof:name":"Pojiagou",
    "wof:placetype":"locality"
},
  "geometry": {"coordinates":[110.23721999999999,35.90964],"type":"Point"}
}