{
  "type": "Feature",
  "properties": {
    "gn:admin1_code":"7",
    "gn:asciiname":"Shangjiaokeng",
    "gn:country_code":"CN",
    "gn:dem":740,
    "gn:feature_class":"P",
    "gn:feature_code":"PPL",
    "gn:name":"Shangjiaokeng",
    "gn:population":0,
    "gn:timezone":"Asia/Shanghai",
    "iso:country":"CN",
    "name:zho_x_preferred":[
        "\u4e0a\u8549\u5751"
    ],
    "wof:name":"Shangjiaokeng",
    "wof:placetype":"locality"
},
  "geometry": {"coordinates":[117.11278,24.57944],"type":"Point"}
}