{
  "type": "Feature",
  "properties": {
    "gn:admin1_code":"3.0",
    "gn:asciiname":"Jiantian",
    "gn:country_code":"CN",
    "gn:dem":166,
    "gn:feature_class":"P",
    "gn:feature_code":"PPL",
    "gn:name":"Jiantian",
    "gn:population":0,
    "gn:timezone":"Asia/Shanghai",
    "iso:country":"CN",
    "name:und_x_variant":[
        "\u67a7\u7530"
    ],
    "wof:name":"Jiantian",
    "wof:placetype":"locality"
},
  "geometry": {"coordinates":[115.61714000000001,26.73367],"type":"Point"}
}