{
  "type": "Feature",
  "properties": {
    "gn:admin1_code":"13",
    "gn:asciiname":"Aiji'ermaili",
    "gn:country_code":"CN",
    "gn:dem":1064,
    "gn:feature_class":"P",
    "gn:feature_code":"PPL",
    "gn:name":"Aiji\u2019ermaili",
    "gn:population":0,
    "gn:timezone":"Asia/Shanghai",
    "iso:country":"CN",
    "name:und_x_variant":[
        "Aiji\u2019ermaili",
        "\u827e\u5409\u5c14\u4e70\u91cc"
    ],
    "wof:name":"Aiji'ermaili",
    "wof:placetype":"locality"
},
  "geometry": {"coordinates":[80.62836999999998,40.93207],"type":"Point"}
}