{
  "type": "Feature",
  "properties": {
    "gn:admin1_code":"15.0",
    "gn:asciiname":"Gouquan",
    "gn:country_code":"CN",
    "gn:dem":1405,
    "gn:feature_class":"P",
    "gn:feature_code":"PPL",
    "gn:name":"Gouquan",
    "gn:population":0,
    "gn:timezone":"Asia/Shanghai",
    "iso:country":"CN",
    "name:zho_x_preferred":[
        "\u6c9f\u5708"
    ],
    "wof:name":"Gouquan",
    "wof:placetype":"locality"
},
  "geometry": {"coordinates":[107.35599999999999,35.1278],"type":"Point"}
}