{
  "type": "Feature",
  "properties": {
    "gn:admin1_code":"32.0",
    "gn:asciiname":"Sijiacun",
    "gn:country_code":"CN",
    "gn:dem":3057,
    "gn:feature_class":"P",
    "gn:feature_code":"PPL",
    "gn:name":"Sijiacun",
    "gn:population":0,
    "gn:timezone":"Asia/Shanghai",
    "iso:country":"CN",
    "name:zho_x_preferred":[
        "\u56db\u5bb6\u6751"
    ],
    "wof:name":"Sijiacun",
    "wof:placetype":"locality"
},
  "geometry": {"coordinates":[101.19683999999999,27.13528],"type":"Point"}
}