{
  "type": "Feature",
  "properties": {
    "gn:admin1_code":"3.0",
    "gn:asciiname":"Nanshanxia",
    "gn:country_code":"CN",
    "gn:dem":196,
    "gn:feature_class":"P",
    "gn:feature_code":"PPL",
    "gn:name":"Nanshanxia",
    "gn:population":0,
    "gn:timezone":"Asia/Shanghai",
    "iso:country":"CN",
    "name:und_x_variant":[
        "\u5357\u5c71\u4e0b"
    ],
    "wof:name":"Nanshanxia",
    "wof:placetype":"locality"
},
  "geometry": {"coordinates":[115.88120000000001,25.65777000000001],"type":"Point"}
}