{
  "type": "Feature",
  "properties": {
    "gn:admin1_code":"9.0",
    "gn:asciiname":"Chenmen",
    "gn:country_code":"CN",
    "gn:dem":76,
    "gn:feature_class":"P",
    "gn:feature_code":"PPL",
    "gn:name":"Chenmen",
    "gn:population":0,
    "gn:timezone":"Asia/Shanghai",
    "iso:country":"CN",
    "name:zho_x_preferred":[
        "\u9648\u95e8"
    ],
    "wof:name":"Chenmen",
    "wof:placetype":"locality"
},
  "geometry": {"coordinates":[113.88866000000002,34.10824],"type":"Point"}
}