{
  "type": "Feature",
  "properties": {
    "gn:admin1_code":"16.0",
    "gn:asciiname":"Fengmengang",
    "gn:country_code":"CN",
    "gn:dem":77,
    "gn:feature_class":"P",
    "gn:feature_code":"PPL",
    "gn:name":"Fengmengang",
    "gn:population":0,
    "gn:timezone":"Asia/Shanghai",
    "iso:country":"CN",
    "name:zho_x_preferred":[
        "\u98ce\u95e8\u5c97"
    ],
    "wof:name":"Fengmengang",
    "wof:placetype":"locality"
},
  "geometry": {"coordinates":[110.31399999999999,23.3568],"type":"Point"}
}