{
  "type": "Feature",
  "properties": {
    "gn:admin1_code":"5.0",
    "gn:asciiname":"Baoquancun",
    "gn:country_code":"CN",
    "gn:dem":232,
    "gn:feature_class":"P",
    "gn:feature_code":"PPL",
    "gn:name":"Baoquancun",
    "gn:population":0,
    "gn:timezone":"Asia/Shanghai",
    "iso:country":"CN",
    "name:zho_x_preferred":[
        "\u5b9d\u6cc9\u6751"
    ],
    "wof:name":"Baoquancun",
    "wof:placetype":"locality"
},
  "geometry": {"coordinates":[122.03868,45.66211],"type":"Point"}
}