{
  "type": "Feature",
  "properties": {
    "gn:admin1_code":"11",
    "gn:asciiname":"Shuixi",
    "gn:country_code":"CN",
    "gn:dem":325,
    "gn:feature_class":"P",
    "gn:feature_code":"PPL",
    "gn:name":"Shuixi",
    "gn:population":0,
    "gn:timezone":"Asia/Shanghai",
    "iso:country":"CN",
    "wof:name":"Shuixi",
    "wof:placetype":"locality"
},
  "geometry": {"coordinates":[110.79778,27.22389],"type":"Point"}
}