{
  "type": "Feature",
  "properties": {
    "gn:admin1_code":"11.0",
    "gn:asciiname":"Zhimata",
    "gn:country_code":"CN",
    "gn:dem":724,
    "gn:feature_class":"P",
    "gn:feature_code":"PPL",
    "gn:name":"Zhimata",
    "gn:population":0,
    "gn:timezone":"Asia/Shanghai",
    "iso:country":"CN",
    "name:zho_x_preferred":[
        "\u7eb8\u9a6c\u5854"
    ],
    "wof:name":"Zhimata",
    "wof:placetype":"locality"
},
  "geometry": {"coordinates":[110.47425,29.34363],"type":"Point"}
}