{
  "type": "Feature",
  "properties": {
    "gn:admin1_code":"11.0",
    "gn:asciiname":"Tangniwan",
    "gn:country_code":"CN",
    "gn:dem":256,
    "gn:feature_class":"P",
    "gn:feature_code":"PPL",
    "gn:name":"Tangniwan",
    "gn:population":0,
    "gn:timezone":"Asia/Shanghai",
    "iso:country":"CN",
    "name:zho_x_preferred":[
        "\u5858\u6ce5\u6e7e"
    ],
    "wof:name":"Tangniwan",
    "wof:placetype":"locality"
},
  "geometry": {"coordinates":[111.43785,27.70837],"type":"Point"}
}