{
  "type": "Feature",
  "properties": {
    "gn:admin1_code":"7.0",
    "gn:asciiname":"Dongjiyang",
    "gn:country_code":"CN",
    "gn:dem":600,
    "gn:feature_class":"P",
    "gn:feature_code":"PPL",
    "gn:name":"Dongjiyang",
    "gn:population":0,
    "gn:timezone":"Asia/Shanghai",
    "iso:country":"CN",
    "name:zho_x_preferred":[
        "\u4e1c\u5409\u6d0b"
    ],
    "wof:name":"Dongjiyang",
    "wof:placetype":"locality"
},
  "geometry": {"coordinates":[119.60135,27.42157000000001],"type":"Point"}
}