{
  "type": "Feature",
  "properties": {
    "gn:admin1_code":"8.0",
    "gn:asciiname":"Sunjia Wobu",
    "gn:country_code":"CN",
    "gn:dem":157,
    "gn:feature_class":"P",
    "gn:feature_code":"PPL",
    "gn:name":"Sunjia Wobu",
    "gn:population":0,
    "gn:timezone":"Asia/Shanghai",
    "iso:country":"CN",
    "name:zho_x_preferred":[
        "\u5b59\u5bb6\u7a9d\u5821"
    ],
    "wof:name":"Sunjia Wobu",
    "wof:placetype":"locality"
},
  "geometry": {"coordinates":[126.76000000000001,46.47449],"type":"Point"}
}