{
  "type": "Feature",
  "properties": {
    "gn:admin1_code":"25.0",
    "gn:asciiname":"Beiluojia",
    "gn:country_code":"CN",
    "gn:dem":69,
    "gn:feature_class":"P",
    "gn:feature_code":"PPL",
    "gn:name":"Beiluojia",
    "gn:population":0,
    "gn:timezone":"Asia/Shanghai",
    "iso:country":"CN",
    "name:zho_x_preferred":[
        "\u5317\u7f57\u5bb6"
    ],
    "wof:name":"Beiluojia",
    "wof:placetype":"locality"
},
  "geometry": {"coordinates":[120.65945000000001,37.72444],"type":"Point"}
}