{
  "type": "Feature",
  "properties": {
    "gn:admin1_code":"16.0",
    "gn:asciiname":"Yongwei",
    "gn:country_code":"CN",
    "gn:dem":155,
    "gn:feature_class":"P",
    "gn:feature_code":"PPL",
    "gn:name":"Yongwei",
    "gn:population":0,
    "gn:timezone":"Asia/Shanghai",
    "iso:country":"CN",
    "name:zho_x_preferred":[
        "\u52c7\u4f1f"
    ],
    "wof:name":"Yongwei",
    "wof:placetype":"locality"
},
  "geometry": {"coordinates":[109.294,25.7048],"type":"Point"}
}