{
  "type": "Feature",
  "properties": {
    "gn:admin1_code":"33.0",
    "gn:asciiname":"Changping",
    "gn:country_code":"CN",
    "gn:dem":228,
    "gn:feature_class":"P",
    "gn:feature_code":"PPLA4",
    "gn:name":"Changping",
    "gn:population":0,
    "gn:timezone":"Asia/Shanghai",
    "iso:country":"CN",
    "name:ceb_x_preferred":[
        "Changping"
    ],
    "name:ces_x_preferred":[
        "\u010cchang-pching"
    ],
    "name:mlg_x_preferred":[
        "Changping"
    ],
    "name:swe_x_preferred":[
        "Changping"
    ],
    "name:und_x_variant":[
        "Changping Xiang",
        "Wuyangba"
    ],
    "name:zho_x_preferred":[
        "\u957f\u576a"
    ],
    "name:zho_x_variant":[
        "\u957f\u576a\u4e61",
        "\u4e4c\u6768\u575d"
    ],
    "wof:name":"Changping",
    "wof:placetype":"locality"
},
  "geometry": {"coordinates":[108.24841000000001,30.44274],"type":"Point"}
}