{
  "type": "Feature",
  "properties": {
    "gn:admin1_code":"14.0",
    "gn:asciiname":"Tongmoin",
    "gn:country_code":"CN",
    "gn:dem":3922,
    "gn:feature_class":"P",
    "gn:feature_code":"PPLF",
    "gn:name":"Tongmoin",
    "gn:population":0,
    "gn:timezone":"Asia/Urumqi",
    "iso:country":"CN",
    "name:bod_x_preferred":[
        "Tongmoin"
    ],
    "name:zho_x_preferred":[
        "Tongmen"
    ],
    "name:zho_x_variant":[
        "\u901a\u95e8"
    ],
    "wof:name":"Tongmoin",
    "wof:placetype":"locality"
},
  "geometry": {"coordinates":[88.205,29.405],"type":"Point"}
}