{
  "type": "Feature",
  "properties": {
    "gn:admin1_code":"18",
    "gn:asciiname":"Zhutang",
    "gn:country_code":"CN",
    "gn:dem":1149,
    "gn:feature_class":"P",
    "gn:feature_code":"PPL",
    "gn:name":"Zhutang",
    "gn:population":0,
    "gn:timezone":"Asia/Shanghai",
    "iso:country":"CN",
    "name:deu_x_preferred":[
        "Zhutang"
    ],
    "name:zho_x_preferred":[
        "\u7af9\u5858"
    ],
    "wof:name":"Zhutang",
    "wof:placetype":"locality"
},
  "geometry": {"coordinates":[105.035,26.0045],"type":"Point"}
}