{
  "type": "Feature",
  "properties": {
    "gn:admin1_code":"3.0",
    "gn:asciiname":"Xuezhushan",
    "gn:country_code":"CN",
    "gn:dem":538,
    "gn:feature_class":"P",
    "gn:feature_code":"PPL",
    "gn:name":"Xuezhushan",
    "gn:population":0,
    "gn:timezone":"Asia/Shanghai",
    "iso:country":"CN",
    "name:und_x_variant":[
        "\u96ea\u7af9\u5c71"
    ],
    "wof:name":"Xuezhushan",
    "wof:placetype":"locality"
},
  "geometry": {"coordinates":[115.46458,25.79134],"type":"Point"}
}