{
  "type": "Feature",
  "properties": {
    "gn:admin1_code":"18",
    "gn:asciiname":"Baitai",
    "gn:country_code":"CN",
    "gn:dem":792,
    "gn:feature_class":"P",
    "gn:feature_code":"PPL",
    "gn:name":"Baitai",
    "gn:population":0,
    "gn:timezone":"Asia/Shanghai",
    "iso:country":"CN",
    "name:zho_x_preferred":[
        "\u767d\u53f0"
    ],
    "wof:name":"Baitai",
    "wof:placetype":"locality"
},
  "geometry": {"coordinates":[107.14700000000001,28.8245],"type":"Point"}
}