{
  "type": "Feature",
  "properties": {
    "gn:admin1_code":"7.0",
    "gn:asciiname":"Xiayang",
    "gn:country_code":"CN",
    "gn:dem":345,
    "gn:feature_class":"P",
    "gn:feature_code":"PPLA4",
    "gn:name":"Xiayang",
    "gn:population":0,
    "gn:timezone":"Asia/Shanghai",
    "iso:country":"CN",
    "name:und_x_variant":[
        "Hsia-yang",
        "Xiayang",
        "\u590f\u9633",
        "Xiayang Xiang",
        "\u590f\u9633\u4e61"
    ],
    "name:zho_x_preferred":[
        "\u590f\u9633"
    ],
    "wof:name":"Xiayang",
    "wof:placetype":"locality"
},
  "geometry": {"coordinates":[117.45417,26.42876],"type":"Point"}
}