{
  "type": "Feature",
  "properties": {
    "gn:admin1_code":"8.0",
    "gn:asciiname":"Le'ancun",
    "gn:country_code":"CN",
    "gn:dem":182,
    "gn:feature_class":"P",
    "gn:feature_code":"PPL",
    "gn:name":"Le\u2019ancun",
    "gn:population":0,
    "gn:timezone":"Asia/Shanghai",
    "iso:country":"CN",
    "name:und_x_variant":[
        "Le\u2019ancun"
    ],
    "name:zho_x_preferred":[
        "\u4e50\u5b89\u6751"
    ],
    "wof:name":"Le'ancun",
    "wof:placetype":"locality"
},
  "geometry": {"coordinates":[125.50190000000001,46.20121],"type":"Point"}
}