{
  "type": "Feature",
  "properties": {
    "gn:admin1_code":"3.0",
    "gn:asciiname":"Gangxia",
    "gn:country_code":"CN",
    "gn:dem":132,
    "gn:feature_class":"P",
    "gn:feature_code":"PPL",
    "gn:name":"Gangxia",
    "gn:population":0,
    "gn:timezone":"Asia/Shanghai",
    "iso:country":"CN",
    "name:und_x_variant":[
        "\u6e2f\u4e0b",
        "Gangxiaxiang",
        "\u6e2f\u4e0b\u4e61"
    ],
    "wof:name":"Gangxia",
    "wof:placetype":"locality"
},
  "geometry": {"coordinates":[116.07170000000001,27.51366],"type":"Point"}
}