{
  "type": "Feature",
  "properties": {
    "gn:admin1_code":"22.0",
    "gn:asciiname":"Dongbajianfangcun",
    "gn:country_code":"CN",
    "gn:dem":32,
    "gn:feature_class":"P",
    "gn:feature_code":"PPL",
    "gn:name":"Dongbajianfangcun",
    "gn:population":0,
    "gn:timezone":"Asia/Shanghai",
    "iso:country":"CN",
    "name:zho_x_preferred":[
        "\u4e1c\u516b\u95f4\u623f\u6751"
    ],
    "wof:name":"Dongbajianfangcun",
    "wof:placetype":"locality"
},
  "geometry": {"coordinates":[116.50781000000001,39.9745],"type":"Point"}
}