{
  "type": "Feature",
  "properties": {
    "gn:admin1_code":"15.0",
    "gn:asciiname":"Yuchi",
    "gn:country_code":"CN",
    "gn:dem":1112,
    "gn:feature_class":"P",
    "gn:feature_code":"PPLA4",
    "gn:name":"Yuchi",
    "gn:population":0,
    "gn:timezone":"Asia/Shanghai",
    "iso:country":"CN",
    "name:cat_x_preferred":[
        "Yuchis"
    ],
    "name:deu_x_preferred":[
        "Yuchi"
    ],
    "name:fra_x_preferred":[
        "Yuchis"
    ],
    "name:hrv_x_preferred":[
        "Yuchi Indijanci"
    ],
    "name:lit_x_preferred":[
        "Ju\u010diai"
    ],
    "name:rus_x_preferred":[
        "\u042e\u0447\u0438"
    ],
    "name:spa_x_preferred":[
        "Yuchi"
    ],
    "name:und_x_variant":[
        "\u9c7c\u6c60"
    ],
    "wof:name":"Yuchi",
    "wof:placetype":"locality"
},
  "geometry": {"coordinates":[106.27166,33.83427],"type":"Point"}
}