{
  "type": "Feature",
  "properties": {
    "gn:admin1_code":"19.0",
    "gn:asciiname":"Miaojia",
    "gn:country_code":"CN",
    "gn:dem":3,
    "gn:feature_class":"P",
    "gn:feature_code":"PPL",
    "gn:name":"Miaojia",
    "gn:population":0,
    "gn:timezone":"Asia/Shanghai",
    "iso:country":"CN",
    "name:und_x_variant":[
        "\u82d7\u5bb6"
    ],
    "wof:name":"Miaojia",
    "wof:placetype":"locality"
},
  "geometry": {"coordinates":[122.18273000000001,40.78918],"type":"Point"}
}