{
  "type": "Feature",
  "properties": {
    "gn:admin1_code":"25.0",
    "gn:asciiname":"Shiqiao",
    "gn:cc2":"CN",
    "gn:country_code":"CN",
    "gn:dem":18,
    "gn:feature_class":"P",
    "gn:feature_code":"PPL",
    "gn:name":"Shiqiao",
    "gn:population":0,
    "gn:timezone":"Asia/Shanghai",
    "iso:country":"CN",
    "name:ceb_x_preferred":[
        "Shiqiao"
    ],
    "name:deu_x_preferred":[
        "Shiqiao"
    ],
    "name:swe_x_preferred":[
        "Shiqiao"
    ],
    "name:zho_x_preferred":[
        "\u77f3\u6865"
    ],
    "wof:name":"Shiqiao",
    "wof:placetype":"locality"
},
  "geometry": {"coordinates":[119.68129999999999,35.74831],"type":"Point"}
}