{
  "type": "Feature",
  "properties": {
    "gn:admin1_code":"29.0",
    "gn:asciiname":"Wachang Shangzhai",
    "gn:country_code":"CN",
    "gn:dem":2081,
    "gn:feature_class":"P",
    "gn:feature_code":"PPL",
    "gn:name":"Wachang Shangzhai",
    "gn:population":0,
    "gn:timezone":"Asia/Shanghai",
    "iso:country":"CN",
    "name:zho_x_preferred":[
        "\u74e6\u5382\u4e0a\u5be8"
    ],
    "wof:name":"Wachang Shangzhai",
    "wof:placetype":"locality"
},
  "geometry": {"coordinates":[103.81100000000001,24.0317],"type":"Point"}
}