{
  "type": "Feature",
  "properties": {
    "gn:admin1_code":"19.0",
    "gn:asciiname":"Xiaomadao",
    "gn:country_code":"CN",
    "gn:dem":12,
    "gn:feature_class":"P",
    "gn:feature_code":"PPL",
    "gn:name":"Xiaomadao",
    "gn:population":0,
    "gn:timezone":"Asia/Shanghai",
    "iso:country":"CN",
    "name:und_x_variant":[
        "\u5c0f\u9a6c\u9053"
    ],
    "name:zho_x_preferred":[
        "\u5c0f\u9a6c\u9053"
    ],
    "wof:name":"Xiaomadao",
    "wof:placetype":"locality"
},
  "geometry": {"coordinates":[121.44173000000001,41.07257],"type":"Point"}
}