{
  "type": "Feature",
  "properties": {
    "gn:admin1_code":"26.0",
    "gn:asciiname":"Baimasicun",
    "gn:country_code":"CN",
    "gn:dem":537,
    "gn:feature_class":"P",
    "gn:feature_code":"PPL",
    "gn:name":"Baimasicun",
    "gn:population":0,
    "gn:timezone":"Asia/Shanghai",
    "iso:country":"CN",
    "name:und_x_variant":[
        "\u767d\u9a6c\u5bfa\u6751"
    ],
    "wof:name":"Baimasicun",
    "wof:placetype":"locality"
},
  "geometry": {"coordinates":[106.96957,32.99368],"type":"Point"}
}