{
  "type": "Feature",
  "properties": {
    "gn:admin1_code":"5.0",
    "gn:asciiname":"Xianfengcun",
    "gn:country_code":"CN",
    "gn:dem":247,
    "gn:feature_class":"P",
    "gn:feature_code":"PPL",
    "gn:name":"Xianfengcun",
    "gn:population":0,
    "gn:timezone":"Asia/Shanghai",
    "iso:country":"CN",
    "name:zho_x_preferred":[
        "\u5148\u950b\u6751"
    ],
    "wof:name":"Xianfengcun",
    "wof:placetype":"locality"
},
  "geometry": {"coordinates":[125.17086999999999,44.82169],"type":"Point"}
}