{
  "type": "Feature",
  "properties": {
    "gn:admin1_code":"23.0",
    "gn:asciiname":"Xinhua Badui",
    "gn:country_code":"CN",
    "gn:dem":4,
    "gn:feature_class":"P",
    "gn:feature_code":"PPLF",
    "gn:name":"Xinhua Badui",
    "gn:population":0,
    "gn:timezone":"Asia/Shanghai",
    "iso:country":"CN",
    "name:und_x_variant":[
        "\u65b0\u534e\u516b\u961f"
    ],
    "wof:name":"Xinhua Badui",
    "wof:placetype":"locality"
},
  "geometry": {"coordinates":[121.71662000000001,30.88103],"type":"Point"}
}