{
  "type": "Feature",
  "properties": {
    "gn:admin1_code":"30",
    "gn:asciiname":"Xiapingkeng",
    "gn:country_code":"CN",
    "gn:dem":269,
    "gn:feature_class":"P",
    "gn:feature_code":"PPL",
    "gn:name":"Xiapingkeng",
    "gn:population":0,
    "gn:timezone":"Asia/Shanghai",
    "iso:country":"CN",
    "name:zho_x_preferred":[
        "\u4e0b\u576a\u5751"
    ],
    "wof:name":"Xiapingkeng",
    "wof:placetype":"locality"
},
  "geometry": {"coordinates":[116.63608000000001,24.27186],"type":"Point"}
}