{
  "type": "Feature",
  "properties": {
    "gn:admin1_code":"12.0",
    "gn:asciiname":"Lujiayoufang",
    "gn:country_code":"CN",
    "gn:dem":736,
    "gn:feature_class":"P",
    "gn:feature_code":"PPL",
    "gn:name":"Lujiayoufang",
    "gn:population":0,
    "gn:timezone":"Asia/Shanghai",
    "iso:country":"CN",
    "name:zho_x_preferred":[
        "\u9c81\u5bb6\u6cb9\u574a"
    ],
    "wof:name":"Lujiayoufang",
    "wof:placetype":"locality"
},
  "geometry": {"coordinates":[111.46568000000001,31.99059],"type":"Point"}
}