{
  "type": "Feature",
  "properties": {
    "gn:admin1_code":"32",
    "gn:asciiname":"Suojiangqiangzu",
    "gn:country_code":"CN",
    "gn:dem":907,
    "gn:feature_class":"P",
    "gn:feature_code":"PPL",
    "gn:name":"Suojiangqiangzu",
    "gn:population":0,
    "gn:timezone":"Asia/Shanghai",
    "iso:country":"CN",
    "name:und_x_variant":[
        "Suojiang",
        "Suojiangqiangzu"
    ],
    "name:zho_x_preferred":[
        "\u9501\u6c5f\u7f8c\u65cf"
    ],
    "wof:name":"Suojiangqiangzu",
    "wof:placetype":"locality"
},
  "geometry": {"coordinates":[104.46981,32.16534],"type":"Point"}
}