{
  "type": "Feature",
  "properties": {
    "gn:admin1_code":"24.0",
    "gn:asciiname":"Jingye'an",
    "gn:country_code":"CN",
    "gn:dem":1934,
    "gn:feature_class":"P",
    "gn:feature_code":"PPL",
    "gn:name":"Jingye\u2019an",
    "gn:population":0,
    "gn:timezone":"Asia/Shanghai",
    "iso:country":"CN",
    "name:und_x_variant":[
        "Jingye\u2019an"
    ],
    "name:zho_x_preferred":[
        "\u9759\u4e1a\u5eb5"
    ],
    "wof:name":"Jingye'an",
    "wof:placetype":"locality"
},
  "geometry": {"coordinates":[113.63334,38.97302],"type":"Point"}
}