{
  "type": "Feature",
  "properties": {
    "gn:admin1_code":"3.0",
    "gn:asciiname":"Chengzi Shukeng",
    "gn:country_code":"CN",
    "gn:dem":440,
    "gn:feature_class":"P",
    "gn:feature_code":"PPL",
    "gn:name":"Chengzi Shukeng",
    "gn:population":0,
    "gn:timezone":"Asia/Shanghai",
    "iso:country":"CN",
    "name:und_x_variant":[
        "\u67fd\u5b50\u6811\u5751"
    ],
    "wof:name":"Chengzi Shukeng",
    "wof:placetype":"locality"
},
  "geometry": {"coordinates":[117.6202,29.43767],"type":"Point"}
}