{
  "type": "Feature",
  "properties": {
    "gn:admin1_code":"10",
    "gn:asciiname":"Abugaimiao",
    "gn:country_code":"CN",
    "gn:dem":1524,
    "gn:feature_class":"P",
    "gn:feature_code":"PPL",
    "gn:name":"Abugaimiao",
    "gn:population":0,
    "gn:timezone":"Asia/Shanghai",
    "iso:country":"CN",
    "name:zho_x_preferred":[
        "\u963f\u4e0d\u76d6\u5e99"
    ],
    "wof:name":"Abugaimiao",
    "wof:placetype":"locality"
},
  "geometry": {"coordinates":[114.66800000000001,42.0104],"type":"Point"}
}