{
  "type": "Feature",
  "properties": {
    "gn:admin1_code":"26.0",
    "gn:asciiname":"Guanyinmiao",
    "gn:country_code":"CN",
    "gn:dem":737,
    "gn:feature_class":"P",
    "gn:feature_code":"PPL",
    "gn:name":"Guanyinmiao",
    "gn:population":0,
    "gn:timezone":"Asia/Shanghai",
    "iso:country":"CN",
    "name:zho_x_preferred":[
        "\u89c2\u97f3\u5e99"
    ],
    "wof:name":"Guanyinmiao",
    "wof:placetype":"locality"
},
  "geometry": {"coordinates":[107.51085999999999,32.8584],"type":"Point"}
}