{
  "type": "Feature",
  "properties": {
    "gn:admin1_code":"29.0",
    "gn:asciiname":"Hejiazhai",
    "gn:country_code":"CN",
    "gn:dem":1710,
    "gn:feature_class":"P",
    "gn:feature_code":"PPL",
    "gn:name":"Hejiazhai",
    "gn:population":0,
    "gn:timezone":"Asia/Shanghai",
    "iso:country":"CN",
    "name:zho_x_preferred":[
        "\u4f55\u5bb6\u5be8"
    ],
    "wof:name":"Hejiazhai",
    "wof:placetype":"locality"
},
  "geometry": {"coordinates":[99.13509999999999,23.8979],"type":"Point"}
}