{
  "type": "Feature",
  "properties": {
    "gn:admin1_code":"32.0",
    "gn:asciiname":"Laihu",
    "gn:country_code":"CN",
    "gn:dem":544,
    "gn:feature_class":"P",
    "gn:feature_code":"PPL",
    "gn:name":"Laihu",
    "gn:population":0,
    "gn:timezone":"Asia/Shanghai",
    "iso:country":"CN",
    "name:zho_x_preferred":[
        "\u7c41\u7b0f"
    ],
    "wof:name":"Laihu",
    "wof:placetype":"locality"
},
  "geometry": {"coordinates":[104.60599999999999,28.4101],"type":"Point"}
}