{
  "type": "Feature",
  "properties": {
    "gn:admin1_code":"10",
    "gn:asciiname":"Hanhezhuang",
    "gn:cc2":"CN",
    "gn:country_code":"CN",
    "gn:dem":104,
    "gn:feature_class":"P",
    "gn:feature_code":"PPL",
    "gn:name":"Hanhezhuang",
    "gn:population":0,
    "gn:timezone":"Asia/Shanghai",
    "iso:country":"CN",
    "name:und_x_variant":[
        "Han-ho-chuang",
        "Hanhezhuang"
    ],
    "wof:name":"Hanhezhuang",
    "wof:placetype":"locality"
},
  "geometry": {"coordinates":[117.77806,40.10694],"type":"Point"}
}