{
  "type": "Feature",
  "properties": {
    "gn:admin1_code":"2.0",
    "gn:asciiname":"Hengzhang",
    "gn:country_code":"CN",
    "gn:dem":3,
    "gn:feature_class":"P",
    "gn:feature_code":"PPL",
    "gn:name":"Hengzhang",
    "gn:population":0,
    "gn:timezone":"Asia/Shanghai",
    "iso:country":"CN",
    "name:zho_x_preferred":[
        "\u6a2a\u6da8"
    ],
    "wof:name":"Hengzhang",
    "wof:placetype":"locality"
},
  "geometry": {"coordinates":[121.42355000000001,29.78897000000001],"type":"Point"}
}