{
  "type": "Feature",
  "properties": {
    "gn:admin1_code":"15.0",
    "gn:asciiname":"Dongqiao",
    "gn:country_code":"CN",
    "gn:dem":2177,
    "gn:feature_class":"P",
    "gn:feature_code":"PPL",
    "gn:name":"Dongqiao",
    "gn:population":0,
    "gn:timezone":"Asia/Shanghai",
    "iso:country":"CN",
    "name:und_x_variant":[
        "\u4e1c\u6865"
    ],
    "wof:name":"Dongqiao",
    "wof:placetype":"locality"
},
  "geometry": {"coordinates":[104.26394999999999,34.80611],"type":"Point"}
}