{
  "type": "Feature",
  "properties": {
    "gn:admin1_code":"3",
    "gn:asciiname":"Zhugaoling",
    "gn:country_code":"CN",
    "gn:dem":252,
    "gn:feature_class":"P",
    "gn:feature_code":"PPL",
    "gn:name":"Zhugaoling",
    "gn:population":0,
    "gn:timezone":"Asia/Shanghai",
    "iso:country":"CN",
    "name:zho_x_preferred":[
        "\u7af9\u9ad8\u5cad"
    ],
    "wof:name":"Zhugaoling",
    "wof:placetype":"locality"
},
  "geometry": {"coordinates":[114.77200000000001,26.3501],"type":"Point"}
}