{
  "type": "Feature",
  "properties": {
    "gn:admin1_code":"21.0",
    "gn:asciiname":"Chahekou",
    "gn:country_code":"CN",
    "gn:dem":1345,
    "gn:feature_class":"P",
    "gn:feature_code":"PPL",
    "gn:name":"Chahekou",
    "gn:population":0,
    "gn:timezone":"Asia/Shanghai",
    "iso:country":"CN",
    "name:zho_x_preferred":[
        "\u6c4a\u6cb3\u53e3"
    ],
    "wof:name":"Chahekou",
    "wof:placetype":"locality"
},
  "geometry": {"coordinates":[104.913,37.3998],"type":"Point"}
}