{
  "type": "Feature",
  "properties": {
    "gn:admin1_code":"25.0",
    "gn:asciiname":"Xiaguantun",
    "gn:cc2":"CN",
    "gn:country_code":"CN",
    "gn:dem":37,
    "gn:feature_class":"P",
    "gn:feature_code":"PPL",
    "gn:name":"Xiaguantun",
    "gn:population":0,
    "gn:timezone":"Asia/Shanghai",
    "iso:country":"CN",
    "name:und_x_variant":[
        "Hsia-kuan-t\u2019un",
        "Xiaguantun"
    ],
    "wof:name":"Xiaguantun",
    "wof:placetype":"locality"
},
  "geometry": {"coordinates":[116.16667,35.36667],"type":"Point"}
}