{
  "type": "Feature",
  "properties": {
    "gn:admin1_code":"04",
    "gn:asciiname":"Tangzhuang",
    "gn:country_code":"CN",
    "gn:dem":6,
    "gn:feature_class":"P",
    "gn:feature_code":"PPL",
    "gn:name":"Tangzhuang",
    "gn:population":0,
    "gn:timezone":"Asia/Shanghai",
    "iso:country":"CN",
    "name:ita_x_preferred":[
        "Tangzhuang"
    ],
    "name:zha_x_preferred":[
        "Buhdangzcangh"
    ],
    "wof:name":"Tangzhuang",
    "wof:placetype":"locality"
},
  "geometry": {"coordinates":[120.67638999999998,31.33361],"type":"Point"}
}