{
  "type": "Feature",
  "properties": {
    "gn:admin1_code":"9.0",
    "gn:asciiname":"Yuzhongyao",
    "gn:country_code":"CN",
    "gn:dem":148,
    "gn:feature_class":"P",
    "gn:feature_code":"PPL",
    "gn:name":"Yuzhongyao",
    "gn:population":0,
    "gn:timezone":"Asia/Shanghai",
    "iso:country":"CN",
    "name:zho_x_preferred":[
        "\u4f59\u4e2d\u7a91"
    ],
    "wof:name":"Yuzhongyao",
    "wof:placetype":"locality"
},
  "geometry": {"coordinates":[113.82901,32.50323],"type":"Point"}
}