{
  "type": "Feature",
  "properties": {
    "gn:country":"CN",
    "gn:fcode":"ADM3",
    "gn:population":0,
    "iso:country":"CN",
    "name:und_x_variant":[
        "Ho-p\u2019u Hsien"
    ],
    "qs_pg:aaroncc":"CN",
    "qs_pg:gn_country":"CN",
    "qs_pg:gn_fcode":"ADM3",
    "qs_pg:gn_pop":0,
    "qs_pg:name":"Hepu Xian",
    "qs_pg:photos_9r":0,
    "qs_pg:photos_sr":0,
    "qs_pg:pop_sr":0,
    "qs_pg:qs_pg_placetype":"localadmin",
    "wof:name":"Hepu Xian",
    "wof:placetype":"localadmin"
},
  "geometry": {"coordinates":[109.15000000000001,21.68333],"type":"Point"}
}