{
  "type": "Feature",
  "properties": {
    "gn:admin1_code":"12.0",
    "gn:asciiname":"Songjiachong",
    "gn:country_code":"CN",
    "gn:dem":72,
    "gn:feature_class":"P",
    "gn:feature_code":"PPL",
    "gn:name":"Songjiachong",
    "gn:population":0,
    "gn:timezone":"Asia/Shanghai",
    "iso:country":"CN",
    "name:zho_x_preferred":[
        "\u5b8b\u5bb6\u51b2"
    ],
    "wof:name":"Songjiachong",
    "wof:placetype":"locality"
},
  "geometry": {"coordinates":[113.20354,30.90596],"type":"Point"}
}