{
  "type": "Feature",
  "properties": {
    "gn:admin1_code":"24.0",
    "gn:asciiname":"Mawacun",
    "gn:country_code":"CN",
    "gn:dem":1004,
    "gn:feature_class":"P",
    "gn:feature_code":"PPL",
    "gn:name":"Mawacun",
    "gn:population":0,
    "gn:timezone":"Asia/Shanghai",
    "iso:country":"CN",
    "name:zho_x_preferred":[
        "\u9ebb\u6d3c\u6751"
    ],
    "wof:name":"Mawacun",
    "wof:placetype":"locality"
},
  "geometry": {"coordinates":[110.7574,38.25197],"type":"Point"}
}