{
  "type": "Feature",
  "properties": {
    "gn:admin1_code":"3.0",
    "gn:asciiname":"Banzhukeng",
    "gn:country_code":"CN",
    "gn:dem":274,
    "gn:feature_class":"P",
    "gn:feature_code":"PPL",
    "gn:name":"Banzhukeng",
    "gn:population":0,
    "gn:timezone":"Asia/Shanghai",
    "iso:country":"CN",
    "name:und_x_variant":[
        "\u6591\u7af9\u5751"
    ],
    "wof:name":"Banzhukeng",
    "wof:placetype":"locality"
},
  "geometry": {"coordinates":[115.66498,25.31423],"type":"Point"}
}