{
  "type": "Feature",
  "properties": {
    "gn:admin1_code":"3.0",
    "gn:asciiname":"Wenqiao",
    "gn:country_code":"CN",
    "gn:dem":22,
    "gn:feature_class":"P",
    "gn:feature_code":"PPLA4",
    "gn:name":"Wenqiao",
    "gn:population":0,
    "gn:timezone":"Asia/Shanghai",
    "iso:country":"CN",
    "name:und_x_variant":[
        "Wen-ch\u2019iao",
        "Wenqiao",
        "\u6587\u6865",
        "Wenqiao Xiang",
        "\u6587\u6865\u4e61"
    ],
    "wof:name":"Wenqiao",
    "wof:placetype":"locality"
},
  "geometry": {"coordinates":[116.29864999999999,29.66143],"type":"Point"}
}