{
  "type": "Feature",
  "properties": {
    "gn:admin1_code":"8.0",
    "gn:asciiname":"Doupaichangtun",
    "gn:country_code":"CN",
    "gn:dem":272,
    "gn:feature_class":"P",
    "gn:feature_code":"PPL",
    "gn:name":"Doupaichangtun",
    "gn:population":0,
    "gn:timezone":"Asia/Shanghai",
    "iso:country":"CN",
    "name:zho_x_preferred":[
        "\u7aa6\u6392\u957f\u5c6f"
    ],
    "wof:name":"Doupaichangtun",
    "wof:placetype":"locality"
},
  "geometry": {"coordinates":[125.62036999999999,48.43508],"type":"Point"}
}