{
  "type": "Feature",
  "properties": {
    "gn:admin1_code":"31",
    "gn:asciiname":"Daping",
    "gn:country_code":"CN",
    "gn:dem":168,
    "gn:feature_class":"P",
    "gn:feature_code":"PPL",
    "gn:name":"Daping",
    "gn:population":0,
    "gn:timezone":"Asia/Shanghai",
    "iso:country":"CN",
    "name:und_x_variant":[
        "\u5927\u5e73",
        "Dapinsandui"
    ],
    "wof:name":"Daping",
    "wof:placetype":"locality"
},
  "geometry": {"coordinates":[109.87782,19.11676],"type":"Point"}
}