{
  "type": "Feature",
  "properties": {
    "gn:admin1_code":"2.0",
    "gn:asciiname":"Shantangling",
    "gn:country_code":"CN",
    "gn:dem":74,
    "gn:feature_class":"P",
    "gn:feature_code":"PPL",
    "gn:name":"Shantangling",
    "gn:population":0,
    "gn:timezone":"Asia/Shanghai",
    "iso:country":"CN",
    "name:zho_x_preferred":[
        "\u5c71\u5858\u5cad"
    ],
    "wof:name":"Shantangling",
    "wof:placetype":"locality"
},
  "geometry": {"coordinates":[119.93427,28.47215],"type":"Point"}
}