{
  "type": "Feature",
  "properties": {
    "gn:admin1_code":"4.0",
    "gn:asciiname":"Gaojiayuan",
    "gn:country_code":"CN",
    "gn:dem":4,
    "gn:feature_class":"P",
    "gn:feature_code":"PPL",
    "gn:name":"Gaojiayuan",
    "gn:population":0,
    "gn:timezone":"Asia/Shanghai",
    "iso:country":"CN",
    "name:zho_x_preferred":[
        "\u9ad8\u5bb6\u56ed"
    ],
    "wof:name":"Gaojiayuan",
    "wof:placetype":"locality"
},
  "geometry": {"coordinates":[120.81108,32.24822],"type":"Point"}
}