{
  "type": "Feature",
  "properties": {
    "gn:admin1_code":"19.0",
    "gn:asciiname":"Sanwangbucun",
    "gn:country_code":"CN",
    "gn:dem":14,
    "gn:feature_class":"P",
    "gn:feature_code":"PPL",
    "gn:name":"Sanwangbucun",
    "gn:population":0,
    "gn:timezone":"Asia/Shanghai",
    "iso:country":"CN",
    "name:zho_x_preferred":[
        "\u4e09\u738b\u5821\u6751"
    ],
    "wof:name":"Sanwangbucun",
    "wof:placetype":"locality"
},
  "geometry": {"coordinates":[123.00582,41.69995],"type":"Point"}
}