{
  "type": "Feature",
  "properties": {
    "gn:admin1_code":"11",
    "gn:asciiname":"Wuyahe",
    "gn:country_code":"CN",
    "gn:dem":910,
    "gn:feature_class":"P",
    "gn:feature_code":"PPLA4",
    "gn:name":"Wuyahe",
    "gn:population":0,
    "gn:timezone":"Asia/Shanghai",
    "iso:country":"CN",
    "name:und_x_variant":[
        "Wuya Xiang",
        "Wuyahe"
    ],
    "name:zho_x_preferred":[
        "\u4e4c\u9e26\u6cb3"
    ],
    "name:zho_x_variant":[
        "\u4e4c\u9e26\u4e61"
    ],
    "wof:name":"Wuyahe",
    "wof:placetype":"locality"
},
  "geometry": {"coordinates":[109.71241000000001,29.57652],"type":"Point"}
}