{
  "type": "Feature",
  "properties": {
    "gn:admin1_code":"8.0",
    "gn:asciiname":"Gujialiangzi",
    "gn:country_code":"CN",
    "gn:dem":139,
    "gn:feature_class":"P",
    "gn:feature_code":"PPL",
    "gn:name":"Gujialiangzi",
    "gn:population":0,
    "gn:timezone":"Asia/Shanghai",
    "iso:country":"CN",
    "name:zho_x_preferred":[
        "\u987e\u5bb6\u4eae\u5b50"
    ],
    "wof:name":"Gujialiangzi",
    "wof:placetype":"locality"
},
  "geometry": {"coordinates":[123.47441999999999,46.67782],"type":"Point"}
}