{
  "type": "Feature",
  "properties": {
    "gn:admin1_code":"32",
    "gn:asciiname":"Yuanjiayan",
    "gn:country_code":"CN",
    "gn:dem":636,
    "gn:feature_class":"P",
    "gn:feature_code":"PPL",
    "gn:name":"Yuanjiayan",
    "gn:population":0,
    "gn:timezone":"Asia/Shanghai",
    "iso:country":"CN",
    "name:zho_x_preferred":[
        "\u8881\u5bb6\u5ca9"
    ],
    "wof:name":"Yuanjiayan",
    "wof:placetype":"locality"
},
  "geometry": {"coordinates":[105.61499000000001,31.61249],"type":"Point"}
}