{
  "type": "Feature",
  "properties": {
    "gn:admin1_code":"18.0",
    "gn:asciiname":"Manshanjiao",
    "gn:country_code":"CN",
    "gn:dem":599,
    "gn:feature_class":"P",
    "gn:feature_code":"PPL",
    "gn:name":"Manshanjiao",
    "gn:population":0,
    "gn:timezone":"Asia/Shanghai",
    "iso:country":"CN",
    "name:zho_x_preferred":[
        "\u6f2b\u5c71\u811a"
    ],
    "wof:name":"Manshanjiao",
    "wof:placetype":"locality"
},
  "geometry": {"coordinates":[109.19499999999999,26.1981],"type":"Point"}
}