{
  "type": "Feature",
  "properties": {
    "gn:admin1_code":"2.0",
    "gn:asciiname":"Xinyan",
    "gn:country_code":"CN",
    "gn:dem":154,
    "gn:feature_class":"P",
    "gn:feature_code":"PPL",
    "gn:name":"Xinyan",
    "gn:population":0,
    "gn:timezone":"Asia/Shanghai",
    "iso:country":"CN",
    "name:zho_x_preferred":[
        "\u65b0\u5ca9"
    ],
    "wof:name":"Xinyan",
    "wof:placetype":"locality"
},
  "geometry": {"coordinates":[120.62860000000001,27.81374000000001],"type":"Point"}
}