{
  "type": "Feature",
  "properties": {
    "gn:admin1_code":"12.0",
    "gn:asciiname":"Matang",
    "gn:country_code":"CN",
    "gn:dem":51,
    "gn:feature_class":"P",
    "gn:feature_code":"PPL",
    "gn:name":"Matang",
    "gn:population":0,
    "gn:timezone":"Asia/Shanghai",
    "iso:country":"CN",
    "name:zho_x_preferred":[
        "Matang"
    ],
    "name:zho_x_variant":[
        "\u9ebb\u5858"
    ],
    "wof:name":"Matang",
    "wof:placetype":"locality"
},
  "geometry": {"coordinates":[114.38642,29.83537],"type":"Point"}
}