{
  "type": "Feature",
  "properties": {
    "gn:admin1_code":"7",
    "gn:asciiname":"Wugengliao",
    "gn:country_code":"CN",
    "gn:dem":952,
    "gn:feature_class":"P",
    "gn:feature_code":"PPL",
    "gn:name":"Wugengliao",
    "gn:population":0,
    "gn:timezone":"Asia/Shanghai",
    "iso:country":"CN",
    "name:zho_x_preferred":[
        "\u4e94\u66f4\u5bee"
    ],
    "wof:name":"Wugengliao",
    "wof:placetype":"locality"
},
  "geometry": {"coordinates":[117.06879000000001,24.59271],"type":"Point"}
}