{
  "type": "Feature",
  "properties": {
    "gn:admin1_code":"26.0",
    "gn:asciiname":"Gaotianchi",
    "gn:country_code":"CN",
    "gn:dem":1543,
    "gn:feature_class":"P",
    "gn:feature_code":"PPL",
    "gn:name":"Gaotianchi",
    "gn:population":0,
    "gn:timezone":"Asia/Shanghai",
    "iso:country":"CN",
    "name:zho_x_preferred":[
        "\u9ad8\u5929\u6c60"
    ],
    "wof:name":"Gaotianchi",
    "wof:placetype":"locality"
},
  "geometry": {"coordinates":[107.34529999999999,37.16049],"type":"Point"}
}