{
  "type": "Feature",
  "properties": {
    "gn:admin1_code":"24",
    "gn:asciiname":"Shangwang",
    "gn:cc2":"CN",
    "gn:country_code":"CN",
    "gn:dem":945,
    "gn:feature_class":"P",
    "gn:feature_code":"PPL",
    "gn:name":"Shangwang",
    "gn:population":0,
    "gn:timezone":"Asia/Shanghai",
    "iso:country":"CN",
    "name:und_x_variant":[
        "Shang-wang-ts\u2019un",
        "Shangwang"
    ],
    "wof:name":"Shangwang",
    "wof:placetype":"locality"
},
  "geometry": {"coordinates":[112.67278,38.89028],"type":"Point"}
}