{
  "type": "Feature",
  "properties": {
    "gn:admin1_code":"16.0",
    "gn:asciiname":"Fenjie",
    "gn:country_code":"CN",
    "gn:dem":78,
    "gn:feature_class":"P",
    "gn:feature_code":"PPL",
    "gn:name":"Fenjie",
    "gn:population":0,
    "gn:timezone":"Asia/Shanghai",
    "iso:country":"CN",
    "name:zho_x_preferred":[
        "\u5206\u754c"
    ],
    "wof:name":"Fenjie",
    "wof:placetype":"locality"
},
  "geometry": {"coordinates":[110.16500000000001,22.5536],"type":"Point"}
}