{
  "type": "Feature",
  "properties": {
    "gn:admin1_code":"29.0",
    "gn:asciiname":"Dashitou",
    "gn:country_code":"CN",
    "gn:dem":2038,
    "gn:feature_class":"P",
    "gn:feature_code":"PPL",
    "gn:name":"Dashitou",
    "gn:population":0,
    "gn:timezone":"Asia/Shanghai",
    "iso:country":"CN",
    "name:zho_x_preferred":[
        "\u5927\u77f3\u5934"
    ],
    "wof:name":"Dashitou",
    "wof:placetype":"locality"
},
  "geometry": {"coordinates":[99.1478,24.588],"type":"Point"}
}