{
  "type": "Feature",
  "properties": {
    "gn:admin1_code":"19.0",
    "gn:asciiname":"Koujiagou",
    "gn:country_code":"CN",
    "gn:dem":374,
    "gn:feature_class":"P",
    "gn:feature_code":"PPL",
    "gn:name":"Koujiagou",
    "gn:population":0,
    "gn:timezone":"Asia/Shanghai",
    "iso:country":"CN",
    "name:zho_x_preferred":[
        "\u5bc7\u5bb6\u6c9f"
    ],
    "wof:name":"Koujiagou",
    "wof:placetype":"locality"
},
  "geometry": {"coordinates":[119.64700000000001,41.1041],"type":"Point"}
}