{
  "type": "Feature",
  "properties": {
    "gn:admin1_code":"15.0",
    "gn:asciiname":"Digu",
    "gn:country_code":"CN",
    "gn:dem":2597,
    "gn:feature_class":"P",
    "gn:feature_code":"PPL",
    "gn:name":"Digu",
    "gn:population":0,
    "gn:timezone":"Asia/Shanghai",
    "iso:country":"CN",
    "name:und_x_variant":[
        "\u5e95\u56fa"
    ],
    "wof:name":"Digu",
    "wof:placetype":"locality"
},
  "geometry": {"coordinates":[104.13961,34.57636],"type":"Point"}
}