{
  "type": "Feature",
  "properties": {
    "gn:admin1_code":"3",
    "gn:asciiname":"Potang",
    "gn:country_code":"CN",
    "gn:dem":497,
    "gn:feature_class":"P",
    "gn:feature_code":"PPL",
    "gn:name":"Potang",
    "gn:population":0,
    "gn:timezone":"Asia/Shanghai",
    "iso:country":"CN",
    "name:zho_x_preferred":[
        "\u7834\u5858"
    ],
    "wof:name":"Potang",
    "wof:placetype":"locality"
},
  "geometry": {"coordinates":[114.58799999999999,26.1955],"type":"Point"}
}