{
  "type": "Feature",
  "properties": {
    "gn:admin1_code":"3.0",
    "gn:asciiname":"Lingxi Wangjia",
    "gn:country_code":"CN",
    "gn:dem":672,
    "gn:feature_class":"P",
    "gn:feature_code":"PPL",
    "gn:name":"Lingxi Wangjia",
    "gn:population":0,
    "gn:timezone":"Asia/Shanghai",
    "iso:country":"CN",
    "name:zho_x_preferred":[
        "\u5cad\u897f\u6c6a\u5bb6"
    ],
    "wof:name":"Lingxi Wangjia",
    "wof:placetype":"locality"
},
  "geometry": {"coordinates":[117.25184,27.97441],"type":"Point"}
}