{
  "type": "Feature",
  "properties": {
    "gn:admin1_code":"26.0",
    "gn:asciiname":"Baishuwan",
    "gn:country_code":"CN",
    "gn:dem":919,
    "gn:feature_class":"P",
    "gn:feature_code":"PPL",
    "gn:name":"Baishuwan",
    "gn:population":0,
    "gn:timezone":"Asia/Shanghai",
    "iso:country":"CN",
    "name:und_x_variant":[
        "\u67cf\u6811\u6e7e"
    ],
    "wof:name":"Baishuwan",
    "wof:placetype":"locality"
},
  "geometry": {"coordinates":[107.87061,33.32757],"type":"Point"}
}