{
  "type": "Feature",
  "properties": {
    "gn:admin1_code":"22.0",
    "gn:asciiname":"Tielucun",
    "gn:country_code":"CN",
    "gn:dem":476,
    "gn:feature_class":"P",
    "gn:feature_code":"PPL",
    "gn:name":"Tielucun",
    "gn:population":0,
    "gn:timezone":"Asia/Shanghai",
    "iso:country":"CN",
    "name:zho_x_preferred":[
        "\u94c1\u7089\u6751"
    ],
    "wof:name":"Tielucun",
    "wof:placetype":"locality"
},
  "geometry": {"coordinates":[116.17099,40.39169],"type":"Point"}
}