{
  "type": "Feature",
  "properties": {
    "gn:admin1_code":"3.0",
    "gn:asciiname":"Shangqumaliao",
    "gn:country_code":"CN",
    "gn:dem":873,
    "gn:feature_class":"P",
    "gn:feature_code":"PPL",
    "gn:name":"Shangqumaliao",
    "gn:population":0,
    "gn:timezone":"Asia/Shanghai",
    "iso:country":"CN",
    "name:und_x_variant":[
        "\u4e0a\u66f2\u9a6c\u5bee"
    ],
    "wof:name":"Shangqumaliao",
    "wof:placetype":"locality"
},
  "geometry": {"coordinates":[116.49426,26.54316],"type":"Point"}
}