{
  "type": "Feature",
  "properties": {
    "gn:admin1_code":"29.0",
    "gn:asciiname":"Gubi",
    "gn:country_code":"CN",
    "gn:dem":1754,
    "gn:feature_class":"P",
    "gn:feature_code":"PPL",
    "gn:name":"Gubi",
    "gn:population":0,
    "gn:timezone":"Asia/Shanghai",
    "iso:country":"CN",
    "name:zho_x_preferred":[
        "\u53e4\u5fc5"
    ],
    "wof:name":"Gubi",
    "wof:placetype":"locality"
},
  "geometry": {"coordinates":[104.63500000000001,25.2688],"type":"Point"}
}