{
  "type": "Feature",
  "properties": {
    "gn:admin1_code":"32.0",
    "gn:asciiname":"Shangbanligou",
    "gn:country_code":"CN",
    "gn:dem":1146,
    "gn:feature_class":"P",
    "gn:feature_code":"PPL",
    "gn:name":"Shangbanligou",
    "gn:population":0,
    "gn:timezone":"Asia/Shanghai",
    "iso:country":"CN",
    "name:zho_x_preferred":[
        "\u4e0a\u677f\u6817\u6c9f"
    ],
    "wof:name":"Shangbanligou",
    "wof:placetype":"locality"
},
  "geometry": {"coordinates":[105.63121,27.72789],"type":"Point"}
}