{
  "type": "Feature",
  "properties": {
    "gn:admin1_code":"12.0",
    "gn:asciiname":"Xingjia Caofang",
    "gn:country_code":"CN",
    "gn:dem":102,
    "gn:feature_class":"P",
    "gn:feature_code":"PPL",
    "gn:name":"Xingjia Caofang",
    "gn:population":0,
    "gn:timezone":"Asia/Shanghai",
    "iso:country":"CN",
    "name:zho_x_preferred":[
        "Xingjia Caofang"
    ],
    "name:zho_x_variant":[
        "\u90a2\u5bb6\u69fd\u623f"
    ],
    "wof:name":"Xingjia Caofang",
    "wof:placetype":"locality"
},
  "geometry": {"coordinates":[111.81632,30.92737],"type":"Point"}
}