{
  "type": "Feature",
  "properties": {
    "gn:admin1_code":"26.0",
    "gn:asciiname":"Dadongcun",
    "gn:country_code":"CN",
    "gn:dem":444,
    "gn:feature_class":"P",
    "gn:feature_code":"PPL",
    "gn:name":"Dadongcun",
    "gn:population":0,
    "gn:timezone":"Asia/Shanghai",
    "iso:country":"CN",
    "name:zho_x_preferred":[
        "\u5927\u4e1c\u6751"
    ],
    "wof:name":"Dadongcun",
    "wof:placetype":"locality"
},
  "geometry": {"coordinates":[108.2201,34.14002],"type":"Point"}
}