{
  "type": "Feature",
  "properties": {
    "gn:admin1_code":"29.0",
    "gn:asciiname":"Jipaibu",
    "gn:country_code":"CN",
    "gn:dem":2878,
    "gn:feature_class":"P",
    "gn:feature_code":"PPL",
    "gn:name":"Jipaibu",
    "gn:population":0,
    "gn:timezone":"Asia/Shanghai",
    "iso:country":"CN",
    "name:zho_x_preferred":[
        "\u5409\u6392\u8865"
    ],
    "wof:name":"Jipaibu",
    "wof:placetype":"locality"
},
  "geometry": {"coordinates":[100.369,27.5507],"type":"Point"}
}