{
  "type": "Feature",
  "properties": {
    "gn:admin1_code":"32.0",
    "gn:asciiname":"Yuheba",
    "gn:country_code":"CN",
    "gn:dem":484,
    "gn:feature_class":"P",
    "gn:feature_code":"PPL",
    "gn:name":"Yuheba",
    "gn:population":0,
    "gn:timezone":"Asia/Shanghai",
    "iso:country":"CN",
    "name:zho_x_preferred":[
        "\u4f59\u6cb3\u575d"
    ],
    "wof:name":"Yuheba",
    "wof:placetype":"locality"
},
  "geometry": {"coordinates":[103.79609000000001,30.52499000000001],"type":"Point"}
}