{
  "type": "Feature",
  "properties": {
    "gn:admin1_code":"29",
    "gn:asciiname":"Sanqiutian",
    "gn:country_code":"CN",
    "gn:dem":2049,
    "gn:feature_class":"P",
    "gn:feature_code":"PPL",
    "gn:name":"Sanqiutian",
    "gn:population":0,
    "gn:timezone":"Asia/Shanghai",
    "iso:country":"CN",
    "name:zho_x_preferred":[
        "\u4e09\u4e18\u7530"
    ],
    "wof:name":"Sanqiutian",
    "wof:placetype":"locality"
},
  "geometry": {"coordinates":[102.922,24.9698],"type":"Point"}
}