{
  "type": "Feature",
  "properties": {
    "gn:admin1_code":"32.0",
    "gn:asciiname":"Shangfangzi",
    "gn:country_code":"CN",
    "gn:dem":272,
    "gn:feature_class":"P",
    "gn:feature_code":"PPL",
    "gn:name":"Shangfangzi",
    "gn:population":0,
    "gn:timezone":"Asia/Shanghai",
    "iso:country":"CN",
    "name:zho_x_preferred":[
        "\u4e0a\u623f\u5b50"
    ],
    "wof:name":"Shangfangzi",
    "wof:placetype":"locality"
},
  "geometry": {"coordinates":[105.036,28.8273],"type":"Point"}
}