{
  "type": "Feature",
  "properties": {
    "gn:admin1_code":"25.0",
    "gn:asciiname":"Longshanhou",
    "gn:country_code":"CN",
    "gn:dem":13,
    "gn:feature_class":"P",
    "gn:feature_code":"PPL",
    "gn:name":"Longshanhou",
    "gn:population":0,
    "gn:timezone":"Asia/Shanghai",
    "iso:country":"CN",
    "name:zho_x_preferred":[
        "\u9f99\u5c71\u540e"
    ],
    "wof:name":"Longshanhou",
    "wof:placetype":"locality"
},
  "geometry": {"coordinates":[122.42385,37.00081],"type":"Point"}
}