{
  "type": "Feature",
  "properties": {
    "gn:admin1_code":"12.0",
    "gn:asciiname":"Zengjia Zhuyuan",
    "gn:country_code":"CN",
    "gn:dem":44,
    "gn:feature_class":"P",
    "gn:feature_code":"PPL",
    "gn:name":"Zengjia Zhuyuan",
    "gn:population":0,
    "gn:timezone":"Asia/Shanghai",
    "iso:country":"CN",
    "name:zho_x_preferred":[
        "Zengjia Zhuyuan"
    ],
    "name:zho_x_variant":[
        "\u66fe\u5bb6\u7af9\u56ed"
    ],
    "wof:name":"Zengjia Zhuyuan",
    "wof:placetype":"locality"
},
  "geometry": {"coordinates":[111.81116000000002,30.40511],"type":"Point"}
}