{
  "type": "Feature",
  "properties": {
    "gn:admin1_code":"32.0",
    "gn:asciiname":"Yupingshan",
    "gn:country_code":"CN",
    "gn:dem":406,
    "gn:feature_class":"P",
    "gn:feature_code":"PPL",
    "gn:name":"Yupingshan",
    "gn:population":0,
    "gn:timezone":"Asia/Shanghai",
    "iso:country":"CN",
    "name:zho_x_preferred":[
        "\u7389\u5c4f\u5c71"
    ],
    "wof:name":"Yupingshan",
    "wof:placetype":"locality"
},
  "geometry": {"coordinates":[106.535,30.4854],"type":"Point"}
}