{
  "type": "Feature",
  "properties": {
    "gn:admin1_code":"9.0",
    "gn:asciiname":"Yanggoukou",
    "gn:country_code":"CN",
    "gn:dem":428,
    "gn:feature_class":"P",
    "gn:feature_code":"PPL",
    "gn:name":"Yanggoukou",
    "gn:population":0,
    "gn:timezone":"Asia/Shanghai",
    "iso:country":"CN",
    "name:zho_x_preferred":[
        "\u6768\u6c9f\u53e3"
    ],
    "wof:name":"Yanggoukou",
    "wof:placetype":"locality"
},
  "geometry": {"coordinates":[111.28671,33.16469],"type":"Point"}
}