{
  "type": "Feature",
  "properties": {
    "gn:admin1_code":"15.0",
    "gn:asciiname":"Xianyuan",
    "gn:country_code":"CN",
    "gn:dem":1436,
    "gn:feature_class":"P",
    "gn:feature_code":"PPL",
    "gn:name":"Xianyuan",
    "gn:population":0,
    "gn:timezone":"Asia/Shanghai",
    "iso:country":"CN",
    "name:und_x_variant":[
        "\u5baa\u586c"
    ],
    "wof:name":"Xianyuan",
    "wof:placetype":"locality"
},
  "geometry": {"coordinates":[107.80125,36.21238],"type":"Point"}
}