{
  "type": "Feature",
  "properties": {
    "gn:admin1_code":"4.0",
    "gn:asciiname":"Guduncun",
    "gn:country_code":"CN",
    "gn:dem":14,
    "gn:feature_class":"P",
    "gn:feature_code":"PPL",
    "gn:name":"Guduncun",
    "gn:population":0,
    "gn:timezone":"Asia/Shanghai",
    "iso:country":"CN",
    "name:zho_x_preferred":[
        "\u53e4\u58a9\u6751"
    ],
    "wof:name":"Guduncun",
    "wof:placetype":"locality"
},
  "geometry": {"coordinates":[118.77173000000001,33.88647],"type":"Point"}
}