{
  "type": "Feature",
  "properties": {
    "gn:admin1_code":"24.0",
    "gn:asciiname":"Xikouzi",
    "gn:country_code":"CN",
    "gn:dem":1499,
    "gn:feature_class":"P",
    "gn:feature_code":"PPL",
    "gn:name":"Xikouzi",
    "gn:population":0,
    "gn:timezone":"Asia/Shanghai",
    "iso:country":"CN",
    "name:und_x_variant":[
        "\u897f\u53e3\u5b50"
    ],
    "name:zho_x_preferred":[
        "\u897f\u53e3\u5b50"
    ],
    "wof:name":"Xikouzi",
    "wof:placetype":"locality"
},
  "geometry": {"coordinates":[112.15727,39.07049],"type":"Point"}
}