{
  "type": "Feature",
  "properties": {
    "gn:admin1_code":"6.0",
    "gn:asciiname":"Mashiduo",
    "gn:country_code":"CN",
    "gn:dem":2849,
    "gn:feature_class":"P",
    "gn:feature_code":"PPL",
    "gn:name":"Mashiduo",
    "gn:population":0,
    "gn:timezone":"Asia/Shanghai",
    "iso:country":"CN",
    "name:und_x_variant":[
        "\u9a6c\u4ec0\u591a"
    ],
    "wof:name":"Mashiduo",
    "wof:placetype":"locality"
},
  "geometry": {"coordinates":[102.08203,35.77664],"type":"Point"}
}