{
  "type": "Feature",
  "properties": {
    "gn:admin1_code":"19.0",
    "gn:asciiname":"Zhangtun",
    "gn:country_code":"CN",
    "gn:dem":38,
    "gn:feature_class":"P",
    "gn:feature_code":"PPL",
    "gn:name":"Zhangtun",
    "gn:population":0,
    "gn:timezone":"Asia/Shanghai",
    "iso:country":"CN",
    "name:und_x_variant":[
        "\u5f20\u5c6f"
    ],
    "name:zho_x_preferred":[
        "\u5f20\u5c6f"
    ],
    "wof:name":"Zhangtun",
    "wof:placetype":"locality"
},
  "geometry": {"coordinates":[122.43548,39.76467],"type":"Point"}
}