{
  "type": "Feature",
  "properties": {
    "gn:admin1_code":"19.0",
    "gn:asciiname":"Donggang",
    "gn:country_code":"CN",
    "gn:dem":33,
    "gn:feature_class":"P",
    "gn:feature_code":"PPL",
    "gn:name":"Donggang",
    "gn:population":0,
    "gn:timezone":"Asia/Shanghai",
    "iso:country":"CN",
    "name:ceb_x_preferred":[
        "Donggang"
    ],
    "name:deu_x_preferred":[
        "Donggang"
    ],
    "name:fra_x_preferred":[
        "Donggang"
    ],
    "name:nor_x_preferred":[
        "Donggang"
    ],
    "name:swe_x_preferred":[
        "Donggang"
    ],
    "name:zho_x_preferred":[
        "\u4e1c\u5c97"
    ],
    "wof:name":"Donggang",
    "wof:placetype":"locality"
},
  "geometry": {"coordinates":[122.72790999999999,41.95354],"type":"Point"}
}