{
  "type": "Feature",
  "properties": {
    "gn:admin1_code":"32.0",
    "gn:asciiname":"Masijue",
    "gn:country_code":"CN",
    "gn:dem":2778,
    "gn:feature_class":"P",
    "gn:feature_code":"PPL",
    "gn:name":"Masijue",
    "gn:population":0,
    "gn:timezone":"Asia/Shanghai",
    "iso:country":"CN",
    "name:zho_x_preferred":[
        "\u9a6c\u65af\u89c9"
    ],
    "wof:name":"Masijue",
    "wof:placetype":"locality"
},
  "geometry": {"coordinates":[102.798,28.4255],"type":"Point"}
}