{
  "type": "Feature",
  "properties": {
    "gn:admin1_code":"14.0",
    "gn:asciiname":"Rixoi",
    "gn:country_code":"CN",
    "gn:dem":3864,
    "gn:feature_class":"P",
    "gn:feature_code":"PPLF",
    "gn:name":"Rixoi",
    "gn:population":0,
    "gn:timezone":"Asia/Urumqi",
    "iso:country":"CN",
    "name:bod_x_preferred":[
        "Rixoi"
    ],
    "name:zho_x_preferred":[
        "Rixu"
    ],
    "name:zho_x_variant":[
        "\u65e5\u8bb8"
    ],
    "wof:name":"Rixoi",
    "wof:placetype":"locality"
},
  "geometry": {"coordinates":[95.68898,30.73444000000001],"type":"Point"}
}