{
  "type": "Feature",
  "properties": {
    "gn:admin1_code":"1.0",
    "gn:asciiname":"Zhangyoufangcun",
    "gn:country_code":"CN",
    "gn:dem":32,
    "gn:feature_class":"P",
    "gn:feature_code":"PPL",
    "gn:name":"Zhangyoufangcun",
    "gn:population":0,
    "gn:timezone":"Asia/Shanghai",
    "iso:country":"CN",
    "name:zho_x_preferred":[
        "\u5f20\u6cb9\u574a\u6751"
    ],
    "wof:name":"Zhangyoufangcun",
    "wof:placetype":"locality"
},
  "geometry": {"coordinates":[116.52760000000001,33.4542],"type":"Point"}
}