{
  "type": "Feature",
  "properties": {
    "gn:admin1_code":"25",
    "gn:asciiname":"Matougu",
    "gn:country_code":"CN",
    "gn:dem":178,
    "gn:feature_class":"P",
    "gn:feature_code":"PPL",
    "gn:name":"Matougu",
    "gn:population":0,
    "gn:timezone":"Asia/Shanghai",
    "iso:country":"CN",
    "name:zho_x_preferred":[
        "\u9a6c\u5934\u5d2e"
    ],
    "wof:name":"Matougu",
    "wof:placetype":"locality"
},
  "geometry": {"coordinates":[118.102,35.6037],"type":"Point"}
}