{
  "type": "Feature",
  "properties": {
    "gn:admin1_code":"11.0",
    "gn:asciiname":"Yingtaogang",
    "gn:country_code":"CN",
    "gn:dem":286,
    "gn:feature_class":"P",
    "gn:feature_code":"PPL",
    "gn:name":"Yingtaogang",
    "gn:population":0,
    "gn:timezone":"Asia/Shanghai",
    "iso:country":"CN",
    "name:zho_x_preferred":[
        "Yingtaogang"
    ],
    "name:zho_x_variant":[
        "\u6a31\u6843\u5c97"
    ],
    "wof:name":"Yingtaogang",
    "wof:placetype":"locality"
},
  "geometry": {"coordinates":[111.18153,29.86429],"type":"Point"}
}