{
  "type": "Feature",
  "properties": {
    "gn:admin1_code":"14.0",
    "gn:asciiname":"Kuoda Qicun",
    "gn:country_code":"CN",
    "gn:dem":4136,
    "gn:feature_class":"P",
    "gn:feature_code":"PPL",
    "gn:name":"Kuoda Qicun",
    "gn:population":0,
    "gn:timezone":"Asia/Urumqi",
    "iso:country":"CN",
    "name:zho_x_preferred":[
        "\u6269\u8fbe\u4e03\u6751"
    ],
    "wof:name":"Kuoda Qicun",
    "wof:placetype":"locality"
},
  "geometry": {"coordinates":[98.01208,30.8837],"type":"Point"}
}