{
  "type": "Feature",
  "properties": {
    "gn:admin1_code":"14",
    "gn:asciiname":"Peizhong Nongchang",
    "gn:country_code":"CN",
    "gn:dem":4066,
    "gn:feature_class":"P",
    "gn:feature_code":"PPLF",
    "gn:name":"Peizhong Nongchang",
    "gn:population":0,
    "gn:timezone":"Asia/Urumqi",
    "iso:country":"CN",
    "name:zho_x_preferred":[
        "\u914d\u79cd\u519c\u573a"
    ],
    "wof:name":"Peizhong Nongchang",
    "wof:placetype":"locality"
},
  "geometry": {"coordinates":[89.6446,28.8767],"type":"Point"}
}