{
  "type": "Feature",
  "properties": {
    "gn:admin1_code":"10",
    "gn:asciiname":"Benhanmiao",
    "gn:country_code":"CN",
    "gn:dem":1345,
    "gn:feature_class":"P",
    "gn:feature_code":"PPL",
    "gn:name":"Benhanmiao",
    "gn:population":0,
    "gn:timezone":"Asia/Shanghai",
    "iso:country":"CN",
    "name:zho_x_preferred":[
        "\u8d32\u6c57\u5e99"
    ],
    "wof:name":"Benhanmiao",
    "wof:placetype":"locality"
},
  "geometry": {"coordinates":[114.54452999999999,41.36794],"type":"Point"}
}