{
  "type": "Feature",
  "properties": {
    "gn:admin1_code":"12.0",
    "gn:asciiname":"Hualiba",
    "gn:country_code":"CN",
    "gn:dem":189,
    "gn:feature_class":"P",
    "gn:feature_code":"PPL",
    "gn:name":"Hualiba",
    "gn:population":0,
    "gn:timezone":"Asia/Shanghai",
    "iso:country":"CN",
    "name:zho_x_preferred":[
        "\u6866\u680e\u8019"
    ],
    "wof:name":"Hualiba",
    "wof:placetype":"locality"
},
  "geometry": {"coordinates":[111.82133,31.91427],"type":"Point"}
}