{
  "type": "Feature",
  "properties": {
    "gn:admin1_code":"04",
    "gn:asciiname":"Lujiagang",
    "gn:country_code":"CN",
    "gn:dem":7,
    "gn:feature_class":"P",
    "gn:feature_code":"PPL",
    "gn:name":"Lujiagang",
    "gn:population":0,
    "gn:timezone":"Asia/Shanghai",
    "iso:country":"CN",
    "name:und_x_variant":[
        "Lugangzhen",
        "Lu-chia-chiang-chen",
        "Lu-chia-chiang",
        "Lu-kang-chen",
        "Lujiagang",
        "\u9646\u5bb6\u6e2f",
        "Lugang",
        "\u9646\u6e2f"
    ],
    "wof:name":"Lujiagang",
    "wof:placetype":"locality"
},
  "geometry": {"coordinates":[120.41672,30.96823],"type":"Point"}
}