{
  "type": "Feature",
  "properties": {
    "gn:admin1_code":"30.0",
    "gn:asciiname":"Wutongpu",
    "gn:country_code":"CN",
    "gn:dem":6,
    "gn:feature_class":"P",
    "gn:feature_code":"PPL",
    "gn:name":"Wutongpu",
    "gn:population":0,
    "gn:timezone":"Asia/Shanghai",
    "iso:country":"CN",
    "name:zho_x_preferred":[
        "\u68a7\u6850\u57d4"
    ],
    "wof:name":"Wutongpu",
    "wof:placetype":"locality"
},
  "geometry": {"coordinates":[115.37662,22.88288],"type":"Point"}
}