{
  "type": "Feature",
  "properties": {
    "gn:admin1_code":"32.0",
    "gn:asciiname":"Shuitangzi",
    "gn:country_code":"CN",
    "gn:dem":1597,
    "gn:feature_class":"P",
    "gn:feature_code":"PPL",
    "gn:name":"Shuitangzi",
    "gn:population":0,
    "gn:timezone":"Asia/Shanghai",
    "iso:country":"CN",
    "name:zho_x_preferred":[
        "\u6c34\u5858\u5b50"
    ],
    "wof:name":"Shuitangzi",
    "wof:placetype":"locality"
},
  "geometry": {"coordinates":[102.798,27.0161],"type":"Point"}
}