{
  "type": "Feature",
  "properties": {
    "gn:admin1_code":"14",
    "gn:asciiname":"Qiudui",
    "gn:country_code":"CN",
    "gn:dem":4010,
    "gn:feature_class":"P",
    "gn:feature_code":"PPL",
    "gn:name":"Qiudui",
    "gn:population":0,
    "gn:timezone":"Asia/Urumqi",
    "iso:country":"CN",
    "name:zho_x_preferred":[
        "\u79cb\u5806"
    ],
    "wof:name":"Qiudui",
    "wof:placetype":"locality"
},
  "geometry": {"coordinates":[89.1858,28.9463],"type":"Point"}
}