{
  "type": "Feature",
  "properties": {
    "gn:admin1_code":"12.0",
    "gn:asciiname":"Daliushu",
    "gn:country_code":"CN",
    "gn:dem":364,
    "gn:feature_class":"P",
    "gn:feature_code":"PPL",
    "gn:name":"Daliushu",
    "gn:population":0,
    "gn:timezone":"Asia/Shanghai",
    "iso:country":"CN",
    "name:zho_x_preferred":[
        "\u5927\u67f3\u6811"
    ],
    "wof:name":"Daliushu",
    "wof:placetype":"locality"
},
  "geometry": {"coordinates":[111.22156,32.07178],"type":"Point"}
}