{
  "type": "Feature",
  "properties": {
    "gn:admin1_code":"29.0",
    "gn:asciiname":"Shangpudu",
    "gn:country_code":"CN",
    "gn:dem":1953,
    "gn:feature_class":"P",
    "gn:feature_code":"PPL",
    "gn:name":"Shangpudu",
    "gn:population":0,
    "gn:timezone":"Asia/Shanghai",
    "iso:country":"CN",
    "name:zho_x_preferred":[
        "\u4e0a\u666e\u6e21"
    ],
    "wof:name":"Shangpudu",
    "wof:placetype":"locality"
},
  "geometry": {"coordinates":[103.092,25.4329],"type":"Point"}
}