{
  "type": "Feature",
  "properties": {
    "gn:admin1_code":"12",
    "gn:asciiname":"Huanglongshan Linchang",
    "gn:country_code":"CN",
    "gn:dem":769,
    "gn:feature_class":"P",
    "gn:feature_code":"PPLF",
    "gn:name":"Huanglongshan Linchang",
    "gn:population":0,
    "gn:timezone":"Asia/Shanghai",
    "iso:country":"CN",
    "wof:name":"Huanglongshan Linchang",
    "wof:placetype":"locality"
},
  "geometry": {"coordinates":[110.22972,33.08111],"type":"Point"}
}