{
  "type": "Feature",
  "properties": {
    "gn:admin1_code":"3.0",
    "gn:asciiname":"Shihu",
    "gn:country_code":"CN",
    "gn:dem":102,
    "gn:feature_class":"P",
    "gn:feature_code":"PPL",
    "gn:name":"Shihu",
    "gn:population":0,
    "gn:timezone":"Asia/Shanghai",
    "iso:country":"CN",
    "name:und_x_variant":[
        "\u77f3\u6e56"
    ],
    "wof:name":"Shihu",
    "wof:placetype":"locality"
},
  "geometry": {"coordinates":[114.28928999999999,27.78405],"type":"Point"}
}