{
  "type": "Feature",
  "properties": {
    "gn:admin1_code":"8.0",
    "gn:asciiname":"Qingjiucun",
    "gn:country_code":"CN",
    "gn:dem":125,
    "gn:feature_class":"P",
    "gn:feature_code":"PPL",
    "gn:name":"Qingjiucun",
    "gn:population":0,
    "gn:timezone":"Asia/Shanghai",
    "iso:country":"CN",
    "name:zho_x_preferred":[
        "\u5e86\u4e5d\u6751"
    ],
    "wof:name":"Qingjiucun",
    "wof:placetype":"locality"
},
  "geometry": {"coordinates":[132.01491999999999,45.95931],"type":"Point"}
}