{
  "type": "Feature",
  "properties": {
    "gn:admin1_code":"32",
    "gn:asciiname":"Shirentian",
    "gn:country_code":"CN",
    "gn:dem":725,
    "gn:feature_class":"P",
    "gn:feature_code":"PPL",
    "gn:name":"Shirentian",
    "gn:population":0,
    "gn:timezone":"Asia/Shanghai",
    "iso:country":"CN",
    "name:zho_x_preferred":[
        "\u77f3\u4eba\u7530"
    ],
    "wof:name":"Shirentian",
    "wof:placetype":"locality"
},
  "geometry": {"coordinates":[105.35102000000001,32.0274],"type":"Point"}
}