{
  "type": "Feature",
  "properties": {
    "gn:admin1_code":"29.0",
    "gn:asciiname":"Longgu",
    "gn:country_code":"CN",
    "gn:dem":978,
    "gn:feature_class":"P",
    "gn:feature_code":"PPL",
    "gn:name":"Longgu",
    "gn:population":0,
    "gn:timezone":"Asia/Shanghai",
    "iso:country":"CN",
    "name:zho_x_preferred":[
        "\u9f99\u9aa8"
    ],
    "wof:name":"Longgu",
    "wof:placetype":"locality"
},
  "geometry": {"coordinates":[103.176,22.6956],"type":"Point"}
}