{
  "type": "Feature",
  "properties": {
    "gn:admin1_code":"32.0",
    "gn:asciiname":"Kongziping",
    "gn:country_code":"CN",
    "gn:dem":274,
    "gn:feature_class":"P",
    "gn:feature_code":"PPL",
    "gn:name":"Kongziping",
    "gn:population":0,
    "gn:timezone":"Asia/Shanghai",
    "iso:country":"CN",
    "name:zho_x_preferred":[
        "\u5b54\u5b50\u576a"
    ],
    "wof:name":"Kongziping",
    "wof:placetype":"locality"
},
  "geometry": {"coordinates":[106.80078,30.71432],"type":"Point"}
}