{
  "type": "Feature",
  "properties": {
    "gn:admin1_code":"2.0",
    "gn:asciiname":"Yangkou",
    "gn:country_code":"CN",
    "gn:dem":3,
    "gn:feature_class":"P",
    "gn:feature_code":"PPL",
    "gn:name":"Yangkou",
    "gn:population":0,
    "gn:timezone":"Asia/Shanghai",
    "iso:country":"CN",
    "name:und_x_variant":[
        "\u6f3e\u53e3"
    ],
    "wof:name":"Yangkou",
    "wof:placetype":"locality"
},
  "geometry": {"coordinates":[120.17541,30.62704],"type":"Point"}
}