{
  "type": "Feature",
  "properties": {
    "gn:admin1_code":"8.0",
    "gn:asciiname":"Xige",
    "gn:country_code":"CN",
    "gn:dem":380,
    "gn:feature_class":"P",
    "gn:feature_code":"PPL",
    "gn:name":"Xige",
    "gn:population":0,
    "gn:timezone":"Asia/Shanghai",
    "iso:country":"CN",
    "name:zho_x_preferred":[
        "\u897f\u6208"
    ],
    "wof:name":"Xige",
    "wof:placetype":"locality"
},
  "geometry": {"coordinates":[124.56025,52.32177],"type":"Point"}
}