{
  "type": "Feature",
  "properties": {
    "gn:admin1_code":"4.0",
    "gn:asciiname":"Wangliqiao",
    "gn:country_code":"CN",
    "gn:dem":6,
    "gn:feature_class":"P",
    "gn:feature_code":"PPL",
    "gn:name":"Wangliqiao",
    "gn:population":0,
    "gn:timezone":"Asia/Shanghai",
    "iso:country":"CN",
    "name:zho_x_preferred":[
        "\u738b\u91cc\u6865"
    ],
    "wof:name":"Wangliqiao",
    "wof:placetype":"locality"
},
  "geometry": {"coordinates":[119.78192,32.13039000000001],"type":"Point"}
}