{
  "type": "Feature",
  "properties": {
    "gn:admin1_code":"14",
    "gn:asciiname":"Banzong",
    "gn:country_code":"CN",
    "gn:dem":3972,
    "gn:feature_class":"P",
    "gn:feature_code":"PPL",
    "gn:name":"Banzong",
    "gn:population":0,
    "gn:timezone":"Asia/Urumqi",
    "iso:country":"CN",
    "name:zho_x_preferred":[
        "\u73ed\u5b97"
    ],
    "wof:name":"Banzong",
    "wof:placetype":"locality"
},
  "geometry": {"coordinates":[89.0372,29.6159],"type":"Point"}
}