{
  "type": "Feature",
  "properties": {
    "gn:admin1_code":"29.0",
    "gn:asciiname":"Fajujia",
    "gn:country_code":"CN",
    "gn:dem":2053,
    "gn:feature_class":"P",
    "gn:feature_code":"PPL",
    "gn:name":"Fajujia",
    "gn:population":0,
    "gn:timezone":"Asia/Shanghai",
    "iso:country":"CN",
    "name:zho_x_preferred":[
        "\u53d1\u5c45\u621b"
    ],
    "wof:name":"Fajujia",
    "wof:placetype":"locality"
},
  "geometry": {"coordinates":[103.65300000000001,26.5438],"type":"Point"}
}