{
  "type": "Feature",
  "properties": {
    "gn:admin1_code":"3.0",
    "gn:asciiname":"Duijia",
    "gn:country_code":"CN",
    "gn:dem":490,
    "gn:feature_class":"P",
    "gn:feature_code":"PPL",
    "gn:name":"Duijia",
    "gn:population":0,
    "gn:timezone":"Asia/Shanghai",
    "iso:country":"CN",
    "name:und_x_variant":[
        "\u5bf9\u5bb6"
    ],
    "wof:name":"Duijia",
    "wof:placetype":"locality"
},
  "geometry": {"coordinates":[115.43968999999998,26.51704],"type":"Point"}
}