{
  "type": "Feature",
  "properties": {
    "gn:admin1_code":"1.0",
    "gn:asciiname":"Zhangzhuyuancun",
    "gn:country_code":"CN",
    "gn:dem":38,
    "gn:feature_class":"P",
    "gn:feature_code":"PPL",
    "gn:name":"Zhangzhuyuancun",
    "gn:population":0,
    "gn:timezone":"Asia/Shanghai",
    "iso:country":"CN",
    "name:zho_x_preferred":[
        "\u5f20\u7af9\u56ed\u6751"
    ],
    "wof:name":"Zhangzhuyuancun",
    "wof:placetype":"locality"
},
  "geometry": {"coordinates":[115.98526,33.72955],"type":"Point"}
}