{
  "type": "Feature",
  "properties": {
    "gn:admin1_code":"33",
    "gn:asciiname":"Sanjiao",
    "gn:country_code":"CN",
    "gn:dem":274,
    "gn:feature_class":"P",
    "gn:feature_code":"PPLA4",
    "gn:name":"Sanjiao",
    "gn:population":0,
    "gn:timezone":"Asia/Shanghai",
    "iso:country":"CN",
    "name:ceb_x_preferred":[
        "Sanjiao"
    ],
    "name:deu_x_preferred":[
        "Sanjiao"
    ],
    "name:swe_x_preferred":[
        "Sanjiao"
    ],
    "name:und_x_variant":[
        "San-chiao",
        "San-chiao-chen",
        "Sanjiao",
        "Sanjiao Zhen"
    ],
    "name:zho_x_preferred":[
        "\u4e09\u89d2"
    ],
    "name:zho_x_variant":[
        "\u4e09\u89d2\u9547"
    ],
    "wof:name":"Sanjiao",
    "wof:placetype":"locality"
},
  "geometry": {"coordinates":[106.73639,29.05028],"type":"Point"}
}