{
  "type": "Feature",
  "properties": {
    "gn:admin1_code":"28.0",
    "gn:asciiname":"Xinan",
    "gn:country_code":"CN",
    "gn:dem":13,
    "gn:feature_class":"P",
    "gn:feature_code":"PPL",
    "gn:name":"Xinan",
    "gn:population":0,
    "gn:timezone":"Asia/Shanghai",
    "iso:country":"CN",
    "name:ceb_x_preferred":[
        "Xinan"
    ],
    "name:deu_x_preferred":[
        "Xinan"
    ],
    "name:swe_x_preferred":[
        "Xinan"
    ],
    "name:zho_x_preferred":[
        "\u897f\u5357"
    ],
    "wof:name":"Xinan",
    "wof:placetype":"locality"
},
  "geometry": {"coordinates":[116.91459999999999,39.30705],"type":"Point"}
}