{
  "type": "Feature",
  "properties": {
    "gn:admin1_code":"16.0",
    "gn:asciiname":"Lanbandeng",
    "gn:country_code":"CN",
    "gn:dem":657,
    "gn:feature_class":"P",
    "gn:feature_code":"PPL",
    "gn:name":"Lanbandeng",
    "gn:population":0,
    "gn:timezone":"Asia/Shanghai",
    "iso:country":"CN",
    "name:zho_x_preferred":[
        "\u61d2\u677f\u51f3"
    ],
    "wof:name":"Lanbandeng",
    "wof:placetype":"locality"
},
  "geometry": {"coordinates":[107.703,24.9643],"type":"Point"}
}