{
  "type": "Feature",
  "properties": {
    "gn:admin1_code":"12.0",
    "gn:asciiname":"Baimasihe",
    "gn:country_code":"CN",
    "gn:dem":78,
    "gn:feature_class":"P",
    "gn:feature_code":"PPL",
    "gn:name":"Baimasihe",
    "gn:population":0,
    "gn:timezone":"Asia/Shanghai",
    "iso:country":"CN",
    "name:zho_x_preferred":[
        "\u767d\u9a6c\u5636\u6cb3"
    ],
    "wof:name":"Baimasihe",
    "wof:placetype":"locality"
},
  "geometry": {"coordinates":[114.61884000000001,31.42215],"type":"Point"}
}