{
  "type": "Feature",
  "properties": {
    "gn:admin1_code":"7.0",
    "gn:asciiname":"Liancheng",
    "gn:country_code":"CN",
    "gn:dem":726,
    "gn:feature_class":"P",
    "gn:feature_code":"PPL",
    "gn:name":"Liancheng",
    "gn:population":0,
    "gn:timezone":"Asia/Shanghai",
    "iso:country":"CN",
    "name:ceb_x_preferred":[
        "Liancheng"
    ],
    "name:deu_x_preferred":[
        "Liancheng"
    ],
    "name:zho_x_preferred":[
        "\u8fde\u57ce"
    ],
    "wof:name":"Liancheng",
    "wof:placetype":"locality"
},
  "geometry": {"coordinates":[117.04374,24.54532],"type":"Point"}
}