{
  "type": "Feature",
  "properties": {
    "gn:admin1_code":"19.0",
    "gn:asciiname":"Sundangjia Wobu",
    "gn:country_code":"CN",
    "gn:dem":89,
    "gn:feature_class":"P",
    "gn:feature_code":"PPL",
    "gn:name":"Sundangjia Wobu",
    "gn:population":0,
    "gn:timezone":"Asia/Shanghai",
    "iso:country":"CN",
    "name:zho_x_preferred":[
        "\u5b59\u515a\u5bb6\u7a9d\u5821"
    ],
    "wof:name":"Sundangjia Wobu",
    "wof:placetype":"locality"
},
  "geometry": {"coordinates":[123.65600000000001,42.8694],"type":"Point"}
}