{
  "type": "Feature",
  "properties": {
    "gn:admin1_code":"16.0",
    "gn:asciiname":"Leilai",
    "gn:country_code":"CN",
    "gn:dem":135,
    "gn:feature_class":"P",
    "gn:feature_code":"PPL",
    "gn:name":"Leilai",
    "gn:population":0,
    "gn:timezone":"Asia/Shanghai",
    "iso:country":"CN",
    "name:zho_x_preferred":[
        "\u857e\u8d56"
    ],
    "wof:name":"Leilai",
    "wof:placetype":"locality"
},
  "geometry": {"coordinates":[108.544,22.7471],"type":"Point"}
}