{
  "type": "Feature",
  "properties": {
    "gn:admin1_code":"5.0",
    "gn:asciiname":"Shunshantun",
    "gn:country_code":"CN",
    "gn:dem":360,
    "gn:feature_class":"P",
    "gn:feature_code":"PPL",
    "gn:name":"Shunshantun",
    "gn:population":0,
    "gn:timezone":"Asia/Shanghai",
    "iso:country":"CN",
    "name:zho_x_preferred":[
        "\u987a\u5c71\u5c6f"
    ],
    "wof:name":"Shunshantun",
    "wof:placetype":"locality"
},
  "geometry": {"coordinates":[126.55837,43.02987],"type":"Point"}
}