{
  "type": "Feature",
  "properties": {
    "gn:admin1_code":"22",
    "gn:asciiname":"Shenjiaying",
    "gn:country_code":"CN",
    "gn:dem":503,
    "gn:feature_class":"P",
    "gn:feature_code":"PPLA4",
    "gn:name":"Shenjiaying",
    "gn:population":0,
    "gn:timezone":"Asia/Shanghai",
    "iso:country":"CN",
    "name:und_x_variant":[
        "Shenjiaying Zhen"
    ],
    "name:zho_x_preferred":[
        "\u6c88\u5bb6\u8425"
    ],
    "name:zho_x_variant":[
        "\u6c88\u5bb6\u8425\u9547"
    ],
    "wof:name":"Shenjiaying",
    "wof:placetype":"locality"
},
  "geometry": {"coordinates":[116.04352,40.48595],"type":"Point"}
}