{
  "type": "Feature",
  "properties": {
    "gn:admin1_code":"25",
    "gn:asciiname":"Yangnaotou",
    "gn:country_code":"CN",
    "gn:dem":8,
    "gn:feature_class":"P",
    "gn:feature_code":"PPL",
    "gn:name":"Yangnaotou",
    "gn:population":0,
    "gn:timezone":"Asia/Shanghai",
    "iso:country":"CN",
    "name:zho_x_preferred":[
        "\u6768\u6320\u5934"
    ],
    "wof:name":"Yangnaotou",
    "wof:placetype":"locality"
},
  "geometry": {"coordinates":[117.992,37.5097],"type":"Point"}
}