{
  "type": "Feature",
  "properties": {
    "gn:admin1_code":"26.0",
    "gn:asciiname":"Shuanghuaishu",
    "gn:country_code":"CN",
    "gn:dem":753,
    "gn:feature_class":"P",
    "gn:feature_code":"PPL",
    "gn:name":"Shuanghuaishu",
    "gn:population":0,
    "gn:timezone":"Asia/Shanghai",
    "iso:country":"CN",
    "name:zho_x_preferred":[
        "\u53cc\u69d0\u6811"
    ],
    "wof:name":"Shuanghuaishu",
    "wof:placetype":"locality"
},
  "geometry": {"coordinates":[109.28418000000001,33.35666],"type":"Point"}
}