{
  "type": "Feature",
  "properties": {
    "gn:admin1_code":"32.0",
    "gn:asciiname":"Huajiao",
    "gn:country_code":"CN",
    "gn:dem":1677,
    "gn:feature_class":"P",
    "gn:feature_code":"PPL",
    "gn:name":"Huajiao",
    "gn:population":0,
    "gn:timezone":"Asia/Shanghai",
    "iso:country":"CN",
    "name:zho_x_preferred":[
        "\u82b1\u6912"
    ],
    "wof:name":"Huajiao",
    "wof:placetype":"locality"
},
  "geometry": {"coordinates":[103.39100000000001,27.9873],"type":"Point"}
}