{
  "type": "Feature",
  "properties": {
    "gn:admin1_code":"04",
    "gn:asciiname":"Huaisi",
    "gn:country_code":"CN",
    "gn:dem":12,
    "gn:feature_class":"P",
    "gn:feature_code":"PPL",
    "gn:name":"Huaisi",
    "gn:population":0,
    "gn:timezone":"Asia/Shanghai",
    "iso:country":"CN",
    "name:und_x_variant":[
        "Huaisiqiao",
        "Huai-tzu-ch\u2019iao",
        "Huai-ssu-ch\u2019iao",
        "Huaisi"
    ],
    "name:zho_x_preferred":[
        "\u69d0\u6cd7"
    ],
    "wof:name":"Huaisi",
    "wof:placetype":"locality"
},
  "geometry": {"coordinates":[119.43779000000001,32.45950999999999],"type":"Point"}
}