{
  "type": "Feature",
  "properties": {
    "gn:admin1_code":"04",
    "gn:asciiname":"Dongbang",
    "gn:country_code":"CN",
    "gn:dem":7,
    "gn:feature_class":"P",
    "gn:feature_code":"PPLA4",
    "gn:name":"Dongbang",
    "gn:population":0,
    "gn:timezone":"Asia/Shanghai",
    "iso:country":"CN",
    "name:und_x_variant":[
        "Tung-pang-shih",
        "Tung-peng-shih",
        "Dongbang",
        "\u8463\u6d5c",
        "Dongbang Zhen",
        "\u8463\u6d5c\u9547"
    ],
    "wof:name":"Dongbang",
    "wof:placetype":"locality"
},
  "geometry": {"coordinates":[120.92607,31.64837],"type":"Point"}
}