{
  "type": "Feature",
  "properties": {
    "gn:admin1_code":"19.0",
    "gn:asciiname":"Luoshicun",
    "gn:country_code":"CN",
    "gn:dem":10,
    "gn:feature_class":"P",
    "gn:feature_code":"PPL",
    "gn:name":"Luoshicun",
    "gn:population":0,
    "gn:timezone":"Asia/Shanghai",
    "iso:country":"CN",
    "name:zho_x_preferred":[
        "\u9a86\u77f3\u6751"
    ],
    "wof:name":"Luoshicun",
    "wof:placetype":"locality"
},
  "geometry": {"coordinates":[122.13500000000001,39.2569],"type":"Point"}
}