{
  "type": "Feature",
  "properties": {
    "gn:admin1_code":"32.0",
    "gn:asciiname":"Xinhong",
    "gn:country_code":"CN",
    "gn:dem":371,
    "gn:feature_class":"P",
    "gn:feature_code":"PPL",
    "gn:name":"Xinhong",
    "gn:population":0,
    "gn:timezone":"Asia/Shanghai",
    "iso:country":"CN",
    "name:zho_x_preferred":[
        "\u65b0\u7ea2"
    ],
    "wof:name":"Xinhong",
    "wof:placetype":"locality"
},
  "geometry": {"coordinates":[107.72078999999999,31.41282],"type":"Point"}
}