{
  "type": "Feature",
  "properties": {
    "gn:admin1_code":"16",
    "gn:asciiname":"Dukou",
    "gn:country_code":"CN",
    "gn:dem":298,
    "gn:feature_class":"P",
    "gn:feature_code":"PPL",
    "gn:name":"Dukou",
    "gn:population":0,
    "gn:timezone":"Asia/Shanghai",
    "iso:country":"CN",
    "name:und_x_variant":[
        "Tu-k\u2019ou",
        "Dukou"
    ],
    "name:zho_x_preferred":[
        "\u6e21\u53e3"
    ],
    "wof:name":"Dukou",
    "wof:placetype":"locality"
},
  "geometry": {"coordinates":[106.535,25.0766],"type":"Point"}
}