{
  "type": "Feature",
  "properties": {
    "gn:admin1_code":"19.0",
    "gn:asciiname":"Guafuqiao",
    "gn:country_code":"CN",
    "gn:dem":17,
    "gn:feature_class":"P",
    "gn:feature_code":"PPL",
    "gn:name":"Guafuqiao",
    "gn:population":0,
    "gn:timezone":"Asia/Shanghai",
    "iso:country":"CN",
    "name:und_x_variant":[
        "\u6302\u7b26\u6865"
    ],
    "name:zho_x_preferred":[
        "\u6302\u7b26\u6865"
    ],
    "wof:name":"Guafuqiao",
    "wof:placetype":"locality"
},
  "geometry": {"coordinates":[121.91853,39.3738],"type":"Point"}
}