{
  "type": "Feature",
  "properties": {
    "gn:admin1_code":"18",
    "gn:asciiname":"Ludi",
    "gn:country_code":"CN",
    "gn:dem":1259,
    "gn:feature_class":"P",
    "gn:feature_code":"PPL",
    "gn:name":"Ludi",
    "gn:population":0,
    "gn:timezone":"Asia/Shanghai",
    "iso:country":"CN",
    "name:bel_x_preferred":[
        "\u0413\u0443\u043b\u044c\u043d\u0456"
    ],
    "name:cat_x_preferred":[
        "Jocs romans"
    ],
    "name:deu_x_preferred":[
        "Ludi publici"
    ],
    "name:fra_x_preferred":[
        "Jeux"
    ],
    "name:ita_x_preferred":[
        "Ludi"
    ],
    "name:por_x_preferred":[
        "Jogos"
    ],
    "name:rus_x_preferred":[
        "\u0418\u0433\u0440\u044b"
    ],
    "name:slv_x_preferred":[
        "Ludi"
    ],
    "name:spa_x_preferred":[
        "Ludi"
    ],
    "name:swe_x_preferred":[
        "Ludi"
    ],
    "name:zho_x_preferred":[
        "\u82a6\u837b"
    ],
    "wof:name":"Ludi",
    "wof:placetype":"locality"
},
  "geometry": {"coordinates":[106.348,26.4761],"type":"Point"}
}