{
  "type": "Feature",
  "properties": {
    "gn:admin1_code":"32.0",
    "gn:asciiname":"Duosonggong",
    "gn:country_code":"CN",
    "gn:dem":2732,
    "gn:feature_class":"P",
    "gn:feature_code":"PPL",
    "gn:name":"Duosonggong",
    "gn:population":0,
    "gn:timezone":"Asia/Shanghai",
    "iso:country":"CN",
    "name:zho_x_preferred":[
        "\u593a\u677e\u8d21"
    ],
    "wof:name":"Duosonggong",
    "wof:placetype":"locality"
},
  "geometry": {"coordinates":[99.4272,29.0273],"type":"Point"}
}