{
  "type": "Feature",
  "properties": {
    "gn:admin1_code":"3.0",
    "gn:asciiname":"Luzhou'ao",
    "gn:country_code":"CN",
    "gn:dem":89,
    "gn:feature_class":"P",
    "gn:feature_code":"PPL",
    "gn:name":"Luzhou\u2019ao",
    "gn:population":0,
    "gn:timezone":"Asia/Shanghai",
    "iso:country":"CN",
    "name:und_x_variant":[
        "Luzhou\u2019ao",
        "\u82a6\u6d32\u5773"
    ],
    "wof:name":"Luzhou'ao",
    "wof:placetype":"locality"
},
  "geometry": {"coordinates":[117.40057,29.10629],"type":"Point"}
}