{
  "type": "Feature",
  "properties": {
    "gn:admin1_code":"9.0",
    "gn:asciiname":"Henglianghe",
    "gn:country_code":"CN",
    "gn:dem":187,
    "gn:feature_class":"P",
    "gn:feature_code":"PPL",
    "gn:name":"Henglianghe",
    "gn:population":0,
    "gn:timezone":"Asia/Shanghai",
    "iso:country":"CN",
    "name:und_x_variant":[
        "\u6a2a\u6881\u6cb3",
        "Henglianghe"
    ],
    "wof:name":"Henglianghe",
    "wof:placetype":"locality"
},
  "geometry": {"coordinates":[112.77961999999999,33.60407],"type":"Point"}
}