{
  "type": "Feature",
  "properties": {
    "gn:admin1_code":"30",
    "gn:asciiname":"Shanxu",
    "gn:country_code":"CN",
    "gn:dem":9,
    "gn:feature_class":"P",
    "gn:feature_code":"PPL",
    "gn:name":"Shanxu",
    "gn:population":0,
    "gn:timezone":"Asia/Urumqi",
    "iso:country":"CN",
    "name:fas_x_preferred":[
        "\u0634\u0627\u0646\u0634\u0648"
    ],
    "name:zha_x_preferred":[
        "Sanhih"
    ],
    "name:zho_x_preferred":[
        "\u5c71\u5729"
    ],
    "name:zho_x_variant":[
        "\u5c71\u5729\u9547"
    ],
    "wof:name":"Shanxu",
    "wof:placetype":"locality"
},
  "geometry": {"coordinates":[110.66689,21.43002000000001],"type":"Point"}
}