{
  "type": "Feature",
  "properties": {
    "gn:admin1_code":"18.0",
    "gn:asciiname":"Shuiwei",
    "gn:country_code":"CN",
    "gn:dem":959,
    "gn:feature_class":"P",
    "gn:feature_code":"PPL",
    "gn:name":"Shuiwei",
    "gn:population":0,
    "gn:timezone":"Asia/Shanghai",
    "iso:country":"CN",
    "name:zho_x_preferred":[
        "\u6c34\u5c3e"
    ],
    "wof:name":"Shuiwei",
    "wof:placetype":"locality"
},
  "geometry": {"coordinates":[107.227,26.7682],"type":"Point"}
}