{
  "type": "Feature",
  "properties": {
    "gn:admin1_code":"1.0",
    "gn:asciiname":"Wenxingcun",
    "gn:country_code":"CN",
    "gn:dem":13,
    "gn:feature_class":"P",
    "gn:feature_code":"PPL",
    "gn:name":"Wenxingcun",
    "gn:population":0,
    "gn:timezone":"Asia/Shanghai",
    "iso:country":"CN",
    "name:zho_x_preferred":[
        "\u6587\u5174\u6751"
    ],
    "wof:name":"Wenxingcun",
    "wof:placetype":"locality"
},
  "geometry": {"coordinates":[117.86524,31.14217],"type":"Point"}
}