{
  "type": "Feature",
  "properties": {
    "gn:admin1_code":"11.0",
    "gn:asciiname":"Shayangkeng",
    "gn:country_code":"CN",
    "gn:dem":587,
    "gn:feature_class":"P",
    "gn:feature_code":"PPL",
    "gn:name":"Shayangkeng",
    "gn:population":0,
    "gn:timezone":"Asia/Shanghai",
    "iso:country":"CN",
    "name:zho_x_preferred":[
        "\u6740\u7f8a\u5751"
    ],
    "wof:name":"Shayangkeng",
    "wof:placetype":"locality"
},
  "geometry": {"coordinates":[113.77512,25.51624],"type":"Point"}
}