{
  "type": "Feature",
  "properties": {
    "gn:admin1_code":"25",
    "gn:asciiname":"Changbuling",
    "gn:country_code":"CN",
    "gn:dem":46,
    "gn:feature_class":"P",
    "gn:feature_code":"PPL",
    "gn:name":"Changbuling",
    "gn:population":0,
    "gn:timezone":"Asia/Shanghai",
    "iso:country":"CN",
    "name:zho_x_preferred":[
        "\u957f\u57e0\u5cad"
    ],
    "wof:name":"Changbuling",
    "wof:placetype":"locality"
},
  "geometry": {"coordinates":[118.40900000000001,34.7405],"type":"Point"}
}