{
  "type": "Feature",
  "properties": {
    "gn:admin1_code":"2.0",
    "gn:asciiname":"Tongshantang",
    "gn:country_code":"CN",
    "gn:dem":10,
    "gn:feature_class":"P",
    "gn:feature_code":"PPL",
    "gn:name":"Tongshantang",
    "gn:population":0,
    "gn:timezone":"Asia/Shanghai",
    "iso:country":"CN",
    "name:und_x_variant":[
        "\u540c\u5584\u5802"
    ],
    "wof:name":"Tongshantang",
    "wof:placetype":"locality"
},
  "geometry": {"coordinates":[120.4259,30.66232],"type":"Point"}
}