{
  "type": "Feature",
  "properties": {
    "gn:admin1_code":"29",
    "gn:asciiname":"Dakeju",
    "gn:country_code":"CN",
    "gn:dem":1711,
    "gn:feature_class":"P",
    "gn:feature_code":"PPL",
    "gn:name":"Dakeju",
    "gn:population":0,
    "gn:timezone":"Asia/Shanghai",
    "iso:country":"CN",
    "name:zho_x_preferred":[
        "\u5927\u53ef\u82f4"
    ],
    "wof:name":"Dakeju",
    "wof:placetype":"locality"
},
  "geometry": {"coordinates":[101.706,24.1885],"type":"Point"}
}