{
  "type": "Feature",
  "properties": {
    "gn:admin1_code":"7.0",
    "gn:asciiname":"Xiaofenliu",
    "gn:country_code":"CN",
    "gn:dem":655,
    "gn:feature_class":"P",
    "gn:feature_code":"PPL",
    "gn:name":"Xiaofenliu",
    "gn:population":0,
    "gn:timezone":"Asia/Shanghai",
    "iso:country":"CN",
    "name:zho_x_preferred":[
        "\u5c0f\u5206\u6d41"
    ],
    "wof:name":"Xiaofenliu",
    "wof:placetype":"locality"
},
  "geometry": {"coordinates":[117.73560999999999,25.0061],"type":"Point"}
}