{
  "type": "Feature",
  "properties": {
    "gn:admin1_code":"18",
    "gn:asciiname":"Shangkangli",
    "gn:country_code":"CN",
    "gn:dem":574,
    "gn:feature_class":"P",
    "gn:feature_code":"PPL",
    "gn:name":"Shangkangli",
    "gn:population":0,
    "gn:timezone":"Asia/Shanghai",
    "iso:country":"CN",
    "name:zho_x_preferred":[
        "\u4e0a\u5eb7\u91cc"
    ],
    "wof:name":"Shangkangli",
    "wof:placetype":"locality"
},
  "geometry": {"coordinates":[106.937,25.3869],"type":"Point"}
}