{
  "type": "Feature",
  "properties": {
    "gn:admin1_code":"25",
    "gn:asciiname":"Weihai",
    "gn:country_code":"CN",
    "gn:dem":45,
    "gn:feature_class":"P",
    "gn:feature_code":"PPL",
    "gn:name":"Weihai",
    "gn:population":0,
    "gn:timezone":"Asia/Shanghai",
    "iso:country":"CN",
    "name:afr_x_preferred":[
        "Weihai"
    ],
    "name:ara_x_preferred":[
        "\u0648\u064a\u0647\u0627\u064a"
    ],
    "name:cat_x_preferred":[
        "Weihai"
    ],
    "name:cdo_x_preferred":[
        "\u016ci-h\u0101i"
    ],
    "name:ceb_x_preferred":[
        "Weihai"
    ],
    "name:ces_x_preferred":[
        "Wej-chaj"
    ],
    "name:dan_x_preferred":[
        "Weihai"
    ],
    "name:deu_x_preferred":[
        "Weihai"
    ],
    "name:eus_x_preferred":[
        "Weihai"
    ],
    "name:fas_x_preferred":[
        "\u0648\u06cc\u0647\u0627\u06cc"
    ],
    "name:fin_x_preferred":[
        "Weihai"
    ],
    "name:fra_x_preferred":[
        "Weihai"
    ],
    "name:ind_x_preferred":[
        "Weihai"
    ],
    "name:ita_x_preferred":[
        "Weihai"
    ],
    "name:jpn_x_preferred":[
        "\u5a01\u6d77\u5e02"
    ],
    "name:kik_x_preferred":[
        "Weihai"
    ],
    "name:kor_x_preferred":[
        "\uc6e8\uc774\ud558\uc774\uc2dc"
    ],
    "name:mlg_x_preferred":[
        "Weihai"
    ],
    "name:mya_x_preferred":[
        "\u101d\u1031\u1038\u101f\u102d\u102f\u1004\u103a\u1019\u103c\u102d\u102f\u1037"
    ],
    "name:nld_x_preferred":[
        "Weihai"
    ],
    "name:nno_x_preferred":[
        "Weihai"
    ],
    "name:nor_x_preferred":[
        "Weihai"
    ],
    "name:pol_x_preferred":[
        "Weihai"
    ],
    "name:por_x_preferred":[
        "Weihai"
    ],
    "name:rus_x_preferred":[
        "\u0412\u044d\u0439\u0445\u0430\u0439"
    ],
    "name:spa_x_preferred":[
        "Weihai"
    ],
    "name:swe_x_preferred":[
        "Weihai"
    ],
    "name:tgl_x_preferred":[
        "Weihai"
    ],
    "name:tha_x_preferred":[
        "\u0e40\u0e27\u0e22\u0e44\u0e2b\u0e48"
    ],
    "name:tur_x_preferred":[
        "Weihai"
    ],
    "name:ukr_x_preferred":[
        "\u0412\u0435\u0439\u0445\u0430\u0439"
    ],
    "name:urd_x_preferred":[
        "\u0648\u06cc\u06cc\u06c1\u0627\u0626\u06cc"
    ],
    "name:vep_x_preferred":[
        "Veihai"
    ],
    "name:vie_x_preferred":[
        "Uy H\u1ea3i"
    ],
    "name:war_x_preferred":[
        "Weihai"
    ],
    "name:wuu_x_preferred":[
        "\u5a01\u6d77\u5e02"
    ],
    "name:zho_x_preferred":[
        "\u9b4f\u6d77"
    ],
    "name:zho_x_variant":[
        "\u5a01\u6d77\u5e02"
    ],
    "wof:name":"Weihai",
    "wof:placetype":"locality"
},
  "geometry": {"coordinates":[115.77682,36.07285],"type":"Point"}
}