{
  "type": "Feature",
  "properties": {
    "gn:admin1_code":"30.0",
    "gn:asciiname":"Aotoupu",
    "gn:country_code":"CN",
    "gn:dem":470,
    "gn:feature_class":"P",
    "gn:feature_code":"PPL",
    "gn:name":"Aotoupu",
    "gn:population":0,
    "gn:timezone":"Asia/Shanghai",
    "iso:country":"CN",
    "name:zho_x_preferred":[
        "Aotoupu"
    ],
    "name:zho_x_variant":[
        "\u5773\u5934\u94fa"
    ],
    "wof:name":"Aotoupu",
    "wof:placetype":"locality"
},
  "geometry": {"coordinates":[112.58167,25.1025],"type":"Point"}
}