{
  "type": "Feature",
  "properties": {
    "gn:admin1_code":"9",
    "gn:asciiname":"Shenpaifang",
    "gn:country_code":"CN",
    "gn:dem":50,
    "gn:feature_class":"P",
    "gn:feature_code":"PPL",
    "gn:name":"Shenpaifang",
    "gn:population":0,
    "gn:timezone":"Asia/Shanghai",
    "iso:country":"CN",
    "name:zho_x_preferred":[
        "\u6c88\u724c\u574a"
    ],
    "wof:name":"Shenpaifang",
    "wof:placetype":"locality"
},
  "geometry": {"coordinates":[115.727,34.4152],"type":"Point"}
}