{
  "type": "Feature",
  "properties": {
    "gn:admin1_code":"32.0",
    "gn:asciiname":"Gexianshan",
    "gn:country_code":"CN",
    "gn:dem":619,
    "gn:feature_class":"P",
    "gn:feature_code":"PPL",
    "gn:name":"Gexianshan",
    "gn:population":0,
    "gn:timezone":"Asia/Shanghai",
    "iso:country":"CN",
    "name:zho_x_preferred":[
        "\u845b\u4ed9\u5c71"
    ],
    "wof:name":"Gexianshan",
    "wof:placetype":"locality"
},
  "geometry": {"coordinates":[103.95489999999999,31.13688],"type":"Point"}
}