{
  "type": "Feature",
  "properties": {
    "gn:admin1_code":"30.0",
    "gn:asciiname":"Dalutang",
    "gn:country_code":"CN",
    "gn:dem":100,
    "gn:feature_class":"P",
    "gn:feature_code":"PPL",
    "gn:name":"Dalutang",
    "gn:population":0,
    "gn:timezone":"Asia/Shanghai",
    "iso:country":"CN",
    "name:zho_x_preferred":[
        "\u5927\u9646\u5858"
    ],
    "wof:name":"Dalutang",
    "wof:placetype":"locality"
},
  "geometry": {"coordinates":[111.53315000000001,22.56139],"type":"Point"}
}