{
  "type": "Feature",
  "properties": {
    "gn:admin1_code":"8.0",
    "gn:asciiname":"Dongtaha",
    "gn:country_code":"CN",
    "gn:dem":154,
    "gn:feature_class":"P",
    "gn:feature_code":"PPL",
    "gn:name":"Dongtaha",
    "gn:population":0,
    "gn:timezone":"Asia/Shanghai",
    "iso:country":"CN",
    "name:zho_x_preferred":[
        "\u4e1c\u5854\u54c8"
    ],
    "wof:name":"Dongtaha",
    "wof:placetype":"locality"
},
  "geometry": {"coordinates":[124.26967,47.55973],"type":"Point"}
}