{
  "type": "Feature",
  "properties": {
    "gn:admin1_code":"32.0",
    "gn:asciiname":"Gualuotian",
    "gn:country_code":"CN",
    "gn:dem":325,
    "gn:feature_class":"P",
    "gn:feature_code":"PPL",
    "gn:name":"Gualuotian",
    "gn:population":0,
    "gn:timezone":"Asia/Shanghai",
    "iso:country":"CN",
    "name:zho_x_preferred":[
        "\u74dc\u7f57\u7530"
    ],
    "wof:name":"Gualuotian",
    "wof:placetype":"locality"
},
  "geometry": {"coordinates":[104.877,28.9658],"type":"Point"}
}