{
  "type": "Feature",
  "properties": {
    "gn:admin1_code":"7",
    "gn:asciiname":"Anji",
    "gn:country_code":"CN",
    "gn:dem":63,
    "gn:feature_class":"P",
    "gn:feature_code":"PPL",
    "gn:name":"Anji",
    "gn:population":0,
    "gn:timezone":"Asia/Shanghai",
    "iso:country":"CN",
    "name:ceb_x_preferred":[
        "Anji"
    ],
    "name:deu_x_preferred":[
        "Anji"
    ],
    "name:zho_x_preferred":[
        "\u5b89\u5409"
    ],
    "wof:name":"Anji",
    "wof:placetype":"locality"
},
  "geometry": {"coordinates":[117.23087,23.98292],"type":"Point"}
}