{
  "type": "Feature",
  "properties": {
    "gn:admin1_code":"22.0",
    "gn:asciiname":"Sanshan Zuigou",
    "gn:country_code":"CN",
    "gn:dem":423,
    "gn:feature_class":"P",
    "gn:feature_code":"PPL",
    "gn:name":"Sanshan Zuigou",
    "gn:population":0,
    "gn:timezone":"Asia/Shanghai",
    "iso:country":"CN",
    "name:zho_x_preferred":[
        "\u4e09\u5c71\u5480\u6c9f"
    ],
    "wof:name":"Sanshan Zuigou",
    "wof:placetype":"locality"
},
  "geometry": {"coordinates":[116.56022,40.72607],"type":"Point"}
}