{
  "type": "Feature",
  "properties": {
    "gn:admin1_code":"16.0",
    "gn:asciiname":"Gemaoshan",
    "gn:country_code":"CN",
    "gn:dem":17,
    "gn:feature_class":"P",
    "gn:feature_code":"PPL",
    "gn:name":"Gemaoshan",
    "gn:population":0,
    "gn:timezone":"Asia/Shanghai",
    "iso:country":"CN",
    "name:zho_x_preferred":[
        "\u845b\u8305\u5c71"
    ],
    "wof:name":"Gemaoshan",
    "wof:placetype":"locality"
},
  "geometry": {"coordinates":[108.932,21.6434],"type":"Point"}
}