{
  "type": "Feature",
  "properties": {
    "gn:admin1_code":"26.0",
    "gn:asciiname":"Yangshitoucun",
    "gn:country_code":"CN",
    "gn:dem":758,
    "gn:feature_class":"P",
    "gn:feature_code":"PPL",
    "gn:name":"Yangshitoucun",
    "gn:population":0,
    "gn:timezone":"Asia/Shanghai",
    "iso:country":"CN",
    "name:zho_x_preferred":[
        "\u7f8a\u53f2\u5934\u6751"
    ],
    "wof:name":"Yangshitoucun",
    "wof:placetype":"locality"
},
  "geometry": {"coordinates":[110.45641000000001,35.9761],"type":"Point"}
}