{
  "type": "Feature",
  "properties": {
    "gn:admin1_code":"18",
    "gn:asciiname":"Langxi",
    "gn:country_code":"CN",
    "gn:dem":510,
    "gn:feature_class":"P",
    "gn:feature_code":"PPLA4",
    "gn:name":"Langxi",
    "gn:population":0,
    "gn:timezone":"Asia/Shanghai",
    "iso:country":"CN",
    "name:und_x_variant":[
        "Langxi Zhen"
    ],
    "name:zho_x_preferred":[
        "\u90ce\u6eaa"
    ],
    "name:zho_x_variant":[
        "\u90ce\u6eaa\u9547"
    ],
    "wof:name":"Langxi",
    "wof:placetype":"locality"
},
  "geometry": {"coordinates":[108.47877,28.0116],"type":"Point"}
}