{
  "type": "Feature",
  "properties": {
    "gn:admin1_code":"10",
    "gn:asciiname":"Jichangzhuang",
    "gn:country_code":"CN",
    "gn:dem":18,
    "gn:feature_class":"P",
    "gn:feature_code":"PPL",
    "gn:name":"Jichangzhuang",
    "gn:population":0,
    "gn:timezone":"Asia/Shanghai",
    "iso:country":"CN",
    "name:zho_x_preferred":[
        "\u5b63\u5e38\u5e84"
    ],
    "wof:name":"Jichangzhuang",
    "wof:placetype":"locality"
},
  "geometry": {"coordinates":[116.36687000000001,37.90315],"type":"Point"}
}