{
  "type": "Feature",
  "properties": {
    "gn:admin1_code":"26.0",
    "gn:asciiname":"Shangyaozhuang",
    "gn:country_code":"CN",
    "gn:dem":1595,
    "gn:feature_class":"P",
    "gn:feature_code":"PPL",
    "gn:name":"Shangyaozhuang",
    "gn:population":0,
    "gn:timezone":"Asia/Shanghai",
    "iso:country":"CN",
    "name:und_x_variant":[
        "\u4e0a\u7a91\u5e84"
    ],
    "wof:name":"Shangyaozhuang",
    "wof:placetype":"locality"
},
  "geometry": {"coordinates":[107.43022000000001,34.72499000000001],"type":"Point"}
}