{
  "type": "Feature",
  "properties": {
    "gn:admin1_code":"8.0",
    "gn:asciiname":"Jingchuncun",
    "gn:country_code":"CN",
    "gn:dem":123,
    "gn:feature_class":"P",
    "gn:feature_code":"PPL",
    "gn:name":"Jingchuncun",
    "gn:population":0,
    "gn:timezone":"Asia/Shanghai",
    "iso:country":"CN",
    "name:zho_x_preferred":[
        "\u4e95\u6625\u6751"
    ],
    "wof:name":"Jingchuncun",
    "wof:placetype":"locality"
},
  "geometry": {"coordinates":[129.87013999999999,46.81574000000001],"type":"Point"}
}