{
  "type": "Feature",
  "properties": {
    "gn:admin1_code":"19.0",
    "gn:asciiname":"Yangwanshao",
    "gn:country_code":"CN",
    "gn:dem":153,
    "gn:feature_class":"P",
    "gn:feature_code":"PPL",
    "gn:name":"Yangwanshao",
    "gn:population":0,
    "gn:timezone":"Asia/Shanghai",
    "iso:country":"CN",
    "name:und_x_variant":[
        "\u6768\u6e7e\u54e8"
    ],
    "wof:name":"Yangwanshao",
    "wof:placetype":"locality"
},
  "geometry": {"coordinates":[122.18300000000001,40.0223],"type":"Point"}
}