{
  "type": "Feature",
  "properties": {
    "gn:admin1_code":"14.0",
    "gn:asciiname":"Warigong",
    "gn:country_code":"CN",
    "gn:dem":3860,
    "gn:feature_class":"P",
    "gn:feature_code":"PPL",
    "gn:name":"Warigong",
    "gn:population":0,
    "gn:timezone":"Asia/Urumqi",
    "iso:country":"CN",
    "name:zho_x_preferred":[
        "\u54c7\u65e5\u8d21"
    ],
    "wof:name":"Warigong",
    "wof:placetype":"locality"
},
  "geometry": {"coordinates":[97.19,31.55003],"type":"Point"}
}