{
  "type": "Feature",
  "properties": {
    "gn:admin1_code":"30.0",
    "gn:asciiname":"Xichencun",
    "gn:country_code":"CN",
    "gn:dem":8,
    "gn:feature_class":"P",
    "gn:feature_code":"PPL",
    "gn:name":"Xichencun",
    "gn:population":0,
    "gn:timezone":"Asia/Shanghai",
    "iso:country":"CN",
    "name:zho_x_preferred":[
        "\u897f\u9648\u6751"
    ],
    "wof:name":"Xichencun",
    "wof:placetype":"locality"
},
  "geometry": {"coordinates":[116.39404999999999,23.53518],"type":"Point"}
}