{
  "type": "Feature",
  "properties": {
    "gn:admin1_code":"6.0",
    "gn:asciiname":"Huaita",
    "gn:country_code":"CN",
    "gn:dem":1766,
    "gn:feature_class":"P",
    "gn:feature_code":"PPL",
    "gn:name":"Huaita",
    "gn:population":0,
    "gn:timezone":"Asia/Shanghai",
    "iso:country":"CN",
    "name:und_x_variant":[
        "\u6000\u5854"
    ],
    "wof:name":"Huaita",
    "wof:placetype":"locality"
},
  "geometry": {"coordinates":[102.90304,35.85672],"type":"Point"}
}