{
  "type": "Feature",
  "properties": {
    "gn:admin1_code":"26.0",
    "gn:asciiname":"Jingyicun",
    "gn:country_code":"CN",
    "gn:dem":683,
    "gn:feature_class":"P",
    "gn:feature_code":"PPL",
    "gn:name":"Jingyicun",
    "gn:population":0,
    "gn:timezone":"Asia/Shanghai",
    "iso:country":"CN",
    "name:zho_x_preferred":[
        "\u4e95\u6ea2\u6751"
    ],
    "wof:name":"Jingyicun",
    "wof:placetype":"locality"
},
  "geometry": {"coordinates":[110.04946,35.16983],"type":"Point"}
}