{
  "type": "Feature",
  "properties": {
    "gn:admin1_code":"25.0",
    "gn:asciiname":"Xiaoguozhaiduxingcun",
    "gn:country_code":"CN",
    "gn:dem":40,
    "gn:feature_class":"P",
    "gn:feature_code":"PPL",
    "gn:name":"Xiaoguozhaiduxingcun",
    "gn:population":0,
    "gn:timezone":"Asia/Shanghai",
    "iso:country":"CN",
    "name:zho_x_preferred":[
        "\u5c0f\u90ed\u5be8\u675c\u884c\u6751"
    ],
    "wof:name":"Xiaoguozhaiduxingcun",
    "wof:placetype":"locality"
},
  "geometry": {"coordinates":[115.54704,36.65358],"type":"Point"}
}