{
  "type": "Feature",
  "properties": {
    "gn:admin1_code":"19.0",
    "gn:asciiname":"Zhenjia Buzi",
    "gn:country_code":"CN",
    "gn:dem":254,
    "gn:feature_class":"P",
    "gn:feature_code":"PPL",
    "gn:name":"Zhenjia Buzi",
    "gn:population":0,
    "gn:timezone":"Asia/Shanghai",
    "iso:country":"CN",
    "name:und_x_variant":[
        "Zhenjia Puzi",
        "\u7504\u5bb6\u5821\u5b50",
        "Zhenjia Buzi"
    ],
    "wof:name":"Zhenjia Buzi",
    "wof:placetype":"locality"
},
  "geometry": {"coordinates":[122.90431,40.07885],"type":"Point"}
}