{
  "type": "Feature",
  "properties": {
    "gn:admin1_code":"3.0",
    "gn:asciiname":"Xiatangyuan",
    "gn:country_code":"CN",
    "gn:dem":234,
    "gn:feature_class":"P",
    "gn:feature_code":"PPL",
    "gn:name":"Xiatangyuan",
    "gn:population":0,
    "gn:timezone":"Asia/Shanghai",
    "iso:country":"CN",
    "name:und_x_variant":[
        "\u4e0b\u5510\u6e90"
    ],
    "wof:name":"Xiatangyuan",
    "wof:placetype":"locality"
},
  "geometry": {"coordinates":[116.05012000000001,26.79209],"type":"Point"}
}