{
  "type": "Feature",
  "properties": {
    "gn:admin1_code":"7",
    "gn:asciiname":"Waihuangbo",
    "gn:country_code":"CN",
    "gn:dem":675,
    "gn:feature_class":"P",
    "gn:feature_code":"PPL",
    "gn:name":"Waihuangbo",
    "gn:population":0,
    "gn:timezone":"Asia/Shanghai",
    "iso:country":"CN",
    "name:und_x_variant":[
        "Huangpo",
        "Waihuangpo",
        "Waihuangbo"
    ],
    "wof:name":"Waihuangbo",
    "wof:placetype":"locality"
},
  "geometry": {"coordinates":[117.84618,25.11821],"type":"Point"}
}