{
  "type": "Feature",
  "properties": {
    "gn:admin1_code":"8.0",
    "gn:asciiname":"Zhongfucun",
    "gn:country_code":"CN",
    "gn:dem":204,
    "gn:feature_class":"P",
    "gn:feature_code":"PPL",
    "gn:name":"Zhongfucun",
    "gn:population":0,
    "gn:timezone":"Asia/Shanghai",
    "iso:country":"CN",
    "name:zho_x_preferred":[
        "\u4e2d\u752b\u6751"
    ],
    "wof:name":"Zhongfucun",
    "wof:placetype":"locality"
},
  "geometry": {"coordinates":[125.94562000000001,46.84463],"type":"Point"}
}