{
  "type": "Feature",
  "properties": {
    "gn:admin1_code":"19.0",
    "gn:asciiname":"Shangpiaoyingzi",
    "gn:country_code":"CN",
    "gn:dem":150,
    "gn:feature_class":"P",
    "gn:feature_code":"PPL",
    "gn:name":"Shangpiaoyingzi",
    "gn:population":0,
    "gn:timezone":"Asia/Shanghai",
    "iso:country":"CN",
    "name:zho_x_preferred":[
        "\u4e0a\u6f02\u8425\u5b50"
    ],
    "wof:name":"Shangpiaoyingzi",
    "wof:placetype":"locality"
},
  "geometry": {"coordinates":[122.09399999999999,42.2023],"type":"Point"}
}