{
  "type": "Feature",
  "properties": {
    "gn:admin1_code":"23.0",
    "gn:asciiname":"Zhaoxiang",
    "gn:country_code":"CN",
    "gn:dem":6,
    "gn:feature_class":"P",
    "gn:feature_code":"PPLA4",
    "gn:name":"Zhaoxiang",
    "gn:population":0,
    "gn:timezone":"Asia/Shanghai",
    "iso:country":"CN",
    "name:und_x_variant":[
        "Chao-hsiang",
        "Zhaoxiang",
        "\u8d75\u5df7"
    ],
    "wof:name":"Zhaoxiang",
    "wof:placetype":"locality"
},
  "geometry": {"coordinates":[121.19203,31.15194],"type":"Point"}
}