{
  "type": "Feature",
  "properties": {
    "gn:admin1_code":"19.0",
    "gn:asciiname":"Jiaojiagangzi",
    "gn:country_code":"CN",
    "gn:dem":125,
    "gn:feature_class":"P",
    "gn:feature_code":"PPL",
    "gn:name":"Jiaojiagangzi",
    "gn:population":0,
    "gn:timezone":"Asia/Shanghai",
    "iso:country":"CN",
    "name:und_x_variant":[
        "\u7126\u5bb6\u5c97\u5b50"
    ],
    "name:zho_x_preferred":[
        "\u7126\u5bb6\u5c97\u5b50"
    ],
    "wof:name":"Jiaojiagangzi",
    "wof:placetype":"locality"
},
  "geometry": {"coordinates":[123.50197,42.61848],"type":"Point"}
}