{
  "type": "Feature",
  "properties": {
    "gn:admin1_code":"11.0",
    "gn:asciiname":"Shangxuanlong",
    "gn:country_code":"CN",
    "gn:dem":752,
    "gn:feature_class":"P",
    "gn:feature_code":"PPL",
    "gn:name":"Shangxuanlong",
    "gn:population":0,
    "gn:timezone":"Asia/Shanghai",
    "iso:country":"CN",
    "name:zho_x_preferred":[
        "\u4e0a\u9009\u5785"
    ],
    "wof:name":"Shangxuanlong",
    "wof:placetype":"locality"
},
  "geometry": {"coordinates":[113.87696,25.6748],"type":"Point"}
}