{
  "type": "Feature",
  "properties": {
    "gn:admin1_code":"19.0",
    "gn:asciiname":"Xiaoyecun",
    "gn:country_code":"CN",
    "gn:dem":45,
    "gn:feature_class":"P",
    "gn:feature_code":"PPL",
    "gn:name":"Xiaoyecun",
    "gn:population":0,
    "gn:timezone":"Asia/Shanghai",
    "iso:country":"CN",
    "name:und_x_variant":[
        "Xiaoyebao",
        "Xiaoyebu"
    ],
    "name:zho_x_preferred":[
        "\u5c0f\u4e1a\u6751"
    ],
    "name:zho_x_variant":[
        "\u5c0f\u4e1a\u5821"
    ],
    "wof:name":"Xiaoyecun",
    "wof:placetype":"locality"
},
  "geometry": {"coordinates":[121.2384,41.19407],"type":"Point"}
}