{
  "type": "Feature",
  "properties": {
    "gn:admin1_code":"19.0",
    "gn:asciiname":"Shimiaozi",
    "gn:country_code":"CN",
    "gn:dem":183,
    "gn:feature_class":"P",
    "gn:feature_code":"PPL",
    "gn:name":"Shimiaozi",
    "gn:population":0,
    "gn:timezone":"Asia/Shanghai",
    "iso:country":"CN",
    "name:und_x_variant":[
        "\u77f3\u5e99\u5b50"
    ],
    "name:zho_x_preferred":[
        "\u77f3\u5e99\u5b50"
    ],
    "wof:name":"Shimiaozi",
    "wof:placetype":"locality"
},
  "geometry": {"coordinates":[122.30161,39.80739000000001],"type":"Point"}
}