{
  "type": "Feature",
  "properties": {
    "gn:admin1_code":"13.0",
    "gn:asciiname":"Julesatema",
    "gn:country_code":"CN",
    "gn:dem":5055,
    "gn:feature_class":"P",
    "gn:feature_code":"PPL",
    "gn:name":"Julesatema",
    "gn:population":0,
    "gn:timezone":"Asia/Urumqi",
    "iso:country":"CN",
    "name:zho_x_preferred":[
        "\u5de8\u52d2\u8428\u7279\u739b"
    ],
    "wof:name":"Julesatema",
    "wof:placetype":"locality"
},
  "geometry": {"coordinates":[85.81824,37.21508],"type":"Point"}
}