{
  "type": "Feature",
  "properties": {
    "gn:admin1_code":"20",
    "gn:admin2_code":"8617184",
    "gn:asciiname":"Bayan Hot",
    "gn:country_code":"CN",
    "gn:dem":1529,
    "gn:feature_class":"P",
    "gn:feature_code":"PPLA3",
    "gn:name":"Bayan Hot",
    "gn:population":0,
    "gn:timezone":"Asia/Shanghai",
    "iso:country":"CN",
    "name:und_x_variant":[
        "Pa-yen-hao-t\u2019e-shih",
        "Bayinhot",
        "Pa-yin-hao-t\u2019e",
        "Bayenhot",
        "Pa-yen-hao-t\u2019e",
        "A-la-shan-tso-ch\u2019i",
        "Pa-yen-hao-t\u2019e-chen",
        "A-la-shan-ch\u2019i",
        "Ting-y\u00fcan-ying",
        "Alxa Zuoqi",
        "Tsz\u00f6khushechzhitszyuy",
        "Tzu-hu-she-chih-ch\u00fc",
        "Tzu-hu",
        "Bayan Hot",
        "\u5df4\u5f66\u6d69\u7279",
        "Bayanhaote Zhen",
        "Alashanzuo Qi",
        "\u5df4\u5f66\u6d69\u7279\u9547",
        "\u963f\u62c9\u5584\u5de6\u65d7"
    ],
    "wof:name":"Bayan Hot",
    "wof:placetype":"locality"
},
  "geometry": {"coordinates":[105.66861000000002,38.83861],"type":"Point"}
}