{
  "type": "Feature",
  "properties": {
    "gn:admin1_code":"4.0",
    "gn:asciiname":"Xinghou",
    "gn:country_code":"CN",
    "gn:dem":4,
    "gn:feature_class":"P",
    "gn:feature_code":"PPL",
    "gn:name":"Xinghou",
    "gn:population":0,
    "gn:timezone":"Asia/Shanghai",
    "iso:country":"CN",
    "name:zho_x_preferred":[
        "Xinghou"
    ],
    "name:zho_x_variant":[
        "\u5174\u540e"
    ],
    "wof:name":"Xinghou",
    "wof:placetype":"locality"
},
  "geometry": {"coordinates":[119.1609,34.90024],"type":"Point"}
}