{
  "type": "Feature",
  "properties": {
    "gn:admin1_code":"12.0",
    "gn:asciiname":"Jinghenao",
    "gn:country_code":"CN",
    "gn:dem":28,
    "gn:feature_class":"P",
    "gn:feature_code":"PPL",
    "gn:name":"Jinghenao",
    "gn:population":0,
    "gn:timezone":"Asia/Shanghai",
    "iso:country":"CN",
    "name:zho_x_preferred":[
        "\u8346\u6cb3\u8111"
    ],
    "wof:name":"Jinghenao",
    "wof:placetype":"locality"
},
  "geometry": {"coordinates":[113.13341,29.47998],"type":"Point"}
}