{
  "type": "Feature",
  "properties": {
    "gn:admin1_code":"2.0",
    "gn:asciiname":"Fenshuitang",
    "gn:country_code":"CN",
    "gn:dem":190,
    "gn:feature_class":"P",
    "gn:feature_code":"PPL",
    "gn:name":"Fenshuitang",
    "gn:population":0,
    "gn:timezone":"Asia/Shanghai",
    "iso:country":"CN",
    "name:und_x_variant":[
        "\u5206\u6c34\u5858",
        "Fenshuitang"
    ],
    "wof:name":"Fenshuitang",
    "wof:placetype":"locality"
},
  "geometry": {"coordinates":[119.96028,29.35139],"type":"Point"}
}