{
  "type": "Feature",
  "properties": {
    "gn:admin1_code":"5.0",
    "gn:asciiname":"Lamahuduga",
    "gn:country_code":"CN",
    "gn:dem":147,
    "gn:feature_class":"P",
    "gn:feature_code":"PPL",
    "gn:name":"Lamahuduga",
    "gn:population":0,
    "gn:timezone":"Asia/Shanghai",
    "iso:country":"CN",
    "name:zho_x_preferred":[
        "\u5587\u561b\u6237\u90fd\u560e"
    ],
    "wof:name":"Lamahuduga",
    "wof:placetype":"locality"
},
  "geometry": {"coordinates":[123.08723999999999,44.56674],"type":"Point"}
}