{
  "type": "Feature",
  "properties": {
    "gn:admin1_code":"19.0",
    "gn:asciiname":"Chengjia Buzi",
    "gn:country_code":"CN",
    "gn:dem":159,
    "gn:feature_class":"P",
    "gn:feature_code":"PPL",
    "gn:name":"Chengjia Buzi",
    "gn:population":0,
    "gn:timezone":"Asia/Shanghai",
    "iso:country":"CN",
    "name:und_x_variant":[
        "Chengjia Puzi",
        "\u7a0b\u5bb6\u5821\u5b50",
        "Chengjia Buzi"
    ],
    "wof:name":"Chengjia Buzi",
    "wof:placetype":"locality"
},
  "geometry": {"coordinates":[122.92532,40.10057000000001],"type":"Point"}
}