{
  "type": "Feature",
  "properties": {
    "gn:admin1_code":"8.0",
    "gn:asciiname":"Miaoling",
    "gn:country_code":"CN",
    "gn:dem":258,
    "gn:feature_class":"P",
    "gn:feature_code":"PPL",
    "gn:name":"Miaoling",
    "gn:population":0,
    "gn:timezone":"Asia/Shanghai",
    "iso:country":"CN",
    "name:und_x_variant":[
        "\u5e99\u5cad"
    ],
    "wof:name":"Miaoling",
    "wof:placetype":"locality"
},
  "geometry": {"coordinates":[131.20906000000002,43.81376],"type":"Point"}
}