{
  "type": "Feature",
  "properties": {
    "gn:admin1_code":"15.0",
    "gn:asciiname":"Sunjia Zhaizi",
    "gn:country_code":"CN",
    "gn:dem":1325,
    "gn:feature_class":"P",
    "gn:feature_code":"PPL",
    "gn:name":"Sunjia Zhaizi",
    "gn:population":0,
    "gn:timezone":"Asia/Shanghai",
    "iso:country":"CN",
    "name:zho_x_preferred":[
        "\u5b59\u5bb6\u5be8\u5b50"
    ],
    "wof:name":"Sunjia Zhaizi",
    "wof:placetype":"locality"
},
  "geometry": {"coordinates":[103.364,38.9878],"type":"Point"}
}