{
  "type": "Feature",
  "properties": {
    "gn:admin1_code":"4.0",
    "gn:asciiname":"Jiangyuanli",
    "gn:country_code":"CN",
    "gn:dem":4,
    "gn:feature_class":"P",
    "gn:feature_code":"PPL",
    "gn:name":"Jiangyuanli",
    "gn:population":0,
    "gn:timezone":"Asia/Shanghai",
    "iso:country":"CN",
    "name:zho_x_preferred":[
        "\u848b\u56ed\u91cc"
    ],
    "wof:name":"Jiangyuanli",
    "wof:placetype":"locality"
},
  "geometry": {"coordinates":[119.78198999999999,31.92919],"type":"Point"}
}