{
  "type": "Feature",
  "properties": {
    "gn:admin1_code":"32.0",
    "gn:asciiname":"Zhujiashan",
    "gn:country_code":"CN",
    "gn:dem":667,
    "gn:feature_class":"P",
    "gn:feature_code":"PPL",
    "gn:name":"Zhujiashan",
    "gn:population":0,
    "gn:timezone":"Asia/Shanghai",
    "iso:country":"CN",
    "name:zho_x_preferred":[
        "\u795d\u5bb6\u5c71"
    ],
    "wof:name":"Zhujiashan",
    "wof:placetype":"locality"
},
  "geometry": {"coordinates":[103.3974,30.10929],"type":"Point"}
}