{
  "type": "Feature",
  "properties": {
    "gn:admin1_code":"8.0",
    "gn:asciiname":"Ma'anshan Yisidui",
    "gn:country_code":"CN",
    "gn:dem":373,
    "gn:feature_class":"P",
    "gn:feature_code":"PPLF",
    "gn:name":"Ma\u2019anshan Yisidui",
    "gn:population":0,
    "gn:timezone":"Asia/Shanghai",
    "iso:country":"CN",
    "name:und_x_variant":[
        "Ma\u2019anshan Yisidui"
    ],
    "name:zho_x_preferred":[
        "\u9a6c\u978d\u5c71\u4e00\u56db\u961f"
    ],
    "wof:name":"Ma'anshan Yisidui",
    "wof:placetype":"locality"
},
  "geometry": {"coordinates":[126.08665000000001,50.6103],"type":"Point"}
}