{
  "type": "Feature",
  "properties": {
    "gn:admin1_code":"4.0",
    "gn:asciiname":"Xinchuan Sizu",
    "gn:country_code":"CN",
    "gn:dem":3,
    "gn:feature_class":"P",
    "gn:feature_code":"PPLF",
    "gn:name":"Xinchuan Sizu",
    "gn:population":0,
    "gn:timezone":"Asia/Shanghai",
    "iso:country":"CN",
    "name:und_x_variant":[
        "\u65b0\u5ddd\u56db\u7ec4"
    ],
    "name:zho_x_preferred":[
        "\u65b0\u5ddd\u56db\u7ec4"
    ],
    "wof:name":"Xinchuan Sizu",
    "wof:placetype":"locality"
},
  "geometry": {"coordinates":[120.85914,32.66122],"type":"Point"}
}