{
  "type": "Feature",
  "properties": {
    "gn:admin1_code":"25.0",
    "gn:asciiname":"Guojiahe",
    "gn:country_code":"CN",
    "gn:dem":125,
    "gn:feature_class":"P",
    "gn:feature_code":"PPL",
    "gn:name":"Guojiahe",
    "gn:population":0,
    "gn:timezone":"Asia/Shanghai",
    "iso:country":"CN",
    "name:zho_x_preferred":[
        "\u90ed\u5bb6\u6cb3"
    ],
    "wof:name":"Guojiahe",
    "wof:placetype":"locality"
},
  "geometry": {"coordinates":[120.35772,37.32528],"type":"Point"}
}