{
  "type": "Feature",
  "properties": {
    "gn:admin1_code":"29.0",
    "gn:asciiname":"Bafu",
    "gn:country_code":"CN",
    "gn:dem":1447,
    "gn:feature_class":"P",
    "gn:feature_code":"PPL",
    "gn:name":"Bafu",
    "gn:population":0,
    "gn:timezone":"Asia/Shanghai",
    "iso:country":"CN",
    "name:zho_x_preferred":[
        "\u575d\u592b"
    ],
    "wof:name":"Bafu",
    "wof:placetype":"locality"
},
  "geometry": {"coordinates":[101.77800000000001,22.9676],"type":"Point"}
}