{
  "type": "Feature",
  "properties": {
    "gn:admin1_code":"16",
    "gn:asciiname":"Qiaotoupu",
    "gn:country_code":"CN",
    "gn:dem":157,
    "gn:feature_class":"P",
    "gn:feature_code":"PPL",
    "gn:name":"Qiaotoupu",
    "gn:population":0,
    "gn:timezone":"Asia/Shanghai",
    "iso:country":"CN",
    "name:zho_x_preferred":[
        "\u6865\u5934\u94fa"
    ],
    "wof:name":"Qiaotoupu",
    "wof:placetype":"locality"
},
  "geometry": {"coordinates":[110.56999999999999,24.87],"type":"Point"}
}