{
  "type": "Feature",
  "properties": {
    "gn:admin1_code":"4.0",
    "gn:asciiname":"Xinyangchang",
    "gn:country_code":"CN",
    "gn:dem":53,
    "gn:feature_class":"P",
    "gn:feature_code":"PPL",
    "gn:name":"Xinyangchang",
    "gn:population":0,
    "gn:timezone":"Asia/Shanghai",
    "iso:country":"CN",
    "name:zho_x_preferred":[
        "\u65b0\u6768\u660c"
    ],
    "wof:name":"Xinyangchang",
    "wof:placetype":"locality"
},
  "geometry": {"coordinates":[118.64100000000001,34.6075],"type":"Point"}
}