{
  "type": "Feature",
  "properties": {
    "gn:admin1_code":"1.0",
    "gn:asciiname":"Taoloucun",
    "gn:country_code":"CN",
    "gn:dem":41,
    "gn:feature_class":"P",
    "gn:feature_code":"PPL",
    "gn:name":"Taoloucun",
    "gn:population":0,
    "gn:timezone":"Asia/Shanghai",
    "iso:country":"CN",
    "name:zho_x_preferred":[
        "\u9676\u697c\u6751"
    ],
    "wof:name":"Taoloucun",
    "wof:placetype":"locality"
},
  "geometry": {"coordinates":[116.89349,34.21887],"type":"Point"}
}