{
  "type": "Feature",
  "properties": {
    "gn:admin1_code":"32.0",
    "gn:asciiname":"Hongchunwan",
    "gn:country_code":"CN",
    "gn:dem":1291,
    "gn:feature_class":"P",
    "gn:feature_code":"PPL",
    "gn:name":"Hongchunwan",
    "gn:population":0,
    "gn:timezone":"Asia/Shanghai",
    "iso:country":"CN",
    "name:zho_x_preferred":[
        "\u7ea2\u6625\u6e7e"
    ],
    "wof:name":"Hongchunwan",
    "wof:placetype":"locality"
},
  "geometry": {"coordinates":[105.03400000000001,32.5167],"type":"Point"}
}