{
  "type": "Feature",
  "properties": {
    "gn:admin1_code":"3.0",
    "gn:asciiname":"Jiangyangkeng",
    "gn:country_code":"CN",
    "gn:dem":575,
    "gn:feature_class":"P",
    "gn:feature_code":"PPL",
    "gn:name":"Jiangyangkeng",
    "gn:population":0,
    "gn:timezone":"Asia/Shanghai",
    "iso:country":"CN",
    "name:zho_x_preferred":[
        "\u5c06\u9633\u5751"
    ],
    "wof:name":"Jiangyangkeng",
    "wof:placetype":"locality"
},
  "geometry": {"coordinates":[117.45954,27.97884],"type":"Point"}
}