{
  "type": "Feature",
  "properties": {
    "gn:admin1_code":"20.0",
    "gn:asciiname":"Nuanquanzi",
    "gn:country_code":"CN",
    "gn:dem":757,
    "gn:feature_class":"P",
    "gn:feature_code":"PPL",
    "gn:name":"Nuanquanzi",
    "gn:population":0,
    "gn:timezone":"Asia/Shanghai",
    "iso:country":"CN",
    "name:zho_x_preferred":[
        "\u6696\u6cc9\u5b50"
    ],
    "wof:name":"Nuanquanzi",
    "wof:placetype":"locality"
},
  "geometry": {"coordinates":[120.93492000000001,48.97338],"type":"Point"}
}