{
  "type": "Feature",
  "properties": {
    "gn:admin1_code":"24",
    "gn:asciiname":"Shangxiyaojie",
    "gn:country_code":"CN",
    "gn:dem":1598,
    "gn:feature_class":"P",
    "gn:feature_code":"PPL",
    "gn:name":"Shangxiyaojie",
    "gn:population":0,
    "gn:timezone":"Asia/Shanghai",
    "iso:country":"CN",
    "wof:name":"Shangxiyaojie",
    "wof:placetype":"locality"
},
  "geometry": {"coordinates":[113.72889000000001,39.11528],"type":"Point"}
}