{
  "type": "Feature",
  "properties": {
    "gn:admin1_code":"26",
    "gn:asciiname":"Mozhangcun",
    "gn:country_code":"CN",
    "gn:dem":368,
    "gn:feature_class":"P",
    "gn:feature_code":"PPL",
    "gn:name":"Mozhangcun",
    "gn:population":0,
    "gn:timezone":"Asia/Shanghai",
    "iso:country":"CN",
    "name:zho_x_preferred":[
        "\u964c\u5f20\u6751"
    ],
    "wof:name":"Mozhangcun",
    "wof:placetype":"locality"
},
  "geometry": {"coordinates":[109.48312,34.74028],"type":"Point"}
}