{
  "type": "Feature",
  "properties": {
    "gn:admin1_code":"29.0",
    "gn:asciiname":"Xiaxinzhai",
    "gn:country_code":"CN",
    "gn:dem":1598,
    "gn:feature_class":"P",
    "gn:feature_code":"PPL",
    "gn:name":"Xiaxinzhai",
    "gn:population":0,
    "gn:timezone":"Asia/Shanghai",
    "iso:country":"CN",
    "name:zho_x_preferred":[
        "\u4e0b\u65b0\u5be8"
    ],
    "wof:name":"Xiaxinzhai",
    "wof:placetype":"locality"
},
  "geometry": {"coordinates":[101.51900000000001,23.239],"type":"Point"}
}