{
  "type": "Feature",
  "properties": {
    "gn:admin1_code":"25",
    "gn:asciiname":"Xianrenqiao",
    "gn:country_code":"CN",
    "gn:dem":53,
    "gn:feature_class":"P",
    "gn:feature_code":"PPL",
    "gn:name":"Xianrenqiao",
    "gn:population":0,
    "gn:timezone":"Asia/Shanghai",
    "iso:country":"CN",
    "name:zho_x_preferred":[
        "\u4ed9\u4eba\u6865"
    ],
    "wof:name":"Xianrenqiao",
    "wof:placetype":"locality"
},
  "geometry": {"coordinates":[117.68300000000001,34.7673],"type":"Point"}
}