{
  "type": "Feature",
  "properties": {
    "gn:admin1_code":"29.0",
    "gn:asciiname":"Luping",
    "gn:country_code":"CN",
    "gn:dem":1681,
    "gn:feature_class":"P",
    "gn:feature_code":"PPL",
    "gn:name":"L\u00fcping",
    "gn:population":0,
    "gn:timezone":"Asia/Shanghai",
    "iso:country":"CN",
    "name:und_x_variant":[
        "L\u00fcping",
        "\u7eff\u576a"
    ],
    "wof:name":"Luping",
    "wof:placetype":"locality"
},
  "geometry": {"coordinates":[103.09573,26.48121],"type":"Point"}
}