{
  "type": "Feature",
  "properties": {
    "gn:admin1_code":"19.0",
    "gn:asciiname":"Foyelingcun",
    "gn:country_code":"CN",
    "gn:dem":198,
    "gn:feature_class":"P",
    "gn:feature_code":"PPL",
    "gn:name":"Foyelingcun",
    "gn:population":0,
    "gn:timezone":"Asia/Shanghai",
    "iso:country":"CN",
    "name:zho_x_preferred":[
        "\u4f5b\u7237\u5cad\u6751"
    ],
    "wof:name":"Foyelingcun",
    "wof:placetype":"locality"
},
  "geometry": {"coordinates":[121.928,42.0101],"type":"Point"}
}