{
  "type": "Feature",
  "properties": {
    "gn:admin1_code":"26.0",
    "gn:asciiname":"Duanjiayuancun",
    "gn:country_code":"CN",
    "gn:dem":954,
    "gn:feature_class":"P",
    "gn:feature_code":"PPL",
    "gn:name":"Duanjiayuancun",
    "gn:population":0,
    "gn:timezone":"Asia/Shanghai",
    "iso:country":"CN",
    "name:zho_x_preferred":[
        "\u6bb5\u5bb6\u586c\u6751"
    ],
    "wof:name":"Duanjiayuancun",
    "wof:placetype":"locality"
},
  "geometry": {"coordinates":[109.38195,35.18004000000001],"type":"Point"}
}