{
  "type": "Feature",
  "properties": {
    "gn:admin1_code":"15.0",
    "gn:asciiname":"Gangzipan",
    "gn:country_code":"CN",
    "gn:dem":1262,
    "gn:feature_class":"P",
    "gn:feature_code":"PPL",
    "gn:name":"Gangzipan",
    "gn:population":0,
    "gn:timezone":"Asia/Shanghai",
    "iso:country":"CN",
    "name:und_x_variant":[
        "\u5c97\u5b50\u7554"
    ],
    "wof:name":"Gangzipan",
    "wof:placetype":"locality"
},
  "geometry": {"coordinates":[107.40685000000001,36.33851],"type":"Point"}
}