{
  "type": "Feature",
  "properties": {
    "gn:admin1_code":"29.0",
    "gn:asciiname":"Menglongdi",
    "gn:country_code":"CN",
    "gn:dem":2189,
    "gn:feature_class":"P",
    "gn:feature_code":"PPL",
    "gn:name":"Menglongdi",
    "gn:population":0,
    "gn:timezone":"Asia/Shanghai",
    "iso:country":"CN",
    "name:zho_x_preferred":[
        "\u66da\u663d\u5e95"
    ],
    "wof:name":"Menglongdi",
    "wof:placetype":"locality"
},
  "geometry": {"coordinates":[103.619,26.7789],"type":"Point"}
}