{
  "type": "Feature",
  "properties": {
    "gn:admin1_code":"26.0",
    "gn:asciiname":"Xiaojiazhuangwu",
    "gn:country_code":"CN",
    "gn:dem":941,
    "gn:feature_class":"P",
    "gn:feature_code":"PPL",
    "gn:name":"Xiaojiazhuangwu",
    "gn:population":0,
    "gn:timezone":"Asia/Shanghai",
    "iso:country":"CN",
    "name:zho_x_preferred":[
        "\u8096\u5bb6\u5e84\u5c4b"
    ],
    "wof:name":"Xiaojiazhuangwu",
    "wof:placetype":"locality"
},
  "geometry": {"coordinates":[108.94798,32.34155],"type":"Point"}
}