{
  "type": "Feature",
  "properties": {
    "gn:admin1_code":"15.0",
    "gn:asciiname":"Luoda",
    "gn:country_code":"CN",
    "gn:dem":1704,
    "gn:feature_class":"P",
    "gn:feature_code":"PPLA4",
    "gn:name":"Luoda",
    "gn:population":0,
    "gn:timezone":"Asia/Shanghai",
    "iso:country":"CN",
    "name:und_x_variant":[
        "\u6d1b\u5927"
    ],
    "name:zho_x_preferred":[
        "\u6d1b\u5927"
    ],
    "wof:name":"Luoda",
    "wof:placetype":"locality"
},
  "geometry": {"coordinates":[103.98081000000001,33.98619],"type":"Point"}
}