{
  "type": "Feature",
  "properties": {
    "gn:admin1_code":"5.0",
    "gn:asciiname":"Bo'aicun",
    "gn:country_code":"CN",
    "gn:dem":123,
    "gn:feature_class":"P",
    "gn:feature_code":"PPL",
    "gn:name":"Bo\u2019aicun",
    "gn:population":0,
    "gn:timezone":"Asia/Shanghai",
    "iso:country":"CN",
    "name:und_x_variant":[
        "Bo\u2019aicun"
    ],
    "name:zho_x_preferred":[
        "\u535a\u7231\u6751"
    ],
    "wof:name":"Bo'aicun",
    "wof:placetype":"locality"
},
  "geometry": {"coordinates":[123.83125,43.63541],"type":"Point"}
}