{
  "type": "Feature",
  "properties": {
    "gn:admin1_code":"30.0",
    "gn:asciiname":"Shuangdong",
    "gn:country_code":"CN",
    "gn:dem":46,
    "gn:feature_class":"P",
    "gn:feature_code":"PPLA4",
    "gn:name":"Shuangdong",
    "gn:population":0,
    "gn:timezone":"Asia/Shanghai",
    "iso:country":"CN",
    "name:und_x_variant":[
        "Shuangdong Jiedao"
    ],
    "name:zho_x_preferred":[
        "\u53cc\u4e1c"
    ],
    "name:zho_x_variant":[
        "\u53cc\u4e1c\u8857\u9053"
    ],
    "wof:name":"Shuangdong",
    "wof:placetype":"locality"
},
  "geometry": {"coordinates":[111.59596999999999,22.79348],"type":"Point"}
}