{
  "type": "Feature",
  "properties": {
    "gn:admin1_code":"18",
    "gn:asciiname":"Gaoyuankou",
    "gn:country_code":"CN",
    "gn:dem":1212,
    "gn:feature_class":"P",
    "gn:feature_code":"PPL",
    "gn:name":"Gaoyuankou",
    "gn:population":0,
    "gn:timezone":"Asia/Shanghai",
    "iso:country":"CN",
    "name:zho_x_preferred":[
        "\u9ad8\u82d1\u53e3"
    ],
    "wof:name":"Gaoyuankou",
    "wof:placetype":"locality"
},
  "geometry": {"coordinates":[106.651,26.0276],"type":"Point"}
}