{
  "type": "Feature",
  "properties": {
    "gn:admin1_code":"31",
    "gn:asciiname":"Shukai",
    "gn:country_code":"CN",
    "gn:dem":21,
    "gn:feature_class":"P",
    "gn:feature_code":"PPL",
    "gn:name":"Shukai",
    "gn:population":0,
    "gn:timezone":"Asia/Shanghai",
    "iso:country":"CN",
    "name:und_x_variant":[
        "\u4e66\u5f00",
        "Jiekai"
    ],
    "wof:name":"Shukai",
    "wof:placetype":"locality"
},
  "geometry": {"coordinates":[109.419,19.8427],"type":"Point"}
}