{
  "type": "Feature",
  "properties": {
    "gn:admin1_code":"2.0",
    "gn:asciiname":"Zhucun",
    "gn:country_code":"CN",
    "gn:dem":40,
    "gn:feature_class":"P",
    "gn:feature_code":"PPL",
    "gn:name":"Zhucun",
    "gn:population":0,
    "gn:timezone":"Asia/Shanghai",
    "iso:country":"CN",
    "name:und_x_variant":[
        "\u6731\u6751"
    ],
    "wof:name":"Zhucun",
    "wof:placetype":"locality"
},
  "geometry": {"coordinates":[119.99563999999999,30.94917],"type":"Point"}
}