{
  "type": "Feature",
  "properties": {
    "gn:admin1_code":"2.0",
    "gn:asciiname":"Fang'aoyang",
    "gn:country_code":"CN",
    "gn:dem":50,
    "gn:feature_class":"P",
    "gn:feature_code":"PPL",
    "gn:name":"Fang\u2019aoyang",
    "gn:population":0,
    "gn:timezone":"Asia/Shanghai",
    "iso:country":"CN",
    "name:und_x_variant":[
        "Fang\u2019aoyang"
    ],
    "name:zho_x_preferred":[
        "\u65b9\u5c99\u579f"
    ],
    "wof:name":"Fang'aoyang",
    "wof:placetype":"locality"
},
  "geometry": {"coordinates":[120.56235,28.15376],"type":"Point"}
}