{
  "type": "Feature",
  "properties": {
    "gn:admin1_code":"26",
    "gn:asciiname":"Dongchakou",
    "gn:country_code":"CN",
    "gn:dem":857,
    "gn:feature_class":"P",
    "gn:feature_code":"PPL",
    "gn:name":"Dongchakou",
    "gn:population":0,
    "gn:timezone":"Asia/Shanghai",
    "iso:country":"CN",
    "name:zho_x_preferred":[
        "\u4e1c\u5c94\u53e3"
    ],
    "wof:name":"Dongchakou",
    "wof:placetype":"locality"
},
  "geometry": {"coordinates":[108.41494,34.02644],"type":"Point"}
}