{
  "type": "Feature",
  "properties": {
    "gn:admin1_code":"26.0",
    "gn:asciiname":"Luojia Goucun",
    "gn:country_code":"CN",
    "gn:dem":997,
    "gn:feature_class":"P",
    "gn:feature_code":"PPL",
    "gn:name":"Luojia Goucun",
    "gn:population":0,
    "gn:timezone":"Asia/Shanghai",
    "iso:country":"CN",
    "name:zho_x_preferred":[
        "\u7f57\u5bb6\u6c9f\u6751"
    ],
    "wof:name":"Luojia Goucun",
    "wof:placetype":"locality"
},
  "geometry": {"coordinates":[110.39100000000001,37.5351],"type":"Point"}
}