{
  "type": "Feature",
  "properties": {
    "gn:admin1_code":"11.0",
    "gn:asciiname":"Jiaotouwo",
    "gn:country_code":"CN",
    "gn:dem":855,
    "gn:feature_class":"P",
    "gn:feature_code":"PPL",
    "gn:name":"Jiaotouwo",
    "gn:population":0,
    "gn:timezone":"Asia/Shanghai",
    "iso:country":"CN",
    "name:zho_x_preferred":[
        "\u8549\u5934\u7a9d"
    ],
    "wof:name":"Jiaotouwo",
    "wof:placetype":"locality"
},
  "geometry": {"coordinates":[111.63324,24.8167],"type":"Point"}
}