{
  "type": "Feature",
  "properties": {
    "gn:admin1_code":"9.0",
    "gn:asciiname":"Longwangmiao",
    "gn:country_code":"CN",
    "gn:dem":78,
    "gn:feature_class":"P",
    "gn:feature_code":"PPL",
    "gn:name":"Longwangmiao",
    "gn:population":0,
    "gn:timezone":"Asia/Shanghai",
    "iso:country":"CN",
    "name:zho_x_preferred":[
        "\u9f99\u738b\u5e99"
    ],
    "wof:name":"Longwangmiao",
    "wof:placetype":"locality"
},
  "geometry": {"coordinates":[114.26021,34.71371],"type":"Point"}
}