{
  "type": "Feature",
  "properties": {
    "gn:admin1_code":"10",
    "gn:asciiname":"Yangshudixia",
    "gn:country_code":"CN",
    "gn:dem":512,
    "gn:feature_class":"P",
    "gn:feature_code":"PPL",
    "gn:name":"Yangshudixia",
    "gn:population":0,
    "gn:timezone":"Asia/Shanghai",
    "iso:country":"CN",
    "name:zho_x_preferred":[
        "\u6768\u6811\u5e95\u4e0b"
    ],
    "wof:name":"Yangshudixia",
    "wof:placetype":"locality"
},
  "geometry": {"coordinates":[118.84917,40.58555],"type":"Point"}
}