{
  "type": "Feature",
  "properties": {
    "gn:admin1_code":"8.0",
    "gn:asciiname":"Jinbian Fenchang",
    "gn:country_code":"CN",
    "gn:dem":223,
    "gn:feature_class":"P",
    "gn:feature_code":"PPL",
    "gn:name":"Jinbian Fenchang",
    "gn:population":0,
    "gn:timezone":"Asia/Shanghai",
    "iso:country":"CN",
    "name:zho_x_preferred":[
        "\u91d1\u8fb9\u5206\u573a"
    ],
    "wof:name":"Jinbian Fenchang",
    "wof:placetype":"locality"
},
  "geometry": {"coordinates":[124.14230999999999,48.36882],"type":"Point"}
}