{
  "type": "Feature",
  "properties": {
    "gn:admin1_code":"14.0",
    "gn:asciiname":"Woqiongcun",
    "gn:country_code":"CN",
    "gn:dem":4563,
    "gn:feature_class":"P",
    "gn:feature_code":"PPL",
    "gn:name":"Woqiongcun",
    "gn:population":0,
    "gn:timezone":"Asia/Shanghai",
    "iso:country":"CN",
    "name:zho_x_preferred":[
        "\u7a9d\u7a77\u6751"
    ],
    "wof:name":"Woqiongcun",
    "wof:placetype":"locality"
},
  "geometry": {"coordinates":[82.79021999999998,32.97723],"type":"Point"}
}