{
  "type": "Feature",
  "properties": {
    "gn:admin1_code":"4.0",
    "gn:asciiname":"Fanmingcun",
    "gn:country_code":"CN",
    "gn:dem":4,
    "gn:feature_class":"P",
    "gn:feature_code":"PPL",
    "gn:name":"Fanmingcun",
    "gn:population":0,
    "gn:timezone":"Asia/Shanghai",
    "iso:country":"CN",
    "name:und_x_variant":[
        "\u8303\u660e\u6751",
        "Fanming",
        "\u8303\u660e"
    ],
    "wof:name":"Fanmingcun",
    "wof:placetype":"locality"
},
  "geometry": {"coordinates":[121.52554000000001,32.01793],"type":"Point"}
}