{
  "type": "Feature",
  "properties": {
    "gn:admin1_code":"32.0",
    "gn:asciiname":"Luhe",
    "gn:country_code":"CN",
    "gn:dem":2959,
    "gn:feature_class":"P",
    "gn:feature_code":"PPL",
    "gn:name":"Luhe",
    "gn:population":0,
    "gn:timezone":"Asia/Shanghai",
    "iso:country":"CN",
    "name:zho_x_preferred":[
        "\u8def\u6cb3"
    ],
    "wof:name":"Luhe",
    "wof:placetype":"locality"
},
  "geometry": {"coordinates":[101.176,28.062],"type":"Point"}
}