{
  "type": "Feature",
  "properties": {
    "gn:admin1_code":"18",
    "gn:asciiname":"Haima",
    "gn:country_code":"CN",
    "gn:dem":1465,
    "gn:feature_class":"P",
    "gn:feature_code":"PPL",
    "gn:name":"Haima",
    "gn:population":0,
    "gn:timezone":"Asia/Shanghai",
    "iso:country":"CN",
    "name:nld_x_preferred":[
        "Haima"
    ],
    "name:zho_x_preferred":[
        "\u6d77\u9a6c"
    ],
    "wof:name":"Haima",
    "wof:placetype":"locality"
},
  "geometry": {"coordinates":[105.212,25.5692],"type":"Point"}
}