{
  "type": "Feature",
  "properties": {
    "gn:admin1_code":"11.0",
    "gn:asciiname":"Dashiling",
    "gn:country_code":"CN",
    "gn:dem":458,
    "gn:feature_class":"P",
    "gn:feature_code":"PPL",
    "gn:name":"Dashiling",
    "gn:population":0,
    "gn:timezone":"Asia/Shanghai",
    "iso:country":"CN",
    "name:zho_x_preferred":[
        "\u6253\u77f3\u5cad"
    ],
    "wof:name":"Dashiling",
    "wof:placetype":"locality"
},
  "geometry": {"coordinates":[110.3694,26.49645],"type":"Point"}
}