{
  "type": "Feature",
  "properties": {
    "gn:admin1_code":"19.0",
    "gn:asciiname":"Yingshoubucun",
    "gn:country_code":"CN",
    "gn:dem":67,
    "gn:feature_class":"P",
    "gn:feature_code":"PPL",
    "gn:name":"Yingshoubucun",
    "gn:population":0,
    "gn:timezone":"Asia/Shanghai",
    "iso:country":"CN",
    "name:zho_x_preferred":[
        "\u82f1\u5b88\u5821\u6751"
    ],
    "wof:name":"Yingshoubucun",
    "wof:placetype":"locality"
},
  "geometry": {"coordinates":[122.629,40.4372],"type":"Point"}
}