{
  "type": "Feature",
  "properties": {
    "gn:admin1_code":"5.0",
    "gn:asciiname":"Honghuadian",
    "gn:country_code":"CN",
    "gn:dem":181,
    "gn:feature_class":"P",
    "gn:feature_code":"PPL",
    "gn:name":"Honghuadian",
    "gn:population":0,
    "gn:timezone":"Asia/Shanghai",
    "iso:country":"CN",
    "name:zho_x_preferred":[
        "\u7ea2\u82b1\u5e97"
    ],
    "wof:name":"Honghuadian",
    "wof:placetype":"locality"
},
  "geometry": {"coordinates":[124.45423999999998,42.90279],"type":"Point"}
}