{
  "type": "Feature",
  "properties": {
    "gn:admin1_code":"3.0",
    "gn:asciiname":"Gangkou",
    "gn:country_code":"CN",
    "gn:dem":43,
    "gn:feature_class":"P",
    "gn:feature_code":"PPL",
    "gn:name":"Gangkou",
    "gn:population":0,
    "gn:timezone":"Asia/Shanghai",
    "iso:country":"CN",
    "name:deu_x_preferred":[
        "Gangkou"
    ],
    "name:nor_x_preferred":[
        "Gangkou"
    ],
    "name:und_x_variant":[
        "\u6e2f\u53e3"
    ],
    "wof:name":"Gangkou",
    "wof:placetype":"locality"
},
  "geometry": {"coordinates":[116.21127,27.92294],"type":"Point"}
}