{
  "type": "Feature",
  "properties": {
    "gn:admin1_code":"19",
    "gn:asciiname":"Dachang Shandao",
    "gn:country_code":"CN",
    "gn:dem":18,
    "gn:feature_class":"P",
    "gn:feature_code":"PPLA4",
    "gn:name":"Dachang Shandao",
    "gn:population":0,
    "gn:timezone":"Asia/Shanghai",
    "iso:country":"CN",
    "name:und_x_variant":[
        "Ta-ch\u2019ang-shan-tao",
        "Changhai",
        "Ssu-k\u2019uai-shih",
        "Ch\u2019ang-shan",
        "Sikuanshi",
        "Ch\u2019ang-hai-hsien",
        "Dachang Shandao",
        "\u5927\u957f\u5c71\u5c9b",
        "Dachang Shandao Zhen",
        "\u5927\u957f\u5c71\u5c9b\u9547"
    ],
    "wof:name":"Dachang Shandao",
    "wof:placetype":"locality"
},
  "geometry": {"coordinates":[122.59999999999999,39.27556],"type":"Point"}
}