{
  "type": "Feature",
  "properties": {
    "gn:admin1_code":"14.0",
    "gn:asciiname":"Reweng",
    "gn:country_code":"CN",
    "gn:dem":3717,
    "gn:feature_class":"P",
    "gn:feature_code":"PPL",
    "gn:name":"Reweng",
    "gn:population":0,
    "gn:timezone":"Asia/Urumqi",
    "iso:country":"CN",
    "name:zho_x_preferred":[
        "\u70ed\u55e1"
    ],
    "wof:name":"Reweng",
    "wof:placetype":"locality"
},
  "geometry": {"coordinates":[98.67728,31.53962000000001],"type":"Point"}
}