{
  "type": "Feature",
  "properties": {
    "gn:country":"CN",
    "gn:fcode":"ADM3",
    "gn:pop":396701,
    "iso:country":"CN",
    "name:unk_x_variant":[
        "P\u2019ing-ku Hsien"
    ],
    "name:zho_x_preferred":[
        "\u5e73\u8c37\u533a"
    ],
    "name:zho_x_variant":[
        "\u5e73\u8c37"
    ],
    "qs:name":"Pinggu Qu",
    "qs:photos_9r":0,
    "qs:photos_sr":0,
    "qs:pop_sr":"10",
    "wd:wordcount":374,
    "wof:name":"Pinggu Qu",
    "wof:placetype":"localadmin",
    "wof:population":396701
},
  "geometry": {"coordinates":[117.13793,40.21102],"type":"Point"}
}