{
  "type": "Feature",
  "properties": {
    "gn:country":"CN",
    "gn:fcode":"ADM3",
    "gn:population":396701,
    "iso:country":"CN",
    "name:ara_x_preferred":[
        "\u0628\u064a\u0646\u063a\u0648"
    ],
    "name:bul_x_preferred":[
        "\u041f\u0438\u043d\u0433\u0443"
    ],
    "name:ceb_x_preferred":[
        "Pinggu"
    ],
    "name:ces_x_preferred":[
        "Pching-ku"
    ],
    "name:cym_x_preferred":[
        "Ardal Pinggu"
    ],
    "name:deu_x_preferred":[
        "Pinggu"
    ],
    "name:eng_x_preferred":[
        "Pinggu District"
    ],
    "name:est_x_preferred":[
        "Pinggu"
    ],
    "name:eus_x_preferred":[
        "Pinggu barrutia"
    ],
    "name:fas_x_preferred":[
        "\u067e\u06cc\u0646\u06af\u0627"
    ],
    "name:gan_x_preferred":[
        "\u5e73\u8c37\u533a"
    ],
    "name:jpn_x_preferred":[
        "\u5e73\u8c37\u533a"
    ],
    "name:kor_x_preferred":[
        "\ud551\uad6c\uad6c"
    ],
    "name:mwl_x_preferred":[
        "Pinggu"
    ],
    "name:nan_x_preferred":[
        "P\u00eang-kok-khu"
    ],
    "name:nld_x_preferred":[
        "Pinggu District"
    ],
    "name:nob_x_preferred":[
        "Pinggu"
    ],
    "name:rus_x_preferred":[
        "\u041f\u0438\u043d\u0433\u0443"
    ],
    "name:sco_x_preferred":[
        "Pinggu"
    ],
    "name:spa_x_preferred":[
        "Pinggu"
    ],
    "name:swe_x_preferred":[
        "Pinggu"
    ],
    "name:tur_x_preferred":[
        "Pinggu"
    ],
    "name:und_x_variant":[
        "P\u2019ing-ku Hsien"
    ],
    "name:urd_x_preferred":[
        "\u067e\u06cc\u0646\u06af\u0648 \u0636\u0644\u0639"
    ],
    "name:vie_x_preferred":[
        "B\u00ecnh C\u1ed1c"
    ],
    "name:wuu_x_preferred":[
        "\u5e73\u8c37\u533a"
    ],
    "name:yue_x_preferred":[
        "\u5e73\u8c37\u5340"
    ],
    "name:zho_x_preferred":[
        "\u5e73\u8c37\u533a"
    ],
    "name:zho_x_variant":[
        "\u5e73\u8c37",
        "\u5e73\u8c37\u5340"
    ],
    "qs:name":"Pinggu Qu",
    "qs:photos_9r":0,
    "qs:photos_sr":0,
    "qs:pop_sr":"10",
    "wd:wordcount":374,
    "wof:name":"Pinggu Qu",
    "wof:placetype":"localadmin",
    "wof:population":396701
},
  "geometry": {"coordinates":[117.13793,40.21102],"type":"Point"}
}