{
  "type": "Feature",
  "properties": {
    "gn:admin1_code":"1.0",
    "gn:asciiname":"Gaoqiaocun",
    "gn:country_code":"CN",
    "gn:dem":40,
    "gn:feature_class":"P",
    "gn:feature_code":"PPL",
    "gn:name":"Gaoqiaocun",
    "gn:population":0,
    "gn:timezone":"Asia/Shanghai",
    "iso:country":"CN",
    "name:und_x_variant":[
        "Gaoqiao"
    ],
    "name:zho_x_preferred":[
        "\u9ad8\u6865\u6751"
    ],
    "wof:name":"Gaoqiaocun",
    "wof:placetype":"locality"
},
  "geometry": {"coordinates":[115.45,33.56667],"type":"Point"}
}