{
  "type": "Feature",
  "properties": {
    "gn:admin1_code":"20.0",
    "gn:asciiname":"Machanggou",
    "gn:country_code":"CN",
    "gn:dem":1823,
    "gn:feature_class":"P",
    "gn:feature_code":"PPL",
    "gn:name":"Machanggou",
    "gn:population":0,
    "gn:timezone":"Asia/Shanghai",
    "iso:country":"CN",
    "name:und_x_variant":[
        "\u9a6c\u573a\u6c9f"
    ],
    "wof:name":"Machanggou",
    "wof:placetype":"locality"
},
  "geometry": {"coordinates":[111.62426000000001,41.01984],"type":"Point"}
}