{
  "type": "Feature",
  "properties": {
    "gn:admin1_code":"26.0",
    "gn:asciiname":"Wangjiageta",
    "gn:cc2":"CN",
    "gn:country_code":"CN",
    "gn:dem":1029,
    "gn:feature_class":"P",
    "gn:feature_code":"PPL",
    "gn:name":"Wangjiageta",
    "gn:population":0,
    "gn:timezone":"Asia/Shanghai",
    "iso:country":"CN",
    "name:und_x_variant":[
        "Wang-chia-ko-t\u2019a",
        "Wangjiageta"
    ],
    "wof:name":"Wangjiageta",
    "wof:placetype":"locality"
},
  "geometry": {"coordinates":[109.84999999999999,36.33333],"type":"Point"}
}