{
  "type": "Feature",
  "properties": {
    "gn:admin1_code":"32.0",
    "gn:asciiname":"Buze",
    "gn:country_code":"CN",
    "gn:dem":3107,
    "gn:feature_class":"P",
    "gn:feature_code":"PPL",
    "gn:name":"Buze",
    "gn:population":0,
    "gn:timezone":"Asia/Shanghai",
    "iso:country":"CN",
    "name:zho_x_preferred":[
        "\u5e03\u5219"
    ],
    "wof:name":"Buze",
    "wof:placetype":"locality"
},
  "geometry": {"coordinates":[99.14019999999999,29.0086],"type":"Point"}
}