{
  "type": "Feature",
  "properties": {
    "gn:admin1_code":"8.0",
    "gn:asciiname":"Wanfacun",
    "gn:country_code":"CN",
    "gn:dem":232,
    "gn:feature_class":"P",
    "gn:feature_code":"PPL",
    "gn:name":"Wanfacun",
    "gn:population":0,
    "gn:timezone":"Asia/Shanghai",
    "iso:country":"CN",
    "name:zho_x_preferred":[
        "\u4e07\u53d1\u6751"
    ],
    "wof:name":"Wanfacun",
    "wof:placetype":"locality"
},
  "geometry": {"coordinates":[125.53872,47.80576],"type":"Point"}
}