{
  "type": "Feature",
  "properties": {
    "gn:admin1_code":"8.0",
    "gn:asciiname":"Renhetun",
    "gn:country_code":"CN",
    "gn:dem":104,
    "gn:feature_class":"P",
    "gn:feature_code":"PPL",
    "gn:name":"Renhetun",
    "gn:population":0,
    "gn:timezone":"Asia/Shanghai",
    "iso:country":"CN",
    "name:zho_x_preferred":[
        "\u4ec1\u548c\u5c6f"
    ],
    "wof:name":"Renhetun",
    "wof:placetype":"locality"
},
  "geometry": {"coordinates":[128.71888000000001,45.9237],"type":"Point"}
}