{
  "type": "Feature",
  "properties": {
    "gn:admin1_code":"5.0",
    "gn:asciiname":"Xiluotuolai",
    "gn:country_code":"CN",
    "gn:dem":171,
    "gn:feature_class":"P",
    "gn:feature_code":"PPL",
    "gn:name":"Xiluotuolai",
    "gn:population":0,
    "gn:timezone":"Asia/Shanghai",
    "iso:country":"CN",
    "name:zho_x_preferred":[
        "\u897f\u9a86\u9a7c\u6765"
    ],
    "wof:name":"Xiluotuolai",
    "wof:placetype":"locality"
},
  "geometry": {"coordinates":[123.86068,44.32605],"type":"Point"}
}