{
  "type": "Feature",
  "properties": {
    "gn:admin1_code":"29.0",
    "gn:asciiname":"Nianping",
    "gn:country_code":"CN",
    "gn:dem":2053,
    "gn:feature_class":"P",
    "gn:feature_code":"PPL",
    "gn:name":"Nianping",
    "gn:population":0,
    "gn:timezone":"Asia/Shanghai",
    "iso:country":"CN",
    "name:zho_x_preferred":[
        "\u5ff5\u576a"
    ],
    "wof:name":"Nianping",
    "wof:placetype":"locality"
},
  "geometry": {"coordinates":[98.8634,26.3432],"type":"Point"}
}