{
  "type": "Feature",
  "properties": {
    "gn:admin1_code":"19.0",
    "gn:asciiname":"Dadingtun",
    "gn:country_code":"CN",
    "gn:dem":28,
    "gn:feature_class":"P",
    "gn:feature_code":"PPL",
    "gn:name":"Dadingtun",
    "gn:population":0,
    "gn:timezone":"Asia/Shanghai",
    "iso:country":"CN",
    "name:und_x_variant":[
        "\u5927\u4e01\u5c6f"
    ],
    "wof:name":"Dadingtun",
    "wof:placetype":"locality"
},
  "geometry": {"coordinates":[122.35166,40.34866],"type":"Point"}
}