{
  "type": "Feature",
  "properties": {
    "gn:admin1_code":"19.0",
    "gn:asciiname":"Jiuzhan",
    "gn:country_code":"CN",
    "gn:dem":14,
    "gn:feature_class":"P",
    "gn:feature_code":"PPL",
    "gn:name":"Jiuzhan",
    "gn:population":0,
    "gn:timezone":"Asia/Shanghai",
    "iso:country":"CN",
    "name:zho_x_preferred":[
        "\u65e7\u7ad9"
    ],
    "wof:name":"Jiuzhan",
    "wof:placetype":"locality"
},
  "geometry": {"coordinates":[121.24299999999999,41.091],"type":"Point"}
}