{
  "type": "Feature",
  "properties": {
    "gn:admin1_code":"19.0",
    "gn:asciiname":"Yaoduan",
    "gn:country_code":"CN",
    "gn:dem":227,
    "gn:feature_class":"P",
    "gn:feature_code":"PPL",
    "gn:name":"Yaoduan",
    "gn:population":0,
    "gn:timezone":"Asia/Shanghai",
    "iso:country":"CN",
    "name:und_x_variant":[
        "\u8170\u6bb5"
    ],
    "name:zho_x_preferred":[
        "\u8170\u6bb5"
    ],
    "wof:name":"Yaoduan",
    "wof:placetype":"locality"
},
  "geometry": {"coordinates":[125.05969,40.67537],"type":"Point"}
}