{
  "type": "Feature",
  "properties": {
    "gn:admin1_code":"3",
    "gn:asciiname":"Honghe",
    "gn:country_code":"CN",
    "gn:dem":108,
    "gn:feature_class":"P",
    "gn:feature_code":"PPL",
    "gn:name":"Honghe",
    "gn:population":0,
    "gn:timezone":"Asia/Shanghai",
    "iso:country":"CN",
    "name:zho_x_preferred":[
        "\u7ea2\u6cb3"
    ],
    "wof:name":"Honghe",
    "wof:placetype":"locality"
},
  "geometry": {"coordinates":[114.93232999999999,25.99532],"type":"Point"}
}