{
  "type": "Feature",
  "properties": {
    "gn:admin1_code":"14.0",
    "gn:asciiname":"Guqingma",
    "gn:country_code":"CN",
    "gn:dem":4543,
    "gn:feature_class":"P",
    "gn:feature_code":"PPL",
    "gn:name":"Guqingma",
    "gn:population":0,
    "gn:timezone":"Asia/Urumqi",
    "iso:country":"CN",
    "name:zho_x_preferred":[
        "\u59d1\u9752\u9a6c"
    ],
    "wof:name":"Guqingma",
    "wof:placetype":"locality"
},
  "geometry": {"coordinates":[91.72344,31.2789],"type":"Point"}
}