{
  "type": "Feature",
  "properties": {
    "gn:admin1_code":"3.0",
    "gn:asciiname":"Niugukeng",
    "gn:country_code":"CN",
    "gn:dem":249,
    "gn:feature_class":"P",
    "gn:feature_code":"PPL",
    "gn:name":"Niugukeng",
    "gn:population":0,
    "gn:timezone":"Asia/Shanghai",
    "iso:country":"CN",
    "name:und_x_variant":[
        "\u725b\u726f\u5751"
    ],
    "wof:name":"Niugukeng",
    "wof:placetype":"locality"
},
  "geometry": {"coordinates":[115.67525999999999,24.70926],"type":"Point"}
}