{
  "type": "Feature",
  "properties": {
    "gn:admin1_code":"4.0",
    "gn:asciiname":"Lijiagou",
    "gn:country_code":"CN",
    "gn:dem":5,
    "gn:feature_class":"P",
    "gn:feature_code":"PPL",
    "gn:name":"Lijiagou",
    "gn:population":0,
    "gn:timezone":"Asia/Shanghai",
    "iso:country":"CN",
    "name:zho_x_preferred":[
        "\u9ca4\u5bb6\u6c9f"
    ],
    "wof:name":"Lijiagou",
    "wof:placetype":"locality"
},
  "geometry": {"coordinates":[119.77336,32.04417],"type":"Point"}
}