{
  "type": "Feature",
  "properties": {
    "gn:admin1_code":"30.0",
    "gn:asciiname":"Zaoshiling",
    "gn:country_code":"CN",
    "gn:dem":15,
    "gn:feature_class":"P",
    "gn:feature_code":"PPL",
    "gn:name":"Zaoshiling",
    "gn:population":0,
    "gn:timezone":"Asia/Shanghai",
    "iso:country":"CN",
    "name:zho_x_preferred":[
        "\u51ff\u77f3\u5cad"
    ],
    "wof:name":"Zaoshiling",
    "wof:placetype":"locality"
},
  "geometry": {"coordinates":[113.01916,23.67379],"type":"Point"}
}