{
  "type": "Feature",
  "properties": {
    "gn:admin1_code":"21.0",
    "gn:asciiname":"Heiquanwan",
    "gn:country_code":"CN",
    "gn:dem":1865,
    "gn:feature_class":"P",
    "gn:feature_code":"PPL",
    "gn:name":"Heiquanwan",
    "gn:population":0,
    "gn:timezone":"Asia/Shanghai",
    "iso:country":"CN",
    "name:zho_x_preferred":[
        "\u9ed1\u6cc9\u6e7e"
    ],
    "wof:name":"Heiquanwan",
    "wof:placetype":"locality"
},
  "geometry": {"coordinates":[106.39700000000001,35.9304],"type":"Point"}
}