{
  "type": "Feature",
  "properties": {
    "gn:admin1_code":"12.0",
    "gn:asciiname":"Dafujie",
    "gn:country_code":"CN",
    "gn:dem":29,
    "gn:feature_class":"P",
    "gn:feature_code":"PPL",
    "gn:name":"Dafujie",
    "gn:population":0,
    "gn:timezone":"Asia/Shanghai",
    "iso:country":"CN",
    "name:zho_x_preferred":[
        "\u5927\u798f\u8857"
    ],
    "wof:name":"Dafujie",
    "wof:placetype":"locality"
},
  "geometry": {"coordinates":[113.58319,30.44858],"type":"Point"}
}