{
  "type": "Feature",
  "properties": {
    "gn:admin1_code":"12.0",
    "gn:asciiname":"Dawuke",
    "gn:country_code":"CN",
    "gn:dem":45,
    "gn:feature_class":"P",
    "gn:feature_code":"PPL",
    "gn:name":"Dawuke",
    "gn:population":0,
    "gn:timezone":"Asia/Shanghai",
    "iso:country":"CN",
    "name:und_x_variant":[
        "\u5927\u5c4b\u67ef"
    ],
    "wof:name":"Dawuke",
    "wof:placetype":"locality"
},
  "geometry": {"coordinates":[114.3008,30.10175],"type":"Point"}
}