{
  "type": "Feature",
  "properties": {
    "gn:admin1_code":"5.0",
    "gn:asciiname":"Liufatun",
    "gn:country_code":"CN",
    "gn:dem":152,
    "gn:feature_class":"P",
    "gn:feature_code":"PPL",
    "gn:name":"Liufatun",
    "gn:population":0,
    "gn:timezone":"Asia/Shanghai",
    "iso:country":"CN",
    "name:zho_x_preferred":[
        "\u5218\u53d1\u5c6f"
    ],
    "wof:name":"Liufatun",
    "wof:placetype":"locality"
},
  "geometry": {"coordinates":[125.76875,44.78648],"type":"Point"}
}