{
  "type": "Feature",
  "properties": {
    "gn:admin1_code":"32.0",
    "gn:asciiname":"Niuge",
    "gn:country_code":"CN",
    "gn:dem":4080,
    "gn:feature_class":"P",
    "gn:feature_code":"PPL",
    "gn:name":"Niuge",
    "gn:population":0,
    "gn:timezone":"Asia/Shanghai",
    "iso:country":"CN",
    "name:zho_x_preferred":[
        "\u7ebd\u6208"
    ],
    "wof:name":"Niuge",
    "wof:placetype":"locality"
},
  "geometry": {"coordinates":[98.3246,32.8276],"type":"Point"}
}