{
  "type": "Feature",
  "properties": {
    "gn:admin1_code":"11.0",
    "gn:asciiname":"Longhu",
    "gn:country_code":"CN",
    "gn:dem":208,
    "gn:feature_class":"P",
    "gn:feature_code":"PPL",
    "gn:name":"Longhu",
    "gn:population":0,
    "gn:timezone":"Asia/Shanghai",
    "iso:country":"CN",
    "name:ceb_x_preferred":[
        "Longhu"
    ],
    "name:deu_x_preferred":[
        "Longhu"
    ],
    "name:zho_x_preferred":[
        "\u6cf7\u6e56"
    ],
    "wof:name":"Longhu",
    "wof:placetype":"locality"
},
  "geometry": {"coordinates":[113.64267,26.38688],"type":"Point"}
}