{
  "type": "Feature",
  "properties": {
    "gn:admin1_code":"30.0",
    "gn:asciiname":"Simeicun",
    "gn:country_code":"CN",
    "gn:dem":15,
    "gn:feature_class":"P",
    "gn:feature_code":"PPL",
    "gn:name":"Simeicun",
    "gn:population":0,
    "gn:timezone":"Asia/Shanghai",
    "iso:country":"CN",
    "name:zho_x_preferred":[
        "\u56db\u7f8e\u6751"
    ],
    "wof:name":"Simeicun",
    "wof:placetype":"locality"
},
  "geometry": {"coordinates":[116.51607,23.06004],"type":"Point"}
}