{
  "type": "Feature",
  "properties": {
    "gn:admin1_code":"5.0",
    "gn:asciiname":"Xiangyangpocun",
    "gn:country_code":"CN",
    "gn:dem":227,
    "gn:feature_class":"P",
    "gn:feature_code":"PPL",
    "gn:name":"Xiangyangpocun",
    "gn:population":0,
    "gn:timezone":"Asia/Shanghai",
    "iso:country":"CN",
    "name:zho_x_preferred":[
        "\u5411\u9633\u7834\u6751"
    ],
    "wof:name":"Xiangyangpocun",
    "wof:placetype":"locality"
},
  "geometry": {"coordinates":[124.85363999999998,43.56558],"type":"Point"}
}