{
  "type": "Feature",
  "properties": {
    "gn:admin1_code":"18.0",
    "gn:asciiname":"Aoshang",
    "gn:country_code":"CN",
    "gn:dem":920,
    "gn:feature_class":"P",
    "gn:feature_code":"PPL",
    "gn:name":"Aoshang",
    "gn:population":0,
    "gn:timezone":"Asia/Shanghai",
    "iso:country":"CN",
    "name:zho_x_preferred":[
        "\u5773\u4e0a"
    ],
    "wof:name":"Aoshang",
    "wof:placetype":"locality"
},
  "geometry": {"coordinates":[108.536,27.874],"type":"Point"}
}