{
  "type": "Feature",
  "properties": {
    "gn:admin1_code":"3",
    "gn:asciiname":"Yuanxi",
    "gn:country_code":"CN",
    "gn:dem":219,
    "gn:feature_class":"P",
    "gn:feature_code":"PPL",
    "gn:name":"Yuanxi",
    "gn:population":0,
    "gn:timezone":"Asia/Shanghai",
    "iso:country":"CN",
    "name:zho_x_preferred":[
        "\u9662\u6eaa"
    ],
    "wof:name":"Yuanxi",
    "wof:placetype":"locality"
},
  "geometry": {"coordinates":[114.24299999999999,26.8817],"type":"Point"}
}