{
  "type": "Feature",
  "properties": {
    "gn:admin1_code":"11",
    "gn:asciiname":"Jinxi",
    "gn:country_code":"CN",
    "gn:dem":621,
    "gn:feature_class":"P",
    "gn:feature_code":"PPL",
    "gn:name":"Jinxi",
    "gn:population":0,
    "gn:timezone":"Asia/Shanghai",
    "iso:country":"CN",
    "name:ceb_x_preferred":[
        "Jinxi"
    ],
    "name:deu_x_preferred":[
        "Jinxi"
    ],
    "wof:name":"Jinxi",
    "wof:placetype":"locality"
},
  "geometry": {"coordinates":[110.39749999999999,27.47806],"type":"Point"}
}