{
  "type": "Feature",
  "properties": {
    "gn:country":"CN",
    "gn:fcode":"PPL",
    "gn:population":98259,
    "iso:country":"CN",
    "name:ceb_x_preferred":[
        "Xinyi"
    ],
    "name:deu_x_preferred":[
        "Xinyi"
    ],
    "name:fas_x_preferred":[
        "\u0634\u06cc\u0646\u06cc"
    ],
    "name:fra_x_preferred":[
        "Xinyi"
    ],
    "name:heb_x_preferred":[
        "\u05e7\u05e1\u05d9\u05e0\u05d9\u05d9"
    ],
    "name:hun_x_preferred":[
        "Xinyi"
    ],
    "name:jpn_x_preferred":[
        "\u30b7\u30f3\u30a4\u30fc"
    ],
    "name:kor_x_preferred":[
        "\uc2e0\uc774\uc2dc"
    ],
    "name:mlg_x_preferred":[
        "Xinyi"
    ],
    "name:nor_x_preferred":[
        "Xinyi"
    ],
    "name:rus_x_preferred":[
        "\u0421\u0438\u043d\u044c\u0438"
    ],
    "name:swe_x_preferred":[
        "Xinyi"
    ],
    "name:und_x_variant":[
        "Hsin-i"
    ],
    "name:zho_x_preferred":[
        "\u4fe1\u5b9c"
    ],
    "qs:name":"Xinyi",
    "qs:photos_9r":0,
    "qs:photos_sr":0,
    "qs:pop_sr":"8",
    "wd:wordcount":176,
    "wof:name":"Xinyi",
    "wof:placetype":"locality",
    "wof:population":98259
},
  "geometry": {"coordinates":[110.94746000000001,22.37303],"type":"Point"}
}