{
  "type": "Feature",
  "properties": {
    "gn:country":"CN",
    "gn:fcode":"PPL",
    "gn:pop":98259,
    "iso:country":"CN",
    "name:unk_x_variant":[
        "Hsin-i"
    ],
    "name:zho_x_preferred":[
        "\u4fe1\u5b9c"
    ],
    "qs:name":"Xinyi",
    "qs:photos_9r":0,
    "qs:photos_sr":0,
    "qs:pop_sr":"8",
    "wd:wordcount":176,
    "wof:name":"Xinyi",
    "wof:placetype":"locality",
    "wof:population":98259
},
  "geometry": {"coordinates":[110.94746000000001,22.37303],"type":"Point"}
}