{
  "type": "Feature",
  "properties": {
    "gn:admin1_code":"12.0",
    "gn:asciiname":"Shangqingjiang",
    "gn:country_code":"CN",
    "gn:dem":39,
    "gn:feature_class":"P",
    "gn:feature_code":"PPL",
    "gn:name":"Shangqingjiang",
    "gn:population":0,
    "gn:timezone":"Asia/Shanghai",
    "iso:country":"CN",
    "name:zho_x_preferred":[
        "Shangqingjiang"
    ],
    "name:zho_x_variant":[
        "\u4e0a\u6e05\u6c5f"
    ],
    "wof:name":"Shangqingjiang",
    "wof:placetype":"locality"
},
  "geometry": {"coordinates":[115.33047999999999,29.70712],"type":"Point"}
}