{
  "type": "Feature",
  "properties": {
    "gn:admin1_code":"4.0",
    "gn:asciiname":"Zhoushizhuang",
    "gn:country_code":"CN",
    "gn:dem":19,
    "gn:feature_class":"P",
    "gn:feature_code":"PPL",
    "gn:name":"Zhoushizhuang",
    "gn:population":0,
    "gn:timezone":"Asia/Shanghai",
    "iso:country":"CN",
    "name:zho_x_preferred":[
        "\u5468\u77f3\u5e84"
    ],
    "wof:name":"Zhoushizhuang",
    "wof:placetype":"locality"
},
  "geometry": {"coordinates":[118.35169,33.97113],"type":"Point"}
}