{
  "type": "Feature",
  "properties": {
    "gn:admin1_code":"4.0",
    "gn:asciiname":"Guanhecun",
    "gn:country_code":"CN",
    "gn:dem":4,
    "gn:feature_class":"P",
    "gn:feature_code":"PPL",
    "gn:name":"Guanhecun",
    "gn:population":0,
    "gn:timezone":"Asia/Shanghai",
    "iso:country":"CN",
    "name:zho_x_preferred":[
        "\u5173\u6cb3\u6751"
    ],
    "wof:name":"Guanhecun",
    "wof:placetype":"locality"
},
  "geometry": {"coordinates":[119.56847999999999,32.67389],"type":"Point"}
}