{
  "type": "Feature",
  "properties": {
    "gn:admin1_code":"15.0",
    "gn:asciiname":"Quguoxia",
    "gn:country_code":"CN",
    "gn:dem":3334,
    "gn:feature_class":"P",
    "gn:feature_code":"PPL",
    "gn:name":"Quguoxia",
    "gn:population":0,
    "gn:timezone":"Asia/Shanghai",
    "iso:country":"CN",
    "name:zho_x_preferred":[
        "\u66f2\u679c\u590f"
    ],
    "wof:name":"Quguoxia",
    "wof:placetype":"locality"
},
  "geometry": {"coordinates":[103.048,35.1143],"type":"Point"}
}