{
  "type": "Feature",
  "properties": {
    "gn:admin1_code":"24.0",
    "gn:asciiname":"Xiqin",
    "gn:country_code":"CN",
    "gn:dem":464,
    "gn:feature_class":"P",
    "gn:feature_code":"PPL",
    "gn:name":"Xiqin",
    "gn:population":0,
    "gn:timezone":"Asia/Shanghai",
    "iso:country":"CN",
    "name:deu_x_preferred":[
        "Xiqin"
    ],
    "name:zho_x_preferred":[
        "\u897f\u79e6"
    ],
    "wof:name":"Xiqin",
    "wof:placetype":"locality"
},
  "geometry": {"coordinates":[111.50702,35.98148],"type":"Point"}
}