{
  "type": "Feature",
  "properties": {
    "gn:admin1_code":"1.0",
    "gn:asciiname":"Shexicun",
    "gn:country_code":"CN",
    "gn:dem":241,
    "gn:feature_class":"P",
    "gn:feature_code":"PPL",
    "gn:name":"Shexicun",
    "gn:population":0,
    "gn:timezone":"Asia/Shanghai",
    "iso:country":"CN",
    "name:zho_x_preferred":[
        "\u4f58\u6eaa\u6751"
    ],
    "wof:name":"Shexicun",
    "wof:placetype":"locality"
},
  "geometry": {"coordinates":[117.91477999999999,30.10906],"type":"Point"}
}