{
  "type": "Feature",
  "properties": {
    "gn:admin1_code":"25.0",
    "gn:asciiname":"Chengzhuangcun",
    "gn:country_code":"CN",
    "gn:dem":44,
    "gn:feature_class":"P",
    "gn:feature_code":"PPL",
    "gn:name":"Chengzhuangcun",
    "gn:population":0,
    "gn:timezone":"Asia/Shanghai",
    "iso:country":"CN",
    "name:zho_x_preferred":[
        "\u7a0b\u5e84\u6751"
    ],
    "wof:name":"Chengzhuangcun",
    "wof:placetype":"locality"
},
  "geometry": {"coordinates":[115.57809,36.102],"type":"Point"}
}