{
  "type": "Feature",
  "properties": {
    "gn:admin1_code":"4.0",
    "gn:asciiname":"Liyuancun",
    "gn:country_code":"CN",
    "gn:dem":29,
    "gn:feature_class":"P",
    "gn:feature_code":"PPL",
    "gn:name":"Liyuancun",
    "gn:population":0,
    "gn:timezone":"Asia/Shanghai",
    "iso:country":"CN",
    "name:zho_x_preferred":[
        "\u674e\u56ed\u6751"
    ],
    "wof:name":"Liyuancun",
    "wof:placetype":"locality"
},
  "geometry": {"coordinates":[117.8045,34.1767],"type":"Point"}
}