{
  "type": "Feature",
  "properties": {
    "gn:admin1_code":"19.0",
    "gn:asciiname":"Laoxinglongdian",
    "gn:country_code":"CN",
    "gn:dem":34,
    "gn:feature_class":"P",
    "gn:feature_code":"PPL",
    "gn:name":"Laoxinglongdian",
    "gn:population":0,
    "gn:timezone":"Asia/Shanghai",
    "iso:country":"CN",
    "name:zho_x_preferred":[
        "\u8001\u5174\u9686\u5e97"
    ],
    "wof:name":"Laoxinglongdian",
    "wof:placetype":"locality"
},
  "geometry": {"coordinates":[123.092,41.9987],"type":"Point"}
}