{
  "type": "Feature",
  "properties": {
    "gn:admin1_code":"11.0",
    "gn:asciiname":"Shezuizi",
    "gn:country_code":"CN",
    "gn:dem":42,
    "gn:feature_class":"P",
    "gn:feature_code":"PPL",
    "gn:name":"Shezuizi",
    "gn:population":0,
    "gn:timezone":"Asia/Shanghai",
    "iso:country":"CN",
    "name:zho_x_preferred":[
        "\u86c7\u5634\u5b50"
    ],
    "wof:name":"Shezuizi",
    "wof:placetype":"locality"
},
  "geometry": {"coordinates":[112.94041,28.23649],"type":"Point"}
}