{
  "type": "Feature",
  "properties": {
    "gn:admin1_code":"29.0",
    "gn:asciiname":"Zaopo",
    "gn:country_code":"CN",
    "gn:dem":2303,
    "gn:feature_class":"P",
    "gn:feature_code":"PPL",
    "gn:name":"Zaopo",
    "gn:population":0,
    "gn:timezone":"Asia/Shanghai",
    "iso:country":"CN",
    "name:zho_x_preferred":[
        "\u7cdf\u5761"
    ],
    "wof:name":"Zaopo",
    "wof:placetype":"locality"
},
  "geometry": {"coordinates":[99.2229,27.9582],"type":"Point"}
}