{
  "type": "Feature",
  "properties": {
    "gn:admin1_code":"7.0",
    "gn:asciiname":"Dongshan",
    "gn:country_code":"CN",
    "gn:dem":668,
    "gn:feature_class":"P",
    "gn:feature_code":"PPL",
    "gn:name":"Dongshan",
    "gn:population":0,
    "gn:timezone":"Asia/Shanghai",
    "iso:country":"CN",
    "name:zho_x_preferred":[
        "\u4e1c\u5c71"
    ],
    "wof:name":"Dongshan",
    "wof:placetype":"locality"
},
  "geometry": {"coordinates":[118.62041000000001,26.57921],"type":"Point"}
}