{
  "type": "Feature",
  "properties": {
    "gn:admin1_code":"24.0",
    "gn:asciiname":"Caishulingcun",
    "gn:country_code":"CN",
    "gn:dem":952,
    "gn:feature_class":"P",
    "gn:feature_code":"PPL",
    "gn:name":"Caishulingcun",
    "gn:population":0,
    "gn:timezone":"Asia/Shanghai",
    "iso:country":"CN",
    "name:zho_x_preferred":[
        "\u5f69\u6811\u5cad\u6751"
    ],
    "wof:name":"Caishulingcun",
    "wof:placetype":"locality"
},
  "geometry": {"coordinates":[110.79513,37.76986],"type":"Point"}
}