{
  "type": "Feature",
  "properties": {
    "iso:country":"CN",
    "name:ceb_x_preferred":[
        "Suining Xian"
    ],
    "name:dan_x_preferred":[
        "Suining"
    ],
    "name:deu_x_preferred":[
        "Suining"
    ],
    "name:eng_x_preferred":[
        "Suining County"
    ],
    "name:fas_x_preferred":[
        "\u0634\u0647\u0631\u0633\u062a\u0627\u0646 \u0633\u06cc\u0648\u0646\u06cc\u0646\u06af"
    ],
    "name:gan_x_preferred":[
        "\u7762\u5b81\u53bf"
    ],
    "name:jpn_x_preferred":[
        "\u30b1\u30a4\u5be7\u770c"
    ],
    "name:jpn_x_variant":[
        "\u7762\u5be7\u770c"
    ],
    "name:kor_x_preferred":[
        "\uc464\uc774\ub2dd\ud604"
    ],
    "name:nan_x_preferred":[
        "Sui-l\u00eang-ko\u0101n"
    ],
    "name:nld_x_preferred":[
        "Suining"
    ],
    "name:nob_x_preferred":[
        "Suining"
    ],
    "name:rus_x_preferred":[
        "\u0421\u0443\u0439\u043d\u0438\u043d"
    ],
    "name:swe_x_preferred":[
        "Suining"
    ],
    "name:urd_x_preferred":[
        "\u0633\u0648\u0626\u0646\u06cc\u0646\u06af \u06a9\u0627\u0624\u0646\u0679\u06cc"
    ],
    "name:vie_x_preferred":[
        "Tuy Ninh"
    ],
    "name:wuu_x_preferred":[
        "\u7762\u5b81\u53bf"
    ],
    "name:yue_x_preferred":[
        "\u7762\u5be7"
    ],
    "name:zho_x_preferred":[
        "\u7762\u5b81\u53bf"
    ],
    "qs:name":"\u7762\u5b81\u53bf",
    "qs:name_adm0":"\u4e2d\u570b",
    "qs:name_adm1":"\u6c5f\u82cf\u7701",
    "qs:photos":1,
    "qs:photos_1k":1,
    "qs:photos_9k":1,
    "qs:photos_9r":2,
    "qs:photos_all":56,
    "qs:photos_sr":1,
    "qs:placetype":"LocalAdmin",
    "qs:pop_sr":"0",
    "wd:wordcount":184,
    "wof:name":"\u7762\u5b81\u53bf",
    "wof:placetype":"localadmin"
},
  "geometry": {"coordinates":[118.008166,33.906],"type":"Point"}
}