{
  "type": "Feature",
  "properties": {
    "iso:country":"CN",
    "qs:name":"\u7762\u5b81\u53bf",
    "qs:name_adm0":"\u4e2d\u570b",
    "qs:name_adm1":"\u6c5f\u82cf\u7701",
    "qs:photos":1,
    "qs:photos_1k":1,
    "qs:photos_9k":1,
    "qs:photos_9r":2,
    "qs:photos_all":56,
    "qs:photos_sr":1,
    "qs:placetype":"LocalAdmin",
    "qs:pop_sr":"0",
    "wd:wordcount":184,
    "wof:name":"\u7762\u5b81\u53bf",
    "wof:placetype":"localadmin"
},
  "geometry": {"coordinates":[118.008166,33.906],"type":"Point"}
}