{
  "type": "Feature",
  "properties": {
    "gn:admin1_code":"10.0",
    "gn:asciiname":"Zhandianzi",
    "gn:country_code":"CN",
    "gn:dem":18,
    "gn:feature_class":"P",
    "gn:feature_code":"PPL",
    "gn:name":"Zhandianzi",
    "gn:population":0,
    "gn:timezone":"Asia/Shanghai",
    "iso:country":"CN",
    "name:zho_x_preferred":[
        "\u6e5b\u5e97\u5b50"
    ],
    "wof:name":"Zhandianzi",
    "wof:placetype":"locality"
},
  "geometry": {"coordinates":[118.78033000000001,39.61474000000001],"type":"Point"}
}