{
  "type": "Feature",
  "properties": {
    "gn:admin1_code":"14.0",
    "gn:asciiname":"Zadeng",
    "gn:country_code":"CN",
    "gn:dem":3070,
    "gn:feature_class":"P",
    "gn:feature_code":"PPL",
    "gn:name":"Zadeng",
    "gn:population":0,
    "gn:timezone":"Asia/Urumqi",
    "iso:country":"CN",
    "name:zho_x_preferred":[
        "\u6742\u706f"
    ],
    "wof:name":"Zadeng",
    "wof:placetype":"locality"
},
  "geometry": {"coordinates":[95.40522,29.80225],"type":"Point"}
}