{
  "type": "Feature",
  "properties": {
    "gn:admin1_code":"4.0",
    "gn:asciiname":"Liji",
    "gn:country_code":"CN",
    "gn:dem":3,
    "gn:feature_class":"P",
    "gn:feature_code":"PPL",
    "gn:name":"Liji",
    "gn:population":0,
    "gn:timezone":"Asia/Shanghai",
    "iso:country":"CN",
    "name:zho_x_preferred":[
        "Liji"
    ],
    "name:zho_x_variant":[
        "\u674e\u96c6"
    ],
    "wof:name":"Liji",
    "wof:placetype":"locality"
},
  "geometry": {"coordinates":[119.53349,34.10164],"type":"Point"}
}