{
  "type": "Feature",
  "properties": {
    "gn:admin1_code":"20.0",
    "gn:asciiname":"Boketu",
    "gn:country_code":"CN",
    "gn:dem":702,
    "gn:feature_class":"P",
    "gn:feature_code":"PPLA4",
    "gn:name":"Boketu",
    "gn:population":0,
    "gn:timezone":"Asia/Shanghai",
    "iso:country":"CN",
    "name:und_x_variant":[
        "Boketu Zhen"
    ],
    "name:zho_x_preferred":[
        "\u535a\u514b\u56fe"
    ],
    "name:zho_x_variant":[
        "\u535a\u514b\u56fe\u9547"
    ],
    "wof:name":"Boketu",
    "wof:placetype":"locality"
},
  "geometry": {"coordinates":[121.90991,48.75723],"type":"Point"}
}