{
  "type": "Feature",
  "properties": {
    "gn:admin1_code":"1.0",
    "gn:asciiname":"Lidazhuangcun",
    "gn:country_code":"CN",
    "gn:dem":36,
    "gn:feature_class":"P",
    "gn:feature_code":"PPL",
    "gn:name":"Lidazhuangcun",
    "gn:population":0,
    "gn:timezone":"Asia/Shanghai",
    "iso:country":"CN",
    "name:zho_x_preferred":[
        "\u674e\u5927\u5e84\u6751"
    ],
    "wof:name":"Lidazhuangcun",
    "wof:placetype":"locality"
},
  "geometry": {"coordinates":[115.42121000000002,32.82313],"type":"Point"}
}