{
  "type": "Feature",
  "properties": {
    "gn:admin1_code":"9",
    "gn:asciiname":"Xihanjia",
    "gn:country_code":"CN",
    "gn:dem":53,
    "gn:feature_class":"P",
    "gn:feature_code":"PPL",
    "gn:name":"Xihanjia",
    "gn:population":0,
    "gn:timezone":"Asia/Shanghai",
    "iso:country":"CN",
    "name:zho_x_preferred":[
        "\u897f\u97e9\u5bb6"
    ],
    "wof:name":"Xihanjia",
    "wof:placetype":"locality"
},
  "geometry": {"coordinates":[115.24328,35.8474],"type":"Point"}
}