{
  "type": "Feature",
  "properties": {
    "gn:admin1_code":"12.0",
    "gn:asciiname":"Fengzhuba",
    "gn:country_code":"CN",
    "gn:dem":1421,
    "gn:feature_class":"P",
    "gn:feature_code":"PPL",
    "gn:name":"Fengzhuba",
    "gn:population":0,
    "gn:timezone":"Asia/Shanghai",
    "iso:country":"CN",
    "name:zho_x_preferred":[
        "\u67ab\u7af9\u575d"
    ],
    "wof:name":"Fengzhuba",
    "wof:placetype":"locality"
},
  "geometry": {"coordinates":[108.56635,30.39649],"type":"Point"}
}