{
  "type": "Feature",
  "properties": {
    "gn:admin1_code":"18.0",
    "gn:asciiname":"Jianxi",
    "gn:country_code":"CN",
    "gn:dem":366,
    "gn:feature_class":"P",
    "gn:feature_code":"PPL",
    "gn:name":"Jianxi",
    "gn:population":0,
    "gn:timezone":"Asia/Shanghai",
    "iso:country":"CN",
    "name:zho_x_preferred":[
        "\u67a7\u6eaa"
    ],
    "wof:name":"Jianxi",
    "wof:placetype":"locality"
},
  "geometry": {"coordinates":[109.32599999999999,27.5927],"type":"Point"}
}