{
  "type": "Feature",
  "properties": {
    "gn:admin1_code":"26.0",
    "gn:asciiname":"Sujiadiancun",
    "gn:country_code":"CN",
    "gn:dem":743,
    "gn:feature_class":"P",
    "gn:feature_code":"PPL",
    "gn:name":"Sujiadiancun",
    "gn:population":0,
    "gn:timezone":"Asia/Shanghai",
    "iso:country":"CN",
    "name:zho_x_preferred":[
        "\u82cf\u5bb6\u5e97\u6751"
    ],
    "wof:name":"Sujiadiancun",
    "wof:placetype":"locality"
},
  "geometry": {"coordinates":[108.90266,34.97142],"type":"Point"}
}