{
  "type": "Feature",
  "properties": {
    "gn:admin1_code":"8.0",
    "gn:asciiname":"Bailiucun",
    "gn:country_code":"CN",
    "gn:dem":170,
    "gn:feature_class":"P",
    "gn:feature_code":"PPL",
    "gn:name":"Bailiucun",
    "gn:population":0,
    "gn:timezone":"Asia/Shanghai",
    "iso:country":"CN",
    "name:zho_x_preferred":[
        "\u767d\u516d\u6751"
    ],
    "wof:name":"Bailiucun",
    "wof:placetype":"locality"
},
  "geometry": {"coordinates":[126.3968,46.86124],"type":"Point"}
}