{
  "type": "Feature",
  "properties": {
    "gn:admin1_code":"3.0",
    "gn:asciiname":"Ligeyuan",
    "gn:country_code":"CN",
    "gn:dem":188,
    "gn:feature_class":"P",
    "gn:feature_code":"PPL",
    "gn:name":"Ligeyuan",
    "gn:population":0,
    "gn:timezone":"Asia/Shanghai",
    "iso:country":"CN",
    "name:zho_x_preferred":[
        "\u91cc\u845b\u6e90"
    ],
    "wof:name":"Ligeyuan",
    "wof:placetype":"locality"
},
  "geometry": {"coordinates":[117.01103999999999,27.99285],"type":"Point"}
}