{
  "type": "Feature",
  "properties": {
    "gn:admin1_code":"16.0",
    "gn:asciiname":"Fujichong",
    "gn:country_code":"CN",
    "gn:dem":266,
    "gn:feature_class":"P",
    "gn:feature_code":"PPL",
    "gn:name":"Fujichong",
    "gn:population":0,
    "gn:timezone":"Asia/Shanghai",
    "iso:country":"CN",
    "name:zho_x_preferred":[
        "\u798f\u57fa\u51b2"
    ],
    "wof:name":"Fujichong",
    "wof:placetype":"locality"
},
  "geometry": {"coordinates":[110.143,22.8781],"type":"Point"}
}