{
  "type": "Feature",
  "properties": {
    "gn:admin1_code":"32.0",
    "gn:asciiname":"Jiadanwan",
    "gn:country_code":"CN",
    "gn:dem":401,
    "gn:feature_class":"P",
    "gn:feature_code":"PPL",
    "gn:name":"Jiadanwan",
    "gn:population":0,
    "gn:timezone":"Asia/Shanghai",
    "iso:country":"CN",
    "name:zho_x_preferred":[
        "\u67b7\u62c5\u6e7e"
    ],
    "wof:name":"Jiadanwan",
    "wof:placetype":"locality"
},
  "geometry": {"coordinates":[105.937,31.274],"type":"Point"}
}