{
  "type": "Feature",
  "properties": {
    "gn:admin1_code":"7.0",
    "gn:asciiname":"Shihui'an",
    "gn:country_code":"CN",
    "gn:dem":459,
    "gn:feature_class":"P",
    "gn:feature_code":"PPL",
    "gn:name":"Shihui\u2019an",
    "gn:population":0,
    "gn:timezone":"Asia/Shanghai",
    "iso:country":"CN",
    "name:zho_x_preferred":[
        "Shihui\u2019an"
    ],
    "name:zho_x_variant":[
        "\u77f3\u7070\u5eb5"
    ],
    "wof:name":"Shihui'an",
    "wof:placetype":"locality"
},
  "geometry": {"coordinates":[117.26045999999999,26.39275],"type":"Point"}
}