{
  "type": "Feature",
  "properties": {
    "gn:admin1_code":"32",
    "gn:asciiname":"Hongxi",
    "gn:cc2":"CN",
    "gn:country_code":"CN",
    "gn:dem":2364,
    "gn:feature_class":"P",
    "gn:feature_code":"PPL",
    "gn:name":"Hongxi",
    "gn:population":0,
    "gn:timezone":"Asia/Shanghai",
    "iso:country":"CN",
    "name:und_x_variant":[
        "Hung-hsi",
        "Hongxi"
    ],
    "wof:name":"Hongxi",
    "wof:placetype":"locality"
},
  "geometry": {"coordinates":[103.12667,28.60833],"type":"Point"}
}