{
  "type": "Feature",
  "properties": {
    "gn:admin1_code":"12.0",
    "gn:asciiname":"Taiyangping",
    "gn:country_code":"CN",
    "gn:dem":1847,
    "gn:feature_class":"P",
    "gn:feature_code":"PPL",
    "gn:name":"Taiyangping",
    "gn:population":0,
    "gn:timezone":"Asia/Shanghai",
    "iso:country":"CN",
    "name:zho_x_preferred":[
        "\u592a\u9633\u576a"
    ],
    "wof:name":"Taiyangping",
    "wof:placetype":"locality"
},
  "geometry": {"coordinates":[109.0936,30.54885],"type":"Point"}
}