{
  "type": "Feature",
  "properties": {
    "gn:admin1_code":"29.0",
    "gn:asciiname":"Shantouzhai",
    "gn:country_code":"CN",
    "gn:dem":1962,
    "gn:feature_class":"P",
    "gn:feature_code":"PPL",
    "gn:name":"Shantouzhai",
    "gn:population":0,
    "gn:timezone":"Asia/Shanghai",
    "iso:country":"CN",
    "name:zho_x_preferred":[
        "\u5c71\u5934\u5be8"
    ],
    "wof:name":"Shantouzhai",
    "wof:placetype":"locality"
},
  "geometry": {"coordinates":[99.36499999999999,23.8544],"type":"Point"}
}