{
  "type": "Feature",
  "properties": {
    "gn:admin1_code":"11",
    "gn:asciiname":"Qitouling",
    "gn:country_code":"CN",
    "gn:dem":422,
    "gn:feature_class":"P",
    "gn:feature_code":"PPL",
    "gn:name":"Qitouling",
    "gn:population":0,
    "gn:timezone":"Asia/Shanghai",
    "iso:country":"CN",
    "name:zho_x_preferred":[
        "\u8d77\u5934\u5cad"
    ],
    "wof:name":"Qitouling",
    "wof:placetype":"locality"
},
  "geometry": {"coordinates":[112.19459000000001,26.01121],"type":"Point"}
}