{
  "type": "Feature",
  "properties": {
    "gn:admin1_code":"7",
    "gn:asciiname":"Shantou",
    "gn:country_code":"CN",
    "gn:dem":778,
    "gn:feature_class":"P",
    "gn:feature_code":"PPL",
    "gn:name":"Shantou",
    "gn:population":0,
    "gn:timezone":"Asia/Shanghai",
    "iso:country":"CN",
    "name:rus_x_preferred":[
        "\u0428\u0430\u043d\u044c\u0442\u043e\u0443"
    ],
    "name:und_x_variant":[
        "\u5c71\u5934",
        "Shantou"
    ],
    "wof:name":"Shantou",
    "wof:placetype":"locality"
},
  "geometry": {"coordinates":[119.70022,27.31619],"type":"Point"}
}