{
  "type": "Feature",
  "properties": {
    "gn:admin1_code":"33.0",
    "gn:asciiname":"Longtian",
    "gn:country_code":"CN",
    "gn:dem":739,
    "gn:feature_class":"P",
    "gn:feature_code":"PPLA4",
    "gn:name":"Longtian",
    "gn:population":0,
    "gn:timezone":"Asia/Shanghai",
    "iso:country":"CN",
    "name:ceb_x_preferred":[
        "Longtian"
    ],
    "name:swe_x_preferred":[
        "Longtian"
    ],
    "name:und_x_variant":[
        "Longtian Xiang",
        "Zhongbazi"
    ],
    "name:zho_x_preferred":[
        "\u9f99\u7530"
    ],
    "name:zho_x_variant":[
        "\u9f99\u7530\u4e61",
        "\u4e2d\u575d\u5b50"
    ],
    "wof:name":"Longtian",
    "wof:placetype":"locality"
},
  "geometry": {"coordinates":[108.63473999999999,31.97427],"type":"Point"}
}