{
  "type": "Feature",
  "properties": {
    "gn:admin1_code":"4.0",
    "gn:asciiname":"Xingchen",
    "gn:country_code":"CN",
    "gn:dem":28,
    "gn:feature_class":"P",
    "gn:feature_code":"PPL",
    "gn:name":"Xingchen",
    "gn:population":0,
    "gn:timezone":"Asia/Shanghai",
    "iso:country":"CN",
    "name:und_x_variant":[
        "\u5174\u8fb0"
    ],
    "wof:name":"Xingchen",
    "wof:placetype":"locality"
},
  "geometry": {"coordinates":[118.71428,34.75034],"type":"Point"}
}