{
  "type": "Feature",
  "properties": {
    "gn:admin1_code":"8.0",
    "gn:asciiname":"Xiwangjiatun",
    "gn:country_code":"CN",
    "gn:dem":103,
    "gn:feature_class":"P",
    "gn:feature_code":"PPL",
    "gn:name":"Xiwangjiatun",
    "gn:population":0,
    "gn:timezone":"Asia/Shanghai",
    "iso:country":"CN",
    "name:zho_x_preferred":[
        "\u897f\u738b\u5bb6\u5c6f"
    ],
    "wof:name":"Xiwangjiatun",
    "wof:placetype":"locality"
},
  "geometry": {"coordinates":[128.49420000000001,45.94152],"type":"Point"}
}