{
  "type": "Feature",
  "properties": {
    "gn:admin1_code":"12.0",
    "gn:asciiname":"Chaijia'ao",
    "gn:country_code":"CN",
    "gn:dem":528,
    "gn:feature_class":"P",
    "gn:feature_code":"PPL",
    "gn:name":"Chaijia\u2019ao",
    "gn:population":0,
    "gn:timezone":"Asia/Shanghai",
    "iso:country":"CN",
    "name:und_x_variant":[
        "Chaijia\u2019ao"
    ],
    "name:zho_x_preferred":[
        "\u67f4\u5bb6\u51f9"
    ],
    "wof:name":"Chaijia'ao",
    "wof:placetype":"locality"
},
  "geometry": {"coordinates":[110.96926000000001,33.0095],"type":"Point"}
}