{
  "type": "Feature",
  "properties": {
    "gn:admin1_code":"3.0",
    "gn:asciiname":"Zhengkeng",
    "gn:country_code":"CN",
    "gn:dem":62,
    "gn:feature_class":"P",
    "gn:feature_code":"PPL",
    "gn:name":"Zhengkeng",
    "gn:population":0,
    "gn:timezone":"Asia/Shanghai",
    "iso:country":"CN",
    "name:und_x_variant":[
        "\u6b63\u5751"
    ],
    "wof:name":"Zhengkeng",
    "wof:placetype":"locality"
},
  "geometry": {"coordinates":[114.76148999999999,28.27645],"type":"Point"}
}