{
  "type": "Feature",
  "properties": {
    "gn:admin1_code":"26.0",
    "gn:asciiname":"Hejia Wuji",
    "gn:country_code":"CN",
    "gn:dem":1427,
    "gn:feature_class":"P",
    "gn:feature_code":"PPL",
    "gn:name":"Hejia Wuji",
    "gn:population":0,
    "gn:timezone":"Asia/Shanghai",
    "iso:country":"CN",
    "name:und_x_variant":[
        "\u4f55\u5bb6\u5c4b\u57fa"
    ],
    "wof:name":"Hejia Wuji",
    "wof:placetype":"locality"
},
  "geometry": {"coordinates":[106.34699999999999,32.78661],"type":"Point"}
}