{
  "type": "Feature",
  "properties": {
    "gn:admin1_code":"21.0",
    "gn:asciiname":"Yuwan",
    "gn:country_code":"CN",
    "gn:dem":2164,
    "gn:feature_class":"P",
    "gn:feature_code":"PPL",
    "gn:name":"Yuwan",
    "gn:population":0,
    "gn:timezone":"Asia/Shanghai",
    "iso:country":"CN",
    "name:nno_x_preferred":[
        "Yuwan"
    ],
    "name:urd_x_preferred":[
        "\u06cc\u0648\u0646"
    ],
    "name:zho_x_preferred":[
        "\u7389\u6e7e"
    ],
    "wof:name":"Yuwan",
    "wof:placetype":"locality"
},
  "geometry": {"coordinates":[106.127,35.7295],"type":"Point"}
}