{
  "type": "Feature",
  "properties": {
    "gn:admin1_code":"13.0",
    "gn:asciiname":"Arele",
    "gn:country_code":"CN",
    "gn:dem":1305,
    "gn:feature_class":"P",
    "gn:feature_code":"PPL",
    "gn:name":"Arele",
    "gn:population":0,
    "gn:timezone":"Asia/Shanghai",
    "iso:country":"CN",
    "name:zho_x_preferred":[
        "\u963f\u70ed\u52d2"
    ],
    "wof:name":"Arele",
    "wof:placetype":"locality"
},
  "geometry": {"coordinates":[79.60417,37.41862],"type":"Point"}
}