{
  "type": "Feature",
  "properties": {
    "gn:admin1_code":"12.0",
    "gn:asciiname":"Zoujiahe",
    "gn:country_code":"CN",
    "gn:dem":76,
    "gn:feature_class":"P",
    "gn:feature_code":"PPL",
    "gn:name":"Zoujiahe",
    "gn:population":0,
    "gn:timezone":"Asia/Shanghai",
    "iso:country":"CN",
    "name:zho_x_preferred":[
        "Zoujiahe"
    ],
    "name:zho_x_variant":[
        "\u90b9\u5bb6\u6cb3"
    ],
    "wof:name":"Zoujiahe",
    "wof:placetype":"locality"
},
  "geometry": {"coordinates":[115.05573,30.93391],"type":"Point"}
}