{
  "type": "Feature",
  "properties": {
    "gn:admin1_code":"32.0",
    "gn:asciiname":"Longjiagou",
    "gn:country_code":"CN",
    "gn:dem":2260,
    "gn:feature_class":"P",
    "gn:feature_code":"PPL",
    "gn:name":"Longjiagou",
    "gn:population":0,
    "gn:timezone":"Asia/Shanghai",
    "iso:country":"CN",
    "name:zho_x_preferred":[
        "\u9f99\u5bb6\u6c9f"
    ],
    "wof:name":"Longjiagou",
    "wof:placetype":"locality"
},
  "geometry": {"coordinates":[101.91160000000001,28.44722],"type":"Point"}
}