{
  "type": "Feature",
  "properties": {
    "gn:admin1_code":"32.0",
    "gn:asciiname":"Jidong",
    "gn:country_code":"CN",
    "gn:dem":2954,
    "gn:feature_class":"P",
    "gn:feature_code":"PPL",
    "gn:name":"Jidong",
    "gn:population":0,
    "gn:timezone":"Asia/Shanghai",
    "iso:country":"CN",
    "name:zho_x_preferred":[
        "\u5409\u52a8"
    ],
    "wof:name":"Jidong",
    "wof:placetype":"locality"
},
  "geometry": {"coordinates":[100.59242999999999,28.11807],"type":"Point"}
}