{
  "type": "Feature",
  "properties": {
    "gn:admin1_code":"26.0",
    "gn:asciiname":"Xianhecun",
    "gn:country_code":"CN",
    "gn:dem":1002,
    "gn:feature_class":"P",
    "gn:feature_code":"PPL",
    "gn:name":"Xianhecun",
    "gn:population":0,
    "gn:timezone":"Asia/Shanghai",
    "iso:country":"CN",
    "name:zho_x_preferred":[
        "\u54b8\u5408\u6751"
    ],
    "wof:name":"Xianhecun",
    "wof:placetype":"locality"
},
  "geometry": {"coordinates":[109.98831,35.40423],"type":"Point"}
}