{
  "type": "Feature",
  "properties": {
    "gn:admin1_code":"32.0",
    "gn:asciiname":"Wenxing",
    "gn:country_code":"CN",
    "gn:dem":928,
    "gn:feature_class":"P",
    "gn:feature_code":"PPL",
    "gn:name":"Wenxing",
    "gn:population":0,
    "gn:timezone":"Asia/Shanghai",
    "iso:country":"CN",
    "name:mlg_x_preferred":[
        "Wenxing"
    ],
    "name:und_x_variant":[
        "\u6587\u661f"
    ],
    "name:zho_x_preferred":[
        "\u6587\u661f\u9547"
    ],
    "wof:name":"Wenxing",
    "wof:placetype":"locality"
},
  "geometry": {"coordinates":[106.00436999999999,32.12914],"type":"Point"}
}