{
  "type": "Feature",
  "properties": {
    "gn:admin1_code":"24.0",
    "gn:asciiname":"Zhongmafang",
    "gn:country_code":"CN",
    "gn:dem":1501,
    "gn:feature_class":"P",
    "gn:feature_code":"PPL",
    "gn:name":"Zhongmafang",
    "gn:population":0,
    "gn:timezone":"Asia/Shanghai",
    "iso:country":"CN",
    "name:zho_x_preferred":[
        "\u4e2d\u9a6c\u574a"
    ],
    "wof:name":"Zhongmafang",
    "wof:placetype":"locality"
},
  "geometry": {"coordinates":[112.17668,38.69962],"type":"Point"}
}