{
  "type": "Feature",
  "properties": {
    "gn:admin1_code":"8.0",
    "gn:asciiname":"Yufacun",
    "gn:country_code":"CN",
    "gn:dem":263,
    "gn:feature_class":"P",
    "gn:feature_code":"PPL",
    "gn:name":"Yufacun",
    "gn:population":0,
    "gn:timezone":"Asia/Shanghai",
    "iso:country":"CN",
    "name:zho_x_preferred":[
        "\u88d5\u53d1\u6751"
    ],
    "wof:name":"Yufacun",
    "wof:placetype":"locality"
},
  "geometry": {"coordinates":[129.57602,44.80206],"type":"Point"}
}