{
  "type": "Feature",
  "properties": {
    "gn:admin1_code":"14.0",
    "gn:asciiname":"Xuekacun",
    "gn:country_code":"CN",
    "gn:dem":2944,
    "gn:feature_class":"P",
    "gn:feature_code":"PPL",
    "gn:name":"Xuekacun",
    "gn:population":0,
    "gn:timezone":"Asia/Urumqi",
    "iso:country":"CN",
    "name:zho_x_preferred":[
        "\u96ea\u5361\u6751"
    ],
    "wof:name":"Xuekacun",
    "wof:placetype":"locality"
},
  "geometry": {"coordinates":[94.25826000000001,29.24874],"type":"Point"}
}