{
  "type": "Feature",
  "properties": {
    "gn:admin1_code":"12.0",
    "gn:asciiname":"Zhangjiachi",
    "gn:country_code":"CN",
    "gn:dem":25,
    "gn:feature_class":"P",
    "gn:feature_code":"PPL",
    "gn:name":"Zhangjiachi",
    "gn:population":0,
    "gn:timezone":"Asia/Shanghai",
    "iso:country":"CN",
    "name:zho_x_preferred":[
        "\u5f20\u5bb6\u6c60"
    ],
    "wof:name":"Zhangjiachi",
    "wof:placetype":"locality"
},
  "geometry": {"coordinates":[113.66451000000001,30.12877000000001],"type":"Point"}
}