{
  "type": "Feature",
  "properties": {
    "gn:admin1_code":"11.0",
    "gn:asciiname":"Gaogengli",
    "gn:country_code":"CN",
    "gn:dem":949,
    "gn:feature_class":"P",
    "gn:feature_code":"PPL",
    "gn:name":"Gaogengli",
    "gn:population":0,
    "gn:timezone":"Asia/Shanghai",
    "iso:country":"CN",
    "name:zho_x_preferred":[
        "\u9ad8\u57c2\u91cc"
    ],
    "wof:name":"Gaogengli",
    "wof:placetype":"locality"
},
  "geometry": {"coordinates":[113.642,25.86091],"type":"Point"}
}