{
  "type": "Feature",
  "properties": {
    "gn:admin1_code":"9",
    "gn:asciiname":"Luoligu",
    "gn:country_code":"CN",
    "gn:dem":51,
    "gn:feature_class":"P",
    "gn:feature_code":"PPL",
    "gn:name":"Luoligu",
    "gn:population":0,
    "gn:timezone":"Asia/Shanghai",
    "iso:country":"CN",
    "name:zho_x_preferred":[
        "\u7f57\u91cc\u56fa"
    ],
    "wof:name":"Luoligu",
    "wof:placetype":"locality"
},
  "geometry": {"coordinates":[115.13898,36.02486],"type":"Point"}
}