{
  "type": "Feature",
  "properties": {
    "gn:admin1_code":"10",
    "gn:asciiname":"Sunjiawa",
    "gn:country_code":"CN",
    "gn:dem":24,
    "gn:feature_class":"P",
    "gn:feature_code":"PPL",
    "gn:name":"Sunjiawa",
    "gn:population":0,
    "gn:timezone":"Asia/Shanghai",
    "iso:country":"CN",
    "name:zho_x_preferred":[
        "\u5b59\u5bb6\u6d3c"
    ],
    "wof:name":"Sunjiawa",
    "wof:placetype":"locality"
},
  "geometry": {"coordinates":[115.58199999999999,37.7809],"type":"Point"}
}