{
  "type": "Feature",
  "properties": {
    "gn:admin1_code":"11",
    "gn:asciiname":"Lazhuling",
    "gn:country_code":"CN",
    "gn:dem":590,
    "gn:feature_class":"P",
    "gn:feature_code":"PPL",
    "gn:name":"Lazhuling",
    "gn:population":0,
    "gn:timezone":"Asia/Shanghai",
    "iso:country":"CN",
    "name:zho_x_preferred":[
        "\u814a\u7af9\u5cad"
    ],
    "wof:name":"Lazhuling",
    "wof:placetype":"locality"
},
  "geometry": {"coordinates":[111.81498000000001,25.12758],"type":"Point"}
}