{
  "type": "Feature",
  "properties": {
    "gn:admin1_code":"15.0",
    "gn:asciiname":"Dijiashan",
    "gn:country_code":"CN",
    "gn:dem":1837,
    "gn:feature_class":"P",
    "gn:feature_code":"PPL",
    "gn:name":"Dijiashan",
    "gn:population":0,
    "gn:timezone":"Asia/Shanghai",
    "iso:country":"CN",
    "name:zho_x_preferred":[
        "\u7fdf\u5bb6\u5c71"
    ],
    "wof:name":"Dijiashan",
    "wof:placetype":"locality"
},
  "geometry": {"coordinates":[105.051,34.1863],"type":"Point"}
}