{
  "type": "Feature",
  "properties": {
    "gn:admin1_code":"5.0",
    "gn:asciiname":"Changfatun",
    "gn:country_code":"CN",
    "gn:dem":155,
    "gn:feature_class":"P",
    "gn:feature_code":"PPL",
    "gn:name":"Changfatun",
    "gn:population":0,
    "gn:timezone":"Asia/Shanghai",
    "iso:country":"CN",
    "name:zho_x_preferred":[
        "\u957f\u53d1\u5c6f"
    ],
    "wof:name":"Changfatun",
    "wof:placetype":"locality"
},
  "geometry": {"coordinates":[122.87497,44.86356],"type":"Point"}
}