{
  "type": "Feature",
  "properties": {
    "gn:admin1_code":"9",
    "gn:asciiname":"Qianyuhuangmiao",
    "gn:country_code":"CN",
    "gn:dem":50,
    "gn:feature_class":"P",
    "gn:feature_code":"PPL",
    "gn:name":"Qianyuhuangmiao",
    "gn:population":0,
    "gn:timezone":"Asia/Shanghai",
    "iso:country":"CN",
    "name:zho_x_preferred":[
        "\u524d\u7389\u7687\u5e99"
    ],
    "wof:name":"Qianyuhuangmiao",
    "wof:placetype":"locality"
},
  "geometry": {"coordinates":[115.58,35.86473],"type":"Point"}
}