{
  "type": "Feature",
  "properties": {
    "gn:admin1_code":"12.0",
    "gn:asciiname":"Wanli",
    "gn:country_code":"CN",
    "gn:dem":353,
    "gn:feature_class":"P",
    "gn:feature_code":"PPL",
    "gn:name":"Wanli",
    "gn:population":0,
    "gn:timezone":"Asia/Shanghai",
    "iso:country":"CN",
    "name:ceb_x_preferred":[
        "Wanli"
    ],
    "name:deu_x_preferred":[
        "Wanli"
    ],
    "name:fra_x_preferred":[
        "Wanli"
    ],
    "name:nor_x_preferred":[
        "Wanli"
    ],
    "name:sco_x_preferred":[
        "Wanli"
    ],
    "name:zho_x_preferred":[
        "Wanli"
    ],
    "name:zho_x_variant":[
        "\u6e7e\u91cc"
    ],
    "wof:name":"Wanli",
    "wof:placetype":"locality"
},
  "geometry": {"coordinates":[114.22808000000001,29.25813],"type":"Point"}
}