{
  "type": "Feature",
  "properties": {
    "gn:admin1_code":"21.0",
    "gn:asciiname":"Xiaochazi",
    "gn:country_code":"CN",
    "gn:dem":1731,
    "gn:feature_class":"P",
    "gn:feature_code":"PPL",
    "gn:name":"Xiaochazi",
    "gn:population":0,
    "gn:timezone":"Asia/Shanghai",
    "iso:country":"CN",
    "name:und_x_variant":[
        "\u5c0f\u5c94\u5b50"
    ],
    "name:zho_x_preferred":[
        "\u5c0f\u5c94\u5b50"
    ],
    "wof:name":"Xiaochazi",
    "wof:placetype":"locality"
},
  "geometry": {"coordinates":[106.52427,36.26079],"type":"Point"}
}