{
  "type": "Feature",
  "properties": {
    "gn:admin1_code":"32.0",
    "gn:asciiname":"Niuzhaizi",
    "gn:country_code":"CN",
    "gn:dem":1722,
    "gn:feature_class":"P",
    "gn:feature_code":"PPL",
    "gn:name":"Niuzhaizi",
    "gn:population":0,
    "gn:timezone":"Asia/Shanghai",
    "iso:country":"CN",
    "name:zho_x_preferred":[
        "\u725b\u5be8\u5b50"
    ],
    "wof:name":"Niuzhaizi",
    "wof:placetype":"locality"
},
  "geometry": {"coordinates":[102.679,30.1612],"type":"Point"}
}