{
  "type": "Feature",
  "properties": {
    "gn:admin1_code":"12.0",
    "gn:asciiname":"Tianchishan",
    "gn:country_code":"CN",
    "gn:dem":1234,
    "gn:feature_class":"P",
    "gn:feature_code":"PPL",
    "gn:name":"Tianchishan",
    "gn:population":0,
    "gn:timezone":"Asia/Shanghai",
    "iso:country":"CN",
    "name:zho_x_preferred":[
        "\u5929\u6c60\u5c71"
    ],
    "wof:name":"Tianchishan",
    "wof:placetype":"locality"
},
  "geometry": {"coordinates":[109.64868,30.34379],"type":"Point"}
}