{
  "type": "Feature",
  "properties": {
    "gn:admin1_code":"22.0",
    "gn:asciiname":"Zhengchangzhuang",
    "gn:country_code":"CN",
    "gn:dem":54,
    "gn:feature_class":"P",
    "gn:feature_code":"PPL",
    "gn:name":"Zhengchangzhuang",
    "gn:population":0,
    "gn:timezone":"Asia/Shanghai",
    "iso:country":"CN",
    "name:zho_x_preferred":[
        "\u90d1\u5e38\u5e84"
    ],
    "wof:name":"Zhengchangzhuang",
    "wof:placetype":"locality"
},
  "geometry": {"coordinates":[116.27627,39.88846],"type":"Point"}
}