{
  "type": "Feature",
  "properties": {
    "gn:admin1_code":"30.0",
    "gn:asciiname":"Xiaoligong",
    "gn:country_code":"CN",
    "gn:dem":639,
    "gn:feature_class":"P",
    "gn:feature_code":"PPL",
    "gn:name":"Xiaoligong",
    "gn:population":0,
    "gn:timezone":"Asia/Shanghai",
    "iso:country":"CN",
    "name:zho_x_preferred":[
        "Xiaoligong"
    ],
    "name:zho_x_variant":[
        "\u5c0f\u91cc\u516c"
    ],
    "wof:name":"Xiaoligong",
    "wof:placetype":"locality"
},
  "geometry": {"coordinates":[112.75556,24.37639],"type":"Point"}
}