{
  "type": "Feature",
  "properties": {
    "gn:admin1_code":"7.0",
    "gn:asciiname":"Kengmei",
    "gn:country_code":"CN",
    "gn:dem":677,
    "gn:feature_class":"P",
    "gn:feature_code":"PPL",
    "gn:name":"Kengmei",
    "gn:population":0,
    "gn:timezone":"Asia/Shanghai",
    "iso:country":"CN",
    "name:und_x_variant":[
        "\u5751\u7f8e"
    ],
    "name:zho_x_preferred":[
        "\u5751\u7f8e"
    ],
    "wof:name":"Kengmei",
    "wof:placetype":"locality"
},
  "geometry": {"coordinates":[118.26336999999999,26.03559],"type":"Point"}
}