{
  "type": "Feature",
  "properties": {
    "gn:admin1_code":"8.0",
    "gn:asciiname":"Shichengcun",
    "gn:country_code":"CN",
    "gn:dem":211,
    "gn:feature_class":"P",
    "gn:feature_code":"PPL",
    "gn:name":"Shichengcun",
    "gn:population":0,
    "gn:timezone":"Asia/Shanghai",
    "iso:country":"CN",
    "name:und_x_variant":[
        "Shichengtun"
    ],
    "name:zho_x_preferred":[
        "\u77f3\u57ce\u6751"
    ],
    "name:zho_x_variant":[
        "\u77f3\u57ce\u5c6f"
    ],
    "wof:name":"Shichengcun",
    "wof:placetype":"locality"
},
  "geometry": {"coordinates":[128.01158000000001,45.47056],"type":"Point"}
}