{
  "type": "Feature",
  "properties": {
    "gn:admin1_code":"29",
    "gn:asciiname":"Mozuodie",
    "gn:country_code":"CN",
    "gn:dem":1566,
    "gn:feature_class":"P",
    "gn:feature_code":"PPL",
    "gn:name":"Mozuodie",
    "gn:population":0,
    "gn:timezone":"Asia/Shanghai",
    "iso:country":"CN",
    "name:zho_x_preferred":[
        "\u83ab\u4f5c\u57a4"
    ],
    "wof:name":"Mozuodie",
    "wof:placetype":"locality"
},
  "geometry": {"coordinates":[102.176,23.6113],"type":"Point"}
}