{
  "type": "Feature",
  "properties": {
    "gn:admin1_code":"14.0",
    "gn:asciiname":"Balai",
    "gn:country_code":"CN",
    "gn:dem":4460,
    "gn:feature_class":"P",
    "gn:feature_code":"PPL",
    "gn:name":"Balai",
    "gn:population":0,
    "gn:timezone":"Asia/Urumqi",
    "iso:country":"CN",
    "name:zho_x_preferred":[
        "\u516b\u6765"
    ],
    "wof:name":"Balai",
    "wof:placetype":"locality"
},
  "geometry": {"coordinates":[96.25091999999999,31.50052],"type":"Point"}
}