{
  "type": "Feature",
  "properties": {
    "gn:admin1_code":"25",
    "gn:asciiname":"Lijiatao",
    "gn:country_code":"CN",
    "gn:dem":14,
    "gn:feature_class":"P",
    "gn:feature_code":"PPL",
    "gn:name":"Lijiatao",
    "gn:population":0,
    "gn:timezone":"Asia/Shanghai",
    "iso:country":"CN",
    "name:zho_x_preferred":[
        "\u674e\u5bb6\u5957"
    ],
    "wof:name":"Lijiatao",
    "wof:placetype":"locality"
},
  "geometry": {"coordinates":[117.771,36.9812],"type":"Point"}
}