{
  "type": "Feature",
  "properties": {
    "gn:admin1_code":"5.0",
    "gn:asciiname":"Dongguojiajie",
    "gn:country_code":"CN",
    "gn:dem":212,
    "gn:feature_class":"P",
    "gn:feature_code":"PPL",
    "gn:name":"Dongguojiajie",
    "gn:population":0,
    "gn:timezone":"Asia/Shanghai",
    "iso:country":"CN",
    "name:zho_x_preferred":[
        "\u4e1c\u90ed\u5bb6\u8857"
    ],
    "wof:name":"Dongguojiajie",
    "wof:placetype":"locality"
},
  "geometry": {"coordinates":[125.63849,43.52612],"type":"Point"}
}