{
  "type": "Feature",
  "properties": {
    "gn:admin1_code":"4.0",
    "gn:asciiname":"Dalucun",
    "gn:country_code":"CN",
    "gn:dem":3,
    "gn:feature_class":"P",
    "gn:feature_code":"PPL",
    "gn:name":"Dalucun",
    "gn:population":0,
    "gn:timezone":"Asia/Shanghai",
    "iso:country":"CN",
    "name:zho_x_preferred":[
        "\u5927\u9646\u6751"
    ],
    "wof:name":"Dalucun",
    "wof:placetype":"locality"
},
  "geometry": {"coordinates":[119.35290999999999,33.28027],"type":"Point"}
}