{
  "type": "Feature",
  "properties": {
    "gn:admin1_code":"20.0",
    "gn:asciiname":"Shangsicun",
    "gn:country_code":"CN",
    "gn:dem":1627,
    "gn:feature_class":"P",
    "gn:feature_code":"PPL",
    "gn:name":"Shangsicun",
    "gn:population":0,
    "gn:timezone":"Asia/Shanghai",
    "iso:country":"CN",
    "name:zho_x_preferred":[
        "\u4e0a\u56db\u6751"
    ],
    "wof:name":"Shangsicun",
    "wof:placetype":"locality"
},
  "geometry": {"coordinates":[112.58121,41.4874],"type":"Point"}
}