{
  "type": "Feature",
  "properties": {
    "gn:admin1_code":"29.0",
    "gn:asciiname":"Haimacun",
    "gn:country_code":"CN",
    "gn:dem":1905,
    "gn:feature_class":"P",
    "gn:feature_code":"PPL",
    "gn:name":"Haimacun",
    "gn:population":0,
    "gn:timezone":"Asia/Shanghai",
    "iso:country":"CN",
    "name:zho_x_preferred":[
        "\u6d77\u9a6c\u6751"
    ],
    "wof:name":"Haimacun",
    "wof:placetype":"locality"
},
  "geometry": {"coordinates":[104.09399999999999,25.1035],"type":"Point"}
}