{
  "type": "Feature",
  "properties": {
    "gn:admin1_code":"4.0",
    "gn:asciiname":"Xinxiang",
    "gn:country_code":"CN",
    "gn:dem":6,
    "gn:feature_class":"P",
    "gn:feature_code":"PPL",
    "gn:name":"Xinxiang",
    "gn:population":0,
    "gn:timezone":"Asia/Shanghai",
    "iso:country":"CN",
    "name:und_x_variant":[
        "\u65b0\u5df7"
    ],
    "name:zho_x_preferred":[
        "\u65b0\u5df7"
    ],
    "wof:name":"Xinxiang",
    "wof:placetype":"locality"
},
  "geometry": {"coordinates":[120.57092,32.7368],"type":"Point"}
}