{
  "type": "Feature",
  "properties": {
    "gn:admin1_code":"29",
    "gn:asciiname":"Baduo",
    "gn:country_code":"CN",
    "gn:dem":1052,
    "gn:feature_class":"P",
    "gn:feature_code":"PPL",
    "gn:name":"Baduo",
    "gn:population":0,
    "gn:timezone":"Asia/Shanghai",
    "iso:country":"CN",
    "name:zho_x_preferred":[
        "\u5c9c\u593a"
    ],
    "wof:name":"Baduo",
    "wof:placetype":"locality"
},
  "geometry": {"coordinates":[105.143,24.1479],"type":"Point"}
}