{
  "type": "Feature",
  "properties": {
    "gn:admin1_code":"2.0",
    "gn:asciiname":"Chayekeng",
    "gn:country_code":"CN",
    "gn:dem":173,
    "gn:feature_class":"P",
    "gn:feature_code":"PPL",
    "gn:name":"Chayekeng",
    "gn:population":0,
    "gn:timezone":"Asia/Shanghai",
    "iso:country":"CN",
    "name:zho_x_preferred":[
        "\u8336\u53f6\u5751"
    ],
    "wof:name":"Chayekeng",
    "wof:placetype":"locality"
},
  "geometry": {"coordinates":[120.42095999999999,29.21603],"type":"Point"}
}