{
  "type": "Feature",
  "properties": {
    "gn:admin1_code":"07",
    "gn:asciiname":"Cuntou",
    "gn:country_code":"CN",
    "gn:dem":583,
    "gn:feature_class":"P",
    "gn:feature_code":"PPL",
    "gn:name":"Cuntou",
    "gn:population":0,
    "gn:timezone":"Asia/Shanghai",
    "iso:country":"CN",
    "name:zho_x_preferred":[
        "\u6751\u5934"
    ],
    "wof:name":"Cuntou",
    "wof:placetype":"locality"
},
  "geometry": {"coordinates":[118.57899999999999,26.83228],"type":"Point"}
}