{
  "type": "Feature",
  "properties": {
    "gn:admin1_code":"2.0",
    "gn:asciiname":"Zhangkengkou",
    "gn:country_code":"CN",
    "gn:dem":238,
    "gn:feature_class":"P",
    "gn:feature_code":"PPL",
    "gn:name":"Zhangkengkou",
    "gn:population":0,
    "gn:timezone":"Asia/Shanghai",
    "iso:country":"CN",
    "name:zho_x_preferred":[
        "\u7ae0\u5751\u53e3"
    ],
    "wof:name":"Zhangkengkou",
    "wof:placetype":"locality"
},
  "geometry": {"coordinates":[119.23152,29.69183],"type":"Point"}
}