{
  "type": "Feature",
  "properties": {
    "gn:admin1_code":"32.0",
    "gn:asciiname":"Shangcungou",
    "gn:country_code":"CN",
    "gn:dem":390,
    "gn:feature_class":"P",
    "gn:feature_code":"PPL",
    "gn:name":"Shangcungou",
    "gn:population":0,
    "gn:timezone":"Asia/Shanghai",
    "iso:country":"CN",
    "name:zho_x_preferred":[
        "\u4e0a\u6751\u6c9f"
    ],
    "wof:name":"Shangcungou",
    "wof:placetype":"locality"
},
  "geometry": {"coordinates":[105.51537,30.87473],"type":"Point"}
}