{
  "type": "Feature",
  "properties": {
    "gn:admin1_code":"1.0",
    "gn:asciiname":"Xionggangcun",
    "gn:country_code":"CN",
    "gn:dem":54,
    "gn:feature_class":"P",
    "gn:feature_code":"PPL",
    "gn:name":"Xionggangcun",
    "gn:population":0,
    "gn:timezone":"Asia/Shanghai",
    "iso:country":"CN",
    "name:zho_x_preferred":[
        "\u718a\u5c97\u6751"
    ],
    "wof:name":"Xionggangcun",
    "wof:placetype":"locality"
},
  "geometry": {"coordinates":[117.47714000000001,32.2614],"type":"Point"}
}