{
  "type": "Feature",
  "properties": {
    "gn:admin1_code":"26.0",
    "gn:asciiname":"Yong'an",
    "gn:country_code":"CN",
    "gn:dem":657,
    "gn:feature_class":"P",
    "gn:feature_code":"PPL",
    "gn:name":"Yong\u2019an",
    "gn:population":0,
    "gn:timezone":"Asia/Shanghai",
    "iso:country":"CN",
    "name:und_x_variant":[
        "Yong\u2019an",
        "\u6c38\u5b89"
    ],
    "wof:name":"Yong'an",
    "wof:placetype":"locality"
},
  "geometry": {"coordinates":[107.9097,34.46014],"type":"Point"}
}