{
  "type": "Feature",
  "properties": {
    "gn:admin1_code":"3.0",
    "gn:asciiname":"Bantian",
    "gn:country_code":"CN",
    "gn:dem":94,
    "gn:feature_class":"P",
    "gn:feature_code":"PPL",
    "gn:name":"Bantian",
    "gn:population":0,
    "gn:timezone":"Asia/Shanghai",
    "iso:country":"CN",
    "name:und_x_variant":[
        "\u962a\u7530"
    ],
    "wof:name":"Bantian",
    "wof:placetype":"locality"
},
  "geometry": {"coordinates":[114.59514,28.10351],"type":"Point"}
}