{
  "type": "Feature",
  "properties": {
    "gn:admin1_code":"30.0",
    "gn:asciiname":"Chiziwei",
    "gn:country_code":"CN",
    "gn:dem":298,
    "gn:feature_class":"P",
    "gn:feature_code":"PPL",
    "gn:name":"Chiziwei",
    "gn:population":0,
    "gn:timezone":"Asia/Shanghai",
    "iso:country":"CN",
    "name:zho_x_preferred":[
        "Chiziwei"
    ],
    "name:zho_x_variant":[
        "\u8d64\u5b50\u56f4"
    ],
    "wof:name":"Chiziwei",
    "wof:placetype":"locality"
},
  "geometry": {"coordinates":[114.45531,24.40435],"type":"Point"}
}