{
  "type": "Feature",
  "properties": {
    "gn:admin1_code":"9.0",
    "gn:asciiname":"Baidazhuang",
    "gn:country_code":"CN",
    "gn:dem":631,
    "gn:feature_class":"P",
    "gn:feature_code":"PPL",
    "gn:name":"Baidazhuang",
    "gn:population":0,
    "gn:timezone":"Asia/Shanghai",
    "iso:country":"CN",
    "name:und_x_variant":[
        "\u767d\u5927\u5e84",
        "Baidazhuang"
    ],
    "wof:name":"Baidazhuang",
    "wof:placetype":"locality"
},
  "geometry": {"coordinates":[112.19391,33.41271],"type":"Point"}
}