{
  "type": "Feature",
  "properties": {
    "gn:admin1_code":"2.0",
    "gn:asciiname":"Huangshitan",
    "gn:country_code":"CN",
    "gn:dem":389,
    "gn:feature_class":"P",
    "gn:feature_code":"PPL",
    "gn:name":"Huangshitan",
    "gn:population":0,
    "gn:timezone":"Asia/Shanghai",
    "iso:country":"CN",
    "name:zho_x_preferred":[
        "\u9ec4\u77f3\u5766"
    ],
    "wof:name":"Huangshitan",
    "wof:placetype":"locality"
},
  "geometry": {"coordinates":[120.93706,28.77929],"type":"Point"}
}