{
  "type": "Feature",
  "properties": {
    "gn:admin1_code":"01",
    "gn:asciiname":"Caodun",
    "gn:cc2":"CN",
    "gn:country_code":"CN",
    "gn:dem":41,
    "gn:feature_class":"P",
    "gn:feature_code":"PPL",
    "gn:name":"Caodun",
    "gn:population":0,
    "gn:timezone":"Asia/Shanghai",
    "iso:country":"CN",
    "name:und_x_variant":[
        "Ts\u2019ao-chia-tun",
        "Ts\u2019ao-tun",
        "Caodun"
    ],
    "wof:name":"Caodun",
    "wof:placetype":"locality"
},
  "geometry": {"coordinates":[116.28333000000001,32.21667],"type":"Point"}
}