{
  "type": "Feature",
  "properties": {
    "gn:admin1_code":"8.0",
    "gn:asciiname":"Jiushanmencun",
    "gn:country_code":"CN",
    "gn:dem":139,
    "gn:feature_class":"P",
    "gn:feature_code":"PPL",
    "gn:name":"Jiushanmencun",
    "gn:population":0,
    "gn:timezone":"Asia/Shanghai",
    "iso:country":"CN",
    "name:zho_x_preferred":[
        "\u4e5d\u6247\u95e8\u6751"
    ],
    "wof:name":"Jiushanmencun",
    "wof:placetype":"locality"
},
  "geometry": {"coordinates":[123.96322000000001,46.548],"type":"Point"}
}