{
  "type": "Feature",
  "properties": {
    "gn:admin1_code":"11.0",
    "gn:asciiname":"Changweizi",
    "gn:country_code":"CN",
    "gn:dem":25,
    "gn:feature_class":"P",
    "gn:feature_code":"PPL",
    "gn:name":"Changweizi",
    "gn:population":0,
    "gn:timezone":"Asia/Shanghai",
    "iso:country":"CN",
    "name:zho_x_preferred":[
        "\u957f\u56f4\u5b50"
    ],
    "wof:name":"Changweizi",
    "wof:placetype":"locality"
},
  "geometry": {"coordinates":[112.51788000000001,28.73565],"type":"Point"}
}