{
  "type": "Feature",
  "properties": {
    "gn:admin1_code":"25.0",
    "gn:asciiname":"Jujiazhuang",
    "gn:country_code":"CN",
    "gn:dem":43,
    "gn:feature_class":"P",
    "gn:feature_code":"PPL",
    "gn:name":"Jujiazhuang",
    "gn:population":0,
    "gn:timezone":"Asia/Shanghai",
    "iso:country":"CN",
    "name:zho_x_preferred":[
        "\u5de8\u7532\u5e84"
    ],
    "wof:name":"Jujiazhuang",
    "wof:placetype":"locality"
},
  "geometry": {"coordinates":[121.31955000000001,37.30494],"type":"Point"}
}