{
  "type": "Feature",
  "properties": {
    "gn:admin1_code":"18",
    "gn:asciiname":"Xianglushan",
    "gn:country_code":"CN",
    "gn:dem":1039,
    "gn:feature_class":"P",
    "gn:feature_code":"PPL",
    "gn:name":"Xianglushan",
    "gn:population":0,
    "gn:timezone":"Asia/Shanghai",
    "iso:country":"CN",
    "name:zho_x_preferred":[
        "\u9999\u7089\u5c71"
    ],
    "wof:name":"Xianglushan",
    "wof:placetype":"locality"
},
  "geometry": {"coordinates":[108.22799999999999,27.2511],"type":"Point"}
}