{
  "type": "Feature",
  "properties": {
    "gn:admin1_code":"14.0",
    "gn:asciiname":"Wage",
    "gn:country_code":"CN",
    "gn:dem":3288,
    "gn:feature_class":"P",
    "gn:feature_code":"PPL",
    "gn:name":"Wage",
    "gn:population":0,
    "gn:timezone":"Asia/Shanghai",
    "iso:country":"CN",
    "name:zho_x_preferred":[
        "\u74e6\u683c"
    ],
    "wof:name":"Wage",
    "wof:placetype":"locality"
},
  "geometry": {"coordinates":[98.28446,32.1612],"type":"Point"}
}