{
  "type": "Feature",
  "properties": {
    "gn:admin1_code":"8.0",
    "gn:asciiname":"Liugongli",
    "gn:country_code":"CN",
    "gn:dem":352,
    "gn:feature_class":"P",
    "gn:feature_code":"PPL",
    "gn:name":"Liugongli",
    "gn:population":0,
    "gn:timezone":"Asia/Shanghai",
    "iso:country":"CN",
    "name:zho_x_preferred":[
        "\u516d\u516c\u91cc"
    ],
    "wof:name":"Liugongli",
    "wof:placetype":"locality"
},
  "geometry": {"coordinates":[128.86857000000001,44.51008],"type":"Point"}
}