{
  "type": "Feature",
  "properties": {
    "gn:admin1_code":"30",
    "gn:asciiname":"Bawan",
    "gn:country_code":"CN",
    "gn:dem":28,
    "gn:feature_class":"P",
    "gn:feature_code":"PPLA4",
    "gn:name":"Bawan",
    "gn:population":0,
    "gn:timezone":"Asia/Shanghai",
    "iso:country":"CN",
    "name:und_x_variant":[
        "Bawan Zhen",
        "\u516b\u4e07\u9547"
    ],
    "name:zho_x_preferred":[
        "\u516b\u4e07"
    ],
    "wof:name":"Bawan",
    "wof:placetype":"locality"
},
  "geometry": {"coordinates":[115.75235000000001,23.03367],"type":"Point"}
}