{
  "type": "Feature",
  "properties": {
    "gn:admin1_code":"22",
    "gn:asciiname":"Yanqi",
    "gn:country_code":"CN",
    "gn:dem":55,
    "gn:feature_class":"P",
    "gn:feature_code":"PPLA4",
    "gn:name":"Yanqi",
    "gn:population":0,
    "gn:timezone":"Asia/Shanghai",
    "iso:country":"CN",
    "name:und_x_variant":[
        "Fangezhuang",
        "Yanqi Zhen"
    ],
    "name:zho_x_preferred":[
        "\u96c1\u6816"
    ],
    "name:zho_x_variant":[
        "\u8303\u5404\u5e84",
        "\u96c1\u6816\u9547"
    ],
    "wof:name":"Yanqi",
    "wof:placetype":"locality"
},
  "geometry": {"coordinates":[116.65626,40.36172],"type":"Point"}
}