{
  "type": "Feature",
  "properties": {
    "gn:admin1_code":"9.0",
    "gn:asciiname":"Xiaolizhuang",
    "gn:country_code":"CN",
    "gn:dem":149,
    "gn:feature_class":"P",
    "gn:feature_code":"PPL",
    "gn:name":"Xiaolizhuang",
    "gn:population":0,
    "gn:timezone":"Asia/Shanghai",
    "iso:country":"CN",
    "name:zho_x_preferred":[
        "\u5c0f\u674e\u5e84"
    ],
    "wof:name":"Xiaolizhuang",
    "wof:placetype":"locality"
},
  "geometry": {"coordinates":[113.10382,32.69877],"type":"Point"}
}