{
  "type": "Feature",
  "properties": {
    "gn:admin1_code":"8.0",
    "gn:asciiname":"Guoqingcun",
    "gn:country_code":"CN",
    "gn:dem":291,
    "gn:feature_class":"P",
    "gn:feature_code":"PPL",
    "gn:name":"Guoqingcun",
    "gn:population":0,
    "gn:timezone":"Asia/Shanghai",
    "iso:country":"CN",
    "name:zho_x_preferred":[
        "\u56fd\u5e86\u6751"
    ],
    "wof:name":"Guoqingcun",
    "wof:placetype":"locality"
},
  "geometry": {"coordinates":[125.56726,48.6519],"type":"Point"}
}