{
  "type": "Feature",
  "properties": {
    "gn:admin1_code":"2.0",
    "gn:asciiname":"Xinqiaobang",
    "gn:country_code":"CN",
    "gn:dem":5,
    "gn:feature_class":"P",
    "gn:feature_code":"PPL",
    "gn:name":"Xinqiaobang",
    "gn:population":0,
    "gn:timezone":"Asia/Shanghai",
    "iso:country":"CN",
    "name:und_x_variant":[
        "\u65b0\u6865\u6d5c"
    ],
    "wof:name":"Xinqiaobang",
    "wof:placetype":"locality"
},
  "geometry": {"coordinates":[120.96599999999999,30.7867],"type":"Point"}
}