{
  "type": "Feature",
  "properties": {
    "gn:admin1_code":"13",
    "gn:asciiname":"Gu'erwen Tulega Muchang",
    "gn:country_code":"CN",
    "gn:dem":2634,
    "gn:feature_class":"P",
    "gn:feature_code":"PPLF",
    "gn:name":"Gu\u2019erwen Tulega Muchang",
    "gn:population":0,
    "gn:timezone":"Asia/Urumqi",
    "iso:country":"CN",
    "name:und_x_variant":[
        "Gu\u2019erwen Tulega Muchang",
        "\u53e4\u5c14\u6e29\u56fe\u52d2\u5c15\u7267\u573a"
    ],
    "wof:name":"Gu'erwen Tulega Muchang",
    "wof:placetype":"locality"
},
  "geometry": {"coordinates":[84.83126,42.95564],"type":"Point"}
}