{
  "type": "Feature",
  "properties": {
    "gn:admin1_code":"1.0",
    "gn:asciiname":"Zhouhuangcun",
    "gn:country_code":"CN",
    "gn:dem":20,
    "gn:feature_class":"P",
    "gn:feature_code":"PPL",
    "gn:name":"Zhouhuangcun",
    "gn:population":0,
    "gn:timezone":"Asia/Shanghai",
    "iso:country":"CN",
    "name:zho_x_preferred":[
        "\u5468\u9ec4\u6751"
    ],
    "wof:name":"Zhouhuangcun",
    "wof:placetype":"locality"
},
  "geometry": {"coordinates":[117.56867,31.60587],"type":"Point"}
}