{
  "type": "Feature",
  "properties": {
    "gn:admin1_code":"30.0",
    "gn:asciiname":"Tanlang",
    "gn:country_code":"CN",
    "gn:dem":9,
    "gn:feature_class":"P",
    "gn:feature_code":"PPL",
    "gn:name":"Tanlang",
    "gn:population":0,
    "gn:timezone":"Asia/Urumqi",
    "iso:country":"CN",
    "name:zho_x_preferred":[
        "\u6f6d\u6717"
    ],
    "wof:name":"Tanlang",
    "wof:placetype":"locality"
},
  "geometry": {"coordinates":[109.83859,20.53582],"type":"Point"}
}