{
  "type": "Feature",
  "properties": {
    "gn:admin1_code":"5.0",
    "gn:asciiname":"Minzhucun",
    "gn:country_code":"CN",
    "gn:dem":145,
    "gn:feature_class":"P",
    "gn:feature_code":"PPL",
    "gn:name":"Minzhucun",
    "gn:population":0,
    "gn:timezone":"Asia/Shanghai",
    "iso:country":"CN",
    "name:zho_x_preferred":[
        "\u6c11\u4e3b\u6751"
    ],
    "wof:name":"Minzhucun",
    "wof:placetype":"locality"
},
  "geometry": {"coordinates":[124.88878,45.21282],"type":"Point"}
}