{
  "type": "Feature",
  "properties": {
    "gn:admin1_code":"10",
    "gn:asciiname":"Guoyawo",
    "gn:country_code":"CN",
    "gn:dem":46,
    "gn:feature_class":"P",
    "gn:feature_code":"PPL",
    "gn:name":"Guoyawo",
    "gn:population":0,
    "gn:timezone":"Asia/Shanghai",
    "iso:country":"CN",
    "name:zho_x_preferred":[
        "\u90ed\u9e2d\u7a9d"
    ],
    "wof:name":"Guoyawo",
    "wof:placetype":"locality"
},
  "geometry": {"coordinates":[115.13764,36.46411],"type":"Point"}
}