{
  "type": "Feature",
  "properties": {
    "gn:admin1_code":"8.0",
    "gn:asciiname":"Liuwangshengtun",
    "gn:country_code":"CN",
    "gn:dem":257,
    "gn:feature_class":"P",
    "gn:feature_code":"PPL",
    "gn:name":"Liuwangshengtun",
    "gn:population":0,
    "gn:timezone":"Asia/Shanghai",
    "iso:country":"CN",
    "name:zho_x_preferred":[
        "\u5218\u4e07\u80dc\u5c6f"
    ],
    "wof:name":"Liuwangshengtun",
    "wof:placetype":"locality"
},
  "geometry": {"coordinates":[126.16218000000001,47.99977],"type":"Point"}
}