{
  "type": "Feature",
  "properties": {
    "gn:admin1_code":"7",
    "gn:asciiname":"Puzaihou",
    "gn:country_code":"CN",
    "gn:dem":406,
    "gn:feature_class":"P",
    "gn:feature_code":"PPL",
    "gn:name":"Puzaihou",
    "gn:population":0,
    "gn:timezone":"Asia/Shanghai",
    "iso:country":"CN",
    "name:zho_x_preferred":[
        "\u57d4\u4ed4\u540e"
    ],
    "wof:name":"Puzaihou",
    "wof:placetype":"locality"
},
  "geometry": {"coordinates":[117.46556,24.74389],"type":"Point"}
}