{
  "type": "Feature",
  "properties": {
    "gn:admin1_code":"10",
    "gn:asciiname":"Dongjiubozi",
    "gn:country_code":"CN",
    "gn:dem":277,
    "gn:feature_class":"P",
    "gn:feature_code":"PPL",
    "gn:name":"Dongjiubozi",
    "gn:population":0,
    "gn:timezone":"Asia/Shanghai",
    "iso:country":"CN",
    "name:zho_x_preferred":[
        "\u4e1c\u4e5d\u62e8\u5b50"
    ],
    "wof:name":"Dongjiubozi",
    "wof:placetype":"locality"
},
  "geometry": {"coordinates":[119.11977,40.2314],"type":"Point"}
}