{
  "type": "Feature",
  "properties": {
    "gn:admin1_code":"16.0",
    "gn:asciiname":"Daliteng",
    "gn:country_code":"CN",
    "gn:dem":187,
    "gn:feature_class":"P",
    "gn:feature_code":"PPL",
    "gn:name":"Daliteng",
    "gn:population":0,
    "gn:timezone":"Asia/Shanghai",
    "iso:country":"CN",
    "name:zho_x_preferred":[
        "\u5927\u9ece\u85e4"
    ],
    "wof:name":"Daliteng",
    "wof:placetype":"locality"
},
  "geometry": {"coordinates":[109.16500000000001,25.1727],"type":"Point"}
}