{
  "type": "Feature",
  "properties": {
    "gn:admin1_code":"8.0",
    "gn:asciiname":"Guanzhitun",
    "gn:country_code":"CN",
    "gn:dem":177,
    "gn:feature_class":"P",
    "gn:feature_code":"PPL",
    "gn:name":"Guanzhitun",
    "gn:population":0,
    "gn:timezone":"Asia/Shanghai",
    "iso:country":"CN",
    "name:zho_x_preferred":[
        "\u5173\u5fd7\u5c6f"
    ],
    "wof:name":"Guanzhitun",
    "wof:placetype":"locality"
},
  "geometry": {"coordinates":[125.425,47.27107],"type":"Point"}
}