{
  "type": "Feature",
  "properties": {
    "gn:admin1_code":"4.0",
    "gn:asciiname":"Lifuzhuang",
    "gn:country_code":"CN",
    "gn:dem":9,
    "gn:feature_class":"P",
    "gn:feature_code":"PPL",
    "gn:name":"Lifuzhuang",
    "gn:population":0,
    "gn:timezone":"Asia/Shanghai",
    "iso:country":"CN",
    "name:zho_x_preferred":[
        "\u674e\u5bcc\u5e84"
    ],
    "wof:name":"Lifuzhuang",
    "wof:placetype":"locality"
},
  "geometry": {"coordinates":[118.959,33.0209],"type":"Point"}
}