{
  "type": "Feature",
  "properties": {
    "gn:admin1_code":"29.0",
    "gn:asciiname":"Xiaomuchang",
    "gn:country_code":"CN",
    "gn:dem":2104,
    "gn:feature_class":"P",
    "gn:feature_code":"PPL",
    "gn:name":"Xiaomuchang",
    "gn:population":0,
    "gn:timezone":"Asia/Shanghai",
    "iso:country":"CN",
    "name:zho_x_preferred":[
        "\u5c0f\u6728\u573a"
    ],
    "wof:name":"Xiaomuchang",
    "wof:placetype":"locality"
},
  "geometry": {"coordinates":[102.816,25.3858],"type":"Point"}
}