{
  "type": "Feature",
  "properties": {
    "gn:admin1_code":"4.0",
    "gn:asciiname":"Xisuqiao",
    "gn:country_code":"CN",
    "gn:dem":4,
    "gn:feature_class":"P",
    "gn:feature_code":"PPL",
    "gn:name":"Xisuqiao",
    "gn:population":0,
    "gn:timezone":"Asia/Shanghai",
    "iso:country":"CN",
    "name:und_x_variant":[
        "\u897f\u5bbf\u6865"
    ],
    "wof:name":"Xisuqiao",
    "wof:placetype":"locality"
},
  "geometry": {"coordinates":[120.98293,31.27357],"type":"Point"}
}