{
  "type": "Feature",
  "properties": {
    "gn:admin1_code":"26.0",
    "gn:asciiname":"Yanghegou",
    "gn:country_code":"CN",
    "gn:dem":1138,
    "gn:feature_class":"P",
    "gn:feature_code":"PPL",
    "gn:name":"Yanghegou",
    "gn:population":0,
    "gn:timezone":"Asia/Shanghai",
    "iso:country":"CN",
    "name:zho_x_preferred":[
        "\u9633\u6cb3\u6c9f"
    ],
    "wof:name":"Yanghegou",
    "wof:placetype":"locality"
},
  "geometry": {"coordinates":[108.32007,34.02791],"type":"Point"}
}