{
  "type": "Feature",
  "properties": {
    "gn:admin1_code":"8.0",
    "gn:asciiname":"Ganfanguo",
    "gn:country_code":"CN",
    "gn:dem":213,
    "gn:feature_class":"P",
    "gn:feature_code":"PPL",
    "gn:name":"Ganfanguo",
    "gn:population":0,
    "gn:timezone":"Asia/Shanghai",
    "iso:country":"CN",
    "name:zho_x_preferred":[
        "\u5e72\u996d\u9505"
    ],
    "wof:name":"Ganfanguo",
    "wof:placetype":"locality"
},
  "geometry": {"coordinates":[127.99547,45.42996],"type":"Point"}
}