{
  "type": "Feature",
  "properties": {
    "gn:admin1_code":"1.0",
    "gn:asciiname":"Qidiancun",
    "gn:country_code":"CN",
    "gn:dem":254,
    "gn:feature_class":"P",
    "gn:feature_code":"PPL",
    "gn:name":"Qidiancun",
    "gn:population":0,
    "gn:timezone":"Asia/Shanghai",
    "iso:country":"CN",
    "name:zho_x_preferred":[
        "\u6f06\u5e97\u6751"
    ],
    "wof:name":"Qidiancun",
    "wof:placetype":"locality"
},
  "geometry": {"coordinates":[115.50696000000001,31.32757],"type":"Point"}
}