{
  "type": "Feature",
  "properties": {
    "gn:admin1_code":"08",
    "gn:asciiname":"Dumuhecun",
    "gn:country_code":"CN",
    "gn:dem":74,
    "gn:feature_class":"P",
    "gn:feature_code":"PPL",
    "gn:name":"Dumuhecun",
    "gn:population":0,
    "gn:timezone":"Asia/Shanghai",
    "iso:country":"CN",
    "name:und_x_variant":[
        "Tu-mu-ho",
        "Dumuhe",
        "Dumuhe Linchang",
        "Dumuhecun"
    ],
    "name:zho_x_preferred":[
        "\u72ec\u6728\u6cb3\u6751"
    ],
    "wof:name":"Dumuhecun",
    "wof:placetype":"locality"
},
  "geometry": {"coordinates":[133.55357000000001,46.35797],"type":"Point"}
}