{
  "type": "Feature",
  "properties": {
    "gn:admin1_code":"19.0",
    "gn:asciiname":"Xiaochenjiabu",
    "gn:country_code":"CN",
    "gn:dem":146,
    "gn:feature_class":"P",
    "gn:feature_code":"PPL",
    "gn:name":"Xiaochenjiabu",
    "gn:population":0,
    "gn:timezone":"Asia/Shanghai",
    "iso:country":"CN",
    "name:zho_x_preferred":[
        "\u5c0f\u9648\u5bb6\u5821"
    ],
    "wof:name":"Xiaochenjiabu",
    "wof:placetype":"locality"
},
  "geometry": {"coordinates":[124.449,40.7895],"type":"Point"}
}