{
  "type": "Feature",
  "properties": {
    "gn:admin1_code":"18",
    "gn:asciiname":"Yuhe",
    "gn:country_code":"CN",
    "gn:dem":756,
    "gn:feature_class":"P",
    "gn:feature_code":"PPL",
    "gn:name":"Yuhe",
    "gn:population":0,
    "gn:timezone":"Asia/Shanghai",
    "iso:country":"CN",
    "name:zho_x_preferred":[
        "\u88d5\u6cb3"
    ],
    "wof:name":"Yuhe",
    "wof:placetype":"locality"
},
  "geometry": {"coordinates":[108.892,26.5101],"type":"Point"}
}