{
  "type": "Feature",
  "properties": {
    "gn:admin1_code":"8.0",
    "gn:asciiname":"Qixincun",
    "gn:country_code":"CN",
    "gn:dem":139,
    "gn:feature_class":"P",
    "gn:feature_code":"PPL",
    "gn:name":"Qixincun",
    "gn:population":0,
    "gn:timezone":"Asia/Shanghai",
    "iso:country":"CN",
    "name:zho_x_preferred":[
        "\u9f50\u5fc3\u6751"
    ],
    "wof:name":"Qixincun",
    "wof:placetype":"locality"
},
  "geometry": {"coordinates":[123.63308000000001,46.71665],"type":"Point"}
}