{
  "type": "Feature",
  "properties": {
    "gn:admin1_code":"15.0",
    "gn:asciiname":"Miaoliwan",
    "gn:country_code":"CN",
    "gn:dem":1855,
    "gn:feature_class":"P",
    "gn:feature_code":"PPL",
    "gn:name":"Miaoliwan",
    "gn:population":0,
    "gn:timezone":"Asia/Shanghai",
    "iso:country":"CN",
    "name:zho_x_preferred":[
        "\u5e99\u674e\u6e7e"
    ],
    "wof:name":"Miaoliwan",
    "wof:placetype":"locality"
},
  "geometry": {"coordinates":[104.866,35.8996],"type":"Point"}
}