{
  "type": "Feature",
  "properties": {
    "gn:admin1_code":"32",
    "gn:asciiname":"Macaoshiyan",
    "gn:country_code":"CN",
    "gn:dem":658,
    "gn:feature_class":"P",
    "gn:feature_code":"PPL",
    "gn:name":"Macaoshiyan",
    "gn:population":0,
    "gn:timezone":"Asia/Shanghai",
    "iso:country":"CN",
    "name:zho_x_preferred":[
        "\u9a6c\u69fd\u77f3\u5ca9"
    ],
    "wof:name":"Macaoshiyan",
    "wof:placetype":"locality"
},
  "geometry": {"coordinates":[105.35578,31.91439],"type":"Point"}
}