{
  "type": "Feature",
  "properties": {
    "gn:admin1_code":"32.0",
    "gn:asciiname":"Erhuanggou",
    "gn:country_code":"CN",
    "gn:dem":380,
    "gn:feature_class":"P",
    "gn:feature_code":"PPL",
    "gn:name":"Erhuanggou",
    "gn:population":0,
    "gn:timezone":"Asia/Shanghai",
    "iso:country":"CN",
    "name:zho_x_preferred":[
        "\u4e8c\u9ec4\u6c9f"
    ],
    "wof:name":"Erhuanggou",
    "wof:placetype":"locality"
},
  "geometry": {"coordinates":[105.16500000000001,30.3466],"type":"Point"}
}