{
  "type": "Feature",
  "properties": {
    "gn:admin1_code":"18",
    "gn:asciiname":"Shangyangyong",
    "gn:country_code":"CN",
    "gn:dem":1194,
    "gn:feature_class":"P",
    "gn:feature_code":"PPL",
    "gn:name":"Shangyangyong",
    "gn:population":0,
    "gn:timezone":"Asia/Shanghai",
    "iso:country":"CN",
    "name:zho_x_preferred":[
        "\u4e0a\u7f8a\u62e5"
    ],
    "wof:name":"Shangyangyong",
    "wof:placetype":"locality"
},
  "geometry": {"coordinates":[106.321,25.9462],"type":"Point"}
}