{
  "type": "Feature",
  "properties": {
    "gn:admin1_code":"3.0",
    "gn:asciiname":"Dagangshan",
    "gn:country_code":"CN",
    "gn:dem":237,
    "gn:feature_class":"P",
    "gn:feature_code":"PPLA4",
    "gn:name":"Dagangshan",
    "gn:population":0,
    "gn:timezone":"Asia/Shanghai",
    "iso:country":"CN",
    "name:und_x_variant":[
        "\u5927\u5c97\u5c71",
        "Dagangshan Xiang",
        "\u5927\u5c97\u5c71\u4e61"
    ],
    "wof:name":"Dagangshan",
    "wof:placetype":"locality"
},
  "geometry": {"coordinates":[114.58814,27.6556],"type":"Point"}
}