{
  "type": "Feature",
  "properties": {
    "gn:admin1_code":"32.0",
    "gn:asciiname":"Yuanshi",
    "gn:country_code":"CN",
    "gn:dem":523,
    "gn:feature_class":"P",
    "gn:feature_code":"PPL",
    "gn:name":"Yuanshi",
    "gn:population":0,
    "gn:timezone":"Asia/Shanghai",
    "iso:country":"CN",
    "name:zho_x_preferred":[
        "\u5143\u77f3"
    ],
    "wof:name":"Yuanshi",
    "wof:placetype":"locality"
},
  "geometry": {"coordinates":[104.13392,31.07823],"type":"Point"}
}