{
  "type": "Feature",
  "properties": {
    "gn:admin1_code":"16.0",
    "gn:asciiname":"Xianonglou",
    "gn:country_code":"CN",
    "gn:dem":527,
    "gn:feature_class":"P",
    "gn:feature_code":"PPL",
    "gn:name":"Xianonglou",
    "gn:population":0,
    "gn:timezone":"Asia/Shanghai",
    "iso:country":"CN",
    "name:zho_x_preferred":[
        "\u4e0b\u5f04\u697c"
    ],
    "wof:name":"Xianonglou",
    "wof:placetype":"locality"
},
  "geometry": {"coordinates":[107.892,24.0118],"type":"Point"}
}