{
  "type": "Feature",
  "properties": {
    "gn:admin1_code":"2.0",
    "gn:asciiname":"Changtangtou",
    "gn:country_code":"CN",
    "gn:dem":5,
    "gn:feature_class":"P",
    "gn:feature_code":"PPL",
    "gn:name":"Changtangtou",
    "gn:population":0,
    "gn:timezone":"Asia/Shanghai",
    "iso:country":"CN",
    "name:zho_x_preferred":[
        "\u957f\u5858\u5934"
    ],
    "wof:name":"Changtangtou",
    "wof:placetype":"locality"
},
  "geometry": {"coordinates":[121.50133999999998,28.38853],"type":"Point"}
}