{
  "type": "Feature",
  "properties": {
    "gn:admin1_code":"25",
    "gn:asciiname":"Achengpu",
    "gn:country_code":"CN",
    "gn:dem":39,
    "gn:feature_class":"P",
    "gn:feature_code":"PPL",
    "gn:name":"Achengpu",
    "gn:population":0,
    "gn:timezone":"Asia/Shanghai",
    "iso:country":"CN",
    "name:zho_x_preferred":[
        "\u963f\u57ce\u94fa"
    ],
    "wof:name":"Achengpu",
    "wof:placetype":"locality"
},
  "geometry": {"coordinates":[116.331,35.2444],"type":"Point"}
}