{
  "type": "Feature",
  "properties": {
    "gn:admin1_code":"11",
    "gn:asciiname":"Huangsha",
    "gn:cc2":"CN",
    "gn:country_code":"CN",
    "gn:dem":897,
    "gn:feature_class":"P",
    "gn:feature_code":"PPL",
    "gn:name":"Huangsha",
    "gn:population":0,
    "gn:timezone":"Asia/Shanghai",
    "iso:country":"CN",
    "name:und_x_variant":[
        "Huangshatang",
        "Huangsha"
    ],
    "wof:name":"Huangsha",
    "wof:placetype":"locality"
},
  "geometry": {"coordinates":[110.59667,26.35667],"type":"Point"}
}