{
  "type": "Feature",
  "properties": {
    "gn:admin1_code":"19",
    "gn:asciiname":"Qikou",
    "gn:country_code":"CN",
    "gn:dem":6,
    "gn:feature_class":"P",
    "gn:feature_code":"PPLA4",
    "gn:name":"Qikou",
    "gn:population":0,
    "gn:timezone":"Asia/Shanghai",
    "iso:country":"CN",
    "name:und_x_variant":[
        "Ch\u2019i-k\u2019ou",
        "Lan-ch\u2019i-k\u2019ou-ts\u2019un",
        "Lan-ch\u2019i-p\u2019u",
        "Qikou",
        "\u65d7\u53e3",
        "Qikou Zhen",
        "\u65d7\u53e3\u9547"
    ],
    "wof:name":"Qikou",
    "wof:placetype":"locality"
},
  "geometry": {"coordinates":[122.42337000000001,40.85492],"type":"Point"}
}