{
  "type": "Feature",
  "properties": {
    "gn:admin1_code":"33",
    "gn:asciiname":"Shuangjiang",
    "gn:country_code":"CN",
    "gn:dem":224,
    "gn:feature_class":"P",
    "gn:feature_code":"PPLA3",
    "gn:name":"Shuangjiang",
    "gn:population":0,
    "gn:timezone":"Asia/Shanghai",
    "iso:country":"CN",
    "name:ceb_x_preferred":[
        "Shuangjiang"
    ],
    "name:deu_x_preferred":[
        "Shuangjiang"
    ],
    "name:und_x_variant":[
        "Shuang-chiang",
        "Shuang-chiang-chen",
        "Shuangjiang",
        "Shuangjiang Jiedao",
        "Yunyang Xian"
    ],
    "name:zho_x_preferred":[
        "\u53cc\u6c5f"
    ],
    "name:zho_x_variant":[
        "\u53cc\u6c5f\u8857\u9053",
        "\u4e91\u9633\u53bf"
    ],
    "wof:name":"Shuangjiang",
    "wof:placetype":"locality"
},
  "geometry": {"coordinates":[108.68129,30.9424],"type":"Point"}
}