{
  "type": "Feature",
  "properties": {
    "gn:admin1_code":"18",
    "gn:asciiname":"Zuoqie",
    "gn:country_code":"CN",
    "gn:dem":1049,
    "gn:feature_class":"P",
    "gn:feature_code":"PPL",
    "gn:name":"Zuoqie",
    "gn:population":0,
    "gn:timezone":"Asia/Shanghai",
    "iso:country":"CN",
    "name:zho_x_preferred":[
        "\u5de6\u5207"
    ],
    "wof:name":"Zuoqie",
    "wof:placetype":"locality"
},
  "geometry": {"coordinates":[105.636,25.3967],"type":"Point"}
}