{
  "type": "Feature",
  "properties": {
    "gn:admin1_code":"10.0",
    "gn:asciiname":"Meng'erzhuang",
    "gn:country_code":"CN",
    "gn:dem":173,
    "gn:feature_class":"P",
    "gn:feature_code":"PPL",
    "gn:name":"Meng\u2019erzhuang",
    "gn:population":0,
    "gn:timezone":"Asia/Shanghai",
    "iso:country":"CN",
    "name:und_x_variant":[
        "Meng\u2019erzhuang",
        "\u5b5f\u4e8c\u5e84"
    ],
    "wof:name":"Meng'erzhuang",
    "wof:placetype":"locality"
},
  "geometry": {"coordinates":[114.08580000000001,38.26945],"type":"Point"}
}