{
  "type": "Feature",
  "properties": {
    "gn:admin1_code":"3.0",
    "gn:asciiname":"Taoli Shuxia",
    "gn:country_code":"CN",
    "gn:dem":247,
    "gn:feature_class":"P",
    "gn:feature_code":"PPL",
    "gn:name":"Taoli Shuxia",
    "gn:population":0,
    "gn:timezone":"Asia/Shanghai",
    "iso:country":"CN",
    "name:und_x_variant":[
        "\u6843\u674e\u6811\u4e0b"
    ],
    "wof:name":"Taoli Shuxia",
    "wof:placetype":"locality"
},
  "geometry": {"coordinates":[114.48044,24.96178],"type":"Point"}
}