{
  "type": "Feature",
  "properties": {
    "gn:admin1_code":"25",
    "gn:asciiname":"Zhanggaoce",
    "gn:country_code":"CN",
    "gn:dem":38,
    "gn:feature_class":"P",
    "gn:feature_code":"PPL",
    "gn:name":"Zhanggaoce",
    "gn:population":0,
    "gn:timezone":"Asia/Shanghai",
    "iso:country":"CN",
    "name:zho_x_preferred":[
        "\u5f20\u9ad8\u518c"
    ],
    "wof:name":"Zhanggaoce",
    "wof:placetype":"locality"
},
  "geometry": {"coordinates":[118.264,34.6005],"type":"Point"}
}