{
  "type": "Feature",
  "properties": {
    "gn:admin1_code":"16.0",
    "gn:asciiname":"Jinglan",
    "gn:country_code":"CN",
    "gn:dem":89,
    "gn:feature_class":"P",
    "gn:feature_code":"PPL",
    "gn:name":"Jinglan",
    "gn:population":0,
    "gn:timezone":"Asia/Shanghai",
    "iso:country":"CN",
    "name:zho_x_preferred":[
        "\u9759\u5170"
    ],
    "wof:name":"Jinglan",
    "wof:placetype":"locality"
},
  "geometry": {"coordinates":[109.477,24.3318],"type":"Point"}
}