{
  "type": "Feature",
  "properties": {
    "gn:admin1_code":"7.0",
    "gn:asciiname":"Chengbu",
    "gn:country_code":"CN",
    "gn:dem":316,
    "gn:feature_class":"P",
    "gn:feature_code":"PPL",
    "gn:name":"Chengbu",
    "gn:population":0,
    "gn:timezone":"Asia/Shanghai",
    "iso:country":"CN",
    "name:und_x_variant":[
        "\u7a0b\u8865"
    ],
    "name:zho_x_preferred":[
        "\u7a0b\u8865"
    ],
    "wof:name":"Chengbu",
    "wof:placetype":"locality"
},
  "geometry": {"coordinates":[116.96202,26.29148],"type":"Point"}
}