{
  "type": "Feature",
  "properties": {
    "gn:admin1_code":"18.0",
    "gn:asciiname":"Fengxiangya",
    "gn:country_code":"CN",
    "gn:dem":542,
    "gn:feature_class":"P",
    "gn:feature_code":"PPL",
    "gn:name":"Fengxiangya",
    "gn:population":0,
    "gn:timezone":"Asia/Shanghai",
    "iso:country":"CN",
    "name:zho_x_preferred":[
        "\u67ab\u9999\u57ad"
    ],
    "wof:name":"Fengxiangya",
    "wof:placetype":"locality"
},
  "geometry": {"coordinates":[108.494,28.4381],"type":"Point"}
}