{
  "type": "Feature",
  "properties": {
    "gn:admin1_code":"29.0",
    "gn:asciiname":"Buzhang",
    "gn:country_code":"CN",
    "gn:dem":1313,
    "gn:feature_class":"P",
    "gn:feature_code":"PPL",
    "gn:name":"Buzhang",
    "gn:population":0,
    "gn:timezone":"Asia/Shanghai",
    "iso:country":"CN",
    "name:zho_x_preferred":[
        "\u8865\u638c"
    ],
    "wof:name":"Buzhang",
    "wof:placetype":"locality"
},
  "geometry": {"coordinates":[104.768,25.2291],"type":"Point"}
}