{
  "type": "Feature",
  "properties": {
    "gn:admin1_code":"10.0",
    "gn:asciiname":"Xianggongzhuang",
    "gn:country_code":"CN",
    "gn:dem":47,
    "gn:feature_class":"P",
    "gn:feature_code":"PPL",
    "gn:name":"Xianggongzhuang",
    "gn:population":0,
    "gn:timezone":"Asia/Shanghai",
    "iso:country":"CN",
    "name:zho_x_preferred":[
        "\u76f8\u516c\u5e84"
    ],
    "wof:name":"Xianggongzhuang",
    "wof:placetype":"locality"
},
  "geometry": {"coordinates":[118.31182,39.79683],"type":"Point"}
}