{
  "type": "Feature",
  "properties": {
    "gn:admin1_code":"4.0",
    "gn:asciiname":"Xijiangzhuang",
    "gn:country_code":"CN",
    "gn:dem":3,
    "gn:feature_class":"P",
    "gn:feature_code":"PPL",
    "gn:name":"Xijiangzhuang",
    "gn:population":0,
    "gn:timezone":"Asia/Shanghai",
    "iso:country":"CN",
    "name:zho_x_preferred":[
        "\u897f\u848b\u5e84"
    ],
    "wof:name":"Xijiangzhuang",
    "wof:placetype":"locality"
},
  "geometry": {"coordinates":[119.68886000000001,32.99968],"type":"Point"}
}