{
  "type": "Feature",
  "properties": {
    "gn:admin1_code":"04",
    "gn:asciiname":"Wushan",
    "gn:country_code":"CN",
    "gn:dem":5,
    "gn:feature_class":"P",
    "gn:feature_code":"PPL",
    "gn:name":"Wushan",
    "gn:population":0,
    "gn:timezone":"Asia/Shanghai",
    "iso:country":"CN",
    "name:ceb_x_preferred":[
        "Wushan"
    ],
    "name:deu_x_preferred":[
        "Wushan"
    ],
    "name:fra_x_preferred":[
        "Wushan"
    ],
    "name:kor_x_preferred":[
        "\uc6b0\uc0b0\ud604"
    ],
    "name:nor_x_preferred":[
        "Wushan"
    ],
    "name:swe_x_preferred":[
        "Wushan"
    ],
    "name:und_x_variant":[
        "Wushantou"
    ],
    "name:zho_x_preferred":[
        "\u5434\u5c71"
    ],
    "wof:name":"Wushan",
    "wof:placetype":"locality"
},
  "geometry": {"coordinates":[120.57812,31.21753],"type":"Point"}
}