{
  "type": "Feature",
  "properties": {
    "gn:admin1_code":"5.0",
    "gn:asciiname":"Chajiancun",
    "gn:country_code":"CN",
    "gn:dem":334,
    "gn:feature_class":"P",
    "gn:feature_code":"PPL",
    "gn:name":"Chajiancun",
    "gn:population":0,
    "gn:timezone":"Asia/Shanghai",
    "iso:country":"CN",
    "name:zho_x_preferred":[
        "\u8336\u5c16\u6751"
    ],
    "wof:name":"Chajiancun",
    "wof:placetype":"locality"
},
  "geometry": {"coordinates":[126.35214999999999,42.8413],"type":"Point"}
}