{
  "type": "Feature",
  "properties": {
    "gn:admin1_code":"32.0",
    "gn:asciiname":"Shuiqiao",
    "gn:country_code":"CN",
    "gn:dem":3737,
    "gn:feature_class":"P",
    "gn:feature_code":"PPL",
    "gn:name":"Shuiqiao",
    "gn:population":0,
    "gn:timezone":"Asia/Shanghai",
    "iso:country":"CN",
    "name:zho_x_preferred":[
        "\u6c34\u6865"
    ],
    "wof:name":"Shuiqiao",
    "wof:placetype":"locality"
},
  "geometry": {"coordinates":[101.694,30.0943],"type":"Point"}
}