{
  "type": "Feature",
  "properties": {
    "gn:admin1_code":"32",
    "gn:asciiname":"Baohe",
    "gn:country_code":"CN",
    "gn:dem":369,
    "gn:feature_class":"P",
    "gn:feature_code":"PPL",
    "gn:name":"Baohe",
    "gn:population":0,
    "gn:timezone":"Asia/Shanghai",
    "iso:country":"CN",
    "name:und_x_variant":[
        "Pao-ho",
        "Baohe"
    ],
    "name:zho_x_preferred":[
        "\u4fdd\u548c"
    ],
    "wof:name":"Baohe",
    "wof:placetype":"locality"
},
  "geometry": {"coordinates":[104.75122,30.20201],"type":"Point"}
}