{
  "type": "Feature",
  "properties": {
    "gn:admin1_code":"15.0",
    "gn:asciiname":"Mijiaxia",
    "gn:country_code":"CN",
    "gn:dem":1959,
    "gn:feature_class":"P",
    "gn:feature_code":"PPL",
    "gn:name":"Mijiaxia",
    "gn:population":0,
    "gn:timezone":"Asia/Shanghai",
    "iso:country":"CN",
    "name:und_x_variant":[
        "\u7c73\u5bb6\u5ce1"
    ],
    "wof:name":"Mijiaxia",
    "wof:placetype":"locality"
},
  "geometry": {"coordinates":[105.07758,35.46869],"type":"Point"}
}