{
  "type": "Feature",
  "properties": {
    "gn:admin1_code":"1.0",
    "gn:asciiname":"Jiaocun",
    "gn:country_code":"CN",
    "gn:dem":139,
    "gn:feature_class":"P",
    "gn:feature_code":"PPL",
    "gn:name":"Jiaocun",
    "gn:population":0,
    "gn:timezone":"Asia/Shanghai",
    "iso:country":"CN",
    "name:und_x_variant":[
        "\u7126\u6751"
    ],
    "wof:name":"Jiaocun",
    "wof:placetype":"locality"
},
  "geometry": {"coordinates":[119.27961000000001,30.64854],"type":"Point"}
}