{
  "type": "Feature",
  "properties": {
    "gn:admin1_code":"29.0",
    "gn:asciiname":"Hedi",
    "gn:country_code":"CN",
    "gn:dem":2305,
    "gn:feature_class":"P",
    "gn:feature_code":"PPL",
    "gn:name":"Hedi",
    "gn:population":0,
    "gn:timezone":"Asia/Shanghai",
    "iso:country":"CN",
    "name:zho_x_preferred":[
        "\u6cb3\u5e95"
    ],
    "wof:name":"Hedi",
    "wof:placetype":"locality"
},
  "geometry": {"coordinates":[101.301,25.3734],"type":"Point"}
}