{
  "type": "Feature",
  "properties": {
    "gn:admin1_code":"29.0",
    "gn:asciiname":"Yuwei",
    "gn:country_code":"CN",
    "gn:dem":2639,
    "gn:feature_class":"P",
    "gn:feature_code":"PPL",
    "gn:name":"Yuwei",
    "gn:population":0,
    "gn:timezone":"Asia/Shanghai",
    "iso:country":"CN",
    "name:zho_x_preferred":[
        "\u9c7c\u5473"
    ],
    "wof:name":"Yuwei",
    "wof:placetype":"locality"
},
  "geometry": {"coordinates":[102.907,25.6557],"type":"Point"}
}