{
  "type": "Feature",
  "properties": {
    "gn:admin1_code":"8.0",
    "gn:asciiname":"Shengbeicun",
    "gn:country_code":"CN",
    "gn:dem":194,
    "gn:feature_class":"P",
    "gn:feature_code":"PPL",
    "gn:name":"Shengbeicun",
    "gn:population":0,
    "gn:timezone":"Asia/Shanghai",
    "iso:country":"CN",
    "name:zho_x_preferred":[
        "\u80dc\u5317\u6751"
    ],
    "wof:name":"Shengbeicun",
    "wof:placetype":"locality"
},
  "geometry": {"coordinates":[127.36202,46.59795],"type":"Point"}
}