{
  "type": "Feature",
  "properties": {
    "gn:admin1_code":"8.0",
    "gn:asciiname":"Baopingcun",
    "gn:country_code":"CN",
    "gn:dem":105,
    "gn:feature_class":"P",
    "gn:feature_code":"PPL",
    "gn:name":"Baopingcun",
    "gn:population":0,
    "gn:timezone":"Asia/Shanghai",
    "iso:country":"CN",
    "name:zho_x_preferred":[
        "\u4fdd\u5e73\u6751"
    ],
    "wof:name":"Baopingcun",
    "wof:placetype":"locality"
},
  "geometry": {"coordinates":[129.47201999999999,46.27355],"type":"Point"}
}