{
  "type": "Feature",
  "properties": {
    "gn:admin1_code":"2",
    "gn:asciiname":"Shanji",
    "gn:country_code":"CN",
    "gn:dem":653,
    "gn:feature_class":"P",
    "gn:feature_code":"PPL",
    "gn:name":"Shanji",
    "gn:population":0,
    "gn:timezone":"Asia/Shanghai",
    "iso:country":"CN",
    "name:und_x_variant":[
        "\u5c71\u9645"
    ],
    "wof:name":"Shanji",
    "wof:placetype":"locality"
},
  "geometry": {"coordinates":[119.21028,27.97889],"type":"Point"}
}