{
  "type": "Feature",
  "properties": {
    "gn:admin1_code":"31",
    "gn:asciiname":"Nandan",
    "gn:country_code":"CN",
    "gn:dem":72,
    "gn:feature_class":"P",
    "gn:feature_code":"PPL",
    "gn:name":"Nandan",
    "gn:population":0,
    "gn:timezone":"Asia/Shanghai",
    "iso:country":"CN",
    "name:und_x_variant":[
        "\u5357\u65e6"
    ],
    "wof:name":"Nandan",
    "wof:placetype":"locality"
},
  "geometry": {"coordinates":[109.88200000000001,18.6018],"type":"Point"}
}