{
  "type": "Feature",
  "properties": {
    "gn:admin1_code":"29.0",
    "gn:asciiname":"Changfangzi",
    "gn:country_code":"CN",
    "gn:dem":924,
    "gn:feature_class":"P",
    "gn:feature_code":"PPL",
    "gn:name":"Changfangzi",
    "gn:population":0,
    "gn:timezone":"Asia/Shanghai",
    "iso:country":"CN",
    "name:zho_x_preferred":[
        "\u957f\u623f\u5b50"
    ],
    "wof:name":"Changfangzi",
    "wof:placetype":"locality"
},
  "geometry": {"coordinates":[104.02200000000001,27.5788],"type":"Point"}
}