{
  "type": "Feature",
  "properties": {
    "gn:admin1_code":"18.0",
    "gn:asciiname":"Ganba",
    "gn:country_code":"CN",
    "gn:dem":869,
    "gn:feature_class":"P",
    "gn:feature_code":"PPL",
    "gn:name":"Ganba",
    "gn:population":0,
    "gn:timezone":"Asia/Shanghai",
    "iso:country":"CN",
    "name:zho_x_preferred":[
        "\u5e72\u575d"
    ],
    "wof:name":"Ganba",
    "wof:placetype":"locality"
},
  "geometry": {"coordinates":[107.483,26.0668],"type":"Point"}
}