{
  "type": "Feature",
  "properties": {
    "gn:admin1_code":"3.0",
    "gn:asciiname":"Yingjiazui",
    "gn:country_code":"CN",
    "gn:dem":24,
    "gn:feature_class":"P",
    "gn:feature_code":"PPL",
    "gn:name":"Yingjiazui",
    "gn:population":0,
    "gn:timezone":"Asia/Shanghai",
    "iso:country":"CN",
    "name:und_x_variant":[
        "\u82f1\u5bb6\u5480"
    ],
    "wof:name":"Yingjiazui",
    "wof:placetype":"locality"
},
  "geometry": {"coordinates":[115.92487,28.33937],"type":"Point"}
}