{
  "type": "Feature",
  "properties": {
    "gn:admin1_code":"30.0",
    "gn:asciiname":"Caodong",
    "gn:country_code":"CN",
    "gn:dem":606,
    "gn:feature_class":"P",
    "gn:feature_code":"PPL",
    "gn:name":"Caodong",
    "gn:population":0,
    "gn:timezone":"Asia/Shanghai",
    "iso:country":"CN",
    "name:zho_x_preferred":[
        "Caodong"
    ],
    "name:zho_x_variant":[
        "\u66f9\u6d1e"
    ],
    "wof:name":"Caodong",
    "wof:placetype":"locality"
},
  "geometry": {"coordinates":[114.49336,24.47986],"type":"Point"}
}