{
  "type": "Feature",
  "properties": {
    "gn:admin1_code":"11",
    "gn:asciiname":"Jiufengshan",
    "gn:country_code":"CN",
    "gn:dem":820,
    "gn:feature_class":"P",
    "gn:feature_code":"PPL",
    "gn:name":"Jiufengshan",
    "gn:population":0,
    "gn:timezone":"Asia/Shanghai",
    "iso:country":"CN",
    "name:und_x_variant":[
        "\u4e5d\u5cf0\u5c71",
        "Jiufengshan"
    ],
    "wof:name":"Jiufengshan",
    "wof:placetype":"locality"
},
  "geometry": {"coordinates":[111.85193999999998,25.36583],"type":"Point"}
}