{
  "type": "Feature",
  "properties": {
    "gn:admin1_code":"19.0",
    "gn:asciiname":"Liuxiaochuan",
    "gn:country_code":"CN",
    "gn:dem":70,
    "gn:feature_class":"P",
    "gn:feature_code":"PPL",
    "gn:name":"Liuxiaochuan",
    "gn:population":0,
    "gn:timezone":"Asia/Shanghai",
    "iso:country":"CN",
    "name:und_x_variant":[
        "\u5218\u5c0f\u8239"
    ],
    "name:zho_x_preferred":[
        "\u5218\u5c0f\u8239"
    ],
    "wof:name":"Liuxiaochuan",
    "wof:placetype":"locality"
},
  "geometry": {"coordinates":[123.65745,42.58402],"type":"Point"}
}