{
  "type": "Feature",
  "properties": {
    "gn:admin1_code":"26.0",
    "gn:asciiname":"Fenyuanzuicun",
    "gn:country_code":"CN",
    "gn:dem":1618,
    "gn:feature_class":"P",
    "gn:feature_code":"PPL",
    "gn:name":"Fenyuanzuicun",
    "gn:population":0,
    "gn:timezone":"Asia/Shanghai",
    "iso:country":"CN",
    "name:zho_x_preferred":[
        "\u575f\u56ed\u5480\u6751"
    ],
    "wof:name":"Fenyuanzuicun",
    "wof:placetype":"locality"
},
  "geometry": {"coordinates":[108.57722,36.77151],"type":"Point"}
}