{
  "type": "Feature",
  "properties": {
    "gn:admin1_code":"32.0",
    "gn:asciiname":"Shaozhiba",
    "gn:country_code":"CN",
    "gn:dem":324,
    "gn:feature_class":"P",
    "gn:feature_code":"PPL",
    "gn:name":"Shaozhiba",
    "gn:population":0,
    "gn:timezone":"Asia/Shanghai",
    "iso:country":"CN",
    "name:zho_x_preferred":[
        "\u70e7\u7eb8\u575d"
    ],
    "wof:name":"Shaozhiba",
    "wof:placetype":"locality"
},
  "geometry": {"coordinates":[105.45292999999999,28.67982],"type":"Point"}
}