{
  "type": "Feature",
  "properties": {
    "gn:admin1_code":"12.0",
    "gn:asciiname":"Xiajiabutou",
    "gn:country_code":"CN",
    "gn:dem":30,
    "gn:feature_class":"P",
    "gn:feature_code":"PPL",
    "gn:name":"Xiajiabutou",
    "gn:population":0,
    "gn:timezone":"Asia/Shanghai",
    "iso:country":"CN",
    "name:zho_x_preferred":[
        "\u590f\u5bb6\u57e0\u5934"
    ],
    "wof:name":"Xiajiabutou",
    "wof:placetype":"locality"
},
  "geometry": {"coordinates":[113.22709999999999,30.37784000000001],"type":"Point"}
}