{
  "type": "Feature",
  "properties": {
    "gn:admin1_code":"26",
    "gn:asciiname":"Huangfuzhuang",
    "gn:cc2":"CN",
    "gn:country_code":"CN",
    "gn:dem":971,
    "gn:feature_class":"P",
    "gn:feature_code":"PPL",
    "gn:name":"Huangfuzhuang",
    "gn:population":0,
    "gn:timezone":"Asia/Shanghai",
    "iso:country":"CN",
    "name:und_x_variant":[
        "Huang-fu-chuang",
        "Huangfuzhuang"
    ],
    "wof:name":"Huangfuzhuang",
    "wof:placetype":"locality"
},
  "geometry": {"coordinates":[110.00444,35.41917],"type":"Point"}
}