{
  "type": "Feature",
  "properties": {
    "gn:admin1_code":"29.0",
    "gn:asciiname":"Muyong",
    "gn:country_code":"CN",
    "gn:dem":2830,
    "gn:feature_class":"P",
    "gn:feature_code":"PPL",
    "gn:name":"Muyong",
    "gn:population":0,
    "gn:timezone":"Asia/Shanghai",
    "iso:country":"CN",
    "name:zho_x_preferred":[
        "\u76ee\u7528"
    ],
    "wof:name":"Muyong",
    "wof:placetype":"locality"
},
  "geometry": {"coordinates":[99.2097,28.312],"type":"Point"}
}