{
  "type": "Feature",
  "properties": {
    "gn:admin1_code":"19",
    "gn:asciiname":"Kulongshan",
    "gn:country_code":"CN",
    "gn:dem":357,
    "gn:feature_class":"P",
    "gn:feature_code":"PPL",
    "gn:name":"Kulongshan",
    "gn:population":0,
    "gn:timezone":"Asia/Shanghai",
    "iso:country":"CN",
    "name:zho_x_preferred":[
        "\u7a9f\u7abf\u5c71"
    ],
    "wof:name":"Kulongshan",
    "wof:placetype":"locality"
},
  "geometry": {"coordinates":[121.589,41.5991],"type":"Point"}
}