{
  "type": "Feature",
  "properties": {
    "gn:admin1_code":"29.0",
    "gn:asciiname":"Qingshuigou",
    "gn:country_code":"CN",
    "gn:dem":1880,
    "gn:feature_class":"P",
    "gn:feature_code":"PPL",
    "gn:name":"Qingshuigou",
    "gn:population":0,
    "gn:timezone":"Asia/Shanghai",
    "iso:country":"CN",
    "name:zho_x_preferred":[
        "\u6e05\u6c34\u6c9f"
    ],
    "wof:name":"Qingshuigou",
    "wof:placetype":"locality"
},
  "geometry": {"coordinates":[103.005,23.2972],"type":"Point"}
}