{
  "type": "Feature",
  "properties": {
    "gn:admin1_code":"9.0",
    "gn:asciiname":"Yugou",
    "gn:country_code":"CN",
    "gn:dem":161,
    "gn:feature_class":"P",
    "gn:feature_code":"PPL",
    "gn:name":"Yugou",
    "gn:population":0,
    "gn:timezone":"Asia/Shanghai",
    "iso:country":"CN",
    "name:und_x_variant":[
        "\u4e8e\u6c9f",
        "Yugou"
    ],
    "wof:name":"Yugou",
    "wof:placetype":"locality"
},
  "geometry": {"coordinates":[112.47353,33.08143],"type":"Point"}
}