{
  "type": "Feature",
  "properties": {
    "gn:admin1_code":"31.0",
    "gn:asciiname":"Guantangkou",
    "gn:country_code":"CN",
    "gn:dem":82,
    "gn:feature_class":"P",
    "gn:feature_code":"PPL",
    "gn:name":"Guantangkou",
    "gn:population":0,
    "gn:timezone":"Asia/Shanghai",
    "iso:country":"CN",
    "name:zho_x_preferred":[
        "\u5b98\u5858\u53e3"
    ],
    "wof:name":"Guantangkou",
    "wof:placetype":"locality"
},
  "geometry": {"coordinates":[110.60952,19.54418],"type":"Point"}
}