{
  "type": "Feature",
  "properties": {
    "gn:admin1_code":"26",
    "gn:asciiname":"Chaiping",
    "gn:cc2":"CN",
    "gn:country_code":"CN",
    "gn:dem":670,
    "gn:feature_class":"P",
    "gn:feature_code":"PPL",
    "gn:name":"Chaiping",
    "gn:population":0,
    "gn:timezone":"Asia/Shanghai",
    "iso:country":"CN",
    "name:und_x_variant":[
        "Chaijiaping",
        "Ch\u2019ai-chia-chen",
        "Ch\u2019ai-chia-p\u2019ing",
        "Chaiping"
    ],
    "wof:name":"Chaiping",
    "wof:placetype":"locality"
},
  "geometry": {"coordinates":[108.95944,33.30361],"type":"Point"}
}