{
  "type": "Feature",
  "properties": {
    "gn:admin1_code":"11.0",
    "gn:asciiname":"Caijiadi",
    "gn:country_code":"CN",
    "gn:dem":29,
    "gn:feature_class":"P",
    "gn:feature_code":"PPL",
    "gn:name":"Caijiadi",
    "gn:population":0,
    "gn:timezone":"Asia/Shanghai",
    "iso:country":"CN",
    "name:zho_x_preferred":[
        "Caijiadi"
    ],
    "name:zho_x_variant":[
        "\u8521\u5bb6\u5824"
    ],
    "wof:name":"Caijiadi",
    "wof:placetype":"locality"
},
  "geometry": {"coordinates":[111.96304000000001,29.04232],"type":"Point"}
}