{
  "type": "Feature",
  "properties": {
    "gn:country":"CN",
    "gn:fcode":"PPLA4",
    "gn:pop":3914,
    "iso:country":"CN",
    "name:eng_x_preferred":[
        "Shuanggang"
    ],
    "name:gan_x_preferred":[
        "\u53cc\u6e2f\u9547"
    ],
    "name:jpn_x_preferred":[
        "\u53cc\u6e2f\u93ae"
    ],
    "name:unk_x_variant":[
        "Shuang-lin"
    ],
    "name:wuu_x_preferred":[
        "\u53cc\u6e2f\u9547"
    ],
    "name:zho_x_preferred":[
        "\u53cc\u6e2f"
    ],
    "name:zho_x_variant":[
        "\u53cc\u6e2f\u9547"
    ],
    "qs:name":"Shuanggang",
    "qs:photos_9r":0,
    "qs:photos_sr":0,
    "qs:pop_sr":"4",
    "wd:wordcount":76,
    "wof:name":"Shuanggang",
    "wof:placetype":"locality",
    "wof:population":3914
},
  "geometry": {"coordinates":[117.31014,39.04396],"type":"Point"}
}