{
  "type": "Feature",
  "properties": {
    "gn:admin1_code":"30.0",
    "gn:asciiname":"Shuishan",
    "gn:country_code":"CN",
    "gn:dem":651,
    "gn:feature_class":"P",
    "gn:feature_code":"PPL",
    "gn:name":"Shuishan",
    "gn:population":0,
    "gn:timezone":"Asia/Shanghai",
    "iso:country":"CN",
    "name:zho_x_preferred":[
        "Shuishan"
    ],
    "name:zho_x_variant":[
        "\u6c34\u5c71"
    ],
    "wof:name":"Shuishan",
    "wof:placetype":"locality"
},
  "geometry": {"coordinates":[112.85805999999999,24.5775],"type":"Point"}
}