{
  "type": "Feature",
  "properties": {
    "gn:admin1_code":"29.0",
    "gn:asciiname":"Wanmin",
    "gn:country_code":"CN",
    "gn:dem":2107,
    "gn:feature_class":"P",
    "gn:feature_code":"PPL",
    "gn:name":"Wanmin",
    "gn:population":0,
    "gn:timezone":"Asia/Shanghai",
    "iso:country":"CN",
    "name:swe_x_preferred":[
        "Wanmin Xiang"
    ],
    "name:und_x_variant":[
        "\u4e07\u6c11"
    ],
    "name:zho_x_preferred":[
        "\u4e07\u6c11\u4e61"
    ],
    "wof:name":"Wanmin",
    "wof:placetype":"locality"
},
  "geometry": {"coordinates":[102.7683,25.72672],"type":"Point"}
}