{
  "type": "Feature",
  "properties": {
    "gn:admin1_code":"13.0",
    "gn:asciiname":"Aji Aigele",
    "gn:country_code":"CN",
    "gn:dem":1278,
    "gn:feature_class":"P",
    "gn:feature_code":"PPL",
    "gn:name":"Aji Aigele",
    "gn:population":0,
    "gn:timezone":"Asia/Shanghai",
    "iso:country":"CN",
    "name:zho_x_preferred":[
        "\u963f\u5409\u827e\u683c\u52d2"
    ],
    "wof:name":"Aji Aigele",
    "wof:placetype":"locality"
},
  "geometry": {"coordinates":[80.0314,37.61192],"type":"Point"}
}