{
  "type": "Feature",
  "properties": {
    "gn:admin1_code":"33.0",
    "gn:asciiname":"Guandiantuo",
    "gn:country_code":"CN",
    "gn:dem":933,
    "gn:feature_class":"P",
    "gn:feature_code":"PPL",
    "gn:name":"Guandiantuo",
    "gn:population":0,
    "gn:timezone":"Asia/Shanghai",
    "iso:country":"CN",
    "name:zho_x_preferred":[
        "\u89c2\u6bbf\u5768"
    ],
    "wof:name":"Guandiantuo",
    "wof:placetype":"locality"
},
  "geometry": {"coordinates":[108.51272,28.86789000000001],"type":"Point"}
}