{
  "type": "Feature",
  "properties": {
    "gn:admin1_code":"8.0",
    "gn:asciiname":"Laolongbozi",
    "gn:country_code":"CN",
    "gn:dem":208,
    "gn:feature_class":"P",
    "gn:feature_code":"PPL",
    "gn:name":"Laolongbozi",
    "gn:population":0,
    "gn:timezone":"Asia/Shanghai",
    "iso:country":"CN",
    "name:zho_x_preferred":[
        "\u8001\u9f99\u8116\u5b50"
    ],
    "wof:name":"Laolongbozi",
    "wof:placetype":"locality"
},
  "geometry": {"coordinates":[127.22451,44.82487],"type":"Point"}
}