{
  "type": "Feature",
  "properties": {
    "gn:admin1_code":"29.0",
    "gn:asciiname":"Zhongchang",
    "gn:country_code":"CN",
    "gn:dem":2029,
    "gn:feature_class":"P",
    "gn:feature_code":"PPL",
    "gn:name":"Zhongchang",
    "gn:population":0,
    "gn:timezone":"Asia/Shanghai",
    "iso:country":"CN",
    "name:zho_x_preferred":[
        "\u4e2d\u5382"
    ],
    "wof:name":"Zhongchang",
    "wof:placetype":"locality"
},
  "geometry": {"coordinates":[103.875,27.437],"type":"Point"}
}