{
  "type": "Feature",
  "properties": {
    "gn:admin1_code":"24.0",
    "gn:asciiname":"Yindehecun",
    "gn:country_code":"CN",
    "gn:dem":535,
    "gn:feature_class":"P",
    "gn:feature_code":"PPL",
    "gn:name":"Yindehecun",
    "gn:population":0,
    "gn:timezone":"Asia/Shanghai",
    "iso:country":"CN",
    "name:zho_x_preferred":[
        "\u9634\u5fb7\u6cb3\u6751"
    ],
    "wof:name":"Yindehecun",
    "wof:placetype":"locality"
},
  "geometry": {"coordinates":[110.43291000000001,36.69726],"type":"Point"}
}