{
  "type": "Feature",
  "properties": {
    "gn:admin1_code":"25",
    "gn:asciiname":"Xitaohua",
    "gn:country_code":"CN",
    "gn:dem":208,
    "gn:feature_class":"P",
    "gn:feature_code":"PPL",
    "gn:name":"Xitaohua",
    "gn:population":0,
    "gn:timezone":"Asia/Shanghai",
    "iso:country":"CN",
    "name:zho_x_preferred":[
        "\u897f\u6843\u82b1"
    ],
    "wof:name":"Xitaohua",
    "wof:placetype":"locality"
},
  "geometry": {"coordinates":[118.67700000000001,36.4679],"type":"Point"}
}