{
  "type": "Feature",
  "properties": {
    "gn:admin1_code":"30.0",
    "gn:asciiname":"Xiamenshui",
    "gn:country_code":"CN",
    "gn:dem":135,
    "gn:feature_class":"P",
    "gn:feature_code":"PPL",
    "gn:name":"Xiamenshui",
    "gn:population":0,
    "gn:timezone":"Asia/Shanghai",
    "iso:country":"CN",
    "name:zho_x_preferred":[
        "Xiamenshui"
    ],
    "name:zho_x_variant":[
        "\u4e0b\u95e8\u6c34"
    ],
    "wof:name":"Xiamenshui",
    "wof:placetype":"locality"
},
  "geometry": {"coordinates":[112.33360999999999,24.87111],"type":"Point"}
}