{
  "type": "Feature",
  "properties": {
    "gn:admin1_code":"32.0",
    "gn:asciiname":"Yao'erba",
    "gn:country_code":"CN",
    "gn:dem":1335,
    "gn:feature_class":"P",
    "gn:feature_code":"PPL",
    "gn:name":"Yao\u2019erba",
    "gn:population":0,
    "gn:timezone":"Asia/Shanghai",
    "iso:country":"CN",
    "name:zho_x_preferred":[
        "\u4e48\u5152\u575d"
    ],
    "name:zho_x_variant":[
        "Yao\u2019erba"
    ],
    "wof:name":"Yao'erba",
    "wof:placetype":"locality"
},
  "geometry": {"coordinates":[104.24093999999999,32.38979],"type":"Point"}
}