{
  "type": "Feature",
  "properties": {
    "gn:admin1_code":"30",
    "gn:asciiname":"Laodongkeng",
    "gn:country_code":"CN",
    "gn:dem":34,
    "gn:feature_class":"P",
    "gn:feature_code":"PPL",
    "gn:name":"Laodongkeng",
    "gn:population":0,
    "gn:timezone":"Asia/Shanghai",
    "iso:country":"CN",
    "name:zho_x_preferred":[
        "\u8001\u4e1c\u5751"
    ],
    "wof:name":"Laodongkeng",
    "wof:placetype":"locality"
},
  "geometry": {"coordinates":[116.21463,23.38638],"type":"Point"}
}