{
  "type": "Feature",
  "properties": {
    "gn:admin1_code":"23.0",
    "gn:asciiname":"Xinmixing",
    "gn:country_code":"CN",
    "gn:dem":2,
    "gn:feature_class":"P",
    "gn:feature_code":"PPL",
    "gn:name":"Xinmixing",
    "gn:population":0,
    "gn:timezone":"Asia/Shanghai",
    "iso:country":"CN",
    "name:zho_x_preferred":[
        "Xinmixing"
    ],
    "name:zho_x_variant":[
        "\u65b0\u7c73\u884c"
    ],
    "wof:name":"Xinmixing",
    "wof:placetype":"locality"
},
  "geometry": {"coordinates":[121.72117,31.55771],"type":"Point"}
}