{
  "type": "Feature",
  "properties": {
    "gn:admin1_code":"19.0",
    "gn:asciiname":"Shuishou",
    "gn:country_code":"CN",
    "gn:dem":237,
    "gn:feature_class":"P",
    "gn:feature_code":"PPL",
    "gn:name":"Shuishou",
    "gn:population":0,
    "gn:timezone":"Asia/Shanghai",
    "iso:country":"CN",
    "name:und_x_variant":[
        "\u6c34\u624b"
    ],
    "name:zho_x_preferred":[
        "\u6c34\u624b"
    ],
    "wof:name":"Shuishou",
    "wof:placetype":"locality"
},
  "geometry": {"coordinates":[124.60144,41.7893],"type":"Point"}
}