{
  "type": "Feature",
  "properties": {
    "gn:admin1_code":"9.0",
    "gn:asciiname":"Nano'ao",
    "gn:country_code":"CN",
    "gn:dem":962,
    "gn:feature_class":"P",
    "gn:feature_code":"PPL",
    "gn:name":"Nano\u2019ao",
    "gn:population":0,
    "gn:timezone":"Asia/Shanghai",
    "iso:country":"CN",
    "name:und_x_variant":[
        "Nano\u2019ao"
    ],
    "name:zho_x_preferred":[
        "\u5357\u51f9"
    ],
    "wof:name":"Nano'ao",
    "wof:placetype":"locality"
},
  "geometry": {"coordinates":[111.07229,34.42991],"type":"Point"}
}