{
  "type": "Feature",
  "properties": {
    "gn:admin1_code":"32.0",
    "gn:asciiname":"Haopanhe",
    "gn:country_code":"CN",
    "gn:dem":913,
    "gn:feature_class":"P",
    "gn:feature_code":"PPL",
    "gn:name":"Haopanhe",
    "gn:population":0,
    "gn:timezone":"Asia/Shanghai",
    "iso:country":"CN",
    "name:zho_x_preferred":[
        "\u8585\u76d8\u6cb3"
    ],
    "wof:name":"Haopanhe",
    "wof:placetype":"locality"
},
  "geometry": {"coordinates":[104.69326,32.14026],"type":"Point"}
}