{
  "type": "Feature",
  "properties": {
    "gn:admin1_code":"14.0",
    "gn:asciiname":"Baijiucun",
    "gn:country_code":"CN",
    "gn:dem":3380,
    "gn:feature_class":"P",
    "gn:feature_code":"PPL",
    "gn:name":"Baijiucun",
    "gn:population":0,
    "gn:timezone":"Asia/Urumqi",
    "iso:country":"CN",
    "name:zho_x_preferred":[
        "\u767d\u4e45\u6751"
    ],
    "wof:name":"Baijiucun",
    "wof:placetype":"locality"
},
  "geometry": {"coordinates":[97.51597,30.73686],"type":"Point"}
}