{
  "type": "Feature",
  "properties": {
    "gn:admin1_code":"11",
    "gn:asciiname":"Leijiapo",
    "gn:country_code":"CN",
    "gn:dem":466,
    "gn:feature_class":"P",
    "gn:feature_code":"PPL",
    "gn:name":"Leijiapo",
    "gn:population":0,
    "gn:timezone":"Asia/Shanghai",
    "iso:country":"CN",
    "name:zho_x_preferred":[
        "\u96f7\u5bb6\u5761"
    ],
    "wof:name":"Leijiapo",
    "wof:placetype":"locality"
},
  "geometry": {"coordinates":[110.27679000000001,27.79933],"type":"Point"}
}