{
  "type": "Feature",
  "properties": {
    "gn:admin1_code":"26.0",
    "gn:asciiname":"Zhuniu",
    "gn:cc2":"CN",
    "gn:country_code":"CN",
    "gn:dem":841,
    "gn:feature_class":"P",
    "gn:feature_code":"PPL",
    "gn:name":"Zhuniu",
    "gn:population":0,
    "gn:timezone":"Asia/Shanghai",
    "iso:country":"CN",
    "name:und_x_variant":[
        "Chu-niu",
        "Chu-lung-chen",
        "Zhuniu"
    ],
    "wof:name":"Zhuniu",
    "wof:placetype":"locality"
},
  "geometry": {"coordinates":[109.52167,35.42333],"type":"Point"}
}