{
  "type": "Feature",
  "properties": {
    "gn:admin1_code":"25",
    "gn:asciiname":"Peijialing",
    "gn:country_code":"CN",
    "gn:dem":13,
    "gn:feature_class":"P",
    "gn:feature_code":"PPL",
    "gn:name":"Peijialing",
    "gn:population":0,
    "gn:timezone":"Asia/Shanghai",
    "iso:country":"CN",
    "name:zho_x_preferred":[
        "\u88f4\u5bb6\u5cad"
    ],
    "wof:name":"Peijialing",
    "wof:placetype":"locality"
},
  "geometry": {"coordinates":[118.554,36.9886],"type":"Point"}
}