{
  "type": "Feature",
  "properties": {
    "gn:admin1_code":"7.0",
    "gn:asciiname":"Liuchuan",
    "gn:country_code":"CN",
    "gn:dem":4,
    "gn:feature_class":"P",
    "gn:feature_code":"PPL",
    "gn:name":"Liuchuan",
    "gn:population":0,
    "gn:timezone":"Asia/Shanghai",
    "iso:country":"CN",
    "name:zho_x_preferred":[
        "\u6d41\u4f20"
    ],
    "wof:name":"Liuchuan",
    "wof:placetype":"locality"
},
  "geometry": {"coordinates":[117.83632,24.48652],"type":"Point"}
}