{
  "type": "Feature",
  "properties": {
    "gn:admin1_code":"1.0",
    "gn:asciiname":"Chengxicun",
    "gn:country_code":"CN",
    "gn:dem":15,
    "gn:feature_class":"P",
    "gn:feature_code":"PPL",
    "gn:name":"Chengxicun",
    "gn:population":0,
    "gn:timezone":"Asia/Shanghai",
    "iso:country":"CN",
    "name:und_x_variant":[
        "Chengxi",
        "Chengxicun"
    ],
    "name:zho_x_preferred":[
        "\u57ce\u897f"
    ],
    "name:zho_x_variant":[
        "\u57ce\u897f\u6751"
    ],
    "wof:name":"Chengxicun",
    "wof:placetype":"locality"
},
  "geometry": {"coordinates":[118.31498000000001,30.92008],"type":"Point"}
}