{
  "type": "Feature",
  "properties": {
    "gn:admin1_code":"26.0",
    "gn:asciiname":"Zhengzegou",
    "gn:country_code":"CN",
    "gn:dem":1198,
    "gn:feature_class":"P",
    "gn:feature_code":"PPL",
    "gn:name":"Zhengzegou",
    "gn:population":0,
    "gn:timezone":"Asia/Shanghai",
    "iso:country":"CN",
    "name:zho_x_preferred":[
        "\u6b63\u5219\u6c9f"
    ],
    "wof:name":"Zhengzegou",
    "wof:placetype":"locality"
},
  "geometry": {"coordinates":[110.54935,38.98875],"type":"Point"}
}