{
  "type": "Feature",
  "properties": {
    "gn:admin1_code":"14.0",
    "gn:asciiname":"Xuegongcun",
    "gn:country_code":"CN",
    "gn:dem":2446,
    "gn:feature_class":"P",
    "gn:feature_code":"PPL",
    "gn:name":"Xuegongcun",
    "gn:population":0,
    "gn:timezone":"Asia/Urumqi",
    "iso:country":"CN",
    "name:zho_x_preferred":[
        "\u5b66\u8d21\u6751"
    ],
    "wof:name":"Xuegongcun",
    "wof:placetype":"locality"
},
  "geometry": {"coordinates":[98.08095,28.98041],"type":"Point"}
}