{
  "type": "Feature",
  "properties": {
    "gn:admin1_code":"24.0",
    "gn:asciiname":"Wengshan",
    "gn:country_code":"CN",
    "gn:dem":1038,
    "gn:feature_class":"P",
    "gn:feature_code":"PPL",
    "gn:name":"Wengshan",
    "gn:population":0,
    "gn:timezone":"Asia/Shanghai",
    "iso:country":"CN",
    "name:zho_x_preferred":[
        "\u74ee\u5c71"
    ],
    "wof:name":"Wengshan",
    "wof:placetype":"locality"
},
  "geometry": {"coordinates":[112.77195,35.60066],"type":"Point"}
}