{
  "type": "Feature",
  "properties": {
    "gn:admin1_code":"29.0",
    "gn:asciiname":"Dagoutou",
    "gn:country_code":"CN",
    "gn:dem":1904,
    "gn:feature_class":"P",
    "gn:feature_code":"PPL",
    "gn:name":"Dagoutou",
    "gn:population":0,
    "gn:timezone":"Asia/Shanghai",
    "iso:country":"CN",
    "name:zho_x_preferred":[
        "\u5927\u6c9f\u5934"
    ],
    "wof:name":"Dagoutou",
    "wof:placetype":"locality"
},
  "geometry": {"coordinates":[98.56870000000001,25.5999],"type":"Point"}
}