{
  "type": "Feature",
  "properties": {
    "gn:admin1_code":"32.0",
    "gn:asciiname":"Pifatian",
    "gn:country_code":"CN",
    "gn:dem":1929,
    "gn:feature_class":"P",
    "gn:feature_code":"PPL",
    "gn:name":"Pifatian",
    "gn:population":0,
    "gn:timezone":"Asia/Shanghai",
    "iso:country":"CN",
    "name:zho_x_preferred":[
        "\u6279\u53d1\u7530"
    ],
    "wof:name":"Pifatian",
    "wof:placetype":"locality"
},
  "geometry": {"coordinates":[102.50988,26.41414],"type":"Point"}
}