{
  "type": "Feature",
  "properties": {
    "gn:admin1_code":"25",
    "gn:asciiname":"Nanleibu",
    "gn:country_code":"CN",
    "gn:dem":8,
    "gn:feature_class":"P",
    "gn:feature_code":"PPL",
    "gn:name":"Nanleibu",
    "gn:population":0,
    "gn:timezone":"Asia/Shanghai",
    "iso:country":"CN",
    "name:zho_x_preferred":[
        "\u5357\u96f7\u57e0"
    ],
    "wof:name":"Nanleibu",
    "wof:placetype":"locality"
},
  "geometry": {"coordinates":[118.56999999999999,37.074],"type":"Point"}
}