{
  "type": "Feature",
  "properties": {
    "gn:admin1_code":"26.0",
    "gn:asciiname":"Baiyangshugou",
    "gn:country_code":"CN",
    "gn:dem":1188,
    "gn:feature_class":"P",
    "gn:feature_code":"PPL",
    "gn:name":"Baiyangshugou",
    "gn:population":0,
    "gn:timezone":"Asia/Shanghai",
    "iso:country":"CN",
    "name:und_x_variant":[
        "\u767d\u6768\u6811\u6c9f"
    ],
    "wof:name":"Baiyangshugou",
    "wof:placetype":"locality"
},
  "geometry": {"coordinates":[107.10333,34.93036],"type":"Point"}
}