{
  "type": "Feature",
  "properties": {
    "gn:admin1_code":"29.0",
    "gn:asciiname":"Gongwan",
    "gn:country_code":"CN",
    "gn:dem":1874,
    "gn:feature_class":"P",
    "gn:feature_code":"PPL",
    "gn:name":"Gongwan",
    "gn:population":0,
    "gn:timezone":"Asia/Shanghai",
    "iso:country":"CN",
    "name:zho_x_preferred":[
        "\u9f9a\u6e7e"
    ],
    "wof:name":"Gongwan",
    "wof:placetype":"locality"
},
  "geometry": {"coordinates":[101.32899999999999,25.7016],"type":"Point"}
}