{
  "type": "Feature",
  "properties": {
    "gn:admin1_code":"26.0",
    "gn:asciiname":"Qishugouquan",
    "gn:country_code":"CN",
    "gn:dem":1494,
    "gn:feature_class":"P",
    "gn:feature_code":"PPL",
    "gn:name":"Qishugouquan",
    "gn:population":0,
    "gn:timezone":"Asia/Shanghai",
    "iso:country":"CN",
    "name:zho_x_preferred":[
        "\u6f06\u6811\u6c9f\u5708"
    ],
    "wof:name":"Qishugouquan",
    "wof:placetype":"locality"
},
  "geometry": {"coordinates":[108.46993000000001,35.26305],"type":"Point"}
}