{
  "type": "Feature",
  "properties": {
    "gn:admin1_code":"30.0",
    "gn:asciiname":"Zhangshutou",
    "gn:country_code":"CN",
    "gn:dem":70,
    "gn:feature_class":"P",
    "gn:feature_code":"PPL",
    "gn:name":"Zhangshutou",
    "gn:population":0,
    "gn:timezone":"Asia/Shanghai",
    "iso:country":"CN",
    "name:und_x_variant":[
        "Tanshutou"
    ],
    "name:zho_x_preferred":[
        "\u6a1f\u6811\u5934"
    ],
    "name:zho_x_variant":[
        "\u6a80\u6811\u5934"
    ],
    "wof:name":"Zhangshutou",
    "wof:placetype":"locality"
},
  "geometry": {"coordinates":[115.63873999999998,23.24182],"type":"Point"}
}