{
  "type": "Feature",
  "properties": {
    "gn:admin1_code":"7",
    "gn:asciiname":"Huangdun",
    "gn:country_code":"CN",
    "gn:dem":299,
    "gn:feature_class":"P",
    "gn:feature_code":"PPL",
    "gn:name":"Huangdun",
    "gn:population":0,
    "gn:timezone":"Asia/Shanghai",
    "iso:country":"CN",
    "name:und_x_variant":[
        "\u9ec4\u58a9"
    ],
    "wof:name":"Huangdun",
    "wof:placetype":"locality"
},
  "geometry": {"coordinates":[118.57659,27.97259],"type":"Point"}
}