{
  "type": "Feature",
  "properties": {
    "gn:admin1_code":"30.0",
    "gn:asciiname":"Fuwo",
    "gn:country_code":"CN",
    "gn:dem":47,
    "gn:feature_class":"P",
    "gn:feature_code":"PPL",
    "gn:name":"Fuwo",
    "gn:population":0,
    "gn:timezone":"Asia/Shanghai",
    "iso:country":"CN",
    "name:zho_x_preferred":[
        "\u5bcc\u7a9d"
    ],
    "wof:name":"Fuwo",
    "wof:placetype":"locality"
},
  "geometry": {"coordinates":[111.48578999999999,23.23288],"type":"Point"}
}