{
  "type": "Feature",
  "properties": {
    "gn:admin1_code":"12",
    "gn:asciiname":"Dafan",
    "gn:country_code":"CN",
    "gn:dem":72,
    "gn:feature_class":"P",
    "gn:feature_code":"PPLA4",
    "gn:name":"Dafan",
    "gn:population":0,
    "gn:timezone":"Asia/Shanghai",
    "iso:country":"CN",
    "name:und_x_variant":[
        "Ta-fan",
        "Ta-fan-chen",
        "Dafan",
        "\u5927\u7548",
        "Dafan Zhen",
        "\u5927\u7548\u9547"
    ],
    "wof:name":"Dafan",
    "wof:placetype":"locality"
},
  "geometry": {"coordinates":[114.66437000000001,29.65883],"type":"Point"}
}