{
  "type": "Feature",
  "properties": {
    "gn:admin1_code":"15.0",
    "gn:asciiname":"Liushu Yaoxian",
    "gn:country_code":"CN",
    "gn:dem":1357,
    "gn:feature_class":"P",
    "gn:feature_code":"PPL",
    "gn:name":"Liushu Yaoxian",
    "gn:population":0,
    "gn:timezone":"Asia/Shanghai",
    "iso:country":"CN",
    "name:zho_x_preferred":[
        "\u67f3\u6811\u5d3e\u5c98"
    ],
    "wof:name":"Liushu Yaoxian",
    "wof:placetype":"locality"
},
  "geometry": {"coordinates":[107.328,35.9147],"type":"Point"}
}