{
  "type": "Feature",
  "properties": {
    "gn:admin1_code":"3.0",
    "gn:asciiname":"Aikeng",
    "gn:country_code":"CN",
    "gn:dem":309,
    "gn:feature_class":"P",
    "gn:feature_code":"PPL",
    "gn:name":"Aikeng",
    "gn:population":0,
    "gn:timezone":"Asia/Shanghai",
    "iso:country":"CN",
    "name:und_x_variant":[
        "\u827e\u5751"
    ],
    "wof:name":"Aikeng",
    "wof:placetype":"locality"
},
  "geometry": {"coordinates":[116.01931999999999,25.75656],"type":"Point"}
}