{
  "type": "Feature",
  "properties": {
    "gn:admin1_code":"19.0",
    "gn:asciiname":"Xichang Shanbu",
    "gn:country_code":"CN",
    "gn:dem":120,
    "gn:feature_class":"P",
    "gn:feature_code":"PPL",
    "gn:name":"Xichang Shanbu",
    "gn:population":0,
    "gn:timezone":"Asia/Shanghai",
    "iso:country":"CN",
    "name:zho_x_preferred":[
        "\u897f\u957f\u5c71\u5821"
    ],
    "wof:name":"Xichang Shanbu",
    "wof:placetype":"locality"
},
  "geometry": {"coordinates":[123.94799999999999,42.819],"type":"Point"}
}