{
  "type": "Feature",
  "properties": {
    "gn:admin1_code":"6.0",
    "gn:asciiname":"Jiamao",
    "gn:country_code":"CN",
    "gn:dem":2522,
    "gn:feature_class":"P",
    "gn:feature_code":"PPL",
    "gn:name":"Jiamao",
    "gn:population":0,
    "gn:timezone":"Asia/Shanghai",
    "iso:country":"CN",
    "name:und_x_variant":[
        "\u52a0\u6bdb"
    ],
    "wof:name":"Jiamao",
    "wof:placetype":"locality"
},
  "geometry": {"coordinates":[102.01524000000001,35.50227],"type":"Point"}
}