{
  "type": "Feature",
  "properties": {
    "gn:admin1_code":"7",
    "gn:asciiname":"Ruanyang",
    "gn:country_code":"CN",
    "gn:dem":147,
    "gn:feature_class":"P",
    "gn:feature_code":"PPL",
    "gn:name":"Ruanyang",
    "gn:population":0,
    "gn:timezone":"Asia/Shanghai",
    "iso:country":"CN",
    "name:zho_x_preferred":[
        "\u962e\u6d0b"
    ],
    "wof:name":"Ruanyang",
    "wof:placetype":"locality"
},
  "geometry": {"coordinates":[119.81056,27.08519],"type":"Point"}
}