{
  "type": "Feature",
  "properties": {
    "gn:admin1_code":"29.0",
    "gn:asciiname":"Mabuchong",
    "gn:country_code":"CN",
    "gn:dem":1340,
    "gn:feature_class":"P",
    "gn:feature_code":"PPL",
    "gn:name":"Mabuchong",
    "gn:population":0,
    "gn:timezone":"Asia/Shanghai",
    "iso:country":"CN",
    "name:zho_x_preferred":[
        "\u9ebb\u5e03\u51b2"
    ],
    "wof:name":"Mabuchong",
    "wof:placetype":"locality"
},
  "geometry": {"coordinates":[103.88200000000001,23.0604],"type":"Point"}
}