{
  "type": "Feature",
  "properties": {
    "gn:admin1_code":"25",
    "gn:asciiname":"Xiaozhang Guanzhuang",
    "gn:country_code":"CN",
    "gn:dem":182,
    "gn:feature_class":"P",
    "gn:feature_code":"PPL",
    "gn:name":"Xiaozhang Guanzhuang",
    "gn:population":0,
    "gn:timezone":"Asia/Shanghai",
    "iso:country":"CN",
    "name:zho_x_preferred":[
        "\u5c0f\u5f20\u5b98\u5e84"
    ],
    "wof:name":"Xiaozhang Guanzhuang",
    "wof:placetype":"locality"
},
  "geometry": {"coordinates":[118.76300000000001,35.8033],"type":"Point"}
}