{
  "type": "Feature",
  "properties": {
    "gn:admin1_code":"32.0",
    "gn:asciiname":"Xiaogouzi",
    "gn:country_code":"CN",
    "gn:dem":489,
    "gn:feature_class":"P",
    "gn:feature_code":"PPL",
    "gn:name":"Xiaogouzi",
    "gn:population":0,
    "gn:timezone":"Asia/Shanghai",
    "iso:country":"CN",
    "name:zho_x_preferred":[
        "\u5c0f\u6c9f\u5b50"
    ],
    "wof:name":"Xiaogouzi",
    "wof:placetype":"locality"
},
  "geometry": {"coordinates":[105.42261999999999,31.45781],"type":"Point"}
}