{
  "type": "Feature",
  "properties": {
    "gn:admin1_code":"26.0",
    "gn:asciiname":"Yue'ercun",
    "gn:country_code":"CN",
    "gn:dem":803,
    "gn:feature_class":"P",
    "gn:feature_code":"PPL",
    "gn:name":"Yue\u2019ercun",
    "gn:population":0,
    "gn:timezone":"Asia/Shanghai",
    "iso:country":"CN",
    "name:und_x_variant":[
        "Yue\u2019ercun"
    ],
    "name:zho_x_preferred":[
        "\u60a6\u8033\u6751"
    ],
    "wof:name":"Yue'ercun",
    "wof:placetype":"locality"
},
  "geometry": {"coordinates":[109.60127,35.3507],"type":"Point"}
}