{
  "type": "Feature",
  "properties": {
    "gn:admin1_code":"18.0",
    "gn:asciiname":"Zhaiji",
    "gn:country_code":"CN",
    "gn:dem":952,
    "gn:feature_class":"P",
    "gn:feature_code":"PPL",
    "gn:name":"Zhaiji",
    "gn:population":0,
    "gn:timezone":"Asia/Shanghai",
    "iso:country":"CN",
    "wof:name":"Zhaiji",
    "wof:placetype":"locality"
},
  "geometry": {"coordinates":[107.12139000000001,27.29806],"type":"Point"}
}