{
  "type": "Feature",
  "properties": {
    "gn:admin1_code":"26.0",
    "gn:asciiname":"Furongcun",
    "gn:country_code":"CN",
    "gn:dem":828,
    "gn:feature_class":"P",
    "gn:feature_code":"PPL",
    "gn:name":"Furongcun",
    "gn:population":0,
    "gn:timezone":"Asia/Shanghai",
    "iso:country":"CN",
    "name:zho_x_preferred":[
        "\u8299\u84c9\u6751"
    ],
    "wof:name":"Furongcun",
    "wof:placetype":"locality"
},
  "geometry": {"coordinates":[110.43089000000001,36.57745],"type":"Point"}
}