{
  "type": "Feature",
  "properties": {
    "gn:admin1_code":"12.0",
    "gn:asciiname":"Tuochuanpu",
    "gn:country_code":"CN",
    "gn:dem":42,
    "gn:feature_class":"P",
    "gn:feature_code":"PPL",
    "gn:name":"Tuochuanpu",
    "gn:population":0,
    "gn:timezone":"Asia/Shanghai",
    "iso:country":"CN",
    "name:zho_x_preferred":[
        "Tuochuanpu"
    ],
    "name:zho_x_variant":[
        "\u62d6\u8239\u94fa"
    ],
    "wof:name":"Tuochuanpu",
    "wof:placetype":"locality"
},
  "geometry": {"coordinates":[112.04976000000001,29.82391],"type":"Point"}
}