{
  "type": "Feature",
  "properties": {
    "gn:admin1_code":"4.0",
    "gn:asciiname":"Bitancun",
    "gn:country_code":"CN",
    "gn:dem":15,
    "gn:feature_class":"P",
    "gn:feature_code":"PPL",
    "gn:name":"Bitancun",
    "gn:population":0,
    "gn:timezone":"Asia/Shanghai",
    "iso:country":"CN",
    "name:zho_x_preferred":[
        "\u6bd5\u6ee9\u6751"
    ],
    "wof:name":"Bitancun",
    "wof:placetype":"locality"
},
  "geometry": {"coordinates":[118.57971000000001,33.80408],"type":"Point"}
}