{
  "type": "Feature",
  "properties": {
    "gn:admin1_code":"25",
    "gn:asciiname":"Liliucun",
    "gn:country_code":"CN",
    "gn:dem":50,
    "gn:feature_class":"P",
    "gn:feature_code":"PPL",
    "gn:name":"Liliucun",
    "gn:population":0,
    "gn:timezone":"Asia/Shanghai",
    "iso:country":"CN",
    "name:zho_x_preferred":[
        "\u674e\u516d\u6751"
    ],
    "wof:name":"Liliucun",
    "wof:placetype":"locality"
},
  "geometry": {"coordinates":[116.09399999999999,34.6946],"type":"Point"}
}