{
  "type": "Feature",
  "properties": {
    "gn:admin1_code":"30",
    "gn:asciiname":"Jiangzitou",
    "gn:country_code":"CN",
    "gn:dem":75,
    "gn:feature_class":"P",
    "gn:feature_code":"PPL",
    "gn:name":"Jiangzitou",
    "gn:population":0,
    "gn:timezone":"Asia/Shanghai",
    "iso:country":"CN",
    "name:zho_x_preferred":[
        "\u6c5f\u5b50\u5934"
    ],
    "wof:name":"Jiangzitou",
    "wof:placetype":"locality"
},
  "geometry": {"coordinates":[115.66553,23.31415],"type":"Point"}
}