{
  "type": "Feature",
  "properties": {
    "gn:admin1_code":"04",
    "gn:asciiname":"Daduo",
    "gn:country_code":"CN",
    "gn:dem":4,
    "gn:feature_class":"P",
    "gn:feature_code":"PPLA4",
    "gn:name":"Daduo",
    "gn:population":0,
    "gn:timezone":"Asia/Shanghai",
    "iso:country":"CN",
    "name:und_x_variant":[
        "Ta-to-chen",
        "Ta-to",
        "Daduo",
        "\u5927\u579b",
        "Daduo Zhen",
        "\u5927\u579b\u9547"
    ],
    "wof:name":"Daduo",
    "wof:placetype":"locality"
},
  "geometry": {"coordinates":[120.03407,32.89706],"type":"Point"}
}