{
  "type": "Feature",
  "properties": {
    "gn:admin1_code":"23.0",
    "gn:asciiname":"Wanjiazhai",
    "gn:country_code":"CN",
    "gn:dem":4,
    "gn:feature_class":"P",
    "gn:feature_code":"PPL",
    "gn:name":"Wanjiazhai",
    "gn:population":0,
    "gn:timezone":"Asia/Shanghai",
    "iso:country":"CN",
    "name:zho_x_preferred":[
        "Wanjiazhai"
    ],
    "name:zho_x_variant":[
        "\u4e07\u5bb6\u5b85"
    ],
    "wof:name":"Wanjiazhai",
    "wof:placetype":"locality"
},
  "geometry": {"coordinates":[121.24381,31.28065],"type":"Point"}
}