{
  "type": "Feature",
  "properties": {
    "gn:admin1_code":"4.0",
    "gn:asciiname":"Qianjiawan",
    "gn:country_code":"CN",
    "gn:dem":3,
    "gn:feature_class":"P",
    "gn:feature_code":"PPL",
    "gn:name":"Qianjiawan",
    "gn:population":0,
    "gn:timezone":"Asia/Shanghai",
    "iso:country":"CN",
    "name:zho_x_preferred":[
        "\u94b1\u5bb6\u6e7e"
    ],
    "wof:name":"Qianjiawan",
    "wof:placetype":"locality"
},
  "geometry": {"coordinates":[120.28963,32.07891],"type":"Point"}
}