{
  "type": "Feature",
  "properties": {
    "gn:admin1_code":"8.0",
    "gn:asciiname":"Zhenluncun",
    "gn:country_code":"CN",
    "gn:dem":179,
    "gn:feature_class":"P",
    "gn:feature_code":"PPL",
    "gn:name":"Zhenluncun",
    "gn:population":0,
    "gn:timezone":"Asia/Shanghai",
    "iso:country":"CN",
    "name:zho_x_preferred":[
        "\u632f\u4f26\u6751"
    ],
    "wof:name":"Zhenluncun",
    "wof:placetype":"locality"
},
  "geometry": {"coordinates":[126.48757000000001,47.10036],"type":"Point"}
}