{
  "type": "Feature",
  "properties": {
    "gn:admin1_code":"13.0",
    "gn:asciiname":"Tamuqi",
    "gn:country_code":"CN",
    "gn:dem":2553,
    "gn:feature_class":"P",
    "gn:feature_code":"PPL",
    "gn:name":"Tamuqi",
    "gn:population":0,
    "gn:timezone":"Asia/Shanghai",
    "iso:country":"CN",
    "name:zho_x_preferred":[
        "\u5854\u6728\u5176"
    ],
    "wof:name":"Tamuqi",
    "wof:placetype":"locality"
},
  "geometry": {"coordinates":[82.09133,36.47964],"type":"Point"}
}