{
  "type": "Feature",
  "properties": {
    "gn:admin1_code":"26.0",
    "gn:asciiname":"Sujiashan",
    "gn:country_code":"CN",
    "gn:dem":855,
    "gn:feature_class":"P",
    "gn:feature_code":"PPL",
    "gn:name":"Sujiashan",
    "gn:population":0,
    "gn:timezone":"Asia/Shanghai",
    "iso:country":"CN",
    "name:und_x_variant":[
        "\u82cf\u5bb6\u5c71"
    ],
    "wof:name":"Sujiashan",
    "wof:placetype":"locality"
},
  "geometry": {"coordinates":[107.19132999999999,34.5599],"type":"Point"}
}