{
  "type": "Feature",
  "properties": {
    "gn:admin1_code":"9",
    "gn:asciiname":"Caozhuang",
    "gn:country_code":"CN",
    "gn:dem":35,
    "gn:feature_class":"P",
    "gn:feature_code":"PPL",
    "gn:name":"Caozhuang",
    "gn:population":0,
    "gn:timezone":"Asia/Shanghai",
    "iso:country":"CN",
    "name:ceb_x_preferred":[
        "Caozhuang"
    ],
    "name:swe_x_preferred":[
        "Caozhuang"
    ],
    "name:zho_x_preferred":[
        "\u66f9\u5e84"
    ],
    "wof:name":"Caozhuang",
    "wof:placetype":"locality"
},
  "geometry": {"coordinates":[116.492,33.9583],"type":"Point"}
}