{
  "type": "Feature",
  "properties": {
    "gn:admin1_code":"10.0",
    "gn:asciiname":"Diguantun",
    "gn:country_code":"CN",
    "gn:dem":13,
    "gn:feature_class":"P",
    "gn:feature_code":"PPL",
    "gn:name":"Diguantun",
    "gn:population":0,
    "gn:timezone":"Asia/Shanghai",
    "iso:country":"CN",
    "name:zho_x_preferred":[
        "\u7fdf\u5b98\u5c6f"
    ],
    "wof:name":"Diguantun",
    "wof:placetype":"locality"
},
  "geometry": {"coordinates":[116.715,38.0505],"type":"Point"}
}