{
  "type": "Feature",
  "properties": {
    "gn:admin1_code":"10",
    "gn:asciiname":"Nankaihe",
    "gn:country_code":"CN",
    "gn:dem":70,
    "gn:feature_class":"P",
    "gn:feature_code":"PPL",
    "gn:name":"Nankaihe",
    "gn:population":0,
    "gn:timezone":"Asia/Shanghai",
    "iso:country":"CN",
    "name:zho_x_preferred":[
        "\u5357\u5f00\u6cb3"
    ],
    "wof:name":"Nankaihe",
    "wof:placetype":"locality"
},
  "geometry": {"coordinates":[114.402,36.357],"type":"Point"}
}