{
  "type": "Feature",
  "properties": {
    "gn:admin1_code":"8.0",
    "gn:asciiname":"Anmincun",
    "gn:country_code":"CN",
    "gn:dem":123,
    "gn:feature_class":"P",
    "gn:feature_code":"PPL",
    "gn:name":"Anmincun",
    "gn:population":0,
    "gn:timezone":"Asia/Shanghai",
    "iso:country":"CN",
    "name:zho_x_preferred":[
        "\u5b89\u6c11\u6751"
    ],
    "wof:name":"Anmincun",
    "wof:placetype":"locality"
},
  "geometry": {"coordinates":[128.71365,49.3691],"type":"Point"}
}