{
  "type": "Feature",
  "properties": {
    "gn:admin1_code":"18",
    "gn:asciiname":"Huoshaoba",
    "gn:country_code":"CN",
    "gn:dem":1663,
    "gn:feature_class":"P",
    "gn:feature_code":"PPL",
    "gn:name":"Huoshaoba",
    "gn:population":0,
    "gn:timezone":"Asia/Shanghai",
    "iso:country":"CN",
    "name:zho_x_preferred":[
        "\u706b\u70e7\u575d"
    ],
    "wof:name":"Huoshaoba",
    "wof:placetype":"locality"
},
  "geometry": {"coordinates":[105.28700000000001,27.5432],"type":"Point"}
}