{
  "type": "Feature",
  "properties": {
    "gn:admin1_code":"3.0",
    "gn:asciiname":"Shihuikeng",
    "gn:country_code":"CN",
    "gn:dem":399,
    "gn:feature_class":"P",
    "gn:feature_code":"PPL",
    "gn:name":"Shihuikeng",
    "gn:population":0,
    "gn:timezone":"Asia/Shanghai",
    "iso:country":"CN",
    "name:und_x_variant":[
        "\u77f3\u7070\u5751"
    ],
    "wof:name":"Shihuikeng",
    "wof:placetype":"locality"
},
  "geometry": {"coordinates":[114.10068,27.98768],"type":"Point"}
}