{
  "type": "Feature",
  "properties": {
    "gn:admin1_code":"07",
    "gn:asciiname":"Taiba",
    "gn:country_code":"CN",
    "gn:dem":237,
    "gn:feature_class":"P",
    "gn:feature_code":"PPLA4",
    "gn:name":"Taiba",
    "gn:population":0,
    "gn:timezone":"Asia/Shanghai",
    "iso:country":"CN",
    "name:und_x_variant":[
        "Taiba Xiang"
    ],
    "name:zho_x_preferred":[
        "T\u2019ai-pa"
    ],
    "name:zho_x_variant":[
        "\u592a\u62d4",
        "\u592a\u62d4\u4e61"
    ],
    "wof:name":"Taiba",
    "wof:placetype":"locality"
},
  "geometry": {"coordinates":[116.63549,24.98536],"type":"Point"}
}