{
  "type": "Feature",
  "properties": {
    "gn:admin1_code":"8.0",
    "gn:asciiname":"Guangyicun",
    "gn:country_code":"CN",
    "gn:dem":240,
    "gn:feature_class":"P",
    "gn:feature_code":"PPL",
    "gn:name":"Guangyicun",
    "gn:population":0,
    "gn:timezone":"Asia/Shanghai",
    "iso:country":"CN",
    "name:zho_x_preferred":[
        "\u5e7f\u4e49\u6751"
    ],
    "wof:name":"Guangyicun",
    "wof:placetype":"locality"
},
  "geometry": {"coordinates":[124.82398000000001,48.19121],"type":"Point"}
}