{
  "type": "Feature",
  "properties": {
    "gn:admin1_code":"16.0",
    "gn:asciiname":"Guimushan",
    "gn:country_code":"CN",
    "gn:dem":177,
    "gn:feature_class":"P",
    "gn:feature_code":"PPL",
    "gn:name":"Guimushan",
    "gn:population":0,
    "gn:timezone":"Asia/Shanghai",
    "iso:country":"CN",
    "name:zho_x_preferred":[
        "\u6842\u6728\u5c71"
    ],
    "wof:name":"Guimushan",
    "wof:placetype":"locality"
},
  "geometry": {"coordinates":[110.387,23.1275],"type":"Point"}
}