{
  "type": "Feature",
  "properties": {
    "gn:admin1_code":"30.0",
    "gn:asciiname":"Huangjiekeng",
    "gn:country_code":"CN",
    "gn:dem":84,
    "gn:feature_class":"P",
    "gn:feature_code":"PPL",
    "gn:name":"Huangjiekeng",
    "gn:population":0,
    "gn:timezone":"Asia/Shanghai",
    "iso:country":"CN",
    "name:zho_x_preferred":[
        "\u9ec4\u754c\u5751"
    ],
    "wof:name":"Huangjiekeng",
    "wof:placetype":"locality"
},
  "geometry": {"coordinates":[112.31068,23.88321],"type":"Point"}
}