{
  "type": "Feature",
  "properties": {
    "gn:admin1_code":"19.0",
    "gn:asciiname":"Yangbizi",
    "gn:country_code":"CN",
    "gn:dem":118,
    "gn:feature_class":"P",
    "gn:feature_code":"PPL",
    "gn:name":"Yangbizi",
    "gn:population":0,
    "gn:timezone":"Asia/Shanghai",
    "iso:country":"CN",
    "name:zho_x_preferred":[
        "\u7f8a\u9f3b\u5b50"
    ],
    "wof:name":"Yangbizi",
    "wof:placetype":"locality"
},
  "geometry": {"coordinates":[121.895,39.24],"type":"Point"}
}