{
  "type": "Feature",
  "properties": {
    "gn:admin1_code":"20.0",
    "gn:asciiname":"Qiancha Bagou",
    "gn:country_code":"CN",
    "gn:dem":1481,
    "gn:feature_class":"P",
    "gn:feature_code":"PPL",
    "gn:name":"Qiancha Bagou",
    "gn:population":0,
    "gn:timezone":"Asia/Shanghai",
    "iso:country":"CN",
    "name:und_x_variant":[
        "\u524d\u6748\u6252\u6c9f"
    ],
    "wof:name":"Qiancha Bagou",
    "wof:placetype":"locality"
},
  "geometry": {"coordinates":[111.96145,39.87774],"type":"Point"}
}