{
  "type": "Feature",
  "properties": {
    "gn:admin1_code":"20.0",
    "gn:asciiname":"Changling",
    "gn:country_code":"CN",
    "gn:dem":313,
    "gn:feature_class":"P",
    "gn:feature_code":"PPL",
    "gn:name":"Changling",
    "gn:population":0,
    "gn:timezone":"Asia/Shanghai",
    "iso:country":"CN",
    "name:ara_x_preferred":[
        "\u062a\u0634\u0627\u0646\u062c\u0644\u064a\u0646\u062c"
    ],
    "name:ben_x_preferred":[
        "\u099a\u09cd\u09af\u09be\u0982\u09b2\u09bf\u0982"
    ],
    "name:ceb_x_preferred":[
        "Changling"
    ],
    "name:deu_x_preferred":[
        "Changling"
    ],
    "name:ell_x_preferred":[
        "\u03a4\u03c3\u03b1\u03bd\u03c4\u03c3\u03bb\u03af\u03bd\u03b3\u03ba"
    ],
    "name:heb_x_preferred":[
        "\u05e6'\u05d0\u05e0\u05d2\u05dc\u05d9\u05e0\u05d2"
    ],
    "name:hin_x_preferred":[
        "\u091a\u0948\u0902\u0917\u0932\u093f\u0902\u0917"
    ],
    "name:hun_x_preferred":[
        "Changling"
    ],
    "name:ind_x_preferred":[
        "Changling"
    ],
    "name:mlg_x_preferred":[
        "Changling"
    ],
    "name:por_x_preferred":[
        "Changling"
    ],
    "name:swe_x_preferred":[
        "Changling"
    ],
    "name:tur_x_preferred":[
        "Changling"
    ],
    "name:ukr_x_preferred":[
        "\u0427\u0430\u043d\u043b\u0456\u043d"
    ],
    "name:zho_x_preferred":[
        "\u957f\u5cad"
    ],
    "wof:name":"Changling",
    "wof:placetype":"locality"
},
  "geometry": {"coordinates":[124.50129,49.48738],"type":"Point"}
}