{
  "type": "Feature",
  "properties": {
    "gn:admin1_code":"20.0",
    "gn:asciiname":"Yangchanggou",
    "gn:country_code":"CN",
    "gn:dem":1813,
    "gn:feature_class":"P",
    "gn:feature_code":"PPL",
    "gn:name":"Yangchanggou",
    "gn:population":0,
    "gn:timezone":"Asia/Shanghai",
    "iso:country":"CN",
    "name:und_x_variant":[
        "\u7f8a\u573a\u6c9f"
    ],
    "wof:name":"Yangchanggou",
    "wof:placetype":"locality"
},
  "geometry": {"coordinates":[112.52307,41.048],"type":"Point"}
}