{
  "type": "Feature",
  "properties": {
    "gn:admin1_code":"15.0",
    "gn:asciiname":"Huangjiajing",
    "gn:country_code":"CN",
    "gn:dem":1314,
    "gn:feature_class":"P",
    "gn:feature_code":"PPL",
    "gn:name":"Huangjiajing",
    "gn:population":0,
    "gn:timezone":"Asia/Shanghai",
    "iso:country":"CN",
    "name:zho_x_preferred":[
        "\u9ec4\u5bb6\u4e95"
    ],
    "wof:name":"Huangjiajing",
    "wof:placetype":"locality"
},
  "geometry": {"coordinates":[103.967,39.1181],"type":"Point"}
}