{
  "type": "Feature",
  "properties": {
    "gn:admin1_code":"1.0",
    "gn:asciiname":"Youfanggangcun",
    "gn:country_code":"CN",
    "gn:dem":18,
    "gn:feature_class":"P",
    "gn:feature_code":"PPL",
    "gn:name":"Youfanggangcun",
    "gn:population":0,
    "gn:timezone":"Asia/Shanghai",
    "iso:country":"CN",
    "name:zho_x_preferred":[
        "\u6cb9\u574a\u5c97\u6751"
    ],
    "wof:name":"Youfanggangcun",
    "wof:placetype":"locality"
},
  "geometry": {"coordinates":[117.26656,31.80067],"type":"Point"}
}