{
  "type": "Feature",
  "properties": {
    "gn:admin1_code":"3.0",
    "gn:asciiname":"Baishikeng",
    "gn:country_code":"CN",
    "gn:dem":570,
    "gn:feature_class":"P",
    "gn:feature_code":"PPL",
    "gn:name":"Baishikeng",
    "gn:population":0,
    "gn:timezone":"Asia/Shanghai",
    "iso:country":"CN",
    "name:zho_x_preferred":[
        "\u767d\u77f3\u5751"
    ],
    "wof:name":"Baishikeng",
    "wof:placetype":"locality"
},
  "geometry": {"coordinates":[115.504,24.8967],"type":"Point"}
}