{
  "type": "Feature",
  "properties": {
    "gn:admin1_code":"26.0",
    "gn:asciiname":"Tongshuling",
    "gn:country_code":"CN",
    "gn:dem":917,
    "gn:feature_class":"P",
    "gn:feature_code":"PPL",
    "gn:name":"Tongshuling",
    "gn:population":0,
    "gn:timezone":"Asia/Shanghai",
    "iso:country":"CN",
    "name:und_x_variant":[
        "\u6850\u6811\u5cad"
    ],
    "wof:name":"Tongshuling",
    "wof:placetype":"locality"
},
  "geometry": {"coordinates":[107.05551,34.32126],"type":"Point"}
}