{
  "type": "Feature",
  "properties": {
    "gn:admin1_code":"1.0",
    "gn:asciiname":"Cailicun",
    "gn:country_code":"CN",
    "gn:dem":37,
    "gn:feature_class":"P",
    "gn:feature_code":"PPL",
    "gn:name":"Cailicun",
    "gn:population":0,
    "gn:timezone":"Asia/Shanghai",
    "iso:country":"CN",
    "name:zho_x_preferred":[
        "\u8521\u91cc\u6751"
    ],
    "wof:name":"Cailicun",
    "wof:placetype":"locality"
},
  "geometry": {"coordinates":[116.91211,33.92853],"type":"Point"}
}