{
  "type": "Feature",
  "properties": {
    "gn:admin1_code":"15",
    "gn:asciiname":"Gancaodian",
    "gn:cc2":"CN",
    "gn:country_code":"CN",
    "gn:dem":1875,
    "gn:feature_class":"P",
    "gn:feature_code":"PPL",
    "gn:name":"Gancaodian",
    "gn:population":0,
    "gn:timezone":"Asia/Shanghai",
    "iso:country":"CN",
    "name:und_x_variant":[
        "Kan-ts\u2019ao-tien",
        "Gan\u2019tsaodyan\u2019",
        "Kan-ts\u2019au-tien",
        "Gancaodian"
    ],
    "wof:name":"Gancaodian",
    "wof:placetype":"locality"
},
  "geometry": {"coordinates":[104.28417,35.79889],"type":"Point"}
}