{
  "type": "Feature",
  "properties": {
    "gn:admin1_code":"12.0",
    "gn:asciiname":"Gaoyunhuang",
    "gn:country_code":"CN",
    "gn:dem":1112,
    "gn:feature_class":"P",
    "gn:feature_code":"PPL",
    "gn:name":"Gaoyunhuang",
    "gn:population":0,
    "gn:timezone":"Asia/Shanghai",
    "iso:country":"CN",
    "name:zho_x_preferred":[
        "\u9ad8\u4e91\u8352"
    ],
    "wof:name":"Gaoyunhuang",
    "wof:placetype":"locality"
},
  "geometry": {"coordinates":[109.44164000000001,30.50766],"type":"Point"}
}