{
  "type": "Feature",
  "properties": {
    "gn:admin1_code":"9.0",
    "gn:asciiname":"Ranjia",
    "gn:country_code":"CN",
    "gn:dem":110,
    "gn:feature_class":"P",
    "gn:feature_code":"PPL",
    "gn:name":"Ranjia",
    "gn:population":0,
    "gn:timezone":"Asia/Shanghai",
    "iso:country":"CN",
    "name:zho_x_preferred":[
        "\u5189\u5bb6"
    ],
    "wof:name":"Ranjia",
    "wof:placetype":"locality"
},
  "geometry": {"coordinates":[113.98054999999999,34.5015],"type":"Point"}
}