{
  "type": "Feature",
  "properties": {
    "gn:admin1_code":"24.0",
    "gn:asciiname":"Xishahe",
    "gn:country_code":"CN",
    "gn:dem":1065,
    "gn:feature_class":"P",
    "gn:feature_code":"PPL",
    "gn:name":"Xishahe",
    "gn:population":0,
    "gn:timezone":"Asia/Shanghai",
    "iso:country":"CN",
    "name:zho_x_preferred":[
        "\u897f\u7802\u6cb3"
    ],
    "wof:name":"Xishahe",
    "wof:placetype":"locality"
},
  "geometry": {"coordinates":[113.51013,39.25941],"type":"Point"}
}