{
  "type": "Feature",
  "properties": {
    "gn:admin1_code":"29",
    "gn:asciiname":"Dapingzhen",
    "gn:country_code":"CN",
    "gn:dem":1556,
    "gn:feature_class":"P",
    "gn:feature_code":"PPL",
    "gn:name":"Dapingzhen",
    "gn:population":0,
    "gn:timezone":"Asia/Shanghai",
    "iso:country":"CN",
    "wof:name":"Dapingzhen",
    "wof:placetype":"locality"
},
  "geometry": {"coordinates":[104.59028000000001,23.10917],"type":"Point"}
}