{
  "type": "Feature",
  "properties": {
    "gn:admin1_code":"29.0",
    "gn:asciiname":"Xinfangzi",
    "gn:country_code":"CN",
    "gn:dem":2419,
    "gn:feature_class":"P",
    "gn:feature_code":"PPL",
    "gn:name":"Xinfangzi",
    "gn:population":0,
    "gn:timezone":"Asia/Shanghai",
    "iso:country":"CN",
    "name:zho_x_preferred":[
        "\u65b0\u623f\u5b50"
    ],
    "wof:name":"Xinfangzi",
    "wof:placetype":"locality"
},
  "geometry": {"coordinates":[103.425,26.8565],"type":"Point"}
}