{
  "type": "Feature",
  "properties": {
    "gn:admin1_code":"7.0",
    "gn:asciiname":"Wuyuan",
    "gn:country_code":"CN",
    "gn:dem":38,
    "gn:feature_class":"P",
    "gn:feature_code":"PPL",
    "gn:name":"Wuyuan",
    "gn:population":0,
    "gn:timezone":"Asia/Shanghai",
    "iso:country":"CN",
    "name:ceb_x_preferred":[
        "Wuyuan"
    ],
    "name:deu_x_preferred":[
        "Wuyuan"
    ],
    "name:fra_x_preferred":[
        "Wuyuan"
    ],
    "name:kor_x_preferred":[
        "\uc6b0\uc704\uc548"
    ],
    "name:kor_x_variant":[
        "\uc6b0\uc704\uc548\ud604"
    ],
    "name:nld_x_preferred":[
        "Wuyuan"
    ],
    "name:nor_x_preferred":[
        "Wuyuan"
    ],
    "name:pol_x_preferred":[
        "Wuyuan"
    ],
    "name:por_x_preferred":[
        "Wuyuan"
    ],
    "name:rus_x_preferred":[
        "\u0423\u044e\u0430\u043d\u044c"
    ],
    "name:swe_x_preferred":[
        "Wuyuan"
    ],
    "name:tur_x_preferred":[
        "Wuyuan"
    ],
    "name:ukr_x_preferred":[
        "\u0424\u0443\u044e\u0430\u043d\u044c"
    ],
    "name:urd_x_preferred":[
        "\u0648\u0648\u06cc\u0627\u0646"
    ],
    "name:vie_x_preferred":[
        "V\u1ee5 Nguy\u00ean"
    ],
    "name:zho_cn_x_preferred":[
        "\u5a7a\u6e90"
    ],
    "name:zho_tw_x_preferred":[
        "\u5a7a\u6e90"
    ],
    "name:zho_x_preferred":[
        "\u6d6f\u6e90"
    ],
    "wof:name":"Wuyuan",
    "wof:placetype":"locality"
},
  "geometry": {"coordinates":[117.69634000000001,24.16815],"type":"Point"}
}