{
  "type": "Feature",
  "properties": {
    "gn:admin1_code":"3.0",
    "gn:asciiname":"Shunde",
    "gn:country_code":"CN",
    "gn:dem":26,
    "gn:feature_class":"P",
    "gn:feature_code":"PPL",
    "gn:name":"Shunde",
    "gn:population":0,
    "gn:timezone":"Asia/Shanghai",
    "iso:country":"CN",
    "name:und_x_variant":[
        "\u821c\u5fb7",
        "Shundexiang",
        "\u821c\u5fb7\u4e61"
    ],
    "wof:name":"Shunde",
    "wof:placetype":"locality"
},
  "geometry": {"coordinates":[116.22691,29.57923],"type":"Point"}
}