{
  "type": "Feature",
  "properties": {
    "gn:admin1_code":"7",
    "gn:asciiname":"Sukeng",
    "gn:country_code":"CN",
    "gn:dem":597,
    "gn:feature_class":"P",
    "gn:feature_code":"PPLA4",
    "gn:name":"Sukeng",
    "gn:population":0,
    "gn:timezone":"Asia/Shanghai",
    "iso:country":"CN",
    "name:und_x_variant":[
        "Daxiban",
        "Sukeng",
        "Sukeng Zhen"
    ],
    "name:zho_x_preferred":[
        "\u82cf\u5751"
    ],
    "name:zho_x_variant":[
        "\u5927\u6eaa\u5742",
        "\u82cf\u5751\u9547"
    ],
    "wof:name":"Sukeng",
    "wof:placetype":"locality"
},
  "geometry": {"coordinates":[118.21473,25.43531],"type":"Point"}
}