{
  "type": "Feature",
  "properties": {
    "gn:admin1_code":"02",
    "gn:asciiname":"Lingnan",
    "gn:country_code":"CN",
    "gn:dem":4,
    "gn:feature_class":"P",
    "gn:feature_code":"PPL",
    "gn:name":"Lingnan",
    "gn:population":0,
    "gn:timezone":"Asia/Shanghai",
    "iso:country":"CN",
    "name:deu_x_preferred":[
        "Lingnan"
    ],
    "name:ind_x_preferred":[
        "Lingnan"
    ],
    "name:ita_x_preferred":[
        "Lingnan"
    ],
    "name:jpn_x_preferred":[
        "\u5dba\u5357"
    ],
    "name:kor_x_preferred":[
        "\uc601\ub0a8"
    ],
    "name:rus_x_preferred":[
        "\u041b\u0438\u043d\u043d\u0430\u043d\u044c"
    ],
    "name:vie_x_preferred":[
        "L\u0129nh Nam"
    ],
    "wof:name":"Lingnan",
    "wof:placetype":"locality"
},
  "geometry": {"coordinates":[121.76389,29.32],"type":"Point"}
}