{
  "type": "Feature",
  "properties": {
    "gn:admin1_code":"26.0",
    "gn:asciiname":"Chaiguanshancun",
    "gn:country_code":"CN",
    "gn:dem":1479,
    "gn:feature_class":"P",
    "gn:feature_code":"PPL",
    "gn:name":"Chaiguanshancun",
    "gn:population":0,
    "gn:timezone":"Asia/Shanghai",
    "iso:country":"CN",
    "name:zho_x_preferred":[
        "\u67f4\u5173\u5c71\u6751"
    ],
    "wof:name":"Chaiguanshancun",
    "wof:placetype":"locality"
},
  "geometry": {"coordinates":[108.94643000000001,36.54018],"type":"Point"}
}