{
  "type": "Feature",
  "properties": {
    "gn:admin1_code":"24.0",
    "gn:asciiname":"Dipengyao",
    "gn:country_code":"CN",
    "gn:dem":1127,
    "gn:feature_class":"P",
    "gn:feature_code":"PPL",
    "gn:name":"Dipengyao",
    "gn:population":0,
    "gn:timezone":"Asia/Shanghai",
    "iso:country":"CN",
    "name:zho_x_preferred":[
        "\u5730\u68da\u8170"
    ],
    "wof:name":"Dipengyao",
    "wof:placetype":"locality"
},
  "geometry": {"coordinates":[112.09309,35.28175],"type":"Point"}
}