{
  "type": "Feature",
  "properties": {
    "gn:admin1_code":"14.0",
    "gn:asciiname":"Chabug",
    "gn:country_code":"CN",
    "gn:dem":4999,
    "gn:feature_class":"P",
    "gn:feature_code":"PPL",
    "gn:name":"Chabug",
    "gn:population":0,
    "gn:timezone":"Asia/Urumqi",
    "iso:country":"CN",
    "name:bod_x_preferred":[
        "Chabug"
    ],
    "name:msa_x_preferred":[
        "Chabug"
    ],
    "name:swe_x_preferred":[
        "Cabu"
    ],
    "name:zho_x_preferred":[
        "Chabu"
    ],
    "name:zho_x_variant":[
        "\u67e5\u5e03",
        "\u5bdf\u5e03\u4e61"
    ],
    "wof:name":"Chabug",
    "wof:placetype":"locality"
},
  "geometry": {"coordinates":[89.33280000000001,31.1016],"type":"Point"}
}