{
  "type": "Feature",
  "properties": {
    "gn:admin1_code":"10",
    "gn:asciiname":"Shangluoyu",
    "gn:country_code":"CN",
    "gn:dem":531,
    "gn:feature_class":"P",
    "gn:feature_code":"PPL",
    "gn:name":"Shangluoyu",
    "gn:population":0,
    "gn:timezone":"Asia/Shanghai",
    "iso:country":"CN",
    "name:zho_x_preferred":[
        "\u4e0a\u7f57\u5cea"
    ],
    "wof:name":"Shangluoyu",
    "wof:placetype":"locality"
},
  "geometry": {"coordinates":[114.133,37.8615],"type":"Point"}
}