{
  "type": "Feature",
  "properties": {
    "gn:admin1_code":"15.0",
    "gn:asciiname":"Yushuzhuang",
    "gn:country_code":"CN",
    "gn:dem":1372,
    "gn:feature_class":"P",
    "gn:feature_code":"PPL",
    "gn:name":"Yushuzhuang",
    "gn:population":0,
    "gn:timezone":"Asia/Shanghai",
    "iso:country":"CN",
    "name:zho_x_preferred":[
        "\u6986\u6811\u5e84"
    ],
    "wof:name":"Yushuzhuang",
    "wof:placetype":"locality"
},
  "geometry": {"coordinates":[108.407,36.3258],"type":"Point"}
}