{
  "type": "Feature",
  "properties": {
    "gn:admin1_code":"4.0",
    "gn:asciiname":"Changyicun",
    "gn:country_code":"CN",
    "gn:dem":58,
    "gn:feature_class":"P",
    "gn:feature_code":"PPL",
    "gn:name":"Changyicun",
    "gn:population":0,
    "gn:timezone":"Asia/Shanghai",
    "iso:country":"CN",
    "name:zho_x_preferred":[
        "\u660c\u6c82\u6751"
    ],
    "wof:name":"Changyicun",
    "wof:placetype":"locality"
},
  "geometry": {"coordinates":[118.59332000000001,34.60028],"type":"Point"}
}