{
  "type": "Feature",
  "properties": {
    "gn:admin1_code":"10.0",
    "gn:asciiname":"Daohongsi",
    "gn:country_code":"CN",
    "gn:dem":1137,
    "gn:feature_class":"P",
    "gn:feature_code":"PPL",
    "gn:name":"Daohongsi",
    "gn:population":0,
    "gn:timezone":"Asia/Shanghai",
    "iso:country":"CN",
    "name:zho_x_preferred":[
        "\u9053\u6d2a\u5bfa"
    ],
    "wof:name":"Daohongsi",
    "wof:placetype":"locality"
},
  "geometry": {"coordinates":[115.16656,39.98963],"type":"Point"}
}