{
  "type": "Feature",
  "properties": {
    "gn:admin1_code":"2.0",
    "gn:asciiname":"Huangnidong",
    "gn:country_code":"CN",
    "gn:dem":44,
    "gn:feature_class":"P",
    "gn:feature_code":"PPL",
    "gn:name":"Huangnidong",
    "gn:population":0,
    "gn:timezone":"Asia/Shanghai",
    "iso:country":"CN",
    "name:und_x_variant":[
        "Shepan",
        "Huangnidong"
    ],
    "name:zho_x_preferred":[
        "\u9ec4\u6ce5\u6d1e"
    ],
    "name:zho_x_variant":[
        "\u86c7\u87e0"
    ],
    "wof:name":"Huangnidong",
    "wof:placetype":"locality"
},
  "geometry": {"coordinates":[121.57708,29.14446],"type":"Point"}
}