{
  "type": "Feature",
  "properties": {
    "gn:admin1_code":"29.0",
    "gn:asciiname":"Zimajie",
    "gn:country_code":"CN",
    "gn:dem":1458,
    "gn:feature_class":"P",
    "gn:feature_code":"PPL",
    "gn:name":"Zimajie",
    "gn:population":0,
    "gn:timezone":"Asia/Shanghai",
    "iso:country":"CN",
    "wof:name":"Zimajie",
    "wof:placetype":"locality"
},
  "geometry": {"coordinates":[100.66667,23.93333],"type":"Point"}
}