{
  "type": "Feature",
  "properties": {
    "gn:admin1_code":"04",
    "gn:asciiname":"Wuxiangbang",
    "gn:country_code":"CN",
    "gn:dem":7,
    "gn:feature_class":"P",
    "gn:feature_code":"PPL",
    "gn:name":"Wuxiangbang",
    "gn:population":0,
    "gn:timezone":"Asia/Shanghai",
    "iso:country":"CN",
    "name:und_x_variant":[
        "\u5434\u7965\u6d5c"
    ],
    "wof:name":"Wuxiangbang",
    "wof:placetype":"locality"
},
  "geometry": {"coordinates":[120.84832,31.76381],"type":"Point"}
}