{
  "type": "Feature",
  "properties": {
    "gn:admin1_code":"20.0",
    "gn:asciiname":"Tuanjie Wudui",
    "gn:country_code":"CN",
    "gn:dem":394,
    "gn:feature_class":"P",
    "gn:feature_code":"PPLF",
    "gn:name":"Tuanjie Wudui",
    "gn:population":0,
    "gn:timezone":"Asia/Shanghai",
    "iso:country":"CN",
    "name:zho_x_preferred":[
        "\u56e2\u7ed3\u4e94\u961f"
    ],
    "wof:name":"Tuanjie Wudui",
    "wof:placetype":"locality"
},
  "geometry": {"coordinates":[122.24729000000001,47.49275],"type":"Point"}
}