{
  "type": "Feature",
  "properties": {
    "gn:admin1_code":"11",
    "gn:asciiname":"Meitianhu",
    "gn:country_code":"CN",
    "gn:dem":34,
    "gn:feature_class":"P",
    "gn:feature_code":"PPLA4",
    "gn:name":"Meitianhu",
    "gn:population":0,
    "gn:timezone":"Asia/Shanghai",
    "iso:country":"CN",
    "name:und_x_variant":[
        "Meitianhu Zhen"
    ],
    "name:zho_x_preferred":[
        "\u6885\u7530\u6e56"
    ],
    "name:zho_x_variant":[
        "\u6885\u7530\u6e56\u9547"
    ],
    "wof:name":"Meitianhu",
    "wof:placetype":"locality"
},
  "geometry": {"coordinates":[112.36194,29.52417],"type":"Point"}
}