{
  "type": "Feature",
  "properties": {
    "gn:admin1_code":"3.0",
    "gn:asciiname":"Jiangqiancun",
    "gn:country_code":"CN",
    "gn:dem":50,
    "gn:feature_class":"P",
    "gn:feature_code":"PPL",
    "gn:name":"Jiangqiancun",
    "gn:population":0,
    "gn:timezone":"Asia/Shanghai",
    "iso:country":"CN",
    "name:und_x_variant":[
        "\u6c5f\u524d\u6751"
    ],
    "wof:name":"Jiangqiancun",
    "wof:placetype":"locality"
},
  "geometry": {"coordinates":[116.58282,28.04825],"type":"Point"}
}