{
  "type": "Feature",
  "properties": {
    "gn:admin1_code":"15.0",
    "gn:asciiname":"Hulinbeihou",
    "gn:country_code":"CN",
    "gn:dem":2711,
    "gn:feature_class":"P",
    "gn:feature_code":"PPL",
    "gn:name":"Hulinbeihou",
    "gn:population":0,
    "gn:timezone":"Asia/Shanghai",
    "iso:country":"CN",
    "name:und_x_variant":[
        "\u62a4\u6797\u80cc\u540e"
    ],
    "wof:name":"Hulinbeihou",
    "wof:placetype":"locality"
},
  "geometry": {"coordinates":[104.44840000000001,34.32187],"type":"Point"}
}