{
  "type": "Feature",
  "properties": {
    "gn:admin1_code":"4.0",
    "gn:asciiname":"Dingtaixu",
    "gn:country_code":"CN",
    "gn:dem":5,
    "gn:feature_class":"P",
    "gn:feature_code":"PPL",
    "gn:name":"Dingtaixu",
    "gn:population":0,
    "gn:timezone":"Asia/Shanghai",
    "iso:country":"CN",
    "name:zho_x_preferred":[
        "\u9f0e\u6cf0\u5729"
    ],
    "wof:name":"Dingtaixu",
    "wof:placetype":"locality"
},
  "geometry": {"coordinates":[120.66217,31.95393],"type":"Point"}
}