{
  "type": "Feature",
  "properties": {
    "gn:admin1_code":"14",
    "gn:asciiname":"Labuzun",
    "gn:country_code":"CN",
    "gn:dem":4065,
    "gn:feature_class":"P",
    "gn:feature_code":"PPL",
    "gn:name":"Labuzun",
    "gn:population":0,
    "gn:timezone":"Asia/Urumqi",
    "iso:country":"CN",
    "name:zho_x_preferred":[
        "\u62c9\u5e03\u9075"
    ],
    "wof:name":"Labuzun",
    "wof:placetype":"locality"
},
  "geometry": {"coordinates":[89.27070000000001,29.4423],"type":"Point"}
}