{
  "type": "Feature",
  "properties": {
    "gn:country":"CN",
    "gn:fcode":"ADM3",
    "gn:population":0,
    "iso:country":"CN",
    "name:und_x_variant":[
        "Minhang"
    ],
    "name:zho_x_preferred":[
        "\u95fd\u884c\u533a"
    ],
    "name:zho_x_variant":[
        "\u95f5\u884c\u533a",
        "\u95fd\u884c"
    ],
    "qs:name":"Minxing Qu",
    "qs:photos_9r":0,
    "qs:photos_sr":0,
    "qs:pop_sr":"0",
    "wof:name":"Minxing Qu",
    "wof:placetype":"localadmin",
    "wof:population":0
},
  "geometry": {"coordinates":[121.42480999999999,31.08147],"type":"Point"}
}