{
  "type": "Feature",
  "properties": {
    "gn:admin1_code":"32.0",
    "gn:asciiname":"Xunjiashan",
    "gn:country_code":"CN",
    "gn:dem":728,
    "gn:feature_class":"P",
    "gn:feature_code":"PPL",
    "gn:name":"Xunjiashan",
    "gn:population":0,
    "gn:timezone":"Asia/Shanghai",
    "iso:country":"CN",
    "name:zho_x_preferred":[
        "\u8340\u5bb6\u5c71"
    ],
    "wof:name":"Xunjiashan",
    "wof:placetype":"locality"
},
  "geometry": {"coordinates":[102.93307,30.11893],"type":"Point"}
}