{
  "type": "Feature",
  "properties": {
    "gn:admin1_code":"29.0",
    "gn:asciiname":"Yangyushan",
    "gn:country_code":"CN",
    "gn:dem":2298,
    "gn:feature_class":"P",
    "gn:feature_code":"PPL",
    "gn:name":"Yangyushan",
    "gn:population":0,
    "gn:timezone":"Asia/Shanghai",
    "iso:country":"CN",
    "name:zho_x_preferred":[
        "\u6d0b\u828b\u5c71"
    ],
    "wof:name":"Yangyushan",
    "wof:placetype":"locality"
},
  "geometry": {"coordinates":[101.48999999999999,24.0516],"type":"Point"}
}