{
  "type": "Feature",
  "properties": {
    "gn:admin1_code":"10",
    "gn:asciiname":"Dongwen'an",
    "gn:country_code":"CN",
    "gn:dem":43,
    "gn:feature_class":"P",
    "gn:feature_code":"PPL",
    "gn:name":"Dongwen\u2019an",
    "gn:population":0,
    "gn:timezone":"Asia/Shanghai",
    "iso:country":"CN",
    "name:und_x_variant":[
        "Dongwen\u2019an"
    ],
    "name:zho_x_preferred":[
        "\u4e1c\u6587\u5b89"
    ],
    "wof:name":"Dongwen'an",
    "wof:placetype":"locality"
},
  "geometry": {"coordinates":[114.705,37.4661],"type":"Point"}
}