{
  "type": "Feature",
  "properties": {
    "gn:admin1_code":"24.0",
    "gn:asciiname":"Dong'erwa",
    "gn:country_code":"CN",
    "gn:dem":980,
    "gn:feature_class":"P",
    "gn:feature_code":"PPL",
    "gn:name":"Dong\u2019erwa",
    "gn:population":0,
    "gn:timezone":"Asia/Shanghai",
    "iso:country":"CN",
    "name:und_x_variant":[
        "Dong\u2019erwa"
    ],
    "name:zho_x_preferred":[
        "\u6d1e\u513f\u6d3c"
    ],
    "wof:name":"Dong'erwa",
    "wof:placetype":"locality"
},
  "geometry": {"coordinates":[111.60248,35.84216],"type":"Point"}
}