{
  "type": "Feature",
  "properties": {
    "gn:admin1_code":"3",
    "gn:asciiname":"Tangduli",
    "gn:country_code":"CN",
    "gn:dem":213,
    "gn:feature_class":"P",
    "gn:feature_code":"PPL",
    "gn:name":"Tangduli",
    "gn:population":0,
    "gn:timezone":"Asia/Shanghai",
    "iso:country":"CN",
    "name:zho_x_preferred":[
        "\u5858\u809a\u91cc"
    ],
    "wof:name":"Tangduli",
    "wof:placetype":"locality"
},
  "geometry": {"coordinates":[114.355,26.3939],"type":"Point"}
}