{
  "type": "Feature",
  "properties": {
    "gn:admin1_code":"26.0",
    "gn:asciiname":"Shiligou",
    "gn:country_code":"CN",
    "gn:dem":1258,
    "gn:feature_class":"P",
    "gn:feature_code":"PPL",
    "gn:name":"Shiligou",
    "gn:population":0,
    "gn:timezone":"Asia/Shanghai",
    "iso:country":"CN",
    "name:zho_x_preferred":[
        "\u5341\u91cc\u6c9f"
    ],
    "wof:name":"Shiligou",
    "wof:placetype":"locality"
},
  "geometry": {"coordinates":[109.76661,35.45539],"type":"Point"}
}