{
  "type": "Feature",
  "properties": {
    "gn:admin1_code":"26.0",
    "gn:asciiname":"Mao'ergoucun",
    "gn:country_code":"CN",
    "gn:dem":957,
    "gn:feature_class":"P",
    "gn:feature_code":"PPL",
    "gn:name":"Mao\u2019ergoucun",
    "gn:population":0,
    "gn:timezone":"Asia/Shanghai",
    "iso:country":"CN",
    "name:und_x_variant":[
        "Mao\u2019ergoucun"
    ],
    "name:zho_x_preferred":[
        "\u732b\u8033\u6c9f\u6751"
    ],
    "wof:name":"Mao'ergoucun",
    "wof:placetype":"locality"
},
  "geometry": {"coordinates":[109.05664,33.38063],"type":"Point"}
}