{
  "type": "Feature",
  "properties": {
    "gn:admin1_code":"2.0",
    "gn:asciiname":"Xiajiadou",
    "gn:country_code":"CN",
    "gn:dem":8,
    "gn:feature_class":"P",
    "gn:feature_code":"PPL",
    "gn:name":"Xiajiadou",
    "gn:population":0,
    "gn:timezone":"Asia/Shanghai",
    "iso:country":"CN",
    "name:und_x_variant":[
        "\u590f\u5bb6\u515c"
    ],
    "wof:name":"Xiajiadou",
    "wof:placetype":"locality"
},
  "geometry": {"coordinates":[120.56177,30.45437],"type":"Point"}
}