{
  "type": "Feature",
  "properties": {
    "gn:admin1_code":"29",
    "gn:asciiname":"Demike",
    "gn:country_code":"CN",
    "gn:dem":1699,
    "gn:feature_class":"P",
    "gn:feature_code":"PPL",
    "gn:name":"Demike",
    "gn:population":0,
    "gn:timezone":"Asia/Shanghai",
    "iso:country":"CN",
    "name:zho_x_preferred":[
        "\u5f97\u7c73\u514b"
    ],
    "wof:name":"Demike",
    "wof:placetype":"locality"
},
  "geometry": {"coordinates":[101.65300000000001,24.2201],"type":"Point"}
}