{
  "type": "Feature",
  "properties": {
    "gn:admin1_code":"26.0",
    "gn:asciiname":"Banchanggou",
    "gn:country_code":"CN",
    "gn:dem":1014,
    "gn:feature_class":"P",
    "gn:feature_code":"PPL",
    "gn:name":"Banchanggou",
    "gn:population":0,
    "gn:timezone":"Asia/Shanghai",
    "iso:country":"CN",
    "name:zho_x_preferred":[
        "\u534a\u5e38\u6c9f"
    ],
    "wof:name":"Banchanggou",
    "wof:placetype":"locality"
},
  "geometry": {"coordinates":[108.37287000000001,34.00675],"type":"Point"}
}