{
  "type": "Feature",
  "properties": {
    "gn:admin1_code":"07",
    "gn:asciiname":"Minzhu",
    "gn:country_code":"CN",
    "gn:dem":336,
    "gn:feature_class":"P",
    "gn:feature_code":"PPLA4",
    "gn:name":"Minzhu",
    "gn:population":0,
    "gn:timezone":"Asia/Shanghai",
    "iso:country":"CN",
    "name:und_x_variant":[
        "Minzhu Xiang",
        "\u6c11\u4e3b\u4e61"
    ],
    "name:zho_x_preferred":[
        "\u6c11\u4e3b"
    ],
    "wof:name":"Minzhu",
    "wof:placetype":"locality"
},
  "geometry": {"coordinates":[115.93979,25.00252],"type":"Point"}
}