{
  "type": "Feature",
  "properties": {
    "gn:admin1_code":"29",
    "gn:asciiname":"Tianchong",
    "gn:country_code":"CN",
    "gn:dem":1342,
    "gn:feature_class":"P",
    "gn:feature_code":"PPL",
    "gn:name":"Tianchong",
    "gn:population":0,
    "gn:timezone":"Asia/Shanghai",
    "iso:country":"CN",
    "name:zho_x_preferred":[
        "\u7530\u51b2"
    ],
    "wof:name":"Tianchong",
    "wof:placetype":"locality"
},
  "geometry": {"coordinates":[104.506,23.2153],"type":"Point"}
}