{
  "type": "Feature",
  "properties": {
    "gn:admin1_code":"14.0",
    "gn:asciiname":"Yidetong",
    "gn:country_code":"CN",
    "gn:dem":3762,
    "gn:feature_class":"P",
    "gn:feature_code":"PPL",
    "gn:name":"Yidetong",
    "gn:population":0,
    "gn:timezone":"Asia/Urumqi",
    "iso:country":"CN",
    "name:zho_x_preferred":[
        "\u4e49\u5f97\u540c"
    ],
    "wof:name":"Yidetong",
    "wof:placetype":"locality"
},
  "geometry": {"coordinates":[98.26492,29.00476],"type":"Point"}
}