{
  "type": "Feature",
  "properties": {
    "gn:admin1_code":"11.0",
    "gn:asciiname":"Laochongnao",
    "gn:country_code":"CN",
    "gn:dem":160,
    "gn:feature_class":"P",
    "gn:feature_code":"PPL",
    "gn:name":"Laochongnao",
    "gn:population":0,
    "gn:timezone":"Asia/Shanghai",
    "iso:country":"CN",
    "name:zho_x_preferred":[
        "\u8001\u51b2\u57b4"
    ],
    "wof:name":"Laochongnao",
    "wof:placetype":"locality"
},
  "geometry": {"coordinates":[110.04082,27.94298],"type":"Point"}
}