{
  "type": "Feature",
  "properties": {
    "gn:admin1_code":"29.0",
    "gn:asciiname":"Xiachibuge",
    "gn:country_code":"CN",
    "gn:dem":1799,
    "gn:feature_class":"P",
    "gn:feature_code":"PPL",
    "gn:name":"Xiachibuge",
    "gn:population":0,
    "gn:timezone":"Asia/Shanghai",
    "iso:country":"CN",
    "name:zho_x_preferred":[
        "\u4e0b\u6c60\u4e0d\u683c"
    ],
    "wof:name":"Xiachibuge",
    "wof:placetype":"locality"
},
  "geometry": {"coordinates":[104.114,24.5432],"type":"Point"}
}