{
  "type": "Feature",
  "properties": {
    "gn:admin1_code":"8.0",
    "gn:asciiname":"Susucun",
    "gn:country_code":"CN",
    "gn:dem":75,
    "gn:feature_class":"P",
    "gn:feature_code":"PPL",
    "gn:name":"Susucun",
    "gn:population":0,
    "gn:timezone":"Asia/Shanghai",
    "iso:country":"CN",
    "name:zho_x_preferred":[
        "\u82cf\u82cf\u6751"
    ],
    "wof:name":"Susucun",
    "wof:placetype":"locality"
},
  "geometry": {"coordinates":[130.65674999999999,47.0132],"type":"Point"}
}