{
  "type": "Feature",
  "properties": {
    "gn:admin1_code":"15.0",
    "gn:asciiname":"Choujiawan",
    "gn:country_code":"CN",
    "gn:dem":1932,
    "gn:feature_class":"P",
    "gn:feature_code":"PPL",
    "gn:name":"Choujiawan",
    "gn:population":0,
    "gn:timezone":"Asia/Shanghai",
    "iso:country":"CN",
    "name:und_x_variant":[
        "\u4ec7\u5bb6\u6e7e"
    ],
    "wof:name":"Choujiawan",
    "wof:placetype":"locality"
},
  "geometry": {"coordinates":[105.33148,35.34387],"type":"Point"}
}