{
  "type": "Feature",
  "properties": {
    "gn:admin1_code":"18.0",
    "gn:asciiname":"Peiji",
    "gn:country_code":"CN",
    "gn:dem":805,
    "gn:feature_class":"P",
    "gn:feature_code":"PPL",
    "gn:name":"Peiji",
    "gn:population":0,
    "gn:timezone":"Asia/Shanghai",
    "iso:country":"CN",
    "name:zho_x_preferred":[
        "\u57f9\u57fa"
    ],
    "wof:name":"Peiji",
    "wof:placetype":"locality"
},
  "geometry": {"coordinates":[108.78700000000001,26.4875],"type":"Point"}
}