{
  "type": "Feature",
  "properties": {
    "gn:admin1_code":"2.0",
    "gn:asciiname":"Shuzhuang",
    "gn:country_code":"CN",
    "gn:dem":172,
    "gn:feature_class":"P",
    "gn:feature_code":"PPL",
    "gn:name":"Shuzhuang",
    "gn:population":0,
    "gn:timezone":"Asia/Shanghai",
    "iso:country":"CN",
    "name:zho_x_preferred":[
        "\u8212\u5e84"
    ],
    "wof:name":"Shuzhuang",
    "wof:placetype":"locality"
},
  "geometry": {"coordinates":[118.95116000000002,28.84284],"type":"Point"}
}