{
  "type": "Feature",
  "properties": {
    "gn:admin1_code":"12.0",
    "gn:asciiname":"Wanghuashan",
    "gn:country_code":"CN",
    "gn:dem":63,
    "gn:feature_class":"P",
    "gn:feature_code":"PPL",
    "gn:name":"Wanghuashan",
    "gn:population":0,
    "gn:timezone":"Asia/Shanghai",
    "iso:country":"CN",
    "name:zho_x_preferred":[
        "Wanghuashan"
    ],
    "name:zho_x_variant":[
        "\u671b\u82b1\u5c71"
    ],
    "wof:name":"Wanghuashan",
    "wof:placetype":"locality"
},
  "geometry": {"coordinates":[115.00845,30.98824],"type":"Point"}
}