{
  "type": "Feature",
  "properties": {
    "gn:admin1_code":"02",
    "gn:asciiname":"Shangshacun",
    "gn:country_code":"CN",
    "gn:dem":5,
    "gn:feature_class":"P",
    "gn:feature_code":"PPL",
    "gn:name":"Shangshacun",
    "gn:population":0,
    "gn:timezone":"Asia/Shanghai",
    "iso:country":"CN",
    "name:und_x_variant":[
        "Shangsha",
        "Shangshacun"
    ],
    "name:zho_x_preferred":[
        "\u4e0a\u6c99"
    ],
    "name:zho_x_variant":[
        "\u4e0a\u6c99\u6751"
    ],
    "wof:name":"Shangshacun",
    "wof:placetype":"locality"
},
  "geometry": {"coordinates":[120.74312999999999,28.01861],"type":"Point"}
}