{
  "type": "Feature",
  "properties": {
    "gn:admin1_code":"3.0",
    "gn:asciiname":"Zoufang",
    "gn:country_code":"CN",
    "gn:dem":159,
    "gn:feature_class":"P",
    "gn:feature_code":"PPL",
    "gn:name":"Zoufang",
    "gn:population":0,
    "gn:timezone":"Asia/Shanghai",
    "iso:country":"CN",
    "name:und_x_variant":[
        "\u90b9\u574a"
    ],
    "wof:name":"Zoufang",
    "wof:placetype":"locality"
},
  "geometry": {"coordinates":[116.21751,27.36734],"type":"Point"}
}