{
  "type": "Feature",
  "properties": {
    "gn:admin1_code":"11.0",
    "gn:asciiname":"Huangtutang",
    "gn:country_code":"CN",
    "gn:dem":546,
    "gn:feature_class":"P",
    "gn:feature_code":"PPL",
    "gn:name":"Huangtutang",
    "gn:population":0,
    "gn:timezone":"Asia/Shanghai",
    "iso:country":"CN",
    "name:zho_x_preferred":[
        "\u9ec4\u571f\u5858"
    ],
    "wof:name":"Huangtutang",
    "wof:placetype":"locality"
},
  "geometry": {"coordinates":[113.27871,25.52396],"type":"Point"}
}