{
  "type": "Feature",
  "properties": {
    "gn:admin1_code":"18",
    "gn:asciiname":"Heishan",
    "gn:country_code":"CN",
    "gn:dem":1276,
    "gn:feature_class":"P",
    "gn:feature_code":"PPL",
    "gn:name":"Heishan",
    "gn:population":0,
    "gn:timezone":"Asia/Shanghai",
    "iso:country":"CN",
    "name:zho_x_preferred":[
        "\u9ed1\u5c71"
    ],
    "wof:name":"Heishan",
    "wof:placetype":"locality"
},
  "geometry": {"coordinates":[106.15300000000001,26.1647],"type":"Point"}
}