{
  "type": "Feature",
  "properties": {
    "gn:admin1_code":"24.0",
    "gn:asciiname":"Nanjiabu",
    "gn:country_code":"CN",
    "gn:dem":1073,
    "gn:feature_class":"P",
    "gn:feature_code":"PPL",
    "gn:name":"Nanjiabu",
    "gn:population":0,
    "gn:timezone":"Asia/Shanghai",
    "iso:country":"CN",
    "name:und_x_variant":[
        "\u5357\u5bb6\u5821"
    ],
    "wof:name":"Nanjiabu",
    "wof:placetype":"locality"
},
  "geometry": {"coordinates":[112.83441999999999,39.67859],"type":"Point"}
}