{
  "type": "Feature",
  "properties": {
    "gn:admin1_code":"25",
    "gn:asciiname":"Wangguantun",
    "gn:country_code":"CN",
    "gn:dem":35,
    "gn:feature_class":"P",
    "gn:feature_code":"PPL",
    "gn:name":"Wangguantun",
    "gn:population":0,
    "gn:timezone":"Asia/Shanghai",
    "iso:country":"CN",
    "name:und_x_variant":[
        "Wangtun"
    ],
    "name:zho_x_preferred":[
        "\u738b\u5b98\u5c6f"
    ],
    "name:zho_x_variant":[
        "\u738b\u5c6f"
    ],
    "wof:name":"Wangguantun",
    "wof:placetype":"locality"
},
  "geometry": {"coordinates":[115.99191,36.49753],"type":"Point"}
}