{
  "type": "Feature",
  "properties": {
    "gn:admin1_code":"19.0",
    "gn:asciiname":"Chaganchaolaotai",
    "gn:country_code":"CN",
    "gn:dem":291,
    "gn:feature_class":"P",
    "gn:feature_code":"PPL",
    "gn:name":"Chaganchaolaotai",
    "gn:population":0,
    "gn:timezone":"Asia/Shanghai",
    "iso:country":"CN",
    "name:und_x_variant":[
        "\u67e5\u5e72\u671d\u8001\u53f0"
    ],
    "name:zho_x_preferred":[
        "\u67e5\u5e72\u671d\u8001\u53f0"
    ],
    "wof:name":"Chaganchaolaotai",
    "wof:placetype":"locality"
},
  "geometry": {"coordinates":[121.73061,42.39385],"type":"Point"}
}