{
  "type": "Feature",
  "properties": {
    "gn:admin1_code":"05",
    "gn:asciiname":"Zhangjiawopu",
    "gn:cc2":"CN",
    "gn:country_code":"CN",
    "gn:dem":151,
    "gn:feature_class":"P",
    "gn:feature_code":"PPL",
    "gn:name":"Zhangjiawopu",
    "gn:population":0,
    "gn:timezone":"Asia/Shanghai",
    "iso:country":"CN",
    "name:und_x_variant":[
        "Chang-chia-wo-p\u2019u",
        "Zhangjiawopu"
    ],
    "wof:name":"Zhangjiawopu",
    "wof:placetype":"locality"
},
  "geometry": {"coordinates":[122.59999999999999,45.18333],"type":"Point"}
}