{
  "type": "Feature",
  "properties": {
    "gn:admin1_code":"10.0",
    "gn:asciiname":"Zhengpantai",
    "gn:country_code":"CN",
    "gn:dem":1259,
    "gn:feature_class":"P",
    "gn:feature_code":"PPL",
    "gn:name":"Zhengpantai",
    "gn:population":0,
    "gn:timezone":"Asia/Shanghai",
    "iso:country":"CN",
    "name:zho_x_preferred":[
        "\u6b63\u76d8\u53f0"
    ],
    "wof:name":"Zhengpantai",
    "wof:placetype":"locality"
},
  "geometry": {"coordinates":[115.41436000000002,40.76978],"type":"Point"}
}