{
  "type": "Feature",
  "properties": {
    "gn:admin1_code":"1.0",
    "gn:asciiname":"Chengshoucun",
    "gn:country_code":"CN",
    "gn:dem":65,
    "gn:feature_class":"P",
    "gn:feature_code":"PPL",
    "gn:name":"Chengshoucun",
    "gn:population":0,
    "gn:timezone":"Asia/Shanghai",
    "iso:country":"CN",
    "name:zho_x_preferred":[
        "\u6210\u719f\u6751"
    ],
    "wof:name":"Chengshoucun",
    "wof:placetype":"locality"
},
  "geometry": {"coordinates":[118.77692,30.7879],"type":"Point"}
}