{
  "type": "Feature",
  "properties": {
    "gn:admin1_code":"4.0",
    "gn:asciiname":"Weizhuang",
    "gn:country_code":"CN",
    "gn:dem":2,
    "gn:feature_class":"P",
    "gn:feature_code":"PPL",
    "gn:name":"Weizhuang",
    "gn:population":0,
    "gn:timezone":"Asia/Shanghai",
    "iso:country":"CN",
    "name:und_x_variant":[
        "\u9b4f\u5e84",
        "Linhu",
        "Wei-chuang",
        "Wei-chia-chuang",
        "\u6797\u6e56"
    ],
    "wof:name":"Weizhuang",
    "wof:placetype":"locality"
},
  "geometry": {"coordinates":[120.02206,32.99493],"type":"Point"}
}