{
  "type": "Feature",
  "properties": {
    "gn:admin1_code":"19.0",
    "gn:asciiname":"Tuhulucun",
    "gn:country_code":"CN",
    "gn:dem":130,
    "gn:feature_class":"P",
    "gn:feature_code":"PPL",
    "gn:name":"Tuhulucun",
    "gn:population":0,
    "gn:timezone":"Asia/Shanghai",
    "iso:country":"CN",
    "name:zho_x_preferred":[
        "\u5410\u547c\u9c81\u6751"
    ],
    "wof:name":"Tuhulucun",
    "wof:placetype":"locality"
},
  "geometry": {"coordinates":[121.53100000000001,41.9165],"type":"Point"}
}