{
  "type": "Feature",
  "properties": {
    "gn:admin1_code":"26.0",
    "gn:asciiname":"Taoxigou",
    "gn:country_code":"CN",
    "gn:dem":1032,
    "gn:feature_class":"P",
    "gn:feature_code":"PPL",
    "gn:name":"Taoxigou",
    "gn:population":0,
    "gn:timezone":"Asia/Shanghai",
    "iso:country":"CN",
    "name:und_x_variant":[
        "\u6843\u897f\u6c9f"
    ],
    "wof:name":"Taoxigou",
    "wof:placetype":"locality"
},
  "geometry": {"coordinates":[107.92829,33.31717],"type":"Point"}
}