{
  "type": "Feature",
  "properties": {
    "gn:admin1_code":"10",
    "gn:asciiname":"Qianshudi",
    "gn:country_code":"CN",
    "gn:dem":809,
    "gn:feature_class":"P",
    "gn:feature_code":"PPL",
    "gn:name":"Qianshudi",
    "gn:population":0,
    "gn:timezone":"Asia/Shanghai",
    "iso:country":"CN",
    "name:zho_x_preferred":[
        "\u5343\u6811\u5e95"
    ],
    "wof:name":"Qianshudi",
    "wof:placetype":"locality"
},
  "geometry": {"coordinates":[115.22887,39.93557],"type":"Point"}
}