{
  "type": "Feature",
  "properties": {
    "gn:admin1_code":"29",
    "gn:asciiname":"Yunengde",
    "gn:country_code":"CN",
    "gn:dem":1082,
    "gn:feature_class":"P",
    "gn:feature_code":"PPL",
    "gn:name":"Yunengde",
    "gn:population":0,
    "gn:timezone":"Asia/Shanghai",
    "iso:country":"CN",
    "name:zho_x_preferred":[
        "\u9c7c\u80fd\u5f97"
    ],
    "wof:name":"Yunengde",
    "wof:placetype":"locality"
},
  "geometry": {"coordinates":[101.717,23.9349],"type":"Point"}
}