{
  "type": "Feature",
  "properties": {
    "gn:admin1_code":"29.0",
    "gn:asciiname":"Liangshan",
    "gn:country_code":"CN",
    "gn:dem":2051,
    "gn:feature_class":"P",
    "gn:feature_code":"PPL",
    "gn:name":"Liangshan",
    "gn:population":0,
    "gn:timezone":"Asia/Shanghai",
    "iso:country":"CN",
    "name:ceb_x_preferred":[
        "Liangshan"
    ],
    "name:deu_x_preferred":[
        "Liangshan"
    ],
    "name:fra_x_preferred":[
        "Liangshan"
    ],
    "name:nor_x_preferred":[
        "Liangshan"
    ],
    "name:pol_x_preferred":[
        "Liangshan"
    ],
    "name:swe_x_preferred":[
        "Liangshan"
    ],
    "name:zho_x_preferred":[
        "\u4eae\u5c71"
    ],
    "wof:name":"Liangshan",
    "wof:placetype":"locality"
},
  "geometry": {"coordinates":[99.6721,23.0991],"type":"Point"}
}