{
  "type": "Feature",
  "properties": {
    "gn:admin1_code":"12.0",
    "gn:asciiname":"Yuanzizhou",
    "gn:country_code":"CN",
    "gn:dem":26,
    "gn:feature_class":"P",
    "gn:feature_code":"PPL",
    "gn:name":"Yuanzizhou",
    "gn:population":0,
    "gn:timezone":"Asia/Shanghai",
    "iso:country":"CN",
    "name:zho_x_preferred":[
        "\u57b8\u5b50\u6d32"
    ],
    "wof:name":"Yuanzizhou",
    "wof:placetype":"locality"
},
  "geometry": {"coordinates":[113.61587,29.8648],"type":"Point"}
}