{
  "type": "Feature",
  "properties": {
    "gn:admin1_code":"24.0",
    "gn:asciiname":"Caogoubu",
    "gn:country_code":"CN",
    "gn:dem":1299,
    "gn:feature_class":"P",
    "gn:feature_code":"PPL",
    "gn:name":"Caogoubu",
    "gn:population":0,
    "gn:timezone":"Asia/Shanghai",
    "iso:country":"CN",
    "name:und_x_variant":[
        "\u8349\u6c9f\u5821"
    ],
    "name:zho_x_preferred":[
        "\u8349\u6c9f\u5821"
    ],
    "wof:name":"Caogoubu",
    "wof:placetype":"locality"
},
  "geometry": {"coordinates":[112.36382999999999,40.10365],"type":"Point"}
}