{
  "type": "Feature",
  "properties": {
    "gn:admin1_code":"16.0",
    "gn:asciiname":"Jiuxian",
    "gn:country_code":"CN",
    "gn:dem":512,
    "gn:feature_class":"P",
    "gn:feature_code":"PPL",
    "gn:name":"Jiuxian",
    "gn:population":0,
    "gn:timezone":"Asia/Shanghai",
    "iso:country":"CN",
    "name:zho_x_preferred":[
        "\u65e7\u53bf"
    ],
    "wof:name":"Jiuxian",
    "wof:placetype":"locality"
},
  "geometry": {"coordinates":[108.97799999999999,25.146],"type":"Point"}
}