{
  "type": "Feature",
  "properties": {
    "gn:admin1_code":"21.0",
    "gn:asciiname":"Xinjing",
    "gn:country_code":"CN",
    "gn:dem":1241,
    "gn:feature_class":"P",
    "gn:feature_code":"PPL",
    "gn:name":"Xinjing",
    "gn:population":0,
    "gn:timezone":"Asia/Shanghai",
    "iso:country":"CN",
    "name:zho_x_preferred":[
        "\u65b0\u4e95"
    ],
    "wof:name":"Xinjing",
    "wof:placetype":"locality"
},
  "geometry": {"coordinates":[106.468,37.7315],"type":"Point"}
}