{
  "type": "Feature",
  "properties": {
    "gn:admin1_code":"26.0",
    "gn:asciiname":"Qingqiu",
    "gn:country_code":"CN",
    "gn:dem":504,
    "gn:feature_class":"P",
    "gn:feature_code":"PPL",
    "gn:name":"Qingqiu",
    "gn:population":0,
    "gn:timezone":"Asia/Shanghai",
    "iso:country":"CN",
    "name:und_x_variant":[
        "\u6e05\u6e6b"
    ],
    "wof:name":"Qingqiu",
    "wof:placetype":"locality"
},
  "geometry": {"coordinates":[107.83741000000001,34.21937],"type":"Point"}
}