{
  "type": "Feature",
  "properties": {
    "gn:admin1_code":"10",
    "gn:asciiname":"Shuang'aitang",
    "gn:country_code":"CN",
    "gn:dem":1390,
    "gn:feature_class":"P",
    "gn:feature_code":"PPL",
    "gn:name":"Shuang\u2019aitang",
    "gn:population":0,
    "gn:timezone":"Asia/Shanghai",
    "iso:country":"CN",
    "name:und_x_variant":[
        "Shuang\u2019aitang"
    ],
    "name:zho_x_preferred":[
        "\u53cc\u7231\u5802"
    ],
    "wof:name":"Shuang'aitang",
    "wof:placetype":"locality"
},
  "geometry": {"coordinates":[115.06399,41.42357],"type":"Point"}
}