{
  "type": "Feature",
  "properties": {
    "gn:admin1_code":"9.0",
    "gn:asciiname":"Daijiangou",
    "gn:country_code":"CN",
    "gn:dem":255,
    "gn:feature_class":"P",
    "gn:feature_code":"PPL",
    "gn:name":"Daijiangou",
    "gn:population":0,
    "gn:timezone":"Asia/Shanghai",
    "iso:country":"CN",
    "name:zho_x_preferred":[
        "\u5e26\u7bad\u6c9f"
    ],
    "wof:name":"Daijiangou",
    "wof:placetype":"locality"
},
  "geometry": {"coordinates":[114.37072000000001,31.74818],"type":"Point"}
}