{
  "type": "Feature",
  "properties": {
    "gn:admin1_code":"21.0",
    "gn:asciiname":"Zhangjiaxiaohe",
    "gn:country_code":"CN",
    "gn:dem":1788,
    "gn:feature_class":"P",
    "gn:feature_code":"PPL",
    "gn:name":"Zhangjiaxiaohe",
    "gn:population":0,
    "gn:timezone":"Asia/Shanghai",
    "iso:country":"CN",
    "name:zho_x_preferred":[
        "\u5f20\u5bb6\u5c0f\u6cb3"
    ],
    "wof:name":"Zhangjiaxiaohe",
    "wof:placetype":"locality"
},
  "geometry": {"coordinates":[105.88894999999999,35.55432000000001],"type":"Point"}
}