{
  "type": "Feature",
  "properties": {
    "gn:admin1_code":"25",
    "gn:asciiname":"Nansongzhuang",
    "gn:country_code":"CN",
    "gn:dem":44,
    "gn:feature_class":"P",
    "gn:feature_code":"PPL",
    "gn:name":"Nansongzhuang",
    "gn:population":0,
    "gn:timezone":"Asia/Shanghai",
    "iso:country":"CN",
    "name:zho_x_preferred":[
        "\u5357\u5b8b\u5e84"
    ],
    "wof:name":"Nansongzhuang",
    "wof:placetype":"locality"
},
  "geometry": {"coordinates":[117.126,34.9013],"type":"Point"}
}