{
  "type": "Feature",
  "properties": {
    "gn:admin1_code":"10.0",
    "gn:asciiname":"Zhaolingzhuang",
    "gn:country_code":"CN",
    "gn:dem":4,
    "gn:feature_class":"P",
    "gn:feature_code":"PPL",
    "gn:name":"Zhaolingzhuang",
    "gn:population":0,
    "gn:timezone":"Asia/Shanghai",
    "iso:country":"CN",
    "name:zho_x_preferred":[
        "\u8d75\u7fce\u5e84"
    ],
    "wof:name":"Zhaolingzhuang",
    "wof:placetype":"locality"
},
  "geometry": {"coordinates":[117.97751,39.44995],"type":"Point"}
}