{
  "type": "Feature",
  "properties": {
    "gn:admin1_code":"30",
    "gn:asciiname":"Doucun",
    "gn:country_code":"CN",
    "gn:dem":54,
    "gn:feature_class":"P",
    "gn:feature_code":"PPL",
    "gn:name":"Doucun",
    "gn:population":0,
    "gn:timezone":"Asia/Urumqi",
    "iso:country":"CN",
    "name:zho_x_preferred":[
        "\u8c46\u6751"
    ],
    "wof:name":"Doucun",
    "wof:placetype":"locality"
},
  "geometry": {"coordinates":[110.45112,21.71992],"type":"Point"}
}