{
  "type": "Feature",
  "properties": {
    "gn:admin1_code":"4.0",
    "gn:asciiname":"Hangqiao",
    "gn:country_code":"CN",
    "gn:dem":4,
    "gn:feature_class":"P",
    "gn:feature_code":"PPL",
    "gn:name":"Hangqiao",
    "gn:population":0,
    "gn:timezone":"Asia/Shanghai",
    "iso:country":"CN",
    "name:zho_x_preferred":[
        "\u676d\u6865"
    ],
    "wof:name":"Hangqiao",
    "wof:placetype":"locality"
},
  "geometry": {"coordinates":[120.65107999999999,32.43676],"type":"Point"}
}