{
  "type": "Feature",
  "properties": {
    "gn:admin1_code":"14.0",
    "gn:asciiname":"Woinbodol",
    "gn:country_code":"CN",
    "gn:dem":3149,
    "gn:feature_class":"P",
    "gn:feature_code":"PPL",
    "gn:name":"Woinbodol",
    "gn:population":0,
    "gn:timezone":"Asia/Urumqi",
    "iso:country":"CN",
    "name:bod_x_preferred":[
        "Woinbodol"
    ],
    "name:msa_x_preferred":[
        "Woinbodol"
    ],
    "name:und_x_variant":[
        "Jiga",
        "\u5409\u560e"
    ],
    "name:zho_x_preferred":[
        "Wangbudui"
    ],
    "name:zho_x_variant":[
        "\u6c6a\u5e03\u5806"
    ],
    "wof:name":"Woinbodol",
    "wof:placetype":"locality"
},
  "geometry": {"coordinates":[98.401,31.901],"type":"Point"}
}