{
  "type": "Feature",
  "properties": {
    "gn:admin1_code":"25",
    "gn:asciiname":"Miaojiazhuang",
    "gn:country_code":"CN",
    "gn:dem":56,
    "gn:feature_class":"P",
    "gn:feature_code":"PPL",
    "gn:name":"Miaojiazhuang",
    "gn:population":0,
    "gn:timezone":"Asia/Shanghai",
    "iso:country":"CN",
    "name:zho_x_preferred":[
        "\u82d7\u5bb6\u5e84"
    ],
    "wof:name":"Miaojiazhuang",
    "wof:placetype":"locality"
},
  "geometry": {"coordinates":[118.06699999999999,34.9307],"type":"Point"}
}