{
  "type": "Feature",
  "properties": {
    "gn:admin1_code":"30",
    "gn:asciiname":"Damaping",
    "gn:country_code":"CN",
    "gn:dem":218,
    "gn:feature_class":"P",
    "gn:feature_code":"PPL",
    "gn:name":"Damaping",
    "gn:population":0,
    "gn:timezone":"Asia/Shanghai",
    "iso:country":"CN",
    "name:zho_x_preferred":[
        "\u6253\u9a6c\u576a"
    ],
    "wof:name":"Damaping",
    "wof:placetype":"locality"
},
  "geometry": {"coordinates":[116.04548,24.42458],"type":"Point"}
}