{
  "type": "Feature",
  "properties": {
    "gn:admin1_code":"7.0",
    "gn:asciiname":"Huangxiqiao",
    "gn:country_code":"CN",
    "gn:dem":560,
    "gn:feature_class":"P",
    "gn:feature_code":"PPL",
    "gn:name":"Huangxiqiao",
    "gn:population":0,
    "gn:timezone":"Asia/Shanghai",
    "iso:country":"CN",
    "name:zho_x_preferred":[
        "\u9ec4\u897f\u6865"
    ],
    "wof:name":"Huangxiqiao",
    "wof:placetype":"locality"
},
  "geometry": {"coordinates":[116.14400999999999,25.55627],"type":"Point"}
}