{
  "type": "Feature",
  "properties": {
    "gn:admin1_code":"1.0",
    "gn:asciiname":"Heloucun",
    "gn:country_code":"CN",
    "gn:dem":29,
    "gn:feature_class":"P",
    "gn:feature_code":"PPL",
    "gn:name":"Heloucun",
    "gn:population":0,
    "gn:timezone":"Asia/Shanghai",
    "iso:country":"CN",
    "name:zho_x_preferred":[
        "\u4f55\u697c\u6751"
    ],
    "wof:name":"Heloucun",
    "wof:placetype":"locality"
},
  "geometry": {"coordinates":[116.50526000000001,33.26589],"type":"Point"}
}