{
  "type": "Feature",
  "properties": {
    "gn:admin1_code":"29.0",
    "gn:asciiname":"Dabingnong",
    "gn:country_code":"CN",
    "gn:dem":1302,
    "gn:feature_class":"P",
    "gn:feature_code":"PPL",
    "gn:name":"Dabingnong",
    "gn:population":0,
    "gn:timezone":"Asia/Shanghai",
    "iso:country":"CN",
    "name:zho_x_preferred":[
        "\u5927\u4e19\u5f04"
    ],
    "wof:name":"Dabingnong",
    "wof:placetype":"locality"
},
  "geometry": {"coordinates":[100.182,24.5323],"type":"Point"}
}