{
  "type": "Feature",
  "properties": {
    "gn:admin1_code":"16.0",
    "gn:asciiname":"Songbailin",
    "gn:country_code":"CN",
    "gn:dem":8,
    "gn:feature_class":"P",
    "gn:feature_code":"PPL",
    "gn:name":"Songbailin",
    "gn:population":0,
    "gn:timezone":"Asia/Shanghai",
    "iso:country":"CN",
    "name:zho_x_preferred":[
        "\u677e\u67cf\u6797"
    ],
    "wof:name":"Songbailin",
    "wof:placetype":"locality"
},
  "geometry": {"coordinates":[108.518,21.6447],"type":"Point"}
}