{
  "type": "Feature",
  "properties": {
    "gn:admin1_code":"9.0",
    "gn:asciiname":"Tongshuyuan",
    "gn:country_code":"CN",
    "gn:dem":964,
    "gn:feature_class":"P",
    "gn:feature_code":"PPL",
    "gn:name":"Tongshuyuan",
    "gn:population":0,
    "gn:timezone":"Asia/Shanghai",
    "iso:country":"CN",
    "name:zho_x_preferred":[
        "\u6850\u6811\u56ed"
    ],
    "wof:name":"Tongshuyuan",
    "wof:placetype":"locality"
},
  "geometry": {"coordinates":[111.44801,34.06002],"type":"Point"}
}