{
  "type": "Feature",
  "properties": {
    "gn:admin1_code":"25",
    "gn:asciiname":"Liujiacaiyuanjie",
    "gn:country_code":"CN",
    "gn:dem":105,
    "gn:feature_class":"P",
    "gn:feature_code":"PPL",
    "gn:name":"Liujiacaiyuanjie",
    "gn:population":0,
    "gn:timezone":"Asia/Shanghai",
    "iso:country":"CN",
    "name:zho_x_preferred":[
        "\u5218\u5bb6\u83dc\u56ed\u8857"
    ],
    "wof:name":"Liujiacaiyuanjie",
    "wof:placetype":"locality"
},
  "geometry": {"coordinates":[118.825,35.5696],"type":"Point"}
}