{
  "type": "Feature",
  "properties": {
    "gn:admin1_code":"25",
    "gn:asciiname":"Zhengjiapo",
    "gn:country_code":"CN",
    "gn:dem":7,
    "gn:feature_class":"P",
    "gn:feature_code":"PPL",
    "gn:name":"Zhengjiapo",
    "gn:population":0,
    "gn:timezone":"Asia/Shanghai",
    "iso:country":"CN",
    "name:zho_x_preferred":[
        "\u90d1\u5bb6\u5761"
    ],
    "wof:name":"Zhengjiapo",
    "wof:placetype":"locality"
},
  "geometry": {"coordinates":[119.584,36.8758],"type":"Point"}
}