{
  "type": "Feature",
  "properties": {
    "gn:admin1_code":"33",
    "gn:asciiname":"Yunlong",
    "gn:country_code":"CN",
    "gn:dem":440,
    "gn:feature_class":"P",
    "gn:feature_code":"PPLA4",
    "gn:name":"Yunlong",
    "gn:population":0,
    "gn:timezone":"Asia/Shanghai",
    "iso:country":"CN",
    "name:ceb_x_preferred":[
        "Yunlong"
    ],
    "name:deu_x_preferred":[
        "Yunlong"
    ],
    "name:fra_x_preferred":[
        "Yunlong"
    ],
    "name:rus_x_preferred":[
        "\u042e\u043d\u044c\u043b\u0443\u043d"
    ],
    "name:swe_x_preferred":[
        "Yunlong"
    ],
    "name:und_x_variant":[
        "Shayachang",
        "Yunlong Zhen"
    ],
    "name:zho_x_preferred":[
        "\u4e91\u9f99"
    ],
    "name:zho_x_variant":[
        "\u6c99\u57ad\u573a",
        "\u4e91\u9f99\u9547"
    ],
    "wof:name":"Yunlong",
    "wof:placetype":"locality"
},
  "geometry": {"coordinates":[107.64196,30.5228],"type":"Point"}
}