{
  "type": "Feature",
  "properties": {
    "gn:admin1_code":"01",
    "gn:asciiname":"Lihen",
    "gn:country_code":"CN",
    "gn:dem":96,
    "gn:feature_class":"P",
    "gn:feature_code":"PPLA4",
    "gn:name":"Lihen",
    "gn:population":0,
    "gn:timezone":"Asia/Shanghai",
    "iso:country":"CN",
    "name:und_x_variant":[
        "Li-an",
        "Lihen",
        "\u9ece\u75d5",
        "Li\u2019an Xiang",
        "\u5229\u5b89\u4e61"
    ],
    "wof:name":"Lihen",
    "wof:placetype":"locality"
},
  "geometry": {"coordinates":[116.99223000000001,29.75416],"type":"Point"}
}