{
  "type": "Feature",
  "properties": {
    "gn:admin1_code":"14.0",
    "gn:asciiname":"Tarenda",
    "gn:country_code":"CN",
    "gn:dem":3983,
    "gn:feature_class":"P",
    "gn:feature_code":"PPL",
    "gn:name":"Tarenda",
    "gn:population":0,
    "gn:timezone":"Asia/Urumqi",
    "iso:country":"CN",
    "name:zho_x_preferred":[
        "\u5b83\u4ec1\u8fbe"
    ],
    "wof:name":"Tarenda",
    "wof:placetype":"locality"
},
  "geometry": {"coordinates":[95.72477000000001,31.43863],"type":"Point"}
}