{
  "type": "Feature",
  "properties": {
    "gn:admin1_code":"26.0",
    "gn:asciiname":"Wolong",
    "gn:country_code":"CN",
    "gn:dem":724,
    "gn:feature_class":"P",
    "gn:feature_code":"PPL",
    "gn:name":"Wolong",
    "gn:population":0,
    "gn:timezone":"Asia/Shanghai",
    "iso:country":"CN",
    "name:ceb_x_preferred":[
        "Wolong"
    ],
    "name:deu_x_preferred":[
        "Wolong"
    ],
    "name:fra_x_preferred":[
        "Wolong"
    ],
    "name:und_x_variant":[
        "\u5367\u9f99"
    ],
    "name:vie_x_preferred":[
        "Ng\u1ecda Long"
    ],
    "wof:name":"Wolong",
    "wof:placetype":"locality"
},
  "geometry": {"coordinates":[107.47451,34.44761],"type":"Point"}
}