{
  "type": "Feature",
  "properties": {
    "gn:admin1_code":"1.0",
    "gn:asciiname":"Guanshancun",
    "gn:country_code":"CN",
    "gn:dem":54,
    "gn:feature_class":"P",
    "gn:feature_code":"PPL",
    "gn:name":"Guanshancun",
    "gn:population":0,
    "gn:timezone":"Asia/Shanghai",
    "iso:country":"CN",
    "name:zho_x_preferred":[
        "\u5173\u5c71\u6751"
    ],
    "wof:name":"Guanshancun",
    "wof:placetype":"locality"
},
  "geometry": {"coordinates":[118.18883999999998,32.31225999999999],"type":"Point"}
}