{
  "type": "Feature",
  "properties": {
    "gn:admin1_code":"12.0",
    "gn:asciiname":"Guantianba",
    "gn:country_code":"CN",
    "gn:dem":702,
    "gn:feature_class":"P",
    "gn:feature_code":"PPL",
    "gn:name":"Guantianba",
    "gn:population":0,
    "gn:timezone":"Asia/Shanghai",
    "iso:country":"CN",
    "name:zho_x_preferred":[
        "Guantianba"
    ],
    "name:zho_x_variant":[
        "\u5b98\u7530\u575d"
    ],
    "wof:name":"Guantianba",
    "wof:placetype":"locality"
},
  "geometry": {"coordinates":[109.23065,29.75894000000001],"type":"Point"}
}