{
  "type": "Feature",
  "properties": {
    "gn:admin1_code":"10.0",
    "gn:asciiname":"Dalongmen",
    "gn:country_code":"CN",
    "gn:dem":471,
    "gn:feature_class":"P",
    "gn:feature_code":"PPL",
    "gn:name":"Dalongmen",
    "gn:population":0,
    "gn:timezone":"Asia/Shanghai",
    "iso:country":"CN",
    "name:zho_x_preferred":[
        "\u5927\u9f99\u95e8"
    ],
    "wof:name":"Dalongmen",
    "wof:placetype":"locality"
},
  "geometry": {"coordinates":[115.36078000000001,39.8382],"type":"Point"}
}