{
  "type": "Feature",
  "properties": {
    "gn:admin1_code":"8.0",
    "gn:asciiname":"Liufutun",
    "gn:country_code":"CN",
    "gn:dem":214,
    "gn:feature_class":"P",
    "gn:feature_code":"PPL",
    "gn:name":"Liufutun",
    "gn:population":0,
    "gn:timezone":"Asia/Shanghai",
    "iso:country":"CN",
    "name:zho_x_preferred":[
        "\u5218\u5bcc\u5c6f"
    ],
    "wof:name":"Liufutun",
    "wof:placetype":"locality"
},
  "geometry": {"coordinates":[125.84914999999999,46.72638],"type":"Point"}
}