{
  "type": "Feature",
  "properties": {
    "gn:admin1_code":"33.0",
    "gn:asciiname":"Shuijingtuo",
    "gn:country_code":"CN",
    "gn:dem":517,
    "gn:feature_class":"P",
    "gn:feature_code":"PPL",
    "gn:name":"Shuijingtuo",
    "gn:population":0,
    "gn:timezone":"Asia/Shanghai",
    "iso:country":"CN",
    "name:zho_x_preferred":[
        "\u6c34\u4e95\u5768"
    ],
    "wof:name":"Shuijingtuo",
    "wof:placetype":"locality"
},
  "geometry": {"coordinates":[109.06788,28.90322],"type":"Point"}
}