{
  "type": "Feature",
  "properties": {
    "gn:admin1_code":"3.0",
    "gn:asciiname":"Shuangfengchong",
    "gn:country_code":"CN",
    "gn:dem":184,
    "gn:feature_class":"P",
    "gn:feature_code":"PPL",
    "gn:name":"Shuangfengchong",
    "gn:population":0,
    "gn:timezone":"Asia/Shanghai",
    "iso:country":"CN",
    "name:zho_x_preferred":[
        "\u53cc\u51e4\u51b2"
    ],
    "wof:name":"Shuangfengchong",
    "wof:placetype":"locality"
},
  "geometry": {"coordinates":[113.911,27.5756],"type":"Point"}
}