{
  "type": "Feature",
  "properties": {
    "gn:admin1_code":"19.0",
    "gn:asciiname":"Xibangtun",
    "gn:country_code":"CN",
    "gn:dem":45,
    "gn:feature_class":"P",
    "gn:feature_code":"PPL",
    "gn:name":"Xibangtun",
    "gn:population":0,
    "gn:timezone":"Asia/Shanghai",
    "iso:country":"CN",
    "name:zho_x_preferred":[
        "\u897f\u90a6\u5c6f"
    ],
    "wof:name":"Xibangtun",
    "wof:placetype":"locality"
},
  "geometry": {"coordinates":[122.706,39.0419],"type":"Point"}
}