{
  "type": "Feature",
  "properties": {
    "gn:admin1_code":"11.0",
    "gn:asciiname":"Shilichong Nongchang",
    "gn:country_code":"CN",
    "gn:dem":153,
    "gn:feature_class":"P",
    "gn:feature_code":"PPLF",
    "gn:name":"Shilichong Nongchang",
    "gn:population":0,
    "gn:timezone":"Asia/Shanghai",
    "iso:country":"CN",
    "name:zho_x_preferred":[
        "\u5341\u91cc\u51b2\u519c\u573a"
    ],
    "wof:name":"Shilichong Nongchang",
    "wof:placetype":"locality"
},
  "geometry": {"coordinates":[113.65286999999999,26.81558],"type":"Point"}
}