{
  "type": "Feature",
  "properties": {
    "gn:admin1_code":"18.0",
    "gn:asciiname":"Guilaogou",
    "gn:country_code":"CN",
    "gn:dem":874,
    "gn:feature_class":"P",
    "gn:feature_code":"PPL",
    "gn:name":"Guilaogou",
    "gn:population":0,
    "gn:timezone":"Asia/Shanghai",
    "iso:country":"CN",
    "name:zho_x_preferred":[
        "\u8d35\u8001\u6c9f"
    ],
    "wof:name":"Guilaogou",
    "wof:placetype":"locality"
},
  "geometry": {"coordinates":[108.47799999999999,26.9699],"type":"Point"}
}