{
  "type": "Feature",
  "properties": {
    "gn:admin1_code":"8.0",
    "gn:asciiname":"Sipai'ercun",
    "gn:country_code":"CN",
    "gn:dem":274,
    "gn:feature_class":"P",
    "gn:feature_code":"PPL",
    "gn:name":"Sipai\u2019ercun",
    "gn:population":0,
    "gn:timezone":"Asia/Shanghai",
    "iso:country":"CN",
    "name:und_x_variant":[
        "Sipai\u2019ercun"
    ],
    "name:zho_x_preferred":[
        "\u56db\u6392\u4e8c\u6751"
    ],
    "wof:name":"Sipai'ercun",
    "wof:placetype":"locality"
},
  "geometry": {"coordinates":[126.48238000000001,47.86735],"type":"Point"}
}