{
  "type": "Feature",
  "properties": {
    "gn:admin1_code":"32.0",
    "gn:asciiname":"Wolong",
    "gn:country_code":"CN",
    "gn:dem":3620,
    "gn:feature_class":"P",
    "gn:feature_code":"PPL",
    "gn:name":"Wolong",
    "gn:population":0,
    "gn:timezone":"Asia/Shanghai",
    "iso:country":"CN",
    "name:ceb_x_preferred":[
        "Wolong"
    ],
    "name:deu_x_preferred":[
        "Wolong"
    ],
    "name:fra_x_preferred":[
        "Wolong"
    ],
    "name:vie_x_preferred":[
        "Ng\u1ecda Long"
    ],
    "name:zho_x_preferred":[
        "\u7a9d\u9f99"
    ],
    "wof:name":"Wolong",
    "wof:placetype":"locality"
},
  "geometry": {"coordinates":[100.726,28.3513],"type":"Point"}
}