{
  "type": "Feature",
  "properties": {
    "gn:admin1_code":"10.0",
    "gn:asciiname":"Yongle",
    "gn:country_code":"CN",
    "gn:dem":34,
    "gn:feature_class":"P",
    "gn:feature_code":"PPL",
    "gn:name":"Yongle",
    "gn:population":0,
    "gn:timezone":"Asia/Shanghai",
    "iso:country":"CN",
    "name:und_x_variant":[
        "Yung-lo",
        "Yongle"
    ],
    "name:zho_x_preferred":[
        "\u6c38\u4e50"
    ],
    "wof:name":"Yongle",
    "wof:placetype":"locality"
},
  "geometry": {"coordinates":[115.99517,39.52399000000001],"type":"Point"}
}