{
  "type": "Feature",
  "properties": {
    "gn:admin1_code":"14.0",
    "gn:asciiname":"Zhunqiong",
    "gn:country_code":"CN",
    "gn:dem":4550,
    "gn:feature_class":"P",
    "gn:feature_code":"PPL",
    "gn:name":"Zhunqiong",
    "gn:population":0,
    "gn:timezone":"Asia/Urumqi",
    "iso:country":"CN",
    "name:zho_x_preferred":[
        "\u51c6\u7a77"
    ],
    "wof:name":"Zhunqiong",
    "wof:placetype":"locality"
},
  "geometry": {"coordinates":[96.75935,30.84675],"type":"Point"}
}