{
  "type": "Feature",
  "properties": {
    "gn:admin1_code":"14.0",
    "gn:asciiname":"Youlu",
    "gn:country_code":"CN",
    "gn:dem":4411,
    "gn:feature_class":"P",
    "gn:feature_code":"PPL",
    "gn:name":"Youlu",
    "gn:population":0,
    "gn:timezone":"Asia/Urumqi",
    "iso:country":"CN",
    "name:zho_x_preferred":[
        "\u7531\u8def"
    ],
    "wof:name":"Youlu",
    "wof:placetype":"locality"
},
  "geometry": {"coordinates":[86.5998,29.1425],"type":"Point"}
}