{
  "type": "Feature",
  "properties": {
    "gn:admin1_code":"26.0",
    "gn:asciiname":"Taishangounao",
    "gn:country_code":"CN",
    "gn:dem":1061,
    "gn:feature_class":"P",
    "gn:feature_code":"PPL",
    "gn:name":"Taishangounao",
    "gn:population":0,
    "gn:timezone":"Asia/Shanghai",
    "iso:country":"CN",
    "name:zho_x_preferred":[
        "\u592a\u5c71\u6c9f\u8111"
    ],
    "wof:name":"Taishangounao",
    "wof:placetype":"locality"
},
  "geometry": {"coordinates":[109.77736000000002,33.30404],"type":"Point"}
}