{
  "type": "Feature",
  "properties": {
    "gn:admin1_code":"24",
    "gn:asciiname":"Xishe",
    "gn:cc2":"CN",
    "gn:country_code":"CN",
    "gn:dem":449,
    "gn:feature_class":"P",
    "gn:feature_code":"PPL",
    "gn:name":"Xishe",
    "gn:population":0,
    "gn:timezone":"Asia/Shanghai",
    "iso:country":"CN",
    "name:und_x_variant":[
        "Hsi-she",
        "Hsi-she-ts\u2019un",
        "Xishe"
    ],
    "wof:name":"Xishe",
    "wof:placetype":"locality"
},
  "geometry": {"coordinates":[111.00528,35.65083],"type":"Point"}
}