{
  "type": "Feature",
  "properties": {
    "gn:admin1_code":"11.0",
    "gn:asciiname":"Fanjiazui",
    "gn:country_code":"CN",
    "gn:dem":80,
    "gn:feature_class":"P",
    "gn:feature_code":"PPL",
    "gn:name":"Fanjiazui",
    "gn:population":0,
    "gn:timezone":"Asia/Shanghai",
    "iso:country":"CN",
    "name:zho_x_preferred":[
        "Fanjiazui"
    ],
    "name:zho_x_variant":[
        "\u8303\u5bb6\u5480"
    ],
    "wof:name":"Fanjiazui",
    "wof:placetype":"locality"
},
  "geometry": {"coordinates":[111.62745,29.53993],"type":"Point"}
}