{
  "type": "Feature",
  "properties": {
    "gn:admin1_code":"15.0",
    "gn:asciiname":"Shimenpingshan",
    "gn:country_code":"CN",
    "gn:dem":1897,
    "gn:feature_class":"P",
    "gn:feature_code":"PPL",
    "gn:name":"Shimenpingshan",
    "gn:population":0,
    "gn:timezone":"Asia/Shanghai",
    "iso:country":"CN",
    "name:zho_x_preferred":[
        "\u77f3\u95e8\u576a\u5c71"
    ],
    "wof:name":"Shimenpingshan",
    "wof:placetype":"locality"
},
  "geometry": {"coordinates":[104.48148999999999,33.67788],"type":"Point"}
}