{
  "type": "Feature",
  "properties": {
    "gn:admin1_code":"4.0",
    "gn:asciiname":"Gongyuan Yizu",
    "gn:country_code":"CN",
    "gn:dem":5,
    "gn:feature_class":"P",
    "gn:feature_code":"PPLF",
    "gn:name":"Gongyuan Yizu",
    "gn:population":0,
    "gn:timezone":"Asia/Shanghai",
    "iso:country":"CN",
    "name:zho_x_preferred":[
        "\u516c\u56ed\u4e00\u7ec4"
    ],
    "wof:name":"Gongyuan Yizu",
    "wof:placetype":"locality"
},
  "geometry": {"coordinates":[120.81587,32.07284],"type":"Point"}
}