{
  "type": "Feature",
  "properties": {
    "gn:admin1_code":"12.0",
    "gn:asciiname":"Xiaozhuchong",
    "gn:country_code":"CN",
    "gn:dem":127,
    "gn:feature_class":"P",
    "gn:feature_code":"PPL",
    "gn:name":"Xiaozhuchong",
    "gn:population":0,
    "gn:timezone":"Asia/Shanghai",
    "iso:country":"CN",
    "name:zho_x_preferred":[
        "\u5c0f\u7af9\u51b2"
    ],
    "wof:name":"Xiaozhuchong",
    "wof:placetype":"locality"
},
  "geometry": {"coordinates":[115.80177,30.52993],"type":"Point"}
}