{
  "type": "Feature",
  "properties": {
    "gn:admin1_code":"12.0",
    "gn:asciiname":"Changling",
    "gn:country_code":"CN",
    "gn:dem":55,
    "gn:feature_class":"P",
    "gn:feature_code":"PPL",
    "gn:name":"Changling",
    "gn:population":0,
    "gn:timezone":"Asia/Shanghai",
    "iso:country":"CN",
    "name:zho_x_preferred":[
        "\u957f\u5cad"
    ],
    "wof:name":"Changling",
    "wof:placetype":"locality"
},
  "geometry": {"coordinates":[115.53404999999999,30.13439],"type":"Point"}
}