{
  "type": "Feature",
  "properties": {
    "gn:admin1_code":"7",
    "gn:asciiname":"Chunjian",
    "gn:country_code":"CN",
    "gn:dem":21,
    "gn:feature_class":"P",
    "gn:feature_code":"PPL",
    "gn:name":"Chunjian",
    "gn:population":0,
    "gn:timezone":"Asia/Shanghai",
    "iso:country":"CN",
    "name:und_x_variant":[
        "Xibian"
    ],
    "name:zho_x_preferred":[
        "\u6625\u5efa"
    ],
    "name:zho_x_variant":[
        "\u897f\u8fb9"
    ],
    "wof:name":"Chunjian",
    "wof:placetype":"locality"
},
  "geometry": {"coordinates":[117.71801000000001,24.29804],"type":"Point"}
}