{
  "type": "Feature",
  "properties": {
    "gn:admin1_code":"3.0",
    "gn:asciiname":"Nanlincun",
    "gn:country_code":"CN",
    "gn:dem":269,
    "gn:feature_class":"P",
    "gn:feature_code":"PPL",
    "gn:name":"Nanlincun",
    "gn:population":0,
    "gn:timezone":"Asia/Shanghai",
    "iso:country":"CN",
    "name:und_x_variant":[
        "\u5357\u6797\u6751"
    ],
    "wof:name":"Nanlincun",
    "wof:placetype":"locality"
},
  "geometry": {"coordinates":[115.72823,26.78098],"type":"Point"}
}