{
  "type": "Feature",
  "properties": {
    "gn:admin1_code":"20",
    "gn:asciiname":"Bayan Hudag",
    "gn:cc2":"CN",
    "gn:country_code":"CN",
    "gn:dem":1454,
    "gn:feature_class":"P",
    "gn:feature_code":"PPL",
    "gn:name":"Bayan Hudag",
    "gn:population":0,
    "gn:timezone":"Asia/Shanghai",
    "iso:country":"CN",
    "name:und_x_variant":[
        "Ha-la-wu-su",
        "Bayan Hudag"
    ],
    "wof:name":"Bayan Hudag",
    "wof:placetype":"locality"
},
  "geometry": {"coordinates":[108.07056,41.71222],"type":"Point"}
}