{
  "type": "Feature",
  "properties": {
    "gn:admin1_code":"25.0",
    "gn:asciiname":"Xibeidaocun",
    "gn:country_code":"CN",
    "gn:dem":5,
    "gn:feature_class":"P",
    "gn:feature_code":"PPL",
    "gn:name":"Xibeidaocun",
    "gn:population":0,
    "gn:timezone":"Asia/Shanghai",
    "iso:country":"CN",
    "name:zho_x_preferred":[
        "\u897f\u5317\u5c9b\u6751"
    ],
    "wof:name":"Xibeidaocun",
    "wof:placetype":"locality"
},
  "geometry": {"coordinates":[121.49254999999999,36.82252],"type":"Point"}
}