{
  "type": "Feature",
  "properties": {
    "gn:admin1_code":"26.0",
    "gn:asciiname":"Taizishang",
    "gn:country_code":"CN",
    "gn:dem":1134,
    "gn:feature_class":"P",
    "gn:feature_code":"PPL",
    "gn:name":"Taizishang",
    "gn:population":0,
    "gn:timezone":"Asia/Shanghai",
    "iso:country":"CN",
    "name:und_x_variant":[
        "\u53f0\u5b50\u4e0a"
    ],
    "wof:name":"Taizishang",
    "wof:placetype":"locality"
},
  "geometry": {"coordinates":[107.11659,33.88059000000001],"type":"Point"}
}