{
  "type": "Feature",
  "properties": {
    "gn:admin1_code":"11.0",
    "gn:asciiname":"Zhongzhoujia",
    "gn:country_code":"CN",
    "gn:dem":378,
    "gn:feature_class":"P",
    "gn:feature_code":"PPL",
    "gn:name":"Zhongzhoujia",
    "gn:population":0,
    "gn:timezone":"Asia/Shanghai",
    "iso:country":"CN",
    "name:zho_x_preferred":[
        "\u4e2d\u5468\u5bb6"
    ],
    "wof:name":"Zhongzhoujia",
    "wof:placetype":"locality"
},
  "geometry": {"coordinates":[110.62663000000001,28.15486],"type":"Point"}
}