{
  "type": "Feature",
  "properties": {
    "gn:admin1_code":"23",
    "gn:asciiname":"Huangjialu",
    "gn:cc2":"CN",
    "gn:country_code":"CN",
    "gn:dem":9,
    "gn:feature_class":"P",
    "gn:feature_code":"PPL",
    "gn:name":"Huangjialu",
    "gn:population":0,
    "gn:timezone":"Asia/Shanghai",
    "iso:country":"CN",
    "name:und_x_variant":[
        "Huang-chia-lu",
        "Huangjialu"
    ],
    "wof:name":"Huangjialu",
    "wof:placetype":"locality"
},
  "geometry": {"coordinates":[121.76222,31.05083],"type":"Point"}
}