{
  "type": "Feature",
  "properties": {
    "gn:admin1_code":"32.0",
    "gn:asciiname":"Yawangmiao",
    "gn:country_code":"CN",
    "gn:dem":432,
    "gn:feature_class":"P",
    "gn:feature_code":"PPL",
    "gn:name":"Yawangmiao",
    "gn:population":0,
    "gn:timezone":"Asia/Shanghai",
    "iso:country":"CN",
    "name:zho_x_preferred":[
        "\u538b\u738b\u5e99"
    ],
    "wof:name":"Yawangmiao",
    "wof:placetype":"locality"
},
  "geometry": {"coordinates":[104.72281,30.6776],"type":"Point"}
}