{
  "type": "Feature",
  "properties": {
    "gn:admin1_code":"18",
    "gn:asciiname":"Suoduoxi",
    "gn:country_code":"CN",
    "gn:dem":1329,
    "gn:feature_class":"P",
    "gn:feature_code":"PPL",
    "gn:name":"Suoduoxi",
    "gn:population":0,
    "gn:timezone":"Asia/Shanghai",
    "iso:country":"CN",
    "name:zho_x_preferred":[
        "\u9501\u579b\u6eaa"
    ],
    "wof:name":"Suoduoxi",
    "wof:placetype":"locality"
},
  "geometry": {"coordinates":[105.996,27.5642],"type":"Point"}
}