{
  "type": "Feature",
  "properties": {
    "gn:admin1_code":"33.0",
    "gn:asciiname":"Guangfuqiao",
    "gn:country_code":"CN",
    "gn:dem":712,
    "gn:feature_class":"P",
    "gn:feature_code":"PPL",
    "gn:name":"Guangfuqiao",
    "gn:population":0,
    "gn:timezone":"Asia/Shanghai",
    "iso:country":"CN",
    "name:zho_x_preferred":[
        "\u5e7f\u798f\u6865"
    ],
    "name:zho_x_variant":[
        "\u5e7f\u798f\u6865\u9547"
    ],
    "wof:name":"Guangfuqiao",
    "wof:placetype":"locality"
},
  "geometry": {"coordinates":[107.27200000000001,28.8435],"type":"Point"}
}