{
  "type": "Feature",
  "properties": {
    "gn:admin1_code":"2.0",
    "gn:asciiname":"Wujili",
    "gn:country_code":"CN",
    "gn:dem":183,
    "gn:feature_class":"P",
    "gn:feature_code":"PPL",
    "gn:name":"Wujili",
    "gn:population":0,
    "gn:timezone":"Asia/Shanghai",
    "iso:country":"CN",
    "name:zho_x_preferred":[
        "\u5c4b\u57fa\u91cc"
    ],
    "wof:name":"Wujili",
    "wof:placetype":"locality"
},
  "geometry": {"coordinates":[119.62872,29.4804],"type":"Point"}
}