{
  "type": "Feature",
  "properties": {
    "gn:admin1_code":"14.0",
    "gn:asciiname":"Nagqu",
    "gn:country_code":"CN",
    "gn:dem":4609,
    "gn:feature_class":"P",
    "gn:feature_code":"PPLF",
    "gn:name":"Nagqu",
    "gn:population":0,
    "gn:timezone":"Asia/Urumqi",
    "iso:country":"CN",
    "name:bod_x_preferred":[
        "Nagqu"
    ],
    "name:zho_x_preferred":[
        "Naqu"
    ],
    "name:zho_x_variant":[
        "\u7eb3\u66f2",
        "Xiongrurisu",
        "\u96c4\u5982\u65e5\u82cf"
    ],
    "wof:name":"Nagqu",
    "wof:placetype":"locality"
},
  "geometry": {"coordinates":[83.40100000000002,29.701],"type":"Point"}
}