{
  "type": "Feature",
  "properties": {
    "gn:admin1_code":"15.0",
    "gn:asciiname":"Xintoufen",
    "gn:country_code":"CN",
    "gn:dem":1238,
    "gn:feature_class":"P",
    "gn:feature_code":"PPL",
    "gn:name":"Xintoufen",
    "gn:population":0,
    "gn:timezone":"Asia/Shanghai",
    "iso:country":"CN",
    "name:zho_x_preferred":[
        "\u65b0\u5934\u5206"
    ],
    "wof:name":"Xintoufen",
    "wof:placetype":"locality"
},
  "geometry": {"coordinates":[98.84220000000001,40.1823],"type":"Point"}
}