{
  "type": "Feature",
  "properties": {
    "gn:admin1_code":"12.0",
    "gn:asciiname":"Shengtianjie",
    "gn:country_code":"CN",
    "gn:dem":1028,
    "gn:feature_class":"P",
    "gn:feature_code":"PPL",
    "gn:name":"Shengtianjie",
    "gn:population":0,
    "gn:timezone":"Asia/Shanghai",
    "iso:country":"CN",
    "name:zho_x_preferred":[
        "\u5347\u5929\u754c"
    ],
    "wof:name":"Shengtianjie",
    "wof:placetype":"locality"
},
  "geometry": {"coordinates":[108.88795,29.66867],"type":"Point"}
}