{
  "type": "Feature",
  "properties": {
    "gn:admin1_code":"3.0",
    "gn:asciiname":"Zhangqing",
    "gn:country_code":"CN",
    "gn:dem":32,
    "gn:feature_class":"P",
    "gn:feature_code":"PPLA4",
    "gn:name":"Zhangqing",
    "gn:population":0,
    "gn:timezone":"Asia/Shanghai",
    "iso:country":"CN",
    "name:und_x_variant":[
        "\u5f20\u9752",
        "Zhangqing Xiang",
        "\u5f20\u9752\u4e61"
    ],
    "wof:name":"Zhangqing",
    "wof:placetype":"locality"
},
  "geometry": {"coordinates":[116.33223,29.7151],"type":"Point"}
}