{
  "type": "Feature",
  "properties": {
    "gn:admin1_code":"12.0",
    "gn:asciiname":"Laodengwan",
    "gn:country_code":"CN",
    "gn:dem":35,
    "gn:feature_class":"P",
    "gn:feature_code":"PPL",
    "gn:name":"Laodengwan",
    "gn:population":0,
    "gn:timezone":"Asia/Shanghai",
    "iso:country":"CN",
    "name:und_x_variant":[
        "\u8001\u9093\u5846"
    ],
    "wof:name":"Laodengwan",
    "wof:placetype":"locality"
},
  "geometry": {"coordinates":[114.27273,30.76631],"type":"Point"}
}