{
  "type": "Feature",
  "properties": {
    "gn:admin1_code":"19.0",
    "gn:asciiname":"Qianlama Zhangzi",
    "gn:country_code":"CN",
    "gn:dem":465,
    "gn:feature_class":"P",
    "gn:feature_code":"PPL",
    "gn:name":"Qianlama Zhangzi",
    "gn:population":0,
    "gn:timezone":"Asia/Shanghai",
    "iso:country":"CN",
    "name:zho_x_preferred":[
        "\u524d\u5587\u561b\u6756\u5b50"
    ],
    "wof:name":"Qianlama Zhangzi",
    "wof:placetype":"locality"
},
  "geometry": {"coordinates":[119.21677,41.17559],"type":"Point"}
}