{
  "type": "Feature",
  "properties": {
    "gn:admin1_code":"8.0",
    "gn:asciiname":"Zhoubucun",
    "gn:country_code":"CN",
    "gn:dem":141,
    "gn:feature_class":"P",
    "gn:feature_code":"PPL",
    "gn:name":"Zhoubucun",
    "gn:population":0,
    "gn:timezone":"Asia/Shanghai",
    "iso:country":"CN",
    "name:zho_x_preferred":[
        "\u5468\u5821\u6751"
    ],
    "wof:name":"Zhoubucun",
    "wof:placetype":"locality"
},
  "geometry": {"coordinates":[126.84562,46.10575],"type":"Point"}
}