{
  "type": "Feature",
  "properties": {
    "gn:admin1_code":"32.0",
    "gn:asciiname":"Antanping",
    "gn:country_code":"CN",
    "gn:dem":1630,
    "gn:feature_class":"P",
    "gn:feature_code":"PPL",
    "gn:name":"Antanping",
    "gn:population":0,
    "gn:timezone":"Asia/Shanghai",
    "iso:country":"CN",
    "name:zho_x_preferred":[
        "\u5b89\u6ee9\u576a"
    ],
    "wof:name":"Antanping",
    "wof:placetype":"locality"
},
  "geometry": {"coordinates":[102.14188,29.40392],"type":"Point"}
}