{
  "type": "Feature",
  "properties": {
    "gn:admin1_code":"12.0",
    "gn:asciiname":"Lanping",
    "gn:country_code":"CN",
    "gn:dem":98,
    "gn:feature_class":"P",
    "gn:feature_code":"PPL",
    "gn:name":"Lanping",
    "gn:population":0,
    "gn:timezone":"Asia/Shanghai",
    "iso:country":"CN",
    "name:zho_x_preferred":[
        "Lanping"
    ],
    "name:zho_x_variant":[
        "\u5c9a\u576a"
    ],
    "wof:name":"Lanping",
    "wof:placetype":"locality"
},
  "geometry": {"coordinates":[114.85231,29.48945],"type":"Point"}
}