{
  "type": "Feature",
  "properties": {
    "gn:admin1_code":"02",
    "gn:asciiname":"Huangnan",
    "gn:country_code":"CN",
    "gn:dem":167,
    "gn:feature_class":"P",
    "gn:feature_code":"PPLA4",
    "gn:name":"Huangnan",
    "gn:population":0,
    "gn:timezone":"Asia/Shanghai",
    "iso:country":"CN",
    "name:und_x_variant":[
        "Huangnan Xiang"
    ],
    "name:zho_x_preferred":[
        "\u9ec4\u5357"
    ],
    "name:zho_x_variant":[
        "\u9ec4\u5357\u4e61"
    ],
    "wof:name":"Huangnan",
    "wof:placetype":"locality"
},
  "geometry": {"coordinates":[120.68128,28.52913],"type":"Point"}
}