{
  "type": "Feature",
  "properties": {
    "gn:admin1_code":"26.0",
    "gn:asciiname":"Hejiapan",
    "gn:country_code":"CN",
    "gn:dem":1213,
    "gn:feature_class":"P",
    "gn:feature_code":"PPL",
    "gn:name":"Hejiapan",
    "gn:population":0,
    "gn:timezone":"Asia/Shanghai",
    "iso:country":"CN",
    "name:zho_x_preferred":[
        "\u8d3a\u5bb6\u7554"
    ],
    "wof:name":"Hejiapan",
    "wof:placetype":"locality"
},
  "geometry": {"coordinates":[109.51517,37.63622],"type":"Point"}
}