{
  "type": "Feature",
  "properties": {
    "gn:admin1_code":"13.0",
    "gn:asciiname":"Tuwat",
    "gn:country_code":"CN",
    "gn:dem":1315,
    "gn:feature_class":"P",
    "gn:feature_code":"PPL",
    "gn:name":"T\u00fcwat",
    "gn:population":0,
    "gn:timezone":"Asia/Shanghai",
    "iso:country":"CN",
    "name:uig_x_preferred":[
        "T\u00fcw\u0259t"
    ],
    "name:uig_x_variant":[
        "T\u00fcwet",
        "\u062a\u06c8\u06cb\u06d5\u062a",
        "\u0422\u04af\u0432\u04d9\u0442"
    ],
    "name:und_x_variant":[
        "T\u00fcwat"
    ],
    "wof:name":"Tuwat",
    "wof:placetype":"locality"
},
  "geometry": {"coordinates":[79.78333000000001,37.33333],"type":"Point"}
}