{
  "type": "Feature",
  "properties": {
    "gn:admin1_code":"29.0",
    "gn:asciiname":"Shayijiu",
    "gn:country_code":"CN",
    "gn:dem":1879,
    "gn:feature_class":"P",
    "gn:feature_code":"PPL",
    "gn:name":"Shayijiu",
    "gn:population":0,
    "gn:timezone":"Asia/Shanghai",
    "iso:country":"CN",
    "name:zho_x_preferred":[
        "\u6c99\u77e3\u65e7"
    ],
    "wof:name":"Shayijiu",
    "wof:placetype":"locality"
},
  "geometry": {"coordinates":[101.926,25.2887],"type":"Point"}
}