{
  "type": "Feature",
  "properties": {
    "gn:admin1_code":"02",
    "gn:asciiname":"Wushizi",
    "gn:cc2":"CN",
    "gn:country_code":"CN",
    "gn:dem":80,
    "gn:feature_class":"P",
    "gn:feature_code":"PPL",
    "gn:name":"Wushizi",
    "gn:population":0,
    "gn:timezone":"Asia/Shanghai",
    "iso:country":"CN",
    "name:und_x_variant":[
        "Wu-shih-tzu-ts\u2019un",
        "Wushizi",
        "\u4e4c\u77f3\u5b50"
    ],
    "wof:name":"Wushizi",
    "wof:placetype":"locality"
},
  "geometry": {"coordinates":[122.31417,29.78306],"type":"Point"}
}