{
  "type": "Feature",
  "properties": {
    "gn:admin1_code":"30",
    "gn:asciiname":"Guye",
    "gn:country_code":"CN",
    "gn:dem":62,
    "gn:feature_class":"P",
    "gn:feature_code":"PPL",
    "gn:name":"Guye",
    "gn:population":0,
    "gn:timezone":"Asia/Shanghai",
    "iso:country":"CN",
    "name:ceb_x_preferred":[
        "Guye"
    ],
    "name:deu_x_preferred":[
        "Guye"
    ],
    "name:fra_x_preferred":[
        "Guye"
    ],
    "name:mlg_x_preferred":[
        "Guye"
    ],
    "name:rus_x_preferred":[
        "\u0413\u044e\u0438"
    ],
    "name:zho_x_preferred":[
        "\u53e4\u91ce"
    ],
    "wof:name":"Guye",
    "wof:placetype":"locality"
},
  "geometry": {"coordinates":[116.64131,24.18994],"type":"Point"}
}