{
  "type": "Feature",
  "properties": {
    "gn:admin1_code":"26.0",
    "gn:asciiname":"Suojiazhai",
    "gn:country_code":"CN",
    "gn:dem":786,
    "gn:feature_class":"P",
    "gn:feature_code":"PPL",
    "gn:name":"Suojiazhai",
    "gn:population":0,
    "gn:timezone":"Asia/Shanghai",
    "iso:country":"CN",
    "name:zho_x_preferred":[
        "\u7d22\u5bb6\u5be8"
    ],
    "wof:name":"Suojiazhai",
    "wof:placetype":"locality"
},
  "geometry": {"coordinates":[109.6743,35.34438],"type":"Point"}
}