{
  "type": "Feature",
  "properties": {
    "gn:admin1_code":"16.0",
    "gn:asciiname":"Genlun",
    "gn:country_code":"CN",
    "gn:dem":81,
    "gn:feature_class":"P",
    "gn:feature_code":"PPL",
    "gn:name":"Genlun",
    "gn:population":0,
    "gn:timezone":"Asia/Shanghai",
    "iso:country":"CN",
    "name:zho_x_preferred":[
        "\u6839\u4f26"
    ],
    "wof:name":"Genlun",
    "wof:placetype":"locality"
},
  "geometry": {"coordinates":[109.376,24.0095],"type":"Point"}
}