{
  "type": "Feature",
  "properties": {
    "gn:admin1_code":"1.0",
    "gn:asciiname":"Shenglongcun",
    "gn:country_code":"CN",
    "gn:dem":41,
    "gn:feature_class":"P",
    "gn:feature_code":"PPL",
    "gn:name":"Shenglongcun",
    "gn:population":0,
    "gn:timezone":"Asia/Shanghai",
    "iso:country":"CN",
    "name:zho_x_preferred":[
        "\u80dc\u9f99\u6751"
    ],
    "wof:name":"Shenglongcun",
    "wof:placetype":"locality"
},
  "geometry": {"coordinates":[116.91391000000002,31.01849],"type":"Point"}
}