{
  "type": "Feature",
  "properties": {
    "gn:admin1_code":"16.0",
    "gn:asciiname":"Yexi",
    "gn:country_code":"CN",
    "gn:dem":265,
    "gn:feature_class":"P",
    "gn:feature_code":"PPL",
    "gn:name":"Yexi",
    "gn:population":0,
    "gn:timezone":"Asia/Shanghai",
    "iso:country":"CN",
    "name:zho_x_preferred":[
        "\u4e5f\u897f"
    ],
    "wof:name":"Yexi",
    "wof:placetype":"locality"
},
  "geometry": {"coordinates":[110.752,23.835],"type":"Point"}
}