{
  "type": "Feature",
  "properties": {
    "gn:admin1_code":"24.0",
    "gn:asciiname":"Xiyangchan",
    "gn:country_code":"CN",
    "gn:dem":1032,
    "gn:feature_class":"P",
    "gn:feature_code":"PPL",
    "gn:name":"Xiyangchan",
    "gn:population":0,
    "gn:timezone":"Asia/Shanghai",
    "iso:country":"CN",
    "name:zho_x_preferred":[
        "\u897f\u9633\u8fbf"
    ],
    "wof:name":"Xiyangchan",
    "wof:placetype":"locality"
},
  "geometry": {"coordinates":[112.07729999999999,35.54837],"type":"Point"}
}