{
  "type": "Feature",
  "properties": {
    "gn:admin1_code":"29",
    "gn:asciiname":"Anle",
    "gn:country_code":"CN",
    "gn:dem":1590,
    "gn:feature_class":"P",
    "gn:feature_code":"PPL",
    "gn:name":"Anle",
    "gn:population":0,
    "gn:timezone":"Asia/Shanghai",
    "iso:country":"CN",
    "name:ceb_x_preferred":[
        "Anle"
    ],
    "name:deu_x_preferred":[
        "Anle"
    ],
    "name:swe_x_preferred":[
        "Anle"
    ],
    "wof:name":"Anle",
    "wof:placetype":"locality"
},
  "geometry": {"coordinates":[101.70806,25.30083],"type":"Point"}
}