{
  "type": "Feature",
  "properties": {
    "gn:admin1_code":"32.0",
    "gn:asciiname":"Cuojiwan",
    "gn:country_code":"CN",
    "gn:dem":935,
    "gn:feature_class":"P",
    "gn:feature_code":"PPL",
    "gn:name":"Cuojiwan",
    "gn:population":0,
    "gn:timezone":"Asia/Shanghai",
    "iso:country":"CN",
    "name:zho_x_preferred":[
        "\u64ae\u7b95\u6e7e"
    ],
    "wof:name":"Cuojiwan",
    "wof:placetype":"locality"
},
  "geometry": {"coordinates":[104.66,28.1238],"type":"Point"}
}