{
  "type": "Feature",
  "properties": {
    "gn:admin1_code":"6.0",
    "gn:asciiname":"Dasha",
    "gn:country_code":"CN",
    "gn:dem":2951,
    "gn:feature_class":"P",
    "gn:feature_code":"PPL",
    "gn:name":"Dasha",
    "gn:population":0,
    "gn:timezone":"Asia/Shanghai",
    "iso:country":"CN",
    "name:ceb_x_preferred":[
        "Dasha"
    ],
    "name:deu_x_preferred":[
        "Dasha"
    ],
    "name:ita_x_preferred":[
        "Dasha"
    ],
    "name:swe_x_preferred":[
        "Dasha"
    ],
    "name:zho_x_preferred":[
        "\u8fbe\u6c99"
    ],
    "wof:name":"Dasha",
    "wof:placetype":"locality"
},
  "geometry": {"coordinates":[101.92946000000001,35.25963],"type":"Point"}
}