{
  "type": "Feature",
  "properties": {
    "gn:admin1_code":"14.0",
    "gn:asciiname":"Mazhong",
    "gn:country_code":"CN",
    "gn:dem":3704,
    "gn:feature_class":"P",
    "gn:feature_code":"PPL",
    "gn:name":"Mazhong",
    "gn:population":0,
    "gn:timezone":"Asia/Urumqi",
    "iso:country":"CN",
    "name:zho_x_preferred":[
        "\u9a6c\u4e2d"
    ],
    "wof:name":"Mazhong",
    "wof:placetype":"locality"
},
  "geometry": {"coordinates":[95.77253,31.21443],"type":"Point"}
}