{
  "type": "Feature",
  "properties": {
    "gn:admin1_code":"2.0",
    "gn:asciiname":"Suankeng",
    "gn:country_code":"CN",
    "gn:dem":227,
    "gn:feature_class":"P",
    "gn:feature_code":"PPL",
    "gn:name":"Suankeng",
    "gn:population":0,
    "gn:timezone":"Asia/Shanghai",
    "iso:country":"CN",
    "name:zho_x_preferred":[
        "\u7b97\u5751"
    ],
    "wof:name":"Suankeng",
    "wof:placetype":"locality"
},
  "geometry": {"coordinates":[121.21189,29.84392],"type":"Point"}
}