{
  "type": "Feature",
  "properties": {
    "gn:admin1_code":"14.0",
    "gn:asciiname":"Gongga",
    "gn:country_code":"CN",
    "gn:dem":2967,
    "gn:feature_class":"P",
    "gn:feature_code":"PPL",
    "gn:name":"Gongga",
    "gn:population":0,
    "gn:timezone":"Asia/Urumqi",
    "iso:country":"CN",
    "name:nld_x_preferred":[
        "Gongga"
    ],
    "name:zho_x_preferred":[
        "\u8d21\u560e"
    ],
    "wof:name":"Gongga",
    "wof:placetype":"locality"
},
  "geometry": {"coordinates":[94.45223,29.50128],"type":"Point"}
}