{
  "type": "Feature",
  "properties": {
    "gn:admin1_code":"13.0",
    "gn:asciiname":"Shuiding",
    "gn:cc2":"CN",
    "gn:country_code":"CN",
    "gn:dem":601,
    "gn:feature_class":"P",
    "gn:feature_code":"PPL",
    "gn:name":"Shuiding",
    "gn:population":0,
    "gn:timezone":"Asia/Shanghai",
    "iso:country":"CN",
    "name:por_x_preferred":[
        "Suiding"
    ],
    "name:rus_x_preferred":[
        "\u0428\u0443\u0439\u0434\u0438\u043d"
    ],
    "name:uig_x_preferred":[
        "\u0633\u06c8\u064a\u062f\u06c8\u06ad \u0628\u0627\u0632\u0649\u0631\u0649"
    ],
    "name:und_x_variant":[
        "Huo-ch\u2019eng-hsien",
        "Sui-ting",
        "I-li",
        "Sui-ting-chen",
        "Huocheng",
        "Shui-ting-chen",
        "Huocheng Xian",
        "Sui-ting-hsien",
        "Sui-ding",
        "Suydun",
        "Shuiding"
    ],
    "name:zho_x_preferred":[
        "\u6c34\u5b9a\u9547"
    ],
    "wof:name":"Shuiding",
    "wof:placetype":"locality"
},
  "geometry": {"coordinates":[80.80778000000002,44.01],"type":"Point"}
}