{
  "type": "Feature",
  "properties": {
    "gn:admin1_code":"14.0",
    "gn:asciiname":"Niangcun",
    "gn:country_code":"CN",
    "gn:dem":3275,
    "gn:feature_class":"P",
    "gn:feature_code":"PPL",
    "gn:name":"Niangcun",
    "gn:population":0,
    "gn:timezone":"Asia/Urumqi",
    "iso:country":"CN",
    "name:zho_x_preferred":[
        "\u5a18\u6751"
    ],
    "wof:name":"Niangcun",
    "wof:placetype":"locality"
},
  "geometry": {"coordinates":[92.99509999999999,29.02197],"type":"Point"}
}