{
  "type": "Feature",
  "properties": {
    "gn:admin1_code":"11.0",
    "gn:asciiname":"Dongguazui",
    "gn:country_code":"CN",
    "gn:dem":59,
    "gn:feature_class":"P",
    "gn:feature_code":"PPL",
    "gn:name":"Dongguazui",
    "gn:population":0,
    "gn:timezone":"Asia/Shanghai",
    "iso:country":"CN",
    "name:zho_x_preferred":[
        "\u51ac\u74dc\u5480"
    ],
    "wof:name":"Dongguazui",
    "wof:placetype":"locality"
},
  "geometry": {"coordinates":[113.04411,28.26096],"type":"Point"}
}