{
  "type": "Feature",
  "properties": {
    "gn:admin1_code":"11.0",
    "gn:asciiname":"Yanmentou",
    "gn:country_code":"CN",
    "gn:dem":1082,
    "gn:feature_class":"P",
    "gn:feature_code":"PPL",
    "gn:name":"Yanmentou",
    "gn:population":0,
    "gn:timezone":"Asia/Shanghai",
    "iso:country":"CN",
    "name:zho_x_preferred":[
        "\u5ca9\u95e8\u5934"
    ],
    "wof:name":"Yanmentou",
    "wof:placetype":"locality"
},
  "geometry": {"coordinates":[110.18763,26.28987],"type":"Point"}
}