{
  "type": "Feature",
  "properties": {
    "gn:admin1_code":"26.0",
    "gn:asciiname":"Zhaojia Pancun",
    "gn:country_code":"CN",
    "gn:dem":923,
    "gn:feature_class":"P",
    "gn:feature_code":"PPL",
    "gn:name":"Zhaojia Pancun",
    "gn:population":0,
    "gn:timezone":"Asia/Shanghai",
    "iso:country":"CN",
    "name:zho_x_preferred":[
        "\u8d75\u5bb6\u7554\u6751"
    ],
    "wof:name":"Zhaojia Pancun",
    "wof:placetype":"locality"
},
  "geometry": {"coordinates":[109.96299999999999,37.9649],"type":"Point"}
}