{
  "type": "Feature",
  "properties": {
    "gn:admin1_code":"29.0",
    "gn:asciiname":"Xiabanqiao",
    "gn:country_code":"CN",
    "gn:dem":1532,
    "gn:feature_class":"P",
    "gn:feature_code":"PPL",
    "gn:name":"Xiabanqiao",
    "gn:population":0,
    "gn:timezone":"Asia/Shanghai",
    "iso:country":"CN",
    "name:zho_x_preferred":[
        "\u4e0b\u677f\u6865"
    ],
    "wof:name":"Xiabanqiao",
    "wof:placetype":"locality"
},
  "geometry": {"coordinates":[104.87,27.5312],"type":"Point"}
}