{
  "type": "Feature",
  "properties": {
    "gn:admin1_code":"5.0",
    "gn:asciiname":"Xiangwanli",
    "gn:country_code":"CN",
    "gn:dem":172,
    "gn:feature_class":"P",
    "gn:feature_code":"PPL",
    "gn:name":"Xiangwanli",
    "gn:population":0,
    "gn:timezone":"Asia/Shanghai",
    "iso:country":"CN",
    "name:zho_x_preferred":[
        "\u7fd4\u5f2f\u91cc"
    ],
    "wof:name":"Xiangwanli",
    "wof:placetype":"locality"
},
  "geometry": {"coordinates":[123.76533000000001,43.74664],"type":"Point"}
}