{
  "type": "Feature",
  "properties": {
    "gn:admin1_code":"19.0",
    "gn:asciiname":"Lengjiacun",
    "gn:country_code":"CN",
    "gn:dem":234,
    "gn:feature_class":"P",
    "gn:feature_code":"PPL",
    "gn:name":"Lengjiacun",
    "gn:population":0,
    "gn:timezone":"Asia/Shanghai",
    "iso:country":"CN",
    "name:und_x_variant":[
        "Lengjiawobao",
        "Lengjia Wobu"
    ],
    "name:zho_x_preferred":[
        "\u51b7\u5bb6\u6751"
    ],
    "name:zho_x_variant":[
        "\u51b7\u5bb6\u7a9d\u5821"
    ],
    "wof:name":"Lengjiacun",
    "wof:placetype":"locality"
},
  "geometry": {"coordinates":[122.005,42.62],"type":"Point"}
}