{
  "type": "Feature",
  "properties": {
    "gn:admin1_code":"12.0",
    "gn:asciiname":"Wujiaozui",
    "gn:country_code":"CN",
    "gn:dem":15,
    "gn:feature_class":"P",
    "gn:feature_code":"PPL",
    "gn:name":"Wujiaozui",
    "gn:population":0,
    "gn:timezone":"Asia/Shanghai",
    "iso:country":"CN",
    "name:und_x_variant":[
        "\u4e94\u89d2\u5480"
    ],
    "wof:name":"Wujiaozui",
    "wof:placetype":"locality"
},
  "geometry": {"coordinates":[114.67158999999999,30.44148],"type":"Point"}
}