{
  "type": "Feature",
  "properties": {
    "gn:admin1_code":"14.0",
    "gn:asciiname":"Amuduoguo",
    "gn:country_code":"CN",
    "gn:dem":4757,
    "gn:feature_class":"P",
    "gn:feature_code":"PPL",
    "gn:name":"Amuduoguo",
    "gn:population":0,
    "gn:timezone":"Asia/Urumqi",
    "iso:country":"CN",
    "name:zho_x_preferred":[
        "\u963f\u6728\u593a\u679c"
    ],
    "wof:name":"Amuduoguo",
    "wof:placetype":"locality"
},
  "geometry": {"coordinates":[90.35214999999999,29.66267],"type":"Point"}
}