{
  "type": "Feature",
  "properties": {
    "gn:admin1_code":"8.0",
    "gn:asciiname":"Xiaoyuejin",
    "gn:country_code":"CN",
    "gn:dem":304,
    "gn:feature_class":"P",
    "gn:feature_code":"PPL",
    "gn:name":"Xiaoyuejin",
    "gn:population":0,
    "gn:timezone":"Asia/Shanghai",
    "iso:country":"CN",
    "name:zho_x_preferred":[
        "\u5c0f\u8dc3\u8fdb"
    ],
    "wof:name":"Xiaoyuejin",
    "wof:placetype":"locality"
},
  "geometry": {"coordinates":[129.88861,47.76841],"type":"Point"}
}