{
  "type": "Feature",
  "properties": {
    "gn:admin1_code":"9.0",
    "gn:asciiname":"Shibalitun",
    "gn:country_code":"CN",
    "gn:dem":121,
    "gn:feature_class":"P",
    "gn:feature_code":"PPL",
    "gn:name":"Shibalitun",
    "gn:population":0,
    "gn:timezone":"Asia/Shanghai",
    "iso:country":"CN",
    "name:zho_x_preferred":[
        "\u5341\u516b\u91cc\u5c6f"
    ],
    "wof:name":"Shibalitun",
    "wof:placetype":"locality"
},
  "geometry": {"coordinates":[112.50244000000001,32.92629],"type":"Point"}
}