{
  "type": "Feature",
  "properties": {
    "gn:admin1_code":"11.0",
    "gn:asciiname":"Sanziqiang",
    "gn:country_code":"CN",
    "gn:dem":49,
    "gn:feature_class":"P",
    "gn:feature_code":"PPL",
    "gn:name":"Sanziqiang",
    "gn:population":0,
    "gn:timezone":"Asia/Shanghai",
    "iso:country":"CN",
    "name:zho_x_preferred":[
        "\u4e09\u5b57\u5899"
    ],
    "wof:name":"Sanziqiang",
    "wof:placetype":"locality"
},
  "geometry": {"coordinates":[113.04695,28.33647],"type":"Point"}
}