{
  "type": "Feature",
  "properties": {
    "gn:admin1_code":"25",
    "gn:asciiname":"Nanshigang",
    "gn:country_code":"CN",
    "gn:dem":192,
    "gn:feature_class":"P",
    "gn:feature_code":"PPL",
    "gn:name":"Nanshigang",
    "gn:population":0,
    "gn:timezone":"Asia/Shanghai",
    "iso:country":"CN",
    "name:zho_x_preferred":[
        "\u5357\u77f3\u5c97"
    ],
    "wof:name":"Nanshigang",
    "wof:placetype":"locality"
},
  "geometry": {"coordinates":[117.85599999999999,35.19300000000001],"type":"Point"}
}