{
  "type": "Feature",
  "properties": {
    "gn:admin1_code":"30",
    "gn:asciiname":"Shangtan",
    "gn:country_code":"CN",
    "gn:dem":108,
    "gn:feature_class":"P",
    "gn:feature_code":"PPL",
    "gn:name":"Shangtan",
    "gn:population":0,
    "gn:timezone":"Asia/Shanghai",
    "iso:country":"CN",
    "name:und_x_variant":[
        "Shangtan"
    ],
    "name:zho_x_preferred":[
        "\u4e0a\u6f6d"
    ],
    "wof:name":"Shangtan",
    "wof:placetype":"locality"
},
  "geometry": {"coordinates":[115.77029,24.0871],"type":"Point"}
}