{
  "type": "Feature",
  "properties": {
    "gn:admin1_code":"9.0",
    "gn:asciiname":"Kouzhuang",
    "gn:country_code":"CN",
    "gn:dem":56,
    "gn:feature_class":"P",
    "gn:feature_code":"PPL",
    "gn:name":"Kouzhuang",
    "gn:population":0,
    "gn:timezone":"Asia/Shanghai",
    "iso:country":"CN",
    "name:zho_x_preferred":[
        "\u5bc7\u5e84"
    ],
    "wof:name":"Kouzhuang",
    "wof:placetype":"locality"
},
  "geometry": {"coordinates":[114.29843,33.35761],"type":"Point"}
}