{
  "type": "Feature",
  "properties": {
    "gn:admin1_code":"5.0",
    "gn:asciiname":"Banshi Dingzi",
    "gn:country_code":"CN",
    "gn:dem":448,
    "gn:feature_class":"P",
    "gn:feature_code":"PPL",
    "gn:name":"Banshi Dingzi",
    "gn:population":0,
    "gn:timezone":"Asia/Shanghai",
    "iso:country":"CN",
    "name:zho_x_preferred":[
        "\u677f\u77f3\u9876\u5b50"
    ],
    "wof:name":"Banshi Dingzi",
    "wof:placetype":"locality"
},
  "geometry": {"coordinates":[128.06897000000001,43.73939],"type":"Point"}
}