{
  "type": "Feature",
  "properties": {
    "gn:admin1_code":"26",
    "gn:asciiname":"Kekegai",
    "gn:cc2":"CN",
    "gn:country_code":"CN",
    "gn:dem":1279,
    "gn:feature_class":"P",
    "gn:feature_code":"PPL",
    "gn:name":"Kekegai",
    "gn:population":0,
    "gn:timezone":"Asia/Shanghai",
    "iso:country":"CN",
    "name:und_x_variant":[
        "K\u2019o-k\u2019o-kai",
        "Kekegai"
    ],
    "wof:name":"Kekegai",
    "wof:placetype":"locality"
},
  "geometry": {"coordinates":[109.28333000000001,38.46667],"type":"Point"}
}