{
  "type": "Feature",
  "properties": {
    "gn:admin1_code":"19.0",
    "gn:asciiname":"Xiaohuangdicun",
    "gn:country_code":"CN",
    "gn:dem":29,
    "gn:feature_class":"P",
    "gn:feature_code":"PPL",
    "gn:name":"Xiaohuangdicun",
    "gn:population":0,
    "gn:timezone":"Asia/Shanghai",
    "iso:country":"CN",
    "name:zho_x_preferred":[
        "\u5c0f\u8352\u5730\u6751"
    ],
    "wof:name":"Xiaohuangdicun",
    "wof:placetype":"locality"
},
  "geometry": {"coordinates":[123.023,41.8799],"type":"Point"}
}