{
  "type": "Feature",
  "properties": {
    "gn:admin1_code":"26.0",
    "gn:asciiname":"Weichi",
    "gn:country_code":"CN",
    "gn:dem":664,
    "gn:feature_class":"P",
    "gn:feature_code":"PPL",
    "gn:name":"Weichi",
    "gn:population":0,
    "gn:timezone":"Asia/Shanghai",
    "iso:country":"CN",
    "name:und_x_variant":[
        "\u5c09\u8fdf"
    ],
    "wof:name":"Weichi",
    "wof:placetype":"locality"
},
  "geometry": {"coordinates":[107.70935,34.35248],"type":"Point"}
}