{
  "type": "Feature",
  "properties": {
    "gn:admin1_code":"30.0",
    "gn:asciiname":"Shangzhuang",
    "gn:country_code":"CN",
    "gn:dem":483,
    "gn:feature_class":"P",
    "gn:feature_code":"PPL",
    "gn:name":"Shangzhuang",
    "gn:population":0,
    "gn:timezone":"Asia/Shanghai",
    "iso:country":"CN",
    "name:und_x_variant":[
        "\u4e0a\u5e84"
    ],
    "name:zho_x_preferred":[
        "\u4e0a\u5e84"
    ],
    "wof:name":"Shangzhuang",
    "wof:placetype":"locality"
},
  "geometry": {"coordinates":[114.90476,23.59461],"type":"Point"}
}