{
  "type": "Feature",
  "properties": {
    "gn:admin1_code":"32.0",
    "gn:asciiname":"Wa'er",
    "gn:country_code":"CN",
    "gn:dem":2296,
    "gn:feature_class":"P",
    "gn:feature_code":"PPL",
    "gn:name":"Wa\u2019er",
    "gn:population":0,
    "gn:timezone":"Asia/Shanghai",
    "iso:country":"CN",
    "name:und_x_variant":[
        "Wa\u2019er"
    ],
    "name:zho_x_preferred":[
        "\u74e6\u5c14"
    ],
    "wof:name":"Wa'er",
    "wof:placetype":"locality"
},
  "geometry": {"coordinates":[102.608,28.4281],"type":"Point"}
}