{
  "type": "Feature",
  "properties": {
    "gn:admin1_code":"9.0",
    "gn:asciiname":"Daogutian",
    "gn:country_code":"CN",
    "gn:dem":212,
    "gn:feature_class":"P",
    "gn:feature_code":"PPL",
    "gn:name":"Daogutian",
    "gn:population":0,
    "gn:timezone":"Asia/Shanghai",
    "iso:country":"CN",
    "name:zho_x_preferred":[
        "\u7a3b\u8c37\u7530"
    ],
    "wof:name":"Daogutian",
    "wof:placetype":"locality"
},
  "geometry": {"coordinates":[112.33459000000001,33.45455],"type":"Point"}
}