{
  "type": "Feature",
  "properties": {
    "gn:admin1_code":"32.0",
    "gn:asciiname":"Bubaqiao",
    "gn:country_code":"CN",
    "gn:dem":341,
    "gn:feature_class":"P",
    "gn:feature_code":"PPL",
    "gn:name":"Bubaqiao",
    "gn:population":0,
    "gn:timezone":"Asia/Shanghai",
    "iso:country":"CN",
    "name:zho_x_preferred":[
        "\u8865\u575d\u6865"
    ],
    "name:zho_x_variant":[
        "\u8865\u5df4\u6865"
    ],
    "wof:name":"Bubaqiao",
    "wof:placetype":"locality"
},
  "geometry": {"coordinates":[106.982,30.1504],"type":"Point"}
}