{
  "type": "Feature",
  "properties": {
    "gn:admin1_code":"11.0",
    "gn:asciiname":"Chaotian",
    "gn:country_code":"CN",
    "gn:dem":180,
    "gn:feature_class":"P",
    "gn:feature_code":"PPL",
    "gn:name":"Chaotian",
    "gn:population":0,
    "gn:timezone":"Asia/Shanghai",
    "iso:country":"CN",
    "name:zho_x_preferred":[
        "\u6f6e\u7530"
    ],
    "wof:name":"Chaotian",
    "wof:placetype":"locality"
},
  "geometry": {"coordinates":[112.86798,25.80001],"type":"Point"}
}