{
  "type": "Feature",
  "properties": {
    "gn:admin1_code":"29.0",
    "gn:asciiname":"Jicilin",
    "gn:country_code":"CN",
    "gn:dem":1720,
    "gn:feature_class":"P",
    "gn:feature_code":"PPL",
    "gn:name":"Jicilin",
    "gn:population":0,
    "gn:timezone":"Asia/Shanghai",
    "iso:country":"CN",
    "name:zho_x_preferred":[
        "\u9e21\u8328\u6797"
    ],
    "wof:name":"Jicilin",
    "wof:placetype":"locality"
},
  "geometry": {"coordinates":[99.4067,23.958],"type":"Point"}
}