{
  "type": "Feature",
  "properties": {
    "gn:admin1_code":"32.0",
    "gn:asciiname":"Xintianzui",
    "gn:country_code":"CN",
    "gn:dem":843,
    "gn:feature_class":"P",
    "gn:feature_code":"PPL",
    "gn:name":"Xintianzui",
    "gn:population":0,
    "gn:timezone":"Asia/Shanghai",
    "iso:country":"CN",
    "name:zho_x_preferred":[
        "\u65b0\u7530\u5480"
    ],
    "wof:name":"Xintianzui",
    "wof:placetype":"locality"
},
  "geometry": {"coordinates":[104.71274,28.0351],"type":"Point"}
}