{
  "type": "Feature",
  "properties": {
    "gn:admin1_code":"5.0",
    "gn:asciiname":"Jiaban'erling Houcun",
    "gn:country_code":"CN",
    "gn:dem":295,
    "gn:feature_class":"P",
    "gn:feature_code":"PPL",
    "gn:name":"Jiaban\u2019erling Houcun",
    "gn:population":0,
    "gn:timezone":"Asia/Shanghai",
    "iso:country":"CN",
    "name:und_x_variant":[
        "Jiaban\u2019erling Houcun"
    ],
    "name:zho_x_preferred":[
        "\u67b7\u677f\u513f\u5cad\u540e\u6751"
    ],
    "wof:name":"Jiaban'erling Houcun",
    "wof:placetype":"locality"
},
  "geometry": {"coordinates":[126.71536999999999,44.15934],"type":"Point"}
}