{
  "type": "Feature",
  "properties": {
    "gn:admin1_code":"29.0",
    "gn:asciiname":"Baipo",
    "gn:country_code":"CN",
    "gn:dem":1635,
    "gn:feature_class":"P",
    "gn:feature_code":"PPL",
    "gn:name":"Baipo",
    "gn:population":0,
    "gn:timezone":"Asia/Shanghai",
    "iso:country":"CN",
    "name:zho_x_preferred":[
        "\u767d\u5761"
    ],
    "wof:name":"Baipo",
    "wof:placetype":"locality"
},
  "geometry": {"coordinates":[102.839,23.8129],"type":"Point"}
}