{
  "type": "Feature",
  "properties": {
    "gn:admin1_code":"18.0",
    "gn:asciiname":"Leibiyan",
    "gn:country_code":"CN",
    "gn:dem":938,
    "gn:feature_class":"P",
    "gn:feature_code":"PPL",
    "gn:name":"Leibiyan",
    "gn:population":0,
    "gn:timezone":"Asia/Shanghai",
    "iso:country":"CN",
    "name:zho_x_preferred":[
        "\u96f7\u6bd5\u5ca9"
    ],
    "wof:name":"Leibiyan",
    "wof:placetype":"locality"
},
  "geometry": {"coordinates":[107.38,25.9184],"type":"Point"}
}