{
  "type": "Feature",
  "properties": {
    "gn:admin1_code":"2.0",
    "gn:asciiname":"Qianjiadai",
    "gn:country_code":"CN",
    "gn:dem":8,
    "gn:feature_class":"P",
    "gn:feature_code":"PPL",
    "gn:name":"Qianjiadai",
    "gn:population":0,
    "gn:timezone":"Asia/Shanghai",
    "iso:country":"CN",
    "name:und_x_variant":[
        "\u94b1\u5bb6\u57ed"
    ],
    "wof:name":"Qianjiadai",
    "wof:placetype":"locality"
},
  "geometry": {"coordinates":[120.51335,30.45022],"type":"Point"}
}