{
  "type": "Feature",
  "properties": {
    "gn:admin1_code":"16.0",
    "gn:asciiname":"Yandun",
    "gn:country_code":"CN",
    "gn:dem":77,
    "gn:feature_class":"P",
    "gn:feature_code":"PPL",
    "gn:name":"Yandun",
    "gn:population":0,
    "gn:timezone":"Asia/Shanghai",
    "iso:country":"CN",
    "name:ceb_x_preferred":[
        "Yandun"
    ],
    "name:swe_x_preferred":[
        "Yandun"
    ],
    "wof:name":"Yandun",
    "wof:placetype":"locality"
},
  "geometry": {"coordinates":[109.08444,22.48667],"type":"Point"}
}