{
  "type": "Feature",
  "properties": {
    "gn:admin1_code":"32.0",
    "gn:asciiname":"Xuanwu",
    "gn:country_code":"CN",
    "gn:dem":623,
    "gn:feature_class":"P",
    "gn:feature_code":"PPL",
    "gn:name":"Xuanwu",
    "gn:population":0,
    "gn:timezone":"Asia/Shanghai",
    "iso:country":"CN",
    "name:zho_x_preferred":[
        "\u7384\u6b66"
    ],
    "wof:name":"Xuanwu",
    "wof:placetype":"locality"
},
  "geometry": {"coordinates":[105.077,31.9615],"type":"Point"}
}