{
  "type": "Feature",
  "properties": {
    "gn:admin1_code":"25.0",
    "gn:asciiname":"Yuanxia",
    "gn:country_code":"CN",
    "gn:dem":21,
    "gn:feature_class":"P",
    "gn:feature_code":"PPL",
    "gn:name":"Yuanxia",
    "gn:population":0,
    "gn:timezone":"Asia/Shanghai",
    "iso:country":"CN",
    "name:zho_x_preferred":[
        "\u9662\u4e0b"
    ],
    "wof:name":"Yuanxia",
    "wof:placetype":"locality"
},
  "geometry": {"coordinates":[121.30804000000001,36.82157],"type":"Point"}
}