{
  "type": "Feature",
  "properties": {
    "gn:admin1_code":"32.0",
    "gn:asciiname":"Muji",
    "gn:country_code":"CN",
    "gn:dem":2024,
    "gn:feature_class":"P",
    "gn:feature_code":"PPL",
    "gn:name":"Muji",
    "gn:population":0,
    "gn:timezone":"Asia/Shanghai",
    "iso:country":"CN",
    "name:zho_x_preferred":[
        "\u6728\u5409"
    ],
    "wof:name":"Muji",
    "wof:placetype":"locality"
},
  "geometry": {"coordinates":[102.955,28.4289],"type":"Point"}
}