{
  "type": "Feature",
  "properties": {
    "gn:admin1_code":"26.0",
    "gn:asciiname":"Liangfengyan",
    "gn:country_code":"CN",
    "gn:dem":1197,
    "gn:feature_class":"P",
    "gn:feature_code":"PPL",
    "gn:name":"Liangfengyan",
    "gn:population":0,
    "gn:timezone":"Asia/Shanghai",
    "iso:country":"CN",
    "name:zho_x_preferred":[
        "\u51c9\u51e4\u5ca9"
    ],
    "wof:name":"Liangfengyan",
    "wof:placetype":"locality"
},
  "geometry": {"coordinates":[108.67932999999999,33.46547],"type":"Point"}
}