{
  "type": "Feature",
  "properties": {
    "gn:admin1_code":"32.0",
    "gn:asciiname":"Zhageman'er",
    "gn:country_code":"CN",
    "gn:dem":3666,
    "gn:feature_class":"P",
    "gn:feature_code":"PPL",
    "gn:name":"Zhageman\u2019er",
    "gn:population":0,
    "gn:timezone":"Asia/Shanghai",
    "iso:country":"CN",
    "name:und_x_variant":[
        "Zhageman\u2019er"
    ],
    "name:zho_x_preferred":[
        "\u624e\u683c\u66fc\u5c14"
    ],
    "wof:name":"Zhageman'er",
    "wof:placetype":"locality"
},
  "geometry": {"coordinates":[101.892,32.8854],"type":"Point"}
}