{
  "type": "Feature",
  "properties": {
    "gn:admin1_code":"30",
    "gn:asciiname":"Yishen",
    "gn:country_code":"CN",
    "gn:dem":60,
    "gn:feature_class":"P",
    "gn:feature_code":"PPL",
    "gn:name":"Yishen",
    "gn:population":0,
    "gn:timezone":"Asia/Urumqi",
    "iso:country":"CN",
    "name:zho_x_preferred":[
        "L-shen-ts\u2019un"
    ],
    "name:zho_x_variant":[
        "\u4e59\u795e"
    ],
    "wof:name":"Yishen",
    "wof:placetype":"locality"
},
  "geometry": {"coordinates":[110.22452,20.34532],"type":"Point"}
}