{
  "type": "Feature",
  "properties": {
    "gn:admin1_code":"24.0",
    "gn:asciiname":"Xingcun",
    "gn:cc2":"CN",
    "gn:country_code":"CN",
    "gn:dem":820,
    "gn:feature_class":"P",
    "gn:feature_code":"PPL",
    "gn:name":"Xingcun",
    "gn:population":0,
    "gn:timezone":"Asia/Shanghai",
    "iso:country":"CN",
    "name:und_x_variant":[
        "Hsing-ts\u2019un",
        "Xingcun"
    ],
    "name:zho_x_preferred":[
        "\u884c\u6751\u9547"
    ],
    "wof:name":"Xingcun",
    "wof:placetype":"locality"
},
  "geometry": {"coordinates":[112.25667,37.17028],"type":"Point"}
}