{
  "type": "Feature",
  "properties": {
    "gn:admin1_code":"25.0",
    "gn:asciiname":"Donghonghecun",
    "gn:country_code":"CN",
    "gn:dem":58,
    "gn:feature_class":"P",
    "gn:feature_code":"PPL",
    "gn:name":"Donghonghecun",
    "gn:population":0,
    "gn:timezone":"Asia/Shanghai",
    "iso:country":"CN",
    "name:zho_x_preferred":[
        "\u4e1c\u6d2a\u6cb3\u6751"
    ],
    "wof:name":"Donghonghecun",
    "wof:placetype":"locality"
},
  "geometry": {"coordinates":[119.28095,35.54895],"type":"Point"}
}