{
  "type": "Feature",
  "properties": {
    "gn:admin1_code":"26.0",
    "gn:asciiname":"Huangtutu",
    "gn:country_code":"CN",
    "gn:dem":1289,
    "gn:feature_class":"P",
    "gn:feature_code":"PPL",
    "gn:name":"Huangtutu",
    "gn:population":0,
    "gn:timezone":"Asia/Shanghai",
    "iso:country":"CN",
    "name:zho_x_preferred":[
        "\u9ec4\u571f\u51f8"
    ],
    "wof:name":"Huangtutu",
    "wof:placetype":"locality"
},
  "geometry": {"coordinates":[109.17913,33.7617],"type":"Point"}
}