{
  "type": "Feature",
  "properties": {
    "gn:admin1_code":"26.0",
    "gn:asciiname":"Liuyuancun",
    "gn:country_code":"CN",
    "gn:dem":659,
    "gn:feature_class":"P",
    "gn:feature_code":"PPL",
    "gn:name":"Liuyuancun",
    "gn:population":0,
    "gn:timezone":"Asia/Shanghai",
    "iso:country":"CN",
    "name:und_x_variant":[
        "\u5218\u9662\u6751"
    ],
    "wof:name":"Liuyuancun",
    "wof:placetype":"locality"
},
  "geometry": {"coordinates":[107.75539000000001,33.10032],"type":"Point"}
}