{
  "type": "Feature",
  "properties": {
    "gn:admin1_code":"14.0",
    "gn:asciiname":"Quguokongcun",
    "gn:country_code":"CN",
    "gn:dem":4772,
    "gn:feature_class":"P",
    "gn:feature_code":"PPL",
    "gn:name":"Quguokongcun",
    "gn:population":0,
    "gn:timezone":"Asia/Urumqi",
    "iso:country":"CN",
    "name:zho_x_preferred":[
        "\u66f2\u679c\u5b54\u6751"
    ],
    "wof:name":"Quguokongcun",
    "wof:placetype":"locality"
},
  "geometry": {"coordinates":[91.80588,31.10527],"type":"Point"}
}