{
  "type": "Feature",
  "properties": {
    "gn:admin1_code":"4.0",
    "gn:asciiname":"Hongtumiao",
    "gn:country_code":"CN",
    "gn:dem":27,
    "gn:feature_class":"P",
    "gn:feature_code":"PPL",
    "gn:name":"Hongtumiao",
    "gn:population":0,
    "gn:timezone":"Asia/Shanghai",
    "iso:country":"CN",
    "name:zho_x_preferred":[
        "\u7ea2\u571f\u5e99"
    ],
    "wof:name":"Hongtumiao",
    "wof:placetype":"locality"
},
  "geometry": {"coordinates":[118.58799999999999,33.7356],"type":"Point"}
}