{
  "type": "Feature",
  "properties": {
    "gn:admin1_code":"12.0",
    "gn:asciiname":"Shenjialong",
    "gn:country_code":"CN",
    "gn:dem":99,
    "gn:feature_class":"P",
    "gn:feature_code":"PPL",
    "gn:name":"Shenjialong",
    "gn:population":0,
    "gn:timezone":"Asia/Shanghai",
    "iso:country":"CN",
    "name:zho_x_preferred":[
        "\u6c88\u5bb6\u5785"
    ],
    "wof:name":"Shenjialong",
    "wof:placetype":"locality"
},
  "geometry": {"coordinates":[114.36318,31.48334],"type":"Point"}
}