{
  "type": "Feature",
  "properties": {
    "gn:admin1_code":"19.0",
    "gn:asciiname":"Bingling",
    "gn:country_code":"CN",
    "gn:dem":57,
    "gn:feature_class":"P",
    "gn:feature_code":"PPL",
    "gn:name":"Bingling",
    "gn:population":0,
    "gn:timezone":"Asia/Shanghai",
    "iso:country":"CN",
    "name:und_x_variant":[
        "\u51b0\u5cad"
    ],
    "wof:name":"Bingling",
    "wof:placetype":"locality"
},
  "geometry": {"coordinates":[123.35218999999999,40.22984],"type":"Point"}
}