{
  "type": "Feature",
  "properties": {
    "gn:admin1_code":"32.0",
    "gn:asciiname":"Daogu",
    "gn:country_code":"CN",
    "gn:dem":2189,
    "gn:feature_class":"P",
    "gn:feature_code":"PPL",
    "gn:name":"Daogu",
    "gn:population":0,
    "gn:timezone":"Asia/Shanghai",
    "iso:country":"CN",
    "name:zho_x_preferred":[
        "\u7a3b\u8c37"
    ],
    "wof:name":"Daogu",
    "wof:placetype":"locality"
},
  "geometry": {"coordinates":[102.61181999999999,27.10858],"type":"Point"}
}