{
  "type": "Feature",
  "properties": {
    "gn:admin1_code":"29",
    "gn:asciiname":"Yusheng",
    "gn:country_code":"CN",
    "gn:dem":2042,
    "gn:feature_class":"P",
    "gn:feature_code":"PPL",
    "gn:name":"Yusheng",
    "gn:population":0,
    "gn:timezone":"Asia/Shanghai",
    "iso:country":"CN",
    "name:fra_x_preferred":[
        "Yusheng"
    ],
    "name:ind_x_preferred":[
        "Yee sang"
    ],
    "name:ita_x_preferred":[
        "Yusheng"
    ],
    "name:msa_x_preferred":[
        "Yee sang"
    ],
    "name:spa_x_preferred":[
        "Yusheng"
    ],
    "name:zho_x_preferred":[
        "\u96e8\u80dc"
    ],
    "name:zho_x_variant":[
        "\u6488\u8d77\u9b5a\u751f"
    ],
    "wof:name":"Yusheng",
    "wof:placetype":"locality"
},
  "geometry": {"coordinates":[103.46948,24.69698],"type":"Point"}
}