{
  "type": "Feature",
  "properties": {
    "gn:admin1_code":"30.0",
    "gn:asciiname":"Chaoweicun",
    "gn:country_code":"CN",
    "gn:dem":6,
    "gn:feature_class":"P",
    "gn:feature_code":"PPL",
    "gn:name":"Chaoweicun",
    "gn:population":0,
    "gn:timezone":"Asia/Shanghai",
    "iso:country":"CN",
    "name:zho_x_preferred":[
        "\u6f6e\u5c3e\u6751"
    ],
    "wof:name":"Chaoweicun",
    "wof:placetype":"locality"
},
  "geometry": {"coordinates":[116.22948,23.51027],"type":"Point"}
}