{
  "type": "Feature",
  "properties": {
    "gn:admin1_code":"19.0",
    "gn:asciiname":"Shangsandaocun",
    "gn:country_code":"CN",
    "gn:dem":197,
    "gn:feature_class":"P",
    "gn:feature_code":"PPL",
    "gn:name":"Shangsandaocun",
    "gn:population":0,
    "gn:timezone":"Asia/Shanghai",
    "iso:country":"CN",
    "name:zho_x_preferred":[
        "\u4e0a\u4e09\u9053\u6751"
    ],
    "wof:name":"Shangsandaocun",
    "wof:placetype":"locality"
},
  "geometry": {"coordinates":[124.193,42.2065],"type":"Point"}
}