{
  "type": "Feature",
  "properties": {
    "gn:admin1_code":"24",
    "gn:asciiname":"Sangbi",
    "gn:cc2":"CN",
    "gn:country_code":"CN",
    "gn:dem":1016,
    "gn:feature_class":"P",
    "gn:feature_code":"PPL",
    "gn:name":"Sangbi",
    "gn:population":0,
    "gn:timezone":"Asia/Shanghai",
    "iso:country":"CN",
    "name:und_x_variant":[
        "Sang-pi",
        "Sang-pi-chen",
        "Sangbi"
    ],
    "wof:name":"Sangbi",
    "wof:placetype":"locality"
},
  "geometry": {"coordinates":[110.71167,36.64056],"type":"Point"}
}