{
  "type": "Feature",
  "properties": {
    "gn:admin1_code":"01",
    "gn:asciiname":"Huiliu",
    "gn:country_code":"CN",
    "gn:dem":29,
    "gn:feature_class":"P",
    "gn:feature_code":"PPL",
    "gn:name":"Huiliu",
    "gn:population":0,
    "gn:timezone":"Asia/Shanghai",
    "iso:country":"CN",
    "name:und_x_variant":[
        "Hui-liu-chi",
        "Huiliuji",
        "Huiliu"
    ],
    "name:zho_x_preferred":[
        "\u6d04\u6e9c"
    ],
    "wof:name":"Huiliu",
    "wof:placetype":"locality"
},
  "geometry": {"coordinates":[115.96692,32.8169],"type":"Point"}
}