{
  "type": "Feature",
  "properties": {
    "gn:admin1_code":"3",
    "gn:asciiname":"Caiwu",
    "gn:country_code":"CN",
    "gn:dem":719,
    "gn:feature_class":"P",
    "gn:feature_code":"PPL",
    "gn:name":"Caiwu",
    "gn:population":0,
    "gn:timezone":"Asia/Shanghai",
    "iso:country":"CN",
    "name:zho_x_preferred":[
        "\u8521\u5c4b"
    ],
    "wof:name":"Caiwu",
    "wof:placetype":"locality"
},
  "geometry": {"coordinates":[114.16800000000001,26.0052],"type":"Point"}
}