{
  "type": "Feature",
  "properties": {
    "gn:country":"CN",
    "gn:fcode":"PPL",
    "gn:population":306450,
    "iso:country":"CN",
    "name:ces_x_preferred":[
        "Tung-jing"
    ],
    "name:deu_x_preferred":[
        "Dongying"
    ],
    "name:eng_x_preferred":[
        "Dongying"
    ],
    "name:jpn_x_preferred":[
        "\u6771\u55b6\u5e02"
    ],
    "name:kor_x_preferred":[
        "\ub465\uc789 \uc2dc"
    ],
    "name:nor_x_preferred":[
        "Dongying"
    ],
    "name:por_x_preferred":[
        "Dongying"
    ],
    "name:rus_x_preferred":[
        "\u0414\u0443\u043d\u044c\u0438\u043d"
    ],
    "name:rus_x_variant":[
        "\u0414\u0443\u043d\u044a\u0438\u043d"
    ],
    "name:srp_x_preferred":[
        "\u0414\u0443\u043d\u0433\u0458\u0438\u043d\u0433"
    ],
    "name:und_x_variant":[
        "Tung-ying"
    ],
    "name:vie_x_preferred":[
        "\u0110\u00f4ng Dinh"
    ],
    "name:yue_x_preferred":[
        "\u6771\u71df"
    ],
    "name:zho_x_preferred":[
        "\u4e1c\u8425\u5e02"
    ],
    "name:zho_x_variant":[
        "\u80dc\u5229",
        "\u80dc\u5229\u8857\u9053"
    ],
    "qs_pg:aaroncc":"CN",
    "qs_pg:gn_country":"CN",
    "qs_pg:gn_fcode":"PPL",
    "qs_pg:gn_pop":306450,
    "qs_pg:name":"\u4e1c\u8425\u5e02",
    "qs_pg:name_adm0":"\u4e2d\u570b",
    "qs_pg:name_adm1":"\u5c71\u4e1c\u7701",
    "qs_pg:photos":6,
    "qs_pg:photos_1k":1,
    "qs_pg:photos_9k":1,
    "qs_pg:photos_9r":1,
    "qs_pg:photos_all":6,
    "qs_pg:photos_sr":1,
    "qs_pg:pop_sr":10,
    "qs_pg:qs_pg_placetype":"localadmin",
    "qs_pg:qs_pg_placetype_gp":"LocalAdmin",
    "qs_pg:woe_adm0":23424781,
    "woe:adm0_id":23424781,
    "woe:name_adm0":"\u4e2d\u570b",
    "woe:name_adm1":"\u5c71\u4e1c\u7701",
    "woe:placetype":"LocalAdmin",
    "wof:name":"\u4e1c\u8425\u5e02",
    "wof:placetype":"localadmin",
    "wof:population":306450
},
  "geometry": {"coordinates":[118.48556000000001,37.45639],"type":"Point"}
}