{
  "type": "Feature",
  "properties": {
    "gn:admin1_code":"21.0",
    "gn:asciiname":"Nanchuan",
    "gn:country_code":"CN",
    "gn:dem":2082,
    "gn:feature_class":"P",
    "gn:feature_code":"PPL",
    "gn:name":"Nanchuan",
    "gn:population":0,
    "gn:timezone":"Asia/Shanghai",
    "iso:country":"CN",
    "name:zho_x_preferred":[
        "\u5357\u5ddd"
    ],
    "wof:name":"Nanchuan",
    "wof:placetype":"locality"
},
  "geometry": {"coordinates":[105.733,36.3507],"type":"Point"}
}