{
  "type": "Feature",
  "properties": {
    "gn:admin1_code":"22.0",
    "gn:asciiname":"Yuhuangmiaocun",
    "gn:country_code":"CN",
    "gn:dem":495,
    "gn:feature_class":"P",
    "gn:feature_code":"PPL",
    "gn:name":"Yuhuangmiaocun",
    "gn:population":0,
    "gn:timezone":"Asia/Shanghai",
    "iso:country":"CN",
    "name:zho_x_preferred":[
        "\u7389\u7687\u5e99\u6751"
    ],
    "wof:name":"Yuhuangmiaocun",
    "wof:placetype":"locality"
},
  "geometry": {"coordinates":[115.90563,39.95414],"type":"Point"}
}