{
  "type": "Feature",
  "properties": {
    "gn:admin1_code":"24.0",
    "gn:asciiname":"Fentaigou",
    "gn:country_code":"CN",
    "gn:dem":1738,
    "gn:feature_class":"P",
    "gn:feature_code":"PPL",
    "gn:name":"Fentaigou",
    "gn:population":0,
    "gn:timezone":"Asia/Shanghai",
    "iso:country":"CN",
    "name:zho_x_preferred":[
        "\u575f\u53f0\u6c9f"
    ],
    "wof:name":"Fentaigou",
    "wof:placetype":"locality"
},
  "geometry": {"coordinates":[113.98304,39.63028],"type":"Point"}
}