{
  "type": "Feature",
  "properties": {
    "gn:admin1_code":"11.0",
    "gn:asciiname":"Zhangheling",
    "gn:country_code":"CN",
    "gn:dem":271,
    "gn:feature_class":"P",
    "gn:feature_code":"PPL",
    "gn:name":"Zhangheling",
    "gn:population":0,
    "gn:timezone":"Asia/Shanghai",
    "iso:country":"CN",
    "name:zho_x_preferred":[
        "\u5f20\u79be\u5cad"
    ],
    "wof:name":"Zhangheling",
    "wof:placetype":"locality"
},
  "geometry": {"coordinates":[113.16386,26.61552],"type":"Point"}
}