{
  "type": "Feature",
  "properties": {
    "gn:admin1_code":"32.0",
    "gn:asciiname":"Shazui",
    "gn:country_code":"CN",
    "gn:dem":356,
    "gn:feature_class":"P",
    "gn:feature_code":"PPL",
    "gn:name":"Shazui",
    "gn:population":0,
    "gn:timezone":"Asia/Shanghai",
    "iso:country":"CN",
    "name:zho_x_preferred":[
        "\u6c99\u5634"
    ],
    "wof:name":"Shazui",
    "wof:placetype":"locality"
},
  "geometry": {"coordinates":[106.788,30.6516],"type":"Point"}
}