{
  "type": "Feature",
  "properties": {
    "gn:admin1_code":"8.0",
    "gn:asciiname":"Languang",
    "gn:country_code":"CN",
    "gn:dem":251,
    "gn:feature_class":"P",
    "gn:feature_code":"PPL",
    "gn:name":"Languang",
    "gn:population":0,
    "gn:timezone":"Asia/Shanghai",
    "iso:country":"CN",
    "name:zho_x_preferred":[
        "\u5c9a\u5149"
    ],
    "wof:name":"Languang",
    "wof:placetype":"locality"
},
  "geometry": {"coordinates":[126.97563999999998,47.82374],"type":"Point"}
}