{
  "type": "Feature",
  "properties": {
    "gn:admin1_code":"0.0",
    "gn:asciiname":"Pai-shih-yen",
    "gn:country_code":"CN",
    "gn:dem":1585,
    "gn:feature_class":"P",
    "gn:feature_code":"PPL",
    "gn:name":"Pai-shih-yen",
    "gn:population":0,
    "gn:timezone":"Asia/Shanghai",
    "iso:country":"CN",
    "wof:name":"Pai-shih-yen",
    "wof:placetype":"locality"
},
  "geometry": {"coordinates":[104.50593000000001,23.66049],"type":"Point"}
}