{
  "type": "Feature",
  "properties": {
    "gn:admin1_code":"3",
    "gn:asciiname":"Shanxia",
    "gn:country_code":"CN",
    "gn:dem":231,
    "gn:feature_class":"P",
    "gn:feature_code":"PPL",
    "gn:name":"Shanxia",
    "gn:population":0,
    "gn:timezone":"Asia/Shanghai",
    "iso:country":"CN",
    "name:ces_x_preferred":[
        "Shanxia"
    ],
    "name:deu_x_preferred":[
        "Shanxia"
    ],
    "name:nld_x_preferred":[
        "Shanxia"
    ],
    "name:ori_x_preferred":[
        "Shanxia"
    ],
    "name:pol_x_preferred":[
        "Shanxia"
    ],
    "name:slk_x_preferred":[
        "Shanxia"
    ],
    "name:spa_x_preferred":[
        "Shanxia"
    ],
    "name:ukr_x_preferred":[
        "Shanxia tianzhenensis"
    ],
    "name:vie_x_preferred":[
        "Shanxia"
    ],
    "name:vol_x_preferred":[
        "Shanxia"
    ],
    "name:zho_x_preferred":[
        "\u5c71\u897f\u9f8d\u5c6c"
    ],
    "wof:name":"Shanxia",
    "wof:placetype":"locality"
},
  "geometry": {"coordinates":[115.38167,26.85389],"type":"Point"}
}