{
  "type": "Feature",
  "properties": {
    "gn:admin1_code":"4.0",
    "gn:asciiname":"Qinwanzhuang",
    "gn:country_code":"CN",
    "gn:dem":7,
    "gn:feature_class":"P",
    "gn:feature_code":"PPL",
    "gn:name":"Qinwanzhuang",
    "gn:population":0,
    "gn:timezone":"Asia/Shanghai",
    "iso:country":"CN",
    "name:zho_x_preferred":[
        "Qinwanzhuang"
    ],
    "name:zho_x_variant":[
        "\u79e6\u4e07\u5e84"
    ],
    "wof:name":"Qinwanzhuang",
    "wof:placetype":"locality"
},
  "geometry": {"coordinates":[119.22159000000001,33.30508],"type":"Point"}
}