{
  "type": "Feature",
  "properties": {
    "gn:admin1_code":"9",
    "gn:asciiname":"Xiangshanmiao",
    "gn:country_code":"CN",
    "gn:dem":44,
    "gn:feature_class":"P",
    "gn:feature_code":"PPL",
    "gn:name":"Xiangshanmiao",
    "gn:population":0,
    "gn:timezone":"Asia/Shanghai",
    "iso:country":"CN",
    "name:zho_x_preferred":[
        "\u9999\u5c71\u5e99"
    ],
    "wof:name":"Xiangshanmiao",
    "wof:placetype":"locality"
},
  "geometry": {"coordinates":[116.129,34.2248],"type":"Point"}
}