{
  "type": "Feature",
  "properties": {
    "gn:admin1_code":"05",
    "gn:asciiname":"Xiaoqinggoumen",
    "gn:country_code":"CN",
    "gn:dem":316,
    "gn:feature_class":"P",
    "gn:feature_code":"PPL",
    "gn:name":"Xiaoqinggoumen",
    "gn:population":0,
    "gn:timezone":"Asia/Shanghai",
    "iso:country":"CN",
    "name:und_x_variant":[
        "\u5c0f\u9752\u6c9f\u95e8",
        "Xiaoqinggou"
    ],
    "wof:name":"Xiaoqinggoumen",
    "wof:placetype":"locality"
},
  "geometry": {"coordinates":[126.20917,41.19472],"type":"Point"}
}