{
  "type": "Feature",
  "properties": {
    "gn:admin1_code":"4.0",
    "gn:asciiname":"Hutang",
    "gn:country_code":"CN",
    "gn:dem":30,
    "gn:feature_class":"P",
    "gn:feature_code":"PPL",
    "gn:name":"Hutang",
    "gn:population":0,
    "gn:timezone":"Asia/Shanghai",
    "iso:country":"CN",
    "name:mlg_x_preferred":[
        "Hutang"
    ],
    "name:zho_x_preferred":[
        "\u80e1\u5858"
    ],
    "wof:name":"Hutang",
    "wof:placetype":"locality"
},
  "geometry": {"coordinates":[118.059,34.4477],"type":"Point"}
}