{
  "type": "Feature",
  "properties": {
    "gn:admin1_code":"25",
    "gn:asciiname":"Gengjia",
    "gn:country_code":"CN",
    "gn:dem":12,
    "gn:feature_class":"P",
    "gn:feature_code":"PPL",
    "gn:name":"Gengjia",
    "gn:population":0,
    "gn:timezone":"Asia/Shanghai",
    "iso:country":"CN",
    "name:zho_x_preferred":[
        "\u803f\u5bb6"
    ],
    "wof:name":"Gengjia",
    "wof:placetype":"locality"
},
  "geometry": {"coordinates":[117.88200000000001,37.0979],"type":"Point"}
}