{
  "type": "Feature",
  "properties": {
    "gn:admin1_code":"26.0",
    "gn:asciiname":"Xibeishancun",
    "gn:country_code":"CN",
    "gn:dem":963,
    "gn:feature_class":"P",
    "gn:feature_code":"PPL",
    "gn:name":"Xibeishancun",
    "gn:population":0,
    "gn:timezone":"Asia/Shanghai",
    "iso:country":"CN",
    "name:zho_x_preferred":[
        "\u897f\u5317\u5c71\u6751"
    ],
    "wof:name":"Xibeishancun",
    "wof:placetype":"locality"
},
  "geometry": {"coordinates":[110.38838,37.27179],"type":"Point"}
}