{
  "type": "Feature",
  "properties": {
    "gn:admin1_code":"33.0",
    "gn:asciiname":"Guipeng",
    "gn:country_code":"CN",
    "gn:dem":357,
    "gn:feature_class":"P",
    "gn:feature_code":"PPL",
    "gn:name":"Guipeng",
    "gn:population":0,
    "gn:timezone":"Asia/Shanghai",
    "iso:country":"CN",
    "name:zho_x_preferred":[
        "\u8d35\u68da"
    ],
    "wof:name":"Guipeng",
    "wof:placetype":"locality"
},
  "geometry": {"coordinates":[109.27083,28.54956],"type":"Point"}
}