{
  "type": "Feature",
  "properties": {
    "gn:admin1_code":"30.0",
    "gn:asciiname":"Hongjunying",
    "gn:country_code":"CN",
    "gn:dem":41,
    "gn:feature_class":"P",
    "gn:feature_code":"PPL",
    "gn:name":"Hongjunying",
    "gn:population":0,
    "gn:timezone":"Asia/Shanghai",
    "iso:country":"CN",
    "name:zho_x_preferred":[
        "\u7ea2\u519b\u8425"
    ],
    "wof:name":"Hongjunying",
    "wof:placetype":"locality"
},
  "geometry": {"coordinates":[114.84516000000001,23.83865],"type":"Point"}
}