{
  "type": "Feature",
  "properties": {
    "gn:admin1_code":"3",
    "gn:asciiname":"Shangqiuwu",
    "gn:country_code":"CN",
    "gn:dem":352,
    "gn:feature_class":"P",
    "gn:feature_code":"PPL",
    "gn:name":"Shangqiuwu",
    "gn:population":0,
    "gn:timezone":"Asia/Shanghai",
    "iso:country":"CN",
    "name:zho_x_preferred":[
        "\u4e0a\u90b1\u5c4b"
    ],
    "wof:name":"Shangqiuwu",
    "wof:placetype":"locality"
},
  "geometry": {"coordinates":[114.09699999999999,25.7256],"type":"Point"}
}