{
  "type": "Feature",
  "properties": {
    "gn:admin1_code":"14",
    "gn:asciiname":"Yangning",
    "gn:country_code":"CN",
    "gn:dem":4971,
    "gn:feature_class":"P",
    "gn:feature_code":"PPL",
    "gn:name":"Yangning",
    "gn:population":0,
    "gn:timezone":"Asia/Urumqi",
    "iso:country":"CN",
    "name:zho_x_preferred":[
        "\u592e\u5b81"
    ],
    "wof:name":"Yangning",
    "wof:placetype":"locality"
},
  "geometry": {"coordinates":[88.8023,32.7583],"type":"Point"}
}