{
  "type": "Feature",
  "properties": {
    "gn:admin1_code":"2",
    "gn:asciiname":"Zhangyuankeng",
    "gn:country_code":"CN",
    "gn:dem":592,
    "gn:feature_class":"P",
    "gn:feature_code":"PPL",
    "gn:name":"Zhangyuankeng",
    "gn:population":0,
    "gn:timezone":"Asia/Shanghai",
    "iso:country":"CN",
    "name:zho_x_preferred":[
        "\u5f20\u6e90\u5751"
    ],
    "wof:name":"Zhangyuankeng",
    "wof:placetype":"locality"
},
  "geometry": {"coordinates":[118.94194,27.58194],"type":"Point"}
}