{
  "type": "Feature",
  "properties": {
    "gn:admin1_code":"32.0",
    "gn:asciiname":"Dongmiaozi",
    "gn:country_code":"CN",
    "gn:dem":322,
    "gn:feature_class":"P",
    "gn:feature_code":"PPL",
    "gn:name":"Dongmiaozi",
    "gn:population":0,
    "gn:timezone":"Asia/Shanghai",
    "iso:country":"CN",
    "name:zho_x_preferred":[
        "\u4e1c\u5e99\u5b50"
    ],
    "wof:name":"Dongmiaozi",
    "wof:placetype":"locality"
},
  "geometry": {"coordinates":[106.381,30.79300000000001],"type":"Point"}
}