{
  "type": "Feature",
  "properties": {
    "gn:admin1_code":"2",
    "gn:asciiname":"Entan",
    "gn:country_code":"CN",
    "gn:dem":180,
    "gn:feature_class":"P",
    "gn:feature_code":"PPL",
    "gn:name":"Entan",
    "gn:population":0,
    "gn:timezone":"Asia/Shanghai",
    "iso:country":"CN",
    "name:zho_x_preferred":[
        "\u6069\u6f6d"
    ],
    "wof:name":"Entan",
    "wof:placetype":"locality"
},
  "geometry": {"coordinates":[118.47278,28.58194],"type":"Point"}
}