{
  "type": "Feature",
  "properties": {
    "gn:admin1_code":"4.0",
    "gn:asciiname":"Qianhe",
    "gn:country_code":"CN",
    "gn:dem":8,
    "gn:feature_class":"P",
    "gn:feature_code":"PPL",
    "gn:name":"Qianhe",
    "gn:population":0,
    "gn:timezone":"Asia/Shanghai",
    "iso:country":"CN",
    "name:und_x_variant":[
        "\u524d\u6cb3"
    ],
    "name:zho_x_preferred":[
        "\u524d\u6cb3"
    ],
    "wof:name":"Qianhe",
    "wof:placetype":"locality"
},
  "geometry": {"coordinates":[120.66674999999999,31.34855],"type":"Point"}
}