{
  "type": "Feature",
  "properties": {
    "gn:admin1_code":"18.0",
    "gn:asciiname":"Sanghe",
    "gn:country_code":"CN",
    "gn:dem":1970,
    "gn:feature_class":"P",
    "gn:feature_code":"PPL",
    "gn:name":"Sanghe",
    "gn:population":0,
    "gn:timezone":"Asia/Shanghai",
    "iso:country":"CN",
    "wof:name":"Sanghe",
    "wof:placetype":"locality"
},
  "geometry": {"coordinates":[104.63333,26.75833],"type":"Point"}
}