{
  "type": "Feature",
  "properties": {
    "gn:admin1_code":"24.0",
    "gn:asciiname":"Zhangquan",
    "gn:country_code":"CN",
    "gn:dem":899,
    "gn:feature_class":"P",
    "gn:feature_code":"PPL",
    "gn:name":"Zhangquan",
    "gn:population":0,
    "gn:timezone":"Asia/Shanghai",
    "iso:country":"CN",
    "name:zho_x_preferred":[
        "\u5f20\u6cc9"
    ],
    "wof:name":"Zhangquan",
    "wof:placetype":"locality"
},
  "geometry": {"coordinates":[111.5652,36.49942],"type":"Point"}
}