{
  "type": "Feature",
  "properties": {
    "gn:admin1_code":"09",
    "gn:asciiname":"Dongcun",
    "gn:country_code":"CN",
    "gn:dem":169,
    "gn:feature_class":"P",
    "gn:feature_code":"PPL",
    "gn:name":"Dongcun",
    "gn:population":0,
    "gn:timezone":"Asia/Shanghai",
    "iso:country":"CN",
    "wof:name":"Dongcun",
    "wof:placetype":"locality"
},
  "geometry": {"coordinates":[112.80028,33.79417],"type":"Point"}
}