{
  "type": "Feature",
  "properties": {
    "gn:admin1_code":"3",
    "gn:asciiname":"Huangshijiao",
    "gn:country_code":"CN",
    "gn:dem":333,
    "gn:feature_class":"P",
    "gn:feature_code":"PPL",
    "gn:name":"Huangshijiao",
    "gn:population":0,
    "gn:timezone":"Asia/Shanghai",
    "iso:country":"CN",
    "name:zho_x_preferred":[
        "\u749c\u77f3\u89d2"
    ],
    "wof:name":"Huangshijiao",
    "wof:placetype":"locality"
},
  "geometry": {"coordinates":[114.19,26.0783],"type":"Point"}
}