{
  "type": "Feature",
  "properties": {
    "gn:admin1_code":"29.0",
    "gn:asciiname":"Fengyuzhen",
    "gn:country_code":"CN",
    "gn:dem":2179,
    "gn:feature_class":"P",
    "gn:feature_code":"PPL",
    "gn:name":"Fengyuzhen",
    "gn:population":0,
    "gn:timezone":"Asia/Shanghai",
    "iso:country":"CN",
    "wof:name":"Fengyuzhen",
    "wof:placetype":"locality"
},
  "geometry": {"coordinates":[99.93333,25.98333],"type":"Point"}
}