{
  "type": "Feature",
  "properties": {
    "gn:admin1_code":"14.0",
    "gn:asciiname":"Doxoggu",
    "gn:country_code":"CN",
    "gn:dem":4663,
    "gn:feature_class":"P",
    "gn:feature_code":"PPL",
    "gn:name":"Doxoggu",
    "gn:population":0,
    "gn:timezone":"Asia/Urumqi",
    "iso:country":"CN",
    "name:bod_x_preferred":[
        "Doxoggu"
    ],
    "name:zho_x_preferred":[
        "Duoxueku"
    ],
    "name:zho_x_variant":[
        "\u591a\u5b66\u5e93"
    ],
    "wof:name":"Doxoggu",
    "wof:placetype":"locality"
},
  "geometry": {"coordinates":[90.13529,31.86457],"type":"Point"}
}