{
  "type": "Feature",
  "properties": {
    "gn:admin1_code":"30.0",
    "gn:asciiname":"Yuanshanli",
    "gn:country_code":"CN",
    "gn:dem":288,
    "gn:feature_class":"P",
    "gn:feature_code":"PPL",
    "gn:name":"Yuanshanli",
    "gn:population":0,
    "gn:timezone":"Asia/Shanghai",
    "iso:country":"CN",
    "name:zho_x_preferred":[
        "Yuanshanli"
    ],
    "name:zho_x_variant":[
        "\u56ed\u5c71\u91cc"
    ],
    "wof:name":"Yuanshanli",
    "wof:placetype":"locality"
},
  "geometry": {"coordinates":[115.30167,24.62778],"type":"Point"}
}