{
  "type": "Feature",
  "properties": {
    "gn:admin1_code":"7.0",
    "gn:asciiname":"Jinhuang",
    "gn:country_code":"CN",
    "gn:dem":1051,
    "gn:feature_class":"P",
    "gn:feature_code":"PPL",
    "gn:name":"Jinhuang",
    "gn:population":0,
    "gn:timezone":"Asia/Shanghai",
    "iso:country":"CN",
    "name:zho_x_preferred":[
        "\u91d1\u9ec4"
    ],
    "wof:name":"Jinhuang",
    "wof:placetype":"locality"
},
  "geometry": {"coordinates":[118.04940000000001,25.66931],"type":"Point"}
}