{
  "type": "Feature",
  "properties": {
    "gn:admin1_code":"21.0",
    "gn:asciiname":"Dongjiao",
    "gn:country_code":"CN",
    "gn:dem":1719,
    "gn:feature_class":"P",
    "gn:feature_code":"PPLA4",
    "gn:name":"Dongjiao",
    "gn:population":0,
    "gn:timezone":"Asia/Shanghai",
    "iso:country":"CN",
    "name:und_x_variant":[
        "\u4e1c\u90ca",
        "Dongjiao Xiang",
        "\u4e1c\u90ca\u4e61"
    ],
    "name:zho_x_preferred":[
        "\u4e1c\u90ca\u4e61"
    ],
    "wof:name":"Dongjiao",
    "wof:placetype":"locality"
},
  "geometry": {"coordinates":[106.28876,36.00458],"type":"Point"}
}