{
  "type": "Feature",
  "properties": {
    "gn:admin1_code":"29.0",
    "gn:asciiname":"Mojiao",
    "gn:country_code":"CN",
    "gn:dem":2183,
    "gn:feature_class":"P",
    "gn:feature_code":"PPL",
    "gn:name":"Mojiao",
    "gn:population":0,
    "gn:timezone":"Asia/Shanghai",
    "iso:country":"CN",
    "name:und_x_variant":[
        "\u78e8\u811a"
    ],
    "wof:name":"Mojiao",
    "wof:placetype":"locality"
},
  "geometry": {"coordinates":[103.902,25.9303],"type":"Point"}
}