{
  "type": "Feature",
  "properties": {
    "gn:admin1_code":"19.0",
    "gn:asciiname":"Aojiabu",
    "gn:country_code":"CN",
    "gn:dem":69,
    "gn:feature_class":"P",
    "gn:feature_code":"PPL",
    "gn:name":"Aojiabu",
    "gn:population":0,
    "gn:timezone":"Asia/Shanghai",
    "iso:country":"CN",
    "name:und_x_variant":[
        "Aojiabao",
        "\u6556\u5bb6\u5821",
        "Aojiabu"
    ],
    "wof:name":"Aojiabu",
    "wof:placetype":"locality"
},
  "geometry": {"coordinates":[123.94349,40.2086],"type":"Point"}
}