{
  "type": "Feature",
  "properties": {
    "gn:admin1_code":"10",
    "gn:asciiname":"Shangchenyi",
    "gn:country_code":"CN",
    "gn:dem":211,
    "gn:feature_class":"P",
    "gn:feature_code":"PPL",
    "gn:name":"Shangchenyi",
    "gn:population":0,
    "gn:timezone":"Asia/Shanghai",
    "iso:country":"CN",
    "name:und_x_variant":[
        "Shang-ch\u2019en-i",
        "Shangchenyi"
    ],
    "name:zho_x_preferred":[
        "\u4e0a\u9648\u9a7f"
    ],
    "wof:name":"Shangchenyi",
    "wof:placetype":"locality"
},
  "geometry": {"coordinates":[115.18783999999999,39.37206],"type":"Point"}
}