{
  "type": "Feature",
  "properties": {
    "gn:admin1_code":"32.0",
    "gn:asciiname":"Youyi",
    "gn:country_code":"CN",
    "gn:dem":544,
    "gn:feature_class":"P",
    "gn:feature_code":"PPL",
    "gn:name":"Youyi",
    "gn:population":0,
    "gn:timezone":"Asia/Shanghai",
    "iso:country":"CN",
    "name:zho_x_preferred":[
        "\u53cb\u8c0a"
    ],
    "wof:name":"Youyi",
    "wof:placetype":"locality"
},
  "geometry": {"coordinates":[103.166,29.8665],"type":"Point"}
}