{
  "type": "Feature",
  "properties": {
    "gn:admin1_code":"7",
    "gn:asciiname":"Houlinpu",
    "gn:country_code":"CN",
    "gn:dem":26,
    "gn:feature_class":"P",
    "gn:feature_code":"PPL",
    "gn:name":"Houlinpu",
    "gn:population":0,
    "gn:timezone":"Asia/Shanghai",
    "iso:country":"CN",
    "name:zho_x_preferred":[
        "\u540e\u6797\u57d4"
    ],
    "wof:name":"Houlinpu",
    "wof:placetype":"locality"
},
  "geometry": {"coordinates":[118.47331,24.86608],"type":"Point"}
}