{
  "type": "Feature",
  "properties": {
    "gn:admin1_code":"2.0",
    "gn:asciiname":"Huoshaoji",
    "gn:country_code":"CN",
    "gn:dem":449,
    "gn:feature_class":"P",
    "gn:feature_code":"PPL",
    "gn:name":"Huoshaoji",
    "gn:population":0,
    "gn:timezone":"Asia/Shanghai",
    "iso:country":"CN",
    "name:und_x_variant":[
        "\u706b\u70e7\u57fa",
        "Huoshaoji"
    ],
    "wof:name":"Huoshaoji",
    "wof:placetype":"locality"
},
  "geometry": {"coordinates":[119.64716,29.9416],"type":"Point"}
}