{
  "type": "Feature",
  "properties": {
    "gn:admin1_code":"1.0",
    "gn:asciiname":"Dianmenkou",
    "gn:country_code":"CN",
    "gn:dem":18,
    "gn:feature_class":"P",
    "gn:feature_code":"PPL",
    "gn:name":"Dianmenkou",
    "gn:population":0,
    "gn:timezone":"Asia/Shanghai",
    "iso:country":"CN",
    "name:zho_x_preferred":[
        "\u5e97\u95e8\u53e3"
    ],
    "wof:name":"Dianmenkou",
    "wof:placetype":"locality"
},
  "geometry": {"coordinates":[118.86332,31.0324],"type":"Point"}
}