{
  "type": "Feature",
  "properties": {
    "gn:admin1_code":"3.0",
    "gn:asciiname":"Dongkuang",
    "gn:country_code":"CN",
    "gn:dem":164,
    "gn:feature_class":"P",
    "gn:feature_code":"PPL",
    "gn:name":"Dongkuang",
    "gn:population":0,
    "gn:timezone":"Asia/Shanghai",
    "iso:country":"CN",
    "name:zho_x_preferred":[
        "\u4e1c\u77ff"
    ],
    "wof:name":"Dongkuang",
    "wof:placetype":"locality"
},
  "geometry": {"coordinates":[117.75578,28.98021],"type":"Point"}
}