{
  "type": "Feature",
  "properties": {
    "gn:admin1_code":"18",
    "gn:asciiname":"Sujiaba",
    "gn:country_code":"CN",
    "gn:dem":930,
    "gn:feature_class":"P",
    "gn:feature_code":"PPL",
    "gn:name":"Sujiaba",
    "gn:population":0,
    "gn:timezone":"Asia/Shanghai",
    "iso:country":"CN",
    "name:zho_x_preferred":[
        "\u82cf\u5bb6\u575d"
    ],
    "wof:name":"Sujiaba",
    "wof:placetype":"locality"
},
  "geometry": {"coordinates":[106.925,27.557],"type":"Point"}
}