{
  "type": "Feature",
  "properties": {
    "gn:admin1_code":"24.0",
    "gn:asciiname":"Wangliang",
    "gn:country_code":"CN",
    "gn:dem":1124,
    "gn:feature_class":"P",
    "gn:feature_code":"PPL",
    "gn:name":"Wangliang",
    "gn:population":0,
    "gn:timezone":"Asia/Shanghai",
    "iso:country":"CN",
    "name:zho_x_preferred":[
        "\u738b\u826f"
    ],
    "wof:name":"Wangliang",
    "wof:placetype":"locality"
},
  "geometry": {"coordinates":[111.92372,35.69024],"type":"Point"}
}