{
  "type": "Feature",
  "properties": {
    "gn:admin1_code":"32.0",
    "gn:asciiname":"Jingu",
    "gn:country_code":"CN",
    "gn:dem":359,
    "gn:feature_class":"P",
    "gn:feature_code":"PPL",
    "gn:name":"Jingu",
    "gn:population":0,
    "gn:timezone":"Asia/Shanghai",
    "iso:country":"CN",
    "name:ceb_x_preferred":[
        "Jingu"
    ],
    "name:deu_x_preferred":[
        "Jingu"
    ],
    "name:hrv_x_preferred":[
        "Jing\u016b"
    ],
    "name:spa_x_preferred":[
        "Jingu"
    ],
    "name:swe_x_preferred":[
        "Jingu"
    ],
    "name:zho_x_preferred":[
        "\u91d1\u9f13"
    ],
    "wof:name":"Jingu",
    "wof:placetype":"locality"
},
  "geometry": {"coordinates":[107.044,30.4826],"type":"Point"}
}