{
  "type": "Feature",
  "properties": {
    "gn:admin1_code":"18",
    "gn:asciiname":"Longgun",
    "gn:country_code":"CN",
    "gn:dem":714,
    "gn:feature_class":"P",
    "gn:feature_code":"PPL",
    "gn:name":"Longgun",
    "gn:population":0,
    "gn:timezone":"Asia/Shanghai",
    "iso:country":"CN",
    "name:zho_x_preferred":[
        "\u9f99\u6eda"
    ],
    "wof:name":"Longgun",
    "wof:placetype":"locality"
},
  "geometry": {"coordinates":[107.831,27.1349],"type":"Point"}
}