{
  "type": "Feature",
  "properties": {
    "gn:admin1_code":"11.0",
    "gn:asciiname":"Aojia'ao",
    "gn:country_code":"CN",
    "gn:dem":66,
    "gn:feature_class":"P",
    "gn:feature_code":"PPL",
    "gn:name":"Aojia\u2019ao",
    "gn:population":0,
    "gn:timezone":"Asia/Shanghai",
    "iso:country":"CN",
    "name:und_x_variant":[
        "Aojia\u2019ao"
    ],
    "name:zho_x_preferred":[
        "\u6556\u5bb6\u5773"
    ],
    "wof:name":"Aojia'ao",
    "wof:placetype":"locality"
},
  "geometry": {"coordinates":[113.15325,28.75031],"type":"Point"}
}