{
  "type": "Feature",
  "properties": {
    "gn:admin1_code":"8.0",
    "gn:asciiname":"Chiwei Qidui",
    "gn:country_code":"CN",
    "gn:dem":241,
    "gn:feature_class":"P",
    "gn:feature_code":"PPLF",
    "gn:name":"Chiwei Qidui",
    "gn:population":0,
    "gn:timezone":"Asia/Shanghai",
    "iso:country":"CN",
    "name:zho_x_preferred":[
        "\u8d64\u536b\u4e03\u961f"
    ],
    "wof:name":"Chiwei Qidui",
    "wof:placetype":"locality"
},
  "geometry": {"coordinates":[124.85858,48.90078],"type":"Point"}
}