{
  "type": "Feature",
  "properties": {
    "gn:admin1_code":"4.0",
    "gn:asciiname":"Nandang",
    "gn:country_code":"CN",
    "gn:dem":3,
    "gn:feature_class":"P",
    "gn:feature_code":"PPL",
    "gn:name":"Nandang",
    "gn:population":0,
    "gn:timezone":"Asia/Shanghai",
    "iso:country":"CN",
    "name:zho_x_preferred":[
        "Nandang"
    ],
    "name:zho_x_variant":[
        "\u5357\u8361"
    ],
    "wof:name":"Nandang",
    "wof:placetype":"locality"
},
  "geometry": {"coordinates":[119.61541,33.62963],"type":"Point"}
}