{
  "type": "Feature",
  "properties": {
    "gn:admin1_code":"2.0",
    "gn:asciiname":"Xuanjia",
    "gn:country_code":"CN",
    "gn:dem":20,
    "gn:feature_class":"P",
    "gn:feature_code":"PPL",
    "gn:name":"Xuanjia",
    "gn:population":0,
    "gn:timezone":"Asia/Shanghai",
    "iso:country":"CN",
    "name:zho_x_preferred":[
        "\u5ba3\u5bb6"
    ],
    "wof:name":"Xuanjia",
    "wof:placetype":"locality"
},
  "geometry": {"coordinates":[121.27072,28.55933],"type":"Point"}
}