{
  "type": "Feature",
  "properties": {
    "gn:admin1_code":"18.0",
    "gn:asciiname":"Panjiatian",
    "gn:country_code":"CN",
    "gn:dem":362,
    "gn:feature_class":"P",
    "gn:feature_code":"PPL",
    "gn:name":"Panjiatian",
    "gn:population":0,
    "gn:timezone":"Asia/Shanghai",
    "iso:country":"CN",
    "name:zho_x_preferred":[
        "\u76d8\u5bb6\u7530"
    ],
    "wof:name":"Panjiatian",
    "wof:placetype":"locality"
},
  "geometry": {"coordinates":[109.30500000000001,26.757],"type":"Point"}
}