{
  "type": "Feature",
  "properties": {
    "gn:admin1_code":"3.0",
    "gn:asciiname":"Tengfangcun",
    "gn:country_code":"CN",
    "gn:dem":30,
    "gn:feature_class":"P",
    "gn:feature_code":"PPL",
    "gn:name":"Tengfangcun",
    "gn:population":0,
    "gn:timezone":"Asia/Shanghai",
    "iso:country":"CN",
    "name:und_x_variant":[
        "\u6ed5\u574a\u6751"
    ],
    "wof:name":"Tengfangcun",
    "wof:placetype":"locality"
},
  "geometry": {"coordinates":[115.60912,28.40627000000001],"type":"Point"}
}