{
  "type": "Feature",
  "properties": {
    "gn:admin1_code":"4.0",
    "gn:asciiname":"Qisha",
    "gn:country_code":"CN",
    "gn:dem":5,
    "gn:feature_class":"P",
    "gn:feature_code":"PPL",
    "gn:name":"Qisha",
    "gn:population":0,
    "gn:timezone":"Asia/Shanghai",
    "iso:country":"CN",
    "name:und_x_variant":[
        "\u789b\u7802"
    ],
    "name:zho_x_preferred":[
        "\u789b\u7802"
    ],
    "wof:name":"Qisha",
    "wof:placetype":"locality"
},
  "geometry": {"coordinates":[120.84218,31.24023],"type":"Point"}
}