{
  "type": "Feature",
  "properties": {
    "gn:admin1_code":"30.0",
    "gn:asciiname":"Taojun Qiancun",
    "gn:country_code":"CN",
    "gn:dem":291,
    "gn:feature_class":"P",
    "gn:feature_code":"PPL",
    "gn:name":"Taojun Qiancun",
    "gn:population":0,
    "gn:timezone":"Asia/Shanghai",
    "iso:country":"CN",
    "name:zho_x_preferred":[
        "\u6843\u519b\u524d\u6751"
    ],
    "wof:name":"Taojun Qiancun",
    "wof:placetype":"locality"
},
  "geometry": {"coordinates":[115.66388999999999,23.83477],"type":"Point"}
}