{
  "type": "Feature",
  "properties": {
    "gn:admin1_code":"16.0",
    "gn:asciiname":"Changhua",
    "gn:country_code":"CN",
    "gn:dem":154,
    "gn:feature_class":"P",
    "gn:feature_code":"PPL",
    "gn:name":"Changhua",
    "gn:population":0,
    "gn:timezone":"Asia/Shanghai",
    "iso:country":"CN",
    "name:ara_x_preferred":[
        "\u062a\u0634\u0627\u0646\u063a\u0647\u0648\u0627"
    ],
    "name:ben_x_preferred":[
        "\u099a\u09be\u0999\u09cd\u0998\u09c1\u09df\u09be"
    ],
    "name:ces_x_preferred":[
        "\u010cang-chua"
    ],
    "name:deu_x_preferred":[
        "Changhua"
    ],
    "name:ell_x_preferred":[
        "\u03a4\u03c3\u03ac\u03bd\u03b3\u03ba\u03bf\u03c5\u03b1"
    ],
    "name:fas_x_preferred":[
        "\u062c\u0627\u0646\u06af\u0648\u0622"
    ],
    "name:fin_x_preferred":[
        "Changhua"
    ],
    "name:fra_x_preferred":[
        "Changhua"
    ],
    "name:hak_x_preferred":[
        "Ch\u00f4ng-fa-s\u1e73"
    ],
    "name:heb_x_preferred":[
        "\u05e6'\u05d0\u05e0\u05d2'\u05d5\u05d0\u05d4"
    ],
    "name:hin_x_preferred":[
        "\u091a\u093e\u0902\u0917\u0941\u0906"
    ],
    "name:hun_x_preferred":[
        "Changhua"
    ],
    "name:ind_x_preferred":[
        "Changhua"
    ],
    "name:ita_x_preferred":[
        "Changhua"
    ],
    "name:jpn_x_preferred":[
        "\u5f70\u5316\u5e02"
    ],
    "name:kor_x_preferred":[
        "\uc7a5\ud654\uc2dc"
    ],
    "name:lit_x_preferred":[
        "D\u017eanghua"
    ],
    "name:nld_x_preferred":[
        "Changhua"
    ],
    "name:pol_x_preferred":[
        "Zhanghua"
    ],
    "name:por_x_preferred":[
        "Changhua"
    ],
    "name:rus_x_preferred":[
        "\u0427\u0436\u0430\u043d\u0445\u0443\u0430"
    ],
    "name:spa_x_preferred":[
        "Changhua"
    ],
    "name:swe_x_preferred":[
        "Changhua"
    ],
    "name:tha_x_preferred":[
        "\u0e08\u0e31\u0e07\u0e2e\u0e27\u0e48\u0e32"
    ],
    "name:tur_x_preferred":[
        "Changhua"
    ],
    "name:ukr_x_preferred":[
        "\u0427\u0436\u0430\u043d\u0445\u0443\u0430"
    ],
    "name:urd_x_preferred":[
        "\u0686\u0627\u0646\u06af\u06c1\u0648\u0627 \u0634\u06c1\u0631"
    ],
    "name:vie_x_preferred":[
        "Ch\u01b0\u01a1ng H\u00f3a"
    ],
    "name:war_x_preferred":[
        "Changhua"
    ],
    "name:zho_x_preferred":[
        "\u957f\u534e"
    ],
    "name:zho_x_variant":[
        "\u5f70\u5316\u5e02"
    ],
    "wof:name":"Changhua",
    "wof:placetype":"locality"
},
  "geometry": {"coordinates":[110.035,22.8945],"type":"Point"}
}