{
  "type": "Feature",
  "properties": {
    "gn:admin1_code":"18.0",
    "gn:asciiname":"Denggu",
    "gn:country_code":"CN",
    "gn:dem":739,
    "gn:feature_class":"P",
    "gn:feature_code":"PPL",
    "gn:name":"Denggu",
    "gn:population":0,
    "gn:timezone":"Asia/Shanghai",
    "iso:country":"CN",
    "name:zho_x_preferred":[
        "\u767b\u8c37"
    ],
    "wof:name":"Denggu",
    "wof:placetype":"locality"
},
  "geometry": {"coordinates":[109.185,25.9789],"type":"Point"}
}