{
  "type": "Feature",
  "properties": {
    "gn:admin1_code":"7.0",
    "gn:asciiname":"Fengkengli",
    "gn:country_code":"CN",
    "gn:dem":400,
    "gn:feature_class":"P",
    "gn:feature_code":"PPL",
    "gn:name":"Fengkengli",
    "gn:population":0,
    "gn:timezone":"Asia/Shanghai",
    "iso:country":"CN",
    "name:zho_x_preferred":[
        "\u51af\u5751\u91cc"
    ],
    "wof:name":"Fengkengli",
    "wof:placetype":"locality"
},
  "geometry": {"coordinates":[116.64302000000001,24.92894],"type":"Point"}
}