{
  "type": "Feature",
  "properties": {
    "gn:admin1_code":"14.0",
    "gn:asciiname":"Wurongcun",
    "gn:country_code":"CN",
    "gn:dem":4859,
    "gn:feature_class":"P",
    "gn:feature_code":"PPL",
    "gn:name":"Wurongcun",
    "gn:population":0,
    "gn:timezone":"Asia/Urumqi",
    "iso:country":"CN",
    "name:zho_x_preferred":[
        "\u543e\u8363\u6751"
    ],
    "wof:name":"Wurongcun",
    "wof:placetype":"locality"
},
  "geometry": {"coordinates":[90.27955,31.56141],"type":"Point"}
}