{
  "type": "Feature",
  "properties": {
    "gn:admin1_code":"11.0",
    "gn:asciiname":"Zinitang",
    "gn:country_code":"CN",
    "gn:dem":419,
    "gn:feature_class":"P",
    "gn:feature_code":"PPL",
    "gn:name":"Zinitang",
    "gn:population":0,
    "gn:timezone":"Asia/Shanghai",
    "iso:country":"CN",
    "name:zho_x_preferred":[
        "\u5b50\u6ce5\u5858"
    ],
    "wof:name":"Zinitang",
    "wof:placetype":"locality"
},
  "geometry": {"coordinates":[110.82159,26.56651],"type":"Point"}
}