{
  "type": "Feature",
  "properties": {
    "gn:admin1_code":"5.0",
    "gn:asciiname":"Zhangjia Weizicun",
    "gn:country_code":"CN",
    "gn:dem":156,
    "gn:feature_class":"P",
    "gn:feature_code":"PPL",
    "gn:name":"Zhangjia Weizicun",
    "gn:population":0,
    "gn:timezone":"Asia/Shanghai",
    "iso:country":"CN",
    "name:zho_x_preferred":[
        "\u5f20\u5bb6\u56f4\u5b50\u6751"
    ],
    "wof:name":"Zhangjia Weizicun",
    "wof:placetype":"locality"
},
  "geometry": {"coordinates":[123.8892,44.47679],"type":"Point"}
}