{
  "type": "Feature",
  "properties": {
    "gn:admin1_code":"13.0",
    "gn:asciiname":"Kusita Aigezi",
    "gn:country_code":"CN",
    "gn:dem":2158,
    "gn:feature_class":"P",
    "gn:feature_code":"PPL",
    "gn:name":"Kusita Aigezi",
    "gn:population":0,
    "gn:timezone":"Asia/Shanghai",
    "iso:country":"CN",
    "name:zho_x_preferred":[
        "\u5e93\u65af\u5854\u827e\u683c\u5b5c"
    ],
    "wof:name":"Kusita Aigezi",
    "wof:placetype":"locality"
},
  "geometry": {"coordinates":[78.83305,36.94064],"type":"Point"}
}