{
  "type": "Feature",
  "properties": {
    "gn:admin1_code":"32.0",
    "gn:asciiname":"Bubu",
    "gn:country_code":"CN",
    "gn:dem":2343,
    "gn:feature_class":"P",
    "gn:feature_code":"PPL",
    "gn:name":"Bubu",
    "gn:population":0,
    "gn:timezone":"Asia/Shanghai",
    "iso:country":"CN",
    "name:zho_x_preferred":[
        "\u4e0d\u4e0d"
    ],
    "wof:name":"Bubu",
    "wof:placetype":"locality"
},
  "geometry": {"coordinates":[102.28704999999999,28.07359000000001],"type":"Point"}
}