{
  "type": "Feature",
  "properties": {
    "gn:admin1_code":"3",
    "gn:asciiname":"Baiguo Shuxia",
    "gn:country_code":"CN",
    "gn:dem":215,
    "gn:feature_class":"P",
    "gn:feature_code":"PPL",
    "gn:name":"Baiguo Shuxia",
    "gn:population":0,
    "gn:timezone":"Asia/Shanghai",
    "iso:country":"CN",
    "name:zho_x_preferred":[
        "\u767d\u679c\u6811\u4e0b"
    ],
    "wof:name":"Baiguo Shuxia",
    "wof:placetype":"locality"
},
  "geometry": {"coordinates":[114.628,25.6797],"type":"Point"}
}