{
  "type": "Feature",
  "properties": {
    "gn:admin1_code":"4.0",
    "gn:asciiname":"Kongdaicun",
    "gn:country_code":"CN",
    "gn:dem":2,
    "gn:feature_class":"P",
    "gn:feature_code":"PPL",
    "gn:name":"Kongdaicun",
    "gn:population":0,
    "gn:timezone":"Asia/Shanghai",
    "iso:country":"CN",
    "name:und_x_variant":[
        "Wangqi",
        "\u738b\u621a",
        "Kongdaicun"
    ],
    "name:zho_x_preferred":[
        "\u738b\u621a"
    ],
    "name:zho_x_variant":[
        "\u5b54\u6234\u6751"
    ],
    "wof:name":"Kongdaicun",
    "wof:placetype":"locality"
},
  "geometry": {"coordinates":[119.89359,32.88650999999999],"type":"Point"}
}