{
  "type": "Feature",
  "properties": {
    "gn:admin1_code":"16.0",
    "gn:asciiname":"Banding",
    "gn:country_code":"CN",
    "gn:dem":164,
    "gn:feature_class":"P",
    "gn:feature_code":"PPL",
    "gn:name":"Banding",
    "gn:population":0,
    "gn:timezone":"Asia/Shanghai",
    "iso:country":"CN",
    "name:deu_x_preferred":[
        "Banding"
    ],
    "name:jpn_x_preferred":[
        "\u30d0\u30f3\u30c7\u30a3\u30f3\u30b0"
    ],
    "name:nld_x_preferred":[
        "Banding"
    ],
    "name:zho_x_preferred":[
        "\u677f\u5b9a"
    ],
    "wof:name":"Banding",
    "wof:placetype":"locality"
},
  "geometry": {"coordinates":[108.43899999999999,24.1176],"type":"Point"}
}