{
  "type": "Feature",
  "properties": {
    "gn:admin1_code":"9.0",
    "gn:asciiname":"Huaishudian",
    "gn:country_code":"CN",
    "gn:dem":140,
    "gn:feature_class":"P",
    "gn:feature_code":"PPL",
    "gn:name":"Huaishudian",
    "gn:population":0,
    "gn:timezone":"Asia/Shanghai",
    "iso:country":"CN",
    "name:zho_x_preferred":[
        "\u69d0\u6811\u5e97"
    ],
    "wof:name":"Huaishudian",
    "wof:placetype":"locality"
},
  "geometry": {"coordinates":[114.72457,31.63707],"type":"Point"}
}