{
  "type": "Feature",
  "properties": {
    "gn:admin1_code":"18",
    "gn:asciiname":"Majiagou",
    "gn:country_code":"CN",
    "gn:dem":904,
    "gn:feature_class":"P",
    "gn:feature_code":"PPL",
    "gn:name":"Majiagou",
    "gn:population":0,
    "gn:timezone":"Asia/Shanghai",
    "iso:country":"CN",
    "name:zho_x_preferred":[
        "\u9a6c\u5bb6\u6c9f"
    ],
    "wof:name":"Majiagou",
    "wof:placetype":"locality"
},
  "geometry": {"coordinates":[106.76000000000001,27.5558],"type":"Point"}
}