{
  "type": "Feature",
  "properties": {
    "gn:admin1_code":"26.0",
    "gn:asciiname":"He'erzhuang",
    "gn:country_code":"CN",
    "gn:dem":1362,
    "gn:feature_class":"P",
    "gn:feature_code":"PPL",
    "gn:name":"He\u2019erzhuang",
    "gn:population":0,
    "gn:timezone":"Asia/Shanghai",
    "iso:country":"CN",
    "name:und_x_variant":[
        "He\u2019erzhuang"
    ],
    "name:zho_x_preferred":[
        "\u4f55\u513f\u5e84"
    ],
    "wof:name":"He'erzhuang",
    "wof:placetype":"locality"
},
  "geometry": {"coordinates":[107.40798999999998,37.56917],"type":"Point"}
}