{
  "type": "Feature",
  "properties": {
    "gn:admin1_code":"32.0",
    "gn:asciiname":"Tianjia'an",
    "gn:country_code":"CN",
    "gn:dem":602,
    "gn:feature_class":"P",
    "gn:feature_code":"PPL",
    "gn:name":"Tianjia\u2019an",
    "gn:population":0,
    "gn:timezone":"Asia/Shanghai",
    "iso:country":"CN",
    "name:zho_x_preferred":[
        "\u7530\u5bb6\u5eb5"
    ],
    "name:zho_x_variant":[
        "Tianjia\u2019an"
    ],
    "wof:name":"Tianjia'an",
    "wof:placetype":"locality"
},
  "geometry": {"coordinates":[104.28780999999999,31.44047],"type":"Point"}
}