{
  "type": "Feature",
  "properties": {
    "gn:admin1_code":"14.0",
    "gn:asciiname":"Nagqu",
    "gn:country_code":"CN",
    "gn:dem":4536,
    "gn:feature_class":"P",
    "gn:feature_code":"PPLA3",
    "gn:name":"Nagqu",
    "gn:population":0,
    "gn:timezone":"Asia/Urumqi",
    "iso:country":"CN",
    "name:bod_x_preferred":[
        "Nagqu Zhen"
    ],
    "name:und_x_variant":[
        "Naqu Zhen",
        "Nagqu"
    ],
    "name:zho_x_preferred":[
        "\u90a3\u66f2\u9547"
    ],
    "name:zho_x_variant":[
        "\u90a3\u66f2"
    ],
    "wof:name":"Nagqu",
    "wof:placetype":"locality"
},
  "geometry": {"coordinates":[92.003,31.403],"type":"Point"}
}