{
  "type": "Feature",
  "properties": {
    "gn:admin1_code":"14.0",
    "gn:asciiname":"Nagqu",
    "gn:country_code":"CN",
    "gn:dem":4536,
    "gn:feature_class":"P",
    "gn:feature_code":"PPLA3",
    "gn:name":"Nagqu",
    "gn:population":0,
    "gn:timezone":"Asia/Urumqi",
    "iso:country":"CN",
    "name:ben_x_preferred":[
        "\u09a8\u09be\u0997-\u099b\u09c1 \u09ac\u09bf\u09ad\u09be\u0997"
    ],
    "name:bod_x_preferred":[
        "Nagqu Zhen"
    ],
    "name:bod_x_variant":[
        "\u0f53\u0f42\u0f0b\u0f46\u0f74\u0f0b\u0f66\u0f0b\u0f41\u0f74\u0f63\u0f0d"
    ],
    "name:cdo_x_preferred":[
        "Nagqu"
    ],
    "name:ceb_x_preferred":[
        "Nagqu"
    ],
    "name:ces_x_preferred":[
        "Nag\u010dhu"
    ],
    "name:dan_x_preferred":[
        "Nagqu"
    ],
    "name:deu_x_preferred":[
        "Nagqu"
    ],
    "name:eus_x_preferred":[
        "Nagqu Prefektura"
    ],
    "name:fas_x_preferred":[
        "\u0646\u0627\u0686\u0648"
    ],
    "name:fin_x_preferred":[
        "Nagqu"
    ],
    "name:hak_x_preferred":[
        "Nagqu"
    ],
    "name:hin_x_preferred":[
        "\u0928\u0917\u091a\u0941 \u0935\u093f\u092d\u093e\u0917"
    ],
    "name:jpn_x_preferred":[
        "\u30ca\u30af\u30c1\u30e5\u5e02"
    ],
    "name:kor_x_preferred":[
        "\ub098\ucde8\uc2dc"
    ],
    "name:lit_x_preferred":[
        "Nag\u010du prefekt\u016bra"
    ],
    "name:mlg_x_preferred":[
        "Nagqu"
    ],
    "name:nld_x_preferred":[
        "Nagchu"
    ],
    "name:nor_x_preferred":[
        "Nagqu"
    ],
    "name:pol_x_preferred":[
        "Nagqu"
    ],
    "name:rus_x_preferred":[
        "\u041d\u0430\u0433\u0447\u0443"
    ],
    "name:spa_x_preferred":[
        "Nagqu"
    ],
    "name:swe_x_preferred":[
        "Nagchu"
    ],
    "name:tur_x_preferred":[
        "Nagqu"
    ],
    "name:und_x_variant":[
        "Naqu Zhen"
    ],
    "name:urd_x_preferred":[
        "\u0646\u0627\u06af\u0686\u0648"
    ],
    "name:vie_x_preferred":[
        "Nagqu"
    ],
    "name:wuu_x_preferred":[
        "\u90a3\u66f2\u5e02"
    ],
    "name:zho_x_preferred":[
        "\u90a3\u66f2\u9547"
    ],
    "name:zho_x_variant":[
        "\u90a3\u66f2",
        "\u90a3\u66f2\u5e02"
    ],
    "wof:name":"Nagqu",
    "wof:placetype":"locality"
},
  "geometry": {"coordinates":[92.003,31.403],"type":"Point"}
}