{
  "type": "Feature",
  "properties": {
    "gn:admin1_code":"30",
    "gn:asciiname":"Tunbu",
    "gn:country_code":"CN",
    "gn:dem":13,
    "gn:feature_class":"P",
    "gn:feature_code":"PPL",
    "gn:name":"Tunbu",
    "gn:population":0,
    "gn:timezone":"Asia/Shanghai",
    "iso:country":"CN",
    "name:zho_x_preferred":[
        "\u5c6f\u57d4"
    ],
    "wof:name":"Tunbu",
    "wof:placetype":"locality"
},
  "geometry": {"coordinates":[116.29481,23.46886],"type":"Point"}
}