{
  "type": "Feature",
  "properties": {
    "gn:admin1_code":"32.0",
    "gn:asciiname":"Heiziwan",
    "gn:country_code":"CN",
    "gn:dem":413,
    "gn:feature_class":"P",
    "gn:feature_code":"PPL",
    "gn:name":"Heiziwan",
    "gn:population":0,
    "gn:timezone":"Asia/Shanghai",
    "iso:country":"CN",
    "name:zho_x_preferred":[
        "\u9ed1\u5b50\u6e7e"
    ],
    "wof:name":"Heiziwan",
    "wof:placetype":"locality"
},
  "geometry": {"coordinates":[104.34999999999999,30.2402],"type":"Point"}
}