{
  "type": "Feature",
  "properties": {
    "gn:admin1_code":"19.0",
    "gn:asciiname":"Dahuangjia Wobucun",
    "gn:country_code":"CN",
    "gn:dem":87,
    "gn:feature_class":"P",
    "gn:feature_code":"PPL",
    "gn:name":"Dahuangjia Wobucun",
    "gn:population":0,
    "gn:timezone":"Asia/Shanghai",
    "iso:country":"CN",
    "name:und_x_variant":[
        "Dahuangjiawobucun",
        "Huangjiawobao",
        "Huangjia Wobu",
        "Dahuangjia Wobucun"
    ],
    "name:zho_x_preferred":[
        "\u5927\u9ec4\u5bb6\u7a9d\u5821\u6751"
    ],
    "name:zho_x_variant":[
        "\u9ec4\u5bb6\u7a9d\u5821"
    ],
    "wof:name":"Dahuangjia Wobucun",
    "wof:placetype":"locality"
},
  "geometry": {"coordinates":[123.08103,42.66002],"type":"Point"}
}