{
  "type": "Feature",
  "properties": {
    "gn:admin1_code":"15.0",
    "gn:asciiname":"Xiaoliushugou",
    "gn:country_code":"CN",
    "gn:dem":2904,
    "gn:feature_class":"P",
    "gn:feature_code":"PPL",
    "gn:name":"Xiaoliushugou",
    "gn:population":0,
    "gn:timezone":"Asia/Shanghai",
    "iso:country":"CN",
    "name:zho_x_preferred":[
        "\u5c0f\u67f3\u6811\u6c9f"
    ],
    "wof:name":"Xiaoliushugou",
    "wof:placetype":"locality"
},
  "geometry": {"coordinates":[102.873,37.2367],"type":"Point"}
}