{
  "type": "Feature",
  "properties": {
    "gn:admin1_code":"05",
    "gn:asciiname":"Jiangmifeng",
    "gn:cc2":"CN",
    "gn:country_code":"CN",
    "gn:dem":224,
    "gn:feature_class":"P",
    "gn:feature_code":"PPL",
    "gn:name":"Jiangmifeng",
    "gn:population":0,
    "gn:timezone":"Asia/Shanghai",
    "iso:country":"CN",
    "name:und_x_variant":[
        "Chiang-mi-feng",
        "Jiangmifeng"
    ],
    "wof:name":"Jiangmifeng",
    "wof:placetype":"locality"
},
  "geometry": {"coordinates":[126.74722,43.95139],"type":"Point"}
}