{
  "type": "Feature",
  "properties": {
    "gn:admin1_code":"15.0",
    "gn:asciiname":"Baijiashan",
    "gn:country_code":"CN",
    "gn:dem":1410,
    "gn:feature_class":"P",
    "gn:feature_code":"PPL",
    "gn:name":"Baijiashan",
    "gn:population":0,
    "gn:timezone":"Asia/Shanghai",
    "iso:country":"CN",
    "name:und_x_variant":[
        "\u767d\u5bb6\u5c71"
    ],
    "wof:name":"Baijiashan",
    "wof:placetype":"locality"
},
  "geometry": {"coordinates":[107.066,36.0275],"type":"Point"}
}