{
  "type": "Feature",
  "properties": {
    "gn:admin1_code":"10.0",
    "gn:asciiname":"Nanshengban",
    "gn:country_code":"CN",
    "gn:dem":70,
    "gn:feature_class":"P",
    "gn:feature_code":"PPL",
    "gn:name":"Nanshengban",
    "gn:population":0,
    "gn:timezone":"Asia/Shanghai",
    "iso:country":"CN",
    "name:und_x_variant":[
        "\u5357\u5723\u677f"
    ],
    "wof:name":"Nanshengban",
    "wof:placetype":"locality"
},
  "geometry": {"coordinates":[114.66021000000001,38.17134],"type":"Point"}
}