{
  "type": "Feature",
  "properties": {
    "gn:admin1_code":"7.0",
    "gn:asciiname":"Guishan",
    "gn:country_code":"CN",
    "gn:dem":89,
    "gn:feature_class":"P",
    "gn:feature_code":"PPL",
    "gn:name":"Guishan",
    "gn:population":0,
    "gn:timezone":"Asia/Shanghai",
    "iso:country":"CN",
    "name:deu_x_preferred":[
        "Guishan"
    ],
    "name:kor_x_preferred":[
        "\uad6c\uc774\uc0b0"
    ],
    "name:zho_x_preferred":[
        "\u9f9f\u5c71"
    ],
    "wof:name":"Guishan",
    "wof:placetype":"locality"
},
  "geometry": {"coordinates":[119.54644,25.80799],"type":"Point"}
}