{
  "type": "Feature",
  "properties": {
    "gn:admin1_code":"14.0",
    "gn:asciiname":"Zilung",
    "gn:country_code":"CN",
    "gn:dem":5024,
    "gn:feature_class":"P",
    "gn:feature_code":"PPLF",
    "gn:name":"Zilung",
    "gn:population":0,
    "gn:timezone":"Asia/Urumqi",
    "iso:country":"CN",
    "name:bod_x_preferred":[
        "Zilung"
    ],
    "name:zho_x_preferred":[
        "Zilong"
    ],
    "name:zho_x_variant":[
        "\u5b50\u9f99",
        "Bare",
        "\u5df4\u60f9"
    ],
    "wof:name":"Zilung",
    "wof:placetype":"locality"
},
  "geometry": {"coordinates":[93.001,29.101],"type":"Point"}
}