{
  "type": "Feature",
  "properties": {
    "gn:admin1_code":"33.0",
    "gn:asciiname":"Dajing",
    "gn:country_code":"CN",
    "gn:dem":303,
    "gn:feature_class":"P",
    "gn:feature_code":"PPL",
    "gn:name":"Dajing",
    "gn:population":0,
    "gn:timezone":"Asia/Shanghai",
    "iso:country":"CN",
    "name:ceb_x_preferred":[
        "Dajing"
    ],
    "name:swe_x_preferred":[
        "Dajing"
    ],
    "name:zho_x_preferred":[
        "\u5927\u4e95"
    ],
    "wof:name":"Dajing",
    "wof:placetype":"locality"
},
  "geometry": {"coordinates":[105.90161999999999,29.81151],"type":"Point"}
}