{
  "type": "Feature",
  "properties": {
    "gn:admin1_code":"32.0",
    "gn:asciiname":"Xingguang",
    "gn:country_code":"CN",
    "gn:dem":331,
    "gn:feature_class":"P",
    "gn:feature_code":"PPL",
    "gn:name":"Xingguang",
    "gn:population":0,
    "gn:timezone":"Asia/Shanghai",
    "iso:country":"CN",
    "name:zho_x_preferred":[
        "\u661f\u5149"
    ],
    "wof:name":"Xingguang",
    "wof:placetype":"locality"
},
  "geometry": {"coordinates":[105.396,30.8587],"type":"Point"}
}