{
  "type": "Feature",
  "properties": {
    "gn:admin1_code":"16",
    "gn:asciiname":"Daning",
    "gn:cc2":"CN",
    "gn:country_code":"CN",
    "gn:dem":210,
    "gn:feature_class":"P",
    "gn:feature_code":"PPL",
    "gn:name":"Daning",
    "gn:population":0,
    "gn:timezone":"Asia/Shanghai",
    "iso:country":"CN",
    "name:ceb_x_preferred":[
        "Daning"
    ],
    "name:und_x_variant":[
        "Ta-ning",
        "Daning"
    ],
    "wof:name":"Daning",
    "wof:placetype":"locality"
},
  "geometry": {"coordinates":[111.90000000000001,24.51667],"type":"Point"}
}