{
  "type": "Feature",
  "properties": {
    "gn:admin1_code":"3",
    "gn:asciiname":"Pengjiacun",
    "gn:country_code":"CN",
    "gn:dem":85,
    "gn:feature_class":"P",
    "gn:feature_code":"PPL",
    "gn:name":"Pengjiacun",
    "gn:population":0,
    "gn:timezone":"Asia/Shanghai",
    "iso:country":"CN",
    "wof:name":"Pengjiacun",
    "wof:placetype":"locality"
},
  "geometry": {"coordinates":[115.02634,26.65189],"type":"Point"}
}