{
  "type": "Feature",
  "properties": {
    "gn:admin1_code":"29.0",
    "gn:asciiname":"Xiaoguangzha",
    "gn:country_code":"CN",
    "gn:dem":1731,
    "gn:feature_class":"P",
    "gn:feature_code":"PPL",
    "gn:name":"Xiaoguangzha",
    "gn:population":0,
    "gn:timezone":"Asia/Shanghai",
    "iso:country":"CN",
    "name:zho_x_preferred":[
        "\u5c0f\u5e7f\u624e"
    ],
    "wof:name":"Xiaoguangzha",
    "wof:placetype":"locality"
},
  "geometry": {"coordinates":[100.33799999999999,23.9127],"type":"Point"}
}