{
  "type": "Feature",
  "properties": {
    "gn:admin1_code":"4.0",
    "gn:asciiname":"Xingdong",
    "gn:country_code":"CN",
    "gn:dem":3,
    "gn:feature_class":"P",
    "gn:feature_code":"PPL",
    "gn:name":"Xingdong",
    "gn:population":0,
    "gn:timezone":"Asia/Shanghai",
    "iso:country":"CN",
    "name:und_x_variant":[
        "\u5174\u4e1c"
    ],
    "wof:name":"Xingdong",
    "wof:placetype":"locality"
},
  "geometry": {"coordinates":[121.21966,32.00347],"type":"Point"}
}