{
  "type": "Feature",
  "properties": {
    "gn:admin1_code":"16.0",
    "gn:asciiname":"Xiajiawan",
    "gn:country_code":"CN",
    "gn:dem":1426,
    "gn:feature_class":"P",
    "gn:feature_code":"PPL",
    "gn:name":"Xiajiawan",
    "gn:population":0,
    "gn:timezone":"Asia/Shanghai",
    "iso:country":"CN",
    "name:zho_x_preferred":[
        "\u590f\u5bb6\u6e7e"
    ],
    "wof:name":"Xiajiawan",
    "wof:placetype":"locality"
},
  "geometry": {"coordinates":[105.134,24.5954],"type":"Point"}
}