{
  "type": "Feature",
  "properties": {
    "gn:admin1_code":"14",
    "gn:asciiname":"Qamda",
    "gn:country_code":"CN",
    "gn:dem":4322,
    "gn:feature_class":"P",
    "gn:feature_code":"PPL",
    "gn:name":"Qamda",
    "gn:population":0,
    "gn:timezone":"Asia/Urumqi",
    "iso:country":"CN",
    "name:bod_x_preferred":[
        "\u0f47\u0f0b\u0f58\u0f51\u0f60"
    ],
    "wof:name":"Qamda",
    "wof:placetype":"locality"
},
  "geometry": {"coordinates":[91.23725,28.35356],"type":"Point"}
}