{
  "type": "Feature",
  "properties": {
    "gn:admin1_code":"30.0",
    "gn:asciiname":"Fuzai",
    "gn:country_code":"CN",
    "gn:dem":12,
    "gn:feature_class":"P",
    "gn:feature_code":"PPL",
    "gn:name":"Fuzai",
    "gn:population":0,
    "gn:timezone":"Asia/Shanghai",
    "iso:country":"CN",
    "name:zho_x_preferred":[
        "\u752b\u4ed4"
    ],
    "wof:name":"Fuzai",
    "wof:placetype":"locality"
},
  "geometry": {"coordinates":[112.36631,21.78524],"type":"Point"}
}