{
  "type": "Feature",
  "properties": {
    "gn:admin1_code":"19.0",
    "gn:asciiname":"Disuotuncun",
    "gn:country_code":"CN",
    "gn:dem":43,
    "gn:feature_class":"P",
    "gn:feature_code":"PPL",
    "gn:name":"Disuotuncun",
    "gn:population":0,
    "gn:timezone":"Asia/Shanghai",
    "iso:country":"CN",
    "name:zho_x_preferred":[
        "\u5730\u6240\u5c6f\u6751"
    ],
    "wof:name":"Disuotuncun",
    "wof:placetype":"locality"
},
  "geometry": {"coordinates":[122.943,41.0265],"type":"Point"}
}