{
  "type": "Feature",
  "properties": {
    "gn:admin1_code":"9.0",
    "gn:asciiname":"Wanghuzhai",
    "gn:country_code":"CN",
    "gn:dem":118,
    "gn:feature_class":"P",
    "gn:feature_code":"PPL",
    "gn:name":"Wanghuzhai",
    "gn:population":0,
    "gn:timezone":"Asia/Shanghai",
    "iso:country":"CN",
    "name:zho_x_preferred":[
        "\u738b\u80e1\u5be8"
    ],
    "wof:name":"Wanghuzhai",
    "wof:placetype":"locality"
},
  "geometry": {"coordinates":[113.64225999999999,34.70222],"type":"Point"}
}