{
  "type": "Feature",
  "properties": {
    "gn:admin1_code":"1.0",
    "gn:asciiname":"Yuandian",
    "gn:cc2":"CN",
    "gn:country_code":"CN",
    "gn:dem":17,
    "gn:feature_class":"P",
    "gn:feature_code":"PPL",
    "gn:name":"Yuandian",
    "gn:population":0,
    "gn:timezone":"Asia/Shanghai",
    "iso:country":"CN",
    "name:und_x_variant":[
        "T\u2019ang-shih-tz\u2019u",
        "Y\u00fcan-tien",
        "Yuandian"
    ],
    "wof:name":"Yuandian",
    "wof:placetype":"locality"
},
  "geometry": {"coordinates":[116.90000000000001,31.55],"type":"Point"}
}