{
  "type": "Feature",
  "properties": {
    "gn:admin1_code":"8.0",
    "gn:asciiname":"Fengmancun",
    "gn:country_code":"CN",
    "gn:dem":220,
    "gn:feature_class":"P",
    "gn:feature_code":"PPL",
    "gn:name":"Fengmancun",
    "gn:population":0,
    "gn:timezone":"Asia/Shanghai",
    "iso:country":"CN",
    "name:zho_x_preferred":[
        "\u4e30\u6ee1\u6751"
    ],
    "wof:name":"Fengmancun",
    "wof:placetype":"locality"
},
  "geometry": {"coordinates":[125.71929,47.19668],"type":"Point"}
}