{
  "type": "Feature",
  "properties": {
    "gn:admin1_code":"2.0",
    "gn:asciiname":"Suomen",
    "gn:country_code":"CN",
    "gn:dem":12,
    "gn:feature_class":"P",
    "gn:feature_code":"PPL",
    "gn:name":"Suomen",
    "gn:population":0,
    "gn:timezone":"Asia/Shanghai",
    "iso:country":"CN",
    "name:zho_x_preferred":[
        "\u6240\u95e8"
    ],
    "wof:name":"Suomen",
    "wof:placetype":"locality"
},
  "geometry": {"coordinates":[121.60656000000002,29.02028],"type":"Point"}
}