{
  "type": "Feature",
  "properties": {
    "gn:admin1_code":"29.0",
    "gn:asciiname":"Yisi",
    "gn:country_code":"CN",
    "gn:dem":3409,
    "gn:feature_class":"P",
    "gn:feature_code":"PPL",
    "gn:name":"Yisi",
    "gn:population":0,
    "gn:timezone":"Asia/Shanghai",
    "iso:country":"CN",
    "name:zho_x_preferred":[
        "\u76ca\u53f8"
    ],
    "wof:name":"Yisi",
    "wof:placetype":"locality"
},
  "geometry": {"coordinates":[99.64448,27.91108],"type":"Point"}
}