{
  "type": "Feature",
  "properties": {
    "gn:admin1_code":"19.0",
    "gn:asciiname":"Wufengsicun",
    "gn:country_code":"CN",
    "gn:dem":261,
    "gn:feature_class":"P",
    "gn:feature_code":"PPL",
    "gn:name":"Wufengsicun",
    "gn:population":0,
    "gn:timezone":"Asia/Shanghai",
    "iso:country":"CN",
    "name:zho_x_preferred":[
        "\u4e94\u5cf0\u5bfa\u6751"
    ],
    "wof:name":"Wufengsicun",
    "wof:placetype":"locality"
},
  "geometry": {"coordinates":[121.607,41.5285],"type":"Point"}
}