{
  "type": "Feature",
  "properties": {
    "gn:admin1_code":"1.0",
    "gn:asciiname":"Xieshancun",
    "gn:country_code":"CN",
    "gn:dem":27,
    "gn:feature_class":"P",
    "gn:feature_code":"PPL",
    "gn:name":"Xieshancun",
    "gn:population":0,
    "gn:timezone":"Asia/Shanghai",
    "iso:country":"CN",
    "name:zho_x_preferred":[
        "\u8c22\u5c71\u6751"
    ],
    "wof:name":"Xieshancun",
    "wof:placetype":"locality"
},
  "geometry": {"coordinates":[116.82708999999998,30.7005],"type":"Point"}
}