{
  "type": "Feature",
  "properties": {
    "gn:admin1_code":"19.0",
    "gn:asciiname":"Xihuahonggou",
    "gn:country_code":"CN",
    "gn:dem":193,
    "gn:feature_class":"P",
    "gn:feature_code":"PPL",
    "gn:name":"Xihuahonggou",
    "gn:population":0,
    "gn:timezone":"Asia/Shanghai",
    "iso:country":"CN",
    "name:und_x_variant":[
        "\u897f\u82b1\u7ea2\u6c9f"
    ],
    "wof:name":"Xihuahonggou",
    "wof:placetype":"locality"
},
  "geometry": {"coordinates":[123.26300000000001,40.9263],"type":"Point"}
}