{
  "type": "Feature",
  "properties": {
    "gn:admin1_code":"4.0",
    "gn:asciiname":"Tengmacun",
    "gn:country_code":"CN",
    "gn:dem":5,
    "gn:feature_class":"P",
    "gn:feature_code":"PPL",
    "gn:name":"Tengmacun",
    "gn:population":0,
    "gn:timezone":"Asia/Shanghai",
    "iso:country":"CN",
    "name:zho_x_preferred":[
        "\u6ed5\u9a6c\u6751"
    ],
    "wof:name":"Tengmacun",
    "wof:placetype":"locality"
},
  "geometry": {"coordinates":[119.12433,33.40112],"type":"Point"}
}