{
  "type": "Feature",
  "properties": {
    "gn:admin1_code":"18",
    "gn:asciiname":"Qianhaizi",
    "gn:country_code":"CN",
    "gn:dem":1427,
    "gn:feature_class":"P",
    "gn:feature_code":"PPL",
    "gn:name":"Qianhaizi",
    "gn:population":0,
    "gn:timezone":"Asia/Shanghai",
    "iso:country":"CN",
    "name:zho_x_preferred":[
        "\u4e7e\u6d77\u5b50"
    ],
    "wof:name":"Qianhaizi",
    "wof:placetype":"locality"
},
  "geometry": {"coordinates":[105.06100000000001,25.2836],"type":"Point"}
}