{
  "type": "Feature",
  "properties": {
    "gn:admin1_code":"8.0",
    "gn:asciiname":"Laohei Gangzi",
    "gn:country_code":"CN",
    "gn:dem":182,
    "gn:feature_class":"P",
    "gn:feature_code":"PPL",
    "gn:name":"Laohei Gangzi",
    "gn:population":0,
    "gn:timezone":"Asia/Shanghai",
    "iso:country":"CN",
    "name:zho_x_preferred":[
        "\u8001\u9ed1\u5c97\u5b50"
    ],
    "wof:name":"Laohei Gangzi",
    "wof:placetype":"locality"
},
  "geometry": {"coordinates":[124.61991999999999,48.36924000000001],"type":"Point"}
}