{
  "type": "Feature",
  "properties": {
    "gn:admin1_code":"30",
    "gn:asciiname":"Pingshitou",
    "gn:country_code":"CN",
    "gn:dem":66,
    "gn:feature_class":"P",
    "gn:feature_code":"PPL",
    "gn:name":"Pingshitou",
    "gn:population":0,
    "gn:timezone":"Asia/Shanghai",
    "iso:country":"CN",
    "name:zho_x_preferred":[
        "\u576a\u77f3\u5934"
    ],
    "wof:name":"Pingshitou",
    "wof:placetype":"locality"
},
  "geometry": {"coordinates":[116.59617,24.531],"type":"Point"}
}