{
  "type": "Feature",
  "properties": {
    "gn:admin1_code":"13",
    "gn:asciiname":"Gulewen Tulega Muchang",
    "gn:country_code":"CN",
    "gn:dem":3255,
    "gn:feature_class":"P",
    "gn:feature_code":"PPLF",
    "gn:name":"Gulewen Tulega Muchang",
    "gn:population":0,
    "gn:timezone":"Asia/Urumqi",
    "iso:country":"CN",
    "name:und_x_variant":[
        "\u53e4\u52d2\u6e29\u56fe\u52d2\u5c15\u7267\u573a"
    ],
    "wof:name":"Gulewen Tulega Muchang",
    "wof:placetype":"locality"
},
  "geometry": {"coordinates":[84.57930999999998,42.97767],"type":"Point"}
}