{
  "type": "Feature",
  "properties": {
    "gn:admin1_code":"19.0",
    "gn:asciiname":"Yahua",
    "gn:country_code":"CN",
    "gn:dem":9,
    "gn:feature_class":"P",
    "gn:feature_code":"PPL",
    "gn:name":"Yahua",
    "gn:population":0,
    "gn:timezone":"Asia/Shanghai",
    "iso:country":"CN",
    "name:und_x_variant":[
        "\u96c5\u5316"
    ],
    "name:zho_x_preferred":[
        "\u96c5\u5316"
    ],
    "wof:name":"Yahua",
    "wof:placetype":"locality"
},
  "geometry": {"coordinates":[122.47311000000001,41.42516],"type":"Point"}
}