{
  "type": "Feature",
  "properties": {
    "gn:admin1_code":"32.0",
    "gn:asciiname":"Tangfang",
    "gn:country_code":"CN",
    "gn:dem":1716,
    "gn:feature_class":"P",
    "gn:feature_code":"PPL",
    "gn:name":"Tangfang",
    "gn:population":0,
    "gn:timezone":"Asia/Shanghai",
    "iso:country":"CN",
    "name:zho_x_preferred":[
        "\u5858\u623f"
    ],
    "wof:name":"Tangfang",
    "wof:placetype":"locality"
},
  "geometry": {"coordinates":[102.86199999999999,26.6504],"type":"Point"}
}