{
  "type": "Feature",
  "properties": {
    "gn:admin1_code":"29.0",
    "gn:asciiname":"Yingpan",
    "gn:country_code":"CN",
    "gn:dem":1951,
    "gn:feature_class":"P",
    "gn:feature_code":"PPL",
    "gn:name":"Yingpan",
    "gn:population":0,
    "gn:timezone":"Asia/Shanghai",
    "iso:country":"CN",
    "name:zho_x_preferred":[
        "\u8425\u76d8"
    ],
    "wof:name":"Yingpan",
    "wof:placetype":"locality"
},
  "geometry": {"coordinates":[103.764,27.2617],"type":"Point"}
}