{
  "type": "Feature",
  "properties": {
    "gn:country":"CN",
    "gn:fcode":"PPL",
    "gn:pop":0,
    "iso:country":"CN",
    "name:unk_x_variant":[
        "Meng-hua"
    ],
    "qs:name":"\u9b4f\u5c71",
    "qs:name_adm0":"\u4e2d\u570b",
    "qs:name_adm1":"\u4e91\u5357\u7701",
    "qs:photos":133,
    "qs:photos_1k":27,
    "qs:photos_9k":1,
    "qs:photos_9r":3,
    "qs:photos_all":133,
    "qs:photos_sr":3,
    "qs:placetype":"Town",
    "qs:pop_sr":"5",
    "wof:name":"\u9b4f\u5c71",
    "wof:placetype":"locality",
    "wof:population":0
},
  "geometry": {"coordinates":[100.34999999999999,25.26667],"type":"Point"}
}