{
  "type": "Feature",
  "properties": {
    "gn:admin1_code":"08",
    "gn:asciiname":"Chelu",
    "gn:country_code":"CN",
    "gn:dem":188,
    "gn:feature_class":"P",
    "gn:feature_code":"PPLA4",
    "gn:name":"Chelu",
    "gn:population":0,
    "gn:timezone":"Asia/Shanghai",
    "iso:country":"CN",
    "name:eng_x_preferred":[
        "Chelu"
    ],
    "name:rus_x_preferred":[
        "\u0427\u044d\u043b\u0443"
    ],
    "name:und_x_variant":[
        "Chelu Xiang"
    ],
    "name:zho_x_preferred":[
        "\u8f66\u9646"
    ],
    "name:zho_x_variant":[
        "\u8f66\u9646\u4e61"
    ],
    "wof:name":"Chelu",
    "wof:placetype":"locality"
},
  "geometry": {"coordinates":[128.78609,49.44242],"type":"Point"}
}