{
  "type": "Feature",
  "properties": {
    "gn:admin1_code":"32.0",
    "gn:asciiname":"Huilonggou",
    "gn:country_code":"CN",
    "gn:dem":461,
    "gn:feature_class":"P",
    "gn:feature_code":"PPL",
    "gn:name":"Huilonggou",
    "gn:population":0,
    "gn:timezone":"Asia/Shanghai",
    "iso:country":"CN",
    "name:zho_x_preferred":[
        "\u56de\u9f99\u6c9f"
    ],
    "wof:name":"Huilonggou",
    "wof:placetype":"locality"
},
  "geometry": {"coordinates":[104.76300000000001,31.37],"type":"Point"}
}