{
  "type": "Feature",
  "properties": {
    "gn:admin1_code":"11.0",
    "gn:asciiname":"Damenxi",
    "gn:country_code":"CN",
    "gn:dem":303,
    "gn:feature_class":"P",
    "gn:feature_code":"PPL",
    "gn:name":"Damenxi",
    "gn:population":0,
    "gn:timezone":"Asia/Shanghai",
    "iso:country":"CN",
    "name:zho_x_preferred":[
        "\u5927\u95e8\u6eaa"
    ],
    "wof:name":"Damenxi",
    "wof:placetype":"locality"
},
  "geometry": {"coordinates":[110.04113,27.73148],"type":"Point"}
}