{
  "type": "Feature",
  "properties": {
    "gn:admin1_code":"15.0",
    "gn:asciiname":"Xiangjiayao",
    "gn:country_code":"CN",
    "gn:dem":1934,
    "gn:feature_class":"P",
    "gn:feature_code":"PPL",
    "gn:name":"Xiangjiayao",
    "gn:population":0,
    "gn:timezone":"Asia/Shanghai",
    "iso:country":"CN",
    "name:zho_x_preferred":[
        "\u9879\u5bb6\u7a91"
    ],
    "wof:name":"Xiangjiayao",
    "wof:placetype":"locality"
},
  "geometry": {"coordinates":[104.336,36.7113],"type":"Point"}
}