{
  "type": "Feature",
  "properties": {
    "gn:admin1_code":"8.0",
    "gn:asciiname":"Xixing",
    "gn:country_code":"CN",
    "gn:dem":243,
    "gn:feature_class":"P",
    "gn:feature_code":"PPLA4",
    "gn:name":"Xixing",
    "gn:population":0,
    "gn:timezone":"Asia/Shanghai",
    "iso:country":"CN",
    "name:und_x_variant":[
        "Xixing Xiang"
    ],
    "name:zho_x_preferred":[
        "\u897f\u5174"
    ],
    "name:zho_x_variant":[
        "\u897f\u5174\u4e61"
    ],
    "wof:name":"Xixing",
    "wof:placetype":"locality"
},
  "geometry": {"coordinates":[127.27088999999999,49.41044],"type":"Point"}
}