{
  "type": "Feature",
  "properties": {
    "gn:admin1_code":"4.0",
    "gn:asciiname":"Dongchengcun",
    "gn:country_code":"CN",
    "gn:dem":33,
    "gn:feature_class":"P",
    "gn:feature_code":"PPL",
    "gn:name":"Dongchengcun",
    "gn:population":0,
    "gn:timezone":"Asia/Shanghai",
    "iso:country":"CN",
    "name:zho_x_preferred":[
        "\u4e1c\u57ce\u6751"
    ],
    "wof:name":"Dongchengcun",
    "wof:placetype":"locality"
},
  "geometry": {"coordinates":[117.11951000000001,34.35608],"type":"Point"}
}