{
  "type": "Feature",
  "properties": {
    "gn:admin1_code":"8.0",
    "gn:asciiname":"Housanmajia",
    "gn:country_code":"CN",
    "gn:dem":152,
    "gn:feature_class":"P",
    "gn:feature_code":"PPL",
    "gn:name":"Housanmajia",
    "gn:population":0,
    "gn:timezone":"Asia/Shanghai",
    "iso:country":"CN",
    "name:zho_x_preferred":[
        "\u540e\u4e09\u9a6c\u67b6"
    ],
    "wof:name":"Housanmajia",
    "wof:placetype":"locality"
},
  "geometry": {"coordinates":[125.91802,45.79014],"type":"Point"}
}