{
  "type": "Feature",
  "properties": {
    "gn:admin1_code":"25.0",
    "gn:asciiname":"Liushunzhuangcun",
    "gn:country_code":"CN",
    "gn:dem":72,
    "gn:feature_class":"P",
    "gn:feature_code":"PPL",
    "gn:name":"Liushunzhuangcun",
    "gn:population":0,
    "gn:timezone":"Asia/Shanghai",
    "iso:country":"CN",
    "name:zho_x_preferred":[
        "\u5218\u987a\u5e84\u6751"
    ],
    "wof:name":"Liushunzhuangcun",
    "wof:placetype":"locality"
},
  "geometry": {"coordinates":[119.50595,36.19624],"type":"Point"}
}