{
  "type": "Feature",
  "properties": {
    "gn:admin1_code":"16.0",
    "gn:asciiname":"Xiao'anchong",
    "gn:country_code":"CN",
    "gn:dem":209,
    "gn:feature_class":"P",
    "gn:feature_code":"PPL",
    "gn:name":"Xiao\u2019anchong",
    "gn:population":0,
    "gn:timezone":"Asia/Shanghai",
    "iso:country":"CN",
    "name:und_x_variant":[
        "Xiao\u2019anchong"
    ],
    "name:zho_x_preferred":[
        "\u5c0f\u6697\u51b2"
    ],
    "wof:name":"Xiao'anchong",
    "wof:placetype":"locality"
},
  "geometry": {"coordinates":[110.023,23.7203],"type":"Point"}
}