{
  "type": "Feature",
  "properties": {
    "gn:admin1_code":"10.0",
    "gn:asciiname":"Dakuishitang",
    "gn:country_code":"CN",
    "gn:dem":1055,
    "gn:feature_class":"P",
    "gn:feature_code":"PPL",
    "gn:name":"Dakuishitang",
    "gn:population":0,
    "gn:timezone":"Asia/Shanghai",
    "iso:country":"CN",
    "name:zho_x_preferred":[
        "\u5927\u9b41\u77f3\u5802"
    ],
    "wof:name":"Dakuishitang",
    "wof:placetype":"locality"
},
  "geometry": {"coordinates":[113.87623000000001,38.85415],"type":"Point"}
}