{
  "type": "Feature",
  "properties": {
    "gn:admin1_code":"18",
    "gn:asciiname":"Datiangang",
    "gn:country_code":"CN",
    "gn:dem":785,
    "gn:feature_class":"P",
    "gn:feature_code":"PPL",
    "gn:name":"Datiangang",
    "gn:population":0,
    "gn:timezone":"Asia/Shanghai",
    "iso:country":"CN",
    "name:zho_x_preferred":[
        "\u5927\u7530\u5c97"
    ],
    "wof:name":"Datiangang",
    "wof:placetype":"locality"
},
  "geometry": {"coordinates":[106.783,28.5988],"type":"Point"}
}