{
  "type": "Feature",
  "properties": {
    "gn:admin1_code":"15.0",
    "gn:asciiname":"Houjiagoumenxia",
    "gn:country_code":"CN",
    "gn:dem":1275,
    "gn:feature_class":"P",
    "gn:feature_code":"PPL",
    "gn:name":"Houjiagoumenxia",
    "gn:population":0,
    "gn:timezone":"Asia/Shanghai",
    "iso:country":"CN",
    "name:und_x_variant":[
        "\u4faf\u5bb6\u6c9f\u95e8\u4e0b"
    ],
    "wof:name":"Houjiagoumenxia",
    "wof:placetype":"locality"
},
  "geometry": {"coordinates":[105.86815,33.95091],"type":"Point"}
}