{
  "type": "Feature",
  "properties": {
    "gn:admin1_code":"32.0",
    "gn:asciiname":"Shageditang",
    "gn:country_code":"CN",
    "gn:dem":3866,
    "gn:feature_class":"P",
    "gn:feature_code":"PPL",
    "gn:name":"Shageditang",
    "gn:population":0,
    "gn:timezone":"Asia/Shanghai",
    "iso:country":"CN",
    "name:zho_x_preferred":[
        "\u6c99\u6208\u72c4\u5858"
    ],
    "wof:name":"Shageditang",
    "wof:placetype":"locality"
},
  "geometry": {"coordinates":[99.0063,32.7984],"type":"Point"}
}