{
  "type": "Feature",
  "properties": {
    "gn:admin1_code":"29.0",
    "gn:asciiname":"Yitouwan",
    "gn:country_code":"CN",
    "gn:dem":2450,
    "gn:feature_class":"P",
    "gn:feature_code":"PPL",
    "gn:name":"Yitouwan",
    "gn:population":0,
    "gn:timezone":"Asia/Shanghai",
    "iso:country":"CN",
    "name:zho_x_preferred":[
        "\u4ee5\u5934\u5f2f"
    ],
    "wof:name":"Yitouwan",
    "wof:placetype":"locality"
},
  "geometry": {"coordinates":[102.021,25.9091],"type":"Point"}
}