{
  "type": "Feature",
  "properties": {
    "gn:admin1_code":"10",
    "gn:asciiname":"Huapi",
    "gn:country_code":"CN",
    "gn:dem":95,
    "gn:feature_class":"P",
    "gn:feature_code":"PPLA4",
    "gn:name":"Huapi",
    "gn:population":0,
    "gn:timezone":"Asia/Shanghai",
    "iso:country":"CN",
    "name:und_x_variant":[
        "\u5316\u76ae",
        "Huapi Zhen"
    ],
    "name:zho_x_preferred":[
        "\u5316\u76ae\u9547"
    ],
    "wof:name":"Huapi",
    "wof:placetype":"locality"
},
  "geometry": {"coordinates":[114.55638999999999,38.31156],"type":"Point"}
}