{
  "type": "Feature",
  "properties": {
    "gn:admin1_code":"10",
    "gn:asciiname":"Douying",
    "gn:cc2":"CN",
    "gn:country_code":"CN",
    "gn:dem":687,
    "gn:feature_class":"P",
    "gn:feature_code":"PPL",
    "gn:name":"Douying",
    "gn:population":0,
    "gn:timezone":"Asia/Shanghai",
    "iso:country":"CN",
    "name:und_x_variant":[
        "Tou-ying",
        "Douying"
    ],
    "wof:name":"Douying",
    "wof:placetype":"locality"
},
  "geometry": {"coordinates":[115.59999999999999,40.21667],"type":"Point"}
}