{
  "type": "Feature",
  "properties": {
    "gn:admin1_code":"5.0",
    "gn:asciiname":"Fuyutun",
    "gn:country_code":"CN",
    "gn:dem":219,
    "gn:feature_class":"P",
    "gn:feature_code":"PPL",
    "gn:name":"Fuyutun",
    "gn:population":0,
    "gn:timezone":"Asia/Shanghai",
    "iso:country":"CN",
    "name:und_x_variant":[
        "\u5bcc\u88d5\u5c6f"
    ],
    "wof:name":"Fuyutun",
    "wof:placetype":"locality"
},
  "geometry": {"coordinates":[129.33937,42.9274],"type":"Point"}
}