{
  "type": "Feature",
  "properties": {
    "gn:admin1_code":"19.0",
    "gn:asciiname":"Hongyan",
    "gn:country_code":"CN",
    "gn:dem":530,
    "gn:feature_class":"P",
    "gn:feature_code":"PPL",
    "gn:name":"Hongyan",
    "gn:population":0,
    "gn:timezone":"Asia/Shanghai",
    "iso:country":"CN",
    "name:ceb_x_preferred":[
        "Hongyan"
    ],
    "name:deu_x_preferred":[
        "Hongyan"
    ],
    "name:ita_x_preferred":[
        "Hongyan"
    ],
    "name:swe_x_preferred":[
        "Hongyan"
    ],
    "name:zho_x_preferred":[
        "\u9e3f\u96c1"
    ],
    "wof:name":"Hongyan",
    "wof:placetype":"locality"
},
  "geometry": {"coordinates":[124.81404999999999,41.3185],"type":"Point"}
}