{
  "type": "Feature",
  "properties": {
    "gn:admin1_code":"18",
    "gn:asciiname":"Zhichang",
    "gn:country_code":"CN",
    "gn:dem":1451,
    "gn:feature_class":"P",
    "gn:feature_code":"PPL",
    "gn:name":"Zhichang",
    "gn:population":0,
    "gn:timezone":"Asia/Shanghai",
    "iso:country":"CN",
    "name:zho_x_preferred":[
        "\u7eb8\u5382"
    ],
    "wof:name":"Zhichang",
    "wof:placetype":"locality"
},
  "geometry": {"coordinates":[107.078,28.4703],"type":"Point"}
}