{
  "type": "Feature",
  "properties": {
    "gn:admin1_code":"32.0",
    "gn:asciiname":"Ji'eryide",
    "gn:country_code":"CN",
    "gn:dem":2110,
    "gn:feature_class":"P",
    "gn:feature_code":"PPL",
    "gn:name":"Ji\u2019eryide",
    "gn:population":0,
    "gn:timezone":"Asia/Shanghai",
    "iso:country":"CN",
    "name:zho_x_preferred":[
        "\u5409\u5c14\u4f9d\u5f97"
    ],
    "name:zho_x_variant":[
        "Ji\u2019eryide"
    ],
    "wof:name":"Ji'eryide",
    "wof:placetype":"locality"
},
  "geometry": {"coordinates":[102.0672,28.38052],"type":"Point"}
}