{
  "type": "Feature",
  "properties": {
    "gn:admin1_code":"2.0",
    "gn:asciiname":"Xuankeng",
    "gn:country_code":"CN",
    "gn:dem":369,
    "gn:feature_class":"P",
    "gn:feature_code":"PPL",
    "gn:name":"Xuankeng",
    "gn:population":0,
    "gn:timezone":"Asia/Shanghai",
    "iso:country":"CN",
    "name:zho_x_preferred":[
        "\u9009\u5751"
    ],
    "wof:name":"Xuankeng",
    "wof:placetype":"locality"
},
  "geometry": {"coordinates":[120.8959,28.19468],"type":"Point"}
}