{
  "type": "Feature",
  "properties": {
    "gn:admin1_code":"14.0",
    "gn:asciiname":"Xueda",
    "gn:country_code":"CN",
    "gn:dem":3636,
    "gn:feature_class":"P",
    "gn:feature_code":"PPL",
    "gn:name":"Xueda",
    "gn:population":0,
    "gn:timezone":"Asia/Urumqi",
    "iso:country":"CN",
    "name:zho_x_preferred":[
        "\u96ea\u8fbe"
    ],
    "wof:name":"Xueda",
    "wof:placetype":"locality"
},
  "geometry": {"coordinates":[87.3528,28.1319],"type":"Point"}
}