{
  "type": "Feature",
  "properties": {
    "gn:admin1_code":"11.0",
    "gn:asciiname":"Jinzhu",
    "gn:country_code":"CN",
    "gn:dem":676,
    "gn:feature_class":"P",
    "gn:feature_code":"PPL",
    "gn:name":"Jinzhu",
    "gn:population":0,
    "gn:timezone":"Asia/Shanghai",
    "iso:country":"CN",
    "name:ceb_x_preferred":[
        "Jinzhu"
    ],
    "name:deu_x_preferred":[
        "Jinzhu"
    ],
    "name:swe_x_preferred":[
        "Jinzhu"
    ],
    "name:zho_x_preferred":[
        "\u91d1\u7af9"
    ],
    "wof:name":"Jinzhu",
    "wof:placetype":"locality"
},
  "geometry": {"coordinates":[111.60772,24.87699],"type":"Point"}
}