{
  "type": "Feature",
  "properties": {
    "gn:admin1_code":"11",
    "gn:asciiname":"Niuzhai",
    "gn:country_code":"CN",
    "gn:dem":324,
    "gn:feature_class":"P",
    "gn:feature_code":"PPL",
    "gn:name":"Niuzhai",
    "gn:population":0,
    "gn:timezone":"Asia/Shanghai",
    "iso:country":"CN",
    "wof:name":"Niuzhai",
    "wof:placetype":"locality"
},
  "geometry": {"coordinates":[111.15667000000001,27.63278],"type":"Point"}
}