{
  "type": "Feature",
  "properties": {
    "gn:admin1_code":"26.0",
    "gn:asciiname":"Leijiacha",
    "gn:country_code":"CN",
    "gn:dem":937,
    "gn:feature_class":"P",
    "gn:feature_code":"PPL",
    "gn:name":"Leijiacha",
    "gn:population":0,
    "gn:timezone":"Asia/Shanghai",
    "iso:country":"CN",
    "name:zho_x_preferred":[
        "\u96f7\u5bb6\u5c94"
    ],
    "wof:name":"Leijiacha",
    "wof:placetype":"locality"
},
  "geometry": {"coordinates":[110.26672000000001,37.67074],"type":"Point"}
}