{
  "type": "Feature",
  "properties": {
    "gn:admin1_code":"32.0",
    "gn:asciiname":"Shajigou",
    "gn:country_code":"CN",
    "gn:dem":1137,
    "gn:feature_class":"P",
    "gn:feature_code":"PPL",
    "gn:name":"Shajigou",
    "gn:population":0,
    "gn:timezone":"Asia/Shanghai",
    "iso:country":"CN",
    "name:zho_x_preferred":[
        "\u6c99\u57fa\u6c9f"
    ],
    "wof:name":"Shajigou",
    "wof:placetype":"locality"
},
  "geometry": {"coordinates":[105.29079,28.03585],"type":"Point"}
}