{
  "type": "Feature",
  "properties": {
    "gn:admin1_code":"25",
    "gn:asciiname":"Shuangshanquan",
    "gn:country_code":"CN",
    "gn:dem":402,
    "gn:feature_class":"P",
    "gn:feature_code":"PPL",
    "gn:name":"Shuangshanquan",
    "gn:population":0,
    "gn:timezone":"Asia/Shanghai",
    "iso:country":"CN",
    "name:zho_x_preferred":[
        "\u53cc\u5c71\u6cc9"
    ],
    "wof:name":"Shuangshanquan",
    "wof:placetype":"locality"
},
  "geometry": {"coordinates":[117.73099999999999,36.4932],"type":"Point"}
}