{
  "type": "Feature",
  "properties": {
    "gn:admin1_code":"10.0",
    "gn:asciiname":"Huren",
    "gn:country_code":"CN",
    "gn:dem":464,
    "gn:feature_class":"P",
    "gn:feature_code":"PPL",
    "gn:name":"Huren",
    "gn:population":0,
    "gn:timezone":"Asia/Shanghai",
    "iso:country":"CN",
    "name:zho_x_preferred":[
        "\u80e1\u4ec1"
    ],
    "wof:name":"Huren",
    "wof:placetype":"locality"
},
  "geometry": {"coordinates":[113.95959999999999,38.14937000000001],"type":"Point"}
}