{
  "type": "Feature",
  "properties": {
    "gn:admin1_code":"26.0",
    "gn:asciiname":"Zhaojia Pingcun",
    "gn:country_code":"CN",
    "gn:dem":1070,
    "gn:feature_class":"P",
    "gn:feature_code":"PPL",
    "gn:name":"Zhaojia Pingcun",
    "gn:population":0,
    "gn:timezone":"Asia/Shanghai",
    "iso:country":"CN",
    "name:zho_x_preferred":[
        "\u8d75\u5bb6\u576a\u6751"
    ],
    "wof:name":"Zhaojia Pingcun",
    "wof:placetype":"locality"
},
  "geometry": {"coordinates":[109.873,37.6482],"type":"Point"}
}