{
  "type": "Feature",
  "properties": {
    "gn:admin1_code":"29.0",
    "gn:asciiname":"Chenjiawan",
    "gn:country_code":"CN",
    "gn:dem":1991,
    "gn:feature_class":"P",
    "gn:feature_code":"PPL",
    "gn:name":"Chenjiawan",
    "gn:population":0,
    "gn:timezone":"Asia/Shanghai",
    "iso:country":"CN",
    "name:zho_x_preferred":[
        "\u9648\u5bb6\u5846"
    ],
    "wof:name":"Chenjiawan",
    "wof:placetype":"locality"
},
  "geometry": {"coordinates":[103.956,27.5977],"type":"Point"}
}