{
  "type": "Feature",
  "properties": {
    "gn:admin1_code":"24.0",
    "gn:asciiname":"Geluzhuang",
    "gn:country_code":"CN",
    "gn:dem":1020,
    "gn:feature_class":"P",
    "gn:feature_code":"PPL",
    "gn:name":"Geluzhuang",
    "gn:population":0,
    "gn:timezone":"Asia/Shanghai",
    "iso:country":"CN",
    "name:zho_x_preferred":[
        "\u572a\u82a6\u5e84"
    ],
    "wof:name":"Geluzhuang",
    "wof:placetype":"locality"
},
  "geometry": {"coordinates":[110.84914000000001,36.34101],"type":"Point"}
}