{
  "type": "Feature",
  "properties": {
    "gn:admin1_code":"29.0",
    "gn:asciiname":"Shaheba",
    "gn:country_code":"CN",
    "gn:dem":1835,
    "gn:feature_class":"P",
    "gn:feature_code":"PPL",
    "gn:name":"Shaheba",
    "gn:population":0,
    "gn:timezone":"Asia/Shanghai",
    "iso:country":"CN",
    "name:zho_x_preferred":[
        "\u6c99\u6cb3\u575d"
    ],
    "wof:name":"Shaheba",
    "wof:placetype":"locality"
},
  "geometry": {"coordinates":[100.04600000000001,23.5938],"type":"Point"}
}