{
  "type": "Feature",
  "properties": {
    "gn:admin1_code":"30.0",
    "gn:asciiname":"Jixinling",
    "gn:country_code":"CN",
    "gn:dem":75,
    "gn:feature_class":"P",
    "gn:feature_code":"PPL",
    "gn:name":"Jixinling",
    "gn:population":0,
    "gn:timezone":"Asia/Shanghai",
    "iso:country":"CN",
    "name:zho_x_preferred":[
        "\u9e21\u5fc3\u5cad"
    ],
    "wof:name":"Jixinling",
    "wof:placetype":"locality"
},
  "geometry": {"coordinates":[113.78361,23.37338],"type":"Point"}
}