{
  "type": "Feature",
  "properties": {
    "gn:admin1_code":"26",
    "gn:asciiname":"Dongwenyangfang",
    "gn:country_code":"CN",
    "gn:dem":420,
    "gn:feature_class":"P",
    "gn:feature_code":"PPL",
    "gn:name":"Dongwenyangfang",
    "gn:population":0,
    "gn:timezone":"Asia/Shanghai",
    "iso:country":"CN",
    "name:und_x_variant":[
        "\u4e1c\u6e29\u9633\u8bbf"
    ],
    "name:zho_x_preferred":[
        "\u4e1c\u6e29\u9633\u8bbf"
    ],
    "wof:name":"Dongwenyangfang",
    "wof:placetype":"locality"
},
  "geometry": {"coordinates":[108.41361000000001,34.27389],"type":"Point"}
}