{
  "type": "Feature",
  "properties": {
    "gn:admin1_code":"07",
    "gn:asciiname":"Qiaodou",
    "gn:country_code":"CN",
    "gn:dem":660,
    "gn:feature_class":"P",
    "gn:feature_code":"PPL",
    "gn:name":"Qiaodou",
    "gn:population":0,
    "gn:timezone":"Asia/Shanghai",
    "iso:country":"CN",
    "name:zho_x_preferred":[
        "\u6865\u515c"
    ],
    "wof:name":"Qiaodou",
    "wof:placetype":"locality"
},
  "geometry": {"coordinates":[118.07135,25.5808],"type":"Point"}
}