{
  "type": "Feature",
  "properties": {
    "gn:admin1_code":"13",
    "gn:asciiname":"Eryilian",
    "gn:country_code":"CN",
    "gn:dem":1045,
    "gn:feature_class":"P",
    "gn:feature_code":"PPL",
    "gn:name":"Eryilian",
    "gn:population":0,
    "gn:timezone":"Asia/Shanghai",
    "iso:country":"CN",
    "name:und_x_variant":[
        "\u4e8c\u4e00\u8fde"
    ],
    "wof:name":"Eryilian",
    "wof:placetype":"locality"
},
  "geometry": {"coordinates":[80.1883,40.40863],"type":"Point"}
}