{
  "type": "Feature",
  "properties": {
    "gn:admin1_code":"32",
    "gn:asciiname":"Quanlong",
    "gn:country_code":"CN",
    "gn:dem":546,
    "gn:feature_class":"P",
    "gn:feature_code":"PPL",
    "gn:name":"Quanlong",
    "gn:population":0,
    "gn:timezone":"Asia/Shanghai",
    "iso:country":"CN",
    "name:zho_x_preferred":[
        "\u5708\u9f99"
    ],
    "wof:name":"Quanlong",
    "wof:placetype":"locality"
},
  "geometry": {"coordinates":[105.63603000000001,31.74636],"type":"Point"}
}