{
  "type": "Feature",
  "properties": {
    "gn:admin1_code":"15.0",
    "gn:asciiname":"Songshugeng",
    "gn:country_code":"CN",
    "gn:dem":2593,
    "gn:feature_class":"P",
    "gn:feature_code":"PPL",
    "gn:name":"Songshugeng",
    "gn:population":0,
    "gn:timezone":"Asia/Shanghai",
    "iso:country":"CN",
    "name:und_x_variant":[
        "\u677e\u6811\u57c2"
    ],
    "wof:name":"Songshugeng",
    "wof:placetype":"locality"
},
  "geometry": {"coordinates":[103.90860000000001,34.67666],"type":"Point"}
}