{
  "type": "Feature",
  "properties": {
    "gn:admin1_code":"3.0",
    "gn:asciiname":"Qiancang",
    "gn:country_code":"CN",
    "gn:dem":656,
    "gn:feature_class":"P",
    "gn:feature_code":"PPL",
    "gn:name":"Qiancang",
    "gn:population":0,
    "gn:timezone":"Asia/Shanghai",
    "iso:country":"CN",
    "name:und_x_variant":[
        "\u524d\u8231"
    ],
    "wof:name":"Qiancang",
    "wof:placetype":"locality"
},
  "geometry": {"coordinates":[116.82407000000001,29.94668],"type":"Point"}
}