{
  "type": "Feature",
  "properties": {
    "gn:admin1_code":"3.0",
    "gn:asciiname":"Dayuanjiao",
    "gn:country_code":"CN",
    "gn:dem":148,
    "gn:feature_class":"P",
    "gn:feature_code":"PPL",
    "gn:name":"Dayuanjiao",
    "gn:population":0,
    "gn:timezone":"Asia/Shanghai",
    "iso:country":"CN",
    "name:und_x_variant":[
        "\u5927\u6c85\u89d2"
    ],
    "wof:name":"Dayuanjiao",
    "wof:placetype":"locality"
},
  "geometry": {"coordinates":[115.71133,26.19408],"type":"Point"}
}