{
  "type": "Feature",
  "properties": {
    "gn:admin1_code":"1.0",
    "gn:asciiname":"Lulicun",
    "gn:country_code":"CN",
    "gn:dem":184,
    "gn:feature_class":"P",
    "gn:feature_code":"PPL",
    "gn:name":"Lulicun",
    "gn:population":0,
    "gn:timezone":"Asia/Shanghai",
    "iso:country":"CN",
    "name:zho_x_preferred":[
        "\u82a6\u91cc\u6751"
    ],
    "name:zho_x_variant":[
        "\u82a6\u8354\u6751"
    ],
    "wof:name":"Lulicun",
    "wof:placetype":"locality"
},
  "geometry": {"coordinates":[117.62689,30.05328],"type":"Point"}
}