{
  "type": "Feature",
  "properties": {
    "gn:admin1_code":"04",
    "gn:asciiname":"Yejiagangcun",
    "gn:country_code":"CN",
    "gn:dem":8,
    "gn:feature_class":"P",
    "gn:feature_code":"PPL",
    "gn:name":"Yejiagangcun",
    "gn:population":0,
    "gn:timezone":"Asia/Shanghai",
    "iso:country":"CN",
    "name:und_x_variant":[
        "Yeh-chia-kang",
        "Yejiagang",
        "\u53f6\u5bb6\u6e2f",
        "Yejiagangcun"
    ],
    "name:zho_x_preferred":[
        "\u53f6\u5bb6\u6e2f\u6751"
    ],
    "wof:name":"Yejiagangcun",
    "wof:placetype":"locality"
},
  "geometry": {"coordinates":[120.5047,31.02008],"type":"Point"}
}