{
  "type": "Feature",
  "properties": {
    "gn:admin1_code":"20.0",
    "gn:asciiname":"Gongyingpan",
    "gn:country_code":"CN",
    "gn:dem":1773,
    "gn:feature_class":"P",
    "gn:feature_code":"PPL",
    "gn:name":"Gongyingpan",
    "gn:population":0,
    "gn:timezone":"Asia/Shanghai",
    "iso:country":"CN",
    "name:und_x_variant":[
        "\u516c\u8425\u76d8"
    ],
    "wof:name":"Gongyingpan",
    "wof:placetype":"locality"
},
  "geometry": {"coordinates":[110.56495,41.27922],"type":"Point"}
}