{
  "type": "Feature",
  "properties": {
    "gn:admin1_code":"2.0",
    "gn:asciiname":"Yudian",
    "gn:country_code":"CN",
    "gn:dem":120,
    "gn:feature_class":"P",
    "gn:feature_code":"PPL",
    "gn:name":"Yudian",
    "gn:population":0,
    "gn:timezone":"Asia/Shanghai",
    "iso:country":"CN",
    "name:zho_x_preferred":[
        "\u79b9\u7538"
    ],
    "wof:name":"Yudian",
    "wof:placetype":"locality"
},
  "geometry": {"coordinates":[119.01861,29.26895],"type":"Point"}
}