{
  "type": "Feature",
  "properties": {
    "gn:admin1_code":"33.0",
    "gn:asciiname":"Xieli",
    "gn:country_code":"CN",
    "gn:dem":337,
    "gn:feature_class":"P",
    "gn:feature_code":"PPL",
    "gn:name":"Xieli",
    "gn:population":0,
    "gn:timezone":"Asia/Shanghai",
    "iso:country":"CN",
    "name:zho_x_preferred":[
        "\u534f\u529b"
    ],
    "wof:name":"Xieli",
    "wof:placetype":"locality"
},
  "geometry": {"coordinates":[108.91307999999999,30.66293],"type":"Point"}
}