{
  "type": "Feature",
  "properties": {
    "gn:admin1_code":"12.0",
    "gn:asciiname":"Liaoyehu",
    "gn:country_code":"CN",
    "gn:dem":943,
    "gn:feature_class":"P",
    "gn:feature_code":"PPL",
    "gn:name":"Liaoyehu",
    "gn:population":0,
    "gn:timezone":"Asia/Shanghai",
    "iso:country":"CN",
    "name:zho_x_preferred":[
        "\u8fbd\u53f6\u6e56"
    ],
    "wof:name":"Liaoyehu",
    "wof:placetype":"locality"
},
  "geometry": {"coordinates":[110.32211,32.53872],"type":"Point"}
}