{
  "type": "Feature",
  "properties": {
    "gn:admin1_code":"25.0",
    "gn:asciiname":"Waguanyaocun",
    "gn:country_code":"CN",
    "gn:dem":22,
    "gn:feature_class":"P",
    "gn:feature_code":"PPL",
    "gn:name":"Waguanyaocun",
    "gn:population":0,
    "gn:timezone":"Asia/Shanghai",
    "iso:country":"CN",
    "name:zho_x_preferred":[
        "\u74e6\u7f50\u7a91\u6751"
    ],
    "wof:name":"Waguanyaocun",
    "wof:placetype":"locality"
},
  "geometry": {"coordinates":[120.98223,36.67796],"type":"Point"}
}