{
  "type": "Feature",
  "properties": {
    "gn:admin1_code":"11.0",
    "gn:asciiname":"Ya'ertian",
    "gn:country_code":"CN",
    "gn:dem":549,
    "gn:feature_class":"P",
    "gn:feature_code":"PPL",
    "gn:name":"Ya\u2019ertian",
    "gn:population":0,
    "gn:timezone":"Asia/Shanghai",
    "iso:country":"CN",
    "name:und_x_variant":[
        "Ya\u2019ertian"
    ],
    "name:zho_x_preferred":[
        "\u9e2d\u513f\u7530"
    ],
    "wof:name":"Ya'ertian",
    "wof:placetype":"locality"
},
  "geometry": {"coordinates":[110.55669,27.66191],"type":"Point"}
}