{
  "type": "Feature",
  "properties": {
    "gn:admin1_code":"30",
    "gn:asciiname":"Makengshui",
    "gn:country_code":"CN",
    "gn:dem":607,
    "gn:feature_class":"P",
    "gn:feature_code":"PPL",
    "gn:name":"Makengshui",
    "gn:population":0,
    "gn:timezone":"Asia/Shanghai",
    "iso:country":"CN",
    "name:und_x_variant":[
        "\u9ebb\u5751\u6c34",
        "Makeng"
    ],
    "wof:name":"Makengshui",
    "wof:placetype":"locality"
},
  "geometry": {"coordinates":[113.46666999999999,25.26],"type":"Point"}
}