{
  "type": "Feature",
  "properties": {
    "gn:admin1_code":"29.0",
    "gn:asciiname":"Haijiaoluo",
    "gn:country_code":"CN",
    "gn:dem":1870,
    "gn:feature_class":"P",
    "gn:feature_code":"PPL",
    "gn:name":"Haijiaoluo",
    "gn:population":0,
    "gn:timezone":"Asia/Shanghai",
    "iso:country":"CN",
    "name:zho_x_preferred":[
        "\u6d77\u89d2\u843d"
    ],
    "wof:name":"Haijiaoluo",
    "wof:placetype":"locality"
},
  "geometry": {"coordinates":[101.214,25.5432],"type":"Point"}
}