{
  "type": "Feature",
  "properties": {
    "gn:admin1_code":"13",
    "gn:asciiname":"Xincaoyuan",
    "gn:country_code":"CN",
    "gn:dem":-97,
    "gn:feature_class":"P",
    "gn:feature_code":"PPL",
    "gn:name":"Xincaoyuan",
    "gn:population":0,
    "gn:timezone":"Asia/Urumqi",
    "iso:country":"CN",
    "name:und_x_variant":[
        "\u65b0\u8349\u539f"
    ],
    "wof:name":"Xincaoyuan",
    "wof:placetype":"locality"
},
  "geometry": {"coordinates":[88.98021,42.69612],"type":"Point"}
}