{
  "type": "Feature",
  "properties": {
    "gn:admin1_code":"30",
    "gn:asciiname":"Guiling",
    "gn:country_code":"CN",
    "gn:dem":14,
    "gn:feature_class":"P",
    "gn:feature_code":"PPLA4",
    "gn:name":"Guiling",
    "gn:population":0,
    "gn:timezone":"Asia/Shanghai",
    "iso:country":"CN",
    "name:und_x_variant":[
        "\u6842\u5cad",
        "Guiling Zhen",
        "\u6842\u5cad\u9547"
    ],
    "wof:name":"Guiling",
    "wof:placetype":"locality"
},
  "geometry": {"coordinates":[116.2375,23.588],"type":"Point"}
}