{
  "type": "Feature",
  "properties": {
    "gn:admin1_code":"13.0",
    "gn:asciiname":"Kutaikelike",
    "gn:country_code":"CN",
    "gn:dem":1193,
    "gn:feature_class":"P",
    "gn:feature_code":"PPL",
    "gn:name":"Kutaikelike",
    "gn:population":0,
    "gn:timezone":"Asia/Shanghai",
    "iso:country":"CN",
    "name:zho_x_preferred":[
        "\u5e93\u53f0\u514b\u529b\u514b"
    ],
    "wof:name":"Kutaikelike",
    "wof:placetype":"locality"
},
  "geometry": {"coordinates":[76.92681,39.12284],"type":"Point"}
}