{
  "type": "Feature",
  "properties": {
    "gn:admin1_code":"1.0",
    "gn:asciiname":"Anwu",
    "gn:country_code":"CN",
    "gn:dem":47,
    "gn:feature_class":"P",
    "gn:feature_code":"PPLA4",
    "gn:name":"Anwu",
    "gn:population":0,
    "gn:timezone":"Asia/Shanghai",
    "iso:country":"CN",
    "name:und_x_variant":[
        "\u5b89\u5434",
        "Anwuxiang",
        "\u5b89\u5434\u4e61"
    ],
    "wof:name":"Anwu",
    "wof:placetype":"locality"
},
  "geometry": {"coordinates":[118.24803,30.58808],"type":"Point"}
}