{
  "type": "Feature",
  "properties": {
    "gn:admin1_code":"15.0",
    "gn:asciiname":"Malian",
    "gn:country_code":"CN",
    "gn:dem":1272,
    "gn:feature_class":"P",
    "gn:feature_code":"PPL",
    "gn:name":"Malian",
    "gn:population":0,
    "gn:timezone":"Asia/Shanghai",
    "iso:country":"CN",
    "name:deu_x_preferred":[
        "Malian"
    ],
    "name:und_x_variant":[
        "\u9a6c\u8fde"
    ],
    "wof:name":"Malian",
    "wof:placetype":"locality"
},
  "geometry": {"coordinates":[105.60518,33.49739],"type":"Point"}
}