{
  "type": "Feature",
  "properties": {
    "gn:admin1_code":"11.0",
    "gn:asciiname":"Yuanchong Wujia",
    "gn:country_code":"CN",
    "gn:dem":64,
    "gn:feature_class":"P",
    "gn:feature_code":"PPL",
    "gn:name":"Yuanchong Wujia",
    "gn:population":0,
    "gn:timezone":"Asia/Shanghai",
    "iso:country":"CN",
    "name:zho_x_preferred":[
        "\u5143\u51b2\u4f0d\u5bb6"
    ],
    "wof:name":"Yuanchong Wujia",
    "wof:placetype":"locality"
},
  "geometry": {"coordinates":[112.82056,26.65329],"type":"Point"}
}