{
  "type": "Feature",
  "properties": {
    "gn:admin1_code":"21.0",
    "gn:asciiname":"Erbudun",
    "gn:country_code":"CN",
    "gn:dem":1560,
    "gn:feature_class":"P",
    "gn:feature_code":"PPL",
    "gn:name":"Erbudun",
    "gn:population":0,
    "gn:timezone":"Asia/Shanghai",
    "iso:country":"CN",
    "name:zho_x_preferred":[
        "\u4e8c\u6b65\u58a9"
    ],
    "wof:name":"Erbudun",
    "wof:placetype":"locality"
},
  "geometry": {"coordinates":[106.504,37.0961],"type":"Point"}
}