{
  "type": "Feature",
  "properties": {
    "gn:admin1_code":"7.0",
    "gn:asciiname":"Longfengchang",
    "gn:country_code":"CN",
    "gn:dem":499,
    "gn:feature_class":"P",
    "gn:feature_code":"PPL",
    "gn:name":"Longfengchang",
    "gn:population":0,
    "gn:timezone":"Asia/Shanghai",
    "iso:country":"CN",
    "name:und_x_variant":[
        "\u9f99\u51e4\u573a"
    ],
    "name:zho_x_preferred":[
        "\u9f99\u51e4\u573a"
    ],
    "wof:name":"Longfengchang",
    "wof:placetype":"locality"
},
  "geometry": {"coordinates":[117.75479,26.02535],"type":"Point"}
}