{
  "type": "Feature",
  "properties": {
    "gn:admin1_code":"5.0",
    "gn:asciiname":"Wubentun",
    "gn:country_code":"CN",
    "gn:dem":306,
    "gn:feature_class":"P",
    "gn:feature_code":"PPL",
    "gn:name":"Wubentun",
    "gn:population":0,
    "gn:timezone":"Asia/Shanghai",
    "iso:country":"CN",
    "name:zho_x_preferred":[
        "\u52a1\u672c\u5c6f"
    ],
    "wof:name":"Wubentun",
    "wof:placetype":"locality"
},
  "geometry": {"coordinates":[126.4789,42.96961],"type":"Point"}
}