{
  "type": "Feature",
  "properties": {
    "gn:admin1_code":"10",
    "gn:asciiname":"Xiakanzi",
    "gn:country_code":"CN",
    "gn:dem":360,
    "gn:feature_class":"P",
    "gn:feature_code":"PPL",
    "gn:name":"Xiakanzi",
    "gn:population":0,
    "gn:timezone":"Asia/Shanghai",
    "iso:country":"CN",
    "name:zho_x_preferred":[
        "\u4e0b\u574e\u5b50"
    ],
    "wof:name":"Xiakanzi",
    "wof:placetype":"locality"
},
  "geometry": {"coordinates":[118.46062000000001,40.63701],"type":"Point"}
}