{
  "type": "Feature",
  "properties": {
    "gn:admin1_code":"14.0",
    "gn:asciiname":"Wuqiancun",
    "gn:country_code":"CN",
    "gn:dem":4897,
    "gn:feature_class":"P",
    "gn:feature_code":"PPL",
    "gn:name":"Wuqiancun",
    "gn:population":0,
    "gn:timezone":"Asia/Urumqi",
    "iso:country":"CN",
    "name:zho_x_preferred":[
        "\u4e4c\u94c5\u6751"
    ],
    "wof:name":"Wuqiancun",
    "wof:placetype":"locality"
},
  "geometry": {"coordinates":[92.87672000000001,30.95171],"type":"Point"}
}