{
  "type": "Feature",
  "properties": {
    "gn:admin1_code":"2.0",
    "gn:asciiname":"Panshantou",
    "gn:country_code":"CN",
    "gn:dem":557,
    "gn:feature_class":"P",
    "gn:feature_code":"PPL",
    "gn:name":"Panshantou",
    "gn:population":0,
    "gn:timezone":"Asia/Shanghai",
    "iso:country":"CN",
    "name:zho_x_preferred":[
        "\u6f58\u5c71\u5934"
    ],
    "wof:name":"Panshantou",
    "wof:placetype":"locality"
},
  "geometry": {"coordinates":[119.68505,28.58631],"type":"Point"}
}