{
  "type": "Feature",
  "properties": {
    "gn:admin1_code":"3.0",
    "gn:asciiname":"Zhashu",
    "gn:country_code":"CN",
    "gn:dem":51,
    "gn:feature_class":"P",
    "gn:feature_code":"PPL",
    "gn:name":"Zhashu",
    "gn:population":0,
    "gn:timezone":"Asia/Shanghai",
    "iso:country":"CN",
    "name:und_x_variant":[
        "\u69a8\u6811"
    ],
    "wof:name":"Zhashu",
    "wof:placetype":"locality"
},
  "geometry": {"coordinates":[117.23539,29.54324],"type":"Point"}
}