{
  "type": "Feature",
  "properties": {
    "gn:admin1_code":"26.0",
    "gn:asciiname":"Baiying",
    "gn:country_code":"CN",
    "gn:dem":884,
    "gn:feature_class":"P",
    "gn:feature_code":"PPL",
    "gn:name":"Baiying",
    "gn:population":0,
    "gn:timezone":"Asia/Shanghai",
    "iso:country":"CN",
    "name:zho_x_preferred":[
        "\u767d\u8425"
    ],
    "wof:name":"Baiying",
    "wof:placetype":"locality"
},
  "geometry": {"coordinates":[109.431,33.1243],"type":"Point"}
}