{
  "type": "Feature",
  "properties": {
    "gn:admin1_code":"32.0",
    "gn:asciiname":"Wuxianmiao",
    "gn:country_code":"CN",
    "gn:dem":1868,
    "gn:feature_class":"P",
    "gn:feature_code":"PPL",
    "gn:name":"Wuxianmiao",
    "gn:population":0,
    "gn:timezone":"Asia/Shanghai",
    "iso:country":"CN",
    "name:zho_x_preferred":[
        "\u4e94\u4ed9\u5e99"
    ],
    "wof:name":"Wuxianmiao",
    "wof:placetype":"locality"
},
  "geometry": {"coordinates":[103.872,31.6693],"type":"Point"}
}