{
  "type": "Feature",
  "properties": {
    "gn:admin1_code":"24.0",
    "gn:asciiname":"Jing'ao",
    "gn:country_code":"CN",
    "gn:dem":1162,
    "gn:feature_class":"P",
    "gn:feature_code":"PPL",
    "gn:name":"Jing\u2019ao",
    "gn:population":0,
    "gn:timezone":"Asia/Shanghai",
    "iso:country":"CN",
    "name:und_x_variant":[
        "Jing\u2019ao"
    ],
    "name:zho_x_preferred":[
        "\u4e95\u51f9"
    ],
    "wof:name":"Jing'ao",
    "wof:placetype":"locality"
},
  "geometry": {"coordinates":[113.20422000000001,35.65107000000001],"type":"Point"}
}