{
  "type": "Feature",
  "properties": {
    "gn:admin1_code":"8.0",
    "gn:asciiname":"Chedi Yingzi",
    "gn:country_code":"CN",
    "gn:dem":346,
    "gn:feature_class":"P",
    "gn:feature_code":"PPL",
    "gn:name":"Chedi Yingzi",
    "gn:population":0,
    "gn:timezone":"Asia/Shanghai",
    "iso:country":"CN",
    "name:zho_x_preferred":[
        "\u8f66\u5730\u8425\u5b50"
    ],
    "wof:name":"Chedi Yingzi",
    "wof:placetype":"locality"
},
  "geometry": {"coordinates":[126.91279,49.97547],"type":"Point"}
}