{
  "type": "Feature",
  "properties": {
    "gn:admin1_code":"24.0",
    "gn:asciiname":"Fengcangcun",
    "gn:country_code":"CN",
    "gn:dem":912,
    "gn:feature_class":"P",
    "gn:feature_code":"PPL",
    "gn:name":"Fengcangcun",
    "gn:population":0,
    "gn:timezone":"Asia/Shanghai",
    "iso:country":"CN",
    "name:zho_x_preferred":[
        "\u51af\u4ed3\u6751"
    ],
    "wof:name":"Fengcangcun",
    "wof:placetype":"locality"
},
  "geometry": {"coordinates":[110.59977000000001,36.61926],"type":"Point"}
}