{
  "type": "Feature",
  "properties": {
    "gn:admin1_code":"32.0",
    "gn:asciiname":"Heiri",
    "gn:country_code":"CN",
    "gn:dem":3731,
    "gn:feature_class":"P",
    "gn:feature_code":"PPL",
    "gn:name":"Heiri",
    "gn:population":0,
    "gn:timezone":"Asia/Shanghai",
    "iso:country":"CN",
    "name:zho_x_preferred":[
        "\u9ed1\u65e5"
    ],
    "wof:name":"Heiri",
    "wof:placetype":"locality"
},
  "geometry": {"coordinates":[100.26276,30.88198],"type":"Point"}
}