{
  "type": "Feature",
  "properties": {
    "gn:admin1_code":"18",
    "gn:asciiname":"Nimogu",
    "gn:country_code":"CN",
    "gn:dem":1473,
    "gn:feature_class":"P",
    "gn:feature_code":"PPL",
    "gn:name":"Nimogu",
    "gn:population":0,
    "gn:timezone":"Asia/Shanghai",
    "iso:country":"CN",
    "name:zho_x_preferred":[
        "\u6ce5\u58a8\u53e4"
    ],
    "wof:name":"Nimogu",
    "wof:placetype":"locality"
},
  "geometry": {"coordinates":[104.788,25.1589],"type":"Point"}
}