{
  "type": "Feature",
  "properties": {
    "gn:admin1_code":"12.0",
    "gn:asciiname":"Sangyuanba",
    "gn:country_code":"CN",
    "gn:dem":698,
    "gn:feature_class":"P",
    "gn:feature_code":"PPL",
    "gn:name":"Sangyuanba",
    "gn:population":0,
    "gn:timezone":"Asia/Shanghai",
    "iso:country":"CN",
    "name:zho_x_preferred":[
        "\u6851\u56ed\u575d"
    ],
    "wof:name":"Sangyuanba",
    "wof:placetype":"locality"
},
  "geometry": {"coordinates":[110.05788,30.64581],"type":"Point"}
}