{
  "type": "Feature",
  "properties": {
    "gn:admin1_code":"12.0",
    "gn:asciiname":"Hongjiachang",
    "gn:country_code":"CN",
    "gn:dem":31,
    "gn:feature_class":"P",
    "gn:feature_code":"PPL",
    "gn:name":"Hongjiachang",
    "gn:population":0,
    "gn:timezone":"Asia/Shanghai",
    "iso:country":"CN",
    "name:zho_x_preferred":[
        "Hongjiachang"
    ],
    "name:zho_x_variant":[
        "\u6d2a\u5bb6\u573a"
    ],
    "wof:name":"Hongjiachang",
    "wof:placetype":"locality"
},
  "geometry": {"coordinates":[112.63155999999999,30.29999],"type":"Point"}
}