{
  "type": "Feature",
  "properties": {
    "gn:admin1_code":"26.0",
    "gn:asciiname":"Baiqisi",
    "gn:country_code":"CN",
    "gn:dem":483,
    "gn:feature_class":"P",
    "gn:feature_code":"PPL",
    "gn:name":"Baiqisi",
    "gn:population":0,
    "gn:timezone":"Asia/Shanghai",
    "iso:country":"CN",
    "name:zho_x_preferred":[
        "\u767d\u8d77\u5bfa"
    ],
    "wof:name":"Baiqisi",
    "wof:placetype":"locality"
},
  "geometry": {"coordinates":[109.81301000000001,34.97412],"type":"Point"}
}