{
  "type": "Feature",
  "properties": {
    "gn:admin1_code":"2.0",
    "gn:asciiname":"Dashatou",
    "gn:country_code":"CN",
    "gn:dem":1,
    "gn:feature_class":"P",
    "gn:feature_code":"PPL",
    "gn:name":"Dashatou",
    "gn:population":0,
    "gn:timezone":"Asia/Shanghai",
    "iso:country":"CN",
    "name:zho_x_preferred":[
        "\u5927\u6c99\u5934"
    ],
    "wof:name":"Dashatou",
    "wof:placetype":"locality"
},
  "geometry": {"coordinates":[121.92650999999999,30.31622],"type":"Point"}
}