{
  "type": "Feature",
  "properties": {
    "gn:admin1_code":"19.0",
    "gn:asciiname":"Wangjia Wopu",
    "gn:country_code":"CN",
    "gn:dem":482,
    "gn:feature_class":"P",
    "gn:feature_code":"PPL",
    "gn:name":"Wangjia Wopu",
    "gn:population":0,
    "gn:timezone":"Asia/Shanghai",
    "iso:country":"CN",
    "name:zho_x_preferred":[
        "\u738b\u5bb6\u7a9d\u94fa"
    ],
    "wof:name":"Wangjia Wopu",
    "wof:placetype":"locality"
},
  "geometry": {"coordinates":[119.65900000000001,40.441],"type":"Point"}
}