{
  "type": "Feature",
  "properties": {
    "gn:admin1_code":"32.0",
    "gn:asciiname":"Xiaoniuchang",
    "gn:country_code":"CN",
    "gn:dem":2386,
    "gn:feature_class":"P",
    "gn:feature_code":"PPLF",
    "gn:name":"Xiaoniuchang",
    "gn:population":0,
    "gn:timezone":"Asia/Shanghai",
    "iso:country":"CN",
    "name:zho_x_preferred":[
        "\u5c0f\u725b\u573a"
    ],
    "wof:name":"Xiaoniuchang",
    "wof:placetype":"locality"
},
  "geometry": {"coordinates":[102.29600000000001,29.4646],"type":"Point"}
}