{
  "type": "Feature",
  "properties": {
    "gn:admin1_code":"26.0",
    "gn:asciiname":"Xuyaoxian",
    "gn:country_code":"CN",
    "gn:dem":1536,
    "gn:feature_class":"P",
    "gn:feature_code":"PPL",
    "gn:name":"Xuyaoxian",
    "gn:population":0,
    "gn:timezone":"Asia/Shanghai",
    "iso:country":"CN",
    "name:und_x_variant":[
        "\u8bb8\u5d3e\u5c98"
    ],
    "wof:name":"Xuyaoxian",
    "wof:placetype":"locality"
},
  "geometry": {"coordinates":[107.91437999999999,36.96918],"type":"Point"}
}