{
  "type": "Feature",
  "properties": {
    "gn:admin1_code":"26.0",
    "gn:asciiname":"Longdong'ao",
    "gn:country_code":"CN",
    "gn:dem":976,
    "gn:feature_class":"P",
    "gn:feature_code":"PPL",
    "gn:name":"Longdong\u2019ao",
    "gn:population":0,
    "gn:timezone":"Asia/Shanghai",
    "iso:country":"CN",
    "name:und_x_variant":[
        "Longdong\u2019ao"
    ],
    "name:zho_x_preferred":[
        "\u9f99\u6d1e\u51f9"
    ],
    "wof:name":"Longdong'ao",
    "wof:placetype":"locality"
},
  "geometry": {"coordinates":[110.25718000000001,33.41520999999999],"type":"Point"}
}