{
  "type": "Feature",
  "properties": {
    "gn:admin1_code":"25",
    "gn:asciiname":"Tumen",
    "gn:country_code":"CN",
    "gn:dem":189,
    "gn:feature_class":"P",
    "gn:feature_code":"PPL",
    "gn:name":"Tumen",
    "gn:population":0,
    "gn:timezone":"Asia/Shanghai",
    "iso:country":"CN",
    "name:ceb_x_preferred":[
        "Tumen"
    ],
    "name:deu_x_preferred":[
        "Tumen"
    ],
    "name:fra_x_preferred":[
        "Tumen"
    ],
    "name:ita_x_preferred":[
        "Tumen"
    ],
    "name:nds_x_preferred":[
        "Tumen"
    ],
    "name:nld_x_preferred":[
        "Tumen"
    ],
    "name:nor_x_preferred":[
        "Tumen"
    ],
    "name:pol_x_preferred":[
        "Tumen"
    ],
    "name:spa_x_preferred":[
        "Tumen"
    ],
    "name:swe_x_preferred":[
        "Tumen"
    ],
    "name:zho_x_preferred":[
        "\u571f\u95e8"
    ],
    "wof:name":"Tumen",
    "wof:placetype":"locality"
},
  "geometry": {"coordinates":[117.343,36.0845],"type":"Point"}
}