{
  "type": "Feature",
  "properties": {
    "gn:admin1_code":"9.0",
    "gn:asciiname":"Shanqiancun",
    "gn:country_code":"CN",
    "gn:dem":775,
    "gn:feature_class":"P",
    "gn:feature_code":"PPL",
    "gn:name":"Shanqiancun",
    "gn:population":0,
    "gn:timezone":"Asia/Shanghai",
    "iso:country":"CN",
    "name:zho_x_preferred":[
        "\u5c71\u524d\u6751"
    ],
    "wof:name":"Shanqiancun",
    "wof:placetype":"locality"
},
  "geometry": {"coordinates":[111.55596,34.02734],"type":"Point"}
}