{
  "type": "Feature",
  "properties": {
    "gn:admin1_code":"19.0",
    "gn:asciiname":"Lashufang",
    "gn:country_code":"CN",
    "gn:dem":68,
    "gn:feature_class":"P",
    "gn:feature_code":"PPL",
    "gn:name":"Lashufang",
    "gn:population":0,
    "gn:timezone":"Asia/Shanghai",
    "iso:country":"CN",
    "name:zho_x_preferred":[
        "\u814a\u6811\u623f"
    ],
    "wof:name":"Lashufang",
    "wof:placetype":"locality"
},
  "geometry": {"coordinates":[121.75700000000001,39.6028],"type":"Point"}
}