{
  "type": "Feature",
  "properties": {
    "gn:admin1_code":"8.0",
    "gn:asciiname":"Xiduangouzi",
    "gn:country_code":"CN",
    "gn:dem":325,
    "gn:feature_class":"P",
    "gn:feature_code":"PPL",
    "gn:name":"Xiduangouzi",
    "gn:population":0,
    "gn:timezone":"Asia/Shanghai",
    "iso:country":"CN",
    "name:und_x_variant":[
        "\u897f\u77ed\u6c9f\u5b50"
    ],
    "wof:name":"Xiduangouzi",
    "wof:placetype":"locality"
},
  "geometry": {"coordinates":[130.82660000000001,43.74407],"type":"Point"}
}