{
  "type": "Feature",
  "properties": {
    "gn:admin1_code":"14.0",
    "gn:asciiname":"Duodongjia",
    "gn:country_code":"CN",
    "gn:dem":4256,
    "gn:feature_class":"P",
    "gn:feature_code":"PPL",
    "gn:name":"Duodongjia",
    "gn:population":0,
    "gn:timezone":"Asia/Urumqi",
    "iso:country":"CN",
    "name:zho_x_preferred":[
        "\u591a\u4e1c\u7532"
    ],
    "wof:name":"Duodongjia",
    "wof:placetype":"locality"
},
  "geometry": {"coordinates":[93.68971000000001,29.44873],"type":"Point"}
}