{
  "type": "Feature",
  "properties": {
    "gn:admin1_code":"21.0",
    "gn:asciiname":"Nanbu",
    "gn:country_code":"CN",
    "gn:dem":1565,
    "gn:feature_class":"P",
    "gn:feature_code":"PPL",
    "gn:name":"Nanbu",
    "gn:population":0,
    "gn:timezone":"Asia/Shanghai",
    "iso:country":"CN",
    "name:ceb_x_preferred":[
        "Nanbu"
    ],
    "name:fra_x_preferred":[
        "Nanbu"
    ],
    "name:jpn_x_preferred":[
        "\u5357\u90e8\u753a"
    ],
    "name:kor_x_preferred":[
        "\ub09c\ubd80\uc815"
    ],
    "name:und_x_variant":[
        "\u5357\u5821"
    ],
    "name:zho_x_preferred":[
        "\u5357\u5821"
    ],
    "name:zho_x_variant":[
        "\u5357\u90e8\u753a"
    ],
    "wof:name":"Nanbu",
    "wof:placetype":"locality"
},
  "geometry": {"coordinates":[106.09448,36.48122],"type":"Point"}
}