{
  "type": "Feature",
  "properties": {
    "gn:admin1_code":"11.0",
    "gn:asciiname":"Lefuting",
    "gn:country_code":"CN",
    "gn:dem":263,
    "gn:feature_class":"P",
    "gn:feature_code":"PPL",
    "gn:name":"Lefuting",
    "gn:population":0,
    "gn:timezone":"Asia/Shanghai",
    "iso:country":"CN",
    "name:zho_x_preferred":[
        "\u4e50\u798f\u4ead"
    ],
    "wof:name":"Lefuting",
    "wof:placetype":"locality"
},
  "geometry": {"coordinates":[111.82897,27.2101],"type":"Point"}
}