{
  "type": "Feature",
  "properties": {
    "gn:admin1_code":"32.0",
    "gn:asciiname":"Xiaoshan",
    "gn:country_code":"CN",
    "gn:dem":758,
    "gn:feature_class":"P",
    "gn:feature_code":"PPL",
    "gn:name":"Xiaoshan",
    "gn:population":0,
    "gn:timezone":"Asia/Shanghai",
    "iso:country":"CN",
    "name:zho_x_preferred":[
        "\u8096\u5c71"
    ],
    "wof:name":"Xiaoshan",
    "wof:placetype":"locality"
},
  "geometry": {"coordinates":[103.4007,29.62306],"type":"Point"}
}