{
  "type": "Feature",
  "properties": {
    "gn:admin1_code":"29.0",
    "gn:asciiname":"Tianbaosi",
    "gn:country_code":"CN",
    "gn:dem":1831,
    "gn:feature_class":"P",
    "gn:feature_code":"PPL",
    "gn:name":"Tianbaosi",
    "gn:population":0,
    "gn:timezone":"Asia/Shanghai",
    "iso:country":"CN",
    "name:zho_x_preferred":[
        "\u5929\u5b9d\u5bfa"
    ],
    "wof:name":"Tianbaosi",
    "wof:placetype":"locality"
},
  "geometry": {"coordinates":[103.739,25.0525],"type":"Point"}
}