{
  "type": "Feature",
  "properties": {
    "gn:admin1_code":"19.0",
    "gn:asciiname":"Heidagou",
    "gn:country_code":"CN",
    "gn:dem":292,
    "gn:feature_class":"P",
    "gn:feature_code":"PPL",
    "gn:name":"Heidagou",
    "gn:population":0,
    "gn:timezone":"Asia/Shanghai",
    "iso:country":"CN",
    "name:und_x_variant":[
        "\u9ed1\u8fbe\u6c9f"
    ],
    "wof:name":"Heidagou",
    "wof:placetype":"locality"
},
  "geometry": {"coordinates":[124.32086,41.76038],"type":"Point"}
}