{
  "type": "Feature",
  "properties": {
    "gn:admin1_code":"26.0",
    "gn:asciiname":"Gongchengcun",
    "gn:country_code":"CN",
    "gn:dem":997,
    "gn:feature_class":"P",
    "gn:feature_code":"PPL",
    "gn:name":"Gongchengcun",
    "gn:population":0,
    "gn:timezone":"Asia/Shanghai",
    "iso:country":"CN",
    "name:zho_x_preferred":[
        "\u516c\u57ce\u6751"
    ],
    "wof:name":"Gongchengcun",
    "wof:placetype":"locality"
},
  "geometry": {"coordinates":[110.17082000000001,36.23182],"type":"Point"}
}