{
  "type": "Feature",
  "properties": {
    "gn:admin1_code":"11.0",
    "gn:asciiname":"Qingtianping",
    "gn:country_code":"CN",
    "gn:dem":1239,
    "gn:feature_class":"P",
    "gn:feature_code":"PPL",
    "gn:name":"Qingtianping",
    "gn:population":0,
    "gn:timezone":"Asia/Shanghai",
    "iso:country":"CN",
    "name:zho_x_preferred":[
        "\u9752\u5929\u576a"
    ],
    "wof:name":"Qingtianping",
    "wof:placetype":"locality"
},
  "geometry": {"coordinates":[109.25331,28.89037],"type":"Point"}
}