{
  "type": "Feature",
  "properties": {
    "gn:admin1_code":"24.0",
    "gn:asciiname":"Yangjiayu",
    "gn:cc2":"CN",
    "gn:country_code":"CN",
    "gn:dem":922,
    "gn:feature_class":"P",
    "gn:feature_code":"PPL",
    "gn:name":"Yangjiayu",
    "gn:population":0,
    "gn:timezone":"Asia/Shanghai",
    "iso:country":"CN",
    "name:und_x_variant":[
        "Yang-chia-y\u00fc",
        "Yangjiayu"
    ],
    "wof:name":"Yangjiayu",
    "wof:placetype":"locality"
},
  "geometry": {"coordinates":[112.60639,37.89222],"type":"Point"}
}