{
  "type": "Feature",
  "properties": {
    "gn:admin1_code":"32.0",
    "gn:asciiname":"Panjia Yuanzi",
    "gn:country_code":"CN",
    "gn:dem":500,
    "gn:feature_class":"P",
    "gn:feature_code":"PPL",
    "gn:name":"Panjia Yuanzi",
    "gn:population":0,
    "gn:timezone":"Asia/Shanghai",
    "iso:country":"CN",
    "name:zho_x_preferred":[
        "\u6f58\u5bb6\u9662\u5b50"
    ],
    "wof:name":"Panjia Yuanzi",
    "wof:placetype":"locality"
},
  "geometry": {"coordinates":[104.24299999999999,31.114],"type":"Point"}
}