{
  "type": "Feature",
  "properties": {
    "gn:admin1_code":"29.0",
    "gn:asciiname":"Songshanlin",
    "gn:country_code":"CN",
    "gn:dem":1410,
    "gn:feature_class":"P",
    "gn:feature_code":"PPL",
    "gn:name":"Songshanlin",
    "gn:population":0,
    "gn:timezone":"Asia/Shanghai",
    "iso:country":"CN",
    "name:zho_x_preferred":[
        "\u677e\u5c71\u6797"
    ],
    "wof:name":"Songshanlin",
    "wof:placetype":"locality"
},
  "geometry": {"coordinates":[100.61499999999999,22.9355],"type":"Point"}
}