{
  "type": "Feature",
  "properties": {
    "gn:admin1_code":"32.0",
    "gn:asciiname":"Tianhuangyuan",
    "gn:country_code":"CN",
    "gn:dem":587,
    "gn:feature_class":"P",
    "gn:feature_code":"PPL",
    "gn:name":"Tianhuangyuan",
    "gn:population":0,
    "gn:timezone":"Asia/Shanghai",
    "iso:country":"CN",
    "name:zho_x_preferred":[
        "\u5929\u968d\u9662"
    ],
    "wof:name":"Tianhuangyuan",
    "wof:placetype":"locality"
},
  "geometry": {"coordinates":[105.43600000000001,32.657],"type":"Point"}
}