{
  "type": "Feature",
  "properties": {
    "gn:admin1_code":"20.0",
    "gn:asciiname":"Songmushao",
    "gn:country_code":"CN",
    "gn:dem":249,
    "gn:feature_class":"P",
    "gn:feature_code":"PPL",
    "gn:name":"Songmushao",
    "gn:population":0,
    "gn:timezone":"Asia/Shanghai",
    "iso:country":"CN",
    "name:zho_x_preferred":[
        "\u677e\u6728\u54e8"
    ],
    "wof:name":"Songmushao",
    "wof:placetype":"locality"
},
  "geometry": {"coordinates":[125.15694000000001,49.67038],"type":"Point"}
}