{
  "type": "Feature",
  "properties": {
    "gn:admin1_code":"12",
    "gn:asciiname":"Guishan",
    "gn:country_code":"CN",
    "gn:dem":299,
    "gn:feature_class":"P",
    "gn:feature_code":"PPLA4",
    "gn:name":"Guishan",
    "gn:population":0,
    "gn:timezone":"Asia/Shanghai",
    "iso:country":"CN",
    "name:und_x_variant":[
        "Guishan Xiang",
        "\u9f9f\u5c71\u4e61"
    ],
    "name:zho_x_preferred":[
        "\u9f9f\u5c71"
    ],
    "wof:name":"Guishan",
    "wof:placetype":"locality"
},
  "geometry": {"coordinates":[115.18183999999999,31.07566],"type":"Point"}
}