{
  "type": "Feature",
  "properties": {
    "gn:admin1_code":"14.0",
    "gn:asciiname":"Naixiucun",
    "gn:country_code":"CN",
    "gn:dem":4094,
    "gn:feature_class":"P",
    "gn:feature_code":"PPL",
    "gn:name":"Naixiucun",
    "gn:population":0,
    "gn:timezone":"Asia/Urumqi",
    "iso:country":"CN",
    "name:zho_x_preferred":[
        "\u4e43\u79c0\u6751"
    ],
    "wof:name":"Naixiucun",
    "wof:placetype":"locality"
},
  "geometry": {"coordinates":[93.39158,31.53538],"type":"Point"}
}