{
  "type": "Feature",
  "properties": {
    "gn:admin1_code":"15.0",
    "gn:asciiname":"Sishen",
    "gn:country_code":"CN",
    "gn:dem":1518,
    "gn:feature_class":"P",
    "gn:feature_code":"PPL",
    "gn:name":"Sishen",
    "gn:population":0,
    "gn:timezone":"Asia/Shanghai",
    "iso:country":"CN",
    "name:zho_x_preferred":[
        "\u56db\u795e"
    ],
    "wof:name":"Sishen",
    "wof:placetype":"locality"
},
  "geometry": {"coordinates":[106.224,34.7031],"type":"Point"}
}