{
  "type": "Feature",
  "properties": {
    "gn:admin1_code":"1.0",
    "gn:asciiname":"Shangfang",
    "gn:country_code":"CN",
    "gn:dem":127,
    "gn:feature_class":"P",
    "gn:feature_code":"PPL",
    "gn:name":"Shangfang",
    "gn:population":0,
    "gn:timezone":"Asia/Shanghai",
    "iso:country":"CN",
    "name:zho_x_preferred":[
        "\u4e0a\u82b3"
    ],
    "name:zho_x_variant":[
        "\u4e0a\u65b9\u5c71\u56fd\u5bb6\u68ee\u6797\u516c\u56ed"
    ],
    "wof:name":"Shangfang",
    "wof:placetype":"locality"
},
  "geometry": {"coordinates":[118.37602,29.8783],"type":"Point"}
}