{
  "type": "Feature",
  "properties": {
    "gn:admin1_code":"10",
    "gn:asciiname":"Guandaoli",
    "gn:cc2":"CN",
    "gn:country_code":"CN",
    "gn:dem":25,
    "gn:feature_class":"P",
    "gn:feature_code":"PPL",
    "gn:name":"Guandaoli",
    "gn:population":0,
    "gn:timezone":"Asia/Shanghai",
    "iso:country":"CN",
    "name:und_x_variant":[
        "Kuan-tao-li",
        "Kuan-tao-li-chuang",
        "Guandaoli"
    ],
    "wof:name":"Guandaoli",
    "wof:placetype":"locality"
},
  "geometry": {"coordinates":[115.41667,37.68333],"type":"Point"}
}