{
  "type": "Feature",
  "properties": {
    "gn:admin1_code":"16.0",
    "gn:asciiname":"Huanjiang",
    "gn:country_code":"CN",
    "gn:dem":599,
    "gn:feature_class":"P",
    "gn:feature_code":"PPL",
    "gn:name":"Huanjiang",
    "gn:population":0,
    "gn:timezone":"Asia/Shanghai",
    "iso:country":"CN",
    "name:zho_x_preferred":[
        "\u5e7b\u6c5f"
    ],
    "wof:name":"Huanjiang",
    "wof:placetype":"locality"
},
  "geometry": {"coordinates":[107.01000000000001,23.1648],"type":"Point"}
}