{
  "type": "Feature",
  "properties": {
    "gn:admin1_code":"20.0",
    "gn:asciiname":"Ershiliuhao",
    "gn:country_code":"CN",
    "gn:dem":1067,
    "gn:feature_class":"P",
    "gn:feature_code":"PPL",
    "gn:name":"Ershiliuhao",
    "gn:population":0,
    "gn:timezone":"Asia/Shanghai",
    "iso:country":"CN",
    "name:zho_x_preferred":[
        "\u4e8c\u5341\u516d\u53f7"
    ],
    "wof:name":"Ershiliuhao",
    "wof:placetype":"locality"
},
  "geometry": {"coordinates":[100.32344999999999,41.00644000000001],"type":"Point"}
}