{
  "type": "Feature",
  "properties": {
    "gn:admin1_code":"8.0",
    "gn:asciiname":"Hefatun",
    "gn:country_code":"CN",
    "gn:dem":105,
    "gn:feature_class":"P",
    "gn:feature_code":"PPL",
    "gn:name":"Hefatun",
    "gn:population":0,
    "gn:timezone":"Asia/Shanghai",
    "iso:country":"CN",
    "name:zho_x_preferred":[
        "\u548c\u53d1\u5c6f"
    ],
    "wof:name":"Hefatun",
    "wof:placetype":"locality"
},
  "geometry": {"coordinates":[127.72944,45.90875],"type":"Point"}
}