{
  "type": "Feature",
  "properties": {
    "gn:admin1_code":"15",
    "gn:asciiname":"Mafang",
    "gn:country_code":"CN",
    "gn:dem":1732,
    "gn:feature_class":"P",
    "gn:feature_code":"PPL",
    "gn:name":"Mafang",
    "gn:population":0,
    "gn:timezone":"Asia/Shanghai",
    "iso:country":"CN",
    "wof:name":"Mafang",
    "wof:placetype":"locality"
},
  "geometry": {"coordinates":[105.72667,34.16944],"type":"Point"}
}