{
  "type": "Feature",
  "properties": {
    "gn:admin1_code":"32.0",
    "gn:asciiname":"Lianjing",
    "gn:country_code":"CN",
    "gn:dem":412,
    "gn:feature_class":"P",
    "gn:feature_code":"PPL",
    "gn:name":"Lianjing",
    "gn:population":0,
    "gn:timezone":"Asia/Shanghai",
    "iso:country":"CN",
    "name:zho_x_preferred":[
        "\u8fde\u4e95"
    ],
    "wof:name":"Lianjing",
    "wof:placetype":"locality"
},
  "geometry": {"coordinates":[106.004,31.4443],"type":"Point"}
}