{
  "type": "Feature",
  "properties": {
    "gn:admin1_code":"26.0",
    "gn:asciiname":"Matiguacun",
    "gn:country_code":"CN",
    "gn:dem":988,
    "gn:feature_class":"P",
    "gn:feature_code":"PPL",
    "gn:name":"Matiguacun",
    "gn:population":0,
    "gn:timezone":"Asia/Shanghai",
    "iso:country":"CN",
    "name:zho_x_preferred":[
        "\u9a6c\u8e44\u576c\u6751"
    ],
    "wof:name":"Matiguacun",
    "wof:placetype":"locality"
},
  "geometry": {"coordinates":[110.17279000000001,37.84648],"type":"Point"}
}