{
  "type": "Feature",
  "properties": {
    "gn:admin1_code":"9.0",
    "gn:asciiname":"Zhanggong",
    "gn:cc2":"CN",
    "gn:country_code":"CN",
    "gn:dem":56,
    "gn:feature_class":"P",
    "gn:feature_code":"PPL",
    "gn:name":"Zhanggong",
    "gn:population":0,
    "gn:timezone":"Asia/Shanghai",
    "iso:country":"CN",
    "name:und_x_variant":[
        "Chang-kung",
        "Zhanggong"
    ],
    "wof:name":"Zhanggong",
    "wof:placetype":"locality"
},
  "geometry": {"coordinates":[115.23333,34.33333],"type":"Point"}
}