{
  "type": "Feature",
  "properties": {
    "gn:admin1_code":"18",
    "gn:asciiname":"Qingkou",
    "gn:country_code":"CN",
    "gn:dem":1577,
    "gn:feature_class":"P",
    "gn:feature_code":"PPL",
    "gn:name":"Qingkou",
    "gn:population":0,
    "gn:timezone":"Asia/Shanghai",
    "iso:country":"CN",
    "wof:name":"Qingkou",
    "wof:placetype":"locality"
},
  "geometry": {"coordinates":[105.26667,26.26667],"type":"Point"}
}