{
  "type": "Feature",
  "properties": {
    "gn:admin1_code":"33.0",
    "gn:asciiname":"Changbang",
    "gn:country_code":"CN",
    "gn:dem":450,
    "gn:feature_class":"P",
    "gn:feature_code":"PPL",
    "gn:name":"Changbang",
    "gn:population":0,
    "gn:timezone":"Asia/Shanghai",
    "iso:country":"CN",
    "name:zho_x_preferred":[
        "\u957f\u585d"
    ],
    "wof:name":"Changbang",
    "wof:placetype":"locality"
},
  "geometry": {"coordinates":[108.21866,30.50694],"type":"Point"}
}