{
  "type": "Feature",
  "properties": {
    "gn:admin1_code":"3",
    "gn:asciiname":"Shimenling",
    "gn:country_code":"CN",
    "gn:dem":758,
    "gn:feature_class":"P",
    "gn:feature_code":"PPL",
    "gn:name":"Shimenling",
    "gn:population":0,
    "gn:timezone":"Asia/Shanghai",
    "iso:country":"CN",
    "name:zho_x_preferred":[
        "\u77f3\u95e8\u5cad"
    ],
    "wof:name":"Shimenling",
    "wof:placetype":"locality"
},
  "geometry": {"coordinates":[114.1305,26.39212],"type":"Point"}
}