{
  "type": "Feature",
  "properties": {
    "gn:admin1_code":"26",
    "gn:asciiname":"Machi",
    "gn:cc2":"CN",
    "gn:country_code":"CN",
    "gn:dem":377,
    "gn:feature_class":"P",
    "gn:feature_code":"PPL",
    "gn:name":"Machi",
    "gn:population":0,
    "gn:timezone":"Asia/Shanghai",
    "iso:country":"CN",
    "name:und_x_variant":[
        "Ho-ch\u2019ih",
        "Ma-ch\u2019ih",
        "Ch\u2019ih-ho",
        "Machi"
    ],
    "wof:name":"Machi",
    "wof:placetype":"locality"
},
  "geometry": {"coordinates":[108.32917,32.95167],"type":"Point"}
}