{
  "type": "Feature",
  "properties": {
    "gn:admin1_code":"33.0",
    "gn:asciiname":"Hehua",
    "gn:country_code":"CN",
    "gn:dem":430,
    "gn:feature_class":"P",
    "gn:feature_code":"PPL",
    "gn:name":"Hehua",
    "gn:population":0,
    "gn:timezone":"Asia/Shanghai",
    "iso:country":"CN",
    "name:zho_x_preferred":[
        "\u8377\u82b1"
    ],
    "wof:name":"Hehua",
    "wof:placetype":"locality"
},
  "geometry": {"coordinates":[108.01803,30.3707],"type":"Point"}
}