{
  "type": "Feature",
  "properties": {
    "gn:admin1_code":"4.0",
    "gn:asciiname":"Wanfengcun",
    "gn:country_code":"CN",
    "gn:dem":2,
    "gn:feature_class":"P",
    "gn:feature_code":"PPL",
    "gn:name":"Wanfengcun",
    "gn:population":0,
    "gn:timezone":"Asia/Shanghai",
    "iso:country":"CN",
    "name:zho_x_preferred":[
        "\u4e07\u4e30\u6751"
    ],
    "wof:name":"Wanfengcun",
    "wof:placetype":"locality"
},
  "geometry": {"coordinates":[120.51947,33.22211],"type":"Point"}
}