{
  "type": "Feature",
  "properties": {
    "gn:admin1_code":"7.0",
    "gn:asciiname":"Jinghoucun",
    "gn:country_code":"CN",
    "gn:dem":472,
    "gn:feature_class":"P",
    "gn:feature_code":"PPL",
    "gn:name":"Jinghoucun",
    "gn:population":0,
    "gn:timezone":"Asia/Shanghai",
    "iso:country":"CN",
    "name:zho_x_preferred":[
        "\u4e95\u540e\u6751"
    ],
    "wof:name":"Jinghoucun",
    "wof:placetype":"locality"
},
  "geometry": {"coordinates":[119.19465,26.3498],"type":"Point"}
}