{
  "type": "Feature",
  "properties": {
    "gn:admin1_code":"20",
    "gn:asciiname":"Shantaizi",
    "gn:country_code":"CN",
    "gn:dem":1272,
    "gn:feature_class":"P",
    "gn:feature_code":"PPLA4",
    "gn:name":"Shantaizi",
    "gn:population":0,
    "gn:timezone":"Asia/Shanghai",
    "iso:country":"CN",
    "name:und_x_variant":[
        "Shan-t\u2019ai-tzu",
        "Shantaizi",
        "\u5355\u53f0\u5b50"
    ],
    "wof:name":"Shantaizi",
    "wof:placetype":"locality"
},
  "geometry": {"coordinates":[111.45972,39.68611],"type":"Point"}
}