{
  "type": "Feature",
  "properties": {
    "gn:admin1_code":"14.0",
    "gn:asciiname":"Badui",
    "gn:country_code":"CN",
    "gn:dem":3710,
    "gn:feature_class":"P",
    "gn:feature_code":"PPL",
    "gn:name":"Badui",
    "gn:population":0,
    "gn:timezone":"Asia/Urumqi",
    "iso:country":"CN",
    "name:zho_x_preferred":[
        "\u6252\u5806"
    ],
    "wof:name":"Badui",
    "wof:placetype":"locality"
},
  "geometry": {"coordinates":[91.96951,29.24291],"type":"Point"}
}