{
  "type": "Feature",
  "properties": {
    "gn:admin1_code":"26.0",
    "gn:asciiname":"Caoyantang",
    "gn:country_code":"CN",
    "gn:dem":516,
    "gn:feature_class":"P",
    "gn:feature_code":"PPL",
    "gn:name":"Caoyantang",
    "gn:population":0,
    "gn:timezone":"Asia/Shanghai",
    "iso:country":"CN",
    "name:und_x_variant":[
        "\u8349\u5830\u5858"
    ],
    "wof:name":"Caoyantang",
    "wof:placetype":"locality"
},
  "geometry": {"coordinates":[106.96744,33.01825],"type":"Point"}
}