{
  "type": "Feature",
  "properties": {
    "gn:admin1_code":"1.0",
    "gn:asciiname":"Liantancun",
    "gn:country_code":"CN",
    "gn:dem":19,
    "gn:feature_class":"P",
    "gn:feature_code":"PPL",
    "gn:name":"Liantancun",
    "gn:population":0,
    "gn:timezone":"Asia/Shanghai",
    "iso:country":"CN",
    "name:zho_x_preferred":[
        "\u7ec3\u6f6d\u6751"
    ],
    "wof:name":"Liantancun",
    "wof:placetype":"locality"
},
  "geometry": {"coordinates":[117.00014,30.76558],"type":"Point"}
}