{
  "type": "Feature",
  "properties": {
    "gn:admin1_code":"18.0",
    "gn:asciiname":"Wangxin",
    "gn:country_code":"CN",
    "gn:dem":697,
    "gn:feature_class":"P",
    "gn:feature_code":"PPL",
    "gn:name":"Wangxin",
    "gn:population":0,
    "gn:timezone":"Asia/Shanghai",
    "iso:country":"CN",
    "name:zho_x_preferred":[
        "\u5f80\u4fe1"
    ],
    "wof:name":"Wangxin",
    "wof:placetype":"locality"
},
  "geometry": {"coordinates":[109.01300000000001,25.8917],"type":"Point"}
}