{
  "type": "Feature",
  "properties": {
    "gn:admin1_code":"14.0",
    "gn:asciiname":"Chukug",
    "gn:country_code":"CN",
    "gn:dem":4101,
    "gn:feature_class":"P",
    "gn:feature_code":"PPLF",
    "gn:name":"Chukug",
    "gn:population":0,
    "gn:timezone":"Asia/Urumqi",
    "iso:country":"CN",
    "name:bod_x_preferred":[
        "Chukug"
    ],
    "name:zho_x_preferred":[
        "Chugu"
    ],
    "name:zho_x_variant":[
        "\u695a\u53e4"
    ],
    "wof:name":"Chukug",
    "wof:placetype":"locality"
},
  "geometry": {"coordinates":[89.50200000000002,28.902],"type":"Point"}
}