{
  "type": "Feature",
  "properties": {
    "gn:admin1_code":"29.0",
    "gn:asciiname":"Dagu",
    "gn:country_code":"CN",
    "gn:dem":817,
    "gn:feature_class":"P",
    "gn:feature_code":"PPL",
    "gn:name":"Dagu",
    "gn:population":0,
    "gn:timezone":"Asia/Shanghai",
    "iso:country":"CN",
    "name:ceb_x_preferred":[
        "Dagu"
    ],
    "name:deu_x_preferred":[
        "Dagu"
    ],
    "name:swe_x_preferred":[
        "Dagu"
    ],
    "name:zho_x_preferred":[
        "\u5927\u59d1"
    ],
    "wof:name":"Dagu",
    "wof:placetype":"locality"
},
  "geometry": {"coordinates":[102.28,22.6284],"type":"Point"}
}