{
  "type": "Feature",
  "properties": {
    "gn:admin1_code":"10",
    "gn:asciiname":"Dabeiliangshang",
    "gn:country_code":"CN",
    "gn:dem":567,
    "gn:feature_class":"P",
    "gn:feature_code":"PPL",
    "gn:name":"Dabeiliangshang",
    "gn:population":0,
    "gn:timezone":"Asia/Shanghai",
    "iso:country":"CN",
    "name:zho_x_preferred":[
        "\u5927\u5317\u6881\u4e0a"
    ],
    "wof:name":"Dabeiliangshang",
    "wof:placetype":"locality"
},
  "geometry": {"coordinates":[118.19038,40.88931],"type":"Point"}
}