{
  "type": "Feature",
  "properties": {
    "gn:admin1_code":"3.0",
    "gn:asciiname":"Huangzhu Touxia",
    "gn:country_code":"CN",
    "gn:dem":83,
    "gn:feature_class":"P",
    "gn:feature_code":"PPL",
    "gn:name":"Huangzhu Touxia",
    "gn:population":0,
    "gn:timezone":"Asia/Shanghai",
    "iso:country":"CN",
    "name:und_x_variant":[
        "\u9ec4\u7af9\u5934\u4e0b"
    ],
    "wof:name":"Huangzhu Touxia",
    "wof:placetype":"locality"
},
  "geometry": {"coordinates":[114.77922,27.84673],"type":"Point"}
}