{
  "type": "Feature",
  "properties": {
    "gn:admin1_code":"7",
    "gn:asciiname":"Liangongping",
    "gn:country_code":"CN",
    "gn:dem":450,
    "gn:feature_class":"P",
    "gn:feature_code":"PPL",
    "gn:name":"Liangongping",
    "gn:population":0,
    "gn:timezone":"Asia/Shanghai",
    "iso:country":"CN",
    "name:und_x_variant":[
        "\u7ec3\u529f\u576a",
        "Liangongping"
    ],
    "wof:name":"Liangongping",
    "wof:placetype":"locality"
},
  "geometry": {"coordinates":[119.67068999999999,27.45274],"type":"Point"}
}