{
  "type": "Feature",
  "properties": {
    "gn:admin1_code":"4.0",
    "gn:asciiname":"Yongzhuang",
    "gn:country_code":"CN",
    "gn:dem":3,
    "gn:feature_class":"P",
    "gn:feature_code":"PPL",
    "gn:name":"Yongzhuang",
    "gn:population":0,
    "gn:timezone":"Asia/Shanghai",
    "iso:country":"CN",
    "name:und_x_variant":[
        "\u96cd\u5e84"
    ],
    "name:zho_x_preferred":[
        "\u96cd\u5e84"
    ],
    "wof:name":"Yongzhuang",
    "wof:placetype":"locality"
},
  "geometry": {"coordinates":[120.12452,32.98655],"type":"Point"}
}