{
  "type": "Feature",
  "properties": {
    "gn:admin1_code":"18.0",
    "gn:asciiname":"Heyang",
    "gn:country_code":"CN",
    "gn:dem":491,
    "gn:feature_class":"P",
    "gn:feature_code":"PPL",
    "gn:name":"Heyang",
    "gn:population":0,
    "gn:timezone":"Asia/Shanghai",
    "iso:country":"CN",
    "name:ceb_x_preferred":[
        "Heyang"
    ],
    "name:zho_x_preferred":[
        "\u5408\u9633"
    ],
    "wof:name":"Heyang",
    "wof:placetype":"locality"
},
  "geometry": {"coordinates":[109.23699999999999,27.1052],"type":"Point"}
}