{
  "type": "Feature",
  "properties": {
    "gn:admin1_code":"24.0",
    "gn:asciiname":"Sunjiazhuocun",
    "gn:country_code":"CN",
    "gn:dem":398,
    "gn:feature_class":"P",
    "gn:feature_code":"PPL",
    "gn:name":"Sunjiazhuocun",
    "gn:population":0,
    "gn:timezone":"Asia/Shanghai",
    "iso:country":"CN",
    "name:zho_x_preferred":[
        "\u5b59\u5bb6\u5353\u6751"
    ],
    "wof:name":"Sunjiazhuocun",
    "wof:placetype":"locality"
},
  "geometry": {"coordinates":[110.83539,35.15739],"type":"Point"}
}