{
  "type": "Feature",
  "properties": {
    "gn:admin1_code":"25",
    "gn:asciiname":"Weijiajishan",
    "gn:country_code":"CN",
    "gn:dem":173,
    "gn:feature_class":"P",
    "gn:feature_code":"PPL",
    "gn:name":"Weijiajishan",
    "gn:population":0,
    "gn:timezone":"Asia/Shanghai",
    "iso:country":"CN",
    "name:zho_x_preferred":[
        "\u9b4f\u5bb6\u9e21\u5c71"
    ],
    "wof:name":"Weijiajishan",
    "wof:placetype":"locality"
},
  "geometry": {"coordinates":[118.93000000000001,35.3195],"type":"Point"}
}