{
  "type": "Feature",
  "properties": {
    "gn:admin1_code":"32.0",
    "gn:asciiname":"Zhuganwo",
    "gn:country_code":"CN",
    "gn:dem":2056,
    "gn:feature_class":"P",
    "gn:feature_code":"PPL",
    "gn:name":"Zhuganwo",
    "gn:population":0,
    "gn:timezone":"Asia/Shanghai",
    "iso:country":"CN",
    "name:zho_x_preferred":[
        "\u7af9\u6746\u7a9d"
    ],
    "wof:name":"Zhuganwo",
    "wof:placetype":"locality"
},
  "geometry": {"coordinates":[103.351,28.362],"type":"Point"}
}