{
  "type": "Feature",
  "properties": {
    "gn:admin1_code":"26",
    "gn:asciiname":"Wahutong",
    "gn:country_code":"CN",
    "gn:dem":443,
    "gn:feature_class":"P",
    "gn:feature_code":"PPL",
    "gn:name":"Wahutong",
    "gn:population":0,
    "gn:timezone":"Asia/Shanghai",
    "iso:country":"CN",
    "name:zho_x_preferred":[
        "\u74e6\u80e1\u540c"
    ],
    "wof:name":"Wahutong",
    "wof:placetype":"locality"
},
  "geometry": {"coordinates":[108.94544,34.19115],"type":"Point"}
}