{
  "type": "Feature",
  "properties": {
    "gn:admin1_code":"14",
    "gn:asciiname":"Shengji",
    "gn:country_code":"CN",
    "gn:dem":4274,
    "gn:feature_class":"P",
    "gn:feature_code":"PPL",
    "gn:name":"Shengji",
    "gn:population":0,
    "gn:timezone":"Asia/Urumqi",
    "iso:country":"CN",
    "name:zho_x_preferred":[
        "\u751f\u57fa"
    ],
    "wof:name":"Shengji",
    "wof:placetype":"locality"
},
  "geometry": {"coordinates":[89.0264,29.5306],"type":"Point"}
}