{
  "type": "Feature",
  "properties": {
    "gn:admin1_code":"30.0",
    "gn:asciiname":"Huicheng",
    "gn:country_code":"CN",
    "gn:dem":19,
    "gn:feature_class":"P",
    "gn:feature_code":"PPLA4",
    "gn:name":"Huicheng",
    "gn:population":0,
    "gn:timezone":"Asia/Shanghai",
    "iso:country":"CN",
    "name:und_x_variant":[
        "Huicheng Jiedao",
        "\u4f1a\u57ce\u8857\u9053"
    ],
    "name:zho_x_preferred":[
        "\u4f1a\u57ce"
    ],
    "wof:name":"Huicheng",
    "wof:placetype":"locality"
},
  "geometry": {"coordinates":[113.02985,22.52625],"type":"Point"}
}