{
  "type": "Feature",
  "properties": {
    "gn:admin1_code":"25.0",
    "gn:asciiname":"Wuning",
    "gn:country_code":"CN",
    "gn:dem":18,
    "gn:feature_class":"P",
    "gn:feature_code":"PPLA4",
    "gn:name":"Wuning",
    "gn:population":0,
    "gn:timezone":"Asia/Shanghai",
    "iso:country":"CN",
    "name:und_x_variant":[
        "Wuning Zhen"
    ],
    "name:zho_x_preferred":[
        "\u6b66\u5b81"
    ],
    "name:zho_x_variant":[
        "\u6b66\u5b81\u9547"
    ],
    "wof:name":"Wuning",
    "wof:placetype":"locality"
},
  "geometry": {"coordinates":[121.55637,37.36825],"type":"Point"}
}