{
  "type": "Feature",
  "properties": {
    "gn:admin1_code":"14.0",
    "gn:asciiname":"Lamutun",
    "gn:country_code":"CN",
    "gn:dem":4426,
    "gn:feature_class":"P",
    "gn:feature_code":"PPL",
    "gn:name":"Lamutun",
    "gn:population":0,
    "gn:timezone":"Asia/Urumqi",
    "iso:country":"CN",
    "name:zho_x_preferred":[
        "\u62c9\u6728\u5c6f"
    ],
    "wof:name":"Lamutun",
    "wof:placetype":"locality"
},
  "geometry": {"coordinates":[86.9618,28.4215],"type":"Point"}
}