{
  "type": "Feature",
  "properties": {
    "gn:admin1_code":"24.0",
    "gn:asciiname":"Budaigou",
    "gn:country_code":"CN",
    "gn:dem":1601,
    "gn:feature_class":"P",
    "gn:feature_code":"PPL",
    "gn:name":"Budaigou",
    "gn:population":0,
    "gn:timezone":"Asia/Shanghai",
    "iso:country":"CN",
    "name:zho_x_preferred":[
        "\u5e03\u888b\u6c9f"
    ],
    "wof:name":"Budaigou",
    "wof:placetype":"locality"
},
  "geometry": {"coordinates":[112.10207,38.38407],"type":"Point"}
}