{
  "type": "Feature",
  "properties": {
    "gn:admin1_code":"07",
    "gn:asciiname":"Yuhu",
    "gn:country_code":"CN",
    "gn:dem":20,
    "gn:feature_class":"P",
    "gn:feature_code":"PPL",
    "gn:name":"Yuhu",
    "gn:population":0,
    "gn:timezone":"Asia/Shanghai",
    "iso:country":"CN",
    "name:und_x_variant":[
        "Yanwei"
    ],
    "name:zho_x_preferred":[
        "\u7389\u6e56"
    ],
    "name:zho_x_variant":[
        "\u5830\u5c3e"
    ],
    "wof:name":"Yuhu",
    "wof:placetype":"locality"
},
  "geometry": {"coordinates":[118.45874000000001,25.00886],"type":"Point"}
}