{
  "type": "Feature",
  "properties": {
    "gn:admin1_code":"19.0",
    "gn:asciiname":"Yingtaogou",
    "gn:country_code":"CN",
    "gn:dem":331,
    "gn:feature_class":"P",
    "gn:feature_code":"PPL",
    "gn:name":"Yingtaogou",
    "gn:population":0,
    "gn:timezone":"Asia/Shanghai",
    "iso:country":"CN",
    "name:und_x_variant":[
        "\u6a31\u6843\u6c9f"
    ],
    "name:zho_x_preferred":[
        "\u6a31\u6843\u6c9f"
    ],
    "wof:name":"Yingtaogou",
    "wof:placetype":"locality"
},
  "geometry": {"coordinates":[121.21532000000001,41.83526],"type":"Point"}
}