{
  "type": "Feature",
  "properties": {
    "gn:admin1_code":"16.0",
    "gn:asciiname":"Deqing",
    "gn:country_code":"CN",
    "gn:dem":179,
    "gn:feature_class":"P",
    "gn:feature_code":"PPL",
    "gn:name":"Deqing",
    "gn:population":0,
    "gn:timezone":"Asia/Shanghai",
    "iso:country":"CN",
    "name:ceb_x_preferred":[
        "Deqing"
    ],
    "name:deu_x_preferred":[
        "Deqing"
    ],
    "name:fra_x_preferred":[
        "Deqing"
    ],
    "name:ita_x_preferred":[
        "Deqing"
    ],
    "name:kor_x_preferred":[
        "\ub354\uce6d\ud604"
    ],
    "name:mlg_x_preferred":[
        "Deqing"
    ],
    "name:nor_x_preferred":[
        "Deqing"
    ],
    "name:swe_x_preferred":[
        "Deqing"
    ],
    "name:zho_x_preferred":[
        "\u5fb7\u5e86"
    ],
    "wof:name":"Deqing",
    "wof:placetype":"locality"
},
  "geometry": {"coordinates":[110.32899999999999,24.4172],"type":"Point"}
}