{
  "type": "Feature",
  "properties": {
    "gn:admin1_code":"02",
    "gn:asciiname":"Chidicun",
    "gn:country_code":"CN",
    "gn:dem":8,
    "gn:feature_class":"P",
    "gn:feature_code":"PPL",
    "gn:name":"Chidicun",
    "gn:population":0,
    "gn:timezone":"Asia/Shanghai",
    "iso:country":"CN",
    "name:und_x_variant":[
        "Chidi",
        "Chidicun"
    ],
    "name:zho_x_preferred":[
        "Ch\u2019ih-ti"
    ],
    "name:zho_x_variant":[
        "\u6c60\u5e95",
        "\u6c60\u5e95\u6751"
    ],
    "wof:name":"Chidicun",
    "wof:placetype":"locality"
},
  "geometry": {"coordinates":[120.69732999999999,27.94849],"type":"Point"}
}