{
  "type": "Feature",
  "properties": {
    "gn:admin1_code":"30.0",
    "gn:asciiname":"Baifengshan",
    "gn:country_code":"CN",
    "gn:dem":900,
    "gn:feature_class":"P",
    "gn:feature_code":"PPL",
    "gn:name":"Baifengshan",
    "gn:population":0,
    "gn:timezone":"Asia/Shanghai",
    "iso:country":"CN",
    "name:zho_x_preferred":[
        "\u767d\u5cf0\u5c71"
    ],
    "wof:name":"Baifengshan",
    "wof:placetype":"locality"
},
  "geometry": {"coordinates":[113.9592,24.80411],"type":"Point"}
}