{
  "type": "Feature",
  "properties": {
    "gn:admin1_code":"24.0",
    "gn:asciiname":"Shangshicha",
    "gn:country_code":"CN",
    "gn:dem":1577,
    "gn:feature_class":"P",
    "gn:feature_code":"PPL",
    "gn:name":"Shangshicha",
    "gn:population":0,
    "gn:timezone":"Asia/Shanghai",
    "iso:country":"CN",
    "name:zho_x_preferred":[
        "\u4e0a\u77f3\u5c94"
    ],
    "wof:name":"Shangshicha",
    "wof:placetype":"locality"
},
  "geometry": {"coordinates":[112.7473,39.84077],"type":"Point"}
}