{
  "type": "Feature",
  "properties": {
    "gn:admin1_code":"29.0",
    "gn:asciiname":"Chazhiluo",
    "gn:country_code":"CN",
    "gn:dem":2633,
    "gn:feature_class":"P",
    "gn:feature_code":"PPL",
    "gn:name":"Chazhiluo",
    "gn:population":0,
    "gn:timezone":"Asia/Shanghai",
    "iso:country":"CN",
    "name:zho_x_preferred":[
        "\u5dee\u679d\u843d"
    ],
    "wof:name":"Chazhiluo",
    "wof:placetype":"locality"
},
  "geometry": {"coordinates":[99.8677,26.7646],"type":"Point"}
}