{
  "type": "Feature",
  "properties": {
    "gn:admin1_code":"29.0",
    "gn:asciiname":"Hualinshanjiao",
    "gn:country_code":"CN",
    "gn:dem":2002,
    "gn:feature_class":"P",
    "gn:feature_code":"PPL",
    "gn:name":"Hualinshanjiao",
    "gn:population":0,
    "gn:timezone":"Asia/Shanghai",
    "iso:country":"CN",
    "name:zho_x_preferred":[
        "\u82b1\u6797\u5c71\u811a"
    ],
    "wof:name":"Hualinshanjiao",
    "wof:placetype":"locality"
},
  "geometry": {"coordinates":[98.53,25.659],"type":"Point"}
}