{
  "type": "Feature",
  "properties": {
    "gn:admin1_code":"25",
    "gn:asciiname":"Tuquan",
    "gn:country_code":"CN",
    "gn:dem":170,
    "gn:feature_class":"P",
    "gn:feature_code":"PPL",
    "gn:name":"Tuquan",
    "gn:population":0,
    "gn:timezone":"Asia/Shanghai",
    "iso:country":"CN",
    "name:zho_x_preferred":[
        "\u7a81\u6cc9"
    ],
    "wof:name":"Tuquan",
    "wof:placetype":"locality"
},
  "geometry": {"coordinates":[117.066,36.4535],"type":"Point"}
}