{
  "type": "Feature",
  "properties": {
    "gn:admin1_code":"12",
    "gn:asciiname":"Daxiakou",
    "gn:cc2":"CN",
    "gn:country_code":"CN",
    "gn:dem":339,
    "gn:feature_class":"P",
    "gn:feature_code":"PPL",
    "gn:name":"Daxiakou",
    "gn:population":0,
    "gn:timezone":"Asia/Shanghai",
    "iso:country":"CN",
    "name:und_x_variant":[
        "Ta-hsia-k\u2019ou-shih",
        "Ta-hsia-k\u2019ou",
        "Daxiakou"
    ],
    "wof:name":"Daxiakou",
    "wof:placetype":"locality"
},
  "geometry": {"coordinates":[110.78333000000001,31.13333],"type":"Point"}
}