{
  "type": "Feature",
  "properties": {
    "gn:admin1_code":"18",
    "gn:asciiname":"Jiangsi",
    "gn:cc2":"CN",
    "gn:country_code":"CN",
    "gn:dem":537,
    "gn:feature_class":"P",
    "gn:feature_code":"PPL",
    "gn:name":"Jiangsi",
    "gn:population":0,
    "gn:timezone":"Asia/Shanghai",
    "iso:country":"CN",
    "name:und_x_variant":[
        "Tehkiang",
        "Dejiang",
        "Te-chiang",
        "Anhwahsien",
        "Te-chiang-hsien",
        "An-hua",
        "Jiangsi"
    ],
    "wof:name":"Jiangsi",
    "wof:placetype":"locality"
},
  "geometry": {"coordinates":[108.11694,28.26861],"type":"Point"}
}