{
  "type": "Feature",
  "properties": {
    "gn:admin1_code":"8.0",
    "gn:asciiname":"Zhouhuamatun",
    "gn:country_code":"CN",
    "gn:dem":216,
    "gn:feature_class":"P",
    "gn:feature_code":"PPL",
    "gn:name":"Zhouhuamatun",
    "gn:population":0,
    "gn:timezone":"Asia/Shanghai",
    "iso:country":"CN",
    "name:zho_x_preferred":[
        "\u5468\u82b1\u9a6c\u5c6f"
    ],
    "wof:name":"Zhouhuamatun",
    "wof:placetype":"locality"
},
  "geometry": {"coordinates":[126.77222999999999,47.63923],"type":"Point"}
}