{
  "type": "Feature",
  "properties": {
    "gn:admin1_code":"02",
    "gn:asciiname":"Dachen",
    "gn:country_code":"CN",
    "gn:dem":68,
    "gn:feature_class":"P",
    "gn:feature_code":"PPLA4",
    "gn:name":"Dachen",
    "gn:population":0,
    "gn:timezone":"Asia/Shanghai",
    "iso:country":"CN",
    "name:und_x_variant":[
        "Ta-ch\u2019en",
        "Ta-ch\u2019en-shih",
        "Dachen",
        "Dachen Zhen"
    ],
    "name:zho_x_preferred":[
        "\u5927\u9648"
    ],
    "name:zho_x_variant":[
        "\u5927\u9648\u9547"
    ],
    "wof:name":"Dachen",
    "wof:placetype":"locality"
},
  "geometry": {"coordinates":[120.12527,29.4521],"type":"Point"}
}