{
  "type": "Feature",
  "properties": {
    "gn:admin1_code":"18",
    "gn:asciiname":"Xuanyan",
    "gn:country_code":"CN",
    "gn:dem":866,
    "gn:feature_class":"P",
    "gn:feature_code":"PPL",
    "gn:name":"Xuanyan",
    "gn:population":0,
    "gn:timezone":"Asia/Shanghai",
    "iso:country":"CN",
    "name:zho_x_preferred":[
        "\u60ac\u5ca9"
    ],
    "wof:name":"Xuanyan",
    "wof:placetype":"locality"
},
  "geometry": {"coordinates":[105.959,28.6437],"type":"Point"}
}