{
  "type": "Feature",
  "properties": {
    "gn:admin1_code":"32.0",
    "gn:asciiname":"Sanpuzi",
    "gn:country_code":"CN",
    "gn:dem":2246,
    "gn:feature_class":"P",
    "gn:feature_code":"PPL",
    "gn:name":"Sanpuzi",
    "gn:population":0,
    "gn:timezone":"Asia/Shanghai",
    "iso:country":"CN",
    "name:zho_x_preferred":[
        "\u4e09\u666e\u5b50"
    ],
    "wof:name":"Sanpuzi",
    "wof:placetype":"locality"
},
  "geometry": {"coordinates":[102.2877,28.26422],"type":"Point"}
}