{
  "type": "Feature",
  "properties": {
    "gn:admin1_code":"12",
    "gn:asciiname":"Yaoxin",
    "gn:cc2":"CN",
    "gn:country_code":"CN",
    "gn:dem":38,
    "gn:feature_class":"P",
    "gn:feature_code":"PPL",
    "gn:name":"Yaoxin",
    "gn:population":0,
    "gn:timezone":"Asia/Shanghai",
    "iso:country":"CN",
    "name:und_x_variant":[
        "Yao-hsing-ch\u2019ang",
        "Yaoxin"
    ],
    "wof:name":"Yaoxin",
    "wof:placetype":"locality"
},
  "geometry": {"coordinates":[112.21639,30.13],"type":"Point"}
}