{
  "type": "Feature",
  "properties": {
    "gn:admin1_code":"16.0",
    "gn:asciiname":"Xiadili",
    "gn:country_code":"CN",
    "gn:dem":132,
    "gn:feature_class":"P",
    "gn:feature_code":"PPL",
    "gn:name":"Xiadili",
    "gn:population":0,
    "gn:timezone":"Asia/Shanghai",
    "iso:country":"CN",
    "name:zho_x_preferred":[
        "\u4e0b\u5730\u7406"
    ],
    "wof:name":"Xiadili",
    "wof:placetype":"locality"
},
  "geometry": {"coordinates":[108.94799999999999,24.9531],"type":"Point"}
}