{
  "type": "Feature",
  "properties": {
    "gn:admin1_code":"26.0",
    "gn:asciiname":"Miaoping",
    "gn:country_code":"CN",
    "gn:dem":1839,
    "gn:feature_class":"P",
    "gn:feature_code":"PPL",
    "gn:name":"Miaoping",
    "gn:population":0,
    "gn:timezone":"Asia/Shanghai",
    "iso:country":"CN",
    "name:und_x_variant":[
        "\u5e99\u576a"
    ],
    "wof:name":"Miaoping",
    "wof:placetype":"locality"
},
  "geometry": {"coordinates":[106.67167000000001,33.64703],"type":"Point"}
}