{
  "type": "Feature",
  "properties": {
    "gn:admin1_code":"32.0",
    "gn:asciiname":"Wuguidang",
    "gn:country_code":"CN",
    "gn:dem":385,
    "gn:feature_class":"P",
    "gn:feature_code":"PPL",
    "gn:name":"Wuguidang",
    "gn:population":0,
    "gn:timezone":"Asia/Shanghai",
    "iso:country":"CN",
    "name:zho_x_preferred":[
        "\u4e4c\u9f9f\u51fc"
    ],
    "wof:name":"Wuguidang",
    "wof:placetype":"locality"
},
  "geometry": {"coordinates":[104.70291,29.8746],"type":"Point"}
}