{
  "type": "Feature",
  "properties": {
    "gn:admin1_code":"16.0",
    "gn:asciiname":"Gengma",
    "gn:country_code":"CN",
    "gn:dem":551,
    "gn:feature_class":"P",
    "gn:feature_code":"PPL",
    "gn:name":"Gengma",
    "gn:population":0,
    "gn:timezone":"Asia/Shanghai",
    "iso:country":"CN",
    "name:zho_x_preferred":[
        "\u57c2\u9a6c"
    ],
    "wof:name":"Gengma",
    "wof:placetype":"locality"
},
  "geometry": {"coordinates":[106.89,23.0472],"type":"Point"}
}