{
  "type": "Feature",
  "properties": {
    "gn:admin1_code":"4.0",
    "gn:asciiname":"Baishitou",
    "gn:country_code":"CN",
    "gn:dem":51,
    "gn:feature_class":"P",
    "gn:feature_code":"PPL",
    "gn:name":"Baishitou",
    "gn:population":0,
    "gn:timezone":"Asia/Shanghai",
    "iso:country":"CN",
    "name:und_x_variant":[
        "\u767d\u77f3\u5934"
    ],
    "wof:name":"Baishitou",
    "wof:placetype":"locality"
},
  "geometry": {"coordinates":[118.47832,34.6471],"type":"Point"}
}