{
  "type": "Feature",
  "properties": {
    "gn:admin1_code":"14.0",
    "gn:asciiname":"Ri'nga",
    "gn:country_code":"CN",
    "gn:dem":4025,
    "gn:feature_class":"P",
    "gn:feature_code":"PPL",
    "gn:name":"Ri\u2019nga",
    "gn:population":0,
    "gn:timezone":"Asia/Urumqi",
    "iso:country":"CN",
    "name:bod_x_preferred":[
        "Ri\u2019nga"
    ],
    "name:zho_x_preferred":[
        "Ren\u2019a"
    ],
    "name:zho_x_variant":[
        "\u4ec1\u963f",
        "Dejilin Gongshe",
        "\u5fb7\u5409\u6797\u516c\u793e"
    ],
    "wof:name":"Ri'nga",
    "wof:placetype":"locality"
},
  "geometry": {"coordinates":[89.90299999999998,29.20300000000001],"type":"Point"}
}