{
  "type": "Feature",
  "properties": {
    "gn:admin1_code":"32.0",
    "gn:asciiname":"Xinminchang",
    "gn:country_code":"CN",
    "gn:dem":579,
    "gn:feature_class":"P",
    "gn:feature_code":"PPL",
    "gn:name":"Xinminchang",
    "gn:population":0,
    "gn:timezone":"Asia/Shanghai",
    "iso:country":"CN",
    "name:zho_x_preferred":[
        "\u65b0\u6c11\u573a"
    ],
    "wof:name":"Xinminchang",
    "wof:placetype":"locality"
},
  "geometry": {"coordinates":[103.85947,30.88304],"type":"Point"}
}