{
  "type": "Feature",
  "properties": {
    "gn:admin1_code":"31.0",
    "gn:asciiname":"Changjiao",
    "gn:country_code":"CN",
    "gn:dem":44,
    "gn:feature_class":"P",
    "gn:feature_code":"PPL",
    "gn:name":"Changjiao",
    "gn:population":0,
    "gn:timezone":"Asia/Shanghai",
    "iso:country":"CN",
    "name:und_x_variant":[
        "\u957f\u89d2"
    ],
    "wof:name":"Changjiao",
    "wof:placetype":"locality"
},
  "geometry": {"coordinates":[109.97575000000001,18.58719],"type":"Point"}
}