{
  "type": "Feature",
  "properties": {
    "gn:admin1_code":"01",
    "gn:asciiname":"Daying",
    "gn:country_code":"CN",
    "gn:dem":11,
    "gn:feature_class":"P",
    "gn:feature_code":"PPLA4",
    "gn:name":"Daying",
    "gn:population":0,
    "gn:timezone":"Asia/Shanghai",
    "iso:country":"CN",
    "name:und_x_variant":[
        "Ta-ying",
        "Dayingji",
        "Ta-ying-chi",
        "Daying",
        "Daying Zhen"
    ],
    "name:zho_x_preferred":[
        "\u5927\u82f1"
    ],
    "name:zho_x_variant":[
        "\u5927\u82f1\u9547"
    ],
    "wof:name":"Daying",
    "wof:placetype":"locality"
},
  "geometry": {"coordinates":[118.60120999999999,32.30268],"type":"Point"}
}