{
  "type": "Feature",
  "properties": {
    "gn:admin1_code":"6.0",
    "gn:asciiname":"Dongzhuan",
    "gn:country_code":"CN",
    "gn:dem":4058,
    "gn:feature_class":"P",
    "gn:feature_code":"PPL",
    "gn:name":"Dongzhuan",
    "gn:population":0,
    "gn:timezone":"Asia/Shanghai",
    "iso:country":"CN",
    "name:zho_x_preferred":[
        "\u680b\u4e13"
    ],
    "wof:name":"Dongzhuan",
    "wof:placetype":"locality"
},
  "geometry": {"coordinates":[100.02692,33.05795999999999],"type":"Point"}
}