{
  "type": "Feature",
  "properties": {
    "gn:admin1_code":"32.0",
    "gn:asciiname":"Zhaiziding",
    "gn:country_code":"CN",
    "gn:dem":697,
    "gn:feature_class":"P",
    "gn:feature_code":"PPL",
    "gn:name":"Zhaiziding",
    "gn:population":0,
    "gn:timezone":"Asia/Shanghai",
    "iso:country":"CN",
    "name:zho_x_preferred":[
        "\u5be8\u5b50\u9876"
    ],
    "wof:name":"Zhaiziding",
    "wof:placetype":"locality"
},
  "geometry": {"coordinates":[104.60799,28.23123],"type":"Point"}
}