{
  "type": "Feature",
  "properties": {
    "gn:admin1_code":"11.0",
    "gn:asciiname":"Yanglinwan",
    "gn:country_code":"CN",
    "gn:dem":308,
    "gn:feature_class":"P",
    "gn:feature_code":"PPL",
    "gn:name":"Yanglinwan",
    "gn:population":0,
    "gn:timezone":"Asia/Shanghai",
    "iso:country":"CN",
    "name:zho_x_preferred":[
        "\u9633\u6797\u6e7e"
    ],
    "wof:name":"Yanglinwan",
    "wof:placetype":"locality"
},
  "geometry": {"coordinates":[110.89641,27.20238],"type":"Point"}
}