{
  "type": "Feature",
  "properties": {
    "gn:admin1_code":"32",
    "gn:asciiname":"Ganai",
    "gn:country_code":"CN",
    "gn:dem":2929,
    "gn:feature_class":"P",
    "gn:feature_code":"PPL",
    "gn:name":"Ganai",
    "gn:population":0,
    "gn:timezone":"Asia/Shanghai",
    "iso:country":"CN",
    "wof:name":"Ganai",
    "wof:placetype":"locality"
},
  "geometry": {"coordinates":[101.53333000000001,31.81667],"type":"Point"}
}