{
  "type": "Feature",
  "properties": {
    "gn:admin1_code":"14.0",
    "gn:asciiname":"Xoglung",
    "gn:country_code":"CN",
    "gn:dem":4055,
    "gn:feature_class":"P",
    "gn:feature_code":"PPLF",
    "gn:name":"Xoglung",
    "gn:population":0,
    "gn:timezone":"Asia/Urumqi",
    "iso:country":"CN",
    "name:bod_x_preferred":[
        "Xoglung"
    ],
    "name:zho_x_preferred":[
        "Xuelong"
    ],
    "name:zho_x_variant":[
        "\u5b66\u9f99"
    ],
    "wof:name":"Xoglung",
    "wof:placetype":"locality"
},
  "geometry": {"coordinates":[97.92364000000001,30.46098],"type":"Point"}
}