{
  "type": "Feature",
  "properties": {
    "gn:admin1_code":"33.0",
    "gn:asciiname":"Xindian",
    "gn:country_code":"CN",
    "gn:dem":1060,
    "gn:feature_class":"P",
    "gn:feature_code":"PPL",
    "gn:name":"Xindian",
    "gn:population":0,
    "gn:timezone":"Asia/Shanghai",
    "iso:country":"CN",
    "name:ceb_x_preferred":[
        "Xindian"
    ],
    "name:deu_x_preferred":[
        "Xindian"
    ],
    "name:swe_x_preferred":[
        "Xindian"
    ],
    "name:zho_x_preferred":[
        "\u65b0\u5e97"
    ],
    "wof:name":"Xindian",
    "wof:placetype":"locality"
},
  "geometry": {"coordinates":[108.6324,31.44572],"type":"Point"}
}