{
  "type": "Feature",
  "properties": {
    "gn:admin1_code":"4.0",
    "gn:asciiname":"Qingquancun",
    "gn:country_code":"CN",
    "gn:dem":2,
    "gn:feature_class":"P",
    "gn:feature_code":"PPL",
    "gn:name":"Qingquancun",
    "gn:population":0,
    "gn:timezone":"Asia/Shanghai",
    "iso:country":"CN",
    "name:zho_x_preferred":[
        "\u6e05\u6cc9\u6751"
    ],
    "wof:name":"Qingquancun",
    "wof:placetype":"locality"
},
  "geometry": {"coordinates":[119.45569,34.09253],"type":"Point"}
}