{
  "type": "Feature",
  "properties": {
    "gn:admin1_code":"32.0",
    "gn:asciiname":"Lianghekou",
    "gn:country_code":"CN",
    "gn:dem":1291,
    "gn:feature_class":"P",
    "gn:feature_code":"PPL",
    "gn:name":"Lianghekou",
    "gn:population":0,
    "gn:timezone":"Asia/Shanghai",
    "iso:country":"CN",
    "name:zho_x_preferred":[
        "\u4e24\u6cb3\u53e3"
    ],
    "wof:name":"Lianghekou",
    "wof:placetype":"locality"
},
  "geometry": {"coordinates":[104.62062,32.17346],"type":"Point"}
}