{
  "type": "Feature",
  "properties": {
    "gn:admin1_code":"3.0",
    "gn:asciiname":"Zhujia Tangli",
    "gn:country_code":"CN",
    "gn:dem":163,
    "gn:feature_class":"P",
    "gn:feature_code":"PPL",
    "gn:name":"Zhujia Tangli",
    "gn:population":0,
    "gn:timezone":"Asia/Shanghai",
    "iso:country":"CN",
    "name:zho_x_preferred":[
        "\u6731\u5bb6\u5858\u91cc"
    ],
    "wof:name":"Zhujia Tangli",
    "wof:placetype":"locality"
},
  "geometry": {"coordinates":[118.29353,28.44924],"type":"Point"}
}