{
  "type": "Feature",
  "properties": {
    "gn:admin1_code":"8.0",
    "gn:asciiname":"Zhusancun",
    "gn:country_code":"CN",
    "gn:dem":140,
    "gn:feature_class":"P",
    "gn:feature_code":"PPL",
    "gn:name":"Zhusancun",
    "gn:population":0,
    "gn:timezone":"Asia/Shanghai",
    "iso:country":"CN",
    "name:zho_x_preferred":[
        "\u795d\u4e09\u6751"
    ],
    "wof:name":"Zhusancun",
    "wof:placetype":"locality"
},
  "geometry": {"coordinates":[125.00216,45.9442],"type":"Point"}
}