{
  "type": "Feature",
  "properties": {
    "gn:admin1_code":"16.0",
    "gn:asciiname":"Bengtang",
    "gn:country_code":"CN",
    "gn:dem":14,
    "gn:feature_class":"P",
    "gn:feature_code":"PPL",
    "gn:name":"Bengtang",
    "gn:population":0,
    "gn:timezone":"Asia/Shanghai",
    "iso:country":"CN",
    "name:zho_x_preferred":[
        "\u5d29\u5858"
    ],
    "wof:name":"Bengtang",
    "wof:placetype":"locality"
},
  "geometry": {"coordinates":[109.71299999999999,21.6139],"type":"Point"}
}