{
  "type": "Feature",
  "properties": {
    "gn:admin1_code":"26",
    "gn:asciiname":"Nanlijie",
    "gn:country_code":"CN",
    "gn:dem":443,
    "gn:feature_class":"P",
    "gn:feature_code":"PPL",
    "gn:name":"Nanlijie",
    "gn:population":0,
    "gn:timezone":"Asia/Shanghai",
    "iso:country":"CN",
    "name:zho_x_preferred":[
        "\u5357\u7acb\u8282"
    ],
    "wof:name":"Nanlijie",
    "wof:placetype":"locality"
},
  "geometry": {"coordinates":[108.14687000000001,34.23723],"type":"Point"}
}