{
  "type": "Feature",
  "properties": {
    "gn:admin1_code":"19",
    "gn:asciiname":"Tianshifu",
    "gn:country_code":"CN",
    "gn:dem":285,
    "gn:feature_class":"P",
    "gn:feature_code":"PPLA4",
    "gn:name":"Tianshifu",
    "gn:population":0,
    "gn:timezone":"Asia/Shanghai",
    "iso:country":"CN",
    "name:und_x_variant":[
        "T\u2019ien-shih-fu-kow",
        "T\u2019ien-shih-fu-ku-k\u2019ou",
        "Tien-shi-fu",
        "T\u2019ien-shih-fu-kou",
        "T\u2019ien-shih-fu-kou-k\u2019ou",
        "T\u2019ien-tzu-fu-kou-k\u2019ou",
        "T\u2019ien-shih-fu",
        "T\u2019ien-tzu-fu",
        "Tianshifu",
        "\u7530\u5e08\u4ed8",
        "Tianshifu Zhen",
        "Dapu",
        "\u7530\u5e08\u4ed8\u9547",
        "\u5927\u5821"
    ],
    "name:zho_x_preferred":[
        "\u7530\u5e08\u5085\u9547"
    ],
    "wof:name":"Tianshifu",
    "wof:placetype":"locality"
},
  "geometry": {"coordinates":[124.35312999999999,41.25563],"type":"Point"}
}