{
  "type": "Feature",
  "properties": {
    "gn:country":"CN",
    "gn:fcode":"PPL",
    "gn:pop":0,
    "iso:country":"CN",
    "name:uig_x_preferred":[
        "Yengix\u0259h\u0328\u0259r"
    ],
    "name:uig_x_variant":[
        "Y\u00e9ngisheher",
        "\u064a\u06d0\u06ad\u0649\u0634\u06d5\u06be\u06d5\u0631",
        "\u0415\u04a3\u0438\u0448\u04d9\u04bb\u04d9\u0440"
    ],
    "name:unk_x_variant":[
        "Su-lo"
    ],
    "name:zho_x_preferred":[
        "\u758f\u52d2"
    ],
    "qs:name":"\u758f\u52d2",
    "qs:name_adm0":"\u4e2d\u570b",
    "qs:name_adm1":"\u65b0\u7586\u7ef4\u543e\u5c14\u81ea\u6cbb\u533a",
    "qs:photos":12,
    "qs:photos_1k":2,
    "qs:photos_9k":1,
    "qs:photos_9r":1,
    "qs:photos_all":12,
    "qs:photos_sr":1,
    "qs:placetype":"Town",
    "qs:pop_sr":"6",
    "wd:wordcount":85,
    "wof:name":"\u758f\u52d2",
    "wof:placetype":"locality",
    "wof:population":0
},
  "geometry": {"coordinates":[76.04000000000001,39.39139],"type":"Point"}
}