{
  "type": "Feature",
  "properties": {
    "gn:country":"CN",
    "gn:fcode":"PPL",
    "gn:population":0,
    "iso:country":"CN",
    "name:ara_x_preferred":[
        "\u0645\u0642\u0627\u0637\u0639\u0629 \u0634\u0648\u0644"
    ],
    "name:deu_x_preferred":[
        "Shule"
    ],
    "name:eng_x_preferred":[
        "Shule County"
    ],
    "name:epo_x_preferred":[
        "Shule"
    ],
    "name:fas_x_preferred":[
        "\u0634\u0647\u0631\u0633\u062a\u0627\u0646 \u0634\u0648\u0644\u0647"
    ],
    "name:fin_x_preferred":[
        "Shule"
    ],
    "name:gan_x_preferred":[
        "\u758f\u52d2\u53bf"
    ],
    "name:jpn_x_preferred":[
        "\u758f\u52d2\u770c"
    ],
    "name:kor_x_preferred":[
        "\uc218\ub7ec\ud604"
    ],
    "name:nan_x_preferred":[
        "So\u0358-le\u030dk-ko\u0101n"
    ],
    "name:nld_x_preferred":[
        "Shule"
    ],
    "name:nob_x_preferred":[
        "Shule"
    ],
    "name:pol_x_preferred":[
        "Shule"
    ],
    "name:rus_x_preferred":[
        "\u042f\u043d\u0433\u0438\u0448\u0430\u0440"
    ],
    "name:swe_x_preferred":[
        "Shule"
    ],
    "name:uig_x_preferred":[
        "Yengix\u0259h\u0328\u0259r"
    ],
    "name:uig_x_variant":[
        "Y\u00e9ngisheher",
        "\u064a\u06d0\u06ad\u0649\u0634\u06d5\u06be\u06d5\u0631",
        "\u0415\u04a3\u0438\u0448\u04d9\u04bb\u04d9\u0440"
    ],
    "name:ukr_x_preferred":[
        "\u042f\u043d\u0433\u0456\u0448\u0430\u0440"
    ],
    "name:und_x_variant":[
        "Su-lo"
    ],
    "name:urd_x_preferred":[
        "\u0634\u0648\u0644\u06d2 \u06a9\u0627\u0624\u0646\u0679\u06cc"
    ],
    "name:vie_x_preferred":[
        "S\u01a1 L\u1eb7c"
    ],
    "name:wuu_x_preferred":[
        "\u758f\u52d2\u53bf"
    ],
    "name:zho_x_preferred":[
        "\u758f\u52d2"
    ],
    "name:zho_x_variant":[
        "\u758f\u52d2\u53bf"
    ],
    "qs:name":"\u758f\u52d2",
    "qs:name_adm0":"\u4e2d\u570b",
    "qs:name_adm1":"\u65b0\u7586\u7ef4\u543e\u5c14\u81ea\u6cbb\u533a",
    "qs:photos":12,
    "qs:photos_1k":2,
    "qs:photos_9k":1,
    "qs:photos_9r":1,
    "qs:photos_all":12,
    "qs:photos_sr":1,
    "qs:placetype":"Town",
    "qs:pop_sr":"6",
    "wd:wordcount":85,
    "wof:name":"\u758f\u52d2",
    "wof:placetype":"locality",
    "wof:population":0
},
  "geometry": {"coordinates":[76.04000000000001,39.39139],"type":"Point"}
}