{
  "type": "Feature",
  "properties": {
    "gn:admin1_code":"14.0",
    "gn:asciiname":"Lili",
    "gn:country_code":"CN",
    "gn:dem":3885,
    "gn:feature_class":"P",
    "gn:feature_code":"PPL",
    "gn:name":"Lili",
    "gn:population":0,
    "gn:timezone":"Asia/Urumqi",
    "iso:country":"CN",
    "name:cat_x_preferred":[
        "Lil\u00ed"
    ],
    "name:deu_x_preferred":[
        "Lili"
    ],
    "name:fas_x_preferred":[
        "\u0644\u06cc\u0644\u06cc"
    ],
    "name:fra_x_preferred":[
        "Lili"
    ],
    "name:heb_x_preferred":[
        "\u05dc\u05d9\u05dc\u05d9"
    ],
    "name:ind_x_preferred":[
        "Lili"
    ],
    "name:ita_x_preferred":[
        "Lili"
    ],
    "name:pol_x_preferred":[
        "Lili"
    ],
    "name:zho_x_preferred":[
        "\u5229\u5229"
    ],
    "wof:name":"Lili",
    "wof:placetype":"locality"
},
  "geometry": {"coordinates":[96.16571999999999,30.92438],"type":"Point"}
}