{
  "type": "Feature",
  "properties": {
    "gn:admin1_code":"7",
    "gn:asciiname":"Lingxiadian",
    "gn:country_code":"CN",
    "gn:dem":127,
    "gn:feature_class":"P",
    "gn:feature_code":"PPL",
    "gn:name":"Lingxiadian",
    "gn:population":0,
    "gn:timezone":"Asia/Shanghai",
    "iso:country":"CN",
    "name:zho_x_preferred":[
        "\u5cad\u4e0b\u5e97"
    ],
    "wof:name":"Lingxiadian",
    "wof:placetype":"locality"
},
  "geometry": {"coordinates":[118.88159,25.96011],"type":"Point"}
}