{
  "type": "Feature",
  "properties": {
    "gn:admin1_code":"29.0",
    "gn:asciiname":"Cenglila",
    "gn:country_code":"CN",
    "gn:dem":3585,
    "gn:feature_class":"P",
    "gn:feature_code":"PPL",
    "gn:name":"Cenglila",
    "gn:population":0,
    "gn:timezone":"Asia/Shanghai",
    "iso:country":"CN",
    "name:zho_x_preferred":[
        "\u5c42\u674e\u62c9"
    ],
    "wof:name":"Cenglila",
    "wof:placetype":"locality"
},
  "geometry": {"coordinates":[98.9081,28.5105],"type":"Point"}
}