{
  "type": "Feature",
  "properties": {
    "gn:admin1_code":"14.0",
    "gn:asciiname":"Zekaqimi",
    "gn:country_code":"CN",
    "gn:dem":4438,
    "gn:feature_class":"P",
    "gn:feature_code":"PPL",
    "gn:name":"Zekaqimi",
    "gn:population":0,
    "gn:timezone":"Asia/Urumqi",
    "iso:country":"CN",
    "name:bod_x_preferred":[
        "Z\u00eakaqim\u00ea"
    ],
    "name:zho_x_preferred":[
        "Zekaqimi"
    ],
    "name:zho_x_variant":[
        "\u8d23\u5361\u67d2\u7c73",
        "Meiyu Qu",
        "\u7f8e\u7389\u533a"
    ],
    "wof:name":"Zekaqimi",
    "wof:placetype":"locality"
},
  "geometry": {"coordinates":[97.40300000000001,30.103],"type":"Point"}
}