{
  "type": "Feature",
  "properties": {
    "gn:admin1_code":"26.0",
    "gn:asciiname":"Taixingcun",
    "gn:country_code":"CN",
    "gn:dem":643,
    "gn:feature_class":"P",
    "gn:feature_code":"PPL",
    "gn:name":"Taixingcun",
    "gn:population":0,
    "gn:timezone":"Asia/Shanghai",
    "iso:country":"CN",
    "name:zho_x_preferred":[
        "\u592a\u884c\u6751"
    ],
    "wof:name":"Taixingcun",
    "wof:placetype":"locality"
},
  "geometry": {"coordinates":[108.44364,32.97273],"type":"Point"}
}