{
  "type": "Feature",
  "properties": {
    "gn:admin1_code":"14.0",
    "gn:asciiname":"Duixucun",
    "gn:country_code":"CN",
    "gn:dem":3353,
    "gn:feature_class":"P",
    "gn:feature_code":"PPL",
    "gn:name":"Duixucun",
    "gn:population":0,
    "gn:timezone":"Asia/Urumqi",
    "iso:country":"CN",
    "name:zho_x_preferred":[
        "\u5806\u8bb8\u6751"
    ],
    "wof:name":"Duixucun",
    "wof:placetype":"locality"
},
  "geometry": {"coordinates":[92.85599999999999,28.95667000000001],"type":"Point"}
}