{
  "type": "Feature",
  "properties": {
    "gn:admin1_code":"8.0",
    "gn:asciiname":"Jianchengcun",
    "gn:country_code":"CN",
    "gn:dem":232,
    "gn:feature_class":"P",
    "gn:feature_code":"PPL",
    "gn:name":"Jianchengcun",
    "gn:population":0,
    "gn:timezone":"Asia/Shanghai",
    "iso:country":"CN",
    "name:zho_x_preferred":[
        "\u5efa\u57ce\u6751"
    ],
    "wof:name":"Jianchengcun",
    "wof:placetype":"locality"
},
  "geometry": {"coordinates":[126.98953,47.47642000000001],"type":"Point"}
}