{
  "type": "Feature",
  "properties": {
    "gn:admin1_code":"3.0",
    "gn:asciiname":"Boluo",
    "gn:country_code":"CN",
    "gn:dem":120,
    "gn:feature_class":"P",
    "gn:feature_code":"PPL",
    "gn:name":"Boluo",
    "gn:population":0,
    "gn:timezone":"Asia/Shanghai",
    "iso:country":"CN",
    "name:und_x_variant":[
        "\u6ce2\u7f57",
        "Boluoxiang",
        "\u6ce2\u7f57\u4e61"
    ],
    "wof:name":"Boluo",
    "wof:placetype":"locality"
},
  "geometry": {"coordinates":[116.40004,27.00914],"type":"Point"}
}