{
  "type": "Feature",
  "properties": {
    "gn:admin1_code":"30",
    "gn:asciiname":"Youheng",
    "gn:country_code":"CN",
    "gn:dem":26,
    "gn:feature_class":"P",
    "gn:feature_code":"PPL",
    "gn:name":"Youheng",
    "gn:population":0,
    "gn:timezone":"Asia/Urumqi",
    "iso:country":"CN",
    "name:zho_x_preferred":[
        "\u6cb9\u6841"
    ],
    "wof:name":"Youheng",
    "wof:placetype":"locality"
},
  "geometry": {"coordinates":[111.28531,21.57172000000001],"type":"Point"}
}