{
  "type": "Feature",
  "properties": {
    "gn:admin1_code":"7",
    "gn:asciiname":"Jixiacun",
    "gn:country_code":"CN",
    "gn:dem":327,
    "gn:feature_class":"P",
    "gn:feature_code":"PPL",
    "gn:name":"Jixiacun",
    "gn:population":0,
    "gn:timezone":"Asia/Shanghai",
    "iso:country":"CN",
    "name:zho_x_preferred":[
        "\u9645\u4e0b\u6751"
    ],
    "wof:name":"Jixiacun",
    "wof:placetype":"locality"
},
  "geometry": {"coordinates":[118.625,27.95917],"type":"Point"}
}