{
  "type": "Feature",
  "properties": {
    "gn:admin1_code":"15.0",
    "gn:asciiname":"Awencang",
    "gn:country_code":"CN",
    "gn:dem":2735,
    "gn:feature_class":"P",
    "gn:feature_code":"PPL",
    "gn:name":"Awencang",
    "gn:population":0,
    "gn:timezone":"Asia/Shanghai",
    "iso:country":"CN",
    "name:und_x_variant":[
        "\u963f\u6e29\u4ed3"
    ],
    "wof:name":"Awencang",
    "wof:placetype":"locality"
},
  "geometry": {"coordinates":[103.39632,34.60205],"type":"Point"}
}