{
  "type": "Feature",
  "properties": {
    "gn:admin1_code":"15.0",
    "gn:asciiname":"Dongyawanzhuang",
    "gn:country_code":"CN",
    "gn:dem":2080,
    "gn:feature_class":"P",
    "gn:feature_code":"PPL",
    "gn:name":"Dongyawanzhuang",
    "gn:population":0,
    "gn:timezone":"Asia/Shanghai",
    "iso:country":"CN",
    "name:zho_x_preferred":[
        "\u4e1c\u5d16\u6e7e\u5e84"
    ],
    "wof:name":"Dongyawanzhuang",
    "wof:placetype":"locality"
},
  "geometry": {"coordinates":[104.67700000000001,35.5404],"type":"Point"}
}