{
  "type": "Feature",
  "properties": {
    "gn:admin1_code":"26.0",
    "gn:asciiname":"Xiagaochi",
    "gn:country_code":"CN",
    "gn:dem":1277,
    "gn:feature_class":"P",
    "gn:feature_code":"PPL",
    "gn:name":"Xiagaochi",
    "gn:population":0,
    "gn:timezone":"Asia/Shanghai",
    "iso:country":"CN",
    "name:zho_x_preferred":[
        "\u4e0b\u9ad8\u6c60"
    ],
    "wof:name":"Xiagaochi",
    "wof:placetype":"locality"
},
  "geometry": {"coordinates":[109.13261,36.02672000000001],"type":"Point"}
}