{
  "type": "Feature",
  "properties": {
    "gn:admin1_code":"29.0",
    "gn:asciiname":"Dabaidi",
    "gn:country_code":"CN",
    "gn:dem":2375,
    "gn:feature_class":"P",
    "gn:feature_code":"PPL",
    "gn:name":"Dabaidi",
    "gn:population":0,
    "gn:timezone":"Asia/Shanghai",
    "iso:country":"CN",
    "name:zho_x_preferred":[
        "\u5927\u767d\u5730"
    ],
    "wof:name":"Dabaidi",
    "wof:placetype":"locality"
},
  "geometry": {"coordinates":[100.663,27.0789],"type":"Point"}
}