{
  "type": "Feature",
  "properties": {
    "gn:admin1_code":"7.0",
    "gn:asciiname":"Pingdicun",
    "gn:country_code":"CN",
    "gn:dem":636,
    "gn:feature_class":"P",
    "gn:feature_code":"PPL",
    "gn:name":"Pingdicun",
    "gn:population":0,
    "gn:timezone":"Asia/Shanghai",
    "iso:country":"CN",
    "name:und_x_variant":[
        "\u576a\u5730\u6751"
    ],
    "name:zho_x_preferred":[
        "\u576a\u5730\u6751"
    ],
    "wof:name":"Pingdicun",
    "wof:placetype":"locality"
},
  "geometry": {"coordinates":[117.25058,26.41859],"type":"Point"}
}