{
  "type": "Feature",
  "properties": {
    "gn:admin1_code":"14",
    "gn:asciiname":"Jialong",
    "gn:country_code":"CN",
    "gn:dem":4537,
    "gn:feature_class":"P",
    "gn:feature_code":"PPL",
    "gn:name":"Jialong",
    "gn:population":0,
    "gn:timezone":"Asia/Urumqi",
    "iso:country":"CN",
    "name:zho_x_preferred":[
        "\u52a0\u9686"
    ],
    "wof:name":"Jialong",
    "wof:placetype":"locality"
},
  "geometry": {"coordinates":[87.6463,31.8252],"type":"Point"}
}