{
  "type": "Feature",
  "properties": {
    "gn:admin1_code":"7.0",
    "gn:asciiname":"Liankengcun",
    "gn:country_code":"CN",
    "gn:dem":281,
    "gn:feature_class":"P",
    "gn:feature_code":"PPL",
    "gn:name":"Liankengcun",
    "gn:population":0,
    "gn:timezone":"Asia/Shanghai",
    "iso:country":"CN",
    "name:zho_x_preferred":[
        "\u8fde\u5751\u6751"
    ],
    "wof:name":"Liankengcun",
    "wof:placetype":"locality"
},
  "geometry": {"coordinates":[117.82093999999999,26.91185],"type":"Point"}
}