{
  "type": "Feature",
  "properties": {
    "gn:admin1_code":"30",
    "gn:asciiname":"Nanren",
    "gn:country_code":"CN",
    "gn:dem":5,
    "gn:feature_class":"P",
    "gn:feature_code":"PPL",
    "gn:name":"Nanren",
    "gn:population":0,
    "gn:timezone":"Asia/Shanghai",
    "iso:country":"CN",
    "name:und_x_variant":[
        "\u5357\u4efb"
    ],
    "name:zho_x_preferred":[
        "\u5357\u4efb"
    ],
    "wof:name":"Nanren",
    "wof:placetype":"locality"
},
  "geometry": {"coordinates":[117.07971999999999,23.62944],"type":"Point"}
}