{
  "type": "Feature",
  "properties": {
    "gn:admin1_code":"19.0",
    "gn:asciiname":"Dalijiatun",
    "gn:country_code":"CN",
    "gn:dem":123,
    "gn:feature_class":"P",
    "gn:feature_code":"PPL",
    "gn:name":"Dalijiatun",
    "gn:population":0,
    "gn:timezone":"Asia/Shanghai",
    "iso:country":"CN",
    "name:zho_x_preferred":[
        "\u5927\u674e\u5bb6\u5c6f"
    ],
    "wof:name":"Dalijiatun",
    "wof:placetype":"locality"
},
  "geometry": {"coordinates":[121.90589,39.62741],"type":"Point"}
}