{
  "type": "Feature",
  "properties": {
    "gn:admin1_code":"29.0",
    "gn:asciiname":"Nanshanbei",
    "gn:country_code":"CN",
    "gn:dem":1078,
    "gn:feature_class":"P",
    "gn:feature_code":"PPL",
    "gn:name":"Nanshanbei",
    "gn:population":0,
    "gn:timezone":"Asia/Shanghai",
    "iso:country":"CN",
    "name:zho_x_preferred":[
        "\u5357\u5c71\u5317"
    ],
    "wof:name":"Nanshanbei",
    "wof:placetype":"locality"
},
  "geometry": {"coordinates":[99.2773,22.1776],"type":"Point"}
}