{
  "type": "Feature",
  "properties": {
    "gn:admin1_code":"1.0",
    "gn:asciiname":"Dongyanzhuangcun",
    "gn:country_code":"CN",
    "gn:dem":35,
    "gn:feature_class":"P",
    "gn:feature_code":"PPL",
    "gn:name":"Dongyanzhuangcun",
    "gn:population":0,
    "gn:timezone":"Asia/Shanghai",
    "iso:country":"CN",
    "name:zho_x_preferred":[
        "\u4e1c\u960e\u5e84\u6751"
    ],
    "wof:name":"Dongyanzhuangcun",
    "wof:placetype":"locality"
},
  "geometry": {"coordinates":[115.50112,32.97583],"type":"Point"}
}