{
  "type": "Feature",
  "properties": {
    "gn:admin1_code":"12.0",
    "gn:asciiname":"Maotaihe",
    "gn:country_code":"CN",
    "gn:dem":32,
    "gn:feature_class":"P",
    "gn:feature_code":"PPL",
    "gn:name":"Maotaihe",
    "gn:population":0,
    "gn:timezone":"Asia/Shanghai",
    "iso:country":"CN",
    "name:zho_x_preferred":[
        "\u6bdb\u592a\u6cb3"
    ],
    "wof:name":"Maotaihe",
    "wof:placetype":"locality"
},
  "geometry": {"coordinates":[113.08698,30.4487],"type":"Point"}
}