{
  "type": "Feature",
  "properties": {
    "gn:country":"CN",
    "gn:fcode":"PPL",
    "gn:population":153714,
    "iso:country":"CN",
    "name:cym_x_preferred":[
        "Ardal Sanshui"
    ],
    "name:deu_x_preferred":[
        "Sanshui"
    ],
    "name:eng_x_preferred":[
        "Sanshui District"
    ],
    "name:fas_x_preferred":[
        "\u0633\u0627\u0646\u0634\u0648\u06cc"
    ],
    "name:gan_x_preferred":[
        "\u4e09\u6c34\u533a"
    ],
    "name:hak_x_preferred":[
        "S\u00e2m-s\u00fai-kh\u00ee"
    ],
    "name:jpn_x_preferred":[
        "\u4e09\u6c34\u533a"
    ],
    "name:kor_x_preferred":[
        "\uc2fc\uc218\uc774\uad6c"
    ],
    "name:mwl_x_preferred":[
        "Sanshui"
    ],
    "name:nan_x_preferred":[
        "Sam-s\u00fai-khu"
    ],
    "name:nld_x_preferred":[
        "Sanshui"
    ],
    "name:nob_x_preferred":[
        "Sanshui"
    ],
    "name:spa_x_preferred":[
        "Sanshui"
    ],
    "name:swe_x_preferred":[
        "Sanshui"
    ],
    "name:und_x_variant":[
        "Sainam"
    ],
    "name:vie_x_preferred":[
        "Tam Th\u1ee7y"
    ],
    "name:wuu_x_preferred":[
        "\u4e09\u6c34\u533a"
    ],
    "name:yue_x_preferred":[
        "\u4e09\u6c34"
    ],
    "name:zho_x_preferred":[
        "\u4e09\u6c34"
    ],
    "name:zho_x_variant":[
        "\u4e09\u6c34\u533a"
    ],
    "qs:name":"Sanshui",
    "qs:photos_9r":0,
    "qs:photos_sr":0,
    "qs:pop_sr":"9",
    "wd:wordcount":426,
    "wof:name":"Sanshui",
    "wof:placetype":"locality",
    "wof:population":153714
},
  "geometry": {"coordinates":[112.89161,23.15486],"type":"Point"}
}