{
  "type": "Feature",
  "properties": {
    "gn:country":"CN",
    "gn:fcode":"PPL",
    "gn:pop":153714,
    "iso:country":"CN",
    "name:unk_x_variant":[
        "Sainam"
    ],
    "name:zho_x_preferred":[
        "\u4e09\u6c34"
    ],
    "qs:name":"Sanshui",
    "qs:photos_9r":0,
    "qs:photos_sr":0,
    "qs:pop_sr":"9",
    "wd:wordcount":426,
    "wof:name":"Sanshui",
    "wof:placetype":"locality",
    "wof:population":153714
},
  "geometry": {"coordinates":[112.89161,23.15486],"type":"Point"}
}