{
  "type": "Feature",
  "properties": {
    "gn:admin1_code":"26.0",
    "gn:asciiname":"Liushumaocun",
    "gn:country_code":"CN",
    "gn:dem":1062,
    "gn:feature_class":"P",
    "gn:feature_code":"PPL",
    "gn:name":"Liushumaocun",
    "gn:population":0,
    "gn:timezone":"Asia/Shanghai",
    "iso:country":"CN",
    "name:zho_x_preferred":[
        "\u67f3\u6811\u5cc1\u6751"
    ],
    "wof:name":"Liushumaocun",
    "wof:placetype":"locality"
},
  "geometry": {"coordinates":[110.55074999999999,37.43818],"type":"Point"}
}