{
  "type": "Feature",
  "properties": {
    "gn:admin1_code":"7.0",
    "gn:asciiname":"Bendoukeng",
    "gn:country_code":"CN",
    "gn:dem":41,
    "gn:feature_class":"P",
    "gn:feature_code":"PPL",
    "gn:name":"Bendoukeng",
    "gn:population":0,
    "gn:timezone":"Asia/Shanghai",
    "iso:country":"CN",
    "name:zho_x_preferred":[
        "\u755a\u6597\u5751"
    ],
    "wof:name":"Bendoukeng",
    "wof:placetype":"locality"
},
  "geometry": {"coordinates":[119.68548,26.71876],"type":"Point"}
}