{
  "type": "Feature",
  "properties": {
    "gn:admin1_code":"3.0",
    "gn:asciiname":"Sifangping",
    "gn:country_code":"CN",
    "gn:dem":368,
    "gn:feature_class":"P",
    "gn:feature_code":"PPL",
    "gn:name":"Sifangping",
    "gn:population":0,
    "gn:timezone":"Asia/Shanghai",
    "iso:country":"CN",
    "name:und_x_variant":[
        "\u56db\u65b9\u576a"
    ],
    "wof:name":"Sifangping",
    "wof:placetype":"locality"
},
  "geometry": {"coordinates":[114.18652,28.75188],"type":"Point"}
}