{
  "type": "Feature",
  "properties": {
    "gn:admin1_code":"18.0",
    "gn:asciiname":"Baiyangping",
    "gn:country_code":"CN",
    "gn:dem":839,
    "gn:feature_class":"P",
    "gn:feature_code":"PPL",
    "gn:name":"Baiyangping",
    "gn:population":0,
    "gn:timezone":"Asia/Shanghai",
    "iso:country":"CN",
    "name:zho_x_preferred":[
        "\u767d\u79e7\u576a"
    ],
    "wof:name":"Baiyangping",
    "wof:placetype":"locality"
},
  "geometry": {"coordinates":[107.652,26.6909],"type":"Point"}
}