{
  "type": "Feature",
  "properties": {
    "gn:admin1_code":"11.0",
    "gn:asciiname":"Tanxi",
    "gn:country_code":"CN",
    "gn:dem":541,
    "gn:feature_class":"P",
    "gn:feature_code":"PPL",
    "gn:name":"Tanxi",
    "gn:population":0,
    "gn:timezone":"Asia/Shanghai",
    "iso:country":"CN",
    "name:zho_x_preferred":[
        "\u8c2d\u6eaa"
    ],
    "wof:name":"Tanxi",
    "wof:placetype":"locality"
},
  "geometry": {"coordinates":[112.66981,25.51751],"type":"Point"}
}