{
  "type": "Feature",
  "properties": {
    "gn:admin1_code":"18",
    "gn:asciiname":"Ranjiao",
    "gn:country_code":"CN",
    "gn:dem":1184,
    "gn:feature_class":"P",
    "gn:feature_code":"PPL",
    "gn:name":"Ranjiao",
    "gn:population":0,
    "gn:timezone":"Asia/Shanghai",
    "iso:country":"CN",
    "name:zho_x_preferred":[
        "\u5189\u4ea4"
    ],
    "wof:name":"Ranjiao",
    "wof:placetype":"locality"
},
  "geometry": {"coordinates":[105.849,25.8368],"type":"Point"}
}