{
  "type": "Feature",
  "properties": {
    "gn:admin1_code":"3.0",
    "gn:asciiname":"Goudaozui",
    "gn:country_code":"CN",
    "gn:dem":456,
    "gn:feature_class":"P",
    "gn:feature_code":"PPL",
    "gn:name":"Goudaozui",
    "gn:population":0,
    "gn:timezone":"Asia/Shanghai",
    "iso:country":"CN",
    "name:und_x_variant":[
        "\u94a9\u5200\u5480"
    ],
    "wof:name":"Goudaozui",
    "wof:placetype":"locality"
},
  "geometry": {"coordinates":[115.22032,27.0976],"type":"Point"}
}