{
  "type": "Feature",
  "properties": {
    "gn:admin1_code":"15.0",
    "gn:asciiname":"Xinwen",
    "gn:country_code":"CN",
    "gn:dem":1664,
    "gn:feature_class":"P",
    "gn:feature_code":"PPL",
    "gn:name":"Xinwen",
    "gn:population":0,
    "gn:timezone":"Asia/Shanghai",
    "iso:country":"CN",
    "name:zho_x_preferred":[
        "\u65b0\u6587"
    ],
    "wof:name":"Xinwen",
    "wof:placetype":"locality"
},
  "geometry": {"coordinates":[105.486,34.1561],"type":"Point"}
}