{
  "type": "Feature",
  "properties": {
    "gn:admin1_code":"29.0",
    "gn:asciiname":"Dongpu",
    "gn:country_code":"CN",
    "gn:dem":1793,
    "gn:feature_class":"P",
    "gn:feature_code":"PPL",
    "gn:name":"Dongpu",
    "gn:population":0,
    "gn:timezone":"Asia/Shanghai",
    "iso:country":"CN",
    "name:zho_x_preferred":[
        "\u7850\u6d66"
    ],
    "wof:name":"Dongpu",
    "wof:placetype":"locality"
},
  "geometry": {"coordinates":[102.765,23.0757],"type":"Point"}
}