{
  "type": "Feature",
  "properties": {
    "gn:admin1_code":"1.0",
    "gn:asciiname":"Yangwu",
    "gn:country_code":"CN",
    "gn:dem":186,
    "gn:feature_class":"P",
    "gn:feature_code":"PPL",
    "gn:name":"Yangwu",
    "gn:population":0,
    "gn:timezone":"Asia/Shanghai",
    "iso:country":"CN",
    "name:zho_x_preferred":[
        "Yangwu"
    ],
    "name:zho_x_variant":[
        "\u9633\u575e"
    ],
    "wof:name":"Yangwu",
    "wof:placetype":"locality"
},
  "geometry": {"coordinates":[119.24638,30.45192],"type":"Point"}
}