{
  "type": "Feature",
  "properties": {
    "gn:admin1_code":"23.0",
    "gn:asciiname":"Chenjiazhai",
    "gn:country_code":"CN",
    "gn:dem":7,
    "gn:feature_class":"P",
    "gn:feature_code":"PPL",
    "gn:name":"Chenjiazhai",
    "gn:population":0,
    "gn:timezone":"Asia/Shanghai",
    "iso:country":"CN",
    "name:zho_x_preferred":[
        "Chenjiazhai"
    ],
    "name:zho_x_variant":[
        "\u9648\u5bb6\u5b85"
    ],
    "wof:name":"Chenjiazhai",
    "wof:placetype":"locality"
},
  "geometry": {"coordinates":[121.68863,31.18531],"type":"Point"}
}