{
  "type": "Feature",
  "properties": {
    "gn:admin1_code":"6.0",
    "gn:asciiname":"Obson Jah",
    "gn:cc2":"CN",
    "gn:country_code":"CN",
    "gn:dem":2759,
    "gn:feature_class":"P",
    "gn:feature_code":"PPL",
    "gn:name":"Obson Jah",
    "gn:population":0,
    "gn:timezone":"Asia/Urumqi",
    "iso:country":"CN",
    "name:und_x_variant":[
        "Wu-pu-su-i-cha-la",
        "Obson Jah"
    ],
    "wof:name":"Obson Jah",
    "wof:placetype":"locality"
},
  "geometry": {"coordinates":[94.31667,37.83333],"type":"Point"}
}