{
  "type": "Feature",
  "properties": {
    "gn:admin1_code":"11.0",
    "gn:asciiname":"Xinhekou",
    "gn:country_code":"CN",
    "gn:dem":37,
    "gn:feature_class":"P",
    "gn:feature_code":"PPL",
    "gn:name":"Xinhekou",
    "gn:population":0,
    "gn:timezone":"Asia/Shanghai",
    "iso:country":"CN",
    "name:zho_x_preferred":[
        "Xinhekou"
    ],
    "name:zho_x_variant":[
        "\u65b0\u6cb3\u53e3"
    ],
    "wof:name":"Xinhekou",
    "wof:placetype":"locality"
},
  "geometry": {"coordinates":[111.99485,29.67034],"type":"Point"}
}