{
  "type": "Feature",
  "properties": {
    "gn:admin1_code":"29.0",
    "gn:asciiname":"Manhai",
    "gn:country_code":"CN",
    "gn:dem":1218,
    "gn:feature_class":"P",
    "gn:feature_code":"PPL",
    "gn:name":"Manhai",
    "gn:population":0,
    "gn:timezone":"Asia/Shanghai",
    "iso:country":"CN",
    "name:zho_x_preferred":[
        "\u86ee\u6d77"
    ],
    "wof:name":"Manhai",
    "wof:placetype":"locality"
},
  "geometry": {"coordinates":[101.148,23.2185],"type":"Point"}
}