{
  "type": "Feature",
  "properties": {
    "gn:admin1_code":"32.0",
    "gn:asciiname":"Yuwa",
    "gn:country_code":"CN",
    "gn:dem":2088,
    "gn:feature_class":"P",
    "gn:feature_code":"PPL",
    "gn:name":"Yuwa",
    "gn:population":0,
    "gn:timezone":"Asia/Shanghai",
    "iso:country":"CN",
    "name:zho_x_preferred":[
        "\u7389\u74e6"
    ],
    "wof:name":"Yuwa",
    "wof:placetype":"locality"
},
  "geometry": {"coordinates":[103.889,33.5794],"type":"Point"}
}