{
  "type": "Feature",
  "properties": {
    "gn:admin1_code":"30.0",
    "gn:asciiname":"Yuangangliao",
    "gn:country_code":"CN",
    "gn:dem":24,
    "gn:feature_class":"P",
    "gn:feature_code":"PPL",
    "gn:name":"Yuangangliao",
    "gn:population":0,
    "gn:timezone":"Asia/Shanghai",
    "iso:country":"CN",
    "name:zho_x_preferred":[
        "Yuangangliao"
    ],
    "name:zho_x_variant":[
        "\u5143\u5c97\u6f66"
    ],
    "wof:name":"Yuangangliao",
    "wof:placetype":"locality"
},
  "geometry": {"coordinates":[113.26278000000001,23.80083],"type":"Point"}
}