{
  "type": "Feature",
  "properties": {
    "gn:admin1_code":"3.0",
    "gn:asciiname":"Dongtufang",
    "gn:country_code":"CN",
    "gn:dem":37,
    "gn:feature_class":"P",
    "gn:feature_code":"PPL",
    "gn:name":"Dongtufang",
    "gn:population":0,
    "gn:timezone":"Asia/Shanghai",
    "iso:country":"CN",
    "name:und_x_variant":[
        "\u4e1c\u6d82\u574a"
    ],
    "wof:name":"Dongtufang",
    "wof:placetype":"locality"
},
  "geometry": {"coordinates":[115.50905,28.8283],"type":"Point"}
}