{
  "type": "Feature",
  "properties": {
    "gn:admin1_code":"11.0",
    "gn:asciiname":"Lishuxiang",
    "gn:country_code":"CN",
    "gn:dem":156,
    "gn:feature_class":"P",
    "gn:feature_code":"PPL",
    "gn:name":"Lishuxiang",
    "gn:population":0,
    "gn:timezone":"Asia/Shanghai",
    "iso:country":"CN",
    "name:zho_x_preferred":[
        "\u6817\u6811\u5df7"
    ],
    "wof:name":"Lishuxiang",
    "wof:placetype":"locality"
},
  "geometry": {"coordinates":[112.11964999999999,28.32236],"type":"Point"}
}