{
  "type": "Feature",
  "properties": {
    "gn:admin1_code":"25",
    "gn:asciiname":"Shuangyangdian",
    "gn:country_code":"CN",
    "gn:dem":92,
    "gn:feature_class":"P",
    "gn:feature_code":"PPL",
    "gn:name":"Shuangyangdian",
    "gn:population":0,
    "gn:timezone":"Asia/Shanghai",
    "iso:country":"CN",
    "name:zho_x_preferred":[
        "\u53cc\u6768\u5e97"
    ],
    "wof:name":"Shuangyangdian",
    "wof:placetype":"locality"
},
  "geometry": {"coordinates":[117.03400000000001,35.9954],"type":"Point"}
}