{
  "type": "Feature",
  "properties": {
    "gn:admin1_code":"30",
    "gn:asciiname":"Huangwu Linchang",
    "gn:country_code":"CN",
    "gn:dem":92,
    "gn:feature_class":"P",
    "gn:feature_code":"PPLF",
    "gn:name":"Huangwu Linchang",
    "gn:population":0,
    "gn:timezone":"Asia/Shanghai",
    "iso:country":"CN",
    "name:und_x_variant":[
        "Danxia Linchang",
        "Huangwu Linchang",
        "\u9ec4\u5c4b\u6797\u573a"
    ],
    "wof:name":"Huangwu Linchang",
    "wof:placetype":"locality"
},
  "geometry": {"coordinates":[113.76000000000001,25.06],"type":"Point"}
}