{
  "type": "Feature",
  "properties": {
    "gn:admin1_code":"11",
    "gn:asciiname":"Sanjiang",
    "gn:country_code":"CN",
    "gn:dem":81,
    "gn:feature_class":"P",
    "gn:feature_code":"PPL",
    "gn:name":"Sanjiang",
    "gn:population":0,
    "gn:timezone":"Asia/Shanghai",
    "iso:country":"CN",
    "name:ceb_x_preferred":[
        "Sanjiang"
    ],
    "name:deu_x_preferred":[
        "Sanjiang"
    ],
    "wof:name":"Sanjiang",
    "wof:placetype":"locality"
},
  "geometry": {"coordinates":[111.985,26.3975],"type":"Point"}
}