{
  "type": "Feature",
  "properties": {
    "gn:admin1_code":"30.0",
    "gn:asciiname":"Gongjiaotou",
    "gn:country_code":"CN",
    "gn:dem":228,
    "gn:feature_class":"P",
    "gn:feature_code":"PPL",
    "gn:name":"Gongjiaotou",
    "gn:population":0,
    "gn:timezone":"Asia/Shanghai",
    "iso:country":"CN",
    "name:zho_x_preferred":[
        "\u5bab\u89d2\u5934"
    ],
    "wof:name":"Gongjiaotou",
    "wof:placetype":"locality"
},
  "geometry": {"coordinates":[115.44077,23.94764],"type":"Point"}
}