{
  "type": "Feature",
  "properties": {
    "gn:admin1_code":"29",
    "gn:asciiname":"Poluodian",
    "gn:country_code":"CN",
    "gn:dem":1798,
    "gn:feature_class":"P",
    "gn:feature_code":"PPL",
    "gn:name":"Poluodian",
    "gn:population":0,
    "gn:timezone":"Asia/Shanghai",
    "iso:country":"CN",
    "name:zho_x_preferred":[
        "\u5761\u843d\u7538"
    ],
    "wof:name":"Poluodian",
    "wof:placetype":"locality"
},
  "geometry": {"coordinates":[102.16,24.2176],"type":"Point"}
}