{
  "type": "Feature",
  "properties": {
    "gn:admin1_code":"25",
    "gn:asciiname":"Donglu",
    "gn:country_code":"CN",
    "gn:dem":10,
    "gn:feature_class":"P",
    "gn:feature_code":"PPL",
    "gn:name":"Dongl\u00fc",
    "gn:population":0,
    "gn:timezone":"Asia/Shanghai",
    "iso:country":"CN",
    "name:und_x_variant":[
        "Dongl\u00fc"
    ],
    "name:zho_x_preferred":[
        "\u4e1c\u5415"
    ],
    "wof:name":"Donglu",
    "wof:placetype":"locality"
},
  "geometry": {"coordinates":[118.08799999999999,37.6261],"type":"Point"}
}