{
  "type": "Feature",
  "properties": {
    "gn:admin1_code":"11.0",
    "gn:asciiname":"Lishinian",
    "gn:country_code":"CN",
    "gn:dem":62,
    "gn:feature_class":"P",
    "gn:feature_code":"PPL",
    "gn:name":"Lishinian",
    "gn:population":0,
    "gn:timezone":"Asia/Shanghai",
    "iso:country":"CN",
    "name:zho_x_preferred":[
        "\u674e\u5e02\u5e74"
    ],
    "wof:name":"Lishinian",
    "wof:placetype":"locality"
},
  "geometry": {"coordinates":[113.16101999999999,28.7344],"type":"Point"}
}