{
  "type": "Feature",
  "properties": {
    "gn:admin1_code":"24.0",
    "gn:asciiname":"Wanze",
    "gn:country_code":"CN",
    "gn:dem":1029,
    "gn:feature_class":"P",
    "gn:feature_code":"PPL",
    "gn:name":"Wanze",
    "gn:population":0,
    "gn:timezone":"Asia/Shanghai",
    "iso:country":"CN",
    "name:bre_x_preferred":[
        "Wanze"
    ],
    "name:bul_x_preferred":[
        "\u0423\u0430\u043d\u0437"
    ],
    "name:cat_x_preferred":[
        "Wanze"
    ],
    "name:ceb_x_preferred":[
        "Wanze"
    ],
    "name:ces_x_preferred":[
        "Wanze"
    ],
    "name:dan_x_preferred":[
        "Wanze"
    ],
    "name:deu_x_preferred":[
        "Wanze"
    ],
    "name:epo_x_preferred":[
        "Wanze"
    ],
    "name:eus_x_preferred":[
        "Wanze"
    ],
    "name:fas_x_preferred":[
        "\u0627\u0648\u0626\u0627\u0646\u0632"
    ],
    "name:fra_x_preferred":[
        "Wanze"
    ],
    "name:ita_x_preferred":[
        "Wanze"
    ],
    "name:lim_x_preferred":[
        "Wanze"
    ],
    "name:nld_x_preferred":[
        "Wanze"
    ],
    "name:nor_x_preferred":[
        "Wanze"
    ],
    "name:oci_x_preferred":[
        "Wanze"
    ],
    "name:pol_x_preferred":[
        "Wanze"
    ],
    "name:por_x_preferred":[
        "Wanze"
    ],
    "name:ron_x_preferred":[
        "Wanze"
    ],
    "name:rus_x_preferred":[
        "\u0412\u0430\u043d\u0437"
    ],
    "name:slk_x_preferred":[
        "Wanze"
    ],
    "name:slv_x_preferred":[
        "Wanze"
    ],
    "name:spa_x_preferred":[
        "Wanze"
    ],
    "name:swe_x_preferred":[
        "Wanze"
    ],
    "name:vie_x_preferred":[
        "Wanze"
    ],
    "name:vol_x_preferred":[
        "Wanze"
    ],
    "name:war_x_preferred":[
        "Wanze"
    ],
    "name:zho_x_preferred":[
        "\u6e7e\u5219"
    ],
    "wof:name":"Wanze",
    "wof:placetype":"locality"
},
  "geometry": {"coordinates":[112.10329,35.7334],"type":"Point"}
}