{
  "type": "Feature",
  "properties": {
    "gn:admin1_code":"3.0",
    "gn:asciiname":"Dongkou Wujia",
    "gn:country_code":"CN",
    "gn:dem":138,
    "gn:feature_class":"P",
    "gn:feature_code":"PPL",
    "gn:name":"Dongkou Wujia",
    "gn:population":0,
    "gn:timezone":"Asia/Shanghai",
    "iso:country":"CN",
    "name:und_x_variant":[
        "\u6d1e\u53e3\u5434\u5bb6"
    ],
    "wof:name":"Dongkou Wujia",
    "wof:placetype":"locality"
},
  "geometry": {"coordinates":[115.03308,29.16804],"type":"Point"}
}