{
  "type": "Feature",
  "properties": {
    "gn:admin1_code":"32.0",
    "gn:asciiname":"Guanyinbali",
    "gn:country_code":"CN",
    "gn:dem":637,
    "gn:feature_class":"P",
    "gn:feature_code":"PPL",
    "gn:name":"Guanyinbali",
    "gn:population":0,
    "gn:timezone":"Asia/Shanghai",
    "iso:country":"CN",
    "name:zho_x_preferred":[
        "\u89c2\u97f3\u575d\u91cc"
    ],
    "wof:name":"Guanyinbali",
    "wof:placetype":"locality"
},
  "geometry": {"coordinates":[107.76349999999999,31.96022],"type":"Point"}
}