{
  "type": "Feature",
  "properties": {
    "gn:admin1_code":"19.0",
    "gn:asciiname":"Housifangtai",
    "gn:country_code":"CN",
    "gn:dem":36,
    "gn:feature_class":"P",
    "gn:feature_code":"PPL",
    "gn:name":"Housifangtai",
    "gn:population":0,
    "gn:timezone":"Asia/Shanghai",
    "iso:country":"CN",
    "name:zho_x_preferred":[
        "\u540e\u56db\u65b9\u53f0"
    ],
    "wof:name":"Housifangtai",
    "wof:placetype":"locality"
},
  "geometry": {"coordinates":[120.471,40.405],"type":"Point"}
}