{
  "type": "Feature",
  "properties": {
    "gn:admin1_code":"14.0",
    "gn:asciiname":"Zuohu",
    "gn:country_code":"CN",
    "gn:dem":4074,
    "gn:feature_class":"P",
    "gn:feature_code":"PPL",
    "gn:name":"Zuohu",
    "gn:population":0,
    "gn:timezone":"Asia/Urumqi",
    "iso:country":"CN",
    "name:zho_x_preferred":[
        "\u4f5c\u864e"
    ],
    "wof:name":"Zuohu",
    "wof:placetype":"locality"
},
  "geometry": {"coordinates":[97.09259,30.86795],"type":"Point"}
}