{
  "type": "Feature",
  "properties": {
    "gn:admin1_code":"20.0",
    "gn:asciiname":"Xiwuzhu'er Sumu",
    "gn:country_code":"CN",
    "gn:dem":570,
    "gn:feature_class":"P",
    "gn:feature_code":"PPL",
    "gn:name":"Xiwuzhu\u2019er Sumu",
    "gn:population":0,
    "gn:timezone":"Asia/Shanghai",
    "iso:country":"CN",
    "name:und_x_variant":[
        "Xiwuzhu\u2019er Sumu"
    ],
    "name:zho_x_preferred":[
        "\u897f\u4e4c\u73e0\u5c14\u82cf\u6728"
    ],
    "wof:name":"Xiwuzhu'er Sumu",
    "wof:placetype":"locality"
},
  "geometry": {"coordinates":[118.55522999999999,49.47485],"type":"Point"}
}