{
  "type": "Feature",
  "properties": {
    "gn:admin1_code":"32.0",
    "gn:asciiname":"Daoping",
    "gn:country_code":"CN",
    "gn:dem":1206,
    "gn:feature_class":"P",
    "gn:feature_code":"PPL",
    "gn:name":"Daoping",
    "gn:population":0,
    "gn:timezone":"Asia/Shanghai",
    "iso:country":"CN",
    "name:zho_x_preferred":[
        "\u5012\u576a"
    ],
    "wof:name":"Daoping",
    "wof:placetype":"locality"
},
  "geometry": {"coordinates":[103.833,31.1981],"type":"Point"}
}