{
  "type": "Feature",
  "properties": {
    "gn:admin1_code":"1.0",
    "gn:asciiname":"Liangjicun",
    "gn:country_code":"CN",
    "gn:dem":39,
    "gn:feature_class":"P",
    "gn:feature_code":"PPL",
    "gn:name":"Liangjicun",
    "gn:population":0,
    "gn:timezone":"Asia/Shanghai",
    "iso:country":"CN",
    "name:zho_x_preferred":[
        "\u4eae\u96c6\u6751"
    ],
    "wof:name":"Liangjicun",
    "wof:placetype":"locality"
},
  "geometry": {"coordinates":[115.42465,33.15853],"type":"Point"}
}