{
  "type": "Feature",
  "properties": {
    "gn:admin1_code":"26.0",
    "gn:asciiname":"Yuanshanbu",
    "gn:country_code":"CN",
    "gn:dem":712,
    "gn:feature_class":"P",
    "gn:feature_code":"PPL",
    "gn:name":"Yuanshanbu",
    "gn:population":0,
    "gn:timezone":"Asia/Shanghai",
    "iso:country":"CN",
    "name:zho_x_preferred":[
        "\u56ed\u5c71\u5821"
    ],
    "wof:name":"Yuanshanbu",
    "wof:placetype":"locality"
},
  "geometry": {"coordinates":[107.173,34.5141],"type":"Point"}
}