{
  "type": "Feature",
  "properties": {
    "gn:admin1_code":"14.0",
    "gn:asciiname":"Garbo",
    "gn:cc2":"CN",
    "gn:country_code":"CN",
    "gn:dem":3868,
    "gn:feature_class":"P",
    "gn:feature_code":"PPL",
    "gn:name":"Garbo",
    "gn:population":0,
    "gn:timezone":"Asia/Urumqi",
    "iso:country":"CN",
    "name:bod_x_preferred":[
        "\u0f63\u0fb7\u0f7c\u0f0b\u0f56\u0fb2\u0f42"
    ],
    "name:bod_x_variant":[
        "\u0f51\u0f7c\u0f0b\u0f56",
        "\u0f51\u0f40\u0f62\u0f0b\u0f54\u0f7c"
    ],
    "name:und_x_variant":[
        "To-tsung",
        "Lo-jo",
        "Towa Dzong",
        "Ka-po",
        "To-hua",
        "Lo-cha",
        "To",
        "Lhozhag",
        "To-wa-ch'eng",
        "Towa",
        "Luozha",
        "Gabo"
    ],
    "name:zho_x_preferred":[
        "\u6d1b\u624e"
    ],
    "name:zho_x_variant":[
        "\u560e\u6ce2"
    ],
    "wof:name":"Garbo",
    "wof:placetype":"locality"
},
  "geometry": {"coordinates":[90.85917000000001,28.38981],"type":"Point"}
}