{
  "type": "Feature",
  "properties": {
    "gn:admin1_code":"32.0",
    "gn:asciiname":"Mingshandian",
    "gn:country_code":"CN",
    "gn:dem":369,
    "gn:feature_class":"P",
    "gn:feature_code":"PPL",
    "gn:name":"Mingshandian",
    "gn:population":0,
    "gn:timezone":"Asia/Shanghai",
    "iso:country":"CN",
    "name:zho_x_preferred":[
        "\u540d\u5c71\u6bbf"
    ],
    "wof:name":"Mingshandian",
    "wof:placetype":"locality"
},
  "geometry": {"coordinates":[104.643,29.0924],"type":"Point"}
}