{
  "type": "Feature",
  "properties": {
    "gn:admin1_code":"16.0",
    "gn:asciiname":"Zhongzhi",
    "gn:country_code":"CN",
    "gn:dem":17,
    "gn:feature_class":"P",
    "gn:feature_code":"PPL",
    "gn:name":"Zhongzhi",
    "gn:population":0,
    "gn:timezone":"Asia/Shanghai",
    "iso:country":"CN",
    "name:zho_x_preferred":[
        "\u5fe0\u76f4"
    ],
    "wof:name":"Zhongzhi",
    "wof:placetype":"locality"
},
  "geometry": {"coordinates":[109.32299999999999,21.8592],"type":"Point"}
}