{
  "type": "Feature",
  "properties": {
    "gn:admin1_code":"29.0",
    "gn:asciiname":"Heiyanjing",
    "gn:country_code":"CN",
    "gn:dem":1820,
    "gn:feature_class":"P",
    "gn:feature_code":"PPL",
    "gn:name":"Heiyanjing",
    "gn:population":0,
    "gn:timezone":"Asia/Shanghai",
    "iso:country":"CN",
    "name:zho_x_preferred":[
        "\u9ed1\u76d0\u4e95"
    ],
    "wof:name":"Heiyanjing",
    "wof:placetype":"locality"
},
  "geometry": {"coordinates":[105.05500000000001,27.5158],"type":"Point"}
}