{
  "type": "Feature",
  "properties": {
    "gn:admin1_code":"8.0",
    "gn:asciiname":"Dongsheng Yidui",
    "gn:country_code":"CN",
    "gn:dem":289,
    "gn:feature_class":"P",
    "gn:feature_code":"PPLF",
    "gn:name":"Dongsheng Yidui",
    "gn:population":0,
    "gn:timezone":"Asia/Shanghai",
    "iso:country":"CN",
    "name:zho_x_preferred":[
        "\u4e1c\u5347\u4e00\u961f"
    ],
    "wof:name":"Dongsheng Yidui",
    "wof:placetype":"locality"
},
  "geometry": {"coordinates":[125.24935000000001,48.33666],"type":"Point"}
}