{
  "type": "Feature",
  "properties": {
    "gn:admin1_code":"25.0",
    "gn:asciiname":"Beitaicun",
    "gn:country_code":"CN",
    "gn:dem":21,
    "gn:feature_class":"P",
    "gn:feature_code":"PPL",
    "gn:name":"Beitaicun",
    "gn:population":0,
    "gn:timezone":"Asia/Shanghai",
    "iso:country":"CN",
    "name:zho_x_preferred":[
        "\u5317\u53f0\u6751"
    ],
    "wof:name":"Beitaicun",
    "wof:placetype":"locality"
},
  "geometry": {"coordinates":[121.82062000000001,37.36174000000001],"type":"Point"}
}