{
  "type": "Feature",
  "properties": {
    "gn:admin1_code":"12",
    "gn:asciiname":"Liji",
    "gn:country_code":"CN",
    "gn:dem":29,
    "gn:feature_class":"P",
    "gn:feature_code":"PPLA4",
    "gn:name":"Liji",
    "gn:population":0,
    "gn:timezone":"Asia/Shanghai",
    "iso:country":"CN",
    "name:und_x_variant":[
        "Li-chi",
        "Liji",
        "\u674e\u96c6",
        "Liji Zhen",
        "\u674e\u96c6\u9547"
    ],
    "wof:name":"Liji",
    "wof:placetype":"locality"
},
  "geometry": {"coordinates":[114.66576999999999,30.87247],"type":"Point"}
}