{
  "type": "Feature",
  "properties": {
    "gn:admin1_code":"24.0",
    "gn:asciiname":"Shanglinghu",
    "gn:country_code":"CN",
    "gn:dem":920,
    "gn:feature_class":"P",
    "gn:feature_code":"PPL",
    "gn:name":"Shanglinghu",
    "gn:population":0,
    "gn:timezone":"Asia/Shanghai",
    "iso:country":"CN",
    "name:zho_x_preferred":[
        "\u4e0a\u4ee4\u72d0"
    ],
    "wof:name":"Shanglinghu",
    "wof:placetype":"locality"
},
  "geometry": {"coordinates":[111.65347,37.07789],"type":"Point"}
}