{
  "type": "Feature",
  "properties": {
    "gn:admin1_code":"25.0",
    "gn:asciiname":"Diaojia",
    "gn:country_code":"CN",
    "gn:dem":20,
    "gn:feature_class":"P",
    "gn:feature_code":"PPL",
    "gn:name":"Diaojia",
    "gn:population":0,
    "gn:timezone":"Asia/Shanghai",
    "iso:country":"CN",
    "name:zho_x_preferred":[
        "\u5201\u5bb6"
    ],
    "wof:name":"Diaojia",
    "wof:placetype":"locality"
},
  "geometry": {"coordinates":[122.31401,37.02498],"type":"Point"}
}