{
  "type": "Feature",
  "properties": {
    "gn:admin1_code":"4.0",
    "gn:asciiname":"Ershisiqing",
    "gn:country_code":"CN",
    "gn:dem":4,
    "gn:feature_class":"P",
    "gn:feature_code":"PPL",
    "gn:name":"Ershisiqing",
    "gn:population":0,
    "gn:timezone":"Asia/Shanghai",
    "iso:country":"CN",
    "name:zho_x_preferred":[
        "\u4e8c\u5341\u56db\u9877"
    ],
    "wof:name":"Ershisiqing",
    "wof:placetype":"locality"
},
  "geometry": {"coordinates":[120.226,33.7321],"type":"Point"}
}