{
  "type": "Feature",
  "properties": {
    "gn:admin1_code":"10.0",
    "gn:asciiname":"Shuixibu",
    "gn:country_code":"CN",
    "gn:dem":967,
    "gn:feature_class":"P",
    "gn:feature_code":"PPL",
    "gn:name":"Shuixibu",
    "gn:population":0,
    "gn:timezone":"Asia/Shanghai",
    "iso:country":"CN",
    "name:zho_x_preferred":[
        "\u6c34\u897f\u5821"
    ],
    "wof:name":"Shuixibu",
    "wof:placetype":"locality"
},
  "geometry": {"coordinates":[114.50382,39.86317],"type":"Point"}
}