{
  "type": "Feature",
  "properties": {
    "gn:admin1_code":"13.0",
    "gn:asciiname":"Koksu",
    "gn:country_code":"CN",
    "gn:dem":1157,
    "gn:feature_class":"P",
    "gn:feature_code":"PPL",
    "gn:name":"Koksu",
    "gn:population":0,
    "gn:timezone":"Asia/Shanghai",
    "iso:country":"CN",
    "name:msa_x_preferred":[
        "Koksu"
    ],
    "name:uig_x_preferred":[
        "K\u0275ksu"
    ],
    "name:uig_x_variant":[
        "K\u00f6ksu",
        "\u0643\u06c6\u0643\u0633\u06c7",
        "\u041a\u04e9\u043a\u0441\u0443"
    ],
    "wof:name":"Koksu",
    "wof:placetype":"locality"
},
  "geometry": {"coordinates":[81.94204000000001,43.20055],"type":"Point"}
}