{
  "type": "Feature",
  "properties": {
    "gn:admin1_code":"6.0",
    "gn:asciiname":"Dagtang",
    "gn:country_code":"CN",
    "gn:dem":3784,
    "gn:feature_class":"P",
    "gn:feature_code":"PPL",
    "gn:name":"Dagtang",
    "gn:population":0,
    "gn:timezone":"Asia/Shanghai",
    "iso:country":"CN",
    "wof:name":"Dagtang",
    "wof:placetype":"locality"
},
  "geometry": {"coordinates":[99.83333,35.06667],"type":"Point"}
}