{
  "type": "Feature",
  "properties": {
    "gn:admin1_code":"4.0",
    "gn:asciiname":"Shanzhengqiao",
    "gn:country_code":"CN",
    "gn:dem":5,
    "gn:feature_class":"P",
    "gn:feature_code":"PPL",
    "gn:name":"Shanzhengqiao",
    "gn:population":0,
    "gn:timezone":"Asia/Shanghai",
    "iso:country":"CN",
    "name:und_x_variant":[
        "\u5584\u653f\u6865"
    ],
    "name:zho_x_preferred":[
        "\u5584\u653f\u6865"
    ],
    "wof:name":"Shanzhengqiao",
    "wof:placetype":"locality"
},
  "geometry": {"coordinates":[120.45404000000001,31.94201],"type":"Point"}
}