{
  "type": "Feature",
  "properties": {
    "gn:admin1_code":"26.0",
    "gn:asciiname":"Yousuocun",
    "gn:country_code":"CN",
    "gn:dem":932,
    "gn:feature_class":"P",
    "gn:feature_code":"PPL",
    "gn:name":"Yousuocun",
    "gn:population":0,
    "gn:timezone":"Asia/Shanghai",
    "iso:country":"CN",
    "name:zho_x_preferred":[
        "\u4f51\u6240\u6751"
    ],
    "wof:name":"Yousuocun",
    "wof:placetype":"locality"
},
  "geometry": {"coordinates":[109.989,37.55526],"type":"Point"}
}