{
  "type": "Feature",
  "properties": {
    "gn:admin1_code":"25",
    "gn:asciiname":"Liangquanzhuang",
    "gn:country_code":"CN",
    "gn:dem":159,
    "gn:feature_class":"P",
    "gn:feature_code":"PPL",
    "gn:name":"Liangquanzhuang",
    "gn:population":0,
    "gn:timezone":"Asia/Shanghai",
    "iso:country":"CN",
    "name:zho_x_preferred":[
        "\u4e24\u6cc9\u5e84"
    ],
    "wof:name":"Liangquanzhuang",
    "wof:placetype":"locality"
},
  "geometry": {"coordinates":[117.577,35.622],"type":"Point"}
}