{
  "type": "Feature",
  "properties": {
    "gn:admin1_code":"31.0",
    "gn:asciiname":"Zhenhai",
    "gn:country_code":"CN",
    "gn:dem":6,
    "gn:feature_class":"P",
    "gn:feature_code":"PPL",
    "gn:name":"Zhenhai",
    "gn:population":0,
    "gn:timezone":"Asia/Shanghai",
    "iso:country":"CN",
    "name:zho_x_preferred":[
        "\u9547\u6d77"
    ],
    "wof:name":"Zhenhai",
    "wof:placetype":"locality"
},
  "geometry": {"coordinates":[109.07098999999999,18.37135],"type":"Point"}
}