{
  "type": "Feature",
  "properties": {
    "gn:admin1_code":"8.0",
    "gn:asciiname":"Qingniandian",
    "gn:country_code":"CN",
    "gn:dem":607,
    "gn:feature_class":"P",
    "gn:feature_code":"PPL",
    "gn:name":"Qingniandian",
    "gn:population":0,
    "gn:timezone":"Asia/Shanghai",
    "iso:country":"CN",
    "name:zho_x_preferred":[
        "\u9752\u5e74\u70b9"
    ],
    "wof:name":"Qingniandian",
    "wof:placetype":"locality"
},
  "geometry": {"coordinates":[130.81196,44.85621],"type":"Point"}
}