{
  "type": "Feature",
  "properties": {
    "gn:admin1_code":"18",
    "gn:asciiname":"Qingcaipo",
    "gn:country_code":"CN",
    "gn:dem":1088,
    "gn:feature_class":"P",
    "gn:feature_code":"PPL",
    "gn:name":"Qingcaipo",
    "gn:population":0,
    "gn:timezone":"Asia/Shanghai",
    "iso:country":"CN",
    "name:zho_x_preferred":[
        "\u9752\u83dc\u5761"
    ],
    "wof:name":"Qingcaipo",
    "wof:placetype":"locality"
},
  "geometry": {"coordinates":[106.294,28.3223],"type":"Point"}
}