{
  "type": "Feature",
  "properties": {
    "gn:admin1_code":"10.0",
    "gn:asciiname":"Wuzhuangzi Beipai",
    "gn:country_code":"CN",
    "gn:dem":9,
    "gn:feature_class":"P",
    "gn:feature_code":"PPL",
    "gn:name":"Wuzhuangzi Beipai",
    "gn:population":0,
    "gn:timezone":"Asia/Shanghai",
    "iso:country":"CN",
    "name:zho_x_preferred":[
        "\u5434\u5e84\u5b50\u5317\u6392"
    ],
    "wof:name":"Wuzhuangzi Beipai",
    "wof:placetype":"locality"
},
  "geometry": {"coordinates":[117.10899999999999,38.4185],"type":"Point"}
}