{
  "type": "Feature",
  "properties": {
    "gn:admin1_code":"10",
    "gn:asciiname":"Beixiabu",
    "gn:country_code":"CN",
    "gn:dem":46,
    "gn:feature_class":"P",
    "gn:feature_code":"PPL",
    "gn:name":"Beixiabu",
    "gn:population":0,
    "gn:timezone":"Asia/Shanghai",
    "iso:country":"CN",
    "name:zho_x_preferred":[
        "\u5317\u4e0b\u5821"
    ],
    "wof:name":"Beixiabu",
    "wof:placetype":"locality"
},
  "geometry": {"coordinates":[115.09238999999999,36.57113],"type":"Point"}
}