{
  "type": "Feature",
  "properties": {
    "gn:admin1_code":"14.0",
    "gn:asciiname":"Dongzhu",
    "gn:country_code":"CN",
    "gn:dem":2780,
    "gn:feature_class":"P",
    "gn:feature_code":"PPL",
    "gn:name":"Dongzhu",
    "gn:population":0,
    "gn:timezone":"Asia/Urumqi",
    "iso:country":"CN",
    "name:zho_x_preferred":[
        "\u51ac\u7af9"
    ],
    "name:zho_x_variant":[
        "\u4e1c\u6e1a\u8857\u9053"
    ],
    "wof:name":"Dongzhu",
    "wof:placetype":"locality"
},
  "geometry": {"coordinates":[94.41276000000001,30.3603],"type":"Point"}
}