{
  "type": "Feature",
  "properties": {
    "gn:admin1_code":"25.0",
    "gn:asciiname":"Xiaoguozhuangcun",
    "gn:country_code":"CN",
    "gn:dem":44,
    "gn:feature_class":"P",
    "gn:feature_code":"PPL",
    "gn:name":"Xiaoguozhuangcun",
    "gn:population":0,
    "gn:timezone":"Asia/Shanghai",
    "iso:country":"CN",
    "name:zho_x_preferred":[
        "\u8096\u90ed\u5e84\u6751"
    ],
    "wof:name":"Xiaoguozhuangcun",
    "wof:placetype":"locality"
},
  "geometry": {"coordinates":[115.53787,36.16183],"type":"Point"}
}