{
  "type": "Feature",
  "properties": {
    "gn:admin1_code":"8.0",
    "gn:asciiname":"Changshengcun",
    "gn:country_code":"CN",
    "gn:dem":202,
    "gn:feature_class":"P",
    "gn:feature_code":"PPL",
    "gn:name":"Changshengcun",
    "gn:population":0,
    "gn:timezone":"Asia/Shanghai",
    "iso:country":"CN",
    "name:zho_x_preferred":[
        "\u660c\u76db\u6751"
    ],
    "wof:name":"Changshengcun",
    "wof:placetype":"locality"
},
  "geometry": {"coordinates":[125.62963000000001,46.03417],"type":"Point"}
}