{
  "type": "Feature",
  "properties": {
    "gn:admin1_code":"11.0",
    "gn:asciiname":"Jingxiali",
    "gn:country_code":"CN",
    "gn:dem":123,
    "gn:feature_class":"P",
    "gn:feature_code":"PPL",
    "gn:name":"Jingxiali",
    "gn:population":0,
    "gn:timezone":"Asia/Shanghai",
    "iso:country":"CN",
    "name:zho_x_preferred":[
        "\u4e95\u4e0b\u91cc"
    ],
    "wof:name":"Jingxiali",
    "wof:placetype":"locality"
},
  "geometry": {"coordinates":[113.90062,28.3372],"type":"Point"}
}