{
  "type": "Feature",
  "properties": {
    "gn:admin1_code":"10.0",
    "gn:asciiname":"Niugouzhang",
    "gn:country_code":"CN",
    "gn:dem":949,
    "gn:feature_class":"P",
    "gn:feature_code":"PPL",
    "gn:name":"Niugouzhang",
    "gn:population":0,
    "gn:timezone":"Asia/Shanghai",
    "iso:country":"CN",
    "name:zho_x_preferred":[
        "\u725b\u6c9f\u638c"
    ],
    "wof:name":"Niugouzhang",
    "wof:placetype":"locality"
},
  "geometry": {"coordinates":[114.89431,39.32805],"type":"Point"}
}