{
  "type": "Feature",
  "properties": {
    "gn:country":"CN",
    "gn:fcode":"PPL",
    "gn:population":0,
    "iso:country":"CN",
    "name:ceb_x_preferred":[
        "Qingpu Qu"
    ],
    "name:ces_x_preferred":[
        "\u010cching-pchu"
    ],
    "name:cym_x_preferred":[
        "Ardal Qingpu"
    ],
    "name:deu_x_preferred":[
        "Qingpu"
    ],
    "name:eng_x_preferred":[
        "Qingpu District"
    ],
    "name:eus_x_preferred":[
        "Qingpu Barrutia"
    ],
    "name:fas_x_preferred":[
        "\u06a9\u06cc\u0646\u06af\u067e\u0648"
    ],
    "name:gan_x_preferred":[
        "\u9752\u6d66\u533a"
    ],
    "name:jpn_x_preferred":[
        "\u9752\u6d66\u533a"
    ],
    "name:kor_x_preferred":[
        "\uce6d\ud478\uad6c"
    ],
    "name:nan_x_preferred":[
        "Chheng-ph\u00f3\u0358-khu"
    ],
    "name:nld_x_preferred":[
        "Qingpu"
    ],
    "name:nob_x_preferred":[
        "Qingpu"
    ],
    "name:rus_x_preferred":[
        "\u0426\u0438\u043d\u043f\u0443"
    ],
    "name:spa_x_preferred":[
        "Qingpu"
    ],
    "name:swe_x_preferred":[
        "Qingpu"
    ],
    "name:tur_x_preferred":[
        "Qingpu"
    ],
    "name:ukr_x_preferred":[
        "\u0420\u0430\u0439\u043e\u043d \u0426\u0456\u043d\u043f\u0443"
    ],
    "name:und_x_variant":[
        "Zhujiajiao"
    ],
    "name:vie_x_preferred":[
        "Thanh Ph\u1ed1"
    ],
    "name:wuu_x_preferred":[
        "\u9752\u6d66\u533a"
    ],
    "name:yue_x_preferred":[
        "\u9752\u6d66\u5340"
    ],
    "name:zho_x_preferred":[
        "\u9752\u6d66\u533a"
    ],
    "qs:name":"\u6731\u5bb6\u89d2\u9547",
    "qs:name_adm0":"\u4e2d\u570b",
    "qs:name_adm1":"\u4e0a\u6d77\u76f4\u8f96\u5e02",
    "qs:photos":2,
    "qs:photos_1k":1,
    "qs:photos_9k":1,
    "qs:photos_9r":1,
    "qs:photos_all":2,
    "qs:photos_sr":1,
    "qs:placetype":"Suburb",
    "qs:pop_sr":"0",
    "wd:wordcount":547,
    "wof:name":"\u6731\u5bb6\u89d2\u9547",
    "wof:placetype":"neighbourhood",
    "wof:population":0
},
  "geometry": {"coordinates":[120.42556999999999,30.47984],"type":"Point"}
}