{
  "type": "Feature",
  "properties": {
    "gn:admin1_code":"12.0",
    "gn:asciiname":"Chepanjia",
    "gn:country_code":"CN",
    "gn:dem":1137,
    "gn:feature_class":"P",
    "gn:feature_code":"PPL",
    "gn:name":"Chepanjia",
    "gn:population":0,
    "gn:timezone":"Asia/Shanghai",
    "iso:country":"CN",
    "name:zho_x_preferred":[
        "\u8f66\u76d8\u67b6"
    ],
    "wof:name":"Chepanjia",
    "wof:placetype":"locality"
},
  "geometry": {"coordinates":[109.89354,31.9299],"type":"Point"}
}