{
  "type": "Feature",
  "properties": {
    "gn:admin1_code":"01",
    "gn:asciiname":"Hongtan",
    "gn:cc2":"CN",
    "gn:country_code":"CN",
    "gn:dem":324,
    "gn:feature_class":"P",
    "gn:feature_code":"PPL",
    "gn:name":"Hongtan",
    "gn:population":0,
    "gn:timezone":"Asia/Shanghai",
    "iso:country":"CN",
    "name:und_x_variant":[
        "T\u2019ang-ts\u2019un",
        "Hung-t\u2019an",
        "Hongtan"
    ],
    "wof:name":"Hongtan",
    "wof:placetype":"locality"
},
  "geometry": {"coordinates":[117.76667,30.08333],"type":"Point"}
}