{
  "type": "Feature",
  "properties": {
    "gn:admin1_code":"25.0",
    "gn:asciiname":"Linjiamiaozi",
    "gn:country_code":"CN",
    "gn:dem":30,
    "gn:feature_class":"P",
    "gn:feature_code":"PPL",
    "gn:name":"Linjiamiaozi",
    "gn:population":0,
    "gn:timezone":"Asia/Shanghai",
    "iso:country":"CN",
    "name:zho_x_preferred":[
        "\u6797\u5bb6\u5e99\u5b50"
    ],
    "wof:name":"Linjiamiaozi",
    "wof:placetype":"locality"
},
  "geometry": {"coordinates":[119.58114,36.29554],"type":"Point"}
}