{
  "type": "Feature",
  "properties": {
    "gn:admin1_code":"19.0",
    "gn:asciiname":"Changlinzi",
    "gn:country_code":"CN",
    "gn:dem":10,
    "gn:feature_class":"P",
    "gn:feature_code":"PPL",
    "gn:name":"Changlinzi",
    "gn:population":0,
    "gn:timezone":"Asia/Shanghai",
    "iso:country":"CN",
    "name:zho_x_preferred":[
        "\u957f\u6797\u5b50"
    ],
    "wof:name":"Changlinzi",
    "wof:placetype":"locality"
},
  "geometry": {"coordinates":[122.63437999999999,41.31727],"type":"Point"}
}