{
  "type": "Feature",
  "properties": {
    "gn:admin1_code":"8.0",
    "gn:asciiname":"Ruiguangcun",
    "gn:country_code":"CN",
    "gn:dem":151,
    "gn:feature_class":"P",
    "gn:feature_code":"PPL",
    "gn:name":"Ruiguangcun",
    "gn:population":0,
    "gn:timezone":"Asia/Shanghai",
    "iso:country":"CN",
    "name:zho_x_preferred":[
        "\u745e\u5149\u6751"
    ],
    "wof:name":"Ruiguangcun",
    "wof:placetype":"locality"
},
  "geometry": {"coordinates":[125.73202000000001,46.18947],"type":"Point"}
}