{
  "type": "Feature",
  "properties": {
    "gn:admin1_code":"11.0",
    "gn:asciiname":"Bajiawan",
    "gn:country_code":"CN",
    "gn:dem":31,
    "gn:feature_class":"P",
    "gn:feature_code":"PPL",
    "gn:name":"Bajiawan",
    "gn:population":0,
    "gn:timezone":"Asia/Shanghai",
    "iso:country":"CN",
    "name:zho_x_preferred":[
        "\u516b\u5bb6\u6e7e"
    ],
    "wof:name":"Bajiawan",
    "wof:placetype":"locality"
},
  "geometry": {"coordinates":[112.19925000000001,29.36631],"type":"Point"}
}