{
  "type": "Feature",
  "properties": {
    "gn:admin1_code":"11",
    "gn:asciiname":"Yintang",
    "gn:cc2":"CN",
    "gn:country_code":"CN",
    "gn:dem":103,
    "gn:feature_class":"P",
    "gn:feature_code":"PPL",
    "gn:name":"Yintang",
    "gn:population":0,
    "gn:timezone":"Asia/Shanghai",
    "iso:country":"CN",
    "name:und_x_variant":[
        "Baishimiao",
        "Yintang"
    ],
    "wof:name":"Yintang",
    "wof:placetype":"locality"
},
  "geometry": {"coordinates":[112.12417000000001,27.42556],"type":"Point"}
}