{
  "type": "Feature",
  "properties": {
    "gn:admin1_code":"8.0",
    "gn:asciiname":"Guhecun",
    "gn:country_code":"CN",
    "gn:dem":276,
    "gn:feature_class":"P",
    "gn:feature_code":"PPL",
    "gn:name":"Guhecun",
    "gn:population":0,
    "gn:timezone":"Asia/Shanghai",
    "iso:country":"CN",
    "name:zho_x_preferred":[
        "\u4f30\u6cb3\u6751"
    ],
    "wof:name":"Guhecun",
    "wof:placetype":"locality"
},
  "geometry": {"coordinates":[127.5129,49.16401],"type":"Point"}
}