{
  "type": "Feature",
  "properties": {
    "gn:admin1_code":"14.0",
    "gn:asciiname":"Aimori",
    "gn:country_code":"CN",
    "gn:dem":4032,
    "gn:feature_class":"P",
    "gn:feature_code":"PPL",
    "gn:name":"Aimori",
    "gn:population":0,
    "gn:timezone":"Asia/Urumqi",
    "iso:country":"CN",
    "name:zho_x_preferred":[
        "\u9698\u83ab\u65e5"
    ],
    "wof:name":"Aimori",
    "wof:placetype":"locality"
},
  "geometry": {"coordinates":[91.81910000000001,29.20208],"type":"Point"}
}