{
  "type": "Feature",
  "properties": {
    "gn:admin1_code":"24.0",
    "gn:asciiname":"Xingwang",
    "gn:country_code":"CN",
    "gn:dem":978,
    "gn:feature_class":"P",
    "gn:feature_code":"PPL",
    "gn:name":"Xingwang",
    "gn:population":0,
    "gn:timezone":"Asia/Shanghai",
    "iso:country":"CN",
    "name:und_x_variant":[
        "\u5174\u65fa"
    ],
    "wof:name":"Xingwang",
    "wof:placetype":"locality"
},
  "geometry": {"coordinates":[113.28838,39.77914000000001],"type":"Point"}
}