{
  "type": "Feature",
  "properties": {
    "gn:admin1_code":"30.0",
    "gn:asciiname":"Lingtoutang",
    "gn:country_code":"CN",
    "gn:dem":327,
    "gn:feature_class":"P",
    "gn:feature_code":"PPL",
    "gn:name":"Lingtoutang",
    "gn:population":0,
    "gn:timezone":"Asia/Shanghai",
    "iso:country":"CN",
    "name:zho_x_preferred":[
        "Lingtoutang"
    ],
    "name:zho_x_variant":[
        "\u5cad\u5934\u5858"
    ],
    "wof:name":"Lingtoutang",
    "wof:placetype":"locality"
},
  "geometry": {"coordinates":[112.57417,24.47306],"type":"Point"}
}