{
  "type": "Feature",
  "properties": {
    "gn:admin1_code":"09",
    "gn:asciiname":"Batai",
    "gn:country_code":"CN",
    "gn:dem":93,
    "gn:feature_class":"P",
    "gn:feature_code":"PPL",
    "gn:name":"Batai",
    "gn:population":0,
    "gn:timezone":"Asia/Shanghai",
    "iso:country":"CN",
    "name:und_x_variant":[
        "Liangbatai",
        "Batai Zhen",
        "Batai"
    ],
    "name:zho_x_preferred":[
        "\u516b\u53f0"
    ],
    "wof:name":"Batai",
    "wof:placetype":"locality"
},
  "geometry": {"coordinates":[113.48972000000001,33.38722],"type":"Point"}
}