{
  "type": "Feature",
  "properties": {
    "gn:admin1_code":"4.0",
    "gn:asciiname":"Zhuangchangcun",
    "gn:country_code":"CN",
    "gn:dem":23,
    "gn:feature_class":"P",
    "gn:feature_code":"PPL",
    "gn:name":"Zhuangchangcun",
    "gn:population":0,
    "gn:timezone":"Asia/Shanghai",
    "iso:country":"CN",
    "name:und_x_variant":[
        "Zhuangchang",
        "Zhuangchangcun"
    ],
    "name:zho_x_preferred":[
        "\u5e84\u573a"
    ],
    "name:zho_x_variant":[
        "\u5e84\u573a\u6751"
    ],
    "wof:name":"Zhuangchangcun",
    "wof:placetype":"locality"
},
  "geometry": {"coordinates":[118.04169,34.23572],"type":"Point"}
}