{
  "type": "Feature",
  "properties": {
    "gn:admin1_code":"7.0",
    "gn:asciiname":"Yekang",
    "gn:country_code":"CN",
    "gn:dem":202,
    "gn:feature_class":"P",
    "gn:feature_code":"PPL",
    "gn:name":"Yekang",
    "gn:population":0,
    "gn:timezone":"Asia/Shanghai",
    "iso:country":"CN",
    "name:und_x_variant":[
        "\u53f6\u5eb7"
    ],
    "name:zho_x_preferred":[
        "\u53f6\u5eb7"
    ],
    "wof:name":"Yekang",
    "wof:placetype":"locality"
},
  "geometry": {"coordinates":[118.31010999999999,26.80087],"type":"Point"}
}