{
  "type": "Feature",
  "properties": {
    "gn:admin1_code":"29.0",
    "gn:asciiname":"Xinpengzi",
    "gn:country_code":"CN",
    "gn:dem":2283,
    "gn:feature_class":"P",
    "gn:feature_code":"PPL",
    "gn:name":"Xinpengzi",
    "gn:population":0,
    "gn:timezone":"Asia/Shanghai",
    "iso:country":"CN",
    "name:zho_x_preferred":[
        "\u65b0\u68da\u5b50"
    ],
    "wof:name":"Xinpengzi",
    "wof:placetype":"locality"
},
  "geometry": {"coordinates":[103.447,27.0849],"type":"Point"}
}