{
  "type": "Feature",
  "properties": {
    "gn:admin1_code":"3.0",
    "gn:asciiname":"Xiaolongli",
    "gn:country_code":"CN",
    "gn:dem":77,
    "gn:feature_class":"P",
    "gn:feature_code":"PPL",
    "gn:name":"Xiaolongli",
    "gn:population":0,
    "gn:timezone":"Asia/Shanghai",
    "iso:country":"CN",
    "name:zho_x_preferred":[
        "\u5c0f\u5784\u91cc"
    ],
    "wof:name":"Xiaolongli",
    "wof:placetype":"locality"
},
  "geometry": {"coordinates":[115.20399999999999,28.7033],"type":"Point"}
}