{
  "type": "Feature",
  "properties": {
    "gn:admin1_code":"25",
    "gn:asciiname":"Datiandi",
    "gn:country_code":"CN",
    "gn:dem":212,
    "gn:feature_class":"P",
    "gn:feature_code":"PPL",
    "gn:name":"Datiandi",
    "gn:population":0,
    "gn:timezone":"Asia/Shanghai",
    "iso:country":"CN",
    "name:zho_x_preferred":[
        "\u5927\u7530\u5730"
    ],
    "wof:name":"Datiandi",
    "wof:placetype":"locality"
},
  "geometry": {"coordinates":[117.56399999999999,35.2127],"type":"Point"}
}