{
  "type": "Feature",
  "properties": {
    "gn:admin1_code":"7.0",
    "gn:asciiname":"Xianqiang",
    "gn:country_code":"CN",
    "gn:dem":25,
    "gn:feature_class":"P",
    "gn:feature_code":"PPL",
    "gn:name":"Xianqiang",
    "gn:population":0,
    "gn:timezone":"Asia/Shanghai",
    "iso:country":"CN",
    "name:zho_x_preferred":[
        "\u5148\u5f3a"
    ],
    "wof:name":"Xianqiang",
    "wof:placetype":"locality"
},
  "geometry": {"coordinates":[119.44450000000001,25.72399],"type":"Point"}
}