{
  "type": "Feature",
  "properties": {
    "gn:admin1_code":"33.0",
    "gn:asciiname":"Wufeng",
    "gn:country_code":"CN",
    "gn:dem":1056,
    "gn:feature_class":"P",
    "gn:feature_code":"PPL",
    "gn:name":"Wufeng",
    "gn:population":0,
    "gn:timezone":"Asia/Shanghai",
    "iso:country":"CN",
    "name:ceb_x_preferred":[
        "Wufeng"
    ],
    "name:deu_x_preferred":[
        "Wufeng"
    ],
    "name:fra_x_preferred":[
        "Wufeng"
    ],
    "name:pol_x_preferred":[
        "Wufeng"
    ],
    "name:zho_x_preferred":[
        "\u4e94\u5cf0"
    ],
    "wof:name":"Wufeng",
    "wof:placetype":"locality"
},
  "geometry": {"coordinates":[108.61551,31.91145],"type":"Point"}
}