{
  "type": "Feature",
  "properties": {
    "gn:admin1_code":"19.0",
    "gn:asciiname":"Lijiagou",
    "gn:country_code":"CN",
    "gn:dem":258,
    "gn:feature_class":"P",
    "gn:feature_code":"PPL",
    "gn:name":"Lijiagou",
    "gn:population":0,
    "gn:timezone":"Asia/Shanghai",
    "iso:country":"CN",
    "name:zho_x_preferred":[
        "\u674e\u5bb6\u6c9f"
    ],
    "wof:name":"Lijiagou",
    "wof:placetype":"locality"
},
  "geometry": {"coordinates":[120.63,41.1554],"type":"Point"}
}