{
  "type": "Feature",
  "properties": {
    "gn:admin1_code":"1.0",
    "gn:asciiname":"Yaohancun",
    "gn:country_code":"CN",
    "gn:dem":23,
    "gn:feature_class":"P",
    "gn:feature_code":"PPL",
    "gn:name":"Yaohancun",
    "gn:population":0,
    "gn:timezone":"Asia/Shanghai",
    "iso:country":"CN",
    "name:zho_x_preferred":[
        "\u59da\u97e9\u6751"
    ],
    "wof:name":"Yaohancun",
    "wof:placetype":"locality"
},
  "geometry": {"coordinates":[117.6088,33.3345],"type":"Point"}
}