{
  "type": "Feature",
  "properties": {
    "gn:admin1_code":"30.0",
    "gn:asciiname":"Tianxinli",
    "gn:country_code":"CN",
    "gn:dem":34,
    "gn:feature_class":"P",
    "gn:feature_code":"PPL",
    "gn:name":"Tianxinli",
    "gn:population":0,
    "gn:timezone":"Asia/Shanghai",
    "iso:country":"CN",
    "name:zho_x_preferred":[
        "\u7530\u5fc3\u91cc"
    ],
    "wof:name":"Tianxinli",
    "wof:placetype":"locality"
},
  "geometry": {"coordinates":[113.49526000000002,23.75643],"type":"Point"}
}