{
  "type": "Feature",
  "properties": {
    "gn:admin1_code":"16.0",
    "gn:asciiname":"Zhulong",
    "gn:country_code":"CN",
    "gn:dem":446,
    "gn:feature_class":"P",
    "gn:feature_code":"PPL",
    "gn:name":"Zhulong",
    "gn:population":0,
    "gn:timezone":"Asia/Shanghai",
    "iso:country":"CN",
    "name:zho_x_preferred":[
        "\u9010\u9f99"
    ],
    "wof:name":"Zhulong",
    "wof:placetype":"locality"
},
  "geometry": {"coordinates":[107.08499999999999,23.0859],"type":"Point"}
}