{
  "type": "Feature",
  "properties": {
    "gn:admin1_code":"18",
    "gn:asciiname":"Cheyaoka",
    "gn:country_code":"CN",
    "gn:dem":2259,
    "gn:feature_class":"P",
    "gn:feature_code":"PPL",
    "gn:name":"Cheyaoka",
    "gn:population":0,
    "gn:timezone":"Asia/Shanghai",
    "iso:country":"CN",
    "name:und_x_variant":[
        "Chemeka",
        "Cheyaoka"
    ],
    "name:zho_x_preferred":[
        "\u626f\u4e48\u5361"
    ],
    "wof:name":"Cheyaoka",
    "wof:placetype":"locality"
},
  "geometry": {"coordinates":[103.946,26.9441],"type":"Point"}
}