{
  "type": "Feature",
  "properties": {
    "gn:admin1_code":"24.0",
    "gn:asciiname":"Nanluozhuang",
    "gn:country_code":"CN",
    "gn:dem":1028,
    "gn:feature_class":"P",
    "gn:feature_code":"PPL",
    "gn:name":"Nanluozhuang",
    "gn:population":0,
    "gn:timezone":"Asia/Shanghai",
    "iso:country":"CN",
    "name:zho_x_preferred":[
        "\u5357\u7f57\u5e84"
    ],
    "wof:name":"Nanluozhuang",
    "wof:placetype":"locality"
},
  "geometry": {"coordinates":[112.76239,39.41692000000001],"type":"Point"}
}