{
  "type": "Feature",
  "properties": {
    "gn:admin1_code":"29.0",
    "gn:asciiname":"Niuwangtang",
    "gn:country_code":"CN",
    "gn:dem":1396,
    "gn:feature_class":"P",
    "gn:feature_code":"PPL",
    "gn:name":"Niuwangtang",
    "gn:population":0,
    "gn:timezone":"Asia/Shanghai",
    "iso:country":"CN",
    "name:zho_x_preferred":[
        "\u725b\u6c6a\u5858"
    ],
    "wof:name":"Niuwangtang",
    "wof:placetype":"locality"
},
  "geometry": {"coordinates":[99.0722,24.5607],"type":"Point"}
}