{
  "type": "Feature",
  "properties": {
    "gn:admin1_code":"26",
    "gn:asciiname":"Lihoucun",
    "gn:country_code":"CN",
    "gn:dem":598,
    "gn:feature_class":"P",
    "gn:feature_code":"PPL",
    "gn:name":"Lihoucun",
    "gn:population":0,
    "gn:timezone":"Asia/Shanghai",
    "iso:country":"CN",
    "name:und_x_variant":[
        "\u674e\u540e\u6751",
        "Lihoucun"
    ],
    "wof:name":"Lihoucun",
    "wof:placetype":"locality"
},
  "geometry": {"coordinates":[109.35302,34.16936],"type":"Point"}
}