{
  "type": "Feature",
  "properties": {
    "gn:admin1_code":"11.0",
    "gn:asciiname":"Dajiang",
    "gn:country_code":"CN",
    "gn:dem":262,
    "gn:feature_class":"P",
    "gn:feature_code":"PPL",
    "gn:name":"Dajiang",
    "gn:population":0,
    "gn:timezone":"Asia/Shanghai",
    "iso:country":"CN",
    "name:zho_x_preferred":[
        "\u5927\u5c06"
    ],
    "wof:name":"Dajiang",
    "wof:placetype":"locality"
},
  "geometry": {"coordinates":[111.61793,28.1444],"type":"Point"}
}