{
  "type": "Feature",
  "properties": {
    "gn:admin1_code":"33.0",
    "gn:asciiname":"Laoguang",
    "gn:country_code":"CN",
    "gn:dem":185,
    "gn:feature_class":"P",
    "gn:feature_code":"PPL",
    "gn:name":"Laoguang",
    "gn:population":0,
    "gn:timezone":"Asia/Shanghai",
    "iso:country":"CN",
    "name:zho_x_preferred":[
        "\u52b3\u5149"
    ],
    "wof:name":"Laoguang",
    "wof:placetype":"locality"
},
  "geometry": {"coordinates":[106.67328000000001,29.63392],"type":"Point"}
}