{
  "type": "Feature",
  "properties": {
    "gn:admin1_code":"9.0",
    "gn:asciiname":"Minggoukou",
    "gn:country_code":"CN",
    "gn:dem":1023,
    "gn:feature_class":"P",
    "gn:feature_code":"PPL",
    "gn:name":"Minggoukou",
    "gn:population":0,
    "gn:timezone":"Asia/Shanghai",
    "iso:country":"CN",
    "name:zho_x_preferred":[
        "\u660e\u6c9f\u53e3"
    ],
    "wof:name":"Minggoukou",
    "wof:placetype":"locality"
},
  "geometry": {"coordinates":[110.7625,33.82621],"type":"Point"}
}