{
  "type": "Feature",
  "properties": {
    "gn:admin1_code":"03",
    "gn:asciiname":"Huangcun",
    "gn:country_code":"CN",
    "gn:dem":442,
    "gn:feature_class":"P",
    "gn:feature_code":"PPL",
    "gn:name":"Huangcun",
    "gn:population":0,
    "gn:timezone":"Asia/Shanghai",
    "iso:country":"CN",
    "name:zho_x_preferred":[
        "Huang-ts\u2019un"
    ],
    "name:zho_x_variant":[
        "\u7bc1\u6751"
    ],
    "wof:name":"Huangcun",
    "wof:placetype":"locality"
},
  "geometry": {"coordinates":[117.77397999999999,27.95533],"type":"Point"}
}