{
  "type": "Feature",
  "properties": {
    "gn:admin1_code":"26.0",
    "gn:asciiname":"Liaodi",
    "gn:country_code":"CN",
    "gn:dem":632,
    "gn:feature_class":"P",
    "gn:feature_code":"PPL",
    "gn:name":"Liaodi",
    "gn:population":0,
    "gn:timezone":"Asia/Shanghai",
    "iso:country":"CN",
    "name:und_x_variant":[
        "\u6599\u5730"
    ],
    "wof:name":"Liaodi",
    "wof:placetype":"locality"
},
  "geometry": {"coordinates":[107.78614,34.33222],"type":"Point"}
}