{
  "type": "Feature",
  "properties": {
    "gn:admin1_code":"6.0",
    "gn:asciiname":"Aduo",
    "gn:country_code":"CN",
    "gn:dem":4192,
    "gn:feature_class":"P",
    "gn:feature_code":"PPLA4",
    "gn:name":"Aduo",
    "gn:population":0,
    "gn:timezone":"Asia/Urumqi",
    "iso:country":"CN",
    "name:und_x_variant":[
        "Aduo Xiang"
    ],
    "name:zho_x_preferred":[
        "\u963f\u591a"
    ],
    "name:zho_x_variant":[
        "\u963f\u591a\u4e61"
    ],
    "wof:name":"Aduo",
    "wof:placetype":"locality"
},
  "geometry": {"coordinates":[95.04943,32.93999],"type":"Point"}
}