{
  "type": "Feature",
  "properties": {
    "gn:admin1_code":"9.0",
    "gn:asciiname":"Zhangguanying",
    "gn:country_code":"CN",
    "gn:dem":93,
    "gn:feature_class":"P",
    "gn:feature_code":"PPL",
    "gn:name":"Zhangguanying",
    "gn:population":0,
    "gn:timezone":"Asia/Shanghai",
    "iso:country":"CN",
    "name:zho_x_preferred":[
        "\u5f20\u5b98\u8425"
    ],
    "wof:name":"Zhangguanying",
    "wof:placetype":"locality"
},
  "geometry": {"coordinates":[112.59707,32.57617],"type":"Point"}
}