{
  "type": "Feature",
  "properties": {
    "gn:admin1_code":"4.0",
    "gn:asciiname":"Huaihecun",
    "gn:country_code":"CN",
    "gn:dem":12,
    "gn:feature_class":"P",
    "gn:feature_code":"PPL",
    "gn:name":"Huaihecun",
    "gn:population":0,
    "gn:timezone":"Asia/Shanghai",
    "iso:country":"CN",
    "name:zho_x_preferred":[
        "\u6dee\u6cb3\u6751"
    ],
    "wof:name":"Huaihecun",
    "wof:placetype":"locality"
},
  "geometry": {"coordinates":[118.81873,33.94171],"type":"Point"}
}