{
  "type": "Feature",
  "properties": {
    "gn:admin1_code":"29.0",
    "gn:asciiname":"Wulacun",
    "gn:country_code":"CN",
    "gn:dem":1893,
    "gn:feature_class":"P",
    "gn:feature_code":"PPL",
    "gn:name":"Wulacun",
    "gn:population":0,
    "gn:timezone":"Asia/Shanghai",
    "iso:country":"CN",
    "name:zho_x_preferred":[
        "\u4e94\u814a\u6751"
    ],
    "wof:name":"Wulacun",
    "wof:placetype":"locality"
},
  "geometry": {"coordinates":[102.76900000000001,24.9329],"type":"Point"}
}