{
  "type": "Feature",
  "properties": {
    "gn:admin1_code":"30",
    "gn:asciiname":"Qinggouping",
    "gn:country_code":"CN",
    "gn:dem":271,
    "gn:feature_class":"P",
    "gn:feature_code":"PPL",
    "gn:name":"Qinggouping",
    "gn:population":0,
    "gn:timezone":"Asia/Shanghai",
    "iso:country":"CN",
    "name:zho_x_preferred":[
        "\u9752\u6c9f\u576a"
    ],
    "wof:name":"Qinggouping",
    "wof:placetype":"locality"
},
  "geometry": {"coordinates":[116.30817,23.99012],"type":"Point"}
}