{
  "type": "Feature",
  "properties": {
    "gn:admin1_code":"32.0",
    "gn:asciiname":"Luoha",
    "gn:country_code":"CN",
    "gn:dem":2431,
    "gn:feature_class":"P",
    "gn:feature_code":"PPL",
    "gn:name":"Luoha",
    "gn:population":0,
    "gn:timezone":"Asia/Shanghai",
    "iso:country":"CN",
    "name:zho_x_preferred":[
        "\u843d\u54c8"
    ],
    "wof:name":"Luoha",
    "wof:placetype":"locality"
},
  "geometry": {"coordinates":[102.925,27.9621],"type":"Point"}
}