{
  "type": "Feature",
  "properties": {
    "gn:admin1_code":"7.0",
    "gn:asciiname":"Yangliba",
    "gn:country_code":"CN",
    "gn:dem":440,
    "gn:feature_class":"P",
    "gn:feature_code":"PPL",
    "gn:name":"Yangliba",
    "gn:population":0,
    "gn:timezone":"Asia/Shanghai",
    "iso:country":"CN",
    "name:zho_x_preferred":[
        "\u6d0b\u5229\u575d"
    ],
    "wof:name":"Yangliba",
    "wof:placetype":"locality"
},
  "geometry": {"coordinates":[116.63347,25.65958],"type":"Point"}
}