{
  "type": "Feature",
  "properties": {
    "gn:admin1_code":"26.0",
    "gn:asciiname":"Changliangshang",
    "gn:country_code":"CN",
    "gn:dem":1369,
    "gn:feature_class":"P",
    "gn:feature_code":"PPL",
    "gn:name":"Changliangshang",
    "gn:population":0,
    "gn:timezone":"Asia/Shanghai",
    "iso:country":"CN",
    "name:zho_x_preferred":[
        "\u957f\u6881\u4e0a"
    ],
    "wof:name":"Changliangshang",
    "wof:placetype":"locality"
},
  "geometry": {"coordinates":[107.92561000000001,32.38274000000001],"type":"Point"}
}