{
  "type": "Feature",
  "properties": {
    "gn:admin1_code":"8.0",
    "gn:asciiname":"Dongxinfa",
    "gn:country_code":"CN",
    "gn:dem":189,
    "gn:feature_class":"P",
    "gn:feature_code":"PPL",
    "gn:name":"Dongxinfa",
    "gn:population":0,
    "gn:timezone":"Asia/Shanghai",
    "iso:country":"CN",
    "name:zho_x_preferred":[
        "\u4e1c\u65b0\u53d1"
    ],
    "wof:name":"Dongxinfa",
    "wof:placetype":"locality"
},
  "geometry": {"coordinates":[127.50422,44.95412],"type":"Point"}
}