{
  "type": "Feature",
  "properties": {
    "gn:admin1_code":"12.0",
    "gn:asciiname":"Mazongling",
    "gn:country_code":"CN",
    "gn:dem":870,
    "gn:feature_class":"P",
    "gn:feature_code":"PPL",
    "gn:name":"Mazongling",
    "gn:population":0,
    "gn:timezone":"Asia/Shanghai",
    "iso:country":"CN",
    "name:zho_x_preferred":[
        "\u9a6c\u9b03\u5cad"
    ],
    "wof:name":"Mazongling",
    "wof:placetype":"locality"
},
  "geometry": {"coordinates":[110.86924999999999,30.32509000000001],"type":"Point"}
}