{
  "type": "Feature",
  "properties": {
    "gn:admin1_code":"14.0",
    "gn:asciiname":"Awang",
    "gn:country_code":"CN",
    "gn:dem":4275,
    "gn:feature_class":"P",
    "gn:feature_code":"PPLF",
    "gn:name":"Awang",
    "gn:population":0,
    "gn:timezone":"Asia/Urumqi",
    "iso:country":"CN",
    "name:bod_x_preferred":[
        "Awang"
    ],
    "name:zho_x_preferred":[
        "\u963f\u65fa"
    ],
    "name:zho_x_variant":[
        "Jiaqiong",
        "\u7532\u7a79"
    ],
    "wof:name":"Awang",
    "wof:placetype":"locality"
},
  "geometry": {"coordinates":[98.44969,30.52886],"type":"Point"}
}