{
  "type": "Feature",
  "properties": {
    "gn:admin1_code":"30",
    "gn:asciiname":"Zhazidu",
    "gn:country_code":"CN",
    "gn:dem":264,
    "gn:feature_class":"P",
    "gn:feature_code":"PPL",
    "gn:name":"Zhazidu",
    "gn:population":0,
    "gn:timezone":"Asia/Shanghai",
    "iso:country":"CN",
    "name:zho_x_preferred":[
        "\u6805\u5b50\u809a"
    ],
    "wof:name":"Zhazidu",
    "wof:placetype":"locality"
},
  "geometry": {"coordinates":[116.42395,23.83115],"type":"Point"}
}