{
  "type": "Feature",
  "properties": {
    "gn:admin1_code":"3",
    "gn:asciiname":"Laoweishan",
    "gn:country_code":"CN",
    "gn:dem":219,
    "gn:feature_class":"P",
    "gn:feature_code":"PPL",
    "gn:name":"Laoweishan",
    "gn:population":0,
    "gn:timezone":"Asia/Shanghai",
    "iso:country":"CN",
    "name:zho_x_preferred":[
        "\u8001\u56f4\u5c71"
    ],
    "wof:name":"Laoweishan",
    "wof:placetype":"locality"
},
  "geometry": {"coordinates":[114.72,25.4109],"type":"Point"}
}