{
  "type": "Feature",
  "properties": {
    "gn:admin1_code":"3.0",
    "gn:asciiname":"Huangbai",
    "gn:country_code":"CN",
    "gn:dem":79,
    "gn:feature_class":"P",
    "gn:feature_code":"PPL",
    "gn:name":"Huangbai",
    "gn:population":0,
    "gn:timezone":"Asia/Shanghai",
    "iso:country":"CN",
    "name:und_x_variant":[
        "\u9ec4\u67cf"
    ],
    "wof:name":"Huangbai",
    "wof:placetype":"locality"
},
  "geometry": {"coordinates":[114.76268,27.08054000000001],"type":"Point"}
}