{
  "type": "Feature",
  "properties": {
    "gn:admin1_code":"19.0",
    "gn:asciiname":"Hougangzi",
    "gn:country_code":"CN",
    "gn:dem":51,
    "gn:feature_class":"P",
    "gn:feature_code":"PPL",
    "gn:name":"Hougangzi",
    "gn:population":0,
    "gn:timezone":"Asia/Shanghai",
    "iso:country":"CN",
    "name:zho_x_preferred":[
        "\u540e\u5c97\u5b50"
    ],
    "wof:name":"Hougangzi",
    "wof:placetype":"locality"
},
  "geometry": {"coordinates":[122.726,42.1611],"type":"Point"}
}