{
  "type": "Feature",
  "properties": {
    "gn:admin1_code":"19.0",
    "gn:asciiname":"Zhongwawo",
    "gn:country_code":"CN",
    "gn:dem":111,
    "gn:feature_class":"P",
    "gn:feature_code":"PPL",
    "gn:name":"Zhongwawo",
    "gn:population":0,
    "gn:timezone":"Asia/Shanghai",
    "iso:country":"CN",
    "name:und_x_variant":[
        "\u4e2d\u74e6\u7a9d"
    ],
    "name:zho_x_preferred":[
        "\u4e2d\u74e6\u7a9d"
    ],
    "wof:name":"Zhongwawo",
    "wof:placetype":"locality"
},
  "geometry": {"coordinates":[122.07362000000001,39.73005],"type":"Point"}
}