{
  "type": "Feature",
  "properties": {
    "gn:admin1_code":"9.0",
    "gn:asciiname":"Dengdongcun",
    "gn:country_code":"CN",
    "gn:dem":64,
    "gn:feature_class":"P",
    "gn:feature_code":"PPL",
    "gn:name":"Dengdongcun",
    "gn:population":0,
    "gn:timezone":"Asia/Shanghai",
    "iso:country":"CN",
    "name:zho_x_preferred":[
        "\u9093\u4e1c\u6751"
    ],
    "wof:name":"Dengdongcun",
    "wof:placetype":"locality"
},
  "geometry": {"coordinates":[114.76394000000001,35.25334],"type":"Point"}
}