{
  "type": "Feature",
  "properties": {
    "gn:admin1_code":"8.0",
    "gn:asciiname":"Zhongpingcun",
    "gn:country_code":"CN",
    "gn:dem":132,
    "gn:feature_class":"P",
    "gn:feature_code":"PPL",
    "gn:name":"Zhongpingcun",
    "gn:population":0,
    "gn:timezone":"Asia/Shanghai",
    "iso:country":"CN",
    "name:zho_x_preferred":[
        "\u4e2d\u5e73\u6751"
    ],
    "wof:name":"Zhongpingcun",
    "wof:placetype":"locality"
},
  "geometry": {"coordinates":[131.77477999999999,45.34584],"type":"Point"}
}