{
  "type": "Feature",
  "properties": {
    "gn:admin1_code":"8.0",
    "gn:asciiname":"Furaocun",
    "gn:country_code":"CN",
    "gn:dem":219,
    "gn:feature_class":"P",
    "gn:feature_code":"PPL",
    "gn:name":"Furaocun",
    "gn:population":0,
    "gn:timezone":"Asia/Shanghai",
    "iso:country":"CN",
    "name:zho_x_preferred":[
        "\u5bcc\u9976\u6751"
    ],
    "wof:name":"Furaocun",
    "wof:placetype":"locality"
},
  "geometry": {"coordinates":[125.57426,45.9428],"type":"Point"}
}