{
  "type": "Feature",
  "properties": {
    "gn:admin1_code":"8.0",
    "gn:asciiname":"Qiongbangzitun",
    "gn:country_code":"CN",
    "gn:dem":239,
    "gn:feature_class":"P",
    "gn:feature_code":"PPL",
    "gn:name":"Qiongbangzitun",
    "gn:population":0,
    "gn:timezone":"Asia/Shanghai",
    "iso:country":"CN",
    "name:zho_x_preferred":[
        "\u7a77\u68d2\u5b50\u5c6f"
    ],
    "wof:name":"Qiongbangzitun",
    "wof:placetype":"locality"
},
  "geometry": {"coordinates":[122.77876000000001,47.58616],"type":"Point"}
}