{
  "type": "Feature",
  "properties": {
    "gn:admin1_code":"25",
    "gn:asciiname":"Hongshiban",
    "gn:country_code":"CN",
    "gn:dem":168,
    "gn:feature_class":"P",
    "gn:feature_code":"PPL",
    "gn:name":"Hongshiban",
    "gn:population":0,
    "gn:timezone":"Asia/Shanghai",
    "iso:country":"CN",
    "name:zho_x_preferred":[
        "\u7ea2\u77f3\u677f"
    ],
    "wof:name":"Hongshiban",
    "wof:placetype":"locality"
},
  "geometry": {"coordinates":[117.669,35.8993],"type":"Point"}
}