{
  "type": "Feature",
  "properties": {
    "gn:admin1_code":"29.0",
    "gn:asciiname":"Shangheinitian",
    "gn:country_code":"CN",
    "gn:dem":1513,
    "gn:feature_class":"P",
    "gn:feature_code":"PPL",
    "gn:name":"Shangheinitian",
    "gn:population":0,
    "gn:timezone":"Asia/Shanghai",
    "iso:country":"CN",
    "name:zho_x_preferred":[
        "\u4e0a\u9ed1\u6ce5\u7530"
    ],
    "wof:name":"Shangheinitian",
    "wof:placetype":"locality"
},
  "geometry": {"coordinates":[104.074,24.5265],"type":"Point"}
}