{
  "type": "Feature",
  "properties": {
    "gn:admin1_code":"10",
    "gn:asciiname":"Li'erzhu",
    "gn:country_code":"CN",
    "gn:dem":1385,
    "gn:feature_class":"P",
    "gn:feature_code":"PPL",
    "gn:name":"Li\u2019erzhu",
    "gn:population":0,
    "gn:timezone":"Asia/Shanghai",
    "iso:country":"CN",
    "name:und_x_variant":[
        "Li\u2019erzhu"
    ],
    "name:zho_x_preferred":[
        "\u674e\u4e8c\u73e0"
    ],
    "wof:name":"Li'erzhu",
    "wof:placetype":"locality"
},
  "geometry": {"coordinates":[114.53261999999999,41.62718],"type":"Point"}
}