{
  "type": "Feature",
  "properties": {
    "gn:admin1_code":"5.0",
    "gn:asciiname":"Cang'ancun",
    "gn:country_code":"CN",
    "gn:dem":191,
    "gn:feature_class":"P",
    "gn:feature_code":"PPL",
    "gn:name":"Cang\u2019ancun",
    "gn:population":0,
    "gn:timezone":"Asia/Shanghai",
    "iso:country":"CN",
    "name:und_x_variant":[
        "Cang\u2019ancun"
    ],
    "name:zho_x_preferred":[
        "\u82cd\u5b89\u6751"
    ],
    "wof:name":"Cang'ancun",
    "wof:placetype":"locality"
},
  "geometry": {"coordinates":[129.63312999999999,43.31657],"type":"Point"}
}