{
  "type": "Feature",
  "properties": {
    "gn:admin1_code":"9.0",
    "gn:asciiname":"Weiwan",
    "gn:country_code":"CN",
    "gn:dem":90,
    "gn:feature_class":"P",
    "gn:feature_code":"PPL",
    "gn:name":"Weiwan",
    "gn:population":0,
    "gn:timezone":"Asia/Shanghai",
    "iso:country":"CN",
    "name:und_x_variant":[
        "\u9b4f\u6e7e"
    ],
    "name:zho_x_preferred":[
        "\u9b4f\u6e7e"
    ],
    "wof:name":"Weiwan",
    "wof:placetype":"locality"
},
  "geometry": {"coordinates":[113.75255,33.0115],"type":"Point"}
}