{
  "type": "Feature",
  "properties": {
    "gn:admin1_code":"26.0",
    "gn:asciiname":"Jingshiya",
    "gn:country_code":"CN",
    "gn:dem":1592,
    "gn:feature_class":"P",
    "gn:feature_code":"PPL",
    "gn:name":"Jingshiya",
    "gn:population":0,
    "gn:timezone":"Asia/Shanghai",
    "iso:country":"CN",
    "name:zho_x_preferred":[
        "\u666f\u77f3\u5d16"
    ],
    "wof:name":"Jingshiya",
    "wof:placetype":"locality"
},
  "geometry": {"coordinates":[106.69701000000001,34.98282],"type":"Point"}
}