{
  "type": "Feature",
  "properties": {
    "gn:admin1_code":"19.0",
    "gn:asciiname":"Nantang Jiabucun",
    "gn:country_code":"CN",
    "gn:dem":57,
    "gn:feature_class":"P",
    "gn:feature_code":"PPL",
    "gn:name":"Nantang Jiabucun",
    "gn:population":0,
    "gn:timezone":"Asia/Shanghai",
    "iso:country":"CN",
    "name:zho_x_preferred":[
        "\u5357\u5510\u5bb6\u5821\u6751"
    ],
    "wof:name":"Nantang Jiabucun",
    "wof:placetype":"locality"
},
  "geometry": {"coordinates":[123.42036,40.11203],"type":"Point"}
}