{
  "type": "Feature",
  "properties": {
    "gn:admin1_code":"33.0",
    "gn:asciiname":"Pailou",
    "gn:country_code":"CN",
    "gn:dem":487,
    "gn:feature_class":"P",
    "gn:feature_code":"PPL",
    "gn:name":"Pailou",
    "gn:population":0,
    "gn:timezone":"Asia/Shanghai",
    "iso:country":"CN",
    "name:ceb_x_preferred":[
        "Pailou"
    ],
    "name:pol_x_preferred":[
        "Pailou"
    ],
    "name:swe_x_preferred":[
        "Pailou"
    ],
    "name:zho_x_preferred":[
        "\u724c\u697c"
    ],
    "wof:name":"Pailou",
    "wof:placetype":"locality"
},
  "geometry": {"coordinates":[108.28707,30.65653],"type":"Point"}
}