{
  "type": "Feature",
  "properties": {
    "gn:admin1_code":"18",
    "gn:asciiname":"Lilai",
    "gn:country_code":"CN",
    "gn:dem":1109,
    "gn:feature_class":"P",
    "gn:feature_code":"PPL",
    "gn:name":"Lilai",
    "gn:population":0,
    "gn:timezone":"Asia/Shanghai",
    "iso:country":"CN",
    "name:zho_x_preferred":[
        "\u91cc\u8d56"
    ],
    "wof:name":"Lilai",
    "wof:placetype":"locality"
},
  "geometry": {"coordinates":[106.253,25.2903],"type":"Point"}
}