{
  "type": "Feature",
  "properties": {
    "gn:admin1_code":"26.0",
    "gn:asciiname":"Zhujia Miaogou",
    "gn:country_code":"CN",
    "gn:dem":1133,
    "gn:feature_class":"P",
    "gn:feature_code":"PPL",
    "gn:name":"Zhujia Miaogou",
    "gn:population":0,
    "gn:timezone":"Asia/Shanghai",
    "iso:country":"CN",
    "name:zho_x_preferred":[
        "\u6731\u5bb6\u5e99\u6c9f"
    ],
    "wof:name":"Zhujia Miaogou",
    "wof:placetype":"locality"
},
  "geometry": {"coordinates":[110.408,38.9162],"type":"Point"}
}