{
  "type": "Feature",
  "properties": {
    "gn:admin1_code":"26.0",
    "gn:asciiname":"Erlaijiazihan",
    "gn:country_code":"CN",
    "gn:dem":1292,
    "gn:feature_class":"P",
    "gn:feature_code":"PPL",
    "gn:name":"Erlaijiazihan",
    "gn:population":0,
    "gn:timezone":"Asia/Shanghai",
    "iso:country":"CN",
    "name:zho_x_preferred":[
        "\u8033\u6765\u52a0\u5b50\u6c57"
    ],
    "wof:name":"Erlaijiazihan",
    "wof:placetype":"locality"
},
  "geometry": {"coordinates":[109.75199000000001,38.79748],"type":"Point"}
}