{
  "type": "Feature",
  "properties": {
    "gn:admin1_code":"24.0",
    "gn:asciiname":"Shangchenggou",
    "gn:country_code":"CN",
    "gn:dem":1451,
    "gn:feature_class":"P",
    "gn:feature_code":"PPL",
    "gn:name":"Shangchenggou",
    "gn:population":0,
    "gn:timezone":"Asia/Shanghai",
    "iso:country":"CN",
    "name:zho_x_preferred":[
        "\u4e0a\u79f0\u6c9f"
    ],
    "wof:name":"Shangchenggou",
    "wof:placetype":"locality"
},
  "geometry": {"coordinates":[112.23531,39.51149],"type":"Point"}
}