{
  "type": "Feature",
  "properties": {
    "gn:admin1_code":"30.0",
    "gn:asciiname":"Zhongshan Yilu",
    "gn:country_code":"CN",
    "gn:dem":25,
    "gn:feature_class":"P",
    "gn:feature_code":"PPL",
    "gn:name":"Zhongshan Yilu",
    "gn:population":0,
    "gn:timezone":"Asia/Shanghai",
    "iso:country":"CN",
    "name:zho_x_preferred":[
        "\u4e2d\u5c71\u4e00\u8def"
    ],
    "wof:name":"Zhongshan Yilu",
    "wof:placetype":"locality"
},
  "geometry": {"coordinates":[113.29289,23.12747],"type":"Point"}
}