{
  "type": "Feature",
  "properties": {
    "gn:admin1_code":"30.0",
    "gn:asciiname":"Tiemacun",
    "gn:country_code":"CN",
    "gn:dem":216,
    "gn:feature_class":"P",
    "gn:feature_code":"PPL",
    "gn:name":"Tiemacun",
    "gn:population":0,
    "gn:timezone":"Asia/Shanghai",
    "iso:country":"CN",
    "name:und_x_variant":[
        "Tiemazhai"
    ],
    "name:zho_x_preferred":[
        "\u94c1\u9a6c\u6751"
    ],
    "name:zho_x_variant":[
        "\u94c1\u9a6c\u5be8"
    ],
    "wof:name":"Tiemacun",
    "wof:placetype":"locality"
},
  "geometry": {"coordinates":[115.8378,24.2052],"type":"Point"}
}