{
  "type": "Feature",
  "properties": {
    "gn:admin1_code":"16.0",
    "gn:asciiname":"Helin",
    "gn:country_code":"CN",
    "gn:dem":87,
    "gn:feature_class":"P",
    "gn:feature_code":"PPL",
    "gn:name":"Helin",
    "gn:population":0,
    "gn:timezone":"Asia/Shanghai",
    "iso:country":"CN",
    "name:bel_x_preferred":[
        "\u0425\u0435\u043b\u0456\u043d"
    ],
    "name:ceb_x_preferred":[
        "Helin"
    ],
    "name:chv_x_preferred":[
        "\u0425\u0435\u043b\u0438\u043d"
    ],
    "name:deu_x_preferred":[
        "Helin"
    ],
    "name:epo_x_preferred":[
        "Helin"
    ],
    "name:nno_x_preferred":[
        "Helin"
    ],
    "name:nor_x_preferred":[
        "Helin"
    ],
    "name:rus_x_preferred":[
        "\u0425\u0435\u043b\u0438\u043d"
    ],
    "name:ukr_x_preferred":[
        "\u0413\u0435\u043b\u0456\u043d"
    ],
    "name:zho_x_preferred":[
        "\u9e64\u6797"
    ],
    "wof:name":"Helin",
    "wof:placetype":"locality"
},
  "geometry": {"coordinates":[110.069,22.6807],"type":"Point"}
}