{
  "type": "Feature",
  "properties": {
    "gn:admin1_code":"4.0",
    "gn:asciiname":"Zhangshetang",
    "gn:country_code":"CN",
    "gn:dem":2,
    "gn:feature_class":"P",
    "gn:feature_code":"PPL",
    "gn:name":"Zhangshetang",
    "gn:population":0,
    "gn:timezone":"Asia/Shanghai",
    "iso:country":"CN",
    "name:und_x_variant":[
        "\u5f20\u820d\u5858"
    ],
    "name:zho_x_preferred":[
        "\u5f20\u820d\u5858"
    ],
    "wof:name":"Zhangshetang",
    "wof:placetype":"locality"
},
  "geometry": {"coordinates":[120.34457,32.68182],"type":"Point"}
}