{
  "type": "Feature",
  "properties": {
    "gn:admin1_code":"29.0",
    "gn:asciiname":"Xiaoyingpan",
    "gn:country_code":"CN",
    "gn:dem":1629,
    "gn:feature_class":"P",
    "gn:feature_code":"PPL",
    "gn:name":"Xiaoyingpan",
    "gn:population":0,
    "gn:timezone":"Asia/Shanghai",
    "iso:country":"CN",
    "name:zho_x_preferred":[
        "\u5c0f\u8425\u76d8"
    ],
    "wof:name":"Xiaoyingpan",
    "wof:placetype":"locality"
},
  "geometry": {"coordinates":[100.005,23.3541],"type":"Point"}
}