{
  "type": "Feature",
  "properties": {
    "gn:admin1_code":"15.0",
    "gn:asciiname":"Jiangou",
    "gn:country_code":"CN",
    "gn:dem":1328,
    "gn:feature_class":"P",
    "gn:feature_code":"PPL",
    "gn:name":"Jiangou",
    "gn:population":0,
    "gn:timezone":"Asia/Shanghai",
    "iso:country":"CN",
    "name:zho_x_preferred":[
        "\u6da7\u6c9f"
    ],
    "wof:name":"Jiangou",
    "wof:placetype":"locality"
},
  "geometry": {"coordinates":[107.25,35.1273],"type":"Point"}
}