{
  "type": "Feature",
  "properties": {
    "gn:admin1_code":"14",
    "gn:asciiname":"Ganchang'e",
    "gn:country_code":"CN",
    "gn:dem":4863,
    "gn:feature_class":"P",
    "gn:feature_code":"PPL",
    "gn:name":"Ganchang\u2019e",
    "gn:population":0,
    "gn:timezone":"Asia/Urumqi",
    "iso:country":"CN",
    "name:und_x_variant":[
        "Ganchang\u2019e"
    ],
    "name:zho_x_preferred":[
        "\u5e72\u660c\u4fc4"
    ],
    "wof:name":"Ganchang'e",
    "wof:placetype":"locality"
},
  "geometry": {"coordinates":[89.45399999999999,29.5505],"type":"Point"}
}