{
  "type": "Feature",
  "properties": {
    "gn:admin1_code":"30.0",
    "gn:asciiname":"Lianzhuping",
    "gn:country_code":"CN",
    "gn:dem":236,
    "gn:feature_class":"P",
    "gn:feature_code":"PPL",
    "gn:name":"Lianzhuping",
    "gn:population":0,
    "gn:timezone":"Asia/Shanghai",
    "iso:country":"CN",
    "name:zho_x_preferred":[
        "\u8fde\u73e0\u576a"
    ],
    "wof:name":"Lianzhuping",
    "wof:placetype":"locality"
},
  "geometry": {"coordinates":[111.46861,23.10908],"type":"Point"}
}