{
  "type": "Feature",
  "properties": {
    "gn:admin1_code":"16.0",
    "gn:asciiname":"Lusi",
    "gn:country_code":"CN",
    "gn:dem":287,
    "gn:feature_class":"P",
    "gn:feature_code":"PPL",
    "gn:name":"Lusi",
    "gn:population":0,
    "gn:timezone":"Asia/Shanghai",
    "iso:country":"CN",
    "name:ceb_x_preferred":[
        "Lusi"
    ],
    "name:deu_x_preferred":[
        "Lusi"
    ],
    "name:fra_x_preferred":[
        "Lusi"
    ],
    "name:ita_x_preferred":[
        "Lusi"
    ],
    "name:swe_x_preferred":[
        "Lusi"
    ],
    "name:zho_x_preferred":[
        "\u6e0c\u601d"
    ],
    "wof:name":"Lusi",
    "wof:placetype":"locality"
},
  "geometry": {"coordinates":[108.786,23.1576],"type":"Point"}
}