{
  "type": "Feature",
  "properties": {
    "gn:admin1_code":"9.0",
    "gn:asciiname":"Hualishu",
    "gn:country_code":"CN",
    "gn:dem":784,
    "gn:feature_class":"P",
    "gn:feature_code":"PPL",
    "gn:name":"Hualishu",
    "gn:population":0,
    "gn:timezone":"Asia/Shanghai",
    "iso:country":"CN",
    "name:zho_x_preferred":[
        "\u6866\u680e\u6811"
    ],
    "wof:name":"Hualishu",
    "wof:placetype":"locality"
},
  "geometry": {"coordinates":[111.03232,33.91813],"type":"Point"}
}