{
  "type": "Feature",
  "properties": {
    "gn:admin1_code":"23",
    "gn:asciiname":"Dujiahang",
    "gn:cc2":"CN",
    "gn:country_code":"CN",
    "gn:dem":5,
    "gn:feature_class":"P",
    "gn:feature_code":"PPL",
    "gn:name":"Dujiahang",
    "gn:population":0,
    "gn:timezone":"Asia/Shanghai",
    "iso:country":"CN",
    "name:und_x_variant":[
        "Tu-chia-hang",
        "Tu-hang",
        "Dujiahang"
    ],
    "wof:name":"Dujiahang",
    "wof:placetype":"locality"
},
  "geometry": {"coordinates":[121.49333,31.05167],"type":"Point"}
}