{
  "type": "Feature",
  "properties": {
    "gn:admin1_code":"18",
    "gn:asciiname":"Shuitian",
    "gn:country_code":"CN",
    "gn:dem":579,
    "gn:feature_class":"P",
    "gn:feature_code":"PPL",
    "gn:name":"Shuitian",
    "gn:population":0,
    "gn:timezone":"Asia/Shanghai",
    "iso:country":"CN",
    "name:zho_x_preferred":[
        "\u6c34\u7530"
    ],
    "wof:name":"Shuitian",
    "wof:placetype":"locality"
},
  "geometry": {"coordinates":[106.31699999999999,28.152],"type":"Point"}
}