{
  "type": "Feature",
  "properties": {
    "gn:admin1_code":"9",
    "gn:asciiname":"Zhangdian",
    "gn:country_code":"CN",
    "gn:dem":38,
    "gn:feature_class":"P",
    "gn:feature_code":"PPL",
    "gn:name":"Zhangdian",
    "gn:population":0,
    "gn:timezone":"Asia/Shanghai",
    "iso:country":"CN",
    "name:zho_x_preferred":[
        "\u5f20\u5e97"
    ],
    "wof:name":"Zhangdian",
    "wof:placetype":"locality"
},
  "geometry": {"coordinates":[116.13200000000001,33.8739],"type":"Point"}
}