{
  "type": "Feature",
  "properties": {
    "gn:admin1_code":"29.0",
    "gn:asciiname":"Zhujishan",
    "gn:country_code":"CN",
    "gn:dem":1609,
    "gn:feature_class":"P",
    "gn:feature_code":"PPL",
    "gn:name":"Zhujishan",
    "gn:population":0,
    "gn:timezone":"Asia/Shanghai",
    "iso:country":"CN",
    "name:zho_x_preferred":[
        "\u7af9\u9e21\u5c71"
    ],
    "wof:name":"Zhujishan",
    "wof:placetype":"locality"
},
  "geometry": {"coordinates":[104.90900000000001,27.4018],"type":"Point"}
}