{
  "type": "Feature",
  "properties": {
    "gn:admin1_code":"18.0",
    "gn:asciiname":"Zhiyan",
    "gn:country_code":"CN",
    "gn:dem":665,
    "gn:feature_class":"P",
    "gn:feature_code":"PPL",
    "gn:name":"Zhiyan",
    "gn:population":0,
    "gn:timezone":"Asia/Shanghai",
    "iso:country":"CN",
    "name:kor_x_preferred":[
        "\uc9c0\uc5c4"
    ],
    "name:pol_x_preferred":[
        "Yunhua Zhiyan"
    ],
    "name:rus_x_preferred":[
        "\u0427\u0436\u0438\u044f\u043d\u044c"
    ],
    "name:ukr_x_preferred":[
        "\u0427\u0436\u0456\u044f\u043d\u044c"
    ],
    "name:zho_x_preferred":[
        "\u6cbb\u5f66"
    ],
    "wof:name":"Zhiyan",
    "wof:placetype":"locality"
},
  "geometry": {"coordinates":[108.754,26.2371],"type":"Point"}
}