{
  "type": "Feature",
  "properties": {
    "gn:admin1_code":"3.0",
    "gn:asciiname":"Baizhubei",
    "gn:country_code":"CN",
    "gn:dem":108,
    "gn:feature_class":"P",
    "gn:feature_code":"PPL",
    "gn:name":"Baizhubei",
    "gn:population":0,
    "gn:timezone":"Asia/Shanghai",
    "iso:country":"CN",
    "name:und_x_variant":[
        "\u767d\u7af9\u80cc"
    ],
    "wof:name":"Baizhubei",
    "wof:placetype":"locality"
},
  "geometry": {"coordinates":[115.41262999999999,27.495],"type":"Point"}
}