{
  "type": "Feature",
  "properties": {
    "gn:admin1_code":"33",
    "gn:asciiname":"Tianci",
    "gn:country_code":"CN",
    "gn:dem":712,
    "gn:feature_class":"P",
    "gn:feature_code":"PPL",
    "gn:name":"Tianci",
    "gn:population":0,
    "gn:timezone":"Asia/Shanghai",
    "iso:country":"CN",
    "wof:name":"Tianci",
    "wof:placetype":"locality"
},
  "geometry": {"coordinates":[106.93056,29.43028],"type":"Point"}
}