{
  "type": "Feature",
  "properties": {
    "gn:admin1_code":"4.0",
    "gn:asciiname":"Jinkangcun",
    "gn:country_code":"CN",
    "gn:dem":4,
    "gn:feature_class":"P",
    "gn:feature_code":"PPL",
    "gn:name":"Jinkangcun",
    "gn:population":0,
    "gn:timezone":"Asia/Shanghai",
    "iso:country":"CN",
    "name:zho_x_preferred":[
        "\u91d1\u5eb7\u6751"
    ],
    "wof:name":"Jinkangcun",
    "wof:placetype":"locality"
},
  "geometry": {"coordinates":[120.59350999999999,32.86188],"type":"Point"}
}