{
  "type": "Feature",
  "properties": {
    "gn:admin1_code":"29",
    "gn:asciiname":"Shangzhemeng",
    "gn:country_code":"CN",
    "gn:dem":976,
    "gn:feature_class":"P",
    "gn:feature_code":"PPL",
    "gn:name":"Shangzhemeng",
    "gn:population":0,
    "gn:timezone":"Asia/Shanghai",
    "iso:country":"CN",
    "name:zho_x_preferred":[
        "\u4e0a\u8005\u5b5f"
    ],
    "wof:name":"Shangzhemeng",
    "wof:placetype":"locality"
},
  "geometry": {"coordinates":[105.075,24.375],"type":"Point"}
}