{
  "type": "Feature",
  "properties": {
    "gn:admin1_code":"29.0",
    "gn:asciiname":"Zasa",
    "gn:country_code":"CN",
    "gn:dem":1477,
    "gn:feature_class":"P",
    "gn:feature_code":"PPL",
    "gn:name":"Zasa",
    "gn:population":0,
    "gn:timezone":"Asia/Shanghai",
    "iso:country":"CN",
    "name:zho_x_preferred":[
        "\u6742\u6d12"
    ],
    "wof:name":"Zasa",
    "wof:placetype":"locality"
},
  "geometry": {"coordinates":[101.21599999999999,23.5395],"type":"Point"}
}