{
  "type": "Feature",
  "properties": {
    "gn:admin1_code":"14.0",
    "gn:asciiname":"Langmacun",
    "gn:country_code":"CN",
    "gn:dem":4257,
    "gn:feature_class":"P",
    "gn:feature_code":"PPL",
    "gn:name":"Langmacun",
    "gn:population":0,
    "gn:timezone":"Asia/Shanghai",
    "iso:country":"CN",
    "name:zho_x_preferred":[
        "\u90ce\u739b\u6751"
    ],
    "wof:name":"Langmacun",
    "wof:placetype":"locality"
},
  "geometry": {"coordinates":[79.8028,32.3694],"type":"Point"}
}