{
  "type": "Feature",
  "properties": {
    "gn:admin1_code":"32.0",
    "gn:asciiname":"Di'ele",
    "gn:country_code":"CN",
    "gn:dem":2221,
    "gn:feature_class":"P",
    "gn:feature_code":"PPL",
    "gn:name":"Di\u2019ele",
    "gn:population":0,
    "gn:timezone":"Asia/Shanghai",
    "iso:country":"CN",
    "name:zho_x_preferred":[
        "\u5e95\u4fc4\u52d2"
    ],
    "name:zho_x_variant":[
        "Di\u2019ele"
    ],
    "wof:name":"Di'ele",
    "wof:placetype":"locality"
},
  "geometry": {"coordinates":[103.18611,32.1726],"type":"Point"}
}