{
  "type": "Feature",
  "properties": {
    "gn:admin1_code":"10",
    "gn:asciiname":"Yongcheng",
    "gn:country_code":"CN",
    "gn:dem":11,
    "gn:feature_class":"P",
    "gn:feature_code":"PPL",
    "gn:name":"Yongcheng",
    "gn:population":0,
    "gn:timezone":"Asia/Shanghai",
    "iso:country":"CN",
    "name:zho_x_preferred":[
        "\u62e5\u57ce"
    ],
    "wof:name":"Yongcheng",
    "wof:placetype":"locality"
},
  "geometry": {"coordinates":[115.864,38.7528],"type":"Point"}
}