{
  "type": "Feature",
  "properties": {
    "gn:admin1_code":"29.0",
    "gn:asciiname":"Mahuangqing",
    "gn:country_code":"CN",
    "gn:dem":2062,
    "gn:feature_class":"P",
    "gn:feature_code":"PPL",
    "gn:name":"Mahuangqing",
    "gn:population":0,
    "gn:timezone":"Asia/Shanghai",
    "iso:country":"CN",
    "name:zho_x_preferred":[
        "\u8682\u8757\u7b90"
    ],
    "wof:name":"Mahuangqing",
    "wof:placetype":"locality"
},
  "geometry": {"coordinates":[101.09399999999999,25.0315],"type":"Point"}
}