{
  "type": "Feature",
  "properties": {
    "gn:admin1_code":"22.0",
    "gn:asciiname":"Zhangzuocun",
    "gn:country_code":"CN",
    "gn:dem":143,
    "gn:feature_class":"P",
    "gn:feature_code":"PPL",
    "gn:name":"Zhangzuocun",
    "gn:population":0,
    "gn:timezone":"Asia/Shanghai",
    "iso:country":"CN",
    "name:zho_x_preferred":[
        "\u5f70\u4f5c\u6751"
    ],
    "wof:name":"Zhangzuocun",
    "wof:placetype":"locality"
},
  "geometry": {"coordinates":[117.32789,40.21545],"type":"Point"}
}