{
  "type": "Feature",
  "properties": {
    "gn:admin1_code":"3.0",
    "gn:asciiname":"Chisha",
    "gn:country_code":"CN",
    "gn:dem":243,
    "gn:feature_class":"P",
    "gn:feature_code":"PPL",
    "gn:name":"Chisha",
    "gn:population":0,
    "gn:timezone":"Asia/Shanghai",
    "iso:country":"CN",
    "name:und_x_variant":[
        "\u8d64\u6c99"
    ],
    "wof:name":"Chisha",
    "wof:placetype":"locality"
},
  "geometry": {"coordinates":[115.91236000000001,25.64313],"type":"Point"}
}