{
  "type": "Feature",
  "properties": {
    "gn:admin1_code":"12.0",
    "gn:asciiname":"Gufu",
    "gn:country_code":"CN",
    "gn:dem":918,
    "gn:feature_class":"P",
    "gn:feature_code":"PPLA3",
    "gn:name":"Gufu",
    "gn:population":0,
    "gn:timezone":"Asia/Shanghai",
    "iso:country":"CN",
    "name:zho_x_preferred":[
        "\u53e4\u592b"
    ],
    "wof:name":"Gufu",
    "wof:placetype":"locality"
},
  "geometry": {"coordinates":[110.72918,31.36208],"type":"Point"}
}