{
  "type": "Feature",
  "properties": {
    "gn:admin1_code":"29.0",
    "gn:asciiname":"Hewaishan",
    "gn:country_code":"CN",
    "gn:dem":2075,
    "gn:feature_class":"P",
    "gn:feature_code":"PPL",
    "gn:name":"Hewaishan",
    "gn:population":0,
    "gn:timezone":"Asia/Shanghai",
    "iso:country":"CN",
    "name:zho_x_preferred":[
        "\u6cb3\u5916\u5c71"
    ],
    "wof:name":"Hewaishan",
    "wof:placetype":"locality"
},
  "geometry": {"coordinates":[99.9684,24.6253],"type":"Point"}
}