{
  "type": "Feature",
  "properties": {
    "gn:admin1_code":"22.0",
    "gn:asciiname":"Naizifangcun",
    "gn:country_code":"CN",
    "gn:dem":40,
    "gn:feature_class":"P",
    "gn:feature_code":"PPL",
    "gn:name":"Naizifangcun",
    "gn:population":0,
    "gn:timezone":"Asia/Shanghai",
    "iso:country":"CN",
    "name:zho_x_preferred":[
        "\u5976\u5b50\u623f\u6751"
    ],
    "wof:name":"Naizifangcun",
    "wof:placetype":"locality"
},
  "geometry": {"coordinates":[116.46335000000001,40.04485],"type":"Point"}
}