{
  "type": "Feature",
  "properties": {
    "gn:admin1_code":"11.0",
    "gn:asciiname":"Beifengya",
    "gn:country_code":"CN",
    "gn:dem":633,
    "gn:feature_class":"P",
    "gn:feature_code":"PPL",
    "gn:name":"Beifengya",
    "gn:population":0,
    "gn:timezone":"Asia/Shanghai",
    "iso:country":"CN",
    "name:zho_x_preferred":[
        "Beifengya"
    ],
    "name:zho_x_variant":[
        "\u5317\u98ce\u57ad"
    ],
    "wof:name":"Beifengya",
    "wof:placetype":"locality"
},
  "geometry": {"coordinates":[111.20103,29.73794],"type":"Point"}
}