{
  "type": "Feature",
  "properties": {
    "gn:admin1_code":"14.0",
    "gn:asciiname":"Shazong",
    "gn:country_code":"CN",
    "gn:dem":4533,
    "gn:feature_class":"P",
    "gn:feature_code":"PPL",
    "gn:name":"Shazong",
    "gn:population":0,
    "gn:timezone":"Asia/Urumqi",
    "iso:country":"CN",
    "name:zho_x_preferred":[
        "\u6c99\u5b97"
    ],
    "wof:name":"Shazong",
    "wof:placetype":"locality"
},
  "geometry": {"coordinates":[93.77392,31.04953],"type":"Point"}
}