{
  "type": "Feature",
  "properties": {
    "gn:admin1_code":"29",
    "gn:asciiname":"Heishulin",
    "gn:country_code":"CN",
    "gn:dem":1826,
    "gn:feature_class":"P",
    "gn:feature_code":"PPL",
    "gn:name":"Heishulin",
    "gn:population":0,
    "gn:timezone":"Asia/Shanghai",
    "iso:country":"CN",
    "name:zho_x_preferred":[
        "\u9ed1\u6811\u6797"
    ],
    "wof:name":"Heishulin",
    "wof:placetype":"locality"
},
  "geometry": {"coordinates":[103.0425,24.66203],"type":"Point"}
}