{
  "type": "Feature",
  "properties": {
    "gn:admin1_code":"19.0",
    "gn:asciiname":"Taijiacun",
    "gn:country_code":"CN",
    "gn:dem":219,
    "gn:feature_class":"P",
    "gn:feature_code":"PPL",
    "gn:name":"Taijiacun",
    "gn:population":0,
    "gn:timezone":"Asia/Shanghai",
    "iso:country":"CN",
    "name:und_x_variant":[
        "Taijiawobao",
        "Taijia Wobu"
    ],
    "name:zho_x_preferred":[
        "\u90b0\u5bb6\u6751"
    ],
    "name:zho_x_variant":[
        "\u90b0\u5bb6\u7a9d\u5821"
    ],
    "wof:name":"Taijiacun",
    "wof:placetype":"locality"
},
  "geometry": {"coordinates":[122.529,42.7034],"type":"Point"}
}