{
  "type": "Feature",
  "properties": {
    "gn:admin1_code":"7",
    "gn:asciiname":"Yonghe",
    "gn:cc2":"CN",
    "gn:country_code":"CN",
    "gn:dem":46,
    "gn:feature_class":"P",
    "gn:feature_code":"PPL",
    "gn:name":"Yonghe",
    "gn:population":0,
    "gn:timezone":"Asia/Shanghai",
    "iso:country":"CN",
    "name:ceb_x_preferred":[
        "Yonghe"
    ],
    "name:deu_x_preferred":[
        "Yonghe"
    ],
    "name:rus_x_preferred":[
        "\u042e\u043d\u0445\u044d"
    ],
    "name:und_x_variant":[
        "Chuang-chai",
        "Zhuangzhai"
    ],
    "wof:name":"Yonghe",
    "wof:placetype":"locality"
},
  "geometry": {"coordinates":[118.56417,24.70083],"type":"Point"}
}