{
  "type": "Feature",
  "properties": {
    "gn:admin1_code":"15.0",
    "gn:asciiname":"Shaotangou",
    "gn:country_code":"CN",
    "gn:dem":1206,
    "gn:feature_class":"P",
    "gn:feature_code":"PPL",
    "gn:name":"Shaotangou",
    "gn:population":0,
    "gn:timezone":"Asia/Shanghai",
    "iso:country":"CN",
    "name:und_x_variant":[
        "\u70e7\u70ad\u6c9f"
    ],
    "wof:name":"Shaotangou",
    "wof:placetype":"locality"
},
  "geometry": {"coordinates":[106.34255,33.91526],"type":"Point"}
}