{
  "type": "Feature",
  "properties": {
    "gn:admin1_code":"19.0",
    "gn:asciiname":"Gandaozi",
    "gn:country_code":"CN",
    "gn:dem":6,
    "gn:feature_class":"P",
    "gn:feature_code":"PPL",
    "gn:name":"Gandaozi",
    "gn:population":0,
    "gn:timezone":"Asia/Shanghai",
    "iso:country":"CN",
    "name:zho_x_preferred":[
        "\u5e72\u5c9b\u5b50"
    ],
    "wof:name":"Gandaozi",
    "wof:placetype":"locality"
},
  "geometry": {"coordinates":[122.721,39.5512],"type":"Point"}
}