{
  "type": "Feature",
  "properties": {
    "gn:admin1_code":"14.0",
    "gn:asciiname":"Namling",
    "gn:country_code":"CN",
    "gn:dem":4004,
    "gn:feature_class":"P",
    "gn:feature_code":"PPLA3",
    "gn:name":"Namling",
    "gn:population":0,
    "gn:timezone":"Asia/Urumqi",
    "iso:country":"CN",
    "name:bod_x_preferred":[
        "Namling"
    ],
    "name:fas_x_preferred":[
        "\u0646\u0627\u0645\u0644\u06cc\u0646\u06af"
    ],
    "name:msa_x_preferred":[
        "Namlingxoi"
    ],
    "name:und_x_variant":[
        "Na-mu-lin-tsung",
        "Nan-mu-lin",
        "Na-lin",
        "Na-mu-ling-hs\u00fcn",
        "Na-mu-ling-tsung",
        "Namling Dzong",
        "Na-mu-ling",
        "Nanmulin Zhen"
    ],
    "name:zho_x_preferred":[
        "Nanmulin"
    ],
    "name:zho_x_variant":[
        "\u5357\u6728\u6797",
        "Renwu",
        "\u4ec1\u4f0d",
        "\u5357\u6728\u6797\u9547"
    ],
    "wof:name":"Namling",
    "wof:placetype":"locality"
},
  "geometry": {"coordinates":[89.09555999999998,29.68527000000001],"type":"Point"}
}