{
  "type": "Feature",
  "properties": {
    "gn:admin1_code":"09",
    "gn:asciiname":"Shangjiuwu",
    "gn:country_code":"CN",
    "gn:dem":167,
    "gn:feature_class":"P",
    "gn:feature_code":"PPLA4",
    "gn:name":"Shangjiuwu",
    "gn:population":0,
    "gn:timezone":"Asia/Shanghai",
    "iso:country":"CN",
    "name:und_x_variant":[
        "Shang-chiu-wu",
        "\u5546\u9152\u52a1",
        "Shangjiuwu Zhen",
        "\u5546\u9152\u52a1\u9547",
        "Shangjiuwu"
    ],
    "wof:name":"Shangjiuwu",
    "wof:placetype":"locality"
},
  "geometry": {"coordinates":[112.97767,33.94896],"type":"Point"}
}