{
  "type": "Feature",
  "properties": {
    "gn:admin1_code":"26.0",
    "gn:asciiname":"Shangshancun",
    "gn:country_code":"CN",
    "gn:dem":904,
    "gn:feature_class":"P",
    "gn:feature_code":"PPL",
    "gn:name":"Shangshancun",
    "gn:population":0,
    "gn:timezone":"Asia/Shanghai",
    "iso:country":"CN",
    "name:und_x_variant":[
        "\u5c1a\u5c71\u6751"
    ],
    "wof:name":"Shangshancun",
    "wof:placetype":"locality"
},
  "geometry": {"coordinates":[107.90964,33.26772],"type":"Point"}
}