{
  "type": "Feature",
  "properties": {
    "gn:admin1_code":"10",
    "gn:asciiname":"Luanzhou",
    "gn:country_code":"CN",
    "gn:dem":34,
    "gn:feature_class":"P",
    "gn:feature_code":"PPLA3",
    "gn:name":"Luanzhou",
    "gn:population":0,
    "gn:timezone":"Asia/Shanghai",
    "iso:country":"CN",
    "name:und_x_variant":[
        "Lwanchow",
        "Luan-hsien-ch\u2019eng",
        "Lwanhsien",
        "Luan-hsien-ch\u2019eng-kuan",
        "Luan-hsien",
        "Lu-an",
        "Luan-chou",
        "Luan Xian",
        "Luanzhou"
    ],
    "name:zho_x_preferred":[
        "\u6ee6\u5dde"
    ],
    "name:zho_x_variant":[
        "\u6ee6\u53bf"
    ],
    "wof:name":"Luanzhou",
    "wof:placetype":"locality"
},
  "geometry": {"coordinates":[118.73333,39.75],"type":"Point"}
}