{
  "type": "Feature",
  "properties": {
    "gn:admin1_code":"30.0",
    "gn:asciiname":"Heinichang",
    "gn:country_code":"CN",
    "gn:dem":194,
    "gn:feature_class":"P",
    "gn:feature_code":"PPL",
    "gn:name":"Heinichang",
    "gn:population":0,
    "gn:timezone":"Asia/Shanghai",
    "iso:country":"CN",
    "name:zho_x_preferred":[
        "\u9ed1\u576d\u5382"
    ],
    "wof:name":"Heinichang",
    "wof:placetype":"locality"
},
  "geometry": {"coordinates":[111.99951,22.22006],"type":"Point"}
}