{
  "type": "Feature",
  "properties": {
    "gn:admin1_code":"26",
    "gn:asciiname":"Ancun",
    "gn:country_code":"CN",
    "gn:dem":699,
    "gn:feature_class":"P",
    "gn:feature_code":"PPLA4",
    "gn:name":"Ancun",
    "gn:population":0,
    "gn:timezone":"Asia/Shanghai",
    "iso:country":"CN",
    "name:und_x_variant":[
        "\u5b89\u6751",
        "Ancun"
    ],
    "wof:name":"Ancun",
    "wof:placetype":"locality"
},
  "geometry": {"coordinates":[109.26861,34.12134],"type":"Point"}
}