{
  "type": "Feature",
  "properties": {
    "gn:admin1_code":"20.0",
    "gn:asciiname":"Nancaonian",
    "gn:country_code":"CN",
    "gn:dem":1549,
    "gn:feature_class":"P",
    "gn:feature_code":"PPL",
    "gn:name":"Nancaonian",
    "gn:population":0,
    "gn:timezone":"Asia/Shanghai",
    "iso:country":"CN",
    "name:und_x_variant":[
        "\u5357\u66f9\u78be"
    ],
    "wof:name":"Nancaonian",
    "wof:placetype":"locality"
},
  "geometry": {"coordinates":[111.85776,39.80636],"type":"Point"}
}