{
  "type": "Feature",
  "properties": {
    "gn:admin1_code":"26.0",
    "gn:asciiname":"Banbianjie",
    "gn:country_code":"CN",
    "gn:dem":550,
    "gn:feature_class":"P",
    "gn:feature_code":"PPL",
    "gn:name":"Banbianjie",
    "gn:population":0,
    "gn:timezone":"Asia/Shanghai",
    "iso:country":"CN",
    "name:zho_x_preferred":[
        "\u534a\u8fb9\u8857"
    ],
    "wof:name":"Banbianjie",
    "wof:placetype":"locality"
},
  "geometry": {"coordinates":[108.46331000000001,32.86632],"type":"Point"}
}