{
  "type": "Feature",
  "properties": {
    "gn:admin1_code":"18.0",
    "gn:asciiname":"Xiaogudong",
    "gn:country_code":"CN",
    "gn:dem":1019,
    "gn:feature_class":"P",
    "gn:feature_code":"PPL",
    "gn:name":"Xiaogudong",
    "gn:population":0,
    "gn:timezone":"Asia/Shanghai",
    "iso:country":"CN",
    "name:zho_x_preferred":[
        "\u5c0f\u8c37\u6d1e"
    ],
    "wof:name":"Xiaogudong",
    "wof:placetype":"locality"
},
  "geometry": {"coordinates":[107.45999999999999,26.5051],"type":"Point"}
}