{
  "type": "Feature",
  "properties": {
    "gn:admin1_code":"7.0",
    "gn:asciiname":"Shangkuzhukeng",
    "gn:country_code":"CN",
    "gn:dem":487,
    "gn:feature_class":"P",
    "gn:feature_code":"PPL",
    "gn:name":"Shangkuzhukeng",
    "gn:population":0,
    "gn:timezone":"Asia/Shanghai",
    "iso:country":"CN",
    "name:zho_x_preferred":[
        "\u4e0a\u82e6\u7af9\u5751"
    ],
    "wof:name":"Shangkuzhukeng",
    "wof:placetype":"locality"
},
  "geometry": {"coordinates":[116.97037,24.78956],"type":"Point"}
}