{
  "type": "Feature",
  "properties": {
    "gn:admin1_code":"8.0",
    "gn:asciiname":"Yifaqu",
    "gn:country_code":"CN",
    "gn:dem":260,
    "gn:feature_class":"P",
    "gn:feature_code":"PPL",
    "gn:name":"Yifaqu",
    "gn:population":0,
    "gn:timezone":"Asia/Shanghai",
    "iso:country":"CN",
    "name:zho_x_preferred":[
        "\u4e00\u4f10\u533a"
    ],
    "wof:name":"Yifaqu",
    "wof:placetype":"locality"
},
  "geometry": {"coordinates":[131.02376000000001,46.31017],"type":"Point"}
}