{
  "type": "Feature",
  "properties": {
    "gn:admin1_code":"14.0",
    "gn:asciiname":"Jiangle",
    "gn:country_code":"CN",
    "gn:dem":4756,
    "gn:feature_class":"P",
    "gn:feature_code":"PPL",
    "gn:name":"Jiangle",
    "gn:population":0,
    "gn:timezone":"Asia/Urumqi",
    "iso:country":"CN",
    "name:zho_x_preferred":[
        "\u6c5f\u52d2"
    ],
    "wof:name":"Jiangle",
    "wof:placetype":"locality"
},
  "geometry": {"coordinates":[87.03959999999999,30.7282],"type":"Point"}
}