{
  "type": "Feature",
  "properties": {
    "gn:admin1_code":"32.0",
    "gn:asciiname":"Xiaoshiwa",
    "gn:country_code":"CN",
    "gn:dem":1895,
    "gn:feature_class":"P",
    "gn:feature_code":"PPL",
    "gn:name":"Xiaoshiwa",
    "gn:population":0,
    "gn:timezone":"Asia/Shanghai",
    "iso:country":"CN",
    "name:zho_x_preferred":[
        "\u5c0f\u77f3\u6d3c"
    ],
    "wof:name":"Xiaoshiwa",
    "wof:placetype":"locality"
},
  "geometry": {"coordinates":[101.672,27.01],"type":"Point"}
}