{
  "type": "Feature",
  "properties": {
    "gn:admin1_code":"3",
    "gn:asciiname":"Shihanjing",
    "gn:country_code":"CN",
    "gn:dem":216,
    "gn:feature_class":"P",
    "gn:feature_code":"PPL",
    "gn:name":"Shihanjing",
    "gn:population":0,
    "gn:timezone":"Asia/Shanghai",
    "iso:country":"CN",
    "name:zho_x_preferred":[
        "\u77f3\u542b\u5f84"
    ],
    "wof:name":"Shihanjing",
    "wof:placetype":"locality"
},
  "geometry": {"coordinates":[114.589,26.0191],"type":"Point"}
}