{
  "type": "Feature",
  "properties": {
    "gn:admin1_code":"26.0",
    "gn:asciiname":"Yanjiaping",
    "gn:country_code":"CN",
    "gn:dem":1129,
    "gn:feature_class":"P",
    "gn:feature_code":"PPL",
    "gn:name":"Yanjiaping",
    "gn:population":0,
    "gn:timezone":"Asia/Shanghai",
    "iso:country":"CN",
    "name:und_x_variant":[
        "\u960e\u5bb6\u576a"
    ],
    "wof:name":"Yanjiaping",
    "wof:placetype":"locality"
},
  "geometry": {"coordinates":[107.60945,34.55058],"type":"Point"}
}