{
  "type": "Feature",
  "properties": {
    "gn:admin1_code":"3.0",
    "gn:asciiname":"Zhangshu Xiongjia",
    "gn:country_code":"CN",
    "gn:dem":25,
    "gn:feature_class":"P",
    "gn:feature_code":"PPL",
    "gn:name":"Zhangshu Xiongjia",
    "gn:population":0,
    "gn:timezone":"Asia/Shanghai",
    "iso:country":"CN",
    "name:und_x_variant":[
        "\u6a1f\u6811\u718a\u5bb6"
    ],
    "wof:name":"Zhangshu Xiongjia",
    "wof:placetype":"locality"
},
  "geometry": {"coordinates":[115.71366,29.17152],"type":"Point"}
}