{
  "type": "Feature",
  "properties": {
    "gn:admin1_code":"32.0",
    "gn:asciiname":"Lalong",
    "gn:country_code":"CN",
    "gn:dem":4249,
    "gn:feature_class":"P",
    "gn:feature_code":"PPL",
    "gn:name":"Lalong",
    "gn:population":0,
    "gn:timezone":"Asia/Shanghai",
    "iso:country":"CN",
    "name:zho_x_preferred":[
        "\u62c9\u9f99"
    ],
    "wof:name":"Lalong",
    "wof:placetype":"locality"
},
  "geometry": {"coordinates":[97.6387,33.3256],"type":"Point"}
}