{
  "type": "Feature",
  "properties": {
    "gn:admin1_code":"5.0",
    "gn:asciiname":"Hua'ancun",
    "gn:country_code":"CN",
    "gn:dem":146,
    "gn:feature_class":"P",
    "gn:feature_code":"PPL",
    "gn:name":"Hua\u2019ancun",
    "gn:population":0,
    "gn:timezone":"Asia/Shanghai",
    "iso:country":"CN",
    "name:und_x_variant":[
        "Hua\u2019ancun"
    ],
    "name:zho_x_preferred":[
        "\u534e\u5b89\u6751"
    ],
    "wof:name":"Hua'ancun",
    "wof:placetype":"locality"
},
  "geometry": {"coordinates":[123.26597,44.66601],"type":"Point"}
}