{
  "type": "Feature",
  "properties": {
    "gn:admin1_code":"16.0",
    "gn:asciiname":"Yunpanshan",
    "gn:country_code":"CN",
    "gn:dem":849,
    "gn:feature_class":"P",
    "gn:feature_code":"PPL",
    "gn:name":"Yunpanshan",
    "gn:population":0,
    "gn:timezone":"Asia/Shanghai",
    "iso:country":"CN",
    "name:zho_x_preferred":[
        "\u4e91\u76d8\u5c71"
    ],
    "wof:name":"Yunpanshan",
    "wof:placetype":"locality"
},
  "geometry": {"coordinates":[106.874,24.6635],"type":"Point"}
}