{
  "type": "Feature",
  "properties": {
    "gn:admin1_code":"3.0",
    "gn:asciiname":"Qianxi",
    "gn:country_code":"CN",
    "gn:dem":117,
    "gn:feature_class":"P",
    "gn:feature_code":"PPL",
    "gn:name":"Qianxi",
    "gn:population":0,
    "gn:timezone":"Asia/Shanghai",
    "iso:country":"CN",
    "name:ceb_x_preferred":[
        "Qianxi"
    ],
    "name:deu_x_preferred":[
        "Qianxi"
    ],
    "name:fra_x_preferred":[
        "Qianxi"
    ],
    "name:kor_x_preferred":[
        "\uccb8\uc2dc\ud604"
    ],
    "name:nor_x_preferred":[
        "Qianxi"
    ],
    "name:swe_x_preferred":[
        "Qianxi"
    ],
    "name:und_x_variant":[
        "\u94b1\u6eaa"
    ],
    "wof:name":"Qianxi",
    "wof:placetype":"locality"
},
  "geometry": {"coordinates":[114.27243,27.05368],"type":"Point"}
}