{
  "type": "Feature",
  "properties": {
    "gn:admin1_code":"19.0",
    "gn:asciiname":"Laojuntuncun",
    "gn:country_code":"CN",
    "gn:dem":10,
    "gn:feature_class":"P",
    "gn:feature_code":"PPL",
    "gn:name":"Laojuntuncun",
    "gn:population":0,
    "gn:timezone":"Asia/Shanghai",
    "iso:country":"CN",
    "name:zho_x_preferred":[
        "\u8001\u519b\u5c6f\u6751"
    ],
    "wof:name":"Laojuntuncun",
    "wof:placetype":"locality"
},
  "geometry": {"coordinates":[119.876,40.0624],"type":"Point"}
}