{
  "type": "Feature",
  "properties": {
    "gn:admin1_code":"32.0",
    "gn:asciiname":"Kejia Wanzi",
    "gn:country_code":"CN",
    "gn:dem":2764,
    "gn:feature_class":"P",
    "gn:feature_code":"PPL",
    "gn:name":"Kejia Wanzi",
    "gn:population":0,
    "gn:timezone":"Asia/Shanghai",
    "iso:country":"CN",
    "name:zho_x_preferred":[
        "\u67ef\u5bb6\u6e7e\u5b50"
    ],
    "wof:name":"Kejia Wanzi",
    "wof:placetype":"locality"
},
  "geometry": {"coordinates":[101.202,27.1957],"type":"Point"}
}