{
  "type": "Feature",
  "properties": {
    "gn:admin1_code":"8.0",
    "gn:asciiname":"Xumuchang",
    "gn:country_code":"CN",
    "gn:dem":368,
    "gn:feature_class":"P",
    "gn:feature_code":"PPL",
    "gn:name":"Xumuchang",
    "gn:population":0,
    "gn:timezone":"Asia/Shanghai",
    "iso:country":"CN",
    "name:und_x_variant":[
        "\u755c\u7267\u573a"
    ],
    "wof:name":"Xumuchang",
    "wof:placetype":"locality"
},
  "geometry": {"coordinates":[126.98650000000001,50.55587],"type":"Point"}
}