{
  "type": "Feature",
  "properties": {
    "gn:admin1_code":"30",
    "gn:asciiname":"Jiangtouping",
    "gn:country_code":"CN",
    "gn:dem":191,
    "gn:feature_class":"P",
    "gn:feature_code":"PPL",
    "gn:name":"Jiangtouping",
    "gn:population":0,
    "gn:timezone":"Asia/Shanghai",
    "iso:country":"CN",
    "name:und_x_variant":[
        "\u6c5f\u5934\u576a",
        "Jiangtouping"
    ],
    "wof:name":"Jiangtouping",
    "wof:placetype":"locality"
},
  "geometry": {"coordinates":[115.52776,24.19125],"type":"Point"}
}