{
  "type": "Feature",
  "properties": {
    "gn:admin1_code":"1.0",
    "gn:asciiname":"Hongdangcun",
    "gn:country_code":"CN",
    "gn:dem":31,
    "gn:feature_class":"P",
    "gn:feature_code":"PPL",
    "gn:name":"Hongdangcun",
    "gn:population":0,
    "gn:timezone":"Asia/Shanghai",
    "iso:country":"CN",
    "name:zho_x_preferred":[
        "\u6d2a\u5b95\u6751"
    ],
    "wof:name":"Hongdangcun",
    "wof:placetype":"locality"
},
  "geometry": {"coordinates":[116.86548000000001,31.40747],"type":"Point"}
}