{
  "type": "Feature",
  "properties": {
    "gn:admin1_code":"07",
    "gn:asciiname":"Liyang",
    "gn:country_code":"CN",
    "gn:dem":77,
    "gn:feature_class":"P",
    "gn:feature_code":"PPL",
    "gn:name":"Liyang",
    "gn:population":0,
    "gn:timezone":"Asia/Shanghai",
    "iso:country":"CN",
    "name:und_x_variant":[
        "Liyangli",
        "Liyang"
    ],
    "name:zho_x_preferred":[
        "\u68a8\u6d0b"
    ],
    "wof:name":"Liyang",
    "wof:placetype":"locality"
},
  "geometry": {"coordinates":[120.33531000000001,27.12844],"type":"Point"}
}