{
  "type": "Feature",
  "properties": {
    "gn:admin1_code":"9.0",
    "gn:asciiname":"Longquansi",
    "gn:country_code":"CN",
    "gn:dem":119,
    "gn:feature_class":"P",
    "gn:feature_code":"PPL",
    "gn:name":"Longquansi",
    "gn:population":0,
    "gn:timezone":"Asia/Shanghai",
    "iso:country":"CN",
    "name:zho_x_preferred":[
        "\u9f99\u6cc9\u5bfa"
    ],
    "wof:name":"Longquansi",
    "wof:placetype":"locality"
},
  "geometry": {"coordinates":[112.95115,33.03484],"type":"Point"}
}