{
  "type": "Feature",
  "properties": {
    "gn:admin1_code":"29.0",
    "gn:asciiname":"Xiaojing",
    "gn:country_code":"CN",
    "gn:dem":2540,
    "gn:feature_class":"P",
    "gn:feature_code":"PPL",
    "gn:name":"Xiaojing",
    "gn:population":0,
    "gn:timezone":"Asia/Shanghai",
    "iso:country":"CN",
    "name:nld_x_preferred":[
        "Xiaojing"
    ],
    "name:swe_x_preferred":[
        "Xiaojing"
    ],
    "name:zho_x_preferred":[
        "\u785d\u4e95"
    ],
    "wof:name":"Xiaojing",
    "wof:placetype":"locality"
},
  "geometry": {"coordinates":[102.545,26.0394],"type":"Point"}
}