{
  "type": "Feature",
  "properties": {
    "gn:admin1_code":"11.0",
    "gn:asciiname":"Junzhougang",
    "gn:country_code":"CN",
    "gn:dem":34,
    "gn:feature_class":"P",
    "gn:feature_code":"PPL",
    "gn:name":"Junzhougang",
    "gn:population":0,
    "gn:timezone":"Asia/Shanghai",
    "iso:country":"CN",
    "name:zho_x_preferred":[
        "Junzhougang"
    ],
    "name:zho_x_variant":[
        "\u519b\u5468\u5c97"
    ],
    "wof:name":"Junzhougang",
    "wof:placetype":"locality"
},
  "geometry": {"coordinates":[111.65563,29.08039],"type":"Point"}
}