{
  "type": "Feature",
  "properties": {
    "gn:admin1_code":"1.0",
    "gn:asciiname":"Louzhuangcun",
    "gn:country_code":"CN",
    "gn:dem":26,
    "gn:feature_class":"P",
    "gn:feature_code":"PPL",
    "gn:name":"Louzhuangcun",
    "gn:population":0,
    "gn:timezone":"Asia/Shanghai",
    "iso:country":"CN",
    "name:zho_x_preferred":[
        "\u5a04\u5e84\u6751"
    ],
    "wof:name":"Louzhuangcun",
    "wof:placetype":"locality"
},
  "geometry": {"coordinates":[117.4419,33.49487],"type":"Point"}
}