{
  "type": "Feature",
  "properties": {
    "gn:admin1_code":"18",
    "gn:asciiname":"Zhuyuanba",
    "gn:country_code":"CN",
    "gn:dem":1061,
    "gn:feature_class":"P",
    "gn:feature_code":"PPL",
    "gn:name":"Zhuyuanba",
    "gn:population":0,
    "gn:timezone":"Asia/Shanghai",
    "iso:country":"CN",
    "name:zho_x_preferred":[
        "\u795d\u56ed\u575d"
    ],
    "wof:name":"Zhuyuanba",
    "wof:placetype":"locality"
},
  "geometry": {"coordinates":[107.467,28.8995],"type":"Point"}
}