{
  "type": "Feature",
  "properties": {
    "gn:admin1_code":"10.0",
    "gn:asciiname":"Baishuigang",
    "gn:country_code":"CN",
    "gn:dem":188,
    "gn:feature_class":"P",
    "gn:feature_code":"PPL",
    "gn:name":"Baishuigang",
    "gn:population":0,
    "gn:timezone":"Asia/Shanghai",
    "iso:country":"CN",
    "name:zho_x_preferred":[
        "\u767d\u6c34\u6e2f"
    ],
    "wof:name":"Baishuigang",
    "wof:placetype":"locality"
},
  "geometry": {"coordinates":[115.28922,39.39191],"type":"Point"}
}