{
  "type": "Feature",
  "properties": {
    "gn:admin1_code":"3.0",
    "gn:asciiname":"Duimen",
    "gn:country_code":"CN",
    "gn:dem":41,
    "gn:feature_class":"P",
    "gn:feature_code":"PPL",
    "gn:name":"Duimen",
    "gn:population":0,
    "gn:timezone":"Asia/Shanghai",
    "iso:country":"CN",
    "name:und_x_variant":[
        "\u5bf9\u95e8"
    ],
    "wof:name":"Duimen",
    "wof:placetype":"locality"
},
  "geometry": {"coordinates":[115.08934000000001,28.29359],"type":"Point"}
}