{
  "type": "Feature",
  "properties": {
    "gn:admin1_code":"14.0",
    "gn:asciiname":"Dungro",
    "gn:country_code":"CN",
    "gn:dem":3753,
    "gn:feature_class":"P",
    "gn:feature_code":"PPL",
    "gn:name":"Dungro",
    "gn:population":0,
    "gn:timezone":"Asia/Urumqi",
    "iso:country":"CN",
    "name:bod_x_preferred":[
        "Dungro"
    ],
    "wof:name":"Dungro",
    "wof:placetype":"locality"
},
  "geometry": {"coordinates":[95.98333,29.76667],"type":"Point"}
}