{
  "type": "Feature",
  "properties": {
    "gn:admin1_code":"8.0",
    "gn:asciiname":"Banmiancun",
    "gn:country_code":"CN",
    "gn:dem":89,
    "gn:feature_class":"P",
    "gn:feature_code":"PPL",
    "gn:name":"Banmiancun",
    "gn:population":0,
    "gn:timezone":"Asia/Shanghai",
    "iso:country":"CN",
    "name:zho_x_preferred":[
        "\u677f\u9762\u6751"
    ],
    "wof:name":"Banmiancun",
    "wof:placetype":"locality"
},
  "geometry": {"coordinates":[132.51143999999999,45.53669],"type":"Point"}
}