{
  "type": "Feature",
  "properties": {
    "gn:admin1_code":"19.0",
    "gn:asciiname":"Qianchangtuozicun",
    "gn:country_code":"CN",
    "gn:dem":98,
    "gn:feature_class":"P",
    "gn:feature_code":"PPL",
    "gn:name":"Qianchangtuozicun",
    "gn:population":0,
    "gn:timezone":"Asia/Shanghai",
    "iso:country":"CN",
    "name:zho_x_preferred":[
        "\u524d\u957f\u5768\u5b50\u6751"
    ],
    "wof:name":"Qianchangtuozicun",
    "wof:placetype":"locality"
},
  "geometry": {"coordinates":[122.565,42.44600000000001],"type":"Point"}
}