{
  "type": "Feature",
  "properties": {
    "gn:admin1_code":"4.0",
    "gn:asciiname":"Shuangjing",
    "gn:country_code":"CN",
    "gn:dem":28,
    "gn:feature_class":"P",
    "gn:feature_code":"PPL",
    "gn:name":"Shuangjing",
    "gn:population":0,
    "gn:timezone":"Asia/Shanghai",
    "iso:country":"CN",
    "name:ceb_x_preferred":[
        "Shuangjing"
    ],
    "name:swe_x_preferred":[
        "Shuangjing"
    ],
    "name:zho_x_preferred":[
        "\u53cc\u4e95"
    ],
    "wof:name":"Shuangjing",
    "wof:placetype":"locality"
},
  "geometry": {"coordinates":[118.98729,32.41625],"type":"Point"}
}