{
  "type": "Feature",
  "properties": {
    "gn:admin1_code":"32.0",
    "gn:asciiname":"Jinquwamo",
    "gn:country_code":"CN",
    "gn:dem":2793,
    "gn:feature_class":"P",
    "gn:feature_code":"PPL",
    "gn:name":"Jinquwamo",
    "gn:population":0,
    "gn:timezone":"Asia/Shanghai",
    "iso:country":"CN",
    "name:zho_x_preferred":[
        "\u91d1\u66f2\u74e6\u83ab"
    ],
    "wof:name":"Jinquwamo",
    "wof:placetype":"locality"
},
  "geometry": {"coordinates":[102.744,28.1295],"type":"Point"}
}