{
  "type": "Feature",
  "properties": {
    "gn:admin1_code":"26.0",
    "gn:asciiname":"Yanchanggounao",
    "gn:country_code":"CN",
    "gn:dem":1540,
    "gn:feature_class":"P",
    "gn:feature_code":"PPL",
    "gn:name":"Yanchanggounao",
    "gn:population":0,
    "gn:timezone":"Asia/Shanghai",
    "iso:country":"CN",
    "name:zho_x_preferred":[
        "\u5ef6\u957f\u6c9f\u8111"
    ],
    "wof:name":"Yanchanggounao",
    "wof:placetype":"locality"
},
  "geometry": {"coordinates":[108.63269,33.34224],"type":"Point"}
}