{
  "type": "Feature",
  "properties": {
    "gn:admin1_code":"18.0",
    "gn:asciiname":"Zaigoutang",
    "gn:country_code":"CN",
    "gn:dem":842,
    "gn:feature_class":"P",
    "gn:feature_code":"PPL",
    "gn:name":"Zaigoutang",
    "gn:population":0,
    "gn:timezone":"Asia/Shanghai",
    "iso:country":"CN",
    "name:zho_x_preferred":[
        "\u54c9\u72d7\u5858"
    ],
    "wof:name":"Zaigoutang",
    "wof:placetype":"locality"
},
  "geometry": {"coordinates":[108.765,27.6349],"type":"Point"}
}