{
  "type": "Feature",
  "properties": {
    "gn:admin1_code":"32.0",
    "gn:asciiname":"Taiyanggou",
    "gn:country_code":"CN",
    "gn:dem":301,
    "gn:feature_class":"P",
    "gn:feature_code":"PPL",
    "gn:name":"Taiyanggou",
    "gn:population":0,
    "gn:timezone":"Asia/Shanghai",
    "iso:country":"CN",
    "name:zho_x_preferred":[
        "\u592a\u9633\u6c9f"
    ],
    "wof:name":"Taiyanggou",
    "wof:placetype":"locality"
},
  "geometry": {"coordinates":[106.009,30.7099],"type":"Point"}
}