{
  "type": "Feature",
  "properties": {
    "gn:admin1_code":"29.0",
    "gn:asciiname":"Mianshawan",
    "gn:country_code":"CN",
    "gn:dem":920,
    "gn:feature_class":"P",
    "gn:feature_code":"PPL",
    "gn:name":"Mianshawan",
    "gn:population":0,
    "gn:timezone":"Asia/Shanghai",
    "iso:country":"CN",
    "name:zho_x_preferred":[
        "\u7ef5\u6c99\u6e7e"
    ],
    "wof:name":"Mianshawan",
    "wof:placetype":"locality"
},
  "geometry": {"coordinates":[102.863,26.3369],"type":"Point"}
}