{
  "type": "Feature",
  "properties": {
    "gn:admin1_code":"02",
    "gn:asciiname":"Banliao",
    "gn:country_code":"CN",
    "gn:dem":295,
    "gn:feature_class":"P",
    "gn:feature_code":"PPL",
    "gn:name":"Banliao",
    "gn:population":0,
    "gn:timezone":"Asia/Shanghai",
    "iso:country":"CN",
    "name:und_x_variant":[
        "Pan-liao",
        "Banliao"
    ],
    "name:zho_x_preferred":[
        "\u677f\u6599"
    ],
    "wof:name":"Banliao",
    "wof:placetype":"locality"
},
  "geometry": {"coordinates":[120.86109999999999,28.5706],"type":"Point"}
}