{
  "type": "Feature",
  "properties": {
    "gn:admin1_code":"16.0",
    "gn:asciiname":"Dalang",
    "gn:country_code":"CN",
    "gn:dem":306,
    "gn:feature_class":"P",
    "gn:feature_code":"PPL",
    "gn:name":"Dalang",
    "gn:population":0,
    "gn:timezone":"Asia/Shanghai",
    "iso:country":"CN",
    "name:ceb_x_preferred":[
        "Dalang"
    ],
    "name:deu_x_preferred":[
        "Dalang"
    ],
    "name:nld_x_preferred":[
        "Dalang"
    ],
    "name:sco_x_preferred":[
        "Dalang"
    ],
    "name:swe_x_preferred":[
        "Dalang"
    ],
    "name:zho_x_preferred":[
        "\u5927\u6717"
    ],
    "wof:name":"Dalang",
    "wof:placetype":"locality"
},
  "geometry": {"coordinates":[111.298,23.719],"type":"Point"}
}