{
  "type": "Feature",
  "properties": {
    "gn:admin1_code":"25.0",
    "gn:asciiname":"Xiaozhuliu",
    "gn:country_code":"CN",
    "gn:dem":51,
    "gn:feature_class":"P",
    "gn:feature_code":"PPL",
    "gn:name":"Xiaozhuliu",
    "gn:population":0,
    "gn:timezone":"Asia/Shanghai",
    "iso:country":"CN",
    "name:zho_x_preferred":[
        "\u5c0f\u8bf8\u6d41"
    ],
    "wof:name":"Xiaozhuliu",
    "wof:placetype":"locality"
},
  "geometry": {"coordinates":[120.20560999999999,37.42575],"type":"Point"}
}