{
  "type": "Feature",
  "properties": {
    "gn:admin1_code":"3.0",
    "gn:asciiname":"Tangyuancun",
    "gn:country_code":"CN",
    "gn:dem":67,
    "gn:feature_class":"P",
    "gn:feature_code":"PPL",
    "gn:name":"Tangyuancun",
    "gn:population":0,
    "gn:timezone":"Asia/Shanghai",
    "iso:country":"CN",
    "name:und_x_variant":[
        "\u6c64\u6e90\u6751"
    ],
    "wof:name":"Tangyuancun",
    "wof:placetype":"locality"
},
  "geometry": {"coordinates":[116.96380000000001,28.53184000000001],"type":"Point"}
}