{
  "type": "Feature",
  "properties": {
    "gn:admin1_code":"30.0",
    "gn:asciiname":"Chengongping Shangcun",
    "gn:country_code":"CN",
    "gn:dem":451,
    "gn:feature_class":"P",
    "gn:feature_code":"PPL",
    "gn:name":"Chengongping Shangcun",
    "gn:population":0,
    "gn:timezone":"Asia/Shanghai",
    "iso:country":"CN",
    "name:zho_x_preferred":[
        "\u9648\u516c\u576a\u4e0a\u6751"
    ],
    "wof:name":"Chengongping Shangcun",
    "wof:placetype":"locality"
},
  "geometry": {"coordinates":[116.18155,24.13668],"type":"Point"}
}