{
  "type": "Feature",
  "properties": {
    "gn:admin1_code":"5",
    "gn:asciiname":"Tianbao",
    "gn:country_code":"CN",
    "gn:dem":303,
    "gn:feature_class":"P",
    "gn:feature_code":"PPL",
    "gn:name":"Tianbao",
    "gn:population":0,
    "gn:timezone":"Asia/Shanghai",
    "iso:country":"CN",
    "name:zho_x_preferred":[
        "\u7530\u5b9d"
    ],
    "wof:name":"Tianbao",
    "wof:placetype":"locality"
},
  "geometry": {"coordinates":[127.31408,43.8555],"type":"Point"}
}