{
  "type": "Feature",
  "properties": {
    "gn:admin1_code":"4.0",
    "gn:asciiname":"Huayuanzhuang",
    "gn:country_code":"CN",
    "gn:dem":17,
    "gn:feature_class":"P",
    "gn:feature_code":"PPL",
    "gn:name":"Huayuanzhuang",
    "gn:population":0,
    "gn:timezone":"Asia/Shanghai",
    "iso:country":"CN",
    "name:zho_x_preferred":[
        "\u82b1\u56ed\u5e84"
    ],
    "wof:name":"Huayuanzhuang",
    "wof:placetype":"locality"
},
  "geometry": {"coordinates":[118.99421,32.98008],"type":"Point"}
}