{
  "type": "Feature",
  "properties": {
    "gn:admin1_code":"15.0",
    "gn:asciiname":"Huojiaquan",
    "gn:country_code":"CN",
    "gn:dem":1779,
    "gn:feature_class":"P",
    "gn:feature_code":"PPL",
    "gn:name":"Huojiaquan",
    "gn:population":0,
    "gn:timezone":"Asia/Shanghai",
    "iso:country":"CN",
    "name:zho_x_preferred":[
        "\u4f19\u5bb6\u5708"
    ],
    "wof:name":"Huojiaquan",
    "wof:placetype":"locality"
},
  "geometry": {"coordinates":[103.98999999999999,36.0183],"type":"Point"}
}