{
  "type": "Feature",
  "properties": {
    "gn:admin1_code":"02",
    "gn:asciiname":"Ban'aocun",
    "gn:country_code":"CN",
    "gn:dem":138,
    "gn:feature_class":"P",
    "gn:feature_code":"PPL",
    "gn:name":"Ban\u2019aocun",
    "gn:population":0,
    "gn:timezone":"Asia/Shanghai",
    "iso:country":"CN",
    "name:und_x_variant":[
        "Pan-ao",
        "Ban\u2019ao",
        "\u534a\u5c99",
        "Ban\u2019aocun"
    ],
    "name:zho_x_preferred":[
        "\u534a\u5c99\u6751"
    ],
    "wof:name":"Ban'aocun",
    "wof:placetype":"locality"
},
  "geometry": {"coordinates":[121.29205,30.06166],"type":"Point"}
}