{
  "type": "Feature",
  "properties": {
    "gn:admin1_code":"2.0",
    "gn:asciiname":"Linshikeng",
    "gn:country_code":"CN",
    "gn:dem":430,
    "gn:feature_class":"P",
    "gn:feature_code":"PPL",
    "gn:name":"Linshikeng",
    "gn:population":0,
    "gn:timezone":"Asia/Shanghai",
    "iso:country":"CN",
    "name:zho_x_preferred":[
        "\u6797\u77f3\u5751"
    ],
    "wof:name":"Linshikeng",
    "wof:placetype":"locality"
},
  "geometry": {"coordinates":[118.90367999999999,28.21315],"type":"Point"}
}