{
  "type": "Feature",
  "properties": {
    "gn:admin1_code":"15.0",
    "gn:asciiname":"Xiaxiaowan",
    "gn:country_code":"CN",
    "gn:dem":1772,
    "gn:feature_class":"P",
    "gn:feature_code":"PPL",
    "gn:name":"Xiaxiaowan",
    "gn:population":0,
    "gn:timezone":"Asia/Shanghai",
    "iso:country":"CN",
    "name:zho_x_preferred":[
        "\u4e0b\u5c0f\u6e7e"
    ],
    "wof:name":"Xiaxiaowan",
    "wof:placetype":"locality"
},
  "geometry": {"coordinates":[104.845,36.9454],"type":"Point"}
}