{
  "type": "Feature",
  "properties": {
    "gn:admin1_code":"32.0",
    "gn:asciiname":"Zikujiaoba",
    "gn:country_code":"CN",
    "gn:dem":2282,
    "gn:feature_class":"P",
    "gn:feature_code":"PPL",
    "gn:name":"Zikujiaoba",
    "gn:population":0,
    "gn:timezone":"Asia/Shanghai",
    "iso:country":"CN",
    "name:zho_x_preferred":[
        "\u5b50\u5e93\u811a\u5df4"
    ],
    "wof:name":"Zikujiaoba",
    "wof:placetype":"locality"
},
  "geometry": {"coordinates":[102.304,28.1406],"type":"Point"}
}