{
  "type": "Feature",
  "properties": {
    "gn:admin1_code":"30",
    "gn:asciiname":"Wentougen",
    "gn:country_code":"CN",
    "gn:dem":51,
    "gn:feature_class":"P",
    "gn:feature_code":"PPL",
    "gn:name":"Wentougen",
    "gn:population":0,
    "gn:timezone":"Asia/Shanghai",
    "iso:country":"CN",
    "name:zho_x_preferred":[
        "\u6587\u5934\u6839"
    ],
    "wof:name":"Wentougen",
    "wof:placetype":"locality"
},
  "geometry": {"coordinates":[111.9243,22.33807],"type":"Point"}
}