{
  "type": "Feature",
  "properties": {
    "gn:admin1_code":"14.0",
    "gn:asciiname":"Deri'a",
    "gn:country_code":"CN",
    "gn:dem":3718,
    "gn:feature_class":"P",
    "gn:feature_code":"PPL",
    "gn:name":"Deri\u2019a",
    "gn:population":0,
    "gn:timezone":"Asia/Urumqi",
    "iso:country":"CN",
    "name:und_x_variant":[
        "Deri\u2019a"
    ],
    "name:zho_x_preferred":[
        "\u5f97\u65e5\u963f"
    ],
    "wof:name":"Deri'a",
    "wof:placetype":"locality"
},
  "geometry": {"coordinates":[97.13223000000001,31.65311],"type":"Point"}
}