{
  "type": "Feature",
  "properties": {
    "gn:admin1_code":"4.0",
    "gn:asciiname":"Bangxing",
    "gn:country_code":"CN",
    "gn:dem":6,
    "gn:feature_class":"P",
    "gn:feature_code":"PPL",
    "gn:name":"Bangxing",
    "gn:population":0,
    "gn:timezone":"Asia/Shanghai",
    "iso:country":"CN",
    "name:ceb_x_preferred":[
        "Bangxing"
    ],
    "name:fas_x_preferred":[
        "\u0628\u0627\u0646\u06af\u0634\u06cc\u0646\u06af"
    ],
    "name:fra_x_preferred":[
        "Bangxing"
    ],
    "name:msa_x_preferred":[
        "Bangxing"
    ],
    "name:swe_x_preferred":[
        "Bangxing"
    ],
    "name:zho_x_preferred":[
        "\u508d\u674f"
    ],
    "name:zho_x_variant":[
        "\u65c1\u8f9b\u4e61"
    ],
    "wof:name":"Bangxing",
    "wof:placetype":"locality"
},
  "geometry": {"coordinates":[119.09446,31.88096],"type":"Point"}
}