{
  "type": "Feature",
  "properties": {
    "gn:admin1_code":"19.0",
    "gn:asciiname":"Zhangjiagang",
    "gn:country_code":"CN",
    "gn:dem":113,
    "gn:feature_class":"P",
    "gn:feature_code":"PPL",
    "gn:name":"Zhangjiagang",
    "gn:population":0,
    "gn:timezone":"Asia/Shanghai",
    "iso:country":"CN",
    "name:ara_x_preferred":[
        "\u062a\u0634\u0627\u0646\u063a \u062c\u064a\u0627\u063a\u0627\u0646\u063a"
    ],
    "name:ceb_x_preferred":[
        "Zhangjiagang"
    ],
    "name:deu_x_preferred":[
        "Zhangjiagang"
    ],
    "name:fas_x_preferred":[
        "\u0698\u0627\u0646\u06af\u0698\u06cc\u0627\u0646\u06af\u0627\u0646\u06af"
    ],
    "name:fra_x_preferred":[
        "Zhangjiagang"
    ],
    "name:ita_x_preferred":[
        "Zhangjiagang"
    ],
    "name:jpn_x_preferred":[
        "\u5f35\u5bb6\u6e2f\u5e02"
    ],
    "name:kik_x_preferred":[
        "Zhangjiagang"
    ],
    "name:kor_x_preferred":[
        "\uc7a5\uc790\uac15\uc2dc"
    ],
    "name:mlg_x_preferred":[
        "Zhangjiagang"
    ],
    "name:nor_x_preferred":[
        "Zhangjiagang"
    ],
    "name:rus_x_preferred":[
        "\u0427\u0436\u0430\u043d\u0446\u0437\u044f\u0433\u0430\u043d"
    ],
    "name:spa_x_preferred":[
        "Zhangjiagang"
    ],
    "name:swe_x_preferred":[
        "Zhangjiagang"
    ],
    "name:tgl_x_preferred":[
        "Zhangjiagang"
    ],
    "name:urd_x_preferred":[
        "\u0698\u0627\u0646\u06af\u062c\u06cc\u0627\u06af\u0627\u0646\u06af"
    ],
    "name:war_x_preferred":[
        "Zhangjiagang"
    ],
    "name:wuu_x_preferred":[
        "\u5f20\u5bb6\u6e2f\u5e02"
    ],
    "name:zho_x_preferred":[
        "\u5f20\u5bb6\u5c97"
    ],
    "name:zho_x_variant":[
        "\u5f20\u5bb6\u6e2f\u5e02"
    ],
    "wof:name":"Zhangjiagang",
    "wof:placetype":"locality"
},
  "geometry": {"coordinates":[123.373,42.6803],"type":"Point"}
}