{
  "type": "Feature",
  "properties": {
    "gn:admin1_code":"29.0",
    "gn:asciiname":"Xiaoxinzhai",
    "gn:country_code":"CN",
    "gn:dem":1418,
    "gn:feature_class":"P",
    "gn:feature_code":"PPL",
    "gn:name":"Xiaoxinzhai",
    "gn:population":0,
    "gn:timezone":"Asia/Shanghai",
    "iso:country":"CN",
    "name:zho_x_preferred":[
        "\u5c0f\u65b0\u5be8"
    ],
    "wof:name":"Xiaoxinzhai",
    "wof:placetype":"locality"
},
  "geometry": {"coordinates":[102.828,23.7496],"type":"Point"}
}