{
  "type": "Feature",
  "properties": {
    "gn:admin1_code":"30.0",
    "gn:asciiname":"Shazibiao",
    "gn:country_code":"CN",
    "gn:dem":218,
    "gn:feature_class":"P",
    "gn:feature_code":"PPL",
    "gn:name":"Shazibiao",
    "gn:population":0,
    "gn:timezone":"Asia/Shanghai",
    "iso:country":"CN",
    "name:zho_x_preferred":[
        "\u6c99\u5b50\u8868"
    ],
    "wof:name":"Shazibiao",
    "wof:placetype":"locality"
},
  "geometry": {"coordinates":[111.46392,23.36792],"type":"Point"}
}