{
  "type": "Feature",
  "properties": {
    "gn:admin1_code":"8.0",
    "gn:asciiname":"Nanpaizi",
    "gn:country_code":"CN",
    "gn:dem":198,
    "gn:feature_class":"P",
    "gn:feature_code":"PPL",
    "gn:name":"Nanpaizi",
    "gn:population":0,
    "gn:timezone":"Asia/Shanghai",
    "iso:country":"CN",
    "name:zho_x_preferred":[
        "\u5357\u6392\u5b50"
    ],
    "wof:name":"Nanpaizi",
    "wof:placetype":"locality"
},
  "geometry": {"coordinates":[127.15812,45.56299],"type":"Point"}
}