{
  "type": "Feature",
  "properties": {
    "gn:admin1_code":"4.0",
    "gn:asciiname":"Lijiatan",
    "gn:country_code":"CN",
    "gn:dem":5,
    "gn:feature_class":"P",
    "gn:feature_code":"PPL",
    "gn:name":"Lijiatan",
    "gn:population":0,
    "gn:timezone":"Asia/Shanghai",
    "iso:country":"CN",
    "name:zho_x_preferred":[
        "Lijiatan"
    ],
    "name:zho_x_variant":[
        "\u674e\u5bb6\u6ee9"
    ],
    "wof:name":"Lijiatan",
    "wof:placetype":"locality"
},
  "geometry": {"coordinates":[119.32151,33.49674],"type":"Point"}
}