{
  "type": "Feature",
  "properties": {
    "gn:admin1_code":"4.0",
    "gn:asciiname":"Guochang",
    "gn:country_code":"CN",
    "gn:dem":17,
    "gn:feature_class":"P",
    "gn:feature_code":"PPL",
    "gn:name":"Guochang",
    "gn:population":0,
    "gn:timezone":"Asia/Shanghai",
    "iso:country":"CN",
    "name:zho_x_preferred":[
        "\u679c\u573a"
    ],
    "wof:name":"Guochang",
    "wof:placetype":"locality"
},
  "geometry": {"coordinates":[118.89928999999999,32.05591],"type":"Point"}
}