{
  "type": "Feature",
  "properties": {
    "gn:admin1_code":"32.0",
    "gn:asciiname":"Jianshanping",
    "gn:country_code":"CN",
    "gn:dem":756,
    "gn:feature_class":"P",
    "gn:feature_code":"PPL",
    "gn:name":"Jianshanping",
    "gn:population":0,
    "gn:timezone":"Asia/Shanghai",
    "iso:country":"CN",
    "name:zho_x_preferred":[
        "\u5c16\u5c71\u576a"
    ],
    "wof:name":"Jianshanping",
    "wof:placetype":"locality"
},
  "geometry": {"coordinates":[107.322,31.8138],"type":"Point"}
}