{
  "type": "Feature",
  "properties": {
    "gn:admin1_code":"32.0",
    "gn:asciiname":"Wulongjing",
    "gn:country_code":"CN",
    "gn:dem":444,
    "gn:feature_class":"P",
    "gn:feature_code":"PPL",
    "gn:name":"Wulongjing",
    "gn:population":0,
    "gn:timezone":"Asia/Shanghai",
    "iso:country":"CN",
    "name:zho_x_preferred":[
        "\u4e94\u9f99\u4e95"
    ],
    "wof:name":"Wulongjing",
    "wof:placetype":"locality"
},
  "geometry": {"coordinates":[104.88,30.1264],"type":"Point"}
}