{
  "type": "Feature",
  "properties": {
    "gn:admin1_code":"16.0",
    "gn:asciiname":"Shipen",
    "gn:country_code":"CN",
    "gn:dem":202,
    "gn:feature_class":"P",
    "gn:feature_code":"PPL",
    "gn:name":"Shipen",
    "gn:population":0,
    "gn:timezone":"Asia/Shanghai",
    "iso:country":"CN",
    "name:zho_x_preferred":[
        "\u77f3\u76c6"
    ],
    "wof:name":"Shipen",
    "wof:placetype":"locality"
},
  "geometry": {"coordinates":[108.164,24.5433],"type":"Point"}
}