{
  "type": "Feature",
  "properties": {
    "gn:admin1_code":"32.0",
    "gn:asciiname":"Shangmachang",
    "gn:country_code":"CN",
    "gn:dem":2593,
    "gn:feature_class":"P",
    "gn:feature_code":"PPL",
    "gn:name":"Shangmachang",
    "gn:population":0,
    "gn:timezone":"Asia/Shanghai",
    "iso:country":"CN",
    "name:zho_x_preferred":[
        "\u4e0a\u9a6c\u5382"
    ],
    "wof:name":"Shangmachang",
    "wof:placetype":"locality"
},
  "geometry": {"coordinates":[102.548,31.022],"type":"Point"}
}