{
  "type": "Feature",
  "properties": {
    "gn:admin1_code":"2.0",
    "gn:asciiname":"Jinlingtou",
    "gn:country_code":"CN",
    "gn:dem":598,
    "gn:feature_class":"P",
    "gn:feature_code":"PPL",
    "gn:name":"Jinlingtou",
    "gn:population":0,
    "gn:timezone":"Asia/Shanghai",
    "iso:country":"CN",
    "name:zho_x_preferred":[
        "\u91d1\u5cad\u5934"
    ],
    "wof:name":"Jinlingtou",
    "wof:placetype":"locality"
},
  "geometry": {"coordinates":[119.90882999999999,28.62435],"type":"Point"}
}