{
  "type": "Feature",
  "properties": {
    "gn:admin1_code":"19",
    "gn:asciiname":"Wangqingmen Chaoxiancun",
    "gn:country_code":"CN",
    "gn:dem":394,
    "gn:feature_class":"P",
    "gn:feature_code":"PPL",
    "gn:name":"Wangqingmen Chaoxiancun",
    "gn:population":0,
    "gn:timezone":"Asia/Shanghai",
    "iso:country":"CN",
    "name:und_x_variant":[
        "Wang-ch\u2019ing-men",
        "Wangqingmen",
        "Wangqingmenchaoxianzu",
        "Wangqingmen Chaoxiancun"
    ],
    "name:zho_x_preferred":[
        "\u65fa\u6e05\u95e8\u671d\u9c9c\u6751"
    ],
    "wof:name":"Wangqingmen Chaoxiancun",
    "wof:placetype":"locality"
},
  "geometry": {"coordinates":[125.30038999999999,41.68132],"type":"Point"}
}