{
  "type": "Feature",
  "properties": {
    "gn:admin1_code":"14.0",
    "gn:asciiname":"Daruo",
    "gn:country_code":"CN",
    "gn:dem":4051,
    "gn:feature_class":"P",
    "gn:feature_code":"PPL",
    "gn:name":"Daruo",
    "gn:population":0,
    "gn:timezone":"Asia/Urumqi",
    "iso:country":"CN",
    "name:zho_x_preferred":[
        "\u6253\u82e5"
    ],
    "wof:name":"Daruo",
    "wof:placetype":"locality"
},
  "geometry": {"coordinates":[96.36714000000001,30.82515],"type":"Point"}
}