{
  "type": "Feature",
  "properties": {
    "gn:admin1_code":"13.0",
    "gn:asciiname":"Kairangguluke",
    "gn:country_code":"CN",
    "gn:dem":1165,
    "gn:feature_class":"P",
    "gn:feature_code":"PPL",
    "gn:name":"Kairangguluke",
    "gn:population":0,
    "gn:timezone":"Asia/Shanghai",
    "iso:country":"CN",
    "name:zho_x_preferred":[
        "\u5580\u8ba9\u53e4\u9c81\u514b"
    ],
    "wof:name":"Kairangguluke",
    "wof:placetype":"locality"
},
  "geometry": {"coordinates":[77.36773000000002,39.70296],"type":"Point"}
}