{
  "type": "Feature",
  "properties": {
    "gn:admin1_code":"11",
    "gn:asciiname":"Anding",
    "gn:cc2":"CN",
    "gn:country_code":"CN",
    "gn:dem":89,
    "gn:feature_class":"P",
    "gn:feature_code":"PPL",
    "gn:name":"Anding",
    "gn:population":0,
    "gn:timezone":"Asia/Shanghai",
    "iso:country":"CN",
    "name:und_x_variant":[
        "An-ting-ch\u2019iao",
        "Anding"
    ],
    "wof:name":"Anding",
    "wof:placetype":"locality"
},
  "geometry": {"coordinates":[113.66667,28.58139000000001],"type":"Point"}
}