{
  "type": "Feature",
  "properties": {
    "gn:admin1_code":"24",
    "gn:asciiname":"Beishe",
    "gn:cc2":"CN",
    "gn:country_code":"CN",
    "gn:dem":1065,
    "gn:feature_class":"P",
    "gn:feature_code":"PPL",
    "gn:name":"Beishe",
    "gn:population":0,
    "gn:timezone":"Asia/Shanghai",
    "iso:country":"CN",
    "name:und_x_variant":[
        "Pei-she",
        "Pei-she-ts\u2019un",
        "Beishe"
    ],
    "wof:name":"Beishe",
    "wof:placetype":"locality"
},
  "geometry": {"coordinates":[113.09361,35.85361],"type":"Point"}
}