{
  "type": "Feature",
  "properties": {
    "gn:admin1_code":"9",
    "gn:asciiname":"Louzhang",
    "gn:country_code":"CN",
    "gn:dem":129,
    "gn:feature_class":"P",
    "gn:feature_code":"PPL",
    "gn:name":"Louzhang",
    "gn:population":0,
    "gn:timezone":"Asia/Shanghai",
    "iso:country":"CN",
    "name:und_x_variant":[
        "\u697c\u5f20",
        "Louzhang"
    ],
    "wof:name":"Louzhang",
    "wof:placetype":"locality"
},
  "geometry": {"coordinates":[112.93546000000001,33.70191],"type":"Point"}
}