{
  "type": "Feature",
  "properties": {
    "gn:admin1_code":"7",
    "gn:asciiname":"Junbing",
    "gn:country_code":"CN",
    "gn:dem":11,
    "gn:feature_class":"P",
    "gn:feature_code":"PPL",
    "gn:name":"Junbing",
    "gn:population":0,
    "gn:timezone":"Asia/Shanghai",
    "iso:country":"CN",
    "name:und_x_variant":[
        "\u83cc\u67c4"
    ],
    "name:zho_x_preferred":[
        "\u83cc\u67c4"
    ],
    "wof:name":"Junbing",
    "wof:placetype":"locality"
},
  "geometry": {"coordinates":[118.49388999999999,24.71417000000001],"type":"Point"}
}