{
  "type": "Feature",
  "properties": {
    "gn:admin1_code":"33.0",
    "gn:asciiname":"Laofenshan",
    "gn:country_code":"CN",
    "gn:dem":294,
    "gn:feature_class":"P",
    "gn:feature_code":"PPL",
    "gn:name":"Laofenshan",
    "gn:population":0,
    "gn:timezone":"Asia/Shanghai",
    "iso:country":"CN",
    "name:zho_x_preferred":[
        "\u8001\u575f\u5c71"
    ],
    "wof:name":"Laofenshan",
    "wof:placetype":"locality"
},
  "geometry": {"coordinates":[105.73193999999999,30.14507],"type":"Point"}
}