{
  "type": "Feature",
  "properties": {
    "gn:admin1_code":"15.0",
    "gn:asciiname":"Qishilipu",
    "gn:country_code":"CN",
    "gn:dem":1473,
    "gn:feature_class":"P",
    "gn:feature_code":"PPL",
    "gn:name":"Qishilipu",
    "gn:population":0,
    "gn:timezone":"Asia/Shanghai",
    "iso:country":"CN",
    "name:zho_x_preferred":[
        "\u4e03\u5341\u91cc\u94fa"
    ],
    "wof:name":"Qishilipu",
    "wof:placetype":"locality"
},
  "geometry": {"coordinates":[105.405,34.6238],"type":"Point"}
}