{
  "type": "Feature",
  "properties": {
    "gn:admin1_code":"18",
    "gn:asciiname":"Jiubudi",
    "gn:country_code":"CN",
    "gn:dem":1680,
    "gn:feature_class":"P",
    "gn:feature_code":"PPL",
    "gn:name":"Jiubudi",
    "gn:population":0,
    "gn:timezone":"Asia/Shanghai",
    "iso:country":"CN",
    "name:zho_x_preferred":[
        "\u4e5d\u8865\u5e95"
    ],
    "wof:name":"Jiubudi",
    "wof:placetype":"locality"
},
  "geometry": {"coordinates":[104.782,25.5965],"type":"Point"}
}