{
  "type": "Feature",
  "properties": {
    "gn:admin1_code":"30",
    "gn:asciiname":"Hongyou",
    "gn:country_code":"CN",
    "gn:dem":57,
    "gn:feature_class":"P",
    "gn:feature_code":"PPL",
    "gn:name":"Hongyou",
    "gn:population":0,
    "gn:timezone":"Asia/Urumqi",
    "iso:country":"CN",
    "name:zho_x_preferred":[
        "\u6d2a\u5c24"
    ],
    "wof:name":"Hongyou",
    "wof:placetype":"locality"
},
  "geometry": {"coordinates":[110.99585,21.84376],"type":"Point"}
}