{
  "type": "Feature",
  "properties": {
    "gn:admin1_code":"12.0",
    "gn:asciiname":"Baojiatian",
    "gn:country_code":"CN",
    "gn:dem":55,
    "gn:feature_class":"P",
    "gn:feature_code":"PPL",
    "gn:name":"Baojiatian",
    "gn:population":0,
    "gn:timezone":"Asia/Shanghai",
    "iso:country":"CN",
    "name:zho_x_preferred":[
        "\u5305\u5bb6\u7530"
    ],
    "wof:name":"Baojiatian",
    "wof:placetype":"locality"
},
  "geometry": {"coordinates":[114.55868999999998,30.99595],"type":"Point"}
}