{
  "type": "Feature",
  "properties": {
    "gn:admin1_code":"2.0",
    "gn:asciiname":"Qiantouzi",
    "gn:country_code":"CN",
    "gn:dem":705,
    "gn:feature_class":"P",
    "gn:feature_code":"PPL",
    "gn:name":"Qiantouzi",
    "gn:population":0,
    "gn:timezone":"Asia/Shanghai",
    "iso:country":"CN",
    "name:zho_x_preferred":[
        "\u4e7e\u5934\u4ed4"
    ],
    "wof:name":"Qiantouzi",
    "wof:placetype":"locality"
},
  "geometry": {"coordinates":[120.12701,27.8073],"type":"Point"}
}