{
  "type": "Feature",
  "properties": {
    "gn:admin1_code":"18",
    "gn:asciiname":"Lujiazhai",
    "gn:country_code":"CN",
    "gn:dem":945,
    "gn:feature_class":"P",
    "gn:feature_code":"PPL",
    "gn:name":"Lujiazhai",
    "gn:population":0,
    "gn:timezone":"Asia/Shanghai",
    "iso:country":"CN",
    "name:zho_x_preferred":[
        "\u9c81\u5bb6\u5be8"
    ],
    "wof:name":"Lujiazhai",
    "wof:placetype":"locality"
},
  "geometry": {"coordinates":[106.804,27.4473],"type":"Point"}
}