{
  "type": "Feature",
  "properties": {
    "gn:admin1_code":"8.0",
    "gn:asciiname":"Lianfangcun",
    "gn:country_code":"CN",
    "gn:dem":280,
    "gn:feature_class":"P",
    "gn:feature_code":"PPL",
    "gn:name":"Lianfangcun",
    "gn:population":0,
    "gn:timezone":"Asia/Shanghai",
    "iso:country":"CN",
    "name:zho_x_preferred":[
        "\u8054\u653e\u6751"
    ],
    "wof:name":"Lianfangcun",
    "wof:placetype":"locality"
},
  "geometry": {"coordinates":[125.66379999999999,48.13811],"type":"Point"}
}