{
  "type": "Feature",
  "properties": {
    "gn:admin1_code":"6.0",
    "gn:asciiname":"Enba Quni",
    "gn:country_code":"CN",
    "gn:dem":3911,
    "gn:feature_class":"P",
    "gn:feature_code":"PPL",
    "gn:name":"Enba Quni",
    "gn:population":0,
    "gn:timezone":"Asia/Urumqi",
    "iso:country":"CN",
    "name:zho_x_preferred":[
        "\u6069\u5df4\u66f2\u5c3c"
    ],
    "wof:name":"Enba Quni",
    "wof:placetype":"locality"
},
  "geometry": {"coordinates":[95.92917,32.06312],"type":"Point"}
}