{
  "type": "Feature",
  "properties": {
    "gn:admin1_code":"11.0",
    "gn:asciiname":"Fuxing'an",
    "gn:country_code":"CN",
    "gn:dem":602,
    "gn:feature_class":"P",
    "gn:feature_code":"PPL",
    "gn:name":"Fuxing\u2019an",
    "gn:population":0,
    "gn:timezone":"Asia/Shanghai",
    "iso:country":"CN",
    "name:und_x_variant":[
        "Fuxing\u2019an"
    ],
    "name:zho_x_preferred":[
        "\u5bcc\u5174\u5eb5"
    ],
    "wof:name":"Fuxing'an",
    "wof:placetype":"locality"
},
  "geometry": {"coordinates":[110.69877,27.77217000000001],"type":"Point"}
}