{
  "type": "Feature",
  "properties": {
    "gn:admin1_code":"32.0",
    "gn:asciiname":"Tuzhu",
    "gn:country_code":"CN",
    "gn:dem":573,
    "gn:feature_class":"P",
    "gn:feature_code":"PPL",
    "gn:name":"Tuzhu",
    "gn:population":0,
    "gn:timezone":"Asia/Shanghai",
    "iso:country":"CN",
    "name:zho_x_preferred":[
        "\u571f\u4e3b"
    ],
    "wof:name":"Tuzhu",
    "wof:placetype":"locality"
},
  "geometry": {"coordinates":[106.86199999999999,31.7238],"type":"Point"}
}