{
  "type": "Feature",
  "properties": {
    "gn:admin1_code":"8.0",
    "gn:asciiname":"Dehuabu",
    "gn:country_code":"CN",
    "gn:dem":155,
    "gn:feature_class":"P",
    "gn:feature_code":"PPL",
    "gn:name":"Dehuabu",
    "gn:population":0,
    "gn:timezone":"Asia/Shanghai",
    "iso:country":"CN",
    "name:zho_x_preferred":[
        "\u5fb7\u5316\u5821"
    ],
    "wof:name":"Dehuabu",
    "wof:placetype":"locality"
},
  "geometry": {"coordinates":[125.63029,46.2856],"type":"Point"}
}