{
  "type": "Feature",
  "properties": {
    "gn:admin1_code":"16.0",
    "gn:asciiname":"Nanyu",
    "gn:country_code":"CN",
    "gn:dem":72,
    "gn:feature_class":"P",
    "gn:feature_code":"PPL",
    "gn:name":"Nanyu",
    "gn:population":0,
    "gn:timezone":"Asia/Shanghai",
    "iso:country":"CN",
    "name:deu_x_preferred":[
        "Nanyu"
    ],
    "name:zho_x_preferred":[
        "\u5357\u9685"
    ],
    "wof:name":"Nanyu",
    "wof:placetype":"locality"
},
  "geometry": {"coordinates":[110.068,23.1633],"type":"Point"}
}