{
  "type": "Feature",
  "properties": {
    "gn:admin1_code":"1.0",
    "gn:asciiname":"Dalingcun",
    "gn:country_code":"CN",
    "gn:dem":27,
    "gn:feature_class":"P",
    "gn:feature_code":"PPL",
    "gn:name":"Dalingcun",
    "gn:population":0,
    "gn:timezone":"Asia/Shanghai",
    "iso:country":"CN",
    "name:zho_x_preferred":[
        "\u5927\u51cc\u6751"
    ],
    "wof:name":"Dalingcun",
    "wof:placetype":"locality"
},
  "geometry": {"coordinates":[117.9974,31.83159],"type":"Point"}
}