{
  "type": "Feature",
  "properties": {
    "gn:admin1_code":"3",
    "gn:asciiname":"Zengbian",
    "gn:country_code":"CN",
    "gn:dem":136,
    "gn:feature_class":"P",
    "gn:feature_code":"PPL",
    "gn:name":"Zengbian",
    "gn:population":0,
    "gn:timezone":"Asia/Shanghai",
    "iso:country":"CN",
    "name:zho_x_preferred":[
        "\u66fe\u8fb9"
    ],
    "wof:name":"Zengbian",
    "wof:placetype":"locality"
},
  "geometry": {"coordinates":[114.70699999999999,25.7358],"type":"Point"}
}