{
  "type": "Feature",
  "properties": {
    "gn:admin1_code":"30.0",
    "gn:asciiname":"Shuimeicun",
    "gn:country_code":"CN",
    "gn:dem":7,
    "gn:feature_class":"P",
    "gn:feature_code":"PPL",
    "gn:name":"Shuimeicun",
    "gn:population":0,
    "gn:timezone":"Asia/Shanghai",
    "iso:country":"CN",
    "name:und_x_variant":[
        "Shuimei"
    ],
    "name:zho_x_preferred":[
        "\u6c34\u7f8e\u6751"
    ],
    "wof:name":"Shuimeicun",
    "wof:placetype":"locality"
},
  "geometry": {"coordinates":[116.654,23.50978],"type":"Point"}
}