{
  "type": "Feature",
  "properties": {
    "gn:admin1_code":"29.0",
    "gn:asciiname":"Laodaozhai",
    "gn:country_code":"CN",
    "gn:dem":1271,
    "gn:feature_class":"P",
    "gn:feature_code":"PPL",
    "gn:name":"Laodaozhai",
    "gn:population":0,
    "gn:timezone":"Asia/Shanghai",
    "iso:country":"CN",
    "name:zho_x_preferred":[
        "\u8001\u5200\u5be8"
    ],
    "wof:name":"Laodaozhai",
    "wof:placetype":"locality"
},
  "geometry": {"coordinates":[101.666,22.9433],"type":"Point"}
}