{
  "type": "Feature",
  "properties": {
    "gn:admin1_code":"12.0",
    "gn:asciiname":"Baiyudong",
    "gn:country_code":"CN",
    "gn:dem":1136,
    "gn:feature_class":"P",
    "gn:feature_code":"PPL",
    "gn:name":"Baiyudong",
    "gn:population":0,
    "gn:timezone":"Asia/Shanghai",
    "iso:country":"CN",
    "name:zho_x_preferred":[
        "\u767d\u9c7c\u6d1e"
    ],
    "wof:name":"Baiyudong",
    "wof:placetype":"locality"
},
  "geometry": {"coordinates":[110.72204000000001,31.82834],"type":"Point"}
}