{
  "type": "Feature",
  "properties": {
    "gn:admin1_code":"26.0",
    "gn:asciiname":"Denglutan Sidui",
    "gn:country_code":"CN",
    "gn:dem":1246,
    "gn:feature_class":"P",
    "gn:feature_code":"PPLF",
    "gn:name":"Denglutan Sidui",
    "gn:population":0,
    "gn:timezone":"Asia/Shanghai",
    "iso:country":"CN",
    "name:zho_x_preferred":[
        "\u706f\u7089\u6ee9\u56db\u961f"
    ],
    "wof:name":"Denglutan Sidui",
    "wof:placetype":"locality"
},
  "geometry": {"coordinates":[109.36076,38.64427],"type":"Point"}
}