{
  "type": "Feature",
  "properties": {
    "gn:admin1_code":"02",
    "gn:asciiname":"Houxicun",
    "gn:country_code":"CN",
    "gn:dem":54,
    "gn:feature_class":"P",
    "gn:feature_code":"PPL",
    "gn:name":"Houxicun",
    "gn:population":0,
    "gn:timezone":"Asia/Shanghai",
    "iso:country":"CN",
    "name:und_x_variant":[
        "Hou-hsi-chieh",
        "Houxijie",
        "Houxi",
        "Houxicun"
    ],
    "name:zho_x_preferred":[
        "\u540e\u6eaa"
    ],
    "name:zho_x_variant":[
        "\u540e\u6eaa\u6751"
    ],
    "wof:name":"Houxicun",
    "wof:placetype":"locality"
},
  "geometry": {"coordinates":[118.74458,28.835],"type":"Point"}
}