{
  "type": "Feature",
  "properties": {
    "gn:admin1_code":"16.0",
    "gn:asciiname":"Limubi",
    "gn:country_code":"CN",
    "gn:dem":166,
    "gn:feature_class":"P",
    "gn:feature_code":"PPL",
    "gn:name":"Limubi",
    "gn:population":0,
    "gn:timezone":"Asia/Shanghai",
    "iso:country":"CN",
    "name:zho_x_preferred":[
        "\u5229\u6728\u5f3c"
    ],
    "wof:name":"Limubi",
    "wof:placetype":"locality"
},
  "geometry": {"coordinates":[109.929,22.3998],"type":"Point"}
}