{
  "type": "Feature",
  "properties": {
    "gn:admin1_code":"12.0",
    "gn:asciiname":"Dacaowan",
    "gn:country_code":"CN",
    "gn:dem":1080,
    "gn:feature_class":"P",
    "gn:feature_code":"PPL",
    "gn:name":"Dacaowan",
    "gn:population":0,
    "gn:timezone":"Asia/Shanghai",
    "iso:country":"CN",
    "name:zho_x_preferred":[
        "\u5927\u69fd\u6e7e"
    ],
    "wof:name":"Dacaowan",
    "wof:placetype":"locality"
},
  "geometry": {"coordinates":[109.64019,30.08064],"type":"Point"}
}