{
  "type": "Feature",
  "properties": {
    "gn:admin1_code":"21.0",
    "gn:asciiname":"Guojiacha",
    "gn:country_code":"CN",
    "gn:dem":1657,
    "gn:feature_class":"P",
    "gn:feature_code":"PPL",
    "gn:name":"Guojiacha",
    "gn:population":0,
    "gn:timezone":"Asia/Shanghai",
    "iso:country":"CN",
    "name:zho_x_preferred":[
        "\u90ed\u5bb6\u5c94"
    ],
    "wof:name":"Guojiacha",
    "wof:placetype":"locality"
},
  "geometry": {"coordinates":[106.45323,36.95885],"type":"Point"}
}