{
  "type": "Feature",
  "properties": {
    "gn:admin1_code":"7.0",
    "gn:asciiname":"Tangxie",
    "gn:country_code":"CN",
    "gn:dem":37,
    "gn:feature_class":"P",
    "gn:feature_code":"PPL",
    "gn:name":"Tangxie",
    "gn:population":0,
    "gn:timezone":"Asia/Shanghai",
    "iso:country":"CN",
    "name:zho_x_preferred":[
        "Tangxie"
    ],
    "name:zho_x_variant":[
        "\u6c64\u659c"
    ],
    "wof:name":"Tangxie",
    "wof:placetype":"locality"
},
  "geometry": {"coordinates":[119.31655000000001,26.15447],"type":"Point"}
}