{
  "type": "Feature",
  "properties": {
    "gn:admin1_code":"26.0",
    "gn:asciiname":"Zhubuli",
    "gn:country_code":"CN",
    "gn:dem":585,
    "gn:feature_class":"P",
    "gn:feature_code":"PPL",
    "gn:name":"Zhubuli",
    "gn:population":0,
    "gn:timezone":"Asia/Shanghai",
    "iso:country":"CN",
    "name:und_x_variant":[
        "\u795d\u535c\u674e"
    ],
    "wof:name":"Zhubuli",
    "wof:placetype":"locality"
},
  "geometry": {"coordinates":[107.89981,34.36024],"type":"Point"}
}