{
  "type": "Feature",
  "properties": {
    "gn:admin1_code":"29.0",
    "gn:asciiname":"Wei'e",
    "gn:country_code":"CN",
    "gn:dem":2423,
    "gn:feature_class":"P",
    "gn:feature_code":"PPL",
    "gn:name":"Wei\u2019e",
    "gn:population":0,
    "gn:timezone":"Asia/Shanghai",
    "iso:country":"CN",
    "name:und_x_variant":[
        "Wei\u2019e"
    ],
    "name:zho_x_preferred":[
        "\u672a\u4fc4"
    ],
    "wof:name":"Wei'e",
    "wof:placetype":"locality"
},
  "geometry": {"coordinates":[101.11799999999999,26.0157],"type":"Point"}
}