{
  "type": "Feature",
  "properties": {
    "gn:admin1_code":"24.0",
    "gn:asciiname":"Shileng",
    "gn:country_code":"CN",
    "gn:dem":1408,
    "gn:feature_class":"P",
    "gn:feature_code":"PPL",
    "gn:name":"Shileng",
    "gn:population":0,
    "gn:timezone":"Asia/Shanghai",
    "iso:country":"CN",
    "name:zho_x_preferred":[
        "\u77f3\u580e"
    ],
    "wof:name":"Shileng",
    "wof:placetype":"locality"
},
  "geometry": {"coordinates":[111.40989,39.09237],"type":"Point"}
}