{
  "type": "Feature",
  "properties": {
    "gn:admin1_code":"4.0",
    "gn:asciiname":"Fangxiangcun",
    "gn:country_code":"CN",
    "gn:dem":2,
    "gn:feature_class":"P",
    "gn:feature_code":"PPL",
    "gn:name":"Fangxiangcun",
    "gn:population":0,
    "gn:timezone":"Asia/Shanghai",
    "iso:country":"CN",
    "name:zho_x_preferred":[
        "\u65b9\u5411\u6751"
    ],
    "wof:name":"Fangxiangcun",
    "wof:placetype":"locality"
},
  "geometry": {"coordinates":[120.63507,32.94647],"type":"Point"}
}