{
  "type": "Feature",
  "properties": {
    "gn:admin1_code":"15.0",
    "gn:asciiname":"Wujiawanzhang",
    "gn:country_code":"CN",
    "gn:dem":1505,
    "gn:feature_class":"P",
    "gn:feature_code":"PPL",
    "gn:name":"Wujiawanzhang",
    "gn:population":0,
    "gn:timezone":"Asia/Shanghai",
    "iso:country":"CN",
    "name:und_x_variant":[
        "\u5434\u5bb6\u6e7e\u638c"
    ],
    "wof:name":"Wujiawanzhang",
    "wof:placetype":"locality"
},
  "geometry": {"coordinates":[107.08273,36.80371],"type":"Point"}
}