{
  "type": "Feature",
  "properties": {
    "gn:admin1_code":"5.0",
    "gn:asciiname":"Qian'ershisihaocun",
    "gn:country_code":"CN",
    "gn:dem":203,
    "gn:feature_class":"P",
    "gn:feature_code":"PPL",
    "gn:name":"Qian\u2019ershisihaocun",
    "gn:population":0,
    "gn:timezone":"Asia/Shanghai",
    "iso:country":"CN",
    "name:und_x_variant":[
        "Qian\u2019ershisihaocun"
    ],
    "name:zho_x_preferred":[
        "\u524d\u4e8c\u5341\u56db\u53f7\u6751"
    ],
    "wof:name":"Qian'ershisihaocun",
    "wof:placetype":"locality"
},
  "geometry": {"coordinates":[126.03328,45.02879],"type":"Point"}
}