{
  "type": "Feature",
  "properties": {
    "gn:admin1_code":"14",
    "gn:asciiname":"Kaibo",
    "gn:country_code":"CN",
    "gn:dem":3971,
    "gn:feature_class":"P",
    "gn:feature_code":"PPL",
    "gn:name":"Kaibo",
    "gn:population":0,
    "gn:timezone":"Asia/Urumqi",
    "iso:country":"CN",
    "name:bod_x_preferred":[
        "\u0f42\u0f51\u0f0b\u0f54\u0f7c"
    ],
    "name:und_x_variant":[
        "Kebu",
        "Gaibu"
    ],
    "name:zho_x_preferred":[
        "\u514b\u5e03"
    ],
    "name:zho_x_variant":[
        "\u6539\u5e03"
    ],
    "wof:name":"Kaibo",
    "wof:placetype":"locality"
},
  "geometry": {"coordinates":[91.03382999999999,29.89989000000001],"type":"Point"}
}