{
  "type": "Feature",
  "properties": {
    "gn:admin1_code":"10",
    "gn:asciiname":"Lushuichi",
    "gn:country_code":"CN",
    "gn:dem":573,
    "gn:feature_class":"P",
    "gn:feature_code":"PPL",
    "gn:name":"L\u00fcshuichi",
    "gn:population":0,
    "gn:timezone":"Asia/Shanghai",
    "iso:country":"CN",
    "name:und_x_variant":[
        "L\u00fcshuichi"
    ],
    "name:zho_x_preferred":[
        "\u7eff\u6c34\u6c60"
    ],
    "wof:name":"Lushuichi",
    "wof:placetype":"locality"
},
  "geometry": {"coordinates":[114.03,36.9074],"type":"Point"}
}