{
  "type": "Feature",
  "properties": {
    "gn:admin1_code":"02",
    "gn:asciiname":"Chao-chia-tz'u",
    "gn:country_code":"CN",
    "gn:dem":7,
    "gn:feature_class":"P",
    "gn:feature_code":"PPL",
    "gn:name":"Chao-chia-tz\u2019u",
    "gn:population":0,
    "gn:timezone":"Asia/Shanghai",
    "iso:country":"CN",
    "name:zho_x_preferred":[
        "Chao-chia-tz\u2019u"
    ],
    "wof:name":"Chao-chia-tz'u",
    "wof:placetype":"locality"
},
  "geometry": {"coordinates":[120.85306,28.06833],"type":"Point"}
}