{
  "type": "Feature",
  "properties": {
    "gn:admin1_code":"11.0",
    "gn:asciiname":"Muzi Yangjia",
    "gn:country_code":"CN",
    "gn:dem":106,
    "gn:feature_class":"P",
    "gn:feature_code":"PPL",
    "gn:name":"Muzi Yangjia",
    "gn:population":0,
    "gn:timezone":"Asia/Shanghai",
    "iso:country":"CN",
    "name:zho_x_preferred":[
        "\u6728\u6893\u6768\u5bb6"
    ],
    "wof:name":"Muzi Yangjia",
    "wof:placetype":"locality"
},
  "geometry": {"coordinates":[113.593,29.21493],"type":"Point"}
}