{
  "type": "Feature",
  "properties": {
    "gn:admin1_code":"30",
    "gn:asciiname":"Xintang",
    "gn:country_code":"CN",
    "gn:dem":205,
    "gn:feature_class":"P",
    "gn:feature_code":"PPL",
    "gn:name":"Xintang",
    "gn:population":0,
    "gn:timezone":"Asia/Shanghai",
    "iso:country":"CN",
    "name:zho_x_preferred":[
        "\u65b0\u5510"
    ],
    "name:zho_x_variant":[
        "\u65b0\u5858"
    ],
    "wof:name":"Xintang",
    "wof:placetype":"locality"
},
  "geometry": {"coordinates":[115.63273,23.42672],"type":"Point"}
}