{
  "type": "Feature",
  "properties": {
    "gn:admin1_code":"16.0",
    "gn:asciiname":"Xiaojiama",
    "gn:country_code":"CN",
    "gn:dem":237,
    "gn:feature_class":"P",
    "gn:feature_code":"PPL",
    "gn:name":"Xiaojiama",
    "gn:population":0,
    "gn:timezone":"Asia/Shanghai",
    "iso:country":"CN",
    "name:zho_x_preferred":[
        "\u5c0f\u67b6\u9a6c"
    ],
    "wof:name":"Xiaojiama",
    "wof:placetype":"locality"
},
  "geometry": {"coordinates":[110.267,24.5232],"type":"Point"}
}