{
  "type": "Feature",
  "properties": {
    "gn:admin1_code":"16.0",
    "gn:asciiname":"Chengshi",
    "gn:country_code":"CN",
    "gn:dem":127,
    "gn:feature_class":"P",
    "gn:feature_code":"PPL",
    "gn:name":"Chengshi",
    "gn:population":0,
    "gn:timezone":"Asia/Shanghai",
    "iso:country":"CN",
    "name:zho_x_preferred":[
        "\u7a0b\u77f3"
    ],
    "wof:name":"Chengshi",
    "wof:placetype":"locality"
},
  "geometry": {"coordinates":[111.33499999999999,24.528],"type":"Point"}
}