{
  "type": "Feature",
  "properties": {
    "gn:admin1_code":"12.0",
    "gn:asciiname":"Shanghan Tian",
    "gn:country_code":"CN",
    "gn:dem":893,
    "gn:feature_class":"P",
    "gn:feature_code":"PPL",
    "gn:name":"Shanghan Tian",
    "gn:population":0,
    "gn:timezone":"Asia/Shanghai",
    "iso:country":"CN",
    "name:zho_x_preferred":[
        "\u5c1a\u65f1\u7530"
    ],
    "wof:name":"Shanghan Tian",
    "wof:placetype":"locality"
},
  "geometry": {"coordinates":[110.21037,32.68275999999999],"type":"Point"}
}