{
  "type": "Feature",
  "properties": {
    "gn:admin1_code":"3",
    "gn:asciiname":"Huangbailing",
    "gn:country_code":"CN",
    "gn:dem":328,
    "gn:feature_class":"P",
    "gn:feature_code":"PPL",
    "gn:name":"Huangbailing",
    "gn:population":0,
    "gn:timezone":"Asia/Shanghai",
    "iso:country":"CN",
    "name:und_x_variant":[
        "\u9ec4\u67cf\u5cad"
    ],
    "wof:name":"Huangbailing",
    "wof:placetype":"locality"
},
  "geometry": {"coordinates":[116.13594999999999,27.16515],"type":"Point"}
}