{
  "type": "Feature",
  "properties": {
    "gn:admin1_code":"16.0",
    "gn:asciiname":"Longdao",
    "gn:country_code":"CN",
    "gn:dem":236,
    "gn:feature_class":"P",
    "gn:feature_code":"PPL",
    "gn:name":"Longdao",
    "gn:population":0,
    "gn:timezone":"Asia/Shanghai",
    "iso:country":"CN",
    "name:zho_x_preferred":[
        "\u9647\u5200"
    ],
    "wof:name":"Longdao",
    "wof:placetype":"locality"
},
  "geometry": {"coordinates":[106.58499999999999,22.4102],"type":"Point"}
}