{
  "type": "Feature",
  "properties": {
    "gn:admin1_code":"26.0",
    "gn:asciiname":"Duanjiayingcun",
    "gn:country_code":"CN",
    "gn:dem":417,
    "gn:feature_class":"P",
    "gn:feature_code":"PPL",
    "gn:name":"Duanjiayingcun",
    "gn:population":0,
    "gn:timezone":"Asia/Shanghai",
    "iso:country":"CN",
    "name:und_x_variant":[
        "\u6bb5\u5bb6\u8425\u6751"
    ],
    "wof:name":"Duanjiayingcun",
    "wof:placetype":"locality"
},
  "geometry": {"coordinates":[107.92910999999999,33.15682],"type":"Point"}
}