{
  "type": "Feature",
  "properties": {
    "gn:admin1_code":"4.0",
    "gn:asciiname":"Xiaozhuang",
    "gn:country_code":"CN",
    "gn:dem":39,
    "gn:feature_class":"P",
    "gn:feature_code":"PPL",
    "gn:name":"Xiaozhuang",
    "gn:population":0,
    "gn:timezone":"Asia/Shanghai",
    "iso:country":"CN",
    "name:und_x_variant":[
        "\u6653\u5e84"
    ],
    "wof:name":"Xiaozhuang",
    "wof:placetype":"locality"
},
  "geometry": {"coordinates":[118.70802,34.62453],"type":"Point"}
}