{
  "type": "Feature",
  "properties": {
    "gn:admin1_code":"6.0",
    "gn:asciiname":"Qubucangka",
    "gn:country_code":"CN",
    "gn:dem":3358,
    "gn:feature_class":"P",
    "gn:feature_code":"PPL",
    "gn:name":"Qubucangka",
    "gn:population":0,
    "gn:timezone":"Asia/Shanghai",
    "iso:country":"CN",
    "name:und_x_variant":[
        "\u66f2\u5e03\u85cf\u5361"
    ],
    "wof:name":"Qubucangka",
    "wof:placetype":"locality"
},
  "geometry": {"coordinates":[100.37241,35.61785],"type":"Point"}
}