{
  "type": "Feature",
  "properties": {
    "gn:admin1_code":"2.0",
    "gn:asciiname":"Xiaomiaotou",
    "gn:country_code":"CN",
    "gn:dem":7,
    "gn:feature_class":"P",
    "gn:feature_code":"PPL",
    "gn:name":"Xiaomiaotou",
    "gn:population":0,
    "gn:timezone":"Asia/Shanghai",
    "iso:country":"CN",
    "name:und_x_variant":[
        "\u5c0f\u5e99\u5934"
    ],
    "wof:name":"Xiaomiaotou",
    "wof:placetype":"locality"
},
  "geometry": {"coordinates":[120.57943,30.67916],"type":"Point"}
}