{
  "type": "Feature",
  "properties": {
    "gn:admin1_code":"32.0",
    "gn:asciiname":"Sichuan Pingzi",
    "gn:country_code":"CN",
    "gn:dem":1792,
    "gn:feature_class":"P",
    "gn:feature_code":"PPL",
    "gn:name":"Sichuan Pingzi",
    "gn:population":0,
    "gn:timezone":"Asia/Shanghai",
    "iso:country":"CN",
    "name:zho_x_preferred":[
        "\u56db\u5ddd\u576a\u5b50"
    ],
    "wof:name":"Sichuan Pingzi",
    "wof:placetype":"locality"
},
  "geometry": {"coordinates":[100.31851,27.73937],"type":"Point"}
}