{
  "type": "Feature",
  "properties": {
    "gn:admin1_code":"16.0",
    "gn:asciiname":"Liaoxiu",
    "gn:country_code":"CN",
    "gn:dem":105,
    "gn:feature_class":"P",
    "gn:feature_code":"PPL",
    "gn:name":"Liaoxiu",
    "gn:population":0,
    "gn:timezone":"Asia/Shanghai",
    "iso:country":"CN",
    "name:zho_x_preferred":[
        "\u50da\u79c0"
    ],
    "wof:name":"Liaoxiu",
    "wof:placetype":"locality"
},
  "geometry": {"coordinates":[110.473,23.0825],"type":"Point"}
}