{
  "type": "Feature",
  "properties": {
    "gn:admin1_code":"12.0",
    "gn:asciiname":"Xinji",
    "gn:country_code":"CN",
    "gn:dem":99,
    "gn:feature_class":"P",
    "gn:feature_code":"PPL",
    "gn:name":"Xinji",
    "gn:population":0,
    "gn:timezone":"Asia/Shanghai",
    "iso:country":"CN",
    "name:ara_x_preferred":[
        "\u0634\u064a\u0646\u062c\u064a"
    ],
    "name:deu_x_preferred":[
        "Xinji"
    ],
    "name:eus_x_preferred":[
        "Xinji"
    ],
    "name:fra_x_preferred":[
        "Xinji"
    ],
    "name:ita_x_preferred":[
        "Xinji"
    ],
    "name:jpn_x_preferred":[
        "\u8f9b\u96c6\u5e02"
    ],
    "name:kik_x_preferred":[
        "Xinji"
    ],
    "name:kor_x_preferred":[
        "\uc2e0\uc9c0\uc2dc"
    ],
    "name:mlg_x_preferred":[
        "Xinji"
    ],
    "name:nor_x_preferred":[
        "Xinji"
    ],
    "name:pam_x_preferred":[
        "Xinji"
    ],
    "name:rus_x_preferred":[
        "\u0421\u0438\u043d\u044c\u0446\u0437\u0438"
    ],
    "name:sco_x_preferred":[
        "Xinji"
    ],
    "name:swe_x_preferred":[
        "Xinji"
    ],
    "name:urd_x_preferred":[
        "\u0634\u0646\u062c\u06cc"
    ],
    "name:vie_x_preferred":[
        "T\u00e2n T\u1eadp"
    ],
    "name:war_x_preferred":[
        "Xinji"
    ],
    "name:zho_x_preferred":[
        "\u65b0\u96c6"
    ],
    "name:zho_x_variant":[
        "\u8f9b\u96c6\u5e02"
    ],
    "wof:name":"Xinji",
    "wof:placetype":"locality"
},
  "geometry": {"coordinates":[111.93431,31.98798],"type":"Point"}
}