{
  "type": "Feature",
  "properties": {
    "gn:admin1_code":"21.0",
    "gn:asciiname":"Shijichang",
    "gn:country_code":"CN",
    "gn:dem":1529,
    "gn:feature_class":"P",
    "gn:feature_code":"PPL",
    "gn:name":"Shijichang",
    "gn:population":0,
    "gn:timezone":"Asia/Shanghai",
    "iso:country":"CN",
    "name:zho_x_preferred":[
        "\u77f3\u8bb0\u573a"
    ],
    "wof:name":"Shijichang",
    "wof:placetype":"locality"
},
  "geometry": {"coordinates":[107.096,37.5658],"type":"Point"}
}