{
  "type": "Feature",
  "properties": {
    "gn:admin1_code":"32",
    "gn:asciiname":"Guangezhen",
    "gn:cc2":"CN",
    "gn:country_code":"CN",
    "gn:dem":305,
    "gn:feature_class":"P",
    "gn:feature_code":"PPL",
    "gn:name":"Guangezhen",
    "gn:population":0,
    "gn:timezone":"Asia/Shanghai",
    "iso:country":"CN",
    "name:und_x_variant":[
        "Kuan-ko-chen",
        "Guangezhen"
    ],
    "wof:name":"Guangezhen",
    "wof:placetype":"locality"
},
  "geometry": {"coordinates":[106.91667,30.55],"type":"Point"}
}