{
  "type": "Feature",
  "properties": {
    "gn:admin1_code":"24.0",
    "gn:asciiname":"Hongjiashan",
    "gn:country_code":"CN",
    "gn:dem":848,
    "gn:feature_class":"P",
    "gn:feature_code":"PPL",
    "gn:name":"Hongjiashan",
    "gn:population":0,
    "gn:timezone":"Asia/Shanghai",
    "iso:country":"CN",
    "name:zho_x_preferred":[
        "\u6d2a\u5bb6\u5c71"
    ],
    "wof:name":"Hongjiashan",
    "wof:placetype":"locality"
},
  "geometry": {"coordinates":[111.75023,35.61356],"type":"Point"}
}