{
  "type": "Feature",
  "properties": {
    "gn:admin1_code":"19.0",
    "gn:asciiname":"Xiangyanggou",
    "gn:country_code":"CN",
    "gn:dem":466,
    "gn:feature_class":"P",
    "gn:feature_code":"PPL",
    "gn:name":"Xiangyanggou",
    "gn:population":0,
    "gn:timezone":"Asia/Shanghai",
    "iso:country":"CN",
    "name:zho_x_preferred":[
        "\u5411\u9633\u6c9f"
    ],
    "wof:name":"Xiangyanggou",
    "wof:placetype":"locality"
},
  "geometry": {"coordinates":[120.252,41.7809],"type":"Point"}
}