{
  "type": "Feature",
  "properties": {
    "gn:admin1_code":"32.0",
    "gn:asciiname":"Laogaigu",
    "gn:country_code":"CN",
    "gn:dem":2594,
    "gn:feature_class":"P",
    "gn:feature_code":"PPL",
    "gn:name":"Laogaigu",
    "gn:population":0,
    "gn:timezone":"Asia/Shanghai",
    "iso:country":"CN",
    "name:zho_x_preferred":[
        "\u8001\u6539\u53e4"
    ],
    "wof:name":"Laogaigu",
    "wof:placetype":"locality"
},
  "geometry": {"coordinates":[102.348,28.1955],"type":"Point"}
}