{
  "type": "Feature",
  "properties": {
    "gn:admin1_code":"2.0",
    "gn:asciiname":"Caojiali",
    "gn:country_code":"CN",
    "gn:dem":8,
    "gn:feature_class":"P",
    "gn:feature_code":"PPL",
    "gn:name":"Caojiali",
    "gn:population":0,
    "gn:timezone":"Asia/Shanghai",
    "iso:country":"CN",
    "name:und_x_variant":[
        "\u66f9\u5bb6\u91cc"
    ],
    "wof:name":"Caojiali",
    "wof:placetype":"locality"
},
  "geometry": {"coordinates":[120.30307000000001,30.55577000000001],"type":"Point"}
}