{
  "type": "Feature",
  "properties": {
    "gn:admin1_code":"30",
    "gn:asciiname":"Chang'an",
    "gn:country_code":"CN",
    "gn:dem":6,
    "gn:feature_class":"P",
    "gn:feature_code":"PPLA3",
    "gn:name":"Chang\u2019an",
    "gn:population":0,
    "gn:timezone":"Asia/Shanghai",
    "iso:country":"CN",
    "name:und_x_variant":[
        "Chang\u2019an Zhen"
    ],
    "name:zho_x_preferred":[
        "Chang\u2019an"
    ],
    "wof:name":"Chang'an",
    "wof:placetype":"locality"
},
  "geometry": {"coordinates":[113.80278,22.80648],"type":"Point"}
}