{
  "type": "Feature",
  "properties": {
    "gn:admin1_code":"10",
    "gn:asciiname":"Doubudian",
    "gn:country_code":"CN",
    "gn:dem":25,
    "gn:feature_class":"P",
    "gn:feature_code":"PPL",
    "gn:name":"Doubudian",
    "gn:population":0,
    "gn:timezone":"Asia/Shanghai",
    "iso:country":"CN",
    "name:zho_x_preferred":[
        "\u7aa6\u5821\u5e97"
    ],
    "wof:name":"Doubudian",
    "wof:placetype":"locality"
},
  "geometry": {"coordinates":[116.09184,37.49353],"type":"Point"}
}