{
  "type": "Feature",
  "properties": {
    "gn:admin1_code":"16.0",
    "gn:asciiname":"Fuming",
    "gn:country_code":"CN",
    "gn:dem":182,
    "gn:feature_class":"P",
    "gn:feature_code":"PPL",
    "gn:name":"Fuming",
    "gn:population":0,
    "gn:timezone":"Asia/Shanghai",
    "iso:country":"CN",
    "name:zho_x_preferred":[
        "\u798f\u660e"
    ],
    "wof:name":"Fuming",
    "wof:placetype":"locality"
},
  "geometry": {"coordinates":[109.67400000000001,22.4212],"type":"Point"}
}