{
  "type": "Feature",
  "properties": {
    "gn:admin1_code":"2.0",
    "gn:asciiname":"Shangzheng",
    "gn:country_code":"CN",
    "gn:dem":138,
    "gn:feature_class":"P",
    "gn:feature_code":"PPL",
    "gn:name":"Shangzheng",
    "gn:population":0,
    "gn:timezone":"Asia/Shanghai",
    "iso:country":"CN",
    "name:zho_x_preferred":[
        "\u4e0a\u90d1"
    ],
    "wof:name":"Shangzheng",
    "wof:placetype":"locality"
},
  "geometry": {"coordinates":[121.64915000000001,29.64277],"type":"Point"}
}