{
  "type": "Feature",
  "properties": {
    "gn:admin1_code":"19.0",
    "gn:asciiname":"Xiaojiangjiatun",
    "gn:country_code":"CN",
    "gn:dem":6,
    "gn:feature_class":"P",
    "gn:feature_code":"PPL",
    "gn:name":"Xiaojiangjiatun",
    "gn:population":0,
    "gn:timezone":"Asia/Shanghai",
    "iso:country":"CN",
    "name:zho_x_preferred":[
        "\u5c0f\u59dc\u5bb6\u5c6f"
    ],
    "wof:name":"Xiaojiangjiatun",
    "wof:placetype":"locality"
},
  "geometry": {"coordinates":[121.62236,39.43977],"type":"Point"}
}