{
  "type": "Feature",
  "properties": {
    "gn:admin1_code":"32.0",
    "gn:asciiname":"Tiejue",
    "gn:country_code":"CN",
    "gn:dem":779,
    "gn:feature_class":"P",
    "gn:feature_code":"PPL",
    "gn:name":"Tiejue",
    "gn:population":0,
    "gn:timezone":"Asia/Shanghai",
    "iso:country":"CN",
    "name:zho_x_preferred":[
        "\u94c1\u89c9"
    ],
    "wof:name":"Tiejue",
    "wof:placetype":"locality"
},
  "geometry": {"coordinates":[103.42995999999999,28.62119],"type":"Point"}
}