{
  "type": "Feature",
  "properties": {
    "gn:admin1_code":"15.0",
    "gn:asciiname":"Liudui",
    "gn:country_code":"CN",
    "gn:dem":1227,
    "gn:feature_class":"P",
    "gn:feature_code":"PPLF",
    "gn:name":"Liudui",
    "gn:population":0,
    "gn:timezone":"Asia/Shanghai",
    "iso:country":"CN",
    "name:zho_x_preferred":[
        "\u516d\u961f"
    ],
    "wof:name":"Liudui",
    "wof:placetype":"locality"
},
  "geometry": {"coordinates":[98.96169999999999,40.2282],"type":"Point"}
}