{
  "type": "Feature",
  "properties": {
    "gn:admin1_code":"1.0",
    "gn:asciiname":"Yingjiachangcun",
    "gn:country_code":"CN",
    "gn:dem":79,
    "gn:feature_class":"P",
    "gn:feature_code":"PPL",
    "gn:name":"Yingjiachangcun",
    "gn:population":0,
    "gn:timezone":"Asia/Shanghai",
    "iso:country":"CN",
    "name:zho_x_preferred":[
        "\u8fce\u9a7e\u5382\u6751"
    ],
    "wof:name":"Yingjiachangcun",
    "wof:placetype":"locality"
},
  "geometry": {"coordinates":[116.25566999999999,31.40355],"type":"Point"}
}