{
  "type": "Feature",
  "properties": {
    "gn:admin1_code":"26.0",
    "gn:asciiname":"Guojia Yayaocun",
    "gn:country_code":"CN",
    "gn:dem":1010,
    "gn:feature_class":"P",
    "gn:feature_code":"PPL",
    "gn:name":"Guojia Yayaocun",
    "gn:population":0,
    "gn:timezone":"Asia/Shanghai",
    "iso:country":"CN",
    "name:zho_x_preferred":[
        "\u90ed\u5bb6\u5d16\u5c27\u6751"
    ],
    "wof:name":"Guojia Yayaocun",
    "wof:placetype":"locality"
},
  "geometry": {"coordinates":[110.94199999999999,38.8766],"type":"Point"}
}