{
  "type": "Feature",
  "properties": {
    "gn:admin1_code":"29.0",
    "gn:asciiname":"Muzeng",
    "gn:country_code":"CN",
    "gn:dem":2346,
    "gn:feature_class":"P",
    "gn:feature_code":"PPLA4",
    "gn:name":"Muzeng",
    "gn:population":0,
    "gn:timezone":"Asia/Shanghai",
    "iso:country":"CN",
    "name:und_x_variant":[
        "\u6728\u589e",
        "Shuanghua",
        "Shuanghua Xiang",
        "\u53cc\u5316",
        "\u53cc\u5316\u4e61"
    ],
    "wof:name":"Muzeng",
    "wof:placetype":"locality"
},
  "geometry": {"coordinates":[102.47927,26.05241],"type":"Point"}
}