{
  "type": "Feature",
  "properties": {
    "gn:admin1_code":"3",
    "gn:asciiname":"Lianmin",
    "gn:country_code":"CN",
    "gn:dem":143,
    "gn:feature_class":"P",
    "gn:feature_code":"PPL",
    "gn:name":"Lianmin",
    "gn:population":0,
    "gn:timezone":"Asia/Shanghai",
    "iso:country":"CN",
    "name:zho_x_preferred":[
        "\u8054\u6c11"
    ],
    "wof:name":"Lianmin",
    "wof:placetype":"locality"
},
  "geometry": {"coordinates":[114.72196,25.72065],"type":"Point"}
}