{
  "type": "Feature",
  "properties": {
    "gn:admin1_code":"3.0",
    "gn:asciiname":"Jiufengsi",
    "gn:country_code":"CN",
    "gn:dem":357,
    "gn:feature_class":"P",
    "gn:feature_code":"PPL",
    "gn:name":"Jiufengsi",
    "gn:population":0,
    "gn:timezone":"Asia/Shanghai",
    "iso:country":"CN",
    "name:und_x_variant":[
        "\u4e5d\u5cf0\u5bfa"
    ],
    "wof:name":"Jiufengsi",
    "wof:placetype":"locality"
},
  "geometry": {"coordinates":[115.41934000000001,29.67773],"type":"Point"}
}