{
  "type": "Feature",
  "properties": {
    "gn:admin1_code":"9.0",
    "gn:asciiname":"Huangdongcun",
    "gn:country_code":"CN",
    "gn:dem":65,
    "gn:feature_class":"P",
    "gn:feature_code":"PPL",
    "gn:name":"Huangdongcun",
    "gn:population":0,
    "gn:timezone":"Asia/Shanghai",
    "iso:country":"CN",
    "name:zho_x_preferred":[
        "\u9ec4\u4e1c\u6751"
    ],
    "wof:name":"Huangdongcun",
    "wof:placetype":"locality"
},
  "geometry": {"coordinates":[114.71123,34.6656],"type":"Point"}
}