{
  "type": "Feature",
  "properties": {
    "gn:admin1_code":"24.0",
    "gn:asciiname":"Datangou",
    "gn:country_code":"CN",
    "gn:dem":1907,
    "gn:feature_class":"P",
    "gn:feature_code":"PPL",
    "gn:name":"Datangou",
    "gn:population":0,
    "gn:timezone":"Asia/Shanghai",
    "iso:country":"CN",
    "name:und_x_variant":[
        "\u5927\u6ee9\u6c9f"
    ],
    "name:zho_x_preferred":[
        "\u5927\u6ee9\u6c9f"
    ],
    "wof:name":"Datangou",
    "wof:placetype":"locality"
},
  "geometry": {"coordinates":[112.31091000000001,38.58921],"type":"Point"}
}