{
  "type": "Feature",
  "properties": {
    "gn:admin1_code":"19.0",
    "gn:asciiname":"Dawozi",
    "gn:country_code":"CN",
    "gn:dem":12,
    "gn:feature_class":"P",
    "gn:feature_code":"PPL",
    "gn:name":"Dawozi",
    "gn:population":0,
    "gn:timezone":"Asia/Shanghai",
    "iso:country":"CN",
    "name:und_x_variant":[
        "\u5927\u5367\u5b50"
    ],
    "name:zho_x_preferred":[
        "\u5927\u5367\u5b50"
    ],
    "wof:name":"Dawozi",
    "wof:placetype":"locality"
},
  "geometry": {"coordinates":[122.90902,41.30971],"type":"Point"}
}