{
  "type": "Feature",
  "properties": {
    "gn:admin1_code":"32.0",
    "gn:asciiname":"Caocaoping",
    "gn:country_code":"CN",
    "gn:dem":1506,
    "gn:feature_class":"P",
    "gn:feature_code":"PPL",
    "gn:name":"Caocaoping",
    "gn:population":0,
    "gn:timezone":"Asia/Shanghai",
    "iso:country":"CN",
    "name:zho_x_preferred":[
        "\u8349\u69fd\u576a"
    ],
    "wof:name":"Caocaoping",
    "wof:placetype":"locality"
},
  "geometry": {"coordinates":[104.13800000000001,31.6019],"type":"Point"}
}