{
  "type": "Feature",
  "properties": {
    "gn:admin1_code":"19.0",
    "gn:asciiname":"Gaoligou",
    "gn:country_code":"CN",
    "gn:dem":238,
    "gn:feature_class":"P",
    "gn:feature_code":"PPL",
    "gn:name":"Gaoligou",
    "gn:population":0,
    "gn:timezone":"Asia/Shanghai",
    "iso:country":"CN",
    "name:zho_x_preferred":[
        "\u9ad8\u4e3d\u6c9f"
    ],
    "wof:name":"Gaoligou",
    "wof:placetype":"locality"
},
  "geometry": {"coordinates":[125.58799999999999,40.9786],"type":"Point"}
}