{
  "type": "Feature",
  "properties": {
    "gn:admin1_code":"4.0",
    "gn:asciiname":"Laoduicun",
    "gn:country_code":"CN",
    "gn:dem":7,
    "gn:feature_class":"P",
    "gn:feature_code":"PPL",
    "gn:name":"Laoduicun",
    "gn:population":0,
    "gn:timezone":"Asia/Shanghai",
    "iso:country":"CN",
    "name:zho_x_preferred":[
        "\u8001\u5806\u6751"
    ],
    "wof:name":"Laoduicun",
    "wof:placetype":"locality"
},
  "geometry": {"coordinates":[119.14673000000001,33.99048],"type":"Point"}
}