{
  "type": "Feature",
  "properties": {
    "gn:admin1_code":"29.0",
    "gn:asciiname":"Laoyishan",
    "gn:country_code":"CN",
    "gn:dem":2121,
    "gn:feature_class":"P",
    "gn:feature_code":"PPL",
    "gn:name":"Laoyishan",
    "gn:population":0,
    "gn:timezone":"Asia/Shanghai",
    "iso:country":"CN",
    "name:zho_x_preferred":[
        "\u8001\u8bae\u5c71"
    ],
    "wof:name":"Laoyishan",
    "wof:placetype":"locality"
},
  "geometry": {"coordinates":[99.9385,24.8055],"type":"Point"}
}