{
  "type": "Feature",
  "properties": {
    "gn:admin1_code":"29.0",
    "gn:asciiname":"Zhayingshan",
    "gn:country_code":"CN",
    "gn:dem":1117,
    "gn:feature_class":"P",
    "gn:feature_code":"PPL",
    "gn:name":"Zhayingshan",
    "gn:population":0,
    "gn:timezone":"Asia/Shanghai",
    "iso:country":"CN",
    "name:zho_x_preferred":[
        "\u624e\u8425\u5c71"
    ],
    "wof:name":"Zhayingshan",
    "wof:placetype":"locality"
},
  "geometry": {"coordinates":[101.373,23.0634],"type":"Point"}
}