{
  "type": "Feature",
  "properties": {
    "gn:admin1_code":"16.0",
    "gn:asciiname":"Dongpo",
    "gn:country_code":"CN",
    "gn:dem":141,
    "gn:feature_class":"P",
    "gn:feature_code":"PPL",
    "gn:name":"Dongpo",
    "gn:population":0,
    "gn:timezone":"Asia/Shanghai",
    "iso:country":"CN",
    "name:deu_x_preferred":[
        "Dongpo"
    ],
    "name:fra_x_preferred":[
        "Dongpo"
    ],
    "name:zho_x_preferred":[
        "\u6d1e\u5761"
    ],
    "wof:name":"Dongpo",
    "wof:placetype":"locality"
},
  "geometry": {"coordinates":[107.227,22.0911],"type":"Point"}
}