{
  "type": "Feature",
  "properties": {
    "gn:admin1_code":"6.0",
    "gn:asciiname":"Xiatan",
    "gn:country_code":"CN",
    "gn:dem":3295,
    "gn:feature_class":"P",
    "gn:feature_code":"PPL",
    "gn:name":"Xiatan",
    "gn:population":0,
    "gn:timezone":"Asia/Shanghai",
    "iso:country":"CN",
    "name:zho_x_preferred":[
        "\u4e0b\u6ee9"
    ],
    "wof:name":"Xiatan",
    "wof:placetype":"locality"
},
  "geometry": {"coordinates":[101.51128,36.31251],"type":"Point"}
}