{
  "type": "Feature",
  "properties": {
    "gn:admin1_code":"1.0",
    "gn:asciiname":"Zhangluocun",
    "gn:country_code":"CN",
    "gn:dem":31,
    "gn:feature_class":"P",
    "gn:feature_code":"PPL",
    "gn:name":"Zhangluocun",
    "gn:population":0,
    "gn:timezone":"Asia/Shanghai",
    "iso:country":"CN",
    "name:zho_x_preferred":[
        "\u5f20\u7f57\u6751"
    ],
    "wof:name":"Zhangluocun",
    "wof:placetype":"locality"
},
  "geometry": {"coordinates":[116.07089000000001,32.3519],"type":"Point"}
}