{
  "type": "Feature",
  "properties": {
    "gn:admin1_code":"5.0",
    "gn:asciiname":"Xinfengtun",
    "gn:country_code":"CN",
    "gn:dem":201,
    "gn:feature_class":"P",
    "gn:feature_code":"PPL",
    "gn:name":"Xinfengtun",
    "gn:population":0,
    "gn:timezone":"Asia/Shanghai",
    "iso:country":"CN",
    "name:zho_x_preferred":[
        "\u65b0\u4e30\u5c6f"
    ],
    "wof:name":"Xinfengtun",
    "wof:placetype":"locality"
},
  "geometry": {"coordinates":[126.53502,44.69123],"type":"Point"}
}