{
  "type": "Feature",
  "properties": {
    "gn:admin1_code":"19.0",
    "gn:asciiname":"Qinjiabu",
    "gn:country_code":"CN",
    "gn:dem":244,
    "gn:feature_class":"P",
    "gn:feature_code":"PPL",
    "gn:name":"Qinjiabu",
    "gn:population":0,
    "gn:timezone":"Asia/Shanghai",
    "iso:country":"CN",
    "name:und_x_variant":[
        "Qinjiapu",
        "\u79e6\u5bb6\u5821",
        "Qinjiabu"
    ],
    "wof:name":"Qinjiabu",
    "wof:placetype":"locality"
},
  "geometry": {"coordinates":[122.88439,40.47121],"type":"Point"}
}