{
  "type": "Feature",
  "properties": {
    "gn:admin1_code":"24",
    "gn:asciiname":"Caojiazhuang",
    "gn:country_code":"CN",
    "gn:dem":921,
    "gn:feature_class":"P",
    "gn:feature_code":"PPL",
    "gn:name":"Caojiazhuang",
    "gn:population":0,
    "gn:timezone":"Asia/Shanghai",
    "iso:country":"CN",
    "name:und_x_variant":[
        "Ts\u2019ao-chia-chuang",
        "Caojiazhuang"
    ],
    "name:zho_x_preferred":[
        "\u66f9\u5bb6\u5e84"
    ],
    "wof:name":"Caojiazhuang",
    "wof:placetype":"locality"
},
  "geometry": {"coordinates":[111.51065,35.14704],"type":"Point"}
}