{
  "type": "Feature",
  "properties": {
    "gn:admin1_code":"8.0",
    "gn:asciiname":"Diaoziyangtun",
    "gn:country_code":"CN",
    "gn:dem":237,
    "gn:feature_class":"P",
    "gn:feature_code":"PPL",
    "gn:name":"Diaoziyangtun",
    "gn:population":0,
    "gn:timezone":"Asia/Shanghai",
    "iso:country":"CN",
    "name:zho_x_preferred":[
        "\u5201\u5b50\u6768\u5c6f"
    ],
    "wof:name":"Diaoziyangtun",
    "wof:placetype":"locality"
},
  "geometry": {"coordinates":[125.12605000000001,48.15486],"type":"Point"}
}