{
  "type": "Feature",
  "properties": {
    "gn:admin1_code":"7.0",
    "gn:asciiname":"Caotianshang",
    "gn:country_code":"CN",
    "gn:dem":226,
    "gn:feature_class":"P",
    "gn:feature_code":"PPL",
    "gn:name":"Caotianshang",
    "gn:population":0,
    "gn:timezone":"Asia/Shanghai",
    "iso:country":"CN",
    "name:zho_x_preferred":[
        "\u66f9\u7530\u4e0a"
    ],
    "wof:name":"Caotianshang",
    "wof:placetype":"locality"
},
  "geometry": {"coordinates":[116.34808999999998,25.32067],"type":"Point"}
}