{
  "type": "Feature",
  "properties": {
    "gn:admin1_code":"18.0",
    "gn:asciiname":"Wudiao",
    "gn:country_code":"CN",
    "gn:dem":852,
    "gn:feature_class":"P",
    "gn:feature_code":"PPL",
    "gn:name":"Wudiao",
    "gn:population":0,
    "gn:timezone":"Asia/Shanghai",
    "iso:country":"CN",
    "name:zho_x_preferred":[
        "\u52a1\u8c03"
    ],
    "wof:name":"Wudiao",
    "wof:placetype":"locality"
},
  "geometry": {"coordinates":[107.81,25.6252],"type":"Point"}
}