{
  "type": "Feature",
  "properties": {
    "gn:admin1_code":"15.0",
    "gn:asciiname":"Qiaowutang",
    "gn:country_code":"CN",
    "gn:dem":2829,
    "gn:feature_class":"P",
    "gn:feature_code":"PPL",
    "gn:name":"Qiaowutang",
    "gn:population":0,
    "gn:timezone":"Asia/Shanghai",
    "iso:country":"CN",
    "name:und_x_variant":[
        "\u4e54\u543e\u5858"
    ],
    "wof:name":"Qiaowutang",
    "wof:placetype":"locality"
},
  "geometry": {"coordinates":[102.9717,34.68123],"type":"Point"}
}