{
  "type": "Feature",
  "properties": {
    "gn:admin1_code":"30",
    "gn:asciiname":"Qingshuijiang",
    "gn:country_code":"CN",
    "gn:dem":869,
    "gn:feature_class":"P",
    "gn:feature_code":"PPL",
    "gn:name":"Qingshuijiang",
    "gn:population":0,
    "gn:timezone":"Asia/Shanghai",
    "iso:country":"CN",
    "name:und_x_variant":[
        "\u6e05\u6c34\u6c5f"
    ],
    "wof:name":"Qingshuijiang",
    "wof:placetype":"locality"
},
  "geometry": {"coordinates":[113.56246000000002,25.30121],"type":"Point"}
}