{
  "type": "Feature",
  "properties": {
    "gn:admin1_code":"8.0",
    "gn:asciiname":"Huojia Wobu",
    "gn:country_code":"CN",
    "gn:dem":162,
    "gn:feature_class":"P",
    "gn:feature_code":"PPL",
    "gn:name":"Huojia Wobu",
    "gn:population":0,
    "gn:timezone":"Asia/Shanghai",
    "iso:country":"CN",
    "name:zho_x_preferred":[
        "\u970d\u5bb6\u7a9d\u5821"
    ],
    "wof:name":"Huojia Wobu",
    "wof:placetype":"locality"
},
  "geometry": {"coordinates":[124.71372,47.63389],"type":"Point"}
}