{
  "type": "Feature",
  "properties": {
    "gn:admin1_code":"15.0",
    "gn:asciiname":"Zhuoluo",
    "gn:country_code":"CN",
    "gn:dem":2652,
    "gn:feature_class":"P",
    "gn:feature_code":"PPL",
    "gn:name":"Zhuoluo",
    "gn:population":0,
    "gn:timezone":"Asia/Shanghai",
    "iso:country":"CN",
    "name:und_x_variant":[
        "\u5353\u843d"
    ],
    "wof:name":"Zhuoluo",
    "wof:placetype":"locality"
},
  "geometry": {"coordinates":[104.20085,34.52272],"type":"Point"}
}