{
  "type": "Feature",
  "properties": {
    "gn:admin1_code":"13.0",
    "gn:asciiname":"Yengisar",
    "gn:cc2":"CN",
    "gn:country_code":"CN",
    "gn:dem":1298,
    "gn:feature_class":"P",
    "gn:feature_code":"PPL",
    "gn:name":"Yengisar",
    "gn:population":0,
    "gn:timezone":"Asia/Shanghai",
    "iso:country":"CN",
    "name:uig_x_preferred":[
        "Y\u00e9ngisar"
    ],
    "name:uig_x_variant":[
        "\u064a\u06d0\u06ad\u0649\u0633\u0627\u0631",
        "\u0415\u04a3\u0438\u0441\u0430\u0440"
    ],
    "name:und_x_variant":[
        "Yangi-Gisar",
        "Yingkisha",
        "Ying-chi-sha-chen",
        "Ying-chi-ho-sha-erh",
        "Yang Hissar",
        "Ying-chi-sha",
        "Yangihessar",
        "Yengi Hissar",
        "Ying-chi-sha-erh",
        "Yangi Hisar",
        "Yangihissar",
        "Ying-chi-sha-hsien",
        "Yangihissai",
        "Yengisar"
    ],
    "wof:name":"Yengisar",
    "wof:placetype":"locality"
},
  "geometry": {"coordinates":[76.17139,38.92583],"type":"Point"}
}