{
  "type": "Feature",
  "properties": {
    "gn:admin1_code":"13.0",
    "gn:asciiname":"Yengisar",
    "gn:cc2":"CN",
    "gn:country_code":"CN",
    "gn:dem":1298,
    "gn:feature_class":"P",
    "gn:feature_code":"PPL",
    "gn:name":"Yengisar",
    "gn:population":0,
    "gn:timezone":"Asia/Shanghai",
    "iso:country":"CN",
    "name:deu_x_preferred":[
        "Yengisar"
    ],
    "name:ell_x_preferred":[
        "\u039a\u03bf\u03bc\u03b7\u03c4\u03b5\u03af\u03b1 \u0393\u03b9\u03b5\u03bd\u03b3\u03ba\u03b9\u03c3\u03ac\u03c1"
    ],
    "name:fas_x_preferred":[
        "\u0634\u0647\u0631\u0633\u062a\u0627\u0646 \u06cc\u0646\u06af\u06cc\u0633\u0627\u0631"
    ],
    "name:jpn_x_preferred":[
        "\u30a4\u30a7\u30f3\u30ae\u30b5\u30fc\u30eb\u770c"
    ],
    "name:kor_x_preferred":[
        "\uc789\uc9c0\uc0ac\ud604"
    ],
    "name:nld_x_preferred":[
        "Yengisar"
    ],
    "name:nor_x_preferred":[
        "Yengisar"
    ],
    "name:pol_x_preferred":[
        "Yengisar"
    ],
    "name:por_x_preferred":[
        "Yengisar"
    ],
    "name:rus_x_preferred":[
        "\u042f\u043d\u0433\u0438\u0433\u0438\u0441\u0430\u0440"
    ],
    "name:swe_x_preferred":[
        "Yengisar"
    ],
    "name:tur_x_preferred":[
        "Yengisar \u0130l\u00e7esi"
    ],
    "name:uig_x_preferred":[
        "Y\u00e9ngisar"
    ],
    "name:uig_x_variant":[
        "\u064a\u06d0\u06ad\u0649\u0633\u0627\u0631",
        "\u0415\u04a3\u0438\u0441\u0430\u0440",
        "\u064a\u06d0\u06ad\u0649\u0633\u0627\u0631 \u0646\u0627\u06be\u0649\u064a\u0649\u0633\u0649"
    ],
    "name:und_x_variant":[
        "Yangi-Gisar",
        "Yingkisha",
        "Ying-chi-sha-chen",
        "Ying-chi-ho-sha-erh",
        "Yang Hissar",
        "Ying-chi-sha",
        "Yangihessar",
        "Yengi Hissar",
        "Ying-chi-sha-erh",
        "Yangi Hisar",
        "Yangihissar",
        "Ying-chi-sha-hsien",
        "Yangihissai",
        "Yengisar"
    ],
    "name:urd_x_preferred":[
        "\u06cc\u0626\u0646\u06af\u06cc\u0633\u0627\u0631 \u06a9\u0627\u0624\u0646\u0679\u06cc"
    ],
    "name:vie_x_preferred":[
        "Yengisar"
    ],
    "name:zho_x_preferred":[
        "\u82f1\u5409\u6c99\u53bf"
    ],
    "wof:name":"Yengisar",
    "wof:placetype":"locality"
},
  "geometry": {"coordinates":[76.17139,38.92583],"type":"Point"}
}