{
  "type": "Feature",
  "properties": {
    "gn:admin1_code":"11.0",
    "gn:asciiname":"Baishu Huangjia",
    "gn:country_code":"CN",
    "gn:dem":300,
    "gn:feature_class":"P",
    "gn:feature_code":"PPL",
    "gn:name":"Baishu Huangjia",
    "gn:population":0,
    "gn:timezone":"Asia/Shanghai",
    "iso:country":"CN",
    "name:zho_x_preferred":[
        "\u67cf\u6811\u9ec4\u5bb6"
    ],
    "wof:name":"Baishu Huangjia",
    "wof:placetype":"locality"
},
  "geometry": {"coordinates":[112.81403,26.08029],"type":"Point"}
}