{
  "type": "Feature",
  "properties": {
    "gn:admin1_code":"14.0",
    "gn:asciiname":"Namuqicun",
    "gn:country_code":"CN",
    "gn:dem":4688,
    "gn:feature_class":"P",
    "gn:feature_code":"PPL",
    "gn:name":"Namuqicun",
    "gn:population":0,
    "gn:timezone":"Asia/Urumqi",
    "iso:country":"CN",
    "name:zho_x_preferred":[
        "\u90a3\u6728\u68cb\u6751"
    ],
    "wof:name":"Namuqicun",
    "wof:placetype":"locality"
},
  "geometry": {"coordinates":[90.34632999999999,28.76094],"type":"Point"}
}