{
  "type": "Feature",
  "properties": {
    "gn:admin1_code":"2",
    "gn:asciiname":"Panxi",
    "gn:cc2":"CN",
    "gn:country_code":"CN",
    "gn:dem":133,
    "gn:feature_class":"P",
    "gn:feature_code":"PPL",
    "gn:name":"Panxi",
    "gn:population":0,
    "gn:timezone":"Asia/Shanghai",
    "iso:country":"CN",
    "name:und_x_variant":[
        "P\u2019an-ch\u2019i-chen",
        "Panxi Xiang",
        "Panxi"
    ],
    "wof:name":"Panxi",
    "wof:placetype":"locality"
},
  "geometry": {"coordinates":[119.34166999999999,30.58694],"type":"Point"}
}