{
  "type": "Feature",
  "properties": {
    "gn:admin1_code":"1.0",
    "gn:asciiname":"Ranfangcun",
    "gn:country_code":"CN",
    "gn:dem":23,
    "gn:feature_class":"P",
    "gn:feature_code":"PPL",
    "gn:name":"Ranfangcun",
    "gn:population":0,
    "gn:timezone":"Asia/Shanghai",
    "iso:country":"CN",
    "name:zho_x_preferred":[
        "\u67d3\u574a\u6751"
    ],
    "wof:name":"Ranfangcun",
    "wof:placetype":"locality"
},
  "geometry": {"coordinates":[116.52293,32.23164000000001],"type":"Point"}
}