{
  "type": "Feature",
  "properties": {
    "gn:admin1_code":"15.0",
    "gn:asciiname":"Kafenkou",
    "gn:country_code":"CN",
    "gn:dem":2411,
    "gn:feature_class":"P",
    "gn:feature_code":"PPL",
    "gn:name":"Kafenkou",
    "gn:population":0,
    "gn:timezone":"Asia/Shanghai",
    "iso:country":"CN",
    "name:und_x_variant":[
        "\u5361\u594b\u53e3"
    ],
    "wof:name":"Kafenkou",
    "wof:placetype":"locality"
},
  "geometry": {"coordinates":[104.21332,34.18254],"type":"Point"}
}