{
  "type": "Feature",
  "properties": {
    "gn:admin1_code":"3",
    "gn:asciiname":"Youfu",
    "gn:country_code":"CN",
    "gn:dem":164,
    "gn:feature_class":"P",
    "gn:feature_code":"PPL",
    "gn:name":"Youfu",
    "gn:population":0,
    "gn:timezone":"Asia/Shanghai",
    "iso:country":"CN",
    "name:zho_x_preferred":[
        "\u60a0\u5bcc"
    ],
    "wof:name":"Youfu",
    "wof:placetype":"locality"
},
  "geometry": {"coordinates":[114.40600000000001,26.2465],"type":"Point"}
}