{
  "type": "Feature",
  "properties": {
    "gn:admin1_code":"25",
    "gn:asciiname":"Buxitoucun",
    "gn:country_code":"CN",
    "gn:dem":68,
    "gn:feature_class":"P",
    "gn:feature_code":"PPL",
    "gn:name":"Buxitoucun",
    "gn:population":0,
    "gn:timezone":"Asia/Shanghai",
    "iso:country":"CN",
    "name:und_x_variant":[
        "Fou-hsi-t\u2019ou",
        "Buxitou",
        "Buxitoucun"
    ],
    "name:zho_x_preferred":[
        "\u57e0\u897f\u5934"
    ],
    "name:zho_x_variant":[
        "\u57e0\u897f\u5934\u6751"
    ],
    "wof:name":"Buxitoucun",
    "wof:placetype":"locality"
},
  "geometry": {"coordinates":[121.20696,37.14624],"type":"Point"}
}