{
  "type": "Feature",
  "properties": {
    "gn:admin1_code":"1.0",
    "gn:asciiname":"Tangwangcun",
    "gn:country_code":"CN",
    "gn:dem":34,
    "gn:feature_class":"P",
    "gn:feature_code":"PPL",
    "gn:name":"Tangwangcun",
    "gn:population":0,
    "gn:timezone":"Asia/Shanghai",
    "iso:country":"CN",
    "name:zho_x_preferred":[
        "\u5510\u738b\u6751"
    ],
    "wof:name":"Tangwangcun",
    "wof:placetype":"locality"
},
  "geometry": {"coordinates":[115.84153999999999,33.43849],"type":"Point"}
}