{
  "type": "Feature",
  "properties": {
    "gn:admin1_code":"7.0",
    "gn:asciiname":"Xiuyang",
    "gn:country_code":"CN",
    "gn:dem":553,
    "gn:feature_class":"P",
    "gn:feature_code":"PPL",
    "gn:name":"Xiuyang",
    "gn:population":0,
    "gn:timezone":"Asia/Shanghai",
    "iso:country":"CN",
    "name:zho_x_preferred":[
        "\u79c0\u6d0b"
    ],
    "wof:name":"Xiuyang",
    "wof:placetype":"locality"
},
  "geometry": {"coordinates":[119.73144000000001,26.93149],"type":"Point"}
}