{
  "type": "Feature",
  "properties": {
    "gn:admin1_code":"29.0",
    "gn:asciiname":"Huodongchang",
    "gn:country_code":"CN",
    "gn:dem":3072,
    "gn:feature_class":"P",
    "gn:feature_code":"PPL",
    "gn:name":"Huodongchang",
    "gn:population":0,
    "gn:timezone":"Asia/Shanghai",
    "iso:country":"CN",
    "name:zho_x_preferred":[
        "\u706b\u4e1c\u5382"
    ],
    "wof:name":"Huodongchang",
    "wof:placetype":"locality"
},
  "geometry": {"coordinates":[101.105,27.0909],"type":"Point"}
}