{
  "type": "Feature",
  "properties": {
    "gn:admin1_code":"5.0",
    "gn:asciiname":"Houxinglongshan",
    "gn:country_code":"CN",
    "gn:dem":150,
    "gn:feature_class":"P",
    "gn:feature_code":"PPL",
    "gn:name":"Houxinglongshan",
    "gn:population":0,
    "gn:timezone":"Asia/Shanghai",
    "iso:country":"CN",
    "name:zho_x_preferred":[
        "\u540e\u5174\u9f99\u5c71"
    ],
    "wof:name":"Houxinglongshan",
    "wof:placetype":"locality"
},
  "geometry": {"coordinates":[122.95654,44.75925],"type":"Point"}
}