{
  "type": "Feature",
  "properties": {
    "gn:admin1_code":"32.0",
    "gn:asciiname":"Baixiangba",
    "gn:country_code":"CN",
    "gn:dem":681,
    "gn:feature_class":"P",
    "gn:feature_code":"PPL",
    "gn:name":"Baixiangba",
    "gn:population":0,
    "gn:timezone":"Asia/Shanghai",
    "iso:country":"CN",
    "name:zho_x_preferred":[
        "\u67cf\u9999\u575d"
    ],
    "wof:name":"Baixiangba",
    "wof:placetype":"locality"
},
  "geometry": {"coordinates":[103.879,28.6766],"type":"Point"}
}