{
  "type": "Feature",
  "properties": {
    "gn:admin1_code":"16.0",
    "gn:asciiname":"Dadang",
    "gn:country_code":"CN",
    "gn:dem":875,
    "gn:feature_class":"P",
    "gn:feature_code":"PPL",
    "gn:name":"Dadang",
    "gn:population":0,
    "gn:timezone":"Asia/Shanghai",
    "iso:country":"CN",
    "name:zho_x_preferred":[
        "\u5927\u5f53"
    ],
    "wof:name":"Dadang",
    "wof:placetype":"locality"
},
  "geometry": {"coordinates":[106.182,23.3179],"type":"Point"}
}