{
  "type": "Feature",
  "properties": {
    "gn:admin1_code":"29.0",
    "gn:asciiname":"Moshiqing",
    "gn:country_code":"CN",
    "gn:dem":1982,
    "gn:feature_class":"P",
    "gn:feature_code":"PPL",
    "gn:name":"Moshiqing",
    "gn:population":0,
    "gn:timezone":"Asia/Shanghai",
    "iso:country":"CN",
    "name:zho_x_preferred":[
        "\u78e8\u77f3\u7b90"
    ],
    "wof:name":"Moshiqing",
    "wof:placetype":"locality"
},
  "geometry": {"coordinates":[101.562,26.1722],"type":"Point"}
}