{
  "type": "Feature",
  "properties": {
    "gn:admin1_code":"16",
    "gn:asciiname":"Renliang",
    "gn:country_code":"CN",
    "gn:dem":107,
    "gn:feature_class":"P",
    "gn:feature_code":"PPL",
    "gn:name":"Renliang",
    "gn:population":0,
    "gn:timezone":"Asia/Shanghai",
    "iso:country":"CN",
    "name:und_x_variant":[
        "Jen-liang-ts\u2019un",
        "Renliang"
    ],
    "name:zho_x_preferred":[
        "\u4ec1\u826f"
    ],
    "wof:name":"Renliang",
    "wof:placetype":"locality"
},
  "geometry": {"coordinates":[107.473,22.4768],"type":"Point"}
}