{
  "type": "Feature",
  "properties": {
    "gn:admin1_code":"14",
    "gn:asciiname":"Zhilie",
    "gn:country_code":"CN",
    "gn:dem":4302,
    "gn:feature_class":"P",
    "gn:feature_code":"PPL",
    "gn:name":"Zhilie",
    "gn:population":0,
    "gn:timezone":"Asia/Urumqi",
    "iso:country":"CN",
    "name:zho_x_preferred":[
        "\u804c\u5217"
    ],
    "wof:name":"Zhilie",
    "wof:placetype":"locality"
},
  "geometry": {"coordinates":[88.9315,29.0676],"type":"Point"}
}