{
  "type": "Feature",
  "properties": {
    "gn:admin1_code":"9.0",
    "gn:asciiname":"Heli Wangying",
    "gn:country_code":"CN",
    "gn:dem":130,
    "gn:feature_class":"P",
    "gn:feature_code":"PPL",
    "gn:name":"Heli Wangying",
    "gn:population":0,
    "gn:timezone":"Asia/Shanghai",
    "iso:country":"CN",
    "name:zho_x_preferred":[
        "\u6cb3\u91cc\u738b\u8425"
    ],
    "wof:name":"Heli Wangying",
    "wof:placetype":"locality"
},
  "geometry": {"coordinates":[111.89049,32.56887],"type":"Point"}
}