{
  "type": "Feature",
  "properties": {
    "gn:admin1_code":"32.0",
    "gn:asciiname":"Zharonggong",
    "gn:country_code":"CN",
    "gn:dem":3316,
    "gn:feature_class":"P",
    "gn:feature_code":"PPL",
    "gn:name":"Zharonggong",
    "gn:population":0,
    "gn:timezone":"Asia/Shanghai",
    "iso:country":"CN",
    "name:zho_x_preferred":[
        "\u624e\u7ed2\u516c"
    ],
    "wof:name":"Zharonggong",
    "wof:placetype":"locality"
},
  "geometry": {"coordinates":[99.2945,28.656],"type":"Point"}
}