{
  "type": "Feature",
  "properties": {
    "gn:admin1_code":"16.0",
    "gn:asciiname":"Wulin",
    "gn:cc2":"CN",
    "gn:country_code":"CN",
    "gn:dem":34,
    "gn:feature_class":"P",
    "gn:feature_code":"PPL",
    "gn:name":"Wulin",
    "gn:population":0,
    "gn:timezone":"Asia/Shanghai",
    "iso:country":"CN",
    "name:und_x_variant":[
        "Wu-lin-k\u2019ou",
        "Wulin"
    ],
    "wof:name":"Wulin",
    "wof:placetype":"locality"
},
  "geometry": {"coordinates":[110.53111,23.42028],"type":"Point"}
}