{
  "type": "Feature",
  "properties": {
    "gn:admin1_code":"19.0",
    "gn:asciiname":"Sanzuofen",
    "gn:country_code":"CN",
    "gn:dem":29,
    "gn:feature_class":"P",
    "gn:feature_code":"PPL",
    "gn:name":"Sanzuofen",
    "gn:population":0,
    "gn:timezone":"Asia/Shanghai",
    "iso:country":"CN",
    "name:zho_x_preferred":[
        "\u4e09\u5ea7\u575f"
    ],
    "wof:name":"Sanzuofen",
    "wof:placetype":"locality"
},
  "geometry": {"coordinates":[122.505,41.8463],"type":"Point"}
}