{
  "type": "Feature",
  "properties": {
    "gn:admin1_code":"9.0",
    "gn:asciiname":"Houzhuang",
    "gn:country_code":"CN",
    "gn:dem":101,
    "gn:feature_class":"P",
    "gn:feature_code":"PPL",
    "gn:name":"Houzhuang",
    "gn:population":0,
    "gn:timezone":"Asia/Shanghai",
    "iso:country":"CN",
    "name:zho_x_preferred":[
        "\u4faf\u5e84"
    ],
    "wof:name":"Houzhuang",
    "wof:placetype":"locality"
},
  "geometry": {"coordinates":[114.36533,35.76107000000001],"type":"Point"}
}