{
  "type": "Feature",
  "properties": {
    "gn:admin1_code":"2.0",
    "gn:asciiname":"Shandichen",
    "gn:country_code":"CN",
    "gn:dem":77,
    "gn:feature_class":"P",
    "gn:feature_code":"PPL",
    "gn:name":"Shandichen",
    "gn:population":0,
    "gn:timezone":"Asia/Shanghai",
    "iso:country":"CN",
    "name:zho_x_preferred":[
        "\u5c71\u5e95\u9648"
    ],
    "wof:name":"Shandichen",
    "wof:placetype":"locality"
},
  "geometry": {"coordinates":[119.08523,29.1126],"type":"Point"}
}