{
  "type": "Feature",
  "properties": {
    "gn:admin1_code":"3.0",
    "gn:asciiname":"Zhanfang",
    "gn:country_code":"CN",
    "gn:dem":233,
    "gn:feature_class":"P",
    "gn:feature_code":"PPL",
    "gn:name":"Zhanfang",
    "gn:population":0,
    "gn:timezone":"Asia/Shanghai",
    "iso:country":"CN",
    "name:und_x_variant":[
        "\u5360\u574a"
    ],
    "wof:name":"Zhanfang",
    "wof:placetype":"locality"
},
  "geometry": {"coordinates":[114.30789,28.72771],"type":"Point"}
}