{
  "type": "Feature",
  "properties": {
    "gn:admin1_code":"33.0",
    "gn:asciiname":"Tanchangpo",
    "gn:country_code":"CN",
    "gn:dem":528,
    "gn:feature_class":"P",
    "gn:feature_code":"PPL",
    "gn:name":"Tanchangpo",
    "gn:population":0,
    "gn:timezone":"Asia/Shanghai",
    "iso:country":"CN",
    "name:zho_x_preferred":[
        "\u70ad\u5382\u5761"
    ],
    "wof:name":"Tanchangpo",
    "wof:placetype":"locality"
},
  "geometry": {"coordinates":[106.703,28.8361],"type":"Point"}
}