{
  "type": "Feature",
  "properties": {
    "gn:admin1_code":"11.0",
    "gn:asciiname":"Xulufan",
    "gn:country_code":"CN",
    "gn:dem":34,
    "gn:feature_class":"P",
    "gn:feature_code":"PPL",
    "gn:name":"Xulufan",
    "gn:population":0,
    "gn:timezone":"Asia/Shanghai",
    "iso:country":"CN",
    "name:zho_x_preferred":[
        "\u80e5\u82a6\u7548"
    ],
    "wof:name":"Xulufan",
    "wof:placetype":"locality"
},
  "geometry": {"coordinates":[113.24284,29.5219],"type":"Point"}
}