{
  "type": "Feature",
  "properties": {
    "gn:admin1_code":"07",
    "gn:asciiname":"Pingdiyang",
    "gn:country_code":"CN",
    "gn:dem":511,
    "gn:feature_class":"P",
    "gn:feature_code":"PPL",
    "gn:name":"Pingdiyang",
    "gn:population":0,
    "gn:timezone":"Asia/Shanghai",
    "iso:country":"CN",
    "name:zho_x_preferred":[
        "\u576a\u5730\u6d0b"
    ],
    "wof:name":"Pingdiyang",
    "wof:placetype":"locality"
},
  "geometry": {"coordinates":[118.32138999999999,25.76513],"type":"Point"}
}