{
  "type": "Feature",
  "properties": {
    "gn:admin1_code":"29",
    "gn:asciiname":"Mile",
    "gn:country_code":"CN",
    "gn:dem":1654,
    "gn:feature_class":"P",
    "gn:feature_code":"PPL",
    "gn:name":"Mile",
    "gn:population":0,
    "gn:timezone":"Asia/Shanghai",
    "iso:country":"CN",
    "name:zho_x_preferred":[
        "\u5f25\u52d2"
    ],
    "wof:name":"Mile",
    "wof:placetype":"locality"
},
  "geometry": {"coordinates":[102.592,23.3898],"type":"Point"}
}