{
  "type": "Feature",
  "properties": {
    "gn:admin1_code":"4.0",
    "gn:asciiname":"Tangdingcun",
    "gn:country_code":"CN",
    "gn:dem":4,
    "gn:feature_class":"P",
    "gn:feature_code":"PPL",
    "gn:name":"Tangdingcun",
    "gn:population":0,
    "gn:timezone":"Asia/Shanghai",
    "iso:country":"CN",
    "name:zho_x_preferred":[
        "\u5510\u9876\u6751"
    ],
    "wof:name":"Tangdingcun",
    "wof:placetype":"locality"
},
  "geometry": {"coordinates":[119.07953000000001,34.66888],"type":"Point"}
}