{
  "type": "Feature",
  "properties": {
    "gn:admin1_code":"11.0",
    "gn:asciiname":"Zexiping",
    "gn:country_code":"CN",
    "gn:dem":525,
    "gn:feature_class":"P",
    "gn:feature_code":"PPL",
    "gn:name":"Zexiping",
    "gn:population":0,
    "gn:timezone":"Asia/Shanghai",
    "iso:country":"CN",
    "name:zho_x_preferred":[
        "\u6cfd\u897f\u576a"
    ],
    "wof:name":"Zexiping",
    "wof:placetype":"locality"
},
  "geometry": {"coordinates":[109.46673,29.00217],"type":"Point"}
}