{
  "type": "Feature",
  "properties": {
    "gn:admin1_code":"29",
    "gn:asciiname":"Nanzhao",
    "gn:country_code":"CN",
    "gn:dem":1713,
    "gn:feature_class":"P",
    "gn:feature_code":"PPLA3",
    "gn:name":"Nanzhao",
    "gn:population":0,
    "gn:timezone":"Asia/Shanghai",
    "iso:country":"CN",
    "name:zho_x_preferred":[
        "\u5357\u8bcf"
    ],
    "wof:name":"Nanzhao",
    "wof:placetype":"locality"
},
  "geometry": {"coordinates":[100.30343999999999,25.22222],"type":"Point"}
}