{
  "type": "Feature",
  "properties": {
    "gn:admin1_code":"14.0",
    "gn:asciiname":"Magmang",
    "gn:country_code":"CN",
    "gn:dem":3442,
    "gn:feature_class":"P",
    "gn:feature_code":"PPLF",
    "gn:name":"Magmang",
    "gn:population":0,
    "gn:timezone":"Asia/Urumqi",
    "iso:country":"CN",
    "name:bod_x_preferred":[
        "Magmang"
    ],
    "name:zho_x_preferred":[
        "Mama"
    ],
    "name:zho_x_variant":[
        "\u9ebb\u739b",
        "Lebu Qu",
        "\u52d2\u5e03\u533a"
    ],
    "wof:name":"Magmang",
    "wof:placetype":"locality"
},
  "geometry": {"coordinates":[91.70399999999999,27.804],"type":"Point"}
}