{
  "type": "Feature",
  "properties": {
    "gn:admin1_code":"02",
    "gn:asciiname":"Dingtoucun",
    "gn:country_code":"CN",
    "gn:dem":13,
    "gn:feature_class":"P",
    "gn:feature_code":"PPL",
    "gn:name":"Dingtoucun",
    "gn:population":0,
    "gn:timezone":"Asia/Shanghai",
    "iso:country":"CN",
    "name:und_x_variant":[
        "Hsia-ting-t\u2019ou",
        "Dingtou",
        "Dingtoucun"
    ],
    "name:zho_x_preferred":[
        "\u5b9a\u5934\u6751"
    ],
    "wof:name":"Dingtoucun",
    "wof:placetype":"locality"
},
  "geometry": {"coordinates":[121.19849000000001,28.38031],"type":"Point"}
}