{
  "type": "Feature",
  "properties": {
    "gn:admin1_code":"18",
    "gn:asciiname":"Dalan",
    "gn:country_code":"CN",
    "gn:dem":1642,
    "gn:feature_class":"P",
    "gn:feature_code":"PPL",
    "gn:name":"Dalan",
    "gn:population":0,
    "gn:timezone":"Asia/Shanghai",
    "iso:country":"CN",
    "name:zho_x_preferred":[
        "\u5927\u5170"
    ],
    "wof:name":"Dalan",
    "wof:placetype":"locality"
},
  "geometry": {"coordinates":[105.261,27.2806],"type":"Point"}
}