{
  "type": "Feature",
  "properties": {
    "gn:admin1_code":"2.0",
    "gn:asciiname":"Zhuangrenqiao",
    "gn:country_code":"CN",
    "gn:dem":7,
    "gn:feature_class":"P",
    "gn:feature_code":"PPL",
    "gn:name":"Zhuangrenqiao",
    "gn:population":0,
    "gn:timezone":"Asia/Shanghai",
    "iso:country":"CN",
    "name:und_x_variant":[
        "\u5e84\u4ec1\u6865"
    ],
    "wof:name":"Zhuangrenqiao",
    "wof:placetype":"locality"
},
  "geometry": {"coordinates":[120.66343000000001,30.43738],"type":"Point"}
}