{
  "type": "Feature",
  "properties": {
    "gn:admin1_code":"11.0",
    "gn:asciiname":"Jieshou",
    "gn:country_code":"CN",
    "gn:dem":63,
    "gn:feature_class":"P",
    "gn:feature_code":"PPL",
    "gn:name":"Jieshou",
    "gn:population":0,
    "gn:timezone":"Asia/Shanghai",
    "iso:country":"CN",
    "name:ara_x_preferred":[
        "\u062c\u064a\u0634\u0648"
    ],
    "name:ceb_x_preferred":[
        "Jieshou"
    ],
    "name:deu_x_preferred":[
        "Jieshou"
    ],
    "name:fas_x_preferred":[
        "\u0698\u0627\u06cc\u0634\u0648"
    ],
    "name:fra_x_preferred":[
        "Jieshou"
    ],
    "name:ita_x_preferred":[
        "Jieshou"
    ],
    "name:jpn_x_preferred":[
        "\u754c\u9996\u5e02"
    ],
    "name:kik_x_preferred":[
        "Jieshou"
    ],
    "name:kor_x_preferred":[
        "\uc81c\uc11c\uc6b0\uc2dc"
    ],
    "name:mlg_x_preferred":[
        "Jieshou"
    ],
    "name:msa_x_preferred":[
        "Jieshou"
    ],
    "name:mwl_x_preferred":[
        "Jieshou"
    ],
    "name:nld_x_preferred":[
        "Jieshou"
    ],
    "name:nor_x_preferred":[
        "Jieshou"
    ],
    "name:pam_x_preferred":[
        "Jieshou"
    ],
    "name:pnb_x_preferred":[
        "\u062c\u06cc\u0634\u0648\u0624"
    ],
    "name:pol_x_preferred":[
        "Jieshou"
    ],
    "name:spa_x_preferred":[
        "Ji\u00e8sh\u014fu Sh\u00ec"
    ],
    "name:swe_x_preferred":[
        "Jieshou"
    ],
    "name:urd_x_preferred":[
        "\u062c\u0626\u06cc\u0634\u0648\u0648"
    ],
    "name:vie_x_preferred":[
        "Gi\u1edbi Th\u1ee7"
    ],
    "name:war_x_preferred":[
        "Jieshou"
    ],
    "name:zho_x_preferred":[
        "\u754c\u9996"
    ],
    "name:zho_x_variant":[
        "\u754c\u9996\u5e02"
    ],
    "wof:name":"Jieshou",
    "wof:placetype":"locality"
},
  "geometry": {"coordinates":[111.06641999999999,28.80652000000001],"type":"Point"}
}