{
  "type": "Feature",
  "properties": {
    "gn:admin1_code":"10",
    "gn:asciiname":"Lujiao Goumen",
    "gn:country_code":"CN",
    "gn:dem":615,
    "gn:feature_class":"P",
    "gn:feature_code":"PPL",
    "gn:name":"Lujiao Goumen",
    "gn:population":0,
    "gn:timezone":"Asia/Shanghai",
    "iso:country":"CN",
    "name:zho_x_preferred":[
        "\u9e7f\u89d2\u6c9f\u95e8"
    ],
    "wof:name":"Lujiao Goumen",
    "wof:placetype":"locality"
},
  "geometry": {"coordinates":[117.04276000000002,41.17108],"type":"Point"}
}