{
  "type": "Feature",
  "properties": {
    "gn:admin1_code":"8.0",
    "gn:asciiname":"Zhaolincun",
    "gn:country_code":"CN",
    "gn:dem":96,
    "gn:feature_class":"P",
    "gn:feature_code":"PPL",
    "gn:name":"Zhaolincun",
    "gn:population":0,
    "gn:timezone":"Asia/Shanghai",
    "iso:country":"CN",
    "name:zho_x_preferred":[
        "\u5146\u6797\u6751"
    ],
    "wof:name":"Zhaolincun",
    "wof:placetype":"locality"
},
  "geometry": {"coordinates":[131.22092000000001,46.77738],"type":"Point"}
}