{
  "type": "Feature",
  "properties": {
    "gn:admin1_code":"5.0",
    "gn:asciiname":"Dalaga",
    "gn:country_code":"CN",
    "gn:dem":154,
    "gn:feature_class":"P",
    "gn:feature_code":"PPL",
    "gn:name":"Dalaga",
    "gn:population":0,
    "gn:timezone":"Asia/Shanghai",
    "iso:country":"CN",
    "name:zho_x_preferred":[
        "\u8fbe\u62c9\u560e"
    ],
    "wof:name":"Dalaga",
    "wof:placetype":"locality"
},
  "geometry": {"coordinates":[122.58801,45.43113],"type":"Point"}
}