{
  "type": "Feature",
  "properties": {
    "gn:admin1_code":"30.0",
    "gn:asciiname":"Shamugang",
    "gn:country_code":"CN",
    "gn:dem":17,
    "gn:feature_class":"P",
    "gn:feature_code":"PPL",
    "gn:name":"Shamugang",
    "gn:population":0,
    "gn:timezone":"Asia/Shanghai",
    "iso:country":"CN",
    "name:zho_x_preferred":[
        "\u6749\u6728\u5c97"
    ],
    "wof:name":"Shamugang",
    "wof:placetype":"locality"
},
  "geometry": {"coordinates":[112.6465,23.40674],"type":"Point"}
}