{
  "type": "Feature",
  "properties": {
    "gn:admin1_code":"15.0",
    "gn:asciiname":"Shanchangli",
    "gn:country_code":"CN",
    "gn:dem":2485,
    "gn:feature_class":"P",
    "gn:feature_code":"PPL",
    "gn:name":"Shanchangli",
    "gn:population":0,
    "gn:timezone":"Asia/Shanghai",
    "iso:country":"CN",
    "name:und_x_variant":[
        "\u5c71\u573a\u91cc"
    ],
    "wof:name":"Shanchangli",
    "wof:placetype":"locality"
},
  "geometry": {"coordinates":[104.43976000000001,34.59566],"type":"Point"}
}