{
  "type": "Feature",
  "properties": {
    "gn:admin1_code":"29.0",
    "gn:asciiname":"Shanggezhu",
    "gn:country_code":"CN",
    "gn:dem":1999,
    "gn:feature_class":"P",
    "gn:feature_code":"PPL",
    "gn:name":"Shanggezhu",
    "gn:population":0,
    "gn:timezone":"Asia/Shanghai",
    "iso:country":"CN",
    "name:zho_x_preferred":[
        "\u4e0a\u683c\u7af9"
    ],
    "wof:name":"Shanggezhu",
    "wof:placetype":"locality"
},
  "geometry": {"coordinates":[104.346,25.2353],"type":"Point"}
}