{
  "type": "Feature",
  "properties": {
    "gn:admin1_code":"11.0",
    "gn:asciiname":"Zhuyuanpo",
    "gn:country_code":"CN",
    "gn:dem":536,
    "gn:feature_class":"P",
    "gn:feature_code":"PPL",
    "gn:name":"Zhuyuanpo",
    "gn:population":0,
    "gn:timezone":"Asia/Shanghai",
    "iso:country":"CN",
    "name:zho_x_preferred":[
        "\u7af9\u56ed\u5761"
    ],
    "wof:name":"Zhuyuanpo",
    "wof:placetype":"locality"
},
  "geometry": {"coordinates":[110.25452,29.16696],"type":"Point"}
}