{
  "type": "Feature",
  "properties": {
    "gn:admin1_code":"14.0",
    "gn:asciiname":"Zhaxigangcun",
    "gn:country_code":"CN",
    "gn:dem":3367,
    "gn:feature_class":"P",
    "gn:feature_code":"PPL",
    "gn:name":"Zhaxigangcun",
    "gn:population":0,
    "gn:timezone":"Asia/Urumqi",
    "iso:country":"CN",
    "name:zho_x_preferred":[
        "\u624e\u897f\u5c97\u6751"
    ],
    "wof:name":"Zhaxigangcun",
    "wof:placetype":"locality"
},
  "geometry": {"coordinates":[94.74332,29.74713],"type":"Point"}
}