{
  "type": "Feature",
  "properties": {
    "gn:admin1_code":"8.0",
    "gn:asciiname":"Benfucun",
    "gn:country_code":"CN",
    "gn:dem":67,
    "gn:feature_class":"P",
    "gn:feature_code":"PPL",
    "gn:name":"Benfucun",
    "gn:population":0,
    "gn:timezone":"Asia/Shanghai",
    "iso:country":"CN",
    "name:zho_x_preferred":[
        "\u672c\u798f\u6751"
    ],
    "wof:name":"Benfucun",
    "wof:placetype":"locality"
},
  "geometry": {"coordinates":[132.21486999999999,46.51969],"type":"Point"}
}