{
  "type": "Feature",
  "properties": {
    "gn:admin1_code":"30.0",
    "gn:asciiname":"Oujiadong",
    "gn:country_code":"CN",
    "gn:dem":96,
    "gn:feature_class":"P",
    "gn:feature_code":"PPL",
    "gn:name":"Oujiadong",
    "gn:population":0,
    "gn:timezone":"Asia/Shanghai",
    "iso:country":"CN",
    "name:zho_x_preferred":[
        "\u6b27\u5bb6\u6d1e"
    ],
    "wof:name":"Oujiadong",
    "wof:placetype":"locality"
},
  "geometry": {"coordinates":[113.80783999999998,25.01021],"type":"Point"}
}