{
  "type": "Feature",
  "properties": {
    "gn:admin1_code":"25",
    "gn:asciiname":"Yuligou",
    "gn:country_code":"CN",
    "gn:dem":168,
    "gn:feature_class":"P",
    "gn:feature_code":"PPL",
    "gn:name":"Yuligou",
    "gn:population":0,
    "gn:timezone":"Asia/Shanghai",
    "iso:country":"CN",
    "name:zho_x_preferred":[
        "\u4e8e\u91cc\u6c9f"
    ],
    "wof:name":"Yuligou",
    "wof:placetype":"locality"
},
  "geometry": {"coordinates":[118.95099999999999,35.8126],"type":"Point"}
}