{
  "type": "Feature",
  "properties": {
    "gn:admin1_code":"02",
    "gn:asciiname":"Fangjiahe Toucun",
    "gn:country_code":"CN",
    "gn:dem":91,
    "gn:feature_class":"P",
    "gn:feature_code":"PPL",
    "gn:name":"Fangjiahe Toucun",
    "gn:population":0,
    "gn:timezone":"Asia/Shanghai",
    "iso:country":"CN",
    "name:und_x_variant":[
        "Fengjia Hetou",
        "\u65b9\u5bb6\u6cb3\u5934",
        "Linghu",
        "\u65b9\u5bb6\u6cb3\u5934\u6751",
        "Fangjia Hetou",
        "Hetou",
        "Fangjiahe Toucun"
    ],
    "name:zho_x_preferred":[
        "\u6cb3\u5934"
    ],
    "wof:name":"Fangjiahe Toucun",
    "wof:placetype":"locality"
},
  "geometry": {"coordinates":[121.48352,30.0745],"type":"Point"}
}