{
  "type": "Feature",
  "properties": {
    "gn:admin1_code":"12.0",
    "gn:asciiname":"Dongjiawan",
    "gn:country_code":"CN",
    "gn:dem":83,
    "gn:feature_class":"P",
    "gn:feature_code":"PPL",
    "gn:name":"Dongjiawan",
    "gn:population":0,
    "gn:timezone":"Asia/Shanghai",
    "iso:country":"CN",
    "name:zho_x_preferred":[
        "Dongjiawan"
    ],
    "name:zho_x_variant":[
        "\u8463\u5bb6\u6e7e"
    ],
    "wof:name":"Dongjiawan",
    "wof:placetype":"locality"
},
  "geometry": {"coordinates":[114.52848,29.82048],"type":"Point"}
}