{
  "type": "Feature",
  "properties": {
    "gn:admin1_code":"9.0",
    "gn:asciiname":"Huoshuiyang",
    "gn:country_code":"CN",
    "gn:dem":233,
    "gn:feature_class":"P",
    "gn:feature_code":"PPL",
    "gn:name":"Huoshuiyang",
    "gn:population":0,
    "gn:timezone":"Asia/Shanghai",
    "iso:country":"CN",
    "name:zho_x_preferred":[
        "\u6d3b\u6c34\u6768"
    ],
    "wof:name":"Huoshuiyang",
    "wof:placetype":"locality"
},
  "geometry": {"coordinates":[112.82183000000001,32.38768],"type":"Point"}
}