{
  "type": "Feature",
  "properties": {
    "gn:admin1_code":"8.0",
    "gn:asciiname":"Qiaoxitun",
    "gn:country_code":"CN",
    "gn:dem":122,
    "gn:feature_class":"P",
    "gn:feature_code":"PPL",
    "gn:name":"Qiaoxitun",
    "gn:population":0,
    "gn:timezone":"Asia/Shanghai",
    "iso:country":"CN",
    "name:zho_x_preferred":[
        "\u6865\u897f\u5c6f"
    ],
    "wof:name":"Qiaoxitun",
    "wof:placetype":"locality"
},
  "geometry": {"coordinates":[126.20089,45.78442],"type":"Point"}
}