{
  "type": "Feature",
  "properties": {
    "gn:admin1_code":"18",
    "gn:asciiname":"Tundixia",
    "gn:country_code":"CN",
    "gn:dem":779,
    "gn:feature_class":"P",
    "gn:feature_code":"PPL",
    "gn:name":"Tundixia",
    "gn:population":0,
    "gn:timezone":"Asia/Shanghai",
    "iso:country":"CN",
    "name:zho_x_preferred":[
        "\u5c6f\u5e95\u4e0b"
    ],
    "wof:name":"Tundixia",
    "wof:placetype":"locality"
},
  "geometry": {"coordinates":[108.078,28.2309],"type":"Point"}
}