{
  "type": "Feature",
  "properties": {
    "gn:admin1_code":"9.0",
    "gn:asciiname":"Nanda Wangzhuang",
    "gn:country_code":"CN",
    "gn:dem":68,
    "gn:feature_class":"P",
    "gn:feature_code":"PPL",
    "gn:name":"Nanda Wangzhuang",
    "gn:population":0,
    "gn:timezone":"Asia/Shanghai",
    "iso:country":"CN",
    "name:zho_x_preferred":[
        "\u5357\u5927\u738b\u5e84"
    ],
    "wof:name":"Nanda Wangzhuang",
    "wof:placetype":"locality"
},
  "geometry": {"coordinates":[114.50971,35.25644000000001],"type":"Point"}
}