{
  "type": "Feature",
  "properties": {
    "gn:admin1_code":"7.0",
    "gn:asciiname":"Houyangcun",
    "gn:country_code":"CN",
    "gn:dem":385,
    "gn:feature_class":"P",
    "gn:feature_code":"PPL",
    "gn:name":"Houyangcun",
    "gn:population":0,
    "gn:timezone":"Asia/Shanghai",
    "iso:country":"CN",
    "name:zho_x_preferred":[
        "\u540e\u6d0b\u6751"
    ],
    "wof:name":"Houyangcun",
    "wof:placetype":"locality"
},
  "geometry": {"coordinates":[117.47602000000001,26.45394000000001],"type":"Point"}
}