{
  "type": "Feature",
  "properties": {
    "gn:admin1_code":"12.0",
    "gn:asciiname":"Shuanglouzi",
    "gn:country_code":"CN",
    "gn:dem":115,
    "gn:feature_class":"P",
    "gn:feature_code":"PPL",
    "gn:name":"Shuanglouzi",
    "gn:population":0,
    "gn:timezone":"Asia/Shanghai",
    "iso:country":"CN",
    "name:zho_x_preferred":[
        "\u53cc\u697c\u5b50"
    ],
    "wof:name":"Shuanglouzi",
    "wof:placetype":"locality"
},
  "geometry": {"coordinates":[112.82951,31.9883],"type":"Point"}
}