{
  "type": "Feature",
  "properties": {
    "gn:admin1_code":"25",
    "gn:asciiname":"Sanshilipu",
    "gn:country_code":"CN",
    "gn:dem":75,
    "gn:feature_class":"P",
    "gn:feature_code":"PPL",
    "gn:name":"Sanshilipu",
    "gn:population":0,
    "gn:timezone":"Asia/Shanghai",
    "iso:country":"CN",
    "name:zho_x_preferred":[
        "\u4e09\u5341\u91cc\u94fa"
    ],
    "wof:name":"Sanshilipu",
    "wof:placetype":"locality"
},
  "geometry": {"coordinates":[119.187,36.3054],"type":"Point"}
}