{
  "type": "Feature",
  "properties": {
    "gn:admin1_code":"30.0",
    "gn:asciiname":"Guilin",
    "gn:country_code":"CN",
    "gn:dem":415,
    "gn:feature_class":"P",
    "gn:feature_code":"PPL",
    "gn:name":"Guilin",
    "gn:population":0,
    "gn:timezone":"Asia/Shanghai",
    "iso:country":"CN",
    "name:zho_x_preferred":[
        "Guilin"
    ],
    "name:zho_x_variant":[
        "\u6842\u6797"
    ],
    "wof:name":"Guilin",
    "wof:placetype":"locality"
},
  "geometry": {"coordinates":[115.08056000000001,24.12139],"type":"Point"}
}