{
  "type": "Feature",
  "properties": {
    "gn:admin1_code":"4.0",
    "gn:asciiname":"Yuezhuangcun",
    "gn:country_code":"CN",
    "gn:dem":29,
    "gn:feature_class":"P",
    "gn:feature_code":"PPL",
    "gn:name":"Yuezhuangcun",
    "gn:population":0,
    "gn:timezone":"Asia/Shanghai",
    "iso:country":"CN",
    "name:zho_x_preferred":[
        "\u5cb3\u5e84\u6751"
    ],
    "wof:name":"Yuezhuangcun",
    "wof:placetype":"locality"
},
  "geometry": {"coordinates":[117.49688999999999,34.31012],"type":"Point"}
}