{
  "type": "Feature",
  "properties": {
    "gn:admin1_code":"25",
    "gn:asciiname":"Wangchengzhai",
    "gn:country_code":"CN",
    "gn:dem":27,
    "gn:feature_class":"P",
    "gn:feature_code":"PPL",
    "gn:name":"Wangchengzhai",
    "gn:population":0,
    "gn:timezone":"Asia/Shanghai",
    "iso:country":"CN",
    "name:zho_x_preferred":[
        "\u738b\u7a0b\u5be8"
    ],
    "wof:name":"Wangchengzhai",
    "wof:placetype":"locality"
},
  "geometry": {"coordinates":[116.33799999999999,37.274],"type":"Point"}
}