{
  "type": "Feature",
  "properties": {
    "gn:admin1_code":"29",
    "gn:asciiname":"Pohuo",
    "gn:country_code":"CN",
    "gn:dem":1260,
    "gn:feature_class":"P",
    "gn:feature_code":"PPL",
    "gn:name":"Pohuo",
    "gn:population":0,
    "gn:timezone":"Asia/Shanghai",
    "iso:country":"CN",
    "name:zho_x_preferred":[
        "\u5761\u6216"
    ],
    "wof:name":"Pohuo",
    "wof:placetype":"locality"
},
  "geometry": {"coordinates":[105.586,23.5418],"type":"Point"}
}