{
  "type": "Feature",
  "properties": {
    "gn:admin1_code":"30",
    "gn:asciiname":"Jitiling",
    "gn:country_code":"CN",
    "gn:dem":15,
    "gn:feature_class":"P",
    "gn:feature_code":"PPL",
    "gn:name":"Jitiling",
    "gn:population":0,
    "gn:timezone":"Asia/Urumqi",
    "iso:country":"CN",
    "name:zho_x_preferred":[
        "\u9e21\u557c\u5cad"
    ],
    "wof:name":"Jitiling",
    "wof:placetype":"locality"
},
  "geometry": {"coordinates":[110.95341999999999,21.61464],"type":"Point"}
}