{
  "type": "Feature",
  "properties": {
    "gn:admin1_code":"26.0",
    "gn:asciiname":"Linchang",
    "gn:country_code":"CN",
    "gn:dem":1413,
    "gn:feature_class":"P",
    "gn:feature_code":"PPLF",
    "gn:name":"Linchang",
    "gn:population":0,
    "gn:timezone":"Asia/Shanghai",
    "iso:country":"CN",
    "name:und_x_variant":[
        "\u6797\u573a"
    ],
    "wof:name":"Linchang",
    "wof:placetype":"locality"
},
  "geometry": {"coordinates":[107.46402999999999,33.63755],"type":"Point"}
}