{
  "type": "Feature",
  "properties": {
    "gn:admin1_code":"30.0",
    "gn:asciiname":"Sumaoping",
    "gn:country_code":"CN",
    "gn:dem":634,
    "gn:feature_class":"P",
    "gn:feature_code":"PPL",
    "gn:name":"Sumaoping",
    "gn:population":0,
    "gn:timezone":"Asia/Shanghai",
    "iso:country":"CN",
    "name:zho_x_preferred":[
        "\u82cf\u8305\u576a"
    ],
    "wof:name":"Sumaoping",
    "wof:placetype":"locality"
},
  "geometry": {"coordinates":[115.39847,23.24519],"type":"Point"}
}