{
  "type": "Feature",
  "properties": {
    "gn:admin1_code":"7.0",
    "gn:asciiname":"Xiafeng",
    "gn:country_code":"CN",
    "gn:dem":358,
    "gn:feature_class":"P",
    "gn:feature_code":"PPL",
    "gn:name":"Xiafeng",
    "gn:population":0,
    "gn:timezone":"Asia/Shanghai",
    "iso:country":"CN",
    "name:zho_x_preferred":[
        "\u971e\u5cf0"
    ],
    "wof:name":"Xiafeng",
    "wof:placetype":"locality"
},
  "geometry": {"coordinates":[117.17189999999999,24.77265],"type":"Point"}
}