{
  "type": "Feature",
  "properties": {
    "gn:admin1_code":"15.0",
    "gn:asciiname":"Baohuacha",
    "gn:country_code":"CN",
    "gn:dem":1726,
    "gn:feature_class":"P",
    "gn:feature_code":"PPL",
    "gn:name":"Baohuacha",
    "gn:population":0,
    "gn:timezone":"Asia/Shanghai",
    "iso:country":"CN",
    "name:und_x_variant":[
        "\u5821\u82b1\u5c94"
    ],
    "wof:name":"Baohuacha",
    "wof:placetype":"locality"
},
  "geometry": {"coordinates":[104.99934,35.80769],"type":"Point"}
}