{
  "type": "Feature",
  "properties": {
    "gn:admin1_code":"29.0",
    "gn:asciiname":"Heiwucun",
    "gn:country_code":"CN",
    "gn:dem":2118,
    "gn:feature_class":"P",
    "gn:feature_code":"PPL",
    "gn:name":"Heiwucun",
    "gn:population":0,
    "gn:timezone":"Asia/Shanghai",
    "iso:country":"CN",
    "name:zho_x_preferred":[
        "\u9ed1\u6b66\u6751"
    ],
    "wof:name":"Heiwucun",
    "wof:placetype":"locality"
},
  "geometry": {"coordinates":[103.39100000000001,27.6297],"type":"Point"}
}