{
  "type": "Feature",
  "properties": {
    "gn:admin1_code":"20",
    "gn:asciiname":"Erden Bulag Sum",
    "gn:cc2":"CN",
    "gn:country_code":"CN",
    "gn:dem":1044,
    "gn:feature_class":"P",
    "gn:feature_code":"PPL",
    "gn:name":"Erden Bulag Sum",
    "gn:population":0,
    "gn:timezone":"Asia/Shanghai",
    "iso:country":"CN",
    "name:und_x_variant":[
        "Kung-chi-ssu-ling",
        "Erden Bulag",
        "Erden Bulag Sum"
    ],
    "wof:name":"Erden Bulag Sum",
    "wof:placetype":"locality"
},
  "geometry": {"coordinates":[108.91139,40.85417],"type":"Point"}
}