{
  "type": "Feature",
  "properties": {
    "gn:admin1_code":"18.0",
    "gn:asciiname":"Xiayong",
    "gn:country_code":"CN",
    "gn:dem":578,
    "gn:feature_class":"P",
    "gn:feature_code":"PPL",
    "gn:name":"Xiayong",
    "gn:population":0,
    "gn:timezone":"Asia/Shanghai",
    "iso:country":"CN",
    "name:zho_x_preferred":[
        "\u4e0b\u5eb8"
    ],
    "wof:name":"Xiayong",
    "wof:placetype":"locality"
},
  "geometry": {"coordinates":[107.755,25.8249],"type":"Point"}
}