{
  "type": "Feature",
  "properties": {
    "gn:admin1_code":"29.0",
    "gn:asciiname":"Xiaozhizhai",
    "gn:country_code":"CN",
    "gn:dem":1572,
    "gn:feature_class":"P",
    "gn:feature_code":"PPL",
    "gn:name":"Xiaozhizhai",
    "gn:population":0,
    "gn:timezone":"Asia/Shanghai",
    "iso:country":"CN",
    "name:zho_x_preferred":[
        "\u5c0f\u5740\u5be8"
    ],
    "wof:name":"Xiaozhizhai",
    "wof:placetype":"locality"
},
  "geometry": {"coordinates":[104.048,24.5088],"type":"Point"}
}