{
  "type": "Feature",
  "properties": {
    "gn:admin1_code":"11",
    "gn:asciiname":"Shangjietou",
    "gn:country_code":"CN",
    "gn:dem":323,
    "gn:feature_class":"P",
    "gn:feature_code":"PPL",
    "gn:name":"Shangjietou",
    "gn:population":0,
    "gn:timezone":"Asia/Shanghai",
    "iso:country":"CN",
    "name:und_x_variant":[
        "\u4e0a\u754c\u5934",
        "Shangjietou"
    ],
    "wof:name":"Shangjietou",
    "wof:placetype":"locality"
},
  "geometry": {"coordinates":[112.23056,25.64],"type":"Point"}
}