{
  "type": "Feature",
  "properties": {
    "gn:admin1_code":"7.0",
    "gn:asciiname":"Yangzhong",
    "gn:country_code":"CN",
    "gn:dem":446,
    "gn:feature_class":"P",
    "gn:feature_code":"PPL",
    "gn:name":"Yangzhong",
    "gn:population":0,
    "gn:timezone":"Asia/Shanghai",
    "iso:country":"CN",
    "name:zho_x_preferred":[
        "Yangzhong"
    ],
    "name:zho_x_variant":[
        "\u6d0b\u4e2d"
    ],
    "wof:name":"Yangzhong",
    "wof:placetype":"locality"
},
  "geometry": {"coordinates":[118.90722,26.59833],"type":"Point"}
}