{
  "type": "Feature",
  "properties": {
    "gn:admin1_code":"7.0",
    "gn:asciiname":"Yangzhong",
    "gn:country_code":"CN",
    "gn:dem":446,
    "gn:feature_class":"P",
    "gn:feature_code":"PPL",
    "gn:name":"Yangzhong",
    "gn:population":0,
    "gn:timezone":"Asia/Shanghai",
    "iso:country":"CN",
    "name:deu_x_preferred":[
        "Yangzhong"
    ],
    "name:fas_x_preferred":[
        "\u06cc\u0627\u0646\u06af\u0698\u0627\u0646\u06af"
    ],
    "name:fra_x_preferred":[
        "Yangzhong"
    ],
    "name:ita_x_preferred":[
        "Yangzhong"
    ],
    "name:jpn_x_preferred":[
        "\u63da\u4e2d\u5e02"
    ],
    "name:kik_x_preferred":[
        "Yangzhong"
    ],
    "name:kor_x_preferred":[
        "\uc591\uc911\uc2dc"
    ],
    "name:nor_x_preferred":[
        "Yangzhong"
    ],
    "name:rus_x_preferred":[
        "\u042f\u043d\u0447\u0436\u0443\u043d"
    ],
    "name:swe_x_preferred":[
        "Yangzhong"
    ],
    "name:tgl_x_preferred":[
        "Yangzhong"
    ],
    "name:urd_x_preferred":[
        "\u06cc\u0627\u0646\u06af\u0698\u0648\u0646\u06af"
    ],
    "name:vie_x_preferred":[
        "D\u01b0\u01a1ng Trung"
    ],
    "name:wuu_x_preferred":[
        "\u626c\u4e2d\u5e02"
    ],
    "name:zho_x_preferred":[
        "Yangzhong"
    ],
    "name:zho_x_variant":[
        "\u6d0b\u4e2d",
        "\u626c\u4e2d\u5e02"
    ],
    "wof:name":"Yangzhong",
    "wof:placetype":"locality"
},
  "geometry": {"coordinates":[118.90722,26.59833],"type":"Point"}
}