{
  "type": "Feature",
  "properties": {
    "gn:admin1_code":"2.0",
    "gn:asciiname":"Mingong",
    "gn:country_code":"CN",
    "gn:dem":1097,
    "gn:feature_class":"P",
    "gn:feature_code":"PPLF",
    "gn:name":"Mingong",
    "gn:population":0,
    "gn:timezone":"Asia/Shanghai",
    "iso:country":"CN",
    "name:zho_x_preferred":[
        "\u6c11\u516c"
    ],
    "wof:name":"Mingong",
    "wof:placetype":"locality"
},
  "geometry": {"coordinates":[119.27385,27.75325],"type":"Point"}
}