{
  "type": "Feature",
  "properties": {
    "gn:admin1_code":"9",
    "gn:asciiname":"Houwa",
    "gn:country_code":"CN",
    "gn:dem":39,
    "gn:feature_class":"P",
    "gn:feature_code":"PPL",
    "gn:name":"Houwa",
    "gn:population":0,
    "gn:timezone":"Asia/Shanghai",
    "iso:country":"CN",
    "name:zho_x_preferred":[
        "\u4faf\u6d3c"
    ],
    "wof:name":"Houwa",
    "wof:placetype":"locality"
},
  "geometry": {"coordinates":[116.15300000000001,34.0168],"type":"Point"}
}