{
  "type": "Feature",
  "properties": {
    "gn:admin1_code":"5.0",
    "gn:asciiname":"Gaojia Shaoguo Hebeicun",
    "gn:country_code":"CN",
    "gn:dem":205,
    "gn:feature_class":"P",
    "gn:feature_code":"PPL",
    "gn:name":"Gaojia Shaoguo Hebeicun",
    "gn:population":0,
    "gn:timezone":"Asia/Shanghai",
    "iso:country":"CN",
    "name:zho_x_preferred":[
        "\u9ad8\u5bb6\u70e7\u9505\u6cb3\u5317\u6751"
    ],
    "wof:name":"Gaojia Shaoguo Hebeicun",
    "wof:placetype":"locality"
},
  "geometry": {"coordinates":[126.08305,43.96389],"type":"Point"}
}