{
  "type": "Feature",
  "properties": {
    "gn:admin1_code":"8.0",
    "gn:asciiname":"Huanan",
    "gn:country_code":"CN",
    "gn:dem":403,
    "gn:feature_class":"P",
    "gn:feature_code":"PPL",
    "gn:name":"Huanan",
    "gn:population":0,
    "gn:timezone":"Asia/Shanghai",
    "iso:country":"CN",
    "name:deu_x_preferred":[
        "Huanan"
    ],
    "name:zho_x_preferred":[
        "\u534e\u5357"
    ],
    "wof:name":"Huanan",
    "wof:placetype":"locality"
},
  "geometry": {"coordinates":[128.72020000000001,47.12796],"type":"Point"}
}