{
  "type": "Feature",
  "properties": {
    "gn:admin1_code":"11",
    "gn:asciiname":"Yanghongyan",
    "gn:country_code":"CN",
    "gn:dem":268,
    "gn:feature_class":"P",
    "gn:feature_code":"PPL",
    "gn:name":"Yanghongyan",
    "gn:population":0,
    "gn:timezone":"Asia/Shanghai",
    "iso:country":"CN",
    "name:zho_x_preferred":[
        "\u6768\u6d2a\u5ca9"
    ],
    "wof:name":"Yanghongyan",
    "wof:placetype":"locality"
},
  "geometry": {"coordinates":[111.50958,27.969],"type":"Point"}
}