{
  "type": "Feature",
  "properties": {
    "gn:admin1_code":"14",
    "gn:asciiname":"Gebai",
    "gn:country_code":"CN",
    "gn:dem":4137,
    "gn:feature_class":"P",
    "gn:feature_code":"PPL",
    "gn:name":"Gebai",
    "gn:population":0,
    "gn:timezone":"Asia/Urumqi",
    "iso:country":"CN",
    "name:zho_x_preferred":[
        "\u683c\u767d"
    ],
    "wof:name":"Gebai",
    "wof:placetype":"locality"
},
  "geometry": {"coordinates":[89.3793,29.1414],"type":"Point"}
}