{
  "type": "Feature",
  "properties": {
    "gn:admin1_code":"26.0",
    "gn:asciiname":"Taipingzhuangcun",
    "gn:country_code":"CN",
    "gn:dem":400,
    "gn:feature_class":"P",
    "gn:feature_code":"PPL",
    "gn:name":"Taipingzhuangcun",
    "gn:population":0,
    "gn:timezone":"Asia/Shanghai",
    "iso:country":"CN",
    "name:zho_x_preferred":[
        "\u592a\u5e73\u5e84\u6751"
    ],
    "wof:name":"Taipingzhuangcun",
    "wof:placetype":"locality"
},
  "geometry": {"coordinates":[110.76286,33.42843],"type":"Point"}
}