{
  "type": "Feature",
  "properties": {
    "gn:admin1_code":"10",
    "gn:asciiname":"Yidaoliang",
    "gn:country_code":"CN",
    "gn:dem":1584,
    "gn:feature_class":"P",
    "gn:feature_code":"PPL",
    "gn:name":"Yidaoliang",
    "gn:population":0,
    "gn:timezone":"Asia/Shanghai",
    "iso:country":"CN",
    "name:zho_x_preferred":[
        "\u4e00\u9053\u6881"
    ],
    "wof:name":"Yidaoliang",
    "wof:placetype":"locality"
},
  "geometry": {"coordinates":[116.20984,41.86865],"type":"Point"}
}