{
  "type": "Feature",
  "properties": {
    "gn:admin1_code":"29",
    "gn:asciiname":"Gaoshishao",
    "gn:country_code":"CN",
    "gn:dem":1858,
    "gn:feature_class":"P",
    "gn:feature_code":"PPL",
    "gn:name":"Gaoshishao",
    "gn:population":0,
    "gn:timezone":"Asia/Shanghai",
    "iso:country":"CN",
    "name:zho_x_preferred":[
        "\u9ad8\u77f3\u54e8"
    ],
    "wof:name":"Gaoshishao",
    "wof:placetype":"locality"
},
  "geometry": {"coordinates":[103.372,24.8875],"type":"Point"}
}