{
  "type": "Feature",
  "properties": {
    "gn:admin1_code":"15.0",
    "gn:asciiname":"Loufangzi",
    "gn:country_code":"CN",
    "gn:dem":1210,
    "gn:feature_class":"P",
    "gn:feature_code":"PPL",
    "gn:name":"Loufangzi",
    "gn:population":0,
    "gn:timezone":"Asia/Shanghai",
    "iso:country":"CN",
    "name:und_x_variant":[
        "\u697c\u623f\u5b50"
    ],
    "wof:name":"Loufangzi",
    "wof:placetype":"locality"
},
  "geometry": {"coordinates":[107.35696000000002,36.34121],"type":"Point"}
}