{
  "type": "Feature",
  "properties": {
    "gn:admin1_code":"3.0",
    "gn:asciiname":"Yushancun",
    "gn:country_code":"CN",
    "gn:dem":53,
    "gn:feature_class":"P",
    "gn:feature_code":"PPL",
    "gn:name":"Yushancun",
    "gn:population":0,
    "gn:timezone":"Asia/Shanghai",
    "iso:country":"CN",
    "name:und_x_variant":[
        "\u7389\u5c71\u6751"
    ],
    "wof:name":"Yushancun",
    "wof:placetype":"locality"
},
  "geometry": {"coordinates":[115.44079000000001,28.69487],"type":"Point"}
}