{
  "type": "Feature",
  "properties": {
    "gn:admin1_code":"19.0",
    "gn:asciiname":"Chuanjinggou",
    "gn:country_code":"CN",
    "gn:dem":11,
    "gn:feature_class":"P",
    "gn:feature_code":"PPL",
    "gn:name":"Chuanjinggou",
    "gn:population":0,
    "gn:timezone":"Asia/Shanghai",
    "iso:country":"CN",
    "name:zho_x_preferred":[
        "\u5ddd\u4e95\u6c9f"
    ],
    "wof:name":"Chuanjinggou",
    "wof:placetype":"locality"
},
  "geometry": {"coordinates":[121.461,39.0167],"type":"Point"}
}