{
  "type": "Feature",
  "properties": {
    "gn:admin1_code":"32.0",
    "gn:asciiname":"Xingchangzi",
    "gn:country_code":"CN",
    "gn:dem":424,
    "gn:feature_class":"P",
    "gn:feature_code":"PPL",
    "gn:name":"Xingchangzi",
    "gn:population":0,
    "gn:timezone":"Asia/Shanghai",
    "iso:country":"CN",
    "name:zho_x_preferred":[
        "\u5174\u957f\u5b50"
    ],
    "wof:name":"Xingchangzi",
    "wof:placetype":"locality"
},
  "geometry": {"coordinates":[105.39861000000001,28.70215],"type":"Point"}
}