{
  "type": "Feature",
  "properties": {
    "gn:admin1_code":"4.0",
    "gn:asciiname":"Tangxu",
    "gn:country_code":"CN",
    "gn:dem":4,
    "gn:feature_class":"P",
    "gn:feature_code":"PPL",
    "gn:name":"Tangxu",
    "gn:population":0,
    "gn:timezone":"Asia/Shanghai",
    "iso:country":"CN",
    "name:zho_x_preferred":[
        "Tangxu"
    ],
    "name:zho_x_variant":[
        "\u5510\u5729"
    ],
    "wof:name":"Tangxu",
    "wof:placetype":"locality"
},
  "geometry": {"coordinates":[119.09591,33.27199],"type":"Point"}
}