{
  "type": "Feature",
  "properties": {
    "gn:admin1_code":"26.0",
    "gn:asciiname":"Shaogouyuancun",
    "gn:country_code":"CN",
    "gn:dem":1716,
    "gn:feature_class":"P",
    "gn:feature_code":"PPL",
    "gn:name":"Shaogouyuancun",
    "gn:population":0,
    "gn:timezone":"Asia/Shanghai",
    "iso:country":"CN",
    "name:zho_x_preferred":[
        "\u68a2\u6c9f\u586c\u6751"
    ],
    "wof:name":"Shaogouyuancun",
    "wof:placetype":"locality"
},
  "geometry": {"coordinates":[107.28507,37.34333],"type":"Point"}
}