{
  "type": "Feature",
  "properties": {
    "gn:admin1_code":"29.0",
    "gn:asciiname":"Bubeng",
    "gn:country_code":"CN",
    "gn:dem":717,
    "gn:feature_class":"P",
    "gn:feature_code":"PPL",
    "gn:name":"Bubeng",
    "gn:population":0,
    "gn:timezone":"Asia/Shanghai",
    "iso:country":"CN",
    "name:zho_x_preferred":[
        "\u8865\u868c"
    ],
    "wof:name":"Bubeng",
    "wof:placetype":"locality"
},
  "geometry": {"coordinates":[101.583,21.6025],"type":"Point"}
}