{
  "type": "Feature",
  "properties": {
    "gn:admin1_code":"29.0",
    "gn:asciiname":"Lannigou",
    "gn:country_code":"CN",
    "gn:dem":2676,
    "gn:feature_class":"P",
    "gn:feature_code":"PPL",
    "gn:name":"Lannigou",
    "gn:population":0,
    "gn:timezone":"Asia/Shanghai",
    "iso:country":"CN",
    "name:zho_x_preferred":[
        "\u6ee5\u6ce5\u6c9f"
    ],
    "wof:name":"Lannigou",
    "wof:placetype":"locality"
},
  "geometry": {"coordinates":[103.38200000000001,25.9643],"type":"Point"}
}