{
  "type": "Feature",
  "properties": {
    "gn:admin1_code":"19.0",
    "gn:asciiname":"Wangbaozhai",
    "gn:country_code":"CN",
    "gn:dem":124,
    "gn:feature_class":"P",
    "gn:feature_code":"PPL",
    "gn:name":"Wangbaozhai",
    "gn:population":0,
    "gn:timezone":"Asia/Shanghai",
    "iso:country":"CN",
    "name:zho_x_preferred":[
        "\u671b\u5b9d\u5be8"
    ],
    "wof:name":"Wangbaozhai",
    "wof:placetype":"locality"
},
  "geometry": {"coordinates":[123.27146999999999,41.10414],"type":"Point"}
}