{
  "type": "Feature",
  "properties": {
    "gn:admin1_code":"29",
    "gn:asciiname":"Luchong",
    "gn:country_code":"CN",
    "gn:dem":1741,
    "gn:feature_class":"P",
    "gn:feature_code":"PPL",
    "gn:name":"Luchong",
    "gn:population":0,
    "gn:timezone":"Asia/Shanghai",
    "iso:country":"CN",
    "name:zho_x_preferred":[
        "\u7984\u5145"
    ],
    "wof:name":"Luchong",
    "wof:placetype":"locality"
},
  "geometry": {"coordinates":[102.839,24.5588],"type":"Point"}
}