{
  "type": "Feature",
  "properties": {
    "gn:admin1_code":"1.0",
    "gn:asciiname":"Yanglingtou",
    "gn:country_code":"CN",
    "gn:dem":16,
    "gn:feature_class":"P",
    "gn:feature_code":"PPL",
    "gn:name":"Yanglingtou",
    "gn:population":0,
    "gn:timezone":"Asia/Shanghai",
    "iso:country":"CN",
    "name:und_x_variant":[
        "\u6768\u5cad\u5934"
    ],
    "wof:name":"Yanglingtou",
    "wof:placetype":"locality"
},
  "geometry": {"coordinates":[116.24111000000001,29.90729],"type":"Point"}
}