{
  "type": "Feature",
  "properties": {
    "gn:admin1_code":"10",
    "gn:asciiname":"Liujiazhuang",
    "gn:cc2":"CN",
    "gn:country_code":"CN",
    "gn:dem":163,
    "gn:feature_class":"P",
    "gn:feature_code":"PPL",
    "gn:name":"Liujiazhuang",
    "gn:population":0,
    "gn:timezone":"Asia/Shanghai",
    "iso:country":"CN",
    "name:und_x_variant":[
        "Liu-chia-chuang",
        "Liujiazhuang"
    ],
    "wof:name":"Liujiazhuang",
    "wof:placetype":"locality"
},
  "geometry": {"coordinates":[118.51667,40.11667],"type":"Point"}
}