{
  "type": "Feature",
  "properties": {
    "gn:admin1_code":"3.0",
    "gn:asciiname":"Lishupai",
    "gn:country_code":"CN",
    "gn:dem":244,
    "gn:feature_class":"P",
    "gn:feature_code":"PPL",
    "gn:name":"Lishupai",
    "gn:population":0,
    "gn:timezone":"Asia/Shanghai",
    "iso:country":"CN",
    "name:und_x_variant":[
        "\u674e\u6811\u6392"
    ],
    "wof:name":"Lishupai",
    "wof:placetype":"locality"
},
  "geometry": {"coordinates":[115.9765,26.1845],"type":"Point"}
}