{
  "type": "Feature",
  "properties": {
    "gn:admin1_code":"4.0",
    "gn:asciiname":"Xiaowangzhuang",
    "gn:country_code":"CN",
    "gn:dem":5,
    "gn:feature_class":"P",
    "gn:feature_code":"PPL",
    "gn:name":"Xiaowangzhuang",
    "gn:population":0,
    "gn:timezone":"Asia/Shanghai",
    "iso:country":"CN",
    "name:und_x_variant":[
        "\u5c0f\u738b\u5e84"
    ],
    "name:zho_x_preferred":[
        "\u5c0f\u738b\u5e84"
    ],
    "wof:name":"Xiaowangzhuang",
    "wof:placetype":"locality"
},
  "geometry": {"coordinates":[120.51392,32.18214],"type":"Point"}
}