{
  "type": "Feature",
  "properties": {
    "gn:admin1_code":"4.0",
    "gn:asciiname":"Yinjiayuan",
    "gn:country_code":"CN",
    "gn:dem":5,
    "gn:feature_class":"P",
    "gn:feature_code":"PPL",
    "gn:name":"Yinjiayuan",
    "gn:population":0,
    "gn:timezone":"Asia/Shanghai",
    "iso:country":"CN",
    "name:und_x_variant":[
        "\u5370\u5bb6\u9662"
    ],
    "name:zho_x_preferred":[
        "\u5370\u5bb6\u9662"
    ],
    "wof:name":"Yinjiayuan",
    "wof:placetype":"locality"
},
  "geometry": {"coordinates":[120.20226,32.181],"type":"Point"}
}