{
  "type": "Feature",
  "properties": {
    "gn:admin1_code":"2.0",
    "gn:asciiname":"Zhangjiatian",
    "gn:country_code":"CN",
    "gn:dem":329,
    "gn:feature_class":"P",
    "gn:feature_code":"PPL",
    "gn:name":"Zhangjiatian",
    "gn:population":0,
    "gn:timezone":"Asia/Shanghai",
    "iso:country":"CN",
    "name:zho_x_preferred":[
        "\u6a1f\u5bb6\u7530"
    ],
    "wof:name":"Zhangjiatian",
    "wof:placetype":"locality"
},
  "geometry": {"coordinates":[120.96541000000001,29.72893],"type":"Point"}
}