{
  "type": "Feature",
  "properties": {
    "gn:admin1_code":"18",
    "gn:asciiname":"Chaoshui",
    "gn:country_code":"CN",
    "gn:dem":883,
    "gn:feature_class":"P",
    "gn:feature_code":"PPL",
    "gn:name":"Chaoshui",
    "gn:population":0,
    "gn:timezone":"Asia/Shanghai",
    "iso:country":"CN",
    "name:zho_x_preferred":[
        "\u6f6e\u6c34"
    ],
    "wof:name":"Chaoshui",
    "wof:placetype":"locality"
},
  "geometry": {"coordinates":[106.68899999999999,27.1492],"type":"Point"}
}