{
  "type": "Feature",
  "properties": {
    "gn:admin1_code":"14",
    "gn:asciiname":"Huijie",
    "gn:country_code":"CN",
    "gn:dem":4675,
    "gn:feature_class":"P",
    "gn:feature_code":"PPL",
    "gn:name":"Huijie",
    "gn:population":0,
    "gn:timezone":"Asia/Urumqi",
    "iso:country":"CN",
    "name:zho_x_preferred":[
        "\u6bc1\u59d0"
    ],
    "wof:name":"Huijie",
    "wof:placetype":"locality"
},
  "geometry": {"coordinates":[88.9624,28.7048],"type":"Point"}
}