{
  "type": "Feature",
  "properties": {
    "gn:admin1_code":"16.0",
    "gn:asciiname":"Dujiang",
    "gn:country_code":"CN",
    "gn:dem":25,
    "gn:feature_class":"P",
    "gn:feature_code":"PPL",
    "gn:name":"Dujiang",
    "gn:population":0,
    "gn:timezone":"Asia/Shanghai",
    "iso:country":"CN",
    "name:zho_x_preferred":[
        "\u72ec\u6c5f"
    ],
    "wof:name":"Dujiang",
    "wof:placetype":"locality"
},
  "geometry": {"coordinates":[109.19,21.561],"type":"Point"}
}