{
  "type": "Feature",
  "properties": {
    "gn:admin1_code":"21.0",
    "gn:asciiname":"Mutouwan",
    "gn:country_code":"CN",
    "gn:dem":1704,
    "gn:feature_class":"P",
    "gn:feature_code":"PPL",
    "gn:name":"Mutouwan",
    "gn:population":0,
    "gn:timezone":"Asia/Shanghai",
    "iso:country":"CN",
    "name:und_x_variant":[
        "\u6728\u5934\u6e7e"
    ],
    "name:zho_x_preferred":[
        "\u6728\u5934\u6e7e"
    ],
    "wof:name":"Mutouwan",
    "wof:placetype":"locality"
},
  "geometry": {"coordinates":[106.39927,36.08499000000001],"type":"Point"}
}