{
  "type": "Feature",
  "properties": {
    "gn:admin1_code":"29.0",
    "gn:asciiname":"Nongyang",
    "gn:country_code":"CN",
    "gn:dem":483,
    "gn:feature_class":"P",
    "gn:feature_code":"PPL",
    "gn:name":"Nongyang",
    "gn:population":0,
    "gn:timezone":"Asia/Shanghai",
    "iso:country":"CN",
    "name:zho_x_preferred":[
        "\u5f04\u517b"
    ],
    "wof:name":"Nongyang",
    "wof:placetype":"locality"
},
  "geometry": {"coordinates":[99.0552,23.5608],"type":"Point"}
}