{
  "type": "Feature",
  "properties": {
    "gn:admin1_code":"30.0",
    "gn:asciiname":"Changxincun",
    "gn:country_code":"CN",
    "gn:dem":356,
    "gn:feature_class":"P",
    "gn:feature_code":"PPL",
    "gn:name":"Changxincun",
    "gn:population":0,
    "gn:timezone":"Asia/Shanghai",
    "iso:country":"CN",
    "name:zho_x_preferred":[
        "\u957f\u65b0\u6751"
    ],
    "wof:name":"Changxincun",
    "wof:placetype":"locality"
},
  "geometry": {"coordinates":[116.77007,24.38896],"type":"Point"}
}