{
  "type": "Feature",
  "properties": {
    "gn:admin1_code":"29.0",
    "gn:asciiname":"Wutai",
    "gn:country_code":"CN",
    "gn:dem":2163,
    "gn:feature_class":"P",
    "gn:feature_code":"PPL",
    "gn:name":"Wutai",
    "gn:population":0,
    "gn:timezone":"Asia/Shanghai",
    "iso:country":"CN",
    "name:ceb_x_preferred":[
        "Wutai"
    ],
    "name:fra_x_preferred":[
        "Wutai"
    ],
    "name:nor_x_preferred":[
        "Wutai"
    ],
    "name:zho_x_preferred":[
        "\u4e94\u53f0"
    ],
    "wof:name":"Wutai",
    "wof:placetype":"locality"
},
  "geometry": {"coordinates":[100.64400000000001,25.1939],"type":"Point"}
}