{
  "type": "Feature",
  "properties": {
    "gn:admin1_code":"30.0",
    "gn:asciiname":"Tancai",
    "gn:country_code":"CN",
    "gn:dem":18,
    "gn:feature_class":"P",
    "gn:feature_code":"PPL",
    "gn:name":"Tancai",
    "gn:population":0,
    "gn:timezone":"Asia/Urumqi",
    "iso:country":"CN",
    "name:zho_x_preferred":[
        "\u8c08\u624d"
    ],
    "wof:name":"Tancai",
    "wof:placetype":"locality"
},
  "geometry": {"coordinates":[109.94166,20.32341],"type":"Point"}
}