{
  "type": "Feature",
  "properties": {
    "gn:admin1_code":"26.0",
    "gn:asciiname":"Laohugou",
    "gn:country_code":"CN",
    "gn:dem":1176,
    "gn:feature_class":"P",
    "gn:feature_code":"PPL",
    "gn:name":"Laohugou",
    "gn:population":0,
    "gn:timezone":"Asia/Shanghai",
    "iso:country":"CN",
    "name:und_x_variant":[
        "\u8001\u864e\u6c9f"
    ],
    "wof:name":"Laohugou",
    "wof:placetype":"locality"
},
  "geometry": {"coordinates":[107.23263,34.82530999999999],"type":"Point"}
}