{
  "type": "Feature",
  "properties": {
    "gn:admin1_code":"15.0",
    "gn:asciiname":"Xiaozhaiping",
    "gn:country_code":"CN",
    "gn:dem":2214,
    "gn:feature_class":"P",
    "gn:feature_code":"PPL",
    "gn:name":"Xiaozhaiping",
    "gn:population":0,
    "gn:timezone":"Asia/Shanghai",
    "iso:country":"CN",
    "name:zho_x_preferred":[
        "\u5c0f\u5be8\u576a"
    ],
    "wof:name":"Xiaozhaiping",
    "wof:placetype":"locality"
},
  "geometry": {"coordinates":[103.88500000000001,35.352],"type":"Point"}
}