{
  "type": "Feature",
  "properties": {
    "gn:admin1_code":"1.0",
    "gn:asciiname":"Pinggangcun",
    "gn:country_code":"CN",
    "gn:dem":423,
    "gn:feature_class":"P",
    "gn:feature_code":"PPL",
    "gn:name":"Pinggangcun",
    "gn:population":0,
    "gn:timezone":"Asia/Shanghai",
    "iso:country":"CN",
    "name:zho_x_preferred":[
        "\u5e73\u5c97\u6751"
    ],
    "wof:name":"Pinggangcun",
    "wof:placetype":"locality"
},
  "geometry": {"coordinates":[116.31353,30.86171],"type":"Point"}
}