{
  "type": "Feature",
  "properties": {
    "gn:admin1_code":"29.0",
    "gn:asciiname":"Feihong",
    "gn:country_code":"CN",
    "gn:dem":945,
    "gn:feature_class":"P",
    "gn:feature_code":"PPL",
    "gn:name":"Feihong",
    "gn:population":0,
    "gn:timezone":"Asia/Shanghai",
    "iso:country":"CN",
    "name:zho_x_preferred":[
        "\u83f2\u7ea2"
    ],
    "wof:name":"Feihong",
    "wof:placetype":"locality"
},
  "geometry": {"coordinates":[98.4164,24.3647],"type":"Point"}
}