{
  "type": "Feature",
  "properties": {
    "gn:admin1_code":"12.0",
    "gn:asciiname":"Baiping",
    "gn:country_code":"CN",
    "gn:dem":70,
    "gn:feature_class":"P",
    "gn:feature_code":"PPL",
    "gn:name":"Baiping",
    "gn:population":0,
    "gn:timezone":"Asia/Shanghai",
    "iso:country":"CN",
    "name:zho_x_preferred":[
        "Baiping"
    ],
    "name:zho_x_variant":[
        "\u767d\u576a"
    ],
    "wof:name":"Baiping",
    "wof:placetype":"locality"
},
  "geometry": {"coordinates":[114.80193,29.66311],"type":"Point"}
}