{
  "type": "Feature",
  "properties": {
    "gn:admin1_code":"8.0",
    "gn:asciiname":"Lalatun",
    "gn:country_code":"CN",
    "gn:dem":263,
    "gn:feature_class":"P",
    "gn:feature_code":"PPL",
    "gn:name":"Lalatun",
    "gn:population":0,
    "gn:timezone":"Asia/Shanghai",
    "iso:country":"CN",
    "name:zho_x_preferred":[
        "\u62c9\u62c9\u5c6f"
    ],
    "wof:name":"Lalatun",
    "wof:placetype":"locality"
},
  "geometry": {"coordinates":[125.08016000000001,48.19108],"type":"Point"}
}