{
  "type": "Feature",
  "properties": {
    "gn:admin1_code":"5.0",
    "gn:asciiname":"Sanjing Dianzi",
    "gn:country_code":"CN",
    "gn:dem":164,
    "gn:feature_class":"P",
    "gn:feature_code":"PPL",
    "gn:name":"Sanjing Dianzi",
    "gn:population":0,
    "gn:timezone":"Asia/Shanghai",
    "iso:country":"CN",
    "name:zho_x_preferred":[
        "\u4e09\u4e95\u5e97\u5b50"
    ],
    "wof:name":"Sanjing Dianzi",
    "wof:placetype":"locality"
},
  "geometry": {"coordinates":[122.37142,44.69327],"type":"Point"}
}