{
  "type": "Feature",
  "properties": {
    "gn:admin1_code":"31",
    "gn:asciiname":"Maojie",
    "gn:country_code":"CN",
    "gn:dem":97,
    "gn:feature_class":"P",
    "gn:feature_code":"PPL",
    "gn:name":"Maojie",
    "gn:population":0,
    "gn:timezone":"Asia/Shanghai",
    "iso:country":"CN",
    "name:und_x_variant":[
        "\u6bdb\u4ecb"
    ],
    "wof:name":"Maojie",
    "wof:placetype":"locality"
},
  "geometry": {"coordinates":[109.66894000000001,18.68475],"type":"Point"}
}