{
  "type": "Feature",
  "properties": {
    "gn:admin1_code":"8.0",
    "gn:asciiname":"Zhaojiagang",
    "gn:country_code":"CN",
    "gn:dem":182,
    "gn:feature_class":"P",
    "gn:feature_code":"PPL",
    "gn:name":"Zhaojiagang",
    "gn:population":0,
    "gn:timezone":"Asia/Shanghai",
    "iso:country":"CN",
    "name:zho_x_preferred":[
        "\u8d75\u5bb6\u5c97"
    ],
    "name:zho_x_variant":[
        "\u8d75\u5bb6\u5c97\u571f\u5bb6\u65cf\u4e61"
    ],
    "wof:name":"Zhaojiagang",
    "wof:placetype":"locality"
},
  "geometry": {"coordinates":[125.86394,45.77231],"type":"Point"}
}