{
  "type": "Feature",
  "properties": {
    "gn:admin1_code":"12.0",
    "gn:asciiname":"Fanjiawan",
    "gn:country_code":"CN",
    "gn:dem":284,
    "gn:feature_class":"P",
    "gn:feature_code":"PPL",
    "gn:name":"Fanjiawan",
    "gn:population":0,
    "gn:timezone":"Asia/Shanghai",
    "iso:country":"CN",
    "name:zho_x_preferred":[
        "\u6a0a\u5bb6\u6e7e"
    ],
    "wof:name":"Fanjiawan",
    "wof:placetype":"locality"
},
  "geometry": {"coordinates":[111.43006,32.43931],"type":"Point"}
}