{
  "type": "Feature",
  "properties": {
    "gn:admin1_code":"32",
    "gn:asciiname":"Sanguo",
    "gn:country_code":"CN",
    "gn:dem":888,
    "gn:feature_class":"P",
    "gn:feature_code":"PPL",
    "gn:name":"Sanguo",
    "gn:population":0,
    "gn:timezone":"Asia/Shanghai",
    "iso:country":"CN",
    "name:und_x_variant":[
        "Sanguoshi",
        "Sanguo"
    ],
    "wof:name":"Sanguo",
    "wof:placetype":"locality"
},
  "geometry": {"coordinates":[105.01232,32.52669],"type":"Point"}
}