{
  "type": "Feature",
  "properties": {
    "gn:admin1_code":"11.0",
    "gn:asciiname":"Shizuitou",
    "gn:country_code":"CN",
    "gn:dem":85,
    "gn:feature_class":"P",
    "gn:feature_code":"PPL",
    "gn:name":"Shizuitou",
    "gn:population":0,
    "gn:timezone":"Asia/Shanghai",
    "iso:country":"CN",
    "name:zho_x_preferred":[
        "\u77f3\u5480\u5934"
    ],
    "wof:name":"Shizuitou",
    "wof:placetype":"locality"
},
  "geometry": {"coordinates":[112.79358999999999,27.3951],"type":"Point"}
}