{
  "type": "Feature",
  "properties": {
    "gn:admin1_code":"32.0",
    "gn:asciiname":"Yuping",
    "gn:country_code":"CN",
    "gn:dem":375,
    "gn:feature_class":"P",
    "gn:feature_code":"PPL",
    "gn:name":"Yuping",
    "gn:population":0,
    "gn:timezone":"Asia/Shanghai",
    "iso:country":"CN",
    "name:zho_x_preferred":[
        "\u7389\u5c4f"
    ],
    "wof:name":"Yuping",
    "wof:placetype":"locality"
},
  "geometry": {"coordinates":[104.02602,29.26714],"type":"Point"}
}