{
  "type": "Feature",
  "properties": {
    "gn:admin1_code":"3.0",
    "gn:asciiname":"Shangchenluocun",
    "gn:country_code":"CN",
    "gn:dem":27,
    "gn:feature_class":"P",
    "gn:feature_code":"PPL",
    "gn:name":"Shangchenluocun",
    "gn:population":0,
    "gn:timezone":"Asia/Shanghai",
    "iso:country":"CN",
    "name:und_x_variant":[
        "\u4e0a\u9648\u843d\u6751"
    ],
    "wof:name":"Shangchenluocun",
    "wof:placetype":"locality"
},
  "geometry": {"coordinates":[116.38807,28.56054],"type":"Point"}
}