{
  "type": "Feature",
  "properties": {
    "gn:admin1_code":"25.0",
    "gn:asciiname":"Pengjiahecun",
    "gn:country_code":"CN",
    "gn:dem":31,
    "gn:feature_class":"P",
    "gn:feature_code":"PPL",
    "gn:name":"Pengjiahecun",
    "gn:population":0,
    "gn:timezone":"Asia/Shanghai",
    "iso:country":"CN",
    "name:zho_x_preferred":[
        "\u5f6d\u5bb6\u6cb3\u6751"
    ],
    "wof:name":"Pengjiahecun",
    "wof:placetype":"locality"
},
  "geometry": {"coordinates":[119.36709,35.46089],"type":"Point"}
}