{
  "type": "Feature",
  "properties": {
    "gn:admin1_code":"3.0",
    "gn:asciiname":"Gaoxiwan Sujia",
    "gn:country_code":"CN",
    "gn:dem":66,
    "gn:feature_class":"P",
    "gn:feature_code":"PPL",
    "gn:name":"Gaoxiwan Sujia",
    "gn:population":0,
    "gn:timezone":"Asia/Shanghai",
    "iso:country":"CN",
    "name:zho_x_preferred":[
        "\u9ad8\u6eaa\u6e7e\u82cf\u5bb6"
    ],
    "wof:name":"Gaoxiwan Sujia",
    "wof:placetype":"locality"
},
  "geometry": {"coordinates":[117.21299999999999,28.1156],"type":"Point"}
}