{
  "type": "Feature",
  "properties": {
    "gn:admin1_code":"18.0",
    "gn:asciiname":"Laozhaichang",
    "gn:country_code":"CN",
    "gn:dem":1169,
    "gn:feature_class":"P",
    "gn:feature_code":"PPL",
    "gn:name":"Laozhaichang",
    "gn:population":0,
    "gn:timezone":"Asia/Shanghai",
    "iso:country":"CN",
    "name:und_x_variant":[
        "Lao-chai-ch\u2019ang",
        "Laozhaichang"
    ],
    "name:zho_x_preferred":[
        "\u8001\u5be8\u573a"
    ],
    "wof:name":"Laozhaichang",
    "wof:placetype":"locality"
},
  "geometry": {"coordinates":[108.143,27.2402],"type":"Point"}
}