{
  "type": "Feature",
  "properties": {
    "gn:admin1_code":"14.0",
    "gn:asciiname":"Ganggenmeng",
    "gn:country_code":"CN",
    "gn:dem":4085,
    "gn:feature_class":"P",
    "gn:feature_code":"PPL",
    "gn:name":"Ganggenmeng",
    "gn:population":0,
    "gn:timezone":"Asia/Urumqi",
    "iso:country":"CN",
    "name:zho_x_preferred":[
        "\u5c97\u6839\u5b5f"
    ],
    "wof:name":"Ganggenmeng",
    "wof:placetype":"locality"
},
  "geometry": {"coordinates":[91.78988,29.92592],"type":"Point"}
}