{
  "type": "Feature",
  "properties": {
    "gn:admin1_code":"24.0",
    "gn:asciiname":"Nanzuishang",
    "gn:country_code":"CN",
    "gn:dem":653,
    "gn:feature_class":"P",
    "gn:feature_code":"PPL",
    "gn:name":"Nanzuishang",
    "gn:population":0,
    "gn:timezone":"Asia/Shanghai",
    "iso:country":"CN",
    "name:zho_x_preferred":[
        "\u5357\u5480\u4e0a"
    ],
    "wof:name":"Nanzuishang",
    "wof:placetype":"locality"
},
  "geometry": {"coordinates":[110.37675,37.014],"type":"Point"}
}