{
  "type": "Feature",
  "properties": {
    "gn:admin1_code":"15.0",
    "gn:asciiname":"Yanwotai",
    "gn:country_code":"CN",
    "gn:dem":1884,
    "gn:feature_class":"P",
    "gn:feature_code":"PPL",
    "gn:name":"Yanwotai",
    "gn:population":0,
    "gn:timezone":"Asia/Shanghai",
    "iso:country":"CN",
    "name:und_x_variant":[
        "\u71d5\u7a9d\u53f0"
    ],
    "wof:name":"Yanwotai",
    "wof:placetype":"locality"
},
  "geometry": {"coordinates":[106.55873,36.51162],"type":"Point"}
}