{
  "type": "Feature",
  "properties": {
    "gn:admin1_code":"9.0",
    "gn:asciiname":"Qiangou",
    "gn:country_code":"CN",
    "gn:dem":83,
    "gn:feature_class":"P",
    "gn:feature_code":"PPL",
    "gn:name":"Qiangou",
    "gn:population":0,
    "gn:timezone":"Asia/Shanghai",
    "iso:country":"CN",
    "name:zho_x_preferred":[
        "\u94b1\u6c9f"
    ],
    "wof:name":"Qiangou",
    "wof:placetype":"locality"
},
  "geometry": {"coordinates":[114.05464000000001,32.74394],"type":"Point"}
}