{
  "type": "Feature",
  "properties": {
    "gn:admin1_code":"29.0",
    "gn:asciiname":"Qiaogoutou",
    "gn:country_code":"CN",
    "gn:dem":982,
    "gn:feature_class":"P",
    "gn:feature_code":"PPL",
    "gn:name":"Qiaogoutou",
    "gn:population":0,
    "gn:timezone":"Asia/Shanghai",
    "iso:country":"CN",
    "name:und_x_variant":[
        "\u6865\u6c9f\u5934"
    ],
    "wof:name":"Qiaogoutou",
    "wof:placetype":"locality"
},
  "geometry": {"coordinates":[104.06896999999999,28.58566],"type":"Point"}
}