{
  "type": "Feature",
  "properties": {
    "gn:admin1_code":"26.0",
    "gn:asciiname":"Zhengjiawan",
    "gn:country_code":"CN",
    "gn:dem":535,
    "gn:feature_class":"P",
    "gn:feature_code":"PPL",
    "gn:name":"Zhengjiawan",
    "gn:population":0,
    "gn:timezone":"Asia/Shanghai",
    "iso:country":"CN",
    "name:zho_x_preferred":[
        "\u90d1\u5bb6\u6e7e"
    ],
    "wof:name":"Zhengjiawan",
    "wof:placetype":"locality"
},
  "geometry": {"coordinates":[109.24236000000001,32.74288],"type":"Point"}
}