{
  "type": "Feature",
  "properties": {
    "gn:admin1_code":"1.0",
    "gn:asciiname":"Zhilizhuang",
    "gn:country_code":"CN",
    "gn:dem":15,
    "gn:feature_class":"P",
    "gn:feature_code":"PPL",
    "gn:name":"Zhilizhuang",
    "gn:population":0,
    "gn:timezone":"Asia/Shanghai",
    "iso:country":"CN",
    "name:zho_x_preferred":[
        "\u690d\u674e\u5e84"
    ],
    "wof:name":"Zhilizhuang",
    "wof:placetype":"locality"
},
  "geometry": {"coordinates":[119.00033999999999,32.95155],"type":"Point"}
}