{
  "type": "Feature",
  "properties": {
    "gn:admin1_code":"11.0",
    "gn:asciiname":"Lijiatai",
    "gn:country_code":"CN",
    "gn:dem":181,
    "gn:feature_class":"P",
    "gn:feature_code":"PPL",
    "gn:name":"Lijiatai",
    "gn:population":0,
    "gn:timezone":"Asia/Shanghai",
    "iso:country":"CN",
    "name:zho_x_preferred":[
        "Lijiatai"
    ],
    "name:zho_x_variant":[
        "\u674e\u5bb6\u53f0"
    ],
    "wof:name":"Lijiatai",
    "wof:placetype":"locality"
},
  "geometry": {"coordinates":[111.23515999999999,29.59514],"type":"Point"}
}