{
  "type": "Feature",
  "properties": {
    "gn:admin1_code":"32.0",
    "gn:asciiname":"Tundu",
    "gn:country_code":"CN",
    "gn:dem":2695,
    "gn:feature_class":"P",
    "gn:feature_code":"PPL",
    "gn:name":"Tundu",
    "gn:population":0,
    "gn:timezone":"Asia/Shanghai",
    "iso:country":"CN",
    "name:est_x_preferred":[
        "Tundu"
    ],
    "name:hye_x_preferred":[
        "\u054f\u0578\u0582\u0576\u0564\u0578\u0582"
    ],
    "name:pol_x_preferred":[
        "Tundu"
    ],
    "name:spa_x_preferred":[
        "Tundu"
    ],
    "name:ukr_x_preferred":[
        "\u0422\u0443\u043d\u0434\u0443"
    ],
    "name:vol_x_preferred":[
        "Tundu"
    ],
    "name:zho_x_preferred":[
        "\u541e\u90fd"
    ],
    "wof:name":"Tundu",
    "wof:placetype":"locality"
},
  "geometry": {"coordinates":[101.422,31.7527],"type":"Point"}
}