{
  "type": "Feature",
  "properties": {
    "gn:admin1_code":"2.0",
    "gn:asciiname":"Dibanwu",
    "gn:country_code":"CN",
    "gn:dem":45,
    "gn:feature_class":"P",
    "gn:feature_code":"PPL",
    "gn:name":"Dibanwu",
    "gn:population":0,
    "gn:timezone":"Asia/Shanghai",
    "iso:country":"CN",
    "name:und_x_variant":[
        "\u5730\u677f\u575e"
    ],
    "wof:name":"Dibanwu",
    "wof:placetype":"locality"
},
  "geometry": {"coordinates":[119.86699,30.54098],"type":"Point"}
}