{
  "type": "Feature",
  "properties": {
    "gn:admin1_code":"12.0",
    "gn:asciiname":"Zhoubajia",
    "gn:country_code":"CN",
    "gn:dem":89,
    "gn:feature_class":"P",
    "gn:feature_code":"PPL",
    "gn:name":"Zhoubajia",
    "gn:population":0,
    "gn:timezone":"Asia/Shanghai",
    "iso:country":"CN",
    "name:zho_x_preferred":[
        "\u5468\u516b\u5bb6"
    ],
    "wof:name":"Zhoubajia",
    "wof:placetype":"locality"
},
  "geometry": {"coordinates":[114.67943,31.53931],"type":"Point"}
}