{
  "type": "Feature",
  "properties": {
    "gn:admin1_code":"15.0",
    "gn:asciiname":"Shijiazui",
    "gn:country_code":"CN",
    "gn:dem":1996,
    "gn:feature_class":"P",
    "gn:feature_code":"PPL",
    "gn:name":"Shijiazui",
    "gn:population":0,
    "gn:timezone":"Asia/Shanghai",
    "iso:country":"CN",
    "name:zho_x_preferred":[
        "\u53f2\u5bb6\u5634"
    ],
    "wof:name":"Shijiazui",
    "wof:placetype":"locality"
},
  "geometry": {"coordinates":[104.53100000000001,35.8436],"type":"Point"}
}