{
  "type": "Feature",
  "properties": {
    "gn:admin1_code":"8.0",
    "gn:asciiname":"Daohe Xiaotun",
    "gn:country_code":"CN",
    "gn:dem":619,
    "gn:feature_class":"P",
    "gn:feature_code":"PPL",
    "gn:name":"Daohe Xiaotun",
    "gn:population":0,
    "gn:timezone":"Asia/Shanghai",
    "iso:country":"CN",
    "name:und_x_variant":[
        "\u9053\u6cb3\u5c0f\u5c6f"
    ],
    "wof:name":"Daohe Xiaotun",
    "wof:placetype":"locality"
},
  "geometry": {"coordinates":[130.59792999999999,43.97491],"type":"Point"}
}