{
  "type": "Feature",
  "properties": {
    "gn:admin1_code":"04",
    "gn:asciiname":"Changhetan",
    "gn:cc2":"CN",
    "gn:country_code":"CN",
    "gn:dem":5,
    "gn:feature_class":"P",
    "gn:feature_code":"PPL",
    "gn:name":"Changhetan",
    "gn:population":0,
    "gn:timezone":"Asia/Shanghai",
    "iso:country":"CN",
    "name:und_x_variant":[
        "Chang-hsien-sheng-ch\u2019iao",
        "Ch\u2019ang-ho-t\u2019an",
        "Changhetan"
    ],
    "wof:name":"Changhetan",
    "wof:placetype":"locality"
},
  "geometry": {"coordinates":[120.88500000000001,32.20083],"type":"Point"}
}