{
  "type": "Feature",
  "properties": {
    "gn:admin1_code":"30",
    "gn:asciiname":"Waipo",
    "gn:country_code":"CN",
    "gn:dem":39,
    "gn:feature_class":"P",
    "gn:feature_code":"PPL",
    "gn:name":"Waipo",
    "gn:population":0,
    "gn:timezone":"Asia/Urumqi",
    "iso:country":"CN",
    "name:zho_x_preferred":[
        "\u5916\u5761"
    ],
    "wof:name":"Waipo",
    "wof:placetype":"locality"
},
  "geometry": {"coordinates":[110.61320000000001,21.81331],"type":"Point"}
}