{
  "type": "Feature",
  "properties": {
    "gn:admin1_code":"30.0",
    "gn:asciiname":"Jiepo",
    "gn:country_code":"CN",
    "gn:dem":90,
    "gn:feature_class":"P",
    "gn:feature_code":"PPL",
    "gn:name":"Jiepo",
    "gn:population":0,
    "gn:timezone":"Asia/Urumqi",
    "iso:country":"CN",
    "name:zho_x_preferred":[
        "\u7ed3\u5761"
    ],
    "wof:name":"Jiepo",
    "wof:placetype":"locality"
},
  "geometry": {"coordinates":[110.82398999999999,22.30313],"type":"Point"}
}