{
  "type": "Feature",
  "properties": {
    "gn:admin1_code":"29.0",
    "gn:asciiname":"Batangzhai",
    "gn:country_code":"CN",
    "gn:dem":1467,
    "gn:feature_class":"P",
    "gn:feature_code":"PPL",
    "gn:name":"Batangzhai",
    "gn:population":0,
    "gn:timezone":"Asia/Shanghai",
    "iso:country":"CN",
    "name:zho_x_preferred":[
        "\u575d\u5858\u5be8"
    ],
    "wof:name":"Batangzhai",
    "wof:placetype":"locality"
},
  "geometry": {"coordinates":[100.602,22.8392],"type":"Point"}
}