{
  "type": "Feature",
  "properties": {
    "gn:admin1_code":"4.0",
    "gn:asciiname":"Haifengcun",
    "gn:country_code":"CN",
    "gn:dem":0,
    "gn:feature_class":"P",
    "gn:feature_code":"PPL",
    "gn:name":"Haifengcun",
    "gn:population":0,
    "gn:timezone":"Asia/Shanghai",
    "iso:country":"CN",
    "name:zho_x_preferred":[
        "\u6d77\u4e30\u6751"
    ],
    "wof:name":"Haifengcun",
    "wof:placetype":"locality"
},
  "geometry": {"coordinates":[119.71509,33.93347],"type":"Point"}
}