{
  "type": "Feature",
  "properties": {
    "gn:admin1_code":"15.0",
    "gn:asciiname":"Xikuhu Luchang",
    "gn:country_code":"CN",
    "gn:dem":3476,
    "gn:feature_class":"P",
    "gn:feature_code":"PPLF",
    "gn:name":"Xikuhu Luchang",
    "gn:population":0,
    "gn:timezone":"Asia/Shanghai",
    "iso:country":"CN",
    "name:zho_x_preferred":[
        "\u897f\u5e93\u4e4e\u9e7f\u573a"
    ],
    "wof:name":"Xikuhu Luchang",
    "wof:placetype":"locality"
},
  "geometry": {"coordinates":[101.137,34.2626],"type":"Point"}
}