{
  "type": "Feature",
  "properties": {
    "gn:admin1_code":"14.0",
    "gn:asciiname":"Songxicun",
    "gn:country_code":"CN",
    "gn:dem":5217,
    "gn:feature_class":"P",
    "gn:feature_code":"PPL",
    "gn:name":"Songxicun",
    "gn:population":0,
    "gn:timezone":"Asia/Shanghai",
    "iso:country":"CN",
    "name:zho_x_preferred":[
        "\u677e\u897f\u6751"
    ],
    "wof:name":"Songxicun",
    "wof:placetype":"locality"
},
  "geometry": {"coordinates":[80.3827,34.4135],"type":"Point"}
}