{
  "type": "Feature",
  "properties": {
    "gn:admin1_code":"29",
    "gn:asciiname":"Xinachong",
    "gn:country_code":"CN",
    "gn:dem":2118,
    "gn:feature_class":"P",
    "gn:feature_code":"PPL",
    "gn:name":"Xinachong",
    "gn:population":0,
    "gn:timezone":"Asia/Shanghai",
    "iso:country":"CN",
    "name:zho_x_preferred":[
        "\u897f\u90a3\u51b2"
    ],
    "wof:name":"Xinachong",
    "wof:placetype":"locality"
},
  "geometry": {"coordinates":[103.017,24.4084],"type":"Point"}
}