{
  "type": "Feature",
  "properties": {
    "gn:admin1_code":"11.0",
    "gn:asciiname":"Daojiachong",
    "gn:country_code":"CN",
    "gn:dem":173,
    "gn:feature_class":"P",
    "gn:feature_code":"PPL",
    "gn:name":"Daojiachong",
    "gn:population":0,
    "gn:timezone":"Asia/Shanghai",
    "iso:country":"CN",
    "name:zho_x_preferred":[
        "\u9053\u5bb6\u51b2"
    ],
    "wof:name":"Daojiachong",
    "wof:placetype":"locality"
},
  "geometry": {"coordinates":[112.13426,27.1982],"type":"Point"}
}