{
  "type": "Feature",
  "properties": {
    "gn:admin1_code":"11.0",
    "gn:asciiname":"Luojiaping",
    "gn:country_code":"CN",
    "gn:dem":118,
    "gn:feature_class":"P",
    "gn:feature_code":"PPL",
    "gn:name":"Luojiaping",
    "gn:population":0,
    "gn:timezone":"Asia/Shanghai",
    "iso:country":"CN",
    "name:zho_x_preferred":[
        "Luojiaping"
    ],
    "name:zho_x_variant":[
        "\u6d1b\u5bb6\u576a"
    ],
    "wof:name":"Luojiaping",
    "wof:placetype":"locality"
},
  "geometry": {"coordinates":[111.11868,28.96671],"type":"Point"}
}