{
  "type": "Feature",
  "properties": {
    "gn:admin1_code":"12.0",
    "gn:asciiname":"Laoyatan",
    "gn:country_code":"CN",
    "gn:dem":115,
    "gn:feature_class":"P",
    "gn:feature_code":"PPL",
    "gn:name":"Laoyatan",
    "gn:population":0,
    "gn:timezone":"Asia/Shanghai",
    "iso:country":"CN",
    "name:zho_x_preferred":[
        "Laoyatan"
    ],
    "name:zho_x_variant":[
        "\u8001\u9e26\u6f6d"
    ],
    "wof:name":"Laoyatan",
    "wof:placetype":"locality"
},
  "geometry": {"coordinates":[114.91773999999999,29.50496],"type":"Point"}
}