{
  "type": "Feature",
  "properties": {
    "gn:admin1_code":"15.0",
    "gn:asciiname":"Zhangbu",
    "gn:country_code":"CN",
    "gn:dem":1701,
    "gn:feature_class":"P",
    "gn:feature_code":"PPL",
    "gn:name":"Zhangbu",
    "gn:population":0,
    "gn:timezone":"Asia/Shanghai",
    "iso:country":"CN",
    "name:und_x_variant":[
        "\u5f20\u5821"
    ],
    "wof:name":"Zhangbu",
    "wof:placetype":"locality"
},
  "geometry": {"coordinates":[105.67655000000001,35.58573],"type":"Point"}
}