{
  "type": "Feature",
  "properties": {
    "gn:admin1_code":"9.0",
    "gn:asciiname":"Meiliangtai",
    "gn:country_code":"CN",
    "gn:dem":967,
    "gn:feature_class":"P",
    "gn:feature_code":"PPL",
    "gn:name":"Meiliangtai",
    "gn:population":0,
    "gn:timezone":"Asia/Shanghai",
    "iso:country":"CN",
    "name:zho_x_preferred":[
        "\u6ca1\u6881\u53f0"
    ],
    "wof:name":"Meiliangtai",
    "wof:placetype":"locality"
},
  "geometry": {"coordinates":[112.52891,34.01473],"type":"Point"}
}