{
  "type": "Feature",
  "properties": {
    "gn:admin1_code":"11.0",
    "gn:asciiname":"Huochang",
    "gn:country_code":"CN",
    "gn:dem":206,
    "gn:feature_class":"P",
    "gn:feature_code":"PPL",
    "gn:name":"Huochang",
    "gn:population":0,
    "gn:timezone":"Asia/Shanghai",
    "iso:country":"CN",
    "name:zho_x_preferred":[
        "Huochang"
    ],
    "name:zho_x_variant":[
        "\u706b\u5382"
    ],
    "wof:name":"Huochang",
    "wof:placetype":"locality"
},
  "geometry": {"coordinates":[114.00843999999999,28.22265],"type":"Point"}
}