{
  "type": "Feature",
  "properties": {
    "gn:admin1_code":"18",
    "gn:asciiname":"Daqingkou",
    "gn:country_code":"CN",
    "gn:dem":1472,
    "gn:feature_class":"P",
    "gn:feature_code":"PPL",
    "gn:name":"Daqingkou",
    "gn:population":0,
    "gn:timezone":"Asia/Shanghai",
    "iso:country":"CN",
    "name:zho_x_preferred":[
        "\u5927\u7b90\u53e3"
    ],
    "wof:name":"Daqingkou",
    "wof:placetype":"locality"
},
  "geometry": {"coordinates":[104.833,25.1166],"type":"Point"}
}