{
  "type": "Feature",
  "properties": {
    "gn:admin1_code":"4.0",
    "gn:asciiname":"Sima",
    "gn:country_code":"CN",
    "gn:dem":9,
    "gn:feature_class":"P",
    "gn:feature_code":"PPL",
    "gn:name":"Sima",
    "gn:population":0,
    "gn:timezone":"Asia/Shanghai",
    "iso:country":"CN",
    "name:und_x_variant":[
        "Hsi-ma",
        "Sima",
        "Hsi-ma-chen",
        "Xima"
    ],
    "name:zho_x_preferred":[
        "\u5636\u9a6c"
    ],
    "wof:name":"Sima",
    "wof:placetype":"locality"
},
  "geometry": {"coordinates":[119.77386,32.33898],"type":"Point"}
}