{
  "type": "Feature",
  "properties": {
    "gn:admin1_code":"26.0",
    "gn:asciiname":"Gaoyacun",
    "gn:country_code":"CN",
    "gn:dem":629,
    "gn:feature_class":"P",
    "gn:feature_code":"PPL",
    "gn:name":"Gaoyacun",
    "gn:population":0,
    "gn:timezone":"Asia/Shanghai",
    "iso:country":"CN",
    "name:zho_x_preferred":[
        "\u9ad8\u57ad\u6751"
    ],
    "wof:name":"Gaoyacun",
    "wof:placetype":"locality"
},
  "geometry": {"coordinates":[109.25274,32.78678],"type":"Point"}
}