{
  "type": "Feature",
  "properties": {
    "gn:admin1_code":"25",
    "gn:asciiname":"Bunantou",
    "gn:country_code":"CN",
    "gn:dem":113,
    "gn:feature_class":"P",
    "gn:feature_code":"PPL",
    "gn:name":"Bunantou",
    "gn:population":0,
    "gn:timezone":"Asia/Shanghai",
    "iso:country":"CN",
    "name:zho_x_preferred":[
        "\u57e0\u5357\u5934"
    ],
    "wof:name":"Bunantou",
    "wof:placetype":"locality"
},
  "geometry": {"coordinates":[118.91500000000001,36.3889],"type":"Point"}
}