{
  "type": "Feature",
  "properties": {
    "gn:admin1_code":"16.0",
    "gn:asciiname":"Baihuai",
    "gn:country_code":"CN",
    "gn:dem":299,
    "gn:feature_class":"P",
    "gn:feature_code":"PPL",
    "gn:name":"Baihuai",
    "gn:population":0,
    "gn:timezone":"Asia/Shanghai",
    "iso:country":"CN",
    "name:zho_x_preferred":[
        "\u767d\u6000"
    ],
    "wof:name":"Baihuai",
    "wof:placetype":"locality"
},
  "geometry": {"coordinates":[108.357,24.8261],"type":"Point"}
}