{
  "type": "Feature",
  "properties": {
    "gn:admin1_code":"1.0",
    "gn:asciiname":"Qingtiancun",
    "gn:country_code":"CN",
    "gn:dem":37,
    "gn:feature_class":"P",
    "gn:feature_code":"PPL",
    "gn:name":"Qingtiancun",
    "gn:population":0,
    "gn:timezone":"Asia/Shanghai",
    "iso:country":"CN",
    "name:zho_x_preferred":[
        "\u9752\u7530\u6751"
    ],
    "wof:name":"Qingtiancun",
    "wof:placetype":"locality"
},
  "geometry": {"coordinates":[116.71057999999999,30.84125],"type":"Point"}
}