{
  "type": "Feature",
  "properties": {
    "gn:admin1_code":"29.0",
    "gn:asciiname":"Neluo",
    "gn:country_code":"CN",
    "gn:dem":1836,
    "gn:feature_class":"P",
    "gn:feature_code":"PPL",
    "gn:name":"Neluo",
    "gn:population":0,
    "gn:timezone":"Asia/Shanghai",
    "iso:country":"CN",
    "name:zho_x_preferred":[
        "\u5462\u843d"
    ],
    "wof:name":"Neluo",
    "wof:placetype":"locality"
},
  "geometry": {"coordinates":[100.43000000000001,27.7399],"type":"Point"}
}