{
  "type": "Feature",
  "properties": {
    "gn:admin1_code":"29.0",
    "gn:asciiname":"Leye",
    "gn:country_code":"CN",
    "gn:dem":1955,
    "gn:feature_class":"P",
    "gn:feature_code":"PPL",
    "gn:name":"Leye",
    "gn:population":0,
    "gn:timezone":"Asia/Shanghai",
    "iso:country":"CN",
    "name:ceb_x_preferred":[
        "Leye"
    ],
    "name:deu_x_preferred":[
        "Leye"
    ],
    "name:swe_x_preferred":[
        "Leye"
    ],
    "name:und_x_variant":[
        "\u4e50\u4e1a"
    ],
    "wof:name":"Leye",
    "wof:placetype":"locality"
},
  "geometry": {"coordinates":[102.53964000000001,25.72826],"type":"Point"}
}