{
  "type": "Feature",
  "properties": {
    "gn:admin1_code":"15.0",
    "gn:asciiname":"Shangzhaojia",
    "gn:country_code":"CN",
    "gn:dem":1543,
    "gn:feature_class":"P",
    "gn:feature_code":"PPL",
    "gn:name":"Shangzhaojia",
    "gn:population":0,
    "gn:timezone":"Asia/Shanghai",
    "iso:country":"CN",
    "name:zho_x_preferred":[
        "\u4e0a\u8d75\u5bb6"
    ],
    "wof:name":"Shangzhaojia",
    "wof:placetype":"locality"
},
  "geometry": {"coordinates":[106.193,34.8239],"type":"Point"}
}