{
  "type": "Feature",
  "properties": {
    "gn:admin1_code":"12.0",
    "gn:asciiname":"Dingjiazuishang",
    "gn:country_code":"CN",
    "gn:dem":28,
    "gn:feature_class":"P",
    "gn:feature_code":"PPL",
    "gn:name":"Dingjiazuishang",
    "gn:population":0,
    "gn:timezone":"Asia/Shanghai",
    "iso:country":"CN",
    "name:zho_x_preferred":[
        "\u4e01\u5bb6\u5480\u4e0a"
    ],
    "wof:name":"Dingjiazuishang",
    "wof:placetype":"locality"
},
  "geometry": {"coordinates":[113.05453,29.81419],"type":"Point"}
}