{
  "type": "Feature",
  "properties": {
    "gn:admin1_code":"29.0",
    "gn:asciiname":"Dongjiao Xiazhai",
    "gn:country_code":"CN",
    "gn:dem":1384,
    "gn:feature_class":"P",
    "gn:feature_code":"PPL",
    "gn:name":"Dongjiao Xiazhai",
    "gn:population":0,
    "gn:timezone":"Asia/Shanghai",
    "iso:country":"CN",
    "name:zho_x_preferred":[
        "\u4e1c\u89d2\u4e0b\u5be8"
    ],
    "wof:name":"Dongjiao Xiazhai",
    "wof:placetype":"locality"
},
  "geometry": {"coordinates":[102.59,22.8379],"type":"Point"}
}