{
  "type": "Feature",
  "properties": {
    "gn:admin1_code":"32.0",
    "gn:asciiname":"Maoniuping",
    "gn:country_code":"CN",
    "gn:dem":3015,
    "gn:feature_class":"P",
    "gn:feature_code":"PPL",
    "gn:name":"Maoniuping",
    "gn:population":0,
    "gn:timezone":"Asia/Shanghai",
    "iso:country":"CN",
    "name:zho_x_preferred":[
        "\u7266\u725b\u576a"
    ],
    "wof:name":"Maoniuping",
    "wof:placetype":"locality"
},
  "geometry": {"coordinates":[100.93966,27.89293],"type":"Point"}
}