{
  "type": "Feature",
  "properties": {
    "gn:admin1_code":"15.0",
    "gn:asciiname":"Shuangshu",
    "gn:country_code":"CN",
    "gn:dem":1638,
    "gn:feature_class":"P",
    "gn:feature_code":"PPL",
    "gn:name":"Shuangshu",
    "gn:population":0,
    "gn:timezone":"Asia/Shanghai",
    "iso:country":"CN",
    "name:zho_x_preferred":[
        "\u53cc\u6811"
    ],
    "wof:name":"Shuangshu",
    "wof:placetype":"locality"
},
  "geometry": {"coordinates":[103.974,37.5235],"type":"Point"}
}