{
  "type": "Feature",
  "properties": {
    "gn:admin1_code":"21.0",
    "gn:asciiname":"Jingjiqiao",
    "gn:country_code":"CN",
    "gn:dem":1108,
    "gn:feature_class":"P",
    "gn:feature_code":"PPL",
    "gn:name":"Jingjiqiao",
    "gn:population":0,
    "gn:timezone":"Asia/Shanghai",
    "iso:country":"CN",
    "name:zho_x_preferred":[
        "\u7ecf\u6d4e\u6865"
    ],
    "wof:name":"Jingjiqiao",
    "wof:placetype":"locality"
},
  "geometry": {"coordinates":[106.31699999999999,38.5758],"type":"Point"}
}