{
  "type": "Feature",
  "properties": {
    "gn:admin1_code":"33.0",
    "gn:asciiname":"Gaodongzi",
    "gn:country_code":"CN",
    "gn:dem":840,
    "gn:feature_class":"P",
    "gn:feature_code":"PPL",
    "gn:name":"Gaodongzi",
    "gn:population":0,
    "gn:timezone":"Asia/Shanghai",
    "iso:country":"CN",
    "name:zho_x_preferred":[
        "\u9ad8\u6d1e\u5b50"
    ],
    "wof:name":"Gaodongzi",
    "wof:placetype":"locality"
},
  "geometry": {"coordinates":[108.58896,29.2694],"type":"Point"}
}