{
  "type": "Feature",
  "properties": {
    "gn:admin1_code":"7.0",
    "gn:asciiname":"Dingkeng",
    "gn:country_code":"CN",
    "gn:dem":120,
    "gn:feature_class":"P",
    "gn:feature_code":"PPL",
    "gn:name":"Dingkeng",
    "gn:population":0,
    "gn:timezone":"Asia/Shanghai",
    "iso:country":"CN",
    "name:zho_x_preferred":[
        "\u9876\u5751"
    ],
    "wof:name":"Dingkeng",
    "wof:placetype":"locality"
},
  "geometry": {"coordinates":[118.88722,25.50252],"type":"Point"}
}