{
  "type": "Feature",
  "properties": {
    "gn:admin1_code":"24.0",
    "gn:asciiname":"Donggou",
    "gn:country_code":"CN",
    "gn:dem":1456,
    "gn:feature_class":"P",
    "gn:feature_code":"PPL",
    "gn:name":"Donggou",
    "gn:population":0,
    "gn:timezone":"Asia/Shanghai",
    "iso:country":"CN",
    "name:zho_x_preferred":[
        "\u4e1c\u6c9f"
    ],
    "wof:name":"Donggou",
    "wof:placetype":"locality"
},
  "geometry": {"coordinates":[111.33872,38.56408],"type":"Point"}
}