{
  "type": "Feature",
  "properties": {
    "gn:admin1_code":"10",
    "gn:asciiname":"Yuzhuang",
    "gn:country_code":"CN",
    "gn:dem":38,
    "gn:feature_class":"P",
    "gn:feature_code":"PPL",
    "gn:name":"Yuzhuang",
    "gn:population":0,
    "gn:timezone":"Asia/Shanghai",
    "iso:country":"CN",
    "name:zho_x_preferred":[
        "\u96e8\u5e84"
    ],
    "wof:name":"Yuzhuang",
    "wof:placetype":"locality"
},
  "geometry": {"coordinates":[115.13443999999998,36.76635],"type":"Point"}
}