{
  "type": "Feature",
  "properties": {
    "gn:admin1_code":"10",
    "gn:asciiname":"Guandongying",
    "gn:country_code":"CN",
    "gn:dem":404,
    "gn:feature_class":"P",
    "gn:feature_code":"PPL",
    "gn:name":"Guandongying",
    "gn:population":0,
    "gn:timezone":"Asia/Shanghai",
    "iso:country":"CN",
    "name:zho_x_preferred":[
        "\u5173\u4e1c\u8425"
    ],
    "wof:name":"Guandongying",
    "wof:placetype":"locality"
},
  "geometry": {"coordinates":[118.14078000000001,40.85395],"type":"Point"}
}