{
  "type": "Feature",
  "properties": {
    "gn:admin1_code":"1.0",
    "gn:asciiname":"Huomiaocun",
    "gn:country_code":"CN",
    "gn:dem":31,
    "gn:feature_class":"P",
    "gn:feature_code":"PPL",
    "gn:name":"Huomiaocun",
    "gn:population":0,
    "gn:timezone":"Asia/Shanghai",
    "iso:country":"CN",
    "name:und_x_variant":[
        "Huoshenmiao"
    ],
    "name:zho_x_preferred":[
        "\u706b\u5e99\u6751"
    ],
    "wof:name":"Huomiaocun",
    "wof:placetype":"locality"
},
  "geometry": {"coordinates":[117.52399,34.04474],"type":"Point"}
}