{
  "type": "Feature",
  "properties": {
    "gn:admin1_code":"02",
    "gn:asciiname":"Sitangnan",
    "gn:country_code":"CN",
    "gn:dem":6,
    "gn:feature_class":"P",
    "gn:feature_code":"PPL",
    "gn:name":"Sitangnan",
    "gn:population":0,
    "gn:timezone":"Asia/Shanghai",
    "iso:country":"CN",
    "name:und_x_variant":[
        "\u56db\u5858\u5357",
        "Erzaositangnan"
    ],
    "wof:name":"Sitangnan",
    "wof:placetype":"locality"
},
  "geometry": {"coordinates":[121.27384000000001,30.25264],"type":"Point"}
}