{
  "type": "Feature",
  "properties": {
    "gn:admin1_code":"29.0",
    "gn:asciiname":"Nabujiaoluo",
    "gn:country_code":"CN",
    "gn:dem":2539,
    "gn:feature_class":"P",
    "gn:feature_code":"PPL",
    "gn:name":"Nabujiaoluo",
    "gn:population":0,
    "gn:timezone":"Asia/Shanghai",
    "iso:country":"CN",
    "name:zho_x_preferred":[
        "\u7eb3\u6b65\u811a\u843d"
    ],
    "wof:name":"Nabujiaoluo",
    "wof:placetype":"locality"
},
  "geometry": {"coordinates":[100.44499999999999,27.6965],"type":"Point"}
}