{
  "type": "Feature",
  "properties": {
    "gn:admin1_code":"3.0",
    "gn:asciiname":"Keguan",
    "gn:country_code":"CN",
    "gn:dem":30,
    "gn:feature_class":"P",
    "gn:feature_code":"PPL",
    "gn:name":"Keguan",
    "gn:population":0,
    "gn:timezone":"Asia/Shanghai",
    "iso:country":"CN",
    "name:und_x_variant":[
        "\u67ef\u89c2"
    ],
    "wof:name":"Keguan",
    "wof:placetype":"locality"
},
  "geometry": {"coordinates":[116.31075,29.68912000000001],"type":"Point"}
}