{
  "type": "Feature",
  "properties": {
    "gn:admin1_code":"5.0",
    "gn:asciiname":"Huashudi",
    "gn:country_code":"CN",
    "gn:dem":482,
    "gn:feature_class":"P",
    "gn:feature_code":"PPL",
    "gn:name":"Huashudi",
    "gn:population":0,
    "gn:timezone":"Asia/Shanghai",
    "iso:country":"CN",
    "name:zho_x_preferred":[
        "\u6866\u6811\u5e95"
    ],
    "wof:name":"Huashudi",
    "wof:placetype":"locality"
},
  "geometry": {"coordinates":[125.20728,42.46731],"type":"Point"}
}