{
  "type": "Feature",
  "properties": {
    "gn:admin1_code":"7.0",
    "gn:asciiname":"Liangang",
    "gn:country_code":"CN",
    "gn:dem":413,
    "gn:feature_class":"P",
    "gn:feature_code":"PPL",
    "gn:name":"Liangang",
    "gn:population":0,
    "gn:timezone":"Asia/Shanghai",
    "iso:country":"CN",
    "name:und_x_variant":[
        "\u8fde\u5c97"
    ],
    "name:zho_x_preferred":[
        "\u8fde\u5c97"
    ],
    "wof:name":"Liangang",
    "wof:placetype":"locality"
},
  "geometry": {"coordinates":[116.73353,25.991],"type":"Point"}
}