{
  "type": "Feature",
  "properties": {
    "gn:admin1_code":"16.0",
    "gn:asciiname":"Dilu",
    "gn:country_code":"CN",
    "gn:dem":26,
    "gn:feature_class":"P",
    "gn:feature_code":"PPL",
    "gn:name":"Dilu",
    "gn:population":0,
    "gn:timezone":"Asia/Shanghai",
    "iso:country":"CN",
    "name:zho_x_preferred":[
        "\u4f4e\u8def"
    ],
    "wof:name":"Dilu",
    "wof:placetype":"locality"
},
  "geometry": {"coordinates":[109.444,21.5178],"type":"Point"}
}