{
  "type": "Feature",
  "properties": {
    "gn:admin1_code":"30.0",
    "gn:asciiname":"Lidongcun",
    "gn:country_code":"CN",
    "gn:dem":156,
    "gn:feature_class":"P",
    "gn:feature_code":"PPL",
    "gn:name":"Lidongcun",
    "gn:population":0,
    "gn:timezone":"Asia/Shanghai",
    "iso:country":"CN",
    "name:zho_x_preferred":[
        "\u4e3d\u6d1e\u6751"
    ],
    "wof:name":"Lidongcun",
    "wof:placetype":"locality"
},
  "geometry": {"coordinates":[112.32832999999999,24.10294],"type":"Point"}
}