{
  "type": "Feature",
  "properties": {
    "gn:admin1_code":"15.0",
    "gn:asciiname":"Ningchang",
    "gn:country_code":"CN",
    "gn:dem":2348,
    "gn:feature_class":"P",
    "gn:feature_code":"PPL",
    "gn:name":"Ningchang",
    "gn:population":0,
    "gn:timezone":"Asia/Shanghai",
    "iso:country":"CN",
    "name:zho_x_preferred":[
        "\u5b81\u660c"
    ],
    "wof:name":"Ningchang",
    "wof:placetype":"locality"
},
  "geometry": {"coordinates":[102.005,37.8306],"type":"Point"}
}