{
  "type": "Feature",
  "properties": {
    "gn:admin1_code":"32.0",
    "gn:asciiname":"Sha'ezu",
    "gn:country_code":"CN",
    "gn:dem":1983,
    "gn:feature_class":"P",
    "gn:feature_code":"PPL",
    "gn:name":"Sha\u2019ezu",
    "gn:population":0,
    "gn:timezone":"Asia/Shanghai",
    "iso:country":"CN",
    "name:und_x_variant":[
        "Sha\u2019ezu"
    ],
    "name:zho_x_preferred":[
        "\u6c99\u6076\u7956"
    ],
    "wof:name":"Sha'ezu",
    "wof:placetype":"locality"
},
  "geometry": {"coordinates":[102.812,28.9772],"type":"Point"}
}