{
  "type": "Feature",
  "properties": {
    "gn:admin1_code":"30",
    "gn:asciiname":"Baiyincun",
    "gn:country_code":"CN",
    "gn:dem":42,
    "gn:feature_class":"P",
    "gn:feature_code":"PPL",
    "gn:name":"Baiyincun",
    "gn:population":0,
    "gn:timezone":"Asia/Urumqi",
    "iso:country":"CN",
    "name:und_x_variant":[
        "Baiyin",
        "Baiyincun"
    ],
    "name:zho_x_preferred":[
        "\u767d\u94f6\u6751"
    ],
    "wof:name":"Baiyincun",
    "wof:placetype":"locality"
},
  "geometry": {"coordinates":[109.85523999999999,20.78934],"type":"Point"}
}