{
  "type": "Feature",
  "properties": {
    "gn:admin1_code":"1.0",
    "gn:asciiname":"Xiewacun",
    "gn:country_code":"CN",
    "gn:dem":32,
    "gn:feature_class":"P",
    "gn:feature_code":"PPL",
    "gn:name":"Xiewacun",
    "gn:population":0,
    "gn:timezone":"Asia/Shanghai",
    "iso:country":"CN",
    "name:zho_x_preferred":[
        "\u8c22\u6d3c\u6751"
    ],
    "wof:name":"Xiewacun",
    "wof:placetype":"locality"
},
  "geometry": {"coordinates":[117.19105,33.99924],"type":"Point"}
}