{
  "type": "Feature",
  "properties": {
    "gn:admin1_code":"12.0",
    "gn:asciiname":"Xiongjiapai",
    "gn:country_code":"CN",
    "gn:dem":179,
    "gn:feature_class":"P",
    "gn:feature_code":"PPL",
    "gn:name":"Xiongjiapai",
    "gn:population":0,
    "gn:timezone":"Asia/Shanghai",
    "iso:country":"CN",
    "name:zho_x_preferred":[
        "Xiongjiapai"
    ],
    "name:zho_x_variant":[
        "\u718a\u5bb6\u6392"
    ],
    "wof:name":"Xiongjiapai",
    "wof:placetype":"locality"
},
  "geometry": {"coordinates":[114.14381000000002,29.62932],"type":"Point"}
}