{
  "type": "Feature",
  "properties": {
    "gn:admin1_code":"30.0",
    "gn:asciiname":"Macaokeng",
    "gn:country_code":"CN",
    "gn:dem":59,
    "gn:feature_class":"P",
    "gn:feature_code":"PPL",
    "gn:name":"Macaokeng",
    "gn:population":0,
    "gn:timezone":"Asia/Shanghai",
    "iso:country":"CN",
    "name:zho_x_preferred":[
        "\u9a6c\u66f9\u5751"
    ],
    "wof:name":"Macaokeng",
    "wof:placetype":"locality"
},
  "geometry": {"coordinates":[113.17111,24.04639],"type":"Point"}
}