{
  "type": "Feature",
  "properties": {
    "gn:admin1_code":"26.0",
    "gn:asciiname":"Caijiawan",
    "gn:country_code":"CN",
    "gn:dem":615,
    "gn:feature_class":"P",
    "gn:feature_code":"PPL",
    "gn:name":"Caijiawan",
    "gn:population":0,
    "gn:timezone":"Asia/Shanghai",
    "iso:country":"CN",
    "name:und_x_variant":[
        "\u8521\u5bb6\u6e7e"
    ],
    "wof:name":"Caijiawan",
    "wof:placetype":"locality"
},
  "geometry": {"coordinates":[107.25707,32.97148],"type":"Point"}
}