{
  "type": "Feature",
  "properties": {
    "gn:admin1_code":"19.0",
    "gn:asciiname":"Dayaogou",
    "gn:country_code":"CN",
    "gn:dem":361,
    "gn:feature_class":"P",
    "gn:feature_code":"PPL",
    "gn:name":"Dayaogou",
    "gn:population":0,
    "gn:timezone":"Asia/Shanghai",
    "iso:country":"CN",
    "name:zho_x_preferred":[
        "\u5927\u7a91\u6c9f"
    ],
    "wof:name":"Dayaogou",
    "wof:placetype":"locality"
},
  "geometry": {"coordinates":[119.64100000000001,40.8266],"type":"Point"}
}