{
  "type": "Feature",
  "properties": {
    "gn:admin1_code":"29",
    "gn:asciiname":"Xiaoshaojing",
    "gn:country_code":"CN",
    "gn:dem":2028,
    "gn:feature_class":"P",
    "gn:feature_code":"PPL",
    "gn:name":"Xiaoshaojing",
    "gn:population":0,
    "gn:timezone":"Asia/Shanghai",
    "iso:country":"CN",
    "name:zho_x_preferred":[
        "\u5c0f\u54e8\u9631"
    ],
    "wof:name":"Xiaoshaojing",
    "wof:placetype":"locality"
},
  "geometry": {"coordinates":[102.907,24.9556],"type":"Point"}
}