{
  "type": "Feature",
  "properties": {
    "gn:admin1_code":"31.0",
    "gn:asciiname":"Nanban",
    "gn:country_code":"CN",
    "gn:dem":175,
    "gn:feature_class":"P",
    "gn:feature_code":"PPL",
    "gn:name":"Nanban",
    "gn:population":0,
    "gn:timezone":"Asia/Shanghai",
    "iso:country":"CN",
    "name:fra_x_preferred":[
        "Nanban"
    ],
    "name:und_x_variant":[
        "\u5357\u73ed"
    ],
    "wof:name":"Nanban",
    "wof:placetype":"locality"
},
  "geometry": {"coordinates":[109.27852,18.83192],"type":"Point"}
}