{
  "type": "Feature",
  "properties": {
    "gn:admin1_code":"8.0",
    "gn:asciiname":"Xingyi",
    "gn:country_code":"CN",
    "gn:dem":212,
    "gn:feature_class":"P",
    "gn:feature_code":"PPL",
    "gn:name":"Xingyi",
    "gn:population":0,
    "gn:timezone":"Asia/Shanghai",
    "iso:country":"CN",
    "name:ceb_x_preferred":[
        "Xingyi"
    ],
    "name:deu_x_preferred":[
        "Xingyi"
    ],
    "name:nor_x_preferred":[
        "Xingyi"
    ],
    "name:pol_x_preferred":[
        "Xingyi"
    ],
    "name:zho_x_preferred":[
        "\u5174\u4e49"
    ],
    "wof:name":"Xingyi",
    "wof:placetype":"locality"
},
  "geometry": {"coordinates":[125.54004,47.31716],"type":"Point"}
}