{
  "type": "Feature",
  "properties": {
    "gn:admin1_code":"15.0",
    "gn:asciiname":"Yujingzi",
    "gn:country_code":"CN",
    "gn:dem":1495,
    "gn:feature_class":"P",
    "gn:feature_code":"PPL",
    "gn:name":"Yujingzi",
    "gn:population":0,
    "gn:timezone":"Asia/Shanghai",
    "iso:country":"CN",
    "name:zho_x_preferred":[
        "\u4fde\u4e95\u5b50"
    ],
    "wof:name":"Yujingzi",
    "wof:placetype":"locality"
},
  "geometry": {"coordinates":[98.6306,40.4992],"type":"Point"}
}