{
  "type": "Feature",
  "properties": {
    "gn:admin1_code":"04",
    "gn:asciiname":"Wangji",
    "gn:country_code":"CN",
    "gn:dem":6,
    "gn:feature_class":"P",
    "gn:feature_code":"PPL",
    "gn:name":"Wangji",
    "gn:population":0,
    "gn:timezone":"Asia/Shanghai",
    "iso:country":"CN",
    "name:und_x_variant":[
        "Wang-chi",
        "Wangji",
        "\u738b\u96c6"
    ],
    "wof:name":"Wangji",
    "wof:placetype":"locality"
},
  "geometry": {"coordinates":[119.23520000000001,33.85305],"type":"Point"}
}