{
  "type": "Feature",
  "properties": {
    "gn:admin1_code":"15.0",
    "gn:asciiname":"Qutoushan",
    "gn:country_code":"CN",
    "gn:dem":1883,
    "gn:feature_class":"P",
    "gn:feature_code":"PPL",
    "gn:name":"Qutoushan",
    "gn:population":0,
    "gn:timezone":"Asia/Shanghai",
    "iso:country":"CN",
    "name:zho_x_preferred":[
        "\u66f2\u5934\u5c71"
    ],
    "wof:name":"Qutoushan",
    "wof:placetype":"locality"
},
  "geometry": {"coordinates":[104.54737,33.91672],"type":"Point"}
}