{
  "type": "Feature",
  "properties": {
    "gn:admin1_code":"9.0",
    "gn:asciiname":"Weimasi",
    "gn:country_code":"CN",
    "gn:dem":201,
    "gn:feature_class":"P",
    "gn:feature_code":"PPL",
    "gn:name":"Weimasi",
    "gn:population":0,
    "gn:timezone":"Asia/Shanghai",
    "iso:country":"CN",
    "name:und_x_variant":[
        "\u7ef4\u6469\u5bfa",
        "Weimasi"
    ],
    "wof:name":"Weimasi",
    "wof:placetype":"locality"
},
  "geometry": {"coordinates":[112.86217000000001,33.37383],"type":"Point"}
}