{
  "type": "Feature",
  "properties": {
    "gn:admin1_code":"19.0",
    "gn:asciiname":"Yaotaizicun",
    "gn:country_code":"CN",
    "gn:dem":16,
    "gn:feature_class":"P",
    "gn:feature_code":"PPL",
    "gn:name":"Yaotaizicun",
    "gn:population":0,
    "gn:timezone":"Asia/Shanghai",
    "iso:country":"CN",
    "name:zho_x_preferred":[
        "\u5e7a\u53f0\u5b50\u6751"
    ],
    "name:zho_x_variant":[
        "\u4e48\u53f0\u5b50\u6751"
    ],
    "wof:name":"Yaotaizicun",
    "wof:placetype":"locality"
},
  "geometry": {"coordinates":[122.0933,41.61023],"type":"Point"}
}