{
  "type": "Feature",
  "properties": {
    "gn:admin1_code":"13.0",
    "gn:asciiname":"Yingxiao'ertang",
    "gn:country_code":"CN",
    "gn:dem":1298,
    "gn:feature_class":"P",
    "gn:feature_code":"PPL",
    "gn:name":"Yingxiao\u2019ertang",
    "gn:population":0,
    "gn:timezone":"Asia/Urumqi",
    "iso:country":"CN",
    "name:und_x_variant":[
        "Yingxiao\u2019ertang"
    ],
    "name:zho_x_preferred":[
        "\u82f1\u785d\u5c14\u5802"
    ],
    "wof:name":"Yingxiao'ertang",
    "wof:placetype":"locality"
},
  "geometry": {"coordinates":[84.19244,37.79301],"type":"Point"}
}