{
  "type": "Feature",
  "properties": {
    "gn:admin1_code":"3.0",
    "gn:asciiname":"Zhuyuan",
    "gn:country_code":"CN",
    "gn:dem":171,
    "gn:feature_class":"P",
    "gn:feature_code":"PPL",
    "gn:name":"Zhuyuan",
    "gn:population":0,
    "gn:timezone":"Asia/Shanghai",
    "iso:country":"CN",
    "name:und_x_variant":[
        "\u7af9\u6e90"
    ],
    "wof:name":"Zhuyuan",
    "wof:placetype":"locality"
},
  "geometry": {"coordinates":[116.43476,27.20554000000001],"type":"Point"}
}