{
  "type": "Feature",
  "properties": {
    "gn:admin1_code":"30",
    "gn:asciiname":"Haokeng",
    "gn:country_code":"CN",
    "gn:dem":339,
    "gn:feature_class":"P",
    "gn:feature_code":"PPL",
    "gn:name":"Haokeng",
    "gn:population":0,
    "gn:timezone":"Asia/Shanghai",
    "iso:country":"CN",
    "name:zho_x_preferred":[
        "\u8c6a\u5751"
    ],
    "wof:name":"Haokeng",
    "wof:placetype":"locality"
},
  "geometry": {"coordinates":[115.81140000000001,24.76857],"type":"Point"}
}