{
  "type": "Feature",
  "properties": {
    "gn:admin1_code":"32.0",
    "gn:asciiname":"Simubuyou",
    "gn:country_code":"CN",
    "gn:dem":2481,
    "gn:feature_class":"P",
    "gn:feature_code":"PPL",
    "gn:name":"Simubuyou",
    "gn:population":0,
    "gn:timezone":"Asia/Shanghai",
    "iso:country":"CN",
    "name:zho_x_preferred":[
        "\u53f8\u6bcd\u4e0d\u7531"
    ],
    "wof:name":"Simubuyou",
    "wof:placetype":"locality"
},
  "geometry": {"coordinates":[102.93300000000001,28.1554],"type":"Point"}
}