{
  "type": "Feature",
  "properties": {
    "gn:admin1_code":"29.0",
    "gn:asciiname":"Songjiazaotang",
    "gn:country_code":"CN",
    "gn:dem":1901,
    "gn:feature_class":"P",
    "gn:feature_code":"PPL",
    "gn:name":"Songjiazaotang",
    "gn:population":0,
    "gn:timezone":"Asia/Shanghai",
    "iso:country":"CN",
    "name:zho_x_preferred":[
        "\u5b8b\u5bb6\u6fa1\u5858"
    ],
    "wof:name":"Songjiazaotang",
    "wof:placetype":"locality"
},
  "geometry": {"coordinates":[98.9389,24.5299],"type":"Point"}
}