{
  "type": "Feature",
  "properties": {
    "gn:admin1_code":"9.0",
    "gn:asciiname":"Daguogou",
    "gn:country_code":"CN",
    "gn:dem":226,
    "gn:feature_class":"P",
    "gn:feature_code":"PPL",
    "gn:name":"Daguogou",
    "gn:population":0,
    "gn:timezone":"Asia/Shanghai",
    "iso:country":"CN",
    "name:und_x_variant":[
        "\u5927\u90ed\u6c9f",
        "Daguogou"
    ],
    "wof:name":"Daguogou",
    "wof:placetype":"locality"
},
  "geometry": {"coordinates":[112.86198,33.39593],"type":"Point"}
}