{
  "type": "Feature",
  "properties": {
    "gn:admin1_code":"13",
    "gn:asciiname":"Machanghu",
    "gn:country_code":"CN",
    "gn:dem":519,
    "gn:feature_class":"P",
    "gn:feature_code":"PPL",
    "gn:name":"Machanghu",
    "gn:population":0,
    "gn:timezone":"Asia/Urumqi",
    "iso:country":"CN",
    "name:zho_x_preferred":[
        "\u9a6c\u573a\u6e56"
    ],
    "wof:name":"Machanghu",
    "wof:placetype":"locality"
},
  "geometry": {"coordinates":[87.60429000000001,44.03947],"type":"Point"}
}