{
  "type": "Feature",
  "properties": {
    "gn:admin1_code":"8.0",
    "gn:asciiname":"Lichengtun",
    "gn:country_code":"CN",
    "gn:dem":338,
    "gn:feature_class":"P",
    "gn:feature_code":"PPL",
    "gn:name":"Lichengtun",
    "gn:population":0,
    "gn:timezone":"Asia/Shanghai",
    "iso:country":"CN",
    "name:zho_x_preferred":[
        "\u674e\u6210\u5c6f"
    ],
    "wof:name":"Lichengtun",
    "wof:placetype":"locality"
},
  "geometry": {"coordinates":[125.47674000000001,48.21876],"type":"Point"}
}