{
  "type": "Feature",
  "properties": {
    "gn:admin1_code":"14.0",
    "gn:asciiname":"Bodong",
    "gn:country_code":"CN",
    "gn:dem":3853,
    "gn:feature_class":"P",
    "gn:feature_code":"PPL",
    "gn:name":"Bodong",
    "gn:population":0,
    "gn:timezone":"Asia/Urumqi",
    "iso:country":"CN",
    "name:zho_x_preferred":[
        "\u4f2f\u4e1c"
    ],
    "wof:name":"Bodong",
    "wof:placetype":"locality"
},
  "geometry": {"coordinates":[93.89712,30.2783],"type":"Point"}
}