{
  "type": "Feature",
  "properties": {
    "gn:admin1_code":"8.0",
    "gn:asciiname":"Jubao",
    "gn:country_code":"CN",
    "gn:dem":167,
    "gn:feature_class":"P",
    "gn:feature_code":"PPLA4",
    "gn:name":"Jubao",
    "gn:population":0,
    "gn:timezone":"Asia/Shanghai",
    "iso:country":"CN",
    "name:und_x_variant":[
        "Jubao Zhen"
    ],
    "name:zho_x_preferred":[
        "\u5de8\u5b9d"
    ],
    "name:zho_x_variant":[
        "\u5de8\u5b9d\u9547"
    ],
    "wof:name":"Jubao",
    "wof:placetype":"locality"
},
  "geometry": {"coordinates":[124.18331999999999,47.89447],"type":"Point"}
}