{
  "type": "Feature",
  "properties": {
    "gn:admin1_code":"29.0",
    "gn:asciiname":"Chayelin",
    "gn:country_code":"CN",
    "gn:dem":1251,
    "gn:feature_class":"P",
    "gn:feature_code":"PPL",
    "gn:name":"Chayelin",
    "gn:population":0,
    "gn:timezone":"Asia/Shanghai",
    "iso:country":"CN",
    "name:zho_x_preferred":[
        "\u8336\u53f6\u6797"
    ],
    "wof:name":"Chayelin",
    "wof:placetype":"locality"
},
  "geometry": {"coordinates":[98.91379999999999,23.9883],"type":"Point"}
}