{
  "type": "Feature",
  "properties": {
    "gn:admin1_code":"4.0",
    "gn:asciiname":"Nansongjiadun",
    "gn:country_code":"CN",
    "gn:dem":2,
    "gn:feature_class":"P",
    "gn:feature_code":"PPL",
    "gn:name":"Nansongjiadun",
    "gn:population":0,
    "gn:timezone":"Asia/Shanghai",
    "iso:country":"CN",
    "name:zho_x_preferred":[
        "\u5357\u5b8b\u5bb6\u58a9"
    ],
    "wof:name":"Nansongjiadun",
    "wof:placetype":"locality"
},
  "geometry": {"coordinates":[120.4705,32.93277],"type":"Point"}
}