{
  "type": "Feature",
  "properties": {
    "gn:admin1_code":"13.0",
    "gn:asciiname":"Shifan Xuexiao Nongchang",
    "gn:country_code":"CN",
    "gn:dem":1333,
    "gn:feature_class":"P",
    "gn:feature_code":"PPLF",
    "gn:name":"Shifan Xuexiao Nongchang",
    "gn:population":0,
    "gn:timezone":"Asia/Shanghai",
    "iso:country":"CN",
    "name:zho_x_preferred":[
        "\u5e08\u8303\u5b66\u6821\u519c\u573a"
    ],
    "wof:name":"Shifan Xuexiao Nongchang",
    "wof:placetype":"locality"
},
  "geometry": {"coordinates":[79.90748000000001,37.169],"type":"Point"}
}