{
  "type": "Feature",
  "properties": {
    "gn:admin1_code":"1.0",
    "gn:asciiname":"Wanniantaicun",
    "gn:country_code":"CN",
    "gn:dem":49,
    "gn:feature_class":"P",
    "gn:feature_code":"PPL",
    "gn:name":"Wanniantaicun",
    "gn:population":0,
    "gn:timezone":"Asia/Shanghai",
    "iso:country":"CN",
    "name:zho_x_preferred":[
        "\u4e07\u5e74\u53f0\u6751"
    ],
    "wof:name":"Wanniantaicun",
    "wof:placetype":"locality"
},
  "geometry": {"coordinates":[117.54612,31.08988],"type":"Point"}
}