{
  "type": "Feature",
  "properties": {
    "gn:admin1_code":"11.0",
    "gn:asciiname":"Songjiarong",
    "gn:country_code":"CN",
    "gn:dem":105,
    "gn:feature_class":"P",
    "gn:feature_code":"PPL",
    "gn:name":"Songjiarong",
    "gn:population":0,
    "gn:timezone":"Asia/Shanghai",
    "iso:country":"CN",
    "name:zho_x_preferred":[
        "Songjiarong"
    ],
    "name:zho_x_variant":[
        "\u5b8b\u5bb6\u6eb6"
    ],
    "wof:name":"Songjiarong",
    "wof:placetype":"locality"
},
  "geometry": {"coordinates":[111.56931000000002,29.2082],"type":"Point"}
}