{
  "type": "Feature",
  "properties": {
    "gn:admin1_code":"30",
    "gn:asciiname":"Jianghu",
    "gn:country_code":"CN",
    "gn:dem":28,
    "gn:feature_class":"P",
    "gn:feature_code":"PPLA4",
    "gn:name":"Jianghu",
    "gn:population":0,
    "gn:timezone":"Asia/Urumqi",
    "iso:country":"CN",
    "name:und_x_variant":[
        "Jianghu Zhen",
        "\u6c5f\u6e56\u9547"
    ],
    "name:zho_x_preferred":[
        "\u6c5f\u6e56"
    ],
    "wof:name":"Jianghu",
    "wof:placetype":"locality"
},
  "geometry": {"coordinates":[110.60472,21.87083],"type":"Point"}
}