{
  "type": "Feature",
  "properties": {
    "gn:admin1_code":"8.0",
    "gn:asciiname":"Dagaoliangcun",
    "gn:country_code":"CN",
    "gn:dem":151,
    "gn:feature_class":"P",
    "gn:feature_code":"PPL",
    "gn:name":"Dagaoliangcun",
    "gn:population":0,
    "gn:timezone":"Asia/Shanghai",
    "iso:country":"CN",
    "name:zho_x_preferred":[
        "\u5927\u9ad8\u7cae\u6751"
    ],
    "wof:name":"Dagaoliangcun",
    "wof:placetype":"locality"
},
  "geometry": {"coordinates":[124.05856,47.49796],"type":"Point"}
}