{
  "type": "Feature",
  "properties": {
    "gn:admin1_code":"11.0",
    "gn:asciiname":"Jiaodaowan",
    "gn:country_code":"CN",
    "gn:dem":662,
    "gn:feature_class":"P",
    "gn:feature_code":"PPL",
    "gn:name":"Jiaodaowan",
    "gn:population":0,
    "gn:timezone":"Asia/Shanghai",
    "iso:country":"CN",
    "name:zho_x_preferred":[
        "\u7126\u5200\u6e7e"
    ],
    "wof:name":"Jiaodaowan",
    "wof:placetype":"locality"
},
  "geometry": {"coordinates":[110.36237,26.15596],"type":"Point"}
}