{
  "type": "Feature",
  "properties": {
    "gn:admin1_code":"04",
    "gn:asciiname":"Nangang",
    "gn:country_code":"CN",
    "gn:dem":28,
    "gn:feature_class":"P",
    "gn:feature_code":"PPL",
    "gn:name":"Nangang",
    "gn:population":0,
    "gn:timezone":"Asia/Shanghai",
    "iso:country":"CN",
    "name:ceb_x_preferred":[
        "Nangang"
    ],
    "name:deu_x_preferred":[
        "Nangang"
    ],
    "name:eus_x_preferred":[
        "Nangang"
    ],
    "name:fra_x_preferred":[
        "Nangang"
    ],
    "name:kor_x_preferred":[
        "\ub09c\uac15\uad6c"
    ],
    "name:nor_x_preferred":[
        "Nangang"
    ],
    "name:sco_x_preferred":[
        "Nangang"
    ],
    "name:swe_x_preferred":[
        "Nangang"
    ],
    "name:und_x_variant":[
        "Nan-kang-shang",
        "Nangangshang",
        "Nan-chiang-shang",
        "Nangang"
    ],
    "wof:name":"Nangang",
    "wof:placetype":"locality"
},
  "geometry": {"coordinates":[118.11861,34.5225],"type":"Point"}
}