{
  "type": "Feature",
  "properties": {
    "gn:admin1_code":"18",
    "gn:asciiname":"Kongkeshu",
    "gn:country_code":"CN",
    "gn:dem":860,
    "gn:feature_class":"P",
    "gn:feature_code":"PPL",
    "gn:name":"Kongkeshu",
    "gn:population":0,
    "gn:timezone":"Asia/Shanghai",
    "iso:country":"CN",
    "name:zho_x_preferred":[
        "\u7a7a\u58f3\u6811"
    ],
    "name:zho_x_variant":[
        "\u7a7a\u58f3\u6811\u4e61"
    ],
    "wof:name":"Kongkeshu",
    "wof:placetype":"locality"
},
  "geometry": {"coordinates":[105.764,28.4139],"type":"Point"}
}