{
  "type": "Feature",
  "properties": {
    "gn:admin1_code":"30.0",
    "gn:asciiname":"Shangmugu",
    "gn:country_code":"CN",
    "gn:dem":74,
    "gn:feature_class":"P",
    "gn:feature_code":"PPL",
    "gn:name":"Shangmugu",
    "gn:population":0,
    "gn:timezone":"Asia/Shanghai",
    "iso:country":"CN",
    "name:zho_x_preferred":[
        "\u4e0a\u6728\u53e4"
    ],
    "wof:name":"Shangmugu",
    "wof:placetype":"locality"
},
  "geometry": {"coordinates":[114.11315999999999,22.67107],"type":"Point"}
}