{
  "type": "Feature",
  "properties": {
    "gn:admin1_code":"3.0",
    "gn:asciiname":"Maxie'ao",
    "gn:country_code":"CN",
    "gn:dem":408,
    "gn:feature_class":"P",
    "gn:feature_code":"PPL",
    "gn:name":"Maxie\u2019ao",
    "gn:population":0,
    "gn:timezone":"Asia/Shanghai",
    "iso:country":"CN",
    "name:und_x_variant":[
        "Maxie\u2019ao",
        "\u9ebb\u659c\u5773"
    ],
    "wof:name":"Maxie'ao",
    "wof:placetype":"locality"
},
  "geometry": {"coordinates":[116.19937,26.86191],"type":"Point"}
}