{
  "type": "Feature",
  "properties": {
    "gn:admin1_code":"22.0",
    "gn:asciiname":"Pingyifen",
    "gn:country_code":"CN",
    "gn:dem":71,
    "gn:feature_class":"P",
    "gn:feature_code":"PPL",
    "gn:name":"Pingyifen",
    "gn:population":0,
    "gn:timezone":"Asia/Shanghai",
    "iso:country":"CN",
    "name:zho_x_preferred":[
        "\u5e73\u4e49\u5206"
    ],
    "wof:name":"Pingyifen",
    "wof:placetype":"locality"
},
  "geometry": {"coordinates":[116.52155999999999,40.26885],"type":"Point"}
}