{
  "type": "Feature",
  "properties": {
    "gn:admin1_code":"13",
    "gn:asciiname":"Kan'erjing",
    "gn:country_code":"CN",
    "gn:dem":565,
    "gn:feature_class":"P",
    "gn:feature_code":"PPL",
    "gn:name":"Kan\u2019erjing",
    "gn:population":0,
    "gn:timezone":"Asia/Urumqi",
    "iso:country":"CN",
    "name:und_x_variant":[
        "Kan\u2019erjing",
        "\u574e\u513f\u4e95"
    ],
    "wof:name":"Kan'erjing",
    "wof:placetype":"locality"
},
  "geometry": {"coordinates":[94.21630999999999,43.95741],"type":"Point"}
}