{
  "type": "Feature",
  "properties": {
    "gn:admin1_code":"4.0",
    "gn:asciiname":"Jingxi",
    "gn:country_code":"CN",
    "gn:dem":0,
    "gn:feature_class":"P",
    "gn:feature_code":"PPL",
    "gn:name":"Jingxi",
    "gn:population":0,
    "gn:timezone":"Asia/Shanghai",
    "iso:country":"CN",
    "name:ceb_x_preferred":[
        "Jingxi"
    ],
    "name:rus_x_preferred":[
        "\u0426\u0437\u0438\u043d\u0441\u0438"
    ],
    "name:zho_x_preferred":[
        "Jingxi"
    ],
    "name:zho_x_variant":[
        "\u8346\u6eaa"
    ],
    "wof:name":"Jingxi",
    "wof:placetype":"locality"
},
  "geometry": {"coordinates":[119.76907,33.52301],"type":"Point"}
}