{
  "type": "Feature",
  "properties": {
    "gn:admin1_code":"33.0",
    "gn:asciiname":"Malan",
    "gn:country_code":"CN",
    "gn:dem":1026,
    "gn:feature_class":"P",
    "gn:feature_code":"PPL",
    "gn:name":"Malan",
    "gn:population":0,
    "gn:timezone":"Asia/Shanghai",
    "iso:country":"CN",
    "name:afr_x_preferred":[
        "Malan"
    ],
    "name:ceb_x_preferred":[
        "Malan"
    ],
    "name:ces_x_preferred":[
        "Malan"
    ],
    "name:dan_x_preferred":[
        "Malan"
    ],
    "name:deu_x_preferred":[
        "Malan"
    ],
    "name:fin_x_preferred":[
        "Malan"
    ],
    "name:fra_x_preferred":[
        "Malan"
    ],
    "name:ita_x_preferred":[
        "Malan"
    ],
    "name:pol_x_preferred":[
        "Malan"
    ],
    "name:rus_x_preferred":[
        "\u041c\u0430\u043b\u0430\u043d"
    ],
    "name:swe_x_preferred":[
        "Malan"
    ],
    "name:zho_x_preferred":[
        "\u9a6c\u680f"
    ],
    "wof:name":"Malan",
    "wof:placetype":"locality"
},
  "geometry": {"coordinates":[108.38197,30.04596],"type":"Point"}
}