{
  "type": "Feature",
  "properties": {
    "gn:admin1_code":"18",
    "gn:asciiname":"Wangcao",
    "gn:country_code":"CN",
    "gn:dem":695,
    "gn:feature_class":"P",
    "gn:feature_code":"PPLA4",
    "gn:name":"Wangcao",
    "gn:population":0,
    "gn:timezone":"Asia/Shanghai",
    "iso:country":"CN",
    "name:und_x_variant":[
        "Wang-ts\u2019ao-pa",
        "Wangcaoba",
        "Wang-ts\u2019ao-ch\u2019ang",
        "Wangcao",
        "Wangcao Zhen"
    ],
    "name:zho_x_preferred":[
        "\u65fa\u8349"
    ],
    "name:zho_x_variant":[
        "\u65fa\u8349\u9547"
    ],
    "wof:name":"Wangcao",
    "wof:placetype":"locality"
},
  "geometry": {"coordinates":[107.26672000000001,28.11711],"type":"Point"}
}