{
  "type": "Feature",
  "properties": {
    "gn:admin1_code":"29.0",
    "gn:asciiname":"Samajiu",
    "gn:country_code":"CN",
    "gn:dem":1890,
    "gn:feature_class":"P",
    "gn:feature_code":"PPL",
    "gn:name":"Samajiu",
    "gn:population":0,
    "gn:timezone":"Asia/Shanghai",
    "iso:country":"CN",
    "name:zho_x_preferred":[
        "\u6d12\u9a6c\u65e7"
    ],
    "wof:name":"Samajiu",
    "wof:placetype":"locality"
},
  "geometry": {"coordinates":[101.93000000000001,25.4678],"type":"Point"}
}