{
  "type": "Feature",
  "properties": {
    "gn:admin1_code":"26.0",
    "gn:asciiname":"Laizijian",
    "gn:country_code":"CN",
    "gn:dem":1528,
    "gn:feature_class":"P",
    "gn:feature_code":"PPL",
    "gn:name":"Laizijian",
    "gn:population":0,
    "gn:timezone":"Asia/Shanghai",
    "iso:country":"CN",
    "name:und_x_variant":[
        "\u6765\u5b50\u6da7"
    ],
    "wof:name":"Laizijian",
    "wof:placetype":"locality"
},
  "geometry": {"coordinates":[107.9015,36.77422],"type":"Point"}
}