{
  "type": "Feature",
  "properties": {
    "gn:admin1_code":"12.0",
    "gn:asciiname":"Bukou",
    "gn:country_code":"CN",
    "gn:dem":83,
    "gn:feature_class":"P",
    "gn:feature_code":"PPL",
    "gn:name":"Bukou",
    "gn:population":0,
    "gn:timezone":"Asia/Shanghai",
    "iso:country":"CN",
    "name:zho_x_preferred":[
        "\u57e0\u53e3"
    ],
    "wof:name":"Bukou",
    "wof:placetype":"locality"
},
  "geometry": {"coordinates":[111.79062999999999,32.15985999999999],"type":"Point"}
}