{
  "type": "Feature",
  "properties": {
    "gn:admin1_code":"16",
    "gn:asciiname":"Nutu",
    "gn:country_code":"CN",
    "gn:dem":597,
    "gn:feature_class":"P",
    "gn:feature_code":"PPL",
    "gn:name":"Nutu",
    "gn:population":0,
    "gn:timezone":"Asia/Shanghai",
    "iso:country":"CN",
    "name:zho_x_preferred":[
        "\u5974\u56fe"
    ],
    "wof:name":"Nutu",
    "wof:placetype":"locality"
},
  "geometry": {"coordinates":[109.354,25.7428],"type":"Point"}
}