{
  "type": "Feature",
  "properties": {
    "gn:admin1_code":"3.0",
    "gn:asciiname":"Shixia",
    "gn:country_code":"CN",
    "gn:dem":136,
    "gn:feature_class":"P",
    "gn:feature_code":"PPL",
    "gn:name":"Shixia",
    "gn:population":0,
    "gn:timezone":"Asia/Shanghai",
    "iso:country":"CN",
    "name:deu_x_preferred":[
        "Shixia"
    ],
    "name:und_x_variant":[
        "\u77f3\u4e0b"
    ],
    "wof:name":"Shixia",
    "wof:placetype":"locality"
},
  "geometry": {"coordinates":[115.13833,28.68254],"type":"Point"}
}