{
  "type": "Feature",
  "properties": {
    "gn:admin1_code":"1.0",
    "gn:asciiname":"Gaolihong Linchang",
    "gn:country_code":"CN",
    "gn:dem":83,
    "gn:feature_class":"P",
    "gn:feature_code":"PPLF",
    "gn:name":"Gaolihong Linchang",
    "gn:population":0,
    "gn:timezone":"Asia/Shanghai",
    "iso:country":"CN",
    "wof:name":"Gaolihong Linchang",
    "wof:placetype":"locality"
},
  "geometry": {"coordinates":[118.84166999999999,31.16667],"type":"Point"}
}