{
  "type": "Feature",
  "properties": {
    "gn:admin1_code":"14.0",
    "gn:asciiname":"Shala",
    "gn:country_code":"CN",
    "gn:dem":4277,
    "gn:feature_class":"P",
    "gn:feature_code":"PPL",
    "gn:name":"Shala",
    "gn:population":0,
    "gn:timezone":"Asia/Urumqi",
    "iso:country":"CN",
    "name:zho_x_preferred":[
        "\u838e\u62c9"
    ],
    "wof:name":"Shala",
    "wof:placetype":"locality"
},
  "geometry": {"coordinates":[87.5472,28.3574],"type":"Point"}
}