{
  "type": "Feature",
  "properties": {
    "gn:admin1_code":"24.0",
    "gn:asciiname":"Qiaoxiaofeng",
    "gn:country_code":"CN",
    "gn:dem":1596,
    "gn:feature_class":"P",
    "gn:feature_code":"PPL",
    "gn:name":"Qiaoxiaofeng",
    "gn:population":0,
    "gn:timezone":"Asia/Shanghai",
    "iso:country":"CN",
    "name:zho_x_preferred":[
        "\u4e54\u5c0f\u5cf0"
    ],
    "wof:name":"Qiaoxiaofeng",
    "wof:placetype":"locality"
},
  "geometry": {"coordinates":[112.29658999999999,39.64167],"type":"Point"}
}