{
  "type": "Feature",
  "properties": {
    "gn:admin1_code":"26",
    "gn:asciiname":"Zhaojiayuan",
    "gn:country_code":"CN",
    "gn:dem":516,
    "gn:feature_class":"P",
    "gn:feature_code":"PPL",
    "gn:name":"Zhaojiayuan",
    "gn:population":0,
    "gn:timezone":"Asia/Shanghai",
    "iso:country":"CN",
    "name:und_x_variant":[
        "Ch\u2019ien-yang",
        "Qianyang",
        "Zhaojiayuan"
    ],
    "name:zho_x_preferred":[
        "\u8d75\u5bb6\u586c"
    ],
    "wof:name":"Zhaojiayuan",
    "wof:placetype":"locality"
},
  "geometry": {"coordinates":[109.6636,34.96685],"type":"Point"}
}