{
  "type": "Feature",
  "properties": {
    "gn:admin1_code":"32.0",
    "gn:asciiname":"Fengliang",
    "gn:country_code":"CN",
    "gn:dem":488,
    "gn:feature_class":"P",
    "gn:feature_code":"PPL",
    "gn:name":"Fengliang",
    "gn:population":0,
    "gn:timezone":"Asia/Shanghai",
    "iso:country":"CN",
    "name:zho_x_preferred":[
        "\u51e4\u6881"
    ],
    "name:zho_x_variant":[
        "\u4e30\u826f\u9547"
    ],
    "wof:name":"Fengliang",
    "wof:placetype":"locality"
},
  "geometry": {"coordinates":[107.44199999999999,31.7658],"type":"Point"}
}