{
  "type": "Feature",
  "properties": {
    "gn:admin1_code":"15.0",
    "gn:asciiname":"Dahuangbao",
    "gn:country_code":"CN",
    "gn:dem":2833,
    "gn:feature_class":"P",
    "gn:feature_code":"PPL",
    "gn:name":"Dahuangbao",
    "gn:population":0,
    "gn:timezone":"Asia/Shanghai",
    "iso:country":"CN",
    "name:zho_x_preferred":[
        "\u5927\u9ec4\u4fdd"
    ],
    "wof:name":"Dahuangbao",
    "wof:placetype":"locality"
},
  "geometry": {"coordinates":[102.831,37.2984],"type":"Point"}
}