{
  "type": "Feature",
  "properties": {
    "gn:country":"CN",
    "gn:fcode":"PPL",
    "gn:pop":425,
    "iso:country":"CN",
    "qs:name":"Datangzhuang",
    "qs:photos_9r":0,
    "qs:photos_sr":0,
    "qs:pop_sr":"2",
    "wd:wordcount":192,
    "wof:name":"Datangzhuang",
    "wof:placetype":"locality",
    "wof:population":425
},
  "geometry": {"coordinates":[117.34305999999999,39.98667],"type":"Point"}
}