{
  "type": "Feature",
  "properties": {
    "gn:admin1_code":"21.0",
    "gn:asciiname":"Liujiataozi",
    "gn:country_code":"CN",
    "gn:dem":1805,
    "gn:feature_class":"P",
    "gn:feature_code":"PPL",
    "gn:name":"Liujiataozi",
    "gn:population":0,
    "gn:timezone":"Asia/Shanghai",
    "iso:country":"CN",
    "name:und_x_variant":[
        "\u5218\u5bb6\u5957\u5b50"
    ],
    "name:zho_x_preferred":[
        "\u5218\u5bb6\u5957\u5b50"
    ],
    "wof:name":"Liujiataozi",
    "wof:placetype":"locality"
},
  "geometry": {"coordinates":[106.4682,36.65746],"type":"Point"}
}