{
  "type": "Feature",
  "properties": {
    "gn:admin1_code":"26.0",
    "gn:asciiname":"Xujunzhaicun",
    "gn:country_code":"CN",
    "gn:dem":758,
    "gn:feature_class":"P",
    "gn:feature_code":"PPL",
    "gn:name":"Xujunzhaicun",
    "gn:population":0,
    "gn:timezone":"Asia/Shanghai",
    "iso:country":"CN",
    "name:und_x_variant":[
        "\u5f90\u519b\u5be8\u6751"
    ],
    "wof:name":"Xujunzhaicun",
    "wof:placetype":"locality"
},
  "geometry": {"coordinates":[109.40821,34.19449],"type":"Point"}
}