{
  "type": "Feature",
  "properties": {
    "gn:admin1_code":"8.0",
    "gn:asciiname":"Defu Bajiudui",
    "gn:country_code":"CN",
    "gn:dem":241,
    "gn:feature_class":"P",
    "gn:feature_code":"PPLF",
    "gn:name":"Defu Bajiudui",
    "gn:population":0,
    "gn:timezone":"Asia/Shanghai",
    "iso:country":"CN",
    "name:zho_x_preferred":[
        "\u5fb7\u798f\u516b\u4e5d\u961f"
    ],
    "wof:name":"Defu Bajiudui",
    "wof:placetype":"locality"
},
  "geometry": {"coordinates":[123.07619,47.48214],"type":"Point"}
}