{
  "type": "Feature",
  "properties": {
    "gn:admin1_code":"29.0",
    "gn:asciiname":"Dangziluo",
    "gn:country_code":"CN",
    "gn:dem":1752,
    "gn:feature_class":"P",
    "gn:feature_code":"PPL",
    "gn:name":"Dangziluo",
    "gn:population":0,
    "gn:timezone":"Asia/Shanghai",
    "iso:country":"CN",
    "name:zho_x_preferred":[
        "\u5f53\u5b50\u843d"
    ],
    "wof:name":"Dangziluo",
    "wof:placetype":"locality"
},
  "geometry": {"coordinates":[100.491,27.3096],"type":"Point"}
}