{
  "type": "Feature",
  "properties": {
    "gn:admin1_code":"12.0",
    "gn:asciiname":"Tanjiawan",
    "gn:country_code":"CN",
    "gn:dem":94,
    "gn:feature_class":"P",
    "gn:feature_code":"PPL",
    "gn:name":"Tanjiawan",
    "gn:population":0,
    "gn:timezone":"Asia/Shanghai",
    "iso:country":"CN",
    "name:zho_x_preferred":[
        "Tanjiawan"
    ],
    "name:zho_x_variant":[
        "\u8c2d\u5bb6\u6e7e"
    ],
    "wof:name":"Tanjiawan",
    "wof:placetype":"locality"
},
  "geometry": {"coordinates":[111.41696,30.69674],"type":"Point"}
}