{
  "type": "Feature",
  "properties": {
    "gn:admin1_code":"29",
    "gn:asciiname":"Benggu",
    "gn:country_code":"CN",
    "gn:dem":1172,
    "gn:feature_class":"P",
    "gn:feature_code":"PPL",
    "gn:name":"Benggu",
    "gn:population":0,
    "gn:timezone":"Asia/Shanghai",
    "iso:country":"CN",
    "name:zho_x_preferred":[
        "\u868c\u53e4"
    ],
    "wof:name":"Benggu",
    "wof:placetype":"locality"
},
  "geometry": {"coordinates":[104.628,24.2988],"type":"Point"}
}