{
  "type": "Feature",
  "properties": {
    "gn:admin1_code":"9.0",
    "gn:asciiname":"Linzhuang",
    "gn:country_code":"CN",
    "gn:dem":66,
    "gn:feature_class":"P",
    "gn:feature_code":"PPL",
    "gn:name":"Linzhuang",
    "gn:population":0,
    "gn:timezone":"Asia/Shanghai",
    "iso:country":"CN",
    "name:zho_x_preferred":[
        "\u6797\u5e84"
    ],
    "wof:name":"Linzhuang",
    "wof:placetype":"locality"
},
  "geometry": {"coordinates":[114.20402,32.93348],"type":"Point"}
}