{
  "type": "Feature",
  "properties": {
    "gn:admin1_code":"5.0",
    "gn:asciiname":"Xiwangjialucun",
    "gn:country_code":"CN",
    "gn:dem":197,
    "gn:feature_class":"P",
    "gn:feature_code":"PPL",
    "gn:name":"Xiwangjialucun",
    "gn:population":0,
    "gn:timezone":"Asia/Shanghai",
    "iso:country":"CN",
    "name:zho_x_preferred":[
        "\u897f\u738b\u5bb6\u7089\u6751"
    ],
    "wof:name":"Xiwangjialucun",
    "wof:placetype":"locality"
},
  "geometry": {"coordinates":[125.94237,44.45303],"type":"Point"}
}