{
  "type": "Feature",
  "properties": {
    "gn:admin1_code":"4.0",
    "gn:asciiname":"Dagangzhakou",
    "gn:country_code":"CN",
    "gn:dem":1,
    "gn:feature_class":"P",
    "gn:feature_code":"PPL",
    "gn:name":"Dagangzhakou",
    "gn:population":0,
    "gn:timezone":"Asia/Shanghai",
    "iso:country":"CN",
    "name:zho_x_preferred":[
        "\u5927\u7eb2\u95f8\u53e3"
    ],
    "wof:name":"Dagangzhakou",
    "wof:placetype":"locality"
},
  "geometry": {"coordinates":[120.312,33.7786],"type":"Point"}
}