{
  "type": "Feature",
  "properties": {
    "gn:admin1_code":"19.0",
    "gn:asciiname":"Sijianfang",
    "gn:country_code":"CN",
    "gn:dem":20,
    "gn:feature_class":"P",
    "gn:feature_code":"PPL",
    "gn:name":"Sijianfang",
    "gn:population":0,
    "gn:timezone":"Asia/Shanghai",
    "iso:country":"CN",
    "name:und_x_variant":[
        "\u56db\u95f4\u623f"
    ],
    "name:zho_x_preferred":[
        "\u56db\u95f4\u623f"
    ],
    "wof:name":"Sijianfang",
    "wof:placetype":"locality"
},
  "geometry": {"coordinates":[122.21193999999998,41.70204],"type":"Point"}
}