{
  "type": "Feature",
  "properties": {
    "gn:admin1_code":"8.0",
    "gn:asciiname":"Minshengtun",
    "gn:country_code":"CN",
    "gn:dem":216,
    "gn:feature_class":"P",
    "gn:feature_code":"PPL",
    "gn:name":"Minshengtun",
    "gn:population":0,
    "gn:timezone":"Asia/Shanghai",
    "iso:country":"CN",
    "name:zho_x_preferred":[
        "\u6c11\u751f\u5c6f"
    ],
    "wof:name":"Minshengtun",
    "wof:placetype":"locality"
},
  "geometry": {"coordinates":[125.38088999999999,48.52899],"type":"Point"}
}