{
  "type": "Feature",
  "properties": {
    "gn:admin1_code":"4.0",
    "gn:asciiname":"Xinglian",
    "gn:country_code":"CN",
    "gn:dem":2,
    "gn:feature_class":"P",
    "gn:feature_code":"PPL",
    "gn:name":"Xinglian",
    "gn:population":0,
    "gn:timezone":"Asia/Shanghai",
    "iso:country":"CN",
    "name:zho_x_preferred":[
        "\u5174\u8054"
    ],
    "wof:name":"Xinglian",
    "wof:placetype":"locality"
},
  "geometry": {"coordinates":[119.57653999999999,32.90928],"type":"Point"}
}