{
  "type": "Feature",
  "properties": {
    "gn:admin1_code":"3",
    "gn:asciiname":"Jiaotang",
    "gn:country_code":"CN",
    "gn:dem":259,
    "gn:feature_class":"P",
    "gn:feature_code":"PPL",
    "gn:name":"Jiaotang",
    "gn:population":0,
    "gn:timezone":"Asia/Shanghai",
    "iso:country":"CN",
    "name:zho_x_preferred":[
        "\u8549\u5858"
    ],
    "wof:name":"Jiaotang",
    "wof:placetype":"locality"
},
  "geometry": {"coordinates":[113.92677999999999,26.6584],"type":"Point"}
}