{
  "type": "Feature",
  "properties": {
    "gn:admin1_code":"11.0",
    "gn:asciiname":"Xiaoliu",
    "gn:country_code":"CN",
    "gn:dem":603,
    "gn:feature_class":"P",
    "gn:feature_code":"PPL",
    "gn:name":"Xiaoliu",
    "gn:population":0,
    "gn:timezone":"Asia/Shanghai",
    "iso:country":"CN",
    "name:zho_x_preferred":[
        "\u5c0f\u69b4"
    ],
    "wof:name":"Xiaoliu",
    "wof:placetype":"locality"
},
  "geometry": {"coordinates":[109.40787,26.59248],"type":"Point"}
}