{
  "type": "Feature",
  "properties": {
    "gn:admin1_code":"29.0",
    "gn:asciiname":"Jiufang",
    "gn:cc2":"CN",
    "gn:country_code":"CN",
    "gn:dem":1122,
    "gn:feature_class":"P",
    "gn:feature_code":"PPL",
    "gn:name":"Jiufang",
    "gn:population":0,
    "gn:timezone":"Asia/Shanghai",
    "iso:country":"CN",
    "name:und_x_variant":[
        "Chiu-fang",
        "Jiufang"
    ],
    "wof:name":"Jiufang",
    "wof:placetype":"locality"
},
  "geometry": {"coordinates":[99.98333,22.48333],"type":"Point"}
}