{
  "type": "Feature",
  "properties": {
    "gn:admin1_code":"32",
    "gn:asciiname":"Chuanxing",
    "gn:country_code":"CN",
    "gn:dem":1534,
    "gn:feature_class":"P",
    "gn:feature_code":"PPL",
    "gn:name":"Chuanxing",
    "gn:population":0,
    "gn:timezone":"Asia/Shanghai",
    "iso:country":"CN",
    "name:und_x_variant":[
        "Ch\u2019uan-hsing-pao",
        "Chuanxingpu",
        "Chuanxing"
    ],
    "name:zho_x_preferred":[
        "\u5ddd\u5174"
    ],
    "wof:name":"Chuanxing",
    "wof:placetype":"locality"
},
  "geometry": {"coordinates":[102.31469,27.87292],"type":"Point"}
}