{
  "type": "Feature",
  "properties": {
    "gn:admin1_code":"20",
    "gn:asciiname":"Qagan Ders",
    "gn:cc2":"CN",
    "gn:country_code":"CN",
    "gn:dem":1196,
    "gn:feature_class":"P",
    "gn:feature_code":"PPL",
    "gn:name":"Qagan Ders",
    "gn:population":0,
    "gn:timezone":"Asia/Shanghai",
    "iso:country":"CN",
    "name:und_x_variant":[
        "Ch\u2019a-kan-te-jih-ssu",
        "Qagan Ders"
    ],
    "wof:name":"Qagan Ders",
    "wof:placetype":"locality"
},
  "geometry": {"coordinates":[105.94417,40.28972],"type":"Point"}
}