{
  "type": "Feature",
  "properties": {
    "gn:admin1_code":"30.0",
    "gn:asciiname":"Shuanghucun",
    "gn:country_code":"CN",
    "gn:dem":164,
    "gn:feature_class":"P",
    "gn:feature_code":"PPL",
    "gn:name":"Shuanghucun",
    "gn:population":0,
    "gn:timezone":"Asia/Shanghai",
    "iso:country":"CN",
    "name:zho_x_preferred":[
        "\u53cc\u6e56\u6751"
    ],
    "wof:name":"Shuanghucun",
    "wof:placetype":"locality"
},
  "geometry": {"coordinates":[116.05676,24.06641],"type":"Point"}
}