{
  "type": "Feature",
  "properties": {
    "gn:admin1_code":"5.0",
    "gn:asciiname":"Longyuancun",
    "gn:country_code":"CN",
    "gn:dem":279,
    "gn:feature_class":"P",
    "gn:feature_code":"PPL",
    "gn:name":"Longyuancun",
    "gn:population":0,
    "gn:timezone":"Asia/Shanghai",
    "iso:country":"CN",
    "name:zho_x_preferred":[
        "\u9f99\u6e0a\u6751"
    ],
    "wof:name":"Longyuancun",
    "wof:placetype":"locality"
},
  "geometry": {"coordinates":[129.43805,42.94922],"type":"Point"}
}