{
  "type": "Feature",
  "properties": {
    "gn:admin1_code":"1.0",
    "gn:asciiname":"Miaobeicun",
    "gn:country_code":"CN",
    "gn:dem":45,
    "gn:feature_class":"P",
    "gn:feature_code":"PPL",
    "gn:name":"Miaobeicun",
    "gn:population":0,
    "gn:timezone":"Asia/Shanghai",
    "iso:country":"CN",
    "name:zho_x_preferred":[
        "\u5e99\u5317\u6751"
    ],
    "wof:name":"Miaobeicun",
    "wof:placetype":"locality"
},
  "geometry": {"coordinates":[117.20216000000001,32.2095],"type":"Point"}
}