{
  "type": "Feature",
  "properties": {
    "gn:admin1_code":"2.0",
    "gn:asciiname":"Langyuan",
    "gn:country_code":"CN",
    "gn:dem":52,
    "gn:feature_class":"P",
    "gn:feature_code":"PPL",
    "gn:name":"Langyuan",
    "gn:population":0,
    "gn:timezone":"Asia/Shanghai",
    "iso:country":"CN",
    "name:zho_x_preferred":[
        "\u9606\u82d1"
    ],
    "wof:name":"Langyuan",
    "wof:placetype":"locality"
},
  "geometry": {"coordinates":[119.66475,29.84481],"type":"Point"}
}