{
  "type": "Feature",
  "properties": {
    "gn:admin1_code":"11.0",
    "gn:asciiname":"Sankoupeng",
    "gn:country_code":"CN",
    "gn:dem":57,
    "gn:feature_class":"P",
    "gn:feature_code":"PPL",
    "gn:name":"Sankoupeng",
    "gn:population":0,
    "gn:timezone":"Asia/Shanghai",
    "iso:country":"CN",
    "name:zho_x_preferred":[
        "\u4e09\u53e3\u68da"
    ],
    "wof:name":"Sankoupeng",
    "wof:placetype":"locality"
},
  "geometry": {"coordinates":[113.40979,27.61464],"type":"Point"}
}