{
  "type": "Feature",
  "properties": {
    "gn:country":"CN",
    "gn:fcode":"PPL",
    "gn:population":82641,
    "iso:country":"CN",
    "name:ara_x_preferred":[
        "\u0628\u064a\u062c\u0648"
    ],
    "name:ben_x_preferred":[
        "\u09aa\u09bf\u099d\u09c1"
    ],
    "name:dan_x_preferred":[
        "Pizhou"
    ],
    "name:deu_x_preferred":[
        "Pizhou"
    ],
    "name:ell_x_preferred":[
        "\u03a0\u03af\u03b6\u03bf\u03c5"
    ],
    "name:eng_x_preferred":[
        "Pizhou"
    ],
    "name:fin_x_preferred":[
        "Pizhou"
    ],
    "name:fra_x_preferred":[
        "Pizhou"
    ],
    "name:gan_x_preferred":[
        "\u90b3\u5dde\u5e02"
    ],
    "name:guj_x_preferred":[
        "\u0aaa\u0ac0\u0a9d\u0acb\u0a89"
    ],
    "name:hin_x_preferred":[
        "\u092a\u093f\u091c\u093c\u094d\u0939\u094c"
    ],
    "name:ind_x_preferred":[
        "Pizhou"
    ],
    "name:ita_x_preferred":[
        "Pizhou"
    ],
    "name:jpn_x_preferred":[
        "\u30d2\u5dde\u5e02"
    ],
    "name:kan_x_preferred":[
        "\u0caa\u0cbf\u0c9d\u0ccc"
    ],
    "name:kik_x_preferred":[
        "Pizhou"
    ],
    "name:kor_x_preferred":[
        "\ud53c\uc800\uc6b0\uc2dc"
    ],
    "name:lav_x_preferred":[
        "Pi\u017eou"
    ],
    "name:lit_x_preferred":[
        "Pi\u017eou"
    ],
    "name:mar_x_preferred":[
        "\u092a\u093f\u091d\u094b\u0909"
    ],
    "name:msa_x_preferred":[
        "Pizhou"
    ],
    "name:nan_x_preferred":[
        "Phi-chiu-chh\u012b"
    ],
    "name:nld_x_preferred":[
        "Pizhou"
    ],
    "name:nob_x_preferred":[
        "Pizhou"
    ],
    "name:pol_x_preferred":[
        "Pizhou"
    ],
    "name:rus_x_preferred":[
        "\u041f\u0438\u0447\u0436\u043e\u0443"
    ],
    "name:sin_x_preferred":[
        "\u0db4\u0dd2\u0dc3\u0dde"
    ],
    "name:swe_x_preferred":[
        "Pizhou"
    ],
    "name:tam_x_preferred":[
        "\u0baa\u0bbf\u0bb7\u0bcb\u0bb5\u0bc1"
    ],
    "name:tel_x_preferred":[
        "\u0c2a\u0c3f\u0c1c\u0c4d\u0c39\u0c4c"
    ],
    "name:tgl_x_preferred":[
        "Pizhou"
    ],
    "name:tha_x_preferred":[
        "\u0e1c\u0e35\u0e42\u0e08\u0e27"
    ],
    "name:tur_x_preferred":[
        "Pizhou"
    ],
    "name:ukr_x_preferred":[
        "\u041f\u0456\u0447\u0436\u043e\u0443"
    ],
    "name:und_x_variant":[
        "P\u2019ei-hsien"
    ],
    "name:urd_x_preferred":[
        "\u067e\u06cc\u0632\u062d\u0648\u0648"
    ],
    "name:vie_x_preferred":[
        "Bi Ch\u00e2u"
    ],
    "name:wuu_x_preferred":[
        "\u90b3\u5dde\u5e02"
    ],
    "name:yue_x_preferred":[
        "\u90b3\u5dde"
    ],
    "name:zho_x_preferred":[
        "\u90b3\u5dde\u5e02"
    ],
    "qs:name":"Pizhou",
    "qs:name_adm0":"\u4e2d\u570b",
    "qs:name_adm1":"\u6c5f\u82cf\u7701",
    "qs:photos_9k":1,
    "qs:photos_9r":1,
    "qs:photos_all":1,
    "qs:photos_sr":0,
    "qs:placetype":"Town",
    "qs:pop_sr":"8",
    "wd:wordcount":372,
    "wof:name":"Pizhou",
    "wof:placetype":"locality",
    "wof:population":82641
},
  "geometry": {"coordinates":[117.95028000000001,34.31139],"type":"Point"}
}