{
  "type": "Feature",
  "properties": {
    "gn:country":"CN",
    "gn:fcode":"PPL",
    "gn:pop":82641,
    "iso:country":"CN",
    "name:unk_x_variant":[
        "P\u2019ei-hsien"
    ],
    "qs:name":"Pizhou",
    "qs:name_adm0":"\u4e2d\u570b",
    "qs:name_adm1":"\u6c5f\u82cf\u7701",
    "qs:photos_9k":1,
    "qs:photos_9r":1,
    "qs:photos_all":1,
    "qs:photos_sr":0,
    "qs:placetype":"Town",
    "qs:pop_sr":"8",
    "wd:wordcount":372,
    "wof:name":"Pizhou",
    "wof:placetype":"locality",
    "wof:population":82641
},
  "geometry": {"coordinates":[117.95028000000001,34.31139],"type":"Point"}
}