{
  "type": "Feature",
  "properties": {
    "gn:admin1_code":"16.0",
    "gn:asciiname":"Nonglixia",
    "gn:country_code":"CN",
    "gn:dem":502,
    "gn:feature_class":"P",
    "gn:feature_code":"PPL",
    "gn:name":"Nonglixia",
    "gn:population":0,
    "gn:timezone":"Asia/Shanghai",
    "iso:country":"CN",
    "name:zho_x_preferred":[
        "\u5f04\u529b\u4e0b"
    ],
    "wof:name":"Nonglixia",
    "wof:placetype":"locality"
},
  "geometry": {"coordinates":[107.869,24.0114],"type":"Point"}
}