{
  "type": "Feature",
  "properties": {
    "gn:admin1_code":"29.0",
    "gn:asciiname":"Fujiawan",
    "gn:country_code":"CN",
    "gn:dem":2832,
    "gn:feature_class":"P",
    "gn:feature_code":"PPL",
    "gn:name":"Fujiawan",
    "gn:population":0,
    "gn:timezone":"Asia/Shanghai",
    "iso:country":"CN",
    "name:zho_x_preferred":[
        "\u7b26\u5bb6\u6e7e"
    ],
    "wof:name":"Fujiawan",
    "wof:placetype":"locality"
},
  "geometry": {"coordinates":[103.11,26.9227],"type":"Point"}
}