{
  "type": "Feature",
  "properties": {
    "gn:admin1_code":"29.0",
    "gn:asciiname":"Xiaopuzi",
    "gn:country_code":"CN",
    "gn:dem":2283,
    "gn:feature_class":"P",
    "gn:feature_code":"PPL",
    "gn:name":"Xiaopuzi",
    "gn:population":0,
    "gn:timezone":"Asia/Shanghai",
    "iso:country":"CN",
    "name:zho_x_preferred":[
        "\u5c0f\u94fa\u5b50"
    ],
    "wof:name":"Xiaopuzi",
    "wof:placetype":"locality"
},
  "geometry": {"coordinates":[101.825,25.3439],"type":"Point"}
}