{
  "type": "Feature",
  "properties": {
    "gn:admin1_code":"29.0",
    "gn:asciiname":"Jialanggu",
    "gn:country_code":"CN",
    "gn:dem":2107,
    "gn:feature_class":"P",
    "gn:feature_code":"PPL",
    "gn:name":"Jialanggu",
    "gn:population":0,
    "gn:timezone":"Asia/Shanghai",
    "iso:country":"CN",
    "name:zho_x_preferred":[
        "\u8d3e\u90ce\u53e4"
    ],
    "wof:name":"Jialanggu",
    "wof:placetype":"locality"
},
  "geometry": {"coordinates":[102.768,25.3527],"type":"Point"}
}