{
  "type": "Feature",
  "properties": {
    "gn:admin1_code":"05",
    "gn:asciiname":"Zhoujiawo Linchang",
    "gn:country_code":"CN",
    "gn:dem":849,
    "gn:feature_class":"P",
    "gn:feature_code":"PPLF",
    "gn:name":"Zhoujiawo Linchang",
    "gn:population":0,
    "gn:timezone":"Asia/Shanghai",
    "iso:country":"CN",
    "name:und_x_variant":[
        "\u5468\u5bb6\u7a9d\u6797\u573a"
    ],
    "wof:name":"Zhoujiawo Linchang",
    "wof:placetype":"locality"
},
  "geometry": {"coordinates":[126.73056,41.84222000000001],"type":"Point"}
}