{
  "type": "Feature",
  "properties": {
    "gn:country":"CN",
    "gn:fcode":"PPL",
    "gn:pop":1468,
    "iso:country":"CN",
    "qs:name":"Fuzhuang",
    "qs:photos_9r":0,
    "qs:photos_sr":0,
    "qs:pop_sr":"3",
    "wd:wordcount":213,
    "wof:name":"Fuzhuang",
    "wof:placetype":"locality",
    "wof:population":1468
},
  "geometry": {"coordinates":[117.93444,39.26611],"type":"Point"}
}