{
  "type": "Feature",
  "properties": {
    "gn:country":"CN",
    "gn:fcode":"PPL",
    "gn:population":1468,
    "iso:country":"CN",
    "name:ceb_x_preferred":[
        "Yuanyang Xian"
    ],
    "name:deu_x_preferred":[
        "Yuanyang"
    ],
    "name:fas_x_preferred":[
        "\u0634\u0647\u0631\u0633\u062a\u0627\u0646 \u06cc\u0648\u0627\u0646\u06cc\u0627\u0646\u06af"
    ],
    "name:jpn_x_preferred":[
        "\u539f\u967d\u770c"
    ],
    "name:kor_x_preferred":[
        "\uc704\uc548\uc591\ud604"
    ],
    "name:nor_x_preferred":[
        "Yuanyang"
    ],
    "name:rus_x_preferred":[
        "\u042e\u0430\u043d\u044c\u044f\u043d"
    ],
    "name:swe_x_preferred":[
        "Yuanyang"
    ],
    "name:vie_x_preferred":[
        "Nguy\u00ean D\u01b0\u01a1ng"
    ],
    "name:zho_x_preferred":[
        "\u539f\u9633\u53bf"
    ],
    "qs:name":"Fuzhuang",
    "qs:photos_9r":0,
    "qs:photos_sr":0,
    "qs:pop_sr":"3",
    "wd:wordcount":213,
    "wof:name":"Fuzhuang",
    "wof:placetype":"locality",
    "wof:population":1468
},
  "geometry": {"coordinates":[117.93444,39.26611],"type":"Point"}
}