{
  "type": "Feature",
  "properties": {
    "gn:admin1_code":"5.0",
    "gn:asciiname":"Toudao Hezi",
    "gn:country_code":"CN",
    "gn:dem":711,
    "gn:feature_class":"P",
    "gn:feature_code":"PPL",
    "gn:name":"Toudao Hezi",
    "gn:population":0,
    "gn:timezone":"Asia/Shanghai",
    "iso:country":"CN",
    "name:zho_x_preferred":[
        "\u5934\u9053\u6cb3\u5b50"
    ],
    "wof:name":"Toudao Hezi",
    "wof:placetype":"locality"
},
  "geometry": {"coordinates":[125.97469,42.06713],"type":"Point"}
}