{
  "type": "Feature",
  "properties": {
    "gn:admin1_code":"12.0",
    "gn:asciiname":"Changli",
    "gn:country_code":"CN",
    "gn:dem":77,
    "gn:feature_class":"P",
    "gn:feature_code":"PPL",
    "gn:name":"Changli",
    "gn:population":0,
    "gn:timezone":"Asia/Shanghai",
    "iso:country":"CN",
    "name:zho_x_preferred":[
        "Changli"
    ],
    "name:zho_x_variant":[
        "\u957f\u7b20"
    ],
    "wof:name":"Changli",
    "wof:placetype":"locality"
},
  "geometry": {"coordinates":[114.85713,29.67261],"type":"Point"}
}