{
  "type": "Feature",
  "properties": {
    "gn:admin1_code":"1.0",
    "gn:asciiname":"Ziyuancun",
    "gn:country_code":"CN",
    "gn:dem":8,
    "gn:feature_class":"P",
    "gn:feature_code":"PPL",
    "gn:name":"Ziyuancun",
    "gn:population":0,
    "gn:timezone":"Asia/Shanghai",
    "iso:country":"CN",
    "name:zho_x_preferred":[
        "\u7d2b\u56ed\u6751"
    ],
    "wof:name":"Ziyuancun",
    "wof:placetype":"locality"
},
  "geometry": {"coordinates":[118.58313,31.26611],"type":"Point"}
}