{
  "type": "Feature",
  "properties": {
    "gn:admin1_code":"20.0",
    "gn:asciiname":"Gangta Gaoji Gao'er",
    "gn:country_code":"CN",
    "gn:dem":782,
    "gn:feature_class":"P",
    "gn:feature_code":"PPL",
    "gn:name":"Gangta Gaoji Gao\u2019er",
    "gn:population":0,
    "gn:timezone":"Asia/Shanghai",
    "iso:country":"CN",
    "name:und_x_variant":[
        "Gangta Gaoji Gao\u2019er"
    ],
    "name:zho_x_preferred":[
        "\u94a2\u5854\u9ad8\u5409\u9ad8\u5c14"
    ],
    "wof:name":"Gangta Gaoji Gao'er",
    "wof:placetype":"locality"
},
  "geometry": {"coordinates":[116.22707,48.86772],"type":"Point"}
}