{
  "type": "Feature",
  "properties": {
    "gn:admin1_code":"11.0",
    "gn:asciiname":"Guantangwei",
    "gn:country_code":"CN",
    "gn:dem":103,
    "gn:feature_class":"P",
    "gn:feature_code":"PPL",
    "gn:name":"Guantangwei",
    "gn:population":0,
    "gn:timezone":"Asia/Shanghai",
    "iso:country":"CN",
    "name:zho_x_preferred":[
        "\u5b98\u5802\u5c3e"
    ],
    "wof:name":"Guantangwei",
    "wof:placetype":"locality"
},
  "geometry": {"coordinates":[112.63234,26.69777],"type":"Point"}
}