{
  "type": "Feature",
  "properties": {
    "gn:admin1_code":"13.0",
    "gn:asciiname":"Kangtuokayi",
    "gn:country_code":"CN",
    "gn:dem":2324,
    "gn:feature_class":"P",
    "gn:feature_code":"PPL",
    "gn:name":"Kangtuokayi",
    "gn:population":0,
    "gn:timezone":"Asia/Urumqi",
    "iso:country":"CN",
    "name:zho_x_preferred":[
        "\u5eb7\u6258\u5580\u4f9d"
    ],
    "wof:name":"Kangtuokayi",
    "wof:placetype":"locality"
},
  "geometry": {"coordinates":[83.81307,36.96395],"type":"Point"}
}