{
  "type": "Feature",
  "properties": {
    "gn:admin1_code":"7.0",
    "gn:asciiname":"Guangliang",
    "gn:country_code":"CN",
    "gn:dem":105,
    "gn:feature_class":"P",
    "gn:feature_code":"PPL",
    "gn:name":"Guangliang",
    "gn:population":0,
    "gn:timezone":"Asia/Shanghai",
    "iso:country":"CN",
    "name:zho_x_preferred":[
        "\u5149\u4eae"
    ],
    "wof:name":"Guangliang",
    "wof:placetype":"locality"
},
  "geometry": {"coordinates":[117.06432,24.01362],"type":"Point"}
}