{
  "type": "Feature",
  "properties": {
    "gn:admin1_code":"15.0",
    "gn:asciiname":"Zhaizi",
    "gn:country_code":"CN",
    "gn:dem":1730,
    "gn:feature_class":"P",
    "gn:feature_code":"PPL",
    "gn:name":"Zhaizi",
    "gn:population":0,
    "gn:timezone":"Asia/Shanghai",
    "iso:country":"CN",
    "name:und_x_variant":[
        "Zhaizitan"
    ],
    "name:zho_x_preferred":[
        "\u5be8\u5b50"
    ],
    "wof:name":"Zhaizi",
    "wof:placetype":"locality"
},
  "geometry": {"coordinates":[102.319,38.0647],"type":"Point"}
}