{
  "type": "Feature",
  "properties": {
    "gn:admin1_code":"4.0",
    "gn:asciiname":"Longganqiao",
    "gn:country_code":"CN",
    "gn:dem":5,
    "gn:feature_class":"P",
    "gn:feature_code":"PPL",
    "gn:name":"Longganqiao",
    "gn:population":0,
    "gn:timezone":"Asia/Shanghai",
    "iso:country":"CN",
    "name:und_x_variant":[
        "\u9f99\u5e72\u6865"
    ],
    "name:zho_x_preferred":[
        "\u9f99\u5e72\u6865"
    ],
    "wof:name":"Longganqiao",
    "wof:placetype":"locality"
},
  "geometry": {"coordinates":[120.77670999999999,32.76926],"type":"Point"}
}