{
  "type": "Feature",
  "properties": {
    "gn:admin1_code":"29",
    "gn:asciiname":"Xiangpingshan",
    "gn:country_code":"CN",
    "gn:dem":1474,
    "gn:feature_class":"P",
    "gn:feature_code":"PPL",
    "gn:name":"Xiangpingshan",
    "gn:population":0,
    "gn:timezone":"Asia/Shanghai",
    "iso:country":"CN",
    "wof:name":"Xiangpingshan",
    "wof:placetype":"locality"
},
  "geometry": {"coordinates":[104.45972,23.29972],"type":"Point"}
}