{
  "type": "Feature",
  "properties": {
    "gn:admin1_code":"11.0",
    "gn:asciiname":"Yanluping",
    "gn:country_code":"CN",
    "gn:dem":292,
    "gn:feature_class":"P",
    "gn:feature_code":"PPL",
    "gn:name":"Yanluping",
    "gn:population":0,
    "gn:timezone":"Asia/Shanghai",
    "iso:country":"CN",
    "name:zho_x_preferred":[
        "\u5ca9\u8def\u576a"
    ],
    "wof:name":"Yanluping",
    "wof:placetype":"locality"
},
  "geometry": {"coordinates":[110.82023,28.23984],"type":"Point"}
}