{
  "type": "Feature",
  "properties": {
    "gn:admin1_code":"32.0",
    "gn:asciiname":"Tianwangmiao",
    "gn:country_code":"CN",
    "gn:dem":363,
    "gn:feature_class":"P",
    "gn:feature_code":"PPL",
    "gn:name":"Tianwangmiao",
    "gn:population":0,
    "gn:timezone":"Asia/Shanghai",
    "iso:country":"CN",
    "name:zho_x_preferred":[
        "\u5929\u738b\u5e99"
    ],
    "wof:name":"Tianwangmiao",
    "wof:placetype":"locality"
},
  "geometry": {"coordinates":[106.384,30.4767],"type":"Point"}
}