{
  "type": "Feature",
  "properties": {
    "gn:admin1_code":"20.0",
    "gn:asciiname":"Qianguaishang",
    "gn:country_code":"CN",
    "gn:dem":1060,
    "gn:feature_class":"P",
    "gn:feature_code":"PPL",
    "gn:name":"Qianguaishang",
    "gn:population":0,
    "gn:timezone":"Asia/Shanghai",
    "iso:country":"CN",
    "name:und_x_variant":[
        "\u524d\u62d0\u4e0a"
    ],
    "wof:name":"Qianguaishang",
    "wof:placetype":"locality"
},
  "geometry": {"coordinates":[111.39927,39.69649],"type":"Point"}
}