{
  "type": "Feature",
  "properties": {
    "gn:admin1_code":"29.0",
    "gn:asciiname":"Laolufang",
    "gn:country_code":"CN",
    "gn:dem":1944,
    "gn:feature_class":"P",
    "gn:feature_code":"PPL",
    "gn:name":"Laolufang",
    "gn:population":0,
    "gn:timezone":"Asia/Shanghai",
    "iso:country":"CN",
    "name:zho_x_preferred":[
        "\u8001\u7089\u623f"
    ],
    "wof:name":"Laolufang",
    "wof:placetype":"locality"
},
  "geometry": {"coordinates":[101.36199999999999,26.3126],"type":"Point"}
}