{
  "type": "Feature",
  "properties": {
    "gn:admin1_code":"26.0",
    "gn:asciiname":"Yingzhong",
    "gn:country_code":"CN",
    "gn:dem":466,
    "gn:feature_class":"P",
    "gn:feature_code":"PPL",
    "gn:name":"Yingzhong",
    "gn:population":0,
    "gn:timezone":"Asia/Shanghai",
    "iso:country":"CN",
    "name:und_x_variant":[
        "\u8425\u4e2d"
    ],
    "wof:name":"Yingzhong",
    "wof:placetype":"locality"
},
  "geometry": {"coordinates":[107.97733999999998,34.26094000000001],"type":"Point"}
}