{
  "type": "Feature",
  "properties": {
    "gn:admin1_code":"11.0",
    "gn:asciiname":"Meijitang",
    "gn:country_code":"CN",
    "gn:dem":69,
    "gn:feature_class":"P",
    "gn:feature_code":"PPL",
    "gn:name":"Meijitang",
    "gn:population":0,
    "gn:timezone":"Asia/Shanghai",
    "iso:country":"CN",
    "name:zho_x_preferred":[
        "\u7f8e\u57fa\u5802"
    ],
    "wof:name":"Meijitang",
    "wof:placetype":"locality"
},
  "geometry": {"coordinates":[112.42686999999999,26.96115],"type":"Point"}
}