{
  "type": "Feature",
  "properties": {
    "gn:admin1_code":"18",
    "gn:asciiname":"Chaofang",
    "gn:country_code":"CN",
    "gn:dem":1274,
    "gn:feature_class":"P",
    "gn:feature_code":"PPL",
    "gn:name":"Chaofang",
    "gn:population":0,
    "gn:timezone":"Asia/Shanghai",
    "iso:country":"CN",
    "name:zho_x_preferred":[
        "\u671d\u623f"
    ],
    "wof:name":"Chaofang",
    "wof:placetype":"locality"
},
  "geometry": {"coordinates":[106.211,28.2512],"type":"Point"}
}