{
  "type": "Feature",
  "properties": {
    "gn:admin1_code":"30.0",
    "gn:asciiname":"Jinxicun",
    "gn:country_code":"CN",
    "gn:dem":358,
    "gn:feature_class":"P",
    "gn:feature_code":"PPL",
    "gn:name":"Jinxicun",
    "gn:population":0,
    "gn:timezone":"Asia/Shanghai",
    "iso:country":"CN",
    "name:zho_x_preferred":[
        "\u91d1\u6eaa\u6751"
    ],
    "wof:name":"Jinxicun",
    "wof:placetype":"locality"
},
  "geometry": {"coordinates":[115.79733,24.71878],"type":"Point"}
}