{
  "type": "Feature",
  "properties": {
    "gn:admin1_code":"32.0",
    "gn:asciiname":"Moda",
    "gn:country_code":"CN",
    "gn:dem":3905,
    "gn:feature_class":"P",
    "gn:feature_code":"PPL",
    "gn:name":"Moda",
    "gn:population":0,
    "gn:timezone":"Asia/Shanghai",
    "iso:country":"CN",
    "name:zho_x_preferred":[
        "\u83ab\u8fbe"
    ],
    "wof:name":"Moda",
    "wof:placetype":"locality"
},
  "geometry": {"coordinates":[101.66503,29.50568],"type":"Point"}
}