{
  "type": "Feature",
  "properties": {
    "gn:admin1_code":"26.0",
    "gn:asciiname":"Laozhuangzi",
    "gn:country_code":"CN",
    "gn:dem":906,
    "gn:feature_class":"P",
    "gn:feature_code":"PPL",
    "gn:name":"Laozhuangzi",
    "gn:population":0,
    "gn:timezone":"Asia/Shanghai",
    "iso:country":"CN",
    "name:zho_x_preferred":[
        "\u8001\u5e84\u5b50"
    ],
    "wof:name":"Laozhuangzi",
    "wof:placetype":"locality"
},
  "geometry": {"coordinates":[108.71181,33.58696],"type":"Point"}
}