{
  "type": "Feature",
  "properties": {
    "gn:admin1_code":"29.0",
    "gn:asciiname":"Luyintang",
    "gn:country_code":"CN",
    "gn:dem":2176,
    "gn:feature_class":"P",
    "gn:feature_code":"PPL",
    "gn:name":"L\u00fcyintang",
    "gn:population":0,
    "gn:timezone":"Asia/Shanghai",
    "iso:country":"CN",
    "name:und_x_variant":[
        "L\u00fcyintang"
    ],
    "name:zho_x_preferred":[
        "\u7eff\u836b\u5858"
    ],
    "wof:name":"Luyintang",
    "wof:placetype":"locality"
},
  "geometry": {"coordinates":[99.0891,23.718],"type":"Point"}
}