{
  "type": "Feature",
  "properties": {
    "gn:admin1_code":"26.0",
    "gn:asciiname":"Longdonggou",
    "gn:country_code":"CN",
    "gn:dem":680,
    "gn:feature_class":"P",
    "gn:feature_code":"PPL",
    "gn:name":"Longdonggou",
    "gn:population":0,
    "gn:timezone":"Asia/Shanghai",
    "iso:country":"CN",
    "name:und_x_variant":[
        "\u9f99\u6d1e\u6c9f"
    ],
    "wof:name":"Longdonggou",
    "wof:placetype":"locality"
},
  "geometry": {"coordinates":[107.24097999999999,32.93652],"type":"Point"}
}