{
  "type": "Feature",
  "properties": {
    "gn:admin1_code":"4.0",
    "gn:asciiname":"Yuanjing",
    "gn:country_code":"CN",
    "gn:dem":1,
    "gn:feature_class":"P",
    "gn:feature_code":"PPL",
    "gn:name":"Yuanjing",
    "gn:population":0,
    "gn:timezone":"Asia/Shanghai",
    "iso:country":"CN",
    "name:zho_x_preferred":[
        "Yuanjing"
    ],
    "name:zho_x_variant":[
        "\u8881\u6cfe"
    ],
    "wof:name":"Yuanjing",
    "wof:placetype":"locality"
},
  "geometry": {"coordinates":[121.74481000000002,31.8223],"type":"Point"}
}