{
  "type": "Feature",
  "properties": {
    "gn:admin1_code":"3",
    "gn:asciiname":"Jintiangao",
    "gn:country_code":"CN",
    "gn:dem":176,
    "gn:feature_class":"P",
    "gn:feature_code":"PPL",
    "gn:name":"Jintiangao",
    "gn:population":0,
    "gn:timezone":"Asia/Shanghai",
    "iso:country":"CN",
    "name:zho_x_preferred":[
        "\u91d1\u7530\u9ad8"
    ],
    "wof:name":"Jintiangao",
    "wof:placetype":"locality"
},
  "geometry": {"coordinates":[115.018,25.2838],"type":"Point"}
}