{
  "type": "Feature",
  "properties": {
    "gn:admin1_code":"11.0",
    "gn:asciiname":"Wulishan",
    "gn:country_code":"CN",
    "gn:dem":348,
    "gn:feature_class":"P",
    "gn:feature_code":"PPL",
    "gn:name":"Wulishan",
    "gn:population":0,
    "gn:timezone":"Asia/Shanghai",
    "iso:country":"CN",
    "name:zho_x_preferred":[
        "\u4e94\u91cc\u5c71"
    ],
    "wof:name":"Wulishan",
    "wof:placetype":"locality"
},
  "geometry": {"coordinates":[110.77052999999999,28.53439],"type":"Point"}
}