{
  "type": "Feature",
  "properties": {
    "gn:admin1_code":"33.0",
    "gn:asciiname":"Shihuzhai",
    "gn:country_code":"CN",
    "gn:dem":253,
    "gn:feature_class":"P",
    "gn:feature_code":"PPL",
    "gn:name":"Shihuzhai",
    "gn:population":0,
    "gn:timezone":"Asia/Shanghai",
    "iso:country":"CN",
    "name:zho_x_preferred":[
        "\u77f3\u864e\u5be8"
    ],
    "wof:name":"Shihuzhai",
    "wof:placetype":"locality"
},
  "geometry": {"coordinates":[107.7697,29.99424],"type":"Point"}
}