{
  "type": "Feature",
  "properties": {
    "gn:admin1_code":"3.0",
    "gn:asciiname":"Yezhulong",
    "gn:country_code":"CN",
    "gn:dem":86,
    "gn:feature_class":"P",
    "gn:feature_code":"PPL",
    "gn:name":"Yezhulong",
    "gn:population":0,
    "gn:timezone":"Asia/Shanghai",
    "iso:country":"CN",
    "name:zho_x_preferred":[
        "\u591c\u73e0\u5784"
    ],
    "wof:name":"Yezhulong",
    "wof:placetype":"locality"
},
  "geometry": {"coordinates":[117.88245000000001,28.40842],"type":"Point"}
}