{
  "type": "Feature",
  "properties": {
    "gn:admin1_code":"3.0",
    "gn:asciiname":"Gantianmian",
    "gn:country_code":"CN",
    "gn:dem":185,
    "gn:feature_class":"P",
    "gn:feature_code":"PPL",
    "gn:name":"Gantianmian",
    "gn:population":0,
    "gn:timezone":"Asia/Shanghai",
    "iso:country":"CN",
    "name:und_x_variant":[
        "\u5e72\u7530\u9762"
    ],
    "wof:name":"Gantianmian",
    "wof:placetype":"locality"
},
  "geometry": {"coordinates":[115.79386,26.20191],"type":"Point"}
}