{
  "type": "Feature",
  "properties": {
    "gn:admin1_code":"19.0",
    "gn:asciiname":"Beixuemeicun",
    "gn:country_code":"CN",
    "gn:dem":60,
    "gn:feature_class":"P",
    "gn:feature_code":"PPL",
    "gn:name":"Beixuemeicun",
    "gn:population":0,
    "gn:timezone":"Asia/Shanghai",
    "iso:country":"CN",
    "name:zho_x_preferred":[
        "\u5317\u96ea\u6885\u6751"
    ],
    "wof:name":"Beixuemeicun",
    "wof:placetype":"locality"
},
  "geometry": {"coordinates":[123.392,41.2262],"type":"Point"}
}