{
  "type": "Feature",
  "properties": {
    "gn:admin1_code":"16",
    "gn:asciiname":"Quanfeng",
    "gn:country_code":"CN",
    "gn:dem":129,
    "gn:feature_class":"P",
    "gn:feature_code":"PPL",
    "gn:name":"Quanfeng",
    "gn:population":0,
    "gn:timezone":"Asia/Shanghai",
    "iso:country":"CN",
    "name:zho_x_preferred":[
        "\u5168\u51e4"
    ],
    "name:zho_x_variant":[
        "\u6cc9\u5cf0\u8857\u9053"
    ],
    "wof:name":"Quanfeng",
    "wof:placetype":"locality"
},
  "geometry": {"coordinates":[107.455,22.4078],"type":"Point"}
}