{
  "type": "Feature",
  "properties": {
    "gn:admin1_code":"19.0",
    "gn:asciiname":"Sandaoyanggou",
    "gn:country_code":"CN",
    "gn:dem":313,
    "gn:feature_class":"P",
    "gn:feature_code":"PPL",
    "gn:name":"Sandaoyanggou",
    "gn:population":0,
    "gn:timezone":"Asia/Shanghai",
    "iso:country":"CN",
    "name:zho_x_preferred":[
        "\u4e09\u9053\u592e\u6c9f"
    ],
    "wof:name":"Sandaoyanggou",
    "wof:placetype":"locality"
},
  "geometry": {"coordinates":[124.428,40.9981],"type":"Point"}
}