{
  "type": "Feature",
  "properties": {
    "gn:admin1_code":"25",
    "gn:asciiname":"Niejiazhuang",
    "gn:country_code":"CN",
    "gn:dem":213,
    "gn:feature_class":"P",
    "gn:feature_code":"PPL",
    "gn:name":"Niejiazhuang",
    "gn:population":0,
    "gn:timezone":"Asia/Shanghai",
    "iso:country":"CN",
    "name:zho_x_preferred":[
        "\u8042\u5bb6\u5e84"
    ],
    "wof:name":"Niejiazhuang",
    "wof:placetype":"locality"
},
  "geometry": {"coordinates":[118.56699999999999,36.2944],"type":"Point"}
}