{
  "type": "Feature",
  "properties": {
    "gn:admin1_code":"1.0",
    "gn:asciiname":"Yaoluocun",
    "gn:country_code":"CN",
    "gn:dem":1075,
    "gn:feature_class":"P",
    "gn:feature_code":"PPL",
    "gn:name":"Yaoluocun",
    "gn:population":0,
    "gn:timezone":"Asia/Shanghai",
    "iso:country":"CN",
    "name:und_x_variant":[
        "Yaoluoping"
    ],
    "name:zho_x_preferred":[
        "\u9e5e\u843d\u6751"
    ],
    "wof:name":"Yaoluocun",
    "wof:placetype":"locality"
},
  "geometry": {"coordinates":[116.0812,30.99479],"type":"Point"}
}