{
  "type": "Feature",
  "properties": {
    "gn:admin1_code":"2.0",
    "gn:asciiname":"Gaodishang",
    "gn:country_code":"CN",
    "gn:dem":4,
    "gn:feature_class":"P",
    "gn:feature_code":"PPL",
    "gn:name":"Gaodishang",
    "gn:population":0,
    "gn:timezone":"Asia/Shanghai",
    "iso:country":"CN",
    "name:und_x_variant":[
        "\u9ad8\u5730\u4e0a"
    ],
    "wof:name":"Gaodishang",
    "wof:placetype":"locality"
},
  "geometry": {"coordinates":[120.71811,30.58268],"type":"Point"}
}