{
  "type": "Feature",
  "properties": {
    "gn:admin1_code":"14.0",
    "gn:asciiname":"Dangtuocun",
    "gn:country_code":"CN",
    "gn:dem":3649,
    "gn:feature_class":"P",
    "gn:feature_code":"PPL",
    "gn:name":"Dangtuocun",
    "gn:population":0,
    "gn:timezone":"Asia/Urumqi",
    "iso:country":"CN",
    "name:zho_x_preferred":[
        "\u5f53\u59a5\u6751"
    ],
    "wof:name":"Dangtuocun",
    "wof:placetype":"locality"
},
  "geometry": {"coordinates":[96.90429,31.97706],"type":"Point"}
}