{
  "type": "Feature",
  "properties": {
    "gn:admin1_code":"14.0",
    "gn:asciiname":"Jinglincun",
    "gn:country_code":"CN",
    "gn:dem":3912,
    "gn:feature_class":"P",
    "gn:feature_code":"PPL",
    "gn:name":"Jinglincun",
    "gn:population":0,
    "gn:timezone":"Asia/Urumqi",
    "iso:country":"CN",
    "name:zho_x_preferred":[
        "\u4e95\u6797\u6751"
    ],
    "wof:name":"Jinglincun",
    "wof:placetype":"locality"
},
  "geometry": {"coordinates":[96.48818,31.25189],"type":"Point"}
}