{
  "type": "Feature",
  "properties": {
    "gn:admin1_code":"32.0",
    "gn:asciiname":"Luohanbao",
    "gn:country_code":"CN",
    "gn:dem":1295,
    "gn:feature_class":"P",
    "gn:feature_code":"PPL",
    "gn:name":"Luohanbao",
    "gn:population":0,
    "gn:timezone":"Asia/Shanghai",
    "iso:country":"CN",
    "name:zho_x_preferred":[
        "\u7f57\u6c49\u5305"
    ],
    "wof:name":"Luohanbao",
    "wof:placetype":"locality"
},
  "geometry": {"coordinates":[107.639,32.0497],"type":"Point"}
}