{
  "type": "Feature",
  "properties": {
    "gn:admin1_code":"2.0",
    "gn:asciiname":"Dongxibang",
    "gn:country_code":"CN",
    "gn:dem":4,
    "gn:feature_class":"P",
    "gn:feature_code":"PPL",
    "gn:name":"Dongxibang",
    "gn:population":0,
    "gn:timezone":"Asia/Shanghai",
    "iso:country":"CN",
    "name:und_x_variant":[
        "\u4e1c\u897f\u6d5c"
    ],
    "wof:name":"Dongxibang",
    "wof:placetype":"locality"
},
  "geometry": {"coordinates":[120.85557,30.89234],"type":"Point"}
}