{
  "type": "Feature",
  "properties": {
    "gn:admin1_code":"08",
    "gn:asciiname":"Tongjiangxiang",
    "gn:country_code":"CN",
    "gn:dem":42,
    "gn:feature_class":"P",
    "gn:feature_code":"PPL",
    "gn:name":"Tongjiangxiang",
    "gn:population":0,
    "gn:timezone":"Asia/Shanghai",
    "iso:country":"CN",
    "name:und_x_variant":[
        "Han-ch\u2019i-ho",
        "Tongjiangxiang"
    ],
    "wof:name":"Tongjiangxiang",
    "wof:placetype":"locality"
},
  "geometry": {"coordinates":[134.41056,48.35139],"type":"Point"}
}