{
  "type": "Feature",
  "properties": {
    "gn:admin1_code":"32.0",
    "gn:asciiname":"Tanguanyao",
    "gn:country_code":"CN",
    "gn:dem":1948,
    "gn:feature_class":"P",
    "gn:feature_code":"PPL",
    "gn:name":"Tanguanyao",
    "gn:population":0,
    "gn:timezone":"Asia/Shanghai",
    "iso:country":"CN",
    "name:zho_x_preferred":[
        "\u575b\u7f50\u7a91"
    ],
    "wof:name":"Tanguanyao",
    "wof:placetype":"locality"
},
  "geometry": {"coordinates":[102.292,26.3367],"type":"Point"}
}