{
  "type": "Feature",
  "properties": {
    "gn:admin1_code":"25",
    "gn:asciiname":"Mazhuangqian",
    "gn:country_code":"CN",
    "gn:dem":256,
    "gn:feature_class":"P",
    "gn:feature_code":"PPL",
    "gn:name":"Mazhuangqian",
    "gn:population":0,
    "gn:timezone":"Asia/Shanghai",
    "iso:country":"CN",
    "name:zho_x_preferred":[
        "\u9a6c\u5e84\u524d"
    ],
    "wof:name":"Mazhuangqian",
    "wof:placetype":"locality"
},
  "geometry": {"coordinates":[117.851,35.9811],"type":"Point"}
}