{
  "type": "Feature",
  "properties": {
    "gn:admin1_code":"3.0",
    "gn:asciiname":"Wenfeng",
    "gn:country_code":"CN",
    "gn:dem":48,
    "gn:feature_class":"P",
    "gn:feature_code":"PPLA3",
    "gn:name":"Wenfeng",
    "gn:population":0,
    "gn:timezone":"Asia/Shanghai",
    "iso:country":"CN",
    "name:und_x_variant":[
        "Kishui",
        "Jishui",
        "Chi-shui",
        "Kishuihsien",
        "Chi-shai-hsien",
        "Chi-shui-hsien-ch\u2019eng",
        "Wenfeng",
        "\u6587\u5cf0",
        "Wenfeng Zhen",
        "Jishui Xian",
        "\u6587\u5cf0\u9547",
        "\u5409\u6c34\u53bf"
    ],
    "wof:name":"Wenfeng",
    "wof:placetype":"locality"
},
  "geometry": {"coordinates":[115.11963,27.19899],"type":"Point"}
}