{
  "type": "Feature",
  "properties": {
    "gn:admin1_code":"3.0",
    "gn:asciiname":"Wenfeng",
    "gn:country_code":"CN",
    "gn:dem":48,
    "gn:feature_class":"P",
    "gn:feature_code":"PPLA3",
    "gn:name":"Wenfeng",
    "gn:population":0,
    "gn:timezone":"Asia/Shanghai",
    "iso:country":"CN",
    "name:ceb_x_preferred":[
        "Jishui Xian"
    ],
    "name:deu_x_preferred":[
        "Jishui"
    ],
    "name:fas_x_preferred":[
        "\u0634\u0647\u0631\u0633\u062a\u0627\u0646 \u062c\u06cc\u0634\u0648\u06cc"
    ],
    "name:jpn_x_preferred":[
        "\u5409\u6c34\u770c"
    ],
    "name:kor_x_preferred":[
        "\uc9c0\uc218\uc774\ud604"
    ],
    "name:nor_x_preferred":[
        "Jishui"
    ],
    "name:swe_x_preferred":[
        "Jishui"
    ],
    "name:und_x_variant":[
        "Kishui",
        "Chi-shui",
        "Kishuihsien",
        "Chi-shai-hsien",
        "Chi-shui-hsien-ch\u2019eng",
        "Wenfeng",
        "\u6587\u5cf0",
        "Wenfeng Zhen",
        "\u6587\u5cf0\u9547"
    ],
    "name:vie_x_preferred":[
        "C\u00e1t Th\u1ee7y"
    ],
    "name:zho_x_preferred":[
        "\u5409\u6c34\u53bf"
    ],
    "wof:name":"Wenfeng",
    "wof:placetype":"locality"
},
  "geometry": {"coordinates":[115.11963,27.19899],"type":"Point"}
}