{
  "type": "Feature",
  "properties": {
    "gn:admin1_code":"24.0",
    "gn:asciiname":"Weizecun",
    "gn:country_code":"CN",
    "gn:dem":954,
    "gn:feature_class":"P",
    "gn:feature_code":"PPL",
    "gn:name":"Weizecun",
    "gn:population":0,
    "gn:timezone":"Asia/Shanghai",
    "iso:country":"CN",
    "name:zho_x_preferred":[
        "\u82c7\u5219\u6751"
    ],
    "wof:name":"Weizecun",
    "wof:placetype":"locality"
},
  "geometry": {"coordinates":[113.52363,36.92063],"type":"Point"}
}