{
  "type": "Feature",
  "properties": {
    "gn:admin1_code":"15",
    "gn:asciiname":"Pujiahe",
    "gn:country_code":"CN",
    "gn:dem":1071,
    "gn:feature_class":"P",
    "gn:feature_code":"PPL",
    "gn:name":"Pujiahe",
    "gn:population":0,
    "gn:timezone":"Asia/Shanghai",
    "iso:country":"CN",
    "name:zho_x_preferred":[
        "\u84b2\u5bb6\u6cb3"
    ],
    "wof:name":"Pujiahe",
    "wof:placetype":"locality"
},
  "geometry": {"coordinates":[107.617,35.4685],"type":"Point"}
}