{
  "type": "Feature",
  "properties": {
    "gn:admin1_code":"3.0",
    "gn:asciiname":"Jintianjie",
    "gn:country_code":"CN",
    "gn:dem":48,
    "gn:feature_class":"P",
    "gn:feature_code":"PPL",
    "gn:name":"Jintianjie",
    "gn:population":0,
    "gn:timezone":"Asia/Shanghai",
    "iso:country":"CN",
    "name:zho_x_preferred":[
        "\u91d1\u7530\u8857"
    ],
    "wof:name":"Jintianjie",
    "wof:placetype":"locality"
},
  "geometry": {"coordinates":[115.083,28.0453],"type":"Point"}
}