{
  "type": "Feature",
  "properties": {
    "gn:admin1_code":"26.0",
    "gn:asciiname":"Wuguanyizhen",
    "gn:country_code":"CN",
    "gn:dem":820,
    "gn:feature_class":"P",
    "gn:feature_code":"PPL",
    "gn:name":"Wuguanyizhen",
    "gn:population":0,
    "gn:timezone":"Asia/Shanghai",
    "iso:country":"CN",
    "name:und_x_variant":[
        "\u6b66\u5173\u9a7f\u9547"
    ],
    "wof:name":"Wuguanyizhen",
    "wof:placetype":"locality"
},
  "geometry": {"coordinates":[106.9781,33.55173],"type":"Point"}
}