{
  "type": "Feature",
  "properties": {
    "gn:admin1_code":"29.0",
    "gn:asciiname":"Yinchanggou",
    "gn:country_code":"CN",
    "gn:dem":1506,
    "gn:feature_class":"P",
    "gn:feature_code":"PPL",
    "gn:name":"Yinchanggou",
    "gn:population":0,
    "gn:timezone":"Asia/Shanghai",
    "iso:country":"CN",
    "name:zho_x_preferred":[
        "\u94f6\u957f\u6c9f"
    ],
    "wof:name":"Yinchanggou",
    "wof:placetype":"locality"
},
  "geometry": {"coordinates":[104.991,27.6811],"type":"Point"}
}