{
  "type": "Feature",
  "properties": {
    "gn:admin1_code":"10",
    "gn:asciiname":"Changjia",
    "gn:country_code":"CN",
    "gn:dem":1445,
    "gn:feature_class":"P",
    "gn:feature_code":"PPL",
    "gn:name":"Changjia",
    "gn:population":0,
    "gn:timezone":"Asia/Shanghai",
    "iso:country":"CN",
    "name:zho_x_preferred":[
        "\u5e38\u5bb6"
    ],
    "wof:name":"Changjia",
    "wof:placetype":"locality"
},
  "geometry": {"coordinates":[114.25841,41.25778],"type":"Point"}
}