{
  "type": "Feature",
  "properties": {
    "gn:admin1_code":"3.0",
    "gn:asciiname":"Ruilan",
    "gn:country_code":"CN",
    "gn:dem":214,
    "gn:feature_class":"P",
    "gn:feature_code":"PPL",
    "gn:name":"Ruilan",
    "gn:population":0,
    "gn:timezone":"Asia/Shanghai",
    "iso:country":"CN",
    "name:und_x_variant":[
        "\u745e\u5170"
    ],
    "wof:name":"Ruilan",
    "wof:placetype":"locality"
},
  "geometry": {"coordinates":[116.03291000000002,25.94035],"type":"Point"}
}