{
  "type": "Feature",
  "properties": {
    "gn:admin1_code":"9.0",
    "gn:asciiname":"Caitun",
    "gn:country_code":"CN",
    "gn:dem":90,
    "gn:feature_class":"P",
    "gn:feature_code":"PPL",
    "gn:name":"Caitun",
    "gn:population":0,
    "gn:timezone":"Asia/Shanghai",
    "iso:country":"CN",
    "name:ceb_x_preferred":[
        "Caitun"
    ],
    "name:swe_x_preferred":[
        "Caitun"
    ],
    "name:zho_x_preferred":[
        "\u8521\u5c6f"
    ],
    "name:zho_x_variant":[
        "\u83dc\u5c6f\u9547"
    ],
    "wof:name":"Caitun",
    "wof:placetype":"locality"
},
  "geometry": {"coordinates":[114.25779,33.17912],"type":"Point"}
}