{
  "type": "Feature",
  "properties": {
    "gn:admin1_code":"25",
    "gn:asciiname":"Nanji",
    "gn:cc2":"CN",
    "gn:country_code":"CN",
    "gn:dem":4,
    "gn:feature_class":"P",
    "gn:feature_code":"PPL",
    "gn:name":"Nanji",
    "gn:population":0,
    "gn:timezone":"Asia/Shanghai",
    "iso:country":"CN",
    "name:und_x_variant":[
        "Nan-chi",
        "Nanji"
    ],
    "wof:name":"Nanji",
    "wof:placetype":"locality"
},
  "geometry": {"coordinates":[117.93333,37.76667],"type":"Point"}
}