{
  "type": "Feature",
  "properties": {
    "gn:admin1_code":"18",
    "gn:asciiname":"Tongguba",
    "gn:country_code":"CN",
    "gn:dem":1187,
    "gn:feature_class":"P",
    "gn:feature_code":"PPL",
    "gn:name":"Tongguba",
    "gn:population":0,
    "gn:timezone":"Asia/Shanghai",
    "iso:country":"CN",
    "name:zho_x_preferred":[
        "\u94dc\u9f13\u575d"
    ],
    "wof:name":"Tongguba",
    "wof:placetype":"locality"
},
  "geometry": {"coordinates":[106.92,27.1243],"type":"Point"}
}