{
  "type": "Feature",
  "properties": {
    "gn:admin1_code":"15.0",
    "gn:asciiname":"Zhang'ao",
    "gn:country_code":"CN",
    "gn:dem":1428,
    "gn:feature_class":"P",
    "gn:feature_code":"PPL",
    "gn:name":"Zhang\u2019ao",
    "gn:population":0,
    "gn:timezone":"Asia/Shanghai",
    "iso:country":"CN",
    "name:und_x_variant":[
        "Zhang\u2019ao"
    ],
    "name:zho_x_preferred":[
        "\u5f20\u5773"
    ],
    "wof:name":"Zhang'ao",
    "wof:placetype":"locality"
},
  "geometry": {"coordinates":[107.599,35.8276],"type":"Point"}
}