{
  "type": "Feature",
  "properties": {
    "gn:admin1_code":"16.0",
    "gn:asciiname":"Dongbu",
    "gn:country_code":"CN",
    "gn:dem":225,
    "gn:feature_class":"P",
    "gn:feature_code":"PPL",
    "gn:name":"Dongbu",
    "gn:population":0,
    "gn:timezone":"Asia/Shanghai",
    "iso:country":"CN",
    "name:zho_x_preferred":[
        "\u4e1c\u90e8"
    ],
    "wof:name":"Dongbu",
    "wof:placetype":"locality"
},
  "geometry": {"coordinates":[106.348,24.1758],"type":"Point"}
}