{
  "type": "Feature",
  "properties": {
    "gn:admin1_code":"02",
    "gn:asciiname":"Qingyun",
    "gn:cc2":"CN",
    "gn:country_code":"CN",
    "gn:dem":111,
    "gn:feature_class":"P",
    "gn:feature_code":"PPL",
    "gn:name":"Qingyun",
    "gn:population":0,
    "gn:timezone":"Asia/Shanghai",
    "iso:country":"CN",
    "name:und_x_variant":[
        "Ch\u2019ing-y\u00fcn-ch\u2019iao",
        "Ch\u2019ing-y\u00fcn",
        "Qingyun",
        "\u9752\u4e91"
    ],
    "wof:name":"Qingyun",
    "wof:placetype":"locality"
},
  "geometry": {"coordinates":[119.59166999999999,30.27],"type":"Point"}
}