{
  "type": "Feature",
  "properties": {
    "gn:admin1_code":"21.0",
    "gn:asciiname":"Yaoxian",
    "gn:country_code":"CN",
    "gn:dem":1779,
    "gn:feature_class":"P",
    "gn:feature_code":"PPL",
    "gn:name":"Yaoxian",
    "gn:population":0,
    "gn:timezone":"Asia/Shanghai",
    "iso:country":"CN",
    "name:und_x_variant":[
        "\u5d3e\u5c98"
    ],
    "name:zho_x_preferred":[
        "\u5d3e\u5c98"
    ],
    "wof:name":"Yaoxian",
    "wof:placetype":"locality"
},
  "geometry": {"coordinates":[106.53019,36.15075],"type":"Point"}
}