{
  "type": "Feature",
  "properties": {
    "gn:admin1_code":"14.0",
    "gn:asciiname":"Jangcangdo",
    "gn:country_code":"CN",
    "gn:dem":4915,
    "gn:feature_class":"P",
    "gn:feature_code":"PPL",
    "gn:name":"Jangcangdo",
    "gn:population":0,
    "gn:timezone":"Asia/Urumqi",
    "iso:country":"CN",
    "name:bod_x_preferred":[
        "Jangcangdo"
    ],
    "name:zho_x_preferred":[
        "Jiangcangduo"
    ],
    "name:zho_x_variant":[
        "\u6c5f\u4ed3\u591a"
    ],
    "wof:name":"Jangcangdo",
    "wof:placetype":"locality"
},
  "geometry": {"coordinates":[92.206,32.006],"type":"Point"}
}