{
  "type": "Feature",
  "properties": {
    "gn:admin1_code":"8.0",
    "gn:asciiname":"Lanhecun",
    "gn:country_code":"CN",
    "gn:dem":199,
    "gn:feature_class":"P",
    "gn:feature_code":"PPL",
    "gn:name":"Lanhecun",
    "gn:population":0,
    "gn:timezone":"Asia/Shanghai",
    "iso:country":"CN",
    "name:zho_x_preferred":[
        "\u5170\u6cb3\u6751"
    ],
    "wof:name":"Lanhecun",
    "wof:placetype":"locality"
},
  "geometry": {"coordinates":[127.91199,47.03009],"type":"Point"}
}