{
  "type": "Feature",
  "properties": {
    "gn:admin1_code":"12.0",
    "gn:asciiname":"Leidaling",
    "gn:country_code":"CN",
    "gn:dem":89,
    "gn:feature_class":"P",
    "gn:feature_code":"PPL",
    "gn:name":"Leidaling",
    "gn:population":0,
    "gn:timezone":"Asia/Shanghai",
    "iso:country":"CN",
    "name:zho_x_preferred":[
        "Leidaling"
    ],
    "name:zho_x_variant":[
        "\u96f7\u6253\u5cad"
    ],
    "wof:name":"Leidaling",
    "wof:placetype":"locality"
},
  "geometry": {"coordinates":[111.57626999999999,30.23353],"type":"Point"}
}