{
  "type": "Feature",
  "properties": {
    "gn:admin1_code":"4.0",
    "gn:asciiname":"Jiaxi",
    "gn:country_code":"CN",
    "gn:dem":3,
    "gn:feature_class":"P",
    "gn:feature_code":"PPL",
    "gn:name":"Jiaxi",
    "gn:population":0,
    "gn:timezone":"Asia/Shanghai",
    "iso:country":"CN",
    "name:ceb_x_preferred":[
        "Jiaxi"
    ],
    "name:swe_x_preferred":[
        "Jiaxi"
    ],
    "name:zho_x_preferred":[
        "\u8d3e\u897f"
    ],
    "name:zho_x_variant":[
        "\u7532\u897f\u9547"
    ],
    "wof:name":"Jiaxi",
    "wof:placetype":"locality"
},
  "geometry": {"coordinates":[119.57607,32.36621],"type":"Point"}
}