{
  "type": "Feature",
  "properties": {
    "gn:admin1_code":"7.0",
    "gn:asciiname":"Xinchenshan",
    "gn:country_code":"CN",
    "gn:dem":18,
    "gn:feature_class":"P",
    "gn:feature_code":"PPL",
    "gn:name":"Xinchenshan",
    "gn:population":0,
    "gn:timezone":"Asia/Shanghai",
    "iso:country":"CN",
    "name:zho_x_preferred":[
        "\u65b0\u9648\u5c71"
    ],
    "wof:name":"Xinchenshan",
    "wof:placetype":"locality"
},
  "geometry": {"coordinates":[118.48233,24.72614],"type":"Point"}
}