{
  "type": "Feature",
  "properties": {
    "gn:admin1_code":"14.0",
    "gn:asciiname":"Dangbu",
    "gn:country_code":"CN",
    "gn:dem":4050,
    "gn:feature_class":"P",
    "gn:feature_code":"PPL",
    "gn:name":"Dangbu",
    "gn:population":0,
    "gn:timezone":"Asia/Urumqi",
    "iso:country":"CN",
    "name:zho_x_preferred":[
        "\u5f53\u5e03"
    ],
    "wof:name":"Dangbu",
    "wof:placetype":"locality"
},
  "geometry": {"coordinates":[94.11443,30.30693],"type":"Point"}
}