{
  "type": "Feature",
  "properties": {
    "gn:admin1_code":"16.0",
    "gn:asciiname":"Guanxiao",
    "gn:country_code":"CN",
    "gn:dem":485,
    "gn:feature_class":"P",
    "gn:feature_code":"PPL",
    "gn:name":"Guanxiao",
    "gn:population":0,
    "gn:timezone":"Asia/Shanghai",
    "iso:country":"CN",
    "name:zho_x_preferred":[
        "\u7ba1\u8096"
    ],
    "wof:name":"Guanxiao",
    "wof:placetype":"locality"
},
  "geometry": {"coordinates":[105.497,24.8079],"type":"Point"}
}