{
  "type": "Feature",
  "properties": {
    "gn:admin1_code":"4.0",
    "gn:asciiname":"Chahecun",
    "gn:country_code":"CN",
    "gn:dem":25,
    "gn:feature_class":"P",
    "gn:feature_code":"PPL",
    "gn:name":"Chahecun",
    "gn:population":0,
    "gn:timezone":"Asia/Shanghai",
    "iso:country":"CN",
    "name:zho_x_preferred":[
        "\u5c94\u6cb3\u6751"
    ],
    "wof:name":"Chahecun",
    "wof:placetype":"locality"
},
  "geometry": {"coordinates":[117.89127999999999,34.54051],"type":"Point"}
}