{
  "type": "Feature",
  "properties": {
    "gn:admin1_code":"16.0",
    "gn:asciiname":"Beitian",
    "gn:country_code":"CN",
    "gn:dem":111,
    "gn:feature_class":"P",
    "gn:feature_code":"PPL",
    "gn:name":"Beitian",
    "gn:population":0,
    "gn:timezone":"Asia/Shanghai",
    "iso:country":"CN",
    "name:zho_x_preferred":[
        "\u7891\u7530"
    ],
    "wof:name":"Beitian",
    "wof:placetype":"locality"
},
  "geometry": {"coordinates":[109.408,24.5492],"type":"Point"}
}