{
  "type": "Feature",
  "properties": {
    "gn:admin1_code":"19.0",
    "gn:asciiname":"Huayushu",
    "gn:country_code":"CN",
    "gn:dem":611,
    "gn:feature_class":"P",
    "gn:feature_code":"PPL",
    "gn:name":"Huayushu",
    "gn:population":0,
    "gn:timezone":"Asia/Shanghai",
    "iso:country":"CN",
    "name:zho_x_preferred":[
        "\u6866\u6986\u6811"
    ],
    "wof:name":"Huayushu",
    "wof:placetype":"locality"
},
  "geometry": {"coordinates":[119.40260000000001,41.49381],"type":"Point"}
}