{
  "type": "Feature",
  "properties": {
    "gn:admin1_code":"3.0",
    "gn:asciiname":"Wenquancun",
    "gn:country_code":"CN",
    "gn:dem":34,
    "gn:feature_class":"P",
    "gn:feature_code":"PPL",
    "gn:name":"Wenquancun",
    "gn:population":0,
    "gn:timezone":"Asia/Shanghai",
    "iso:country":"CN",
    "name:und_x_variant":[
        "\u6e29\u6cc9\u6751"
    ],
    "wof:name":"Wenquancun",
    "wof:placetype":"locality"
},
  "geometry": {"coordinates":[116.22904,28.09603],"type":"Point"}
}