{
  "type": "Feature",
  "properties": {
    "gn:admin1_code":"15.0",
    "gn:asciiname":"Tianbuxiang",
    "gn:country_code":"CN",
    "gn:dem":1843,
    "gn:feature_class":"P",
    "gn:feature_code":"PPL",
    "gn:name":"Tianbuxiang",
    "gn:population":0,
    "gn:timezone":"Asia/Shanghai",
    "iso:country":"CN",
    "name:und_x_variant":[
        "\u7530\u5821\u4e61"
    ],
    "wof:name":"Tianbuxiang",
    "wof:placetype":"locality"
},
  "geometry": {"coordinates":[105.45972999999999,35.40846],"type":"Point"}
}