{
  "type": "Feature",
  "properties": {
    "gn:admin1_code":"7",
    "gn:asciiname":"Gangdong",
    "gn:country_code":"CN",
    "gn:dem":14,
    "gn:feature_class":"P",
    "gn:feature_code":"PPL",
    "gn:name":"Gangdong",
    "gn:population":0,
    "gn:timezone":"Asia/Shanghai",
    "iso:country":"CN",
    "name:und_x_variant":[
        "Chiang-tung",
        "Gangdong"
    ],
    "name:zho_x_preferred":[
        "\u6e2f\u4e1c"
    ],
    "wof:name":"Gangdong",
    "wof:placetype":"locality"
},
  "geometry": {"coordinates":[118.71705,24.71879],"type":"Point"}
}