{
  "type": "Feature",
  "properties": {
    "gn:admin1_code":"29",
    "gn:asciiname":"Bomo Zhongzhai",
    "gn:country_code":"CN",
    "gn:dem":1633,
    "gn:feature_class":"P",
    "gn:feature_code":"PPL",
    "gn:name":"Bomo Zhongzhai",
    "gn:population":0,
    "gn:timezone":"Asia/Shanghai",
    "iso:country":"CN",
    "name:zho_x_preferred":[
        "\u6ce2\u6469\u4e2d\u5be8"
    ],
    "wof:name":"Bomo Zhongzhai",
    "wof:placetype":"locality"
},
  "geometry": {"coordinates":[105.111,23.7003],"type":"Point"}
}