{
  "type": "Feature",
  "properties": {
    "gn:admin1_code":"4.0",
    "gn:asciiname":"Moyun",
    "gn:country_code":"CN",
    "gn:dem":31,
    "gn:feature_class":"P",
    "gn:feature_code":"PPL",
    "gn:name":"Moyun",
    "gn:population":0,
    "gn:timezone":"Asia/Shanghai",
    "iso:country":"CN",
    "name:zho_x_preferred":[
        "\u58a8\u4e91"
    ],
    "wof:name":"Moyun",
    "wof:placetype":"locality"
},
  "geometry": {"coordinates":[118.22685,34.27226],"type":"Point"}
}