{
  "type": "Feature",
  "properties": {
    "gn:admin1_code":"18.0",
    "gn:asciiname":"Wulian",
    "gn:country_code":"CN",
    "gn:dem":854,
    "gn:feature_class":"P",
    "gn:feature_code":"PPL",
    "gn:name":"Wulian",
    "gn:population":0,
    "gn:timezone":"Asia/Shanghai",
    "iso:country":"CN",
    "name:zho_x_preferred":[
        "\u5deb\u8138"
    ],
    "wof:name":"Wulian",
    "wof:placetype":"locality"
},
  "geometry": {"coordinates":[108.45,26.4761],"type":"Point"}
}