{
  "type": "Feature",
  "properties": {
    "gn:admin1_code":"29.0",
    "gn:asciiname":"Guojiazhai",
    "gn:country_code":"CN",
    "gn:dem":1825,
    "gn:feature_class":"P",
    "gn:feature_code":"PPL",
    "gn:name":"Guojiazhai",
    "gn:population":0,
    "gn:timezone":"Asia/Shanghai",
    "iso:country":"CN",
    "name:zho_x_preferred":[
        "\u90ed\u5bb6\u5be8"
    ],
    "wof:name":"Guojiazhai",
    "wof:placetype":"locality"
},
  "geometry": {"coordinates":[98.471,25.0684],"type":"Point"}
}