{
  "type": "Feature",
  "properties": {
    "gn:admin1_code":"3.0",
    "gn:asciiname":"Gumao",
    "gn:country_code":"CN",
    "gn:dem":159,
    "gn:feature_class":"P",
    "gn:feature_code":"PPL",
    "gn:name":"Gumao",
    "gn:population":0,
    "gn:timezone":"Asia/Shanghai",
    "iso:country":"CN",
    "name:und_x_variant":[
        "\u53e4\u8302"
    ],
    "wof:name":"Gumao",
    "wof:placetype":"locality"
},
  "geometry": {"coordinates":[115.34757999999999,26.12131],"type":"Point"}
}