{
  "type": "Feature",
  "properties": {
    "gn:admin1_code":"25",
    "gn:asciiname":"Nanyan Sicun",
    "gn:country_code":"CN",
    "gn:dem":388,
    "gn:feature_class":"P",
    "gn:feature_code":"PPL",
    "gn:name":"Nanyan Sicun",
    "gn:population":0,
    "gn:timezone":"Asia/Shanghai",
    "iso:country":"CN",
    "name:zho_x_preferred":[
        "\u5357\u5ca9\u56db\u6751"
    ],
    "wof:name":"Nanyan Sicun",
    "wof:placetype":"locality"
},
  "geometry": {"coordinates":[118.005,36.0943],"type":"Point"}
}