{
  "type": "Feature",
  "properties": {
    "gn:admin1_code":"20.0",
    "gn:asciiname":"Hougong Hudong",
    "gn:country_code":"CN",
    "gn:dem":1765,
    "gn:feature_class":"P",
    "gn:feature_code":"PPL",
    "gn:name":"Hougong Hudong",
    "gn:population":0,
    "gn:timezone":"Asia/Shanghai",
    "iso:country":"CN",
    "name:und_x_variant":[
        "\u540e\u516c\u5ffd\u6d1e"
    ],
    "wof:name":"Hougong Hudong",
    "wof:placetype":"locality"
},
  "geometry": {"coordinates":[110.44978999999999,41.0788],"type":"Point"}
}