{
  "type": "Feature",
  "properties": {
    "gn:admin1_code":"7.0",
    "gn:asciiname":"Zhangkeng",
    "gn:country_code":"CN",
    "gn:dem":137,
    "gn:feature_class":"P",
    "gn:feature_code":"PPL",
    "gn:name":"Zhangkeng",
    "gn:population":0,
    "gn:timezone":"Asia/Shanghai",
    "iso:country":"CN",
    "name:und_x_variant":[
        "\u5f20\u5751"
    ],
    "name:zho_x_preferred":[
        "\u5f20\u5751"
    ],
    "wof:name":"Zhangkeng",
    "wof:placetype":"locality"
},
  "geometry": {"coordinates":[118.2422,26.56308],"type":"Point"}
}