{
  "type": "Feature",
  "properties": {
    "gn:admin1_code":"15.0",
    "gn:asciiname":"Beizhan",
    "gn:country_code":"CN",
    "gn:dem":1736,
    "gn:feature_class":"P",
    "gn:feature_code":"PPL",
    "gn:name":"Beizhan",
    "gn:population":0,
    "gn:timezone":"Asia/Shanghai",
    "iso:country":"CN",
    "name:zho_x_preferred":[
        "\u5317\u7ad9"
    ],
    "wof:name":"Beizhan",
    "wof:placetype":"locality"
},
  "geometry": {"coordinates":[104.684,35.031],"type":"Point"}
}