{
  "type": "Feature",
  "properties": {
    "gn:admin1_code":"10",
    "gn:asciiname":"Taitou",
    "gn:country_code":"CN",
    "gn:dem":375,
    "gn:feature_class":"P",
    "gn:feature_code":"PPL",
    "gn:name":"Taitou",
    "gn:population":0,
    "gn:timezone":"Asia/Shanghai",
    "iso:country":"CN",
    "name:ceb_x_preferred":[
        "Taitou"
    ],
    "name:swe_x_preferred":[
        "Taitou"
    ],
    "name:zho_x_preferred":[
        "\u53f0\u5934"
    ],
    "name:zho_x_variant":[
        "\u53f0\u5934\u9547"
    ],
    "wof:name":"Taitou",
    "wof:placetype":"locality"
},
  "geometry": {"coordinates":[113.938,38.0168],"type":"Point"}
}