{
  "type": "Feature",
  "properties": {
    "gn:admin1_code":"2",
    "gn:asciiname":"Pingniao",
    "gn:country_code":"CN",
    "gn:dem":481,
    "gn:feature_class":"P",
    "gn:feature_code":"PPL",
    "gn:name":"Pingniao",
    "gn:population":0,
    "gn:timezone":"Asia/Shanghai",
    "iso:country":"CN",
    "name:zho_x_preferred":[
        "\u576a\u9e1f"
    ],
    "wof:name":"Pingniao",
    "wof:placetype":"locality"
},
  "geometry": {"coordinates":[119.02861,27.5175],"type":"Point"}
}