{
  "type": "Feature",
  "properties": {
    "gn:admin1_code":"8.0",
    "gn:asciiname":"Sanrenban Wudui",
    "gn:country_code":"CN",
    "gn:dem":109,
    "gn:feature_class":"P",
    "gn:feature_code":"PPLF",
    "gn:name":"Sanrenban Wudui",
    "gn:population":0,
    "gn:timezone":"Asia/Shanghai",
    "iso:country":"CN",
    "name:zho_x_preferred":[
        "\u4e09\u4eba\u73ed\u4e94\u961f"
    ],
    "wof:name":"Sanrenban Wudui",
    "wof:placetype":"locality"
},
  "geometry": {"coordinates":[132.00171,45.61858],"type":"Point"}
}