{
  "type": "Feature",
  "properties": {
    "gn:admin1_code":"15.0",
    "gn:asciiname":"Hejiawan",
    "gn:country_code":"CN",
    "gn:dem":986,
    "gn:feature_class":"P",
    "gn:feature_code":"PPL",
    "gn:name":"Hejiawan",
    "gn:population":0,
    "gn:timezone":"Asia/Shanghai",
    "iso:country":"CN",
    "name:und_x_variant":[
        "\u4f55\u5bb6\u6e7e"
    ],
    "wof:name":"Hejiawan",
    "wof:placetype":"locality"
},
  "geometry": {"coordinates":[105.68798,33.16001],"type":"Point"}
}