{
  "type": "Feature",
  "properties": {
    "gn:admin1_code":"24.0",
    "gn:asciiname":"Genuyancun",
    "gn:country_code":"CN",
    "gn:dem":1033,
    "gn:feature_class":"P",
    "gn:feature_code":"PPL",
    "gn:name":"Genuyancun",
    "gn:population":0,
    "gn:timezone":"Asia/Shanghai",
    "iso:country":"CN",
    "name:zho_x_preferred":[
        "\u572a\u52aa\u5895\u6751"
    ],
    "wof:name":"Genuyancun",
    "wof:placetype":"locality"
},
  "geometry": {"coordinates":[110.90422,37.80375],"type":"Point"}
}