{
  "type": "Feature",
  "properties": {
    "gn:admin1_code":"7",
    "gn:asciiname":"Dongpingyuan",
    "gn:country_code":"CN",
    "gn:dem":299,
    "gn:feature_class":"P",
    "gn:feature_code":"PPL",
    "gn:name":"Dongpingyuan",
    "gn:population":0,
    "gn:timezone":"Asia/Shanghai",
    "iso:country":"CN",
    "name:zho_x_preferred":[
        "\u4e1c\u576a\u9662"
    ],
    "wof:name":"Dongpingyuan",
    "wof:placetype":"locality"
},
  "geometry": {"coordinates":[119.1686,25.71422],"type":"Point"}
}