{
  "type": "Feature",
  "properties": {
    "gn:admin1_code":"9.0",
    "gn:asciiname":"Wangjicun",
    "gn:country_code":"CN",
    "gn:dem":104,
    "gn:feature_class":"P",
    "gn:feature_code":"PPL",
    "gn:name":"Wangjicun",
    "gn:population":0,
    "gn:timezone":"Asia/Shanghai",
    "iso:country":"CN",
    "name:und_x_variant":[
        "\u738b\u96c6\u6751"
    ],
    "name:zho_x_preferred":[
        "\u738b\u96c6\u6751"
    ],
    "wof:name":"Wangjicun",
    "wof:placetype":"locality"
},
  "geometry": {"coordinates":[113.26697,33.92992],"type":"Point"}
}