{
  "type": "Feature",
  "properties": {
    "gn:admin1_code":"18",
    "gn:asciiname":"Xuguan",
    "gn:country_code":"CN",
    "gn:dem":1247,
    "gn:feature_class":"P",
    "gn:feature_code":"PPL",
    "gn:name":"Xuguan",
    "gn:population":0,
    "gn:timezone":"Asia/Shanghai",
    "iso:country":"CN",
    "name:zho_x_preferred":[
        "\u8bb8\u5b98"
    ],
    "wof:name":"Xuguan",
    "wof:placetype":"locality"
},
  "geometry": {"coordinates":[106.126,26.1309],"type":"Point"}
}