{
  "type": "Feature",
  "properties": {
    "gn:admin1_code":"29",
    "gn:asciiname":"Pingsang",
    "gn:country_code":"CN",
    "gn:dem":889,
    "gn:feature_class":"P",
    "gn:feature_code":"PPL",
    "gn:name":"Pingsang",
    "gn:population":0,
    "gn:timezone":"Asia/Shanghai",
    "iso:country":"CN",
    "name:zho_x_preferred":[
        "\u5e73\u6851"
    ],
    "wof:name":"Pingsang",
    "wof:placetype":"locality"
},
  "geometry": {"coordinates":[105.604,23.6457],"type":"Point"}
}