{
  "type": "Feature",
  "properties": {
    "gn:admin1_code":"12.0",
    "gn:asciiname":"Lanchaigou",
    "gn:country_code":"CN",
    "gn:dem":871,
    "gn:feature_class":"P",
    "gn:feature_code":"PPL",
    "gn:name":"Lanchaigou",
    "gn:population":0,
    "gn:timezone":"Asia/Shanghai",
    "iso:country":"CN",
    "name:zho_x_preferred":[
        "\u70c2\u67f4\u6c9f"
    ],
    "wof:name":"Lanchaigou",
    "wof:placetype":"locality"
},
  "geometry": {"coordinates":[110.14646999999999,32.0058],"type":"Point"}
}