{
  "type": "Feature",
  "properties": {
    "gn:admin1_code":"01",
    "gn:asciiname":"Tanggou",
    "gn:country_code":"CN",
    "gn:dem":9,
    "gn:feature_class":"P",
    "gn:feature_code":"PPL",
    "gn:name":"Tanggou",
    "gn:population":0,
    "gn:timezone":"Asia/Shanghai",
    "iso:country":"CN",
    "name:und_x_variant":[
        "T\u2019ang-chia-kou",
        "T\u2019ang-kou",
        "Tangjiagou",
        "Tanggouzhen",
        "Tanggou Zhen",
        "\u6c64\u6c9f\u9547",
        "Tanggou"
    ],
    "name:zho_x_preferred":[
        "\u6c64\u6c9f"
    ],
    "wof:name":"Tanggou",
    "wof:placetype":"locality"
},
  "geometry": {"coordinates":[118.17843999999999,31.321],"type":"Point"}
}