{
  "type": "Feature",
  "properties": {
    "gn:admin1_code":"30",
    "gn:asciiname":"Damiaokeng",
    "gn:country_code":"CN",
    "gn:dem":371,
    "gn:feature_class":"P",
    "gn:feature_code":"PPL",
    "gn:name":"Damiaokeng",
    "gn:population":0,
    "gn:timezone":"Asia/Shanghai",
    "iso:country":"CN",
    "name:zho_x_preferred":[
        "\u5927\u5999\u5751"
    ],
    "wof:name":"Damiaokeng",
    "wof:placetype":"locality"
},
  "geometry": {"coordinates":[111.09611,22.72861],"type":"Point"}
}