{
  "type": "Feature",
  "properties": {
    "gn:admin1_code":"29.0",
    "gn:asciiname":"Luotaiyi",
    "gn:country_code":"CN",
    "gn:dem":1612,
    "gn:feature_class":"P",
    "gn:feature_code":"PPL",
    "gn:name":"Luotaiyi",
    "gn:population":0,
    "gn:timezone":"Asia/Shanghai",
    "iso:country":"CN",
    "name:zho_x_preferred":[
        "\u843d\u592a\u9091"
    ],
    "wof:name":"Luotaiyi",
    "wof:placetype":"locality"
},
  "geometry": {"coordinates":[103.93899999999999,23.7992],"type":"Point"}
}