{
  "type": "Feature",
  "properties": {
    "gn:admin1_code":"19.0",
    "gn:asciiname":"Banlashan",
    "gn:country_code":"CN",
    "gn:dem":210,
    "gn:feature_class":"P",
    "gn:feature_code":"PPL",
    "gn:name":"Banlashan",
    "gn:population":0,
    "gn:timezone":"Asia/Shanghai",
    "iso:country":"CN",
    "name:zho_x_preferred":[
        "\u534a\u62c9\u5c71"
    ],
    "wof:name":"Banlashan",
    "wof:placetype":"locality"
},
  "geometry": {"coordinates":[124.81798999999999,42.37712],"type":"Point"}
}