{
  "type": "Feature",
  "properties": {
    "gn:admin1_code":"11.0",
    "gn:asciiname":"Taoyuanping",
    "gn:country_code":"CN",
    "gn:dem":672,
    "gn:feature_class":"P",
    "gn:feature_code":"PPL",
    "gn:name":"Taoyuanping",
    "gn:population":0,
    "gn:timezone":"Asia/Shanghai",
    "iso:country":"CN",
    "name:zho_x_preferred":[
        "\u6843\u6e90\u576a"
    ],
    "wof:name":"Taoyuanping",
    "wof:placetype":"locality"
},
  "geometry": {"coordinates":[112.39659,25.21369],"type":"Point"}
}