{
  "type": "Feature",
  "properties": {
    "gn:admin1_code":"29.0",
    "gn:asciiname":"Ninong",
    "gn:country_code":"CN",
    "gn:dem":2202,
    "gn:feature_class":"P",
    "gn:feature_code":"PPL",
    "gn:name":"Ninong",
    "gn:population":0,
    "gn:timezone":"Asia/Shanghai",
    "iso:country":"CN",
    "name:zho_x_preferred":[
        "\u5c3c\u519c"
    ],
    "wof:name":"Ninong",
    "wof:placetype":"locality"
},
  "geometry": {"coordinates":[98.8535,28.3733],"type":"Point"}
}