{
  "type": "Feature",
  "properties": {
    "gn:admin1_code":"29.0",
    "gn:asciiname":"Xiaolongtan",
    "gn:country_code":"CN",
    "gn:dem":1790,
    "gn:feature_class":"P",
    "gn:feature_code":"PPL",
    "gn:name":"Xiaolongtan",
    "gn:population":0,
    "gn:timezone":"Asia/Shanghai",
    "iso:country":"CN",
    "name:zho_x_preferred":[
        "\u5c0f\u9f99\u6f6d"
    ],
    "wof:name":"Xiaolongtan",
    "wof:placetype":"locality"
},
  "geometry": {"coordinates":[103.559,26.141],"type":"Point"}
}