{
  "type": "Feature",
  "properties": {
    "gn:admin1_code":"16.0",
    "gn:asciiname":"Shanzhongcun",
    "gn:country_code":"CN",
    "gn:dem":139,
    "gn:feature_class":"P",
    "gn:feature_code":"PPL",
    "gn:name":"Shanzhongcun",
    "gn:population":0,
    "gn:timezone":"Asia/Shanghai",
    "iso:country":"CN",
    "name:zho_x_preferred":[
        "\u5584\u4e2d\u6751"
    ],
    "wof:name":"Shanzhongcun",
    "wof:placetype":"locality"
},
  "geometry": {"coordinates":[111.66500000000001,24.2631],"type":"Point"}
}