{
  "type": "Feature",
  "properties": {
    "gn:admin1_code":"24.0",
    "gn:asciiname":"Liuzhuang",
    "gn:country_code":"CN",
    "gn:dem":335,
    "gn:feature_class":"P",
    "gn:feature_code":"PPL",
    "gn:name":"Liuzhuang",
    "gn:population":0,
    "gn:timezone":"Asia/Shanghai",
    "iso:country":"CN",
    "name:zho_x_preferred":[
        "\u67f3\u5e84"
    ],
    "wof:name":"Liuzhuang",
    "wof:placetype":"locality"
},
  "geometry": {"coordinates":[111.80033,35.14457],"type":"Point"}
}