{
  "type": "Feature",
  "properties": {
    "gn:admin1_code":"07",
    "gn:asciiname":"Mayang",
    "gn:country_code":"CN",
    "gn:dem":511,
    "gn:feature_class":"P",
    "gn:feature_code":"PPL",
    "gn:name":"Mayang",
    "gn:population":0,
    "gn:timezone":"Asia/Shanghai",
    "iso:country":"CN",
    "name:zho_x_preferred":[
        "\u9a6c\u6d0b"
    ],
    "wof:name":"Mayang",
    "wof:placetype":"locality"
},
  "geometry": {"coordinates":[118.30500000000001,25.27778],"type":"Point"}
}