{
  "type": "Feature",
  "properties": {
    "gn:admin1_code":"15.0",
    "gn:asciiname":"Daya",
    "gn:country_code":"CN",
    "gn:dem":2845,
    "gn:feature_class":"P",
    "gn:feature_code":"PPL",
    "gn:name":"Daya",
    "gn:population":0,
    "gn:timezone":"Asia/Shanghai",
    "iso:country":"CN",
    "name:ceb_x_preferred":[
        "Daya"
    ],
    "name:heb_x_preferred":[
        "\u05d3\u05d9\u05d4"
    ],
    "name:pol_x_preferred":[
        "Daya"
    ],
    "name:swe_x_preferred":[
        "Daya"
    ],
    "name:vie_x_preferred":[
        "Daya"
    ],
    "name:zho_x_preferred":[
        "\u5927\u5d16"
    ],
    "wof:name":"Daya",
    "wof:placetype":"locality"
},
  "geometry": {"coordinates":[97.69580000000001,39.6538],"type":"Point"}
}