{
  "type": "Feature",
  "properties": {
    "gn:admin1_code":"32.0",
    "gn:asciiname":"Liutingmi",
    "gn:country_code":"CN",
    "gn:dem":3152,
    "gn:feature_class":"P",
    "gn:feature_code":"PPL",
    "gn:name":"Liutingmi",
    "gn:population":0,
    "gn:timezone":"Asia/Shanghai",
    "iso:country":"CN",
    "name:zho_x_preferred":[
        "\u5218\u505c\u7c73"
    ],
    "wof:name":"Liutingmi",
    "wof:placetype":"locality"
},
  "geometry": {"coordinates":[102.149,29.2623],"type":"Point"}
}