{
  "type": "Feature",
  "properties": {
    "gn:admin1_code":"12",
    "gn:asciiname":"Shagang",
    "gn:country_code":"CN",
    "gn:dem":29,
    "gn:feature_class":"P",
    "gn:feature_code":"PPLA4",
    "gn:name":"Shagang",
    "gn:population":0,
    "gn:timezone":"Asia/Shanghai",
    "iso:country":"CN",
    "name:und_x_variant":[
        "Sha-kang",
        "Shagang",
        "\u6c99\u5c97",
        "Shagang Zhen",
        "\u6c99\u5c97\u9547"
    ],
    "wof:name":"Shagang",
    "wof:placetype":"locality"
},
  "geometry": {"coordinates":[112.63333,30.06667],"type":"Point"}
}