{
  "type": "Feature",
  "properties": {
    "gn:admin1_code":"30.0",
    "gn:asciiname":"Litangwei",
    "gn:country_code":"CN",
    "gn:dem":330,
    "gn:feature_class":"P",
    "gn:feature_code":"PPL",
    "gn:name":"Litangwei",
    "gn:population":0,
    "gn:timezone":"Asia/Shanghai",
    "iso:country":"CN",
    "name:zho_x_preferred":[
        "\u91cc\u5858\u56f4"
    ],
    "wof:name":"Litangwei",
    "wof:placetype":"locality"
},
  "geometry": {"coordinates":[114.60901,25.09929],"type":"Point"}
}