{
  "type": "Feature",
  "properties": {
    "gn:admin1_code":"15.0",
    "gn:asciiname":"Lixiancun",
    "gn:country_code":"CN",
    "gn:dem":1933,
    "gn:feature_class":"P",
    "gn:feature_code":"PPL",
    "gn:name":"Lixiancun",
    "gn:population":0,
    "gn:timezone":"Asia/Shanghai",
    "iso:country":"CN",
    "name:und_x_variant":[
        "\u674e\u5c98\u6751"
    ],
    "wof:name":"Lixiancun",
    "wof:placetype":"locality"
},
  "geometry": {"coordinates":[105.41905,35.31989],"type":"Point"}
}