{
  "type": "Feature",
  "properties": {
    "gn:admin1_code":"18.0",
    "gn:asciiname":"Dangkai",
    "gn:country_code":"CN",
    "gn:dem":901,
    "gn:feature_class":"P",
    "gn:feature_code":"PPL",
    "gn:name":"Dangkai",
    "gn:population":0,
    "gn:timezone":"Asia/Shanghai",
    "iso:country":"CN",
    "name:zho_x_preferred":[
        "\u515a\u5f00"
    ],
    "wof:name":"Dangkai",
    "wof:placetype":"locality"
},
  "geometry": {"coordinates":[108.44799999999999,26.6201],"type":"Point"}
}