{
  "type": "Feature",
  "properties": {
    "gn:admin1_code":"02",
    "gn:asciiname":"Sanqiaobu",
    "gn:cc2":"CN",
    "gn:country_code":"CN",
    "gn:dem":9,
    "gn:feature_class":"P",
    "gn:feature_code":"PPL",
    "gn:name":"Sanqiaobu",
    "gn:population":0,
    "gn:timezone":"Asia/Shanghai",
    "iso:country":"CN",
    "name:und_x_variant":[
        "San-ch\u2019iao",
        "Sanqiao",
        "Sanqiaobu",
        "\u4e09\u6865\u57e0"
    ],
    "wof:name":"Sanqiaobu",
    "wof:placetype":"locality"
},
  "geometry": {"coordinates":[119.95305999999999,30.57833],"type":"Point"}
}