{
  "type": "Feature",
  "properties": {
    "gn:admin1_code":"1.0",
    "gn:asciiname":"Chugangcun",
    "gn:country_code":"CN",
    "gn:dem":367,
    "gn:feature_class":"P",
    "gn:feature_code":"PPL",
    "gn:name":"Chugangcun",
    "gn:population":0,
    "gn:timezone":"Asia/Shanghai",
    "iso:country":"CN",
    "name:zho_x_preferred":[
        "\u521d\u6e2f\u6751"
    ],
    "wof:name":"Chugangcun",
    "wof:placetype":"locality"
},
  "geometry": {"coordinates":[118.7085,29.74371],"type":"Point"}
}