{
  "type": "Feature",
  "properties": {
    "gn:admin1_code":"15.0",
    "gn:asciiname":"Baluzhuang",
    "gn:country_code":"CN",
    "gn:dem":2415,
    "gn:feature_class":"P",
    "gn:feature_code":"PPL",
    "gn:name":"Baluzhuang",
    "gn:population":0,
    "gn:timezone":"Asia/Shanghai",
    "iso:country":"CN",
    "name:und_x_variant":[
        "\u82ad\u82a6\u5e84"
    ],
    "wof:name":"Baluzhuang",
    "wof:placetype":"locality"
},
  "geometry": {"coordinates":[103.95859,35.06674],"type":"Point"}
}