{
  "type": "Feature",
  "properties": {
    "gn:admin1_code":"11.0",
    "gn:asciiname":"Qingshuitan",
    "gn:country_code":"CN",
    "gn:dem":755,
    "gn:feature_class":"P",
    "gn:feature_code":"PPL",
    "gn:name":"Qingshuitan",
    "gn:population":0,
    "gn:timezone":"Asia/Shanghai",
    "iso:country":"CN",
    "name:zho_x_preferred":[
        "\u9752\u6c34\u6ee9"
    ],
    "wof:name":"Qingshuitan",
    "wof:placetype":"locality"
},
  "geometry": {"coordinates":[109.88283,29.66877],"type":"Point"}
}