{
  "type": "Feature",
  "properties": {
    "gn:admin1_code":"32.0",
    "gn:asciiname":"Wanghe",
    "gn:country_code":"CN",
    "gn:dem":660,
    "gn:feature_class":"P",
    "gn:feature_code":"PPL",
    "gn:name":"Wanghe",
    "gn:population":0,
    "gn:timezone":"Asia/Shanghai",
    "iso:country":"CN",
    "name:zho_x_preferred":[
        "\u738b\u6cb3"
    ],
    "wof:name":"Wanghe",
    "wof:placetype":"locality"
},
  "geometry": {"coordinates":[105.25700000000001,31.9982],"type":"Point"}
}