{
  "type": "Feature",
  "properties": {
    "gn:admin1_code":"9.0",
    "gn:asciiname":"Zhonglou",
    "gn:country_code":"CN",
    "gn:dem":62,
    "gn:feature_class":"P",
    "gn:feature_code":"PPL",
    "gn:name":"Zhonglou",
    "gn:population":0,
    "gn:timezone":"Asia/Shanghai",
    "iso:country":"CN",
    "name:zho_x_preferred":[
        "\u949f\u697c"
    ],
    "wof:name":"Zhonglou",
    "wof:placetype":"locality"
},
  "geometry": {"coordinates":[114.19840000000001,32.9986],"type":"Point"}
}