{
  "type": "Feature",
  "properties": {
    "gn:admin1_code":"26.0",
    "gn:asciiname":"Chengxicun",
    "gn:country_code":"CN",
    "gn:dem":521,
    "gn:feature_class":"P",
    "gn:feature_code":"PPL",
    "gn:name":"Chengxicun",
    "gn:population":0,
    "gn:timezone":"Asia/Shanghai",
    "iso:country":"CN",
    "name:und_x_variant":[
        "\u57ce\u897f\u6751"
    ],
    "wof:name":"Chengxicun",
    "wof:placetype":"locality"
},
  "geometry": {"coordinates":[109.31663,34.9229],"type":"Point"}
}