{
  "type": "Feature",
  "properties": {
    "gn:admin1_code":"19.0",
    "gn:asciiname":"Ba'erhugou",
    "gn:country_code":"CN",
    "gn:dem":45,
    "gn:feature_class":"P",
    "gn:feature_code":"PPL",
    "gn:name":"Ba\u2019erhugou",
    "gn:population":0,
    "gn:timezone":"Asia/Shanghai",
    "iso:country":"CN",
    "name:und_x_variant":[
        "Ba\u2019erhugou"
    ],
    "name:zho_x_preferred":[
        "\u5df4\u5c14\u864e\u6c9f"
    ],
    "wof:name":"Ba'erhugou",
    "wof:placetype":"locality"
},
  "geometry": {"coordinates":[121.83199999999999,39.6909],"type":"Point"}
}