{
  "type": "Feature",
  "properties": {
    "gn:admin1_code":"19.0",
    "gn:asciiname":"Houyaowangmiao",
    "gn:country_code":"CN",
    "gn:dem":101,
    "gn:feature_class":"P",
    "gn:feature_code":"PPL",
    "gn:name":"Houyaowangmiao",
    "gn:population":0,
    "gn:timezone":"Asia/Shanghai",
    "iso:country":"CN",
    "name:und_x_variant":[
        "\u540e\u836f\u738b\u5e99"
    ],
    "name:zho_x_preferred":[
        "\u540e\u836f\u738b\u5e99"
    ],
    "wof:name":"Houyaowangmiao",
    "wof:placetype":"locality"
},
  "geometry": {"coordinates":[121.39027,41.70133],"type":"Point"}
}