{
  "type": "Feature",
  "properties": {
    "gn:admin1_code":"11.0",
    "gn:asciiname":"Shenzhoujie",
    "gn:country_code":"CN",
    "gn:dem":689,
    "gn:feature_class":"P",
    "gn:feature_code":"PPL",
    "gn:name":"Shenzhoujie",
    "gn:population":0,
    "gn:timezone":"Asia/Shanghai",
    "iso:country":"CN",
    "name:zho_x_preferred":[
        "\u795e\u5dde\u754c"
    ],
    "name:zho_x_variant":[
        "\u795e\u6d32\u754c"
    ],
    "wof:name":"Shenzhoujie",
    "wof:placetype":"locality"
},
  "geometry": {"coordinates":[109.82425000000001,29.54805],"type":"Point"}
}