{
  "type": "Feature",
  "properties": {
    "gn:admin1_code":"29.0",
    "gn:asciiname":"Juecaiping",
    "gn:country_code":"CN",
    "gn:dem":2532,
    "gn:feature_class":"P",
    "gn:feature_code":"PPL",
    "gn:name":"Juecaiping",
    "gn:population":0,
    "gn:timezone":"Asia/Shanghai",
    "iso:country":"CN",
    "name:zho_x_preferred":[
        "\u8568\u83dc\u576a"
    ],
    "wof:name":"Juecaiping",
    "wof:placetype":"locality"
},
  "geometry": {"coordinates":[99.6815,26.093],"type":"Point"}
}