{
  "type": "Feature",
  "properties": {
    "gn:admin1_code":"29.0",
    "gn:asciiname":"Huangcaoshan",
    "gn:country_code":"CN",
    "gn:dem":2016,
    "gn:feature_class":"P",
    "gn:feature_code":"PPL",
    "gn:name":"Huangcaoshan",
    "gn:population":0,
    "gn:timezone":"Asia/Shanghai",
    "iso:country":"CN",
    "name:zho_x_preferred":[
        "\u9ec4\u8349\u5c71"
    ],
    "wof:name":"Huangcaoshan",
    "wof:placetype":"locality"
},
  "geometry": {"coordinates":[99.6007,24.149],"type":"Point"}
}