{
  "type": "Feature",
  "properties": {
    "gn:admin1_code":"18",
    "gn:asciiname":"Muzong",
    "gn:country_code":"CN",
    "gn:dem":1512,
    "gn:feature_class":"P",
    "gn:feature_code":"PPL",
    "gn:name":"Muzong",
    "gn:population":0,
    "gn:timezone":"Asia/Shanghai",
    "iso:country":"CN",
    "name:deu_x_preferred":[
        "Muzong"
    ],
    "name:nld_x_preferred":[
        "Muzong"
    ],
    "name:zho_x_preferred":[
        "\u6728\u5b97"
    ],
    "wof:name":"Muzong",
    "wof:placetype":"locality"
},
  "geometry": {"coordinates":[104.495,26.0129],"type":"Point"}
}