{
  "type": "Feature",
  "properties": {
    "gn:admin1_code":"25.0",
    "gn:asciiname":"Beixugezhuang",
    "gn:country_code":"CN",
    "gn:dem":125,
    "gn:feature_class":"P",
    "gn:feature_code":"PPL",
    "gn:name":"Beixugezhuang",
    "gn:population":0,
    "gn:timezone":"Asia/Shanghai",
    "iso:country":"CN",
    "name:zho_x_preferred":[
        "\u5317\u5f90\u683c\u5e84"
    ],
    "wof:name":"Beixugezhuang",
    "wof:placetype":"locality"
},
  "geometry": {"coordinates":[121.45726999999999,37.1824],"type":"Point"}
}