{
  "type": "Feature",
  "properties": {
    "gn:admin1_code":"1.0",
    "gn:asciiname":"Yangjiagangcun",
    "gn:country_code":"CN",
    "gn:dem":24,
    "gn:feature_class":"P",
    "gn:feature_code":"PPL",
    "gn:name":"Yangjiagangcun",
    "gn:population":0,
    "gn:timezone":"Asia/Shanghai",
    "iso:country":"CN",
    "name:zho_x_preferred":[
        "\u6768\u5bb6\u5c97\u6751"
    ],
    "wof:name":"Yangjiagangcun",
    "wof:placetype":"locality"
},
  "geometry": {"coordinates":[116.35872999999999,32.62823],"type":"Point"}
}