{
  "type": "Feature",
  "properties": {
    "gn:admin1_code":"31.0",
    "gn:asciiname":"Yadai",
    "gn:country_code":"CN",
    "gn:dem":352,
    "gn:feature_class":"P",
    "gn:feature_code":"PPL",
    "gn:name":"Yadai",
    "gn:population":0,
    "gn:timezone":"Asia/Shanghai",
    "iso:country":"CN",
    "name:und_x_variant":[
        "\u7259\u4ee3"
    ],
    "name:zho_x_preferred":[
        "\u7259\u4ee3"
    ],
    "wof:name":"Yadai",
    "wof:placetype":"locality"
},
  "geometry": {"coordinates":[109.77401,18.87836],"type":"Point"}
}