{
  "type": "Feature",
  "properties": {
    "gn:admin1_code":"32.0",
    "gn:asciiname":"Yingui",
    "gn:country_code":"CN",
    "gn:dem":3324,
    "gn:feature_class":"P",
    "gn:feature_code":"PPL",
    "gn:name":"Yingui",
    "gn:population":0,
    "gn:timezone":"Asia/Shanghai",
    "iso:country":"CN",
    "name:zho_x_preferred":[
        "\u56e0\u5f52"
    ],
    "wof:name":"Yingui",
    "wof:placetype":"locality"
},
  "geometry": {"coordinates":[99.2282,28.4177],"type":"Point"}
}