{
  "type": "Feature",
  "properties": {
    "gn:admin1_code":"3.0",
    "gn:asciiname":"Cangxiacun",
    "gn:country_code":"CN",
    "gn:dem":45,
    "gn:feature_class":"P",
    "gn:feature_code":"PPL",
    "gn:name":"Cangxiacun",
    "gn:population":0,
    "gn:timezone":"Asia/Shanghai",
    "iso:country":"CN",
    "name:zho_x_preferred":[
        "\u4ed3\u4e0b\u6751"
    ],
    "wof:name":"Cangxiacun",
    "wof:placetype":"locality"
},
  "geometry": {"coordinates":[117.511,28.8682],"type":"Point"}
}