{
  "type": "Feature",
  "properties": {
    "gn:admin1_code":"32.0",
    "gn:asciiname":"Datonggou",
    "gn:country_code":"CN",
    "gn:dem":1029,
    "gn:feature_class":"P",
    "gn:feature_code":"PPL",
    "gn:name":"Datonggou",
    "gn:population":0,
    "gn:timezone":"Asia/Shanghai",
    "iso:country":"CN",
    "name:und_x_variant":[
        "\u5927\u540c\u6c9f"
    ],
    "wof:name":"Datonggou",
    "wof:placetype":"locality"
},
  "geometry": {"coordinates":[106.91271,32.59356],"type":"Point"}
}