{
  "type": "Feature",
  "properties": {
    "gn:admin1_code":"26.0",
    "gn:asciiname":"Yushuguacun",
    "gn:country_code":"CN",
    "gn:dem":1500,
    "gn:feature_class":"P",
    "gn:feature_code":"PPL",
    "gn:name":"Yushuguacun",
    "gn:population":0,
    "gn:timezone":"Asia/Shanghai",
    "iso:country":"CN",
    "name:zho_x_preferred":[
        "\u6986\u6811\u576c\u6751"
    ],
    "wof:name":"Yushuguacun",
    "wof:placetype":"locality"
},
  "geometry": {"coordinates":[108.318,36.6056],"type":"Point"}
}