{
  "type": "Feature",
  "properties": {
    "gn:admin1_code":"16.0",
    "gn:asciiname":"Nongzhuxia",
    "gn:country_code":"CN",
    "gn:dem":383,
    "gn:feature_class":"P",
    "gn:feature_code":"PPL",
    "gn:name":"Nongzhuxia",
    "gn:population":0,
    "gn:timezone":"Asia/Shanghai",
    "iso:country":"CN",
    "name:zho_x_preferred":[
        "\u5f04\u73e0\u4e0b"
    ],
    "wof:name":"Nongzhuxia",
    "wof:placetype":"locality"
},
  "geometry": {"coordinates":[108.211,23.9804],"type":"Point"}
}