{
  "type": "Feature",
  "properties": {
    "gn:admin1_code":"15.0",
    "gn:asciiname":"Dahaigou",
    "gn:country_code":"CN",
    "gn:dem":2242,
    "gn:feature_class":"P",
    "gn:feature_code":"PPL",
    "gn:name":"Dahaigou",
    "gn:population":0,
    "gn:timezone":"Asia/Shanghai",
    "iso:country":"CN",
    "name:zho_x_preferred":[
        "\u5927\u6d77\u6c9f"
    ],
    "wof:name":"Dahaigou",
    "wof:placetype":"locality"
},
  "geometry": {"coordinates":[104.24375999999999,33.62016],"type":"Point"}
}