{
  "type": "Feature",
  "properties": {
    "gn:admin1_code":"32.0",
    "gn:asciiname":"Zhicaokao",
    "gn:country_code":"CN",
    "gn:dem":3888,
    "gn:feature_class":"P",
    "gn:feature_code":"PPL",
    "gn:name":"Zhicaokao",
    "gn:population":0,
    "gn:timezone":"Asia/Shanghai",
    "iso:country":"CN",
    "name:zho_x_preferred":[
        "\u652f\u66f9\u8003"
    ],
    "wof:name":"Zhicaokao",
    "wof:placetype":"locality"
},
  "geometry": {"coordinates":[99.5916,28.8462],"type":"Point"}
}