{
  "type": "Feature",
  "properties": {
    "gn:admin1_code":"5.0",
    "gn:asciiname":"Yaojingzicun",
    "gn:country_code":"CN",
    "gn:dem":148,
    "gn:feature_class":"P",
    "gn:feature_code":"PPL",
    "gn:name":"Yaojingzicun",
    "gn:population":0,
    "gn:timezone":"Asia/Shanghai",
    "iso:country":"CN",
    "name:zho_x_preferred":[
        "\u8170\u4e95\u5b50\u6751"
    ],
    "wof:name":"Yaojingzicun",
    "wof:placetype":"locality"
},
  "geometry": {"coordinates":[123.60593,44.57634],"type":"Point"}
}