{
  "type": "Feature",
  "properties": {
    "gn:admin1_code":"29.0",
    "gn:asciiname":"Houziyan",
    "gn:country_code":"CN",
    "gn:dem":2262,
    "gn:feature_class":"P",
    "gn:feature_code":"PPL",
    "gn:name":"Houziyan",
    "gn:population":0,
    "gn:timezone":"Asia/Shanghai",
    "iso:country":"CN",
    "name:zho_x_preferred":[
        "\u7334\u5b50\u5ca9"
    ],
    "wof:name":"Houziyan",
    "wof:placetype":"locality"
},
  "geometry": {"coordinates":[99.075,26.5218],"type":"Point"}
}