{
  "type": "Feature",
  "properties": {
    "gn:admin1_code":"12.0",
    "gn:asciiname":"Kuzhu'ao",
    "gn:country_code":"CN",
    "gn:dem":87,
    "gn:feature_class":"P",
    "gn:feature_code":"PPL",
    "gn:name":"Kuzhu\u2019ao",
    "gn:population":0,
    "gn:timezone":"Asia/Shanghai",
    "iso:country":"CN",
    "name:zho_x_preferred":[
        "Kuzhu\u2019ao"
    ],
    "name:zho_x_variant":[
        "\u82e6\u7af9\u51f9"
    ],
    "wof:name":"Kuzhu'ao",
    "wof:placetype":"locality"
},
  "geometry": {"coordinates":[113.22332,31.00754],"type":"Point"}
}