{
  "type": "Feature",
  "properties": {
    "gn:admin1_code":"29.0",
    "gn:asciiname":"Shuangguanbu",
    "gn:country_code":"CN",
    "gn:dem":2048,
    "gn:feature_class":"P",
    "gn:feature_code":"PPL",
    "gn:name":"Shuangguanbu",
    "gn:population":0,
    "gn:timezone":"Asia/Shanghai",
    "iso:country":"CN",
    "name:zho_x_preferred":[
        "\u53cc\u5b98\u5821"
    ],
    "wof:name":"Shuangguanbu",
    "wof:placetype":"locality"
},
  "geometry": {"coordinates":[103.547,25.1688],"type":"Point"}
}