{
  "type": "Feature",
  "properties": {
    "gn:admin1_code":"32.0",
    "gn:asciiname":"Fengping",
    "gn:country_code":"CN",
    "gn:dem":316,
    "gn:feature_class":"P",
    "gn:feature_code":"PPL",
    "gn:name":"Fengping",
    "gn:population":0,
    "gn:timezone":"Asia/Shanghai",
    "iso:country":"CN",
    "name:zho_x_preferred":[
        "\u51af\u576a"
    ],
    "wof:name":"Fengping",
    "wof:placetype":"locality"
},
  "geometry": {"coordinates":[105.21535,29.16123],"type":"Point"}
}