{
  "type": "Feature",
  "properties": {
    "gn:admin1_code":"12.0",
    "gn:asciiname":"Xiaodongpo",
    "gn:country_code":"CN",
    "gn:dem":1344,
    "gn:feature_class":"P",
    "gn:feature_code":"PPL",
    "gn:name":"Xiaodongpo",
    "gn:population":0,
    "gn:timezone":"Asia/Shanghai",
    "iso:country":"CN",
    "name:zho_x_preferred":[
        "\u785d\u6d1e\u5761"
    ],
    "wof:name":"Xiaodongpo",
    "wof:placetype":"locality"
},
  "geometry": {"coordinates":[110.36060999999999,30.35969],"type":"Point"}
}