{
  "type": "Feature",
  "properties": {
    "gn:admin1_code":"1.0",
    "gn:asciiname":"Chengshulincun",
    "gn:country_code":"CN",
    "gn:dem":352,
    "gn:feature_class":"P",
    "gn:feature_code":"PPL",
    "gn:name":"Chengshulincun",
    "gn:population":0,
    "gn:timezone":"Asia/Shanghai",
    "iso:country":"CN",
    "name:zho_x_preferred":[
        "\u67fd\u6811\u6797\u6751"
    ],
    "wof:name":"Chengshulincun",
    "wof:placetype":"locality"
},
  "geometry": {"coordinates":[116.01564999999999,31.18337],"type":"Point"}
}