{
  "type": "Feature",
  "properties": {
    "gn:admin1_code":"20.0",
    "gn:asciiname":"Litun",
    "gn:country_code":"CN",
    "gn:dem":228,
    "gn:feature_class":"P",
    "gn:feature_code":"PPL",
    "gn:name":"Litun",
    "gn:population":0,
    "gn:timezone":"Asia/Shanghai",
    "iso:country":"CN",
    "name:zho_x_preferred":[
        "\u674e\u5c6f"
    ],
    "wof:name":"Litun",
    "wof:placetype":"locality"
},
  "geometry": {"coordinates":[125.06444999999999,49.21227],"type":"Point"}
}