{
  "type": "Feature",
  "properties": {
    "gn:admin1_code":"30.0",
    "gn:asciiname":"Liantangjiao",
    "gn:country_code":"CN",
    "gn:dem":141,
    "gn:feature_class":"P",
    "gn:feature_code":"PPL",
    "gn:name":"Liantangjiao",
    "gn:population":0,
    "gn:timezone":"Asia/Shanghai",
    "iso:country":"CN",
    "name:und_x_variant":[
        "\u8fde\u5858\u89d2"
    ],
    "name:zho_x_preferred":[
        "\u8fde\u5858\u89d2"
    ],
    "wof:name":"Liantangjiao",
    "wof:placetype":"locality"
},
  "geometry": {"coordinates":[115.13767,23.58513],"type":"Point"}
}