{
  "type": "Feature",
  "properties": {
    "gn:admin1_code":"25.0",
    "gn:asciiname":"Haogezhuangcun",
    "gn:country_code":"CN",
    "gn:dem":68,
    "gn:feature_class":"P",
    "gn:feature_code":"PPL",
    "gn:name":"Haogezhuangcun",
    "gn:population":0,
    "gn:timezone":"Asia/Shanghai",
    "iso:country":"CN",
    "name:zho_x_preferred":[
        "\u90dd\u683c\u5e84\u6751"
    ],
    "wof:name":"Haogezhuangcun",
    "wof:placetype":"locality"
},
  "geometry": {"coordinates":[121.19624,37.15956],"type":"Point"}
}