{
  "type": "Feature",
  "properties": {
    "gn:admin1_code":"2.0",
    "gn:asciiname":"Yuanshanwei",
    "gn:country_code":"CN",
    "gn:dem":59,
    "gn:feature_class":"P",
    "gn:feature_code":"PPL",
    "gn:name":"Yuanshanwei",
    "gn:population":0,
    "gn:timezone":"Asia/Shanghai",
    "iso:country":"CN",
    "name:zho_x_preferred":[
        "\u56ed\u5c71\u5c3e"
    ],
    "wof:name":"Yuanshanwei",
    "wof:placetype":"locality"
},
  "geometry": {"coordinates":[120.4421,27.21099],"type":"Point"}
}