{
  "type": "Feature",
  "properties": {
    "gn:admin1_code":"10",
    "gn:asciiname":"Xiaohei Tugou",
    "gn:country_code":"CN",
    "gn:dem":1532,
    "gn:feature_class":"P",
    "gn:feature_code":"PPL",
    "gn:name":"Xiaohei Tugou",
    "gn:population":0,
    "gn:timezone":"Asia/Shanghai",
    "iso:country":"CN",
    "name:zho_x_preferred":[
        "\u5c0f\u9ed1\u571f\u6c9f"
    ],
    "wof:name":"Xiaohei Tugou",
    "wof:placetype":"locality"
},
  "geometry": {"coordinates":[114.65183,41.04141],"type":"Point"}
}