{
  "type": "Feature",
  "properties": {
    "gn:admin1_code":"18",
    "gn:asciiname":"Daxiangping",
    "gn:country_code":"CN",
    "gn:dem":1128,
    "gn:feature_class":"P",
    "gn:feature_code":"PPL",
    "gn:name":"Daxiangping",
    "gn:population":0,
    "gn:timezone":"Asia/Shanghai",
    "iso:country":"CN",
    "name:zho_x_preferred":[
        "\u5927\u5df7\u576a"
    ],
    "wof:name":"Daxiangping",
    "wof:placetype":"locality"
},
  "geometry": {"coordinates":[106.67100000000001,27.9637],"type":"Point"}
}