{
  "type": "Feature",
  "properties": {
    "gn:admin1_code":"03",
    "gn:asciiname":"Fangdun",
    "gn:country_code":"CN",
    "gn:dem":91,
    "gn:feature_class":"P",
    "gn:feature_code":"PPL",
    "gn:name":"Fangdun",
    "gn:population":0,
    "gn:timezone":"Asia/Shanghai",
    "iso:country":"CN",
    "name:und_x_variant":[
        "Fangjiadun"
    ],
    "name:zho_x_preferred":[
        "\u82b3\u5bb6\u58a9"
    ],
    "name:zho_x_variant":[
        "\u82b3\u58a9"
    ],
    "wof:name":"Fangdun",
    "wof:placetype":"locality"
},
  "geometry": {"coordinates":[117.34,28.5805],"type":"Point"}
}