{
  "type": "Feature",
  "properties": {
    "gn:admin1_code":"11.0",
    "gn:asciiname":"Tianliping",
    "gn:country_code":"CN",
    "gn:dem":166,
    "gn:feature_class":"P",
    "gn:feature_code":"PPL",
    "gn:name":"Tianliping",
    "gn:population":0,
    "gn:timezone":"Asia/Shanghai",
    "iso:country":"CN",
    "name:zho_x_preferred":[
        "\u5929\u91cc\u576a"
    ],
    "wof:name":"Tianliping",
    "wof:placetype":"locality"
},
  "geometry": {"coordinates":[111.69239,26.67685],"type":"Point"}
}