{
  "type": "Feature",
  "properties": {
    "gn:admin1_code":"26.0",
    "gn:asciiname":"Sijiabian",
    "gn:country_code":"CN",
    "gn:dem":1018,
    "gn:feature_class":"P",
    "gn:feature_code":"PPL",
    "gn:name":"Sijiabian",
    "gn:population":0,
    "gn:timezone":"Asia/Shanghai",
    "iso:country":"CN",
    "name:zho_x_preferred":[
        "\u601d\u5bb6\u782d"
    ],
    "wof:name":"Sijiabian",
    "wof:placetype":"locality"
},
  "geometry": {"coordinates":[109.57702999999999,38.02066],"type":"Point"}
}