{
  "type": "Feature",
  "properties": {
    "gn:admin1_code":"24.0",
    "gn:asciiname":"Xitianjing",
    "gn:country_code":"CN",
    "gn:dem":1565,
    "gn:feature_class":"P",
    "gn:feature_code":"PPL",
    "gn:name":"Xitianjing",
    "gn:population":0,
    "gn:timezone":"Asia/Shanghai",
    "iso:country":"CN",
    "name:und_x_variant":[
        "\u897f\u5929\u4e95"
    ],
    "name:zho_x_preferred":[
        "\u897f\u5929\u4e95"
    ],
    "wof:name":"Xitianjing",
    "wof:placetype":"locality"
},
  "geometry": {"coordinates":[113.31135999999999,39.09538],"type":"Point"}
}