{
  "type": "Feature",
  "properties": {
    "gn:admin1_code":"11.0",
    "gn:asciiname":"Shuangshaxi",
    "gn:country_code":"CN",
    "gn:dem":328,
    "gn:feature_class":"P",
    "gn:feature_code":"PPL",
    "gn:name":"Shuangshaxi",
    "gn:population":0,
    "gn:timezone":"Asia/Shanghai",
    "iso:country":"CN",
    "name:zho_x_preferred":[
        "\u53cc\u6c99\u6eaa"
    ],
    "wof:name":"Shuangshaxi",
    "wof:placetype":"locality"
},
  "geometry": {"coordinates":[111.09690000000001,28.39872],"type":"Point"}
}