{
  "type": "Feature",
  "properties": {
    "gn:admin1_code":"5.0",
    "gn:asciiname":"Qianwudao Gangzi",
    "gn:country_code":"CN",
    "gn:dem":146,
    "gn:feature_class":"P",
    "gn:feature_code":"PPL",
    "gn:name":"Qianwudao Gangzi",
    "gn:population":0,
    "gn:timezone":"Asia/Shanghai",
    "iso:country":"CN",
    "name:zho_x_preferred":[
        "\u524d\u4e94\u9053\u5c97\u5b50"
    ],
    "wof:name":"Qianwudao Gangzi",
    "wof:placetype":"locality"
},
  "geometry": {"coordinates":[123.27106000000001,44.62972],"type":"Point"}
}