{
  "type": "Feature",
  "properties": {
    "gn:admin1_code":"14.0",
    "gn:asciiname":"Gechika",
    "gn:country_code":"CN",
    "gn:dem":4131,
    "gn:feature_class":"P",
    "gn:feature_code":"PPL",
    "gn:name":"Gechika",
    "gn:population":0,
    "gn:timezone":"Asia/Urumqi",
    "iso:country":"CN",
    "name:zho_x_preferred":[
        "\u54e5\u8d64\u5361"
    ],
    "wof:name":"Gechika",
    "wof:placetype":"locality"
},
  "geometry": {"coordinates":[93.94859,31.16708],"type":"Point"}
}