{
  "type": "Feature",
  "properties": {
    "gn:admin1_code":"3.0",
    "gn:asciiname":"Yuanjialong",
    "gn:country_code":"CN",
    "gn:dem":45,
    "gn:feature_class":"P",
    "gn:feature_code":"PPL",
    "gn:name":"Yuanjialong",
    "gn:population":0,
    "gn:timezone":"Asia/Shanghai",
    "iso:country":"CN",
    "name:und_x_variant":[
        "\u8881\u5bb6\u5784"
    ],
    "wof:name":"Yuanjialong",
    "wof:placetype":"locality"
},
  "geometry": {"coordinates":[116.68579,28.46111],"type":"Point"}
}