{
  "type": "Feature",
  "properties": {
    "gn:admin1_code":"11.0",
    "gn:asciiname":"Lianhuayan",
    "gn:country_code":"CN",
    "gn:dem":63,
    "gn:feature_class":"P",
    "gn:feature_code":"PPL",
    "gn:name":"Lianhuayan",
    "gn:population":0,
    "gn:timezone":"Asia/Shanghai",
    "iso:country":"CN",
    "name:zho_x_preferred":[
        "\u83b2\u82b1\u5830"
    ],
    "wof:name":"Lianhuayan",
    "wof:placetype":"locality"
},
  "geometry": {"coordinates":[112.71948999999999,29.56337000000001],"type":"Point"}
}