{
  "type": "Feature",
  "properties": {
    "gn:admin1_code":"18",
    "gn:asciiname":"Weixi",
    "gn:country_code":"CN",
    "gn:dem":778,
    "gn:feature_class":"P",
    "gn:feature_code":"PPL",
    "gn:name":"Weixi",
    "gn:population":0,
    "gn:timezone":"Asia/Shanghai",
    "iso:country":"CN",
    "name:zho_x_preferred":[
        "\u5c3e\u7ec6"
    ],
    "wof:name":"Weixi",
    "wof:placetype":"locality"
},
  "geometry": {"coordinates":[106.002,24.8499],"type":"Point"}
}