{
  "type": "Feature",
  "properties": {
    "gn:admin1_code":"18",
    "gn:asciiname":"Dengxi",
    "gn:country_code":"CN",
    "gn:dem":560,
    "gn:feature_class":"P",
    "gn:feature_code":"PPL",
    "gn:name":"Dengxi",
    "gn:population":0,
    "gn:timezone":"Asia/Shanghai",
    "iso:country":"CN",
    "name:zho_x_preferred":[
        "\u7b49\u6eaa"
    ],
    "wof:name":"Dengxi",
    "wof:placetype":"locality"
},
  "geometry": {"coordinates":[108.97199999999999,26.9457],"type":"Point"}
}