{
  "type": "Feature",
  "properties": {
    "gn:admin1_code":"10",
    "gn:asciiname":"Tiaohetou",
    "gn:cc2":"CN",
    "gn:country_code":"CN",
    "gn:dem":16,
    "gn:feature_class":"P",
    "gn:feature_code":"PPL",
    "gn:name":"Tiaohetou",
    "gn:population":0,
    "gn:timezone":"Asia/Shanghai",
    "iso:country":"CN",
    "name:und_x_variant":[
        "Chzhoukhetouchzhen",
        "T\u2019iao-ho-t\u2019ou",
        "Tiaohotu",
        "Tiaohetou"
    ],
    "wof:name":"Tiaohetou",
    "wof:placetype":"locality"
},
  "geometry": {"coordinates":[116.71861,39.25389000000001],"type":"Point"}
}