{
  "type": "Feature",
  "properties": {
    "gn:admin1_code":"29.0",
    "gn:asciiname":"Laoka",
    "gn:country_code":"CN",
    "gn:dem":1746,
    "gn:feature_class":"P",
    "gn:feature_code":"PPL",
    "gn:name":"Laoka",
    "gn:population":0,
    "gn:timezone":"Asia/Shanghai",
    "iso:country":"CN",
    "name:zho_x_preferred":[
        "\u8001\u5361"
    ],
    "wof:name":"Laoka",
    "wof:placetype":"locality"
},
  "geometry": {"coordinates":[102.819,25.4724],"type":"Point"}
}