{
  "type": "Feature",
  "properties": {
    "gn:admin1_code":"19.0",
    "gn:asciiname":"Shaojiabu",
    "gn:country_code":"CN",
    "gn:dem":111,
    "gn:feature_class":"P",
    "gn:feature_code":"PPL",
    "gn:name":"Shaojiabu",
    "gn:population":0,
    "gn:timezone":"Asia/Shanghai",
    "iso:country":"CN",
    "name:und_x_variant":[
        "Shaojiabao",
        "\u90b5\u5bb6\u5821",
        "Shaojiabu"
    ],
    "name:zho_x_preferred":[
        "\u90b5\u5bb6\u5821"
    ],
    "wof:name":"Shaojiabu",
    "wof:placetype":"locality"
},
  "geometry": {"coordinates":[123.3867,40.15701],"type":"Point"}
}