{
  "type": "Feature",
  "properties": {
    "gn:admin1_code":"24.0",
    "gn:asciiname":"Xizhongpai",
    "gn:country_code":"CN",
    "gn:dem":1389,
    "gn:feature_class":"P",
    "gn:feature_code":"PPL",
    "gn:name":"Xizhongpai",
    "gn:population":0,
    "gn:timezone":"Asia/Shanghai",
    "iso:country":"CN",
    "name:und_x_variant":[
        "\u897f\u949f\u724c"
    ],
    "wof:name":"Xizhongpai",
    "wof:placetype":"locality"
},
  "geometry": {"coordinates":[112.29371999999999,39.56376],"type":"Point"}
}