{
  "type": "Feature",
  "properties": {
    "gn:admin1_code":"5.0",
    "gn:asciiname":"Zhaotun",
    "gn:country_code":"CN",
    "gn:dem":171,
    "gn:feature_class":"P",
    "gn:feature_code":"PPL",
    "gn:name":"Zhaotun",
    "gn:population":0,
    "gn:timezone":"Asia/Shanghai",
    "iso:country":"CN",
    "name:zho_x_preferred":[
        "\u8d75\u5c6f"
    ],
    "wof:name":"Zhaotun",
    "wof:placetype":"locality"
},
  "geometry": {"coordinates":[126.48269000000001,44.14749000000001],"type":"Point"}
}