{
  "type": "Feature",
  "properties": {
    "gn:admin1_code":"29",
    "gn:asciiname":"Sumadong",
    "gn:country_code":"CN",
    "gn:dem":844,
    "gn:feature_class":"P",
    "gn:feature_code":"PPL",
    "gn:name":"Sumadong",
    "gn:population":0,
    "gn:timezone":"Asia/Shanghai",
    "iso:country":"CN",
    "name:zho_x_preferred":[
        "\u82cf\u9ebb\u6d1e"
    ],
    "wof:name":"Sumadong",
    "wof:placetype":"locality"
},
  "geometry": {"coordinates":[105.804,23.9094],"type":"Point"}
}