{
  "type": "Feature",
  "properties": {
    "gn:admin1_code":"32.0",
    "gn:asciiname":"Rikedi",
    "gn:country_code":"CN",
    "gn:dem":2261,
    "gn:feature_class":"P",
    "gn:feature_code":"PPL",
    "gn:name":"Rikedi",
    "gn:population":0,
    "gn:timezone":"Asia/Shanghai",
    "iso:country":"CN",
    "name:zho_x_preferred":[
        "\u65e5\u514b\u5730"
    ],
    "wof:name":"Rikedi",
    "wof:placetype":"locality"
},
  "geometry": {"coordinates":[103.054,27.7921],"type":"Point"}
}