{
  "type": "Feature",
  "properties": {
    "gn:admin1_code":"8.0",
    "gn:asciiname":"Lantou Qiancun",
    "gn:country_code":"CN",
    "gn:dem":168,
    "gn:feature_class":"P",
    "gn:feature_code":"PPL",
    "gn:name":"Lantou Qiancun",
    "gn:population":0,
    "gn:timezone":"Asia/Shanghai",
    "iso:country":"CN",
    "name:zho_x_preferred":[
        "\u5170\u5934\u524d\u6751"
    ],
    "wof:name":"Lantou Qiancun",
    "wof:placetype":"locality"
},
  "geometry": {"coordinates":[126.52979999999999,46.66062],"type":"Point"}
}