{
  "type": "Feature",
  "properties": {
    "gn:admin1_code":"18",
    "gn:asciiname":"Jiangzilin",
    "gn:country_code":"CN",
    "gn:dem":2256,
    "gn:feature_class":"P",
    "gn:feature_code":"PPL",
    "gn:name":"Jiangzilin",
    "gn:population":0,
    "gn:timezone":"Asia/Shanghai",
    "iso:country":"CN",
    "name:zho_x_preferred":[
        "\u6c5f\u5b50\u6797"
    ],
    "wof:name":"Jiangzilin",
    "wof:placetype":"locality"
},
  "geometry": {"coordinates":[104.35899999999999,26.9063],"type":"Point"}
}