{
  "type": "Feature",
  "properties": {
    "gn:country":"CN",
    "gn:fcode":"ADM3",
    "gn:pop":0,
    "iso:country":"CN",
    "name:unk_x_variant":[
        "Chung-mou Hsien"
    ],
    "name:zho_x_preferred":[
        "\u4e2d\u725f\u53bf"
    ],
    "name:zho_x_variant":[
        "\u4e2d\u725f"
    ],
    "qs:name":"Zhongmou Xian",
    "qs:photos_9r":0,
    "qs:photos_sr":0,
    "qs:pop_sr":"0",
    "wd:wordcount":75,
    "wof:name":"Zhongmou Xian",
    "wof:placetype":"localadmin",
    "wof:population":0
},
  "geometry": {"coordinates":[114.01056,34.71528],"type":"Point"}
}