{
  "type": "Feature",
  "properties": {
    "gn:country":"CN",
    "gn:fcode":"ADM3",
    "gn:pop":0,
    "iso:country":"CN",
    "name:ceb_x_preferred":[
        "Zhongmou Xian"
    ],
    "name:deu_x_preferred":[
        "Zhongmu"
    ],
    "name:eng_x_preferred":[
        "Zhongmu County"
    ],
    "name:eus_x_preferred":[
        "Zhongmu konderria"
    ],
    "name:fas_x_preferred":[
        "\u0634\u0647\u0631\u0633\u062a\u0627\u0646 \u0698\u0648\u0646\u06af\u0645\u0648"
    ],
    "name:gan_x_preferred":[
        "\u4e2d\u725f\u53bf"
    ],
    "name:jpn_x_preferred":[
        "\u4e2d\u725f\u770c"
    ],
    "name:kor_x_preferred":[
        "\uc911\ubb34\ud604"
    ],
    "name:nan_x_preferred":[
        "Tiong-b\u00f4\u0358-ko\u0101n"
    ],
    "name:nld_x_preferred":[
        "Zhongmu"
    ],
    "name:nob_x_preferred":[
        "Zhongmu"
    ],
    "name:rus_x_preferred":[
        "\u0427\u0436\u0443\u043d\u043c\u0443"
    ],
    "name:swe_x_preferred":[
        "Zhongmou"
    ],
    "name:unk_x_variant":[
        "Chung-mou Hsien"
    ],
    "name:vie_x_preferred":[
        "Trung M\u01b0u"
    ],
    "name:wuu_x_preferred":[
        "\u4e2d\u725f\u53bf"
    ],
    "name:yue_x_preferred":[
        "\u4e2d\u725f"
    ],
    "name:zho_x_preferred":[
        "\u4e2d\u725f\u53bf"
    ],
    "name:zho_x_variant":[
        "\u4e2d\u725f"
    ],
    "qs:name":"Zhongmou Xian",
    "qs:photos_9r":0,
    "qs:photos_sr":0,
    "qs:pop_sr":"0",
    "wd:wordcount":75,
    "wof:name":"Zhongmou Xian",
    "wof:placetype":"localadmin",
    "wof:population":0
},
  "geometry": {"coordinates":[114.01056,34.71528],"type":"Point"}
}