{
  "type": "Feature",
  "properties": {
    "gn:admin1_code":"14.0",
    "gn:asciiname":"Ranzhongcun",
    "gn:country_code":"CN",
    "gn:dem":4456,
    "gn:feature_class":"P",
    "gn:feature_code":"PPL",
    "gn:name":"Ranzhongcun",
    "gn:population":0,
    "gn:timezone":"Asia/Urumqi",
    "iso:country":"CN",
    "name:zho_x_preferred":[
        "\u7136\u4e2d\u6751"
    ],
    "wof:name":"Ranzhongcun",
    "wof:placetype":"locality"
},
  "geometry": {"coordinates":[97.46998000000001,30.04315],"type":"Point"}
}