{
  "type": "Feature",
  "properties": {
    "gn:admin1_code":"3",
    "gn:asciiname":"Wudi",
    "gn:country_code":"CN",
    "gn:dem":691,
    "gn:feature_class":"P",
    "gn:feature_code":"PPL",
    "gn:name":"Wudi",
    "gn:population":0,
    "gn:timezone":"Asia/Shanghai",
    "iso:country":"CN",
    "name:zho_x_preferred":[
        "\u4e4c\u5730"
    ],
    "wof:name":"Wudi",
    "wof:placetype":"locality"
},
  "geometry": {"coordinates":[114.105,25.8589],"type":"Point"}
}