{
  "type": "Feature",
  "properties": {
    "gn:admin1_code":"19.0",
    "gn:asciiname":"Jiahecun",
    "gn:country_code":"CN",
    "gn:dem":10,
    "gn:feature_class":"P",
    "gn:feature_code":"PPL",
    "gn:name":"Jiahecun",
    "gn:population":0,
    "gn:timezone":"Asia/Shanghai",
    "iso:country":"CN",
    "name:zho_x_preferred":[
        "\u5047\u6cb3\u6751"
    ],
    "wof:name":"Jiahecun",
    "wof:placetype":"locality"
},
  "geometry": {"coordinates":[121.508,41.0393],"type":"Point"}
}