{
  "type": "Feature",
  "properties": {
    "gn:admin1_code":"18",
    "gn:asciiname":"Yezhuwo",
    "gn:country_code":"CN",
    "gn:dem":631,
    "gn:feature_class":"P",
    "gn:feature_code":"PPL",
    "gn:name":"Yezhuwo",
    "gn:population":0,
    "gn:timezone":"Asia/Shanghai",
    "iso:country":"CN",
    "name:zho_x_preferred":[
        "\u91ce\u732a\u7a9d"
    ],
    "wof:name":"Yezhuwo",
    "wof:placetype":"locality"
},
  "geometry": {"coordinates":[108.383,28.5297],"type":"Point"}
}