{
  "type": "Feature",
  "properties": {
    "gn:admin1_code":"22.0",
    "gn:asciiname":"Yaoziyucun",
    "gn:country_code":"CN",
    "gn:dem":340,
    "gn:feature_class":"P",
    "gn:feature_code":"PPL",
    "gn:name":"Yaoziyucun",
    "gn:population":0,
    "gn:timezone":"Asia/Shanghai",
    "iso:country":"CN",
    "name:zho_x_preferred":[
        "\u9e5e\u5b50\u5cea\u6751"
    ],
    "wof:name":"Yaoziyucun",
    "wof:placetype":"locality"
},
  "geometry": {"coordinates":[116.31555,40.42573],"type":"Point"}
}