{
  "type": "Feature",
  "properties": {
    "gn:admin1_code":"19.0",
    "gn:asciiname":"Huoronggou",
    "gn:country_code":"CN",
    "gn:dem":176,
    "gn:feature_class":"P",
    "gn:feature_code":"PPL",
    "gn:name":"Huoronggou",
    "gn:population":0,
    "gn:timezone":"Asia/Shanghai",
    "iso:country":"CN",
    "name:und_x_variant":[
        "\u706b\u8338\u6c9f"
    ],
    "wof:name":"Huoronggou",
    "wof:placetype":"locality"
},
  "geometry": {"coordinates":[123.88276999999999,40.63913],"type":"Point"}
}