{
  "type": "Feature",
  "properties": {
    "gn:admin1_code":"3.0",
    "gn:asciiname":"Zhongtong",
    "gn:country_code":"CN",
    "gn:dem":39,
    "gn:feature_class":"P",
    "gn:feature_code":"PPLA4",
    "gn:name":"Zhongtong",
    "gn:population":0,
    "gn:timezone":"Asia/Shanghai",
    "iso:country":"CN",
    "name:und_x_variant":[
        "\u4e2d\u7ae5",
        "Zhongtong Zhen",
        "\u4e2d\u7ae5\u9547"
    ],
    "wof:name":"Zhongtong",
    "wof:placetype":"locality"
},
  "geometry": {"coordinates":[116.96811,28.30127],"type":"Point"}
}