{
  "type": "Feature",
  "properties": {
    "gn:admin1_code":"9.0",
    "gn:asciiname":"Donggou",
    "gn:country_code":"CN",
    "gn:dem":182,
    "gn:feature_class":"P",
    "gn:feature_code":"PPL",
    "gn:name":"Donggou",
    "gn:population":0,
    "gn:timezone":"Asia/Shanghai",
    "iso:country":"CN",
    "name:und_x_variant":[
        "\u4e1c\u6c9f",
        "Donggou"
    ],
    "wof:name":"Donggou",
    "wof:placetype":"locality"
},
  "geometry": {"coordinates":[112.43671999999999,33.44085],"type":"Point"}
}