{
  "type": "Feature",
  "properties": {
    "gn:admin1_code":"2",
    "gn:asciiname":"Dangkou",
    "gn:country_code":"CN",
    "gn:dem":937,
    "gn:feature_class":"P",
    "gn:feature_code":"PPL",
    "gn:name":"Dangkou",
    "gn:population":0,
    "gn:timezone":"Asia/Shanghai",
    "iso:country":"CN",
    "name:und_x_variant":[
        "\u8361\u53e3"
    ],
    "wof:name":"Dangkou",
    "wof:placetype":"locality"
},
  "geometry": {"coordinates":[119.28111,27.47861],"type":"Point"}
}