{
  "type": "Feature",
  "properties": {
    "gn:admin1_code":"1.0",
    "gn:asciiname":"Jiangmiaocun",
    "gn:country_code":"CN",
    "gn:dem":28,
    "gn:feature_class":"P",
    "gn:feature_code":"PPL",
    "gn:name":"Jiangmiaocun",
    "gn:population":0,
    "gn:timezone":"Asia/Shanghai",
    "iso:country":"CN",
    "name:zho_x_preferred":[
        "\u848b\u5e99\u6751"
    ],
    "wof:name":"Jiangmiaocun",
    "wof:placetype":"locality"
},
  "geometry": {"coordinates":[118.31225000000001,32.39715],"type":"Point"}
}