{
  "type": "Feature",
  "properties": {
    "gn:admin1_code":"26.0",
    "gn:asciiname":"Zhangmeijing",
    "gn:country_code":"CN",
    "gn:dem":1501,
    "gn:feature_class":"P",
    "gn:feature_code":"PPL",
    "gn:name":"Zhangmeijing",
    "gn:population":0,
    "gn:timezone":"Asia/Shanghai",
    "iso:country":"CN",
    "name:zho_x_preferred":[
        "\u5f20\u7f8e\u4e95"
    ],
    "wof:name":"Zhangmeijing",
    "wof:placetype":"locality"
},
  "geometry": {"coordinates":[107.94322,37.37186],"type":"Point"}
}