{
  "type": "Feature",
  "properties": {
    "gn:admin1_code":"04",
    "gn:asciiname":"Miaoqiao",
    "gn:country_code":"CN",
    "gn:dem":4,
    "gn:feature_class":"P",
    "gn:feature_code":"PPL",
    "gn:name":"Miaoqiao",
    "gn:population":0,
    "gn:timezone":"Asia/Shanghai",
    "iso:country":"CN",
    "name:und_x_variant":[
        "\u5e99\u6865",
        "Miaoqiaozhen",
        "Miao-ch\u2019iao-chen",
        "Miaoqiao Zhen",
        "\u5e99\u6865\u9547"
    ],
    "wof:name":"Miaoqiao",
    "wof:placetype":"locality"
},
  "geometry": {"coordinates":[121.50111,31.90207],"type":"Point"}
}