{
  "type": "Feature",
  "properties": {
    "gn:admin1_code":"4.0",
    "gn:asciiname":"Maojiadu",
    "gn:country_code":"CN",
    "gn:dem":4,
    "gn:feature_class":"P",
    "gn:feature_code":"PPL",
    "gn:name":"Maojiadu",
    "gn:population":0,
    "gn:timezone":"Asia/Shanghai",
    "iso:country":"CN",
    "name:zho_x_preferred":[
        "\u5192\u5bb6\u6e21"
    ],
    "wof:name":"Maojiadu",
    "wof:placetype":"locality"
},
  "geometry": {"coordinates":[120.74572000000001,32.35381],"type":"Point"}
}