{
  "type": "Feature",
  "properties": {
    "gn:admin1_code":"3.0",
    "gn:asciiname":"Lindeng Shuxia",
    "gn:country_code":"CN",
    "gn:dem":233,
    "gn:feature_class":"P",
    "gn:feature_code":"PPL",
    "gn:name":"Lindeng Shuxia",
    "gn:population":0,
    "gn:timezone":"Asia/Shanghai",
    "iso:country":"CN",
    "name:und_x_variant":[
        "\u6797\u706f\u6811\u4e0b"
    ],
    "wof:name":"Lindeng Shuxia",
    "wof:placetype":"locality"
},
  "geometry": {"coordinates":[114.85618999999998,28.50086],"type":"Point"}
}