{
  "type": "Feature",
  "properties": {
    "gn:admin1_code":"29.0",
    "gn:asciiname":"Jiyidu",
    "gn:country_code":"CN",
    "gn:dem":2375,
    "gn:feature_class":"P",
    "gn:feature_code":"PPL",
    "gn:name":"Jiyidu",
    "gn:population":0,
    "gn:timezone":"Asia/Shanghai",
    "iso:country":"CN",
    "name:zho_x_preferred":[
        "\u5409\u4e49\u72ec"
    ],
    "wof:name":"Jiyidu",
    "wof:placetype":"locality"
},
  "geometry": {"coordinates":[99.25490000000001,27.7734],"type":"Point"}
}