{
  "type": "Feature",
  "properties": {
    "gn:admin1_code":"30.0",
    "gn:asciiname":"Dengzhan'e",
    "gn:country_code":"CN",
    "gn:dem":68,
    "gn:feature_class":"P",
    "gn:feature_code":"PPL",
    "gn:name":"Dengzhan\u2019e",
    "gn:population":0,
    "gn:timezone":"Asia/Shanghai",
    "iso:country":"CN",
    "name:zho_x_preferred":[
        "\u706f\u76cf\u989d"
    ],
    "name:zho_x_variant":[
        "Dengzhan\u2019e"
    ],
    "wof:name":"Dengzhan'e",
    "wof:placetype":"locality"
},
  "geometry": {"coordinates":[112.5068,23.23635],"type":"Point"}
}