{
  "type": "Feature",
  "properties": {
    "gn:admin1_code":"30",
    "gn:asciiname":"Duxiangliao",
    "gn:country_code":"CN",
    "gn:dem":23,
    "gn:feature_class":"P",
    "gn:feature_code":"PPL",
    "gn:name":"Duxiangliao",
    "gn:population":0,
    "gn:timezone":"Asia/Shanghai",
    "iso:country":"CN",
    "name:und_x_variant":[
        "\u675c\u9999\u5bee",
        "Duxiangliao"
    ],
    "name:zho_x_preferred":[
        "\u675c\u9999\u5bee"
    ],
    "wof:name":"Duxiangliao",
    "wof:placetype":"locality"
},
  "geometry": {"coordinates":[116.15141,23.39113],"type":"Point"}
}