{
  "type": "Feature",
  "properties": {
    "gn:admin1_code":"2.0",
    "gn:asciiname":"Beizhoudai",
    "gn:country_code":"CN",
    "gn:dem":670,
    "gn:feature_class":"P",
    "gn:feature_code":"PPL",
    "gn:name":"Beizhoudai",
    "gn:population":0,
    "gn:timezone":"Asia/Shanghai",
    "iso:country":"CN",
    "name:zho_x_preferred":[
        "\u5317\u5468\u57ed"
    ],
    "wof:name":"Beizhoudai",
    "wof:placetype":"locality"
},
  "geometry": {"coordinates":[120.1352,28.09951],"type":"Point"}
}