{
  "type": "Feature",
  "properties": {
    "gn:admin1_code":"26.0",
    "gn:asciiname":"Lijiahecun",
    "gn:country_code":"CN",
    "gn:dem":984,
    "gn:feature_class":"P",
    "gn:feature_code":"PPL",
    "gn:name":"Lijiahecun",
    "gn:population":0,
    "gn:timezone":"Asia/Shanghai",
    "iso:country":"CN",
    "name:zho_x_preferred":[
        "\u674e\u5bb6\u6cb3\u6751"
    ],
    "wof:name":"Lijiahecun",
    "wof:placetype":"locality"
},
  "geometry": {"coordinates":[110.03136000000001,37.0767],"type":"Point"}
}