{
  "type": "Feature",
  "properties": {
    "gn:admin1_code":"10",
    "gn:asciiname":"Sandao Wopu",
    "gn:country_code":"CN",
    "gn:dem":1430,
    "gn:feature_class":"P",
    "gn:feature_code":"PPL",
    "gn:name":"Sandao Wopu",
    "gn:population":0,
    "gn:timezone":"Asia/Shanghai",
    "iso:country":"CN",
    "name:zho_x_preferred":[
        "\u4e09\u9053\u7a9d\u94fa"
    ],
    "wof:name":"Sandao Wopu",
    "wof:placetype":"locality"
},
  "geometry": {"coordinates":[116.32013999999999,41.60084000000001],"type":"Point"}
}