{
  "type": "Feature",
  "properties": {
    "gn:admin1_code":"04",
    "gn:asciiname":"Sigang",
    "gn:country_code":"CN",
    "gn:dem":10,
    "gn:feature_class":"P",
    "gn:feature_code":"PPL",
    "gn:name":"Sigang",
    "gn:population":0,
    "gn:timezone":"Asia/Shanghai",
    "iso:country":"CN",
    "name:und_x_variant":[
        "Ssu-kang-chen",
        "Sigangzhen",
        "Ssu-chiang-chen",
        "Ssu-chiang",
        "Sigang"
    ],
    "name:zho_x_preferred":[
        "\u6cd7\u6e2f"
    ],
    "wof:name":"Sigang",
    "wof:placetype":"locality"
},
  "geometry": {"coordinates":[120.50579,31.88984],"type":"Point"}
}