{
  "type": "Feature",
  "properties": {
    "gn:admin1_code":"9.0",
    "gn:asciiname":"Chuzhai",
    "gn:country_code":"CN",
    "gn:dem":67,
    "gn:feature_class":"P",
    "gn:feature_code":"PPL",
    "gn:name":"Chuzhai",
    "gn:population":0,
    "gn:timezone":"Asia/Shanghai",
    "iso:country":"CN",
    "name:zho_x_preferred":[
        "\u695a\u5be8"
    ],
    "wof:name":"Chuzhai",
    "wof:placetype":"locality"
},
  "geometry": {"coordinates":[114.64782,34.61374],"type":"Point"}
}