{
  "type": "Feature",
  "properties": {
    "gn:admin1_code":"8.0",
    "gn:asciiname":"Mincaitun",
    "gn:country_code":"CN",
    "gn:dem":162,
    "gn:feature_class":"P",
    "gn:feature_code":"PPL",
    "gn:name":"Mincaitun",
    "gn:population":0,
    "gn:timezone":"Asia/Shanghai",
    "iso:country":"CN",
    "name:zho_x_preferred":[
        "\u6c11\u624d\u5c6f"
    ],
    "wof:name":"Mincaitun",
    "wof:placetype":"locality"
},
  "geometry": {"coordinates":[127.55894000000001,45.8407],"type":"Point"}
}