{
  "type": "Feature",
  "properties": {
    "gn:admin1_code":"08",
    "gn:asciiname":"Pan-la-fang-li",
    "gn:country_code":"CN",
    "gn:dem":145,
    "gn:feature_class":"P",
    "gn:feature_code":"PPL",
    "gn:name":"Pan-la-fang-li",
    "gn:population":0,
    "gn:timezone":"Asia/Shanghai",
    "iso:country":"CN",
    "wof:name":"Pan-la-fang-li",
    "wof:placetype":"locality"
},
  "geometry": {"coordinates":[126.80056,46.40361],"type":"Point"}
}