{
  "type": "Feature",
  "properties": {
    "gn:admin1_code":"12.0",
    "gn:asciiname":"Gongluqiao",
    "gn:country_code":"CN",
    "gn:dem":40,
    "gn:feature_class":"P",
    "gn:feature_code":"PPL",
    "gn:name":"Gongluqiao",
    "gn:population":0,
    "gn:timezone":"Asia/Shanghai",
    "iso:country":"CN",
    "name:zho_x_preferred":[
        "Gongluqiao"
    ],
    "name:zho_x_variant":[
        "\u516c\u8def\u6865"
    ],
    "wof:name":"Gongluqiao",
    "wof:placetype":"locality"
},
  "geometry": {"coordinates":[111.89465,30.18063],"type":"Point"}
}