{
  "type": "Feature",
  "properties": {
    "gn:admin1_code":"29.0",
    "gn:asciiname":"Liujiaqing",
    "gn:country_code":"CN",
    "gn:dem":1792,
    "gn:feature_class":"P",
    "gn:feature_code":"PPL",
    "gn:name":"Liujiaqing",
    "gn:population":0,
    "gn:timezone":"Asia/Shanghai",
    "iso:country":"CN",
    "name:zho_x_preferred":[
        "\u5218\u5bb6\u7b90"
    ],
    "wof:name":"Liujiaqing",
    "wof:placetype":"locality"
},
  "geometry": {"coordinates":[100.105,24.2971],"type":"Point"}
}