{
  "type": "Feature",
  "properties": {
    "gn:admin1_code":"2.0",
    "gn:asciiname":"Ganshi'ao",
    "gn:country_code":"CN",
    "gn:dem":61,
    "gn:feature_class":"P",
    "gn:feature_code":"PPL",
    "gn:name":"Ganshi\u2019ao",
    "gn:population":0,
    "gn:timezone":"Asia/Shanghai",
    "iso:country":"CN",
    "name:und_x_variant":[
        "Ganshi\u2019ao"
    ],
    "name:zho_x_preferred":[
        "\u5e72\u65bd\u5c99"
    ],
    "wof:name":"Ganshi'ao",
    "wof:placetype":"locality"
},
  "geometry": {"coordinates":[122.27684000000001,30.01687],"type":"Point"}
}