{
  "type": "Feature",
  "properties": {
    "gn:admin1_code":"19.0",
    "gn:asciiname":"Hejia Buzi",
    "gn:country_code":"CN",
    "gn:dem":195,
    "gn:feature_class":"P",
    "gn:feature_code":"PPL",
    "gn:name":"Hejia Buzi",
    "gn:population":0,
    "gn:timezone":"Asia/Shanghai",
    "iso:country":"CN",
    "name:und_x_variant":[
        "Hejiabaozi",
        "\u8d6b\u5bb6\u5821\u5b50",
        "Hejia Buzi"
    ],
    "name:zho_x_preferred":[
        "\u8d6b\u5bb6\u5821\u5b50"
    ],
    "wof:name":"Hejia Buzi",
    "wof:placetype":"locality"
},
  "geometry": {"coordinates":[123.65441,40.63194],"type":"Point"}
}