{
  "type": "Feature",
  "properties": {
    "gn:admin1_code":"10",
    "gn:asciiname":"Zhaojiagou",
    "gn:cc2":"CN",
    "gn:country_code":"CN",
    "gn:dem":573,
    "gn:feature_class":"P",
    "gn:feature_code":"PPL",
    "gn:name":"Zhaojiagou",
    "gn:population":0,
    "gn:timezone":"Asia/Shanghai",
    "iso:country":"CN",
    "name:und_x_variant":[
        "Chao-chia-kou",
        "Zhaojiagou"
    ],
    "wof:name":"Zhaojiagou",
    "wof:placetype":"locality"
},
  "geometry": {"coordinates":[113.94222000000001,37.1225],"type":"Point"}
}