{
  "type": "Feature",
  "properties": {
    "gn:admin1_code":"29.0",
    "gn:asciiname":"Ajiebai",
    "gn:country_code":"CN",
    "gn:dem":2022,
    "gn:feature_class":"P",
    "gn:feature_code":"PPL",
    "gn:name":"Ajiebai",
    "gn:population":0,
    "gn:timezone":"Asia/Shanghai",
    "iso:country":"CN",
    "name:zho_x_preferred":[
        "\u963f\u7ed3\u767e"
    ],
    "wof:name":"Ajiebai",
    "wof:placetype":"locality"
},
  "geometry": {"coordinates":[102.955,25.8233],"type":"Point"}
}