{
  "type": "Feature",
  "properties": {
    "gn:admin1_code":"18.0",
    "gn:asciiname":"Jili",
    "gn:country_code":"CN",
    "gn:dem":549,
    "gn:feature_class":"P",
    "gn:feature_code":"PPL",
    "gn:name":"Jili",
    "gn:population":0,
    "gn:timezone":"Asia/Shanghai",
    "iso:country":"CN",
    "name:bre_x_preferred":[
        "Jili"
    ],
    "name:ceb_x_preferred":[
        "Jili"
    ],
    "name:deu_x_preferred":[
        "Jili"
    ],
    "name:fra_x_preferred":[
        "Jili"
    ],
    "name:swe_x_preferred":[
        "Jili"
    ],
    "name:zho_x_preferred":[
        "\u57fa\u7acb"
    ],
    "wof:name":"Jili",
    "wof:placetype":"locality"
},
  "geometry": {"coordinates":[108.82299999999999,26.5451],"type":"Point"}
}