{
  "type": "Feature",
  "properties": {
    "gn:admin1_code":"9.0",
    "gn:asciiname":"Kacun",
    "gn:country_code":"CN",
    "gn:dem":533,
    "gn:feature_class":"P",
    "gn:feature_code":"PPL",
    "gn:name":"Kacun",
    "gn:population":0,
    "gn:timezone":"Asia/Shanghai",
    "iso:country":"CN",
    "name:zho_x_preferred":[
        "\u5361\u6751"
    ],
    "wof:name":"Kacun",
    "wof:placetype":"locality"
},
  "geometry": {"coordinates":[111.66436000000002,34.43377],"type":"Point"}
}