{
  "type": "Feature",
  "properties": {
    "gn:admin1_code":"7",
    "gn:asciiname":"Liuzhai",
    "gn:country_code":"CN",
    "gn:dem":197,
    "gn:feature_class":"P",
    "gn:feature_code":"PPL",
    "gn:name":"Liuzhai",
    "gn:population":0,
    "gn:timezone":"Asia/Shanghai",
    "iso:country":"CN",
    "name:und_x_variant":[
        "\u5218\u5b85",
        "Liuzhai"
    ],
    "wof:name":"Liuzhai",
    "wof:placetype":"locality"
},
  "geometry": {"coordinates":[118.34778,24.67468],"type":"Point"}
}