{
  "type": "Feature",
  "properties": {
    "gn:admin1_code":"19.0",
    "gn:asciiname":"Gaofangcun",
    "gn:country_code":"CN",
    "gn:dem":14,
    "gn:feature_class":"P",
    "gn:feature_code":"PPL",
    "gn:name":"Gaofangcun",
    "gn:population":0,
    "gn:timezone":"Asia/Shanghai",
    "iso:country":"CN",
    "name:zho_x_preferred":[
        "\u9ad8\u623f\u6751"
    ],
    "wof:name":"Gaofangcun",
    "wof:placetype":"locality"
},
  "geometry": {"coordinates":[123.2467,39.88565],"type":"Point"}
}