{
  "type": "Feature",
  "properties": {
    "gn:admin1_code":"1.0",
    "gn:asciiname":"Xihecun",
    "gn:country_code":"CN",
    "gn:dem":189,
    "gn:feature_class":"P",
    "gn:feature_code":"PPL",
    "gn:name":"Xihecun",
    "gn:population":0,
    "gn:timezone":"Asia/Shanghai",
    "iso:country":"CN",
    "name:zho_x_preferred":[
        "\u6eaa\u6cb3\u6751"
    ],
    "wof:name":"Xihecun",
    "wof:placetype":"locality"
},
  "geometry": {"coordinates":[115.8891,30.73712],"type":"Point"}
}