{
  "type": "Feature",
  "properties": {
    "gn:admin1_code":"9.0",
    "gn:asciiname":"Cha'an",
    "gn:country_code":"CN",
    "gn:dem":717,
    "gn:feature_class":"P",
    "gn:feature_code":"PPL",
    "gn:name":"Cha\u2019an",
    "gn:population":0,
    "gn:timezone":"Asia/Shanghai",
    "iso:country":"CN",
    "name:und_x_variant":[
        "Cha\u2019an"
    ],
    "name:zho_x_preferred":[
        "\u8336\u5eb5"
    ],
    "name:zho_x_variant":[
        "\u8336\u5eb5\u9547"
    ],
    "wof:name":"Cha'an",
    "wof:placetype":"locality"
},
  "geometry": {"coordinates":[112.35517,33.80356],"type":"Point"}
}