{
  "type": "Feature",
  "properties": {
    "gn:admin1_code":"5.0",
    "gn:asciiname":"Sidaohuanggoucun",
    "gn:country_code":"CN",
    "gn:dem":584,
    "gn:feature_class":"P",
    "gn:feature_code":"PPL",
    "gn:name":"Sidaohuanggoucun",
    "gn:population":0,
    "gn:timezone":"Asia/Shanghai",
    "iso:country":"CN",
    "name:zho_x_preferred":[
        "\u56db\u9053\u8352\u6c9f\u6751"
    ],
    "wof:name":"Sidaohuanggoucun",
    "wof:placetype":"locality"
},
  "geometry": {"coordinates":[128.05681000000001,43.15545],"type":"Point"}
}