{
  "type": "Feature",
  "properties": {
    "gn:admin1_code":"3.0",
    "gn:asciiname":"Daorentang",
    "gn:country_code":"CN",
    "gn:dem":808,
    "gn:feature_class":"P",
    "gn:feature_code":"PPL",
    "gn:name":"Daorentang",
    "gn:population":0,
    "gn:timezone":"Asia/Shanghai",
    "iso:country":"CN",
    "name:und_x_variant":[
        "\u9053\u4ec1\u5802"
    ],
    "wof:name":"Daorentang",
    "wof:placetype":"locality"
},
  "geometry": {"coordinates":[116.53709000000001,26.51507],"type":"Point"}
}