{
  "type": "Feature",
  "properties": {
    "gn:admin1_code":"25",
    "gn:asciiname":"Lujiatai",
    "gn:country_code":"CN",
    "gn:dem":384,
    "gn:feature_class":"P",
    "gn:feature_code":"PPL",
    "gn:name":"Lujiatai",
    "gn:population":0,
    "gn:timezone":"Asia/Shanghai",
    "iso:country":"CN",
    "name:zho_x_preferred":[
        "\u82a6\u5bb6\u53f0"
    ],
    "wof:name":"Lujiatai",
    "wof:placetype":"locality"
},
  "geometry": {"coordinates":[117.86499999999999,36.3896],"type":"Point"}
}