{
  "type": "Feature",
  "properties": {
    "gn:admin1_code":"8.0",
    "gn:asciiname":"Gonglitun",
    "gn:country_code":"CN",
    "gn:dem":169,
    "gn:feature_class":"P",
    "gn:feature_code":"PPL",
    "gn:name":"Gonglitun",
    "gn:population":0,
    "gn:timezone":"Asia/Shanghai",
    "iso:country":"CN",
    "name:zho_x_preferred":[
        "\u516c\u7acb\u5c6f"
    ],
    "wof:name":"Gonglitun",
    "wof:placetype":"locality"
},
  "geometry": {"coordinates":[126.97331,45.87583],"type":"Point"}
}