{
  "type": "Feature",
  "properties": {
    "gn:admin1_code":"26.0",
    "gn:asciiname":"Yaojiahe",
    "gn:country_code":"CN",
    "gn:dem":1096,
    "gn:feature_class":"P",
    "gn:feature_code":"PPL",
    "gn:name":"Yaojiahe",
    "gn:population":0,
    "gn:timezone":"Asia/Shanghai",
    "iso:country":"CN",
    "name:und_x_variant":[
        "\u59da\u5bb6\u6cb3"
    ],
    "wof:name":"Yaojiahe",
    "wof:placetype":"locality"
},
  "geometry": {"coordinates":[106.07174999999999,32.77636],"type":"Point"}
}