{
  "type": "Feature",
  "properties": {
    "gn:admin1_code":"1.0",
    "gn:asciiname":"Heyicun",
    "gn:country_code":"CN",
    "gn:dem":79,
    "gn:feature_class":"P",
    "gn:feature_code":"PPL",
    "gn:name":"Heyicun",
    "gn:population":0,
    "gn:timezone":"Asia/Shanghai",
    "iso:country":"CN",
    "name:zho_x_preferred":[
        "\u5408\u4e49\u6751"
    ],
    "wof:name":"Heyicun",
    "wof:placetype":"locality"
},
  "geometry": {"coordinates":[117.16677,30.02092],"type":"Point"}
}