{
  "type": "Feature",
  "properties": {
    "gn:admin1_code":"11.0",
    "gn:asciiname":"Mawangchong",
    "gn:country_code":"CN",
    "gn:dem":339,
    "gn:feature_class":"P",
    "gn:feature_code":"PPL",
    "gn:name":"Mawangchong",
    "gn:population":0,
    "gn:timezone":"Asia/Shanghai",
    "iso:country":"CN",
    "name:zho_x_preferred":[
        "\u9a6c\u738b\u51b2"
    ],
    "wof:name":"Mawangchong",
    "wof:placetype":"locality"
},
  "geometry": {"coordinates":[111.79434999999999,27.39667],"type":"Point"}
}