{
  "type": "Feature",
  "properties": {
    "gn:admin1_code":"32.0",
    "gn:asciiname":"Dajinzhushan",
    "gn:country_code":"CN",
    "gn:dem":789,
    "gn:feature_class":"P",
    "gn:feature_code":"PPL",
    "gn:name":"Dajinzhushan",
    "gn:population":0,
    "gn:timezone":"Asia/Shanghai",
    "iso:country":"CN",
    "name:zho_x_preferred":[
        "\u5927\u91d1\u7af9\u5c71"
    ],
    "wof:name":"Dajinzhushan",
    "wof:placetype":"locality"
},
  "geometry": {"coordinates":[107.98054999999999,31.93789],"type":"Point"}
}