{
  "type": "Feature",
  "properties": {
    "gn:admin1_code":"3.0",
    "gn:asciiname":"Baishishan",
    "gn:country_code":"CN",
    "gn:dem":764,
    "gn:feature_class":"P",
    "gn:feature_code":"PPL",
    "gn:name":"Baishishan",
    "gn:population":0,
    "gn:timezone":"Asia/Shanghai",
    "iso:country":"CN",
    "name:zho_x_preferred":[
        "\u767d\u77f3\u5c71"
    ],
    "wof:name":"Baishishan",
    "wof:placetype":"locality"
},
  "geometry": {"coordinates":[117.75433,28.65252000000001],"type":"Point"}
}