{
  "type": "Feature",
  "properties": {
    "gn:admin1_code":"11.0",
    "gn:asciiname":"Dongnaotian",
    "gn:country_code":"CN",
    "gn:dem":599,
    "gn:feature_class":"P",
    "gn:feature_code":"PPL",
    "gn:name":"Dongnaotian",
    "gn:population":0,
    "gn:timezone":"Asia/Shanghai",
    "iso:country":"CN",
    "name:zho_x_preferred":[
        "\u6d1e\u8111\u7530"
    ],
    "wof:name":"Dongnaotian",
    "wof:placetype":"locality"
},
  "geometry": {"coordinates":[111.62823,24.92457000000001],"type":"Point"}
}