{
  "type": "Feature",
  "properties": {
    "gn:admin1_code":"26",
    "gn:asciiname":"Hujiagou",
    "gn:country_code":"CN",
    "gn:dem":494,
    "gn:feature_class":"P",
    "gn:feature_code":"PPL",
    "gn:name":"Hujiagou",
    "gn:population":0,
    "gn:timezone":"Asia/Shanghai",
    "iso:country":"CN",
    "name:und_x_variant":[
        "\u80e1\u5bb6\u6c9f",
        "Hujiagou"
    ],
    "wof:name":"Hujiagou",
    "wof:placetype":"locality"
},
  "geometry": {"coordinates":[109.13861,34.28728],"type":"Point"}
}