{
  "type": "Feature",
  "properties": {
    "iso:country":"CN",
    "qs:name":"\u9f99\u53e3\u5e02",
    "qs:name_adm0":"\u4e2d\u570b",
    "qs:name_adm1":"\u5c71\u4e1c\u7701",
    "qs:photos":7,
    "qs:photos_1k":1,
    "qs:photos_9k":1,
    "qs:photos_9r":2,
    "qs:photos_all":27,
    "qs:photos_sr":1,
    "qs:placetype":"LocalAdmin",
    "qs:pop_sr":"0",
    "wof:name":"\u9f99\u53e3\u5e02",
    "wof:placetype":"localadmin"
},
  "geometry": {"coordinates":[120.31538849999998,37.669163],"type":"Point"}
}