{
  "type": "Feature",
  "properties": {
    "gn:admin1_code":"3.0",
    "gn:asciiname":"Dongyecun",
    "gn:country_code":"CN",
    "gn:dem":18,
    "gn:feature_class":"P",
    "gn:feature_code":"PPL",
    "gn:name":"Dongyecun",
    "gn:population":0,
    "gn:timezone":"Asia/Shanghai",
    "iso:country":"CN",
    "name:und_x_variant":[
        "\u4e1c\u90ba\u6751"
    ],
    "wof:name":"Dongyecun",
    "wof:placetype":"locality"
},
  "geometry": {"coordinates":[116.01063000000001,28.80654],"type":"Point"}
}