{
  "type": "Feature",
  "properties": {
    "gn:admin1_code":"21.0",
    "gn:asciiname":"Shangda Taozi",
    "gn:country_code":"CN",
    "gn:dem":2002,
    "gn:feature_class":"P",
    "gn:feature_code":"PPL",
    "gn:name":"Shangda Taozi",
    "gn:population":0,
    "gn:timezone":"Asia/Shanghai",
    "iso:country":"CN",
    "name:zho_x_preferred":[
        "\u4e0a\u5927\u5957\u5b50"
    ],
    "wof:name":"Shangda Taozi",
    "wof:placetype":"locality"
},
  "geometry": {"coordinates":[106.00700000000001,35.9116],"type":"Point"}
}