{
  "type": "Feature",
  "properties": {
    "gn:admin1_code":"02",
    "gn:asciiname":"Renqiaocun",
    "gn:country_code":"CN",
    "gn:dem":11,
    "gn:feature_class":"P",
    "gn:feature_code":"PPL",
    "gn:name":"Renqiaocun",
    "gn:population":0,
    "gn:timezone":"Asia/Shanghai",
    "iso:country":"CN",
    "name:und_x_variant":[
        "Renqiao",
        "Renqiaocun"
    ],
    "name:zho_x_preferred":[
        "Jen-ch\u2019iao"
    ],
    "name:zho_x_variant":[
        "\u4efb\u6865",
        "\u4efb\u6865\u6751"
    ],
    "wof:name":"Renqiaocun",
    "wof:placetype":"locality"
},
  "geometry": {"coordinates":[120.56451,27.98352],"type":"Point"}
}