{
  "type": "Feature",
  "properties": {
    "gn:admin1_code":"8.0",
    "gn:asciiname":"Xuxianyi",
    "gn:country_code":"CN",
    "gn:dem":194,
    "gn:feature_class":"P",
    "gn:feature_code":"PPL",
    "gn:name":"Xuxianyi",
    "gn:population":0,
    "gn:timezone":"Asia/Shanghai",
    "iso:country":"CN",
    "name:zho_x_preferred":[
        "\u5f90\u663e\u4e00"
    ],
    "wof:name":"Xuxianyi",
    "wof:placetype":"locality"
},
  "geometry": {"coordinates":[125.42270000000001,46.02599],"type":"Point"}
}