{
  "type": "Feature",
  "properties": {
    "gn:admin1_code":"29.0",
    "gn:asciiname":"Xiabaxin",
    "gn:country_code":"CN",
    "gn:dem":1770,
    "gn:feature_class":"P",
    "gn:feature_code":"PPL",
    "gn:name":"Xiabaxin",
    "gn:population":0,
    "gn:timezone":"Asia/Shanghai",
    "iso:country":"CN",
    "name:zho_x_preferred":[
        "\u4e0b\u575d\u65b0"
    ],
    "wof:name":"Xiabaxin",
    "wof:placetype":"locality"
},
  "geometry": {"coordinates":[103.447,23.7708],"type":"Point"}
}