{
  "type": "Feature",
  "properties": {
    "gn:admin1_code":"23.0",
    "gn:asciiname":"Xusheng",
    "gn:country_code":"CN",
    "gn:dem":4,
    "gn:feature_class":"P",
    "gn:feature_code":"PPL",
    "gn:name":"Xusheng",
    "gn:population":0,
    "gn:timezone":"Asia/Shanghai",
    "iso:country":"CN",
    "name:zho_x_preferred":[
        "Xusheng"
    ],
    "name:zho_x_variant":[
        "\u65ed\u5347"
    ],
    "wof:name":"Xusheng",
    "wof:placetype":"locality"
},
  "geometry": {"coordinates":[121.43621,31.66124000000001],"type":"Point"}
}