{
  "type": "Feature",
  "properties": {
    "gn:admin1_code":"2.0",
    "gn:asciiname":"Zhanling",
    "gn:country_code":"CN",
    "gn:dem":212,
    "gn:feature_class":"P",
    "gn:feature_code":"PPL",
    "gn:name":"Zhanling",
    "gn:population":0,
    "gn:timezone":"Asia/Shanghai",
    "iso:country":"CN",
    "name:zho_x_preferred":[
        "\u6218\u5cad"
    ],
    "wof:name":"Zhanling",
    "wof:placetype":"locality"
},
  "geometry": {"coordinates":[119.69018,31.15244],"type":"Point"}
}