{
  "type": "Feature",
  "properties": {
    "gn:admin1_code":"11.0",
    "gn:asciiname":"Zhenzhutan",
    "gn:country_code":"CN",
    "gn:dem":50,
    "gn:feature_class":"P",
    "gn:feature_code":"PPL",
    "gn:name":"Zhenzhutan",
    "gn:population":0,
    "gn:timezone":"Asia/Shanghai",
    "iso:country":"CN",
    "name:zho_x_preferred":[
        "\u73cd\u73e0\u6f6d"
    ],
    "wof:name":"Zhenzhutan",
    "wof:placetype":"locality"
},
  "geometry": {"coordinates":[112.99527999999999,27.4276],"type":"Point"}
}