{
  "type": "Feature",
  "properties": {
    "gn:admin1_code":"14.0",
    "gn:asciiname":"Guoluogang",
    "gn:country_code":"CN",
    "gn:dem":3501,
    "gn:feature_class":"P",
    "gn:feature_code":"PPL",
    "gn:name":"Guoluogang",
    "gn:population":0,
    "gn:timezone":"Asia/Urumqi",
    "iso:country":"CN",
    "name:zho_x_preferred":[
        "\u8fc7\u7f57\u6e2f"
    ],
    "wof:name":"Guoluogang",
    "wof:placetype":"locality"
},
  "geometry": {"coordinates":[94.51522,29.57307],"type":"Point"}
}