{
  "type": "Feature",
  "properties": {
    "gn:admin1_code":"25.0",
    "gn:asciiname":"Beilujiagoucun",
    "gn:country_code":"CN",
    "gn:dem":258,
    "gn:feature_class":"P",
    "gn:feature_code":"PPL",
    "gn:name":"Beilujiagoucun",
    "gn:population":0,
    "gn:timezone":"Asia/Shanghai",
    "iso:country":"CN",
    "name:zho_x_preferred":[
        "\u5317\u8def\u5bb6\u6c9f\u6751"
    ],
    "wof:name":"Beilujiagoucun",
    "wof:placetype":"locality"
},
  "geometry": {"coordinates":[120.75968,37.40165],"type":"Point"}
}