{
  "type": "Feature",
  "properties": {
    "gn:admin1_code":"04",
    "gn:asciiname":"Huangmaodong",
    "gn:country_code":"CN",
    "gn:dem":5,
    "gn:feature_class":"P",
    "gn:feature_code":"PPL",
    "gn:name":"Huangmaodong",
    "gn:population":0,
    "gn:timezone":"Asia/Shanghai",
    "iso:country":"CN",
    "name:zho_x_preferred":[
        "\u9ec4\u732b\u6d1e"
    ],
    "wof:name":"Huangmaodong",
    "wof:placetype":"locality"
},
  "geometry": {"coordinates":[120.71544,32.73267],"type":"Point"}
}