{
  "type": "Feature",
  "properties": {
    "gn:admin1_code":"3.0",
    "gn:asciiname":"Xialing",
    "gn:country_code":"CN",
    "gn:dem":318,
    "gn:feature_class":"P",
    "gn:feature_code":"PPL",
    "gn:name":"Xialing",
    "gn:population":0,
    "gn:timezone":"Asia/Shanghai",
    "iso:country":"CN",
    "name:zho_x_preferred":[
        "\u4e0b\u5cad"
    ],
    "wof:name":"Xialing",
    "wof:placetype":"locality"
},
  "geometry": {"coordinates":[115.205,25.5969],"type":"Point"}
}