{
  "type": "Feature",
  "properties": {
    "gn:admin1_code":"4.0",
    "gn:asciiname":"Liuyingcun",
    "gn:country_code":"CN",
    "gn:dem":20,
    "gn:feature_class":"P",
    "gn:feature_code":"PPL",
    "gn:name":"Liuyingcun",
    "gn:population":0,
    "gn:timezone":"Asia/Shanghai",
    "iso:country":"CN",
    "name:zho_x_preferred":[
        "\u5218\u8425\u6751"
    ],
    "wof:name":"Liuyingcun",
    "wof:placetype":"locality"
},
  "geometry": {"coordinates":[119.20471000000001,32.43951],"type":"Point"}
}