{
  "type": "Feature",
  "properties": {
    "gn:admin1_code":"12.0",
    "gn:asciiname":"Caijiawan",
    "gn:country_code":"CN",
    "gn:dem":157,
    "gn:feature_class":"P",
    "gn:feature_code":"PPL",
    "gn:name":"Caijiawan",
    "gn:population":0,
    "gn:timezone":"Asia/Shanghai",
    "iso:country":"CN",
    "name:zho_x_preferred":[
        "\u8521\u5bb6\u6e7e"
    ],
    "wof:name":"Caijiawan",
    "wof:placetype":"locality"
},
  "geometry": {"coordinates":[111.54872,31.24477000000001],"type":"Point"}
}