{
  "type": "Feature",
  "properties": {
    "gn:admin1_code":"15.0",
    "gn:asciiname":"Xiajiadunwan",
    "gn:country_code":"CN",
    "gn:dem":1191,
    "gn:feature_class":"P",
    "gn:feature_code":"PPL",
    "gn:name":"Xiajiadunwan",
    "gn:population":0,
    "gn:timezone":"Asia/Shanghai",
    "iso:country":"CN",
    "name:zho_x_preferred":[
        "\u4e0b\u5939\u58a9\u6e7e"
    ],
    "wof:name":"Xiajiadunwan",
    "wof:placetype":"locality"
},
  "geometry": {"coordinates":[99.41200000000001,40.2363],"type":"Point"}
}