{
  "type": "Feature",
  "properties": {
    "gn:admin1_code":"32.0",
    "gn:asciiname":"Laluodedi",
    "gn:country_code":"CN",
    "gn:dem":2498,
    "gn:feature_class":"P",
    "gn:feature_code":"PPL",
    "gn:name":"Laluodedi",
    "gn:population":0,
    "gn:timezone":"Asia/Shanghai",
    "iso:country":"CN",
    "name:zho_x_preferred":[
        "\u5566\u843d\u7684\u5730"
    ],
    "wof:name":"Laluodedi",
    "wof:placetype":"locality"
},
  "geometry": {"coordinates":[102.0844,28.26182],"type":"Point"}
}