{
  "type": "Feature",
  "properties": {
    "gn:admin1_code":"24.0",
    "gn:asciiname":"Xiaomuchang",
    "gn:country_code":"CN",
    "gn:dem":1871,
    "gn:feature_class":"P",
    "gn:feature_code":"PPL",
    "gn:name":"Xiaomuchang",
    "gn:population":0,
    "gn:timezone":"Asia/Shanghai",
    "iso:country":"CN",
    "name:zho_x_preferred":[
        "\u5c0f\u6728\u5382"
    ],
    "wof:name":"Xiaomuchang",
    "wof:placetype":"locality"
},
  "geometry": {"coordinates":[112.16630000000001,38.88162],"type":"Point"}
}