{
  "type": "Feature",
  "properties": {
    "gn:admin1_code":"10.0",
    "gn:asciiname":"Hanjialou",
    "gn:country_code":"CN",
    "gn:dem":95,
    "gn:feature_class":"P",
    "gn:feature_code":"PPL",
    "gn:name":"Hanjialou",
    "gn:population":0,
    "gn:timezone":"Asia/Shanghai",
    "iso:country":"CN",
    "name:und_x_variant":[
        "\u97e9\u5bb6\u697c"
    ],
    "wof:name":"Hanjialou",
    "wof:placetype":"locality"
},
  "geometry": {"coordinates":[114.44457,38.25522],"type":"Point"}
}