{
  "type": "Feature",
  "properties": {
    "gn:admin1_code":"16.0",
    "gn:asciiname":"Shutoutang",
    "gn:country_code":"CN",
    "gn:dem":68,
    "gn:feature_class":"P",
    "gn:feature_code":"PPL",
    "gn:name":"Shutoutang",
    "gn:population":0,
    "gn:timezone":"Asia/Shanghai",
    "iso:country":"CN",
    "name:zho_x_preferred":[
        "\u6811\u5934\u5858"
    ],
    "wof:name":"Shutoutang",
    "wof:placetype":"locality"
},
  "geometry": {"coordinates":[109.358,21.9687],"type":"Point"}
}