{
  "type": "Feature",
  "properties": {
    "gn:admin1_code":"1.0",
    "gn:asciiname":"Taoyuancun",
    "gn:country_code":"CN",
    "gn:dem":29,
    "gn:feature_class":"P",
    "gn:feature_code":"PPL",
    "gn:name":"Taoyuancun",
    "gn:population":0,
    "gn:timezone":"Asia/Shanghai",
    "iso:country":"CN",
    "name:zho_x_preferred":[
        "\u6843\u56ed\u6751"
    ],
    "wof:name":"Taoyuancun",
    "wof:placetype":"locality"
},
  "geometry": {"coordinates":[117.02919,30.60357],"type":"Point"}
}