{
  "type": "Feature",
  "properties": {
    "gn:admin1_code":"3.0",
    "gn:asciiname":"Lishoucun",
    "gn:country_code":"CN",
    "gn:dem":24,
    "gn:feature_class":"P",
    "gn:feature_code":"PPL",
    "gn:name":"Lishoucun",
    "gn:population":0,
    "gn:timezone":"Asia/Shanghai",
    "iso:country":"CN",
    "name:und_x_variant":[
        "Lishou Hujia"
    ],
    "name:zho_x_preferred":[
        "\u91cc\u9996\u6751"
    ],
    "name:zho_x_variant":[
        "\u91cc\u9996\u80e1\u5bb6"
    ],
    "wof:name":"Lishoucun",
    "wof:placetype":"locality"
},
  "geometry": {"coordinates":[117.086,28.9361],"type":"Point"}
}