{
  "type": "Feature",
  "properties": {
    "gn:admin1_code":"30",
    "gn:asciiname":"Wangjiacun",
    "gn:country_code":"CN",
    "gn:dem":41,
    "gn:feature_class":"P",
    "gn:feature_code":"PPL",
    "gn:name":"Wangjiacun",
    "gn:population":0,
    "gn:timezone":"Asia/Urumqi",
    "iso:country":"CN",
    "name:zho_x_preferred":[
        "\u738b\u5bb6\u6751"
    ],
    "wof:name":"Wangjiacun",
    "wof:placetype":"locality"
},
  "geometry": {"coordinates":[110.01356,20.72026],"type":"Point"}
}