{
  "type": "Feature",
  "properties": {
    "gn:admin1_code":"26.0",
    "gn:asciiname":"Fujiawan",
    "gn:country_code":"CN",
    "gn:dem":1110,
    "gn:feature_class":"P",
    "gn:feature_code":"PPL",
    "gn:name":"Fujiawan",
    "gn:population":0,
    "gn:timezone":"Asia/Shanghai",
    "iso:country":"CN",
    "name:zho_x_preferred":[
        "\u5bcc\u5bb6\u6e7e"
    ],
    "wof:name":"Fujiawan",
    "wof:placetype":"locality"
},
  "geometry": {"coordinates":[110.32549,36.18035],"type":"Point"}
}