{
  "type": "Feature",
  "properties": {
    "gn:admin1_code":"22.0",
    "gn:asciiname":"Beigandi",
    "gn:country_code":"CN",
    "gn:dem":60,
    "gn:feature_class":"P",
    "gn:feature_code":"PPL",
    "gn:name":"Beigandi",
    "gn:population":0,
    "gn:timezone":"Asia/Shanghai",
    "iso:country":"CN",
    "name:zho_x_preferred":[
        "\u5317\u7518\u5730"
    ],
    "wof:name":"Beigandi",
    "wof:placetype":"locality"
},
  "geometry": {"coordinates":[115.87278000000001,39.59931],"type":"Point"}
}