{
  "type": "Feature",
  "properties": {
    "gn:admin1_code":"10",
    "gn:asciiname":"Xidadi",
    "gn:country_code":"CN",
    "gn:dem":797,
    "gn:feature_class":"P",
    "gn:feature_code":"PPL",
    "gn:name":"Xidadi",
    "gn:population":0,
    "gn:timezone":"Asia/Shanghai",
    "iso:country":"CN",
    "name:zho_x_preferred":[
        "\u897f\u5927\u5730"
    ],
    "wof:name":"Xidadi",
    "wof:placetype":"locality"
},
  "geometry": {"coordinates":[118.58298000000001,41.25103],"type":"Point"}
}