{
  "type": "Feature",
  "properties": {
    "gn:admin1_code":"10",
    "gn:asciiname":"Banjiawo",
    "gn:cc2":"CN",
    "gn:country_code":"CN",
    "gn:dem":14,
    "gn:feature_class":"P",
    "gn:feature_code":"PPL",
    "gn:name":"Banjiawo",
    "gn:population":0,
    "gn:timezone":"Asia/Shanghai",
    "iso:country":"CN",
    "name:und_x_variant":[
        "Pan-chia-wo",
        "Pan-chia-wo-chen",
        "Banjiawo"
    ],
    "wof:name":"Banjiawo",
    "wof:placetype":"locality"
},
  "geometry": {"coordinates":[116.19083000000001,39.1225],"type":"Point"}
}