{
  "type": "Feature",
  "properties": {
    "gn:admin1_code":"32.0",
    "gn:asciiname":"Se'ergong",
    "gn:country_code":"CN",
    "gn:dem":2842,
    "gn:feature_class":"P",
    "gn:feature_code":"PPL",
    "gn:name":"Se\u2019ergong",
    "gn:population":0,
    "gn:timezone":"Asia/Shanghai",
    "iso:country":"CN",
    "name:und_x_variant":[
        "Se\u2019ergong"
    ],
    "name:zho_x_preferred":[
        "\u8272\u5c14\u5bab"
    ],
    "wof:name":"Se'ergong",
    "wof:placetype":"locality"
},
  "geometry": {"coordinates":[99.80070000000001,28.9455],"type":"Point"}
}