{
  "type": "Feature",
  "properties": {
    "gn:admin1_code":"15.0",
    "gn:asciiname":"Wangjia Laozhuang",
    "gn:country_code":"CN",
    "gn:dem":1415,
    "gn:feature_class":"P",
    "gn:feature_code":"PPL",
    "gn:name":"Wangjia Laozhuang",
    "gn:population":0,
    "gn:timezone":"Asia/Shanghai",
    "iso:country":"CN",
    "name:zho_x_preferred":[
        "\u738b\u5bb6\u8001\u5e84"
    ],
    "wof:name":"Wangjia Laozhuang",
    "wof:placetype":"locality"
},
  "geometry": {"coordinates":[108.42700000000001,36.0877],"type":"Point"}
}