{
  "type": "Feature",
  "properties": {
    "gn:admin1_code":"24.0",
    "gn:asciiname":"Lujiazhuang",
    "gn:country_code":"CN",
    "gn:dem":1210,
    "gn:feature_class":"P",
    "gn:feature_code":"PPL",
    "gn:name":"Lujiazhuang",
    "gn:population":0,
    "gn:timezone":"Asia/Shanghai",
    "iso:country":"CN",
    "name:zho_x_preferred":[
        "\u82a6\u5bb6\u5e84"
    ],
    "wof:name":"Lujiazhuang",
    "wof:placetype":"locality"
},
  "geometry": {"coordinates":[110.80809000000001,36.76323],"type":"Point"}
}