{
  "type": "Feature",
  "properties": {
    "gn:admin1_code":"8.0",
    "gn:asciiname":"Dayong",
    "gn:country_code":"CN",
    "gn:dem":144,
    "gn:feature_class":"P",
    "gn:feature_code":"PPLA4",
    "gn:name":"Dayong",
    "gn:population":0,
    "gn:timezone":"Asia/Shanghai",
    "iso:country":"CN",
    "name:und_x_variant":[
        "Dayong Zhen"
    ],
    "name:zho_x_preferred":[
        "\u5927\u7528"
    ],
    "name:zho_x_variant":[
        "\u5927\u7528\u9547"
    ],
    "wof:name":"Dayong",
    "wof:placetype":"locality"
},
  "geometry": {"coordinates":[126.71525,46.28407],"type":"Point"}
}