{
  "type": "Feature",
  "properties": {
    "gn:admin1_code":"3.0",
    "gn:asciiname":"Duimiankeng",
    "gn:country_code":"CN",
    "gn:dem":935,
    "gn:feature_class":"P",
    "gn:feature_code":"PPL",
    "gn:name":"Duimiankeng",
    "gn:population":0,
    "gn:timezone":"Asia/Shanghai",
    "iso:country":"CN",
    "name:zho_x_preferred":[
        "\u5bf9\u9762\u5751"
    ],
    "wof:name":"Duimiankeng",
    "wof:placetype":"locality"
},
  "geometry": {"coordinates":[118.12325,28.06645],"type":"Point"}
}