{
  "type": "Feature",
  "properties": {
    "gn:admin1_code":"32.0",
    "gn:asciiname":"Yejiwo",
    "gn:country_code":"CN",
    "gn:dem":2095,
    "gn:feature_class":"P",
    "gn:feature_code":"PPL",
    "gn:name":"Yejiwo",
    "gn:population":0,
    "gn:timezone":"Asia/Shanghai",
    "iso:country":"CN",
    "name:zho_x_preferred":[
        "\u91ce\u9e21\u7a9d"
    ],
    "wof:name":"Yejiwo",
    "wof:placetype":"locality"
},
  "geometry": {"coordinates":[102.35418,29.11212],"type":"Point"}
}