{
  "type": "Feature",
  "properties": {
    "gn:admin1_code":"25",
    "gn:asciiname":"Ximamiao",
    "gn:country_code":"CN",
    "gn:dem":93,
    "gn:feature_class":"P",
    "gn:feature_code":"PPL",
    "gn:name":"Ximamiao",
    "gn:population":0,
    "gn:timezone":"Asia/Shanghai",
    "iso:country":"CN",
    "name:zho_x_preferred":[
        "\u897f\u9a6c\u5e99"
    ],
    "wof:name":"Ximamiao",
    "wof:placetype":"locality"
},
  "geometry": {"coordinates":[117.72799999999999,34.9212],"type":"Point"}
}