{
  "type": "Feature",
  "properties": {
    "gn:admin1_code":"19.0",
    "gn:asciiname":"Changling Xinantun",
    "gn:country_code":"CN",
    "gn:dem":32,
    "gn:feature_class":"P",
    "gn:feature_code":"PPL",
    "gn:name":"Changling Xinantun",
    "gn:population":0,
    "gn:timezone":"Asia/Shanghai",
    "iso:country":"CN",
    "name:zho_x_preferred":[
        "\u957f\u5cad\u897f\u5357\u5c6f"
    ],
    "wof:name":"Changling Xinantun",
    "wof:placetype":"locality"
},
  "geometry": {"coordinates":[121.327,39.5444],"type":"Point"}
}