{
  "type": "Feature",
  "properties": {
    "gn:admin1_code":"32.0",
    "gn:asciiname":"Dashichang",
    "gn:country_code":"CN",
    "gn:dem":317,
    "gn:feature_class":"P",
    "gn:feature_code":"PPL",
    "gn:name":"Dashichang",
    "gn:population":0,
    "gn:timezone":"Asia/Shanghai",
    "iso:country":"CN",
    "name:zho_x_preferred":[
        "\u5927\u77f3\u573a"
    ],
    "wof:name":"Dashichang",
    "wof:placetype":"locality"
},
  "geometry": {"coordinates":[107.045,30.1365],"type":"Point"}
}