{
  "type": "Feature",
  "properties": {
    "gn:admin1_code":"8.0",
    "gn:asciiname":"Tong'ancun",
    "gn:country_code":"CN",
    "gn:dem":339,
    "gn:feature_class":"P",
    "gn:feature_code":"PPL",
    "gn:name":"Tong\u2019ancun",
    "gn:population":0,
    "gn:timezone":"Asia/Shanghai",
    "iso:country":"CN",
    "name:und_x_variant":[
        "Tong\u2019ancun"
    ],
    "name:zho_x_preferred":[
        "\u540c\u5b89\u6751"
    ],
    "wof:name":"Tong'ancun",
    "wof:placetype":"locality"
},
  "geometry": {"coordinates":[125.51038,48.29351],"type":"Point"}
}