{
  "type": "Feature",
  "properties": {
    "gn:admin1_code":"8.0",
    "gn:asciiname":"Songshancun",
    "gn:country_code":"CN",
    "gn:dem":131,
    "gn:feature_class":"P",
    "gn:feature_code":"PPL",
    "gn:name":"Songshancun",
    "gn:population":0,
    "gn:timezone":"Asia/Shanghai",
    "iso:country":"CN",
    "name:zho_x_preferred":[
        "\u677e\u5c71\u6751"
    ],
    "wof:name":"Songshancun",
    "wof:placetype":"locality"
},
  "geometry": {"coordinates":[126.27603999999999,45.68398],"type":"Point"}
}