{
  "type": "Feature",
  "properties": {
    "gn:admin1_code":"19.0",
    "gn:asciiname":"Songshu Zuocan Zhongchang",
    "gn:country_code":"CN",
    "gn:dem":166,
    "gn:feature_class":"P",
    "gn:feature_code":"PPLF",
    "gn:name":"Songshu Zuocan Zhongchang",
    "gn:population":0,
    "gn:timezone":"Asia/Shanghai",
    "iso:country":"CN",
    "name:und_x_variant":[
        "\u677e\u6811\u67de\u8695\u79cd\u573a"
    ],
    "name:zho_x_preferred":[
        "\u677e\u6811\u67de\u8695\u79cd\u573a"
    ],
    "wof:name":"Songshu Zuocan Zhongchang",
    "wof:placetype":"locality"
},
  "geometry": {"coordinates":[124.38057999999999,42.69754],"type":"Point"}
}