{
  "type": "Feature",
  "properties": {
    "gn:admin1_code":"24.0",
    "gn:asciiname":"Xinjianping",
    "gn:country_code":"CN",
    "gn:dem":1859,
    "gn:feature_class":"P",
    "gn:feature_code":"PPL",
    "gn:name":"Xinjianping",
    "gn:population":0,
    "gn:timezone":"Asia/Shanghai",
    "iso:country":"CN",
    "name:und_x_variant":[
        "\u65b0\u5efa\u576a"
    ],
    "wof:name":"Xinjianping",
    "wof:placetype":"locality"
},
  "geometry": {"coordinates":[113.47317,39.38146],"type":"Point"}
}