{
  "type": "Feature",
  "properties": {
    "gn:admin1_code":"15.0",
    "gn:asciiname":"Wuxing Dadui",
    "gn:country_code":"CN",
    "gn:dem":1247,
    "gn:feature_class":"P",
    "gn:feature_code":"PPLF",
    "gn:name":"Wuxing Dadui",
    "gn:population":0,
    "gn:timezone":"Asia/Shanghai",
    "iso:country":"CN",
    "name:zho_x_preferred":[
        "\u4e94\u661f\u5927\u961f"
    ],
    "wof:name":"Wuxing Dadui",
    "wof:placetype":"locality"
},
  "geometry": {"coordinates":[99.0206,40.05],"type":"Point"}
}