{
  "type": "Feature",
  "properties": {
    "gn:admin1_code":"5.0",
    "gn:asciiname":"Shibahaocun",
    "gn:country_code":"CN",
    "gn:dem":159,
    "gn:feature_class":"P",
    "gn:feature_code":"PPL",
    "gn:name":"Shibahaocun",
    "gn:population":0,
    "gn:timezone":"Asia/Shanghai",
    "iso:country":"CN",
    "name:zho_x_preferred":[
        "\u5341\u516b\u53f7\u6751"
    ],
    "wof:name":"Shibahaocun",
    "wof:placetype":"locality"
},
  "geometry": {"coordinates":[123.67658,44.29881],"type":"Point"}
}