{
  "type": "Feature",
  "properties": {
    "gn:admin1_code":"3.0",
    "gn:asciiname":"Kuzhen",
    "gn:country_code":"CN",
    "gn:dem":95,
    "gn:feature_class":"P",
    "gn:feature_code":"PPL",
    "gn:name":"Kuzhen",
    "gn:population":0,
    "gn:timezone":"Asia/Shanghai",
    "iso:country":"CN",
    "name:zho_x_preferred":[
        "\u5800\u5733"
    ],
    "wof:name":"Kuzhen",
    "wof:placetype":"locality"
},
  "geometry": {"coordinates":[114.751,27.4335],"type":"Point"}
}