{
  "type": "Feature",
  "properties": {
    "gn:admin1_code":"16.0",
    "gn:asciiname":"Bocun",
    "gn:country_code":"CN",
    "gn:dem":113,
    "gn:feature_class":"P",
    "gn:feature_code":"PPL",
    "gn:name":"Bocun",
    "gn:population":0,
    "gn:timezone":"Asia/Shanghai",
    "iso:country":"CN",
    "name:zho_x_preferred":[
        "\u52c3\u6751"
    ],
    "wof:name":"Bocun",
    "wof:placetype":"locality"
},
  "geometry": {"coordinates":[109.30200000000001,24.2583],"type":"Point"}
}