{
  "type": "Feature",
  "properties": {
    "gn:admin1_code":"14",
    "gn:asciiname":"Laiququda",
    "gn:country_code":"CN",
    "gn:dem":4065,
    "gn:feature_class":"P",
    "gn:feature_code":"PPL",
    "gn:name":"Laiququda",
    "gn:population":0,
    "gn:timezone":"Asia/Urumqi",
    "iso:country":"CN",
    "name:zho_x_preferred":[
        "\u6765\u66f2\u66f2\u6253"
    ],
    "wof:name":"Laiququda",
    "wof:placetype":"locality"
},
  "geometry": {"coordinates":[89.06700000000002,29.1203],"type":"Point"}
}