{
  "type": "Feature",
  "properties": {
    "gn:admin1_code":"15.0",
    "gn:asciiname":"Zhuantai Xiacun",
    "gn:country_code":"CN",
    "gn:dem":2209,
    "gn:feature_class":"P",
    "gn:feature_code":"PPL",
    "gn:name":"Zhuantai Xiacun",
    "gn:population":0,
    "gn:timezone":"Asia/Shanghai",
    "iso:country":"CN",
    "name:zho_x_preferred":[
        "\u7816\u53f0\u4e0b\u6751"
    ],
    "wof:name":"Zhuantai Xiacun",
    "wof:placetype":"locality"
},
  "geometry": {"coordinates":[104.84999999999999,33.9282],"type":"Point"}
}