{
  "type": "Feature",
  "properties": {
    "gn:admin1_code":"5.0",
    "gn:asciiname":"Wangjiacun",
    "gn:country_code":"CN",
    "gn:dem":323,
    "gn:feature_class":"P",
    "gn:feature_code":"PPL",
    "gn:name":"Wangjiacun",
    "gn:population":0,
    "gn:timezone":"Asia/Shanghai",
    "iso:country":"CN",
    "name:zho_x_preferred":[
        "\u738b\u5bb6\u6751"
    ],
    "wof:name":"Wangjiacun",
    "wof:placetype":"locality"
},
  "geometry": {"coordinates":[125.84241000000002,42.72789],"type":"Point"}
}