{
  "type": "Feature",
  "properties": {
    "gn:admin1_code":"12.0",
    "gn:asciiname":"Gongjiashan",
    "gn:country_code":"CN",
    "gn:dem":98,
    "gn:feature_class":"P",
    "gn:feature_code":"PPL",
    "gn:name":"Gongjiashan",
    "gn:population":0,
    "gn:timezone":"Asia/Shanghai",
    "iso:country":"CN",
    "name:zho_x_preferred":[
        "Gongjiashan"
    ],
    "name:zho_x_variant":[
        "\u9f9a\u5bb6\u5c71"
    ],
    "wof:name":"Gongjiashan",
    "wof:placetype":"locality"
},
  "geometry": {"coordinates":[115.02978,29.57345],"type":"Point"}
}