{
  "type": "Feature",
  "properties": {
    "gn:admin1_code":"14.0",
    "gn:asciiname":"Repida",
    "gn:country_code":"CN",
    "gn:dem":4528,
    "gn:feature_class":"P",
    "gn:feature_code":"PPL",
    "gn:name":"Repida",
    "gn:population":0,
    "gn:timezone":"Asia/Urumqi",
    "iso:country":"CN",
    "name:bod_x_preferred":[
        "Ranp\u00eada"
    ],
    "name:zho_x_preferred":[
        "Repida"
    ],
    "name:zho_x_variant":[
        "\u60f9\u76ae\u8fbe"
    ],
    "wof:name":"Repida",
    "wof:placetype":"locality"
},
  "geometry": {"coordinates":[97.001,31.401],"type":"Point"}
}