{
  "type": "Feature",
  "properties": {
    "gn:admin1_code":"3.0",
    "gn:asciiname":"Tieluping",
    "gn:country_code":"CN",
    "gn:dem":115,
    "gn:feature_class":"P",
    "gn:feature_code":"PPL",
    "gn:name":"Tieluping",
    "gn:population":0,
    "gn:timezone":"Asia/Shanghai",
    "iso:country":"CN",
    "name:zho_x_preferred":[
        "\u94c1\u8def\u576a"
    ],
    "wof:name":"Tieluping",
    "wof:placetype":"locality"
},
  "geometry": {"coordinates":[117.66534,28.12969],"type":"Point"}
}