{
  "type": "Feature",
  "properties": {
    "gn:admin1_code":"29.0",
    "gn:asciiname":"Shanpianfang",
    "gn:country_code":"CN",
    "gn:dem":1142,
    "gn:feature_class":"P",
    "gn:feature_code":"PPL",
    "gn:name":"Shanpianfang",
    "gn:population":0,
    "gn:timezone":"Asia/Shanghai",
    "iso:country":"CN",
    "name:zho_x_preferred":[
        "\u95ea\u7247\u623f"
    ],
    "wof:name":"Shanpianfang",
    "wof:placetype":"locality"
},
  "geometry": {"coordinates":[100.931,22.7388],"type":"Point"}
}