{
  "type": "Feature",
  "properties": {
    "gn:admin1_code":"15.0",
    "gn:asciiname":"Bianchazi",
    "gn:country_code":"CN",
    "gn:dem":2003,
    "gn:feature_class":"P",
    "gn:feature_code":"PPL",
    "gn:name":"Bianchazi",
    "gn:population":0,
    "gn:timezone":"Asia/Shanghai",
    "iso:country":"CN",
    "name:zho_x_preferred":[
        "\u97ad\u5c94\u5b50"
    ],
    "wof:name":"Bianchazi",
    "wof:placetype":"locality"
},
  "geometry": {"coordinates":[104.16200000000001,36.0556],"type":"Point"}
}