{
  "type": "Feature",
  "properties": {
    "gn:admin1_code":"4.0",
    "gn:asciiname":"Dazhuxu",
    "gn:country_code":"CN",
    "gn:dem":6,
    "gn:feature_class":"P",
    "gn:feature_code":"PPL",
    "gn:name":"Dazhuxu",
    "gn:population":0,
    "gn:timezone":"Asia/Shanghai",
    "iso:country":"CN",
    "name:zho_x_preferred":[
        "Dazhuxu"
    ],
    "name:zho_x_variant":[
        "\u5927\u6731\u65ed"
    ],
    "wof:name":"Dazhuxu",
    "wof:placetype":"locality"
},
  "geometry": {"coordinates":[119.13755,34.86017],"type":"Point"}
}