{
  "type": "Feature",
  "properties": {
    "gn:admin1_code":"29.0",
    "gn:asciiname":"Mujiaying",
    "gn:country_code":"CN",
    "gn:dem":1464,
    "gn:feature_class":"P",
    "gn:feature_code":"PPL",
    "gn:name":"Mujiaying",
    "gn:population":0,
    "gn:timezone":"Asia/Shanghai",
    "iso:country":"CN",
    "name:zho_x_preferred":[
        "\u7a46\u5bb6\u8425"
    ],
    "wof:name":"Mujiaying",
    "wof:placetype":"locality"
},
  "geometry": {"coordinates":[104.92100000000001,27.5785],"type":"Point"}
}