{
  "type": "Feature",
  "properties": {
    "gn:admin1_code":"30",
    "gn:asciiname":"Shantang",
    "gn:country_code":"CN",
    "gn:dem":553,
    "gn:feature_class":"P",
    "gn:feature_code":"PPL",
    "gn:name":"Shantang",
    "gn:population":0,
    "gn:timezone":"Asia/Urumqi",
    "iso:country":"CN",
    "name:zho_x_preferred":[
        "\u5c71\u5858"
    ],
    "wof:name":"Shantang",
    "wof:placetype":"locality"
},
  "geometry": {"coordinates":[111.10883,22.20815],"type":"Point"}
}