{
  "type": "Feature",
  "properties": {
    "gn:country":"CN",
    "gn:fcode":"PPL",
    "gn:pop":8939,
    "iso:country":"CN",
    "name:unk_x_variant":[
        "Chijiantan"
    ],
    "name:zho_x_preferred":[
        "\u8d64\u571f"
    ],
    "qs:name":"Chitu",
    "qs:photos_9r":0,
    "qs:photos_sr":0,
    "qs:pop_sr":"5",
    "wd:wordcount":16,
    "wof:name":"Chitu",
    "wof:placetype":"locality",
    "wof:population":8939
},
  "geometry": {"coordinates":[117.40278000000001,39.20333],"type":"Point"}
}