{
  "type": "Feature",
  "properties": {
    "gn:admin1_code":"29.0",
    "gn:asciiname":"Juancaogou",
    "gn:country_code":"CN",
    "gn:dem":2976,
    "gn:feature_class":"P",
    "gn:feature_code":"PPL",
    "gn:name":"Juancaogou",
    "gn:population":0,
    "gn:timezone":"Asia/Shanghai",
    "iso:country":"CN",
    "name:zho_x_preferred":[
        "\u5377\u69fd\u6c9f"
    ],
    "wof:name":"Juancaogou",
    "wof:placetype":"locality"
},
  "geometry": {"coordinates":[102.967,26.2545],"type":"Point"}
}