{
  "type": "Feature",
  "properties": {
    "gn:admin1_code":"19.0",
    "gn:asciiname":"Sujiadian",
    "gn:country_code":"CN",
    "gn:dem":452,
    "gn:feature_class":"P",
    "gn:feature_code":"PPL",
    "gn:name":"Sujiadian",
    "gn:population":0,
    "gn:timezone":"Asia/Shanghai",
    "iso:country":"CN",
    "name:und_x_variant":[
        "\u82cf\u5bb6\u5e97"
    ],
    "name:zho_x_preferred":[
        "\u82cf\u5bb6\u5e97"
    ],
    "wof:name":"Sujiadian",
    "wof:placetype":"locality"
},
  "geometry": {"coordinates":[120.21821,41.28977],"type":"Point"}
}