{
  "type": "Feature",
  "properties": {
    "gn:admin1_code":"8.0",
    "gn:asciiname":"Gongsan Houcun",
    "gn:country_code":"CN",
    "gn:dem":179,
    "gn:feature_class":"P",
    "gn:feature_code":"PPL",
    "gn:name":"Gongsan Houcun",
    "gn:population":0,
    "gn:timezone":"Asia/Shanghai",
    "iso:country":"CN",
    "name:zho_x_preferred":[
        "\u606d\u4e09\u540e\u6751"
    ],
    "wof:name":"Gongsan Houcun",
    "wof:placetype":"locality"
},
  "geometry": {"coordinates":[126.83546,46.89733],"type":"Point"}
}