{
  "type": "Feature",
  "properties": {
    "gn:admin1_code":"29.0",
    "gn:asciiname":"Jialaxi",
    "gn:country_code":"CN",
    "gn:dem":979,
    "gn:feature_class":"P",
    "gn:feature_code":"PPL",
    "gn:name":"Jialaxi",
    "gn:population":0,
    "gn:timezone":"Asia/Shanghai",
    "iso:country":"CN",
    "name:zho_x_preferred":[
        "\u621b\u62c9\u897f"
    ],
    "wof:name":"Jialaxi",
    "wof:placetype":"locality"
},
  "geometry": {"coordinates":[103.47,23.0167],"type":"Point"}
}