{
  "type": "Feature",
  "properties": {
    "gn:admin1_code":"26.0",
    "gn:asciiname":"Caodiliang",
    "gn:country_code":"CN",
    "gn:dem":1050,
    "gn:feature_class":"P",
    "gn:feature_code":"PPL",
    "gn:name":"Caodiliang",
    "gn:population":0,
    "gn:timezone":"Asia/Shanghai",
    "iso:country":"CN",
    "name:zho_x_preferred":[
        "\u8349\u5730\u6881"
    ],
    "wof:name":"Caodiliang",
    "wof:placetype":"locality"
},
  "geometry": {"coordinates":[109.33503,38.04502],"type":"Point"}
}