{
  "type": "Feature",
  "properties": {
    "gn:admin1_code":"19.0",
    "gn:asciiname":"Xiaotaizi",
    "gn:country_code":"CN",
    "gn:dem":0,
    "gn:feature_class":"P",
    "gn:feature_code":"PPL",
    "gn:name":"Xiaotaizi",
    "gn:population":0,
    "gn:timezone":"Asia/Shanghai",
    "iso:country":"CN",
    "name:zho_x_preferred":[
        "\u5c0f\u53f0\u5b50"
    ],
    "wof:name":"Xiaotaizi",
    "wof:placetype":"locality"
},
  "geometry": {"coordinates":[121.827,40.9579],"type":"Point"}
}