{
  "type": "Feature",
  "properties": {
    "gn:admin1_code":"26.0",
    "gn:asciiname":"Zhoujiayuan",
    "gn:country_code":"CN",
    "gn:dem":1074,
    "gn:feature_class":"P",
    "gn:feature_code":"PPL",
    "gn:name":"Zhoujiayuan",
    "gn:population":0,
    "gn:timezone":"Asia/Shanghai",
    "iso:country":"CN",
    "name:zho_x_preferred":[
        "\u5468\u5bb6\u9662"
    ],
    "wof:name":"Zhoujiayuan",
    "wof:placetype":"locality"
},
  "geometry": {"coordinates":[109.98215999999999,34.08872],"type":"Point"}
}