{
  "type": "Feature",
  "properties": {
    "gn:admin1_code":"26.0",
    "gn:asciiname":"Goujiayuan",
    "gn:country_code":"CN",
    "gn:dem":1326,
    "gn:feature_class":"P",
    "gn:feature_code":"PPL",
    "gn:name":"Goujiayuan",
    "gn:population":0,
    "gn:timezone":"Asia/Shanghai",
    "iso:country":"CN",
    "name:und_x_variant":[
        "\u82df\u5bb6\u9662"
    ],
    "wof:name":"Goujiayuan",
    "wof:placetype":"locality"
},
  "geometry": {"coordinates":[106.67234999999999,33.81879],"type":"Point"}
}