{
  "type": "Feature",
  "properties": {
    "gn:admin1_code":"16.0",
    "gn:asciiname":"Qianhe",
    "gn:country_code":"CN",
    "gn:dem":257,
    "gn:feature_class":"P",
    "gn:feature_code":"PPL",
    "gn:name":"Qianhe",
    "gn:population":0,
    "gn:timezone":"Asia/Shanghai",
    "iso:country":"CN",
    "name:zho_x_preferred":[
        "\u4e7e\u5408"
    ],
    "wof:name":"Qianhe",
    "wof:placetype":"locality"
},
  "geometry": {"coordinates":[108.271,24.6825],"type":"Point"}
}