{
  "type": "Feature",
  "properties": {
    "gn:admin1_code":"6.0",
    "gn:asciiname":"Laiye",
    "gn:country_code":"CN",
    "gn:dem":3925,
    "gn:feature_class":"P",
    "gn:feature_code":"PPL",
    "gn:name":"Laiye",
    "gn:population":0,
    "gn:timezone":"Asia/Urumqi",
    "iso:country":"CN",
    "name:zho_x_preferred":[
        "\u6765\u53f6"
    ],
    "wof:name":"Laiye",
    "wof:placetype":"locality"
},
  "geometry": {"coordinates":[96.61485999999999,33.562],"type":"Point"}
}