{
  "type": "Feature",
  "properties": {
    "gn:admin1_code":"16.0",
    "gn:asciiname":"Liuxincun",
    "gn:country_code":"CN",
    "gn:dem":92,
    "gn:feature_class":"P",
    "gn:feature_code":"PPL",
    "gn:name":"Liuxincun",
    "gn:population":0,
    "gn:timezone":"Asia/Shanghai",
    "iso:country":"CN",
    "name:zho_x_preferred":[
        "\u516d\u65b0\u6751"
    ],
    "wof:name":"Liuxincun",
    "wof:placetype":"locality"
},
  "geometry": {"coordinates":[109.55800000000001,22.3446],"type":"Point"}
}