{
  "type": "Feature",
  "properties": {
    "gn:admin1_code":"19.0",
    "gn:asciiname":"Chenjiatuncun",
    "gn:country_code":"CN",
    "gn:dem":39,
    "gn:feature_class":"P",
    "gn:feature_code":"PPL",
    "gn:name":"Chenjiatuncun",
    "gn:population":0,
    "gn:timezone":"Asia/Shanghai",
    "iso:country":"CN",
    "name:zho_x_preferred":[
        "\u9648\u5bb6\u5c6f\u6751"
    ],
    "wof:name":"Chenjiatuncun",
    "wof:placetype":"locality"
},
  "geometry": {"coordinates":[120.99942,40.97402],"type":"Point"}
}