{
  "type": "Feature",
  "properties": {
    "gn:admin1_code":"3.0",
    "gn:asciiname":"Banqiaocun",
    "gn:country_code":"CN",
    "gn:dem":25,
    "gn:feature_class":"P",
    "gn:feature_code":"PPL",
    "gn:name":"Banqiaocun",
    "gn:population":0,
    "gn:timezone":"Asia/Shanghai",
    "iso:country":"CN",
    "name:und_x_variant":[
        "\u677f\u6865\u6751"
    ],
    "wof:name":"Banqiaocun",
    "wof:placetype":"locality"
},
  "geometry": {"coordinates":[115.9003,28.55996],"type":"Point"}
}