{
  "type": "Feature",
  "properties": {
    "gn:admin1_code":"26.0",
    "gn:asciiname":"Qingfengyuan",
    "gn:country_code":"CN",
    "gn:dem":1596,
    "gn:feature_class":"P",
    "gn:feature_code":"PPL",
    "gn:name":"Qingfengyuan",
    "gn:population":0,
    "gn:timezone":"Asia/Shanghai",
    "iso:country":"CN",
    "name:und_x_variant":[
        "\u9752\u5cf0\u9662"
    ],
    "wof:name":"Qingfengyuan",
    "wof:placetype":"locality"
},
  "geometry": {"coordinates":[106.48775000000001,33.86485],"type":"Point"}
}