{
  "type": "Feature",
  "properties": {
    "gn:admin1_code":"10",
    "gn:asciiname":"Sanqingbu",
    "gn:country_code":"CN",
    "gn:dem":1510,
    "gn:feature_class":"P",
    "gn:feature_code":"PPL",
    "gn:name":"Sanqingbu",
    "gn:population":0,
    "gn:timezone":"Asia/Shanghai",
    "iso:country":"CN",
    "name:zho_x_preferred":[
        "\u4e09\u9877\u535c"
    ],
    "wof:name":"Sanqingbu",
    "wof:placetype":"locality"
},
  "geometry": {"coordinates":[114.60735,41.95818],"type":"Point"}
}