{
  "type": "Feature",
  "properties": {
    "gn:admin1_code":"29",
    "gn:asciiname":"Hsin-ti-tang",
    "gn:country_code":"CN",
    "gn:dem":682,
    "gn:feature_class":"P",
    "gn:feature_code":"PPL",
    "gn:name":"Hsin-ti-tang",
    "gn:population":0,
    "gn:timezone":"Asia/Shanghai",
    "iso:country":"CN",
    "wof:name":"Hsin-ti-tang",
    "wof:placetype":"locality"
},
  "geometry": {"coordinates":[103.92111,22.92194],"type":"Point"}
}