{
  "type": "Feature",
  "properties": {
    "gn:admin1_code":"14.0",
    "gn:asciiname":"Haikongma",
    "gn:country_code":"CN",
    "gn:dem":4652,
    "gn:feature_class":"P",
    "gn:feature_code":"PPL",
    "gn:name":"Haikongma",
    "gn:population":0,
    "gn:timezone":"Asia/Urumqi",
    "iso:country":"CN",
    "name:zho_x_preferred":[
        "\u9a87\u5b54\u739b"
    ],
    "wof:name":"Haikongma",
    "wof:placetype":"locality"
},
  "geometry": {"coordinates":[90.47662,31.79306],"type":"Point"}
}