{
  "type": "Feature",
  "properties": {
    "gn:admin1_code":"8.0",
    "gn:asciiname":"Wenhuacun",
    "gn:country_code":"CN",
    "gn:dem":180,
    "gn:feature_class":"P",
    "gn:feature_code":"PPL",
    "gn:name":"Wenhuacun",
    "gn:population":0,
    "gn:timezone":"Asia/Shanghai",
    "iso:country":"CN",
    "name:zho_x_preferred":[
        "\u6587\u5316\u6751"
    ],
    "wof:name":"Wenhuacun",
    "wof:placetype":"locality"
},
  "geometry": {"coordinates":[125.59303,46.79435],"type":"Point"}
}