{
  "type": "Feature",
  "properties": {
    "gn:admin1_code":"12.0",
    "gn:asciiname":"Xiaofanzhou",
    "gn:country_code":"CN",
    "gn:dem":77,
    "gn:feature_class":"P",
    "gn:feature_code":"PPL",
    "gn:name":"Xiaofanzhou",
    "gn:population":0,
    "gn:timezone":"Asia/Shanghai",
    "iso:country":"CN",
    "name:zho_x_preferred":[
        "\u5c0f\u6a0a\u6d32"
    ],
    "wof:name":"Xiaofanzhou",
    "wof:placetype":"locality"
},
  "geometry": {"coordinates":[111.82717,32.09244],"type":"Point"}
}