{
  "type": "Feature",
  "properties": {
    "gn:admin1_code":"16",
    "gn:asciiname":"Dakouyan",
    "gn:country_code":"CN",
    "gn:dem":291,
    "gn:feature_class":"P",
    "gn:feature_code":"PPL",
    "gn:name":"Dakouyan",
    "gn:population":0,
    "gn:timezone":"Asia/Shanghai",
    "iso:country":"CN",
    "name:zho_x_preferred":[
        "\u5927\u53e3\u5ca9"
    ],
    "wof:name":"Dakouyan",
    "wof:placetype":"locality"
},
  "geometry": {"coordinates":[110.86,25.6419],"type":"Point"}
}