{
  "type": "Feature",
  "properties": {
    "gn:admin1_code":"26.0",
    "gn:asciiname":"Dashaotai",
    "gn:country_code":"CN",
    "gn:dem":1185,
    "gn:feature_class":"P",
    "gn:feature_code":"PPL",
    "gn:name":"Dashaotai",
    "gn:population":0,
    "gn:timezone":"Asia/Shanghai",
    "iso:country":"CN",
    "name:zho_x_preferred":[
        "\u5927\u70e7\u53f0"
    ],
    "wof:name":"Dashaotai",
    "wof:placetype":"locality"
},
  "geometry": {"coordinates":[107.41278,32.77379000000001],"type":"Point"}
}