{
  "type": "Feature",
  "properties": {
    "gn:admin1_code":"3.0",
    "gn:asciiname":"Saozhou Lingtou",
    "gn:country_code":"CN",
    "gn:dem":956,
    "gn:feature_class":"P",
    "gn:feature_code":"PPL",
    "gn:name":"Saozhou Lingtou",
    "gn:population":0,
    "gn:timezone":"Asia/Shanghai",
    "iso:country":"CN",
    "name:zho_x_preferred":[
        "\u626b\u5e1a\u5cad\u5934"
    ],
    "wof:name":"Saozhou Lingtou",
    "wof:placetype":"locality"
},
  "geometry": {"coordinates":[118.20442,28.23455],"type":"Point"}
}