{
  "type": "Feature",
  "properties": {
    "gn:admin1_code":"11.0",
    "gn:asciiname":"Jiaqiaochong",
    "gn:country_code":"CN",
    "gn:dem":871,
    "gn:feature_class":"P",
    "gn:feature_code":"PPL",
    "gn:name":"Jiaqiaochong",
    "gn:population":0,
    "gn:timezone":"Asia/Shanghai",
    "iso:country":"CN",
    "name:zho_x_preferred":[
        "\u67b6\u6865\u51b2"
    ],
    "wof:name":"Jiaqiaochong",
    "wof:placetype":"locality"
},
  "geometry": {"coordinates":[110.33556000000002,26.16911],"type":"Point"}
}