{
  "type": "Feature",
  "properties": {
    "gn:admin1_code":"6.0",
    "gn:asciiname":"Dengkousai",
    "gn:country_code":"CN",
    "gn:dem":4010,
    "gn:feature_class":"P",
    "gn:feature_code":"PPL",
    "gn:name":"Dengkousai",
    "gn:population":0,
    "gn:timezone":"Asia/Urumqi",
    "iso:country":"CN",
    "name:zho_x_preferred":[
        "\u767b\u6263\u8d5b"
    ],
    "wof:name":"Dengkousai",
    "wof:placetype":"locality"
},
  "geometry": {"coordinates":[97.18228000000001,32.83077],"type":"Point"}
}