{
  "type": "Feature",
  "properties": {
    "gn:admin1_code":"24.0",
    "gn:asciiname":"Fangtou",
    "gn:country_code":"CN",
    "gn:dem":1037,
    "gn:feature_class":"P",
    "gn:feature_code":"PPL",
    "gn:name":"Fangtou",
    "gn:population":0,
    "gn:timezone":"Asia/Shanghai",
    "iso:country":"CN",
    "name:zho_x_preferred":[
        "\u623f\u5934"
    ],
    "wof:name":"Fangtou",
    "wof:placetype":"locality"
},
  "geometry": {"coordinates":[112.66746999999999,36.08149],"type":"Point"}
}