{
  "type": "Feature",
  "properties": {
    "gn:admin1_code":"4.0",
    "gn:asciiname":"Kainan Gongqu",
    "gn:country_code":"CN",
    "gn:dem":4,
    "gn:feature_class":"P",
    "gn:feature_code":"PPLF",
    "gn:name":"Kainan Gongqu",
    "gn:population":0,
    "gn:timezone":"Asia/Shanghai",
    "iso:country":"CN",
    "name:zho_x_preferred":[
        "\u5f00\u5357\u5de5\u533a"
    ],
    "wof:name":"Kainan Gongqu",
    "wof:placetype":"locality"
},
  "geometry": {"coordinates":[120.93277999999999,31.891],"type":"Point"}
}