{
  "type": "Feature",
  "properties": {
    "gn:admin1_code":"29.0",
    "gn:asciiname":"Fengmi",
    "gn:country_code":"CN",
    "gn:dem":2209,
    "gn:feature_class":"P",
    "gn:feature_code":"PPL",
    "gn:name":"Fengmi",
    "gn:population":0,
    "gn:timezone":"Asia/Shanghai",
    "iso:country":"CN",
    "name:zho_x_preferred":[
        "\u9022\u5bc6"
    ],
    "wof:name":"Fengmi",
    "wof:placetype":"locality"
},
  "geometry": {"coordinates":[100.215,26.6672],"type":"Point"}
}