{
  "type": "Feature",
  "properties": {
    "gn:admin1_code":"33.0",
    "gn:asciiname":"Dangyang",
    "gn:country_code":"CN",
    "gn:dem":1425,
    "gn:feature_class":"P",
    "gn:feature_code":"PPL",
    "gn:name":"Dangyang",
    "gn:population":0,
    "gn:timezone":"Asia/Shanghai",
    "iso:country":"CN",
    "name:deu_x_preferred":[
        "Dangyang"
    ],
    "name:fra_x_preferred":[
        "Dangyang"
    ],
    "name:ita_x_preferred":[
        "Dangyang"
    ],
    "name:jpn_x_preferred":[
        "\u5f53\u967d\u5e02"
    ],
    "name:kik_x_preferred":[
        "Dangyang"
    ],
    "name:kor_x_preferred":[
        "\ub2f9\uc591\uc2dc"
    ],
    "name:mlg_x_preferred":[
        "Dangyang"
    ],
    "name:nld_x_preferred":[
        "Dangyang"
    ],
    "name:nor_x_preferred":[
        "Dangyang"
    ],
    "name:pam_x_preferred":[
        "Dangyang"
    ],
    "name:pol_x_preferred":[
        "Dangyang"
    ],
    "name:swe_x_preferred":[
        "Dangyang"
    ],
    "name:vie_x_preferred":[
        "\u0110\u01b0\u01a1ng D\u01b0\u01a1ng"
    ],
    "name:war_x_preferred":[
        "Dangyang"
    ],
    "name:zho_x_preferred":[
        "\u5f53\u9633"
    ],
    "name:zho_x_variant":[
        "\u5f53\u9633\u5e02"
    ],
    "wof:name":"Dangyang",
    "wof:placetype":"locality"
},
  "geometry": {"coordinates":[108.74464,31.75276],"type":"Point"}
}