{
  "type": "Feature",
  "properties": {
    "gn:admin1_code":"33.0",
    "gn:asciiname":"Dangyang",
    "gn:country_code":"CN",
    "gn:dem":1425,
    "gn:feature_class":"P",
    "gn:feature_code":"PPL",
    "gn:name":"Dangyang",
    "gn:population":0,
    "gn:timezone":"Asia/Shanghai",
    "iso:country":"CN",
    "name:zho_x_preferred":[
        "\u5f53\u9633"
    ],
    "wof:name":"Dangyang",
    "wof:placetype":"locality"
},
  "geometry": {"coordinates":[108.74464,31.75276],"type":"Point"}
}