{
  "type": "Feature",
  "properties": {
    "gn:admin1_code":"11",
    "gn:asciiname":"Qiaotouhe",
    "gn:country_code":"CN",
    "gn:dem":90,
    "gn:feature_class":"P",
    "gn:feature_code":"PPL",
    "gn:name":"Qiaotouhe",
    "gn:population":0,
    "gn:timezone":"Asia/Shanghai",
    "iso:country":"CN",
    "name:und_x_variant":[
        "Ch\u2019iao-t\u2019ou-ho",
        "Qiaotouhe"
    ],
    "name:zho_x_preferred":[
        "\u6865\u5934\u6cb3"
    ],
    "name:zho_x_variant":[
        "\u6865\u5934\u6cb3\u9547"
    ],
    "wof:name":"Qiaotouhe",
    "wof:placetype":"locality"
},
  "geometry": {"coordinates":[112.13146,28.33901],"type":"Point"}
}