{
  "type": "Feature",
  "properties": {
    "gn:admin1_code":"15.0",
    "gn:asciiname":"Shang'erchali",
    "gn:country_code":"CN",
    "gn:dem":3051,
    "gn:feature_class":"P",
    "gn:feature_code":"PPL",
    "gn:name":"Shang\u2019erchali",
    "gn:population":0,
    "gn:timezone":"Asia/Shanghai",
    "iso:country":"CN",
    "name:und_x_variant":[
        "Shang\u2019erchali",
        "\u4e0a\u4e8c\u5c94\u91cc"
    ],
    "wof:name":"Shang'erchali",
    "wof:placetype":"locality"
},
  "geometry": {"coordinates":[104.16446000000001,34.63639000000001],"type":"Point"}
}