{
  "type": "Feature",
  "properties": {
    "gn:admin1_code":"7.0",
    "gn:asciiname":"Kenghuang",
    "gn:country_code":"CN",
    "gn:dem":19,
    "gn:feature_class":"P",
    "gn:feature_code":"PPL",
    "gn:name":"Kenghuang",
    "gn:population":0,
    "gn:timezone":"Asia/Shanghai",
    "iso:country":"CN",
    "name:zho_x_preferred":[
        "\u5751\u9ec4"
    ],
    "wof:name":"Kenghuang",
    "wof:placetype":"locality"
},
  "geometry": {"coordinates":[118.93247,24.98206],"type":"Point"}
}