{
  "type": "Feature",
  "properties": {
    "gn:admin1_code":"4.0",
    "gn:asciiname":"Nijiazhai",
    "gn:country_code":"CN",
    "gn:dem":5,
    "gn:feature_class":"P",
    "gn:feature_code":"PPL",
    "gn:name":"Nijiazhai",
    "gn:population":0,
    "gn:timezone":"Asia/Shanghai",
    "iso:country":"CN",
    "name:zho_x_preferred":[
        "\u502a\u5bb6\u5b85"
    ],
    "wof:name":"Nijiazhai",
    "wof:placetype":"locality"
},
  "geometry": {"coordinates":[121.46312,32.01701],"type":"Point"}
}