{
  "type": "Feature",
  "properties": {
    "gn:admin1_code":"25.0",
    "gn:asciiname":"Sunjiahuang",
    "gn:country_code":"CN",
    "gn:dem":39,
    "gn:feature_class":"P",
    "gn:feature_code":"PPL",
    "gn:name":"Sunjiahuang",
    "gn:population":0,
    "gn:timezone":"Asia/Shanghai",
    "iso:country":"CN",
    "name:zho_x_preferred":[
        "\u5b59\u5bb6\u8352"
    ],
    "wof:name":"Sunjiahuang",
    "wof:placetype":"locality"
},
  "geometry": {"coordinates":[120.07818,36.72228],"type":"Point"}
}