{
  "type": "Feature",
  "properties": {
    "gn:admin1_code":"1.0",
    "gn:asciiname":"Jiuyi",
    "gn:country_code":"CN",
    "gn:dem":45,
    "gn:feature_class":"P",
    "gn:feature_code":"PPL",
    "gn:name":"Jiuyi",
    "gn:population":0,
    "gn:timezone":"Asia/Shanghai",
    "iso:country":"CN",
    "name:zho_x_preferred":[
        "\u4e5d\u4e49"
    ],
    "wof:name":"Jiuyi",
    "wof:placetype":"locality"
},
  "geometry": {"coordinates":[118.34411,30.62638],"type":"Point"}
}