{
  "type": "Feature",
  "properties": {
    "gn:admin1_code":"25.0",
    "gn:asciiname":"Daozi",
    "gn:country_code":"CN",
    "gn:dem":47,
    "gn:feature_class":"P",
    "gn:feature_code":"PPL",
    "gn:name":"Daozi",
    "gn:population":0,
    "gn:timezone":"Asia/Shanghai",
    "iso:country":"CN",
    "name:zho_x_preferred":[
        "\u5c9b\u5b50"
    ],
    "wof:name":"Daozi",
    "wof:placetype":"locality"
},
  "geometry": {"coordinates":[121.30991000000002,37.06647],"type":"Point"}
}