{
  "type": "Feature",
  "properties": {
    "gn:admin1_code":"26.0",
    "gn:asciiname":"Huang'er Zhuangcun",
    "gn:country_code":"CN",
    "gn:dem":1413,
    "gn:feature_class":"P",
    "gn:feature_code":"PPL",
    "gn:name":"Huang\u2019er Zhuangcun",
    "gn:population":0,
    "gn:timezone":"Asia/Shanghai",
    "iso:country":"CN",
    "name:und_x_variant":[
        "Huang\u2019er Zhuangcun"
    ],
    "name:zho_x_preferred":[
        "\u9ec4\u5c14\u5e84\u6751"
    ],
    "wof:name":"Huang'er Zhuangcun",
    "wof:placetype":"locality"
},
  "geometry": {"coordinates":[107.38,37.4604],"type":"Point"}
}