{
  "type": "Feature",
  "properties": {
    "gn:admin1_code":"29.0",
    "gn:asciiname":"Ermuzu",
    "gn:country_code":"CN",
    "gn:dem":1853,
    "gn:feature_class":"P",
    "gn:feature_code":"PPL",
    "gn:name":"Ermuzu",
    "gn:population":0,
    "gn:timezone":"Asia/Shanghai",
    "iso:country":"CN",
    "name:zho_x_preferred":[
        "\u4e8c\u6bcd\u7956"
    ],
    "wof:name":"Ermuzu",
    "wof:placetype":"locality"
},
  "geometry": {"coordinates":[99.93429999999999,25.0518],"type":"Point"}
}