{
  "type": "Feature",
  "properties": {
    "gn:country":"CN",
    "gn:fcode":"ADM3",
    "gn:pop":636479,
    "iso:country":"CN",
    "name:eng_x_preferred":[
        "Shunyi Xian"
    ],
    "name:eng_x_variant":[
        "Shunyi",
        "Shunyi qu"
    ],
    "name:unk_x_variant":[
        "Shun-i Hsien"
    ],
    "name:zho_x_preferred":[
        "\u987a\u4e49\u533a"
    ],
    "name:zho_x_variant":[
        "\u987a\u4e49",
        "Shunyi"
    ],
    "qs:name":"Shunyi Qu",
    "qs:photos_9r":0,
    "qs:photos_sr":0,
    "qs:pop_sr":"11",
    "wd:wordcount":1516,
    "wof:name":"Shunyi Qu",
    "wof:placetype":"localadmin",
    "wof:population":636479
},
  "geometry": {"coordinates":[116.70959999999999,40.15652],"type":"Point"}
}