{
  "type": "Feature",
  "properties": {
    "gn:country":"CN",
    "gn:fcode":"ADM3",
    "gn:population":636479,
    "iso:country":"CN",
    "name:ara_x_preferred":[
        "\u0634\u0627\u0646\u064a"
    ],
    "name:ast_x_preferred":[
        "Shunyi"
    ],
    "name:cdo_x_preferred":[
        "S\u00f3ng-ngi\u00ea-k\u1e73\u0306"
    ],
    "name:ceb_x_preferred":[
        "Shunyi"
    ],
    "name:ces_x_preferred":[
        "\u0160un-i"
    ],
    "name:cym_x_preferred":[
        "Ardal Shunyi"
    ],
    "name:dan_x_preferred":[
        "Shunyi"
    ],
    "name:deu_x_preferred":[
        "Shunyi"
    ],
    "name:eng_x_preferred":[
        "Shunyi Xian"
    ],
    "name:eng_x_variant":[
        "Shunyi",
        "Shunyi qu",
        "Shunyi District"
    ],
    "name:eus_x_preferred":[
        "Shunyi barrutia"
    ],
    "name:fas_x_preferred":[
        "\u0634\u0648\u0646\u06cc\u0627\u06cc"
    ],
    "name:gan_x_preferred":[
        "\u987a\u4e49\u533a"
    ],
    "name:heb_x_preferred":[
        "\u05e8\u05d5\u05d1\u05e2 \u05e9\u05d5\u05e0\u05d9\u05d9"
    ],
    "name:hun_x_preferred":[
        "Shunyi"
    ],
    "name:ind_x_preferred":[
        "Distrik Shunyi"
    ],
    "name:jpn_x_preferred":[
        "\u9806\u7fa9\u533a"
    ],
    "name:kor_x_preferred":[
        "\uc21c\uc774\uad6c"
    ],
    "name:mwl_x_preferred":[
        "Shunyi"
    ],
    "name:nan_x_preferred":[
        "S\u016bn-g\u012b-khu"
    ],
    "name:nld_x_preferred":[
        "Shunyi District"
    ],
    "name:nob_x_preferred":[
        "Shunyi"
    ],
    "name:pol_x_preferred":[
        "Shunyi"
    ],
    "name:rus_x_preferred":[
        "\u0428\u0443\u043d\u044c\u0438"
    ],
    "name:spa_x_preferred":[
        "Shunyi"
    ],
    "name:swe_x_preferred":[
        "Shunyi"
    ],
    "name:tur_x_preferred":[
        "Shunyi"
    ],
    "name:ukr_x_preferred":[
        "\u0428\u0443\u043d\u044c\u0457"
    ],
    "name:und_x_variant":[
        "Shun-i Hsien"
    ],
    "name:urd_x_preferred":[
        "\u0634\u0648\u0646\u06cc\u0626\u06cc \u0636\u0644\u0639"
    ],
    "name:vie_x_preferred":[
        "Thu\u1eadn Ngh\u0129a"
    ],
    "name:war_x_preferred":[
        "Distrito han Shunyi"
    ],
    "name:wuu_x_preferred":[
        "\u987a\u4e49\u533a"
    ],
    "name:yue_x_preferred":[
        "\u9806\u7fa9\u5340"
    ],
    "name:zho_x_preferred":[
        "\u987a\u4e49\u533a"
    ],
    "name:zho_x_variant":[
        "\u987a\u4e49",
        "Shunyi",
        "\u9806\u7fa9\u5340"
    ],
    "qs:name":"Shunyi Qu",
    "qs:photos_9r":0,
    "qs:photos_sr":0,
    "qs:pop_sr":"11",
    "wd:wordcount":1516,
    "wof:name":"Shunyi Qu",
    "wof:placetype":"localadmin",
    "wof:population":636479
},
  "geometry": {"coordinates":[116.70959999999999,40.15652],"type":"Point"}
}