{
  "type": "Feature",
  "properties": {
    "gn:admin1_code":"2.0",
    "gn:asciiname":"Likengwu",
    "gn:country_code":"CN",
    "gn:dem":221,
    "gn:feature_class":"P",
    "gn:feature_code":"PPL",
    "gn:name":"Likengwu",
    "gn:population":0,
    "gn:timezone":"Asia/Shanghai",
    "iso:country":"CN",
    "name:zho_x_preferred":[
        "\u91cc\u5751\u575e"
    ],
    "wof:name":"Likengwu",
    "wof:placetype":"locality"
},
  "geometry": {"coordinates":[119.07415,29.82352],"type":"Point"}
}