{
  "type": "Feature",
  "properties": {
    "gn:admin1_code":"8.0",
    "gn:asciiname":"Xincheng Sandui",
    "gn:country_code":"CN",
    "gn:dem":237,
    "gn:feature_class":"P",
    "gn:feature_code":"PPLF",
    "gn:name":"Xincheng Sandui",
    "gn:population":0,
    "gn:timezone":"Asia/Shanghai",
    "iso:country":"CN",
    "name:zho_x_preferred":[
        "\u65b0\u57ce\u4e09\u961f"
    ],
    "wof:name":"Xincheng Sandui",
    "wof:placetype":"locality"
},
  "geometry": {"coordinates":[131.19540000000001,45.0981],"type":"Point"}
}