{
  "type": "Feature",
  "properties": {
    "gn:admin1_code":"16.0",
    "gn:asciiname":"Hushuangcun",
    "gn:country_code":"CN",
    "gn:dem":68,
    "gn:feature_class":"P",
    "gn:feature_code":"PPL",
    "gn:name":"Hushuangcun",
    "gn:population":0,
    "gn:timezone":"Asia/Shanghai",
    "iso:country":"CN",
    "name:zho_x_preferred":[
        "\u62a4\u53cc\u6751"
    ],
    "wof:name":"Hushuangcun",
    "wof:placetype":"locality"
},
  "geometry": {"coordinates":[110.01600000000001,22.3426],"type":"Point"}
}