{
  "type": "Feature",
  "properties": {
    "gn:admin1_code":"12.0",
    "gn:asciiname":"Heigoushan",
    "gn:country_code":"CN",
    "gn:dem":528,
    "gn:feature_class":"P",
    "gn:feature_code":"PPL",
    "gn:name":"Heigoushan",
    "gn:population":0,
    "gn:timezone":"Asia/Shanghai",
    "iso:country":"CN",
    "name:zho_x_preferred":[
        "\u9ed1\u6c9f\u5c71"
    ],
    "wof:name":"Heigoushan",
    "wof:placetype":"locality"
},
  "geometry": {"coordinates":[111.00736000000001,32.93714],"type":"Point"}
}