{
  "type": "Feature",
  "properties": {
    "gn:admin1_code":"16.0",
    "gn:asciiname":"Daoshi",
    "gn:country_code":"CN",
    "gn:dem":119,
    "gn:feature_class":"P",
    "gn:feature_code":"PPL",
    "gn:name":"Daoshi",
    "gn:population":0,
    "gn:timezone":"Asia/Shanghai",
    "iso:country":"CN",
    "name:zho_x_preferred":[
        "\u9053\u77f3"
    ],
    "wof:name":"Daoshi",
    "wof:placetype":"locality"
},
  "geometry": {"coordinates":[111.486,24.3771],"type":"Point"}
}