{
  "type": "Feature",
  "properties": {
    "gn:admin1_code":"3",
    "gn:asciiname":"Xiaowuling",
    "gn:country_code":"CN",
    "gn:dem":97,
    "gn:feature_class":"P",
    "gn:feature_code":"PPL",
    "gn:name":"Xiaowuling",
    "gn:population":0,
    "gn:timezone":"Asia/Shanghai",
    "iso:country":"CN",
    "name:zho_x_preferred":[
        "\u9704\u575e\u5cad"
    ],
    "wof:name":"Xiaowuling",
    "wof:placetype":"locality"
},
  "geometry": {"coordinates":[114.783,26.862],"type":"Point"}
}