{
  "type": "Feature",
  "properties": {
    "gn:admin1_code":"6.0",
    "gn:asciiname":"Jiande",
    "gn:country_code":"CN",
    "gn:dem":3440,
    "gn:feature_class":"P",
    "gn:feature_code":"PPL",
    "gn:name":"Jiande",
    "gn:population":0,
    "gn:timezone":"Asia/Shanghai",
    "iso:country":"CN",
    "name:und_x_variant":[
        "\u5c16\u5fb7"
    ],
    "wof:name":"Jiande",
    "wof:placetype":"locality"
},
  "geometry": {"coordinates":[102.33897,35.23931],"type":"Point"}
}