{
  "type": "Feature",
  "properties": {
    "gn:admin1_code":"6.0",
    "gn:asciiname":"Jiande",
    "gn:country_code":"CN",
    "gn:dem":3440,
    "gn:feature_class":"P",
    "gn:feature_code":"PPL",
    "gn:name":"Jiande",
    "gn:population":0,
    "gn:timezone":"Asia/Shanghai",
    "iso:country":"CN",
    "name:deu_x_preferred":[
        "Jiande"
    ],
    "name:eus_x_preferred":[
        "Jiande"
    ],
    "name:fra_x_preferred":[
        "Jiande"
    ],
    "name:hak_x_preferred":[
        "Kien-tet-s\u1e73"
    ],
    "name:ita_x_preferred":[
        "Jiande"
    ],
    "name:jpn_x_preferred":[
        "\u5efa\u5fb3\u5e02"
    ],
    "name:kik_x_preferred":[
        "Jiande"
    ],
    "name:kor_x_preferred":[
        "\uc820\ub354\uc2dc"
    ],
    "name:nld_x_preferred":[
        "Jiande"
    ],
    "name:nor_x_preferred":[
        "Jiande"
    ],
    "name:pol_x_preferred":[
        "Jiande"
    ],
    "name:spa_x_preferred":[
        "Jiande"
    ],
    "name:swe_x_preferred":[
        "Jiande"
    ],
    "name:tgl_x_preferred":[
        "Jiate"
    ],
    "name:und_x_variant":[
        "\u5c16\u5fb7"
    ],
    "name:urd_x_preferred":[
        "\u062c\u06cc\u0627\u0646\u062f\u0648"
    ],
    "name:vie_x_preferred":[
        "Ki\u1ebfn \u0110\u1ee9c"
    ],
    "name:wuu_x_preferred":[
        "\u5efa\u5fb7\u5e02"
    ],
    "name:zho_x_preferred":[
        "\u5efa\u5fb7\u5e02"
    ],
    "wof:name":"Jiande",
    "wof:placetype":"locality"
},
  "geometry": {"coordinates":[102.33897,35.23931],"type":"Point"}
}