{
  "type": "Feature",
  "properties": {
    "gn:admin1_code":"10.0",
    "gn:asciiname":"Ganqiu",
    "gn:country_code":"CN",
    "gn:dem":343,
    "gn:feature_class":"P",
    "gn:feature_code":"PPL",
    "gn:name":"Ganqiu",
    "gn:population":0,
    "gn:timezone":"Asia/Shanghai",
    "iso:country":"CN",
    "name:zho_x_preferred":[
        "\u7518\u79cb"
    ],
    "wof:name":"Ganqiu",
    "wof:placetype":"locality"
},
  "geometry": {"coordinates":[113.90267,38.22809],"type":"Point"}
}