{
  "type": "Feature",
  "properties": {
    "gn:admin1_code":"10",
    "gn:asciiname":"Wangshawo",
    "gn:country_code":"CN",
    "gn:dem":20,
    "gn:feature_class":"P",
    "gn:feature_code":"PPL",
    "gn:name":"Wangshawo",
    "gn:population":0,
    "gn:timezone":"Asia/Shanghai",
    "iso:country":"CN",
    "name:zho_x_preferred":[
        "\u738b\u6c99\u7a9d"
    ],
    "wof:name":"Wangshawo",
    "wof:placetype":"locality"
},
  "geometry": {"coordinates":[116.38978,37.72141],"type":"Point"}
}