{
  "type": "Feature",
  "properties": {
    "gn:admin1_code":"26.0",
    "gn:asciiname":"Xijiangducun",
    "gn:country_code":"CN",
    "gn:dem":392,
    "gn:feature_class":"P",
    "gn:feature_code":"PPL",
    "gn:name":"Xijiangducun",
    "gn:population":0,
    "gn:timezone":"Asia/Shanghai",
    "iso:country":"CN",
    "name:zho_x_preferred":[
        "\u897f\u6c5f\u6e21\u6751"
    ],
    "wof:name":"Xijiangducun",
    "wof:placetype":"locality"
},
  "geometry": {"coordinates":[108.65648,34.24243],"type":"Point"}
}