{
  "type": "Feature",
  "properties": {
    "gn:admin1_code":"18",
    "gn:asciiname":"Lizitai",
    "gn:country_code":"CN",
    "gn:dem":654,
    "gn:feature_class":"P",
    "gn:feature_code":"PPL",
    "gn:name":"Lizitai",
    "gn:population":0,
    "gn:timezone":"Asia/Shanghai",
    "iso:country":"CN",
    "name:zho_x_preferred":[
        "\u68a8\u5b50\u53f0"
    ],
    "wof:name":"Lizitai",
    "wof:placetype":"locality"
},
  "geometry": {"coordinates":[107.672,28.8974],"type":"Point"}
}