{
  "type": "Feature",
  "properties": {
    "gn:admin1_code":"8.0",
    "gn:asciiname":"Dongming Linyedui",
    "gn:country_code":"CN",
    "gn:dem":158,
    "gn:feature_class":"P",
    "gn:feature_code":"PPLF",
    "gn:name":"Dongming Linyedui",
    "gn:population":0,
    "gn:timezone":"Asia/Shanghai",
    "iso:country":"CN",
    "name:zho_x_preferred":[
        "\u4e1c\u660e\u6797\u4e1a\u961f"
    ],
    "wof:name":"Dongming Linyedui",
    "wof:placetype":"locality"
},
  "geometry": {"coordinates":[125.07708999999998,47.15826],"type":"Point"}
}