{
  "type": "Feature",
  "properties": {
    "gn:admin1_code":"26.0",
    "gn:asciiname":"Daniujiatai",
    "gn:country_code":"CN",
    "gn:dem":1069,
    "gn:feature_class":"P",
    "gn:feature_code":"PPL",
    "gn:name":"Daniujiatai",
    "gn:population":0,
    "gn:timezone":"Asia/Shanghai",
    "iso:country":"CN",
    "name:zho_x_preferred":[
        "\u5927\u725b\u5bb6\u53f0"
    ],
    "wof:name":"Daniujiatai",
    "wof:placetype":"locality"
},
  "geometry": {"coordinates":[110.80853,33.61475],"type":"Point"}
}