{
  "type": "Feature",
  "properties": {
    "gn:admin1_code":"15.0",
    "gn:asciiname":"Xiaojiagou",
    "gn:country_code":"CN",
    "gn:dem":2774,
    "gn:feature_class":"P",
    "gn:feature_code":"PPL",
    "gn:name":"Xiaojiagou",
    "gn:population":0,
    "gn:timezone":"Asia/Shanghai",
    "iso:country":"CN",
    "name:und_x_variant":[
        "\u8096\u5bb6\u6c9f"
    ],
    "wof:name":"Xiaojiagou",
    "wof:placetype":"locality"
},
  "geometry": {"coordinates":[103.66713,34.67765],"type":"Point"}
}