{
  "type": "Feature",
  "properties": {
    "gn:admin1_code":"10",
    "gn:asciiname":"Hongshili",
    "gn:country_code":"CN",
    "gn:dem":885,
    "gn:feature_class":"P",
    "gn:feature_code":"PPL",
    "gn:name":"Hongshili",
    "gn:population":0,
    "gn:timezone":"Asia/Shanghai",
    "iso:country":"CN",
    "name:zho_x_preferred":[
        "\u7ea2\u77f3\u783e"
    ],
    "wof:name":"Hongshili",
    "wof:placetype":"locality"
},
  "geometry": {"coordinates":[118.3473,41.19254],"type":"Point"}
}