{
  "type": "Feature",
  "properties": {
    "gn:admin1_code":"15.0",
    "gn:asciiname":"Jinta",
    "gn:country_code":"CN",
    "gn:dem":1785,
    "gn:feature_class":"P",
    "gn:feature_code":"PPL",
    "gn:name":"Jinta",
    "gn:population":0,
    "gn:timezone":"Asia/Shanghai",
    "iso:country":"CN",
    "name:zho_x_preferred":[
        "\u91d1\u5854"
    ],
    "wof:name":"Jinta",
    "wof:placetype":"locality"
},
  "geometry": {"coordinates":[102.556,37.8366],"type":"Point"}
}