{
  "type": "Feature",
  "properties": {
    "gn:admin1_code":"3.0",
    "gn:asciiname":"Jingangshi",
    "gn:country_code":"CN",
    "gn:dem":215,
    "gn:feature_class":"P",
    "gn:feature_code":"PPL",
    "gn:name":"Jingangshi",
    "gn:population":0,
    "gn:timezone":"Asia/Shanghai",
    "iso:country":"CN",
    "name:und_x_variant":[
        "\u91d1\u521a\u77f3"
    ],
    "wof:name":"Jingangshi",
    "wof:placetype":"locality"
},
  "geometry": {"coordinates":[114.71065,28.00566],"type":"Point"}
}