{
  "type": "Feature",
  "properties": {
    "gn:admin1_code":"29.0",
    "gn:asciiname":"Zhoujia Baobao",
    "gn:country_code":"CN",
    "gn:dem":2149,
    "gn:feature_class":"P",
    "gn:feature_code":"PPL",
    "gn:name":"Zhoujia Baobao",
    "gn:population":0,
    "gn:timezone":"Asia/Shanghai",
    "iso:country":"CN",
    "name:zho_x_preferred":[
        "\u5468\u5bb6\u5305\u5305"
    ],
    "wof:name":"Zhoujia Baobao",
    "wof:placetype":"locality"
},
  "geometry": {"coordinates":[102.551,25.2992],"type":"Point"}
}