{
  "type": "Feature",
  "properties": {
    "gn:admin1_code":"8.0",
    "gn:asciiname":"Qianguojia",
    "gn:country_code":"CN",
    "gn:dem":184,
    "gn:feature_class":"P",
    "gn:feature_code":"PPL",
    "gn:name":"Qianguojia",
    "gn:population":0,
    "gn:timezone":"Asia/Shanghai",
    "iso:country":"CN",
    "name:zho_x_preferred":[
        "\u524d\u90ed\u5bb6"
    ],
    "wof:name":"Qianguojia",
    "wof:placetype":"locality"
},
  "geometry": {"coordinates":[125.53109000000001,45.76602000000001],"type":"Point"}
}