{
  "type": "Feature",
  "properties": {
    "gn:admin1_code":"3.0",
    "gn:asciiname":"Lishan",
    "gn:country_code":"CN",
    "gn:dem":57,
    "gn:feature_class":"P",
    "gn:feature_code":"PPL",
    "gn:name":"Lishan",
    "gn:population":0,
    "gn:timezone":"Asia/Shanghai",
    "iso:country":"CN",
    "name:ceb_x_preferred":[
        "Lishan"
    ],
    "name:deu_x_preferred":[
        "Lishan"
    ],
    "name:nor_x_preferred":[
        "Lishan"
    ],
    "name:und_x_variant":[
        "\u5386\u5c71"
    ],
    "wof:name":"Lishan",
    "wof:placetype":"locality"
},
  "geometry": {"coordinates":[117.09659000000001,29.4444],"type":"Point"}
}