{
  "type": "Feature",
  "properties": {
    "gn:admin1_code":"1.0",
    "gn:asciiname":"Banhucun",
    "gn:country_code":"CN",
    "gn:dem":25,
    "gn:feature_class":"P",
    "gn:feature_code":"PPL",
    "gn:name":"Banhucun",
    "gn:population":0,
    "gn:timezone":"Asia/Shanghai",
    "iso:country":"CN",
    "name:zho_x_preferred":[
        "\u534a\u6e56\u6751"
    ],
    "wof:name":"Banhucun",
    "wof:placetype":"locality"
},
  "geometry": {"coordinates":[116.74866000000002,32.96644000000001],"type":"Point"}
}