{
  "type": "Feature",
  "properties": {
    "gn:admin1_code":"09",
    "gn:asciiname":"Beiye",
    "gn:country_code":"CN",
    "gn:dem":401,
    "gn:feature_class":"P",
    "gn:feature_code":"PPL",
    "gn:name":"Beiye",
    "gn:population":0,
    "gn:timezone":"Asia/Shanghai",
    "iso:country":"CN",
    "wof:name":"Beiye",
    "wof:placetype":"locality"
},
  "geometry": {"coordinates":[112.11583,34.86139],"type":"Point"}
}