{
  "type": "Feature",
  "properties": {
    "gn:admin1_code":"11.0",
    "gn:asciiname":"Mapoling",
    "gn:country_code":"CN",
    "gn:dem":65,
    "gn:feature_class":"P",
    "gn:feature_code":"PPL",
    "gn:name":"Mapoling",
    "gn:population":0,
    "gn:timezone":"Asia/Shanghai",
    "iso:country":"CN",
    "name:zho_x_preferred":[
        "\u9a6c\u5761\u5cad"
    ],
    "wof:name":"Mapoling",
    "wof:placetype":"locality"
},
  "geometry": {"coordinates":[113.06288000000001,28.20597],"type":"Point"}
}