{
  "type": "Feature",
  "properties": {
    "gn:admin1_code":"25",
    "gn:asciiname":"Tazi",
    "gn:country_code":"CN",
    "gn:dem":211,
    "gn:feature_class":"P",
    "gn:feature_code":"PPL",
    "gn:name":"Tazi",
    "gn:population":0,
    "gn:timezone":"Asia/Shanghai",
    "iso:country":"CN",
    "name:deu_x_preferred":[
        "Tazi"
    ],
    "name:fas_x_preferred":[
        "\u062a\u0627\u0632\u06cc"
    ],
    "name:fra_x_preferred":[
        "Tazi"
    ],
    "name:ita_x_preferred":[
        "Tazi"
    ],
    "name:jpn_x_preferred":[
        "\u30bf\u30fc\u30b8"
    ],
    "name:zho_x_preferred":[
        "\u5854\u5b50"
    ],
    "wof:name":"Tazi",
    "wof:placetype":"locality"
},
  "geometry": {"coordinates":[117.613,36.1609],"type":"Point"}
}