{
  "type": "Feature",
  "properties": {
    "gn:admin1_code":"16.0",
    "gn:asciiname":"Baifenling",
    "gn:country_code":"CN",
    "gn:dem":61,
    "gn:feature_class":"P",
    "gn:feature_code":"PPL",
    "gn:name":"Baifenling",
    "gn:population":0,
    "gn:timezone":"Asia/Shanghai",
    "iso:country":"CN",
    "name:zho_x_preferred":[
        "\u767d\u575f\u5cad"
    ],
    "wof:name":"Baifenling",
    "wof:placetype":"locality"
},
  "geometry": {"coordinates":[110.58499999999999,23.3692],"type":"Point"}
}