{
  "type": "Feature",
  "properties": {
    "gn:admin1_code":"24.0",
    "gn:asciiname":"Tanquan",
    "gn:country_code":"CN",
    "gn:dem":622,
    "gn:feature_class":"P",
    "gn:feature_code":"PPL",
    "gn:name":"Tanquan",
    "gn:population":0,
    "gn:timezone":"Asia/Shanghai",
    "iso:country":"CN",
    "name:und_x_variant":[
        "\u6619\u6cc9"
    ],
    "name:zho_x_preferred":[
        "\u6619\u6cc9"
    ],
    "wof:name":"Tanquan",
    "wof:placetype":"locality"
},
  "geometry": {"coordinates":[111.38664,35.5406],"type":"Point"}
}