{
  "type": "Feature",
  "properties": {
    "gn:admin1_code":"3.0",
    "gn:asciiname":"Xintiangang",
    "gn:country_code":"CN",
    "gn:dem":115,
    "gn:feature_class":"P",
    "gn:feature_code":"PPL",
    "gn:name":"Xintiangang",
    "gn:population":0,
    "gn:timezone":"Asia/Shanghai",
    "iso:country":"CN",
    "name:zho_x_preferred":[
        "\u65b0\u7530\u5c97"
    ],
    "wof:name":"Xintiangang",
    "wof:placetype":"locality"
},
  "geometry": {"coordinates":[117.34959000000001,28.59591],"type":"Point"}
}