{
  "type": "Feature",
  "properties": {
    "gn:admin1_code":"26.0",
    "gn:asciiname":"Majiaqu",
    "gn:country_code":"CN",
    "gn:dem":1044,
    "gn:feature_class":"P",
    "gn:feature_code":"PPL",
    "gn:name":"Majiaqu",
    "gn:population":0,
    "gn:timezone":"Asia/Shanghai",
    "iso:country":"CN",
    "name:zho_x_preferred":[
        "\u9ebb\u5bb6\u6e20"
    ],
    "wof:name":"Majiaqu",
    "wof:placetype":"locality"
},
  "geometry": {"coordinates":[109.74661,37.05945],"type":"Point"}
}