{
  "type": "Feature",
  "properties": {
    "gn:admin1_code":"24",
    "gn:asciiname":"Liminzhai",
    "gn:cc2":"CN",
    "gn:country_code":"CN",
    "gn:dem":1581,
    "gn:feature_class":"P",
    "gn:feature_code":"PPL",
    "gn:name":"Liminzhai",
    "gn:population":0,
    "gn:timezone":"Asia/Shanghai",
    "iso:country":"CN",
    "name:und_x_variant":[
        "Li-min-chai",
        "Liminzhai",
        "\u5229\u6c11\u5be8"
    ],
    "wof:name":"Liminzhai",
    "wof:placetype":"locality"
},
  "geometry": {"coordinates":[112.16777999999999,39.23444],"type":"Point"}
}