{
  "type": "Feature",
  "properties": {
    "gn:admin1_code":"25",
    "gn:asciiname":"Nanjiawang",
    "gn:country_code":"CN",
    "gn:dem":10,
    "gn:feature_class":"P",
    "gn:feature_code":"PPL",
    "gn:name":"Nanjiawang",
    "gn:population":0,
    "gn:timezone":"Asia/Shanghai",
    "iso:country":"CN",
    "name:zho_x_preferred":[
        "\u5357\u8d3e\u738b"
    ],
    "wof:name":"Nanjiawang",
    "wof:placetype":"locality"
},
  "geometry": {"coordinates":[118.24494,37.33592],"type":"Point"}
}