{
  "type": "Feature",
  "properties": {
    "gn:admin1_code":"26.0",
    "gn:asciiname":"Bazhaicun",
    "gn:country_code":"CN",
    "gn:dem":1057,
    "gn:feature_class":"P",
    "gn:feature_code":"PPL",
    "gn:name":"Bazhaicun",
    "gn:population":0,
    "gn:timezone":"Asia/Shanghai",
    "iso:country":"CN",
    "name:zho_x_preferred":[
        "\u516b\u5be8\u6751"
    ],
    "wof:name":"Bazhaicun",
    "wof:placetype":"locality"
},
  "geometry": {"coordinates":[108.2304,34.88858],"type":"Point"}
}