{
  "type": "Feature",
  "properties": {
    "gn:admin1_code":"30",
    "gn:asciiname":"He'an",
    "gn:country_code":"CN",
    "gn:dem":8,
    "gn:feature_class":"P",
    "gn:feature_code":"PPL",
    "gn:name":"He\u2019an",
    "gn:population":0,
    "gn:timezone":"Asia/Shanghai",
    "iso:country":"CN",
    "name:und_x_variant":[
        "He\u2019an",
        "\u548c\u5b89"
    ],
    "name:zho_x_preferred":[
        "\u548c\u5b89\u5e02"
    ],
    "name:zho_x_variant":[
        "He\u2019anshi"
    ],
    "wof:name":"He'an",
    "wof:placetype":"locality"
},
  "geometry": {"coordinates":[112.56596999999999,22.16531],"type":"Point"}
}