{
  "type": "Feature",
  "properties": {
    "gn:admin1_code":"8.0",
    "gn:asciiname":"Zhennancun",
    "gn:country_code":"CN",
    "gn:dem":92,
    "gn:feature_class":"P",
    "gn:feature_code":"PPL",
    "gn:name":"Zhennancun",
    "gn:population":0,
    "gn:timezone":"Asia/Shanghai",
    "iso:country":"CN",
    "name:zho_x_preferred":[
        "\u9547\u5357\u6751"
    ],
    "wof:name":"Zhennancun",
    "wof:placetype":"locality"
},
  "geometry": {"coordinates":[129.85448,46.56834],"type":"Point"}
}