{
  "type": "Feature",
  "properties": {
    "gn:admin1_code":"29.0",
    "gn:asciiname":"Dimula",
    "gn:country_code":"CN",
    "gn:dem":2125,
    "gn:feature_class":"P",
    "gn:feature_code":"PPL",
    "gn:name":"Dimula",
    "gn:population":0,
    "gn:timezone":"Asia/Shanghai",
    "iso:country":"CN",
    "name:zho_x_preferred":[
        "\u5730\u6728\u62c9"
    ],
    "wof:name":"Dimula",
    "wof:placetype":"locality"
},
  "geometry": {"coordinates":[102.81999999999999,25.7797],"type":"Point"}
}