{
  "type": "Feature",
  "properties": {
    "gn:admin1_code":"3.0",
    "gn:asciiname":"Guangdong Pengli",
    "gn:country_code":"CN",
    "gn:dem":113,
    "gn:feature_class":"P",
    "gn:feature_code":"PPL",
    "gn:name":"Guangdong Pengli",
    "gn:population":0,
    "gn:timezone":"Asia/Shanghai",
    "iso:country":"CN",
    "name:und_x_variant":[
        "\u5e7f\u4e1c\u68da\u91cc"
    ],
    "wof:name":"Guangdong Pengli",
    "wof:placetype":"locality"
},
  "geometry": {"coordinates":[114.39852999999999,27.38957000000001],"type":"Point"}
}