{
  "type": "Feature",
  "properties": {
    "gn:admin1_code":"32.0",
    "gn:asciiname":"Zhangdu",
    "gn:country_code":"CN",
    "gn:dem":3260,
    "gn:feature_class":"P",
    "gn:feature_code":"PPL",
    "gn:name":"Zhangdu",
    "gn:population":0,
    "gn:timezone":"Asia/Shanghai",
    "iso:country":"CN",
    "name:und_x_variant":[
        "Zomdo",
        "Zhangdu"
    ],
    "name:zho_x_preferred":[
        "\u7ae0\u90fd"
    ],
    "wof:name":"Zhangdu",
    "wof:placetype":"locality"
},
  "geometry": {"coordinates":[99.01499,31.12211],"type":"Point"}
}