{
  "type": "Feature",
  "properties": {
    "gn:admin1_code":"29.0",
    "gn:asciiname":"Echongyi",
    "gn:country_code":"CN",
    "gn:dem":2005,
    "gn:feature_class":"P",
    "gn:feature_code":"PPL",
    "gn:name":"Echongyi",
    "gn:population":0,
    "gn:timezone":"Asia/Shanghai",
    "iso:country":"CN",
    "name:zho_x_preferred":[
        "\u989d\u51b2\u8863"
    ],
    "wof:name":"Echongyi",
    "wof:placetype":"locality"
},
  "geometry": {"coordinates":[103.53100000000001,24.7085],"type":"Point"}
}