{
  "type": "Feature",
  "properties": {
    "gn:admin1_code":"15.0",
    "gn:asciiname":"Liaotan",
    "gn:country_code":"CN",
    "gn:dem":1769,
    "gn:feature_class":"P",
    "gn:feature_code":"PPL",
    "gn:name":"Liaotan",
    "gn:population":0,
    "gn:timezone":"Asia/Shanghai",
    "iso:country":"CN",
    "name:und_x_variant":[
        "\u6599\u6ee9"
    ],
    "wof:name":"Liaotan",
    "wof:placetype":"locality"
},
  "geometry": {"coordinates":[105.52855,35.20050999999999],"type":"Point"}
}