{
  "type": "Feature",
  "properties": {
    "gn:admin1_code":"2.0",
    "gn:asciiname":"Songzhuang",
    "gn:country_code":"CN",
    "gn:dem":565,
    "gn:feature_class":"P",
    "gn:feature_code":"PPL",
    "gn:name":"Songzhuang",
    "gn:population":0,
    "gn:timezone":"Asia/Shanghai",
    "iso:country":"CN",
    "name:zho_x_preferred":[
        "\u5b8b\u5e84"
    ],
    "wof:name":"Songzhuang",
    "wof:placetype":"locality"
},
  "geometry": {"coordinates":[119.56303,28.45233],"type":"Point"}
}