{
  "type": "Feature",
  "properties": {
    "gn:admin1_code":"33.0",
    "gn:asciiname":"Zhaping",
    "gn:country_code":"CN",
    "gn:dem":826,
    "gn:feature_class":"P",
    "gn:feature_code":"PPL",
    "gn:name":"Zhaping",
    "gn:population":0,
    "gn:timezone":"Asia/Shanghai",
    "iso:country":"CN",
    "name:zho_x_preferred":[
        "\u69a8\u576a"
    ],
    "wof:name":"Zhaping",
    "wof:placetype":"locality"
},
  "geometry": {"coordinates":[108.98403999999999,30.76541],"type":"Point"}
}