{
  "type": "Feature",
  "properties": {
    "gn:admin1_code":"24.0",
    "gn:asciiname":"Shiquan",
    "gn:country_code":"CN",
    "gn:dem":1006,
    "gn:feature_class":"P",
    "gn:feature_code":"PPL",
    "gn:name":"Shiquan",
    "gn:population":0,
    "gn:timezone":"Asia/Shanghai",
    "iso:country":"CN",
    "name:zho_x_preferred":[
        "\u77f3\u5708"
    ],
    "wof:name":"Shiquan",
    "wof:placetype":"locality"
},
  "geometry": {"coordinates":[112.32653000000001,35.2706],"type":"Point"}
}