{
  "type": "Feature",
  "properties": {
    "gn:admin1_code":"33.0",
    "gn:asciiname":"Zhonggupo",
    "gn:country_code":"CN",
    "gn:dem":368,
    "gn:feature_class":"P",
    "gn:feature_code":"PPL",
    "gn:name":"Zhonggupo",
    "gn:population":0,
    "gn:timezone":"Asia/Shanghai",
    "iso:country":"CN",
    "name:zho_x_preferred":[
        "\u949f\u9f13\u5761"
    ],
    "wof:name":"Zhonggupo",
    "wof:placetype":"locality"
},
  "geometry": {"coordinates":[106.00359,30.22886],"type":"Point"}
}