{
  "type": "Feature",
  "properties": {
    "gn:admin1_code":"29",
    "gn:asciiname":"Luomei",
    "gn:country_code":"CN",
    "gn:dem":1679,
    "gn:feature_class":"P",
    "gn:feature_code":"PPL",
    "gn:name":"Luomei",
    "gn:population":0,
    "gn:timezone":"Asia/Shanghai",
    "iso:country":"CN",
    "name:zho_x_preferred":[
        "\u843d\u6885"
    ],
    "wof:name":"Luomei",
    "wof:placetype":"locality"
},
  "geometry": {"coordinates":[102.97799999999999,24.422],"type":"Point"}
}