{
  "type": "Feature",
  "properties": {
    "gn:admin1_code":"14.0",
    "gn:asciiname":"Longmage",
    "gn:country_code":"CN",
    "gn:dem":4156,
    "gn:feature_class":"P",
    "gn:feature_code":"PPL",
    "gn:name":"Longmage",
    "gn:population":0,
    "gn:timezone":"Asia/Urumqi",
    "iso:country":"CN",
    "name:zho_x_preferred":[
        "\u9f99\u739b\u683c"
    ],
    "wof:name":"Longmage",
    "wof:placetype":"locality"
},
  "geometry": {"coordinates":[94.24567999999999,31.56878],"type":"Point"}
}