{
  "type": "Feature",
  "properties": {
    "gn:admin1_code":"2.0",
    "gn:asciiname":"Waiwan",
    "gn:country_code":"CN",
    "gn:dem":37,
    "gn:feature_class":"P",
    "gn:feature_code":"PPL",
    "gn:name":"Waiwan",
    "gn:population":0,
    "gn:timezone":"Asia/Shanghai",
    "iso:country":"CN",
    "name:zho_x_preferred":[
        "\u5916\u6e7e"
    ],
    "wof:name":"Waiwan",
    "wof:placetype":"locality"
},
  "geometry": {"coordinates":[121.18402,28.92953],"type":"Point"}
}