{
  "type": "Feature",
  "properties": {
    "gn:admin1_code":"14",
    "gn:asciiname":"Ri'abeidarang",
    "gn:country_code":"CN",
    "gn:dem":4678,
    "gn:feature_class":"P",
    "gn:feature_code":"PPL",
    "gn:name":"Ri\u2019abeidarang",
    "gn:population":0,
    "gn:timezone":"Asia/Urumqi",
    "iso:country":"CN",
    "name:und_x_variant":[
        "Ri\u2019abeidarang"
    ],
    "name:zho_x_preferred":[
        "\u65e5\u963f\u5317\u8fbe\u8ba9"
    ],
    "wof:name":"Ri'abeidarang",
    "wof:placetype":"locality"
},
  "geometry": {"coordinates":[89.12909999999999,32.2263],"type":"Point"}
}