{
  "type": "Feature",
  "properties": {
    "gn:admin1_code":"18.0",
    "gn:asciiname":"Shitouzhai",
    "gn:country_code":"CN",
    "gn:dem":958,
    "gn:feature_class":"P",
    "gn:feature_code":"PPL",
    "gn:name":"Shitouzhai",
    "gn:population":0,
    "gn:timezone":"Asia/Shanghai",
    "iso:country":"CN",
    "name:zho_x_preferred":[
        "\u77f3\u5934\u5be8"
    ],
    "wof:name":"Shitouzhai",
    "wof:placetype":"locality"
},
  "geometry": {"coordinates":[107.59099999999999,25.5631],"type":"Point"}
}