{
  "type": "Feature",
  "properties": {
    "gn:admin1_code":"25",
    "gn:asciiname":"Houbeizuo",
    "gn:country_code":"CN",
    "gn:dem":148,
    "gn:feature_class":"P",
    "gn:feature_code":"PPL",
    "gn:name":"Houbeizuo",
    "gn:population":0,
    "gn:timezone":"Asia/Shanghai",
    "iso:country":"CN",
    "name:zho_x_preferred":[
        "\u540e\u5317\u4f50"
    ],
    "wof:name":"Houbeizuo",
    "wof:placetype":"locality"
},
  "geometry": {"coordinates":[117.489,35.9193],"type":"Point"}
}