{
  "type": "Feature",
  "properties": {
    "gn:admin1_code":"29.0",
    "gn:asciiname":"Tuobacun",
    "gn:country_code":"CN",
    "gn:dem":2105,
    "gn:feature_class":"P",
    "gn:feature_code":"PPL",
    "gn:name":"Tuobacun",
    "gn:population":0,
    "gn:timezone":"Asia/Shanghai",
    "iso:country":"CN",
    "name:zho_x_preferred":[
        "\u6258\u516b\u6751"
    ],
    "wof:name":"Tuobacun",
    "wof:placetype":"locality"
},
  "geometry": {"coordinates":[99.1641,27.0398],"type":"Point"}
}