{
  "type": "Feature",
  "properties": {
    "gn:admin1_code":"7",
    "gn:asciiname":"Shaocuo",
    "gn:country_code":"CN",
    "gn:dem":120,
    "gn:feature_class":"P",
    "gn:feature_code":"PPL",
    "gn:name":"Shaocuo",
    "gn:population":0,
    "gn:timezone":"Asia/Shanghai",
    "iso:country":"CN",
    "name:und_x_variant":[
        "\u70e7\u539d",
        "Shaocuo"
    ],
    "wof:name":"Shaocuo",
    "wof:placetype":"locality"
},
  "geometry": {"coordinates":[118.36529,24.68139],"type":"Point"}
}