{
  "type": "Feature",
  "properties": {
    "gn:admin1_code":"15.0",
    "gn:asciiname":"Zhaoshipo",
    "gn:country_code":"CN",
    "gn:dem":1656,
    "gn:feature_class":"P",
    "gn:feature_code":"PPL",
    "gn:name":"Zhaoshipo",
    "gn:population":0,
    "gn:timezone":"Asia/Shanghai",
    "iso:country":"CN",
    "name:und_x_variant":[
        "\u7167\u4e16\u5761"
    ],
    "wof:name":"Zhaoshipo",
    "wof:placetype":"locality"
},
  "geometry": {"coordinates":[105.68724,35.50547],"type":"Point"}
}