{
  "type": "Feature",
  "properties": {
    "gn:admin1_code":"29.0",
    "gn:asciiname":"Mawuzhuo",
    "gn:country_code":"CN",
    "gn:dem":2544,
    "gn:feature_class":"P",
    "gn:feature_code":"PPL",
    "gn:name":"Mawuzhuo",
    "gn:population":0,
    "gn:timezone":"Asia/Shanghai",
    "iso:country":"CN",
    "name:zho_x_preferred":[
        "\u9a6c\u543e\u5353"
    ],
    "wof:name":"Mawuzhuo",
    "wof:placetype":"locality"
},
  "geometry": {"coordinates":[99.34350000000001,26.8338],"type":"Point"}
}