{
  "type": "Feature",
  "properties": {
    "gn:admin1_code":"24.0",
    "gn:asciiname":"Gelieyuan",
    "gn:country_code":"CN",
    "gn:dem":800,
    "gn:feature_class":"P",
    "gn:feature_code":"PPL",
    "gn:name":"Gelieyuan",
    "gn:population":0,
    "gn:timezone":"Asia/Shanghai",
    "iso:country":"CN",
    "name:zho_x_preferred":[
        "\u572a\u5217\u586c"
    ],
    "wof:name":"Gelieyuan",
    "wof:placetype":"locality"
},
  "geometry": {"coordinates":[110.51218,36.61953],"type":"Point"}
}