{
  "type": "Feature",
  "properties": {
    "gn:admin1_code":"3.0",
    "gn:asciiname":"Nantuancun",
    "gn:country_code":"CN",
    "gn:dem":294,
    "gn:feature_class":"P",
    "gn:feature_code":"PPL",
    "gn:name":"Nantuancun",
    "gn:population":0,
    "gn:timezone":"Asia/Shanghai",
    "iso:country":"CN",
    "name:und_x_variant":[
        "\u5357\u56e2\u6751"
    ],
    "wof:name":"Nantuancun",
    "wof:placetype":"locality"
},
  "geometry": {"coordinates":[115.93086,26.8941],"type":"Point"}
}