{
  "type": "Feature",
  "properties": {
    "gn:admin1_code":"15.0",
    "gn:asciiname":"Miaodi Xiacun",
    "gn:country_code":"CN",
    "gn:dem":1475,
    "gn:feature_class":"P",
    "gn:feature_code":"PPL",
    "gn:name":"Miaodi Xiacun",
    "gn:population":0,
    "gn:timezone":"Asia/Shanghai",
    "iso:country":"CN",
    "name:zho_x_preferred":[
        "\u5e99\u5e95\u4e0b\u6751"
    ],
    "wof:name":"Miaodi Xiacun",
    "wof:placetype":"locality"
},
  "geometry": {"coordinates":[106.569,35.5592],"type":"Point"}
}