{
  "type": "Feature",
  "properties": {
    "gn:admin1_code":"4.0",
    "gn:asciiname":"Nanshi",
    "gn:country_code":"CN",
    "gn:dem":2,
    "gn:feature_class":"P",
    "gn:feature_code":"PPL",
    "gn:name":"Nanshi",
    "gn:population":0,
    "gn:timezone":"Asia/Shanghai",
    "iso:country":"CN",
    "name:und_x_variant":[
        "\u5357\u77f3"
    ],
    "name:zho_x_preferred":[
        "\u5357\u77f3"
    ],
    "wof:name":"Nanshi",
    "wof:placetype":"locality"
},
  "geometry": {"coordinates":[120.11745999999999,32.89918],"type":"Point"}
}