{
  "type": "Feature",
  "properties": {
    "gn:admin1_code":"25",
    "gn:asciiname":"Lunjiabupo",
    "gn:country_code":"CN",
    "gn:dem":151,
    "gn:feature_class":"P",
    "gn:feature_code":"PPL",
    "gn:name":"Lunjiabupo",
    "gn:population":0,
    "gn:timezone":"Asia/Shanghai",
    "iso:country":"CN",
    "name:zho_x_preferred":[
        "\u4f26\u5bb6\u57e0\u5761"
    ],
    "wof:name":"Lunjiabupo",
    "wof:placetype":"locality"
},
  "geometry": {"coordinates":[118.87,36.4742],"type":"Point"}
}