{
  "type": "Feature",
  "properties": {
    "gn:admin1_code":"23.0",
    "gn:asciiname":"Lujiajiao",
    "gn:country_code":"CN",
    "gn:dem":2,
    "gn:feature_class":"P",
    "gn:feature_code":"PPL",
    "gn:name":"Lujiajiao",
    "gn:population":0,
    "gn:timezone":"Asia/Shanghai",
    "iso:country":"CN",
    "name:und_x_variant":[
        "\u9646\u5bb6\u89d2"
    ],
    "wof:name":"Lujiajiao",
    "wof:placetype":"locality"
},
  "geometry": {"coordinates":[121.24797,31.17962],"type":"Point"}
}