{
  "type": "Feature",
  "properties": {
    "gn:admin1_code":"26.0",
    "gn:asciiname":"Gechoucun",
    "gn:country_code":"CN",
    "gn:dem":1331,
    "gn:feature_class":"P",
    "gn:feature_code":"PPL",
    "gn:name":"Gechoucun",
    "gn:population":0,
    "gn:timezone":"Asia/Shanghai",
    "iso:country":"CN",
    "name:zho_x_preferred":[
        "\u572a\u4e11\u6751"
    ],
    "wof:name":"Gechoucun",
    "wof:placetype":"locality"
},
  "geometry": {"coordinates":[107.86405999999999,37.76941],"type":"Point"}
}