{
  "type": "Feature",
  "properties": {
    "gn:admin1_code":"15.0",
    "gn:asciiname":"Luhe",
    "gn:country_code":"CN",
    "gn:dem":1625,
    "gn:feature_class":"P",
    "gn:feature_code":"PPLA4",
    "gn:name":"Luhe",
    "gn:population":0,
    "gn:timezone":"Asia/Shanghai",
    "iso:country":"CN",
    "name:ceb_x_preferred":[
        "Luhe"
    ],
    "name:dan_x_preferred":[
        "Luhe"
    ],
    "name:deu_x_preferred":[
        "Luhe"
    ],
    "name:fra_x_preferred":[
        "Luhe"
    ],
    "name:nor_x_preferred":[
        "Luhe"
    ],
    "name:pol_x_preferred":[
        "Luhe"
    ],
    "name:swe_x_preferred":[
        "Luhe"
    ],
    "name:und_x_variant":[
        "\u5362\u6cb3"
    ],
    "wof:name":"Luhe",
    "wof:placetype":"locality"
},
  "geometry": {"coordinates":[105.34021,34.00918],"type":"Point"}
}