{
  "type": "Feature",
  "properties": {
    "gn:admin1_code":"29.0",
    "gn:asciiname":"Laoshenzhai",
    "gn:country_code":"CN",
    "gn:dem":1513,
    "gn:feature_class":"P",
    "gn:feature_code":"PPL",
    "gn:name":"Laoshenzhai",
    "gn:population":0,
    "gn:timezone":"Asia/Shanghai",
    "iso:country":"CN",
    "name:zho_x_preferred":[
        "\u8001\u795e\u5be8"
    ],
    "wof:name":"Laoshenzhai",
    "wof:placetype":"locality"
},
  "geometry": {"coordinates":[98.7492,23.9169],"type":"Point"}
}