{
  "type": "Feature",
  "properties": {
    "gn:admin1_code":"7",
    "gn:asciiname":"Xiaoguokeng",
    "gn:country_code":"CN",
    "gn:dem":15,
    "gn:feature_class":"P",
    "gn:feature_code":"PPL",
    "gn:name":"Xiaoguokeng",
    "gn:population":0,
    "gn:timezone":"Asia/Shanghai",
    "iso:country":"CN",
    "name:zho_x_preferred":[
        "\u5c0f\u90ed\u5751"
    ],
    "wof:name":"Xiaoguokeng",
    "wof:placetype":"locality"
},
  "geometry": {"coordinates":[117.77091,24.50187],"type":"Point"}
}