{
  "type": "Feature",
  "properties": {
    "gn:admin1_code":"7",
    "gn:asciiname":"Zhennan",
    "gn:country_code":"CN",
    "gn:dem":90,
    "gn:feature_class":"P",
    "gn:feature_code":"PPL",
    "gn:name":"Zhennan",
    "gn:population":0,
    "gn:timezone":"Asia/Shanghai",
    "iso:country":"CN",
    "name:zho_x_preferred":[
        "\u5733\u5357"
    ],
    "wof:name":"Zhennan",
    "wof:placetype":"locality"
},
  "geometry": {"coordinates":[118.76222,25.7475],"type":"Point"}
}