{
  "type": "Feature",
  "properties": {
    "gn:admin1_code":"7.0",
    "gn:asciiname":"Changshankeng",
    "gn:country_code":"CN",
    "gn:dem":828,
    "gn:feature_class":"P",
    "gn:feature_code":"PPL",
    "gn:name":"Changshankeng",
    "gn:population":0,
    "gn:timezone":"Asia/Shanghai",
    "iso:country":"CN",
    "name:zho_x_preferred":[
        "\u957f\u5c71\u5751"
    ],
    "wof:name":"Changshankeng",
    "wof:placetype":"locality"
},
  "geometry": {"coordinates":[118.09026,26.38305],"type":"Point"}
}