{
  "type": "Feature",
  "properties": {
    "gn:admin1_code":"29.0",
    "gn:asciiname":"Qiche",
    "gn:country_code":"CN",
    "gn:dem":1931,
    "gn:feature_class":"P",
    "gn:feature_code":"PPL",
    "gn:name":"Qiche",
    "gn:population":0,
    "gn:timezone":"Asia/Shanghai",
    "iso:country":"CN",
    "name:zho_x_preferred":[
        "\u671f\u626f"
    ],
    "wof:name":"Qiche",
    "wof:placetype":"locality"
},
  "geometry": {"coordinates":[103.52200000000001,23.0427],"type":"Point"}
}