{
  "type": "Feature",
  "properties": {
    "gn:admin1_code":"20.0",
    "gn:asciiname":"Jiucai'er Sandui",
    "gn:country_code":"CN",
    "gn:dem":354,
    "gn:feature_class":"P",
    "gn:feature_code":"PPLF",
    "gn:name":"Jiucai\u2019er Sandui",
    "gn:population":0,
    "gn:timezone":"Asia/Shanghai",
    "iso:country":"CN",
    "name:und_x_variant":[
        "Jiucai\u2019er Sandui"
    ],
    "name:zho_x_preferred":[
        "\u97ed\u83dc\u4e8c\u4e09\u961f"
    ],
    "wof:name":"Jiucai'er Sandui",
    "wof:placetype":"locality"
},
  "geometry": {"coordinates":[123.38132,48.72706],"type":"Point"}
}