{
  "type": "Feature",
  "properties": {
    "gn:admin1_code":"11.0",
    "gn:asciiname":"Pingshang Yangjia",
    "gn:country_code":"CN",
    "gn:dem":276,
    "gn:feature_class":"P",
    "gn:feature_code":"PPL",
    "gn:name":"Pingshang Yangjia",
    "gn:population":0,
    "gn:timezone":"Asia/Shanghai",
    "iso:country":"CN",
    "name:zho_x_preferred":[
        "\u576a\u4e0a\u6768\u5bb6"
    ],
    "wof:name":"Pingshang Yangjia",
    "wof:placetype":"locality"
},
  "geometry": {"coordinates":[111.21285,27.40389],"type":"Point"}
}