{
  "type": "Feature",
  "properties": {
    "gn:admin1_code":"29.0",
    "gn:asciiname":"Gongding",
    "gn:country_code":"CN",
    "gn:dem":1257,
    "gn:feature_class":"P",
    "gn:feature_code":"PPL",
    "gn:name":"Gongding",
    "gn:population":0,
    "gn:timezone":"Asia/Shanghai",
    "iso:country":"CN",
    "name:zho_x_preferred":[
        "\u516c\u9876"
    ],
    "wof:name":"Gongding",
    "wof:placetype":"locality"
},
  "geometry": {"coordinates":[99.13500000000001,23.3431],"type":"Point"}
}