{
  "type": "Feature",
  "properties": {
    "gn:admin1_code":"33.0",
    "gn:asciiname":"Shibuzhai",
    "gn:country_code":"CN",
    "gn:dem":369,
    "gn:feature_class":"P",
    "gn:feature_code":"PPL",
    "gn:name":"Shibuzhai",
    "gn:population":0,
    "gn:timezone":"Asia/Shanghai",
    "iso:country":"CN",
    "name:zho_x_preferred":[
        "\u72ee\u5821\u5be8"
    ],
    "wof:name":"Shibuzhai",
    "wof:placetype":"locality"
},
  "geometry": {"coordinates":[106.60418,30.12899],"type":"Point"}
}