{
  "type": "Feature",
  "properties": {
    "gn:admin1_code":"7",
    "gn:asciiname":"Tangqian",
    "gn:country_code":"CN",
    "gn:dem":374,
    "gn:feature_class":"P",
    "gn:feature_code":"PPL",
    "gn:name":"Tangqian",
    "gn:population":0,
    "gn:timezone":"Asia/Shanghai",
    "iso:country":"CN",
    "name:und_x_variant":[
        "\u5858\u524d",
        "Tangqian Xiang",
        "\u5858\u524d\u4e61"
    ],
    "wof:name":"Tangqian",
    "wof:placetype":"locality"
},
  "geometry": {"coordinates":[116.85271000000002,25.76821],"type":"Point"}
}