{
  "type": "Feature",
  "properties": {
    "gn:admin1_code":"4.0",
    "gn:asciiname":"Wuzong",
    "gn:country_code":"CN",
    "gn:dem":8,
    "gn:feature_class":"P",
    "gn:feature_code":"PPL",
    "gn:name":"Wuzong",
    "gn:population":0,
    "gn:timezone":"Asia/Shanghai",
    "iso:country":"CN",
    "name:und_x_variant":[
        "Wu-tsung-pu",
        "Wu-tsung-fou",
        "Wu-tsung",
        "Wuzong",
        "\u4e94\u603b"
    ],
    "wof:name":"Wuzong",
    "wof:placetype":"locality"
},
  "geometry": {"coordinates":[121.05670000000001,32.21973],"type":"Point"}
}