{
  "type": "Feature",
  "properties": {
    "gn:admin1_code":"4.0",
    "gn:asciiname":"Wuzong",
    "gn:country_code":"CN",
    "gn:dem":8,
    "gn:feature_class":"P",
    "gn:feature_code":"PPL",
    "gn:name":"Wuzong",
    "gn:population":0,
    "gn:timezone":"Asia/Shanghai",
    "iso:country":"CN",
    "name:deu_x_preferred":[
        "Wuzong"
    ],
    "name:nld_x_preferred":[
        "Wuzong"
    ],
    "name:pol_x_preferred":[
        "Wuzong"
    ],
    "name:ukr_x_preferred":[
        "\u0423\u0446\u0437\u0443\u043d"
    ],
    "name:und_x_variant":[
        "Wu-tsung-pu",
        "Wu-tsung-fou",
        "Wu-tsung",
        "\u4e94\u603b"
    ],
    "name:vie_x_preferred":[
        "V\u0169 T\u00f4ng"
    ],
    "wof:name":"Wuzong",
    "wof:placetype":"locality"
},
  "geometry": {"coordinates":[121.05670000000001,32.21973],"type":"Point"}
}