{
  "type": "Feature",
  "properties": {
    "gn:admin1_code":"30",
    "gn:asciiname":"Kengweitou",
    "gn:country_code":"CN",
    "gn:dem":484,
    "gn:feature_class":"P",
    "gn:feature_code":"PPL",
    "gn:name":"Kengweitou",
    "gn:population":0,
    "gn:timezone":"Asia/Shanghai",
    "iso:country":"CN",
    "name:zho_x_preferred":[
        "\u5751\u5c3e\u5934"
    ],
    "wof:name":"Kengweitou",
    "wof:placetype":"locality"
},
  "geometry": {"coordinates":[115.45141,23.40133],"type":"Point"}
}