{
  "type": "Feature",
  "properties": {
    "gn:admin1_code":"32.0",
    "gn:asciiname":"Mijiang",
    "gn:country_code":"CN",
    "gn:dem":456,
    "gn:feature_class":"P",
    "gn:feature_code":"PPL",
    "gn:name":"Mijiang",
    "gn:population":0,
    "gn:timezone":"Asia/Shanghai",
    "iso:country":"CN",
    "name:zho_x_preferred":[
        "\u5f25\u6c5f"
    ],
    "wof:name":"Mijiang",
    "wof:placetype":"locality"
},
  "geometry": {"coordinates":[105.422,31.4779],"type":"Point"}
}