{
  "type": "Feature",
  "properties": {
    "gn:admin1_code":"18.0",
    "gn:asciiname":"Tuoda",
    "gn:country_code":"CN",
    "gn:dem":2389,
    "gn:feature_class":"P",
    "gn:feature_code":"PPL",
    "gn:name":"Tuoda",
    "gn:population":0,
    "gn:timezone":"Asia/Shanghai",
    "iso:country":"CN",
    "name:zho_x_preferred":[
        "\u59a5\u6253"
    ],
    "wof:name":"Tuoda",
    "wof:placetype":"locality"
},
  "geometry": {"coordinates":[104.09,27.0356],"type":"Point"}
}