{
  "type": "Feature",
  "properties": {
    "gn:admin1_code":"25.0",
    "gn:asciiname":"Huangshan",
    "gn:cc2":"CN",
    "gn:country_code":"CN",
    "gn:dem":37,
    "gn:feature_class":"P",
    "gn:feature_code":"PPL",
    "gn:name":"Huangshan",
    "gn:population":0,
    "gn:timezone":"Asia/Shanghai",
    "iso:country":"CN",
    "name:zho_x_preferred":[
        "\u9ec4\u5c71"
    ],
    "wof:name":"Huangshan",
    "wof:placetype":"locality"
},
  "geometry": {"coordinates":[119.98712,36.02613],"type":"Point"}
}