{
  "type": "Feature",
  "properties": {
    "gn:admin1_code":"29.0",
    "gn:asciiname":"Ouhei",
    "gn:country_code":"CN",
    "gn:dem":1410,
    "gn:feature_class":"P",
    "gn:feature_code":"PPL",
    "gn:name":"Ouhei",
    "gn:population":0,
    "gn:timezone":"Asia/Shanghai",
    "iso:country":"CN",
    "name:zho_x_preferred":[
        "\u6b27\u9ed1"
    ],
    "wof:name":"Ouhei",
    "wof:placetype":"locality"
},
  "geometry": {"coordinates":[102.011,22.9672],"type":"Point"}
}