{
  "type": "Feature",
  "properties": {
    "gn:admin1_code":"1.0",
    "gn:asciiname":"Liangtangcun",
    "gn:country_code":"CN",
    "gn:dem":21,
    "gn:feature_class":"P",
    "gn:feature_code":"PPL",
    "gn:name":"Liangtangcun",
    "gn:population":0,
    "gn:timezone":"Asia/Shanghai",
    "iso:country":"CN",
    "name:zho_x_preferred":[
        "\u826f\u5858\u6751"
    ],
    "wof:name":"Liangtangcun",
    "wof:placetype":"locality"
},
  "geometry": {"coordinates":[118.4093,32.27921],"type":"Point"}
}