{
  "type": "Feature",
  "properties": {
    "gn:admin1_code":"14.0",
    "gn:asciiname":"Langruoka",
    "gn:country_code":"CN",
    "gn:dem":4557,
    "gn:feature_class":"P",
    "gn:feature_code":"PPL",
    "gn:name":"Langruoka",
    "gn:population":0,
    "gn:timezone":"Asia/Urumqi",
    "iso:country":"CN",
    "name:zho_x_preferred":[
        "\u6717\u82e5\u5361"
    ],
    "wof:name":"Langruoka",
    "wof:placetype":"locality"
},
  "geometry": {"coordinates":[93.19556,30.65117],"type":"Point"}
}