{
  "type": "Feature",
  "properties": {
    "gn:admin1_code":"19.0",
    "gn:asciiname":"Shangliuhuangtun",
    "gn:country_code":"CN",
    "gn:dem":104,
    "gn:feature_class":"P",
    "gn:feature_code":"PPL",
    "gn:name":"Shangliuhuangtun",
    "gn:population":0,
    "gn:timezone":"Asia/Shanghai",
    "iso:country":"CN",
    "name:und_x_variant":[
        "\u4e0a\u67f3\u9ec4\u5c6f"
    ],
    "name:zho_x_preferred":[
        "\u4e0a\u67f3\u9ec4\u5c6f"
    ],
    "wof:name":"Shangliuhuangtun",
    "wof:placetype":"locality"
},
  "geometry": {"coordinates":[121.01186,41.66876],"type":"Point"}
}