{
  "type": "Feature",
  "properties": {
    "gn:admin1_code":"29.0",
    "gn:asciiname":"Goutouqing",
    "gn:country_code":"CN",
    "gn:dem":1781,
    "gn:feature_class":"P",
    "gn:feature_code":"PPL",
    "gn:name":"Goutouqing",
    "gn:population":0,
    "gn:timezone":"Asia/Shanghai",
    "iso:country":"CN",
    "name:zho_x_preferred":[
        "\u6c9f\u5934\u7b90"
    ],
    "wof:name":"Goutouqing",
    "wof:placetype":"locality"
},
  "geometry": {"coordinates":[100.071,25.6041],"type":"Point"}
}