{
  "type": "Feature",
  "properties": {
    "gn:admin1_code":"30.0",
    "gn:asciiname":"Siwei",
    "gn:country_code":"CN",
    "gn:dem":65,
    "gn:feature_class":"P",
    "gn:feature_code":"PPL",
    "gn:name":"Siwei",
    "gn:population":0,
    "gn:timezone":"Asia/Shanghai",
    "iso:country":"CN",
    "name:zho_x_preferred":[
        "\u56db\u56f4"
    ],
    "wof:name":"Siwei",
    "wof:placetype":"locality"
},
  "geometry": {"coordinates":[114.18926,23.6308],"type":"Point"}
}