{
  "type": "Feature",
  "properties": {
    "gn:admin1_code":"32.0",
    "gn:asciiname":"Lantiankan",
    "gn:country_code":"CN",
    "gn:dem":288,
    "gn:feature_class":"P",
    "gn:feature_code":"PPL",
    "gn:name":"Lantiankan",
    "gn:population":0,
    "gn:timezone":"Asia/Shanghai",
    "iso:country":"CN",
    "name:zho_x_preferred":[
        "\u70c2\u7530\u574e"
    ],
    "wof:name":"Lantiankan",
    "wof:placetype":"locality"
},
  "geometry": {"coordinates":[105.59399999999999,28.8737],"type":"Point"}
}