{
  "type": "Feature",
  "properties": {
    "gn:admin1_code":"12.0",
    "gn:asciiname":"Matouwan",
    "gn:country_code":"CN",
    "gn:dem":20,
    "gn:feature_class":"P",
    "gn:feature_code":"PPL",
    "gn:name":"Matouwan",
    "gn:population":0,
    "gn:timezone":"Asia/Shanghai",
    "iso:country":"CN",
    "name:und_x_variant":[
        "\u9a6c\u5934\u5846"
    ],
    "wof:name":"Matouwan",
    "wof:placetype":"locality"
},
  "geometry": {"coordinates":[115.38761,30.19463],"type":"Point"}
}