{
  "type": "Feature",
  "properties": {
    "gn:admin1_code":"29.0",
    "gn:asciiname":"Lunan",
    "gn:country_code":"CN",
    "gn:dem":1040,
    "gn:feature_class":"P",
    "gn:feature_code":"PPL",
    "gn:name":"L\u00fcnan",
    "gn:population":0,
    "gn:timezone":"Asia/Shanghai",
    "iso:country":"CN",
    "name:ceb_x_preferred":[
        "Lunan"
    ],
    "name:deu_x_preferred":[
        "Lunan"
    ],
    "name:nld_x_preferred":[
        "Lunan"
    ],
    "name:swe_x_preferred":[
        "Lunan"
    ],
    "name:und_x_variant":[
        "L\u00fcnan",
        "\u7eff\u5357"
    ],
    "wof:name":"Lunan",
    "wof:placetype":"locality"
},
  "geometry": {"coordinates":[104.02533,27.81837],"type":"Point"}
}