{
  "type": "Feature",
  "properties": {
    "gn:admin1_code":"3.0",
    "gn:asciiname":"Huajiayuan Lijia",
    "gn:country_code":"CN",
    "gn:dem":62,
    "gn:feature_class":"P",
    "gn:feature_code":"PPL",
    "gn:name":"Huajiayuan Lijia",
    "gn:population":0,
    "gn:timezone":"Asia/Shanghai",
    "iso:country":"CN",
    "name:und_x_variant":[
        "\u5316\u5bb6\u6e90\u674e\u5bb6"
    ],
    "wof:name":"Huajiayuan Lijia",
    "wof:placetype":"locality"
},
  "geometry": {"coordinates":[114.70298,27.21901],"type":"Point"}
}