{
  "type": "Feature",
  "properties": {
    "gn:admin1_code":"15.0",
    "gn:asciiname":"Aluoquan",
    "gn:country_code":"CN",
    "gn:dem":2898,
    "gn:feature_class":"P",
    "gn:feature_code":"PPL",
    "gn:name":"Aluoquan",
    "gn:population":0,
    "gn:timezone":"Asia/Shanghai",
    "iso:country":"CN",
    "name:zho_x_preferred":[
        "\u554a\u7f57\u5708"
    ],
    "wof:name":"Aluoquan",
    "wof:placetype":"locality"
},
  "geometry": {"coordinates":[103.42,37.1569],"type":"Point"}
}