{
  "type": "Feature",
  "properties": {
    "gn:admin1_code":"11.0",
    "gn:asciiname":"Tu'nanxi",
    "gn:country_code":"CN",
    "gn:dem":502,
    "gn:feature_class":"P",
    "gn:feature_code":"PPL",
    "gn:name":"Tu\u2019nanxi",
    "gn:population":0,
    "gn:timezone":"Asia/Shanghai",
    "iso:country":"CN",
    "name:und_x_variant":[
        "Tu\u2019nanxi"
    ],
    "name:zho_x_preferred":[
        "\u571f\u5357\u6eaa"
    ],
    "name:zho_x_variant":[
        "Tu\u2019nanxi"
    ],
    "wof:name":"Tu'nanxi",
    "wof:placetype":"locality"
},
  "geometry": {"coordinates":[110.08389,29.4966],"type":"Point"}
}