{
  "type": "Feature",
  "properties": {
    "gn:admin1_code":"18",
    "gn:asciiname":"Shanghuang",
    "gn:country_code":"CN",
    "gn:dem":1033,
    "gn:feature_class":"P",
    "gn:feature_code":"PPL",
    "gn:name":"Shanghuang",
    "gn:population":0,
    "gn:timezone":"Asia/Shanghai",
    "iso:country":"CN",
    "name:zho_x_preferred":[
        "\u4e0a\u9ec4"
    ],
    "wof:name":"Shanghuang",
    "wof:placetype":"locality"
},
  "geometry": {"coordinates":[106.708,26.2699],"type":"Point"}
}