{
  "type": "Feature",
  "properties": {
    "gn:admin1_code":"14.0",
    "gn:asciiname":"Gezha",
    "gn:country_code":"CN",
    "gn:dem":3683,
    "gn:feature_class":"P",
    "gn:feature_code":"PPL",
    "gn:name":"Gezha",
    "gn:population":0,
    "gn:timezone":"Asia/Urumqi",
    "iso:country":"CN",
    "name:bod_x_preferred":[
        "G\u00eaza"
    ],
    "name:zho_x_preferred":[
        "Gezha"
    ],
    "name:zho_x_variant":[
        "\u683c\u624e",
        "Gelong Gongshe",
        "\u683c\u9f99\u516c\u793e"
    ],
    "wof:name":"Gezha",
    "wof:placetype":"locality"
},
  "geometry": {"coordinates":[97.12739999999999,31.98019],"type":"Point"}
}