{
  "type": "Feature",
  "properties": {
    "gn:admin1_code":"15.0",
    "gn:asciiname":"Changshan",
    "gn:country_code":"CN",
    "gn:dem":1707,
    "gn:feature_class":"P",
    "gn:feature_code":"PPL",
    "gn:name":"Changshan",
    "gn:population":0,
    "gn:timezone":"Asia/Shanghai",
    "iso:country":"CN",
    "name:zho_x_preferred":[
        "\u5e38\u5c71"
    ],
    "wof:name":"Changshan",
    "wof:placetype":"locality"
},
  "geometry": {"coordinates":[105.023,34.1251],"type":"Point"}
}