{
  "type": "Feature",
  "properties": {
    "gn:admin1_code":"24.0",
    "gn:asciiname":"Xiaoganhe",
    "gn:country_code":"CN",
    "gn:dem":1639,
    "gn:feature_class":"P",
    "gn:feature_code":"PPL",
    "gn:name":"Xiaoganhe",
    "gn:population":0,
    "gn:timezone":"Asia/Shanghai",
    "iso:country":"CN",
    "name:zho_x_preferred":[
        "\u5c0f\u7518\u6cb3"
    ],
    "wof:name":"Xiaoganhe",
    "wof:placetype":"locality"
},
  "geometry": {"coordinates":[113.71026000000001,38.94244000000001],"type":"Point"}
}