{
  "type": "Feature",
  "properties": {
    "gn:admin1_code":"15.0",
    "gn:asciiname":"Chajia Wopu",
    "gn:country_code":"CN",
    "gn:dem":2610,
    "gn:feature_class":"P",
    "gn:feature_code":"PPL",
    "gn:name":"Chajia Wopu",
    "gn:population":0,
    "gn:timezone":"Asia/Shanghai",
    "iso:country":"CN",
    "name:zho_x_preferred":[
        "\u67e5\u5bb6\u7a9d\u94fa"
    ],
    "wof:name":"Chajia Wopu",
    "wof:placetype":"locality"
},
  "geometry": {"coordinates":[102.398,37.679],"type":"Point"}
}