{
  "type": "Feature",
  "properties": {
    "gn:admin1_code":"11.0",
    "gn:asciiname":"Washi",
    "gn:country_code":"CN",
    "gn:dem":368,
    "gn:feature_class":"P",
    "gn:feature_code":"PPL",
    "gn:name":"Washi",
    "gn:population":0,
    "gn:timezone":"Asia/Shanghai",
    "iso:country":"CN",
    "name:cat_x_preferred":[
        "Washi"
    ],
    "name:dan_x_preferred":[
        "Japanpapir"
    ],
    "name:deu_x_preferred":[
        "Japanpapier"
    ],
    "name:epo_x_preferred":[
        "Washi"
    ],
    "name:fas_x_preferred":[
        "\u0648\u0627\u0634\u06cc"
    ],
    "name:fin_x_preferred":[
        "Japaninpaperi"
    ],
    "name:fra_x_preferred":[
        "Washi"
    ],
    "name:hrv_x_preferred":[
        "Japanski papir"
    ],
    "name:hun_x_preferred":[
        "Vasi"
    ],
    "name:ind_x_preferred":[
        "Washi"
    ],
    "name:ita_x_preferred":[
        "Washi"
    ],
    "name:jav_x_preferred":[
        "Washi"
    ],
    "name:msa_x_preferred":[
        "Washi"
    ],
    "name:nld_x_preferred":[
        "Washi"
    ],
    "name:nno_x_preferred":[
        "Japanpapir"
    ],
    "name:nor_x_preferred":[
        "Japanpapir"
    ],
    "name:por_x_preferred":[
        "Washi"
    ],
    "name:ron_x_preferred":[
        "Washi"
    ],
    "name:rus_x_preferred":[
        "\u0412\u0430\u0441\u0438"
    ],
    "name:spa_x_preferred":[
        "Washi"
    ],
    "name:swe_x_preferred":[
        "Japanpapper"
    ],
    "name:tur_x_preferred":[
        "Washi"
    ],
    "name:ukr_x_preferred":[
        "\u042f\u043f\u043e\u043d\u0441\u044c\u043a\u0438\u0439 \u043f\u0430\u043f\u0456\u0440"
    ],
    "name:vie_x_preferred":[
        "Gi\u1ea5y washi"
    ],
    "name:zho_x_preferred":[
        "\u74e6\u77f3"
    ],
    "wof:name":"Washi",
    "wof:placetype":"locality"
},
  "geometry": {"coordinates":[112.51600999999999,25.55147],"type":"Point"}
}