{
  "type": "Feature",
  "properties": {
    "gn:admin1_code":"01",
    "gn:asciiname":"Guanyingqiao",
    "gn:country_code":"CN",
    "gn:dem":217,
    "gn:feature_class":"P",
    "gn:feature_code":"PPL",
    "gn:name":"Guanyingqiao",
    "gn:population":0,
    "gn:timezone":"Asia/Shanghai",
    "iso:country":"CN",
    "name:und_x_variant":[
        "Kuan-yin-ch\u2019iao",
        "Kuan-ying-ch\u2019iao",
        "Guanyingqiao",
        "\u5173\u82f1\u6865"
    ],
    "wof:name":"Guanyingqiao",
    "wof:placetype":"locality"
},
  "geometry": {"coordinates":[118.72986000000002,30.27325],"type":"Point"}
}