{
  "type": "Feature",
  "properties": {
    "gn:admin1_code":"32.0",
    "gn:asciiname":"Guihuawan",
    "gn:country_code":"CN",
    "gn:dem":347,
    "gn:feature_class":"P",
    "gn:feature_code":"PPL",
    "gn:name":"Guihuawan",
    "gn:population":0,
    "gn:timezone":"Asia/Shanghai",
    "iso:country":"CN",
    "name:zho_x_preferred":[
        "\u6842\u82b1\u6e7e"
    ],
    "wof:name":"Guihuawan",
    "wof:placetype":"locality"
},
  "geometry": {"coordinates":[104.66200000000001,29.9677],"type":"Point"}
}