{
  "type": "Feature",
  "properties": {
    "gn:admin1_code":"1.0",
    "gn:asciiname":"Wu'aicun",
    "gn:country_code":"CN",
    "gn:dem":20,
    "gn:feature_class":"P",
    "gn:feature_code":"PPL",
    "gn:name":"Wu\u2019aicun",
    "gn:population":0,
    "gn:timezone":"Asia/Shanghai",
    "iso:country":"CN",
    "name:und_x_variant":[
        "Wu\u2019aicun"
    ],
    "name:zho_x_preferred":[
        "\u4e94\u7231\u6751"
    ],
    "wof:name":"Wu'aicun",
    "wof:placetype":"locality"
},
  "geometry": {"coordinates":[117.3537,31.41632],"type":"Point"}
}