{
  "type": "Feature",
  "properties": {
    "gn:admin1_code":"29.0",
    "gn:asciiname":"Hengdulegu",
    "gn:country_code":"CN",
    "gn:dem":2536,
    "gn:feature_class":"P",
    "gn:feature_code":"PPL",
    "gn:name":"Hengdulegu",
    "gn:population":0,
    "gn:timezone":"Asia/Shanghai",
    "iso:country":"CN",
    "name:zho_x_preferred":[
        "\u4ea8\u72ec\u4e50\u56fa"
    ],
    "wof:name":"Hengdulegu",
    "wof:placetype":"locality"
},
  "geometry": {"coordinates":[99.5621,27.4236],"type":"Point"}
}