{
  "type": "Feature",
  "properties": {
    "gn:admin1_code":"32.0",
    "gn:asciiname":"Gushanbao",
    "gn:country_code":"CN",
    "gn:dem":665,
    "gn:feature_class":"P",
    "gn:feature_code":"PPL",
    "gn:name":"Gushanbao",
    "gn:population":0,
    "gn:timezone":"Asia/Shanghai",
    "iso:country":"CN",
    "name:zho_x_preferred":[
        "\u8c37\u5c71\u5305"
    ],
    "wof:name":"Gushanbao",
    "wof:placetype":"locality"
},
  "geometry": {"coordinates":[107.316,31.7224],"type":"Point"}
}