{
  "type": "Feature",
  "properties": {
    "gn:admin1_code":"18",
    "gn:asciiname":"Po'ang",
    "gn:country_code":"CN",
    "gn:dem":915,
    "gn:feature_class":"P",
    "gn:feature_code":"PPL",
    "gn:name":"Po\u2019ang",
    "gn:population":0,
    "gn:timezone":"Asia/Shanghai",
    "iso:country":"CN",
    "name:und_x_variant":[
        "Po\u2019ang"
    ],
    "name:zho_x_preferred":[
        "\u5761\u76ce"
    ],
    "wof:name":"Po'ang",
    "wof:placetype":"locality"
},
  "geometry": {"coordinates":[105.678,25.2757],"type":"Point"}
}