{
  "type": "Feature",
  "properties": {
    "gn:admin1_code":"29",
    "gn:asciiname":"Muwuji",
    "gn:country_code":"CN",
    "gn:dem":1270,
    "gn:feature_class":"P",
    "gn:feature_code":"PPL",
    "gn:name":"Muwuji",
    "gn:population":0,
    "gn:timezone":"Asia/Shanghai",
    "iso:country":"CN",
    "name:zho_x_preferred":[
        "\u6728\u5c4b\u57fa"
    ],
    "wof:name":"Muwuji",
    "wof:placetype":"locality"
},
  "geometry": {"coordinates":[105.53400000000001,23.8928],"type":"Point"}
}