{
  "type": "Feature",
  "properties": {
    "gn:admin1_code":"12.0",
    "gn:asciiname":"Gongjiachong",
    "gn:country_code":"CN",
    "gn:dem":160,
    "gn:feature_class":"P",
    "gn:feature_code":"PPL",
    "gn:name":"Gongjiachong",
    "gn:population":0,
    "gn:timezone":"Asia/Shanghai",
    "iso:country":"CN",
    "name:zho_x_preferred":[
        "Gongjiachong"
    ],
    "name:zho_x_variant":[
        "\u9f9a\u5bb6\u51b2"
    ],
    "wof:name":"Gongjiachong",
    "wof:placetype":"locality"
},
  "geometry": {"coordinates":[111.76259,30.69675],"type":"Point"}
}