{
  "type": "Feature",
  "properties": {
    "gn:admin1_code":"15.0",
    "gn:asciiname":"Zaixiang",
    "gn:country_code":"CN",
    "gn:dem":1456,
    "gn:feature_class":"P",
    "gn:feature_code":"PPL",
    "gn:name":"Zaixiang",
    "gn:population":0,
    "gn:timezone":"Asia/Shanghai",
    "iso:country":"CN",
    "name:zho_x_preferred":[
        "\u5bb0\u76f8"
    ],
    "wof:name":"Zaixiang",
    "wof:placetype":"locality"
},
  "geometry": {"coordinates":[106.946,35.0815],"type":"Point"}
}