{
  "type": "Feature",
  "properties": {
    "gn:admin1_code":"33.0",
    "gn:asciiname":"Caishanping",
    "gn:country_code":"CN",
    "gn:dem":603,
    "gn:feature_class":"P",
    "gn:feature_code":"PPL",
    "gn:name":"Caishanping",
    "gn:population":0,
    "gn:timezone":"Asia/Shanghai",
    "iso:country":"CN",
    "name:zho_x_preferred":[
        "\u8e29\u5c71\u576a"
    ],
    "wof:name":"Caishanping",
    "wof:placetype":"locality"
},
  "geometry": {"coordinates":[106.723,28.5981],"type":"Point"}
}