{
  "type": "Feature",
  "properties": {
    "gn:admin1_code":"30",
    "gn:asciiname":"Dongjiagong",
    "gn:country_code":"CN",
    "gn:dem":25,
    "gn:feature_class":"P",
    "gn:feature_code":"PPL",
    "gn:name":"Dongjiagong",
    "gn:population":0,
    "gn:timezone":"Asia/Shanghai",
    "iso:country":"CN",
    "name:zho_x_preferred":[
        "\u4e1c\u5bb6\u5bab"
    ],
    "wof:name":"Dongjiagong",
    "wof:placetype":"locality"
},
  "geometry": {"coordinates":[116.59265000000001,23.28536],"type":"Point"}
}