{
  "type": "Feature",
  "properties": {
    "gn:admin1_code":"18",
    "gn:asciiname":"Nuli",
    "gn:country_code":"CN",
    "gn:dem":1013,
    "gn:feature_class":"P",
    "gn:feature_code":"PPL",
    "gn:name":"Nuli",
    "gn:population":0,
    "gn:timezone":"Asia/Shanghai",
    "iso:country":"CN",
    "name:zho_x_preferred":[
        "\u52aa\u529b"
    ],
    "wof:name":"Nuli",
    "wof:placetype":"locality"
},
  "geometry": {"coordinates":[106.572,26.0309],"type":"Point"}
}