{
  "type": "Feature",
  "properties": {
    "gn:admin1_code":"30.0",
    "gn:asciiname":"Caodailong",
    "gn:country_code":"CN",
    "gn:dem":417,
    "gn:feature_class":"P",
    "gn:feature_code":"PPL",
    "gn:name":"Caodailong",
    "gn:population":0,
    "gn:timezone":"Asia/Shanghai",
    "iso:country":"CN",
    "name:zho_x_preferred":[
        "\u66f9\u6234\u7b3c"
    ],
    "wof:name":"Caodailong",
    "wof:placetype":"locality"
},
  "geometry": {"coordinates":[113.26443999999999,24.19639],"type":"Point"}
}