{
  "type": "Feature",
  "properties": {
    "gn:admin1_code":"10.0",
    "gn:asciiname":"Beishaya",
    "gn:country_code":"CN",
    "gn:dem":5,
    "gn:feature_class":"P",
    "gn:feature_code":"PPL",
    "gn:name":"Beishaya",
    "gn:population":0,
    "gn:timezone":"Asia/Shanghai",
    "iso:country":"CN",
    "name:zho_x_preferred":[
        "\u5317\u6c99\u5d16"
    ],
    "wof:name":"Beishaya",
    "wof:placetype":"locality"
},
  "geometry": {"coordinates":[119.11547,39.39272],"type":"Point"}
}