{
  "type": "Feature",
  "properties": {
    "gn:admin1_code":"30",
    "gn:asciiname":"Langkou",
    "gn:country_code":"CN",
    "gn:dem":210,
    "gn:feature_class":"P",
    "gn:feature_code":"PPL",
    "gn:name":"Langkou",
    "gn:population":0,
    "gn:timezone":"Asia/Shanghai",
    "iso:country":"CN",
    "name:und_x_variant":[
        "\u6717\u53e3"
    ],
    "name:zho_x_preferred":[
        "\u6717\u53e3"
    ],
    "wof:name":"Langkou",
    "wof:placetype":"locality"
},
  "geometry": {"coordinates":[113.93556,23.85],"type":"Point"}
}