{
  "type": "Feature",
  "properties": {
    "gn:admin1_code":"12.0",
    "gn:asciiname":"Hulubao",
    "gn:country_code":"CN",
    "gn:dem":683,
    "gn:feature_class":"P",
    "gn:feature_code":"PPL",
    "gn:name":"Hulubao",
    "gn:population":0,
    "gn:timezone":"Asia/Shanghai",
    "iso:country":"CN",
    "name:zho_x_preferred":[
        "\u846b\u82a6\u5305"
    ],
    "wof:name":"Hulubao",
    "wof:placetype":"locality"
},
  "geometry": {"coordinates":[111.18608999999999,32.21604],"type":"Point"}
}