{
  "type": "Feature",
  "properties": {
    "gn:admin1_code":"12.0",
    "gn:asciiname":"Shazigang",
    "gn:country_code":"CN",
    "gn:dem":185,
    "gn:feature_class":"P",
    "gn:feature_code":"PPL",
    "gn:name":"Shazigang",
    "gn:population":0,
    "gn:timezone":"Asia/Shanghai",
    "iso:country":"CN",
    "name:zho_x_preferred":[
        "\u7802\u5b50\u5c97"
    ],
    "wof:name":"Shazigang",
    "wof:placetype":"locality"
},
  "geometry": {"coordinates":[112.84997,32.31891],"type":"Point"}
}