{
  "type": "Feature",
  "properties": {
    "gn:admin1_code":"26.0",
    "gn:asciiname":"Mafangcun",
    "gn:country_code":"CN",
    "gn:dem":939,
    "gn:feature_class":"P",
    "gn:feature_code":"PPL",
    "gn:name":"Mafangcun",
    "gn:population":0,
    "gn:timezone":"Asia/Shanghai",
    "iso:country":"CN",
    "name:zho_x_preferred":[
        "\u9a6c\u574a\u6751"
    ],
    "wof:name":"Mafangcun",
    "wof:placetype":"locality"
},
  "geometry": {"coordinates":[109.77276000000001,38.00679],"type":"Point"}
}