{
  "type": "Feature",
  "properties": {
    "gn:admin1_code":"08",
    "gn:asciiname":"Kertai",
    "gn:country_code":"CN",
    "gn:dem":145,
    "gn:feature_class":"P",
    "gn:feature_code":"PPLA4",
    "gn:name":"Kertai",
    "gn:population":0,
    "gn:timezone":"Asia/Shanghai",
    "iso:country":"CN",
    "name:mon_x_preferred":[
        "Kertai"
    ],
    "name:und_x_variant":[
        "Ke\u2019ertai",
        "Ke\u2019ertai Xiang"
    ],
    "name:zho_x_preferred":[
        "\u514b\u5c14\u53f0"
    ],
    "name:zho_x_variant":[
        "\u514b\u5c14\u53f0\u4e61"
    ],
    "wof:name":"Kertai",
    "wof:placetype":"locality"
},
  "geometry": {"coordinates":[124.20302,46.89623],"type":"Point"}
}