{
  "type": "Feature",
  "properties": {
    "gn:admin1_code":"12.0",
    "gn:asciiname":"Niejiawan",
    "gn:country_code":"CN",
    "gn:dem":141,
    "gn:feature_class":"P",
    "gn:feature_code":"PPL",
    "gn:name":"Niejiawan",
    "gn:population":0,
    "gn:timezone":"Asia/Shanghai",
    "iso:country":"CN",
    "name:zho_x_preferred":[
        "\u8042\u5bb6\u5846"
    ],
    "wof:name":"Niejiawan",
    "wof:placetype":"locality"
},
  "geometry": {"coordinates":[112.92404999999999,32.05832],"type":"Point"}
}