{
  "type": "Feature",
  "properties": {
    "gn:admin1_code":"8.0",
    "gn:asciiname":"Fulongcun",
    "gn:country_code":"CN",
    "gn:dem":200,
    "gn:feature_class":"P",
    "gn:feature_code":"PPL",
    "gn:name":"Fulongcun",
    "gn:population":0,
    "gn:timezone":"Asia/Shanghai",
    "iso:country":"CN",
    "name:zho_x_preferred":[
        "\u798f\u9686\u6751"
    ],
    "wof:name":"Fulongcun",
    "wof:placetype":"locality"
},
  "geometry": {"coordinates":[125.5119,45.89485],"type":"Point"}
}