{
  "type": "Feature",
  "properties": {
    "gn:admin1_code":"18.0",
    "gn:asciiname":"Shangguijiao",
    "gn:country_code":"CN",
    "gn:dem":471,
    "gn:feature_class":"P",
    "gn:feature_code":"PPL",
    "gn:name":"Shangguijiao",
    "gn:population":0,
    "gn:timezone":"Asia/Shanghai",
    "iso:country":"CN",
    "name:zho_x_preferred":[
        "\u4e0a\u5f52\u7ede"
    ],
    "wof:name":"Shangguijiao",
    "wof:placetype":"locality"
},
  "geometry": {"coordinates":[109.089,26.6329],"type":"Point"}
}