{
  "type": "Feature",
  "properties": {
    "gn:admin1_code":"14.0",
    "gn:asciiname":"Zanlalong",
    "gn:country_code":"CN",
    "gn:dem":4267,
    "gn:feature_class":"P",
    "gn:feature_code":"PPL",
    "gn:name":"Zanlalong",
    "gn:population":0,
    "gn:timezone":"Asia/Urumqi",
    "iso:country":"CN",
    "name:zho_x_preferred":[
        "\u54b1\u62c9\u62e2"
    ],
    "wof:name":"Zanlalong",
    "wof:placetype":"locality"
},
  "geometry": {"coordinates":[95.43483000000001,30.79793],"type":"Point"}
}