{
  "type": "Feature",
  "properties": {
    "gn:admin1_code":"32.0",
    "gn:asciiname":"Changxugongma",
    "gn:country_code":"CN",
    "gn:dem":3931,
    "gn:feature_class":"P",
    "gn:feature_code":"PPL",
    "gn:name":"Changxugongma",
    "gn:population":0,
    "gn:timezone":"Asia/Shanghai",
    "iso:country":"CN",
    "name:und_x_variant":[
        "Chox\u00fckongma",
        "Changxugongma"
    ],
    "name:zho_x_preferred":[
        "\u957f\u987b\u8d21\u9a6c"
    ],
    "wof:name":"Changxugongma",
    "wof:placetype":"locality"
},
  "geometry": {"coordinates":[98.93901,32.76444],"type":"Point"}
}