{
  "type": "Feature",
  "properties": {
    "gn:admin1_code":"29.0",
    "gn:asciiname":"Laolintou",
    "gn:country_code":"CN",
    "gn:dem":1621,
    "gn:feature_class":"P",
    "gn:feature_code":"PPL",
    "gn:name":"Laolintou",
    "gn:population":0,
    "gn:timezone":"Asia/Shanghai",
    "iso:country":"CN",
    "name:zho_x_preferred":[
        "\u8001\u6797\u5934"
    ],
    "wof:name":"Laolintou",
    "wof:placetype":"locality"
},
  "geometry": {"coordinates":[104.70099999999999,27.4735],"type":"Point"}
}