{
  "type": "Feature",
  "properties": {
    "gn:admin1_code":"31",
    "gn:asciiname":"Liqun",
    "gn:country_code":"CN",
    "gn:dem":29,
    "gn:feature_class":"P",
    "gn:feature_code":"PPL",
    "gn:name":"Liqun",
    "gn:population":0,
    "gn:timezone":"Asia/Shanghai",
    "iso:country":"CN",
    "name:und_x_variant":[
        "\u529b\u7fa4"
    ],
    "wof:name":"Liqun",
    "wof:placetype":"locality"
},
  "geometry": {"coordinates":[110.813,19.8064],"type":"Point"}
}