{
  "type": "Feature",
  "properties": {
    "gn:admin1_code":"9.0",
    "gn:asciiname":"Jiusun",
    "gn:country_code":"CN",
    "gn:dem":154,
    "gn:feature_class":"P",
    "gn:feature_code":"PPL",
    "gn:name":"Jiusun",
    "gn:population":0,
    "gn:timezone":"Asia/Shanghai",
    "iso:country":"CN",
    "name:zho_x_preferred":[
        "\u9152\u5b59"
    ],
    "wof:name":"Jiusun",
    "wof:placetype":"locality"
},
  "geometry": {"coordinates":[113.78848000000001,34.57724],"type":"Point"}
}