{
  "type": "Feature",
  "properties": {
    "gn:admin1_code":"32.0",
    "gn:asciiname":"Gaopozi",
    "gn:country_code":"CN",
    "gn:dem":1222,
    "gn:feature_class":"P",
    "gn:feature_code":"PPL",
    "gn:name":"Gaopozi",
    "gn:population":0,
    "gn:timezone":"Asia/Shanghai",
    "iso:country":"CN",
    "name:zho_x_preferred":[
        "\u9ad8\u5761\u5b50"
    ],
    "wof:name":"Gaopozi",
    "wof:placetype":"locality"
},
  "geometry": {"coordinates":[105.99681,32.48751],"type":"Point"}
}