{
  "type": "Feature",
  "properties": {
    "gn:admin1_code":"26",
    "gn:asciiname":"Xiqiaotou",
    "gn:country_code":"CN",
    "gn:dem":443,
    "gn:feature_class":"P",
    "gn:feature_code":"PPL",
    "gn:name":"Xiqiaotou",
    "gn:population":0,
    "gn:timezone":"Asia/Shanghai",
    "iso:country":"CN",
    "name:zho_x_preferred":[
        "\u897f\u6865\u5934"
    ],
    "wof:name":"Xiqiaotou",
    "wof:placetype":"locality"
},
  "geometry": {"coordinates":[108.10015,34.24642],"type":"Point"}
}