{
  "type": "Feature",
  "properties": {
    "gn:admin1_code":"5.0",
    "gn:asciiname":"Sandaoyangcha",
    "gn:country_code":"CN",
    "gn:dem":427,
    "gn:feature_class":"P",
    "gn:feature_code":"PPL",
    "gn:name":"Sandaoyangcha",
    "gn:population":0,
    "gn:timezone":"Asia/Shanghai",
    "iso:country":"CN",
    "name:und_x_variant":[
        "\u4e09\u9053\u9633\u5c94"
    ],
    "wof:name":"Sandaoyangcha",
    "wof:placetype":"locality"
},
  "geometry": {"coordinates":[125.70323,41.26742],"type":"Point"}
}