{
  "type": "Feature",
  "properties": {
    "gn:admin1_code":"14.0",
    "gn:asciiname":"Kaqinka",
    "gn:country_code":"CN",
    "gn:dem":4542,
    "gn:feature_class":"P",
    "gn:feature_code":"PPL",
    "gn:name":"Kaqinka",
    "gn:population":0,
    "gn:timezone":"Asia/Urumqi",
    "iso:country":"CN",
    "name:bod_x_preferred":[
        "Kaq\u00eanka"
    ],
    "name:zho_x_preferred":[
        "Kaqinka"
    ],
    "name:zho_x_variant":[
        "\u5580\u94a6\u5580",
        "Songta Gongshe",
        "\u677e\u5854\u516c\u793e"
    ],
    "wof:name":"Kaqinka",
    "wof:placetype":"locality"
},
  "geometry": {"coordinates":[93.901,31.901],"type":"Point"}
}