{
  "type": "Feature",
  "properties": {
    "gn:admin1_code":"13",
    "gn:asciiname":"Dengcaogou",
    "gn:country_code":"CN",
    "gn:dem":1846,
    "gn:feature_class":"P",
    "gn:feature_code":"PPL",
    "gn:name":"Dengcaogou",
    "gn:population":0,
    "gn:timezone":"Asia/Urumqi",
    "iso:country":"CN",
    "name:zho_x_preferred":[
        "\u706f\u8349\u6c9f"
    ],
    "wof:name":"Dengcaogou",
    "wof:placetype":"locality"
},
  "geometry": {"coordinates":[87.37263,43.42863],"type":"Point"}
}