{
  "type": "Feature",
  "properties": {
    "gn:admin1_code":"30.0",
    "gn:asciiname":"Lizhigang",
    "gn:country_code":"CN",
    "gn:dem":79,
    "gn:feature_class":"P",
    "gn:feature_code":"PPL",
    "gn:name":"Lizhigang",
    "gn:population":0,
    "gn:timezone":"Asia/Shanghai",
    "iso:country":"CN",
    "name:zho_x_preferred":[
        "\u8354\u679d\u5c97"
    ],
    "wof:name":"Lizhigang",
    "wof:placetype":"locality"
},
  "geometry": {"coordinates":[112.15831,22.62954],"type":"Point"}
}