{
  "type": "Feature",
  "properties": {
    "gn:admin1_code":"25",
    "gn:asciiname":"Kongzhen",
    "gn:cc2":"CN",
    "gn:country_code":"CN",
    "gn:dem":13,
    "gn:feature_class":"P",
    "gn:feature_code":"PPL",
    "gn:name":"Kongzhen",
    "gn:population":0,
    "gn:timezone":"Asia/Shanghai",
    "iso:country":"CN",
    "name:und_x_variant":[
        "K\u2019ung-chia-chen",
        "K\u2019ung-chen",
        "Kongzhen"
    ],
    "wof:name":"Kongzhen",
    "wof:placetype":"locality"
},
  "geometry": {"coordinates":[116.96666999999999,37.58333],"type":"Point"}
}