{
  "type": "Feature",
  "properties": {
    "gn:admin1_code":"14.0",
    "gn:asciiname":"Yili",
    "gn:country_code":"CN",
    "gn:dem":3623,
    "gn:feature_class":"P",
    "gn:feature_code":"PPL",
    "gn:name":"Yili",
    "gn:population":0,
    "gn:timezone":"Asia/Shanghai",
    "iso:country":"CN",
    "name:ceb_x_preferred":[
        "Yili"
    ],
    "name:deu_x_preferred":[
        "Yili"
    ],
    "name:fra_x_preferred":[
        "Yili"
    ],
    "name:swe_x_preferred":[
        "Yili"
    ],
    "name:zho_x_preferred":[
        "\u8863\u529b"
    ],
    "wof:name":"Yili",
    "wof:placetype":"locality"
},
  "geometry": {"coordinates":[78.86199999999999,31.8369],"type":"Point"}
}