{
  "type": "Feature",
  "properties": {
    "gn:admin1_code":"7.0",
    "gn:asciiname":"Nanbing",
    "gn:country_code":"CN",
    "gn:dem":414,
    "gn:feature_class":"P",
    "gn:feature_code":"PPL",
    "gn:name":"Nanbing",
    "gn:population":0,
    "gn:timezone":"Asia/Shanghai",
    "iso:country":"CN",
    "name:zho_x_preferred":[
        "\u5357\u70b3"
    ],
    "wof:name":"Nanbing",
    "wof:placetype":"locality"
},
  "geometry": {"coordinates":[117.61296000000002,25.48281],"type":"Point"}
}