{
  "type": "Feature",
  "properties": {
    "gn:admin1_code":"2.0",
    "gn:asciiname":"Xiyan",
    "gn:country_code":"CN",
    "gn:dem":10,
    "gn:feature_class":"P",
    "gn:feature_code":"PPL",
    "gn:name":"Xiyan",
    "gn:population":0,
    "gn:timezone":"Asia/Shanghai",
    "iso:country":"CN",
    "name:ceb_x_preferred":[
        "Xiyan"
    ],
    "name:swe_x_preferred":[
        "Xiyan"
    ],
    "name:zho_x_preferred":[
        "\u6eaa\u6cbf"
    ],
    "wof:name":"Xiyan",
    "wof:placetype":"locality"
},
  "geometry": {"coordinates":[121.90921000000002,29.60656],"type":"Point"}
}