{
  "type": "Feature",
  "properties": {
    "gn:admin1_code":"26.0",
    "gn:asciiname":"Nanwan",
    "gn:country_code":"CN",
    "gn:dem":964,
    "gn:feature_class":"P",
    "gn:feature_code":"PPL",
    "gn:name":"Nanwan",
    "gn:population":0,
    "gn:timezone":"Asia/Shanghai",
    "iso:country":"CN",
    "name:zho_x_preferred":[
        "\u5357\u6e7e"
    ],
    "wof:name":"Nanwan",
    "wof:placetype":"locality"
},
  "geometry": {"coordinates":[110.12268,35.57706],"type":"Point"}
}