{
  "type": "Feature",
  "properties": {
    "gn:admin1_code":"32.0",
    "gn:asciiname":"Shaduo",
    "gn:country_code":"CN",
    "gn:dem":3464,
    "gn:feature_class":"P",
    "gn:feature_code":"PPL",
    "gn:name":"Shaduo",
    "gn:population":0,
    "gn:timezone":"Asia/Shanghai",
    "iso:country":"CN",
    "name:zho_x_preferred":[
        "\u6c99\u591a"
    ],
    "wof:name":"Shaduo",
    "wof:placetype":"locality"
},
  "geometry": {"coordinates":[101.125,31.0363],"type":"Point"}
}