{
  "type": "Feature",
  "properties": {
    "gn:admin1_code":"10",
    "gn:asciiname":"Beibao",
    "gn:country_code":"CN",
    "gn:dem":488,
    "gn:feature_class":"P",
    "gn:feature_code":"PPL",
    "gn:name":"Beibao",
    "gn:population":0,
    "gn:timezone":"Asia/Shanghai",
    "iso:country":"CN",
    "wof:name":"Beibao",
    "wof:placetype":"locality"
},
  "geometry": {"coordinates":[117.63443999999998,40.52583],"type":"Point"}
}