{
  "type": "Feature",
  "properties": {
    "gn:admin1_code":"32.0",
    "gn:asciiname":"Famuchang",
    "gn:country_code":"CN",
    "gn:dem":3618,
    "gn:feature_class":"P",
    "gn:feature_code":"PPL",
    "gn:name":"Famuchang",
    "gn:population":0,
    "gn:timezone":"Asia/Shanghai",
    "iso:country":"CN",
    "name:zho_x_preferred":[
        "\u4f10\u6728\u573a"
    ],
    "wof:name":"Famuchang",
    "wof:placetype":"locality"
},
  "geometry": {"coordinates":[100.92700000000001,32.2785],"type":"Point"}
}