{
  "type": "Feature",
  "properties": {
    "gn:admin1_code":"18",
    "gn:asciiname":"Modajia",
    "gn:country_code":"CN",
    "gn:dem":1655,
    "gn:feature_class":"P",
    "gn:feature_code":"PPL",
    "gn:name":"Modajia",
    "gn:population":0,
    "gn:timezone":"Asia/Shanghai",
    "iso:country":"CN",
    "name:zho_x_preferred":[
        "\u78e8\u6253\u621b"
    ],
    "wof:name":"Modajia",
    "wof:placetype":"locality"
},
  "geometry": {"coordinates":[104.529,25.9635],"type":"Point"}
}