{
  "type": "Feature",
  "properties": {
    "gn:admin1_code":"15.0",
    "gn:asciiname":"Luzixia",
    "gn:country_code":"CN",
    "gn:dem":2450,
    "gn:feature_class":"P",
    "gn:feature_code":"PPL",
    "gn:name":"Luzixia",
    "gn:population":0,
    "gn:timezone":"Asia/Shanghai",
    "iso:country":"CN",
    "name:und_x_variant":[
        "\u82a6\u5b50\u4e0b"
    ],
    "wof:name":"Luzixia",
    "wof:placetype":"locality"
},
  "geometry": {"coordinates":[104.33108,34.79612],"type":"Point"}
}