{
  "type": "Feature",
  "properties": {
    "gn:admin1_code":"15.0",
    "gn:asciiname":"Chixiajie",
    "gn:country_code":"CN",
    "gn:dem":1573,
    "gn:feature_class":"P",
    "gn:feature_code":"PPL",
    "gn:name":"Chixiajie",
    "gn:population":0,
    "gn:timezone":"Asia/Shanghai",
    "iso:country":"CN",
    "name:zho_x_preferred":[
        "\u8d64\u5ce1\u8857"
    ],
    "wof:name":"Chixiajie",
    "wof:placetype":"locality"
},
  "geometry": {"coordinates":[97.37269999999999,40.0828],"type":"Point"}
}