{
  "type": "Feature",
  "properties": {
    "gn:admin1_code":"26.0",
    "gn:asciiname":"Wenjiaping",
    "gn:country_code":"CN",
    "gn:dem":1341,
    "gn:feature_class":"P",
    "gn:feature_code":"PPL",
    "gn:name":"Wenjiaping",
    "gn:population":0,
    "gn:timezone":"Asia/Shanghai",
    "iso:country":"CN",
    "name:und_x_variant":[
        "\u6587\u5bb6\u576a"
    ],
    "wof:name":"Wenjiaping",
    "wof:placetype":"locality"
},
  "geometry": {"coordinates":[106.73007,32.8141],"type":"Point"}
}