{
  "type": "Feature",
  "properties": {
    "gn:admin1_code":"30",
    "gn:asciiname":"Zhongxinkeng",
    "gn:country_code":"CN",
    "gn:dem":234,
    "gn:feature_class":"P",
    "gn:feature_code":"PPL",
    "gn:name":"Zhongxinkeng",
    "gn:population":0,
    "gn:timezone":"Asia/Shanghai",
    "iso:country":"CN",
    "name:zho_x_preferred":[
        "\u4e2d\u5fc3\u5751"
    ],
    "wof:name":"Zhongxinkeng",
    "wof:placetype":"locality"
},
  "geometry": {"coordinates":[115.9858,24.66597],"type":"Point"}
}