{
  "type": "Feature",
  "properties": {
    "gn:admin1_code":"3.0",
    "gn:asciiname":"Xijiabian",
    "gn:country_code":"CN",
    "gn:dem":53,
    "gn:feature_class":"P",
    "gn:feature_code":"PPL",
    "gn:name":"Xijiabian",
    "gn:population":0,
    "gn:timezone":"Asia/Shanghai",
    "iso:country":"CN",
    "name:zho_x_preferred":[
        "\u897f\u5bb6\u8fb9"
    ],
    "wof:name":"Xijiabian",
    "wof:placetype":"locality"
},
  "geometry": {"coordinates":[114.979,27.8255],"type":"Point"}
}