{
  "type": "Feature",
  "properties": {
    "gn:admin1_code":"30",
    "gn:asciiname":"Shaba Zhen",
    "gn:country_code":"CN",
    "gn:dem":12,
    "gn:feature_class":"P",
    "gn:feature_code":"PPLA4",
    "gn:name":"Shaba Zhen",
    "gn:population":0,
    "gn:timezone":"Asia/Shanghai",
    "iso:country":"CN",
    "name:und_x_variant":[
        "\u6c99\u6252",
        "Shaba Zhen"
    ],
    "wof:name":"Shaba Zhen",
    "wof:placetype":"locality"
},
  "geometry": {"coordinates":[111.47884000000001,21.53162],"type":"Point"}
}