{
  "type": "Feature",
  "properties": {
    "gn:admin1_code":"4.0",
    "gn:asciiname":"Qianjiaxiang",
    "gn:country_code":"CN",
    "gn:dem":5,
    "gn:feature_class":"P",
    "gn:feature_code":"PPL",
    "gn:name":"Qianjiaxiang",
    "gn:population":0,
    "gn:timezone":"Asia/Shanghai",
    "iso:country":"CN",
    "name:und_x_variant":[
        "\u94b1\u5bb6\u5df7"
    ],
    "wof:name":"Qianjiaxiang",
    "wof:placetype":"locality"
},
  "geometry": {"coordinates":[121.1245,31.65842],"type":"Point"}
}