{
  "type": "Feature",
  "properties": {
    "gn:admin1_code":"32.0",
    "gn:asciiname":"Re'er",
    "gn:country_code":"CN",
    "gn:dem":2602,
    "gn:feature_class":"P",
    "gn:feature_code":"PPL",
    "gn:name":"Re\u2019er",
    "gn:population":0,
    "gn:timezone":"Asia/Shanghai",
    "iso:country":"CN",
    "name:zho_x_preferred":[
        "\u70ed\u5c14"
    ],
    "name:zho_x_variant":[
        "Re\u2019er"
    ],
    "wof:name":"Re'er",
    "wof:placetype":"locality"
},
  "geometry": {"coordinates":[103.07984,34.05127],"type":"Point"}
}