{
  "type": "Feature",
  "properties": {
    "gn:admin1_code":"4.0",
    "gn:asciiname":"Xieqiao",
    "gn:country_code":"CN",
    "gn:dem":5,
    "gn:feature_class":"P",
    "gn:feature_code":"PPL",
    "gn:name":"Xieqiao",
    "gn:population":0,
    "gn:timezone":"Asia/Shanghai",
    "iso:country":"CN",
    "name:und_x_variant":[
        "\u659c\u6865"
    ],
    "wof:name":"Xieqiao",
    "wof:placetype":"locality"
},
  "geometry": {"coordinates":[121.51245,32.01108],"type":"Point"}
}