{
  "type": "Feature",
  "properties": {
    "gn:admin1_code":"32.0",
    "gn:asciiname":"Baiyanxi",
    "gn:country_code":"CN",
    "gn:dem":499,
    "gn:feature_class":"P",
    "gn:feature_code":"PPL",
    "gn:name":"Baiyanxi",
    "gn:population":0,
    "gn:timezone":"Asia/Shanghai",
    "iso:country":"CN",
    "name:zho_x_preferred":[
        "\u767d\u71d5\u6eaa"
    ],
    "wof:name":"Baiyanxi",
    "wof:placetype":"locality"
},
  "geometry": {"coordinates":[107.94,31.9069],"type":"Point"}
}