{
  "type": "Feature",
  "properties": {
    "gn:admin1_code":"9.0",
    "gn:asciiname":"Shangen",
    "gn:country_code":"CN",
    "gn:dem":212,
    "gn:feature_class":"P",
    "gn:feature_code":"PPL",
    "gn:name":"Shangen",
    "gn:population":0,
    "gn:timezone":"Asia/Shanghai",
    "iso:country":"CN",
    "name:und_x_variant":[
        "\u5c71\u6839",
        "Shangen"
    ],
    "wof:name":"Shangen",
    "wof:placetype":"locality"
},
  "geometry": {"coordinates":[112.43362999999999,33.26475],"type":"Point"}
}