{
  "type": "Feature",
  "properties": {
    "gn:admin1_code":"12.0",
    "gn:asciiname":"Tianzhutang",
    "gn:country_code":"CN",
    "gn:dem":46,
    "gn:feature_class":"P",
    "gn:feature_code":"PPL",
    "gn:name":"Tianzhutang",
    "gn:population":0,
    "gn:timezone":"Asia/Shanghai",
    "iso:country":"CN",
    "name:zho_x_preferred":[
        "\u5929\u4e3b\u5802"
    ],
    "wof:name":"Tianzhutang",
    "wof:placetype":"locality"
},
  "geometry": {"coordinates":[112.59278,31.02683],"type":"Point"}
}