{
  "type": "Feature",
  "properties": {
    "gn:admin1_code":"32.0",
    "gn:asciiname":"Changwangge",
    "gn:country_code":"CN",
    "gn:dem":3408,
    "gn:feature_class":"P",
    "gn:feature_code":"PPL",
    "gn:name":"Changwangge",
    "gn:population":0,
    "gn:timezone":"Asia/Shanghai",
    "iso:country":"CN",
    "name:zho_x_preferred":[
        "\u660c\u65fa\u5404"
    ],
    "wof:name":"Changwangge",
    "wof:placetype":"locality"
},
  "geometry": {"coordinates":[99.1101,29.2929],"type":"Point"}
}