{
  "type": "Feature",
  "properties": {
    "gn:admin1_code":"2.0",
    "gn:asciiname":"Mantoushan",
    "gn:country_code":"CN",
    "gn:dem":95,
    "gn:feature_class":"P",
    "gn:feature_code":"PPL",
    "gn:name":"Mantoushan",
    "gn:population":0,
    "gn:timezone":"Asia/Shanghai",
    "iso:country":"CN",
    "name:zho_x_preferred":[
        "\u9992\u5934\u5c71"
    ],
    "wof:name":"Mantoushan",
    "wof:placetype":"locality"
},
  "geometry": {"coordinates":[118.86127999999999,29.03289],"type":"Point"}
}