{
  "type": "Feature",
  "properties": {
    "gn:admin1_code":"10",
    "gn:asciiname":"Xingjiuyuan",
    "gn:country_code":"CN",
    "gn:dem":14,
    "gn:feature_class":"P",
    "gn:feature_code":"PPL",
    "gn:name":"Xingjiuyuan",
    "gn:population":0,
    "gn:timezone":"Asia/Shanghai",
    "iso:country":"CN",
    "name:zho_x_preferred":[
        "\u90a2\u4e5d\u63f4"
    ],
    "wof:name":"Xingjiuyuan",
    "wof:placetype":"locality"
},
  "geometry": {"coordinates":[116.87794,37.97431],"type":"Point"}
}