{
  "type": "Feature",
  "properties": {
    "gn:admin1_code":"18",
    "gn:asciiname":"Huangjiaci",
    "gn:country_code":"CN",
    "gn:dem":731,
    "gn:feature_class":"P",
    "gn:feature_code":"PPL",
    "gn:name":"Huangjiaci",
    "gn:population":0,
    "gn:timezone":"Asia/Shanghai",
    "iso:country":"CN",
    "name:zho_x_preferred":[
        "\u9ec4\u5bb6\u7960"
    ],
    "wof:name":"Huangjiaci",
    "wof:placetype":"locality"
},
  "geometry": {"coordinates":[107.715,27.9499],"type":"Point"}
}