{
  "type": "Feature",
  "properties": {
    "gn:admin1_code":"05",
    "gn:asciiname":"Banshi",
    "gn:country_code":"CN",
    "gn:dem":51,
    "gn:feature_class":"P",
    "gn:feature_code":"PPLA4",
    "gn:name":"Banshi",
    "gn:population":0,
    "gn:timezone":"Asia/Shanghai",
    "iso:country":"CN",
    "name:und_x_variant":[
        "Pan-shih",
        "Pan-shih-kou-t\u2019un",
        "Banshi",
        "\u677f\u77f3",
        "Pan-shin",
        "Banshi Zhen",
        "\u677f\u77f3\u9547"
    ],
    "wof:name":"Banshi",
    "wof:placetype":"locality"
},
  "geometry": {"coordinates":[130.33833000000001,42.77833],"type":"Point"}
}