{
  "type": "Feature",
  "properties": {
    "gn:admin1_code":"14.0",
    "gn:asciiname":"Ri'axue",
    "gn:country_code":"CN",
    "gn:dem":4033,
    "gn:feature_class":"P",
    "gn:feature_code":"PPL",
    "gn:name":"Ri\u2019axue",
    "gn:population":0,
    "gn:timezone":"Asia/Urumqi",
    "iso:country":"CN",
    "name:und_x_variant":[
        "Ri\u2019axue"
    ],
    "name:zho_x_preferred":[
        "\u65e5\u963f\u8840"
    ],
    "wof:name":"Ri'axue",
    "wof:placetype":"locality"
},
  "geometry": {"coordinates":[96.4186,31.4104],"type":"Point"}
}