{
  "type": "Feature",
  "properties": {
    "gn:admin1_code":"29.0",
    "gn:asciiname":"Wanluo",
    "gn:country_code":"CN",
    "gn:dem":2356,
    "gn:feature_class":"P",
    "gn:feature_code":"PPL",
    "gn:name":"Wanluo",
    "gn:population":0,
    "gn:timezone":"Asia/Shanghai",
    "iso:country":"CN",
    "name:zho_x_preferred":[
        "\u6e7e\u843d"
    ],
    "wof:name":"Wanluo",
    "wof:placetype":"locality"
},
  "geometry": {"coordinates":[99.92,26.8061],"type":"Point"}
}