{
  "type": "Feature",
  "properties": {
    "gn:admin1_code":"29.0",
    "gn:asciiname":"Liziping",
    "gn:country_code":"CN",
    "gn:dem":2453,
    "gn:feature_class":"P",
    "gn:feature_code":"PPL",
    "gn:name":"Liziping",
    "gn:population":0,
    "gn:timezone":"Asia/Shanghai",
    "iso:country":"CN",
    "name:zho_x_preferred":[
        "\u674e\u5b50\u576a"
    ],
    "wof:name":"Liziping",
    "wof:placetype":"locality"
},
  "geometry": {"coordinates":[99.2311,26.8622],"type":"Point"}
}