{
  "type": "Feature",
  "properties": {
    "gn:admin1_code":"8.0",
    "gn:asciiname":"Sanduan Dongcun",
    "gn:country_code":"CN",
    "gn:dem":146,
    "gn:feature_class":"P",
    "gn:feature_code":"PPL",
    "gn:name":"Sanduan Dongcun",
    "gn:population":0,
    "gn:timezone":"Asia/Shanghai",
    "iso:country":"CN",
    "name:zho_x_preferred":[
        "\u4e09\u6bb5\u4e1c\u6751"
    ],
    "wof:name":"Sanduan Dongcun",
    "wof:placetype":"locality"
},
  "geometry": {"coordinates":[126.23524,46.85749000000001],"type":"Point"}
}