{
  "type": "Feature",
  "properties": {
    "gn:admin1_code":"32.0",
    "gn:asciiname":"Yangfang",
    "gn:country_code":"CN",
    "gn:dem":1896,
    "gn:feature_class":"P",
    "gn:feature_code":"PPL",
    "gn:name":"Yangfang",
    "gn:population":0,
    "gn:timezone":"Asia/Shanghai",
    "iso:country":"CN",
    "name:zho_x_preferred":[
        "\u7f8a\u623f"
    ],
    "wof:name":"Yangfang",
    "wof:placetype":"locality"
},
  "geometry": {"coordinates":[101.935,28.6255],"type":"Point"}
}