{
  "type": "Feature",
  "properties": {
    "gn:admin1_code":"20.0",
    "gn:asciiname":"Dedu",
    "gn:country_code":"CN",
    "gn:dem":284,
    "gn:feature_class":"P",
    "gn:feature_code":"PPL",
    "gn:name":"Dedu",
    "gn:population":0,
    "gn:timezone":"Asia/Shanghai",
    "iso:country":"CN",
    "name:ceb_x_preferred":[
        "Dedu"
    ],
    "name:swe_x_preferred":[
        "Dedu"
    ],
    "name:zho_x_preferred":[
        "\u5fb7\u90fd"
    ],
    "wof:name":"Dedu",
    "wof:placetype":"locality"
},
  "geometry": {"coordinates":[124.84385,49.48798],"type":"Point"}
}