{
  "type": "Feature",
  "properties": {
    "gn:admin1_code":"30.0",
    "gn:asciiname":"Jiangbeicun",
    "gn:country_code":"CN",
    "gn:dem":113,
    "gn:feature_class":"P",
    "gn:feature_code":"PPL",
    "gn:name":"Jiangbeicun",
    "gn:population":0,
    "gn:timezone":"Asia/Shanghai",
    "iso:country":"CN",
    "name:zho_x_preferred":[
        "\u6c5f\u80cc\u6751"
    ],
    "wof:name":"Jiangbeicun",
    "wof:placetype":"locality"
},
  "geometry": {"coordinates":[113.40263,24.88891],"type":"Point"}
}