{
  "type": "Feature",
  "properties": {
    "gn:admin1_code":"29.0",
    "gn:asciiname":"Anongba",
    "gn:country_code":"CN",
    "gn:dem":880,
    "gn:feature_class":"P",
    "gn:feature_code":"PPL",
    "gn:name":"Anongba",
    "gn:population":0,
    "gn:timezone":"Asia/Shanghai",
    "iso:country":"CN",
    "name:zho_x_preferred":[
        "\u963f\u5f04\u575d"
    ],
    "wof:name":"Anongba",
    "wof:placetype":"locality"
},
  "geometry": {"coordinates":[97.60380000000001,23.9414],"type":"Point"}
}