{
  "type": "Feature",
  "properties": {
    "gn:admin1_code":"29.0",
    "gn:asciiname":"Sidaidi",
    "gn:country_code":"CN",
    "gn:dem":2127,
    "gn:feature_class":"P",
    "gn:feature_code":"PPL",
    "gn:name":"Sidaidi",
    "gn:population":0,
    "gn:timezone":"Asia/Shanghai",
    "iso:country":"CN",
    "name:zho_x_preferred":[
        "\u56db\u4ee3\u5730"
    ],
    "wof:name":"Sidaidi",
    "wof:placetype":"locality"
},
  "geometry": {"coordinates":[100.961,25.101],"type":"Point"}
}