{
  "type": "Feature",
  "properties": {
    "gn:admin1_code":"16.0",
    "gn:asciiname":"Xingren",
    "gn:country_code":"CN",
    "gn:dem":584,
    "gn:feature_class":"P",
    "gn:feature_code":"PPL",
    "gn:name":"Xingren",
    "gn:population":0,
    "gn:timezone":"Asia/Shanghai",
    "iso:country":"CN",
    "name:ceb_x_preferred":[
        "Xingren Xian"
    ],
    "name:deu_x_preferred":[
        "Xingren"
    ],
    "name:ita_x_preferred":[
        "Xingren"
    ],
    "name:jpn_x_preferred":[
        "\u8208\u4ec1\u5e02"
    ],
    "name:kor_x_preferred":[
        "\uc2f1\ub7f0\uc2dc"
    ],
    "name:nor_x_preferred":[
        "Xingren"
    ],
    "name:swe_x_preferred":[
        "Xingren"
    ],
    "name:vie_x_preferred":[
        "H\u01b0ng Nh\u00e2n"
    ],
    "name:zho_x_preferred":[
        "\u5174\u4ec1"
    ],
    "name:zho_x_variant":[
        "\u5174\u4ec1\u5e02"
    ],
    "wof:name":"Xingren",
    "wof:placetype":"locality"
},
  "geometry": {"coordinates":[107.06699999999999,24.3518],"type":"Point"}
}