{
  "type": "Feature",
  "properties": {
    "gn:admin1_code":"13.0",
    "gn:asciiname":"Xinquchengzi",
    "gn:country_code":"CN",
    "gn:dem":427,
    "gn:feature_class":"P",
    "gn:feature_code":"PPL",
    "gn:name":"Xinquchengzi",
    "gn:population":0,
    "gn:timezone":"Asia/Urumqi",
    "iso:country":"CN",
    "name:zho_x_preferred":[
        "\u65b0\u6e20\u57ce\u5b50"
    ],
    "wof:name":"Xinquchengzi",
    "wof:placetype":"locality"
},
  "geometry": {"coordinates":[87.43958000000001,44.55084],"type":"Point"}
}