{
  "type": "Feature",
  "properties": {
    "gn:admin1_code":"25",
    "gn:asciiname":"Hulin",
    "gn:country_code":"CN",
    "gn:dem":98,
    "gn:feature_class":"P",
    "gn:feature_code":"PPL",
    "gn:name":"Hulin",
    "gn:population":0,
    "gn:timezone":"Asia/Shanghai",
    "iso:country":"CN",
    "name:deu_x_preferred":[
        "Hulin"
    ],
    "name:fra_x_preferred":[
        "Hulin"
    ],
    "name:ita_x_preferred":[
        "Hulin"
    ],
    "name:jpn_x_preferred":[
        "\u864e\u6797\u5e02"
    ],
    "name:kik_x_preferred":[
        "Hulin"
    ],
    "name:kor_x_preferred":[
        "\ud6c4\ub9b0\uc2dc"
    ],
    "name:mlg_x_preferred":[
        "Hulin"
    ],
    "name:nld_x_preferred":[
        "Hulin"
    ],
    "name:nor_x_preferred":[
        "Hulin"
    ],
    "name:pam_x_preferred":[
        "Hulin"
    ],
    "name:rus_x_preferred":[
        "\u0425\u0443\u043b\u0438\u043d\u044c"
    ],
    "name:swe_x_preferred":[
        "Hulin"
    ],
    "name:urd_x_preferred":[
        "\u06c1\u0648\u0644\u0646"
    ],
    "name:vie_x_preferred":[
        "H\u1ed5 L\u00e2m"
    ],
    "name:zho_x_preferred":[
        "\u80e1\u6797"
    ],
    "name:zho_x_variant":[
        "\u864e\u6797\u5e02"
    ],
    "wof:name":"Hulin",
    "wof:placetype":"locality"
},
  "geometry": {"coordinates":[116.643,36.3856],"type":"Point"}
}