{
  "type": "Feature",
  "properties": {
    "gn:admin1_code":"14.0",
    "gn:asciiname":"Cuobaikacun",
    "gn:country_code":"CN",
    "gn:dem":3912,
    "gn:feature_class":"P",
    "gn:feature_code":"PPL",
    "gn:name":"Cuobaikacun",
    "gn:population":0,
    "gn:timezone":"Asia/Urumqi",
    "iso:country":"CN",
    "name:zho_x_preferred":[
        "\u63aa\u767d\u5494\u6751"
    ],
    "wof:name":"Cuobaikacun",
    "wof:placetype":"locality"
},
  "geometry": {"coordinates":[94.33544999999999,31.46947],"type":"Point"}
}