{
  "type": "Feature",
  "properties": {
    "gn:admin1_code":"11.0",
    "gn:asciiname":"Luqian",
    "gn:country_code":"CN",
    "gn:dem":329,
    "gn:feature_class":"P",
    "gn:feature_code":"PPL",
    "gn:name":"Luqian",
    "gn:population":0,
    "gn:timezone":"Asia/Shanghai",
    "iso:country":"CN",
    "name:zho_x_preferred":[
        "\u7089\u524d"
    ],
    "wof:name":"Luqian",
    "wof:placetype":"locality"
},
  "geometry": {"coordinates":[113.82571000000002,28.44052000000001],"type":"Point"}
}