{
  "type": "Feature",
  "properties": {
    "gn:admin1_code":"5.0",
    "gn:asciiname":"Delige Yingzi",
    "gn:country_code":"CN",
    "gn:dem":156,
    "gn:feature_class":"P",
    "gn:feature_code":"PPL",
    "gn:name":"Delige Yingzi",
    "gn:population":0,
    "gn:timezone":"Asia/Shanghai",
    "iso:country":"CN",
    "name:zho_x_preferred":[
        "\u5fb7\u529b\u683c\u8425\u5b50"
    ],
    "wof:name":"Delige Yingzi",
    "wof:placetype":"locality"
},
  "geometry": {"coordinates":[122.84569999999999,44.77997],"type":"Point"}
}