{
  "type": "Feature",
  "properties": {
    "gn:admin1_code":"9",
    "gn:asciiname":"Dashilou",
    "gn:country_code":"CN",
    "gn:dem":54,
    "gn:feature_class":"P",
    "gn:feature_code":"PPL",
    "gn:name":"Dashilou",
    "gn:population":0,
    "gn:timezone":"Asia/Shanghai",
    "iso:country":"CN",
    "name:zho_x_preferred":[
        "\u5927\u53f2\u697c"
    ],
    "wof:name":"Dashilou",
    "wof:placetype":"locality"
},
  "geometry": {"coordinates":[115.52800000000001,34.3698],"type":"Point"}
}