{
  "type": "Feature",
  "properties": {
    "gn:admin1_code":"08",
    "gn:asciiname":"Longshenghe",
    "gn:country_code":"CN",
    "gn:dem":139,
    "gn:feature_class":"P",
    "gn:feature_code":"PPL",
    "gn:name":"Longshenghe",
    "gn:population":0,
    "gn:timezone":"Asia/Shanghai",
    "iso:country":"CN",
    "name:und_x_variant":[
        "Lung-sheng-ho",
        "Longshenghe"
    ],
    "name:zho_x_preferred":[
        "\u9686\u76db\u6cb3"
    ],
    "wof:name":"Longshenghe",
    "wof:placetype":"locality"
},
  "geometry": {"coordinates":[126.27835,46.4678],"type":"Point"}
}