{
  "type": "Feature",
  "properties": {
    "gn:admin1_code":"4.0",
    "gn:asciiname":"Nixiangcun",
    "gn:country_code":"CN",
    "gn:dem":12,
    "gn:feature_class":"P",
    "gn:feature_code":"PPL",
    "gn:name":"Nixiangcun",
    "gn:population":0,
    "gn:timezone":"Asia/Shanghai",
    "iso:country":"CN",
    "name:und_x_variant":[
        "\u502a\u5df7\u6751"
    ],
    "name:zho_x_preferred":[
        "\u502a\u5df7\u6751"
    ],
    "wof:name":"Nixiangcun",
    "wof:placetype":"locality"
},
  "geometry": {"coordinates":[120.36637,31.2865],"type":"Point"}
}