{
  "type": "Feature",
  "properties": {
    "gn:admin1_code":"14.0",
    "gn:asciiname":"Kangrancun",
    "gn:country_code":"CN",
    "gn:dem":2304,
    "gn:feature_class":"P",
    "gn:feature_code":"PPL",
    "gn:name":"Kangrancun",
    "gn:population":0,
    "gn:timezone":"Asia/Urumqi",
    "iso:country":"CN",
    "name:zho_x_preferred":[
        "\u5eb7\u7136\u6751"
    ],
    "wof:name":"Kangrancun",
    "wof:placetype":"locality"
},
  "geometry": {"coordinates":[98.39051000000001,28.47837],"type":"Point"}
}