{
  "type": "Feature",
  "properties": {
    "gn:admin1_code":"32.0",
    "gn:asciiname":"Heduimen",
    "gn:country_code":"CN",
    "gn:dem":489,
    "gn:feature_class":"P",
    "gn:feature_code":"PPL",
    "gn:name":"Heduimen",
    "gn:population":0,
    "gn:timezone":"Asia/Shanghai",
    "iso:country":"CN",
    "name:zho_x_preferred":[
        "\u6cb3\u5bf9\u95e8"
    ],
    "wof:name":"Heduimen",
    "wof:placetype":"locality"
},
  "geometry": {"coordinates":[104.611,28.5199],"type":"Point"}
}