{
  "type": "Feature",
  "properties": {
    "gn:admin1_code":"32.0",
    "gn:asciiname":"Shangwudaokou",
    "gn:country_code":"CN",
    "gn:dem":435,
    "gn:feature_class":"P",
    "gn:feature_code":"PPL",
    "gn:name":"Shangwudaokou",
    "gn:population":0,
    "gn:timezone":"Asia/Shanghai",
    "iso:country":"CN",
    "name:zho_x_preferred":[
        "\u4e0a\u4e94\u9053\u53e3"
    ],
    "wof:name":"Shangwudaokou",
    "wof:placetype":"locality"
},
  "geometry": {"coordinates":[107.86081,31.46317],"type":"Point"}
}