{
  "type": "Feature",
  "properties": {
    "gn:admin1_code":"5.0",
    "gn:asciiname":"Taihecun",
    "gn:country_code":"CN",
    "gn:dem":330,
    "gn:feature_class":"P",
    "gn:feature_code":"PPL",
    "gn:name":"Taihecun",
    "gn:population":0,
    "gn:timezone":"Asia/Shanghai",
    "iso:country":"CN",
    "name:zho_x_preferred":[
        "\u592a\u6cb3\u6751"
    ],
    "wof:name":"Taihecun",
    "wof:placetype":"locality"
},
  "geometry": {"coordinates":[126.20742,42.86868],"type":"Point"}
}