{
  "type": "Feature",
  "properties": {
    "gn:admin1_code":"25",
    "gn:asciiname":"Shiliulin",
    "gn:country_code":"CN",
    "gn:dem":42,
    "gn:feature_class":"P",
    "gn:feature_code":"PPL",
    "gn:name":"Shiliulin",
    "gn:population":0,
    "gn:timezone":"Asia/Shanghai",
    "iso:country":"CN",
    "name:zho_x_preferred":[
        "\u5e08\u67f3\u6797"
    ],
    "wof:name":"Shiliulin",
    "wof:placetype":"locality"
},
  "geometry": {"coordinates":[116.35599999999999,35.8706],"type":"Point"}
}