{
  "type": "Feature",
  "properties": {
    "gn:admin1_code":"11.0",
    "gn:asciiname":"Hsiao-chai",
    "gn:country_code":"CN",
    "gn:dem":1709,
    "gn:feature_class":"P",
    "gn:feature_code":"PPL",
    "gn:name":"Hsiao-chai",
    "gn:population":0,
    "gn:timezone":"Asia/Yangon",
    "iso:country":"CN",
    "wof:name":"Hsiao-chai",
    "wof:placetype":"locality"
},
  "geometry": {"coordinates":[98.94829,23.35092],"type":"Point"}
}