{
  "type": "Feature",
  "properties": {
    "gn:admin1_code":"30",
    "gn:asciiname":"Qianjinshuxia",
    "gn:country_code":"CN",
    "gn:dem":224,
    "gn:feature_class":"P",
    "gn:feature_code":"PPL",
    "gn:name":"Qianjinshuxia",
    "gn:population":0,
    "gn:timezone":"Asia/Shanghai",
    "iso:country":"CN",
    "name:zho_x_preferred":[
        "\u5343\u91d1\u6811\u4e0b"
    ],
    "wof:name":"Qianjinshuxia",
    "wof:placetype":"locality"
},
  "geometry": {"coordinates":[115.75479,24.33506],"type":"Point"}
}