{
  "type": "Feature",
  "properties": {
    "gn:admin1_code":"19.0",
    "gn:asciiname":"Dataigou",
    "gn:country_code":"CN",
    "gn:dem":160,
    "gn:feature_class":"P",
    "gn:feature_code":"PPL",
    "gn:name":"Dataigou",
    "gn:population":0,
    "gn:timezone":"Asia/Shanghai",
    "iso:country":"CN",
    "name:und_x_variant":[
        "\u5927\u53f0\u6c9f"
    ],
    "name:zho_x_preferred":[
        "\u5927\u53f0\u6c9f"
    ],
    "wof:name":"Dataigou",
    "wof:placetype":"locality"
},
  "geometry": {"coordinates":[123.71763,41.17554000000001],"type":"Point"}
}