{
  "type": "Feature",
  "properties": {
    "gn:admin1_code":"3.0",
    "gn:asciiname":"Wangqiao",
    "gn:country_code":"CN",
    "gn:dem":62,
    "gn:feature_class":"P",
    "gn:feature_code":"PPLA4",
    "gn:name":"Wangqiao",
    "gn:population":0,
    "gn:timezone":"Asia/Shanghai",
    "iso:country":"CN",
    "name:und_x_variant":[
        "\u738b\u6865",
        "Wangqiao Zhen",
        "\u738b\u6865\u9547"
    ],
    "wof:name":"Wangqiao",
    "wof:placetype":"locality"
},
  "geometry": {"coordinates":[116.71339999999999,28.17662],"type":"Point"}
}