{
  "type": "Feature",
  "properties": {
    "gn:admin1_code":"15.0",
    "gn:asciiname":"Wenjiawan",
    "gn:country_code":"CN",
    "gn:dem":2514,
    "gn:feature_class":"P",
    "gn:feature_code":"PPL",
    "gn:name":"Wenjiawan",
    "gn:population":0,
    "gn:timezone":"Asia/Shanghai",
    "iso:country":"CN",
    "name:zho_x_preferred":[
        "\u6e29\u5bb6\u6e7e"
    ],
    "wof:name":"Wenjiawan",
    "wof:placetype":"locality"
},
  "geometry": {"coordinates":[104.84356,33.67695],"type":"Point"}
}