{
  "type": "Feature",
  "properties": {
    "gn:admin1_code":"32.0",
    "gn:asciiname":"Da'er",
    "gn:country_code":"CN",
    "gn:dem":1897,
    "gn:feature_class":"P",
    "gn:feature_code":"PPL",
    "gn:name":"Da\u2019er",
    "gn:population":0,
    "gn:timezone":"Asia/Shanghai",
    "iso:country":"CN",
    "name:und_x_variant":[
        "Da\u2019er"
    ],
    "name:zho_x_preferred":[
        "\u6253\u513f"
    ],
    "wof:name":"Da'er",
    "wof:placetype":"locality"
},
  "geometry": {"coordinates":[102.113,28.2276],"type":"Point"}
}