{
  "type": "Feature",
  "properties": {
    "iso:country":"CN",
    "name:ceb_x_preferred":[
        "Ji Xian"
    ],
    "name:ces_x_preferred":[
        "\u0164i"
    ],
    "name:cym_x_preferred":[
        "Ardal Jizhou"
    ],
    "name:deu_x_preferred":[
        "Jizhou"
    ],
    "name:eng_x_preferred":[
        "Jizhou District"
    ],
    "name:eus_x_preferred":[
        "Ji konderria"
    ],
    "name:gan_x_preferred":[
        "\u84df\u5dde\u533a"
    ],
    "name:jpn_x_preferred":[
        "\u858a\u5dde\u533a"
    ],
    "name:kor_x_preferred":[
        "\uc9c0\uc800\uc6b0\uad6c"
    ],
    "name:nan_x_preferred":[
        "K\u00e8-chiu-khu"
    ],
    "name:nld_x_preferred":[
        "Ji County"
    ],
    "name:nob_x_preferred":[
        "Ji"
    ],
    "name:rus_x_preferred":[
        "\u0426\u0437\u0438\u0447\u0436\u043e\u0443"
    ],
    "name:swe_x_preferred":[
        "Ji"
    ],
    "name:urd_x_preferred":[
        "\u062c\u06cc\u0698\u0648\u0648 \u0636\u0644\u0639"
    ],
    "name:vie_x_preferred":[
        "K\u1ebf Ch\u00e2u"
    ],
    "name:wuu_x_preferred":[
        "\u84df\u5dde\u533a"
    ],
    "name:zho_x_preferred":[
        "\u84df\u5dde\u533a"
    ],
    "qs:name":"\u84df\u53bf",
    "qs:name_adm0":"\u4e2d\u570b",
    "qs:name_adm1":"\u5929\u6d25\u76f4\u8f96\u5e02",
    "qs:photos":2,
    "qs:photos_1k":1,
    "qs:photos_9k":1,
    "qs:photos_9r":2,
    "qs:photos_all":49,
    "qs:photos_sr":1,
    "qs:placetype":"LocalAdmin",
    "qs:pop_sr":"0",
    "wd:wordcount":335,
    "wof:name":"\u84df\u53bf",
    "wof:placetype":"localadmin"
},
  "geometry": {"coordinates":[117.395095,40.036946],"type":"Point"}
}