{
  "type": "Feature",
  "properties": {
    "gn:admin1_code":"30",
    "gn:asciiname":"Beitou",
    "gn:country_code":"CN",
    "gn:dem":466,
    "gn:feature_class":"P",
    "gn:feature_code":"PPLA4",
    "gn:name":"Beitou",
    "gn:population":0,
    "gn:timezone":"Asia/Shanghai",
    "iso:country":"CN",
    "name:und_x_variant":[
        "\u9642\u5934",
        "Beitou Zhen",
        "\u9642\u5934\u9547"
    ],
    "wof:name":"Beitou",
    "wof:placetype":"locality"
},
  "geometry": {"coordinates":[114.27678,24.38651],"type":"Point"}
}