{
  "type": "Feature",
  "properties": {
    "gn:admin1_code":"29.0",
    "gn:asciiname":"Dongchuan",
    "gn:country_code":"CN",
    "gn:dem":1512,
    "gn:feature_class":"P",
    "gn:feature_code":"PPL",
    "gn:name":"Dongchuan",
    "gn:population":0,
    "gn:timezone":"Asia/Shanghai",
    "iso:country":"CN",
    "name:zho_x_preferred":[
        "\u4e1c\u5ddd"
    ],
    "wof:name":"Dongchuan",
    "wof:placetype":"locality"
},
  "geometry": {"coordinates":[101.81100000000001,23.3256],"type":"Point"}
}