{
  "type": "Feature",
  "properties": {
    "gn:admin1_code":"24.0",
    "gn:asciiname":"Wuxingzhuang",
    "gn:country_code":"CN",
    "gn:dem":520,
    "gn:feature_class":"P",
    "gn:feature_code":"PPL",
    "gn:name":"Wuxingzhuang",
    "gn:population":0,
    "gn:timezone":"Asia/Shanghai",
    "iso:country":"CN",
    "name:und_x_variant":[
        "\u5434\u5174\u5e84"
    ],
    "wof:name":"Wuxingzhuang",
    "wof:placetype":"locality"
},
  "geometry": {"coordinates":[111.22499000000001,35.78559],"type":"Point"}
}