{
  "type": "Feature",
  "properties": {
    "gn:admin1_code":"25",
    "gn:asciiname":"Qianshangzhuang",
    "gn:country_code":"CN",
    "gn:dem":187,
    "gn:feature_class":"P",
    "gn:feature_code":"PPL",
    "gn:name":"Qianshangzhuang",
    "gn:population":0,
    "gn:timezone":"Asia/Shanghai",
    "iso:country":"CN",
    "name:zho_x_preferred":[
        "\u524d\u4e0a\u5e84"
    ],
    "wof:name":"Qianshangzhuang",
    "wof:placetype":"locality"
},
  "geometry": {"coordinates":[119.02,35.7501],"type":"Point"}
}