{
  "type": "Feature",
  "properties": {
    "gn:admin1_code":"32.0",
    "gn:asciiname":"Jiejia Bazi",
    "gn:country_code":"CN",
    "gn:dem":2352,
    "gn:feature_class":"P",
    "gn:feature_code":"PPL",
    "gn:name":"Jiejia Bazi",
    "gn:population":0,
    "gn:timezone":"Asia/Shanghai",
    "iso:country":"CN",
    "name:zho_x_preferred":[
        "\u89e3\u5bb6\u575d\u5b50"
    ],
    "wof:name":"Jiejia Bazi",
    "wof:placetype":"locality"
},
  "geometry": {"coordinates":[101.49299999999999,27.4937],"type":"Point"}
}