{
  "type": "Feature",
  "properties": {
    "gn:admin1_code":"19",
    "gn:asciiname":"Yangyun",
    "gn:country_code":"CN",
    "gn:dem":77,
    "gn:feature_class":"P",
    "gn:feature_code":"PPL",
    "gn:name":"Yangyun",
    "gn:population":0,
    "gn:timezone":"Asia/Shanghai",
    "iso:country":"CN",
    "name:und_x_variant":[
        "\u6768\u8fd0",
        "Yangyunzhen",
        "\u6768\u8fd0\u9547"
    ],
    "wof:name":"Yangyun",
    "wof:placetype":"locality"
},
  "geometry": {"coordinates":[122.24269,40.10112],"type":"Point"}
}