{
  "type": "Feature",
  "properties": {
    "gn:admin1_code":"11.0",
    "gn:asciiname":"Sheweichong",
    "gn:country_code":"CN",
    "gn:dem":269,
    "gn:feature_class":"P",
    "gn:feature_code":"PPL",
    "gn:name":"Sheweichong",
    "gn:population":0,
    "gn:timezone":"Asia/Shanghai",
    "iso:country":"CN",
    "name:zho_x_preferred":[
        "\u86c7\u5c3e\u51b2"
    ],
    "wof:name":"Sheweichong",
    "wof:placetype":"locality"
},
  "geometry": {"coordinates":[109.63307,27.38777],"type":"Point"}
}