{
  "type": "Feature",
  "properties": {
    "gn:admin1_code":"5.0",
    "gn:asciiname":"Qianhuanghuacun",
    "gn:country_code":"CN",
    "gn:dem":391,
    "gn:feature_class":"P",
    "gn:feature_code":"PPL",
    "gn:name":"Qianhuanghuacun",
    "gn:population":0,
    "gn:timezone":"Asia/Shanghai",
    "iso:country":"CN",
    "name:zho_x_preferred":[
        "\u524d\u9ec4\u82b1\u6751"
    ],
    "wof:name":"Qianhuanghuacun",
    "wof:placetype":"locality"
},
  "geometry": {"coordinates":[128.3014,43.67971],"type":"Point"}
}