{
  "type": "Feature",
  "properties": {
    "gn:admin1_code":"30.0",
    "gn:asciiname":"Tatang",
    "gn:country_code":"CN",
    "gn:dem":38,
    "gn:feature_class":"P",
    "gn:feature_code":"PPL",
    "gn:name":"Tatang",
    "gn:population":0,
    "gn:timezone":"Asia/Shanghai",
    "iso:country":"CN",
    "name:zho_x_preferred":[
        "\u736d\u5858"
    ],
    "wof:name":"Tatang",
    "wof:placetype":"locality"
},
  "geometry": {"coordinates":[113.43805999999999,24.19444],"type":"Point"}
}