{
  "type": "Feature",
  "properties": {
    "gn:admin1_code":"1.0",
    "gn:asciiname":"Sunmiaocun",
    "gn:country_code":"CN",
    "gn:dem":38,
    "gn:feature_class":"P",
    "gn:feature_code":"PPL",
    "gn:name":"Sunmiaocun",
    "gn:population":0,
    "gn:timezone":"Asia/Shanghai",
    "iso:country":"CN",
    "name:zho_x_preferred":[
        "\u5b59\u5e99\u6751"
    ],
    "wof:name":"Sunmiaocun",
    "wof:placetype":"locality"
},
  "geometry": {"coordinates":[115.43389999999999,32.97809],"type":"Point"}
}