{
  "type": "Feature",
  "properties": {
    "gn:admin1_code":"12.0",
    "gn:asciiname":"Daijiachong",
    "gn:country_code":"CN",
    "gn:dem":225,
    "gn:feature_class":"P",
    "gn:feature_code":"PPL",
    "gn:name":"Daijiachong",
    "gn:population":0,
    "gn:timezone":"Asia/Shanghai",
    "iso:country":"CN",
    "name:zho_x_preferred":[
        "Daijiachong"
    ],
    "name:zho_x_variant":[
        "\u6234\u5bb6\u51b2"
    ],
    "wof:name":"Daijiachong",
    "wof:placetype":"locality"
},
  "geometry": {"coordinates":[111.63826,30.79671],"type":"Point"}
}