{
  "type": "Feature",
  "properties": {
    "gn:admin1_code":"15.0",
    "gn:asciiname":"Diwan",
    "gn:country_code":"CN",
    "gn:dem":1481,
    "gn:feature_class":"P",
    "gn:feature_code":"PPL",
    "gn:name":"Diwan",
    "gn:population":0,
    "gn:timezone":"Asia/Shanghai",
    "iso:country":"CN",
    "name:ara_x_preferred":[
        "\u062f\u064a\u0648\u0627\u0646"
    ],
    "name:cat_x_preferred":[
        "Diwan"
    ],
    "name:ceb_x_preferred":[
        "Diwan"
    ],
    "name:ckb_x_preferred":[
        "\u062f\u06cc\u0648\u0627\u0646"
    ],
    "name:deu_x_preferred":[
        "Diwan"
    ],
    "name:fas_x_preferred":[
        "\u062f\u06cc\u0648\u0627\u0646"
    ],
    "name:fra_x_preferred":[
        "Diwan"
    ],
    "name:ita_x_preferred":[
        "Diwan"
    ],
    "name:nld_x_preferred":[
        "Diwan"
    ],
    "name:pol_x_preferred":[
        "Dywan"
    ],
    "name:por_x_preferred":[
        "Div\u00e3"
    ],
    "name:swe_x_preferred":[
        "Diwan"
    ],
    "name:urd_x_preferred":[
        "\u062f\u06cc\u0648\u0627\u0646"
    ],
    "name:zho_x_preferred":[
        "\u5730\u6e7e"
    ],
    "wof:name":"Diwan",
    "wof:placetype":"locality"
},
  "geometry": {"coordinates":[102.669,38.0613],"type":"Point"}
}