{
  "type": "Feature",
  "properties": {
    "gn:admin1_code":"9.0",
    "gn:asciiname":"Dongsunlou",
    "gn:country_code":"CN",
    "gn:dem":42,
    "gn:feature_class":"P",
    "gn:feature_code":"PPL",
    "gn:name":"Dongsunlou",
    "gn:population":0,
    "gn:timezone":"Asia/Shanghai",
    "iso:country":"CN",
    "name:zho_x_preferred":[
        "\u4e1c\u5b59\u697c"
    ],
    "wof:name":"Dongsunlou",
    "wof:placetype":"locality"
},
  "geometry": {"coordinates":[115.12820000000001,33.40314],"type":"Point"}
}