{
  "type": "Feature",
  "properties": {
    "gn:admin1_code":"25",
    "gn:asciiname":"Dawan",
    "gn:country_code":"CN",
    "gn:dem":18,
    "gn:feature_class":"P",
    "gn:feature_code":"PPL",
    "gn:name":"Dawan",
    "gn:population":0,
    "gn:timezone":"Asia/Shanghai",
    "iso:country":"CN",
    "name:ceb_x_preferred":[
        "Dawan"
    ],
    "name:deu_x_preferred":[
        "Dawan"
    ],
    "name:ind_x_preferred":[
        "Dawan"
    ],
    "name:swe_x_preferred":[
        "Dawan"
    ],
    "wof:name":"Dawan",
    "wof:placetype":"locality"
},
  "geometry": {"coordinates":[117.48721999999999,37.30194],"type":"Point"}
}