{
  "type": "Feature",
  "properties": {
    "gn:admin1_code":"20.0",
    "gn:asciiname":"Halasu Sandui",
    "gn:country_code":"CN",
    "gn:dem":406,
    "gn:feature_class":"P",
    "gn:feature_code":"PPLF",
    "gn:name":"Halasu Sandui",
    "gn:population":0,
    "gn:timezone":"Asia/Shanghai",
    "iso:country":"CN",
    "name:zho_x_preferred":[
        "\u54c8\u62c9\u82cf\u4e09\u961f"
    ],
    "wof:name":"Halasu Sandui",
    "wof:placetype":"locality"
},
  "geometry": {"coordinates":[122.13148,47.63222],"type":"Point"}
}