{
  "type": "Feature",
  "properties": {
    "gn:admin1_code":"19.0",
    "gn:asciiname":"Houhaojia Wobu",
    "gn:country_code":"CN",
    "gn:dem":134,
    "gn:feature_class":"P",
    "gn:feature_code":"PPL",
    "gn:name":"Houhaojia Wobu",
    "gn:population":0,
    "gn:timezone":"Asia/Shanghai",
    "iso:country":"CN",
    "name:und_x_variant":[
        "Houhaojiawobao",
        "Houhaojia Wobu"
    ],
    "name:zho_x_preferred":[
        "\u540e\u90dd\u5bb6\u7a9d\u5821"
    ],
    "wof:name":"Houhaojia Wobu",
    "wof:placetype":"locality"
},
  "geometry": {"coordinates":[123.31399999999999,42.9781],"type":"Point"}
}