{
  "type": "Feature",
  "properties": {
    "gn:admin1_code":"4.0",
    "gn:asciiname":"Yong'ancun",
    "gn:country_code":"CN",
    "gn:dem":4,
    "gn:feature_class":"P",
    "gn:feature_code":"PPL",
    "gn:name":"Yong\u2019ancun",
    "gn:population":0,
    "gn:timezone":"Asia/Shanghai",
    "iso:country":"CN",
    "name:zho_x_preferred":[
        "Yong\u2019ancun"
    ],
    "name:zho_x_variant":[
        "\u6c38\u5b89\u6751"
    ],
    "wof:name":"Yong'ancun",
    "wof:placetype":"locality"
},
  "geometry": {"coordinates":[120.57456000000001,31.7606],"type":"Point"}
}