{
  "type": "Feature",
  "properties": {
    "gn:admin1_code":"32.0",
    "gn:asciiname":"Zengjiaqiao",
    "gn:country_code":"CN",
    "gn:dem":395,
    "gn:feature_class":"P",
    "gn:feature_code":"PPL",
    "gn:name":"Zengjiaqiao",
    "gn:population":0,
    "gn:timezone":"Asia/Shanghai",
    "iso:country":"CN",
    "name:zho_x_preferred":[
        "\u66fe\u5bb6\u6865"
    ],
    "wof:name":"Zengjiaqiao",
    "wof:placetype":"locality"
},
  "geometry": {"coordinates":[104.52034,30.01585],"type":"Point"}
}