{
  "type": "Feature",
  "properties": {
    "gn:admin1_code":"24.0",
    "gn:asciiname":"Sijiaping",
    "gn:country_code":"CN",
    "gn:dem":1256,
    "gn:feature_class":"P",
    "gn:feature_code":"PPL",
    "gn:name":"Sijiaping",
    "gn:population":0,
    "gn:timezone":"Asia/Shanghai",
    "iso:country":"CN",
    "name:zho_x_preferred":[
        "\u56db\u5bb6\u576a"
    ],
    "wof:name":"Sijiaping",
    "wof:placetype":"locality"
},
  "geometry": {"coordinates":[111.82928,38.06242],"type":"Point"}
}