{
  "type": "Feature",
  "properties": {
    "gn:admin1_code":"24.0",
    "gn:asciiname":"Qianchengdonggou",
    "gn:country_code":"CN",
    "gn:dem":1327,
    "gn:feature_class":"P",
    "gn:feature_code":"PPL",
    "gn:name":"Qianchengdonggou",
    "gn:population":0,
    "gn:timezone":"Asia/Shanghai",
    "iso:country":"CN",
    "name:zho_x_preferred":[
        "\u524d\u57ce\u4e1c\u6c9f"
    ],
    "wof:name":"Qianchengdonggou",
    "wof:placetype":"locality"
},
  "geometry": {"coordinates":[111.72991,38.02229000000001],"type":"Point"}
}