{
  "type": "Feature",
  "properties": {
    "gn:admin1_code":"5.0",
    "gn:asciiname":"Hongshicun",
    "gn:country_code":"CN",
    "gn:dem":404,
    "gn:feature_class":"P",
    "gn:feature_code":"PPL",
    "gn:name":"Hongshicun",
    "gn:population":0,
    "gn:timezone":"Asia/Shanghai",
    "iso:country":"CN",
    "name:und_x_variant":[
        "Hongshila"
    ],
    "name:zho_x_preferred":[
        "\u7ea2\u77f3\u6751"
    ],
    "wof:name":"Hongshicun",
    "wof:placetype":"locality"
},
  "geometry": {"coordinates":[125.89894,43.04695],"type":"Point"}
}