{
  "type": "Feature",
  "properties": {
    "gn:admin1_code":"16",
    "gn:asciiname":"Xiabaima",
    "gn:country_code":"CN",
    "gn:dem":165,
    "gn:feature_class":"P",
    "gn:feature_code":"PPL",
    "gn:name":"Xiabaima",
    "gn:population":0,
    "gn:timezone":"Asia/Shanghai",
    "iso:country":"CN",
    "name:zho_x_preferred":[
        "\u4e0b\u767d\u9a6c"
    ],
    "wof:name":"Xiabaima",
    "wof:placetype":"locality"
},
  "geometry": {"coordinates":[110.02,24.9381],"type":"Point"}
}