{
  "type": "Feature",
  "properties": {
    "gn:admin1_code":"20.0",
    "gn:asciiname":"Zuligeng",
    "gn:country_code":"CN",
    "gn:dem":1345,
    "gn:feature_class":"P",
    "gn:feature_code":"PPL",
    "gn:name":"Zuligeng",
    "gn:population":0,
    "gn:timezone":"Asia/Shanghai",
    "iso:country":"CN",
    "name:und_x_variant":[
        "\u8db3\u529b\u66f4"
    ],
    "wof:name":"Zuligeng",
    "wof:placetype":"locality"
},
  "geometry": {"coordinates":[113.4297,41.47549],"type":"Point"}
}