{
  "type": "Feature",
  "properties": {
    "gn:admin1_code":"8.0",
    "gn:asciiname":"Lidawan",
    "gn:country_code":"CN",
    "gn:dem":240,
    "gn:feature_class":"P",
    "gn:feature_code":"PPL",
    "gn:name":"Lidawan",
    "gn:population":0,
    "gn:timezone":"Asia/Shanghai",
    "iso:country":"CN",
    "name:zho_x_preferred":[
        "\u674e\u5927\u7897"
    ],
    "wof:name":"Lidawan",
    "wof:placetype":"locality"
},
  "geometry": {"coordinates":[126.00539999999999,47.29795],"type":"Point"}
}