{
  "type": "Feature",
  "properties": {
    "gn:admin1_code":"7",
    "gn:asciiname":"Shangxintian",
    "gn:country_code":"CN",
    "gn:dem":196,
    "gn:feature_class":"P",
    "gn:feature_code":"PPL",
    "gn:name":"Shangxintian",
    "gn:population":0,
    "gn:timezone":"Asia/Shanghai",
    "iso:country":"CN",
    "name:zho_x_preferred":[
        "\u4e0a\u65b0\u7530"
    ],
    "wof:name":"Shangxintian",
    "wof:placetype":"locality"
},
  "geometry": {"coordinates":[117.22248999999999,24.59529],"type":"Point"}
}