{
  "type": "Feature",
  "properties": {
    "gn:admin1_code":"18",
    "gn:asciiname":"Xiashatuo",
    "gn:country_code":"CN",
    "gn:dem":1683,
    "gn:feature_class":"P",
    "gn:feature_code":"PPL",
    "gn:name":"Xiashatuo",
    "gn:population":0,
    "gn:timezone":"Asia/Shanghai",
    "iso:country":"CN",
    "name:zho_x_preferred":[
        "\u4e0b\u6c99\u9640"
    ],
    "wof:name":"Xiashatuo",
    "wof:placetype":"locality"
},
  "geometry": {"coordinates":[104.426,25.7227],"type":"Point"}
}