{
  "type": "Feature",
  "properties": {
    "gn:admin1_code":"18.0",
    "gn:asciiname":"Alai",
    "gn:country_code":"CN",
    "gn:dem":1394,
    "gn:feature_class":"P",
    "gn:feature_code":"PPL",
    "gn:name":"Alai",
    "gn:population":0,
    "gn:timezone":"Asia/Shanghai",
    "iso:country":"CN",
    "name:ceb_x_preferred":[
        "Alai"
    ],
    "name:deu_x_preferred":[
        "Alai"
    ],
    "name:nld_x_preferred":[
        "Alai"
    ],
    "name:rus_x_preferred":[
        "\u0410\u043b\u0430\u0439"
    ],
    "name:spa_x_preferred":[
        "Alai"
    ],
    "name:swe_x_preferred":[
        "Alai"
    ],
    "name:ukr_x_preferred":[
        "\u0410\u043b\u0430\u0439"
    ],
    "name:zho_x_preferred":[
        "\u963f\u8d56"
    ],
    "wof:name":"Alai",
    "wof:placetype":"locality"
},
  "geometry": {"coordinates":[105.539,25.1969],"type":"Point"}
}