{
  "type": "Feature",
  "properties": {
    "gn:admin1_code":"16.0",
    "gn:asciiname":"Yanai",
    "gn:country_code":"CN",
    "gn:dem":627,
    "gn:feature_class":"P",
    "gn:feature_code":"PPL",
    "gn:name":"Yanai",
    "gn:population":0,
    "gn:timezone":"Asia/Shanghai",
    "iso:country":"CN",
    "name:ceb_x_preferred":[
        "Yanai"
    ],
    "name:deu_x_preferred":[
        "Yanai"
    ],
    "name:zho_x_preferred":[
        "\u7259\u4e43"
    ],
    "wof:name":"Yanai",
    "wof:placetype":"locality"
},
  "geometry": {"coordinates":[107.149,24.3488],"type":"Point"}
}