{
  "type": "Feature",
  "properties": {
    "gn:admin1_code":"32.0",
    "gn:asciiname":"Yugen",
    "gn:country_code":"CN",
    "gn:dem":2646,
    "gn:feature_class":"P",
    "gn:feature_code":"PPL",
    "gn:name":"Yugen",
    "gn:population":0,
    "gn:timezone":"Asia/Shanghai",
    "iso:country":"CN",
    "name:zho_x_preferred":[
        "\u9c7c\u6839"
    ],
    "wof:name":"Yugen",
    "wof:placetype":"locality"
},
  "geometry": {"coordinates":[99.2921,28.6932],"type":"Point"}
}