{
  "type": "Feature",
  "properties": {
    "gn:admin1_code":"32.0",
    "gn:asciiname":"Waha",
    "gn:country_code":"CN",
    "gn:dem":2806,
    "gn:feature_class":"P",
    "gn:feature_code":"PPL",
    "gn:name":"Waha",
    "gn:population":0,
    "gn:timezone":"Asia/Shanghai",
    "iso:country":"CN",
    "name:deu_x_preferred":[
        "Waha"
    ],
    "name:fra_x_preferred":[
        "Waha"
    ],
    "name:ltz_x_preferred":[
        "Waha"
    ],
    "name:nld_x_preferred":[
        "Waha"
    ],
    "name:rus_x_preferred":[
        "\u0412\u0430\u0430"
    ],
    "name:wln_x_preferred":[
        "Wah\u00e5"
    ],
    "name:zho_x_preferred":[
        "\u74e6\u54c8"
    ],
    "wof:name":"Waha",
    "wof:placetype":"locality"
},
  "geometry": {"coordinates":[102.57969,28.13036],"type":"Point"}
}