{
  "type": "Feature",
  "properties": {
    "gn:admin1_code":"14.0",
    "gn:asciiname":"Ma'erjin",
    "gn:country_code":"CN",
    "gn:dem":4685,
    "gn:feature_class":"P",
    "gn:feature_code":"PPL",
    "gn:name":"Ma\u2019erjin",
    "gn:population":0,
    "gn:timezone":"Asia/Urumqi",
    "iso:country":"CN",
    "name:und_x_variant":[
        "Ma\u2019erjin"
    ],
    "name:zho_x_preferred":[
        "\u739b\u5c14\u91d1"
    ],
    "wof:name":"Ma'erjin",
    "wof:placetype":"locality"
},
  "geometry": {"coordinates":[84.82089999999999,29.522],"type":"Point"}
}