{
  "type": "Feature",
  "properties": {
    "gn:admin1_code":"30.0",
    "gn:asciiname":"Xianzhoucun",
    "gn:country_code":"CN",
    "gn:dem":13,
    "gn:feature_class":"P",
    "gn:feature_code":"PPL",
    "gn:name":"Xianzhoucun",
    "gn:population":0,
    "gn:timezone":"Asia/Shanghai",
    "iso:country":"CN",
    "name:zho_x_preferred":[
        "\u4ed9\u6d32\u6751"
    ],
    "wof:name":"Xianzhoucun",
    "wof:placetype":"locality"
},
  "geometry": {"coordinates":[116.65542000000001,23.57249],"type":"Point"}
}