{
  "type": "Feature",
  "properties": {
    "gn:admin1_code":"29.0",
    "gn:asciiname":"Dadutian",
    "gn:country_code":"CN",
    "gn:dem":1518,
    "gn:feature_class":"P",
    "gn:feature_code":"PPL",
    "gn:name":"Dadutian",
    "gn:population":0,
    "gn:timezone":"Asia/Shanghai",
    "iso:country":"CN",
    "name:zho_x_preferred":[
        "\u5927\u72ec\u7530"
    ],
    "wof:name":"Dadutian",
    "wof:placetype":"locality"
},
  "geometry": {"coordinates":[100.53700000000001,23.664],"type":"Point"}
}