{
  "type": "Feature",
  "properties": {
    "gn:admin1_code":"10.0",
    "gn:asciiname":"Xiaoshankou",
    "gn:country_code":"CN",
    "gn:dem":616,
    "gn:feature_class":"P",
    "gn:feature_code":"PPL",
    "gn:name":"Xiaoshankou",
    "gn:population":0,
    "gn:timezone":"Asia/Shanghai",
    "iso:country":"CN",
    "name:zho_x_preferred":[
        "\u5c0f\u5c71\u53e3"
    ],
    "wof:name":"Xiaoshankou",
    "wof:placetype":"locality"
},
  "geometry": {"coordinates":[115.77773000000001,40.29348],"type":"Point"}
}