{
  "type": "Feature",
  "properties": {
    "gn:admin1_code":"15.0",
    "gn:asciiname":"Wujiaya",
    "gn:country_code":"CN",
    "gn:dem":1439,
    "gn:feature_class":"P",
    "gn:feature_code":"PPL",
    "gn:name":"Wujiaya",
    "gn:population":0,
    "gn:timezone":"Asia/Shanghai",
    "iso:country":"CN",
    "name:zho_x_preferred":[
        "\u5434\u5bb6\u5d16"
    ],
    "wof:name":"Wujiaya",
    "wof:placetype":"locality"
},
  "geometry": {"coordinates":[105.437,34.5361],"type":"Point"}
}