{
  "type": "Feature",
  "properties": {
    "gn:admin1_code":"30.0",
    "gn:asciiname":"Tandoushui",
    "gn:country_code":"CN",
    "gn:dem":293,
    "gn:feature_class":"P",
    "gn:feature_code":"PPL",
    "gn:name":"Tandoushui",
    "gn:population":0,
    "gn:timezone":"Asia/Shanghai",
    "iso:country":"CN",
    "name:zho_x_preferred":[
        "Tandoushui"
    ],
    "name:zho_x_variant":[
        "\u6f6d\u6597\u6c34"
    ],
    "wof:name":"Tandoushui",
    "wof:placetype":"locality"
},
  "geometry": {"coordinates":[113.14417,25.34139],"type":"Point"}
}