{
  "type": "Feature",
  "properties": {
    "gn:admin1_code":"1.0",
    "gn:asciiname":"Fanzhaicun",
    "gn:country_code":"CN",
    "gn:dem":36,
    "gn:feature_class":"P",
    "gn:feature_code":"PPL",
    "gn:name":"Fanzhaicun",
    "gn:population":0,
    "gn:timezone":"Asia/Shanghai",
    "iso:country":"CN",
    "name:zho_x_preferred":[
        "\u8303\u5be8\u6751"
    ],
    "wof:name":"Fanzhaicun",
    "wof:placetype":"locality"
},
  "geometry": {"coordinates":[115.49784,33.42457],"type":"Point"}
}