{
  "type": "Feature",
  "properties": {
    "gn:admin1_code":"12",
    "gn:asciiname":"Longtanhe",
    "gn:country_code":"CN",
    "gn:dem":239,
    "gn:feature_class":"P",
    "gn:feature_code":"PPL",
    "gn:name":"Longtanhe",
    "gn:population":0,
    "gn:timezone":"Asia/Shanghai",
    "iso:country":"CN",
    "name:und_x_variant":[
        "\u9f99\u6f6d\u6cb3"
    ],
    "wof:name":"Longtanhe",
    "wof:placetype":"locality"
},
  "geometry": {"coordinates":[111.28487,30.17105],"type":"Point"}
}