{
  "type": "Feature",
  "properties": {
    "gn:admin1_code":"25",
    "gn:asciiname":"Liuyuezhuang",
    "gn:country_code":"CN",
    "gn:dem":29,
    "gn:feature_class":"P",
    "gn:feature_code":"PPL",
    "gn:name":"Liuyuezhuang",
    "gn:population":0,
    "gn:timezone":"Asia/Shanghai",
    "iso:country":"CN",
    "name:zho_x_preferred":[
        "\u5218\u60a6\u5e84"
    ],
    "wof:name":"Liuyuezhuang",
    "wof:placetype":"locality"
},
  "geometry": {"coordinates":[116.364,36.9816],"type":"Point"}
}