{
  "type": "Feature",
  "properties": {
    "gn:admin1_code":"14.0",
    "gn:asciiname":"Zhongdong",
    "gn:country_code":"CN",
    "gn:dem":4272,
    "gn:feature_class":"P",
    "gn:feature_code":"PPL",
    "gn:name":"Zhongdong",
    "gn:population":0,
    "gn:timezone":"Asia/Urumqi",
    "iso:country":"CN",
    "name:zho_x_preferred":[
        "\u949f\u6d1e"
    ],
    "wof:name":"Zhongdong",
    "wof:placetype":"locality"
},
  "geometry": {"coordinates":[94.65627000000001,29.89059],"type":"Point"}
}