{
  "type": "Feature",
  "properties": {
    "gn:admin1_code":"3.0",
    "gn:asciiname":"Zaoheduan",
    "gn:country_code":"CN",
    "gn:dem":120,
    "gn:feature_class":"P",
    "gn:feature_code":"PPL",
    "gn:name":"Zaoheduan",
    "gn:population":0,
    "gn:timezone":"Asia/Shanghai",
    "iso:country":"CN",
    "name:und_x_variant":[
        "\u65e9\u79be\u6bb5"
    ],
    "wof:name":"Zaoheduan",
    "wof:placetype":"locality"
},
  "geometry": {"coordinates":[117.93854,29.16167],"type":"Point"}
}