{
  "type": "Feature",
  "properties": {
    "gn:admin1_code":"3.0",
    "gn:asciiname":"Fulikeng",
    "gn:country_code":"CN",
    "gn:dem":474,
    "gn:feature_class":"P",
    "gn:feature_code":"PPL",
    "gn:name":"Fulikeng",
    "gn:population":0,
    "gn:timezone":"Asia/Shanghai",
    "iso:country":"CN",
    "name:und_x_variant":[
        "\u6276\u68a8\u5751"
    ],
    "wof:name":"Fulikeng",
    "wof:placetype":"locality"
},
  "geometry": {"coordinates":[114.40863,24.56189],"type":"Point"}
}