{
  "type": "Feature",
  "properties": {
    "gn:admin1_code":"16",
    "gn:asciiname":"Jingle",
    "gn:country_code":"CN",
    "gn:dem":50,
    "gn:feature_class":"P",
    "gn:feature_code":"PPL",
    "gn:name":"Jingle",
    "gn:population":0,
    "gn:timezone":"Asia/Shanghai",
    "iso:country":"CN",
    "name:ara_x_preferred":[
        "\u062c\u0644\u062c\u0644"
    ],
    "name:bar_x_preferred":[
        "Jingle"
    ],
    "name:cat_x_preferred":[
        "Jingle"
    ],
    "name:dan_x_preferred":[
        "Jingle"
    ],
    "name:deu_x_preferred":[
        "Jingle"
    ],
    "name:fas_x_preferred":[
        "\u0632\u0646\u06af\u0648\u0644\u0647"
    ],
    "name:fin_x_preferred":[
        "Jingle"
    ],
    "name:fra_x_preferred":[
        "Jingle"
    ],
    "name:heb_x_preferred":[
        "\u05d6\u05de\u05e8\u05d9\u05e8"
    ],
    "name:jpn_x_preferred":[
        "\u30b8\u30f3\u30b0\u30eb"
    ],
    "name:nld_x_preferred":[
        "Jingle"
    ],
    "name:pol_x_preferred":[
        "D\u017cingiel"
    ],
    "name:por_x_preferred":[
        "Jingle"
    ],
    "name:rus_x_preferred":[
        "\u0414\u0436\u0438\u043d\u0433\u043b"
    ],
    "name:slv_x_preferred":[
        "Jingle"
    ],
    "name:spa_x_preferred":[
        "Jingle"
    ],
    "name:swe_x_preferred":[
        "Jingel"
    ],
    "name:tha_x_preferred":[
        "\u0e40\u0e1e\u0e25\u0e07\u0e42\u0e06\u0e29\u0e13\u0e32"
    ],
    "name:tur_x_preferred":[
        "Jingle"
    ],
    "name:ukr_x_preferred":[
        "\u0414\u0436\u0438\u043d\u0491\u043b"
    ],
    "name:zho_x_preferred":[
        "\u666f\u4e50"
    ],
    "name:zho_x_variant":[
        "Jingle"
    ],
    "wof:name":"Jingle",
    "wof:placetype":"locality"
},
  "geometry": {"coordinates":[109.92700000000001,23.1676],"type":"Point"}
}