{
  "type": "Feature",
  "properties": {
    "gn:admin1_code":"22",
    "gn:asciiname":"Lixian",
    "gn:country_code":"CN",
    "gn:dem":32,
    "gn:feature_class":"P",
    "gn:feature_code":"PPLA4",
    "gn:name":"Lixian",
    "gn:population":0,
    "gn:timezone":"Asia/Shanghai",
    "iso:country":"CN",
    "name:und_x_variant":[
        "Li-hsien-chen",
        "Li-hsien",
        "Ligzhuichzhen\u2019",
        "Lixian",
        "Lixian Zhen"
    ],
    "name:zho_x_preferred":[
        "\u793c\u8d24"
    ],
    "name:zho_x_variant":[
        "\u793c\u8d24\u9547"
    ],
    "wof:name":"Lixian",
    "wof:placetype":"locality"
},
  "geometry": {"coordinates":[116.44757,39.55625],"type":"Point"}
}