{
  "type": "Feature",
  "properties": {
    "gn:admin1_code":"29.0",
    "gn:asciiname":"Xiadawotang",
    "gn:country_code":"CN",
    "gn:dem":2244,
    "gn:feature_class":"P",
    "gn:feature_code":"PPL",
    "gn:name":"Xiadawotang",
    "gn:population":0,
    "gn:timezone":"Asia/Shanghai",
    "iso:country":"CN",
    "name:zho_x_preferred":[
        "\u4e0b\u5927\u7a9d\u5858"
    ],
    "wof:name":"Xiadawotang",
    "wof:placetype":"locality"
},
  "geometry": {"coordinates":[102.599,25.7111],"type":"Point"}
}