{
  "type": "Feature",
  "properties": {
    "gn:admin1_code":"19.0",
    "gn:asciiname":"Shahe Hougou",
    "gn:country_code":"CN",
    "gn:dem":477,
    "gn:feature_class":"P",
    "gn:feature_code":"PPL",
    "gn:name":"Shahe Hougou",
    "gn:population":0,
    "gn:timezone":"Asia/Shanghai",
    "iso:country":"CN",
    "name:zho_x_preferred":[
        "Shahe Hougou"
    ],
    "name:zho_x_variant":[
        "\u6c99\u6cb3\u540e\u6c9f"
    ],
    "wof:name":"Shahe Hougou",
    "wof:placetype":"locality"
},
  "geometry": {"coordinates":[124.93022999999999,41.98248],"type":"Point"}
}