{
  "type": "Feature",
  "properties": {
    "gn:admin1_code":"19.0",
    "gn:asciiname":"Jiehuotaicun",
    "gn:country_code":"CN",
    "gn:dem":19,
    "gn:feature_class":"P",
    "gn:feature_code":"PPL",
    "gn:name":"Jiehuotaicun",
    "gn:population":0,
    "gn:timezone":"Asia/Shanghai",
    "iso:country":"CN",
    "name:zho_x_preferred":[
        "\u63a5\u706b\u53f0\u6751"
    ],
    "wof:name":"Jiehuotaicun",
    "wof:placetype":"locality"
},
  "geometry": {"coordinates":[120.51379,40.53779],"type":"Point"}
}