{
  "type": "Feature",
  "properties": {
    "gn:admin1_code":"18",
    "gn:asciiname":"Yanshangcun",
    "gn:country_code":"CN",
    "gn:dem":1182,
    "gn:feature_class":"P",
    "gn:feature_code":"PPL",
    "gn:name":"Yanshangcun",
    "gn:population":0,
    "gn:timezone":"Asia/Shanghai",
    "iso:country":"CN",
    "name:zho_x_preferred":[
        "\u5ca9\u4e0a\u6751"
    ],
    "wof:name":"Yanshangcun",
    "wof:placetype":"locality"
},
  "geometry": {"coordinates":[105.934,25.8008],"type":"Point"}
}