{
  "type": "Feature",
  "properties": {
    "gn:admin1_code":"26.0",
    "gn:asciiname":"Sanlanggou",
    "gn:country_code":"CN",
    "gn:dem":625,
    "gn:feature_class":"P",
    "gn:feature_code":"PPL",
    "gn:name":"Sanlanggou",
    "gn:population":0,
    "gn:timezone":"Asia/Shanghai",
    "iso:country":"CN",
    "name:zho_x_preferred":[
        "\u4e09\u90ce\u6c9f"
    ],
    "wof:name":"Sanlanggou",
    "wof:placetype":"locality"
},
  "geometry": {"coordinates":[109.7118,32.71228],"type":"Point"}
}