{
  "type": "Feature",
  "properties": {
    "gn:admin1_code":"14.0",
    "gn:asciiname":"Seshacun",
    "gn:country_code":"CN",
    "gn:dem":3949,
    "gn:feature_class":"P",
    "gn:feature_code":"PPL",
    "gn:name":"Seshacun",
    "gn:population":0,
    "gn:timezone":"Asia/Urumqi",
    "iso:country":"CN",
    "name:zho_x_preferred":[
        "\u8272\u6c99\u6751"
    ],
    "wof:name":"Seshacun",
    "wof:placetype":"locality"
},
  "geometry": {"coordinates":[98.21622000000001,31.31905],"type":"Point"}
}