{
  "type": "Feature",
  "properties": {
    "gn:admin1_code":"16.0",
    "gn:asciiname":"Kuhang",
    "gn:country_code":"CN",
    "gn:dem":212,
    "gn:feature_class":"P",
    "gn:feature_code":"PPL",
    "gn:name":"Kuhang",
    "gn:population":0,
    "gn:timezone":"Asia/Shanghai",
    "iso:country":"CN",
    "name:zho_x_preferred":[
        "\u67af\u676d"
    ],
    "wof:name":"Kuhang",
    "wof:placetype":"locality"
},
  "geometry": {"coordinates":[108.76000000000001,23.6538],"type":"Point"}
}