{
  "type": "Feature",
  "properties": {
    "gn:admin1_code":"22.0",
    "gn:asciiname":"Nanliugezhuang",
    "gn:country_code":"CN",
    "gn:dem":24,
    "gn:feature_class":"P",
    "gn:feature_code":"PPL",
    "gn:name":"Nanliugezhuang",
    "gn:population":0,
    "gn:timezone":"Asia/Shanghai",
    "iso:country":"CN",
    "name:zho_x_preferred":[
        "\u5357\u5218\u5404\u5e84"
    ],
    "wof:name":"Nanliugezhuang",
    "wof:placetype":"locality"
},
  "geometry": {"coordinates":[116.75566000000001,39.88017],"type":"Point"}
}