{
  "type": "Feature",
  "properties": {
    "gn:admin1_code":"29",
    "gn:asciiname":"Tatamo",
    "gn:country_code":"CN",
    "gn:dem":1342,
    "gn:feature_class":"P",
    "gn:feature_code":"PPL",
    "gn:name":"Tatamo",
    "gn:population":0,
    "gn:timezone":"Asia/Shanghai",
    "iso:country":"CN",
    "name:zho_x_preferred":[
        "\u5b83\u4ed6\u83ab"
    ],
    "wof:name":"Tatamo",
    "wof:placetype":"locality"
},
  "geometry": {"coordinates":[102.211,23.5449],"type":"Point"}
}