{
  "type": "Feature",
  "properties": {
    "gn:admin1_code":"4.0",
    "gn:asciiname":"Xiaomaqiaocun",
    "gn:country_code":"CN",
    "gn:dem":6,
    "gn:feature_class":"P",
    "gn:feature_code":"PPL",
    "gn:name":"Xiaomaqiaocun",
    "gn:population":0,
    "gn:timezone":"Asia/Shanghai",
    "iso:country":"CN",
    "name:und_x_variant":[
        "Xiaomaqiao"
    ],
    "name:zho_x_preferred":[
        "\u5c0f\u9a6c\u6865\u6751"
    ],
    "wof:name":"Xiaomaqiaocun",
    "wof:placetype":"locality"
},
  "geometry": {"coordinates":[120.71613000000001,32.18372],"type":"Point"}
}