{
  "type": "Feature",
  "properties": {
    "gn:admin1_code":"4.0",
    "gn:asciiname":"Nanshuangqiao",
    "gn:country_code":"CN",
    "gn:dem":4,
    "gn:feature_class":"P",
    "gn:feature_code":"PPL",
    "gn:name":"Nanshuangqiao",
    "gn:population":0,
    "gn:timezone":"Asia/Shanghai",
    "iso:country":"CN",
    "name:und_x_variant":[
        "\u5357\u53cc\u6865"
    ],
    "name:zho_x_preferred":[
        "\u5357\u53cc\u6865"
    ],
    "wof:name":"Nanshuangqiao",
    "wof:placetype":"locality"
},
  "geometry": {"coordinates":[120.97685,31.57486],"type":"Point"}
}