{
  "type": "Feature",
  "properties": {
    "gn:admin1_code":"6.0",
    "gn:asciiname":"Bo'er",
    "gn:country_code":"CN",
    "gn:dem":3402,
    "gn:feature_class":"P",
    "gn:feature_code":"PPL",
    "gn:name":"Bo\u2019er",
    "gn:population":0,
    "gn:timezone":"Asia/Shanghai",
    "iso:country":"CN",
    "name:und_x_variant":[
        "Bo\u2019er"
    ],
    "name:zho_x_preferred":[
        "\u6ce2\u5c14"
    ],
    "wof:name":"Bo'er",
    "wof:placetype":"locality"
},
  "geometry": {"coordinates":[101.14165,32.68949],"type":"Point"}
}