{
  "type": "Feature",
  "properties": {
    "gn:admin1_code":"25",
    "gn:asciiname":"Nanquan",
    "gn:country_code":"CN",
    "gn:dem":249,
    "gn:feature_class":"P",
    "gn:feature_code":"PPL",
    "gn:name":"Nanquan",
    "gn:population":0,
    "gn:timezone":"Asia/Shanghai",
    "iso:country":"CN",
    "name:deu_x_preferred":[
        "Nanquan"
    ],
    "name:fas_x_preferred":[
        "\u0646\u0627\u0646\u200c\u0686\u0648\u0626\u0646"
    ],
    "name:fra_x_preferred":[
        "Nan quan"
    ],
    "name:ita_x_preferred":[
        "Nanquan"
    ],
    "name:por_x_preferred":[
        "Nan quan"
    ],
    "name:spa_x_preferred":[
        "Nanquan"
    ],
    "name:vie_x_preferred":[
        "Nam quy\u1ec1n"
    ],
    "name:zho_x_preferred":[
        "\u5357\u6cc9"
    ],
    "wof:name":"Nanquan",
    "wof:placetype":"locality"
},
  "geometry": {"coordinates":[117.26300000000001,36.5943],"type":"Point"}
}