{
  "type": "Feature",
  "properties": {
    "gn:admin1_code":"10",
    "gn:asciiname":"Gangnan",
    "gn:country_code":"CN",
    "gn:dem":162,
    "gn:feature_class":"P",
    "gn:feature_code":"PPLA4",
    "gn:name":"Gangnan",
    "gn:population":0,
    "gn:timezone":"Asia/Shanghai",
    "iso:country":"CN",
    "name:fas_x_preferred":[
        "\u06af\u0627\u0646\u06af\u0646\u0627\u0646"
    ],
    "name:und_x_variant":[
        "Kang-nan",
        "Gangnan",
        "\u5c97\u5357",
        "Gangnan Zhen"
    ],
    "name:zho_x_preferred":[
        "\u5c97\u5357\u9547"
    ],
    "wof:name":"Gangnan",
    "wof:placetype":"locality"
},
  "geometry": {"coordinates":[114.02153,38.3215],"type":"Point"}
}