{
  "type": "Feature",
  "properties": {
    "gn:admin1_code":"31",
    "gn:asciiname":"Fengmu",
    "gn:country_code":"CN",
    "gn:dem":142,
    "gn:feature_class":"P",
    "gn:feature_code":"PPLA4",
    "gn:name":"Fengmu",
    "gn:population":0,
    "gn:timezone":"Asia/Shanghai",
    "iso:country":"CN",
    "name:und_x_variant":[
        "\u67ab\u6728",
        "Fengmu Zhen",
        "\u67ab\u6728\u9547"
    ],
    "wof:name":"Fengmu",
    "wof:placetype":"locality"
},
  "geometry": {"coordinates":[110.00829,19.20933],"type":"Point"}
}