{
  "type": "Feature",
  "properties": {
    "gn:admin1_code":"4.0",
    "gn:asciiname":"Batoushen",
    "gn:country_code":"CN",
    "gn:dem":22,
    "gn:feature_class":"P",
    "gn:feature_code":"PPL",
    "gn:name":"Batoushen",
    "gn:population":0,
    "gn:timezone":"Asia/Shanghai",
    "iso:country":"CN",
    "name:zho_x_preferred":[
        "\u575d\u5934\u6c88"
    ],
    "wof:name":"Batoushen",
    "wof:placetype":"locality"
},
  "geometry": {"coordinates":[118.74748999999998,32.51788],"type":"Point"}
}