{
  "type": "Feature",
  "properties": {
    "gn:admin1_code":"14.0",
    "gn:asciiname":"Ketuocun",
    "gn:country_code":"CN",
    "gn:dem":3928,
    "gn:feature_class":"P",
    "gn:feature_code":"PPL",
    "gn:name":"Ketuocun",
    "gn:population":0,
    "gn:timezone":"Asia/Urumqi",
    "iso:country":"CN",
    "name:zho_x_preferred":[
        "\u514b\u6258\u6751"
    ],
    "wof:name":"Ketuocun",
    "wof:placetype":"locality"
},
  "geometry": {"coordinates":[95.76090000000001,31.06466],"type":"Point"}
}