{
  "type": "Feature",
  "properties": {
    "gn:admin1_code":"30",
    "gn:asciiname":"Nanlang",
    "gn:country_code":"CN",
    "gn:dem":17,
    "gn:feature_class":"P",
    "gn:feature_code":"PPLA4",
    "gn:name":"Nanlang",
    "gn:population":0,
    "gn:timezone":"Asia/Shanghai",
    "iso:country":"CN",
    "name:und_x_variant":[
        "Namlong",
        "Nan-lang-hs\u00fc",
        "Nanlang",
        "Nanlang Zhen",
        "\u5357\u6717\u9547"
    ],
    "name:zho_x_preferred":[
        "\u5357\u84e2"
    ],
    "wof:name":"Nanlang",
    "wof:placetype":"locality"
},
  "geometry": {"coordinates":[113.53736000000001,22.49171],"type":"Point"}
}