{
  "type": "Feature",
  "properties": {
    "gn:admin1_code":"11",
    "gn:asciiname":"Lubianshan",
    "gn:country_code":"CN",
    "gn:dem":199,
    "gn:feature_class":"P",
    "gn:feature_code":"PPL",
    "gn:name":"Lubianshan",
    "gn:population":0,
    "gn:timezone":"Asia/Shanghai",
    "iso:country":"CN",
    "name:zho_x_preferred":[
        "\u7089\u8fb9\u5c71"
    ],
    "wof:name":"Lubianshan",
    "wof:placetype":"locality"
},
  "geometry": {"coordinates":[111.82338,26.94811],"type":"Point"}
}