{
  "type": "Feature",
  "properties": {
    "gn:admin1_code":"19.0",
    "gn:asciiname":"Laogesanjiazi",
    "gn:country_code":"CN",
    "gn:dem":47,
    "gn:feature_class":"P",
    "gn:feature_code":"PPL",
    "gn:name":"Laogesanjiazi",
    "gn:population":0,
    "gn:timezone":"Asia/Shanghai",
    "iso:country":"CN",
    "name:zho_x_preferred":[
        "\u8001\u6208\u4e09\u5bb6\u5b50"
    ],
    "wof:name":"Laogesanjiazi",
    "wof:placetype":"locality"
},
  "geometry": {"coordinates":[123.41200000000001,42.1434],"type":"Point"}
}