{
  "type": "Feature",
  "properties": {
    "gn:admin1_code":"26.0",
    "gn:asciiname":"Yueshuya",
    "gn:country_code":"CN",
    "gn:dem":783,
    "gn:feature_class":"P",
    "gn:feature_code":"PPL",
    "gn:name":"Yueshuya",
    "gn:population":0,
    "gn:timezone":"Asia/Shanghai",
    "iso:country":"CN",
    "name:zho_x_preferred":[
        "\u6a3e\u6811\u57ad"
    ],
    "wof:name":"Yueshuya",
    "wof:placetype":"locality"
},
  "geometry": {"coordinates":[109.02715999999999,32.8026],"type":"Point"}
}