{
  "type": "Feature",
  "properties": {
    "gn:admin1_code":"30.0",
    "gn:asciiname":"Dungaocun",
    "gn:country_code":"CN",
    "gn:dem":14,
    "gn:feature_class":"P",
    "gn:feature_code":"PPL",
    "gn:name":"Dungaocun",
    "gn:population":0,
    "gn:timezone":"Asia/Shanghai",
    "iso:country":"CN",
    "name:zho_x_preferred":[
        "\u58a9\u9ad8\u6751"
    ],
    "wof:name":"Dungaocun",
    "wof:placetype":"locality"
},
  "geometry": {"coordinates":[116.28651000000001,23.03239],"type":"Point"}
}