{
  "type": "Feature",
  "properties": {
    "gn:admin1_code":"4.0",
    "gn:asciiname":"Fubaizhuang",
    "gn:country_code":"CN",
    "gn:dem":14,
    "gn:feature_class":"P",
    "gn:feature_code":"PPL",
    "gn:name":"Fubaizhuang",
    "gn:population":0,
    "gn:timezone":"Asia/Shanghai",
    "iso:country":"CN",
    "name:zho_x_preferred":[
        "\u5085\u67cf\u5e84"
    ],
    "wof:name":"Fubaizhuang",
    "wof:placetype":"locality"
},
  "geometry": {"coordinates":[118.90673,32.99704000000001],"type":"Point"}
}