{
  "type": "Feature",
  "properties": {
    "gn:admin1_code":"19.0",
    "gn:asciiname":"Dafangshen",
    "gn:country_code":"CN",
    "gn:dem":14,
    "gn:feature_class":"P",
    "gn:feature_code":"PPL",
    "gn:name":"Dafangshen",
    "gn:population":0,
    "gn:timezone":"Asia/Shanghai",
    "iso:country":"CN",
    "name:zho_x_preferred":[
        "\u5927\u623f\u8eab"
    ],
    "wof:name":"Dafangshen",
    "wof:placetype":"locality"
},
  "geometry": {"coordinates":[123.018,41.313],"type":"Point"}
}