{
  "type": "Feature",
  "properties": {
    "gn:admin1_code":"26.0",
    "gn:asciiname":"Dongyuanhe",
    "gn:country_code":"CN",
    "gn:dem":891,
    "gn:feature_class":"P",
    "gn:feature_code":"PPL",
    "gn:name":"Dongyuanhe",
    "gn:population":0,
    "gn:timezone":"Asia/Shanghai",
    "iso:country":"CN",
    "name:zho_x_preferred":[
        "\u4e1c\u586c\u6cb3"
    ],
    "wof:name":"Dongyuanhe",
    "wof:placetype":"locality"
},
  "geometry": {"coordinates":[110.27658999999998,36.88461],"type":"Point"}
}