{
  "type": "Feature",
  "properties": {
    "gn:admin1_code":"32.0",
    "gn:asciiname":"Hongsicun",
    "gn:country_code":"CN",
    "gn:dem":813,
    "gn:feature_class":"P",
    "gn:feature_code":"PPL",
    "gn:name":"Hongsicun",
    "gn:population":0,
    "gn:timezone":"Asia/Shanghai",
    "iso:country":"CN",
    "name:und_x_variant":[
        "Hongsixiang",
        "\u7ea2\u56db\u4e61"
    ],
    "name:zho_x_preferred":[
        "\u7ea2\u56db\u6751"
    ],
    "wof:name":"Hongsicun",
    "wof:placetype":"locality"
},
  "geometry": {"coordinates":[106.64861999999999,32.20973],"type":"Point"}
}