{
  "type": "Feature",
  "properties": {
    "gn:admin1_code":"11.0",
    "gn:asciiname":"Chashubei",
    "gn:country_code":"CN",
    "gn:dem":543,
    "gn:feature_class":"P",
    "gn:feature_code":"PPL",
    "gn:name":"Chashubei",
    "gn:population":0,
    "gn:timezone":"Asia/Shanghai",
    "iso:country":"CN",
    "name:zho_x_preferred":[
        "\u8336\u6811\u80cc"
    ],
    "wof:name":"Chashubei",
    "wof:placetype":"locality"
},
  "geometry": {"coordinates":[109.81241,26.77707],"type":"Point"}
}