{
  "type": "Feature",
  "properties": {
    "gn:admin1_code":"15.0",
    "gn:asciiname":"Heimaquanhe",
    "gn:country_code":"CN",
    "gn:dem":2948,
    "gn:feature_class":"P",
    "gn:feature_code":"PPL",
    "gn:name":"Heimaquanhe",
    "gn:population":0,
    "gn:timezone":"Asia/Shanghai",
    "iso:country":"CN",
    "name:zho_x_preferred":[
        "\u9ed1\u9a6c\u5708\u6cb3"
    ],
    "wof:name":"Heimaquanhe",
    "wof:placetype":"locality"
},
  "geometry": {"coordinates":[103.375,37.1643],"type":"Point"}
}