{
  "type": "Feature",
  "properties": {
    "gn:admin1_code":"30.0",
    "gn:asciiname":"Huangfengtang",
    "gn:country_code":"CN",
    "gn:dem":409,
    "gn:feature_class":"P",
    "gn:feature_code":"PPL",
    "gn:name":"Huangfengtang",
    "gn:population":0,
    "gn:timezone":"Asia/Shanghai",
    "iso:country":"CN",
    "name:zho_x_preferred":[
        "\u9ec4\u8702\u5858"
    ],
    "wof:name":"Huangfengtang",
    "wof:placetype":"locality"
},
  "geometry": {"coordinates":[112.2165,23.43722],"type":"Point"}
}