{
  "type": "Feature",
  "properties": {
    "gn:admin1_code":"7",
    "gn:asciiname":"Fuqian Nongchang",
    "gn:country_code":"CN",
    "gn:dem":244,
    "gn:feature_class":"P",
    "gn:feature_code":"PPLF",
    "gn:name":"Fuqian Nongchang",
    "gn:population":0,
    "gn:timezone":"Asia/Shanghai",
    "iso:country":"CN",
    "wof:name":"Fuqian Nongchang",
    "wof:placetype":"locality"
},
  "geometry": {"coordinates":[117.61694,25.26278],"type":"Point"}
}