{
  "type": "Feature",
  "properties": {
    "gn:admin1_code":"8.0",
    "gn:asciiname":"Hejiacun",
    "gn:country_code":"CN",
    "gn:dem":352,
    "gn:feature_class":"P",
    "gn:feature_code":"PPL",
    "gn:name":"Hejiacun",
    "gn:population":0,
    "gn:timezone":"Asia/Shanghai",
    "iso:country":"CN",
    "name:zho_x_preferred":[
        "\u79be\u5609\u6751"
    ],
    "wof:name":"Hejiacun",
    "wof:placetype":"locality"
},
  "geometry": {"coordinates":[130.40174999999999,45.29432],"type":"Point"}
}