{
  "type": "Feature",
  "properties": {
    "gn:admin1_code":"3.0",
    "gn:asciiname":"Weiqiangli",
    "gn:country_code":"CN",
    "gn:dem":95,
    "gn:feature_class":"P",
    "gn:feature_code":"PPL",
    "gn:name":"Weiqiangli",
    "gn:population":0,
    "gn:timezone":"Asia/Shanghai",
    "iso:country":"CN",
    "name:und_x_variant":[
        "\u56f4\u5899\u91cc"
    ],
    "wof:name":"Weiqiangli",
    "wof:placetype":"locality"
},
  "geometry": {"coordinates":[115.58322,27.32467],"type":"Point"}
}