{
  "type": "Feature",
  "properties": {
    "gn:admin1_code":"1.0",
    "gn:asciiname":"Tuanshancun",
    "gn:country_code":"CN",
    "gn:dem":26,
    "gn:feature_class":"P",
    "gn:feature_code":"PPL",
    "gn:name":"Tuanshancun",
    "gn:population":0,
    "gn:timezone":"Asia/Shanghai",
    "iso:country":"CN",
    "name:zho_x_preferred":[
        "\u56e2\u5c71\u6751"
    ],
    "wof:name":"Tuanshancun",
    "wof:placetype":"locality"
},
  "geometry": {"coordinates":[117.91621000000001,31.47359],"type":"Point"}
}