{
  "type": "Feature",
  "properties": {
    "gn:admin1_code":"3",
    "gn:asciiname":"Guanqiaotou",
    "gn:country_code":"CN",
    "gn:dem":235,
    "gn:feature_class":"P",
    "gn:feature_code":"PPL",
    "gn:name":"Guanqiaotou",
    "gn:population":0,
    "gn:timezone":"Asia/Shanghai",
    "iso:country":"CN",
    "name:und_x_variant":[
        "\u5b98\u6865\u5934"
    ],
    "wof:name":"Guanqiaotou",
    "wof:placetype":"locality"
},
  "geometry": {"coordinates":[116.3436,26.23616],"type":"Point"}
}