{
  "type": "Feature",
  "properties": {
    "gn:admin1_code":"14.0",
    "gn:asciiname":"Duorulega",
    "gn:country_code":"CN",
    "gn:dem":4762,
    "gn:feature_class":"P",
    "gn:feature_code":"PPL",
    "gn:name":"Duorulega",
    "gn:population":0,
    "gn:timezone":"Asia/Urumqi",
    "iso:country":"CN",
    "name:zho_x_preferred":[
        "\u591a\u5982\u52d2\u560e"
    ],
    "wof:name":"Duorulega",
    "wof:placetype":"locality"
},
  "geometry": {"coordinates":[86.5097,30.7257],"type":"Point"}
}