{
  "type": "Feature",
  "properties": {
    "gn:admin1_code":"16.0",
    "gn:asciiname":"Anle",
    "gn:country_code":"CN",
    "gn:dem":298,
    "gn:feature_class":"P",
    "gn:feature_code":"PPL",
    "gn:name":"Anle",
    "gn:population":0,
    "gn:timezone":"Asia/Shanghai",
    "iso:country":"CN",
    "name:ceb_x_preferred":[
        "Anle"
    ],
    "name:deu_x_preferred":[
        "Anle"
    ],
    "name:swe_x_preferred":[
        "Anle"
    ],
    "name:zho_x_preferred":[
        "\u5b89\u4e50"
    ],
    "wof:name":"Anle",
    "wof:placetype":"locality"
},
  "geometry": {"coordinates":[108.04900000000001,24.2879],"type":"Point"}
}