{
  "type": "Feature",
  "properties": {
    "gn:admin1_code":"19",
    "gn:asciiname":"Lijiacun",
    "gn:country_code":"CN",
    "gn:dem":19,
    "gn:feature_class":"P",
    "gn:feature_code":"PPL",
    "gn:name":"Lijiacun",
    "gn:population":0,
    "gn:timezone":"Asia/Shanghai",
    "iso:country":"CN",
    "name:und_x_variant":[
        "Li-chia",
        "Li-chia-p\u2019u-tzu",
        "Lijia",
        "\u674e\u5bb6",
        "Lijiacun"
    ],
    "name:zho_x_preferred":[
        "\u674e\u5bb6\u6751"
    ],
    "wof:name":"Lijiacun",
    "wof:placetype":"locality"
},
  "geometry": {"coordinates":[123.67198999999999,40.17832],"type":"Point"}
}