{
  "type": "Feature",
  "properties": {
    "gn:admin1_code":"12.0",
    "gn:asciiname":"Yuhuangding",
    "gn:country_code":"CN",
    "gn:dem":248,
    "gn:feature_class":"P",
    "gn:feature_code":"PPLA4",
    "gn:name":"Yuhuangding",
    "gn:population":0,
    "gn:timezone":"Asia/Shanghai",
    "iso:country":"CN",
    "name:und_x_variant":[
        "Yuhuangding Xiang"
    ],
    "name:zho_x_preferred":[
        "\u7389\u7687\u9876"
    ],
    "name:zho_x_variant":[
        "\u7389\u7687\u9876\u4e61"
    ],
    "wof:name":"Yuhuangding",
    "wof:placetype":"locality"
},
  "geometry": {"coordinates":[111.4466,32.71357],"type":"Point"}
}