{
  "type": "Feature",
  "properties": {
    "gn:admin1_code":"3",
    "gn:asciiname":"Aotou",
    "gn:country_code":"CN",
    "gn:dem":147,
    "gn:feature_class":"P",
    "gn:feature_code":"PPL",
    "gn:name":"Aotou",
    "gn:population":0,
    "gn:timezone":"Asia/Shanghai",
    "iso:country":"CN",
    "name:zho_x_preferred":[
        "\u5787\u5934"
    ],
    "wof:name":"Aotou",
    "wof:placetype":"locality"
},
  "geometry": {"coordinates":[114.81471000000001,25.88067],"type":"Point"}
}