{
  "type": "Feature",
  "properties": {
    "gn:country":"CN",
    "gn:fcode":"ADM3",
    "gn:population":0,
    "iso:country":"CN",
    "name:und_x_variant":[
        "Li-hsin Hsien"
    ],
    "name:zho_x_preferred":[
        "\u5229\u8f9b\u53bf"
    ],
    "name:zho_x_variant":[
        "\u5229\u8f9b"
    ],
    "qs:name":"Lixin Xian",
    "qs:photos_9r":0,
    "qs:photos_sr":0,
    "qs:pop_sr":"0",
    "wof:name":"Lixin Xian",
    "wof:placetype":"localadmin",
    "wof:population":0
},
  "geometry": {"coordinates":[116.16813,33.17317],"type":"Point"}
}