{
  "type": "Feature",
  "properties": {
    "gn:admin1_code":"32.0",
    "gn:asciiname":"Wayangou",
    "gn:country_code":"CN",
    "gn:dem":337,
    "gn:feature_class":"P",
    "gn:feature_code":"PPL",
    "gn:name":"Wayangou",
    "gn:population":0,
    "gn:timezone":"Asia/Shanghai",
    "iso:country":"CN",
    "name:zho_x_preferred":[
        "\u6d3c\u5ca9\u6c9f"
    ],
    "wof:name":"Wayangou",
    "wof:placetype":"locality"
},
  "geometry": {"coordinates":[106.37817,30.82418],"type":"Point"}
}