{
  "type": "Feature",
  "properties": {
    "gn:admin1_code":"3.0",
    "gn:asciiname":"Lizitang",
    "gn:country_code":"CN",
    "gn:dem":645,
    "gn:feature_class":"P",
    "gn:feature_code":"PPL",
    "gn:name":"Lizitang",
    "gn:population":0,
    "gn:timezone":"Asia/Shanghai",
    "iso:country":"CN",
    "name:und_x_variant":[
        "\u674e\u5b50\u5858"
    ],
    "wof:name":"Lizitang",
    "wof:placetype":"locality"
},
  "geometry": {"coordinates":[114.17828,28.20747],"type":"Point"}
}