{
  "type": "Feature",
  "properties": {
    "gn:admin1_code":"2.0",
    "gn:asciiname":"Nianwubang",
    "gn:country_code":"CN",
    "gn:dem":8,
    "gn:feature_class":"P",
    "gn:feature_code":"PPL",
    "gn:name":"Nianwubang",
    "gn:population":0,
    "gn:timezone":"Asia/Shanghai",
    "iso:country":"CN",
    "name:und_x_variant":[
        "\u5ff5\u4e94\u6d5c"
    ],
    "wof:name":"Nianwubang",
    "wof:placetype":"locality"
},
  "geometry": {"coordinates":[120.5791,30.55052],"type":"Point"}
}