{
  "type": "Feature",
  "properties": {
    "gn:admin1_code":"16.0",
    "gn:asciiname":"Namin",
    "gn:country_code":"CN",
    "gn:dem":284,
    "gn:feature_class":"P",
    "gn:feature_code":"PPL",
    "gn:name":"Namin",
    "gn:population":0,
    "gn:timezone":"Asia/Shanghai",
    "iso:country":"CN",
    "name:rus_x_preferred":[
        "\u041d\u0430\u043c\u0438\u043d"
    ],
    "name:zho_x_preferred":[
        "\u90a3\u654f"
    ],
    "wof:name":"Namin",
    "wof:placetype":"locality"
},
  "geometry": {"coordinates":[108.113,23.6003],"type":"Point"}
}