{
  "type": "Feature",
  "properties": {
    "gn:admin1_code":"11.0",
    "gn:asciiname":"Reshuiping",
    "gn:country_code":"CN",
    "gn:dem":184,
    "gn:feature_class":"P",
    "gn:feature_code":"PPL",
    "gn:name":"Reshuiping",
    "gn:population":0,
    "gn:timezone":"Asia/Shanghai",
    "iso:country":"CN",
    "name:zho_x_preferred":[
        "\u70ed\u6c34\u576a"
    ],
    "wof:name":"Reshuiping",
    "wof:placetype":"locality"
},
  "geometry": {"coordinates":[110.18196,28.53583],"type":"Point"}
}