{
  "type": "Feature",
  "properties": {
    "gn:admin1_code":"16.0",
    "gn:asciiname":"Huangni'ao",
    "gn:country_code":"CN",
    "gn:dem":426,
    "gn:feature_class":"P",
    "gn:feature_code":"PPL",
    "gn:name":"Huangni\u2019ao",
    "gn:population":0,
    "gn:timezone":"Asia/Shanghai",
    "iso:country":"CN",
    "name:und_x_variant":[
        "Huangni\u2019ao"
    ],
    "name:zho_x_preferred":[
        "\u9ec4\u576d\u5773"
    ],
    "wof:name":"Huangni'ao",
    "wof:placetype":"locality"
},
  "geometry": {"coordinates":[108.831,25.2324],"type":"Point"}
}