{
  "type": "Feature",
  "properties": {
    "gn:admin1_code":"23.0",
    "gn:asciiname":"Beige",
    "gn:country_code":"CN",
    "gn:dem":5,
    "gn:feature_class":"P",
    "gn:feature_code":"PPL",
    "gn:name":"Beige",
    "gn:population":0,
    "gn:timezone":"Asia/Shanghai",
    "iso:country":"CN",
    "name:zho_x_preferred":[
        "Beige"
    ],
    "name:zho_x_variant":[
        "\u5317\u845b"
    ],
    "wof:name":"Beige",
    "wof:placetype":"locality"
},
  "geometry": {"coordinates":[121.23139999999999,31.21498],"type":"Point"}
}