{
  "type": "Feature",
  "properties": {
    "gn:admin1_code":"23.0",
    "gn:asciiname":"Beige",
    "gn:country_code":"CN",
    "gn:dem":5,
    "gn:feature_class":"P",
    "gn:feature_code":"PPL",
    "gn:name":"Beige",
    "gn:population":0,
    "gn:timezone":"Asia/Shanghai",
    "iso:country":"CN",
    "name:afr_x_preferred":[
        "Beige"
    ],
    "name:ara_x_preferred":[
        "\u0628\u064a\u062c"
    ],
    "name:bel_x_preferred":[
        "\u0411\u044d\u0436"
    ],
    "name:ben_x_preferred":[
        "\u09ac\u09c7\u099c\u09c7\u09b0\u09be\u0999\u09be"
    ],
    "name:cat_x_preferred":[
        "Beix"
    ],
    "name:ces_x_preferred":[
        "B\u00e9\u017eov\u00e1"
    ],
    "name:dan_x_preferred":[
        "Beige"
    ],
    "name:eus_x_preferred":[
        "Beix"
    ],
    "name:fas_x_preferred":[
        "\u0646\u062e\u0648\u062f\u06cc"
    ],
    "name:fra_x_preferred":[
        "Beige"
    ],
    "name:heb_x_preferred":[
        "\u05d1\u05d6'"
    ],
    "name:hin_x_preferred":[
        "\u092c\u0947\u091c \u0930\u0902\u0917"
    ],
    "name:ind_x_preferred":[
        "Krem"
    ],
    "name:ita_x_preferred":[
        "Beige"
    ],
    "name:jpn_x_preferred":[
        "\u30d9\u30fc\u30b8\u30e5"
    ],
    "name:kor_x_preferred":[
        "\ubca0\uc774\uc9c0\uc0c9"
    ],
    "name:nld_x_preferred":[
        "Beige"
    ],
    "name:nno_x_preferred":[
        "Besj"
    ],
    "name:nor_x_preferred":[
        "Beige"
    ],
    "name:nso_x_preferred":[
        "Beige"
    ],
    "name:pol_x_preferred":[
        "Barwa be\u017cowa"
    ],
    "name:por_x_preferred":[
        "Bege"
    ],
    "name:rus_x_preferred":[
        "\u0411\u0435\u0436"
    ],
    "name:slk_x_preferred":[
        "B\u00e9\u017eov\u00e1"
    ],
    "name:spa_x_preferred":[
        "Beige"
    ],
    "name:srp_x_preferred":[
        "\u0411\u0435\u0436 \u0431\u043e\u0458\u0430"
    ],
    "name:swe_x_preferred":[
        "Beige"
    ],
    "name:tur_x_preferred":[
        "Bej"
    ],
    "name:ukr_x_preferred":[
        "\u0411\u0435\u0436\u0435\u0432\u0438\u0439 \u043a\u043e\u043b\u0456\u0440"
    ],
    "name:vie_x_preferred":[
        "M\u00e0u be"
    ],
    "name:yid_x_preferred":[
        "\u05d1\u05d9\u05d9\u05d6\u05e9"
    ],
    "name:zho_x_preferred":[
        "Beige"
    ],
    "name:zho_x_variant":[
        "\u5317\u845b"
    ],
    "wof:name":"Beige",
    "wof:placetype":"locality"
},
  "geometry": {"coordinates":[121.23139999999999,31.21498],"type":"Point"}
}