{
  "type": "Feature",
  "properties": {
    "gn:admin1_code":"30",
    "gn:asciiname":"Jialuocun",
    "gn:country_code":"CN",
    "gn:dem":25,
    "gn:feature_class":"P",
    "gn:feature_code":"PPL",
    "gn:name":"Jialuocun",
    "gn:population":0,
    "gn:timezone":"Asia/Urumqi",
    "iso:country":"CN",
    "name:zho_x_preferred":[
        "\u67b6\u7f57\u6751"
    ],
    "wof:name":"Jialuocun",
    "wof:placetype":"locality"
},
  "geometry": {"coordinates":[109.8732,21.26629],"type":"Point"}
}