{
  "type": "Feature",
  "properties": {
    "gn:admin1_code":"26.0",
    "gn:asciiname":"Sangshutang",
    "gn:country_code":"CN",
    "gn:dem":1321,
    "gn:feature_class":"P",
    "gn:feature_code":"PPL",
    "gn:name":"Sangshutang",
    "gn:population":0,
    "gn:timezone":"Asia/Shanghai",
    "iso:country":"CN",
    "name:zho_x_preferred":[
        "\u6851\u6811\u5802"
    ],
    "wof:name":"Sangshutang",
    "wof:placetype":"locality"
},
  "geometry": {"coordinates":[108.74321999999999,36.52569],"type":"Point"}
}