{
  "type": "Feature",
  "properties": {
    "gn:admin1_code":"15.0",
    "gn:asciiname":"Shangsifendui",
    "gn:country_code":"CN",
    "gn:dem":1251,
    "gn:feature_class":"P",
    "gn:feature_code":"PPLF",
    "gn:name":"Shangsifendui",
    "gn:population":0,
    "gn:timezone":"Asia/Shanghai",
    "iso:country":"CN",
    "name:zho_x_preferred":[
        "\u4e0a\u56db\u5206\u961f"
    ],
    "wof:name":"Shangsifendui",
    "wof:placetype":"locality"
},
  "geometry": {"coordinates":[98.7924,40.0868],"type":"Point"}
}