{
  "type": "Feature",
  "properties": {
    "gn:admin1_code":"10.0",
    "gn:asciiname":"Liangzhang",
    "gn:country_code":"CN",
    "gn:dem":8,
    "gn:feature_class":"P",
    "gn:feature_code":"PPL",
    "gn:name":"Liangzhang",
    "gn:population":0,
    "gn:timezone":"Asia/Shanghai",
    "iso:country":"CN",
    "name:zho_x_preferred":[
        "\u826f\u7ae0"
    ],
    "wof:name":"Liangzhang",
    "wof:placetype":"locality"
},
  "geometry": {"coordinates":[117.45699999999999,38.0075],"type":"Point"}
}