{
  "type": "Feature",
  "properties": {
    "gn:admin1_code":"11.0",
    "gn:asciiname":"Shanyandong",
    "gn:country_code":"CN",
    "gn:dem":1171,
    "gn:feature_class":"P",
    "gn:feature_code":"PPL",
    "gn:name":"Shanyandong",
    "gn:population":0,
    "gn:timezone":"Asia/Shanghai",
    "iso:country":"CN",
    "name:zho_x_preferred":[
        "\u5c71\u5830\u6d1e"
    ],
    "wof:name":"Shanyandong",
    "wof:placetype":"locality"
},
  "geometry": {"coordinates":[109.56010000000001,29.41898],"type":"Point"}
}