{
  "type": "Feature",
  "properties": {
    "gn:admin1_code":"21",
    "gn:asciiname":"Baquan",
    "gn:country_code":"CN",
    "gn:dem":1353,
    "gn:feature_class":"P",
    "gn:feature_code":"PPL",
    "gn:name":"Baquan",
    "gn:population":0,
    "gn:timezone":"Asia/Shanghai",
    "iso:country":"CN",
    "name:zho_x_preferred":[
        "\u5df4\u6cc9"
    ],
    "wof:name":"Baquan",
    "wof:placetype":"locality"
},
  "geometry": {"coordinates":[106.14100000000001,37.514],"type":"Point"}
}