{
  "type": "Feature",
  "properties": {
    "gn:admin1_code":"15.0",
    "gn:asciiname":"Xiaocha",
    "gn:country_code":"CN",
    "gn:dem":2336,
    "gn:feature_class":"P",
    "gn:feature_code":"PPL",
    "gn:name":"Xiaocha",
    "gn:population":0,
    "gn:timezone":"Asia/Shanghai",
    "iso:country":"CN",
    "name:zho_x_preferred":[
        "\u5c0f\u5c94"
    ],
    "wof:name":"Xiaocha",
    "wof:placetype":"locality"
},
  "geometry": {"coordinates":[104.43600000000001,36.2565],"type":"Point"}
}