{
  "type": "Feature",
  "properties": {
    "gn:admin1_code":"32.0",
    "gn:asciiname":"Changtanba",
    "gn:country_code":"CN",
    "gn:dem":360,
    "gn:feature_class":"P",
    "gn:feature_code":"PPL",
    "gn:name":"Changtanba",
    "gn:population":0,
    "gn:timezone":"Asia/Shanghai",
    "iso:country":"CN",
    "name:zho_x_preferred":[
        "\u957f\u6ee9\u575d"
    ],
    "wof:name":"Changtanba",
    "wof:placetype":"locality"
},
  "geometry": {"coordinates":[105.88800000000001,30.8786],"type":"Point"}
}