{
  "type": "Feature",
  "properties": {
    "gn:admin1_code":"12.0",
    "gn:asciiname":"Qixingshu",
    "gn:country_code":"CN",
    "gn:dem":812,
    "gn:feature_class":"P",
    "gn:feature_code":"PPL",
    "gn:name":"Qixingshu",
    "gn:population":0,
    "gn:timezone":"Asia/Shanghai",
    "iso:country":"CN",
    "name:zho_x_preferred":[
        "\u4e03\u661f\u6811"
    ],
    "wof:name":"Qixingshu",
    "wof:placetype":"locality"
},
  "geometry": {"coordinates":[111.00700999999999,32.41476],"type":"Point"}
}