{
  "type": "Feature",
  "properties": {
    "gn:admin1_code":"30.0",
    "gn:asciiname":"Laomashan",
    "gn:country_code":"CN",
    "gn:dem":358,
    "gn:feature_class":"P",
    "gn:feature_code":"PPL",
    "gn:name":"Laomashan",
    "gn:population":0,
    "gn:timezone":"Asia/Shanghai",
    "iso:country":"CN",
    "name:zho_x_preferred":[
        "\u8001\u9a6c\u5c71"
    ],
    "wof:name":"Laomashan",
    "wof:placetype":"locality"
},
  "geometry": {"coordinates":[115.0534,24.03318],"type":"Point"}
}