{
  "type": "Feature",
  "properties": {
    "gn:admin1_code":"30.0",
    "gn:asciiname":"Yangzishan",
    "gn:country_code":"CN",
    "gn:dem":582,
    "gn:feature_class":"P",
    "gn:feature_code":"PPL",
    "gn:name":"Yangzishan",
    "gn:population":0,
    "gn:timezone":"Asia/Shanghai",
    "iso:country":"CN",
    "name:zho_x_preferred":[
        "Yangzishan"
    ],
    "name:zho_x_variant":[
        "\u7f8a\u5b50\u5c71"
    ],
    "wof:name":"Yangzishan",
    "wof:placetype":"locality"
},
  "geometry": {"coordinates":[112.53167000000001,24.67389],"type":"Point"}
}