{
  "type": "Feature",
  "properties": {
    "gn:admin1_code":"2.0",
    "gn:asciiname":"Qianhouchen",
    "gn:country_code":"CN",
    "gn:dem":7,
    "gn:feature_class":"P",
    "gn:feature_code":"PPL",
    "gn:name":"Qianhouchen",
    "gn:population":0,
    "gn:timezone":"Asia/Shanghai",
    "iso:country":"CN",
    "name:zho_x_preferred":[
        "\u524d\u540e\u9648"
    ],
    "wof:name":"Qianhouchen",
    "wof:placetype":"locality"
},
  "geometry": {"coordinates":[121.59021,29.786],"type":"Point"}
}