{
  "type": "Feature",
  "properties": {
    "gn:admin1_code":"10.0",
    "gn:asciiname":"Laoyangquan",
    "gn:country_code":"CN",
    "gn:dem":786,
    "gn:feature_class":"P",
    "gn:feature_code":"PPL",
    "gn:name":"Laoyangquan",
    "gn:population":0,
    "gn:timezone":"Asia/Shanghai",
    "iso:country":"CN",
    "name:zho_x_preferred":[
        "\u8001\u7f8a\u5708"
    ],
    "wof:name":"Laoyangquan",
    "wof:placetype":"locality"
},
  "geometry": {"coordinates":[114.30681,39.04744],"type":"Point"}
}