{
  "type": "Feature",
  "properties": {
    "gn:admin1_code":"11.0",
    "gn:asciiname":"Shangbaishaping",
    "gn:country_code":"CN",
    "gn:dem":976,
    "gn:feature_class":"P",
    "gn:feature_code":"PPL",
    "gn:name":"Shangbaishaping",
    "gn:population":0,
    "gn:timezone":"Asia/Shanghai",
    "iso:country":"CN",
    "name:zho_x_preferred":[
        "\u4e0a\u767d\u6c99\u576a"
    ],
    "wof:name":"Shangbaishaping",
    "wof:placetype":"locality"
},
  "geometry": {"coordinates":[110.95542,27.75753],"type":"Point"}
}