{
  "type": "Feature",
  "properties": {
    "gn:admin1_code":"24.0",
    "gn:asciiname":"Xijinjiawa",
    "gn:country_code":"CN",
    "gn:dem":1039,
    "gn:feature_class":"P",
    "gn:feature_code":"PPL",
    "gn:name":"Xijinjiawa",
    "gn:population":0,
    "gn:timezone":"Asia/Shanghai",
    "iso:country":"CN",
    "name:zho_x_preferred":[
        "\u897f\u9773\u5bb6\u6d3c"
    ],
    "wof:name":"Xijinjiawa",
    "wof:placetype":"locality"
},
  "geometry": {"coordinates":[113.92904,40.12531],"type":"Point"}
}