{
  "type": "Feature",
  "properties": {
    "gn:admin1_code":"9.0",
    "gn:asciiname":"Kongzhuang",
    "gn:country_code":"CN",
    "gn:dem":126,
    "gn:feature_class":"P",
    "gn:feature_code":"PPL",
    "gn:name":"Kongzhuang",
    "gn:population":0,
    "gn:timezone":"Asia/Shanghai",
    "iso:country":"CN",
    "name:und_x_variant":[
        "\u5b54\u5e84",
        "Kongzhuang"
    ],
    "wof:name":"Kongzhuang",
    "wof:placetype":"locality"
},
  "geometry": {"coordinates":[112.89489,33.01892],"type":"Point"}
}