{
  "type": "Feature",
  "properties": {
    "gn:admin1_code":"15.0",
    "gn:asciiname":"Changgu",
    "gn:country_code":"CN",
    "gn:dem":1836,
    "gn:feature_class":"P",
    "gn:feature_code":"PPL",
    "gn:name":"Changgu",
    "gn:population":0,
    "gn:timezone":"Asia/Shanghai",
    "iso:country":"CN",
    "name:und_x_variant":[
        "\u660c\u8c37"
    ],
    "wof:name":"Changgu",
    "wof:placetype":"locality"
},
  "geometry": {"coordinates":[104.58714000000001,34.98573],"type":"Point"}
}