{
  "type": "Feature",
  "properties": {
    "gn:admin1_code":"11.0",
    "gn:asciiname":"Malongxi",
    "gn:country_code":"CN",
    "gn:dem":447,
    "gn:feature_class":"P",
    "gn:feature_code":"PPL",
    "gn:name":"Malongxi",
    "gn:population":0,
    "gn:timezone":"Asia/Shanghai",
    "iso:country":"CN",
    "name:zho_x_preferred":[
        "\u9a6c\u9f99\u6eaa"
    ],
    "wof:name":"Malongxi",
    "wof:placetype":"locality"
},
  "geometry": {"coordinates":[109.99701,29.34832],"type":"Point"}
}