{
  "type": "Feature",
  "properties": {
    "gn:admin1_code":"31.0",
    "gn:asciiname":"Shuiweichao",
    "gn:country_code":"CN",
    "gn:dem":30,
    "gn:feature_class":"P",
    "gn:feature_code":"PPL",
    "gn:name":"Shuiweichao",
    "gn:population":0,
    "gn:timezone":"Asia/Shanghai",
    "iso:country":"CN",
    "name:zho_x_preferred":[
        "\u6c34\u5c3e\u6f6e"
    ],
    "wof:name":"Shuiweichao",
    "wof:placetype":"locality"
},
  "geometry": {"coordinates":[110.37245,18.94529],"type":"Point"}
}