{
  "type": "Feature",
  "properties": {
    "gn:admin1_code":"02",
    "gn:asciiname":"Chang'anqiaocun",
    "gn:country_code":"CN",
    "gn:dem":6,
    "gn:feature_class":"P",
    "gn:feature_code":"PPL",
    "gn:name":"Chang\u2019anqiaocun",
    "gn:population":0,
    "gn:timezone":"Asia/Shanghai",
    "iso:country":"CN",
    "name:und_x_variant":[
        "Ch\u2019ang-an-ch\u2019iao",
        "Chang\u2019anqiao",
        "\u957f\u5b89\u6865",
        "Chang\u2019anqiaocun"
    ],
    "name:zho_x_preferred":[
        "\u957f\u5b89\u6865\u6751"
    ],
    "wof:name":"Chang'anqiaocun",
    "wof:placetype":"locality"
},
  "geometry": {"coordinates":[121.13831,30.63099],"type":"Point"}
}