{
  "type": "Feature",
  "properties": {
    "gn:admin1_code":"24.0",
    "gn:asciiname":"Jiangtaibei",
    "gn:country_code":"CN",
    "gn:dem":1797,
    "gn:feature_class":"P",
    "gn:feature_code":"PPL",
    "gn:name":"Jiangtaibei",
    "gn:population":0,
    "gn:timezone":"Asia/Shanghai",
    "iso:country":"CN",
    "name:und_x_variant":[
        "\u5c06\u53f0\u80cc"
    ],
    "wof:name":"Jiangtaibei",
    "wof:placetype":"locality"
},
  "geometry": {"coordinates":[113.41835,39.34689],"type":"Point"}
}