{
  "type": "Feature",
  "properties": {
    "gn:admin1_code":"9.0",
    "gn:asciiname":"Suoxiakou",
    "gn:country_code":"CN",
    "gn:dem":102,
    "gn:feature_class":"P",
    "gn:feature_code":"PPL",
    "gn:name":"Suoxiakou",
    "gn:population":0,
    "gn:timezone":"Asia/Shanghai",
    "iso:country":"CN",
    "name:zho_x_preferred":[
        "\u7d22\u4e0b\u6263"
    ],
    "wof:name":"Suoxiakou",
    "wof:placetype":"locality"
},
  "geometry": {"coordinates":[114.29695,35.8676],"type":"Point"}
}