{
  "type": "Feature",
  "properties": {
    "gn:admin1_code":"19.0",
    "gn:asciiname":"Dongyangcao",
    "gn:country_code":"CN",
    "gn:dem":94,
    "gn:feature_class":"P",
    "gn:feature_code":"PPL",
    "gn:name":"Dongyangcao",
    "gn:population":0,
    "gn:timezone":"Asia/Shanghai",
    "iso:country":"CN",
    "name:zho_x_preferred":[
        "\u4e1c\u7f8a\u8349"
    ],
    "wof:name":"Dongyangcao",
    "wof:placetype":"locality"
},
  "geometry": {"coordinates":[120.62071,40.76438],"type":"Point"}
}