{
  "type": "Feature",
  "properties": {
    "gn:admin1_code":"16",
    "gn:asciiname":"Longkou",
    "gn:country_code":"CN",
    "gn:dem":171,
    "gn:feature_class":"P",
    "gn:feature_code":"PPL",
    "gn:name":"Longkou",
    "gn:population":0,
    "gn:timezone":"Asia/Shanghai",
    "iso:country":"CN",
    "name:deu_x_preferred":[
        "Longkou"
    ],
    "name:fin_x_preferred":[
        "Longkou"
    ],
    "name:fra_x_preferred":[
        "Longkou"
    ],
    "name:ita_x_preferred":[
        "Longkou"
    ],
    "name:jpn_x_preferred":[
        "\u7adc\u53e3\u5e02"
    ],
    "name:kik_x_preferred":[
        "Longkou"
    ],
    "name:kor_x_preferred":[
        "\ub8fd\ucee4\uc6b0\uc2dc"
    ],
    "name:nor_x_preferred":[
        "Longkou"
    ],
    "name:rus_x_preferred":[
        "\u041b\u0443\u043d\u043a\u043e\u0443"
    ],
    "name:swe_x_preferred":[
        "Longkou"
    ],
    "name:urd_x_preferred":[
        "\u0644\u0648\u0646\u06af\u06a9\u0648\u0648"
    ],
    "name:vie_x_preferred":[
        "Long Kh\u1ea9u"
    ],
    "name:war_x_preferred":[
        "Longkou"
    ],
    "name:zho_x_preferred":[
        "\u9f99\u53e3"
    ],
    "name:zho_x_variant":[
        "\u9f99\u53e3\u5e02"
    ],
    "wof:name":"Longkou",
    "wof:placetype":"locality"
},
  "geometry": {"coordinates":[107.964,23.6737],"type":"Point"}
}