{
  "type": "Feature",
  "properties": {
    "gn:admin1_code":"10",
    "gn:asciiname":"Beixintun",
    "gn:country_code":"CN",
    "gn:dem":1070,
    "gn:feature_class":"P",
    "gn:feature_code":"PPL",
    "gn:name":"Beixintun",
    "gn:population":0,
    "gn:timezone":"Asia/Shanghai",
    "iso:country":"CN",
    "name:und_x_variant":[
        "Pei-hsin-t\u2019un",
        "Beixintun"
    ],
    "name:zho_x_preferred":[
        "\u5317\u65b0\u5c6f"
    ],
    "wof:name":"Beixintun",
    "wof:placetype":"locality"
},
  "geometry": {"coordinates":[114.62966000000002,40.89404],"type":"Point"}
}