{
  "type": "Feature",
  "properties": {
    "gn:admin1_code":"32.0",
    "gn:asciiname":"Zhangyagou",
    "gn:country_code":"CN",
    "gn:dem":2680,
    "gn:feature_class":"P",
    "gn:feature_code":"PPL",
    "gn:name":"Zhangyagou",
    "gn:population":0,
    "gn:timezone":"Asia/Shanghai",
    "iso:country":"CN",
    "name:zho_x_preferred":[
        "\u5f20\u7259\u6c9f"
    ],
    "wof:name":"Zhangyagou",
    "wof:placetype":"locality"
},
  "geometry": {"coordinates":[101.20999999999999,28.9143],"type":"Point"}
}