{
  "type": "Feature",
  "properties": {
    "gn:admin1_code":"26.0",
    "gn:asciiname":"Weizitan",
    "gn:country_code":"CN",
    "gn:dem":1511,
    "gn:feature_class":"P",
    "gn:feature_code":"PPL",
    "gn:name":"Weizitan",
    "gn:population":0,
    "gn:timezone":"Asia/Shanghai",
    "iso:country":"CN",
    "name:und_x_variant":[
        "\u82c7\u5b50\u6ee9"
    ],
    "wof:name":"Weizitan",
    "wof:placetype":"locality"
},
  "geometry": {"coordinates":[106.94841,34.07583],"type":"Point"}
}