{
  "type": "Feature",
  "properties": {
    "gn:admin1_code":"2.0",
    "gn:asciiname":"Yinlingkeng",
    "gn:country_code":"CN",
    "gn:dem":345,
    "gn:feature_class":"P",
    "gn:feature_code":"PPL",
    "gn:name":"Yinlingkeng",
    "gn:population":0,
    "gn:timezone":"Asia/Shanghai",
    "iso:country":"CN",
    "name:zho_x_preferred":[
        "\u9634\u5cad\u5751"
    ],
    "wof:name":"Yinlingkeng",
    "wof:placetype":"locality"
},
  "geometry": {"coordinates":[119.02207,28.62498],"type":"Point"}
}