{
  "type": "Feature",
  "properties": {
    "gn:admin1_code":"30",
    "gn:asciiname":"Yuliangkeng",
    "gn:country_code":"CN",
    "gn:dem":97,
    "gn:feature_class":"P",
    "gn:feature_code":"PPL",
    "gn:name":"Yuliangkeng",
    "gn:population":0,
    "gn:timezone":"Asia/Shanghai",
    "iso:country":"CN",
    "name:zho_x_preferred":[
        "\u9c7c\u6881\u5751"
    ],
    "wof:name":"Yuliangkeng",
    "wof:placetype":"locality"
},
  "geometry": {"coordinates":[111.82546000000001,22.59275],"type":"Point"}
}