{
  "type": "Feature",
  "properties": {
    "gn:admin1_code":"26.0",
    "gn:asciiname":"Bachengcun",
    "gn:country_code":"CN",
    "gn:dem":351,
    "gn:feature_class":"P",
    "gn:feature_code":"PPL",
    "gn:name":"Bachengcun",
    "gn:population":0,
    "gn:timezone":"Asia/Shanghai",
    "iso:country":"CN",
    "name:und_x_variant":[
        "\u9738\u57ce\u6751"
    ],
    "wof:name":"Bachengcun",
    "wof:placetype":"locality"
},
  "geometry": {"coordinates":[110.00475,34.7532],"type":"Point"}
}