{
  "type": "Feature",
  "properties": {
    "gn:admin1_code":"4.0",
    "gn:asciiname":"Tuanjie",
    "gn:country_code":"CN",
    "gn:dem":18,
    "gn:feature_class":"P",
    "gn:feature_code":"PPL",
    "gn:name":"Tuanjie",
    "gn:population":0,
    "gn:timezone":"Asia/Shanghai",
    "iso:country":"CN",
    "name:zho_x_preferred":[
        "\u56e2\u7ed3"
    ],
    "wof:name":"Tuanjie",
    "wof:placetype":"locality"
},
  "geometry": {"coordinates":[119.36835000000001,31.92602],"type":"Point"}
}