{
  "type": "Feature",
  "properties": {
    "gn:admin1_code":"10",
    "gn:asciiname":"Tangshugou",
    "gn:country_code":"CN",
    "gn:dem":761,
    "gn:feature_class":"P",
    "gn:feature_code":"PPL",
    "gn:name":"Tangshugou",
    "gn:population":0,
    "gn:timezone":"Asia/Shanghai",
    "iso:country":"CN",
    "name:zho_x_preferred":[
        "\u68e0\u6811\u6c9f"
    ],
    "wof:name":"Tangshugou",
    "wof:placetype":"locality"
},
  "geometry": {"coordinates":[116.58241,41.23501],"type":"Point"}
}