{
  "type": "Feature",
  "properties": {
    "gn:admin1_code":"15.0",
    "gn:asciiname":"Mazuizi",
    "gn:country_code":"CN",
    "gn:dem":1318,
    "gn:feature_class":"P",
    "gn:feature_code":"PPL",
    "gn:name":"Mazuizi",
    "gn:population":0,
    "gn:timezone":"Asia/Shanghai",
    "iso:country":"CN",
    "name:und_x_variant":[
        "\u9a6c\u5480\u5b50"
    ],
    "wof:name":"Mazuizi",
    "wof:placetype":"locality"
},
  "geometry": {"coordinates":[107.86471,36.59519],"type":"Point"}
}