{
  "type": "Feature",
  "properties": {
    "gn:admin1_code":"29.0",
    "gn:asciiname":"Maziqing",
    "gn:country_code":"CN",
    "gn:dem":2006,
    "gn:feature_class":"P",
    "gn:feature_code":"PPL",
    "gn:name":"Maziqing",
    "gn:population":0,
    "gn:timezone":"Asia/Shanghai",
    "iso:country":"CN",
    "name:zho_x_preferred":[
        "\u9a6c\u8d44\u7b90"
    ],
    "wof:name":"Maziqing",
    "wof:placetype":"locality"
},
  "geometry": {"coordinates":[102.613,25.699],"type":"Point"}
}