{
  "type": "Feature",
  "properties": {
    "gn:admin1_code":"4.0",
    "gn:asciiname":"Wangpinshe",
    "gn:country_code":"CN",
    "gn:dem":-1,
    "gn:feature_class":"P",
    "gn:feature_code":"PPL",
    "gn:name":"Wangpinshe",
    "gn:population":0,
    "gn:timezone":"Asia/Shanghai",
    "iso:country":"CN",
    "name:zho_x_preferred":[
        "Wangpinshe"
    ],
    "name:zho_x_variant":[
        "\u738b\u54c1\u793e"
    ],
    "wof:name":"Wangpinshe",
    "wof:placetype":"locality"
},
  "geometry": {"coordinates":[119.44204999999999,33.25784],"type":"Point"}
}