{
  "type": "Feature",
  "properties": {
    "gn:admin1_code":"30",
    "gn:asciiname":"Tanbu",
    "gn:country_code":"CN",
    "gn:dem":347,
    "gn:feature_class":"P",
    "gn:feature_code":"PPLA4",
    "gn:name":"Tanbu",
    "gn:population":0,
    "gn:timezone":"Asia/Shanghai",
    "iso:country":"CN",
    "name:fas_x_preferred":[
        "\u062a\u0646\u0628\u0648"
    ],
    "name:msa_x_preferred":[
        "Tanbu"
    ],
    "name:ukr_x_preferred":[
        "\u0422\u0430\u043d\u0431\u0443"
    ],
    "name:und_x_variant":[
        "Tanbu Zhen",
        "\u6f6d\u5e03\u9547"
    ],
    "name:zho_x_preferred":[
        "\u6f6d\u5e03"
    ],
    "wof:name":"Tanbu",
    "wof:placetype":"locality"
},
  "geometry": {"coordinates":[112.55979000000001,23.62306],"type":"Point"}
}