{
  "type": "Feature",
  "properties": {
    "gn:admin1_code":"9.0",
    "gn:asciiname":"Jinjiahe",
    "gn:country_code":"CN",
    "gn:dem":744,
    "gn:feature_class":"P",
    "gn:feature_code":"PPL",
    "gn:name":"Jinjiahe",
    "gn:population":0,
    "gn:timezone":"Asia/Shanghai",
    "iso:country":"CN",
    "name:zho_x_preferred":[
        "\u664b\u5bb6\u6cb3"
    ],
    "wof:name":"Jinjiahe",
    "wof:placetype":"locality"
},
  "geometry": {"coordinates":[110.68947,34.26585],"type":"Point"}
}