{
  "type": "Feature",
  "properties": {
    "gn:admin1_code":"14.0",
    "gn:asciiname":"Yongnong",
    "gn:country_code":"CN",
    "gn:dem":4413,
    "gn:feature_class":"P",
    "gn:feature_code":"PPL",
    "gn:name":"Yongnong",
    "gn:population":0,
    "gn:timezone":"Asia/Urumqi",
    "iso:country":"CN",
    "name:zho_x_preferred":[
        "\u7528\u5f04"
    ],
    "wof:name":"Yongnong",
    "wof:placetype":"locality"
},
  "geometry": {"coordinates":[94.35004000000001,31.0754],"type":"Point"}
}