{
  "type": "Feature",
  "properties": {
    "gn:admin1_code":"26.0",
    "gn:asciiname":"Zhaoyaokuo",
    "gn:country_code":"CN",
    "gn:dem":1107,
    "gn:feature_class":"P",
    "gn:feature_code":"PPL",
    "gn:name":"Zhaoyaokuo",
    "gn:population":0,
    "gn:timezone":"Asia/Shanghai",
    "iso:country":"CN",
    "name:zho_x_preferred":[
        "\u8d75\u7a91\u5ed3"
    ],
    "wof:name":"Zhaoyaokuo",
    "wof:placetype":"locality"
},
  "geometry": {"coordinates":[109.28686,35.40659],"type":"Point"}
}