{
  "type": "Feature",
  "properties": {
    "gn:admin1_code":"10",
    "gn:asciiname":"Xiaomaotougou",
    "gn:country_code":"CN",
    "gn:dem":779,
    "gn:feature_class":"P",
    "gn:feature_code":"PPL",
    "gn:name":"Xiaomaotougou",
    "gn:population":0,
    "gn:timezone":"Asia/Shanghai",
    "iso:country":"CN",
    "name:zho_x_preferred":[
        "\u5c0f\u6bdb\u5934\u6c9f"
    ],
    "wof:name":"Xiaomaotougou",
    "wof:placetype":"locality"
},
  "geometry": {"coordinates":[117.63184,41.58855],"type":"Point"}
}