{
  "type": "Feature",
  "properties": {
    "gn:admin1_code":"15.0",
    "gn:asciiname":"Maying",
    "gn:country_code":"CN",
    "gn:dem":1422,
    "gn:feature_class":"P",
    "gn:feature_code":"PPL",
    "gn:name":"Maying",
    "gn:population":0,
    "gn:timezone":"Asia/Shanghai",
    "iso:country":"CN",
    "name:deu_x_preferred":[
        "Maying"
    ],
    "name:zho_x_preferred":[
        "\u9a6c\u8425"
    ],
    "wof:name":"Maying",
    "wof:placetype":"locality"
},
  "geometry": {"coordinates":[100.148,39.2065],"type":"Point"}
}