{
  "type": "Feature",
  "properties": {
    "gn:admin1_code":"4.0",
    "gn:asciiname":"Yangli",
    "gn:country_code":"CN",
    "gn:dem":4,
    "gn:feature_class":"P",
    "gn:feature_code":"PPL",
    "gn:name":"Yangli",
    "gn:population":0,
    "gn:timezone":"Asia/Shanghai",
    "iso:country":"CN",
    "name:zho_x_preferred":[
        "Yangli"
    ],
    "name:zho_x_variant":[
        "\u6768\u674e"
    ],
    "wof:name":"Yangli",
    "wof:placetype":"locality"
},
  "geometry": {"coordinates":[119.29425000000001,34.13093],"type":"Point"}
}