{
  "type": "Feature",
  "properties": {
    "gn:admin1_code":"31",
    "gn:asciiname":"Wanchong",
    "gn:country_code":"CN",
    "gn:dem":180,
    "gn:feature_class":"P",
    "gn:feature_code":"PPLA4",
    "gn:name":"Wanchong",
    "gn:population":0,
    "gn:timezone":"Asia/Shanghai",
    "iso:country":"CN",
    "name:und_x_variant":[
        "\u4e07\u51b2",
        "Wanchong Zhen",
        "\u4e07\u51b2\u9547"
    ],
    "wof:name":"Wanchong",
    "wof:placetype":"locality"
},
  "geometry": {"coordinates":[109.31708,18.84864],"type":"Point"}
}