{
  "type": "Feature",
  "properties": {
    "gn:admin1_code":"29.0",
    "gn:asciiname":"Honggang",
    "gn:country_code":"CN",
    "gn:dem":1864,
    "gn:feature_class":"P",
    "gn:feature_code":"PPL",
    "gn:name":"Honggang",
    "gn:population":0,
    "gn:timezone":"Asia/Shanghai",
    "iso:country":"CN",
    "name:zho_x_preferred":[
        "\u7ea2\u5c97"
    ],
    "wof:name":"Honggang",
    "wof:placetype":"locality"
},
  "geometry": {"coordinates":[99.8104,24.1555],"type":"Point"}
}