{
  "type": "Feature",
  "properties": {
    "gn:admin1_code":"25",
    "gn:asciiname":"Wancangzhuang",
    "gn:country_code":"CN",
    "gn:dem":114,
    "gn:feature_class":"P",
    "gn:feature_code":"PPL",
    "gn:name":"Wancangzhuang",
    "gn:population":0,
    "gn:timezone":"Asia/Shanghai",
    "iso:country":"CN",
    "name:zho_x_preferred":[
        "\u4e07\u4ed3\u5e84"
    ],
    "wof:name":"Wancangzhuang",
    "wof:placetype":"locality"
},
  "geometry": {"coordinates":[117.923,35.3717],"type":"Point"}
}