{
  "type": "Feature",
  "properties": {
    "gn:admin1_code":"9.0",
    "gn:asciiname":"Houkeng",
    "gn:country_code":"CN",
    "gn:dem":893,
    "gn:feature_class":"P",
    "gn:feature_code":"PPL",
    "gn:name":"Houkeng",
    "gn:population":0,
    "gn:timezone":"Asia/Shanghai",
    "iso:country":"CN",
    "name:zho_x_preferred":[
        "\u540e\u5751"
    ],
    "wof:name":"Houkeng",
    "wof:placetype":"locality"
},
  "geometry": {"coordinates":[112.32016000000002,33.9068],"type":"Point"}
}