{
  "type": "Feature",
  "properties": {
    "gn:admin1_code":"19.0",
    "gn:asciiname":"Huashilingzicun",
    "gn:country_code":"CN",
    "gn:dem":131,
    "gn:feature_class":"P",
    "gn:feature_code":"PPL",
    "gn:name":"Huashilingzicun",
    "gn:population":0,
    "gn:timezone":"Asia/Shanghai",
    "iso:country":"CN",
    "name:zho_x_preferred":[
        "\u6ed1\u77f3\u5cad\u5b50\u6751"
    ],
    "wof:name":"Huashilingzicun",
    "wof:placetype":"locality"
},
  "geometry": {"coordinates":[121.596,41.7296],"type":"Point"}
}