{
  "type": "Feature",
  "properties": {
    "gn:admin1_code":"1.0",
    "gn:asciiname":"Qianliucun",
    "gn:country_code":"CN",
    "gn:dem":35,
    "gn:feature_class":"P",
    "gn:feature_code":"PPL",
    "gn:name":"Qianliucun",
    "gn:population":0,
    "gn:timezone":"Asia/Shanghai",
    "iso:country":"CN",
    "name:zho_x_preferred":[
        "\u524d\u5218\u6751"
    ],
    "wof:name":"Qianliucun",
    "wof:placetype":"locality"
},
  "geometry": {"coordinates":[116.25223,33.71120999999999],"type":"Point"}
}