{
  "type": "Feature",
  "properties": {
    "gn:admin1_code":"12.0",
    "gn:asciiname":"Dayantou",
    "gn:country_code":"CN",
    "gn:dem":43,
    "gn:feature_class":"P",
    "gn:feature_code":"PPL",
    "gn:name":"Dayantou",
    "gn:population":0,
    "gn:timezone":"Asia/Shanghai",
    "iso:country":"CN",
    "name:zho_x_preferred":[
        "Dayantou"
    ],
    "name:zho_x_variant":[
        "\u5927\u5830\u5934"
    ],
    "wof:name":"Dayantou",
    "wof:placetype":"locality"
},
  "geometry": {"coordinates":[111.73084,30.33544],"type":"Point"}
}