{
  "type": "Feature",
  "properties": {
    "gn:admin1_code":"10",
    "gn:asciiname":"Laomigou",
    "gn:country_code":"CN",
    "gn:dem":1480,
    "gn:feature_class":"P",
    "gn:feature_code":"PPL",
    "gn:name":"Laomigou",
    "gn:population":0,
    "gn:timezone":"Asia/Shanghai",
    "iso:country":"CN",
    "name:zho_x_preferred":[
        "\u8001\u8ff7\u6c9f"
    ],
    "wof:name":"Laomigou",
    "wof:placetype":"locality"
},
  "geometry": {"coordinates":[115.59201000000002,41.30926],"type":"Point"}
}