{
  "type": "Feature",
  "properties": {
    "gn:admin1_code":"14.0",
    "gn:asciiname":"Niruo",
    "gn:country_code":"CN",
    "gn:dem":3629,
    "gn:feature_class":"P",
    "gn:feature_code":"PPL",
    "gn:name":"Niruo",
    "gn:population":0,
    "gn:timezone":"Asia/Urumqi",
    "iso:country":"CN",
    "name:zho_x_preferred":[
        "\u5c3c\u82e5"
    ],
    "wof:name":"Niruo",
    "wof:placetype":"locality"
},
  "geometry": {"coordinates":[91.83723999999999,29.34552],"type":"Point"}
}