{
  "type": "Feature",
  "properties": {
    "gn:admin1_code":"3.0",
    "gn:asciiname":"Luwu",
    "gn:country_code":"CN",
    "gn:dem":180,
    "gn:feature_class":"P",
    "gn:feature_code":"PPL",
    "gn:name":"Luwu",
    "gn:population":0,
    "gn:timezone":"Asia/Shanghai",
    "iso:country":"CN",
    "name:ind_x_preferred":[
        "Kedatuan Luwu"
    ],
    "name:msa_x_preferred":[
        "Kerajaan Luwuk"
    ],
    "name:und_x_variant":[
        "\u5362\u5c4b"
    ],
    "wof:name":"Luwu",
    "wof:placetype":"locality"
},
  "geometry": {"coordinates":[115.07222,25.73221],"type":"Point"}
}