{
  "type": "Feature",
  "properties": {
    "gn:admin1_code":"14.0",
    "gn:asciiname":"Yuelong",
    "gn:country_code":"CN",
    "gn:dem":3255,
    "gn:feature_class":"P",
    "gn:feature_code":"PPL",
    "gn:name":"Yuelong",
    "gn:population":0,
    "gn:timezone":"Asia/Urumqi",
    "iso:country":"CN",
    "name:zho_x_preferred":[
        "\u7ea6\u9f99"
    ],
    "wof:name":"Yuelong",
    "wof:placetype":"locality"
},
  "geometry": {"coordinates":[97.35375999999999,30.86645],"type":"Point"}
}