{
  "type": "Feature",
  "properties": {
    "gn:admin1_code":"30.0",
    "gn:asciiname":"Shuangxiacun",
    "gn:country_code":"CN",
    "gn:dem":123,
    "gn:feature_class":"P",
    "gn:feature_code":"PPL",
    "gn:name":"Shuangxiacun",
    "gn:population":0,
    "gn:timezone":"Asia/Shanghai",
    "iso:country":"CN",
    "name:zho_x_preferred":[
        "\u53cc\u4e0b\u6751"
    ],
    "wof:name":"Shuangxiacun",
    "wof:placetype":"locality"
},
  "geometry": {"coordinates":[114.01579,24.32579],"type":"Point"}
}