{
  "type": "Feature",
  "properties": {
    "gn:admin1_code":"3.0",
    "gn:asciiname":"Sheqian",
    "gn:country_code":"CN",
    "gn:dem":48,
    "gn:feature_class":"P",
    "gn:feature_code":"PPL",
    "gn:name":"Sheqian",
    "gn:population":0,
    "gn:timezone":"Asia/Shanghai",
    "iso:country":"CN",
    "name:und_x_variant":[
        "\u793e\u524d"
    ],
    "wof:name":"Sheqian",
    "wof:placetype":"locality"
},
  "geometry": {"coordinates":[115.1438,28.41671],"type":"Point"}
}