{
  "type": "Feature",
  "properties": {
    "gn:admin1_code":"8.0",
    "gn:asciiname":"Mengjia Weizi",
    "gn:country_code":"CN",
    "gn:dem":200,
    "gn:feature_class":"P",
    "gn:feature_code":"PPL",
    "gn:name":"Mengjia Weizi",
    "gn:population":0,
    "gn:timezone":"Asia/Shanghai",
    "iso:country":"CN",
    "name:zho_x_preferred":[
        "\u5b5f\u5bb6\u56f4\u5b50"
    ],
    "wof:name":"Mengjia Weizi",
    "wof:placetype":"locality"
},
  "geometry": {"coordinates":[125.48178,46.019],"type":"Point"}
}