{
  "type": "Feature",
  "properties": {
    "gn:admin1_code":"12.0",
    "gn:asciiname":"Niuchedun",
    "gn:country_code":"CN",
    "gn:dem":33,
    "gn:feature_class":"P",
    "gn:feature_code":"PPL",
    "gn:name":"Niuchedun",
    "gn:population":0,
    "gn:timezone":"Asia/Shanghai",
    "iso:country":"CN",
    "name:zho_x_preferred":[
        "\u725b\u8f66\u58a9"
    ],
    "wof:name":"Niuchedun",
    "wof:placetype":"locality"
},
  "geometry": {"coordinates":[112.31168999999998,29.66548],"type":"Point"}
}