{
  "type": "Feature",
  "properties": {
    "gn:admin1_code":"15.0",
    "gn:asciiname":"Baituxian",
    "gn:country_code":"CN",
    "gn:dem":1885,
    "gn:feature_class":"P",
    "gn:feature_code":"PPL",
    "gn:name":"Baituxian",
    "gn:population":0,
    "gn:timezone":"Asia/Shanghai",
    "iso:country":"CN",
    "name:zho_x_preferred":[
        "\u767d\u571f\u5c98"
    ],
    "wof:name":"Baituxian",
    "wof:placetype":"locality"
},
  "geometry": {"coordinates":[105.333,34.9604],"type":"Point"}
}