{
  "type": "Feature",
  "properties": {
    "gn:admin1_code":"29.0",
    "gn:asciiname":"Qingzhu",
    "gn:country_code":"CN",
    "gn:dem":2642,
    "gn:feature_class":"P",
    "gn:feature_code":"PPL",
    "gn:name":"Qingzhu",
    "gn:population":0,
    "gn:timezone":"Asia/Shanghai",
    "iso:country":"CN",
    "name:zho_x_preferred":[
        "\u9752\u7af9"
    ],
    "wof:name":"Qingzhu",
    "wof:placetype":"locality"
},
  "geometry": {"coordinates":[99.1545,28.0892],"type":"Point"}
}