{
  "type": "Feature",
  "properties": {
    "gn:admin1_code":"26.0",
    "gn:asciiname":"Taohutu",
    "gn:country_code":"CN",
    "gn:dem":1205,
    "gn:feature_class":"P",
    "gn:feature_code":"PPL",
    "gn:name":"Taohutu",
    "gn:population":0,
    "gn:timezone":"Asia/Shanghai",
    "iso:country":"CN",
    "name:zho_x_preferred":[
        "\u9676\u5ffd\u56fe"
    ],
    "wof:name":"Taohutu",
    "wof:placetype":"locality"
},
  "geometry": {"coordinates":[108.95751,38.18781],"type":"Point"}
}