{
  "type": "Feature",
  "properties": {
    "gn:admin1_code":"15.0",
    "gn:asciiname":"Liangbaogou",
    "gn:country_code":"CN",
    "gn:dem":2159,
    "gn:feature_class":"P",
    "gn:feature_code":"PPL",
    "gn:name":"Liangbaogou",
    "gn:population":0,
    "gn:timezone":"Asia/Shanghai",
    "iso:country":"CN",
    "name:und_x_variant":[
        "\u6881\u8c79\u6c9f"
    ],
    "wof:name":"Liangbaogou",
    "wof:placetype":"locality"
},
  "geometry": {"coordinates":[105.13305,33.94446],"type":"Point"}
}