{
  "type": "Feature",
  "properties": {
    "gn:admin1_code":"10",
    "gn:asciiname":"Houxinyao",
    "gn:country_code":"CN",
    "gn:dem":1215,
    "gn:feature_class":"P",
    "gn:feature_code":"PPL",
    "gn:name":"Houxinyao",
    "gn:population":0,
    "gn:timezone":"Asia/Shanghai",
    "iso:country":"CN",
    "name:zho_x_preferred":[
        "\u540e\u65b0\u7a91"
    ],
    "wof:name":"Houxinyao",
    "wof:placetype":"locality"
},
  "geometry": {"coordinates":[114.23735000000001,40.97815],"type":"Point"}
}