{
  "type": "Feature",
  "properties": {
    "gn:admin1_code":"14.0",
    "gn:asciiname":"Xangga",
    "gn:country_code":"CN",
    "gn:dem":5230,
    "gn:feature_class":"P",
    "gn:feature_code":"PPL",
    "gn:name":"Xangga",
    "gn:population":0,
    "gn:timezone":"Asia/Urumqi",
    "iso:country":"CN",
    "name:bod_x_preferred":[
        "Xangga"
    ],
    "name:zho_x_preferred":[
        "Xiangga"
    ],
    "name:zho_x_variant":[
        "\u9999\u560e"
    ],
    "wof:name":"Xangga",
    "wof:placetype":"locality"
},
  "geometry": {"coordinates":[92.402,28.902],"type":"Point"}
}