{
  "type": "Feature",
  "properties": {
    "gn:admin1_code":"3.0",
    "gn:asciiname":"Zhaili",
    "gn:country_code":"CN",
    "gn:dem":134,
    "gn:feature_class":"P",
    "gn:feature_code":"PPL",
    "gn:name":"Zhaili",
    "gn:population":0,
    "gn:timezone":"Asia/Shanghai",
    "iso:country":"CN",
    "name:und_x_variant":[
        "\u5be8\u91cc"
    ],
    "wof:name":"Zhaili",
    "wof:placetype":"locality"
},
  "geometry": {"coordinates":[116.61922,27.04272000000001],"type":"Point"}
}