{
  "type": "Feature",
  "properties": {
    "gn:admin1_code":"02",
    "gn:asciiname":"Nanlu'aocun",
    "gn:country_code":"CN",
    "gn:dem":11,
    "gn:feature_class":"P",
    "gn:feature_code":"PPL",
    "gn:name":"Nanl\u00fc\u2019aocun",
    "gn:population":0,
    "gn:timezone":"Asia/Shanghai",
    "iso:country":"CN",
    "name:und_x_variant":[
        "Nanl\u00fc\u2019aocun"
    ],
    "name:zho_x_preferred":[
        "L\u00fc-ao-ts\u2019un"
    ],
    "name:zho_x_variant":[
        "\u5357\u5415\u5c99\u6751"
    ],
    "wof:name":"Nanlu'aocun",
    "wof:placetype":"locality"
},
  "geometry": {"coordinates":[120.91889,28.05778],"type":"Point"}
}