{
  "type": "Feature",
  "properties": {
    "gn:admin1_code":"7.0",
    "gn:asciiname":"Xiaojia",
    "gn:country_code":"CN",
    "gn:dem":655,
    "gn:feature_class":"P",
    "gn:feature_code":"PPL",
    "gn:name":"Xiaojia",
    "gn:population":0,
    "gn:timezone":"Asia/Shanghai",
    "iso:country":"CN",
    "name:zho_x_preferred":[
        "Xiaojia"
    ],
    "name:zho_x_variant":[
        "\u5c0f\u7532"
    ],
    "wof:name":"Xiaojia",
    "wof:placetype":"locality"
},
  "geometry": {"coordinates":[119.30052000000001,26.65271],"type":"Point"}
}