{
  "type": "Feature",
  "properties": {
    "gn:admin1_code":"1.0",
    "gn:asciiname":"Cangfangcun",
    "gn:country_code":"CN",
    "gn:dem":80,
    "gn:feature_class":"P",
    "gn:feature_code":"PPL",
    "gn:name":"Cangfangcun",
    "gn:population":0,
    "gn:timezone":"Asia/Shanghai",
    "iso:country":"CN",
    "name:zho_x_preferred":[
        "\u4ed3\u623f\u6751"
    ],
    "wof:name":"Cangfangcun",
    "wof:placetype":"locality"
},
  "geometry": {"coordinates":[116.52123,31.61682],"type":"Point"}
}