{
  "type": "Feature",
  "properties": {
    "gn:admin1_code":"26.0",
    "gn:asciiname":"Sanzhanghecun",
    "gn:country_code":"CN",
    "gn:dem":1248,
    "gn:feature_class":"P",
    "gn:feature_code":"PPL",
    "gn:name":"Sanzhanghecun",
    "gn:population":0,
    "gn:timezone":"Asia/Shanghai",
    "iso:country":"CN",
    "name:zho_x_preferred":[
        "\u4e09\u4e08\u6cb3\u6751"
    ],
    "wof:name":"Sanzhanghecun",
    "wof:placetype":"locality"
},
  "geometry": {"coordinates":[109.24714,35.22891],"type":"Point"}
}