{
  "type": "Feature",
  "properties": {
    "gn:admin1_code":"15.0",
    "gn:asciiname":"Qingyangou",
    "gn:country_code":"CN",
    "gn:dem":2279,
    "gn:feature_class":"P",
    "gn:feature_code":"PPL",
    "gn:name":"Qingyangou",
    "gn:population":0,
    "gn:timezone":"Asia/Shanghai",
    "iso:country":"CN",
    "name:zho_x_preferred":[
        "\u9752\u5ca9\u6c9f"
    ],
    "wof:name":"Qingyangou",
    "wof:placetype":"locality"
},
  "geometry": {"coordinates":[104.68724,33.76071],"type":"Point"}
}