{
  "type": "Feature",
  "properties": {
    "gn:admin1_code":"5.0",
    "gn:asciiname":"Delitun",
    "gn:country_code":"CN",
    "gn:dem":349,
    "gn:feature_class":"P",
    "gn:feature_code":"PPL",
    "gn:name":"Delitun",
    "gn:population":0,
    "gn:timezone":"Asia/Shanghai",
    "iso:country":"CN",
    "name:zho_x_preferred":[
        "\u5f97\u5229\u5c6f"
    ],
    "wof:name":"Delitun",
    "wof:placetype":"locality"
},
  "geometry": {"coordinates":[126.06431000000001,43.04442],"type":"Point"}
}