{
  "type": "Feature",
  "properties": {
    "gn:admin1_code":"3.0",
    "gn:asciiname":"Wankeng",
    "gn:country_code":"CN",
    "gn:dem":176,
    "gn:feature_class":"P",
    "gn:feature_code":"PPL",
    "gn:name":"Wankeng",
    "gn:population":0,
    "gn:timezone":"Asia/Shanghai",
    "iso:country":"CN",
    "name:zho_x_preferred":[
        "\u4e07\u5751"
    ],
    "wof:name":"Wankeng",
    "wof:placetype":"locality"
},
  "geometry": {"coordinates":[115.58,27.0113],"type":"Point"}
}