{
  "type": "Feature",
  "properties": {
    "gn:admin1_code":"25",
    "gn:asciiname":"Liangtianzhuang",
    "gn:country_code":"CN",
    "gn:dem":157,
    "gn:feature_class":"P",
    "gn:feature_code":"PPL",
    "gn:name":"Liangtianzhuang",
    "gn:population":0,
    "gn:timezone":"Asia/Shanghai",
    "iso:country":"CN",
    "name:zho_x_preferred":[
        "\u826f\u7530\u5e84"
    ],
    "wof:name":"Liangtianzhuang",
    "wof:placetype":"locality"
},
  "geometry": {"coordinates":[117.81699999999999,35.2884],"type":"Point"}
}