{
  "type": "Feature",
  "properties": {
    "gn:admin1_code":"30",
    "gn:asciiname":"Xinbei",
    "gn:country_code":"CN",
    "gn:dem":125,
    "gn:feature_class":"P",
    "gn:feature_code":"PPLA4",
    "gn:name":"Xinbei",
    "gn:population":0,
    "gn:timezone":"Asia/Shanghai",
    "iso:country":"CN",
    "name:deu_x_preferred":[
        "Xinbei"
    ],
    "name:und_x_variant":[
        "Xinbei Zhen",
        "Xinpi Zhen",
        "\u65b0\u9642\u9547"
    ],
    "name:zho_x_preferred":[
        "\u65b0\u9642"
    ],
    "wof:name":"Xinbei",
    "wof:placetype":"locality"
},
  "geometry": {"coordinates":[115.68942,24.15832],"type":"Point"}
}