{
  "type": "Feature",
  "properties": {
    "gn:admin1_code":"29",
    "gn:asciiname":"Shaku",
    "gn:country_code":"CN",
    "gn:dem":1206,
    "gn:feature_class":"P",
    "gn:feature_code":"PPL",
    "gn:name":"Shaku",
    "gn:population":0,
    "gn:timezone":"Asia/Shanghai",
    "iso:country":"CN",
    "name:heb_x_preferred":[
        "\u05e9\u05d0\u05e7\u05d5"
    ],
    "name:zho_x_preferred":[
        "\u6c99\u82e6"
    ],
    "wof:name":"Shaku",
    "wof:placetype":"locality"
},
  "geometry": {"coordinates":[102.089,23.4653],"type":"Point"}
}