{
  "type": "Feature",
  "properties": {
    "gn:admin1_code":"16.0",
    "gn:asciiname":"Aidong",
    "gn:country_code":"CN",
    "gn:dem":348,
    "gn:feature_class":"P",
    "gn:feature_code":"PPL",
    "gn:name":"Aidong",
    "gn:population":0,
    "gn:timezone":"Asia/Shanghai",
    "iso:country":"CN",
    "name:zho_x_preferred":[
        "\u9698\u5cd2"
    ],
    "wof:name":"Aidong",
    "wof:placetype":"locality"
},
  "geometry": {"coordinates":[108.562,24.6005],"type":"Point"}
}