{
  "type": "Feature",
  "properties": {
    "gn:admin1_code":"11.0",
    "gn:asciiname":"Caidong",
    "gn:country_code":"CN",
    "gn:dem":840,
    "gn:feature_class":"P",
    "gn:feature_code":"PPL",
    "gn:name":"Caidong",
    "gn:population":0,
    "gn:timezone":"Asia/Shanghai",
    "iso:country":"CN",
    "name:zho_x_preferred":[
        "\u5f69\u6d1e"
    ],
    "wof:name":"Caidong",
    "wof:placetype":"locality"
},
  "geometry": {"coordinates":[113.55341,26.1813],"type":"Point"}
}