{
  "type": "Feature",
  "properties": {
    "gn:admin1_code":"12.0",
    "gn:asciiname":"Daliufu",
    "gn:country_code":"CN",
    "gn:dem":46,
    "gn:feature_class":"P",
    "gn:feature_code":"PPL",
    "gn:name":"Daliufu",
    "gn:population":0,
    "gn:timezone":"Asia/Shanghai",
    "iso:country":"CN",
    "name:und_x_variant":[
        "\u5927\u5218\u798f"
    ],
    "wof:name":"Daliufu",
    "wof:placetype":"locality"
},
  "geometry": {"coordinates":[114.92822,30.24818],"type":"Point"}
}