{
  "type": "Feature",
  "properties": {
    "gn:admin1_code":"4.0",
    "gn:asciiname":"Wanqiaocun",
    "gn:country_code":"CN",
    "gn:dem":3,
    "gn:feature_class":"P",
    "gn:feature_code":"PPL",
    "gn:name":"Wanqiaocun",
    "gn:population":0,
    "gn:timezone":"Asia/Shanghai",
    "iso:country":"CN",
    "name:zho_x_preferred":[
        "\u4e07\u6865\u6751"
    ],
    "wof:name":"Wanqiaocun",
    "wof:placetype":"locality"
},
  "geometry": {"coordinates":[120.55132999999999,32.7497],"type":"Point"}
}