{
  "type": "Feature",
  "properties": {
    "gn:admin1_code":"29.0",
    "gn:asciiname":"Laiwen",
    "gn:country_code":"CN",
    "gn:dem":1132,
    "gn:feature_class":"P",
    "gn:feature_code":"PPL",
    "gn:name":"Laiwen",
    "gn:population":0,
    "gn:timezone":"Asia/Shanghai",
    "iso:country":"CN",
    "name:zho_x_preferred":[
        "\u8d56\u6587"
    ],
    "wof:name":"Laiwen",
    "wof:placetype":"locality"
},
  "geometry": {"coordinates":[100.542,24.4938],"type":"Point"}
}