{
  "type": "Feature",
  "properties": {
    "gn:admin1_code":"14.0",
    "gn:asciiname":"Mala",
    "gn:country_code":"CN",
    "gn:dem":3755,
    "gn:feature_class":"P",
    "gn:feature_code":"PPL",
    "gn:name":"Mala",
    "gn:population":0,
    "gn:timezone":"Asia/Urumqi",
    "iso:country":"CN",
    "name:zho_x_preferred":[
        "\u9ebb\u62c9"
    ],
    "wof:name":"Mala",
    "wof:placetype":"locality"
},
  "geometry": {"coordinates":[93.70019000000001,30.40144],"type":"Point"}
}