{
  "type": "Feature",
  "properties": {
    "gn:admin1_code":"26.0",
    "gn:asciiname":"Chaicunpingcun",
    "gn:country_code":"CN",
    "gn:dem":1063,
    "gn:feature_class":"P",
    "gn:feature_code":"PPL",
    "gn:name":"Chaicunpingcun",
    "gn:population":0,
    "gn:timezone":"Asia/Shanghai",
    "iso:country":"CN",
    "name:zho_x_preferred":[
        "\u67f4\u6751\u576a\u6751"
    ],
    "wof:name":"Chaicunpingcun",
    "wof:placetype":"locality"
},
  "geometry": {"coordinates":[110.2253,36.37458],"type":"Point"}
}