{
  "type": "Feature",
  "properties": {
    "gn:admin1_code":"31.0",
    "gn:asciiname":"Wu'er",
    "gn:country_code":"CN",
    "gn:dem":57,
    "gn:feature_class":"P",
    "gn:feature_code":"PPL",
    "gn:name":"Wu\u2019er",
    "gn:population":0,
    "gn:timezone":"Asia/Shanghai",
    "iso:country":"CN",
    "name:zho_x_preferred":[
        "Wu\u2019er"
    ],
    "name:zho_x_variant":[
        "\u543e\u5c14"
    ],
    "wof:name":"Wu'er",
    "wof:placetype":"locality"
},
  "geometry": {"coordinates":[109.70959000000001,19.82371],"type":"Point"}
}