{
  "type": "Feature",
  "properties": {
    "gn:admin1_code":"8.0",
    "gn:asciiname":"Huxincun",
    "gn:country_code":"CN",
    "gn:dem":215,
    "gn:feature_class":"P",
    "gn:feature_code":"PPL",
    "gn:name":"Huxincun",
    "gn:population":0,
    "gn:timezone":"Asia/Shanghai",
    "iso:country":"CN",
    "name:zho_x_preferred":[
        "\u62a4\u5fc3\u6751"
    ],
    "wof:name":"Huxincun",
    "wof:placetype":"locality"
},
  "geometry": {"coordinates":[125.76385000000001,47.91407],"type":"Point"}
}