{
  "type": "Feature",
  "properties": {
    "gn:admin1_code":"19.0",
    "gn:asciiname":"Shuangtagoucun",
    "gn:country_code":"CN",
    "gn:dem":166,
    "gn:feature_class":"P",
    "gn:feature_code":"PPL",
    "gn:name":"Shuangtagoucun",
    "gn:population":0,
    "gn:timezone":"Asia/Shanghai",
    "iso:country":"CN",
    "name:zho_x_preferred":[
        "\u53cc\u5854\u6c9f\u6751"
    ],
    "wof:name":"Shuangtagoucun",
    "wof:placetype":"locality"
},
  "geometry": {"coordinates":[120.63109,41.11662000000001],"type":"Point"}
}