{
  "type": "Feature",
  "properties": {
    "gn:admin1_code":"1.0",
    "gn:asciiname":"Yongfacun",
    "gn:country_code":"CN",
    "gn:dem":37,
    "gn:feature_class":"P",
    "gn:feature_code":"PPL",
    "gn:name":"Yongfacun",
    "gn:population":0,
    "gn:timezone":"Asia/Shanghai",
    "iso:country":"CN",
    "name:zho_x_preferred":[
        "\u6c38\u53d1\u6751"
    ],
    "wof:name":"Yongfacun",
    "wof:placetype":"locality"
},
  "geometry": {"coordinates":[116.5476,30.37383],"type":"Point"}
}