{
  "type": "Feature",
  "properties": {
    "gn:admin1_code":"8.0",
    "gn:asciiname":"Ershiqihao",
    "gn:country_code":"CN",
    "gn:dem":211,
    "gn:feature_class":"P",
    "gn:feature_code":"PPL",
    "gn:name":"Ershiqihao",
    "gn:population":0,
    "gn:timezone":"Asia/Shanghai",
    "iso:country":"CN",
    "name:zho_x_preferred":[
        "\u4e8c\u5341\u4e03\u53f7"
    ],
    "wof:name":"Ershiqihao",
    "wof:placetype":"locality"
},
  "geometry": {"coordinates":[125.35845999999999,47.94731],"type":"Point"}
}