{
  "type": "Feature",
  "properties": {
    "gn:admin1_code":"04",
    "gn:asciiname":"Shiwu Dadui",
    "gn:country_code":"CN",
    "gn:dem":7,
    "gn:feature_class":"P",
    "gn:feature_code":"PPLF",
    "gn:name":"Shiwu Dadui",
    "gn:population":0,
    "gn:timezone":"Asia/Shanghai",
    "iso:country":"CN",
    "name:und_x_variant":[
        "Tongnong Shiwudui",
        "Shiwu Dadui"
    ],
    "wof:name":"Shiwu Dadui",
    "wof:placetype":"locality"
},
  "geometry": {"coordinates":[120.99482,31.84105],"type":"Point"}
}