{
  "type": "Feature",
  "properties": {
    "gn:admin1_code":"16.0",
    "gn:asciiname":"Yali",
    "gn:country_code":"CN",
    "gn:dem":363,
    "gn:feature_class":"P",
    "gn:feature_code":"PPL",
    "gn:name":"Yali",
    "gn:population":0,
    "gn:timezone":"Asia/Shanghai",
    "iso:country":"CN",
    "name:ceb_x_preferred":[
        "Yali"
    ],
    "name:deu_x_preferred":[
        "Yali"
    ],
    "name:ita_x_preferred":[
        "Yali"
    ],
    "name:nld_x_preferred":[
        "Yali"
    ],
    "name:nor_x_preferred":[
        "Yali"
    ],
    "name:pol_x_preferred":[
        "Yali"
    ],
    "name:slk_x_preferred":[
        "Yali"
    ],
    "name:swe_x_preferred":[
        "Yali"
    ],
    "name:tur_x_preferred":[
        "Yal\u0131"
    ],
    "name:zho_x_preferred":[
        "\u7259\u91cc"
    ],
    "wof:name":"Yali",
    "wof:placetype":"locality"
},
  "geometry": {"coordinates":[107.247,24.9426],"type":"Point"}
}