{
  "type": "Feature",
  "properties": {
    "gn:admin1_code":"14.0",
    "gn:asciiname":"Benduilama",
    "gn:country_code":"CN",
    "gn:dem":3762,
    "gn:feature_class":"P",
    "gn:feature_code":"PPL",
    "gn:name":"Benduilama",
    "gn:population":0,
    "gn:timezone":"Asia/Urumqi",
    "iso:country":"CN",
    "name:zho_x_preferred":[
        "\u672c\u5bf9\u62c9\u9ebb"
    ],
    "wof:name":"Benduilama",
    "wof:placetype":"locality"
},
  "geometry": {"coordinates":[93.60720000000001,30.19903],"type":"Point"}
}