{
  "type": "Feature",
  "properties": {
    "gn:admin1_code":"30",
    "gn:asciiname":"Dongshan",
    "gn:country_code":"CN",
    "gn:dem":10,
    "gn:feature_class":"P",
    "gn:feature_code":"PPLA4",
    "gn:name":"Dongshan",
    "gn:population":0,
    "gn:timezone":"Asia/Urumqi",
    "iso:country":"CN",
    "name:ceb_x_preferred":[
        "Dongshan"
    ],
    "name:deu_x_preferred":[
        "Dongshan"
    ],
    "name:eus_x_preferred":[
        "Dongshan"
    ],
    "name:fra_x_preferred":[
        "Dongshan"
    ],
    "name:nor_x_preferred":[
        "Dongshan"
    ],
    "name:rus_x_preferred":[
        "\u0414\u0443\u043d\u0448\u0430\u043d\u044c"
    ],
    "name:spa_x_preferred":[
        "Dongshan"
    ],
    "name:swe_x_preferred":[
        "Dongshan"
    ],
    "name:und_x_variant":[
        "Lei-tung",
        "Tung-shan",
        "Dongshan",
        "\u4e1c\u5c71",
        "Dongshan Zhen",
        "\u4e1c\u5c71\u9547"
    ],
    "wof:name":"Dongshan",
    "wof:placetype":"locality"
},
  "geometry": {"coordinates":[110.39236,21.03506],"type":"Point"}
}