{
  "type": "Feature",
  "properties": {
    "gn:admin1_code":"5.0",
    "gn:asciiname":"Taiyangchuan",
    "gn:country_code":"CN",
    "gn:dem":278,
    "gn:feature_class":"P",
    "gn:feature_code":"PPL",
    "gn:name":"Taiyangchuan",
    "gn:population":0,
    "gn:timezone":"Asia/Shanghai",
    "iso:country":"CN",
    "name:und_x_variant":[
        "\u592a\u9633\u5ddd"
    ],
    "wof:name":"Taiyangchuan",
    "wof:placetype":"locality"
},
  "geometry": {"coordinates":[130.97970000000001,43.30037],"type":"Point"}
}