{
  "type": "Feature",
  "properties": {
    "gn:admin1_code":"05",
    "gn:asciiname":"Sanhetun",
    "gn:cc2":"CN",
    "gn:country_code":"CN",
    "gn:dem":412,
    "gn:feature_class":"P",
    "gn:feature_code":"PPL",
    "gn:name":"Sanhetun",
    "gn:population":0,
    "gn:timezone":"Asia/Shanghai",
    "iso:country":"CN",
    "name:und_x_variant":[
        "San-ho-t\u2019un",
        "Sanhe",
        "Sanhetun"
    ],
    "wof:name":"Sanhetun",
    "wof:placetype":"locality"
},
  "geometry": {"coordinates":[125.24028,42.39611],"type":"Point"}
}