{
  "type": "Feature",
  "properties": {
    "gn:admin1_code":"13",
    "gn:asciiname":"Siqi",
    "gn:country_code":"CN",
    "gn:dem":500,
    "gn:feature_class":"P",
    "gn:feature_code":"PPL",
    "gn:name":"Siqi",
    "gn:population":0,
    "gn:timezone":"Asia/Urumqi",
    "iso:country":"CN",
    "name:zho_x_preferred":[
        "\u56db\u7566"
    ],
    "wof:name":"Siqi",
    "wof:placetype":"locality"
},
  "geometry": {"coordinates":[87.38339000000001,44.14098],"type":"Point"}
}