{
  "type": "Feature",
  "properties": {
    "gn:admin1_code":"10",
    "gn:asciiname":"Dapanzhuang",
    "gn:country_code":"CN",
    "gn:dem":27,
    "gn:feature_class":"P",
    "gn:feature_code":"PPL",
    "gn:name":"Dapanzhuang",
    "gn:population":0,
    "gn:timezone":"Asia/Shanghai",
    "iso:country":"CN",
    "name:zho_x_preferred":[
        "\u5927\u6f58\u5e84"
    ],
    "wof:name":"Dapanzhuang",
    "wof:placetype":"locality"
},
  "geometry": {"coordinates":[115.021,37.3794],"type":"Point"}
}