{
  "type": "Feature",
  "properties": {
    "gn:admin1_code":"14.0",
    "gn:asciiname":"Dingqie",
    "gn:country_code":"CN",
    "gn:dem":4353,
    "gn:feature_class":"P",
    "gn:feature_code":"PPL",
    "gn:name":"Dingqie",
    "gn:population":0,
    "gn:timezone":"Asia/Urumqi",
    "iso:country":"CN",
    "name:zho_x_preferred":[
        "\u9876\u5207"
    ],
    "wof:name":"Dingqie",
    "wof:placetype":"locality"
},
  "geometry": {"coordinates":[94.08023,31.42119000000001],"type":"Point"}
}