{
  "type": "Feature",
  "properties": {
    "gn:admin1_code":"20.0",
    "gn:asciiname":"Hongsheng Sanzu",
    "gn:country_code":"CN",
    "gn:dem":346,
    "gn:feature_class":"P",
    "gn:feature_code":"PPL",
    "gn:name":"Hongsheng Sanzu",
    "gn:population":0,
    "gn:timezone":"Asia/Shanghai",
    "iso:country":"CN",
    "name:zho_x_preferred":[
        "\u7ea2\u5347\u4e09\u7ec4"
    ],
    "wof:name":"Hongsheng Sanzu",
    "wof:placetype":"locality"
},
  "geometry": {"coordinates":[124.86415,49.59075],"type":"Point"}
}