{
  "type": "Feature",
  "properties": {
    "gn:admin1_code":"26.0",
    "gn:asciiname":"Gongjiayuancun",
    "gn:country_code":"CN",
    "gn:dem":974,
    "gn:feature_class":"P",
    "gn:feature_code":"PPL",
    "gn:name":"Gongjiayuancun",
    "gn:population":0,
    "gn:timezone":"Asia/Shanghai",
    "iso:country":"CN",
    "name:und_x_variant":[
        "\u9f9a\u5bb6\u9662\u6751"
    ],
    "wof:name":"Gongjiayuancun",
    "wof:placetype":"locality"
},
  "geometry": {"coordinates":[107.05119999999999,33.43386],"type":"Point"}
}