{
  "type": "Feature",
  "properties": {
    "gn:admin1_code":"16.0",
    "gn:asciiname":"Wutang",
    "gn:cc2":"CN",
    "gn:country_code":"CN",
    "gn:dem":83,
    "gn:feature_class":"P",
    "gn:feature_code":"PPL",
    "gn:name":"Wutang",
    "gn:population":0,
    "gn:timezone":"Asia/Shanghai",
    "iso:country":"CN",
    "name:deu_x_preferred":[
        "Wudang"
    ],
    "name:eus_x_preferred":[
        "Wudang"
    ],
    "name:fra_x_preferred":[
        "Wudang"
    ],
    "name:swe_x_preferred":[
        "Wudang"
    ],
    "name:und_x_variant":[
        "Wu-t\u2019ang-hs\u00fc",
        "Wutang"
    ],
    "wof:name":"Wutang",
    "wof:placetype":"locality"
},
  "geometry": {"coordinates":[108.55,22.95],"type":"Point"}
}