{
  "type": "Feature",
  "properties": {
    "gn:admin1_code":"11.0",
    "gn:asciiname":"Yandong",
    "gn:country_code":"CN",
    "gn:dem":31,
    "gn:feature_class":"P",
    "gn:feature_code":"PPL",
    "gn:name":"Yandong",
    "gn:population":0,
    "gn:timezone":"Asia/Shanghai",
    "iso:country":"CN",
    "name:zho_x_preferred":[
        "\u6edf\u4e1c"
    ],
    "wof:name":"Yandong",
    "wof:placetype":"locality"
},
  "geometry": {"coordinates":[112.35824,29.31209],"type":"Point"}
}