{
  "type": "Feature",
  "properties": {
    "gn:admin1_code":"19.0",
    "gn:asciiname":"Dabagou",
    "gn:country_code":"CN",
    "gn:dem":217,
    "gn:feature_class":"P",
    "gn:feature_code":"PPL",
    "gn:name":"Dabagou",
    "gn:population":0,
    "gn:timezone":"Asia/Shanghai",
    "iso:country":"CN",
    "name:und_x_variant":[
        "\u5927\u575d\u6c9f"
    ],
    "name:zho_x_preferred":[
        "\u5927\u575d\u6c9f"
    ],
    "wof:name":"Dabagou",
    "wof:placetype":"locality"
},
  "geometry": {"coordinates":[121.76564,42.00572],"type":"Point"}
}