{
  "type": "Feature",
  "properties": {
    "gn:admin1_code":"1.0",
    "gn:asciiname":"Dongzhangzhaicun",
    "gn:country_code":"CN",
    "gn:dem":33,
    "gn:feature_class":"P",
    "gn:feature_code":"PPL",
    "gn:name":"Dongzhangzhaicun",
    "gn:population":0,
    "gn:timezone":"Asia/Shanghai",
    "iso:country":"CN",
    "name:zho_x_preferred":[
        "\u4e1c\u5f20\u5be8\u6751"
    ],
    "wof:name":"Dongzhangzhaicun",
    "wof:placetype":"locality"
},
  "geometry": {"coordinates":[115.53152,32.4834],"type":"Point"}
}