{
  "type": "Feature",
  "properties": {
    "gn:admin1_code":"4.0",
    "gn:asciiname":"Yaohuacun",
    "gn:country_code":"CN",
    "gn:dem":22,
    "gn:feature_class":"P",
    "gn:feature_code":"PPL",
    "gn:name":"Yaohuacun",
    "gn:population":0,
    "gn:timezone":"Asia/Shanghai",
    "iso:country":"CN",
    "name:zho_x_preferred":[
        "\u8000\u534e\u6751"
    ],
    "wof:name":"Yaohuacun",
    "wof:placetype":"locality"
},
  "geometry": {"coordinates":[119.00530000000001,31.8933],"type":"Point"}
}