{
  "type": "Feature",
  "properties": {
    "gn:admin1_code":"18",
    "gn:asciiname":"Huangjuedian",
    "gn:country_code":"CN",
    "gn:dem":336,
    "gn:feature_class":"P",
    "gn:feature_code":"PPL",
    "gn:name":"Huangjuedian",
    "gn:population":0,
    "gn:timezone":"Asia/Shanghai",
    "iso:country":"CN",
    "name:zho_x_preferred":[
        "\u9ec4\u6877\u5e97"
    ],
    "wof:name":"Huangjuedian",
    "wof:placetype":"locality"
},
  "geometry": {"coordinates":[105.922,28.6554],"type":"Point"}
}