{
  "type": "Feature",
  "properties": {
    "gn:admin1_code":"20.0",
    "gn:asciiname":"Zhangsanhao",
    "gn:country_code":"CN",
    "gn:dem":1569,
    "gn:feature_class":"P",
    "gn:feature_code":"PPL",
    "gn:name":"Zhangsanhao",
    "gn:population":0,
    "gn:timezone":"Asia/Shanghai",
    "iso:country":"CN",
    "name:und_x_variant":[
        "\u5f20\u4e09\u58d5"
    ],
    "wof:name":"Zhangsanhao",
    "wof:placetype":"locality"
},
  "geometry": {"coordinates":[110.26228,41.04608],"type":"Point"}
}