{
  "type": "Feature",
  "properties": {
    "gn:admin1_code":"19",
    "gn:asciiname":"Baijiagou",
    "gn:cc2":"CN",
    "gn:country_code":"CN",
    "gn:dem":89,
    "gn:feature_class":"P",
    "gn:feature_code":"PPL",
    "gn:name":"Baijiagou",
    "gn:population":0,
    "gn:timezone":"Asia/Shanghai",
    "iso:country":"CN",
    "name:und_x_variant":[
        "Pai-chia-kou",
        "Po-chia-kou",
        "Baijiagou"
    ],
    "wof:name":"Baijiagou",
    "wof:placetype":"locality"
},
  "geometry": {"coordinates":[123.61167,42.55056],"type":"Point"}
}