{
  "type": "Feature",
  "properties": {
    "gn:admin1_code":"15.0",
    "gn:asciiname":"Heiyangquan",
    "gn:country_code":"CN",
    "gn:dem":2441,
    "gn:feature_class":"P",
    "gn:feature_code":"PPLF",
    "gn:name":"Heiyangquan",
    "gn:population":0,
    "gn:timezone":"Asia/Shanghai",
    "iso:country":"CN",
    "name:zho_x_preferred":[
        "\u9ed1\u7f8a\u5708"
    ],
    "wof:name":"Heiyangquan",
    "wof:placetype":"locality"
},
  "geometry": {"coordinates":[98.3383,39.5009],"type":"Point"}
}