{
  "type": "Feature",
  "properties": {
    "gn:admin1_code":"32.0",
    "gn:asciiname":"Shiwangmiao",
    "gn:country_code":"CN",
    "gn:dem":444,
    "gn:feature_class":"P",
    "gn:feature_code":"PPL",
    "gn:name":"Shiwangmiao",
    "gn:population":0,
    "gn:timezone":"Asia/Shanghai",
    "iso:country":"CN",
    "name:zho_x_preferred":[
        "\u77f3\u738b\u5e99"
    ],
    "wof:name":"Shiwangmiao",
    "wof:placetype":"locality"
},
  "geometry": {"coordinates":[104.557,30.5872],"type":"Point"}
}