{
  "type": "Feature",
  "properties": {
    "gn:admin1_code":"25",
    "gn:asciiname":"Beimacun",
    "gn:country_code":"CN",
    "gn:dem":85,
    "gn:feature_class":"P",
    "gn:feature_code":"PPL",
    "gn:name":"Beimacun",
    "gn:population":0,
    "gn:timezone":"Asia/Shanghai",
    "iso:country":"CN",
    "name:zho_x_preferred":[
        "\u5317\u9a6c\u6751"
    ],
    "wof:name":"Beimacun",
    "wof:placetype":"locality"
},
  "geometry": {"coordinates":[117.06100000000001,35.6744],"type":"Point"}
}