{
  "type": "Feature",
  "properties": {
    "gn:admin1_code":"16.0",
    "gn:asciiname":"Longyangzhai",
    "gn:country_code":"CN",
    "gn:dem":1033,
    "gn:feature_class":"P",
    "gn:feature_code":"PPL",
    "gn:name":"Longyangzhai",
    "gn:population":0,
    "gn:timezone":"Asia/Shanghai",
    "iso:country":"CN",
    "name:zho_x_preferred":[
        "\u9f99\u7f8a\u5be8"
    ],
    "wof:name":"Longyangzhai",
    "wof:placetype":"locality"
},
  "geometry": {"coordinates":[105.34099999999999,24.1184],"type":"Point"}
}