{
  "type": "Feature",
  "properties": {
    "gn:admin1_code":"30.0",
    "gn:asciiname":"Qiuwu",
    "gn:country_code":"CN",
    "gn:dem":157,
    "gn:feature_class":"P",
    "gn:feature_code":"PPL",
    "gn:name":"Qiuwu",
    "gn:population":0,
    "gn:timezone":"Asia/Shanghai",
    "iso:country":"CN",
    "name:zho_x_preferred":[
        "\u4e18\u5c4b"
    ],
    "wof:name":"Qiuwu",
    "wof:placetype":"locality"
},
  "geometry": {"coordinates":[113.85621999999999,24.36179],"type":"Point"}
}