{
  "type": "Feature",
  "properties": {
    "gn:admin1_code":"12.0",
    "gn:asciiname":"Wengjiamiao",
    "gn:country_code":"CN",
    "gn:dem":141,
    "gn:feature_class":"P",
    "gn:feature_code":"PPL",
    "gn:name":"Wengjiamiao",
    "gn:population":0,
    "gn:timezone":"Asia/Shanghai",
    "iso:country":"CN",
    "name:zho_x_preferred":[
        "Wengjiamiao"
    ],
    "name:zho_x_variant":[
        "\u7fc1\u5bb6\u5e99"
    ],
    "wof:name":"Wengjiamiao",
    "wof:placetype":"locality"
},
  "geometry": {"coordinates":[111.61815,30.70414],"type":"Point"}
}