{
  "type": "Feature",
  "properties": {
    "gn:admin1_code":"14.0",
    "gn:asciiname":"Rewu",
    "gn:country_code":"CN",
    "gn:dem":4055,
    "gn:feature_class":"P",
    "gn:feature_code":"PPL",
    "gn:name":"Rewu",
    "gn:population":0,
    "gn:timezone":"Asia/Urumqi",
    "iso:country":"CN",
    "name:zho_x_preferred":[
        "\u70ed\u4f0d"
    ],
    "wof:name":"Rewu",
    "wof:placetype":"locality"
},
  "geometry": {"coordinates":[97.52104,29.99058],"type":"Point"}
}