{
  "type": "Feature",
  "properties": {
    "gn:admin1_code":"29.0",
    "gn:asciiname":"Manditang",
    "gn:country_code":"CN",
    "gn:dem":1851,
    "gn:feature_class":"P",
    "gn:feature_code":"PPL",
    "gn:name":"Manditang",
    "gn:population":0,
    "gn:timezone":"Asia/Shanghai",
    "iso:country":"CN",
    "name:zho_x_preferred":[
        "\u6ee1\u5730\u5858"
    ],
    "wof:name":"Manditang",
    "wof:placetype":"locality"
},
  "geometry": {"coordinates":[99.0373,27.8161],"type":"Point"}
}