{
  "type": "Feature",
  "properties": {
    "gn:admin1_code":"15.0",
    "gn:asciiname":"Wangjiashao",
    "gn:country_code":"CN",
    "gn:dem":1350,
    "gn:feature_class":"P",
    "gn:feature_code":"PPL",
    "gn:name":"Wangjiashao",
    "gn:population":0,
    "gn:timezone":"Asia/Shanghai",
    "iso:country":"CN",
    "name:zho_x_preferred":[
        "\u738b\u5bb6\u68a2"
    ],
    "wof:name":"Wangjiashao",
    "wof:placetype":"locality"
},
  "geometry": {"coordinates":[103.29600000000001,38.733],"type":"Point"}
}