{
  "type": "Feature",
  "properties": {
    "gn:admin1_code":"11.0",
    "gn:asciiname":"Xujiaping",
    "gn:country_code":"CN",
    "gn:dem":644,
    "gn:feature_class":"P",
    "gn:feature_code":"PPL",
    "gn:name":"Xujiaping",
    "gn:population":0,
    "gn:timezone":"Asia/Shanghai",
    "iso:country":"CN",
    "name:zho_x_preferred":[
        "\u5f90\u5bb6\u576a"
    ],
    "wof:name":"Xujiaping",
    "wof:placetype":"locality"
},
  "geometry": {"coordinates":[111.63017000000001,25.79667],"type":"Point"}
}