{
  "type": "Feature",
  "properties": {
    "gn:admin1_code":"32.0",
    "gn:asciiname":"Lianxizhai",
    "gn:country_code":"CN",
    "gn:dem":835,
    "gn:feature_class":"P",
    "gn:feature_code":"PPL",
    "gn:name":"Lianxizhai",
    "gn:population":0,
    "gn:timezone":"Asia/Shanghai",
    "iso:country":"CN",
    "name:zho_x_preferred":[
        "\u83b2\u6eaa\u5be8"
    ],
    "wof:name":"Lianxizhai",
    "wof:placetype":"locality"
},
  "geometry": {"coordinates":[105.24342,32.26221],"type":"Point"}
}