{
  "type": "Feature",
  "properties": {
    "gn:admin1_code":"11.0",
    "gn:asciiname":"Qingjiatang",
    "gn:country_code":"CN",
    "gn:dem":77,
    "gn:feature_class":"P",
    "gn:feature_code":"PPL",
    "gn:name":"Qingjiatang",
    "gn:population":0,
    "gn:timezone":"Asia/Shanghai",
    "iso:country":"CN",
    "name:zho_x_preferred":[
        "\u5e86\u5bb6\u5858"
    ],
    "wof:name":"Qingjiatang",
    "wof:placetype":"locality"
},
  "geometry": {"coordinates":[112.7521,28.2723],"type":"Point"}
}