{
  "type": "Feature",
  "properties": {
    "gn:admin1_code":"19.0",
    "gn:asciiname":"Xiadianzi",
    "gn:country_code":"CN",
    "gn:dem":297,
    "gn:feature_class":"P",
    "gn:feature_code":"PPL",
    "gn:name":"Xiadianzi",
    "gn:population":0,
    "gn:timezone":"Asia/Shanghai",
    "iso:country":"CN",
    "name:und_x_variant":[
        "\u4e0b\u7538\u5b50"
    ],
    "wof:name":"Xiadianzi",
    "wof:placetype":"locality"
},
  "geometry": {"coordinates":[123.8777,40.73777000000001],"type":"Point"}
}