{
  "type": "Feature",
  "properties": {
    "gn:admin1_code":"26.0",
    "gn:asciiname":"Huazuigou",
    "gn:country_code":"CN",
    "gn:dem":580,
    "gn:feature_class":"P",
    "gn:feature_code":"PPL",
    "gn:name":"Huazuigou",
    "gn:population":0,
    "gn:timezone":"Asia/Shanghai",
    "iso:country":"CN",
    "name:zho_x_preferred":[
        "\u94e7\u5480\u6c9f"
    ],
    "wof:name":"Huazuigou",
    "wof:placetype":"locality"
},
  "geometry": {"coordinates":[109.30191000000001,34.20289],"type":"Point"}
}