{
  "type": "Feature",
  "properties": {
    "gn:admin1_code":"11.0",
    "gn:asciiname":"Doushanli",
    "gn:country_code":"CN",
    "gn:dem":1381,
    "gn:feature_class":"P",
    "gn:feature_code":"PPL",
    "gn:name":"Doushanli",
    "gn:population":0,
    "gn:timezone":"Asia/Shanghai",
    "iso:country":"CN",
    "name:zho_x_preferred":[
        "\u9661\u5c71\u91cc"
    ],
    "wof:name":"Doushanli",
    "wof:placetype":"locality"
},
  "geometry": {"coordinates":[110.59219,26.49329],"type":"Point"}
}