{
  "type": "Feature",
  "properties": {
    "gn:admin1_code":"32.0",
    "gn:asciiname":"Xiaobu",
    "gn:country_code":"CN",
    "gn:dem":954,
    "gn:feature_class":"P",
    "gn:feature_code":"PPL",
    "gn:name":"Xiaobu",
    "gn:population":0,
    "gn:timezone":"Asia/Shanghai",
    "iso:country":"CN",
    "name:zho_x_preferred":[
        "\u5c0f\u5821"
    ],
    "wof:name":"Xiaobu",
    "wof:placetype":"locality"
},
  "geometry": {"coordinates":[105.97138,27.95161],"type":"Point"}
}