{
  "type": "Feature",
  "properties": {
    "gn:admin1_code":"24.0",
    "gn:asciiname":"Qinjiahe",
    "gn:country_code":"CN",
    "gn:dem":1238,
    "gn:feature_class":"P",
    "gn:feature_code":"PPL",
    "gn:name":"Qinjiahe",
    "gn:population":0,
    "gn:timezone":"Asia/Shanghai",
    "iso:country":"CN",
    "name:zho_x_preferred":[
        "\u79e6\u5bb6\u6cb3"
    ],
    "wof:name":"Qinjiahe",
    "wof:placetype":"locality"
},
  "geometry": {"coordinates":[111.19448,38.77336],"type":"Point"}
}