{
  "type": "Feature",
  "properties": {
    "gn:admin1_code":"11.0",
    "gn:asciiname":"Shatangchong",
    "gn:country_code":"CN",
    "gn:dem":58,
    "gn:feature_class":"P",
    "gn:feature_code":"PPL",
    "gn:name":"Shatangchong",
    "gn:population":0,
    "gn:timezone":"Asia/Shanghai",
    "iso:country":"CN",
    "name:zho_x_preferred":[
        "\u6749\u5858\u51b2"
    ],
    "wof:name":"Shatangchong",
    "wof:placetype":"locality"
},
  "geometry": {"coordinates":[112.93973,27.7432],"type":"Point"}
}