{
  "type": "Feature",
  "properties": {
    "gn:admin1_code":"26.0",
    "gn:asciiname":"Xiaoyan",
    "gn:country_code":"CN",
    "gn:dem":1236,
    "gn:feature_class":"P",
    "gn:feature_code":"PPL",
    "gn:name":"Xiaoyan",
    "gn:population":0,
    "gn:timezone":"Asia/Shanghai",
    "iso:country":"CN",
    "name:zho_x_preferred":[
        "\u5c0f\u5830"
    ],
    "wof:name":"Xiaoyan",
    "wof:placetype":"locality"
},
  "geometry": {"coordinates":[108.11807,33.39521],"type":"Point"}
}