{
  "type": "Feature",
  "properties": {
    "gn:admin1_code":"23.0",
    "gn:asciiname":"Baowei",
    "gn:country_code":"CN",
    "gn:dem":5,
    "gn:feature_class":"P",
    "gn:feature_code":"PPL",
    "gn:name":"Baowei",
    "gn:population":0,
    "gn:timezone":"Asia/Shanghai",
    "iso:country":"CN",
    "name:zho_x_preferred":[
        "Baowei"
    ],
    "name:zho_x_variant":[
        "\u4fdd\u536b"
    ],
    "wof:name":"Baowei",
    "wof:placetype":"locality"
},
  "geometry": {"coordinates":[121.04178,31.06046],"type":"Point"}
}