{
  "type": "Feature",
  "properties": {
    "gn:admin1_code":"11.0",
    "gn:asciiname":"Minjia Dawu",
    "gn:country_code":"CN",
    "gn:dem":34,
    "gn:feature_class":"P",
    "gn:feature_code":"PPL",
    "gn:name":"Minjia Dawu",
    "gn:population":0,
    "gn:timezone":"Asia/Shanghai",
    "iso:country":"CN",
    "name:zho_x_preferred":[
        "\u95f5\u5bb6\u5927\u5c4b"
    ],
    "wof:name":"Minjia Dawu",
    "wof:placetype":"locality"
},
  "geometry": {"coordinates":[112.93119,28.67635],"type":"Point"}
}