{
  "type": "Feature",
  "properties": {
    "gn:admin1_code":"4.0",
    "gn:asciiname":"Shaojiaga",
    "gn:country_code":"CN",
    "gn:dem":6,
    "gn:feature_class":"P",
    "gn:feature_code":"PPL",
    "gn:name":"Shaojiaga",
    "gn:population":0,
    "gn:timezone":"Asia/Shanghai",
    "iso:country":"CN",
    "name:und_x_variant":[
        "\u90b5\u5bb6\u65ee"
    ],
    "name:zho_x_preferred":[
        "\u90b5\u5bb6\u65ee"
    ],
    "wof:name":"Shaojiaga",
    "wof:placetype":"locality"
},
  "geometry": {"coordinates":[120.02392999999999,31.51374],"type":"Point"}
}