{
  "type": "Feature",
  "properties": {
    "gn:admin1_code":"29.0",
    "gn:asciiname":"Pingpangzhai",
    "gn:country_code":"CN",
    "gn:dem":1631,
    "gn:feature_class":"P",
    "gn:feature_code":"PPL",
    "gn:name":"Pingpangzhai",
    "gn:population":0,
    "gn:timezone":"Asia/Shanghai",
    "iso:country":"CN",
    "name:zho_x_preferred":[
        "\u4e52\u4e53\u5be8"
    ],
    "wof:name":"Pingpangzhai",
    "wof:placetype":"locality"
},
  "geometry": {"coordinates":[99.76439999999999,24.8919],"type":"Point"}
}