{
  "type": "Feature",
  "properties": {
    "gn:admin1_code":"30",
    "gn:asciiname":"Jiebeicheng",
    "gn:country_code":"CN",
    "gn:dem":4,
    "gn:feature_class":"P",
    "gn:feature_code":"PPL",
    "gn:name":"Jiebeicheng",
    "gn:population":0,
    "gn:timezone":"Asia/Shanghai",
    "iso:country":"CN",
    "name:und_x_variant":[
        "\u78a3\u5317\u57ce"
    ],
    "name:zho_x_preferred":[
        "\u78a3\u5317\u57ce"
    ],
    "wof:name":"Jiebeicheng",
    "wof:placetype":"locality"
},
  "geometry": {"coordinates":[115.82306,22.79528],"type":"Point"}
}