{
  "type": "Feature",
  "properties": {
    "gn:admin1_code":"20.0",
    "gn:asciiname":"Lixiangou",
    "gn:country_code":"CN",
    "gn:dem":448,
    "gn:feature_class":"P",
    "gn:feature_code":"PPL",
    "gn:name":"Lixiangou",
    "gn:population":0,
    "gn:timezone":"Asia/Shanghai",
    "iso:country":"CN",
    "name:zho_x_preferred":[
        "\u674e\u5148\u6c9f"
    ],
    "wof:name":"Lixiangou",
    "wof:placetype":"locality"
},
  "geometry": {"coordinates":[122.71108,48.20676],"type":"Point"}
}