{
  "type": "Feature",
  "properties": {
    "gn:admin1_code":"19.0",
    "gn:asciiname":"Beiwafangdian",
    "gn:country_code":"CN",
    "gn:dem":89,
    "gn:feature_class":"P",
    "gn:feature_code":"PPL",
    "gn:name":"Beiwafangdian",
    "gn:population":0,
    "gn:timezone":"Asia/Shanghai",
    "iso:country":"CN",
    "name:und_x_variant":[
        "\u5317\u74e6\u623f\u5e97"
    ],
    "name:zho_x_preferred":[
        "\u5317\u74e6\u623f\u5e97"
    ],
    "wof:name":"Beiwafangdian",
    "wof:placetype":"locality"
},
  "geometry": {"coordinates":[122.14942000000001,39.9702],"type":"Point"}
}