{
  "type": "Feature",
  "properties": {
    "gn:admin1_code":"19.0",
    "gn:asciiname":"Yangzigou",
    "gn:country_code":"CN",
    "gn:dem":163,
    "gn:feature_class":"P",
    "gn:feature_code":"PPL",
    "gn:name":"Yangzigou",
    "gn:population":0,
    "gn:timezone":"Asia/Shanghai",
    "iso:country":"CN",
    "name:zho_x_preferred":[
        "\u6837\u5b50\u6c9f"
    ],
    "wof:name":"Yangzigou",
    "wof:placetype":"locality"
},
  "geometry": {"coordinates":[120.194,40.6605],"type":"Point"}
}