{
  "type": "Feature",
  "properties": {
    "gn:admin1_code":"04",
    "gn:asciiname":"Dachang",
    "gn:country_code":"CN",
    "gn:dem":29,
    "gn:feature_class":"P",
    "gn:feature_code":"PPL",
    "gn:name":"Dachang",
    "gn:population":0,
    "gn:timezone":"Asia/Shanghai",
    "iso:country":"CN",
    "name:und_x_variant":[
        "Ta-ch\u2019ang-chen",
        "Ch\u2019en-chia-wa",
        "Ta-ch\u2019ang",
        "Dachangzhen",
        "Dachang"
    ],
    "name:zho_x_preferred":[
        "\u5927\u5382"
    ],
    "wof:name":"Dachang",
    "wof:placetype":"locality"
},
  "geometry": {"coordinates":[118.75979,32.23294],"type":"Point"}
}