{
  "type": "Feature",
  "properties": {
    "gn:admin1_code":"12",
    "gn:asciiname":"Tiefosi",
    "gn:country_code":"CN",
    "gn:dem":1062,
    "gn:feature_class":"P",
    "gn:feature_code":"PPL",
    "gn:name":"Tiefosi",
    "gn:population":0,
    "gn:timezone":"Asia/Shanghai",
    "iso:country":"CN",
    "name:und_x_variant":[
        "T\u2019ieh-fo-ssu",
        "Tiefosi"
    ],
    "name:zho_x_preferred":[
        "\u94c1\u4f5b\u5bfa"
    ],
    "wof:name":"Tiefosi",
    "wof:placetype":"locality"
},
  "geometry": {"coordinates":[110.69396,33.07788],"type":"Point"}
}