{
  "type": "Feature",
  "properties": {
    "gn:admin1_code":"32.0",
    "gn:asciiname":"Honglian",
    "gn:country_code":"CN",
    "gn:dem":1735,
    "gn:feature_class":"P",
    "gn:feature_code":"PPL",
    "gn:name":"Honglian",
    "gn:population":0,
    "gn:timezone":"Asia/Shanghai",
    "iso:country":"CN",
    "name:zho_x_preferred":[
        "\u7ea2\u8054"
    ],
    "wof:name":"Honglian",
    "wof:placetype":"locality"
},
  "geometry": {"coordinates":[103.12867,27.5104],"type":"Point"}
}