{
  "type": "Feature",
  "properties": {
    "gn:admin1_code":"21.0",
    "gn:asciiname":"Nanhuang Jiquan",
    "gn:country_code":"CN",
    "gn:dem":1373,
    "gn:feature_class":"P",
    "gn:feature_code":"PPL",
    "gn:name":"Nanhuang Jiquan",
    "gn:population":0,
    "gn:timezone":"Asia/Shanghai",
    "iso:country":"CN",
    "name:zho_x_preferred":[
        "\u5357\u9ec4\u8bb0\u5708"
    ],
    "wof:name":"Nanhuang Jiquan",
    "wof:placetype":"locality"
},
  "geometry": {"coordinates":[107.36,37.7364],"type":"Point"}
}