{
  "type": "Feature",
  "properties": {
    "gn:admin1_code":"2.0",
    "gn:asciiname":"Xinjinggang",
    "gn:country_code":"CN",
    "gn:dem":6,
    "gn:feature_class":"P",
    "gn:feature_code":"PPL",
    "gn:name":"Xinjinggang",
    "gn:population":0,
    "gn:timezone":"Asia/Shanghai",
    "iso:country":"CN",
    "name:zho_x_preferred":[
        "\u65b0\u6cfe\u6e2f"
    ],
    "wof:name":"Xinjinggang",
    "wof:placetype":"locality"
},
  "geometry": {"coordinates":[121.03888000000001,30.78614],"type":"Point"}
}