{
  "type": "Feature",
  "properties": {
    "gn:admin1_code":"4.0",
    "gn:asciiname":"Guoqing",
    "gn:country_code":"CN",
    "gn:dem":5,
    "gn:feature_class":"P",
    "gn:feature_code":"PPL",
    "gn:name":"Guoqing",
    "gn:population":0,
    "gn:timezone":"Asia/Shanghai",
    "iso:country":"CN",
    "name:zho_x_preferred":[
        "\u56fd\u5e86"
    ],
    "wof:name":"Guoqing",
    "wof:placetype":"locality"
},
  "geometry": {"coordinates":[120.77929,32.07176],"type":"Point"}
}