{
  "type": "Feature",
  "properties": {
    "gn:admin1_code":"25",
    "gn:asciiname":"Cheli",
    "gn:country_code":"CN",
    "gn:dem":8,
    "gn:feature_class":"P",
    "gn:feature_code":"PPL",
    "gn:name":"Cheli",
    "gn:population":0,
    "gn:timezone":"Asia/Shanghai",
    "iso:country":"CN",
    "name:ast_x_preferred":[
        "Cheli"
    ],
    "name:fra_x_preferred":[
        "Cheli"
    ],
    "name:spa_x_preferred":[
        "Cheli"
    ],
    "name:zho_x_preferred":[
        "\u8f66\u91cc"
    ],
    "wof:name":"Cheli",
    "wof:placetype":"locality"
},
  "geometry": {"coordinates":[118.44705999999999,37.33724],"type":"Point"}
}