{
  "type": "Feature",
  "properties": {
    "gn:admin1_code":"26.0",
    "gn:asciiname":"Gaojialing",
    "gn:country_code":"CN",
    "gn:dem":595,
    "gn:feature_class":"P",
    "gn:feature_code":"PPLA4",
    "gn:name":"Gaojialing",
    "gn:population":0,
    "gn:timezone":"Asia/Shanghai",
    "iso:country":"CN",
    "name:und_x_variant":[
        "\u9ad8\u5bb6\u5cad"
    ],
    "wof:name":"Gaojialing",
    "wof:placetype":"locality"
},
  "geometry": {"coordinates":[107.03304,32.93458],"type":"Point"}
}