{
  "type": "Feature",
  "properties": {
    "gn:admin1_code":"8.0",
    "gn:asciiname":"Lujiangtun",
    "gn:country_code":"CN",
    "gn:dem":306,
    "gn:feature_class":"P",
    "gn:feature_code":"PPL",
    "gn:name":"L\u00fcjiangtun",
    "gn:population":0,
    "gn:timezone":"Asia/Shanghai",
    "iso:country":"CN",
    "name:und_x_variant":[
        "L\u00fcjiangtun"
    ],
    "name:zho_x_preferred":[
        "\u5415\u6c5f\u5c6f"
    ],
    "wof:name":"Lujiangtun",
    "wof:placetype":"locality"
},
  "geometry": {"coordinates":[126.10938,48.43008],"type":"Point"}
}