{
  "type": "Feature",
  "properties": {
    "gn:admin1_code":"33.0",
    "gn:asciiname":"Qingyuan",
    "gn:country_code":"CN",
    "gn:dem":596,
    "gn:feature_class":"P",
    "gn:feature_code":"PPL",
    "gn:name":"Qingyuan",
    "gn:population":0,
    "gn:timezone":"Asia/Shanghai",
    "iso:country":"CN",
    "name:ara_x_preferred":[
        "\u0643\u064a\u0646\u063a\u0648\u0627\u0646"
    ],
    "name:cdo_x_preferred":[
        "Ch\u012dng-u\u014dng"
    ],
    "name:ceb_x_preferred":[
        "Qingyuan"
    ],
    "name:ces_x_preferred":[
        "\u010cching-j\u00fcan"
    ],
    "name:cym_x_preferred":[
        "Qingyuan"
    ],
    "name:dan_x_preferred":[
        "Qingyuan"
    ],
    "name:deu_x_preferred":[
        "Qingyuan"
    ],
    "name:eus_x_preferred":[
        "Qingyuan"
    ],
    "name:fas_x_preferred":[
        "\u06a9\u06cc\u0646\u06af\u0648\u0627\u0646"
    ],
    "name:fin_x_preferred":[
        "Qingyuan"
    ],
    "name:fra_x_preferred":[
        "Qingyuan"
    ],
    "name:hak_x_preferred":[
        "Chh\u00een-y\u00e9n-s\u1e73"
    ],
    "name:hun_x_preferred":[
        "Qingyuan"
    ],
    "name:ita_x_preferred":[
        "Qingyuan"
    ],
    "name:jpn_x_preferred":[
        "\u6e05\u9060\u5e02"
    ],
    "name:kik_x_preferred":[
        "Qingyuan"
    ],
    "name:kor_x_preferred":[
        "\uce6d\uc704\uc548\uc2dc"
    ],
    "name:mlg_x_preferred":[
        "Qingyuan"
    ],
    "name:nld_x_preferred":[
        "Qingyuan"
    ],
    "name:nno_x_preferred":[
        "Qingyuan"
    ],
    "name:nor_x_preferred":[
        "Qingyuan"
    ],
    "name:pam_x_preferred":[
        "Qingyuan"
    ],
    "name:pnb_x_preferred":[
        "\u0686\u0646\u06af\u06cc\u0648\u0622\u0646"
    ],
    "name:pol_x_preferred":[
        "Qingyuan"
    ],
    "name:por_x_preferred":[
        "Qingyuan"
    ],
    "name:rus_x_preferred":[
        "\u0426\u0438\u043d\u044a\u044e\u0430\u043d\u044c"
    ],
    "name:spa_x_preferred":[
        "Qingyuan"
    ],
    "name:swa_x_preferred":[
        "Qingyuan"
    ],
    "name:swe_x_preferred":[
        "Qingyuan"
    ],
    "name:tur_x_preferred":[
        "Qingyuan"
    ],
    "name:urd_x_preferred":[
        "\u0686\u06cc\u0646\u06af\u06cc\u0648\u0627\u0646"
    ],
    "name:vie_x_preferred":[
        "Thanh Vi\u1ec5n"
    ],
    "name:war_x_preferred":[
        "Qingyuan"
    ],
    "name:zho_x_preferred":[
        "\u9752\u5143"
    ],
    "name:zho_x_variant":[
        "\u6e05\u8fdc\u5e02"
    ],
    "wof:name":"Qingyuan",
    "wof:placetype":"locality"
},
  "geometry": {"coordinates":[108.83566999999999,29.43039],"type":"Point"}
}