{
  "type": "Feature",
  "properties": {
    "gn:admin1_code":"26.0",
    "gn:asciiname":"Dundunshi",
    "gn:country_code":"CN",
    "gn:dem":1198,
    "gn:feature_class":"P",
    "gn:feature_code":"PPL",
    "gn:name":"Dundunshi",
    "gn:population":0,
    "gn:timezone":"Asia/Shanghai",
    "iso:country":"CN",
    "name:und_x_variant":[
        "\u58a9\u58a9\u77f3"
    ],
    "wof:name":"Dundunshi",
    "wof:placetype":"locality"
},
  "geometry": {"coordinates":[106.87085999999999,33.57288],"type":"Point"}
}