{
  "type": "Feature",
  "properties": {
    "gn:admin1_code":"30.0",
    "gn:asciiname":"Kuigang",
    "gn:country_code":"CN",
    "gn:dem":5,
    "gn:feature_class":"P",
    "gn:feature_code":"PPL",
    "gn:name":"Kuigang",
    "gn:population":0,
    "gn:timezone":"Asia/Shanghai",
    "iso:country":"CN",
    "name:zho_x_preferred":[
        "\u9b41\u5c97"
    ],
    "wof:name":"Kuigang",
    "wof:placetype":"locality"
},
  "geometry": {"coordinates":[112.59211999999999,22.38232],"type":"Point"}
}