{
  "type": "Feature",
  "properties": {
    "gn:admin1_code":"29.0",
    "gn:asciiname":"Baluotian",
    "gn:country_code":"CN",
    "gn:dem":792,
    "gn:feature_class":"P",
    "gn:feature_code":"PPL",
    "gn:name":"Baluotian",
    "gn:population":0,
    "gn:timezone":"Asia/Shanghai",
    "iso:country":"CN",
    "name:zho_x_preferred":[
        "\u516b\u7ba9\u7530"
    ],
    "wof:name":"Baluotian",
    "wof:placetype":"locality"
},
  "geometry": {"coordinates":[98.87220000000001,25.4282],"type":"Point"}
}