{
  "type": "Feature",
  "properties": {
    "gn:admin1_code":"24.0",
    "gn:asciiname":"Mahuicun",
    "gn:country_code":"CN",
    "gn:dem":1714,
    "gn:feature_class":"P",
    "gn:feature_code":"PPL",
    "gn:name":"Mahuicun",
    "gn:population":0,
    "gn:timezone":"Asia/Shanghai",
    "iso:country":"CN",
    "name:und_x_variant":[
        "\u9ebb\u4f1a\u6751"
    ],
    "name:zho_x_preferred":[
        "\u9ebb\u4f1a\u6751"
    ],
    "wof:name":"Mahuicun",
    "wof:placetype":"locality"
},
  "geometry": {"coordinates":[113.37079,39.3766],"type":"Point"}
}