{
  "type": "Feature",
  "properties": {
    "gn:admin1_code":"04",
    "gn:asciiname":"Baqiao",
    "gn:country_code":"CN",
    "gn:dem":6,
    "gn:feature_class":"P",
    "gn:feature_code":"PPLA4",
    "gn:name":"Baqiao",
    "gn:population":0,
    "gn:timezone":"Asia/Shanghai",
    "iso:country":"CN",
    "name:und_x_variant":[
        "Pa-tzu-ch\u2019iao",
        "Baqiao Zhen",
        "Pa-ch\u2019iao-chen",
        "Baqiao"
    ],
    "name:zho_x_preferred":[
        "\u516b\u6865"
    ],
    "name:zho_x_variant":[
        "\u516b\u6865\u9547"
    ],
    "wof:name":"Baqiao",
    "wof:placetype":"locality"
},
  "geometry": {"coordinates":[119.58244000000001,32.67975999999999],"type":"Point"}
}