{
  "type": "Feature",
  "properties": {
    "gn:admin1_code":"3.0",
    "gn:asciiname":"Hefangcun",
    "gn:country_code":"CN",
    "gn:dem":85,
    "gn:feature_class":"P",
    "gn:feature_code":"PPL",
    "gn:name":"Hefangcun",
    "gn:population":0,
    "gn:timezone":"Asia/Shanghai",
    "iso:country":"CN",
    "name:und_x_variant":[
        "\u4f55\u574a\u6751"
    ],
    "wof:name":"Hefangcun",
    "wof:placetype":"locality"
},
  "geometry": {"coordinates":[116.64111,28.20491],"type":"Point"}
}