{
  "type": "Feature",
  "properties": {
    "gn:admin1_code":"3.0",
    "gn:asciiname":"Yujiawa",
    "gn:country_code":"CN",
    "gn:dem":22,
    "gn:feature_class":"P",
    "gn:feature_code":"PPL",
    "gn:name":"Yujiawa",
    "gn:population":0,
    "gn:timezone":"Asia/Shanghai",
    "iso:country":"CN",
    "name:und_x_variant":[
        "\u55bb\u5bb6\u6d3c"
    ],
    "wof:name":"Yujiawa",
    "wof:placetype":"locality"
},
  "geometry": {"coordinates":[116.12224999999999,28.48196],"type":"Point"}
}