{
  "type": "Feature",
  "properties": {
    "gn:admin1_code":"28",
    "gn:asciiname":"Qianshuang Liushu",
    "gn:country_code":"CN",
    "gn:dem":5,
    "gn:feature_class":"P",
    "gn:feature_code":"PPL",
    "gn:name":"Qianshuang Liushu",
    "gn:population":0,
    "gn:timezone":"Asia/Shanghai",
    "iso:country":"CN",
    "name:zho_x_preferred":[
        "\u524d\u53cc\u67f3\u6811"
    ],
    "wof:name":"Qianshuang Liushu",
    "wof:placetype":"locality"
},
  "geometry": {"coordinates":[117.00611000000001,38.925],"type":"Point"}
}