{
  "type": "Feature",
  "properties": {
    "gn:admin1_code":"11.0",
    "gn:asciiname":"Chacixi",
    "gn:country_code":"CN",
    "gn:dem":229,
    "gn:feature_class":"P",
    "gn:feature_code":"PPL",
    "gn:name":"Chacixi",
    "gn:population":0,
    "gn:timezone":"Asia/Shanghai",
    "iso:country":"CN",
    "name:zho_x_preferred":[
        "Chacixi"
    ],
    "name:zho_x_variant":[
        "\u67e5\u6b21\u6eaa"
    ],
    "wof:name":"Chacixi",
    "wof:placetype":"locality"
},
  "geometry": {"coordinates":[111.17941,29.54715],"type":"Point"}
}