{
  "type": "Feature",
  "properties": {
    "gn:admin1_code":"5.0",
    "gn:asciiname":"Sandong Sidui",
    "gn:country_code":"CN",
    "gn:dem":244,
    "gn:feature_class":"P",
    "gn:feature_code":"PPLF",
    "gn:name":"Sandong Sidui",
    "gn:population":0,
    "gn:timezone":"Asia/Shanghai",
    "iso:country":"CN",
    "name:und_x_variant":[
        "\u4e09\u6d1e\u56db\u961f"
    ],
    "wof:name":"Sandong Sidui",
    "wof:placetype":"locality"
},
  "geometry": {"coordinates":[129.74704,42.89451],"type":"Point"}
}