{
  "type": "Feature",
  "properties": {
    "gn:admin1_code":"26",
    "gn:asciiname":"Shizuiyi",
    "gn:cc2":"CN",
    "gn:country_code":"CN",
    "gn:dem":1089,
    "gn:feature_class":"P",
    "gn:feature_code":"PPL",
    "gn:name":"Shizuiyi",
    "gn:population":0,
    "gn:timezone":"Asia/Shanghai",
    "iso:country":"CN",
    "name:und_x_variant":[
        "Shih-tsui",
        "Shih-tsui-i",
        "Shizuiyi"
    ],
    "wof:name":"Shizuiyi",
    "wof:placetype":"locality"
},
  "geometry": {"coordinates":[110.15000000000001,37.31667],"type":"Point"}
}