{
  "type": "Feature",
  "properties": {
    "gn:admin1_code":"29.0",
    "gn:asciiname":"Yuhu",
    "gn:country_code":"CN",
    "gn:dem":2054,
    "gn:feature_class":"P",
    "gn:feature_code":"PPLA3",
    "gn:name":"Yuhu",
    "gn:population":0,
    "gn:timezone":"Asia/Shanghai",
    "iso:country":"CN",
    "name:und_x_variant":[
        "Eryuan",
        "Lankiunghsien",
        "Erh-yuan",
        "Y\u00fc-hu-chen",
        "Langkiunghsien",
        "Lankiung",
        "Yuhu"
    ],
    "name:zho_x_preferred":[
        "Lang-ch\u2019iung"
    ],
    "name:zho_x_variant":[
        "Lan-ch\u2019iung",
        "\u7389\u6e56",
        "Y\u00fc-hu-chen"
    ],
    "wof:name":"Yuhu",
    "wof:placetype":"locality"
},
  "geometry": {"coordinates":[99.98291999999999,26.10679],"type":"Point"}
}