{
  "type": "Feature",
  "properties": {
    "gn:admin1_code":"29.0",
    "gn:asciiname":"Yuhu",
    "gn:country_code":"CN",
    "gn:dem":2054,
    "gn:feature_class":"P",
    "gn:feature_code":"PPLA3",
    "gn:name":"Yuhu",
    "gn:population":0,
    "gn:timezone":"Asia/Shanghai",
    "iso:country":"CN",
    "name:deu_x_preferred":[
        "Eryuan"
    ],
    "name:fas_x_preferred":[
        "\u0634\u0647\u0631\u0633\u062a\u0627\u0646 \u0627\u0631\u06cc\u0648\u0627\u0646"
    ],
    "name:fra_x_preferred":[
        "Xian d'Eryuan"
    ],
    "name:jpn_x_preferred":[
        "\u30b8\u6e90\u770c"
    ],
    "name:kor_x_preferred":[
        "\uc5bc\uc704\uc548\ud604"
    ],
    "name:nor_x_preferred":[
        "Eryuan"
    ],
    "name:swe_x_preferred":[
        "Eryuan"
    ],
    "name:und_x_variant":[
        "Lankiunghsien",
        "Erh-yuan",
        "Langkiunghsien",
        "Lankiung",
        "Yuhu"
    ],
    "name:urd_x_preferred":[
        "\u0639\u0631\u06cc\u0648\u0627\u0646 \u06a9\u0627\u0624\u0646\u0679\u06cc"
    ],
    "name:vie_x_preferred":[
        "Nh\u0129 Nguy\u00ean"
    ],
    "name:zho_x_preferred":[
        "Lang-ch\u2019iung"
    ],
    "name:zho_x_variant":[
        "Lan-ch\u2019iung",
        "\u7389\u6e56",
        "Y\u00fc-hu-chen",
        "\u6d31\u6e90\u53bf"
    ],
    "wof:name":"Yuhu",
    "wof:placetype":"locality"
},
  "geometry": {"coordinates":[99.98291999999999,26.10679],"type":"Point"}
}