{
  "type": "Feature",
  "properties": {
    "gn:admin1_code":"3.0",
    "gn:asciiname":"Xianzaotang",
    "gn:country_code":"CN",
    "gn:dem":464,
    "gn:feature_class":"P",
    "gn:feature_code":"PPL",
    "gn:name":"Xianzaotang",
    "gn:population":0,
    "gn:timezone":"Asia/Shanghai",
    "iso:country":"CN",
    "name:zho_x_preferred":[
        "\u732a\u6bdb\u575e"
    ],
    "wof:name":"Xianzaotang",
    "wof:placetype":"locality"
},
  "geometry": {"coordinates":[117.89749,28.19555],"type":"Point"}
}