{
  "type": "Feature",
  "properties": {
    "gn:admin1_code":"4.0",
    "gn:asciiname":"Yijing",
    "gn:country_code":"CN",
    "gn:dem":6,
    "gn:feature_class":"P",
    "gn:feature_code":"PPL",
    "gn:name":"Yijing",
    "gn:population":0,
    "gn:timezone":"Asia/Shanghai",
    "iso:country":"CN",
    "name:zho_x_preferred":[
        "\u9038\u6cfe"
    ],
    "wof:name":"Yijing",
    "wof:placetype":"locality"
},
  "geometry": {"coordinates":[120.95778,31.28109000000001],"type":"Point"}
}