{
  "type": "Feature",
  "properties": {
    "gn:admin1_code":"15.0",
    "gn:asciiname":"Hongjiatai",
    "gn:country_code":"CN",
    "gn:dem":1905,
    "gn:feature_class":"P",
    "gn:feature_code":"PPL",
    "gn:name":"Hongjiatai",
    "gn:population":0,
    "gn:timezone":"Asia/Shanghai",
    "iso:country":"CN",
    "name:zho_x_preferred":[
        "\u7ea2\u5bb6\u53f0"
    ],
    "wof:name":"Hongjiatai",
    "wof:placetype":"locality"
},
  "geometry": {"coordinates":[104.435,37.0538],"type":"Point"}
}