{
  "type": "Feature",
  "properties": {
    "gn:admin1_code":"09",
    "gn:asciiname":"Jianling",
    "gn:cc2":"CN",
    "gn:country_code":"CN",
    "gn:dem":123,
    "gn:feature_class":"P",
    "gn:feature_code":"PPL",
    "gn:name":"Jianling",
    "gn:population":0,
    "gn:timezone":"Asia/Shanghai",
    "iso:country":"CN",
    "name:und_x_variant":[
        "Chien-ling",
        "Jianling"
    ],
    "wof:name":"Jianling",
    "wof:placetype":"locality"
},
  "geometry": {"coordinates":[113.17471999999999,32.72],"type":"Point"}
}