{
  "type": "Feature",
  "properties": {
    "gn:admin1_code":"30.0",
    "gn:asciiname":"Tiekengtang",
    "gn:country_code":"CN",
    "gn:dem":204,
    "gn:feature_class":"P",
    "gn:feature_code":"PPL",
    "gn:name":"Tiekengtang",
    "gn:population":0,
    "gn:timezone":"Asia/Shanghai",
    "iso:country":"CN",
    "name:zho_x_preferred":[
        "\u94c1\u5751\u5858"
    ],
    "wof:name":"Tiekengtang",
    "wof:placetype":"locality"
},
  "geometry": {"coordinates":[112.1908,23.23078],"type":"Point"}
}