{
  "type": "Feature",
  "properties": {
    "gn:admin1_code":"19.0",
    "gn:asciiname":"Sishilicun",
    "gn:country_code":"CN",
    "gn:dem":16,
    "gn:feature_class":"P",
    "gn:feature_code":"PPL",
    "gn:name":"Sishilicun",
    "gn:population":0,
    "gn:timezone":"Asia/Shanghai",
    "iso:country":"CN",
    "name:zho_x_preferred":[
        "\u56db\u5341\u91cc\u6751"
    ],
    "wof:name":"Sishilicun",
    "wof:placetype":"locality"
},
  "geometry": {"coordinates":[121.794,39.2866],"type":"Point"}
}