{
  "type": "Feature",
  "properties": {
    "gn:admin1_code":"9",
    "gn:asciiname":"Yueyoufang",
    "gn:country_code":"CN",
    "gn:dem":49,
    "gn:feature_class":"P",
    "gn:feature_code":"PPL",
    "gn:name":"Yueyoufang",
    "gn:population":0,
    "gn:timezone":"Asia/Shanghai",
    "iso:country":"CN",
    "name:zho_x_preferred":[
        "\u5cb3\u6cb9\u574a"
    ],
    "wof:name":"Yueyoufang",
    "wof:placetype":"locality"
},
  "geometry": {"coordinates":[114.96299999999999,33.941],"type":"Point"}
}