{
  "type": "Feature",
  "properties": {
    "gn:admin1_code":"15.0",
    "gn:asciiname":"Shijiaquan",
    "gn:country_code":"CN",
    "gn:dem":2572,
    "gn:feature_class":"P",
    "gn:feature_code":"PPL",
    "gn:name":"Shijiaquan",
    "gn:population":0,
    "gn:timezone":"Asia/Shanghai",
    "iso:country":"CN",
    "name:zho_x_preferred":[
        "\u77f3\u5bb6\u6cc9"
    ],
    "wof:name":"Shijiaquan",
    "wof:placetype":"locality"
},
  "geometry": {"coordinates":[101.099,38.3375],"type":"Point"}
}