{
  "type": "Feature",
  "properties": {
    "gn:admin1_code":"5.0",
    "gn:asciiname":"Niuxindingzi",
    "gn:country_code":"CN",
    "gn:dem":440,
    "gn:feature_class":"P",
    "gn:feature_code":"PPL",
    "gn:name":"Niuxindingzi",
    "gn:population":0,
    "gn:timezone":"Asia/Shanghai",
    "iso:country":"CN",
    "name:und_x_variant":[
        "\u725b\u5fc3\u9876\u5b50"
    ],
    "wof:name":"Niuxindingzi",
    "wof:placetype":"locality"
},
  "geometry": {"coordinates":[125.73831,41.54058],"type":"Point"}
}