{
  "type": "Feature",
  "properties": {
    "gn:admin1_code":"12.0",
    "gn:asciiname":"Tongxingji",
    "gn:country_code":"CN",
    "gn:dem":34,
    "gn:feature_class":"P",
    "gn:feature_code":"PPL",
    "gn:name":"Tongxingji",
    "gn:population":0,
    "gn:timezone":"Asia/Shanghai",
    "iso:country":"CN",
    "name:zho_x_preferred":[
        "\u540c\u5174\u96c6"
    ],
    "wof:name":"Tongxingji",
    "wof:placetype":"locality"
},
  "geometry": {"coordinates":[113.77482999999999,30.5485],"type":"Point"}
}