{
  "type": "Feature",
  "properties": {
    "gn:admin1_code":"1.0",
    "gn:asciiname":"Dazhengcun",
    "gn:country_code":"CN",
    "gn:dem":25,
    "gn:feature_class":"P",
    "gn:feature_code":"PPL",
    "gn:name":"Dazhengcun",
    "gn:population":0,
    "gn:timezone":"Asia/Shanghai",
    "iso:country":"CN",
    "name:zho_x_preferred":[
        "\u5927\u90d1\u6751"
    ],
    "wof:name":"Dazhengcun",
    "wof:placetype":"locality"
},
  "geometry": {"coordinates":[118.36248999999999,32.10472],"type":"Point"}
}