{
  "type": "Feature",
  "properties": {
    "gn:admin1_code":"2.0",
    "gn:asciiname":"Jiangjiabang",
    "gn:country_code":"CN",
    "gn:dem":8,
    "gn:feature_class":"P",
    "gn:feature_code":"PPL",
    "gn:name":"Jiangjiabang",
    "gn:population":0,
    "gn:timezone":"Asia/Shanghai",
    "iso:country":"CN",
    "name:und_x_variant":[
        "\u59dc\u5bb6\u6d5c"
    ],
    "wof:name":"Jiangjiabang",
    "wof:placetype":"locality"
},
  "geometry": {"coordinates":[120.89928999999999,30.49268],"type":"Point"}
}