{
  "type": "Feature",
  "properties": {
    "gn:country":"CN",
    "gn:fcode":"PPLA4",
    "gn:pop":95433,
    "iso:country":"CN",
    "name:unk_x_variant":[
        "San Ka Mun"
    ],
    "qs:name":"Shenjiamen",
    "qs:photos_9r":0,
    "qs:photos_sr":0,
    "qs:pop_sr":"8",
    "wof:name":"Shenjiamen",
    "wof:placetype":"locality",
    "wof:population":95433
},
  "geometry": {"coordinates":[122.29801999999999,29.95762],"type":"Point"}
}