{
  "type": "Feature",
  "properties": {
    "gn:admin1_code":"29",
    "gn:asciiname":"Buqi",
    "gn:country_code":"CN",
    "gn:dem":1635,
    "gn:feature_class":"P",
    "gn:feature_code":"PPL",
    "gn:name":"Buqi",
    "gn:population":0,
    "gn:timezone":"Asia/Shanghai",
    "iso:country":"CN",
    "name:zho_x_preferred":[
        "\u8865\u5176"
    ],
    "wof:name":"Buqi",
    "wof:placetype":"locality"
},
  "geometry": {"coordinates":[103.45999999999999,24.1758],"type":"Point"}
}