{
  "type": "Feature",
  "properties": {
    "gn:admin1_code":"2",
    "gn:asciiname":"Xugongyang",
    "gn:country_code":"CN",
    "gn:dem":877,
    "gn:feature_class":"P",
    "gn:feature_code":"PPL",
    "gn:name":"Xugongyang",
    "gn:population":0,
    "gn:timezone":"Asia/Shanghai",
    "iso:country":"CN",
    "name:zho_x_preferred":[
        "\u5f90\u516c\u579f"
    ],
    "wof:name":"Xugongyang",
    "wof:placetype":"locality"
},
  "geometry": {"coordinates":[119.68667000000001,27.86861],"type":"Point"}
}