{
  "type": "Feature",
  "properties": {
    "gn:admin1_code":"8.0",
    "gn:asciiname":"Dongjia Youfang",
    "gn:country_code":"CN",
    "gn:dem":185,
    "gn:feature_class":"P",
    "gn:feature_code":"PPL",
    "gn:name":"Dongjia Youfang",
    "gn:population":0,
    "gn:timezone":"Asia/Shanghai",
    "iso:country":"CN",
    "name:zho_x_preferred":[
        "\u8463\u5bb6\u6cb9\u574a"
    ],
    "wof:name":"Dongjia Youfang",
    "wof:placetype":"locality"
},
  "geometry": {"coordinates":[126.8944,45.45148],"type":"Point"}
}