{
  "type": "Feature",
  "properties": {
    "gn:admin1_code":"14.0",
    "gn:asciiname":"Angka",
    "gn:country_code":"CN",
    "gn:dem":4114,
    "gn:feature_class":"P",
    "gn:feature_code":"PPL",
    "gn:name":"Angka",
    "gn:population":0,
    "gn:timezone":"Asia/Urumqi",
    "iso:country":"CN",
    "name:zho_x_preferred":[
        "\u6602\u5361"
    ],
    "wof:name":"Angka",
    "wof:placetype":"locality"
},
  "geometry": {"coordinates":[96.31589,30.70887],"type":"Point"}
}