{
  "type": "Feature",
  "properties": {
    "gn:admin1_code":"12.0",
    "gn:asciiname":"Qijiaoping",
    "gn:country_code":"CN",
    "gn:dem":965,
    "gn:feature_class":"P",
    "gn:feature_code":"PPL",
    "gn:name":"Qijiaoping",
    "gn:population":0,
    "gn:timezone":"Asia/Shanghai",
    "iso:country":"CN",
    "name:zho_x_preferred":[
        "\u4e03\u89d2\u576a"
    ],
    "wof:name":"Qijiaoping",
    "wof:placetype":"locality"
},
  "geometry": {"coordinates":[110.83071,31.47779],"type":"Point"}
}