{
  "type": "Feature",
  "properties": {
    "gn:admin1_code":"14.0",
    "gn:asciiname":"Damao Jiaoriwa",
    "gn:country_code":"CN",
    "gn:dem":3589,
    "gn:feature_class":"P",
    "gn:feature_code":"PPL",
    "gn:name":"Damao Jiaoriwa",
    "gn:population":0,
    "gn:timezone":"Asia/Urumqi",
    "iso:country":"CN",
    "name:zho_x_preferred":[
        "\u5927\u5192\u7ede\u65e5\u74e6"
    ],
    "wof:name":"Damao Jiaoriwa",
    "wof:placetype":"locality"
},
  "geometry": {"coordinates":[96.58625000000001,31.67403],"type":"Point"}
}