{
  "type": "Feature",
  "properties": {
    "gn:admin1_code":"5.0",
    "gn:asciiname":"Qianda Yushu",
    "gn:country_code":"CN",
    "gn:dem":142,
    "gn:feature_class":"P",
    "gn:feature_code":"PPL",
    "gn:name":"Qianda Yushu",
    "gn:population":0,
    "gn:timezone":"Asia/Shanghai",
    "iso:country":"CN",
    "name:zho_x_preferred":[
        "\u524d\u5927\u6986\u6811"
    ],
    "wof:name":"Qianda Yushu",
    "wof:placetype":"locality"
},
  "geometry": {"coordinates":[123.73039,45.06646],"type":"Point"}
}