{
  "type": "Feature",
  "properties": {
    "gn:admin1_code":"16.0",
    "gn:asciiname":"Zhongna",
    "gn:country_code":"CN",
    "gn:dem":688,
    "gn:feature_class":"P",
    "gn:feature_code":"PPL",
    "gn:name":"Zhongna",
    "gn:population":0,
    "gn:timezone":"Asia/Shanghai",
    "iso:country":"CN",
    "name:zho_x_preferred":[
        "\u4e2d\u90a3"
    ],
    "wof:name":"Zhongna",
    "wof:placetype":"locality"
},
  "geometry": {"coordinates":[106.271,23.601],"type":"Point"}
}