{
  "type": "Feature",
  "properties": {
    "gn:admin1_code":"5.0",
    "gn:asciiname":"Huangpingyang",
    "gn:country_code":"CN",
    "gn:dem":255,
    "gn:feature_class":"P",
    "gn:feature_code":"PPL",
    "gn:name":"Huangpingyang",
    "gn:population":0,
    "gn:timezone":"Asia/Shanghai",
    "iso:country":"CN",
    "name:und_x_variant":[
        "\u8352\u576a\u6d0b"
    ],
    "wof:name":"Huangpingyang",
    "wof:placetype":"locality"
},
  "geometry": {"coordinates":[129.67615000000001,43.35332],"type":"Point"}
}