{
  "type": "Feature",
  "properties": {
    "gn:admin1_code":"14.0",
    "gn:asciiname":"Guiqiong",
    "gn:country_code":"CN",
    "gn:dem":4787,
    "gn:feature_class":"P",
    "gn:feature_code":"PPL",
    "gn:name":"Guiqiong",
    "gn:population":0,
    "gn:timezone":"Asia/Urumqi",
    "iso:country":"CN",
    "name:zho_x_preferred":[
        "\u5f52\u7a77"
    ],
    "wof:name":"Guiqiong",
    "wof:placetype":"locality"
},
  "geometry": {"coordinates":[90.14960000000001,29.63094],"type":"Point"}
}