{
  "type": "Feature",
  "properties": {
    "gn:admin1_code":"19.0",
    "gn:asciiname":"Heshen",
    "gn:country_code":"CN",
    "gn:dem":25,
    "gn:feature_class":"P",
    "gn:feature_code":"PPL",
    "gn:name":"Heshen",
    "gn:population":0,
    "gn:timezone":"Asia/Shanghai",
    "iso:country":"CN",
    "name:und_x_variant":[
        "\u548c\u7533"
    ],
    "name:zho_x_preferred":[
        "\u548c\u7533"
    ],
    "wof:name":"Heshen",
    "wof:placetype":"locality"
},
  "geometry": {"coordinates":[122.324,41.7855],"type":"Point"}
}