{
  "type": "Feature",
  "properties": {
    "gn:admin1_code":"19.0",
    "gn:asciiname":"Heshen",
    "gn:country_code":"CN",
    "gn:dem":25,
    "gn:feature_class":"P",
    "gn:feature_code":"PPL",
    "gn:name":"Heshen",
    "gn:population":0,
    "gn:timezone":"Asia/Shanghai",
    "iso:country":"CN",
    "name:ara_x_preferred":[
        "\u062e\u0648 \u0634\u064a\u0646"
    ],
    "name:cat_x_preferred":[
        "Heshen"
    ],
    "name:cdo_x_preferred":[
        "Hu\u00f2-s\u012dng"
    ],
    "name:deu_x_preferred":[
        "Heshen"
    ],
    "name:fra_x_preferred":[
        "Heshen"
    ],
    "name:jpn_x_preferred":[
        "\u30d8\u30b7\u30a7\u30f3"
    ],
    "name:kor_x_preferred":[
        "\ud654\uc2e0"
    ],
    "name:nld_x_preferred":[
        "Heshen"
    ],
    "name:nor_x_preferred":[
        "Heshen"
    ],
    "name:pol_x_preferred":[
        "Heshen"
    ],
    "name:rus_x_preferred":[
        "\u0425\u044d\u0448\u044d\u043d\u044c"
    ],
    "name:spa_x_preferred":[
        "Heshen"
    ],
    "name:swe_x_preferred":[
        "Heshen"
    ],
    "name:tha_x_preferred":[
        "\u0e40\u0e2b\u0e2d\u0e40\u0e0a\u0e34\u0e19"
    ],
    "name:vie_x_preferred":[
        "H\u00f2a Th\u00e2n"
    ],
    "name:zho_x_preferred":[
        "\u548c\u7533"
    ],
    "wof:name":"Heshen",
    "wof:placetype":"locality"
},
  "geometry": {"coordinates":[122.324,41.7855],"type":"Point"}
}