{
  "type": "Feature",
  "properties": {
    "gn:admin1_code":"24.0",
    "gn:asciiname":"Leijiayao",
    "gn:country_code":"CN",
    "gn:dem":1627,
    "gn:feature_class":"P",
    "gn:feature_code":"PPL",
    "gn:name":"Leijiayao",
    "gn:population":0,
    "gn:timezone":"Asia/Shanghai",
    "iso:country":"CN",
    "name:und_x_variant":[
        "\u96f7\u5bb6\u7a91"
    ],
    "wof:name":"Leijiayao",
    "wof:placetype":"locality"
},
  "geometry": {"coordinates":[112.04671,39.82466],"type":"Point"}
}