{
  "type": "Feature",
  "properties": {
    "gn:admin1_code":"07",
    "gn:asciiname":"Siketing",
    "gn:country_code":"CN",
    "gn:dem":194,
    "gn:feature_class":"P",
    "gn:feature_code":"PPL",
    "gn:name":"Siketing",
    "gn:population":0,
    "gn:timezone":"Asia/Shanghai",
    "iso:country":"CN",
    "name:zho_x_preferred":[
        "\u56db\u79d1\u4ead"
    ],
    "wof:name":"Siketing",
    "wof:placetype":"locality"
},
  "geometry": {"coordinates":[118.01709,25.91557],"type":"Point"}
}