{
  "type": "Feature",
  "properties": {
    "gn:admin1_code":"11.0",
    "gn:asciiname":"Lijiabian",
    "gn:country_code":"CN",
    "gn:dem":214,
    "gn:feature_class":"P",
    "gn:feature_code":"PPL",
    "gn:name":"Lijiabian",
    "gn:population":0,
    "gn:timezone":"Asia/Shanghai",
    "iso:country":"CN",
    "name:zho_x_preferred":[
        "\u793c\u4f73\u8fb9"
    ],
    "wof:name":"Lijiabian",
    "wof:placetype":"locality"
},
  "geometry": {"coordinates":[111.96969,27.92465],"type":"Point"}
}