{
  "type": "Feature",
  "properties": {
    "gn:admin1_code":"32.0",
    "gn:asciiname":"Xiatanggongmiao",
    "gn:country_code":"CN",
    "gn:dem":317,
    "gn:feature_class":"P",
    "gn:feature_code":"PPL",
    "gn:name":"Xiatanggongmiao",
    "gn:population":0,
    "gn:timezone":"Asia/Shanghai",
    "iso:country":"CN",
    "name:zho_x_preferred":[
        "\u4e0b\u5510\u516c\u5e99"
    ],
    "wof:name":"Xiatanggongmiao",
    "wof:placetype":"locality"
},
  "geometry": {"coordinates":[106.4109,31.08446],"type":"Point"}
}