{
  "type": "Feature",
  "properties": {
    "gn:admin1_code":"25.0",
    "gn:asciiname":"Hedongyujiacun",
    "gn:country_code":"CN",
    "gn:dem":30,
    "gn:feature_class":"P",
    "gn:feature_code":"PPL",
    "gn:name":"Hedongyujiacun",
    "gn:population":0,
    "gn:timezone":"Asia/Shanghai",
    "iso:country":"CN",
    "name:zho_x_preferred":[
        "\u6cb3\u4e1c\u4e8e\u5bb6\u6751"
    ],
    "wof:name":"Hedongyujiacun",
    "wof:placetype":"locality"
},
  "geometry": {"coordinates":[119.30432999999999,36.7552],"type":"Point"}
}