{
  "type": "Feature",
  "properties": {
    "gn:admin1_code":"12.0",
    "gn:asciiname":"Zhawutai",
    "gn:country_code":"CN",
    "gn:dem":27,
    "gn:feature_class":"P",
    "gn:feature_code":"PPL",
    "gn:name":"Zhawutai",
    "gn:population":0,
    "gn:timezone":"Asia/Shanghai",
    "iso:country":"CN",
    "name:zho_x_preferred":[
        "\u69a8\u5c4b\u53f0"
    ],
    "wof:name":"Zhawutai",
    "wof:placetype":"locality"
},
  "geometry": {"coordinates":[113.54411,30.72196],"type":"Point"}
}