{
  "type": "Feature",
  "properties": {
    "gn:admin1_code":"11.0",
    "gn:asciiname":"Shuidaokeng",
    "gn:country_code":"CN",
    "gn:dem":784,
    "gn:feature_class":"P",
    "gn:feature_code":"PPL",
    "gn:name":"Shuidaokeng",
    "gn:population":0,
    "gn:timezone":"Asia/Shanghai",
    "iso:country":"CN",
    "name:zho_x_preferred":[
        "\u6c34\u9053\u5751"
    ],
    "wof:name":"Shuidaokeng",
    "wof:placetype":"locality"
},
  "geometry": {"coordinates":[113.53857000000001,25.87154],"type":"Point"}
}