{
  "type": "Feature",
  "properties": {
    "gn:admin1_code":"12.0",
    "gn:asciiname":"Fengjiatian",
    "gn:country_code":"CN",
    "gn:dem":76,
    "gn:feature_class":"P",
    "gn:feature_code":"PPL",
    "gn:name":"Fengjiatian",
    "gn:population":0,
    "gn:timezone":"Asia/Shanghai",
    "iso:country":"CN",
    "name:zho_x_preferred":[
        "\u51af\u5bb6\u7530"
    ],
    "wof:name":"Fengjiatian",
    "wof:placetype":"locality"
},
  "geometry": {"coordinates":[114.52213999999999,31.25848],"type":"Point"}
}