{
  "type": "Feature",
  "properties": {
    "gn:admin1_code":"19.0",
    "gn:asciiname":"Nansandao",
    "gn:country_code":"CN",
    "gn:dem":78,
    "gn:feature_class":"P",
    "gn:feature_code":"PPL",
    "gn:name":"Nansandao",
    "gn:population":0,
    "gn:timezone":"Asia/Shanghai",
    "iso:country":"CN",
    "name:und_x_variant":[
        "\u5357\u4e09\u9053"
    ],
    "wof:name":"Nansandao",
    "wof:placetype":"locality"
},
  "geometry": {"coordinates":[122.70041999999999,40.73023],"type":"Point"}
}