{
  "type": "Feature",
  "properties": {
    "gn:admin1_code":"19",
    "gn:asciiname":"Bajiazi",
    "gn:cc2":"CN",
    "gn:country_code":"CN",
    "gn:dem":238,
    "gn:feature_class":"P",
    "gn:feature_code":"PPL",
    "gn:name":"Bajiazi",
    "gn:population":0,
    "gn:timezone":"Asia/Shanghai",
    "iso:country":"CN",
    "name:und_x_variant":[
        "Pa-chia-tzu",
        "Bajiazi"
    ],
    "wof:name":"Bajiazi",
    "wof:placetype":"locality"
},
  "geometry": {"coordinates":[123.89221999999999,41.58083],"type":"Point"}
}