{
  "type": "Feature",
  "properties": {
    "gn:admin1_code":"12.0",
    "gn:asciiname":"Xihe",
    "gn:country_code":"CN",
    "gn:dem":28,
    "gn:feature_class":"P",
    "gn:feature_code":"PPL",
    "gn:name":"Xihe",
    "gn:population":0,
    "gn:timezone":"Asia/Shanghai",
    "iso:country":"CN",
    "name:ceb_x_preferred":[
        "Xihe"
    ],
    "name:deu_x_preferred":[
        "Xihe"
    ],
    "name:fra_x_preferred":[
        "Xihe"
    ],
    "name:nor_x_preferred":[
        "Xihe"
    ],
    "name:swe_x_preferred":[
        "Xihe"
    ],
    "name:zho_x_preferred":[
        "\u897f\u6cb3"
    ],
    "wof:name":"Xihe",
    "wof:placetype":"locality"
},
  "geometry": {"coordinates":[112.59128,30.33637],"type":"Point"}
}