{
  "type": "Feature",
  "properties": {
    "gn:admin1_code":"15.0",
    "gn:asciiname":"Jianshiya",
    "gn:country_code":"CN",
    "gn:dem":2696,
    "gn:feature_class":"P",
    "gn:feature_code":"PPL",
    "gn:name":"Jianshiya",
    "gn:population":0,
    "gn:timezone":"Asia/Shanghai",
    "iso:country":"CN",
    "name:zho_x_preferred":[
        "\u5c16\u77f3\u5d16"
    ],
    "wof:name":"Jianshiya",
    "wof:placetype":"locality"
},
  "geometry": {"coordinates":[102.68899999999999,37.6076],"type":"Point"}
}