{
  "type": "Feature",
  "properties": {
    "gn:admin1_code":"18",
    "gn:asciiname":"Fake",
    "gn:country_code":"CN",
    "gn:dem":1686,
    "gn:feature_class":"P",
    "gn:feature_code":"PPL",
    "gn:name":"Fake",
    "gn:population":0,
    "gn:timezone":"Asia/Shanghai",
    "iso:country":"CN",
    "name:deu_x_preferred":[
        "Fake"
    ],
    "name:fra_x_preferred":[
        "Fake"
    ],
    "name:jpn_x_preferred":[
        "\u30d5\u30a7\u30a4\u30af"
    ],
    "name:kor_x_preferred":[
        "\ud398\uc774\ud06c"
    ],
    "name:nld_x_preferred":[
        "Fake"
    ],
    "name:rus_x_preferred":[
        "Fake"
    ],
    "name:spa_x_preferred":[
        "Fake"
    ],
    "name:zho_x_preferred":[
        "\u53d1\u514b"
    ],
    "wof:name":"Fake",
    "wof:placetype":"locality"
},
  "geometry": {"coordinates":[105.146,26.6512],"type":"Point"}
}