{
  "type": "Feature",
  "properties": {
    "gn:admin1_code":"14.0",
    "gn:asciiname":"Kuolacun",
    "gn:country_code":"CN",
    "gn:dem":3385,
    "gn:feature_class":"P",
    "gn:feature_code":"PPL",
    "gn:name":"Kuolacun",
    "gn:population":0,
    "gn:timezone":"Asia/Urumqi",
    "iso:country":"CN",
    "name:zho_x_preferred":[
        "\u62ec\u62c9\u6751"
    ],
    "wof:name":"Kuolacun",
    "wof:placetype":"locality"
},
  "geometry": {"coordinates":[96.04915,30.01928],"type":"Point"}
}