{
  "type": "Feature",
  "properties": {
    "gn:admin1_code":"14.0",
    "gn:asciiname":"Jingtou",
    "gn:country_code":"CN",
    "gn:dem":3799,
    "gn:feature_class":"P",
    "gn:feature_code":"PPL",
    "gn:name":"Jingtou",
    "gn:population":0,
    "gn:timezone":"Asia/Urumqi",
    "iso:country":"CN",
    "name:zho_x_preferred":[
        "\u7adf\u900f"
    ],
    "wof:name":"Jingtou",
    "wof:placetype":"locality"
},
  "geometry": {"coordinates":[98.32201999999999,31.70809],"type":"Point"}
}