{
  "type": "Feature",
  "properties": {
    "gn:admin1_code":"14",
    "gn:asciiname":"Yangxiongle",
    "gn:country_code":"CN",
    "gn:dem":4845,
    "gn:feature_class":"P",
    "gn:feature_code":"PPL",
    "gn:name":"Yangxiongle",
    "gn:population":0,
    "gn:timezone":"Asia/Urumqi",
    "iso:country":"CN",
    "name:zho_x_preferred":[
        "\u592e\u96c4\u52d2"
    ],
    "wof:name":"Yangxiongle",
    "wof:placetype":"locality"
},
  "geometry": {"coordinates":[88.1571,30.813],"type":"Point"}
}