{
  "type": "Feature",
  "properties": {
    "gn:admin1_code":"16.0",
    "gn:asciiname":"Sanhe",
    "gn:country_code":"CN",
    "gn:dem":34,
    "gn:feature_class":"P",
    "gn:feature_code":"PPL",
    "gn:name":"Sanhe",
    "gn:population":0,
    "gn:timezone":"Asia/Shanghai",
    "iso:country":"CN",
    "name:ceb_x_preferred":[
        "Sanhe"
    ],
    "name:deu_x_preferred":[
        "Sanhe"
    ],
    "name:nor_x_preferred":[
        "Sanhe"
    ],
    "name:zho_x_preferred":[
        "\u4e09\u6cb3"
    ],
    "wof:name":"Sanhe",
    "wof:placetype":"locality"
},
  "geometry": {"coordinates":[110.492,23.491],"type":"Point"}
}