{
  "type": "Feature",
  "properties": {
    "gn:admin1_code":"13.0",
    "gn:asciiname":"Kala Kuzi",
    "gn:country_code":"CN",
    "gn:dem":1510,
    "gn:feature_class":"P",
    "gn:feature_code":"PPL",
    "gn:name":"Kala Kuzi",
    "gn:population":0,
    "gn:timezone":"Asia/Shanghai",
    "iso:country":"CN",
    "name:und_x_variant":[
        "\u5580\u62c9\u5e93\u5b5c"
    ],
    "wof:name":"Kala Kuzi",
    "wof:placetype":"locality"
},
  "geometry": {"coordinates":[75.95913,38.89316],"type":"Point"}
}