{
  "type": "Feature",
  "properties": {
    "gn:admin1_code":"21",
    "gn:asciiname":"Quanhe",
    "gn:country_code":"CN",
    "gn:dem":2036,
    "gn:feature_class":"P",
    "gn:feature_code":"PPL",
    "gn:name":"Quanhe",
    "gn:population":0,
    "gn:timezone":"Asia/Shanghai",
    "iso:country":"CN",
    "wof:name":"Quanhe",
    "wof:placetype":"locality"
},
  "geometry": {"coordinates":[105.43333,35.85],"type":"Point"}
}