{
  "type": "Feature",
  "properties": {
    "gn:admin1_code":"30",
    "gn:asciiname":"Dalang",
    "gn:country_code":"CN",
    "gn:dem":50,
    "gn:feature_class":"P",
    "gn:feature_code":"PPL",
    "gn:name":"Dalang",
    "gn:population":0,
    "gn:timezone":"Asia/Urumqi",
    "iso:country":"CN",
    "name:zho_x_preferred":[
        "\u5927\u6717"
    ],
    "wof:name":"Dalang",
    "wof:placetype":"locality"
},
  "geometry": {"coordinates":[110.49318999999998,21.65327000000001],"type":"Point"}
}