{
  "type": "Feature",
  "properties": {
    "gn:admin1_code":"20.0",
    "gn:asciiname":"Dachengxi",
    "gn:country_code":"CN",
    "gn:dem":1587,
    "gn:feature_class":"P",
    "gn:feature_code":"PPL",
    "gn:name":"Dachengxi",
    "gn:population":0,
    "gn:timezone":"Asia/Shanghai",
    "iso:country":"CN",
    "name:und_x_variant":[
        "\u5927\u57ce\u897f"
    ],
    "wof:name":"Dachengxi",
    "wof:placetype":"locality"
},
  "geometry": {"coordinates":[110.20268,41.30938],"type":"Point"}
}