{
  "type": "Feature",
  "properties": {
    "gn:admin1_code":"32.0",
    "gn:asciiname":"Guzhou",
    "gn:country_code":"CN",
    "gn:dem":571,
    "gn:feature_class":"P",
    "gn:feature_code":"PPL",
    "gn:name":"Guzhou",
    "gn:population":0,
    "gn:timezone":"Asia/Shanghai",
    "iso:country":"CN",
    "name:zho_x_preferred":[
        "\u56fa\u5468"
    ],
    "wof:name":"Guzhou",
    "wof:placetype":"locality"
},
  "geometry": {"coordinates":[106.83799999999999,31.238],"type":"Point"}
}