{
  "type": "Feature",
  "properties": {
    "gn:admin1_code":"19.0",
    "gn:asciiname":"Houbeizitun",
    "gn:country_code":"CN",
    "gn:dem":69,
    "gn:feature_class":"P",
    "gn:feature_code":"PPL",
    "gn:name":"Houbeizitun",
    "gn:population":0,
    "gn:timezone":"Asia/Shanghai",
    "iso:country":"CN",
    "name:zho_x_preferred":[
        "\u4faf\u8d1d\u5b50\u5c6f"
    ],
    "name:zho_x_variant":[
        "\u5019\u8d1d\u5b50\u5c6f"
    ],
    "wof:name":"Houbeizitun",
    "wof:placetype":"locality"
},
  "geometry": {"coordinates":[122.054,41.8322],"type":"Point"}
}