{
  "type": "Feature",
  "properties": {
    "gn:admin1_code":"32.0",
    "gn:asciiname":"Shigengzi",
    "gn:country_code":"CN",
    "gn:dem":490,
    "gn:feature_class":"P",
    "gn:feature_code":"PPL",
    "gn:name":"Shigengzi",
    "gn:population":0,
    "gn:timezone":"Asia/Shanghai",
    "iso:country":"CN",
    "name:zho_x_preferred":[
        "\u77f3\u57c2\u5b50"
    ],
    "wof:name":"Shigengzi",
    "wof:placetype":"locality"
},
  "geometry": {"coordinates":[103.58727,30.17193],"type":"Point"}
}