{
  "type": "Feature",
  "properties": {
    "gn:admin1_code":"30",
    "gn:asciiname":"Dengtang",
    "gn:country_code":"CN",
    "gn:dem":20,
    "gn:feature_class":"P",
    "gn:feature_code":"PPLA4",
    "gn:name":"Dengtang",
    "gn:population":0,
    "gn:timezone":"Asia/Shanghai",
    "iso:country":"CN",
    "name:und_x_variant":[
        "Dengtang Zhen",
        "\u767b\u5858\u9547"
    ],
    "name:zho_x_preferred":[
        "\u767b\u5858"
    ],
    "wof:name":"Dengtang",
    "wof:placetype":"locality"
},
  "geometry": {"coordinates":[116.52591,23.68214],"type":"Point"}
}