{
  "type": "Feature",
  "properties": {
    "gn:admin1_code":"04",
    "gn:asciiname":"Houyangcun",
    "gn:country_code":"CN",
    "gn:dem":9,
    "gn:feature_class":"P",
    "gn:feature_code":"PPL",
    "gn:name":"Houyangcun",
    "gn:population":0,
    "gn:timezone":"Asia/Shanghai",
    "iso:country":"CN",
    "name:und_x_variant":[
        "Hou-yang-kan-chen",
        "Houyangwei",
        "Houyang",
        "Houyangcun"
    ],
    "name:zho_x_preferred":[
        "\u540e\u9633"
    ],
    "name:zho_x_variant":[
        "\u540e\u9633\u6751"
    ],
    "wof:name":"Houyangcun",
    "wof:placetype":"locality"
},
  "geometry": {"coordinates":[119.50988999999998,31.74829],"type":"Point"}
}