{
  "type": "Feature",
  "properties": {
    "gn:admin1_code":"15.0",
    "gn:asciiname":"Hongguozijing",
    "gn:country_code":"CN",
    "gn:dem":1452,
    "gn:feature_class":"P",
    "gn:feature_code":"PPL",
    "gn:name":"Hongguozijing",
    "gn:population":0,
    "gn:timezone":"Asia/Shanghai",
    "iso:country":"CN",
    "name:zho_x_preferred":[
        "\u7ea2\u679c\u5b50\u4e95"
    ],
    "wof:name":"Hongguozijing",
    "wof:placetype":"locality"
},
  "geometry": {"coordinates":[102.62,38.9937],"type":"Point"}
}