{
  "type": "Feature",
  "properties": {
    "gn:admin1_code":"18",
    "gn:asciiname":"Maodangzi",
    "gn:country_code":"CN",
    "gn:dem":1129,
    "gn:feature_class":"P",
    "gn:feature_code":"PPL",
    "gn:name":"Maodangzi",
    "gn:population":0,
    "gn:timezone":"Asia/Shanghai",
    "iso:country":"CN",
    "name:zho_x_preferred":[
        "\u6bdb\u51fc\u5b50"
    ],
    "wof:name":"Maodangzi",
    "wof:placetype":"locality"
},
  "geometry": {"coordinates":[105.131,25.0492],"type":"Point"}
}