{
  "type": "Feature",
  "properties": {
    "gn:admin1_code":"16.0",
    "gn:asciiname":"Linyang",
    "gn:country_code":"CN",
    "gn:dem":910,
    "gn:feature_class":"P",
    "gn:feature_code":"PPL",
    "gn:name":"Linyang",
    "gn:population":0,
    "gn:timezone":"Asia/Shanghai",
    "iso:country":"CN",
    "name:zho_x_preferred":[
        "\u6797\u7f8a"
    ],
    "wof:name":"Linyang",
    "wof:placetype":"locality"
},
  "geometry": {"coordinates":[106.843,24.3114],"type":"Point"}
}