{
  "type": "Feature",
  "properties": {
    "gn:admin1_code":"8.0",
    "gn:asciiname":"Majia Weizi",
    "gn:country_code":"CN",
    "gn:dem":198,
    "gn:feature_class":"P",
    "gn:feature_code":"PPL",
    "gn:name":"Majia Weizi",
    "gn:population":0,
    "gn:timezone":"Asia/Shanghai",
    "iso:country":"CN",
    "name:zho_x_preferred":[
        "\u9a6c\u5bb6\u56f4\u5b50"
    ],
    "wof:name":"Majia Weizi",
    "wof:placetype":"locality"
},
  "geometry": {"coordinates":[125.62376999999999,47.14612],"type":"Point"}
}