{
  "type": "Feature",
  "properties": {
    "gn:admin1_code":"12",
    "gn:asciiname":"Sanxi",
    "gn:country_code":"CN",
    "gn:dem":80,
    "gn:feature_class":"P",
    "gn:feature_code":"PPLA4",
    "gn:name":"Sanxi",
    "gn:population":0,
    "gn:timezone":"Asia/Shanghai",
    "iso:country":"CN",
    "name:und_x_variant":[
        "San-hsi-k\u2019ou",
        "Sanxikou",
        "Sanxi",
        "\u4e09\u6eaa",
        "Sanxi Zhen",
        "\u4e09\u6eaa\u9547"
    ],
    "wof:name":"Sanxi",
    "wof:placetype":"locality"
},
  "geometry": {"coordinates":[114.93978,29.82617],"type":"Point"}
}