{
  "type": "Feature",
  "properties": {
    "gn:admin1_code":"33.0",
    "gn:asciiname":"Shi'an",
    "gn:country_code":"CN",
    "gn:dem":262,
    "gn:feature_class":"P",
    "gn:feature_code":"PPLA4",
    "gn:name":"Shi\u2019an",
    "gn:population":0,
    "gn:timezone":"Asia/Shanghai",
    "iso:country":"CN",
    "name:und_x_variant":[
        "Shi\u2019an",
        "Shi\u2019an Zhen",
        "Shijiachang"
    ],
    "name:zho_x_preferred":[
        "\u77f3\u5b89"
    ],
    "name:zho_x_variant":[
        "\u77f3\u5b89\u9547",
        "\u77f3\u5bb6\u573a"
    ],
    "wof:name":"Shi'an",
    "wof:placetype":"locality"
},
  "geometry": {"coordinates":[107.97657,30.59028],"type":"Point"}
}