{
  "type": "Feature",
  "properties": {
    "gn:admin1_code":"33.0",
    "gn:asciiname":"Qingshui",
    "gn:country_code":"CN",
    "gn:dem":656,
    "gn:feature_class":"P",
    "gn:feature_code":"PPLA4",
    "gn:name":"Qingshui",
    "gn:population":0,
    "gn:timezone":"Asia/Shanghai",
    "iso:country":"CN",
    "name:ceb_x_preferred":[
        "Qingshui"
    ],
    "name:deu_x_preferred":[
        "Qingshui"
    ],
    "name:und_x_variant":[
        "Qingshui Tujiazu Xiang"
    ],
    "name:zho_x_preferred":[
        "\u6e05\u6c34"
    ],
    "name:zho_x_variant":[
        "\u6e05\u6c34\u571f\u5bb6\u65cf\u4e61"
    ],
    "wof:name":"Qingshui",
    "wof:placetype":"locality"
},
  "geometry": {"coordinates":[108.96809,30.70508],"type":"Point"}
}