{
  "type": "Feature",
  "properties": {
    "gn:admin1_code":"16.0",
    "gn:asciiname":"Tongyougen",
    "gn:country_code":"CN",
    "gn:dem":89,
    "gn:feature_class":"P",
    "gn:feature_code":"PPL",
    "gn:name":"Tongyougen",
    "gn:population":0,
    "gn:timezone":"Asia/Shanghai",
    "iso:country":"CN",
    "name:zho_x_preferred":[
        "\u6850\u6cb9\u6839"
    ],
    "wof:name":"Tongyougen",
    "wof:placetype":"locality"
},
  "geometry": {"coordinates":[110.27500000000001,22.0344],"type":"Point"}
}