{
  "type": "Feature",
  "properties": {
    "gn:admin1_code":"24",
    "gn:asciiname":"Wujiazhuang",
    "gn:country_code":"CN",
    "gn:dem":744,
    "gn:feature_class":"P",
    "gn:feature_code":"PPL",
    "gn:name":"Wujiazhuang",
    "gn:population":0,
    "gn:timezone":"Asia/Shanghai",
    "iso:country":"CN",
    "name:und_x_variant":[
        "Wu-chia-chuang",
        "Wujiazhuang"
    ],
    "name:zho_x_preferred":[
        "\u6b66\u5bb6\u5e84"
    ],
    "wof:name":"Wujiazhuang",
    "wof:placetype":"locality"
},
  "geometry": {"coordinates":[112.11912,37.32399],"type":"Point"}
}