{
  "type": "Feature",
  "properties": {
    "gn:admin1_code":"6.0",
    "gn:asciiname":"Laocang",
    "gn:country_code":"CN",
    "gn:dem":3214,
    "gn:feature_class":"P",
    "gn:feature_code":"PPL",
    "gn:name":"Laocang",
    "gn:population":0,
    "gn:timezone":"Asia/Shanghai",
    "iso:country":"CN",
    "name:zho_x_preferred":[
        "\u8001\u85cf"
    ],
    "wof:name":"Laocang",
    "wof:placetype":"locality"
},
  "geometry": {"coordinates":[101.89133,35.26638],"type":"Point"}
}