{
  "type": "Feature",
  "properties": {
    "gn:admin1_code":"3.0",
    "gn:asciiname":"Yankeng Yaojia",
    "gn:country_code":"CN",
    "gn:dem":72,
    "gn:feature_class":"P",
    "gn:feature_code":"PPL",
    "gn:name":"Yankeng Yaojia",
    "gn:population":0,
    "gn:timezone":"Asia/Shanghai",
    "iso:country":"CN",
    "name:und_x_variant":[
        "\u9122\u5751\u59da\u5bb6"
    ],
    "wof:name":"Yankeng Yaojia",
    "wof:placetype":"locality"
},
  "geometry": {"coordinates":[115.25275999999999,28.47764],"type":"Point"}
}