{
  "type": "Feature",
  "properties": {
    "gn:admin1_code":"29.0",
    "gn:asciiname":"Jingmengban",
    "gn:country_code":"CN",
    "gn:dem":718,
    "gn:feature_class":"P",
    "gn:feature_code":"PPL",
    "gn:name":"Jingmengban",
    "gn:population":0,
    "gn:timezone":"Asia/Shanghai",
    "iso:country":"CN",
    "name:zho_x_preferred":[
        "\u666f\u52d0\u677f"
    ],
    "wof:name":"Jingmengban",
    "wof:placetype":"locality"
},
  "geometry": {"coordinates":[100.205,21.7489],"type":"Point"}
}