{
  "type": "Feature",
  "properties": {
    "gn:admin1_code":"8.0",
    "gn:asciiname":"Dongbajiacun",
    "gn:country_code":"CN",
    "gn:dem":130,
    "gn:feature_class":"P",
    "gn:feature_code":"PPL",
    "gn:name":"Dongbajiacun",
    "gn:population":0,
    "gn:timezone":"Asia/Shanghai",
    "iso:country":"CN",
    "name:zho_x_preferred":[
        "\u4e1c\u516b\u5bb6\u6751"
    ],
    "wof:name":"Dongbajiacun",
    "wof:placetype":"locality"
},
  "geometry": {"coordinates":[126.66365,46.07629],"type":"Point"}
}