{
  "type": "Feature",
  "properties": {
    "gn:admin1_code":"3.0",
    "gn:asciiname":"Chongzaili",
    "gn:country_code":"CN",
    "gn:dem":516,
    "gn:feature_class":"P",
    "gn:feature_code":"PPL",
    "gn:name":"Chongzaili",
    "gn:population":0,
    "gn:timezone":"Asia/Shanghai",
    "iso:country":"CN",
    "name:zho_x_preferred":[
        "\u51b2\u4ed4\u91cc"
    ],
    "wof:name":"Chongzaili",
    "wof:placetype":"locality"
},
  "geometry": {"coordinates":[113.996,27.3471],"type":"Point"}
}