{
  "type": "Feature",
  "properties": {
    "gn:admin1_code":"18.0",
    "gn:asciiname":"Hongyantian",
    "gn:country_code":"CN",
    "gn:dem":724,
    "gn:feature_class":"P",
    "gn:feature_code":"PPL",
    "gn:name":"Hongyantian",
    "gn:population":0,
    "gn:timezone":"Asia/Shanghai",
    "iso:country":"CN",
    "name:zho_x_preferred":[
        "\u7ea2\u5ca9\u7530"
    ],
    "wof:name":"Hongyantian",
    "wof:placetype":"locality"
},
  "geometry": {"coordinates":[108.218,27.1049],"type":"Point"}
}