{
  "type": "Feature",
  "properties": {
    "gn:admin1_code":"4.0",
    "gn:asciiname":"Gangbian Sanzu",
    "gn:country_code":"CN",
    "gn:dem":6,
    "gn:feature_class":"P",
    "gn:feature_code":"PPLF",
    "gn:name":"Gangbian Sanzu",
    "gn:population":0,
    "gn:timezone":"Asia/Shanghai",
    "iso:country":"CN",
    "name:zho_x_preferred":[
        "\u6e2f\u8fb9\u4e09\u7ec4"
    ],
    "wof:name":"Gangbian Sanzu",
    "wof:placetype":"locality"
},
  "geometry": {"coordinates":[120.66955,32.8624],"type":"Point"}
}