{
  "type": "Feature",
  "properties": {
    "gn:admin1_code":"15",
    "gn:asciiname":"Heshuilaocheng",
    "gn:cc2":"CN",
    "gn:country_code":"CN",
    "gn:dem":1410,
    "gn:feature_class":"P",
    "gn:feature_code":"PPL",
    "gn:name":"Heshuilaocheng",
    "gn:population":0,
    "gn:timezone":"Asia/Shanghai",
    "iso:country":"CN",
    "name:und_x_variant":[
        "Ho-shui-lao-ch\u2019eng",
        "Heshuilaocheng"
    ],
    "wof:name":"Heshuilaocheng",
    "wof:placetype":"locality"
},
  "geometry": {"coordinates":[108.08333,36.03333],"type":"Point"}
}