{
  "type": "Feature",
  "properties": {
    "gn:admin1_code":"21.0",
    "gn:asciiname":"Xiangyang Liudui",
    "gn:country_code":"CN",
    "gn:dem":1100,
    "gn:feature_class":"P",
    "gn:feature_code":"PPLF",
    "gn:name":"Xiangyang Liudui",
    "gn:population":0,
    "gn:timezone":"Asia/Shanghai",
    "iso:country":"CN",
    "name:zho_x_preferred":[
        "\u5411\u9633\u516d\u961f"
    ],
    "wof:name":"Xiangyang Liudui",
    "wof:placetype":"locality"
},
  "geometry": {"coordinates":[106.23099999999999,38.8408],"type":"Point"}
}