{
  "type": "Feature",
  "properties": {
    "gn:admin1_code":"8.0",
    "gn:asciiname":"Nuanquanzitun",
    "gn:country_code":"CN",
    "gn:dem":154,
    "gn:feature_class":"P",
    "gn:feature_code":"PPL",
    "gn:name":"Nuanquanzitun",
    "gn:population":0,
    "gn:timezone":"Asia/Shanghai",
    "iso:country":"CN",
    "name:zho_x_preferred":[
        "\u6696\u6cc9\u5b50\u5c6f"
    ],
    "wof:name":"Nuanquanzitun",
    "wof:placetype":"locality"
},
  "geometry": {"coordinates":[125.00888999999999,47.11137],"type":"Point"}
}