{
  "type": "Feature",
  "properties": {
    "gn:admin1_code":"26.0",
    "gn:asciiname":"Youfangping",
    "gn:country_code":"CN",
    "gn:dem":1523,
    "gn:feature_class":"P",
    "gn:feature_code":"PPL",
    "gn:name":"Youfangping",
    "gn:population":0,
    "gn:timezone":"Asia/Shanghai",
    "iso:country":"CN",
    "name:und_x_variant":[
        "\u6cb9\u623f\u576a"
    ],
    "wof:name":"Youfangping",
    "wof:placetype":"locality"
},
  "geometry": {"coordinates":[106.80797,33.6623],"type":"Point"}
}