{
  "type": "Feature",
  "properties": {
    "gn:admin1_code":"5.0",
    "gn:asciiname":"Yugouzi",
    "gn:country_code":"CN",
    "gn:dem":816,
    "gn:feature_class":"P",
    "gn:feature_code":"PPL",
    "gn:name":"Yugouzi",
    "gn:population":0,
    "gn:timezone":"Asia/Shanghai",
    "iso:country":"CN",
    "name:und_x_variant":[
        "\u4e8e\u6c9f\u5b50"
    ],
    "wof:name":"Yugouzi",
    "wof:placetype":"locality"
},
  "geometry": {"coordinates":[127.2003,41.71126],"type":"Point"}
}