{
  "type": "Feature",
  "properties": {
    "gn:admin1_code":"15.0",
    "gn:asciiname":"Linjiaping",
    "gn:country_code":"CN",
    "gn:dem":1823,
    "gn:feature_class":"P",
    "gn:feature_code":"PPL",
    "gn:name":"Linjiaping",
    "gn:population":0,
    "gn:timezone":"Asia/Shanghai",
    "iso:country":"CN",
    "name:zho_x_preferred":[
        "\u853a\u5bb6\u576a"
    ],
    "wof:name":"Linjiaping",
    "wof:placetype":"locality"
},
  "geometry": {"coordinates":[105.29900000000001,34.9565],"type":"Point"}
}