{
  "type": "Feature",
  "properties": {
    "gn:admin1_code":"19.0",
    "gn:asciiname":"Shipenggou",
    "gn:country_code":"CN",
    "gn:dem":114,
    "gn:feature_class":"P",
    "gn:feature_code":"PPL",
    "gn:name":"Shipenggou",
    "gn:population":0,
    "gn:timezone":"Asia/Shanghai",
    "iso:country":"CN",
    "name:und_x_variant":[
        "\u77f3\u68da\u6c9f"
    ],
    "name:zho_x_preferred":[
        "\u77f3\u68da\u6c9f"
    ],
    "wof:name":"Shipenggou",
    "wof:placetype":"locality"
},
  "geometry": {"coordinates":[123.47978000000001,40.49242],"type":"Point"}
}