{
  "type": "Feature",
  "properties": {
    "gn:admin1_code":"32.0",
    "gn:asciiname":"Jianzhulin",
    "gn:country_code":"CN",
    "gn:dem":1240,
    "gn:feature_class":"P",
    "gn:feature_code":"PPL",
    "gn:name":"Jianzhulin",
    "gn:population":0,
    "gn:timezone":"Asia/Shanghai",
    "iso:country":"CN",
    "name:zho_x_preferred":[
        "\u7bad\u7af9\u6797"
    ],
    "wof:name":"Jianzhulin",
    "wof:placetype":"locality"
},
  "geometry": {"coordinates":[104.51836,32.22725],"type":"Point"}
}