{
  "type": "Feature",
  "properties": {
    "gn:admin1_code":"32.0",
    "gn:asciiname":"Huashi",
    "gn:country_code":"CN",
    "gn:dem":365,
    "gn:feature_class":"P",
    "gn:feature_code":"PPL",
    "gn:name":"Huashi",
    "gn:population":0,
    "gn:timezone":"Asia/Shanghai",
    "iso:country":"CN",
    "name:zho_x_preferred":[
        "\u534e\u5b9e"
    ],
    "wof:name":"Huashi",
    "wof:placetype":"locality"
},
  "geometry": {"coordinates":[104.99944000000001,30.62316],"type":"Point"}
}