{
  "type": "Feature",
  "properties": {
    "gn:admin1_code":"29.0",
    "gn:asciiname":"Shuiyanba",
    "gn:country_code":"CN",
    "gn:dem":1523,
    "gn:feature_class":"P",
    "gn:feature_code":"PPL",
    "gn:name":"Shuiyanba",
    "gn:population":0,
    "gn:timezone":"Asia/Shanghai",
    "iso:country":"CN",
    "name:zho_x_preferred":[
        "\u6c34\u6df9\u575d"
    ],
    "wof:name":"Shuiyanba",
    "wof:placetype":"locality"
},
  "geometry": {"coordinates":[104.321,23.1223],"type":"Point"}
}