{
  "type": "Feature",
  "properties": {
    "gn:admin1_code":"14.0",
    "gn:asciiname":"Chaqing",
    "gn:country_code":"CN",
    "gn:dem":4582,
    "gn:feature_class":"P",
    "gn:feature_code":"PPL",
    "gn:name":"Chaqing",
    "gn:population":0,
    "gn:timezone":"Asia/Urumqi",
    "iso:country":"CN",
    "name:zho_x_preferred":[
        "\u53c9\u9752"
    ],
    "wof:name":"Chaqing",
    "wof:placetype":"locality"
},
  "geometry": {"coordinates":[92.33141000000001,30.52723],"type":"Point"}
}