{
  "type": "Feature",
  "properties": {
    "gn:admin1_code":"26.0",
    "gn:asciiname":"Xiaseqin",
    "gn:country_code":"CN",
    "gn:dem":785,
    "gn:feature_class":"P",
    "gn:feature_code":"PPL",
    "gn:name":"Xiaseqin",
    "gn:population":0,
    "gn:timezone":"Asia/Shanghai",
    "iso:country":"CN",
    "name:zho_x_preferred":[
        "\u4e0b\u745f\u7434"
    ],
    "wof:name":"Xiaseqin",
    "wof:placetype":"locality"
},
  "geometry": {"coordinates":[110.44549000000001,36.358],"type":"Point"}
}