{
  "type": "Feature",
  "properties": {
    "gn:admin1_code":"25.0",
    "gn:asciiname":"Yuegou",
    "gn:cc2":"CN",
    "gn:country_code":"CN",
    "gn:dem":63,
    "gn:feature_class":"P",
    "gn:feature_code":"PPL",
    "gn:name":"Yuegou",
    "gn:population":0,
    "gn:timezone":"Asia/Shanghai",
    "iso:country":"CN",
    "name:zho_x_preferred":[
        "\u5cb3\u6c9f"
    ],
    "wof:name":"Yuegou",
    "wof:placetype":"locality"
},
  "geometry": {"coordinates":[119.59211000000001,36.18036],"type":"Point"}
}