{
  "type": "Feature",
  "properties": {
    "gn:admin1_code":"30",
    "gn:asciiname":"Kuantianlou",
    "gn:country_code":"CN",
    "gn:dem":52,
    "gn:feature_class":"P",
    "gn:feature_code":"PPL",
    "gn:name":"Kuantianlou",
    "gn:population":0,
    "gn:timezone":"Asia/Shanghai",
    "iso:country":"CN",
    "name:zho_x_preferred":[
        "\u5bbd\u7530\u697c"
    ],
    "wof:name":"Kuantianlou",
    "wof:placetype":"locality"
},
  "geometry": {"coordinates":[116.84473,23.71488],"type":"Point"}
}