{
  "type": "Feature",
  "properties": {
    "gn:admin1_code":"6.0",
    "gn:asciiname":"Gangchagunba",
    "gn:country_code":"CN",
    "gn:dem":3578,
    "gn:feature_class":"P",
    "gn:feature_code":"PPL",
    "gn:name":"Gangchagunba",
    "gn:population":0,
    "gn:timezone":"Asia/Shanghai",
    "iso:country":"CN",
    "name:und_x_variant":[
        "\u5188\u5bdf\u68cd\u5df4"
    ],
    "wof:name":"Gangchagunba",
    "wof:placetype":"locality"
},
  "geometry": {"coordinates":[102.24508,35.64017],"type":"Point"}
}