{
  "type": "Feature",
  "properties": {
    "gn:admin1_code":"30.0",
    "gn:asciiname":"Chencun Xinxu",
    "gn:country_code":"CN",
    "gn:dem":3,
    "gn:feature_class":"P",
    "gn:feature_code":"PPL",
    "gn:name":"Chencun Xinxu",
    "gn:population":0,
    "gn:timezone":"Asia/Shanghai",
    "iso:country":"CN",
    "name:zho_x_preferred":[
        "\u9648\u6751\u65b0\u5729"
    ],
    "wof:name":"Chencun Xinxu",
    "wof:placetype":"locality"
},
  "geometry": {"coordinates":[113.24292,22.95447],"type":"Point"}
}