{
  "type": "Feature",
  "properties": {
    "gn:admin1_code":"32.0",
    "gn:asciiname":"Ladi",
    "gn:country_code":"CN",
    "gn:dem":3749,
    "gn:feature_class":"P",
    "gn:feature_code":"PPL",
    "gn:name":"Ladi",
    "gn:population":0,
    "gn:timezone":"Asia/Shanghai",
    "iso:country":"CN",
    "name:zho_x_preferred":[
        "\u62c9\u5e95"
    ],
    "wof:name":"Ladi",
    "wof:placetype":"locality"
},
  "geometry": {"coordinates":[100.56424,31.68617],"type":"Point"}
}