{
  "type": "Feature",
  "properties": {
    "gn:admin1_code":"24",
    "gn:asciiname":"Nanyucun",
    "gn:country_code":"CN",
    "gn:dem":935,
    "gn:feature_class":"P",
    "gn:feature_code":"PPL",
    "gn:name":"Nanyucun",
    "gn:population":0,
    "gn:timezone":"Asia/Shanghai",
    "iso:country":"CN",
    "name:und_x_variant":[
        "Nanyu"
    ],
    "name:zho_x_preferred":[
        "\u5357\u5cea\u6751"
    ],
    "wof:name":"Nanyucun",
    "wof:placetype":"locality"
},
  "geometry": {"coordinates":[110.54825,36.97564000000001],"type":"Point"}
}