{
  "type": "Feature",
  "properties": {
    "gn:admin1_code":"11",
    "gn:asciiname":"Niwan",
    "gn:country_code":"CN",
    "gn:dem":458,
    "gn:feature_class":"P",
    "gn:feature_code":"PPL",
    "gn:name":"Niwan",
    "gn:population":0,
    "gn:timezone":"Asia/Shanghai",
    "iso:country":"CN",
    "name:zho_x_preferred":[
        "\u6ce5\u6e7e"
    ],
    "wof:name":"Niwan",
    "wof:placetype":"locality"
},
  "geometry": {"coordinates":[110.68172,27.29653],"type":"Point"}
}