{
  "type": "Feature",
  "properties": {
    "gn:admin1_code":"25.0",
    "gn:asciiname":"Nanqiaotou",
    "gn:country_code":"CN",
    "gn:dem":19,
    "gn:feature_class":"P",
    "gn:feature_code":"PPL",
    "gn:name":"Nanqiaotou",
    "gn:population":0,
    "gn:timezone":"Asia/Shanghai",
    "iso:country":"CN",
    "name:zho_x_preferred":[
        "\u5357\u6865\u5934"
    ],
    "wof:name":"Nanqiaotou",
    "wof:placetype":"locality"
},
  "geometry": {"coordinates":[122.37193000000001,36.95843],"type":"Point"}
}