{
  "type": "Feature",
  "properties": {
    "gn:country":"CN",
    "gn:fcode":"PPL",
    "gn:pop":550,
    "iso:country":"CN",
    "qs:name":"Dadengzhuang",
    "qs:photos_9r":0,
    "qs:photos_sr":0,
    "qs:pop_sr":"2",
    "wof:name":"Dadengzhuang",
    "wof:placetype":"locality",
    "wof:population":550
},
  "geometry": {"coordinates":[117.61750000000001,39.48639],"type":"Point"}
}