{
  "type": "Feature",
  "properties": {
    "gn:admin1_code":"24",
    "gn:asciiname":"Tanjiazhuang",
    "gn:country_code":"CN",
    "gn:dem":945,
    "gn:feature_class":"P",
    "gn:feature_code":"PPL",
    "gn:name":"Tanjiazhuang",
    "gn:population":0,
    "gn:timezone":"Asia/Shanghai",
    "iso:country":"CN",
    "name:und_x_variant":[
        "\u8c08\u5bb6\u5e84"
    ],
    "wof:name":"Tanjiazhuang",
    "wof:placetype":"locality"
},
  "geometry": {"coordinates":[111.58578,35.84034000000001],"type":"Point"}
}