{
  "type": "Feature",
  "properties": {
    "gn:admin1_code":"32.0",
    "gn:asciiname":"Qiulong",
    "gn:country_code":"CN",
    "gn:dem":3253,
    "gn:feature_class":"P",
    "gn:feature_code":"PPL",
    "gn:name":"Qiulong",
    "gn:population":0,
    "gn:timezone":"Asia/Shanghai",
    "iso:country":"CN",
    "name:zho_x_preferred":[
        "\u4e18\u9f99"
    ],
    "wof:name":"Qiulong",
    "wof:placetype":"locality"
},
  "geometry": {"coordinates":[100.60137,31.54686],"type":"Point"}
}