{
  "type": "Feature",
  "properties": {
    "gn:admin1_code":"32",
    "gn:asciiname":"Hongkou",
    "gn:country_code":"CN",
    "gn:dem":517,
    "gn:feature_class":"P",
    "gn:feature_code":"PPL",
    "gn:name":"Hongkou",
    "gn:population":0,
    "gn:timezone":"Asia/Shanghai",
    "iso:country":"CN",
    "name:und_x_variant":[
        "Hung-k\u2019ou-ch\u2019ang",
        "Khunkouchan",
        "Hung-k\u2019ou",
        "Hongkou"
    ],
    "name:zho_x_preferred":[
        "\u6d2a\u53e3"
    ],
    "wof:name":"Hongkou",
    "wof:placetype":"locality"
},
  "geometry": {"coordinates":[107.54425999999999,32.07625],"type":"Point"}
}