{
  "type": "Feature",
  "properties": {
    "gn:admin1_code":"26.0",
    "gn:asciiname":"Dayanggounao",
    "gn:country_code":"CN",
    "gn:dem":914,
    "gn:feature_class":"P",
    "gn:feature_code":"PPL",
    "gn:name":"Dayanggounao",
    "gn:population":0,
    "gn:timezone":"Asia/Shanghai",
    "iso:country":"CN",
    "name:zho_x_preferred":[
        "\u5927\u9633\u6c9f\u57b4"
    ],
    "wof:name":"Dayanggounao",
    "wof:placetype":"locality"
},
  "geometry": {"coordinates":[108.88169000000001,32.8567],"type":"Point"}
}