{
  "type": "Feature",
  "properties": {
    "gn:admin1_code":"26.0",
    "gn:asciiname":"Yanghe",
    "gn:country_code":"CN",
    "gn:dem":1341,
    "gn:feature_class":"P",
    "gn:feature_code":"PPL",
    "gn:name":"Yanghe",
    "gn:population":0,
    "gn:timezone":"Asia/Shanghai",
    "iso:country":"CN",
    "name:ceb_x_preferred":[
        "Yanghe"
    ],
    "name:deu_x_preferred":[
        "Yanghe"
    ],
    "name:swe_x_preferred":[
        "Yanghe"
    ],
    "name:und_x_variant":[
        "\u6768\u6cb3"
    ],
    "wof:name":"Yanghe",
    "wof:placetype":"locality"
},
  "geometry": {"coordinates":[107.02518999999999,34.02222],"type":"Point"}
}