{
  "type": "Feature",
  "properties": {
    "gn:admin1_code":"10",
    "gn:asciiname":"Xigaozhuang",
    "gn:country_code":"CN",
    "gn:dem":34,
    "gn:feature_class":"P",
    "gn:feature_code":"PPL",
    "gn:name":"Xigaozhuang",
    "gn:population":0,
    "gn:timezone":"Asia/Shanghai",
    "iso:country":"CN",
    "name:zho_x_preferred":[
        "\u897f\u9ad8\u5e84"
    ],
    "wof:name":"Xigaozhuang",
    "wof:placetype":"locality"
},
  "geometry": {"coordinates":[115.682,37.1092],"type":"Point"}
}