{
  "type": "Feature",
  "properties": {
    "gn:admin1_code":"4.0",
    "gn:asciiname":"Yanjiayuan",
    "gn:country_code":"CN",
    "gn:dem":3,
    "gn:feature_class":"P",
    "gn:feature_code":"PPL",
    "gn:name":"Yanjiayuan",
    "gn:population":0,
    "gn:timezone":"Asia/Shanghai",
    "iso:country":"CN",
    "name:und_x_variant":[
        "\u4e25\u5bb6\u56ed"
    ],
    "wof:name":"Yanjiayuan",
    "wof:placetype":"locality"
},
  "geometry": {"coordinates":[121.12734,32.07641],"type":"Point"}
}