{
  "type": "Feature",
  "properties": {
    "gn:admin1_code":"9.0",
    "gn:asciiname":"Xinwangzhuang",
    "gn:country_code":"CN",
    "gn:dem":152,
    "gn:feature_class":"P",
    "gn:feature_code":"PPL",
    "gn:name":"Xinwangzhuang",
    "gn:population":0,
    "gn:timezone":"Asia/Shanghai",
    "iso:country":"CN",
    "name:zho_x_preferred":[
        "\u65b0\u738b\u5e84"
    ],
    "wof:name":"Xinwangzhuang",
    "wof:placetype":"locality"
},
  "geometry": {"coordinates":[113.44857,32.38683],"type":"Point"}
}