{
  "type": "Feature",
  "properties": {
    "gn:admin1_code":"15.0",
    "gn:asciiname":"Gongzhai",
    "gn:country_code":"CN",
    "gn:dem":3497,
    "gn:feature_class":"P",
    "gn:feature_code":"PPL",
    "gn:name":"Gongzhai",
    "gn:population":0,
    "gn:timezone":"Asia/Shanghai",
    "iso:country":"CN",
    "name:zho_x_preferred":[
        "\u8d21\u5be8"
    ],
    "wof:name":"Gongzhai",
    "wof:placetype":"locality"
},
  "geometry": {"coordinates":[101.72016000000001,33.70195],"type":"Point"}
}