{
  "type": "Feature",
  "properties": {
    "gn:admin1_code":"32.0",
    "gn:asciiname":"Dasongwan",
    "gn:country_code":"CN",
    "gn:dem":420,
    "gn:feature_class":"P",
    "gn:feature_code":"PPL",
    "gn:name":"Dasongwan",
    "gn:population":0,
    "gn:timezone":"Asia/Shanghai",
    "iso:country":"CN",
    "name:zho_x_preferred":[
        "\u5927\u677e\u5f2f"
    ],
    "wof:name":"Dasongwan",
    "wof:placetype":"locality"
},
  "geometry": {"coordinates":[105.68600000000001,31.3536],"type":"Point"}
}