{
  "type": "Feature",
  "properties": {
    "gn:admin1_code":"30.0",
    "gn:asciiname":"Sanbajie",
    "gn:country_code":"CN",
    "gn:dem":80,
    "gn:feature_class":"P",
    "gn:feature_code":"PPL",
    "gn:name":"Sanbajie",
    "gn:population":0,
    "gn:timezone":"Asia/Shanghai",
    "iso:country":"CN",
    "name:zho_x_preferred":[
        "\u4e09\u516b\u8857"
    ],
    "wof:name":"Sanbajie",
    "wof:placetype":"locality"
},
  "geometry": {"coordinates":[113.4205,23.88679],"type":"Point"}
}