{
  "type": "Feature",
  "properties": {
    "gn:admin1_code":"8.0",
    "gn:asciiname":"Baojiatun",
    "gn:country_code":"CN",
    "gn:dem":248,
    "gn:feature_class":"P",
    "gn:feature_code":"PPL",
    "gn:name":"Baojiatun",
    "gn:population":0,
    "gn:timezone":"Asia/Shanghai",
    "iso:country":"CN",
    "name:zho_x_preferred":[
        "\u9c8d\u5bb6\u5c6f"
    ],
    "wof:name":"Baojiatun",
    "wof:placetype":"locality"
},
  "geometry": {"coordinates":[125.69275,47.79267],"type":"Point"}
}