{
  "type": "Feature",
  "properties": {
    "gn:admin1_code":"4.0",
    "gn:asciiname":"Doulaozhuang",
    "gn:country_code":"CN",
    "gn:dem":41,
    "gn:feature_class":"P",
    "gn:feature_code":"PPL",
    "gn:name":"Doulaozhuang",
    "gn:population":0,
    "gn:timezone":"Asia/Shanghai",
    "iso:country":"CN",
    "name:zho_x_preferred":[
        "\u7aa6\u8001\u5e84"
    ],
    "wof:name":"Doulaozhuang",
    "wof:placetype":"locality"
},
  "geometry": {"coordinates":[118.75059,32.93129],"type":"Point"}
}