{
  "type": "Feature",
  "properties": {
    "gn:admin1_code":"33.0",
    "gn:asciiname":"Baiyangping",
    "gn:country_code":"CN",
    "gn:dem":903,
    "gn:feature_class":"P",
    "gn:feature_code":"PPL",
    "gn:name":"Baiyangping",
    "gn:population":0,
    "gn:timezone":"Asia/Shanghai",
    "iso:country":"CN",
    "name:zho_x_preferred":[
        "\u67cf\u6768\u576a"
    ],
    "wof:name":"Baiyangping",
    "wof:placetype":"locality"
},
  "geometry": {"coordinates":[108.60623,28.45019000000001],"type":"Point"}
}