{
  "type": "Feature",
  "properties": {
    "gn:admin1_code":"2.0",
    "gn:asciiname":"Aotou",
    "gn:country_code":"CN",
    "gn:dem":807,
    "gn:feature_class":"P",
    "gn:feature_code":"PPL",
    "gn:name":"Aotou",
    "gn:population":0,
    "gn:timezone":"Asia/Shanghai",
    "iso:country":"CN",
    "name:zho_x_preferred":[
        "\u5c99\u5934"
    ],
    "wof:name":"Aotou",
    "wof:placetype":"locality"
},
  "geometry": {"coordinates":[118.79040000000001,28.40633],"type":"Point"}
}