{
  "type": "Feature",
  "properties": {
    "gn:admin1_code":"5.0",
    "gn:asciiname":"Songjiangcun",
    "gn:country_code":"CN",
    "gn:dem":130,
    "gn:feature_class":"P",
    "gn:feature_code":"PPL",
    "gn:name":"Songjiangcun",
    "gn:population":0,
    "gn:timezone":"Asia/Shanghai",
    "iso:country":"CN",
    "name:zho_x_preferred":[
        "\u677e\u6c5f\u6751"
    ],
    "wof:name":"Songjiangcun",
    "wof:placetype":"locality"
},
  "geometry": {"coordinates":[124.67158999999999,45.28806],"type":"Point"}
}