{
  "type": "Feature",
  "properties": {
    "gn:admin1_code":"24.0",
    "gn:asciiname":"Donglenggou",
    "gn:country_code":"CN",
    "gn:dem":1776,
    "gn:feature_class":"P",
    "gn:feature_code":"PPL",
    "gn:name":"Donglenggou",
    "gn:population":0,
    "gn:timezone":"Asia/Shanghai",
    "iso:country":"CN",
    "name:und_x_variant":[
        "\u51bb\u51b7\u6c9f"
    ],
    "name:zho_x_preferred":[
        "\u51bb\u51b7\u6c9f"
    ],
    "wof:name":"Donglenggou",
    "wof:placetype":"locality"
},
  "geometry": {"coordinates":[113.50138,39.14719],"type":"Point"}
}