{
  "type": "Feature",
  "properties": {
    "iso:country":"CN",
    "name:ara_x_preferred":[
        "\u062c\u064a\u0627\u0646 \u0634\u0648\u064a"
    ],
    "name:deu_x_preferred":[
        "Jianshui"
    ],
    "name:eng_x_preferred":[
        "Jianshui County"
    ],
    "name:fas_x_preferred":[
        "\u0634\u0647\u0631\u0633\u062a\u0627\u0646 \u062c\u06cc\u0627\u0646\u0634\u0648\u06cc"
    ],
    "name:gan_x_preferred":[
        "\u5efa\u6c34\u53bf"
    ],
    "name:ind_x_preferred":[
        "Wilayah Jianshui"
    ],
    "name:jpn_x_preferred":[
        "\u5efa\u6c34\u770c"
    ],
    "name:kor_x_preferred":[
        "\uc820\uc218\uc774\ud604"
    ],
    "name:nan_x_preferred":[
        "Ki\u00e0n-s\u00fai-ko\u0101n"
    ],
    "name:nld_x_preferred":[
        "Jianshui"
    ],
    "name:nob_x_preferred":[
        "Jianshui"
    ],
    "name:rus_x_preferred":[
        "\u0426\u0437\u044f\u043d\u044c\u0448\u0443\u0439"
    ],
    "name:spa_x_preferred":[
        "Jianshui"
    ],
    "name:swe_x_preferred":[
        "Jianshui"
    ],
    "name:urd_x_preferred":[
        "\u062c\u06cc\u0627\u0646\u0634\u0648\u06cc \u06a9\u0627\u0624\u0646\u0679\u06cc"
    ],
    "name:vie_x_preferred":[
        "Ki\u1ebfn Th\u1ee7y"
    ],
    "name:wuu_x_preferred":[
        "\u5efa\u6c34\u53bf"
    ],
    "name:yue_x_preferred":[
        "\u5efa\u6c34"
    ],
    "name:zho_x_preferred":[
        "\u5efa\u6c34\u53bf"
    ],
    "qs:name":"\u5efa\u6c34",
    "qs:name_adm0":"\u4e2d\u570b",
    "qs:name_adm1":"\u4e91\u5357\u7701",
    "qs:photos":469,
    "qs:photos_1k":95,
    "qs:photos_9k":2,
    "qs:photos_9r":5,
    "qs:photos_all":469,
    "qs:photos_sr":7,
    "qs:placetype":"Town",
    "qs:pop_sr":"0",
    "wd:wordcount":166,
    "wof:name":"\u5efa\u6c34",
    "wof:placetype":"locality"
},
  "geometry": {"coordinates":[102.822074,23.620384],"type":"Point"}
}