{
  "type": "Feature",
  "properties": {
    "iso:country":"CN",
    "qs:name":"\u5efa\u6c34",
    "qs:name_adm0":"\u4e2d\u570b",
    "qs:name_adm1":"\u4e91\u5357\u7701",
    "qs:photos":469,
    "qs:photos_1k":95,
    "qs:photos_9k":2,
    "qs:photos_9r":5,
    "qs:photos_all":469,
    "qs:photos_sr":7,
    "qs:placetype":"Town",
    "qs:pop_sr":"0",
    "wd:wordcount":166,
    "wof:name":"\u5efa\u6c34",
    "wof:placetype":"locality"
},
  "geometry": {"coordinates":[102.822074,23.620384],"type":"Point"}
}