{
  "type": "Feature",
  "properties": {
    "gn:admin1_code":"7",
    "gn:asciiname":"Liuyelou",
    "gn:country_code":"CN",
    "gn:dem":36,
    "gn:feature_class":"P",
    "gn:feature_code":"PPL",
    "gn:name":"Liuyelou",
    "gn:population":0,
    "gn:timezone":"Asia/Shanghai",
    "iso:country":"CN",
    "name:und_x_variant":[
        "Luyalou",
        "Liuyelou"
    ],
    "name:zho_x_preferred":[
        "\u516d\u7237\u697c"
    ],
    "wof:name":"Liuyelou",
    "wof:placetype":"locality"
},
  "geometry": {"coordinates":[117.06692,23.73427],"type":"Point"}
}