{
  "type": "Feature",
  "properties": {
    "gn:admin1_code":"18",
    "gn:asciiname":"Hangdong",
    "gn:country_code":"CN",
    "gn:dem":1308,
    "gn:feature_class":"P",
    "gn:feature_code":"PPL",
    "gn:name":"Hangdong",
    "gn:population":0,
    "gn:timezone":"Asia/Shanghai",
    "iso:country":"CN",
    "name:zho_x_preferred":[
        "\u676d\u6d1e"
    ],
    "wof:name":"Hangdong",
    "wof:placetype":"locality"
},
  "geometry": {"coordinates":[105.312,25.2169],"type":"Point"}
}