{
  "type": "Feature",
  "properties": {
    "gn:admin1_code":"32.0",
    "gn:asciiname":"Shanchongping",
    "gn:country_code":"CN",
    "gn:dem":3599,
    "gn:feature_class":"P",
    "gn:feature_code":"PPL",
    "gn:name":"Shanchongping",
    "gn:population":0,
    "gn:timezone":"Asia/Shanghai",
    "iso:country":"CN",
    "name:zho_x_preferred":[
        "\u5c71\u51b2\u576a"
    ],
    "wof:name":"Shanchongping",
    "wof:placetype":"locality"
},
  "geometry": {"coordinates":[101.158,27.7286],"type":"Point"}
}