{
  "type": "Feature",
  "properties": {
    "gn:admin1_code":"5.0",
    "gn:asciiname":"Laoyaokeng",
    "gn:country_code":"CN",
    "gn:dem":303,
    "gn:feature_class":"P",
    "gn:feature_code":"PPL",
    "gn:name":"Laoyaokeng",
    "gn:population":0,
    "gn:timezone":"Asia/Shanghai",
    "iso:country":"CN",
    "name:und_x_variant":[
        "Laoyaokengtun"
    ],
    "name:zho_x_preferred":[
        "\u8001\u7a91\u5751"
    ],
    "wof:name":"Laoyaokeng",
    "wof:placetype":"locality"
},
  "geometry": {"coordinates":[125.46908000000001,43.13014],"type":"Point"}
}