{
  "type": "Feature",
  "properties": {
    "gn:admin1_code":"30.0",
    "gn:asciiname":"Shuiduikeng",
    "gn:country_code":"CN",
    "gn:dem":172,
    "gn:feature_class":"P",
    "gn:feature_code":"PPL",
    "gn:name":"Shuiduikeng",
    "gn:population":0,
    "gn:timezone":"Asia/Urumqi",
    "iso:country":"CN",
    "name:zho_x_preferred":[
        "\u6c34\u7893\u5751"
    ],
    "wof:name":"Shuiduikeng",
    "wof:placetype":"locality"
},
  "geometry": {"coordinates":[111.55296,22.50852],"type":"Point"}
}