{
  "type": "Feature",
  "properties": {
    "gn:admin1_code":"11",
    "gn:asciiname":"Zhuanwuli",
    "gn:country_code":"CN",
    "gn:dem":305,
    "gn:feature_class":"P",
    "gn:feature_code":"PPL",
    "gn:name":"Zhuanwuli",
    "gn:population":0,
    "gn:timezone":"Asia/Shanghai",
    "iso:country":"CN",
    "name:zho_x_preferred":[
        "\u7816\u5c4b\u91cc"
    ],
    "wof:name":"Zhuanwuli",
    "wof:placetype":"locality"
},
  "geometry": {"coordinates":[111.01778,27.185],"type":"Point"}
}