{
  "type": "Feature",
  "properties": {
    "gn:admin1_code":"5.0",
    "gn:asciiname":"Daqingchuan",
    "gn:country_code":"CN",
    "gn:dem":265,
    "gn:feature_class":"P",
    "gn:feature_code":"PPL",
    "gn:name":"Daqingchuan",
    "gn:population":0,
    "gn:timezone":"Asia/Shanghai",
    "iso:country":"CN",
    "name:zho_x_preferred":[
        "\u5927\u5e86\u5ddd"
    ],
    "wof:name":"Daqingchuan",
    "wof:placetype":"locality"
},
  "geometry": {"coordinates":[127.28543000000001,44.42284],"type":"Point"}
}