{
  "type": "Feature",
  "properties": {
    "gn:admin1_code":"1.0",
    "gn:asciiname":"Tonglecun",
    "gn:country_code":"CN",
    "gn:dem":13,
    "gn:feature_class":"P",
    "gn:feature_code":"PPL",
    "gn:name":"Tonglecun",
    "gn:population":0,
    "gn:timezone":"Asia/Shanghai",
    "iso:country":"CN",
    "name:zho_x_preferred":[
        "\u540c\u4e50\u6751"
    ],
    "wof:name":"Tonglecun",
    "wof:placetype":"locality"
},
  "geometry": {"coordinates":[117.37322,30.66231],"type":"Point"}
}