{
  "type": "Feature",
  "properties": {
    "gn:admin1_code":"7.0",
    "gn:asciiname":"Danshan",
    "gn:country_code":"CN",
    "gn:dem":836,
    "gn:feature_class":"P",
    "gn:feature_code":"PPL",
    "gn:name":"Danshan",
    "gn:population":0,
    "gn:timezone":"Asia/Shanghai",
    "iso:country":"CN",
    "name:zho_x_preferred":[
        "\u4e39\u5c71"
    ],
    "wof:name":"Danshan",
    "wof:placetype":"locality"
},
  "geometry": {"coordinates":[117.87958999999999,26.14697],"type":"Point"}
}