{
  "type": "Feature",
  "properties": {
    "gn:admin1_code":"10.0",
    "gn:asciiname":"Dongyanli",
    "gn:country_code":"CN",
    "gn:dem":72,
    "gn:feature_class":"P",
    "gn:feature_code":"PPL",
    "gn:name":"Dongyanli",
    "gn:population":0,
    "gn:timezone":"Asia/Shanghai",
    "iso:country":"CN",
    "name:und_x_variant":[
        "\u4e1c\u6cbf\u91cc"
    ],
    "wof:name":"Dongyanli",
    "wof:placetype":"locality"
},
  "geometry": {"coordinates":[114.84609,38.52509000000001],"type":"Point"}
}