{
  "type": "Feature",
  "properties": {
    "gn:admin1_code":"32.0",
    "gn:asciiname":"Jingqiaopu",
    "gn:country_code":"CN",
    "gn:dem":681,
    "gn:feature_class":"P",
    "gn:feature_code":"PPL",
    "gn:name":"Jingqiaopu",
    "gn:population":0,
    "gn:timezone":"Asia/Shanghai",
    "iso:country":"CN",
    "name:zho_x_preferred":[
        "\u8346\u6865\u94fa"
    ],
    "wof:name":"Jingqiaopu",
    "wof:placetype":"locality"
},
  "geometry": {"coordinates":[108.127,31.9977],"type":"Point"}
}