{
  "type": "Feature",
  "properties": {
    "gn:admin1_code":"29.0",
    "gn:asciiname":"Hongjia Liangzi",
    "gn:country_code":"CN",
    "gn:dem":2140,
    "gn:feature_class":"P",
    "gn:feature_code":"PPL",
    "gn:name":"Hongjia Liangzi",
    "gn:population":0,
    "gn:timezone":"Asia/Shanghai",
    "iso:country":"CN",
    "name:zho_x_preferred":[
        "\u6d2a\u5bb6\u6881\u5b50"
    ],
    "wof:name":"Hongjia Liangzi",
    "wof:placetype":"locality"
},
  "geometry": {"coordinates":[102.994,27.2026],"type":"Point"}
}