{
  "type": "Feature",
  "properties": {
    "gn:admin1_code":"32.0",
    "gn:asciiname":"Tianhuashui",
    "gn:country_code":"CN",
    "gn:dem":1212,
    "gn:feature_class":"P",
    "gn:feature_code":"PPL",
    "gn:name":"Tianhuashui",
    "gn:population":0,
    "gn:timezone":"Asia/Shanghai",
    "iso:country":"CN",
    "name:zho_x_preferred":[
        "\u5929\u82b1\u6c34"
    ],
    "wof:name":"Tianhuashui",
    "wof:placetype":"locality"
},
  "geometry": {"coordinates":[103.444,28.926],"type":"Point"}
}