{
  "type": "Feature",
  "properties": {
    "gn:admin1_code":"26.0",
    "gn:asciiname":"Yushugou",
    "gn:country_code":"CN",
    "gn:dem":1445,
    "gn:feature_class":"P",
    "gn:feature_code":"PPL",
    "gn:name":"Yushugou",
    "gn:population":0,
    "gn:timezone":"Asia/Shanghai",
    "iso:country":"CN",
    "name:zho_x_preferred":[
        "\u6986\u6811\u6c9f"
    ],
    "wof:name":"Yushugou",
    "wof:placetype":"locality"
},
  "geometry": {"coordinates":[108.86087999999999,36.53019000000001],"type":"Point"}
}