{
  "type": "Feature",
  "properties": {
    "gn:admin1_code":"7",
    "gn:asciiname":"Wuling",
    "gn:country_code":"CN",
    "gn:dem":184,
    "gn:feature_class":"P",
    "gn:feature_code":"PPL",
    "gn:name":"Wuling",
    "gn:population":0,
    "gn:timezone":"Asia/Shanghai",
    "iso:country":"CN",
    "name:ceb_x_preferred":[
        "Wuling"
    ],
    "name:nld_x_preferred":[
        "Wuling"
    ],
    "name:pol_x_preferred":[
        "Wuling"
    ],
    "name:zho_x_preferred":[
        "\u68a7\u5cad"
    ],
    "wof:name":"Wuling",
    "wof:placetype":"locality"
},
  "geometry": {"coordinates":[118.94183999999998,25.93764],"type":"Point"}
}