{
  "type": "Feature",
  "properties": {
    "gn:admin1_code":"4.0",
    "gn:asciiname":"Luyangcun",
    "gn:country_code":"CN",
    "gn:dem":5,
    "gn:feature_class":"P",
    "gn:feature_code":"PPL",
    "gn:name":"L\u00fcyangcun",
    "gn:population":0,
    "gn:timezone":"Asia/Shanghai",
    "iso:country":"CN",
    "name:und_x_variant":[
        "L\u00fcyangcun"
    ],
    "name:zho_x_preferred":[
        "\u5415\u6768\u6751"
    ],
    "wof:name":"Luyangcun",
    "wof:placetype":"locality"
},
  "geometry": {"coordinates":[119.72308,32.92957],"type":"Point"}
}