{
  "type": "Feature",
  "properties": {
    "gn:admin1_code":"25",
    "gn:asciiname":"Houjia Guanzhuang",
    "gn:country_code":"CN",
    "gn:dem":476,
    "gn:feature_class":"P",
    "gn:feature_code":"PPL",
    "gn:name":"Houjia Guanzhuang",
    "gn:population":0,
    "gn:timezone":"Asia/Shanghai",
    "iso:country":"CN",
    "name:zho_x_preferred":[
        "\u4faf\u5bb6\u5b98\u5e84"
    ],
    "wof:name":"Houjia Guanzhuang",
    "wof:placetype":"locality"
},
  "geometry": {"coordinates":[118.524,36.1119],"type":"Point"}
}