{
  "type": "Feature",
  "properties": {
    "gn:admin1_code":"11.0",
    "gn:asciiname":"Anmeiwan",
    "gn:country_code":"CN",
    "gn:dem":197,
    "gn:feature_class":"P",
    "gn:feature_code":"PPL",
    "gn:name":"Anmeiwan",
    "gn:population":0,
    "gn:timezone":"Asia/Shanghai",
    "iso:country":"CN",
    "name:zho_x_preferred":[
        "\u5b89\u6885\u6e7e"
    ],
    "wof:name":"Anmeiwan",
    "wof:placetype":"locality"
},
  "geometry": {"coordinates":[111.44589000000001,28.4254],"type":"Point"}
}