{
  "type": "Feature",
  "properties": {
    "gn:admin1_code":"4.0",
    "gn:asciiname":"Qinxiangli",
    "gn:country_code":"CN",
    "gn:dem":7,
    "gn:feature_class":"P",
    "gn:feature_code":"PPL",
    "gn:name":"Qinxiangli",
    "gn:population":0,
    "gn:timezone":"Asia/Shanghai",
    "iso:country":"CN",
    "name:zho_x_preferred":[
        "\u79e6\u5df7\u91cc"
    ],
    "wof:name":"Qinxiangli",
    "wof:placetype":"locality"
},
  "geometry": {"coordinates":[119.88276999999999,31.96728],"type":"Point"}
}