{
  "type": "Feature",
  "properties": {
    "gn:admin1_code":"4.0",
    "gn:asciiname":"Wangxiucun",
    "gn:country_code":"CN",
    "gn:dem":5,
    "gn:feature_class":"P",
    "gn:feature_code":"PPL",
    "gn:name":"Wangxiucun",
    "gn:population":0,
    "gn:timezone":"Asia/Shanghai",
    "iso:country":"CN",
    "name:zho_x_preferred":[
        "\u738b\u79c0\u6751"
    ],
    "wof:name":"Wangxiucun",
    "wof:placetype":"locality"
},
  "geometry": {"coordinates":[121.0534,31.64351],"type":"Point"}
}