{
  "type": "Feature",
  "properties": {
    "gn:admin1_code":"14.0",
    "gn:asciiname":"Jiudiwucun",
    "gn:country_code":"CN",
    "gn:dem":4636,
    "gn:feature_class":"P",
    "gn:feature_code":"PPL",
    "gn:name":"Jiudiwucun",
    "gn:population":0,
    "gn:timezone":"Asia/Urumqi",
    "iso:country":"CN",
    "name:zho_x_preferred":[
        "\u4e45\u5824\u543e\u6751"
    ],
    "wof:name":"Jiudiwucun",
    "wof:placetype":"locality"
},
  "geometry": {"coordinates":[91.94144,31.29565],"type":"Point"}
}