{
  "type": "Feature",
  "properties": {
    "gn:admin1_code":"5.0",
    "gn:asciiname":"Houdingjia",
    "gn:country_code":"CN",
    "gn:dem":143,
    "gn:feature_class":"P",
    "gn:feature_code":"PPL",
    "gn:name":"Houdingjia",
    "gn:population":0,
    "gn:timezone":"Asia/Shanghai",
    "iso:country":"CN",
    "name:zho_x_preferred":[
        "\u540e\u4e01\u5bb6"
    ],
    "wof:name":"Houdingjia",
    "wof:placetype":"locality"
},
  "geometry": {"coordinates":[123.4324,44.04287],"type":"Point"}
}