{
  "type": "Feature",
  "properties": {
    "gn:admin1_code":"3.0",
    "gn:asciiname":"Songjiawu",
    "gn:country_code":"CN",
    "gn:dem":15,
    "gn:feature_class":"P",
    "gn:feature_code":"PPL",
    "gn:name":"Songjiawu",
    "gn:population":0,
    "gn:timezone":"Asia/Shanghai",
    "iso:country":"CN",
    "name:und_x_variant":[
        "\u5b8b\u5bb6\u5c4b"
    ],
    "wof:name":"Songjiawu",
    "wof:placetype":"locality"
},
  "geometry": {"coordinates":[116.63566000000002,29.9011],"type":"Point"}
}