{
  "type": "Feature",
  "properties": {
    "gn:admin1_code":"15.0",
    "gn:asciiname":"Zhanzhan",
    "gn:country_code":"CN",
    "gn:dem":2049,
    "gn:feature_class":"P",
    "gn:feature_code":"PPL",
    "gn:name":"Zhanzhan",
    "gn:population":0,
    "gn:timezone":"Asia/Shanghai",
    "iso:country":"CN",
    "name:und_x_variant":[
        "\u7ad9\u7ad9"
    ],
    "name:zho_x_preferred":[
        "\u7ad9\u7ad9"
    ],
    "wof:name":"Zhanzhan",
    "wof:placetype":"locality"
},
  "geometry": {"coordinates":[104.03784,33.8564],"type":"Point"}
}