{
  "type": "Feature",
  "properties": {
    "gn:admin1_code":"24.0",
    "gn:asciiname":"Baihu",
    "gn:country_code":"CN",
    "gn:dem":1656,
    "gn:feature_class":"P",
    "gn:feature_code":"PPL",
    "gn:name":"Baihu",
    "gn:population":0,
    "gn:timezone":"Asia/Shanghai",
    "iso:country":"CN",
    "name:und_x_variant":[
        "\u8d25\u864e"
    ],
    "name:zho_x_preferred":[
        "\u8d25\u864e"
    ],
    "wof:name":"Baihu",
    "wof:placetype":"locality"
},
  "geometry": {"coordinates":[112.03326,39.80706],"type":"Point"}
}