{
  "type": "Feature",
  "properties": {
    "gn:admin1_code":"19.0",
    "gn:asciiname":"Chedaoling",
    "gn:country_code":"CN",
    "gn:dem":266,
    "gn:feature_class":"P",
    "gn:feature_code":"PPL",
    "gn:name":"Chedaoling",
    "gn:population":0,
    "gn:timezone":"Asia/Shanghai",
    "iso:country":"CN",
    "name:und_x_variant":[
        "\u8f66\u9053\u5cad"
    ],
    "wof:name":"Chedaoling",
    "wof:placetype":"locality"
},
  "geometry": {"coordinates":[125.38191,40.78771],"type":"Point"}
}