{
  "type": "Feature",
  "properties": {
    "gn:admin1_code":"16.0",
    "gn:asciiname":"Longtan",
    "gn:country_code":"CN",
    "gn:dem":177,
    "gn:feature_class":"P",
    "gn:feature_code":"PPL",
    "gn:name":"Longtan",
    "gn:population":0,
    "gn:timezone":"Asia/Shanghai",
    "iso:country":"CN",
    "name:ceb_x_preferred":[
        "Longtan"
    ],
    "name:deu_x_preferred":[
        "Longtan"
    ],
    "name:fra_x_preferred":[
        "Longtan"
    ],
    "name:zho_x_preferred":[
        "\u9647\u575b"
    ],
    "wof:name":"Longtan",
    "wof:placetype":"locality"
},
  "geometry": {"coordinates":[107.17,22.4526],"type":"Point"}
}