{
  "type": "Feature",
  "properties": {
    "gn:admin1_code":"16.0",
    "gn:asciiname":"Luwu",
    "gn:country_code":"CN",
    "gn:dem":200,
    "gn:feature_class":"P",
    "gn:feature_code":"PPL",
    "gn:name":"Luwu",
    "gn:population":0,
    "gn:timezone":"Asia/Shanghai",
    "iso:country":"CN",
    "name:ind_x_preferred":[
        "Kedatuan Luwu"
    ],
    "name:msa_x_preferred":[
        "Kerajaan Luwuk"
    ],
    "name:zho_x_preferred":[
        "\u6e0c\u68a7"
    ],
    "wof:name":"Luwu",
    "wof:placetype":"locality"
},
  "geometry": {"coordinates":[107.726,23.4465],"type":"Point"}
}