{
  "type": "Feature",
  "properties": {
    "gn:admin1_code":"14.0",
    "gn:asciiname":"Wadacun",
    "gn:country_code":"CN",
    "gn:dem":3572,
    "gn:feature_class":"P",
    "gn:feature_code":"PPL",
    "gn:name":"Wadacun",
    "gn:population":0,
    "gn:timezone":"Asia/Urumqi",
    "iso:country":"CN",
    "name:zho_x_preferred":[
        "\u74e6\u8fbe\u6751"
    ],
    "wof:name":"Wadacun",
    "wof:placetype":"locality"
},
  "geometry": {"coordinates":[97.39327,31.50711],"type":"Point"}
}