{
  "type": "Feature",
  "properties": {
    "gn:admin1_code":"29.0",
    "gn:asciiname":"Mugualin",
    "gn:country_code":"CN",
    "gn:dem":1888,
    "gn:feature_class":"P",
    "gn:feature_code":"PPL",
    "gn:name":"Mugualin",
    "gn:population":0,
    "gn:timezone":"Asia/Shanghai",
    "iso:country":"CN",
    "name:zho_x_preferred":[
        "\u6728\u74dc\u6797"
    ],
    "wof:name":"Mugualin",
    "wof:placetype":"locality"
},
  "geometry": {"coordinates":[99.0548,25.3467],"type":"Point"}
}