{
  "type": "Feature",
  "properties": {
    "gn:admin1_code":"11.0",
    "gn:asciiname":"Yudongmiao",
    "gn:country_code":"CN",
    "gn:dem":26,
    "gn:feature_class":"P",
    "gn:feature_code":"PPL",
    "gn:name":"Yudongmiao",
    "gn:population":0,
    "gn:timezone":"Asia/Shanghai",
    "iso:country":"CN",
    "name:zho_x_preferred":[
        "\u79b9\u4e1c\u5e99"
    ],
    "wof:name":"Yudongmiao",
    "wof:placetype":"locality"
},
  "geometry": {"coordinates":[112.68827,29.38404],"type":"Point"}
}