{
  "type": "Feature",
  "properties": {
    "gn:admin1_code":"7",
    "gn:asciiname":"Xiaxia",
    "gn:country_code":"CN",
    "gn:dem":931,
    "gn:feature_class":"P",
    "gn:feature_code":"PPL",
    "gn:name":"Xiaxia",
    "gn:population":0,
    "gn:timezone":"Asia/Shanghai",
    "iso:country":"CN",
    "name:und_x_variant":[
        "\u4e0b\u5ce1"
    ],
    "wof:name":"Xiaxia",
    "wof:placetype":"locality"
},
  "geometry": {"coordinates":[119.01694000000001,27.20194],"type":"Point"}
}