{
  "type": "Feature",
  "properties": {
    "gn:admin1_code":"29.0",
    "gn:asciiname":"Guihua",
    "gn:country_code":"CN",
    "gn:dem":951,
    "gn:feature_class":"P",
    "gn:feature_code":"PPL",
    "gn:name":"Guihua",
    "gn:population":0,
    "gn:timezone":"Asia/Shanghai",
    "iso:country":"CN",
    "name:ceb_x_preferred":[
        "Guihua"
    ],
    "name:deu_x_preferred":[
        "Guihua"
    ],
    "name:swe_x_preferred":[
        "Guihua"
    ],
    "name:und_x_variant":[
        "\u6842\u82b1"
    ],
    "wof:name":"Guihua",
    "wof:placetype":"locality"
},
  "geometry": {"coordinates":[104.02473999999999,28.47433],"type":"Point"}
}