{
  "type": "Feature",
  "properties": {
    "gn:admin1_code":"18",
    "gn:asciiname":"Mashanpo",
    "gn:country_code":"CN",
    "gn:dem":1145,
    "gn:feature_class":"P",
    "gn:feature_code":"PPL",
    "gn:name":"Mashanpo",
    "gn:population":0,
    "gn:timezone":"Asia/Shanghai",
    "iso:country":"CN",
    "name:zho_x_preferred":[
        "\u9ebb\u5c71\u5761"
    ],
    "wof:name":"Mashanpo",
    "wof:placetype":"locality"
},
  "geometry": {"coordinates":[106.34699999999999,25.202],"type":"Point"}
}