{
  "type": "Feature",
  "properties": {
    "gn:admin1_code":"10",
    "gn:asciiname":"Tianshuitun",
    "gn:country_code":"CN",
    "gn:dem":32,
    "gn:feature_class":"P",
    "gn:feature_code":"PPL",
    "gn:name":"Tianshuitun",
    "gn:population":0,
    "gn:timezone":"Asia/Shanghai",
    "iso:country":"CN",
    "name:zho_x_preferred":[
        "\u5929\u6c34\u5c6f"
    ],
    "wof:name":"Tianshuitun",
    "wof:placetype":"locality"
},
  "geometry": {"coordinates":[115.895,37.1936],"type":"Point"}
}