{
  "type": "Feature",
  "properties": {
    "gn:admin1_code":"11.0",
    "gn:asciiname":"Huli Nongchang",
    "gn:country_code":"CN",
    "gn:dem":150,
    "gn:feature_class":"P",
    "gn:feature_code":"PPLF",
    "gn:name":"Huli Nongchang",
    "gn:population":0,
    "gn:timezone":"Asia/Shanghai",
    "iso:country":"CN",
    "name:zho_x_preferred":[
        "\u6e56\u91cc\u519c\u573a"
    ],
    "wof:name":"Huli Nongchang",
    "wof:placetype":"locality"
},
  "geometry": {"coordinates":[113.69719000000001,26.86233],"type":"Point"}
}