{
  "type": "Feature",
  "properties": {
    "gn:admin1_code":"30",
    "gn:asciiname":"Sulilu",
    "gn:country_code":"CN",
    "gn:dem":30,
    "gn:feature_class":"P",
    "gn:feature_code":"PPL",
    "gn:name":"Sulilu",
    "gn:population":0,
    "gn:timezone":"Asia/Urumqi",
    "iso:country":"CN",
    "name:zho_x_preferred":[
        "\u82cf\u91cc\u9646"
    ],
    "wof:name":"Sulilu",
    "wof:placetype":"locality"
},
  "geometry": {"coordinates":[109.82758,21.0915],"type":"Point"}
}