{
  "type": "Feature",
  "properties": {
    "gn:admin1_code":"11.0",
    "gn:asciiname":"Taoguanshan",
    "gn:country_code":"CN",
    "gn:dem":170,
    "gn:feature_class":"P",
    "gn:feature_code":"PPL",
    "gn:name":"Taoguanshan",
    "gn:population":0,
    "gn:timezone":"Asia/Shanghai",
    "iso:country":"CN",
    "name:zho_x_preferred":[
        "\u6843\u5173\u6247"
    ],
    "wof:name":"Taoguanshan",
    "wof:placetype":"locality"
},
  "geometry": {"coordinates":[113.54548,29.4034],"type":"Point"}
}