{
  "type": "Feature",
  "properties": {
    "gn:admin1_code":"30",
    "gn:asciiname":"Mayan",
    "gn:country_code":"CN",
    "gn:dem":3,
    "gn:feature_class":"P",
    "gn:feature_code":"PPL",
    "gn:name":"Mayan",
    "gn:population":0,
    "gn:timezone":"Asia/Urumqi",
    "iso:country":"CN",
    "name:ceb_x_preferred":[
        "Mayan"
    ],
    "name:deu_x_preferred":[
        "Mayan"
    ],
    "name:swe_x_preferred":[
        "Mayan"
    ],
    "name:zho_x_preferred":[
        "\u9ebb\u6f14"
    ],
    "wof:name":"Mayan",
    "wof:placetype":"locality"
},
  "geometry": {"coordinates":[110.11790000000001,20.875],"type":"Point"}
}