{
  "type": "Feature",
  "properties": {
    "gn:admin1_code":"4.0",
    "gn:asciiname":"Hanshang",
    "gn:country_code":"CN",
    "gn:dem":5,
    "gn:feature_class":"P",
    "gn:feature_code":"PPL",
    "gn:name":"Hanshang",
    "gn:population":0,
    "gn:timezone":"Asia/Shanghai",
    "iso:country":"CN",
    "name:und_x_variant":[
        "\u9097\u4e0a"
    ],
    "name:zho_x_preferred":[
        "\u9097\u4e0a"
    ],
    "wof:name":"Hanshang",
    "wof:placetype":"locality"
},
  "geometry": {"coordinates":[120.85295000000001,31.00436],"type":"Point"}
}