{
  "type": "Feature",
  "properties": {
    "gn:admin1_code":"19.0",
    "gn:asciiname":"Cuijia Wopu",
    "gn:country_code":"CN",
    "gn:dem":270,
    "gn:feature_class":"P",
    "gn:feature_code":"PPL",
    "gn:name":"Cuijia Wopu",
    "gn:population":0,
    "gn:timezone":"Asia/Shanghai",
    "iso:country":"CN",
    "name:zho_x_preferred":[
        "\u5d14\u5bb6\u7a9d\u94fa"
    ],
    "wof:name":"Cuijia Wopu",
    "wof:placetype":"locality"
},
  "geometry": {"coordinates":[120.59111,41.39217],"type":"Point"}
}