{
  "type": "Feature",
  "properties": {
    "gn:admin1_code":"29.0",
    "gn:asciiname":"Jiakong",
    "gn:country_code":"CN",
    "gn:dem":1367,
    "gn:feature_class":"P",
    "gn:feature_code":"PPL",
    "gn:name":"Jiakong",
    "gn:population":0,
    "gn:timezone":"Asia/Shanghai",
    "iso:country":"CN",
    "name:zho_x_preferred":[
        "\u621b\u7a7a"
    ],
    "wof:name":"Jiakong",
    "wof:placetype":"locality"
},
  "geometry": {"coordinates":[100.16,23.2099],"type":"Point"}
}