{
  "type": "Feature",
  "properties": {
    "iso:country":"CN",
    "ne:ADM0CAP":0.0,
    "ne:ADM0NAME":"China",
    "ne:ADM0_A3":"CHN",
    "ne:ADM1NAME":"Jiangxi",
    "ne:ADMIN1_COD":0,
    "ne:CAPALT":0,
    "ne:CHANGED":0,
    "ne:CHECKME":0,
    "ne:COMPARE":0,
    "ne:DIFFASCII":0,
    "ne:ELEVATION":0.0,
    "ne:FEATURECLA":"Populated place",
    "ne:GEONAMEID":-1,
    "ne:GEONAMESNO":"No GeoNames match due to small population, not in GeoNames, or poor NEV placement.",
    "ne:GN_POP":0,
    "ne:GTOPO30":0.0,
    "ne:ISO_A2":"CN",
    "ne:LABELRANK":1,
    "ne:LATITUDE":27.970346,
    "ne:LONGITUDE":116.360019,
    "ne:LS_MATCH":1,
    "ne:LS_NAME":"Linchuan",
    "ne:MAX_AREAKM":70.0,
    "ne:MAX_AREAMI":27.0,
    "ne:MAX_BBXMAX":116.425,
    "ne:MAX_BBXMIN":116.291667,
    "ne:MAX_BBYMAX":28.041667,
    "ne:MAX_BBYMIN":27.95,
    "ne:MAX_NATSCA":20.0,
    "ne:MAX_PERKM":67.0,
    "ne:MAX_PERMI":41.0,
    "ne:MAX_POP10":241104,
    "ne:MAX_POP20":241104,
    "ne:MAX_POP300":0,
    "ne:MAX_POP310":0,
    "ne:MAX_POP50":0,
    "ne:MEAN_BBXC":116.356341,
    "ne:MEAN_BBYC":27.996014,
    "ne:MEGACITY":0,
    "ne:MIN_AREAKM":70.0,
    "ne:MIN_AREAMI":27.0,
    "ne:MIN_BBXMAX":116.425,
    "ne:MIN_BBXMIN":116.291667,
    "ne:MIN_BBYMAX":28.041667,
    "ne:MIN_BBYMIN":27.95,
    "ne:MIN_PERKM":67.0,
    "ne:MIN_PERMI":41.0,
    "ne:NAME":"Linchuan",
    "ne:NAMEASCII":"Linchuan",
    "ne:NAMEDIFF":0,
    "ne:NATSCALE":20,
    "ne:POP1950":0,
    "ne:POP1955":0,
    "ne:POP1960":0,
    "ne:POP1965":0,
    "ne:POP1970":0,
    "ne:POP1975":0,
    "ne:POP1980":0,
    "ne:POP1985":0,
    "ne:POP1990":0,
    "ne:POP1995":0,
    "ne:POP2000":0,
    "ne:POP2005":0,
    "ne:POP2010":0,
    "ne:POP2015":0,
    "ne:POP2020":0,
    "ne:POP2025":0,
    "ne:POP2050":0,
    "ne:POP_MAX":241104,
    "ne:POP_MIN":241104,
    "ne:POP_OTHER":282920,
    "ne:RANK_MAX":10,
    "ne:RANK_MIN":10,
    "ne:SCALERANK":7,
    "ne:SOV0NAME":"China",
    "ne:SOV_A3":"CHN",
    "ne:UN_FID":0,
    "ne:UN_LAT":0.0,
    "ne:UN_LONG":0.0,
    "ne:WORLDCITY":0,
    "ne:min_zoom":6.7,
    "wof:name":"Linchuan",
    "wof:placetype":"locality"
},
  "geometry": {"coordinates":[116.36001867580865,27.970345681769],"type":"Point"}
}