{
  "type": "Feature",
  "properties": {
    "gn:admin1_code":"30",
    "gn:asciiname":"Dengta",
    "gn:country_code":"CN",
    "gn:dem":126,
    "gn:feature_class":"P",
    "gn:feature_code":"PPLA4",
    "gn:name":"Dengta",
    "gn:population":0,
    "gn:timezone":"Asia/Shanghai",
    "iso:country":"CN",
    "name:und_x_variant":[
        "Teng-t\u2019a-hs\u00fc",
        "Teng-t\u2019a",
        "Dengta",
        "\u706f\u5854",
        "Dengta Zhen",
        "\u706f\u5854\u9547"
    ],
    "wof:name":"Dengta",
    "wof:placetype":"locality"
},
  "geometry": {"coordinates":[114.7872,24.01094],"type":"Point"}
}