{
  "type": "Feature",
  "properties": {
    "gn:admin1_code":"1.0",
    "gn:asciiname":"Yushuicun",
    "gn:country_code":"CN",
    "gn:dem":34,
    "gn:feature_class":"P",
    "gn:feature_code":"PPL",
    "gn:name":"Yushuicun",
    "gn:population":0,
    "gn:timezone":"Asia/Shanghai",
    "iso:country":"CN",
    "name:zho_x_preferred":[
        "\u4e8e\u6c34\u6751"
    ],
    "wof:name":"Yushuicun",
    "wof:placetype":"locality"
},
  "geometry": {"coordinates":[115.64439,33.45829000000001],"type":"Point"}
}