{
  "type": "Feature",
  "properties": {
    "gn:admin1_code":"30",
    "gn:asciiname":"Huangzhuping",
    "gn:country_code":"CN",
    "gn:dem":522,
    "gn:feature_class":"P",
    "gn:feature_code":"PPL",
    "gn:name":"Huangzhuping",
    "gn:population":0,
    "gn:timezone":"Asia/Shanghai",
    "iso:country":"CN",
    "name:zho_x_preferred":[
        "\u9ec4\u7af9\u576a"
    ],
    "wof:name":"Huangzhuping",
    "wof:placetype":"locality"
},
  "geometry": {"coordinates":[115.98557,23.77868],"type":"Point"}
}