{
  "type": "Feature",
  "properties": {
    "gn:admin1_code":"32.0",
    "gn:asciiname":"Cailuo",
    "gn:country_code":"CN",
    "gn:dem":2441,
    "gn:feature_class":"P",
    "gn:feature_code":"PPL",
    "gn:name":"Cailuo",
    "gn:population":0,
    "gn:timezone":"Asia/Shanghai",
    "iso:country":"CN",
    "name:zho_x_preferred":[
        "\u91c7\u6d1b"
    ],
    "wof:name":"Cailuo",
    "wof:placetype":"locality"
},
  "geometry": {"coordinates":[102.9101,27.86532],"type":"Point"}
}