{
  "type": "Feature",
  "properties": {
    "gn:admin1_code":"29.0",
    "gn:asciiname":"Tianbaxin",
    "gn:country_code":"CN",
    "gn:dem":2284,
    "gn:feature_class":"P",
    "gn:feature_code":"PPL",
    "gn:name":"Tianbaxin",
    "gn:population":0,
    "gn:timezone":"Asia/Shanghai",
    "iso:country":"CN",
    "name:zho_x_preferred":[
        "\u7530\u575d\u5fc3"
    ],
    "wof:name":"Tianbaxin",
    "wof:placetype":"locality"
},
  "geometry": {"coordinates":[102.598,25.995],"type":"Point"}
}