{
  "type": "Feature",
  "properties": {
    "gn:admin1_code":"15.0",
    "gn:asciiname":"Goujiashan",
    "gn:country_code":"CN",
    "gn:dem":2164,
    "gn:feature_class":"P",
    "gn:feature_code":"PPL",
    "gn:name":"Goujiashan",
    "gn:population":0,
    "gn:timezone":"Asia/Shanghai",
    "iso:country":"CN",
    "name:und_x_variant":[
        "\u82df\u5bb6\u5c71"
    ],
    "name:zho_x_preferred":[
        "\u82df\u5bb6\u5c71"
    ],
    "wof:name":"Goujiashan",
    "wof:placetype":"locality"
},
  "geometry": {"coordinates":[104.89445000000001,33.952],"type":"Point"}
}