{
  "type": "Feature",
  "properties": {
    "gn:admin1_code":"32.0",
    "gn:asciiname":"Bengbengchong",
    "gn:country_code":"CN",
    "gn:dem":2709,
    "gn:feature_class":"P",
    "gn:feature_code":"PPL",
    "gn:name":"Bengbengchong",
    "gn:population":0,
    "gn:timezone":"Asia/Shanghai",
    "iso:country":"CN",
    "name:zho_x_preferred":[
        "\u5d29\u5d29\u51b2"
    ],
    "wof:name":"Bengbengchong",
    "wof:placetype":"locality"
},
  "geometry": {"coordinates":[101.28400000000001,28.7988],"type":"Point"}
}