{
  "type": "Feature",
  "properties": {
    "gn:admin1_code":"29.0",
    "gn:asciiname":"Youben",
    "gn:country_code":"CN",
    "gn:dem":2605,
    "gn:feature_class":"P",
    "gn:feature_code":"PPL",
    "gn:name":"Youben",
    "gn:population":0,
    "gn:timezone":"Asia/Shanghai",
    "iso:country":"CN",
    "name:zho_x_preferred":[
        "\u6cb9\u672c"
    ],
    "wof:name":"Youben",
    "wof:placetype":"locality"
},
  "geometry": {"coordinates":[100.33,26.9109],"type":"Point"}
}