{
  "type": "Feature",
  "properties": {
    "gn:admin1_code":"32.0",
    "gn:asciiname":"Fengshou",
    "gn:country_code":"CN",
    "gn:dem":375,
    "gn:feature_class":"P",
    "gn:feature_code":"PPL",
    "gn:name":"Fengshou",
    "gn:population":0,
    "gn:timezone":"Asia/Shanghai",
    "iso:country":"CN",
    "name:zho_x_preferred":[
        "\u4e30\u6536"
    ],
    "wof:name":"Fengshou",
    "wof:placetype":"locality"
},
  "geometry": {"coordinates":[106.235,31.1042],"type":"Point"}
}