{
  "type": "Feature",
  "properties": {
    "gn:admin1_code":"32.0",
    "gn:asciiname":"Songmai",
    "gn:country_code":"CN",
    "gn:dem":2399,
    "gn:feature_class":"P",
    "gn:feature_code":"PPLA3",
    "gn:name":"Songmai",
    "gn:population":0,
    "gn:timezone":"Asia/Shanghai",
    "iso:country":"CN",
    "name:und_x_variant":[
        "D\u00earong",
        "Te-jung-hsien",
        "Te-jung",
        "Tehjung",
        "Te-yung",
        "Songmai",
        "Songmai Zhen"
    ],
    "name:zho_x_preferred":[
        "\u677e\u9ea6"
    ],
    "name:zho_x_variant":[
        "\u677e\u9ea6\u9547",
        "\u5f97\u8363"
    ],
    "wof:name":"Songmai",
    "wof:placetype":"locality"
},
  "geometry": {"coordinates":[99.28633000000001,28.71471],"type":"Point"}
}