{
  "type": "Feature",
  "properties": {
    "gn:admin1_code":"15",
    "gn:asciiname":"Tumen",
    "gn:cc2":"CN",
    "gn:country_code":"CN",
    "gn:dem":1753,
    "gn:feature_class":"P",
    "gn:feature_code":"PPL",
    "gn:name":"Tumen",
    "gn:population":0,
    "gn:timezone":"Asia/Shanghai",
    "iso:country":"CN",
    "name:und_x_variant":[
        "T\u2019u-men-tzu",
        "Tumenzi",
        "Tumen"
    ],
    "wof:name":"Tumen",
    "wof:placetype":"locality"
},
  "geometry": {"coordinates":[103.08056000000001,37.61861],"type":"Point"}
}