{
  "type": "Feature",
  "properties": {
    "gn:admin1_code":"15",
    "gn:asciiname":"Tumen",
    "gn:cc2":"CN",
    "gn:country_code":"CN",
    "gn:dem":1753,
    "gn:feature_class":"P",
    "gn:feature_code":"PPL",
    "gn:name":"Tumen",
    "gn:population":0,
    "gn:timezone":"Asia/Shanghai",
    "iso:country":"CN",
    "name:ceb_x_preferred":[
        "Tumen"
    ],
    "name:deu_x_preferred":[
        "Tumen"
    ],
    "name:ell_x_preferred":[
        "\u03a4\u03bf\u03cd\u03bc\u03b5\u03bd"
    ],
    "name:fas_x_preferred":[
        "\u062a\u0648\u0645\u0646"
    ],
    "name:fra_x_preferred":[
        "Tumen"
    ],
    "name:heb_x_preferred":[
        "\u05d8\u05d5\u05de\u05df"
    ],
    "name:hun_x_preferred":[
        "Tumen"
    ],
    "name:ita_x_preferred":[
        "Tumen"
    ],
    "name:nds_x_preferred":[
        "Tumen"
    ],
    "name:nld_x_preferred":[
        "Tumen"
    ],
    "name:nor_x_preferred":[
        "Tumen"
    ],
    "name:pol_x_preferred":[
        "Tumen"
    ],
    "name:spa_x_preferred":[
        "Tumen"
    ],
    "name:swe_x_preferred":[
        "Tumen"
    ],
    "name:und_x_variant":[
        "T\u2019u-men-tzu",
        "Tumenzi"
    ],
    "name:urd_x_preferred":[
        "\u0679\u06cc\u0648\u0645\u06cc\u0646"
    ],
    "wof:name":"Tumen",
    "wof:placetype":"locality"
},
  "geometry": {"coordinates":[103.08056000000001,37.61861],"type":"Point"}
}