{
  "type": "Feature",
  "properties": {
    "gn:admin1_code":"12.0",
    "gn:asciiname":"Dongnaoquan",
    "gn:country_code":"CN",
    "gn:dem":205,
    "gn:feature_class":"P",
    "gn:feature_code":"PPL",
    "gn:name":"Dongnaoquan",
    "gn:population":0,
    "gn:timezone":"Asia/Shanghai",
    "iso:country":"CN",
    "name:zho_x_preferred":[
        "Dongnaoquan"
    ],
    "name:zho_x_variant":[
        "\u6d1e\u57b4\u6cc9"
    ],
    "wof:name":"Dongnaoquan",
    "wof:placetype":"locality"
},
  "geometry": {"coordinates":[115.09465,29.6015],"type":"Point"}
}