{
  "type": "Feature",
  "properties": {
    "gn:admin1_code":"1.0",
    "gn:asciiname":"Zilaidun",
    "gn:country_code":"CN",
    "gn:dem":5,
    "gn:feature_class":"P",
    "gn:feature_code":"PPL",
    "gn:name":"Zilaidun",
    "gn:population":0,
    "gn:timezone":"Asia/Shanghai",
    "iso:country":"CN",
    "name:zho_x_preferred":[
        "\u81ea\u6765\u58a9"
    ],
    "wof:name":"Zilaidun",
    "wof:placetype":"locality"
},
  "geometry": {"coordinates":[119.00765,32.72855999999999],"type":"Point"}
}