{
  "type": "Feature",
  "properties": {
    "gn:admin1_code":"12.0",
    "gn:asciiname":"Hualingshang",
    "gn:country_code":"CN",
    "gn:dem":1111,
    "gn:feature_class":"P",
    "gn:feature_code":"PPL",
    "gn:name":"Hualingshang",
    "gn:population":0,
    "gn:timezone":"Asia/Shanghai",
    "iso:country":"CN",
    "name:zho_x_preferred":[
        "\u82b1\u5cad\u4e0a"
    ],
    "wof:name":"Hualingshang",
    "wof:placetype":"locality"
},
  "geometry": {"coordinates":[110.71165000000001,31.48915],"type":"Point"}
}