{
  "type": "Feature",
  "properties": {
    "gn:admin1_code":"1.0",
    "gn:asciiname":"Liuxucun",
    "gn:country_code":"CN",
    "gn:dem":34,
    "gn:feature_class":"P",
    "gn:feature_code":"PPL",
    "gn:name":"Liuxucun",
    "gn:population":0,
    "gn:timezone":"Asia/Shanghai",
    "iso:country":"CN",
    "name:zho_x_preferred":[
        "\u5218\u5729\u6751"
    ],
    "wof:name":"Liuxucun",
    "wof:placetype":"locality"
},
  "geometry": {"coordinates":[116.41506,33.44054000000001],"type":"Point"}
}