{
  "type": "Feature",
  "properties": {
    "gn:admin1_code":"26.0",
    "gn:asciiname":"Xiaohe",
    "gn:country_code":"CN",
    "gn:dem":899,
    "gn:feature_class":"P",
    "gn:feature_code":"PPL",
    "gn:name":"Xiaohe",
    "gn:population":0,
    "gn:timezone":"Asia/Shanghai",
    "iso:country":"CN",
    "name:ceb_x_preferred":[
        "Xiaohe"
    ],
    "name:deu_x_preferred":[
        "Xiaohe"
    ],
    "name:nor_x_preferred":[
        "Xiaohe"
    ],
    "name:swe_x_preferred":[
        "Xiaohe"
    ],
    "name:und_x_variant":[
        "Hsiao-ho",
        "Hsiao-ho-k\u2019ou",
        "Xiaohequ"
    ],
    "wof:name":"Xiaohe",
    "wof:placetype":"locality"
},
  "geometry": {"coordinates":[109.29083,33.10694],"type":"Point"}
}