{
  "type": "Feature",
  "properties": {
    "gn:admin1_code":"29.0",
    "gn:asciiname":"Heipozhai",
    "gn:country_code":"CN",
    "gn:dem":1249,
    "gn:feature_class":"P",
    "gn:feature_code":"PPL",
    "gn:name":"Heipozhai",
    "gn:population":0,
    "gn:timezone":"Asia/Shanghai",
    "iso:country":"CN",
    "name:zho_x_preferred":[
        "\u9ed1\u5761\u5be8"
    ],
    "wof:name":"Heipozhai",
    "wof:placetype":"locality"
},
  "geometry": {"coordinates":[100.97799999999999,23.3441],"type":"Point"}
}