{
  "type": "Feature",
  "properties": {
    "gn:admin1_code":"1.0",
    "gn:asciiname":"Qimen Yuanyichang",
    "gn:country_code":"CN",
    "gn:dem":135,
    "gn:feature_class":"P",
    "gn:feature_code":"PPLF",
    "gn:name":"Qimen Yuanyichang",
    "gn:population":0,
    "gn:timezone":"Asia/Shanghai",
    "iso:country":"CN",
    "name:zho_x_preferred":[
        "\u7941\u95e8\u56ed\u827a\u573a"
    ],
    "wof:name":"Qimen Yuanyichang",
    "wof:placetype":"locality"
},
  "geometry": {"coordinates":[117.76361,29.85553],"type":"Point"}
}