{
  "type": "Feature",
  "properties": {
    "gn:admin1_code":"31",
    "gn:asciiname":"Changpo",
    "gn:country_code":"CN",
    "gn:dem":18,
    "gn:feature_class":"P",
    "gn:feature_code":"PPL",
    "gn:name":"Changpo",
    "gn:population":0,
    "gn:timezone":"Asia/Shanghai",
    "iso:country":"CN",
    "name:und_x_variant":[
        "Ch\u2019ang-p\u2019o-shih",
        "Changpo",
        "\u957f\u5761"
    ],
    "wof:name":"Changpo",
    "wof:placetype":"locality"
},
  "geometry": {"coordinates":[109.42037999999999,19.69811],"type":"Point"}
}