{
  "type": "Feature",
  "properties": {
    "gn:admin1_code":"26.0",
    "gn:asciiname":"Zhifangcun",
    "gn:country_code":"CN",
    "gn:dem":1457,
    "gn:feature_class":"P",
    "gn:feature_code":"PPL",
    "gn:name":"Zhifangcun",
    "gn:population":0,
    "gn:timezone":"Asia/Shanghai",
    "iso:country":"CN",
    "name:zho_x_preferred":[
        "\u7eb8\u574a\u6751"
    ],
    "wof:name":"Zhifangcun",
    "wof:placetype":"locality"
},
  "geometry": {"coordinates":[108.26058,36.59734],"type":"Point"}
}