{
  "type": "Feature",
  "properties": {
    "gn:admin1_code":"25",
    "gn:asciiname":"Liangbaosi",
    "gn:cc2":"CN",
    "gn:country_code":"CN",
    "gn:dem":39,
    "gn:feature_class":"P",
    "gn:feature_code":"PPL",
    "gn:name":"Liangbaosi",
    "gn:population":0,
    "gn:timezone":"Asia/Shanghai",
    "iso:country":"CN",
    "name:und_x_variant":[
        "Liang-pao-ssu",
        "Liangbaosi"
    ],
    "wof:name":"Liangbaosi",
    "wof:placetype":"locality"
},
  "geometry": {"coordinates":[116.20999999999999,35.57583],"type":"Point"}
}