{
  "type": "Feature",
  "properties": {
    "gn:admin1_code":"04",
    "gn:asciiname":"Hexiaoba",
    "gn:country_code":"CN",
    "gn:dem":6,
    "gn:feature_class":"P",
    "gn:feature_code":"PPL",
    "gn:name":"Hexiaoba",
    "gn:population":0,
    "gn:timezone":"Asia/Shanghai",
    "iso:country":"CN",
    "name:und_x_variant":[
        "Hou-hsiao-pa",
        "Hexiaoba",
        "\u6cb3\u5c0f\u575d"
    ],
    "wof:name":"Hexiaoba",
    "wof:placetype":"locality"
},
  "geometry": {"coordinates":[120.90416999999999,31.70583],"type":"Point"}
}