{
  "type": "Feature",
  "properties": {
    "gn:admin1_code":"5.0",
    "gn:asciiname":"Shanxitoucun",
    "gn:country_code":"CN",
    "gn:dem":195,
    "gn:feature_class":"P",
    "gn:feature_code":"PPL",
    "gn:name":"Shanxitoucun",
    "gn:population":0,
    "gn:timezone":"Asia/Shanghai",
    "iso:country":"CN",
    "name:zho_x_preferred":[
        "\u5c71\u897f\u5934\u6751"
    ],
    "wof:name":"Shanxitoucun",
    "wof:placetype":"locality"
},
  "geometry": {"coordinates":[125.34677000000001,44.16668],"type":"Point"}
}