{
  "type": "Feature",
  "properties": {
    "gn:admin1_code":"29.0",
    "gn:asciiname":"Bainiuchang",
    "gn:country_code":"CN",
    "gn:dem":2158,
    "gn:feature_class":"P",
    "gn:feature_code":"PPL",
    "gn:name":"Bainiuchang",
    "gn:population":0,
    "gn:timezone":"Asia/Shanghai",
    "iso:country":"CN",
    "name:und_x_variant":[
        "\u767d\u725b\u5382"
    ],
    "wof:name":"Bainiuchang",
    "wof:placetype":"locality"
},
  "geometry": {"coordinates":[103.23896000000001,27.05376],"type":"Point"}
}