{
  "type": "Feature",
  "properties": {
    "gn:admin1_code":"16.0",
    "gn:asciiname":"Shanghuangling",
    "gn:country_code":"CN",
    "gn:dem":78,
    "gn:feature_class":"P",
    "gn:feature_code":"PPL",
    "gn:name":"Shanghuangling",
    "gn:population":0,
    "gn:timezone":"Asia/Shanghai",
    "iso:country":"CN",
    "name:zho_x_preferred":[
        "\u4e0a\u9ec4\u5cad"
    ],
    "wof:name":"Shanghuangling",
    "wof:placetype":"locality"
},
  "geometry": {"coordinates":[109.38800000000001,23.2141],"type":"Point"}
}