{
  "type": "Feature",
  "properties": {
    "gn:admin1_code":"32.0",
    "gn:asciiname":"Anluluo",
    "gn:country_code":"CN",
    "gn:dem":1875,
    "gn:feature_class":"P",
    "gn:feature_code":"PPL",
    "gn:name":"Anl\u00fcl\u00fco",
    "gn:population":0,
    "gn:timezone":"Asia/Shanghai",
    "iso:country":"CN",
    "name:und_x_variant":[
        "Anl\u00fcl\u00fco"
    ],
    "name:zho_x_preferred":[
        "\u5b89\u5415\u6d1b"
    ],
    "wof:name":"Anluluo",
    "wof:placetype":"locality"
},
  "geometry": {"coordinates":[102.65000000000001,29.0448],"type":"Point"}
}