{
  "type": "Feature",
  "properties": {
    "gn:admin1_code":"31",
    "gn:asciiname":"Zhi'e",
    "gn:country_code":"CN",
    "gn:dem":291,
    "gn:feature_class":"P",
    "gn:feature_code":"PPL",
    "gn:name":"Zhi\u2019e",
    "gn:population":0,
    "gn:timezone":"Asia/Shanghai",
    "iso:country":"CN",
    "name:und_x_variant":[
        "Zhi\u2019e",
        "\u53ea\u5ce8"
    ],
    "wof:name":"Zhi'e",
    "wof:placetype":"locality"
},
  "geometry": {"coordinates":[109.161,18.521],"type":"Point"}
}