{
  "type": "Feature",
  "properties": {
    "gn:admin1_code":"1.0",
    "gn:asciiname":"Dengdiancun",
    "gn:country_code":"CN",
    "gn:dem":34,
    "gn:feature_class":"P",
    "gn:feature_code":"PPL",
    "gn:name":"Dengdiancun",
    "gn:population":0,
    "gn:timezone":"Asia/Shanghai",
    "iso:country":"CN",
    "name:zho_x_preferred":[
        "\u9093\u5e97\u6751"
    ],
    "wof:name":"Dengdiancun",
    "wof:placetype":"locality"
},
  "geometry": {"coordinates":[117.14490000000001,31.8977],"type":"Point"}
}