{
  "type": "Feature",
  "properties": {
    "gn:admin1_code":"29.0",
    "gn:asciiname":"Tengqing",
    "gn:country_code":"CN",
    "gn:dem":2363,
    "gn:feature_class":"P",
    "gn:feature_code":"PPL",
    "gn:name":"Tengqing",
    "gn:population":0,
    "gn:timezone":"Asia/Shanghai",
    "iso:country":"CN",
    "name:zho_x_preferred":[
        "\u85e4\u7b90"
    ],
    "wof:name":"Tengqing",
    "wof:placetype":"locality"
},
  "geometry": {"coordinates":[99.34269999999999,26.0974],"type":"Point"}
}