{
  "type": "Feature",
  "properties": {
    "gn:admin1_code":"20.0",
    "gn:asciiname":"Nanjinggou",
    "gn:country_code":"CN",
    "gn:dem":1564,
    "gn:feature_class":"P",
    "gn:feature_code":"PPL",
    "gn:name":"Nanjinggou",
    "gn:population":0,
    "gn:timezone":"Asia/Shanghai",
    "iso:country":"CN",
    "name:und_x_variant":[
        "\u5357\u4e95\u6c9f"
    ],
    "wof:name":"Nanjinggou",
    "wof:placetype":"locality"
},
  "geometry": {"coordinates":[111.65517,41.04227],"type":"Point"}
}