{
  "type": "Feature",
  "properties": {
    "gn:admin1_code":"10.0",
    "gn:asciiname":"Liang'anzi",
    "gn:country_code":"CN",
    "gn:dem":8,
    "gn:feature_class":"P",
    "gn:feature_code":"PPL",
    "gn:name":"Liang\u2019anzi",
    "gn:population":0,
    "gn:timezone":"Asia/Shanghai",
    "iso:country":"CN",
    "name:und_x_variant":[
        "Liang\u2019anzi"
    ],
    "name:zho_x_preferred":[
        "\u6881\u5b89\u5b50"
    ],
    "wof:name":"Liang'anzi",
    "wof:placetype":"locality"
},
  "geometry": {"coordinates":[117.61194,39.88734],"type":"Point"}
}