{
  "type": "Feature",
  "properties": {
    "gn:admin1_code":"29.0",
    "gn:asciiname":"Liaojiadaqing",
    "gn:country_code":"CN",
    "gn:dem":1636,
    "gn:feature_class":"P",
    "gn:feature_code":"PPL",
    "gn:name":"Liaojiadaqing",
    "gn:population":0,
    "gn:timezone":"Asia/Shanghai",
    "iso:country":"CN",
    "name:zho_x_preferred":[
        "\u5ed6\u5bb6\u5927\u7b90"
    ],
    "wof:name":"Liaojiadaqing",
    "wof:placetype":"locality"
},
  "geometry": {"coordinates":[100.11799999999999,25.1528],"type":"Point"}
}