{
  "type": "Feature",
  "properties": {
    "gn:admin1_code":"4.0",
    "gn:asciiname":"Beidijiadun",
    "gn:country_code":"CN",
    "gn:dem":-2,
    "gn:feature_class":"P",
    "gn:feature_code":"PPL",
    "gn:name":"Beidijiadun",
    "gn:population":0,
    "gn:timezone":"Asia/Shanghai",
    "iso:country":"CN",
    "name:zho_x_preferred":[
        "Beidijiadun"
    ],
    "name:zho_x_variant":[
        "\u5317\u7fdf\u5bb6\u58a9"
    ],
    "wof:name":"Beidijiadun",
    "wof:placetype":"locality"
},
  "geometry": {"coordinates":[119.76445,33.83501],"type":"Point"}
}