{
  "type": "Feature",
  "properties": {
    "gn:admin1_code":"8.0",
    "gn:asciiname":"Wulingjiucun",
    "gn:country_code":"CN",
    "gn:dem":349,
    "gn:feature_class":"P",
    "gn:feature_code":"PPL",
    "gn:name":"Wulingjiucun",
    "gn:population":0,
    "gn:timezone":"Asia/Shanghai",
    "iso:country":"CN",
    "name:zho_x_preferred":[
        "\u4e94\u96f6\u4e5d\u6751"
    ],
    "wof:name":"Wulingjiucun",
    "wof:placetype":"locality"
},
  "geometry": {"coordinates":[129.22897,47.86301],"type":"Point"}
}