{
  "type": "Feature",
  "properties": {
    "gn:admin1_code":"32.0",
    "gn:asciiname":"Sanxue",
    "gn:country_code":"CN",
    "gn:dem":408,
    "gn:feature_class":"P",
    "gn:feature_code":"PPL",
    "gn:name":"Sanxue",
    "gn:population":0,
    "gn:timezone":"Asia/Shanghai",
    "iso:country":"CN",
    "name:zho_x_preferred":[
        "\u4e09\u5b66"
    ],
    "wof:name":"Sanxue",
    "wof:placetype":"locality"
},
  "geometry": {"coordinates":[105.489,31.2206],"type":"Point"}
}