{
  "type": "Feature",
  "properties": {
    "gn:admin1_code":"10.0",
    "gn:asciiname":"Sichang Qidui",
    "gn:country_code":"CN",
    "gn:dem":3,
    "gn:feature_class":"P",
    "gn:feature_code":"PPLF",
    "gn:name":"Sichang Qidui",
    "gn:population":0,
    "gn:timezone":"Asia/Shanghai",
    "iso:country":"CN",
    "name:zho_x_preferred":[
        "\u56db\u573a\u4e03\u961f"
    ],
    "wof:name":"Sichang Qidui",
    "wof:placetype":"locality"
},
  "geometry": {"coordinates":[118.41876999999999,39.22599],"type":"Point"}
}