{
  "type": "Feature",
  "properties": {
    "gn:admin1_code":"15.0",
    "gn:asciiname":"Guyaowan",
    "gn:country_code":"CN",
    "gn:dem":2323,
    "gn:feature_class":"P",
    "gn:feature_code":"PPL",
    "gn:name":"Guyaowan",
    "gn:population":0,
    "gn:timezone":"Asia/Shanghai",
    "iso:country":"CN",
    "name:zho_x_preferred":[
        "\u53e4\u7a91\u6e7e"
    ],
    "wof:name":"Guyaowan",
    "wof:placetype":"locality"
},
  "geometry": {"coordinates":[104.432,36.2165],"type":"Point"}
}