{
  "type": "Feature",
  "properties": {
    "gn:admin1_code":"19.0",
    "gn:asciiname":"Jiguanlazi",
    "gn:country_code":"CN",
    "gn:dem":369,
    "gn:feature_class":"P",
    "gn:feature_code":"PPL",
    "gn:name":"Jiguanlazi",
    "gn:population":0,
    "gn:timezone":"Asia/Shanghai",
    "iso:country":"CN",
    "name:zho_x_preferred":[
        "\u9e21\u51a0\u782c\u5b50"
    ],
    "wof:name":"Jiguanlazi",
    "wof:placetype":"locality"
},
  "geometry": {"coordinates":[125.46477,41.20356],"type":"Point"}
}