{
  "type": "Feature",
  "properties": {
    "gn:admin1_code":"2.0",
    "gn:asciiname":"Dahouzhou",
    "gn:country_code":"CN",
    "gn:dem":375,
    "gn:feature_class":"P",
    "gn:feature_code":"PPL",
    "gn:name":"Dahouzhou",
    "gn:population":0,
    "gn:timezone":"Asia/Shanghai",
    "iso:country":"CN",
    "name:zho_x_preferred":[
        "\u5927\u5019\u5468"
    ],
    "wof:name":"Dahouzhou",
    "wof:placetype":"locality"
},
  "geometry": {"coordinates":[119.23942,28.68686],"type":"Point"}
}