{
  "type": "Feature",
  "properties": {
    "gn:admin1_code":"9.0",
    "gn:asciiname":"Liuying",
    "gn:country_code":"CN",
    "gn:dem":37,
    "gn:feature_class":"P",
    "gn:feature_code":"PPL",
    "gn:name":"Liuying",
    "gn:population":0,
    "gn:timezone":"Asia/Shanghai",
    "iso:country":"CN",
    "name:zho_x_preferred":[
        "\u5218\u8425"
    ],
    "wof:name":"Liuying",
    "wof:placetype":"locality"
},
  "geometry": {"coordinates":[115.41269,32.42769000000001],"type":"Point"}
}