{
  "type": "Feature",
  "properties": {
    "gn:admin1_code":"8.0",
    "gn:asciiname":"Duluhe",
    "gn:country_code":"CN",
    "gn:dem":75,
    "gn:feature_class":"P",
    "gn:feature_code":"PPL",
    "gn:name":"Duluhe",
    "gn:population":0,
    "gn:timezone":"Asia/Shanghai",
    "iso:country":"CN",
    "name:zho_x_preferred":[
        "\u561f\u565c\u6cb3"
    ],
    "wof:name":"Duluhe",
    "wof:placetype":"locality"
},
  "geometry": {"coordinates":[130.83708999999999,47.37186],"type":"Point"}
}