{
  "type": "Feature",
  "properties": {
    "gn:admin1_code":"11.0",
    "gn:asciiname":"Jinjipo",
    "gn:country_code":"CN",
    "gn:dem":401,
    "gn:feature_class":"P",
    "gn:feature_code":"PPL",
    "gn:name":"Jinjipo",
    "gn:population":0,
    "gn:timezone":"Asia/Shanghai",
    "iso:country":"CN",
    "name:zho_x_preferred":[
        "\u91d1\u9e21\u5761"
    ],
    "wof:name":"Jinjipo",
    "wof:placetype":"locality"
},
  "geometry": {"coordinates":[109.81876,28.8292],"type":"Point"}
}