{
  "type": "Feature",
  "properties": {
    "gn:admin1_code":"32.0",
    "gn:asciiname":"Mafengcun",
    "gn:country_code":"CN",
    "gn:dem":3348,
    "gn:feature_class":"P",
    "gn:feature_code":"PPL",
    "gn:name":"Mafengcun",
    "gn:population":0,
    "gn:timezone":"Asia/Shanghai",
    "iso:country":"CN",
    "name:zho_x_preferred":[
        "\u9ebb\u75af\u6751"
    ],
    "wof:name":"Mafengcun",
    "wof:placetype":"locality"
},
  "geometry": {"coordinates":[103.77397999999999,32.63217],"type":"Point"}
}