{
  "type": "Feature",
  "properties": {
    "gn:admin1_code":"1.0",
    "gn:asciiname":"Xiangyuan",
    "gn:country_code":"CN",
    "gn:dem":50,
    "gn:feature_class":"P",
    "gn:feature_code":"PPL",
    "gn:name":"Xiangyuan",
    "gn:population":0,
    "gn:timezone":"Asia/Shanghai",
    "iso:country":"CN",
    "name:zho_x_preferred":[
        "\u7965\u56ed"
    ],
    "wof:name":"Xiangyuan",
    "wof:placetype":"locality"
},
  "geometry": {"coordinates":[118.33722,30.80441],"type":"Point"}
}