{
  "type": "Feature",
  "properties": {
    "gn:admin1_code":"30",
    "gn:asciiname":"Ningtang",
    "gn:country_code":"CN",
    "gn:dem":134,
    "gn:feature_class":"P",
    "gn:feature_code":"PPLA4",
    "gn:name":"Ningtang",
    "gn:population":0,
    "gn:timezone":"Asia/Shanghai",
    "iso:country":"CN",
    "name:und_x_variant":[
        "Ningtang Zhen"
    ],
    "name:zho_x_preferred":[
        "\u5b81\u5858"
    ],
    "name:zho_x_variant":[
        "\u5b81\u5858\u9547"
    ],
    "wof:name":"Ningtang",
    "wof:placetype":"locality"
},
  "geometry": {"coordinates":[115.74748999999998,24.17542000000001],"type":"Point"}
}