{
  "type": "Feature",
  "properties": {
    "gn:admin1_code":"16",
    "gn:asciiname":"Shamushui",
    "gn:country_code":"CN",
    "gn:dem":817,
    "gn:feature_class":"P",
    "gn:feature_code":"PPL",
    "gn:name":"Shamushui",
    "gn:population":0,
    "gn:timezone":"Asia/Shanghai",
    "iso:country":"CN",
    "name:zho_x_preferred":[
        "\u6749\u6728\u6c34"
    ],
    "wof:name":"Shamushui",
    "wof:placetype":"locality"
},
  "geometry": {"coordinates":[110.553,26.0345],"type":"Point"}
}