{
  "type": "Feature",
  "properties": {
    "gn:admin1_code":"18.0",
    "gn:asciiname":"Heshui",
    "gn:country_code":"CN",
    "gn:dem":805,
    "gn:feature_class":"P",
    "gn:feature_code":"PPL",
    "gn:name":"Heshui",
    "gn:population":0,
    "gn:timezone":"Asia/Shanghai",
    "iso:country":"CN",
    "name:zho_x_preferred":[
        "\u548c\u6c34"
    ],
    "wof:name":"Heshui",
    "wof:placetype":"locality"
},
  "geometry": {"coordinates":[109.042,26.04],"type":"Point"}
}