{
  "type": "Feature",
  "properties": {
    "gn:admin1_code":"24.0",
    "gn:asciiname":"Xiweicun",
    "gn:country_code":"CN",
    "gn:dem":994,
    "gn:feature_class":"P",
    "gn:feature_code":"PPL",
    "gn:name":"Xiweicun",
    "gn:population":0,
    "gn:timezone":"Asia/Shanghai",
    "iso:country":"CN",
    "name:zho_x_preferred":[
        "\u897f\u9b4f\u6751"
    ],
    "wof:name":"Xiweicun",
    "wof:placetype":"locality"
},
  "geometry": {"coordinates":[113.18772,39.21018],"type":"Point"}
}