{
  "type": "Feature",
  "properties": {
    "gn:admin1_code":"14.0",
    "gn:asciiname":"Jimaicun",
    "gn:country_code":"CN",
    "gn:dem":3642,
    "gn:feature_class":"P",
    "gn:feature_code":"PPL",
    "gn:name":"Jimaicun",
    "gn:population":0,
    "gn:timezone":"Asia/Urumqi",
    "iso:country":"CN",
    "name:zho_x_preferred":[
        "\u5409\u9ea6\u6751"
    ],
    "wof:name":"Jimaicun",
    "wof:placetype":"locality"
},
  "geometry": {"coordinates":[92.57805,28.22367],"type":"Point"}
}