{
  "type": "Feature",
  "properties": {
    "gn:admin1_code":"14.0",
    "gn:asciiname":"Migba",
    "gn:country_code":"CN",
    "gn:dem":3421,
    "gn:feature_class":"P",
    "gn:feature_code":"PPL",
    "gn:name":"Migba",
    "gn:population":0,
    "gn:timezone":"Asia/Urumqi",
    "iso:country":"CN",
    "name:bod_x_preferred":[
        "Migba"
    ],
    "name:zho_x_preferred":[
        "Miba"
    ],
    "name:zho_x_variant":[
        "\u7c73\u5df4"
    ],
    "wof:name":"Migba",
    "wof:placetype":"locality"
},
  "geometry": {"coordinates":[97.20099999999999,31.401],"type":"Point"}
}