{
  "type": "Feature",
  "properties": {
    "gn:admin1_code":"29",
    "gn:asciiname":"Hongpojiao",
    "gn:country_code":"CN",
    "gn:dem":1210,
    "gn:feature_class":"P",
    "gn:feature_code":"PPL",
    "gn:name":"Hongpojiao",
    "gn:population":0,
    "gn:timezone":"Asia/Shanghai",
    "iso:country":"CN",
    "name:zho_x_preferred":[
        "\u7ea2\u5761\u811a"
    ],
    "wof:name":"Hongpojiao",
    "wof:placetype":"locality"
},
  "geometry": {"coordinates":[105.01900000000001,23.8951],"type":"Point"}
}