{
  "type": "Feature",
  "properties": {
    "gn:admin1_code":"18",
    "gn:asciiname":"Yangfukan",
    "gn:country_code":"CN",
    "gn:dem":769,
    "gn:feature_class":"P",
    "gn:feature_code":"PPL",
    "gn:name":"Yangfukan",
    "gn:population":0,
    "gn:timezone":"Asia/Shanghai",
    "iso:country":"CN",
    "name:zho_x_preferred":[
        "\u7f8a\u590d\u574e"
    ],
    "wof:name":"Yangfukan",
    "wof:placetype":"locality"
},
  "geometry": {"coordinates":[106.679,28.0261],"type":"Point"}
}