{
  "type": "Feature",
  "properties": {
    "gn:admin1_code":"32.0",
    "gn:asciiname":"Daiba",
    "gn:country_code":"CN",
    "gn:dem":919,
    "gn:feature_class":"P",
    "gn:feature_code":"PPL",
    "gn:name":"Daiba",
    "gn:population":0,
    "gn:timezone":"Asia/Shanghai",
    "iso:country":"CN",
    "name:zho_x_preferred":[
        "\u4ee3\u575d"
    ],
    "wof:name":"Daiba",
    "wof:placetype":"locality"
},
  "geometry": {"coordinates":[104.72,32.386],"type":"Point"}
}