{
  "type": "Feature",
  "properties": {
    "gn:admin1_code":"4.0",
    "gn:asciiname":"Zhengxing",
    "gn:country_code":"CN",
    "gn:dem":2,
    "gn:feature_class":"P",
    "gn:feature_code":"PPL",
    "gn:name":"Zhengxing",
    "gn:population":0,
    "gn:timezone":"Asia/Shanghai",
    "iso:country":"CN",
    "name:zho_x_preferred":[
        "Zhengxing"
    ],
    "name:zho_x_variant":[
        "\u6b63\u5174"
    ],
    "wof:name":"Zhengxing",
    "wof:placetype":"locality"
},
  "geometry": {"coordinates":[119.50181000000001,34.44778],"type":"Point"}
}