{
  "type": "Feature",
  "properties": {
    "gn:admin1_code":"12.0",
    "gn:asciiname":"Zhonghuanggongyuan",
    "gn:country_code":"CN",
    "gn:dem":29,
    "gn:feature_class":"P",
    "gn:feature_code":"PPL",
    "gn:name":"Zhonghuanggongyuan",
    "gn:population":0,
    "gn:timezone":"Asia/Shanghai",
    "iso:country":"CN",
    "name:zho_x_preferred":[
        "\u4e2d\u7687\u516c\u57b8"
    ],
    "wof:name":"Zhonghuanggongyuan",
    "wof:placetype":"locality"
},
  "geometry": {"coordinates":[112.91916999999999,29.81177000000001],"type":"Point"}
}