{
  "type": "Feature",
  "properties": {
    "gn:admin1_code":"11",
    "gn:asciiname":"Baiyunshan Chumuchang",
    "gn:country_code":"CN",
    "gn:dem":920,
    "gn:feature_class":"P",
    "gn:feature_code":"PPL",
    "gn:name":"Baiyunshan Chumuchang",
    "gn:population":0,
    "gn:timezone":"Asia/Shanghai",
    "iso:country":"CN",
    "wof:name":"Baiyunshan Chumuchang",
    "wof:placetype":"locality"
},
  "geometry": {"coordinates":[109.40000000000001,28.71444],"type":"Point"}
}