{
  "type": "Feature",
  "properties": {
    "gn:admin1_code":"1.0",
    "gn:asciiname":"Zhannongcun",
    "gn:country_code":"CN",
    "gn:dem":28,
    "gn:feature_class":"P",
    "gn:feature_code":"PPLF",
    "gn:name":"Zhannongcun",
    "gn:population":0,
    "gn:timezone":"Asia/Shanghai",
    "iso:country":"CN",
    "name:zho_x_preferred":[
        "\u5c55\u519c\u6751"
    ],
    "wof:name":"Zhannongcun",
    "wof:placetype":"locality"
},
  "geometry": {"coordinates":[117.55181,31.64157],"type":"Point"}
}