{
  "type": "Feature",
  "properties": {
    "gn:admin1_code":"11",
    "gn:asciiname":"Bishagou",
    "gn:country_code":"CN",
    "gn:dem":448,
    "gn:feature_class":"P",
    "gn:feature_code":"PPLA4",
    "gn:name":"Bishagou",
    "gn:population":0,
    "gn:timezone":"Asia/Shanghai",
    "iso:country":"CN",
    "name:und_x_variant":[
        "Xihu Xiang",
        "Bishagou"
    ],
    "name:zho_x_preferred":[
        "\u6bd4\u6c99\u6c9f"
    ],
    "name:zho_x_variant":[
        "\u897f\u6e56\u4e61"
    ],
    "wof:name":"Bishagou",
    "wof:placetype":"locality"
},
  "geometry": {"coordinates":[109.59139,29.34264000000001],"type":"Point"}
}