{
  "type": "Feature",
  "properties": {
    "gn:admin1_code":"25",
    "gn:asciiname":"Wangquan",
    "gn:country_code":"CN",
    "gn:dem":336,
    "gn:feature_class":"P",
    "gn:feature_code":"PPL",
    "gn:name":"Wangquan",
    "gn:population":0,
    "gn:timezone":"Asia/Shanghai",
    "iso:country":"CN",
    "name:zho_x_preferred":[
        "\u738b\u6cc9"
    ],
    "wof:name":"Wangquan",
    "wof:placetype":"locality"
},
  "geometry": {"coordinates":[116.95,36.459],"type":"Point"}
}