{
  "type": "Feature",
  "properties": {
    "gn:admin1_code":"15.0",
    "gn:asciiname":"Kasashui",
    "gn:country_code":"CN",
    "gn:dem":2965,
    "gn:feature_class":"P",
    "gn:feature_code":"PPL",
    "gn:name":"Kasashui",
    "gn:population":0,
    "gn:timezone":"Asia/Shanghai",
    "iso:country":"CN",
    "name:zho_x_preferred":[
        "\u5361\u6d12\u6c34"
    ],
    "wof:name":"Kasashui",
    "wof:placetype":"locality"
},
  "geometry": {"coordinates":[101.962,37.9414],"type":"Point"}
}