{
  "type": "Feature",
  "properties": {
    "gn:admin1_code":"30",
    "gn:asciiname":"Chengyue",
    "gn:country_code":"CN",
    "gn:dem":20,
    "gn:feature_class":"P",
    "gn:feature_code":"PPLA4",
    "gn:name":"Chengyue",
    "gn:population":0,
    "gn:timezone":"Asia/Urumqi",
    "iso:country":"CN",
    "name:und_x_variant":[
        "Shinguet",
        "Ch\u2019eng-y\u00fceh-shih",
        "Shingyueh",
        "Ch\u2019eng-y\u00fceh",
        "Shingyuet",
        "\u57ce\u6708",
        "Chengyue",
        "Chengyue Zhen",
        "\u57ce\u6708\u9547"
    ],
    "wof:name":"Chengyue",
    "wof:placetype":"locality"
},
  "geometry": {"coordinates":[110.07214,21.16679],"type":"Point"}
}