{
  "type": "Feature",
  "properties": {
    "gn:admin1_code":"14.0",
    "gn:asciiname":"Kainag",
    "gn:country_code":"CN",
    "gn:dem":5007,
    "gn:feature_class":"P",
    "gn:feature_code":"PPL",
    "gn:name":"Kainag",
    "gn:population":0,
    "gn:timezone":"Asia/Urumqi",
    "iso:country":"CN",
    "name:bod_x_preferred":[
        "Kainag"
    ],
    "name:zho_x_preferred":[
        "Kaina"
    ],
    "name:zho_x_variant":[
        "\u51ef\u90a3"
    ],
    "wof:name":"Kainag",
    "wof:placetype":"locality"
},
  "geometry": {"coordinates":[92.301,32.001],"type":"Point"}
}