{
  "type": "Feature",
  "properties": {
    "gn:admin1_code":"29.0",
    "gn:asciiname":"Baofengsi",
    "gn:country_code":"CN",
    "gn:dem":2147,
    "gn:feature_class":"P",
    "gn:feature_code":"PPL",
    "gn:name":"Baofengsi",
    "gn:population":0,
    "gn:timezone":"Asia/Shanghai",
    "iso:country":"CN",
    "name:zho_x_preferred":[
        "\u5b9d\u4e30\u5bfa"
    ],
    "wof:name":"Baofengsi",
    "wof:placetype":"locality"
},
  "geometry": {"coordinates":[100.33199999999999,25.7997],"type":"Point"}
}