{
  "type": "Feature",
  "properties": {
    "gn:admin1_code":"18",
    "gn:asciiname":"Daoxuantang",
    "gn:country_code":"CN",
    "gn:dem":1155,
    "gn:feature_class":"P",
    "gn:feature_code":"PPL",
    "gn:name":"Daoxuantang",
    "gn:population":0,
    "gn:timezone":"Asia/Shanghai",
    "iso:country":"CN",
    "name:zho_x_preferred":[
        "\u5012\u65cb\u5858"
    ],
    "wof:name":"Daoxuantang",
    "wof:placetype":"locality"
},
  "geometry": {"coordinates":[106.11,27.5618],"type":"Point"}
}