{
  "type": "Feature",
  "properties": {
    "gn:admin1_code":"32.0",
    "gn:asciiname":"Liuhuangshui",
    "gn:country_code":"CN",
    "gn:dem":1259,
    "gn:feature_class":"P",
    "gn:feature_code":"PPL",
    "gn:name":"Liuhuangshui",
    "gn:population":0,
    "gn:timezone":"Asia/Shanghai",
    "iso:country":"CN",
    "name:zho_x_preferred":[
        "\u6d41\u9ec4\u6c34"
    ],
    "wof:name":"Liuhuangshui",
    "wof:placetype":"locality"
},
  "geometry": {"coordinates":[103.09126999999999,29.21509],"type":"Point"}
}