{
  "type": "Feature",
  "properties": {
    "gn:admin1_code":"7",
    "gn:asciiname":"Kantoudian",
    "gn:country_code":"CN",
    "gn:dem":172,
    "gn:feature_class":"P",
    "gn:feature_code":"PPL",
    "gn:name":"Kantoudian",
    "gn:population":0,
    "gn:timezone":"Asia/Shanghai",
    "iso:country":"CN",
    "name:zho_x_preferred":[
        "\u574e\u5934\u5e97"
    ],
    "wof:name":"Kantoudian",
    "wof:placetype":"locality"
},
  "geometry": {"coordinates":[118.94222000000001,25.63222],"type":"Point"}
}