{
  "type": "Feature",
  "properties": {
    "gn:admin1_code":"25",
    "gn:asciiname":"Daxiapo",
    "gn:country_code":"CN",
    "gn:dem":110,
    "gn:feature_class":"P",
    "gn:feature_code":"PPL",
    "gn:name":"Daxiapo",
    "gn:population":0,
    "gn:timezone":"Asia/Shanghai",
    "iso:country":"CN",
    "name:zho_x_preferred":[
        "\u5927\u4e0b\u5761"
    ],
    "wof:name":"Daxiapo",
    "wof:placetype":"locality"
},
  "geometry": {"coordinates":[119.056,36.0118],"type":"Point"}
}