{
  "type": "Feature",
  "properties": {
    "gn:admin1_code":"30",
    "gn:asciiname":"Haishapo",
    "gn:country_code":"CN",
    "gn:dem":9,
    "gn:feature_class":"P",
    "gn:feature_code":"PPL",
    "gn:name":"Haishapo",
    "gn:population":0,
    "gn:timezone":"Asia/Urumqi",
    "iso:country":"CN",
    "name:und_x_variant":[
        "Sha-p\u2019o",
        "Haishapo"
    ],
    "name:zho_x_preferred":[
        "\u6d77\u6c99\u5761"
    ],
    "wof:name":"Haishapo",
    "wof:placetype":"locality"
},
  "geometry": {"coordinates":[110.94698,21.41796],"type":"Point"}
}