{
  "type": "Feature",
  "properties": {
    "gn:admin1_code":"9.0",
    "gn:asciiname":"Zushicun",
    "gn:country_code":"CN",
    "gn:dem":67,
    "gn:feature_class":"P",
    "gn:feature_code":"PPL",
    "gn:name":"Zushicun",
    "gn:population":0,
    "gn:timezone":"Asia/Shanghai",
    "iso:country":"CN",
    "name:und_x_variant":[
        "\u7956\u5e08\u6751"
    ],
    "name:zho_x_preferred":[
        "\u7956\u5e08\u6751"
    ],
    "wof:name":"Zushicun",
    "wof:placetype":"locality"
},
  "geometry": {"coordinates":[113.87456,33.99307],"type":"Point"}
}