{
  "type": "Feature",
  "properties": {
    "gn:admin1_code":"18.0",
    "gn:asciiname":"Yachan",
    "gn:country_code":"CN",
    "gn:dem":571,
    "gn:feature_class":"P",
    "gn:feature_code":"PPL",
    "gn:name":"Yachan",
    "gn:population":0,
    "gn:timezone":"Asia/Shanghai",
    "iso:country":"CN",
    "name:zho_x_preferred":[
        "\u7259\u8749"
    ],
    "wof:name":"Yachan",
    "wof:placetype":"locality"
},
  "geometry": {"coordinates":[109.169,26.0398],"type":"Point"}
}