{
  "type": "Feature",
  "properties": {
    "gn:admin1_code":"23",
    "gn:asciiname":"Daoyuan",
    "gn:cc2":"CN",
    "gn:country_code":"CN",
    "gn:dem":4,
    "gn:feature_class":"P",
    "gn:feature_code":"PPL",
    "gn:name":"Daoyuan",
    "gn:population":0,
    "gn:timezone":"Asia/Shanghai",
    "iso:country":"CN",
    "name:und_x_variant":[
        "Tao-y\u00fcan -chen",
        "Daoyuan"
    ],
    "wof:name":"Daoyuan",
    "wof:placetype":"locality"
},
  "geometry": {"coordinates":[121.485,30.87056],"type":"Point"}
}