{
  "type": "Feature",
  "properties": {
    "gn:admin1_code":"10.0",
    "gn:asciiname":"Jimingzhuang",
    "gn:country_code":"CN",
    "gn:dem":63,
    "gn:feature_class":"P",
    "gn:feature_code":"PPL",
    "gn:name":"Jimingzhuang",
    "gn:population":0,
    "gn:timezone":"Asia/Shanghai",
    "iso:country":"CN",
    "name:zho_x_preferred":[
        "\u9e21\u9e23\u5e84"
    ],
    "wof:name":"Jimingzhuang",
    "wof:placetype":"locality"
},
  "geometry": {"coordinates":[118.82940000000001,40.08794],"type":"Point"}
}