{
  "type": "Feature",
  "properties": {
    "gn:admin1_code":"11.0",
    "gn:asciiname":"Yangwuzui",
    "gn:country_code":"CN",
    "gn:dem":80,
    "gn:feature_class":"P",
    "gn:feature_code":"PPL",
    "gn:name":"Yangwuzui",
    "gn:population":0,
    "gn:timezone":"Asia/Shanghai",
    "iso:country":"CN",
    "name:zho_x_preferred":[
        "\u6d0b\u6b66\u5480"
    ],
    "wof:name":"Yangwuzui",
    "wof:placetype":"locality"
},
  "geometry": {"coordinates":[112.87956,26.42199],"type":"Point"}
}