{
  "type": "Feature",
  "properties": {
    "gn:admin1_code":"02",
    "gn:asciiname":"Luodian",
    "gn:country_code":"CN",
    "gn:dem":98,
    "gn:feature_class":"P",
    "gn:feature_code":"PPLA4",
    "gn:name":"Luodian",
    "gn:population":0,
    "gn:timezone":"Asia/Shanghai",
    "iso:country":"CN",
    "name:und_x_variant":[
        "\u7f57\u5e97",
        "Luodian",
        "Luodian Zhen"
    ],
    "name:zho_x_preferred":[
        "\u7f57\u5e97\u9547"
    ],
    "wof:name":"Luodian",
    "wof:placetype":"locality"
},
  "geometry": {"coordinates":[119.61415,29.1616],"type":"Point"}
}