{
  "type": "Feature",
  "properties": {
    "gn:admin1_code":"14.0",
    "gn:asciiname":"Kougamucun",
    "gn:country_code":"CN",
    "gn:dem":4670,
    "gn:feature_class":"P",
    "gn:feature_code":"PPL",
    "gn:name":"Kougamucun",
    "gn:population":0,
    "gn:timezone":"Asia/Urumqi",
    "iso:country":"CN",
    "name:zho_x_preferred":[
        "\u6263\u560e\u6728\u6751"
    ],
    "wof:name":"Kougamucun",
    "wof:placetype":"locality"
},
  "geometry": {"coordinates":[90.69334000000001,31.16548],"type":"Point"}
}