{
  "type": "Feature",
  "properties": {
    "gn:admin1_code":"32.0",
    "gn:asciiname":"Huozhuanmiao",
    "gn:country_code":"CN",
    "gn:dem":520,
    "gn:feature_class":"P",
    "gn:feature_code":"PPL",
    "gn:name":"Huozhuanmiao",
    "gn:population":0,
    "gn:timezone":"Asia/Shanghai",
    "iso:country":"CN",
    "name:zho_x_preferred":[
        "\u706b\u7816\u5e99"
    ],
    "wof:name":"Huozhuanmiao",
    "wof:placetype":"locality"
},
  "geometry": {"coordinates":[104.27128999999999,31.20368],"type":"Point"}
}