{
  "type": "Feature",
  "properties": {
    "gn:admin1_code":"18",
    "gn:asciiname":"Tiekeng",
    "gn:country_code":"CN",
    "gn:dem":519,
    "gn:feature_class":"P",
    "gn:feature_code":"PPL",
    "gn:name":"Tiekeng",
    "gn:population":0,
    "gn:timezone":"Asia/Shanghai",
    "iso:country":"CN",
    "name:zho_x_preferred":[
        "\u94c1\u5751"
    ],
    "wof:name":"Tiekeng",
    "wof:placetype":"locality"
},
  "geometry": {"coordinates":[108.212,28.3014],"type":"Point"}
}