{
  "type": "Feature",
  "properties": {
    "gn:admin1_code":"9.0",
    "gn:asciiname":"Lizhuang",
    "gn:country_code":"CN",
    "gn:dem":375,
    "gn:feature_class":"P",
    "gn:feature_code":"PPL",
    "gn:name":"Lizhuang",
    "gn:population":0,
    "gn:timezone":"Asia/Shanghai",
    "iso:country":"CN",
    "name:ceb_x_preferred":[
        "Lizhuang"
    ],
    "name:swe_x_preferred":[
        "Lizhuang"
    ],
    "name:und_x_variant":[
        "\u674e\u5e84",
        "Lizhuang"
    ],
    "wof:name":"Lizhuang",
    "wof:placetype":"locality"
},
  "geometry": {"coordinates":[112.2353,33.42396],"type":"Point"}
}