{
  "type": "Feature",
  "properties": {
    "gn:admin1_code":"24.0",
    "gn:asciiname":"Xishangcun",
    "gn:country_code":"CN",
    "gn:dem":1009,
    "gn:feature_class":"P",
    "gn:feature_code":"PPL",
    "gn:name":"Xishangcun",
    "gn:population":0,
    "gn:timezone":"Asia/Shanghai",
    "iso:country":"CN",
    "name:zho_x_preferred":[
        "\u7ec6\u4e0a\u6751"
    ],
    "wof:name":"Xishangcun",
    "wof:placetype":"locality"
},
  "geometry": {"coordinates":[111.5421,36.58203],"type":"Point"}
}