{
  "type": "Feature",
  "properties": {
    "gn:admin1_code":"8.0",
    "gn:asciiname":"Zhangjia Shaoguo",
    "gn:country_code":"CN",
    "gn:dem":133,
    "gn:feature_class":"P",
    "gn:feature_code":"PPL",
    "gn:name":"Zhangjia Shaoguo",
    "gn:population":0,
    "gn:timezone":"Asia/Shanghai",
    "iso:country":"CN",
    "name:zho_x_preferred":[
        "\u5f20\u5bb6\u70e7\u9505"
    ],
    "wof:name":"Zhangjia Shaoguo",
    "wof:placetype":"locality"
},
  "geometry": {"coordinates":[124.78675,46.00873],"type":"Point"}
}