{
  "type": "Feature",
  "properties": {
    "gn:admin1_code":"12",
    "gn:asciiname":"Donghuangdian",
    "gn:cc2":"CN",
    "gn:country_code":"CN",
    "gn:dem":101,
    "gn:feature_class":"P",
    "gn:feature_code":"PPL",
    "gn:name":"Donghuangdian",
    "gn:population":0,
    "gn:timezone":"Asia/Shanghai",
    "iso:country":"CN",
    "name:und_x_variant":[
        "Tunghwangtien",
        "Tung-huang-tien",
        "Donghuangdian"
    ],
    "wof:name":"Donghuangdian",
    "wof:placetype":"locality"
},
  "geometry": {"coordinates":[114.02583,31.66806],"type":"Point"}
}