{
  "type": "Feature",
  "properties": {
    "gn:admin1_code":"25",
    "gn:asciiname":"Bizidian",
    "gn:country_code":"CN",
    "gn:dem":126,
    "gn:feature_class":"P",
    "gn:feature_code":"PPL",
    "gn:name":"Bizidian",
    "gn:population":0,
    "gn:timezone":"Asia/Shanghai",
    "iso:country":"CN",
    "name:zho_x_preferred":[
        "\u7be6\u5b50\u5e97"
    ],
    "wof:name":"Bizidian",
    "wof:placetype":"locality"
},
  "geometry": {"coordinates":[117.14,36.1413],"type":"Point"}
}