{
  "type": "Feature",
  "properties": {
    "gn:admin1_code":"10",
    "gn:asciiname":"Qidiliang",
    "gn:country_code":"CN",
    "gn:dem":1376,
    "gn:feature_class":"P",
    "gn:feature_code":"PPL",
    "gn:name":"Qidiliang",
    "gn:population":0,
    "gn:timezone":"Asia/Shanghai",
    "iso:country":"CN",
    "name:zho_x_preferred":[
        "\u65d7\u5730\u6881"
    ],
    "wof:name":"Qidiliang",
    "wof:placetype":"locality"
},
  "geometry": {"coordinates":[114.15678,41.36287],"type":"Point"}
}