{
  "type": "Feature",
  "properties": {
    "gn:admin1_code":"14.0",
    "gn:asciiname":"Kangbuding",
    "gn:country_code":"CN",
    "gn:dem":3982,
    "gn:feature_class":"P",
    "gn:feature_code":"PPL",
    "gn:name":"Kangbuding",
    "gn:population":0,
    "gn:timezone":"Asia/Urumqi",
    "iso:country":"CN",
    "name:zho_x_preferred":[
        "\u5eb7\u5e03\u9876"
    ],
    "wof:name":"Kangbuding",
    "wof:placetype":"locality"
},
  "geometry": {"coordinates":[91.9744,29.21796],"type":"Point"}
}