{
  "type": "Feature",
  "properties": {
    "gn:admin1_code":"7.0",
    "gn:asciiname":"Bailu",
    "gn:country_code":"CN",
    "gn:dem":22,
    "gn:feature_class":"P",
    "gn:feature_code":"PPL",
    "gn:name":"Bailu",
    "gn:population":0,
    "gn:timezone":"Asia/Shanghai",
    "iso:country":"CN",
    "name:deu_x_preferred":[
        "Bailu"
    ],
    "name:swe_x_preferred":[
        "Bailu"
    ],
    "name:zho_x_preferred":[
        "\u767d\u9e6d"
    ],
    "wof:name":"Bailu",
    "wof:placetype":"locality"
},
  "geometry": {"coordinates":[119.92230000000001,26.75832],"type":"Point"}
}