{
  "type": "Feature",
  "properties": {
    "gn:admin1_code":"32.0",
    "gn:asciiname":"Dalanba",
    "gn:country_code":"CN",
    "gn:dem":1583,
    "gn:feature_class":"P",
    "gn:feature_code":"PPL",
    "gn:name":"Dalanba",
    "gn:population":0,
    "gn:timezone":"Asia/Shanghai",
    "iso:country":"CN",
    "name:zho_x_preferred":[
        "\u5927\u70c2\u575d"
    ],
    "wof:name":"Dalanba",
    "wof:placetype":"locality"
},
  "geometry": {"coordinates":[101.506,26.6338],"type":"Point"}
}