{
  "type": "Feature",
  "properties": {
    "gn:admin1_code":"11.0",
    "gn:asciiname":"Xiawanli",
    "gn:country_code":"CN",
    "gn:dem":106,
    "gn:feature_class":"P",
    "gn:feature_code":"PPL",
    "gn:name":"Xiawanli",
    "gn:population":0,
    "gn:timezone":"Asia/Shanghai",
    "iso:country":"CN",
    "name:zho_x_preferred":[
        "\u4e0b\u6e7e\u91cc"
    ],
    "wof:name":"Xiawanli",
    "wof:placetype":"locality"
},
  "geometry": {"coordinates":[113.52200999999999,26.81286],"type":"Point"}
}