{
  "type": "Feature",
  "properties": {
    "gn:admin1_code":"7",
    "gn:asciiname":"Lingtou",
    "gn:country_code":"CN",
    "gn:dem":733,
    "gn:feature_class":"P",
    "gn:feature_code":"PPL",
    "gn:name":"Lingtou",
    "gn:population":0,
    "gn:timezone":"Asia/Shanghai",
    "iso:country":"CN",
    "name:und_x_variant":[
        "\u5cad\u5934",
        "Lingtou"
    ],
    "wof:name":"Lingtou",
    "wof:placetype":"locality"
},
  "geometry": {"coordinates":[119.37638,27.03798],"type":"Point"}
}