{
  "type": "Feature",
  "properties": {
    "gn:admin1_code":"32.0",
    "gn:asciiname":"Weiganping",
    "gn:country_code":"CN",
    "gn:dem":409,
    "gn:feature_class":"P",
    "gn:feature_code":"PPL",
    "gn:name":"Weiganping",
    "gn:population":0,
    "gn:timezone":"Asia/Shanghai",
    "iso:country":"CN",
    "name:zho_x_preferred":[
        "\u6845\u6746\u576a"
    ],
    "wof:name":"Weiganping",
    "wof:placetype":"locality"
},
  "geometry": {"coordinates":[106.48999999999999,31.4903],"type":"Point"}
}