{
  "type": "Feature",
  "properties": {
    "gn:admin1_code":"12.0",
    "gn:asciiname":"Jinzhuwuchang",
    "gn:country_code":"CN",
    "gn:dem":1061,
    "gn:feature_class":"P",
    "gn:feature_code":"PPL",
    "gn:name":"Jinzhuwuchang",
    "gn:population":0,
    "gn:timezone":"Asia/Shanghai",
    "iso:country":"CN",
    "name:zho_x_preferred":[
        "\u91d1\u7af9\u5c4b\u573a"
    ],
    "wof:name":"Jinzhuwuchang",
    "wof:placetype":"locality"
},
  "geometry": {"coordinates":[110.01182,31.77821],"type":"Point"}
}