{
  "type": "Feature",
  "properties": {
    "gn:admin1_code":"15",
    "gn:asciiname":"Sanjiaocheng",
    "gn:country_code":"CN",
    "gn:dem":1856,
    "gn:feature_class":"P",
    "gn:feature_code":"PPL",
    "gn:name":"Sanjiaocheng",
    "gn:population":0,
    "gn:timezone":"Asia/Shanghai",
    "iso:country":"CN",
    "wof:name":"Sanjiaocheng",
    "wof:placetype":"locality"
},
  "geometry": {"coordinates":[104.14528,35.88333],"type":"Point"}
}