{
  "type": "Feature",
  "properties": {
    "gn:admin1_code":"7",
    "gn:asciiname":"Dalikeng",
    "gn:country_code":"CN",
    "gn:dem":401,
    "gn:feature_class":"P",
    "gn:feature_code":"PPL",
    "gn:name":"Dalikeng",
    "gn:population":0,
    "gn:timezone":"Asia/Shanghai",
    "iso:country":"CN",
    "name:zho_x_preferred":[
        "\u5927\u91cc\u5751"
    ],
    "wof:name":"Dalikeng",
    "wof:placetype":"locality"
},
  "geometry": {"coordinates":[117.37273999999999,24.80236],"type":"Point"}
}