{
  "type": "Feature",
  "properties": {
    "gn:admin1_code":"16",
    "gn:asciiname":"Xianrendui",
    "gn:country_code":"CN",
    "gn:dem":203,
    "gn:feature_class":"P",
    "gn:feature_code":"PPL",
    "gn:name":"Xianrendui",
    "gn:population":0,
    "gn:timezone":"Asia/Shanghai",
    "iso:country":"CN",
    "name:zho_x_preferred":[
        "\u4ed9\u4eba\u7893"
    ],
    "wof:name":"Xianrendui",
    "wof:placetype":"locality"
},
  "geometry": {"coordinates":[109.964,25.032],"type":"Point"}
}