{
  "type": "Feature",
  "properties": {
    "gn:admin1_code":"25.0",
    "gn:asciiname":"Dongmawancun",
    "gn:country_code":"CN",
    "gn:dem":29,
    "gn:feature_class":"P",
    "gn:feature_code":"PPL",
    "gn:name":"Dongmawancun",
    "gn:population":0,
    "gn:timezone":"Asia/Shanghai",
    "iso:country":"CN",
    "name:zho_x_preferred":[
        "\u4e1c\u9ebb\u6e7e\u6751"
    ],
    "wof:name":"Dongmawancun",
    "wof:placetype":"locality"
},
  "geometry": {"coordinates":[119.55110999999999,36.50604000000001],"type":"Point"}
}