{
  "type": "Feature",
  "properties": {
    "gn:admin1_code":"11",
    "gn:asciiname":"Huyatang",
    "gn:country_code":"CN",
    "gn:dem":104,
    "gn:feature_class":"P",
    "gn:feature_code":"PPL",
    "gn:name":"Huyatang",
    "gn:population":0,
    "gn:timezone":"Asia/Shanghai",
    "iso:country":"CN",
    "name:zho_x_preferred":[
        "\u6e56\u9e26\u5858"
    ],
    "wof:name":"Huyatang",
    "wof:placetype":"locality"
},
  "geometry": {"coordinates":[112.32554,26.81006],"type":"Point"}
}