{
  "type": "Feature",
  "properties": {
    "gn:admin1_code":"25.0",
    "gn:asciiname":"Jiaoshuzhuang",
    "gn:country_code":"CN",
    "gn:dem":83,
    "gn:feature_class":"P",
    "gn:feature_code":"PPL",
    "gn:name":"Jiaoshuzhuang",
    "gn:population":0,
    "gn:timezone":"Asia/Shanghai",
    "iso:country":"CN",
    "name:zho_x_preferred":[
        "\u6559\u4e66\u5e84"
    ],
    "wof:name":"Jiaoshuzhuang",
    "wof:placetype":"locality"
},
  "geometry": {"coordinates":[120.30947,36.98185],"type":"Point"}
}