{
  "type": "Feature",
  "properties": {
    "gn:admin1_code":"21.0",
    "gn:asciiname":"Taiyangwa",
    "gn:country_code":"CN",
    "gn:dem":1942,
    "gn:feature_class":"P",
    "gn:feature_code":"PPL",
    "gn:name":"Taiyangwa",
    "gn:population":0,
    "gn:timezone":"Asia/Shanghai",
    "iso:country":"CN",
    "name:zho_x_preferred":[
        "\u592a\u9633\u6d3c"
    ],
    "wof:name":"Taiyangwa",
    "wof:placetype":"locality"
},
  "geometry": {"coordinates":[106.32599999999999,35.6491],"type":"Point"}
}