{
  "type": "Feature",
  "properties": {
    "gn:admin1_code":"30",
    "gn:asciiname":"Hengshi",
    "gn:country_code":"CN",
    "gn:dem":143,
    "gn:feature_class":"P",
    "gn:feature_code":"PPL",
    "gn:name":"Hengshi",
    "gn:population":0,
    "gn:timezone":"Asia/Shanghai",
    "iso:country":"CN",
    "name:jpn_x_preferred":[
        "\u6a2a\u5e02\u93ae"
    ],
    "name:zho_x_preferred":[
        "\u6a2a\u77f3"
    ],
    "name:zho_x_variant":[
        "\u6a2a\u5e02\u9547"
    ],
    "wof:name":"Hengshi",
    "wof:placetype":"locality"
},
  "geometry": {"coordinates":[115.53154000000001,23.22431],"type":"Point"}
}