{
  "type": "Feature",
  "properties": {
    "gn:admin1_code":"5.0",
    "gn:asciiname":"Zhongyantong Lazi",
    "gn:country_code":"CN",
    "gn:dem":414,
    "gn:feature_class":"P",
    "gn:feature_code":"PPL",
    "gn:name":"Zhongyantong Lazi",
    "gn:population":0,
    "gn:timezone":"Asia/Shanghai",
    "iso:country":"CN",
    "name:zho_x_preferred":[
        "\u4e2d\u70df\u7b52\u782c\u5b50"
    ],
    "wof:name":"Zhongyantong Lazi",
    "wof:placetype":"locality"
},
  "geometry": {"coordinates":[126.66752,43.33511],"type":"Point"}
}