{
  "type": "Feature",
  "properties": {
    "gn:admin1_code":"32.0",
    "gn:asciiname":"Xiangbizui",
    "gn:country_code":"CN",
    "gn:dem":586,
    "gn:feature_class":"P",
    "gn:feature_code":"PPL",
    "gn:name":"Xiangbizui",
    "gn:population":0,
    "gn:timezone":"Asia/Shanghai",
    "iso:country":"CN",
    "name:zho_x_preferred":[
        "\u8c61\u9f3b\u5480"
    ],
    "wof:name":"Xiangbizui",
    "wof:placetype":"locality"
},
  "geometry": {"coordinates":[104.654,28.0973],"type":"Point"}
}