{
  "type": "Feature",
  "properties": {
    "gn:admin1_code":"11",
    "gn:asciiname":"Langtang",
    "gn:country_code":"CN",
    "gn:dem":191,
    "gn:feature_class":"P",
    "gn:feature_code":"PPLA4",
    "gn:name":"Langtang",
    "gn:population":0,
    "gn:timezone":"Asia/Shanghai",
    "iso:country":"CN",
    "name:und_x_variant":[
        "Langtang Zhen"
    ],
    "name:zho_x_preferred":[
        "\u7405\u5858"
    ],
    "name:zho_x_variant":[
        "\u7405\u5858\u9547"
    ],
    "wof:name":"Langtang",
    "wof:placetype":"locality"
},
  "geometry": {"coordinates":[111.14861000000001,28.00528],"type":"Point"}
}