{
  "type": "Feature",
  "properties": {
    "gn:admin1_code":"7",
    "gn:asciiname":"Changcheng",
    "gn:country_code":"CN",
    "gn:dem":45,
    "gn:feature_class":"P",
    "gn:feature_code":"PPL",
    "gn:name":"Changcheng",
    "gn:population":0,
    "gn:timezone":"Asia/Shanghai",
    "iso:country":"CN",
    "name:und_x_variant":[
        "\u957f\u57d5"
    ],
    "wof:name":"Changcheng",
    "wof:placetype":"locality"
},
  "geometry": {"coordinates":[118.33263999999998,24.99833],"type":"Point"}
}