{
  "type": "Feature",
  "properties": {
    "gn:admin1_code":"5.0",
    "gn:asciiname":"Jiujingou",
    "gn:country_code":"CN",
    "gn:dem":371,
    "gn:feature_class":"P",
    "gn:feature_code":"PPL",
    "gn:name":"Jiujingou",
    "gn:population":0,
    "gn:timezone":"Asia/Shanghai",
    "iso:country":"CN",
    "name:zho_x_preferred":[
        "\u4e5d\u91d1\u6c9f"
    ],
    "wof:name":"Jiujingou",
    "wof:placetype":"locality"
},
  "geometry": {"coordinates":[127.50166000000002,44.19593],"type":"Point"}
}