{
  "type": "Feature",
  "properties": {
    "gn:admin1_code":"19.0",
    "gn:asciiname":"Qiujialing",
    "gn:country_code":"CN",
    "gn:dem":56,
    "gn:feature_class":"P",
    "gn:feature_code":"PPL",
    "gn:name":"Qiujialing",
    "gn:population":0,
    "gn:timezone":"Asia/Shanghai",
    "iso:country":"CN",
    "name:zho_x_preferred":[
        "\u4e18\u5bb6\u5cad"
    ],
    "wof:name":"Qiujialing",
    "wof:placetype":"locality"
},
  "geometry": {"coordinates":[121.303,38.8852],"type":"Point"}
}