{
  "type": "Feature",
  "properties": {
    "gn:admin1_code":"33.0",
    "gn:asciiname":"Wuping",
    "gn:country_code":"CN",
    "gn:dem":978,
    "gn:feature_class":"P",
    "gn:feature_code":"PPLA4",
    "gn:name":"Wuping",
    "gn:population":0,
    "gn:timezone":"Asia/Shanghai",
    "iso:country":"CN",
    "name:und_x_variant":[
        "Wuping Zhen",
        "Modaodong"
    ],
    "name:zho_x_preferred":[
        "\u6b66\u5e73"
    ],
    "name:zho_x_variant":[
        "\u6b66\u5e73\u9547",
        "\u78e8\u5200\u6d1e"
    ],
    "wof:name":"Wuping",
    "wof:placetype":"locality"
},
  "geometry": {"coordinates":[108.08548,29.79628],"type":"Point"}
}