{
  "type": "Feature",
  "properties": {
    "gn:admin1_code":"12.0",
    "gn:asciiname":"Baojiashan",
    "gn:country_code":"CN",
    "gn:dem":208,
    "gn:feature_class":"P",
    "gn:feature_code":"PPL",
    "gn:name":"Baojiashan",
    "gn:population":0,
    "gn:timezone":"Asia/Shanghai",
    "iso:country":"CN",
    "name:zho_x_preferred":[
        "Baojiashan"
    ],
    "name:zho_x_variant":[
        "\u9c8d\u5bb6\u5c71"
    ],
    "wof:name":"Baojiashan",
    "wof:placetype":"locality"
},
  "geometry": {"coordinates":[115.48766999999999,30.56984000000001],"type":"Point"}
}