{
  "type": "Feature",
  "properties": {
    "gn:admin1_code":"2.0",
    "gn:asciiname":"Dazuo'ao",
    "gn:country_code":"CN",
    "gn:dem":42,
    "gn:feature_class":"P",
    "gn:feature_code":"PPL",
    "gn:name":"Dazuo\u2019ao",
    "gn:population":0,
    "gn:timezone":"Asia/Shanghai",
    "iso:country":"CN",
    "name:und_x_variant":[
        "Dazuo\u2019ao"
    ],
    "name:zho_x_preferred":[
        "\u5927\u5de6\u5c99"
    ],
    "wof:name":"Dazuo'ao",
    "wof:placetype":"locality"
},
  "geometry": {"coordinates":[121.10741000000002,28.71356],"type":"Point"}
}