{
  "type": "Feature",
  "properties": {
    "gn:admin1_code":"8.0",
    "gn:asciiname":"Xituanjiecun",
    "gn:country_code":"CN",
    "gn:dem":154,
    "gn:feature_class":"P",
    "gn:feature_code":"PPL",
    "gn:name":"Xituanjiecun",
    "gn:population":0,
    "gn:timezone":"Asia/Shanghai",
    "iso:country":"CN",
    "name:zho_x_preferred":[
        "\u897f\u56e2\u7ed3\u6751"
    ],
    "wof:name":"Xituanjiecun",
    "wof:placetype":"locality"
},
  "geometry": {"coordinates":[123.7478,47.49305],"type":"Point"}
}