{
  "type": "Feature",
  "properties": {
    "gn:admin1_code":"15",
    "gn:asciiname":"Lazi",
    "gn:country_code":"CN",
    "gn:dem":1949,
    "gn:feature_class":"P",
    "gn:feature_code":"PPLA4",
    "gn:name":"Lazi",
    "gn:population":0,
    "gn:timezone":"Asia/Shanghai",
    "iso:country":"CN",
    "name:bos_x_preferred":[
        "Lazi"
    ],
    "name:ceb_x_preferred":[
        "Lazi"
    ],
    "name:deu_x_preferred":[
        "Lazi"
    ],
    "name:epo_x_preferred":[
        "Lazi"
    ],
    "name:fra_x_preferred":[
        "Lazi"
    ],
    "name:hrv_x_preferred":[
        "Lazi"
    ],
    "name:hun_x_preferred":[
        "Lazi"
    ],
    "name:jpn_x_preferred":[
        "\u30ef\u30b8"
    ],
    "name:lit_x_preferred":[
        "Lazai"
    ],
    "name:sco_x_preferred":[
        "Lazi"
    ],
    "name:slv_x_preferred":[
        "Lazi"
    ],
    "name:srp_x_preferred":[
        "\u041b\u0430\u0437\u0438"
    ],
    "name:swe_x_preferred":[
        "Lazi"
    ],
    "name:und_x_variant":[
        "\u814a\u5b50",
        "Lazikou"
    ],
    "name:zho_x_preferred":[
        "\u814a\u5b50\u53e3"
    ],
    "wof:name":"Lazi",
    "wof:placetype":"locality"
},
  "geometry": {"coordinates":[103.89402,34.06634],"type":"Point"}
}