{
  "type": "Feature",
  "properties": {
    "gn:admin1_code":"19.0",
    "gn:asciiname":"Dianzhuangzicun",
    "gn:country_code":"CN",
    "gn:dem":23,
    "gn:feature_class":"P",
    "gn:feature_code":"PPL",
    "gn:name":"Dianzhuangzicun",
    "gn:population":0,
    "gn:timezone":"Asia/Shanghai",
    "iso:country":"CN",
    "name:zho_x_preferred":[
        "\u975b\u5e84\u5b50\u6751"
    ],
    "wof:name":"Dianzhuangzicun",
    "wof:placetype":"locality"
},
  "geometry": {"coordinates":[122.932,41.6752],"type":"Point"}
}