{
  "type": "Feature",
  "properties": {
    "gn:admin1_code":"26.0",
    "gn:asciiname":"Xinliancun",
    "gn:country_code":"CN",
    "gn:dem":898,
    "gn:feature_class":"P",
    "gn:feature_code":"PPL",
    "gn:name":"Xinliancun",
    "gn:population":0,
    "gn:timezone":"Asia/Shanghai",
    "iso:country":"CN",
    "name:zho_x_preferred":[
        "\u65b0\u8054\u6751"
    ],
    "wof:name":"Xinliancun",
    "wof:placetype":"locality"
},
  "geometry": {"coordinates":[109.32487,33.3725],"type":"Point"}
}