{
  "type": "Feature",
  "properties": {
    "gn:admin1_code":"9.0",
    "gn:asciiname":"Songke Linggou",
    "gn:country_code":"CN",
    "gn:dem":526,
    "gn:feature_class":"P",
    "gn:feature_code":"PPL",
    "gn:name":"Songke Linggou",
    "gn:population":0,
    "gn:timezone":"Asia/Shanghai",
    "iso:country":"CN",
    "name:zho_x_preferred":[
        "\u9001\u5ba2\u5cad\u6c9f"
    ],
    "wof:name":"Songke Linggou",
    "wof:placetype":"locality"
},
  "geometry": {"coordinates":[111.46062000000001,33.54548],"type":"Point"}
}