{
  "type": "Feature",
  "properties": {
    "gn:admin1_code":"12.0",
    "gn:asciiname":"Xiaogounao",
    "gn:country_code":"CN",
    "gn:dem":478,
    "gn:feature_class":"P",
    "gn:feature_code":"PPL",
    "gn:name":"Xiaogounao",
    "gn:population":0,
    "gn:timezone":"Asia/Shanghai",
    "iso:country":"CN",
    "name:zho_x_preferred":[
        "\u5c0f\u6c9f\u8111"
    ],
    "wof:name":"Xiaogounao",
    "wof:placetype":"locality"
},
  "geometry": {"coordinates":[110.80738999999998,32.5356],"type":"Point"}
}