{
  "type": "Feature",
  "properties": {
    "gn:admin1_code":"29.0",
    "gn:asciiname":"Biema Xinzhai",
    "gn:country_code":"CN",
    "gn:dem":1052,
    "gn:feature_class":"P",
    "gn:feature_code":"PPL",
    "gn:name":"Biema Xinzhai",
    "gn:population":0,
    "gn:timezone":"Asia/Shanghai",
    "iso:country":"CN",
    "name:zho_x_preferred":[
        "\u522b\u9a6c\u65b0\u5be8"
    ],
    "wof:name":"Biema Xinzhai",
    "wof:placetype":"locality"
},
  "geometry": {"coordinates":[101.821,22.5362],"type":"Point"}
}