{
  "type": "Feature",
  "properties": {
    "gn:admin1_code":"9.0",
    "gn:asciiname":"Taishanmiao",
    "gn:country_code":"CN",
    "gn:dem":254,
    "gn:feature_class":"P",
    "gn:feature_code":"PPL",
    "gn:name":"Taishanmiao",
    "gn:population":0,
    "gn:timezone":"Asia/Shanghai",
    "iso:country":"CN",
    "name:zho_x_preferred":[
        "\u592a\u5c71\u5e99"
    ],
    "wof:name":"Taishanmiao",
    "wof:placetype":"locality"
},
  "geometry": {"coordinates":[113.09345,32.41661],"type":"Point"}
}