{
  "type": "Feature",
  "properties": {
    "gn:admin1_code":"11.0",
    "gn:asciiname":"Shibadun",
    "gn:country_code":"CN",
    "gn:dem":94,
    "gn:feature_class":"P",
    "gn:feature_code":"PPL",
    "gn:name":"Shibadun",
    "gn:population":0,
    "gn:timezone":"Asia/Shanghai",
    "iso:country":"CN",
    "name:zho_x_preferred":[
        "\u77f3\u516b\u58a9"
    ],
    "wof:name":"Shibadun",
    "wof:placetype":"locality"
},
  "geometry": {"coordinates":[112.67851,26.48662],"type":"Point"}
}