{
  "type": "Feature",
  "properties": {
    "gn:admin1_code":"32.0",
    "gn:asciiname":"Wandigu",
    "gn:country_code":"CN",
    "gn:dem":1997,
    "gn:feature_class":"P",
    "gn:feature_code":"PPL",
    "gn:name":"Wandigu",
    "gn:population":0,
    "gn:timezone":"Asia/Shanghai",
    "iso:country":"CN",
    "name:zho_x_preferred":[
        "\u5f2f\u5730\u6cbd"
    ],
    "wof:name":"Wandigu",
    "wof:placetype":"locality"
},
  "geometry": {"coordinates":[102.6686,26.99285],"type":"Point"}
}