{
  "type": "Feature",
  "properties": {
    "gn:admin1_code":"29.0",
    "gn:asciiname":"Xiashilata",
    "gn:country_code":"CN",
    "gn:dem":2097,
    "gn:feature_class":"P",
    "gn:feature_code":"PPL",
    "gn:name":"Xiashilata",
    "gn:population":0,
    "gn:timezone":"Asia/Shanghai",
    "iso:country":"CN",
    "name:zho_x_preferred":[
        "\u4e0b\u77f3\u814a\u5b83"
    ],
    "wof:name":"Xiashilata",
    "wof:placetype":"locality"
},
  "geometry": {"coordinates":[102.142,25.6745],"type":"Point"}
}