{
  "type": "Feature",
  "properties": {
    "gn:admin1_code":"02",
    "gn:asciiname":"Haitoucun",
    "gn:country_code":"CN",
    "gn:dem":4,
    "gn:feature_class":"P",
    "gn:feature_code":"PPL",
    "gn:name":"Haitoucun",
    "gn:population":0,
    "gn:timezone":"Asia/Shanghai",
    "iso:country":"CN",
    "name:und_x_variant":[
        "Hai-t\u2019ou-ts\u2019un",
        "Haitou",
        "Haitoucun"
    ],
    "name:zho_x_preferred":[
        "\u6d77\u5934"
    ],
    "name:zho_x_variant":[
        "\u6d77\u5934\u6751"
    ],
    "wof:name":"Haitoucun",
    "wof:placetype":"locality"
},
  "geometry": {"coordinates":[121.63287,29.31207],"type":"Point"}
}