{
  "type": "Feature",
  "properties": {
    "gn:admin1_code":"19.0",
    "gn:asciiname":"Qiujiatun",
    "gn:country_code":"CN",
    "gn:dem":163,
    "gn:feature_class":"P",
    "gn:feature_code":"PPL",
    "gn:name":"Qiujiatun",
    "gn:population":0,
    "gn:timezone":"Asia/Shanghai",
    "iso:country":"CN",
    "name:und_x_variant":[
        "\u90b1\u5bb6\u5c6f"
    ],
    "name:zho_x_preferred":[
        "\u90b1\u5bb6\u5c6f"
    ],
    "wof:name":"Qiujiatun",
    "wof:placetype":"locality"
},
  "geometry": {"coordinates":[120.99213,41.3209],"type":"Point"}
}