{
  "type": "Feature",
  "properties": {
    "gn:admin1_code":"19.0",
    "gn:asciiname":"Wujiaxigou",
    "gn:country_code":"CN",
    "gn:dem":254,
    "gn:feature_class":"P",
    "gn:feature_code":"PPL",
    "gn:name":"Wujiaxigou",
    "gn:population":0,
    "gn:timezone":"Asia/Shanghai",
    "iso:country":"CN",
    "name:zho_x_preferred":[
        "\u5434\u5bb6\u897f\u6c9f"
    ],
    "wof:name":"Wujiaxigou",
    "wof:placetype":"locality"
},
  "geometry": {"coordinates":[124.482,40.8798],"type":"Point"}
}