{
  "type": "Feature",
  "properties": {
    "gn:admin1_code":"19.0",
    "gn:asciiname":"Gaijia",
    "gn:country_code":"CN",
    "gn:dem":35,
    "gn:feature_class":"P",
    "gn:feature_code":"PPL",
    "gn:name":"Gaijia",
    "gn:population":0,
    "gn:timezone":"Asia/Shanghai",
    "iso:country":"CN",
    "name:und_x_variant":[
        "\u76d6\u5bb6"
    ],
    "wof:name":"Gaijia",
    "wof:placetype":"locality"
},
  "geometry": {"coordinates":[123.61082,40.18658],"type":"Point"}
}