{
  "type": "Feature",
  "properties": {
    "gn:admin1_code":"31.0",
    "gn:asciiname":"Shibaojiao",
    "gn:country_code":"CN",
    "gn:dem":33,
    "gn:feature_class":"P",
    "gn:feature_code":"PPL",
    "gn:name":"Shibaojiao",
    "gn:population":0,
    "gn:timezone":"Asia/Shanghai",
    "iso:country":"CN",
    "name:zho_x_preferred":[
        "\u77f3\u5b9d\u89d2"
    ],
    "wof:name":"Shibaojiao",
    "wof:placetype":"locality"
},
  "geometry": {"coordinates":[110.30088000000001,19.12791],"type":"Point"}
}