{
  "type": "Feature",
  "properties": {
    "gn:admin1_code":"9.0",
    "gn:asciiname":"Weichengsi",
    "gn:country_code":"CN",
    "gn:dem":258,
    "gn:feature_class":"P",
    "gn:feature_code":"PPL",
    "gn:name":"Weichengsi",
    "gn:population":0,
    "gn:timezone":"Asia/Shanghai",
    "iso:country":"CN",
    "name:zho_x_preferred":[
        "\u9b4f\u7a0b\u5bfa"
    ],
    "wof:name":"Weichengsi",
    "wof:placetype":"locality"
},
  "geometry": {"coordinates":[113.31097,32.58342],"type":"Point"}
}