{
  "type": "Feature",
  "properties": {
    "gn:admin1_code":"16.0",
    "gn:asciiname":"Maluyan",
    "gn:country_code":"CN",
    "gn:dem":172,
    "gn:feature_class":"P",
    "gn:feature_code":"PPL",
    "gn:name":"Maluyan",
    "gn:population":0,
    "gn:timezone":"Asia/Shanghai",
    "iso:country":"CN",
    "name:zho_x_preferred":[
        "\u9a6c\u9e7f\u5ca9"
    ],
    "wof:name":"Maluyan",
    "wof:placetype":"locality"
},
  "geometry": {"coordinates":[108.511,24.5075],"type":"Point"}
}