{
  "type": "Feature",
  "properties": {
    "gn:admin1_code":"24",
    "gn:asciiname":"Tashang",
    "gn:country_code":"CN",
    "gn:dem":1804,
    "gn:feature_class":"P",
    "gn:feature_code":"PPL",
    "gn:name":"Tashang",
    "gn:population":0,
    "gn:timezone":"Asia/Shanghai",
    "iso:country":"CN",
    "wof:name":"Tashang",
    "wof:placetype":"locality"
},
  "geometry": {"coordinates":[111.47889000000001,37.82472],"type":"Point"}
}