{
  "type": "Feature",
  "properties": {
    "gn:admin1_code":"31.0",
    "gn:asciiname":"Polin",
    "gn:country_code":"CN",
    "gn:dem":140,
    "gn:feature_class":"P",
    "gn:feature_code":"PPL",
    "gn:name":"Polin",
    "gn:population":0,
    "gn:timezone":"Asia/Shanghai",
    "iso:country":"CN",
    "name:pol_x_preferred":[
        "Polin"
    ],
    "name:zho_x_preferred":[
        "\u5761\u6797"
    ],
    "wof:name":"Polin",
    "wof:placetype":"locality"
},
  "geometry": {"coordinates":[109.80338,19.53402],"type":"Point"}
}