{
  "type": "Feature",
  "properties": {
    "gn:admin1_code":"1.0",
    "gn:asciiname":"Liangyuancun",
    "gn:country_code":"CN",
    "gn:dem":71,
    "gn:feature_class":"P",
    "gn:feature_code":"PPL",
    "gn:name":"Liangyuancun",
    "gn:population":0,
    "gn:timezone":"Asia/Shanghai",
    "iso:country":"CN",
    "name:zho_x_preferred":[
        "\u6881\u8881\u6751"
    ],
    "wof:name":"Liangyuancun",
    "wof:placetype":"locality"
},
  "geometry": {"coordinates":[117.49815,32.47374],"type":"Point"}
}