{
  "type": "Feature",
  "properties": {
    "gn:admin1_code":"02",
    "gn:asciiname":"Tengqiao",
    "gn:country_code":"CN",
    "gn:dem":7,
    "gn:feature_class":"P",
    "gn:feature_code":"PPL",
    "gn:name":"Tengqiao",
    "gn:population":0,
    "gn:timezone":"Asia/Shanghai",
    "iso:country":"CN",
    "name:und_x_variant":[
        "T\u2019un-ch\u2019iao",
        "Tengqiao",
        "\u85e4\u6865"
    ],
    "wof:name":"Tengqiao",
    "wof:placetype":"locality"
},
  "geometry": {"coordinates":[120.66195,30.4767],"type":"Point"}
}