{
  "type": "Feature",
  "properties": {
    "gn:admin1_code":"1.0",
    "gn:asciiname":"Houniucun",
    "gn:country_code":"CN",
    "gn:dem":36,
    "gn:feature_class":"P",
    "gn:feature_code":"PPL",
    "gn:name":"Houniucun",
    "gn:population":0,
    "gn:timezone":"Asia/Shanghai",
    "iso:country":"CN",
    "name:zho_x_preferred":[
        "\u540e\u725b\u6751"
    ],
    "wof:name":"Houniucun",
    "wof:placetype":"locality"
},
  "geometry": {"coordinates":[116.28610999999999,33.52518],"type":"Point"}
}