{
  "type": "Feature",
  "properties": {
    "gn:admin1_code":"19.0",
    "gn:asciiname":"Yangjiabucun",
    "gn:country_code":"CN",
    "gn:dem":79,
    "gn:feature_class":"P",
    "gn:feature_code":"PPL",
    "gn:name":"Yangjiabucun",
    "gn:population":0,
    "gn:timezone":"Asia/Shanghai",
    "iso:country":"CN",
    "name:zho_x_preferred":[
        "\u6768\u5bb6\u5821\u6751"
    ],
    "wof:name":"Yangjiabucun",
    "wof:placetype":"locality"
},
  "geometry": {"coordinates":[123.3353,40.19294],"type":"Point"}
}