{
  "type": "Feature",
  "properties": {
    "gn:admin1_code":"12.0",
    "gn:asciiname":"Suofengwan",
    "gn:country_code":"CN",
    "gn:dem":238,
    "gn:feature_class":"P",
    "gn:feature_code":"PPL",
    "gn:name":"Suofengwan",
    "gn:population":0,
    "gn:timezone":"Asia/Shanghai",
    "iso:country":"CN",
    "name:zho_x_preferred":[
        "\u9501\u51e4\u6e7e"
    ],
    "wof:name":"Suofengwan",
    "wof:placetype":"locality"
},
  "geometry": {"coordinates":[110.60124999999999,30.43407],"type":"Point"}
}