{
  "type": "Feature",
  "properties": {
    "gn:admin1_code":"19.0",
    "gn:asciiname":"Xiaoshangtun",
    "gn:country_code":"CN",
    "gn:dem":217,
    "gn:feature_class":"P",
    "gn:feature_code":"PPL",
    "gn:name":"Xiaoshangtun",
    "gn:population":0,
    "gn:timezone":"Asia/Shanghai",
    "iso:country":"CN",
    "name:zho_x_preferred":[
        "\u5c0f\u4e0a\u5c6f"
    ],
    "wof:name":"Xiaoshangtun",
    "wof:placetype":"locality"
},
  "geometry": {"coordinates":[120.42682000000001,41.13929],"type":"Point"}
}