{
  "type": "Feature",
  "properties": {
    "gn:admin1_code":"02",
    "gn:asciiname":"Dong'ancun",
    "gn:country_code":"CN",
    "gn:dem":16,
    "gn:feature_class":"P",
    "gn:feature_code":"PPL",
    "gn:name":"Dong\u2019ancun",
    "gn:population":0,
    "gn:timezone":"Asia/Shanghai",
    "iso:country":"CN",
    "name:und_x_variant":[
        "Tung-y\u00fcan",
        "Dong\u2019an",
        "Dong\u2019ancun"
    ],
    "name:zho_x_preferred":[
        "\u4e1c\u5cb8"
    ],
    "name:zho_x_variant":[
        "\u4e1c\u5cb8\u6751"
    ],
    "wof:name":"Dong'ancun",
    "wof:placetype":"locality"
},
  "geometry": {"coordinates":[120.37268,28.16009],"type":"Point"}
}