{
  "type": "Feature",
  "properties": {
    "gn:admin1_code":"32.0",
    "gn:asciiname":"Xiaoshuijing",
    "gn:country_code":"CN",
    "gn:dem":2324,
    "gn:feature_class":"P",
    "gn:feature_code":"PPL",
    "gn:name":"Xiaoshuijing",
    "gn:population":0,
    "gn:timezone":"Asia/Shanghai",
    "iso:country":"CN",
    "name:zho_x_preferred":[
        "\u5c0f\u6c34\u4e95"
    ],
    "wof:name":"Xiaoshuijing",
    "wof:placetype":"locality"
},
  "geometry": {"coordinates":[102.905,26.6007],"type":"Point"}
}