{
  "type": "Feature",
  "properties": {
    "gn:admin1_code":"29.0",
    "gn:asciiname":"Yingpanshan",
    "gn:country_code":"CN",
    "gn:dem":1647,
    "gn:feature_class":"P",
    "gn:feature_code":"PPL",
    "gn:name":"Yingpanshan",
    "gn:population":0,
    "gn:timezone":"Asia/Shanghai",
    "iso:country":"CN",
    "name:zho_x_preferred":[
        "\u8425\u76d8\u5c71"
    ],
    "wof:name":"Yingpanshan",
    "wof:placetype":"locality"
},
  "geometry": {"coordinates":[101.354,26.4631],"type":"Point"}
}