{
  "type": "Feature",
  "properties": {
    "gn:admin1_code":"15",
    "gn:asciiname":"Chengjiao Chengguanzhen",
    "gn:country_code":"CN",
    "gn:dem":2316,
    "gn:feature_class":"P",
    "gn:feature_code":"PPLA3",
    "gn:name":"Chengjiao Chengguanzhen",
    "gn:population":0,
    "gn:timezone":"Asia/Shanghai",
    "iso:country":"CN",
    "name:und_x_variant":[
        "Min",
        "Min-hsien",
        "Minchow",
        "MIN\u2019SYAN",
        "Chengjiao Chengguanzhen",
        "\u57ce\u90ca\u57ce\u5173\u9547",
        "Minxian",
        "Min Xian",
        "Chengguanzhen",
        "Chengjiao",
        "Min Xian Chengjiao Chengguanzhen",
        "\u5cb7\u53bf",
        "\u57ce\u5173\u9547",
        "\u57ce\u90ca",
        "\u5cb7\u53bf\u57ce\u90ca\u57ce\u5173\u9547"
    ],
    "wof:name":"Chengjiao Chengguanzhen",
    "wof:placetype":"locality"
},
  "geometry": {"coordinates":[104.03055999999999,34.43583],"type":"Point"}
}