{
  "type": "Feature",
  "properties": {
    "gn:admin1_code":"15",
    "gn:asciiname":"Chengjiao Chengguanzhen",
    "gn:country_code":"CN",
    "gn:dem":2316,
    "gn:feature_class":"P",
    "gn:feature_code":"PPLA3",
    "gn:name":"Chengjiao Chengguanzhen",
    "gn:population":0,
    "gn:timezone":"Asia/Shanghai",
    "iso:country":"CN",
    "name:deu_x_preferred":[
        "Min"
    ],
    "name:fas_x_preferred":[
        "\u0634\u0647\u0631\u0633\u062a\u0627\u0646 \u0645\u06cc\u0646"
    ],
    "name:kor_x_preferred":[
        "\ubbfc\ud604"
    ],
    "name:mwl_x_preferred":[
        "Minxian"
    ],
    "name:nor_x_preferred":[
        "Min"
    ],
    "name:rus_x_preferred":[
        "\u041c\u0438\u043d\u044c\u0441\u044f\u043d\u044c"
    ],
    "name:swe_x_preferred":[
        "Min"
    ],
    "name:und_x_variant":[
        "Min-hsien",
        "Minchow",
        "MIN\u2019SYAN",
        "Chengjiao Chengguanzhen",
        "\u57ce\u90ca\u57ce\u5173\u9547",
        "Min Xian",
        "Chengguanzhen",
        "Chengjiao",
        "Min Xian Chengjiao Chengguanzhen",
        "\u5cb7\u53bf",
        "\u57ce\u5173\u9547",
        "\u57ce\u90ca",
        "\u5cb7\u53bf\u57ce\u90ca\u57ce\u5173\u9547"
    ],
    "name:urd_x_preferred":[
        "\u0645\u06cc\u0646 \u06a9\u0627\u0624\u0646\u0679\u06cc"
    ],
    "name:vie_x_preferred":[
        "M\u00e2n"
    ],
    "wof:name":"Chengjiao Chengguanzhen",
    "wof:placetype":"locality"
},
  "geometry": {"coordinates":[104.03055999999999,34.43583],"type":"Point"}
}