{
  "type": "Feature",
  "properties": {
    "gn:admin1_code":"11",
    "gn:asciiname":"Lingshan",
    "gn:country_code":"CN",
    "gn:dem":142,
    "gn:feature_class":"P",
    "gn:feature_code":"PPL",
    "gn:name":"Lingshan",
    "gn:population":0,
    "gn:timezone":"Asia/Shanghai",
    "iso:country":"CN",
    "name:ceb_x_preferred":[
        "Lingshan"
    ],
    "name:deu_x_preferred":[
        "Lingshan"
    ],
    "name:swe_x_preferred":[
        "Lingshan"
    ],
    "wof:name":"Lingshan",
    "wof:placetype":"locality"
},
  "geometry": {"coordinates":[112.31444,27.57278],"type":"Point"}
}