{
  "type": "Feature",
  "properties": {
    "gn:admin1_code":"20.0",
    "gn:asciiname":"Aobao Wula",
    "gn:country_code":"CN",
    "gn:dem":736,
    "gn:feature_class":"P",
    "gn:feature_code":"PPL",
    "gn:name":"Aobao Wula",
    "gn:population":0,
    "gn:timezone":"Asia/Shanghai",
    "iso:country":"CN",
    "name:zho_x_preferred":[
        "\u50b2\u5305\u4e4c\u62c9"
    ],
    "wof:name":"Aobao Wula",
    "wof:placetype":"locality"
},
  "geometry": {"coordinates":[116.38781000000002,49.02646],"type":"Point"}
}