{
  "type": "Feature",
  "properties": {
    "gn:admin1_code":"29.0",
    "gn:asciiname":"Mashesuo",
    "gn:country_code":"CN",
    "gn:dem":1907,
    "gn:feature_class":"P",
    "gn:feature_code":"PPL",
    "gn:name":"Mashesuo",
    "gn:population":0,
    "gn:timezone":"Asia/Shanghai",
    "iso:country":"CN",
    "name:zho_x_preferred":[
        "\u9ebb\u820d\u6240"
    ],
    "wof:name":"Mashesuo",
    "wof:placetype":"locality"
},
  "geometry": {"coordinates":[103.586,24.9231],"type":"Point"}
}