{
  "type": "Feature",
  "properties": {
    "gn:admin1_code":"8.0",
    "gn:asciiname":"Juxing",
    "gn:country_code":"CN",
    "gn:dem":171,
    "gn:feature_class":"P",
    "gn:feature_code":"PPL",
    "gn:name":"Juxing",
    "gn:population":0,
    "gn:timezone":"Asia/Shanghai",
    "iso:country":"CN",
    "name:zho_x_preferred":[
        "\u5de8\u5174"
    ],
    "wof:name":"Juxing",
    "wof:placetype":"locality"
},
  "geometry": {"coordinates":[123.96048,48.0057],"type":"Point"}
}