{
  "type": "Feature",
  "properties": {
    "gn:admin1_code":"14.0",
    "gn:asciiname":"Qionglongge",
    "gn:country_code":"CN",
    "gn:dem":4287,
    "gn:feature_class":"P",
    "gn:feature_code":"PPL",
    "gn:name":"Qionglongge",
    "gn:population":0,
    "gn:timezone":"Asia/Urumqi",
    "iso:country":"CN",
    "name:zho_x_preferred":[
        "\u7a77\u9f99\u683c"
    ],
    "wof:name":"Qionglongge",
    "wof:placetype":"locality"
},
  "geometry": {"coordinates":[94.38473999999999,31.90992],"type":"Point"}
}