{
  "type": "Feature",
  "properties": {
    "gn:admin1_code":"3.0",
    "gn:asciiname":"Huliyuan",
    "gn:country_code":"CN",
    "gn:dem":199,
    "gn:feature_class":"P",
    "gn:feature_code":"PPL",
    "gn:name":"Huliyuan",
    "gn:population":0,
    "gn:timezone":"Asia/Shanghai",
    "iso:country":"CN",
    "name:zho_x_preferred":[
        "\u9e44\u7acb\u6e90"
    ],
    "wof:name":"Huliyuan",
    "wof:placetype":"locality"
},
  "geometry": {"coordinates":[117.96283,28.69305],"type":"Point"}
}