{
  "type": "Feature",
  "properties": {
    "gn:admin1_code":"10",
    "gn:asciiname":"Dong'erdaohe",
    "gn:country_code":"CN",
    "gn:dem":1086,
    "gn:feature_class":"P",
    "gn:feature_code":"PPL",
    "gn:name":"Dong\u2019erdaohe",
    "gn:population":0,
    "gn:timezone":"Asia/Shanghai",
    "iso:country":"CN",
    "name:und_x_variant":[
        "Dong\u2019erdaohe"
    ],
    "name:zho_x_preferred":[
        "\u4e1c\u4e8c\u9053\u6cb3"
    ],
    "wof:name":"Dong'erdaohe",
    "wof:placetype":"locality"
},
  "geometry": {"coordinates":[116.4944,41.71658],"type":"Point"}
}