{
  "type": "Feature",
  "properties": {
    "gn:admin1_code":"5.0",
    "gn:asciiname":"Gangliujia",
    "gn:country_code":"CN",
    "gn:dem":202,
    "gn:feature_class":"P",
    "gn:feature_code":"PPL",
    "gn:name":"Gangliujia",
    "gn:population":0,
    "gn:timezone":"Asia/Shanghai",
    "iso:country":"CN",
    "name:zho_x_preferred":[
        "\u5c97\u5218\u5bb6"
    ],
    "wof:name":"Gangliujia",
    "wof:placetype":"locality"
},
  "geometry": {"coordinates":[126.9641,44.86313],"type":"Point"}
}