{
  "type": "Feature",
  "properties": {
    "gn:admin1_code":"32.0",
    "gn:asciiname":"Lengyan",
    "gn:country_code":"CN",
    "gn:dem":509,
    "gn:feature_class":"P",
    "gn:feature_code":"PPL",
    "gn:name":"Lengyan",
    "gn:population":0,
    "gn:timezone":"Asia/Shanghai",
    "iso:country":"CN",
    "name:zho_x_preferred":[
        "\u695e\u4e25"
    ],
    "wof:name":"Lengyan",
    "wof:placetype":"locality"
},
  "geometry": {"coordinates":[103.676,30.5636],"type":"Point"}
}