{
  "type": "Feature",
  "properties": {
    "gn:admin1_code":"14.0",
    "gn:asciiname":"Gechong",
    "gn:country_code":"CN",
    "gn:dem":4621,
    "gn:feature_class":"P",
    "gn:feature_code":"PPLF",
    "gn:name":"Gechong",
    "gn:population":0,
    "gn:timezone":"Asia/Urumqi",
    "iso:country":"CN",
    "name:bod_x_preferred":[
        "G\u00eacang"
    ],
    "name:zho_x_preferred":[
        "Gechong"
    ],
    "name:zho_x_variant":[
        "\u683c\u51b2"
    ],
    "wof:name":"Gechong",
    "wof:placetype":"locality"
},
  "geometry": {"coordinates":[97.401,30.101],"type":"Point"}
}