{
  "type": "Feature",
  "properties": {
    "gn:admin1_code":"33.0",
    "gn:asciiname":"Huituoyuan",
    "gn:country_code":"CN",
    "gn:dem":708,
    "gn:feature_class":"P",
    "gn:feature_code":"PPL",
    "gn:name":"Huituoyuan",
    "gn:population":0,
    "gn:timezone":"Asia/Shanghai",
    "iso:country":"CN",
    "name:zho_x_preferred":[
        "\u56de\u5768\u56ed"
    ],
    "wof:name":"Huituoyuan",
    "wof:placetype":"locality"
},
  "geometry": {"coordinates":[108.54563,28.83217],"type":"Point"}
}