{
  "type": "Feature",
  "properties": {
    "gn:admin1_code":"15.0",
    "gn:asciiname":"Gejiatan",
    "gn:country_code":"CN",
    "gn:dem":1949,
    "gn:feature_class":"P",
    "gn:feature_code":"PPL",
    "gn:name":"Gejiatan",
    "gn:population":0,
    "gn:timezone":"Asia/Shanghai",
    "iso:country":"CN",
    "name:und_x_variant":[
        "\u845b\u5bb6\u6ee9"
    ],
    "wof:name":"Gejiatan",
    "wof:placetype":"locality"
},
  "geometry": {"coordinates":[105.16598999999999,35.46908],"type":"Point"}
}