{
  "type": "Feature",
  "properties": {
    "gn:admin1_code":"31.0",
    "gn:asciiname":"Puzai",
    "gn:country_code":"CN",
    "gn:dem":166,
    "gn:feature_class":"P",
    "gn:feature_code":"PPL",
    "gn:name":"Puzai",
    "gn:population":0,
    "gn:timezone":"Asia/Shanghai",
    "iso:country":"CN",
    "name:zho_x_preferred":[
        "\u94fa\u4ed4"
    ],
    "wof:name":"Puzai",
    "wof:placetype":"locality"
},
  "geometry": {"coordinates":[110.16861000000002,18.88913],"type":"Point"}
}