{
  "type": "Feature",
  "properties": {
    "gn:admin1_code":"14.0",
    "gn:asciiname":"Biyou",
    "gn:country_code":"CN",
    "gn:dem":4421,
    "gn:feature_class":"P",
    "gn:feature_code":"PPL",
    "gn:name":"Biyou",
    "gn:population":0,
    "gn:timezone":"Asia/Urumqi",
    "iso:country":"CN",
    "name:zho_x_preferred":[
        "\u5f7c\u4f18"
    ],
    "wof:name":"Biyou",
    "wof:placetype":"locality"
},
  "geometry": {"coordinates":[86.45350000000001,28.8758],"type":"Point"}
}