{
  "type": "Feature",
  "properties": {
    "gn:admin1_code":"7.0",
    "gn:asciiname":"Wenxincun",
    "gn:country_code":"CN",
    "gn:dem":149,
    "gn:feature_class":"P",
    "gn:feature_code":"PPL",
    "gn:name":"Wenxincun",
    "gn:population":0,
    "gn:timezone":"Asia/Shanghai",
    "iso:country":"CN",
    "name:zho_x_preferred":[
        "\u6587\u65b0\u6751"
    ],
    "wof:name":"Wenxincun",
    "wof:placetype":"locality"
},
  "geometry": {"coordinates":[117.77478000000001,26.854],"type":"Point"}
}