{
  "type": "Feature",
  "properties": {
    "gn:admin1_code":"4.0",
    "gn:asciiname":"Xiya Zixu",
    "gn:country_code":"CN",
    "gn:dem":6,
    "gn:feature_class":"P",
    "gn:feature_code":"PPL",
    "gn:name":"Xiya Zixu",
    "gn:population":0,
    "gn:timezone":"Asia/Shanghai",
    "iso:country":"CN",
    "name:zho_x_preferred":[
        "\u897f\u9e2d\u5b50\u5729"
    ],
    "wof:name":"Xiya Zixu",
    "wof:placetype":"locality"
},
  "geometry": {"coordinates":[120.47863999999998,31.99059],"type":"Point"}
}