{
  "type": "Feature",
  "properties": {
    "gn:admin1_code":"30",
    "gn:asciiname":"Yayao",
    "gn:country_code":"CN",
    "gn:dem":2,
    "gn:feature_class":"P",
    "gn:feature_code":"PPLA4",
    "gn:name":"Yayao",
    "gn:population":0,
    "gn:timezone":"Asia/Shanghai",
    "iso:country":"CN",
    "name:und_x_variant":[
        "Yayao Zhen",
        "\u96c5\u7476\u9547"
    ],
    "wof:name":"Yayao",
    "wof:placetype":"locality"
},
  "geometry": {"coordinates":[113.00602000000001,22.71123],"type":"Point"}
}