{
  "type": "Feature",
  "properties": {
    "gn:admin1_code":"10",
    "gn:asciiname":"Dayeyu",
    "gn:country_code":"CN",
    "gn:dem":391,
    "gn:feature_class":"P",
    "gn:feature_code":"PPL",
    "gn:name":"Dayeyu",
    "gn:population":0,
    "gn:timezone":"Asia/Shanghai",
    "iso:country":"CN",
    "name:zho_x_preferred":[
        "\u5927\u91ce\u5cea"
    ],
    "wof:name":"Dayeyu",
    "wof:placetype":"locality"
},
  "geometry": {"coordinates":[118.48384,40.50278],"type":"Point"}
}