{
  "type": "Feature",
  "properties": {
    "gn:admin1_code":"9.0",
    "gn:asciiname":"Jingpagou",
    "gn:country_code":"CN",
    "gn:dem":121,
    "gn:feature_class":"P",
    "gn:feature_code":"PPL",
    "gn:name":"Jingpagou",
    "gn:population":0,
    "gn:timezone":"Asia/Shanghai",
    "iso:country":"CN",
    "name:zho_x_preferred":[
        "\u8346\u722c\u6c9f"
    ],
    "wof:name":"Jingpagou",
    "wof:placetype":"locality"
},
  "geometry": {"coordinates":[112.70155,32.44247],"type":"Point"}
}