{
  "type": "Feature",
  "properties": {
    "gn:admin1_code":"3.0",
    "gn:asciiname":"Chengyuan",
    "gn:country_code":"CN",
    "gn:dem":453,
    "gn:feature_class":"P",
    "gn:feature_code":"PPL",
    "gn:name":"Chengyuan",
    "gn:population":0,
    "gn:timezone":"Asia/Shanghai",
    "iso:country":"CN",
    "name:und_x_variant":[
        "\u7a0b\u6e90"
    ],
    "wof:name":"Chengyuan",
    "wof:placetype":"locality"
},
  "geometry": {"coordinates":[115.13961999999999,26.48366],"type":"Point"}
}