{
  "type": "Feature",
  "properties": {
    "gn:admin1_code":"18",
    "gn:asciiname":"Maruo",
    "gn:country_code":"CN",
    "gn:dem":1256,
    "gn:feature_class":"P",
    "gn:feature_code":"PPL",
    "gn:name":"Maruo",
    "gn:population":0,
    "gn:timezone":"Asia/Shanghai",
    "iso:country":"CN",
    "name:zho_x_preferred":[
        "\u9a82\u82e5"
    ],
    "wof:name":"Maruo",
    "wof:placetype":"locality"
},
  "geometry": {"coordinates":[105.673,26.3979],"type":"Point"}
}