{
  "type": "Feature",
  "properties": {
    "gn:admin1_code":"29",
    "gn:asciiname":"Shangnanqiu",
    "gn:country_code":"CN",
    "gn:dem":1219,
    "gn:feature_class":"P",
    "gn:feature_code":"PPL",
    "gn:name":"Shangnanqiu",
    "gn:population":0,
    "gn:timezone":"Asia/Shanghai",
    "iso:country":"CN",
    "name:zho_x_preferred":[
        "\u4e0a\u5357\u4e18"
    ],
    "wof:name":"Shangnanqiu",
    "wof:placetype":"locality"
},
  "geometry": {"coordinates":[104.581,23.2929],"type":"Point"}
}