{
  "type": "Feature",
  "properties": {
    "gn:admin1_code":"24.0",
    "gn:asciiname":"Zhangshangou",
    "gn:country_code":"CN",
    "gn:dem":1720,
    "gn:feature_class":"P",
    "gn:feature_code":"PPL",
    "gn:name":"Zhangshangou",
    "gn:population":0,
    "gn:timezone":"Asia/Shanghai",
    "iso:country":"CN",
    "name:und_x_variant":[
        "\u5f20\u5c71\u6c9f"
    ],
    "name:zho_x_preferred":[
        "\u5f20\u5c71\u6c9f"
    ],
    "wof:name":"Zhangshangou",
    "wof:placetype":"locality"
},
  "geometry": {"coordinates":[113.0549,39.2696],"type":"Point"}
}