{
  "type": "Feature",
  "properties": {
    "gn:admin1_code":"14.0",
    "gn:asciiname":"Dacaika",
    "gn:country_code":"CN",
    "gn:dem":4270,
    "gn:feature_class":"P",
    "gn:feature_code":"PPL",
    "gn:name":"Dacaika",
    "gn:population":0,
    "gn:timezone":"Asia/Urumqi",
    "iso:country":"CN",
    "name:zho_x_preferred":[
        "\u8fbe\u91c7\u5361"
    ],
    "wof:name":"Dacaika",
    "wof:placetype":"locality"
},
  "geometry": {"coordinates":[95.06957,30.79581],"type":"Point"}
}