{
  "type": "Feature",
  "properties": {
    "gn:admin1_code":"26.0",
    "gn:asciiname":"Shiyuanzi",
    "gn:country_code":"CN",
    "gn:dem":1115,
    "gn:feature_class":"P",
    "gn:feature_code":"PPL",
    "gn:name":"Shiyuanzi",
    "gn:population":0,
    "gn:timezone":"Asia/Shanghai",
    "iso:country":"CN",
    "name:zho_x_preferred":[
        "\u77f3\u56ed\u5b50"
    ],
    "wof:name":"Shiyuanzi",
    "wof:placetype":"locality"
},
  "geometry": {"coordinates":[109.36297,37.99035],"type":"Point"}
}