{
  "type": "Feature",
  "properties": {
    "gn:admin1_code":"8.0",
    "gn:asciiname":"Xinzhong Erdui",
    "gn:country_code":"CN",
    "gn:dem":147,
    "gn:feature_class":"P",
    "gn:feature_code":"PPLF",
    "gn:name":"Xinzhong Erdui",
    "gn:population":0,
    "gn:timezone":"Asia/Shanghai",
    "iso:country":"CN",
    "name:zho_x_preferred":[
        "\u65b0\u5fe0\u4e8c\u961f"
    ],
    "wof:name":"Xinzhong Erdui",
    "wof:placetype":"locality"
},
  "geometry": {"coordinates":[131.67375000000001,45.45897],"type":"Point"}
}