{
  "type": "Feature",
  "properties": {
    "gn:admin1_code":"1.0",
    "gn:asciiname":"Liuyingcun",
    "gn:country_code":"CN",
    "gn:dem":29,
    "gn:feature_class":"P",
    "gn:feature_code":"PPL",
    "gn:name":"Liuyingcun",
    "gn:population":0,
    "gn:timezone":"Asia/Shanghai",
    "iso:country":"CN",
    "name:zho_x_preferred":[
        "\u5218\u90e2\u6751"
    ],
    "wof:name":"Liuyingcun",
    "wof:placetype":"locality"
},
  "geometry": {"coordinates":[116.07629,32.80322],"type":"Point"}
}