{
  "type": "Feature",
  "properties": {
    "gn:admin1_code":"29",
    "gn:asciiname":"Mixidai",
    "gn:country_code":"CN",
    "gn:dem":1634,
    "gn:feature_class":"P",
    "gn:feature_code":"PPL",
    "gn:name":"Mixidai",
    "gn:population":0,
    "gn:timezone":"Asia/Shanghai",
    "iso:country":"CN",
    "name:zho_x_preferred":[
        "\u7c73\u897f\u4ee3"
    ],
    "wof:name":"Mixidai",
    "wof:placetype":"locality"
},
  "geometry": {"coordinates":[101.72,24.0397],"type":"Point"}
}