{
  "type": "Feature",
  "properties": {
    "gn:admin1_code":"12.0",
    "gn:asciiname":"Yuanjianao",
    "gn:country_code":"CN",
    "gn:dem":27,
    "gn:feature_class":"P",
    "gn:feature_code":"PPL",
    "gn:name":"Yuanjianao",
    "gn:population":0,
    "gn:timezone":"Asia/Shanghai",
    "iso:country":"CN",
    "name:zho_x_preferred":[
        "\u8881\u5bb6\u57b4"
    ],
    "wof:name":"Yuanjianao",
    "wof:placetype":"locality"
},
  "geometry": {"coordinates":[112.60825,30.39917],"type":"Point"}
}