{
  "type": "Feature",
  "properties": {
    "gn:country":"CN",
    "gn:fcode":"PPLA4",
    "gn:pop":0,
    "iso:country":"CN",
    "name:unk_x_variant":[
        "Baizhifang Jiedao"
    ],
    "name:zho_x_preferred":[
        "\u767d\u7eb8\u574a"
    ],
    "name:zho_x_variant":[
        "\u767d\u7eb8\u574a\u8857\u9053",
        "\u5ba3\u6b66\u533a"
    ],
    "qs:name":"Baizhifang",
    "qs:photos_9r":0,
    "qs:photos_sr":0,
    "qs:pop_sr":"0",
    "wd:wordcount":964,
    "wof:name":"Baizhifang",
    "wof:placetype":"locality",
    "wof:population":0
},
  "geometry": {"coordinates":[116.35174000000001,39.88287],"type":"Point"}
}