{
  "type": "Feature",
  "properties": {
    "gn:country":"CN",
    "gn:fcode":"PPLA4",
    "gn:population":0,
    "iso:country":"CN",
    "name:ara_x_preferred":[
        "\u0634\u064a\u062a\u0634\u0646\u063a"
    ],
    "name:bel_x_preferred":[
        "\u0421\u0456\u0447\u044d\u043d"
    ],
    "name:cdo_x_preferred":[
        "S\u0103\u0324-si\u00e0ng-k\u1e73\u0306"
    ],
    "name:ceb_x_preferred":[
        "Xicheng Qu"
    ],
    "name:ces_x_preferred":[
        "Si-\u010dcheng"
    ],
    "name:cym_x_preferred":[
        "Ardal Xicheng"
    ],
    "name:deu_x_preferred":[
        "Xicheng"
    ],
    "name:eng_x_preferred":[
        "Xicheng District"
    ],
    "name:eus_x_preferred":[
        "Xicheng Barrutia"
    ],
    "name:fas_x_preferred":[
        "\u0634\u06cc\u0686\u0646\u06af"
    ],
    "name:fin_x_preferred":[
        "Xicheng"
    ],
    "name:gan_x_preferred":[
        "\u897f\u57ce\u533a"
    ],
    "name:heb_x_preferred":[
        "\u05d1\u05d9\u05d9\u05d2'\u05d9\u05e0\u05d2/\u05e8\u05d5\u05d1\u05e2 \u05e7\u05e1\u05d9\u05e6'\u05e0\u05d2"
    ],
    "name:heb_x_variant":[
        "\u05e8\u05d5\u05d1\u05e2 \u05e9\u05d9\u05e6'\u05e0\u05d2"
    ],
    "name:hun_x_preferred":[
        "Hszicseng"
    ],
    "name:ind_x_preferred":[
        "Distrik Xicheng"
    ],
    "name:jpn_x_preferred":[
        "\u897f\u57ce\u533a"
    ],
    "name:kor_x_preferred":[
        "\uc2dc\uccad\uad6c"
    ],
    "name:lez_x_preferred":[
        "\u0421\u0438\u0447\u044d\u043d"
    ],
    "name:lit_x_preferred":[
        "Si\u010dengas"
    ],
    "name:lzh_x_preferred":[
        "\u897f\u57ce\u5340"
    ],
    "name:mkd_x_preferred":[
        "\u0421\u0438\u0447\u0435\u043d\u0433"
    ],
    "name:mwl_x_preferred":[
        "Xicheng"
    ],
    "name:mya_x_preferred":[
        "\u101b\u103e\u102e\u1038\u1001\u103b\u1014\u103a\u1001\u101b\u102d\u102f\u1004\u103a"
    ],
    "name:myv_x_preferred":[
        "\u0421\u0438\u0447\u044d\u043d"
    ],
    "name:nan_x_preferred":[
        "Sai-si\u00e2\u207f-khu"
    ],
    "name:nld_x_preferred":[
        "Xicheng-district"
    ],
    "name:nob_x_preferred":[
        "Xicheng"
    ],
    "name:pol_x_preferred":[
        "Xicheng"
    ],
    "name:rus_x_preferred":[
        "\u0421\u0438\u0447\u044d\u043d"
    ],
    "name:sco_x_preferred":[
        "Xicheng"
    ],
    "name:spa_x_preferred":[
        "Xicheng"
    ],
    "name:swe_x_preferred":[
        "Xicheng"
    ],
    "name:tur_x_preferred":[
        "Xicheng"
    ],
    "name:und_x_variant":[
        "Baizhifang Jiedao"
    ],
    "name:urd_x_preferred":[
        "\u0634\u06cc\u0686\u06cc\u0646\u06af \u0636\u0644\u0639"
    ],
    "name:vie_x_preferred":[
        "T\u00e2y Th\u00e0nh"
    ],
    "name:wuu_x_preferred":[
        "\u897f\u57ce\u5340"
    ],
    "name:yue_x_preferred":[
        "\u897f\u57ce\u5340"
    ],
    "name:zha_x_preferred":[
        "Sihcwngz Gih"
    ],
    "name:zho_x_preferred":[
        "\u767d\u7eb8\u574a"
    ],
    "name:zho_x_variant":[
        "\u767d\u7eb8\u574a\u8857\u9053",
        "\u5ba3\u6b66\u533a",
        "\u897f\u57ce\u533a"
    ],
    "qs:name":"Baizhifang",
    "qs:photos_9r":0,
    "qs:photos_sr":0,
    "qs:pop_sr":"0",
    "wd:wordcount":964,
    "wof:name":"Baizhifang",
    "wof:placetype":"locality",
    "wof:population":0
},
  "geometry": {"coordinates":[116.35174000000001,39.88287],"type":"Point"}
}