{
  "type": "Feature",
  "properties": {
    "gn:admin1_code":"3.0",
    "gn:asciiname":"Xichanglong",
    "gn:country_code":"CN",
    "gn:dem":43,
    "gn:feature_class":"P",
    "gn:feature_code":"PPL",
    "gn:name":"Xichanglong",
    "gn:population":0,
    "gn:timezone":"Asia/Shanghai",
    "iso:country":"CN",
    "name:und_x_variant":[
        "\u7ec6\u957f\u5784"
    ],
    "wof:name":"Xichanglong",
    "wof:placetype":"locality"
},
  "geometry": {"coordinates":[116.27665,29.47241],"type":"Point"}
}