{
  "type": "Feature",
  "properties": {
    "gn:admin1_code":"30.0",
    "gn:asciiname":"Zhegucun",
    "gn:country_code":"CN",
    "gn:dem":73,
    "gn:feature_class":"P",
    "gn:feature_code":"PPL",
    "gn:name":"Zhegucun",
    "gn:population":0,
    "gn:timezone":"Asia/Shanghai",
    "iso:country":"CN",
    "name:zho_x_preferred":[
        "\u9e67\u9e2a\u6751"
    ],
    "wof:name":"Zhegucun",
    "wof:placetype":"locality"
},
  "geometry": {"coordinates":[116.29526,24.40557],"type":"Point"}
}