{
  "type": "Feature",
  "properties": {
    "gn:admin1_code":"32.0",
    "gn:asciiname":"Wenjiangdu",
    "gn:country_code":"CN",
    "gn:dem":328,
    "gn:feature_class":"P",
    "gn:feature_code":"PPL",
    "gn:name":"Wenjiangdu",
    "gn:population":0,
    "gn:timezone":"Asia/Shanghai",
    "iso:country":"CN",
    "name:zho_x_preferred":[
        "\u6587\u6c5f\u6e21"
    ],
    "wof:name":"Wenjiangdu",
    "wof:placetype":"locality"
},
  "geometry": {"coordinates":[104.82664,29.83761],"type":"Point"}
}