{
  "type": "Feature",
  "properties": {
    "gn:admin1_code":"32.0",
    "gn:asciiname":"Maoding",
    "gn:country_code":"CN",
    "gn:dem":369,
    "gn:feature_class":"P",
    "gn:feature_code":"PPL",
    "gn:name":"Maoding",
    "gn:population":0,
    "gn:timezone":"Asia/Shanghai",
    "iso:country":"CN",
    "name:zho_x_preferred":[
        "\u732b\u9876"
    ],
    "wof:name":"Maoding",
    "wof:placetype":"locality"
},
  "geometry": {"coordinates":[106.81100000000001,31.1883],"type":"Point"}
}