{
  "type": "Feature",
  "properties": {
    "gn:admin1_code":"24.0",
    "gn:asciiname":"Sucunbu",
    "gn:country_code":"CN",
    "gn:dem":418,
    "gn:feature_class":"P",
    "gn:feature_code":"PPL",
    "gn:name":"Sucunbu",
    "gn:population":0,
    "gn:timezone":"Asia/Shanghai",
    "iso:country":"CN",
    "name:und_x_variant":[
        "\u82cf\u6751\u5821"
    ],
    "wof:name":"Sucunbu",
    "wof:placetype":"locality"
},
  "geometry": {"coordinates":[111.15470000000001,35.60601],"type":"Point"}
}