{
  "type": "Feature",
  "properties": {
    "gn:admin1_code":"08",
    "gn:asciiname":"Sujiadian",
    "gn:country_code":"CN",
    "gn:dem":81,
    "gn:feature_class":"P",
    "gn:feature_code":"PPLA4",
    "gn:name":"Sujiadian",
    "gn:population":0,
    "gn:timezone":"Asia/Shanghai",
    "iso:country":"CN",
    "name:und_x_variant":[
        "Su-chia-tien",
        "Su-chia-tien-ts\u2019un",
        "Sujiadian",
        "Sujiadian Zhen"
    ],
    "name:zho_x_preferred":[
        "\u82cf\u5bb6\u5e97"
    ],
    "name:zho_x_variant":[
        "\u82cf\u5bb6\u5e97\u9547"
    ],
    "wof:name":"Sujiadian",
    "wof:placetype":"locality"
},
  "geometry": {"coordinates":[130.78083999999998,46.90296],"type":"Point"}
}