{
  "type": "Feature",
  "properties": {
    "gn:admin1_code":"4.0",
    "gn:asciiname":"Fanrong",
    "gn:country_code":"CN",
    "gn:dem":21,
    "gn:feature_class":"P",
    "gn:feature_code":"PPL",
    "gn:name":"Fanrong",
    "gn:population":0,
    "gn:timezone":"Asia/Shanghai",
    "iso:country":"CN",
    "name:zho_x_preferred":[
        "\u6a0a\u8363"
    ],
    "wof:name":"Fanrong",
    "wof:placetype":"locality"
},
  "geometry": {"coordinates":[119.38301,31.99028],"type":"Point"}
}