{
  "type": "Feature",
  "properties": {
    "gn:admin1_code":"5.0",
    "gn:asciiname":"Niuxindingcun",
    "gn:country_code":"CN",
    "gn:dem":310,
    "gn:feature_class":"P",
    "gn:feature_code":"PPL",
    "gn:name":"Niuxindingcun",
    "gn:population":0,
    "gn:timezone":"Asia/Shanghai",
    "iso:country":"CN",
    "name:zho_x_preferred":[
        "\u725b\u5fc3\u9876\u6751"
    ],
    "wof:name":"Niuxindingcun",
    "wof:placetype":"locality"
},
  "geometry": {"coordinates":[125.90903,42.71422000000001],"type":"Point"}
}