{
  "type": "Feature",
  "properties": {
    "gn:admin1_code":"32.0",
    "gn:asciiname":"Mayinglongba",
    "gn:country_code":"CN",
    "gn:dem":4004,
    "gn:feature_class":"P",
    "gn:feature_code":"PPL",
    "gn:name":"Mayinglongba",
    "gn:population":0,
    "gn:timezone":"Asia/Shanghai",
    "iso:country":"CN",
    "name:zho_x_preferred":[
        "\u9a6c\u786c\u9686\u5df4"
    ],
    "wof:name":"Mayinglongba",
    "wof:placetype":"locality"
},
  "geometry": {"coordinates":[101.215,29.8188],"type":"Point"}
}