{
  "type": "Feature",
  "properties": {
    "gn:admin1_code":"12.0",
    "gn:asciiname":"Taohuayan",
    "gn:country_code":"CN",
    "gn:dem":187,
    "gn:feature_class":"P",
    "gn:feature_code":"PPL",
    "gn:name":"Taohuayan",
    "gn:population":0,
    "gn:timezone":"Asia/Shanghai",
    "iso:country":"CN",
    "name:zho_x_preferred":[
        "\u6843\u82b1\u5830"
    ],
    "wof:name":"Taohuayan",
    "wof:placetype":"locality"
},
  "geometry": {"coordinates":[112.78618,31.56618],"type":"Point"}
}