{
  "type": "Feature",
  "properties": {
    "gn:admin1_code":"13.0",
    "gn:asciiname":"Yuqi Kapa",
    "gn:country_code":"CN",
    "gn:dem":3010,
    "gn:feature_class":"P",
    "gn:feature_code":"PPL",
    "gn:name":"Yuqi Kapa",
    "gn:population":0,
    "gn:timezone":"Asia/Shanghai",
    "iso:country":"CN",
    "name:und_x_variant":[
        "\u7389\u5176\u5580\u5e15"
    ],
    "wof:name":"Yuqi Kapa",
    "wof:placetype":"locality"
},
  "geometry": {"coordinates":[75.18422,38.74333],"type":"Point"}
}