{
  "type": "Feature",
  "properties": {
    "gn:admin1_code":"14.0",
    "gn:asciiname":"Chentang",
    "gn:country_code":"CN",
    "gn:dem":3530,
    "gn:feature_class":"P",
    "gn:feature_code":"PPL",
    "gn:name":"Chentang",
    "gn:population":0,
    "gn:timezone":"Asia/Urumqi",
    "iso:country":"CN",
    "name:ceb_x_preferred":[
        "Chentang"
    ],
    "name:swe_x_preferred":[
        "Chentang"
    ],
    "name:zho_x_preferred":[
        "\u9648\u5858"
    ],
    "name:zho_x_variant":[
        "\u9648\u5858\u9547"
    ],
    "wof:name":"Chentang",
    "wof:placetype":"locality"
},
  "geometry": {"coordinates":[86.28579999999999,28.0414],"type":"Point"}
}