{
  "type": "Feature",
  "properties": {
    "gn:admin1_code":"25.0",
    "gn:asciiname":"Chanzishi",
    "gn:country_code":"CN",
    "gn:dem":66,
    "gn:feature_class":"P",
    "gn:feature_code":"PPL",
    "gn:name":"Chanzishi",
    "gn:population":0,
    "gn:timezone":"Asia/Shanghai",
    "iso:country":"CN",
    "name:zho_x_preferred":[
        "\u4ea7\u5b50\u77f3"
    ],
    "wof:name":"Chanzishi",
    "wof:placetype":"locality"
},
  "geometry": {"coordinates":[122.38472,37.09618],"type":"Point"}
}