{
  "type": "Feature",
  "properties": {
    "gn:admin1_code":"15.0",
    "gn:asciiname":"Xuefangliang",
    "gn:country_code":"CN",
    "gn:dem":1193,
    "gn:feature_class":"P",
    "gn:feature_code":"PPL",
    "gn:name":"Xuefangliang",
    "gn:population":0,
    "gn:timezone":"Asia/Shanghai",
    "iso:country":"CN",
    "name:zho_x_preferred":[
        "\u5b66\u623f\u6881"
    ],
    "wof:name":"Xuefangliang",
    "wof:placetype":"locality"
},
  "geometry": {"coordinates":[105.182,32.6509],"type":"Point"}
}