{
  "type": "Feature",
  "properties": {
    "gn:admin1_code":"25.0",
    "gn:asciiname":"Liangjiabu",
    "gn:country_code":"CN",
    "gn:dem":24,
    "gn:feature_class":"P",
    "gn:feature_code":"PPL",
    "gn:name":"Liangjiabu",
    "gn:population":0,
    "gn:timezone":"Asia/Shanghai",
    "iso:country":"CN",
    "name:zho_x_preferred":[
        "\u4e24\u7532\u57e0"
    ],
    "wof:name":"Liangjiabu",
    "wof:placetype":"locality"
},
  "geometry": {"coordinates":[121.37688,37.41654000000001],"type":"Point"}
}