{
  "type": "Feature",
  "properties": {
    "gn:admin1_code":"7",
    "gn:asciiname":"Wengcun",
    "gn:country_code":"CN",
    "gn:dem":245,
    "gn:feature_class":"P",
    "gn:feature_code":"PPL",
    "gn:name":"Wengcun",
    "gn:population":0,
    "gn:timezone":"Asia/Shanghai",
    "iso:country":"CN",
    "name:und_x_variant":[
        "\u7d0a\u6751"
    ],
    "wof:name":"Wengcun",
    "wof:placetype":"locality"
},
  "geometry": {"coordinates":[118.60668,27.66708],"type":"Point"}
}