{
  "type": "Feature",
  "properties": {
    "gn:admin1_code":"32.0",
    "gn:asciiname":"Eshikua",
    "gn:country_code":"CN",
    "gn:dem":2844,
    "gn:feature_class":"P",
    "gn:feature_code":"PPL",
    "gn:name":"Eshikua",
    "gn:population":0,
    "gn:timezone":"Asia/Shanghai",
    "iso:country":"CN",
    "name:zho_x_preferred":[
        "\u4fc4\u5341\u57ae"
    ],
    "wof:name":"Eshikua",
    "wof:placetype":"locality"
},
  "geometry": {"coordinates":[103.12,32.0221],"type":"Point"}
}