{
  "type": "Feature",
  "properties": {
    "gn:admin1_code":"18",
    "gn:asciiname":"Nafu",
    "gn:country_code":"CN",
    "gn:dem":1078,
    "gn:feature_class":"P",
    "gn:feature_code":"PPL",
    "gn:name":"Nafu",
    "gn:population":0,
    "gn:timezone":"Asia/Shanghai",
    "iso:country":"CN",
    "name:zho_x_preferred":[
        "\u7eb3\u798f"
    ],
    "wof:name":"Nafu",
    "wof:placetype":"locality"
},
  "geometry": {"coordinates":[105.691,25.2064],"type":"Point"}
}