{
  "type": "Feature",
  "properties": {
    "gn:admin1_code":"18",
    "gn:asciiname":"Jinzhushan",
    "gn:country_code":"CN",
    "gn:dem":1339,
    "gn:feature_class":"P",
    "gn:feature_code":"PPL",
    "gn:name":"Jinzhushan",
    "gn:population":0,
    "gn:timezone":"Asia/Shanghai",
    "iso:country":"CN",
    "name:zho_x_preferred":[
        "\u91d1\u7af9\u5c71"
    ],
    "wof:name":"Jinzhushan",
    "wof:placetype":"locality"
},
  "geometry": {"coordinates":[105.512,25.6248],"type":"Point"}
}