{
  "type": "Feature",
  "properties": {
    "gn:admin1_code":"19.0",
    "gn:asciiname":"Weizigou",
    "gn:country_code":"CN",
    "gn:dem":69,
    "gn:feature_class":"P",
    "gn:feature_code":"PPL",
    "gn:name":"Weizigou",
    "gn:population":0,
    "gn:timezone":"Asia/Shanghai",
    "iso:country":"CN",
    "name:zho_x_preferred":[
        "\u82c7\u5b50\u6c9f"
    ],
    "wof:name":"Weizigou",
    "wof:placetype":"locality"
},
  "geometry": {"coordinates":[124.071,40.1542],"type":"Point"}
}