{
  "type": "Feature",
  "properties": {
    "gn:admin1_code":"12.0",
    "gn:asciiname":"Chenjia Zhizui",
    "gn:country_code":"CN",
    "gn:dem":39,
    "gn:feature_class":"P",
    "gn:feature_code":"PPL",
    "gn:name":"Chenjia Zhizui",
    "gn:population":0,
    "gn:timezone":"Asia/Shanghai",
    "iso:country":"CN",
    "name:zho_x_preferred":[
        "Chenjia Zhizui"
    ],
    "name:zho_x_variant":[
        "\u9648\u5bb6\u652f\u5480"
    ],
    "wof:name":"Chenjia Zhizui",
    "wof:placetype":"locality"
},
  "geometry": {"coordinates":[111.90978,30.33001],"type":"Point"}
}