{
  "type": "Feature",
  "properties": {
    "iso:country":"CN",
    "name:eng_x_preferred":[
        "Jishou"
    ],
    "name:zho_x_preferred":[
        "\u5409\u9996\u5e02"
    ],
    "qs:name":"\u5409\u9996\u5e02",
    "qs:name_adm0":"\u4e2d\u570b",
    "qs:name_adm1":"\u6e56\u5357\u7701",
    "qs:photos":32,
    "qs:photos_1k":6,
    "qs:photos_9k":1,
    "qs:photos_9r":4,
    "qs:photos_all":260,
    "qs:photos_sr":2,
    "qs:placetype":"LocalAdmin",
    "qs:pop_sr":"0",
    "wof:name":"Jishou",
    "wof:placetype":"localadmin"
},
  "geometry": {"coordinates":[109.72183200000001,28.320097],"type":"Point"}
}