{
  "type": "Feature",
  "properties": {
    "gn:admin1_code":"30.0",
    "gn:asciiname":"Hengdou",
    "gn:country_code":"CN",
    "gn:dem":82,
    "gn:feature_class":"P",
    "gn:feature_code":"PPL",
    "gn:name":"Hengdou",
    "gn:population":0,
    "gn:timezone":"Asia/Urumqi",
    "iso:country":"CN",
    "name:zho_x_preferred":[
        "\u6a2a\u90fd"
    ],
    "wof:name":"Hengdou",
    "wof:placetype":"locality"
},
  "geometry": {"coordinates":[110.12914000000001,20.45641],"type":"Point"}
}