{
  "type": "Feature",
  "properties": {
    "gn:admin1_code":"16",
    "gn:asciiname":"Hanchong",
    "gn:country_code":"CN",
    "gn:dem":492,
    "gn:feature_class":"P",
    "gn:feature_code":"PPL",
    "gn:name":"Hanchong",
    "gn:population":0,
    "gn:timezone":"Asia/Shanghai",
    "iso:country":"CN",
    "name:zho_x_preferred":[
        "\u65f1\u51b2"
    ],
    "wof:name":"Hanchong",
    "wof:placetype":"locality"
},
  "geometry": {"coordinates":[110.59099999999999,24.5023],"type":"Point"}
}