{
  "type": "Feature",
  "properties": {
    "gn:admin1_code":"25.0",
    "gn:asciiname":"Toubaojia",
    "gn:country_code":"CN",
    "gn:dem":82,
    "gn:feature_class":"P",
    "gn:feature_code":"PPL",
    "gn:name":"Toubaojia",
    "gn:population":0,
    "gn:timezone":"Asia/Shanghai",
    "iso:country":"CN",
    "name:zho_x_preferred":[
        "\u5934\u5305\u5bb6"
    ],
    "wof:name":"Toubaojia",
    "wof:placetype":"locality"
},
  "geometry": {"coordinates":[120.80477,37.73868],"type":"Point"}
}