{
  "type": "Feature",
  "properties": {
    "gn:admin1_code":"19.0",
    "gn:asciiname":"Xiahekou",
    "gn:country_code":"CN",
    "gn:dem":88,
    "gn:feature_class":"P",
    "gn:feature_code":"PPL",
    "gn:name":"Xiahekou",
    "gn:population":0,
    "gn:timezone":"Asia/Shanghai",
    "iso:country":"CN",
    "name:zho_x_preferred":[
        "\u4e0b\u6cb3\u53e3"
    ],
    "wof:name":"Xiahekou",
    "wof:placetype":"locality"
},
  "geometry": {"coordinates":[123.72512,42.87748],"type":"Point"}
}