{
  "type": "Feature",
  "properties": {
    "gn:admin1_code":"3.0",
    "gn:asciiname":"Fenshanbei",
    "gn:country_code":"CN",
    "gn:dem":242,
    "gn:feature_class":"P",
    "gn:feature_code":"PPL",
    "gn:name":"Fenshanbei",
    "gn:population":0,
    "gn:timezone":"Asia/Shanghai",
    "iso:country":"CN",
    "name:und_x_variant":[
        "\u575f\u5c71\u80cc"
    ],
    "wof:name":"Fenshanbei",
    "wof:placetype":"locality"
},
  "geometry": {"coordinates":[114.35223000000001,27.97776],"type":"Point"}
}