{
  "type": "Feature",
  "properties": {
    "gn:admin1_code":"3.0",
    "gn:asciiname":"Xixia",
    "gn:country_code":"CN",
    "gn:dem":55,
    "gn:feature_class":"P",
    "gn:feature_code":"PPL",
    "gn:name":"Xixia",
    "gn:population":0,
    "gn:timezone":"Asia/Shanghai",
    "iso:country":"CN",
    "name:ceb_x_preferred":[
        "Xixia"
    ],
    "name:deu_x_preferred":[
        "Xixia"
    ],
    "name:fra_x_preferred":[
        "Xixia"
    ],
    "name:nor_x_preferred":[
        "Xixia"
    ],
    "name:pol_x_preferred":[
        "Xixia"
    ],
    "name:rus_x_preferred":[
        "\u0421\u0438\u0441\u044f"
    ],
    "name:swe_x_preferred":[
        "Xixia"
    ],
    "name:und_x_variant":[
        "\u6eaa\u4e0b"
    ],
    "wof:name":"Xixia",
    "wof:placetype":"locality"
},
  "geometry": {"coordinates":[115.53395,27.83166],"type":"Point"}
}