{
  "type": "Feature",
  "properties": {
    "gn:admin1_code":"1.0",
    "gn:asciiname":"Lizhaicun",
    "gn:country_code":"CN",
    "gn:dem":33,
    "gn:feature_class":"P",
    "gn:feature_code":"PPL",
    "gn:name":"Lizhaicun",
    "gn:population":0,
    "gn:timezone":"Asia/Shanghai",
    "iso:country":"CN",
    "name:zho_x_preferred":[
        "\u674e\u5be8\u6751"
    ],
    "wof:name":"Lizhaicun",
    "wof:placetype":"locality"
},
  "geometry": {"coordinates":[116.64506000000002,33.84492],"type":"Point"}
}