{
  "type": "Feature",
  "properties": {
    "gn:admin1_code":"5.0",
    "gn:asciiname":"Xinfangzicun",
    "gn:country_code":"CN",
    "gn:dem":371,
    "gn:feature_class":"P",
    "gn:feature_code":"PPL",
    "gn:name":"Xinfangzicun",
    "gn:population":0,
    "gn:timezone":"Asia/Shanghai",
    "iso:country":"CN",
    "name:zho_x_preferred":[
        "\u65b0\u623f\u5b50\u6751"
    ],
    "wof:name":"Xinfangzicun",
    "wof:placetype":"locality"
},
  "geometry": {"coordinates":[128.48182,43.69032],"type":"Point"}
}