{
  "type": "Feature",
  "properties": {
    "gn:admin1_code":"10",
    "gn:asciiname":"Houmazhuang",
    "gn:country_code":"CN",
    "gn:dem":20,
    "gn:feature_class":"P",
    "gn:feature_code":"PPL",
    "gn:name":"Houmazhuang",
    "gn:population":0,
    "gn:timezone":"Asia/Shanghai",
    "iso:country":"CN",
    "name:zho_x_preferred":[
        "\u540e\u9a6c\u5e84"
    ],
    "wof:name":"Houmazhuang",
    "wof:placetype":"locality"
},
  "geometry": {"coordinates":[115.81999999999999,37.9805],"type":"Point"}
}