{
  "type": "Feature",
  "properties": {
    "gn:admin1_code":"12.0",
    "gn:asciiname":"Hujiazhou",
    "gn:country_code":"CN",
    "gn:dem":54,
    "gn:feature_class":"P",
    "gn:feature_code":"PPL",
    "gn:name":"Hujiazhou",
    "gn:population":0,
    "gn:timezone":"Asia/Shanghai",
    "iso:country":"CN",
    "name:zho_x_preferred":[
        "\u62a4\u9a7e\u5dde"
    ],
    "wof:name":"Hujiazhou",
    "wof:placetype":"locality"
},
  "geometry": {"coordinates":[112.37781,31.59677000000001],"type":"Point"}
}