{
  "type": "Feature",
  "properties": {
    "gn:admin1_code":"12.0",
    "gn:asciiname":"Dazhanjiawan",
    "gn:country_code":"CN",
    "gn:dem":156,
    "gn:feature_class":"P",
    "gn:feature_code":"PPL",
    "gn:name":"Dazhanjiawan",
    "gn:population":0,
    "gn:timezone":"Asia/Shanghai",
    "iso:country":"CN",
    "name:zho_x_preferred":[
        "\u5927\u8a79\u5bb6\u5846"
    ],
    "wof:name":"Dazhanjiawan",
    "wof:placetype":"locality"
},
  "geometry": {"coordinates":[113.53215,32.08525],"type":"Point"}
}