{
  "type": "Feature",
  "properties": {
    "gn:admin1_code":"1.0",
    "gn:asciiname":"Hucungou",
    "gn:country_code":"CN",
    "gn:dem":39,
    "gn:feature_class":"P",
    "gn:feature_code":"PPL",
    "gn:name":"Hucungou",
    "gn:population":0,
    "gn:timezone":"Asia/Shanghai",
    "iso:country":"CN",
    "name:zho_x_preferred":[
        "Hucungou"
    ],
    "name:zho_x_variant":[
        "\u80e1\u6751\u6c9f"
    ],
    "wof:name":"Hucungou",
    "wof:placetype":"locality"
},
  "geometry": {"coordinates":[119.10467,30.96988],"type":"Point"}
}