{
  "type": "Feature",
  "properties": {
    "gn:admin1_code":"30",
    "gn:asciiname":"Baojinwei",
    "gn:country_code":"CN",
    "gn:dem":18,
    "gn:feature_class":"P",
    "gn:feature_code":"PPL",
    "gn:name":"Baojinwei",
    "gn:population":0,
    "gn:timezone":"Asia/Urumqi",
    "iso:country":"CN",
    "name:zho_x_preferred":[
        "\u5305\u91d1\u5729"
    ],
    "wof:name":"Baojinwei",
    "wof:placetype":"locality"
},
  "geometry": {"coordinates":[109.69369,20.95193],"type":"Point"}
}