{
  "type": "Feature",
  "properties": {
    "gn:admin1_code":"26",
    "gn:asciiname":"Jiujianfang",
    "gn:country_code":"CN",
    "gn:dem":715,
    "gn:feature_class":"P",
    "gn:feature_code":"PPLA4",
    "gn:name":"Jiujianfang",
    "gn:population":0,
    "gn:timezone":"Asia/Shanghai",
    "iso:country":"CN",
    "name:und_x_variant":[
        "Mu-chia-yen",
        "\u4e5d\u95f4\u623f",
        "Jiujianfang"
    ],
    "wof:name":"Jiujianfang",
    "wof:placetype":"locality"
},
  "geometry": {"coordinates":[109.51513,34.1858],"type":"Point"}
}