{
  "type": "Feature",
  "properties": {
    "gn:admin1_code":"30",
    "gn:asciiname":"Kezishe",
    "gn:country_code":"CN",
    "gn:dem":240,
    "gn:feature_class":"P",
    "gn:feature_code":"PPL",
    "gn:name":"Kezishe",
    "gn:population":0,
    "gn:timezone":"Asia/Shanghai",
    "iso:country":"CN",
    "name:zho_x_preferred":[
        "\u5ba2\u5b50\u8f0b"
    ],
    "wof:name":"Kezishe",
    "wof:placetype":"locality"
},
  "geometry": {"coordinates":[116.26027999999999,24.46352000000001],"type":"Point"}
}