{
  "type": "Feature",
  "properties": {
    "gn:admin1_code":"02",
    "gn:asciiname":"Xiayangpucun",
    "gn:country_code":"CN",
    "gn:dem":3,
    "gn:feature_class":"P",
    "gn:feature_code":"PPL",
    "gn:name":"Xiayangpucun",
    "gn:population":0,
    "gn:timezone":"Asia/Shanghai",
    "iso:country":"CN",
    "name:und_x_variant":[
        "Hsia-yang-p\u2019u-miao",
        "Xiayangpu",
        "\u4e0b\u6d0b\u6d66",
        "Xiayangpucun"
    ],
    "name:zho_x_preferred":[
        "\u4e0b\u6d0b\u6d66\u6751"
    ],
    "wof:name":"Xiayangpucun",
    "wof:placetype":"locality"
},
  "geometry": {"coordinates":[121.41215,30.24495],"type":"Point"}
}