{
  "type": "Feature",
  "properties": {
    "gn:admin1_code":"02",
    "gn:asciiname":"Hsiang-t'ing-shan",
    "gn:country_code":"CN",
    "gn:dem":87,
    "gn:feature_class":"P",
    "gn:feature_code":"PPL",
    "gn:name":"Hsiang-t\u2019ing-shan",
    "gn:population":0,
    "gn:timezone":"Asia/Shanghai",
    "iso:country":"CN",
    "wof:name":"Hsiang-t'ing-shan",
    "wof:placetype":"locality"
},
  "geometry": {"coordinates":[121.32805999999999,29.26528],"type":"Point"}
}