{
  "type": "Feature",
  "properties": {
    "gn:admin1_code":"32.0",
    "gn:asciiname":"Huangposhan",
    "gn:country_code":"CN",
    "gn:dem":2012,
    "gn:feature_class":"P",
    "gn:feature_code":"PPL",
    "gn:name":"Huangposhan",
    "gn:population":0,
    "gn:timezone":"Asia/Shanghai",
    "iso:country":"CN",
    "name:zho_x_preferred":[
        "\u9ec4\u5761\u5c71"
    ],
    "wof:name":"Huangposhan",
    "wof:placetype":"locality"
},
  "geometry": {"coordinates":[102.19929999999999,28.70252],"type":"Point"}
}