{
  "type": "Feature",
  "properties": {
    "gn:admin1_code":"25.0",
    "gn:asciiname":"Hongyuncun",
    "gn:country_code":"CN",
    "gn:dem":39,
    "gn:feature_class":"P",
    "gn:feature_code":"PPL",
    "gn:name":"Hongyuncun",
    "gn:population":0,
    "gn:timezone":"Asia/Shanghai",
    "iso:country":"CN",
    "name:zho_x_preferred":[
        "\u7ea2\u8fd0\u6751"
    ],
    "wof:name":"Hongyuncun",
    "wof:placetype":"locality"
},
  "geometry": {"coordinates":[116.33853000000001,35.54258],"type":"Point"}
}