{
  "type": "Feature",
  "properties": {
    "gn:admin1_code":"5.0",
    "gn:asciiname":"Xituan Shanzi",
    "gn:country_code":"CN",
    "gn:dem":194,
    "gn:feature_class":"P",
    "gn:feature_code":"PPL",
    "gn:name":"Xituan Shanzi",
    "gn:population":0,
    "gn:timezone":"Asia/Shanghai",
    "iso:country":"CN",
    "name:zho_x_preferred":[
        "\u897f\u56e2\u5c71\u5b50"
    ],
    "wof:name":"Xituan Shanzi",
    "wof:placetype":"locality"
},
  "geometry": {"coordinates":[124.10800999999999,43.97861],"type":"Point"}
}