{
  "type": "Feature",
  "properties": {
    "gn:admin1_code":"16.0",
    "gn:asciiname":"Nongdou",
    "gn:country_code":"CN",
    "gn:dem":424,
    "gn:feature_class":"P",
    "gn:feature_code":"PPL",
    "gn:name":"Nongdou",
    "gn:population":0,
    "gn:timezone":"Asia/Shanghai",
    "iso:country":"CN",
    "name:zho_x_preferred":[
        "\u5f04\u8c46"
    ],
    "wof:name":"Nongdou",
    "wof:placetype":"locality"
},
  "geometry": {"coordinates":[107.90300000000001,24.063],"type":"Point"}
}