{
  "type": "Feature",
  "properties": {
    "gn:admin1_code":"32.0",
    "gn:asciiname":"Egongbao",
    "gn:country_code":"CN",
    "gn:dem":2387,
    "gn:feature_class":"P",
    "gn:feature_code":"PPL",
    "gn:name":"Egongbao",
    "gn:population":0,
    "gn:timezone":"Asia/Shanghai",
    "iso:country":"CN",
    "name:zho_x_preferred":[
        "\u4fc4\u516c\u4fdd"
    ],
    "wof:name":"Egongbao",
    "wof:placetype":"locality"
},
  "geometry": {"coordinates":[100.86799999999999,28.3831],"type":"Point"}
}