{
  "type": "Feature",
  "properties": {
    "gn:admin1_code":"01",
    "gn:asciiname":"Shuanggou",
    "gn:cc2":"CN",
    "gn:country_code":"CN",
    "gn:dem":21,
    "gn:feature_class":"P",
    "gn:feature_code":"PPL",
    "gn:name":"Shuanggou",
    "gn:population":0,
    "gn:timezone":"Asia/Shanghai",
    "iso:country":"CN",
    "name:und_x_variant":[
        "Shuang-kou-chi",
        "Shuang-kou",
        "Shuanggou"
    ],
    "wof:name":"Shuanggou",
    "wof:placetype":"locality"
},
  "geometry": {"coordinates":[117.03528,33.03889],"type":"Point"}
}