{
  "type": "Feature",
  "properties": {
    "gn:admin1_code":"7",
    "gn:asciiname":"Donghua",
    "gn:country_code":"CN",
    "gn:dem":12,
    "gn:feature_class":"P",
    "gn:feature_code":"PPL",
    "gn:name":"Donghua",
    "gn:population":0,
    "gn:timezone":"Asia/Shanghai",
    "iso:country":"CN",
    "name:ceb_x_preferred":[
        "Donghua"
    ],
    "name:deu_x_preferred":[
        "Donghua"
    ],
    "name:swe_x_preferred":[
        "Donghua"
    ],
    "name:zho_x_preferred":[
        "\u4e1c\u534e"
    ],
    "wof:name":"Donghua",
    "wof:placetype":"locality"
},
  "geometry": {"coordinates":[119.07335999999999,25.28414],"type":"Point"}
}