{
  "type": "Feature",
  "properties": {
    "gn:admin1_code":"32.0",
    "gn:asciiname":"Yangjia Pingzi",
    "gn:country_code":"CN",
    "gn:dem":2821,
    "gn:feature_class":"P",
    "gn:feature_code":"PPL",
    "gn:name":"Yangjia Pingzi",
    "gn:population":0,
    "gn:timezone":"Asia/Shanghai",
    "iso:country":"CN",
    "name:zho_x_preferred":[
        "\u6768\u5bb6\u576a\u5b50"
    ],
    "wof:name":"Yangjia Pingzi",
    "wof:placetype":"locality"
},
  "geometry": {"coordinates":[102.663,26.4266],"type":"Point"}
}