{
  "type": "Feature",
  "properties": {
    "gn:admin1_code":"29.0",
    "gn:asciiname":"Huanglong",
    "gn:country_code":"CN",
    "gn:dem":2098,
    "gn:feature_class":"P",
    "gn:feature_code":"PPL",
    "gn:name":"Huanglong",
    "gn:population":0,
    "gn:timezone":"Asia/Shanghai",
    "iso:country":"CN",
    "name:ceb_x_preferred":[
        "Huanglong"
    ],
    "name:deu_x_preferred":[
        "Huanglong"
    ],
    "name:fra_x_preferred":[
        "Huanglong"
    ],
    "name:kor_x_preferred":[
        "\ud669\ub8e1"
    ],
    "name:nor_x_preferred":[
        "Huanglong"
    ],
    "name:rus_x_preferred":[
        "\u0425\u0443\u0430\u043d\u043b\u0443\u043d"
    ],
    "name:vie_x_preferred":[
        "Ho\u00e0ng Long"
    ],
    "name:zho_x_preferred":[
        "\u9ec4\u9f99"
    ],
    "wof:name":"Huanglong",
    "wof:placetype":"locality"
},
  "geometry": {"coordinates":[100.008,26.2021],"type":"Point"}
}