{
  "type": "Feature",
  "properties": {
    "gn:admin1_code":"4.0",
    "gn:asciiname":"Baotashancun",
    "gn:country_code":"CN",
    "gn:dem":53,
    "gn:feature_class":"P",
    "gn:feature_code":"PPL",
    "gn:name":"Baotashancun",
    "gn:population":0,
    "gn:timezone":"Asia/Shanghai",
    "iso:country":"CN",
    "name:zho_x_preferred":[
        "\u5b9d\u5854\u5c71\u6751"
    ],
    "wof:name":"Baotashancun",
    "wof:placetype":"locality"
},
  "geometry": {"coordinates":[118.50115,32.85754],"type":"Point"}
}