{
  "type": "Feature",
  "properties": {
    "gn:admin1_code":"18.0",
    "gn:asciiname":"Qingganglin",
    "gn:country_code":"CN",
    "gn:dem":726,
    "gn:feature_class":"P",
    "gn:feature_code":"PPL",
    "gn:name":"Qingganglin",
    "gn:population":0,
    "gn:timezone":"Asia/Shanghai",
    "iso:country":"CN",
    "name:zho_x_preferred":[
        "\u9752\u6760\u6797"
    ],
    "wof:name":"Qingganglin",
    "wof:placetype":"locality"
},
  "geometry": {"coordinates":[108.01900000000001,26.6683],"type":"Point"}
}