{
  "type": "Feature",
  "properties": {
    "gn:admin1_code":"32.0",
    "gn:asciiname":"Sunjia Yuanzi",
    "gn:country_code":"CN",
    "gn:dem":441,
    "gn:feature_class":"P",
    "gn:feature_code":"PPL",
    "gn:name":"Sunjia Yuanzi",
    "gn:population":0,
    "gn:timezone":"Asia/Shanghai",
    "iso:country":"CN",
    "name:zho_x_preferred":[
        "\u5b59\u5bb6\u9662\u5b50"
    ],
    "wof:name":"Sunjia Yuanzi",
    "wof:placetype":"locality"
},
  "geometry": {"coordinates":[104.69799999999999,29.7971],"type":"Point"}
}