{
  "type": "Feature",
  "properties": {
    "gn:admin1_code":"30.0",
    "gn:asciiname":"Baijindong",
    "gn:country_code":"CN",
    "gn:dem":565,
    "gn:feature_class":"P",
    "gn:feature_code":"PPL",
    "gn:name":"Baijindong",
    "gn:population":0,
    "gn:timezone":"Asia/Shanghai",
    "iso:country":"CN",
    "name:zho_x_preferred":[
        "Baijindong"
    ],
    "name:zho_x_variant":[
        "\u767e\u65a4\u6d1e"
    ],
    "wof:name":"Baijindong",
    "wof:placetype":"locality"
},
  "geometry": {"coordinates":[112.32583,24.55194],"type":"Point"}
}