{
  "type": "Feature",
  "properties": {
    "gn:admin1_code":"26",
    "gn:asciiname":"Xiaohekou",
    "gn:country_code":"CN",
    "gn:dem":676,
    "gn:feature_class":"P",
    "gn:feature_code":"PPL",
    "gn:name":"Xiaohekou",
    "gn:population":0,
    "gn:timezone":"Asia/Shanghai",
    "iso:country":"CN",
    "wof:name":"Xiaohekou",
    "wof:placetype":"locality"
},
  "geometry": {"coordinates":[109.31083,32.27139],"type":"Point"}
}