{
  "type": "Feature",
  "properties": {
    "gn:admin1_code":"9.0",
    "gn:asciiname":"Lushigou",
    "gn:country_code":"CN",
    "gn:dem":1054,
    "gn:feature_class":"P",
    "gn:feature_code":"PPL",
    "gn:name":"Lushigou",
    "gn:population":0,
    "gn:timezone":"Asia/Shanghai",
    "iso:country":"CN",
    "name:zho_x_preferred":[
        "\u5362\u6c0f\u6c9f"
    ],
    "wof:name":"Lushigou",
    "wof:placetype":"locality"
},
  "geometry": {"coordinates":[110.81740000000001,34.12018],"type":"Point"}
}