{
  "type": "Feature",
  "properties": {
    "gn:admin1_code":"21.0",
    "gn:asciiname":"Xujia Kengkeng",
    "gn:country_code":"CN",
    "gn:dem":1697,
    "gn:feature_class":"P",
    "gn:feature_code":"PPL",
    "gn:name":"Xujia Kengkeng",
    "gn:population":0,
    "gn:timezone":"Asia/Shanghai",
    "iso:country":"CN",
    "name:zho_x_preferred":[
        "\u5f90\u5bb6\u5751\u5751"
    ],
    "wof:name":"Xujia Kengkeng",
    "wof:placetype":"locality"
},
  "geometry": {"coordinates":[105.218,36.9977],"type":"Point"}
}