{
  "type": "Feature",
  "properties": {
    "gn:admin1_code":"1.0",
    "gn:asciiname":"Liangyingcun",
    "gn:country_code":"CN",
    "gn:dem":59,
    "gn:feature_class":"P",
    "gn:feature_code":"PPL",
    "gn:name":"Liangyingcun",
    "gn:population":0,
    "gn:timezone":"Asia/Shanghai",
    "iso:country":"CN",
    "name:zho_x_preferred":[
        "\u6881\u90e2\u6751"
    ],
    "wof:name":"Liangyingcun",
    "wof:placetype":"locality"
},
  "geometry": {"coordinates":[116.45144999999999,31.95463],"type":"Point"}
}