{
  "type": "Feature",
  "properties": {
    "gn:admin1_code":"18",
    "gn:asciiname":"Daliangtian",
    "gn:country_code":"CN",
    "gn:dem":914,
    "gn:feature_class":"P",
    "gn:feature_code":"PPL",
    "gn:name":"Daliangtian",
    "gn:population":0,
    "gn:timezone":"Asia/Shanghai",
    "iso:country":"CN",
    "name:zho_x_preferred":[
        "\u5927\u7cae\u7530"
    ],
    "wof:name":"Daliangtian",
    "wof:placetype":"locality"
},
  "geometry": {"coordinates":[107.566,26.5235],"type":"Point"}
}