{
  "type": "Feature",
  "properties": {
    "gn:admin1_code":"15",
    "gn:asciiname":"Qinchuan",
    "gn:country_code":"CN",
    "gn:dem":2098,
    "gn:feature_class":"P",
    "gn:feature_code":"PPL",
    "gn:name":"Qinchuan",
    "gn:population":0,
    "gn:timezone":"Asia/Shanghai",
    "iso:country":"CN",
    "name:zho_x_preferred":[
        "\u79e6\u5ddd"
    ],
    "wof:name":"Qinchuan",
    "wof:placetype":"locality"
},
  "geometry": {"coordinates":[103.59999999999999,36.66667],"type":"Point"}
}