{
  "type": "Feature",
  "properties": {
    "gn:admin1_code":"19.0",
    "gn:asciiname":"Majiayingcun",
    "gn:country_code":"CN",
    "gn:dem":201,
    "gn:feature_class":"P",
    "gn:feature_code":"PPL",
    "gn:name":"Majiayingcun",
    "gn:population":0,
    "gn:timezone":"Asia/Shanghai",
    "iso:country":"CN",
    "name:zho_x_preferred":[
        "\u9a6c\u5bb6\u8425\u6751"
    ],
    "wof:name":"Majiayingcun",
    "wof:placetype":"locality"
},
  "geometry": {"coordinates":[121.11351000000001,41.66363],"type":"Point"}
}