{
  "type": "Feature",
  "properties": {
    "gn:admin1_code":"14.0",
    "gn:asciiname":"Banglong",
    "gn:country_code":"CN",
    "gn:dem":4966,
    "gn:feature_class":"P",
    "gn:feature_code":"PPL",
    "gn:name":"Banglong",
    "gn:population":0,
    "gn:timezone":"Asia/Urumqi",
    "iso:country":"CN",
    "name:zho_x_preferred":[
        "\u5e2e\u9f99"
    ],
    "wof:name":"Banglong",
    "wof:placetype":"locality"
},
  "geometry": {"coordinates":[93.97905,30.97048],"type":"Point"}
}