{
  "type": "Feature",
  "properties": {
    "gn:admin1_code":"26.0",
    "gn:asciiname":"Guandao Shancun",
    "gn:country_code":"CN",
    "gn:dem":970,
    "gn:feature_class":"P",
    "gn:feature_code":"PPL",
    "gn:name":"Guandao Shancun",
    "gn:population":0,
    "gn:timezone":"Asia/Shanghai",
    "iso:country":"CN",
    "name:zho_x_preferred":[
        "\u5b98\u9053\u5c71\u6751"
    ],
    "wof:name":"Guandao Shancun",
    "wof:placetype":"locality"
},
  "geometry": {"coordinates":[110.541,37.2673],"type":"Point"}
}