{
  "type": "Feature",
  "properties": {
    "gn:admin1_code":"11.0",
    "gn:asciiname":"Chenboshi",
    "gn:country_code":"CN",
    "gn:dem":51,
    "gn:feature_class":"P",
    "gn:feature_code":"PPL",
    "gn:name":"Chenboshi",
    "gn:population":0,
    "gn:timezone":"Asia/Shanghai",
    "iso:country":"CN",
    "name:zho_x_preferred":[
        "\u9648\u535a\u58eb"
    ],
    "wof:name":"Chenboshi",
    "wof:placetype":"locality"
},
  "geometry": {"coordinates":[113.19165,29.17579000000001],"type":"Point"}
}