{
  "type": "Feature",
  "properties": {
    "gn:admin1_code":"10",
    "gn:asciiname":"Huoshui",
    "gn:country_code":"CN",
    "gn:dem":597,
    "gn:feature_class":"P",
    "gn:feature_code":"PPL",
    "gn:name":"Huoshui",
    "gn:population":0,
    "gn:timezone":"Asia/Shanghai",
    "iso:country":"CN",
    "wof:name":"Huoshui",
    "wof:placetype":"locality"
},
  "geometry": {"coordinates":[113.98333,36.78333],"type":"Point"}
}