{
  "type": "Feature",
  "properties": {
    "gn:admin1_code":"7",
    "gn:asciiname":"Neiliao",
    "gn:country_code":"CN",
    "gn:dem":730,
    "gn:feature_class":"P",
    "gn:feature_code":"PPL",
    "gn:name":"Neiliao",
    "gn:population":0,
    "gn:timezone":"Asia/Shanghai",
    "iso:country":"CN",
    "name:zho_x_preferred":[
        "\u5185\u5bee"
    ],
    "wof:name":"Neiliao",
    "wof:placetype":"locality"
},
  "geometry": {"coordinates":[117.51342,24.88979],"type":"Point"}
}