{
  "type": "Feature",
  "properties": {
    "gn:admin1_code":"19.0",
    "gn:asciiname":"Shasong Xiabucun",
    "gn:country_code":"CN",
    "gn:dem":336,
    "gn:feature_class":"P",
    "gn:feature_code":"PPL",
    "gn:name":"Shasong Xiabucun",
    "gn:population":0,
    "gn:timezone":"Asia/Shanghai",
    "iso:country":"CN",
    "name:zho_x_preferred":[
        "\u6749\u677e\u4e0b\u5821\u6751"
    ],
    "wof:name":"Shasong Xiabucun",
    "wof:placetype":"locality"
},
  "geometry": {"coordinates":[124.45699999999999,41.4492],"type":"Point"}
}