{
  "type": "Feature",
  "properties": {
    "gn:admin1_code":"7.0",
    "gn:asciiname":"Liantangban",
    "gn:country_code":"CN",
    "gn:dem":537,
    "gn:feature_class":"P",
    "gn:feature_code":"PPL",
    "gn:name":"Liantangban",
    "gn:population":0,
    "gn:timezone":"Asia/Shanghai",
    "iso:country":"CN",
    "name:zho_x_preferred":[
        "\u83b2\u5858\u5742"
    ],
    "wof:name":"Liantangban",
    "wof:placetype":"locality"
},
  "geometry": {"coordinates":[118.73144000000001,27.95648],"type":"Point"}
}