{
  "type": "Feature",
  "properties": {
    "gn:admin1_code":"26.0",
    "gn:asciiname":"Shuichetoucun",
    "gn:country_code":"CN",
    "gn:dem":705,
    "gn:feature_class":"P",
    "gn:feature_code":"PPL",
    "gn:name":"Shuichetoucun",
    "gn:population":0,
    "gn:timezone":"Asia/Shanghai",
    "iso:country":"CN",
    "name:zho_x_preferred":[
        "\u6c34\u8f66\u5934\u6751"
    ],
    "wof:name":"Shuichetoucun",
    "wof:placetype":"locality"
},
  "geometry": {"coordinates":[110.14762,35.21859],"type":"Point"}
}