{
  "type": "Feature",
  "properties": {
    "gn:admin1_code":"15.0",
    "gn:asciiname":"Shuangdunzi",
    "gn:country_code":"CN",
    "gn:dem":1384,
    "gn:feature_class":"P",
    "gn:feature_code":"PPL",
    "gn:name":"Shuangdunzi",
    "gn:population":0,
    "gn:timezone":"Asia/Shanghai",
    "iso:country":"CN",
    "name:zho_x_preferred":[
        "\u53cc\u58a9\u5b50"
    ],
    "wof:name":"Shuangdunzi",
    "wof:placetype":"locality"
},
  "geometry": {"coordinates":[102.663,38.4639],"type":"Point"}
}