{
  "type": "Feature",
  "properties": {
    "gn:admin1_code":"15",
    "gn:asciiname":"Luoba",
    "gn:country_code":"CN",
    "gn:dem":1602,
    "gn:feature_class":"P",
    "gn:feature_code":"PPL",
    "gn:name":"Luoba",
    "gn:population":0,
    "gn:timezone":"Asia/Shanghai",
    "iso:country":"CN",
    "name:ces_x_preferred":[
        "Luoba"
    ],
    "wof:name":"Luoba",
    "wof:placetype":"locality"
},
  "geometry": {"coordinates":[105.06471999999999,34.32278],"type":"Point"}
}