{
  "type": "Feature",
  "properties": {
    "gn:admin1_code":"7.0",
    "gn:asciiname":"Shenqiaocun",
    "gn:country_code":"CN",
    "gn:dem":20,
    "gn:feature_class":"P",
    "gn:feature_code":"PPL",
    "gn:name":"Shenqiaocun",
    "gn:population":0,
    "gn:timezone":"Asia/Shanghai",
    "iso:country":"CN",
    "name:zho_x_preferred":[
        "\u6df1\u6865\u6751"
    ],
    "wof:name":"Shenqiaocun",
    "wof:placetype":"locality"
},
  "geometry": {"coordinates":[117.14058,23.72998],"type":"Point"}
}