{
  "type": "Feature",
  "properties": {
    "gn:admin1_code":"18",
    "gn:asciiname":"Moranzhai",
    "gn:country_code":"CN",
    "gn:dem":1189,
    "gn:feature_class":"P",
    "gn:feature_code":"PPL",
    "gn:name":"Moranzhai",
    "gn:population":0,
    "gn:timezone":"Asia/Shanghai",
    "iso:country":"CN",
    "name:zho_x_preferred":[
        "\u6a21\u7136\u5be8"
    ],
    "wof:name":"Moranzhai",
    "wof:placetype":"locality"
},
  "geometry": {"coordinates":[106.77200000000001,25.99],"type":"Point"}
}