{
  "type": "Feature",
  "properties": {
    "gn:admin1_code":"11.0",
    "gn:asciiname":"Goulaohuo",
    "gn:country_code":"CN",
    "gn:dem":597,
    "gn:feature_class":"P",
    "gn:feature_code":"PPL",
    "gn:name":"Goulaohuo",
    "gn:population":0,
    "gn:timezone":"Asia/Shanghai",
    "iso:country":"CN",
    "name:zho_x_preferred":[
        "\u72d7\u8001\u6d3b"
    ],
    "wof:name":"Goulaohuo",
    "wof:placetype":"locality"
},
  "geometry": {"coordinates":[113.29181,25.77938],"type":"Point"}
}