{
  "type": "Feature",
  "properties": {
    "gn:admin1_code":"29.0",
    "gn:asciiname":"Longtanzhai",
    "gn:country_code":"CN",
    "gn:dem":1714,
    "gn:feature_class":"P",
    "gn:feature_code":"PPL",
    "gn:name":"Longtanzhai",
    "gn:population":0,
    "gn:timezone":"Asia/Shanghai",
    "iso:country":"CN",
    "name:zho_x_preferred":[
        "\u9f99\u6f6d\u5be8"
    ],
    "wof:name":"Longtanzhai",
    "wof:placetype":"locality"
},
  "geometry": {"coordinates":[99.6507,24.8242],"type":"Point"}
}