{
  "type": "Feature",
  "properties": {
    "gn:admin1_code":"12.0",
    "gn:asciiname":"Dengjiatiankeng",
    "gn:country_code":"CN",
    "gn:dem":947,
    "gn:feature_class":"P",
    "gn:feature_code":"PPL",
    "gn:name":"Dengjiatiankeng",
    "gn:population":0,
    "gn:timezone":"Asia/Shanghai",
    "iso:country":"CN",
    "name:zho_x_preferred":[
        "\u9093\u5bb6\u5929\u5751"
    ],
    "wof:name":"Dengjiatiankeng",
    "wof:placetype":"locality"
},
  "geometry": {"coordinates":[110.78267,33.06804],"type":"Point"}
}