{
  "type": "Feature",
  "properties": {
    "gn:admin1_code":"24.0",
    "gn:asciiname":"Daizhaoling",
    "gn:country_code":"CN",
    "gn:dem":1083,
    "gn:feature_class":"P",
    "gn:feature_code":"PPL",
    "gn:name":"Daizhaoling",
    "gn:population":0,
    "gn:timezone":"Asia/Shanghai",
    "iso:country":"CN",
    "name:zho_x_preferred":[
        "\u4ee3\u7167\u5cad"
    ],
    "wof:name":"Daizhaoling",
    "wof:placetype":"locality"
},
  "geometry": {"coordinates":[112.82298,36.77525],"type":"Point"}
}