{
  "type": "Feature",
  "properties": {
    "gn:admin1_code":"16.0",
    "gn:asciiname":"Fenghao",
    "gn:country_code":"CN",
    "gn:dem":1192,
    "gn:feature_class":"P",
    "gn:feature_code":"PPL",
    "gn:name":"Fenghao",
    "gn:population":0,
    "gn:timezone":"Asia/Shanghai",
    "iso:country":"CN",
    "name:deu_x_preferred":[
        "Feng-Hao-St\u00e4tte"
    ],
    "name:epo_x_preferred":[
        "Feng-Hao ejo"
    ],
    "name:fas_x_preferred":[
        "\u0641\u0646\u06af\u0647\u0627\u0648"
    ],
    "name:ita_x_preferred":[
        "Fenghao"
    ],
    "name:rus_x_preferred":[
        "\u0424\u044d\u043d\u0445\u0430\u043e"
    ],
    "name:urd_x_preferred":[
        "\u0641\u06cc\u0646\u06af\u06c1\u0627\u0648"
    ],
    "name:zho_x_preferred":[
        "\u98ce\u7693"
    ],
    "wof:name":"Fenghao",
    "wof:placetype":"locality"
},
  "geometry": {"coordinates":[105.158,24.911],"type":"Point"}
}