{
  "type": "Feature",
  "properties": {
    "gn:admin1_code":"19.0",
    "gn:asciiname":"Baoshishancun",
    "gn:country_code":"CN",
    "gn:dem":141,
    "gn:feature_class":"P",
    "gn:feature_code":"PPL",
    "gn:name":"Baoshishancun",
    "gn:population":0,
    "gn:timezone":"Asia/Shanghai",
    "iso:country":"CN",
    "name:und_x_variant":[
        "Bushishancun",
        "Baoshishancun"
    ],
    "name:zho_x_preferred":[
        "\u5b9d\u77f3\u5c71\u6751"
    ],
    "wof:name":"Baoshishancun",
    "wof:placetype":"locality"
},
  "geometry": {"coordinates":[123.96116000000001,40.45477],"type":"Point"}
}