{
  "type": "Feature",
  "properties": {
    "gn:admin1_code":"30.0",
    "gn:asciiname":"Shawantang",
    "gn:country_code":"CN",
    "gn:dem":0,
    "gn:feature_class":"P",
    "gn:feature_code":"PPL",
    "gn:name":"Shawantang",
    "gn:population":0,
    "gn:timezone":"Asia/Shanghai",
    "iso:country":"CN",
    "name:zho_x_preferred":[
        "\u6c99\u6e7e\u5858"
    ],
    "wof:name":"Shawantang",
    "wof:placetype":"locality"
},
  "geometry": {"coordinates":[112.38330000000001,21.92253],"type":"Point"}
}