{
  "type": "Feature",
  "properties": {
    "gn:admin1_code":"19.0",
    "gn:asciiname":"Baotai Beigou",
    "gn:country_code":"CN",
    "gn:dem":66,
    "gn:feature_class":"P",
    "gn:feature_code":"PPL",
    "gn:name":"Baotai Beigou",
    "gn:population":0,
    "gn:timezone":"Asia/Shanghai",
    "iso:country":"CN",
    "name:und_x_variant":[
        "\u5b9d\u592a\u5317\u6c9f"
    ],
    "wof:name":"Baotai Beigou",
    "wof:placetype":"locality"
},
  "geometry": {"coordinates":[123.93079,40.14409000000001],"type":"Point"}
}