{
  "type": "Feature",
  "properties": {
    "gn:admin1_code":"30",
    "gn:asciiname":"Fengzhoudong",
    "gn:country_code":"CN",
    "gn:dem":29,
    "gn:feature_class":"P",
    "gn:feature_code":"PPL",
    "gn:name":"Fengzhoudong",
    "gn:population":0,
    "gn:timezone":"Asia/Urumqi",
    "iso:country":"CN",
    "name:zho_x_preferred":[
        "\u4e30\u5468\u578c"
    ],
    "wof:name":"Fengzhoudong",
    "wof:placetype":"locality"
},
  "geometry": {"coordinates":[110.17395,21.64398],"type":"Point"}
}