{
  "type": "Feature",
  "properties": {
    "gn:admin1_code":"16",
    "gn:asciiname":"Doufuzha",
    "gn:country_code":"CN",
    "gn:dem":162,
    "gn:feature_class":"P",
    "gn:feature_code":"PPL",
    "gn:name":"Doufuzha",
    "gn:population":0,
    "gn:timezone":"Asia/Shanghai",
    "iso:country":"CN",
    "name:zho_x_preferred":[
        "\u8c46\u8150\u69a8"
    ],
    "wof:name":"Doufuzha",
    "wof:placetype":"locality"
},
  "geometry": {"coordinates":[110.86799999999999,24.9811],"type":"Point"}
}