{
  "type": "Feature",
  "properties": {
    "gn:admin1_code":"26.0",
    "gn:asciiname":"Jinqicun",
    "gn:country_code":"CN",
    "gn:dem":707,
    "gn:feature_class":"P",
    "gn:feature_code":"PPL",
    "gn:name":"Jinqicun",
    "gn:population":0,
    "gn:timezone":"Asia/Shanghai",
    "iso:country":"CN",
    "name:zho_x_preferred":[
        "\u91d1\u9f50\u6751"
    ],
    "wof:name":"Jinqicun",
    "wof:placetype":"locality"
},
  "geometry": {"coordinates":[108.12588999999998,32.90765],"type":"Point"}
}