{
  "type": "Feature",
  "properties": {
    "gn:admin1_code":"24.0",
    "gn:asciiname":"Huanghualiang",
    "gn:country_code":"CN",
    "gn:dem":1932,
    "gn:feature_class":"P",
    "gn:feature_code":"PPL",
    "gn:name":"Huanghualiang",
    "gn:population":0,
    "gn:timezone":"Asia/Shanghai",
    "iso:country":"CN",
    "name:zho_x_preferred":[
        "\u9ec4\u82b1\u6881"
    ],
    "wof:name":"Huanghualiang",
    "wof:placetype":"locality"
},
  "geometry": {"coordinates":[113.50909,38.7759],"type":"Point"}
}