{
  "type": "Feature",
  "properties": {
    "gn:admin1_code":"15.0",
    "gn:asciiname":"Xianghuaping",
    "gn:country_code":"CN",
    "gn:dem":2299,
    "gn:feature_class":"P",
    "gn:feature_code":"PPL",
    "gn:name":"Xianghuaping",
    "gn:population":0,
    "gn:timezone":"Asia/Shanghai",
    "iso:country":"CN",
    "name:zho_x_preferred":[
        "\u9999\u82b1\u576a"
    ],
    "wof:name":"Xianghuaping",
    "wof:placetype":"locality"
},
  "geometry": {"coordinates":[103.13800000000001,35.3649],"type":"Point"}
}