{
  "type": "Feature",
  "properties": {
    "gn:admin1_code":"9.0",
    "gn:asciiname":"Shenxiancui",
    "gn:country_code":"CN",
    "gn:dem":248,
    "gn:feature_class":"P",
    "gn:feature_code":"PPL",
    "gn:name":"Shenxiancui",
    "gn:population":0,
    "gn:timezone":"Asia/Shanghai",
    "iso:country":"CN",
    "name:und_x_variant":[
        "\u795e\u4ed9\u5d14",
        "Shenxiancui"
    ],
    "wof:name":"Shenxiancui",
    "wof:placetype":"locality"
},
  "geometry": {"coordinates":[112.29333,33.23115],"type":"Point"}
}