{
  "type": "Feature",
  "properties": {
    "gn:admin1_code":"4.0",
    "gn:asciiname":"Shenzhuang",
    "gn:country_code":"CN",
    "gn:dem":3,
    "gn:feature_class":"P",
    "gn:feature_code":"PPL",
    "gn:name":"Shenzhuang",
    "gn:population":0,
    "gn:timezone":"Asia/Shanghai",
    "iso:country":"CN",
    "name:zho_x_preferred":[
        "\u6c88\u5e84"
    ],
    "wof:name":"Shenzhuang",
    "wof:placetype":"locality"
},
  "geometry": {"coordinates":[118.864,34.4323],"type":"Point"}
}