{
  "type": "Feature",
  "properties": {
    "gn:admin1_code":"30.0",
    "gn:asciiname":"Jikeng",
    "gn:country_code":"CN",
    "gn:dem":95,
    "gn:feature_class":"P",
    "gn:feature_code":"PPL",
    "gn:name":"Jikeng",
    "gn:population":0,
    "gn:timezone":"Asia/Shanghai",
    "iso:country":"CN",
    "name:zho_x_preferred":[
        "\u57fa\u5751"
    ],
    "wof:name":"Jikeng",
    "wof:placetype":"locality"
},
  "geometry": {"coordinates":[114.11127999999999,23.70601],"type":"Point"}
}