{
  "type": "Feature",
  "properties": {
    "gn:admin1_code":"29",
    "gn:asciiname":"Anyi",
    "gn:country_code":"CN",
    "gn:dem":1557,
    "gn:feature_class":"P",
    "gn:feature_code":"PPL",
    "gn:name":"Anyi",
    "gn:population":0,
    "gn:timezone":"Asia/Shanghai",
    "iso:country":"CN",
    "name:ceb_x_preferred":[
        "Anyi"
    ],
    "name:deu_x_preferred":[
        "Anyi"
    ],
    "name:fra_x_preferred":[
        "Anyi"
    ],
    "name:nld_x_preferred":[
        "Anyi"
    ],
    "name:nor_x_preferred":[
        "Anyi"
    ],
    "name:rus_x_preferred":[
        "\u0410\u043d\u044c\u0438"
    ],
    "name:zho_x_preferred":[
        "\u5b89\u9038"
    ],
    "wof:name":"Anyi",
    "wof:placetype":"locality"
},
  "geometry": {"coordinates":[102.413,24.1645],"type":"Point"}
}