{
  "type": "Feature",
  "properties": {
    "gn:admin1_code":"3.0",
    "gn:asciiname":"Hongqiao",
    "gn:country_code":"CN",
    "gn:dem":77,
    "gn:feature_class":"P",
    "gn:feature_code":"PPL",
    "gn:name":"Hongqiao",
    "gn:population":0,
    "gn:timezone":"Asia/Shanghai",
    "iso:country":"CN",
    "name:ceb_x_preferred":[
        "Hongqiao"
    ],
    "name:deu_x_preferred":[
        "Hongqiao"
    ],
    "name:fra_x_preferred":[
        "Hongqiao"
    ],
    "name:kor_x_preferred":[
        "\ud6d9\ucc28\uc624"
    ],
    "name:mlg_x_preferred":[
        "Hongqiao"
    ],
    "name:zho_x_preferred":[
        "\u6d2a\u6865"
    ],
    "wof:name":"Hongqiao",
    "wof:placetype":"locality"
},
  "geometry": {"coordinates":[115.378,27.1177],"type":"Point"}
}