{
  "type": "Feature",
  "properties": {
    "gn:admin1_code":"14.0",
    "gn:asciiname":"Gedou",
    "gn:country_code":"CN",
    "gn:dem":4100,
    "gn:feature_class":"P",
    "gn:feature_code":"PPL",
    "gn:name":"Gedou",
    "gn:population":0,
    "gn:timezone":"Asia/Urumqi",
    "iso:country":"CN",
    "name:zho_x_preferred":[
        "\u683c\u6597"
    ],
    "wof:name":"Gedou",
    "wof:placetype":"locality"
},
  "geometry": {"coordinates":[95.88701,30.68541],"type":"Point"}
}