{
  "type": "Feature",
  "properties": {
    "gn:admin1_code":"15.0",
    "gn:asciiname":"Yunwu",
    "gn:country_code":"CN",
    "gn:dem":1343,
    "gn:feature_class":"P",
    "gn:feature_code":"PPL",
    "gn:name":"Yunwu",
    "gn:population":0,
    "gn:timezone":"Asia/Shanghai",
    "iso:country":"CN",
    "name:zho_x_preferred":[
        "\u4e91\u52a1"
    ],
    "wof:name":"Yunwu",
    "wof:placetype":"locality"
},
  "geometry": {"coordinates":[105.902,34.4306],"type":"Point"}
}