{
  "type": "Feature",
  "properties": {
    "gn:admin1_code":"29.0",
    "gn:asciiname":"Wanyaodi",
    "gn:country_code":"CN",
    "gn:dem":2049,
    "gn:feature_class":"P",
    "gn:feature_code":"PPL",
    "gn:name":"Wanyaodi",
    "gn:population":0,
    "gn:timezone":"Asia/Shanghai",
    "iso:country":"CN",
    "name:zho_x_preferred":[
        "\u5f2f\u8170\u5730"
    ],
    "wof:name":"Wanyaodi",
    "wof:placetype":"locality"
},
  "geometry": {"coordinates":[102.80200000000001,25.8091],"type":"Point"}
}