{
  "type": "Feature",
  "properties": {
    "gn:admin1_code":"1.0",
    "gn:asciiname":"Nanchangcun",
    "gn:country_code":"CN",
    "gn:dem":47,
    "gn:feature_class":"P",
    "gn:feature_code":"PPL",
    "gn:name":"Nanchangcun",
    "gn:population":0,
    "gn:timezone":"Asia/Shanghai",
    "iso:country":"CN",
    "name:zho_x_preferred":[
        "\u5357\u573a\u6751"
    ],
    "wof:name":"Nanchangcun",
    "wof:placetype":"locality"
},
  "geometry": {"coordinates":[117.28668,32.72308],"type":"Point"}
}