{
  "type": "Feature",
  "properties": {
    "gn:admin1_code":"30",
    "gn:asciiname":"Bangtang Beicun",
    "gn:country_code":"CN",
    "gn:dem":36,
    "gn:feature_class":"P",
    "gn:feature_code":"PPL",
    "gn:name":"Bangtang Beicun",
    "gn:population":0,
    "gn:timezone":"Asia/Urumqi",
    "iso:country":"CN",
    "name:zho_x_preferred":[
        "\u90a6\u5858\u5317\u6751"
    ],
    "wof:name":"Bangtang Beicun",
    "wof:placetype":"locality"
},
  "geometry": {"coordinates":[110.04658000000001,20.9569],"type":"Point"}
}