{
  "type": "Feature",
  "properties": {
    "gn:admin1_code":"18",
    "gn:asciiname":"Xiangshuping",
    "gn:country_code":"CN",
    "gn:dem":1069,
    "gn:feature_class":"P",
    "gn:feature_code":"PPL",
    "gn:name":"Xiangshuping",
    "gn:population":0,
    "gn:timezone":"Asia/Shanghai",
    "iso:country":"CN",
    "name:zho_x_preferred":[
        "\u9999\u6811\u576a"
    ],
    "wof:name":"Xiangshuping",
    "wof:placetype":"locality"
},
  "geometry": {"coordinates":[106.86199999999999,27.1141],"type":"Point"}
}