{
  "type": "Feature",
  "properties": {
    "gn:admin1_code":"32.0",
    "gn:asciiname":"Duozheng",
    "gn:country_code":"CN",
    "gn:dem":3781,
    "gn:feature_class":"P",
    "gn:feature_code":"PPL",
    "gn:name":"Duozheng",
    "gn:population":0,
    "gn:timezone":"Asia/Shanghai",
    "iso:country":"CN",
    "name:zho_x_preferred":[
        "\u593a\u5ce5"
    ],
    "wof:name":"Duozheng",
    "wof:placetype":"locality"
},
  "geometry": {"coordinates":[98.2607,32.3516],"type":"Point"}
}