{
  "type": "Feature",
  "properties": {
    "gn:admin1_code":"5.0",
    "gn:asciiname":"Bali Yingzi",
    "gn:country_code":"CN",
    "gn:dem":133,
    "gn:feature_class":"P",
    "gn:feature_code":"PPL",
    "gn:name":"Bali Yingzi",
    "gn:population":0,
    "gn:timezone":"Asia/Shanghai",
    "iso:country":"CN",
    "name:zho_x_preferred":[
        "\u516b\u91cc\u8425\u5b50"
    ],
    "wof:name":"Bali Yingzi",
    "wof:placetype":"locality"
},
  "geometry": {"coordinates":[124.03903,43.72512],"type":"Point"}
}