{
  "type": "Feature",
  "properties": {
    "gn:admin1_code":"2.0",
    "gn:asciiname":"Qiaotouhuang",
    "gn:country_code":"CN",
    "gn:dem":61,
    "gn:feature_class":"P",
    "gn:feature_code":"PPL",
    "gn:name":"Qiaotouhuang",
    "gn:population":0,
    "gn:timezone":"Asia/Shanghai",
    "iso:country":"CN",
    "name:zho_x_preferred":[
        "\u6865\u5934\u9ec4"
    ],
    "wof:name":"Qiaotouhuang",
    "wof:placetype":"locality"
},
  "geometry": {"coordinates":[120.14637999999999,29.95243],"type":"Point"}
}