{
  "type": "Feature",
  "properties": {
    "gn:admin1_code":"16.0",
    "gn:asciiname":"Shenjia Dongzi",
    "gn:country_code":"CN",
    "gn:dem":1262,
    "gn:feature_class":"P",
    "gn:feature_code":"PPL",
    "gn:name":"Shenjia Dongzi",
    "gn:population":0,
    "gn:timezone":"Asia/Shanghai",
    "iso:country":"CN",
    "name:zho_x_preferred":[
        "\u7533\u5bb6\u5cd2\u5b50"
    ],
    "wof:name":"Shenjia Dongzi",
    "wof:placetype":"locality"
},
  "geometry": {"coordinates":[106.42,24.7271],"type":"Point"}
}