{
  "type": "Feature",
  "properties": {
    "gn:admin1_code":"2.0",
    "gn:asciiname":"Santan",
    "gn:country_code":"CN",
    "gn:dem":657,
    "gn:feature_class":"P",
    "gn:feature_code":"PPL",
    "gn:name":"Santan",
    "gn:population":0,
    "gn:timezone":"Asia/Shanghai",
    "iso:country":"CN",
    "name:und_x_variant":[
        "\u4e09\u6ee9",
        "Santan"
    ],
    "wof:name":"Santan",
    "wof:placetype":"locality"
},
  "geometry": {"coordinates":[119.96505000000001,27.90496],"type":"Point"}
}