{
  "type": "Feature",
  "properties": {
    "gn:admin1_code":"16.0",
    "gn:asciiname":"Longxing",
    "gn:country_code":"CN",
    "gn:dem":188,
    "gn:feature_class":"P",
    "gn:feature_code":"PPL",
    "gn:name":"Longxing",
    "gn:population":0,
    "gn:timezone":"Asia/Shanghai",
    "iso:country":"CN",
    "name:deu_x_preferred":[
        "Longxing"
    ],
    "name:zho_x_preferred":[
        "\u9f99\u5174"
    ],
    "wof:name":"Longxing",
    "wof:placetype":"locality"
},
  "geometry": {"coordinates":[109.18300000000001,24.2242],"type":"Point"}
}