{
  "type": "Feature",
  "properties": {
    "gn:admin1_code":"24.0",
    "gn:asciiname":"Yunshibu",
    "gn:country_code":"CN",
    "gn:dem":1569,
    "gn:feature_class":"P",
    "gn:feature_code":"PPL",
    "gn:name":"Yunshibu",
    "gn:population":0,
    "gn:timezone":"Asia/Shanghai",
    "iso:country":"CN",
    "name:und_x_variant":[
        "\u4e91\u77f3\u5821"
    ],
    "name:zho_x_preferred":[
        "\u4e91\u77f3\u5821"
    ],
    "wof:name":"Yunshibu",
    "wof:placetype":"locality"
},
  "geometry": {"coordinates":[112.16621000000001,40.03238],"type":"Point"}
}