{
  "type": "Feature",
  "properties": {
    "gn:admin1_code":"29",
    "gn:asciiname":"Hetouzhangjia",
    "gn:country_code":"CN",
    "gn:dem":1890,
    "gn:feature_class":"P",
    "gn:feature_code":"PPL",
    "gn:name":"Hetouzhangjia",
    "gn:population":0,
    "gn:timezone":"Asia/Shanghai",
    "iso:country":"CN",
    "name:zho_x_preferred":[
        "\u6cb3\u5934\u5f20\u5bb6"
    ],
    "wof:name":"Hetouzhangjia",
    "wof:placetype":"locality"
},
  "geometry": {"coordinates":[101.59099999999999,25.1753],"type":"Point"}
}