{
  "type": "Feature",
  "properties": {
    "gn:admin1_code":"15.0",
    "gn:asciiname":"Tu'anshan",
    "gn:country_code":"CN",
    "gn:dem":1582,
    "gn:feature_class":"P",
    "gn:feature_code":"PPL",
    "gn:name":"Tu\u2019anshan",
    "gn:population":0,
    "gn:timezone":"Asia/Shanghai",
    "iso:country":"CN",
    "name:und_x_variant":[
        "Tu\u2019anshan",
        "\u571f\u5b89\u5c71"
    ],
    "wof:name":"Tu'anshan",
    "wof:placetype":"locality"
},
  "geometry": {"coordinates":[105.60192000000001,33.19777],"type":"Point"}
}