{
  "type": "Feature",
  "properties": {
    "gn:admin1_code":"21.0",
    "gn:asciiname":"Luping",
    "gn:country_code":"CN",
    "gn:dem":1664,
    "gn:feature_class":"P",
    "gn:feature_code":"PPL",
    "gn:name":"L\u00fcping",
    "gn:population":0,
    "gn:timezone":"Asia/Shanghai",
    "iso:country":"CN",
    "name:und_x_variant":[
        "L\u00fcping",
        "\u5415\u576a"
    ],
    "name:zho_x_preferred":[
        "\u5415\u576a"
    ],
    "wof:name":"Luping",
    "wof:placetype":"locality"
},
  "geometry": {"coordinates":[106.46165999999999,36.05805],"type":"Point"}
}