{
  "type": "Feature",
  "properties": {
    "gn:admin1_code":"7",
    "gn:asciiname":"Niuchengwei",
    "gn:country_code":"CN",
    "gn:dem":76,
    "gn:feature_class":"P",
    "gn:feature_code":"PPL",
    "gn:name":"Niuchengwei",
    "gn:population":0,
    "gn:timezone":"Asia/Shanghai",
    "iso:country":"CN",
    "name:zho_x_preferred":[
        "\u725b\u57d5\u5c3e"
    ],
    "wof:name":"Niuchengwei",
    "wof:placetype":"locality"
},
  "geometry": {"coordinates":[117.77657000000001,24.21768],"type":"Point"}
}