{
  "type": "Feature",
  "properties": {
    "gn:admin1_code":"21.0",
    "gn:asciiname":"Haijiagou",
    "gn:country_code":"CN",
    "gn:dem":1685,
    "gn:feature_class":"P",
    "gn:feature_code":"PPL",
    "gn:name":"Haijiagou",
    "gn:population":0,
    "gn:timezone":"Asia/Shanghai",
    "iso:country":"CN",
    "name:zho_x_preferred":[
        "\u6d77\u5bb6\u6c9f"
    ],
    "wof:name":"Haijiagou",
    "wof:placetype":"locality"
},
  "geometry": {"coordinates":[106.44799999999999,35.8451],"type":"Point"}
}