{
  "type": "Feature",
  "properties": {
    "gn:admin1_code":"11",
    "gn:asciiname":"Laoganling",
    "gn:country_code":"CN",
    "gn:dem":290,
    "gn:feature_class":"P",
    "gn:feature_code":"PPL",
    "gn:name":"Laoganling",
    "gn:population":0,
    "gn:timezone":"Asia/Shanghai",
    "iso:country":"CN",
    "name:zho_x_preferred":[
        "\u8001\u5e72\u5cad"
    ],
    "wof:name":"Laoganling",
    "wof:placetype":"locality"
},
  "geometry": {"coordinates":[111.39005,25.57679],"type":"Point"}
}