{
  "type": "Feature",
  "properties": {
    "gn:admin1_code":"11",
    "gn:asciiname":"Tiandang",
    "gn:country_code":"CN",
    "gn:dem":312,
    "gn:feature_class":"P",
    "gn:feature_code":"PPL",
    "gn:name":"Tiandang",
    "gn:population":0,
    "gn:timezone":"Asia/Shanghai",
    "iso:country":"CN",
    "name:zho_x_preferred":[
        "\u7530\u51fc"
    ],
    "wof:name":"Tiandang",
    "wof:placetype":"locality"
},
  "geometry": {"coordinates":[111.11378000000001,27.36362],"type":"Point"}
}