{
  "type": "Feature",
  "properties": {
    "gn:admin1_code":"11.0",
    "gn:asciiname":"Guanfenshan",
    "gn:country_code":"CN",
    "gn:dem":417,
    "gn:feature_class":"P",
    "gn:feature_code":"PPL",
    "gn:name":"Guanfenshan",
    "gn:population":0,
    "gn:timezone":"Asia/Shanghai",
    "iso:country":"CN",
    "name:zho_x_preferred":[
        "\u5b98\u575f\u5c71"
    ],
    "wof:name":"Guanfenshan",
    "wof:placetype":"locality"
},
  "geometry": {"coordinates":[110.99854999999999,29.80234],"type":"Point"}
}