{
  "type": "Feature",
  "properties": {
    "gn:admin1_code":"11.0",
    "gn:asciiname":"Xinao",
    "gn:country_code":"CN",
    "gn:dem":388,
    "gn:feature_class":"P",
    "gn:feature_code":"PPL",
    "gn:name":"Xinao",
    "gn:population":0,
    "gn:timezone":"Asia/Shanghai",
    "iso:country":"CN",
    "name:zho_x_preferred":[
        "\u6eaa\u8111"
    ],
    "wof:name":"Xinao",
    "wof:placetype":"locality"
},
  "geometry": {"coordinates":[109.72722,25.94356],"type":"Point"}
}