{
  "type": "Feature",
  "properties": {
    "gn:admin1_code":"19.0",
    "gn:asciiname":"Zhoujia Buzi",
    "gn:country_code":"CN",
    "gn:dem":243,
    "gn:feature_class":"P",
    "gn:feature_code":"PPL",
    "gn:name":"Zhoujia Buzi",
    "gn:population":0,
    "gn:timezone":"Asia/Shanghai",
    "iso:country":"CN",
    "name:und_x_variant":[
        "Zhoujia Puzi",
        "Zhoujia Buzi"
    ],
    "name:zho_x_preferred":[
        "\u5468\u5bb6\u5821\u5b50"
    ],
    "wof:name":"Zhoujia Buzi",
    "wof:placetype":"locality"
},
  "geometry": {"coordinates":[122.99269,40.27276],"type":"Point"}
}