{
  "type": "Feature",
  "properties": {
    "gn:admin1_code":"15.0",
    "gn:asciiname":"Chaizhuang",
    "gn:country_code":"CN",
    "gn:dem":1388,
    "gn:feature_class":"P",
    "gn:feature_code":"PPL",
    "gn:name":"Chaizhuang",
    "gn:population":0,
    "gn:timezone":"Asia/Shanghai",
    "iso:country":"CN",
    "name:zho_x_preferred":[
        "\u67f4\u5e84"
    ],
    "wof:name":"Chaizhuang",
    "wof:placetype":"locality"
},
  "geometry": {"coordinates":[107.398,35.7273],"type":"Point"}
}