{
  "type": "Feature",
  "properties": {
    "gn:admin1_code":"7.0",
    "gn:asciiname":"Lingao'ao",
    "gn:country_code":"CN",
    "gn:dem":395,
    "gn:feature_class":"P",
    "gn:feature_code":"PPL",
    "gn:name":"Lingao\u2019ao",
    "gn:population":0,
    "gn:timezone":"Asia/Shanghai",
    "iso:country":"CN",
    "name:und_x_variant":[
        "\u6797\u9ad8\u5773"
    ],
    "name:zho_x_preferred":[
        "Lingao\u2019ao"
    ],
    "name:zho_x_variant":[
        "\u6797\u9ad8\u5773"
    ],
    "wof:name":"Lingao'ao",
    "wof:placetype":"locality"
},
  "geometry": {"coordinates":[116.78610999999999,26.42319],"type":"Point"}
}