{
  "type": "Feature",
  "properties": {
    "gn:admin1_code":"8.0",
    "gn:asciiname":"De'ancun",
    "gn:country_code":"CN",
    "gn:dem":79,
    "gn:feature_class":"P",
    "gn:feature_code":"PPL",
    "gn:name":"De\u2019ancun",
    "gn:population":0,
    "gn:timezone":"Asia/Shanghai",
    "iso:country":"CN",
    "name:und_x_variant":[
        "De\u2019ancun"
    ],
    "name:zho_x_preferred":[
        "\u5fb7\u5b89\u6751"
    ],
    "wof:name":"De'ancun",
    "wof:placetype":"locality"
},
  "geometry": {"coordinates":[131.80938,47.19132000000001],"type":"Point"}
}