{
  "type": "Feature",
  "properties": {
    "gn:admin1_code":"7.0",
    "gn:asciiname":"Chilushui",
    "gn:country_code":"CN",
    "gn:dem":279,
    "gn:feature_class":"P",
    "gn:feature_code":"PPL",
    "gn:name":"Chilushui",
    "gn:population":0,
    "gn:timezone":"Asia/Shanghai",
    "iso:country":"CN",
    "name:zho_x_preferred":[
        "\u8d64\u9732\u6c34"
    ],
    "wof:name":"Chilushui",
    "wof:placetype":"locality"
},
  "geometry": {"coordinates":[116.09677000000001,25.05955],"type":"Point"}
}