{
  "type": "Feature",
  "properties": {
    "gn:admin1_code":"32",
    "gn:asciiname":"Guanba",
    "gn:country_code":"CN",
    "gn:dem":895,
    "gn:feature_class":"P",
    "gn:feature_code":"PPL",
    "gn:name":"Guanba",
    "gn:population":0,
    "gn:timezone":"Asia/Shanghai",
    "iso:country":"CN",
    "wof:name":"Guanba",
    "wof:placetype":"locality"
},
  "geometry": {"coordinates":[107.85056000000002,32.16167],"type":"Point"}
}