{
  "type": "Feature",
  "properties": {
    "gn:admin1_code":"32.0",
    "gn:asciiname":"Renheyan",
    "gn:country_code":"CN",
    "gn:dem":2387,
    "gn:feature_class":"P",
    "gn:feature_code":"PPL",
    "gn:name":"Renheyan",
    "gn:population":0,
    "gn:timezone":"Asia/Shanghai",
    "iso:country":"CN",
    "name:zho_x_preferred":[
        "\u4ec1\u548c\u5830"
    ],
    "wof:name":"Renheyan",
    "wof:placetype":"locality"
},
  "geometry": {"coordinates":[101.545,27.4707],"type":"Point"}
}