{
  "type": "Feature",
  "properties": {
    "gn:admin1_code":"15",
    "gn:asciiname":"Dachuan",
    "gn:cc2":"CN",
    "gn:country_code":"CN",
    "gn:dem":1586,
    "gn:feature_class":"P",
    "gn:feature_code":"PPL",
    "gn:name":"Dachuan",
    "gn:population":0,
    "gn:timezone":"Asia/Shanghai",
    "iso:country":"CN",
    "name:und_x_variant":[
        "Pa-p\u2019an-hsia",
        "Dachuan"
    ],
    "wof:name":"Dachuan",
    "wof:placetype":"locality"
},
  "geometry": {"coordinates":[103.35527999999999,36.12611],"type":"Point"}
}