{
  "type": "Feature",
  "properties": {
    "gn:admin1_code":"26",
    "gn:asciiname":"Kangmacun",
    "gn:country_code":"CN",
    "gn:dem":419,
    "gn:feature_class":"P",
    "gn:feature_code":"PPL",
    "gn:name":"Kangmacun",
    "gn:population":0,
    "gn:timezone":"Asia/Shanghai",
    "iso:country":"CN",
    "name:und_x_variant":[
        "\u5eb7\u9a6c\u6751",
        "Kangmacun"
    ],
    "wof:name":"Kangmacun",
    "wof:placetype":"locality"
},
  "geometry": {"coordinates":[109.03563,34.67484],"type":"Point"}
}