{
  "type": "Feature",
  "properties": {
    "gn:admin1_code":"19.0",
    "gn:asciiname":"Damuyu",
    "gn:country_code":"CN",
    "gn:dem":229,
    "gn:feature_class":"P",
    "gn:feature_code":"PPL",
    "gn:name":"Damuyu",
    "gn:population":0,
    "gn:timezone":"Asia/Shanghai",
    "iso:country":"CN",
    "name:und_x_variant":[
        "\u5927\u6728\u5cea"
    ],
    "wof:name":"Damuyu",
    "wof:placetype":"locality"
},
  "geometry": {"coordinates":[122.72951,40.43352],"type":"Point"}
}