{
  "type": "Feature",
  "properties": {
    "gn:admin1_code":"29",
    "gn:asciiname":"Yingmenqian",
    "gn:country_code":"CN",
    "gn:dem":1576,
    "gn:feature_class":"P",
    "gn:feature_code":"PPL",
    "gn:name":"Yingmenqian",
    "gn:population":0,
    "gn:timezone":"Asia/Shanghai",
    "iso:country":"CN",
    "name:zho_x_preferred":[
        "\u8425\u95e8\u524d"
    ],
    "wof:name":"Yingmenqian",
    "wof:placetype":"locality"
},
  "geometry": {"coordinates":[105.229,24.0031],"type":"Point"}
}