{
  "type": "Feature",
  "properties": {
    "gn:admin1_code":"10",
    "gn:asciiname":"Shuiquanliang",
    "gn:country_code":"CN",
    "gn:dem":1503,
    "gn:feature_class":"P",
    "gn:feature_code":"PPL",
    "gn:name":"Shuiquanliang",
    "gn:population":0,
    "gn:timezone":"Asia/Shanghai",
    "iso:country":"CN",
    "name:zho_x_preferred":[
        "\u6c34\u6cc9\u6881"
    ],
    "wof:name":"Shuiquanliang",
    "wof:placetype":"locality"
},
  "geometry": {"coordinates":[115.70937000000001,41.46314],"type":"Point"}
}