{
  "type": "Feature",
  "properties": {
    "gn:admin1_code":"30.0",
    "gn:asciiname":"Qingxicun",
    "gn:country_code":"CN",
    "gn:dem":77,
    "gn:feature_class":"P",
    "gn:feature_code":"PPL",
    "gn:name":"Qingxicun",
    "gn:population":0,
    "gn:timezone":"Asia/Shanghai",
    "iso:country":"CN",
    "name:und_x_variant":[
        "Qingxi"
    ],
    "name:zho_x_preferred":[
        "\u9752\u6eaa\u6751"
    ],
    "name:zho_x_variant":[
        "\u9752\u6eaa"
    ],
    "wof:name":"Qingxicun",
    "wof:placetype":"locality"
},
  "geometry": {"coordinates":[116.62166000000001,24.59175],"type":"Point"}
}