{
  "type": "Feature",
  "properties": {
    "gn:admin1_code":"29.0",
    "gn:asciiname":"Mizudi",
    "gn:country_code":"CN",
    "gn:dem":1855,
    "gn:feature_class":"P",
    "gn:feature_code":"PPL",
    "gn:name":"Mizudi",
    "gn:population":0,
    "gn:timezone":"Asia/Shanghai",
    "iso:country":"CN",
    "name:zho_x_preferred":[
        "\u7c73\u79df\u5e95"
    ],
    "wof:name":"Mizudi",
    "wof:placetype":"locality"
},
  "geometry": {"coordinates":[103.896,23.2709],"type":"Point"}
}