{
  "type": "Feature",
  "properties": {
    "gn:admin1_code":"12.0",
    "gn:asciiname":"Mozixi",
    "gn:country_code":"CN",
    "gn:dem":137,
    "gn:feature_class":"P",
    "gn:feature_code":"PPL",
    "gn:name":"Mozixi",
    "gn:population":0,
    "gn:timezone":"Asia/Shanghai",
    "iso:country":"CN",
    "name:zho_x_preferred":[
        "Mozixi"
    ],
    "name:zho_x_variant":[
        "\u78e8\u5b50\u6eaa"
    ],
    "wof:name":"Mozixi",
    "wof:placetype":"locality"
},
  "geometry": {"coordinates":[111.49097,30.66373],"type":"Point"}
}