{
  "type": "Feature",
  "properties": {
    "gn:admin1_code":"1.0",
    "gn:asciiname":"Zhanglaoyuancun",
    "gn:country_code":"CN",
    "gn:dem":44,
    "gn:feature_class":"P",
    "gn:feature_code":"PPL",
    "gn:name":"Zhanglaoyuancun",
    "gn:population":0,
    "gn:timezone":"Asia/Shanghai",
    "iso:country":"CN",
    "name:zho_x_preferred":[
        "\u5f20\u8001\u56ed\u6751"
    ],
    "wof:name":"Zhanglaoyuancun",
    "wof:placetype":"locality"
},
  "geometry": {"coordinates":[116.26515999999999,32.16935],"type":"Point"}
}