{
  "type": "Feature",
  "properties": {
    "gn:admin1_code":"14.0",
    "gn:asciiname":"Tungkar",
    "gn:country_code":"CN",
    "gn:dem":4291,
    "gn:feature_class":"P",
    "gn:feature_code":"PPLF",
    "gn:name":"Tungkar",
    "gn:population":0,
    "gn:timezone":"Asia/Urumqi",
    "iso:country":"CN",
    "name:bod_x_preferred":[
        "Tungkar"
    ],
    "name:und_x_variant":[
        "Dongga"
    ],
    "name:zho_x_preferred":[
        "\u6d1e\u560e"
    ],
    "wof:name":"Tungkar",
    "wof:placetype":"locality"
},
  "geometry": {"coordinates":[91.70099999999999,29.001],"type":"Point"}
}