{
  "type": "Feature",
  "properties": {
    "gn:admin1_code":"3.0",
    "gn:asciiname":"Lisongyang",
    "gn:country_code":"CN",
    "gn:dem":532,
    "gn:feature_class":"P",
    "gn:feature_code":"PPL",
    "gn:name":"Lisongyang",
    "gn:population":0,
    "gn:timezone":"Asia/Shanghai",
    "iso:country":"CN",
    "name:zho_x_preferred":[
        "\u91cc\u677e\u9633"
    ],
    "wof:name":"Lisongyang",
    "wof:placetype":"locality"
},
  "geometry": {"coordinates":[117.85548,28.80172],"type":"Point"}
}