{
  "type": "Feature",
  "properties": {
    "gn:admin1_code":"11.0",
    "gn:asciiname":"Taochongkou",
    "gn:country_code":"CN",
    "gn:dem":229,
    "gn:feature_class":"P",
    "gn:feature_code":"PPL",
    "gn:name":"Taochongkou",
    "gn:population":0,
    "gn:timezone":"Asia/Shanghai",
    "iso:country":"CN",
    "name:zho_x_preferred":[
        "\u6843\u51b2\u53e3"
    ],
    "wof:name":"Taochongkou",
    "wof:placetype":"locality"
},
  "geometry": {"coordinates":[112.91987,25.91414],"type":"Point"}
}