{
  "type": "Feature",
  "properties": {
    "gn:admin1_code":"11",
    "gn:asciiname":"Baiguoshi",
    "gn:cc2":"CN",
    "gn:country_code":"CN",
    "gn:dem":624,
    "gn:feature_class":"P",
    "gn:feature_code":"PPL",
    "gn:name":"Baiguoshi",
    "gn:population":0,
    "gn:timezone":"Asia/Shanghai",
    "iso:country":"CN",
    "name:und_x_variant":[
        "Pai-kuo-shih",
        "Baiguoshi"
    ],
    "wof:name":"Baiguoshi",
    "wof:placetype":"locality"
},
  "geometry": {"coordinates":[112.00917,26.15861],"type":"Point"}
}