{
  "type": "Feature",
  "properties": {
    "gn:admin1_code":"19.0",
    "gn:asciiname":"Mamiaocun",
    "gn:country_code":"CN",
    "gn:dem":19,
    "gn:feature_class":"P",
    "gn:feature_code":"PPL",
    "gn:name":"Mamiaocun",
    "gn:population":0,
    "gn:timezone":"Asia/Shanghai",
    "iso:country":"CN",
    "name:zho_x_preferred":[
        "\u9a6c\u5e99\u6751"
    ],
    "wof:name":"Mamiaocun",
    "wof:placetype":"locality"
},
  "geometry": {"coordinates":[122.62961,39.6524],"type":"Point"}
}