{
  "type": "Feature",
  "properties": {
    "gn:admin1_code":"25.0",
    "gn:asciiname":"Datuncun",
    "gn:country_code":"CN",
    "gn:dem":82,
    "gn:feature_class":"P",
    "gn:feature_code":"PPL",
    "gn:name":"Datuncun",
    "gn:population":0,
    "gn:timezone":"Asia/Shanghai",
    "iso:country":"CN",
    "name:zho_x_preferred":[
        "\u5927\u5c6f\u6751"
    ],
    "wof:name":"Datuncun",
    "wof:placetype":"locality"
},
  "geometry": {"coordinates":[119.63292,36.03712],"type":"Point"}
}