{
  "type": "Feature",
  "properties": {
    "gn:admin1_code":"16",
    "gn:asciiname":"Lingtian",
    "gn:cc2":"CN",
    "gn:country_code":"CN",
    "gn:dem":186,
    "gn:feature_class":"P",
    "gn:feature_code":"PPL",
    "gn:name":"Lingtian",
    "gn:population":0,
    "gn:timezone":"Asia/Shanghai",
    "iso:country":"CN",
    "name:und_x_variant":[
        "Lina-t\u2019ien-chieh",
        "Ling-t\u2019ien",
        "Ling-t\u2019ien-chieh",
        "Lingtian"
    ],
    "wof:name":"Lingtian",
    "wof:placetype":"locality"
},
  "geometry": {"coordinates":[110.47221999999999,25.33222],"type":"Point"}
}