{
  "type": "Feature",
  "properties": {
    "gn:admin1_code":"23.0",
    "gn:asciiname":"Liujiazhuang",
    "gn:country_code":"CN",
    "gn:dem":2,
    "gn:feature_class":"P",
    "gn:feature_code":"PPL",
    "gn:name":"Liujiazhuang",
    "gn:population":0,
    "gn:timezone":"Asia/Shanghai",
    "iso:country":"CN",
    "name:zho_x_preferred":[
        "Liujiazhuang"
    ],
    "name:zho_x_variant":[
        "\u67f3\u5bb6\u5e84"
    ],
    "wof:name":"Liujiazhuang",
    "wof:placetype":"locality"
},
  "geometry": {"coordinates":[121.19141999999999,31.02058],"type":"Point"}
}