{
  "type": "Feature",
  "properties": {
    "gn:admin1_code":"14",
    "gn:asciiname":"Guga",
    "gn:country_code":"CN",
    "gn:dem":4842,
    "gn:feature_class":"P",
    "gn:feature_code":"PPL",
    "gn:name":"Guga",
    "gn:population":0,
    "gn:timezone":"Asia/Urumqi",
    "iso:country":"CN",
    "name:ceb_x_preferred":[
        "Guga"
    ],
    "name:deu_x_preferred":[
        "Guga"
    ],
    "name:por_x_preferred":[
        "Guga"
    ],
    "name:swe_x_preferred":[
        "Guga"
    ],
    "name:zho_x_preferred":[
        "\u53e4\u560e"
    ],
    "wof:name":"Guga",
    "wof:placetype":"locality"
},
  "geometry": {"coordinates":[89.33410000000001,31.2102],"type":"Point"}
}