{
  "type": "Feature",
  "properties": {
    "gn:admin1_code":"14.0",
    "gn:asciiname":"Ya'ergong",
    "gn:country_code":"CN",
    "gn:dem":4653,
    "gn:feature_class":"P",
    "gn:feature_code":"PPL",
    "gn:name":"Ya\u2019ergong",
    "gn:population":0,
    "gn:timezone":"Asia/Urumqi",
    "iso:country":"CN",
    "name:und_x_variant":[
        "Ya\u2019ergong"
    ],
    "name:zho_x_preferred":[
        "\u4e9a\u5c14\u8d21"
    ],
    "wof:name":"Ya'ergong",
    "wof:placetype":"locality"
},
  "geometry": {"coordinates":[93.60236999999999,31.20545],"type":"Point"}
}