{
  "type": "Feature",
  "properties": {
    "gn:admin1_code":"19.0",
    "gn:asciiname":"Xiaoyangliutun",
    "gn:country_code":"CN",
    "gn:dem":92,
    "gn:feature_class":"P",
    "gn:feature_code":"PPL",
    "gn:name":"Xiaoyangliutun",
    "gn:population":0,
    "gn:timezone":"Asia/Shanghai",
    "iso:country":"CN",
    "name:zho_x_preferred":[
        "\u5c0f\u6768\u67f3\u5c6f"
    ],
    "wof:name":"Xiaoyangliutun",
    "wof:placetype":"locality"
},
  "geometry": {"coordinates":[121.20999999999999,41.4951],"type":"Point"}
}