{
  "type": "Feature",
  "properties": {
    "gn:admin1_code":"14.0",
    "gn:asciiname":"Bama",
    "gn:country_code":"CN",
    "gn:dem":4196,
    "gn:feature_class":"P",
    "gn:feature_code":"PPL",
    "gn:name":"Bama",
    "gn:population":0,
    "gn:timezone":"Asia/Urumqi",
    "iso:country":"CN",
    "name:zho_x_preferred":[
        "\u5df4\u9a6c"
    ],
    "wof:name":"Bama",
    "wof:placetype":"locality"
},
  "geometry": {"coordinates":[84.965,28.6529],"type":"Point"}
}