{
  "type": "Feature",
  "properties": {
    "gn:admin1_code":"14.0",
    "gn:asciiname":"Zhuqiong",
    "gn:country_code":"CN",
    "gn:dem":4949,
    "gn:feature_class":"P",
    "gn:feature_code":"PPL",
    "gn:name":"Zhuqiong",
    "gn:population":0,
    "gn:timezone":"Asia/Urumqi",
    "iso:country":"CN",
    "name:zho_x_preferred":[
        "\u716e\u7a77"
    ],
    "wof:name":"Zhuqiong",
    "wof:placetype":"locality"
},
  "geometry": {"coordinates":[89.94801,30.32392],"type":"Point"}
}