{
  "type": "Feature",
  "properties": {
    "gn:admin1_code":"11.0",
    "gn:asciiname":"Pailouqian",
    "gn:country_code":"CN",
    "gn:dem":92,
    "gn:feature_class":"P",
    "gn:feature_code":"PPL",
    "gn:name":"Pailouqian",
    "gn:population":0,
    "gn:timezone":"Asia/Shanghai",
    "iso:country":"CN",
    "name:zho_x_preferred":[
        "\u6392\u697c\u524d"
    ],
    "wof:name":"Pailouqian",
    "wof:placetype":"locality"
},
  "geometry": {"coordinates":[113.42368,27.1276],"type":"Point"}
}