{
  "type": "Feature",
  "properties": {
    "gn:admin1_code":"14.0",
    "gn:asciiname":"Xiongqiansiga",
    "gn:country_code":"CN",
    "gn:dem":5107,
    "gn:feature_class":"P",
    "gn:feature_code":"PPL",
    "gn:name":"Xiongqiansiga",
    "gn:population":0,
    "gn:timezone":"Asia/Urumqi",
    "iso:country":"CN",
    "name:zho_x_preferred":[
        "\u96c4\u5343\u53f8\u560e"
    ],
    "wof:name":"Xiongqiansiga",
    "wof:placetype":"locality"
},
  "geometry": {"coordinates":[88.2985,28.8619],"type":"Point"}
}