{
  "type": "Feature",
  "properties": {
    "gn:admin1_code":"11",
    "gn:asciiname":"Yangjiarun",
    "gn:country_code":"CN",
    "gn:dem":623,
    "gn:feature_class":"P",
    "gn:feature_code":"PPL",
    "gn:name":"Yangjiarun",
    "gn:population":0,
    "gn:timezone":"Asia/Shanghai",
    "iso:country":"CN",
    "name:und_x_variant":[
        "\u6768\u5bb6\u6da6",
        "Yangjiarun"
    ],
    "wof:name":"Yangjiarun",
    "wof:placetype":"locality"
},
  "geometry": {"coordinates":[112.1125,25.11889],"type":"Point"}
}