{
  "type": "Feature",
  "properties": {
    "gn:admin1_code":"29.0",
    "gn:asciiname":"Nuomu",
    "gn:country_code":"CN",
    "gn:dem":1911,
    "gn:feature_class":"P",
    "gn:feature_code":"PPL",
    "gn:name":"Nuomu",
    "gn:population":0,
    "gn:timezone":"Asia/Shanghai",
    "iso:country":"CN",
    "name:zho_x_preferred":[
        "\u7cef\u6728"
    ],
    "wof:name":"Nuomu",
    "wof:placetype":"locality"
},
  "geometry": {"coordinates":[104.238,25.381],"type":"Point"}
}