{
  "type": "Feature",
  "properties": {
    "gn:admin1_code":"32.0",
    "gn:asciiname":"Kagong",
    "gn:country_code":"CN",
    "gn:dem":3810,
    "gn:feature_class":"P",
    "gn:feature_code":"PPL",
    "gn:name":"Kagong",
    "gn:population":0,
    "gn:timezone":"Asia/Shanghai",
    "iso:country":"CN",
    "name:zho_x_preferred":[
        "\u5361\u8d21"
    ],
    "wof:name":"Kagong",
    "wof:placetype":"locality"
},
  "geometry": {"coordinates":[98.08593,32.43971],"type":"Point"}
}