{
  "type": "Feature",
  "properties": {
    "gn:admin1_code":"15.0",
    "gn:asciiname":"Xiwan",
    "gn:country_code":"CN",
    "gn:dem":2400,
    "gn:feature_class":"P",
    "gn:feature_code":"PPL",
    "gn:name":"Xiwan",
    "gn:population":0,
    "gn:timezone":"Asia/Shanghai",
    "iso:country":"CN",
    "name:zho_x_preferred":[
        "\u897f\u6e7e"
    ],
    "wof:name":"Xiwan",
    "wof:placetype":"locality"
},
  "geometry": {"coordinates":[101.569,38.1897],"type":"Point"}
}