{
  "type": "Feature",
  "properties": {
    "gn:admin1_code":"11",
    "gn:asciiname":"Jiangjia",
    "gn:country_code":"CN",
    "gn:dem":202,
    "gn:feature_class":"P",
    "gn:feature_code":"PPL",
    "gn:name":"Jiangjia",
    "gn:population":0,
    "gn:timezone":"Asia/Shanghai",
    "iso:country":"CN",
    "name:und_x_variant":[
        "\u848b\u5bb6",
        "Jiangjia"
    ],
    "wof:name":"Jiangjia",
    "wof:placetype":"locality"
},
  "geometry": {"coordinates":[111.89139,25.58028],"type":"Point"}
}