{
  "type": "Feature",
  "properties": {
    "gn:admin1_code":"29.0",
    "gn:asciiname":"Zhongyuanzhu",
    "gn:country_code":"CN",
    "gn:dem":1479,
    "gn:feature_class":"P",
    "gn:feature_code":"PPL",
    "gn:name":"Zhongyuanzhu",
    "gn:population":0,
    "gn:timezone":"Asia/Shanghai",
    "iso:country":"CN",
    "name:zho_x_preferred":[
        "\u4e2d\u6e90\u73e0"
    ],
    "wof:name":"Zhongyuanzhu",
    "wof:placetype":"locality"
},
  "geometry": {"coordinates":[99.12479999999999,24.871],"type":"Point"}
}