{
  "type": "Feature",
  "properties": {
    "gn:admin1_code":"4.0",
    "gn:asciiname":"Yiyuanxin",
    "gn:country_code":"CN",
    "gn:dem":7,
    "gn:feature_class":"P",
    "gn:feature_code":"PPL",
    "gn:name":"Yiyuanxin",
    "gn:population":0,
    "gn:timezone":"Asia/Shanghai",
    "iso:country":"CN",
    "name:zho_x_preferred":[
        "\u6021\u56ed\u65b0"
    ],
    "wof:name":"Yiyuanxin",
    "wof:placetype":"locality"
},
  "geometry": {"coordinates":[120.84678,32.04711],"type":"Point"}
}