{
  "type": "Feature",
  "properties": {
    "gn:admin1_code":"14.0",
    "gn:asciiname":"Nanjia",
    "gn:country_code":"CN",
    "gn:dem":3995,
    "gn:feature_class":"P",
    "gn:feature_code":"PPL",
    "gn:name":"Nanjia",
    "gn:population":0,
    "gn:timezone":"Asia/Urumqi",
    "iso:country":"CN",
    "name:zho_x_preferred":[
        "\u96be\u52a0"
    ],
    "wof:name":"Nanjia",
    "wof:placetype":"locality"
},
  "geometry": {"coordinates":[96.41033,30.50957],"type":"Point"}
}