{
  "type": "Feature",
  "properties": {
    "gn:admin1_code":"12.0",
    "gn:asciiname":"Yuanjia Huawu",
    "gn:country_code":"CN",
    "gn:dem":886,
    "gn:feature_class":"P",
    "gn:feature_code":"PPL",
    "gn:name":"Yuanjia Huawu",
    "gn:population":0,
    "gn:timezone":"Asia/Shanghai",
    "iso:country":"CN",
    "name:zho_x_preferred":[
        "\u8881\u5bb6\u82b1\u5c4b"
    ],
    "wof:name":"Yuanjia Huawu",
    "wof:placetype":"locality"
},
  "geometry": {"coordinates":[109.88014,31.88496],"type":"Point"}
}