{
  "type": "Feature",
  "properties": {
    "gn:admin1_code":"14.0",
    "gn:asciiname":"Shangyarucun",
    "gn:country_code":"CN",
    "gn:dem":4459,
    "gn:feature_class":"P",
    "gn:feature_code":"PPL",
    "gn:name":"Shangyarucun",
    "gn:population":0,
    "gn:timezone":"Asia/Urumqi",
    "iso:country":"CN",
    "name:zho_x_preferred":[
        "\u4e0a\u4e9a\u5982\u6751"
    ],
    "wof:name":"Shangyarucun",
    "wof:placetype":"locality"
},
  "geometry": {"coordinates":[90.71339,28.78342],"type":"Point"}
}