{
  "type": "Feature",
  "properties": {
    "gn:admin1_code":"32.0",
    "gn:asciiname":"Zhuanlongshan",
    "gn:country_code":"CN",
    "gn:dem":1221,
    "gn:feature_class":"P",
    "gn:feature_code":"PPL",
    "gn:name":"Zhuanlongshan",
    "gn:population":0,
    "gn:timezone":"Asia/Shanghai",
    "iso:country":"CN",
    "name:zho_x_preferred":[
        "\u8f6c\u9f99\u5c71"
    ],
    "wof:name":"Zhuanlongshan",
    "wof:placetype":"locality"
},
  "geometry": {"coordinates":[106.30931,28.54253],"type":"Point"}
}