{
  "type": "Feature",
  "properties": {
    "gn:admin1_code":"7.0",
    "gn:asciiname":"Yuankengzi",
    "gn:country_code":"CN",
    "gn:dem":599,
    "gn:feature_class":"P",
    "gn:feature_code":"PPL",
    "gn:name":"Yuankengzi",
    "gn:population":0,
    "gn:timezone":"Asia/Shanghai",
    "iso:country":"CN",
    "name:zho_x_preferred":[
        "\u5143\u5751\u5b50"
    ],
    "wof:name":"Yuankengzi",
    "wof:placetype":"locality"
},
  "geometry": {"coordinates":[116.50743,25.46707],"type":"Point"}
}