{
  "type": "Feature",
  "properties": {
    "gn:admin1_code":"25",
    "gn:asciiname":"Chao Xicun",
    "gn:country_code":"CN",
    "gn:dem":56,
    "gn:feature_class":"P",
    "gn:feature_code":"PPL",
    "gn:name":"Chao Xicun",
    "gn:population":0,
    "gn:timezone":"Asia/Shanghai",
    "iso:country":"CN",
    "name:zho_x_preferred":[
        "\u671d\u897f\u6751"
    ],
    "wof:name":"Chao Xicun",
    "wof:placetype":"locality"
},
  "geometry": {"coordinates":[116.791,35.1682],"type":"Point"}
}