{
  "type": "Feature",
  "properties": {
    "gn:admin1_code":"19.0",
    "gn:asciiname":"Pangtun",
    "gn:country_code":"CN",
    "gn:dem":23,
    "gn:feature_class":"P",
    "gn:feature_code":"PPL",
    "gn:name":"Pangtun",
    "gn:population":0,
    "gn:timezone":"Asia/Shanghai",
    "iso:country":"CN",
    "name:zho_x_preferred":[
        "\u5e9e\u5c6f"
    ],
    "wof:name":"Pangtun",
    "wof:placetype":"locality"
},
  "geometry": {"coordinates":[121.81802,41.46936],"type":"Point"}
}