{
  "type": "Feature",
  "properties": {
    "gn:admin1_code":"30",
    "gn:asciiname":"Luoyangxu",
    "gn:country_code":"CN",
    "gn:dem":192,
    "gn:feature_class":"P",
    "gn:feature_code":"PPL",
    "gn:name":"Luoyangxu",
    "gn:population":0,
    "gn:timezone":"Asia/Shanghai",
    "iso:country":"CN",
    "name:zho_x_preferred":[
        "\u7f57\u9633\u5729"
    ],
    "wof:name":"Luoyangxu",
    "wof:placetype":"locality"
},
  "geometry": {"coordinates":[111.77631,22.60636],"type":"Point"}
}