{
  "type": "Feature",
  "properties": {
    "gn:admin1_code":"4.0",
    "gn:asciiname":"Wujiaqiao",
    "gn:country_code":"CN",
    "gn:dem":3,
    "gn:feature_class":"P",
    "gn:feature_code":"PPL",
    "gn:name":"Wujiaqiao",
    "gn:population":0,
    "gn:timezone":"Asia/Shanghai",
    "iso:country":"CN",
    "name:und_x_variant":[
        "\u5434\u5bb6\u6865"
    ],
    "wof:name":"Wujiaqiao",
    "wof:placetype":"locality"
},
  "geometry": {"coordinates":[121.29588,32.02762],"type":"Point"}
}