{
  "type": "Feature",
  "properties": {
    "gn:admin1_code":"11",
    "gn:asciiname":"Shentian",
    "gn:country_code":"CN",
    "gn:dem":311,
    "gn:feature_class":"P",
    "gn:feature_code":"PPL",
    "gn:name":"Shentian",
    "gn:population":0,
    "gn:timezone":"Asia/Shanghai",
    "iso:country":"CN",
    "name:zho_x_preferred":[
        "\u6df1\u7530"
    ],
    "wof:name":"Shentian",
    "wof:placetype":"locality"
},
  "geometry": {"coordinates":[111.39536,25.59147],"type":"Point"}
}