{
  "type": "Feature",
  "properties": {
    "gn:admin1_code":"5.0",
    "gn:asciiname":"Xilama Yingzi",
    "gn:country_code":"CN",
    "gn:dem":175,
    "gn:feature_class":"P",
    "gn:feature_code":"PPL",
    "gn:name":"Xilama Yingzi",
    "gn:population":0,
    "gn:timezone":"Asia/Shanghai",
    "iso:country":"CN",
    "name:zho_x_preferred":[
        "\u897f\u5587\u561b\u8425\u5b50"
    ],
    "wof:name":"Xilama Yingzi",
    "wof:placetype":"locality"
},
  "geometry": {"coordinates":[125.6859,44.81037],"type":"Point"}
}