{
  "type": "Feature",
  "properties": {
    "gn:admin1_code":"05",
    "gn:asciiname":"Ying-tsui-la-t'un",
    "gn:country_code":"CN",
    "gn:dem":314,
    "gn:feature_class":"P",
    "gn:feature_code":"PPL",
    "gn:name":"Ying-tsui-la-t\u2019un",
    "gn:population":0,
    "gn:timezone":"Asia/Shanghai",
    "iso:country":"CN",
    "wof:name":"Ying-tsui-la-t'un",
    "wof:placetype":"locality"
},
  "geometry": {"coordinates":[126.24139,42.95583],"type":"Point"}
}