{
  "type": "Feature",
  "properties": {
    "gn:admin1_code":"24.0",
    "gn:asciiname":"Dayatang",
    "gn:country_code":"CN",
    "gn:dem":1648,
    "gn:feature_class":"P",
    "gn:feature_code":"PPL",
    "gn:name":"Dayatang",
    "gn:population":0,
    "gn:timezone":"Asia/Shanghai",
    "iso:country":"CN",
    "name:zho_x_preferred":[
        "\u5927\u5d16\u5802"
    ],
    "wof:name":"Dayatang",
    "wof:placetype":"locality"
},
  "geometry": {"coordinates":[113.48505,38.63011],"type":"Point"}
}