{
  "type": "Feature",
  "properties": {
    "gn:admin1_code":"16",
    "gn:asciiname":"Baofeng",
    "gn:country_code":"CN",
    "gn:dem":247,
    "gn:feature_class":"P",
    "gn:feature_code":"PPL",
    "gn:name":"Baofeng",
    "gn:population":0,
    "gn:timezone":"Asia/Shanghai",
    "iso:country":"CN",
    "name:zho_x_preferred":[
        "\u5b9d\u4e30"
    ],
    "wof:name":"Baofeng",
    "wof:placetype":"locality"
},
  "geometry": {"coordinates":[110.76900000000001,25.6724],"type":"Point"}
}