{
  "type": "Feature",
  "properties": {
    "gn:admin1_code":"08",
    "gn:asciiname":"Huoshishan",
    "gn:country_code":"CN",
    "gn:dem":180,
    "gn:feature_class":"P",
    "gn:feature_code":"PPLA4",
    "gn:name":"Huoshishan",
    "gn:population":0,
    "gn:timezone":"Asia/Shanghai",
    "iso:country":"CN",
    "name:und_x_variant":[
        "Huo-shih-shan",
        "Huoshishan",
        "Huoshishan Xiang"
    ],
    "name:zho_x_preferred":[
        "\u706b\u77f3\u5c71"
    ],
    "name:zho_x_variant":[
        "\u706b\u77f3\u5c71\u4e61"
    ],
    "wof:name":"Huoshishan",
    "wof:placetype":"locality"
},
  "geometry": {"coordinates":[125.67474,46.50028],"type":"Point"}
}