{
  "type": "Feature",
  "properties": {
    "gn:admin1_code":"25",
    "gn:asciiname":"Zhantuan",
    "gn:country_code":"CN",
    "gn:dem":174,
    "gn:feature_class":"P",
    "gn:feature_code":"PPL",
    "gn:name":"Zhantuan",
    "gn:population":0,
    "gn:timezone":"Asia/Shanghai",
    "iso:country":"CN",
    "name:zho_x_preferred":[
        "\u5360\u7583"
    ],
    "wof:name":"Zhantuan",
    "wof:placetype":"locality"
},
  "geometry": {"coordinates":[120.96599999999999,37.3107],"type":"Point"}
}