{
  "type": "Feature",
  "properties": {
    "gn:admin1_code":"29.0",
    "gn:asciiname":"Dahuangcaoba",
    "gn:country_code":"CN",
    "gn:dem":1637,
    "gn:feature_class":"P",
    "gn:feature_code":"PPL",
    "gn:name":"Dahuangcaoba",
    "gn:population":0,
    "gn:timezone":"Asia/Shanghai",
    "iso:country":"CN",
    "name:zho_x_preferred":[
        "\u5927\u9ec4\u8349\u575d"
    ],
    "wof:name":"Dahuangcaoba",
    "wof:placetype":"locality"
},
  "geometry": {"coordinates":[99.9623,24.297],"type":"Point"}
}