{
  "type": "Feature",
  "properties": {
    "gn:admin1_code":"15.0",
    "gn:asciiname":"Xiayujiaya",
    "gn:country_code":"CN",
    "gn:dem":2395,
    "gn:feature_class":"P",
    "gn:feature_code":"PPL",
    "gn:name":"Xiayujiaya",
    "gn:population":0,
    "gn:timezone":"Asia/Shanghai",
    "iso:country":"CN",
    "name:zho_x_preferred":[
        "\u4e0b\u4f59\u5bb6\u5d16"
    ],
    "wof:name":"Xiayujiaya",
    "wof:placetype":"locality"
},
  "geometry": {"coordinates":[104.461,35.3808],"type":"Point"}
}