{
  "type": "Feature",
  "properties": {
    "gn:admin1_code":"32.0",
    "gn:asciiname":"Gaozumiao",
    "gn:country_code":"CN",
    "gn:dem":506,
    "gn:feature_class":"P",
    "gn:feature_code":"PPL",
    "gn:name":"Gaozumiao",
    "gn:population":0,
    "gn:timezone":"Asia/Shanghai",
    "iso:country":"CN",
    "name:zho_x_preferred":[
        "\u9ad8\u7956\u5e99"
    ],
    "wof:name":"Gaozumiao",
    "wof:placetype":"locality"
},
  "geometry": {"coordinates":[104.11775,30.89014],"type":"Point"}
}