{
  "type": "Feature",
  "properties": {
    "gn:admin1_code":"9",
    "gn:asciiname":"Yangjiazhuang",
    "gn:country_code":"CN",
    "gn:dem":902,
    "gn:feature_class":"P",
    "gn:feature_code":"PPL",
    "gn:name":"Yangjiazhuang",
    "gn:population":0,
    "gn:timezone":"Asia/Shanghai",
    "iso:country":"CN",
    "name:und_x_variant":[
        "\u6768\u5bb6\u5e84",
        "Yangjiacun",
        "Yangjiazhuang"
    ],
    "wof:name":"Yangjiazhuang",
    "wof:placetype":"locality"
},
  "geometry": {"coordinates":[112.26536000000002,33.83349],"type":"Point"}
}