{
  "type": "Feature",
  "properties": {
    "gn:admin1_code":"19.0",
    "gn:asciiname":"Pozidian",
    "gn:country_code":"CN",
    "gn:dem":128,
    "gn:feature_class":"P",
    "gn:feature_code":"PPL",
    "gn:name":"Pozidian",
    "gn:population":0,
    "gn:timezone":"Asia/Shanghai",
    "iso:country":"CN",
    "name:und_x_variant":[
        "\u5761\u5b50\u5e97"
    ],
    "name:zho_x_preferred":[
        "\u5761\u5b50\u5e97"
    ],
    "wof:name":"Pozidian",
    "wof:placetype":"locality"
},
  "geometry": {"coordinates":[122.238,39.63],"type":"Point"}
}