{
  "type": "Feature",
  "properties": {
    "gn:admin1_code":"23.0",
    "gn:asciiname":"Chulou",
    "gn:country_code":"CN",
    "gn:dem":6,
    "gn:feature_class":"P",
    "gn:feature_code":"PPL",
    "gn:name":"Chulou",
    "gn:population":0,
    "gn:timezone":"Asia/Shanghai",
    "iso:country":"CN",
    "name:zho_x_preferred":[
        "Chulou"
    ],
    "name:zho_x_variant":[
        "\u50a8\u697c"
    ],
    "wof:name":"Chulou",
    "wof:placetype":"locality"
},
  "geometry": {"coordinates":[121.61391999999999,31.07104],"type":"Point"}
}