{
  "type": "Feature",
  "properties": {
    "gn:admin1_code":"19.0",
    "gn:asciiname":"Zhi'ancun",
    "gn:country_code":"CN",
    "gn:dem":338,
    "gn:feature_class":"P",
    "gn:feature_code":"PPL",
    "gn:name":"Zhi\u2019ancun",
    "gn:population":0,
    "gn:timezone":"Asia/Shanghai",
    "iso:country":"CN",
    "name:zho_x_preferred":[
        "\u6cbb\u5b89\u6751"
    ],
    "name:zho_x_variant":[
        "Zhi\u2019ancun"
    ],
    "wof:name":"Zhi'ancun",
    "wof:placetype":"locality"
},
  "geometry": {"coordinates":[125.113,42.379],"type":"Point"}
}