{
  "type": "Feature",
  "properties": {
    "gn:admin1_code":"30.0",
    "gn:asciiname":"Huangnuocun",
    "gn:country_code":"CN",
    "gn:dem":46,
    "gn:feature_class":"P",
    "gn:feature_code":"PPL",
    "gn:name":"Huangnuocun",
    "gn:population":0,
    "gn:timezone":"Asia/Shanghai",
    "iso:country":"CN",
    "name:zho_x_preferred":[
        "\u9ec4\u7cef\u6751"
    ],
    "wof:name":"Huangnuocun",
    "wof:placetype":"locality"
},
  "geometry": {"coordinates":[111.53628999999999,22.78253],"type":"Point"}
}