{
  "type": "Feature",
  "properties": {
    "gn:admin1_code":"15.0",
    "gn:asciiname":"Jinjiachuan",
    "gn:country_code":"CN",
    "gn:dem":1425,
    "gn:feature_class":"P",
    "gn:feature_code":"PPL",
    "gn:name":"Jinjiachuan",
    "gn:population":0,
    "gn:timezone":"Asia/Shanghai",
    "iso:country":"CN",
    "name:zho_x_preferred":[
        "\u91d1\u5bb6\u5ddd"
    ],
    "wof:name":"Jinjiachuan",
    "wof:placetype":"locality"
},
  "geometry": {"coordinates":[107.518,35.933],"type":"Point"}
}