{
  "type": "Feature",
  "properties": {
    "gn:admin1_code":"26.0",
    "gn:asciiname":"Youfangya",
    "gn:country_code":"CN",
    "gn:dem":1408,
    "gn:feature_class":"P",
    "gn:feature_code":"PPL",
    "gn:name":"Youfangya",
    "gn:population":0,
    "gn:timezone":"Asia/Shanghai",
    "iso:country":"CN",
    "name:zho_x_preferred":[
        "\u6cb9\u623f\u57ad"
    ],
    "wof:name":"Youfangya",
    "wof:placetype":"locality"
},
  "geometry": {"coordinates":[108.96077,32.36502],"type":"Point"}
}