{
  "type": "Feature",
  "properties": {
    "gn:admin1_code":"29.0",
    "gn:asciiname":"Nasi",
    "gn:country_code":"CN",
    "gn:dem":1491,
    "gn:feature_class":"P",
    "gn:feature_code":"PPL",
    "gn:name":"Nasi",
    "gn:population":0,
    "gn:timezone":"Asia/Shanghai",
    "iso:country":"CN",
    "name:zho_x_preferred":[
        "\u7eb3\u601d"
    ],
    "wof:name":"Nasi",
    "wof:placetype":"locality"
},
  "geometry": {"coordinates":[104.29600000000001,24.026],"type":"Point"}
}