{
  "type": "Feature",
  "properties": {
    "gn:admin1_code":"29.0",
    "gn:asciiname":"Nasi",
    "gn:country_code":"CN",
    "gn:dem":1491,
    "gn:feature_class":"P",
    "gn:feature_code":"PPL",
    "gn:name":"Nasi",
    "gn:population":0,
    "gn:timezone":"Asia/Shanghai",
    "iso:country":"CN",
    "name:ceb_x_preferred":[
        "Nasi"
    ],
    "name:deu_x_preferred":[
        "Nasi"
    ],
    "name:fra_x_preferred":[
        "Nasi"
    ],
    "name:ita_x_preferred":[
        "Nasi"
    ],
    "name:lat_x_preferred":[
        "Nasi"
    ],
    "name:nld_x_preferred":[
        "Nasi"
    ],
    "name:rus_x_preferred":[
        "\u041d\u0430\u0441\u0438"
    ],
    "name:spa_x_preferred":[
        "Nasi"
    ],
    "name:swe_x_preferred":[
        "Nasi"
    ],
    "name:zho_x_preferred":[
        "\u7eb3\u601d"
    ],
    "wof:name":"Nasi",
    "wof:placetype":"locality"
},
  "geometry": {"coordinates":[104.29600000000001,24.026],"type":"Point"}
}