{
  "type": "Feature",
  "properties": {
    "gn:admin1_code":"6.0",
    "gn:asciiname":"Longrongrong",
    "gn:country_code":"CN",
    "gn:dem":4026,
    "gn:feature_class":"P",
    "gn:feature_code":"PPL",
    "gn:name":"Longrongrong",
    "gn:population":0,
    "gn:timezone":"Asia/Urumqi",
    "iso:country":"CN",
    "name:zho_x_preferred":[
        "\u9647\u5bb9\u7ed2"
    ],
    "wof:name":"Longrongrong",
    "wof:placetype":"locality"
},
  "geometry": {"coordinates":[96.20263,33.72883],"type":"Point"}
}