{
  "type": "Feature",
  "properties": {
    "gn:admin1_code":"16.0",
    "gn:asciiname":"Naguopu",
    "gn:country_code":"CN",
    "gn:dem":703,
    "gn:feature_class":"P",
    "gn:feature_code":"PPL",
    "gn:name":"Naguopu",
    "gn:population":0,
    "gn:timezone":"Asia/Shanghai",
    "iso:country":"CN",
    "name:zho_x_preferred":[
        "\u90a3\u679c\u6251"
    ],
    "wof:name":"Naguopu",
    "wof:placetype":"locality"
},
  "geometry": {"coordinates":[106.914,24.2858],"type":"Point"}
}