{
  "type": "Feature",
  "properties": {
    "gn:admin1_code":"19.0",
    "gn:asciiname":"Yaojiacun",
    "gn:country_code":"CN",
    "gn:dem":669,
    "gn:feature_class":"P",
    "gn:feature_code":"PPL",
    "gn:name":"Yaojiacun",
    "gn:population":0,
    "gn:timezone":"Asia/Shanghai",
    "iso:country":"CN",
    "name:und_x_variant":[
        "Yaojia Wopu"
    ],
    "name:zho_x_preferred":[
        "\u59da\u5bb6\u6751"
    ],
    "name:zho_x_variant":[
        "\u59da\u5bb6\u7a9d\u94fa"
    ],
    "wof:name":"Yaojiacun",
    "wof:placetype":"locality"
},
  "geometry": {"coordinates":[119.59099999999999,41.8315],"type":"Point"}
}