{
  "type": "Feature",
  "properties": {
    "gn:admin1_code":"25.0",
    "gn:asciiname":"Wangnou",
    "gn:country_code":"CN",
    "gn:dem":13,
    "gn:feature_class":"P",
    "gn:feature_code":"PPL",
    "gn:name":"Wangnou",
    "gn:population":0,
    "gn:timezone":"Asia/Shanghai",
    "iso:country":"CN",
    "name:zho_x_preferred":[
        "\u738b\u8028"
    ],
    "wof:name":"Wangnou",
    "wof:placetype":"locality"
},
  "geometry": {"coordinates":[119.33262000000001,36.80198],"type":"Point"}
}