{
  "type": "Feature",
  "properties": {
    "gn:admin1_code":"2",
    "gn:asciiname":"Zhuyang",
    "gn:country_code":"CN",
    "gn:dem":754,
    "gn:feature_class":"P",
    "gn:feature_code":"PPL",
    "gn:name":"Zhuyang",
    "gn:population":0,
    "gn:timezone":"Asia/Shanghai",
    "iso:country":"CN",
    "name:zho_x_preferred":[
        "\u7af9\u579f"
    ],
    "wof:name":"Zhuyang",
    "wof:placetype":"locality"
},
  "geometry": {"coordinates":[118.77500000000001,27.99056],"type":"Point"}
}