{
  "type": "Feature",
  "properties": {
    "gn:admin1_code":"32.0",
    "gn:asciiname":"Gunbagong",
    "gn:country_code":"CN",
    "gn:dem":3557,
    "gn:feature_class":"P",
    "gn:feature_code":"PPL",
    "gn:name":"Gunbagong",
    "gn:population":0,
    "gn:timezone":"Asia/Shanghai",
    "iso:country":"CN",
    "name:zho_x_preferred":[
        "\u68cd\u5df4\u5171"
    ],
    "wof:name":"Gunbagong",
    "wof:placetype":"locality"
},
  "geometry": {"coordinates":[99.18219999999999,30.0693],"type":"Point"}
}