{
  "type": "Feature",
  "properties": {
    "gn:admin1_code":"29.0",
    "gn:asciiname":"Juejuping",
    "gn:country_code":"CN",
    "gn:dem":2621,
    "gn:feature_class":"P",
    "gn:feature_code":"PPL",
    "gn:name":"Juejuping",
    "gn:population":0,
    "gn:timezone":"Asia/Shanghai",
    "iso:country":"CN",
    "name:zho_x_preferred":[
        "\u8568\u5c45\u576a"
    ],
    "wof:name":"Juejuping",
    "wof:placetype":"locality"
},
  "geometry": {"coordinates":[99.8143,27.096],"type":"Point"}
}