{
  "type": "Feature",
  "properties": {
    "gn:admin1_code":"4.0",
    "gn:asciiname":"Xiyicun",
    "gn:country_code":"CN",
    "gn:dem":6,
    "gn:feature_class":"P",
    "gn:feature_code":"PPL",
    "gn:name":"Xiyicun",
    "gn:population":0,
    "gn:timezone":"Asia/Shanghai",
    "iso:country":"CN",
    "name:und_x_variant":[
        "Xibiancheng"
    ],
    "name:zho_x_preferred":[
        "\u897f\u4e00\u6751"
    ],
    "name:zho_x_variant":[
        "\u897f\u8fb9\u57ce"
    ],
    "wof:name":"Xiyicun",
    "wof:placetype":"locality"
},
  "geometry": {"coordinates":[119.98387,32.67827],"type":"Point"}
}