{
  "type": "Feature",
  "properties": {
    "gn:admin1_code":"26.0",
    "gn:asciiname":"Yanggui",
    "gn:country_code":"CN",
    "gn:dem":1247,
    "gn:feature_class":"P",
    "gn:feature_code":"PPL",
    "gn:name":"Yanggui",
    "gn:population":0,
    "gn:timezone":"Asia/Shanghai",
    "iso:country":"CN",
    "name:zho_x_preferred":[
        "\u6768\u8d35"
    ],
    "wof:name":"Yanggui",
    "wof:placetype":"locality"
},
  "geometry": {"coordinates":[110.28471999999999,39.37433],"type":"Point"}
}