{
  "type": "Feature",
  "properties": {
    "gn:admin1_code":"1.0",
    "gn:asciiname":"Zhuohucun",
    "gn:country_code":"CN",
    "gn:dem":17,
    "gn:feature_class":"P",
    "gn:feature_code":"PPL",
    "gn:name":"Zhuohucun",
    "gn:population":0,
    "gn:timezone":"Asia/Shanghai",
    "iso:country":"CN",
    "name:zho_x_preferred":[
        "\u5353\u6e56\u6751"
    ],
    "wof:name":"Zhuohucun",
    "wof:placetype":"locality"
},
  "geometry": {"coordinates":[116.67594,30.52426],"type":"Point"}
}