{
  "type": "Feature",
  "properties": {
    "gn:admin1_code":"29",
    "gn:asciiname":"Xiaojianghe",
    "gn:country_code":"CN",
    "gn:dem":1936,
    "gn:feature_class":"P",
    "gn:feature_code":"PPL",
    "gn:name":"Xiaojianghe",
    "gn:population":0,
    "gn:timezone":"Asia/Shanghai",
    "iso:country":"CN",
    "name:zho_x_preferred":[
        "\u5c0f\u6c5f\u6cb3"
    ],
    "wof:name":"Xiaojianghe",
    "wof:placetype":"locality"
},
  "geometry": {"coordinates":[102.38303000000001,24.05505],"type":"Point"}
}