{
  "type": "Feature",
  "properties": {
    "gn:admin1_code":"8.0",
    "gn:asciiname":"Hongqi Erduidi Wopeng",
    "gn:country_code":"CN",
    "gn:dem":77,
    "gn:feature_class":"P",
    "gn:feature_code":"PPLF",
    "gn:name":"Hongqi Erduidi Wopeng",
    "gn:population":0,
    "gn:timezone":"Asia/Shanghai",
    "iso:country":"CN",
    "name:zho_x_preferred":[
        "\u7ea2\u65d7\u4e8c\u961f\u5730\u7a9d\u68da"
    ],
    "wof:name":"Hongqi Erduidi Wopeng",
    "wof:placetype":"locality"
},
  "geometry": {"coordinates":[130.61641,46.83698],"type":"Point"}
}