{
  "type": "Feature",
  "properties": {
    "gn:admin1_code":"18.0",
    "gn:asciiname":"Jiatang",
    "gn:country_code":"CN",
    "gn:dem":926,
    "gn:feature_class":"P",
    "gn:feature_code":"PPL",
    "gn:name":"Jiatang",
    "gn:population":0,
    "gn:timezone":"Asia/Shanghai",
    "iso:country":"CN",
    "name:zho_x_preferred":[
        "\u7532\u5858"
    ],
    "wof:name":"Jiatang",
    "wof:placetype":"locality"
},
  "geometry": {"coordinates":[107.48699999999999,25.5096],"type":"Point"}
}