{
  "type": "Feature",
  "properties": {
    "gn:admin1_code":"32.0",
    "gn:asciiname":"Xieli",
    "gn:country_code":"CN",
    "gn:dem":325,
    "gn:feature_class":"P",
    "gn:feature_code":"PPL",
    "gn:name":"Xieli",
    "gn:population":0,
    "gn:timezone":"Asia/Shanghai",
    "iso:country":"CN",
    "name:zho_x_preferred":[
        "\u534f\u529b"
    ],
    "wof:name":"Xieli",
    "wof:placetype":"locality"
},
  "geometry": {"coordinates":[105.00700000000001,29.5784],"type":"Point"}
}