{
  "type": "Feature",
  "properties": {
    "gn:admin1_code":"12.0",
    "gn:asciiname":"Maozhangwu",
    "gn:country_code":"CN",
    "gn:dem":53,
    "gn:feature_class":"P",
    "gn:feature_code":"PPL",
    "gn:name":"Maozhangwu",
    "gn:population":0,
    "gn:timezone":"Asia/Shanghai",
    "iso:country":"CN",
    "name:zho_x_preferred":[
        "\u6bdb\u5f20\u575e"
    ],
    "wof:name":"Maozhangwu",
    "wof:placetype":"locality"
},
  "geometry": {"coordinates":[114.60236999999999,31.04582000000001],"type":"Point"}
}