{
  "type": "Feature",
  "properties": {
    "gn:admin1_code":"11.0",
    "gn:asciiname":"Jiayan",
    "gn:country_code":"CN",
    "gn:dem":439,
    "gn:feature_class":"P",
    "gn:feature_code":"PPL",
    "gn:name":"Jiayan",
    "gn:population":0,
    "gn:timezone":"Asia/Shanghai",
    "iso:country":"CN",
    "name:zho_x_preferred":[
        "\u5939\u5ca9"
    ],
    "wof:name":"Jiayan",
    "wof:placetype":"locality"
},
  "geometry": {"coordinates":[110.15260000000001,28.56533],"type":"Point"}
}