{
  "type": "Feature",
  "properties": {
    "gn:admin1_code":"25",
    "gn:asciiname":"Guanfangjie",
    "gn:country_code":"CN",
    "gn:dem":102,
    "gn:feature_class":"P",
    "gn:feature_code":"PPL",
    "gn:name":"Guanfangjie",
    "gn:population":0,
    "gn:timezone":"Asia/Shanghai",
    "iso:country":"CN",
    "name:zho_x_preferred":[
        "\u5b98\u574a\u8857"
    ],
    "wof:name":"Guanfangjie",
    "wof:placetype":"locality"
},
  "geometry": {"coordinates":[118.74299999999999,35.1371],"type":"Point"}
}