{
  "type": "Feature",
  "properties": {
    "gn:admin1_code":"30.0",
    "gn:asciiname":"Yaogu",
    "gn:country_code":"CN",
    "gn:dem":28,
    "gn:feature_class":"P",
    "gn:feature_code":"PPLA4",
    "gn:name":"Yaogu",
    "gn:population":0,
    "gn:timezone":"Asia/Shanghai",
    "iso:country":"CN",
    "name:und_x_variant":[
        "Yiuku",
        "Yao-ku",
        "Yao-ku-hs\u00fc",
        "Yaogu",
        "Yaogu Zhen",
        "\u8170\u53e4\u9547"
    ],
    "name:zho_x_preferred":[
        "\u8170\u53e4"
    ],
    "wof:name":"Yaogu",
    "wof:placetype":"locality"
},
  "geometry": {"coordinates":[112.28191,22.89258],"type":"Point"}
}