{
  "type": "Feature",
  "properties": {
    "gn:admin1_code":"32.0",
    "gn:asciiname":"Wangjia Puzi",
    "gn:country_code":"CN",
    "gn:dem":2354,
    "gn:feature_class":"P",
    "gn:feature_code":"PPL",
    "gn:name":"Wangjia Puzi",
    "gn:population":0,
    "gn:timezone":"Asia/Shanghai",
    "iso:country":"CN",
    "name:zho_x_preferred":[
        "\u738b\u5bb6\u94fa\u5b50"
    ],
    "wof:name":"Wangjia Puzi",
    "wof:placetype":"locality"
},
  "geometry": {"coordinates":[102.23999999999999,27.6134],"type":"Point"}
}