{
  "type": "Feature",
  "properties": {
    "gn:admin1_code":"4.0",
    "gn:asciiname":"Yanjiazhuang",
    "gn:country_code":"CN",
    "gn:dem":1,
    "gn:feature_class":"P",
    "gn:feature_code":"PPL",
    "gn:name":"Yanjiazhuang",
    "gn:population":0,
    "gn:timezone":"Asia/Shanghai",
    "iso:country":"CN",
    "name:zho_x_preferred":[
        "Yanjiazhuang"
    ],
    "name:zho_x_variant":[
        "\u4e25\u5bb6\u5e84"
    ],
    "wof:name":"Yanjiazhuang",
    "wof:placetype":"locality"
},
  "geometry": {"coordinates":[119.95199,33.44839],"type":"Point"}
}