{
  "type": "Feature",
  "properties": {
    "gn:admin1_code":"15.0",
    "gn:asciiname":"Jijitan",
    "gn:country_code":"CN",
    "gn:dem":2831,
    "gn:feature_class":"P",
    "gn:feature_code":"PPL",
    "gn:name":"Jijitan",
    "gn:population":0,
    "gn:timezone":"Asia/Shanghai",
    "iso:country":"CN",
    "name:zho_x_preferred":[
        "\u82a8\u82a8\u6ee9"
    ],
    "wof:name":"Jijitan",
    "wof:placetype":"locality"
},
  "geometry": {"coordinates":[103.32599999999999,37.0838],"type":"Point"}
}