{
  "type": "Feature",
  "properties": {
    "gn:admin1_code":"14.0",
    "gn:asciiname":"Labi",
    "gn:country_code":"CN",
    "gn:dem":2878,
    "gn:feature_class":"P",
    "gn:feature_code":"PPL",
    "gn:name":"Labi",
    "gn:population":0,
    "gn:timezone":"Asia/Urumqi",
    "iso:country":"CN",
    "name:bod_x_preferred":[
        "Lap\u00ea"
    ],
    "name:ceb_x_preferred":[
        "Labi"
    ],
    "name:deu_x_preferred":[
        "Labi"
    ],
    "name:swe_x_preferred":[
        "Labi"
    ],
    "name:tgl_x_preferred":[
        "Labi"
    ],
    "name:zho_x_preferred":[
        "Labi"
    ],
    "name:zho_x_variant":[
        "\u62c9\u6bd4"
    ],
    "wof:name":"Labi",
    "wof:placetype":"locality"
},
  "geometry": {"coordinates":[85.40179999999999,28.3201],"type":"Point"}
}