{
  "type": "Feature",
  "properties": {
    "gn:admin1_code":"16.0",
    "gn:asciiname":"Shangmu'en",
    "gn:country_code":"CN",
    "gn:dem":161,
    "gn:feature_class":"P",
    "gn:feature_code":"PPL",
    "gn:name":"Shangmu\u2019en",
    "gn:population":0,
    "gn:timezone":"Asia/Shanghai",
    "iso:country":"CN",
    "name:und_x_variant":[
        "Shangmu\u2019en"
    ],
    "name:zho_x_preferred":[
        "\u4e0a\u6c90\u6069"
    ],
    "wof:name":"Shangmu'en",
    "wof:placetype":"locality"
},
  "geometry": {"coordinates":[109.72199999999999,23.9295],"type":"Point"}
}