{
  "type": "Feature",
  "properties": {
    "gn:admin1_code":"11.0",
    "gn:asciiname":"Bangshan",
    "gn:country_code":"CN",
    "gn:dem":275,
    "gn:feature_class":"P",
    "gn:feature_code":"PPL",
    "gn:name":"Bangshan",
    "gn:population":0,
    "gn:timezone":"Asia/Shanghai",
    "iso:country":"CN",
    "name:zho_x_preferred":[
        "\u699c\u5c71"
    ],
    "wof:name":"Bangshan",
    "wof:placetype":"locality"
},
  "geometry": {"coordinates":[112.73931,25.63497000000001],"type":"Point"}
}