{
  "type": "Feature",
  "properties": {
    "gn:admin1_code":"1.0",
    "gn:asciiname":"Longmiaocun",
    "gn:country_code":"CN",
    "gn:dem":29,
    "gn:feature_class":"P",
    "gn:feature_code":"PPL",
    "gn:name":"Longmiaocun",
    "gn:population":0,
    "gn:timezone":"Asia/Shanghai",
    "iso:country":"CN",
    "name:zho_x_preferred":[
        "\u9f99\u5e99\u6751"
    ],
    "wof:name":"Longmiaocun",
    "wof:placetype":"locality"
},
  "geometry": {"coordinates":[116.36855,33.05882],"type":"Point"}
}