{
  "type": "Feature",
  "properties": {
    "gn:admin1_code":"15.0",
    "gn:asciiname":"Binglincha",
    "gn:country_code":"CN",
    "gn:dem":1384,
    "gn:feature_class":"P",
    "gn:feature_code":"PPL",
    "gn:name":"Binglincha",
    "gn:population":0,
    "gn:timezone":"Asia/Shanghai",
    "iso:country":"CN",
    "name:und_x_variant":[
        "\u51b0\u6dcb\u5c94"
    ],
    "wof:name":"Binglincha",
    "wof:placetype":"locality"
},
  "geometry": {"coordinates":[107.35936,36.03972],"type":"Point"}
}