{
  "type": "Feature",
  "properties": {
    "gn:admin1_code":"30.0",
    "gn:asciiname":"Hexi",
    "gn:country_code":"CN",
    "gn:dem":10,
    "gn:feature_class":"P",
    "gn:feature_code":"PPL",
    "gn:name":"Hexi",
    "gn:population":0,
    "gn:timezone":"Asia/Shanghai",
    "iso:country":"CN",
    "name:ceb_x_preferred":[
        "Hexi"
    ],
    "name:deu_x_preferred":[
        "Hexi"
    ],
    "name:eus_x_preferred":[
        "Hexi"
    ],
    "name:fra_x_preferred":[
        "Hexi"
    ],
    "name:nld_x_preferred":[
        "H\u00e0 T\u00e2y"
    ],
    "name:vie_x_preferred":[
        "H\u00e0 T\u00e2y"
    ],
    "name:zho_x_preferred":[
        "\u6cb3\u897f"
    ],
    "wof:name":"Hexi",
    "wof:placetype":"locality"
},
  "geometry": {"coordinates":[112.49317000000001,21.98981],"type":"Point"}
}