{
  "type": "Feature",
  "properties": {
    "gn:admin1_code":"11",
    "gn:asciiname":"Mapo",
    "gn:country_code":"CN",
    "gn:dem":396,
    "gn:feature_class":"P",
    "gn:feature_code":"PPL",
    "gn:name":"Mapo",
    "gn:population":0,
    "gn:timezone":"Asia/Shanghai",
    "iso:country":"CN",
    "name:ceb_x_preferred":[
        "Mapo"
    ],
    "name:deu_x_preferred":[
        "Mapo"
    ],
    "name:swe_x_preferred":[
        "Mapo"
    ],
    "wof:name":"Mapo",
    "wof:placetype":"locality"
},
  "geometry": {"coordinates":[109.74083,27.31694],"type":"Point"}
}