{
  "type": "Feature",
  "properties": {
    "gn:admin1_code":"8.0",
    "gn:asciiname":"Yihao",
    "gn:country_code":"CN",
    "gn:dem":157,
    "gn:feature_class":"P",
    "gn:feature_code":"PPLF",
    "gn:name":"Yihao",
    "gn:population":0,
    "gn:timezone":"Asia/Shanghai",
    "iso:country":"CN",
    "name:zho_x_preferred":[
        "\u4e00\u53f7"
    ],
    "wof:name":"Yihao",
    "wof:placetype":"locality"
},
  "geometry": {"coordinates":[124.84444999999999,47.36668],"type":"Point"}
}