{
  "type": "Feature",
  "properties": {
    "gn:admin1_code":"3.0",
    "gn:asciiname":"Jiangyuanli",
    "gn:country_code":"CN",
    "gn:dem":277,
    "gn:feature_class":"P",
    "gn:feature_code":"PPL",
    "gn:name":"Jiangyuanli",
    "gn:population":0,
    "gn:timezone":"Asia/Shanghai",
    "iso:country":"CN",
    "name:und_x_variant":[
        "\u6c5f\u6e90\u91cc"
    ],
    "wof:name":"Jiangyuanli",
    "wof:placetype":"locality"
},
  "geometry": {"coordinates":[114.80013,28.91943],"type":"Point"}
}