{
  "type": "Feature",
  "properties": {
    "gn:admin1_code":"26.0",
    "gn:asciiname":"Yujiayuan",
    "gn:country_code":"CN",
    "gn:dem":894,
    "gn:feature_class":"P",
    "gn:feature_code":"PPL",
    "gn:name":"Yujiayuan",
    "gn:population":0,
    "gn:timezone":"Asia/Shanghai",
    "iso:country":"CN",
    "name:zho_x_preferred":[
        "\u55bb\u5bb6\u9662"
    ],
    "wof:name":"Yujiayuan",
    "wof:placetype":"locality"
},
  "geometry": {"coordinates":[109.90248,32.73779],"type":"Point"}
}