{
  "type": "Feature",
  "properties": {
    "gn:admin1_code":"29.0",
    "gn:asciiname":"Yankou",
    "gn:country_code":"CN",
    "gn:dem":1127,
    "gn:feature_class":"P",
    "gn:feature_code":"PPL",
    "gn:name":"Yankou",
    "gn:population":0,
    "gn:timezone":"Asia/Shanghai",
    "iso:country":"CN",
    "name:zho_x_preferred":[
        "\u5ca9\u53e3"
    ],
    "wof:name":"Yankou",
    "wof:placetype":"locality"
},
  "geometry": {"coordinates":[104.24720000000001,28.01831],"type":"Point"}
}