{
  "type": "Feature",
  "properties": {
    "gn:admin1_code":"1.0",
    "gn:asciiname":"Chentuancun",
    "gn:country_code":"CN",
    "gn:dem":32,
    "gn:feature_class":"P",
    "gn:feature_code":"PPL",
    "gn:name":"Chentuancun",
    "gn:population":0,
    "gn:timezone":"Asia/Shanghai",
    "iso:country":"CN",
    "name:und_x_variant":[
        "Chentuan"
    ],
    "name:zho_x_preferred":[
        "\u9648\u7583\u6751"
    ],
    "wof:name":"Chentuancun",
    "wof:placetype":"locality"
},
  "geometry": {"coordinates":[117.15833000000001,34.00278],"type":"Point"}
}