{
  "type": "Feature",
  "properties": {
    "gn:admin1_code":"32.0",
    "gn:asciiname":"Changyaopo",
    "gn:country_code":"CN",
    "gn:dem":712,
    "gn:feature_class":"P",
    "gn:feature_code":"PPL",
    "gn:name":"Changyaopo",
    "gn:population":0,
    "gn:timezone":"Asia/Shanghai",
    "iso:country":"CN",
    "name:zho_x_preferred":[
        "\u957f\u8170\u5761"
    ],
    "wof:name":"Changyaopo",
    "wof:placetype":"locality"
},
  "geometry": {"coordinates":[104.84623000000001,28.36222],"type":"Point"}
}