{
  "type": "Feature",
  "properties": {
    "gn:admin1_code":"8.0",
    "gn:asciiname":"Xunke Yifenchang",
    "gn:country_code":"CN",
    "gn:dem":282,
    "gn:feature_class":"P",
    "gn:feature_code":"PPLF",
    "gn:name":"Xunke Yifenchang",
    "gn:population":0,
    "gn:timezone":"Asia/Shanghai",
    "iso:country":"CN",
    "name:zho_x_preferred":[
        "\u900a\u514b\u4e00\u5206\u573a"
    ],
    "wof:name":"Xunke Yifenchang",
    "wof:placetype":"locality"
},
  "geometry": {"coordinates":[128.3869,49.2339],"type":"Point"}
}