{
  "type": "Feature",
  "properties": {
    "gn:admin1_code":"3.0",
    "gn:asciiname":"Wangfang",
    "gn:country_code":"CN",
    "gn:dem":112,
    "gn:feature_class":"P",
    "gn:feature_code":"PPL",
    "gn:name":"Wangfang",
    "gn:population":0,
    "gn:timezone":"Asia/Shanghai",
    "iso:country":"CN",
    "name:ceb_x_preferred":[
        "Wangfang"
    ],
    "name:swe_x_preferred":[
        "Wangfang"
    ],
    "name:zho_x_preferred":[
        "\u738b\u574a"
    ],
    "name:zho_x_variant":[
        "\u738b\u574a\u9547"
    ],
    "wof:name":"Wangfang",
    "wof:placetype":"locality"
},
  "geometry": {"coordinates":[117.09036999999999,28.50938],"type":"Point"}
}