{
  "type": "Feature",
  "properties": {
    "gn:admin1_code":"08",
    "gn:asciiname":"Yuanbao",
    "gn:country_code":"CN",
    "gn:dem":208,
    "gn:feature_class":"P",
    "gn:feature_code":"PPL",
    "gn:name":"Yuanbao",
    "gn:population":0,
    "gn:timezone":"Asia/Shanghai",
    "iso:country":"CN",
    "name:und_x_variant":[
        "Y\u00fcan-pao-wan",
        "Yuanbao"
    ],
    "name:zho_x_preferred":[
        "\u5143\u5b9d"
    ],
    "wof:name":"Yuanbao",
    "wof:placetype":"locality"
},
  "geometry": {"coordinates":[127.41167,46.79969000000001],"type":"Point"}
}