{
  "type": "Feature",
  "properties": {
    "gn:admin1_code":"29.0",
    "gn:asciiname":"Zhemeng",
    "gn:country_code":"CN",
    "gn:dem":1144,
    "gn:feature_class":"P",
    "gn:feature_code":"PPL",
    "gn:name":"Zhemeng",
    "gn:population":0,
    "gn:timezone":"Asia/Shanghai",
    "iso:country":"CN",
    "name:zho_x_preferred":[
        "\u8005\u5b5f"
    ],
    "wof:name":"Zhemeng",
    "wof:placetype":"locality"
},
  "geometry": {"coordinates":[100.91,24.3458],"type":"Point"}
}