{
  "type": "Feature",
  "properties": {
    "gn:admin1_code":"19.0",
    "gn:asciiname":"Laodachuan",
    "gn:country_code":"CN",
    "gn:dem":414,
    "gn:feature_class":"P",
    "gn:feature_code":"PPL",
    "gn:name":"Laodachuan",
    "gn:population":0,
    "gn:timezone":"Asia/Shanghai",
    "iso:country":"CN",
    "name:und_x_variant":[
        "\u8001\u5927\u5ddd"
    ],
    "name:zho_x_preferred":[
        "\u8001\u5927\u5ddd"
    ],
    "wof:name":"Laodachuan",
    "wof:placetype":"locality"
},
  "geometry": {"coordinates":[125.24115999999999,41.41907],"type":"Point"}
}