{
  "type": "Feature",
  "properties": {
    "gn:admin1_code":"4.0",
    "gn:asciiname":"Danlian",
    "gn:country_code":"CN",
    "gn:dem":9,
    "gn:feature_class":"P",
    "gn:feature_code":"PPL",
    "gn:name":"Danlian",
    "gn:population":0,
    "gn:timezone":"Asia/Shanghai",
    "iso:country":"CN",
    "name:zho_x_preferred":[
        "\u4e39\u83b2"
    ],
    "wof:name":"Danlian",
    "wof:placetype":"locality"
},
  "geometry": {"coordinates":[118.72929000000001,31.32088],"type":"Point"}
}