{
  "type": "Feature",
  "properties": {
    "gn:admin1_code":"32.0",
    "gn:asciiname":"Chongyuan",
    "gn:country_code":"CN",
    "gn:dem":1963,
    "gn:feature_class":"P",
    "gn:feature_code":"PPL",
    "gn:name":"Chongyuan",
    "gn:population":0,
    "gn:timezone":"Asia/Shanghai",
    "iso:country":"CN",
    "name:zho_x_preferred":[
        "\u866b\u56ed"
    ],
    "wof:name":"Chongyuan",
    "wof:placetype":"locality"
},
  "geometry": {"coordinates":[102.372,26.6246],"type":"Point"}
}