{
  "type": "Feature",
  "properties": {
    "gn:admin1_code":"1.0",
    "gn:asciiname":"Mudan",
    "gn:country_code":"CN",
    "gn:dem":71,
    "gn:feature_class":"P",
    "gn:feature_code":"PPL",
    "gn:name":"Mudan",
    "gn:population":0,
    "gn:timezone":"Asia/Shanghai",
    "iso:country":"CN",
    "name:zho_x_preferred":[
        "\u7261\u4e39"
    ],
    "wof:name":"Mudan",
    "wof:placetype":"locality"
},
  "geometry": {"coordinates":[118.03512000000001,30.87276],"type":"Point"}
}