{
  "type": "Feature",
  "properties": {
    "gn:admin1_code":"12.0",
    "gn:asciiname":"Daxingshan",
    "gn:country_code":"CN",
    "gn:dem":915,
    "gn:feature_class":"P",
    "gn:feature_code":"PPL",
    "gn:name":"Daxingshan",
    "gn:population":0,
    "gn:timezone":"Asia/Shanghai",
    "iso:country":"CN",
    "name:zho_x_preferred":[
        "\u5927\u5174\u5c71"
    ],
    "wof:name":"Daxingshan",
    "wof:placetype":"locality"
},
  "geometry": {"coordinates":[111.31955000000001,31.09715],"type":"Point"}
}