{
  "type": "Feature",
  "properties": {
    "gn:admin1_code":"24",
    "gn:asciiname":"Nanyu",
    "gn:cc2":"CN",
    "gn:country_code":"CN",
    "gn:dem":1566,
    "gn:feature_class":"P",
    "gn:feature_code":"PPL",
    "gn:name":"Nanyu",
    "gn:population":0,
    "gn:timezone":"Asia/Shanghai",
    "iso:country":"CN",
    "name:deu_x_preferred":[
        "Nanyu"
    ],
    "name:und_x_variant":[
        "Nan-y\u00fc-ts\u2019un"
    ],
    "wof:name":"Nanyu",
    "wof:placetype":"locality"
},
  "geometry": {"coordinates":[111.59999999999999,38.08333],"type":"Point"}
}