{
  "type": "Feature",
  "properties": {
    "gn:admin1_code":"29.0",
    "gn:asciiname":"Luobushan",
    "gn:country_code":"CN",
    "gn:dem":2204,
    "gn:feature_class":"P",
    "gn:feature_code":"PPL",
    "gn:name":"Luobushan",
    "gn:population":0,
    "gn:timezone":"Asia/Shanghai",
    "iso:country":"CN",
    "name:zho_x_preferred":[
        "\u841d\u535c\u5c71"
    ],
    "wof:name":"Luobushan",
    "wof:placetype":"locality"
},
  "geometry": {"coordinates":[100.16800000000001,23.8287],"type":"Point"}
}