{
  "type": "Feature",
  "properties": {
    "gn:admin1_code":"11",
    "gn:asciiname":"Hongshizui",
    "gn:country_code":"CN",
    "gn:dem":149,
    "gn:feature_class":"P",
    "gn:feature_code":"PPL",
    "gn:name":"Hongshizui",
    "gn:population":0,
    "gn:timezone":"Asia/Shanghai",
    "iso:country":"CN",
    "name:zho_x_preferred":[
        "\u7ea2\u77f3\u5480"
    ],
    "wof:name":"Hongshizui",
    "wof:placetype":"locality"
},
  "geometry": {"coordinates":[112.19268999999998,27.94661],"type":"Point"}
}