{
  "type": "Feature",
  "properties": {
    "gn:admin1_code":"2.0",
    "gn:asciiname":"Yeshan",
    "gn:country_code":"CN",
    "gn:dem":435,
    "gn:feature_class":"P",
    "gn:feature_code":"PPL",
    "gn:name":"Yeshan",
    "gn:population":0,
    "gn:timezone":"Asia/Shanghai",
    "iso:country":"CN",
    "name:zho_x_preferred":[
        "\u53f6\u5c71"
    ],
    "wof:name":"Yeshan",
    "wof:placetype":"locality"
},
  "geometry": {"coordinates":[120.64676,28.48871],"type":"Point"}
}