{
  "type": "Feature",
  "properties": {
    "gn:admin1_code":"32.0",
    "gn:asciiname":"Duogenbai",
    "gn:country_code":"CN",
    "gn:dem":3567,
    "gn:feature_class":"P",
    "gn:feature_code":"PPL",
    "gn:name":"Duogenbai",
    "gn:population":0,
    "gn:timezone":"Asia/Shanghai",
    "iso:country":"CN",
    "name:zho_x_preferred":[
        "\u593a\u6839\u767d"
    ],
    "wof:name":"Duogenbai",
    "wof:placetype":"locality"
},
  "geometry": {"coordinates":[100.65828999999999,32.01419],"type":"Point"}
}