{
  "type": "Feature",
  "properties": {
    "gn:admin1_code":"19.0",
    "gn:asciiname":"Xiaohulun",
    "gn:country_code":"CN",
    "gn:dem":382,
    "gn:feature_class":"P",
    "gn:feature_code":"PPL",
    "gn:name":"Xiaohulun",
    "gn:population":0,
    "gn:timezone":"Asia/Shanghai",
    "iso:country":"CN",
    "name:zho_x_preferred":[
        "\u5c0f\u547c\u4f26"
    ],
    "wof:name":"Xiaohulun",
    "wof:placetype":"locality"
},
  "geometry": {"coordinates":[124.56853999999998,41.52527],"type":"Point"}
}