{
  "type": "Feature",
  "properties": {
    "gn:admin1_code":"16",
    "gn:asciiname":"Cuiping",
    "gn:country_code":"CN",
    "gn:dem":201,
    "gn:feature_class":"P",
    "gn:feature_code":"PPL",
    "gn:name":"Cuiping",
    "gn:population":0,
    "gn:timezone":"Asia/Shanghai",
    "iso:country":"CN",
    "name:zho_x_preferred":[
        "\u7fe0\u5c4f"
    ],
    "wof:name":"Cuiping",
    "wof:placetype":"locality"
},
  "geometry": {"coordinates":[110.372,24.8925],"type":"Point"}
}