{
  "type": "Feature",
  "properties": {
    "gn:admin1_code":"19",
    "gn:asciiname":"Xianrendaocun",
    "gn:country_code":"CN",
    "gn:dem":-9999,
    "gn:feature_class":"P",
    "gn:feature_code":"PPL",
    "gn:name":"Xianrendaocun",
    "gn:population":0,
    "gn:timezone":"Asia/Shanghai",
    "iso:country":"CN",
    "name:und_x_variant":[
        "Xianrendao",
        "\u4ed9\u4eba\u5c9b",
        "Xianrendaocun"
    ],
    "name:zho_x_preferred":[
        "\u4ed9\u4eba\u5c9b\u6751"
    ],
    "wof:name":"Xianrendaocun",
    "wof:placetype":"locality"
},
  "geometry": {"coordinates":[121.99841000000001,40.18395],"type":"Point"}
}