{
  "type": "Feature",
  "properties": {
    "gn:admin1_code":"3.0",
    "gn:asciiname":"Zhushanli",
    "gn:country_code":"CN",
    "gn:dem":546,
    "gn:feature_class":"P",
    "gn:feature_code":"PPL",
    "gn:name":"Zhushanli",
    "gn:population":0,
    "gn:timezone":"Asia/Shanghai",
    "iso:country":"CN",
    "name:und_x_variant":[
        "\u7af9\u5c71\u91cc"
    ],
    "wof:name":"Zhushanli",
    "wof:placetype":"locality"
},
  "geometry": {"coordinates":[116.51197999999999,27.5118],"type":"Point"}
}