{
  "type": "Feature",
  "properties": {
    "gn:admin1_code":"3.0",
    "gn:asciiname":"Dongjiao",
    "gn:country_code":"CN",
    "gn:dem":77,
    "gn:feature_class":"P",
    "gn:feature_code":"PPL",
    "gn:name":"Dongjiao",
    "gn:population":0,
    "gn:timezone":"Asia/Shanghai",
    "iso:country":"CN",
    "name:ceb_x_preferred":[
        "Dongjiao"
    ],
    "name:swe_x_preferred":[
        "Dongjiao"
    ],
    "name:und_x_variant":[
        "\u4e1c\u90ca"
    ],
    "wof:name":"Dongjiao",
    "wof:placetype":"locality"
},
  "geometry": {"coordinates":[115.00497,27.169],"type":"Point"}
}