{
  "type": "Feature",
  "properties": {
    "gn:admin1_code":"3.0",
    "gn:asciiname":"Chenjiali",
    "gn:country_code":"CN",
    "gn:dem":71,
    "gn:feature_class":"P",
    "gn:feature_code":"PPL",
    "gn:name":"Chenjiali",
    "gn:population":0,
    "gn:timezone":"Asia/Shanghai",
    "iso:country":"CN",
    "name:und_x_variant":[
        "\u9648\u5bb6\u91cc"
    ],
    "wof:name":"Chenjiali",
    "wof:placetype":"locality"
},
  "geometry": {"coordinates":[114.57304000000001,27.79297],"type":"Point"}
}