{
  "type": "Feature",
  "properties": {
    "gn:admin1_code":"14.0",
    "gn:asciiname":"Zhubacun",
    "gn:country_code":"CN",
    "gn:dem":3316,
    "gn:feature_class":"P",
    "gn:feature_code":"PPL",
    "gn:name":"Zhubacun",
    "gn:population":0,
    "gn:timezone":"Asia/Urumqi",
    "iso:country":"CN",
    "name:zho_x_preferred":[
        "\u6731\u5df4\u6751"
    ],
    "wof:name":"Zhubacun",
    "wof:placetype":"locality"
},
  "geometry": {"coordinates":[96.88127,30.05829],"type":"Point"}
}