{
  "type": "Feature",
  "properties": {
    "gn:admin1_code":"11.0",
    "gn:asciiname":"Dashiqiao",
    "gn:country_code":"CN",
    "gn:dem":92,
    "gn:feature_class":"P",
    "gn:feature_code":"PPL",
    "gn:name":"Dashiqiao",
    "gn:population":0,
    "gn:timezone":"Asia/Shanghai",
    "iso:country":"CN",
    "name:zho_x_preferred":[
        "\u5927\u77f3\u6865"
    ],
    "wof:name":"Dashiqiao",
    "wof:placetype":"locality"
},
  "geometry": {"coordinates":[113.00914,28.58747],"type":"Point"}
}