{
  "type": "Feature",
  "properties": {
    "gn:admin1_code":"3.0",
    "gn:asciiname":"Dongshanding",
    "gn:country_code":"CN",
    "gn:dem":377,
    "gn:feature_class":"P",
    "gn:feature_code":"PPL",
    "gn:name":"Dongshanding",
    "gn:population":0,
    "gn:timezone":"Asia/Shanghai",
    "iso:country":"CN",
    "name:und_x_variant":[
        "\u4e1c\u5c71\u9876"
    ],
    "wof:name":"Dongshanding",
    "wof:placetype":"locality"
},
  "geometry": {"coordinates":[115.91849000000001,27.23428],"type":"Point"}
}