{
  "type": "Feature",
  "properties": {
    "gn:admin1_code":"32.0",
    "gn:asciiname":"Tiemenkan",
    "gn:country_code":"CN",
    "gn:dem":536,
    "gn:feature_class":"P",
    "gn:feature_code":"PPL",
    "gn:name":"Tiemenkan",
    "gn:population":0,
    "gn:timezone":"Asia/Shanghai",
    "iso:country":"CN",
    "name:zho_x_preferred":[
        "\u94c1\u95e8\u574e"
    ],
    "wof:name":"Tiemenkan",
    "wof:placetype":"locality"
},
  "geometry": {"coordinates":[104.11199999999999,31.1199],"type":"Point"}
}