{
  "type": "Feature",
  "properties": {
    "gn:admin1_code":"29.0",
    "gn:asciiname":"Wan Himmang",
    "gn:country_code":"CN",
    "gn:dem":1470,
    "gn:feature_class":"P",
    "gn:feature_code":"PPL",
    "gn:name":"W\u0101n Himmang",
    "gn:population":0,
    "gn:timezone":"Asia/Yangon",
    "iso:country":"CN",
    "wof:name":"Wan Himmang",
    "wof:placetype":"locality"
},
  "geometry": {"coordinates":[99.98130999999999,21.84197],"type":"Point"}
}