{
  "type": "Feature",
  "properties": {
    "gn:admin1_code":"12.0",
    "gn:asciiname":"Caowugang",
    "gn:country_code":"CN",
    "gn:dem":156,
    "gn:feature_class":"P",
    "gn:feature_code":"PPL",
    "gn:name":"Caowugang",
    "gn:population":0,
    "gn:timezone":"Asia/Shanghai",
    "iso:country":"CN",
    "name:zho_x_preferred":[
        "Caowugang"
    ],
    "name:zho_x_variant":[
        "\u8349\u5c4b\u5c97"
    ],
    "wof:name":"Caowugang",
    "wof:placetype":"locality"
},
  "geometry": {"coordinates":[111.72620999999999,30.97819],"type":"Point"}
}