{
  "type": "Feature",
  "properties": {
    "gn:admin1_code":"32.0",
    "gn:asciiname":"Gaoshengchang",
    "gn:country_code":"CN",
    "gn:dem":370,
    "gn:feature_class":"P",
    "gn:feature_code":"PPL",
    "gn:name":"Gaoshengchang",
    "gn:population":0,
    "gn:timezone":"Asia/Shanghai",
    "iso:country":"CN",
    "name:zho_x_preferred":[
        "\u9ad8\u5347\u573a"
    ],
    "wof:name":"Gaoshengchang",
    "wof:placetype":"locality"
},
  "geometry": {"coordinates":[104.60906,29.18523],"type":"Point"}
}