{
  "type": "Feature",
  "properties": {
    "gn:admin1_code":"11.0",
    "gn:asciiname":"Zhang'afu",
    "gn:country_code":"CN",
    "gn:dem":122,
    "gn:feature_class":"P",
    "gn:feature_code":"PPL",
    "gn:name":"Zhang\u2019afu",
    "gn:population":0,
    "gn:timezone":"Asia/Shanghai",
    "iso:country":"CN",
    "name:und_x_variant":[
        "Zhang\u2019afu"
    ],
    "name:zho_x_preferred":[
        "\u5f20\u963f\u590d"
    ],
    "wof:name":"Zhang'afu",
    "wof:placetype":"locality"
},
  "geometry": {"coordinates":[111.58225,26.09932],"type":"Point"}
}