{
  "type": "Feature",
  "properties": {
    "gn:admin1_code":"23.0",
    "gn:asciiname":"Hongxing Nongchang Wulian",
    "gn:country_code":"CN",
    "gn:dem":7,
    "gn:feature_class":"P",
    "gn:feature_code":"PPL",
    "gn:name":"Hongxing Nongchang Wulian",
    "gn:population":0,
    "gn:timezone":"Asia/Shanghai",
    "iso:country":"CN",
    "name:zho_x_preferred":[
        "Hongxing Nongchang Wulian"
    ],
    "name:zho_x_variant":[
        "\u7ea2\u661f\u519c\u573a\u4e94\u8fde"
    ],
    "wof:name":"Hongxing Nongchang Wulian",
    "wof:placetype":"locality"
},
  "geometry": {"coordinates":[121.36991999999999,31.78607],"type":"Point"}
}