{
  "type": "Feature",
  "properties": {
    "gn:admin1_code":"26.0",
    "gn:asciiname":"Jinshuizhen",
    "gn:country_code":"CN",
    "gn:dem":493,
    "gn:feature_class":"P",
    "gn:feature_code":"PPL",
    "gn:name":"Jinshuizhen",
    "gn:population":0,
    "gn:timezone":"Asia/Shanghai",
    "iso:country":"CN",
    "name:und_x_variant":[
        "\u91d1\u6c34\u9547"
    ],
    "wof:name":"Jinshuizhen",
    "wof:placetype":"locality"
},
  "geometry": {"coordinates":[107.84672,33.27999000000001],"type":"Point"}
}