{
  "type": "Feature",
  "properties": {
    "gn:admin1_code":"14",
    "gn:asciiname":"Luomachang",
    "gn:country_code":"CN",
    "gn:dem":3828,
    "gn:feature_class":"P",
    "gn:feature_code":"PPL",
    "gn:name":"Luomachang",
    "gn:population":0,
    "gn:timezone":"Asia/Urumqi",
    "iso:country":"CN",
    "name:zho_x_preferred":[
        "\u9aa1\u9a6c\u573a"
    ],
    "wof:name":"Luomachang",
    "wof:placetype":"locality"
},
  "geometry": {"coordinates":[88.97110000000001,29.3372],"type":"Point"}
}