{
  "type": "Feature",
  "properties": {
    "gn:admin1_code":"19.0",
    "gn:asciiname":"Lianjiatun",
    "gn:country_code":"CN",
    "gn:dem":9,
    "gn:feature_class":"P",
    "gn:feature_code":"PPL",
    "gn:name":"Lianjiatun",
    "gn:population":0,
    "gn:timezone":"Asia/Shanghai",
    "iso:country":"CN",
    "name:zho_x_preferred":[
        "\u5ec9\u5bb6\u5c6f"
    ],
    "wof:name":"Lianjiatun",
    "wof:placetype":"locality"
},
  "geometry": {"coordinates":[121.67700000000001,39.5135],"type":"Point"}
}