{
  "type": "Feature",
  "properties": {
    "gn:admin1_code":"9.0",
    "gn:asciiname":"Xilizhuang",
    "gn:country_code":"CN",
    "gn:dem":240,
    "gn:feature_class":"P",
    "gn:feature_code":"PPL",
    "gn:name":"Xilizhuang",
    "gn:population":0,
    "gn:timezone":"Asia/Shanghai",
    "iso:country":"CN",
    "name:und_x_variant":[
        "\u897f\u674e\u5e84",
        "Xilizhuang"
    ],
    "wof:name":"Xilizhuang",
    "wof:placetype":"locality"
},
  "geometry": {"coordinates":[112.09277,33.12483],"type":"Point"}
}