{
  "type": "Feature",
  "properties": {
    "gn:admin1_code":"16.0",
    "gn:asciiname":"Podong",
    "gn:country_code":"CN",
    "gn:dem":988,
    "gn:feature_class":"P",
    "gn:feature_code":"PPL",
    "gn:name":"Podong",
    "gn:population":0,
    "gn:timezone":"Asia/Shanghai",
    "iso:country":"CN",
    "name:zho_x_preferred":[
        "\u5761\u4e1c"
    ],
    "wof:name":"Podong",
    "wof:placetype":"locality"
},
  "geometry": {"coordinates":[106.01300000000001,23.3445],"type":"Point"}
}