{
  "type": "Feature",
  "properties": {
    "gn:admin1_code":"16.0",
    "gn:asciiname":"Pingwa",
    "gn:country_code":"CN",
    "gn:dem":1095,
    "gn:feature_class":"P",
    "gn:feature_code":"PPL",
    "gn:name":"Pingwa",
    "gn:population":0,
    "gn:timezone":"Asia/Shanghai",
    "iso:country":"CN",
    "name:zho_x_preferred":[
        "\u576a\u74e6"
    ],
    "wof:name":"Pingwa",
    "wof:placetype":"locality"
},
  "geometry": {"coordinates":[104.91500000000001,24.6982],"type":"Point"}
}