{
  "type": "Feature",
  "properties": {
    "gn:admin1_code":"29.0",
    "gn:asciiname":"Tongsu",
    "gn:country_code":"CN",
    "gn:dem":1204,
    "gn:feature_class":"P",
    "gn:feature_code":"PPL",
    "gn:name":"Tongsu",
    "gn:population":0,
    "gn:timezone":"Asia/Shanghai",
    "iso:country":"CN",
    "name:zho_x_preferred":[
        "\u901a\u4fd7"
    ],
    "wof:name":"Tongsu",
    "wof:placetype":"locality"
},
  "geometry": {"coordinates":[102.40600000000001,22.9149],"type":"Point"}
}