{
  "type": "Feature",
  "properties": {
    "gn:admin1_code":"4.0",
    "gn:asciiname":"Xudang",
    "gn:country_code":"CN",
    "gn:dem":4,
    "gn:feature_class":"P",
    "gn:feature_code":"PPL",
    "gn:name":"Xudang",
    "gn:population":0,
    "gn:timezone":"Asia/Shanghai",
    "iso:country":"CN",
    "name:zho_x_preferred":[
        "\u5729\u8361"
    ],
    "wof:name":"Xudang",
    "wof:placetype":"locality"
},
  "geometry": {"coordinates":[121.32832999999999,32.08934],"type":"Point"}
}