{
  "type": "Feature",
  "properties": {
    "gn:admin1_code":"18.0",
    "gn:asciiname":"Zaishengba",
    "gn:country_code":"CN",
    "gn:dem":744,
    "gn:feature_class":"P",
    "gn:feature_code":"PPL",
    "gn:name":"Zaishengba",
    "gn:population":0,
    "gn:timezone":"Asia/Shanghai",
    "iso:country":"CN",
    "name:zho_x_preferred":[
        "\u518d\u751f\u575d"
    ],
    "wof:name":"Zaishengba",
    "wof:placetype":"locality"
},
  "geometry": {"coordinates":[108.565,27.8228],"type":"Point"}
}