{
  "type": "Feature",
  "properties": {
    "gn:admin1_code":"21.0",
    "gn:asciiname":"Dongshaqu",
    "gn:country_code":"CN",
    "gn:dem":1470,
    "gn:feature_class":"P",
    "gn:feature_code":"PPL",
    "gn:name":"Dongshaqu",
    "gn:population":0,
    "gn:timezone":"Asia/Shanghai",
    "iso:country":"CN",
    "name:zho_x_preferred":[
        "\u4e1c\u6c99\u6e20"
    ],
    "wof:name":"Dongshaqu",
    "wof:placetype":"locality"
},
  "geometry": {"coordinates":[106.108,37.2925],"type":"Point"}
}