{
  "type": "Feature",
  "properties": {
    "gn:admin1_code":"13.0",
    "gn:asciiname":"Jiayizha Gelake",
    "gn:country_code":"CN",
    "gn:dem":1233,
    "gn:feature_class":"P",
    "gn:feature_code":"PPL",
    "gn:name":"Jiayizha Gelake",
    "gn:population":0,
    "gn:timezone":"Asia/Shanghai",
    "iso:country":"CN",
    "name:zho_x_preferred":[
        "\u52a0\u4f9d\u624e\u683c\u62c9\u514b"
    ],
    "wof:name":"Jiayizha Gelake",
    "wof:placetype":"locality"
},
  "geometry": {"coordinates":[76.52476999999998,39.25632],"type":"Point"}
}