{
  "type": "Feature",
  "properties": {
    "gn:admin1_code":"29.0",
    "gn:asciiname":"Bende",
    "gn:country_code":"CN",
    "gn:dem":2003,
    "gn:feature_class":"P",
    "gn:feature_code":"PPL",
    "gn:name":"Bende",
    "gn:population":0,
    "gn:timezone":"Asia/Shanghai",
    "iso:country":"CN",
    "name:ceb_x_preferred":[
        "Bende"
    ],
    "name:deu_x_preferred":[
        "Bende"
    ],
    "name:fra_x_preferred":[
        "Bende"
    ],
    "name:ita_x_preferred":[
        "Bende"
    ],
    "name:nld_x_preferred":[
        "Bende"
    ],
    "name:swe_x_preferred":[
        "Bende"
    ],
    "name:zho_x_preferred":[
        "\u672c\u5fb7"
    ],
    "wof:name":"Bende",
    "wof:placetype":"locality"
},
  "geometry": {"coordinates":[98.8373,26.4901],"type":"Point"}
}