{
  "type": "Feature",
  "properties": {
    "gn:admin1_code":"26.0",
    "gn:asciiname":"Mijiagoucun",
    "gn:country_code":"CN",
    "gn:dem":985,
    "gn:feature_class":"P",
    "gn:feature_code":"PPL",
    "gn:name":"Mijiagoucun",
    "gn:population":0,
    "gn:timezone":"Asia/Shanghai",
    "iso:country":"CN",
    "name:zho_x_preferred":[
        "\u7c73\u5bb6\u6c9f\u6751"
    ],
    "wof:name":"Mijiagoucun",
    "wof:placetype":"locality"
},
  "geometry": {"coordinates":[109.34363,36.19813],"type":"Point"}
}