{
  "type": "Feature",
  "properties": {
    "gn:admin1_code":"29.0",
    "gn:asciiname":"Jianglou",
    "gn:country_code":"CN",
    "gn:dem":1774,
    "gn:feature_class":"P",
    "gn:feature_code":"PPL",
    "gn:name":"Jianglou",
    "gn:population":0,
    "gn:timezone":"Asia/Shanghai",
    "iso:country":"CN",
    "name:zho_x_preferred":[
        "\u6c5f\u697c"
    ],
    "wof:name":"Jianglou",
    "wof:placetype":"locality"
},
  "geometry": {"coordinates":[99.8038,24.8395],"type":"Point"}
}