{
  "type": "Feature",
  "properties": {
    "gn:admin1_code":"15.0",
    "gn:asciiname":"Baishui Duibu",
    "gn:country_code":"CN",
    "gn:dem":3273,
    "gn:feature_class":"P",
    "gn:feature_code":"PPL",
    "gn:name":"Baishui Duibu",
    "gn:population":0,
    "gn:timezone":"Asia/Shanghai",
    "iso:country":"CN",
    "name:zho_x_preferred":[
        "\u767d\u6c34\u961f\u90e8"
    ],
    "wof:name":"Baishui Duibu",
    "wof:placetype":"locality"
},
  "geometry": {"coordinates":[102.54000000000001,37.2522],"type":"Point"}
}