{
  "type": "Feature",
  "properties": {
    "gn:admin1_code":"29",
    "gn:asciiname":"Qingshui",
    "gn:country_code":"CN",
    "gn:dem":2036,
    "gn:feature_class":"P",
    "gn:feature_code":"PPL",
    "gn:name":"Qingshui",
    "gn:population":0,
    "gn:timezone":"Asia/Shanghai",
    "iso:country":"CN",
    "name:ceb_x_preferred":[
        "Qingshui"
    ],
    "name:deu_x_preferred":[
        "Qingshui"
    ],
    "name:zho_x_preferred":[
        "\u6e05\u6c34"
    ],
    "wof:name":"Qingshui",
    "wof:placetype":"locality"
},
  "geometry": {"coordinates":[102.8873,24.99431],"type":"Point"}
}