{
  "type": "Feature",
  "properties": {
    "gn:admin1_code":"26.0",
    "gn:asciiname":"Lipancun",
    "gn:country_code":"CN",
    "gn:dem":1540,
    "gn:feature_class":"P",
    "gn:feature_code":"PPL",
    "gn:name":"Lipancun",
    "gn:population":0,
    "gn:timezone":"Asia/Shanghai",
    "iso:country":"CN",
    "name:zho_x_preferred":[
        "\u674e\u7554\u6751"
    ],
    "wof:name":"Lipancun",
    "wof:placetype":"locality"
},
  "geometry": {"coordinates":[108.46872,36.95042],"type":"Point"}
}