{
  "type": "Feature",
  "properties": {
    "gn:admin1_code":"32.0",
    "gn:asciiname":"Huangwasi",
    "gn:country_code":"CN",
    "gn:dem":379,
    "gn:feature_class":"P",
    "gn:feature_code":"PPL",
    "gn:name":"Huangwasi",
    "gn:population":0,
    "gn:timezone":"Asia/Shanghai",
    "iso:country":"CN",
    "name:zho_x_preferred":[
        "\u9ec4\u74e6\u5bfa"
    ],
    "wof:name":"Huangwasi",
    "wof:placetype":"locality"
},
  "geometry": {"coordinates":[105.812,31.2556],"type":"Point"}
}