{
  "type": "Feature",
  "properties": {
    "gn:admin1_code":"18.0",
    "gn:asciiname":"Gaoliangchong",
    "gn:country_code":"CN",
    "gn:dem":512,
    "gn:feature_class":"P",
    "gn:feature_code":"PPL",
    "gn:name":"Gaoliangchong",
    "gn:population":0,
    "gn:timezone":"Asia/Shanghai",
    "iso:country":"CN",
    "name:zho_x_preferred":[
        "\u9ad8\u6881\u51b2"
    ],
    "wof:name":"Gaoliangchong",
    "wof:placetype":"locality"
},
  "geometry": {"coordinates":[109.078,28.0915],"type":"Point"}
}