{
  "type": "Feature",
  "properties": {
    "gn:admin1_code":"14",
    "gn:asciiname":"Menga",
    "gn:country_code":"CN",
    "gn:dem":4082,
    "gn:feature_class":"P",
    "gn:feature_code":"PPL",
    "gn:name":"Menga",
    "gn:population":0,
    "gn:timezone":"Asia/Urumqi",
    "iso:country":"CN",
    "name:zho_x_preferred":[
        "\u95e8\u560e"
    ],
    "wof:name":"Menga",
    "wof:placetype":"locality"
},
  "geometry": {"coordinates":[89.1217,28.9886],"type":"Point"}
}