{
  "type": "Feature",
  "properties": {
    "gn:admin1_code":"16.0",
    "gn:asciiname":"Chahua",
    "gn:country_code":"CN",
    "gn:dem":181,
    "gn:feature_class":"P",
    "gn:feature_code":"PPL",
    "gn:name":"Chahua",
    "gn:population":0,
    "gn:timezone":"Asia/Shanghai",
    "iso:country":"CN",
    "name:zho_x_preferred":[
        "\u63d2\u82b1"
    ],
    "wof:name":"Chahua",
    "wof:placetype":"locality"
},
  "geometry": {"coordinates":[108.94199999999999,24.8881],"type":"Point"}
}