{
  "type": "Feature",
  "properties": {
    "gn:admin1_code":"02",
    "gn:asciiname":"Shendang",
    "gn:country_code":"CN",
    "gn:dem":11,
    "gn:feature_class":"P",
    "gn:feature_code":"PPLA4",
    "gn:name":"Shendang",
    "gn:population":0,
    "gn:timezone":"Asia/Shanghai",
    "iso:country":"CN",
    "name:und_x_variant":[
        "Shen-tang-chen",
        "Shen-tang",
        "Shendang",
        "\u6c88\u8361",
        "Shendang Zhen",
        "\u6c88\u8361\u9547"
    ],
    "wof:name":"Shendang",
    "wof:placetype":"locality"
},
  "geometry": {"coordinates":[120.82129,30.57736],"type":"Point"}
}