{
  "type": "Feature",
  "properties": {
    "gn:admin1_code":"7.0",
    "gn:asciiname":"Kaiyuan",
    "gn:country_code":"CN",
    "gn:dem":939,
    "gn:feature_class":"P",
    "gn:feature_code":"PPL",
    "gn:name":"Kaiyuan",
    "gn:population":0,
    "gn:timezone":"Asia/Shanghai",
    "iso:country":"CN",
    "name:ceb_x_preferred":[
        "Kaiyuan"
    ],
    "name:deu_x_preferred":[
        "Kaiyuan"
    ],
    "name:fra_x_preferred":[
        "Kaiyuan"
    ],
    "name:kor_x_preferred":[
        "\uce74\uc774\uc704\uc548\uc2dc"
    ],
    "name:mlg_x_preferred":[
        "Kaiyuan"
    ],
    "name:nld_x_preferred":[
        "Kaiyuan"
    ],
    "name:nor_x_preferred":[
        "Kaiyuan"
    ],
    "name:pol_x_preferred":[
        "Kaiyuan"
    ],
    "name:swe_x_preferred":[
        "Kaiyuan"
    ],
    "name:zho_x_preferred":[
        "\u5f00\u6e90"
    ],
    "wof:name":"Kaiyuan",
    "wof:placetype":"locality"
},
  "geometry": {"coordinates":[118.95381999999999,27.07968],"type":"Point"}
}