{
  "type": "Feature",
  "properties": {
    "gn:admin1_code":"8.0",
    "gn:asciiname":"Shengjiatun",
    "gn:country_code":"CN",
    "gn:dem":182,
    "gn:feature_class":"P",
    "gn:feature_code":"PPL",
    "gn:name":"Shengjiatun",
    "gn:population":0,
    "gn:timezone":"Asia/Shanghai",
    "iso:country":"CN",
    "name:zho_x_preferred":[
        "\u80dc\u5bb6\u5c6f"
    ],
    "wof:name":"Shengjiatun",
    "wof:placetype":"locality"
},
  "geometry": {"coordinates":[127.07509,46.98866],"type":"Point"}
}