{
  "type": "Feature",
  "properties": {
    "gn:admin1_code":"10",
    "gn:asciiname":"Ruiyunguan",
    "gn:country_code":"CN",
    "gn:dem":626,
    "gn:feature_class":"P",
    "gn:feature_code":"PPL",
    "gn:name":"Ruiyunguan",
    "gn:population":0,
    "gn:timezone":"Asia/Shanghai",
    "iso:country":"CN",
    "name:zho_x_preferred":[
        "\u745e\u4e91\u89c2"
    ],
    "wof:name":"Ruiyunguan",
    "wof:placetype":"locality"
},
  "geometry": {"coordinates":[115.82746000000002,40.28715],"type":"Point"}
}