{
  "type": "Feature",
  "properties": {
    "gn:admin1_code":"11.0",
    "gn:asciiname":"Aiziyu",
    "gn:country_code":"CN",
    "gn:dem":271,
    "gn:feature_class":"P",
    "gn:feature_code":"PPL",
    "gn:name":"Aiziyu",
    "gn:population":0,
    "gn:timezone":"Asia/Shanghai",
    "iso:country":"CN",
    "name:zho_x_preferred":[
        "\u827e\u5b50\u5cea"
    ],
    "wof:name":"Aiziyu",
    "wof:placetype":"locality"
},
  "geometry": {"coordinates":[110.32674,29.2004],"type":"Point"}
}