{
  "type": "Feature",
  "properties": {
    "gn:admin1_code":"07",
    "gn:asciiname":"Fudetou",
    "gn:country_code":"CN",
    "gn:dem":334,
    "gn:feature_class":"P",
    "gn:feature_code":"PPL",
    "gn:name":"Fudetou",
    "gn:population":0,
    "gn:timezone":"Asia/Shanghai",
    "iso:country":"CN",
    "name:zho_x_preferred":[
        "\u798f\u5fb7\u5934"
    ],
    "wof:name":"Fudetou",
    "wof:placetype":"locality"
},
  "geometry": {"coordinates":[117.8526,25.40484],"type":"Point"}
}