{
  "type": "Feature",
  "properties": {
    "gn:admin1_code":"03",
    "gn:asciiname":"Qiuxi",
    "gn:country_code":"CN",
    "gn:dem":52,
    "gn:feature_class":"P",
    "gn:feature_code":"PPLA4",
    "gn:name":"Qiuxi",
    "gn:population":0,
    "gn:timezone":"Asia/Shanghai",
    "iso:country":"CN",
    "name:und_x_variant":[
        "\u79cb\u6eaa",
        "Qiuxi Zhen",
        "\u79cb\u6eaa\u9547"
    ],
    "wof:name":"Qiuxi",
    "wof:placetype":"locality"
},
  "geometry": {"coordinates":[116.27179,27.84877],"type":"Point"}
}