{
  "type": "Feature",
  "properties": {
    "gn:admin1_code":"26.0",
    "gn:asciiname":"Bianjia Qucun",
    "gn:country_code":"CN",
    "gn:dem":1073,
    "gn:feature_class":"P",
    "gn:feature_code":"PPL",
    "gn:name":"Bianjia Qucun",
    "gn:population":0,
    "gn:timezone":"Asia/Shanghai",
    "iso:country":"CN",
    "name:zho_x_preferred":[
        "\u8fb9\u5bb6\u6e20\u6751"
    ],
    "wof:name":"Bianjia Qucun",
    "wof:placetype":"locality"
},
  "geometry": {"coordinates":[110.212,38.5074],"type":"Point"}
}