{
  "type": "Feature",
  "properties": {
    "gn:admin1_code":"16.0",
    "gn:asciiname":"Shibuxu",
    "gn:country_code":"CN",
    "gn:dem":49,
    "gn:feature_class":"P",
    "gn:feature_code":"PPL",
    "gn:name":"Shibuxu",
    "gn:population":0,
    "gn:timezone":"Asia/Shanghai",
    "iso:country":"CN",
    "name:zho_x_preferred":[
        "\u77f3\u57e0\u5729"
    ],
    "wof:name":"Shibuxu",
    "wof:placetype":"locality"
},
  "geometry": {"coordinates":[108.89100000000001,22.046],"type":"Point"}
}