{
  "type": "Feature",
  "properties": {
    "gn:admin1_code":"30.0",
    "gn:asciiname":"Zhengmaxu",
    "gn:country_code":"CN",
    "gn:dem":216,
    "gn:feature_class":"P",
    "gn:feature_code":"PPL",
    "gn:name":"Zhengmaxu",
    "gn:population":0,
    "gn:timezone":"Asia/Shanghai",
    "iso:country":"CN",
    "name:zho_x_preferred":[
        "\u90d1\u9a6c\u5729"
    ],
    "wof:name":"Zhengmaxu",
    "wof:placetype":"locality"
},
  "geometry": {"coordinates":[115.30623,24.51484],"type":"Point"}
}