{
  "type": "Feature",
  "properties": {
    "gn:admin1_code":"16.0",
    "gn:asciiname":"Leipen",
    "gn:country_code":"CN",
    "gn:dem":74,
    "gn:feature_class":"P",
    "gn:feature_code":"PPL",
    "gn:name":"Leipen",
    "gn:population":0,
    "gn:timezone":"Asia/Shanghai",
    "iso:country":"CN",
    "name:zho_x_preferred":[
        "\u857e\u76c6"
    ],
    "wof:name":"Leipen",
    "wof:placetype":"locality"
},
  "geometry": {"coordinates":[108.301,21.8834],"type":"Point"}
}