{
  "type": "Feature",
  "properties": {
    "gn:admin1_code":"29.0",
    "gn:asciiname":"Qifa",
    "gn:country_code":"CN",
    "gn:dem":1905,
    "gn:feature_class":"P",
    "gn:feature_code":"PPL",
    "gn:name":"Qifa",
    "gn:population":0,
    "gn:timezone":"Asia/Shanghai",
    "iso:country":"CN",
    "name:zho_x_preferred":[
        "\u542f\u53d1"
    ],
    "wof:name":"Qifa",
    "wof:placetype":"locality"
},
  "geometry": {"coordinates":[104.008,24.7389],"type":"Point"}
}