{
  "type": "Feature",
  "properties": {
    "gn:admin1_code":"02",
    "gn:asciiname":"Dadaocun",
    "gn:country_code":"CN",
    "gn:dem":8,
    "gn:feature_class":"P",
    "gn:feature_code":"PPL",
    "gn:name":"Dadaocun",
    "gn:population":0,
    "gn:timezone":"Asia/Shanghai",
    "iso:country":"CN",
    "name:und_x_variant":[
        "Dadao",
        "Dadaocun"
    ],
    "name:zho_x_preferred":[
        "\u8fbe\u9053"
    ],
    "name:zho_x_variant":[
        "\u8fbe\u9053\u6751"
    ],
    "wof:name":"Dadaocun",
    "wof:placetype":"locality"
},
  "geometry": {"coordinates":[121.61829,28.72028],"type":"Point"}
}