{
  "type": "Feature",
  "properties": {
    "gn:admin1_code":"16.0",
    "gn:asciiname":"Pingnan",
    "gn:country_code":"CN",
    "gn:dem":110,
    "gn:feature_class":"P",
    "gn:feature_code":"PPL",
    "gn:name":"Pingnan",
    "gn:population":0,
    "gn:timezone":"Asia/Shanghai",
    "iso:country":"CN",
    "name:ceb_x_preferred":[
        "Pingnan"
    ],
    "name:deu_x_preferred":[
        "Pingnan"
    ],
    "name:fra_x_preferred":[
        "Pingnan"
    ],
    "name:kor_x_preferred":[
        "\ud551\ub09c\ud604"
    ],
    "name:mlg_x_preferred":[
        "Pingnan"
    ],
    "name:nor_x_preferred":[
        "Pingnan"
    ],
    "name:swe_x_preferred":[
        "Pingnan"
    ],
    "name:zho_x_preferred":[
        "\u5e73\u5357"
    ],
    "wof:name":"Pingnan",
    "wof:placetype":"locality"
},
  "geometry": {"coordinates":[108.965,23.1046],"type":"Point"}
}