{
  "type": "Feature",
  "properties": {
    "gn:country":"CN",
    "gn:fcode":"PPL",
    "gn:population":67945,
    "iso:country":"CN",
    "name:ceb_x_preferred":[
        "Minggang"
    ],
    "name:eng_x_preferred":[
        "Minggang"
    ],
    "name:gan_x_preferred":[
        "\u660e\u6e2f\u9547"
    ],
    "name:jpn_x_preferred":[
        "\u660e\u6e2f\u93ae"
    ],
    "name:nob_x_preferred":[
        "Minggang"
    ],
    "name:swe_x_preferred":[
        "Minggang"
    ],
    "name:und_x_variant":[
        "Ming-chiang"
    ],
    "name:wuu_x_preferred":[
        "\u660e\u6e2f\u9547"
    ],
    "name:zho_x_preferred":[
        "\u660e\u6e2f\u9547"
    ],
    "name:zho_x_variant":[
        "\u9547\u5eb7\u53bf"
    ],
    "qs:name":"\u660e\u6e2f",
    "qs:name_adm0":"\u4e2d\u570b",
    "qs:name_adm1":"\u6cb3\u5357\u7701",
    "qs:photos_9r":0,
    "qs:photos_sr":0,
    "qs:placetype":"Town",
    "qs:pop_sr":"8",
    "wof:name":"\u660e\u6e2f",
    "wof:placetype":"locality",
    "wof:population":67945
},
  "geometry": {"coordinates":[114.04861,32.45861],"type":"Point"}
}