{
  "type": "Feature",
  "properties": {
    "gn:admin1_code":"18",
    "gn:asciiname":"Yantoushang",
    "gn:country_code":"CN",
    "gn:dem":1195,
    "gn:feature_class":"P",
    "gn:feature_code":"PPL",
    "gn:name":"Yantoushang",
    "gn:population":0,
    "gn:timezone":"Asia/Shanghai",
    "iso:country":"CN",
    "name:zho_x_preferred":[
        "\u5ca9\u5934\u4e0a"
    ],
    "wof:name":"Yantoushang",
    "wof:placetype":"locality"
},
  "geometry": {"coordinates":[106.151,26.7093],"type":"Point"}
}