{
  "type": "Feature",
  "properties": {
    "gn:admin1_code":"18",
    "gn:asciiname":"Cizhuguan",
    "gn:country_code":"CN",
    "gn:dem":1015,
    "gn:feature_class":"P",
    "gn:feature_code":"PPL",
    "gn:name":"Cizhuguan",
    "gn:population":0,
    "gn:timezone":"Asia/Shanghai",
    "iso:country":"CN",
    "name:zho_x_preferred":[
        "\u523a\u7af9\u5173"
    ],
    "wof:name":"Cizhuguan",
    "wof:placetype":"locality"
},
  "geometry": {"coordinates":[106.98699999999999,25.6391],"type":"Point"}
}