{
  "type": "Feature",
  "properties": {
    "gn:admin1_code":"30.0",
    "gn:asciiname":"Fenghuanggang",
    "gn:country_code":"CN",
    "gn:dem":18,
    "gn:feature_class":"P",
    "gn:feature_code":"PPL",
    "gn:name":"Fenghuanggang",
    "gn:population":0,
    "gn:timezone":"Asia/Shanghai",
    "iso:country":"CN",
    "name:zho_x_preferred":[
        "\u51e4\u51f0\u5c97"
    ],
    "wof:name":"Fenghuanggang",
    "wof:placetype":"locality"
},
  "geometry": {"coordinates":[113.06352,23.66138],"type":"Point"}
}