{
  "type": "Feature",
  "properties": {
    "gn:admin1_code":"19.0",
    "gn:asciiname":"Dongjingzi",
    "gn:country_code":"CN",
    "gn:dem":494,
    "gn:feature_class":"P",
    "gn:feature_code":"PPL",
    "gn:name":"Dongjingzi",
    "gn:population":0,
    "gn:timezone":"Asia/Shanghai",
    "iso:country":"CN",
    "name:und_x_variant":[
        "\u4e1c\u4e95\u5b50"
    ],
    "name:zho_x_preferred":[
        "\u4e1c\u4e95\u5b50"
    ],
    "wof:name":"Dongjingzi",
    "wof:placetype":"locality"
},
  "geometry": {"coordinates":[120.401,41.9369],"type":"Point"}
}