{
  "type": "Feature",
  "properties": {
    "gn:admin1_code":"26.0",
    "gn:asciiname":"Xiayuan",
    "gn:country_code":"CN",
    "gn:dem":1172,
    "gn:feature_class":"P",
    "gn:feature_code":"PPL",
    "gn:name":"Xiayuan",
    "gn:population":0,
    "gn:timezone":"Asia/Shanghai",
    "iso:country":"CN",
    "name:zho_x_preferred":[
        "\u4e0b\u9662"
    ],
    "wof:name":"Xiayuan",
    "wof:placetype":"locality"
},
  "geometry": {"coordinates":[110.21848,33.62655],"type":"Point"}
}