{
  "type": "Feature",
  "properties": {
    "gn:admin1_code":"11.0",
    "gn:asciiname":"Yangjia Bianshan",
    "gn:country_code":"CN",
    "gn:dem":62,
    "gn:feature_class":"P",
    "gn:feature_code":"PPL",
    "gn:name":"Yangjia Bianshan",
    "gn:population":0,
    "gn:timezone":"Asia/Shanghai",
    "iso:country":"CN",
    "name:zho_x_preferred":[
        "Yangjia Bianshan"
    ],
    "name:zho_x_variant":[
        "\u6768\u5bb6\u8fb9\u5c71"
    ],
    "wof:name":"Yangjia Bianshan",
    "wof:placetype":"locality"
},
  "geometry": {"coordinates":[111.48273,29.04904],"type":"Point"}
}