{
  "type": "Feature",
  "properties": {
    "gn:admin1_code":"15.0",
    "gn:asciiname":"Zhigou",
    "gn:country_code":"CN",
    "gn:dem":2735,
    "gn:feature_class":"P",
    "gn:feature_code":"PPL",
    "gn:name":"Zhigou",
    "gn:population":0,
    "gn:timezone":"Asia/Shanghai",
    "iso:country":"CN",
    "name:zho_x_preferred":[
        "\u76f4\u6c9f"
    ],
    "wof:name":"Zhigou",
    "wof:placetype":"locality"
},
  "geometry": {"coordinates":[102.85899999999999,37.2486],"type":"Point"}
}