{
  "type": "Feature",
  "properties": {
    "gn:admin1_code":"16.0",
    "gn:asciiname":"Yongwang",
    "gn:country_code":"CN",
    "gn:dem":128,
    "gn:feature_class":"P",
    "gn:feature_code":"PPL",
    "gn:name":"Yongwang",
    "gn:population":0,
    "gn:timezone":"Asia/Shanghai",
    "iso:country":"CN",
    "name:zho_x_preferred":[
        "\u6c38\u65fa"
    ],
    "wof:name":"Yongwang",
    "wof:placetype":"locality"
},
  "geometry": {"coordinates":[110.197,22.4176],"type":"Point"}
}