{
  "type": "Feature",
  "properties": {
    "gn:admin1_code":"1.0",
    "gn:asciiname":"Chuzhuangcun",
    "gn:country_code":"CN",
    "gn:dem":29,
    "gn:feature_class":"P",
    "gn:feature_code":"PPL",
    "gn:name":"Chuzhuangcun",
    "gn:population":0,
    "gn:timezone":"Asia/Shanghai",
    "iso:country":"CN",
    "name:zho_x_preferred":[
        "\u50a8\u5e84\u6751"
    ],
    "wof:name":"Chuzhuangcun",
    "wof:placetype":"locality"
},
  "geometry": {"coordinates":[116.06211999999999,32.92111],"type":"Point"}
}