{
  "type": "Feature",
  "properties": {
    "gn:admin1_code":"29.0",
    "gn:asciiname":"Sagezhu",
    "gn:country_code":"CN",
    "gn:dem":2241,
    "gn:feature_class":"P",
    "gn:feature_code":"PPL",
    "gn:name":"Sagezhu",
    "gn:population":0,
    "gn:timezone":"Asia/Shanghai",
    "iso:country":"CN",
    "name:zho_x_preferred":[
        "\u6d12\u4e2a\u52a9"
    ],
    "wof:name":"Sagezhu",
    "wof:placetype":"locality"
},
  "geometry": {"coordinates":[99.7435,25.6931],"type":"Point"}
}