{
  "type": "Feature",
  "properties": {
    "gn:admin1_code":"08",
    "gn:asciiname":"Daxing",
    "gn:country_code":"CN",
    "gn:dem":124,
    "gn:feature_class":"P",
    "gn:feature_code":"PPL",
    "gn:name":"Daxing",
    "gn:population":0,
    "gn:timezone":"Asia/Shanghai",
    "iso:country":"CN",
    "name:ceb_x_preferred":[
        "Daxing"
    ],
    "name:deu_x_preferred":[
        "Daxing"
    ],
    "name:mlg_x_preferred":[
        "Daxing"
    ],
    "name:nor_x_preferred":[
        "Daxing"
    ],
    "wof:name":"Daxing",
    "wof:placetype":"locality"
},
  "geometry": {"coordinates":[124.59999999999999,45.78333],"type":"Point"}
}