{
  "type": "Feature",
  "properties": {
    "gn:admin1_code":"16.0",
    "gn:asciiname":"Mogecun",
    "gn:country_code":"CN",
    "gn:dem":1372,
    "gn:feature_class":"P",
    "gn:feature_code":"PPL",
    "gn:name":"Mogecun",
    "gn:population":0,
    "gn:timezone":"Asia/Shanghai",
    "iso:country":"CN",
    "name:zho_x_preferred":[
        "\u83ab\u54e5\u5bf8"
    ],
    "wof:name":"Mogecun",
    "wof:placetype":"locality"
},
  "geometry": {"coordinates":[105.122,24.6155],"type":"Point"}
}