{
  "type": "Feature",
  "properties": {
    "gn:admin1_code":"18.0",
    "gn:asciiname":"Wuxiu",
    "gn:country_code":"CN",
    "gn:dem":543,
    "gn:feature_class":"P",
    "gn:feature_code":"PPL",
    "gn:name":"Wuxiu",
    "gn:population":0,
    "gn:timezone":"Asia/Shanghai",
    "iso:country":"CN",
    "name:zho_x_preferred":[
        "\u5deb\u79c0"
    ],
    "wof:name":"Wuxiu",
    "wof:placetype":"locality"
},
  "geometry": {"coordinates":[108.05,25.9817],"type":"Point"}
}