{
  "type": "Feature",
  "properties": {
    "gn:admin1_code":"30",
    "gn:asciiname":"Shangchengshi",
    "gn:country_code":"CN",
    "gn:dem":262,
    "gn:feature_class":"P",
    "gn:feature_code":"PPL",
    "gn:name":"Shangchengshi",
    "gn:population":0,
    "gn:timezone":"Asia/Shanghai",
    "iso:country":"CN",
    "name:zho_x_preferred":[
        "\u4e0a\u57d5\u77f3"
    ],
    "wof:name":"Shangchengshi",
    "wof:placetype":"locality"
},
  "geometry": {"coordinates":[116.16667,24.1654],"type":"Point"}
}