{
  "type": "Feature",
  "properties": {
    "gn:admin1_code":"1.0",
    "gn:asciiname":"Liyuan",
    "gn:country_code":"CN",
    "gn:dem":244,
    "gn:feature_class":"P",
    "gn:feature_code":"PPL",
    "gn:name":"Liyuan",
    "gn:population":0,
    "gn:timezone":"Asia/Shanghai",
    "iso:country":"CN",
    "wof:name":"Liyuan",
    "wof:placetype":"locality"
},
  "geometry": {"coordinates":[119.30694,30.42083],"type":"Point"}
}