{
  "type": "Feature",
  "properties": {
    "gn:admin1_code":"3.0",
    "gn:asciiname":"Chengdi",
    "gn:country_code":"CN",
    "gn:dem":349,
    "gn:feature_class":"P",
    "gn:feature_code":"PPL",
    "gn:name":"Chengdi",
    "gn:population":0,
    "gn:timezone":"Asia/Shanghai",
    "iso:country":"CN",
    "name:und_x_variant":[
        "\u7a0b\u5730"
    ],
    "wof:name":"Chengdi",
    "wof:placetype":"locality"
},
  "geometry": {"coordinates":[116.07928,26.14101],"type":"Point"}
}