{
  "type": "Feature",
  "properties": {
    "gn:admin1_code":"25.0",
    "gn:asciiname":"Jianghaicun",
    "gn:country_code":"CN",
    "gn:dem":43,
    "gn:feature_class":"P",
    "gn:feature_code":"PPL",
    "gn:name":"Jianghaicun",
    "gn:population":0,
    "gn:timezone":"Asia/Shanghai",
    "iso:country":"CN",
    "name:zho_x_preferred":[
        "\u848b\u6d77\u6751"
    ],
    "wof:name":"Jianghaicun",
    "wof:placetype":"locality"
},
  "geometry": {"coordinates":[115.84663,36.03934],"type":"Point"}
}