{
  "type": "Feature",
  "properties": {
    "gn:admin1_code":"3.0",
    "gn:asciiname":"Yuye",
    "gn:country_code":"CN",
    "gn:dem":35,
    "gn:feature_class":"P",
    "gn:feature_code":"PPL",
    "gn:name":"Yuye",
    "gn:population":0,
    "gn:timezone":"Asia/Shanghai",
    "iso:country":"CN",
    "name:und_x_variant":[
        "\u6e14\u4e1a"
    ],
    "wof:name":"Yuye",
    "wof:placetype":"locality"
},
  "geometry": {"coordinates":[116.51018999999999,29.77284],"type":"Point"}
}