{
  "type": "Feature",
  "properties": {
    "gn:admin1_code":"15.0",
    "gn:asciiname":"Sunjiayuan",
    "gn:country_code":"CN",
    "gn:dem":2028,
    "gn:feature_class":"P",
    "gn:feature_code":"PPL",
    "gn:name":"Sunjiayuan",
    "gn:population":0,
    "gn:timezone":"Asia/Shanghai",
    "iso:country":"CN",
    "name:zho_x_preferred":[
        "\u5b59\u5bb6\u586c"
    ],
    "wof:name":"Sunjiayuan",
    "wof:placetype":"locality"
},
  "geometry": {"coordinates":[105.301,36.2123],"type":"Point"}
}