{
  "type": "Feature",
  "properties": {
    "gn:admin1_code":"2.0",
    "gn:asciiname":"Linggezhang",
    "gn:country_code":"CN",
    "gn:dem":99,
    "gn:feature_class":"P",
    "gn:feature_code":"PPL",
    "gn:name":"Linggezhang",
    "gn:population":0,
    "gn:timezone":"Asia/Shanghai",
    "iso:country":"CN",
    "name:und_x_variant":[
        "\u51cc\u9601\u5f20",
        "Linggezhang"
    ],
    "wof:name":"Linggezhang",
    "wof:placetype":"locality"
},
  "geometry": {"coordinates":[119.23468,29.23244],"type":"Point"}
}