{
  "type": "Feature",
  "properties": {
    "gn:admin1_code":"18",
    "gn:asciiname":"Lazidi",
    "gn:country_code":"CN",
    "gn:dem":991,
    "gn:feature_class":"P",
    "gn:feature_code":"PPL",
    "gn:name":"Lazidi",
    "gn:population":0,
    "gn:timezone":"Asia/Shanghai",
    "iso:country":"CN",
    "name:zho_x_preferred":[
        "\u8fa3\u5b50\u5730"
    ],
    "wof:name":"Lazidi",
    "wof:placetype":"locality"
},
  "geometry": {"coordinates":[105.611,25.6747],"type":"Point"}
}