{
  "type": "Feature",
  "properties": {
    "gn:admin1_code":"2",
    "gn:asciiname":"Wangjiatang",
    "gn:country_code":"CN",
    "gn:dem":637,
    "gn:feature_class":"P",
    "gn:feature_code":"PPL",
    "gn:name":"Wangjiatang",
    "gn:population":0,
    "gn:timezone":"Asia/Shanghai",
    "iso:country":"CN",
    "name:und_x_variant":[
        "Wangjiawan",
        "Wangjiatang"
    ],
    "name:zho_x_preferred":[
        "\u738b\u5bb6\u5858"
    ],
    "wof:name":"Wangjiatang",
    "wof:placetype":"locality"
},
  "geometry": {"coordinates":[119.88056,27.57083],"type":"Point"}
}