{
  "type": "Feature",
  "properties": {
    "gn:admin1_code":"2.0",
    "gn:asciiname":"Yanziling",
    "gn:country_code":"CN",
    "gn:dem":72,
    "gn:feature_class":"P",
    "gn:feature_code":"PPL",
    "gn:name":"Yanziling",
    "gn:population":0,
    "gn:timezone":"Asia/Shanghai",
    "iso:country":"CN",
    "name:zho_x_preferred":[
        "\u71d5\u5b50\u5cad"
    ],
    "wof:name":"Yanziling",
    "wof:placetype":"locality"
},
  "geometry": {"coordinates":[119.81229,29.19272],"type":"Point"}
}