{
  "type": "Feature",
  "properties": {
    "gn:admin1_code":"30",
    "gn:asciiname":"Changfa",
    "gn:country_code":"CN",
    "gn:dem":20,
    "gn:feature_class":"P",
    "gn:feature_code":"PPL",
    "gn:name":"Changfa",
    "gn:population":0,
    "gn:timezone":"Asia/Urumqi",
    "iso:country":"CN",
    "name:zho_x_preferred":[
        "\u660c\u53d1"
    ],
    "wof:name":"Changfa",
    "wof:placetype":"locality"
},
  "geometry": {"coordinates":[110.36583,20.32333],"type":"Point"}
}