{
  "type": "Feature",
  "properties": {
    "gn:admin1_code":"29.0",
    "gn:asciiname":"Damabu",
    "gn:country_code":"CN",
    "gn:dem":1945,
    "gn:feature_class":"P",
    "gn:feature_code":"PPL",
    "gn:name":"Damabu",
    "gn:population":0,
    "gn:timezone":"Asia/Shanghai",
    "iso:country":"CN",
    "name:zho_x_preferred":[
        "\u6253\u9ebb\u5e03"
    ],
    "wof:name":"Damabu",
    "wof:placetype":"locality"
},
  "geometry": {"coordinates":[100.599,23.9894],"type":"Point"}
}