{
  "type": "Feature",
  "properties": {
    "gn:admin1_code":"12.0",
    "gn:asciiname":"Huangtutang",
    "gn:country_code":"CN",
    "gn:dem":337,
    "gn:feature_class":"P",
    "gn:feature_code":"PPL",
    "gn:name":"Huangtutang",
    "gn:population":0,
    "gn:timezone":"Asia/Shanghai",
    "iso:country":"CN",
    "name:zho_x_preferred":[
        "Huangtutang"
    ],
    "name:zho_x_variant":[
        "\u9ec4\u571f\u5858"
    ],
    "wof:name":"Huangtutang",
    "wof:placetype":"locality"
},
  "geometry": {"coordinates":[115.15631999999999,29.99261],"type":"Point"}
}