{
  "type": "Feature",
  "properties": {
    "gn:admin1_code":"19.0",
    "gn:asciiname":"Minzhu",
    "gn:country_code":"CN",
    "gn:dem":350,
    "gn:feature_class":"P",
    "gn:feature_code":"PPL",
    "gn:name":"Minzhu",
    "gn:population":0,
    "gn:timezone":"Asia/Shanghai",
    "iso:country":"CN",
    "name:und_x_variant":[
        "\u6c11\u4e3b"
    ],
    "wof:name":"Minzhu",
    "wof:placetype":"locality"
},
  "geometry": {"coordinates":[124.52531,41.27007],"type":"Point"}
}