{
  "type": "Feature",
  "properties": {
    "gn:admin1_code":"2.0",
    "gn:asciiname":"Dalou",
    "gn:country_code":"CN",
    "gn:dem":317,
    "gn:feature_class":"P",
    "gn:feature_code":"PPL",
    "gn:name":"Dalou",
    "gn:population":0,
    "gn:timezone":"Asia/Shanghai",
    "iso:country":"CN",
    "name:und_x_variant":[
        "\u5927\u697c",
        "Dalou"
    ],
    "wof:name":"Dalou",
    "wof:placetype":"locality"
},
  "geometry": {"coordinates":[119.83031,29.53889],"type":"Point"}
}