{
  "type": "Feature",
  "properties": {
    "gn:admin1_code":"20.0",
    "gn:asciiname":"Tianyuanhao",
    "gn:country_code":"CN",
    "gn:dem":1660,
    "gn:feature_class":"P",
    "gn:feature_code":"PPL",
    "gn:name":"Tianyuanhao",
    "gn:population":0,
    "gn:timezone":"Asia/Shanghai",
    "iso:country":"CN",
    "name:und_x_variant":[
        "\u5929\u5143\u53f7"
    ],
    "wof:name":"Tianyuanhao",
    "wof:placetype":"locality"
},
  "geometry": {"coordinates":[111.58674999999999,41.08452],"type":"Point"}
}