{
  "type": "Feature",
  "properties": {
    "gn:admin1_code":"14.0",
    "gn:asciiname":"Luobucun",
    "gn:country_code":"CN",
    "gn:dem":4831,
    "gn:feature_class":"P",
    "gn:feature_code":"PPL",
    "gn:name":"Luobucun",
    "gn:population":0,
    "gn:timezone":"Asia/Urumqi",
    "iso:country":"CN",
    "name:zho_x_preferred":[
        "\u6d1b\u5e03\u6751"
    ],
    "wof:name":"Luobucun",
    "wof:placetype":"locality"
},
  "geometry": {"coordinates":[92.13933,32.13023],"type":"Point"}
}