{
  "type": "Feature",
  "properties": {
    "gn:admin1_code":"6.0",
    "gn:asciiname":"Tanggama",
    "gn:country_code":"CN",
    "gn:dem":3915,
    "gn:feature_class":"P",
    "gn:feature_code":"PPL",
    "gn:name":"Tanggama",
    "gn:population":0,
    "gn:timezone":"Asia/Shanghai",
    "iso:country":"CN",
    "name:zho_x_preferred":[
        "\u5858\u5c15\u739b"
    ],
    "wof:name":"Tanggama",
    "wof:placetype":"locality"
},
  "geometry": {"coordinates":[100.38970999999999,33.13304],"type":"Point"}
}