{
  "type": "Feature",
  "properties": {
    "gn:admin1_code":"7.0",
    "gn:asciiname":"Baiyedi",
    "gn:country_code":"CN",
    "gn:dem":669,
    "gn:feature_class":"P",
    "gn:feature_code":"PPL",
    "gn:name":"Baiyedi",
    "gn:population":0,
    "gn:timezone":"Asia/Shanghai",
    "iso:country":"CN",
    "name:zho_x_preferred":[
        "\u767d\u53f6\u5e95"
    ],
    "wof:name":"Baiyedi",
    "wof:placetype":"locality"
},
  "geometry": {"coordinates":[117.17957,24.43136],"type":"Point"}
}