{
  "type": "Feature",
  "properties": {
    "gn:admin1_code":"12.0",
    "gn:asciiname":"Huangshidong",
    "gn:country_code":"CN",
    "gn:dem":215,
    "gn:feature_class":"P",
    "gn:feature_code":"PPL",
    "gn:name":"Huangshidong",
    "gn:population":0,
    "gn:timezone":"Asia/Shanghai",
    "iso:country":"CN",
    "name:zho_x_preferred":[
        "Huangshidong"
    ],
    "name:zho_x_variant":[
        "\u9ec4\u72ee\u6d1e"
    ],
    "wof:name":"Huangshidong",
    "wof:placetype":"locality"
},
  "geometry": {"coordinates":[114.27485,29.6924],"type":"Point"}
}