{
  "type": "Feature",
  "properties": {
    "gn:admin1_code":"12.0",
    "gn:asciiname":"Malukou",
    "gn:country_code":"CN",
    "gn:dem":550,
    "gn:feature_class":"P",
    "gn:feature_code":"PPL",
    "gn:name":"Malukou",
    "gn:population":0,
    "gn:timezone":"Asia/Shanghai",
    "iso:country":"CN",
    "name:zho_x_preferred":[
        "\u9a6c\u8def\u53e3"
    ],
    "wof:name":"Malukou",
    "wof:placetype":"locality"
},
  "geometry": {"coordinates":[109.46477,30.18128],"type":"Point"}
}