{
  "type": "Feature",
  "properties": {
    "gn:admin1_code":"14.0",
    "gn:asciiname":"Raocun",
    "gn:country_code":"CN",
    "gn:dem":4395,
    "gn:feature_class":"P",
    "gn:feature_code":"PPL",
    "gn:name":"Raocun",
    "gn:population":0,
    "gn:timezone":"Asia/Urumqi",
    "iso:country":"CN",
    "name:zho_x_preferred":[
        "\u7ed5\u6751"
    ],
    "wof:name":"Raocun",
    "wof:placetype":"locality"
},
  "geometry": {"coordinates":[94.97002999999999,30.85896],"type":"Point"}
}