{
  "type": "Feature",
  "properties": {
    "gn:admin1_code":"18.0",
    "gn:asciiname":"Dalukan",
    "gn:country_code":"CN",
    "gn:dem":890,
    "gn:feature_class":"P",
    "gn:feature_code":"PPL",
    "gn:name":"Dalukan",
    "gn:population":0,
    "gn:timezone":"Asia/Shanghai",
    "iso:country":"CN",
    "name:zho_x_preferred":[
        "\u5927\u8def\u574e"
    ],
    "wof:name":"Dalukan",
    "wof:placetype":"locality"
},
  "geometry": {"coordinates":[108.461,27.4037],"type":"Point"}
}