{
  "type": "Feature",
  "properties": {
    "gn:admin1_code":"16.0",
    "gn:asciiname":"Fuluzhai",
    "gn:country_code":"CN",
    "gn:dem":131,
    "gn:feature_class":"P",
    "gn:feature_code":"PPL",
    "gn:name":"Fuluzhai",
    "gn:population":0,
    "gn:timezone":"Asia/Shanghai",
    "iso:country":"CN",
    "name:zho_x_preferred":[
        "\u6276\u82a6\u5be8"
    ],
    "wof:name":"Fuluzhai",
    "wof:placetype":"locality"
},
  "geometry": {"coordinates":[109.13200000000001,25.0024],"type":"Point"}
}