{
  "type": "Feature",
  "properties": {
    "gn:admin1_code":"9",
    "gn:asciiname":"Zhaopulou",
    "gn:country_code":"CN",
    "gn:dem":54,
    "gn:feature_class":"P",
    "gn:feature_code":"PPL",
    "gn:name":"Zhaopulou",
    "gn:population":0,
    "gn:timezone":"Asia/Shanghai",
    "iso:country":"CN",
    "name:zho_x_preferred":[
        "\u8d75\u666e\u697c"
    ],
    "wof:name":"Zhaopulou",
    "wof:placetype":"locality"
},
  "geometry": {"coordinates":[115.428,34.3211],"type":"Point"}
}