{
  "type": "Feature",
  "properties": {
    "gn:admin1_code":"8.0",
    "gn:asciiname":"Tianfacun",
    "gn:country_code":"CN",
    "gn:dem":60,
    "gn:feature_class":"P",
    "gn:feature_code":"PPL",
    "gn:name":"Tianfacun",
    "gn:population":0,
    "gn:timezone":"Asia/Shanghai",
    "iso:country":"CN",
    "name:zho_x_preferred":[
        "\u7530\u53d1\u6751"
    ],
    "wof:name":"Tianfacun",
    "wof:placetype":"locality"
},
  "geometry": {"coordinates":[132.16423999999998,47.16939],"type":"Point"}
}