{
  "type": "Feature",
  "properties": {
    "gn:admin1_code":"9",
    "gn:asciiname":"Caiyoufang",
    "gn:country_code":"CN",
    "gn:dem":67,
    "gn:feature_class":"P",
    "gn:feature_code":"PPL",
    "gn:name":"Caiyoufang",
    "gn:population":0,
    "gn:timezone":"Asia/Shanghai",
    "iso:country":"CN",
    "name:zho_x_preferred":[
        "\u8521\u6cb9\u574a"
    ],
    "wof:name":"Caiyoufang",
    "wof:placetype":"locality"
},
  "geometry": {"coordinates":[115.31399999999999,34.7315],"type":"Point"}
}