{
  "type": "Feature",
  "properties": {
    "gn:admin1_code":"29",
    "gn:asciiname":"Pianjiao",
    "gn:cc2":"CN",
    "gn:country_code":"CN",
    "gn:dem":1475,
    "gn:feature_class":"P",
    "gn:feature_code":"PPL",
    "gn:name":"Pianjiao",
    "gn:population":0,
    "gn:timezone":"Asia/Shanghai",
    "iso:country":"CN",
    "name:und_x_variant":[
        "P\u2019ien-chiao-chieh",
        "P\u2019ien-chiao",
        "Pianjiaojie",
        "Pianjiao"
    ],
    "wof:name":"Pianjiao",
    "wof:placetype":"locality"
},
  "geometry": {"coordinates":[100.58333,26.01667],"type":"Point"}
}