{
  "type": "Feature",
  "properties": {
    "gn:admin1_code":"33",
    "gn:asciiname":"Tanjia",
    "gn:country_code":"CN",
    "gn:dem":251,
    "gn:feature_class":"P",
    "gn:feature_code":"PPLA4",
    "gn:name":"Tanjia",
    "gn:population":0,
    "gn:timezone":"Asia/Shanghai",
    "iso:country":"CN",
    "name:und_x_variant":[
        "T\u2019an-chia-pa",
        "Tanjia",
        "Tanjia Xiang"
    ],
    "name:zho_x_preferred":[
        "\u8c2d\u5bb6"
    ],
    "name:zho_x_variant":[
        "\u8c2d\u5bb6\u4e61"
    ],
    "wof:name":"Tanjia",
    "wof:placetype":"locality"
},
  "geometry": {"coordinates":[108.49861,31.45574],"type":"Point"}
}