{
  "type": "Feature",
  "properties": {
    "gn:admin1_code":"19.0",
    "gn:asciiname":"Xitangjiatun",
    "gn:country_code":"CN",
    "gn:dem":52,
    "gn:feature_class":"P",
    "gn:feature_code":"PPL",
    "gn:name":"Xitangjiatun",
    "gn:population":0,
    "gn:timezone":"Asia/Shanghai",
    "iso:country":"CN",
    "name:und_x_variant":[
        "\u897f\u5510\u5bb6\u5c6f"
    ],
    "name:zho_x_preferred":[
        "\u897f\u5510\u5bb6\u5c6f"
    ],
    "wof:name":"Xitangjiatun",
    "wof:placetype":"locality"
},
  "geometry": {"coordinates":[122.47074000000001,39.7352],"type":"Point"}
}