{
  "type": "Feature",
  "properties": {
    "gn:admin1_code":"3",
    "gn:asciiname":"Yunling Shangbao",
    "gn:country_code":"CN",
    "gn:dem":122,
    "gn:feature_class":"P",
    "gn:feature_code":"PPL",
    "gn:name":"Yunling Shangbao",
    "gn:population":0,
    "gn:timezone":"Asia/Shanghai",
    "iso:country":"CN",
    "name:und_x_variant":[
        "\u4e91\u5cad\u4e0a\u4fdd",
        "Shangbao"
    ],
    "wof:name":"Yunling Shangbao",
    "wof:placetype":"locality"
},
  "geometry": {"coordinates":[116.49166,27.3988],"type":"Point"}
}