{
  "type": "Feature",
  "properties": {
    "gn:admin1_code":"18",
    "gn:asciiname":"Gaojinggou",
    "gn:country_code":"CN",
    "gn:dem":817,
    "gn:feature_class":"P",
    "gn:feature_code":"PPL",
    "gn:name":"Gaojinggou",
    "gn:population":0,
    "gn:timezone":"Asia/Shanghai",
    "iso:country":"CN",
    "name:zho_x_preferred":[
        "\u9ad8\u4e95\u6c9f"
    ],
    "wof:name":"Gaojinggou",
    "wof:placetype":"locality"
},
  "geometry": {"coordinates":[107.85599999999999,28.2964],"type":"Point"}
}