{
  "type": "Feature",
  "properties": {
    "gn:admin1_code":"1.0",
    "gn:asciiname":"Zhangyingcun",
    "gn:country_code":"CN",
    "gn:dem":46,
    "gn:feature_class":"P",
    "gn:feature_code":"PPL",
    "gn:name":"Zhangyingcun",
    "gn:population":0,
    "gn:timezone":"Asia/Shanghai",
    "iso:country":"CN",
    "name:zho_x_preferred":[
        "\u5f20\u90e2\u6751"
    ],
    "wof:name":"Zhangyingcun",
    "wof:placetype":"locality"
},
  "geometry": {"coordinates":[117.0526,32.22433],"type":"Point"}
}