{
  "type": "Feature",
  "properties": {
    "gn:admin1_code":"9.0",
    "gn:asciiname":"Shanxian Laocheng",
    "gn:country_code":"CN",
    "gn:dem":334,
    "gn:feature_class":"P",
    "gn:feature_code":"PPL",
    "gn:name":"Shanxian Laocheng",
    "gn:population":0,
    "gn:timezone":"Asia/Shanghai",
    "iso:country":"CN",
    "name:zho_x_preferred":[
        "\u9655\u53bf\u8001\u57ce"
    ],
    "wof:name":"Shanxian Laocheng",
    "wof:placetype":"locality"
},
  "geometry": {"coordinates":[111.14258999999998,34.79269],"type":"Point"}
}