{
  "type": "Feature",
  "properties": {
    "gn:admin1_code":"14.0",
    "gn:asciiname":"Yeyong",
    "gn:country_code":"CN",
    "gn:dem":3926,
    "gn:feature_class":"P",
    "gn:feature_code":"PPL",
    "gn:name":"Yeyong",
    "gn:population":0,
    "gn:timezone":"Asia/Urumqi",
    "iso:country":"CN",
    "name:zho_x_preferred":[
        "\u4e5f\u52c7"
    ],
    "wof:name":"Yeyong",
    "wof:placetype":"locality"
},
  "geometry": {"coordinates":[96.51506000000001,30.41368],"type":"Point"}
}