{
  "type": "Feature",
  "properties": {
    "gn:admin1_code":"24.0",
    "gn:asciiname":"Conggou",
    "gn:country_code":"CN",
    "gn:dem":1849,
    "gn:feature_class":"P",
    "gn:feature_code":"PPL",
    "gn:name":"Conggou",
    "gn:population":0,
    "gn:timezone":"Asia/Shanghai",
    "iso:country":"CN",
    "name:und_x_variant":[
        "\u8471\u6c9f"
    ],
    "name:zho_x_preferred":[
        "\u8471\u6c9f"
    ],
    "wof:name":"Conggou",
    "wof:placetype":"locality"
},
  "geometry": {"coordinates":[112.33767,38.64763],"type":"Point"}
}