{
  "type": "Feature",
  "properties": {
    "gn:admin1_code":"15.0",
    "gn:asciiname":"Xingjia Gouquan",
    "gn:country_code":"CN",
    "gn:dem":1505,
    "gn:feature_class":"P",
    "gn:feature_code":"PPL",
    "gn:name":"Xingjia Gouquan",
    "gn:population":0,
    "gn:timezone":"Asia/Shanghai",
    "iso:country":"CN",
    "name:zho_x_preferred":[
        "\u90a2\u5bb6\u6c9f\u5708"
    ],
    "wof:name":"Xingjia Gouquan",
    "wof:placetype":"locality"
},
  "geometry": {"coordinates":[107.60599999999999,35.9458],"type":"Point"}
}