{
  "type": "Feature",
  "properties": {
    "gn:admin1_code":"3.0",
    "gn:asciiname":"Luxia",
    "gn:country_code":"CN",
    "gn:dem":34,
    "gn:feature_class":"P",
    "gn:feature_code":"PPL",
    "gn:name":"Luxia",
    "gn:population":0,
    "gn:timezone":"Asia/Shanghai",
    "iso:country":"CN",
    "name:und_x_variant":[
        "\u8def\u4e0b"
    ],
    "wof:name":"Luxia",
    "wof:placetype":"locality"
},
  "geometry": {"coordinates":[115.38001,28.04554000000001],"type":"Point"}
}