{
  "type": "Feature",
  "properties": {
    "gn:admin1_code":"19.0",
    "gn:asciiname":"Beiqianjia",
    "gn:country_code":"CN",
    "gn:dem":16,
    "gn:feature_class":"P",
    "gn:feature_code":"PPL",
    "gn:name":"Beiqianjia",
    "gn:population":0,
    "gn:timezone":"Asia/Shanghai",
    "iso:country":"CN",
    "name:und_x_variant":[
        "\u5317\u94b1\u5bb6"
    ],
    "wof:name":"Beiqianjia",
    "wof:placetype":"locality"
},
  "geometry": {"coordinates":[122.67865999999999,40.89819],"type":"Point"}
}