{
  "type": "Feature",
  "properties": {
    "gn:admin1_code":"26.0",
    "gn:asciiname":"Yangpoli",
    "gn:country_code":"CN",
    "gn:dem":1138,
    "gn:feature_class":"P",
    "gn:feature_code":"PPL",
    "gn:name":"Yangpoli",
    "gn:population":0,
    "gn:timezone":"Asia/Shanghai",
    "iso:country":"CN",
    "name:und_x_variant":[
        "\u9633\u5761\u91cc"
    ],
    "wof:name":"Yangpoli",
    "wof:placetype":"locality"
},
  "geometry": {"coordinates":[107.17532,34.75879],"type":"Point"}
}