{
  "type": "Feature",
  "properties": {
    "gn:admin1_code":"5.0",
    "gn:asciiname":"Sanjiazitun",
    "gn:country_code":"CN",
    "gn:dem":186,
    "gn:feature_class":"P",
    "gn:feature_code":"PPL",
    "gn:name":"Sanjiazitun",
    "gn:population":0,
    "gn:timezone":"Asia/Shanghai",
    "iso:country":"CN",
    "name:zho_x_preferred":[
        "\u4e09\u5bb6\u5b50\u5c6f"
    ],
    "wof:name":"Sanjiazitun",
    "wof:placetype":"locality"
},
  "geometry": {"coordinates":[124.96653000000001,44.01492],"type":"Point"}
}