{
  "type": "Feature",
  "properties": {
    "gn:admin1_code":"12.0",
    "gn:asciiname":"Liujiachong",
    "gn:country_code":"CN",
    "gn:dem":1381,
    "gn:feature_class":"P",
    "gn:feature_code":"PPL",
    "gn:name":"Liujiachong",
    "gn:population":0,
    "gn:timezone":"Asia/Shanghai",
    "iso:country":"CN",
    "name:zho_x_preferred":[
        "\u5218\u5bb6\u51b2"
    ],
    "wof:name":"Liujiachong",
    "wof:placetype":"locality"
},
  "geometry": {"coordinates":[111.43832999999999,31.62871],"type":"Point"}
}