{
  "type": "Feature",
  "properties": {
    "gn:admin1_code":"30",
    "gn:asciiname":"Tuhu",
    "gn:country_code":"CN",
    "gn:dem":94,
    "gn:feature_class":"P",
    "gn:feature_code":"PPL",
    "gn:name":"Tuhu",
    "gn:population":0,
    "gn:timezone":"Asia/Shanghai",
    "iso:country":"CN",
    "name:ara_x_preferred":[
        "\u062a\u0648\u0647\u0648"
    ],
    "name:zho_x_preferred":[
        "\u571f\u6e56"
    ],
    "wof:name":"Tuhu",
    "wof:placetype":"locality"
},
  "geometry": {"coordinates":[114.15492999999999,23.70095],"type":"Point"}
}