{
  "type": "Feature",
  "properties": {
    "gn:admin1_code":"25",
    "gn:asciiname":"Mojiaya",
    "gn:country_code":"CN",
    "gn:dem":104,
    "gn:feature_class":"P",
    "gn:feature_code":"PPL",
    "gn:name":"Mojiaya",
    "gn:population":0,
    "gn:timezone":"Asia/Shanghai",
    "iso:country":"CN",
    "name:und_x_variant":[
        "\u83ab\u5bb6\u5d16"
    ],
    "wof:name":"Mojiaya",
    "wof:placetype":"locality"
},
  "geometry": {"coordinates":[119.09192,35.93096],"type":"Point"}
}