{
  "type": "Feature",
  "properties": {
    "gn:admin1_code":"18",
    "gn:asciiname":"Tongqing",
    "gn:country_code":"CN",
    "gn:dem":655,
    "gn:feature_class":"P",
    "gn:feature_code":"PPL",
    "gn:name":"Tongqing",
    "gn:population":0,
    "gn:timezone":"Asia/Shanghai",
    "iso:country":"CN",
    "name:zho_x_preferred":[
        "\u6850\u6e05"
    ],
    "wof:name":"Tongqing",
    "wof:placetype":"locality"
},
  "geometry": {"coordinates":[107.917,27.9638],"type":"Point"}
}