{
  "type": "Feature",
  "properties": {
    "gn:admin1_code":"21.0",
    "gn:asciiname":"Fantai",
    "gn:country_code":"CN",
    "gn:dem":1832,
    "gn:feature_class":"P",
    "gn:feature_code":"PPL",
    "gn:name":"Fantai",
    "gn:population":0,
    "gn:timezone":"Asia/Shanghai",
    "iso:country":"CN",
    "name:zho_x_preferred":[
        "\u8303\u53f0"
    ],
    "wof:name":"Fantai",
    "wof:placetype":"locality"
},
  "geometry": {"coordinates":[105.423,36.6397],"type":"Point"}
}