{
  "type": "Feature",
  "properties": {
    "gn:admin1_code":"18.0",
    "gn:asciiname":"Demu",
    "gn:country_code":"CN",
    "gn:dem":876,
    "gn:feature_class":"P",
    "gn:feature_code":"PPL",
    "gn:name":"Demu",
    "gn:population":0,
    "gn:timezone":"Asia/Shanghai",
    "iso:country":"CN",
    "name:zho_x_preferred":[
        "\u7684\u6bcd"
    ],
    "wof:name":"Demu",
    "wof:placetype":"locality"
},
  "geometry": {"coordinates":[107.872,25.6996],"type":"Point"}
}