{
  "type": "Feature",
  "properties": {
    "gn:admin1_code":"16",
    "gn:asciiname":"Huajiang Yaozuxiang",
    "gn:country_code":"CN",
    "gn:dem":277,
    "gn:feature_class":"P",
    "gn:feature_code":"PPL",
    "gn:name":"Huajiang Yaozuxiang",
    "gn:population":0,
    "gn:timezone":"Asia/Shanghai",
    "iso:country":"CN",
    "wof:name":"Huajiang Yaozuxiang",
    "wof:placetype":"locality"
},
  "geometry": {"coordinates":[110.46472,25.77083],"type":"Point"}
}