{
  "type": "Feature",
  "properties": {
    "gn:admin1_code":"5.0",
    "gn:asciiname":"Jinkuang",
    "gn:country_code":"CN",
    "gn:dem":436,
    "gn:feature_class":"P",
    "gn:feature_code":"PPL",
    "gn:name":"Jinkuang",
    "gn:population":0,
    "gn:timezone":"Asia/Shanghai",
    "iso:country":"CN",
    "name:und_x_variant":[
        "\u91d1\u77ff"
    ],
    "wof:name":"Jinkuang",
    "wof:placetype":"locality"
},
  "geometry": {"coordinates":[129.30399,43.73586],"type":"Point"}
}