{
  "type": "Feature",
  "properties": {
    "gn:admin1_code":"4.0",
    "gn:asciiname":"Tianqicun",
    "gn:country_code":"CN",
    "gn:dem":37,
    "gn:feature_class":"P",
    "gn:feature_code":"PPL",
    "gn:name":"Tianqicun",
    "gn:population":0,
    "gn:timezone":"Asia/Shanghai",
    "iso:country":"CN",
    "name:zho_x_preferred":[
        "\u5929\u9f50\u6751"
    ],
    "wof:name":"Tianqicun",
    "wof:placetype":"locality"
},
  "geometry": {"coordinates":[117.15318000000001,34.31209],"type":"Point"}
}