{
  "type": "Feature",
  "properties": {
    "gn:admin1_code":"11.0",
    "gn:asciiname":"Xiongjiata",
    "gn:country_code":"CN",
    "gn:dem":496,
    "gn:feature_class":"P",
    "gn:feature_code":"PPL",
    "gn:name":"Xiongjiata",
    "gn:population":0,
    "gn:timezone":"Asia/Shanghai",
    "iso:country":"CN",
    "name:zho_x_preferred":[
        "Xiongjiata"
    ],
    "name:zho_x_variant":[
        "\u718a\u5bb6\u5854"
    ],
    "wof:name":"Xiongjiata",
    "wof:placetype":"locality"
},
  "geometry": {"coordinates":[110.36603999999998,28.95024],"type":"Point"}
}