{
  "type": "Feature",
  "properties": {
    "gn:admin1_code":"5.0",
    "gn:asciiname":"Qiangu Luhua",
    "gn:country_code":"CN",
    "gn:dem":197,
    "gn:feature_class":"P",
    "gn:feature_code":"PPL",
    "gn:name":"Qiangu Luhua",
    "gn:population":0,
    "gn:timezone":"Asia/Shanghai",
    "iso:country":"CN",
    "name:zho_x_preferred":[
        "\u524d\u53e4\u9c81\u5316"
    ],
    "wof:name":"Qiangu Luhua",
    "wof:placetype":"locality"
},
  "geometry": {"coordinates":[124.12009,44.31547],"type":"Point"}
}