{
  "type": "Feature",
  "properties": {
    "gn:admin1_code":"14.0",
    "gn:asciiname":"Menduicun",
    "gn:country_code":"CN",
    "gn:dem":4455,
    "gn:feature_class":"P",
    "gn:feature_code":"PPL",
    "gn:name":"Menduicun",
    "gn:population":0,
    "gn:timezone":"Asia/Urumqi",
    "iso:country":"CN",
    "name:zho_x_preferred":[
        "\u95e8\u5806\u6751"
    ],
    "wof:name":"Menduicun",
    "wof:placetype":"locality"
},
  "geometry": {"coordinates":[90.90682,30.07039],"type":"Point"}
}