{
  "type": "Feature",
  "properties": {
    "gn:admin1_code":"3.0",
    "gn:asciiname":"Genggushui",
    "gn:country_code":"CN",
    "gn:dem":215,
    "gn:feature_class":"P",
    "gn:feature_code":"PPL",
    "gn:name":"Genggushui",
    "gn:population":0,
    "gn:timezone":"Asia/Shanghai",
    "iso:country":"CN",
    "name:und_x_variant":[
        "\u66f4\u9f13\u6c34"
    ],
    "wof:name":"Genggushui",
    "wof:placetype":"locality"
},
  "geometry": {"coordinates":[115.49639000000001,26.36933],"type":"Point"}
}