{
  "type": "Feature",
  "properties": {
    "gn:admin1_code":"33.0",
    "gn:asciiname":"Xuanwu",
    "gn:country_code":"CN",
    "gn:dem":959,
    "gn:feature_class":"P",
    "gn:feature_code":"PPL",
    "gn:name":"Xuanwu",
    "gn:population":0,
    "gn:timezone":"Asia/Shanghai",
    "iso:country":"CN",
    "name:ceb_x_preferred":[
        "Xuanwu"
    ],
    "name:deu_x_preferred":[
        "Xuanwu"
    ],
    "name:fra_x_preferred":[
        "Xuanwu"
    ],
    "name:jpn_x_preferred":[
        "\u7384\u6b66"
    ],
    "name:nor_x_preferred":[
        "Xuanwu"
    ],
    "name:pol_x_preferred":[
        "Xuanwu"
    ],
    "name:rus_x_preferred":[
        "\u0421\u044e\u0430\u043d\u044c\u0443"
    ],
    "name:swe_x_preferred":[
        "Xuanwu"
    ],
    "name:vie_x_preferred":[
        "Huy\u1ec1n V\u0169"
    ],
    "name:zho_x_preferred":[
        "\u7384\u6b66"
    ],
    "wof:name":"Xuanwu",
    "wof:placetype":"locality"
},
  "geometry": {"coordinates":[106.49043,28.65673],"type":"Point"}
}