{
  "type": "Feature",
  "properties": {
    "gn:admin1_code":"12.0",
    "gn:asciiname":"Meizishu",
    "gn:country_code":"CN",
    "gn:dem":510,
    "gn:feature_class":"P",
    "gn:feature_code":"PPL",
    "gn:name":"Meizishu",
    "gn:population":0,
    "gn:timezone":"Asia/Shanghai",
    "iso:country":"CN",
    "name:zho_x_preferred":[
        "Meizishu"
    ],
    "name:zho_x_variant":[
        "\u6885\u5b50\u6811"
    ],
    "wof:name":"Meizishu",
    "wof:placetype":"locality"
},
  "geometry": {"coordinates":[109.32165000000001,29.38979],"type":"Point"}
}