{
  "type": "Feature",
  "properties": {
    "gn:admin1_code":"4.0",
    "gn:asciiname":"Jianggu",
    "gn:country_code":"CN",
    "gn:dem":0,
    "gn:feature_class":"P",
    "gn:feature_code":"PPL",
    "gn:name":"Jianggu",
    "gn:population":0,
    "gn:timezone":"Asia/Shanghai",
    "iso:country":"CN",
    "name:zho_x_preferred":[
        "Jianggu"
    ],
    "name:zho_x_variant":[
        "\u848b\u987e"
    ],
    "wof:name":"Jianggu",
    "wof:placetype":"locality"
},
  "geometry": {"coordinates":[119.92104,33.78491],"type":"Point"}
}