{
  "type": "Feature",
  "properties": {
    "gn:admin1_code":"12",
    "gn:asciiname":"Fengxi",
    "gn:country_code":"CN",
    "gn:dem":790,
    "gn:feature_class":"P",
    "gn:feature_code":"PPLA4",
    "gn:name":"Fengxi",
    "gn:population":0,
    "gn:timezone":"Asia/Shanghai",
    "iso:country":"CN",
    "name:und_x_variant":[
        "Fengxi Zhen"
    ],
    "name:zho_x_preferred":[
        "\u4e30\u6eaa"
    ],
    "name:zho_x_variant":[
        "\u4e30\u6eaa\u9547"
    ],
    "wof:name":"Fengxi",
    "wof:placetype":"locality"
},
  "geometry": {"coordinates":[109.70222,31.87527],"type":"Point"}
}