{
  "type": "Feature",
  "properties": {
    "gn:admin1_code":"12.0",
    "gn:asciiname":"Zhulinzui",
    "gn:country_code":"CN",
    "gn:dem":39,
    "gn:feature_class":"P",
    "gn:feature_code":"PPL",
    "gn:name":"Zhulinzui",
    "gn:population":0,
    "gn:timezone":"Asia/Shanghai",
    "iso:country":"CN",
    "name:zho_x_preferred":[
        "Zhulinzui"
    ],
    "name:zho_x_variant":[
        "\u7af9\u6797\u5480"
    ],
    "wof:name":"Zhulinzui",
    "wof:placetype":"locality"
},
  "geometry": {"coordinates":[115.42068,29.74157],"type":"Point"}
}