{
  "type": "Feature",
  "properties": {
    "gn:admin1_code":"03",
    "gn:asciiname":"Guxiandu",
    "gn:country_code":"CN",
    "gn:dem":24,
    "gn:feature_class":"P",
    "gn:feature_code":"PPL",
    "gn:name":"Guxiandu",
    "gn:population":0,
    "gn:timezone":"Asia/Shanghai",
    "iso:country":"CN",
    "name:und_x_variant":[
        "Ku-hsien-tu",
        "Guxiandu",
        "\u53e4\u53bf\u6e21",
        "Guxianduzhen",
        "\u53e4\u53bf\u6e21\u9547"
    ],
    "wof:name":"Guxiandu",
    "wof:placetype":"locality"
},
  "geometry": {"coordinates":[116.86586,29.07894000000001],"type":"Point"}
}