{
  "type": "Feature",
  "properties": {
    "gn:admin1_code":"14.0",
    "gn:asciiname":"Deri Niuchang",
    "gn:country_code":"CN",
    "gn:dem":4199,
    "gn:feature_class":"P",
    "gn:feature_code":"PPLF",
    "gn:name":"Deri Niuchang",
    "gn:population":0,
    "gn:timezone":"Asia/Urumqi",
    "iso:country":"CN",
    "name:zho_x_preferred":[
        "\u5f97\u65e5\u725b\u573a"
    ],
    "wof:name":"Deri Niuchang",
    "wof:placetype":"locality"
},
  "geometry": {"coordinates":[98.21006,30.62112],"type":"Point"}
}