{
  "type": "Feature",
  "properties": {
    "gn:admin1_code":"16.0",
    "gn:asciiname":"Zhaoya",
    "gn:country_code":"CN",
    "gn:dem":7,
    "gn:feature_class":"P",
    "gn:feature_code":"PPL",
    "gn:name":"Zhaoya",
    "gn:population":0,
    "gn:timezone":"Asia/Shanghai",
    "iso:country":"CN",
    "name:zho_x_preferred":[
        "\u5146\u96c5"
    ],
    "wof:name":"Zhaoya",
    "wof:placetype":"locality"
},
  "geometry": {"coordinates":[108.42100000000001,21.9506],"type":"Point"}
}