{
  "type": "Feature",
  "properties": {
    "gn:admin1_code":"33.0",
    "gn:asciiname":"Lanyuan",
    "gn:country_code":"CN",
    "gn:dem":892,
    "gn:feature_class":"P",
    "gn:feature_code":"PPL",
    "gn:name":"Lanyuan",
    "gn:population":0,
    "gn:timezone":"Asia/Shanghai",
    "iso:country":"CN",
    "name:zho_x_preferred":[
        "\u5170\u56ed"
    ],
    "wof:name":"Lanyuan",
    "wof:placetype":"locality"
},
  "geometry": {"coordinates":[108.37000999999999,29.01087],"type":"Point"}
}