{
  "type": "Feature",
  "properties": {
    "gn:admin1_code":"11.0",
    "gn:asciiname":"Zhujia Shankou",
    "gn:country_code":"CN",
    "gn:dem":36,
    "gn:feature_class":"P",
    "gn:feature_code":"PPL",
    "gn:name":"Zhujia Shankou",
    "gn:population":0,
    "gn:timezone":"Asia/Shanghai",
    "iso:country":"CN",
    "name:zho_x_preferred":[
        "Zhujia Shankou"
    ],
    "name:zho_x_variant":[
        "\u6731\u5bb6\u5c71\u53e3"
    ],
    "wof:name":"Zhujia Shankou",
    "wof:placetype":"locality"
},
  "geometry": {"coordinates":[111.81974,29.79441],"type":"Point"}
}