{
  "type": "Feature",
  "properties": {
    "gn:admin1_code":"19.0",
    "gn:asciiname":"Yinhugoucun",
    "gn:country_code":"CN",
    "gn:dem":511,
    "gn:feature_class":"P",
    "gn:feature_code":"PPL",
    "gn:name":"Yinhugoucun",
    "gn:population":0,
    "gn:timezone":"Asia/Shanghai",
    "iso:country":"CN",
    "name:zho_x_preferred":[
        "\u94f6\u864e\u6c9f\u6751"
    ],
    "wof:name":"Yinhugoucun",
    "wof:placetype":"locality"
},
  "geometry": {"coordinates":[125.366,42.1047],"type":"Point"}
}