{
  "type": "Feature",
  "properties": {
    "gn:admin1_code":"25",
    "gn:asciiname":"Dong'antian",
    "gn:country_code":"CN",
    "gn:dem":147,
    "gn:feature_class":"P",
    "gn:feature_code":"PPL",
    "gn:name":"Dong\u2019antian",
    "gn:population":0,
    "gn:timezone":"Asia/Shanghai",
    "iso:country":"CN",
    "name:und_x_variant":[
        "Dong\u2019antian"
    ],
    "name:zho_x_preferred":[
        "\u4e1c\u5b89\u7530"
    ],
    "wof:name":"Dong'antian",
    "wof:placetype":"locality"
},
  "geometry": {"coordinates":[117.878,35.1861],"type":"Point"}
}