{
  "type": "Feature",
  "properties": {
    "gn:admin1_code":"16.0",
    "gn:asciiname":"Bozhu",
    "gn:country_code":"CN",
    "gn:dem":65,
    "gn:feature_class":"P",
    "gn:feature_code":"PPL",
    "gn:name":"Bozhu",
    "gn:population":0,
    "gn:timezone":"Asia/Shanghai",
    "iso:country":"CN",
    "name:zho_x_preferred":[
        "\u7b94\u7af9"
    ],
    "wof:name":"Bozhu",
    "wof:placetype":"locality"
},
  "geometry": {"coordinates":[109.04900000000001,22.1668],"type":"Point"}
}