{
  "type": "Feature",
  "properties": {
    "gn:admin1_code":"29.0",
    "gn:asciiname":"Huizhuqing",
    "gn:country_code":"CN",
    "gn:dem":1638,
    "gn:feature_class":"P",
    "gn:feature_code":"PPL",
    "gn:name":"Huizhuqing",
    "gn:population":0,
    "gn:timezone":"Asia/Shanghai",
    "iso:country":"CN",
    "name:zho_x_preferred":[
        "\u7070\u7af9\u7b90"
    ],
    "wof:name":"Huizhuqing",
    "wof:placetype":"locality"
},
  "geometry": {"coordinates":[103.34399999999999,22.8759],"type":"Point"}
}