{
  "type": "Feature",
  "properties": {
    "gn:admin1_code":"16.0",
    "gn:asciiname":"Dapozhai",
    "gn:country_code":"CN",
    "gn:dem":119,
    "gn:feature_class":"P",
    "gn:feature_code":"PPL",
    "gn:name":"Dapozhai",
    "gn:population":0,
    "gn:timezone":"Asia/Shanghai",
    "iso:country":"CN",
    "name:zho_x_preferred":[
        "\u5927\u5761\u5be8"
    ],
    "wof:name":"Dapozhai",
    "wof:placetype":"locality"
},
  "geometry": {"coordinates":[109.383,25.1811],"type":"Point"}
}