{
  "type": "Feature",
  "properties": {
    "gn:admin1_code":"29.0",
    "gn:asciiname":"Azuobi",
    "gn:country_code":"CN",
    "gn:dem":2025,
    "gn:feature_class":"P",
    "gn:feature_code":"PPL",
    "gn:name":"Azuobi",
    "gn:population":0,
    "gn:timezone":"Asia/Shanghai",
    "iso:country":"CN",
    "name:zho_x_preferred":[
        "\u963f\u5de6\u5fc5"
    ],
    "wof:name":"Azuobi",
    "wof:placetype":"locality"
},
  "geometry": {"coordinates":[103.453,25.5175],"type":"Point"}
}