{
  "type": "Feature",
  "properties": {
    "gn:admin1_code":"1.0",
    "gn:asciiname":"Fuquancun",
    "gn:country_code":"CN",
    "gn:dem":13,
    "gn:feature_class":"P",
    "gn:feature_code":"PPL",
    "gn:name":"Fuquancun",
    "gn:population":0,
    "gn:timezone":"Asia/Shanghai",
    "iso:country":"CN",
    "name:zho_x_preferred":[
        "\u798f\u6cc9\u6751"
    ],
    "wof:name":"Fuquancun",
    "wof:placetype":"locality"
},
  "geometry": {"coordinates":[117.69611,31.33191],"type":"Point"}
}