{
  "type": "Feature",
  "properties": {
    "gn:admin1_code":"3.0",
    "gn:asciiname":"Zhaolinpu",
    "gn:country_code":"CN",
    "gn:dem":200,
    "gn:feature_class":"P",
    "gn:feature_code":"PPL",
    "gn:name":"Zhaolinpu",
    "gn:population":0,
    "gn:timezone":"Asia/Shanghai",
    "iso:country":"CN",
    "name:und_x_variant":[
        "\u7167\u6797\u94fa"
    ],
    "wof:name":"Zhaolinpu",
    "wof:placetype":"locality"
},
  "geometry": {"coordinates":[115.4109,29.13111],"type":"Point"}
}