{
  "type": "Feature",
  "properties": {
    "gn:admin1_code":"25.0",
    "gn:asciiname":"Xiche Menkuang",
    "gn:country_code":"CN",
    "gn:dem":67,
    "gn:feature_class":"P",
    "gn:feature_code":"PPL",
    "gn:name":"Xiche Menkuang",
    "gn:population":0,
    "gn:timezone":"Asia/Shanghai",
    "iso:country":"CN",
    "name:zho_x_preferred":[
        "\u897f\u8f66\u95e8\u593c"
    ],
    "wof:name":"Xiche Menkuang",
    "wof:placetype":"locality"
},
  "geometry": {"coordinates":[121.89185000000001,37.3768],"type":"Point"}
}