{
  "type": "Feature",
  "properties": {
    "gn:admin1_code":"29.0",
    "gn:asciiname":"Sharong",
    "gn:country_code":"CN",
    "gn:dem":3081,
    "gn:feature_class":"P",
    "gn:feature_code":"PPL",
    "gn:name":"Sharong",
    "gn:population":0,
    "gn:timezone":"Asia/Shanghai",
    "iso:country":"CN",
    "name:zho_x_preferred":[
        "\u6c99\u8363"
    ],
    "wof:name":"Sharong",
    "wof:placetype":"locality"
},
  "geometry": {"coordinates":[99.0998,28.6187],"type":"Point"}
}