{
  "type": "Feature",
  "properties": {
    "gn:admin1_code":"32.0",
    "gn:asciiname":"Jingoumiao",
    "gn:country_code":"CN",
    "gn:dem":329,
    "gn:feature_class":"P",
    "gn:feature_code":"PPL",
    "gn:name":"Jingoumiao",
    "gn:population":0,
    "gn:timezone":"Asia/Shanghai",
    "iso:country":"CN",
    "name:zho_x_preferred":[
        "\u91d1\u72d7\u5e99"
    ],
    "wof:name":"Jingoumiao",
    "wof:placetype":"locality"
},
  "geometry": {"coordinates":[105.29810000000001,28.80515],"type":"Point"}
}