{
  "type": "Feature",
  "properties": {
    "gn:admin1_code":"32.0",
    "gn:asciiname":"Nianke",
    "gn:country_code":"CN",
    "gn:dem":3968,
    "gn:feature_class":"P",
    "gn:feature_code":"PPL",
    "gn:name":"Nianke",
    "gn:population":0,
    "gn:timezone":"Asia/Shanghai",
    "iso:country":"CN",
    "name:zho_x_preferred":[
        "\u5e74\u514b"
    ],
    "wof:name":"Nianke",
    "wof:placetype":"locality"
},
  "geometry": {"coordinates":[101.81207000000001,31.86695],"type":"Point"}
}