{
  "type": "Feature",
  "properties": {
    "gn:admin1_code":"30",
    "gn:asciiname":"Dongfang",
    "gn:country_code":"CN",
    "gn:dem":141,
    "gn:feature_class":"P",
    "gn:feature_code":"PPL",
    "gn:name":"Dongfang",
    "gn:population":0,
    "gn:timezone":"Asia/Shanghai",
    "iso:country":"CN",
    "name:ceb_x_preferred":[
        "Dongfang"
    ],
    "name:deu_x_preferred":[
        "Dongfang"
    ],
    "name:nld_x_preferred":[
        "Dongfang"
    ],
    "name:swe_x_preferred":[
        "Dongfang"
    ],
    "wof:name":"Dongfang",
    "wof:placetype":"locality"
},
  "geometry": {"coordinates":[112.30583,21.81306],"type":"Point"}
}