{
  "type": "Feature",
  "properties": {
    "gn:admin1_code":"04",
    "gn:asciiname":"Jiaoxi",
    "gn:country_code":"CN",
    "gn:dem":38,
    "gn:feature_class":"P",
    "gn:feature_code":"PPL",
    "gn:name":"Jiaoxi",
    "gn:population":0,
    "gn:timezone":"Asia/Shanghai",
    "iso:country":"CN",
    "name:zho_x_preferred":[
        "\u7126\u6eaa"
    ],
    "wof:name":"Jiaoxi",
    "wof:placetype":"locality"
},
  "geometry": {"coordinates":[120.2094,31.83223],"type":"Point"}
}