{
  "type": "Feature",
  "properties": {
    "gn:admin1_code":"26",
    "gn:asciiname":"Daguping",
    "gn:country_code":"CN",
    "gn:dem":1260,
    "gn:feature_class":"P",
    "gn:feature_code":"PPL",
    "gn:name":"Daguping",
    "gn:population":0,
    "gn:timezone":"Asia/Shanghai",
    "iso:country":"CN",
    "name:und_x_variant":[
        "T\u2019ai-ku-p\u2019ing",
        "Ta-ku-p\u2019ing",
        "Daguping"
    ],
    "name:zho_x_preferred":[
        "\u5927\u53e4\u576a"
    ],
    "wof:name":"Daguping",
    "wof:placetype":"locality"
},
  "geometry": {"coordinates":[107.76161999999999,33.59791],"type":"Point"}
}