{
  "type": "Feature",
  "properties": {
    "gn:admin1_code":"9",
    "gn:asciiname":"Wanlou",
    "gn:country_code":"CN",
    "gn:dem":43,
    "gn:feature_class":"P",
    "gn:feature_code":"PPL",
    "gn:name":"Wanlou",
    "gn:population":0,
    "gn:timezone":"Asia/Shanghai",
    "iso:country":"CN",
    "name:zho_x_preferred":[
        "\u5b8c\u697c"
    ],
    "wof:name":"Wanlou",
    "wof:placetype":"locality"
},
  "geometry": {"coordinates":[115.557,33.9538],"type":"Point"}
}