{
  "type": "Feature",
  "properties": {
    "gn:admin1_code":"28",
    "gn:asciiname":"Xiaoguozhuang",
    "gn:country_code":"CN",
    "gn:dem":6,
    "gn:feature_class":"P",
    "gn:feature_code":"PPL",
    "gn:name":"Xiaoguozhuang",
    "gn:population":0,
    "gn:timezone":"Asia/Shanghai",
    "iso:country":"CN",
    "name:zho_x_preferred":[
        "\u5c0f\u56fd\u5e84"
    ],
    "wof:name":"Xiaoguozhuang",
    "wof:placetype":"locality"
},
  "geometry": {"coordinates":[117.23520000000001,38.81434],"type":"Point"}
}