{
  "type": "Feature",
  "properties": {
    "gn:admin1_code":"3.0",
    "gn:asciiname":"Shenkeng",
    "gn:country_code":"CN",
    "gn:dem":29,
    "gn:feature_class":"P",
    "gn:feature_code":"PPL",
    "gn:name":"Shenkeng",
    "gn:population":0,
    "gn:timezone":"Asia/Shanghai",
    "iso:country":"CN",
    "name:und_x_variant":[
        "\u6df1\u5751"
    ],
    "wof:name":"Shenkeng",
    "wof:placetype":"locality"
},
  "geometry": {"coordinates":[116.22535999999999,29.33309],"type":"Point"}
}