{
  "type": "Feature",
  "properties": {
    "gn:admin1_code":"02",
    "gn:asciiname":"Zhanmao",
    "gn:country_code":"CN",
    "gn:dem":10,
    "gn:feature_class":"P",
    "gn:feature_code":"PPLA4",
    "gn:name":"Zhanmao",
    "gn:population":0,
    "gn:timezone":"Asia/Shanghai",
    "iso:country":"CN",
    "name:und_x_variant":[
        "Dazhan",
        "\u5927\u5c55",
        "Zhanmao",
        "Zhanmao Zhen",
        "\u5c55\u8305\u9547",
        "\u5c55\u8305"
    ],
    "wof:name":"Zhanmao",
    "wof:placetype":"locality"
},
  "geometry": {"coordinates":[122.2829,30.02698],"type":"Point"}
}