{
  "type": "Feature",
  "properties": {
    "gn:admin1_code":"16.0",
    "gn:asciiname":"Shangjindong",
    "gn:country_code":"CN",
    "gn:dem":476,
    "gn:feature_class":"P",
    "gn:feature_code":"PPL",
    "gn:name":"Shangjindong",
    "gn:population":0,
    "gn:timezone":"Asia/Shanghai",
    "iso:country":"CN",
    "name:zho_x_preferred":[
        "\u4e0a\u91d1\u5cd2"
    ],
    "wof:name":"Shangjindong",
    "wof:placetype":"locality"
},
  "geometry": {"coordinates":[108.73999999999999,24.9708],"type":"Point"}
}