{
  "type": "Feature",
  "properties": {
    "gn:admin1_code":"18",
    "gn:asciiname":"Wuli",
    "gn:country_code":"CN",
    "gn:dem":1168,
    "gn:feature_class":"P",
    "gn:feature_code":"PPL",
    "gn:name":"Wuli",
    "gn:population":0,
    "gn:timezone":"Asia/Shanghai",
    "iso:country":"CN",
    "name:ceb_x_preferred":[
        "Wuli"
    ],
    "name:deu_x_preferred":[
        "Wuli"
    ],
    "name:fra_x_preferred":[
        "Wuli"
    ],
    "name:swe_x_preferred":[
        "Wuli"
    ],
    "name:zho_x_preferred":[
        "\u4e4c\u6817"
    ],
    "wof:name":"Wuli",
    "wof:placetype":"locality"
},
  "geometry": {"coordinates":[106.46899999999999,26.8392],"type":"Point"}
}