{
  "type": "Feature",
  "properties": {
    "gn:admin1_code":"4.0",
    "gn:asciiname":"Minyaocun",
    "gn:country_code":"CN",
    "gn:dem":2,
    "gn:feature_class":"P",
    "gn:feature_code":"PPL",
    "gn:name":"Minyaocun",
    "gn:population":0,
    "gn:timezone":"Asia/Shanghai",
    "iso:country":"CN",
    "name:zho_x_preferred":[
        "\u6c11\u7a91\u6751"
    ],
    "wof:name":"Minyaocun",
    "wof:placetype":"locality"
},
  "geometry": {"coordinates":[120.3291,33.04712],"type":"Point"}
}