{
  "type": "Feature",
  "properties": {
    "gn:admin1_code":"30.0",
    "gn:asciiname":"Wufu",
    "gn:country_code":"CN",
    "gn:dem":3,
    "gn:feature_class":"P",
    "gn:feature_code":"PPL",
    "gn:name":"Wufu",
    "gn:population":0,
    "gn:timezone":"Asia/Shanghai",
    "iso:country":"CN",
    "name:swe_x_preferred":[
        "Wufu"
    ],
    "name:vie_x_preferred":[
        "Ng\u0169 ph\u00fac"
    ],
    "name:zho_x_preferred":[
        "\u4e94\u798f"
    ],
    "wof:name":"Wufu",
    "wof:placetype":"locality"
},
  "geometry": {"coordinates":[112.46545,21.85524],"type":"Point"}
}