{
  "type": "Feature",
  "properties": {
    "gn:admin1_code":"24.0",
    "gn:asciiname":"Cuijia Diyi",
    "gn:country_code":"CN",
    "gn:dem":1152,
    "gn:feature_class":"P",
    "gn:feature_code":"PPL",
    "gn:name":"Cuijia Diyi",
    "gn:population":0,
    "gn:timezone":"Asia/Shanghai",
    "iso:country":"CN",
    "name:zho_x_preferred":[
        "\u5d14\u5bb6\u7b2c\u4e00"
    ],
    "wof:name":"Cuijia Diyi",
    "wof:placetype":"locality"
},
  "geometry": {"coordinates":[111.41003000000001,39.41813],"type":"Point"}
}