{
  "type": "Feature",
  "properties": {
    "gn:admin1_code":"10",
    "gn:asciiname":"Nanliuzhuang",
    "gn:country_code":"CN",
    "gn:dem":47,
    "gn:feature_class":"P",
    "gn:feature_code":"PPL",
    "gn:name":"Nanliuzhuang",
    "gn:population":0,
    "gn:timezone":"Asia/Shanghai",
    "iso:country":"CN",
    "name:zho_x_preferred":[
        "\u5357\u7559\u5e84"
    ],
    "wof:name":"Nanliuzhuang",
    "wof:placetype":"locality"
},
  "geometry": {"coordinates":[115.18600000000001,36.4799],"type":"Point"}
}