{
  "type": "Feature",
  "properties": {
    "gn:admin1_code":"31.0",
    "gn:asciiname":"Jiashen",
    "gn:country_code":"CN",
    "gn:dem":106,
    "gn:feature_class":"P",
    "gn:feature_code":"PPL",
    "gn:name":"Jiashen",
    "gn:population":0,
    "gn:timezone":"Asia/Shanghai",
    "iso:country":"CN",
    "name:und_x_variant":[
        "\u52a0\u53c2"
    ],
    "wof:name":"Jiashen",
    "wof:placetype":"locality"
},
  "geometry": {"coordinates":[110.26794,19.20003],"type":"Point"}
}