{
  "type": "Feature",
  "properties": {
    "gn:admin1_code":"10",
    "gn:asciiname":"Sanyimiao",
    "gn:country_code":"CN",
    "gn:dem":596,
    "gn:feature_class":"P",
    "gn:feature_code":"PPL",
    "gn:name":"Sanyimiao",
    "gn:population":0,
    "gn:timezone":"Asia/Shanghai",
    "iso:country":"CN",
    "name:zho_x_preferred":[
        "\u4e09\u4e49\u5e99"
    ],
    "wof:name":"Sanyimiao",
    "wof:placetype":"locality"
},
  "geometry": {"coordinates":[118.4579,40.95305],"type":"Point"}
}