{
  "type": "Feature",
  "properties": {
    "gn:admin1_code":"15.0",
    "gn:asciiname":"Yangshan",
    "gn:country_code":"CN",
    "gn:dem":1317,
    "gn:feature_class":"P",
    "gn:feature_code":"PPL",
    "gn:name":"Yangshan",
    "gn:population":0,
    "gn:timezone":"Asia/Shanghai",
    "iso:country":"CN",
    "name:ceb_x_preferred":[
        "Yangshan"
    ],
    "name:deu_x_preferred":[
        "Yangshan"
    ],
    "name:fra_x_preferred":[
        "Yangshan"
    ],
    "name:rus_x_preferred":[
        "\u042f\u043d\u0448\u0430\u043d\u044c"
    ],
    "name:zho_x_preferred":[
        "\u9633\u5c71"
    ],
    "wof:name":"Yangshan",
    "wof:placetype":"locality"
},
  "geometry": {"coordinates":[108.38,35.5592],"type":"Point"}
}