{
  "type": "Feature",
  "properties": {
    "gn:admin1_code":"11.0",
    "gn:asciiname":"Huamenlou",
    "gn:country_code":"CN",
    "gn:dem":145,
    "gn:feature_class":"P",
    "gn:feature_code":"PPL",
    "gn:name":"Huamenlou",
    "gn:population":0,
    "gn:timezone":"Asia/Shanghai",
    "iso:country":"CN",
    "name:zho_x_preferred":[
        "\u82b1\u95e8\u697c"
    ],
    "wof:name":"Huamenlou",
    "wof:placetype":"locality"
},
  "geometry": {"coordinates":[113.47481000000001,26.62571],"type":"Point"}
}