{
  "type": "Feature",
  "properties": {
    "gn:admin1_code":"32.0",
    "gn:asciiname":"Douchansi",
    "gn:country_code":"CN",
    "gn:dem":432,
    "gn:feature_class":"P",
    "gn:feature_code":"PPL",
    "gn:name":"Douchansi",
    "gn:population":0,
    "gn:timezone":"Asia/Shanghai",
    "iso:country":"CN",
    "name:zho_x_preferred":[
        "\u7aa6\u7985\u5bfa"
    ],
    "wof:name":"Douchansi",
    "wof:placetype":"locality"
},
  "geometry": {"coordinates":[105.746,31.1864],"type":"Point"}
}