{
  "type": "Feature",
  "properties": {
    "gn:admin1_code":"25",
    "gn:asciiname":"Dongcaiyuan",
    "gn:country_code":"CN",
    "gn:dem":120,
    "gn:feature_class":"P",
    "gn:feature_code":"PPL",
    "gn:name":"Dongcaiyuan",
    "gn:population":0,
    "gn:timezone":"Asia/Shanghai",
    "iso:country":"CN",
    "name:zho_x_preferred":[
        "\u4e1c\u83dc\u56ed"
    ],
    "wof:name":"Dongcaiyuan",
    "wof:placetype":"locality"
},
  "geometry": {"coordinates":[116.827,36.4223],"type":"Point"}
}