{
  "type": "Feature",
  "properties": {
    "gn:admin1_code":"02",
    "gn:asciiname":"Quanshancun",
    "gn:country_code":"CN",
    "gn:dem":436,
    "gn:feature_class":"P",
    "gn:feature_code":"PPL",
    "gn:name":"Quanshancun",
    "gn:population":0,
    "gn:timezone":"Asia/Shanghai",
    "iso:country":"CN",
    "name:und_x_variant":[
        "Ch\u2019en-shan",
        "Quanshan",
        "Quanshancun"
    ],
    "name:zho_x_preferred":[
        "\u5168\u5c71\u6751"
    ],
    "wof:name":"Quanshancun",
    "wof:placetype":"locality"
},
  "geometry": {"coordinates":[120.80448,28.21744],"type":"Point"}
}