{
  "type": "Feature",
  "properties": {
    "gn:admin1_code":"18.0",
    "gn:asciiname":"Dudong",
    "gn:country_code":"CN",
    "gn:dem":715,
    "gn:feature_class":"P",
    "gn:feature_code":"PPL",
    "gn:name":"Dudong",
    "gn:population":0,
    "gn:timezone":"Asia/Shanghai",
    "iso:country":"CN",
    "name:zho_x_preferred":[
        "\u72ec\u6d1e"
    ],
    "wof:name":"Dudong",
    "wof:placetype":"locality"
},
  "geometry": {"coordinates":[109.18300000000001,26.232],"type":"Point"}
}