{
  "type": "Feature",
  "properties": {
    "gn:admin1_code":"18.0",
    "gn:asciiname":"Bianxian",
    "gn:country_code":"CN",
    "gn:dem":724,
    "gn:feature_class":"P",
    "gn:feature_code":"PPL",
    "gn:name":"Bianxian",
    "gn:population":0,
    "gn:timezone":"Asia/Shanghai",
    "iso:country":"CN",
    "name:zho_x_preferred":[
        "\u4fbf\u53bf"
    ],
    "wof:name":"Bianxian",
    "wof:placetype":"locality"
},
  "geometry": {"coordinates":[108.866,26.1171],"type":"Point"}
}