{
  "type": "Feature",
  "properties": {
    "gn:admin1_code":"19.0",
    "gn:asciiname":"Beigangzi",
    "gn:country_code":"CN",
    "gn:dem":23,
    "gn:feature_class":"P",
    "gn:feature_code":"PPL",
    "gn:name":"Beigangzi",
    "gn:population":0,
    "gn:timezone":"Asia/Shanghai",
    "iso:country":"CN",
    "name:und_x_variant":[
        "\u5317\u5c97\u5b50"
    ],
    "name:zho_x_preferred":[
        "\u5317\u5c97\u5b50"
    ],
    "wof:name":"Beigangzi",
    "wof:placetype":"locality"
},
  "geometry": {"coordinates":[122.74169999999999,41.79028],"type":"Point"}
}