{
  "type": "Feature",
  "properties": {
    "gn:admin1_code":"1.0",
    "gn:asciiname":"Banjianwu",
    "gn:country_code":"CN",
    "gn:dem":934,
    "gn:feature_class":"P",
    "gn:feature_code":"PPL",
    "gn:name":"Banjianwu",
    "gn:population":0,
    "gn:timezone":"Asia/Shanghai",
    "iso:country":"CN",
    "name:zho_x_preferred":[
        "\u73ed\u80a9\u575e"
    ],
    "wof:name":"Banjianwu",
    "wof:placetype":"locality"
},
  "geometry": {"coordinates":[118.81443,30.13114],"type":"Point"}
}