{
  "type": "Feature",
  "properties": {
    "gn:admin1_code":"26.0",
    "gn:asciiname":"Fenggouquan",
    "gn:country_code":"CN",
    "gn:dem":1817,
    "gn:feature_class":"P",
    "gn:feature_code":"PPL",
    "gn:name":"Fenggouquan",
    "gn:population":0,
    "gn:timezone":"Asia/Shanghai",
    "iso:country":"CN",
    "name:zho_x_preferred":[
        "\u51af\u6c9f\u6cc9"
    ],
    "wof:name":"Fenggouquan",
    "wof:placetype":"locality"
},
  "geometry": {"coordinates":[107.43250999999999,37.10996],"type":"Point"}
}