{
  "type": "Feature",
  "properties": {
    "gn:admin1_code":"25",
    "gn:asciiname":"Houpuli",
    "gn:country_code":"CN",
    "gn:dem":19,
    "gn:feature_class":"P",
    "gn:feature_code":"PPL",
    "gn:name":"Houpuli",
    "gn:population":0,
    "gn:timezone":"Asia/Shanghai",
    "iso:country":"CN",
    "name:zho_x_preferred":[
        "\u540e\u6734\u91cc"
    ],
    "wof:name":"Houpuli",
    "wof:placetype":"locality"
},
  "geometry": {"coordinates":[118.761,36.8933],"type":"Point"}
}