{
  "type": "Feature",
  "properties": {
    "gn:admin1_code":"3",
    "gn:asciiname":"Puhantang",
    "gn:country_code":"CN",
    "gn:dem":75,
    "gn:feature_class":"P",
    "gn:feature_code":"PPL",
    "gn:name":"Puhantang",
    "gn:population":0,
    "gn:timezone":"Asia/Shanghai",
    "iso:country":"CN",
    "name:und_x_variant":[
        "\u666e\u6db5\u5858"
    ],
    "wof:name":"Puhantang",
    "wof:placetype":"locality"
},
  "geometry": {"coordinates":[116.64118000000001,28.10635],"type":"Point"}
}