{
  "type": "Feature",
  "properties": {
    "gn:admin1_code":"1.0",
    "gn:asciiname":"Huatangcun",
    "gn:country_code":"CN",
    "gn:dem":43,
    "gn:feature_class":"P",
    "gn:feature_code":"PPL",
    "gn:name":"Huatangcun",
    "gn:population":0,
    "gn:timezone":"Asia/Shanghai",
    "iso:country":"CN",
    "name:zho_x_preferred":[
        "\u82b1\u5858\u6751"
    ],
    "wof:name":"Huatangcun",
    "wof:placetype":"locality"
},
  "geometry": {"coordinates":[117.15182,32.37763],"type":"Point"}
}