{
  "type": "Feature",
  "properties": {
    "gn:admin1_code":"24.0",
    "gn:asciiname":"Lianjianta",
    "gn:country_code":"CN",
    "gn:dem":1243,
    "gn:feature_class":"P",
    "gn:feature_code":"PPL",
    "gn:name":"Lianjianta",
    "gn:population":0,
    "gn:timezone":"Asia/Shanghai",
    "iso:country":"CN",
    "name:zho_x_preferred":[
        "\u8fde\u5c16\u5854"
    ],
    "wof:name":"Lianjianta",
    "wof:placetype":"locality"
},
  "geometry": {"coordinates":[113.15366000000002,38.44976],"type":"Point"}
}