{
  "type": "Feature",
  "properties": {
    "gn:admin1_code":"24.0",
    "gn:asciiname":"Baihuayu",
    "gn:country_code":"CN",
    "gn:dem":1711,
    "gn:feature_class":"P",
    "gn:feature_code":"PPL",
    "gn:name":"Baihuayu",
    "gn:population":0,
    "gn:timezone":"Asia/Shanghai",
    "iso:country":"CN",
    "name:zho_x_preferred":[
        "\u767d\u5316\u5b87"
    ],
    "wof:name":"Baihuayu",
    "wof:placetype":"locality"
},
  "geometry": {"coordinates":[111.53645,38.1373],"type":"Point"}
}