{
  "type": "Feature",
  "properties": {
    "gn:admin1_code":"11.0",
    "gn:asciiname":"Wanmipu",
    "gn:country_code":"CN",
    "gn:dem":205,
    "gn:feature_class":"P",
    "gn:feature_code":"PPL",
    "gn:name":"Wanmipu",
    "gn:population":0,
    "gn:timezone":"Asia/Shanghai",
    "iso:country":"CN",
    "name:zho_x_preferred":[
        "\u7897\u7c73\u94fa"
    ],
    "wof:name":"Wanmipu",
    "wof:placetype":"locality"
},
  "geometry": {"coordinates":[111.38035000000001,26.4208],"type":"Point"}
}