{
  "type": "Feature",
  "properties": {
    "gn:admin1_code":"15.0",
    "gn:asciiname":"Hexipo",
    "gn:country_code":"CN",
    "gn:dem":1660,
    "gn:feature_class":"P",
    "gn:feature_code":"PPL",
    "gn:name":"Hexipo",
    "gn:population":0,
    "gn:timezone":"Asia/Shanghai",
    "iso:country":"CN",
    "name:zho_x_preferred":[
        "\u6cb3\u897f\u5761"
    ],
    "wof:name":"Hexipo",
    "wof:placetype":"locality"
},
  "geometry": {"coordinates":[104.964,35.8693],"type":"Point"}
}