{
  "type": "Feature",
  "properties": {
    "gn:admin1_code":"1.0",
    "gn:asciiname":"Tongliucun",
    "gn:country_code":"CN",
    "gn:dem":70,
    "gn:feature_class":"P",
    "gn:feature_code":"PPL",
    "gn:name":"Tongliucun",
    "gn:population":0,
    "gn:timezone":"Asia/Shanghai",
    "iso:country":"CN",
    "name:zho_x_preferred":[
        "\u7ae5\u5218\u6751"
    ],
    "wof:name":"Tongliucun",
    "wof:placetype":"locality"
},
  "geometry": {"coordinates":[117.78839000000001,32.62371],"type":"Point"}
}