{
  "type": "Feature",
  "properties": {
    "gn:admin1_code":"12.0",
    "gn:asciiname":"Shiweiquan",
    "gn:country_code":"CN",
    "gn:dem":1579,
    "gn:feature_class":"P",
    "gn:feature_code":"PPL",
    "gn:name":"Shiweiquan",
    "gn:population":0,
    "gn:timezone":"Asia/Shanghai",
    "iso:country":"CN",
    "name:zho_x_preferred":[
        "\u77f3\u56f4\u5708"
    ],
    "wof:name":"Shiweiquan",
    "wof:placetype":"locality"
},
  "geometry": {"coordinates":[110.37503,31.34758],"type":"Point"}
}