{
  "type": "Feature",
  "properties": {
    "gn:admin1_code":"12.0",
    "gn:asciiname":"Wujiawa",
    "gn:country_code":"CN",
    "gn:dem":1005,
    "gn:feature_class":"P",
    "gn:feature_code":"PPL",
    "gn:name":"Wujiawa",
    "gn:population":0,
    "gn:timezone":"Asia/Shanghai",
    "iso:country":"CN",
    "name:zho_x_preferred":[
        "\u5434\u5bb6\u6d3c"
    ],
    "wof:name":"Wujiawa",
    "wof:placetype":"locality"
},
  "geometry": {"coordinates":[110.21684,31.89652],"type":"Point"}
}