{
  "type": "Feature",
  "properties": {
    "gn:admin1_code":"8.0",
    "gn:asciiname":"Yaowopeng",
    "gn:country_code":"CN",
    "gn:dem":205,
    "gn:feature_class":"P",
    "gn:feature_code":"PPL",
    "gn:name":"Yaowopeng",
    "gn:population":0,
    "gn:timezone":"Asia/Shanghai",
    "iso:country":"CN",
    "name:zho_x_preferred":[
        "\u8170\u7a9d\u68da"
    ],
    "wof:name":"Yaowopeng",
    "wof:placetype":"locality"
},
  "geometry": {"coordinates":[126.67666,47.57523],"type":"Point"}
}