{
  "type": "Feature",
  "properties": {
    "gn:admin1_code":"11",
    "gn:asciiname":"Guniushan",
    "gn:country_code":"CN",
    "gn:dem":421,
    "gn:feature_class":"P",
    "gn:feature_code":"PPLA4",
    "gn:name":"Guniushan",
    "gn:population":0,
    "gn:timezone":"Asia/Shanghai",
    "iso:country":"CN",
    "name:und_x_variant":[
        "Sanjiang",
        "Guniushan Xiang"
    ],
    "name:zho_x_preferred":[
        "\u726f\u725b\u5c71"
    ],
    "name:zho_x_variant":[
        "\u726f\u725b\u5c71\u4e61"
    ],
    "wof:name":"Guniushan",
    "wof:placetype":"locality"
},
  "geometry": {"coordinates":[111.26147,28.5457],"type":"Point"}
}