{
  "type": "Feature",
  "properties": {
    "gn:admin1_code":"15.0",
    "gn:asciiname":"Chenjiagou",
    "gn:country_code":"CN",
    "gn:dem":2377,
    "gn:feature_class":"P",
    "gn:feature_code":"PPL",
    "gn:name":"Chenjiagou",
    "gn:population":0,
    "gn:timezone":"Asia/Shanghai",
    "iso:country":"CN",
    "name:und_x_variant":[
        "\u9648\u5bb6\u6c9f"
    ],
    "wof:name":"Chenjiagou",
    "wof:placetype":"locality"
},
  "geometry": {"coordinates":[104.27893,34.21027],"type":"Point"}
}