{
  "type": "Feature",
  "properties": {
    "gn:admin1_code":"19.0",
    "gn:asciiname":"Shangshun Shanbu",
    "gn:country_code":"CN",
    "gn:dem":78,
    "gn:feature_class":"P",
    "gn:feature_code":"PPL",
    "gn:name":"Shangshun Shanbu",
    "gn:population":0,
    "gn:timezone":"Asia/Shanghai",
    "iso:country":"CN",
    "name:und_x_variant":[
        "Shangshunshanbao",
        "Shangshun Shanbu"
    ],
    "name:zho_x_preferred":[
        "\u4e0a\u987a\u5c71\u5821"
    ],
    "wof:name":"Shangshun Shanbu",
    "wof:placetype":"locality"
},
  "geometry": {"coordinates":[120.16007,40.31618],"type":"Point"}
}