{
  "type": "Feature",
  "properties": {
    "gn:admin1_code":"25",
    "gn:asciiname":"Guanluzhuang",
    "gn:country_code":"CN",
    "gn:dem":33,
    "gn:feature_class":"P",
    "gn:feature_code":"PPL",
    "gn:name":"Guanluzhuang",
    "gn:population":0,
    "gn:timezone":"Asia/Shanghai",
    "iso:country":"CN",
    "name:zho_x_preferred":[
        "\u5b98\u8def\u5e84"
    ],
    "wof:name":"Guanluzhuang",
    "wof:placetype":"locality"
},
  "geometry": {"coordinates":[119.015,36.7055],"type":"Point"}
}