{
  "type": "Feature",
  "properties": {
    "gn:admin1_code":"16.0",
    "gn:asciiname":"Lazhushan",
    "gn:country_code":"CN",
    "gn:dem":467,
    "gn:feature_class":"P",
    "gn:feature_code":"PPL",
    "gn:name":"Lazhushan",
    "gn:population":0,
    "gn:timezone":"Asia/Shanghai",
    "iso:country":"CN",
    "name:zho_x_preferred":[
        "\u814a\u7af9\u5c71"
    ],
    "wof:name":"Lazhushan",
    "wof:placetype":"locality"
},
  "geometry": {"coordinates":[109.64400000000001,25.2182],"type":"Point"}
}