{
  "type": "Feature",
  "properties": {
    "gn:admin1_code":"18.0",
    "gn:asciiname":"Mula",
    "gn:country_code":"CN",
    "gn:dem":618,
    "gn:feature_class":"P",
    "gn:feature_code":"PPL",
    "gn:name":"Mula",
    "gn:population":0,
    "gn:timezone":"Asia/Shanghai",
    "iso:country":"CN",
    "name:ara_x_preferred":[
        "\u0645\u0648\u0644\u0629"
    ],
    "name:arg_x_preferred":[
        "Mula"
    ],
    "name:cat_x_preferred":[
        "Mula"
    ],
    "name:ceb_x_preferred":[
        "Mula"
    ],
    "name:deu_x_preferred":[
        "Mula"
    ],
    "name:fra_x_preferred":[
        "Mula"
    ],
    "name:ita_x_preferred":[
        "Mula"
    ],
    "name:nds_x_preferred":[
        "Mula"
    ],
    "name:por_x_preferred":[
        "Mula"
    ],
    "name:spa_x_preferred":[
        "Mula"
    ],
    "name:swe_x_preferred":[
        "Mula"
    ],
    "name:tur_x_preferred":[
        "Mula"
    ],
    "name:zho_x_preferred":[
        "\u6728\u814a"
    ],
    "wof:name":"Mula",
    "wof:placetype":"locality"
},
  "geometry": {"coordinates":[108.565,28.0618],"type":"Point"}
}