{
  "type": "Feature",
  "properties": {
    "gn:admin1_code":"30.0",
    "gn:asciiname":"Wei'an",
    "gn:country_code":"CN",
    "gn:dem":12,
    "gn:feature_class":"P",
    "gn:feature_code":"PPL",
    "gn:name":"Wei\u2019an",
    "gn:population":0,
    "gn:timezone":"Asia/Shanghai",
    "iso:country":"CN",
    "name:und_x_variant":[
        "Wei\u2019an"
    ],
    "name:zho_x_preferred":[
        "\u56f4\u5b89"
    ],
    "wof:name":"Wei'an",
    "wof:placetype":"locality"
},
  "geometry": {"coordinates":[112.45036,22.95493],"type":"Point"}
}