{
  "type": "Feature",
  "properties": {
    "gn:admin1_code":"24.0",
    "gn:asciiname":"Chedaopo",
    "gn:country_code":"CN",
    "gn:dem":1417,
    "gn:feature_class":"P",
    "gn:feature_code":"PPL",
    "gn:name":"Chedaopo",
    "gn:population":0,
    "gn:timezone":"Asia/Shanghai",
    "iso:country":"CN",
    "name:zho_x_preferred":[
        "\u8f66\u9053\u5761"
    ],
    "wof:name":"Chedaopo",
    "wof:placetype":"locality"
},
  "geometry": {"coordinates":[111.83722,39.46516],"type":"Point"}
}