{
  "type": "Feature",
  "properties": {
    "gn:admin1_code":"26.0",
    "gn:asciiname":"Xionghuangta",
    "gn:country_code":"CN",
    "gn:dem":1168,
    "gn:feature_class":"P",
    "gn:feature_code":"PPL",
    "gn:name":"Xionghuangta",
    "gn:population":0,
    "gn:timezone":"Asia/Shanghai",
    "iso:country":"CN",
    "name:zho_x_preferred":[
        "\u96c4\u9ec4\u584c"
    ],
    "wof:name":"Xionghuangta",
    "wof:placetype":"locality"
},
  "geometry": {"coordinates":[109.2032,36.41179],"type":"Point"}
}