{
  "type": "Feature",
  "properties": {
    "gn:admin1_code":"19.0",
    "gn:asciiname":"Wutaizi",
    "gn:country_code":"CN",
    "gn:dem":46,
    "gn:feature_class":"P",
    "gn:feature_code":"PPL",
    "gn:name":"Wutaizi",
    "gn:population":0,
    "gn:timezone":"Asia/Shanghai",
    "iso:country":"CN",
    "name:und_x_variant":[
        "\u4e94\u53f0\u5b50"
    ],
    "name:zho_x_preferred":[
        "\u4e94\u53f0\u5b50"
    ],
    "wof:name":"Wutaizi",
    "wof:placetype":"locality"
},
  "geometry": {"coordinates":[122.26513,42.03586],"type":"Point"}
}