{
  "type": "Feature",
  "properties": {
    "gn:admin1_code":"2.0",
    "gn:asciiname":"Xiguatang",
    "gn:country_code":"CN",
    "gn:dem":25,
    "gn:feature_class":"P",
    "gn:feature_code":"PPL",
    "gn:name":"Xiguatang",
    "gn:population":0,
    "gn:timezone":"Asia/Shanghai",
    "iso:country":"CN",
    "name:zho_x_preferred":[
        "\u897f\u74dc\u5858"
    ],
    "wof:name":"Xiguatang",
    "wof:placetype":"locality"
},
  "geometry": {"coordinates":[120.95938999999998,28.85107],"type":"Point"}
}