{
  "type": "Feature",
  "properties": {
    "gn:admin1_code":"15.0",
    "gn:asciiname":"Taizidi",
    "gn:country_code":"CN",
    "gn:dem":1559,
    "gn:feature_class":"P",
    "gn:feature_code":"PPL",
    "gn:name":"Taizidi",
    "gn:population":0,
    "gn:timezone":"Asia/Shanghai",
    "iso:country":"CN",
    "name:zho_x_preferred":[
        "\u53f0\u5b50\u5e95"
    ],
    "wof:name":"Taizidi",
    "wof:placetype":"locality"
},
  "geometry": {"coordinates":[97.38590000000001,40.0994],"type":"Point"}
}