{
  "type": "Feature",
  "properties": {
    "gn:admin1_code":"26.0",
    "gn:asciiname":"Beilupingcun",
    "gn:country_code":"CN",
    "gn:dem":1038,
    "gn:feature_class":"P",
    "gn:feature_code":"PPL",
    "gn:name":"Beilupingcun",
    "gn:population":0,
    "gn:timezone":"Asia/Shanghai",
    "iso:country":"CN",
    "name:zho_x_preferred":[
        "\u7891\u8def\u576a\u6751"
    ],
    "wof:name":"Beilupingcun",
    "wof:placetype":"locality"
},
  "geometry": {"coordinates":[109.65757000000001,36.82068],"type":"Point"}
}