{
  "type": "Feature",
  "properties": {
    "gn:admin1_code":"14.0",
    "gn:asciiname":"Chuotang",
    "gn:country_code":"CN",
    "gn:dem":4058,
    "gn:feature_class":"P",
    "gn:feature_code":"PPL",
    "gn:name":"Chuotang",
    "gn:population":0,
    "gn:timezone":"Asia/Urumqi",
    "iso:country":"CN",
    "name:zho_x_preferred":[
        "\u7ef0\u5802"
    ],
    "wof:name":"Chuotang",
    "wof:placetype":"locality"
},
  "geometry": {"coordinates":[98.39648,31.12056],"type":"Point"}
}