{
  "type": "Feature",
  "properties": {
    "gn:admin1_code":"32.0",
    "gn:asciiname":"Yeba",
    "gn:country_code":"CN",
    "gn:dem":3560,
    "gn:feature_class":"P",
    "gn:feature_code":"PPL",
    "gn:name":"Yeba",
    "gn:population":0,
    "gn:timezone":"Asia/Shanghai",
    "iso:country":"CN",
    "name:zho_x_preferred":[
        "\u53f6\u5df4"
    ],
    "wof:name":"Yeba",
    "wof:placetype":"locality"
},
  "geometry": {"coordinates":[98.96731,30.78343],"type":"Point"}
}