{
  "type": "Feature",
  "properties": {
    "gn:admin1_code":"29.0",
    "gn:asciiname":"Siluzi",
    "gn:country_code":"CN",
    "gn:dem":2463,
    "gn:feature_class":"P",
    "gn:feature_code":"PPL",
    "gn:name":"Siluzi",
    "gn:population":0,
    "gn:timezone":"Asia/Shanghai",
    "iso:country":"CN",
    "name:zho_x_preferred":[
        "\u56db\u8def\u5b50"
    ],
    "wof:name":"Siluzi",
    "wof:placetype":"locality"
},
  "geometry": {"coordinates":[99.6541,26.7728],"type":"Point"}
}