{
  "type": "Feature",
  "properties": {
    "gn:admin1_code":"16.0",
    "gn:asciiname":"Menggan",
    "gn:country_code":"CN",
    "gn:dem":924,
    "gn:feature_class":"P",
    "gn:feature_code":"PPL",
    "gn:name":"Menggan",
    "gn:population":0,
    "gn:timezone":"Asia/Shanghai",
    "iso:country":"CN",
    "name:zho_x_preferred":[
        "\u731b\u5e72"
    ],
    "wof:name":"Menggan",
    "wof:placetype":"locality"
},
  "geometry": {"coordinates":[106.84099999999999,24.5887],"type":"Point"}
}