{
  "type": "Feature",
  "properties": {
    "gn:admin1_code":"9.0",
    "gn:asciiname":"Hulou",
    "gn:country_code":"CN",
    "gn:dem":63,
    "gn:feature_class":"P",
    "gn:feature_code":"PPL",
    "gn:name":"Hulou",
    "gn:population":0,
    "gn:timezone":"Asia/Shanghai",
    "iso:country":"CN",
    "name:zho_x_preferred":[
        "\u80e1\u697c"
    ],
    "wof:name":"Hulou",
    "wof:placetype":"locality"
},
  "geometry": {"coordinates":[114.05175,33.37897],"type":"Point"}
}