{
  "type": "Feature",
  "properties": {
    "gn:admin1_code":"29.0",
    "gn:asciiname":"Cuobidian",
    "gn:country_code":"CN",
    "gn:dem":2761,
    "gn:feature_class":"P",
    "gn:feature_code":"PPL",
    "gn:name":"Cuobidian",
    "gn:population":0,
    "gn:timezone":"Asia/Shanghai",
    "iso:country":"CN",
    "name:zho_x_preferred":[
        "\u64ae\u5f7c\u7538"
    ],
    "wof:name":"Cuobidian",
    "wof:placetype":"locality"
},
  "geometry": {"coordinates":[100.47799999999999,27.7466],"type":"Point"}
}