{
  "type": "Feature",
  "properties": {
    "gn:admin1_code":"9.0",
    "gn:asciiname":"Qiwan",
    "gn:country_code":"CN",
    "gn:dem":64,
    "gn:feature_class":"P",
    "gn:feature_code":"PPL",
    "gn:name":"Qiwan",
    "gn:population":0,
    "gn:timezone":"Asia/Shanghai",
    "iso:country":"CN",
    "name:zho_x_preferred":[
        "\u7941\u6e7e"
    ],
    "wof:name":"Qiwan",
    "wof:placetype":"locality"
},
  "geometry": {"coordinates":[114.48801,34.37628],"type":"Point"}
}