{
  "type": "Feature",
  "properties": {
    "gn:admin1_code":"29.0",
    "gn:asciiname":"Xiaobazi",
    "gn:country_code":"CN",
    "gn:dem":1633,
    "gn:feature_class":"P",
    "gn:feature_code":"PPL",
    "gn:name":"Xiaobazi",
    "gn:population":0,
    "gn:timezone":"Asia/Shanghai",
    "iso:country":"CN",
    "name:zho_x_preferred":[
        "\u5c0f\u575d\u5b50"
    ],
    "wof:name":"Xiaobazi",
    "wof:placetype":"locality"
},
  "geometry": {"coordinates":[100.07599999999999,24.0204],"type":"Point"}
}