{
  "type": "Feature",
  "properties": {
    "gn:admin1_code":"07",
    "gn:asciiname":"Meilin",
    "gn:country_code":"CN",
    "gn:dem":800,
    "gn:feature_class":"P",
    "gn:feature_code":"PPL",
    "gn:name":"Meilin",
    "gn:population":0,
    "gn:timezone":"Asia/Shanghai",
    "iso:country":"CN",
    "name:ceb_x_preferred":[
        "Meilin"
    ],
    "name:deu_x_preferred":[
        "Meilin"
    ],
    "name:swe_x_preferred":[
        "Meilin"
    ],
    "name:zho_x_preferred":[
        "\u7f8e\u6797"
    ],
    "wof:name":"Meilin",
    "wof:placetype":"locality"
},
  "geometry": {"coordinates":[117.79535,25.18619],"type":"Point"}
}