{
  "type": "Feature",
  "properties": {
    "gn:admin1_code":"4.0",
    "gn:asciiname":"Huameicun",
    "gn:country_code":"CN",
    "gn:dem":4,
    "gn:feature_class":"P",
    "gn:feature_code":"PPL",
    "gn:name":"Huameicun",
    "gn:population":0,
    "gn:timezone":"Asia/Shanghai",
    "iso:country":"CN",
    "name:zho_x_preferred":[
        "\u534e\u7f8e\u6751"
    ],
    "wof:name":"Huameicun",
    "wof:placetype":"locality"
},
  "geometry": {"coordinates":[120.64428999999998,32.74548],"type":"Point"}
}