{
  "type": "Feature",
  "properties": {
    "gn:admin1_code":"22.0",
    "gn:asciiname":"Miliangtun",
    "gn:country_code":"CN",
    "gn:dem":555,
    "gn:feature_class":"P",
    "gn:feature_code":"PPL",
    "gn:name":"Miliangtun",
    "gn:population":0,
    "gn:timezone":"Asia/Shanghai",
    "iso:country":"CN",
    "name:zho_x_preferred":[
        "\u7c73\u7cae\u5c6f"
    ],
    "wof:name":"Miliangtun",
    "wof:placetype":"locality"
},
  "geometry": {"coordinates":[116.0501,40.55324],"type":"Point"}
}