{
  "type": "Feature",
  "properties": {
    "gn:admin1_code":"15.0",
    "gn:asciiname":"Liangjiashan",
    "gn:country_code":"CN",
    "gn:dem":2235,
    "gn:feature_class":"P",
    "gn:feature_code":"PPL",
    "gn:name":"Liangjiashan",
    "gn:population":0,
    "gn:timezone":"Asia/Shanghai",
    "iso:country":"CN",
    "name:zho_x_preferred":[
        "\u6881\u5bb6\u5c71"
    ],
    "wof:name":"Liangjiashan",
    "wof:placetype":"locality"
},
  "geometry": {"coordinates":[103.041,35.4893],"type":"Point"}
}