{
  "type": "Feature",
  "properties": {
    "gn:admin1_code":"2.0",
    "gn:asciiname":"Zhongshuangmiao",
    "gn:country_code":"CN",
    "gn:dem":29,
    "gn:feature_class":"P",
    "gn:feature_code":"PPL",
    "gn:name":"Zhongshuangmiao",
    "gn:population":0,
    "gn:timezone":"Asia/Shanghai",
    "iso:country":"CN",
    "name:zho_x_preferred":[
        "\u4e2d\u53cc\u82d7"
    ],
    "wof:name":"Zhongshuangmiao",
    "wof:placetype":"locality"
},
  "geometry": {"coordinates":[121.23396,28.26831],"type":"Point"}
}