{
  "type": "Feature",
  "properties": {
    "gn:admin1_code":"4.0",
    "gn:asciiname":"Xinyun Liuzu",
    "gn:country_code":"CN",
    "gn:dem":4,
    "gn:feature_class":"P",
    "gn:feature_code":"PPL",
    "gn:name":"Xinyun Liuzu",
    "gn:population":0,
    "gn:timezone":"Asia/Shanghai",
    "iso:country":"CN",
    "name:und_x_variant":[
        "\u65b0\u8fd0\u516d\u7ec4"
    ],
    "name:zho_x_preferred":[
        "\u65b0\u8fd0\u516d\u7ec4"
    ],
    "wof:name":"Xinyun Liuzu",
    "wof:placetype":"locality"
},
  "geometry": {"coordinates":[120.45234000000001,32.11851],"type":"Point"}
}