{
  "type": "Feature",
  "properties": {
    "gn:admin1_code":"15.0",
    "gn:asciiname":"Tianmen",
    "gn:country_code":"CN",
    "gn:dem":1400,
    "gn:feature_class":"P",
    "gn:feature_code":"PPL",
    "gn:name":"Tianmen",
    "gn:population":0,
    "gn:timezone":"Asia/Shanghai",
    "iso:country":"CN",
    "name:deu_x_preferred":[
        "Tianmen"
    ],
    "name:fas_x_preferred":[
        "\u062a\u06cc\u0627\u0646\u0645\u0646"
    ],
    "name:fin_x_preferred":[
        "Tianmen"
    ],
    "name:fra_x_preferred":[
        "Tianmen"
    ],
    "name:ita_x_preferred":[
        "Tianmen"
    ],
    "name:jpn_x_preferred":[
        "\u5929\u9580\u5e02"
    ],
    "name:kik_x_preferred":[
        "Tianmen"
    ],
    "name:kor_x_preferred":[
        "\ud188\uba3c\uc2dc"
    ],
    "name:mlg_x_preferred":[
        "Tianmen"
    ],
    "name:nld_x_preferred":[
        "Tianmen"
    ],
    "name:nno_x_preferred":[
        "Tianmen"
    ],
    "name:nor_x_preferred":[
        "Tianmen"
    ],
    "name:pam_x_preferred":[
        "Tianmen"
    ],
    "name:pol_x_preferred":[
        "Tianmen"
    ],
    "name:por_x_preferred":[
        "Tianmen"
    ],
    "name:rus_x_preferred":[
        "\u0422\u044f\u043d\u044c\u043c\u044d\u043d\u044c"
    ],
    "name:srp_x_preferred":[
        "\u0422\u0458\u0435\u043d\u043c\u0435\u043d"
    ],
    "name:swe_x_preferred":[
        "Tianmen"
    ],
    "name:tur_x_preferred":[
        "Tianmen"
    ],
    "name:urd_x_preferred":[
        "\u062a\u06cc\u0627\u0646\u0645\u06cc\u0646"
    ],
    "name:vie_x_preferred":[
        "Thi\u00ean M\u00f4n"
    ],
    "name:war_x_preferred":[
        "Tianmen"
    ],
    "name:wuu_x_preferred":[
        "\u5929\u95e8\u5e02"
    ],
    "name:zho_x_preferred":[
        "\u5929\u95e8"
    ],
    "name:zho_x_variant":[
        "\u5929\u95e8\u5e02"
    ],
    "wof:name":"Tianmen",
    "wof:placetype":"locality"
},
  "geometry": {"coordinates":[106.643,35.5474],"type":"Point"}
}