{
  "type": "Feature",
  "properties": {
    "gn:admin1_code":"15.0",
    "gn:asciiname":"Tianmen",
    "gn:country_code":"CN",
    "gn:dem":1400,
    "gn:feature_class":"P",
    "gn:feature_code":"PPL",
    "gn:name":"Tianmen",
    "gn:population":0,
    "gn:timezone":"Asia/Shanghai",
    "iso:country":"CN",
    "name:zho_x_preferred":[
        "\u5929\u95e8"
    ],
    "wof:name":"Tianmen",
    "wof:placetype":"locality"
},
  "geometry": {"coordinates":[106.643,35.5474],"type":"Point"}
}