{
  "type": "Feature",
  "properties": {
    "gn:admin1_code":"25",
    "gn:asciiname":"Cheguo",
    "gn:country_code":"CN",
    "gn:dem":15,
    "gn:feature_class":"P",
    "gn:feature_code":"PPL",
    "gn:name":"Cheguo",
    "gn:population":0,
    "gn:timezone":"Asia/Shanghai",
    "iso:country":"CN",
    "name:zho_x_preferred":[
        "\u8f66\u90ed"
    ],
    "wof:name":"Cheguo",
    "wof:placetype":"locality"
},
  "geometry": {"coordinates":[117.758,37.0469],"type":"Point"}
}