{
  "type": "Feature",
  "properties": {
    "gn:admin1_code":"19.0",
    "gn:asciiname":"Guligutai",
    "gn:country_code":"CN",
    "gn:dem":212,
    "gn:feature_class":"P",
    "gn:feature_code":"PPL",
    "gn:name":"Guligutai",
    "gn:population":0,
    "gn:timezone":"Asia/Shanghai",
    "iso:country":"CN",
    "name:und_x_variant":[
        "\u53e4\u529b\u53e4\u53f0"
    ],
    "name:zho_x_preferred":[
        "\u53e4\u529b\u53e4\u53f0"
    ],
    "wof:name":"Guligutai",
    "wof:placetype":"locality"
},
  "geometry": {"coordinates":[121.90268,42.34918],"type":"Point"}
}