{
  "type": "Feature",
  "properties": {
    "gn:admin1_code":"5.0",
    "gn:asciiname":"Beiwangjia Tuozi",
    "gn:country_code":"CN",
    "gn:dem":157,
    "gn:feature_class":"P",
    "gn:feature_code":"PPL",
    "gn:name":"Beiwangjia Tuozi",
    "gn:population":0,
    "gn:timezone":"Asia/Shanghai",
    "iso:country":"CN",
    "name:zho_x_preferred":[
        "\u5317\u738b\u5bb6\u5768\u5b50"
    ],
    "wof:name":"Beiwangjia Tuozi",
    "wof:placetype":"locality"
},
  "geometry": {"coordinates":[126.05069,44.71957],"type":"Point"}
}