{
  "type": "Feature",
  "properties": {
    "gn:admin1_code":"15.0",
    "gn:asciiname":"Maogazha",
    "gn:country_code":"CN",
    "gn:dem":2277,
    "gn:feature_class":"P",
    "gn:feature_code":"PPL",
    "gn:name":"Maogazha",
    "gn:population":0,
    "gn:timezone":"Asia/Shanghai",
    "iso:country":"CN",
    "name:zho_x_preferred":[
        "\u6bdb\u5c15\u624e"
    ],
    "wof:name":"Maogazha",
    "wof:placetype":"locality"
},
  "geometry": {"coordinates":[103.50700000000001,35.7398],"type":"Point"}
}