{
  "type": "Feature",
  "properties": {
    "gn:admin1_code":"9.0",
    "gn:asciiname":"Wangminggao",
    "gn:country_code":"CN",
    "gn:dem":168,
    "gn:feature_class":"P",
    "gn:feature_code":"PPL",
    "gn:name":"Wangminggao",
    "gn:population":0,
    "gn:timezone":"Asia/Shanghai",
    "iso:country":"CN",
    "name:und_x_variant":[
        "\u738b\u9e23\u768b",
        "Wangminggao"
    ],
    "wof:name":"Wangminggao",
    "wof:placetype":"locality"
},
  "geometry": {"coordinates":[112.87554,33.22738],"type":"Point"}
}