{
  "type": "Feature",
  "properties": {
    "gn:admin1_code":"14.0",
    "gn:asciiname":"Xueba",
    "gn:country_code":"CN",
    "gn:dem":3690,
    "gn:feature_class":"P",
    "gn:feature_code":"PPL",
    "gn:name":"Xueba",
    "gn:population":0,
    "gn:timezone":"Asia/Urumqi",
    "iso:country":"CN",
    "name:zho_x_preferred":[
        "\u96ea\u5df4"
    ],
    "wof:name":"Xueba",
    "wof:placetype":"locality"
},
  "geometry": {"coordinates":[92.68163,28.57615],"type":"Point"}
}