{
  "type": "Feature",
  "properties": {
    "gn:admin1_code":"14.0",
    "gn:asciiname":"Zhajiu",
    "gn:country_code":"CN",
    "gn:dem":3223,
    "gn:feature_class":"P",
    "gn:feature_code":"PPL",
    "gn:name":"Zhajiu",
    "gn:population":0,
    "gn:timezone":"Asia/Urumqi",
    "iso:country":"CN",
    "name:zho_x_preferred":[
        "\u624e\u4e5d"
    ],
    "wof:name":"Zhajiu",
    "wof:placetype":"locality"
},
  "geometry": {"coordinates":[97.82165999999999,29.01996],"type":"Point"}
}