{
  "type": "Feature",
  "properties": {
    "gn:admin1_code":"3.0",
    "gn:asciiname":"Pengchengwei",
    "gn:country_code":"CN",
    "gn:dem":35,
    "gn:feature_class":"P",
    "gn:feature_code":"PPL",
    "gn:name":"Pengchengwei",
    "gn:population":0,
    "gn:timezone":"Asia/Shanghai",
    "iso:country":"CN",
    "name:und_x_variant":[
        "\u9e4f\u7a0b\u5c3e"
    ],
    "wof:name":"Pengchengwei",
    "wof:placetype":"locality"
},
  "geometry": {"coordinates":[115.54125000000001,28.1559],"type":"Point"}
}