{
  "type": "Feature",
  "properties": {
    "gn:admin1_code":"1.0",
    "gn:asciiname":"Xikengwu",
    "gn:country_code":"CN",
    "gn:dem":165,
    "gn:feature_class":"P",
    "gn:feature_code":"PPL",
    "gn:name":"Xikengwu",
    "gn:population":0,
    "gn:timezone":"Asia/Shanghai",
    "iso:country":"CN",
    "name:und_x_variant":[
        "\u897f\u5751\u575e"
    ],
    "wof:name":"Xikengwu",
    "wof:placetype":"locality"
},
  "geometry": {"coordinates":[118.90631999999999,30.58528],"type":"Point"}
}