{
  "type": "Feature",
  "properties": {
    "gn:admin1_code":"25",
    "gn:asciiname":"Yaxia",
    "gn:country_code":"CN",
    "gn:dem":248,
    "gn:feature_class":"P",
    "gn:feature_code":"PPL",
    "gn:name":"Yaxia",
    "gn:population":0,
    "gn:timezone":"Asia/Shanghai",
    "iso:country":"CN",
    "name:zho_x_preferred":[
        "\u5d16\u4e0b"
    ],
    "wof:name":"Yaxia",
    "wof:placetype":"locality"
},
  "geometry": {"coordinates":[118.502,36.1472],"type":"Point"}
}