{
  "type": "Feature",
  "properties": {
    "gn:admin1_code":"19.0",
    "gn:asciiname":"Gejiabucun",
    "gn:country_code":"CN",
    "gn:dem":134,
    "gn:feature_class":"P",
    "gn:feature_code":"PPL",
    "gn:name":"Gejiabucun",
    "gn:population":0,
    "gn:timezone":"Asia/Shanghai",
    "iso:country":"CN",
    "name:zho_x_preferred":[
        "\u845b\u5bb6\u5821\u6751"
    ],
    "wof:name":"Gejiabucun",
    "wof:placetype":"locality"
},
  "geometry": {"coordinates":[123.35048,40.11821],"type":"Point"}
}