{
  "type": "Feature",
  "properties": {
    "gn:admin1_code":"30",
    "gn:asciiname":"Hushanjiao",
    "gn:country_code":"CN",
    "gn:dem":86,
    "gn:feature_class":"P",
    "gn:feature_code":"PPL",
    "gn:name":"Hushanjiao",
    "gn:population":0,
    "gn:timezone":"Asia/Shanghai",
    "iso:country":"CN",
    "name:zho_x_preferred":[
        "\u6e56\u5c71\u89d2"
    ],
    "wof:name":"Hushanjiao",
    "wof:placetype":"locality"
},
  "geometry": {"coordinates":[116.3112,24.41984],"type":"Point"}
}