{
  "type": "Feature",
  "properties": {
    "gn:admin1_code":"29.0",
    "gn:asciiname":"Doufuzhai",
    "gn:country_code":"CN",
    "gn:dem":1425,
    "gn:feature_class":"P",
    "gn:feature_code":"PPL",
    "gn:name":"Doufuzhai",
    "gn:population":0,
    "gn:timezone":"Asia/Shanghai",
    "iso:country":"CN",
    "name:zho_x_preferred":[
        "\u8c46\u8150\u5be8"
    ],
    "wof:name":"Doufuzhai",
    "wof:placetype":"locality"
},
  "geometry": {"coordinates":[99.8451,23.6798],"type":"Point"}
}