{
  "type": "Feature",
  "properties": {
    "gn:admin1_code":"16.0",
    "gn:asciiname":"Shukang",
    "gn:country_code":"CN",
    "gn:dem":180,
    "gn:feature_class":"P",
    "gn:feature_code":"PPL",
    "gn:name":"Shukang",
    "gn:population":0,
    "gn:timezone":"Asia/Shanghai",
    "iso:country":"CN",
    "name:zho_x_preferred":[
        "\u719f\u5eb7"
    ],
    "wof:name":"Shukang",
    "wof:placetype":"locality"
},
  "geometry": {"coordinates":[107.901,22.1143],"type":"Point"}
}