{
  "type": "Feature",
  "properties": {
    "gn:admin1_code":"16",
    "gn:asciiname":"Longzhua",
    "gn:country_code":"CN",
    "gn:dem":277,
    "gn:feature_class":"P",
    "gn:feature_code":"PPL",
    "gn:name":"Longzhua",
    "gn:population":0,
    "gn:timezone":"Asia/Shanghai",
    "iso:country":"CN",
    "name:zho_x_preferred":[
        "\u9f99\u722a"
    ],
    "wof:name":"Longzhua",
    "wof:placetype":"locality"
},
  "geometry": {"coordinates":[110.26600000000001,25.5973],"type":"Point"}
}