{
  "type": "Feature",
  "properties": {
    "gn:admin1_code":"7.0",
    "gn:asciiname":"Shangyi",
    "gn:country_code":"CN",
    "gn:dem":468,
    "gn:feature_class":"P",
    "gn:feature_code":"PPL",
    "gn:name":"Shangyi",
    "gn:population":0,
    "gn:timezone":"Asia/Shanghai",
    "iso:country":"CN",
    "name:und_x_variant":[
        "\u4e0a\u6ea2"
    ],
    "name:zho_x_preferred":[
        "\u4e0a\u6ea2"
    ],
    "wof:name":"Shangyi",
    "wof:placetype":"locality"
},
  "geometry": {"coordinates":[116.70161,26.89705],"type":"Point"}
}