{
  "type": "Feature",
  "properties": {
    "gn:admin1_code":"15.0",
    "gn:asciiname":"Xiawulang",
    "gn:country_code":"CN",
    "gn:dem":1286,
    "gn:feature_class":"P",
    "gn:feature_code":"PPL",
    "gn:name":"Xiawulang",
    "gn:population":0,
    "gn:timezone":"Asia/Shanghai",
    "iso:country":"CN",
    "name:und_x_variant":[
        "\u4e0b\u4e94\u90ce"
    ],
    "wof:name":"Xiawulang",
    "wof:placetype":"locality"
},
  "geometry": {"coordinates":[105.60303999999999,33.61702],"type":"Point"}
}