{
  "type": "Feature",
  "properties": {
    "gn:admin1_code":"16",
    "gn:asciiname":"Xinzhaiwan",
    "gn:country_code":"CN",
    "gn:dem":227,
    "gn:feature_class":"P",
    "gn:feature_code":"PPL",
    "gn:name":"Xinzhaiwan",
    "gn:population":0,
    "gn:timezone":"Asia/Shanghai",
    "iso:country":"CN",
    "name:zho_x_preferred":[
        "\u65b0\u5b85\u6e7e"
    ],
    "wof:name":"Xinzhaiwan",
    "wof:placetype":"locality"
},
  "geometry": {"coordinates":[110.729,25.7622],"type":"Point"}
}