{
  "type": "Feature",
  "properties": {
    "gn:admin1_code":"11.0",
    "gn:asciiname":"Guishannao",
    "gn:country_code":"CN",
    "gn:dem":368,
    "gn:feature_class":"P",
    "gn:feature_code":"PPL",
    "gn:name":"Guishannao",
    "gn:population":0,
    "gn:timezone":"Asia/Shanghai",
    "iso:country":"CN",
    "name:zho_x_preferred":[
        "\u9f9f\u5c71\u57b4"
    ],
    "wof:name":"Guishannao",
    "wof:placetype":"locality"
},
  "geometry": {"coordinates":[110.77463,27.93397],"type":"Point"}
}