{
  "type": "Feature",
  "properties": {
    "gn:admin1_code":"22.0",
    "gn:asciiname":"Huangtukengcun",
    "gn:country_code":"CN",
    "gn:dem":599,
    "gn:feature_class":"P",
    "gn:feature_code":"PPL",
    "gn:name":"Huangtukengcun",
    "gn:population":0,
    "gn:timezone":"Asia/Shanghai",
    "iso:country":"CN",
    "name:zho_x_preferred":[
        "\u9ec4\u571f\u5751\u6751"
    ],
    "wof:name":"Huangtukengcun",
    "wof:placetype":"locality"
},
  "geometry": {"coordinates":[115.84658,40.0674],"type":"Point"}
}