{
  "type": "Feature",
  "properties": {
    "gn:admin1_code":"29.0",
    "gn:asciiname":"Aoneyao",
    "gn:country_code":"CN",
    "gn:dem":2294,
    "gn:feature_class":"P",
    "gn:feature_code":"PPL",
    "gn:name":"Aoneyao",
    "gn:population":0,
    "gn:timezone":"Asia/Shanghai",
    "iso:country":"CN",
    "name:und_x_variant":[
        "Aoneme",
        "Aoneyao"
    ],
    "name:zho_x_preferred":[
        "\u51f9\u5462\u4e48"
    ],
    "wof:name":"Aoneyao",
    "wof:placetype":"locality"
},
  "geometry": {"coordinates":[101.017,24.6474],"type":"Point"}
}