{
  "type": "Feature",
  "properties": {
    "gn:admin1_code":"30.0",
    "gn:asciiname":"Sanwuzhai",
    "gn:country_code":"CN",
    "gn:dem":247,
    "gn:feature_class":"P",
    "gn:feature_code":"PPL",
    "gn:name":"Sanwuzhai",
    "gn:population":0,
    "gn:timezone":"Asia/Shanghai",
    "iso:country":"CN",
    "name:zho_x_preferred":[
        "\u4e09\u5c4b\u5be8"
    ],
    "wof:name":"Sanwuzhai",
    "wof:placetype":"locality"
},
  "geometry": {"coordinates":[111.18039,22.71251],"type":"Point"}
}