{
  "type": "Feature",
  "properties": {
    "gn:admin1_code":"2.0",
    "gn:asciiname":"Tiantu Yuye",
    "gn:country_code":"CN",
    "gn:dem":17,
    "gn:feature_class":"P",
    "gn:feature_code":"PPLF",
    "gn:name":"Tiantu Yuye",
    "gn:population":0,
    "gn:timezone":"Asia/Shanghai",
    "iso:country":"CN",
    "name:zho_x_preferred":[
        "\u7530\u6d82\u6e14\u4e1a"
    ],
    "wof:name":"Tiantu Yuye",
    "wof:placetype":"locality"
},
  "geometry": {"coordinates":[122.41107,30.43964],"type":"Point"}
}