{
  "type": "Feature",
  "properties": {
    "gn:admin1_code":"19.0",
    "gn:asciiname":"Sandaohe",
    "gn:country_code":"CN",
    "gn:dem":89,
    "gn:feature_class":"P",
    "gn:feature_code":"PPL",
    "gn:name":"Sandaohe",
    "gn:population":0,
    "gn:timezone":"Asia/Shanghai",
    "iso:country":"CN",
    "name:zho_x_preferred":[
        "\u4e09\u9053\u6cb3"
    ],
    "wof:name":"Sandaohe",
    "wof:placetype":"locality"
},
  "geometry": {"coordinates":[124.024,40.5942],"type":"Point"}
}