{
  "type": "Feature",
  "properties": {
    "gn:admin1_code":"9.0",
    "gn:asciiname":"Leiyinsi",
    "gn:country_code":"CN",
    "gn:dem":331,
    "gn:feature_class":"P",
    "gn:feature_code":"PPL",
    "gn:name":"Leiyinsi",
    "gn:population":0,
    "gn:timezone":"Asia/Shanghai",
    "iso:country":"CN",
    "name:zho_x_preferred":[
        "\u96f7\u97f3\u5bfa"
    ],
    "wof:name":"Leiyinsi",
    "wof:placetype":"locality"
},
  "geometry": {"coordinates":[112.69094,33.92372],"type":"Point"}
}