{
  "type": "Feature",
  "properties": {
    "gn:admin1_code":"25",
    "gn:asciiname":"Nanliang",
    "gn:country_code":"CN",
    "gn:dem":121,
    "gn:feature_class":"P",
    "gn:feature_code":"PPL",
    "gn:name":"Nanliang",
    "gn:population":0,
    "gn:timezone":"Asia/Shanghai",
    "iso:country":"CN",
    "name:zho_x_preferred":[
        "\u5357\u826f"
    ],
    "wof:name":"Nanliang",
    "wof:placetype":"locality"
},
  "geometry": {"coordinates":[118.874,36.3865],"type":"Point"}
}