{
  "type": "Feature",
  "properties": {
    "gn:admin1_code":"19.0",
    "gn:asciiname":"Wangjia Dagou",
    "gn:country_code":"CN",
    "gn:dem":106,
    "gn:feature_class":"P",
    "gn:feature_code":"PPL",
    "gn:name":"Wangjia Dagou",
    "gn:population":0,
    "gn:timezone":"Asia/Shanghai",
    "iso:country":"CN",
    "name:und_x_variant":[
        "\u738b\u5bb6\u5927\u6c9f"
    ],
    "wof:name":"Wangjia Dagou",
    "wof:placetype":"locality"
},
  "geometry": {"coordinates":[123.30233,40.21112],"type":"Point"}
}