{
  "type": "Feature",
  "properties": {
    "gn:admin1_code":"25.0",
    "gn:asciiname":"Tuochekuangcun",
    "gn:country_code":"CN",
    "gn:dem":66,
    "gn:feature_class":"P",
    "gn:feature_code":"PPL",
    "gn:name":"Tuochekuangcun",
    "gn:population":0,
    "gn:timezone":"Asia/Shanghai",
    "iso:country":"CN",
    "name:zho_x_preferred":[
        "\u62d6\u8f66\u593c\u6751"
    ],
    "wof:name":"Tuochekuangcun",
    "wof:placetype":"locality"
},
  "geometry": {"coordinates":[120.54971999999999,36.3616],"type":"Point"}
}