{
  "type": "Feature",
  "properties": {
    "gn:admin1_code":"3.0",
    "gn:asciiname":"Zhuzaikeng Shangcun",
    "gn:country_code":"CN",
    "gn:dem":456,
    "gn:feature_class":"P",
    "gn:feature_code":"PPL",
    "gn:name":"Zhuzaikeng Shangcun",
    "gn:population":0,
    "gn:timezone":"Asia/Shanghai",
    "iso:country":"CN",
    "name:und_x_variant":[
        "\u732a\u4ed4\u5751\u4e0a\u6751"
    ],
    "wof:name":"Zhuzaikeng Shangcun",
    "wof:placetype":"locality"
},
  "geometry": {"coordinates":[116.27611,26.61739],"type":"Point"}
}