{
  "type": "Feature",
  "properties": {
    "gn:admin1_code":"32.0",
    "gn:asciiname":"Changshi",
    "gn:country_code":"CN",
    "gn:dem":336,
    "gn:feature_class":"P",
    "gn:feature_code":"PPL",
    "gn:name":"Changshi",
    "gn:population":0,
    "gn:timezone":"Asia/Shanghai",
    "iso:country":"CN",
    "name:zho_x_preferred":[
        "\u957f\u77f3"
    ],
    "wof:name":"Changshi",
    "wof:placetype":"locality"
},
  "geometry": {"coordinates":[106.714,31.0097],"type":"Point"}
}