{
  "type": "Feature",
  "properties": {
    "gn:admin1_code":"32.0",
    "gn:asciiname":"Changshi",
    "gn:country_code":"CN",
    "gn:dem":336,
    "gn:feature_class":"P",
    "gn:feature_code":"PPL",
    "gn:name":"Changshi",
    "gn:population":0,
    "gn:timezone":"Asia/Shanghai",
    "iso:country":"CN",
    "name:cat_x_preferred":[
        "Txangxi"
    ],
    "name:ita_x_preferred":[
        "Changshi Khan"
    ],
    "name:mon_x_preferred":[
        "\u0427\u0430\u043d\u0448\u0438"
    ],
    "name:uig_x_preferred":[
        "\u0686\u0627\u06ad\u0634\u0649"
    ],
    "name:ukr_x_preferred":[
        "\u0427\u0430\u043d\u043a\u0448\u0456-\u0445\u0430\u043d"
    ],
    "name:uzb_x_preferred":[
        "Djenkshi"
    ],
    "name:zho_x_preferred":[
        "\u957f\u77f3"
    ],
    "wof:name":"Changshi",
    "wof:placetype":"locality"
},
  "geometry": {"coordinates":[106.714,31.0097],"type":"Point"}
}