{
  "type": "Feature",
  "properties": {
    "gn:admin1_code":"11.0",
    "gn:asciiname":"Shijiawan",
    "gn:country_code":"CN",
    "gn:dem":334,
    "gn:feature_class":"P",
    "gn:feature_code":"PPL",
    "gn:name":"Shijiawan",
    "gn:population":0,
    "gn:timezone":"Asia/Shanghai",
    "iso:country":"CN",
    "name:zho_x_preferred":[
        "\u77f3\u5bb6\u6e7e"
    ],
    "wof:name":"Shijiawan",
    "wof:placetype":"locality"
},
  "geometry": {"coordinates":[110.29667999999999,27.29014],"type":"Point"}
}