{
  "type": "Feature",
  "properties": {
    "gn:admin1_code":"14.0",
    "gn:asciiname":"Yongzongka",
    "gn:country_code":"CN",
    "gn:dem":4274,
    "gn:feature_class":"P",
    "gn:feature_code":"PPL",
    "gn:name":"Yongzongka",
    "gn:population":0,
    "gn:timezone":"Asia/Urumqi",
    "iso:country":"CN",
    "name:zho_x_preferred":[
        "\u62e5\u5b97\u5361"
    ],
    "wof:name":"Yongzongka",
    "wof:placetype":"locality"
},
  "geometry": {"coordinates":[95.30927,31.50391],"type":"Point"}
}