{
  "type": "Feature",
  "properties": {
    "gn:admin1_code":"32.0",
    "gn:asciiname":"Gaowuji",
    "gn:country_code":"CN",
    "gn:dem":396,
    "gn:feature_class":"P",
    "gn:feature_code":"PPL",
    "gn:name":"Gaowuji",
    "gn:population":0,
    "gn:timezone":"Asia/Shanghai",
    "iso:country":"CN",
    "name:zho_x_preferred":[
        "\u9ad8\u5c4b\u57fa"
    ],
    "wof:name":"Gaowuji",
    "wof:placetype":"locality"
},
  "geometry": {"coordinates":[107.724,30.9897],"type":"Point"}
}