{
  "type": "Feature",
  "properties": {
    "gn:admin1_code":"8.0",
    "gn:asciiname":"Lixincun",
    "gn:country_code":"CN",
    "gn:dem":125,
    "gn:feature_class":"P",
    "gn:feature_code":"PPL",
    "gn:name":"Lixincun",
    "gn:population":0,
    "gn:timezone":"Asia/Shanghai",
    "iso:country":"CN",
    "name:zho_x_preferred":[
        "\u5229\u65b0\u6751"
    ],
    "wof:name":"Lixincun",
    "wof:placetype":"locality"
},
  "geometry": {"coordinates":[127.89425,46.14625],"type":"Point"}
}