{
  "type": "Feature",
  "properties": {
    "gn:admin1_code":"2.0",
    "gn:asciiname":"Caoxieling",
    "gn:country_code":"CN",
    "gn:dem":258,
    "gn:feature_class":"P",
    "gn:feature_code":"PPL",
    "gn:name":"Caoxieling",
    "gn:population":0,
    "gn:timezone":"Asia/Shanghai",
    "iso:country":"CN",
    "name:zho_x_preferred":[
        "\u8349\u978b\u5cad"
    ],
    "wof:name":"Caoxieling",
    "wof:placetype":"locality"
},
  "geometry": {"coordinates":[118.91117,29.16064],"type":"Point"}
}