{
  "type": "Feature",
  "properties": {
    "gn:admin1_code":"11",
    "gn:asciiname":"Longtian",
    "gn:country_code":"CN",
    "gn:dem":328,
    "gn:feature_class":"P",
    "gn:feature_code":"PPL",
    "gn:name":"Longtian",
    "gn:population":0,
    "gn:timezone":"Asia/Shanghai",
    "iso:country":"CN",
    "name:ceb_x_preferred":[
        "Longtian"
    ],
    "name:swe_x_preferred":[
        "Longtian"
    ],
    "wof:name":"Longtian",
    "wof:placetype":"locality"
},
  "geometry": {"coordinates":[110.07193999999998,27.31028],"type":"Point"}
}