{
  "type": "Feature",
  "properties": {
    "gn:admin1_code":"11.0",
    "gn:asciiname":"Mengxikou",
    "gn:country_code":"CN",
    "gn:dem":349,
    "gn:feature_class":"P",
    "gn:feature_code":"PPL",
    "gn:name":"Mengxikou",
    "gn:population":0,
    "gn:timezone":"Asia/Shanghai",
    "iso:country":"CN",
    "name:zho_x_preferred":[
        "\u5b5f\u6eaa\u53e3"
    ],
    "wof:name":"Mengxikou",
    "wof:placetype":"locality"
},
  "geometry": {"coordinates":[110.3297,28.86068],"type":"Point"}
}