{
  "type": "Feature",
  "properties": {
    "gn:admin1_code":"32.0",
    "gn:asciiname":"Xiongying",
    "gn:country_code":"CN",
    "gn:dem":646,
    "gn:feature_class":"P",
    "gn:feature_code":"PPL",
    "gn:name":"Xiongying",
    "gn:population":0,
    "gn:timezone":"Asia/Shanghai",
    "iso:country":"CN",
    "name:und_x_variant":[
        "\u96c4\u82f1"
    ],
    "wof:name":"Xiongying",
    "wof:placetype":"locality"
},
  "geometry": {"coordinates":[106.47423999999999,32.50747],"type":"Point"}
}