{
  "type": "Feature",
  "properties": {
    "gn:admin1_code":"18",
    "gn:asciiname":"Quanjianshui",
    "gn:country_code":"CN",
    "gn:dem":779,
    "gn:feature_class":"P",
    "gn:feature_code":"PPL",
    "gn:name":"Quanjianshui",
    "gn:population":0,
    "gn:timezone":"Asia/Shanghai",
    "iso:country":"CN",
    "name:zho_x_preferred":[
        "\u6cc9\u6da7\u6c34"
    ],
    "wof:name":"Quanjianshui",
    "wof:placetype":"locality"
},
  "geometry": {"coordinates":[107.16500000000001,27.56],"type":"Point"}
}