{
  "type": "Feature",
  "properties": {
    "gn:admin1_code":"11.0",
    "gn:asciiname":"Mianxupo",
    "gn:country_code":"CN",
    "gn:dem":210,
    "gn:feature_class":"P",
    "gn:feature_code":"PPL",
    "gn:name":"Mianxupo",
    "gn:population":0,
    "gn:timezone":"Asia/Shanghai",
    "iso:country":"CN",
    "name:zho_x_preferred":[
        "\u68c9\u7d6e\u5761"
    ],
    "wof:name":"Mianxupo",
    "wof:placetype":"locality"
},
  "geometry": {"coordinates":[113.63164,27.9565],"type":"Point"}
}