{
  "type": "Feature",
  "properties": {
    "gn:admin1_code":"29",
    "gn:asciiname":"Laolong",
    "gn:country_code":"CN",
    "gn:dem":1299,
    "gn:feature_class":"P",
    "gn:feature_code":"PPL",
    "gn:name":"Laolong",
    "gn:population":0,
    "gn:timezone":"Asia/Shanghai",
    "iso:country":"CN",
    "name:zho_x_preferred":[
        "\u8001\u9f99"
    ],
    "name:zho_x_variant":[
        "\u8001\u9686\u9547"
    ],
    "wof:name":"Laolong",
    "wof:placetype":"locality"
},
  "geometry": {"coordinates":[104.941,24.1227],"type":"Point"}
}