{
  "type": "Feature",
  "properties": {
    "gn:admin1_code":"10.0",
    "gn:asciiname":"Maojiaying",
    "gn:country_code":"CN",
    "gn:dem":18,
    "gn:feature_class":"P",
    "gn:feature_code":"PPL",
    "gn:name":"Maojiaying",
    "gn:population":0,
    "gn:timezone":"Asia/Shanghai",
    "iso:country":"CN",
    "name:zho_x_preferred":[
        "\u6bdb\u5bb6\u8425"
    ],
    "wof:name":"Maojiaying",
    "wof:placetype":"locality"
},
  "geometry": {"coordinates":[116.113,38.0186],"type":"Point"}
}