{
  "type": "Feature",
  "properties": {
    "gn:admin1_code":"30.0",
    "gn:asciiname":"Wanyaoxia",
    "gn:country_code":"CN",
    "gn:dem":309,
    "gn:feature_class":"P",
    "gn:feature_code":"PPL",
    "gn:name":"Wanyaoxia",
    "gn:population":0,
    "gn:timezone":"Asia/Shanghai",
    "iso:country":"CN",
    "name:und_x_variant":[
        "\u7897\u7a91\u4e0b"
    ],
    "name:zho_x_preferred":[
        "\u7897\u7a91\u4e0b"
    ],
    "wof:name":"Wanyaoxia",
    "wof:placetype":"locality"
},
  "geometry": {"coordinates":[114.10059,23.96553],"type":"Point"}
}