{
  "type": "Feature",
  "properties": {
    "gn:admin1_code":"19.0",
    "gn:asciiname":"Tashancun",
    "gn:country_code":"CN",
    "gn:dem":107,
    "gn:feature_class":"P",
    "gn:feature_code":"PPL",
    "gn:name":"Tashancun",
    "gn:population":0,
    "gn:timezone":"Asia/Shanghai",
    "iso:country":"CN",
    "name:zho_x_preferred":[
        "\u5854\u5c71\u6751"
    ],
    "wof:name":"Tashancun",
    "wof:placetype":"locality"
},
  "geometry": {"coordinates":[120.682,41.22600000000001],"type":"Point"}
}