{
  "type": "Feature",
  "properties": {
    "gn:admin1_code":"33",
    "gn:asciiname":"Tuzhu",
    "gn:country_code":"CN",
    "gn:dem":287,
    "gn:feature_class":"P",
    "gn:feature_code":"PPLA4",
    "gn:name":"Tuzhu",
    "gn:population":0,
    "gn:timezone":"Asia/Shanghai",
    "iso:country":"CN",
    "name:und_x_variant":[
        "Tuzhu Zhen"
    ],
    "name:zho_x_preferred":[
        "\u571f\u4e3b"
    ],
    "name:zho_x_variant":[
        "\u571f\u4e3b\u9547"
    ],
    "wof:name":"Tuzhu",
    "wof:placetype":"locality"
},
  "geometry": {"coordinates":[106.36717,29.64412],"type":"Point"}
}