{
  "type": "Feature",
  "properties": {
    "gn:admin1_code":"30.0",
    "gn:asciiname":"Jinjing",
    "gn:country_code":"CN",
    "gn:dem":18,
    "gn:feature_class":"P",
    "gn:feature_code":"PPL",
    "gn:name":"Jinjing",
    "gn:population":0,
    "gn:timezone":"Asia/Urumqi",
    "iso:country":"CN",
    "name:zho_x_preferred":[
        "\u91d1\u4e95"
    ],
    "wof:name":"Jinjing",
    "wof:placetype":"locality"
},
  "geometry": {"coordinates":[110.46988,20.55676],"type":"Point"}
}