{
  "type": "Feature",
  "properties": {
    "gn:admin1_code":"11.0",
    "gn:asciiname":"Pingli",
    "gn:country_code":"CN",
    "gn:dem":260,
    "gn:feature_class":"P",
    "gn:feature_code":"PPL",
    "gn:name":"Pingli",
    "gn:population":0,
    "gn:timezone":"Asia/Shanghai",
    "iso:country":"CN",
    "name:zho_x_preferred":[
        "\u576a\u91cc"
    ],
    "wof:name":"Pingli",
    "wof:placetype":"locality"
},
  "geometry": {"coordinates":[113.43692,26.28572],"type":"Point"}
}