{
  "type": "Feature",
  "properties": {
    "gn:admin1_code":"11",
    "gn:asciiname":"Xiwuzui",
    "gn:country_code":"CN",
    "gn:dem":71,
    "gn:feature_class":"P",
    "gn:feature_code":"PPL",
    "gn:name":"Xiwuzui",
    "gn:population":0,
    "gn:timezone":"Asia/Shanghai",
    "iso:country":"CN",
    "name:zho_x_preferred":[
        "\u7ec6\u5c4b\u5480"
    ],
    "wof:name":"Xiwuzui",
    "wof:placetype":"locality"
},
  "geometry": {"coordinates":[112.35952,27.78612],"type":"Point"}
}