{
  "type": "Feature",
  "properties": {
    "gn:admin1_code":"19.0",
    "gn:asciiname":"Huahongyu",
    "gn:country_code":"CN",
    "gn:dem":165,
    "gn:feature_class":"P",
    "gn:feature_code":"PPL",
    "gn:name":"Huahongyu",
    "gn:population":0,
    "gn:timezone":"Asia/Shanghai",
    "iso:country":"CN",
    "name:zho_x_preferred":[
        "\u82b1\u7ea2\u5cea"
    ],
    "wof:name":"Huahongyu",
    "wof:placetype":"locality"
},
  "geometry": {"coordinates":[123.05477,40.67421],"type":"Point"}
}