{
  "type": "Feature",
  "properties": {
    "gn:admin1_code":"14.0",
    "gn:asciiname":"Xarxoi",
    "gn:country_code":"CN",
    "gn:dem":3897,
    "gn:feature_class":"P",
    "gn:feature_code":"PPL",
    "gn:name":"Xarxoi",
    "gn:population":0,
    "gn:timezone":"Asia/Urumqi",
    "iso:country":"CN",
    "name:bod_x_preferred":[
        "Xarxoi"
    ],
    "name:zho_x_preferred":[
        "Xiaxue"
    ],
    "name:zho_x_variant":[
        "\u590f\u5b66",
        "Tubujia Gongshe",
        "\u571f\u5e03\u52a0\u516c\u793e"
    ],
    "wof:name":"Xarxoi",
    "wof:placetype":"locality"
},
  "geometry": {"coordinates":[89.4457,29.4129],"type":"Point"}
}