{
  "type": "Feature",
  "properties": {
    "gn:admin1_code":"30.0",
    "gn:asciiname":"Fulingcun",
    "gn:country_code":"CN",
    "gn:dem":206,
    "gn:feature_class":"P",
    "gn:feature_code":"PPL",
    "gn:name":"Fulingcun",
    "gn:population":0,
    "gn:timezone":"Asia/Shanghai",
    "iso:country":"CN",
    "name:zho_x_preferred":[
        "\u5bcc\u5cad\u6751"
    ],
    "wof:name":"Fulingcun",
    "wof:placetype":"locality"
},
  "geometry": {"coordinates":[116.73356,24.1445],"type":"Point"}
}