{
  "type": "Feature",
  "properties": {
    "gn:admin1_code":"11.0",
    "gn:asciiname":"Linjiaping",
    "gn:country_code":"CN",
    "gn:dem":131,
    "gn:feature_class":"P",
    "gn:feature_code":"PPL",
    "gn:name":"Linjiaping",
    "gn:population":0,
    "gn:timezone":"Asia/Shanghai",
    "iso:country":"CN",
    "name:zho_x_preferred":[
        "\u6797\u5bb6\u576a"
    ],
    "wof:name":"Linjiaping",
    "wof:placetype":"locality"
},
  "geometry": {"coordinates":[113.7192,28.7196],"type":"Point"}
}