{
  "type": "Feature",
  "properties": {
    "gn:admin1_code":"12.0",
    "gn:asciiname":"Sunjiapo",
    "gn:country_code":"CN",
    "gn:dem":176,
    "gn:feature_class":"P",
    "gn:feature_code":"PPL",
    "gn:name":"Sunjiapo",
    "gn:population":0,
    "gn:timezone":"Asia/Shanghai",
    "iso:country":"CN",
    "name:zho_x_preferred":[
        "Sunjiapo"
    ],
    "name:zho_x_variant":[
        "\u5b59\u5bb6\u5761"
    ],
    "wof:name":"Sunjiapo",
    "wof:placetype":"locality"
},
  "geometry": {"coordinates":[111.26000000000001,30.31371],"type":"Point"}
}