{
  "type": "Feature",
  "properties": {
    "gn:admin1_code":"25.0",
    "gn:asciiname":"Gujia",
    "gn:country_code":"CN",
    "gn:dem":117,
    "gn:feature_class":"P",
    "gn:feature_code":"PPL",
    "gn:name":"Gujia",
    "gn:population":0,
    "gn:timezone":"Asia/Shanghai",
    "iso:country":"CN",
    "name:bih_x_preferred":[
        "\u0917\u094b\u091d\u093f\u092f\u093e"
    ],
    "name:fra_x_preferred":[
        "Gujia"
    ],
    "name:hin_x_preferred":[
        "\u0917\u0941\u091d\u093f\u092f\u093e"
    ],
    "name:mai_x_preferred":[
        "\u092a\u0941\u0921\u093c\u0941\u0915\u093f\u092f\u093e"
    ],
    "name:mal_x_preferred":[
        "\u0d17\u0d41\u0d1c\u0d3f\u0d2f"
    ],
    "name:ori_x_preferred":[
        "\u0b15\u0b30\u0b1e\u0b4d\u0b1c\u0b3f"
    ],
    "name:pan_x_preferred":[
        "\u0a17\u0a41\u0a1c\u0a40\u0a06"
    ],
    "name:pnb_x_preferred":[
        "\u06af\u062c\u06cc\u0627"
    ],
    "name:tel_x_preferred":[
        "\u0c15\u0c1c\u0c4d\u0c1c\u0c3f\u0c15\u0c3e\u0c2f"
    ],
    "name:zho_x_preferred":[
        "\u987e\u5bb6"
    ],
    "wof:name":"Gujia",
    "wof:placetype":"locality"
},
  "geometry": {"coordinates":[120.46612,37.11155],"type":"Point"}
}