{
  "type": "Feature",
  "properties": {
    "gn:admin1_code":"15.0",
    "gn:asciiname":"Sujiashan",
    "gn:country_code":"CN",
    "gn:dem":2399,
    "gn:feature_class":"P",
    "gn:feature_code":"PPL",
    "gn:name":"Sujiashan",
    "gn:population":0,
    "gn:timezone":"Asia/Shanghai",
    "iso:country":"CN",
    "name:zho_x_preferred":[
        "\u82cf\u5bb6\u5c71"
    ],
    "wof:name":"Sujiashan",
    "wof:placetype":"locality"
},
  "geometry": {"coordinates":[105.23099999999999,36.5368],"type":"Point"}
}