{
  "type": "Feature",
  "properties": {
    "gn:admin1_code":"25",
    "gn:asciiname":"Matiejiangzhuang",
    "gn:country_code":"CN",
    "gn:dem":26,
    "gn:feature_class":"P",
    "gn:feature_code":"PPL",
    "gn:name":"Matiejiangzhuang",
    "gn:population":0,
    "gn:timezone":"Asia/Shanghai",
    "iso:country":"CN",
    "name:zho_x_preferred":[
        "\u9a6c\u94c1\u5320\u5e84"
    ],
    "wof:name":"Matiejiangzhuang",
    "wof:placetype":"locality"
},
  "geometry": {"coordinates":[116.48399999999999,37.091],"type":"Point"}
}