{
  "type": "Feature",
  "properties": {
    "gn:admin1_code":"5.0",
    "gn:asciiname":"Beigouling",
    "gn:country_code":"CN",
    "gn:dem":672,
    "gn:feature_class":"P",
    "gn:feature_code":"PPL",
    "gn:name":"Beigouling",
    "gn:population":0,
    "gn:timezone":"Asia/Shanghai",
    "iso:country":"CN",
    "name:und_x_variant":[
        "\u5317\u6c9f\u5cad"
    ],
    "wof:name":"Beigouling",
    "wof:placetype":"locality"
},
  "geometry": {"coordinates":[128.63773,42.95563],"type":"Point"}
}