{
  "type": "Feature",
  "properties": {
    "gn:admin1_code":"30.0",
    "gn:asciiname":"Sanzhou Xicun",
    "gn:country_code":"CN",
    "gn:dem":130,
    "gn:feature_class":"P",
    "gn:feature_code":"PPL",
    "gn:name":"Sanzhou Xicun",
    "gn:population":0,
    "gn:timezone":"Asia/Shanghai",
    "iso:country":"CN",
    "name:zho_x_preferred":[
        "\u4e09\u6d32\u6eaa\u6751"
    ],
    "wof:name":"Sanzhou Xicun",
    "wof:placetype":"locality"
},
  "geometry": {"coordinates":[116.4864,24.09297],"type":"Point"}
}