{
  "type": "Feature",
  "properties": {
    "gn:admin1_code":"16.0",
    "gn:asciiname":"Liangshanchong",
    "gn:country_code":"CN",
    "gn:dem":179,
    "gn:feature_class":"P",
    "gn:feature_code":"PPL",
    "gn:name":"Liangshanchong",
    "gn:population":0,
    "gn:timezone":"Asia/Shanghai",
    "iso:country":"CN",
    "name:zho_x_preferred":[
        "\u51c9\u5c71\u51b2"
    ],
    "wof:name":"Liangshanchong",
    "wof:placetype":"locality"
},
  "geometry": {"coordinates":[108.623,24.4622],"type":"Point"}
}