{
  "type": "Feature",
  "properties": {
    "gn:admin1_code":"18",
    "gn:asciiname":"Yangliuyuan",
    "gn:country_code":"CN",
    "gn:dem":916,
    "gn:feature_class":"P",
    "gn:feature_code":"PPL",
    "gn:name":"Yangliuyuan",
    "gn:population":0,
    "gn:timezone":"Asia/Shanghai",
    "iso:country":"CN",
    "name:zho_x_preferred":[
        "\u6768\u67f3\u56ed"
    ],
    "wof:name":"Yangliuyuan",
    "wof:placetype":"locality"
},
  "geometry": {"coordinates":[107.72799999999999,28.9478],"type":"Point"}
}