{
  "type": "Feature",
  "properties": {
    "gn:admin1_code":"25",
    "gn:asciiname":"Dashenbu",
    "gn:country_code":"CN",
    "gn:dem":57,
    "gn:feature_class":"P",
    "gn:feature_code":"PPL",
    "gn:name":"Dashenbu",
    "gn:population":0,
    "gn:timezone":"Asia/Shanghai",
    "iso:country":"CN",
    "name:zho_x_preferred":[
        "\u5927\u6c88\u57e0"
    ],
    "wof:name":"Dashenbu",
    "wof:placetype":"locality"
},
  "geometry": {"coordinates":[118.682,34.7075],"type":"Point"}
}