{
  "type": "Feature",
  "properties": {
    "gn:admin1_code":"32.0",
    "gn:asciiname":"Maoshanqiao",
    "gn:country_code":"CN",
    "gn:dem":278,
    "gn:feature_class":"P",
    "gn:feature_code":"PPL",
    "gn:name":"Maoshanqiao",
    "gn:population":0,
    "gn:timezone":"Asia/Shanghai",
    "iso:country":"CN",
    "name:zho_x_preferred":[
        "\u6bdb\u5584\u6865"
    ],
    "wof:name":"Maoshanqiao",
    "wof:placetype":"locality"
},
  "geometry": {"coordinates":[105.59741,28.97189],"type":"Point"}
}