{
  "type": "Feature",
  "properties": {
    "gn:admin1_code":"16.0",
    "gn:asciiname":"Changdong",
    "gn:country_code":"CN",
    "gn:dem":592,
    "gn:feature_class":"P",
    "gn:feature_code":"PPL",
    "gn:name":"Changdong",
    "gn:population":0,
    "gn:timezone":"Asia/Shanghai",
    "iso:country":"CN",
    "name:zho_x_preferred":[
        "\u957f\u5cd2"
    ],
    "wof:name":"Changdong",
    "wof:placetype":"locality"
},
  "geometry": {"coordinates":[107.372,24.2592],"type":"Point"}
}