{
  "type": "Feature",
  "properties": {
    "gn:admin1_code":"25",
    "gn:asciiname":"Lihuayuan",
    "gn:country_code":"CN",
    "gn:dem":48,
    "gn:feature_class":"P",
    "gn:feature_code":"PPL",
    "gn:name":"Lihuayuan",
    "gn:population":0,
    "gn:timezone":"Asia/Shanghai",
    "iso:country":"CN",
    "name:und_x_variant":[
        "Huayuan"
    ],
    "name:zho_x_preferred":[
        "\u674e\u82b1\u56ed"
    ],
    "name:zho_x_variant":[
        "\u82b1\u56ed"
    ],
    "wof:name":"Lihuayuan",
    "wof:placetype":"locality"
},
  "geometry": {"coordinates":[115.721,35.2253],"type":"Point"}
}