{
  "type": "Feature",
  "properties": {
    "gn:admin1_code":"29",
    "gn:asciiname":"Daheitu",
    "gn:country_code":"CN",
    "gn:dem":1779,
    "gn:feature_class":"P",
    "gn:feature_code":"PPL",
    "gn:name":"Daheitu",
    "gn:population":0,
    "gn:timezone":"Asia/Shanghai",
    "iso:country":"CN",
    "name:zho_x_preferred":[
        "\u5927\u9ed1\u571f"
    ],
    "wof:name":"Daheitu",
    "wof:placetype":"locality"
},
  "geometry": {"coordinates":[103.227,24.1975],"type":"Point"}
}