{
  "type": "Feature",
  "properties": {
    "gn:admin1_code":"11.0",
    "gn:asciiname":"Jinhuaquan",
    "gn:country_code":"CN",
    "gn:dem":296,
    "gn:feature_class":"P",
    "gn:feature_code":"PPL",
    "gn:name":"Jinhuaquan",
    "gn:population":0,
    "gn:timezone":"Asia/Shanghai",
    "iso:country":"CN",
    "name:zho_x_preferred":[
        "Jinhuaquan"
    ],
    "name:zho_x_variant":[
        "\u91d1\u82b1\u6cc9"
    ],
    "wof:name":"Jinhuaquan",
    "wof:placetype":"locality"
},
  "geometry": {"coordinates":[111.0818,29.07635],"type":"Point"}
}