{
  "type": "Feature",
  "properties": {
    "gn:admin1_code":"32.0",
    "gn:asciiname":"Puling",
    "gn:country_code":"CN",
    "gn:dem":360,
    "gn:feature_class":"P",
    "gn:feature_code":"PPL",
    "gn:name":"Puling",
    "gn:population":0,
    "gn:timezone":"Asia/Shanghai",
    "iso:country":"CN",
    "name:zho_x_preferred":[
        "\u666e\u5cad"
    ],
    "wof:name":"Puling",
    "wof:placetype":"locality"
},
  "geometry": {"coordinates":[106.85065,31.2571],"type":"Point"}
}