{
  "type": "Feature",
  "properties": {
    "gn:admin1_code":"18",
    "gn:asciiname":"Huangjiaoba",
    "gn:country_code":"CN",
    "gn:dem":1337,
    "gn:feature_class":"P",
    "gn:feature_code":"PPL",
    "gn:name":"Huangjiaoba",
    "gn:population":0,
    "gn:timezone":"Asia/Shanghai",
    "iso:country":"CN",
    "name:zho_x_preferred":[
        "\u9ec4\u89d2\u575d"
    ],
    "wof:name":"Huangjiaoba",
    "wof:placetype":"locality"
},
  "geometry": {"coordinates":[105.38,25.5911],"type":"Point"}
}