{
  "type": "Feature",
  "properties": {
    "gn:admin1_code":"16.0",
    "gn:asciiname":"Lapu",
    "gn:country_code":"CN",
    "gn:dem":305,
    "gn:feature_class":"P",
    "gn:feature_code":"PPL",
    "gn:name":"Lapu",
    "gn:population":0,
    "gn:timezone":"Asia/Shanghai",
    "iso:country":"CN",
    "name:zho_x_preferred":[
        "\u62c9\u666e"
    ],
    "wof:name":"Lapu",
    "wof:placetype":"locality"
},
  "geometry": {"coordinates":[108.068,24.5479],"type":"Point"}
}