{
  "type": "Feature",
  "properties": {
    "gn:admin1_code":"16.0",
    "gn:asciiname":"Lapu",
    "gn:country_code":"CN",
    "gn:dem":305,
    "gn:feature_class":"P",
    "gn:feature_code":"PPL",
    "gn:name":"Lapu",
    "gn:population":0,
    "gn:timezone":"Asia/Shanghai",
    "iso:country":"CN",
    "name:ceb_x_preferred":[
        "Lapu"
    ],
    "name:mai_x_preferred":[
        "\u0932\u092a\u0941"
    ],
    "name:msa_x_preferred":[
        "Lapu"
    ],
    "name:new_x_preferred":[
        "\u0932\u093e\u092a\u0941"
    ],
    "name:pol_x_preferred":[
        "Lapu"
    ],
    "name:urd_x_preferred":[
        "\u0644\u0627\u067e\u0648"
    ],
    "name:zho_x_preferred":[
        "\u62c9\u666e"
    ],
    "wof:name":"Lapu",
    "wof:placetype":"locality"
},
  "geometry": {"coordinates":[108.068,24.5479],"type":"Point"}
}