{
  "type": "Feature",
  "properties": {
    "gn:admin1_code":"7.0",
    "gn:asciiname":"Qiaozitou",
    "gn:country_code":"CN",
    "gn:dem":240,
    "gn:feature_class":"P",
    "gn:feature_code":"PPL",
    "gn:name":"Qiaozitou",
    "gn:population":0,
    "gn:timezone":"Asia/Shanghai",
    "iso:country":"CN",
    "name:zho_x_preferred":[
        "\u6865\u5b50\u5934"
    ],
    "wof:name":"Qiaozitou",
    "wof:placetype":"locality"
},
  "geometry": {"coordinates":[116.77743999999998,24.77447],"type":"Point"}
}