{
  "type": "Feature",
  "properties": {
    "gn:admin1_code":"07",
    "gn:asciiname":"Luodijia",
    "gn:country_code":"CN",
    "gn:dem":206,
    "gn:feature_class":"P",
    "gn:feature_code":"PPL",
    "gn:name":"Luodijia",
    "gn:population":0,
    "gn:timezone":"Asia/Shanghai",
    "iso:country":"CN",
    "name:zho_x_preferred":[
        "\u7f57\u5730\u7532"
    ],
    "wof:name":"Luodijia",
    "wof:placetype":"locality"
},
  "geometry": {"coordinates":[117.38540999999999,25.93262],"type":"Point"}
}