{
  "type": "Feature",
  "properties": {
    "gn:admin1_code":"7.0",
    "gn:asciiname":"Danian",
    "gn:country_code":"CN",
    "gn:dem":373,
    "gn:feature_class":"P",
    "gn:feature_code":"PPL",
    "gn:name":"Danian",
    "gn:population":0,
    "gn:timezone":"Asia/Shanghai",
    "iso:country":"CN",
    "name:afr_x_preferred":[
        "Danium"
    ],
    "name:ara_x_preferred":[
        "\u0627\u0644\u062f\u0627\u0646\u064a"
    ],
    "name:ast_x_preferred":[
        "Danianu"
    ],
    "name:cat_x_preferred":[
        "Dani\u00e0"
    ],
    "name:dan_x_preferred":[
        "Danien"
    ],
    "name:deu_x_preferred":[
        "Danium"
    ],
    "name:eus_x_preferred":[
        "Daniar"
    ],
    "name:fas_x_preferred":[
        "\u062f\u0627\u0646\u06cc\u0646"
    ],
    "name:fin_x_preferred":[
        "Dania-vaihe"
    ],
    "name:fra_x_preferred":[
        "Danien"
    ],
    "name:ita_x_preferred":[
        "Daniano"
    ],
    "name:jpn_x_preferred":[
        "\u30c0\u30cb\u30a2\u30f3"
    ],
    "name:nds_x_preferred":[
        "Danium"
    ],
    "name:nld_x_preferred":[
        "Danien"
    ],
    "name:nno_x_preferred":[
        "Danium"
    ],
    "name:pol_x_preferred":[
        "Dan"
    ],
    "name:por_x_preferred":[
        "Daniano"
    ],
    "name:rus_x_preferred":[
        "\u0414\u0430\u0442\u0441\u043a\u0438\u0439 \u044f\u0440\u0443\u0441"
    ],
    "name:spa_x_preferred":[
        "Daniense"
    ],
    "name:swe_x_preferred":[
        "Dan"
    ],
    "name:ukr_x_preferred":[
        "\u0414\u0430\u043d\u0441\u044c\u043a\u0438\u0439 \u044f\u0440\u0443\u0441"
    ],
    "name:zho_x_preferred":[
        "\u5927\u5e74"
    ],
    "name:zho_x_variant":[
        "\u8fbe\u5b81\u671f"
    ],
    "wof:name":"Danian",
    "wof:placetype":"locality"
},
  "geometry": {"coordinates":[117.62555999999999,27.56561],"type":"Point"}
}