{
  "type": "Feature",
  "properties": {
    "gn:admin1_code":"1.0",
    "gn:asciiname":"Nibawacun",
    "gn:country_code":"CN",
    "gn:dem":39,
    "gn:feature_class":"P",
    "gn:feature_code":"PPL",
    "gn:name":"Nibawacun",
    "gn:population":0,
    "gn:timezone":"Asia/Shanghai",
    "iso:country":"CN",
    "name:zho_x_preferred":[
        "\u6ce5\u5df4\u6d3c\u6751"
    ],
    "wof:name":"Nibawacun",
    "wof:placetype":"locality"
},
  "geometry": {"coordinates":[115.20180999999999,32.68656],"type":"Point"}
}