{
  "type": "Feature",
  "properties": {
    "gn:admin1_code":"32.0",
    "gn:asciiname":"Cujiaomajue",
    "gn:country_code":"CN",
    "gn:dem":2772,
    "gn:feature_class":"P",
    "gn:feature_code":"PPL",
    "gn:name":"Cujiaomajue",
    "gn:population":0,
    "gn:timezone":"Asia/Shanghai",
    "iso:country":"CN",
    "name:zho_x_preferred":[
        "\u7c97\u89d2\u9a6c\u89c9"
    ],
    "wof:name":"Cujiaomajue",
    "wof:placetype":"locality"
},
  "geometry": {"coordinates":[103.28182,28.39945],"type":"Point"}
}