{
  "type": "Feature",
  "properties": {
    "gn:admin1_code":"33",
    "gn:asciiname":"Daxi",
    "gn:country_code":"CN",
    "gn:dem":391,
    "gn:feature_class":"P",
    "gn:feature_code":"PPLA4",
    "gn:name":"Daxi",
    "gn:population":0,
    "gn:timezone":"Asia/Shanghai",
    "iso:country":"CN",
    "name:und_x_variant":[
        "Daxi Zhen",
        "Daxi"
    ],
    "name:zho_x_preferred":[
        "\u5927\u6eaa"
    ],
    "name:zho_x_variant":[
        "\u5927\u6eaa\u9547"
    ],
    "wof:name":"Daxi",
    "wof:placetype":"locality"
},
  "geometry": {"coordinates":[109.14797,29.09405],"type":"Point"}
}