{
  "type": "Feature",
  "properties": {
    "gn:admin1_code":"15.0",
    "gn:asciiname":"Caijiashan",
    "gn:country_code":"CN",
    "gn:dem":1268,
    "gn:feature_class":"P",
    "gn:feature_code":"PPL",
    "gn:name":"Caijiashan",
    "gn:population":0,
    "gn:timezone":"Asia/Shanghai",
    "iso:country":"CN",
    "name:zho_x_preferred":[
        "\u624d\u5bb6\u5c71"
    ],
    "wof:name":"Caijiashan",
    "wof:placetype":"locality"
},
  "geometry": {"coordinates":[108.465,35.3725],"type":"Point"}
}