{
  "type": "Feature",
  "properties": {
    "gn:admin1_code":"19.0",
    "gn:asciiname":"Fengtaichang",
    "gn:country_code":"CN",
    "gn:dem":372,
    "gn:feature_class":"P",
    "gn:feature_code":"PPL",
    "gn:name":"Fengtaichang",
    "gn:population":0,
    "gn:timezone":"Asia/Shanghai",
    "iso:country":"CN",
    "name:zho_x_preferred":[
        "\u4e30\u6cf0\u660c"
    ],
    "wof:name":"Fengtaichang",
    "wof:placetype":"locality"
},
  "geometry": {"coordinates":[124.666,40.7372],"type":"Point"}
}