{
  "type": "Feature",
  "properties": {
    "gn:admin1_code":"2.0",
    "gn:asciiname":"Lijiabang",
    "gn:country_code":"CN",
    "gn:dem":6,
    "gn:feature_class":"P",
    "gn:feature_code":"PPL",
    "gn:name":"Lijiabang",
    "gn:population":0,
    "gn:timezone":"Asia/Shanghai",
    "iso:country":"CN",
    "name:und_x_variant":[
        "\u674e\u5bb6\u6d5c"
    ],
    "wof:name":"Lijiabang",
    "wof:placetype":"locality"
},
  "geometry": {"coordinates":[120.56529999999999,30.75557],"type":"Point"}
}