{
  "type": "Feature",
  "properties": {
    "gn:admin1_code":"15.0",
    "gn:asciiname":"Shiyang",
    "gn:country_code":"CN",
    "gn:dem":1348,
    "gn:feature_class":"P",
    "gn:feature_code":"PPL",
    "gn:name":"Shiyang",
    "gn:population":0,
    "gn:timezone":"Asia/Shanghai",
    "iso:country":"CN",
    "name:zho_x_preferred":[
        "\u77f3\u7f8a"
    ],
    "wof:name":"Shiyang",
    "wof:placetype":"locality"
},
  "geometry": {"coordinates":[107.36199999999999,35.6777],"type":"Point"}
}