{
  "type": "Feature",
  "properties": {
    "gn:admin1_code":"8.0",
    "gn:asciiname":"Fuyoucun",
    "gn:country_code":"CN",
    "gn:dem":199,
    "gn:feature_class":"P",
    "gn:feature_code":"PPL",
    "gn:name":"Fuyoucun",
    "gn:population":0,
    "gn:timezone":"Asia/Shanghai",
    "iso:country":"CN",
    "name:zho_x_preferred":[
        "\u5bcc\u6709\u6751"
    ],
    "wof:name":"Fuyoucun",
    "wof:placetype":"locality"
},
  "geometry": {"coordinates":[127.38421,47.03582],"type":"Point"}
}