{
  "type": "Feature",
  "properties": {
    "gn:admin1_code":"24.0",
    "gn:asciiname":"Haodongcun",
    "gn:country_code":"CN",
    "gn:dem":762,
    "gn:feature_class":"P",
    "gn:feature_code":"PPL",
    "gn:name":"Haodongcun",
    "gn:population":0,
    "gn:timezone":"Asia/Shanghai",
    "iso:country":"CN",
    "name:zho_x_preferred":[
        "\u90dd\u6d1e\u6751"
    ],
    "wof:name":"Haodongcun",
    "wof:placetype":"locality"
},
  "geometry": {"coordinates":[112.27006000000002,37.28283],"type":"Point"}
}