{
  "type": "Feature",
  "properties": {
    "gn:admin1_code":"21.0",
    "gn:asciiname":"Tongdong Sandui",
    "gn:country_code":"CN",
    "gn:dem":1107,
    "gn:feature_class":"P",
    "gn:feature_code":"PPLF",
    "gn:name":"Tongdong Sandui",
    "gn:population":0,
    "gn:timezone":"Asia/Shanghai",
    "iso:country":"CN",
    "name:zho_x_preferred":[
        "\u901a\u4e1c\u4e09\u961f"
    ],
    "wof:name":"Tongdong Sandui",
    "wof:placetype":"locality"
},
  "geometry": {"coordinates":[106.506,38.4906],"type":"Point"}
}