{
  "type": "Feature",
  "properties": {
    "gn:admin1_code":"29.0",
    "gn:asciiname":"Liangzhuzhai",
    "gn:country_code":"CN",
    "gn:dem":1163,
    "gn:feature_class":"P",
    "gn:feature_code":"PPL",
    "gn:name":"Liangzhuzhai",
    "gn:population":0,
    "gn:timezone":"Asia/Shanghai",
    "iso:country":"CN",
    "name:zho_x_preferred":[
        "\u826f\u7af9\u5be8"
    ],
    "wof:name":"Liangzhuzhai",
    "wof:placetype":"locality"
},
  "geometry": {"coordinates":[102.66,22.7658],"type":"Point"}
}