{
  "type": "Feature",
  "properties": {
    "gn:admin1_code":"13",
    "gn:asciiname":"Pie'erma Kuduke",
    "gn:country_code":"CN",
    "gn:dem":1288,
    "gn:feature_class":"P",
    "gn:feature_code":"PPL",
    "gn:name":"Pie\u2019erma Kuduke",
    "gn:population":0,
    "gn:timezone":"Asia/Urumqi",
    "iso:country":"CN",
    "name:und_x_variant":[
        "Pie\u2019erma Kuduke",
        "\u6487\u5c14\u9a6c\u5e93\u90fd\u514b"
    ],
    "wof:name":"Pie'erma Kuduke",
    "wof:placetype":"locality"
},
  "geometry": {"coordinates":[91.52106000000001,44.18054],"type":"Point"}
}