{
  "type": "Feature",
  "properties": {
    "gn:admin1_code":"33.0",
    "gn:asciiname":"Haoyang",
    "gn:country_code":"CN",
    "gn:dem":284,
    "gn:feature_class":"P",
    "gn:feature_code":"PPL",
    "gn:name":"Haoyang",
    "gn:population":0,
    "gn:timezone":"Asia/Shanghai",
    "iso:country":"CN",
    "name:zho_x_preferred":[
        "\u6d69\u6d0b"
    ],
    "wof:name":"Haoyang",
    "wof:placetype":"locality"
},
  "geometry": {"coordinates":[105.64772000000001,30.11002],"type":"Point"}
}