{
  "type": "Feature",
  "properties": {
    "gn:admin1_code":"20.0",
    "gn:asciiname":"Tiemian Wudong",
    "gn:country_code":"CN",
    "gn:dem":1740,
    "gn:feature_class":"P",
    "gn:feature_code":"PPL",
    "gn:name":"Tiemian Wudong",
    "gn:population":0,
    "gn:timezone":"Asia/Shanghai",
    "iso:country":"CN",
    "name:und_x_variant":[
        "\u94c1\u9762\u52ff\u6d1e"
    ],
    "wof:name":"Tiemian Wudong",
    "wof:placetype":"locality"
},
  "geometry": {"coordinates":[113.02433000000001,41.31045],"type":"Point"}
}