{
  "type": "Feature",
  "properties": {
    "gn:admin1_code":"6.0",
    "gn:asciiname":"Ba'eqin Jiyi",
    "gn:country_code":"CN",
    "gn:dem":3809,
    "gn:feature_class":"P",
    "gn:feature_code":"PPL",
    "gn:name":"Ba\u2019eqin Jiyi",
    "gn:population":0,
    "gn:timezone":"Asia/Urumqi",
    "iso:country":"CN",
    "name:und_x_variant":[
        "Ba\u2019eqin Jiyi"
    ],
    "name:zho_x_preferred":[
        "\u5df4\u4fc4\u94a6\u7ed9\u610f"
    ],
    "wof:name":"Ba'eqin Jiyi",
    "wof:placetype":"locality"
},
  "geometry": {"coordinates":[96.92894,33.01604],"type":"Point"}
}