{
  "type": "Feature",
  "properties": {
    "gn:admin1_code":"6.0",
    "gn:asciiname":"Wushijiu Daoban",
    "gn:country_code":"CN",
    "gn:dem":4171,
    "gn:feature_class":"P",
    "gn:feature_code":"PPL",
    "gn:name":"Wushijiu Daoban",
    "gn:population":0,
    "gn:timezone":"Asia/Urumqi",
    "iso:country":"CN",
    "name:und_x_variant":[
        "\u4e94\u5341\u4e5d\u9053\u73ed"
    ],
    "wof:name":"Wushijiu Daoban",
    "wof:placetype":"locality"
},
  "geometry": {"coordinates":[94.32838,35.75523],"type":"Point"}
}