{
  "type": "Feature",
  "properties": {
    "gn:admin1_code":"19.0",
    "gn:asciiname":"Dahutai",
    "gn:country_code":"CN",
    "gn:dem":5,
    "gn:feature_class":"P",
    "gn:feature_code":"PPL",
    "gn:name":"Dahutai",
    "gn:population":0,
    "gn:timezone":"Asia/Shanghai",
    "iso:country":"CN",
    "name:und_x_variant":[
        "\u5927\u80e1\u53f0"
    ],
    "wof:name":"Dahutai",
    "wof:placetype":"locality"
},
  "geometry": {"coordinates":[122.205,40.9614],"type":"Point"}
}