{
  "type": "Feature",
  "properties": {
    "gn:admin1_code":"8.0",
    "gn:asciiname":"Dachangcun",
    "gn:country_code":"CN",
    "gn:dem":94,
    "gn:feature_class":"P",
    "gn:feature_code":"PPL",
    "gn:name":"Dachangcun",
    "gn:population":0,
    "gn:timezone":"Asia/Shanghai",
    "iso:country":"CN",
    "name:zho_x_preferred":[
        "\u5927\u660c\u6751"
    ],
    "wof:name":"Dachangcun",
    "wof:placetype":"locality"
},
  "geometry": {"coordinates":[129.75394,46.66314000000001],"type":"Point"}
}