{
  "type": "Feature",
  "properties": {
    "gn:admin1_code":"14",
    "gn:asciiname":"Changma",
    "gn:country_code":"CN",
    "gn:dem":4724,
    "gn:feature_class":"P",
    "gn:feature_code":"PPL",
    "gn:name":"Changma",
    "gn:population":0,
    "gn:timezone":"Asia/Urumqi",
    "iso:country":"CN",
    "name:zho_x_preferred":[
        "\u5e38\u739b"
    ],
    "wof:name":"Changma",
    "wof:placetype":"locality"
},
  "geometry": {"coordinates":[87.87690000000001,32.2664],"type":"Point"}
}