{
  "type": "Feature",
  "properties": {
    "gn:admin1_code":"30.0",
    "gn:asciiname":"Waijieyong",
    "gn:country_code":"CN",
    "gn:dem":3,
    "gn:feature_class":"P",
    "gn:feature_code":"PPL",
    "gn:name":"Waijieyong",
    "gn:population":0,
    "gn:timezone":"Asia/Shanghai",
    "iso:country":"CN",
    "name:zho_x_preferred":[
        "\u5916\u754c\u6d8c"
    ],
    "wof:name":"Waijieyong",
    "wof:placetype":"locality"
},
  "geometry": {"coordinates":[113.47729,22.31051],"type":"Point"}
}