{
  "type": "Feature",
  "properties": {
    "gn:admin1_code":"32.0",
    "gn:asciiname":"Yuanpoxi",
    "gn:country_code":"CN",
    "gn:dem":2667,
    "gn:feature_class":"P",
    "gn:feature_code":"PPL",
    "gn:name":"Yuanpoxi",
    "gn:population":0,
    "gn:timezone":"Asia/Shanghai",
    "iso:country":"CN",
    "name:zho_x_preferred":[
        "\u56ed\u5a46\u897f"
    ],
    "wof:name":"Yuanpoxi",
    "wof:placetype":"locality"
},
  "geometry": {"coordinates":[101.52249999999999,27.66189],"type":"Point"}
}