{
  "type": "Feature",
  "properties": {
    "gn:admin1_code":"02",
    "gn:asciiname":"Baoyang",
    "gn:country_code":"CN",
    "gn:dem":3,
    "gn:feature_class":"P",
    "gn:feature_code":"PPL",
    "gn:name":"Baoyang",
    "gn:population":0,
    "gn:timezone":"Asia/Shanghai",
    "iso:country":"CN",
    "name:zho_x_preferred":[
        "\u9b91\u579f"
    ],
    "wof:name":"Baoyang",
    "wof:placetype":"locality"
},
  "geometry": {"coordinates":[120.73976999999999,27.8008],"type":"Point"}
}