{
  "type": "Feature",
  "properties": {
    "gn:admin1_code":"29.0",
    "gn:asciiname":"Gaojiancao",
    "gn:country_code":"CN",
    "gn:dem":1983,
    "gn:feature_class":"P",
    "gn:feature_code":"PPL",
    "gn:name":"Gaojiancao",
    "gn:population":0,
    "gn:timezone":"Asia/Shanghai",
    "iso:country":"CN",
    "name:zho_x_preferred":[
        "\u9ad8\u67a7\u69fd"
    ],
    "wof:name":"Gaojiancao",
    "wof:placetype":"locality"
},
  "geometry": {"coordinates":[103.521,25.4588],"type":"Point"}
}