{
  "type": "Feature",
  "properties": {
    "gn:admin1_code":"8.0",
    "gn:asciiname":"Weixing",
    "gn:country_code":"CN",
    "gn:dem":322,
    "gn:feature_class":"P",
    "gn:feature_code":"PPL",
    "gn:name":"Weixing",
    "gn:population":0,
    "gn:timezone":"Asia/Shanghai",
    "iso:country":"CN",
    "name:und_x_variant":[
        "\u536b\u661f"
    ],
    "wof:name":"Weixing",
    "wof:placetype":"locality"
},
  "geometry": {"coordinates":[127.03308,49.63127],"type":"Point"}
}