{
  "type": "Feature",
  "properties": {
    "gn:admin1_code":"26.0",
    "gn:asciiname":"Jiezhuangcun",
    "gn:country_code":"CN",
    "gn:dem":924,
    "gn:feature_class":"P",
    "gn:feature_code":"PPL",
    "gn:name":"Jiezhuangcun",
    "gn:population":0,
    "gn:timezone":"Asia/Shanghai",
    "iso:country":"CN",
    "name:zho_x_preferred":[
        "\u89e3\u5e84\u6751"
    ],
    "wof:name":"Jiezhuangcun",
    "wof:placetype":"locality"
},
  "geometry": {"coordinates":[110.00642999999999,35.35055999999999],"type":"Point"}
}