{
  "type": "Feature",
  "properties": {
    "gn:admin1_code":"10.0",
    "gn:asciiname":"Chadaozi",
    "gn:country_code":"CN",
    "gn:dem":744,
    "gn:feature_class":"P",
    "gn:feature_code":"PPL",
    "gn:name":"Chadaozi",
    "gn:population":0,
    "gn:timezone":"Asia/Shanghai",
    "iso:country":"CN",
    "name:zho_x_preferred":[
        "\u5c94\u9053\u5b50"
    ],
    "wof:name":"Chadaozi",
    "wof:placetype":"locality"
},
  "geometry": {"coordinates":[114.93980000000001,39.46073],"type":"Point"}
}