{
  "type": "Feature",
  "properties": {
    "gn:admin1_code":"12",
    "gn:asciiname":"Jiantian",
    "gn:country_code":"CN",
    "gn:dem":1220,
    "gn:feature_class":"P",
    "gn:feature_code":"PPL",
    "gn:name":"Jiantian",
    "gn:population":0,
    "gn:timezone":"Asia/Shanghai",
    "iso:country":"CN",
    "name:zho_x_preferred":[
        "\u89c1\u5929"
    ],
    "wof:name":"Jiantian",
    "wof:placetype":"locality"
},
  "geometry": {"coordinates":[109.06283000000001,30.45247],"type":"Point"}
}