{
  "type": "Feature",
  "properties": {
    "gn:admin1_code":"30.0",
    "gn:asciiname":"Yanghezhai",
    "gn:country_code":"CN",
    "gn:dem":253,
    "gn:feature_class":"P",
    "gn:feature_code":"PPL",
    "gn:name":"Yanghezhai",
    "gn:population":0,
    "gn:timezone":"Asia/Shanghai",
    "iso:country":"CN",
    "name:und_x_variant":[
        "\u9633\u548c\u5be8"
    ],
    "name:zho_x_preferred":[
        "\u9633\u548c\u5be8"
    ],
    "wof:name":"Yanghezhai",
    "wof:placetype":"locality"
},
  "geometry": {"coordinates":[115.33839,23.44375],"type":"Point"}
}