{
  "type": "Feature",
  "properties": {
    "gn:admin1_code":"25",
    "gn:asciiname":"Bajiazhu",
    "gn:country_code":"CN",
    "gn:dem":4,
    "gn:feature_class":"P",
    "gn:feature_code":"PPL",
    "gn:name":"Bajiazhu",
    "gn:population":0,
    "gn:timezone":"Asia/Shanghai",
    "iso:country":"CN",
    "name:zho_x_preferred":[
        "\u516b\u7532\u6731"
    ],
    "wof:name":"Bajiazhu",
    "wof:placetype":"locality"
},
  "geometry": {"coordinates":[119.05800000000001,36.9519],"type":"Point"}
}