{
  "type": "Feature",
  "properties": {
    "gn:admin1_code":"8.0",
    "gn:asciiname":"Xishanhetun",
    "gn:country_code":"CN",
    "gn:dem":264,
    "gn:feature_class":"P",
    "gn:feature_code":"PPL",
    "gn:name":"Xishanhetun",
    "gn:population":0,
    "gn:timezone":"Asia/Shanghai",
    "iso:country":"CN",
    "name:zho_x_preferred":[
        "\u897f\u5c71\u5408\u5c6f"
    ],
    "wof:name":"Xishanhetun",
    "wof:placetype":"locality"
},
  "geometry": {"coordinates":[125.01479999999999,48.21876],"type":"Point"}
}