{
  "type": "Feature",
  "properties": {
    "gn:admin1_code":"2.0",
    "gn:asciiname":"Tianchang",
    "gn:country_code":"CN",
    "gn:dem":533,
    "gn:feature_class":"P",
    "gn:feature_code":"PPL",
    "gn:name":"Tianchang",
    "gn:population":0,
    "gn:timezone":"Asia/Shanghai",
    "iso:country":"CN",
    "name:ara_x_preferred":[
        "\u062a\u064a\u0627\u0646\u0634\u0627\u0646\u063a"
    ],
    "name:deu_x_preferred":[
        "Tianchang"
    ],
    "name:fas_x_preferred":[
        "\u062a\u06cc\u0627\u0646\u0686\u0627\u0646\u06af"
    ],
    "name:fra_x_preferred":[
        "Tianchang"
    ],
    "name:ita_x_preferred":[
        "Tianchang"
    ],
    "name:jpn_x_preferred":[
        "\u5929\u9577\u5e02"
    ],
    "name:kik_x_preferred":[
        "Tianchang"
    ],
    "name:kor_x_preferred":[
        "\ud188\ucc3d\uc2dc"
    ],
    "name:mlg_x_preferred":[
        "Tianchang"
    ],
    "name:mwl_x_preferred":[
        "Tianchang"
    ],
    "name:nld_x_preferred":[
        "Tianchang"
    ],
    "name:nor_x_preferred":[
        "Tianchang"
    ],
    "name:pam_x_preferred":[
        "Tianchang"
    ],
    "name:spa_x_preferred":[
        "Ti\u0101nch\u00e1ng Sh\u00ec"
    ],
    "name:swe_x_preferred":[
        "Tianchang"
    ],
    "name:urd_x_preferred":[
        "\u062a\u06cc\u0627\u0646\u0686\u0627\u0646\u06af"
    ],
    "name:vie_x_preferred":[
        "Thi\u00ean Tr\u01b0\u1eddng"
    ],
    "name:wuu_x_preferred":[
        "\u5929\u957f\u5e02"
    ],
    "name:zho_x_preferred":[
        "\u7530\u5382"
    ],
    "name:zho_x_variant":[
        "\u5929\u957f\u5e02"
    ],
    "wof:name":"Tianchang",
    "wof:placetype":"locality"
},
  "geometry": {"coordinates":[120.11758,27.69056],"type":"Point"}
}