{
  "type": "Feature",
  "properties": {
    "gn:admin1_code":"25",
    "gn:asciiname":"Anliucun",
    "gn:country_code":"CN",
    "gn:dem":48,
    "gn:feature_class":"P",
    "gn:feature_code":"PPL",
    "gn:name":"Anliucun",
    "gn:population":0,
    "gn:timezone":"Asia/Shanghai",
    "iso:country":"CN",
    "name:zho_x_preferred":[
        "\u5b89\u516d\u6751"
    ],
    "wof:name":"Anliucun",
    "wof:placetype":"locality"
},
  "geometry": {"coordinates":[116.294,34.6313],"type":"Point"}
}