{
  "type": "Feature",
  "properties": {
    "gn:admin1_code":"4.0",
    "gn:asciiname":"Gaoxia",
    "gn:country_code":"CN",
    "gn:dem":1,
    "gn:feature_class":"P",
    "gn:feature_code":"PPL",
    "gn:name":"Gaoxia",
    "gn:population":0,
    "gn:timezone":"Asia/Shanghai",
    "iso:country":"CN",
    "name:zho_x_preferred":[
        "Gaoxia"
    ],
    "name:zho_x_variant":[
        "\u9ad8\u590f"
    ],
    "wof:name":"Gaoxia",
    "wof:placetype":"locality"
},
  "geometry": {"coordinates":[119.65197999999999,33.26982],"type":"Point"}
}