{
  "type": "Feature",
  "properties": {
    "gn:admin1_code":"14.0",
    "gn:asciiname":"Suoxiongcun",
    "gn:country_code":"CN",
    "gn:dem":4310,
    "gn:feature_class":"P",
    "gn:feature_code":"PPL",
    "gn:name":"Suoxiongcun",
    "gn:population":0,
    "gn:timezone":"Asia/Urumqi",
    "iso:country":"CN",
    "name:zho_x_preferred":[
        "\u7d22\u96c4\u6751"
    ],
    "wof:name":"Suoxiongcun",
    "wof:placetype":"locality"
},
  "geometry": {"coordinates":[93.38514000000001,32.3072],"type":"Point"}
}