{
  "type": "Feature",
  "properties": {
    "gn:admin1_code":"26.0",
    "gn:asciiname":"Gantianwan",
    "gn:country_code":"CN",
    "gn:dem":313,
    "gn:feature_class":"P",
    "gn:feature_code":"PPL",
    "gn:name":"Gantianwan",
    "gn:population":0,
    "gn:timezone":"Asia/Shanghai",
    "iso:country":"CN",
    "name:zho_x_preferred":[
        "\u5e72\u7530\u6e7e"
    ],
    "wof:name":"Gantianwan",
    "wof:placetype":"locality"
},
  "geometry": {"coordinates":[108.68854,32.78874],"type":"Point"}
}