{
  "type": "Feature",
  "properties": {
    "gn:admin1_code":"33.0",
    "gn:asciiname":"Yanchengba",
    "gn:country_code":"CN",
    "gn:dem":853,
    "gn:feature_class":"P",
    "gn:feature_code":"PPL",
    "gn:name":"Yanchengba",
    "gn:population":0,
    "gn:timezone":"Asia/Shanghai",
    "iso:country":"CN",
    "name:zho_x_preferred":[
        "\u5ca9\u57ce\u575d"
    ],
    "wof:name":"Yanchengba",
    "wof:placetype":"locality"
},
  "geometry": {"coordinates":[108.58349,28.98225],"type":"Point"}
}