{
  "type": "Feature",
  "properties": {
    "gn:admin1_code":"11",
    "gn:asciiname":"Chezhushan",
    "gn:country_code":"CN",
    "gn:dem":191,
    "gn:feature_class":"P",
    "gn:feature_code":"PPL",
    "gn:name":"Chezhushan",
    "gn:population":0,
    "gn:timezone":"Asia/Shanghai",
    "iso:country":"CN",
    "name:zho_x_preferred":[
        "\u8f66\u7af9\u5c71"
    ],
    "wof:name":"Chezhushan",
    "wof:placetype":"locality"
},
  "geometry": {"coordinates":[111.2897,27.7856],"type":"Point"}
}