{
  "type": "Feature",
  "properties": {
    "gn:admin1_code":"19.0",
    "gn:asciiname":"Housanyangtou",
    "gn:country_code":"CN",
    "gn:dem":7,
    "gn:feature_class":"P",
    "gn:feature_code":"PPL",
    "gn:name":"Housanyangtou",
    "gn:population":0,
    "gn:timezone":"Asia/Shanghai",
    "iso:country":"CN",
    "name:zho_x_preferred":[
        "\u540e\u4e09\u7f8a\u5934"
    ],
    "wof:name":"Housanyangtou",
    "wof:placetype":"locality"
},
  "geometry": {"coordinates":[121.15067999999999,38.8043],"type":"Point"}
}