{
  "type": "Feature",
  "properties": {
    "gn:admin1_code":"24",
    "gn:asciiname":"Chuandi",
    "gn:cc2":"CN",
    "gn:country_code":"CN",
    "gn:dem":749,
    "gn:feature_class":"P",
    "gn:feature_code":"PPL",
    "gn:name":"Chuandi",
    "gn:population":0,
    "gn:timezone":"Asia/Shanghai",
    "iso:country":"CN",
    "name:und_x_variant":[
        "Ch\u2019uan-ti",
        "Ch\u2019uan-ti-ts\u2019un",
        "Chuandi"
    ],
    "wof:name":"Chuandi",
    "wof:placetype":"locality"
},
  "geometry": {"coordinates":[112.68167,35.5275],"type":"Point"}
}