{
  "type": "Feature",
  "properties": {
    "gn:admin1_code":"3.0",
    "gn:asciiname":"Gankengkou",
    "gn:country_code":"CN",
    "gn:dem":205,
    "gn:feature_class":"P",
    "gn:feature_code":"PPL",
    "gn:name":"Gankengkou",
    "gn:population":0,
    "gn:timezone":"Asia/Shanghai",
    "iso:country":"CN",
    "name:und_x_variant":[
        "\u5e72\u5751\u53e3"
    ],
    "wof:name":"Gankengkou",
    "wof:placetype":"locality"
},
  "geometry": {"coordinates":[114.19067,29.03],"type":"Point"}
}