{
  "type": "Feature",
  "properties": {
    "gn:admin1_code":"12.0",
    "gn:asciiname":"Huangyanxi",
    "gn:country_code":"CN",
    "gn:dem":1001,
    "gn:feature_class":"P",
    "gn:feature_code":"PPL",
    "gn:name":"Huangyanxi",
    "gn:population":0,
    "gn:timezone":"Asia/Shanghai",
    "iso:country":"CN",
    "name:zho_x_preferred":[
        "\u9ec4\u6cbf\u6eaa"
    ],
    "wof:name":"Huangyanxi",
    "wof:placetype":"locality"
},
  "geometry": {"coordinates":[110.96623,30.55481],"type":"Point"}
}