{
  "type": "Feature",
  "properties": {
    "gn:admin1_code":"14.0",
    "gn:asciiname":"Zhaxilie",
    "gn:country_code":"CN",
    "gn:dem":3814,
    "gn:feature_class":"P",
    "gn:feature_code":"PPL",
    "gn:name":"Zhaxilie",
    "gn:population":0,
    "gn:timezone":"Asia/Urumqi",
    "iso:country":"CN",
    "name:zho_x_preferred":[
        "\u624e\u897f\u5217"
    ],
    "wof:name":"Zhaxilie",
    "wof:placetype":"locality"
},
  "geometry": {"coordinates":[98.14756,32.24231],"type":"Point"}
}