{
  "type": "Feature",
  "properties": {
    "gn:admin1_code":"14.0",
    "gn:asciiname":"Qaqukong",
    "gn:country_code":"CN",
    "gn:dem":4438,
    "gn:feature_class":"P",
    "gn:feature_code":"PPL",
    "gn:name":"Qaqukong",
    "gn:population":0,
    "gn:timezone":"Asia/Urumqi",
    "iso:country":"CN",
    "name:bod_x_preferred":[
        "Qaqukong"
    ],
    "name:zho_x_preferred":[
        "Jiaqugong"
    ],
    "name:zho_x_variant":[
        "\u7532\u66f2\u8d21"
    ],
    "wof:name":"Qaqukong",
    "wof:placetype":"locality"
},
  "geometry": {"coordinates":[93.19974999999999,28.3477],"type":"Point"}
}