{
  "type": "Feature",
  "properties": {
    "gn:admin1_code":"32.0",
    "gn:asciiname":"Jianjiaodi",
    "gn:country_code":"CN",
    "gn:dem":1800,
    "gn:feature_class":"P",
    "gn:feature_code":"PPL",
    "gn:name":"Jianjiaodi",
    "gn:population":0,
    "gn:timezone":"Asia/Shanghai",
    "iso:country":"CN",
    "name:zho_x_preferred":[
        "\u5c16\u89d2\u5730"
    ],
    "wof:name":"Jianjiaodi",
    "wof:placetype":"locality"
},
  "geometry": {"coordinates":[102.39,26.4363],"type":"Point"}
}