{
  "type": "Feature",
  "properties": {
    "gn:admin1_code":"32",
    "gn:asciiname":"Fenggu",
    "gn:country_code":"CN",
    "gn:dem":437,
    "gn:feature_class":"P",
    "gn:feature_code":"PPL",
    "gn:name":"Fenggu",
    "gn:population":0,
    "gn:timezone":"Asia/Shanghai",
    "iso:country":"CN",
    "name:und_x_variant":[
        "Fengguzhen",
        "Feng-y\u00fc-ching",
        "Feng-ku",
        "Feng-ku-chen",
        "F_nyuytszin",
        "Fenggu"
    ],
    "wof:name":"Fenggu",
    "wof:placetype":"locality"
},
  "geometry": {"coordinates":[104.82572999999999,31.35148],"type":"Point"}
}