{
  "type": "Feature",
  "properties": {
    "gn:admin1_code":"26.0",
    "gn:asciiname":"Yuanyuanshang",
    "gn:country_code":"CN",
    "gn:dem":1256,
    "gn:feature_class":"P",
    "gn:feature_code":"PPL",
    "gn:name":"Yuanyuanshang",
    "gn:population":0,
    "gn:timezone":"Asia/Shanghai",
    "iso:country":"CN",
    "name:zho_x_preferred":[
        "\u9662\u56ed\u4e0a"
    ],
    "wof:name":"Yuanyuanshang",
    "wof:placetype":"locality"
},
  "geometry": {"coordinates":[106.81562,34.68343],"type":"Point"}
}