{
  "type": "Feature",
  "properties": {
    "gn:admin1_code":"26.0",
    "gn:asciiname":"Tai'ercun",
    "gn:country_code":"CN",
    "gn:dem":1199,
    "gn:feature_class":"P",
    "gn:feature_code":"PPL",
    "gn:name":"Tai\u2019ercun",
    "gn:population":0,
    "gn:timezone":"Asia/Shanghai",
    "iso:country":"CN",
    "name:und_x_variant":[
        "Tai\u2019ercun"
    ],
    "name:zho_x_preferred":[
        "\u53f0\u5c14\u6751"
    ],
    "wof:name":"Tai'ercun",
    "wof:placetype":"locality"
},
  "geometry": {"coordinates":[108.72508999999999,35.01714],"type":"Point"}
}