{
  "type": "Feature",
  "properties": {
    "gn:admin1_code":"2.0",
    "gn:asciiname":"Daling",
    "gn:country_code":"CN",
    "gn:dem":97,
    "gn:feature_class":"P",
    "gn:feature_code":"PPL",
    "gn:name":"Daling",
    "gn:population":0,
    "gn:timezone":"Asia/Shanghai",
    "iso:country":"CN",
    "name:ceb_x_preferred":[
        "Daling"
    ],
    "name:swe_x_preferred":[
        "Daling"
    ],
    "name:zho_x_preferred":[
        "\u5927\u5cad"
    ],
    "wof:name":"Daling",
    "wof:placetype":"locality"
},
  "geometry": {"coordinates":[122.04828999999999,30.10006],"type":"Point"}
}