{
  "type": "Feature",
  "properties": {
    "gn:admin1_code":"1.0",
    "gn:asciiname":"Yandiancun",
    "gn:country_code":"CN",
    "gn:dem":28,
    "gn:feature_class":"P",
    "gn:feature_code":"PPL",
    "gn:name":"Yandiancun",
    "gn:population":0,
    "gn:timezone":"Asia/Shanghai",
    "iso:country":"CN",
    "name:zho_x_preferred":[
        "\u960e\u5e97\u6751"
    ],
    "wof:name":"Yandiancun",
    "wof:placetype":"locality"
},
  "geometry": {"coordinates":[117.04846999999999,33.60515],"type":"Point"}
}