{
  "type": "Feature",
  "properties": {
    "gn:admin1_code":"19.0",
    "gn:asciiname":"Xigouli",
    "gn:country_code":"CN",
    "gn:dem":138,
    "gn:feature_class":"P",
    "gn:feature_code":"PPL",
    "gn:name":"Xigouli",
    "gn:population":0,
    "gn:timezone":"Asia/Shanghai",
    "iso:country":"CN",
    "name:und_x_variant":[
        "\u897f\u6c9f\u91cc"
    ],
    "wof:name":"Xigouli",
    "wof:placetype":"locality"
},
  "geometry": {"coordinates":[123.99943,40.36596],"type":"Point"}
}