{
  "type": "Feature",
  "properties": {
    "gn:admin1_code":"7.0",
    "gn:asciiname":"Wenjia",
    "gn:country_code":"CN",
    "gn:dem":512,
    "gn:feature_class":"P",
    "gn:feature_code":"PPL",
    "gn:name":"Wenjia",
    "gn:population":0,
    "gn:timezone":"Asia/Shanghai",
    "iso:country":"CN",
    "name:und_x_variant":[
        "\u6e29\u5bb6"
    ],
    "name:zho_x_preferred":[
        "\u6e29\u5bb6"
    ],
    "wof:name":"Wenjia",
    "wof:placetype":"locality"
},
  "geometry": {"coordinates":[117.06386000000001,26.26533],"type":"Point"}
}