{
  "type": "Feature",
  "properties": {
    "gn:admin1_code":"9.0",
    "gn:asciiname":"Dadaizhuang",
    "gn:country_code":"CN",
    "gn:dem":79,
    "gn:feature_class":"P",
    "gn:feature_code":"PPL",
    "gn:name":"Dadaizhuang",
    "gn:population":0,
    "gn:timezone":"Asia/Shanghai",
    "iso:country":"CN",
    "name:zho_x_preferred":[
        "\u5927\u6234\u5e84"
    ],
    "wof:name":"Dadaizhuang",
    "wof:placetype":"locality"
},
  "geometry": {"coordinates":[114.16392,32.54306],"type":"Point"}
}