{
  "type": "Feature",
  "properties": {
    "gn:admin1_code":"11",
    "gn:asciiname":"Sangesi",
    "gn:country_code":"CN",
    "gn:dem":254,
    "gn:feature_class":"P",
    "gn:feature_code":"PPLA4",
    "gn:name":"Sangesi",
    "gn:population":0,
    "gn:timezone":"Asia/Shanghai",
    "iso:country":"CN",
    "name:und_x_variant":[
        "Sangesi Xiang"
    ],
    "name:zho_x_preferred":[
        "\u4e09\u9601\u53f8"
    ],
    "name:zho_x_variant":[
        "\u4e09\u9601\u53f8\u4e61"
    ],
    "wof:name":"Sangesi",
    "wof:placetype":"locality"
},
  "geometry": {"coordinates":[110.95444000000001,27.06694],"type":"Point"}
}