{
  "type": "Feature",
  "properties": {
    "gn:admin1_code":"18.0",
    "gn:asciiname":"Kabang Dazhai",
    "gn:country_code":"CN",
    "gn:dem":935,
    "gn:feature_class":"P",
    "gn:feature_code":"PPL",
    "gn:name":"Kabang Dazhai",
    "gn:population":0,
    "gn:timezone":"Asia/Shanghai",
    "iso:country":"CN",
    "name:zho_x_preferred":[
        "\u5361\u699c\u5927\u5be8"
    ],
    "wof:name":"Kabang Dazhai",
    "wof:placetype":"locality"
},
  "geometry": {"coordinates":[107.441,25.9431],"type":"Point"}
}