{
  "type": "Feature",
  "properties": {
    "gn:admin1_code":"01",
    "gn:asciiname":"Jinniu",
    "gn:cc2":"CN",
    "gn:country_code":"CN",
    "gn:dem":11,
    "gn:feature_class":"P",
    "gn:feature_code":"PPL",
    "gn:name":"Jinniu",
    "gn:population":0,
    "gn:timezone":"Asia/Shanghai",
    "iso:country":"CN",
    "name:und_x_variant":[
        "Chin-niu-chen",
        "Chin-niu",
        "Jinniu"
    ],
    "wof:name":"Jinniu",
    "wof:placetype":"locality"
},
  "geometry": {"coordinates":[117.20611,31.39778],"type":"Point"}
}