{
  "type": "Feature",
  "properties": {
    "gn:admin1_code":"9.0",
    "gn:asciiname":"Yangbei",
    "gn:country_code":"CN",
    "gn:dem":427,
    "gn:feature_class":"P",
    "gn:feature_code":"PPL",
    "gn:name":"Yangbei",
    "gn:population":0,
    "gn:timezone":"Asia/Shanghai",
    "iso:country":"CN",
    "name:zho_x_preferred":[
        "\u9633\u80cc"
    ],
    "wof:name":"Yangbei",
    "wof:placetype":"locality"
},
  "geometry": {"coordinates":[112.37315,34.99310999999999],"type":"Point"}
}