{
  "type": "Feature",
  "properties": {
    "gn:admin1_code":"20",
    "gn:asciiname":"Chijiacun",
    "gn:country_code":"CN",
    "gn:dem":1418,
    "gn:feature_class":"P",
    "gn:feature_code":"PPL",
    "gn:name":"Chijiacun",
    "gn:population":0,
    "gn:timezone":"Asia/Shanghai",
    "iso:country":"CN",
    "wof:name":"Chijiacun",
    "wof:placetype":"locality"
},
  "geometry": {"coordinates":[113.54277999999999,41.6375],"type":"Point"}
}