{
  "type": "Feature",
  "properties": {
    "gn:admin1_code":"32.0",
    "gn:asciiname":"Xiangding",
    "gn:country_code":"CN",
    "gn:dem":2686,
    "gn:feature_class":"P",
    "gn:feature_code":"PPL",
    "gn:name":"Xiangding",
    "gn:population":0,
    "gn:timezone":"Asia/Shanghai",
    "iso:country":"CN",
    "name:zho_x_preferred":[
        "\u5411\u4e01"
    ],
    "wof:name":"Xiangding",
    "wof:placetype":"locality"
},
  "geometry": {"coordinates":[100.59035,28.77688],"type":"Point"}
}