{
  "type": "Feature",
  "properties": {
    "gn:admin1_code":"7",
    "gn:asciiname":"Yuangu",
    "gn:country_code":"CN",
    "gn:dem":186,
    "gn:feature_class":"P",
    "gn:feature_code":"PPL",
    "gn:name":"Yuangu",
    "gn:population":0,
    "gn:timezone":"Asia/Shanghai",
    "iso:country":"CN",
    "name:und_x_variant":[
        "\u56ed\u53e4"
    ],
    "wof:name":"Yuangu",
    "wof:placetype":"locality"
},
  "geometry": {"coordinates":[118.73778,27.27],"type":"Point"}
}