{
  "type": "Feature",
  "properties": {
    "gn:admin1_code":"16.0",
    "gn:asciiname":"Litoucao",
    "gn:country_code":"CN",
    "gn:dem":1337,
    "gn:feature_class":"P",
    "gn:feature_code":"PPL",
    "gn:name":"Litoucao",
    "gn:population":0,
    "gn:timezone":"Asia/Shanghai",
    "iso:country":"CN",
    "name:zho_x_preferred":[
        "\u91cc\u5934\u69fd"
    ],
    "wof:name":"Litoucao",
    "wof:placetype":"locality"
},
  "geometry": {"coordinates":[106.42400000000001,24.7554],"type":"Point"}
}