{
  "type": "Feature",
  "properties": {
    "gn:admin1_code":"15.0",
    "gn:asciiname":"Dinggou",
    "gn:country_code":"CN",
    "gn:dem":2089,
    "gn:feature_class":"P",
    "gn:feature_code":"PPL",
    "gn:name":"Dinggou",
    "gn:population":0,
    "gn:timezone":"Asia/Shanghai",
    "iso:country":"CN",
    "name:zho_x_preferred":[
        "\u4e01\u6c9f"
    ],
    "wof:name":"Dinggou",
    "wof:placetype":"locality"
},
  "geometry": {"coordinates":[104.94499999999999,35.4206],"type":"Point"}
}