{
  "type": "Feature",
  "properties": {
    "gn:admin1_code":"25.0",
    "gn:asciiname":"Menjiabucun",
    "gn:country_code":"CN",
    "gn:dem":30,
    "gn:feature_class":"P",
    "gn:feature_code":"PPL",
    "gn:name":"Menjiabucun",
    "gn:population":0,
    "gn:timezone":"Asia/Shanghai",
    "iso:country":"CN",
    "name:zho_x_preferred":[
        "\u95e8\u5bb6\u57e0\u6751"
    ],
    "wof:name":"Menjiabucun",
    "wof:placetype":"locality"
},
  "geometry": {"coordinates":[119.81066,36.29765],"type":"Point"}
}