{
  "type": "Feature",
  "properties": {
    "gn:admin1_code":"29.0",
    "gn:asciiname":"Kuiqing",
    "gn:country_code":"CN",
    "gn:dem":1614,
    "gn:feature_class":"P",
    "gn:feature_code":"PPL",
    "gn:name":"Kuiqing",
    "gn:population":0,
    "gn:timezone":"Asia/Shanghai",
    "iso:country":"CN",
    "name:zho_x_preferred":[
        "\u9b41\u7b90"
    ],
    "wof:name":"Kuiqing",
    "wof:placetype":"locality"
},
  "geometry": {"coordinates":[101.24299999999999,24.1077],"type":"Point"}
}