{
  "type": "Feature",
  "properties": {
    "gn:admin1_code":"15.0",
    "gn:asciiname":"Maoci",
    "gn:country_code":"CN",
    "gn:dem":1807,
    "gn:feature_class":"P",
    "gn:feature_code":"PPL",
    "gn:name":"Maoci",
    "gn:population":0,
    "gn:timezone":"Asia/Shanghai",
    "iso:country":"CN",
    "name:zho_x_preferred":[
        "\u8305\u8328"
    ],
    "wof:name":"Maoci",
    "wof:placetype":"locality"
},
  "geometry": {"coordinates":[103.59699999999999,36.3618],"type":"Point"}
}