{
  "type": "Feature",
  "properties": {
    "gn:admin1_code":"7.0",
    "gn:asciiname":"Cuoxiang",
    "gn:country_code":"CN",
    "gn:dem":10,
    "gn:feature_class":"P",
    "gn:feature_code":"PPL",
    "gn:name":"Cuoxiang",
    "gn:population":0,
    "gn:timezone":"Asia/Shanghai",
    "iso:country":"CN",
    "name:zho_x_preferred":[
        "\u539d\u7965"
    ],
    "wof:name":"Cuoxiang",
    "wof:placetype":"locality"
},
  "geometry": {"coordinates":[119.73043,25.49485],"type":"Point"}
}