{
  "type": "Feature",
  "properties": {
    "gn:admin1_code":"25",
    "gn:asciiname":"Dazhuzhou",
    "gn:country_code":"CN",
    "gn:dem":153,
    "gn:feature_class":"P",
    "gn:feature_code":"PPL",
    "gn:name":"Dazhuzhou",
    "gn:population":0,
    "gn:timezone":"Asia/Shanghai",
    "iso:country":"CN",
    "name:und_x_variant":[
        "\u5927\u6731\u6d32"
    ],
    "wof:name":"Dazhuzhou",
    "wof:placetype":"locality"
},
  "geometry": {"coordinates":[119.03627,35.39702],"type":"Point"}
}