{
  "type": "Feature",
  "properties": {
    "gn:admin1_code":"4.0",
    "gn:asciiname":"Caoqiaocun",
    "gn:country_code":"CN",
    "gn:dem":2,
    "gn:feature_class":"P",
    "gn:feature_code":"PPL",
    "gn:name":"Caoqiaocun",
    "gn:population":0,
    "gn:timezone":"Asia/Shanghai",
    "iso:country":"CN",
    "name:zho_x_preferred":[
        "\u6f15\u6865\u6751"
    ],
    "wof:name":"Caoqiaocun",
    "wof:placetype":"locality"
},
  "geometry": {"coordinates":[119.70489000000001,33.40228],"type":"Point"}
}