{
  "type": "Feature",
  "properties": {
    "gn:admin1_code":"3.0",
    "gn:asciiname":"Youkeng",
    "gn:country_code":"CN",
    "gn:dem":277,
    "gn:feature_class":"P",
    "gn:feature_code":"PPL",
    "gn:name":"Youkeng",
    "gn:population":0,
    "gn:timezone":"Asia/Shanghai",
    "iso:country":"CN",
    "name:und_x_variant":[
        "\u6cb9\u5751"
    ],
    "wof:name":"Youkeng",
    "wof:placetype":"locality"
},
  "geometry": {"coordinates":[115.05842,25.13303],"type":"Point"}
}