{
  "type": "Feature",
  "properties": {
    "gn:admin1_code":"29",
    "gn:asciiname":"Douganli",
    "gn:country_code":"CN",
    "gn:dem":1984,
    "gn:feature_class":"P",
    "gn:feature_code":"PPL",
    "gn:name":"Douganli",
    "gn:population":0,
    "gn:timezone":"Asia/Shanghai",
    "iso:country":"CN",
    "name:zho_x_preferred":[
        "\u6597\u5e72\u5229"
    ],
    "wof:name":"Douganli",
    "wof:placetype":"locality"
},
  "geometry": {"coordinates":[101.191,24.86],"type":"Point"}
}