{
  "type": "Feature",
  "properties": {
    "gn:admin1_code":"24.0",
    "gn:asciiname":"Zhong'ersi",
    "gn:country_code":"CN",
    "gn:dem":948,
    "gn:feature_class":"P",
    "gn:feature_code":"PPL",
    "gn:name":"Zhong\u2019ersi",
    "gn:population":0,
    "gn:timezone":"Asia/Shanghai",
    "iso:country":"CN",
    "name:und_x_variant":[
        "\u949f\u8033\u5bfa"
    ],
    "name:zho_x_preferred":[
        "Zhong\u2019ersi"
    ],
    "name:zho_x_variant":[
        "\u949f\u8033\u5bfa"
    ],
    "wof:name":"Zhong'ersi",
    "wof:placetype":"locality"
},
  "geometry": {"coordinates":[113.89637,39.15163],"type":"Point"}
}