{
  "type": "Feature",
  "properties": {
    "gn:admin1_code":"25",
    "gn:asciiname":"Liujiazhaozi",
    "gn:country_code":"CN",
    "gn:dem":233,
    "gn:feature_class":"P",
    "gn:feature_code":"PPL",
    "gn:name":"Liujiazhaozi",
    "gn:population":0,
    "gn:timezone":"Asia/Shanghai",
    "iso:country":"CN",
    "name:zho_x_preferred":[
        "\u5218\u5bb6\u53ec\u5b50"
    ],
    "wof:name":"Liujiazhaozi",
    "wof:placetype":"locality"
},
  "geometry": {"coordinates":[117.923,35.7435],"type":"Point"}
}