{
  "type": "Feature",
  "properties": {
    "gn:admin1_code":"19.0",
    "gn:asciiname":"Xiaqinghe",
    "gn:country_code":"CN",
    "gn:dem":192,
    "gn:feature_class":"P",
    "gn:feature_code":"PPL",
    "gn:name":"Xiaqinghe",
    "gn:population":0,
    "gn:timezone":"Asia/Shanghai",
    "iso:country":"CN",
    "name:und_x_variant":[
        "\u4e0b\u6e05\u6cb3"
    ],
    "name:zho_x_preferred":[
        "\u4e0b\u6e05\u6cb3"
    ],
    "wof:name":"Xiaqinghe",
    "wof:placetype":"locality"
},
  "geometry": {"coordinates":[124.71294,42.3707],"type":"Point"}
}