{
  "type": "Feature",
  "properties": {
    "gn:admin1_code":"3.0",
    "gn:asciiname":"Zhuzi",
    "gn:country_code":"CN",
    "gn:dem":466,
    "gn:feature_class":"P",
    "gn:feature_code":"PPL",
    "gn:name":"Zhuzi",
    "gn:population":0,
    "gn:timezone":"Asia/Shanghai",
    "iso:country":"CN",
    "name:und_x_variant":[
        "\u682a\u6893"
    ],
    "wof:name":"Zhuzi",
    "wof:placetype":"locality"
},
  "geometry": {"coordinates":[114.95323999999999,28.78083],"type":"Point"}
}