{
  "type": "Feature",
  "properties": {
    "gn:admin1_code":"5.0",
    "gn:asciiname":"Niangniangmiao",
    "gn:country_code":"CN",
    "gn:dem":200,
    "gn:feature_class":"P",
    "gn:feature_code":"PPL",
    "gn:name":"Niangniangmiao",
    "gn:population":0,
    "gn:timezone":"Asia/Shanghai",
    "iso:country":"CN",
    "name:zho_x_preferred":[
        "\u5a18\u5a18\u5e99"
    ],
    "wof:name":"Niangniangmiao",
    "wof:placetype":"locality"
},
  "geometry": {"coordinates":[126.24652,44.08213],"type":"Point"}
}