{
  "type": "Feature",
  "properties": {
    "gn:admin1_code":"15.0",
    "gn:asciiname":"Xishankou",
    "gn:country_code":"CN",
    "gn:dem":2801,
    "gn:feature_class":"P",
    "gn:feature_code":"PPL",
    "gn:name":"Xishankou",
    "gn:population":0,
    "gn:timezone":"Asia/Urumqi",
    "iso:country":"CN",
    "name:zho_x_preferred":[
        "\u897f\u5c71\u53e3"
    ],
    "wof:name":"Xishankou",
    "wof:placetype":"locality"
},
  "geometry": {"coordinates":[97.06659999999999,39.4568],"type":"Point"}
}