{
  "type": "Feature",
  "properties": {
    "gn:admin1_code":"20.0",
    "gn:asciiname":"Caosiyao",
    "gn:country_code":"CN",
    "gn:dem":1301,
    "gn:feature_class":"P",
    "gn:feature_code":"PPL",
    "gn:name":"Caosiyao",
    "gn:population":0,
    "gn:timezone":"Asia/Shanghai",
    "iso:country":"CN",
    "name:und_x_variant":[
        "\u66f9\u56db\u592d"
    ],
    "wof:name":"Caosiyao",
    "wof:placetype":"locality"
},
  "geometry": {"coordinates":[113.87958999999999,40.82695],"type":"Point"}
}