{
  "type": "Feature",
  "properties": {
    "gn:admin1_code":"29",
    "gn:asciiname":"Samayi",
    "gn:country_code":"CN",
    "gn:dem":1909,
    "gn:feature_class":"P",
    "gn:feature_code":"PPL",
    "gn:name":"Samayi",
    "gn:population":0,
    "gn:timezone":"Asia/Shanghai",
    "iso:country":"CN",
    "name:und_x_variant":[
        "\u6492\u9a6c\u4f9d"
    ],
    "wof:name":"Samayi",
    "wof:placetype":"locality"
},
  "geometry": {"coordinates":[104.05847,25.17306],"type":"Point"}
}