{
  "type": "Feature",
  "properties": {
    "gn:admin1_code":"9.0",
    "gn:asciiname":"Ximazhuang",
    "gn:country_code":"CN",
    "gn:dem":212,
    "gn:feature_class":"P",
    "gn:feature_code":"PPL",
    "gn:name":"Ximazhuang",
    "gn:population":0,
    "gn:timezone":"Asia/Shanghai",
    "iso:country":"CN",
    "name:zho_x_preferred":[
        "\u897f\u9a6c\u5e84"
    ],
    "wof:name":"Ximazhuang",
    "wof:placetype":"locality"
},
  "geometry": {"coordinates":[114.12044,35.79466],"type":"Point"}
}