{
  "type": "Feature",
  "properties": {
    "gn:admin1_code":"24",
    "gn:asciiname":"Haibeitou",
    "gn:country_code":"CN",
    "gn:dem":994,
    "gn:feature_class":"P",
    "gn:feature_code":"PPLA4",
    "gn:name":"Haibeitou",
    "gn:population":0,
    "gn:timezone":"Asia/Shanghai",
    "iso:country":"CN",
    "name:und_x_variant":[
        "Hai-pei-t\u2019ou",
        "Haibeitou",
        "\u6d77\u5317\u5934",
        "Haibeitou Xiang",
        "\u6d77\u5317\u5934\u4e61"
    ],
    "wof:name":"Haibeitou",
    "wof:placetype":"locality"
},
  "geometry": {"coordinates":[113.18501000000001,39.80382],"type":"Point"}
}