{
  "type": "Feature",
  "properties": {
    "gn:admin1_code":"32.0",
    "gn:asciiname":"Xuedui Gaxiao",
    "gn:country_code":"CN",
    "gn:dem":3201,
    "gn:feature_class":"P",
    "gn:feature_code":"PPL",
    "gn:name":"Xuedui Gaxiao",
    "gn:population":0,
    "gn:timezone":"Asia/Shanghai",
    "iso:country":"CN",
    "name:zho_x_preferred":[
        "\u96ea\u5806\u560e\u6821"
    ],
    "wof:name":"Xuedui Gaxiao",
    "wof:placetype":"locality"
},
  "geometry": {"coordinates":[99.1664,28.7717],"type":"Point"}
}