{
  "type": "Feature",
  "properties": {
    "gn:admin1_code":"32.0",
    "gn:asciiname":"Qinglongguan",
    "gn:country_code":"CN",
    "gn:dem":361,
    "gn:feature_class":"P",
    "gn:feature_code":"PPL",
    "gn:name":"Qinglongguan",
    "gn:population":0,
    "gn:timezone":"Asia/Shanghai",
    "iso:country":"CN",
    "name:zho_x_preferred":[
        "\u9752\u9f99\u89c2"
    ],
    "wof:name":"Qinglongguan",
    "wof:placetype":"locality"
},
  "geometry": {"coordinates":[105.23782,29.48891],"type":"Point"}
}