{
  "type": "Feature",
  "properties": {
    "gn:admin1_code":"18",
    "gn:asciiname":"Lijiagou",
    "gn:country_code":"CN",
    "gn:dem":770,
    "gn:feature_class":"P",
    "gn:feature_code":"PPL",
    "gn:name":"Lijiagou",
    "gn:population":0,
    "gn:timezone":"Asia/Shanghai",
    "iso:country":"CN",
    "name:zho_x_preferred":[
        "\u9ece\u5bb6\u6c9f"
    ],
    "wof:name":"Lijiagou",
    "wof:placetype":"locality"
},
  "geometry": {"coordinates":[108.354,27.619],"type":"Point"}
}