{
  "type": "Feature",
  "properties": {
    "gn:admin1_code":"11.0",
    "gn:asciiname":"Longwanli",
    "gn:country_code":"CN",
    "gn:dem":109,
    "gn:feature_class":"P",
    "gn:feature_code":"PPL",
    "gn:name":"Longwanli",
    "gn:population":0,
    "gn:timezone":"Asia/Shanghai",
    "iso:country":"CN",
    "name:zho_x_preferred":[
        "\u9f99\u5f2f\u91cc"
    ],
    "wof:name":"Longwanli",
    "wof:placetype":"locality"
},
  "geometry": {"coordinates":[113.81334,28.61694],"type":"Point"}
}