{
  "type": "Feature",
  "properties": {
    "gn:admin1_code":"5.0",
    "gn:asciiname":"Shuangduizi",
    "gn:country_code":"CN",
    "gn:dem":144,
    "gn:feature_class":"P",
    "gn:feature_code":"PPL",
    "gn:name":"Shuangduizi",
    "gn:population":0,
    "gn:timezone":"Asia/Shanghai",
    "iso:country":"CN",
    "name:zho_x_preferred":[
        "\u53cc\u5806\u5b50"
    ],
    "wof:name":"Shuangduizi",
    "wof:placetype":"locality"
},
  "geometry": {"coordinates":[124.36015,44.92074],"type":"Point"}
}