{
  "type": "Feature",
  "properties": {
    "gn:admin1_code":"32.0",
    "gn:asciiname":"Miaofeng",
    "gn:country_code":"CN",
    "gn:dem":475,
    "gn:feature_class":"P",
    "gn:feature_code":"PPL",
    "gn:name":"Miaofeng",
    "gn:population":0,
    "gn:timezone":"Asia/Shanghai",
    "iso:country":"CN",
    "name:zho_x_preferred":[
        "\u5999\u5cf0"
    ],
    "name:zho_x_variant":[
        "\u5999\u4e30"
    ],
    "wof:name":"Miaofeng",
    "wof:placetype":"locality"
},
  "geometry": {"coordinates":[104.83399,30.6763],"type":"Point"}
}