{
  "type": "Feature",
  "properties": {
    "gn:admin1_code":"8.0",
    "gn:asciiname":"Yongfucun",
    "gn:country_code":"CN",
    "gn:dem":180,
    "gn:feature_class":"P",
    "gn:feature_code":"PPL",
    "gn:name":"Yongfucun",
    "gn:population":0,
    "gn:timezone":"Asia/Shanghai",
    "iso:country":"CN",
    "name:zho_x_preferred":[
        "\u6c38\u5bcc\u6751"
    ],
    "wof:name":"Yongfucun",
    "wof:placetype":"locality"
},
  "geometry": {"coordinates":[125.55016999999999,47.09727],"type":"Point"}
}