{
  "type": "Feature",
  "properties": {
    "gn:admin1_code":"29.0",
    "gn:asciiname":"Shangsaba",
    "gn:country_code":"CN",
    "gn:dem":1402,
    "gn:feature_class":"P",
    "gn:feature_code":"PPL",
    "gn:name":"Shangsaba",
    "gn:population":0,
    "gn:timezone":"Asia/Shanghai",
    "iso:country":"CN",
    "name:zho_x_preferred":[
        "\u4e0a\u6492\u628a"
    ],
    "wof:name":"Shangsaba",
    "wof:placetype":"locality"
},
  "geometry": {"coordinates":[101.029,26.3118],"type":"Point"}
}