{
  "type": "Feature",
  "properties": {
    "gn:admin1_code":"25.0",
    "gn:asciiname":"Damaozhuangcun",
    "gn:country_code":"CN",
    "gn:dem":90,
    "gn:feature_class":"P",
    "gn:feature_code":"PPL",
    "gn:name":"Damaozhuangcun",
    "gn:population":0,
    "gn:timezone":"Asia/Shanghai",
    "iso:country":"CN",
    "name:zho_x_preferred":[
        "\u5927\u8305\u5e84\u6751"
    ],
    "wof:name":"Damaozhuangcun",
    "wof:placetype":"locality"
},
  "geometry": {"coordinates":[119.32501999999999,35.8804],"type":"Point"}
}