{
  "type": "Feature",
  "properties": {
    "gn:admin1_code":"19.0",
    "gn:asciiname":"Baozhenggou",
    "gn:country_code":"CN",
    "gn:dem":200,
    "gn:feature_class":"P",
    "gn:feature_code":"PPL",
    "gn:name":"Baozhenggou",
    "gn:population":0,
    "gn:timezone":"Asia/Shanghai",
    "iso:country":"CN",
    "name:zho_x_preferred":[
        "\u4fdd\u8bc1\u6c9f"
    ],
    "wof:name":"Baozhenggou",
    "wof:placetype":"locality"
},
  "geometry": {"coordinates":[120.40707,40.87387],"type":"Point"}
}