{
  "type": "Feature",
  "properties": {
    "gn:admin1_code":"8.0",
    "gn:asciiname":"Jinguangcun",
    "gn:country_code":"CN",
    "gn:dem":104,
    "gn:feature_class":"P",
    "gn:feature_code":"PPL",
    "gn:name":"Jinguangcun",
    "gn:population":0,
    "gn:timezone":"Asia/Shanghai",
    "iso:country":"CN",
    "name:zho_x_preferred":[
        "\u91d1\u5149\u6751"
    ],
    "wof:name":"Jinguangcun",
    "wof:placetype":"locality"
},
  "geometry": {"coordinates":[129.75847999999999,46.55685],"type":"Point"}
}