{
  "type": "Feature",
  "properties": {
    "gn:admin1_code":"24.0",
    "gn:asciiname":"Xiliujia",
    "gn:country_code":"CN",
    "gn:dem":506,
    "gn:feature_class":"P",
    "gn:feature_code":"PPL",
    "gn:name":"Xiliujia",
    "gn:population":0,
    "gn:timezone":"Asia/Shanghai",
    "iso:country":"CN",
    "name:und_x_variant":[
        "\u897f\u5218\u5bb6"
    ],
    "wof:name":"Xiliujia",
    "wof:placetype":"locality"
},
  "geometry": {"coordinates":[111.37866,35.43552000000001],"type":"Point"}
}