{
  "type": "Feature",
  "properties": {
    "gn:admin1_code":"11.0",
    "gn:asciiname":"Zhongcunping",
    "gn:country_code":"CN",
    "gn:dem":114,
    "gn:feature_class":"P",
    "gn:feature_code":"PPL",
    "gn:name":"Zhongcunping",
    "gn:population":0,
    "gn:timezone":"Asia/Shanghai",
    "iso:country":"CN",
    "name:zho_x_preferred":[
        "Zhongcunping"
    ],
    "name:zho_x_variant":[
        "\u4e2d\u6751\u576a"
    ],
    "wof:name":"Zhongcunping",
    "wof:placetype":"locality"
},
  "geometry": {"coordinates":[111.36623,29.95318],"type":"Point"}
}