{
  "type": "Feature",
  "properties": {
    "gn:admin1_code":"32.0",
    "gn:asciiname":"Ma'anshi",
    "gn:country_code":"CN",
    "gn:dem":361,
    "gn:feature_class":"P",
    "gn:feature_code":"PPL",
    "gn:name":"Ma\u2019anshi",
    "gn:population":0,
    "gn:timezone":"Asia/Shanghai",
    "iso:country":"CN",
    "name:zho_x_preferred":[
        "\u9a6c\u978d\u5e02"
    ],
    "name:zho_x_variant":[
        "Ma\u2019anshi"
    ],
    "wof:name":"Ma'anshi",
    "wof:placetype":"locality"
},
  "geometry": {"coordinates":[105.27249999999999,29.57156],"type":"Point"}
}