{
  "type": "Feature",
  "properties": {
    "gn:admin1_code":"21.0",
    "gn:asciiname":"Shihuangwa",
    "gn:country_code":"CN",
    "gn:dem":1486,
    "gn:feature_class":"P",
    "gn:feature_code":"PPL",
    "gn:name":"Shihuangwa",
    "gn:population":0,
    "gn:timezone":"Asia/Shanghai",
    "iso:country":"CN",
    "name:zho_x_preferred":[
        "\u77f3\u8352\u6d3c"
    ],
    "wof:name":"Shihuangwa",
    "wof:placetype":"locality"
},
  "geometry": {"coordinates":[106.688,37.8927],"type":"Point"}
}