{
  "type": "Feature",
  "properties": {
    "gn:admin1_code":"16.0",
    "gn:asciiname":"Simin",
    "gn:country_code":"CN",
    "gn:dem":65,
    "gn:feature_class":"P",
    "gn:feature_code":"PPL",
    "gn:name":"Simin",
    "gn:population":0,
    "gn:timezone":"Asia/Shanghai",
    "iso:country":"CN",
    "name:zho_x_preferred":[
        "\u6cd7\u6c11"
    ],
    "wof:name":"Simin",
    "wof:placetype":"locality"
},
  "geometry": {"coordinates":[109.518,23.1292],"type":"Point"}
}