{
  "type": "Feature",
  "properties": {
    "gn:admin1_code":"07",
    "gn:asciiname":"Jiangxikou",
    "gn:country_code":"CN",
    "gn:dem":318,
    "gn:feature_class":"P",
    "gn:feature_code":"PPL",
    "gn:name":"Jiangxikou",
    "gn:population":0,
    "gn:timezone":"Asia/Shanghai",
    "iso:country":"CN",
    "name:zho_x_preferred":[
        "Chiang-hsi-k\u2019ou"
    ],
    "name:zho_x_variant":[
        "\u5c06\u6eaa\u53e3"
    ],
    "wof:name":"Jiangxikou",
    "wof:placetype":"locality"
},
  "geometry": {"coordinates":[118.40644,27.61176],"type":"Point"}
}