{
  "type": "Feature",
  "properties": {
    "gn:admin1_code":"26.0",
    "gn:asciiname":"Nongchangbalian",
    "gn:country_code":"CN",
    "gn:dem":1150,
    "gn:feature_class":"P",
    "gn:feature_code":"PPLA4",
    "gn:name":"Nongchangbalian",
    "gn:population":0,
    "gn:timezone":"Asia/Shanghai",
    "iso:country":"CN",
    "name:zho_x_preferred":[
        "\u519c\u573a\u516b\u8fde"
    ],
    "wof:name":"Nongchangbalian",
    "wof:placetype":"locality"
},
  "geometry": {"coordinates":[109.6224,36.36563],"type":"Point"}
}