{
  "type": "Feature",
  "properties": {
    "gn:admin1_code":"7.0",
    "gn:asciiname":"Sanyuan",
    "gn:country_code":"CN",
    "gn:dem":253,
    "gn:feature_class":"P",
    "gn:feature_code":"PPL",
    "gn:name":"Sanyuan",
    "gn:population":0,
    "gn:timezone":"Asia/Shanghai",
    "iso:country":"CN",
    "name:ceb_x_preferred":[
        "Sanyuan"
    ],
    "name:deu_x_preferred":[
        "Sanyuan"
    ],
    "name:fra_x_preferred":[
        "Sanyuan"
    ],
    "name:nor_x_preferred":[
        "Sanyuan"
    ],
    "name:rus_x_preferred":[
        "\u0421\u0430\u043d\u044c\u044e\u0430\u043d\u044c"
    ],
    "name:swe_x_preferred":[
        "Sanyuan"
    ],
    "name:zho_x_preferred":[
        "\u4e09\u6e90"
    ],
    "wof:name":"Sanyuan",
    "wof:placetype":"locality"
},
  "geometry": {"coordinates":[118.52733000000001,27.98368],"type":"Point"}
}