{
  "type": "Feature",
  "properties": {
    "gn:admin1_code":"24.0",
    "gn:asciiname":"Huanghuata",
    "gn:country_code":"CN",
    "gn:dem":1187,
    "gn:feature_class":"P",
    "gn:feature_code":"PPL",
    "gn:name":"Huanghuata",
    "gn:population":0,
    "gn:timezone":"Asia/Shanghai",
    "iso:country":"CN",
    "name:zho_x_preferred":[
        "\u9ec4\u82b1\u5854"
    ],
    "wof:name":"Huanghuata",
    "wof:placetype":"locality"
},
  "geometry": {"coordinates":[110.82937,36.16259],"type":"Point"}
}