{
  "type": "Feature",
  "properties": {
    "gn:admin1_code":"24.0",
    "gn:asciiname":"Dongshuigou",
    "gn:country_code":"CN",
    "gn:dem":983,
    "gn:feature_class":"P",
    "gn:feature_code":"PPL",
    "gn:name":"Dongshuigou",
    "gn:population":0,
    "gn:timezone":"Asia/Shanghai",
    "iso:country":"CN",
    "name:zho_x_preferred":[
        "\u4e1c\u6c34\u6c9f"
    ],
    "wof:name":"Dongshuigou",
    "wof:placetype":"locality"
},
  "geometry": {"coordinates":[113.53973000000001,38.08306],"type":"Point"}
}