{
  "type": "Feature",
  "properties": {
    "gn:admin1_code":"11.0",
    "gn:asciiname":"Tudi'ao",
    "gn:country_code":"CN",
    "gn:dem":155,
    "gn:feature_class":"P",
    "gn:feature_code":"PPL",
    "gn:name":"Tudi\u2019ao",
    "gn:population":0,
    "gn:timezone":"Asia/Shanghai",
    "iso:country":"CN",
    "name:und_x_variant":[
        "Tudi\u2019ao"
    ],
    "name:zho_x_preferred":[
        "\u571f\u5730\u5773"
    ],
    "wof:name":"Tudi'ao",
    "wof:placetype":"locality"
},
  "geometry": {"coordinates":[110.11903999999998,27.95076],"type":"Point"}
}