{
  "type": "Feature",
  "properties": {
    "gn:admin1_code":"15.0",
    "gn:asciiname":"Quzisuika",
    "gn:country_code":"CN",
    "gn:dem":2673,
    "gn:feature_class":"P",
    "gn:feature_code":"PPL",
    "gn:name":"Quzisuika",
    "gn:population":0,
    "gn:timezone":"Asia/Shanghai",
    "iso:country":"CN",
    "name:und_x_variant":[
        "\u66f2\u5b50\u5c81\u5361",
        "Quzibuka",
        "\u66f2\u5b50\u6b65\u5361"
    ],
    "wof:name":"Quzisuika",
    "wof:placetype":"locality"
},
  "geometry": {"coordinates":[103.63893,34.01552],"type":"Point"}
}