{
  "type": "Feature",
  "properties": {
    "gn:admin1_code":"10",
    "gn:asciiname":"Sanshibaqing",
    "gn:country_code":"CN",
    "gn:dem":1440,
    "gn:feature_class":"P",
    "gn:feature_code":"PPL",
    "gn:name":"Sanshibaqing",
    "gn:population":0,
    "gn:timezone":"Asia/Shanghai",
    "iso:country":"CN",
    "name:zho_x_preferred":[
        "\u4e09\u5341\u516b\u9877"
    ],
    "wof:name":"Sanshibaqing",
    "wof:placetype":"locality"
},
  "geometry": {"coordinates":[114.68053,41.7738],"type":"Point"}
}