{
  "type": "Feature",
  "properties": {
    "gn:admin1_code":"1.0",
    "gn:asciiname":"Binguangcun",
    "gn:country_code":"CN",
    "gn:dem":11,
    "gn:feature_class":"P",
    "gn:feature_code":"PPL",
    "gn:name":"Binguangcun",
    "gn:population":0,
    "gn:timezone":"Asia/Shanghai",
    "iso:country":"CN",
    "name:zho_x_preferred":[
        "\u6ee8\u5149\u6751"
    ],
    "wof:name":"Binguangcun",
    "wof:placetype":"locality"
},
  "geometry": {"coordinates":[117.35229,31.54712],"type":"Point"}
}