{
  "type": "Feature",
  "properties": {
    "gn:admin1_code":"11.0",
    "gn:asciiname":"Longtouzhai",
    "gn:country_code":"CN",
    "gn:dem":311,
    "gn:feature_class":"P",
    "gn:feature_code":"PPL",
    "gn:name":"Longtouzhai",
    "gn:population":0,
    "gn:timezone":"Asia/Shanghai",
    "iso:country":"CN",
    "name:zho_x_preferred":[
        "\u9f99\u5934\u5be8"
    ],
    "wof:name":"Longtouzhai",
    "wof:placetype":"locality"
},
  "geometry": {"coordinates":[109.83987999999999,28.07778],"type":"Point"}
}