{
  "type": "Feature",
  "properties": {
    "gn:admin1_code":"25",
    "gn:asciiname":"Nanzhujiazhuang",
    "gn:country_code":"CN",
    "gn:dem":22,
    "gn:feature_class":"P",
    "gn:feature_code":"PPL",
    "gn:name":"Nanzhujiazhuang",
    "gn:population":0,
    "gn:timezone":"Asia/Shanghai",
    "iso:country":"CN",
    "name:zho_x_preferred":[
        "\u5357\u6731\u5bb6\u5e84"
    ],
    "wof:name":"Nanzhujiazhuang",
    "wof:placetype":"locality"
},
  "geometry": {"coordinates":[120.09699999999999,36.604],"type":"Point"}
}