{
  "type": "Feature",
  "properties": {
    "gn:admin1_code":"30.0",
    "gn:asciiname":"Changgengzi",
    "gn:country_code":"CN",
    "gn:dem":836,
    "gn:feature_class":"P",
    "gn:feature_code":"PPL",
    "gn:name":"Changgengzi",
    "gn:population":0,
    "gn:timezone":"Asia/Shanghai",
    "iso:country":"CN",
    "name:zho_x_preferred":[
        "Changgengzi"
    ],
    "name:zho_x_variant":[
        "\u957f\u57c2\u5b50"
    ],
    "wof:name":"Changgengzi",
    "wof:placetype":"locality"
},
  "geometry": {"coordinates":[113.32528000000001,25.44917],"type":"Point"}
}