{
  "type": "Feature",
  "properties": {
    "gn:admin1_code":"24",
    "gn:asciiname":"Yunzhong",
    "gn:country_code":"CN",
    "gn:dem":1039,
    "gn:feature_class":"P",
    "gn:feature_code":"PPLA3",
    "gn:name":"Yunzhong",
    "gn:population":0,
    "gn:timezone":"Asia/Shanghai",
    "iso:country":"CN",
    "name:und_x_variant":[
        "Hwaijensha",
        "Huai-jen-chen",
        "Huai-jen-hsien",
        "Huai-jen",
        "Huairen Xian",
        "Yunzhong",
        "Yunzhong Zhen",
        "\u4e91\u4e2d\u9547",
        "\u6000\u4ec1\u53bf"
    ],
    "name:zho_x_preferred":[
        "\u4e91\u4e2d"
    ],
    "wof:name":"Yunzhong",
    "wof:placetype":"locality"
},
  "geometry": {"coordinates":[113.09622,39.82707],"type":"Point"}
}