{
  "type": "Feature",
  "properties": {
    "gn:admin1_code":"14.0",
    "gn:asciiname":"Lhoma",
    "gn:country_code":"CN",
    "gn:dem":4793,
    "gn:feature_class":"P",
    "gn:feature_code":"PPL",
    "gn:name":"Lhoma",
    "gn:population":0,
    "gn:timezone":"Asia/Urumqi",
    "iso:country":"CN",
    "name:bod_x_preferred":[
        "Lhoma"
    ],
    "name:msa_x_preferred":[
        "Lhoma"
    ],
    "name:und_x_variant":[
        "Luoma Gongshe"
    ],
    "name:zho_x_preferred":[
        "Luoma"
    ],
    "name:zho_x_variant":[
        "\u7f57\u739b",
        "Zadong",
        "\u6742\u51ac",
        "\u7f57\u739b\u516c\u793e"
    ],
    "wof:name":"Lhoma",
    "wof:placetype":"locality"
},
  "geometry": {"coordinates":[83.20650000000001,31.7647],"type":"Point"}
}