{
  "type": "Feature",
  "properties": {
    "gn:admin1_code":"19.0",
    "gn:asciiname":"Dasheshanzi",
    "gn:country_code":"CN",
    "gn:dem":85,
    "gn:feature_class":"P",
    "gn:feature_code":"PPL",
    "gn:name":"Dasheshanzi",
    "gn:population":0,
    "gn:timezone":"Asia/Shanghai",
    "iso:country":"CN",
    "name:und_x_variant":[
        "\u5927\u86c7\u5c71\u5b50"
    ],
    "name:zho_x_preferred":[
        "\u5927\u86c7\u5c71\u5b50"
    ],
    "wof:name":"Dasheshanzi",
    "wof:placetype":"locality"
},
  "geometry": {"coordinates":[123.21975,42.37826],"type":"Point"}
}