{
  "type": "Feature",
  "properties": {
    "gn:admin1_code":"5.0",
    "gn:asciiname":"Qianlongkeng",
    "gn:country_code":"CN",
    "gn:dem":183,
    "gn:feature_class":"P",
    "gn:feature_code":"PPL",
    "gn:name":"Qianlongkeng",
    "gn:population":0,
    "gn:timezone":"Asia/Shanghai",
    "iso:country":"CN",
    "name:zho_x_preferred":[
        "\u524d\u9f99\u5751"
    ],
    "wof:name":"Qianlongkeng",
    "wof:placetype":"locality"
},
  "geometry": {"coordinates":[124.61185,44.68122],"type":"Point"}
}