{
  "type": "Feature",
  "properties": {
    "gn:admin1_code":"29",
    "gn:asciiname":"Muhan",
    "gn:country_code":"CN",
    "gn:dem":1536,
    "gn:feature_class":"P",
    "gn:feature_code":"PPL",
    "gn:name":"Muhan",
    "gn:population":0,
    "gn:timezone":"Asia/Shanghai",
    "iso:country":"CN",
    "name:zho_x_preferred":[
        "\u6728\u5bd2"
    ],
    "wof:name":"Muhan",
    "wof:placetype":"locality"
},
  "geometry": {"coordinates":[105.422,23.4905],"type":"Point"}
}