{
  "type": "Feature",
  "properties": {
    "gn:admin1_code":"11.0",
    "gn:asciiname":"Majia'ao",
    "gn:country_code":"CN",
    "gn:dem":118,
    "gn:feature_class":"P",
    "gn:feature_code":"PPL",
    "gn:name":"Majia\u2019ao",
    "gn:population":0,
    "gn:timezone":"Asia/Shanghai",
    "iso:country":"CN",
    "name:und_x_variant":[
        "Majia\u2019ao"
    ],
    "name:zho_x_preferred":[
        "\u9ebb\u5bb6\u5773"
    ],
    "wof:name":"Majia'ao",
    "wof:placetype":"locality"
},
  "geometry": {"coordinates":[112.5431,27.03116],"type":"Point"}
}