{
  "type": "Feature",
  "properties": {
    "gn:admin1_code":"32.0",
    "gn:asciiname":"Tongbaoshan",
    "gn:country_code":"CN",
    "gn:dem":597,
    "gn:feature_class":"P",
    "gn:feature_code":"PPL",
    "gn:name":"Tongbaoshan",
    "gn:population":0,
    "gn:timezone":"Asia/Shanghai",
    "iso:country":"CN",
    "name:zho_x_preferred":[
        "\u901a\u5b9d\u5c71"
    ],
    "wof:name":"Tongbaoshan",
    "wof:placetype":"locality"
},
  "geometry": {"coordinates":[105.503,28.4748],"type":"Point"}
}