{
  "type": "Feature",
  "properties": {
    "gn:admin1_code":"11.0",
    "gn:asciiname":"Yantangwan",
    "gn:country_code":"CN",
    "gn:dem":388,
    "gn:feature_class":"P",
    "gn:feature_code":"PPL",
    "gn:name":"Yantangwan",
    "gn:population":0,
    "gn:timezone":"Asia/Shanghai",
    "iso:country":"CN",
    "name:zho_x_preferred":[
        "Yantangwan"
    ],
    "name:zho_x_variant":[
        "\u5830\u5858\u6e7e"
    ],
    "wof:name":"Yantangwan",
    "wof:placetype":"locality"
},
  "geometry": {"coordinates":[110.51373999999998,28.91506],"type":"Point"}
}