{
  "type": "Feature",
  "properties": {
    "gn:admin1_code":"24.0",
    "gn:asciiname":"Xiangzigou",
    "gn:country_code":"CN",
    "gn:dem":1472,
    "gn:feature_class":"P",
    "gn:feature_code":"PPL",
    "gn:name":"Xiangzigou",
    "gn:population":0,
    "gn:timezone":"Asia/Shanghai",
    "iso:country":"CN",
    "name:zho_x_preferred":[
        "\u5df7\u5b50\u6c9f"
    ],
    "wof:name":"Xiangzigou",
    "wof:placetype":"locality"
},
  "geometry": {"coordinates":[112.48921,38.7914],"type":"Point"}
}