{
  "type": "Feature",
  "properties": {
    "gn:admin1_code":"7.0",
    "gn:asciiname":"Cunxicun",
    "gn:country_code":"CN",
    "gn:dem":327,
    "gn:feature_class":"P",
    "gn:feature_code":"PPL",
    "gn:name":"Cunxicun",
    "gn:population":0,
    "gn:timezone":"Asia/Shanghai",
    "iso:country":"CN",
    "name:zho_x_preferred":[
        "\u6751\u6eaa\u6751"
    ],
    "wof:name":"Cunxicun",
    "wof:placetype":"locality"
},
  "geometry": {"coordinates":[118.34166,27.62426],"type":"Point"}
}