{
  "type": "Feature",
  "properties": {
    "gn:admin1_code":"16",
    "gn:asciiname":"Chaxiangping",
    "gn:country_code":"CN",
    "gn:dem":910,
    "gn:feature_class":"P",
    "gn:feature_code":"PPL",
    "gn:name":"Chaxiangping",
    "gn:population":0,
    "gn:timezone":"Asia/Shanghai",
    "iso:country":"CN",
    "name:zho_x_preferred":[
        "\u8336\u9999\u576a"
    ],
    "wof:name":"Chaxiangping",
    "wof:placetype":"locality"
},
  "geometry": {"coordinates":[110.581,26.1177],"type":"Point"}
}