{
  "type": "Feature",
  "properties": {
    "gn:admin1_code":"26.0",
    "gn:asciiname":"Muxin Zhuangcun",
    "gn:country_code":"CN",
    "gn:dem":1470,
    "gn:feature_class":"P",
    "gn:feature_code":"PPL",
    "gn:name":"Muxin Zhuangcun",
    "gn:population":0,
    "gn:timezone":"Asia/Shanghai",
    "iso:country":"CN",
    "name:zho_x_preferred":[
        "\u6155\u65b0\u5e84\u6751"
    ],
    "wof:name":"Muxin Zhuangcun",
    "wof:placetype":"locality"
},
  "geometry": {"coordinates":[108.23699999999999,37.3221],"type":"Point"}
}