{
  "type": "Feature",
  "properties": {
    "gn:admin1_code":"3",
    "gn:asciiname":"Tianlongzi",
    "gn:country_code":"CN",
    "gn:dem":201,
    "gn:feature_class":"P",
    "gn:feature_code":"PPL",
    "gn:name":"Tianlongzi",
    "gn:population":0,
    "gn:timezone":"Asia/Shanghai",
    "iso:country":"CN",
    "name:zho_x_preferred":[
        "\u7530\u5785\u5b5c"
    ],
    "wof:name":"Tianlongzi",
    "wof:placetype":"locality"
},
  "geometry": {"coordinates":[114.581,25.6716],"type":"Point"}
}