{
  "type": "Feature",
  "properties": {
    "gn:admin1_code":"32.0",
    "gn:asciiname":"Tielugou",
    "gn:country_code":"CN",
    "gn:dem":386,
    "gn:feature_class":"P",
    "gn:feature_code":"PPL",
    "gn:name":"Tielugou",
    "gn:population":0,
    "gn:timezone":"Asia/Shanghai",
    "iso:country":"CN",
    "name:zho_x_preferred":[
        "\u94c1\u8def\u6c9f"
    ],
    "wof:name":"Tielugou",
    "wof:placetype":"locality"
},
  "geometry": {"coordinates":[105.13655,30.47264],"type":"Point"}
}