{
  "type": "Feature",
  "properties": {
    "gn:admin1_code":"3.0",
    "gn:asciiname":"Meiziyuan",
    "gn:country_code":"CN",
    "gn:dem":178,
    "gn:feature_class":"P",
    "gn:feature_code":"PPL",
    "gn:name":"Meiziyuan",
    "gn:population":0,
    "gn:timezone":"Asia/Shanghai",
    "iso:country":"CN",
    "name:und_x_variant":[
        "\u6885\u5b50\u56ed"
    ],
    "wof:name":"Meiziyuan",
    "wof:placetype":"locality"
},
  "geometry": {"coordinates":[114.12177,27.9717],"type":"Point"}
}