{
  "type": "Feature",
  "properties": {
    "gn:admin1_code":"1.0",
    "gn:asciiname":"Qingfengcun",
    "gn:country_code":"CN",
    "gn:dem":56,
    "gn:feature_class":"P",
    "gn:feature_code":"PPL",
    "gn:name":"Qingfengcun",
    "gn:population":0,
    "gn:timezone":"Asia/Shanghai",
    "iso:country":"CN",
    "name:zho_x_preferred":[
        "\u9752\u5cf0\u6751"
    ],
    "wof:name":"Qingfengcun",
    "wof:placetype":"locality"
},
  "geometry": {"coordinates":[116.65286999999999,31.91644],"type":"Point"}
}