{
  "type": "Feature",
  "properties": {
    "gn:admin1_code":"11.0",
    "gn:asciiname":"Mulongchong",
    "gn:country_code":"CN",
    "gn:dem":70,
    "gn:feature_class":"P",
    "gn:feature_code":"PPL",
    "gn:name":"Mulongchong",
    "gn:population":0,
    "gn:timezone":"Asia/Shanghai",
    "iso:country":"CN",
    "name:zho_x_preferred":[
        "\u6728\u9f99\u51b2"
    ],
    "wof:name":"Mulongchong",
    "wof:placetype":"locality"
},
  "geometry": {"coordinates":[111.49126,28.72355],"type":"Point"}
}