{
  "type": "Feature",
  "properties": {
    "gn:admin1_code":"4.0",
    "gn:asciiname":"Zhenmiaocun",
    "gn:country_code":"CN",
    "gn:dem":37,
    "gn:feature_class":"P",
    "gn:feature_code":"PPL",
    "gn:name":"Zhenmiaocun",
    "gn:population":0,
    "gn:timezone":"Asia/Shanghai",
    "iso:country":"CN",
    "name:zho_x_preferred":[
        "\u7504\u5e99\u6751"
    ],
    "wof:name":"Zhenmiaocun",
    "wof:placetype":"locality"
},
  "geometry": {"coordinates":[116.85089000000001,34.73328],"type":"Point"}
}