{
  "type": "Feature",
  "properties": {
    "gn:admin1_code":"24.0",
    "gn:asciiname":"Shangxiashi",
    "gn:country_code":"CN",
    "gn:dem":1176,
    "gn:feature_class":"P",
    "gn:feature_code":"PPL",
    "gn:name":"Shangxiashi",
    "gn:population":0,
    "gn:timezone":"Asia/Shanghai",
    "iso:country":"CN",
    "name:zho_x_preferred":[
        "\u4e0a\u7856\u77f3"
    ],
    "wof:name":"Shangxiashi",
    "wof:placetype":"locality"
},
  "geometry": {"coordinates":[111.34708000000001,36.89574],"type":"Point"}
}