{
  "type": "Feature",
  "properties": {
    "gn:admin1_code":"12.0",
    "gn:asciiname":"Chenjialaotai",
    "gn:country_code":"CN",
    "gn:dem":26,
    "gn:feature_class":"P",
    "gn:feature_code":"PPL",
    "gn:name":"Chenjialaotai",
    "gn:population":0,
    "gn:timezone":"Asia/Shanghai",
    "iso:country":"CN",
    "name:zho_x_preferred":[
        "\u9648\u5bb6\u8001\u53f0"
    ],
    "wof:name":"Chenjialaotai",
    "wof:placetype":"locality"
},
  "geometry": {"coordinates":[113.63825,30.40216],"type":"Point"}
}