{
  "type": "Feature",
  "properties": {
    "gn:admin1_code":"12.0",
    "gn:asciiname":"Xinjianping",
    "gn:country_code":"CN",
    "gn:dem":1338,
    "gn:feature_class":"P",
    "gn:feature_code":"PPL",
    "gn:name":"Xinjianping",
    "gn:population":0,
    "gn:timezone":"Asia/Shanghai",
    "iso:country":"CN",
    "name:zho_x_preferred":[
        "\u65b0\u5efa\u576a"
    ],
    "wof:name":"Xinjianping",
    "wof:placetype":"locality"
},
  "geometry": {"coordinates":[108.79181,30.13808],"type":"Point"}
}