{
  "type": "Feature",
  "properties": {
    "gn:admin1_code":"14.0",
    "gn:asciiname":"Yinbai",
    "gn:country_code":"CN",
    "gn:dem":4485,
    "gn:feature_class":"P",
    "gn:feature_code":"PPL",
    "gn:name":"Yinbai",
    "gn:population":0,
    "gn:timezone":"Asia/Urumqi",
    "iso:country":"CN",
    "name:zho_x_preferred":[
        "\u94f6\u767d"
    ],
    "wof:name":"Yinbai",
    "wof:placetype":"locality"
},
  "geometry": {"coordinates":[94.26739000000001,29.44747000000001],"type":"Point"}
}