{
  "type": "Feature",
  "properties": {
    "gn:admin1_code":"3.0",
    "gn:asciiname":"Caiwu",
    "gn:country_code":"CN",
    "gn:dem":48,
    "gn:feature_class":"P",
    "gn:feature_code":"PPL",
    "gn:name":"Caiwu",
    "gn:population":0,
    "gn:timezone":"Asia/Shanghai",
    "iso:country":"CN",
    "name:und_x_variant":[
        "\u8521\u5c4b"
    ],
    "wof:name":"Caiwu",
    "wof:placetype":"locality"
},
  "geometry": {"coordinates":[115.29595999999999,28.30654],"type":"Point"}
}