{
  "type": "Feature",
  "properties": {
    "gn:admin1_code":"15.0",
    "gn:asciiname":"Qiuchigou",
    "gn:country_code":"CN",
    "gn:dem":1304,
    "gn:feature_class":"P",
    "gn:feature_code":"PPL",
    "gn:name":"Qiuchigou",
    "gn:population":0,
    "gn:timezone":"Asia/Shanghai",
    "iso:country":"CN",
    "name:zho_x_preferred":[
        "\u6e6b\u6c60\u6c9f"
    ],
    "wof:name":"Qiuchigou",
    "wof:placetype":"locality"
},
  "geometry": {"coordinates":[107.45999999999999,35.4219],"type":"Point"}
}