{
  "type": "Feature",
  "properties": {
    "gn:admin1_code":"7",
    "gn:asciiname":"Jiadingkeng",
    "gn:country_code":"CN",
    "gn:dem":569,
    "gn:feature_class":"P",
    "gn:feature_code":"PPL",
    "gn:name":"Jiadingkeng",
    "gn:population":0,
    "gn:timezone":"Asia/Shanghai",
    "iso:country":"CN",
    "name:zho_x_preferred":[
        "\u4f73\u4e01\u5751"
    ],
    "wof:name":"Jiadingkeng",
    "wof:placetype":"locality"
},
  "geometry": {"coordinates":[118.65761999999999,25.82554],"type":"Point"}
}