{
  "type": "Feature",
  "properties": {
    "gn:admin1_code":"13.0",
    "gn:asciiname":"Fuhaiyi Nongchang",
    "gn:country_code":"CN",
    "gn:dem":527,
    "gn:feature_class":"P",
    "gn:feature_code":"PPLF",
    "gn:name":"Fuhaiyi Nongchang",
    "gn:population":0,
    "gn:timezone":"Asia/Urumqi",
    "iso:country":"CN",
    "wof:name":"Fuhaiyi Nongchang",
    "wof:placetype":"locality"
},
  "geometry": {"coordinates":[87.81416999999998,47.01111],"type":"Point"}
}