{
  "type": "Feature",
  "properties": {
    "gn:admin1_code":"25",
    "gn:asciiname":"Dongshaolou",
    "gn:country_code":"CN",
    "gn:dem":50,
    "gn:feature_class":"P",
    "gn:feature_code":"PPL",
    "gn:name":"Dongshaolou",
    "gn:population":0,
    "gn:timezone":"Asia/Shanghai",
    "iso:country":"CN",
    "name:zho_x_preferred":[
        "\u8463\u90b5\u697c"
    ],
    "wof:name":"Dongshaolou",
    "wof:placetype":"locality"
},
  "geometry": {"coordinates":[115.85599999999999,34.7516],"type":"Point"}
}