{
  "type": "Feature",
  "properties": {
    "gn:admin1_code":"24.0",
    "gn:asciiname":"Wanminzhuang",
    "gn:country_code":"CN",
    "gn:dem":1314,
    "gn:feature_class":"P",
    "gn:feature_code":"PPL",
    "gn:name":"Wanminzhuang",
    "gn:population":0,
    "gn:timezone":"Asia/Shanghai",
    "iso:country":"CN",
    "name:zho_x_preferred":[
        "\u4e07\u6c11\u5e84"
    ],
    "wof:name":"Wanminzhuang",
    "wof:placetype":"locality"
},
  "geometry": {"coordinates":[113.73984,39.35677],"type":"Point"}
}