{
  "type": "Feature",
  "properties": {
    "gn:admin1_code":"7.0",
    "gn:asciiname":"Guiyang",
    "gn:country_code":"CN",
    "gn:dem":585,
    "gn:feature_class":"P",
    "gn:feature_code":"PPL",
    "gn:name":"Guiyang",
    "gn:population":0,
    "gn:timezone":"Asia/Shanghai",
    "iso:country":"CN",
    "name:rus_x_preferred":[
        "\u0413\u0443\u0439\u044f\u043d"
    ],
    "name:zho_x_preferred":[
        "\u572d\u9633"
    ],
    "wof:name":"Guiyang",
    "wof:placetype":"locality"
},
  "geometry": {"coordinates":[118.46838,27.19313],"type":"Point"}
}