{
  "type": "Feature",
  "properties": {
    "gn:admin1_code":"32.0",
    "gn:asciiname":"Yuanyang",
    "gn:country_code":"CN",
    "gn:dem":899,
    "gn:feature_class":"P",
    "gn:feature_code":"PPL",
    "gn:name":"Yuanyang",
    "gn:population":0,
    "gn:timezone":"Asia/Shanghai",
    "iso:country":"CN",
    "name:ceb_x_preferred":[
        "Yuanyang"
    ],
    "name:ces_x_preferred":[
        "J\u00fcan-jang"
    ],
    "name:deu_x_preferred":[
        "Yuanyang"
    ],
    "name:fra_x_preferred":[
        "Yuanyang"
    ],
    "name:kor_x_preferred":[
        "\uc704\uc548\uc591\ud604"
    ],
    "name:nor_x_preferred":[
        "Yuanyang"
    ],
    "name:rus_x_preferred":[
        "\u042e\u0430\u043d\u044c\u044f\u043d"
    ],
    "name:zho_x_preferred":[
        "\u9e33\u9e2f"
    ],
    "wof:name":"Yuanyang",
    "wof:placetype":"locality"
},
  "geometry": {"coordinates":[107.515,32.0297],"type":"Point"}
}