{
  "type": "Feature",
  "properties": {
    "gn:admin1_code":"32.0",
    "gn:asciiname":"Yuanyang",
    "gn:country_code":"CN",
    "gn:dem":899,
    "gn:feature_class":"P",
    "gn:feature_code":"PPL",
    "gn:name":"Yuanyang",
    "gn:population":0,
    "gn:timezone":"Asia/Shanghai",
    "iso:country":"CN",
    "name:zho_x_preferred":[
        "\u9e33\u9e2f"
    ],
    "wof:name":"Yuanyang",
    "wof:placetype":"locality"
},
  "geometry": {"coordinates":[107.515,32.0297],"type":"Point"}
}