{
  "type": "Feature",
  "properties": {
    "gn:admin1_code":"32",
    "gn:asciiname":"Taihe",
    "gn:country_code":"CN",
    "gn:dem":1024,
    "gn:feature_class":"P",
    "gn:feature_code":"PPL",
    "gn:name":"Taihe",
    "gn:population":0,
    "gn:timezone":"Asia/Shanghai",
    "iso:country":"CN",
    "wof:name":"Taihe",
    "wof:placetype":"locality"
},
  "geometry": {"coordinates":[106.03333000000001,27.98333],"type":"Point"}
}