{
  "type": "Feature",
  "properties": {
    "gn:admin1_code":"8.0",
    "gn:asciiname":"Shuangsheng Machang",
    "gn:country_code":"CN",
    "gn:dem":355,
    "gn:feature_class":"P",
    "gn:feature_code":"PPLF",
    "gn:name":"Shuangsheng Machang",
    "gn:population":0,
    "gn:timezone":"Asia/Shanghai",
    "iso:country":"CN",
    "name:zho_x_preferred":[
        "\u53cc\u80dc\u9a6c\u573a"
    ],
    "wof:name":"Shuangsheng Machang",
    "wof:placetype":"locality"
},
  "geometry": {"coordinates":[127.36187,48.25429000000001],"type":"Point"}
}