{
  "type": "Feature",
  "properties": {
    "gn:admin1_code":"30.0",
    "gn:asciiname":"Bogong'ao",
    "gn:country_code":"CN",
    "gn:dem":160,
    "gn:feature_class":"P",
    "gn:feature_code":"PPL",
    "gn:name":"Bogong\u2019ao",
    "gn:population":0,
    "gn:timezone":"Asia/Shanghai",
    "iso:country":"CN",
    "name:zho_x_preferred":[
        "Bogong\u2019ao"
    ],
    "name:zho_x_variant":[
        "\u4f2f\u516c\u5773"
    ],
    "wof:name":"Bogong'ao",
    "wof:placetype":"locality"
},
  "geometry": {"coordinates":[114.90470999999999,23.51798],"type":"Point"}
}