{
  "type": "Feature",
  "properties": {
    "gn:admin1_code":"9.0",
    "gn:asciiname":"Xingcun",
    "gn:country_code":"CN",
    "gn:dem":78,
    "gn:feature_class":"P",
    "gn:feature_code":"PPL",
    "gn:name":"Xingcun",
    "gn:population":0,
    "gn:timezone":"Asia/Shanghai",
    "iso:country":"CN",
    "name:zho_x_preferred":[
        "\u90a2\u6751"
    ],
    "name:zho_x_variant":[
        "\u884c\u6751\u9547"
    ],
    "wof:name":"Xingcun",
    "wof:placetype":"locality"
},
  "geometry": {"coordinates":[114.22671,34.71467],"type":"Point"}
}