{
  "type": "Feature",
  "properties": {
    "gn:admin1_code":"16",
    "gn:asciiname":"Beining",
    "gn:country_code":"CN",
    "gn:dem":180,
    "gn:feature_class":"P",
    "gn:feature_code":"PPL",
    "gn:name":"Beining",
    "gn:population":0,
    "gn:timezone":"Asia/Shanghai",
    "iso:country":"CN",
    "name:und_x_variant":[
        "Pei-ning-hsiang",
        "Beining"
    ],
    "name:zho_x_preferred":[
        "\u5317\u5b81"
    ],
    "wof:name":"Beining",
    "wof:placetype":"locality"
},
  "geometry": {"coordinates":[107.218,22.2095],"type":"Point"}
}