{
  "type": "Feature",
  "properties": {
    "gn:admin1_code":"4.0",
    "gn:asciiname":"Xiaowucun",
    "gn:country_code":"CN",
    "gn:dem":51,
    "gn:feature_class":"P",
    "gn:feature_code":"PPL",
    "gn:name":"Xiaowucun",
    "gn:population":0,
    "gn:timezone":"Asia/Shanghai",
    "iso:country":"CN",
    "name:und_x_variant":[
        "Xiaowu",
        "Xiaowujia",
        "Xiaowucun"
    ],
    "name:zho_x_preferred":[
        "\u5c0f\u5434"
    ],
    "name:zho_x_variant":[
        "\u5c0f\u5434\u6751"
    ],
    "wof:name":"Xiaowucun",
    "wof:placetype":"locality"
},
  "geometry": {"coordinates":[117.61591,34.48029],"type":"Point"}
}