{
  "type": "Feature",
  "properties": {
    "gn:admin1_code":"8.0",
    "gn:asciiname":"Changmingcun",
    "gn:country_code":"CN",
    "gn:dem":61,
    "gn:feature_class":"P",
    "gn:feature_code":"PPL",
    "gn:name":"Changmingcun",
    "gn:population":0,
    "gn:timezone":"Asia/Shanghai",
    "iso:country":"CN",
    "name:zho_x_preferred":[
        "\u957f\u660e\u6751"
    ],
    "wof:name":"Changmingcun",
    "wof:placetype":"locality"
},
  "geometry": {"coordinates":[132.06568999999999,47.14106],"type":"Point"}
}