{
  "type": "Feature",
  "properties": {
    "gn:admin1_code":"15.0",
    "gn:asciiname":"Hongxian",
    "gn:country_code":"CN",
    "gn:dem":1693,
    "gn:feature_class":"P",
    "gn:feature_code":"PPL",
    "gn:name":"Hongxian",
    "gn:population":0,
    "gn:timezone":"Asia/Shanghai",
    "iso:country":"CN",
    "name:zho_x_preferred":[
        "\u7ea2\u5c98"
    ],
    "wof:name":"Hongxian",
    "wof:placetype":"locality"
},
  "geometry": {"coordinates":[104.182,36.7514],"type":"Point"}
}