{
  "type": "Feature",
  "properties": {
    "gn:admin1_code":"25",
    "gn:asciiname":"Xiangfuzhaibei",
    "gn:country_code":"CN",
    "gn:dem":61,
    "gn:feature_class":"P",
    "gn:feature_code":"PPL",
    "gn:name":"Xiangfuzhaibei",
    "gn:population":0,
    "gn:timezone":"Asia/Shanghai",
    "iso:country":"CN",
    "name:zho_x_preferred":[
        "\u7965\u7b26\u5be8\u5317"
    ],
    "wof:name":"Xiangfuzhaibei",
    "wof:placetype":"locality"
},
  "geometry": {"coordinates":[115.18300000000001,35.0438],"type":"Point"}
}