{
  "type": "Feature",
  "properties": {
    "gn:admin1_code":"7.0",
    "gn:asciiname":"Zao'ao",
    "gn:country_code":"CN",
    "gn:dem":101,
    "gn:feature_class":"P",
    "gn:feature_code":"PPL",
    "gn:name":"Zao\u2019ao",
    "gn:population":0,
    "gn:timezone":"Asia/Shanghai",
    "iso:country":"CN",
    "name:zho_x_preferred":[
        "Zao\u2019ao"
    ],
    "name:zho_x_variant":[
        "\u7076\u6fb3"
    ],
    "wof:name":"Zao'ao",
    "wof:placetype":"locality"
},
  "geometry": {"coordinates":[120.36903,26.93882],"type":"Point"}
}