{
  "type": "Feature",
  "properties": {
    "gn:admin1_code":"12.0",
    "gn:asciiname":"Shengkongping",
    "gn:country_code":"CN",
    "gn:dem":1250,
    "gn:feature_class":"P",
    "gn:feature_code":"PPL",
    "gn:name":"Shengkongping",
    "gn:population":0,
    "gn:timezone":"Asia/Shanghai",
    "iso:country":"CN",
    "name:zho_x_preferred":[
        "\u5723\u5b54\u576a"
    ],
    "wof:name":"Shengkongping",
    "wof:placetype":"locality"
},
  "geometry": {"coordinates":[109.22834,30.08865],"type":"Point"}
}