{
  "type": "Feature",
  "properties": {
    "gn:admin1_code":"29.0",
    "gn:asciiname":"Mina",
    "gn:country_code":"CN",
    "gn:dem":1283,
    "gn:feature_class":"P",
    "gn:feature_code":"PPL",
    "gn:name":"Mina",
    "gn:population":0,
    "gn:timezone":"Asia/Shanghai",
    "iso:country":"CN",
    "name:zho_x_preferred":[
        "\u8ff7\u90a3"
    ],
    "wof:name":"Mina",
    "wof:placetype":"locality"
},
  "geometry": {"coordinates":[101.866,22.9385],"type":"Point"}
}