{
  "type": "Feature",
  "properties": {
    "gn:admin1_code":"14.0",
    "gn:asciiname":"Lapei",
    "gn:country_code":"CN",
    "gn:dem":4559,
    "gn:feature_class":"P",
    "gn:feature_code":"PPL",
    "gn:name":"Lapei",
    "gn:population":0,
    "gn:timezone":"Asia/Urumqi",
    "iso:country":"CN",
    "name:zho_x_preferred":[
        "\u62c9\u57f9"
    ],
    "wof:name":"Lapei",
    "wof:placetype":"locality"
},
  "geometry": {"coordinates":[93.86745000000001,31.07959],"type":"Point"}
}