{
  "type": "Feature",
  "properties": {
    "gn:admin1_code":"14.0",
    "gn:asciiname":"Cunduo",
    "gn:country_code":"CN",
    "gn:dem":2665,
    "gn:feature_class":"P",
    "gn:feature_code":"PPL",
    "gn:name":"Cunduo",
    "gn:population":0,
    "gn:timezone":"Asia/Urumqi",
    "iso:country":"CN",
    "name:zho_x_preferred":[
        "\u5bf8\u591a"
    ],
    "wof:name":"Cunduo",
    "wof:placetype":"locality"
},
  "geometry": {"coordinates":[95.48142,29.89908],"type":"Point"}
}