{
  "type": "Feature",
  "properties": {
    "gn:admin1_code":"4.0",
    "gn:asciiname":"Huangpuzhuang",
    "gn:country_code":"CN",
    "gn:dem":4,
    "gn:feature_class":"P",
    "gn:feature_code":"PPL",
    "gn:name":"Huangpuzhuang",
    "gn:population":0,
    "gn:timezone":"Asia/Shanghai",
    "iso:country":"CN",
    "name:zho_x_preferred":[
        "Huangpuzhuang"
    ],
    "name:zho_x_variant":[
        "\u9ec4\u6d66\u5e84"
    ],
    "wof:name":"Huangpuzhuang",
    "wof:placetype":"locality"
},
  "geometry": {"coordinates":[119.40628,33.19447],"type":"Point"}
}