{
  "type": "Feature",
  "properties": {
    "gn:admin1_code":"14.0",
    "gn:asciiname":"Kebo",
    "gn:country_code":"CN",
    "gn:dem":4310,
    "gn:feature_class":"P",
    "gn:feature_code":"PPL",
    "gn:name":"Kebo",
    "gn:population":0,
    "gn:timezone":"Asia/Urumqi",
    "iso:country":"CN",
    "name:zho_x_preferred":[
        "\u53ef\u52c3"
    ],
    "wof:name":"Kebo",
    "wof:placetype":"locality"
},
  "geometry": {"coordinates":[96.48318999999999,30.58099],"type":"Point"}
}