{
  "type": "Feature",
  "properties": {
    "gn:admin1_code":"32.0",
    "gn:asciiname":"Xiema",
    "gn:country_code":"CN",
    "gn:dem":491,
    "gn:feature_class":"P",
    "gn:feature_code":"PPL",
    "gn:name":"Xiema",
    "gn:population":0,
    "gn:timezone":"Asia/Shanghai",
    "iso:country":"CN",
    "name:zho_x_preferred":[
        "\u6b47\u9a6c"
    ],
    "wof:name":"Xiema",
    "wof:placetype":"locality"
},
  "geometry": {"coordinates":[103.36957,29.78856],"type":"Point"}
}