{
  "type": "Feature",
  "properties": {
    "gn:admin1_code":"1.0",
    "gn:asciiname":"Banshiling",
    "gn:country_code":"CN",
    "gn:dem":104,
    "gn:feature_class":"P",
    "gn:feature_code":"PPL",
    "gn:name":"Banshiling",
    "gn:population":0,
    "gn:timezone":"Asia/Shanghai",
    "iso:country":"CN",
    "name:zho_x_preferred":[
        "\u677f\u77f3\u5cad"
    ],
    "wof:name":"Banshiling",
    "wof:placetype":"locality"
},
  "geometry": {"coordinates":[118.19261000000002,31.01129],"type":"Point"}
}