{
  "type": "Feature",
  "properties": {
    "gn:admin1_code":"8.0",
    "gn:asciiname":"Lianfeng",
    "gn:country_code":"CN",
    "gn:dem":209,
    "gn:feature_class":"P",
    "gn:feature_code":"PPLA4",
    "gn:name":"Lianfeng",
    "gn:population":0,
    "gn:timezone":"Asia/Shanghai",
    "iso:country":"CN",
    "name:und_x_variant":[
        "Lianfeng Xiang"
    ],
    "name:zho_x_preferred":[
        "\u8fde\u4e30"
    ],
    "name:zho_x_variant":[
        "\u8fde\u4e30\u4e61"
    ],
    "wof:name":"Lianfeng",
    "wof:placetype":"locality"
},
  "geometry": {"coordinates":[125.87873999999999,46.89618],"type":"Point"}
}