{
  "type": "Feature",
  "properties": {
    "gn:admin1_code":"26.0",
    "gn:asciiname":"Huaishuzhuang",
    "gn:country_code":"CN",
    "gn:dem":1164,
    "gn:feature_class":"P",
    "gn:feature_code":"PPL",
    "gn:name":"Huaishuzhuang",
    "gn:population":0,
    "gn:timezone":"Asia/Shanghai",
    "iso:country":"CN",
    "name:zho_x_preferred":[
        "\u69d0\u6811\u5e84"
    ],
    "wof:name":"Huaishuzhuang",
    "wof:placetype":"locality"
},
  "geometry": {"coordinates":[109.20865999999999,36.59832],"type":"Point"}
}