{
  "type": "Feature",
  "properties": {
    "gn:admin1_code":"01",
    "gn:asciiname":"Santacun",
    "gn:country_code":"CN",
    "gn:dem":34,
    "gn:feature_class":"P",
    "gn:feature_code":"PPL",
    "gn:name":"Santacun",
    "gn:population":0,
    "gn:timezone":"Asia/Shanghai",
    "iso:country":"CN",
    "name:und_x_variant":[
        "San-t\u2019a-chi",
        "Santa",
        "Santacun"
    ],
    "name:zho_x_preferred":[
        "\u4e09\u5854\u6751"
    ],
    "wof:name":"Santacun",
    "wof:placetype":"locality"
},
  "geometry": {"coordinates":[115.79810000000001,33.23431],"type":"Point"}
}