{
  "type": "Feature",
  "properties": {
    "gn:admin1_code":"3.0",
    "gn:asciiname":"Liwanbu",
    "gn:country_code":"CN",
    "gn:dem":27,
    "gn:feature_class":"P",
    "gn:feature_code":"PPL",
    "gn:name":"Liwanbu",
    "gn:population":0,
    "gn:timezone":"Asia/Shanghai",
    "iso:country":"CN",
    "name:und_x_variant":[
        "\u91cc\u4e07\u57e0"
    ],
    "wof:name":"Liwanbu",
    "wof:placetype":"locality"
},
  "geometry": {"coordinates":[116.64421000000002,28.60895],"type":"Point"}
}