{
  "type": "Feature",
  "properties": {
    "gn:admin1_code":"11.0",
    "gn:asciiname":"Shangdingwu",
    "gn:country_code":"CN",
    "gn:dem":80,
    "gn:feature_class":"P",
    "gn:feature_code":"PPL",
    "gn:name":"Shangdingwu",
    "gn:population":0,
    "gn:timezone":"Asia/Shanghai",
    "iso:country":"CN",
    "name:zho_x_preferred":[
        "\u4e0a\u9f0e\u5c4b"
    ],
    "wof:name":"Shangdingwu",
    "wof:placetype":"locality"
},
  "geometry": {"coordinates":[113.41027,29.5709],"type":"Point"}
}