{
  "type": "Feature",
  "properties": {
    "gn:admin1_code":"10",
    "gn:asciiname":"Longwangmiao",
    "gn:country_code":"CN",
    "gn:dem":455,
    "gn:feature_class":"P",
    "gn:feature_code":"PPL",
    "gn:name":"Longwangmiao",
    "gn:population":0,
    "gn:timezone":"Asia/Shanghai",
    "iso:country":"CN",
    "name:und_x_variant":[
        "Lunwan\u2019myao",
        "Lung-wang-miao",
        "Longwangmiao"
    ],
    "name:zho_x_preferred":[
        "\u9f99\u738b\u5e99"
    ],
    "wof:name":"Longwangmiao",
    "wof:placetype":"locality"
},
  "geometry": {"coordinates":[115.25320000000001,39.49367],"type":"Point"}
}