{
  "type": "Feature",
  "properties": {
    "gn:admin1_code":"30.0",
    "gn:asciiname":"Disanxi",
    "gn:country_code":"CN",
    "gn:dem":192,
    "gn:feature_class":"P",
    "gn:feature_code":"PPL",
    "gn:name":"Disanxi",
    "gn:population":0,
    "gn:timezone":"Asia/Shanghai",
    "iso:country":"CN",
    "name:zho_x_preferred":[
        "\u7b2c\u4e09\u6eaa"
    ],
    "wof:name":"Disanxi",
    "wof:placetype":"locality"
},
  "geometry": {"coordinates":[116.96254999999999,23.87014],"type":"Point"}
}