{
  "type": "Feature",
  "properties": {
    "gn:admin1_code":"10",
    "gn:asciiname":"Erdaoba",
    "gn:country_code":"CN",
    "gn:dem":1623,
    "gn:feature_class":"P",
    "gn:feature_code":"PPL",
    "gn:name":"Erdaoba",
    "gn:population":0,
    "gn:timezone":"Asia/Shanghai",
    "iso:country":"CN",
    "name:zho_x_preferred":[
        "\u4e8c\u9053\u575d"
    ],
    "wof:name":"Erdaoba",
    "wof:placetype":"locality"
},
  "geometry": {"coordinates":[115.42128999999998,41.33143],"type":"Point"}
}