{
  "type": "Feature",
  "properties": {
    "gn:admin1_code":"10",
    "gn:asciiname":"Mentouying",
    "gn:country_code":"CN",
    "gn:dem":1445,
    "gn:feature_class":"P",
    "gn:feature_code":"PPL",
    "gn:name":"Mentouying",
    "gn:population":0,
    "gn:timezone":"Asia/Shanghai",
    "iso:country":"CN",
    "name:zho_x_preferred":[
        "\u95e8\u5934\u8425"
    ],
    "wof:name":"Mentouying",
    "wof:placetype":"locality"
},
  "geometry": {"coordinates":[115.39896,41.07143],"type":"Point"}
}