{
  "type": "Feature",
  "properties": {
    "gn:admin1_code":"21.0",
    "gn:asciiname":"Longhuwan",
    "gn:country_code":"CN",
    "gn:dem":1615,
    "gn:feature_class":"P",
    "gn:feature_code":"PPL",
    "gn:name":"Longhuwan",
    "gn:population":0,
    "gn:timezone":"Asia/Shanghai",
    "iso:country":"CN",
    "name:zho_x_preferred":[
        "\u9f99\u864e\u6e7e"
    ],
    "wof:name":"Longhuwan",
    "wof:placetype":"locality"
},
  "geometry": {"coordinates":[106.84636999999999,36.05145],"type":"Point"}
}