{
  "type": "Feature",
  "properties": {
    "gn:admin1_code":"1.0",
    "gn:asciiname":"Hanmiaotaicun",
    "gn:country_code":"CN",
    "gn:dem":31,
    "gn:feature_class":"P",
    "gn:feature_code":"PPL",
    "gn:name":"Hanmiaotaicun",
    "gn:population":0,
    "gn:timezone":"Asia/Shanghai",
    "iso:country":"CN",
    "name:zho_x_preferred":[
        "\u97e9\u5e99\u53f0\u6751"
    ],
    "wof:name":"Hanmiaotaicun",
    "wof:placetype":"locality"
},
  "geometry": {"coordinates":[116.66506,33.40393],"type":"Point"}
}