{
  "type": "Feature",
  "properties": {
    "gn:admin1_code":"13.0",
    "gn:asciiname":"Ganjisayi",
    "gn:country_code":"CN",
    "gn:dem":2628,
    "gn:feature_class":"P",
    "gn:feature_code":"PPL",
    "gn:name":"Ganjisayi",
    "gn:population":0,
    "gn:timezone":"Asia/Shanghai",
    "iso:country":"CN",
    "name:zho_x_preferred":[
        "\u5e72\u5409\u8428\u4f9d"
    ],
    "wof:name":"Ganjisayi",
    "wof:placetype":"locality"
},
  "geometry": {"coordinates":[80.57628000000003,36.29854],"type":"Point"}
}