{
  "type": "Feature",
  "properties": {
    "gn:admin1_code":"9",
    "gn:asciiname":"Zhangdikou",
    "gn:country_code":"CN",
    "gn:dem":53,
    "gn:feature_class":"P",
    "gn:feature_code":"PPL",
    "gn:name":"Zhangdikou",
    "gn:population":0,
    "gn:timezone":"Asia/Shanghai",
    "iso:country":"CN",
    "name:zho_x_preferred":[
        "\u5f20\u5824\u53e3"
    ],
    "wof:name":"Zhangdikou",
    "wof:placetype":"locality"
},
  "geometry": {"coordinates":[115.804,34.5508],"type":"Point"}
}