{
  "type": "Feature",
  "properties": {
    "gn:admin1_code":"26.0",
    "gn:asciiname":"Xiazuitou",
    "gn:country_code":"CN",
    "gn:dem":1226,
    "gn:feature_class":"P",
    "gn:feature_code":"PPL",
    "gn:name":"Xiazuitou",
    "gn:population":0,
    "gn:timezone":"Asia/Shanghai",
    "iso:country":"CN",
    "name:zho_x_preferred":[
        "\u4e0b\u5480\u5934"
    ],
    "wof:name":"Xiazuitou",
    "wof:placetype":"locality"
},
  "geometry": {"coordinates":[108.14149999999999,35.22235],"type":"Point"}
}