{
  "type": "Feature",
  "properties": {
    "gn:admin1_code":"29.0",
    "gn:asciiname":"Dafuna",
    "gn:country_code":"CN",
    "gn:dem":1138,
    "gn:feature_class":"P",
    "gn:feature_code":"PPL",
    "gn:name":"Dafuna",
    "gn:population":0,
    "gn:timezone":"Asia/Shanghai",
    "iso:country":"CN",
    "name:zho_x_preferred":[
        "\u5927\u5bcc\u90a3"
    ],
    "wof:name":"Dafuna",
    "wof:placetype":"locality"
},
  "geometry": {"coordinates":[100.504,23.7224],"type":"Point"}
}