{
  "type": "Feature",
  "properties": {
    "gn:admin1_code":"2.0",
    "gn:asciiname":"Dingshan",
    "gn:country_code":"CN",
    "gn:dem":441,
    "gn:feature_class":"P",
    "gn:feature_code":"PPL",
    "gn:name":"Dingshan",
    "gn:population":0,
    "gn:timezone":"Asia/Shanghai",
    "iso:country":"CN",
    "name:zho_x_preferred":[
        "\u4e01\u5c71"
    ],
    "wof:name":"Dingshan",
    "wof:placetype":"locality"
},
  "geometry": {"coordinates":[120.77661000000001,29.23602],"type":"Point"}
}