{
  "type": "Feature",
  "properties": {
    "gn:admin1_code":"3",
    "gn:asciiname":"Shitouxia",
    "gn:country_code":"CN",
    "gn:dem":209,
    "gn:feature_class":"P",
    "gn:feature_code":"PPL",
    "gn:name":"Shitouxia",
    "gn:population":0,
    "gn:timezone":"Asia/Shanghai",
    "iso:country":"CN",
    "name:zho_x_preferred":[
        "\u77f3\u5934\u4e0b"
    ],
    "wof:name":"Shitouxia",
    "wof:placetype":"locality"
},
  "geometry": {"coordinates":[114.759,26.2054],"type":"Point"}
}