{
  "type": "Feature",
  "properties": {
    "gn:admin1_code":"19.0",
    "gn:asciiname":"Dagaojialing",
    "gn:country_code":"CN",
    "gn:dem":98,
    "gn:feature_class":"P",
    "gn:feature_code":"PPL",
    "gn:name":"Dagaojialing",
    "gn:population":0,
    "gn:timezone":"Asia/Shanghai",
    "iso:country":"CN",
    "name:zho_x_preferred":[
        "\u5927\u9ad8\u5bb6\u5cad"
    ],
    "wof:name":"Dagaojialing",
    "wof:placetype":"locality"
},
  "geometry": {"coordinates":[120.04346,40.33712],"type":"Point"}
}