{
  "type": "Feature",
  "properties": {
    "gn:admin1_code":"30.0",
    "gn:asciiname":"Xinhecun",
    "gn:country_code":"CN",
    "gn:dem":7,
    "gn:feature_class":"P",
    "gn:feature_code":"PPL",
    "gn:name":"Xinhecun",
    "gn:population":0,
    "gn:timezone":"Asia/Shanghai",
    "iso:country":"CN",
    "name:zho_x_preferred":[
        "\u65b0\u6cb3\u6751"
    ],
    "wof:name":"Xinhecun",
    "wof:placetype":"locality"
},
  "geometry": {"coordinates":[116.37247000000001,23.56349],"type":"Point"}
}