{
  "type": "Feature",
  "properties": {
    "gn:admin1_code":"12.0",
    "gn:asciiname":"Ninggang",
    "gn:country_code":"CN",
    "gn:dem":34,
    "gn:feature_class":"P",
    "gn:feature_code":"PPL",
    "gn:name":"Ninggang",
    "gn:population":0,
    "gn:timezone":"Asia/Shanghai",
    "iso:country":"CN",
    "name:und_x_variant":[
        "\u5b81\u6e2f"
    ],
    "wof:name":"Ninggang",
    "wof:placetype":"locality"
},
  "geometry": {"coordinates":[114.34479,30.3115],"type":"Point"}
}