{
  "type": "Feature",
  "properties": {
    "gn:admin1_code":"10",
    "gn:asciiname":"Houshuayu",
    "gn:country_code":"CN",
    "gn:dem":96,
    "gn:feature_class":"P",
    "gn:feature_code":"PPL",
    "gn:name":"Houshuayu",
    "gn:population":0,
    "gn:timezone":"Asia/Shanghai",
    "iso:country":"CN",
    "name:zho_x_preferred":[
        "\u540e\u800d\u5cea"
    ],
    "wof:name":"Houshuayu",
    "wof:placetype":"locality"
},
  "geometry": {"coordinates":[117.97595,39.97389],"type":"Point"}
}