{
  "type": "Feature",
  "properties": {
    "gn:admin1_code":"8.0",
    "gn:asciiname":"Niejiatun",
    "gn:country_code":"CN",
    "gn:dem":133,
    "gn:feature_class":"P",
    "gn:feature_code":"PPL",
    "gn:name":"Niejiatun",
    "gn:population":0,
    "gn:timezone":"Asia/Shanghai",
    "iso:country":"CN",
    "name:zho_x_preferred":[
        "\u8042\u5bb6\u5c6f"
    ],
    "wof:name":"Niejiatun",
    "wof:placetype":"locality"
},
  "geometry": {"coordinates":[127.73016,45.80862],"type":"Point"}
}