{
  "type": "Feature",
  "properties": {
    "gn:admin1_code":"32.0",
    "gn:asciiname":"Jigu",
    "gn:country_code":"CN",
    "gn:dem":3129,
    "gn:feature_class":"P",
    "gn:feature_code":"PPL",
    "gn:name":"Jigu",
    "gn:population":0,
    "gn:timezone":"Asia/Shanghai",
    "iso:country":"CN",
    "name:zho_x_preferred":[
        "\u9e21\u8c37"
    ],
    "wof:name":"Jigu",
    "wof:placetype":"locality"
},
  "geometry": {"coordinates":[100.97199999999999,27.8635],"type":"Point"}
}