{
  "type": "Feature",
  "properties": {
    "gn:admin1_code":"6.0",
    "gn:asciiname":"Cashunka",
    "gn:country_code":"CN",
    "gn:dem":4180,
    "gn:feature_class":"P",
    "gn:feature_code":"PPL",
    "gn:name":"Cashunka",
    "gn:population":0,
    "gn:timezone":"Asia/Urumqi",
    "iso:country":"CN",
    "name:zho_x_preferred":[
        "\u64e6\u987a\u5361"
    ],
    "wof:name":"Cashunka",
    "wof:placetype":"locality"
},
  "geometry": {"coordinates":[95.63388999999999,32.87353],"type":"Point"}
}