{
  "type": "Feature",
  "properties": {
    "gn:admin1_code":"2",
    "gn:asciiname":"Chenshancun",
    "gn:country_code":"CN",
    "gn:dem":525,
    "gn:feature_class":"P",
    "gn:feature_code":"PPL",
    "gn:name":"Chenshancun",
    "gn:population":0,
    "gn:timezone":"Asia/Shanghai",
    "iso:country":"CN",
    "name:zho_x_preferred":[
        "\u9648\u5c71\u6751"
    ],
    "wof:name":"Chenshancun",
    "wof:placetype":"locality"
},
  "geometry": {"coordinates":[119.01972000000001,27.88917],"type":"Point"}
}