{
  "type": "Feature",
  "properties": {
    "gn:admin1_code":"4.0",
    "gn:asciiname":"Guanhuocun",
    "gn:country_code":"CN",
    "gn:dem":3,
    "gn:feature_class":"P",
    "gn:feature_code":"PPL",
    "gn:name":"Guanhuocun",
    "gn:population":0,
    "gn:timezone":"Asia/Shanghai",
    "iso:country":"CN",
    "name:zho_x_preferred":[
        "\u7ba1\u4f19\u6751"
    ],
    "wof:name":"Guanhuocun",
    "wof:placetype":"locality"
},
  "geometry": {"coordinates":[119.47272,32.72809],"type":"Point"}
}