{
  "type": "Feature",
  "properties": {
    "gn:admin1_code":"26.0",
    "gn:asciiname":"Xiaozhuyuan",
    "gn:country_code":"CN",
    "gn:dem":999,
    "gn:feature_class":"P",
    "gn:feature_code":"PPL",
    "gn:name":"Xiaozhuyuan",
    "gn:population":0,
    "gn:timezone":"Asia/Shanghai",
    "iso:country":"CN",
    "name:zho_x_preferred":[
        "\u5c0f\u7af9\u56ed"
    ],
    "wof:name":"Xiaozhuyuan",
    "wof:placetype":"locality"
},
  "geometry": {"coordinates":[106.78206000000002,34.46296],"type":"Point"}
}