{
  "type": "Feature",
  "properties": {
    "gn:admin1_code":"33.0",
    "gn:asciiname":"Jingmei",
    "gn:country_code":"CN",
    "gn:dem":857,
    "gn:feature_class":"P",
    "gn:feature_code":"PPL",
    "gn:name":"Jingmei",
    "gn:population":0,
    "gn:timezone":"Asia/Shanghai",
    "iso:country":"CN",
    "name:zho_x_preferred":[
        "\u8346\u7164"
    ],
    "wof:name":"Jingmei",
    "wof:placetype":"locality"
},
  "geometry": {"coordinates":[108.16668,30.81033],"type":"Point"}
}