{
  "type": "Feature",
  "properties": {
    "gn:admin1_code":"4.0",
    "gn:asciiname":"Shuangxiancun",
    "gn:country_code":"CN",
    "gn:dem":4,
    "gn:feature_class":"P",
    "gn:feature_code":"PPL",
    "gn:name":"Shuangxiancun",
    "gn:population":0,
    "gn:timezone":"Asia/Shanghai",
    "iso:country":"CN",
    "name:zho_x_preferred":[
        "\u53cc\u5148\u6751"
    ],
    "wof:name":"Shuangxiancun",
    "wof:placetype":"locality"
},
  "geometry": {"coordinates":[120.27271,32.71448],"type":"Point"}
}