{
  "type": "Feature",
  "properties": {
    "gn:admin1_code":"20.0",
    "gn:asciiname":"Hougouzi",
    "gn:country_code":"CN",
    "gn:dem":358,
    "gn:feature_class":"P",
    "gn:feature_code":"PPL",
    "gn:name":"Hougouzi",
    "gn:population":0,
    "gn:timezone":"Asia/Shanghai",
    "iso:country":"CN",
    "name:zho_x_preferred":[
        "\u540e\u6c9f\u5b50"
    ],
    "wof:name":"Hougouzi",
    "wof:placetype":"locality"
},
  "geometry": {"coordinates":[124.05835999999999,48.91727],"type":"Point"}
}