{
  "type": "Feature",
  "properties": {
    "gn:admin1_code":"16.0",
    "gn:asciiname":"Xiyiling",
    "gn:country_code":"CN",
    "gn:dem":38,
    "gn:feature_class":"P",
    "gn:feature_code":"PPL",
    "gn:name":"Xiyiling",
    "gn:population":0,
    "gn:timezone":"Asia/Shanghai",
    "iso:country":"CN",
    "name:zho_x_preferred":[
        "\u897f\u76ca\u5cad"
    ],
    "wof:name":"Xiyiling",
    "wof:placetype":"locality"
},
  "geometry": {"coordinates":[110.446,23.5741],"type":"Point"}
}