{
  "type": "Feature",
  "properties": {
    "gn:admin1_code":"24",
    "gn:asciiname":"Dajiao",
    "gn:cc2":"CN",
    "gn:country_code":"CN",
    "gn:dem":508,
    "gn:feature_class":"P",
    "gn:feature_code":"PPL",
    "gn:name":"Dajiao",
    "gn:population":0,
    "gn:timezone":"Asia/Shanghai",
    "iso:country":"CN",
    "name:und_x_variant":[
        "Ta-chiao",
        "Ta-chiao-chen",
        "Dajiao"
    ],
    "wof:name":"Dajiao",
    "wof:placetype":"locality"
},
  "geometry": {"coordinates":[111.65472,35.63306],"type":"Point"}
}