{
  "type": "Feature",
  "properties": {
    "gn:admin1_code":"19.0",
    "gn:asciiname":"Shangpaishanlou Beigou",
    "gn:country_code":"CN",
    "gn:dem":328,
    "gn:feature_class":"P",
    "gn:feature_code":"PPL",
    "gn:name":"Shangpaishanlou Beigou",
    "gn:population":0,
    "gn:timezone":"Asia/Shanghai",
    "iso:country":"CN",
    "name:zho_x_preferred":[
        "\u4e0a\u6392\u5c71\u697c\u5317\u6c9f"
    ],
    "wof:name":"Shangpaishanlou Beigou",
    "wof:placetype":"locality"
},
  "geometry": {"coordinates":[121.73999999999999,41.8907],"type":"Point"}
}