{
  "type": "Feature",
  "properties": {
    "gn:admin1_code":"16.0",
    "gn:asciiname":"Yongqi",
    "gn:country_code":"CN",
    "gn:dem":310,
    "gn:feature_class":"P",
    "gn:feature_code":"PPL",
    "gn:name":"Yongqi",
    "gn:population":0,
    "gn:timezone":"Asia/Shanghai",
    "iso:country":"CN",
    "name:zho_x_preferred":[
        "\u62e5\u9f50"
    ],
    "wof:name":"Yongqi",
    "wof:placetype":"locality"
},
  "geometry": {"coordinates":[107.538,23.6467],"type":"Point"}
}