{
  "type": "Feature",
  "properties": {
    "gn:admin1_code":"32.0",
    "gn:asciiname":"Banzhushan",
    "gn:country_code":"CN",
    "gn:dem":443,
    "gn:feature_class":"P",
    "gn:feature_code":"PPL",
    "gn:name":"Banzhushan",
    "gn:population":0,
    "gn:timezone":"Asia/Shanghai",
    "iso:country":"CN",
    "name:zho_x_preferred":[
        "\u6591\u7af9\u5c71"
    ],
    "wof:name":"Banzhushan",
    "wof:placetype":"locality"
},
  "geometry": {"coordinates":[104.803,31.0205],"type":"Point"}
}