{
  "type": "Feature",
  "properties": {
    "gn:admin1_code":"12.0",
    "gn:asciiname":"Jianjiazui",
    "gn:country_code":"CN",
    "gn:dem":130,
    "gn:feature_class":"P",
    "gn:feature_code":"PPL",
    "gn:name":"Jianjiazui",
    "gn:population":0,
    "gn:timezone":"Asia/Shanghai",
    "iso:country":"CN",
    "name:zho_x_preferred":[
        "Jianjiazui"
    ],
    "name:zho_x_variant":[
        "\u7b80\u5bb6\u5480"
    ],
    "wof:name":"Jianjiazui",
    "wof:placetype":"locality"
},
  "geometry": {"coordinates":[111.20425,30.71187],"type":"Point"}
}