{
  "type": "Feature",
  "properties": {
    "gn:admin1_code":"7.0",
    "gn:asciiname":"Nanxing",
    "gn:country_code":"CN",
    "gn:dem":621,
    "gn:feature_class":"P",
    "gn:feature_code":"PPL",
    "gn:name":"Nanxing",
    "gn:population":0,
    "gn:timezone":"Asia/Shanghai",
    "iso:country":"CN",
    "name:zho_x_preferred":[
        "\u5357\u5174"
    ],
    "wof:name":"Nanxing",
    "wof:placetype":"locality"
},
  "geometry": {"coordinates":[118.77055,25.51081],"type":"Point"}
}