{
  "type": "Feature",
  "properties": {
    "gn:country":"CN",
    "gn:fcode":"PPL",
    "gn:pop":431,
    "iso:country":"CN",
    "qs:name":"Nuxi",
    "qs:photos_9r":0,
    "qs:photos_sr":0,
    "qs:pop_sr":"2",
    "wof:name":"Nuxi",
    "wof:placetype":"locality",
    "wof:population":431
},
  "geometry": {"coordinates":[108.91110999999999,27.86833],"type":"Point"}
}