{
  "type": "Feature",
  "properties": {
    "gn:admin1_code":"32.0",
    "gn:asciiname":"Longxing",
    "gn:country_code":"CN",
    "gn:dem":314,
    "gn:feature_class":"P",
    "gn:feature_code":"PPL",
    "gn:name":"Longxing",
    "gn:population":0,
    "gn:timezone":"Asia/Shanghai",
    "iso:country":"CN",
    "name:deu_x_preferred":[
        "Longxing"
    ],
    "name:zho_x_preferred":[
        "\u9f99\u5174"
    ],
    "wof:name":"Longxing",
    "wof:placetype":"locality"
},
  "geometry": {"coordinates":[105.51600000000001,30.5401],"type":"Point"}
}