{
  "type": "Feature",
  "properties": {
    "gn:admin1_code":"13.0",
    "gn:asciiname":"Aiwuzaile",
    "gn:country_code":"CN",
    "gn:dem":2941,
    "gn:feature_class":"P",
    "gn:feature_code":"PPL",
    "gn:name":"Aiwuzaile",
    "gn:population":0,
    "gn:timezone":"Asia/Shanghai",
    "iso:country":"CN",
    "name:zho_x_preferred":[
        "\u827e\u543e\u518d\u52d2"
    ],
    "wof:name":"Aiwuzaile",
    "wof:placetype":"locality"
},
  "geometry": {"coordinates":[78.36148,36.84122],"type":"Point"}
}