{
  "type": "Feature",
  "properties": {
    "gn:admin1_code":"24.0",
    "gn:asciiname":"Sihao",
    "gn:country_code":"CN",
    "gn:dem":1445,
    "gn:feature_class":"P",
    "gn:feature_code":"PPL",
    "gn:name":"Sihao",
    "gn:population":0,
    "gn:timezone":"Asia/Shanghai",
    "iso:country":"CN",
    "name:zho_x_preferred":[
        "\u56db\u7693"
    ],
    "wof:name":"Sihao",
    "wof:placetype":"locality"
},
  "geometry": {"coordinates":[111.41377,38.01534],"type":"Point"}
}