{
  "type": "Feature",
  "properties": {
    "gn:admin1_code":"15.0",
    "gn:asciiname":"Maoniu Taizi",
    "gn:country_code":"CN",
    "gn:dem":3035,
    "gn:feature_class":"P",
    "gn:feature_code":"PPL",
    "gn:name":"Maoniu Taizi",
    "gn:population":0,
    "gn:timezone":"Asia/Shanghai",
    "iso:country":"CN",
    "name:zho_x_preferred":[
        "\u7266\u725b\u53f0\u5b50"
    ],
    "wof:name":"Maoniu Taizi",
    "wof:placetype":"locality"
},
  "geometry": {"coordinates":[102.69199999999999,37.3604],"type":"Point"}
}