{
  "type": "Feature",
  "properties": {
    "gn:admin1_code":"2.0",
    "gn:asciiname":"Shuiluding",
    "gn:country_code":"CN",
    "gn:dem":45,
    "gn:feature_class":"P",
    "gn:feature_code":"PPL",
    "gn:name":"Shuiluding",
    "gn:population":0,
    "gn:timezone":"Asia/Shanghai",
    "iso:country":"CN",
    "name:und_x_variant":[
        "\u6c34\u8def\u9876",
        "Shuiluding"
    ],
    "wof:name":"Shuiluding",
    "wof:placetype":"locality"
},
  "geometry": {"coordinates":[119.30989,29.15944],"type":"Point"}
}