{
  "type": "Feature",
  "properties": {
    "gn:admin1_code":"29.0",
    "gn:asciiname":"Muguazhe",
    "gn:country_code":"CN",
    "gn:dem":2128,
    "gn:feature_class":"P",
    "gn:feature_code":"PPL",
    "gn:name":"Muguazhe",
    "gn:population":0,
    "gn:timezone":"Asia/Shanghai",
    "iso:country":"CN",
    "name:zho_x_preferred":[
        "\u6728\u74dc\u8005"
    ],
    "wof:name":"Muguazhe",
    "wof:placetype":"locality"
},
  "geometry": {"coordinates":[100.836,25.0642],"type":"Point"}
}