{
  "type": "Feature",
  "properties": {
    "gn:admin1_code":"26",
    "gn:asciiname":"Shangyunan",
    "gn:country_code":"CN",
    "gn:dem":985,
    "gn:feature_class":"P",
    "gn:feature_code":"PPL",
    "gn:name":"Shangyunan",
    "gn:population":0,
    "gn:timezone":"Asia/Shanghai",
    "iso:country":"CN",
    "name:und_x_variant":[
        "\u4e0a\u5cea\u5357"
    ],
    "name:zho_x_preferred":[
        "\u4e0a\u5cea\u5357"
    ],
    "wof:name":"Shangyunan",
    "wof:placetype":"locality"
},
  "geometry": {"coordinates":[108.47306,34.64306],"type":"Point"}
}