{
  "type": "Feature",
  "properties": {
    "gn:admin1_code":"29.0",
    "gn:asciiname":"Bailongtan",
    "gn:country_code":"CN",
    "gn:dem":2398,
    "gn:feature_class":"P",
    "gn:feature_code":"PPL",
    "gn:name":"Bailongtan",
    "gn:population":0,
    "gn:timezone":"Asia/Shanghai",
    "iso:country":"CN",
    "name:zho_x_preferred":[
        "\u767d\u9f99\u6f6d"
    ],
    "wof:name":"Bailongtan",
    "wof:placetype":"locality"
},
  "geometry": {"coordinates":[103.48,25.8966],"type":"Point"}
}