{
  "type": "Feature",
  "properties": {
    "gn:admin1_code":"3.0",
    "gn:asciiname":"Xinrenping",
    "gn:country_code":"CN",
    "gn:dem":141,
    "gn:feature_class":"P",
    "gn:feature_code":"PPL",
    "gn:name":"Xinrenping",
    "gn:population":0,
    "gn:timezone":"Asia/Shanghai",
    "iso:country":"CN",
    "name:und_x_variant":[
        "\u65b0\u4eba\u576a"
    ],
    "wof:name":"Xinrenping",
    "wof:placetype":"locality"
},
  "geometry": {"coordinates":[116.29613000000001,26.86216],"type":"Point"}
}