{
  "type": "Feature",
  "properties": {
    "gn:admin1_code":"3.0",
    "gn:asciiname":"Chijia'ao",
    "gn:country_code":"CN",
    "gn:dem":417,
    "gn:feature_class":"P",
    "gn:feature_code":"PPL",
    "gn:name":"Chijia\u2019ao",
    "gn:population":0,
    "gn:timezone":"Asia/Shanghai",
    "iso:country":"CN",
    "name:und_x_variant":[
        "Chijia\u2019ao",
        "\u6c60\u5bb6\u5773"
    ],
    "wof:name":"Chijia'ao",
    "wof:placetype":"locality"
},
  "geometry": {"coordinates":[116.44864,26.58939],"type":"Point"}
}