{
  "type": "Feature",
  "properties": {
    "gn:admin1_code":"30.0",
    "gn:asciiname":"Hepaishui",
    "gn:country_code":"CN",
    "gn:dem":46,
    "gn:feature_class":"P",
    "gn:feature_code":"PPL",
    "gn:name":"Hepaishui",
    "gn:population":0,
    "gn:timezone":"Asia/Shanghai",
    "iso:country":"CN",
    "name:zho_x_preferred":[
        "\u4f55\u6392\u6c34"
    ],
    "wof:name":"Hepaishui",
    "wof:placetype":"locality"
},
  "geometry": {"coordinates":[113.03055999999999,24.27056],"type":"Point"}
}