{
  "type": "Feature",
  "properties": {
    "gn:admin1_code":"25.0",
    "gn:asciiname":"Zijiadian",
    "gn:country_code":"CN",
    "gn:dem":26,
    "gn:feature_class":"P",
    "gn:feature_code":"PPL",
    "gn:name":"Zijiadian",
    "gn:population":0,
    "gn:timezone":"Asia/Shanghai",
    "iso:country":"CN",
    "name:zho_x_preferred":[
        "\u8a3e\u5bb6\u5e97"
    ],
    "wof:name":"Zijiadian",
    "wof:placetype":"locality"
},
  "geometry": {"coordinates":[119.30929,35.31378],"type":"Point"}
}