{
  "type": "Feature",
  "properties": {
    "gn:admin1_code":"3.0",
    "gn:asciiname":"Shangyang Meikeng",
    "gn:country_code":"CN",
    "gn:dem":319,
    "gn:feature_class":"P",
    "gn:feature_code":"PPL",
    "gn:name":"Shangyang Meikeng",
    "gn:population":0,
    "gn:timezone":"Asia/Shanghai",
    "iso:country":"CN",
    "name:zho_x_preferred":[
        "\u4e0a\u6768\u6885\u5751"
    ],
    "wof:name":"Shangyang Meikeng",
    "wof:placetype":"locality"
},
  "geometry": {"coordinates":[115.67573,24.95767],"type":"Point"}
}