{
  "type": "Feature",
  "properties": {
    "gn:admin1_code":"29.0",
    "gn:asciiname":"Fanjiazhai",
    "gn:country_code":"CN",
    "gn:dem":1806,
    "gn:feature_class":"P",
    "gn:feature_code":"PPL",
    "gn:name":"Fanjiazhai",
    "gn:population":0,
    "gn:timezone":"Asia/Shanghai",
    "iso:country":"CN",
    "name:zho_x_preferred":[
        "\u8303\u5bb6\u5be8"
    ],
    "wof:name":"Fanjiazhai",
    "wof:placetype":"locality"
},
  "geometry": {"coordinates":[98.67359999999999,25.2576],"type":"Point"}
}