{
  "type": "Feature",
  "properties": {
    "gn:admin1_code":"19.0",
    "gn:asciiname":"Xiaowangjiatun",
    "gn:country_code":"CN",
    "gn:dem":23,
    "gn:feature_class":"P",
    "gn:feature_code":"PPL",
    "gn:name":"Xiaowangjiatun",
    "gn:population":0,
    "gn:timezone":"Asia/Shanghai",
    "iso:country":"CN",
    "name:und_x_variant":[
        "\u5c0f\u738b\u5bb6\u5c6f"
    ],
    "name:zho_x_preferred":[
        "\u5c0f\u738b\u5bb6\u5c6f"
    ],
    "wof:name":"Xiaowangjiatun",
    "wof:placetype":"locality"
},
  "geometry": {"coordinates":[122.90586,39.67977],"type":"Point"}
}