{
  "type": "Feature",
  "properties": {
    "gn:admin1_code":"19.0",
    "gn:asciiname":"Erdaohezicun",
    "gn:country_code":"CN",
    "gn:dem":120,
    "gn:feature_class":"P",
    "gn:feature_code":"PPL",
    "gn:name":"Erdaohezicun",
    "gn:population":0,
    "gn:timezone":"Asia/Shanghai",
    "iso:country":"CN",
    "name:zho_x_preferred":[
        "\u4e8c\u9053\u6cb3\u5b50\u6751"
    ],
    "wof:name":"Erdaohezicun",
    "wof:placetype":"locality"
},
  "geometry": {"coordinates":[124.29000000000001,42.694],"type":"Point"}
}