{
  "type": "Feature",
  "properties": {
    "gn:admin1_code":"16.0",
    "gn:asciiname":"Chuangcun",
    "gn:country_code":"CN",
    "gn:dem":95,
    "gn:feature_class":"P",
    "gn:feature_code":"PPL",
    "gn:name":"Chuangcun",
    "gn:population":0,
    "gn:timezone":"Asia/Shanghai",
    "iso:country":"CN",
    "name:zho_x_preferred":[
        "\u521b\u6751"
    ],
    "wof:name":"Chuangcun",
    "wof:placetype":"locality"
},
  "geometry": {"coordinates":[109.687,21.8818],"type":"Point"}
}