{
  "type": "Feature",
  "properties": {
    "gn:admin1_code":"2.0",
    "gn:asciiname":"Waishuangxi",
    "gn:country_code":"CN",
    "gn:dem":794,
    "gn:feature_class":"P",
    "gn:feature_code":"PPL",
    "gn:name":"Waishuangxi",
    "gn:population":0,
    "gn:timezone":"Asia/Shanghai",
    "iso:country":"CN",
    "name:zho_x_preferred":[
        "\u5916\u53cc\u6eaa"
    ],
    "wof:name":"Waishuangxi",
    "wof:placetype":"locality"
},
  "geometry": {"coordinates":[119.07834,28.25837000000001],"type":"Point"}
}