{
  "type": "Feature",
  "properties": {
    "gn:admin1_code":"32.0",
    "gn:asciiname":"Xiaoliushu",
    "gn:country_code":"CN",
    "gn:dem":1840,
    "gn:feature_class":"P",
    "gn:feature_code":"PPL",
    "gn:name":"Xiaoliushu",
    "gn:population":0,
    "gn:timezone":"Asia/Shanghai",
    "iso:country":"CN",
    "name:zho_x_preferred":[
        "\u5c0f\u67f3\u6811"
    ],
    "wof:name":"Xiaoliushu",
    "wof:placetype":"locality"
},
  "geometry": {"coordinates":[102.224,26.5821],"type":"Point"}
}