{
  "type": "Feature",
  "properties": {
    "gn:admin1_code":"24.0",
    "gn:asciiname":"Leping",
    "gn:country_code":"CN",
    "gn:dem":914,
    "gn:feature_class":"P",
    "gn:feature_code":"PPLA3",
    "gn:name":"Leping",
    "gn:population":0,
    "gn:timezone":"Asia/Shanghai",
    "iso:country":"CN",
    "name:deu_x_preferred":[
        "Leping"
    ],
    "name:est_x_preferred":[
        "Leping"
    ],
    "name:fra_x_preferred":[
        "Leping"
    ],
    "name:ita_x_preferred":[
        "Leping"
    ],
    "name:jpn_x_preferred":[
        "\u697d\u5e73\u5e02"
    ],
    "name:kik_x_preferred":[
        "Leping"
    ],
    "name:kor_x_preferred":[
        "\ub7ec\ud551\uc2dc"
    ],
    "name:nor_x_preferred":[
        "Leping"
    ],
    "name:swe_x_preferred":[
        "Leping"
    ],
    "name:und_x_variant":[
        "Hsi-yang",
        "Siyang",
        "Hsi-yang-hsien",
        "Xiyang",
        "Leping",
        "Leping Zhen",
        "Xiyang Xian",
        "\u6614\u9633\u53bf",
        "\u4e50\u5e73\u9547"
    ],
    "name:vie_x_preferred":[
        "L\u1ea1c B\u00ecnh"
    ],
    "name:zho_x_preferred":[
        "Lo-p\u2019ing"
    ],
    "name:zho_x_variant":[
        "\u4e50\u5e73",
        "\u4e50\u5e73\u5e02"
    ],
    "wof:name":"Leping",
    "wof:placetype":"locality"
},
  "geometry": {"coordinates":[113.66499,37.61469],"type":"Point"}
}