{
  "type": "Feature",
  "properties": {
    "gn:admin1_code":"26",
    "gn:asciiname":"Dongzhongcun",
    "gn:country_code":"CN",
    "gn:dem":513,
    "gn:feature_class":"P",
    "gn:feature_code":"PPL",
    "gn:name":"Dongzhongcun",
    "gn:population":0,
    "gn:timezone":"Asia/Shanghai",
    "iso:country":"CN",
    "name:zho_x_preferred":[
        "\u4e1c\u4e2d\u6751"
    ],
    "wof:name":"Dongzhongcun",
    "wof:placetype":"locality"
},
  "geometry": {"coordinates":[109.31431000000001,34.91335],"type":"Point"}
}