{
  "type": "Feature",
  "properties": {
    "gn:admin1_code":"30.0",
    "gn:asciiname":"Huangzhitang",
    "gn:country_code":"CN",
    "gn:dem":245,
    "gn:feature_class":"P",
    "gn:feature_code":"PPL",
    "gn:name":"Huangzhitang",
    "gn:population":0,
    "gn:timezone":"Asia/Shanghai",
    "iso:country":"CN",
    "name:zho_x_preferred":[
        "\u9ec4\u679d\u5858"
    ],
    "wof:name":"Huangzhitang",
    "wof:placetype":"locality"
},
  "geometry": {"coordinates":[113.00444,24.01889],"type":"Point"}
}