{
  "type": "Feature",
  "properties": {
    "gn:admin1_code":"3.0",
    "gn:asciiname":"Nantang'an",
    "gn:country_code":"CN",
    "gn:dem":117,
    "gn:feature_class":"P",
    "gn:feature_code":"PPL",
    "gn:name":"Nantang\u2019an",
    "gn:population":0,
    "gn:timezone":"Asia/Shanghai",
    "iso:country":"CN",
    "name:und_x_variant":[
        "Nantang\u2019an"
    ],
    "name:zho_x_preferred":[
        "\u5357\u5802\u5eb5"
    ],
    "wof:name":"Nantang'an",
    "wof:placetype":"locality"
},
  "geometry": {"coordinates":[113.621,27.4641],"type":"Point"}
}