{
  "type": "Feature",
  "properties": {
    "gn:admin1_code":"15.0",
    "gn:asciiname":"Majiawan",
    "gn:country_code":"CN",
    "gn:dem":2165,
    "gn:feature_class":"P",
    "gn:feature_code":"PPL",
    "gn:name":"Majiawan",
    "gn:population":0,
    "gn:timezone":"Asia/Shanghai",
    "iso:country":"CN",
    "name:und_x_variant":[
        "\u9a6c\u5bb6\u6e7e"
    ],
    "wof:name":"Majiawan",
    "wof:placetype":"locality"
},
  "geometry": {"coordinates":[102.827,35.8198],"type":"Point"}
}