{
  "type": "Feature",
  "properties": {
    "gn:admin1_code":"5.0",
    "gn:asciiname":"Pengjiayao",
    "gn:country_code":"CN",
    "gn:dem":599,
    "gn:feature_class":"P",
    "gn:feature_code":"PPL",
    "gn:name":"Pengjiayao",
    "gn:population":0,
    "gn:timezone":"Asia/Shanghai",
    "iso:country":"CN",
    "name:und_x_variant":[
        "\u5f6d\u5bb6\u7a91"
    ],
    "wof:name":"Pengjiayao",
    "wof:placetype":"locality"
},
  "geometry": {"coordinates":[126.55793,41.91627],"type":"Point"}
}