{
  "type": "Feature",
  "properties": {
    "gn:admin1_code":"28",
    "gn:asciiname":"Chenguantun",
    "gn:country_code":"CN",
    "gn:dem":8,
    "gn:feature_class":"P",
    "gn:feature_code":"PPLA4",
    "gn:name":"Chenguantun",
    "gn:population":0,
    "gn:timezone":"Asia/Shanghai",
    "iso:country":"CN",
    "name:und_x_variant":[
        "Ch\u2019en-kuan-t\u2019un",
        "Chenguantun",
        "Chenguantun Zhen"
    ],
    "name:zho_x_preferred":[
        "\u9648\u5b98\u5c6f"
    ],
    "name:zho_x_variant":[
        "\u9648\u5b98\u5c6f\u9547"
    ],
    "wof:name":"Chenguantun",
    "wof:placetype":"locality"
},
  "geometry": {"coordinates":[116.9057,38.81963],"type":"Point"}
}