{
  "type": "Feature",
  "properties": {
    "gn:admin1_code":"25",
    "gn:asciiname":"Yuanjia'an",
    "gn:country_code":"CN",
    "gn:dem":11,
    "gn:feature_class":"P",
    "gn:feature_code":"PPL",
    "gn:name":"Yuanjia\u2019an",
    "gn:population":0,
    "gn:timezone":"Asia/Shanghai",
    "iso:country":"CN",
    "name:und_x_variant":[
        "Yuanjia\u2019an"
    ],
    "name:zho_x_preferred":[
        "\u8881\u5bb6\u5eb5"
    ],
    "wof:name":"Yuanjia'an",
    "wof:placetype":"locality"
},
  "geometry": {"coordinates":[117.919,37.4969],"type":"Point"}
}