{
  "type": "Feature",
  "properties": {
    "gn:admin1_code":"11.0",
    "gn:asciiname":"Lisu",
    "gn:country_code":"CN",
    "gn:dem":317,
    "gn:feature_class":"P",
    "gn:feature_code":"PPL",
    "gn:name":"Lisu",
    "gn:population":0,
    "gn:timezone":"Asia/Shanghai",
    "iso:country":"CN",
    "name:zho_x_preferred":[
        "\u6817\u7c9f"
    ],
    "wof:name":"Lisu",
    "wof:placetype":"locality"
},
  "geometry": {"coordinates":[109.73741,28.24204000000001],"type":"Point"}
}