{
  "type": "Feature",
  "properties": {
    "gn:admin1_code":"2.0",
    "gn:asciiname":"Shanxiapeng",
    "gn:country_code":"CN",
    "gn:dem":47,
    "gn:feature_class":"P",
    "gn:feature_code":"PPL",
    "gn:name":"Shanxiapeng",
    "gn:population":0,
    "gn:timezone":"Asia/Shanghai",
    "iso:country":"CN",
    "name:zho_x_preferred":[
        "\u5c71\u4e0b\u5f6d"
    ],
    "wof:name":"Shanxiapeng",
    "wof:placetype":"locality"
},
  "geometry": {"coordinates":[120.53861999999999,27.63884],"type":"Point"}
}