{
  "type": "Feature",
  "properties": {
    "gn:admin1_code":"9.0",
    "gn:asciiname":"Jiangdongzhuang",
    "gn:country_code":"CN",
    "gn:dem":141,
    "gn:feature_class":"P",
    "gn:feature_code":"PPL",
    "gn:name":"Jiangdongzhuang",
    "gn:population":0,
    "gn:timezone":"Asia/Shanghai",
    "iso:country":"CN",
    "name:und_x_variant":[
        "\u59dc\u680b\u5e84",
        "Jiangdongzhuang"
    ],
    "wof:name":"Jiangdongzhuang",
    "wof:placetype":"locality"
},
  "geometry": {"coordinates":[112.83556000000002,33.13888],"type":"Point"}
}