{
  "type": "Feature",
  "properties": {
    "gn:admin1_code":"4.0",
    "gn:asciiname":"Tingkui Yizu",
    "gn:country_code":"CN",
    "gn:dem":4,
    "gn:feature_class":"P",
    "gn:feature_code":"PPLF",
    "gn:name":"Tingkui Yizu",
    "gn:population":0,
    "gn:timezone":"Asia/Shanghai",
    "iso:country":"CN",
    "name:zho_x_preferred":[
        "\u5ef7\u594e\u4e00\u7ec4"
    ],
    "wof:name":"Tingkui Yizu",
    "wof:placetype":"locality"
},
  "geometry": {"coordinates":[121.44374999999999,32.01103],"type":"Point"}
}