{
  "type": "Feature",
  "properties": {
    "gn:admin1_code":"19.0",
    "gn:asciiname":"Nantianmen",
    "gn:country_code":"CN",
    "gn:dem":238,
    "gn:feature_class":"P",
    "gn:feature_code":"PPL",
    "gn:name":"Nantianmen",
    "gn:population":0,
    "gn:timezone":"Asia/Shanghai",
    "iso:country":"CN",
    "name:zho_x_preferred":[
        "\u5357\u5929\u95e8"
    ],
    "wof:name":"Nantianmen",
    "wof:placetype":"locality"
},
  "geometry": {"coordinates":[122.322,39.7155],"type":"Point"}
}