{
  "type": "Feature",
  "properties": {
    "gn:admin1_code":"4.0",
    "gn:asciiname":"Hangji",
    "gn:country_code":"CN",
    "gn:dem":6,
    "gn:feature_class":"P",
    "gn:feature_code":"PPLA4",
    "gn:name":"Hangji",
    "gn:population":0,
    "gn:timezone":"Asia/Shanghai",
    "iso:country":"CN",
    "name:und_x_variant":[
        "Hangji Zhen"
    ],
    "name:zho_x_preferred":[
        "\u676d\u96c6"
    ],
    "name:zho_x_variant":[
        "\u676d\u96c6\u9547"
    ],
    "wof:name":"Hangji",
    "wof:placetype":"locality"
},
  "geometry": {"coordinates":[119.533,32.36815],"type":"Point"}
}