{
  "type": "Feature",
  "properties": {
    "gn:admin1_code":"25",
    "gn:asciiname":"Guocun",
    "gn:country_code":"CN",
    "gn:dem":101,
    "gn:feature_class":"P",
    "gn:feature_code":"PPL",
    "gn:name":"Guocun",
    "gn:population":0,
    "gn:timezone":"Asia/Shanghai",
    "iso:country":"CN",
    "name:zho_x_preferred":[
        "\u8fc7\u6751"
    ],
    "wof:name":"Guocun",
    "wof:placetype":"locality"
},
  "geometry": {"coordinates":[116.90600000000001,36.0445],"type":"Point"}
}