{
  "type": "Feature",
  "properties": {
    "gn:admin1_code":"2.0",
    "gn:asciiname":"Yunxi",
    "gn:country_code":"CN",
    "gn:dem":228,
    "gn:feature_class":"P",
    "gn:feature_code":"PPL",
    "gn:name":"Yunxi",
    "gn:population":0,
    "gn:timezone":"Asia/Shanghai",
    "iso:country":"CN",
    "name:ceb_x_preferred":[
        "Yunxi"
    ],
    "name:deu_x_preferred":[
        "Yunxi"
    ],
    "name:fra_x_preferred":[
        "Yunxi"
    ],
    "name:nor_x_preferred":[
        "Yunxi"
    ],
    "name:swe_x_preferred":[
        "Yunxi"
    ],
    "name:zho_x_preferred":[
        "\u4e91\u6eaa"
    ],
    "wof:name":"Yunxi",
    "wof:placetype":"locality"
},
  "geometry": {"coordinates":[120.82940000000001,28.6609],"type":"Point"}
}