{
  "type": "Feature",
  "properties": {
    "gn:admin1_code":"8.0",
    "gn:asciiname":"Zhaodiankuan",
    "gn:country_code":"CN",
    "gn:dem":167,
    "gn:feature_class":"P",
    "gn:feature_code":"PPL",
    "gn:name":"Zhaodiankuan",
    "gn:population":0,
    "gn:timezone":"Asia/Shanghai",
    "iso:country":"CN",
    "name:zho_x_preferred":[
        "\u8d75\u6bbf\u5bbd"
    ],
    "wof:name":"Zhaodiankuan",
    "wof:placetype":"locality"
},
  "geometry": {"coordinates":[127.31975,46.82727],"type":"Point"}
}