{
  "type": "Feature",
  "properties": {
    "gn:admin1_code":"10.0",
    "gn:asciiname":"Nanshi",
    "gn:country_code":"CN",
    "gn:dem":22,
    "gn:feature_class":"P",
    "gn:feature_code":"PPL",
    "gn:name":"Nanshi",
    "gn:population":0,
    "gn:timezone":"Asia/Shanghai",
    "iso:country":"CN",
    "name:ceb_x_preferred":[
        "Nanshi"
    ],
    "name:deu_x_preferred":[
        "Nanshi"
    ],
    "name:swe_x_preferred":[
        "Nanshi"
    ],
    "name:zho_x_preferred":[
        "\u5357\u77f3"
    ],
    "wof:name":"Nanshi",
    "wof:placetype":"locality"
},
  "geometry": {"coordinates":[116.59657,39.43422],"type":"Point"}
}