{
  "type": "Feature",
  "properties": {
    "gn:admin1_code":"26.0",
    "gn:asciiname":"Anransi",
    "gn:country_code":"CN",
    "gn:dem":523,
    "gn:feature_class":"P",
    "gn:feature_code":"PPL",
    "gn:name":"Anransi",
    "gn:population":0,
    "gn:timezone":"Asia/Shanghai",
    "iso:country":"CN",
    "name:und_x_variant":[
        "\u5b89\u7136\u5bfa"
    ],
    "wof:name":"Anransi",
    "wof:placetype":"locality"
},
  "geometry": {"coordinates":[107.089,33.10868],"type":"Point"}
}