{
  "type": "Feature",
  "properties": {
    "gn:admin1_code":"8.0",
    "gn:asciiname":"Minzhengcun",
    "gn:country_code":"CN",
    "gn:dem":300,
    "gn:feature_class":"P",
    "gn:feature_code":"PPL",
    "gn:name":"Minzhengcun",
    "gn:population":0,
    "gn:timezone":"Asia/Shanghai",
    "iso:country":"CN",
    "name:zho_x_preferred":[
        "\u6c11\u653f\u6751"
    ],
    "wof:name":"Minzhengcun",
    "wof:placetype":"locality"
},
  "geometry": {"coordinates":[126.07453999999998,47.77133],"type":"Point"}
}