{
  "type": "Feature",
  "properties": {
    "gn:admin1_code":"29.0",
    "gn:asciiname":"Shuangtaishu",
    "gn:country_code":"CN",
    "gn:dem":1097,
    "gn:feature_class":"P",
    "gn:feature_code":"PPL",
    "gn:name":"Shuangtaishu",
    "gn:population":0,
    "gn:timezone":"Asia/Shanghai",
    "iso:country":"CN",
    "name:zho_x_preferred":[
        "\u53cc\u53f0\u6811"
    ],
    "wof:name":"Shuangtaishu",
    "wof:placetype":"locality"
},
  "geometry": {"coordinates":[101.125,23.9724],"type":"Point"}
}