{
  "type": "Feature",
  "properties": {
    "gn:admin1_code":"14.0",
    "gn:asciiname":"Sele",
    "gn:country_code":"CN",
    "gn:dem":4695,
    "gn:feature_class":"P",
    "gn:feature_code":"PPL",
    "gn:name":"Sele",
    "gn:population":0,
    "gn:timezone":"Asia/Urumqi",
    "iso:country":"CN",
    "name:bos_x_preferred":[
        "Sele"
    ],
    "name:ceb_x_preferred":[
        "Sele"
    ],
    "name:dan_x_preferred":[
        "Sele"
    ],
    "name:deu_x_preferred":[
        "Sele"
    ],
    "name:hrv_x_preferred":[
        "Sele"
    ],
    "name:nld_x_preferred":[
        "Sele"
    ],
    "name:nor_x_preferred":[
        "Sele"
    ],
    "name:pms_x_preferred":[
        "Sele"
    ],
    "name:pol_x_preferred":[
        "Sele"
    ],
    "name:rus_x_preferred":[
        "\u0421\u0435\u043b\u0435"
    ],
    "name:slv_x_preferred":[
        "Sele"
    ],
    "name:srp_x_preferred":[
        "\u0421\u0435\u043b\u0435"
    ],
    "name:swe_x_preferred":[
        "Sele"
    ],
    "name:zho_x_preferred":[
        "\u8272\u52d2"
    ],
    "wof:name":"Sele",
    "wof:placetype":"locality"
},
  "geometry": {"coordinates":[86.08,31.0224],"type":"Point"}
}