{
  "type": "Feature",
  "properties": {
    "gn:admin1_code":"14.0",
    "gn:asciiname":"Sele",
    "gn:country_code":"CN",
    "gn:dem":4695,
    "gn:feature_class":"P",
    "gn:feature_code":"PPL",
    "gn:name":"Sele",
    "gn:population":0,
    "gn:timezone":"Asia/Urumqi",
    "iso:country":"CN",
    "name:zho_x_preferred":[
        "\u8272\u52d2"
    ],
    "wof:name":"Sele",
    "wof:placetype":"locality"
},
  "geometry": {"coordinates":[86.08,31.0224],"type":"Point"}
}