{
  "type": "Feature",
  "properties": {
    "gn:admin1_code":"18",
    "gn:asciiname":"Chejia",
    "gn:country_code":"CN",
    "gn:dem":2413,
    "gn:feature_class":"P",
    "gn:feature_code":"PPL",
    "gn:name":"Chejia",
    "gn:population":0,
    "gn:timezone":"Asia/Shanghai",
    "iso:country":"CN",
    "name:zho_x_preferred":[
        "\u626f\u621b"
    ],
    "wof:name":"Chejia",
    "wof:placetype":"locality"
},
  "geometry": {"coordinates":[104.048,26.79300000000001],"type":"Point"}
}