{
  "type": "Feature",
  "properties": {
    "gn:admin1_code":"11.0",
    "gn:asciiname":"Fengfuling",
    "gn:country_code":"CN",
    "gn:dem":83,
    "gn:feature_class":"P",
    "gn:feature_code":"PPL",
    "gn:name":"Fengfuling",
    "gn:population":0,
    "gn:timezone":"Asia/Shanghai",
    "iso:country":"CN",
    "name:zho_x_preferred":[
        "\u4e30\u5bcc\u5cad"
    ],
    "wof:name":"Fengfuling",
    "wof:placetype":"locality"
},
  "geometry": {"coordinates":[113.44186999999999,28.22744],"type":"Point"}
}