{
  "type": "Feature",
  "properties": {
    "gn:admin1_code":"19.0",
    "gn:asciiname":"Tongzhangzi",
    "gn:country_code":"CN",
    "gn:dem":398,
    "gn:feature_class":"P",
    "gn:feature_code":"PPL",
    "gn:name":"Tongzhangzi",
    "gn:population":0,
    "gn:timezone":"Asia/Shanghai",
    "iso:country":"CN",
    "name:und_x_variant":[
        "\u4f5f\u6756\u5b50"
    ],
    "name:zho_x_preferred":[
        "\u4f5f\u6756\u5b50"
    ],
    "wof:name":"Tongzhangzi",
    "wof:placetype":"locality"
},
  "geometry": {"coordinates":[119.8031,40.69699],"type":"Point"}
}