{
  "type": "Feature",
  "properties": {
    "gn:admin1_code":"19.0",
    "gn:asciiname":"Dajiangjiatun",
    "gn:country_code":"CN",
    "gn:dem":7,
    "gn:feature_class":"P",
    "gn:feature_code":"PPL",
    "gn:name":"Dajiangjiatun",
    "gn:population":0,
    "gn:timezone":"Asia/Shanghai",
    "iso:country":"CN",
    "name:zho_x_preferred":[
        "\u5927\u59dc\u5bb6\u5c6f"
    ],
    "wof:name":"Dajiangjiatun",
    "wof:placetype":"locality"
},
  "geometry": {"coordinates":[123.25700000000001,39.8148],"type":"Point"}
}