{
  "type": "Feature",
  "properties": {
    "gn:admin1_code":"2.0",
    "gn:asciiname":"Chiyuan",
    "gn:country_code":"CN",
    "gn:dem":731,
    "gn:feature_class":"P",
    "gn:feature_code":"PPL",
    "gn:name":"Chiyuan",
    "gn:population":0,
    "gn:timezone":"Asia/Shanghai",
    "iso:country":"CN",
    "name:zho_x_preferred":[
        "\u6c60\u6e90"
    ],
    "wof:name":"Chiyuan",
    "wof:placetype":"locality"
},
  "geometry": {"coordinates":[120.01178,27.54362],"type":"Point"}
}