{
  "type": "Feature",
  "properties": {
    "gn:admin1_code":"32.0",
    "gn:asciiname":"Wujia Pipashan",
    "gn:country_code":"CN",
    "gn:dem":497,
    "gn:feature_class":"P",
    "gn:feature_code":"PPL",
    "gn:name":"Wujia Pipashan",
    "gn:population":0,
    "gn:timezone":"Asia/Shanghai",
    "iso:country":"CN",
    "name:zho_x_preferred":[
        "\u4f0d\u5bb6\u7435\u7436\u5c71"
    ],
    "wof:name":"Wujia Pipashan",
    "wof:placetype":"locality"
},
  "geometry": {"coordinates":[106.325,30.7136],"type":"Point"}
}