{
  "type": "Feature",
  "properties": {
    "gn:admin1_code":"4.0",
    "gn:asciiname":"Jianghe",
    "gn:country_code":"CN",
    "gn:dem":17,
    "gn:feature_class":"P",
    "gn:feature_code":"PPL",
    "gn:name":"Jianghe",
    "gn:population":0,
    "gn:timezone":"Asia/Shanghai",
    "iso:country":"CN",
    "name:zho_x_preferred":[
        "Jianghe"
    ],
    "name:zho_x_variant":[
        "\u848b\u6cb3"
    ],
    "wof:name":"Jianghe",
    "wof:placetype":"locality"
},
  "geometry": {"coordinates":[119.0278,34.92493],"type":"Point"}
}