{
  "type": "Feature",
  "properties": {
    "gn:admin1_code":"2.0",
    "gn:asciiname":"Duntangjiao",
    "gn:country_code":"CN",
    "gn:dem":11,
    "gn:feature_class":"P",
    "gn:feature_code":"PPL",
    "gn:name":"Duntangjiao",
    "gn:population":0,
    "gn:timezone":"Asia/Shanghai",
    "iso:country":"CN",
    "name:und_x_variant":[
        "\u58a9\u5858\u89d2"
    ],
    "wof:name":"Duntangjiao",
    "wof:placetype":"locality"
},
  "geometry": {"coordinates":[120.32946,30.44244],"type":"Point"}
}