{
  "type": "Feature",
  "properties": {
    "gn:admin1_code":"4.0",
    "gn:asciiname":"Qiangaoshe",
    "gn:country_code":"CN",
    "gn:dem":3,
    "gn:feature_class":"P",
    "gn:feature_code":"PPL",
    "gn:name":"Qiangaoshe",
    "gn:population":0,
    "gn:timezone":"Asia/Shanghai",
    "iso:country":"CN",
    "name:zho_x_preferred":[
        "Qiangaoshe"
    ],
    "name:zho_x_variant":[
        "\u524d\u9ad8\u820d"
    ],
    "wof:name":"Qiangaoshe",
    "wof:placetype":"locality"
},
  "geometry": {"coordinates":[119.44153,33.40164],"type":"Point"}
}