{
  "type": "Feature",
  "properties": {
    "gn:admin1_code":"7",
    "gn:asciiname":"Xiandian",
    "gn:country_code":"CN",
    "gn:dem":212,
    "gn:feature_class":"P",
    "gn:feature_code":"PPL",
    "gn:name":"Xiandian",
    "gn:population":0,
    "gn:timezone":"Asia/Shanghai",
    "iso:country":"CN",
    "name:und_x_variant":[
        "\u4ed9\u5e97"
    ],
    "name:zho_x_preferred":[
        "\u4ed9\u5e97"
    ],
    "wof:name":"Xiandian",
    "wof:placetype":"locality"
},
  "geometry": {"coordinates":[117.98694,27.57611],"type":"Point"}
}