{
  "type": "Feature",
  "properties": {
    "gn:admin1_code":"24.0",
    "gn:asciiname":"Shaoyaogou",
    "gn:country_code":"CN",
    "gn:dem":1643,
    "gn:feature_class":"P",
    "gn:feature_code":"PPL",
    "gn:name":"Shaoyaogou",
    "gn:population":0,
    "gn:timezone":"Asia/Shanghai",
    "iso:country":"CN",
    "name:und_x_variant":[
        "\u828d\u836f\u6c9f"
    ],
    "wof:name":"Shaoyaogou",
    "wof:placetype":"locality"
},
  "geometry": {"coordinates":[112.77475,39.73451],"type":"Point"}
}