{
  "type": "Feature",
  "properties": {
    "gn:admin1_code":"14",
    "gn:asciiname":"Bomdoi",
    "gn:country_code":"CN",
    "gn:dem":3705,
    "gn:feature_class":"P",
    "gn:feature_code":"PPL",
    "gn:name":"Bomdoi",
    "gn:population":0,
    "gn:timezone":"Asia/Urumqi",
    "iso:country":"CN",
    "name:bod_x_preferred":[
        "\u0f60\u0f56\u0fb2\u0f7c\u0f58\u0f0b\u0f66\u0f9f\u0f7c\u0f51"
    ],
    "name:bod_x_variant":[
        "\u0f60\u0f56\u0fb2\u0f7c\u0f58\u0f0b\u0f50\u0f7c\u0f51"
    ],
    "name:und_x_variant":[
        "Bangdui",
        "Zhomtoi"
    ],
    "name:zho_x_preferred":[
        "\u5e2e\u5806"
    ],
    "wof:name":"Bomdoi",
    "wof:placetype":"locality"
},
  "geometry": {"coordinates":[91.38342,29.69625],"type":"Point"}
}