{
  "type": "Feature",
  "properties": {
    "gn:admin1_code":"12.0",
    "gn:asciiname":"Wangjiatian",
    "gn:country_code":"CN",
    "gn:dem":62,
    "gn:feature_class":"P",
    "gn:feature_code":"PPL",
    "gn:name":"Wangjiatian",
    "gn:population":0,
    "gn:timezone":"Asia/Shanghai",
    "iso:country":"CN",
    "name:zho_x_preferred":[
        "\u6c6a\u5bb6\u7530"
    ],
    "wof:name":"Wangjiatian",
    "wof:placetype":"locality"
},
  "geometry": {"coordinates":[114.58223999999998,31.0505],"type":"Point"}
}