{
  "type": "Feature",
  "properties": {
    "gn:admin1_code":"7.0",
    "gn:asciiname":"Cuoping",
    "gn:country_code":"CN",
    "gn:dem":53,
    "gn:feature_class":"P",
    "gn:feature_code":"PPL",
    "gn:name":"Cuoping",
    "gn:population":0,
    "gn:timezone":"Asia/Shanghai",
    "iso:country":"CN",
    "name:zho_x_preferred":[
        "\u539d\u576a"
    ],
    "wof:name":"Cuoping",
    "wof:placetype":"locality"
},
  "geometry": {"coordinates":[119.58766,26.92229],"type":"Point"}
}