{
  "type": "Feature",
  "properties": {
    "gn:admin1_code":"10",
    "gn:asciiname":"Toudao Goumen",
    "gn:country_code":"CN",
    "gn:dem":953,
    "gn:feature_class":"P",
    "gn:feature_code":"PPL",
    "gn:name":"Toudao Goumen",
    "gn:population":0,
    "gn:timezone":"Asia/Shanghai",
    "iso:country":"CN",
    "name:zho_x_preferred":[
        "\u5934\u9053\u6c9f\u95e8"
    ],
    "wof:name":"Toudao Goumen",
    "wof:placetype":"locality"
},
  "geometry": {"coordinates":[117.03892,41.52566],"type":"Point"}
}