{
  "type": "Feature",
  "properties": {
    "gn:admin1_code":"24.0",
    "gn:asciiname":"Shanyaozi",
    "gn:country_code":"CN",
    "gn:dem":1357,
    "gn:feature_class":"P",
    "gn:feature_code":"PPL",
    "gn:name":"Shanyaozi",
    "gn:population":0,
    "gn:timezone":"Asia/Shanghai",
    "iso:country":"CN",
    "name:und_x_variant":[
        "\u912f\u7a91\u5b50"
    ],
    "wof:name":"Shanyaozi",
    "wof:placetype":"locality"
},
  "geometry": {"coordinates":[112.38978,39.12559],"type":"Point"}
}