{
  "type": "Feature",
  "properties": {
    "gn:admin1_code":"7.0",
    "gn:asciiname":"Shiliao",
    "gn:country_code":"CN",
    "gn:dem":550,
    "gn:feature_class":"P",
    "gn:feature_code":"PPL",
    "gn:name":"Shiliao",
    "gn:population":0,
    "gn:timezone":"Asia/Shanghai",
    "iso:country":"CN",
    "name:und_x_variant":[
        "\u77f3\u5bee"
    ],
    "name:zho_x_preferred":[
        "\u77f3\u5bee"
    ],
    "wof:name":"Shiliao",
    "wof:placetype":"locality"
},
  "geometry": {"coordinates":[116.79165,26.40093],"type":"Point"}
}