{
  "type": "Feature",
  "properties": {
    "gn:admin1_code":"4.0",
    "gn:asciiname":"Libacun",
    "gn:country_code":"CN",
    "gn:dem":3,
    "gn:feature_class":"P",
    "gn:feature_code":"PPL",
    "gn:name":"Libacun",
    "gn:population":0,
    "gn:timezone":"Asia/Shanghai",
    "iso:country":"CN",
    "name:zho_x_preferred":[
        "\u674e\u575d\u6751"
    ],
    "wof:name":"Libacun",
    "wof:placetype":"locality"
},
  "geometry": {"coordinates":[120.32250999999999,33.3081],"type":"Point"}
}