{
  "type": "Feature",
  "properties": {
    "gn:admin1_code":"5.0",
    "gn:asciiname":"Jiapigou",
    "gn:country_code":"CN",
    "gn:dem":413,
    "gn:feature_class":"P",
    "gn:feature_code":"PPL",
    "gn:name":"Jiapigou",
    "gn:population":0,
    "gn:timezone":"Asia/Shanghai",
    "iso:country":"CN",
    "name:und_x_variant":[
        "\u5939\u76ae\u6c9f"
    ],
    "wof:name":"Jiapigou",
    "wof:placetype":"locality"
},
  "geometry": {"coordinates":[127.17443,41.58191],"type":"Point"}
}