{
  "type": "Feature",
  "properties": {
    "gn:admin1_code":"16",
    "gn:asciiname":"Qingpan",
    "gn:country_code":"CN",
    "gn:dem":142,
    "gn:feature_class":"P",
    "gn:feature_code":"PPL",
    "gn:name":"Qingpan",
    "gn:population":0,
    "gn:timezone":"Asia/Shanghai",
    "iso:country":"CN",
    "name:zho_x_preferred":[
        "\u5e86\u76d8"
    ],
    "wof:name":"Qingpan",
    "wof:placetype":"locality"
},
  "geometry": {"coordinates":[110.527,24.5348],"type":"Point"}
}