{
  "type": "Feature",
  "properties": {
    "gn:admin1_code":"7",
    "gn:asciiname":"Tingxi",
    "gn:country_code":"CN",
    "gn:dem":864,
    "gn:feature_class":"P",
    "gn:feature_code":"PPL",
    "gn:name":"Tingxi",
    "gn:population":0,
    "gn:timezone":"Asia/Shanghai",
    "iso:country":"CN",
    "name:und_x_variant":[
        "\u4ead\u6eaa",
        "Tingxi"
    ],
    "wof:name":"Tingxi",
    "wof:placetype":"locality"
},
  "geometry": {"coordinates":[119.53304,27.48914000000001],"type":"Point"}
}