{
  "type": "Feature",
  "properties": {
    "gn:admin1_code":"8.0",
    "gn:asciiname":"Xishantoucun",
    "gn:country_code":"CN",
    "gn:dem":191,
    "gn:feature_class":"P",
    "gn:feature_code":"PPL",
    "gn:name":"Xishantoucun",
    "gn:population":0,
    "gn:timezone":"Asia/Shanghai",
    "iso:country":"CN",
    "name:zho_x_preferred":[
        "\u897f\u5c71\u5934\u6751"
    ],
    "wof:name":"Xishantoucun",
    "wof:placetype":"locality"
},
  "geometry": {"coordinates":[123.00379,46.74039000000001],"type":"Point"}
}