{
  "type": "Feature",
  "properties": {
    "gn:admin1_code":"16.0",
    "gn:asciiname":"Baihua",
    "gn:country_code":"CN",
    "gn:dem":111,
    "gn:feature_class":"P",
    "gn:feature_code":"PPL",
    "gn:name":"Baihua",
    "gn:population":0,
    "gn:timezone":"Asia/Shanghai",
    "iso:country":"CN",
    "name:vie_x_preferred":[
        "B\u1ea1ch tho\u1ea1i"
    ],
    "name:zho_x_preferred":[
        "\u767d\u82b1"
    ],
    "wof:name":"Baihua",
    "wof:placetype":"locality"
},
  "geometry": {"coordinates":[111.64100000000001,24.4227],"type":"Point"}
}