{
  "type": "Feature",
  "properties": {
    "gn:admin1_code":"30",
    "gn:asciiname":"Xiapingshan",
    "gn:country_code":"CN",
    "gn:dem":49,
    "gn:feature_class":"P",
    "gn:feature_code":"PPL",
    "gn:name":"Xiapingshan",
    "gn:population":0,
    "gn:timezone":"Asia/Urumqi",
    "iso:country":"CN",
    "name:zho_x_preferred":[
        "\u4e0b\u5e73\u5c71"
    ],
    "wof:name":"Xiapingshan",
    "wof:placetype":"locality"
},
  "geometry": {"coordinates":[111.12927000000001,21.79588],"type":"Point"}
}