{
  "type": "Feature",
  "properties": {
    "gn:admin1_code":"18",
    "gn:asciiname":"Jiadingchang",
    "gn:country_code":"CN",
    "gn:dem":1311,
    "gn:feature_class":"P",
    "gn:feature_code":"PPL",
    "gn:name":"Jiadingchang",
    "gn:population":0,
    "gn:timezone":"Asia/Shanghai",
    "iso:country":"CN",
    "name:zho_x_preferred":[
        "\u7532\u5b9a\u573a"
    ],
    "wof:name":"Jiadingchang",
    "wof:placetype":"locality"
},
  "geometry": {"coordinates":[106.857,26.2316],"type":"Point"}
}