{
  "type": "Feature",
  "properties": {
    "gn:admin1_code":"32.0",
    "gn:asciiname":"Moduozha",
    "gn:country_code":"CN",
    "gn:dem":1770,
    "gn:feature_class":"P",
    "gn:feature_code":"PPL",
    "gn:name":"Moduozha",
    "gn:population":0,
    "gn:timezone":"Asia/Shanghai",
    "iso:country":"CN",
    "name:zho_x_preferred":[
        "\u6469\u54c6\u6805"
    ],
    "wof:name":"Moduozha",
    "wof:placetype":"locality"
},
  "geometry": {"coordinates":[102.26799,26.35273],"type":"Point"}
}