{
  "type": "Feature",
  "properties": {
    "gn:admin1_code":"24.0",
    "gn:asciiname":"Longhuacun",
    "gn:country_code":"CN",
    "gn:dem":1073,
    "gn:feature_class":"P",
    "gn:feature_code":"PPL",
    "gn:name":"Longhuacun",
    "gn:population":0,
    "gn:timezone":"Asia/Shanghai",
    "iso:country":"CN",
    "name:zho_x_preferred":[
        "\u9f99\u5316\u6751"
    ],
    "wof:name":"Longhuacun",
    "wof:placetype":"locality"
},
  "geometry": {"coordinates":[110.95322,36.53878],"type":"Point"}
}