{
  "type": "Feature",
  "properties": {
    "gn:admin1_code":"32.0",
    "gn:asciiname":"Cangtoushan",
    "gn:country_code":"CN",
    "gn:dem":1568,
    "gn:feature_class":"P",
    "gn:feature_code":"PPL",
    "gn:name":"Cangtoushan",
    "gn:population":0,
    "gn:timezone":"Asia/Shanghai",
    "iso:country":"CN",
    "name:zho_x_preferred":[
        "\u82cd\u5934\u5c71"
    ],
    "wof:name":"Cangtoushan",
    "wof:placetype":"locality"
},
  "geometry": {"coordinates":[104.5742,31.95013],"type":"Point"}
}