{
  "type": "Feature",
  "properties": {
    "gn:admin1_code":"12.0",
    "gn:asciiname":"Xiacaiqi",
    "gn:country_code":"CN",
    "gn:dem":1443,
    "gn:feature_class":"P",
    "gn:feature_code":"PPL",
    "gn:name":"Xiacaiqi",
    "gn:population":0,
    "gn:timezone":"Asia/Shanghai",
    "iso:country":"CN",
    "name:zho_x_preferred":[
        "\u4e0b\u5f69\u65d7"
    ],
    "wof:name":"Xiacaiqi",
    "wof:placetype":"locality"
},
  "geometry": {"coordinates":[110.43093,31.4585],"type":"Point"}
}