{
  "type": "Feature",
  "properties": {
    "gn:admin1_code":"29.0",
    "gn:asciiname":"Muguashu",
    "gn:country_code":"CN",
    "gn:dem":1808,
    "gn:feature_class":"P",
    "gn:feature_code":"PPL",
    "gn:name":"Muguashu",
    "gn:population":0,
    "gn:timezone":"Asia/Shanghai",
    "iso:country":"CN",
    "name:zho_x_preferred":[
        "\u6728\u74dc\u6811"
    ],
    "wof:name":"Muguashu",
    "wof:placetype":"locality"
},
  "geometry": {"coordinates":[99.93380000000001,25.7665],"type":"Point"}
}