{
  "type": "Feature",
  "properties": {
    "gn:admin1_code":"2.0",
    "gn:asciiname":"Lingjia'an",
    "gn:country_code":"CN",
    "gn:dem":7,
    "gn:feature_class":"P",
    "gn:feature_code":"PPL",
    "gn:name":"Lingjia\u2019an",
    "gn:population":0,
    "gn:timezone":"Asia/Shanghai",
    "iso:country":"CN",
    "name:zho_x_preferred":[
        "\u51cc\u5bb6\u5cb8"
    ],
    "name:zho_x_variant":[
        "Lingjia\u2019an"
    ],
    "wof:name":"Lingjia'an",
    "wof:placetype":"locality"
},
  "geometry": {"coordinates":[120.54604,29.98196],"type":"Point"}
}