{
  "type": "Feature",
  "properties": {
    "gn:admin1_code":"16.0",
    "gn:asciiname":"Nongwang",
    "gn:country_code":"CN",
    "gn:dem":418,
    "gn:feature_class":"P",
    "gn:feature_code":"PPL",
    "gn:name":"Nongwang",
    "gn:population":0,
    "gn:timezone":"Asia/Shanghai",
    "iso:country":"CN",
    "name:zho_x_preferred":[
        "\u5f04\u65fa"
    ],
    "wof:name":"Nongwang",
    "wof:placetype":"locality"
},
  "geometry": {"coordinates":[108.066,24.1528],"type":"Point"}
}