{
  "type": "Feature",
  "properties": {
    "gn:admin1_code":"5.0",
    "gn:asciiname":"Quanyancun",
    "gn:country_code":"CN",
    "gn:dem":350,
    "gn:feature_class":"P",
    "gn:feature_code":"PPL",
    "gn:name":"Quanyancun",
    "gn:population":0,
    "gn:timezone":"Asia/Shanghai",
    "iso:country":"CN",
    "name:zho_x_preferred":[
        "\u6cc9\u773c\u6751"
    ],
    "wof:name":"Quanyancun",
    "wof:placetype":"locality"
},
  "geometry": {"coordinates":[125.00105000000001,42.69069],"type":"Point"}
}