{
  "type": "Feature",
  "properties": {
    "gn:admin1_code":"31.0",
    "gn:asciiname":"Shijiaba",
    "gn:country_code":"CN",
    "gn:dem":424,
    "gn:elevation":"445.0",
    "gn:feature_class":"P",
    "gn:feature_code":"PPL",
    "gn:name":"Shijiaba",
    "gn:population":0,
    "gn:timezone":"Asia/Shanghai",
    "iso:country":"CN",
    "name:und_x_variant":[
        "\u4ec0\u67b6\u5df4"
    ],
    "wof:name":"Shijiaba",
    "wof:placetype":"locality"
},
  "geometry": {"coordinates":[109.89555,18.94186],"type":"Point"}
}