{
  "type": "Feature",
  "properties": {
    "gn:admin1_code":"29.0",
    "gn:asciiname":"Laogaozhai",
    "gn:country_code":"CN",
    "gn:dem":1789,
    "gn:feature_class":"P",
    "gn:feature_code":"PPL",
    "gn:name":"Laogaozhai",
    "gn:population":0,
    "gn:timezone":"Asia/Shanghai",
    "iso:country":"CN",
    "name:zho_x_preferred":[
        "\u8001\u9ad8\u5be8"
    ],
    "wof:name":"Laogaozhai",
    "wof:placetype":"locality"
},
  "geometry": {"coordinates":[104.533,25.3598],"type":"Point"}
}