{
  "type": "Feature",
  "properties": {
    "gn:admin1_code":"1.0",
    "gn:asciiname":"Fenghuangxi",
    "gn:country_code":"CN",
    "gn:dem":384,
    "gn:feature_class":"P",
    "gn:feature_code":"PPL",
    "gn:name":"Fenghuangxi",
    "gn:population":0,
    "gn:timezone":"Asia/Shanghai",
    "iso:country":"CN",
    "name:zho_x_preferred":[
        "\u51e4\u51f0\u6eaa"
    ],
    "wof:name":"Fenghuangxi",
    "wof:placetype":"locality"
},
  "geometry": {"coordinates":[118.40458,29.51654000000001],"type":"Point"}
}