{
  "type": "Feature",
  "properties": {
    "gn:admin1_code":"10.0",
    "gn:asciiname":"Hongqili",
    "gn:country_code":"CN",
    "gn:dem":5,
    "gn:feature_class":"P",
    "gn:feature_code":"PPL",
    "gn:name":"Hongqili",
    "gn:population":0,
    "gn:timezone":"Asia/Shanghai",
    "iso:country":"CN",
    "name:zho_x_preferred":[
        "\u7ea2\u65d7\u91cc"
    ],
    "wof:name":"Hongqili",
    "wof:placetype":"locality"
},
  "geometry": {"coordinates":[119.5814,39.93518],"type":"Point"}
}