{
  "type": "Feature",
  "properties": {
    "gn:admin1_code":"25",
    "gn:asciiname":"Disi",
    "gn:country_code":"CN",
    "gn:dem":30,
    "gn:feature_class":"P",
    "gn:feature_code":"PPL",
    "gn:name":"Disi",
    "gn:population":0,
    "gn:timezone":"Asia/Shanghai",
    "iso:country":"CN",
    "name:bar_x_preferred":[
        "Disi"
    ],
    "name:ceb_x_preferred":[
        "Disi"
    ],
    "name:deu_x_preferred":[
        "Disi"
    ],
    "name:swe_x_preferred":[
        "Disi"
    ],
    "name:zho_x_preferred":[
        "\u7fdf\u5bfa"
    ],
    "wof:name":"Disi",
    "wof:placetype":"locality"
},
  "geometry": {"coordinates":[116.41500000000001,36.5681],"type":"Point"}
}