{
  "type": "Feature",
  "properties": {
    "gn:admin1_code":"5.0",
    "gn:asciiname":"Gongxing",
    "gn:country_code":"CN",
    "gn:dem":254,
    "gn:feature_class":"P",
    "gn:feature_code":"PPL",
    "gn:name":"Gongxing",
    "gn:population":0,
    "gn:timezone":"Asia/Shanghai",
    "iso:country":"CN",
    "name:und_x_variant":[
        "\u5171\u5174"
    ],
    "wof:name":"Gongxing",
    "wof:placetype":"locality"
},
  "geometry": {"coordinates":[129.52122,43.32243],"type":"Point"}
}