{
  "type": "Feature",
  "properties": {
    "gn:admin1_code":"33.0",
    "gn:asciiname":"Chezhuling",
    "gn:country_code":"CN",
    "gn:dem":462,
    "gn:feature_class":"P",
    "gn:feature_code":"PPL",
    "gn:name":"Chezhuling",
    "gn:population":0,
    "gn:timezone":"Asia/Shanghai",
    "iso:country":"CN",
    "name:zho_x_preferred":[
        "\u8f66\u7af9\u5cad"
    ],
    "wof:name":"Chezhuling",
    "wof:placetype":"locality"
},
  "geometry": {"coordinates":[109.17617,28.83793],"type":"Point"}
}