{
  "type": "Feature",
  "properties": {
    "gn:admin1_code":"7.0",
    "gn:asciiname":"Dazuo",
    "gn:country_code":"CN",
    "gn:dem":110,
    "gn:feature_class":"P",
    "gn:feature_code":"PPL",
    "gn:name":"Dazuo",
    "gn:population":0,
    "gn:timezone":"Asia/Shanghai",
    "iso:country":"CN",
    "name:und_x_variant":[
        "\u5927\u4f5c"
    ],
    "name:zho_x_preferred":[
        "\u5927\u4f5c"
    ],
    "wof:name":"Dazuo",
    "wof:placetype":"locality"
},
  "geometry": {"coordinates":[118.14599,26.66148],"type":"Point"}
}