{
  "type": "Feature",
  "properties": {
    "gn:admin1_code":"32.0",
    "gn:asciiname":"Danglong",
    "gn:country_code":"CN",
    "gn:dem":3932,
    "gn:feature_class":"P",
    "gn:feature_code":"PPL",
    "gn:name":"Danglong",
    "gn:population":0,
    "gn:timezone":"Asia/Shanghai",
    "iso:country":"CN",
    "name:zho_x_preferred":[
        "\u5f53\u9686"
    ],
    "wof:name":"Danglong",
    "wof:placetype":"locality"
},
  "geometry": {"coordinates":[99.21442999999999,31.5373],"type":"Point"}
}