{
  "type": "Feature",
  "properties": {
    "gn:admin1_code":"9",
    "gn:asciiname":"Liucun",
    "gn:country_code":"CN",
    "gn:dem":775,
    "gn:feature_class":"P",
    "gn:feature_code":"PPL",
    "gn:name":"Liucun",
    "gn:population":0,
    "gn:timezone":"Asia/Shanghai",
    "iso:country":"CN",
    "wof:name":"Liucun",
    "wof:placetype":"locality"
},
  "geometry": {"coordinates":[110.85056000000002,34.38889],"type":"Point"}
}