{
  "type": "Feature",
  "properties": {
    "gn:admin1_code":"5.0",
    "gn:asciiname":"Anjia Wopeng",
    "gn:country_code":"CN",
    "gn:dem":162,
    "gn:feature_class":"P",
    "gn:feature_code":"PPL",
    "gn:name":"Anjia Wopeng",
    "gn:population":0,
    "gn:timezone":"Asia/Shanghai",
    "iso:country":"CN",
    "name:zho_x_preferred":[
        "\u5b89\u5bb6\u7a9d\u68da"
    ],
    "wof:name":"Anjia Wopeng",
    "wof:placetype":"locality"
},
  "geometry": {"coordinates":[122.64252999999999,44.78404000000001],"type":"Point"}
}