{
  "type": "Feature",
  "properties": {
    "gn:admin1_code":"33.0",
    "gn:asciiname":"Taibai",
    "gn:country_code":"CN",
    "gn:dem":200,
    "gn:feature_class":"P",
    "gn:feature_code":"PPLA4",
    "gn:name":"Taibai",
    "gn:population":0,
    "gn:timezone":"Asia/Shanghai",
    "iso:country":"CN",
    "name:und_x_variant":[
        "Taibai Jiedao"
    ],
    "name:zho_x_preferred":[
        "\u592a\u767d"
    ],
    "name:zho_x_variant":[
        "\u592a\u767d\u8857\u9053"
    ],
    "wof:name":"Taibai",
    "wof:placetype":"locality"
},
  "geometry": {"coordinates":[108.35783000000001,30.82482000000001],"type":"Point"}
}