{
  "type": "Feature",
  "properties": {
    "gn:admin1_code":"9.0",
    "gn:asciiname":"Yangzhonglou",
    "gn:country_code":"CN",
    "gn:dem":44,
    "gn:feature_class":"P",
    "gn:feature_code":"PPL",
    "gn:name":"Yangzhonglou",
    "gn:population":0,
    "gn:timezone":"Asia/Shanghai",
    "iso:country":"CN",
    "name:zho_x_preferred":[
        "\u6768\u4e2d\u697c"
    ],
    "wof:name":"Yangzhonglou",
    "wof:placetype":"locality"
},
  "geometry": {"coordinates":[115.307,33.61476],"type":"Point"}
}