{
  "type": "Feature",
  "properties": {
    "gn:admin1_code":"04",
    "gn:asciiname":"Sangshubang",
    "gn:cc2":"CN",
    "gn:country_code":"CN",
    "gn:dem":5,
    "gn:feature_class":"P",
    "gn:feature_code":"PPL",
    "gn:name":"Sangshubang",
    "gn:population":0,
    "gn:timezone":"Asia/Shanghai",
    "iso:country":"CN",
    "name:und_x_variant":[
        "Shuang-shih-pang",
        "Sangshubang"
    ],
    "wof:name":"Sangshubang",
    "wof:placetype":"locality"
},
  "geometry": {"coordinates":[120.50583,31.40667],"type":"Point"}
}