{
  "type": "Feature",
  "properties": {
    "gn:admin1_code":"4.0",
    "gn:asciiname":"Xiyin",
    "gn:country_code":"CN",
    "gn:dem":6,
    "gn:feature_class":"P",
    "gn:feature_code":"PPL",
    "gn:name":"Xiyin",
    "gn:population":0,
    "gn:timezone":"Asia/Shanghai",
    "iso:country":"CN",
    "name:und_x_variant":[
        "\u897f\u5c39"
    ],
    "name:zho_x_preferred":[
        "\u897f\u5c39"
    ],
    "wof:name":"Xiyin",
    "wof:placetype":"locality"
},
  "geometry": {"coordinates":[120.2949,32.33743],"type":"Point"}
}