{
  "type": "Feature",
  "properties": {
    "gn:admin1_code":"13",
    "gn:asciiname":"Laojidu Jisala",
    "gn:country_code":"CN",
    "gn:dem":2789,
    "gn:feature_class":"P",
    "gn:feature_code":"PPL",
    "gn:name":"Laojidu Jisala",
    "gn:population":0,
    "gn:timezone":"Asia/Urumqi",
    "iso:country":"CN",
    "name:und_x_variant":[
        "\u8001\u5409\u90fd\u5409\u8428\u62c9"
    ],
    "wof:name":"Laojidu Jisala",
    "wof:placetype":"locality"
},
  "geometry": {"coordinates":[84.98846,42.91215],"type":"Point"}
}