{
  "type": "Feature",
  "properties": {
    "gn:admin1_code":"10",
    "gn:asciiname":"Qianjia Shawa",
    "gn:country_code":"CN",
    "gn:dem":825,
    "gn:feature_class":"P",
    "gn:feature_code":"PPL",
    "gn:name":"Qianjia Shawa",
    "gn:population":0,
    "gn:timezone":"Asia/Shanghai",
    "iso:country":"CN",
    "name:und_x_variant":[
        "Cheng-chia-sha-wa",
        "Qianjia Shawa"
    ],
    "name:zho_x_preferred":[
        "\u94b1\u5bb6\u6c99\u6d3c"
    ],
    "wof:name":"Qianjia Shawa",
    "wof:placetype":"locality"
},
  "geometry": {"coordinates":[114.63549999999999,40.19703],"type":"Point"}
}