{
  "type": "Feature",
  "properties": {
    "gn:admin1_code":"19.0",
    "gn:asciiname":"Yangshugou",
    "gn:country_code":"CN",
    "gn:dem":183,
    "gn:feature_class":"P",
    "gn:feature_code":"PPL",
    "gn:name":"Yangshugou",
    "gn:population":0,
    "gn:timezone":"Asia/Shanghai",
    "iso:country":"CN",
    "name:und_x_variant":[
        "\u6768\u6811\u6c9f"
    ],
    "wof:name":"Yangshugou",
    "wof:placetype":"locality"
},
  "geometry": {"coordinates":[123.23699999999999,40.9466],"type":"Point"}
}