{
  "type": "Feature",
  "properties": {
    "gn:admin1_code":"11.0",
    "gn:asciiname":"Xiaoxi",
    "gn:country_code":"CN",
    "gn:dem":395,
    "gn:feature_class":"P",
    "gn:feature_code":"PPL",
    "gn:name":"Xiaoxi",
    "gn:population":0,
    "gn:timezone":"Asia/Shanghai",
    "iso:country":"CN",
    "name:zho_x_preferred":[
        "Xiaoxi"
    ],
    "name:zho_x_variant":[
        "\u5c0f\u6eaa"
    ],
    "wof:name":"Xiaoxi",
    "wof:placetype":"locality"
},
  "geometry": {"coordinates":[114.17957,28.28664],"type":"Point"}
}