{
  "type": "Feature",
  "properties": {
    "gn:admin1_code":"32.0",
    "gn:asciiname":"Erlangba",
    "gn:country_code":"CN",
    "gn:dem":638,
    "gn:feature_class":"P",
    "gn:feature_code":"PPL",
    "gn:name":"Erlangba",
    "gn:population":0,
    "gn:timezone":"Asia/Shanghai",
    "iso:country":"CN",
    "name:zho_x_preferred":[
        "\u4e8c\u72fc\u575d"
    ],
    "wof:name":"Erlangba",
    "wof:placetype":"locality"
},
  "geometry": {"coordinates":[103.206,30.3804],"type":"Point"}
}