{
  "type": "Feature",
  "properties": {
    "gn:admin1_code":"14.0",
    "gn:asciiname":"Langda",
    "gn:country_code":"CN",
    "gn:dem":3883,
    "gn:feature_class":"P",
    "gn:feature_code":"PPL",
    "gn:name":"Langda",
    "gn:population":0,
    "gn:timezone":"Asia/Urumqi",
    "iso:country":"CN",
    "name:zho_x_preferred":[
        "\u6717\u8fbe"
    ],
    "wof:name":"Langda",
    "wof:placetype":"locality"
},
  "geometry": {"coordinates":[94.64147,31.5733],"type":"Point"}
}