{
  "type": "Feature",
  "properties": {
    "gn:admin1_code":"25",
    "gn:asciiname":"Liangshuiquanxi",
    "gn:country_code":"CN",
    "gn:dem":50,
    "gn:feature_class":"P",
    "gn:feature_code":"PPL",
    "gn:name":"Liangshuiquanxi",
    "gn:population":0,
    "gn:timezone":"Asia/Shanghai",
    "iso:country":"CN",
    "name:zho_x_preferred":[
        "\u4e24\u6c34\u6cc9\u897f"
    ],
    "wof:name":"Liangshuiquanxi",
    "wof:placetype":"locality"
},
  "geometry": {"coordinates":[116.988,35.1549],"type":"Point"}
}