{
  "type": "Feature",
  "properties": {
    "gn:admin1_code":"20.0",
    "gn:asciiname":"Wusanwucun",
    "gn:country_code":"CN",
    "gn:dem":650,
    "gn:feature_class":"P",
    "gn:feature_code":"PPL",
    "gn:name":"Wusanwucun",
    "gn:population":0,
    "gn:timezone":"Asia/Shanghai",
    "iso:country":"CN",
    "name:zho_x_preferred":[
        "\u4e94\u4e09\u4e94\u6751"
    ],
    "wof:name":"Wusanwucun",
    "wof:placetype":"locality"
},
  "geometry": {"coordinates":[121.93921,48.72973],"type":"Point"}
}