{
  "type": "Feature",
  "properties": {
    "gn:admin1_code":"32.0",
    "gn:asciiname":"Lengkong",
    "gn:country_code":"CN",
    "gn:dem":3816,
    "gn:feature_class":"P",
    "gn:feature_code":"PPL",
    "gn:name":"Lengkong",
    "gn:population":0,
    "gn:timezone":"Asia/Shanghai",
    "iso:country":"CN",
    "name:zho_x_preferred":[
        "\u51b7\u7a7a"
    ],
    "wof:name":"Lengkong",
    "wof:placetype":"locality"
},
  "geometry": {"coordinates":[99.03729,31.54119],"type":"Point"}
}