{
  "type": "Feature",
  "properties": {
    "gn:admin1_code":"8.0",
    "gn:asciiname":"Liujinchangtun",
    "gn:country_code":"CN",
    "gn:dem":250,
    "gn:feature_class":"P",
    "gn:feature_code":"PPL",
    "gn:name":"Liujinchangtun",
    "gn:population":0,
    "gn:timezone":"Asia/Shanghai",
    "iso:country":"CN",
    "name:zho_x_preferred":[
        "\u5218\u91d1\u573a\u5c6f"
    ],
    "wof:name":"Liujinchangtun",
    "wof:placetype":"locality"
},
  "geometry": {"coordinates":[127.42713999999999,45.60963],"type":"Point"}
}