{
  "type": "Feature",
  "properties": {
    "gn:admin1_code":"16.0",
    "gn:asciiname":"Dacheng",
    "gn:country_code":"CN",
    "gn:dem":110,
    "gn:feature_class":"P",
    "gn:feature_code":"PPL",
    "gn:name":"Dacheng",
    "gn:population":0,
    "gn:timezone":"Asia/Shanghai",
    "iso:country":"CN",
    "name:ceb_x_preferred":[
        "Dacheng"
    ],
    "name:deu_x_preferred":[
        "Dacheng"
    ],
    "name:fra_x_preferred":[
        "Dacheng"
    ],
    "name:zho_x_preferred":[
        "\u5927\u6210"
    ],
    "wof:name":"Dacheng",
    "wof:placetype":"locality"
},
  "geometry": {"coordinates":[106.952,23.6675],"type":"Point"}
}