{
  "type": "Feature",
  "properties": {
    "gn:admin1_code":"32.0",
    "gn:asciiname":"Huangcuncun",
    "gn:country_code":"CN",
    "gn:dem":490,
    "gn:feature_class":"P",
    "gn:feature_code":"PPL",
    "gn:name":"Huangcuncun",
    "gn:population":0,
    "gn:timezone":"Asia/Shanghai",
    "iso:country":"CN",
    "name:zho_x_preferred":[
        "\u9ec4\u6751\u6751"
    ],
    "wof:name":"Huangcuncun",
    "wof:placetype":"locality"
},
  "geometry": {"coordinates":[103.395,29.9584],"type":"Point"}
}