{
  "type": "Feature",
  "properties": {
    "gn:admin1_code":"29",
    "gn:asciiname":"Nanzhuping",
    "gn:country_code":"CN",
    "gn:dem":1322,
    "gn:feature_class":"P",
    "gn:feature_code":"PPL",
    "gn:name":"Nanzhuping",
    "gn:population":0,
    "gn:timezone":"Asia/Shanghai",
    "iso:country":"CN",
    "name:zho_x_preferred":[
        "\u5357\u7af9\u5e73"
    ],
    "wof:name":"Nanzhuping",
    "wof:placetype":"locality"
},
  "geometry": {"coordinates":[105.498,23.4724],"type":"Point"}
}