{
  "type": "Feature",
  "properties": {
    "gn:admin1_code":"32.0",
    "gn:asciiname":"Antanggou",
    "gn:country_code":"CN",
    "gn:dem":561,
    "gn:feature_class":"P",
    "gn:feature_code":"PPL",
    "gn:name":"Antanggou",
    "gn:population":0,
    "gn:timezone":"Asia/Shanghai",
    "iso:country":"CN",
    "name:zho_x_preferred":[
        "\u5b89\u5858\u6c9f"
    ],
    "wof:name":"Antanggou",
    "wof:placetype":"locality"
},
  "geometry": {"coordinates":[104.45918,31.45608],"type":"Point"}
}