{
  "type": "Feature",
  "properties": {
    "gn:admin1_code":"11.0",
    "gn:asciiname":"Yaojia Wuchang",
    "gn:country_code":"CN",
    "gn:dem":40,
    "gn:feature_class":"P",
    "gn:feature_code":"PPL",
    "gn:name":"Yaojia Wuchang",
    "gn:population":0,
    "gn:timezone":"Asia/Shanghai",
    "iso:country":"CN",
    "name:zho_x_preferred":[
        "\u59da\u5bb6\u5c4b\u573a"
    ],
    "wof:name":"Yaojia Wuchang",
    "wof:placetype":"locality"
},
  "geometry": {"coordinates":[112.74327,28.31638],"type":"Point"}
}