{
  "type": "Feature",
  "properties": {
    "gn:admin1_code":"16.0",
    "gn:asciiname":"Maxia",
    "gn:country_code":"CN",
    "gn:dem":51,
    "gn:feature_class":"P",
    "gn:feature_code":"PPL",
    "gn:name":"Maxia",
    "gn:population":0,
    "gn:timezone":"Asia/Shanghai",
    "iso:country":"CN",
    "name:por_x_preferred":[
        "Maxia"
    ],
    "name:vie_x_preferred":[
        "Maxia"
    ],
    "name:zho_x_preferred":[
        "\u9a6c\u5ce1"
    ],
    "wof:name":"Maxia",
    "wof:placetype":"locality"
},
  "geometry": {"coordinates":[111.325,23.3463],"type":"Point"}
}