{
  "type": "Feature",
  "properties": {
    "gn:admin1_code":"18.0",
    "gn:asciiname":"Zhigou",
    "gn:country_code":"CN",
    "gn:dem":1516,
    "gn:feature_class":"P",
    "gn:feature_code":"PPL",
    "gn:name":"Zhigou",
    "gn:population":0,
    "gn:timezone":"Asia/Shanghai",
    "iso:country":"CN",
    "wof:name":"Zhigou",
    "wof:placetype":"locality"
},
  "geometry": {"coordinates":[105.16667,26.89167],"type":"Point"}
}