{
  "type": "Feature",
  "properties": {
    "gn:admin1_code":"14.0",
    "gn:asciiname":"Shading",
    "gn:country_code":"CN",
    "gn:dem":3618,
    "gn:feature_class":"P",
    "gn:feature_code":"PPLA4",
    "gn:name":"Shading",
    "gn:population":0,
    "gn:timezone":"Asia/Urumqi",
    "iso:country":"CN",
    "name:bod_x_preferred":[
        "Sad\u00eang"
    ],
    "name:und_x_variant":[
        "Sating",
        "Sha-ting",
        "Sha-ting-tsung",
        "Sad\u00eang",
        "Shading Xiang"
    ],
    "name:zho_x_preferred":[
        "Shading"
    ],
    "name:zho_x_variant":[
        "\u6c99\u4e01",
        "\u6c99\u4e01\u4e61"
    ],
    "wof:name":"Shading",
    "wof:placetype":"locality"
},
  "geometry": {"coordinates":[94.49558,31.25887],"type":"Point"}
}