{
  "type": "Feature",
  "properties": {
    "gn:admin1_code":"18",
    "gn:asciiname":"Houqibu",
    "gn:country_code":"CN",
    "gn:dem":1199,
    "gn:feature_class":"P",
    "gn:feature_code":"PPL",
    "gn:name":"Houqibu",
    "gn:population":0,
    "gn:timezone":"Asia/Shanghai",
    "iso:country":"CN",
    "name:zho_x_preferred":[
        "\u7334\u5176\u5821"
    ],
    "wof:name":"Houqibu",
    "wof:placetype":"locality"
},
  "geometry": {"coordinates":[105.754,26.0152],"type":"Point"}
}