{
  "type": "Feature",
  "properties": {
    "gn:admin1_code":"02",
    "gn:asciiname":"Qian'ao",
    "gn:country_code":"CN",
    "gn:dem":7,
    "gn:feature_class":"P",
    "gn:feature_code":"PPL",
    "gn:name":"Qian\u2019ao",
    "gn:population":0,
    "gn:timezone":"Asia/Shanghai",
    "iso:country":"CN",
    "name:und_x_variant":[
        "Ch\u2019ien-an",
        "Qian\u2019ao",
        "\u524d\u5c99"
    ],
    "wof:name":"Qian'ao",
    "wof:placetype":"locality"
},
  "geometry": {"coordinates":[122.16591,29.80176],"type":"Point"}
}