{
  "type": "Feature",
  "properties": {
    "gn:admin1_code":"5.0",
    "gn:asciiname":"Guanmen Zuizicun",
    "gn:country_code":"CN",
    "gn:dem":72,
    "gn:feature_class":"P",
    "gn:feature_code":"PPL",
    "gn:name":"Guanmen Zuizicun",
    "gn:population":0,
    "gn:timezone":"Asia/Shanghai",
    "iso:country":"CN",
    "name:zho_x_preferred":[
        "\u5173\u95e8\u5480\u5b50\u6751"
    ],
    "wof:name":"Guanmen Zuizicun",
    "wof:placetype":"locality"
},
  "geometry": {"coordinates":[130.31558000000001,42.93107],"type":"Point"}
}