{
  "type": "Feature",
  "properties": {
    "gn:admin1_code":"11.0",
    "gn:asciiname":"Shishijiang",
    "gn:country_code":"CN",
    "gn:dem":66,
    "gn:feature_class":"P",
    "gn:feature_code":"PPL",
    "gn:name":"Shishijiang",
    "gn:population":0,
    "gn:timezone":"Asia/Shanghai",
    "iso:country":"CN",
    "name:zho_x_preferred":[
        "\u77f3\u72ee\u6c5f"
    ],
    "wof:name":"Shishijiang",
    "wof:placetype":"locality"
},
  "geometry": {"coordinates":[112.41603000000001,27.71465],"type":"Point"}
}