{
  "type": "Feature",
  "properties": {
    "gn:admin1_code":"9.0",
    "gn:asciiname":"Dawazhuanggou",
    "gn:country_code":"CN",
    "gn:dem":528,
    "gn:feature_class":"P",
    "gn:feature_code":"PPL",
    "gn:name":"Dawazhuanggou",
    "gn:population":0,
    "gn:timezone":"Asia/Shanghai",
    "iso:country":"CN",
    "name:zho_x_preferred":[
        "\u5927\u74e6\u5e84\u6c9f"
    ],
    "wof:name":"Dawazhuanggou",
    "wof:placetype":"locality"
},
  "geometry": {"coordinates":[111.45099,33.51705],"type":"Point"}
}