{
  "type": "Feature",
  "properties": {
    "gn:admin1_code":"12.0",
    "gn:asciiname":"Qinjiawan",
    "gn:country_code":"CN",
    "gn:dem":304,
    "gn:feature_class":"P",
    "gn:feature_code":"PPL",
    "gn:name":"Qinjiawan",
    "gn:population":0,
    "gn:timezone":"Asia/Shanghai",
    "iso:country":"CN",
    "name:zho_x_preferred":[
        "\u79e6\u5bb6\u6e7e"
    ],
    "wof:name":"Qinjiawan",
    "wof:placetype":"locality"
},
  "geometry": {"coordinates":[110.80262,32.62297],"type":"Point"}
}