{
  "type": "Feature",
  "properties": {
    "gn:admin1_code":"16.0",
    "gn:asciiname":"Shangcaokou",
    "gn:country_code":"CN",
    "gn:dem":437,
    "gn:feature_class":"P",
    "gn:feature_code":"PPL",
    "gn:name":"Shangcaokou",
    "gn:population":0,
    "gn:timezone":"Asia/Shanghai",
    "iso:country":"CN",
    "name:zho_x_preferred":[
        "\u4e0a\u66f9\u53e3"
    ],
    "wof:name":"Shangcaokou",
    "wof:placetype":"locality"
},
  "geometry": {"coordinates":[109.28100000000001,25.3783],"type":"Point"}
}