{
  "type": "Feature",
  "properties": {
    "gn:admin1_code":"32.0",
    "gn:asciiname":"Niubishan",
    "gn:country_code":"CN",
    "gn:dem":610,
    "gn:feature_class":"P",
    "gn:feature_code":"PPL",
    "gn:name":"Niubishan",
    "gn:population":0,
    "gn:timezone":"Asia/Shanghai",
    "iso:country":"CN",
    "name:zho_x_preferred":[
        "\u725b\u9f3b\u5c71"
    ],
    "wof:name":"Niubishan",
    "wof:placetype":"locality"
},
  "geometry": {"coordinates":[106.77,31.9002],"type":"Point"}
}