{
  "type": "Feature",
  "properties": {
    "gn:admin1_code":"4.0",
    "gn:asciiname":"Zhangjia Laozhaiji",
    "gn:country_code":"CN",
    "gn:dem":5,
    "gn:feature_class":"P",
    "gn:feature_code":"PPL",
    "gn:name":"Zhangjia Laozhaiji",
    "gn:population":0,
    "gn:timezone":"Asia/Shanghai",
    "iso:country":"CN",
    "name:zho_x_preferred":[
        "\u666f\u5df7"
    ],
    "wof:name":"Zhangjia Laozhaiji",
    "wof:placetype":"locality"
},
  "geometry": {"coordinates":[120.83941000000002,31.71416],"type":"Point"}
}