{
  "type": "Feature",
  "properties": {
    "gn:admin1_code":"33.0",
    "gn:asciiname":"Daya",
    "gn:country_code":"CN",
    "gn:dem":674,
    "gn:feature_class":"P",
    "gn:feature_code":"PPLA4",
    "gn:name":"Daya",
    "gn:population":0,
    "gn:timezone":"Asia/Shanghai",
    "iso:country":"CN",
    "name:ceb_x_preferred":[
        "Daya"
    ],
    "name:heb_x_preferred":[
        "\u05d3\u05d9\u05d4"
    ],
    "name:pol_x_preferred":[
        "Daya"
    ],
    "name:swe_x_preferred":[
        "Daya"
    ],
    "name:und_x_variant":[
        "Daya Xiang",
        "Taoziwan"
    ],
    "name:vie_x_preferred":[
        "Daya"
    ],
    "name:zho_x_preferred":[
        "\u5927\u57ad"
    ],
    "name:zho_x_variant":[
        "\u5927\u57ad\u4e61",
        "\u6843\u5b50\u6e7e"
    ],
    "wof:name":"Daya",
    "wof:placetype":"locality"
},
  "geometry": {"coordinates":[107.88601,29.02564000000001],"type":"Point"}
}