{
  "type": "Feature",
  "properties": {
    "gn:admin1_code":"20.0",
    "gn:asciiname":"Houyaozi",
    "gn:country_code":"CN",
    "gn:dem":1134,
    "gn:feature_class":"P",
    "gn:feature_code":"PPL",
    "gn:name":"Houyaozi",
    "gn:population":0,
    "gn:timezone":"Asia/Shanghai",
    "iso:country":"CN",
    "name:und_x_variant":[
        "\u540e\u7a91\u5b50"
    ],
    "wof:name":"Houyaozi",
    "wof:placetype":"locality"
},
  "geometry": {"coordinates":[111.62877,40.07538],"type":"Point"}
}