{
  "type": "Feature",
  "properties": {
    "gn:admin1_code":"11.0",
    "gn:asciiname":"Xianjitang",
    "gn:country_code":"CN",
    "gn:dem":1074,
    "gn:feature_class":"P",
    "gn:feature_code":"PPL",
    "gn:name":"Xianjitang",
    "gn:population":0,
    "gn:timezone":"Asia/Shanghai",
    "iso:country":"CN",
    "name:zho_x_preferred":[
        "\u4ed9\u9e21\u5858"
    ],
    "wof:name":"Xianjitang",
    "wof:placetype":"locality"
},
  "geometry": {"coordinates":[113.63889,26.05873],"type":"Point"}
}