{
  "type": "Feature",
  "properties": {
    "gn:admin1_code":"3.0",
    "gn:asciiname":"Lishenkeng",
    "gn:country_code":"CN",
    "gn:dem":514,
    "gn:feature_class":"P",
    "gn:feature_code":"PPL",
    "gn:name":"Lishenkeng",
    "gn:population":0,
    "gn:timezone":"Asia/Shanghai",
    "iso:country":"CN",
    "name:zho_x_preferred":[
        "\u91cc\u6df1\u5751"
    ],
    "wof:name":"Lishenkeng",
    "wof:placetype":"locality"
},
  "geometry": {"coordinates":[118.05209000000001,29.29298],"type":"Point"}
}