{
  "type": "Feature",
  "properties": {
    "gn:admin1_code":"6.0",
    "gn:asciiname":"Sangdang",
    "gn:country_code":"CN",
    "gn:dem":2886,
    "gn:feature_class":"P",
    "gn:feature_code":"PPL",
    "gn:name":"Sangdang",
    "gn:population":0,
    "gn:timezone":"Asia/Shanghai",
    "iso:country":"CN",
    "name:zho_x_preferred":[
        "\u6851\u5f53"
    ],
    "wof:name":"Sangdang",
    "wof:placetype":"locality"
},
  "geometry": {"coordinates":[99.99791,35.52814],"type":"Point"}
}