{
  "type": "Feature",
  "properties": {
    "gn:admin1_code":"29.0",
    "gn:asciiname":"Sanguanzhai",
    "gn:country_code":"CN",
    "gn:dem":1721,
    "gn:feature_class":"P",
    "gn:feature_code":"PPLA4",
    "gn:name":"Sanguanzhai",
    "gn:population":0,
    "gn:timezone":"Asia/Shanghai",
    "iso:country":"CN",
    "name:und_x_variant":[
        "\u4e09\u5b98\u5be8",
        "Xindian",
        "Xindian Xiang",
        "\u65b0\u5e97",
        "\u65b0\u5e97\u4e61"
    ],
    "wof:name":"Sanguanzhai",
    "wof:placetype":"locality"
},
  "geometry": {"coordinates":[103.25657,27.10766],"type":"Point"}
}