{
  "type": "Feature",
  "properties": {
    "gn:admin1_code":"24.0",
    "gn:asciiname":"Yupingzi",
    "gn:country_code":"CN",
    "gn:dem":1584,
    "gn:feature_class":"P",
    "gn:feature_code":"PPL",
    "gn:name":"Yupingzi",
    "gn:population":0,
    "gn:timezone":"Asia/Shanghai",
    "iso:country":"CN",
    "name:zho_x_preferred":[
        "\u4e8e\u576a\u5b50"
    ],
    "wof:name":"Yupingzi",
    "wof:placetype":"locality"
},
  "geometry": {"coordinates":[112.21572999999999,38.44982],"type":"Point"}
}