{
  "type": "Feature",
  "properties": {
    "gn:admin1_code":"32.0",
    "gn:asciiname":"Lajue'amo",
    "gn:country_code":"CN",
    "gn:dem":2644,
    "gn:feature_class":"P",
    "gn:feature_code":"PPL",
    "gn:name":"Lajue\u2019amo",
    "gn:population":0,
    "gn:timezone":"Asia/Shanghai",
    "iso:country":"CN",
    "name:und_x_variant":[
        "Lajue\u2019amo"
    ],
    "name:zho_x_preferred":[
        "\u62c9\u89c9\u963f\u83ab"
    ],
    "wof:name":"Lajue'amo",
    "wof:placetype":"locality"
},
  "geometry": {"coordinates":[102.79600000000001,28.6055],"type":"Point"}
}