{
  "type": "Feature",
  "properties": {
    "gn:admin1_code":"30.0",
    "gn:asciiname":"Daoyong",
    "gn:country_code":"CN",
    "gn:dem":72,
    "gn:feature_class":"P",
    "gn:feature_code":"PPL",
    "gn:name":"Daoyong",
    "gn:population":0,
    "gn:timezone":"Asia/Urumqi",
    "iso:country":"CN",
    "name:zho_x_preferred":[
        "\u5230\u6c38"
    ],
    "wof:name":"Daoyong",
    "wof:placetype":"locality"
},
  "geometry": {"coordinates":[110.92297000000001,22.26437],"type":"Point"}
}