{
  "type": "Feature",
  "properties": {
    "gn:admin1_code":"12.0",
    "gn:asciiname":"Tuzhaizi",
    "gn:country_code":"CN",
    "gn:dem":541,
    "gn:feature_class":"P",
    "gn:feature_code":"PPL",
    "gn:name":"Tuzhaizi",
    "gn:population":0,
    "gn:timezone":"Asia/Shanghai",
    "iso:country":"CN",
    "name:zho_x_preferred":[
        "\u571f\u5be8\u5b50"
    ],
    "wof:name":"Tuzhaizi",
    "wof:placetype":"locality"
},
  "geometry": {"coordinates":[109.83396999999999,32.37063],"type":"Point"}
}