{
  "type": "Feature",
  "properties": {
    "gn:admin1_code":"1.0",
    "gn:asciiname":"Xiashandou",
    "gn:country_code":"CN",
    "gn:dem":60,
    "gn:feature_class":"P",
    "gn:feature_code":"PPL",
    "gn:name":"Xiashandou",
    "gn:population":0,
    "gn:timezone":"Asia/Shanghai",
    "iso:country":"CN",
    "name:zho_x_preferred":[
        "Xiashandou"
    ],
    "name:zho_x_variant":[
        "\u4e0b\u5c71\u6597"
    ],
    "wof:name":"Xiashandou",
    "wof:placetype":"locality"
},
  "geometry": {"coordinates":[119.27106999999999,30.90801],"type":"Point"}
}