{
  "type": "Feature",
  "properties": {
    "gn:admin1_code":"29.0",
    "gn:asciiname":"Mukewan",
    "gn:country_code":"CN",
    "gn:dem":1921,
    "gn:feature_class":"P",
    "gn:feature_code":"PPL",
    "gn:name":"Mukewan",
    "gn:population":0,
    "gn:timezone":"Asia/Shanghai",
    "iso:country":"CN",
    "name:zho_x_preferred":[
        "\u6728\u53ef\u6e7e"
    ],
    "wof:name":"Mukewan",
    "wof:placetype":"locality"
},
  "geometry": {"coordinates":[99.58540000000001,27.4648],"type":"Point"}
}