{
  "type": "Feature",
  "properties": {
    "gn:admin1_code":"1.0",
    "gn:asciiname":"Wanglihucun",
    "gn:country_code":"CN",
    "gn:dem":21,
    "gn:feature_class":"P",
    "gn:feature_code":"PPL",
    "gn:name":"Wanglihucun",
    "gn:population":0,
    "gn:timezone":"Asia/Shanghai",
    "iso:country":"CN",
    "name:und_x_variant":[
        "Wanglihu"
    ],
    "name:zho_x_preferred":[
        "\u738b\u674e\u6e56\u6751"
    ],
    "wof:name":"Wanglihucun",
    "wof:placetype":"locality"
},
  "geometry": {"coordinates":[117.54089999999999,33.27607],"type":"Point"}
}