{
  "type": "Feature",
  "properties": {
    "gn:admin1_code":"11",
    "gn:asciiname":"Dapingxiang",
    "gn:cc2":"CN",
    "gn:country_code":"CN",
    "gn:dem":105,
    "gn:feature_class":"P",
    "gn:feature_code":"PPL",
    "gn:name":"Dapingxiang",
    "gn:population":0,
    "gn:timezone":"Asia/Shanghai",
    "iso:country":"CN",
    "name:und_x_variant":[
        "Zhanggongqiao",
        "Dapingxiang"
    ],
    "wof:name":"Dapingxiang",
    "wof:placetype":"locality"
},
  "geometry": {"coordinates":[112.41806,27.90167000000001],"type":"Point"}
}