{
  "type": "Feature",
  "properties": {
    "gn:admin1_code":"24.0",
    "gn:asciiname":"Nanfenggou",
    "gn:country_code":"CN",
    "gn:dem":899,
    "gn:feature_class":"P",
    "gn:feature_code":"PPL",
    "gn:name":"Nanfenggou",
    "gn:population":0,
    "gn:timezone":"Asia/Shanghai",
    "iso:country":"CN",
    "name:zho_x_preferred":[
        "\u5357\u4e30\u6c9f"
    ],
    "wof:name":"Nanfenggou",
    "wof:placetype":"locality"
},
  "geometry": {"coordinates":[112.99035000000001,36.47484],"type":"Point"}
}