{
  "type": "Feature",
  "properties": {
    "gn:admin1_code":"04",
    "gn:asciiname":"Da'anqiao",
    "gn:country_code":"CN",
    "gn:dem":5,
    "gn:feature_class":"P",
    "gn:feature_code":"PPL",
    "gn:name":"Da\u2019anqiao",
    "gn:population":0,
    "gn:timezone":"Asia/Shanghai",
    "iso:country":"CN",
    "name:und_x_variant":[
        "Tung-an-ch\u2019iao-chen",
        "Ta-an-ch\u2019iao",
        "Da\u2019anqiao"
    ],
    "wof:name":"Da'anqiao",
    "wof:placetype":"locality"
},
  "geometry": {"coordinates":[121.37806,32.0675],"type":"Point"}
}