{
  "type": "Feature",
  "properties": {
    "gn:admin1_code":"21.0",
    "gn:asciiname":"Malutan",
    "gn:country_code":"CN",
    "gn:dem":1227,
    "gn:feature_class":"P",
    "gn:feature_code":"PPL",
    "gn:name":"Malutan",
    "gn:population":0,
    "gn:timezone":"Asia/Shanghai",
    "iso:country":"CN",
    "name:zho_x_preferred":[
        "\u9a6c\u8def\u6ee9"
    ],
    "wof:name":"Malutan",
    "wof:placetype":"locality"
},
  "geometry": {"coordinates":[105.16800000000001,37.4703],"type":"Point"}
}