{
  "type": "Feature",
  "properties": {
    "gn:admin1_code":"12.0",
    "gn:asciiname":"Puwuzui",
    "gn:country_code":"CN",
    "gn:dem":59,
    "gn:feature_class":"P",
    "gn:feature_code":"PPL",
    "gn:name":"Puwuzui",
    "gn:population":0,
    "gn:timezone":"Asia/Shanghai",
    "iso:country":"CN",
    "name:zho_x_preferred":[
        "Puwuzui"
    ],
    "name:zho_x_variant":[
        "\u94fa\u5c4b\u5480"
    ],
    "wof:name":"Puwuzui",
    "wof:placetype":"locality"
},
  "geometry": {"coordinates":[115.32029,30.86684],"type":"Point"}
}