{
  "type": "Feature",
  "properties": {
    "gn:admin1_code":"29.0",
    "gn:asciiname":"Baijiazhai",
    "gn:country_code":"CN",
    "gn:dem":2052,
    "gn:feature_class":"P",
    "gn:feature_code":"PPL",
    "gn:name":"Baijiazhai",
    "gn:population":0,
    "gn:timezone":"Asia/Shanghai",
    "iso:country":"CN",
    "name:zho_x_preferred":[
        "\u767d\u5bb6\u5be8"
    ],
    "wof:name":"Baijiazhai",
    "wof:placetype":"locality"
},
  "geometry": {"coordinates":[100.188,23.7902],"type":"Point"}
}