{
  "type": "Feature",
  "properties": {
    "gn:admin1_code":"15.0",
    "gn:asciiname":"Nongmin",
    "gn:country_code":"CN",
    "gn:dem":1229,
    "gn:feature_class":"P",
    "gn:feature_code":"PPL",
    "gn:name":"Nongmin",
    "gn:population":0,
    "gn:timezone":"Asia/Shanghai",
    "iso:country":"CN",
    "name:zho_x_preferred":[
        "\u519c\u6c11"
    ],
    "wof:name":"Nongmin",
    "wof:placetype":"locality"
},
  "geometry": {"coordinates":[105.649,34.8506],"type":"Point"}
}