{
  "type": "Feature",
  "properties": {
    "gn:admin1_code":"26",
    "gn:asciiname":"Qingshuihe",
    "gn:cc2":"CN",
    "gn:country_code":"CN",
    "gn:dem":1279,
    "gn:feature_class":"P",
    "gn:feature_code":"PPL",
    "gn:name":"Qingshuihe",
    "gn:population":0,
    "gn:timezone":"Asia/Shanghai",
    "iso:country":"CN",
    "name:und_x_variant":[
        "Ch\u2019ing-shui-ho",
        "Qingshui",
        "Ch\u2019ing-shui",
        "Qingshuihe"
    ],
    "wof:name":"Qingshuihe",
    "wof:placetype":"locality"
},
  "geometry": {"coordinates":[107.74139,32.63111],"type":"Point"}
}