{
  "type": "Feature",
  "properties": {
    "gn:admin1_code":"32.0",
    "gn:asciiname":"Dachaiwan",
    "gn:country_code":"CN",
    "gn:dem":340,
    "gn:feature_class":"P",
    "gn:feature_code":"PPL",
    "gn:name":"Dachaiwan",
    "gn:population":0,
    "gn:timezone":"Asia/Shanghai",
    "iso:country":"CN",
    "name:zho_x_preferred":[
        "\u6253\u67f4\u6e7e"
    ],
    "wof:name":"Dachaiwan",
    "wof:placetype":"locality"
},
  "geometry": {"coordinates":[104.703,29.1161],"type":"Point"}
}