{
  "type": "Feature",
  "properties": {
    "gn:admin1_code":"29.0",
    "gn:asciiname":"Changjiacun",
    "gn:country_code":"CN",
    "gn:dem":1835,
    "gn:feature_class":"P",
    "gn:feature_code":"PPL",
    "gn:name":"Changjiacun",
    "gn:population":0,
    "gn:timezone":"Asia/Shanghai",
    "iso:country":"CN",
    "name:zho_x_preferred":[
        "\u5e38\u5bb6\u6751"
    ],
    "wof:name":"Changjiacun",
    "wof:placetype":"locality"
},
  "geometry": {"coordinates":[103.682,24.9921],"type":"Point"}
}