{
  "type": "Feature",
  "properties": {
    "gn:admin1_code":"4.0",
    "gn:asciiname":"Huangnigoucun",
    "gn:country_code":"CN",
    "gn:dem":18,
    "gn:feature_class":"P",
    "gn:feature_code":"PPL",
    "gn:name":"Huangnigoucun",
    "gn:population":0,
    "gn:timezone":"Asia/Shanghai",
    "iso:country":"CN",
    "name:zho_x_preferred":[
        "\u9ec4\u6ce5\u6c9f\u6751"
    ],
    "wof:name":"Huangnigoucun",
    "wof:placetype":"locality"
},
  "geometry": {"coordinates":[118.87872,34.83191],"type":"Point"}
}