{
  "type": "Feature",
  "properties": {
    "gn:admin1_code":"29",
    "gn:asciiname":"Mabaling",
    "gn:country_code":"CN",
    "gn:dem":1437,
    "gn:feature_class":"P",
    "gn:feature_code":"PPL",
    "gn:name":"Mabaling",
    "gn:population":0,
    "gn:timezone":"Asia/Shanghai",
    "iso:country":"CN",
    "name:zho_x_preferred":[
        "\u9a6c\u6252\u5cad"
    ],
    "wof:name":"Mabaling",
    "wof:placetype":"locality"
},
  "geometry": {"coordinates":[102.479,23.8184],"type":"Point"}
}