{
  "type": "Feature",
  "properties": {
    "gn:admin1_code":"3.0",
    "gn:asciiname":"Wanzai",
    "gn:country_code":"CN",
    "gn:dem":370,
    "gn:feature_class":"P",
    "gn:feature_code":"PPL",
    "gn:name":"Wanzai",
    "gn:population":0,
    "gn:timezone":"Asia/Shanghai",
    "iso:country":"CN",
    "name:und_x_variant":[
        "\u6e7e\u4ed4"
    ],
    "wof:name":"Wanzai",
    "wof:placetype":"locality"
},
  "geometry": {"coordinates":[114.79254,24.66881],"type":"Point"}
}