{
  "type": "Feature",
  "properties": {
    "gn:admin1_code":"11.0",
    "gn:asciiname":"Pengjiawan",
    "gn:country_code":"CN",
    "gn:dem":91,
    "gn:feature_class":"P",
    "gn:feature_code":"PPL",
    "gn:name":"Pengjiawan",
    "gn:population":0,
    "gn:timezone":"Asia/Shanghai",
    "iso:country":"CN",
    "name:zho_x_preferred":[
        "\u5f6d\u5bb6\u6e7e"
    ],
    "wof:name":"Pengjiawan",
    "wof:placetype":"locality"
},
  "geometry": {"coordinates":[112.77106000000001,27.44362000000001],"type":"Point"}
}