{
  "type": "Feature",
  "properties": {
    "gn:admin1_code":"30.0",
    "gn:asciiname":"Lixicun",
    "gn:country_code":"CN",
    "gn:dem":5,
    "gn:feature_class":"P",
    "gn:feature_code":"PPL",
    "gn:name":"Lixicun",
    "gn:population":0,
    "gn:timezone":"Asia/Shanghai",
    "iso:country":"CN",
    "name:zho_x_preferred":[
        "\u701d\u897f\u6751"
    ],
    "wof:name":"Lixicun",
    "wof:placetype":"locality"
},
  "geometry": {"coordinates":[113.10585,23.12443],"type":"Point"}
}