{
  "type": "Feature",
  "properties": {
    "gn:admin1_code":"4.0",
    "gn:asciiname":"Xuduncun",
    "gn:country_code":"CN",
    "gn:dem":15,
    "gn:feature_class":"P",
    "gn:feature_code":"PPL",
    "gn:name":"Xuduncun",
    "gn:population":0,
    "gn:timezone":"Asia/Shanghai",
    "iso:country":"CN",
    "name:zho_x_preferred":[
        "\u5f90\u58a9\u6751"
    ],
    "wof:name":"Xuduncun",
    "wof:placetype":"locality"
},
  "geometry": {"coordinates":[118.45911,33.67529],"type":"Point"}
}