{
  "type": "Feature",
  "properties": {
    "gn:admin1_code":"1.0",
    "gn:asciiname":"Sanzengcun",
    "gn:country_code":"CN",
    "gn:dem":29,
    "gn:feature_class":"P",
    "gn:feature_code":"PPL",
    "gn:name":"Sanzengcun",
    "gn:population":0,
    "gn:timezone":"Asia/Shanghai",
    "iso:country":"CN",
    "name:zho_x_preferred":[
        "\u4e09\u589e\u6751"
    ],
    "wof:name":"Sanzengcun",
    "wof:placetype":"locality"
},
  "geometry": {"coordinates":[117.87427,30.60062000000001],"type":"Point"}
}