{
  "type": "Feature",
  "properties": {
    "gn:admin1_code":"12.0",
    "gn:asciiname":"Hejiamalu",
    "gn:country_code":"CN",
    "gn:dem":45,
    "gn:feature_class":"P",
    "gn:feature_code":"PPL",
    "gn:name":"Hejiamalu",
    "gn:population":0,
    "gn:timezone":"Asia/Shanghai",
    "iso:country":"CN",
    "name:zho_x_preferred":[
        "\u4f55\u5bb6\u9a6c\u8def"
    ],
    "wof:name":"Hejiamalu",
    "wof:placetype":"locality"
},
  "geometry": {"coordinates":[112.55516,30.98742],"type":"Point"}
}