{
  "type": "Feature",
  "properties": {
    "gn:admin1_code":"11.0",
    "gn:asciiname":"Shaluotang",
    "gn:country_code":"CN",
    "gn:dem":301,
    "gn:feature_class":"P",
    "gn:feature_code":"PPL",
    "gn:name":"Shaluotang",
    "gn:population":0,
    "gn:timezone":"Asia/Shanghai",
    "iso:country":"CN",
    "name:zho_x_preferred":[
        "\u6c99\u7f57\u5858"
    ],
    "wof:name":"Shaluotang",
    "wof:placetype":"locality"
},
  "geometry": {"coordinates":[111.66625999999999,27.36925],"type":"Point"}
}