{
  "type": "Feature",
  "properties": {
    "gn:admin1_code":"25.0",
    "gn:asciiname":"Nanshadaocun",
    "gn:country_code":"CN",
    "gn:dem":20,
    "gn:feature_class":"P",
    "gn:feature_code":"PPL",
    "gn:name":"Nanshadaocun",
    "gn:population":0,
    "gn:timezone":"Asia/Shanghai",
    "iso:country":"CN",
    "name:zho_x_preferred":[
        "\u5357\u6c99\u5c9b\u6751"
    ],
    "wof:name":"Nanshadaocun",
    "wof:placetype":"locality"
},
  "geometry": {"coordinates":[122.22302000000001,37.01064],"type":"Point"}
}