{
  "type": "Feature",
  "properties": {
    "gn:admin1_code":"10.0",
    "gn:asciiname":"Zhangfuzhuang",
    "gn:country_code":"CN",
    "gn:dem":8,
    "gn:feature_class":"P",
    "gn:feature_code":"PPL",
    "gn:name":"Zhangfuzhuang",
    "gn:population":0,
    "gn:timezone":"Asia/Shanghai",
    "iso:country":"CN",
    "name:zho_x_preferred":[
        "\u5f20\u798f\u5e84"
    ],
    "wof:name":"Zhangfuzhuang",
    "wof:placetype":"locality"
},
  "geometry": {"coordinates":[117.208,38.4894],"type":"Point"}
}