{
  "type": "Feature",
  "properties": {
    "gn:admin1_code":"19.0",
    "gn:asciiname":"Liufenfang",
    "gn:country_code":"CN",
    "gn:dem":15,
    "gn:feature_class":"P",
    "gn:feature_code":"PPL",
    "gn:name":"Liufenfang",
    "gn:population":0,
    "gn:timezone":"Asia/Shanghai",
    "iso:country":"CN",
    "name:zho_x_preferred":[
        "\u5218\u7c89\u623f"
    ],
    "wof:name":"Liufenfang",
    "wof:placetype":"locality"
},
  "geometry": {"coordinates":[123.33499999999999,39.8513],"type":"Point"}
}