{
  "type": "Feature",
  "properties": {
    "gn:admin1_code":"20.0",
    "gn:asciiname":"Halagou Qingniandian",
    "gn:country_code":"CN",
    "gn:dem":784,
    "gn:feature_class":"P",
    "gn:feature_code":"PPL",
    "gn:name":"Halagou Qingniandian",
    "gn:population":0,
    "gn:timezone":"Asia/Shanghai",
    "iso:country":"CN",
    "name:zho_x_preferred":[
        "\u54c8\u62c9\u6c9f\u9752\u5e74\u70b9"
    ],
    "wof:name":"Halagou Qingniandian",
    "wof:placetype":"locality"
},
  "geometry": {"coordinates":[121.32366,48.82009],"type":"Point"}
}