{
  "type": "Feature",
  "properties": {
    "gn:admin1_code":"15.0",
    "gn:asciiname":"Xueliang",
    "gn:country_code":"CN",
    "gn:dem":1372,
    "gn:feature_class":"P",
    "gn:feature_code":"PPL",
    "gn:name":"Xueliang",
    "gn:population":0,
    "gn:timezone":"Asia/Shanghai",
    "iso:country":"CN",
    "name:zho_x_preferred":[
        "\u5b66\u7cae"
    ],
    "wof:name":"Xueliang",
    "wof:placetype":"locality"
},
  "geometry": {"coordinates":[103.13,38.5687],"type":"Point"}
}