{
  "type": "Feature",
  "properties": {
    "gn:admin1_code":"31.0",
    "gn:asciiname":"Shanjing",
    "gn:country_code":"CN",
    "gn:dem":81,
    "gn:feature_class":"P",
    "gn:feature_code":"PPL",
    "gn:name":"Shanjing",
    "gn:population":0,
    "gn:timezone":"Asia/Shanghai",
    "iso:country":"CN",
    "name:zho_x_preferred":[
        "\u5584\u4e95"
    ],
    "wof:name":"Shanjing",
    "wof:placetype":"locality"
},
  "geometry": {"coordinates":[109.9263,19.70456],"type":"Point"}
}