{
  "type": "Feature",
  "properties": {
    "gn:admin1_code":"18",
    "gn:asciiname":"Dashujiao",
    "gn:country_code":"CN",
    "gn:dem":1657,
    "gn:feature_class":"P",
    "gn:feature_code":"PPL",
    "gn:name":"Dashujiao",
    "gn:population":0,
    "gn:timezone":"Asia/Shanghai",
    "iso:country":"CN",
    "name:zho_x_preferred":[
        "\u5927\u6811\u811a"
    ],
    "wof:name":"Dashujiao",
    "wof:placetype":"locality"
},
  "geometry": {"coordinates":[105.515,26.419],"type":"Point"}
}