{
  "type": "Feature",
  "properties": {
    "gn:admin1_code":"07",
    "gn:asciiname":"Chizaikeng",
    "gn:country_code":"CN",
    "gn:dem":372,
    "gn:feature_class":"P",
    "gn:feature_code":"PPL",
    "gn:name":"Chizaikeng",
    "gn:population":0,
    "gn:timezone":"Asia/Shanghai",
    "iso:country":"CN",
    "name:zho_x_preferred":[
        "\u8d64\u4ed4\u5751"
    ],
    "wof:name":"Chizaikeng",
    "wof:placetype":"locality"
},
  "geometry": {"coordinates":[117.18548,25.98363],"type":"Point"}
}