{
  "type": "Feature",
  "properties": {
    "gn:admin1_code":"9.0",
    "gn:asciiname":"Silingtou",
    "gn:country_code":"CN",
    "gn:dem":245,
    "gn:feature_class":"P",
    "gn:feature_code":"PPL",
    "gn:name":"Silingtou",
    "gn:population":0,
    "gn:timezone":"Asia/Shanghai",
    "iso:country":"CN",
    "name:zho_x_preferred":[
        "\u56db\u5cad\u5934"
    ],
    "wof:name":"Silingtou",
    "wof:placetype":"locality"
},
  "geometry": {"coordinates":[111.95838000000001,34.47333],"type":"Point"}
}