{
  "type": "Feature",
  "properties": {
    "gn:admin1_code":"4.0",
    "gn:asciiname":"Paifang",
    "gn:country_code":"CN",
    "gn:dem":5,
    "gn:feature_class":"P",
    "gn:feature_code":"PPL",
    "gn:name":"Paifang",
    "gn:population":0,
    "gn:timezone":"Asia/Shanghai",
    "iso:country":"CN",
    "name:und_x_variant":[
        "\u724c\u574a"
    ],
    "wof:name":"Paifang",
    "wof:placetype":"locality"
},
  "geometry": {"coordinates":[121.13194,32.03205999999999],"type":"Point"}
}