{
  "type": "Feature",
  "properties": {
    "gn:admin1_code":"2.0",
    "gn:asciiname":"Beijinshan",
    "gn:country_code":"CN",
    "gn:dem":102,
    "gn:feature_class":"P",
    "gn:feature_code":"PPL",
    "gn:name":"Beijinshan",
    "gn:population":0,
    "gn:timezone":"Asia/Shanghai",
    "iso:country":"CN",
    "name:zho_x_preferred":[
        "\u5317\u91d1\u5c71"
    ],
    "wof:name":"Beijinshan",
    "wof:placetype":"locality"
},
  "geometry": {"coordinates":[120.11538,29.47539],"type":"Point"}
}