{
  "type": "Feature",
  "properties": {
    "gn:admin1_code":"29.0",
    "gn:asciiname":"Qimu",
    "gn:country_code":"CN",
    "gn:dem":1868,
    "gn:feature_class":"P",
    "gn:feature_code":"PPL",
    "gn:name":"Qimu",
    "gn:population":0,
    "gn:timezone":"Asia/Shanghai",
    "iso:country":"CN",
    "name:zho_x_preferred":[
        "\u6864\u6728"
    ],
    "wof:name":"Qimu",
    "wof:placetype":"locality"
},
  "geometry": {"coordinates":[99.89870000000001,24.7006],"type":"Point"}
}