{
  "type": "Feature",
  "properties": {
    "gn:admin1_code":"4.0",
    "gn:asciiname":"Xilizhuang",
    "gn:country_code":"CN",
    "gn:dem":45,
    "gn:feature_class":"P",
    "gn:feature_code":"PPL",
    "gn:name":"Xilizhuang",
    "gn:population":0,
    "gn:timezone":"Asia/Shanghai",
    "iso:country":"CN",
    "name:zho_x_preferred":[
        "\u897f\u674e\u5e84"
    ],
    "wof:name":"Xilizhuang",
    "wof:placetype":"locality"
},
  "geometry": {"coordinates":[116.991,34.3639],"type":"Point"}
}