{
  "type": "Feature",
  "properties": {
    "gn:admin1_code":"2.0",
    "gn:asciiname":"Wanglangli",
    "gn:country_code":"CN",
    "gn:dem":315,
    "gn:feature_class":"P",
    "gn:feature_code":"PPL",
    "gn:name":"Wanglangli",
    "gn:population":0,
    "gn:timezone":"Asia/Shanghai",
    "iso:country":"CN",
    "name:zho_x_preferred":[
        "\u7f51\u7405\u91cc"
    ],
    "wof:name":"Wanglangli",
    "wof:placetype":"locality"
},
  "geometry": {"coordinates":[120.52238,28.03057],"type":"Point"}
}