{
  "type": "Feature",
  "properties": {
    "gn:admin1_code":"19.0",
    "gn:asciiname":"Xiaoshifogou",
    "gn:country_code":"CN",
    "gn:dem":762,
    "gn:feature_class":"P",
    "gn:feature_code":"PPL",
    "gn:name":"Xiaoshifogou",
    "gn:population":0,
    "gn:timezone":"Asia/Shanghai",
    "iso:country":"CN",
    "name:zho_x_preferred":[
        "\u5c0f\u77f3\u4f5b\u6c9f"
    ],
    "wof:name":"Xiaoshifogou",
    "wof:placetype":"locality"
},
  "geometry": {"coordinates":[119.78264,41.71769000000001],"type":"Point"}
}