{
  "type": "Feature",
  "properties": {
    "gn:admin1_code":"29.0",
    "gn:asciiname":"Manfang Dazhai",
    "gn:country_code":"CN",
    "gn:dem":1243,
    "gn:feature_class":"P",
    "gn:feature_code":"PPL",
    "gn:name":"Manfang Dazhai",
    "gn:population":0,
    "gn:timezone":"Asia/Shanghai",
    "iso:country":"CN",
    "name:zho_x_preferred":[
        "\u66fc\u65b9\u5927\u5be8"
    ],
    "wof:name":"Manfang Dazhai",
    "wof:placetype":"locality"
},
  "geometry": {"coordinates":[100.511,22.0574],"type":"Point"}
}