{
  "type": "Feature",
  "properties": {
    "gn:admin1_code":"05",
    "gn:asciiname":"Xilinhe",
    "gn:country_code":"CN",
    "gn:dem":286,
    "gn:feature_class":"P",
    "gn:feature_code":"PPLA4",
    "gn:name":"Xilinhe",
    "gn:population":0,
    "gn:timezone":"Asia/Shanghai",
    "iso:country":"CN",
    "name:und_x_variant":[
        "\u7ec6\u9cde\u6cb3",
        "Xilinhe Xiang",
        "\u7ec6\u9cde\u6cb3\u4e61"
    ],
    "wof:name":"Xilinhe",
    "wof:placetype":"locality"
},
  "geometry": {"coordinates":[129.15805,42.83647],"type":"Point"}
}