{
  "type": "Feature",
  "properties": {
    "gn:admin1_code":"32.0",
    "gn:asciiname":"Shengjigou",
    "gn:country_code":"CN",
    "gn:dem":332,
    "gn:feature_class":"P",
    "gn:feature_code":"PPL",
    "gn:name":"Shengjigou",
    "gn:population":0,
    "gn:timezone":"Asia/Shanghai",
    "iso:country":"CN",
    "name:zho_x_preferred":[
        "\u751f\u57fa\u6c9f"
    ],
    "wof:name":"Shengjigou",
    "wof:placetype":"locality"
},
  "geometry": {"coordinates":[105.056,28.56],"type":"Point"}
}