{
  "type": "Feature",
  "properties": {
    "gn:admin1_code":"19.0",
    "gn:asciiname":"Nanlijia Buzi",
    "gn:country_code":"CN",
    "gn:dem":63,
    "gn:feature_class":"P",
    "gn:feature_code":"PPL",
    "gn:name":"Nanlijia Buzi",
    "gn:population":0,
    "gn:timezone":"Asia/Shanghai",
    "iso:country":"CN",
    "name:zho_x_preferred":[
        "\u5357\u674e\u5bb6\u5821\u5b50"
    ],
    "wof:name":"Nanlijia Buzi",
    "wof:placetype":"locality"
},
  "geometry": {"coordinates":[124.21299999999999,40.2656],"type":"Point"}
}