{
  "type": "Feature",
  "properties": {
    "gn:admin1_code":"24.0",
    "gn:asciiname":"Mayugou",
    "gn:country_code":"CN",
    "gn:dem":820,
    "gn:feature_class":"P",
    "gn:feature_code":"PPL",
    "gn:name":"Mayugou",
    "gn:population":0,
    "gn:timezone":"Asia/Shanghai",
    "iso:country":"CN",
    "name:zho_x_preferred":[
        "\u9a6c\u5cea\u6c9f"
    ],
    "wof:name":"Mayugou",
    "wof:placetype":"locality"
},
  "geometry": {"coordinates":[113.74995,38.00717],"type":"Point"}
}