{
  "type": "Feature",
  "properties": {
    "gn:admin1_code":"19.0",
    "gn:asciiname":"Moujia Kanzi",
    "gn:country_code":"CN",
    "gn:dem":226,
    "gn:feature_class":"P",
    "gn:feature_code":"PPL",
    "gn:name":"Moujia Kanzi",
    "gn:population":0,
    "gn:timezone":"Asia/Shanghai",
    "iso:country":"CN",
    "name:zho_x_preferred":[
        "\u725f\u5bb6\u574e\u5b50"
    ],
    "wof:name":"Moujia Kanzi",
    "wof:placetype":"locality"
},
  "geometry": {"coordinates":[124.497,40.7635],"type":"Point"}
}