{
  "type": "Feature",
  "properties": {
    "gn:admin1_code":"3.0",
    "gn:asciiname":"Qiaolecun",
    "gn:country_code":"CN",
    "gn:dem":32,
    "gn:feature_class":"P",
    "gn:feature_code":"PPL",
    "gn:name":"Qiaolecun",
    "gn:population":0,
    "gn:timezone":"Asia/Shanghai",
    "iso:country":"CN",
    "name:und_x_variant":[
        "\u4e54\u4e50\u6751"
    ],
    "wof:name":"Qiaolecun",
    "wof:placetype":"locality"
},
  "geometry": {"coordinates":[116.27791000000001,28.13495],"type":"Point"}
}