{
  "type": "Feature",
  "properties": {
    "gn:admin1_code":"32.0",
    "gn:asciiname":"Ranmuduo",
    "gn:country_code":"CN",
    "gn:dem":3443,
    "gn:feature_class":"P",
    "gn:feature_code":"PPL",
    "gn:name":"Ranmuduo",
    "gn:population":0,
    "gn:timezone":"Asia/Shanghai",
    "iso:country":"CN",
    "name:zho_x_preferred":[
        "\u7136\u6728\u593a"
    ],
    "wof:name":"Ranmuduo",
    "wof:placetype":"locality"
},
  "geometry": {"coordinates":[102.04300000000001,32.7413],"type":"Point"}
}