{
  "type": "Feature",
  "properties": {
    "gn:admin1_code":"8.0",
    "gn:asciiname":"Yanshancun",
    "gn:country_code":"CN",
    "gn:dem":60,
    "gn:feature_class":"P",
    "gn:feature_code":"PPL",
    "gn:name":"Yanshancun",
    "gn:population":0,
    "gn:timezone":"Asia/Shanghai",
    "iso:country":"CN",
    "name:zho_x_preferred":[
        "\u781a\u5c71\u6751"
    ],
    "wof:name":"Yanshancun",
    "wof:placetype":"locality"
},
  "geometry": {"coordinates":[132.15264999999999,47.14752],"type":"Point"}
}