{
  "type": "Feature",
  "properties": {
    "gn:admin1_code":"25.0",
    "gn:asciiname":"Luangezhuang",
    "gn:country_code":"CN",
    "gn:dem":126,
    "gn:feature_class":"P",
    "gn:feature_code":"PPL",
    "gn:name":"Luangezhuang",
    "gn:population":0,
    "gn:timezone":"Asia/Shanghai",
    "iso:country":"CN",
    "name:zho_x_preferred":[
        "\u683e\u683c\u5e84"
    ],
    "wof:name":"Luangezhuang",
    "wof:placetype":"locality"
},
  "geometry": {"coordinates":[120.62192,37.17838],"type":"Point"}
}