{
  "type": "Feature",
  "properties": {
    "gn:admin1_code":"32.0",
    "gn:asciiname":"Shuangshizi",
    "gn:country_code":"CN",
    "gn:dem":510,
    "gn:feature_class":"P",
    "gn:feature_code":"PPL",
    "gn:name":"Shuangshizi",
    "gn:population":0,
    "gn:timezone":"Asia/Shanghai",
    "iso:country":"CN",
    "name:zho_x_preferred":[
        "\u53cc\u72ee\u5b50"
    ],
    "wof:name":"Shuangshizi",
    "wof:placetype":"locality"
},
  "geometry": {"coordinates":[107.06779,31.36339000000001],"type":"Point"}
}