{
  "type": "Feature",
  "properties": {
    "gn:admin1_code":"4.0",
    "gn:asciiname":"Ouzhuangcun",
    "gn:country_code":"CN",
    "gn:dem":41,
    "gn:feature_class":"P",
    "gn:feature_code":"PPL",
    "gn:name":"Ouzhuangcun",
    "gn:population":0,
    "gn:timezone":"Asia/Shanghai",
    "iso:country":"CN",
    "name:zho_x_preferred":[
        "\u6b27\u5e84\u6751"
    ],
    "wof:name":"Ouzhuangcun",
    "wof:placetype":"locality"
},
  "geometry": {"coordinates":[116.8291,34.5177],"type":"Point"}
}