{
  "type": "Feature",
  "properties": {
    "gn:admin1_code":"9.0",
    "gn:asciiname":"Xuchuan",
    "gn:country_code":"CN",
    "gn:dem":184,
    "gn:feature_class":"P",
    "gn:feature_code":"PPL",
    "gn:name":"Xuchuan",
    "gn:population":0,
    "gn:timezone":"Asia/Shanghai",
    "iso:country":"CN",
    "name:zho_x_preferred":[
        "\u8bb8\u4e32"
    ],
    "wof:name":"Xuchuan",
    "wof:placetype":"locality"
},
  "geometry": {"coordinates":[114.19477999999999,36.03529],"type":"Point"}
}