{
  "type": "Feature",
  "properties": {
    "gn:admin1_code":"7.0",
    "gn:asciiname":"Xiamengkeng",
    "gn:country_code":"CN",
    "gn:dem":361,
    "gn:feature_class":"P",
    "gn:feature_code":"PPL",
    "gn:name":"Xiamengkeng",
    "gn:population":0,
    "gn:timezone":"Asia/Shanghai",
    "iso:country":"CN",
    "name:und_x_variant":[
        "\u4e0b\u731b\u5751"
    ],
    "name:zho_x_preferred":[
        "\u4e0b\u731b\u5751"
    ],
    "wof:name":"Xiamengkeng",
    "wof:placetype":"locality"
},
  "geometry": {"coordinates":[117.19523,26.9289],"type":"Point"}
}