{
  "type": "Feature",
  "properties": {
    "gn:admin1_code":"19.0",
    "gn:asciiname":"Toudaogou",
    "gn:country_code":"CN",
    "gn:dem":116,
    "gn:feature_class":"P",
    "gn:feature_code":"PPL",
    "gn:name":"Toudaogou",
    "gn:population":0,
    "gn:timezone":"Asia/Shanghai",
    "iso:country":"CN",
    "name:und_x_variant":[
        "\u5934\u9053\u6c9f"
    ],
    "name:zho_x_preferred":[
        "\u5934\u9053\u6c9f"
    ],
    "wof:name":"Toudaogou",
    "wof:placetype":"locality"
},
  "geometry": {"coordinates":[123.63731,40.36666],"type":"Point"}
}