{
  "type": "Feature",
  "properties": {
    "gn:admin1_code":"7.0",
    "gn:asciiname":"Zaohetian",
    "gn:country_code":"CN",
    "gn:dem":361,
    "gn:feature_class":"P",
    "gn:feature_code":"PPL",
    "gn:name":"Zaohetian",
    "gn:population":0,
    "gn:timezone":"Asia/Shanghai",
    "iso:country":"CN",
    "name:und_x_variant":[
        "\u65e9\u79be\u7530"
    ],
    "name:zho_x_preferred":[
        "\u65e9\u79be\u7530"
    ],
    "wof:name":"Zaohetian",
    "wof:placetype":"locality"
},
  "geometry": {"coordinates":[116.49328,26.26874],"type":"Point"}
}