{
  "type": "Feature",
  "properties": {
    "gn:admin1_code":"18.0",
    "gn:asciiname":"Futouzhai",
    "gn:country_code":"CN",
    "gn:dem":480,
    "gn:feature_class":"P",
    "gn:feature_code":"PPL",
    "gn:name":"Futouzhai",
    "gn:population":0,
    "gn:timezone":"Asia/Shanghai",
    "iso:country":"CN",
    "name:zho_x_preferred":[
        "\u752b\u5934\u5be8"
    ],
    "wof:name":"Futouzhai",
    "wof:placetype":"locality"
},
  "geometry": {"coordinates":[109.05800000000001,26.8619],"type":"Point"}
}