{
  "type": "Feature",
  "properties": {
    "gn:admin1_code":"29.0",
    "gn:asciiname":"Banlin",
    "gn:country_code":"CN",
    "gn:dem":2181,
    "gn:feature_class":"P",
    "gn:feature_code":"PPL",
    "gn:name":"Banlin",
    "gn:population":0,
    "gn:timezone":"Asia/Shanghai",
    "iso:country":"CN",
    "name:zho_x_preferred":[
        "\u534a\u6797"
    ],
    "wof:name":"Banlin",
    "wof:placetype":"locality"
},
  "geometry": {"coordinates":[103.932,27.5529],"type":"Point"}
}