{
  "type": "Feature",
  "properties": {
    "gn:admin1_code":"7.0",
    "gn:asciiname":"Jinfengcun",
    "gn:country_code":"CN",
    "gn:dem":323,
    "gn:feature_class":"P",
    "gn:feature_code":"PPL",
    "gn:name":"Jinfengcun",
    "gn:population":0,
    "gn:timezone":"Asia/Shanghai",
    "iso:country":"CN",
    "name:zho_x_preferred":[
        "\u91d1\u5cf0\u6751"
    ],
    "wof:name":"Jinfengcun",
    "wof:placetype":"locality"
},
  "geometry": {"coordinates":[118.63074,27.46217],"type":"Point"}
}