{
  "type": "Feature",
  "properties": {
    "gn:admin1_code":"14.0",
    "gn:asciiname":"Kongtuocun",
    "gn:country_code":"CN",
    "gn:dem":4617,
    "gn:feature_class":"P",
    "gn:feature_code":"PPL",
    "gn:name":"Kongtuocun",
    "gn:population":0,
    "gn:timezone":"Asia/Urumqi",
    "iso:country":"CN",
    "name:zho_x_preferred":[
        "\u5b54\u6258\u6751"
    ],
    "wof:name":"Kongtuocun",
    "wof:placetype":"locality"
},
  "geometry": {"coordinates":[91.43191,31.18307],"type":"Point"}
}