{
  "type": "Feature",
  "properties": {
    "gn:admin1_code":"1.0",
    "gn:asciiname":"Liujia",
    "gn:country_code":"CN",
    "gn:dem":18,
    "gn:feature_class":"P",
    "gn:feature_code":"PPL",
    "gn:name":"Liujia",
    "gn:population":0,
    "gn:timezone":"Asia/Shanghai",
    "iso:country":"CN",
    "name:ceb_x_preferred":[
        "Liujia"
    ],
    "name:deu_x_preferred":[
        "Liujia"
    ],
    "name:swe_x_preferred":[
        "Liujia"
    ],
    "wof:name":"Liujia",
    "wof:placetype":"locality"
},
  "geometry": {"coordinates":[117.52500000000001,33.15278],"type":"Point"}
}