{
  "type": "Feature",
  "properties": {
    "gn:admin1_code":"12.0",
    "gn:asciiname":"Fengfu",
    "gn:country_code":"CN",
    "gn:dem":1141,
    "gn:feature_class":"P",
    "gn:feature_code":"PPL",
    "gn:name":"Fengfu",
    "gn:population":0,
    "gn:timezone":"Asia/Shanghai",
    "iso:country":"CN",
    "name:zho_x_preferred":[
        "\u4e30\u5bcc"
    ],
    "wof:name":"Fengfu",
    "wof:placetype":"locality"
},
  "geometry": {"coordinates":[108.89109000000001,30.14616],"type":"Point"}
}