{
  "type": "Feature",
  "properties": {
    "gn:admin1_code":"29",
    "gn:asciiname":"Taoshucun",
    "gn:country_code":"CN",
    "gn:dem":1916,
    "gn:feature_class":"P",
    "gn:feature_code":"PPL",
    "gn:name":"Taoshucun",
    "gn:population":0,
    "gn:timezone":"Asia/Shanghai",
    "iso:country":"CN",
    "name:zho_x_preferred":[
        "\u6843\u6811\u6751"
    ],
    "wof:name":"Taoshucun",
    "wof:placetype":"locality"
},
  "geometry": {"coordinates":[102.54198,24.83158],"type":"Point"}
}