{
  "type": "Feature",
  "properties": {
    "gn:admin1_code":"10",
    "gn:asciiname":"Changpanzi",
    "gn:country_code":"CN",
    "gn:dem":1612,
    "gn:feature_class":"P",
    "gn:feature_code":"PPL",
    "gn:name":"Changpanzi",
    "gn:population":0,
    "gn:timezone":"Asia/Shanghai",
    "iso:country":"CN",
    "name:zho_x_preferred":[
        "\u573a\u76d8\u5b50"
    ],
    "wof:name":"Changpanzi",
    "wof:placetype":"locality"
},
  "geometry": {"coordinates":[117.71199,42.36449],"type":"Point"}
}