{
  "type": "Feature",
  "properties": {
    "gn:admin1_code":"29.0",
    "gn:asciiname":"Huaying",
    "gn:country_code":"CN",
    "gn:dem":1993,
    "gn:feature_class":"P",
    "gn:feature_code":"PPL",
    "gn:name":"Huaying",
    "gn:population":0,
    "gn:timezone":"Asia/Shanghai",
    "iso:country":"CN",
    "name:zho_x_preferred":[
        "\u534e\u8425"
    ],
    "wof:name":"Huaying",
    "wof:placetype":"locality"
},
  "geometry": {"coordinates":[100.324,25.6243],"type":"Point"}
}