{
  "type": "Feature",
  "properties": {
    "gn:admin1_code":"15.0",
    "gn:asciiname":"Kuangou",
    "gn:country_code":"CN",
    "gn:dem":2522,
    "gn:feature_class":"P",
    "gn:feature_code":"PPL",
    "gn:name":"Kuangou",
    "gn:population":0,
    "gn:timezone":"Asia/Shanghai",
    "iso:country":"CN",
    "name:zho_x_preferred":[
        "\u5bbd\u6c9f"
    ],
    "wof:name":"Kuangou",
    "wof:placetype":"locality"
},
  "geometry": {"coordinates":[102.411,37.6575],"type":"Point"}
}