{
  "type": "Feature",
  "properties": {
    "gn:admin1_code":"14.0",
    "gn:asciiname":"Pacuo",
    "gn:country_code":"CN",
    "gn:dem":4087,
    "gn:feature_class":"P",
    "gn:feature_code":"PPL",
    "gn:name":"Pacuo",
    "gn:population":0,
    "gn:timezone":"Asia/Urumqi",
    "iso:country":"CN",
    "name:zho_x_preferred":[
        "\u5e15\u9519"
    ],
    "wof:name":"Pacuo",
    "wof:placetype":"locality"
},
  "geometry": {"coordinates":[87.72490000000001,29.3224],"type":"Point"}
}