{
  "type": "Feature",
  "properties": {
    "gn:admin1_code":"18",
    "gn:asciiname":"Jiajiaoshan",
    "gn:country_code":"CN",
    "gn:dem":824,
    "gn:feature_class":"P",
    "gn:feature_code":"PPL",
    "gn:name":"Jiajiaoshan",
    "gn:population":0,
    "gn:timezone":"Asia/Shanghai",
    "iso:country":"CN",
    "name:zho_x_preferred":[
        "\u8d3e\u89d2\u5c71"
    ],
    "wof:name":"Jiajiaoshan",
    "wof:placetype":"locality"
},
  "geometry": {"coordinates":[106.152,27.7106],"type":"Point"}
}