{
  "type": "Feature",
  "properties": {
    "gn:admin1_code":"9.0",
    "gn:asciiname":"Liyoufang",
    "gn:country_code":"CN",
    "gn:dem":104,
    "gn:feature_class":"P",
    "gn:feature_code":"PPL",
    "gn:name":"Liyoufang",
    "gn:population":0,
    "gn:timezone":"Asia/Shanghai",
    "iso:country":"CN",
    "name:zho_x_preferred":[
        "\u674e\u6cb9\u574a"
    ],
    "wof:name":"Liyoufang",
    "wof:placetype":"locality"
},
  "geometry": {"coordinates":[115.45717,31.85579],"type":"Point"}
}