{
  "type": "Feature",
  "properties": {
    "gn:admin1_code":"24.0",
    "gn:asciiname":"Yongfeng",
    "gn:country_code":"CN",
    "gn:dem":1072,
    "gn:feature_class":"P",
    "gn:feature_code":"PPL",
    "gn:name":"Yongfeng",
    "gn:population":0,
    "gn:timezone":"Asia/Shanghai",
    "iso:country":"CN",
    "name:zho_x_preferred":[
        "\u6c38\u4e30"
    ],
    "wof:name":"Yongfeng",
    "wof:placetype":"locality"
},
  "geometry": {"coordinates":[111.09583000000001,37.93617],"type":"Point"}
}