{
  "type": "Feature",
  "properties": {
    "gn:admin1_code":"13.0",
    "gn:asciiname":"Taldi",
    "gn:country_code":"CN",
    "gn:dem":897,
    "gn:feature_class":"P",
    "gn:feature_code":"PPLA4",
    "gn:name":"Taldi",
    "gn:population":0,
    "gn:timezone":"Asia/Urumqi",
    "iso:country":"CN",
    "name:uig_x_preferred":[
        "\u062a\u0627\u0644\u062f\u0649"
    ],
    "name:uig_x_variant":[
        "\u0422\u0430\u043b\u0434\u0438"
    ],
    "name:und_x_variant":[
        "Taldi Xiang",
        "Taldi",
        "Talede",
        "Talede Xiang"
    ],
    "name:zho_x_preferred":[
        "\u5854\u52d2\u5fb7"
    ],
    "name:zho_x_variant":[
        "\u5854\u52d2\u5fb7\u4e61"
    ],
    "wof:name":"Taldi",
    "wof:placetype":"locality"
},
  "geometry": {"coordinates":[83.05389,43.41353],"type":"Point"}
}