{
  "type": "Feature",
  "properties": {
    "gn:admin1_code":"25.0",
    "gn:asciiname":"Xuejialing",
    "gn:cc2":"CN",
    "gn:country_code":"CN",
    "gn:dem":34,
    "gn:feature_class":"P",
    "gn:feature_code":"PPL",
    "gn:name":"Xuejialing",
    "gn:population":0,
    "gn:timezone":"Asia/Shanghai",
    "iso:country":"CN",
    "name:zho_x_preferred":[
        "\u859b\u5bb6\u5cad"
    ],
    "wof:name":"Xuejialing",
    "wof:placetype":"locality"
},
  "geometry": {"coordinates":[120.0198,35.93139],"type":"Point"}
}