{
  "type": "Feature",
  "properties": {
    "gn:admin1_code":"15.0",
    "gn:asciiname":"Xinzhuangwan",
    "gn:country_code":"CN",
    "gn:dem":2860,
    "gn:feature_class":"P",
    "gn:feature_code":"PPL",
    "gn:name":"Xinzhuangwan",
    "gn:population":0,
    "gn:timezone":"Asia/Shanghai",
    "iso:country":"CN",
    "name:und_x_variant":[
        "\u65b0\u5e84\u6e7e"
    ],
    "wof:name":"Xinzhuangwan",
    "wof:placetype":"locality"
},
  "geometry": {"coordinates":[104.17299,34.54805],"type":"Point"}
}