{
  "type": "Feature",
  "properties": {
    "gn:admin1_code":"32.0",
    "gn:asciiname":"Zhanwa",
    "gn:country_code":"CN",
    "gn:dem":3022,
    "gn:feature_class":"P",
    "gn:feature_code":"PPL",
    "gn:name":"Zhanwa",
    "gn:population":0,
    "gn:timezone":"Asia/Shanghai",
    "iso:country":"CN",
    "name:zho_x_preferred":[
        "\u5360\u54c7"
    ],
    "wof:name":"Zhanwa",
    "wof:placetype":"locality"
},
  "geometry": {"coordinates":[102.89409999999999,34.24041],"type":"Point"}
}