{
  "type": "Feature",
  "properties": {
    "gn:admin1_code":"16.0",
    "gn:asciiname":"Quzuo",
    "gn:country_code":"CN",
    "gn:dem":173,
    "gn:feature_class":"P",
    "gn:feature_code":"PPL",
    "gn:name":"Quzuo",
    "gn:population":0,
    "gn:timezone":"Asia/Shanghai",
    "iso:country":"CN",
    "name:zho_x_preferred":[
        "\u6e20\u5ea7"
    ],
    "wof:name":"Quzuo",
    "wof:placetype":"locality"
},
  "geometry": {"coordinates":[107.441,22.3306],"type":"Point"}
}