{
  "type": "Feature",
  "properties": {
    "gn:admin1_code":"9.0",
    "gn:asciiname":"Yangweizi",
    "gn:country_code":"CN",
    "gn:dem":58,
    "gn:feature_class":"P",
    "gn:feature_code":"PPL",
    "gn:name":"Yangweizi",
    "gn:population":0,
    "gn:timezone":"Asia/Shanghai",
    "iso:country":"CN",
    "name:zho_x_preferred":[
        "\u6768\u56f4\u5b50"
    ],
    "wof:name":"Yangweizi",
    "wof:placetype":"locality"
},
  "geometry": {"coordinates":[114.44659,32.8156],"type":"Point"}
}