{
  "type": "Feature",
  "properties": {
    "gn:admin1_code":"30.0",
    "gn:asciiname":"Tianliao",
    "gn:country_code":"CN",
    "gn:dem":32,
    "gn:feature_class":"P",
    "gn:feature_code":"PPL",
    "gn:name":"Tianliao",
    "gn:population":0,
    "gn:timezone":"Asia/Shanghai",
    "iso:country":"CN",
    "name:zho_x_preferred":[
        "\u7530\u5bee"
    ],
    "wof:name":"Tianliao",
    "wof:placetype":"locality"
},
  "geometry": {"coordinates":[114.10999,23.36501],"type":"Point"}
}