{
  "type": "Feature",
  "properties": {
    "gn:admin1_code":"19.0",
    "gn:asciiname":"Huilingzi",
    "gn:country_code":"CN",
    "gn:dem":142,
    "gn:feature_class":"P",
    "gn:feature_code":"PPL",
    "gn:name":"Huilingzi",
    "gn:population":0,
    "gn:timezone":"Asia/Shanghai",
    "iso:country":"CN",
    "name:und_x_variant":[
        "\u7070\u5cad\u5b50"
    ],
    "wof:name":"Huilingzi",
    "wof:placetype":"locality"
},
  "geometry": {"coordinates":[122.75767,40.69171],"type":"Point"}
}