{
  "type": "Feature",
  "properties": {
    "gn:admin1_code":"29.0",
    "gn:asciiname":"Miezhupeng",
    "gn:country_code":"CN",
    "gn:dem":1223,
    "gn:feature_class":"P",
    "gn:feature_code":"PPL",
    "gn:name":"Miezhupeng",
    "gn:population":0,
    "gn:timezone":"Asia/Shanghai",
    "iso:country":"CN",
    "name:zho_x_preferred":[
        "\u8511\u7af9\u68da"
    ],
    "wof:name":"Miezhupeng",
    "wof:placetype":"locality"
},
  "geometry": {"coordinates":[100.349,23.4704],"type":"Point"}
}