{
  "type": "Feature",
  "properties": {
    "gn:admin1_code":"16.0",
    "gn:asciiname":"Yaziping",
    "gn:country_code":"CN",
    "gn:dem":69,
    "gn:feature_class":"P",
    "gn:feature_code":"PPL",
    "gn:name":"Yaziping",
    "gn:population":0,
    "gn:timezone":"Asia/Shanghai",
    "iso:country":"CN",
    "name:zho_x_preferred":[
        "\u96c5\u5b50\u576a"
    ],
    "wof:name":"Yaziping",
    "wof:placetype":"locality"
},
  "geometry": {"coordinates":[109.02800000000001,22.2589],"type":"Point"}
}