{
  "type": "Feature",
  "properties": {
    "gn:admin1_code":"19.0",
    "gn:asciiname":"Chuquandi",
    "gn:country_code":"CN",
    "gn:dem":53,
    "gn:feature_class":"P",
    "gn:feature_code":"PPL",
    "gn:name":"Chuquandi",
    "gn:population":0,
    "gn:timezone":"Asia/Shanghai",
    "iso:country":"CN",
    "name:und_x_variant":[
        "\u51fa\u5708\u5730"
    ],
    "name:zho_x_preferred":[
        "\u51fa\u5708\u5730"
    ],
    "wof:name":"Chuquandi",
    "wof:placetype":"locality"
},
  "geometry": {"coordinates":[120.50960000000001,40.55062],"type":"Point"}
}