{
  "type": "Feature",
  "properties": {
    "gn:admin1_code":"14.0",
    "gn:asciiname":"Xiemacun",
    "gn:country_code":"CN",
    "gn:dem":4464,
    "gn:feature_class":"P",
    "gn:feature_code":"PPL",
    "gn:name":"Xiemacun",
    "gn:population":0,
    "gn:timezone":"Asia/Urumqi",
    "iso:country":"CN",
    "name:zho_x_preferred":[
        "\u534f\u739b\u6751"
    ],
    "wof:name":"Xiemacun",
    "wof:placetype":"locality"
},
  "geometry": {"coordinates":[96.36565,31.05014000000001],"type":"Point"}
}