{
  "type": "Feature",
  "properties": {
    "gn:admin1_code":"11.0",
    "gn:asciiname":"Hegongmiao",
    "gn:country_code":"CN",
    "gn:dem":156,
    "gn:feature_class":"P",
    "gn:feature_code":"PPL",
    "gn:name":"Hegongmiao",
    "gn:population":0,
    "gn:timezone":"Asia/Shanghai",
    "iso:country":"CN",
    "name:zho_x_preferred":[
        "\u79be\u516c\u5e99"
    ],
    "wof:name":"Hegongmiao",
    "wof:placetype":"locality"
},
  "geometry": {"coordinates":[113.28570999999999,26.46333],"type":"Point"}
}