{
  "type": "Feature",
  "properties": {
    "gn:admin1_code":"13",
    "gn:asciiname":"Fengshousanchang Yisilian",
    "gn:country_code":"CN",
    "gn:dem":1040,
    "gn:feature_class":"P",
    "gn:feature_code":"PPL",
    "gn:name":"Fengshousanchang Yisilian",
    "gn:population":0,
    "gn:timezone":"Asia/Shanghai",
    "iso:country":"CN",
    "name:und_x_variant":[
        "\u4e30\u6536\u4e09\u573a\u4e00\u56db\u8fde"
    ],
    "wof:name":"Fengshousanchang Yisilian",
    "wof:placetype":"locality"
},
  "geometry": {"coordinates":[80.34348,40.30336],"type":"Point"}
}