{
  "type": "Feature",
  "properties": {
    "gn:admin1_code":"19.0",
    "gn:asciiname":"Xiaoguoyu",
    "gn:country_code":"CN",
    "gn:dem":178,
    "gn:feature_class":"P",
    "gn:feature_code":"PPL",
    "gn:name":"Xiaoguoyu",
    "gn:population":0,
    "gn:timezone":"Asia/Shanghai",
    "iso:country":"CN",
    "name:und_x_variant":[
        "\u5c0f\u9505\u5cea"
    ],
    "wof:name":"Xiaoguoyu",
    "wof:placetype":"locality"
},
  "geometry": {"coordinates":[122.45092,40.23193],"type":"Point"}
}