{
  "type": "Feature",
  "properties": {
    "gn:admin1_code":"24.0",
    "gn:asciiname":"Laolongshen",
    "gn:country_code":"CN",
    "gn:dem":1440,
    "gn:feature_class":"P",
    "gn:feature_code":"PPL",
    "gn:name":"Laolongshen",
    "gn:population":0,
    "gn:timezone":"Asia/Shanghai",
    "iso:country":"CN",
    "name:zho_x_preferred":[
        "\u8001\u9f99\u795e"
    ],
    "wof:name":"Laolongshen",
    "wof:placetype":"locality"
},
  "geometry": {"coordinates":[111.03991000000001,36.92084000000001],"type":"Point"}
}