{
  "type": "Feature",
  "properties": {
    "gn:admin1_code":"26.0",
    "gn:asciiname":"Xiaobaocheng",
    "gn:country_code":"CN",
    "gn:dem":1397,
    "gn:feature_class":"P",
    "gn:feature_code":"PPL",
    "gn:name":"Xiaobaocheng",
    "gn:population":0,
    "gn:timezone":"Asia/Shanghai",
    "iso:country":"CN",
    "name:und_x_variant":[
        "\u5c0f\u8912\u57ce"
    ],
    "wof:name":"Xiaobaocheng",
    "wof:placetype":"locality"
},
  "geometry": {"coordinates":[106.62612,32.84778],"type":"Point"}
}