{
  "type": "Feature",
  "properties": {
    "gn:admin1_code":"18.0",
    "gn:asciiname":"Niupi",
    "gn:country_code":"CN",
    "gn:dem":803,
    "gn:feature_class":"P",
    "gn:feature_code":"PPL",
    "gn:name":"Niupi",
    "gn:population":0,
    "gn:timezone":"Asia/Shanghai",
    "iso:country":"CN",
    "name:zho_x_preferred":[
        "\u725b\u76ae"
    ],
    "wof:name":"Niupi",
    "wof:placetype":"locality"
},
  "geometry": {"coordinates":[107.991,26.7573],"type":"Point"}
}