{
  "type": "Feature",
  "properties": {
    "gn:admin1_code":"15.0",
    "gn:asciiname":"Zhongjiashan",
    "gn:country_code":"CN",
    "gn:dem":1563,
    "gn:feature_class":"P",
    "gn:feature_code":"PPL",
    "gn:name":"Zhongjiashan",
    "gn:population":0,
    "gn:timezone":"Asia/Shanghai",
    "iso:country":"CN",
    "name:und_x_variant":[
        "\u949f\u5bb6\u5c71"
    ],
    "wof:name":"Zhongjiashan",
    "wof:placetype":"locality"
},
  "geometry": {"coordinates":[105.57353000000001,33.74905],"type":"Point"}
}