{
  "type": "Feature",
  "properties": {
    "gn:admin1_code":"10.0",
    "gn:asciiname":"He'an Nanli",
    "gn:country_code":"CN",
    "gn:dem":4,
    "gn:feature_class":"P",
    "gn:feature_code":"PPL",
    "gn:name":"He\u2019an Nanli",
    "gn:population":0,
    "gn:timezone":"Asia/Shanghai",
    "iso:country":"CN",
    "name:und_x_variant":[
        "He\u2019an Nanli"
    ],
    "name:zho_x_preferred":[
        "\u548c\u5b89\u5357\u91cc"
    ],
    "wof:name":"He'an Nanli",
    "wof:placetype":"locality"
},
  "geometry": {"coordinates":[119.5746,39.93266],"type":"Point"}
}