{
  "type": "Feature",
  "properties": {
    "gn:admin1_code":"02",
    "gn:asciiname":"Jianqiao",
    "gn:country_code":"CN",
    "gn:dem":13,
    "gn:feature_class":"P",
    "gn:feature_code":"PPLA4",
    "gn:name":"Jianqiao",
    "gn:population":0,
    "gn:timezone":"Asia/Shanghai",
    "iso:country":"CN",
    "name:swe_x_preferred":[
        "Jianqiao"
    ],
    "name:und_x_variant":[
        "Chien-ch\u2019iao",
        "Kienkiao",
        "Chien-ch\u2019iao-chen",
        "Jianqiao",
        "\u7b15\u6865",
        "Jianqiao Zhen",
        "\u7b15\u6865\u9547"
    ],
    "wof:name":"Jianqiao",
    "wof:placetype":"locality"
},
  "geometry": {"coordinates":[120.21512,30.31955],"type":"Point"}
}