{
  "type": "Feature",
  "properties": {
    "gn:admin1_code":"26.0",
    "gn:asciiname":"Yawu",
    "gn:country_code":"CN",
    "gn:dem":981,
    "gn:feature_class":"P",
    "gn:feature_code":"PPL",
    "gn:name":"Yawu",
    "gn:population":0,
    "gn:timezone":"Asia/Shanghai",
    "iso:country":"CN",
    "wof:name":"Yawu",
    "wof:placetype":"locality"
},
  "geometry": {"coordinates":[109.43333,33.35],"type":"Point"}
}