{
  "type": "Feature",
  "properties": {
    "gn:admin1_code":"9.0",
    "gn:asciiname":"Shaping",
    "gn:country_code":"CN",
    "gn:dem":369,
    "gn:feature_class":"P",
    "gn:feature_code":"PPL",
    "gn:name":"Shaping",
    "gn:population":0,
    "gn:timezone":"Asia/Shanghai",
    "iso:country":"CN",
    "name:ceb_x_preferred":[
        "Shaping"
    ],
    "name:deu_x_preferred":[
        "Shaping"
    ],
    "name:mlg_x_preferred":[
        "Shaping"
    ],
    "name:rus_x_preferred":[
        "\u0428\u0435\u0439\u043f\u0438\u043d\u0433"
    ],
    "name:zho_x_preferred":[
        "\u6c99\u576a"
    ],
    "wof:name":"Shaping",
    "wof:placetype":"locality"
},
  "geometry": {"coordinates":[112.55087,34.08331],"type":"Point"}
}