{
  "type": "Feature",
  "properties": {
    "gn:admin1_code":"26.0",
    "gn:asciiname":"Bucuncun",
    "gn:country_code":"CN",
    "gn:dem":680,
    "gn:feature_class":"P",
    "gn:feature_code":"PPL",
    "gn:name":"Bucuncun",
    "gn:population":0,
    "gn:timezone":"Asia/Shanghai",
    "iso:country":"CN",
    "name:zho_x_preferred":[
        "\u5e03\u6751\u6751"
    ],
    "wof:name":"Bucuncun",
    "wof:placetype":"locality"
},
  "geometry": {"coordinates":[109.16663,34.14122],"type":"Point"}
}