{
  "type": "Feature",
  "properties": {
    "gn:admin1_code":"7.0",
    "gn:asciiname":"Xibian",
    "gn:country_code":"CN",
    "gn:dem":312,
    "gn:feature_class":"P",
    "gn:feature_code":"PPL",
    "gn:name":"Xibian",
    "gn:population":0,
    "gn:timezone":"Asia/Shanghai",
    "iso:country":"CN",
    "name:und_x_variant":[
        "\u6eaa\u8fb9",
        "Xiaobeidou Famuchang"
    ],
    "name:zho_x_preferred":[
        "\u6eaa\u8fb9"
    ],
    "wof:name":"Xibian",
    "wof:placetype":"locality"
},
  "geometry": {"coordinates":[117.00409999999999,26.907],"type":"Point"}
}