{
  "type": "Feature",
  "properties": {
    "gn:admin1_code":"14.0",
    "gn:asciiname":"Erusongduocun",
    "gn:country_code":"CN",
    "gn:dem":4609,
    "gn:feature_class":"P",
    "gn:feature_code":"PPL",
    "gn:name":"Erusongduocun",
    "gn:population":0,
    "gn:timezone":"Asia/Urumqi",
    "iso:country":"CN",
    "name:zho_x_preferred":[
        "\u4fc4\u5982\u677e\u591a\u6751"
    ],
    "wof:name":"Erusongduocun",
    "wof:placetype":"locality"
},
  "geometry": {"coordinates":[89.7465,31.81858],"type":"Point"}
}