{
  "type": "Feature",
  "properties": {
    "gn:admin1_code":"10",
    "gn:asciiname":"Tiejiangzhuang",
    "gn:country_code":"CN",
    "gn:dem":18,
    "gn:feature_class":"P",
    "gn:feature_code":"PPL",
    "gn:name":"Tiejiangzhuang",
    "gn:population":0,
    "gn:timezone":"Asia/Shanghai",
    "iso:country":"CN",
    "name:zho_x_preferred":[
        "\u94c1\u5320\u5e84"
    ],
    "wof:name":"Tiejiangzhuang",
    "wof:placetype":"locality"
},
  "geometry": {"coordinates":[116.30674999999999,37.94996],"type":"Point"}
}