{
  "type": "Feature",
  "properties": {
    "gn:admin1_code":"16.0",
    "gn:asciiname":"Banbaxia",
    "gn:country_code":"CN",
    "gn:dem":416,
    "gn:feature_class":"P",
    "gn:feature_code":"PPL",
    "gn:name":"Banbaxia",
    "gn:population":0,
    "gn:timezone":"Asia/Shanghai",
    "iso:country":"CN",
    "name:zho_x_preferred":[
        "\u677f\u5c9c\u4e0b"
    ],
    "wof:name":"Banbaxia",
    "wof:placetype":"locality"
},
  "geometry": {"coordinates":[108.381,24.1843],"type":"Point"}
}