{
  "type": "Feature",
  "properties": {
    "gn:admin1_code":"2.0",
    "gn:asciiname":"Xiawuzhai",
    "gn:country_code":"CN",
    "gn:dem":160,
    "gn:feature_class":"P",
    "gn:feature_code":"PPL",
    "gn:name":"Xiawuzhai",
    "gn:population":0,
    "gn:timezone":"Asia/Shanghai",
    "iso:country":"CN",
    "name:zho_x_preferred":[
        "\u4e0b\u5434\u5b85"
    ],
    "wof:name":"Xiawuzhai",
    "wof:placetype":"locality"
},
  "geometry": {"coordinates":[120.42583999999999,29.61987],"type":"Point"}
}