{
  "type": "Feature",
  "properties": {
    "gn:admin1_code":"10.0",
    "gn:asciiname":"Donggouhe",
    "gn:country_code":"CN",
    "gn:dem":17,
    "gn:feature_class":"P",
    "gn:feature_code":"PPL",
    "gn:name":"Donggouhe",
    "gn:population":0,
    "gn:timezone":"Asia/Shanghai",
    "iso:country":"CN",
    "name:zho_x_preferred":[
        "\u4e1c\u6c9f\u6cb3"
    ],
    "wof:name":"Donggouhe",
    "wof:placetype":"locality"
},
  "geometry": {"coordinates":[115.94953,39.21248],"type":"Point"}
}