{
  "type": "Feature",
  "properties": {
    "gn:admin1_code":"5.0",
    "gn:asciiname":"Wufutang",
    "gn:country_code":"CN",
    "gn:dem":175,
    "gn:feature_class":"P",
    "gn:feature_code":"PPL",
    "gn:name":"Wufutang",
    "gn:population":0,
    "gn:timezone":"Asia/Shanghai",
    "iso:country":"CN",
    "name:zho_x_preferred":[
        "\u4e94\u798f\u5802"
    ],
    "wof:name":"Wufutang",
    "wof:placetype":"locality"
},
  "geometry": {"coordinates":[124.99612999999999,44.22041],"type":"Point"}
}