{
  "type": "Feature",
  "properties": {
    "gn:admin1_code":"3.0",
    "gn:asciiname":"Xiaolong",
    "gn:country_code":"CN",
    "gn:dem":280,
    "gn:feature_class":"P",
    "gn:feature_code":"PPLA4",
    "gn:name":"Xiaolong",
    "gn:population":0,
    "gn:timezone":"Asia/Shanghai",
    "iso:country":"CN",
    "name:und_x_variant":[
        "Hsiao-lung",
        "Xiaolong",
        "\u5c0f\u9f99",
        "Xiaolong Zhen",
        "\u5c0f\u9f99\u9547"
    ],
    "wof:name":"Xiaolong",
    "wof:placetype":"locality"
},
  "geometry": {"coordinates":[115.25475,26.68182],"type":"Point"}
}