{
  "type": "Feature",
  "properties": {
    "gn:admin1_code":"24.0",
    "gn:asciiname":"Tongbu",
    "gn:country_code":"CN",
    "gn:dem":1521,
    "gn:feature_class":"P",
    "gn:feature_code":"PPL",
    "gn:name":"Tongbu",
    "gn:population":0,
    "gn:timezone":"Asia/Shanghai",
    "iso:country":"CN",
    "name:zho_x_preferred":[
        "\u540c\u5821"
    ],
    "wof:name":"Tongbu",
    "wof:placetype":"locality"
},
  "geometry": {"coordinates":[111.43857,38.11586],"type":"Point"}
}