{
  "type": "Feature",
  "properties": {
    "gn:admin1_code":"25.0",
    "gn:asciiname":"Chijiazhuangcun",
    "gn:country_code":"CN",
    "gn:dem":35,
    "gn:feature_class":"P",
    "gn:feature_code":"PPL",
    "gn:name":"Chijiazhuangcun",
    "gn:population":0,
    "gn:timezone":"Asia/Shanghai",
    "iso:country":"CN",
    "name:zho_x_preferred":[
        "\u6c60\u5bb6\u5e84\u6751"
    ],
    "wof:name":"Chijiazhuangcun",
    "wof:placetype":"locality"
},
  "geometry": {"coordinates":[120.62072000000001,36.48436],"type":"Point"}
}