{
  "type": "Feature",
  "properties": {
    "gn:admin1_code":"29.0",
    "gn:asciiname":"Yanjiaozhai",
    "gn:country_code":"CN",
    "gn:dem":1602,
    "gn:feature_class":"P",
    "gn:feature_code":"PPL",
    "gn:name":"Yanjiaozhai",
    "gn:population":0,
    "gn:timezone":"Asia/Shanghai",
    "iso:country":"CN",
    "name:zho_x_preferred":[
        "\u5ca9\u811a\u5be8"
    ],
    "wof:name":"Yanjiaozhai",
    "wof:placetype":"locality"
},
  "geometry": {"coordinates":[104.366,26.5615],"type":"Point"}
}