{
  "type": "Feature",
  "properties": {
    "gn:admin1_code":"24",
    "gn:asciiname":"Shangyitang",
    "gn:cc2":"CN",
    "gn:country_code":"CN",
    "gn:dem":1201,
    "gn:feature_class":"P",
    "gn:feature_code":"PPL",
    "gn:name":"Shangyitang",
    "gn:population":0,
    "gn:timezone":"Asia/Shanghai",
    "iso:country":"CN",
    "name:und_x_variant":[
        "Shang-i-t\u2019ang",
        "Shangyitang"
    ],
    "wof:name":"Shangyitang",
    "wof:placetype":"locality"
},
  "geometry": {"coordinates":[111.41583,37.15917],"type":"Point"}
}