{
  "type": "Feature",
  "properties": {
    "gn:admin1_code":"19.0",
    "gn:asciiname":"Huoshigangcun",
    "gn:country_code":"CN",
    "gn:dem":24,
    "gn:feature_class":"P",
    "gn:feature_code":"PPL",
    "gn:name":"Huoshigangcun",
    "gn:population":0,
    "gn:timezone":"Asia/Shanghai",
    "iso:country":"CN",
    "name:zho_x_preferred":[
        "\u706b\u77f3\u5c97\u6751"
    ],
    "wof:name":"Huoshigangcun",
    "wof:placetype":"locality"
},
  "geometry": {"coordinates":[123.003,41.6739],"type":"Point"}
}