{
  "type": "Feature",
  "properties": {
    "gn:admin1_code":"3.0",
    "gn:asciiname":"Quantang",
    "gn:country_code":"CN",
    "gn:dem":48,
    "gn:feature_class":"P",
    "gn:feature_code":"PPL",
    "gn:name":"Quantang",
    "gn:population":0,
    "gn:timezone":"Asia/Shanghai",
    "iso:country":"CN",
    "name:und_x_variant":[
        "\u6cc9\u5858"
    ],
    "wof:name":"Quantang",
    "wof:placetype":"locality"
},
  "geometry": {"coordinates":[115.18138,27.82904000000001],"type":"Point"}
}