{
  "type": "Feature",
  "properties": {
    "gn:admin1_code":"14",
    "gn:asciiname":"Kuqing",
    "gn:country_code":"CN",
    "gn:dem":4333,
    "gn:feature_class":"P",
    "gn:feature_code":"PPL",
    "gn:name":"Kuqing",
    "gn:population":0,
    "gn:timezone":"Asia/Urumqi",
    "iso:country":"CN",
    "name:zho_x_preferred":[
        "\u5e93\u9752"
    ],
    "wof:name":"Kuqing",
    "wof:placetype":"locality"
},
  "geometry": {"coordinates":[89.5249,28.631],"type":"Point"}
}