{
  "type": "Feature",
  "properties": {
    "gn:admin1_code":"1.0",
    "gn:asciiname":"Jinghucun",
    "gn:country_code":"CN",
    "gn:dem":21,
    "gn:feature_class":"P",
    "gn:feature_code":"PPL",
    "gn:name":"Jinghucun",
    "gn:population":0,
    "gn:timezone":"Asia/Shanghai",
    "iso:country":"CN",
    "name:zho_x_preferred":[
        "\u4e95\u6e56\u6751"
    ],
    "wof:name":"Jinghucun",
    "wof:placetype":"locality"
},
  "geometry": {"coordinates":[117.79456999999999,30.93901],"type":"Point"}
}