{
  "type": "Feature",
  "properties": {
    "gn:admin1_code":"14.0",
    "gn:asciiname":"Sainlhai",
    "gn:country_code":"CN",
    "gn:dem":5147,
    "gn:feature_class":"P",
    "gn:feature_code":"PPL",
    "gn:name":"Sainlhai",
    "gn:population":0,
    "gn:timezone":"Asia/Urumqi",
    "iso:country":"CN",
    "name:bod_x_preferred":[
        "Sainlhai"
    ],
    "name:zho_x_preferred":[
        "Shelai"
    ],
    "name:zho_x_variant":[
        "\u820d\u83b1",
        "Mudi Gongshe",
        "\u6728\u5730\u516c\u793e"
    ],
    "wof:name":"Sainlhai",
    "wof:placetype":"locality"
},
  "geometry": {"coordinates":[88.50200000000002,30.602],"type":"Point"}
}