{
  "type": "Feature",
  "properties": {
    "gn:admin1_code":"4.0",
    "gn:asciiname":"Dalou",
    "gn:country_code":"CN",
    "gn:dem":4,
    "gn:feature_class":"P",
    "gn:feature_code":"PPL",
    "gn:name":"Dalou",
    "gn:population":0,
    "gn:timezone":"Asia/Shanghai",
    "iso:country":"CN",
    "name:ceb_x_preferred":[
        "Dalou"
    ],
    "name:deu_x_preferred":[
        "Dalou"
    ],
    "name:fra_x_preferred":[
        "Dalou"
    ],
    "name:rus_x_preferred":[
        "\u0414\u0430\u043b\u0443"
    ],
    "name:zho_x_preferred":[
        "Dalou"
    ],
    "name:zho_x_variant":[
        "\u5927\u697c"
    ],
    "wof:name":"Dalou",
    "wof:placetype":"locality"
},
  "geometry": {"coordinates":[119.89049,33.91943],"type":"Point"}
}