{
  "type": "Feature",
  "properties": {
    "gn:admin1_code":"18.0",
    "gn:asciiname":"Dimei",
    "gn:country_code":"CN",
    "gn:dem":644,
    "gn:feature_class":"P",
    "gn:feature_code":"PPL",
    "gn:name":"Dimei",
    "gn:population":0,
    "gn:timezone":"Asia/Shanghai",
    "iso:country":"CN",
    "name:zho_x_preferred":[
        "\u5730\u59b9"
    ],
    "wof:name":"Dimei",
    "wof:placetype":"locality"
},
  "geometry": {"coordinates":[109.123,27.1235],"type":"Point"}
}