{
  "type": "Feature",
  "properties": {
    "gn:admin1_code":"29.0",
    "gn:asciiname":"Wenping",
    "gn:country_code":"CN",
    "gn:dem":2019,
    "gn:feature_class":"P",
    "gn:feature_code":"PPL",
    "gn:name":"Wenping",
    "gn:population":0,
    "gn:timezone":"Asia/Shanghai",
    "iso:country":"CN",
    "name:zho_x_preferred":[
        "\u6587\u5e73"
    ],
    "wof:name":"Wenping",
    "wof:placetype":"locality"
},
  "geometry": {"coordinates":[100.05,24.7688],"type":"Point"}
}