{
  "type": "Feature",
  "properties": {
    "gn:admin1_code":"32.0",
    "gn:asciiname":"Gaofengsi",
    "gn:country_code":"CN",
    "gn:dem":317,
    "gn:feature_class":"P",
    "gn:feature_code":"PPL",
    "gn:name":"Gaofengsi",
    "gn:population":0,
    "gn:timezone":"Asia/Shanghai",
    "iso:country":"CN",
    "name:zho_x_preferred":[
        "\u9ad8\u5cf0\u5bfa"
    ],
    "wof:name":"Gaofengsi",
    "wof:placetype":"locality"
},
  "geometry": {"coordinates":[104.96698000000001,29.50358],"type":"Point"}
}