{
  "type": "Feature",
  "properties": {
    "gn:admin1_code":"6.0",
    "gn:asciiname":"Rediduo",
    "gn:country_code":"CN",
    "gn:dem":3948,
    "gn:feature_class":"P",
    "gn:feature_code":"PPL",
    "gn:name":"Rediduo",
    "gn:population":0,
    "gn:timezone":"Asia/Urumqi",
    "iso:country":"CN",
    "name:zho_x_preferred":[
        "\u70ed\u5730\u591a"
    ],
    "wof:name":"Rediduo",
    "wof:placetype":"locality"
},
  "geometry": {"coordinates":[96.80817,32.23429],"type":"Point"}
}