{
  "type": "Feature",
  "properties": {
    "gn:admin1_code":"12",
    "gn:asciiname":"Leigong",
    "gn:country_code":"CN",
    "gn:dem":116,
    "gn:feature_class":"P",
    "gn:feature_code":"PPLA4",
    "gn:name":"Leigong",
    "gn:population":0,
    "gn:timezone":"Asia/Shanghai",
    "iso:country":"CN",
    "name:deu_x_preferred":[
        "Lei Gong"
    ],
    "name:fra_x_preferred":[
        "Lei Gong"
    ],
    "name:nld_x_preferred":[
        "Lei Gong"
    ],
    "name:nor_x_preferred":[
        "Lei Gong"
    ],
    "name:pol_x_preferred":[
        "Leigong"
    ],
    "name:swe_x_preferred":[
        "Lei Kung"
    ],
    "name:tha_x_preferred":[
        "\u0e25\u0e38\u0e48\u0e22\u0e01\u0e07"
    ],
    "name:und_x_variant":[
        "Leigongdian",
        "Lei-kung-tien",
        "\u96f7\u516c",
        "Leigong Zhen",
        "\u96f7\u516c\u9547"
    ],
    "name:vie_x_preferred":[
        "L\u00f4i C\u00f4ng"
    ],
    "wof:name":"Leigong",
    "wof:placetype":"locality"
},
  "geometry": {"coordinates":[113.51111000000002,31.29355],"type":"Point"}
}