{
  "type": "Feature",
  "properties": {
    "gn:admin1_code":"29.0",
    "gn:asciiname":"Sanzhongshan",
    "gn:country_code":"CN",
    "gn:dem":2664,
    "gn:feature_class":"P",
    "gn:feature_code":"PPL",
    "gn:name":"Sanzhongshan",
    "gn:population":0,
    "gn:timezone":"Asia/Shanghai",
    "iso:country":"CN",
    "name:zho_x_preferred":[
        "\u4e09\u91cd\u5c71"
    ],
    "wof:name":"Sanzhongshan",
    "wof:placetype":"locality"
},
  "geometry": {"coordinates":[99.4297,26.3983],"type":"Point"}
}