{
  "type": "Feature",
  "properties": {
    "gn:admin1_code":"29.0",
    "gn:asciiname":"Xiaojiezi",
    "gn:country_code":"CN",
    "gn:dem":1871,
    "gn:feature_class":"P",
    "gn:feature_code":"PPL",
    "gn:name":"Xiaojiezi",
    "gn:population":0,
    "gn:timezone":"Asia/Shanghai",
    "iso:country":"CN",
    "name:zho_x_preferred":[
        "\u5c0f\u8857\u5b50"
    ],
    "wof:name":"Xiaojiezi",
    "wof:placetype":"locality"
},
  "geometry": {"coordinates":[104.063,24.6002],"type":"Point"}
}