{
  "type": "Feature",
  "properties": {
    "gn:admin1_code":"29",
    "gn:asciiname":"Zhewan",
    "gn:country_code":"CN",
    "gn:dem":1833,
    "gn:feature_class":"P",
    "gn:feature_code":"PPL",
    "gn:name":"Zhewan",
    "gn:population":0,
    "gn:timezone":"Asia/Shanghai",
    "iso:country":"CN",
    "name:zho_x_preferred":[
        "\u8005\u6e7e"
    ],
    "wof:name":"Zhewan",
    "wof:placetype":"locality"
},
  "geometry": {"coordinates":[102.68637,24.17883],"type":"Point"}
}