{
  "type": "Feature",
  "properties": {
    "gn:admin1_code":"12.0",
    "gn:asciiname":"Xueping",
    "gn:country_code":"CN",
    "gn:dem":821,
    "gn:feature_class":"P",
    "gn:feature_code":"PPLA4",
    "gn:name":"Xueping",
    "gn:population":0,
    "gn:timezone":"Asia/Shanghai",
    "iso:country":"CN",
    "name:und_x_variant":[
        "Hs\u00fceh-p\u2019ing",
        "Xueping",
        "Xueping Zhen"
    ],
    "name:zho_x_preferred":[
        "\u859b\u576a"
    ],
    "name:zho_x_variant":[
        "\u859b\u576a\u9547"
    ],
    "wof:name":"Xueping",
    "wof:placetype":"locality"
},
  "geometry": {"coordinates":[111.66716,31.63649],"type":"Point"}
}