{
  "type": "Feature",
  "properties": {
    "gn:admin1_code":"33.0",
    "gn:asciiname":"Lugaoba",
    "gn:country_code":"CN",
    "gn:dem":1238,
    "gn:feature_class":"P",
    "gn:feature_code":"PPL",
    "gn:name":"Lugaoba",
    "gn:population":0,
    "gn:timezone":"Asia/Shanghai",
    "iso:country":"CN",
    "name:zho_x_preferred":[
        "\u82a6\u7a3f\u575d"
    ],
    "wof:name":"Lugaoba",
    "wof:placetype":"locality"
},
  "geometry": {"coordinates":[108.55728999999999,28.93604],"type":"Point"}
}