{
  "type": "Feature",
  "properties": {
    "gn:admin1_code":"9.0",
    "gn:asciiname":"Chaoge",
    "gn:country_code":"CN",
    "gn:dem":73,
    "gn:feature_class":"P",
    "gn:feature_code":"PPLA3",
    "gn:name":"Chaoge",
    "gn:population":0,
    "gn:timezone":"Asia/Shanghai",
    "iso:country":"CN",
    "name:und_x_variant":[
        "Ch\u2019i",
        "Zhaoge",
        "Ch\u2019i-hsien",
        "Ch\u2019ao-ko",
        "Ch\u2019ao-ko-chen",
        "Qixian",
        "Chaoge"
    ],
    "name:zho_x_preferred":[
        "\u671d\u6b4c"
    ],
    "wof:name":"Chaoge",
    "wof:placetype":"locality"
},
  "geometry": {"coordinates":[114.18861,35.605],"type":"Point"}
}