{
  "type": "Feature",
  "properties": {
    "gn:admin1_code":"4.0",
    "gn:asciiname":"Qiansixuzi",
    "gn:country_code":"CN",
    "gn:dem":57,
    "gn:feature_class":"P",
    "gn:feature_code":"PPL",
    "gn:name":"Qiansixuzi",
    "gn:population":0,
    "gn:timezone":"Asia/Shanghai",
    "iso:country":"CN",
    "name:zho_x_preferred":[
        "\u94c5\u4e1d\u5729\u5b50"
    ],
    "wof:name":"Qiansixuzi",
    "wof:placetype":"locality"
},
  "geometry": {"coordinates":[118.56801000000002,32.76863],"type":"Point"}
}