{
  "type": "Feature",
  "properties": {
    "gn:admin1_code":"3.0",
    "gn:asciiname":"Dengjia",
    "gn:country_code":"CN",
    "gn:dem":46,
    "gn:feature_class":"P",
    "gn:feature_code":"PPL",
    "gn:name":"Dengjia",
    "gn:population":0,
    "gn:timezone":"Asia/Shanghai",
    "iso:country":"CN",
    "name:und_x_variant":[
        "\u9093\u5bb6"
    ],
    "wof:name":"Dengjia",
    "wof:placetype":"locality"
},
  "geometry": {"coordinates":[116.17031,27.84111],"type":"Point"}
}