{
  "type": "Feature",
  "properties": {
    "gn:admin1_code":"16.0",
    "gn:asciiname":"Longpeng",
    "gn:country_code":"CN",
    "gn:dem":160,
    "gn:feature_class":"P",
    "gn:feature_code":"PPL",
    "gn:name":"Longpeng",
    "gn:population":0,
    "gn:timezone":"Asia/Shanghai",
    "iso:country":"CN",
    "name:zho_x_preferred":[
        "\u9f99\u9e4f"
    ],
    "wof:name":"Longpeng",
    "wof:placetype":"locality"
},
  "geometry": {"coordinates":[109.54300000000001,23.3771],"type":"Point"}
}