{
  "type": "Feature",
  "properties": {
    "gn:admin1_code":"11.0",
    "gn:asciiname":"Egongtang",
    "gn:country_code":"CN",
    "gn:dem":1214,
    "gn:feature_class":"P",
    "gn:feature_code":"PPL",
    "gn:name":"Egongtang",
    "gn:population":0,
    "gn:timezone":"Asia/Shanghai",
    "iso:country":"CN",
    "name:zho_x_preferred":[
        "\u9e45\u516c\u5858"
    ],
    "wof:name":"Egongtang",
    "wof:placetype":"locality"
},
  "geometry": {"coordinates":[112.87138,25.48025],"type":"Point"}
}