{
  "type": "Feature",
  "properties": {
    "gn:admin1_code":"21.0",
    "gn:asciiname":"Jiutiaogou",
    "gn:country_code":"CN",
    "gn:dem":2104,
    "gn:feature_class":"P",
    "gn:feature_code":"PPL",
    "gn:name":"Jiutiaogou",
    "gn:population":0,
    "gn:timezone":"Asia/Shanghai",
    "iso:country":"CN",
    "name:zho_x_preferred":[
        "\u4e5d\u6761\u6c9f"
    ],
    "wof:name":"Jiutiaogou",
    "wof:placetype":"locality"
},
  "geometry": {"coordinates":[105.80800000000001,36.1044],"type":"Point"}
}