{
  "type": "Feature",
  "properties": {
    "gn:admin1_code":"19.0",
    "gn:asciiname":"Ailingao",
    "gn:country_code":"CN",
    "gn:dem":306,
    "gn:feature_class":"P",
    "gn:feature_code":"PPL",
    "gn:name":"Ailingao",
    "gn:population":0,
    "gn:timezone":"Asia/Shanghai",
    "iso:country":"CN",
    "name:und_x_variant":[
        "\u827e\u6797\u768b"
    ],
    "name:zho_x_preferred":[
        "\u827e\u6797\u768b"
    ],
    "wof:name":"Ailingao",
    "wof:placetype":"locality"
},
  "geometry": {"coordinates":[121.85111000000001,42.36108],"type":"Point"}
}