{
  "type": "Feature",
  "properties": {
    "gn:admin1_code":"19.0",
    "gn:asciiname":"Majicun",
    "gn:country_code":"CN",
    "gn:dem":515,
    "gn:feature_class":"P",
    "gn:feature_code":"PPL",
    "gn:name":"Majicun",
    "gn:population":0,
    "gn:timezone":"Asia/Shanghai",
    "iso:country":"CN",
    "name:zho_x_preferred":[
        "\u9a6c\u9aa5\u6751"
    ],
    "wof:name":"Majicun",
    "wof:placetype":"locality"
},
  "geometry": {"coordinates":[124.04900000000001,41.0963],"type":"Point"}
}