{
  "type": "Feature",
  "properties": {
    "gn:admin1_code":"2.0",
    "gn:asciiname":"Xiachangkeng",
    "gn:country_code":"CN",
    "gn:dem":30,
    "gn:feature_class":"P",
    "gn:feature_code":"PPL",
    "gn:name":"Xiachangkeng",
    "gn:population":0,
    "gn:timezone":"Asia/Shanghai",
    "iso:country":"CN",
    "name:zho_x_preferred":[
        "\u4e0b\u957f\u5751"
    ],
    "wof:name":"Xiachangkeng",
    "wof:placetype":"locality"
},
  "geometry": {"coordinates":[122.22803999999999,29.83227],"type":"Point"}
}