{
  "type": "Feature",
  "properties": {
    "gn:admin1_code":"9.0",
    "gn:asciiname":"Guanxizhuang",
    "gn:country_code":"CN",
    "gn:dem":118,
    "gn:feature_class":"P",
    "gn:feature_code":"PPL",
    "gn:name":"Guanxizhuang",
    "gn:population":0,
    "gn:timezone":"Asia/Shanghai",
    "iso:country":"CN",
    "name:zho_x_preferred":[
        "\u5173\u897f\u5e84"
    ],
    "wof:name":"Guanxizhuang",
    "wof:placetype":"locality"
},
  "geometry": {"coordinates":[113.13039999999999,33.64543],"type":"Point"}
}