{
  "type": "Feature",
  "properties": {
    "gn:admin1_code":"16.0",
    "gn:asciiname":"Guan'an",
    "gn:country_code":"CN",
    "gn:dem":462,
    "gn:feature_class":"P",
    "gn:feature_code":"PPL",
    "gn:name":"Guan\u2019an",
    "gn:population":0,
    "gn:timezone":"Asia/Shanghai",
    "iso:country":"CN",
    "name:und_x_variant":[
        "Guan\u2019an"
    ],
    "name:zho_x_preferred":[
        "\u5173\u5b89"
    ],
    "wof:name":"Guan'an",
    "wof:placetype":"locality"
},
  "geometry": {"coordinates":[108.389,24.9389],"type":"Point"}
}