{
  "type": "Feature",
  "properties": {
    "gn:admin1_code":"26.0",
    "gn:asciiname":"Xiaochuanzicun",
    "gn:country_code":"CN",
    "gn:dem":1142,
    "gn:feature_class":"P",
    "gn:feature_code":"PPL",
    "gn:name":"Xiaochuanzicun",
    "gn:population":0,
    "gn:timezone":"Asia/Shanghai",
    "iso:country":"CN",
    "name:und_x_variant":[
        "\u5c0f\u5ddd\u5b50\u6751"
    ],
    "wof:name":"Xiaochuanzicun",
    "wof:placetype":"locality"
},
  "geometry": {"coordinates":[107.12909999999999,33.71974],"type":"Point"}
}