{
  "type": "Feature",
  "properties": {
    "gn:admin1_code":"30",
    "gn:asciiname":"Sanhuazhen",
    "gn:country_code":"CN",
    "gn:dem":118,
    "gn:feature_class":"P",
    "gn:feature_code":"PPL",
    "gn:name":"Sanhuazhen",
    "gn:population":0,
    "gn:timezone":"Asia/Shanghai",
    "iso:country":"CN",
    "name:und_x_variant":[
        "San-hua-chen",
        "Sanhuazhen",
        "\u4e09\u534e\u9547"
    ],
    "wof:name":"Sanhuazhen",
    "wof:placetype":"locality"
},
  "geometry": {"coordinates":[114.0351,24.31043],"type":"Point"}
}