{
  "type": "Feature",
  "properties": {
    "gn:admin1_code":"4.0",
    "gn:asciiname":"Longmengang",
    "gn:country_code":"CN",
    "gn:dem":4,
    "gn:feature_class":"P",
    "gn:feature_code":"PPL",
    "gn:name":"Longmengang",
    "gn:population":0,
    "gn:timezone":"Asia/Shanghai",
    "iso:country":"CN",
    "name:zho_x_preferred":[
        "\u9f99\u95e8\u6e2f"
    ],
    "wof:name":"Longmengang",
    "wof:placetype":"locality"
},
  "geometry": {"coordinates":[119.87526,32.03768],"type":"Point"}
}