{
  "type": "Feature",
  "properties": {
    "gn:admin1_code":"3",
    "gn:asciiname":"Shijiang",
    "gn:country_code":"CN",
    "gn:dem":176,
    "gn:feature_class":"P",
    "gn:feature_code":"PPL",
    "gn:name":"Shijiang",
    "gn:population":0,
    "gn:timezone":"Asia/Shanghai",
    "iso:country":"CN",
    "name:zho_x_preferred":[
        "\u5e02\u6c5f"
    ],
    "wof:name":"Shijiang",
    "wof:placetype":"locality"
},
  "geometry": {"coordinates":[113.90300000000001,27.041],"type":"Point"}
}