{
  "type": "Feature",
  "properties": {
    "gn:admin1_code":"24.0",
    "gn:asciiname":"Pucun",
    "gn:country_code":"CN",
    "gn:dem":751,
    "gn:feature_class":"P",
    "gn:feature_code":"PPL",
    "gn:name":"Pucun",
    "gn:population":0,
    "gn:timezone":"Asia/Shanghai",
    "iso:country":"CN",
    "name:zho_x_preferred":[
        "\u6734\u6751"
    ],
    "wof:name":"Pucun",
    "wof:placetype":"locality"
},
  "geometry": {"coordinates":[112.26815000000001,37.34131],"type":"Point"}
}