{
  "type": "Feature",
  "properties": {
    "gn:admin1_code":"7.0",
    "gn:asciiname":"Zhulinwei",
    "gn:country_code":"CN",
    "gn:dem":177,
    "gn:feature_class":"P",
    "gn:feature_code":"PPL",
    "gn:name":"Zhulinwei",
    "gn:population":0,
    "gn:timezone":"Asia/Shanghai",
    "iso:country":"CN",
    "name:und_x_variant":[
        "\u6731\u6797\u5c3e"
    ],
    "name:zho_x_preferred":[
        "\u6731\u6797\u5c3e"
    ],
    "wof:name":"Zhulinwei",
    "wof:placetype":"locality"
},
  "geometry": {"coordinates":[118.18885,26.02843],"type":"Point"}
}