{
  "type": "Feature",
  "properties": {
    "gn:admin1_code":"4.0",
    "gn:asciiname":"Hexingcun",
    "gn:country_code":"CN",
    "gn:dem":18,
    "gn:feature_class":"P",
    "gn:feature_code":"PPL",
    "gn:name":"Hexingcun",
    "gn:population":0,
    "gn:timezone":"Asia/Shanghai",
    "iso:country":"CN",
    "name:zho_x_preferred":[
        "\u5408\u5174\u6751"
    ],
    "wof:name":"Hexingcun",
    "wof:placetype":"locality"
},
  "geometry": {"coordinates":[118.40833000000001,33.72351],"type":"Point"}
}