{
  "type": "Feature",
  "properties": {
    "gn:admin1_code":"11",
    "gn:asciiname":"Lanshixu",
    "gn:cc2":"CN",
    "gn:country_code":"CN",
    "gn:dem":669,
    "gn:feature_class":"P",
    "gn:feature_code":"PPL",
    "gn:name":"Lanshixu",
    "gn:population":0,
    "gn:timezone":"Asia/Shanghai",
    "iso:country":"CN",
    "name:und_x_variant":[
        "Lanshi",
        "Lan-shih",
        "Lanshixu"
    ],
    "wof:name":"Lanshixu",
    "wof:placetype":"locality"
},
  "geometry": {"coordinates":[113.58138999999998,26.15167000000001],"type":"Point"}
}