{
  "type": "Feature",
  "properties": {
    "gn:admin1_code":"26.0",
    "gn:asciiname":"Zuojiawan",
    "gn:country_code":"CN",
    "gn:dem":812,
    "gn:feature_class":"P",
    "gn:feature_code":"PPL",
    "gn:name":"Zuojiawan",
    "gn:population":0,
    "gn:timezone":"Asia/Shanghai",
    "iso:country":"CN",
    "name:zho_x_preferred":[
        "\u5de6\u5bb6\u6e7e"
    ],
    "wof:name":"Zuojiawan",
    "wof:placetype":"locality"
},
  "geometry": {"coordinates":[108.49306,33.17105],"type":"Point"}
}