{
  "type": "Feature",
  "properties": {
    "gn:admin1_code":"30.0",
    "gn:asciiname":"Tangongye",
    "gn:country_code":"CN",
    "gn:dem":37,
    "gn:feature_class":"P",
    "gn:feature_code":"PPL",
    "gn:name":"Tangongye",
    "gn:population":0,
    "gn:timezone":"Asia/Shanghai",
    "iso:country":"CN",
    "name:zho_x_preferred":[
        "\u8c2d\u516c\u7237"
    ],
    "wof:name":"Tangongye",
    "wof:placetype":"locality"
},
  "geometry": {"coordinates":[114.38791999999999,23.07161],"type":"Point"}
}