{
  "type": "Feature",
  "properties": {
    "gn:admin1_code":"26.0",
    "gn:asciiname":"Zhaichengmao",
    "gn:country_code":"CN",
    "gn:dem":1208,
    "gn:feature_class":"P",
    "gn:feature_code":"PPL",
    "gn:name":"Zhaichengmao",
    "gn:population":0,
    "gn:timezone":"Asia/Shanghai",
    "iso:country":"CN",
    "name:zho_x_preferred":[
        "\u5be8\u57ce\u5cc1"
    ],
    "wof:name":"Zhaichengmao",
    "wof:placetype":"locality"
},
  "geometry": {"coordinates":[109.16007,37.85191],"type":"Point"}
}