{
  "type": "Feature",
  "properties": {
    "gn:admin1_code":"26.0",
    "gn:asciiname":"Nanqiangzhuang",
    "gn:country_code":"CN",
    "gn:dem":692,
    "gn:feature_class":"P",
    "gn:feature_code":"PPL",
    "gn:name":"Nanqiangzhuang",
    "gn:population":0,
    "gn:timezone":"Asia/Shanghai",
    "iso:country":"CN",
    "name:zho_x_preferred":[
        "\u5357\u5f3a\u5e84"
    ],
    "wof:name":"Nanqiangzhuang",
    "wof:placetype":"locality"
},
  "geometry": {"coordinates":[110.41061000000001,35.55376],"type":"Point"}
}