{
  "type": "Feature",
  "properties": {
    "gn:admin1_code":"1.0",
    "gn:asciiname":"Gongshanfang",
    "gn:country_code":"CN",
    "gn:dem":47,
    "gn:feature_class":"P",
    "gn:feature_code":"PPL",
    "gn:name":"Gongshanfang",
    "gn:population":0,
    "gn:timezone":"Asia/Shanghai",
    "iso:country":"CN",
    "name:zho_x_preferred":[
        "\u5de5\u5c71\u574a"
    ],
    "wof:name":"Gongshanfang",
    "wof:placetype":"locality"
},
  "geometry": {"coordinates":[118.22669,30.92689],"type":"Point"}
}