{
  "type": "Feature",
  "properties": {
    "gn:admin1_code":"2.0",
    "gn:asciiname":"Nanwukou",
    "gn:country_code":"CN",
    "gn:dem":178,
    "gn:feature_class":"P",
    "gn:feature_code":"PPL",
    "gn:name":"Nanwukou",
    "gn:population":0,
    "gn:timezone":"Asia/Shanghai",
    "iso:country":"CN",
    "name:zho_x_preferred":[
        "\u5357\u575e\u53e3"
    ],
    "wof:name":"Nanwukou",
    "wof:placetype":"locality"
},
  "geometry": {"coordinates":[118.37979,28.96279],"type":"Point"}
}