{
  "type": "Feature",
  "properties": {
    "gn:admin1_code":"30",
    "gn:asciiname":"Ebu",
    "gn:country_code":"CN",
    "gn:dem":13,
    "gn:feature_class":"P",
    "gn:feature_code":"PPLA4",
    "gn:name":"Ebu",
    "gn:population":0,
    "gn:timezone":"Asia/Shanghai",
    "iso:country":"CN",
    "name:und_x_variant":[
        "Ebu Zhen",
        "\u9e45\u57e0\u9547"
    ],
    "name:zho_x_preferred":[
        "\u9e45\u57e0"
    ],
    "wof:name":"Ebu",
    "wof:placetype":"locality"
},
  "geometry": {"coordinates":[114.9943,22.83197],"type":"Point"}
}