{
  "type": "Feature",
  "properties": {
    "gn:admin1_code":"20.0",
    "gn:asciiname":"Danangou",
    "gn:country_code":"CN",
    "gn:dem":1700,
    "gn:feature_class":"P",
    "gn:feature_code":"PPL",
    "gn:name":"Danangou",
    "gn:population":0,
    "gn:timezone":"Asia/Shanghai",
    "iso:country":"CN",
    "name:und_x_variant":[
        "\u5927\u5357\u6c9f"
    ],
    "wof:name":"Danangou",
    "wof:placetype":"locality"
},
  "geometry": {"coordinates":[110.96718,41.27367],"type":"Point"}
}