{
  "type": "Feature",
  "properties": {
    "gn:admin1_code":"8.0",
    "gn:asciiname":"Hefacun",
    "gn:country_code":"CN",
    "gn:dem":225,
    "gn:feature_class":"P",
    "gn:feature_code":"PPL",
    "gn:name":"Hefacun",
    "gn:population":0,
    "gn:timezone":"Asia/Shanghai",
    "iso:country":"CN",
    "name:zho_x_preferred":[
        "\u5408\u53d1\u6751"
    ],
    "wof:name":"Hefacun",
    "wof:placetype":"locality"
},
  "geometry": {"coordinates":[125.10308000000001,47.93148],"type":"Point"}
}