{
  "type": "Feature",
  "properties": {
    "gn:admin1_code":"29.0",
    "gn:asciiname":"Chengtang",
    "gn:country_code":"CN",
    "gn:dem":2018,
    "gn:feature_class":"P",
    "gn:feature_code":"PPL",
    "gn:name":"Chengtang",
    "gn:population":0,
    "gn:timezone":"Asia/Shanghai",
    "iso:country":"CN",
    "name:zho_x_preferred":[
        "\u6210\u5858"
    ],
    "wof:name":"Chengtang",
    "wof:placetype":"locality"
},
  "geometry": {"coordinates":[99.84310000000001,25.0486],"type":"Point"}
}