{
  "type": "Feature",
  "properties": {
    "gn:admin1_code":"29.0",
    "gn:asciiname":"Madongshu",
    "gn:country_code":"CN",
    "gn:dem":1552,
    "gn:feature_class":"P",
    "gn:feature_code":"PPL",
    "gn:name":"Madongshu",
    "gn:population":0,
    "gn:timezone":"Asia/Shanghai",
    "iso:country":"CN",
    "name:zho_x_preferred":[
        "\u9ebb\u680b\u6811"
    ],
    "wof:name":"Madongshu",
    "wof:placetype":"locality"
},
  "geometry": {"coordinates":[100.97799999999999,24.8444],"type":"Point"}
}