{
  "type": "Feature",
  "properties": {
    "gn:admin1_code":"6.0",
    "gn:asciiname":"Jiawuduo",
    "gn:country_code":"CN",
    "gn:dem":4044,
    "gn:feature_class":"P",
    "gn:feature_code":"PPL",
    "gn:name":"Jiawuduo",
    "gn:population":0,
    "gn:timezone":"Asia/Urumqi",
    "iso:country":"CN",
    "name:zho_x_preferred":[
        "\u52a0\u4e4c\u591a"
    ],
    "wof:name":"Jiawuduo",
    "wof:placetype":"locality"
},
  "geometry": {"coordinates":[96.21704,32.58985999999999],"type":"Point"}
}