{
  "type": "Feature",
  "properties": {
    "gn:admin1_code":"8.0",
    "gn:asciiname":"Linsencun",
    "gn:country_code":"CN",
    "gn:dem":152,
    "gn:feature_class":"P",
    "gn:feature_code":"PPL",
    "gn:name":"Linsencun",
    "gn:population":0,
    "gn:timezone":"Asia/Shanghai",
    "iso:country":"CN",
    "name:zho_x_preferred":[
        "\u6797\u68ee\u6751"
    ],
    "wof:name":"Linsencun",
    "wof:placetype":"locality"
},
  "geometry": {"coordinates":[126.21781,46.08324],"type":"Point"}
}