{
  "type": "Feature",
  "properties": {
    "gn:admin1_code":"29.0",
    "gn:asciiname":"Baoguqing",
    "gn:country_code":"CN",
    "gn:dem":2136,
    "gn:feature_class":"P",
    "gn:feature_code":"PPL",
    "gn:name":"Baoguqing",
    "gn:population":0,
    "gn:timezone":"Asia/Shanghai",
    "iso:country":"CN",
    "name:zho_x_preferred":[
        "\u5305\u8c37\u7b90"
    ],
    "wof:name":"Baoguqing",
    "wof:placetype":"locality"
},
  "geometry": {"coordinates":[103.425,26.81],"type":"Point"}
}