{
  "type": "Feature",
  "properties": {
    "gn:admin1_code":"7.0",
    "gn:asciiname":"Shangzhuo",
    "gn:country_code":"CN",
    "gn:dem":261,
    "gn:feature_class":"P",
    "gn:feature_code":"PPL",
    "gn:name":"Shangzhuo",
    "gn:population":0,
    "gn:timezone":"Asia/Shanghai",
    "iso:country":"CN",
    "name:zho_x_preferred":[
        "\u4e0a\u6fef"
    ],
    "wof:name":"Shangzhuo",
    "wof:placetype":"locality"
},
  "geometry": {"coordinates":[116.36806,25.36679],"type":"Point"}
}