{
  "type": "Feature",
  "properties": {
    "gn:admin1_code":"8.0",
    "gn:asciiname":"Laoyefu",
    "gn:country_code":"CN",
    "gn:dem":247,
    "gn:feature_class":"P",
    "gn:feature_code":"PPL",
    "gn:name":"Laoyefu",
    "gn:population":0,
    "gn:timezone":"Asia/Shanghai",
    "iso:country":"CN",
    "name:zho_x_preferred":[
        "\u8001\u7237\u5e9c"
    ],
    "wof:name":"Laoyefu",
    "wof:placetype":"locality"
},
  "geometry": {"coordinates":[127.86218999999998,46.70091],"type":"Point"}
}