{
  "type": "Feature",
  "properties": {
    "gn:admin1_code":"3.0",
    "gn:asciiname":"Daquanlong",
    "gn:country_code":"CN",
    "gn:dem":91,
    "gn:feature_class":"P",
    "gn:feature_code":"PPL",
    "gn:name":"Daquanlong",
    "gn:population":0,
    "gn:timezone":"Asia/Shanghai",
    "iso:country":"CN",
    "name:und_x_variant":[
        "\u5927\u6cc9\u5785"
    ],
    "wof:name":"Daquanlong",
    "wof:placetype":"locality"
},
  "geometry": {"coordinates":[115.41930000000001,29.45762],"type":"Point"}
}