{
  "type": "Feature",
  "properties": {
    "gn:admin1_code":"12.0",
    "gn:asciiname":"Huanglong",
    "gn:country_code":"CN",
    "gn:dem":182,
    "gn:feature_class":"P",
    "gn:feature_code":"PPLA4",
    "gn:name":"Huanglong",
    "gn:population":0,
    "gn:timezone":"Asia/Shanghai",
    "iso:country":"CN",
    "name:und_x_variant":[
        "Huanglong Zhen"
    ],
    "name:zho_x_preferred":[
        "\u9ec4\u9f99"
    ],
    "name:zho_x_variant":[
        "\u9ec4\u9f99\u9547"
    ],
    "wof:name":"Huanglong",
    "wof:placetype":"locality"
},
  "geometry": {"coordinates":[110.56492,32.68281],"type":"Point"}
}