{
  "type": "Feature",
  "properties": {
    "gn:admin1_code":"15.0",
    "gn:asciiname":"Yaha",
    "gn:country_code":"CN",
    "gn:dem":2194,
    "gn:feature_class":"P",
    "gn:feature_code":"PPL",
    "gn:name":"Yaha",
    "gn:population":0,
    "gn:timezone":"Asia/Shanghai",
    "iso:country":"CN",
    "name:und_x_variant":[
        "\u4e9a\u54c8"
    ],
    "name:zho_x_preferred":[
        "\u4e9a\u54c8"
    ],
    "wof:name":"Yaha",
    "wof:placetype":"locality"
},
  "geometry": {"coordinates":[104.33225,33.61551],"type":"Point"}
}