{
  "type": "Feature",
  "properties": {
    "gn:admin1_code":"9",
    "gn:asciiname":"Liuguanmiao",
    "gn:country_code":"CN",
    "gn:dem":48,
    "gn:feature_class":"P",
    "gn:feature_code":"PPL",
    "gn:name":"Liuguanmiao",
    "gn:population":0,
    "gn:timezone":"Asia/Shanghai",
    "iso:country":"CN",
    "name:zho_x_preferred":[
        "\u5218\u5173\u5e99"
    ],
    "wof:name":"Liuguanmiao",
    "wof:placetype":"locality"
},
  "geometry": {"coordinates":[115.669,34.2753],"type":"Point"}
}