{
  "type": "Feature",
  "properties": {
    "gn:admin1_code":"11",
    "gn:asciiname":"Zhengxidang",
    "gn:country_code":"CN",
    "gn:dem":283,
    "gn:feature_class":"P",
    "gn:feature_code":"PPL",
    "gn:name":"Zhengxidang",
    "gn:population":0,
    "gn:timezone":"Asia/Shanghai",
    "iso:country":"CN",
    "name:zho_x_preferred":[
        "\u6b63\u6eaa\u51fc"
    ],
    "wof:name":"Zhengxidang",
    "wof:placetype":"locality"
},
  "geometry": {"coordinates":[111.12073999999998,27.7264],"type":"Point"}
}