{
  "type": "Feature",
  "properties": {
    "gn:admin1_code":"8.0",
    "gn:asciiname":"Gongjia Fenfang",
    "gn:country_code":"CN",
    "gn:dem":185,
    "gn:feature_class":"P",
    "gn:feature_code":"PPL",
    "gn:name":"Gongjia Fenfang",
    "gn:population":0,
    "gn:timezone":"Asia/Shanghai",
    "iso:country":"CN",
    "name:zho_x_preferred":[
        "\u5bab\u5bb6\u7c89\u574a"
    ],
    "wof:name":"Gongjia Fenfang",
    "wof:placetype":"locality"
},
  "geometry": {"coordinates":[126.15748000000001,46.73714],"type":"Point"}
}