{
  "type": "Feature",
  "properties": {
    "gn:admin1_code":"18",
    "gn:asciiname":"Xiaganba",
    "gn:country_code":"CN",
    "gn:dem":910,
    "gn:feature_class":"P",
    "gn:feature_code":"PPL",
    "gn:name":"Xiaganba",
    "gn:population":0,
    "gn:timezone":"Asia/Shanghai",
    "iso:country":"CN",
    "name:zho_x_preferred":[
        "\u4e0b\u5e72\u575d"
    ],
    "wof:name":"Xiaganba",
    "wof:placetype":"locality"
},
  "geometry": {"coordinates":[107.35899999999999,27.1995],"type":"Point"}
}