{
  "type": "Feature",
  "properties": {
    "gn:admin1_code":"19",
    "gn:asciiname":"Leshancun",
    "gn:country_code":"CN",
    "gn:dem":190,
    "gn:feature_class":"P",
    "gn:feature_code":"PPL",
    "gn:name":"Leshancun",
    "gn:population":0,
    "gn:timezone":"Asia/Shanghai",
    "iso:country":"CN",
    "name:und_x_variant":[
        "Leshan"
    ],
    "name:zho_x_preferred":[
        "\u4e50\u5584\u6751"
    ],
    "wof:name":"Leshancun",
    "wof:placetype":"locality"
},
  "geometry": {"coordinates":[124.65746,42.74515],"type":"Point"}
}