{
  "type": "Feature",
  "properties": {
    "gn:admin1_code":"10",
    "gn:asciiname":"Qiandongjingzi",
    "gn:country_code":"CN",
    "gn:dem":1388,
    "gn:feature_class":"P",
    "gn:feature_code":"PPL",
    "gn:name":"Qiandongjingzi",
    "gn:population":0,
    "gn:timezone":"Asia/Shanghai",
    "iso:country":"CN",
    "name:zho_x_preferred":[
        "\u524d\u4e1c\u4e95\u5b50"
    ],
    "wof:name":"Qiandongjingzi",
    "wof:placetype":"locality"
},
  "geometry": {"coordinates":[114.53888999999999,41.47361],"type":"Point"}
}