{
  "type": "Feature",
  "properties": {
    "gn:admin1_code":"1.0",
    "gn:asciiname":"Huangjinshe",
    "gn:country_code":"CN",
    "gn:dem":267,
    "gn:feature_class":"P",
    "gn:feature_code":"PPL",
    "gn:name":"Huangjinshe",
    "gn:population":0,
    "gn:timezone":"Asia/Shanghai",
    "iso:country":"CN",
    "name:und_x_variant":[
        "\u9ec4\u8fdb\u820d"
    ],
    "wof:name":"Huangjinshe",
    "wof:placetype":"locality"
},
  "geometry": {"coordinates":[118.36371,30.04936],"type":"Point"}
}