{
  "type": "Feature",
  "properties": {
    "gn:admin1_code":"12.0",
    "gn:asciiname":"Xiejiachong",
    "gn:country_code":"CN",
    "gn:dem":134,
    "gn:feature_class":"P",
    "gn:feature_code":"PPL",
    "gn:name":"Xiejiachong",
    "gn:population":0,
    "gn:timezone":"Asia/Shanghai",
    "iso:country":"CN",
    "name:zho_x_preferred":[
        "\u8c22\u5bb6\u51b2"
    ],
    "wof:name":"Xiejiachong",
    "wof:placetype":"locality"
},
  "geometry": {"coordinates":[112.03360000000001,31.07266],"type":"Point"}
}