{
  "type": "Feature",
  "properties": {
    "gn:admin1_code":"19.0",
    "gn:asciiname":"Laoyanggou",
    "gn:country_code":"CN",
    "gn:dem":129,
    "gn:feature_class":"P",
    "gn:feature_code":"PPL",
    "gn:name":"Laoyanggou",
    "gn:population":0,
    "gn:timezone":"Asia/Shanghai",
    "iso:country":"CN",
    "name:zho_x_preferred":[
        "\u8001\u9633\u6c9f"
    ],
    "wof:name":"Laoyanggou",
    "wof:placetype":"locality"
},
  "geometry": {"coordinates":[122.26300000000001,42.5452],"type":"Point"}
}