{
  "type": "Feature",
  "properties": {
    "iso:country":"CN",
    "name:eng_x_preferred":[
        "Wuzhen"
    ],
    "name:zho_x_preferred":[
        "\u4e4c\u9547\u9547"
    ],
    "qs:name":"\u4e4c\u9547\u9547",
    "qs:name_adm0":"\u4e2d\u570b",
    "qs:name_adm1":"\u6d59\u6c5f\u7701",
    "qs:photos":4683,
    "qs:photos_1k":949,
    "qs:photos_9k":21,
    "qs:photos_9r":13,
    "qs:photos_all":4683,
    "qs:photos_sr":23,
    "qs:placetype":"Town",
    "qs:pop_sr":"0",
    "wof:name":"Wuzhen",
    "wof:placetype":"locality"
},
  "geometry": {"coordinates":[120.48517200000001,30.743616],"type":"Point"}
}