{
  "type": "Feature",
  "properties": {
    "gn:admin1_code":"15.0",
    "gn:asciiname":"Fengchali",
    "gn:country_code":"CN",
    "gn:dem":1765,
    "gn:feature_class":"P",
    "gn:feature_code":"PPL",
    "gn:name":"Fengchali",
    "gn:population":0,
    "gn:timezone":"Asia/Shanghai",
    "iso:country":"CN",
    "name:und_x_variant":[
        "\u51af\u5c94\u91cc"
    ],
    "wof:name":"Fengchali",
    "wof:placetype":"locality"
},
  "geometry": {"coordinates":[105.43178,35.37373],"type":"Point"}
}