{
  "type": "Feature",
  "properties": {
    "gn:admin1_code":"19.0",
    "gn:asciiname":"Taibao",
    "gn:country_code":"CN",
    "gn:dem":341,
    "gn:feature_class":"P",
    "gn:feature_code":"PPL",
    "gn:name":"Taibao",
    "gn:population":0,
    "gn:timezone":"Asia/Shanghai",
    "iso:country":"CN",
    "name:ces_x_preferred":[
        "Tchaj-pao"
    ],
    "name:deu_x_preferred":[
        "Taibao"
    ],
    "name:fas_x_preferred":[
        "\u062a\u0627\u06cc\u0628\u0627\u0626\u0648"
    ],
    "name:hak_x_preferred":[
        "Thai-p\u00f3-s\u1e73"
    ],
    "name:ind_x_preferred":[
        "Kota Taibao"
    ],
    "name:ita_x_preferred":[
        "Taibao"
    ],
    "name:jpn_x_preferred":[
        "\u592a\u4fdd\u5e02"
    ],
    "name:kor_x_preferred":[
        "\ud0c0\uc774\ubc14\uc624\uc2dc"
    ],
    "name:lit_x_preferred":[
        "Taibao"
    ],
    "name:nld_x_preferred":[
        "Taibao"
    ],
    "name:pol_x_preferred":[
        "Taibao"
    ],
    "name:rus_x_preferred":[
        "\u0422\u0430\u0439\u0431\u0430\u043e"
    ],
    "name:spa_x_preferred":[
        "Taibao"
    ],
    "name:ukr_x_preferred":[
        "\u0422\u0430\u0439\u0431\u0430\u043e"
    ],
    "name:vie_x_preferred":[
        "Th\u00e1i B\u1ea3o"
    ],
    "name:zho_x_preferred":[
        "\u592a\u4fdd"
    ],
    "name:zho_x_variant":[
        "\u592a\u4fdd\u5e02"
    ],
    "wof:name":"Taibao",
    "wof:placetype":"locality"
},
  "geometry": {"coordinates":[119.917,41.3717],"type":"Point"}
}