{
  "type": "Feature",
  "properties": {
    "gn:admin1_code":"19.0",
    "gn:asciiname":"Haojitai'aile",
    "gn:country_code":"CN",
    "gn:dem":95,
    "gn:feature_class":"P",
    "gn:feature_code":"PPL",
    "gn:name":"Haojitai\u2019aile",
    "gn:population":0,
    "gn:timezone":"Asia/Shanghai",
    "iso:country":"CN",
    "name:zho_x_preferred":[
        "Haojitai\u2019aile"
    ],
    "name:zho_x_variant":[
        "\u6d69\u53ca\u592a\u827e\u52d2"
    ],
    "wof:name":"Haojitai'aile",
    "wof:placetype":"locality"
},
  "geometry": {"coordinates":[122.28425,42.2319],"type":"Point"}
}