{
  "type": "Feature",
  "properties": {
    "gn:admin1_code":"24.0",
    "gn:asciiname":"Houyaoyu",
    "gn:country_code":"CN",
    "gn:dem":1123,
    "gn:feature_class":"P",
    "gn:feature_code":"PPL",
    "gn:name":"Houyaoyu",
    "gn:population":0,
    "gn:timezone":"Asia/Shanghai",
    "iso:country":"CN",
    "name:zho_x_preferred":[
        "\u540e\u7a91\u5cea"
    ],
    "wof:name":"Houyaoyu",
    "wof:placetype":"locality"
},
  "geometry": {"coordinates":[111.39749,39.13682],"type":"Point"}
}