{
  "type": "Feature",
  "properties": {
    "gn:admin1_code":"7",
    "gn:asciiname":"Zhenzhuban",
    "gn:country_code":"CN",
    "gn:dem":20,
    "gn:feature_class":"P",
    "gn:feature_code":"PPL",
    "gn:name":"Zhenzhuban",
    "gn:population":0,
    "gn:timezone":"Asia/Shanghai",
    "iso:country":"CN",
    "name:zho_x_preferred":[
        "\u771f\u73e0\u5742"
    ],
    "wof:name":"Zhenzhuban",
    "wof:placetype":"locality"
},
  "geometry": {"coordinates":[117.37533000000001,24.0251],"type":"Point"}
}