{
  "type": "Feature",
  "properties": {
    "gn:admin1_code":"29.0",
    "gn:asciiname":"Shicun",
    "gn:country_code":"CN",
    "gn:dem":2076,
    "gn:feature_class":"P",
    "gn:feature_code":"PPL",
    "gn:name":"Shicun",
    "gn:population":0,
    "gn:timezone":"Asia/Shanghai",
    "iso:country":"CN",
    "name:zho_x_preferred":[
        "\u53f2\u6751"
    ],
    "wof:name":"Shicun",
    "wof:placetype":"locality"
},
  "geometry": {"coordinates":[103.873,26.1593],"type":"Point"}
}