{
  "type": "Feature",
  "properties": {
    "gn:admin1_code":"30",
    "gn:asciiname":"Huilong",
    "gn:country_code":"CN",
    "gn:dem":15,
    "gn:feature_class":"P",
    "gn:feature_code":"PPLA4",
    "gn:name":"Huilong",
    "gn:population":0,
    "gn:timezone":"Asia/Shanghai",
    "iso:country":"CN",
    "name:und_x_variant":[
        "Huilong Zhen",
        "\u56de\u9f99\u9547"
    ],
    "name:zho_x_preferred":[
        "\u56de\u9f99"
    ],
    "wof:name":"Huilong",
    "wof:placetype":"locality"
},
  "geometry": {"coordinates":[112.62868,22.9289],"type":"Point"}
}