{
  "type": "Feature",
  "properties": {
    "gn:admin1_code":"10",
    "gn:asciiname":"Yaogoutai",
    "gn:country_code":"CN",
    "gn:dem":1515,
    "gn:feature_class":"P",
    "gn:feature_code":"PPL",
    "gn:name":"Yaogoutai",
    "gn:population":0,
    "gn:timezone":"Asia/Shanghai",
    "iso:country":"CN",
    "name:zho_x_preferred":[
        "\u7a91\u6c9f\u53f0"
    ],
    "wof:name":"Yaogoutai",
    "wof:placetype":"locality"
},
  "geometry": {"coordinates":[115.81062,41.48078],"type":"Point"}
}