{
  "type": "Feature",
  "properties": {
    "gn:admin1_code":"32.0",
    "gn:asciiname":"Mamu Zeyue",
    "gn:country_code":"CN",
    "gn:dem":2435,
    "gn:feature_class":"P",
    "gn:feature_code":"PPL",
    "gn:name":"Mamu Zeyue",
    "gn:population":0,
    "gn:timezone":"Asia/Shanghai",
    "iso:country":"CN",
    "name:zho_x_preferred":[
        "\u9a6c\u6728\u5219\u7ea6"
    ],
    "wof:name":"Mamu Zeyue",
    "wof:placetype":"locality"
},
  "geometry": {"coordinates":[102.892,28.116],"type":"Point"}
}