{
  "type": "Feature",
  "properties": {
    "gn:admin1_code":"18",
    "gn:asciiname":"Qingjiao",
    "gn:country_code":"CN",
    "gn:dem":1599,
    "gn:feature_class":"P",
    "gn:feature_code":"PPL",
    "gn:name":"Qingjiao",
    "gn:population":0,
    "gn:timezone":"Asia/Shanghai",
    "iso:country":"CN",
    "name:zho_x_preferred":[
        "\u7b90\u811a"
    ],
    "wof:name":"Qingjiao",
    "wof:placetype":"locality"
},
  "geometry": {"coordinates":[105.33499999999999,26.7626],"type":"Point"}
}