{
  "type": "Feature",
  "properties": {
    "gn:admin1_code":"7",
    "gn:asciiname":"Houbaodai",
    "gn:country_code":"CN",
    "gn:dem":864,
    "gn:feature_class":"P",
    "gn:feature_code":"PPL",
    "gn:name":"Houbaodai",
    "gn:population":0,
    "gn:timezone":"Asia/Shanghai",
    "iso:country":"CN",
    "name:und_x_variant":[
        "\u540e\u5b9d\u5cb1"
    ],
    "wof:name":"Houbaodai",
    "wof:placetype":"locality"
},
  "geometry": {"coordinates":[118.92749999999999,27.31472],"type":"Point"}
}