{
  "type": "Feature",
  "properties": {
    "gn:admin1_code":"7",
    "gn:asciiname":"Madu",
    "gn:country_code":"CN",
    "gn:dem":242,
    "gn:feature_class":"P",
    "gn:feature_code":"PPL",
    "gn:name":"Madu",
    "gn:population":0,
    "gn:timezone":"Asia/Shanghai",
    "iso:country":"CN",
    "name:deu_x_preferred":[
        "Madu"
    ],
    "name:lit_x_preferred":[
        "Madu"
    ],
    "name:slv_x_preferred":[
        "Madu"
    ],
    "wof:name":"Madu",
    "wof:placetype":"locality"
},
  "geometry": {"coordinates":[117.76222,24.20917],"type":"Point"}
}