{
  "type": "Feature",
  "properties": {
    "gn:admin1_code":"16.0",
    "gn:asciiname":"Bade",
    "gn:country_code":"CN",
    "gn:dem":691,
    "gn:feature_class":"P",
    "gn:feature_code":"PPL",
    "gn:name":"Bade",
    "gn:population":0,
    "gn:timezone":"Asia/Shanghai",
    "iso:country":"CN",
    "name:zho_x_preferred":[
        "\u516b\u5fb7"
    ],
    "wof:name":"Bade",
    "wof:placetype":"locality"
},
  "geometry": {"coordinates":[106.48699999999999,23.067],"type":"Point"}
}