{
  "type": "Feature",
  "properties": {
    "gn:admin1_code":"7.0",
    "gn:asciiname":"Liushantian",
    "gn:country_code":"CN",
    "gn:dem":274,
    "gn:feature_class":"P",
    "gn:feature_code":"PPL",
    "gn:name":"Liushantian",
    "gn:population":0,
    "gn:timezone":"Asia/Shanghai",
    "iso:country":"CN",
    "name:zho_x_preferred":[
        "\u7559\u5584\u7530"
    ],
    "wof:name":"Liushantian",
    "wof:placetype":"locality"
},
  "geometry": {"coordinates":[116.30655,25.15038],"type":"Point"}
}