{
  "type": "Feature",
  "properties": {
    "gn:admin1_code":"10",
    "gn:asciiname":"Wafangdian",
    "gn:country_code":"CN",
    "gn:dem":625,
    "gn:feature_class":"P",
    "gn:feature_code":"PPL",
    "gn:name":"Wafangdian",
    "gn:population":0,
    "gn:timezone":"Asia/Shanghai",
    "iso:country":"CN",
    "name:ast_x_preferred":[
        "Wafangdian"
    ],
    "name:ceb_x_preferred":[
        "Wafangdian"
    ],
    "name:deu_x_preferred":[
        "Wafangdian"
    ],
    "name:fra_x_preferred":[
        "Wafangdian"
    ],
    "name:ita_x_preferred":[
        "Wafangdian"
    ],
    "name:jpn_x_preferred":[
        "\u74e6\u623f\u5e97\u5e02"
    ],
    "name:kik_x_preferred":[
        "Wafangdian"
    ],
    "name:kor_x_preferred":[
        "\uc640\ud321\ub3ac\uc2dc"
    ],
    "name:mlg_x_preferred":[
        "Wafangdian"
    ],
    "name:nor_x_preferred":[
        "Wafangdian"
    ],
    "name:rus_x_preferred":[
        "\u0412\u0430\u0444\u0430\u043d\u0434\u044f\u043d\u044c"
    ],
    "name:spa_x_preferred":[
        "Wafangdian"
    ],
    "name:srp_x_preferred":[
        "\u0412\u0430\u0444\u0430\u043d\u0433\u0434\u0458\u0435\u043d"
    ],
    "name:swe_x_preferred":[
        "Wafangdian"
    ],
    "name:urd_x_preferred":[
        "\u0648\u0627\u0641\u0627\u0646\u06af\u062f\u06cc\u0627\u0646"
    ],
    "name:war_x_preferred":[
        "Wafangdian"
    ],
    "name:zho_x_preferred":[
        "\u74e6\u623f\u5e97"
    ],
    "name:zho_x_variant":[
        "\u74e6\u623f\u5e97\u5e02"
    ],
    "wof:name":"Wafangdian",
    "wof:placetype":"locality"
},
  "geometry": {"coordinates":[118.7422,41.1443],"type":"Point"}
}