{
  "type": "Feature",
  "properties": {
    "gn:admin1_code":"10",
    "gn:asciiname":"Wafangdian",
    "gn:country_code":"CN",
    "gn:dem":625,
    "gn:feature_class":"P",
    "gn:feature_code":"PPL",
    "gn:name":"Wafangdian",
    "gn:population":0,
    "gn:timezone":"Asia/Shanghai",
    "iso:country":"CN",
    "name:ara_x_preferred":[
        "\u0648\u0627\u0641\u0627\u0646\u063a\u062f\u064a\u0627\u0646"
    ],
    "name:ast_x_preferred":[
        "Wafangdian"
    ],
    "name:ben_x_preferred":[
        "\u0993\u09df\u09be\u09ab\u09cd\u09af\u09be\u0982\u09a6\u09bf\u09df\u09be\u09a8"
    ],
    "name:ceb_x_preferred":[
        "Wafangdian"
    ],
    "name:deu_x_preferred":[
        "Wafangdian"
    ],
    "name:ell_x_preferred":[
        "\u0393\u03bf\u03c5\u03b1\u03c6\u03b1\u03bd\u03b3\u03bd\u03c4\u03b9\u03ac\u03bd"
    ],
    "name:fas_x_preferred":[
        "\u0648\u0627\u0641\u0627\u0646\u06af\u062f\u06cc\u0627\u0646"
    ],
    "name:fra_x_preferred":[
        "Wafangdian"
    ],
    "name:heb_x_preferred":[
        "\u05d5\u05d5\u05e4\u05d0\u05e0\u05d2\u05d3\u05d9\u05d0\u05df"
    ],
    "name:hin_x_preferred":[
        "\u0935\u092b\u093e\u0902\u0917\u0926\u093f\u092f\u093e\u0928"
    ],
    "name:hun_x_preferred":[
        "Wafangdian"
    ],
    "name:ind_x_preferred":[
        "Wafangdian"
    ],
    "name:ita_x_preferred":[
        "Wafangdian"
    ],
    "name:jpn_x_preferred":[
        "\u74e6\u623f\u5e97\u5e02"
    ],
    "name:kik_x_preferred":[
        "Wafangdian"
    ],
    "name:kor_x_preferred":[
        "\uc640\ud321\ub3ac\uc2dc"
    ],
    "name:mlg_x_preferred":[
        "Wafangdian"
    ],
    "name:nor_x_preferred":[
        "Wafangdian"
    ],
    "name:pol_x_preferred":[
        "Wafangdian"
    ],
    "name:por_x_preferred":[
        "Wafangdian"
    ],
    "name:rus_x_preferred":[
        "\u0412\u0430\u0444\u0430\u043d\u0434\u044f\u043d\u044c"
    ],
    "name:spa_x_preferred":[
        "Wafangdian"
    ],
    "name:srp_x_preferred":[
        "\u0412\u0430\u0444\u0430\u043d\u0433\u0434\u0458\u0435\u043d"
    ],
    "name:swe_x_preferred":[
        "Wafangdian"
    ],
    "name:tur_x_preferred":[
        "Wafangdian"
    ],
    "name:ukr_x_preferred":[
        "\u0412\u0430\u0444\u0430\u043d\u0434\u044f\u043d\u044c"
    ],
    "name:urd_x_preferred":[
        "\u0648\u0627\u0641\u0627\u0646\u06af\u062f\u06cc\u0627\u0646"
    ],
    "name:war_x_preferred":[
        "Wafangdian"
    ],
    "name:zho_x_preferred":[
        "\u74e6\u623f\u5e97"
    ],
    "name:zho_x_variant":[
        "\u74e6\u623f\u5e97\u5e02"
    ],
    "wof:name":"Wafangdian",
    "wof:placetype":"locality"
},
  "geometry": {"coordinates":[118.7422,41.1443],"type":"Point"}
}