{
  "type": "Feature",
  "properties": {
    "gn:admin1_code":"14.0",
    "gn:asciiname":"Eyege",
    "gn:country_code":"CN",
    "gn:dem":4013,
    "gn:feature_class":"P",
    "gn:feature_code":"PPL",
    "gn:name":"Eyege",
    "gn:population":0,
    "gn:timezone":"Asia/Urumqi",
    "iso:country":"CN",
    "name:zho_x_preferred":[
        "\u4fc4\u4e5f\u683c"
    ],
    "wof:name":"Eyege",
    "wof:placetype":"locality"
},
  "geometry": {"coordinates":[97.65835,32.0148],"type":"Point"}
}