{
  "type": "Feature",
  "properties": {
    "gn:admin1_code":"20.0",
    "gn:asciiname":"Nanhuangyugou",
    "gn:country_code":"CN",
    "gn:dem":1631,
    "gn:feature_class":"P",
    "gn:feature_code":"PPL",
    "gn:name":"Nanhuangyugou",
    "gn:population":0,
    "gn:timezone":"Asia/Shanghai",
    "iso:country":"CN",
    "name:und_x_variant":[
        "\u5357\u9ec4\u6986\u6c9f"
    ],
    "wof:name":"Nanhuangyugou",
    "wof:placetype":"locality"
},
  "geometry": {"coordinates":[111.92093,39.74029],"type":"Point"}
}