{
  "type": "Feature",
  "properties": {
    "gn:admin1_code":"7.0",
    "gn:asciiname":"Wangyangkeng",
    "gn:country_code":"CN",
    "gn:dem":647,
    "gn:feature_class":"P",
    "gn:feature_code":"PPL",
    "gn:name":"Wangyangkeng",
    "gn:population":0,
    "gn:timezone":"Asia/Shanghai",
    "iso:country":"CN",
    "name:und_x_variant":[
        "\u738b\u6d0b\u5751"
    ],
    "name:zho_x_preferred":[
        "\u738b\u6d0b\u5751"
    ],
    "wof:name":"Wangyangkeng",
    "wof:placetype":"locality"
},
  "geometry": {"coordinates":[117.51987,26.96845],"type":"Point"}
}