{
  "type": "Feature",
  "properties": {
    "gn:admin1_code":"14.0",
    "gn:asciiname":"Jiangbietang",
    "gn:country_code":"CN",
    "gn:dem":2620,
    "gn:feature_class":"P",
    "gn:feature_code":"PPL",
    "gn:name":"Jiangbietang",
    "gn:population":0,
    "gn:timezone":"Asia/Urumqi",
    "iso:country":"CN",
    "name:zho_x_preferred":[
        "\u6c5f\u522b\u5858"
    ],
    "wof:name":"Jiangbietang",
    "wof:placetype":"locality"
},
  "geometry": {"coordinates":[95.74319,29.51719000000001],"type":"Point"}
}