{
  "type": "Feature",
  "properties": {
    "gn:admin1_code":"18",
    "gn:asciiname":"Wengnuo",
    "gn:country_code":"CN",
    "gn:dem":1311,
    "gn:feature_class":"P",
    "gn:feature_code":"PPL",
    "gn:name":"Wengnuo",
    "gn:population":0,
    "gn:timezone":"Asia/Shanghai",
    "iso:country":"CN",
    "name:zho_x_preferred":[
        "\u7fc1\u7cef"
    ],
    "wof:name":"Wengnuo",
    "wof:placetype":"locality"
},
  "geometry": {"coordinates":[106.509,26.1341],"type":"Point"}
}