{
  "type": "Feature",
  "properties": {
    "gn:admin1_code":"19.0",
    "gn:asciiname":"Suotun",
    "gn:country_code":"CN",
    "gn:dem":13,
    "gn:feature_class":"P",
    "gn:feature_code":"PPL",
    "gn:name":"Suotun",
    "gn:population":0,
    "gn:timezone":"Asia/Shanghai",
    "iso:country":"CN",
    "name:zho_x_preferred":[
        "\u7d22\u5c6f"
    ],
    "wof:name":"Suotun",
    "wof:placetype":"locality"
},
  "geometry": {"coordinates":[121.87999000000001,41.44477],"type":"Point"}
}