{
  "type": "Feature",
  "properties": {
    "gn:admin1_code":"25",
    "gn:asciiname":"Beichenzhuang",
    "gn:country_code":"CN",
    "gn:dem":46,
    "gn:feature_class":"P",
    "gn:feature_code":"PPL",
    "gn:name":"Beichenzhuang",
    "gn:population":0,
    "gn:timezone":"Asia/Shanghai",
    "iso:country":"CN",
    "name:zho_x_preferred":[
        "\u5317\u9648\u5e84"
    ],
    "wof:name":"Beichenzhuang",
    "wof:placetype":"locality"
},
  "geometry": {"coordinates":[115.952,35.1127],"type":"Point"}
}