{
  "type": "Feature",
  "properties": {
    "gn:admin1_code":"10",
    "gn:asciiname":"Lixinzhai",
    "gn:country_code":"CN",
    "gn:dem":55,
    "gn:feature_class":"P",
    "gn:feature_code":"PPL",
    "gn:name":"Lixinzhai",
    "gn:population":0,
    "gn:timezone":"Asia/Shanghai",
    "iso:country":"CN",
    "name:zho_x_preferred":[
        "\u674e\u8f9b\u5be8"
    ],
    "wof:name":"Lixinzhai",
    "wof:placetype":"locality"
},
  "geometry": {"coordinates":[114.907,36.3394],"type":"Point"}
}