{
  "type": "Feature",
  "properties": {
    "gn:admin1_code":"30",
    "gn:asciiname":"Nabu",
    "gn:country_code":"CN",
    "gn:dem":138,
    "gn:feature_class":"P",
    "gn:feature_code":"PPL",
    "gn:name":"Nabu",
    "gn:population":0,
    "gn:timezone":"Asia/Urumqi",
    "iso:country":"CN",
    "name:und_x_variant":[
        "Na-pu",
        "Nabu"
    ],
    "name:zho_x_preferred":[
        "\u90a3\u535c"
    ],
    "wof:name":"Nabu",
    "wof:placetype":"locality"
},
  "geometry": {"coordinates":[110.18483000000001,20.56565],"type":"Point"}
}