{
  "type": "Feature",
  "properties": {
    "gn:admin1_code":"30",
    "gn:asciiname":"Nabu",
    "gn:country_code":"CN",
    "gn:dem":138,
    "gn:feature_class":"P",
    "gn:feature_code":"PPL",
    "gn:name":"Nabu",
    "gn:population":0,
    "gn:timezone":"Asia/Urumqi",
    "iso:country":"CN",
    "name:als_x_preferred":[
        "Nabu"
    ],
    "name:ara_x_preferred":[
        "\u0646\u0627\u0628\u0648"
    ],
    "name:aze_x_preferred":[
        "Nabu"
    ],
    "name:cat_x_preferred":[
        "Nabu"
    ],
    "name:ces_x_preferred":[
        "Nabu"
    ],
    "name:deu_x_preferred":[
        "Nabu"
    ],
    "name:ell_x_preferred":[
        "\u039d\u03b1\u03bc\u03c0\u03bf\u03cd"
    ],
    "name:eus_x_preferred":[
        "Nabu"
    ],
    "name:fas_x_preferred":[
        "\u0646\u0628\u0648"
    ],
    "name:fra_x_preferred":[
        "Nab\u00fb"
    ],
    "name:glg_x_preferred":[
        "Nabu"
    ],
    "name:heb_x_preferred":[
        "\u05e0\u05d1\u05d5"
    ],
    "name:ind_x_preferred":[
        "Nabu"
    ],
    "name:ita_x_preferred":[
        "Nabu"
    ],
    "name:jpn_x_preferred":[
        "\u30ca\u30d6\u30fc"
    ],
    "name:msa_x_preferred":[
        "Nabu"
    ],
    "name:nld_x_preferred":[
        "Nabu"
    ],
    "name:nor_x_preferred":[
        "Nebo"
    ],
    "name:oci_x_preferred":[
        "Nabu"
    ],
    "name:pol_x_preferred":[
        "Nabu"
    ],
    "name:por_x_preferred":[
        "Nabu"
    ],
    "name:ron_x_preferred":[
        "Nabu"
    ],
    "name:rus_x_preferred":[
        "\u041d\u0430\u0431\u0443"
    ],
    "name:slk_x_preferred":[
        "Nab\u00fa"
    ],
    "name:slv_x_preferred":[
        "Nabu"
    ],
    "name:snd_x_preferred":[
        "\u0646\u0627\u0628\u0648"
    ],
    "name:spa_x_preferred":[
        "Nabu"
    ],
    "name:swe_x_preferred":[
        "Nabu"
    ],
    "name:tgl_x_preferred":[
        "Nabu"
    ],
    "name:tha_x_preferred":[
        "\u0e40\u0e19\u0e42\u0e1a"
    ],
    "name:tur_x_preferred":[
        "Nabu"
    ],
    "name:ukr_x_preferred":[
        "\u041d\u0430\u0431\u0443"
    ],
    "name:und_x_variant":[
        "Na-pu"
    ],
    "name:urd_x_preferred":[
        "\u0646\u0627\u0628\u0648"
    ],
    "name:zho_x_preferred":[
        "\u90a3\u535c"
    ],
    "wof:name":"Nabu",
    "wof:placetype":"locality"
},
  "geometry": {"coordinates":[110.18483000000001,20.56565],"type":"Point"}
}