{
  "type": "Feature",
  "properties": {
    "gn:admin1_code":"25",
    "gn:asciiname":"Fengmin Yicun",
    "gn:country_code":"CN",
    "gn:dem":6,
    "gn:feature_class":"P",
    "gn:feature_code":"PPL",
    "gn:name":"Fengmin Yicun",
    "gn:population":0,
    "gn:timezone":"Asia/Shanghai",
    "iso:country":"CN",
    "name:zho_x_preferred":[
        "\u4e30\u6c11\u4e00\u6751"
    ],
    "wof:name":"Fengmin Yicun",
    "wof:placetype":"locality"
},
  "geometry": {"coordinates":[118.194,37.7434],"type":"Point"}
}