{
  "type": "Feature",
  "properties": {
    "gn:admin1_code":"30.0",
    "gn:asciiname":"Dalong",
    "gn:country_code":"CN",
    "gn:dem":193,
    "gn:feature_class":"P",
    "gn:feature_code":"PPL",
    "gn:name":"Dalong",
    "gn:population":0,
    "gn:timezone":"Asia/Shanghai",
    "iso:country":"CN",
    "name:zho_x_preferred":[
        "Dalong"
    ],
    "name:zho_x_variant":[
        "\u5927\u9f99"
    ],
    "wof:name":"Dalong",
    "wof:placetype":"locality"
},
  "geometry": {"coordinates":[112.24222,24.8575],"type":"Point"}
}