{
  "type": "Feature",
  "properties": {
    "gn:admin1_code":"15.0",
    "gn:asciiname":"Shilipu",
    "gn:country_code":"CN",
    "gn:dem":1952,
    "gn:feature_class":"P",
    "gn:feature_code":"PPL",
    "gn:name":"Shilipu",
    "gn:population":0,
    "gn:timezone":"Asia/Shanghai",
    "iso:country":"CN",
    "name:zho_x_preferred":[
        "\u5341\u91cc\u94fa"
    ],
    "wof:name":"Shilipu",
    "wof:placetype":"locality"
},
  "geometry": {"coordinates":[104.607,35.6141],"type":"Point"}
}