{
  "type": "Feature",
  "properties": {
    "gn:admin1_code":"19.0",
    "gn:asciiname":"Daqiao",
    "gn:country_code":"CN",
    "gn:dem":182,
    "gn:feature_class":"P",
    "gn:feature_code":"PPL",
    "gn:name":"Daqiao",
    "gn:population":0,
    "gn:timezone":"Asia/Shanghai",
    "iso:country":"CN",
    "name:ceb_x_preferred":[
        "Daqiao"
    ],
    "name:deu_x_preferred":[
        "Daqiao"
    ],
    "name:swe_x_preferred":[
        "Daqiao"
    ],
    "name:und_x_variant":[
        "\u5927\u6865"
    ],
    "name:zho_x_preferred":[
        "\u5927\u6865"
    ],
    "wof:name":"Daqiao",
    "wof:placetype":"locality"
},
  "geometry": {"coordinates":[120.45261000000001,41.52352],"type":"Point"}
}