{
  "type": "Feature",
  "properties": {
    "gn:admin1_code":"31",
    "gn:asciiname":"Langfeng",
    "gn:country_code":"CN",
    "gn:dem":181,
    "gn:feature_class":"P",
    "gn:feature_code":"PPL",
    "gn:name":"Langfeng",
    "gn:population":0,
    "gn:timezone":"Asia/Shanghai",
    "iso:country":"CN",
    "name:und_x_variant":[
        "\u6d6a\u4e30"
    ],
    "wof:name":"Langfeng",
    "wof:placetype":"locality"
},
  "geometry": {"coordinates":[109.17400000000001,19.2137],"type":"Point"}
}