{
  "type": "Feature",
  "properties": {
    "gn:admin1_code":"1.0",
    "gn:asciiname":"Huangshucun",
    "gn:country_code":"CN",
    "gn:dem":18,
    "gn:feature_class":"P",
    "gn:feature_code":"PPL",
    "gn:name":"Huangshucun",
    "gn:population":0,
    "gn:timezone":"Asia/Shanghai",
    "iso:country":"CN",
    "name:zho_x_preferred":[
        "\u9ec4\u5885\u6751"
    ],
    "wof:name":"Huangshucun",
    "wof:placetype":"locality"
},
  "geometry": {"coordinates":[119.25427000000001,31.09271],"type":"Point"}
}