{
  "type": "Feature",
  "properties": {
    "gn:admin1_code":"19.0",
    "gn:asciiname":"Erbaiqianling",
    "gn:country_code":"CN",
    "gn:dem":136,
    "gn:feature_class":"P",
    "gn:feature_code":"PPL",
    "gn:name":"Erbaiqianling",
    "gn:population":0,
    "gn:timezone":"Asia/Shanghai",
    "iso:country":"CN",
    "name:zho_x_preferred":[
        "\u4e8c\u767e\u94b1\u5cad"
    ],
    "wof:name":"Erbaiqianling",
    "wof:placetype":"locality"
},
  "geometry": {"coordinates":[125.25496,40.62696],"type":"Point"}
}