{
  "type": "Feature",
  "properties": {
    "gn:admin1_code":"30.0",
    "gn:asciiname":"Leigongtang",
    "gn:country_code":"CN",
    "gn:dem":20,
    "gn:feature_class":"P",
    "gn:feature_code":"PPL",
    "gn:name":"Leigongtang",
    "gn:population":0,
    "gn:timezone":"Asia/Shanghai",
    "iso:country":"CN",
    "name:zho_x_preferred":[
        "\u96f7\u516c\u5802"
    ],
    "wof:name":"Leigongtang",
    "wof:placetype":"locality"
},
  "geometry": {"coordinates":[114.74802,22.65891],"type":"Point"}
}