{
  "type": "Feature",
  "properties": {
    "gn:admin1_code":"11",
    "gn:asciiname":"Shandou",
    "gn:country_code":"CN",
    "gn:dem":149,
    "gn:feature_class":"P",
    "gn:feature_code":"PPL",
    "gn:name":"Shandou",
    "gn:population":0,
    "gn:timezone":"Asia/Shanghai",
    "iso:country":"CN",
    "wof:name":"Shandou",
    "wof:placetype":"locality"
},
  "geometry": {"coordinates":[113.67278,27.99194],"type":"Point"}
}