{
  "type": "Feature",
  "properties": {
    "gn:admin1_code":"10",
    "gn:asciiname":"Jinbiangou",
    "gn:country_code":"CN",
    "gn:dem":1386,
    "gn:feature_class":"P",
    "gn:feature_code":"PPL",
    "gn:name":"Jinbiangou",
    "gn:population":0,
    "gn:timezone":"Asia/Shanghai",
    "iso:country":"CN",
    "name:zho_x_preferred":[
        "\u8fd1\u8fb9\u6c9f"
    ],
    "wof:name":"Jinbiangou",
    "wof:placetype":"locality"
},
  "geometry": {"coordinates":[115.54092,41.29147],"type":"Point"}
}