{
  "type": "Feature",
  "properties": {
    "gn:admin1_code":"2.0",
    "gn:asciiname":"Dianxiayan",
    "gn:country_code":"CN",
    "gn:dem":37,
    "gn:feature_class":"P",
    "gn:feature_code":"PPL",
    "gn:name":"Dianxiayan",
    "gn:population":0,
    "gn:timezone":"Asia/Shanghai",
    "iso:country":"CN",
    "name:und_x_variant":[
        "\u6bbf\u4e0b\u4e25",
        "Dianxiayan"
    ],
    "wof:name":"Dianxiayan",
    "wof:placetype":"locality"
},
  "geometry": {"coordinates":[119.44577,29.13733],"type":"Point"}
}