{
  "type": "Feature",
  "properties": {
    "gn:admin1_code":"05",
    "gn:asciiname":"Sandaoyangcha",
    "gn:country_code":"CN",
    "gn:dem":516,
    "gn:feature_class":"P",
    "gn:feature_code":"PPL",
    "gn:name":"Sandaoyangcha",
    "gn:population":0,
    "gn:timezone":"Asia/Shanghai",
    "iso:country":"CN",
    "name:und_x_variant":[
        "\u4e09\u9053\u9633\u5c94",
        "San-tao-yang-ch\u2019a"
    ],
    "wof:name":"Sandaoyangcha",
    "wof:placetype":"locality"
},
  "geometry": {"coordinates":[126.02778000000001,41.50306],"type":"Point"}
}