{
  "type": "Feature",
  "properties": {
    "gn:admin1_code":"10",
    "gn:asciiname":"Layangou",
    "gn:country_code":"CN",
    "gn:dem":998,
    "gn:feature_class":"P",
    "gn:feature_code":"PPL",
    "gn:name":"Layangou",
    "gn:population":0,
    "gn:timezone":"Asia/Shanghai",
    "iso:country":"CN",
    "name:zho_x_preferred":[
        "\u782c\u96c1\u6c9f"
    ],
    "wof:name":"Layangou",
    "wof:placetype":"locality"
},
  "geometry": {"coordinates":[117.71382,41.81833],"type":"Point"}
}