{
  "type": "Feature",
  "properties": {
    "gn:admin1_code":"05",
    "gn:asciiname":"Kuan-men-la-tzu",
    "gn:country_code":"CN",
    "gn:dem":560,
    "gn:feature_class":"P",
    "gn:feature_code":"PPL",
    "gn:name":"Kuan-men-la-tzu",
    "gn:population":0,
    "gn:timezone":"Asia/Shanghai",
    "iso:country":"CN",
    "wof:name":"Kuan-men-la-tzu",
    "wof:placetype":"locality"
},
  "geometry": {"coordinates":[126.17528,41.88028],"type":"Point"}
}