{
  "type": "Feature",
  "properties": {
    "gn:admin1_code":"4.0",
    "gn:asciiname":"Xiaoyaojing",
    "gn:country_code":"CN",
    "gn:dem":6,
    "gn:feature_class":"P",
    "gn:feature_code":"PPL",
    "gn:name":"Xiaoyaojing",
    "gn:population":0,
    "gn:timezone":"Asia/Shanghai",
    "iso:country":"CN",
    "name:zho_x_preferred":[
        "\u5c0f\u7a91\u6cfe"
    ],
    "wof:name":"Xiaoyaojing",
    "wof:placetype":"locality"
},
  "geometry": {"coordinates":[120.52876000000001,31.82434000000001],"type":"Point"}
}