{
  "type": "Feature",
  "properties": {
    "gn:admin1_code":"4.0",
    "gn:asciiname":"Nanchangzhuangcun",
    "gn:country_code":"CN",
    "gn:dem":8,
    "gn:feature_class":"P",
    "gn:feature_code":"PPL",
    "gn:name":"Nanchangzhuangcun",
    "gn:population":0,
    "gn:timezone":"Asia/Shanghai",
    "iso:country":"CN",
    "name:zho_x_preferred":[
        "\u5357\u957f\u5e84\u6751"
    ],
    "wof:name":"Nanchangzhuangcun",
    "wof:placetype":"locality"
},
  "geometry": {"coordinates":[118.62793000000001,34.01068],"type":"Point"}
}