{
  "type": "Feature",
  "properties": {
    "gn:admin1_code":"05",
    "gn:asciiname":"Taipinghecun",
    "gn:country_code":"CN",
    "gn:dem":329,
    "gn:feature_class":"P",
    "gn:feature_code":"PPL",
    "gn:name":"Taipinghecun",
    "gn:population":0,
    "gn:timezone":"Asia/Shanghai",
    "iso:country":"CN",
    "name:und_x_variant":[
        "T\u2019ai-p\u2019ing-ho",
        "Taipinghe",
        "Taipinghecun"
    ],
    "name:zho_x_preferred":[
        "\u592a\u5e73\u6cb3\u6751"
    ],
    "wof:name":"Taipinghecun",
    "wof:placetype":"locality"
},
  "geometry": {"coordinates":[125.75579,42.84885],"type":"Point"}
}