{
  "type": "Feature",
  "properties": {
    "gn:admin1_code":"30.0",
    "gn:asciiname":"Zhonghexu",
    "gn:country_code":"CN",
    "gn:dem":15,
    "gn:feature_class":"P",
    "gn:feature_code":"PPL",
    "gn:name":"Zhonghexu",
    "gn:population":0,
    "gn:timezone":"Asia/Shanghai",
    "iso:country":"CN",
    "name:zho_x_preferred":[
        "\u4e2d\u548c\u5729"
    ],
    "wof:name":"Zhonghexu",
    "wof:placetype":"locality"
},
  "geometry": {"coordinates":[114.06910999999999,23.00603],"type":"Point"}
}