{
  "type": "Feature",
  "properties": {
    "gn:admin1_code":"8.0",
    "gn:asciiname":"Xinlitun",
    "gn:country_code":"CN",
    "gn:dem":145,
    "gn:feature_class":"P",
    "gn:feature_code":"PPL",
    "gn:name":"Xinlitun",
    "gn:population":0,
    "gn:timezone":"Asia/Shanghai",
    "iso:country":"CN",
    "name:zho_x_preferred":[
        "\u65b0\u7acb\u5c6f"
    ],
    "wof:name":"Xinlitun",
    "wof:placetype":"locality"
},
  "geometry": {"coordinates":[124.33888,46.81876],"type":"Point"}
}