{
  "type": "Feature",
  "properties": {
    "gn:admin1_code":"18.0",
    "gn:asciiname":"Qiuzhai",
    "gn:country_code":"CN",
    "gn:dem":780,
    "gn:feature_class":"P",
    "gn:feature_code":"PPL",
    "gn:name":"Qiuzhai",
    "gn:population":0,
    "gn:timezone":"Asia/Shanghai",
    "iso:country":"CN",
    "name:zho_x_preferred":[
        "\u6c42\u5be8"
    ],
    "wof:name":"Qiuzhai",
    "wof:placetype":"locality"
},
  "geometry": {"coordinates":[108.782,26.1351],"type":"Point"}
}