{
  "type": "Feature",
  "properties": {
    "gn:admin1_code":"15.0",
    "gn:asciiname":"Jiucaizhang",
    "gn:country_code":"CN",
    "gn:dem":1845,
    "gn:feature_class":"P",
    "gn:feature_code":"PPL",
    "gn:name":"Jiucaizhang",
    "gn:population":0,
    "gn:timezone":"Asia/Shanghai",
    "iso:country":"CN",
    "name:und_x_variant":[
        "\u97ed\u83dc\u638c"
    ],
    "wof:name":"Jiucaizhang",
    "wof:placetype":"locality"
},
  "geometry": {"coordinates":[106.70650000000001,36.91985],"type":"Point"}
}