{
  "type": "Feature",
  "properties": {
    "gn:admin1_code":"19.0",
    "gn:asciiname":"Liuzhangzi",
    "gn:country_code":"CN",
    "gn:dem":325,
    "gn:feature_class":"P",
    "gn:feature_code":"PPL",
    "gn:name":"Liuzhangzi",
    "gn:population":0,
    "gn:timezone":"Asia/Shanghai",
    "iso:country":"CN",
    "name:zho_x_preferred":[
        "\u5218\u6756\u5b50"
    ],
    "wof:name":"Liuzhangzi",
    "wof:placetype":"locality"
},
  "geometry": {"coordinates":[119.08954,40.74746],"type":"Point"}
}