{
  "type": "Feature",
  "properties": {
    "gn:admin1_code":"18.0",
    "gn:asciiname":"Shaping'ao",
    "gn:country_code":"CN",
    "gn:dem":581,
    "gn:feature_class":"P",
    "gn:feature_code":"PPL",
    "gn:name":"Shaping\u2019ao",
    "gn:population":0,
    "gn:timezone":"Asia/Shanghai",
    "iso:country":"CN",
    "name:und_x_variant":[
        "Shaping\u2019ao"
    ],
    "name:zho_x_preferred":[
        "\u6c99\u5e73\u5773"
    ],
    "wof:name":"Shaping'ao",
    "wof:placetype":"locality"
},
  "geometry": {"coordinates":[108.866,27.7504],"type":"Point"}
}