{
  "type": "Feature",
  "properties": {
    "gn:admin1_code":"4.0",
    "gn:asciiname":"Jiangqiao",
    "gn:country_code":"CN",
    "gn:dem":12,
    "gn:feature_class":"P",
    "gn:feature_code":"PPL",
    "gn:name":"Jiangqiao",
    "gn:population":0,
    "gn:timezone":"Asia/Shanghai",
    "iso:country":"CN",
    "name:zho_x_preferred":[
        "\u59dc\u6865"
    ],
    "wof:name":"Jiangqiao",
    "wof:placetype":"locality"
},
  "geometry": {"coordinates":[118.77227999999999,32.2287],"type":"Point"}
}