{
  "type": "Feature",
  "properties": {
    "gn:admin1_code":"26.0",
    "gn:asciiname":"Wangjia Chacun",
    "gn:country_code":"CN",
    "gn:dem":971,
    "gn:feature_class":"P",
    "gn:feature_code":"PPL",
    "gn:name":"Wangjia Chacun",
    "gn:population":0,
    "gn:timezone":"Asia/Shanghai",
    "iso:country":"CN",
    "name:zho_x_preferred":[
        "\u738b\u5bb6\u5c94\u6751"
    ],
    "wof:name":"Wangjia Chacun",
    "wof:placetype":"locality"
},
  "geometry": {"coordinates":[109.97,37.5538],"type":"Point"}
}