{
  "type": "Feature",
  "properties": {
    "gn:admin1_code":"14.0",
    "gn:asciiname":"Qiru",
    "gn:country_code":"CN",
    "gn:dem":4455,
    "gn:feature_class":"P",
    "gn:feature_code":"PPL",
    "gn:name":"Qiru",
    "gn:population":0,
    "gn:timezone":"Asia/Urumqi",
    "iso:country":"CN",
    "name:aym_x_preferred":[
        "Qiru"
    ],
    "name:fra_x_preferred":[
        "Qero"
    ],
    "name:ita_x_preferred":[
        "Quero"
    ],
    "name:oci_x_preferred":[
        "Quero"
    ],
    "name:que_x_preferred":[
        "Qiru"
    ],
    "name:spa_x_preferred":[
        "Quero"
    ],
    "name:ukr_x_preferred":[
        "\u041a\u0435\u0440\u043e"
    ],
    "name:zho_x_preferred":[
        "\u542f\u5982"
    ],
    "wof:name":"Qiru",
    "wof:placetype":"locality"
},
  "geometry": {"coordinates":[91.56656,28.91965],"type":"Point"}
}