{
  "type": "Feature",
  "properties": {
    "gn:admin1_code":"16.0",
    "gn:asciiname":"Longgu",
    "gn:country_code":"CN",
    "gn:dem":1412,
    "gn:feature_class":"P",
    "gn:feature_code":"PPL",
    "gn:name":"Longgu",
    "gn:population":0,
    "gn:timezone":"Asia/Shanghai",
    "iso:country":"CN",
    "name:zho_x_preferred":[
        "\u9f99\u4f30"
    ],
    "wof:name":"Longgu",
    "wof:placetype":"locality"
},
  "geometry": {"coordinates":[105.253,24.6858],"type":"Point"}
}