{
  "type": "Feature",
  "properties": {
    "gn:admin1_code":"26.0",
    "gn:asciiname":"Foliucun",
    "gn:country_code":"CN",
    "gn:dem":577,
    "gn:feature_class":"P",
    "gn:feature_code":"PPL",
    "gn:name":"Foliucun",
    "gn:population":0,
    "gn:timezone":"Asia/Shanghai",
    "iso:country":"CN",
    "name:zho_x_preferred":[
        "\u4f5b\u5218\u6751"
    ],
    "wof:name":"Foliucun",
    "wof:placetype":"locality"
},
  "geometry": {"coordinates":[108.37557,34.50684],"type":"Point"}
}