{
  "type": "Feature",
  "properties": {
    "gn:admin1_code":"32.0",
    "gn:asciiname":"Baozhu",
    "gn:country_code":"CN",
    "gn:dem":615,
    "gn:feature_class":"P",
    "gn:feature_code":"PPL",
    "gn:name":"Baozhu",
    "gn:population":0,
    "gn:timezone":"Asia/Shanghai",
    "iso:country":"CN",
    "name:zho_x_preferred":[
        "\u5b9d\u73e0"
    ],
    "wof:name":"Baozhu",
    "wof:placetype":"locality"
},
  "geometry": {"coordinates":[106.825,31.8189],"type":"Point"}
}