{
  "type": "Feature",
  "properties": {
    "gn:admin1_code":"16.0",
    "gn:asciiname":"Xinjiwei",
    "gn:country_code":"CN",
    "gn:dem":20,
    "gn:feature_class":"P",
    "gn:feature_code":"PPL",
    "gn:name":"Xinjiwei",
    "gn:population":0,
    "gn:timezone":"Asia/Shanghai",
    "iso:country":"CN",
    "name:zho_x_preferred":[
        "\u65b0\u57fa\u56f4"
    ],
    "wof:name":"Xinjiwei",
    "wof:placetype":"locality"
},
  "geometry": {"coordinates":[108.57599999999999,21.781],"type":"Point"}
}