{
  "type": "Feature",
  "properties": {
    "gn:admin1_code":"3.0",
    "gn:asciiname":"Yuduan",
    "gn:country_code":"CN",
    "gn:dem":166,
    "gn:feature_class":"P",
    "gn:feature_code":"PPLA4",
    "gn:name":"Yuduan",
    "gn:population":0,
    "gn:timezone":"Asia/Shanghai",
    "iso:country":"CN",
    "name:und_x_variant":[
        "\u4f59\u5845",
        "Yuduan Xiang",
        "\u4f59\u5845\u4e61"
    ],
    "wof:name":"Yuduan",
    "wof:placetype":"locality"
},
  "geometry": {"coordinates":[114.06910999999999,28.85404],"type":"Point"}
}