{
  "type": "Feature",
  "properties": {
    "gn:admin1_code":"09",
    "gn:asciiname":"Mangzhang",
    "gn:cc2":"CN",
    "gn:country_code":"CN",
    "gn:dem":92,
    "gn:feature_class":"P",
    "gn:feature_code":"PPL",
    "gn:name":"Mangzhang",
    "gn:population":0,
    "gn:timezone":"Asia/Shanghai",
    "iso:country":"CN",
    "name:und_x_variant":[
        "Mang-chang-tien",
        "Mangzhangdian",
        "Mang-chang",
        "Mangzhang"
    ],
    "wof:name":"Mangzhang",
    "wof:placetype":"locality"
},
  "geometry": {"coordinates":[114.50055999999999,32.05611],"type":"Point"}
}