{
  "type": "Feature",
  "properties": {
    "gn:admin1_code":"30",
    "gn:asciiname":"Mazhukeng",
    "gn:country_code":"CN",
    "gn:dem":155,
    "gn:feature_class":"P",
    "gn:feature_code":"PPL",
    "gn:name":"Mazhukeng",
    "gn:population":0,
    "gn:timezone":"Asia/Shanghai",
    "iso:country":"CN",
    "name:zho_x_preferred":[
        "\u9ebb\u7af9\u5751"
    ],
    "wof:name":"Mazhukeng",
    "wof:placetype":"locality"
},
  "geometry": {"coordinates":[116.04939,23.29635],"type":"Point"}
}