{
  "type": "Feature",
  "properties": {
    "gn:admin1_code":"11.0",
    "gn:asciiname":"Paijiu'ang",
    "gn:country_code":"CN",
    "gn:dem":673,
    "gn:feature_class":"P",
    "gn:feature_code":"PPL",
    "gn:name":"Paijiu\u2019ang",
    "gn:population":0,
    "gn:timezone":"Asia/Shanghai",
    "iso:country":"CN",
    "name:und_x_variant":[
        "Paijiu\u2019ang"
    ],
    "name:zho_x_preferred":[
        "\u6392\u4e5d\u6602"
    ],
    "wof:name":"Paijiu'ang",
    "wof:placetype":"locality"
},
  "geometry": {"coordinates":[109.52086,28.30789],"type":"Point"}
}