{
  "type": "Feature",
  "properties": {
    "gn:admin1_code":"26.0",
    "gn:asciiname":"Shuizhuang Nigou",
    "gn:country_code":"CN",
    "gn:dem":1380,
    "gn:feature_class":"P",
    "gn:feature_code":"PPL",
    "gn:name":"Shuizhuang Nigou",
    "gn:population":0,
    "gn:timezone":"Asia/Shanghai",
    "iso:country":"CN",
    "name:zho_x_preferred":[
        "\u6c34\u5e84\u6ce5\u6c9f"
    ],
    "wof:name":"Shuizhuang Nigou",
    "wof:placetype":"locality"
},
  "geometry": {"coordinates":[110.16983999999999,33.64655],"type":"Point"}
}