{
  "type": "Feature",
  "properties": {
    "gn:admin1_code":"3.0",
    "gn:asciiname":"Miaojiaoli",
    "gn:country_code":"CN",
    "gn:dem":77,
    "gn:feature_class":"P",
    "gn:feature_code":"PPL",
    "gn:name":"Miaojiaoli",
    "gn:population":0,
    "gn:timezone":"Asia/Shanghai",
    "iso:country":"CN",
    "name:und_x_variant":[
        "\u5e99\u89d2\u91cc"
    ],
    "wof:name":"Miaojiaoli",
    "wof:placetype":"locality"
},
  "geometry": {"coordinates":[114.52755999999999,28.17538],"type":"Point"}
}