{
  "type": "Feature",
  "properties": {
    "gn:admin1_code":"26.0",
    "gn:asciiname":"Dabailin",
    "gn:country_code":"CN",
    "gn:dem":1105,
    "gn:feature_class":"P",
    "gn:feature_code":"PPL",
    "gn:name":"Dabailin",
    "gn:population":0,
    "gn:timezone":"Asia/Shanghai",
    "iso:country":"CN",
    "name:zho_x_preferred":[
        "\u5927\u67cf\u6797"
    ],
    "wof:name":"Dabailin",
    "wof:placetype":"locality"
},
  "geometry": {"coordinates":[107.83920999999999,32.32492],"type":"Point"}
}