{
  "type": "Feature",
  "properties": {
    "gn:admin1_code":"4.0",
    "gn:asciiname":"Guojiahe",
    "gn:country_code":"CN",
    "gn:dem":3,
    "gn:feature_class":"P",
    "gn:feature_code":"PPL",
    "gn:name":"Guojiahe",
    "gn:population":0,
    "gn:timezone":"Asia/Shanghai",
    "iso:country":"CN",
    "name:zho_x_preferred":[
        "Guojiahe"
    ],
    "name:zho_x_variant":[
        "\u90ed\u5bb6\u6cb3"
    ],
    "wof:name":"Guojiahe",
    "wof:placetype":"locality"
},
  "geometry": {"coordinates":[119.74214000000001,34.23976],"type":"Point"}
}