{
  "type": "Feature",
  "properties": {
    "gn:admin1_code":"10",
    "gn:asciiname":"Dongliugou",
    "gn:country_code":"CN",
    "gn:dem":509,
    "gn:feature_class":"P",
    "gn:feature_code":"PPL",
    "gn:name":"Dongliugou",
    "gn:population":0,
    "gn:timezone":"Asia/Shanghai",
    "iso:country":"CN",
    "name:zho_x_preferred":[
        "\u4e1c\u516d\u6c9f"
    ],
    "wof:name":"Dongliugou",
    "wof:placetype":"locality"
},
  "geometry": {"coordinates":[118.38751999999999,40.99243],"type":"Point"}
}