{
  "type": "Feature",
  "properties": {
    "gn:admin1_code":"11.0",
    "gn:asciiname":"Panguiling",
    "gn:country_code":"CN",
    "gn:dem":97,
    "gn:feature_class":"P",
    "gn:feature_code":"PPL",
    "gn:name":"Panguiling",
    "gn:population":0,
    "gn:timezone":"Asia/Shanghai",
    "iso:country":"CN",
    "name:zho_x_preferred":[
        "\u6500\u6842\u5cad"
    ],
    "wof:name":"Panguiling",
    "wof:placetype":"locality"
},
  "geometry": {"coordinates":[112.97190999999999,26.80813],"type":"Point"}
}