{
  "type": "Feature",
  "properties": {
    "gn:admin1_code":"5.0",
    "gn:asciiname":"Fengxiantun",
    "gn:country_code":"CN",
    "gn:dem":523,
    "gn:feature_class":"P",
    "gn:feature_code":"PPL",
    "gn:name":"Fengxiantun",
    "gn:population":0,
    "gn:timezone":"Asia/Shanghai",
    "iso:country":"CN",
    "name:zho_x_preferred":[
        "\u4e30\u9c9c\u5c6f"
    ],
    "wof:name":"Fengxiantun",
    "wof:placetype":"locality"
},
  "geometry": {"coordinates":[128.03396000000001,43.50861],"type":"Point"}
}