{
  "type": "Feature",
  "properties": {
    "gn:admin1_code":"30.0",
    "gn:asciiname":"Xixiangcun",
    "gn:country_code":"CN",
    "gn:dem":107,
    "gn:feature_class":"P",
    "gn:feature_code":"PPL",
    "gn:name":"Xixiangcun",
    "gn:population":0,
    "gn:timezone":"Asia/Shanghai",
    "iso:country":"CN",
    "name:zho_x_preferred":[
        "\u897f\u5ec2\u6751"
    ],
    "wof:name":"Xixiangcun",
    "wof:placetype":"locality"
},
  "geometry": {"coordinates":[116.20128,23.95506],"type":"Point"}
}