{
  "type": "Feature",
  "properties": {
    "gn:admin1_code":"16.0",
    "gn:asciiname":"Yaodaitian",
    "gn:country_code":"CN",
    "gn:dem":724,
    "gn:feature_class":"P",
    "gn:feature_code":"PPL",
    "gn:name":"Yaodaitian",
    "gn:population":0,
    "gn:timezone":"Asia/Shanghai",
    "iso:country":"CN",
    "name:zho_x_preferred":[
        "\u8170\u5e26\u7530"
    ],
    "wof:name":"Yaodaitian",
    "wof:placetype":"locality"
},
  "geometry": {"coordinates":[106.239,24.3627],"type":"Point"}
}