{
  "type": "Feature",
  "properties": {
    "gn:admin1_code":"14.0",
    "gn:asciiname":"Yada",
    "gn:country_code":"CN",
    "gn:dem":3868,
    "gn:feature_class":"P",
    "gn:feature_code":"PPL",
    "gn:name":"Yada",
    "gn:population":0,
    "gn:timezone":"Asia/Urumqi",
    "iso:country":"CN",
    "name:zho_x_preferred":[
        "\u4e9a\u8fbe"
    ],
    "wof:name":"Yada",
    "wof:placetype":"locality"
},
  "geometry": {"coordinates":[97.54594,32.01629000000001],"type":"Point"}
}