{
  "type": "Feature",
  "properties": {
    "gn:admin1_code":"8.0",
    "gn:asciiname":"Shizhuangzicun",
    "gn:country_code":"CN",
    "gn:dem":129,
    "gn:feature_class":"P",
    "gn:feature_code":"PPL",
    "gn:name":"Shizhuangzicun",
    "gn:population":0,
    "gn:timezone":"Asia/Shanghai",
    "iso:country":"CN",
    "name:zho_x_preferred":[
        "\u77f3\u5e84\u5b50\u6751"
    ],
    "wof:name":"Shizhuangzicun",
    "wof:placetype":"locality"
},
  "geometry": {"coordinates":[124.51317,45.79509],"type":"Point"}
}