{
  "type": "Feature",
  "properties": {
    "gn:admin1_code":"32.0",
    "gn:asciiname":"Huangcunba",
    "gn:country_code":"CN",
    "gn:dem":478,
    "gn:feature_class":"P",
    "gn:feature_code":"PPL",
    "gn:name":"Huangcunba",
    "gn:population":0,
    "gn:timezone":"Asia/Shanghai",
    "iso:country":"CN",
    "name:zho_x_preferred":[
        "\u9ec4\u6751\u575d"
    ],
    "wof:name":"Huangcunba",
    "wof:placetype":"locality"
},
  "geometry": {"coordinates":[103.39838,29.95978],"type":"Point"}
}