{
  "type": "Feature",
  "properties": {
    "gn:admin1_code":"32.0",
    "gn:asciiname":"Zhangjia Heba",
    "gn:country_code":"CN",
    "gn:dem":1479,
    "gn:feature_class":"P",
    "gn:feature_code":"PPL",
    "gn:name":"Zhangjia Heba",
    "gn:population":0,
    "gn:timezone":"Asia/Shanghai",
    "iso:country":"CN",
    "name:zho_x_preferred":[
        "\u5f20\u5bb6\u6cb3\u575d"
    ],
    "wof:name":"Zhangjia Heba",
    "wof:placetype":"locality"
},
  "geometry": {"coordinates":[101.94199999999999,28.6003],"type":"Point"}
}