{
  "type": "Feature",
  "properties": {
    "gn:admin1_code":"18",
    "gn:asciiname":"Shiyakou",
    "gn:country_code":"CN",
    "gn:dem":1533,
    "gn:feature_class":"P",
    "gn:feature_code":"PPL",
    "gn:name":"Shiyakou",
    "gn:population":0,
    "gn:timezone":"Asia/Shanghai",
    "iso:country":"CN",
    "name:zho_x_preferred":[
        "\u77f3\u4e2b\u53e3"
    ],
    "wof:name":"Shiyakou",
    "wof:placetype":"locality"
},
  "geometry": {"coordinates":[105.065,25.8436],"type":"Point"}
}