{
  "type": "Feature",
  "properties": {
    "gn:admin1_code":"1.0",
    "gn:asciiname":"Zhuanqiao",
    "gn:country_code":"CN",
    "gn:dem":145,
    "gn:feature_class":"P",
    "gn:feature_code":"PPL",
    "gn:name":"Zhuanqiao",
    "gn:population":0,
    "gn:timezone":"Asia/Shanghai",
    "iso:country":"CN",
    "name:und_x_variant":[
        "Chuan-ch\u2019iao-chen",
        "Chuan-ch\u2019iao",
        "Zhuanqiao"
    ],
    "name:zho_x_preferred":[
        "\u7816\u6865"
    ],
    "wof:name":"Zhuanqiao",
    "wof:placetype":"locality"
},
  "geometry": {"coordinates":[119.48962,31.12262],"type":"Point"}
}