{
  "type": "Feature",
  "properties": {
    "gn:admin1_code":"11",
    "gn:asciiname":"Shimentou",
    "gn:country_code":"CN",
    "gn:dem":180,
    "gn:feature_class":"P",
    "gn:feature_code":"PPL",
    "gn:name":"Shimentou",
    "gn:population":0,
    "gn:timezone":"Asia/Shanghai",
    "iso:country":"CN",
    "name:und_x_variant":[
        "\u77f3\u95e8\u5934",
        "Shimentou"
    ],
    "wof:name":"Shimentou",
    "wof:placetype":"locality"
},
  "geometry": {"coordinates":[112.30056,25.78917],"type":"Point"}
}