{
  "type": "Feature",
  "properties": {
    "gn:admin1_code":"2.0",
    "gn:asciiname":"Taipingzhu",
    "gn:country_code":"CN",
    "gn:dem":59,
    "gn:feature_class":"P",
    "gn:feature_code":"PPL",
    "gn:name":"Taipingzhu",
    "gn:population":0,
    "gn:timezone":"Asia/Shanghai",
    "iso:country":"CN",
    "name:zho_x_preferred":[
        "\u592a\u5e73\u795d"
    ],
    "wof:name":"Taipingzhu",
    "wof:placetype":"locality"
},
  "geometry": {"coordinates":[119.31871,29.20708],"type":"Point"}
}