{
  "type": "Feature",
  "properties": {
    "gn:admin1_code":"4.0",
    "gn:asciiname":"Shazitou",
    "gn:country_code":"CN",
    "gn:dem":2,
    "gn:feature_class":"P",
    "gn:feature_code":"PPL",
    "gn:name":"Shazitou",
    "gn:population":0,
    "gn:timezone":"Asia/Shanghai",
    "iso:country":"CN",
    "name:zho_x_preferred":[
        "Shazitou"
    ],
    "name:zho_x_variant":[
        "\u6c99\u5b50\u5934"
    ],
    "wof:name":"Shazitou",
    "wof:placetype":"locality"
},
  "geometry": {"coordinates":[119.99693000000001,33.25086],"type":"Point"}
}