{
  "type": "Feature",
  "properties": {
    "gn:admin1_code":"9.0",
    "gn:asciiname":"Nianpanzhuang",
    "gn:country_code":"CN",
    "gn:dem":214,
    "gn:feature_class":"P",
    "gn:feature_code":"PPL",
    "gn:name":"Nianpanzhuang",
    "gn:population":0,
    "gn:timezone":"Asia/Shanghai",
    "iso:country":"CN",
    "name:und_x_variant":[
        "\u78be\u76d8\u5e84",
        "Nianpanzhuang"
    ],
    "wof:name":"Nianpanzhuang",
    "wof:placetype":"locality"
},
  "geometry": {"coordinates":[112.88396000000002,33.42109],"type":"Point"}
}