{
  "type": "Feature",
  "properties": {
    "gn:admin1_code":"26.0",
    "gn:asciiname":"Moshancun",
    "gn:country_code":"CN",
    "gn:dem":1022,
    "gn:feature_class":"P",
    "gn:feature_code":"PPL",
    "gn:name":"Moshancun",
    "gn:population":0,
    "gn:timezone":"Asia/Shanghai",
    "iso:country":"CN",
    "name:zho_x_preferred":[
        "\u62b9\u5c71\u6751"
    ],
    "wof:name":"Moshancun",
    "wof:placetype":"locality"
},
  "geometry": {"coordinates":[110.27929,36.95949],"type":"Point"}
}