{
  "type": "Feature",
  "properties": {
    "gn:admin1_code":"25",
    "gn:asciiname":"Cuimazhuang",
    "gn:country_code":"CN",
    "gn:dem":78,
    "gn:feature_class":"P",
    "gn:feature_code":"PPL",
    "gn:name":"Cuimazhuang",
    "gn:population":0,
    "gn:timezone":"Asia/Shanghai",
    "iso:country":"CN",
    "name:zho_x_preferred":[
        "\u50ac\u9a6c\u5e84"
    ],
    "wof:name":"Cuimazhuang",
    "wof:placetype":"locality"
},
  "geometry": {"coordinates":[116.887,36.5442],"type":"Point"}
}