{
  "type": "Feature",
  "properties": {
    "gn:admin1_code":"24.0",
    "gn:asciiname":"Shangmujiao",
    "gn:country_code":"CN",
    "gn:dem":1640,
    "gn:feature_class":"P",
    "gn:feature_code":"PPL",
    "gn:name":"Shangmujiao",
    "gn:population":0,
    "gn:timezone":"Asia/Shanghai",
    "iso:country":"CN",
    "name:und_x_variant":[
        "\u4e0a\u6728\u89d2"
    ],
    "wof:name":"Shangmujiao",
    "wof:placetype":"locality"
},
  "geometry": {"coordinates":[112.05446999999999,39.42573],"type":"Point"}
}