{
  "type": "Feature",
  "properties": {
    "gn:admin1_code":"26.0",
    "gn:asciiname":"Hanzhuangcun",
    "gn:country_code":"CN",
    "gn:dem":743,
    "gn:feature_class":"P",
    "gn:feature_code":"PPL",
    "gn:name":"Hanzhuangcun",
    "gn:population":0,
    "gn:timezone":"Asia/Shanghai",
    "iso:country":"CN",
    "name:und_x_variant":[
        "\u97e9\u5e84\u6751"
    ],
    "wof:name":"Hanzhuangcun",
    "wof:placetype":"locality"
},
  "geometry": {"coordinates":[107.81202,33.22751],"type":"Point"}
}