{
  "type": "Feature",
  "properties": {
    "gn:admin1_code":"29.0",
    "gn:asciiname":"Tulaozhai",
    "gn:country_code":"CN",
    "gn:dem":1332,
    "gn:feature_class":"P",
    "gn:feature_code":"PPL",
    "gn:name":"Tulaozhai",
    "gn:population":0,
    "gn:timezone":"Asia/Shanghai",
    "iso:country":"CN",
    "name:zho_x_preferred":[
        "\u571f\u8001\u5be8"
    ],
    "wof:name":"Tulaozhai",
    "wof:placetype":"locality"
},
  "geometry": {"coordinates":[102.61799999999999,23.0345],"type":"Point"}
}