{
  "type": "Feature",
  "properties": {
    "gn:admin1_code":"29",
    "gn:asciiname":"Jiujia",
    "gn:country_code":"CN",
    "gn:dem":1430,
    "gn:feature_class":"P",
    "gn:feature_code":"PPL",
    "gn:name":"Jiujia",
    "gn:population":0,
    "gn:timezone":"Asia/Shanghai",
    "iso:country":"CN",
    "name:zho_x_preferred":[
        "\u4e5d\u67b6"
    ],
    "wof:name":"Jiujia",
    "wof:placetype":"locality"
},
  "geometry": {"coordinates":[101.55800000000001,24.6794],"type":"Point"}
}