{
  "type": "Feature",
  "properties": {
    "gn:admin1_code":"32.0",
    "gn:asciiname":"Shama Pingzi",
    "gn:country_code":"CN",
    "gn:dem":1653,
    "gn:feature_class":"P",
    "gn:feature_code":"PPL",
    "gn:name":"Shama Pingzi",
    "gn:population":0,
    "gn:timezone":"Asia/Shanghai",
    "iso:country":"CN",
    "name:zho_x_preferred":[
        "\u6c99\u9a6c\u576a\u5b50"
    ],
    "wof:name":"Shama Pingzi",
    "wof:placetype":"locality"
},
  "geometry": {"coordinates":[103.13,27.529],"type":"Point"}
}