{
  "type": "Feature",
  "properties": {
    "gn:admin1_code":"9.0",
    "gn:asciiname":"Yangdachi",
    "gn:country_code":"CN",
    "gn:dem":502,
    "gn:feature_class":"P",
    "gn:feature_code":"PPL",
    "gn:name":"Yangdachi",
    "gn:population":0,
    "gn:timezone":"Asia/Shanghai",
    "iso:country":"CN",
    "name:zho_x_preferred":[
        "\u6768\u5927\u6c60"
    ],
    "wof:name":"Yangdachi",
    "wof:placetype":"locality"
},
  "geometry": {"coordinates":[111.89346999999999,34.68098],"type":"Point"}
}