{
  "type": "Feature",
  "properties": {
    "gn:admin1_code":"25",
    "gn:asciiname":"Nanmafan",
    "gn:country_code":"CN",
    "gn:dem":19,
    "gn:feature_class":"P",
    "gn:feature_code":"PPL",
    "gn:name":"Nanmafan",
    "gn:population":0,
    "gn:timezone":"Asia/Shanghai",
    "iso:country":"CN",
    "name:zho_x_preferred":[
        "\u5357\u9a6c\u8303"
    ],
    "wof:name":"Nanmafan",
    "wof:placetype":"locality"
},
  "geometry": {"coordinates":[118.818,36.8874],"type":"Point"}
}