{
  "type": "Feature",
  "properties": {
    "gn:admin1_code":"8.0",
    "gn:asciiname":"Banlashantun",
    "gn:country_code":"CN",
    "gn:dem":129,
    "gn:feature_class":"P",
    "gn:feature_code":"PPL",
    "gn:name":"Banlashantun",
    "gn:population":0,
    "gn:timezone":"Asia/Shanghai",
    "iso:country":"CN",
    "name:zho_x_preferred":[
        "\u534a\u62c9\u5c71\u5c6f"
    ],
    "wof:name":"Banlashantun",
    "wof:placetype":"locality"
},
  "geometry": {"coordinates":[127.54953999999999,45.909],"type":"Point"}
}