{
  "type": "Feature",
  "properties": {
    "gn:admin1_code":"19.0",
    "gn:asciiname":"Guosongchuan Shangweizi",
    "gn:country_code":"CN",
    "gn:dem":496,
    "gn:feature_class":"P",
    "gn:feature_code":"PPL",
    "gn:name":"Guosongchuan Shangweizi",
    "gn:population":0,
    "gn:timezone":"Asia/Shanghai",
    "iso:country":"CN",
    "name:zho_x_preferred":[
        "\u679c\u677e\u5ddd\u4e0a\u56f4\u5b50"
    ],
    "wof:name":"Guosongchuan Shangweizi",
    "wof:placetype":"locality"
},
  "geometry": {"coordinates":[124.98434,41.28493],"type":"Point"}
}