{
  "type": "Feature",
  "properties": {
    "gn:admin1_code":"14",
    "gn:asciiname":"Qiangcun",
    "gn:country_code":"CN",
    "gn:dem":4706,
    "gn:feature_class":"P",
    "gn:feature_code":"PPL",
    "gn:name":"Qiangcun",
    "gn:population":0,
    "gn:timezone":"Asia/Urumqi",
    "iso:country":"CN",
    "name:zho_x_preferred":[
        "\u5f3a\u6751"
    ],
    "wof:name":"Qiangcun",
    "wof:placetype":"locality"
},
  "geometry": {"coordinates":[89.2077,28.6378],"type":"Point"}
}