{
  "type": "Feature",
  "properties": {
    "gn:admin1_code":"3.0",
    "gn:asciiname":"Qilufan Tongjia",
    "gn:country_code":"CN",
    "gn:dem":62,
    "gn:feature_class":"P",
    "gn:feature_code":"PPL",
    "gn:name":"Qilufan Tongjia",
    "gn:population":0,
    "gn:timezone":"Asia/Shanghai",
    "iso:country":"CN",
    "name:zho_x_preferred":[
        "\u9f50\u8def\u7548\u7ae5\u5bb6"
    ],
    "wof:name":"Qilufan Tongjia",
    "wof:placetype":"locality"
},
  "geometry": {"coordinates":[117.44253999999999,28.35579],"type":"Point"}
}