{
  "type": "Feature",
  "properties": {
    "gn:admin1_code":"1.0",
    "gn:asciiname":"Jiangzhuangcun",
    "gn:country_code":"CN",
    "gn:dem":31,
    "gn:feature_class":"P",
    "gn:feature_code":"PPL",
    "gn:name":"Jiangzhuangcun",
    "gn:population":0,
    "gn:timezone":"Asia/Shanghai",
    "iso:country":"CN",
    "name:zho_x_preferred":[
        "\u848b\u5e84\u6751"
    ],
    "wof:name":"Jiangzhuangcun",
    "wof:placetype":"locality"
},
  "geometry": {"coordinates":[116.58428000000001,33.85492],"type":"Point"}
}