{
  "type": "Feature",
  "properties": {
    "gn:admin1_code":"25.0",
    "gn:asciiname":"Guodicun",
    "gn:country_code":"CN",
    "gn:dem":38,
    "gn:feature_class":"P",
    "gn:feature_code":"PPL",
    "gn:name":"Guodicun",
    "gn:population":0,
    "gn:timezone":"Asia/Shanghai",
    "iso:country":"CN",
    "name:zho_x_preferred":[
        "\u90ed\u5824\u6751"
    ],
    "wof:name":"Guodicun",
    "wof:placetype":"locality"
},
  "geometry": {"coordinates":[115.76089,36.86442],"type":"Point"}
}