{
  "type": "Feature",
  "properties": {
    "gn:admin1_code":"29.0",
    "gn:asciiname":"Citongzi",
    "gn:country_code":"CN",
    "gn:dem":1484,
    "gn:feature_class":"P",
    "gn:feature_code":"PPL",
    "gn:name":"Citongzi",
    "gn:population":0,
    "gn:timezone":"Asia/Shanghai",
    "iso:country":"CN",
    "name:zho_x_preferred":[
        "\u523a\u6850\u5b50"
    ],
    "wof:name":"Citongzi",
    "wof:placetype":"locality"
},
  "geometry": {"coordinates":[100.86,22.6414],"type":"Point"}
}