{
  "type": "Feature",
  "properties": {
    "gn:admin1_code":"8.0",
    "gn:asciiname":"Haojia Chengzi",
    "gn:country_code":"CN",
    "gn:dem":137,
    "gn:feature_class":"P",
    "gn:feature_code":"PPL",
    "gn:name":"Haojia Chengzi",
    "gn:population":0,
    "gn:timezone":"Asia/Shanghai",
    "iso:country":"CN",
    "name:zho_x_preferred":[
        "\u90dd\u5bb6\u57ce\u5b50"
    ],
    "wof:name":"Haojia Chengzi",
    "wof:placetype":"locality"
},
  "geometry": {"coordinates":[126.61178,46.31122],"type":"Point"}
}