{
  "type": "Feature",
  "properties": {
    "gn:admin1_code":"29.0",
    "gn:asciiname":"Mabu Pingzi",
    "gn:country_code":"CN",
    "gn:dem":2036,
    "gn:feature_class":"P",
    "gn:feature_code":"PPL",
    "gn:name":"Mabu Pingzi",
    "gn:population":0,
    "gn:timezone":"Asia/Shanghai",
    "iso:country":"CN",
    "name:zho_x_preferred":[
        "\u9a6c\u5e03\u576a\u5b50"
    ],
    "wof:name":"Mabu Pingzi",
    "wof:placetype":"locality"
},
  "geometry": {"coordinates":[101.158,26.7687],"type":"Point"}
}