{
  "type": "Feature",
  "properties": {
    "gn:admin1_code":"29.0",
    "gn:asciiname":"Yangjiaqing",
    "gn:country_code":"CN",
    "gn:dem":2069,
    "gn:feature_class":"P",
    "gn:feature_code":"PPL",
    "gn:name":"Yangjiaqing",
    "gn:population":0,
    "gn:timezone":"Asia/Shanghai",
    "iso:country":"CN",
    "name:zho_x_preferred":[
        "\u6768\u5bb6\u7b90"
    ],
    "wof:name":"Yangjiaqing",
    "wof:placetype":"locality"
},
  "geometry": {"coordinates":[103.367,26.5927],"type":"Point"}
}