{
  "type": "Feature",
  "properties": {
    "gn:admin1_code":"9.0",
    "gn:asciiname":"Mayigou",
    "gn:country_code":"CN",
    "gn:dem":959,
    "gn:feature_class":"P",
    "gn:feature_code":"PPL",
    "gn:name":"Mayigou",
    "gn:population":0,
    "gn:timezone":"Asia/Shanghai",
    "iso:country":"CN",
    "name:zho_x_preferred":[
        "\u8682\u8681\u6c9f"
    ],
    "wof:name":"Mayigou",
    "wof:placetype":"locality"
},
  "geometry": {"coordinates":[111.98899,33.44264],"type":"Point"}
}