{
  "type": "Feature",
  "properties": {
    "gn:admin1_code":"11.0",
    "gn:asciiname":"Qishiwan",
    "gn:country_code":"CN",
    "gn:dem":103,
    "gn:feature_class":"P",
    "gn:feature_code":"PPL",
    "gn:name":"Qishiwan",
    "gn:population":0,
    "gn:timezone":"Asia/Shanghai",
    "iso:country":"CN",
    "name:zho_x_preferred":[
        "\u4f01\u77f3\u6e7e"
    ],
    "wof:name":"Qishiwan",
    "wof:placetype":"locality"
},
  "geometry": {"coordinates":[112.18428,28.3618],"type":"Point"}
}