{
  "type": "Feature",
  "properties": {
    "gn:admin1_code":"4.0",
    "gn:asciiname":"Fengyang Sanzu",
    "gn:country_code":"CN",
    "gn:dem":0,
    "gn:feature_class":"P",
    "gn:feature_code":"PPLF",
    "gn:name":"Fengyang Sanzu",
    "gn:population":0,
    "gn:timezone":"Asia/Shanghai",
    "iso:country":"CN",
    "name:zho_x_preferred":[
        "\u51e4\u6d0b\u4e09\u7ec4"
    ],
    "wof:name":"Fengyang Sanzu",
    "wof:placetype":"locality"
},
  "geometry": {"coordinates":[120.33199999999999,33.3441],"type":"Point"}
}