{
  "type": "Feature",
  "properties": {
    "gn:admin1_code":"3.0",
    "gn:asciiname":"Jiangtian",
    "gn:country_code":"CN",
    "gn:dem":25,
    "gn:feature_class":"P",
    "gn:feature_code":"PPL",
    "gn:name":"Jiangtian",
    "gn:population":0,
    "gn:timezone":"Asia/Shanghai",
    "iso:country":"CN",
    "name:und_x_variant":[
        "\u6c5f\u7530"
    ],
    "name:zho_x_preferred":[
        "\u6c5f\u7530\u9547"
    ],
    "wof:name":"Jiangtian",
    "wof:placetype":"locality"
},
  "geometry": {"coordinates":[116.61471,28.63087],"type":"Point"}
}