{
  "type": "Feature",
  "properties": {
    "gn:admin1_code":"19.0",
    "gn:asciiname":"Xiaoyugou",
    "gn:country_code":"CN",
    "gn:dem":48,
    "gn:feature_class":"P",
    "gn:feature_code":"PPL",
    "gn:name":"Xiaoyugou",
    "gn:population":0,
    "gn:timezone":"Asia/Shanghai",
    "iso:country":"CN",
    "name:zho_x_preferred":[
        "\u5c0f\u4e8e\u6c9f"
    ],
    "wof:name":"Xiaoyugou",
    "wof:placetype":"locality"
},
  "geometry": {"coordinates":[122.298,39.582],"type":"Point"}
}