{
  "type": "Feature",
  "properties": {
    "gn:admin1_code":"16.0",
    "gn:asciiname":"Nayao",
    "gn:country_code":"CN",
    "gn:dem":618,
    "gn:feature_class":"P",
    "gn:feature_code":"PPL",
    "gn:name":"Nayao",
    "gn:population":0,
    "gn:timezone":"Asia/Shanghai",
    "iso:country":"CN",
    "name:zho_x_preferred":[
        "\u7eb3\u8170"
    ],
    "wof:name":"Nayao",
    "wof:placetype":"locality"
},
  "geometry": {"coordinates":[107.28700000000001,25.2526],"type":"Point"}
}