{
  "type": "Feature",
  "properties": {
    "gn:admin1_code":"5",
    "gn:asciiname":"Yiqisong",
    "gn:country_code":"CN",
    "gn:dem":430,
    "gn:feature_class":"P",
    "gn:feature_code":"PPL",
    "gn:name":"Yiqisong",
    "gn:population":0,
    "gn:timezone":"Asia/Shanghai",
    "iso:country":"CN",
    "name:zho_x_preferred":[
        "\u610f\u6c14\u677e"
    ],
    "wof:name":"Yiqisong",
    "wof:placetype":"locality"
},
  "geometry": {"coordinates":[127.97199999999999,43.8151],"type":"Point"}
}