{
  "type": "Feature",
  "properties": {
    "gn:admin1_code":"2.0",
    "gn:asciiname":"Xuekeng",
    "gn:country_code":"CN",
    "gn:dem":514,
    "gn:feature_class":"P",
    "gn:feature_code":"PPL",
    "gn:name":"Xuekeng",
    "gn:population":0,
    "gn:timezone":"Asia/Shanghai",
    "iso:country":"CN",
    "name:zho_x_preferred":[
        "\u7a74\u5751"
    ],
    "wof:name":"Xuekeng",
    "wof:placetype":"locality"
},
  "geometry": {"coordinates":[118.70938,28.36872],"type":"Point"}
}