{
  "type": "Feature",
  "properties": {
    "gn:admin1_code":"16.0",
    "gn:asciiname":"Xiayao",
    "gn:country_code":"CN",
    "gn:dem":691,
    "gn:feature_class":"P",
    "gn:feature_code":"PPL",
    "gn:name":"Xiayao",
    "gn:population":0,
    "gn:timezone":"Asia/Shanghai",
    "iso:country":"CN",
    "name:zho_x_preferred":[
        "\u4e0b\u5c27"
    ],
    "wof:name":"Xiayao",
    "wof:placetype":"locality"
},
  "geometry": {"coordinates":[107.889,25.1235],"type":"Point"}
}