{
  "type": "Feature",
  "properties": {
    "gn:admin1_code":"5.0",
    "gn:asciiname":"Xiushuicun",
    "gn:country_code":"CN",
    "gn:dem":385,
    "gn:feature_class":"P",
    "gn:feature_code":"PPL",
    "gn:name":"Xiushuicun",
    "gn:population":0,
    "gn:timezone":"Asia/Shanghai",
    "iso:country":"CN",
    "name:zho_x_preferred":[
        "\u79c0\u6c34\u6751"
    ],
    "wof:name":"Xiushuicun",
    "wof:placetype":"locality"
},
  "geometry": {"coordinates":[125.3185,42.59842],"type":"Point"}
}