{
  "type": "Feature",
  "properties": {
    "gn:admin1_code":"30.0",
    "gn:asciiname":"Shenniao",
    "gn:country_code":"CN",
    "gn:dem":332,
    "gn:feature_class":"P",
    "gn:feature_code":"PPL",
    "gn:name":"Shenniao",
    "gn:population":0,
    "gn:timezone":"Asia/Shanghai",
    "iso:country":"CN",
    "name:zho_x_preferred":[
        "\u6df1\u9e1f"
    ],
    "wof:name":"Shenniao",
    "wof:placetype":"locality"
},
  "geometry": {"coordinates":[111.67928000000001,22.55499],"type":"Point"}
}