{
  "type": "Feature",
  "properties": {
    "gn:admin1_code":"12.0",
    "gn:asciiname":"Lannifan",
    "gn:country_code":"CN",
    "gn:dem":38,
    "gn:feature_class":"P",
    "gn:feature_code":"PPL",
    "gn:name":"Lannifan",
    "gn:population":0,
    "gn:timezone":"Asia/Shanghai",
    "iso:country":"CN",
    "name:und_x_variant":[
        "\u6ee5\u6ce5\u7548"
    ],
    "wof:name":"Lannifan",
    "wof:placetype":"locality"
},
  "geometry": {"coordinates":[114.79725000000001,30.17995],"type":"Point"}
}