{
  "type": "Feature",
  "properties": {
    "gn:admin1_code":"1.0",
    "gn:asciiname":"Sunbaicun",
    "gn:country_code":"CN",
    "gn:dem":28,
    "gn:feature_class":"P",
    "gn:feature_code":"PPL",
    "gn:name":"Sunbaicun",
    "gn:population":0,
    "gn:timezone":"Asia/Shanghai",
    "iso:country":"CN",
    "name:zho_x_preferred":[
        "\u5b59\u767d\u6751"
    ],
    "wof:name":"Sunbaicun",
    "wof:placetype":"locality"
},
  "geometry": {"coordinates":[116.93742,33.34392],"type":"Point"}
}