{
  "type": "Feature",
  "properties": {
    "gn:admin1_code":"32.0",
    "gn:asciiname":"Degong",
    "gn:country_code":"CN",
    "gn:dem":3630,
    "gn:feature_class":"P",
    "gn:feature_code":"PPL",
    "gn:name":"Degong",
    "gn:population":0,
    "gn:timezone":"Asia/Shanghai",
    "iso:country":"CN",
    "name:zho_x_preferred":[
        "\u5f97\u9f9a"
    ],
    "wof:name":"Degong",
    "wof:placetype":"locality"
},
  "geometry": {"coordinates":[99.32599999999999,28.5463],"type":"Point"}
}