{
  "type": "Feature",
  "properties": {
    "gn:admin1_code":"12.0",
    "gn:asciiname":"Baozhen Aoshang",
    "gn:country_code":"CN",
    "gn:dem":1186,
    "gn:feature_class":"P",
    "gn:feature_code":"PPL",
    "gn:name":"Baozhen Aoshang",
    "gn:population":0,
    "gn:timezone":"Asia/Shanghai",
    "iso:country":"CN",
    "name:zho_x_preferred":[
        "\u5821\u9547\u5773\u4e0a"
    ],
    "wof:name":"Baozhen Aoshang",
    "wof:placetype":"locality"
},
  "geometry": {"coordinates":[110.74473999999999,30.61959],"type":"Point"}
}