{
  "type": "Feature",
  "properties": {
    "gn:admin1_code":"13.0",
    "gn:asciiname":"Atelaxi",
    "gn:country_code":"CN",
    "gn:dem":1348,
    "gn:feature_class":"P",
    "gn:feature_code":"PPL",
    "gn:name":"Atelaxi",
    "gn:population":0,
    "gn:timezone":"Asia/Shanghai",
    "iso:country":"CN",
    "name:und_x_variant":[
        "\u963f\u7279\u62c9\u897f"
    ],
    "wof:name":"Atelaxi",
    "wof:placetype":"locality"
},
  "geometry": {"coordinates":[76.98051,38.16709],"type":"Point"}
}