{
  "type": "Feature",
  "properties": {
    "gn:admin1_code":"29.0",
    "gn:asciiname":"Zhuangzishang",
    "gn:country_code":"CN",
    "gn:dem":1771,
    "gn:feature_class":"P",
    "gn:feature_code":"PPL",
    "gn:name":"Zhuangzishang",
    "gn:population":0,
    "gn:timezone":"Asia/Shanghai",
    "iso:country":"CN",
    "name:zho_x_preferred":[
        "\u5e84\u5b50\u4e0a"
    ],
    "wof:name":"Zhuangzishang",
    "wof:placetype":"locality"
},
  "geometry": {"coordinates":[104.327,25.5712],"type":"Point"}
}