{
  "type": "Feature",
  "properties": {
    "gn:admin1_code":"13",
    "gn:asciiname":"Yiwutuan Yilinglian",
    "gn:country_code":"CN",
    "gn:dem":1004,
    "gn:feature_class":"P",
    "gn:feature_code":"PPL",
    "gn:name":"Yiwutuan Yilinglian",
    "gn:population":0,
    "gn:timezone":"Asia/Shanghai",
    "iso:country":"CN",
    "name:und_x_variant":[
        "\u4e00\u4e94\u56e2\u4e00\u96f6\u8fde"
    ],
    "wof:name":"Yiwutuan Yilinglian",
    "wof:placetype":"locality"
},
  "geometry": {"coordinates":[81.61348000000002,40.66871],"type":"Point"}
}