{
  "type": "Feature",
  "properties": {
    "gn:admin1_code":"25.0",
    "gn:asciiname":"Shiliu Litou",
    "gn:country_code":"CN",
    "gn:dem":31,
    "gn:feature_class":"P",
    "gn:feature_code":"PPL",
    "gn:name":"Shiliu Litou",
    "gn:population":0,
    "gn:timezone":"Asia/Shanghai",
    "iso:country":"CN",
    "name:zho_x_preferred":[
        "\u5341\u516d\u91cc\u5934"
    ],
    "wof:name":"Shiliu Litou",
    "wof:placetype":"locality"
},
  "geometry": {"coordinates":[121.63491999999999,37.33536],"type":"Point"}
}