{
  "type": "Feature",
  "properties": {
    "gn:admin1_code":"9.0",
    "gn:asciiname":"Yangtun",
    "gn:country_code":"CN",
    "gn:dem":63,
    "gn:feature_class":"P",
    "gn:feature_code":"PPL",
    "gn:name":"Yangtun",
    "gn:population":0,
    "gn:timezone":"Asia/Shanghai",
    "iso:country":"CN",
    "name:zho_x_preferred":[
        "\u6768\u5c6f"
    ],
    "wof:name":"Yangtun",
    "wof:placetype":"locality"
},
  "geometry": {"coordinates":[114.08634000000001,33.14731],"type":"Point"}
}