{
  "type": "Feature",
  "properties": {
    "gn:admin1_code":"15.0",
    "gn:asciiname":"Mobeihou",
    "gn:country_code":"CN",
    "gn:dem":1424,
    "gn:feature_class":"P",
    "gn:feature_code":"PPL",
    "gn:name":"Mobeihou",
    "gn:population":0,
    "gn:timezone":"Asia/Shanghai",
    "iso:country":"CN",
    "name:und_x_variant":[
        "\u78e8\u80cc\u540e"
    ],
    "wof:name":"Mobeihou",
    "wof:placetype":"locality"
},
  "geometry": {"coordinates":[105.55155000000001,33.19662],"type":"Point"}
}