{
  "type": "Feature",
  "properties": {
    "gn:admin1_code":"7",
    "gn:asciiname":"Pingzhuang",
    "gn:country_code":"CN",
    "gn:dem":212,
    "gn:feature_class":"P",
    "gn:feature_code":"PPL",
    "gn:name":"Pingzhuang",
    "gn:population":0,
    "gn:timezone":"Asia/Shanghai",
    "iso:country":"CN",
    "name:und_x_variant":[
        "\u576a\u5e84"
    ],
    "wof:name":"Pingzhuang",
    "wof:placetype":"locality"
},
  "geometry": {"coordinates":[119.70528,27.24278],"type":"Point"}
}