{
  "type": "Feature",
  "properties": {
    "gn:admin1_code":"26.0",
    "gn:asciiname":"Luoquanyan",
    "gn:country_code":"CN",
    "gn:dem":1177,
    "gn:feature_class":"P",
    "gn:feature_code":"PPL",
    "gn:name":"Luoquanyan",
    "gn:population":0,
    "gn:timezone":"Asia/Shanghai",
    "iso:country":"CN",
    "name:zho_x_preferred":[
        "\u7f57\u5708\u5ca9"
    ],
    "wof:name":"Luoquanyan",
    "wof:placetype":"locality"
},
  "geometry": {"coordinates":[108.00157,32.27086],"type":"Point"}
}