{
  "type": "Feature",
  "properties": {
    "gn:admin1_code":"02",
    "gn:asciiname":"Shaoxingshetou",
    "gn:country_code":"CN",
    "gn:dem":5,
    "gn:feature_class":"P",
    "gn:feature_code":"PPL",
    "gn:name":"Shaoxingshetou",
    "gn:population":0,
    "gn:timezone":"Asia/Shanghai",
    "iso:country":"CN",
    "name:und_x_variant":[
        "\u7ecd\u5174\u820d\u5934",
        "Shao-hsing-sha-t\u2019ou"
    ],
    "wof:name":"Shaoxingshetou",
    "wof:placetype":"locality"
},
  "geometry": {"coordinates":[121.23361,30.24333],"type":"Point"}
}