{
  "type": "Feature",
  "properties": {
    "gn:admin1_code":"14.0",
    "gn:asciiname":"Rongqiaocuo",
    "gn:country_code":"CN",
    "gn:dem":4302,
    "gn:feature_class":"P",
    "gn:feature_code":"PPL",
    "gn:name":"Rongqiaocuo",
    "gn:population":0,
    "gn:timezone":"Asia/Urumqi",
    "iso:country":"CN",
    "name:zho_x_preferred":[
        "\u8363\u5de7\u9519"
    ],
    "wof:name":"Rongqiaocuo",
    "wof:placetype":"locality"
},
  "geometry": {"coordinates":[97.79130000000001,32.12226],"type":"Point"}
}