{
  "type": "Feature",
  "properties": {
    "gn:admin1_code":"26",
    "gn:asciiname":"Huaide",
    "gn:country_code":"CN",
    "gn:dem":394,
    "gn:feature_class":"P",
    "gn:feature_code":"PPL",
    "gn:name":"Huaide",
    "gn:population":0,
    "gn:timezone":"Asia/Shanghai",
    "iso:country":"CN",
    "name:und_x_variant":[
        "Renyicun",
        "Huaide"
    ],
    "name:zho_x_preferred":[
        "\u69d0\u5fb7"
    ],
    "wof:name":"Huaide",
    "wof:placetype":"locality"
},
  "geometry": {"coordinates":[109.52537,34.88128],"type":"Point"}
}