{
  "type": "Feature",
  "properties": {
    "gn:admin1_code":"10.0",
    "gn:asciiname":"Yujiatun",
    "gn:country_code":"CN",
    "gn:dem":1112,
    "gn:feature_class":"P",
    "gn:feature_code":"PPL",
    "gn:name":"Yujiatun",
    "gn:population":0,
    "gn:timezone":"Asia/Shanghai",
    "iso:country":"CN",
    "name:zho_x_preferred":[
        "\u4fde\u5bb6\u5c6f"
    ],
    "wof:name":"Yujiatun",
    "wof:placetype":"locality"
},
  "geometry": {"coordinates":[114.54492999999999,40.44357],"type":"Point"}
}