{
  "type": "Feature",
  "properties": {
    "gn:admin1_code":"3.0",
    "gn:asciiname":"Qiyuan",
    "gn:country_code":"CN",
    "gn:dem":162,
    "gn:feature_class":"P",
    "gn:feature_code":"PPL",
    "gn:name":"Qiyuan",
    "gn:population":0,
    "gn:timezone":"Asia/Shanghai",
    "iso:country":"CN",
    "name:und_x_variant":[
        "\u7941\u6c85"
    ],
    "wof:name":"Qiyuan",
    "wof:placetype":"locality"
},
  "geometry": {"coordinates":[114.35612999999999,29.18747],"type":"Point"}
}