{
  "type": "Feature",
  "properties": {
    "gn:admin1_code":"9.0",
    "gn:asciiname":"Huangtuya",
    "gn:country_code":"CN",
    "gn:dem":315,
    "gn:feature_class":"P",
    "gn:feature_code":"PPL",
    "gn:name":"Huangtuya",
    "gn:population":0,
    "gn:timezone":"Asia/Shanghai",
    "iso:country":"CN",
    "name:und_x_variant":[
        "\u9ec4\u571f\u5c88",
        "Huangtuya"
    ],
    "wof:name":"Huangtuya",
    "wof:placetype":"locality"
},
  "geometry": {"coordinates":[112.40375,33.27192],"type":"Point"}
}