{
  "type": "Feature",
  "properties": {
    "gn:admin1_code":"19.0",
    "gn:asciiname":"Sifangtaicun",
    "gn:country_code":"CN",
    "gn:dem":16,
    "gn:feature_class":"P",
    "gn:feature_code":"PPL",
    "gn:name":"Sifangtaicun",
    "gn:population":0,
    "gn:timezone":"Asia/Shanghai",
    "iso:country":"CN",
    "name:zho_x_preferred":[
        "\u56db\u65b9\u53f0\u6751"
    ],
    "wof:name":"Sifangtaicun",
    "wof:placetype":"locality"
},
  "geometry": {"coordinates":[121.744,41.399],"type":"Point"}
}