{
  "type": "Feature",
  "properties": {
    "gn:admin1_code":"3.0",
    "gn:asciiname":"Maowu",
    "gn:country_code":"CN",
    "gn:dem":63,
    "gn:feature_class":"P",
    "gn:feature_code":"PPL",
    "gn:name":"Maowu",
    "gn:population":0,
    "gn:timezone":"Asia/Shanghai",
    "iso:country":"CN",
    "name:und_x_variant":[
        "\u6bdb\u575e"
    ],
    "wof:name":"Maowu",
    "wof:placetype":"locality"
},
  "geometry": {"coordinates":[117.28926,29.56812],"type":"Point"}
}