{
  "type": "Feature",
  "properties": {
    "gn:admin1_code":"19.0",
    "gn:asciiname":"Fangshendi",
    "gn:country_code":"CN",
    "gn:dem":20,
    "gn:feature_class":"P",
    "gn:feature_code":"PPL",
    "gn:name":"Fangshendi",
    "gn:population":0,
    "gn:timezone":"Asia/Shanghai",
    "iso:country":"CN",
    "name:zho_x_preferred":[
        "\u623f\u8eab\u5730"
    ],
    "wof:name":"Fangshendi",
    "wof:placetype":"locality"
},
  "geometry": {"coordinates":[122.834,41.7233],"type":"Point"}
}