{
  "type": "Feature",
  "properties": {
    "gn:admin1_code":"18.0",
    "gn:asciiname":"Xiaguanzhuang",
    "gn:country_code":"CN",
    "gn:dem":764,
    "gn:feature_class":"P",
    "gn:feature_code":"PPL",
    "gn:name":"Xiaguanzhuang",
    "gn:population":0,
    "gn:timezone":"Asia/Shanghai",
    "iso:country":"CN",
    "name:zho_x_preferred":[
        "\u4e0b\u5173\u5e84"
    ],
    "wof:name":"Xiaguanzhuang",
    "wof:placetype":"locality"
},
  "geometry": {"coordinates":[108.48099999999999,27.2858],"type":"Point"}
}