{
  "type": "Feature",
  "properties": {
    "gn:admin1_code":"24.0",
    "gn:asciiname":"Shangpianqiao",
    "gn:country_code":"CN",
    "gn:dem":624,
    "gn:feature_class":"P",
    "gn:feature_code":"PPL",
    "gn:name":"Shangpianqiao",
    "gn:population":0,
    "gn:timezone":"Asia/Shanghai",
    "iso:country":"CN",
    "name:und_x_variant":[
        "\u4e0a\u504f\u6865"
    ],
    "wof:name":"Shangpianqiao",
    "wof:placetype":"locality"
},
  "geometry": {"coordinates":[111.41816,35.3581],"type":"Point"}
}