{
  "type": "Feature",
  "properties": {
    "gn:admin1_code":"15.0",
    "gn:asciiname":"Secunna",
    "gn:country_code":"CN",
    "gn:dem":2967,
    "gn:feature_class":"P",
    "gn:feature_code":"PPL",
    "gn:name":"Secunna",
    "gn:population":0,
    "gn:timezone":"Asia/Shanghai",
    "iso:country":"CN",
    "name:und_x_variant":[
        "\u8272\u6751\u7eb3"
    ],
    "wof:name":"Secunna",
    "wof:placetype":"locality"
},
  "geometry": {"coordinates":[103.35577000000001,34.45158],"type":"Point"}
}