{
  "type": "Feature",
  "properties": {
    "gn:admin1_code":"24.0",
    "gn:asciiname":"Rulaicun",
    "gn:country_code":"CN",
    "gn:dem":1060,
    "gn:feature_class":"P",
    "gn:feature_code":"PPL",
    "gn:name":"Rulaicun",
    "gn:population":0,
    "gn:timezone":"Asia/Shanghai",
    "iso:country":"CN",
    "name:zho_x_preferred":[
        "\u5982\u6765\u6751"
    ],
    "wof:name":"Rulaicun",
    "wof:placetype":"locality"
},
  "geometry": {"coordinates":[111.592,37.07346],"type":"Point"}
}