{
  "type": "Feature",
  "properties": {
    "gn:admin1_code":"29.0",
    "gn:asciiname":"Lengshui",
    "gn:country_code":"CN",
    "gn:dem":581,
    "gn:feature_class":"P",
    "gn:feature_code":"PPL",
    "gn:name":"Lengshui",
    "gn:population":0,
    "gn:timezone":"Asia/Shanghai",
    "iso:country":"CN",
    "name:zho_x_preferred":[
        "\u51b7\u6c34"
    ],
    "wof:name":"Lengshui",
    "wof:placetype":"locality"
},
  "geometry": {"coordinates":[104.1277,28.24285],"type":"Point"}
}