{
  "type": "Feature",
  "properties": {
    "gn:admin1_code":"12",
    "gn:asciiname":"Mishi",
    "gn:country_code":"CN",
    "gn:dem":41,
    "gn:feature_class":"P",
    "gn:feature_code":"PPLA4",
    "gn:name":"Mishi",
    "gn:population":0,
    "gn:timezone":"Asia/Shanghai",
    "iso:country":"CN",
    "name:und_x_variant":[
        "Mi-t\u2019o-ssu",
        "Mituosi",
        "Mishi",
        "\u5f25\u5e02",
        "Mishi Zhen",
        "\u5f25\u5e02\u9547"
    ],
    "wof:name":"Mishi",
    "wof:placetype":"locality"
},
  "geometry": {"coordinates":[112.11847,30.22751],"type":"Point"}
}