{
  "type": "Feature",
  "properties": {
    "gn:admin1_code":"2.0",
    "gn:asciiname":"Hutoudu",
    "gn:country_code":"CN",
    "gn:dem":15,
    "gn:feature_class":"P",
    "gn:feature_code":"PPL",
    "gn:name":"Hutoudu",
    "gn:population":0,
    "gn:timezone":"Asia/Shanghai",
    "iso:country":"CN",
    "name:zho_x_preferred":[
        "\u6e56\u5934\u6e21"
    ],
    "wof:name":"Hutoudu",
    "wof:placetype":"locality"
},
  "geometry": {"coordinates":[120.85054,29.86666],"type":"Point"}
}