{
  "type": "Feature",
  "properties": {
    "gn:admin1_code":"7",
    "gn:asciiname":"Yanhoukeng",
    "gn:country_code":"CN",
    "gn:dem":1221,
    "gn:feature_class":"P",
    "gn:feature_code":"PPL",
    "gn:name":"Yanhoukeng",
    "gn:population":0,
    "gn:timezone":"Asia/Shanghai",
    "iso:country":"CN",
    "name:und_x_variant":[
        "\u5ca9\u540e\u5751"
    ],
    "wof:name":"Yanhoukeng",
    "wof:placetype":"locality"
},
  "geometry": {"coordinates":[119.18194,27.04778],"type":"Point"}
}