{
  "type": "Feature",
  "properties": {
    "gn:admin1_code":"25",
    "gn:asciiname":"Jianghai",
    "gn:country_code":"CN",
    "gn:dem":43,
    "gn:feature_class":"P",
    "gn:feature_code":"PPL",
    "gn:name":"Jianghai",
    "gn:population":0,
    "gn:timezone":"Asia/Shanghai",
    "iso:country":"CN",
    "name:zho_x_preferred":[
        "\u5c06\u6d77"
    ],
    "wof:name":"Jianghai",
    "wof:placetype":"locality"
},
  "geometry": {"coordinates":[115.84798000000001,36.03924],"type":"Point"}
}