{
  "type": "Feature",
  "properties": {
    "gn:admin1_code":"11.0",
    "gn:asciiname":"Niuhulan",
    "gn:country_code":"CN",
    "gn:dem":417,
    "gn:feature_class":"P",
    "gn:feature_code":"PPL",
    "gn:name":"Niuhulan",
    "gn:population":0,
    "gn:timezone":"Asia/Shanghai",
    "iso:country":"CN",
    "name:zho_x_preferred":[
        "\u725b\u6e56\u680f"
    ],
    "wof:name":"Niuhulan",
    "wof:placetype":"locality"
},
  "geometry": {"coordinates":[110.84918,28.51718],"type":"Point"}
}