{
  "type": "Feature",
  "properties": {
    "gn:admin1_code":"18",
    "gn:asciiname":"Xiqiping",
    "gn:country_code":"CN",
    "gn:dem":1816,
    "gn:feature_class":"P",
    "gn:feature_code":"PPL",
    "gn:name":"Xiqiping",
    "gn:population":0,
    "gn:timezone":"Asia/Shanghai",
    "iso:country":"CN",
    "name:zho_x_preferred":[
        "\u606f\u6c14\u576a"
    ],
    "wof:name":"Xiqiping",
    "wof:placetype":"locality"
},
  "geometry": {"coordinates":[104.86499999999999,26.5023],"type":"Point"}
}