{
  "type": "Feature",
  "properties": {
    "gn:admin1_code":"20.0",
    "gn:asciiname":"Huangxiao",
    "gn:country_code":"CN",
    "gn:dem":1510,
    "gn:feature_class":"P",
    "gn:feature_code":"PPL",
    "gn:name":"Huangxiao",
    "gn:population":0,
    "gn:timezone":"Asia/Shanghai",
    "iso:country":"CN",
    "name:und_x_variant":[
        "\u9ec4\u5c0f"
    ],
    "wof:name":"Huangxiao",
    "wof:placetype":"locality"
},
  "geometry": {"coordinates":[113.06009,41.60257],"type":"Point"}
}