{
  "type": "Feature",
  "properties": {
    "gn:admin1_code":"14.0",
    "gn:asciiname":"Saishenka",
    "gn:country_code":"CN",
    "gn:dem":4255,
    "gn:feature_class":"P",
    "gn:feature_code":"PPL",
    "gn:name":"Saishenka",
    "gn:population":0,
    "gn:timezone":"Asia/Urumqi",
    "iso:country":"CN",
    "name:zho_x_preferred":[
        "\u8d5b\u795e\u5361"
    ],
    "wof:name":"Saishenka",
    "wof:placetype":"locality"
},
  "geometry": {"coordinates":[96.41933,31.4829],"type":"Point"}
}