{
  "type": "Feature",
  "properties": {
    "gn:admin1_code":"8.0",
    "gn:asciiname":"Xinfengcun",
    "gn:country_code":"CN",
    "gn:dem":236,
    "gn:feature_class":"P",
    "gn:feature_code":"PPL",
    "gn:name":"Xinfengcun",
    "gn:population":0,
    "gn:timezone":"Asia/Shanghai",
    "iso:country":"CN",
    "name:zho_x_preferred":[
        "\u65b0\u4e30\u6751"
    ],
    "wof:name":"Xinfengcun",
    "wof:placetype":"locality"
},
  "geometry": {"coordinates":[127.54855999999999,44.58147],"type":"Point"}
}