{
  "type": "Feature",
  "properties": {
    "gn:admin1_code":"26.0",
    "gn:asciiname":"Wujia Yuanzi",
    "gn:country_code":"CN",
    "gn:dem":1109,
    "gn:feature_class":"P",
    "gn:feature_code":"PPL",
    "gn:name":"Wujia Yuanzi",
    "gn:population":0,
    "gn:timezone":"Asia/Shanghai",
    "iso:country":"CN",
    "name:zho_x_preferred":[
        "\u5434\u5bb6\u9662\u5b50"
    ],
    "wof:name":"Wujia Yuanzi",
    "wof:placetype":"locality"
},
  "geometry": {"coordinates":[109.61803999999999,33.37927],"type":"Point"}
}