{
  "type": "Feature",
  "properties": {
    "gn:admin1_code":"11",
    "gn:asciiname":"Keting",
    "gn:country_code":"CN",
    "gn:dem":296,
    "gn:feature_class":"P",
    "gn:feature_code":"PPL",
    "gn:name":"Keting",
    "gn:population":0,
    "gn:timezone":"Asia/Shanghai",
    "iso:country":"CN",
    "name:und_x_variant":[
        "\u53ef\u4ead",
        "Keting"
    ],
    "wof:name":"Keting",
    "wof:placetype":"locality"
},
  "geometry": {"coordinates":[111.97583,25.86611],"type":"Point"}
}