{
  "type": "Feature",
  "properties": {
    "gn:admin1_code":"32.0",
    "gn:asciiname":"Huilongba",
    "gn:country_code":"CN",
    "gn:dem":314,
    "gn:feature_class":"P",
    "gn:feature_code":"PPL",
    "gn:name":"Huilongba",
    "gn:population":0,
    "gn:timezone":"Asia/Shanghai",
    "iso:country":"CN",
    "name:zho_x_preferred":[
        "\u56de\u9f99\u575d"
    ],
    "wof:name":"Huilongba",
    "wof:placetype":"locality"
},
  "geometry": {"coordinates":[105.28543000000001,29.0685],"type":"Point"}
}