{
  "type": "Feature",
  "properties": {
    "gn:admin1_code":"18",
    "gn:asciiname":"Erguan",
    "gn:country_code":"CN",
    "gn:dem":1269,
    "gn:feature_class":"P",
    "gn:feature_code":"PPL",
    "gn:name":"Erguan",
    "gn:population":0,
    "gn:timezone":"Asia/Shanghai",
    "iso:country":"CN",
    "name:zho_x_preferred":[
        "\u4e8c\u5b98"
    ],
    "wof:name":"Erguan",
    "wof:placetype":"locality"
},
  "geometry": {"coordinates":[105.708,26.2372],"type":"Point"}
}