{
  "type": "Feature",
  "properties": {
    "gn:admin1_code":"16.0",
    "gn:asciiname":"Zhaojing",
    "gn:country_code":"CN",
    "gn:dem":56,
    "gn:feature_class":"P",
    "gn:feature_code":"PPL",
    "gn:name":"Zhaojing",
    "gn:population":0,
    "gn:timezone":"Asia/Shanghai",
    "iso:country":"CN",
    "name:zho_x_preferred":[
        "\u7167\u955c"
    ],
    "wof:name":"Zhaojing",
    "wof:placetype":"locality"
},
  "geometry": {"coordinates":[109.88200000000001,21.6617],"type":"Point"}
}