{
  "type": "Feature",
  "properties": {
    "gn:admin1_code":"7.0",
    "gn:asciiname":"Xiabancun",
    "gn:country_code":"CN",
    "gn:dem":347,
    "gn:feature_class":"P",
    "gn:feature_code":"PPL",
    "gn:name":"Xiabancun",
    "gn:population":0,
    "gn:timezone":"Asia/Shanghai",
    "iso:country":"CN",
    "name:und_x_variant":[
        "\u4e0b\u5742\u6751"
    ],
    "name:zho_x_preferred":[
        "\u4e0b\u5742\u6751"
    ],
    "wof:name":"Xiabancun",
    "wof:placetype":"locality"
},
  "geometry": {"coordinates":[117.43344999999999,26.40263],"type":"Point"}
}