{
  "type": "Feature",
  "properties": {
    "gn:admin1_code":"29.0",
    "gn:asciiname":"Xiaoyakou",
    "gn:country_code":"CN",
    "gn:dem":1149,
    "gn:feature_class":"P",
    "gn:feature_code":"PPL",
    "gn:name":"Xiaoyakou",
    "gn:population":0,
    "gn:timezone":"Asia/Vientiane",
    "iso:country":"CN",
    "name:zho_x_preferred":[
        "\u5c0f\u4e2b\u53e3"
    ],
    "wof:name":"Xiaoyakou",
    "wof:placetype":"locality"
},
  "geometry": {"coordinates":[101.78400000000001,21.2914],"type":"Point"}
}