{
  "type": "Feature",
  "properties": {
    "gn:admin1_code":"12.0",
    "gn:asciiname":"Tiankengwan",
    "gn:country_code":"CN",
    "gn:dem":874,
    "gn:feature_class":"P",
    "gn:feature_code":"PPL",
    "gn:name":"Tiankengwan",
    "gn:population":0,
    "gn:timezone":"Asia/Shanghai",
    "iso:country":"CN",
    "name:zho_x_preferred":[
        "\u5929\u5751\u6e7e"
    ],
    "wof:name":"Tiankengwan",
    "wof:placetype":"locality"
},
  "geometry": {"coordinates":[109.65873999999999,30.62747],"type":"Point"}
}