{
  "type": "Feature",
  "properties": {
    "gn:admin1_code":"32.0",
    "gn:asciiname":"Ri'a",
    "gn:country_code":"CN",
    "gn:dem":2652,
    "gn:feature_class":"P",
    "gn:feature_code":"PPL",
    "gn:name":"Ri\u2019a",
    "gn:population":0,
    "gn:timezone":"Asia/Shanghai",
    "iso:country":"CN",
    "name:zho_x_preferred":[
        "\u65e5\u963f"
    ],
    "name:zho_x_variant":[
        "Ri\u2019a"
    ],
    "wof:name":"Ri'a",
    "wof:placetype":"locality"
},
  "geometry": {"coordinates":[101.12188,29.54652],"type":"Point"}
}