{
  "type": "Feature",
  "properties": {
    "gn:admin1_code":"32.0",
    "gn:asciiname":"Shugenpo",
    "gn:country_code":"CN",
    "gn:dem":1308,
    "gn:feature_class":"P",
    "gn:feature_code":"PPL",
    "gn:name":"Shugenpo",
    "gn:population":0,
    "gn:timezone":"Asia/Shanghai",
    "iso:country":"CN",
    "name:zho_x_preferred":[
        "\u6811\u6839\u5761"
    ],
    "wof:name":"Shugenpo",
    "wof:placetype":"locality"
},
  "geometry": {"coordinates":[105.70099999999999,28.1212],"type":"Point"}
}