{
  "type": "Feature",
  "properties": {
    "gn:admin1_code":"1.0",
    "gn:asciiname":"Guduicun",
    "gn:country_code":"CN",
    "gn:dem":20,
    "gn:feature_class":"P",
    "gn:feature_code":"PPL",
    "gn:name":"Guduicun",
    "gn:population":0,
    "gn:timezone":"Asia/Shanghai",
    "iso:country":"CN",
    "name:zho_x_preferred":[
        "\u53e4\u5806\u6751"
    ],
    "wof:name":"Guduicun",
    "wof:placetype":"locality"
},
  "geometry": {"coordinates":[117.17822,32.59934000000001],"type":"Point"}
}