{
  "type": "Feature",
  "properties": {
    "gn:admin1_code":"2.0",
    "gn:asciiname":"Aotan",
    "gn:country_code":"CN",
    "gn:dem":135,
    "gn:feature_class":"P",
    "gn:feature_code":"PPL",
    "gn:name":"Aotan",
    "gn:population":0,
    "gn:timezone":"Asia/Shanghai",
    "iso:country":"CN",
    "name:zho_x_preferred":[
        "\u5c99\u6ee9"
    ],
    "wof:name":"Aotan",
    "wof:placetype":"locality"
},
  "geometry": {"coordinates":[118.39963,29.12389000000001],"type":"Point"}
}