{
  "type": "Feature",
  "properties": {
    "gn:admin1_code":"24.0",
    "gn:asciiname":"Nanweigoucun",
    "gn:country_code":"CN",
    "gn:dem":986,
    "gn:feature_class":"P",
    "gn:feature_code":"PPL",
    "gn:name":"Nanweigoucun",
    "gn:population":0,
    "gn:timezone":"Asia/Shanghai",
    "iso:country":"CN",
    "name:zho_x_preferred":[
        "\u5357\u5c3e\u6c9f\u6751"
    ],
    "wof:name":"Nanweigoucun",
    "wof:placetype":"locality"
},
  "geometry": {"coordinates":[110.87636999999999,37.23484000000001],"type":"Point"}
}