{
  "type": "Feature",
  "properties": {
    "gn:admin1_code":"29.0",
    "gn:asciiname":"Shuidagou",
    "gn:country_code":"CN",
    "gn:dem":576,
    "gn:feature_class":"P",
    "gn:feature_code":"PPL",
    "gn:name":"Shuidagou",
    "gn:population":0,
    "gn:timezone":"Asia/Shanghai",
    "iso:country":"CN",
    "name:zho_x_preferred":[
        "\u6c34\u6253\u6c9f"
    ],
    "wof:name":"Shuidagou",
    "wof:placetype":"locality"
},
  "geometry": {"coordinates":[103.97499999999999,28.5349],"type":"Point"}
}