{
  "type": "Feature",
  "properties": {
    "gn:admin1_code":"29.0",
    "gn:asciiname":"Dahetaoshu",
    "gn:country_code":"CN",
    "gn:dem":1922,
    "gn:feature_class":"P",
    "gn:feature_code":"PPL",
    "gn:name":"Dahetaoshu",
    "gn:population":0,
    "gn:timezone":"Asia/Shanghai",
    "iso:country":"CN",
    "name:zho_x_preferred":[
        "\u5927\u6838\u6843\u6811"
    ],
    "wof:name":"Dahetaoshu",
    "wof:placetype":"locality"
},
  "geometry": {"coordinates":[100.04600000000001,24.4679],"type":"Point"}
}