{
  "type": "Feature",
  "properties": {
    "gn:admin1_code":"32.0",
    "gn:asciiname":"Tangligou",
    "gn:country_code":"CN",
    "gn:dem":1904,
    "gn:feature_class":"P",
    "gn:feature_code":"PPL",
    "gn:name":"Tangligou",
    "gn:population":0,
    "gn:timezone":"Asia/Shanghai",
    "iso:country":"CN",
    "name:zho_x_preferred":[
        "\u7cd6\u68a8\u6c9f"
    ],
    "wof:name":"Tangligou",
    "wof:placetype":"locality"
},
  "geometry": {"coordinates":[102.21080000000001,28.52112],"type":"Point"}
}