{
  "type": "Feature",
  "properties": {
    "gn:admin1_code":"11",
    "gn:asciiname":"Damiaotou",
    "gn:country_code":"CN",
    "gn:dem":134,
    "gn:feature_class":"P",
    "gn:feature_code":"PPL",
    "gn:name":"Damiaotou",
    "gn:population":0,
    "gn:timezone":"Asia/Shanghai",
    "iso:country":"CN",
    "name:zho_x_preferred":[
        "\u5927\u5e99\u5934"
    ],
    "wof:name":"Damiaotou",
    "wof:placetype":"locality"
},
  "geometry": {"coordinates":[111.53752,26.07947],"type":"Point"}
}