{
  "type": "Feature",
  "properties": {
    "gn:admin1_code":"32.0",
    "gn:asciiname":"Tianliangshang",
    "gn:country_code":"CN",
    "gn:dem":772,
    "gn:feature_class":"P",
    "gn:feature_code":"PPL",
    "gn:name":"Tianliangshang",
    "gn:population":0,
    "gn:timezone":"Asia/Shanghai",
    "iso:country":"CN",
    "name:und_x_variant":[
        "\u7530\u6881\u4e0a"
    ],
    "wof:name":"Tianliangshang",
    "wof:placetype":"locality"
},
  "geometry": {"coordinates":[106.69296,32.39625],"type":"Point"}
}