{
  "type": "Feature",
  "properties": {
    "gn:admin1_code":"19.0",
    "gn:asciiname":"Qianjin",
    "gn:country_code":"CN",
    "gn:dem":93,
    "gn:feature_class":"P",
    "gn:feature_code":"PPL",
    "gn:name":"Qianjin",
    "gn:population":0,
    "gn:timezone":"Asia/Shanghai",
    "iso:country":"CN",
    "name:und_x_variant":[
        "\u524d\u8fdb"
    ],
    "name:zho_x_preferred":[
        "\u524d\u8fdb"
    ],
    "wof:name":"Qianjin",
    "wof:placetype":"locality"
},
  "geometry": {"coordinates":[123.16827000000001,42.51134],"type":"Point"}
}