{
  "type": "Feature",
  "properties": {
    "gn:admin1_code":"32.0",
    "gn:asciiname":"Wugenshu",
    "gn:country_code":"CN",
    "gn:dem":528,
    "gn:feature_class":"P",
    "gn:feature_code":"PPL",
    "gn:name":"Wugenshu",
    "gn:population":0,
    "gn:timezone":"Asia/Shanghai",
    "iso:country":"CN",
    "name:zho_x_preferred":[
        "\u4e94\u6839\u6811"
    ],
    "wof:name":"Wugenshu",
    "wof:placetype":"locality"
},
  "geometry": {"coordinates":[104.30971,31.22294],"type":"Point"}
}