{
  "type": "Feature",
  "properties": {
    "gn:admin1_code":"29",
    "gn:asciiname":"Feikai",
    "gn:country_code":"CN",
    "gn:dem":1299,
    "gn:feature_class":"P",
    "gn:feature_code":"PPL",
    "gn:name":"Feikai",
    "gn:population":0,
    "gn:timezone":"Asia/Shanghai",
    "iso:country":"CN",
    "name:zho_x_preferred":[
        "\u80a5\u5f00"
    ],
    "wof:name":"Feikai",
    "wof:placetype":"locality"
},
  "geometry": {"coordinates":[102.33799999999999,23.502],"type":"Point"}
}