{
  "type": "Feature",
  "properties": {
    "gn:admin1_code":"15.0",
    "gn:asciiname":"Guoguori",
    "gn:country_code":"CN",
    "gn:dem":3442,
    "gn:feature_class":"P",
    "gn:feature_code":"PPL",
    "gn:name":"Guoguori",
    "gn:population":0,
    "gn:timezone":"Asia/Shanghai",
    "iso:country":"CN",
    "name:zho_x_preferred":[
        "\u90ed\u679c\u65e5"
    ],
    "wof:name":"Guoguori",
    "wof:placetype":"locality"
},
  "geometry": {"coordinates":[102.303,34.3034],"type":"Point"}
}