{
  "type": "Feature",
  "properties": {
    "gn:admin1_code":"13",
    "gn:asciiname":"Pahataike Mailisi",
    "gn:country_code":"CN",
    "gn:dem":1289,
    "gn:feature_class":"P",
    "gn:feature_code":"PPL",
    "gn:name":"Pahataike Mailisi",
    "gn:population":0,
    "gn:timezone":"Asia/Shanghai",
    "iso:country":"CN",
    "name:und_x_variant":[
        "\u5e15\u54c8\u592a\u514b\u4e70\u91cc\u65af"
    ],
    "wof:name":"Pahataike Mailisi",
    "wof:placetype":"locality"
},
  "geometry": {"coordinates":[76.13549,39.55347],"type":"Point"}
}