{
  "type": "Feature",
  "properties": {
    "gn:admin1_code":"12.0",
    "gn:asciiname":"Shangxiongjia Yuan",
    "gn:country_code":"CN",
    "gn:dem":63,
    "gn:feature_class":"P",
    "gn:feature_code":"PPL",
    "gn:name":"Shangxiongjia Yuan",
    "gn:population":0,
    "gn:timezone":"Asia/Shanghai",
    "iso:country":"CN",
    "name:zho_x_preferred":[
        "\u4e0a\u718a\u5bb6\u9662"
    ],
    "wof:name":"Shangxiongjia Yuan",
    "wof:placetype":"locality"
},
  "geometry": {"coordinates":[112.30674999999999,30.93486],"type":"Point"}
}