{
  "type": "Feature",
  "properties": {
    "gn:admin1_code":"12.0",
    "gn:asciiname":"Shanggangou",
    "gn:country_code":"CN",
    "gn:dem":962,
    "gn:feature_class":"P",
    "gn:feature_code":"PPL",
    "gn:name":"Shanggangou",
    "gn:population":0,
    "gn:timezone":"Asia/Shanghai",
    "iso:country":"CN",
    "name:zho_x_preferred":[
        "\u4e0a\u5e72\u6c9f"
    ],
    "wof:name":"Shanggangou",
    "wof:placetype":"locality"
},
  "geometry": {"coordinates":[111.55764000000001,31.46815],"type":"Point"}
}