{
  "type": "Feature",
  "properties": {
    "gn:admin1_code":"7.0",
    "gn:asciiname":"Sankengkou",
    "gn:country_code":"CN",
    "gn:dem":413,
    "gn:feature_class":"P",
    "gn:feature_code":"PPL",
    "gn:name":"Sankengkou",
    "gn:population":0,
    "gn:timezone":"Asia/Shanghai",
    "iso:country":"CN",
    "name:und_x_variant":[
        "\u4e09\u5751\u53e3"
    ],
    "name:zho_x_preferred":[
        "\u4e09\u5751\u53e3"
    ],
    "wof:name":"Sankengkou",
    "wof:placetype":"locality"
},
  "geometry": {"coordinates":[116.50395,25.94797],"type":"Point"}
}