{
  "type": "Feature",
  "properties": {
    "gn:admin1_code":"8.0",
    "gn:asciiname":"Renyicun",
    "gn:country_code":"CN",
    "gn:dem":204,
    "gn:feature_class":"P",
    "gn:feature_code":"PPL",
    "gn:name":"Renyicun",
    "gn:population":0,
    "gn:timezone":"Asia/Shanghai",
    "iso:country":"CN",
    "name:zho_x_preferred":[
        "\u4ec1\u4e49\u6751"
    ],
    "wof:name":"Renyicun",
    "wof:placetype":"locality"
},
  "geometry": {"coordinates":[125.24044000000001,47.70706],"type":"Point"}
}