{
  "type": "Feature",
  "properties": {
    "gn:admin1_code":"09",
    "gn:asciiname":"Linying",
    "gn:cc2":"CN",
    "gn:country_code":"CN",
    "gn:dem":64,
    "gn:feature_class":"P",
    "gn:feature_code":"PPL",
    "gn:name":"Linying",
    "gn:population":0,
    "gn:timezone":"Asia/Shanghai",
    "iso:country":"CN",
    "name:und_x_variant":[
        "Lin-ying-hsien",
        "Linying"
    ],
    "wof:name":"Linying",
    "wof:placetype":"locality"
},
  "geometry": {"coordinates":[113.94722,33.81],"type":"Point"}
}