{
  "type": "Feature",
  "properties": {
    "gn:admin1_code":"12.0",
    "gn:asciiname":"Shangdaquanchong",
    "gn:country_code":"CN",
    "gn:dem":382,
    "gn:feature_class":"P",
    "gn:feature_code":"PPL",
    "gn:name":"Shangdaquanchong",
    "gn:population":0,
    "gn:timezone":"Asia/Shanghai",
    "iso:country":"CN",
    "name:zho_x_preferred":[
        "\u4e0a\u5927\u6cc9\u51b2"
    ],
    "wof:name":"Shangdaquanchong",
    "wof:placetype":"locality"
},
  "geometry": {"coordinates":[113.21625,32.42284],"type":"Point"}
}