{
  "type": "Feature",
  "properties": {
    "gn:admin1_code":"20.0",
    "gn:asciiname":"Hongqi Sandui",
    "gn:country_code":"CN",
    "gn:dem":331,
    "gn:feature_class":"P",
    "gn:feature_code":"PPLF",
    "gn:name":"Hongqi Sandui",
    "gn:population":0,
    "gn:timezone":"Asia/Shanghai",
    "iso:country":"CN",
    "name:zho_x_preferred":[
        "\u7ea2\u65d7\u4e09\u961f"
    ],
    "wof:name":"Hongqi Sandui",
    "wof:placetype":"locality"
},
  "geometry": {"coordinates":[122.6632,48.07494000000001],"type":"Point"}
}