{
  "type": "Feature",
  "properties": {
    "gn:admin1_code":"32.0",
    "gn:asciiname":"Wenzige",
    "gn:country_code":"CN",
    "gn:dem":2427,
    "gn:feature_class":"P",
    "gn:feature_code":"PPL",
    "gn:name":"Wenzige",
    "gn:population":0,
    "gn:timezone":"Asia/Shanghai",
    "iso:country":"CN",
    "name:zho_x_preferred":[
        "\u6587\u5b50\u5404"
    ],
    "wof:name":"Wenzige",
    "wof:placetype":"locality"
},
  "geometry": {"coordinates":[102.807,28.0231],"type":"Point"}
}