{
  "type": "Feature",
  "properties": {
    "gn:admin1_code":"32.0",
    "gn:asciiname":"Lanaobuke",
    "gn:country_code":"CN",
    "gn:dem":2693,
    "gn:feature_class":"P",
    "gn:feature_code":"PPL",
    "gn:name":"Lanaobuke",
    "gn:population":0,
    "gn:timezone":"Asia/Shanghai",
    "iso:country":"CN",
    "name:zho_x_preferred":[
        "\u62c9\u8111\u4e0d\u53ef"
    ],
    "wof:name":"Lanaobuke",
    "wof:placetype":"locality"
},
  "geometry": {"coordinates":[102.69909,27.82185],"type":"Point"}
}