{
  "type": "Feature",
  "properties": {
    "gn:admin1_code":"16.0",
    "gn:asciiname":"Huabiao",
    "gn:country_code":"CN",
    "gn:dem":792,
    "gn:feature_class":"P",
    "gn:feature_code":"PPL",
    "gn:name":"Huabiao",
    "gn:population":0,
    "gn:timezone":"Asia/Shanghai",
    "iso:country":"CN",
    "name:nor_x_preferred":[
        "Huabiao"
    ],
    "name:pol_x_preferred":[
        "Huabiao"
    ],
    "name:por_x_preferred":[
        "Huabiao"
    ],
    "name:zho_x_preferred":[
        "\u534e\u8868"
    ],
    "wof:name":"Huabiao",
    "wof:placetype":"locality"
},
  "geometry": {"coordinates":[106.47499999999999,23.2583],"type":"Point"}
}