{
  "type": "Feature",
  "properties": {
    "gn:admin1_code":"24.0",
    "gn:asciiname":"Naquan Linchang",
    "gn:country_code":"CN",
    "gn:dem":1317,
    "gn:feature_class":"P",
    "gn:feature_code":"PPLF",
    "gn:name":"Naquan Linchang",
    "gn:population":0,
    "gn:timezone":"Asia/Shanghai",
    "iso:country":"CN",
    "name:zho_x_preferred":[
        "\u5357\u5708\u6797\u573a"
    ],
    "wof:name":"Naquan Linchang",
    "wof:placetype":"locality"
},
  "geometry": {"coordinates":[112.05538,36.06166],"type":"Point"}
}