{
  "type": "Feature",
  "properties": {
    "gn:admin1_code":"12.0",
    "gn:asciiname":"Laowuchang",
    "gn:country_code":"CN",
    "gn:dem":1066,
    "gn:feature_class":"P",
    "gn:feature_code":"PPL",
    "gn:name":"Laowuchang",
    "gn:population":0,
    "gn:timezone":"Asia/Shanghai",
    "iso:country":"CN",
    "name:zho_x_preferred":[
        "Laowuchang"
    ],
    "name:zho_x_variant":[
        "\u8001\u5c4b\u573a"
    ],
    "wof:name":"Laowuchang",
    "wof:placetype":"locality"
},
  "geometry": {"coordinates":[110.62112,30.08257],"type":"Point"}
}