{
  "type": "Feature",
  "properties": {
    "gn:admin1_code":"19",
    "gn:asciiname":"Pinggang",
    "gn:cc2":"CN",
    "gn:country_code":"CN",
    "gn:dem":270,
    "gn:feature_class":"P",
    "gn:feature_code":"PPL",
    "gn:name":"Pinggang",
    "gn:population":0,
    "gn:timezone":"Asia/Shanghai",
    "iso:country":"CN",
    "name:und_x_variant":[
        "P\u2019ing-kang-chen",
        "P\u2019ing-kang",
        "Pinggang"
    ],
    "wof:name":"Pinggang",
    "wof:placetype":"locality"
},
  "geometry": {"coordinates":[124.81667,42.95],"type":"Point"}
}