{
  "type": "Feature",
  "properties": {
    "gn:admin1_code":"15.0",
    "gn:asciiname":"Chenjiadawan",
    "gn:country_code":"CN",
    "gn:dem":1913,
    "gn:feature_class":"P",
    "gn:feature_code":"PPL",
    "gn:name":"Chenjiadawan",
    "gn:population":0,
    "gn:timezone":"Asia/Shanghai",
    "iso:country":"CN",
    "name:und_x_variant":[
        "\u9648\u5bb6\u5927\u6e7e"
    ],
    "wof:name":"Chenjiadawan",
    "wof:placetype":"locality"
},
  "geometry": {"coordinates":[105.50415,35.29292],"type":"Point"}
}