{
  "type": "Feature",
  "properties": {
    "gn:admin1_code":"30",
    "gn:asciiname":"Fanshuiche",
    "gn:country_code":"CN",
    "gn:dem":10,
    "gn:feature_class":"P",
    "gn:feature_code":"PPL",
    "gn:name":"Fanshuiche",
    "gn:population":0,
    "gn:timezone":"Asia/Urumqi",
    "iso:country":"CN",
    "name:zho_x_preferred":[
        "\u756a\u6c34\u8f66"
    ],
    "wof:name":"Fanshuiche",
    "wof:placetype":"locality"
},
  "geometry": {"coordinates":[110.1206,21.54246],"type":"Point"}
}