{
  "type": "Feature",
  "properties": {
    "gn:admin1_code":"7",
    "gn:asciiname":"Tongkeng",
    "gn:country_code":"CN",
    "gn:dem":345,
    "gn:feature_class":"P",
    "gn:feature_code":"PPL",
    "gn:name":"Tongkeng",
    "gn:population":0,
    "gn:timezone":"Asia/Shanghai",
    "iso:country":"CN",
    "name:und_x_variant":[
        "\u7ae5\u5751"
    ],
    "wof:name":"Tongkeng",
    "wof:placetype":"locality"
},
  "geometry": {"coordinates":[118.58778,27.57722],"type":"Point"}
}