{
  "type": "Feature",
  "properties": {
    "gn:admin1_code":"5.0",
    "gn:asciiname":"Jinbucun",
    "gn:country_code":"CN",
    "gn:dem":275,
    "gn:feature_class":"P",
    "gn:feature_code":"PPL",
    "gn:name":"Jinbucun",
    "gn:population":0,
    "gn:timezone":"Asia/Shanghai",
    "iso:country":"CN",
    "name:zho_x_preferred":[
        "\u8fdb\u6b65\u6751"
    ],
    "wof:name":"Jinbucun",
    "wof:placetype":"locality"
},
  "geometry": {"coordinates":[121.93355,45.77319],"type":"Point"}
}