{
  "type": "Feature",
  "properties": {
    "gn:admin1_code":"33.0",
    "gn:asciiname":"Taiyangwan",
    "gn:country_code":"CN",
    "gn:dem":415,
    "gn:feature_class":"P",
    "gn:feature_code":"PPL",
    "gn:name":"Taiyangwan",
    "gn:population":0,
    "gn:timezone":"Asia/Shanghai",
    "iso:country":"CN",
    "name:zho_x_preferred":[
        "\u592a\u9633\u6e7e"
    ],
    "wof:name":"Taiyangwan",
    "wof:placetype":"locality"
},
  "geometry": {"coordinates":[107.64179,30.0301],"type":"Point"}
}