{
  "type": "Feature",
  "properties": {
    "gn:admin1_code":"8.0",
    "gn:asciiname":"Sunjia Weizi",
    "gn:country_code":"CN",
    "gn:dem":132,
    "gn:feature_class":"P",
    "gn:feature_code":"PPL",
    "gn:name":"Sunjia Weizi",
    "gn:population":0,
    "gn:timezone":"Asia/Shanghai",
    "iso:country":"CN",
    "name:zho_x_preferred":[
        "\u5b59\u5bb6\u56f4\u5b50"
    ],
    "wof:name":"Sunjia Weizi",
    "wof:placetype":"locality"
},
  "geometry": {"coordinates":[124.41726,45.7656],"type":"Point"}
}