{
  "type": "Feature",
  "properties": {
    "gn:admin1_code":"7.0",
    "gn:asciiname":"Shapingyuan",
    "gn:country_code":"CN",
    "gn:dem":311,
    "gn:feature_class":"P",
    "gn:feature_code":"PPL",
    "gn:name":"Shapingyuan",
    "gn:population":0,
    "gn:timezone":"Asia/Shanghai",
    "iso:country":"CN",
    "name:zho_x_preferred":[
        "\u6c99\u576a\u6e90"
    ],
    "wof:name":"Shapingyuan",
    "wof:placetype":"locality"
},
  "geometry": {"coordinates":[117.13632,27.49224],"type":"Point"}
}