{
  "type": "Feature",
  "properties": {
    "gn:admin1_code":"2.0",
    "gn:asciiname":"Shigaikou",
    "gn:country_code":"CN",
    "gn:dem":62,
    "gn:feature_class":"P",
    "gn:feature_code":"PPL",
    "gn:name":"Shigaikou",
    "gn:population":0,
    "gn:timezone":"Asia/Shanghai",
    "iso:country":"CN",
    "name:zho_x_preferred":[
        "\u77f3\u76d6\u53e3"
    ],
    "wof:name":"Shigaikou",
    "wof:placetype":"locality"
},
  "geometry": {"coordinates":[120.17362,28.26191],"type":"Point"}
}