{
  "type": "Feature",
  "properties": {
    "gn:admin1_code":"4.0",
    "gn:asciiname":"Wannianqiao",
    "gn:country_code":"CN",
    "gn:dem":7,
    "gn:feature_class":"P",
    "gn:feature_code":"PPL",
    "gn:name":"Wannianqiao",
    "gn:population":0,
    "gn:timezone":"Asia/Shanghai",
    "iso:country":"CN",
    "name:und_x_variant":[
        "\u4e07\u5e74\u6865"
    ],
    "wof:name":"Wannianqiao",
    "wof:placetype":"locality"
},
  "geometry": {"coordinates":[121.02005,31.91266],"type":"Point"}
}