{
  "type": "Feature",
  "properties": {
    "gn:admin1_code":"18.0",
    "gn:asciiname":"Mengzhai",
    "gn:country_code":"CN",
    "gn:dem":1049,
    "gn:feature_class":"P",
    "gn:feature_code":"PPL",
    "gn:name":"Mengzhai",
    "gn:population":0,
    "gn:timezone":"Asia/Shanghai",
    "iso:country":"CN",
    "wof:name":"Mengzhai",
    "wof:placetype":"locality"
},
  "geometry": {"coordinates":[105.26667,25.88333],"type":"Point"}
}