{
  "type": "Feature",
  "properties": {
    "gn:admin1_code":"15.0",
    "gn:asciiname":"Jiufangli",
    "gn:country_code":"CN",
    "gn:dem":1566,
    "gn:feature_class":"P",
    "gn:feature_code":"PPL",
    "gn:name":"Jiufangli",
    "gn:population":0,
    "gn:timezone":"Asia/Shanghai",
    "iso:country":"CN",
    "name:und_x_variant":[
        "\u4e5d\u623f\u91cc"
    ],
    "wof:name":"Jiufangli",
    "wof:placetype":"locality"
},
  "geometry": {"coordinates":[105.33636,33.15084],"type":"Point"}
}