{
  "type": "Feature",
  "properties": {
    "gn:admin1_code":"32.0",
    "gn:asciiname":"Yudaiqiao",
    "gn:country_code":"CN",
    "gn:dem":273,
    "gn:feature_class":"P",
    "gn:feature_code":"PPL",
    "gn:name":"Yudaiqiao",
    "gn:population":0,
    "gn:timezone":"Asia/Shanghai",
    "iso:country":"CN",
    "name:zho_x_preferred":[
        "\u7389\u5e26\u6865"
    ],
    "wof:name":"Yudaiqiao",
    "wof:placetype":"locality"
},
  "geometry": {"coordinates":[105.57019,30.02515],"type":"Point"}
}