{
  "type": "Feature",
  "properties": {
    "gn:admin1_code":"14.0",
    "gn:asciiname":"Mengdacun",
    "gn:country_code":"CN",
    "gn:dem":3980,
    "gn:feature_class":"P",
    "gn:feature_code":"PPL",
    "gn:name":"Mengdacun",
    "gn:population":0,
    "gn:timezone":"Asia/Urumqi",
    "iso:country":"CN",
    "name:zho_x_preferred":[
        "\u5b5f\u8fbe\u6751"
    ],
    "wof:name":"Mengdacun",
    "wof:placetype":"locality"
},
  "geometry": {"coordinates":[96.40214,31.46597],"type":"Point"}
}