{
  "type": "Feature",
  "properties": {
    "gn:admin1_code":"11.0",
    "gn:asciiname":"Yujiazui",
    "gn:country_code":"CN",
    "gn:dem":504,
    "gn:feature_class":"P",
    "gn:feature_code":"PPLA4",
    "gn:name":"Yujiazui",
    "gn:population":0,
    "gn:timezone":"Asia/Shanghai",
    "iso:country":"CN",
    "name:und_x_variant":[
        "Suoxiyu",
        "Suoxiyu Tujiazuxiang",
        "Yujiazui"
    ],
    "name:zho_x_preferred":[
        "\u55bb\u5bb6\u89dc"
    ],
    "name:zho_x_variant":[
        "\u7d22\u6eaa\u5cea",
        "\u7d22\u6eaa\u5cea\u571f\u5bb6\u65cf\u4e61"
    ],
    "wof:name":"Yujiazui",
    "wof:placetype":"locality"
},
  "geometry": {"coordinates":[110.56269,29.35337],"type":"Point"}
}