{
  "type": "Feature",
  "properties": {
    "gn:admin1_code":"18",
    "gn:asciiname":"Shuiyan Pingzi",
    "gn:country_code":"CN",
    "gn:dem":2007,
    "gn:feature_class":"P",
    "gn:feature_code":"PPL",
    "gn:name":"Shuiyan Pingzi",
    "gn:population":0,
    "gn:timezone":"Asia/Shanghai",
    "iso:country":"CN",
    "name:zho_x_preferred":[
        "\u6c34\u6df9\u576a\u5b50"
    ],
    "wof:name":"Shuiyan Pingzi",
    "wof:placetype":"locality"
},
  "geometry": {"coordinates":[103.73999999999999,27.0195],"type":"Point"}
}