{
  "type": "Feature",
  "properties": {
    "gn:admin1_code":"30",
    "gn:asciiname":"Danshuikeng",
    "gn:country_code":"CN",
    "gn:dem":31,
    "gn:feature_class":"P",
    "gn:feature_code":"PPL",
    "gn:name":"Danshuikeng",
    "gn:population":0,
    "gn:timezone":"Asia/Shanghai",
    "iso:country":"CN",
    "name:zho_x_preferred":[
        "\u62c5\u6c34\u5751"
    ],
    "wof:name":"Danshuikeng",
    "wof:placetype":"locality"
},
  "geometry": {"coordinates":[111.62347,22.16297],"type":"Point"}
}