{
  "type": "Feature",
  "properties": {
    "gn:admin1_code":"9.0",
    "gn:asciiname":"Huoshiya",
    "gn:country_code":"CN",
    "gn:dem":1038,
    "gn:feature_class":"P",
    "gn:feature_code":"PPL",
    "gn:name":"Huoshiya",
    "gn:population":0,
    "gn:timezone":"Asia/Shanghai",
    "iso:country":"CN",
    "name:zho_x_preferred":[
        "\u706b\u77f3\u5d16"
    ],
    "wof:name":"Huoshiya",
    "wof:placetype":"locality"
},
  "geometry": {"coordinates":[110.53863,34.45468],"type":"Point"}
}