{
  "type": "Feature",
  "properties": {
    "gn:admin1_code":"14.0",
    "gn:asciiname":"Jichema Dongtuocun",
    "gn:country_code":"CN",
    "gn:dem":4740,
    "gn:feature_class":"P",
    "gn:feature_code":"PPL",
    "gn:name":"Jichema Dongtuocun",
    "gn:population":0,
    "gn:timezone":"Asia/Urumqi",
    "iso:country":"CN",
    "name:zho_x_preferred":[
        "\u5409\u8f66\u739b\u4e1c\u6258\u6751"
    ],
    "wof:name":"Jichema Dongtuocun",
    "wof:placetype":"locality"
},
  "geometry": {"coordinates":[91.93422,31.66388],"type":"Point"}
}