{
  "type": "Feature",
  "properties": {
    "gn:admin1_code":"5.0",
    "gn:asciiname":"Xilihecun",
    "gn:country_code":"CN",
    "gn:dem":238,
    "gn:feature_class":"P",
    "gn:feature_code":"PPL",
    "gn:name":"Xilihecun",
    "gn:population":0,
    "gn:timezone":"Asia/Shanghai",
    "iso:country":"CN",
    "name:zho_x_preferred":[
        "\u897f\u9ece\u6cb3\u6751"
    ],
    "wof:name":"Xilihecun",
    "wof:placetype":"locality"
},
  "geometry": {"coordinates":[125.99642,43.39086],"type":"Point"}
}