{
  "type": "Feature",
  "properties": {
    "gn:admin1_code":"11.0",
    "gn:asciiname":"Hutianping",
    "gn:country_code":"CN",
    "gn:dem":177,
    "gn:feature_class":"P",
    "gn:feature_code":"PPL",
    "gn:name":"Hutianping",
    "gn:population":0,
    "gn:timezone":"Asia/Shanghai",
    "iso:country":"CN",
    "name:zho_x_preferred":[
        "\u6e56\u7530\u576a"
    ],
    "wof:name":"Hutianping",
    "wof:placetype":"locality"
},
  "geometry": {"coordinates":[110.15770000000001,28.40639],"type":"Point"}
}