{
  "type": "Feature",
  "properties": {
    "gn:admin1_code":"29.0",
    "gn:asciiname":"Xinmin Zhongcun",
    "gn:country_code":"CN",
    "gn:dem":2250,
    "gn:feature_class":"P",
    "gn:feature_code":"PPL",
    "gn:name":"Xinmin Zhongcun",
    "gn:population":0,
    "gn:timezone":"Asia/Shanghai",
    "iso:country":"CN",
    "name:zho_x_preferred":[
        "\u65b0\u6c11\u4e2d\u6751"
    ],
    "wof:name":"Xinmin Zhongcun",
    "wof:placetype":"locality"
},
  "geometry": {"coordinates":[100.23999999999999,26.721],"type":"Point"}
}