{
  "type": "Feature",
  "properties": {
    "gn:admin1_code":"13.0",
    "gn:asciiname":"Adatuwai",
    "gn:country_code":"CN",
    "gn:dem":3966,
    "gn:feature_class":"P",
    "gn:feature_code":"PPL",
    "gn:name":"Adatuwai",
    "gn:population":0,
    "gn:timezone":"Asia/Urumqi",
    "iso:country":"CN",
    "name:zho_x_preferred":[
        "\u963f\u8fbe\u5410\u5916"
    ],
    "wof:name":"Adatuwai",
    "wof:placetype":"locality"
},
  "geometry": {"coordinates":[86.44761,37.80643],"type":"Point"}
}