{
  "type": "Feature",
  "properties": {
    "gn:admin1_code":"18.0",
    "gn:asciiname":"Biya",
    "gn:country_code":"CN",
    "gn:dem":467,
    "gn:feature_class":"P",
    "gn:feature_code":"PPL",
    "gn:name":"Biya",
    "gn:population":0,
    "gn:timezone":"Asia/Shanghai",
    "iso:country":"CN",
    "name:ceb_x_preferred":[
        "Biya"
    ],
    "name:deu_x_preferred":[
        "Biya"
    ],
    "name:fra_x_preferred":[
        "Biya"
    ],
    "name:swe_x_preferred":[
        "Biya"
    ],
    "name:uzb_x_preferred":[
        "Biya"
    ],
    "wof:name":"Biya",
    "wof:placetype":"locality"
},
  "geometry": {"coordinates":[109.33638999999999,27.13056],"type":"Point"}
}