{
  "type": "Feature",
  "properties": {
    "gn:admin1_code":"18",
    "gn:asciiname":"Banlai",
    "gn:country_code":"CN",
    "gn:dem":1001,
    "gn:feature_class":"P",
    "gn:feature_code":"PPL",
    "gn:name":"Banlai",
    "gn:population":0,
    "gn:timezone":"Asia/Shanghai",
    "iso:country":"CN",
    "name:zho_x_preferred":[
        "\u677f\u8d56"
    ],
    "wof:name":"Banlai",
    "wof:placetype":"locality"
},
  "geometry": {"coordinates":[105.584,25.3729],"type":"Point"}
}