{
  "type": "Feature",
  "properties": {
    "gn:admin1_code":"19.0",
    "gn:asciiname":"Shiqiaozi",
    "gn:country_code":"CN",
    "gn:dem":86,
    "gn:feature_class":"P",
    "gn:feature_code":"PPL",
    "gn:name":"Shiqiaozi",
    "gn:population":0,
    "gn:timezone":"Asia/Shanghai",
    "iso:country":"CN",
    "name:und_x_variant":[
        "\u77f3\u6865\u5b50"
    ],
    "name:zho_x_preferred":[
        "\u77f3\u6865\u5b50"
    ],
    "wof:name":"Shiqiaozi",
    "wof:placetype":"locality"
},
  "geometry": {"coordinates":[124.25062,40.46947],"type":"Point"}
}