{
  "type": "Feature",
  "properties": {
    "gn:admin1_code":"19.0",
    "gn:asciiname":"Shangguancun",
    "gn:country_code":"CN",
    "gn:dem":66,
    "gn:feature_class":"P",
    "gn:feature_code":"PPL",
    "gn:name":"Shangguancun",
    "gn:population":0,
    "gn:timezone":"Asia/Shanghai",
    "iso:country":"CN",
    "name:zho_x_preferred":[
        "\u4e0a\u89c2\u6751"
    ],
    "wof:name":"Shangguancun",
    "wof:placetype":"locality"
},
  "geometry": {"coordinates":[121.651,41.4647],"type":"Point"}
}