{
  "type": "Feature",
  "properties": {
    "gn:admin1_code":"8.0",
    "gn:asciiname":"Yihantong",
    "gn:country_code":"CN",
    "gn:dem":103,
    "gn:feature_class":"P",
    "gn:feature_code":"PPLA4",
    "gn:name":"Yihantong",
    "gn:population":0,
    "gn:timezone":"Asia/Shanghai",
    "iso:country":"CN",
    "name:und_x_variant":[
        "Yihantong Xiang"
    ],
    "name:zho_x_preferred":[
        "\u4f0a\u6c49\u901a"
    ],
    "name:zho_x_variant":[
        "\u4f0a\u6c49\u901a\u4e61"
    ],
    "wof:name":"Yihantong",
    "wof:placetype":"locality"
},
  "geometry": {"coordinates":[128.89608999999999,45.87628],"type":"Point"}
}