{
  "type": "Feature",
  "properties": {
    "gn:admin1_code":"33",
    "gn:asciiname":"Laisu",
    "gn:country_code":"CN",
    "gn:dem":332,
    "gn:feature_class":"P",
    "gn:feature_code":"PPLA4",
    "gn:name":"Laisu",
    "gn:population":0,
    "gn:timezone":"Asia/Shanghai",
    "iso:country":"CN",
    "name:und_x_variant":[
        "Laisuchang",
        "Laisu Zhen"
    ],
    "name:zho_x_preferred":[
        "\u6765\u82cf"
    ],
    "name:zho_x_variant":[
        "\u6765\u82cf\u9547"
    ],
    "wof:name":"Laisu",
    "wof:placetype":"locality"
},
  "geometry": {"coordinates":[105.77802,29.26597000000001],"type":"Point"}
}