{
  "type": "Feature",
  "properties": {
    "gn:admin1_code":"24",
    "gn:asciiname":"Fanyao",
    "gn:country_code":"CN",
    "gn:dem":1568,
    "gn:feature_class":"P",
    "gn:feature_code":"PPL",
    "gn:name":"Fanyao",
    "gn:population":0,
    "gn:timezone":"Asia/Shanghai",
    "iso:country":"CN",
    "name:zho_x_preferred":[
        "\u8303\u7a91"
    ],
    "wof:name":"Fanyao",
    "wof:placetype":"locality"
},
  "geometry": {"coordinates":[113.58414999999999,40.30748],"type":"Point"}
}