{
  "type": "Feature",
  "properties": {
    "gn:admin1_code":"12.0",
    "gn:asciiname":"Rongjiatai",
    "gn:country_code":"CN",
    "gn:dem":27,
    "gn:feature_class":"P",
    "gn:feature_code":"PPL",
    "gn:name":"Rongjiatai",
    "gn:population":0,
    "gn:timezone":"Asia/Shanghai",
    "iso:country":"CN",
    "name:zho_x_preferred":[
        "\u8363\u5bb6\u53f0"
    ],
    "wof:name":"Rongjiatai",
    "wof:placetype":"locality"
},
  "geometry": {"coordinates":[113.66337,30.50423],"type":"Point"}
}