{
  "type": "Feature",
  "properties": {
    "gn:admin1_code":"1.0",
    "gn:asciiname":"Lilaozhuangcun",
    "gn:country_code":"CN",
    "gn:dem":30,
    "gn:feature_class":"P",
    "gn:feature_code":"PPL",
    "gn:name":"Lilaozhuangcun",
    "gn:population":0,
    "gn:timezone":"Asia/Shanghai",
    "iso:country":"CN",
    "name:zho_x_preferred":[
        "\u674e\u8001\u5e84\u6751"
    ],
    "wof:name":"Lilaozhuangcun",
    "wof:placetype":"locality"
},
  "geometry": {"coordinates":[115.75848000000001,32.95068],"type":"Point"}
}