{
  "type": "Feature",
  "properties": {
    "gn:admin1_code":"4.0",
    "gn:asciiname":"Dengzhuang",
    "gn:country_code":"CN",
    "gn:dem":2,
    "gn:feature_class":"P",
    "gn:feature_code":"PPL",
    "gn:name":"Dengzhuang",
    "gn:population":0,
    "gn:timezone":"Asia/Shanghai",
    "iso:country":"CN",
    "name:zho_x_preferred":[
        "Dengzhuang"
    ],
    "name:zho_x_variant":[
        "\u9093\u5e84"
    ],
    "wof:name":"Dengzhuang",
    "wof:placetype":"locality"
},
  "geometry": {"coordinates":[119.11653,34.7485],"type":"Point"}
}