{
  "type": "Feature",
  "properties": {
    "gn:admin1_code":"25.0",
    "gn:asciiname":"Daduogoucun",
    "gn:country_code":"CN",
    "gn:dem":105,
    "gn:feature_class":"P",
    "gn:feature_code":"PPL",
    "gn:name":"Daduogoucun",
    "gn:population":0,
    "gn:timezone":"Asia/Shanghai",
    "iso:country":"CN",
    "name:zho_x_preferred":[
        "\u5927\u593a\u6c9f\u6751"
    ],
    "wof:name":"Daduogoucun",
    "wof:placetype":"locality"
},
  "geometry": {"coordinates":[120.89660000000001,37.53468],"type":"Point"}
}