{
  "type": "Feature",
  "properties": {
    "gn:admin1_code":"15.0",
    "gn:asciiname":"Shimengou",
    "gn:country_code":"CN",
    "gn:dem":961,
    "gn:feature_class":"P",
    "gn:feature_code":"PPL",
    "gn:name":"Shimengou",
    "gn:population":0,
    "gn:timezone":"Asia/Shanghai",
    "iso:country":"CN",
    "name:und_x_variant":[
        "\u77f3\u95e8\u6c9f"
    ],
    "wof:name":"Shimengou",
    "wof:placetype":"locality"
},
  "geometry": {"coordinates":[105.91476000000002,33.6368],"type":"Point"}
}