{
  "type": "Feature",
  "properties": {
    "gn:admin1_code":"26",
    "gn:asciiname":"Houlijia",
    "gn:country_code":"CN",
    "gn:dem":611,
    "gn:feature_class":"P",
    "gn:feature_code":"PPL",
    "gn:name":"Houlijia",
    "gn:population":0,
    "gn:timezone":"Asia/Shanghai",
    "iso:country":"CN",
    "name:zho_x_preferred":[
        "\u540e\u674e\u5bb6"
    ],
    "wof:name":"Houlijia",
    "wof:placetype":"locality"
},
  "geometry": {"coordinates":[109.36926,34.99728],"type":"Point"}
}