{
  "type": "Feature",
  "properties": {
    "gn:admin1_code":"13",
    "gn:asciiname":"Shaladun",
    "gn:country_code":"CN",
    "gn:dem":-97,
    "gn:feature_class":"P",
    "gn:feature_code":"PPL",
    "gn:name":"Shaladun",
    "gn:population":0,
    "gn:timezone":"Asia/Urumqi",
    "iso:country":"CN",
    "name:und_x_variant":[
        "\u5565\u62c9\u58a9"
    ],
    "wof:name":"Shaladun",
    "wof:placetype":"locality"
},
  "geometry": {"coordinates":[89.67333000000001,42.65242],"type":"Point"}
}