{
  "type": "Feature",
  "properties": {
    "gn:admin1_code":"16.0",
    "gn:asciiname":"Nonghong",
    "gn:country_code":"CN",
    "gn:dem":256,
    "gn:feature_class":"P",
    "gn:feature_code":"PPL",
    "gn:name":"Nonghong",
    "gn:population":0,
    "gn:timezone":"Asia/Shanghai",
    "iso:country":"CN",
    "name:zho_x_preferred":[
        "\u5f04\u6d2a"
    ],
    "wof:name":"Nonghong",
    "wof:placetype":"locality"
},
  "geometry": {"coordinates":[108.07599999999999,23.9355],"type":"Point"}
}