{
  "type": "Feature",
  "properties": {
    "gn:admin1_code":"32.0",
    "gn:asciiname":"Jiagen",
    "gn:country_code":"CN",
    "gn:dem":3041,
    "gn:feature_class":"P",
    "gn:feature_code":"PPL",
    "gn:name":"Jiagen",
    "gn:population":0,
    "gn:timezone":"Asia/Shanghai",
    "iso:country":"CN",
    "name:zho_x_preferred":[
        "\u7532\u6839"
    ],
    "wof:name":"Jiagen",
    "wof:placetype":"locality"
},
  "geometry": {"coordinates":[102.047,32.2405],"type":"Point"}
}