{
  "type": "Feature",
  "properties": {
    "gn:admin1_code":"1.0",
    "gn:asciiname":"Meixicun",
    "gn:country_code":"CN",
    "gn:dem":350,
    "gn:feature_class":"P",
    "gn:feature_code":"PPL",
    "gn:name":"Meixicun",
    "gn:population":0,
    "gn:timezone":"Asia/Shanghai",
    "iso:country":"CN",
    "name:zho_x_preferred":[
        "\u6885\u6eaa\u6751"
    ],
    "wof:name":"Meixicun",
    "wof:placetype":"locality"
},
  "geometry": {"coordinates":[117.68213,29.64728],"type":"Point"}
}