{
  "type": "Feature",
  "properties": {
    "gn:admin1_code":"5.0",
    "gn:asciiname":"Yaolingzi",
    "gn:country_code":"CN",
    "gn:dem":372,
    "gn:feature_class":"P",
    "gn:feature_code":"PPL",
    "gn:name":"Yaolingzi",
    "gn:population":0,
    "gn:timezone":"Asia/Shanghai",
    "iso:country":"CN",
    "name:zho_x_preferred":[
        "\u8170\u5cad\u5b50"
    ],
    "wof:name":"Yaolingzi",
    "wof:placetype":"locality"
},
  "geometry": {"coordinates":[125.51656,42.76878],"type":"Point"}
}