{
  "type": "Feature",
  "properties": {
    "gn:admin1_code":"12.0",
    "gn:asciiname":"Daoqiao",
    "gn:country_code":"CN",
    "gn:dem":137,
    "gn:feature_class":"P",
    "gn:feature_code":"PPL",
    "gn:name":"Daoqiao",
    "gn:population":0,
    "gn:timezone":"Asia/Shanghai",
    "iso:country":"CN",
    "name:zho_x_preferred":[
        "\u5012\u6865"
    ],
    "wof:name":"Daoqiao",
    "wof:placetype":"locality"
},
  "geometry": {"coordinates":[111.48363000000001,32.29881],"type":"Point"}
}