{
  "type": "Feature",
  "properties": {
    "gn:admin1_code":"3",
    "gn:asciiname":"Qiannikeng",
    "gn:country_code":"CN",
    "gn:dem":221,
    "gn:feature_class":"P",
    "gn:feature_code":"PPL",
    "gn:name":"Qiannikeng",
    "gn:population":0,
    "gn:timezone":"Asia/Shanghai",
    "iso:country":"CN",
    "name:zho_x_preferred":[
        "\u6d45\u6ce5\u5751"
    ],
    "wof:name":"Qiannikeng",
    "wof:placetype":"locality"
},
  "geometry": {"coordinates":[114.398,26.6632],"type":"Point"}
}