{
  "type": "Feature",
  "properties": {
    "gn:admin1_code":"19.0",
    "gn:asciiname":"Hejia Wobu",
    "gn:country_code":"CN",
    "gn:dem":43,
    "gn:feature_class":"P",
    "gn:feature_code":"PPL",
    "gn:name":"Hejia Wobu",
    "gn:population":0,
    "gn:timezone":"Asia/Shanghai",
    "iso:country":"CN",
    "name:und_x_variant":[
        "Hejiawobao",
        "Hejia Wobu"
    ],
    "name:zho_x_preferred":[
        "\u4f55\u5bb6\u7a9d\u5821"
    ],
    "wof:name":"Hejia Wobu",
    "wof:placetype":"locality"
},
  "geometry": {"coordinates":[123.27622,42.10447],"type":"Point"}
}