{
  "type": "Feature",
  "properties": {
    "gn:admin1_code":"24",
    "gn:asciiname":"Beijiazao",
    "gn:country_code":"CN",
    "gn:dem":1047,
    "gn:feature_class":"P",
    "gn:feature_code":"PPLA4",
    "gn:name":"Beijiazao",
    "gn:population":0,
    "gn:timezone":"Asia/Shanghai",
    "iso:country":"CN",
    "name:und_x_variant":[
        "Hsin-chia-tsao",
        "Pei-chia-tsao",
        "Beijiazao"
    ],
    "wof:name":"Beijiazao",
    "wof:placetype":"locality"
},
  "geometry": {"coordinates":[113.46917000000001,40.05333],"type":"Point"}
}