{
  "type": "Feature",
  "properties": {
    "gn:admin1_code":"24.0",
    "gn:asciiname":"Pangjialing",
    "gn:country_code":"CN",
    "gn:dem":1330,
    "gn:feature_class":"P",
    "gn:feature_code":"PPL",
    "gn:name":"Pangjialing",
    "gn:population":0,
    "gn:timezone":"Asia/Shanghai",
    "iso:country":"CN",
    "name:zho_x_preferred":[
        "\u5e9e\u5bb6\u5cad"
    ],
    "wof:name":"Pangjialing",
    "wof:placetype":"locality"
},
  "geometry": {"coordinates":[111.33365999999999,36.65937],"type":"Point"}
}