{
  "type": "Feature",
  "properties": {
    "gn:admin1_code":"29.0",
    "gn:asciiname":"Huangjia Baobao",
    "gn:country_code":"CN",
    "gn:dem":1743,
    "gn:feature_class":"P",
    "gn:feature_code":"PPL",
    "gn:name":"Huangjia Baobao",
    "gn:population":0,
    "gn:timezone":"Asia/Shanghai",
    "iso:country":"CN",
    "name:zho_x_preferred":[
        "\u9ec4\u5bb6\u5305\u5305"
    ],
    "wof:name":"Huangjia Baobao",
    "wof:placetype":"locality"
},
  "geometry": {"coordinates":[104.386,26.1047],"type":"Point"}
}