{
  "type": "Feature",
  "properties": {
    "gn:admin1_code":"11",
    "gn:asciiname":"Dawutang",
    "gn:country_code":"CN",
    "gn:dem":205,
    "gn:feature_class":"P",
    "gn:feature_code":"PPL",
    "gn:name":"Dawutang",
    "gn:population":0,
    "gn:timezone":"Asia/Shanghai",
    "iso:country":"CN",
    "name:zho_x_preferred":[
        "\u8fbe\u4e94\u5802"
    ],
    "wof:name":"Dawutang",
    "wof:placetype":"locality"
},
  "geometry": {"coordinates":[111.88424999999999,27.11768],"type":"Point"}
}