{
  "type": "Feature",
  "properties": {
    "gn:admin1_code":"26",
    "gn:asciiname":"Yushi",
    "gn:country_code":"CN",
    "gn:dem":506,
    "gn:feature_class":"P",
    "gn:feature_code":"PPL",
    "gn:name":"Yushi",
    "gn:population":0,
    "gn:timezone":"Asia/Shanghai",
    "iso:country":"CN",
    "name:und_x_variant":[
        "\u5fa1\u53f2",
        "Yushicun"
    ],
    "name:zho_x_preferred":[
        "\u5fa1\u53f2"
    ],
    "wof:name":"Yushi",
    "wof:placetype":"locality"
},
  "geometry": {"coordinates":[108.55389,34.38028],"type":"Point"}
}