{
  "type": "Feature",
  "properties": {
    "gn:admin1_code":"32",
    "gn:asciiname":"Banyou",
    "gn:country_code":"CN",
    "gn:dem":3506,
    "gn:feature_class":"P",
    "gn:feature_code":"PPL",
    "gn:name":"Banyou",
    "gn:population":0,
    "gn:timezone":"Asia/Shanghai",
    "iso:country":"CN",
    "name:und_x_variant":[
        "Doima",
        "Banyou"
    ],
    "name:zho_x_preferred":[
        "\u73ed\u4f51"
    ],
    "wof:name":"Banyou",
    "wof:placetype":"locality"
},
  "geometry": {"coordinates":[103.02897,33.50874],"type":"Point"}
}