{
  "type": "Feature",
  "properties": {
    "gn:admin1_code":"29.0",
    "gn:asciiname":"Luojia Wanzi",
    "gn:country_code":"CN",
    "gn:dem":894,
    "gn:feature_class":"P",
    "gn:feature_code":"PPL",
    "gn:name":"Luojia Wanzi",
    "gn:population":0,
    "gn:timezone":"Asia/Shanghai",
    "iso:country":"CN",
    "name:zho_x_preferred":[
        "\u7f57\u5bb6\u6e7e\u5b50"
    ],
    "wof:name":"Luojia Wanzi",
    "wof:placetype":"locality"
},
  "geometry": {"coordinates":[103.858,27.8387],"type":"Point"}
}