{
  "type": "Feature",
  "properties": {
    "gn:admin1_code":"19.0",
    "gn:asciiname":"Daijiawopu",
    "gn:country_code":"CN",
    "gn:dem":57,
    "gn:feature_class":"P",
    "gn:feature_code":"PPL",
    "gn:name":"Daijiawopu",
    "gn:population":0,
    "gn:timezone":"Asia/Shanghai",
    "iso:country":"CN",
    "name:zho_x_preferred":[
        "\u4ee3\u5bb6\u7a9d\u94fa"
    ],
    "wof:name":"Daijiawopu",
    "wof:placetype":"locality"
},
  "geometry": {"coordinates":[122.41500000000001,42.0939],"type":"Point"}
}