{
  "type": "Feature",
  "properties": {
    "gn:admin1_code":"04",
    "gn:asciiname":"Er'an",
    "gn:country_code":"CN",
    "gn:dem":3,
    "gn:feature_class":"P",
    "gn:feature_code":"PPL",
    "gn:name":"Er\u2019an",
    "gn:population":0,
    "gn:timezone":"Asia/Shanghai",
    "iso:country":"CN",
    "name:und_x_variant":[
        "Erh-an",
        "Erh-wei",
        "Er\u2019an"
    ],
    "wof:name":"Er'an",
    "wof:placetype":"locality"
},
  "geometry": {"coordinates":[120.54833000000001,32.09778],"type":"Point"}
}