{
  "type": "Feature",
  "properties": {
    "gn:admin1_code":"19.0",
    "gn:asciiname":"Shi'an Beigou",
    "gn:country_code":"CN",
    "gn:dem":119,
    "gn:feature_class":"P",
    "gn:feature_code":"PPL",
    "gn:name":"Shi\u2019an Beigou",
    "gn:population":0,
    "gn:timezone":"Asia/Shanghai",
    "iso:country":"CN",
    "name:und_x_variant":[
        "Shi\u2019an Beigou",
        "\u77f3\u5b89\u5317\u6c9f"
    ],
    "wof:name":"Shi'an Beigou",
    "wof:placetype":"locality"
},
  "geometry": {"coordinates":[122.94865,40.79719],"type":"Point"}
}