{
  "type": "Feature",
  "properties": {
    "gn:admin1_code":"11.0",
    "gn:asciiname":"Zhuma'ao",
    "gn:country_code":"CN",
    "gn:dem":560,
    "gn:feature_class":"P",
    "gn:feature_code":"PPL",
    "gn:name":"Zhuma\u2019ao",
    "gn:population":0,
    "gn:timezone":"Asia/Shanghai",
    "iso:country":"CN",
    "name:und_x_variant":[
        "Zhuma\u2019ao"
    ],
    "name:zho_x_preferred":[
        "\u82ce\u9ebb\u5773"
    ],
    "wof:name":"Zhuma'ao",
    "wof:placetype":"locality"
},
  "geometry": {"coordinates":[113.48545,25.56258],"type":"Point"}
}