{
  "type": "Feature",
  "properties": {
    "gn:admin1_code":"13.0",
    "gn:asciiname":"Nurlanggar",
    "gn:country_code":"CN",
    "gn:dem":1964,
    "gn:feature_class":"P",
    "gn:feature_code":"PPL",
    "gn:name":"Nurlanggar",
    "gn:population":0,
    "gn:timezone":"Asia/Shanghai",
    "iso:country":"CN",
    "name:uig_x_preferred":[
        "Nur L\u0259ngg\u0259r"
    ],
    "name:uig_x_variant":[
        "Nur Lengger",
        "\u0646\u06c7\u0631 \u0644\u06d5\u06ad\u06af\u06d5\u0631",
        "\u041d\u0443\u0440 \u041b\u04d9\u04a3\u0433\u04d9\u0440"
    ],
    "name:und_x_variant":[
        "Nu\u2019er Langan"
    ],
    "name:zho_x_preferred":[
        "\u5974\u5c14\u5170\u5e72"
    ],
    "wof:name":"Nurlanggar",
    "wof:placetype":"locality"
},
  "geometry": {"coordinates":[81.43333,36.46667],"type":"Point"}
}