{
  "type": "Feature",
  "properties": {
    "gn:admin1_code":"8.0",
    "gn:asciiname":"Gelatan",
    "gn:country_code":"CN",
    "gn:dem":171,
    "gn:feature_class":"P",
    "gn:feature_code":"PPL",
    "gn:name":"Gelatan",
    "gn:population":0,
    "gn:timezone":"Asia/Shanghai",
    "iso:country":"CN",
    "name:zho_x_preferred":[
        "\u86e4\u62c9\u6ee9"
    ],
    "wof:name":"Gelatan",
    "wof:placetype":"locality"
},
  "geometry": {"coordinates":[127.06731000000001,44.99316],"type":"Point"}
}