{
  "type": "Feature",
  "properties": {
    "gn:admin1_code":"5.0",
    "gn:asciiname":"Houjiaxiangcun",
    "gn:country_code":"CN",
    "gn:dem":245,
    "gn:feature_class":"P",
    "gn:feature_code":"PPL",
    "gn:name":"Houjiaxiangcun",
    "gn:population":0,
    "gn:timezone":"Asia/Shanghai",
    "iso:country":"CN",
    "name:zho_x_preferred":[
        "\u4faf\u5bb6\u4e61\u6751"
    ],
    "wof:name":"Houjiaxiangcun",
    "wof:placetype":"locality"
},
  "geometry": {"coordinates":[126.81856000000001,44.3061],"type":"Point"}
}