{
  "type": "Feature",
  "properties": {
    "gn:admin1_code":"3.0",
    "gn:asciiname":"Kuqian",
    "gn:country_code":"CN",
    "gn:dem":38,
    "gn:feature_class":"P",
    "gn:feature_code":"PPL",
    "gn:name":"Kuqian",
    "gn:population":0,
    "gn:timezone":"Asia/Shanghai",
    "iso:country":"CN",
    "name:und_x_variant":[
        "\u5e93\u524d"
    ],
    "wof:name":"Kuqian",
    "wof:placetype":"locality"
},
  "geometry": {"coordinates":[116.24359,28.18804],"type":"Point"}
}