{
  "type": "Feature",
  "properties": {
    "gn:admin1_code":"26",
    "gn:asciiname":"Guojiabian",
    "gn:cc2":"CN",
    "gn:country_code":"CN",
    "gn:dem":1071,
    "gn:feature_class":"P",
    "gn:feature_code":"PPL",
    "gn:name":"Guojiabian",
    "gn:population":0,
    "gn:timezone":"Asia/Shanghai",
    "iso:country":"CN",
    "name:und_x_variant":[
        "Kuo-chia-pien",
        "Guojiabian"
    ],
    "wof:name":"Guojiabian",
    "wof:placetype":"locality"
},
  "geometry": {"coordinates":[109.96666999999999,37.81667],"type":"Point"}
}