{
  "type": "Feature",
  "properties": {
    "gn:admin1_code":"9.0",
    "gn:asciiname":"Gaogou",
    "gn:country_code":"CN",
    "gn:dem":248,
    "gn:feature_class":"P",
    "gn:feature_code":"PPL",
    "gn:name":"Gaogou",
    "gn:population":0,
    "gn:timezone":"Asia/Shanghai",
    "iso:country":"CN",
    "name:und_x_variant":[
        "\u9ad8\u6c9f",
        "Gaogou"
    ],
    "wof:name":"Gaogou",
    "wof:placetype":"locality"
},
  "geometry": {"coordinates":[112.72187,33.33299],"type":"Point"}
}