{
  "type": "Feature",
  "properties": {
    "gn:admin1_code":"7.0",
    "gn:asciiname":"Chengxia",
    "gn:country_code":"CN",
    "gn:dem":462,
    "gn:feature_class":"P",
    "gn:feature_code":"PPL",
    "gn:name":"Chengxia",
    "gn:population":0,
    "gn:timezone":"Asia/Shanghai",
    "iso:country":"CN",
    "name:und_x_variant":[
        "\u57ce\u4e0b"
    ],
    "wof:name":"Chengxia",
    "wof:placetype":"locality"
},
  "geometry": {"coordinates":[116.93823,26.5443],"type":"Point"}
}