{
  "type": "Feature",
  "properties": {
    "gn:admin1_code":"26",
    "gn:asciiname":"Dancun",
    "gn:country_code":"CN",
    "gn:dem":504,
    "gn:feature_class":"P",
    "gn:feature_code":"PPLA4",
    "gn:name":"Dancun",
    "gn:population":0,
    "gn:timezone":"Asia/Shanghai",
    "iso:country":"CN",
    "name:und_x_variant":[
        "Tan-ts\u2019un",
        "Tan-ts\u2019un-chen",
        "Dancun",
        "Dancun Zhen"
    ],
    "name:zho_x_preferred":[
        "\u6de1\u6751"
    ],
    "wof:name":"Dancun",
    "wof:placetype":"locality"
},
  "geometry": {"coordinates":[109.05352000000001,34.71947],"type":"Point"}
}