{
  "type": "Feature",
  "properties": {
    "gn:admin1_code":"32.0",
    "gn:asciiname":"Niutuitian",
    "gn:country_code":"CN",
    "gn:dem":481,
    "gn:feature_class":"P",
    "gn:feature_code":"PPL",
    "gn:name":"Niutuitian",
    "gn:population":0,
    "gn:timezone":"Asia/Shanghai",
    "iso:country":"CN",
    "name:zho_x_preferred":[
        "\u725b\u817f\u7530"
    ],
    "wof:name":"Niutuitian",
    "wof:placetype":"locality"
},
  "geometry": {"coordinates":[104.407,28.3715],"type":"Point"}
}