{
  "type": "Feature",
  "properties": {
    "gn:admin1_code":"30",
    "gn:asciiname":"Dongba",
    "gn:country_code":"CN",
    "gn:dem":229,
    "gn:feature_class":"P",
    "gn:feature_code":"PPLA4",
    "gn:name":"Dongba",
    "gn:population":0,
    "gn:timezone":"Asia/Shanghai",
    "iso:country":"CN",
    "name:deu_x_preferred":[
        "Dongba"
    ],
    "name:fra_x_preferred":[
        "Dongba"
    ],
    "name:ita_x_preferred":[
        "Dongba"
    ],
    "name:pol_x_preferred":[
        "Dongba"
    ],
    "name:por_x_preferred":[
        "Dongba"
    ],
    "name:tha_x_preferred":[
        "\u0e25\u0e31\u0e17\u0e18\u0e34\u0e15\u0e07\u0e1b\u0e32"
    ],
    "name:und_x_variant":[
        "\u4e1c\u575d",
        "Dongba Zhen",
        "\u4e1c\u575d\u9547"
    ],
    "name:vie_x_preferred":[
        "Dongba"
    ],
    "name:zho_x_preferred":[
        "\u6771\u5df4\u6559"
    ],
    "wof:name":"Dongba",
    "wof:placetype":"locality"
},
  "geometry": {"coordinates":[111.75163999999999,22.94021],"type":"Point"}
}