{
  "type": "Feature",
  "properties": {
    "gn:admin1_code":"2.0",
    "gn:asciiname":"Yujiabang",
    "gn:country_code":"CN",
    "gn:dem":7,
    "gn:feature_class":"P",
    "gn:feature_code":"PPL",
    "gn:name":"Yujiabang",
    "gn:population":0,
    "gn:timezone":"Asia/Shanghai",
    "iso:country":"CN",
    "name:und_x_variant":[
        "\u4fde\u5bb6\u6d5c"
    ],
    "wof:name":"Yujiabang",
    "wof:placetype":"locality"
},
  "geometry": {"coordinates":[121.10871000000002,30.63002],"type":"Point"}
}