{
  "type": "Feature",
  "properties": {
    "gn:admin1_code":"1.0",
    "gn:asciiname":"Lujiazhou",
    "gn:country_code":"CN",
    "gn:dem":238,
    "gn:feature_class":"P",
    "gn:feature_code":"PPL",
    "gn:name":"Lujiazhou",
    "gn:population":0,
    "gn:timezone":"Asia/Shanghai",
    "iso:country":"CN",
    "name:zho_x_preferred":[
        "\u5362\u5bb6\u5dde"
    ],
    "wof:name":"Lujiazhou",
    "wof:placetype":"locality"
},
  "geometry": {"coordinates":[117.16298,29.9451],"type":"Point"}
}