{
  "type": "Feature",
  "properties": {
    "gn:admin1_code":"32.0",
    "gn:asciiname":"Jiefang",
    "gn:country_code":"CN",
    "gn:dem":900,
    "gn:feature_class":"P",
    "gn:feature_code":"PPL",
    "gn:name":"Jiefang",
    "gn:population":0,
    "gn:timezone":"Asia/Shanghai",
    "iso:country":"CN",
    "name:ceb_x_preferred":[
        "Jiefang"
    ],
    "name:deu_x_preferred":[
        "Jiefang"
    ],
    "name:zho_x_preferred":[
        "\u89e3\u653e"
    ],
    "wof:name":"Jiefang",
    "wof:placetype":"locality"
},
  "geometry": {"coordinates":[105.761,32.6896],"type":"Point"}
}