{
  "type": "Feature",
  "properties": {
    "gn:admin1_code":"10",
    "gn:asciiname":"Sangezhuang",
    "gn:country_code":"CN",
    "gn:dem":10,
    "gn:feature_class":"P",
    "gn:feature_code":"PPL",
    "gn:name":"Sangezhuang",
    "gn:population":0,
    "gn:timezone":"Asia/Shanghai",
    "iso:country":"CN",
    "name:zho_x_preferred":[
        "\u4e09\u5404\u5e84"
    ],
    "wof:name":"Sangezhuang",
    "wof:placetype":"locality"
},
  "geometry": {"coordinates":[116.06699999999999,38.8122],"type":"Point"}
}