{
  "type": "Feature",
  "properties": {
    "gn:admin1_code":"29.0",
    "gn:asciiname":"Lueluo",
    "gn:country_code":"CN",
    "gn:dem":1677,
    "gn:feature_class":"P",
    "gn:feature_code":"PPL",
    "gn:name":"Lueluo",
    "gn:population":0,
    "gn:timezone":"Asia/Shanghai",
    "iso:country":"CN",
    "name:zho_x_preferred":[
        "\u7565\u843d"
    ],
    "wof:name":"Lueluo",
    "wof:placetype":"locality"
},
  "geometry": {"coordinates":[104.07599999999999,27.4612],"type":"Point"}
}