{
  "type": "Feature",
  "properties": {
    "gn:admin1_code":"4.0",
    "gn:asciiname":"Hengjiecun",
    "gn:country_code":"CN",
    "gn:dem":9,
    "gn:feature_class":"P",
    "gn:feature_code":"PPL",
    "gn:name":"Hengjiecun",
    "gn:population":0,
    "gn:timezone":"Asia/Shanghai",
    "iso:country":"CN",
    "name:zho_x_preferred":[
        "\u6a2a\u8857\u6751"
    ],
    "wof:name":"Hengjiecun",
    "wof:placetype":"locality"
},
  "geometry": {"coordinates":[118.94568,34.72308],"type":"Point"}
}