{
  "type": "Feature",
  "properties": {
    "gn:admin1_code":"16",
    "gn:asciiname":"Bala",
    "gn:country_code":"CN",
    "gn:dem":351,
    "gn:feature_class":"P",
    "gn:feature_code":"PPL",
    "gn:name":"Bala",
    "gn:population":0,
    "gn:timezone":"Asia/Shanghai",
    "iso:country":"CN",
    "name:und_x_variant":[
        "Pa-la",
        "Bala"
    ],
    "name:zho_x_preferred":[
        "\u516b\u814a"
    ],
    "wof:name":"Bala",
    "wof:placetype":"locality"
},
  "geometry": {"coordinates":[106.986,25.24],"type":"Point"}
}