{
  "type": "Feature",
  "properties": {
    "gn:admin1_code":"26.0",
    "gn:asciiname":"Mengjiahao",
    "gn:country_code":"CN",
    "gn:dem":1144,
    "gn:feature_class":"P",
    "gn:feature_code":"PPL",
    "gn:name":"Mengjiahao",
    "gn:population":0,
    "gn:timezone":"Asia/Shanghai",
    "iso:country":"CN",
    "name:zho_x_preferred":[
        "\u5b5f\u5bb6\u58d5"
    ],
    "wof:name":"Mengjiahao",
    "wof:placetype":"locality"
},
  "geometry": {"coordinates":[109.62820000000001,38.16984],"type":"Point"}
}