{
  "type": "Feature",
  "properties": {
    "gn:admin1_code":"33.0",
    "gn:asciiname":"Xinzheng",
    "gn:country_code":"CN",
    "gn:dem":597,
    "gn:feature_class":"P",
    "gn:feature_code":"PPL",
    "gn:name":"Xinzheng",
    "gn:population":0,
    "gn:timezone":"Asia/Shanghai",
    "iso:country":"CN",
    "name:zho_x_preferred":[
        "\u65b0\u653f"
    ],
    "wof:name":"Xinzheng",
    "wof:placetype":"locality"
},
  "geometry": {"coordinates":[108.71132,30.70778],"type":"Point"}
}