{
  "type": "Feature",
  "properties": {
    "gn:admin1_code":"33.0",
    "gn:asciiname":"Xinzheng",
    "gn:country_code":"CN",
    "gn:dem":597,
    "gn:feature_class":"P",
    "gn:feature_code":"PPL",
    "gn:name":"Xinzheng",
    "gn:population":0,
    "gn:timezone":"Asia/Shanghai",
    "iso:country":"CN",
    "name:amh_x_preferred":[
        "\u123a\u1295\u12e0\u1295\u130d"
    ],
    "name:deu_x_preferred":[
        "Xinzheng"
    ],
    "name:eus_x_preferred":[
        "Xinzheng"
    ],
    "name:fra_x_preferred":[
        "Xinzheng"
    ],
    "name:ind_x_preferred":[
        "Xinzheng"
    ],
    "name:ita_x_preferred":[
        "Xinzheng"
    ],
    "name:jpn_x_preferred":[
        "\u65b0\u912d\u5e02"
    ],
    "name:kik_x_preferred":[
        "Xinzheng"
    ],
    "name:kor_x_preferred":[
        "\uc2e0\uc815\uc2dc"
    ],
    "name:mlg_x_preferred":[
        "Xinzheng"
    ],
    "name:nor_x_preferred":[
        "Xinzheng"
    ],
    "name:pam_x_preferred":[
        "Xinzheng"
    ],
    "name:pol_x_preferred":[
        "Xinzheng"
    ],
    "name:rus_x_preferred":[
        "\u0421\u0438\u043d\u044c\u0447\u0436\u044d\u043d"
    ],
    "name:spa_x_preferred":[
        "Xinzheng"
    ],
    "name:swe_x_preferred":[
        "Xinzheng"
    ],
    "name:urd_x_preferred":[
        "\u0634\u06cc\u0646\u0698\u06cc\u0646\u06af"
    ],
    "name:vie_x_preferred":[
        "T\u00e2n Tr\u1ecbnh"
    ],
    "name:zho_x_preferred":[
        "\u65b0\u653f"
    ],
    "name:zho_x_variant":[
        "\u65b0\u90d1\u5e02"
    ],
    "wof:name":"Xinzheng",
    "wof:placetype":"locality"
},
  "geometry": {"coordinates":[108.71132,30.70778],"type":"Point"}
}