{
  "type": "Feature",
  "properties": {
    "gn:admin1_code":"3.0",
    "gn:asciiname":"Dongzishang",
    "gn:country_code":"CN",
    "gn:dem":721,
    "gn:feature_class":"P",
    "gn:feature_code":"PPL",
    "gn:name":"Dongzishang",
    "gn:population":0,
    "gn:timezone":"Asia/Shanghai",
    "iso:country":"CN",
    "name:und_x_variant":[
        "\u6d1e\u5b50\u4e0a"
    ],
    "wof:name":"Dongzishang",
    "wof:placetype":"locality"
},
  "geometry": {"coordinates":[114.44352000000001,29.3178],"type":"Point"}
}