{
  "type": "Feature",
  "properties": {
    "gn:admin1_code":"14.0",
    "gn:asciiname":"Dongxi",
    "gn:country_code":"CN",
    "gn:dem":4180,
    "gn:feature_class":"P",
    "gn:feature_code":"PPL",
    "gn:name":"Dongxi",
    "gn:population":0,
    "gn:timezone":"Asia/Urumqi",
    "iso:country":"CN",
    "name:ceb_x_preferred":[
        "Dongxi"
    ],
    "name:swe_x_preferred":[
        "Dongxi"
    ],
    "name:zho_x_preferred":[
        "\u6d1e\u6eaa"
    ],
    "wof:name":"Dongxi",
    "wof:placetype":"locality"
},
  "geometry": {"coordinates":[93.92522,30.68523],"type":"Point"}
}