{
  "type": "Feature",
  "properties": {
    "gn:admin1_code":"7.0",
    "gn:asciiname":"Wufeng",
    "gn:country_code":"CN",
    "gn:dem":462,
    "gn:feature_class":"P",
    "gn:feature_code":"PPL",
    "gn:name":"Wufeng",
    "gn:population":0,
    "gn:timezone":"Asia/Shanghai",
    "iso:country":"CN",
    "name:ceb_x_preferred":[
        "Wufeng"
    ],
    "name:deu_x_preferred":[
        "Wufeng"
    ],
    "name:fra_x_preferred":[
        "Wufeng"
    ],
    "name:pol_x_preferred":[
        "Wufeng"
    ],
    "name:zho_x_preferred":[
        "\u68a7\u5cf0"
    ],
    "wof:name":"Wufeng",
    "wof:placetype":"locality"
},
  "geometry": {"coordinates":[118.67010000000001,25.1515],"type":"Point"}
}