{
  "type": "Feature",
  "properties": {
    "gn:admin1_code":"29.0",
    "gn:asciiname":"Tuoluoqing",
    "gn:country_code":"CN",
    "gn:dem":1128,
    "gn:feature_class":"P",
    "gn:feature_code":"PPL",
    "gn:name":"Tuoluoqing",
    "gn:population":0,
    "gn:timezone":"Asia/Shanghai",
    "iso:country":"CN",
    "name:zho_x_preferred":[
        "\u9a6e\u9a86\u7b90"
    ],
    "wof:name":"Tuoluoqing",
    "wof:placetype":"locality"
},
  "geometry": {"coordinates":[101.318,23.838],"type":"Point"}
}