{
  "type": "Feature",
  "properties": {
    "gn:admin1_code":"9",
    "gn:asciiname":"Weidianji",
    "gn:country_code":"CN",
    "gn:dem":48,
    "gn:feature_class":"P",
    "gn:feature_code":"PPL",
    "gn:name":"Weidianji",
    "gn:population":0,
    "gn:timezone":"Asia/Shanghai",
    "iso:country":"CN",
    "name:zho_x_preferred":[
        "\u56f4\u5e97\u96c6"
    ],
    "wof:name":"Weidianji",
    "wof:placetype":"locality"
},
  "geometry": {"coordinates":[115.94199999999999,34.4636],"type":"Point"}
}