{
  "type": "Feature",
  "properties": {
    "gn:admin1_code":"16.0",
    "gn:asciiname":"Chenshuangcun",
    "gn:country_code":"CN",
    "gn:dem":235,
    "gn:feature_class":"P",
    "gn:feature_code":"PPL",
    "gn:name":"Chenshuangcun",
    "gn:population":0,
    "gn:timezone":"Asia/Shanghai",
    "iso:country":"CN",
    "name:zho_x_preferred":[
        "\u9648\u53cc\u6751"
    ],
    "wof:name":"Chenshuangcun",
    "wof:placetype":"locality"
},
  "geometry": {"coordinates":[108.235,24.8792],"type":"Point"}
}