{
  "type": "Feature",
  "properties": {
    "gn:admin1_code":"3.0",
    "gn:asciiname":"Tashuiqiao Zhaojia",
    "gn:country_code":"CN",
    "gn:dem":53,
    "gn:feature_class":"P",
    "gn:feature_code":"PPL",
    "gn:name":"Tashuiqiao Zhaojia",
    "gn:population":0,
    "gn:timezone":"Asia/Shanghai",
    "iso:country":"CN",
    "name:zho_x_preferred":[
        "\u5854\u6c34\u6865\u8d75\u5bb6"
    ],
    "wof:name":"Tashuiqiao Zhaojia",
    "wof:placetype":"locality"
},
  "geometry": {"coordinates":[117.33026,28.21326],"type":"Point"}
}