{
  "type": "Feature",
  "properties": {
    "gn:admin1_code":"16.0",
    "gn:asciiname":"Wujiadong",
    "gn:country_code":"CN",
    "gn:dem":1342,
    "gn:feature_class":"P",
    "gn:feature_code":"PPL",
    "gn:name":"Wujiadong",
    "gn:population":0,
    "gn:timezone":"Asia/Shanghai",
    "iso:country":"CN",
    "name:zho_x_preferred":[
        "\u5deb\u5bb6\u578c"
    ],
    "wof:name":"Wujiadong",
    "wof:placetype":"locality"
},
  "geometry": {"coordinates":[106.29300000000001,24.5171],"type":"Point"}
}