{
  "type": "Feature",
  "properties": {
    "gn:admin1_code":"30.0",
    "gn:asciiname":"Beiwei",
    "gn:country_code":"CN",
    "gn:dem":8,
    "gn:feature_class":"P",
    "gn:feature_code":"PPL",
    "gn:name":"Beiwei",
    "gn:population":0,
    "gn:timezone":"Asia/Urumqi",
    "iso:country":"CN",
    "name:zho_x_preferred":[
        "\u5317\u5c3e"
    ],
    "wof:name":"Beiwei",
    "wof:placetype":"locality"
},
  "geometry": {"coordinates":[110.45461,20.60371],"type":"Point"}
}