{
  "type": "Feature",
  "properties": {
    "gn:admin1_code":"25.0",
    "gn:asciiname":"Qiujia",
    "gn:country_code":"CN",
    "gn:dem":83,
    "gn:feature_class":"P",
    "gn:feature_code":"PPL",
    "gn:name":"Qiujia",
    "gn:population":0,
    "gn:timezone":"Asia/Shanghai",
    "iso:country":"CN",
    "name:zho_x_preferred":[
        "\u4e18\u5bb6"
    ],
    "wof:name":"Qiujia",
    "wof:placetype":"locality"
},
  "geometry": {"coordinates":[120.46487999999999,37.37286],"type":"Point"}
}