{
  "type": "Feature",
  "properties": {
    "gn:admin1_code":"26.0",
    "gn:asciiname":"Baitouyuan",
    "gn:country_code":"CN",
    "gn:dem":1411,
    "gn:feature_class":"P",
    "gn:feature_code":"PPL",
    "gn:name":"Baitouyuan",
    "gn:population":0,
    "gn:timezone":"Asia/Shanghai",
    "iso:country":"CN",
    "name:zho_x_preferred":[
        "\u767d\u5934\u539f"
    ],
    "wof:name":"Baitouyuan",
    "wof:placetype":"locality"
},
  "geometry": {"coordinates":[110.23945999999999,34.39477],"type":"Point"}
}