{
  "type": "Feature",
  "properties": {
    "gn:admin1_code":"16.0",
    "gn:asciiname":"Caihua",
    "gn:country_code":"CN",
    "gn:dem":845,
    "gn:feature_class":"P",
    "gn:feature_code":"PPL",
    "gn:name":"Caihua",
    "gn:population":0,
    "gn:timezone":"Asia/Shanghai",
    "iso:country":"CN",
    "name:zho_x_preferred":[
        "\u624d\u534e"
    ],
    "wof:name":"Caihua",
    "wof:placetype":"locality"
},
  "geometry": {"coordinates":[107.28100000000001,25.3359],"type":"Point"}
}