{
  "type": "Feature",
  "properties": {
    "gn:admin1_code":"3.0",
    "gn:asciiname":"Xiaomaikeng",
    "gn:country_code":"CN",
    "gn:dem":326,
    "gn:feature_class":"P",
    "gn:feature_code":"PPL",
    "gn:name":"Xiaomaikeng",
    "gn:population":0,
    "gn:timezone":"Asia/Shanghai",
    "iso:country":"CN",
    "name:zho_x_preferred":[
        "\u5c0f\u9ea6\u5751"
    ],
    "wof:name":"Xiaomaikeng",
    "wof:placetype":"locality"
},
  "geometry": {"coordinates":[114.94799999999999,29.3297],"type":"Point"}
}