{
  "type": "Feature",
  "properties": {
    "gn:admin1_code":"20",
    "gn:asciiname":"Shui-ch'uan-kou",
    "gn:country_code":"CN",
    "gn:dem":722,
    "gn:feature_class":"P",
    "gn:feature_code":"PPL",
    "gn:name":"Shui-ch\u2019uan-kou",
    "gn:population":0,
    "gn:timezone":"Asia/Shanghai",
    "iso:country":"CN",
    "wof:name":"Shui-ch'uan-kou",
    "wof:placetype":"locality"
},
  "geometry": {"coordinates":[119.03,42.03778],"type":"Point"}
}