{
  "type": "Feature",
  "properties": {
    "gn:admin1_code":"19.0",
    "gn:asciiname":"Xiaodianzi",
    "gn:country_code":"CN",
    "gn:dem":74,
    "gn:feature_class":"P",
    "gn:feature_code":"PPL",
    "gn:name":"Xiaodianzi",
    "gn:population":0,
    "gn:timezone":"Asia/Shanghai",
    "iso:country":"CN",
    "name:zho_x_preferred":[
        "\u5c0f\u7538\u5b50"
    ],
    "wof:name":"Xiaodianzi",
    "wof:placetype":"locality"
},
  "geometry": {"coordinates":[123.58431000000002,40.35815],"type":"Point"}
}