{
  "type": "Feature",
  "properties": {
    "gn:admin1_code":"26.0",
    "gn:asciiname":"Mingshuicun",
    "gn:country_code":"CN",
    "gn:dem":367,
    "gn:feature_class":"P",
    "gn:feature_code":"PPL",
    "gn:name":"Mingshuicun",
    "gn:population":0,
    "gn:timezone":"Asia/Shanghai",
    "iso:country":"CN",
    "name:zho_x_preferred":[
        "\u660e\u6c34\u6751"
    ],
    "wof:name":"Mingshuicun",
    "wof:placetype":"locality"
},
  "geometry": {"coordinates":[109.79192999999999,34.80301],"type":"Point"}
}