{
  "type": "Feature",
  "properties": {
    "gn:admin1_code":"15.0",
    "gn:asciiname":"Dongjia Xinzhuang",
    "gn:country_code":"CN",
    "gn:dem":1921,
    "gn:feature_class":"P",
    "gn:feature_code":"PPL",
    "gn:name":"Dongjia Xinzhuang",
    "gn:population":0,
    "gn:timezone":"Asia/Shanghai",
    "iso:country":"CN",
    "name:zho_x_preferred":[
        "\u8463\u5bb6\u65b0\u5e84"
    ],
    "wof:name":"Dongjia Xinzhuang",
    "wof:placetype":"locality"
},
  "geometry": {"coordinates":[104.678,35.1944],"type":"Point"}
}