{
  "type": "Feature",
  "properties": {
    "gn:admin1_code":"30",
    "gn:asciiname":"Youtian Linchang",
    "gn:country_code":"CN",
    "gn:dem":180,
    "gn:feature_class":"P",
    "gn:feature_code":"PPLF",
    "gn:name":"Youtian Linchang",
    "gn:population":0,
    "gn:timezone":"Asia/Shanghai",
    "iso:country":"CN",
    "name:zho_x_preferred":[
        "\u6cb9\u7530\u6797\u573a"
    ],
    "wof:name":"Youtian Linchang",
    "wof:placetype":"locality"
},
  "geometry": {"coordinates":[114.04158,23.65361],"type":"Point"}
}