{
  "type": "Feature",
  "properties": {
    "gn:admin1_code":"16",
    "gn:asciiname":"Huanglajie",
    "gn:country_code":"CN",
    "gn:dem":517,
    "gn:feature_class":"P",
    "gn:feature_code":"PPL",
    "gn:name":"Huanglajie",
    "gn:population":0,
    "gn:timezone":"Asia/Shanghai",
    "iso:country":"CN",
    "name:zho_x_preferred":[
        "\u9ec4\u814a\u754c"
    ],
    "wof:name":"Huanglajie",
    "wof:placetype":"locality"
},
  "geometry": {"coordinates":[110.711,24.9354],"type":"Point"}
}