{
  "type": "Feature",
  "properties": {
    "gn:admin1_code":"30",
    "gn:asciiname":"Houge",
    "gn:country_code":"CN",
    "gn:dem":9,
    "gn:feature_class":"P",
    "gn:feature_code":"PPL",
    "gn:name":"Houge",
    "gn:population":0,
    "gn:timezone":"Asia/Urumqi",
    "iso:country":"CN",
    "name:und_x_variant":[
        "Hou-ko",
        "Houge"
    ],
    "name:zho_x_preferred":[
        "\u540e\u845b"
    ],
    "wof:name":"Houge",
    "wof:placetype":"locality"
},
  "geometry": {"coordinates":[110.36393,20.82044],"type":"Point"}
}