{
  "type": "Feature",
  "properties": {
    "gn:admin1_code":"8.0",
    "gn:asciiname":"Nanxiangyangcun",
    "gn:country_code":"CN",
    "gn:dem":111,
    "gn:feature_class":"P",
    "gn:feature_code":"PPL",
    "gn:name":"Nanxiangyangcun",
    "gn:population":0,
    "gn:timezone":"Asia/Shanghai",
    "iso:country":"CN",
    "name:zho_x_preferred":[
        "\u5357\u5411\u9633\u6751"
    ],
    "wof:name":"Nanxiangyangcun",
    "wof:placetype":"locality"
},
  "geometry": {"coordinates":[129.82064,46.73032],"type":"Point"}
}