{
  "type": "Feature",
  "properties": {
    "gn:admin1_code":"9.0",
    "gn:asciiname":"Nimamiao",
    "gn:country_code":"CN",
    "gn:dem":66,
    "gn:feature_class":"P",
    "gn:feature_code":"PPL",
    "gn:name":"Nimamiao",
    "gn:population":0,
    "gn:timezone":"Asia/Shanghai",
    "iso:country":"CN",
    "name:zho_x_preferred":[
        "\u6ce5\u9a6c\u5e99"
    ],
    "wof:name":"Nimamiao",
    "wof:placetype":"locality"
},
  "geometry": {"coordinates":[114.52083,35.45608],"type":"Point"}
}