{
  "type": "Feature",
  "properties": {
    "gn:admin1_code":"24.0",
    "gn:asciiname":"Xiashimen",
    "gn:country_code":"CN",
    "gn:dem":739,
    "gn:feature_class":"P",
    "gn:feature_code":"PPL",
    "gn:name":"Xiashimen",
    "gn:population":0,
    "gn:timezone":"Asia/Shanghai",
    "iso:country":"CN",
    "name:zho_x_preferred":[
        "\u4e0b\u77f3\u95e8"
    ],
    "wof:name":"Xiashimen",
    "wof:placetype":"locality"
},
  "geometry": {"coordinates":[111.82606,35.7335],"type":"Point"}
}