{
  "type": "Feature",
  "properties": {
    "gn:admin1_code":"10",
    "gn:asciiname":"Baibao",
    "gn:cc2":"CN",
    "gn:country_code":"CN",
    "gn:dem":57,
    "gn:feature_class":"P",
    "gn:feature_code":"PPL",
    "gn:name":"Baibao",
    "gn:population":0,
    "gn:timezone":"Asia/Shanghai",
    "iso:country":"CN",
    "name:und_x_variant":[
        "Pai-pao-chen",
        "Pai-pao",
        "Baibao"
    ],
    "wof:name":"Baibao",
    "wof:placetype":"locality"
},
  "geometry": {"coordinates":[115.30638999999999,39.05528],"type":"Point"}
}