{
  "type": "Feature",
  "properties": {
    "gn:admin1_code":"8.0",
    "gn:asciiname":"Qianlianhuapao",
    "gn:country_code":"CN",
    "gn:dem":146,
    "gn:feature_class":"P",
    "gn:feature_code":"PPL",
    "gn:name":"Qianlianhuapao",
    "gn:population":0,
    "gn:timezone":"Asia/Shanghai",
    "iso:country":"CN",
    "name:zho_x_preferred":[
        "\u524d\u83b2\u82b1\u6ce1"
    ],
    "wof:name":"Qianlianhuapao",
    "wof:placetype":"locality"
},
  "geometry": {"coordinates":[123.86613,46.65428],"type":"Point"}
}