{
  "type": "Feature",
  "properties": {
    "gn:admin1_code":"32.0",
    "gn:asciiname":"Miaobeihou",
    "gn:country_code":"CN",
    "gn:dem":1710,
    "gn:feature_class":"P",
    "gn:feature_code":"PPL",
    "gn:name":"Miaobeihou",
    "gn:population":0,
    "gn:timezone":"Asia/Shanghai",
    "iso:country":"CN",
    "name:zho_x_preferred":[
        "\u5e99\u80cc\u540e"
    ],
    "wof:name":"Miaobeihou",
    "wof:placetype":"locality"
},
  "geometry": {"coordinates":[104.774,32.569],"type":"Point"}
}