{
  "type": "Feature",
  "properties": {
    "iso:country":"CN",
    "name:eng_x_preferred":[
        "Qiqihar"
    ],
    "name:zho_x_preferred":[
        "\u9f50\u9f50\u54c8\u5c14\u5e02"
    ],
    "qs:name":"\u9f50\u9f50\u54c8\u5c14\u5e02",
    "qs:name_adm0":"\u4e2d\u570b",
    "qs:name_adm1":"\u9ed1\u9f99\u6c5f\u7701",
    "qs:photos":5,
    "qs:photos_1k":1,
    "qs:photos_9k":1,
    "qs:photos_9r":4,
    "qs:photos_all":187,
    "qs:photos_sr":1,
    "qs:placetype":"LocalAdmin",
    "qs:pop_sr":"0",
    "wof:name":"Qiqihar",
    "wof:placetype":"localadmin"
},
  "geometry": {"coordinates":[123.959197,47.343711],"type":"Point"}
}