{
  "type": "Feature",
  "properties": {
    "gn:country":"CN",
    "gn:fcode":"ADM3",
    "gn:population":0,
    "iso:country":"CN",
    "name:ceb_x_preferred":[
        "Tongguan Xian"
    ],
    "name:deu_x_preferred":[
        "Tongguan"
    ],
    "name:eng_x_preferred":[
        "Tongguan County"
    ],
    "name:fas_x_preferred":[
        "\u0634\u0647\u0631\u0633\u062a\u0627\u0646 \u062a\u0648\u0646\u06af\u0648\u0627\u0646"
    ],
    "name:gan_x_preferred":[
        "\u6f7c\u5173\u53bf"
    ],
    "name:ind_x_preferred":[
        "Kabupaten Tongguan"
    ],
    "name:jpn_x_preferred":[
        "\u6f7c\u95a2\u770c"
    ],
    "name:kor_x_preferred":[
        "\ud241\uad00\ud604"
    ],
    "name:nan_x_preferred":[
        "T\u00f4ng-koan-ko\u0101n"
    ],
    "name:nld_x_preferred":[
        "Tongguan"
    ],
    "name:nob_x_preferred":[
        "Tongguan"
    ],
    "name:rus_x_preferred":[
        "\u0422\u0443\u043d\u0433\u0443\u0430\u043d\u044c"
    ],
    "name:swe_x_preferred":[
        "Tongguan"
    ],
    "name:und_x_variant":[
        "T\u2019ung-kuan Hsien"
    ],
    "name:vie_x_preferred":[
        "\u0110\u1ed3ng Quan"
    ],
    "name:wuu_x_preferred":[
        "\u6f7c\u5173\u53bf"
    ],
    "name:yue_x_preferred":[
        "\u6f7c\u95dc"
    ],
    "name:zho_x_preferred":[
        "\u6f7c\u5173\u53bf"
    ],
    "name:zho_x_variant":[
        "\u6f7c\u5173"
    ],
    "qs:name":"Tongguan Xian",
    "qs:photos_9r":0,
    "qs:photos_sr":0,
    "qs:pop_sr":"0",
    "wd:wordcount":217,
    "wof:name":"Tongguan Xian",
    "wof:placetype":"localadmin",
    "wof:population":0
},
  "geometry": {"coordinates":[110.26361,34.48639],"type":"Point"}
}