{
  "type": "Feature",
  "properties": {
    "gn:country":"CN",
    "gn:fcode":"ADM3",
    "gn:pop":0,
    "iso:country":"CN",
    "name:unk_x_variant":[
        "T\u2019ung-kuan Hsien"
    ],
    "name:zho_x_preferred":[
        "\u6f7c\u5173\u53bf"
    ],
    "name:zho_x_variant":[
        "\u6f7c\u5173"
    ],
    "qs:name":"Tongguan Xian",
    "qs:photos_9r":0,
    "qs:photos_sr":0,
    "qs:pop_sr":"0",
    "wd:wordcount":217,
    "wof:name":"Tongguan Xian",
    "wof:placetype":"localadmin",
    "wof:population":0
},
  "geometry": {"coordinates":[110.26361,34.48639],"type":"Point"}
}