{
  "type": "Feature",
  "properties": {
    "gn:admin1_code":"30.0",
    "gn:asciiname":"Luoshun Zhen",
    "gn:country_code":"CN",
    "gn:dem":141,
    "gn:feature_class":"P",
    "gn:feature_code":"PPL",
    "gn:name":"Luoshun Zhen",
    "gn:population":0,
    "gn:timezone":"Asia/Shanghai",
    "iso:country":"CN",
    "name:zho_x_preferred":[
        "\u7f57\u987a\u9547"
    ],
    "wof:name":"Luoshun Zhen",
    "wof:placetype":"locality"
},
  "geometry": {"coordinates":[111.41979000000001,23.10356],"type":"Point"}
}