{
  "type": "Feature",
  "properties": {
    "gn:admin1_code":"4.0",
    "gn:asciiname":"Yinyanghecun",
    "gn:country_code":"CN",
    "gn:dem":5,
    "gn:feature_class":"P",
    "gn:feature_code":"PPL",
    "gn:name":"Yinyanghecun",
    "gn:population":0,
    "gn:timezone":"Asia/Shanghai",
    "iso:country":"CN",
    "name:und_x_variant":[
        "Yinyanghe",
        "\u94f6\u6d0b\u6cb3"
    ],
    "name:zho_x_preferred":[
        "\u94f6\u6d0b\u6cb3\u6751"
    ],
    "wof:name":"Yinyanghecun",
    "wof:placetype":"locality"
},
  "geometry": {"coordinates":[121.00049,31.9173],"type":"Point"}
}