{
  "type": "Feature",
  "properties": {
    "gn:admin1_code":"16.0",
    "gn:asciiname":"Shiluoxu",
    "gn:country_code":"CN",
    "gn:dem":104,
    "gn:feature_class":"P",
    "gn:feature_code":"PPL",
    "gn:name":"Shiluoxu",
    "gn:population":0,
    "gn:timezone":"Asia/Shanghai",
    "iso:country":"CN",
    "name:zho_x_preferred":[
        "\u72ee\u87ba\u5729"
    ],
    "wof:name":"Shiluoxu",
    "wof:placetype":"locality"
},
  "geometry": {"coordinates":[108.777,23.3526],"type":"Point"}
}