{
  "type": "Feature",
  "properties": {
    "gn:admin1_code":"7",
    "gn:asciiname":"Sejiang",
    "gn:country_code":"CN",
    "gn:dem":10,
    "gn:feature_class":"P",
    "gn:feature_code":"PPL",
    "gn:name":"Sejiang",
    "gn:population":0,
    "gn:timezone":"Asia/Shanghai",
    "iso:country":"CN",
    "name:und_x_variant":[
        "Se-chiang",
        "Sejiang"
    ],
    "name:zho_x_preferred":[
        "\u745f\u6c5f"
    ],
    "wof:name":"Sejiang",
    "wof:placetype":"locality"
},
  "geometry": {"coordinates":[119.56123999999998,25.50966],"type":"Point"}
}