{
  "type": "Feature",
  "properties": {
    "gn:admin1_code":"19.0",
    "gn:asciiname":"Daliujia Buzi",
    "gn:country_code":"CN",
    "gn:dem":272,
    "gn:feature_class":"P",
    "gn:feature_code":"PPL",
    "gn:name":"Daliujia Buzi",
    "gn:population":0,
    "gn:timezone":"Asia/Shanghai",
    "iso:country":"CN",
    "name:und_x_variant":[
        "Daliujiabaozi",
        "Daliujia Buzi"
    ],
    "name:zho_x_preferred":[
        "\u5927\u5218\u5bb6\u5821\u5b50"
    ],
    "wof:name":"Daliujia Buzi",
    "wof:placetype":"locality"
},
  "geometry": {"coordinates":[123.76947,40.81949],"type":"Point"}
}