{
  "type": "Feature",
  "properties": {
    "gn:admin1_code":"4.0",
    "gn:asciiname":"Zhangcai",
    "gn:country_code":"CN",
    "gn:dem":6,
    "gn:feature_class":"P",
    "gn:feature_code":"PPL",
    "gn:name":"Zhangcai",
    "gn:population":0,
    "gn:timezone":"Asia/Shanghai",
    "iso:country":"CN",
    "name:zho_x_preferred":[
        "Zhangcai"
    ],
    "name:zho_x_variant":[
        "\u5f20\u8521"
    ],
    "wof:name":"Zhangcai",
    "wof:placetype":"locality"
},
  "geometry": {"coordinates":[119.20267,33.58439],"type":"Point"}
}