{
  "type": "Feature",
  "properties": {
    "gn:admin1_code":"11.0",
    "gn:asciiname":"Sizhiting",
    "gn:country_code":"CN",
    "gn:dem":87,
    "gn:feature_class":"P",
    "gn:feature_code":"PPL",
    "gn:name":"Sizhiting",
    "gn:population":0,
    "gn:timezone":"Asia/Shanghai",
    "iso:country":"CN",
    "name:zho_x_preferred":[
        "\u56db\u77e5\u4ead"
    ],
    "wof:name":"Sizhiting",
    "wof:placetype":"locality"
},
  "geometry": {"coordinates":[113.27994,29.00955],"type":"Point"}
}