{
  "type": "Feature",
  "properties": {
    "gn:admin1_code":"8.0",
    "gn:asciiname":"Dongxing Wudui",
    "gn:country_code":"CN",
    "gn:dem":228,
    "gn:feature_class":"P",
    "gn:feature_code":"PPLF",
    "gn:name":"Dongxing Wudui",
    "gn:population":0,
    "gn:timezone":"Asia/Shanghai",
    "iso:country":"CN",
    "name:zho_x_preferred":[
        "\u4e1c\u5174\u4e94\u961f"
    ],
    "wof:name":"Dongxing Wudui",
    "wof:placetype":"locality"
},
  "geometry": {"coordinates":[127.50490000000001,47.23309],"type":"Point"}
}