{
  "type": "Feature",
  "properties": {
    "gn:admin1_code":"14.0",
    "gn:asciiname":"Guowa",
    "gn:country_code":"CN",
    "gn:dem":4401,
    "gn:feature_class":"P",
    "gn:feature_code":"PPL",
    "gn:name":"Guowa",
    "gn:population":0,
    "gn:timezone":"Asia/Urumqi",
    "iso:country":"CN",
    "name:zho_x_preferred":[
        "\u679c\u74e6"
    ],
    "wof:name":"Guowa",
    "wof:placetype":"locality"
},
  "geometry": {"coordinates":[97.18917999999999,30.47136],"type":"Point"}
}