{
  "type": "Feature",
  "properties": {
    "gn:admin1_code":"32.0",
    "gn:asciiname":"Shangyankou",
    "gn:country_code":"CN",
    "gn:dem":1976,
    "gn:feature_class":"P",
    "gn:feature_code":"PPL",
    "gn:name":"Shangyankou",
    "gn:population":0,
    "gn:timezone":"Asia/Shanghai",
    "iso:country":"CN",
    "name:zho_x_preferred":[
        "\u4e0a\u5ca9\u53e3"
    ],
    "wof:name":"Shangyankou",
    "wof:placetype":"locality"
},
  "geometry": {"coordinates":[102.90300000000001,29.362],"type":"Point"}
}