{
  "type": "Feature",
  "properties": {
    "gn:admin1_code":"5.0",
    "gn:asciiname":"Siliangcun",
    "gn:country_code":"CN",
    "gn:dem":208,
    "gn:feature_class":"P",
    "gn:feature_code":"PPL",
    "gn:name":"Siliangcun",
    "gn:population":0,
    "gn:timezone":"Asia/Shanghai",
    "iso:country":"CN",
    "name:zho_x_preferred":[
        "\u56db\u6881\u6751"
    ],
    "wof:name":"Siliangcun",
    "wof:placetype":"locality"
},
  "geometry": {"coordinates":[126.755,44.50496],"type":"Point"}
}