{
  "type": "Feature",
  "properties": {
    "gn:admin1_code":"3.0",
    "gn:asciiname":"Shangcheyu",
    "gn:country_code":"CN",
    "gn:dem":87,
    "gn:feature_class":"P",
    "gn:feature_code":"PPL",
    "gn:name":"Shangcheyu",
    "gn:population":0,
    "gn:timezone":"Asia/Shanghai",
    "iso:country":"CN",
    "name:und_x_variant":[
        "\u4e0a\u8f66\u4f59"
    ],
    "wof:name":"Shangcheyu",
    "wof:placetype":"locality"
},
  "geometry": {"coordinates":[115.29351,28.63831],"type":"Point"}
}