{
  "type": "Feature",
  "properties": {
    "gn:admin1_code":"26.0",
    "gn:asciiname":"Xixiaya",
    "gn:country_code":"CN",
    "gn:dem":818,
    "gn:feature_class":"P",
    "gn:feature_code":"PPL",
    "gn:name":"Xixiaya",
    "gn:population":0,
    "gn:timezone":"Asia/Shanghai",
    "iso:country":"CN",
    "name:zho_x_preferred":[
        "\u897f\u5ce1\u5d16"
    ],
    "wof:name":"Xixiaya",
    "wof:placetype":"locality"
},
  "geometry": {"coordinates":[110.39615000000001,35.7067],"type":"Point"}
}