{
  "type": "Feature",
  "properties": {
    "gn:admin1_code":"14.0",
    "gn:asciiname":"Galongcun",
    "gn:country_code":"CN",
    "gn:dem":4384,
    "gn:feature_class":"P",
    "gn:feature_code":"PPL",
    "gn:name":"Galongcun",
    "gn:population":0,
    "gn:timezone":"Asia/Urumqi",
    "iso:country":"CN",
    "name:zho_x_preferred":[
        "\u560e\u9686\u6751"
    ],
    "wof:name":"Galongcun",
    "wof:placetype":"locality"
},
  "geometry": {"coordinates":[93.75628,32.12159],"type":"Point"}
}