{
  "type": "Feature",
  "properties": {
    "gn:admin1_code":"32.0",
    "gn:asciiname":"Lingquanmiao",
    "gn:country_code":"CN",
    "gn:dem":351,
    "gn:feature_class":"P",
    "gn:feature_code":"PPL",
    "gn:name":"Lingquanmiao",
    "gn:population":0,
    "gn:timezone":"Asia/Shanghai",
    "iso:country":"CN",
    "name:zho_x_preferred":[
        "\u7075\u6cc9\u5e99"
    ],
    "wof:name":"Lingquanmiao",
    "wof:placetype":"locality"
},
  "geometry": {"coordinates":[105.199,30.1637],"type":"Point"}
}