{
  "type": "Feature",
  "properties": {
    "gn:admin1_code":"18.0",
    "gn:asciiname":"Toubaxi",
    "gn:country_code":"CN",
    "gn:dem":430,
    "gn:feature_class":"P",
    "gn:feature_code":"PPL",
    "gn:name":"Toubaxi",
    "gn:population":0,
    "gn:timezone":"Asia/Shanghai",
    "iso:country":"CN",
    "name:zho_x_preferred":[
        "\u5934\u575d\u6eaa"
    ],
    "wof:name":"Toubaxi",
    "wof:placetype":"locality"
},
  "geometry": {"coordinates":[108.89700000000001,27.606],"type":"Point"}
}