{
  "type": "Feature",
  "properties": {
    "gn:admin1_code":"7.0",
    "gn:asciiname":"Longlingcun",
    "gn:country_code":"CN",
    "gn:dem":375,
    "gn:feature_class":"P",
    "gn:feature_code":"PPL",
    "gn:name":"Longlingcun",
    "gn:population":0,
    "gn:timezone":"Asia/Shanghai",
    "iso:country":"CN",
    "name:zho_x_preferred":[
        "\u9f99\u5cad\u6751"
    ],
    "wof:name":"Longlingcun",
    "wof:placetype":"locality"
},
  "geometry": {"coordinates":[117.46675,26.06957],"type":"Point"}
}