{
  "type": "Feature",
  "properties": {
    "gn:admin1_code":"11.0",
    "gn:asciiname":"Chagan",
    "gn:country_code":"CN",
    "gn:dem":159,
    "gn:feature_class":"P",
    "gn:feature_code":"PPL",
    "gn:name":"Chagan",
    "gn:population":0,
    "gn:timezone":"Asia/Shanghai",
    "iso:country":"CN",
    "name:ceb_x_preferred":[
        "Chagan"
    ],
    "name:fra_x_preferred":[
        "Chagan"
    ],
    "name:pol_x_preferred":[
        "Czagan"
    ],
    "name:rus_x_preferred":[
        "\u0427\u0430\u0433\u0430\u043d"
    ],
    "name:swe_x_preferred":[
        "Chagan"
    ],
    "name:ukr_x_preferred":[
        "\u0427\u0430\u0433\u0430\u043d"
    ],
    "name:zho_x_preferred":[
        "\u53c9\u5e72"
    ],
    "wof:name":"Chagan",
    "wof:placetype":"locality"
},
  "geometry": {"coordinates":[111.34327999999999,26.35176],"type":"Point"}
}