{
  "type": "Feature",
  "properties": {
    "gn:admin1_code":"10",
    "gn:asciiname":"Nanwopu",
    "gn:country_code":"CN",
    "gn:dem":1364,
    "gn:feature_class":"P",
    "gn:feature_code":"PPL",
    "gn:name":"Nanwopu",
    "gn:population":0,
    "gn:timezone":"Asia/Shanghai",
    "iso:country":"CN",
    "name:zho_x_preferred":[
        "\u5357\u7a9d\u94fa"
    ],
    "wof:name":"Nanwopu",
    "wof:placetype":"locality"
},
  "geometry": {"coordinates":[116.35033,41.73581],"type":"Point"}
}