{
  "type": "Feature",
  "properties": {
    "gn:admin1_code":"1.0",
    "gn:asciiname":"Xingwafangcun",
    "gn:country_code":"CN",
    "gn:dem":33,
    "gn:feature_class":"P",
    "gn:feature_code":"PPL",
    "gn:name":"Xingwafangcun",
    "gn:population":0,
    "gn:timezone":"Asia/Shanghai",
    "iso:country":"CN",
    "name:zho_x_preferred":[
        "\u90a2\u74e6\u623f\u6751"
    ],
    "wof:name":"Xingwafangcun",
    "wof:placetype":"locality"
},
  "geometry": {"coordinates":[115.89870999999999,32.71916],"type":"Point"}
}