{
  "type": "Feature",
  "properties": {
    "gn:admin1_code":"14.0",
    "gn:asciiname":"Yingduotong",
    "gn:country_code":"CN",
    "gn:dem":4201,
    "gn:feature_class":"P",
    "gn:feature_code":"PPL",
    "gn:name":"Yingduotong",
    "gn:population":0,
    "gn:timezone":"Asia/Urumqi",
    "iso:country":"CN",
    "name:zho_x_preferred":[
        "\u5e94\u8eb2\u6876"
    ],
    "wof:name":"Yingduotong",
    "wof:placetype":"locality"
},
  "geometry": {"coordinates":[94.45014999999999,31.71694],"type":"Point"}
}