{
  "type": "Feature",
  "properties": {
    "gn:admin1_code":"5.0",
    "gn:asciiname":"Xingnongcun",
    "gn:country_code":"CN",
    "gn:dem":563,
    "gn:feature_class":"P",
    "gn:feature_code":"PPL",
    "gn:name":"Xingnongcun",
    "gn:population":0,
    "gn:timezone":"Asia/Shanghai",
    "iso:country":"CN",
    "name:zho_x_preferred":[
        "\u5174\u519c\u6751"
    ],
    "wof:name":"Xingnongcun",
    "wof:placetype":"locality"
},
  "geometry": {"coordinates":[128.10996,43.16516],"type":"Point"}
}