{
  "type": "Feature",
  "properties": {
    "gn:admin1_code":"4.0",
    "gn:asciiname":"Hujia Shuyuan",
    "gn:country_code":"CN",
    "gn:dem":3,
    "gn:feature_class":"P",
    "gn:feature_code":"PPL",
    "gn:name":"Hujia Shuyuan",
    "gn:population":0,
    "gn:timezone":"Asia/Shanghai",
    "iso:country":"CN",
    "name:zho_x_preferred":[
        "Hujia Shuyuan"
    ],
    "name:zho_x_variant":[
        "\u80e1\u5bb6\u6811\u56ed"
    ],
    "wof:name":"Hujia Shuyuan",
    "wof:placetype":"locality"
},
  "geometry": {"coordinates":[121.14012,32.40657],"type":"Point"}
}