{
  "type": "Feature",
  "properties": {
    "gn:admin1_code":"29.0",
    "gn:asciiname":"Xiao'aotang",
    "gn:country_code":"CN",
    "gn:dem":1546,
    "gn:feature_class":"P",
    "gn:feature_code":"PPL",
    "gn:name":"Xiao\u2019aotang",
    "gn:population":0,
    "gn:timezone":"Asia/Shanghai",
    "iso:country":"CN",
    "name:und_x_variant":[
        "Xiao\u2019aotang"
    ],
    "name:zho_x_preferred":[
        "\u5c0f\u51f9\u5858"
    ],
    "wof:name":"Xiao'aotang",
    "wof:placetype":"locality"
},
  "geometry": {"coordinates":[104.373,23.4183],"type":"Point"}
}