{
  "type": "Feature",
  "properties": {
    "gn:admin1_code":"2.0",
    "gn:asciiname":"Tuofenshan",
    "gn:country_code":"CN",
    "gn:dem":288,
    "gn:feature_class":"P",
    "gn:feature_code":"PPL",
    "gn:name":"Tuofenshan",
    "gn:population":0,
    "gn:timezone":"Asia/Shanghai",
    "iso:country":"CN",
    "name:zho_x_preferred":[
        "\u9a6e\u575f\u5c71"
    ],
    "wof:name":"Tuofenshan",
    "wof:placetype":"locality"
},
  "geometry": {"coordinates":[120.35278,28.37192000000001],"type":"Point"}
}