{
  "type": "Feature",
  "properties": {
    "gn:admin1_code":"19",
    "gn:asciiname":"Saima",
    "gn:cc2":"CN",
    "gn:country_code":"CN",
    "gn:dem":393,
    "gn:feature_class":"P",
    "gn:feature_code":"PPL",
    "gn:name":"Saima",
    "gn:population":0,
    "gn:timezone":"Asia/Shanghai",
    "iso:country":"CN",
    "name:und_x_variant":[
        "Sai-ma-chi",
        "Saymatszy",
        "Saimatsi",
        "Saima"
    ],
    "wof:name":"Saima",
    "wof:placetype":"locality"
},
  "geometry": {"coordinates":[124.26027999999999,40.97333],"type":"Point"}
}