{
  "type": "Feature",
  "properties": {
    "gn:admin1_code":"30",
    "gn:asciiname":"Qixia",
    "gn:country_code":"CN",
    "gn:dem":381,
    "gn:feature_class":"P",
    "gn:feature_code":"PPL",
    "gn:name":"Qixia",
    "gn:population":0,
    "gn:timezone":"Asia/Shanghai",
    "iso:country":"CN",
    "name:ceb_x_preferred":[
        "Qixia"
    ],
    "name:deu_x_preferred":[
        "Qixia"
    ],
    "name:fra_x_preferred":[
        "Qixia"
    ],
    "name:nor_x_preferred":[
        "Qixia"
    ],
    "name:rus_x_preferred":[
        "\u0426\u0438\u0441\u044f"
    ],
    "name:zho_x_preferred":[
        "\u78dc\u4e0b"
    ],
    "wof:name":"Qixia",
    "wof:placetype":"locality"
},
  "geometry": {"coordinates":[115.77851,24.77697],"type":"Point"}
}