{
  "type": "Feature",
  "properties": {
    "gn:admin1_code":"18",
    "gn:asciiname":"Meidongpo",
    "gn:country_code":"CN",
    "gn:dem":1177,
    "gn:feature_class":"P",
    "gn:feature_code":"PPL",
    "gn:name":"Meidongpo",
    "gn:population":0,
    "gn:timezone":"Asia/Shanghai",
    "iso:country":"CN",
    "name:zho_x_preferred":[
        "\u7164\u6d1e\u5761"
    ],
    "wof:name":"Meidongpo",
    "wof:placetype":"locality"
},
  "geometry": {"coordinates":[106.02800000000001,27.6112],"type":"Point"}
}