{
  "type": "Feature",
  "properties": {
    "gn:admin1_code":"4.0",
    "gn:asciiname":"Xulao",
    "gn:country_code":"CN",
    "gn:dem":7,
    "gn:feature_class":"P",
    "gn:feature_code":"PPL",
    "gn:name":"Xulao",
    "gn:population":0,
    "gn:timezone":"Asia/Shanghai",
    "iso:country":"CN",
    "name:zho_x_preferred":[
        "Xulao"
    ],
    "name:zho_x_variant":[
        "\u5f90\u8001"
    ],
    "wof:name":"Xulao",
    "wof:placetype":"locality"
},
  "geometry": {"coordinates":[119.31346000000001,33.88559],"type":"Point"}
}