{
  "type": "Feature",
  "properties": {
    "gn:admin1_code":"16",
    "gn:asciiname":"Baishawan",
    "gn:country_code":"CN",
    "gn:dem":-9999,
    "gn:feature_class":"P",
    "gn:feature_code":"PPL",
    "gn:name":"Baishawan",
    "gn:population":0,
    "gn:timezone":"Asia/Shanghai",
    "iso:country":"CN",
    "wof:name":"Baishawan",
    "wof:placetype":"locality"
},
  "geometry": {"coordinates":[108.31806,21.62472],"type":"Point"}
}