{
  "type": "Feature",
  "properties": {
    "gn:admin1_code":"32.0",
    "gn:asciiname":"Luchechong",
    "gn:country_code":"CN",
    "gn:dem":1370,
    "gn:feature_class":"P",
    "gn:feature_code":"PPL",
    "gn:name":"Luchechong",
    "gn:population":0,
    "gn:timezone":"Asia/Shanghai",
    "iso:country":"CN",
    "name:zho_x_preferred":[
        "\u5362\u8f66\u51b2"
    ],
    "wof:name":"Luchechong",
    "wof:placetype":"locality"
},
  "geometry": {"coordinates":[101.765,26.3535],"type":"Point"}
}