{
  "type": "Feature",
  "properties": {
    "gn:admin1_code":"33.0",
    "gn:asciiname":"Liangshanyan",
    "gn:country_code":"CN",
    "gn:dem":896,
    "gn:feature_class":"P",
    "gn:feature_code":"PPL",
    "gn:name":"Liangshanyan",
    "gn:population":0,
    "gn:timezone":"Asia/Shanghai",
    "iso:country":"CN",
    "name:zho_x_preferred":[
        "\u8c05\u5c71\u5830"
    ],
    "wof:name":"Liangshanyan",
    "wof:placetype":"locality"
},
  "geometry": {"coordinates":[108.73544,28.48999],"type":"Point"}
}