{
  "type": "Feature",
  "properties": {
    "gn:admin1_code":"26.0",
    "gn:asciiname":"Qingmingshancun",
    "gn:country_code":"CN",
    "gn:dem":1176,
    "gn:feature_class":"P",
    "gn:feature_code":"PPL",
    "gn:name":"Qingmingshancun",
    "gn:population":0,
    "gn:timezone":"Asia/Shanghai",
    "iso:country":"CN",
    "name:zho_x_preferred":[
        "\u9752\u660e\u5c71\u6751"
    ],
    "wof:name":"Qingmingshancun",
    "wof:placetype":"locality"
},
  "geometry": {"coordinates":[106.50086,32.95467],"type":"Point"}
}