{
  "type": "Feature",
  "properties": {
    "gn:admin1_code":"2",
    "gn:asciiname":"Shimen Nongyinchang",
    "gn:country_code":"CN",
    "gn:dem":77,
    "gn:feature_class":"P",
    "gn:feature_code":"PPLF",
    "gn:name":"Shimen Nongyinchang",
    "gn:population":0,
    "gn:timezone":"Asia/Shanghai",
    "iso:country":"CN",
    "wof:name":"Shimen Nongyinchang",
    "wof:placetype":"locality"
},
  "geometry": {"coordinates":[119.62006,29.00769],"type":"Point"}
}