{
  "type": "Feature",
  "properties": {
    "gn:admin1_code":"32.0",
    "gn:asciiname":"Boluoguo",
    "gn:country_code":"CN",
    "gn:dem":3435,
    "gn:feature_class":"P",
    "gn:feature_code":"PPL",
    "gn:name":"Boluoguo",
    "gn:population":0,
    "gn:timezone":"Asia/Shanghai",
    "iso:country":"CN",
    "name:zho_x_preferred":[
        "\u535a\u6d1b\u9505"
    ],
    "wof:name":"Boluoguo",
    "wof:placetype":"locality"
},
  "geometry": {"coordinates":[102.039,32.2624],"type":"Point"}
}