{
  "type": "Feature",
  "properties": {
    "gn:admin1_code":"32.0",
    "gn:asciiname":"Xiheba",
    "gn:country_code":"CN",
    "gn:dem":1595,
    "gn:feature_class":"P",
    "gn:feature_code":"PPL",
    "gn:name":"Xiheba",
    "gn:population":0,
    "gn:timezone":"Asia/Shanghai",
    "iso:country":"CN",
    "name:zho_x_preferred":[
        "\u897f\u6cb3\u575d"
    ],
    "wof:name":"Xiheba",
    "wof:placetype":"locality"
},
  "geometry": {"coordinates":[102.157,28.2095],"type":"Point"}
}