{
  "type": "Feature",
  "properties": {
    "gn:admin1_code":"15.0",
    "gn:asciiname":"Liujia Shanwan",
    "gn:country_code":"CN",
    "gn:dem":1844,
    "gn:feature_class":"P",
    "gn:feature_code":"PPL",
    "gn:name":"Liujia Shanwan",
    "gn:population":0,
    "gn:timezone":"Asia/Shanghai",
    "iso:country":"CN",
    "name:zho_x_preferred":[
        "\u5218\u5bb6\u5c71\u6e7e"
    ],
    "wof:name":"Liujia Shanwan",
    "wof:placetype":"locality"
},
  "geometry": {"coordinates":[102.172,38.2334],"type":"Point"}
}