{
  "type": "Feature",
  "properties": {
    "gn:admin1_code":"11.0",
    "gn:asciiname":"Guyue",
    "gn:country_code":"CN",
    "gn:dem":27,
    "gn:feature_class":"P",
    "gn:feature_code":"PPL",
    "gn:name":"Guyue",
    "gn:population":0,
    "gn:timezone":"Asia/Shanghai",
    "iso:country":"CN",
    "name:zho_x_preferred":[
        "\u6c69\u5cb3"
    ],
    "wof:name":"Guyue",
    "wof:placetype":"locality"
},
  "geometry": {"coordinates":[112.96608999999999,29.06276],"type":"Point"}
}