{
  "type": "Feature",
  "properties": {
    "gn:admin1_code":"4.0",
    "gn:asciiname":"Tongqiqiao",
    "gn:country_code":"CN",
    "gn:dem":5,
    "gn:feature_class":"P",
    "gn:feature_code":"PPL",
    "gn:name":"Tongqiqiao",
    "gn:population":0,
    "gn:timezone":"Asia/Shanghai",
    "iso:country":"CN",
    "name:zho_x_preferred":[
        "\u901a\u542f\u6865"
    ],
    "wof:name":"Tongqiqiao",
    "wof:placetype":"locality"
},
  "geometry": {"coordinates":[121.00279,31.94039],"type":"Point"}
}