{
  "type": "Feature",
  "properties": {
    "gn:admin1_code":"30",
    "gn:asciiname":"Chezipaicun",
    "gn:country_code":"CN",
    "gn:dem":172,
    "gn:feature_class":"P",
    "gn:feature_code":"PPL",
    "gn:name":"Chezipaicun",
    "gn:population":0,
    "gn:timezone":"Asia/Shanghai",
    "iso:country":"CN",
    "name:und_x_variant":[
        "Chezipai",
        "Chezipaicun"
    ],
    "name:zho_x_preferred":[
        "\u8f66\u5b50\u6392"
    ],
    "name:zho_x_variant":[
        "\u8f66\u5b50\u6392\u6751"
    ],
    "wof:name":"Chezipaicun",
    "wof:placetype":"locality"
},
  "geometry": {"coordinates":[115.90548,24.42199],"type":"Point"}
}