{
  "type": "Feature",
  "properties": {
    "gn:admin1_code":"8.0",
    "gn:asciiname":"Hongfeng",
    "gn:country_code":"CN",
    "gn:dem":264,
    "gn:feature_class":"P",
    "gn:feature_code":"PPL",
    "gn:name":"Hongfeng",
    "gn:population":0,
    "gn:timezone":"Asia/Shanghai",
    "iso:country":"CN",
    "name:zho_x_preferred":[
        "\u7ea2\u5cf0"
    ],
    "wof:name":"Hongfeng",
    "wof:placetype":"locality"
},
  "geometry": {"coordinates":[131.29608000000002,45.54519000000001],"type":"Point"}
}