{
  "type": "Feature",
  "properties": {
    "gn:admin1_code":"3",
    "gn:asciiname":"Xisheng",
    "gn:country_code":"CN",
    "gn:dem":119,
    "gn:feature_class":"P",
    "gn:feature_code":"PPL",
    "gn:name":"Xisheng",
    "gn:population":0,
    "gn:timezone":"Asia/Shanghai",
    "iso:country":"CN",
    "name:zho_x_preferred":[
        "\u897f\u80dc"
    ],
    "wof:name":"Xisheng",
    "wof:placetype":"locality"
},
  "geometry": {"coordinates":[114.22803999999999,26.95021],"type":"Point"}
}