{
  "type": "Feature",
  "properties": {
    "gn:admin1_code":"16.0",
    "gn:asciiname":"Nawan",
    "gn:country_code":"CN",
    "gn:dem":171,
    "gn:feature_class":"P",
    "gn:feature_code":"PPL",
    "gn:name":"Nawan",
    "gn:population":0,
    "gn:timezone":"Asia/Shanghai",
    "iso:country":"CN",
    "name:fas_x_preferred":[
        "\u0646\u0648\u0627\u0646"
    ],
    "name:hin_x_preferred":[
        "\u0928\u094c\u0935\u093e\u0901"
    ],
    "name:urd_x_preferred":[
        "\u0646\u0648\u0627\u06ba"
    ],
    "name:zho_x_preferred":[
        "\u90a3\u73a9"
    ],
    "wof:name":"Nawan",
    "wof:placetype":"locality"
},
  "geometry": {"coordinates":[107.997,23.7719],"type":"Point"}
}