{
  "type": "Feature",
  "properties": {
    "gn:admin1_code":"25.0",
    "gn:asciiname":"Beitangjia",
    "gn:country_code":"CN",
    "gn:dem":11,
    "gn:feature_class":"P",
    "gn:feature_code":"PPL",
    "gn:name":"Beitangjia",
    "gn:population":0,
    "gn:timezone":"Asia/Shanghai",
    "iso:country":"CN",
    "name:zho_x_preferred":[
        "\u5317\u5510\u5bb6"
    ],
    "wof:name":"Beitangjia",
    "wof:placetype":"locality"
},
  "geometry": {"coordinates":[121.55386,36.86162],"type":"Point"}
}