{
  "type": "Feature",
  "properties": {
    "gn:admin1_code":"3.0",
    "gn:asciiname":"Meifucun",
    "gn:country_code":"CN",
    "gn:dem":226,
    "gn:feature_class":"P",
    "gn:feature_code":"PPL",
    "gn:name":"Meifucun",
    "gn:population":0,
    "gn:timezone":"Asia/Shanghai",
    "iso:country":"CN",
    "name:und_x_variant":[
        "\u6885\u798f\u6751"
    ],
    "wof:name":"Meifucun",
    "wof:placetype":"locality"
},
  "geometry": {"coordinates":[116.34265000000001,26.32953],"type":"Point"}
}