{
  "type": "Feature",
  "properties": {
    "gn:admin1_code":"24.0",
    "gn:asciiname":"Xiwutong",
    "gn:country_code":"CN",
    "gn:dem":846,
    "gn:feature_class":"P",
    "gn:feature_code":"PPL",
    "gn:name":"Xiwutong",
    "gn:population":0,
    "gn:timezone":"Asia/Shanghai",
    "iso:country":"CN",
    "name:zho_x_preferred":[
        "\u897f\u68a7\u6850"
    ],
    "wof:name":"Xiwutong",
    "wof:placetype":"locality"
},
  "geometry": {"coordinates":[111.82895000000001,36.85781],"type":"Point"}
}