{
  "type": "Feature",
  "properties": {
    "gn:admin1_code":"32.0",
    "gn:asciiname":"Qiaotian",
    "gn:country_code":"CN",
    "gn:dem":969,
    "gn:feature_class":"P",
    "gn:feature_code":"PPL",
    "gn:name":"Qiaotian",
    "gn:population":0,
    "gn:timezone":"Asia/Shanghai",
    "iso:country":"CN",
    "name:und_x_variant":[
        "\u835e\u7530"
    ],
    "wof:name":"Qiaotian",
    "wof:placetype":"locality"
},
  "geometry": {"coordinates":[106.07741,32.53888],"type":"Point"}
}