{
  "type": "Feature",
  "properties": {
    "gn:admin1_code":"32.0",
    "gn:asciiname":"Suoguo",
    "gn:country_code":"CN",
    "gn:dem":988,
    "gn:feature_class":"P",
    "gn:feature_code":"PPL",
    "gn:name":"Suoguo",
    "gn:population":0,
    "gn:timezone":"Asia/Shanghai",
    "iso:country":"CN",
    "name:zho_x_preferred":[
        "\u68ad\u9505"
    ],
    "wof:name":"Suoguo",
    "wof:placetype":"locality"
},
  "geometry": {"coordinates":[105.2782,27.82647],"type":"Point"}
}