{
  "type": "Feature",
  "properties": {
    "gn:admin1_code":"29.0",
    "gn:asciiname":"Jiceng",
    "gn:country_code":"CN",
    "gn:dem":1709,
    "gn:feature_class":"P",
    "gn:feature_code":"PPL",
    "gn:name":"Jiceng",
    "gn:population":0,
    "gn:timezone":"Asia/Shanghai",
    "iso:country":"CN",
    "name:und_x_variant":[
        "\u57fa\u564c"
    ],
    "wof:name":"Jiceng",
    "wof:placetype":"locality"
},
  "geometry": {"coordinates":[102.76418,26.11424],"type":"Point"}
}