{
  "type": "Feature",
  "properties": {
    "gn:admin1_code":"26.0",
    "gn:asciiname":"Jiepaiwancun",
    "gn:country_code":"CN",
    "gn:dem":921,
    "gn:feature_class":"P",
    "gn:feature_code":"PPL",
    "gn:name":"Jiepaiwancun",
    "gn:population":0,
    "gn:timezone":"Asia/Shanghai",
    "iso:country":"CN",
    "name:zho_x_preferred":[
        "\u4ecb\u724c\u6e7e\u6751"
    ],
    "wof:name":"Jiepaiwancun",
    "wof:placetype":"locality"
},
  "geometry": {"coordinates":[109.09935,33.70378],"type":"Point"}
}