{
  "type": "Feature",
  "properties": {
    "gn:admin1_code":"11.0",
    "gn:asciiname":"Fengxiang Xiaozhai",
    "gn:country_code":"CN",
    "gn:dem":424,
    "gn:feature_class":"P",
    "gn:feature_code":"PPL",
    "gn:name":"Fengxiang Xiaozhai",
    "gn:population":0,
    "gn:timezone":"Asia/Shanghai",
    "iso:country":"CN",
    "name:zho_x_preferred":[
        "\u67ab\u9999\u5c0f\u5be8"
    ],
    "wof:name":"Fengxiang Xiaozhai",
    "wof:placetype":"locality"
},
  "geometry": {"coordinates":[109.62469,26.167],"type":"Point"}
}