{
  "type": "Feature",
  "properties": {
    "gn:admin1_code":"12.0",
    "gn:asciiname":"Yaojialing",
    "gn:country_code":"CN",
    "gn:dem":220,
    "gn:feature_class":"P",
    "gn:feature_code":"PPL",
    "gn:name":"Yaojialing",
    "gn:population":0,
    "gn:timezone":"Asia/Shanghai",
    "iso:country":"CN",
    "name:zho_x_preferred":[
        "\u7a91\u5bb6\u5cad"
    ],
    "wof:name":"Yaojialing",
    "wof:placetype":"locality"
},
  "geometry": {"coordinates":[113.14858999999998,31.11054],"type":"Point"}
}