{
  "type": "Feature",
  "properties": {
    "gn:admin1_code":"14",
    "gn:asciiname":"Qienai",
    "gn:country_code":"CN",
    "gn:dem":4721,
    "gn:feature_class":"P",
    "gn:feature_code":"PPL",
    "gn:name":"Qienai",
    "gn:population":0,
    "gn:timezone":"Asia/Urumqi",
    "iso:country":"CN",
    "name:zho_x_preferred":[
        "\u5207\u5976"
    ],
    "wof:name":"Qienai",
    "wof:placetype":"locality"
},
  "geometry": {"coordinates":[88.9833,29.8241],"type":"Point"}
}