{
  "type": "Feature",
  "properties": {
    "gn:admin1_code":"33.0",
    "gn:asciiname":"Xinfang",
    "gn:country_code":"CN",
    "gn:dem":1166,
    "gn:feature_class":"P",
    "gn:feature_code":"PPL",
    "gn:name":"Xinfang",
    "gn:population":0,
    "gn:timezone":"Asia/Shanghai",
    "iso:country":"CN",
    "name:zho_x_preferred":[
        "\u65b0\u623f"
    ],
    "wof:name":"Xinfang",
    "wof:placetype":"locality"
},
  "geometry": {"coordinates":[108.32929,30.0234],"type":"Point"}
}