{
  "type": "Feature",
  "properties": {
    "gn:admin1_code":"5.0",
    "gn:asciiname":"Congjiadian",
    "gn:country_code":"CN",
    "gn:dem":202,
    "gn:feature_class":"P",
    "gn:feature_code":"PPL",
    "gn:name":"Congjiadian",
    "gn:population":0,
    "gn:timezone":"Asia/Shanghai",
    "iso:country":"CN",
    "name:zho_x_preferred":[
        "\u4ece\u5bb6\u5e97"
    ],
    "wof:name":"Congjiadian",
    "wof:placetype":"locality"
},
  "geometry": {"coordinates":[124.80416,43.89637000000001],"type":"Point"}
}