{
  "type": "Feature",
  "properties": {
    "gn:admin1_code":"19.0",
    "gn:asciiname":"Houha'erge",
    "gn:country_code":"CN",
    "gn:dem":106,
    "gn:feature_class":"P",
    "gn:feature_code":"PPL",
    "gn:name":"Houha\u2019erge",
    "gn:population":0,
    "gn:timezone":"Asia/Shanghai",
    "iso:country":"CN",
    "name:zho_x_preferred":[
        "Houha\u2019erge"
    ],
    "name:zho_x_variant":[
        "\u540e\u54c8\u5c14\u9601"
    ],
    "wof:name":"Houha'erge",
    "wof:placetype":"locality"
},
  "geometry": {"coordinates":[122.19,42.3973],"type":"Point"}
}