{
  "type": "Feature",
  "properties": {
    "gn:admin1_code":"4.0",
    "gn:asciiname":"Dingjiaba",
    "gn:country_code":"CN",
    "gn:dem":7,
    "gn:feature_class":"P",
    "gn:feature_code":"PPL",
    "gn:name":"Dingjiaba",
    "gn:population":0,
    "gn:timezone":"Asia/Shanghai",
    "iso:country":"CN",
    "name:zho_x_preferred":[
        "\u4e01\u5bb6\u575d"
    ],
    "wof:name":"Dingjiaba",
    "wof:placetype":"locality"
},
  "geometry": {"coordinates":[119.73023000000001,32.10605],"type":"Point"}
}