{
  "type": "Feature",
  "properties": {
    "gn:admin1_code":"8.0",
    "gn:asciiname":"Wujia Shaoguocun",
    "gn:country_code":"CN",
    "gn:dem":250,
    "gn:feature_class":"P",
    "gn:feature_code":"PPL",
    "gn:name":"Wujia Shaoguocun",
    "gn:population":0,
    "gn:timezone":"Asia/Shanghai",
    "iso:country":"CN",
    "name:zho_x_preferred":[
        "\u5434\u5bb6\u70e7\u9505\u6751"
    ],
    "wof:name":"Wujia Shaoguocun",
    "wof:placetype":"locality"
},
  "geometry": {"coordinates":[126.09658,48.58219],"type":"Point"}
}