{
  "type": "Feature",
  "properties": {
    "gn:admin1_code":"18",
    "gn:asciiname":"Jiaozikou",
    "gn:country_code":"CN",
    "gn:dem":2101,
    "gn:feature_class":"P",
    "gn:feature_code":"PPL",
    "gn:name":"Jiaozikou",
    "gn:population":0,
    "gn:timezone":"Asia/Shanghai",
    "iso:country":"CN",
    "name:zho_x_preferred":[
        "\u8f7f\u5b50\u53e3"
    ],
    "wof:name":"Jiaozikou",
    "wof:placetype":"locality"
},
  "geometry": {"coordinates":[103.989,26.8703],"type":"Point"}
}