{
  "type": "Feature",
  "properties": {
    "gn:admin1_code":"32.0",
    "gn:asciiname":"Bayincun",
    "gn:country_code":"CN",
    "gn:dem":3902,
    "gn:feature_class":"P",
    "gn:feature_code":"PPL",
    "gn:name":"Bayincun",
    "gn:population":0,
    "gn:timezone":"Asia/Shanghai",
    "iso:country":"CN",
    "name:zho_x_preferred":[
        "\u5df4\u56e0\u5bf8"
    ],
    "wof:name":"Bayincun",
    "wof:placetype":"locality"
},
  "geometry": {"coordinates":[101.184,28.2738],"type":"Point"}
}