{
  "type": "Feature",
  "properties": {
    "gn:admin1_code":"5.0",
    "gn:asciiname":"Lamenwai",
    "gn:country_code":"CN",
    "gn:dem":487,
    "gn:feature_class":"P",
    "gn:feature_code":"PPL",
    "gn:name":"Lamenwai",
    "gn:population":0,
    "gn:timezone":"Asia/Shanghai",
    "iso:country":"CN",
    "name:und_x_variant":[
        "\u782c\u95e8\u5916"
    ],
    "wof:name":"Lamenwai",
    "wof:placetype":"locality"
},
  "geometry": {"coordinates":[125.92616,41.82542],"type":"Point"}
}