{
  "type": "Feature",
  "properties": {
    "gn:admin1_code":"2",
    "gn:asciiname":"Sixiazhang",
    "gn:country_code":"CN",
    "gn:dem":28,
    "gn:feature_class":"P",
    "gn:feature_code":"PPL",
    "gn:name":"Sixiazhang",
    "gn:population":0,
    "gn:timezone":"Asia/Shanghai",
    "iso:country":"CN",
    "name:und_x_variant":[
        "\u5bfa\u4e0b\u5f20"
    ],
    "wof:name":"Sixiazhang",
    "wof:placetype":"locality"
},
  "geometry": {"coordinates":[120.18361000000002,29.5925],"type":"Point"}
}