{
  "type": "Feature",
  "properties": {
    "gn:admin1_code":"1.0",
    "gn:asciiname":"Heiliushucun",
    "gn:country_code":"CN",
    "gn:dem":38,
    "gn:feature_class":"P",
    "gn:feature_code":"PPL",
    "gn:name":"Heiliushucun",
    "gn:population":0,
    "gn:timezone":"Asia/Shanghai",
    "iso:country":"CN",
    "name:und_x_variant":[
        "Heiliushu"
    ],
    "name:zho_x_preferred":[
        "\u9ed1\u67f3\u6811\u6751"
    ],
    "wof:name":"Heiliushucun",
    "wof:placetype":"locality"
},
  "geometry": {"coordinates":[116.88333,34.25],"type":"Point"}
}