{
  "type": "Feature",
  "properties": {
    "gn:admin1_code":"29.0",
    "gn:asciiname":"Yangmeishan",
    "gn:country_code":"CN",
    "gn:dem":2605,
    "gn:feature_class":"P",
    "gn:feature_code":"PPL",
    "gn:name":"Yangmeishan",
    "gn:population":0,
    "gn:timezone":"Asia/Shanghai",
    "iso:country":"CN",
    "name:und_x_variant":[
        "\u6768\u6885\u5c71"
    ],
    "wof:name":"Yangmeishan",
    "wof:placetype":"locality"
},
  "geometry": {"coordinates":[103.28845,26.71755],"type":"Point"}
}