{
  "type": "Feature",
  "properties": {
    "gn:admin1_code":"29.0",
    "gn:asciiname":"Maomaodong",
    "gn:country_code":"CN",
    "gn:dem":2150,
    "gn:feature_class":"P",
    "gn:feature_code":"PPL",
    "gn:name":"Maomaodong",
    "gn:population":0,
    "gn:timezone":"Asia/Shanghai",
    "iso:country":"CN",
    "name:zho_x_preferred":[
        "\u732b\u732b\u6d1e"
    ],
    "wof:name":"Maomaodong",
    "wof:placetype":"locality"
},
  "geometry": {"coordinates":[103.69,25.2618],"type":"Point"}
}