{
  "type": "Feature",
  "properties": {
    "gn:admin1_code":"11.0",
    "gn:asciiname":"Changlingjiao",
    "gn:country_code":"CN",
    "gn:dem":869,
    "gn:feature_class":"P",
    "gn:feature_code":"PPL",
    "gn:name":"Changlingjiao",
    "gn:population":0,
    "gn:timezone":"Asia/Shanghai",
    "iso:country":"CN",
    "name:zho_x_preferred":[
        "\u957f\u5cad\u811a"
    ],
    "wof:name":"Changlingjiao",
    "wof:placetype":"locality"
},
  "geometry": {"coordinates":[110.00225,26.22009000000001],"type":"Point"}
}