{
  "type": "Feature",
  "properties": {
    "gn:admin1_code":"12.0",
    "gn:asciiname":"Sigou",
    "gn:country_code":"CN",
    "gn:dem":1010,
    "gn:feature_class":"P",
    "gn:feature_code":"PPL",
    "gn:name":"Sigou",
    "gn:population":0,
    "gn:timezone":"Asia/Shanghai",
    "iso:country":"CN",
    "name:zho_x_preferred":[
        "\u5bfa\u6c9f"
    ],
    "wof:name":"Sigou",
    "wof:placetype":"locality"
},
  "geometry": {"coordinates":[109.62832,33.26453],"type":"Point"}
}