{
  "type": "Feature",
  "properties": {
    "gn:admin1_code":"2.0",
    "gn:asciiname":"Yaodaba",
    "gn:country_code":"CN",
    "gn:dem":10,
    "gn:feature_class":"P",
    "gn:feature_code":"PPL",
    "gn:name":"Yaodaba",
    "gn:population":0,
    "gn:timezone":"Asia/Shanghai",
    "iso:country":"CN",
    "name:und_x_variant":[
        "\u59da\u5927\u575d"
    ],
    "wof:name":"Yaodaba",
    "wof:placetype":"locality"
},
  "geometry": {"coordinates":[120.32052,30.46986],"type":"Point"}
}