{
  "type": "Feature",
  "properties": {
    "gn:admin1_code":"33.0",
    "gn:asciiname":"Daijiawan",
    "gn:country_code":"CN",
    "gn:dem":583,
    "gn:feature_class":"P",
    "gn:feature_code":"PPL",
    "gn:name":"Daijiawan",
    "gn:population":0,
    "gn:timezone":"Asia/Shanghai",
    "iso:country":"CN",
    "name:zho_x_preferred":[
        "\u4ee3\u5bb6\u5f2f"
    ],
    "wof:name":"Daijiawan",
    "wof:placetype":"locality"
},
  "geometry": {"coordinates":[107.04000000000001,29.087],"type":"Point"}
}