{
  "type": "Feature",
  "properties": {
    "gn:admin1_code":"14.0",
    "gn:asciiname":"Dazhelega",
    "gn:country_code":"CN",
    "gn:dem":4674,
    "gn:feature_class":"P",
    "gn:feature_code":"PPL",
    "gn:name":"Dazhelega",
    "gn:population":0,
    "gn:timezone":"Asia/Urumqi",
    "iso:country":"CN",
    "name:zho_x_preferred":[
        "\u8fbe\u8005\u52d2\u560e"
    ],
    "wof:name":"Dazhelega",
    "wof:placetype":"locality"
},
  "geometry": {"coordinates":[86.5823,30.8079],"type":"Point"}
}