{
  "type": "Feature",
  "properties": {
    "gn:admin1_code":"22.0",
    "gn:asciiname":"Huayuan Beigoucun",
    "gn:country_code":"CN",
    "gn:dem":657,
    "gn:feature_class":"P",
    "gn:feature_code":"PPL",
    "gn:name":"Huayuan Beigoucun",
    "gn:population":0,
    "gn:timezone":"Asia/Shanghai",
    "iso:country":"CN",
    "name:zho_x_preferred":[
        "\u82b1\u56ed\u5317\u6c9f\u6751"
    ],
    "wof:name":"Huayuan Beigoucun",
    "wof:placetype":"locality"
},
  "geometry": {"coordinates":[117.47459000000001,40.66489],"type":"Point"}
}