{
  "type": "Feature",
  "properties": {
    "gn:admin1_code":"3.0",
    "gn:asciiname":"Chetiangao",
    "gn:country_code":"CN",
    "gn:dem":179,
    "gn:feature_class":"P",
    "gn:feature_code":"PPL",
    "gn:name":"Chetiangao",
    "gn:population":0,
    "gn:timezone":"Asia/Shanghai",
    "iso:country":"CN",
    "name:zho_x_preferred":[
        "\u8f66\u7530\u9ad8"
    ],
    "wof:name":"Chetiangao",
    "wof:placetype":"locality"
},
  "geometry": {"coordinates":[115.17400000000001,25.3989],"type":"Point"}
}