{
  "type": "Feature",
  "properties": {
    "gn:admin1_code":"13.0",
    "gn:asciiname":"Koxtag",
    "gn:cc2":"CN",
    "gn:country_code":"CN",
    "gn:dem":1813,
    "gn:feature_class":"P",
    "gn:feature_code":"PPL",
    "gn:name":"Koxtag",
    "gn:population":0,
    "gn:timezone":"Asia/Shanghai",
    "iso:country":"CN",
    "name:uig_x_preferred":[
        "K\u0329oxta\u01a3"
    ],
    "name:uig_x_variant":[
        "Qoshtagh",
        "\u0642\u0648\u0634\u062a\u0627\u063a",
        "\u049a\u043e\u0448\u0442\u0430\u0493"
    ],
    "name:und_x_variant":[
        "Ho-shih-t\u2019a-ko-pa-cha",
        "Kushtag",
        "K\u2019o-shih-t\u2019a-ko",
        "Qosh tagh",
        "Kosh Tagh",
        "Koxtag"
    ],
    "wof:name":"Koxtag",
    "wof:placetype":"locality"
},
  "geometry": {"coordinates":[78.0475,37.355],"type":"Point"}
}