{
  "type": "Feature",
  "properties": {
    "gn:admin1_code":"8.0",
    "gn:asciiname":"Xiaoxinlicun",
    "gn:country_code":"CN",
    "gn:dem":158,
    "gn:feature_class":"P",
    "gn:feature_code":"PPL",
    "gn:name":"Xiaoxinlicun",
    "gn:population":0,
    "gn:timezone":"Asia/Shanghai",
    "iso:country":"CN",
    "name:zho_x_preferred":[
        "\u5c0f\u65b0\u7acb\u6751"
    ],
    "wof:name":"Xiaoxinlicun",
    "wof:placetype":"locality"
},
  "geometry": {"coordinates":[130.07714000000001,46.06992],"type":"Point"}
}