{
  "type": "Feature",
  "properties": {
    "gn:admin1_code":"8.0",
    "gn:asciiname":"Hongtoucun",
    "gn:country_code":"CN",
    "gn:dem":156,
    "gn:feature_class":"P",
    "gn:feature_code":"PPL",
    "gn:name":"Hongtoucun",
    "gn:population":0,
    "gn:timezone":"Asia/Shanghai",
    "iso:country":"CN",
    "name:zho_x_preferred":[
        "\u7ea2\u5934\u6751"
    ],
    "wof:name":"Hongtoucun",
    "wof:placetype":"locality"
},
  "geometry": {"coordinates":[126.4729,46.68043],"type":"Point"}
}