{
  "type": "Feature",
  "properties": {
    "gn:admin1_code":"10",
    "gn:asciiname":"Beiweijiakou",
    "gn:country_code":"CN",
    "gn:dem":40,
    "gn:feature_class":"P",
    "gn:feature_code":"PPL",
    "gn:name":"Beiweijiakou",
    "gn:population":0,
    "gn:timezone":"Asia/Shanghai",
    "iso:country":"CN",
    "name:zho_x_preferred":[
        "\u5317\u4f4d\u5bb6\u53e3"
    ],
    "wof:name":"Beiweijiakou",
    "wof:placetype":"locality"
},
  "geometry": {"coordinates":[115.04900000000001,37.8232],"type":"Point"}
}