{
  "type": "Feature",
  "properties": {
    "gn:admin1_code":"26.0",
    "gn:asciiname":"Gaoqucun",
    "gn:country_code":"CN",
    "gn:dem":863,
    "gn:feature_class":"P",
    "gn:feature_code":"PPL",
    "gn:name":"Gaoqucun",
    "gn:population":0,
    "gn:timezone":"Asia/Shanghai",
    "iso:country":"CN",
    "name:zho_x_preferred":[
        "\u9ad8\u6e20\u6751"
    ],
    "wof:name":"Gaoqucun",
    "wof:placetype":"locality"
},
  "geometry": {"coordinates":[108.01542999999999,35.08562],"type":"Point"}
}