{
  "type": "Feature",
  "properties": {
    "gn:admin1_code":"33.0",
    "gn:asciiname":"Hongdong",
    "gn:country_code":"CN",
    "gn:dem":948,
    "gn:feature_class":"P",
    "gn:feature_code":"PPL",
    "gn:name":"Hongdong",
    "gn:population":0,
    "gn:timezone":"Asia/Shanghai",
    "iso:country":"CN",
    "name:zho_x_preferred":[
        "\u6d2a\u6d1e"
    ],
    "wof:name":"Hongdong",
    "wof:placetype":"locality"
},
  "geometry": {"coordinates":[106.36360999999999,28.63899],"type":"Point"}
}