{
  "type": "Feature",
  "properties": {
    "gn:admin1_code":"8.0",
    "gn:asciiname":"Baojiangcun",
    "gn:country_code":"CN",
    "gn:dem":215,
    "gn:feature_class":"P",
    "gn:feature_code":"PPL",
    "gn:name":"Baojiangcun",
    "gn:population":0,
    "gn:timezone":"Asia/Shanghai",
    "iso:country":"CN",
    "name:zho_x_preferred":[
        "\u4fdd\u6c5f\u6751"
    ],
    "wof:name":"Baojiangcun",
    "wof:placetype":"locality"
},
  "geometry": {"coordinates":[127.40505,47.19592],"type":"Point"}
}