{
  "type": "Feature",
  "properties": {
    "gn:admin1_code":"26.0",
    "gn:asciiname":"Longzuicun",
    "gn:country_code":"CN",
    "gn:dem":846,
    "gn:feature_class":"P",
    "gn:feature_code":"PPL",
    "gn:name":"Longzuicun",
    "gn:population":0,
    "gn:timezone":"Asia/Shanghai",
    "iso:country":"CN",
    "name:zho_x_preferred":[
        "\u9f99\u5634\u6751"
    ],
    "wof:name":"Longzuicun",
    "wof:placetype":"locality"
},
  "geometry": {"coordinates":[110.2936,33.56024],"type":"Point"}
}