{
  "type": "Feature",
  "properties": {
    "gn:admin1_code":"20",
    "gn:asciiname":"Tung-shui-ch'uan",
    "gn:country_code":"CN",
    "gn:dem":820,
    "gn:feature_class":"P",
    "gn:feature_code":"PPL",
    "gn:name":"Tung-shui-ch\u2019\u00fcan",
    "gn:population":0,
    "gn:timezone":"Asia/Shanghai",
    "iso:country":"CN",
    "wof:name":"Tung-shui-ch'uan",
    "wof:placetype":"locality"
},
  "geometry": {"coordinates":[118.84222,42.79806],"type":"Point"}
}