{
  "type": "Feature",
  "properties": {
    "gn:admin1_code":"25.0",
    "gn:asciiname":"Guanjiahetao",
    "gn:cc2":"CN",
    "gn:country_code":"CN",
    "gn:dem":59,
    "gn:feature_class":"P",
    "gn:feature_code":"PPL",
    "gn:name":"Guanjiahetao",
    "gn:population":0,
    "gn:timezone":"Asia/Shanghai",
    "iso:country":"CN",
    "name:zho_x_preferred":[
        "\u7ba1\u5bb6\u6cb3\u5957"
    ],
    "wof:name":"Guanjiahetao",
    "wof:placetype":"locality"
},
  "geometry": {"coordinates":[119.55768,36.08904],"type":"Point"}
}