{
  "type": "Feature",
  "properties": {
    "gn:admin1_code":"24.0",
    "gn:asciiname":"Yanggancun",
    "gn:country_code":"CN",
    "gn:dem":760,
    "gn:feature_class":"P",
    "gn:feature_code":"PPL",
    "gn:name":"Yanggancun",
    "gn:population":0,
    "gn:timezone":"Asia/Shanghai",
    "iso:country":"CN",
    "name:zho_x_preferred":[
        "\u9633\u5e72\u6751"
    ],
    "wof:name":"Yanggancun",
    "wof:placetype":"locality"
},
  "geometry": {"coordinates":[110.39037999999999,34.71771],"type":"Point"}
}