{
  "type": "Feature",
  "properties": {
    "gn:admin1_code":"8.0",
    "gn:asciiname":"Fengfucun",
    "gn:country_code":"CN",
    "gn:dem":156,
    "gn:feature_class":"P",
    "gn:feature_code":"PPL",
    "gn:name":"Fengfucun",
    "gn:population":0,
    "gn:timezone":"Asia/Shanghai",
    "iso:country":"CN",
    "name:zho_x_preferred":[
        "\u4e30\u5bcc\u6751"
    ],
    "wof:name":"Fengfucun",
    "wof:placetype":"locality"
},
  "geometry": {"coordinates":[130.31045,46.60434],"type":"Point"}
}