{
  "type": "Feature",
  "properties": {
    "gn:admin1_code":"26.0",
    "gn:asciiname":"Peijiashan",
    "gn:country_code":"CN",
    "gn:dem":1144,
    "gn:feature_class":"P",
    "gn:feature_code":"PPL",
    "gn:name":"Peijiashan",
    "gn:population":0,
    "gn:timezone":"Asia/Shanghai",
    "iso:country":"CN",
    "name:und_x_variant":[
        "\u88f4\u5bb6\u5c71"
    ],
    "wof:name":"Peijiashan",
    "wof:placetype":"locality"
},
  "geometry": {"coordinates":[105.97787,33.4054],"type":"Point"}
}