{
  "type": "Feature",
  "properties": {
    "gn:admin1_code":"29",
    "gn:asciiname":"Luoji",
    "gn:country_code":"CN",
    "gn:dem":1799,
    "gn:feature_class":"P",
    "gn:feature_code":"PPL",
    "gn:name":"Luoji",
    "gn:population":0,
    "gn:timezone":"Asia/Shanghai",
    "iso:country":"CN",
    "name:zho_x_preferred":[
        "\u87ba\u9afb"
    ],
    "wof:name":"Luoji",
    "wof:placetype":"locality"
},
  "geometry": {"coordinates":[102.666,24.1257],"type":"Point"}
}