{
  "type": "Feature",
  "properties": {
    "gn:admin1_code":"32.0",
    "gn:asciiname":"Guixiwan",
    "gn:country_code":"CN",
    "gn:dem":420,
    "gn:feature_class":"P",
    "gn:feature_code":"PPL",
    "gn:name":"Guixiwan",
    "gn:population":0,
    "gn:timezone":"Asia/Shanghai",
    "iso:country":"CN",
    "name:zho_x_preferred":[
        "\u9f9f\u4e60\u6e7e"
    ],
    "wof:name":"Guixiwan",
    "wof:placetype":"locality"
},
  "geometry": {"coordinates":[104.923,30.2034],"type":"Point"}
}