{
  "type": "Feature",
  "properties": {
    "gn:admin1_code":"24",
    "gn:asciiname":"Xiqili",
    "gn:country_code":"CN",
    "gn:dem":435,
    "gn:feature_class":"P",
    "gn:feature_code":"PPL",
    "gn:name":"Xiqili",
    "gn:population":0,
    "gn:timezone":"Asia/Shanghai",
    "iso:country":"CN",
    "name:zho_x_preferred":[
        "\u897f\u5176\u91cc"
    ],
    "wof:name":"Xiqili",
    "wof:placetype":"locality"
},
  "geometry": {"coordinates":[111.15817,35.21945],"type":"Point"}
}