{
  "type": "Feature",
  "properties": {
    "gn:admin1_code":"8.0",
    "gn:asciiname":"Qiaojiatun",
    "gn:country_code":"CN",
    "gn:dem":204,
    "gn:feature_class":"P",
    "gn:feature_code":"PPL",
    "gn:name":"Qiaojiatun",
    "gn:population":0,
    "gn:timezone":"Asia/Shanghai",
    "iso:country":"CN",
    "name:zho_x_preferred":[
        "\u4e54\u5bb6\u5c6f"
    ],
    "wof:name":"Qiaojiatun",
    "wof:placetype":"locality"
},
  "geometry": {"coordinates":[125.41092999999999,47.46679],"type":"Point"}
}