{
  "type": "Feature",
  "properties": {
    "gn:admin1_code":"32.0",
    "gn:asciiname":"Lingyun",
    "gn:country_code":"CN",
    "gn:dem":741,
    "gn:feature_class":"P",
    "gn:feature_code":"PPL",
    "gn:name":"Lingyun",
    "gn:population":0,
    "gn:timezone":"Asia/Shanghai",
    "iso:country":"CN",
    "name:zho_x_preferred":[
        "\u51cc\u4e91"
    ],
    "wof:name":"Lingyun",
    "wof:placetype":"locality"
},
  "geometry": {"coordinates":[106.83768000000001,31.91662],"type":"Point"}
}