{
  "type": "Feature",
  "properties": {
    "gn:admin1_code":"32.0",
    "gn:asciiname":"Sawajiao",
    "gn:country_code":"CN",
    "gn:dem":3022,
    "gn:feature_class":"P",
    "gn:feature_code":"PPL",
    "gn:name":"Sawajiao",
    "gn:population":0,
    "gn:timezone":"Asia/Shanghai",
    "iso:country":"CN",
    "name:zho_x_preferred":[
        "\u6492\u74e6\u811a"
    ],
    "wof:name":"Sawajiao",
    "wof:placetype":"locality"
},
  "geometry": {"coordinates":[101.90107,31.55924000000001],"type":"Point"}
}