{
  "type": "Feature",
  "properties": {
    "gn:admin1_code":"4.0",
    "gn:asciiname":"Xiantian",
    "gn:country_code":"CN",
    "gn:dem":15,
    "gn:feature_class":"P",
    "gn:feature_code":"PPL",
    "gn:name":"Xiantian",
    "gn:population":0,
    "gn:timezone":"Asia/Shanghai",
    "iso:country":"CN",
    "name:und_x_variant":[
        "Su-ts\u2019un",
        "Hsien-t\u2019ien",
        "Hsien-t\u2019ien-ts\u2019un",
        "Xiantiancun",
        "Xiantian",
        "\u54b8\u7530"
    ],
    "wof:name":"Xiantian",
    "wof:placetype":"locality"
},
  "geometry": {"coordinates":[118.94025000000001,31.90314],"type":"Point"}
}