{
  "type": "Feature",
  "properties": {
    "gn:admin1_code":"16.0",
    "gn:asciiname":"Pingdishan",
    "gn:country_code":"CN",
    "gn:dem":117,
    "gn:feature_class":"P",
    "gn:feature_code":"PPL",
    "gn:name":"Pingdishan",
    "gn:population":0,
    "gn:timezone":"Asia/Shanghai",
    "iso:country":"CN",
    "name:zho_x_preferred":[
        "\u5e73\u5730\u5c71"
    ],
    "wof:name":"Pingdishan",
    "wof:placetype":"locality"
},
  "geometry": {"coordinates":[110.277,22.7786],"type":"Point"}
}