{
  "type": "Feature",
  "properties": {
    "gn:admin1_code":"19.0",
    "gn:asciiname":"Qiaojiagou",
    "gn:country_code":"CN",
    "gn:dem":100,
    "gn:feature_class":"P",
    "gn:feature_code":"PPL",
    "gn:name":"Qiaojiagou",
    "gn:population":0,
    "gn:timezone":"Asia/Shanghai",
    "iso:country":"CN",
    "name:und_x_variant":[
        "\u4e54\u5bb6\u6c9f"
    ],
    "wof:name":"Qiaojiagou",
    "wof:placetype":"locality"
},
  "geometry": {"coordinates":[122.76852,40.74307],"type":"Point"}
}