{
  "type": "Feature",
  "properties": {
    "gn:admin1_code":"1.0",
    "gn:asciiname":"Weiqiaocun",
    "gn:country_code":"CN",
    "gn:dem":26,
    "gn:feature_class":"P",
    "gn:feature_code":"PPL",
    "gn:name":"Weiqiaocun",
    "gn:population":0,
    "gn:timezone":"Asia/Shanghai",
    "iso:country":"CN",
    "name:zho_x_preferred":[
        "\u6e2d\u6865\u6751"
    ],
    "wof:name":"Weiqiaocun",
    "wof:placetype":"locality"
},
  "geometry": {"coordinates":[117.69562999999999,33.72338],"type":"Point"}
}