{
  "type": "Feature",
  "properties": {
    "gn:admin1_code":"8.0",
    "gn:asciiname":"Dongxingheng",
    "gn:country_code":"CN",
    "gn:dem":184,
    "gn:feature_class":"P",
    "gn:feature_code":"PPL",
    "gn:name":"Dongxingheng",
    "gn:population":0,
    "gn:timezone":"Asia/Shanghai",
    "iso:country":"CN",
    "name:zho_x_preferred":[
        "\u4e1c\u5174\u6052"
    ],
    "wof:name":"Dongxingheng",
    "wof:placetype":"locality"
},
  "geometry": {"coordinates":[127.12416,44.81608],"type":"Point"}
}