{
  "type": "Feature",
  "properties": {
    "gn:admin1_code":"2",
    "gn:asciiname":"Miaoxia",
    "gn:country_code":"CN",
    "gn:dem":172,
    "gn:feature_class":"P",
    "gn:feature_code":"PPL",
    "gn:name":"Miaoxia",
    "gn:population":0,
    "gn:timezone":"Asia/Shanghai",
    "iso:country":"CN",
    "name:zho_x_preferred":[
        "\u5e99\u4e0b"
    ],
    "wof:name":"Miaoxia",
    "wof:placetype":"locality"
},
  "geometry": {"coordinates":[119.15033,28.83729000000001],"type":"Point"}
}