{
  "type": "Feature",
  "properties": {
    "gn:admin1_code":"31",
    "gn:asciiname":"Shuidong",
    "gn:country_code":"CN",
    "gn:dem":21,
    "gn:feature_class":"P",
    "gn:feature_code":"PPL",
    "gn:name":"Shuidong",
    "gn:population":0,
    "gn:timezone":"Asia/Shanghai",
    "iso:country":"CN",
    "name:und_x_variant":[
        "\u6c34\u4e1c",
        "Shuiliudong",
        "Shuiliu",
        "\u6c34\u6d41\u4e1c"
    ],
    "name:zho_x_preferred":[
        "\u6c34\u6d41"
    ],
    "wof:name":"Shuidong",
    "wof:placetype":"locality"
},
  "geometry": {"coordinates":[108.73099999999999,19.2069],"type":"Point"}
}