{
  "type": "Feature",
  "properties": {
    "gn:admin1_code":"29.0",
    "gn:asciiname":"Yongfengjing",
    "gn:country_code":"CN",
    "gn:dem":1643,
    "gn:feature_class":"P",
    "gn:feature_code":"PPL",
    "gn:name":"Yongfengjing",
    "gn:population":0,
    "gn:timezone":"Asia/Shanghai",
    "iso:country":"CN",
    "name:zho_x_preferred":[
        "\u6c38\u4e30\u4e95"
    ],
    "wof:name":"Yongfengjing",
    "wof:placetype":"locality"
},
  "geometry": {"coordinates":[101.119,25.8745],"type":"Point"}
}