{
  "type": "Feature",
  "properties": {
    "gn:admin1_code":"2.0",
    "gn:asciiname":"Hezhai",
    "gn:country_code":"CN",
    "gn:dem":57,
    "gn:feature_class":"P",
    "gn:feature_code":"PPL",
    "gn:name":"Hezhai",
    "gn:population":0,
    "gn:timezone":"Asia/Shanghai",
    "iso:country":"CN",
    "name:und_x_variant":[
        "\u8d3a\u5b85",
        "Hezhai"
    ],
    "wof:name":"Hezhai",
    "wof:placetype":"locality"
},
  "geometry": {"coordinates":[119.48975,29.37048],"type":"Point"}
}