{
  "type": "Feature",
  "properties": {
    "gn:admin1_code":"1.0",
    "gn:asciiname":"Yangchongcun",
    "gn:country_code":"CN",
    "gn:dem":61,
    "gn:feature_class":"P",
    "gn:feature_code":"PPL",
    "gn:name":"Yangchongcun",
    "gn:population":0,
    "gn:timezone":"Asia/Shanghai",
    "iso:country":"CN",
    "name:zho_x_preferred":[
        "\u6768\u51b2\u6751"
    ],
    "wof:name":"Yangchongcun",
    "wof:placetype":"locality"
},
  "geometry": {"coordinates":[116.68028,30.84809000000001],"type":"Point"}
}