{
  "type": "Feature",
  "properties": {
    "gn:admin1_code":"29.0",
    "gn:asciiname":"Xinyi",
    "gn:country_code":"CN",
    "gn:dem":2517,
    "gn:feature_class":"P",
    "gn:feature_code":"PPL",
    "gn:name":"Xinyi",
    "gn:population":0,
    "gn:timezone":"Asia/Shanghai",
    "iso:country":"CN",
    "name:zho_x_preferred":[
        "\u65b0\u9091"
    ],
    "wof:name":"Xinyi",
    "wof:placetype":"locality"
},
  "geometry": {"coordinates":[99.9975,25.9756],"type":"Point"}
}