{
  "type": "Feature",
  "properties": {
    "gn:admin1_code":"19.0",
    "gn:asciiname":"Houkuangzishan",
    "gn:country_code":"CN",
    "gn:dem":12,
    "gn:feature_class":"P",
    "gn:feature_code":"PPL",
    "gn:name":"Houkuangzishan",
    "gn:population":0,
    "gn:timezone":"Asia/Shanghai",
    "iso:country":"CN",
    "name:zho_x_preferred":[
        "\u540e\u77ff\u5b50\u5c71"
    ],
    "wof:name":"Houkuangzishan",
    "wof:placetype":"locality"
},
  "geometry": {"coordinates":[121.40731,39.58716],"type":"Point"}
}