{
  "type": "Feature",
  "properties": {
    "gn:admin1_code":"29.0",
    "gn:asciiname":"Fabao",
    "gn:country_code":"CN",
    "gn:dem":1997,
    "gn:feature_class":"P",
    "gn:feature_code":"PPL",
    "gn:name":"Fabao",
    "gn:population":0,
    "gn:timezone":"Asia/Shanghai",
    "iso:country":"CN",
    "name:zho_x_preferred":[
        "\u6cd5\u5b9d"
    ],
    "wof:name":"Fabao",
    "wof:placetype":"locality"
},
  "geometry": {"coordinates":[102.273,26.0696],"type":"Point"}
}