{
  "type": "Feature",
  "properties": {
    "gn:admin1_code":"30.0",
    "gn:asciiname":"Longtan",
    "gn:country_code":"CN",
    "gn:dem":96,
    "gn:feature_class":"P",
    "gn:feature_code":"PPLA4",
    "gn:name":"Longtan",
    "gn:population":0,
    "gn:timezone":"Asia/Shanghai",
    "iso:country":"CN",
    "name:und_x_variant":[
        "Tso-t\u2019an",
        "Zuotan",
        "Longtan",
        "Longtan Zhen",
        "\u9f99\u6f6d\u9547"
    ],
    "name:zho_x_preferred":[
        "\u9f99\u6f6d"
    ],
    "wof:name":"Longtan",
    "wof:placetype":"locality"
},
  "geometry": {"coordinates":[114.10647,23.7133],"type":"Point"}
}