{
  "type": "Feature",
  "properties": {
    "gn:admin1_code":"29.0",
    "gn:asciiname":"Bangma",
    "gn:country_code":"CN",
    "gn:dem":1676,
    "gn:feature_class":"P",
    "gn:feature_code":"PPL",
    "gn:name":"Bangma",
    "gn:population":0,
    "gn:timezone":"Asia/Shanghai",
    "iso:country":"CN",
    "name:zho_x_preferred":[
        "\u90a6\u9a82"
    ],
    "wof:name":"Bangma",
    "wof:placetype":"locality"
},
  "geometry": {"coordinates":[99.83710000000001,23.6515],"type":"Point"}
}