{
  "type": "Feature",
  "properties": {
    "gn:admin1_code":"19.0",
    "gn:asciiname":"Dapocun",
    "gn:country_code":"CN",
    "gn:dem":435,
    "gn:feature_class":"P",
    "gn:feature_code":"PPL",
    "gn:name":"Dapocun",
    "gn:population":0,
    "gn:timezone":"Asia/Shanghai",
    "iso:country":"CN",
    "name:zho_x_preferred":[
        "\u5927\u5761\u6751"
    ],
    "wof:name":"Dapocun",
    "wof:placetype":"locality"
},
  "geometry": {"coordinates":[125.236,42.0681],"type":"Point"}
}