{
  "type": "Feature",
  "properties": {
    "gn:admin1_code":"33.0",
    "gn:asciiname":"Tiandi",
    "gn:country_code":"CN",
    "gn:dem":587,
    "gn:feature_class":"P",
    "gn:feature_code":"PPL",
    "gn:name":"Tiandi",
    "gn:population":0,
    "gn:timezone":"Asia/Shanghai",
    "iso:country":"CN",
    "name:zho_x_preferred":[
        "\u5929\u5730"
    ],
    "wof:name":"Tiandi",
    "wof:placetype":"locality"
},
  "geometry": {"coordinates":[108.23415,30.8362],"type":"Point"}
}