{
  "type": "Feature",
  "properties": {
    "gn:admin1_code":"30",
    "gn:asciiname":"Shilongqiu",
    "gn:country_code":"CN",
    "gn:dem":114,
    "gn:feature_class":"P",
    "gn:feature_code":"PPL",
    "gn:name":"Shilongqiu",
    "gn:population":0,
    "gn:timezone":"Asia/Shanghai",
    "iso:country":"CN",
    "name:zho_x_preferred":[
        "\u77f3\u9f99\u79cb"
    ],
    "wof:name":"Shilongqiu",
    "wof:placetype":"locality"
},
  "geometry": {"coordinates":[116.32115,23.64931],"type":"Point"}
}