{
  "type": "Feature",
  "properties": {
    "gn:admin1_code":"32.0",
    "gn:asciiname":"Eqing",
    "gn:country_code":"CN",
    "gn:dem":4212,
    "gn:feature_class":"P",
    "gn:feature_code":"PPL",
    "gn:name":"Eqing",
    "gn:population":0,
    "gn:timezone":"Asia/Shanghai",
    "iso:country":"CN",
    "name:zho_x_preferred":[
        "\u4fc4\u9752"
    ],
    "wof:name":"Eqing",
    "wof:placetype":"locality"
},
  "geometry": {"coordinates":[97.9058,33.3793],"type":"Point"}
}