{
  "type": "Feature",
  "properties": {
    "gn:admin1_code":"15",
    "gn:asciiname":"Jikog Yangchang",
    "gn:country_code":"CN",
    "gn:dem":3705,
    "gn:feature_class":"P",
    "gn:feature_code":"PPL",
    "gn:name":"Jikog Yangchang",
    "gn:population":0,
    "gn:timezone":"Asia/Shanghai",
    "iso:country":"CN",
    "wof:name":"Jikog Yangchang",
    "wof:placetype":"locality"
},
  "geometry": {"coordinates":[101.06667,34.23333],"type":"Point"}
}