{
  "type": "Feature",
  "properties": {
    "gn:admin1_code":"32.0",
    "gn:asciiname":"Qianfo",
    "gn:country_code":"CN",
    "gn:dem":608,
    "gn:feature_class":"P",
    "gn:feature_code":"PPL",
    "gn:name":"Qianfo",
    "gn:population":0,
    "gn:timezone":"Asia/Shanghai",
    "iso:country":"CN",
    "name:zho_x_preferred":[
        "\u5343\u4f5b"
    ],
    "wof:name":"Qianfo",
    "wof:placetype":"locality"
},
  "geometry": {"coordinates":[107.25700000000001,31.4611],"type":"Point"}
}