{
  "type": "Feature",
  "properties": {
    "gn:admin1_code":"26.0",
    "gn:asciiname":"Changdianzicun",
    "gn:country_code":"CN",
    "gn:dem":1144,
    "gn:feature_class":"P",
    "gn:feature_code":"PPL",
    "gn:name":"Changdianzicun",
    "gn:population":0,
    "gn:timezone":"Asia/Shanghai",
    "iso:country":"CN",
    "name:zho_x_preferred":[
        "\u957f\u5e97\u5b50\u6751"
    ],
    "wof:name":"Changdianzicun",
    "wof:placetype":"locality"
},
  "geometry": {"coordinates":[107.95202999999999,32.44207],"type":"Point"}
}