{
  "type": "Feature",
  "properties": {
    "gn:admin1_code":"3.0",
    "gn:asciiname":"Shangxiyuan",
    "gn:country_code":"CN",
    "gn:dem":187,
    "gn:feature_class":"P",
    "gn:feature_code":"PPL",
    "gn:name":"Shangxiyuan",
    "gn:population":0,
    "gn:timezone":"Asia/Shanghai",
    "iso:country":"CN",
    "name:und_x_variant":[
        "\u4e0a\u897f\u6e90"
    ],
    "wof:name":"Shangxiyuan",
    "wof:placetype":"locality"
},
  "geometry": {"coordinates":[116.56717999999999,26.99316],"type":"Point"}
}