{
  "type": "Feature",
  "properties": {
    "gn:admin1_code":"20.0",
    "gn:asciiname":"Cuogang",
    "gn:country_code":"CN",
    "gn:dem":554,
    "gn:feature_class":"P",
    "gn:feature_code":"PPLA4",
    "gn:name":"Cuogang",
    "gn:population":0,
    "gn:timezone":"Asia/Shanghai",
    "iso:country":"CN",
    "name:und_x_variant":[
        "Cuogang Zhen"
    ],
    "name:zho_x_preferred":[
        "\u5d6f\u5c97"
    ],
    "name:zho_x_variant":[
        "\u5d6f\u5c97\u9547"
    ],
    "wof:name":"Cuogang",
    "wof:placetype":"locality"
},
  "geometry": {"coordinates":[118.10174000000001,49.25785],"type":"Point"}
}