{
  "type": "Feature",
  "properties": {
    "gn:admin1_code":"29.0",
    "gn:asciiname":"Dimidi",
    "gn:country_code":"CN",
    "gn:dem":1910,
    "gn:feature_class":"P",
    "gn:feature_code":"PPL",
    "gn:name":"Dimidi",
    "gn:population":0,
    "gn:timezone":"Asia/Shanghai",
    "iso:country":"CN",
    "name:zho_x_preferred":[
        "\u5e95\u54aa\u5e95"
    ],
    "wof:name":"Dimidi",
    "wof:placetype":"locality"
},
  "geometry": {"coordinates":[103.852,23.2714],"type":"Point"}
}