{
  "type": "Feature",
  "properties": {
    "gn:admin1_code":"07",
    "gn:asciiname":"Shuitou",
    "gn:country_code":"CN",
    "gn:dem":686,
    "gn:feature_class":"P",
    "gn:feature_code":"PPL",
    "gn:name":"Shuitou",
    "gn:population":0,
    "gn:timezone":"Asia/Shanghai",
    "iso:country":"CN",
    "name:zho_x_preferred":[
        "\u6c34\u5934"
    ],
    "wof:name":"Shuitou",
    "wof:placetype":"locality"
},
  "geometry": {"coordinates":[118.44953999999998,25.51619],"type":"Point"}
}