{
  "type": "Feature",
  "properties": {
    "gn:admin1_code":"15.0",
    "gn:asciiname":"Liujia Xiatou",
    "gn:country_code":"CN",
    "gn:dem":2453,
    "gn:feature_class":"P",
    "gn:feature_code":"PPL",
    "gn:name":"Liujia Xiatou",
    "gn:population":0,
    "gn:timezone":"Asia/Shanghai",
    "iso:country":"CN",
    "name:zho_x_preferred":[
        "\u5218\u5bb6\u4e0b\u5934"
    ],
    "wof:name":"Liujia Xiatou",
    "wof:placetype":"locality"
},
  "geometry": {"coordinates":[103.953,35.6347],"type":"Point"}
}