{
  "type": "Feature",
  "properties": {
    "gn:admin1_code":"32.0",
    "gn:asciiname":"Zhada",
    "gn:country_code":"CN",
    "gn:dem":3351,
    "gn:feature_class":"P",
    "gn:feature_code":"PPL",
    "gn:name":"Zhada",
    "gn:population":0,
    "gn:timezone":"Asia/Shanghai",
    "iso:country":"CN",
    "name:zho_x_preferred":[
        "\u624e\u8fbe"
    ],
    "wof:name":"Zhada",
    "wof:placetype":"locality"
},
  "geometry": {"coordinates":[99.36906999999999,31.49018],"type":"Point"}
}