{
  "type": "Feature",
  "properties": {
    "gn:admin1_code":"15.0",
    "gn:asciiname":"Woniushan",
    "gn:country_code":"CN",
    "gn:dem":2756,
    "gn:feature_class":"P",
    "gn:feature_code":"PPL",
    "gn:name":"Woniushan",
    "gn:population":0,
    "gn:timezone":"Asia/Shanghai",
    "iso:country":"CN",
    "name:zho_x_preferred":[
        "\u5367\u725b\u5c71"
    ],
    "wof:name":"Woniushan",
    "wof:placetype":"locality"
},
  "geometry": {"coordinates":[103.52500000000001,37.1302],"type":"Point"}
}