{
  "type": "Feature",
  "properties": {
    "gn:admin1_code":"9",
    "gn:asciiname":"Zhengshuangmiao",
    "gn:country_code":"CN",
    "gn:dem":40,
    "gn:feature_class":"P",
    "gn:feature_code":"PPL",
    "gn:name":"Zhengshuangmiao",
    "gn:population":0,
    "gn:timezone":"Asia/Shanghai",
    "iso:country":"CN",
    "name:zho_x_preferred":[
        "\u90d1\u53cc\u5e99"
    ],
    "wof:name":"Zhengshuangmiao",
    "wof:placetype":"locality"
},
  "geometry": {"coordinates":[116.131,34.0351],"type":"Point"}
}