{
  "type": "Feature",
  "properties": {
    "gn:admin1_code":"30.0",
    "gn:asciiname":"Jinyouxu",
    "gn:country_code":"CN",
    "gn:dem":39,
    "gn:feature_class":"P",
    "gn:feature_code":"PPL",
    "gn:name":"Jinyouxu",
    "gn:population":0,
    "gn:timezone":"Asia/Shanghai",
    "iso:country":"CN",
    "name:zho_x_preferred":[
        "\u91d1\u6709\u5729"
    ],
    "wof:name":"Jinyouxu",
    "wof:placetype":"locality"
},
  "geometry": {"coordinates":[112.55633,23.24841],"type":"Point"}
}