{
  "type": "Feature",
  "properties": {
    "gn:admin1_code":"16",
    "gn:asciiname":"Songshu'ao",
    "gn:country_code":"CN",
    "gn:dem":565,
    "gn:feature_class":"P",
    "gn:feature_code":"PPL",
    "gn:name":"Songshu\u2019ao",
    "gn:population":0,
    "gn:timezone":"Asia/Shanghai",
    "iso:country":"CN",
    "name:und_x_variant":[
        "Songshu\u2019ao"
    ],
    "name:zho_x_preferred":[
        "\u677e\u6811\u5773"
    ],
    "wof:name":"Songshu'ao",
    "wof:placetype":"locality"
},
  "geometry": {"coordinates":[109.94199999999999,26.0576],"type":"Point"}
}