{
  "type": "Feature",
  "properties": {
    "gn:admin1_code":"11",
    "gn:asciiname":"Lefutang",
    "gn:country_code":"CN",
    "gn:dem":380,
    "gn:feature_class":"P",
    "gn:feature_code":"PPLA4",
    "gn:name":"Lefutang",
    "gn:population":0,
    "gn:timezone":"Asia/Shanghai",
    "iso:country":"CN",
    "name:und_x_variant":[
        "Lefutang Xiang",
        "\u4e50\u798f\u5802\u4e61",
        "Lefutang"
    ],
    "name:zho_x_preferred":[
        "\u4e50\u798f\u5802"
    ],
    "wof:name":"Lefutang",
    "wof:placetype":"locality"
},
  "geometry": {"coordinates":[111.50333000000001,25.64833],"type":"Point"}
}