{
  "type": "Feature",
  "properties": {
    "gn:admin1_code":"18",
    "gn:asciiname":"Hedixia",
    "gn:country_code":"CN",
    "gn:dem":1359,
    "gn:feature_class":"P",
    "gn:feature_code":"PPL",
    "gn:name":"Hedixia",
    "gn:population":0,
    "gn:timezone":"Asia/Shanghai",
    "iso:country":"CN",
    "name:zho_x_preferred":[
        "\u6cb3\u5e95\u4e0b"
    ],
    "wof:name":"Hedixia",
    "wof:placetype":"locality"
},
  "geometry": {"coordinates":[105.301,25.5625],"type":"Point"}
}