{
  "type": "Feature",
  "properties": {
    "gn:admin1_code":"14.0",
    "gn:asciiname":"Yegekangma",
    "gn:country_code":"CN",
    "gn:dem":2993,
    "gn:feature_class":"P",
    "gn:feature_code":"PPL",
    "gn:name":"Yegekangma",
    "gn:population":0,
    "gn:timezone":"Asia/Urumqi",
    "iso:country":"CN",
    "name:zho_x_preferred":[
        "\u53f6\u6208\u625b\u9a6c"
    ],
    "wof:name":"Yegekangma",
    "wof:placetype":"locality"
},
  "geometry": {"coordinates":[94.83547,29.51712],"type":"Point"}
}