{
  "type": "Feature",
  "properties": {
    "gn:admin1_code":"32.0",
    "gn:asciiname":"Haiyanghui",
    "gn:country_code":"CN",
    "gn:dem":1668,
    "gn:feature_class":"P",
    "gn:feature_code":"PPL",
    "gn:name":"Haiyanghui",
    "gn:population":0,
    "gn:timezone":"Asia/Shanghai",
    "iso:country":"CN",
    "name:zho_x_preferred":[
        "\u6d77\u6d0b\u4f1a"
    ],
    "wof:name":"Haiyanghui",
    "wof:placetype":"locality"
},
  "geometry": {"coordinates":[102.315,29.1833],"type":"Point"}
}