{
  "type": "Feature",
  "properties": {
    "gn:admin1_code":"15.0",
    "gn:asciiname":"Shuangming",
    "gn:country_code":"CN",
    "gn:dem":1716,
    "gn:feature_class":"P",
    "gn:feature_code":"PPL",
    "gn:name":"Shuangming",
    "gn:population":0,
    "gn:timezone":"Asia/Shanghai",
    "iso:country":"CN",
    "name:zho_x_preferred":[
        "\u53cc\u660e"
    ],
    "wof:name":"Shuangming",
    "wof:placetype":"locality"
},
  "geometry": {"coordinates":[106.51900000000001,35.22],"type":"Point"}
}