{
  "type": "Feature",
  "properties": {
    "gn:admin1_code":"8.0",
    "gn:asciiname":"Fashengcun",
    "gn:country_code":"CN",
    "gn:dem":193,
    "gn:feature_class":"P",
    "gn:feature_code":"PPL",
    "gn:name":"Fashengcun",
    "gn:population":0,
    "gn:timezone":"Asia/Shanghai",
    "iso:country":"CN",
    "name:zho_x_preferred":[
        "\u53d1\u80dc\u6751"
    ],
    "wof:name":"Fashengcun",
    "wof:placetype":"locality"
},
  "geometry": {"coordinates":[127.56364000000001,47.08036],"type":"Point"}
}