{
  "type": "Feature",
  "properties": {
    "gn:admin1_code":"29.0",
    "gn:asciiname":"Xiaolaoluzhai",
    "gn:country_code":"CN",
    "gn:dem":1029,
    "gn:feature_class":"P",
    "gn:feature_code":"PPL",
    "gn:name":"Xiaolaoluzhai",
    "gn:population":0,
    "gn:timezone":"Asia/Shanghai",
    "iso:country":"CN",
    "name:zho_x_preferred":[
        "\u5c0f\u8001\u9c81\u5be8"
    ],
    "wof:name":"Xiaolaoluzhai",
    "wof:placetype":"locality"
},
  "geometry": {"coordinates":[100.637,23.216],"type":"Point"}
}