{
  "type": "Feature",
  "properties": {
    "gn:admin1_code":"15.0",
    "gn:asciiname":"Zhaojiazui",
    "gn:country_code":"CN",
    "gn:dem":1534,
    "gn:feature_class":"P",
    "gn:feature_code":"PPL",
    "gn:name":"Zhaojiazui",
    "gn:population":0,
    "gn:timezone":"Asia/Shanghai",
    "iso:country":"CN",
    "name:zho_x_preferred":[
        "\u8d75\u5bb6\u5480"
    ],
    "wof:name":"Zhaojiazui",
    "wof:placetype":"locality"
},
  "geometry": {"coordinates":[104.81573,32.93177],"type":"Point"}
}