{
  "type": "Feature",
  "properties": {
    "gn:admin1_code":"8.0",
    "gn:asciiname":"Beilongcun",
    "gn:country_code":"CN",
    "gn:dem":160,
    "gn:feature_class":"P",
    "gn:feature_code":"PPL",
    "gn:name":"Beilongcun",
    "gn:population":0,
    "gn:timezone":"Asia/Shanghai",
    "iso:country":"CN",
    "name:zho_x_preferred":[
        "\u5317\u9f99\u6751"
    ],
    "wof:name":"Beilongcun",
    "wof:placetype":"locality"
},
  "geometry": {"coordinates":[132.04244,46.15705],"type":"Point"}
}