{
  "type": "Feature",
  "properties": {
    "gn:admin1_code":"14.0",
    "gn:asciiname":"Zhatongka",
    "gn:country_code":"CN",
    "gn:dem":4478,
    "gn:feature_class":"P",
    "gn:feature_code":"PPL",
    "gn:name":"Zhatongka",
    "gn:population":0,
    "gn:timezone":"Asia/Urumqi",
    "iso:country":"CN",
    "name:zho_x_preferred":[
        "\u624e\u901a\u5361"
    ],
    "wof:name":"Zhatongka",
    "wof:placetype":"locality"
},
  "geometry": {"coordinates":[95.34613,31.46338],"type":"Point"}
}