{
  "type": "Feature",
  "properties": {
    "gn:admin1_code":"15.0",
    "gn:asciiname":"Haoshuijing",
    "gn:country_code":"CN",
    "gn:dem":1473,
    "gn:feature_class":"P",
    "gn:feature_code":"PPL",
    "gn:name":"Haoshuijing",
    "gn:population":0,
    "gn:timezone":"Asia/Shanghai",
    "iso:country":"CN",
    "name:zho_x_preferred":[
        "\u6d69\u6c34\u4e95"
    ],
    "wof:name":"Haoshuijing",
    "wof:placetype":"locality"
},
  "geometry": {"coordinates":[103.16500000000001,38.2221],"type":"Point"}
}