{
  "type": "Feature",
  "properties": {
    "gn:admin1_code":"2.0",
    "gn:asciiname":"Jijiabu",
    "gn:country_code":"CN",
    "gn:dem":142,
    "gn:feature_class":"P",
    "gn:feature_code":"PPL",
    "gn:name":"Jijiabu",
    "gn:population":0,
    "gn:timezone":"Asia/Shanghai",
    "iso:country":"CN",
    "name:zho_x_preferred":[
        "\u5b63\u5bb6\u57e0"
    ],
    "wof:name":"Jijiabu",
    "wof:placetype":"locality"
},
  "geometry": {"coordinates":[119.93592,27.60588],"type":"Point"}
}