{
  "type": "Feature",
  "properties": {
    "gn:admin1_code":"19.0",
    "gn:asciiname":"Lujiatun",
    "gn:country_code":"CN",
    "gn:dem":158,
    "gn:feature_class":"P",
    "gn:feature_code":"PPL",
    "gn:name":"L\u00fcjiatun",
    "gn:population":0,
    "gn:timezone":"Asia/Shanghai",
    "iso:country":"CN",
    "name:zho_x_preferred":[
        "L\u00fcjiatun"
    ],
    "name:zho_x_variant":[
        "\u5415\u5bb6\u5c6f"
    ],
    "wof:name":"Lujiatun",
    "wof:placetype":"locality"
},
  "geometry": {"coordinates":[124.25490000000001,42.30401],"type":"Point"}
}