{
  "type": "Feature",
  "properties": {
    "gn:admin1_code":"4.0",
    "gn:asciiname":"Yangzhuangcun",
    "gn:country_code":"CN",
    "gn:dem":34,
    "gn:feature_class":"P",
    "gn:feature_code":"PPL",
    "gn:name":"Yangzhuangcun",
    "gn:population":0,
    "gn:timezone":"Asia/Shanghai",
    "iso:country":"CN",
    "name:zho_x_preferred":[
        "\u6768\u5e84\u6751"
    ],
    "wof:name":"Yangzhuangcun",
    "wof:placetype":"locality"
},
  "geometry": {"coordinates":[119.15051,32.46668],"type":"Point"}
}