{
  "type": "Feature",
  "properties": {
    "gn:admin1_code":"7.0",
    "gn:asciiname":"Dahu",
    "gn:country_code":"CN",
    "gn:dem":336,
    "gn:feature_class":"P",
    "gn:feature_code":"PPL",
    "gn:name":"Dahu",
    "gn:population":0,
    "gn:timezone":"Asia/Shanghai",
    "iso:country":"CN",
    "name:zho_x_preferred":[
        "\u5927\u6e56"
    ],
    "wof:name":"Dahu",
    "wof:placetype":"locality"
},
  "geometry": {"coordinates":[117.16943000000001,24.30877000000001],"type":"Point"}
}