{
  "type": "Feature",
  "properties": {
    "gn:admin1_code":"1.0",
    "gn:asciiname":"Yanglincun",
    "gn:country_code":"CN",
    "gn:dem":7,
    "gn:feature_class":"P",
    "gn:feature_code":"PPL",
    "gn:name":"Yanglincun",
    "gn:population":0,
    "gn:timezone":"Asia/Shanghai",
    "iso:country":"CN",
    "name:zho_x_preferred":[
        "\u6768\u6797\u6751"
    ],
    "wof:name":"Yanglincun",
    "wof:placetype":"locality"
},
  "geometry": {"coordinates":[117.80755000000001,31.07899],"type":"Point"}
}