{
  "type": "Feature",
  "properties": {
    "gn:admin1_code":"2.0",
    "gn:asciiname":"Maojiadian",
    "gn:country_code":"CN",
    "gn:dem":511,
    "gn:feature_class":"P",
    "gn:feature_code":"PPL",
    "gn:name":"Maojiadian",
    "gn:population":0,
    "gn:timezone":"Asia/Shanghai",
    "iso:country":"CN",
    "name:zho_x_preferred":[
        "\u6bdb\u5bb6\u6bbf"
    ],
    "wof:name":"Maojiadian",
    "wof:placetype":"locality"
},
  "geometry": {"coordinates":[118.73963000000001,28.65433],"type":"Point"}
}