{
  "type": "Feature",
  "properties": {
    "gn:admin1_code":"12.0",
    "gn:asciiname":"Huangjiaci",
    "gn:country_code":"CN",
    "gn:dem":42,
    "gn:feature_class":"P",
    "gn:feature_code":"PPL",
    "gn:name":"Huangjiaci",
    "gn:population":0,
    "gn:timezone":"Asia/Shanghai",
    "iso:country":"CN",
    "name:zho_x_preferred":[
        "Huangjiaci"
    ],
    "name:zho_x_variant":[
        "\u9ec4\u5bb6\u7960"
    ],
    "wof:name":"Huangjiaci",
    "wof:placetype":"locality"
},
  "geometry": {"coordinates":[114.43776,29.98574],"type":"Point"}
}