{
  "type": "Feature",
  "properties": {
    "gn:admin1_code":"2.0",
    "gn:asciiname":"Tuodai",
    "gn:country_code":"CN",
    "gn:dem":670,
    "gn:feature_class":"P",
    "gn:feature_code":"PPL",
    "gn:name":"Tuodai",
    "gn:population":0,
    "gn:timezone":"Asia/Shanghai",
    "iso:country":"CN",
    "name:zho_x_preferred":[
        "\u9a6e\u5cb1"
    ],
    "wof:name":"Tuodai",
    "wof:placetype":"locality"
},
  "geometry": {"coordinates":[119.27016999999999,28.22909000000001],"type":"Point"}
}