{
  "type": "Feature",
  "properties": {
    "gn:admin1_code":"5.0",
    "gn:asciiname":"Jinfengcun",
    "gn:country_code":"CN",
    "gn:dem":368,
    "gn:feature_class":"P",
    "gn:feature_code":"PPL",
    "gn:name":"Jinfengcun",
    "gn:population":0,
    "gn:timezone":"Asia/Shanghai",
    "iso:country":"CN",
    "name:zho_x_preferred":[
        "\u91d1\u51e4\u6751"
    ],
    "wof:name":"Jinfengcun",
    "wof:placetype":"locality"
},
  "geometry": {"coordinates":[125.48545,42.78052],"type":"Point"}
}