{
  "type": "Feature",
  "properties": {
    "gn:admin1_code":"10.0",
    "gn:asciiname":"Dadiba",
    "gn:country_code":"CN",
    "gn:dem":42,
    "gn:feature_class":"P",
    "gn:feature_code":"PPL",
    "gn:name":"Dadiba",
    "gn:population":0,
    "gn:timezone":"Asia/Shanghai",
    "iso:country":"CN",
    "name:zho_x_preferred":[
        "\u5927\u5f1f\u516b"
    ],
    "wof:name":"Dadiba",
    "wof:placetype":"locality"
},
  "geometry": {"coordinates":[115.06968000000001,36.81085],"type":"Point"}
}