{
  "type": "Feature",
  "properties": {
    "gn:admin1_code":"26.0",
    "gn:asciiname":"Shangjiashancun",
    "gn:country_code":"CN",
    "gn:dem":991,
    "gn:feature_class":"P",
    "gn:feature_code":"PPL",
    "gn:name":"Shangjiashancun",
    "gn:population":0,
    "gn:timezone":"Asia/Shanghai",
    "iso:country":"CN",
    "name:zho_x_preferred":[
        "\u5c1a\u5bb6\u5c71\u6751"
    ],
    "wof:name":"Shangjiashancun",
    "wof:placetype":"locality"
},
  "geometry": {"coordinates":[110.2478,37.08564000000001],"type":"Point"}
}