{
  "type": "Feature",
  "properties": {
    "gn:admin1_code":"3.0",
    "gn:asciiname":"Heling Zhoujia",
    "gn:country_code":"CN",
    "gn:dem":65,
    "gn:feature_class":"P",
    "gn:feature_code":"PPL",
    "gn:name":"Heling Zhoujia",
    "gn:population":0,
    "gn:timezone":"Asia/Shanghai",
    "iso:country":"CN",
    "name:und_x_variant":[
        "\u8377\u5cad\u5468\u5bb6"
    ],
    "wof:name":"Heling Zhoujia",
    "wof:placetype":"locality"
},
  "geometry": {"coordinates":[116.42888000000001,27.78101],"type":"Point"}
}