{
  "type": "Feature",
  "properties": {
    "gn:admin1_code":"26.0",
    "gn:asciiname":"Luochuanwancun",
    "gn:country_code":"CN",
    "gn:dem":709,
    "gn:feature_class":"P",
    "gn:feature_code":"PPL",
    "gn:name":"Luochuanwancun",
    "gn:population":0,
    "gn:timezone":"Asia/Shanghai",
    "iso:country":"CN",
    "name:zho_x_preferred":[
        "\u87ba\u5ddd\u6e7e\u6751"
    ],
    "wof:name":"Luochuanwancun",
    "wof:placetype":"locality"
},
  "geometry": {"coordinates":[109.79755,33.42335],"type":"Point"}
}