{
  "type": "Feature",
  "properties": {
    "gn:admin1_code":"12.0",
    "gn:asciiname":"Sizhuangping",
    "gn:country_code":"CN",
    "gn:dem":812,
    "gn:feature_class":"P",
    "gn:feature_code":"PPL",
    "gn:name":"Sizhuangping",
    "gn:population":0,
    "gn:timezone":"Asia/Shanghai",
    "iso:country":"CN",
    "name:zho_x_preferred":[
        "\u56db\u5e84\u576a"
    ],
    "wof:name":"Sizhuangping",
    "wof:placetype":"locality"
},
  "geometry": {"coordinates":[109.67483,32.56613],"type":"Point"}
}