{
  "type": "Feature",
  "properties": {
    "gn:admin1_code":"19",
    "gn:asciiname":"Sunbotun",
    "gn:country_code":"CN",
    "gn:dem":55,
    "gn:feature_class":"P",
    "gn:feature_code":"PPL",
    "gn:name":"Sunbotun",
    "gn:population":0,
    "gn:timezone":"Asia/Shanghai",
    "iso:country":"CN",
    "name:und_x_variant":[
        "Sunbotuncun",
        "Sunbotun"
    ],
    "name:zho_x_preferred":[
        "\u5b59\u67cf\u5c6f\u6751"
    ],
    "wof:name":"Sunbotun",
    "wof:placetype":"locality"
},
  "geometry": {"coordinates":[121.34193999999999,41.54861],"type":"Point"}
}