{
  "type": "Feature",
  "properties": {
    "gn:admin1_code":"11",
    "gn:asciiname":"Baoziling",
    "gn:country_code":"CN",
    "gn:dem":63,
    "gn:feature_class":"P",
    "gn:feature_code":"PPL",
    "gn:name":"Baoziling",
    "gn:population":0,
    "gn:timezone":"Asia/Shanghai",
    "iso:country":"CN",
    "name:und_x_variant":[
        "\u8c79\u5b50\u5cad"
    ],
    "wof:name":"Baoziling",
    "wof:placetype":"locality"
},
  "geometry": {"coordinates":[111.76054000000001,29.90508],"type":"Point"}
}