{
  "type": "Feature",
  "properties": {
    "gn:admin1_code":"1.0",
    "gn:asciiname":"Gandiancun",
    "gn:country_code":"CN",
    "gn:dem":41,
    "gn:feature_class":"P",
    "gn:feature_code":"PPL",
    "gn:name":"Gandiancun",
    "gn:population":0,
    "gn:timezone":"Asia/Shanghai",
    "iso:country":"CN",
    "name:zho_x_preferred":[
        "\u7518\u5e97\u6751"
    ],
    "wof:name":"Gandiancun",
    "wof:placetype":"locality"
},
  "geometry": {"coordinates":[116.73663000000001,32.23305999999999],"type":"Point"}
}