{
  "type": "Feature",
  "properties": {
    "gn:admin1_code":"2.0",
    "gn:asciiname":"Zhoujia",
    "gn:country_code":"CN",
    "gn:dem":175,
    "gn:feature_class":"P",
    "gn:feature_code":"PPL",
    "gn:name":"Zhoujia",
    "gn:population":0,
    "gn:timezone":"Asia/Shanghai",
    "iso:country":"CN",
    "name:und_x_variant":[
        "\u5468\u5bb6",
        "Zhoujia"
    ],
    "wof:name":"Zhoujia",
    "wof:placetype":"locality"
},
  "geometry": {"coordinates":[119.92653,29.66085],"type":"Point"}
}