{
  "type": "Feature",
  "properties": {
    "gn:admin1_code":"20.0",
    "gn:asciiname":"Shiyi Gongli",
    "gn:country_code":"CN",
    "gn:dem":534,
    "gn:feature_class":"P",
    "gn:feature_code":"PPL",
    "gn:name":"Shiyi Gongli",
    "gn:population":0,
    "gn:timezone":"Asia/Shanghai",
    "iso:country":"CN",
    "name:zho_x_preferred":[
        "\u5341\u4e00\u516c\u91cc"
    ],
    "wof:name":"Shiyi Gongli",
    "wof:placetype":"locality"
},
  "geometry": {"coordinates":[122.19544999999999,48.18065],"type":"Point"}
}