{
  "type": "Feature",
  "properties": {
    "gn:admin1_code":"3.0",
    "gn:asciiname":"Jiantoucun",
    "gn:country_code":"CN",
    "gn:dem":27,
    "gn:feature_class":"P",
    "gn:feature_code":"PPL",
    "gn:name":"Jiantoucun",
    "gn:population":0,
    "gn:timezone":"Asia/Shanghai",
    "iso:country":"CN",
    "name:und_x_variant":[
        "\u7bad\u5934\u6751"
    ],
    "wof:name":"Jiantoucun",
    "wof:placetype":"locality"
},
  "geometry": {"coordinates":[115.87981000000001,28.55464000000001],"type":"Point"}
}