{
  "type": "Feature",
  "properties": {
    "gn:admin1_code":"11.0",
    "gn:asciiname":"Liujiazui",
    "gn:country_code":"CN",
    "gn:dem":29,
    "gn:feature_class":"P",
    "gn:feature_code":"PPL",
    "gn:name":"Liujiazui",
    "gn:population":0,
    "gn:timezone":"Asia/Shanghai",
    "iso:country":"CN",
    "name:zho_x_preferred":[
        "Liujiazui"
    ],
    "name:zho_x_variant":[
        "\u5218\u5bb6\u5480"
    ],
    "wof:name":"Liujiazui",
    "wof:placetype":"locality"
},
  "geometry": {"coordinates":[111.93697,29.07147],"type":"Point"}
}