{
  "type": "Feature",
  "properties": {
    "gn:admin1_code":"32.0",
    "gn:asciiname":"Jizhaoka",
    "gn:country_code":"CN",
    "gn:dem":1801,
    "gn:feature_class":"P",
    "gn:feature_code":"PPL",
    "gn:name":"Jizhaoka",
    "gn:population":0,
    "gn:timezone":"Asia/Shanghai",
    "iso:country":"CN",
    "name:zho_x_preferred":[
        "\u5409\u5146\u5361"
    ],
    "wof:name":"Jizhaoka",
    "wof:placetype":"locality"
},
  "geometry": {"coordinates":[102.98999999999999,26.5671],"type":"Point"}
}