{
  "type": "Feature",
  "properties": {
    "gn:admin1_code":"3.0",
    "gn:asciiname":"Lijiangxiang Linchang",
    "gn:country_code":"CN",
    "gn:dem":131,
    "gn:feature_class":"P",
    "gn:feature_code":"PPLF",
    "gn:name":"Lijiangxiang Linchang",
    "gn:population":0,
    "gn:timezone":"Asia/Shanghai",
    "iso:country":"CN",
    "name:und_x_variant":[
        "\u6ea7\u6c5f\u4e61\u6797\u573a"
    ],
    "wof:name":"Lijiangxiang Linchang",
    "wof:placetype":"locality"
},
  "geometry": {"coordinates":[115.50320000000001,27.80639],"type":"Point"}
}