{
  "type": "Feature",
  "properties": {
    "gn:admin1_code":"26.0",
    "gn:asciiname":"Maiyushan",
    "gn:country_code":"CN",
    "gn:dem":966,
    "gn:feature_class":"P",
    "gn:feature_code":"PPL",
    "gn:name":"Maiyushan",
    "gn:population":0,
    "gn:timezone":"Asia/Shanghai",
    "iso:country":"CN",
    "name:zho_x_preferred":[
        "\u9ea6\u88d5\u5c71"
    ],
    "wof:name":"Maiyushan",
    "wof:placetype":"locality"
},
  "geometry": {"coordinates":[106.98553,34.74323],"type":"Point"}
}