{
  "type": "Feature",
  "properties": {
    "gn:admin1_code":"29",
    "gn:asciiname":"Jijiepu",
    "gn:country_code":"CN",
    "gn:dem":1424,
    "gn:feature_class":"P",
    "gn:feature_code":"PPL",
    "gn:name":"Jijiepu",
    "gn:population":0,
    "gn:timezone":"Asia/Shanghai",
    "iso:country":"CN",
    "name:zho_x_preferred":[
        "\u9e21\u8857\u94fa"
    ],
    "wof:name":"Jijiepu",
    "wof:placetype":"locality"
},
  "geometry": {"coordinates":[103.392,24.3205],"type":"Point"}
}