{
  "type": "Feature",
  "properties": {
    "gn:admin1_code":"4.0",
    "gn:asciiname":"Dabeicun",
    "gn:country_code":"CN",
    "gn:dem":6,
    "gn:feature_class":"P",
    "gn:feature_code":"PPL",
    "gn:name":"Dabeicun",
    "gn:population":0,
    "gn:timezone":"Asia/Shanghai",
    "iso:country":"CN",
    "name:zho_x_preferred":[
        "\u7b2a\u5317\u6751"
    ],
    "wof:name":"Dabeicun",
    "wof:placetype":"locality"
},
  "geometry": {"coordinates":[119.34050999999999,33.82648],"type":"Point"}
}