{
  "type": "Feature",
  "properties": {
    "gn:admin1_code":"14.0",
    "gn:asciiname":"Quche",
    "gn:country_code":"CN",
    "gn:dem":4371,
    "gn:feature_class":"P",
    "gn:feature_code":"PPL",
    "gn:name":"Quche",
    "gn:population":0,
    "gn:timezone":"Asia/Urumqi",
    "iso:country":"CN",
    "name:zho_x_preferred":[
        "\u66f2\u626f"
    ],
    "wof:name":"Quche",
    "wof:placetype":"locality"
},
  "geometry": {"coordinates":[97.08685,30.62146],"type":"Point"}
}