{
  "type": "Feature",
  "properties": {
    "gn:admin1_code":"16.0",
    "gn:asciiname":"Zhonghe",
    "gn:country_code":"CN",
    "gn:dem":54,
    "gn:feature_class":"P",
    "gn:feature_code":"PPL",
    "gn:name":"Zhonghe",
    "gn:population":0,
    "gn:timezone":"Asia/Shanghai",
    "iso:country":"CN",
    "name:ceb_x_preferred":[
        "Zhonghe"
    ],
    "name:deu_x_preferred":[
        "Zhonghe"
    ],
    "name:swe_x_preferred":[
        "Zhonghe"
    ],
    "name:zho_x_preferred":[
        "\u4e2d\u548c"
    ],
    "wof:name":"Zhonghe",
    "wof:placetype":"locality"
},
  "geometry": {"coordinates":[109.81100000000001,23.0009],"type":"Point"}
}