{
  "type": "Feature",
  "properties": {
    "gn:admin1_code":"12.0",
    "gn:asciiname":"Zhongzhulin",
    "gn:country_code":"CN",
    "gn:dem":46,
    "gn:feature_class":"P",
    "gn:feature_code":"PPL",
    "gn:name":"Zhongzhulin",
    "gn:population":0,
    "gn:timezone":"Asia/Shanghai",
    "iso:country":"CN",
    "name:zho_x_preferred":[
        "Zhongzhulin"
    ],
    "name:zho_x_variant":[
        "\u4e2d\u7af9\u6797"
    ],
    "wof:name":"Zhongzhulin",
    "wof:placetype":"locality"
},
  "geometry": {"coordinates":[115.33777000000001,29.72845],"type":"Point"}
}