{
  "type": "Feature",
  "properties": {
    "gn:admin1_code":"26.0",
    "gn:asciiname":"Xiafengjiazhuangcun",
    "gn:country_code":"CN",
    "gn:dem":1066,
    "gn:feature_class":"P",
    "gn:feature_code":"PPL",
    "gn:name":"Xiafengjiazhuangcun",
    "gn:population":0,
    "gn:timezone":"Asia/Shanghai",
    "iso:country":"CN",
    "name:zho_x_preferred":[
        "\u4e0b\u51af\u5bb6\u5e84\u6751"
    ],
    "wof:name":"Xiafengjiazhuangcun",
    "wof:placetype":"locality"
},
  "geometry": {"coordinates":[109.73905999999999,37.12198],"type":"Point"}
}