{
  "type": "Feature",
  "properties": {
    "gn:admin1_code":"30",
    "gn:asciiname":"Luowuwan",
    "gn:country_code":"CN",
    "gn:dem":203,
    "gn:feature_class":"P",
    "gn:feature_code":"PPL",
    "gn:name":"Luowuwan",
    "gn:population":0,
    "gn:timezone":"Asia/Shanghai",
    "iso:country":"CN",
    "name:zho_x_preferred":[
        "\u7f57\u5c4b\u6e7e"
    ],
    "wof:name":"Luowuwan",
    "wof:placetype":"locality"
},
  "geometry": {"coordinates":[115.8989,24.31831],"type":"Point"}
}