{
  "type": "Feature",
  "properties": {
    "gn:admin1_code":"26.0",
    "gn:asciiname":"Laolongchicun",
    "gn:country_code":"CN",
    "gn:dem":1038,
    "gn:feature_class":"P",
    "gn:feature_code":"PPL",
    "gn:name":"Laolongchicun",
    "gn:population":0,
    "gn:timezone":"Asia/Shanghai",
    "iso:country":"CN",
    "name:zho_x_preferred":[
        "\u8001\u9f99\u6c60\u6751"
    ],
    "wof:name":"Laolongchicun",
    "wof:placetype":"locality"
},
  "geometry": {"coordinates":[107.05929999999999,32.79267],"type":"Point"}
}