{
  "type": "Feature",
  "properties": {
    "gn:admin1_code":"14",
    "gn:asciiname":"Daruo",
    "gn:country_code":"CN",
    "gn:dem":4453,
    "gn:feature_class":"P",
    "gn:feature_code":"PPL",
    "gn:name":"Daruo",
    "gn:population":0,
    "gn:timezone":"Asia/Urumqi",
    "iso:country":"CN",
    "name:zho_x_preferred":[
        "\u8fbe\u82e5"
    ],
    "wof:name":"Daruo",
    "wof:placetype":"locality"
},
  "geometry": {"coordinates":[89.43680000000001,28.3459],"type":"Point"}
}