{
  "type": "Feature",
  "properties": {
    "gn:admin1_code":"26.0",
    "gn:asciiname":"Daodagounao",
    "gn:country_code":"CN",
    "gn:dem":846,
    "gn:feature_class":"P",
    "gn:feature_code":"PPL",
    "gn:name":"Daodagounao",
    "gn:population":0,
    "gn:timezone":"Asia/Shanghai",
    "iso:country":"CN",
    "name:zho_x_preferred":[
        "\u5230\u8fbe\u6c9f\u8111"
    ],
    "wof:name":"Daodagounao",
    "wof:placetype":"locality"
},
  "geometry": {"coordinates":[110.51749,33.41636],"type":"Point"}
}