{
  "type": "Feature",
  "properties": {
    "gn:admin1_code":"11.0",
    "gn:asciiname":"Banchangpo",
    "gn:country_code":"CN",
    "gn:dem":1109,
    "gn:feature_class":"P",
    "gn:feature_code":"PPL",
    "gn:name":"Banchangpo",
    "gn:population":0,
    "gn:timezone":"Asia/Shanghai",
    "iso:country":"CN",
    "name:zho_x_preferred":[
        "\u73ed\u957f\u5761"
    ],
    "wof:name":"Banchangpo",
    "wof:placetype":"locality"
},
  "geometry": {"coordinates":[109.5694,29.46774000000001],"type":"Point"}
}