{
  "type": "Feature",
  "properties": {
    "gn:admin1_code":"15.0",
    "gn:asciiname":"Liujia Goumen",
    "gn:country_code":"CN",
    "gn:dem":1942,
    "gn:feature_class":"P",
    "gn:feature_code":"PPL",
    "gn:name":"Liujia Goumen",
    "gn:population":0,
    "gn:timezone":"Asia/Shanghai",
    "iso:country":"CN",
    "name:zho_x_preferred":[
        "\u5218\u5bb6\u6c9f\u95e8"
    ],
    "wof:name":"Liujia Goumen",
    "wof:placetype":"locality"
},
  "geometry": {"coordinates":[103.85299999999999,35.297],"type":"Point"}
}