{
  "type": "Feature",
  "properties": {
    "gn:admin1_code":"14.0",
    "gn:asciiname":"Chici'ertang",
    "gn:country_code":"CN",
    "gn:dem":4485,
    "gn:feature_class":"P",
    "gn:feature_code":"PPL",
    "gn:name":"Chici\u2019ertang",
    "gn:population":0,
    "gn:timezone":"Asia/Urumqi",
    "iso:country":"CN",
    "name:und_x_variant":[
        "Chici\u2019ertang"
    ],
    "name:zho_x_preferred":[
        "\u8d64\u6b21\u5c14\u5858"
    ],
    "wof:name":"Chici'ertang",
    "wof:placetype":"locality"
},
  "geometry": {"coordinates":[96.26711,30.57224],"type":"Point"}
}