{
  "type": "Feature",
  "properties": {
    "gn:admin1_code":"18",
    "gn:asciiname":"Fenghuo",
    "gn:country_code":"CN",
    "gn:dem":1015,
    "gn:feature_class":"P",
    "gn:feature_code":"PPL",
    "gn:name":"Fenghuo",
    "gn:population":0,
    "gn:timezone":"Asia/Shanghai",
    "iso:country":"CN",
    "name:zho_x_preferred":[
        "\u5c01\u706b"
    ],
    "wof:name":"Fenghuo",
    "wof:placetype":"locality"
},
  "geometry": {"coordinates":[106.837,27.8898],"type":"Point"}
}