{
  "type": "Feature",
  "properties": {
    "gn:admin1_code":"14.0",
    "gn:asciiname":"Wabacun",
    "gn:country_code":"CN",
    "gn:dem":4327,
    "gn:feature_class":"P",
    "gn:feature_code":"PPL",
    "gn:name":"Wabacun",
    "gn:population":0,
    "gn:timezone":"Asia/Urumqi",
    "iso:country":"CN",
    "name:zho_x_preferred":[
        "\u74e6\u5df4\u6751"
    ],
    "wof:name":"Wabacun",
    "wof:placetype":"locality"
},
  "geometry": {"coordinates":[96.62584,30.2462],"type":"Point"}
}