{
  "type": "Feature",
  "properties": {
    "gn:admin1_code":"3.0",
    "gn:asciiname":"Niaokeng",
    "gn:country_code":"CN",
    "gn:dem":19,
    "gn:feature_class":"P",
    "gn:feature_code":"PPL",
    "gn:name":"Niaokeng",
    "gn:population":0,
    "gn:timezone":"Asia/Shanghai",
    "iso:country":"CN",
    "name:und_x_variant":[
        "\u9e1f\u5751"
    ],
    "wof:name":"Niaokeng",
    "wof:placetype":"locality"
},
  "geometry": {"coordinates":[115.75563,29.02627],"type":"Point"}
}