{
  "type": "Feature",
  "properties": {
    "gn:admin1_code":"11.0",
    "gn:asciiname":"Tongluoqiu",
    "gn:country_code":"CN",
    "gn:dem":399,
    "gn:feature_class":"P",
    "gn:feature_code":"PPL",
    "gn:name":"Tongluoqiu",
    "gn:population":0,
    "gn:timezone":"Asia/Shanghai",
    "iso:country":"CN",
    "name:zho_x_preferred":[
        "\u94dc\u9523\u4e18"
    ],
    "wof:name":"Tongluoqiu",
    "wof:placetype":"locality"
},
  "geometry": {"coordinates":[113.59752,25.74043],"type":"Point"}
}