{
  "type": "Feature",
  "properties": {
    "gn:admin1_code":"2.0",
    "gn:asciiname":"Zhuanggu",
    "gn:country_code":"CN",
    "gn:dem":5,
    "gn:feature_class":"P",
    "gn:feature_code":"PPL",
    "gn:name":"Zhuanggu",
    "gn:population":0,
    "gn:timezone":"Asia/Shanghai",
    "iso:country":"CN",
    "name:und_x_variant":[
        "\u5e84\u53e4",
        "\u5e84\u53e4\u6751"
    ],
    "name:zho_x_preferred":[
        "Zhuanggucun"
    ],
    "wof:name":"Zhuanggu",
    "wof:placetype":"locality"
},
  "geometry": {"coordinates":[119.90309000000001,30.86209],"type":"Point"}
}