{
  "type": "Feature",
  "properties": {
    "gn:admin1_code":"12.0",
    "gn:asciiname":"Tucheng",
    "gn:country_code":"CN",
    "gn:dem":1031,
    "gn:feature_class":"P",
    "gn:feature_code":"PPL",
    "gn:name":"Tucheng",
    "gn:population":0,
    "gn:timezone":"Asia/Shanghai",
    "iso:country":"CN",
    "name:zho_x_preferred":[
        "\u571f\u57ce"
    ],
    "wof:name":"Tucheng",
    "wof:placetype":"locality"
},
  "geometry": {"coordinates":[109.8522,31.92815],"type":"Point"}
}