{
  "type": "Feature",
  "properties": {
    "gn:admin1_code":"19.0",
    "gn:asciiname":"Zhaotuozicun",
    "gn:country_code":"CN",
    "gn:dem":61,
    "gn:feature_class":"P",
    "gn:feature_code":"PPL",
    "gn:name":"Zhaotuozicun",
    "gn:population":0,
    "gn:timezone":"Asia/Shanghai",
    "iso:country":"CN",
    "name:zho_x_preferred":[
        "\u8d75\u5768\u5b50\u6751"
    ],
    "wof:name":"Zhaotuozicun",
    "wof:placetype":"locality"
},
  "geometry": {"coordinates":[122.56699999999999,42.1831],"type":"Point"}
}