{
  "type": "Feature",
  "properties": {
    "gn:admin1_code":"14.0",
    "gn:asciiname":"Zhongmai",
    "gn:country_code":"CN",
    "gn:dem":3987,
    "gn:feature_class":"P",
    "gn:feature_code":"PPL",
    "gn:name":"Zhongmai",
    "gn:population":0,
    "gn:timezone":"Asia/Urumqi",
    "iso:country":"CN",
    "name:zho_x_preferred":[
        "\u4ef2\u9ea6"
    ],
    "wof:name":"Zhongmai",
    "wof:placetype":"locality"
},
  "geometry": {"coordinates":[91.07755,28.22838],"type":"Point"}
}