{
  "type": "Feature",
  "properties": {
    "gn:admin1_code":"15.0",
    "gn:asciiname":"Machang",
    "gn:country_code":"CN",
    "gn:dem":2549,
    "gn:feature_class":"P",
    "gn:feature_code":"PPL",
    "gn:name":"Machang",
    "gn:population":0,
    "gn:timezone":"Asia/Shanghai",
    "iso:country":"CN",
    "name:und_x_variant":[
        "\u9a6c\u573a"
    ],
    "name:zho_x_preferred":[
        "\u9a6c\u573a"
    ],
    "wof:name":"Machang",
    "wof:placetype":"locality"
},
  "geometry": {"coordinates":[104.9383,33.28745],"type":"Point"}
}