{
  "type": "Feature",
  "properties": {
    "gn:admin1_code":"8.0",
    "gn:asciiname":"Xianzhongmachang Yifenchang",
    "gn:country_code":"CN",
    "gn:dem":195,
    "gn:feature_class":"P",
    "gn:feature_code":"PPLF",
    "gn:name":"Xianzhongmachang Yifenchang",
    "gn:population":0,
    "gn:timezone":"Asia/Shanghai",
    "iso:country":"CN",
    "name:zho_x_preferred":[
        "\u53bf\u79cd\u9a6c\u573a\u4e00\u5206\u573a"
    ],
    "wof:name":"Xianzhongmachang Yifenchang",
    "wof:placetype":"locality"
},
  "geometry": {"coordinates":[127.4012,45.13187],"type":"Point"}
}