{
  "type": "Feature",
  "properties": {
    "gn:admin1_code":"30.0",
    "gn:asciiname":"Houlitang",
    "gn:country_code":"CN",
    "gn:dem":18,
    "gn:feature_class":"P",
    "gn:feature_code":"PPL",
    "gn:name":"Houlitang",
    "gn:population":0,
    "gn:timezone":"Asia/Shanghai",
    "iso:country":"CN",
    "name:zho_x_preferred":[
        "\u539a\u7406\u5858"
    ],
    "wof:name":"Houlitang",
    "wof:placetype":"locality"
},
  "geometry": {"coordinates":[111.56726999999999,23.2088],"type":"Point"}
}