{
  "type": "Feature",
  "properties": {
    "gn:admin1_code":"16.0",
    "gn:asciiname":"Focaonao",
    "gn:country_code":"CN",
    "gn:dem":197,
    "gn:feature_class":"P",
    "gn:feature_code":"PPL",
    "gn:name":"Focaonao",
    "gn:population":0,
    "gn:timezone":"Asia/Shanghai",
    "iso:country":"CN",
    "name:zho_x_preferred":[
        "\u4f5b\u69fd\u8111"
    ],
    "wof:name":"Focaonao",
    "wof:placetype":"locality"
},
  "geometry": {"coordinates":[110.742,24.2106],"type":"Point"}
}