{
  "type": "Feature",
  "properties": {
    "gn:admin1_code":"11",
    "gn:asciiname":"Maolipu",
    "gn:country_code":"CN",
    "gn:dem":86,
    "gn:feature_class":"P",
    "gn:feature_code":"PPL",
    "gn:name":"Maolipu",
    "gn:population":0,
    "gn:timezone":"Asia/Shanghai",
    "iso:country":"CN",
    "name:zho_x_preferred":[
        "\u8305\u6817\u94fa"
    ],
    "wof:name":"Maolipu",
    "wof:placetype":"locality"
},
  "geometry": {"coordinates":[113.15572,29.27053],"type":"Point"}
}