{
  "type": "Feature",
  "properties": {
    "gn:admin1_code":"30",
    "gn:asciiname":"Maoliancun",
    "gn:country_code":"CN",
    "gn:dem":9,
    "gn:feature_class":"P",
    "gn:feature_code":"PPL",
    "gn:name":"Maoliancun",
    "gn:population":0,
    "gn:timezone":"Asia/Urumqi",
    "iso:country":"CN",
    "name:zho_x_preferred":[
        "\u8302\u83b2\u6751"
    ],
    "wof:name":"Maoliancun",
    "wof:placetype":"locality"
},
  "geometry": {"coordinates":[110.12053,21.00875],"type":"Point"}
}