{
  "type": "Feature",
  "properties": {
    "gn:admin1_code":"10.0",
    "gn:asciiname":"Gaoxiandian",
    "gn:country_code":"CN",
    "gn:dem":6,
    "gn:feature_class":"P",
    "gn:feature_code":"PPL",
    "gn:name":"Gaoxiandian",
    "gn:population":0,
    "gn:timezone":"Asia/Shanghai",
    "iso:country":"CN",
    "name:zho_x_preferred":[
        "\u9ad8\u5148\u7538"
    ],
    "wof:name":"Gaoxiandian",
    "wof:placetype":"locality"
},
  "geometry": {"coordinates":[118.0735,39.46007],"type":"Point"}
}