{
  "type": "Feature",
  "properties": {
    "gn:admin1_code":"11.0",
    "gn:asciiname":"Wangjiatuan",
    "gn:country_code":"CN",
    "gn:dem":320,
    "gn:feature_class":"P",
    "gn:feature_code":"PPL",
    "gn:name":"Wangjiatuan",
    "gn:population":0,
    "gn:timezone":"Asia/Shanghai",
    "iso:country":"CN",
    "name:zho_x_preferred":[
        "\u738b\u5bb6\u56e2"
    ],
    "wof:name":"Wangjiatuan",
    "wof:placetype":"locality"
},
  "geometry": {"coordinates":[110.17555,26.59376],"type":"Point"}
}