{
  "type": "Feature",
  "properties": {
    "gn:admin1_code":"5.0",
    "gn:asciiname":"Xiaolongmiao",
    "gn:country_code":"CN",
    "gn:dem":228,
    "gn:feature_class":"P",
    "gn:feature_code":"PPL",
    "gn:name":"Xiaolongmiao",
    "gn:population":0,
    "gn:timezone":"Asia/Shanghai",
    "iso:country":"CN",
    "name:zho_x_preferred":[
        "\u5c0f\u9f99\u5e99"
    ],
    "wof:name":"Xiaolongmiao",
    "wof:placetype":"locality"
},
  "geometry": {"coordinates":[125.63573,43.48406],"type":"Point"}
}