{
  "type": "Feature",
  "properties": {
    "gn:admin1_code":"14.0",
    "gn:asciiname":"Jiagong",
    "gn:country_code":"CN",
    "gn:dem":4169,
    "gn:feature_class":"P",
    "gn:feature_code":"PPL",
    "gn:name":"Jiagong",
    "gn:population":0,
    "gn:timezone":"Asia/Urumqi",
    "iso:country":"CN",
    "name:zho_x_preferred":[
        "\u7532\u8d21"
    ],
    "wof:name":"Jiagong",
    "wof:placetype":"locality"
},
  "geometry": {"coordinates":[94.81501,31.10704],"type":"Point"}
}