{
  "type": "Feature",
  "properties": {
    "gn:admin1_code":"32.0",
    "gn:asciiname":"Se'erji",
    "gn:country_code":"CN",
    "gn:dem":2965,
    "gn:feature_class":"P",
    "gn:feature_code":"PPL",
    "gn:name":"Se\u2019erji",
    "gn:population":0,
    "gn:timezone":"Asia/Shanghai",
    "iso:country":"CN",
    "name:zho_x_preferred":[
        "\u8272\u5c14\u5409"
    ],
    "name:zho_x_variant":[
        "Se\u2019erji"
    ],
    "wof:name":"Se'erji",
    "wof:placetype":"locality"
},
  "geometry": {"coordinates":[101.55535999999999,32.48812],"type":"Point"}
}