{
  "type": "Feature",
  "properties": {
    "gn:admin1_code":"5.0",
    "gn:asciiname":"Qianshisihao",
    "gn:country_code":"CN",
    "gn:dem":160,
    "gn:feature_class":"P",
    "gn:feature_code":"PPL",
    "gn:name":"Qianshisihao",
    "gn:population":0,
    "gn:timezone":"Asia/Shanghai",
    "iso:country":"CN",
    "name:zho_x_preferred":[
        "\u524d\u5341\u56db\u53f7"
    ],
    "wof:name":"Qianshisihao",
    "wof:placetype":"locality"
},
  "geometry": {"coordinates":[126.15853,45.07341],"type":"Point"}
}