{
  "type": "Feature",
  "properties": {
    "gn:admin1_code":"11.0",
    "gn:asciiname":"Shangguanzinao",
    "gn:country_code":"CN",
    "gn:dem":242,
    "gn:feature_class":"P",
    "gn:feature_code":"PPL",
    "gn:name":"Shangguanzinao",
    "gn:population":0,
    "gn:timezone":"Asia/Shanghai",
    "iso:country":"CN",
    "name:zho_x_preferred":[
        "\u4e0a\u7f50\u5b50\u8111"
    ],
    "wof:name":"Shangguanzinao",
    "wof:placetype":"locality"
},
  "geometry": {"coordinates":[111.90254,26.90806],"type":"Point"}
}