{
  "type": "Feature",
  "properties": {
    "gn:admin1_code":"31",
    "gn:asciiname":"Beida",
    "gn:country_code":"CN",
    "gn:dem":30,
    "gn:feature_class":"P",
    "gn:feature_code":"PPLA4",
    "gn:name":"Beida",
    "gn:population":0,
    "gn:timezone":"Asia/Shanghai",
    "iso:country":"CN",
    "name:ceb_x_preferred":[
        "Beida"
    ],
    "name:fra_x_preferred":[
        "Beida"
    ],
    "name:nld_x_preferred":[
        "Beida"
    ],
    "name:swe_x_preferred":[
        "Beida"
    ],
    "name:und_x_variant":[
        "\u5317\u5927",
        "Beida Zhen",
        "\u5317\u5927\u9547"
    ],
    "wof:name":"Beida",
    "wof:placetype":"locality"
},
  "geometry": {"coordinates":[110.33078999999999,18.92416],"type":"Point"}
}