{
  "type": "Feature",
  "properties": {
    "gn:admin1_code":"21.0",
    "gn:asciiname":"Duyaogou",
    "gn:country_code":"CN",
    "gn:dem":1467,
    "gn:feature_class":"P",
    "gn:feature_code":"PPL",
    "gn:name":"Duyaogou",
    "gn:population":0,
    "gn:timezone":"Asia/Shanghai",
    "iso:country":"CN",
    "name:zho_x_preferred":[
        "\u675c\u7a91\u6c9f"
    ],
    "wof:name":"Duyaogou",
    "wof:placetype":"locality"
},
  "geometry": {"coordinates":[106.88,37.5106],"type":"Point"}
}