{
  "type": "Feature",
  "properties": {
    "gn:admin1_code":"30",
    "gn:asciiname":"Huangshatang",
    "gn:country_code":"CN",
    "gn:dem":195,
    "gn:feature_class":"P",
    "gn:feature_code":"PPL",
    "gn:name":"Huangshatang",
    "gn:population":0,
    "gn:timezone":"Asia/Shanghai",
    "iso:country":"CN",
    "name:und_x_variant":[
        "\u9ec4\u6c99\u5858",
        "Huangshatang"
    ],
    "wof:name":"Huangshatang",
    "wof:placetype":"locality"
},
  "geometry": {"coordinates":[115.48621,23.65403],"type":"Point"}
}