{
  "type": "Feature",
  "properties": {
    "gn:admin1_code":"26.0",
    "gn:asciiname":"Qushuzhuang",
    "gn:country_code":"CN",
    "gn:dem":1454,
    "gn:feature_class":"P",
    "gn:feature_code":"PPL",
    "gn:name":"Qushuzhuang",
    "gn:population":0,
    "gn:timezone":"Asia/Shanghai",
    "iso:country":"CN",
    "name:zho_x_preferred":[
        "\u6e20\u6811\u5e84"
    ],
    "wof:name":"Qushuzhuang",
    "wof:placetype":"locality"
},
  "geometry": {"coordinates":[108.19896,36.77572],"type":"Point"}
}