{
  "type": "Feature",
  "properties": {
    "gn:admin1_code":"16",
    "gn:asciiname":"Chetan",
    "gn:country_code":"CN",
    "gn:dem":345,
    "gn:feature_class":"P",
    "gn:feature_code":"PPL",
    "gn:name":"Chetan",
    "gn:population":0,
    "gn:timezone":"Asia/Shanghai",
    "iso:country":"CN",
    "name:ita_x_preferred":[
        "Chetan"
    ],
    "name:uzb_x_preferred":[
        "Chetan"
    ],
    "name:zho_x_preferred":[
        "\u8f66\u6ee9"
    ],
    "wof:name":"Chetan",
    "wof:placetype":"locality"
},
  "geometry": {"coordinates":[110.52500000000001,25.7612],"type":"Point"}
}