{
  "type": "Feature",
  "properties": {
    "gn:admin1_code":"26",
    "gn:asciiname":"Hetaoba",
    "gn:country_code":"CN",
    "gn:dem":1280,
    "gn:feature_class":"P",
    "gn:feature_code":"PPL",
    "gn:name":"Hetaoba",
    "gn:population":0,
    "gn:timezone":"Asia/Shanghai",
    "iso:country":"CN",
    "name:und_x_variant":[
        "Khetaotszyuy",
        "Ho-t\u2019ao-ch\u00fc",
        "Ho-t\u2019ao-pa",
        "Hetaoba",
        "\u6838\u6843\u575d"
    ],
    "wof:name":"Hetaoba",
    "wof:placetype":"locality"
},
  "geometry": {"coordinates":[106.97176,33.98005999999999],"type":"Point"}
}