{
  "type": "Feature",
  "properties": {
    "gn:admin1_code":"4.0",
    "gn:asciiname":"Xunancun",
    "gn:country_code":"CN",
    "gn:dem":1,
    "gn:feature_class":"P",
    "gn:feature_code":"PPL",
    "gn:name":"Xunancun",
    "gn:population":0,
    "gn:timezone":"Asia/Shanghai",
    "iso:country":"CN",
    "name:zho_x_preferred":[
        "\u5729\u5357\u6751"
    ],
    "wof:name":"Xunancun",
    "wof:placetype":"locality"
},
  "geometry": {"coordinates":[119.56873,34.4353],"type":"Point"}
}