{
  "type": "Feature",
  "properties": {
    "gn:admin1_code":"18.0",
    "gn:asciiname":"Dunlun",
    "gn:country_code":"CN",
    "gn:dem":804,
    "gn:feature_class":"P",
    "gn:feature_code":"PPL",
    "gn:name":"Dunlun",
    "gn:population":0,
    "gn:timezone":"Asia/Shanghai",
    "iso:country":"CN",
    "name:zho_x_preferred":[
        "\u6566\u4f26"
    ],
    "wof:name":"Dunlun",
    "wof:placetype":"locality"
},
  "geometry": {"coordinates":[107.901,25.251],"type":"Point"}
}