{
  "type": "Feature",
  "properties": {
    "gn:admin1_code":"9.0",
    "gn:asciiname":"Shibanhe",
    "gn:country_code":"CN",
    "gn:dem":324,
    "gn:feature_class":"P",
    "gn:feature_code":"PPL",
    "gn:name":"Shibanhe",
    "gn:population":0,
    "gn:timezone":"Asia/Shanghai",
    "iso:country":"CN",
    "name:und_x_variant":[
        "\u77f3\u677f\u6cb3",
        "Shibanhe"
    ],
    "wof:name":"Shibanhe",
    "wof:placetype":"locality"
},
  "geometry": {"coordinates":[112.57934,33.97057],"type":"Point"}
}