{
  "type": "Feature",
  "properties": {
    "gn:admin1_code":"6.0",
    "gn:asciiname":"Seqinkou",
    "gn:country_code":"CN",
    "gn:dem":4256,
    "gn:feature_class":"P",
    "gn:feature_code":"PPL",
    "gn:name":"Seqinkou",
    "gn:population":0,
    "gn:timezone":"Asia/Urumqi",
    "iso:country":"CN",
    "name:zho_x_preferred":[
        "\u8272\u52e4\u6263"
    ],
    "wof:name":"Seqinkou",
    "wof:placetype":"locality"
},
  "geometry": {"coordinates":[96.53053,33.21744],"type":"Point"}
}