{
  "type": "Feature",
  "properties": {
    "gn:admin1_code":"3.0",
    "gn:asciiname":"Qitang",
    "gn:country_code":"CN",
    "gn:dem":135,
    "gn:feature_class":"P",
    "gn:feature_code":"PPL",
    "gn:name":"Qitang",
    "gn:population":0,
    "gn:timezone":"Asia/Shanghai",
    "iso:country":"CN",
    "name:und_x_variant":[
        "\u6dc7\u5858"
    ],
    "wof:name":"Qitang",
    "wof:placetype":"locality"
},
  "geometry": {"coordinates":[116.76975,27.24915],"type":"Point"}
}