{
  "type": "Feature",
  "properties": {
    "gn:admin1_code":"26.0",
    "gn:asciiname":"Lishupingcun",
    "gn:country_code":"CN",
    "gn:dem":1399,
    "gn:feature_class":"P",
    "gn:feature_code":"PPL",
    "gn:name":"Lishupingcun",
    "gn:population":0,
    "gn:timezone":"Asia/Shanghai",
    "iso:country":"CN",
    "name:zho_x_preferred":[
        "\u68a8\u6811\u576a\u6751"
    ],
    "wof:name":"Lishupingcun",
    "wof:placetype":"locality"
},
  "geometry": {"coordinates":[109.0343,35.37823],"type":"Point"}
}