{
  "type": "Feature",
  "properties": {
    "gn:admin1_code":"20.0",
    "gn:asciiname":"Chagan Nuo'er Gacha",
    "gn:country_code":"CN",
    "gn:dem":652,
    "gn:feature_class":"P",
    "gn:feature_code":"PPL",
    "gn:name":"Chagan Nuo\u2019er Gacha",
    "gn:population":0,
    "gn:timezone":"Asia/Shanghai",
    "iso:country":"CN",
    "name:und_x_variant":[
        "Chagan Nuo\u2019er Gacha"
    ],
    "name:zho_x_preferred":[
        "\u67e5\u5e72\u8bfa\u5c14\u560e\u67e5"
    ],
    "wof:name":"Chagan Nuo'er Gacha",
    "wof:placetype":"locality"
},
  "geometry": {"coordinates":[119.16958,48.77708],"type":"Point"}
}