{
  "type": "Feature",
  "properties": {
    "gn:admin1_code":"30.0",
    "gn:asciiname":"Longxincun",
    "gn:country_code":"CN",
    "gn:dem":26,
    "gn:feature_class":"P",
    "gn:feature_code":"PPL",
    "gn:name":"Longxincun",
    "gn:population":0,
    "gn:timezone":"Asia/Shanghai",
    "iso:country":"CN",
    "name:zho_x_preferred":[
        "\u9f99\u65b0\u6751"
    ],
    "wof:name":"Longxincun",
    "wof:placetype":"locality"
},
  "geometry": {"coordinates":[112.18359,22.07458],"type":"Point"}
}