{
  "type": "Feature",
  "properties": {
    "gn:admin1_code":"15.0",
    "gn:asciiname":"Zhanquan",
    "gn:country_code":"CN",
    "gn:dem":2190,
    "gn:feature_class":"P",
    "gn:feature_code":"PPL",
    "gn:name":"Zhanquan",
    "gn:population":0,
    "gn:timezone":"Asia/Shanghai",
    "iso:country":"CN",
    "name:zho_x_preferred":[
        "\u5c55\u5708"
    ],
    "wof:name":"Zhanquan",
    "wof:placetype":"locality"
},
  "geometry": {"coordinates":[103.79600000000001,36.7661],"type":"Point"}
}