{
  "type": "Feature",
  "properties": {
    "gn:admin1_code":"25.0",
    "gn:asciiname":"Dongzhuyan",
    "gn:country_code":"CN",
    "gn:dem":20,
    "gn:feature_class":"P",
    "gn:feature_code":"PPL",
    "gn:name":"Dongzhuyan",
    "gn:population":0,
    "gn:timezone":"Asia/Shanghai",
    "iso:country":"CN",
    "name:zho_x_preferred":[
        "\u4e1c\u73e0\u5ca9"
    ],
    "wof:name":"Dongzhuyan",
    "wof:placetype":"locality"
},
  "geometry": {"coordinates":[121.34959000000001,37.42365],"type":"Point"}
}