{
  "type": "Feature",
  "properties": {
    "gn:admin1_code":"26.0",
    "gn:asciiname":"Yuejin Nongchang",
    "gn:country_code":"CN",
    "gn:dem":1137,
    "gn:feature_class":"P",
    "gn:feature_code":"PPLF",
    "gn:name":"Yuejin Nongchang",
    "gn:population":0,
    "gn:timezone":"Asia/Shanghai",
    "iso:country":"CN",
    "name:und_x_variant":[
        "\u8dc3\u8fdb\u519c\u573a"
    ],
    "wof:name":"Yuejin Nongchang",
    "wof:placetype":"locality"
},
  "geometry": {"coordinates":[107.10119,34.91452],"type":"Point"}
}