{
  "type": "Feature",
  "properties": {
    "gn:admin1_code":"18",
    "gn:asciiname":"Wanrenfen",
    "gn:country_code":"CN",
    "gn:dem":1266,
    "gn:feature_class":"P",
    "gn:feature_code":"PPL",
    "gn:name":"Wanrenfen",
    "gn:population":0,
    "gn:timezone":"Asia/Shanghai",
    "iso:country":"CN",
    "name:zho_x_preferred":[
        "\u4e07\u4eba\u575f"
    ],
    "wof:name":"Wanrenfen",
    "wof:placetype":"locality"
},
  "geometry": {"coordinates":[105.779,26.8405],"type":"Point"}
}