{
  "type": "Feature",
  "properties": {
    "gn:admin1_code":"9.0",
    "gn:asciiname":"Beiyuan",
    "gn:country_code":"CN",
    "gn:dem":66,
    "gn:feature_class":"P",
    "gn:feature_code":"PPL",
    "gn:name":"Beiyuan",
    "gn:population":0,
    "gn:timezone":"Asia/Shanghai",
    "iso:country":"CN",
    "name:ceb_x_preferred":[
        "Beiyuan"
    ],
    "name:swe_x_preferred":[
        "Beiyuan"
    ],
    "name:zho_x_preferred":[
        "\u5317\u56ed"
    ],
    "wof:name":"Beiyuan",
    "wof:placetype":"locality"
},
  "geometry": {"coordinates":[115.84387,32.0091],"type":"Point"}
}