{
  "type": "Feature",
  "properties": {
    "gn:admin1_code":"07",
    "gn:asciiname":"Banwei",
    "gn:country_code":"CN",
    "gn:dem":636,
    "gn:feature_class":"P",
    "gn:feature_code":"PPL",
    "gn:name":"Banwei",
    "gn:population":0,
    "gn:timezone":"Asia/Shanghai",
    "iso:country":"CN",
    "name:zho_x_preferred":[
        "\u5742\u5c3e"
    ],
    "wof:name":"Banwei",
    "wof:placetype":"locality"
},
  "geometry": {"coordinates":[118.46418,25.35535],"type":"Point"}
}