{
  "type": "Feature",
  "properties": {
    "gn:admin1_code":"09",
    "gn:asciiname":"Jiangji",
    "gn:cc2":"CN",
    "gn:country_code":"CN",
    "gn:dem":38,
    "gn:feature_class":"P",
    "gn:feature_code":"PPL",
    "gn:name":"Jiangji",
    "gn:population":0,
    "gn:timezone":"Asia/Shanghai",
    "iso:country":"CN",
    "name:und_x_variant":[
        "Chiang-chi",
        "Chiang-chia-chi",
        "Jiangji"
    ],
    "wof:name":"Jiangji",
    "wof:placetype":"locality"
},
  "geometry": {"coordinates":[115.75,32.28333],"type":"Point"}
}