{
  "type": "Feature",
  "properties": {
    "gn:admin1_code":"26.0",
    "gn:asciiname":"Suwangcun",
    "gn:country_code":"CN",
    "gn:dem":635,
    "gn:feature_class":"P",
    "gn:feature_code":"PPL",
    "gn:name":"Suwangcun",
    "gn:population":0,
    "gn:timezone":"Asia/Shanghai",
    "iso:country":"CN",
    "name:und_x_variant":[
        "\u82cf\u738b\u6751"
    ],
    "wof:name":"Suwangcun",
    "wof:placetype":"locality"
},
  "geometry": {"coordinates":[107.73611,33.26277],"type":"Point"}
}