{
  "type": "Feature",
  "properties": {
    "gn:admin1_code":"14.0",
    "gn:asciiname":"Guomeicun",
    "gn:country_code":"CN",
    "gn:dem":4373,
    "gn:feature_class":"P",
    "gn:feature_code":"PPL",
    "gn:name":"Guomeicun",
    "gn:population":0,
    "gn:timezone":"Asia/Urumqi",
    "iso:country":"CN",
    "name:zho_x_preferred":[
        "\u90ed\u6885\u6751"
    ],
    "wof:name":"Guomeicun",
    "wof:placetype":"locality"
},
  "geometry": {"coordinates":[91.76011,28.33503],"type":"Point"}
}