{
  "type": "Feature",
  "properties": {
    "gn:admin1_code":"24",
    "gn:asciiname":"Suoquanling",
    "gn:country_code":"CN",
    "gn:dem":1396,
    "gn:feature_class":"P",
    "gn:feature_code":"PPL",
    "gn:name":"Suoquanling",
    "gn:population":0,
    "gn:timezone":"Asia/Shanghai",
    "iso:country":"CN",
    "name:und_x_variant":[
        "Hs\u00fceh-ch\u2019\u00fcan-chen",
        "So-ch\u2019\u00fcan-ling",
        "Hs\u00fceh-ch\u2019\u00fcan-ling",
        "Suoquanling"
    ],
    "name:zho_x_preferred":[
        "\u7d22\u6cc9\u5cad"
    ],
    "wof:name":"Suoquanling",
    "wof:placetype":"locality"
},
  "geometry": {"coordinates":[112.16158,35.41411],"type":"Point"}
}