{
  "type": "Feature",
  "properties": {
    "gn:admin1_code":"21.0",
    "gn:asciiname":"Yin'erxian",
    "gn:country_code":"CN",
    "gn:dem":1844,
    "gn:feature_class":"P",
    "gn:feature_code":"PPL",
    "gn:name":"Yin\u2019erxian",
    "gn:population":0,
    "gn:timezone":"Asia/Shanghai",
    "iso:country":"CN",
    "name:und_x_variant":[
        "Yin\u2019erxian"
    ],
    "name:zho_x_preferred":[
        "\u56e0\u513f\u5c98"
    ],
    "wof:name":"Yin'erxian",
    "wof:placetype":"locality"
},
  "geometry": {"coordinates":[105.35899999999999,36.7743],"type":"Point"}
}