{
  "type": "Feature",
  "properties": {
    "gn:admin1_code":"21.0",
    "gn:asciiname":"Hongnancun",
    "gn:country_code":"CN",
    "gn:dem":1103,
    "gn:feature_class":"P",
    "gn:feature_code":"PPL",
    "gn:name":"Hongnancun",
    "gn:population":0,
    "gn:timezone":"Asia/Shanghai",
    "iso:country":"CN",
    "name:zho_x_preferred":[
        "\u6d2a\u5357\u6751"
    ],
    "wof:name":"Hongnancun",
    "wof:placetype":"locality"
},
  "geometry": {"coordinates":[106.27800000000001,38.7255],"type":"Point"}
}