{
  "type": "Feature",
  "properties": {
    "gn:admin1_code":"14.0",
    "gn:asciiname":"Aqing",
    "gn:country_code":"CN",
    "gn:dem":4860,
    "gn:feature_class":"P",
    "gn:feature_code":"PPL",
    "gn:name":"Aqing",
    "gn:population":0,
    "gn:timezone":"Asia/Urumqi",
    "iso:country":"CN",
    "name:zho_x_preferred":[
        "\u5509\u9752"
    ],
    "wof:name":"Aqing",
    "wof:placetype":"locality"
},
  "geometry": {"coordinates":[91.86118,31.83945],"type":"Point"}
}