{
  "type": "Feature",
  "properties": {
    "gn:admin1_code":"10",
    "gn:asciiname":"Shangqihao",
    "gn:country_code":"CN",
    "gn:dem":1268,
    "gn:feature_class":"P",
    "gn:feature_code":"PPLF",
    "gn:name":"Shangqihao",
    "gn:population":0,
    "gn:timezone":"Asia/Shanghai",
    "iso:country":"CN",
    "name:zho_x_preferred":[
        "\u4e0a\u4e03\u53f7"
    ],
    "wof:name":"Shangqihao",
    "wof:placetype":"locality"
},
  "geometry": {"coordinates":[117.6438,42.3772],"type":"Point"}
}