{
  "type": "Feature",
  "properties": {
    "gn:admin1_code":"5.0",
    "gn:asciiname":"Pengjialucun",
    "gn:country_code":"CN",
    "gn:dem":161,
    "gn:feature_class":"P",
    "gn:feature_code":"PPL",
    "gn:name":"Pengjialucun",
    "gn:population":0,
    "gn:timezone":"Asia/Shanghai",
    "iso:country":"CN",
    "name:zho_x_preferred":[
        "\u5f6d\u5bb6\u7089\u6751"
    ],
    "wof:name":"Pengjialucun",
    "wof:placetype":"locality"
},
  "geometry": {"coordinates":[125.43785,44.5506],"type":"Point"}
}