{
  "type": "Feature",
  "properties": {
    "gn:admin1_code":"11.0",
    "gn:asciiname":"Mulangxi",
    "gn:country_code":"CN",
    "gn:dem":502,
    "gn:feature_class":"P",
    "gn:feature_code":"PPL",
    "gn:name":"Mulangxi",
    "gn:population":0,
    "gn:timezone":"Asia/Shanghai",
    "iso:country":"CN",
    "name:zho_x_preferred":[
        "\u6728\u6994\u6eaa"
    ],
    "wof:name":"Mulangxi",
    "wof:placetype":"locality"
},
  "geometry": {"coordinates":[110.64378000000001,29.21098],"type":"Point"}
}