{
  "type": "Feature",
  "properties": {
    "gn:admin1_code":"25",
    "gn:asciiname":"Nanliuzhuang",
    "gn:country_code":"CN",
    "gn:dem":53,
    "gn:feature_class":"P",
    "gn:feature_code":"PPL",
    "gn:name":"Nanliuzhuang",
    "gn:population":0,
    "gn:timezone":"Asia/Shanghai",
    "iso:country":"CN",
    "name:zho_x_preferred":[
        "\u5357\u5218\u5e84"
    ],
    "wof:name":"Nanliuzhuang",
    "wof:placetype":"locality"
},
  "geometry": {"coordinates":[115.59399999999999,35.3406],"type":"Point"}
}