{
  "type": "Feature",
  "properties": {
    "gn:admin1_code":"25",
    "gn:asciiname":"Sunliuzhuang",
    "gn:country_code":"CN",
    "gn:dem":59,
    "gn:feature_class":"P",
    "gn:feature_code":"PPL",
    "gn:name":"Sunliuzhuang",
    "gn:population":0,
    "gn:timezone":"Asia/Shanghai",
    "iso:country":"CN",
    "name:zho_x_preferred":[
        "\u5b59\u5218\u5e84"
    ],
    "wof:name":"Sunliuzhuang",
    "wof:placetype":"locality"
},
  "geometry": {"coordinates":[115.238,35.1113],"type":"Point"}
}