{
  "type": "Feature",
  "properties": {
    "gn:admin1_code":"24.0",
    "gn:asciiname":"Wenjiazhuang",
    "gn:country_code":"CN",
    "gn:dem":1107,
    "gn:feature_class":"P",
    "gn:feature_code":"PPL",
    "gn:name":"Wenjiazhuang",
    "gn:population":0,
    "gn:timezone":"Asia/Shanghai",
    "iso:country":"CN",
    "name:zho_x_preferred":[
        "\u6587\u5bb6\u5e84"
    ],
    "wof:name":"Wenjiazhuang",
    "wof:placetype":"locality"
},
  "geometry": {"coordinates":[113.67197,39.76211],"type":"Point"}
}