{
  "type": "Feature",
  "properties": {
    "gn:admin1_code":"4.0",
    "gn:asciiname":"Xiaogengzhuang",
    "gn:country_code":"CN",
    "gn:dem":3,
    "gn:feature_class":"P",
    "gn:feature_code":"PPL",
    "gn:name":"Xiaogengzhuang",
    "gn:population":0,
    "gn:timezone":"Asia/Shanghai",
    "iso:country":"CN",
    "name:zho_x_preferred":[
        "Xiaogengzhuang"
    ],
    "name:zho_x_variant":[
        "\u5c0f\u803f\u5e84"
    ],
    "wof:name":"Xiaogengzhuang",
    "wof:placetype":"locality"
},
  "geometry": {"coordinates":[119.39002000000001,34.22149],"type":"Point"}
}