{
  "type": "Feature",
  "properties": {
    "gn:admin1_code":"15.0",
    "gn:asciiname":"Xinjiuzhuang",
    "gn:country_code":"CN",
    "gn:dem":2192,
    "gn:feature_class":"P",
    "gn:feature_code":"PPL",
    "gn:name":"Xinjiuzhuang",
    "gn:population":0,
    "gn:timezone":"Asia/Shanghai",
    "iso:country":"CN",
    "name:zho_x_preferred":[
        "\u65b0\u65e7\u5e84"
    ],
    "wof:name":"Xinjiuzhuang",
    "wof:placetype":"locality"
},
  "geometry": {"coordinates":[104.45,35.9553],"type":"Point"}
}