{
  "type": "Feature",
  "properties": {
    "gn:admin1_code":"26.0",
    "gn:asciiname":"Qiushutacun",
    "gn:country_code":"CN",
    "gn:dem":1142,
    "gn:feature_class":"P",
    "gn:feature_code":"PPL",
    "gn:name":"Qiushutacun",
    "gn:population":0,
    "gn:timezone":"Asia/Shanghai",
    "iso:country":"CN",
    "name:zho_x_preferred":[
        "\u79cb\u6811\u5854\u6751"
    ],
    "wof:name":"Qiushutacun",
    "wof:placetype":"locality"
},
  "geometry": {"coordinates":[109.53801,36.52757],"type":"Point"}
}