{
  "type": "Feature",
  "properties": {
    "gn:admin1_code":"32.0",
    "gn:asciiname":"Awazhong",
    "gn:country_code":"CN",
    "gn:dem":3478,
    "gn:feature_class":"P",
    "gn:feature_code":"PPL",
    "gn:name":"Awazhong",
    "gn:population":0,
    "gn:timezone":"Asia/Shanghai",
    "iso:country":"CN",
    "name:zho_x_preferred":[
        "\u963f\u6d3c\u4ef2"
    ],
    "wof:name":"Awazhong",
    "wof:placetype":"locality"
},
  "geometry": {"coordinates":[101.51000000000001,30.0429],"type":"Point"}
}