{
  "type": "Feature",
  "properties": {
    "gn:admin1_code":"2.0",
    "gn:asciiname":"Datou",
    "gn:country_code":"CN",
    "gn:dem":389,
    "gn:feature_class":"P",
    "gn:feature_code":"PPL",
    "gn:name":"Datou",
    "gn:population":0,
    "gn:timezone":"Asia/Shanghai",
    "iso:country":"CN",
    "name:zho_x_preferred":[
        "\u5927\u5934"
    ],
    "wof:name":"Datou",
    "wof:placetype":"locality"
},
  "geometry": {"coordinates":[120.60496999999999,28.19201],"type":"Point"}
}