{
  "type": "Feature",
  "properties": {
    "gn:admin1_code":"19.0",
    "gn:asciiname":"Daliujia Wobu",
    "gn:country_code":"CN",
    "gn:dem":185,
    "gn:feature_class":"P",
    "gn:feature_code":"PPL",
    "gn:name":"Daliujia Wobu",
    "gn:population":0,
    "gn:timezone":"Asia/Shanghai",
    "iso:country":"CN",
    "name:und_x_variant":[
        "Daliujiawobao",
        "Daliujia Wobu"
    ],
    "name:zho_x_preferred":[
        "\u5927\u5218\u5bb6\u7a9d\u5821"
    ],
    "wof:name":"Daliujia Wobu",
    "wof:placetype":"locality"
},
  "geometry": {"coordinates":[122.71595000000001,42.75268],"type":"Point"}
}