{
  "type": "Feature",
  "properties": {
    "gn:admin1_code":"4.0",
    "gn:asciiname":"Guoyuantou",
    "gn:country_code":"CN",
    "gn:dem":3,
    "gn:feature_class":"P",
    "gn:feature_code":"PPL",
    "gn:name":"Guoyuantou",
    "gn:population":0,
    "gn:timezone":"Asia/Shanghai",
    "iso:country":"CN",
    "name:zho_x_preferred":[
        "Guoyuantou"
    ],
    "name:zho_x_variant":[
        "\u679c\u56ed\u5934"
    ],
    "wof:name":"Guoyuantou",
    "wof:placetype":"locality"
},
  "geometry": {"coordinates":[119.91482999999999,33.50367],"type":"Point"}
}