{
  "type": "Feature",
  "properties": {
    "gn:admin1_code":"32.0",
    "gn:asciiname":"Fenghuang",
    "gn:country_code":"CN",
    "gn:dem":314,
    "gn:feature_class":"P",
    "gn:feature_code":"PPL",
    "gn:name":"Fenghuang",
    "gn:population":0,
    "gn:timezone":"Asia/Shanghai",
    "iso:country":"CN",
    "name:ara_x_preferred":[
        "\u0641\u0646\u063a\u0647\u0648\u0627\u0646\u063a"
    ],
    "name:aze_x_preferred":[
        "\u00c7in feniksi"
    ],
    "name:cat_x_preferred":[
        "Fenghuang"
    ],
    "name:cdo_x_preferred":[
        "H\u00f4ng-hu\u00f2ng"
    ],
    "name:ces_x_preferred":[
        "Feng-chuang"
    ],
    "name:deu_x_preferred":[
        "Fenghuang"
    ],
    "name:fra_x_preferred":[
        "Fenghuang"
    ],
    "name:hak_x_preferred":[
        "Fung-f\u00f2ng"
    ],
    "name:hrv_x_preferred":[
        "Fenghuang"
    ],
    "name:hun_x_preferred":[
        "Feng-huang"
    ],
    "name:ind_x_preferred":[
        "Fenghuang"
    ],
    "name:isl_x_preferred":[
        "F\u00e8nghu\u00e1ng"
    ],
    "name:ita_x_preferred":[
        "Fenghuang"
    ],
    "name:mlg_x_preferred":[
        "Fenghuang"
    ],
    "name:msa_x_preferred":[
        "Fenghuang"
    ],
    "name:nld_x_preferred":[
        "Feng Huang"
    ],
    "name:nor_x_preferred":[
        "Fenghuang"
    ],
    "name:pol_x_preferred":[
        "Fenghuang"
    ],
    "name:por_x_preferred":[
        "Fenghuang"
    ],
    "name:rus_x_preferred":[
        "\u041a\u0438\u0442\u0430\u0439\u0441\u043a\u0438\u0439 \u0444\u0435\u043d\u0438\u043a\u0441"
    ],
    "name:slk_x_preferred":[
        "Feng-chuang"
    ],
    "name:spa_x_preferred":[
        "Fenghuang"
    ],
    "name:swe_x_preferred":[
        "Fenghuang"
    ],
    "name:tur_x_preferred":[
        "Fenghuang"
    ],
    "name:ukr_x_preferred":[
        "\u041a\u0438\u0442\u0430\u0439\u0441\u044c\u043a\u0438\u0439 \u0444\u0435\u043d\u0456\u043a\u0441"
    ],
    "name:vie_x_preferred":[
        "Ph\u01b0\u1ee3ng ho\u00e0ng"
    ],
    "name:war_x_preferred":[
        "Fenghuang"
    ],
    "name:zha_x_preferred":[
        "Roegfunghvuengz"
    ],
    "name:zho_x_preferred":[
        "\u51e4\u51f0"
    ],
    "wof:name":"Fenghuang",
    "wof:placetype":"locality"
},
  "geometry": {"coordinates":[104.75163000000001,29.36587],"type":"Point"}
}