{
  "type": "Feature",
  "properties": {
    "gn:admin1_code":"30.0",
    "gn:asciiname":"Liubiao",
    "gn:country_code":"CN",
    "gn:dem":209,
    "gn:feature_class":"P",
    "gn:feature_code":"PPL",
    "gn:name":"Liubiao",
    "gn:population":0,
    "gn:timezone":"Asia/Urumqi",
    "iso:country":"CN",
    "name:zho_x_preferred":[
        "\u516d\u4ff5"
    ],
    "wof:name":"Liubiao",
    "wof:placetype":"locality"
},
  "geometry": {"coordinates":[110.8476,22.34514],"type":"Point"}
}