{
  "type": "Feature",
  "properties": {
    "gn:admin1_code":"14.0",
    "gn:asciiname":"Niangge",
    "gn:country_code":"CN",
    "gn:dem":2072,
    "gn:feature_class":"P",
    "gn:feature_code":"PPL",
    "gn:name":"Niangge",
    "gn:population":0,
    "gn:timezone":"Asia/Urumqi",
    "iso:country":"CN",
    "name:zho_x_preferred":[
        "\u5a18\u683c"
    ],
    "wof:name":"Niangge",
    "wof:placetype":"locality"
},
  "geometry": {"coordinates":[96.61287,28.98746],"type":"Point"}
}