{
  "type": "Feature",
  "properties": {
    "gn:admin1_code":"13.0",
    "gn:asciiname":"Tuokayi",
    "gn:country_code":"CN",
    "gn:dem":2043,
    "gn:feature_class":"P",
    "gn:feature_code":"PPL",
    "gn:name":"Tuokayi",
    "gn:population":0,
    "gn:timezone":"Asia/Shanghai",
    "iso:country":"CN",
    "name:zho_x_preferred":[
        "\u6258\u5580\u4f9d"
    ],
    "wof:name":"Tuokayi",
    "wof:placetype":"locality"
},
  "geometry": {"coordinates":[77.84618,37.35177],"type":"Point"}
}