{
  "type": "Feature",
  "properties": {
    "gn:admin1_code":"15.0",
    "gn:asciiname":"Jiaji",
    "gn:country_code":"CN",
    "gn:dem":1894,
    "gn:feature_class":"P",
    "gn:feature_code":"PPL",
    "gn:name":"Jiaji",
    "gn:population":0,
    "gn:timezone":"Asia/Shanghai",
    "iso:country":"CN",
    "name:zho_x_preferred":[
        "\u8d3e\u96c6"
    ],
    "wof:name":"Jiaji",
    "wof:placetype":"locality"
},
  "geometry": {"coordinates":[106.23099999999999,34.6541],"type":"Point"}
}