{
  "type": "Feature",
  "properties": {
    "gn:admin1_code":"4.0",
    "gn:asciiname":"Xiaowan",
    "gn:country_code":"CN",
    "gn:dem":0,
    "gn:feature_class":"P",
    "gn:feature_code":"PPL",
    "gn:name":"Xiaowan",
    "gn:population":0,
    "gn:timezone":"Asia/Shanghai",
    "iso:country":"CN",
    "name:zho_x_preferred":[
        "Xiaowan"
    ],
    "name:zho_x_variant":[
        "\u5c0f\u6e7e"
    ],
    "wof:name":"Xiaowan",
    "wof:placetype":"locality"
},
  "geometry": {"coordinates":[119.81581,33.76577],"type":"Point"}
}