{
  "type": "Feature",
  "properties": {
    "gn:admin1_code":"30.0",
    "gn:asciiname":"Sanshenggong",
    "gn:country_code":"CN",
    "gn:dem":96,
    "gn:feature_class":"P",
    "gn:feature_code":"PPL",
    "gn:name":"Sanshenggong",
    "gn:population":0,
    "gn:timezone":"Asia/Shanghai",
    "iso:country":"CN",
    "name:zho_x_preferred":[
        "\u4e09\u5723\u5bab"
    ],
    "wof:name":"Sanshenggong",
    "wof:placetype":"locality"
},
  "geometry": {"coordinates":[114.55956,22.83875],"type":"Point"}
}