{
  "type": "Feature",
  "properties": {
    "gn:admin1_code":"9.0",
    "gn:asciiname":"Hexima",
    "gn:country_code":"CN",
    "gn:dem":168,
    "gn:feature_class":"P",
    "gn:feature_code":"PPL",
    "gn:name":"Hexima",
    "gn:population":0,
    "gn:timezone":"Asia/Shanghai",
    "iso:country":"CN",
    "name:zho_x_preferred":[
        "\u6cb3\u897f\u9a6c"
    ],
    "wof:name":"Hexima",
    "wof:placetype":"locality"
},
  "geometry": {"coordinates":[113.5859,34.53551],"type":"Point"}
}