{
  "type": "Feature",
  "properties": {
    "gn:admin1_code":"18",
    "gn:asciiname":"Rongxiao",
    "gn:country_code":"CN",
    "gn:dem":975,
    "gn:feature_class":"P",
    "gn:feature_code":"PPL",
    "gn:name":"Rongxiao",
    "gn:population":0,
    "gn:timezone":"Asia/Shanghai",
    "iso:country":"CN",
    "name:zho_x_preferred":[
        "\u5197\u6d88"
    ],
    "wof:name":"Rongxiao",
    "wof:placetype":"locality"
},
  "geometry": {"coordinates":[105.782,25.088],"type":"Point"}
}