{
  "type": "Feature",
  "properties": {
    "gn:admin1_code":"18",
    "gn:asciiname":"Shuixi",
    "gn:country_code":"CN",
    "gn:dem":1011,
    "gn:feature_class":"P",
    "gn:feature_code":"PPL",
    "gn:name":"Shuixi",
    "gn:population":0,
    "gn:timezone":"Asia/Shanghai",
    "iso:country":"CN",
    "name:zho_x_preferred":[
        "\u6c34\u6eaa"
    ],
    "wof:name":"Shuixi",
    "wof:placetype":"locality"
},
  "geometry": {"coordinates":[108.223,28.5696],"type":"Point"}
}