{
  "type": "Feature",
  "properties": {
    "gn:admin1_code":"14.0",
    "gn:asciiname":"Nabucun",
    "gn:country_code":"CN",
    "gn:dem":4167,
    "gn:feature_class":"P",
    "gn:feature_code":"PPL",
    "gn:name":"Nabucun",
    "gn:population":0,
    "gn:timezone":"Asia/Urumqi",
    "iso:country":"CN",
    "name:zho_x_preferred":[
        "\u90a3\u5e03\u6751"
    ],
    "wof:name":"Nabucun",
    "wof:placetype":"locality"
},
  "geometry": {"coordinates":[96.19297,31.37541],"type":"Point"}
}