{
  "type": "Feature",
  "properties": {
    "gn:admin1_code":"9.0",
    "gn:asciiname":"Litieying",
    "gn:country_code":"CN",
    "gn:dem":88,
    "gn:feature_class":"P",
    "gn:feature_code":"PPL",
    "gn:name":"Litieying",
    "gn:population":0,
    "gn:timezone":"Asia/Shanghai",
    "iso:country":"CN",
    "name:zho_x_preferred":[
        "\u674e\u94c1\u8425"
    ],
    "wof:name":"Litieying",
    "wof:placetype":"locality"
},
  "geometry": {"coordinates":[112.41406000000001,32.52213],"type":"Point"}
}