{
  "type": "Feature",
  "properties": {
    "gn:admin1_code":"16.0",
    "gn:asciiname":"Fudan",
    "gn:country_code":"CN",
    "gn:dem":120,
    "gn:feature_class":"P",
    "gn:feature_code":"PPL",
    "gn:name":"Fudan",
    "gn:population":0,
    "gn:timezone":"Asia/Shanghai",
    "iso:country":"CN",
    "name:zho_x_preferred":[
        "\u590d\u65e6"
    ],
    "wof:name":"Fudan",
    "wof:placetype":"locality"
},
  "geometry": {"coordinates":[109.51300000000001,23.5381],"type":"Point"}
}