{
  "type": "Feature",
  "properties": {
    "gn:admin1_code":"15.0",
    "gn:asciiname":"Yaowa",
    "gn:country_code":"CN",
    "gn:dem":1437,
    "gn:feature_class":"P",
    "gn:feature_code":"PPL",
    "gn:name":"Yaowa",
    "gn:population":0,
    "gn:timezone":"Asia/Shanghai",
    "iso:country":"CN",
    "name:zho_x_preferred":[
        "\u59da\u6d3c"
    ],
    "wof:name":"Yaowa",
    "wof:placetype":"locality"
},
  "geometry": {"coordinates":[106.96299999999999,35.2685],"type":"Point"}
}