{
  "type": "Feature",
  "properties": {
    "gn:admin1_code":"19.0",
    "gn:asciiname":"Shengjiagou",
    "gn:country_code":"CN",
    "gn:dem":123,
    "gn:feature_class":"P",
    "gn:feature_code":"PPL",
    "gn:name":"Shengjiagou",
    "gn:population":0,
    "gn:timezone":"Asia/Shanghai",
    "iso:country":"CN",
    "name:zho_x_preferred":[
        "\u76db\u5bb6\u6c9f"
    ],
    "wof:name":"Shengjiagou",
    "wof:placetype":"locality"
},
  "geometry": {"coordinates":[121.96299999999999,39.5947],"type":"Point"}
}