{
  "type": "Feature",
  "properties": {
    "gn:admin1_code":"26.0",
    "gn:asciiname":"Dabaozhai",
    "gn:country_code":"CN",
    "gn:dem":1191,
    "gn:feature_class":"P",
    "gn:feature_code":"PPL",
    "gn:name":"Dabaozhai",
    "gn:population":0,
    "gn:timezone":"Asia/Shanghai",
    "iso:country":"CN",
    "name:zho_x_preferred":[
        "\u5927\u5305\u5be8"
    ],
    "wof:name":"Dabaozhai",
    "wof:placetype":"locality"
},
  "geometry": {"coordinates":[108.33157,32.37094],"type":"Point"}
}