{
  "type": "Feature",
  "properties": {
    "gn:admin1_code":"13",
    "gn:asciiname":"Bayituokayi",
    "gn:country_code":"CN",
    "gn:dem":1238,
    "gn:feature_class":"P",
    "gn:feature_code":"PPL",
    "gn:name":"Bayituokayi",
    "gn:population":0,
    "gn:timezone":"Asia/Shanghai",
    "iso:country":"CN",
    "name:zho_x_preferred":[
        "\u5df4\u4f9d\u6258\u5580\u4f9d"
    ],
    "wof:name":"Bayituokayi",
    "wof:placetype":"locality"
},
  "geometry": {"coordinates":[76.35677,39.40465],"type":"Point"}
}