{
  "type": "Feature",
  "properties": {
    "gn:admin1_code":"32.0",
    "gn:asciiname":"Shuanghekou",
    "gn:country_code":"CN",
    "gn:dem":2280,
    "gn:feature_class":"P",
    "gn:feature_code":"PPL",
    "gn:name":"Shuanghekou",
    "gn:population":0,
    "gn:timezone":"Asia/Shanghai",
    "iso:country":"CN",
    "name:zho_x_preferred":[
        "\u53cc\u6cb3\u53e3"
    ],
    "wof:name":"Shuanghekou",
    "wof:placetype":"locality"
},
  "geometry": {"coordinates":[103.045,28.7181],"type":"Point"}
}