{
  "type": "Feature",
  "properties": {
    "gn:admin1_code":"20.0",
    "gn:asciiname":"Donggouzi",
    "gn:country_code":"CN",
    "gn:dem":1648,
    "gn:feature_class":"P",
    "gn:feature_code":"PPL",
    "gn:name":"Donggouzi",
    "gn:population":0,
    "gn:timezone":"Asia/Shanghai",
    "iso:country":"CN",
    "name:und_x_variant":[
        "\u4e1c\u6c9f\u5b50"
    ],
    "wof:name":"Donggouzi",
    "wof:placetype":"locality"
},
  "geometry": {"coordinates":[110.79083,40.90096],"type":"Point"}
}