{
  "type": "Feature",
  "properties": {
    "gn:admin1_code":"15.0",
    "gn:asciiname":"Guzhu",
    "gn:country_code":"CN",
    "gn:dem":2204,
    "gn:feature_class":"P",
    "gn:feature_code":"PPL",
    "gn:name":"Guzhu",
    "gn:population":0,
    "gn:timezone":"Asia/Shanghai",
    "iso:country":"CN",
    "name:jpn_x_preferred":[
        "\u5b64\u7af9\u56fd"
    ],
    "name:kor_x_preferred":[
        "\uace0\uc8fd\uad6d"
    ],
    "name:vie_x_preferred":[
        "C\u00f4 Tr\u00fac"
    ],
    "name:zho_x_preferred":[
        "\u56fa\u4e3b"
    ],
    "name:zho_x_variant":[
        "\u5b64\u7af9\u56fd"
    ],
    "wof:name":"Guzhu",
    "wof:placetype":"locality"
},
  "geometry": {"coordinates":[104.43513,33.92446],"type":"Point"}
}