{
  "type": "Feature",
  "properties": {
    "gn:admin1_code":"15.0",
    "gn:asciiname":"Guzhu",
    "gn:country_code":"CN",
    "gn:dem":2204,
    "gn:feature_class":"P",
    "gn:feature_code":"PPL",
    "gn:name":"Guzhu",
    "gn:population":0,
    "gn:timezone":"Asia/Shanghai",
    "iso:country":"CN",
    "name:und_x_variant":[
        "\u56fa\u4e3b"
    ],
    "name:zho_x_preferred":[
        "\u56fa\u4e3b"
    ],
    "wof:name":"Guzhu",
    "wof:placetype":"locality"
},
  "geometry": {"coordinates":[104.43513,33.92446],"type":"Point"}
}