{
  "type": "Feature",
  "properties": {
    "gn:admin1_code":"10",
    "gn:asciiname":"Yucheng",
    "gn:country_code":"CN",
    "gn:dem":14,
    "gn:feature_class":"P",
    "gn:feature_code":"PPL",
    "gn:name":"Yucheng",
    "gn:population":0,
    "gn:timezone":"Asia/Shanghai",
    "iso:country":"CN",
    "name:ceb_x_preferred":[
        "Yucheng"
    ],
    "name:deu_x_preferred":[
        "Yucheng"
    ],
    "name:fra_x_preferred":[
        "Yucheng"
    ],
    "name:mlg_x_preferred":[
        "Yucheng"
    ],
    "name:nor_x_preferred":[
        "Yucheng"
    ],
    "name:pol_x_preferred":[
        "Yucheng"
    ],
    "name:rus_x_preferred":[
        "\u042e\u0439\u0447\u044d\u043d"
    ],
    "name:swe_x_preferred":[
        "Yucheng"
    ],
    "name:zho_x_preferred":[
        "\u5fa1\u57ce"
    ],
    "wof:name":"Yucheng",
    "wof:placetype":"locality"
},
  "geometry": {"coordinates":[115.669,38.8205],"type":"Point"}
}