{
  "type": "Feature",
  "properties": {
    "gn:admin1_code":"14",
    "gn:asciiname":"Xiaxiong",
    "gn:country_code":"CN",
    "gn:dem":4703,
    "gn:feature_class":"P",
    "gn:feature_code":"PPL",
    "gn:name":"Xiaxiong",
    "gn:population":0,
    "gn:timezone":"Asia/Urumqi",
    "iso:country":"CN",
    "name:zho_x_preferred":[
        "\u590f\u96c4"
    ],
    "wof:name":"Xiaxiong",
    "wof:placetype":"locality"
},
  "geometry": {"coordinates":[90.05929999999999,28.9175],"type":"Point"}
}