{
  "type": "Feature",
  "properties": {
    "gn:admin1_code":"5.0",
    "gn:asciiname":"Yujiadiancun",
    "gn:country_code":"CN",
    "gn:dem":213,
    "gn:feature_class":"P",
    "gn:feature_code":"PPL",
    "gn:name":"Yujiadiancun",
    "gn:population":0,
    "gn:timezone":"Asia/Shanghai",
    "iso:country":"CN",
    "name:zho_x_preferred":[
        "\u4e8e\u5bb6\u5e97\u6751"
    ],
    "wof:name":"Yujiadiancun",
    "wof:placetype":"locality"
},
  "geometry": {"coordinates":[125.43496,44.23263],"type":"Point"}
}