{
  "type": "Feature",
  "properties": {
    "gn:admin1_code":"04",
    "gn:asciiname":"Huangqiaocun",
    "gn:country_code":"CN",
    "gn:dem":5,
    "gn:feature_class":"P",
    "gn:feature_code":"PPL",
    "gn:name":"Huangqiaocun",
    "gn:population":0,
    "gn:timezone":"Asia/Shanghai",
    "iso:country":"CN",
    "name:und_x_variant":[
        "Huangqiao",
        "\u9ec4\u6865",
        "Huang-ch\u2019iao-chen",
        "Huangqiaocun"
    ],
    "name:zho_x_preferred":[
        "\u9ec4\u6865\u6751"
    ],
    "wof:name":"Huangqiaocun",
    "wof:placetype":"locality"
},
  "geometry": {"coordinates":[120.21129999999999,31.78131],"type":"Point"}
}