{
  "type": "Feature",
  "properties": {
    "gn:admin1_code":"8.0",
    "gn:asciiname":"Shuangxingcun",
    "gn:country_code":"CN",
    "gn:dem":252,
    "gn:feature_class":"P",
    "gn:feature_code":"PPL",
    "gn:name":"Shuangxingcun",
    "gn:population":0,
    "gn:timezone":"Asia/Shanghai",
    "iso:country":"CN",
    "name:zho_x_preferred":[
        "\u53cc\u5174\u6751"
    ],
    "wof:name":"Shuangxingcun",
    "wof:placetype":"locality"
},
  "geometry": {"coordinates":[127.05087,47.59432],"type":"Point"}
}