{
  "type": "Feature",
  "properties": {
    "gn:admin1_code":"3.0",
    "gn:asciiname":"Shizhuang",
    "gn:country_code":"CN",
    "gn:dem":82,
    "gn:feature_class":"P",
    "gn:feature_code":"PPL",
    "gn:name":"Shizhuang",
    "gn:population":0,
    "gn:timezone":"Asia/Shanghai",
    "iso:country":"CN",
    "name:und_x_variant":[
        "\u77f3\u5e84",
        "Shizhuangxiang",
        "\u77f3\u5e84\u4e61"
    ],
    "wof:name":"Shizhuang",
    "wof:placetype":"locality"
},
  "geometry": {"coordinates":[116.03023,27.74616],"type":"Point"}
}