{
  "type": "Feature",
  "properties": {
    "gn:admin1_code":"15.0",
    "gn:asciiname":"Taping",
    "gn:country_code":"CN",
    "gn:dem":2012,
    "gn:feature_class":"P",
    "gn:feature_code":"PPL",
    "gn:name":"Taping",
    "gn:population":0,
    "gn:timezone":"Asia/Shanghai",
    "iso:country":"CN",
    "name:zho_x_preferred":[
        "\u5854\u576a"
    ],
    "wof:name":"Taping",
    "wof:placetype":"locality"
},
  "geometry": {"coordinates":[103.01000000000001,35.8198],"type":"Point"}
}