{
  "type": "Feature",
  "properties": {
    "gn:admin1_code":"14.0",
    "gn:asciiname":"Mutongcun",
    "gn:country_code":"CN",
    "gn:dem":4702,
    "gn:feature_class":"P",
    "gn:feature_code":"PPL",
    "gn:name":"Mutongcun",
    "gn:population":0,
    "gn:timezone":"Asia/Urumqi",
    "iso:country":"CN",
    "name:zho_x_preferred":[
        "\u6728\u540c\u6751"
    ],
    "wof:name":"Mutongcun",
    "wof:placetype":"locality"
},
  "geometry": {"coordinates":[90.16001,31.34153],"type":"Point"}
}