{
  "type": "Feature",
  "properties": {
    "gn:admin1_code":"26",
    "gn:asciiname":"Dashichuancun",
    "gn:country_code":"CN",
    "gn:dem":967,
    "gn:feature_class":"P",
    "gn:feature_code":"PPL",
    "gn:name":"Dashichuancun",
    "gn:population":0,
    "gn:timezone":"Asia/Shanghai",
    "iso:country":"CN",
    "name:und_x_variant":[
        "Ta-shih",
        "Dashi",
        "Ta-shih-ch\u2019uan",
        "Dashichuan",
        "Dashichuancun"
    ],
    "name:zho_x_preferred":[
        "\u5927\u5e02\u5ddd\u6751"
    ],
    "wof:name":"Dashichuancun",
    "wof:placetype":"locality"
},
  "geometry": {"coordinates":[108.09573,32.59562],"type":"Point"}
}