{
  "type": "Feature",
  "properties": {
    "gn:admin1_code":"12.0",
    "gn:asciiname":"Chenjiaqiao",
    "gn:country_code":"CN",
    "gn:dem":31,
    "gn:feature_class":"P",
    "gn:feature_code":"PPL",
    "gn:name":"Chenjiaqiao",
    "gn:population":0,
    "gn:timezone":"Asia/Shanghai",
    "iso:country":"CN",
    "name:zho_x_preferred":[
        "Chenjiaqiao"
    ],
    "name:zho_x_variant":[
        "\u9648\u5bb6\u6865"
    ],
    "wof:name":"Chenjiaqiao",
    "wof:placetype":"locality"
},
  "geometry": {"coordinates":[112.75248000000001,30.52161],"type":"Point"}
}