{
  "type": "Feature",
  "properties": {
    "gn:admin1_code":"8.0",
    "gn:asciiname":"Dongshengcun",
    "gn:country_code":"CN",
    "gn:dem":78,
    "gn:feature_class":"P",
    "gn:feature_code":"PPL",
    "gn:name":"Dongshengcun",
    "gn:population":0,
    "gn:timezone":"Asia/Shanghai",
    "iso:country":"CN",
    "name:zho_x_preferred":[
        "\u4e1c\u80dc\u6751"
    ],
    "wof:name":"Dongshengcun",
    "wof:placetype":"locality"
},
  "geometry": {"coordinates":[130.39245,46.88336],"type":"Point"}
}