{
  "type": "Feature",
  "properties": {
    "gn:admin1_code":"29.0",
    "gn:asciiname":"Zhiluo",
    "gn:country_code":"CN",
    "gn:dem":1740,
    "gn:feature_class":"P",
    "gn:feature_code":"PPL",
    "gn:name":"Zhiluo",
    "gn:population":0,
    "gn:timezone":"Asia/Shanghai",
    "iso:country":"CN",
    "name:zho_x_preferred":[
        "\u77e5\u6d1b"
    ],
    "wof:name":"Zhiluo",
    "wof:placetype":"locality"
},
  "geometry": {"coordinates":[98.88760000000001,27.1442],"type":"Point"}
}