{
  "type": "Feature",
  "properties": {
    "gn:admin1_code":"18.0",
    "gn:asciiname":"Houzhai",
    "gn:country_code":"CN",
    "gn:dem":1153,
    "gn:feature_class":"P",
    "gn:feature_code":"PPL",
    "gn:name":"Houzhai",
    "gn:population":0,
    "gn:timezone":"Asia/Shanghai",
    "iso:country":"CN",
    "name:zho_x_preferred":[
        "\u540e\u5be8"
    ],
    "wof:name":"Houzhai",
    "wof:placetype":"locality"
},
  "geometry": {"coordinates":[107.02200000000001,26.7918],"type":"Point"}
}