{
  "type": "Feature",
  "properties": {
    "gn:admin1_code":"32.0",
    "gn:asciiname":"Duriluo",
    "gn:country_code":"CN",
    "gn:dem":2604,
    "gn:feature_class":"P",
    "gn:feature_code":"PPL",
    "gn:name":"Duriluo",
    "gn:population":0,
    "gn:timezone":"Asia/Shanghai",
    "iso:country":"CN",
    "name:zho_x_preferred":[
        "\u5835\u65e5\u6d1b"
    ],
    "wof:name":"Duriluo",
    "wof:placetype":"locality"
},
  "geometry": {"coordinates":[103.13800000000001,27.7594],"type":"Point"}
}