{
  "type": "Feature",
  "properties": {
    "gn:admin1_code":"26",
    "gn:asciiname":"Raofeng",
    "gn:cc2":"CN",
    "gn:country_code":"CN",
    "gn:dem":710,
    "gn:feature_class":"P",
    "gn:feature_code":"PPL",
    "gn:name":"Raofeng",
    "gn:population":0,
    "gn:timezone":"Asia/Shanghai",
    "iso:country":"CN",
    "name:und_x_variant":[
        "Jao-feng-chen",
        "Jao-feng",
        "Jao-feng-chieh",
        "Raofeng"
    ],
    "wof:name":"Raofeng",
    "wof:placetype":"locality"
},
  "geometry": {"coordinates":[108.15222,33.16889],"type":"Point"}
}