{
  "type": "Feature",
  "properties": {
    "gn:admin1_code":"16.0",
    "gn:asciiname":"Kongduichong",
    "gn:country_code":"CN",
    "gn:dem":133,
    "gn:feature_class":"P",
    "gn:feature_code":"PPL",
    "gn:name":"Kongduichong",
    "gn:population":0,
    "gn:timezone":"Asia/Shanghai",
    "iso:country":"CN",
    "name:zho_x_preferred":[
        "\u5b54\u5bf9\u51b2"
    ],
    "wof:name":"Kongduichong",
    "wof:placetype":"locality"
},
  "geometry": {"coordinates":[110.94199999999999,23.0639],"type":"Point"}
}