{
  "type": "Feature",
  "properties": {
    "gn:admin1_code":"32.0",
    "gn:asciiname":"Ertuo",
    "gn:country_code":"CN",
    "gn:dem":2371,
    "gn:feature_class":"P",
    "gn:feature_code":"PPL",
    "gn:name":"Ertuo",
    "gn:population":0,
    "gn:timezone":"Asia/Shanghai",
    "iso:country":"CN",
    "name:zho_x_preferred":[
        "\u5c14\u62d6"
    ],
    "wof:name":"Ertuo",
    "wof:placetype":"locality"
},
  "geometry": {"coordinates":[103.13800000000001,28.446],"type":"Point"}
}