{
  "type": "Feature",
  "properties": {
    "gn:admin1_code":"23.0",
    "gn:asciiname":"Guiwang",
    "gn:country_code":"CN",
    "gn:dem":7,
    "gn:feature_class":"P",
    "gn:feature_code":"PPL",
    "gn:name":"Guiwang",
    "gn:population":0,
    "gn:timezone":"Asia/Shanghai",
    "iso:country":"CN",
    "name:zho_x_preferred":[
        "Guiwang"
    ],
    "name:zho_x_variant":[
        "\u5f52\u738b"
    ],
    "wof:name":"Guiwang",
    "wof:placetype":"locality"
},
  "geometry": {"coordinates":[121.35154,31.36239],"type":"Point"}
}