{
  "type": "Feature",
  "properties": {
    "gn:admin1_code":"30.0",
    "gn:asciiname":"Yangmeishan",
    "gn:country_code":"CN",
    "gn:dem":438,
    "gn:feature_class":"P",
    "gn:feature_code":"PPL",
    "gn:name":"Yangmeishan",
    "gn:population":0,
    "gn:timezone":"Asia/Shanghai",
    "iso:country":"CN",
    "name:zho_x_preferred":[
        "Yangmeishan"
    ],
    "name:zho_x_variant":[
        "\u6768\u6885\u5c71"
    ],
    "wof:name":"Yangmeishan",
    "wof:placetype":"locality"
},
  "geometry": {"coordinates":[113.01833000000001,25.15694],"type":"Point"}
}