{
  "type": "Feature",
  "properties": {
    "gn:admin1_code":"20.0",
    "gn:asciiname":"Zhonghou",
    "gn:country_code":"CN",
    "gn:dem":276,
    "gn:feature_class":"P",
    "gn:feature_code":"PPL",
    "gn:name":"Zhonghou",
    "gn:population":0,
    "gn:timezone":"Asia/Shanghai",
    "iso:country":"CN",
    "name:zho_x_preferred":[
        "\u4e2d\u539a"
    ],
    "wof:name":"Zhonghou",
    "wof:placetype":"locality"
},
  "geometry": {"coordinates":[123.32201000000001,48.05221],"type":"Point"}
}