{
  "type": "Feature",
  "properties": {
    "gn:admin1_code":"10",
    "gn:asciiname":"Dongmaqun",
    "gn:country_code":"CN",
    "gn:dem":1352,
    "gn:feature_class":"P",
    "gn:feature_code":"PPL",
    "gn:name":"Dongmaqun",
    "gn:population":0,
    "gn:timezone":"Asia/Shanghai",
    "iso:country":"CN",
    "name:zho_x_preferred":[
        "\u4e1c\u9a6c\u7fa4"
    ],
    "wof:name":"Dongmaqun",
    "wof:placetype":"locality"
},
  "geometry": {"coordinates":[116.36872,41.98971],"type":"Point"}
}