{
  "type": "Feature",
  "properties": {
    "gn:admin1_code":"7",
    "gn:asciiname":"Baidu",
    "gn:country_code":"CN",
    "gn:dem":302,
    "gn:feature_class":"P",
    "gn:feature_code":"PPL",
    "gn:name":"Baidu",
    "gn:population":0,
    "gn:timezone":"Asia/Shanghai",
    "iso:country":"CN",
    "name:ara_x_preferred":[
        "\u0628\u0627\u064a\u062f\u0648"
    ],
    "name:azb_x_preferred":[
        "\u0628\u0627\u06cc\u062f\u0648"
    ],
    "name:bel_x_preferred":[
        "Baidu"
    ],
    "name:ben_x_preferred":[
        "\u09ac\u09be\u0987\u09a1\u09c1"
    ],
    "name:cat_x_preferred":[
        "Baidu"
    ],
    "name:ces_x_preferred":[
        "Baidu"
    ],
    "name:dan_x_preferred":[
        "Baidu"
    ],
    "name:deu_x_preferred":[
        "Baidu"
    ],
    "name:dty_x_preferred":[
        "\u092c\u0948\u0926\u0941"
    ],
    "name:ell_x_preferred":[
        "Baidu"
    ],
    "name:epo_x_preferred":[
        "Baidu"
    ],
    "name:est_x_preferred":[
        "Baidu"
    ],
    "name:fas_x_preferred":[
        "\u0628\u0627\u06cc\u062f\u0648"
    ],
    "name:fin_x_preferred":[
        "Baidu"
    ],
    "name:fra_x_preferred":[
        "Baidu"
    ],
    "name:glg_x_preferred":[
        "Baidu"
    ],
    "name:heb_x_preferred":[
        "Baidu"
    ],
    "name:hin_x_preferred":[
        "\u092c\u0948\u0926\u0942"
    ],
    "name:hun_x_preferred":[
        "Baidu"
    ],
    "name:hye_x_preferred":[
        "Baidu"
    ],
    "name:ind_x_preferred":[
        "Baidu"
    ],
    "name:ita_x_preferred":[
        "Baidu"
    ],
    "name:kan_x_preferred":[
        "\u0cac\u0cc8\u0ca6\u0cc1"
    ],
    "name:kat_x_preferred":[
        "Baidu"
    ],
    "name:kir_x_preferred":[
        "Baidu"
    ],
    "name:kor_x_preferred":[
        "\ubc14\uc774\ub450"
    ],
    "name:lit_x_preferred":[
        "Baidu"
    ],
    "name:mal_x_preferred":[
        "\u0d2c\u0d48\u0d26\u0d41"
    ],
    "name:msa_x_preferred":[
        "Baidu"
    ],
    "name:nep_x_preferred":[
        "\u092c\u0948\u0926\u0941"
    ],
    "name:nld_x_preferred":[
        "Baidu"
    ],
    "name:nor_x_preferred":[
        "Baidu"
    ],
    "name:oci_x_preferred":[
        "Baidu"
    ],
    "name:pol_x_preferred":[
        "Baidu"
    ],
    "name:por_x_preferred":[
        "Baidu"
    ],
    "name:ron_x_preferred":[
        "Baidu"
    ],
    "name:rus_x_preferred":[
        "Baidu"
    ],
    "name:sco_x_preferred":[
        "Baidu"
    ],
    "name:slk_x_preferred":[
        "Baidu"
    ],
    "name:spa_x_preferred":[
        "Baidu"
    ],
    "name:swe_x_preferred":[
        "Baidu"
    ],
    "name:tel_x_preferred":[
        "\u0c2c\u0c48\u0c21\u0c41"
    ],
    "name:tha_x_preferred":[
        "\u0e44\u0e1b\u0e48\u0e15\u0e39\u0e49"
    ],
    "name:tur_x_preferred":[
        "Baidu"
    ],
    "name:ukr_x_preferred":[
        "Baidu"
    ],
    "name:vie_x_preferred":[
        "Baidu"
    ],
    "wof:name":"Baidu",
    "wof:placetype":"locality"
},
  "geometry": {"coordinates":[118.66249999999999,25.77222],"type":"Point"}
}