{
  "type": "Feature",
  "properties": {
    "gn:admin1_code":"19.0",
    "gn:asciiname":"Dijiatuncun",
    "gn:country_code":"CN",
    "gn:dem":8,
    "gn:feature_class":"P",
    "gn:feature_code":"PPL",
    "gn:name":"Dijiatuncun",
    "gn:population":0,
    "gn:timezone":"Asia/Shanghai",
    "iso:country":"CN",
    "name:zho_x_preferred":[
        "\u90b8\u5bb6\u5c6f\u6751"
    ],
    "wof:name":"Dijiatuncun",
    "wof:placetype":"locality"
},
  "geometry": {"coordinates":[121.00097,40.94264],"type":"Point"}
}