{
  "type": "Feature",
  "properties": {
    "gn:admin1_code":"23",
    "gn:asciiname":"Dabang",
    "gn:country_code":"CN",
    "gn:dem":7,
    "gn:feature_class":"P",
    "gn:feature_code":"PPL",
    "gn:name":"Dabang",
    "gn:population":0,
    "gn:timezone":"Asia/Shanghai",
    "iso:country":"CN",
    "name:por_x_preferred":[
        "Dabang"
    ],
    "name:und_x_variant":[
        "Ta-cheng-pang",
        "\u5927\u6d5c"
    ],
    "wof:name":"Dabang",
    "wof:placetype":"locality"
},
  "geometry": {"coordinates":[121.02399,30.9563],"type":"Point"}
}