{
  "type": "Feature",
  "properties": {
    "gn:admin1_code":"26.0",
    "gn:asciiname":"Xiaoquanpo",
    "gn:country_code":"CN",
    "gn:dem":1013,
    "gn:feature_class":"P",
    "gn:feature_code":"PPL",
    "gn:name":"Xiaoquanpo",
    "gn:population":0,
    "gn:timezone":"Asia/Shanghai",
    "iso:country":"CN",
    "name:zho_x_preferred":[
        "\u5c0f\u6cc9\u5761"
    ],
    "wof:name":"Xiaoquanpo",
    "wof:placetype":"locality"
},
  "geometry": {"coordinates":[109.40723,35.98754],"type":"Point"}
}