{
  "type": "Feature",
  "properties": {
    "gn:admin1_code":"25",
    "gn:asciiname":"Dawangzhuang",
    "gn:country_code":"CN",
    "gn:dem":32,
    "gn:feature_class":"P",
    "gn:feature_code":"PPL",
    "gn:name":"Dawangzhuang",
    "gn:population":0,
    "gn:timezone":"Asia/Shanghai",
    "iso:country":"CN",
    "name:zho_x_preferred":[
        "\u5927\u738b\u5e84"
    ],
    "wof:name":"Dawangzhuang",
    "wof:placetype":"locality"
},
  "geometry": {"coordinates":[116.124,37.0634],"type":"Point"}
}