{
  "type": "Feature",
  "properties": {
    "gn:admin1_code":"26.0",
    "gn:asciiname":"Wazhahe",
    "gn:country_code":"CN",
    "gn:dem":1177,
    "gn:feature_class":"P",
    "gn:feature_code":"PPL",
    "gn:name":"Wazhahe",
    "gn:population":0,
    "gn:timezone":"Asia/Shanghai",
    "iso:country":"CN",
    "name:und_x_variant":[
        "Wa-cha-ho",
        "Wazhahe"
    ],
    "name:zho_x_preferred":[
        "\u74e6\u6e23\u6cb3"
    ],
    "wof:name":"Wazhahe",
    "wof:placetype":"locality"
},
  "geometry": {"coordinates":[109.74006,36.24948],"type":"Point"}
}