{
  "type": "Feature",
  "properties": {
    "gn:admin1_code":"1.0",
    "gn:asciiname":"Chacun",
    "gn:country_code":"CN",
    "gn:dem":125,
    "gn:feature_class":"P",
    "gn:feature_code":"PPL",
    "gn:name":"Chacun",
    "gn:population":0,
    "gn:timezone":"Asia/Shanghai",
    "iso:country":"CN",
    "name:zho_x_preferred":[
        "\u67e5\u6751"
    ],
    "wof:name":"Chacun",
    "wof:placetype":"locality"
},
  "geometry": {"coordinates":[118.02343,30.51522000000001],"type":"Point"}
}