{
  "type": "Feature",
  "properties": {
    "gn:admin1_code":"8.0",
    "gn:asciiname":"Mengguanghuaitun",
    "gn:country_code":"CN",
    "gn:dem":211,
    "gn:feature_class":"P",
    "gn:feature_code":"PPL",
    "gn:name":"Mengguanghuaitun",
    "gn:population":0,
    "gn:timezone":"Asia/Shanghai",
    "iso:country":"CN",
    "name:zho_x_preferred":[
        "\u5b5f\u5e7f\u6000\u5c6f"
    ],
    "wof:name":"Mengguanghuaitun",
    "wof:placetype":"locality"
},
  "geometry": {"coordinates":[124.66394,48.58717],"type":"Point"}
}