{
  "type": "Feature",
  "properties": {
    "gn:admin1_code":"12.0",
    "gn:asciiname":"Zhuhesi",
    "gn:country_code":"CN",
    "gn:dem":23,
    "gn:feature_class":"P",
    "gn:feature_code":"PPL",
    "gn:name":"Zhuhesi",
    "gn:population":0,
    "gn:timezone":"Asia/Shanghai",
    "iso:country":"CN",
    "name:und_x_variant":[
        "\u7afa\u5408\u5bfa"
    ],
    "wof:name":"Zhuhesi",
    "wof:placetype":"locality"
},
  "geometry": {"coordinates":[114.2209,30.62628],"type":"Point"}
}