{
  "type": "Feature",
  "properties": {
    "gn:admin1_code":"30.0",
    "gn:asciiname":"Longtangbian",
    "gn:country_code":"CN",
    "gn:dem":99,
    "gn:feature_class":"P",
    "gn:feature_code":"PPL",
    "gn:name":"Longtangbian",
    "gn:population":0,
    "gn:timezone":"Asia/Shanghai",
    "iso:country":"CN",
    "name:zho_x_preferred":[
        "\u9f99\u5858\u8fb9"
    ],
    "wof:name":"Longtangbian",
    "wof:placetype":"locality"
},
  "geometry": {"coordinates":[113.54327000000001,24.93799],"type":"Point"}
}