{
  "type": "Feature",
  "properties": {
    "gn:admin1_code":"32.0",
    "gn:asciiname":"Jiajiawan",
    "gn:country_code":"CN",
    "gn:dem":641,
    "gn:feature_class":"P",
    "gn:feature_code":"PPL",
    "gn:name":"Jiajiawan",
    "gn:population":0,
    "gn:timezone":"Asia/Shanghai",
    "iso:country":"CN",
    "name:zho_x_preferred":[
        "\u8d3e\u5bb6\u6e7e"
    ],
    "wof:name":"Jiajiawan",
    "wof:placetype":"locality"
},
  "geometry": {"coordinates":[106.79747,32.26278],"type":"Point"}
}