{
  "type": "Feature",
  "properties": {
    "gn:admin1_code":"12.0",
    "gn:asciiname":"Xinwuzheng",
    "gn:country_code":"CN",
    "gn:dem":29,
    "gn:feature_class":"P",
    "gn:feature_code":"PPL",
    "gn:name":"Xinwuzheng",
    "gn:population":0,
    "gn:timezone":"Asia/Shanghai",
    "iso:country":"CN",
    "name:zho_x_preferred":[
        "Xinwuzheng"
    ],
    "name:zho_x_variant":[
        "\u65b0\u5c4b\u90d1"
    ],
    "wof:name":"Xinwuzheng",
    "wof:placetype":"locality"
},
  "geometry": {"coordinates":[114.28943,29.94641],"type":"Point"}
}