{
  "type": "Feature",
  "properties": {
    "gn:admin1_code":"3",
    "gn:asciiname":"Zhenshang",
    "gn:country_code":"CN",
    "gn:dem":86,
    "gn:feature_class":"P",
    "gn:feature_code":"PPL",
    "gn:name":"Zhenshang",
    "gn:population":0,
    "gn:timezone":"Asia/Shanghai",
    "iso:country":"CN",
    "name:und_x_variant":[
        "\u5733\u4e0a"
    ],
    "wof:name":"Zhenshang",
    "wof:placetype":"locality"
},
  "geometry": {"coordinates":[116.71268999999999,27.66168],"type":"Point"}
}