{
  "type": "Feature",
  "properties": {
    "gn:admin1_code":"16",
    "gn:asciiname":"Lujing",
    "gn:cc2":"CN",
    "gn:country_code":"CN",
    "gn:dem":162,
    "gn:feature_class":"P",
    "gn:feature_code":"PPL",
    "gn:name":"Lujing",
    "gn:population":0,
    "gn:timezone":"Asia/Shanghai",
    "iso:country":"CN",
    "name:und_x_variant":[
        "Lu-ch\u2019ing",
        "Lujing"
    ],
    "wof:name":"Lujing",
    "wof:placetype":"locality"
},
  "geometry": {"coordinates":[110.51667,22.38333],"type":"Point"}
}