{
  "type": "Feature",
  "properties": {
    "gn:admin1_code":"32.0",
    "gn:asciiname":"Wagu'erku",
    "gn:country_code":"CN",
    "gn:dem":2717,
    "gn:feature_class":"P",
    "gn:feature_code":"PPL",
    "gn:name":"Wagu\u2019erku",
    "gn:population":0,
    "gn:timezone":"Asia/Shanghai",
    "iso:country":"CN",
    "name:und_x_variant":[
        "Wagu\u2019erku"
    ],
    "name:zho_x_preferred":[
        "\u6316\u53e4\u5c14\u82e6"
    ],
    "wof:name":"Wagu'erku",
    "wof:placetype":"locality"
},
  "geometry": {"coordinates":[102.818,28.459],"type":"Point"}
}