{
  "type": "Feature",
  "properties": {
    "gn:admin1_code":"15.0",
    "gn:asciiname":"Jizui",
    "gn:country_code":"CN",
    "gn:dem":1406,
    "gn:feature_class":"P",
    "gn:feature_code":"PPL",
    "gn:name":"Jizui",
    "gn:population":0,
    "gn:timezone":"Asia/Shanghai",
    "iso:country":"CN",
    "name:und_x_variant":[
        "\u9e21\u5480"
    ],
    "wof:name":"Jizui",
    "wof:placetype":"locality"
},
  "geometry": {"coordinates":[107.5821,36.68511],"type":"Point"}
}