{
  "type": "Feature",
  "properties": {
    "gn:admin1_code":"4.0",
    "gn:asciiname":"Daiwacun",
    "gn:country_code":"CN",
    "gn:dem":9,
    "gn:feature_class":"P",
    "gn:feature_code":"PPL",
    "gn:name":"Daiwacun",
    "gn:population":0,
    "gn:timezone":"Asia/Shanghai",
    "iso:country":"CN",
    "name:zho_x_preferred":[
        "\u6234\u6d3c\u6751"
    ],
    "wof:name":"Daiwacun",
    "wof:placetype":"locality"
},
  "geometry": {"coordinates":[119.09589,33.99353],"type":"Point"}
}