{
  "type": "Feature",
  "properties": {
    "gn:admin1_code":"4.0",
    "gn:asciiname":"Changchuncun",
    "gn:country_code":"CN",
    "gn:dem":2,
    "gn:feature_class":"P",
    "gn:feature_code":"PPL",
    "gn:name":"Changchuncun",
    "gn:population":0,
    "gn:timezone":"Asia/Shanghai",
    "iso:country":"CN",
    "name:zho_x_preferred":[
        "\u957f\u6625\u6751"
    ],
    "wof:name":"Changchuncun",
    "wof:placetype":"locality"
},
  "geometry": {"coordinates":[119.36432000000001,34.38989],"type":"Point"}
}