{
  "type": "Feature",
  "properties": {
    "gn:admin1_code":"19.0",
    "gn:asciiname":"Tuanjie",
    "gn:country_code":"CN",
    "gn:dem":111,
    "gn:feature_class":"P",
    "gn:feature_code":"PPL",
    "gn:name":"Tuanjie",
    "gn:population":0,
    "gn:timezone":"Asia/Shanghai",
    "iso:country":"CN",
    "name:und_x_variant":[
        "\u56e2\u7ed3"
    ],
    "wof:name":"Tuanjie",
    "wof:placetype":"locality"
},
  "geometry": {"coordinates":[123.87881000000002,40.23859],"type":"Point"}
}