{
  "type": "Feature",
  "properties": {
    "gn:admin1_code":"12.0",
    "gn:asciiname":"Pulizhou",
    "gn:country_code":"CN",
    "gn:dem":17,
    "gn:feature_class":"P",
    "gn:feature_code":"PPL",
    "gn:name":"Pulizhou",
    "gn:population":0,
    "gn:timezone":"Asia/Shanghai",
    "iso:country":"CN",
    "name:zho_x_preferred":[
        "\u84b2\u68a8\u6d32"
    ],
    "wof:name":"Pulizhou",
    "wof:placetype":"locality"
},
  "geometry": {"coordinates":[114.70832,30.2966],"type":"Point"}
}