{
  "type": "Feature",
  "properties": {
    "gn:admin1_code":"32.0",
    "gn:asciiname":"Daqiao",
    "gn:country_code":"CN",
    "gn:dem":1763,
    "gn:feature_class":"P",
    "gn:feature_code":"PPL",
    "gn:name":"Daqiao",
    "gn:population":0,
    "gn:timezone":"Asia/Shanghai",
    "iso:country":"CN",
    "name:ceb_x_preferred":[
        "Daqiao"
    ],
    "name:deu_x_preferred":[
        "Daqiao"
    ],
    "name:swe_x_preferred":[
        "Daqiao"
    ],
    "name:zho_x_preferred":[
        "\u5927\u6865"
    ],
    "wof:name":"Daqiao",
    "wof:placetype":"locality"
},
  "geometry": {"coordinates":[102.081,26.4527],"type":"Point"}
}