{
  "type": "Feature",
  "properties": {
    "gn:admin1_code":"14.0",
    "gn:asciiname":"Maidaozuo",
    "gn:country_code":"CN",
    "gn:dem":4032,
    "gn:feature_class":"P",
    "gn:feature_code":"PPL",
    "gn:name":"Maidaozuo",
    "gn:population":0,
    "gn:timezone":"Asia/Urumqi",
    "iso:country":"CN",
    "name:zho_x_preferred":[
        "\u4e70\u5200\u5de6"
    ],
    "wof:name":"Maidaozuo",
    "wof:placetype":"locality"
},
  "geometry": {"coordinates":[96.87014000000001,31.77659],"type":"Point"}
}