{
  "type": "Feature",
  "properties": {
    "gn:admin1_code":"1.0",
    "gn:asciiname":"Xuniucun",
    "gn:country_code":"CN",
    "gn:dem":29,
    "gn:feature_class":"P",
    "gn:feature_code":"PPL",
    "gn:name":"Xuniucun",
    "gn:population":0,
    "gn:timezone":"Asia/Shanghai",
    "iso:country":"CN",
    "name:zho_x_preferred":[
        "\u5f90\u94ae\u6751"
    ],
    "wof:name":"Xuniucun",
    "wof:placetype":"locality"
},
  "geometry": {"coordinates":[117.26891999999999,32.59047],"type":"Point"}
}