{
  "type": "Feature",
  "properties": {
    "gn:admin1_code":"21.0",
    "gn:asciiname":"Haiwozi",
    "gn:country_code":"CN",
    "gn:dem":1756,
    "gn:feature_class":"P",
    "gn:feature_code":"PPL",
    "gn:name":"Haiwozi",
    "gn:population":0,
    "gn:timezone":"Asia/Shanghai",
    "iso:country":"CN",
    "name:zho_x_preferred":[
        "\u6d77\u7a9d\u5b50"
    ],
    "wof:name":"Haiwozi",
    "wof:placetype":"locality"
},
  "geometry": {"coordinates":[106.17824,36.81025],"type":"Point"}
}