{
  "type": "Feature",
  "properties": {
    "gn:admin1_code":"14.0",
    "gn:asciiname":"Caka",
    "gn:country_code":"CN",
    "gn:dem":4698,
    "gn:feature_class":"P",
    "gn:feature_code":"PPL",
    "gn:name":"Caka",
    "gn:population":0,
    "gn:timezone":"Asia/Urumqi",
    "iso:country":"CN",
    "name:bod_x_preferred":[
        "Caka"
    ],
    "name:ceb_x_preferred":[
        "Caka"
    ],
    "name:ces_x_preferred":[
        "\u010caka"
    ],
    "name:deu_x_preferred":[
        "Caka"
    ],
    "name:slk_x_preferred":[
        "\u010caka"
    ],
    "name:zho_x_preferred":[
        "Chaka"
    ],
    "name:zho_x_variant":[
        "\u67e5\u5361"
    ],
    "wof:name":"Caka",
    "wof:placetype":"locality"
},
  "geometry": {"coordinates":[97.08054,29.84576],"type":"Point"}
}