{
  "type": "Feature",
  "properties": {
    "gn:admin1_code":"19.0",
    "gn:asciiname":"Qianduanjia",
    "gn:country_code":"CN",
    "gn:dem":23,
    "gn:feature_class":"P",
    "gn:feature_code":"PPL",
    "gn:name":"Qianduanjia",
    "gn:population":0,
    "gn:timezone":"Asia/Shanghai",
    "iso:country":"CN",
    "name:zho_x_preferred":[
        "\u524d\u6bb5\u5bb6"
    ],
    "wof:name":"Qianduanjia",
    "wof:placetype":"locality"
},
  "geometry": {"coordinates":[122.24799,41.76241],"type":"Point"}
}