{
  "type": "Feature",
  "properties": {
    "gn:admin1_code":"11.0",
    "gn:asciiname":"Yangjialing",
    "gn:country_code":"CN",
    "gn:dem":198,
    "gn:feature_class":"P",
    "gn:feature_code":"PPL",
    "gn:name":"Yangjialing",
    "gn:population":0,
    "gn:timezone":"Asia/Shanghai",
    "iso:country":"CN",
    "name:zho_x_preferred":[
        "\u7f8a\u5bb6\u5cad"
    ],
    "wof:name":"Yangjialing",
    "wof:placetype":"locality"
},
  "geometry": {"coordinates":[111.95143,27.07116],"type":"Point"}
}