{
  "type": "Feature",
  "properties": {
    "gn:admin1_code":"14.0",
    "gn:asciiname":"Wendeng",
    "gn:country_code":"CN",
    "gn:dem":4206,
    "gn:feature_class":"P",
    "gn:feature_code":"PPL",
    "gn:name":"Wendeng",
    "gn:population":0,
    "gn:timezone":"Asia/Urumqi",
    "iso:country":"CN",
    "name:zho_x_preferred":[
        "\u6e29\u767b"
    ],
    "wof:name":"Wendeng",
    "wof:placetype":"locality"
},
  "geometry": {"coordinates":[86.5941,29.2064],"type":"Point"}
}