{
  "type": "Feature",
  "properties": {
    "gn:admin1_code":"32.0",
    "gn:asciiname":"Dianbing",
    "gn:country_code":"CN",
    "gn:dem":654,
    "gn:feature_class":"P",
    "gn:feature_code":"PPL",
    "gn:name":"Dianbing",
    "gn:population":0,
    "gn:timezone":"Asia/Shanghai",
    "iso:country":"CN",
    "name:zho_x_preferred":[
        "\u70b9\u5175"
    ],
    "wof:name":"Dianbing",
    "wof:placetype":"locality"
},
  "geometry": {"coordinates":[107.29900000000001,31.4339],"type":"Point"}
}