{
  "type": "Feature",
  "properties": {
    "gn:admin1_code":"29.0",
    "gn:asciiname":"Laomianzhai",
    "gn:country_code":"CN",
    "gn:dem":1491,
    "gn:feature_class":"P",
    "gn:feature_code":"PPL",
    "gn:name":"Laomianzhai",
    "gn:population":0,
    "gn:timezone":"Asia/Shanghai",
    "iso:country":"CN",
    "name:zho_x_preferred":[
        "\u8001\u7f05\u5be8"
    ],
    "wof:name":"Laomianzhai",
    "wof:placetype":"locality"
},
  "geometry": {"coordinates":[99.4162,22.3748],"type":"Point"}
}