{
  "type": "Feature",
  "properties": {
    "gn:admin1_code":"11.0",
    "gn:asciiname":"Chaoxianchong",
    "gn:country_code":"CN",
    "gn:dem":39,
    "gn:feature_class":"P",
    "gn:feature_code":"PPL",
    "gn:name":"Chaoxianchong",
    "gn:population":0,
    "gn:timezone":"Asia/Shanghai",
    "iso:country":"CN",
    "name:zho_x_preferred":[
        "\u671d\u4ed9\u51b2"
    ],
    "wof:name":"Chaoxianchong",
    "wof:placetype":"locality"
},
  "geometry": {"coordinates":[113.13639999999999,27.79465],"type":"Point"}
}