{
  "type": "Feature",
  "properties": {
    "gn:admin1_code":"2.0",
    "gn:asciiname":"Shangpansun",
    "gn:country_code":"CN",
    "gn:dem":30,
    "gn:feature_class":"P",
    "gn:feature_code":"PPL",
    "gn:name":"Shangpansun",
    "gn:population":0,
    "gn:timezone":"Asia/Shanghai",
    "iso:country":"CN",
    "name:zho_x_preferred":[
        "\u4e0a\u6f58\u5b59"
    ],
    "wof:name":"Shangpansun",
    "wof:placetype":"locality"
},
  "geometry": {"coordinates":[122.26461999999999,30.03714],"type":"Point"}
}