{
  "type": "Feature",
  "properties": {
    "gn:admin1_code":"26",
    "gn:asciiname":"Hanchengqu",
    "gn:cc2":"CN",
    "gn:country_code":"CN",
    "gn:dem":516,
    "gn:feature_class":"P",
    "gn:feature_code":"PPL",
    "gn:name":"Hanchengqu",
    "gn:population":0,
    "gn:timezone":"Asia/Shanghai",
    "iso:country":"CN",
    "name:und_x_variant":[
        "Hanwangcheng",
        "Hung-hsing",
        "Han-ch\u2019eng",
        "Hang-wang-ch\u2019eng",
        "Hanchengqu"
    ],
    "wof:name":"Hanchengqu",
    "wof:placetype":"locality"
},
  "geometry": {"coordinates":[108.43194,32.70083],"type":"Point"}
}