{
  "type": "Feature",
  "properties": {
    "gn:admin1_code":"21.0",
    "gn:asciiname":"Tiezhuquan",
    "gn:country_code":"CN",
    "gn:dem":1406,
    "gn:feature_class":"P",
    "gn:feature_code":"PPL",
    "gn:name":"Tiezhuquan",
    "gn:population":0,
    "gn:timezone":"Asia/Shanghai",
    "iso:country":"CN",
    "name:zho_x_preferred":[
        "\u94c1\u67f1\u6cc9"
    ],
    "wof:name":"Tiezhuquan",
    "wof:placetype":"locality"
},
  "geometry": {"coordinates":[106.97199999999999,37.6896],"type":"Point"}
}