{
  "type": "Feature",
  "properties": {
    "gn:admin1_code":"15.0",
    "gn:asciiname":"Daijia Xinzhuang",
    "gn:country_code":"CN",
    "gn:dem":1601,
    "gn:feature_class":"P",
    "gn:feature_code":"PPL",
    "gn:name":"Daijia Xinzhuang",
    "gn:population":0,
    "gn:timezone":"Asia/Shanghai",
    "iso:country":"CN",
    "name:zho_x_preferred":[
        "\u6234\u5bb6\u65b0\u5e84"
    ],
    "wof:name":"Daijia Xinzhuang",
    "wof:placetype":"locality"
},
  "geometry": {"coordinates":[106.566,35.2995],"type":"Point"}
}