{
  "type": "Feature",
  "properties": {
    "gn:admin1_code":"4.0",
    "gn:asciiname":"Nanzhangxiang",
    "gn:country_code":"CN",
    "gn:dem":3,
    "gn:feature_class":"P",
    "gn:feature_code":"PPL",
    "gn:name":"Nanzhangxiang",
    "gn:population":0,
    "gn:timezone":"Asia/Shanghai",
    "iso:country":"CN",
    "name:und_x_variant":[
        "\u5357\u7ae0\u5df7"
    ],
    "name:zho_x_preferred":[
        "\u5357\u7ae0\u5df7"
    ],
    "wof:name":"Nanzhangxiang",
    "wof:placetype":"locality"
},
  "geometry": {"coordinates":[120.13831999999999,31.61148],"type":"Point"}
}