{
  "type": "Feature",
  "properties": {
    "gn:admin1_code":"29",
    "gn:asciiname":"Zhonglianchi",
    "gn:country_code":"CN",
    "gn:dem":1673,
    "gn:feature_class":"P",
    "gn:feature_code":"PPL",
    "gn:name":"Zhonglianchi",
    "gn:population":0,
    "gn:timezone":"Asia/Shanghai",
    "iso:country":"CN",
    "name:zho_x_preferred":[
        "\u4e2d\u83b2\u6c60"
    ],
    "wof:name":"Zhonglianchi",
    "wof:placetype":"locality"
},
  "geometry": {"coordinates":[102.529,24.4415],"type":"Point"}
}