{
  "type": "Feature",
  "properties": {
    "gn:admin1_code":"32.0",
    "gn:asciiname":"Dajiesi",
    "gn:country_code":"CN",
    "gn:dem":310,
    "gn:feature_class":"P",
    "gn:feature_code":"PPL",
    "gn:name":"Dajiesi",
    "gn:population":0,
    "gn:timezone":"Asia/Shanghai",
    "iso:country":"CN",
    "name:zho_x_preferred":[
        "\u642d\u754c\u5bfa"
    ],
    "wof:name":"Dajiesi",
    "wof:placetype":"locality"
},
  "geometry": {"coordinates":[106.998,30.0593],"type":"Point"}
}