{
  "type": "Feature",
  "properties": {
    "gn:admin1_code":"32.0",
    "gn:asciiname":"Chuantouhe",
    "gn:country_code":"CN",
    "gn:dem":927,
    "gn:feature_class":"P",
    "gn:feature_code":"PPL",
    "gn:name":"Chuantouhe",
    "gn:population":0,
    "gn:timezone":"Asia/Shanghai",
    "iso:country":"CN",
    "name:zho_x_preferred":[
        "\u8239\u5934\u6cb3"
    ],
    "wof:name":"Chuantouhe",
    "wof:placetype":"locality"
},
  "geometry": {"coordinates":[104.678,32.0712],"type":"Point"}
}