{
  "type": "Feature",
  "properties": {
    "gn:admin1_code":"20.0",
    "gn:asciiname":"Dijiajie",
    "gn:country_code":"CN",
    "gn:dem":421,
    "gn:feature_class":"P",
    "gn:feature_code":"PPL",
    "gn:name":"Dijiajie",
    "gn:population":0,
    "gn:timezone":"Asia/Shanghai",
    "iso:country":"CN",
    "name:zho_x_preferred":[
        "\u72c4\u5bb6\u8857"
    ],
    "wof:name":"Dijiajie",
    "wof:placetype":"locality"
},
  "geometry": {"coordinates":[122.38196000000001,47.58912],"type":"Point"}
}