{
  "type": "Feature",
  "properties": {
    "gn:admin1_code":"4.0",
    "gn:asciiname":"Yanshanhe",
    "gn:country_code":"CN",
    "gn:dem":10,
    "gn:feature_class":"P",
    "gn:feature_code":"PPL",
    "gn:name":"Yanshanhe",
    "gn:population":0,
    "gn:timezone":"Asia/Shanghai",
    "iso:country":"CN",
    "name:zho_x_preferred":[
        "\u6cbf\u5c71\u6cb3"
    ],
    "wof:name":"Yanshanhe",
    "wof:placetype":"locality"
},
  "geometry": {"coordinates":[119.33508999999999,32.37838],"type":"Point"}
}