{
  "type": "Feature",
  "properties": {
    "gn:admin1_code":"32.0",
    "gn:asciiname":"Teruolaiwo",
    "gn:country_code":"CN",
    "gn:dem":2726,
    "gn:feature_class":"P",
    "gn:feature_code":"PPL",
    "gn:name":"Teruolaiwo",
    "gn:population":0,
    "gn:timezone":"Asia/Shanghai",
    "iso:country":"CN",
    "name:zho_x_preferred":[
        "\u7279\u82e5\u6765\u7a9d"
    ],
    "wof:name":"Teruolaiwo",
    "wof:placetype":"locality"
},
  "geometry": {"coordinates":[102.88500000000001,27.7413],"type":"Point"}
}