{
  "type": "Feature",
  "properties": {
    "gn:admin1_code":"30.0",
    "gn:asciiname":"Haicheng",
    "gn:country_code":"CN",
    "gn:dem":1,
    "gn:feature_class":"P",
    "gn:feature_code":"PPL",
    "gn:name":"Haicheng",
    "gn:population":0,
    "gn:timezone":"Asia/Shanghai",
    "iso:country":"CN",
    "name:zho_x_preferred":[
        "\u6d77\u57d5"
    ],
    "wof:name":"Haicheng",
    "wof:placetype":"locality"
},
  "geometry": {"coordinates":[116.22204000000001,23.00376],"type":"Point"}
}