{
  "type": "Feature",
  "properties": {
    "gn:admin1_code":"31.0",
    "gn:asciiname":"Hongwei",
    "gn:country_code":"CN",
    "gn:dem":402,
    "gn:elevation":"879.0",
    "gn:feature_class":"P",
    "gn:feature_code":"PPL",
    "gn:name":"Hongwei",
    "gn:population":0,
    "gn:timezone":"Asia/Shanghai",
    "iso:country":"CN",
    "name:und_x_variant":[
        "\u7ea2\u536b"
    ],
    "wof:name":"Hongwei",
    "wof:placetype":"locality"
},
  "geometry": {"coordinates":[109.19842,18.48531],"type":"Point"}
}