{
  "type": "Feature",
  "properties": {
    "gn:admin1_code":"2.0",
    "gn:asciiname":"Shuijing",
    "gn:country_code":"CN",
    "gn:dem":644,
    "gn:feature_class":"P",
    "gn:feature_code":"PPL",
    "gn:name":"Shuijing",
    "gn:population":0,
    "gn:timezone":"Asia/Shanghai",
    "iso:country":"CN",
    "name:und_x_variant":[
        "\u6c34\u4e95",
        "Shuijing"
    ],
    "wof:name":"Shuijing",
    "wof:placetype":"locality"
},
  "geometry": {"coordinates":[119.45090999999999,27.82967],"type":"Point"}
}