{
  "type": "Feature",
  "properties": {
    "gn:admin1_code":"33.0",
    "gn:asciiname":"Taiyang",
    "gn:country_code":"CN",
    "gn:dem":301,
    "gn:feature_class":"P",
    "gn:feature_code":"PPL",
    "gn:name":"Taiyang",
    "gn:population":0,
    "gn:timezone":"Asia/Shanghai",
    "iso:country":"CN",
    "name:zho_x_preferred":[
        "\u592a\u9633"
    ],
    "wof:name":"Taiyang",
    "wof:placetype":"locality"
},
  "geometry": {"coordinates":[106.03060000000001,29.84183],"type":"Point"}
}