{
  "type": "Feature",
  "properties": {
    "gn:admin1_code":"15.0",
    "gn:asciiname":"Mazi Goukou",
    "gn:country_code":"CN",
    "gn:dem":1095,
    "gn:feature_class":"P",
    "gn:feature_code":"PPL",
    "gn:name":"Mazi Goukou",
    "gn:population":0,
    "gn:timezone":"Asia/Shanghai",
    "iso:country":"CN",
    "name:zho_x_preferred":[
        "\u9a6c\u5b50\u6c9f\u53e3"
    ],
    "wof:name":"Mazi Goukou",
    "wof:placetype":"locality"
},
  "geometry": {"coordinates":[107.40000000000001,35.4874],"type":"Point"}
}