{
  "type": "Feature",
  "properties": {
    "gn:admin1_code":"26.0",
    "gn:asciiname":"Liuyazi",
    "gn:country_code":"CN",
    "gn:dem":644,
    "gn:feature_class":"P",
    "gn:feature_code":"PPL",
    "gn:name":"Liuyazi",
    "gn:population":0,
    "gn:timezone":"Asia/Shanghai",
    "iso:country":"CN",
    "name:und_x_variant":[
        "\u67f3\u57ad\u5b50"
    ],
    "wof:name":"Liuyazi",
    "wof:placetype":"locality"
},
  "geometry": {"coordinates":[107.2298,32.94987],"type":"Point"}
}