{
  "type": "Feature",
  "properties": {
    "gn:admin1_code":"3.0",
    "gn:asciiname":"Huzuichong Aoshang",
    "gn:country_code":"CN",
    "gn:dem":442,
    "gn:feature_class":"P",
    "gn:feature_code":"PPL",
    "gn:name":"Huzuichong Aoshang",
    "gn:population":0,
    "gn:timezone":"Asia/Shanghai",
    "iso:country":"CN",
    "name:zho_x_preferred":[
        "\u6e56\u5480\u51b2\u51f9\u4e0a"
    ],
    "wof:name":"Huzuichong Aoshang",
    "wof:placetype":"locality"
},
  "geometry": {"coordinates":[113.855,27.852],"type":"Point"}
}