{
  "type": "Feature",
  "properties": {
    "gn:admin1_code":"25",
    "gn:asciiname":"Damazhang",
    "gn:country_code":"CN",
    "gn:dem":27,
    "gn:feature_class":"P",
    "gn:feature_code":"PPL",
    "gn:name":"Damazhang",
    "gn:population":0,
    "gn:timezone":"Asia/Shanghai",
    "iso:country":"CN",
    "name:zho_x_preferred":[
        "\u5927\u9a6c\u5f20"
    ],
    "wof:name":"Damazhang",
    "wof:placetype":"locality"
},
  "geometry": {"coordinates":[116.581,36.7201],"type":"Point"}
}