{
  "type": "Feature",
  "properties": {
    "gn:admin1_code":"14.0",
    "gn:asciiname":"Duo'erna Muqicun",
    "gn:country_code":"CN",
    "gn:dem":4565,
    "gn:feature_class":"P",
    "gn:feature_code":"PPL",
    "gn:name":"Duo\u2019erna Muqicun",
    "gn:population":0,
    "gn:timezone":"Asia/Urumqi",
    "iso:country":"CN",
    "name:und_x_variant":[
        "Duo\u2019erna Muqicun"
    ],
    "name:zho_x_preferred":[
        "\u591a\u5c14\u90a3\u6728\u5176\u6751"
    ],
    "wof:name":"Duo'erna Muqicun",
    "wof:placetype":"locality"
},
  "geometry": {"coordinates":[91.61371,31.54788],"type":"Point"}
}