{
  "type": "Feature",
  "properties": {
    "gn:admin1_code":"32.0",
    "gn:asciiname":"Dujiagou",
    "gn:country_code":"CN",
    "gn:dem":820,
    "gn:feature_class":"P",
    "gn:feature_code":"PPL",
    "gn:name":"Dujiagou",
    "gn:population":0,
    "gn:timezone":"Asia/Shanghai",
    "iso:country":"CN",
    "name:und_x_variant":[
        "\u675c\u5bb6\u6c9f"
    ],
    "wof:name":"Dujiagou",
    "wof:placetype":"locality"
},
  "geometry": {"coordinates":[106.6814,32.23132],"type":"Point"}
}