{
  "type": "Feature",
  "properties": {
    "gn:admin1_code":"07",
    "gn:asciiname":"Yingyanglou",
    "gn:country_code":"CN",
    "gn:dem":308,
    "gn:feature_class":"P",
    "gn:feature_code":"PPL",
    "gn:name":"Yingyanglou",
    "gn:population":0,
    "gn:timezone":"Asia/Shanghai",
    "iso:country":"CN",
    "name:zho_x_preferred":[
        "\u8fce\u9633\u697c"
    ],
    "wof:name":"Yingyanglou",
    "wof:placetype":"locality"
},
  "geometry": {"coordinates":[116.98396,24.06913],"type":"Point"}
}