{
  "type": "Feature",
  "properties": {
    "gn:admin1_code":"16.0",
    "gn:asciiname":"Jiangna",
    "gn:country_code":"CN",
    "gn:dem":104,
    "gn:feature_class":"P",
    "gn:feature_code":"PPL",
    "gn:name":"Jiangna",
    "gn:population":0,
    "gn:timezone":"Asia/Shanghai",
    "iso:country":"CN",
    "name:zho_x_preferred":[
        "\u6c5f\u90a3"
    ],
    "wof:name":"Jiangna",
    "wof:placetype":"locality"
},
  "geometry": {"coordinates":[107.922,22.5996],"type":"Point"}
}