{
  "type": "Feature",
  "properties": {
    "gn:admin1_code":"30.0",
    "gn:asciiname":"Mei'ercun",
    "gn:country_code":"CN",
    "gn:dem":143,
    "gn:feature_class":"P",
    "gn:feature_code":"PPL",
    "gn:name":"Mei\u2019ercun",
    "gn:population":0,
    "gn:timezone":"Asia/Shanghai",
    "iso:country":"CN",
    "name:und_x_variant":[
        "Mei\u2019ercun"
    ],
    "name:zho_x_preferred":[
        "\u6885\u4e8c\u6751"
    ],
    "wof:name":"Mei'ercun",
    "wof:placetype":"locality"
},
  "geometry": {"coordinates":[115.938,24.5535],"type":"Point"}
}