{
  "type": "Feature",
  "properties": {
    "gn:admin1_code":"29",
    "gn:asciiname":"Tada Xinzhai",
    "gn:country_code":"CN",
    "gn:dem":2001,
    "gn:feature_class":"P",
    "gn:feature_code":"PPL",
    "gn:name":"Tada Xinzhai",
    "gn:population":0,
    "gn:timezone":"Asia/Shanghai",
    "iso:country":"CN",
    "name:zho_x_preferred":[
        "\u4ed6\u8fbe\u65b0\u5be8"
    ],
    "wof:name":"Tada Xinzhai",
    "wof:placetype":"locality"
},
  "geometry": {"coordinates":[102.273,24.2287],"type":"Point"}
}