{
  "type": "Feature",
  "properties": {
    "gn:admin1_code":"12.0",
    "gn:asciiname":"Siwangzui",
    "gn:country_code":"CN",
    "gn:dem":30,
    "gn:feature_class":"P",
    "gn:feature_code":"PPL",
    "gn:name":"Siwangzui",
    "gn:population":0,
    "gn:timezone":"Asia/Shanghai",
    "iso:country":"CN",
    "name:zho_x_preferred":[
        "\u4e1d\u7f51\u5480"
    ],
    "wof:name":"Siwangzui",
    "wof:placetype":"locality"
},
  "geometry": {"coordinates":[113.39315000000001,30.57454],"type":"Point"}
}