{
  "type": "Feature",
  "properties": {
    "gn:admin1_code":"11.0",
    "gn:asciiname":"Xiaofuyuan",
    "gn:country_code":"CN",
    "gn:dem":237,
    "gn:feature_class":"P",
    "gn:feature_code":"PPL",
    "gn:name":"Xiaofuyuan",
    "gn:population":0,
    "gn:timezone":"Asia/Shanghai",
    "iso:country":"CN",
    "name:zho_x_preferred":[
        "\u5c0f\u5bcc\u6e90"
    ],
    "wof:name":"Xiaofuyuan",
    "wof:placetype":"locality"
},
  "geometry": {"coordinates":[112.80311,26.23873],"type":"Point"}
}