{
  "type": "Feature",
  "properties": {
    "gn:admin1_code":"8.0",
    "gn:asciiname":"Laohengdaohe",
    "gn:country_code":"CN",
    "gn:dem":252,
    "gn:feature_class":"P",
    "gn:feature_code":"PPL",
    "gn:name":"Laohengdaohe",
    "gn:population":0,
    "gn:timezone":"Asia/Shanghai",
    "iso:country":"CN",
    "name:zho_x_preferred":[
        "\u8001\u6a2a\u9053\u6cb3"
    ],
    "wof:name":"Laohengdaohe",
    "wof:placetype":"locality"
},
  "geometry": {"coordinates":[131.35794999999999,46.35291],"type":"Point"}
}