{
  "type": "Feature",
  "properties": {
    "gn:admin1_code":"12.0",
    "gn:asciiname":"Beigaozhuang",
    "gn:country_code":"CN",
    "gn:dem":102,
    "gn:feature_class":"P",
    "gn:feature_code":"PPL",
    "gn:name":"Beigaozhuang",
    "gn:population":0,
    "gn:timezone":"Asia/Shanghai",
    "iso:country":"CN",
    "name:zho_x_preferred":[
        "\u5317\u9ad8\u5e84"
    ],
    "wof:name":"Beigaozhuang",
    "wof:placetype":"locality"
},
  "geometry": {"coordinates":[112.65428,31.97069],"type":"Point"}
}