{
  "type": "Feature",
  "properties": {
    "gn:admin1_code":"26.0",
    "gn:asciiname":"Tiejiangan",
    "gn:country_code":"CN",
    "gn:dem":356,
    "gn:feature_class":"P",
    "gn:feature_code":"PPL",
    "gn:name":"Tiejiangan",
    "gn:population":0,
    "gn:timezone":"Asia/Shanghai",
    "iso:country":"CN",
    "name:zho_x_preferred":[
        "\u94c1\u5320\u5eb5"
    ],
    "wof:name":"Tiejiangan",
    "wof:placetype":"locality"
},
  "geometry": {"coordinates":[108.86574,32.75993],"type":"Point"}
}