{
  "type": "Feature",
  "properties": {
    "gn:admin1_code":"19.0",
    "gn:asciiname":"Ciyu",
    "gn:country_code":"CN",
    "gn:dem":66,
    "gn:feature_class":"P",
    "gn:feature_code":"PPL",
    "gn:name":"Ciyu",
    "gn:population":0,
    "gn:timezone":"Asia/Shanghai",
    "iso:country":"CN",
    "name:und_x_variant":[
        "\u8328\u5cea"
    ],
    "wof:name":"Ciyu",
    "wof:placetype":"locality"
},
  "geometry": {"coordinates":[122.49637,40.32896],"type":"Point"}
}