{
  "type": "Feature",
  "properties": {
    "gn:admin1_code":"19.0",
    "gn:asciiname":"Ciyu",
    "gn:country_code":"CN",
    "gn:dem":66,
    "gn:feature_class":"P",
    "gn:feature_code":"PPL",
    "gn:name":"Ciyu",
    "gn:population":0,
    "gn:timezone":"Asia/Shanghai",
    "iso:country":"CN",
    "name:fas_x_preferred":[
        "\u0633\u06cc\u06cc\u0648"
    ],
    "name:und_x_variant":[
        "\u8328\u5cea"
    ],
    "name:zho_x_preferred":[
        "\u6148\u5cea\u9547"
    ],
    "wof:name":"Ciyu",
    "wof:placetype":"locality"
},
  "geometry": {"coordinates":[122.49637,40.32896],"type":"Point"}
}