{
  "type": "Feature",
  "properties": {
    "gn:admin1_code":"3.0",
    "gn:asciiname":"Shizishan Zhoujia",
    "gn:country_code":"CN",
    "gn:dem":30,
    "gn:feature_class":"P",
    "gn:feature_code":"PPL",
    "gn:name":"Shizishan Zhoujia",
    "gn:population":0,
    "gn:timezone":"Asia/Shanghai",
    "iso:country":"CN",
    "name:und_x_variant":[
        "\u72ee\u5b50\u5c71\u5468\u5bb6"
    ],
    "wof:name":"Shizishan Zhoujia",
    "wof:placetype":"locality"
},
  "geometry": {"coordinates":[116.32031000000001,28.0145],"type":"Point"}
}