{
  "type": "Feature",
  "properties": {
    "gn:admin1_code":"5.0",
    "gn:asciiname":"Gongnongcun",
    "gn:country_code":"CN",
    "gn:dem":496,
    "gn:feature_class":"P",
    "gn:feature_code":"PPLF",
    "gn:name":"Gongnongcun",
    "gn:population":0,
    "gn:timezone":"Asia/Shanghai",
    "iso:country":"CN",
    "name:und_x_variant":[
        "Gongnong",
        "\u5de5\u519c",
        "Gongnongcun",
        "\u5de5\u519c\u6751"
    ],
    "wof:name":"Gongnongcun",
    "wof:placetype":"locality"
},
  "geometry": {"coordinates":[128.94773000000001,42.51163],"type":"Point"}
}