{
  "type": "Feature",
  "properties": {
    "gn:admin1_code":"16.0",
    "gn:asciiname":"Wenli",
    "gn:country_code":"CN",
    "gn:dem":114,
    "gn:feature_class":"P",
    "gn:feature_code":"PPL",
    "gn:name":"Wenli",
    "gn:population":0,
    "gn:timezone":"Asia/Shanghai",
    "iso:country":"CN",
    "name:zho_x_preferred":[
        "\u6587\u5229"
    ],
    "wof:name":"Wenli",
    "wof:placetype":"locality"
},
  "geometry": {"coordinates":[109.517,22.6637],"type":"Point"}
}