{
  "type": "Feature",
  "properties": {
    "gn:admin1_code":"19.0",
    "gn:asciiname":"Huzhanggoucun",
    "gn:country_code":"CN",
    "gn:dem":279,
    "gn:feature_class":"P",
    "gn:feature_code":"PPL",
    "gn:name":"Huzhanggoucun",
    "gn:population":0,
    "gn:timezone":"Asia/Shanghai",
    "iso:country":"CN",
    "name:zho_x_preferred":[
        "\u864e\u638c\u6c9f\u6751"
    ],
    "wof:name":"Huzhanggoucun",
    "wof:placetype":"locality"
},
  "geometry": {"coordinates":[121.16302,42.21744],"type":"Point"}
}