{
  "type": "Feature",
  "properties": {
    "gn:admin1_code":"12.0",
    "gn:asciiname":"Xiasifang",
    "gn:country_code":"CN",
    "gn:dem":20,
    "gn:feature_class":"P",
    "gn:feature_code":"PPL",
    "gn:name":"Xiasifang",
    "gn:population":0,
    "gn:timezone":"Asia/Shanghai",
    "iso:country":"CN",
    "name:zho_x_preferred":[
        "Xiasifang"
    ],
    "name:zho_x_variant":[
        "\u4e0b\u56db\u623f"
    ],
    "wof:name":"Xiasifang",
    "wof:placetype":"locality"
},
  "geometry": {"coordinates":[115.38347,30.16912],"type":"Point"}
}