{
  "type": "Feature",
  "properties": {
    "gn:admin1_code":"15.0",
    "gn:asciiname":"Tianshan",
    "gn:country_code":"CN",
    "gn:dem":2174,
    "gn:feature_class":"P",
    "gn:feature_code":"PPL",
    "gn:name":"Tianshan",
    "gn:population":0,
    "gn:timezone":"Asia/Shanghai",
    "iso:country":"CN",
    "name:zho_x_preferred":[
        "\u5929\u5c71"
    ],
    "wof:name":"Tianshan",
    "wof:placetype":"locality"
},
  "geometry": {"coordinates":[103.646,36.7184],"type":"Point"}
}