{
  "type": "Feature",
  "properties": {
    "gn:admin1_code":"10",
    "gn:asciiname":"Xiguandi",
    "gn:country_code":"CN",
    "gn:dem":806,
    "gn:feature_class":"P",
    "gn:feature_code":"PPL",
    "gn:name":"Xiguandi",
    "gn:population":0,
    "gn:timezone":"Asia/Shanghai",
    "iso:country":"CN",
    "name:zho_x_preferred":[
        "\u897f\u5b98\u5730"
    ],
    "wof:name":"Xiguandi",
    "wof:placetype":"locality"
},
  "geometry": {"coordinates":[117.79098999999999,41.86639],"type":"Point"}
}