{
  "type": "Feature",
  "properties": {
    "gn:admin1_code":"19.0",
    "gn:asciiname":"Nanchazi",
    "gn:country_code":"CN",
    "gn:dem":350,
    "gn:feature_class":"P",
    "gn:feature_code":"PPL",
    "gn:name":"Nanchazi",
    "gn:population":0,
    "gn:timezone":"Asia/Shanghai",
    "iso:country":"CN",
    "name:und_x_variant":[
        "\u5357\u5c94\u5b50"
    ],
    "wof:name":"Nanchazi",
    "wof:placetype":"locality"
},
  "geometry": {"coordinates":[123.489,40.9455],"type":"Point"}
}