{
  "type": "Feature",
  "properties": {
    "gn:admin1_code":"07",
    "gn:asciiname":"Jiuting",
    "gn:country_code":"CN",
    "gn:dem":558,
    "gn:feature_class":"P",
    "gn:feature_code":"PPL",
    "gn:name":"Jiuting",
    "gn:population":0,
    "gn:timezone":"Asia/Shanghai",
    "iso:country":"CN",
    "name:zho_x_preferred":[
        "\u4e5d\u753a"
    ],
    "wof:name":"Jiuting",
    "wof:placetype":"locality"
},
  "geometry": {"coordinates":[117.47528,25.31306],"type":"Point"}
}