{
  "type": "Feature",
  "properties": {
    "gn:admin1_code":"29.0",
    "gn:asciiname":"Liguanchang",
    "gn:country_code":"CN",
    "gn:dem":1796,
    "gn:feature_class":"P",
    "gn:feature_code":"PPL",
    "gn:name":"Liguanchang",
    "gn:population":0,
    "gn:timezone":"Asia/Shanghai",
    "iso:country":"CN",
    "name:zho_x_preferred":[
        "\u674e\u5b98\u5382"
    ],
    "wof:name":"Liguanchang",
    "wof:placetype":"locality"
},
  "geometry": {"coordinates":[102.274,25.3347],"type":"Point"}
}