{
  "type": "Feature",
  "properties": {
    "gn:admin1_code":"3.0",
    "gn:asciiname":"Woli Wangjia",
    "gn:country_code":"CN",
    "gn:dem":25,
    "gn:feature_class":"P",
    "gn:feature_code":"PPL",
    "gn:name":"Woli Wangjia",
    "gn:population":0,
    "gn:timezone":"Asia/Shanghai",
    "iso:country":"CN",
    "name:und_x_variant":[
        "\u7a9d\u91cc\u738b\u5bb6"
    ],
    "wof:name":"Woli Wangjia",
    "wof:placetype":"locality"
},
  "geometry": {"coordinates":[115.76397,28.92318],"type":"Point"}
}