{
  "type": "Feature",
  "properties": {
    "gn:admin1_code":"10",
    "gn:asciiname":"Dicun",
    "gn:cc2":"CN",
    "gn:country_code":"CN",
    "gn:dem":19,
    "gn:feature_class":"P",
    "gn:feature_code":"PPL",
    "gn:name":"Dicun",
    "gn:population":0,
    "gn:timezone":"Asia/Shanghai",
    "iso:country":"CN",
    "name:und_x_variant":[
        "Ti-ts\u2019un",
        "Dicun"
    ],
    "wof:name":"Dicun",
    "wof:placetype":"locality"
},
  "geometry": {"coordinates":[115.84999999999999,38.36667],"type":"Point"}
}