{
  "type": "Feature",
  "properties": {
    "gn:admin1_code":"24.0",
    "gn:asciiname":"Majiayu",
    "gn:country_code":"CN",
    "gn:dem":1495,
    "gn:feature_class":"P",
    "gn:feature_code":"PPL",
    "gn:name":"Majiayu",
    "gn:population":0,
    "gn:timezone":"Asia/Shanghai",
    "iso:country":"CN",
    "name:zho_x_preferred":[
        "\u9a6c\u5bb6\u5cea"
    ],
    "wof:name":"Majiayu",
    "wof:placetype":"locality"
},
  "geometry": {"coordinates":[112.44774,36.90507],"type":"Point"}
}