{
  "type": "Feature",
  "properties": {
    "gn:admin1_code":"14",
    "gn:asciiname":"Chueyue",
    "gn:country_code":"CN",
    "gn:dem":4144,
    "gn:feature_class":"P",
    "gn:feature_code":"PPL",
    "gn:name":"Ch\u00fcy\u00fc",
    "gn:population":0,
    "gn:timezone":"Asia/Urumqi",
    "iso:country":"CN",
    "name:bod_x_preferred":[
        "\u0f41\u0fb2\u0f74\u0f66\u0f0b\u0f61\u0f74\u0f63"
    ],
    "wof:name":"Chueyue",
    "wof:placetype":"locality"
},
  "geometry": {"coordinates":[90.79183,28.23873],"type":"Point"}
}