{
  "type": "Feature",
  "properties": {
    "gn:admin1_code":"24.0",
    "gn:asciiname":"Xiaxizhuang",
    "gn:country_code":"CN",
    "gn:dem":1105,
    "gn:feature_class":"P",
    "gn:feature_code":"PPL",
    "gn:name":"Xiaxizhuang",
    "gn:population":0,
    "gn:timezone":"Asia/Shanghai",
    "iso:country":"CN",
    "name:zho_x_preferred":[
        "\u4e0b\u897f\u5e84"
    ],
    "wof:name":"Xiaxizhuang",
    "wof:placetype":"locality"
},
  "geometry": {"coordinates":[112.96151999999999,36.88465],"type":"Point"}
}