{
  "type": "Feature",
  "properties": {
    "gn:admin1_code":"5.0",
    "gn:asciiname":"Xiwujiacun",
    "gn:country_code":"CN",
    "gn:dem":128,
    "gn:feature_class":"P",
    "gn:feature_code":"PPL",
    "gn:name":"Xiwujiacun",
    "gn:population":0,
    "gn:timezone":"Asia/Shanghai",
    "iso:country":"CN",
    "name:zho_x_preferred":[
        "\u897f\u4e94\u5bb6\u6751"
    ],
    "wof:name":"Xiwujiacun",
    "wof:placetype":"locality"
},
  "geometry": {"coordinates":[123.96732,43.5936],"type":"Point"}
}