{
  "type": "Feature",
  "properties": {
    "gn:admin1_code":"12",
    "gn:asciiname":"Tiandian",
    "gn:country_code":"CN",
    "gn:dem":42,
    "gn:feature_class":"P",
    "gn:feature_code":"PPLA4",
    "gn:name":"Tiandian",
    "gn:population":0,
    "gn:timezone":"Asia/Shanghai",
    "iso:country":"CN",
    "name:und_x_variant":[
        "T\u2019ien-tien",
        "Tiandian",
        "\u7530\u5e97",
        "Tiandian Zhen",
        "\u7530\u5e97\u9547"
    ],
    "wof:name":"Tiandian",
    "wof:placetype":"locality"
},
  "geometry": {"coordinates":[113.44841,31.02945],"type":"Point"}
}