{
  "type": "Feature",
  "properties": {
    "gn:admin1_code":"4.0",
    "gn:asciiname":"Xinnan Shiliu Dadui",
    "gn:country_code":"CN",
    "gn:dem":0,
    "gn:feature_class":"P",
    "gn:feature_code":"PPLF",
    "gn:name":"Xinnan Shiliu Dadui",
    "gn:population":0,
    "gn:timezone":"Asia/Shanghai",
    "iso:country":"CN",
    "name:zho_x_preferred":[
        "\u65b0\u5357\u5341\u516d\u5927\u961f"
    ],
    "wof:name":"Xinnan Shiliu Dadui",
    "wof:placetype":"locality"
},
  "geometry": {"coordinates":[120.30800000000001,33.6362],"type":"Point"}
}