{
  "type": "Feature",
  "properties": {
    "gn:admin1_code":"24.0",
    "gn:asciiname":"Yushuliang",
    "gn:country_code":"CN",
    "gn:dem":1545,
    "gn:feature_class":"P",
    "gn:feature_code":"PPL",
    "gn:name":"Yushuliang",
    "gn:population":0,
    "gn:timezone":"Asia/Shanghai",
    "iso:country":"CN",
    "name:zho_x_preferred":[
        "\u6986\u6811\u6881"
    ],
    "wof:name":"Yushuliang",
    "wof:placetype":"locality"
},
  "geometry": {"coordinates":[112.3439,38.02103],"type":"Point"}
}