{
  "type": "Feature",
  "properties": {
    "gn:admin1_code":"25.0",
    "gn:asciiname":"Ximingzhaoxiancun",
    "gn:country_code":"CN",
    "gn:dem":51,
    "gn:feature_class":"P",
    "gn:feature_code":"PPL",
    "gn:name":"Ximingzhaoxiancun",
    "gn:population":0,
    "gn:timezone":"Asia/Shanghai",
    "iso:country":"CN",
    "name:zho_x_preferred":[
        "\u897f\u660e\u7167\u73b0\u6751"
    ],
    "wof:name":"Ximingzhaoxiancun",
    "wof:placetype":"locality"
},
  "geometry": {"coordinates":[119.30192,35.47300999999999],"type":"Point"}
}