{
  "type": "Feature",
  "properties": {
    "gn:admin1_code":"13",
    "gn:asciiname":"Segezikule",
    "gn:country_code":"CN",
    "gn:dem":233,
    "gn:feature_class":"P",
    "gn:feature_code":"PPL",
    "gn:name":"Segezikule",
    "gn:population":0,
    "gn:timezone":"Asia/Urumqi",
    "iso:country":"CN",
    "name:und_x_variant":[
        "\u8272\u683c\u5b5c\u5e93\u52d2"
    ],
    "wof:name":"Segezikule",
    "wof:placetype":"locality"
},
  "geometry": {"coordinates":[89.62354999999999,42.98129],"type":"Point"}
}