{
  "type": "Feature",
  "properties": {
    "gn:admin1_code":"18.0",
    "gn:asciiname":"Wuguishi",
    "gn:country_code":"CN",
    "gn:dem":640,
    "gn:feature_class":"P",
    "gn:feature_code":"PPL",
    "gn:name":"Wuguishi",
    "gn:population":0,
    "gn:timezone":"Asia/Shanghai",
    "iso:country":"CN",
    "name:zho_x_preferred":[
        "\u4e4c\u9f9f\u77f3"
    ],
    "wof:name":"Wuguishi",
    "wof:placetype":"locality"
},
  "geometry": {"coordinates":[108.20399999999999,27.0364],"type":"Point"}
}