{
  "type": "Feature",
  "properties": {
    "gn:admin1_code":"15.0",
    "gn:asciiname":"Liushuqu",
    "gn:country_code":"CN",
    "gn:dem":1590,
    "gn:feature_class":"P",
    "gn:feature_code":"PPL",
    "gn:name":"Liushuqu",
    "gn:population":0,
    "gn:timezone":"Asia/Shanghai",
    "iso:country":"CN",
    "name:und_x_variant":[
        "\u67f3\u6811\u6e20"
    ],
    "wof:name":"Liushuqu",
    "wof:placetype":"locality"
},
  "geometry": {"coordinates":[106.90206999999999,36.16945],"type":"Point"}
}