{
  "type": "Feature",
  "properties": {
    "gn:admin1_code":"19.0",
    "gn:asciiname":"Daqingdingzigou",
    "gn:country_code":"CN",
    "gn:dem":399,
    "gn:feature_class":"P",
    "gn:feature_code":"PPL",
    "gn:name":"Daqingdingzigou",
    "gn:population":0,
    "gn:timezone":"Asia/Shanghai",
    "iso:country":"CN",
    "name:zho_x_preferred":[
        "\u5927\u9752\u9876\u5b50\u6c9f"
    ],
    "wof:name":"Daqingdingzigou",
    "wof:placetype":"locality"
},
  "geometry": {"coordinates":[125.70179,41.06625],"type":"Point"}
}