{
  "type": "Feature",
  "properties": {
    "gn:admin1_code":"29.0",
    "gn:asciiname":"Bapi",
    "gn:country_code":"CN",
    "gn:dem":2737,
    "gn:feature_class":"P",
    "gn:feature_code":"PPL",
    "gn:name":"Bapi",
    "gn:population":0,
    "gn:timezone":"Asia/Shanghai",
    "iso:country":"CN",
    "name:ceb_x_preferred":[
        "Bapi"
    ],
    "name:fra_x_preferred":[
        "Bapi"
    ],
    "name:swe_x_preferred":[
        "Bapi"
    ],
    "name:und_x_variant":[
        "\u516b\u76ae"
    ],
    "wof:name":"Bapi",
    "wof:placetype":"locality"
},
  "geometry": {"coordinates":[103.20744000000001,26.81658],"type":"Point"}
}