{
  "type": "Feature",
  "properties": {
    "gn:admin1_code":"32.0",
    "gn:asciiname":"Shanglixihe",
    "gn:country_code":"CN",
    "gn:dem":753,
    "gn:feature_class":"P",
    "gn:feature_code":"PPL",
    "gn:name":"Shanglixihe",
    "gn:population":0,
    "gn:timezone":"Asia/Shanghai",
    "iso:country":"CN",
    "name:zho_x_preferred":[
        "\u4e0a\u5229\u6eaa\u6cb3"
    ],
    "wof:name":"Shanglixihe",
    "wof:placetype":"locality"
},
  "geometry": {"coordinates":[107.634,31.9129],"type":"Point"}
}