{
  "type": "Feature",
  "properties": {
    "gn:admin1_code":"31.0",
    "gn:asciiname":"Hongtian Nongchang Shijiudui",
    "gn:country_code":"CN",
    "gn:dem":81,
    "gn:feature_class":"P",
    "gn:feature_code":"PPLF",
    "gn:name":"Hongtian Nongchang Shijiudui",
    "gn:population":0,
    "gn:timezone":"Asia/Shanghai",
    "iso:country":"CN",
    "name:und_x_variant":[
        "\u7ea2\u7530\u519c\u573a\u5341\u4e5d\u961f"
    ],
    "wof:name":"Hongtian Nongchang Shijiudui",
    "wof:placetype":"locality"
},
  "geometry": {"coordinates":[108.9609,19.30844],"type":"Point"}
}