{
  "type": "Feature",
  "properties": {
    "gn:admin1_code":"26.0",
    "gn:asciiname":"Shijiayuan",
    "gn:country_code":"CN",
    "gn:dem":913,
    "gn:feature_class":"P",
    "gn:feature_code":"PPLA4",
    "gn:name":"Shijiayuan",
    "gn:population":0,
    "gn:timezone":"Asia/Shanghai",
    "iso:country":"CN",
    "name:und_x_variant":[
        "\u53f2\u5bb6\u9662"
    ],
    "wof:name":"Shijiayuan",
    "wof:placetype":"locality"
},
  "geometry": {"coordinates":[106.00532,33.2897],"type":"Point"}
}