{
  "type": "Feature",
  "properties": {
    "gn:admin1_code":"24.0",
    "gn:asciiname":"Lijiazhuang",
    "gn:country_code":"CN",
    "gn:dem":857,
    "gn:feature_class":"P",
    "gn:feature_code":"PPL",
    "gn:name":"Lijiazhuang",
    "gn:population":0,
    "gn:timezone":"Asia/Shanghai",
    "iso:country":"CN",
    "name:und_x_variant":[
        "\u674e\u5bb6\u5e84"
    ],
    "wof:name":"Lijiazhuang",
    "wof:placetype":"locality"
},
  "geometry": {"coordinates":[111.51976999999999,35.83501],"type":"Point"}
}