{
  "type": "Feature",
  "properties": {
    "gn:admin1_code":"22.0",
    "gn:asciiname":"Hewancun",
    "gn:country_code":"CN",
    "gn:dem":555,
    "gn:feature_class":"P",
    "gn:feature_code":"PPL",
    "gn:name":"Hewancun",
    "gn:population":0,
    "gn:timezone":"Asia/Shanghai",
    "iso:country":"CN",
    "name:zho_x_preferred":[
        "\u6cb3\u6e7e\u6751"
    ],
    "wof:name":"Hewancun",
    "wof:placetype":"locality"
},
  "geometry": {"coordinates":[116.20405,40.52813],"type":"Point"}
}