{
  "type": "Feature",
  "properties": {
    "gn:admin1_code":"16",
    "gn:asciiname":"Jinxiu",
    "gn:country_code":"CN",
    "gn:dem":908,
    "gn:feature_class":"P",
    "gn:feature_code":"PPLA3",
    "gn:name":"Jinxiu",
    "gn:population":0,
    "gn:timezone":"Asia/Shanghai",
    "iso:country":"CN",
    "name:deu_x_preferred":[
        "Jinxiu"
    ],
    "name:fas_x_preferred":[
        "\u0698\u06cc\u0646\u06af\u0634\u06cc\u0648"
    ],
    "name:jpn_x_preferred":[
        "\u91d1\u79c0\u30e4\u30aa\u65cf\u81ea\u6cbb\u770c"
    ],
    "name:nor_x_preferred":[
        "Jinxiu Yao"
    ],
    "name:spa_x_preferred":[
        "Jinxiu"
    ],
    "name:swe_x_preferred":[
        "Jinxiu"
    ],
    "name:und_x_variant":[
        "Chin-hsiu-chen",
        "Chin-hsiu",
        "Kinsiu",
        "Chin-hsiu-ku-chih",
        "Chin-hsiu-hsiang",
        "Ta-yao-shan-yao-tsu-tzu-chih-hsien",
        "Ta-yao-shan",
        "Jinxiu"
    ],
    "name:vie_x_preferred":[
        "Kim T\u00fa"
    ],
    "name:zho_x_preferred":[
        "Ta-yao-shan-hsien-yao-tsu-tzu-chih-ch\u2019\u00fc"
    ],
    "name:zho_x_variant":[
        "Ta-yao-shan-yao-tsu-tzu-chih-ch\u2019\u00fc",
        "Chin-hsiu-ts\u2019un",
        "\u91d1\u79c0",
        "\u91d1\u79c0\u7476\u65cf\u81ea\u6cbb\u53bf"
    ],
    "wof:name":"Jinxiu",
    "wof:placetype":"locality"
},
  "geometry": {"coordinates":[110.18009000000001,24.13721],"type":"Point"}
}