{
  "type": "Feature",
  "properties": {
    "gn:admin1_code":"16",
    "gn:asciiname":"Jinxiu",
    "gn:country_code":"CN",
    "gn:dem":908,
    "gn:feature_class":"P",
    "gn:feature_code":"PPLA3",
    "gn:name":"Jinxiu",
    "gn:population":0,
    "gn:timezone":"Asia/Shanghai",
    "iso:country":"CN",
    "name:und_x_variant":[
        "Chin-hsiu-chen",
        "Chin-hsiu",
        "Kinsiu",
        "Chin-hsiu-ku-chih",
        "Chin-hsiu-hsiang",
        "Ta-yao-shan-yao-tsu-tzu-chih-hsien",
        "Ta-yao-shan",
        "Jinxiu"
    ],
    "name:zho_x_preferred":[
        "Ta-yao-shan-hsien-yao-tsu-tzu-chih-ch\u2019\u00fc"
    ],
    "name:zho_x_variant":[
        "Ta-yao-shan-yao-tsu-tzu-chih-ch\u2019\u00fc",
        "Chin-hsiu-ts\u2019un",
        "\u91d1\u79c0"
    ],
    "wof:name":"Jinxiu",
    "wof:placetype":"locality"
},
  "geometry": {"coordinates":[110.18009000000001,24.13721],"type":"Point"}
}