{
  "type": "Feature",
  "properties": {
    "gn:admin1_code":"6.0",
    "gn:asciiname":"Tangda",
    "gn:country_code":"CN",
    "gn:dem":3644,
    "gn:feature_class":"P",
    "gn:feature_code":"PPL",
    "gn:name":"Tangda",
    "gn:population":0,
    "gn:timezone":"Asia/Urumqi",
    "iso:country":"CN",
    "name:zho_x_preferred":[
        "\u5858\u8fbe"
    ],
    "wof:name":"Tangda",
    "wof:placetype":"locality"
},
  "geometry": {"coordinates":[97.00499000000001,33.25788],"type":"Point"}
}