{
  "type": "Feature",
  "properties": {
    "gn:admin1_code":"14.0",
    "gn:asciiname":"Tangru",
    "gn:country_code":"CN",
    "gn:dem":4554,
    "gn:feature_class":"P",
    "gn:feature_code":"PPL",
    "gn:name":"Tangru",
    "gn:population":0,
    "gn:timezone":"Asia/Urumqi",
    "iso:country":"CN",
    "name:zho_x_preferred":[
        "\u5510\u5982"
    ],
    "wof:name":"Tangru",
    "wof:placetype":"locality"
},
  "geometry": {"coordinates":[84.76909999999999,29.3938],"type":"Point"}
}