{
  "type": "Feature",
  "properties": {
    "gn:admin1_code":"29",
    "gn:asciiname":"Zhantun",
    "gn:country_code":"CN",
    "gn:dem":1856,
    "gn:feature_class":"P",
    "gn:feature_code":"PPL",
    "gn:name":"Zhantun",
    "gn:population":0,
    "gn:timezone":"Asia/Shanghai",
    "iso:country":"CN",
    "name:zho_x_preferred":[
        "\u7ad9\u5c6f"
    ],
    "wof:name":"Zhantun",
    "wof:placetype":"locality"
},
  "geometry": {"coordinates":[103.355,24.9157],"type":"Point"}
}