{
  "type": "Feature",
  "properties": {
    "gn:admin1_code":"29.0",
    "gn:asciiname":"Fengchuipo",
    "gn:country_code":"CN",
    "gn:dem":1914,
    "gn:feature_class":"P",
    "gn:feature_code":"PPL",
    "gn:name":"Fengchuipo",
    "gn:population":0,
    "gn:timezone":"Asia/Shanghai",
    "iso:country":"CN",
    "name:zho_x_preferred":[
        "\u98ce\u5439\u5761"
    ],
    "wof:name":"Fengchuipo",
    "wof:placetype":"locality"
},
  "geometry": {"coordinates":[98.5954,24.5749],"type":"Point"}
}