{
  "type": "Feature",
  "properties": {
    "gn:admin1_code":"10",
    "gn:asciiname":"Gangfang",
    "gn:country_code":"CN",
    "gn:dem":589,
    "gn:feature_class":"P",
    "gn:feature_code":"PPL",
    "gn:name":"Gangfang",
    "gn:population":0,
    "gn:timezone":"Asia/Shanghai",
    "iso:country":"CN",
    "name:zho_x_preferred":[
        "\u7f38\u623f"
    ],
    "wof:name":"Gangfang",
    "wof:placetype":"locality"
},
  "geometry": {"coordinates":[116.95394,41.16443],"type":"Point"}
}