{
  "type": "Feature",
  "properties": {
    "gn:admin1_code":"8.0",
    "gn:asciiname":"Qingshancun",
    "gn:country_code":"CN",
    "gn:dem":284,
    "gn:feature_class":"P",
    "gn:feature_code":"PPL",
    "gn:name":"Qingshancun",
    "gn:population":0,
    "gn:timezone":"Asia/Shanghai",
    "iso:country":"CN",
    "name:zho_x_preferred":[
        "\u9752\u5c71\u6751"
    ],
    "wof:name":"Qingshancun",
    "wof:placetype":"locality"
},
  "geometry": {"coordinates":[127.89876,45.59874],"type":"Point"}
}