{
  "type": "Feature",
  "properties": {
    "gn:admin1_code":"29",
    "gn:asciiname":"Huashiban",
    "gn:country_code":"CN",
    "gn:dem":1362,
    "gn:feature_class":"P",
    "gn:feature_code":"PPL",
    "gn:name":"Huashiban",
    "gn:population":0,
    "gn:timezone":"Asia/Shanghai",
    "iso:country":"CN",
    "name:zho_x_preferred":[
        "\u6ed1\u77f3\u677f"
    ],
    "wof:name":"Huashiban",
    "wof:placetype":"locality"
},
  "geometry": {"coordinates":[104.53400000000001,24.182],"type":"Point"}
}