{
  "type": "Feature",
  "properties": {
    "gn:admin1_code":"4.0",
    "gn:asciiname":"Lutan",
    "gn:country_code":"CN",
    "gn:dem":-1,
    "gn:feature_class":"P",
    "gn:feature_code":"PPL",
    "gn:name":"Lutan",
    "gn:population":0,
    "gn:timezone":"Asia/Shanghai",
    "iso:country":"CN",
    "name:zho_x_preferred":[
        "Lutan"
    ],
    "name:zho_x_variant":[
        "\u8def\u6ee9"
    ],
    "wof:name":"Lutan",
    "wof:placetype":"locality"
},
  "geometry": {"coordinates":[119.91568999999998,33.73860999999999],"type":"Point"}
}