{
  "type": "Feature",
  "properties": {
    "gn:admin1_code":"10",
    "gn:asciiname":"Zhuanwayao",
    "gn:country_code":"CN",
    "gn:dem":319,
    "gn:feature_class":"P",
    "gn:feature_code":"PPL",
    "gn:name":"Zhuanwayao",
    "gn:population":0,
    "gn:timezone":"Asia/Shanghai",
    "iso:country":"CN",
    "name:zho_x_preferred":[
        "\u7816\u74e6\u7a91"
    ],
    "wof:name":"Zhuanwayao",
    "wof:placetype":"locality"
},
  "geometry": {"coordinates":[117.91556,40.87602],"type":"Point"}
}