{
  "type": "Feature",
  "properties": {
    "gn:admin1_code":"33.0",
    "gn:asciiname":"Nongzhuang",
    "gn:country_code":"CN",
    "gn:dem":1240,
    "gn:feature_class":"P",
    "gn:feature_code":"PPL",
    "gn:name":"Nongzhuang",
    "gn:population":0,
    "gn:timezone":"Asia/Shanghai",
    "iso:country":"CN",
    "name:zho_x_preferred":[
        "\u519c\u5e84"
    ],
    "wof:name":"Nongzhuang",
    "wof:placetype":"locality"
},
  "geometry": {"coordinates":[108.42531,29.97122],"type":"Point"}
}