{
  "type": "Feature",
  "properties": {
    "gn:admin1_code":"32.0",
    "gn:asciiname":"Daobeiya",
    "gn:country_code":"CN",
    "gn:dem":701,
    "gn:feature_class":"P",
    "gn:feature_code":"PPL",
    "gn:name":"Daobeiya",
    "gn:population":0,
    "gn:timezone":"Asia/Shanghai",
    "iso:country":"CN",
    "name:zho_x_preferred":[
        "\u5012\u7891\u57ad"
    ],
    "wof:name":"Daobeiya",
    "wof:placetype":"locality"
},
  "geometry": {"coordinates":[106.38647,32.0026],"type":"Point"}
}