{
  "type": "Feature",
  "properties": {
    "gn:admin1_code":"1.0",
    "gn:asciiname":"Yanmingcun",
    "gn:country_code":"CN",
    "gn:dem":25,
    "gn:feature_class":"P",
    "gn:feature_code":"PPL",
    "gn:name":"Yanmingcun",
    "gn:population":0,
    "gn:timezone":"Asia/Shanghai",
    "iso:country":"CN",
    "name:zho_x_preferred":[
        "\u4e25\u660e\u6751"
    ],
    "wof:name":"Yanmingcun",
    "wof:placetype":"locality"
},
  "geometry": {"coordinates":[117.7238,31.42657],"type":"Point"}
}