{
  "type": "Feature",
  "properties": {
    "gn:admin1_code":"29",
    "gn:asciiname":"Dengjiazhuang",
    "gn:country_code":"CN",
    "gn:dem":1943,
    "gn:feature_class":"P",
    "gn:feature_code":"PPL",
    "gn:name":"Dengjiazhuang",
    "gn:population":0,
    "gn:timezone":"Asia/Shanghai",
    "iso:country":"CN",
    "name:zho_x_preferred":[
        "\u9093\u5bb6\u5e84"
    ],
    "wof:name":"Dengjiazhuang",
    "wof:placetype":"locality"
},
  "geometry": {"coordinates":[102.80200000000001,24.8194],"type":"Point"}
}