{
  "type": "Feature",
  "properties": {
    "gn:admin1_code":"15.0",
    "gn:asciiname":"Fengxigou",
    "gn:country_code":"CN",
    "gn:dem":1332,
    "gn:feature_class":"P",
    "gn:feature_code":"PPL",
    "gn:name":"Fengxigou",
    "gn:population":0,
    "gn:timezone":"Asia/Shanghai",
    "iso:country":"CN",
    "name:zho_x_preferred":[
        "\u51af\u897f\u6c9f"
    ],
    "wof:name":"Fengxigou",
    "wof:placetype":"locality"
},
  "geometry": {"coordinates":[108.417,35.8068],"type":"Point"}
}