{
  "type": "Feature",
  "properties": {
    "gn:admin1_code":"8.0",
    "gn:asciiname":"Longshuiquan",
    "gn:country_code":"CN",
    "gn:dem":167,
    "gn:feature_class":"P",
    "gn:feature_code":"PPL",
    "gn:name":"Longshuiquan",
    "gn:population":0,
    "gn:timezone":"Asia/Shanghai",
    "iso:country":"CN",
    "name:zho_x_preferred":[
        "\u9f99\u6c34\u6cc9"
    ],
    "wof:name":"Longshuiquan",
    "wof:placetype":"locality"
},
  "geometry": {"coordinates":[124.85326000000001,47.68705],"type":"Point"}
}