{
  "type": "Feature",
  "properties": {
    "gn:admin1_code":"26.0",
    "gn:asciiname":"Qiantuantuangou",
    "gn:country_code":"CN",
    "gn:dem":1041,
    "gn:feature_class":"P",
    "gn:feature_code":"PPL",
    "gn:name":"Qiantuantuangou",
    "gn:population":0,
    "gn:timezone":"Asia/Shanghai",
    "iso:country":"CN",
    "name:zho_x_preferred":[
        "\u524d\u56e2\u56e2\u6c9f"
    ],
    "wof:name":"Qiantuantuangou",
    "wof:placetype":"locality"
},
  "geometry": {"coordinates":[110.21444,38.61543],"type":"Point"}
}