{
  "type": "Feature",
  "properties": {
    "gn:admin1_code":"14",
    "gn:asciiname":"Ngazha",
    "gn:country_code":"CN",
    "gn:dem":3682,
    "gn:feature_class":"P",
    "gn:feature_code":"PPL",
    "gn:name":"Ngazha",
    "gn:population":0,
    "gn:timezone":"Asia/Urumqi",
    "iso:country":"CN",
    "name:bod_x_preferred":[
        "\u0f66\u0f94\u0f42\u0f66\u0f0b\u0f42\u0fb2"
    ],
    "name:bod_x_variant":[
        "\u0f63\u0f94\u0f0b\u0f56\u0f40\u0fb2"
    ],
    "name:und_x_variant":[
        "Azha",
        "Ngagzha",
        "Anzha"
    ],
    "name:zho_x_preferred":[
        "\u963f\u624e"
    ],
    "name:zho_x_variant":[
        "\u5b89\u624e"
    ],
    "wof:name":"Ngazha",
    "wof:placetype":"locality"
},
  "geometry": {"coordinates":[91.27244,29.36714000000001],"type":"Point"}
}