{
  "type": "Feature",
  "properties": {
    "gn:admin1_code":"9.0",
    "gn:asciiname":"Laodaizhuang",
    "gn:country_code":"CN",
    "gn:dem":156,
    "gn:feature_class":"P",
    "gn:feature_code":"PPL",
    "gn:name":"Laodaizhuang",
    "gn:population":0,
    "gn:timezone":"Asia/Shanghai",
    "iso:country":"CN",
    "name:zho_x_preferred":[
        "\u8001\u4ee3\u5e84"
    ],
    "wof:name":"Laodaizhuang",
    "wof:placetype":"locality"
},
  "geometry": {"coordinates":[113.05932,33.19378],"type":"Point"}
}