{
  "type": "Feature",
  "properties": {
    "gn:admin1_code":"4.0",
    "gn:asciiname":"Dazhaiji",
    "gn:country_code":"CN",
    "gn:dem":4,
    "gn:feature_class":"P",
    "gn:feature_code":"PPL",
    "gn:name":"Dazhaiji",
    "gn:population":0,
    "gn:timezone":"Asia/Shanghai",
    "iso:country":"CN",
    "name:und_x_variant":[
        "\u5927\u5b85\u57fa"
    ],
    "wof:name":"Dazhaiji",
    "wof:placetype":"locality"
},
  "geometry": {"coordinates":[121.06352,31.49336],"type":"Point"}
}