{
  "type": "Feature",
  "properties": {
    "gn:admin1_code":"30",
    "gn:asciiname":"Tianzai'ao",
    "gn:country_code":"CN",
    "gn:dem":185,
    "gn:feature_class":"P",
    "gn:feature_code":"PPL",
    "gn:name":"Tianzai\u2019ao",
    "gn:population":0,
    "gn:timezone":"Asia/Shanghai",
    "iso:country":"CN",
    "name:und_x_variant":[
        "Tianzai\u2019ao"
    ],
    "name:zho_x_preferred":[
        "\u7530\u4ed4\u5773"
    ],
    "wof:name":"Tianzai'ao",
    "wof:placetype":"locality"
},
  "geometry": {"coordinates":[116.50351999999999,24.29113],"type":"Point"}
}