{
  "type": "Feature",
  "properties": {
    "gn:admin1_code":"2.0",
    "gn:asciiname":"Xiaopu",
    "gn:country_code":"CN",
    "gn:dem":11,
    "gn:feature_class":"P",
    "gn:feature_code":"PPLA4",
    "gn:name":"Xiaopu",
    "gn:population":0,
    "gn:timezone":"Asia/Shanghai",
    "iso:country":"CN",
    "name:und_x_variant":[
        "\u5c0f\u6d66",
        "Xiaopu Zhen"
    ],
    "name:zho_x_preferred":[
        "\u5c0f\u6d66\u9547"
    ],
    "wof:name":"Xiaopu",
    "wof:placetype":"locality"
},
  "geometry": {"coordinates":[119.83105999999999,31.03025],"type":"Point"}
}