{
  "type": "Feature",
  "properties": {
    "gn:admin1_code":"11",
    "gn:asciiname":"Lucaotang",
    "gn:country_code":"CN",
    "gn:dem":474,
    "gn:feature_class":"P",
    "gn:feature_code":"PPL",
    "gn:name":"Lucaotang",
    "gn:population":0,
    "gn:timezone":"Asia/Shanghai",
    "iso:country":"CN",
    "name:zho_x_preferred":[
        "\u9c81\u8349\u5858"
    ],
    "wof:name":"Lucaotang",
    "wof:placetype":"locality"
},
  "geometry": {"coordinates":[112.0157,25.37668],"type":"Point"}
}