{
  "type": "Feature",
  "properties": {
    "gn:admin1_code":"4.0",
    "gn:asciiname":"Houlongxing",
    "gn:country_code":"CN",
    "gn:dem":1,
    "gn:feature_class":"P",
    "gn:feature_code":"PPL",
    "gn:name":"Houlongxing",
    "gn:population":0,
    "gn:timezone":"Asia/Shanghai",
    "iso:country":"CN",
    "name:zho_x_preferred":[
        "Houlongxing"
    ],
    "name:zho_x_variant":[
        "\u540e\u9686\u5174"
    ],
    "wof:name":"Houlongxing",
    "wof:placetype":"locality"
},
  "geometry": {"coordinates":[119.60081,33.08549],"type":"Point"}
}