{
  "type": "Feature",
  "properties": {
    "gn:admin1_code":"12.0",
    "gn:asciiname":"Panlongwan",
    "gn:country_code":"CN",
    "gn:dem":1331,
    "gn:feature_class":"P",
    "gn:feature_code":"PPL",
    "gn:name":"Panlongwan",
    "gn:population":0,
    "gn:timezone":"Asia/Shanghai",
    "iso:country":"CN",
    "name:zho_x_preferred":[
        "\u76d8\u9f99\u6e7e"
    ],
    "wof:name":"Panlongwan",
    "wof:placetype":"locality"
},
  "geometry": {"coordinates":[109.97181999999999,30.43211],"type":"Point"}
}