{
  "type": "Feature",
  "properties": {
    "gn:admin1_code":"11.0",
    "gn:asciiname":"Guiren'ao",
    "gn:country_code":"CN",
    "gn:dem":927,
    "gn:feature_class":"P",
    "gn:feature_code":"PPL",
    "gn:name":"Guiren\u2019ao",
    "gn:population":0,
    "gn:timezone":"Asia/Shanghai",
    "iso:country":"CN",
    "name:und_x_variant":[
        "Guiren\u2019ao"
    ],
    "name:zho_x_preferred":[
        "\u6842\u4ec1\u5773"
    ],
    "wof:name":"Guiren'ao",
    "wof:placetype":"locality"
},
  "geometry": {"coordinates":[112.92601999999999,25.57041],"type":"Point"}
}