{
  "type": "Feature",
  "properties": {
    "gn:admin1_code":"29.0",
    "gn:asciiname":"Mengpianjie",
    "gn:country_code":"CN",
    "gn:dem":1346,
    "gn:feature_class":"P",
    "gn:feature_code":"PPL",
    "gn:name":"Mengpianjie",
    "gn:population":0,
    "gn:timezone":"Asia/Shanghai",
    "iso:country":"CN",
    "name:zho_x_preferred":[
        "\u52d0\u7247\u8857"
    ],
    "wof:name":"Mengpianjie",
    "wof:placetype":"locality"
},
  "geometry": {"coordinates":[100.658,24.2903],"type":"Point"}
}