{
  "type": "Feature",
  "properties": {
    "gn:admin1_code":"9.0",
    "gn:asciiname":"Mengjiazhuang",
    "gn:country_code":"CN",
    "gn:dem":132,
    "gn:feature_class":"P",
    "gn:feature_code":"PPL",
    "gn:name":"Mengjiazhuang",
    "gn:population":0,
    "gn:timezone":"Asia/Shanghai",
    "iso:country":"CN",
    "name:zho_x_preferred":[
        "\u5b5f\u5bb6\u5e84"
    ],
    "name:zho_x_variant":[
        "\u5b5f\u5bb6\u5e84\u9547"
    ],
    "wof:name":"Mengjiazhuang",
    "wof:placetype":"locality"
},
  "geometry": {"coordinates":[114.1786,36.08083],"type":"Point"}
}