{
  "type": "Feature",
  "properties": {
    "gn:admin1_code":"5.0",
    "gn:asciiname":"Dazhangjiayao",
    "gn:country_code":"CN",
    "gn:dem":152,
    "gn:feature_class":"P",
    "gn:feature_code":"PPL",
    "gn:name":"Dazhangjiayao",
    "gn:population":0,
    "gn:timezone":"Asia/Shanghai",
    "iso:country":"CN",
    "name:zho_x_preferred":[
        "\u5927\u5f20\u5bb6\u7a91"
    ],
    "wof:name":"Dazhangjiayao",
    "wof:placetype":"locality"
},
  "geometry": {"coordinates":[123.69453,44.00623],"type":"Point"}
}