{
  "type": "Feature",
  "properties": {
    "gn:admin1_code":"4.0",
    "gn:asciiname":"Duotuancun",
    "gn:country_code":"CN",
    "gn:dem":2,
    "gn:feature_class":"P",
    "gn:feature_code":"PPL",
    "gn:name":"Duotuancun",
    "gn:population":0,
    "gn:timezone":"Asia/Shanghai",
    "iso:country":"CN",
    "name:zho_x_preferred":[
        "\u579b\u56e2\u6751"
    ],
    "wof:name":"Duotuancun",
    "wof:placetype":"locality"
},
  "geometry": {"coordinates":[120.39209,32.88849],"type":"Point"}
}