{
  "type": "Feature",
  "properties": {
    "gn:admin1_code":"11.0",
    "gn:asciiname":"Shangguan",
    "gn:country_code":"CN",
    "gn:dem":282,
    "gn:feature_class":"P",
    "gn:feature_code":"PPL",
    "gn:name":"Shangguan",
    "gn:population":0,
    "gn:timezone":"Asia/Shanghai",
    "iso:country":"CN",
    "name:deu_x_preferred":[
        "Shangguan"
    ],
    "name:zho_x_preferred":[
        "\u4e0a\u9986"
    ],
    "wof:name":"Shangguan",
    "wof:placetype":"locality"
},
  "geometry": {"coordinates":[113.93535,26.59708],"type":"Point"}
}