{
  "type": "Feature",
  "properties": {
    "gn:admin1_code":"11.0",
    "gn:asciiname":"Shantangchong",
    "gn:country_code":"CN",
    "gn:dem":84,
    "gn:feature_class":"P",
    "gn:feature_code":"PPL",
    "gn:name":"Shantangchong",
    "gn:population":0,
    "gn:timezone":"Asia/Shanghai",
    "iso:country":"CN",
    "name:zho_x_preferred":[
        "\u5c71\u5858\u51b2"
    ],
    "wof:name":"Shantangchong",
    "wof:placetype":"locality"
},
  "geometry": {"coordinates":[112.53145000000001,27.01706],"type":"Point"}
}