{
  "type": "Feature",
  "properties": {
    "gn:admin1_code":"29.0",
    "gn:asciiname":"Xintun",
    "gn:country_code":"CN",
    "gn:dem":2100,
    "gn:feature_class":"P",
    "gn:feature_code":"PPL",
    "gn:name":"Xintun",
    "gn:population":0,
    "gn:timezone":"Asia/Shanghai",
    "iso:country":"CN",
    "name:deu_x_preferred":[
        "Xintun"
    ],
    "name:und_x_variant":[
        "\u65b0\u5c6f"
    ],
    "wof:name":"Xintun",
    "wof:placetype":"locality"
},
  "geometry": {"coordinates":[103.99184,25.9341],"type":"Point"}
}