{
  "type": "Feature",
  "properties": {
    "gn:admin1_code":"30.0",
    "gn:asciiname":"Lundaocun",
    "gn:country_code":"CN",
    "gn:dem":52,
    "gn:feature_class":"P",
    "gn:feature_code":"PPL",
    "gn:name":"Lundaocun",
    "gn:population":0,
    "gn:timezone":"Asia/Urumqi",
    "iso:country":"CN",
    "name:zho_x_preferred":[
        "\u4f26\u9053\u6751"
    ],
    "wof:name":"Lundaocun",
    "wof:placetype":"locality"
},
  "geometry": {"coordinates":[110.72195000000001,22.03925],"type":"Point"}
}