{
  "type": "Feature",
  "properties": {
    "gn:admin1_code":"7.0",
    "gn:asciiname":"Hongcuoku",
    "gn:country_code":"CN",
    "gn:dem":18,
    "gn:feature_class":"P",
    "gn:feature_code":"PPL",
    "gn:name":"Hongcuoku",
    "gn:population":0,
    "gn:timezone":"Asia/Shanghai",
    "iso:country":"CN",
    "name:zho_x_preferred":[
        "\u6d2a\u539d\u5800"
    ],
    "wof:name":"Hongcuoku",
    "wof:placetype":"locality"
},
  "geometry": {"coordinates":[118.47948,24.96955],"type":"Point"}
}