{
  "type": "Feature",
  "properties": {
    "gn:admin1_code":"18",
    "gn:asciiname":"Yantang",
    "gn:country_code":"CN",
    "gn:dem":1224,
    "gn:feature_class":"P",
    "gn:feature_code":"PPL",
    "gn:name":"Yantang",
    "gn:population":0,
    "gn:timezone":"Asia/Shanghai",
    "iso:country":"CN",
    "name:ceb_x_preferred":[
        "Yantang"
    ],
    "name:deu_x_preferred":[
        "Yantang"
    ],
    "name:swe_x_preferred":[
        "Yantang"
    ],
    "name:zho_x_preferred":[
        "\u5ca9\u5510"
    ],
    "wof:name":"Yantang",
    "wof:placetype":"locality"
},
  "geometry": {"coordinates":[106.404,25.2796],"type":"Point"}
}