{
  "type": "Feature",
  "properties": {
    "gn:admin1_code":"15.0",
    "gn:asciiname":"Qinjia Taizi",
    "gn:country_code":"CN",
    "gn:dem":1290,
    "gn:feature_class":"P",
    "gn:feature_code":"PPL",
    "gn:name":"Qinjia Taizi",
    "gn:population":0,
    "gn:timezone":"Asia/Shanghai",
    "iso:country":"CN",
    "name:zho_x_preferred":[
        "\u79e6\u5bb6\u53f0\u5b50"
    ],
    "wof:name":"Qinjia Taizi",
    "wof:placetype":"locality"
},
  "geometry": {"coordinates":[106.379,34.4627],"type":"Point"}
}