{
  "type": "Feature",
  "properties": {
    "gn:admin1_code":"32.0",
    "gn:asciiname":"Shangmalutang",
    "gn:country_code":"CN",
    "gn:dem":2025,
    "gn:feature_class":"P",
    "gn:feature_code":"PPL",
    "gn:name":"Shangmalutang",
    "gn:population":0,
    "gn:timezone":"Asia/Shanghai",
    "iso:country":"CN",
    "name:zho_x_preferred":[
        "\u4e0a\u9a6c\u9e7f\u5858"
    ],
    "wof:name":"Shangmalutang",
    "wof:placetype":"locality"
},
  "geometry": {"coordinates":[101.81100000000001,27.1762],"type":"Point"}
}