{
  "type": "Feature",
  "properties": {
    "gn:admin1_code":"32.0",
    "gn:asciiname":"Daqi",
    "gn:country_code":"CN",
    "gn:dem":715,
    "gn:feature_class":"P",
    "gn:feature_code":"PPL",
    "gn:name":"Daqi",
    "gn:population":0,
    "gn:timezone":"Asia/Shanghai",
    "iso:country":"CN",
    "name:zho_x_preferred":[
        "\u5927\u65d7"
    ],
    "wof:name":"Daqi",
    "wof:placetype":"locality"
},
  "geometry": {"coordinates":[105.134,28.1626],"type":"Point"}
}