{
  "type": "Feature",
  "properties": {
    "gn:admin1_code":"23.0",
    "gn:asciiname":"Yangdong",
    "gn:country_code":"CN",
    "gn:dem":5,
    "gn:feature_class":"P",
    "gn:feature_code":"PPL",
    "gn:name":"Yangdong",
    "gn:population":0,
    "gn:timezone":"Asia/Shanghai",
    "iso:country":"CN",
    "name:fra_x_preferred":[
        "Yangdong"
    ],
    "name:und_x_variant":[
        "\u6768\u4e1c"
    ],
    "wof:name":"Yangdong",
    "wof:placetype":"locality"
},
  "geometry": {"coordinates":[121.45397,31.37894],"type":"Point"}
}