{
  "type": "Feature",
  "properties": {
    "gn:admin1_code":"01",
    "gn:asciiname":"Daqiao",
    "gn:cc2":"CN",
    "gn:country_code":"CN",
    "gn:dem":34,
    "gn:feature_class":"P",
    "gn:feature_code":"PPL",
    "gn:name":"Daqiao",
    "gn:population":0,
    "gn:timezone":"Asia/Shanghai",
    "iso:country":"CN",
    "name:und_x_variant":[
        "Ta-ch\u2019iao-chen",
        "Ta-ch\u2019iao",
        "Daqiao"
    ],
    "wof:name":"Daqiao",
    "wof:placetype":"locality"
},
  "geometry": {"coordinates":[117.76443999999999,32.30083],"type":"Point"}
}