{
  "type": "Feature",
  "properties": {
    "gn:admin1_code":"29.0",
    "gn:asciiname":"Mutizi",
    "gn:country_code":"CN",
    "gn:dem":1187,
    "gn:feature_class":"P",
    "gn:feature_code":"PPL",
    "gn:name":"Mutizi",
    "gn:population":0,
    "gn:timezone":"Asia/Shanghai",
    "iso:country":"CN",
    "name:zho_x_preferred":[
        "\u6728\u68af\u5b50"
    ],
    "wof:name":"Mutizi",
    "wof:placetype":"locality"
},
  "geometry": {"coordinates":[104.46299999999999,24.763],"type":"Point"}
}