{
  "type": "Feature",
  "properties": {
    "gn:admin1_code":"29.0",
    "gn:asciiname":"Muchang",
    "gn:country_code":"CN",
    "gn:dem":1853,
    "gn:feature_class":"P",
    "gn:feature_code":"PPL",
    "gn:name":"Muchang",
    "gn:population":0,
    "gn:timezone":"Asia/Shanghai",
    "iso:country":"CN",
    "name:und_x_variant":[
        "\u6728\u5382"
    ],
    "wof:name":"Muchang",
    "wof:placetype":"locality"
},
  "geometry": {"coordinates":[103.19701999999999,27.17475],"type":"Point"}
}