{
  "type": "Feature",
  "properties": {
    "gn:admin1_code":"9",
    "gn:asciiname":"Baimugang",
    "gn:country_code":"CN",
    "gn:dem":65,
    "gn:feature_class":"P",
    "gn:feature_code":"PPL",
    "gn:name":"Baimugang",
    "gn:population":0,
    "gn:timezone":"Asia/Shanghai",
    "iso:country":"CN",
    "name:zho_x_preferred":[
        "\u67cf\u6728\u5c97"
    ],
    "wof:name":"Baimugang",
    "wof:placetype":"locality"
},
  "geometry": {"coordinates":[114.962,34.618],"type":"Point"}
}