{
  "type": "Feature",
  "properties": {
    "gn:admin1_code":"9.0",
    "gn:asciiname":"Dasongfo",
    "gn:country_code":"CN",
    "gn:dem":77,
    "gn:feature_class":"P",
    "gn:feature_code":"PPL",
    "gn:name":"Dasongfo",
    "gn:population":0,
    "gn:timezone":"Asia/Shanghai",
    "iso:country":"CN",
    "name:zho_x_preferred":[
        "\u5927\u9001\u4f5b"
    ],
    "wof:name":"Dasongfo",
    "wof:placetype":"locality"
},
  "geometry": {"coordinates":[113.75606000000001,35.22866],"type":"Point"}
}