{
  "type": "Feature",
  "properties": {
    "gn:admin1_code":"7.0",
    "gn:asciiname":"Luosiwan",
    "gn:country_code":"CN",
    "gn:dem":493,
    "gn:feature_class":"P",
    "gn:feature_code":"PPL",
    "gn:name":"Luosiwan",
    "gn:population":0,
    "gn:timezone":"Asia/Shanghai",
    "iso:country":"CN",
    "name:und_x_variant":[
        "\u87ba\u86f3\u6e7e"
    ],
    "name:zho_x_preferred":[
        "\u87ba\u86f3\u6e7e"
    ],
    "wof:name":"Luosiwan",
    "wof:placetype":"locality"
},
  "geometry": {"coordinates":[116.60927,26.86785],"type":"Point"}
}