{
  "type": "Feature",
  "properties": {
    "gn:admin1_code":"2.0",
    "gn:asciiname":"Wangcun",
    "gn:country_code":"CN",
    "gn:dem":23,
    "gn:feature_class":"P",
    "gn:feature_code":"PPL",
    "gn:name":"Wangcun",
    "gn:population":0,
    "gn:timezone":"Asia/Shanghai",
    "iso:country":"CN",
    "name:und_x_variant":[
        "\u6c6a\u6751"
    ],
    "wof:name":"Wangcun",
    "wof:placetype":"locality"
},
  "geometry": {"coordinates":[120.04552,30.11217000000001],"type":"Point"}
}