{
  "type": "Feature",
  "properties": {
    "gn:admin1_code":"9.0",
    "gn:asciiname":"Yuzhai",
    "gn:country_code":"CN",
    "gn:dem":53,
    "gn:feature_class":"P",
    "gn:feature_code":"PPL",
    "gn:name":"Yuzhai",
    "gn:population":0,
    "gn:timezone":"Asia/Shanghai",
    "iso:country":"CN",
    "name:swe_x_preferred":[
        "Yuzhai"
    ],
    "name:zho_x_preferred":[
        "\u4e8e\u5be8"
    ],
    "wof:name":"Yuzhai",
    "wof:placetype":"locality"
},
  "geometry": {"coordinates":[114.6301,33.73414],"type":"Point"}
}