{
  "type": "Feature",
  "properties": {
    "gn:admin1_code":"4.0",
    "gn:asciiname":"Changbei",
    "gn:country_code":"CN",
    "gn:dem":6,
    "gn:feature_class":"P",
    "gn:feature_code":"PPL",
    "gn:name":"Changbei",
    "gn:population":0,
    "gn:timezone":"Asia/Shanghai",
    "iso:country":"CN",
    "name:zho_x_preferred":[
        "\u5382\u5317"
    ],
    "wof:name":"Changbei",
    "wof:placetype":"locality"
},
  "geometry": {"coordinates":[119.01470999999999,34.08472],"type":"Point"}
}