{
  "type": "Feature",
  "properties": {
    "gn:admin1_code":"7.0",
    "gn:asciiname":"Zaoling",
    "gn:country_code":"CN",
    "gn:dem":689,
    "gn:feature_class":"P",
    "gn:feature_code":"PPL",
    "gn:name":"Zaoling",
    "gn:population":0,
    "gn:timezone":"Asia/Shanghai",
    "iso:country":"CN",
    "name:zho_x_preferred":[
        "\u67a3\u5cad"
    ],
    "wof:name":"Zaoling",
    "wof:placetype":"locality"
},
  "geometry": {"coordinates":[119.30206,26.96667],"type":"Point"}
}