{
  "type": "Feature",
  "properties": {
    "gn:admin1_code":"14.0",
    "gn:asciiname":"Naqiong",
    "gn:country_code":"CN",
    "gn:dem":4851,
    "gn:feature_class":"P",
    "gn:feature_code":"PPL",
    "gn:name":"Naqiong",
    "gn:population":0,
    "gn:timezone":"Asia/Urumqi",
    "iso:country":"CN",
    "name:zho_x_preferred":[
        "\u90a3\u7a77"
    ],
    "wof:name":"Naqiong",
    "wof:placetype":"locality"
},
  "geometry": {"coordinates":[90.49126,31.58545],"type":"Point"}
}