{
  "type": "Feature",
  "properties": {
    "gn:admin1_code":"3.0",
    "gn:asciiname":"Gangshang",
    "gn:country_code":"CN",
    "gn:dem":32,
    "gn:feature_class":"P",
    "gn:feature_code":"PPL",
    "gn:name":"Gangshang",
    "gn:population":0,
    "gn:timezone":"Asia/Shanghai",
    "iso:country":"CN",
    "name:und_x_variant":[
        "\u5c97\u4e0a"
    ],
    "wof:name":"Gangshang",
    "wof:placetype":"locality"
},
  "geometry": {"coordinates":[115.676,28.29873],"type":"Point"}
}