{
  "type": "Feature",
  "properties": {
    "gn:admin1_code":"26.0",
    "gn:asciiname":"Mishichang",
    "gn:country_code":"CN",
    "gn:dem":767,
    "gn:feature_class":"P",
    "gn:feature_code":"PPL",
    "gn:name":"Mishichang",
    "gn:population":0,
    "gn:timezone":"Asia/Shanghai",
    "iso:country":"CN",
    "name:und_x_variant":[
        "\u7c73\u77f3\u5382"
    ],
    "wof:name":"Mishichang",
    "wof:placetype":"locality"
},
  "geometry": {"coordinates":[106.95048,33.32656],"type":"Point"}
}