{
  "type": "Feature",
  "properties": {
    "gn:admin1_code":"10",
    "gn:asciiname":"Nanliang",
    "gn:country_code":"CN",
    "gn:dem":1462,
    "gn:feature_class":"P",
    "gn:feature_code":"PPL",
    "gn:name":"Nanliang",
    "gn:population":0,
    "gn:timezone":"Asia/Shanghai",
    "iso:country":"CN",
    "name:zho_x_preferred":[
        "\u5357\u6881"
    ],
    "wof:name":"Nanliang",
    "wof:placetype":"locality"
},
  "geometry": {"coordinates":[116.25687000000001,41.76087],"type":"Point"}
}