{
  "type": "Feature",
  "properties": {
    "gn:admin1_code":"25",
    "gn:asciiname":"Nugushan",
    "gn:country_code":"CN",
    "gn:dem":14,
    "gn:feature_class":"P",
    "gn:feature_code":"PPL",
    "gn:name":"N\u00fcgushan",
    "gn:population":0,
    "gn:timezone":"Asia/Shanghai",
    "iso:country":"CN",
    "name:und_x_variant":[
        "N\u00fcgushan"
    ],
    "name:zho_x_preferred":[
        "\u5973\u59d1\u5c71"
    ],
    "wof:name":"Nugushan",
    "wof:placetype":"locality"
},
  "geometry": {"coordinates":[120.33904,36.23689],"type":"Point"}
}