{
  "type": "Feature",
  "properties": {
    "gn:admin1_code":"32.0",
    "gn:asciiname":"Baiyangshu",
    "gn:country_code":"CN",
    "gn:dem":2376,
    "gn:feature_class":"P",
    "gn:feature_code":"PPL",
    "gn:name":"Baiyangshu",
    "gn:population":0,
    "gn:timezone":"Asia/Shanghai",
    "iso:country":"CN",
    "name:zho_x_preferred":[
        "\u767d\u6768\u6811"
    ],
    "wof:name":"Baiyangshu",
    "wof:placetype":"locality"
},
  "geometry": {"coordinates":[102.084,27.775],"type":"Point"}
}