{
  "type": "Feature",
  "properties": {
    "gn:admin1_code":"11.0",
    "gn:asciiname":"Yandi",
    "gn:country_code":"CN",
    "gn:dem":225,
    "gn:feature_class":"P",
    "gn:feature_code":"PPL",
    "gn:name":"Yandi",
    "gn:population":0,
    "gn:timezone":"Asia/Shanghai",
    "iso:country":"CN",
    "name:ceb_x_preferred":[
        "Yandi"
    ],
    "name:swe_x_preferred":[
        "Yandi"
    ],
    "name:zho_x_preferred":[
        "\u5ca9\u5e95"
    ],
    "wof:name":"Yandi",
    "wof:placetype":"locality"
},
  "geometry": {"coordinates":[110.589,28.50124000000001],"type":"Point"}
}