{
  "type": "Feature",
  "properties": {
    "gn:admin1_code":"4.0",
    "gn:asciiname":"Liulaozhuang",
    "gn:country_code":"CN",
    "gn:dem":7,
    "gn:feature_class":"P",
    "gn:feature_code":"PPL",
    "gn:name":"Liulaozhuang",
    "gn:population":0,
    "gn:timezone":"Asia/Shanghai",
    "iso:country":"CN",
    "name:zho_x_preferred":[
        "Liulaozhuang"
    ],
    "name:zho_x_variant":[
        "\u5218\u8001\u5e84"
    ],
    "wof:name":"Liulaozhuang",
    "wof:placetype":"locality"
},
  "geometry": {"coordinates":[119.78251000000002,34.12469],"type":"Point"}
}