{
  "type": "Feature",
  "properties": {
    "gn:admin1_code":"18",
    "gn:asciiname":"Mawozhai",
    "gn:country_code":"CN",
    "gn:dem":1777,
    "gn:feature_class":"P",
    "gn:feature_code":"PPL",
    "gn:name":"Mawozhai",
    "gn:population":0,
    "gn:timezone":"Asia/Shanghai",
    "iso:country":"CN",
    "name:zho_x_preferred":[
        "\u9ebb\u7a9d\u5be8"
    ],
    "wof:name":"Mawozhai",
    "wof:placetype":"locality"
},
  "geometry": {"coordinates":[105.914,27.3687],"type":"Point"}
}