{
  "type": "Feature",
  "properties": {
    "gn:admin1_code":"11.0",
    "gn:asciiname":"Meiziyu",
    "gn:country_code":"CN",
    "gn:dem":274,
    "gn:feature_class":"P",
    "gn:feature_code":"PPL",
    "gn:name":"Meiziyu",
    "gn:population":0,
    "gn:timezone":"Asia/Shanghai",
    "iso:country":"CN",
    "name:zho_x_preferred":[
        "\u6885\u5b50\u5cea"
    ],
    "wof:name":"Meiziyu",
    "wof:placetype":"locality"
},
  "geometry": {"coordinates":[110.69018,29.43455],"type":"Point"}
}