{
  "type": "Feature",
  "properties": {
    "gn:admin1_code":"21.0",
    "gn:asciiname":"Hexinzhuang",
    "gn:country_code":"CN",
    "gn:dem":1587,
    "gn:feature_class":"P",
    "gn:feature_code":"PPL",
    "gn:name":"Hexinzhuang",
    "gn:population":0,
    "gn:timezone":"Asia/Shanghai",
    "iso:country":"CN",
    "name:zho_x_preferred":[
        "\u8d3a\u65b0\u5e84"
    ],
    "wof:name":"Hexinzhuang",
    "wof:placetype":"locality"
},
  "geometry": {"coordinates":[107.17,37.1744],"type":"Point"}
}