{
  "type": "Feature",
  "properties": {
    "gn:admin1_code":"8.0",
    "gn:asciiname":"Ducaitun",
    "gn:country_code":"CN",
    "gn:dem":152,
    "gn:feature_class":"P",
    "gn:feature_code":"PPL",
    "gn:name":"Ducaitun",
    "gn:population":0,
    "gn:timezone":"Asia/Shanghai",
    "iso:country":"CN",
    "name:zho_x_preferred":[
        "\u675c\u624d\u5c6f"
    ],
    "wof:name":"Ducaitun",
    "wof:placetype":"locality"
},
  "geometry": {"coordinates":[125.01084,47.04813],"type":"Point"}
}