{
  "type": "Feature",
  "properties": {
    "gn:admin1_code":"4.0",
    "gn:asciiname":"Sunyang",
    "gn:country_code":"CN",
    "gn:dem":3,
    "gn:feature_class":"P",
    "gn:feature_code":"PPL",
    "gn:name":"Sunyang",
    "gn:population":0,
    "gn:timezone":"Asia/Shanghai",
    "iso:country":"CN",
    "name:und_x_variant":[
        "\u5b59\u9633"
    ],
    "name:zho_x_preferred":[
        "\u5b59\u9633"
    ],
    "wof:name":"Sunyang",
    "wof:placetype":"locality"
},
  "geometry": {"coordinates":[119.99359,33.09445],"type":"Point"}
}