{
  "type": "Feature",
  "properties": {
    "gn:admin1_code":"2.0",
    "gn:asciiname":"Paitou",
    "gn:country_code":"CN",
    "gn:dem":18,
    "gn:feature_class":"P",
    "gn:feature_code":"PPL",
    "gn:name":"Paitou",
    "gn:population":0,
    "gn:timezone":"Asia/Shanghai",
    "iso:country":"CN",
    "name:zho_x_preferred":[
        "\u724c\u5934"
    ],
    "wof:name":"Paitou",
    "wof:placetype":"locality"
},
  "geometry": {"coordinates":[121.62027,29.47278],"type":"Point"}
}