{
  "type": "Feature",
  "properties": {
    "gn:admin1_code":"32.0",
    "gn:asciiname":"Jielong",
    "gn:country_code":"CN",
    "gn:dem":392,
    "gn:feature_class":"P",
    "gn:feature_code":"PPL",
    "gn:name":"Jielong",
    "gn:population":0,
    "gn:timezone":"Asia/Shanghai",
    "iso:country":"CN",
    "name:zho_x_preferred":[
        "\u63a5\u9f99"
    ],
    "wof:name":"Jielong",
    "wof:placetype":"locality"
},
  "geometry": {"coordinates":[104.76900000000001,30.3981],"type":"Point"}
}