{
  "type": "Feature",
  "properties": {
    "gn:admin1_code":"10.0",
    "gn:asciiname":"Huangjin Hai'an",
    "gn:country_code":"CN",
    "gn:dem":4,
    "gn:feature_class":"P",
    "gn:feature_code":"PPL",
    "gn:name":"Huangjin Hai\u2019an",
    "gn:population":0,
    "gn:timezone":"Asia/Shanghai",
    "iso:country":"CN",
    "name:und_x_variant":[
        "Huangjin Hai\u2019an"
    ],
    "name:zho_x_preferred":[
        "\u9ec4\u91d1\u6d77\u5cb8"
    ],
    "wof:name":"Huangjin Hai'an",
    "wof:placetype":"locality"
},
  "geometry": {"coordinates":[119.32852,39.70895],"type":"Point"}
}