{
  "type": "Feature",
  "properties": {
    "gn:admin1_code":"16.0",
    "gn:asciiname":"Jiaoya",
    "gn:country_code":"CN",
    "gn:dem":933,
    "gn:feature_class":"P",
    "gn:feature_code":"PPL",
    "gn:name":"Jiaoya",
    "gn:population":0,
    "gn:timezone":"Asia/Shanghai",
    "iso:country":"CN",
    "name:zho_x_preferred":[
        "\u4ea4\u96c5"
    ],
    "wof:name":"Jiaoya",
    "wof:placetype":"locality"
},
  "geometry": {"coordinates":[106.78100000000001,25.0957],"type":"Point"}
}