{
  "type": "Feature",
  "properties": {
    "gn:admin1_code":"19.0",
    "gn:asciiname":"Laowopu",
    "gn:country_code":"CN",
    "gn:dem":81,
    "gn:feature_class":"P",
    "gn:feature_code":"PPL",
    "gn:name":"Laowopu",
    "gn:population":0,
    "gn:timezone":"Asia/Shanghai",
    "iso:country":"CN",
    "name:zho_x_preferred":[
        "\u8001\u7a9d\u94fa"
    ],
    "wof:name":"Laowopu",
    "wof:placetype":"locality"
},
  "geometry": {"coordinates":[122.827,39.0542],"type":"Point"}
}