{
  "type": "Feature",
  "properties": {
    "gn:admin1_code":"19.0",
    "gn:asciiname":"Qiangganyucun",
    "gn:country_code":"CN",
    "gn:dem":162,
    "gn:feature_class":"P",
    "gn:feature_code":"PPL",
    "gn:name":"Qiangganyucun",
    "gn:population":0,
    "gn:timezone":"Asia/Shanghai",
    "iso:country":"CN",
    "name:zho_x_preferred":[
        "\u67aa\u6746\u5cea\u6751"
    ],
    "wof:name":"Qiangganyucun",
    "wof:placetype":"locality"
},
  "geometry": {"coordinates":[124.319,42.3057],"type":"Point"}
}