{
  "type": "Feature",
  "properties": {
    "gn:admin1_code":"11",
    "gn:asciiname":"Taiping",
    "gn:country_code":"CN",
    "gn:dem":399,
    "gn:feature_class":"P",
    "gn:feature_code":"PPLA4",
    "gn:name":"Taiping",
    "gn:population":0,
    "gn:timezone":"Asia/Shanghai",
    "iso:country":"CN",
    "name:und_x_variant":[
        "Taiping Zhen",
        "\u592a\u5e73\u9547",
        "Taiping"
    ],
    "name:zho_x_preferred":[
        "\u592a\u5e73"
    ],
    "wof:name":"Taiping",
    "wof:placetype":"locality"
},
  "geometry": {"coordinates":[112.12306,25.66111],"type":"Point"}
}