{
  "type": "Feature",
  "properties": {
    "gn:admin1_code":"6.0",
    "gn:asciiname":"Ningquxiangka",
    "gn:country_code":"CN",
    "gn:dem":3259,
    "gn:feature_class":"P",
    "gn:feature_code":"PPL",
    "gn:name":"Ningquxiangka",
    "gn:population":0,
    "gn:timezone":"Asia/Shanghai",
    "iso:country":"CN",
    "name:und_x_variant":[
        "\u5b81\u66f2\u9999\u5361"
    ],
    "wof:name":"Ningquxiangka",
    "wof:placetype":"locality"
},
  "geometry": {"coordinates":[99.87461999999999,36.10448],"type":"Point"}
}