{
  "type": "Feature",
  "properties": {
    "gn:admin1_code":"26.0",
    "gn:asciiname":"Nanpowan",
    "gn:country_code":"CN",
    "gn:dem":1335,
    "gn:feature_class":"P",
    "gn:feature_code":"PPL",
    "gn:name":"Nanpowan",
    "gn:population":0,
    "gn:timezone":"Asia/Shanghai",
    "iso:country":"CN",
    "name:und_x_variant":[
        "\u5357\u5761\u6e7e"
    ],
    "wof:name":"Nanpowan",
    "wof:placetype":"locality"
},
  "geometry": {"coordinates":[107.88193,34.84598],"type":"Point"}
}