{
  "type": "Feature",
  "properties": {
    "gn:admin1_code":"13",
    "gn:asciiname":"Mangu Bulake",
    "gn:country_code":"CN",
    "gn:dem":-77,
    "gn:feature_class":"P",
    "gn:feature_code":"PPL",
    "gn:name":"Mangu Bulake",
    "gn:population":0,
    "gn:timezone":"Asia/Urumqi",
    "iso:country":"CN",
    "name:uig_x_preferred":[
        "Mangu Bulak"
    ],
    "name:und_x_variant":[
        "\u66fc\u53e4\u5e03\u62c9\u514b"
    ],
    "wof:name":"Mangu Bulake",
    "wof:placetype":"locality"
},
  "geometry": {"coordinates":[89.47206,42.83164],"type":"Point"}
}