{
  "type": "Feature",
  "properties": {
    "gn:admin1_code":"32.0",
    "gn:asciiname":"Xuekeshe",
    "gn:country_code":"CN",
    "gn:dem":3986,
    "gn:feature_class":"P",
    "gn:feature_code":"PPL",
    "gn:name":"Xuekeshe",
    "gn:population":0,
    "gn:timezone":"Asia/Shanghai",
    "iso:country":"CN",
    "name:zho_x_preferred":[
        "\u96ea\u79d1\u793e"
    ],
    "wof:name":"Xuekeshe",
    "wof:placetype":"locality"
},
  "geometry": {"coordinates":[99.20202,31.91405],"type":"Point"}
}