{
  "type": "Feature",
  "properties": {
    "gn:admin1_code":"15.0",
    "gn:asciiname":"Choujiachuan",
    "gn:country_code":"CN",
    "gn:dem":1043,
    "gn:feature_class":"P",
    "gn:feature_code":"PPL",
    "gn:name":"Choujiachuan",
    "gn:population":0,
    "gn:timezone":"Asia/Shanghai",
    "iso:country":"CN",
    "name:zho_x_preferred":[
        "\u4e11\u5bb6\u5ddd"
    ],
    "wof:name":"Choujiachuan",
    "wof:placetype":"locality"
},
  "geometry": {"coordinates":[108.009,35.7515],"type":"Point"}
}