{
  "type": "Feature",
  "properties": {
    "iso:country":"CN",
    "name:eng_x_preferred":[
        "Bengbu"
    ],
    "name:heb_x_preferred":[
        "\u05d1\u05e0\u05d2\u05d1\u05d5"
    ],
    "name:hun_x_preferred":[
        "Bengbu"
    ],
    "name:zho_x_preferred":[
        "\u868c\u57e0\u5e02"
    ],
    "qs:name":"\u868c\u57e0\u5e02",
    "qs:name_adm0":"\u4e2d\u570b",
    "qs:name_adm1":"\u5b89\u5fbd\u7701",
    "qs:photos":2,
    "qs:photos_1k":1,
    "qs:photos_9k":1,
    "qs:photos_9r":1,
    "qs:photos_all":11,
    "qs:photos_sr":1,
    "qs:placetype":"LocalAdmin",
    "qs:pop_sr":"0",
    "wof:name":"Bengbu",
    "wof:placetype":"localadmin"
},
  "geometry": {"coordinates":[117.3719,32.944],"type":"Point"}
}