{
  "type": "Feature",
  "properties": {
    "gn:admin1_code":"15.0",
    "gn:asciiname":"Dalinke",
    "gn:country_code":"CN",
    "gn:dem":2689,
    "gn:feature_class":"P",
    "gn:feature_code":"PPL",
    "gn:name":"Dalinke",
    "gn:population":0,
    "gn:timezone":"Asia/Shanghai",
    "iso:country":"CN",
    "name:zho_x_preferred":[
        "\u5927\u6797\u68f5"
    ],
    "wof:name":"Dalinke",
    "wof:placetype":"locality"
},
  "geometry": {"coordinates":[102.944,37.3071],"type":"Point"}
}