{
  "type": "Feature",
  "properties": {
    "gn:admin1_code":"10.0",
    "gn:asciiname":"Jiaoniwan",
    "gn:country_code":"CN",
    "gn:dem":679,
    "gn:feature_class":"P",
    "gn:feature_code":"PPL",
    "gn:name":"Jiaoniwan",
    "gn:population":0,
    "gn:timezone":"Asia/Shanghai",
    "iso:country":"CN",
    "name:zho_x_preferred":[
        "\u80f6\u6ce5\u6e7e"
    ],
    "wof:name":"Jiaoniwan",
    "wof:placetype":"locality"
},
  "geometry": {"coordinates":[114.85241000000001,40.64614],"type":"Point"}
}