{
  "type": "Feature",
  "properties": {
    "gn:admin1_code":"1.0",
    "gn:asciiname":"Anzhuangcun",
    "gn:country_code":"CN",
    "gn:dem":32,
    "gn:feature_class":"P",
    "gn:feature_code":"PPL",
    "gn:name":"Anzhuangcun",
    "gn:population":0,
    "gn:timezone":"Asia/Shanghai",
    "iso:country":"CN",
    "name:zho_x_preferred":[
        "\u5b89\u5e84\u6751"
    ],
    "wof:name":"Anzhuangcun",
    "wof:placetype":"locality"
},
  "geometry": {"coordinates":[115.99757,33.50898],"type":"Point"}
}