{
  "type": "Feature",
  "properties": {
    "gn:admin1_code":"22.0",
    "gn:asciiname":"Longmenkou",
    "gn:country_code":"CN",
    "gn:dem":510,
    "gn:feature_class":"P",
    "gn:feature_code":"PPL",
    "gn:name":"Longmenkou",
    "gn:population":0,
    "gn:timezone":"Asia/Shanghai",
    "iso:country":"CN",
    "name:zho_x_preferred":[
        "\u9f99\u95e8\u53e3"
    ],
    "wof:name":"Longmenkou",
    "wof:placetype":"locality"
},
  "geometry": {"coordinates":[115.67832,40.0538],"type":"Point"}
}