{
  "type": "Feature",
  "properties": {
    "gn:admin1_code":"10",
    "gn:asciiname":"Hougou",
    "gn:country_code":"CN",
    "gn:dem":904,
    "gn:feature_class":"P",
    "gn:feature_code":"PPL",
    "gn:name":"Hougou",
    "gn:population":0,
    "gn:timezone":"Asia/Shanghai",
    "iso:country":"CN",
    "name:zho_x_preferred":[
        "\u540e\u6c9f"
    ],
    "wof:name":"Hougou",
    "wof:placetype":"locality"
},
  "geometry": {"coordinates":[117.00809,41.39817],"type":"Point"}
}