{
  "type": "Feature",
  "properties": {
    "gn:admin1_code":"26.0",
    "gn:asciiname":"Shuanghecun",
    "gn:country_code":"CN",
    "gn:dem":645,
    "gn:feature_class":"P",
    "gn:feature_code":"PPL",
    "gn:name":"Shuanghecun",
    "gn:population":0,
    "gn:timezone":"Asia/Shanghai",
    "iso:country":"CN",
    "name:zho_x_preferred":[
        "\u53cc\u6cb3\u6751"
    ],
    "wof:name":"Shuanghecun",
    "wof:placetype":"locality"
},
  "geometry": {"coordinates":[110.41254000000001,33.56578],"type":"Point"}
}