{
  "type": "Feature",
  "properties": {
    "gn:admin1_code":"19.0",
    "gn:asciiname":"Dongwujiadian",
    "gn:country_code":"CN",
    "gn:dem":211,
    "gn:feature_class":"P",
    "gn:feature_code":"PPL",
    "gn:name":"Dongwujiadian",
    "gn:population":0,
    "gn:timezone":"Asia/Shanghai",
    "iso:country":"CN",
    "name:zho_x_preferred":[
        "\u4e1c\u5434\u5bb6\u5e97"
    ],
    "wof:name":"Dongwujiadian",
    "wof:placetype":"locality"
},
  "geometry": {"coordinates":[121.994,42.663],"type":"Point"}
}