{
  "type": "Feature",
  "properties": {
    "gn:admin1_code":"1.0",
    "gn:asciiname":"Lianzhan",
    "gn:country_code":"CN",
    "gn:dem":19,
    "gn:feature_class":"P",
    "gn:feature_code":"PPL",
    "gn:name":"Lianzhan",
    "gn:population":0,
    "gn:timezone":"Asia/Shanghai",
    "iso:country":"CN",
    "wof:name":"Lianzhan",
    "wof:placetype":"locality"
},
  "geometry": {"coordinates":[117.34444000000001,33.24444],"type":"Point"}
}