{
  "type": "Feature",
  "properties": {
    "gn:admin1_code":"1.0",
    "gn:asciiname":"Qiulu",
    "gn:country_code":"CN",
    "gn:dem":10,
    "gn:feature_class":"P",
    "gn:feature_code":"PPL",
    "gn:name":"Qiul\u00fc",
    "gn:population":0,
    "gn:timezone":"Asia/Shanghai",
    "iso:country":"CN",
    "name:und_x_variant":[
        "Qiul\u00fc"
    ],
    "name:zho_x_preferred":[
        "\u90b1\u5415"
    ],
    "wof:name":"Qiulu",
    "wof:placetype":"locality"
},
  "geometry": {"coordinates":[118.26391,31.52705],"type":"Point"}
}