{
  "type": "Feature",
  "properties": {
    "gn:admin1_code":"7.0",
    "gn:asciiname":"Dawoli",
    "gn:country_code":"CN",
    "gn:dem":725,
    "gn:feature_class":"P",
    "gn:feature_code":"PPL",
    "gn:name":"Dawoli",
    "gn:population":0,
    "gn:timezone":"Asia/Shanghai",
    "iso:country":"CN",
    "name:und_x_variant":[
        "\u5927\u7a9d\u91cc"
    ],
    "name:zho_x_preferred":[
        "\u5927\u7a9d\u91cc"
    ],
    "wof:name":"Dawoli",
    "wof:placetype":"locality"
},
  "geometry": {"coordinates":[116.50636000000002,26.38411],"type":"Point"}
}