{
  "type": "Feature",
  "properties": {
    "gn:admin1_code":"3.0",
    "gn:asciiname":"Banjing",
    "gn:country_code":"CN",
    "gn:dem":271,
    "gn:feature_class":"P",
    "gn:feature_code":"PPL",
    "gn:name":"Banjing",
    "gn:population":0,
    "gn:timezone":"Asia/Shanghai",
    "iso:country":"CN",
    "name:und_x_variant":[
        "\u534a\u8ff3"
    ],
    "wof:name":"Banjing",
    "wof:placetype":"locality"
},
  "geometry": {"coordinates":[116.1947,26.25109],"type":"Point"}
}