{
  "type": "Feature",
  "properties": {
    "gn:admin1_code":"16.0",
    "gn:asciiname":"Emei",
    "gn:country_code":"CN",
    "gn:dem":129,
    "gn:feature_class":"P",
    "gn:feature_code":"PPL",
    "gn:name":"Emei",
    "gn:population":0,
    "gn:timezone":"Asia/Shanghai",
    "iso:country":"CN",
    "name:zho_x_preferred":[
        "\u5ce8\u5d4b"
    ],
    "wof:name":"Emei",
    "wof:placetype":"locality"
},
  "geometry": {"coordinates":[110.056,22.0862],"type":"Point"}
}