{
  "type": "Feature",
  "properties": {
    "gn:admin1_code":"11",
    "gn:asciiname":"Huashan Yaozuxiang",
    "gn:cc2":"CN",
    "gn:country_code":"CN",
    "gn:dem":525,
    "gn:feature_class":"P",
    "gn:feature_code":"PPL",
    "gn:name":"Huashan Yaozuxiang",
    "gn:population":0,
    "gn:timezone":"Asia/Shanghai",
    "iso:country":"CN",
    "name:und_x_variant":[
        "Chapan\u2019an",
        "Huashan Yaozuxiang"
    ],
    "wof:name":"Huashan Yaozuxiang",
    "wof:placetype":"locality"
},
  "geometry": {"coordinates":[112.37139000000001,26.06833],"type":"Point"}
}