{
  "type": "Feature",
  "properties": {
    "gn:admin1_code":"11",
    "gn:asciiname":"Mao'ershi",
    "gn:country_code":"CN",
    "gn:dem":432,
    "gn:feature_class":"P",
    "gn:feature_code":"PPL",
    "gn:name":"Mao\u2019ershi",
    "gn:population":0,
    "gn:timezone":"Asia/Shanghai",
    "iso:country":"CN",
    "name:und_x_variant":[
        "Mao\u2019ershi"
    ],
    "name:zho_x_preferred":[
        "\u732b\u513f\u77f3"
    ],
    "wof:name":"Mao'ershi",
    "wof:placetype":"locality"
},
  "geometry": {"coordinates":[111.26607,27.56986],"type":"Point"}
}