{
  "type": "Feature",
  "properties": {
    "gn:admin1_code":"25",
    "gn:asciiname":"Dingganli",
    "gn:country_code":"CN",
    "gn:dem":15,
    "gn:feature_class":"P",
    "gn:feature_code":"PPL",
    "gn:name":"Dingganli",
    "gn:population":0,
    "gn:timezone":"Asia/Shanghai",
    "iso:country":"CN",
    "name:zho_x_preferred":[
        "\u5b9a\u6746\u674e"
    ],
    "wof:name":"Dingganli",
    "wof:placetype":"locality"
},
  "geometry": {"coordinates":[117.119,37.7382],"type":"Point"}
}