{
  "type": "Feature",
  "properties": {
    "gn:admin1_code":"1.0",
    "gn:asciiname":"Liyuan",
    "gn:country_code":"CN",
    "gn:dem":18,
    "gn:feature_class":"P",
    "gn:feature_code":"PPL",
    "gn:name":"Liyuan",
    "gn:population":0,
    "gn:timezone":"Asia/Shanghai",
    "iso:country":"CN",
    "name:ceb_x_preferred":[
        "Liyuan"
    ],
    "name:swe_x_preferred":[
        "Liyuan"
    ],
    "name:zho_x_preferred":[
        "Liyuan"
    ],
    "name:zho_x_variant":[
        "\u6817\u56ed"
    ],
    "wof:name":"Liyuan",
    "wof:placetype":"locality"
},
  "geometry": {"coordinates":[119.25066,31.03594],"type":"Point"}
}