{
  "type": "Feature",
  "properties": {
    "gn:admin1_code":"18",
    "gn:asciiname":"Guanxing",
    "gn:country_code":"CN",
    "gn:dem":934,
    "gn:feature_class":"P",
    "gn:feature_code":"PPL",
    "gn:name":"Guanxing",
    "gn:population":0,
    "gn:timezone":"Asia/Shanghai",
    "iso:country":"CN",
    "wof:name":"Guanxing",
    "wof:placetype":"locality"
},
  "geometry": {"coordinates":[107.72472,27.57889],"type":"Point"}
}