{
  "type": "Feature",
  "properties": {
    "gn:admin1_code":"9.0",
    "gn:asciiname":"Xueyanling",
    "gn:country_code":"CN",
    "gn:dem":91,
    "gn:feature_class":"P",
    "gn:feature_code":"PPL",
    "gn:name":"Xueyanling",
    "gn:population":0,
    "gn:timezone":"Asia/Shanghai",
    "iso:country":"CN",
    "name:zho_x_preferred":[
        "\u859b\u5ef6\u9675"
    ],
    "wof:name":"Xueyanling",
    "wof:placetype":"locality"
},
  "geometry": {"coordinates":[113.38983,35.14738],"type":"Point"}
}