{
  "type": "Feature",
  "properties": {
    "gn:admin1_code":"19.0",
    "gn:asciiname":"Datuozi",
    "gn:country_code":"CN",
    "gn:dem":55,
    "gn:feature_class":"P",
    "gn:feature_code":"PPL",
    "gn:name":"Datuozi",
    "gn:population":0,
    "gn:timezone":"Asia/Shanghai",
    "iso:country":"CN",
    "name:und_x_variant":[
        "\u5927\u5768\u5b50"
    ],
    "name:zho_x_preferred":[
        "\u5927\u5768\u5b50"
    ],
    "wof:name":"Datuozi",
    "wof:placetype":"locality"
},
  "geometry": {"coordinates":[122.58803,42.12993],"type":"Point"}
}