{
  "type": "Feature",
  "properties": {
    "gn:admin1_code":"11",
    "gn:asciiname":"Tuzha",
    "gn:country_code":"CN",
    "gn:dem":463,
    "gn:feature_class":"P",
    "gn:feature_code":"PPLA4",
    "gn:name":"Tuzha",
    "gn:population":0,
    "gn:timezone":"Asia/Shanghai",
    "iso:country":"CN",
    "name:deu_x_preferred":[
        "Tuscha"
    ],
    "name:hun_x_preferred":[
        "Tuzsa"
    ],
    "name:hye_x_preferred":[
        "\u054f\u0578\u0582\u056a\u0561"
    ],
    "name:ita_x_preferred":[
        "Tu\u017ea"
    ],
    "name:myv_x_preferred":[
        "\u0422\u0443\u0436\u0430"
    ],
    "name:rus_x_preferred":[
        "\u0422\u0443\u0436\u0430"
    ],
    "name:und_x_variant":[
        "Tuzha Xiang"
    ],
    "name:zho_x_preferred":[
        "\u6d82\u4e4d"
    ],
    "name:zho_x_variant":[
        "\u6d82\u4e4d\u4e61"
    ],
    "wof:name":"Tuzha",
    "wof:placetype":"locality"
},
  "geometry": {"coordinates":[109.693,28.5821],"type":"Point"}
}