{
  "type": "Feature",
  "properties": {
    "gn:admin1_code":"01",
    "gn:asciiname":"Hujiawan",
    "gn:cc2":"CN",
    "gn:country_code":"CN",
    "gn:dem":6,
    "gn:feature_class":"P",
    "gn:feature_code":"PPL",
    "gn:name":"Hujiawan",
    "gn:population":0,
    "gn:timezone":"Asia/Shanghai",
    "iso:country":"CN",
    "name:und_x_variant":[
        "Hu-chia-wan",
        "Hujiawan"
    ],
    "wof:name":"Hujiawan",
    "wof:placetype":"locality"
},
  "geometry": {"coordinates":[117.28972,31.50972],"type":"Point"}
}