{
  "type": "Feature",
  "properties": {
    "gn:admin1_code":"7.0",
    "gn:asciiname":"Aoshang",
    "gn:country_code":"CN",
    "gn:dem":304,
    "gn:feature_class":"P",
    "gn:feature_code":"PPL",
    "gn:name":"Aoshang",
    "gn:population":0,
    "gn:timezone":"Asia/Shanghai",
    "iso:country":"CN",
    "name:zho_x_preferred":[
        "\u5773\u4e0a"
    ],
    "wof:name":"Aoshang",
    "wof:placetype":"locality"
},
  "geometry": {"coordinates":[117.66545000000001,27.34619],"type":"Point"}
}