{
  "type": "Feature",
  "properties": {
    "gn:admin1_code":"18.0",
    "gn:asciiname":"Xiajianiao",
    "gn:country_code":"CN",
    "gn:dem":693,
    "gn:feature_class":"P",
    "gn:feature_code":"PPL",
    "gn:name":"Xiajianiao",
    "gn:population":0,
    "gn:timezone":"Asia/Shanghai",
    "iso:country":"CN",
    "name:zho_x_preferred":[
        "\u4e0b\u7532\u9e1f"
    ],
    "wof:name":"Xiajianiao",
    "wof:placetype":"locality"
},
  "geometry": {"coordinates":[107.767,26.3106],"type":"Point"}
}