{
  "type": "Feature",
  "properties": {
    "gn:admin1_code":"7",
    "gn:asciiname":"Dongpu",
    "gn:cc2":"CN",
    "gn:country_code":"CN",
    "gn:dem":16,
    "gn:feature_class":"P",
    "gn:feature_code":"PPL",
    "gn:name":"Dongpu",
    "gn:population":0,
    "gn:timezone":"Asia/Shanghai",
    "iso:country":"CN",
    "name:und_x_variant":[
        "Tung-po",
        "Dongpu"
    ],
    "wof:name":"Dongpu",
    "wof:placetype":"locality"
},
  "geometry": {"coordinates":[119.05500000000001,25.16139],"type":"Point"}
}