{
  "type": "Feature",
  "properties": {
    "gn:admin1_code":"30",
    "gn:asciiname":"Chengdong",
    "gn:country_code":"CN",
    "gn:dem":6,
    "gn:feature_class":"P",
    "gn:feature_code":"PPLA4",
    "gn:name":"Chengdong",
    "gn:population":0,
    "gn:timezone":"Asia/Shanghai",
    "iso:country":"CN",
    "name:und_x_variant":[
        "Chengdong Jiedao",
        "Chengdong",
        "\u57ce\u4e1c\u8857\u9053"
    ],
    "name:zho_x_preferred":[
        "\u57ce\u4e1c"
    ],
    "wof:name":"Chengdong",
    "wof:placetype":"locality"
},
  "geometry": {"coordinates":[115.66709,22.95237],"type":"Point"}
}