{
  "type": "Feature",
  "properties": {
    "gn:admin1_code":"3.0",
    "gn:asciiname":"Waiyupu",
    "gn:country_code":"CN",
    "gn:dem":107,
    "gn:feature_class":"P",
    "gn:feature_code":"PPL",
    "gn:name":"Waiyupu",
    "gn:population":0,
    "gn:timezone":"Asia/Shanghai",
    "iso:country":"CN",
    "name:und_x_variant":[
        "\u5916\u7fbd\u94fa"
    ],
    "wof:name":"Waiyupu",
    "wof:placetype":"locality"
},
  "geometry": {"coordinates":[117.62518,29.30388],"type":"Point"}
}