{
  "type": "Feature",
  "properties": {
    "gn:admin1_code":"29.0",
    "gn:asciiname":"Mangbing",
    "gn:country_code":"CN",
    "gn:dem":1145,
    "gn:feature_class":"P",
    "gn:feature_code":"PPL",
    "gn:name":"Mangbing",
    "gn:population":0,
    "gn:timezone":"Asia/Shanghai",
    "iso:country":"CN",
    "name:zho_x_preferred":[
        "\u8292\u4e19"
    ],
    "wof:name":"Mangbing",
    "wof:placetype":"locality"
},
  "geometry": {"coordinates":[98.5352,24.3258],"type":"Point"}
}