{
  "type": "Feature",
  "properties": {
    "gn:admin1_code":"10",
    "gn:asciiname":"Dadongying",
    "gn:country_code":"CN",
    "gn:dem":424,
    "gn:feature_class":"P",
    "gn:feature_code":"PPL",
    "gn:name":"Dadongying",
    "gn:population":0,
    "gn:timezone":"Asia/Shanghai",
    "iso:country":"CN",
    "name:zho_x_preferred":[
        "\u5927\u4e1c\u8425"
    ],
    "wof:name":"Dadongying",
    "wof:placetype":"locality"
},
  "geometry": {"coordinates":[117.79625,40.77157],"type":"Point"}
}