{
  "type": "Feature",
  "properties": {
    "gn:admin1_code":"2.0",
    "gn:asciiname":"Dalikou",
    "gn:country_code":"CN",
    "gn:dem":103,
    "gn:feature_class":"P",
    "gn:feature_code":"PPL",
    "gn:name":"Dalikou",
    "gn:population":0,
    "gn:timezone":"Asia/Shanghai",
    "iso:country":"CN",
    "name:zho_x_preferred":[
        "\u5927\u529b\u53e3"
    ],
    "wof:name":"Dalikou",
    "wof:placetype":"locality"
},
  "geometry": {"coordinates":[118.76381000000001,28.91404],"type":"Point"}
}