{
  "type": "Feature",
  "properties": {
    "gn:admin1_code":"7",
    "gn:asciiname":"Donggao",
    "gn:cc2":"CN",
    "gn:country_code":"CN",
    "gn:dem":14,
    "gn:feature_class":"P",
    "gn:feature_code":"PPL",
    "gn:name":"Donggao",
    "gn:population":0,
    "gn:timezone":"Asia/Shanghai",
    "iso:country":"CN",
    "name:und_x_variant":[
        "Tung-kao",
        "Donggao"
    ],
    "wof:name":"Donggao",
    "wof:placetype":"locality"
},
  "geometry": {"coordinates":[119.54167,25.71694],"type":"Point"}
}