{
  "type": "Feature",
  "properties": {
    "gn:admin1_code":"12.0",
    "gn:asciiname":"Zhongyanhe",
    "gn:country_code":"CN",
    "gn:dem":571,
    "gn:feature_class":"P",
    "gn:feature_code":"PPL",
    "gn:name":"Zhongyanhe",
    "gn:population":0,
    "gn:timezone":"Asia/Shanghai",
    "iso:country":"CN",
    "name:zho_x_preferred":[
        "\u4e2d\u5830\u6cb3"
    ],
    "wof:name":"Zhongyanhe",
    "wof:placetype":"locality"
},
  "geometry": {"coordinates":[110.93013999999999,32.14706],"type":"Point"}
}