{
  "type": "Feature",
  "properties": {
    "gn:admin1_code":"16.0",
    "gn:asciiname":"Beirong",
    "gn:country_code":"CN",
    "gn:dem":189,
    "gn:feature_class":"P",
    "gn:feature_code":"PPL",
    "gn:name":"Beirong",
    "gn:population":0,
    "gn:timezone":"Asia/Shanghai",
    "iso:country":"CN",
    "name:zho_x_preferred":[
        "\u5317\u5bb9"
    ],
    "wof:name":"Beirong",
    "wof:placetype":"locality"
},
  "geometry": {"coordinates":[110.52200000000001,22.6389],"type":"Point"}
}