{
  "type": "Feature",
  "properties": {
    "gn:admin1_code":"1.0",
    "gn:asciiname":"Qianjuncun",
    "gn:country_code":"CN",
    "gn:dem":163,
    "gn:feature_class":"P",
    "gn:feature_code":"PPL",
    "gn:name":"Qianjuncun",
    "gn:population":0,
    "gn:timezone":"Asia/Shanghai",
    "iso:country":"CN",
    "name:zho_x_preferred":[
        "\u5343\u519b\u6751"
    ],
    "wof:name":"Qianjuncun",
    "wof:placetype":"locality"
},
  "geometry": {"coordinates":[118.28668,31.09167],"type":"Point"}
}