{
  "type": "Feature",
  "properties": {
    "gn:admin1_code":"11.0",
    "gn:asciiname":"Liujiaping",
    "gn:country_code":"CN",
    "gn:dem":62,
    "gn:feature_class":"P",
    "gn:feature_code":"PPL",
    "gn:name":"Liujiaping",
    "gn:population":0,
    "gn:timezone":"Asia/Shanghai",
    "iso:country":"CN",
    "name:zho_x_preferred":[
        "Liujiaping"
    ],
    "name:zho_x_variant":[
        "\u5218\u5bb6\u576a"
    ],
    "wof:name":"Liujiaping",
    "wof:placetype":"locality"
},
  "geometry": {"coordinates":[111.37445,29.23792000000001],"type":"Point"}
}