{
  "type": "Feature",
  "properties": {
    "gn:admin1_code":"30.0",
    "gn:asciiname":"Dongcheng",
    "gn:country_code":"CN",
    "gn:dem":16,
    "gn:feature_class":"P",
    "gn:feature_code":"PPL",
    "gn:name":"Dongcheng",
    "gn:population":0,
    "gn:timezone":"Asia/Shanghai",
    "iso:country":"CN",
    "name:ceb_x_preferred":[
        "Dongcheng"
    ],
    "name:deu_x_preferred":[
        "Dongcheng"
    ],
    "name:eus_x_preferred":[
        "Dongcheng"
    ],
    "name:nld_x_preferred":[
        "Dongcheng"
    ],
    "name:zho_x_preferred":[
        "\u4e1c\u6210"
    ],
    "wof:name":"Dongcheng",
    "wof:placetype":"locality"
},
  "geometry": {"coordinates":[112.8381,22.2834],"type":"Point"}
}