{
  "type": "Feature",
  "properties": {
    "gn:admin1_code":"10",
    "gn:asciiname":"Tianzhuangying",
    "gn:country_code":"CN",
    "gn:dem":93,
    "gn:feature_class":"P",
    "gn:feature_code":"PPL",
    "gn:name":"Tianzhuangying",
    "gn:population":0,
    "gn:timezone":"Asia/Shanghai",
    "iso:country":"CN",
    "name:und_x_variant":[
        "T\u2019ien-chia-chuang",
        "T\u2019ien-chuang-ying",
        "Tianzhuangying"
    ],
    "name:zho_x_preferred":[
        "\u7530\u5e84\u8425"
    ],
    "wof:name":"Tianzhuangying",
    "wof:placetype":"locality"
},
  "geometry": {"coordinates":[118.52149,39.90399],"type":"Point"}
}