{
  "type": "Feature",
  "properties": {
    "gn:admin1_code":"24.0",
    "gn:asciiname":"Yangjuangou",
    "gn:cc2":"CN",
    "gn:country_code":"CN",
    "gn:dem":1580,
    "gn:feature_class":"P",
    "gn:feature_code":"PPL",
    "gn:name":"Yangjuangou",
    "gn:population":0,
    "gn:timezone":"Asia/Shanghai",
    "iso:country":"CN",
    "name:und_x_variant":[
        "Yang-ch\u2019\u00fcan-kou",
        "Yangjuangou"
    ],
    "wof:name":"Yangjuangou",
    "wof:placetype":"locality"
},
  "geometry": {"coordinates":[111.88333,38.86667],"type":"Point"}
}