{
  "type": "Feature",
  "properties": {
    "gn:admin1_code":"16.0",
    "gn:asciiname":"Tunjin",
    "gn:country_code":"CN",
    "gn:dem":326,
    "gn:feature_class":"P",
    "gn:feature_code":"PPL",
    "gn:name":"Tunjin",
    "gn:population":0,
    "gn:timezone":"Asia/Shanghai",
    "iso:country":"CN",
    "name:zho_x_preferred":[
        "\u541e\u7981"
    ],
    "wof:name":"Tunjin",
    "wof:placetype":"locality"
},
  "geometry": {"coordinates":[107.994,24.0756],"type":"Point"}
}