{
  "type": "Feature",
  "properties": {
    "gn:admin1_code":"16.0",
    "gn:asciiname":"Pona",
    "gn:country_code":"CN",
    "gn:dem":144,
    "gn:feature_class":"P",
    "gn:feature_code":"PPL",
    "gn:name":"Pona",
    "gn:population":0,
    "gn:timezone":"Asia/Shanghai",
    "iso:country":"CN",
    "name:ceb_x_preferred":[
        "Pona"
    ],
    "name:swe_x_preferred":[
        "Pona"
    ],
    "name:ukr_x_preferred":[
        "\u041f\u043e\u043d\u0430"
    ],
    "name:zho_x_preferred":[
        "\u5761\u90a3"
    ],
    "wof:name":"Pona",
    "wof:placetype":"locality"
},
  "geometry": {"coordinates":[108.227,23.4449],"type":"Point"}
}