{
  "type": "Feature",
  "properties": {
    "gn:admin1_code":"7.0",
    "gn:asciiname":"Xueli",
    "gn:country_code":"CN",
    "gn:dem":46,
    "gn:feature_class":"P",
    "gn:feature_code":"PPL",
    "gn:name":"Xueli",
    "gn:population":0,
    "gn:timezone":"Asia/Shanghai",
    "iso:country":"CN",
    "name:zho_x_preferred":[
        "\u7a74\u5229"
    ],
    "wof:name":"Xueli",
    "wof:placetype":"locality"
},
  "geometry": {"coordinates":[118.95071000000002,25.84389],"type":"Point"}
}