{
  "type": "Feature",
  "properties": {
    "gn:admin1_code":"4.0",
    "gn:asciiname":"Yedingcun",
    "gn:country_code":"CN",
    "gn:dem":0,
    "gn:feature_class":"P",
    "gn:feature_code":"PPL",
    "gn:name":"Yedingcun",
    "gn:population":0,
    "gn:timezone":"Asia/Shanghai",
    "iso:country":"CN",
    "name:zho_x_preferred":[
        "\u91ce\u4e01\u6751"
    ],
    "wof:name":"Yedingcun",
    "wof:placetype":"locality"
},
  "geometry": {"coordinates":[120.15411,33.30292],"type":"Point"}
}