{
  "type": "Feature",
  "properties": {
    "gn:admin1_code":"25",
    "gn:asciiname":"Liujiaheidun",
    "gn:country_code":"CN",
    "gn:dem":67,
    "gn:feature_class":"P",
    "gn:feature_code":"PPL",
    "gn:name":"Liujiaheidun",
    "gn:population":0,
    "gn:timezone":"Asia/Shanghai",
    "iso:country":"CN",
    "name:zho_x_preferred":[
        "\u5218\u5bb6\u9ed1\u58a9"
    ],
    "wof:name":"Liujiaheidun",
    "wof:placetype":"locality"
},
  "geometry": {"coordinates":[118.467,35.0866],"type":"Point"}
}