{
  "type": "Feature",
  "properties": {
    "gn:admin1_code":"14.0",
    "gn:asciiname":"Langmochongjiu",
    "gn:country_code":"CN",
    "gn:dem":4305,
    "gn:feature_class":"P",
    "gn:feature_code":"PPL",
    "gn:name":"Langmochongjiu",
    "gn:population":0,
    "gn:timezone":"Asia/Urumqi",
    "iso:country":"CN",
    "name:zho_x_preferred":[
        "\u90ce\u83ab\u51b2\u7396"
    ],
    "wof:name":"Langmochongjiu",
    "wof:placetype":"locality"
},
  "geometry": {"coordinates":[94.54768,29.88052],"type":"Point"}
}