{
  "type": "Feature",
  "properties": {
    "gn:admin1_code":"26.0",
    "gn:asciiname":"Qincai Goucun",
    "gn:country_code":"CN",
    "gn:dem":1137,
    "gn:feature_class":"P",
    "gn:feature_code":"PPL",
    "gn:name":"Qincai Goucun",
    "gn:population":0,
    "gn:timezone":"Asia/Shanghai",
    "iso:country":"CN",
    "name:zho_x_preferred":[
        "\u82b9\u83dc\u6c9f\u6751"
    ],
    "wof:name":"Qincai Goucun",
    "wof:placetype":"locality"
},
  "geometry": {"coordinates":[110.401,38.8421],"type":"Point"}
}