{
  "type": "Feature",
  "properties": {
    "gn:admin1_code":"07",
    "gn:asciiname":"Qinglinkou",
    "gn:country_code":"CN",
    "gn:dem":47,
    "gn:feature_class":"P",
    "gn:feature_code":"PPL",
    "gn:name":"Qinglinkou",
    "gn:population":0,
    "gn:timezone":"Asia/Shanghai",
    "iso:country":"CN",
    "name:zho_x_preferred":[
        "\u9752\u6797\u53e3"
    ],
    "wof:name":"Qinglinkou",
    "wof:placetype":"locality"
},
  "geometry": {"coordinates":[118.73132,25.03249],"type":"Point"}
}