{
  "type": "Feature",
  "properties": {
    "gn:admin1_code":"8.0",
    "gn:asciiname":"Shanwan Yidui",
    "gn:country_code":"CN",
    "gn:dem":195,
    "gn:feature_class":"P",
    "gn:feature_code":"PPLF",
    "gn:name":"Shanwan Yidui",
    "gn:population":0,
    "gn:timezone":"Asia/Shanghai",
    "iso:country":"CN",
    "name:zho_x_preferred":[
        "\u5c71\u6e7e\u4e00\u961f"
    ],
    "wof:name":"Shanwan Yidui",
    "wof:placetype":"locality"
},
  "geometry": {"coordinates":[123.59025,48.02558],"type":"Point"}
}