{
  "type": "Feature",
  "properties": {
    "gn:admin1_code":"07",
    "gn:asciiname":"Guangaoli",
    "gn:country_code":"CN",
    "gn:dem":226,
    "gn:feature_class":"P",
    "gn:feature_code":"PPL",
    "gn:name":"Guangaoli",
    "gn:population":0,
    "gn:timezone":"Asia/Shanghai",
    "iso:country":"CN",
    "name:zho_x_preferred":[
        "\u5b98\u8bf0\u91cc"
    ],
    "wof:name":"Guangaoli",
    "wof:placetype":"locality"
},
  "geometry": {"coordinates":[116.58929999999999,24.94856],"type":"Point"}
}