{
  "type": "Feature",
  "properties": {
    "gn:admin1_code":"25.0",
    "gn:asciiname":"Tanjiakuangcun",
    "gn:country_code":"CN",
    "gn:dem":126,
    "gn:feature_class":"P",
    "gn:feature_code":"PPL",
    "gn:name":"Tanjiakuangcun",
    "gn:population":0,
    "gn:timezone":"Asia/Shanghai",
    "iso:country":"CN",
    "name:zho_x_preferred":[
        "\u8c2d\u5bb6\u593c\u6751"
    ],
    "wof:name":"Tanjiakuangcun",
    "wof:placetype":"locality"
},
  "geometry": {"coordinates":[119.96174999999999,36.97608],"type":"Point"}
}