{
  "type": "Feature",
  "properties": {
    "gn:admin1_code":"18",
    "gn:asciiname":"Daoliushui",
    "gn:country_code":"CN",
    "gn:dem":926,
    "gn:feature_class":"P",
    "gn:feature_code":"PPL",
    "gn:name":"Daoliushui",
    "gn:population":0,
    "gn:timezone":"Asia/Shanghai",
    "iso:country":"CN",
    "name:zho_x_preferred":[
        "\u5012\u6d41\u6c34"
    ],
    "wof:name":"Daoliushui",
    "wof:placetype":"locality"
},
  "geometry": {"coordinates":[108.09699999999999,28.8583],"type":"Point"}
}