{
  "type": "Feature",
  "properties": {
    "gn:admin1_code":"32.0",
    "gn:asciiname":"Pengjiapo",
    "gn:country_code":"CN",
    "gn:dem":1210,
    "gn:feature_class":"P",
    "gn:feature_code":"PPL",
    "gn:name":"Pengjiapo",
    "gn:population":0,
    "gn:timezone":"Asia/Shanghai",
    "iso:country":"CN",
    "name:zho_x_preferred":[
        "\u5f6d\u5bb6\u5761"
    ],
    "wof:name":"Pengjiapo",
    "wof:placetype":"locality"
},
  "geometry": {"coordinates":[105.55141999999999,27.83756],"type":"Point"}
}