{
  "type": "Feature",
  "properties": {
    "gn:admin1_code":"12.0",
    "gn:asciiname":"Moxiaqu",
    "gn:country_code":"CN",
    "gn:dem":174,
    "gn:feature_class":"P",
    "gn:feature_code":"PPL",
    "gn:name":"Moxiaqu",
    "gn:population":0,
    "gn:timezone":"Asia/Shanghai",
    "iso:country":"CN",
    "name:zho_x_preferred":[
        "Moxiaqu"
    ],
    "name:zho_x_variant":[
        "\u964c\u4e0b\u533a"
    ],
    "wof:name":"Moxiaqu",
    "wof:placetype":"locality"
},
  "geometry": {"coordinates":[111.60824,30.96656],"type":"Point"}
}