{
  "type": "Feature",
  "properties": {
    "gn:admin1_code":"6.0",
    "gn:asciiname":"Zhiwuju",
    "gn:country_code":"CN",
    "gn:dem":2621,
    "gn:feature_class":"P",
    "gn:feature_code":"PPL",
    "gn:name":"Zhiwuju",
    "gn:population":0,
    "gn:timezone":"Asia/Shanghai",
    "iso:country":"CN",
    "name:und_x_variant":[
        "\u76f4\u543e\u5177"
    ],
    "wof:name":"Zhiwuju",
    "wof:placetype":"locality"
},
  "geometry": {"coordinates":[102.2058,35.96836],"type":"Point"}
}