{
  "type": "Feature",
  "properties": {
    "gn:admin1_code":"8.0",
    "gn:asciiname":"Sunhaojitun",
    "gn:country_code":"CN",
    "gn:dem":209,
    "gn:feature_class":"P",
    "gn:feature_code":"PPL",
    "gn:name":"Sunhaojitun",
    "gn:population":0,
    "gn:timezone":"Asia/Shanghai",
    "iso:country":"CN",
    "name:zho_x_preferred":[
        "\u5b59\u6beb\u51e0\u5c6f"
    ],
    "wof:name":"Sunhaojitun",
    "wof:placetype":"locality"
},
  "geometry": {"coordinates":[127.26255,47.44085],"type":"Point"}
}