{
  "type": "Feature",
  "properties": {
    "gn:admin1_code":"26.0",
    "gn:asciiname":"Zhaojia Tuncun",
    "gn:country_code":"CN",
    "gn:dem":941,
    "gn:feature_class":"P",
    "gn:feature_code":"PPL",
    "gn:name":"Zhaojia Tuncun",
    "gn:population":0,
    "gn:timezone":"Asia/Shanghai",
    "iso:country":"CN",
    "name:zho_x_preferred":[
        "\u8d75\u5bb6\u5c6f\u6751"
    ],
    "wof:name":"Zhaojia Tuncun",
    "wof:placetype":"locality"
},
  "geometry": {"coordinates":[110.119,37.5718],"type":"Point"}
}