{
  "type": "Feature",
  "properties": {
    "gn:admin1_code":"4.0",
    "gn:asciiname":"Wujia Dachi",
    "gn:country_code":"CN",
    "gn:dem":4,
    "gn:feature_class":"P",
    "gn:feature_code":"PPL",
    "gn:name":"Wujia Dachi",
    "gn:population":0,
    "gn:timezone":"Asia/Shanghai",
    "iso:country":"CN",
    "name:und_x_variant":[
        "\u5434\u5bb6\u5927\u6c60"
    ],
    "name:zho_x_preferred":[
        "\u5434\u5bb6\u5927\u6c60"
    ],
    "wof:name":"Wujia Dachi",
    "wof:placetype":"locality"
},
  "geometry": {"coordinates":[120.81511,32.34162],"type":"Point"}
}