{
  "type": "Feature",
  "properties": {
    "gn:admin1_code":"7",
    "gn:asciiname":"Wufangxushang",
    "gn:country_code":"CN",
    "gn:dem":377,
    "gn:feature_class":"P",
    "gn:feature_code":"PPL",
    "gn:name":"Wufangxushang",
    "gn:population":0,
    "gn:timezone":"Asia/Shanghai",
    "iso:country":"CN",
    "wof:name":"Wufangxushang",
    "wof:placetype":"locality"
},
  "geometry": {"coordinates":[116.75360999999999,26.29167],"type":"Point"}
}