{
  "type": "Feature",
  "properties": {
    "gn:admin1_code":"19.0",
    "gn:asciiname":"Dapu",
    "gn:country_code":"CN",
    "gn:dem":2,
    "gn:feature_class":"P",
    "gn:feature_code":"PPL",
    "gn:name":"Dapu",
    "gn:population":0,
    "gn:timezone":"Asia/Shanghai",
    "iso:country":"CN",
    "name:ceb_x_preferred":[
        "Dapu"
    ],
    "name:swe_x_preferred":[
        "Dapu"
    ],
    "name:und_x_variant":[
        "\u5927\u94fa"
    ],
    "wof:name":"Dapu",
    "wof:placetype":"locality"
},
  "geometry": {"coordinates":[122.17064000000001,40.76298],"type":"Point"}
}