{
  "type": "Feature",
  "properties": {
    "gn:admin1_code":"11",
    "gn:asciiname":"Jingwanli",
    "gn:country_code":"CN",
    "gn:dem":407,
    "gn:feature_class":"P",
    "gn:feature_code":"PPL",
    "gn:name":"Jingwanli",
    "gn:population":0,
    "gn:timezone":"Asia/Shanghai",
    "iso:country":"CN",
    "name:zho_x_preferred":[
        "\u4e95\u6e7e\u91cc"
    ],
    "wof:name":"Jingwanli",
    "wof:placetype":"locality"
},
  "geometry": {"coordinates":[111.40758999999998,27.98877],"type":"Point"}
}