{
  "type": "Feature",
  "properties": {
    "gn:admin1_code":"18.0",
    "gn:asciiname":"Changqi",
    "gn:country_code":"CN",
    "gn:dem":421,
    "gn:feature_class":"P",
    "gn:feature_code":"PPLA4",
    "gn:name":"Changqi",
    "gn:population":0,
    "gn:timezone":"Asia/Shanghai",
    "iso:country":"CN",
    "name:und_x_variant":[
        "Changqi Zhen"
    ],
    "name:zho_x_preferred":[
        "\u957f\u671f"
    ],
    "name:zho_x_variant":[
        "\u957f\u671f\u9547"
    ],
    "wof:name":"Changqi",
    "wof:placetype":"locality"
},
  "geometry": {"coordinates":[106.06816000000001,28.61992],"type":"Point"}
}