{
  "type": "Feature",
  "properties": {
    "gn:admin1_code":"29.0",
    "gn:asciiname":"Luoshitang",
    "gn:country_code":"CN",
    "gn:dem":1548,
    "gn:feature_class":"P",
    "gn:feature_code":"PPL",
    "gn:name":"Luoshitang",
    "gn:population":0,
    "gn:timezone":"Asia/Shanghai",
    "iso:country":"CN",
    "name:zho_x_preferred":[
        "\u87ba\u5e08\u5858"
    ],
    "wof:name":"Luoshitang",
    "wof:placetype":"locality"
},
  "geometry": {"coordinates":[103.06699999999999,23.661],"type":"Point"}
}