{
  "type": "Feature",
  "properties": {
    "gn:admin1_code":"32.0",
    "gn:asciiname":"Luowucun",
    "gn:country_code":"CN",
    "gn:dem":2452,
    "gn:feature_class":"P",
    "gn:feature_code":"PPL",
    "gn:name":"Luowucun",
    "gn:population":0,
    "gn:timezone":"Asia/Shanghai",
    "iso:country":"CN",
    "name:zho_x_preferred":[
        "\u843d\u4f0d\u6751"
    ],
    "wof:name":"Luowucun",
    "wof:placetype":"locality"
},
  "geometry": {"coordinates":[102.70396,26.46973],"type":"Point"}
}