{
  "type": "Feature",
  "properties": {
    "gn:admin1_code":"32.0",
    "gn:asciiname":"Tiefoguan",
    "gn:country_code":"CN",
    "gn:dem":635,
    "gn:feature_class":"P",
    "gn:feature_code":"PPL",
    "gn:name":"Tiefoguan",
    "gn:population":0,
    "gn:timezone":"Asia/Shanghai",
    "iso:country":"CN",
    "name:zho_x_preferred":[
        "\u94c1\u4f5b\u89c2"
    ],
    "wof:name":"Tiefoguan",
    "wof:placetype":"locality"
},
  "geometry": {"coordinates":[106.312,31.8096],"type":"Point"}
}