{
  "type": "Feature",
  "properties": {
    "gn:admin1_code":"30.0",
    "gn:asciiname":"Huangshantian",
    "gn:country_code":"CN",
    "gn:dem":415,
    "gn:feature_class":"P",
    "gn:feature_code":"PPL",
    "gn:name":"Huangshantian",
    "gn:population":0,
    "gn:timezone":"Asia/Shanghai",
    "iso:country":"CN",
    "name:zho_x_preferred":[
        "\u9ec4\u5584\u7530"
    ],
    "wof:name":"Huangshantian",
    "wof:placetype":"locality"
},
  "geometry": {"coordinates":[112.58447,23.87103],"type":"Point"}
}