{
  "type": "Feature",
  "properties": {
    "gn:admin1_code":"19.0",
    "gn:asciiname":"Xiaohuzui",
    "gn:country_code":"CN",
    "gn:dem":6,
    "gn:feature_class":"P",
    "gn:feature_code":"PPL",
    "gn:name":"Xiaohuzui",
    "gn:population":0,
    "gn:timezone":"Asia/Shanghai",
    "iso:country":"CN",
    "name:und_x_variant":[
        "\u5c0f\u6e56\u5634"
    ],
    "name:zho_x_preferred":[
        "\u5c0f\u6e56\u5634"
    ],
    "wof:name":"Xiaohuzui",
    "wof:placetype":"locality"
},
  "geometry": {"coordinates":[121.67359,41.32286],"type":"Point"}
}