{
  "type": "Feature",
  "properties": {
    "gn:admin1_code":"19.0",
    "gn:asciiname":"Zhangjia",
    "gn:country_code":"CN",
    "gn:dem":22,
    "gn:feature_class":"P",
    "gn:feature_code":"PPL",
    "gn:name":"Zhangjia",
    "gn:population":0,
    "gn:timezone":"Asia/Shanghai",
    "iso:country":"CN",
    "name:und_x_variant":[
        "\u5f20\u5bb6"
    ],
    "name:zho_x_preferred":[
        "\u5f20\u5bb6"
    ],
    "wof:name":"Zhangjia",
    "wof:placetype":"locality"
},
  "geometry": {"coordinates":[122.29476,41.75423],"type":"Point"}
}