{
  "type": "Feature",
  "properties": {
    "gn:admin1_code":"14.0",
    "gn:asciiname":"Yuqiong",
    "gn:country_code":"CN",
    "gn:dem":3900,
    "gn:feature_class":"P",
    "gn:feature_code":"PPL",
    "gn:name":"Yuqiong",
    "gn:population":0,
    "gn:timezone":"Asia/Urumqi",
    "iso:country":"CN",
    "name:zho_x_preferred":[
        "\u4f59\u7a77"
    ],
    "wof:name":"Yuqiong",
    "wof:placetype":"locality"
},
  "geometry": {"coordinates":[96.98768,30.09202],"type":"Point"}
}