{
  "type": "Feature",
  "properties": {
    "gn:admin1_code":"1.0",
    "gn:asciiname":"Bangangcun",
    "gn:country_code":"CN",
    "gn:dem":30,
    "gn:feature_class":"P",
    "gn:feature_code":"PPL",
    "gn:name":"Bangangcun",
    "gn:population":0,
    "gn:timezone":"Asia/Shanghai",
    "iso:country":"CN",
    "name:zho_x_preferred":[
        "\u534a\u5c97\u6751"
    ],
    "wof:name":"Bangangcun",
    "wof:placetype":"locality"
},
  "geometry": {"coordinates":[115.82163,32.75487],"type":"Point"}
}