{
  "type": "Feature",
  "properties": {
    "gn:admin1_code":"24",
    "gn:asciiname":"Gaojiacun",
    "gn:cc2":"CN",
    "gn:country_code":"CN",
    "gn:dem":915,
    "gn:feature_class":"P",
    "gn:feature_code":"PPL",
    "gn:name":"Gaojiacun",
    "gn:population":0,
    "gn:timezone":"Asia/Shanghai",
    "iso:country":"CN",
    "name:und_x_variant":[
        "Kao-chia-ts\u2019un",
        "Gaojiacun"
    ],
    "wof:name":"Gaojiacun",
    "wof:placetype":"locality"
},
  "geometry": {"coordinates":[110.98333,38.48333],"type":"Point"}
}