{
  "type": "Feature",
  "properties": {
    "gn:admin1_code":"14.0",
    "gn:asciiname":"Baga",
    "gn:country_code":"CN",
    "gn:dem":4563,
    "gn:feature_class":"P",
    "gn:feature_code":"PPL",
    "gn:name":"Baga",
    "gn:population":0,
    "gn:timezone":"Asia/Urumqi",
    "iso:country":"CN",
    "name:zho_x_preferred":[
        "\u634c\u560e"
    ],
    "wof:name":"Baga",
    "wof:placetype":"locality"
},
  "geometry": {"coordinates":[93.61638000000001,29.39916],"type":"Point"}
}