{
  "type": "Feature",
  "properties": {
    "gn:admin1_code":"14.0",
    "gn:asciiname":"Baga",
    "gn:country_code":"CN",
    "gn:dem":4563,
    "gn:feature_class":"P",
    "gn:feature_code":"PPL",
    "gn:name":"Baga",
    "gn:population":0,
    "gn:timezone":"Asia/Urumqi",
    "iso:country":"CN",
    "name:ceb_x_preferred":[
        "Baga"
    ],
    "name:deu_x_preferred":[
        "Baga"
    ],
    "name:eus_x_preferred":[
        "Baga"
    ],
    "name:fao_x_preferred":[
        "Baga"
    ],
    "name:fra_x_preferred":[
        "Baga"
    ],
    "name:hye_x_preferred":[
        "\u0532\u0561\u0563\u0561"
    ],
    "name:ita_x_preferred":[
        "Baga"
    ],
    "name:kat_x_preferred":[
        "\u10d1\u10d0\u10d2\u10d0"
    ],
    "name:nld_x_preferred":[
        "Baga"
    ],
    "name:por_x_preferred":[
        "Baga"
    ],
    "name:rus_x_preferred":[
        "\u0411\u0430\u0433\u0430"
    ],
    "name:swe_x_preferred":[
        "Baga"
    ],
    "name:tgl_x_preferred":[
        "Baga"
    ],
    "name:ukr_x_preferred":[
        "\u0411\u0430\u0433\u0430"
    ],
    "name:zho_x_preferred":[
        "\u634c\u560e"
    ],
    "wof:name":"Baga",
    "wof:placetype":"locality"
},
  "geometry": {"coordinates":[93.61638000000001,29.39916],"type":"Point"}
}