{
  "type": "Feature",
  "properties": {
    "gn:admin1_code":"15",
    "gn:asciiname":"Gangu Chengguanzhen",
    "gn:country_code":"CN",
    "gn:dem":1287,
    "gn:feature_class":"P",
    "gn:feature_code":"PPLA3",
    "gn:name":"Gangu Chengguanzhen",
    "gn:population":0,
    "gn:timezone":"Asia/Shanghai",
    "iso:country":"CN",
    "name:und_x_variant":[
        "Kan-ku-hsien",
        "Futsyan",
        "Kan-ku",
        "Fu-k\u2019iang-hi\u00e9n",
        "Fu-ch\u2019iang",
        "Gangu",
        "Gangu Chengguanzhen",
        "Gangu Xian"
    ],
    "name:zho_x_preferred":[
        "\u7518\u53e4\u57ce\u5173\u9547"
    ],
    "name:zho_x_variant":[
        "\u7518\u8c37\u53bf"
    ],
    "wof:name":"Gangu Chengguanzhen",
    "wof:placetype":"locality"
},
  "geometry": {"coordinates":[105.32632,34.73564],"type":"Point"}
}