{
  "type": "Feature",
  "properties": {
    "gn:admin1_code":"29.0",
    "gn:asciiname":"Anleti",
    "gn:country_code":"CN",
    "gn:dem":2023,
    "gn:feature_class":"P",
    "gn:feature_code":"PPL",
    "gn:name":"Anleti",
    "gn:population":0,
    "gn:timezone":"Asia/Shanghai",
    "iso:country":"CN",
    "name:zho_x_preferred":[
        "\u5b89\u4e50\u68af"
    ],
    "wof:name":"Anleti",
    "wof:placetype":"locality"
},
  "geometry": {"coordinates":[100.328,25.1318],"type":"Point"}
}