{
  "type": "Feature",
  "properties": {
    "gn:admin1_code":"5.0",
    "gn:asciiname":"Xiweizi",
    "gn:country_code":"CN",
    "gn:dem":142,
    "gn:feature_class":"P",
    "gn:feature_code":"PPL",
    "gn:name":"Xiweizi",
    "gn:population":0,
    "gn:timezone":"Asia/Shanghai",
    "iso:country":"CN",
    "name:zho_x_preferred":[
        "\u897f\u56f4\u5b50"
    ],
    "wof:name":"Xiweizi",
    "wof:placetype":"locality"
},
  "geometry": {"coordinates":[123.09272,45.51611],"type":"Point"}
}