{
  "type": "Feature",
  "properties": {
    "gn:country":"CN",
    "gn:fcode":"ADM3",
    "gn:population":0,
    "iso:country":"CN",
    "name:deu_x_preferred":[
        "Wei"
    ],
    "name:eng_x_preferred":[
        "Wei County"
    ],
    "name:fas_x_preferred":[
        "\u0634\u0647\u0631\u0633\u062a\u0627\u0646 \u0648\u06cc"
    ],
    "name:gan_x_preferred":[
        "\u9b4f\u53bf"
    ],
    "name:jpn_x_preferred":[
        "\u9b4f\u770c"
    ],
    "name:kor_x_preferred":[
        "\uc6e8\uc774\ud604"
    ],
    "name:nan_x_preferred":[
        "G\u016bi-ko\u0101n"
    ],
    "name:nld_x_preferred":[
        "Wei"
    ],
    "name:nob_x_preferred":[
        "Wei"
    ],
    "name:rus_x_preferred":[
        "\u0412\u044d\u0439\u0441\u044f\u043d\u044c"
    ],
    "name:swe_x_preferred":[
        "Wei"
    ],
    "name:und_x_variant":[
        "Wei Hsien"
    ],
    "name:vie_x_preferred":[
        "Ng\u1ee5y"
    ],
    "name:wuu_x_preferred":[
        "\u9b4f\u53bf"
    ],
    "name:zho_x_preferred":[
        "\u9b4f\u53bf"
    ],
    "qs:name":"Wei Xian",
    "qs:photos_9r":0,
    "qs:photos_sr":0,
    "qs:pop_sr":"0",
    "wd:wordcount":164,
    "wof:name":"Wei Xian",
    "wof:placetype":"localadmin",
    "wof:population":0
},
  "geometry": {"coordinates":[114.93333,36.35],"type":"Point"}
}