{
  "type": "Feature",
  "properties": {
    "gn:country":"CN",
    "gn:fcode":"ADM3",
    "gn:pop":0,
    "iso:country":"CN",
    "name:unk_x_variant":[
        "Wei Hsien"
    ],
    "name:zho_x_preferred":[
        "\u9b4f\u53bf"
    ],
    "qs:name":"Wei Xian",
    "qs:photos_9r":0,
    "qs:photos_sr":0,
    "qs:pop_sr":"0",
    "wd:wordcount":164,
    "wof:name":"Wei Xian",
    "wof:placetype":"localadmin",
    "wof:population":0
},
  "geometry": {"coordinates":[114.93333,36.35],"type":"Point"}
}