{
  "type": "Feature",
  "properties": {
    "gn:admin1_code":"30.0",
    "gn:asciiname":"Fenglai",
    "gn:country_code":"CN",
    "gn:dem":9,
    "gn:feature_class":"P",
    "gn:feature_code":"PPL",
    "gn:name":"Fenglai",
    "gn:population":0,
    "gn:timezone":"Asia/Shanghai",
    "iso:country":"CN",
    "name:zho_x_preferred":[
        "\u51e4\u6765"
    ],
    "wof:name":"Fenglai",
    "wof:placetype":"locality"
},
  "geometry": {"coordinates":[112.47727999999999,22.18182],"type":"Point"}
}