{
  "type": "Feature",
  "properties": {
    "gn:admin1_code":"12.0",
    "gn:asciiname":"Poyanchong",
    "gn:country_code":"CN",
    "gn:dem":108,
    "gn:feature_class":"P",
    "gn:feature_code":"PPL",
    "gn:name":"Poyanchong",
    "gn:population":0,
    "gn:timezone":"Asia/Shanghai",
    "iso:country":"CN",
    "name:zho_x_preferred":[
        "\u7834\u5830\u51b2"
    ],
    "wof:name":"Poyanchong",
    "wof:placetype":"locality"
},
  "geometry": {"coordinates":[112.72102,32.01023],"type":"Point"}
}