{
  "type": "Feature",
  "properties": {
    "gn:admin1_code":"25",
    "gn:asciiname":"Nanxizhou",
    "gn:country_code":"CN",
    "gn:dem":194,
    "gn:feature_class":"P",
    "gn:feature_code":"PPL",
    "gn:name":"Nanxizhou",
    "gn:population":0,
    "gn:timezone":"Asia/Shanghai",
    "iso:country":"CN",
    "name:zho_x_preferred":[
        "\u5357\u897f\u5468"
    ],
    "wof:name":"Nanxizhou",
    "wof:placetype":"locality"
},
  "geometry": {"coordinates":[117.727,35.9184],"type":"Point"}
}