{
  "type": "Feature",
  "properties": {
    "gn:admin1_code":"19.0",
    "gn:asciiname":"Laobu",
    "gn:country_code":"CN",
    "gn:dem":7,
    "gn:feature_class":"P",
    "gn:feature_code":"PPL",
    "gn:name":"Laobu",
    "gn:population":0,
    "gn:timezone":"Asia/Shanghai",
    "iso:country":"CN",
    "name:und_x_variant":[
        "\u8001\u535c"
    ],
    "name:zho_x_preferred":[
        "\u8001\u535c"
    ],
    "wof:name":"Laobu",
    "wof:placetype":"locality"
},
  "geometry": {"coordinates":[123.85558,39.87465],"type":"Point"}
}