{
  "type": "Feature",
  "properties": {
    "gn:admin1_code":"20",
    "gn:asciiname":"Touhao",
    "gn:country_code":"CN",
    "gn:dem":1390,
    "gn:feature_class":"P",
    "gn:feature_code":"PPL",
    "gn:name":"Touhao",
    "gn:population":0,
    "gn:timezone":"Asia/Shanghai",
    "iso:country":"CN",
    "name:und_x_variant":[
        "\u5934\u53f7"
    ],
    "wof:name":"Touhao",
    "wof:placetype":"locality"
},
  "geometry": {"coordinates":[113.69159000000001,41.1069],"type":"Point"}
}