{
  "type": "Feature",
  "properties": {
    "gn:admin1_code":"2",
    "gn:asciiname":"Hongtongmiao",
    "gn:country_code":"CN",
    "gn:dem":5,
    "gn:feature_class":"P",
    "gn:feature_code":"PPL",
    "gn:name":"Hongtongmiao",
    "gn:population":0,
    "gn:timezone":"Asia/Shanghai",
    "iso:country":"CN",
    "name:und_x_variant":[
        "\u6d2a\u6850\u5e99",
        "Hongdongmiao"
    ],
    "wof:name":"Hongtongmiao",
    "wof:placetype":"locality"
},
  "geometry": {"coordinates":[119.92111,30.31222],"type":"Point"}
}