{
  "type": "Feature",
  "properties": {
    "gn:admin1_code":"14.0",
    "gn:asciiname":"Salong",
    "gn:country_code":"CN",
    "gn:dem":4879,
    "gn:feature_class":"P",
    "gn:feature_code":"PPL",
    "gn:name":"Salong",
    "gn:population":0,
    "gn:timezone":"Asia/Urumqi",
    "iso:country":"CN",
    "name:zho_x_preferred":[
        "\u8428\u9f99"
    ],
    "wof:name":"Salong",
    "wof:placetype":"locality"
},
  "geometry": {"coordinates":[84.6597,31.804],"type":"Point"}
}