{
  "type": "Feature",
  "properties": {
    "gn:admin1_code":"3.0",
    "gn:asciiname":"Yangtianwan",
    "gn:country_code":"CN",
    "gn:dem":62,
    "gn:feature_class":"P",
    "gn:feature_code":"PPL",
    "gn:name":"Yangtianwan",
    "gn:population":0,
    "gn:timezone":"Asia/Shanghai",
    "iso:country":"CN",
    "name:zho_x_preferred":[
        "\u6768\u7530\u6e7e"
    ],
    "wof:name":"Yangtianwan",
    "wof:placetype":"locality"
},
  "geometry": {"coordinates":[117.114,29.1687],"type":"Point"}
}