{
  "type": "Feature",
  "properties": {
    "gn:admin1_code":"2.0",
    "gn:asciiname":"Jishang",
    "gn:country_code":"CN",
    "gn:dem":729,
    "gn:feature_class":"P",
    "gn:feature_code":"PPL",
    "gn:name":"Jishang",
    "gn:population":0,
    "gn:timezone":"Asia/Shanghai",
    "iso:country":"CN",
    "name:zho_x_preferred":[
        "\u9645\u4e0a"
    ],
    "wof:name":"Jishang",
    "wof:placetype":"locality"
},
  "geometry": {"coordinates":[118.93941,28.02961],"type":"Point"}
}