{
  "type": "Feature",
  "properties": {
    "gn:admin1_code":"8.0",
    "gn:asciiname":"Niuwangtun",
    "gn:country_code":"CN",
    "gn:dem":262,
    "gn:feature_class":"P",
    "gn:feature_code":"PPL",
    "gn:name":"Niuwangtun",
    "gn:population":0,
    "gn:timezone":"Asia/Shanghai",
    "iso:country":"CN",
    "name:zho_x_preferred":[
        "\u725b\u65fa\u5c6f"
    ],
    "wof:name":"Niuwangtun",
    "wof:placetype":"locality"
},
  "geometry": {"coordinates":[125.60791999999999,48.40736],"type":"Point"}
}