{
  "type": "Feature",
  "properties": {
    "gn:admin1_code":"26.0",
    "gn:asciiname":"Wazizhaicun",
    "gn:country_code":"CN",
    "gn:dem":630,
    "gn:feature_class":"P",
    "gn:feature_code":"PPL",
    "gn:name":"Wazizhaicun",
    "gn:population":0,
    "gn:timezone":"Asia/Shanghai",
    "iso:country":"CN",
    "name:zho_x_preferred":[
        "\u74e6\u7d2b\u5be8\u6751"
    ],
    "wof:name":"Wazizhaicun",
    "wof:placetype":"locality"
},
  "geometry": {"coordinates":[108.94486000000001,34.81127],"type":"Point"}
}