{
  "type": "Feature",
  "properties": {
    "gn:admin1_code":"29.0",
    "gn:asciiname":"Deka",
    "gn:country_code":"CN",
    "gn:dem":2100,
    "gn:feature_class":"P",
    "gn:feature_code":"PPL",
    "gn:name":"Deka",
    "gn:population":0,
    "gn:timezone":"Asia/Shanghai",
    "iso:country":"CN",
    "name:ceb_x_preferred":[
        "Deka"
    ],
    "name:ces_x_preferred":[
        "Deka"
    ],
    "name:deu_x_preferred":[
        "Deka"
    ],
    "name:fin_x_preferred":[
        "Deka"
    ],
    "name:nds_x_preferred":[
        "Deka"
    ],
    "name:rus_x_preferred":[
        "\u0414\u0435\u043a\u0430"
    ],
    "name:swe_x_preferred":[
        "Deka"
    ],
    "name:zho_x_preferred":[
        "\u5fb7\u5361"
    ],
    "wof:name":"Deka",
    "wof:placetype":"locality"
},
  "geometry": {"coordinates":[102.93899999999999,25.78],"type":"Point"}
}