{
  "type": "Feature",
  "properties": {
    "gn:admin1_code":"15.0",
    "gn:asciiname":"Yan Chuan Zi",
    "gn:country_code":"CN",
    "gn:dem":1662,
    "gn:feature_class":"P",
    "gn:feature_code":"PPL",
    "gn:name":"Yan Chuan Zi",
    "gn:population":0,
    "gn:timezone":"Asia/Shanghai",
    "iso:country":"CN",
    "wof:name":"Yan Chuan Zi",
    "wof:placetype":"locality"
},
  "geometry": {"coordinates":[106.46639999999999,35.58237000000001],"type":"Point"}
}