{
  "type": "Feature",
  "properties": {
    "gn:admin1_code":"24.0",
    "gn:asciiname":"Zhuangtoucun",
    "gn:country_code":"CN",
    "gn:dem":1142,
    "gn:feature_class":"P",
    "gn:feature_code":"PPL",
    "gn:name":"Zhuangtoucun",
    "gn:population":0,
    "gn:timezone":"Asia/Shanghai",
    "iso:country":"CN",
    "name:zho_x_preferred":[
        "\u5e84\u5934\u6751"
    ],
    "wof:name":"Zhuangtoucun",
    "wof:placetype":"locality"
},
  "geometry": {"coordinates":[110.79604999999999,38.19136],"type":"Point"}
}