{
  "type": "Feature",
  "properties": {
    "gn:admin1_code":"8.0",
    "gn:asciiname":"Fendoucun",
    "gn:country_code":"CN",
    "gn:dem":146,
    "gn:feature_class":"P",
    "gn:feature_code":"PPL",
    "gn:name":"Fendoucun",
    "gn:population":0,
    "gn:timezone":"Asia/Shanghai",
    "iso:country":"CN",
    "name:zho_x_preferred":[
        "\u594b\u6597\u6751"
    ],
    "wof:name":"Fendoucun",
    "wof:placetype":"locality"
},
  "geometry": {"coordinates":[130.38475,46.43379],"type":"Point"}
}