{
  "type": "Feature",
  "properties": {
    "gn:admin1_code":"12.0",
    "gn:asciiname":"Wengjiadian",
    "gn:country_code":"CN",
    "gn:dem":91,
    "gn:feature_class":"P",
    "gn:feature_code":"PPL",
    "gn:name":"Wengjiadian",
    "gn:population":0,
    "gn:timezone":"Asia/Shanghai",
    "iso:country":"CN",
    "name:zho_x_preferred":[
        "\u7fc1\u5bb6\u5e97"
    ],
    "wof:name":"Wengjiadian",
    "wof:placetype":"locality"
},
  "geometry": {"coordinates":[114.46216,31.18619],"type":"Point"}
}