{
  "type": "Feature",
  "properties": {
    "gn:admin1_code":"26.0",
    "gn:asciiname":"Yangou",
    "gn:country_code":"CN",
    "gn:dem":806,
    "gn:feature_class":"P",
    "gn:feature_code":"PPL",
    "gn:name":"Yangou",
    "gn:population":0,
    "gn:timezone":"Asia/Shanghai",
    "iso:country":"CN",
    "name:und_x_variant":[
        "\u5830\u6c9f"
    ],
    "wof:name":"Yangou",
    "wof:placetype":"locality"
},
  "geometry": {"coordinates":[108.02641,33.16205],"type":"Point"}
}