{
  "type": "Feature",
  "properties": {
    "gn:admin1_code":"3.0",
    "gn:asciiname":"Baishaping",
    "gn:country_code":"CN",
    "gn:dem":1000,
    "gn:feature_class":"P",
    "gn:feature_code":"PPL",
    "gn:name":"Baishaping",
    "gn:population":0,
    "gn:timezone":"Asia/Shanghai",
    "iso:country":"CN",
    "name:und_x_variant":[
        "\u767d\u6c99\u576a"
    ],
    "wof:name":"Baishaping",
    "wof:placetype":"locality"
},
  "geometry": {"coordinates":[114.9059,28.83108],"type":"Point"}
}