{
  "type": "Feature",
  "properties": {
    "gn:admin1_code":"11.0",
    "gn:asciiname":"Shamuchong",
    "gn:country_code":"CN",
    "gn:dem":334,
    "gn:feature_class":"P",
    "gn:feature_code":"PPL",
    "gn:name":"Shamuchong",
    "gn:population":0,
    "gn:timezone":"Asia/Shanghai",
    "iso:country":"CN",
    "name:zho_x_preferred":[
        "\u6749\u6728\u51b2"
    ],
    "wof:name":"Shamuchong",
    "wof:placetype":"locality"
},
  "geometry": {"coordinates":[112.43253,25.49449],"type":"Point"}
}