{
  "type": "Feature",
  "properties": {
    "gn:admin1_code":"29.0",
    "gn:asciiname":"Xifengping",
    "gn:country_code":"CN",
    "gn:dem":2669,
    "gn:feature_class":"P",
    "gn:feature_code":"PPL",
    "gn:name":"Xifengping",
    "gn:population":0,
    "gn:timezone":"Asia/Shanghai",
    "iso:country":"CN",
    "name:zho_x_preferred":[
        "\u897f\u5cf0\u576a"
    ],
    "wof:name":"Xifengping",
    "wof:placetype":"locality"
},
  "geometry": {"coordinates":[99.8565,26.6331],"type":"Point"}
}