{
  "type": "Feature",
  "properties": {
    "gn:admin1_code":"7.0",
    "gn:asciiname":"Xinglian",
    "gn:country_code":"CN",
    "gn:dem":56,
    "gn:feature_class":"P",
    "gn:feature_code":"PPL",
    "gn:name":"Xinglian",
    "gn:population":0,
    "gn:timezone":"Asia/Shanghai",
    "iso:country":"CN",
    "name:zho_x_preferred":[
        "\u674f\u83b2"
    ],
    "wof:name":"Xinglian",
    "wof:placetype":"locality"
},
  "geometry": {"coordinates":[118.38564,24.9204],"type":"Point"}
}