{
  "type": "Feature",
  "properties": {
    "gn:admin1_code":"18",
    "gn:asciiname":"Siyazhai",
    "gn:country_code":"CN",
    "gn:dem":883,
    "gn:feature_class":"P",
    "gn:feature_code":"PPL",
    "gn:name":"Siyazhai",
    "gn:population":0,
    "gn:timezone":"Asia/Shanghai",
    "iso:country":"CN",
    "name:zho_x_preferred":[
        "\u56db\u8859\u5be8"
    ],
    "wof:name":"Siyazhai",
    "wof:placetype":"locality"
},
  "geometry": {"coordinates":[107.06,27.9411],"type":"Point"}
}