{
  "type": "Feature",
  "properties": {
    "gn:admin1_code":"33.0",
    "gn:asciiname":"Longdongtuo",
    "gn:country_code":"CN",
    "gn:dem":1047,
    "gn:feature_class":"P",
    "gn:feature_code":"PPL",
    "gn:name":"Longdongtuo",
    "gn:population":0,
    "gn:timezone":"Asia/Shanghai",
    "iso:country":"CN",
    "name:zho_x_preferred":[
        "\u9f99\u6d1e\u5768"
    ],
    "wof:name":"Longdongtuo",
    "wof:placetype":"locality"
},
  "geometry": {"coordinates":[108.85526000000002,28.86401],"type":"Point"}
}