{
  "type": "Feature",
  "properties": {
    "gn:admin1_code":"5.0",
    "gn:asciiname":"Xiwazicun",
    "gn:country_code":"CN",
    "gn:dem":180,
    "gn:feature_class":"P",
    "gn:feature_code":"PPL",
    "gn:name":"Xiwazicun",
    "gn:population":0,
    "gn:timezone":"Asia/Shanghai",
    "iso:country":"CN",
    "name:zho_x_preferred":[
        "\u897f\u6d3c\u5b50\u6751"
    ],
    "wof:name":"Xiwazicun",
    "wof:placetype":"locality"
},
  "geometry": {"coordinates":[124.81948,43.68497],"type":"Point"}
}