{
  "type": "Feature",
  "properties": {
    "gn:admin1_code":"24.0",
    "gn:asciiname":"Xiaojiawa",
    "gn:country_code":"CN",
    "gn:dem":1081,
    "gn:feature_class":"P",
    "gn:feature_code":"PPL",
    "gn:name":"Xiaojiawa",
    "gn:population":0,
    "gn:timezone":"Asia/Shanghai",
    "iso:country":"CN",
    "name:und_x_variant":[
        "Hsiao-chia-wa",
        "Xiaojiawa"
    ],
    "name:zho_x_preferred":[
        "\u8096\u5bb6\u6d3c"
    ],
    "wof:name":"Xiaojiawa",
    "wof:placetype":"locality"
},
  "geometry": {"coordinates":[111.13840999999999,38.39995],"type":"Point"}
}