{
  "type": "Feature",
  "properties": {
    "gn:admin1_code":"9.0",
    "gn:asciiname":"Nanxian",
    "gn:country_code":"CN",
    "gn:dem":582,
    "gn:feature_class":"P",
    "gn:feature_code":"PPL",
    "gn:name":"Nanxian",
    "gn:population":0,
    "gn:timezone":"Asia/Shanghai",
    "iso:country":"CN",
    "name:zho_x_preferred":[
        "\u5357\u53bf"
    ],
    "wof:name":"Nanxian",
    "wof:placetype":"locality"
},
  "geometry": {"coordinates":[111.30697000000001,34.66445],"type":"Point"}
}