{
  "type": "Feature",
  "properties": {
    "gn:admin1_code":"15.0",
    "gn:asciiname":"Xidian Liudui",
    "gn:country_code":"CN",
    "gn:dem":1447,
    "gn:feature_class":"P",
    "gn:feature_code":"PPLF",
    "gn:name":"Xidian Liudui",
    "gn:population":0,
    "gn:timezone":"Asia/Shanghai",
    "iso:country":"CN",
    "name:zho_x_preferred":[
        "\u897f\u5e97\u516d\u961f"
    ],
    "wof:name":"Xidian Liudui",
    "wof:placetype":"locality"
},
  "geometry": {"coordinates":[98.6305,39.6661],"type":"Point"}
}