{
  "type": "Feature",
  "properties": {
    "gn:admin1_code":"8.0",
    "gn:asciiname":"Xiaolizigou",
    "gn:country_code":"CN",
    "gn:dem":452,
    "gn:feature_class":"P",
    "gn:feature_code":"PPL",
    "gn:name":"Xiaolizigou",
    "gn:population":0,
    "gn:timezone":"Asia/Shanghai",
    "iso:country":"CN",
    "name:und_x_variant":[
        "\u5c0f\u674e\u5b50\u6c9f"
    ],
    "wof:name":"Xiaolizigou",
    "wof:placetype":"locality"
},
  "geometry": {"coordinates":[131.07660000000001,43.72264000000001],"type":"Point"}
}