{
  "type": "Feature",
  "properties": {
    "gn:admin1_code":"02",
    "gn:asciiname":"Pantancun",
    "gn:country_code":"CN",
    "gn:dem":260,
    "gn:feature_class":"P",
    "gn:feature_code":"PPL",
    "gn:name":"Pantancun",
    "gn:population":0,
    "gn:timezone":"Asia/Shanghai",
    "iso:country":"CN",
    "name:und_x_variant":[
        "Pantan",
        "Pantancun"
    ],
    "name:zho_x_preferred":[
        "\u6f58\u6f6d"
    ],
    "name:zho_x_variant":[
        "\u6f58\u6f6d\u6751"
    ],
    "wof:name":"Pantancun",
    "wof:placetype":"locality"
},
  "geometry": {"coordinates":[120.3139,28.89551],"type":"Point"}
}