{
  "type": "Feature",
  "properties": {
    "gn:admin1_code":"16.0",
    "gn:asciiname":"Nonggou",
    "gn:country_code":"CN",
    "gn:dem":538,
    "gn:feature_class":"P",
    "gn:feature_code":"PPL",
    "gn:name":"Nonggou",
    "gn:population":0,
    "gn:timezone":"Asia/Shanghai",
    "iso:country":"CN",
    "name:zho_x_preferred":[
        "\u5f04\u52fe"
    ],
    "wof:name":"Nonggou",
    "wof:placetype":"locality"
},
  "geometry": {"coordinates":[108.152,24.0405],"type":"Point"}
}