{
  "type": "Feature",
  "properties": {
    "gn:admin1_code":"3.0",
    "gn:asciiname":"Taoling",
    "gn:country_code":"CN",
    "gn:dem":45,
    "gn:feature_class":"P",
    "gn:feature_code":"PPL",
    "gn:name":"Taoling",
    "gn:population":0,
    "gn:timezone":"Asia/Shanghai",
    "iso:country":"CN",
    "name:und_x_variant":[
        "\u6843\u5cad"
    ],
    "wof:name":"Taoling",
    "wof:placetype":"locality"
},
  "geometry": {"coordinates":[116.54367000000001,27.94067],"type":"Point"}
}