{
  "type": "Feature",
  "properties": {
    "gn:admin1_code":"1.0",
    "gn:asciiname":"Dinancun",
    "gn:country_code":"CN",
    "gn:dem":25,
    "gn:feature_class":"P",
    "gn:feature_code":"PPL",
    "gn:name":"Dinancun",
    "gn:population":0,
    "gn:timezone":"Asia/Shanghai",
    "iso:country":"CN",
    "name:zho_x_preferred":[
        "\u5824\u5357\u6751"
    ],
    "wof:name":"Dinancun",
    "wof:placetype":"locality"
},
  "geometry": {"coordinates":[116.39821999999999,32.54264000000001],"type":"Point"}
}