{
  "type": "Feature",
  "properties": {
    "gn:admin1_code":"30.0",
    "gn:asciiname":"Dongshengcun",
    "gn:country_code":"CN",
    "gn:dem":274,
    "gn:feature_class":"P",
    "gn:feature_code":"PPL",
    "gn:name":"Dongshengcun",
    "gn:population":0,
    "gn:timezone":"Asia/Shanghai",
    "iso:country":"CN",
    "name:zho_x_preferred":[
        "\u4e1c\u5347\u6751"
    ],
    "wof:name":"Dongshengcun",
    "wof:placetype":"locality"
},
  "geometry": {"coordinates":[115.92601000000001,24.18719],"type":"Point"}
}