{
  "type": "Feature",
  "properties": {
    "gn:admin1_code":"15.0",
    "gn:asciiname":"Xisanshipu",
    "gn:country_code":"CN",
    "gn:dem":1339,
    "gn:feature_class":"P",
    "gn:feature_code":"PPL",
    "gn:name":"Xisanshipu",
    "gn:population":0,
    "gn:timezone":"Asia/Shanghai",
    "iso:country":"CN",
    "name:zho_x_preferred":[
        "\u897f\u4e09\u5341\u94fa"
    ],
    "wof:name":"Xisanshipu",
    "wof:placetype":"locality"
},
  "geometry": {"coordinates":[105.182,34.7486],"type":"Point"}
}