{
  "type": "Feature",
  "properties": {
    "gn:admin1_code":"15.0",
    "gn:asciiname":"Santai",
    "gn:country_code":"CN",
    "gn:dem":2493,
    "gn:feature_class":"P",
    "gn:feature_code":"PPL",
    "gn:name":"Santai",
    "gn:population":0,
    "gn:timezone":"Asia/Shanghai",
    "iso:country":"CN",
    "name:und_x_variant":[
        "\u4e09\u53f0"
    ],
    "wof:name":"Santai",
    "wof:placetype":"locality"
},
  "geometry": {"coordinates":[104.7317,34.5754],"type":"Point"}
}