{
  "type": "Feature",
  "properties": {
    "gn:admin1_code":"3.0",
    "gn:asciiname":"Leigutan",
    "gn:country_code":"CN",
    "gn:dem":90,
    "gn:feature_class":"P",
    "gn:feature_code":"PPL",
    "gn:name":"Leigutan",
    "gn:population":0,
    "gn:timezone":"Asia/Shanghai",
    "iso:country":"CN",
    "name:und_x_variant":[
        "\u96f7\u9f13\u6f6d"
    ],
    "wof:name":"Leigutan",
    "wof:placetype":"locality"
},
  "geometry": {"coordinates":[114.72478999999998,28.31285],"type":"Point"}
}