{
  "type": "Feature",
  "properties": {
    "gn:admin1_code":"13.0",
    "gn:asciiname":"Huojia'er",
    "gn:country_code":"CN",
    "gn:dem":892,
    "gn:feature_class":"P",
    "gn:feature_code":"PPL",
    "gn:name":"Huojia\u2019er",
    "gn:population":0,
    "gn:timezone":"Asia/Urumqi",
    "iso:country":"CN",
    "name:und_x_variant":[
        "Huojia\u2019er"
    ],
    "name:zho_x_preferred":[
        "\u970d\u52a0\u5c14"
    ],
    "wof:name":"Huojia'er",
    "wof:placetype":"locality"
},
  "geometry": {"coordinates":[85.91184,41.08379],"type":"Point"}
}