{
  "type": "Feature",
  "properties": {
    "gn:admin1_code":"30",
    "gn:asciiname":"Yangmei",
    "gn:country_code":"CN",
    "gn:dem":33,
    "gn:feature_class":"P",
    "gn:feature_code":"PPL",
    "gn:name":"Yangmei",
    "gn:population":0,
    "gn:timezone":"Asia/Urumqi",
    "iso:country":"CN",
    "name:ara_x_preferred":[
        "\u064a\u0627\u0646\u063a \u0645\u0627\u064a"
    ],
    "name:ben_x_preferred":[
        "\u0987\u09df\u09be\u0982\u09ae\u09c7\u0987"
    ],
    "name:ceb_x_preferred":[
        "Yangmei"
    ],
    "name:deu_x_preferred":[
        "Yangmei"
    ],
    "name:ell_x_preferred":[
        "\u0393\u03b9\u03b1\u03bd\u03b3\u03ba\u03bc\u03ad\u03b9"
    ],
    "name:fas_x_preferred":[
        "\u06cc\u0627\u0646\u06af\u0645\u06cc"
    ],
    "name:heb_x_preferred":[
        "\u05d9\u05d0\u05e0\u05d2\u05de\u05d0\u05d9"
    ],
    "name:hin_x_preferred":[
        "\u092f\u093e\u0902\u0917\u092e\u0940"
    ],
    "name:hun_x_preferred":[
        "Yangmei"
    ],
    "name:ind_x_preferred":[
        "Yangmei"
    ],
    "name:jpn_x_preferred":[
        "\u694a\u6885\u93ae"
    ],
    "name:por_x_preferred":[
        "Yangmei"
    ],
    "name:swe_x_preferred":[
        "Yangmei"
    ],
    "name:tur_x_preferred":[
        "Yangmei"
    ],
    "name:ukr_x_preferred":[
        "\u042f\u043d\u0433\u043c\u0435\u0439"
    ],
    "name:vie_x_preferred":[
        "D\u01b0\u01a1ng mai"
    ],
    "name:zho_x_preferred":[
        "\u6768\u6885"
    ],
    "name:zho_x_variant":[
        "\u694a\u6885\u93ae"
    ],
    "wof:name":"Yangmei",
    "wof:placetype":"locality"
},
  "geometry": {"coordinates":[110.49724000000001,21.86558],"type":"Point"}
}