{
  "type": "Feature",
  "properties": {
    "gn:admin1_code":"30",
    "gn:asciiname":"Yangmei",
    "gn:country_code":"CN",
    "gn:dem":33,
    "gn:feature_class":"P",
    "gn:feature_code":"PPL",
    "gn:name":"Yangmei",
    "gn:population":0,
    "gn:timezone":"Asia/Urumqi",
    "iso:country":"CN",
    "name:ceb_x_preferred":[
        "Yangmei"
    ],
    "name:deu_x_preferred":[
        "Yangmei"
    ],
    "name:jpn_x_preferred":[
        "\u694a\u6885\u93ae"
    ],
    "name:swe_x_preferred":[
        "Yangmei"
    ],
    "name:vie_x_preferred":[
        "D\u01b0\u01a1ng mai"
    ],
    "name:zho_x_preferred":[
        "\u6768\u6885"
    ],
    "name:zho_x_variant":[
        "\u694a\u6885\u93ae"
    ],
    "wof:name":"Yangmei",
    "wof:placetype":"locality"
},
  "geometry": {"coordinates":[110.49724000000001,21.86558],"type":"Point"}
}