{
  "type": "Feature",
  "properties": {
    "gn:admin1_code":"26",
    "gn:asciiname":"Qingkou",
    "gn:country_code":"CN",
    "gn:dem":563,
    "gn:feature_class":"P",
    "gn:feature_code":"PPL",
    "gn:name":"Qingkou",
    "gn:population":0,
    "gn:timezone":"Asia/Shanghai",
    "iso:country":"CN",
    "name:zho_x_preferred":[
        "\u9752\u53e3"
    ],
    "wof:name":"Qingkou",
    "wof:placetype":"locality"
},
  "geometry": {"coordinates":[108.28666,34.36848],"type":"Point"}
}