{
  "type": "Feature",
  "properties": {
    "gn:admin1_code":"2.0",
    "gn:asciiname":"Waihuangdan",
    "gn:country_code":"CN",
    "gn:dem":308,
    "gn:feature_class":"P",
    "gn:feature_code":"PPL",
    "gn:name":"Waihuangdan",
    "gn:population":0,
    "gn:timezone":"Asia/Shanghai",
    "iso:country":"CN",
    "name:zho_x_preferred":[
        "\u5916\u9ec4\u5f39"
    ],
    "wof:name":"Waihuangdan",
    "wof:placetype":"locality"
},
  "geometry": {"coordinates":[120.05108,29.85316],"type":"Point"}
}