{
  "type": "Feature",
  "properties": {
    "gn:admin1_code":"26.0",
    "gn:asciiname":"Shagoutang",
    "gn:country_code":"CN",
    "gn:dem":343,
    "gn:feature_class":"P",
    "gn:feature_code":"PPL",
    "gn:name":"Shagoutang",
    "gn:population":0,
    "gn:timezone":"Asia/Shanghai",
    "iso:country":"CN",
    "name:zho_x_preferred":[
        "\u6c99\u6c9f\u5858"
    ],
    "wof:name":"Shagoutang",
    "wof:placetype":"locality"
},
  "geometry": {"coordinates":[109.6764,32.91216],"type":"Point"}
}