{
  "type": "Feature",
  "properties": {
    "gn:admin1_code":"10.0",
    "gn:asciiname":"Qijiazao",
    "gn:country_code":"CN",
    "gn:dem":903,
    "gn:feature_class":"P",
    "gn:feature_code":"PPL",
    "gn:name":"Qijiazao",
    "gn:population":0,
    "gn:timezone":"Asia/Shanghai",
    "iso:country":"CN",
    "name:zho_x_preferred":[
        "\u7941\u5bb6\u7682"
    ],
    "wof:name":"Qijiazao",
    "wof:placetype":"locality"
},
  "geometry": {"coordinates":[114.78139,39.97935],"type":"Point"}
}