{
  "type": "Feature",
  "properties": {
    "gn:admin1_code":"32.0",
    "gn:asciiname":"Lanlingping",
    "gn:country_code":"CN",
    "gn:dem":710,
    "gn:feature_class":"P",
    "gn:feature_code":"PPL",
    "gn:name":"Lanlingping",
    "gn:population":0,
    "gn:timezone":"Asia/Shanghai",
    "iso:country":"CN",
    "name:zho_x_preferred":[
        "\u5170\u5cad\u576a"
    ],
    "wof:name":"Lanlingping",
    "wof:placetype":"locality"
},
  "geometry": {"coordinates":[107.61929000000001,31.91387000000001],"type":"Point"}
}