{
  "type": "Feature",
  "properties": {
    "gn:admin1_code":"18",
    "gn:asciiname":"Dingjia Yuanzi",
    "gn:country_code":"CN",
    "gn:dem":2108,
    "gn:feature_class":"P",
    "gn:feature_code":"PPL",
    "gn:name":"Dingjia Yuanzi",
    "gn:population":0,
    "gn:timezone":"Asia/Shanghai",
    "iso:country":"CN",
    "name:zho_x_preferred":[
        "\u4e01\u5bb6\u9662\u5b50"
    ],
    "wof:name":"Dingjia Yuanzi",
    "wof:placetype":"locality"
},
  "geometry": {"coordinates":[103.95999999999999,27.20300000000001],"type":"Point"}
}