{
  "type": "Feature",
  "properties": {
    "gn:admin1_code":"1.0",
    "gn:asciiname":"Gaoyingcun",
    "gn:country_code":"CN",
    "gn:dem":72,
    "gn:feature_class":"P",
    "gn:feature_code":"PPL",
    "gn:name":"Gaoyingcun",
    "gn:population":0,
    "gn:timezone":"Asia/Shanghai",
    "iso:country":"CN",
    "name:zho_x_preferred":[
        "\u9ad8\u90e2\u6751"
    ],
    "wof:name":"Gaoyingcun",
    "wof:placetype":"locality"
},
  "geometry": {"coordinates":[118.46004000000001,32.69318],"type":"Point"}
}