{
  "type": "Feature",
  "properties": {
    "gn:admin1_code":"12",
    "gn:asciiname":"Jiahe",
    "gn:country_code":"CN",
    "gn:dem":208,
    "gn:feature_class":"P",
    "gn:feature_code":"PPLA4",
    "gn:name":"Jiahe",
    "gn:population":0,
    "gn:timezone":"Asia/Shanghai",
    "iso:country":"CN",
    "name:und_x_variant":[
        "Chia-ho",
        "Chia-ho-kuan",
        "Jiahe",
        "Jiahe Zhen",
        "\u5939\u6cb3\u9547"
    ],
    "name:zho_x_preferred":[
        "\u5939\u6cb3"
    ],
    "wof:name":"Jiahe",
    "wof:placetype":"locality"
},
  "geometry": {"coordinates":[110.02573999999998,32.87737],"type":"Point"}
}