{
  "type": "Feature",
  "properties": {
    "gn:admin1_code":"30.0",
    "gn:asciiname":"Genzhugen",
    "gn:country_code":"CN",
    "gn:dem":421,
    "gn:feature_class":"P",
    "gn:feature_code":"PPL",
    "gn:name":"Genzhugen",
    "gn:population":0,
    "gn:timezone":"Asia/Shanghai",
    "iso:country":"CN",
    "name:zho_x_preferred":[
        "\u6839\u7af9\u6839"
    ],
    "wof:name":"Genzhugen",
    "wof:placetype":"locality"
},
  "geometry": {"coordinates":[111.69459999999999,23.12529],"type":"Point"}
}