{
  "type": "Feature",
  "properties": {
    "gn:admin1_code":"7",
    "gn:asciiname":"Jinxianyan",
    "gn:country_code":"CN",
    "gn:dem":116,
    "gn:feature_class":"P",
    "gn:feature_code":"PPL",
    "gn:name":"Jinxianyan",
    "gn:population":0,
    "gn:timezone":"Asia/Shanghai",
    "iso:country":"CN",
    "name:zho_x_preferred":[
        "\u91d1\u4ed9\u5ca9"
    ],
    "wof:name":"Jinxianyan",
    "wof:placetype":"locality"
},
  "geometry": {"coordinates":[117.81771999999999,24.33903],"type":"Point"}
}