{
  "type": "Feature",
  "properties": {
    "gn:admin1_code":"18",
    "gn:asciiname":"Maogong",
    "gn:cc2":"CN",
    "gn:country_code":"CN",
    "gn:dem":810,
    "gn:feature_class":"P",
    "gn:feature_code":"PPL",
    "gn:name":"Maogong",
    "gn:population":0,
    "gn:timezone":"Asia/Shanghai",
    "iso:country":"CN",
    "name:und_x_variant":[
        "Mao-Kung",
        "Maogong"
    ],
    "wof:name":"Maogong",
    "wof:placetype":"locality"
},
  "geometry": {"coordinates":[108.86083000000001,26.14611],"type":"Point"}
}