{
  "type": "Feature",
  "properties": {
    "gn:admin1_code":"11.0",
    "gn:asciiname":"Shangyougongtang",
    "gn:country_code":"CN",
    "gn:dem":141,
    "gn:feature_class":"P",
    "gn:feature_code":"PPL",
    "gn:name":"Shangyougongtang",
    "gn:population":0,
    "gn:timezone":"Asia/Shanghai",
    "iso:country":"CN",
    "name:zho_x_preferred":[
        "\u4e0a\u6cb9\u516c\u5858"
    ],
    "wof:name":"Shangyougongtang",
    "wof:placetype":"locality"
},
  "geometry": {"coordinates":[112.78868,27.57598],"type":"Point"}
}