{
  "type": "Feature",
  "properties": {
    "gn:admin1_code":"8.0",
    "gn:asciiname":"Lixiantun",
    "gn:country_code":"CN",
    "gn:dem":137,
    "gn:feature_class":"P",
    "gn:feature_code":"PPL",
    "gn:name":"Lixiantun",
    "gn:population":0,
    "gn:timezone":"Asia/Shanghai",
    "iso:country":"CN",
    "name:zho_x_preferred":[
        "\u674e\u73b0\u5c6f"
    ],
    "wof:name":"Lixiantun",
    "wof:placetype":"locality"
},
  "geometry": {"coordinates":[126.70075,46.35155],"type":"Point"}
}