{
  "type": "Feature",
  "properties": {
    "gn:admin1_code":"7",
    "gn:asciiname":"Mashan",
    "gn:country_code":"CN",
    "gn:dem":18,
    "gn:feature_class":"P",
    "gn:feature_code":"PPL",
    "gn:name":"Mashan",
    "gn:population":0,
    "gn:timezone":"Asia/Shanghai",
    "iso:country":"CN",
    "name:ceb_x_preferred":[
        "Mashan"
    ],
    "name:deu_x_preferred":[
        "Mashan"
    ],
    "name:fra_x_preferred":[
        "Mashan"
    ],
    "name:nor_x_preferred":[
        "Mashan"
    ],
    "name:rus_x_preferred":[
        "\u041c\u0430\u0448\u0430\u043d\u044c"
    ],
    "name:swe_x_preferred":[
        "Mashan"
    ],
    "name:zho_x_preferred":[
        "\u9a6c\u5c71"
    ],
    "wof:name":"Mashan",
    "wof:placetype":"locality"
},
  "geometry": {"coordinates":[117.35849,23.89193],"type":"Point"}
}