{
  "type": "Feature",
  "properties": {
    "gn:admin1_code":"1.0",
    "gn:asciiname":"Jiangjicun",
    "gn:country_code":"CN",
    "gn:dem":17,
    "gn:feature_class":"P",
    "gn:feature_code":"PPL",
    "gn:name":"Jiangjicun",
    "gn:population":0,
    "gn:timezone":"Asia/Shanghai",
    "iso:country":"CN",
    "name:und_x_variant":[
        "Jiangjizi"
    ],
    "name:zho_x_preferred":[
        "\u848b\u96c6\u6751"
    ],
    "wof:name":"Jiangjicun",
    "wof:placetype":"locality"
},
  "geometry": {"coordinates":[117.71391,32.96536],"type":"Point"}
}