{
  "type": "Feature",
  "properties": {
    "gn:admin1_code":"26",
    "gn:asciiname":"Qiaojia",
    "gn:country_code":"CN",
    "gn:dem":386,
    "gn:feature_class":"P",
    "gn:feature_code":"PPL",
    "gn:name":"Qiaojia",
    "gn:population":0,
    "gn:timezone":"Asia/Shanghai",
    "iso:country":"CN",
    "name:und_x_variant":[
        "\u4e54\u5bb6"
    ],
    "wof:name":"Qiaojia",
    "wof:placetype":"locality"
},
  "geometry": {"coordinates":[109.07805999999999,34.5175],"type":"Point"}
}