{
  "type": "Feature",
  "properties": {
    "gn:admin1_code":"31",
    "gn:asciiname":"Jiangwei",
    "gn:country_code":"CN",
    "gn:dem":139,
    "gn:feature_class":"P",
    "gn:feature_code":"PPL",
    "gn:name":"Jiangwei",
    "gn:population":0,
    "gn:timezone":"Asia/Shanghai",
    "iso:country":"CN",
    "name:und_x_variant":[
        "\u6c5f\u56f4"
    ],
    "wof:name":"Jiangwei",
    "wof:placetype":"locality"
},
  "geometry": {"coordinates":[109.39153,19.44473],"type":"Point"}
}