{
  "type": "Feature",
  "properties": {
    "gn:admin1_code":"11.0",
    "gn:asciiname":"Datianxian",
    "gn:country_code":"CN",
    "gn:dem":1091,
    "gn:feature_class":"P",
    "gn:feature_code":"PPL",
    "gn:name":"Datianxian",
    "gn:population":0,
    "gn:timezone":"Asia/Shanghai",
    "iso:country":"CN",
    "name:zho_x_preferred":[
        "\u5927\u7530\u73b0"
    ],
    "wof:name":"Datianxian",
    "wof:placetype":"locality"
},
  "geometry": {"coordinates":[110.65461000000001,27.36077],"type":"Point"}
}