{
  "type": "Feature",
  "properties": {
    "gn:admin1_code":"19.0",
    "gn:asciiname":"Zuoshangou",
    "gn:country_code":"CN",
    "gn:dem":79,
    "gn:feature_class":"P",
    "gn:feature_code":"PPL",
    "gn:name":"Zuoshangou",
    "gn:population":0,
    "gn:timezone":"Asia/Shanghai",
    "iso:country":"CN",
    "name:zho_x_preferred":[
        "\u5ea7\u5c71\u6c9f"
    ],
    "wof:name":"Zuoshangou",
    "wof:placetype":"locality"
},
  "geometry": {"coordinates":[121.497,38.896],"type":"Point"}
}