{
  "type": "Feature",
  "properties": {
    "gn:admin1_code":"11",
    "gn:asciiname":"Guilingqiao",
    "gn:country_code":"CN",
    "gn:dem":89,
    "gn:feature_class":"P",
    "gn:feature_code":"PPL",
    "gn:name":"Guilingqiao",
    "gn:population":0,
    "gn:timezone":"Asia/Shanghai",
    "iso:country":"CN",
    "name:zho_x_preferred":[
        "\u9f9f\u7075\u6865"
    ],
    "wof:name":"Guilingqiao",
    "wof:placetype":"locality"
},
  "geometry": {"coordinates":[112.19295,27.57743],"type":"Point"}
}