{
  "type": "Feature",
  "properties": {
    "gn:admin1_code":"16",
    "gn:asciiname":"Shuibin",
    "gn:country_code":"CN",
    "gn:dem":385,
    "gn:feature_class":"P",
    "gn:feature_code":"PPL",
    "gn:name":"Shuibin",
    "gn:population":0,
    "gn:timezone":"Asia/Shanghai",
    "iso:country":"CN",
    "name:zho_x_preferred":[
        "\u6c34\u6ee8"
    ],
    "wof:name":"Shuibin",
    "wof:placetype":"locality"
},
  "geometry": {"coordinates":[111.06399999999999,25.228],"type":"Point"}
}