{
  "type": "Feature",
  "properties": {
    "gn:admin1_code":"18",
    "gn:asciiname":"Shaoyan",
    "gn:country_code":"CN",
    "gn:dem":532,
    "gn:feature_class":"P",
    "gn:feature_code":"PPL",
    "gn:name":"Shaoyan",
    "gn:population":0,
    "gn:timezone":"Asia/Shanghai",
    "iso:country":"CN",
    "name:zho_x_preferred":[
        "\u70e7\u5ca9"
    ],
    "wof:name":"Shaoyan",
    "wof:placetype":"locality"
},
  "geometry": {"coordinates":[108.24299999999999,28.8796],"type":"Point"}
}