{
  "type": "Feature",
  "properties": {
    "gn:admin1_code":"8.0",
    "gn:asciiname":"Ling'er",
    "gn:country_code":"CN",
    "gn:dem":285,
    "gn:feature_class":"P",
    "gn:feature_code":"PPL",
    "gn:name":"Ling\u2019er",
    "gn:population":0,
    "gn:timezone":"Asia/Shanghai",
    "iso:country":"CN",
    "name:und_x_variant":[
        "Ling\u2019er"
    ],
    "name:zho_x_preferred":[
        "\u96f6\u4e8c"
    ],
    "wof:name":"Ling'er",
    "wof:placetype":"locality"
},
  "geometry": {"coordinates":[127.21389000000001,45.40948],"type":"Point"}
}