{
  "type": "Feature",
  "properties": {
    "gn:admin1_code":"26.0",
    "gn:asciiname":"Liushuwancun",
    "gn:country_code":"CN",
    "gn:dem":1296,
    "gn:feature_class":"P",
    "gn:feature_code":"PPL",
    "gn:name":"Liushuwancun",
    "gn:population":0,
    "gn:timezone":"Asia/Shanghai",
    "iso:country":"CN",
    "name:zho_x_preferred":[
        "\u67f3\u6811\u6e7e\u6751"
    ],
    "wof:name":"Liushuwancun",
    "wof:placetype":"locality"
},
  "geometry": {"coordinates":[108.92177,37.71956],"type":"Point"}
}