{
  "type": "Feature",
  "properties": {
    "gn:admin1_code":"18.0",
    "gn:asciiname":"Niujiaochong",
    "gn:country_code":"CN",
    "gn:dem":742,
    "gn:feature_class":"P",
    "gn:feature_code":"PPL",
    "gn:name":"Niujiaochong",
    "gn:population":0,
    "gn:timezone":"Asia/Shanghai",
    "iso:country":"CN",
    "name:zho_x_preferred":[
        "\u725b\u89d2\u51b2"
    ],
    "wof:name":"Niujiaochong",
    "wof:placetype":"locality"
},
  "geometry": {"coordinates":[108.735,27.3844],"type":"Point"}
}