{
  "type": "Feature",
  "properties": {
    "gn:admin1_code":"1.0",
    "gn:asciiname":"Qianyancun",
    "gn:country_code":"CN",
    "gn:dem":26,
    "gn:feature_class":"P",
    "gn:feature_code":"PPL",
    "gn:name":"Qianyancun",
    "gn:population":0,
    "gn:timezone":"Asia/Shanghai",
    "iso:country":"CN",
    "name:zho_x_preferred":[
        "\u524d\u960e\u6751"
    ],
    "wof:name":"Qianyancun",
    "wof:placetype":"locality"
},
  "geometry": {"coordinates":[116.73641000000001,33.24778],"type":"Point"}
}