{
  "type": "Feature",
  "properties": {
    "gn:admin1_code":"01",
    "gn:asciiname":"Shendu",
    "gn:country_code":"CN",
    "gn:dem":115,
    "gn:feature_class":"P",
    "gn:feature_code":"PPLA4",
    "gn:name":"Shendu",
    "gn:population":0,
    "gn:timezone":"Asia/Shanghai",
    "iso:country":"CN",
    "name:und_x_variant":[
        "Shen-tu",
        "Shendu Zhen",
        "Shendu"
    ],
    "name:zho_x_preferred":[
        "\u6df1\u6e21"
    ],
    "name:zho_x_variant":[
        "\u6df1\u6e21\u9547"
    ],
    "wof:name":"Shendu",
    "wof:placetype":"locality"
},
  "geometry": {"coordinates":[118.61100999999999,29.86756],"type":"Point"}
}