{
  "type": "Feature",
  "properties": {
    "gn:admin1_code":"29.0",
    "gn:asciiname":"Habu",
    "gn:country_code":"CN",
    "gn:dem":1436,
    "gn:feature_class":"P",
    "gn:feature_code":"PPL",
    "gn:name":"Habu",
    "gn:population":0,
    "gn:timezone":"Asia/Shanghai",
    "iso:country":"CN",
    "name:fra_x_preferred":[
        "Habu"
    ],
    "name:jpn_x_preferred":[
        "\u30cf\u30d6"
    ],
    "name:por_x_preferred":[
        "Habu"
    ],
    "name:zho_x_preferred":[
        "\u54c8\u535c"
    ],
    "wof:name":"Habu",
    "wof:placetype":"locality"
},
  "geometry": {"coordinates":[102.416,23.1419],"type":"Point"}
}