{
  "type": "Feature",
  "properties": {
    "gn:admin1_code":"16.0",
    "gn:asciiname":"Xinyi",
    "gn:country_code":"CN",
    "gn:dem":319,
    "gn:feature_class":"P",
    "gn:feature_code":"PPL",
    "gn:name":"Xinyi",
    "gn:population":0,
    "gn:timezone":"Asia/Shanghai",
    "iso:country":"CN",
    "name:ceb_x_preferred":[
        "Xinyi"
    ],
    "name:deu_x_preferred":[
        "Xinyi"
    ],
    "name:fra_x_preferred":[
        "Xinyi"
    ],
    "name:jpn_x_preferred":[
        "\u30b7\u30f3\u30a4\u30fc"
    ],
    "name:kor_x_preferred":[
        "\uc2e0\uc774\uc2dc"
    ],
    "name:mlg_x_preferred":[
        "Xinyi"
    ],
    "name:nor_x_preferred":[
        "Xinyi"
    ],
    "name:rus_x_preferred":[
        "\u0421\u0438\u043d\u044c\u0438"
    ],
    "name:swe_x_preferred":[
        "Xinyi"
    ],
    "name:zho_x_preferred":[
        "\u65b0\u4f9d"
    ],
    "wof:name":"Xinyi",
    "wof:placetype":"locality"
},
  "geometry": {"coordinates":[107.90900000000001,23.863],"type":"Point"}
}