{
  "type": "Feature",
  "properties": {
    "gn:admin1_code":"31",
    "gn:asciiname":"Xinan Nongchang Nandadui",
    "gn:country_code":"CN",
    "gn:dem":137,
    "gn:feature_class":"P",
    "gn:feature_code":"PPLF",
    "gn:name":"Xinan Nongchang Nandadui",
    "gn:population":0,
    "gn:timezone":"Asia/Shanghai",
    "iso:country":"CN",
    "name:und_x_variant":[
        "Xidanan Dadui",
        "Xinan Nongchang Nandadui",
        "\u897f\u5357\u519c\u573a\u5357\u5927\u961f"
    ],
    "wof:name":"Xinan Nongchang Nandadui",
    "wof:placetype":"locality"
},
  "geometry": {"coordinates":[109.84584,19.47931],"type":"Point"}
}