{
  "type": "Feature",
  "properties": {
    "gn:admin1_code":"5.0",
    "gn:asciiname":"Shituncun",
    "gn:country_code":"CN",
    "gn:dem":174,
    "gn:feature_class":"P",
    "gn:feature_code":"PPL",
    "gn:name":"Shituncun",
    "gn:population":0,
    "gn:timezone":"Asia/Shanghai",
    "iso:country":"CN",
    "name:zho_x_preferred":[
        "\u77f3\u5c6f\u6751"
    ],
    "wof:name":"Shituncun",
    "wof:placetype":"locality"
},
  "geometry": {"coordinates":[126.43217,44.19645],"type":"Point"}
}