{
  "type": "Feature",
  "properties": {
    "gn:admin1_code":"20",
    "gn:asciiname":"Wu-lan-kung-tung-liang",
    "gn:country_code":"CN",
    "gn:dem":1440,
    "gn:feature_class":"P",
    "gn:feature_code":"PPL",
    "gn:name":"Wu-lan-kung-tung-liang",
    "gn:population":0,
    "gn:timezone":"Asia/Shanghai",
    "iso:country":"CN",
    "wof:name":"Wu-lan-kung-tung-liang",
    "wof:placetype":"locality"
},
  "geometry": {"coordinates":[117.31638999999998,42.72667],"type":"Point"}
}