{
  "type": "Feature",
  "properties": {
    "gn:admin1_code":"29.0",
    "gn:asciiname":"Guipi",
    "gn:country_code":"CN",
    "gn:dem":2396,
    "gn:feature_class":"P",
    "gn:feature_code":"PPL",
    "gn:name":"Guipi",
    "gn:population":0,
    "gn:timezone":"Asia/Shanghai",
    "iso:country":"CN",
    "name:zho_x_preferred":[
        "\u6842\u76ae"
    ],
    "wof:name":"Guipi",
    "wof:placetype":"locality"
},
  "geometry": {"coordinates":[100.06699999999999,25.9631],"type":"Point"}
}