{
  "type": "Feature",
  "properties": {
    "gn:admin1_code":"12.0",
    "gn:asciiname":"Yujiaba",
    "gn:country_code":"CN",
    "gn:dem":681,
    "gn:feature_class":"P",
    "gn:feature_code":"PPL",
    "gn:name":"Yujiaba",
    "gn:population":0,
    "gn:timezone":"Asia/Shanghai",
    "iso:country":"CN",
    "name:zho_x_preferred":[
        "Yujiaba"
    ],
    "name:zho_x_variant":[
        "\u7f37\u7532\u575d"
    ],
    "wof:name":"Yujiaba",
    "wof:placetype":"locality"
},
  "geometry": {"coordinates":[109.49575,29.96049],"type":"Point"}
}