{
  "type": "Feature",
  "properties": {
    "gn:admin1_code":"32.0",
    "gn:asciiname":"Wafangwan",
    "gn:country_code":"CN",
    "gn:dem":880,
    "gn:feature_class":"P",
    "gn:feature_code":"PPL",
    "gn:name":"Wafangwan",
    "gn:population":0,
    "gn:timezone":"Asia/Shanghai",
    "iso:country":"CN",
    "name:zho_x_preferred":[
        "\u74e6\u623f\u6e7e"
    ],
    "wof:name":"Wafangwan",
    "wof:placetype":"locality"
},
  "geometry": {"coordinates":[105.52200000000001,32.6103],"type":"Point"}
}