{
  "type": "Feature",
  "properties": {
    "gn:admin1_code":"25",
    "gn:asciiname":"Dongbao",
    "gn:country_code":"CN",
    "gn:dem":179,
    "gn:feature_class":"P",
    "gn:feature_code":"PPL",
    "gn:name":"Dongbao",
    "gn:population":0,
    "gn:timezone":"Asia/Shanghai",
    "iso:country":"CN",
    "name:zho_x_preferred":[
        "\u4e1c\u9c8d"
    ],
    "wof:name":"Dongbao",
    "wof:placetype":"locality"
},
  "geometry": {"coordinates":[116.84399999999999,36.1308],"type":"Point"}
}