{
  "type": "Feature",
  "properties": {
    "gn:admin1_code":"32.0",
    "gn:asciiname":"Karengong",
    "gn:country_code":"CN",
    "gn:dem":3692,
    "gn:feature_class":"P",
    "gn:feature_code":"PPL",
    "gn:name":"Karengong",
    "gn:population":0,
    "gn:timezone":"Asia/Shanghai",
    "iso:country":"CN",
    "name:zho_x_preferred":[
        "\u5361\u4ec1\u8d21"
    ],
    "wof:name":"Karengong",
    "wof:placetype":"locality"
},
  "geometry": {"coordinates":[99.19859,32.28089],"type":"Point"}
}