{
  "type": "Feature",
  "properties": {
    "gn:admin1_code":"12.0",
    "gn:asciiname":"Gongjia",
    "gn:country_code":"CN",
    "gn:dem":26,
    "gn:feature_class":"P",
    "gn:feature_code":"PPL",
    "gn:name":"Gongjia",
    "gn:population":0,
    "gn:timezone":"Asia/Shanghai",
    "iso:country":"CN",
    "name:zho_x_preferred":[
        "\u9f9a\u5bb6"
    ],
    "wof:name":"Gongjia",
    "wof:placetype":"locality"
},
  "geometry": {"coordinates":[114.5385,30.64552],"type":"Point"}
}