{
  "type": "Feature",
  "properties": {
    "gn:admin1_code":"5.0",
    "gn:asciiname":"Houpansa Weizi",
    "gn:country_code":"CN",
    "gn:dem":182,
    "gn:feature_class":"P",
    "gn:feature_code":"PPL",
    "gn:name":"Houpansa Weizi",
    "gn:population":0,
    "gn:timezone":"Asia/Shanghai",
    "iso:country":"CN",
    "name:zho_x_preferred":[
        "\u540e\u80d6\u8428\u56f4\u5b50"
    ],
    "wof:name":"Houpansa Weizi",
    "wof:placetype":"locality"
},
  "geometry": {"coordinates":[124.52782999999999,44.68016],"type":"Point"}
}