{
  "type": "Feature",
  "properties": {
    "gn:admin1_code":"19.0",
    "gn:asciiname":"Loushang",
    "gn:country_code":"CN",
    "gn:dem":117,
    "gn:feature_class":"P",
    "gn:feature_code":"PPL",
    "gn:name":"Loushang",
    "gn:population":0,
    "gn:timezone":"Asia/Shanghai",
    "iso:country":"CN",
    "name:und_x_variant":[
        "\u697c\u4e0a"
    ],
    "wof:name":"Loushang",
    "wof:placetype":"locality"
},
  "geometry": {"coordinates":[122.49596,40.08571],"type":"Point"}
}