{
  "type": "Feature",
  "properties": {
    "gn:admin1_code":"29.0",
    "gn:asciiname":"Shijiaolin",
    "gn:country_code":"CN",
    "gn:dem":1142,
    "gn:feature_class":"P",
    "gn:feature_code":"PPL",
    "gn:name":"Shijiaolin",
    "gn:population":0,
    "gn:timezone":"Asia/Shanghai",
    "iso:country":"CN",
    "name:zho_x_preferred":[
        "\u77f3\u89d2\u5549"
    ],
    "wof:name":"Shijiaolin",
    "wof:placetype":"locality"
},
  "geometry": {"coordinates":[103.929,28.1425],"type":"Point"}
}