{
  "type": "Feature",
  "properties": {
    "gn:admin1_code":"9.0",
    "gn:asciiname":"Zhengjiazhuang",
    "gn:country_code":"CN",
    "gn:dem":69,
    "gn:feature_class":"P",
    "gn:feature_code":"PPL",
    "gn:name":"Zhengjiazhuang",
    "gn:population":0,
    "gn:timezone":"Asia/Shanghai",
    "iso:country":"CN",
    "name:zho_x_preferred":[
        "\u90d1\u5bb6\u5e84"
    ],
    "wof:name":"Zhengjiazhuang",
    "wof:placetype":"locality"
},
  "geometry": {"coordinates":[114.51134999999999,35.48003],"type":"Point"}
}