{
  "type": "Feature",
  "properties": {
    "gn:admin1_code":"8.0",
    "gn:asciiname":"Xianghuacun",
    "gn:country_code":"CN",
    "gn:dem":114,
    "gn:feature_class":"P",
    "gn:feature_code":"PPL",
    "gn:name":"Xianghuacun",
    "gn:population":0,
    "gn:timezone":"Asia/Shanghai",
    "iso:country":"CN",
    "name:zho_x_preferred":[
        "\u5411\u5316\u6751"
    ],
    "wof:name":"Xianghuacun",
    "wof:placetype":"locality"
},
  "geometry": {"coordinates":[132.01363999999998,45.52379000000001],"type":"Point"}
}