{
  "type": "Feature",
  "properties": {
    "gn:admin1_code":"32.0",
    "gn:asciiname":"Shahe",
    "gn:country_code":"CN",
    "gn:dem":422,
    "gn:feature_class":"P",
    "gn:feature_code":"PPL",
    "gn:name":"Shahe",
    "gn:population":0,
    "gn:timezone":"Asia/Shanghai",
    "iso:country":"CN",
    "name:ceb_x_preferred":[
        "Shahe"
    ],
    "name:deu_x_preferred":[
        "Shahe"
    ],
    "name:rus_x_preferred":[
        "\u0428\u0430\u0445\u044d"
    ],
    "name:swe_x_preferred":[
        "Shahe"
    ],
    "name:zho_x_preferred":[
        "\u6c99\u6cb3"
    ],
    "wof:name":"Shahe",
    "wof:placetype":"locality"
},
  "geometry": {"coordinates":[104.724,30.5316],"type":"Point"}
}