{
  "type": "Feature",
  "properties": {
    "gn:admin1_code":"16.0",
    "gn:asciiname":"Niuchangpo",
    "gn:country_code":"CN",
    "gn:dem":1390,
    "gn:feature_class":"P",
    "gn:feature_code":"PPL",
    "gn:name":"Niuchangpo",
    "gn:population":0,
    "gn:timezone":"Asia/Shanghai",
    "iso:country":"CN",
    "name:zho_x_preferred":[
        "\u725b\u573a\u5761"
    ],
    "wof:name":"Niuchangpo",
    "wof:placetype":"locality"
},
  "geometry": {"coordinates":[106.31999999999999,24.5345],"type":"Point"}
}