{
  "type": "Feature",
  "properties": {
    "gn:admin1_code":"11.0",
    "gn:asciiname":"Huanggualing",
    "gn:country_code":"CN",
    "gn:dem":275,
    "gn:feature_class":"P",
    "gn:feature_code":"PPL",
    "gn:name":"Huanggualing",
    "gn:population":0,
    "gn:timezone":"Asia/Shanghai",
    "iso:country":"CN",
    "name:zho_x_preferred":[
        "\u9ec4\u74dc\u5cad"
    ],
    "wof:name":"Huanggualing",
    "wof:placetype":"locality"
},
  "geometry": {"coordinates":[110.94651,27.08343],"type":"Point"}
}