{
  "type": "Feature",
  "properties": {
    "gn:admin1_code":"21.0",
    "gn:asciiname":"Niuwangmiao",
    "gn:country_code":"CN",
    "gn:dem":1135,
    "gn:feature_class":"P",
    "gn:feature_code":"PPL",
    "gn:name":"Niuwangmiao",
    "gn:population":0,
    "gn:timezone":"Asia/Shanghai",
    "iso:country":"CN",
    "name:zho_x_preferred":[
        "\u725b\u738b\u5e99"
    ],
    "wof:name":"Niuwangmiao",
    "wof:placetype":"locality"
},
  "geometry": {"coordinates":[105.982,38.0587],"type":"Point"}
}