{
  "type": "Feature",
  "properties": {
    "gn:admin1_code":"15.0",
    "gn:asciiname":"Tianluochenggang",
    "gn:country_code":"CN",
    "gn:dem":1356,
    "gn:feature_class":"P",
    "gn:feature_code":"PPL",
    "gn:name":"Tianluochenggang",
    "gn:population":0,
    "gn:timezone":"Asia/Shanghai",
    "iso:country":"CN",
    "name:zho_x_preferred":[
        "\u5929\u7f57\u57ce\u5c97"
    ],
    "wof:name":"Tianluochenggang",
    "wof:placetype":"locality"
},
  "geometry": {"coordinates":[98.5813,39.9726],"type":"Point"}
}