{
  "type": "Feature",
  "properties": {
    "gn:admin1_code":"30",
    "gn:asciiname":"Pingdingqiao",
    "gn:country_code":"CN",
    "gn:dem":6,
    "gn:feature_class":"P",
    "gn:feature_code":"PPL",
    "gn:name":"Pingdingqiao",
    "gn:population":0,
    "gn:timezone":"Asia/Shanghai",
    "iso:country":"CN",
    "name:zho_x_preferred":[
        "\u5e73\u5b9a\u6865"
    ],
    "wof:name":"Pingdingqiao",
    "wof:placetype":"locality"
},
  "geometry": {"coordinates":[116.21485,23.50953],"type":"Point"}
}