{
  "type": "Feature",
  "properties": {
    "gn:admin1_code":"7",
    "gn:asciiname":"Tianzhi",
    "gn:country_code":"CN",
    "gn:dem":29,
    "gn:feature_class":"P",
    "gn:feature_code":"PPL",
    "gn:name":"Tianzhi",
    "gn:population":0,
    "gn:timezone":"Asia/Shanghai",
    "iso:country":"CN",
    "name:zho_x_preferred":[
        "\u7530\u82b7"
    ],
    "wof:name":"Tianzhi",
    "wof:placetype":"locality"
},
  "geometry": {"coordinates":[118.44083000000001,24.88111],"type":"Point"}
}