{
  "type": "Feature",
  "properties": {
    "gn:admin1_code":"19.0",
    "gn:asciiname":"Tizishan",
    "gn:country_code":"CN",
    "gn:dem":160,
    "gn:feature_class":"P",
    "gn:feature_code":"PPL",
    "gn:name":"Tizishan",
    "gn:population":0,
    "gn:timezone":"Asia/Shanghai",
    "iso:country":"CN",
    "name:und_x_variant":[
        "\u68af\u5b50\u5c71"
    ],
    "name:zho_x_preferred":[
        "\u68af\u5b50\u5c71"
    ],
    "wof:name":"Tizishan",
    "wof:placetype":"locality"
},
  "geometry": {"coordinates":[123.59747,40.52395],"type":"Point"}
}