{
  "type": "Feature",
  "properties": {
    "gn:admin1_code":"24.0",
    "gn:asciiname":"Xihoucun",
    "gn:country_code":"CN",
    "gn:dem":592,
    "gn:feature_class":"P",
    "gn:feature_code":"PPL",
    "gn:name":"Xihoucun",
    "gn:population":0,
    "gn:timezone":"Asia/Shanghai",
    "iso:country":"CN",
    "name:zho_x_preferred":[
        "\u897f\u4faf\u6751"
    ],
    "wof:name":"Xihoucun",
    "wof:placetype":"locality"
},
  "geometry": {"coordinates":[110.97369,34.79506],"type":"Point"}
}