{
  "type": "Feature",
  "properties": {
    "gn:admin1_code":"26.0",
    "gn:asciiname":"Zhangjiashan",
    "gn:cc2":"CN",
    "gn:country_code":"CN",
    "gn:dem":944,
    "gn:feature_class":"P",
    "gn:feature_code":"PPL",
    "gn:name":"Zhangjiashan",
    "gn:population":0,
    "gn:timezone":"Asia/Shanghai",
    "iso:country":"CN",
    "name:und_x_variant":[
        "Chang-chia-shan",
        "Zhangjiashan"
    ],
    "wof:name":"Zhangjiashan",
    "wof:placetype":"locality"
},
  "geometry": {"coordinates":[110.59999999999999,37.68333],"type":"Point"}
}