{
  "type": "Feature",
  "properties": {
    "gn:admin1_code":"15.0",
    "gn:asciiname":"Huangdunzi Nongchang",
    "gn:country_code":"CN",
    "gn:dem":1067,
    "gn:feature_class":"P",
    "gn:feature_code":"PPLF",
    "gn:name":"Huangdunzi Nongchang",
    "gn:population":0,
    "gn:timezone":"Asia/Urumqi",
    "iso:country":"CN",
    "name:zho_x_preferred":[
        "\u9ec4\u58a9\u5b50\u519c\u573a"
    ],
    "wof:name":"Huangdunzi Nongchang",
    "wof:placetype":"locality"
},
  "geometry": {"coordinates":[94.69757,40.37339],"type":"Point"}
}