{
  "type": "Feature",
  "properties": {
    "gn:admin1_code":"01",
    "gn:asciiname":"Chenzhaicun",
    "gn:country_code":"CN",
    "gn:dem":44,
    "gn:feature_class":"P",
    "gn:feature_code":"PPL",
    "gn:name":"Chenzhaicun",
    "gn:population":0,
    "gn:timezone":"Asia/Shanghai",
    "iso:country":"CN",
    "name:und_x_variant":[
        "Ch\u2019en-chai",
        "Ch\u2019en-chia",
        "Chenzhai",
        "Chenzhaicun"
    ],
    "name:zho_x_preferred":[
        "\u9648\u5be8\u6751"
    ],
    "wof:name":"Chenzhaicun",
    "wof:placetype":"locality"
},
  "geometry": {"coordinates":[116.4469,34.33691],"type":"Point"}
}