{
  "type": "Feature",
  "properties": {
    "gn:admin1_code":"14",
    "gn:asciiname":"Tazhong",
    "gn:country_code":"CN",
    "gn:dem":4245,
    "gn:feature_class":"P",
    "gn:feature_code":"PPL",
    "gn:name":"Tazhong",
    "gn:population":0,
    "gn:timezone":"Asia/Urumqi",
    "iso:country":"CN",
    "name:zho_x_preferred":[
        "\u5854\u4e2d"
    ],
    "wof:name":"Tazhong",
    "wof:placetype":"locality"
},
  "geometry": {"coordinates":[89.27249999999999,29.6726],"type":"Point"}
}