{
  "type": "Feature",
  "properties": {
    "gn:admin1_code":"14.0",
    "gn:asciiname":"Mangdaka",
    "gn:country_code":"CN",
    "gn:dem":3876,
    "gn:feature_class":"P",
    "gn:feature_code":"PPL",
    "gn:name":"Mangdaka",
    "gn:population":0,
    "gn:timezone":"Asia/Urumqi",
    "iso:country":"CN",
    "name:zho_x_preferred":[
        "\u8292\u5927\u5361"
    ],
    "wof:name":"Mangdaka",
    "wof:placetype":"locality"
},
  "geometry": {"coordinates":[95.05575,31.63778],"type":"Point"}
}