{
  "type": "Feature",
  "properties": {
    "gn:admin1_code":"26.0",
    "gn:asciiname":"Hualiji",
    "gn:country_code":"CN",
    "gn:dem":1198,
    "gn:feature_class":"P",
    "gn:feature_code":"PPL",
    "gn:name":"Hualiji",
    "gn:population":0,
    "gn:timezone":"Asia/Shanghai",
    "iso:country":"CN",
    "name:zho_x_preferred":[
        "\u82b1\u6817\u673a"
    ],
    "wof:name":"Hualiji",
    "wof:placetype":"locality"
},
  "geometry": {"coordinates":[109.02593,32.15769],"type":"Point"}
}