{
  "type": "Feature",
  "properties": {
    "gn:admin1_code":"32.0",
    "gn:asciiname":"Dayin",
    "gn:country_code":"CN",
    "gn:dem":468,
    "gn:feature_class":"P",
    "gn:feature_code":"PPL",
    "gn:name":"Dayin",
    "gn:population":0,
    "gn:timezone":"Asia/Shanghai",
    "iso:country":"CN",
    "name:zho_x_preferred":[
        "\u5927\u5bc5"
    ],
    "wof:name":"Dayin",
    "wof:placetype":"locality"
},
  "geometry": {"coordinates":[106.63924,31.35799],"type":"Point"}
}