{
  "type": "Feature",
  "properties": {
    "gn:admin1_code":"26.0",
    "gn:asciiname":"Renjiahoucun",
    "gn:country_code":"CN",
    "gn:dem":798,
    "gn:feature_class":"P",
    "gn:feature_code":"PPL",
    "gn:name":"Renjiahoucun",
    "gn:population":0,
    "gn:timezone":"Asia/Shanghai",
    "iso:country":"CN",
    "name:zho_x_preferred":[
        "\u4efb\u5bb6\u540e\u6751"
    ],
    "wof:name":"Renjiahoucun",
    "wof:placetype":"locality"
},
  "geometry": {"coordinates":[109.84218,33.88093],"type":"Point"}
}