{
  "type": "Feature",
  "properties": {
    "gn:admin1_code":"2.0",
    "gn:asciiname":"Junxi",
    "gn:country_code":"CN",
    "gn:dem":79,
    "gn:feature_class":"P",
    "gn:feature_code":"PPL",
    "gn:name":"Junxi",
    "gn:population":0,
    "gn:timezone":"Asia/Shanghai",
    "iso:country":"CN",
    "name:zho_x_preferred":[
        "\u5747\u6eaa"
    ],
    "wof:name":"Junxi",
    "wof:placetype":"locality"
},
  "geometry": {"coordinates":[119.69645,28.27526],"type":"Point"}
}