{
  "type": "Feature",
  "properties": {
    "gn:admin1_code":"32.0",
    "gn:asciiname":"Shuikoumiao",
    "gn:country_code":"CN",
    "gn:dem":530,
    "gn:feature_class":"P",
    "gn:feature_code":"PPL",
    "gn:name":"Shuikoumiao",
    "gn:population":0,
    "gn:timezone":"Asia/Shanghai",
    "iso:country":"CN",
    "name:zho_x_preferred":[
        "\u6c34\u53e3\u5e99"
    ],
    "wof:name":"Shuikoumiao",
    "wof:placetype":"locality"
},
  "geometry": {"coordinates":[107.40300000000001,30.6294],"type":"Point"}
}