{
  "type": "Feature",
  "properties": {
    "gn:admin1_code":"9.0",
    "gn:asciiname":"Zhangjiazhuang",
    "gn:country_code":"CN",
    "gn:dem":63,
    "gn:feature_class":"P",
    "gn:feature_code":"PPL",
    "gn:name":"Zhangjiazhuang",
    "gn:population":0,
    "gn:timezone":"Asia/Shanghai",
    "iso:country":"CN",
    "name:zho_x_preferred":[
        "\u5f20\u5bb6\u5e84"
    ],
    "name:zho_x_variant":[
        "\u5f20\u5bb6\u5e84\u9547"
    ],
    "wof:name":"Zhangjiazhuang",
    "wof:placetype":"locality"
},
  "geometry": {"coordinates":[114.47431,36.05851],"type":"Point"}
}