{
  "type": "Feature",
  "properties": {
    "gn:admin1_code":"18",
    "gn:asciiname":"Guozhongdi",
    "gn:country_code":"CN",
    "gn:dem":1290,
    "gn:feature_class":"P",
    "gn:feature_code":"PPL",
    "gn:name":"Guozhongdi",
    "gn:population":0,
    "gn:timezone":"Asia/Shanghai",
    "iso:country":"CN",
    "name:zho_x_preferred":[
        "\u9505\u4ef2\u5e95"
    ],
    "wof:name":"Guozhongdi",
    "wof:placetype":"locality"
},
  "geometry": {"coordinates":[106.164,26.9057],"type":"Point"}
}