{
  "type": "Feature",
  "properties": {
    "gn:admin1_code":"5.0",
    "gn:asciiname":"Gaijiajie",
    "gn:country_code":"CN",
    "gn:dem":348,
    "gn:feature_class":"P",
    "gn:feature_code":"PPL",
    "gn:name":"Gaijiajie",
    "gn:population":0,
    "gn:timezone":"Asia/Shanghai",
    "iso:country":"CN",
    "name:zho_x_preferred":[
        "\u76d6\u5bb6\u8857"
    ],
    "wof:name":"Gaijiajie",
    "wof:placetype":"locality"
},
  "geometry": {"coordinates":[126.18683,42.59541],"type":"Point"}
}