{
  "type": "Feature",
  "properties": {
    "gn:admin1_code":"24.0",
    "gn:asciiname":"Lingjiaodi",
    "gn:country_code":"CN",
    "gn:dem":2097,
    "gn:feature_class":"P",
    "gn:feature_code":"PPL",
    "gn:name":"Lingjiaodi",
    "gn:population":0,
    "gn:timezone":"Asia/Shanghai",
    "iso:country":"CN",
    "name:zho_x_preferred":[
        "\u5cad\u811a\u5e95"
    ],
    "wof:name":"Lingjiaodi",
    "wof:placetype":"locality"
},
  "geometry": {"coordinates":[112.12999000000001,38.9829],"type":"Point"}
}