{
  "type": "Feature",
  "properties": {
    "gn:admin1_code":"30.0",
    "gn:asciiname":"Qiaonancun",
    "gn:country_code":"CN",
    "gn:dem":7,
    "gn:feature_class":"P",
    "gn:feature_code":"PPL",
    "gn:name":"Qiaonancun",
    "gn:population":0,
    "gn:timezone":"Asia/Shanghai",
    "iso:country":"CN",
    "name:zho_x_preferred":[
        "\u4e54\u5357\u6751"
    ],
    "wof:name":"Qiaonancun",
    "wof:placetype":"locality"
},
  "geometry": {"coordinates":[116.32759,23.55866],"type":"Point"}
}