{
  "type": "Feature",
  "properties": {
    "gn:admin1_code":"03",
    "gn:asciiname":"Shichajie",
    "gn:country_code":"CN",
    "gn:dem":26,
    "gn:feature_class":"P",
    "gn:feature_code":"PPL",
    "gn:name":"Shichajie",
    "gn:population":0,
    "gn:timezone":"Asia/Shanghai",
    "iso:country":"CN",
    "name:und_x_variant":[
        "Shihchakai",
        "Shichaku",
        "Shih-ch\u2019a",
        "Shih-ch\u2019a-chieh",
        "Shichajie",
        "\u5e02\u6c4a\u8857"
    ],
    "wof:name":"Shichajie",
    "wof:placetype":"locality"
},
  "geometry": {"coordinates":[115.82902,28.40127],"type":"Point"}
}