{
  "type": "Feature",
  "properties": {
    "gn:admin1_code":"18",
    "gn:asciiname":"Yunshang",
    "gn:country_code":"CN",
    "gn:dem":717,
    "gn:feature_class":"P",
    "gn:feature_code":"PPL",
    "gn:name":"Yunshang",
    "gn:population":0,
    "gn:timezone":"Asia/Shanghai",
    "iso:country":"CN",
    "name:zho_x_preferred":[
        "\u4e91\u4e0a"
    ],
    "wof:name":"Yunshang",
    "wof:placetype":"locality"
},
  "geometry": {"coordinates":[105.96599999999999,24.9738],"type":"Point"}
}