{
  "type": "Feature",
  "properties": {
    "gn:admin1_code":"12",
    "gn:asciiname":"Xiaxiangkou",
    "gn:cc2":"CN",
    "gn:country_code":"CN",
    "gn:dem":550,
    "gn:feature_class":"P",
    "gn:feature_code":"PPL",
    "gn:name":"Xiaxiangkou",
    "gn:population":0,
    "gn:timezone":"Asia/Shanghai",
    "iso:country":"CN",
    "name:und_x_variant":[
        "Hsiang-kou-chen",
        "Xiangkou",
        "Xiaxiangkou"
    ],
    "wof:name":"Xiaxiangkou",
    "wof:placetype":"locality"
},
  "geometry": {"coordinates":[110.26833000000001,33.09167],"type":"Point"}
}