{
  "type": "Feature",
  "properties": {
    "gn:admin1_code":"32.0",
    "gn:asciiname":"Dengcaoping",
    "gn:country_code":"CN",
    "gn:dem":2453,
    "gn:feature_class":"P",
    "gn:feature_code":"PPL",
    "gn:name":"Dengcaoping",
    "gn:population":0,
    "gn:timezone":"Asia/Shanghai",
    "iso:country":"CN",
    "name:zho_x_preferred":[
        "\u706f\u8349\u576a"
    ],
    "wof:name":"Dengcaoping",
    "wof:placetype":"locality"
},
  "geometry": {"coordinates":[102.01935,27.05295],"type":"Point"}
}