{
  "type": "Feature",
  "properties": {
    "gn:admin1_code":"6.0",
    "gn:asciiname":"Langqiongda",
    "gn:country_code":"CN",
    "gn:dem":3986,
    "gn:feature_class":"P",
    "gn:feature_code":"PPL",
    "gn:name":"Langqiongda",
    "gn:population":0,
    "gn:timezone":"Asia/Urumqi",
    "iso:country":"CN",
    "name:zho_x_preferred":[
        "\u6d6a\u7a77\u6253"
    ],
    "wof:name":"Langqiongda",
    "wof:placetype":"locality"
},
  "geometry": {"coordinates":[96.42292999999999,32.73858],"type":"Point"}
}