{
  "type": "Feature",
  "properties": {
    "gn:admin1_code":"32.0",
    "gn:asciiname":"Huangjiayan",
    "gn:country_code":"CN",
    "gn:dem":1022,
    "gn:feature_class":"P",
    "gn:feature_code":"PPL",
    "gn:name":"Huangjiayan",
    "gn:population":0,
    "gn:timezone":"Asia/Shanghai",
    "iso:country":"CN",
    "name:zho_x_preferred":[
        "\u9ec4\u5bb6\u5830"
    ],
    "wof:name":"Huangjiayan",
    "wof:placetype":"locality"
},
  "geometry": {"coordinates":[105.97093,32.70529000000001],"type":"Point"}
}