{
  "type": "Feature",
  "properties": {
    "gn:admin1_code":"30",
    "gn:asciiname":"Nanyangzai",
    "gn:country_code":"CN",
    "gn:dem":55,
    "gn:feature_class":"P",
    "gn:feature_code":"PPL",
    "gn:name":"Nanyangzai",
    "gn:population":0,
    "gn:timezone":"Asia/Shanghai",
    "iso:country":"CN",
    "name:zho_x_preferred":[
        "\u5357\u6768\u4ed4"
    ],
    "wof:name":"Nanyangzai",
    "wof:placetype":"locality"
},
  "geometry": {"coordinates":[115.9597,23.11147],"type":"Point"}
}