{
  "type": "Feature",
  "properties": {
    "gn:admin1_code":"10.0",
    "gn:asciiname":"Zijingguan",
    "gn:cc2":"CN",
    "gn:country_code":"CN",
    "gn:dem":556,
    "gn:feature_class":"P",
    "gn:feature_code":"PPL",
    "gn:name":"Zijingguan",
    "gn:population":0,
    "gn:timezone":"Asia/Shanghai",
    "iso:country":"CN",
    "name:und_x_variant":[
        "Tzu-ching-kuan",
        "Zijingguan"
    ],
    "wof:name":"Zijingguan",
    "wof:placetype":"locality"
},
  "geometry": {"coordinates":[115.16388999999999,39.42],"type":"Point"}
}