{
  "type": "Feature",
  "properties": {
    "gn:admin1_code":"29.0",
    "gn:asciiname":"Mali Pingzi",
    "gn:country_code":"CN",
    "gn:dem":2426,
    "gn:feature_class":"P",
    "gn:feature_code":"PPL",
    "gn:name":"Mali Pingzi",
    "gn:population":0,
    "gn:timezone":"Asia/Shanghai",
    "iso:country":"CN",
    "name:zho_x_preferred":[
        "\u9ebb\u68a8\u576a\u5b50"
    ],
    "wof:name":"Mali Pingzi",
    "wof:placetype":"locality"
},
  "geometry": {"coordinates":[103.627,27.6175],"type":"Point"}
}