{
  "type": "Feature",
  "properties": {
    "gn:admin1_code":"9",
    "gn:asciiname":"Laoguawo",
    "gn:country_code":"CN",
    "gn:dem":47,
    "gn:feature_class":"P",
    "gn:feature_code":"PPL",
    "gn:name":"Laoguawo",
    "gn:population":0,
    "gn:timezone":"Asia/Shanghai",
    "iso:country":"CN",
    "name:zho_x_preferred":[
        "\u8001\u9e39\u7a9d"
    ],
    "wof:name":"Laoguawo",
    "wof:placetype":"locality"
},
  "geometry": {"coordinates":[116.066,34.3838],"type":"Point"}
}