{
  "type": "Feature",
  "properties": {
    "gn:admin1_code":"12",
    "gn:asciiname":"Mopanzhou",
    "gn:cc2":"CN",
    "gn:country_code":"CN",
    "gn:dem":39,
    "gn:feature_class":"P",
    "gn:feature_code":"PPL",
    "gn:name":"Mopanzhou",
    "gn:population":0,
    "gn:timezone":"Asia/Shanghai",
    "iso:country":"CN",
    "name:und_x_variant":[
        "Ma-p\u2019an-chou",
        "Sung-tzu",
        "Mo-p\u2019an-chou",
        "Mopanzhou"
    ],
    "wof:name":"Mopanzhou",
    "wof:placetype":"locality"
},
  "geometry": {"coordinates":[111.78417,30.11889],"type":"Point"}
}