{
  "type": "Feature",
  "properties": {
    "gn:admin1_code":"3.0",
    "gn:asciiname":"Xiaruiyuan",
    "gn:country_code":"CN",
    "gn:dem":197,
    "gn:feature_class":"P",
    "gn:feature_code":"PPL",
    "gn:name":"Xiaruiyuan",
    "gn:population":0,
    "gn:timezone":"Asia/Shanghai",
    "iso:country":"CN",
    "name:zho_x_preferred":[
        "\u4e0b\u745e\u6e90"
    ],
    "wof:name":"Xiaruiyuan",
    "wof:placetype":"locality"
},
  "geometry": {"coordinates":[114.101,27.6481],"type":"Point"}
}