{
  "type": "Feature",
  "properties": {
    "gn:admin1_code":"11.0",
    "gn:asciiname":"Kabihu",
    "gn:country_code":"CN",
    "gn:dem":695,
    "gn:feature_class":"P",
    "gn:feature_code":"PPL",
    "gn:name":"Kabihu",
    "gn:population":0,
    "gn:timezone":"Asia/Shanghai",
    "iso:country":"CN",
    "name:zho_x_preferred":[
        "Kabihu"
    ],
    "name:zho_x_variant":[
        "\u5361\u58c1\u6e56"
    ],
    "wof:name":"Kabihu",
    "wof:placetype":"locality"
},
  "geometry": {"coordinates":[109.90152,29.00374],"type":"Point"}
}