{
  "type": "Feature",
  "properties": {
    "gn:admin1_code":"15.0",
    "gn:asciiname":"Dawanshan",
    "gn:country_code":"CN",
    "gn:dem":1616,
    "gn:feature_class":"P",
    "gn:feature_code":"PPL",
    "gn:name":"Dawanshan",
    "gn:population":0,
    "gn:timezone":"Asia/Shanghai",
    "iso:country":"CN",
    "name:zho_x_preferred":[
        "\u5927\u6e7e\u5c71"
    ],
    "wof:name":"Dawanshan",
    "wof:placetype":"locality"
},
  "geometry": {"coordinates":[105.253,32.8326],"type":"Point"}
}