{
  "type": "Feature",
  "properties": {
    "gn:admin1_code":"25",
    "gn:asciiname":"Liezhuang",
    "gn:country_code":"CN",
    "gn:dem":52,
    "gn:feature_class":"P",
    "gn:feature_code":"PPL",
    "gn:name":"Liezhuang",
    "gn:population":0,
    "gn:timezone":"Asia/Shanghai",
    "iso:country":"CN",
    "name:zho_x_preferred":[
        "\u88c2\u5e84"
    ],
    "wof:name":"Liezhuang",
    "wof:placetype":"locality"
},
  "geometry": {"coordinates":[118.485,34.7256],"type":"Point"}
}