{
  "type": "Feature",
  "properties": {
    "gn:admin1_code":"4.0",
    "gn:asciiname":"Xingdongcun",
    "gn:country_code":"CN",
    "gn:dem":5,
    "gn:feature_class":"P",
    "gn:feature_code":"PPL",
    "gn:name":"Xingdongcun",
    "gn:population":0,
    "gn:timezone":"Asia/Shanghai",
    "iso:country":"CN",
    "name:zho_x_preferred":[
        "\u5174\u4e1c\u6751"
    ],
    "wof:name":"Xingdongcun",
    "wof:placetype":"locality"
},
  "geometry": {"coordinates":[118.84412,34.42290999999999],"type":"Point"}
}