{
  "type": "Feature",
  "properties": {
    "gn:admin1_code":"25.0",
    "gn:asciiname":"Dongxiakou",
    "gn:country_code":"CN",
    "gn:dem":13,
    "gn:feature_class":"P",
    "gn:feature_code":"PPL",
    "gn:name":"Dongxiakou",
    "gn:population":0,
    "gn:timezone":"Asia/Shanghai",
    "iso:country":"CN",
    "name:zho_x_preferred":[
        "\u4e1c\u971e\u53e3"
    ],
    "wof:name":"Dongxiakou",
    "wof:placetype":"locality"
},
  "geometry": {"coordinates":[122.62936000000001,37.40585],"type":"Point"}
}