{
  "type": "Feature",
  "properties": {
    "gn:admin1_code":"24.0",
    "gn:asciiname":"Xihouzikou",
    "gn:country_code":"CN",
    "gn:dem":993,
    "gn:feature_class":"P",
    "gn:feature_code":"PPL",
    "gn:name":"Xihouzikou",
    "gn:population":0,
    "gn:timezone":"Asia/Shanghai",
    "iso:country":"CN",
    "name:zho_x_preferred":[
        "\u897f\u540e\u5b50\u53e3"
    ],
    "wof:name":"Xihouzikou",
    "wof:placetype":"locality"
},
  "geometry": {"coordinates":[113.61102,39.90592],"type":"Point"}
}