{
  "type": "Feature",
  "properties": {
    "gn:admin1_code":"29.0",
    "gn:asciiname":"Fawu",
    "gn:country_code":"CN",
    "gn:dem":1534,
    "gn:feature_class":"P",
    "gn:feature_code":"PPL",
    "gn:name":"Fawu",
    "gn:population":0,
    "gn:timezone":"Asia/Shanghai",
    "iso:country":"CN",
    "name:zho_x_preferred":[
        "\u6cd5\u4e4c"
    ],
    "wof:name":"Fawu",
    "wof:placetype":"locality"
},
  "geometry": {"coordinates":[100.807,24.7777],"type":"Point"}
}