{
  "type": "Feature",
  "properties": {
    "gn:admin1_code":"19.0",
    "gn:asciiname":"Puhoutun",
    "gn:country_code":"CN",
    "gn:dem":271,
    "gn:feature_class":"P",
    "gn:feature_code":"PPL",
    "gn:name":"Puhoutun",
    "gn:population":0,
    "gn:timezone":"Asia/Shanghai",
    "iso:country":"CN",
    "name:zho_x_preferred":[
        "\u6734\u539a\u5c6f"
    ],
    "wof:name":"Puhoutun",
    "wof:placetype":"locality"
},
  "geometry": {"coordinates":[124.633,42.543],"type":"Point"}
}