{
  "type": "Feature",
  "properties": {
    "gn:admin1_code":"2.0",
    "gn:asciiname":"Shiwu",
    "gn:country_code":"CN",
    "gn:dem":227,
    "gn:feature_class":"P",
    "gn:feature_code":"PPL",
    "gn:name":"Shiwu",
    "gn:population":0,
    "gn:timezone":"Asia/Shanghai",
    "iso:country":"CN",
    "name:lit_x_preferred":[
        "Shih-wu"
    ],
    "name:pol_x_preferred":[
        "Shiwu Qinggong"
    ],
    "name:zho_x_preferred":[
        "\u77f3\u575e"
    ],
    "wof:name":"Shiwu",
    "wof:placetype":"locality"
},
  "geometry": {"coordinates":[120.49494,29.25107],"type":"Point"}
}