{
  "type": "Feature",
  "properties": {
    "gn:admin1_code":"26.0",
    "gn:asciiname":"Beipo",
    "gn:country_code":"CN",
    "gn:dem":1188,
    "gn:feature_class":"P",
    "gn:feature_code":"PPL",
    "gn:name":"Beipo",
    "gn:population":0,
    "gn:timezone":"Asia/Shanghai",
    "iso:country":"CN",
    "name:zho_x_preferred":[
        "\u5317\u5761"
    ],
    "wof:name":"Beipo",
    "wof:placetype":"locality"
},
  "geometry": {"coordinates":[107.75655999999999,35.14209],"type":"Point"}
}