{
  "type": "Feature",
  "properties": {
    "gn:admin1_code":"14.0",
    "gn:asciiname":"Oubacun",
    "gn:country_code":"CN",
    "gn:dem":3305,
    "gn:feature_class":"P",
    "gn:feature_code":"PPL",
    "gn:name":"Oubacun",
    "gn:population":0,
    "gn:timezone":"Asia/Urumqi",
    "iso:country":"CN",
    "name:zho_x_preferred":[
        "\u6b27\u5df4\u6751"
    ],
    "wof:name":"Oubacun",
    "wof:placetype":"locality"
},
  "geometry": {"coordinates":[93.6497,29.9127],"type":"Point"}
}