{
  "type": "Feature",
  "properties": {
    "gn:admin1_code":"29.0",
    "gn:asciiname":"Manggang",
    "gn:country_code":"CN",
    "gn:dem":1649,
    "gn:feature_class":"P",
    "gn:feature_code":"PPL",
    "gn:name":"Manggang",
    "gn:population":0,
    "gn:timezone":"Asia/Shanghai",
    "iso:country":"CN",
    "name:zho_x_preferred":[
        "\u8292\u5c97"
    ],
    "wof:name":"Manggang",
    "wof:placetype":"locality"
},
  "geometry": {"coordinates":[98.90779999999999,23.6505],"type":"Point"}
}