{
  "type": "Feature",
  "properties": {
    "gn:admin1_code":"29.0",
    "gn:asciiname":"Haiqing",
    "gn:country_code":"CN",
    "gn:dem":2219,
    "gn:feature_class":"P",
    "gn:feature_code":"PPL",
    "gn:name":"Haiqing",
    "gn:population":0,
    "gn:timezone":"Asia/Shanghai",
    "iso:country":"CN",
    "name:und_x_variant":[
        "\u6d77\u5e86"
    ],
    "wof:name":"Haiqing",
    "wof:placetype":"locality"
},
  "geometry": {"coordinates":[104.32176,26.57942],"type":"Point"}
}