{
  "type": "Feature",
  "properties": {
    "gn:admin1_code":"21.0",
    "gn:asciiname":"Liuxiangzhuang",
    "gn:country_code":"CN",
    "gn:dem":1472,
    "gn:feature_class":"P",
    "gn:feature_code":"PPL",
    "gn:name":"Liuxiangzhuang",
    "gn:population":0,
    "gn:timezone":"Asia/Shanghai",
    "iso:country":"CN",
    "name:zho_x_preferred":[
        "\u5218\u76f8\u5e84"
    ],
    "wof:name":"Liuxiangzhuang",
    "wof:placetype":"locality"
},
  "geometry": {"coordinates":[107.119,37.8896],"type":"Point"}
}