{
  "type": "Feature",
  "properties": {
    "gn:admin1_code":"16.0",
    "gn:asciiname":"Gudaokeng",
    "gn:country_code":"CN",
    "gn:dem":577,
    "gn:feature_class":"P",
    "gn:feature_code":"PPL",
    "gn:name":"Gudaokeng",
    "gn:population":0,
    "gn:timezone":"Asia/Shanghai",
    "iso:country":"CN",
    "name:zho_x_preferred":[
        "\u53e4\u9053\u5751"
    ],
    "wof:name":"Gudaokeng",
    "wof:placetype":"locality"
},
  "geometry": {"coordinates":[110.08499999999999,23.7887],"type":"Point"}
}