{
  "type": "Feature",
  "properties": {
    "gn:admin1_code":"33.0",
    "gn:asciiname":"Kongjia Yuanzi",
    "gn:country_code":"CN",
    "gn:dem":1320,
    "gn:feature_class":"P",
    "gn:feature_code":"PPL",
    "gn:name":"Kongjia Yuanzi",
    "gn:population":0,
    "gn:timezone":"Asia/Shanghai",
    "iso:country":"CN",
    "name:zho_x_preferred":[
        "\u5b54\u5bb6\u9662\u5b50"
    ],
    "wof:name":"Kongjia Yuanzi",
    "wof:placetype":"locality"
},
  "geometry": {"coordinates":[108.82362999999999,28.93939],"type":"Point"}
}