{
  "type": "Feature",
  "properties": {
    "gn:admin1_code":"32.0",
    "gn:asciiname":"Chulongba",
    "gn:country_code":"CN",
    "gn:dem":533,
    "gn:feature_class":"P",
    "gn:feature_code":"PPL",
    "gn:name":"Chulongba",
    "gn:population":0,
    "gn:timezone":"Asia/Shanghai",
    "iso:country":"CN",
    "name:zho_x_preferred":[
        "\u51fa\u9f99\u575d"
    ],
    "wof:name":"Chulongba",
    "wof:placetype":"locality"
},
  "geometry": {"coordinates":[104.94156,28.31994000000001],"type":"Point"}
}