{
  "type": "Feature",
  "properties": {
    "gn:admin1_code":"8.0",
    "gn:asciiname":"Yugongtun",
    "gn:country_code":"CN",
    "gn:dem":133,
    "gn:feature_class":"P",
    "gn:feature_code":"PPL",
    "gn:name":"Yugongtun",
    "gn:population":0,
    "gn:timezone":"Asia/Shanghai",
    "iso:country":"CN",
    "name:zho_x_preferred":[
        "\u4e8e\u516c\u5c6f"
    ],
    "wof:name":"Yugongtun",
    "wof:placetype":"locality"
},
  "geometry": {"coordinates":[125.95931000000002,45.50957],"type":"Point"}
}