{
  "type": "Feature",
  "properties": {
    "gn:admin1_code":"15.0",
    "gn:asciiname":"Fumen",
    "gn:country_code":"CN",
    "gn:dem":1630,
    "gn:feature_class":"P",
    "gn:feature_code":"PPL",
    "gn:name":"Fumen",
    "gn:population":0,
    "gn:timezone":"Asia/Shanghai",
    "iso:country":"CN",
    "name:und_x_variant":[
        "\u4ed8\u95e8"
    ],
    "wof:name":"Fumen",
    "wof:placetype":"locality"
},
  "geometry": {"coordinates":[104.71205,34.71773],"type":"Point"}
}