{
  "type": "Feature",
  "properties": {
    "gn:admin1_code":"32.0",
    "gn:asciiname":"Zhuazhuashi",
    "gn:country_code":"CN",
    "gn:dem":655,
    "gn:feature_class":"P",
    "gn:feature_code":"PPL",
    "gn:name":"Zhuazhuashi",
    "gn:population":0,
    "gn:timezone":"Asia/Shanghai",
    "iso:country":"CN",
    "name:zho_x_preferred":[
        "\u6293\u6293\u77f3"
    ],
    "wof:name":"Zhuazhuashi",
    "wof:placetype":"locality"
},
  "geometry": {"coordinates":[104.65633,29.63134],"type":"Point"}
}