{
  "type": "Feature",
  "properties": {
    "gn:admin1_code":"9.0",
    "gn:asciiname":"Wuhumiao",
    "gn:country_code":"CN",
    "gn:dem":177,
    "gn:feature_class":"P",
    "gn:feature_code":"PPL",
    "gn:name":"Wuhumiao",
    "gn:population":0,
    "gn:timezone":"Asia/Shanghai",
    "iso:country":"CN",
    "name:zho_x_preferred":[
        "\u4e94\u864e\u5e99"
    ],
    "wof:name":"Wuhumiao",
    "wof:placetype":"locality"
},
  "geometry": {"coordinates":[113.64176999999999,34.51714],"type":"Point"}
}