{
  "type": "Feature",
  "properties": {
    "gn:admin1_code":"31.0",
    "gn:asciiname":"Baishapo",
    "gn:country_code":"CN",
    "gn:dem":8,
    "gn:feature_class":"P",
    "gn:feature_code":"PPL",
    "gn:name":"Baishapo",
    "gn:population":0,
    "gn:timezone":"Asia/Shanghai",
    "iso:country":"CN",
    "name:zho_x_preferred":[
        "\u767d\u6c99\u5761"
    ],
    "wof:name":"Baishapo",
    "wof:placetype":"locality"
},
  "geometry": {"coordinates":[110.43383,18.81554],"type":"Point"}
}