{
  "type": "Feature",
  "properties": {
    "gn:admin1_code":"9",
    "gn:asciiname":"Niuwang",
    "gn:country_code":"CN",
    "gn:dem":65,
    "gn:feature_class":"P",
    "gn:feature_code":"PPL",
    "gn:name":"Niuwang",
    "gn:population":0,
    "gn:timezone":"Asia/Shanghai",
    "iso:country":"CN",
    "name:und_x_variant":[
        "\u94ae\u738b"
    ],
    "wof:name":"Niuwang",
    "wof:placetype":"locality"
},
  "geometry": {"coordinates":[113.92446,33.67138],"type":"Point"}
}