{
  "type": "Feature",
  "properties": {
    "gn:admin1_code":"26.0",
    "gn:asciiname":"Beishijiazhuangcun",
    "gn:country_code":"CN",
    "gn:dem":857,
    "gn:feature_class":"P",
    "gn:feature_code":"PPL",
    "gn:name":"Beishijiazhuangcun",
    "gn:population":0,
    "gn:timezone":"Asia/Shanghai",
    "iso:country":"CN",
    "name:zho_x_preferred":[
        "\u5317\u53f2\u5bb6\u5e84\u6751"
    ],
    "wof:name":"Beishijiazhuangcun",
    "wof:placetype":"locality"
},
  "geometry": {"coordinates":[110.39295,36.18927],"type":"Point"}
}