{
  "type": "Feature",
  "properties": {
    "gn:country":"CN",
    "gn:fcode":"ADM3",
    "gn:pop":0,
    "iso:country":"CN",
    "name:ceb_x_preferred":[
        "Luxi Xian"
    ],
    "name:deu_x_preferred":[
        "Luxi"
    ],
    "name:fas_x_preferred":[
        "\u0634\u0647\u0631\u0633\u062a\u0627\u0646 \u0644\u0648\u0634\u06cc"
    ],
    "name:jpn_x_preferred":[
        "\u8606\u6e13\u770c"
    ],
    "name:kor_x_preferred":[
        "\ub8e8\uc2dc\ud604"
    ],
    "name:nor_x_preferred":[
        "Luxi"
    ],
    "name:swe_x_preferred":[
        "Luxi"
    ],
    "name:unk_x_variant":[
        "Lu-hsi Hsien"
    ],
    "name:vie_x_preferred":[
        "L\u00f4 Kh\u00ea"
    ],
    "name:zho_x_preferred":[
        "\u6cf8\u897f\u53bf"
    ],
    "name:zho_x_variant":[
        "\u6cf8\u897f",
        "\u82a6\u6eaa\u53bf"
    ],
    "qs:name":"Luxi Xian",
    "qs:photos_9r":0,
    "qs:photos_sr":0,
    "qs:pop_sr":"0",
    "wd:wordcount":62,
    "wof:name":"Luxi Xian",
    "wof:placetype":"localadmin",
    "wof:population":0
},
  "geometry": {"coordinates":[103.74888,24.50955],"type":"Point"}
}