{
  "type": "Feature",
  "properties": {
    "gn:country":"CN",
    "gn:fcode":"ADM3",
    "gn:pop":0,
    "iso:country":"CN",
    "name:unk_x_variant":[
        "Lu-hsi Hsien"
    ],
    "name:zho_x_preferred":[
        "\u6cf8\u897f\u53bf"
    ],
    "name:zho_x_variant":[
        "\u6cf8\u897f"
    ],
    "qs:name":"Luxi Xian",
    "qs:photos_9r":0,
    "qs:photos_sr":0,
    "qs:pop_sr":"0",
    "wd:wordcount":62,
    "wof:name":"Luxi Xian",
    "wof:placetype":"localadmin",
    "wof:population":0
},
  "geometry": {"coordinates":[103.74888,24.50955],"type":"Point"}
}