{
  "type": "Feature",
  "properties": {
    "gn:admin1_code":"9.0",
    "gn:asciiname":"Qiangeda",
    "gn:country_code":"CN",
    "gn:dem":1209,
    "gn:feature_class":"P",
    "gn:feature_code":"PPL",
    "gn:name":"Qiangeda",
    "gn:population":0,
    "gn:timezone":"Asia/Shanghai",
    "iso:country":"CN",
    "name:zho_x_preferred":[
        "\u524d\u7599\u7629"
    ],
    "wof:name":"Qiangeda",
    "wof:placetype":"locality"
},
  "geometry": {"coordinates":[110.80183999999998,33.81037],"type":"Point"}
}