{
  "type": "Feature",
  "properties": {
    "gn:admin1_code":"32.0",
    "gn:asciiname":"Xuzhaochang",
    "gn:country_code":"CN",
    "gn:dem":335,
    "gn:feature_class":"P",
    "gn:feature_code":"PPL",
    "gn:name":"Xuzhaochang",
    "gn:population":0,
    "gn:timezone":"Asia/Shanghai",
    "iso:country":"CN",
    "name:zho_x_preferred":[
        "\u65ed\u7167\u573a"
    ],
    "wof:name":"Xuzhaochang",
    "wof:placetype":"locality"
},
  "geometry": {"coordinates":[105.73408999999999,28.86616],"type":"Point"}
}