{
  "type": "Feature",
  "properties": {
    "gn:admin1_code":"15.0",
    "gn:asciiname":"Shiguaizi",
    "gn:country_code":"CN",
    "gn:dem":2336,
    "gn:feature_class":"P",
    "gn:feature_code":"PPL",
    "gn:name":"Shiguaizi",
    "gn:population":0,
    "gn:timezone":"Asia/Shanghai",
    "iso:country":"CN",
    "name:zho_x_preferred":[
        "\u77f3\u62d0\u5b50"
    ],
    "wof:name":"Shiguaizi",
    "wof:placetype":"locality"
},
  "geometry": {"coordinates":[103.68899999999999,36.8474],"type":"Point"}
}