{
  "type": "Feature",
  "properties": {
    "gn:admin1_code":"18",
    "gn:asciiname":"Tianyakou",
    "gn:country_code":"CN",
    "gn:dem":980,
    "gn:feature_class":"P",
    "gn:feature_code":"PPL",
    "gn:name":"Tianyakou",
    "gn:population":0,
    "gn:timezone":"Asia/Shanghai",
    "iso:country":"CN",
    "name:zho_x_preferred":[
        "\u7530\u57ad\u53e3"
    ],
    "wof:name":"Tianyakou",
    "wof:placetype":"locality"
},
  "geometry": {"coordinates":[106.98399999999999,28.7493],"type":"Point"}
}