{
  "type": "Feature",
  "properties": {
    "gn:admin1_code":"9.0",
    "gn:asciiname":"Sunqituncun",
    "gn:country_code":"CN",
    "gn:dem":186,
    "gn:feature_class":"P",
    "gn:feature_code":"PPL",
    "gn:name":"Sunqituncun",
    "gn:population":0,
    "gn:timezone":"Asia/Shanghai",
    "iso:country":"CN",
    "name:zho_x_preferred":[
        "\u5b59\u65d7\u5c6f\u6751"
    ],
    "wof:name":"Sunqituncun",
    "wof:placetype":"locality"
},
  "geometry": {"coordinates":[112.37513,34.64785],"type":"Point"}
}