{
  "type": "Feature",
  "properties": {
    "gn:admin1_code":"2.0",
    "gn:asciiname":"Songjiabian",
    "gn:country_code":"CN",
    "gn:dem":118,
    "gn:feature_class":"P",
    "gn:feature_code":"PPL",
    "gn:name":"Songjiabian",
    "gn:population":0,
    "gn:timezone":"Asia/Shanghai",
    "iso:country":"CN",
    "name:zho_x_preferred":[
        "\u5b8b\u5bb6\u8fb9"
    ],
    "wof:name":"Songjiabian",
    "wof:placetype":"locality"
},
  "geometry": {"coordinates":[118.56551,29.44009],"type":"Point"}
}