{
  "type": "Feature",
  "properties": {
    "gn:admin1_code":"16.0",
    "gn:asciiname":"Shanhu Xincun",
    "gn:country_code":"CN",
    "gn:dem":54,
    "gn:feature_class":"P",
    "gn:feature_code":"PPL",
    "gn:name":"Shanhu Xincun",
    "gn:population":0,
    "gn:timezone":"Asia/Shanghai",
    "iso:country":"CN",
    "name:zho_x_preferred":[
        "\u5c71\u659b\u65b0\u6751"
    ],
    "wof:name":"Shanhu Xincun",
    "wof:placetype":"locality"
},
  "geometry": {"coordinates":[109.364,23.1236],"type":"Point"}
}