{
  "type": "Feature",
  "properties": {
    "gn:admin1_code":"18",
    "gn:asciiname":"Guantiankan",
    "gn:country_code":"CN",
    "gn:dem":1126,
    "gn:feature_class":"P",
    "gn:feature_code":"PPL",
    "gn:name":"Guantiankan",
    "gn:population":0,
    "gn:timezone":"Asia/Shanghai",
    "iso:country":"CN",
    "name:zho_x_preferred":[
        "\u5b98\u7530\u574e"
    ],
    "wof:name":"Guantiankan",
    "wof:placetype":"locality"
},
  "geometry": {"coordinates":[106.63200000000001,28.2727],"type":"Point"}
}