{
  "type": "Feature",
  "properties": {
    "gn:admin1_code":"29.0",
    "gn:asciiname":"Laowuchong",
    "gn:country_code":"CN",
    "gn:dem":1867,
    "gn:feature_class":"P",
    "gn:feature_code":"PPL",
    "gn:name":"Laowuchong",
    "gn:population":0,
    "gn:timezone":"Asia/Shanghai",
    "iso:country":"CN",
    "name:zho_x_preferred":[
        "\u8001\u5434\u51b2"
    ],
    "wof:name":"Laowuchong",
    "wof:placetype":"locality"
},
  "geometry": {"coordinates":[103.85299999999999,25.2017],"type":"Point"}
}