{
  "type": "Feature",
  "properties": {
    "gn:admin1_code":"4.0",
    "gn:asciiname":"Liushuxu",
    "gn:country_code":"CN",
    "gn:dem":14,
    "gn:feature_class":"P",
    "gn:feature_code":"PPL",
    "gn:name":"Liushuxu",
    "gn:population":0,
    "gn:timezone":"Asia/Shanghai",
    "iso:country":"CN",
    "name:zho_x_preferred":[
        "\u67f3\u6811\u5729"
    ],
    "wof:name":"Liushuxu",
    "wof:placetype":"locality"
},
  "geometry": {"coordinates":[119.06206,32.87828],"type":"Point"}
}