{
  "type": "Feature",
  "properties": {
    "gn:admin1_code":"15.0",
    "gn:asciiname":"Xiaonancha",
    "gn:country_code":"CN",
    "gn:dem":1877,
    "gn:feature_class":"P",
    "gn:feature_code":"PPL",
    "gn:name":"Xiaonancha",
    "gn:population":0,
    "gn:timezone":"Asia/Shanghai",
    "iso:country":"CN",
    "name:zho_x_preferred":[
        "\u5c0f\u5357\u5c94"
    ],
    "wof:name":"Xiaonancha",
    "wof:placetype":"locality"
},
  "geometry": {"coordinates":[105.178,36.0657],"type":"Point"}
}