{
  "type": "Feature",
  "properties": {
    "gn:admin1_code":"29.0",
    "gn:asciiname":"Luodihe Xincun",
    "gn:country_code":"CN",
    "gn:dem":1333,
    "gn:feature_class":"P",
    "gn:feature_code":"PPL",
    "gn:name":"Luodihe Xincun",
    "gn:population":0,
    "gn:timezone":"Asia/Shanghai",
    "iso:country":"CN",
    "name:zho_x_preferred":[
        "\u843d\u5e95\u6cb3\u65b0\u6751"
    ],
    "wof:name":"Luodihe Xincun",
    "wof:placetype":"locality"
},
  "geometry": {"coordinates":[100.39100000000001,24.7667],"type":"Point"}
}