{
  "type": "Feature",
  "properties": {
    "gn:admin1_code":"3.0",
    "gn:asciiname":"Huangjinling",
    "gn:country_code":"CN",
    "gn:dem":142,
    "gn:feature_class":"P",
    "gn:feature_code":"PPL",
    "gn:name":"Huangjinling",
    "gn:population":0,
    "gn:timezone":"Asia/Shanghai",
    "iso:country":"CN",
    "name:zho_x_preferred":[
        "\u9ec4\u91d1\u5cad"
    ],
    "wof:name":"Huangjinling",
    "wof:placetype":"locality"
},
  "geometry": {"coordinates":[118.04928999999998,28.2763],"type":"Point"}
}