{
  "type": "Feature",
  "properties": {
    "gn:admin1_code":"4.0",
    "gn:asciiname":"Gaoba",
    "gn:country_code":"CN",
    "gn:dem":9,
    "gn:feature_class":"P",
    "gn:feature_code":"PPL",
    "gn:name":"Gaoba",
    "gn:population":0,
    "gn:timezone":"Asia/Shanghai",
    "iso:country":"CN",
    "name:zho_x_preferred":[
        "Gaoba"
    ],
    "name:zho_x_variant":[
        "\u9ad8\u575d"
    ],
    "wof:name":"Gaoba",
    "wof:placetype":"locality"
},
  "geometry": {"coordinates":[119.02233,33.45097],"type":"Point"}
}