{
  "type": "Feature",
  "properties": {
    "gn:admin1_code":"4.0",
    "gn:asciiname":"Huangqiao",
    "gn:country_code":"CN",
    "gn:dem":7,
    "gn:feature_class":"P",
    "gn:feature_code":"PPL",
    "gn:name":"Huangqiao",
    "gn:population":0,
    "gn:timezone":"Asia/Shanghai",
    "iso:country":"CN",
    "name:und_x_variant":[
        "\u9ec4\u6865"
    ],
    "name:zho_x_preferred":[
        "\u9ec4\u6865"
    ],
    "wof:name":"Huangqiao",
    "wof:placetype":"locality"
},
  "geometry": {"coordinates":[120.65631999999999,31.83058],"type":"Point"}
}