{
  "type": "Feature",
  "properties": {
    "gn:admin1_code":"29.0",
    "gn:asciiname":"Xiaokuaita",
    "gn:country_code":"CN",
    "gn:dem":1899,
    "gn:feature_class":"P",
    "gn:feature_code":"PPL",
    "gn:name":"Xiaokuaita",
    "gn:population":0,
    "gn:timezone":"Asia/Shanghai",
    "iso:country":"CN",
    "name:zho_x_preferred":[
        "\u5c0f\u5757\u5854"
    ],
    "wof:name":"Xiaokuaita",
    "wof:placetype":"locality"
},
  "geometry": {"coordinates":[104.544,26.469],"type":"Point"}
}