{
  "type": "Feature",
  "properties": {
    "gn:admin1_code":"10.0",
    "gn:asciiname":"Yanjiazhuang",
    "gn:country_code":"CN",
    "gn:dem":966,
    "gn:feature_class":"P",
    "gn:feature_code":"PPL",
    "gn:name":"Yanjiazhuang",
    "gn:population":0,
    "gn:timezone":"Asia/Shanghai",
    "iso:country":"CN",
    "name:zho_x_preferred":[
        "\u664f\u5bb6\u5e84"
    ],
    "wof:name":"Yanjiazhuang",
    "wof:placetype":"locality"
},
  "geometry": {"coordinates":[115.59407,40.51886],"type":"Point"}
}