{
  "type": "Feature",
  "properties": {
    "gn:admin1_code":"3",
    "gn:asciiname":"Bajiang",
    "gn:country_code":"CN",
    "gn:dem":54,
    "gn:feature_class":"P",
    "gn:feature_code":"PPLA4",
    "gn:name":"Bajiang",
    "gn:population":0,
    "gn:timezone":"Asia/Shanghai",
    "iso:country":"CN",
    "name:und_x_variant":[
        "\u516b\u6c5f",
        "Bajiang Xiang",
        "\u516b\u6c5f\u4e61"
    ],
    "wof:name":"Bajiang",
    "wof:placetype":"locality"
},
  "geometry": {"coordinates":[115.35151999999999,27.20363],"type":"Point"}
}