{
  "type": "Feature",
  "properties": {
    "gn:admin1_code":"11",
    "gn:asciiname":"Liantuan",
    "gn:country_code":"CN",
    "gn:dem":961,
    "gn:feature_class":"P",
    "gn:feature_code":"PPL",
    "gn:name":"Liantuan",
    "gn:population":0,
    "gn:timezone":"Asia/Shanghai",
    "iso:country":"CN",
    "wof:name":"Liantuan",
    "wof:placetype":"locality"
},
  "geometry": {"coordinates":[110.40778,26.45111],"type":"Point"}
}