{
  "type": "Feature",
  "properties": {
    "gn:admin1_code":"12.0",
    "gn:asciiname":"Zhouji",
    "gn:country_code":"CN",
    "gn:dem":32,
    "gn:feature_class":"P",
    "gn:feature_code":"PPL",
    "gn:name":"Zhouji",
    "gn:population":0,
    "gn:timezone":"Asia/Shanghai",
    "iso:country":"CN",
    "name:zho_x_preferred":[
        "\u5468\u77f6"
    ],
    "wof:name":"Zhouji",
    "wof:placetype":"locality"
},
  "geometry": {"coordinates":[112.79121000000001,30.37708],"type":"Point"}
}