{
  "type": "Feature",
  "properties": {
    "gn:admin1_code":"3.0",
    "gn:asciiname":"Nanmuchong",
    "gn:country_code":"CN",
    "gn:dem":437,
    "gn:feature_class":"P",
    "gn:feature_code":"PPL",
    "gn:name":"Nanmuchong",
    "gn:population":0,
    "gn:timezone":"Asia/Shanghai",
    "iso:country":"CN",
    "name:und_x_variant":[
        "\u6960\u6728\u51b2"
    ],
    "wof:name":"Nanmuchong",
    "wof:placetype":"locality"
},
  "geometry": {"coordinates":[114.00424,27.47671],"type":"Point"}
}