{
  "type": "Feature",
  "properties": {
    "gn:admin1_code":"15.0",
    "gn:asciiname":"Qilian Yidui",
    "gn:country_code":"CN",
    "gn:dem":1631,
    "gn:feature_class":"P",
    "gn:feature_code":"PPLF",
    "gn:name":"Qilian Yidui",
    "gn:population":0,
    "gn:timezone":"Asia/Shanghai",
    "iso:country":"CN",
    "name:zho_x_preferred":[
        "\u7941\u8fde\u4e00\u961f"
    ],
    "wof:name":"Qilian Yidui",
    "wof:placetype":"locality"
},
  "geometry": {"coordinates":[100.133,38.9831],"type":"Point"}
}