{
  "type": "Feature",
  "properties": {
    "gn:admin1_code":"24.0",
    "gn:asciiname":"Yahecun",
    "gn:country_code":"CN",
    "gn:dem":673,
    "gn:feature_class":"P",
    "gn:feature_code":"PPL",
    "gn:name":"Yahecun",
    "gn:population":0,
    "gn:timezone":"Asia/Shanghai",
    "iso:country":"CN",
    "name:zho_x_preferred":[
        "\u9e2d\u6cb3\u6751"
    ],
    "wof:name":"Yahecun",
    "wof:placetype":"locality"
},
  "geometry": {"coordinates":[110.98352,35.30427],"type":"Point"}
}