{
  "type": "Feature",
  "properties": {
    "gn:admin1_code":"21.0",
    "gn:asciiname":"Yixintan",
    "gn:country_code":"CN",
    "gn:dem":1204,
    "gn:feature_class":"P",
    "gn:feature_code":"PPL",
    "gn:name":"Yixintan",
    "gn:population":0,
    "gn:timezone":"Asia/Shanghai",
    "iso:country":"CN",
    "name:zho_x_preferred":[
        "\u4e00\u5fc3\u6ee9"
    ],
    "wof:name":"Yixintan",
    "wof:placetype":"locality"
},
  "geometry": {"coordinates":[105.384,37.5018],"type":"Point"}
}