{
  "type": "Feature",
  "properties": {
    "gn:admin1_code":"5",
    "gn:asciiname":"Zhuanxinhu",
    "gn:country_code":"CN",
    "gn:dem":290,
    "gn:feature_class":"P",
    "gn:feature_code":"PPL",
    "gn:name":"Zhuanxinhu",
    "gn:population":0,
    "gn:timezone":"Asia/Shanghai",
    "iso:country":"CN",
    "name:zho_x_preferred":[
        "\u8f6c\u5fc3\u6e56"
    ],
    "wof:name":"Zhuanxinhu",
    "wof:placetype":"locality"
},
  "geometry": {"coordinates":[127.206,43.2868],"type":"Point"}
}