{
  "type": "Feature",
  "properties": {
    "gn:admin1_code":"4.0",
    "gn:asciiname":"Yijiaqiao Xincun",
    "gn:country_code":"CN",
    "gn:dem":5,
    "gn:feature_class":"P",
    "gn:feature_code":"PPL",
    "gn:name":"Yijiaqiao Xincun",
    "gn:population":0,
    "gn:timezone":"Asia/Shanghai",
    "iso:country":"CN",
    "name:zho_x_preferred":[
        "\u6613\u5bb6\u6865\u65b0\u6751"
    ],
    "wof:name":"Yijiaqiao Xincun",
    "wof:placetype":"locality"
},
  "geometry": {"coordinates":[120.87633,32.00338],"type":"Point"}
}