{
  "type": "Feature",
  "properties": {
    "gn:admin1_code":"21.0",
    "gn:asciiname":"Youfangtang",
    "gn:country_code":"CN",
    "gn:dem":1744,
    "gn:feature_class":"P",
    "gn:feature_code":"PPL",
    "gn:name":"Youfangtang",
    "gn:population":0,
    "gn:timezone":"Asia/Shanghai",
    "iso:country":"CN",
    "name:und_x_variant":[
        "\u6cb9\u623f\u6dcc"
    ],
    "name:zho_x_preferred":[
        "\u6cb9\u623f\u6dcc"
    ],
    "wof:name":"Youfangtang",
    "wof:placetype":"locality"
},
  "geometry": {"coordinates":[106.56792,36.97177],"type":"Point"}
}