{
  "type": "Feature",
  "properties": {
    "gn:admin1_code":"31.0",
    "gn:asciiname":"Baimao",
    "gn:country_code":"CN",
    "gn:dem":12,
    "gn:feature_class":"P",
    "gn:feature_code":"PPL",
    "gn:name":"Baimao",
    "gn:population":0,
    "gn:timezone":"Asia/Shanghai",
    "iso:country":"CN",
    "name:zho_x_preferred":[
        "Baimao"
    ],
    "name:zho_x_variant":[
        "\u767d\u8305"
    ],
    "wof:name":"Baimao",
    "wof:placetype":"locality"
},
  "geometry": {"coordinates":[110.74113,19.97343],"type":"Point"}
}