{
  "type": "Feature",
  "properties": {
    "gn:admin1_code":"14.0",
    "gn:asciiname":"Dangmuri'a",
    "gn:country_code":"CN",
    "gn:dem":4282,
    "gn:feature_class":"P",
    "gn:feature_code":"PPL",
    "gn:name":"Dangmuri\u2019a",
    "gn:population":0,
    "gn:timezone":"Asia/Urumqi",
    "iso:country":"CN",
    "name:und_x_variant":[
        "Dangmuri\u2019a"
    ],
    "name:zho_x_preferred":[
        "\u515a\u6728\u65e5\u963f"
    ],
    "wof:name":"Dangmuri'a",
    "wof:placetype":"locality"
},
  "geometry": {"coordinates":[94.21287,29.48998],"type":"Point"}
}