{
  "type": "Feature",
  "properties": {
    "gn:admin1_code":"30",
    "gn:asciiname":"Shangpotou",
    "gn:country_code":"CN",
    "gn:dem":19,
    "gn:feature_class":"P",
    "gn:feature_code":"PPL",
    "gn:name":"Shangpotou",
    "gn:population":0,
    "gn:timezone":"Asia/Shanghai",
    "iso:country":"CN",
    "name:zho_x_preferred":[
        "\u4e0a\u5761\u5934"
    ],
    "wof:name":"Shangpotou",
    "wof:placetype":"locality"
},
  "geometry": {"coordinates":[116.07195,23.57612],"type":"Point"}
}