{
  "type": "Feature",
  "properties": {
    "gn:admin1_code":"12.0",
    "gn:asciiname":"Shijia'ao",
    "gn:country_code":"CN",
    "gn:dem":96,
    "gn:feature_class":"P",
    "gn:feature_code":"PPL",
    "gn:name":"Shijia\u2019ao",
    "gn:population":0,
    "gn:timezone":"Asia/Shanghai",
    "iso:country":"CN",
    "name:zho_x_preferred":[
        "Shijia\u2019ao"
    ],
    "name:zho_x_variant":[
        "\u53f2\u5bb6\u5773"
    ],
    "wof:name":"Shijia'ao",
    "wof:placetype":"locality"
},
  "geometry": {"coordinates":[115.24634,30.81083],"type":"Point"}
}