{
  "type": "Feature",
  "properties": {
    "gn:admin1_code":"32",
    "gn:asciiname":"Yinjiashan",
    "gn:country_code":"CN",
    "gn:dem":599,
    "gn:feature_class":"P",
    "gn:feature_code":"PPL",
    "gn:name":"Yinjiashan",
    "gn:population":0,
    "gn:timezone":"Asia/Shanghai",
    "iso:country":"CN",
    "name:zho_x_preferred":[
        "\u5c39\u5bb6\u5c71"
    ],
    "wof:name":"Yinjiashan",
    "wof:placetype":"locality"
},
  "geometry": {"coordinates":[105.51591999999999,31.70814],"type":"Point"}
}