{
  "type": "Feature",
  "properties": {
    "gn:admin1_code":"25.0",
    "gn:asciiname":"Shirenbocun",
    "gn:country_code":"CN",
    "gn:dem":12,
    "gn:feature_class":"P",
    "gn:feature_code":"PPL",
    "gn:name":"Shirenbocun",
    "gn:population":0,
    "gn:timezone":"Asia/Shanghai",
    "iso:country":"CN",
    "name:zho_x_preferred":[
        "\u77f3\u4eba\u6cca\u6751"
    ],
    "wof:name":"Shirenbocun",
    "wof:placetype":"locality"
},
  "geometry": {"coordinates":[121.20703,36.73509],"type":"Point"}
}