{
  "type": "Feature",
  "properties": {
    "gn:admin1_code":"29.0",
    "gn:asciiname":"Naqian",
    "gn:country_code":"CN",
    "gn:dem":1037,
    "gn:feature_class":"P",
    "gn:feature_code":"PPL",
    "gn:name":"Naqian",
    "gn:population":0,
    "gn:timezone":"Asia/Shanghai",
    "iso:country":"CN",
    "name:zho_x_preferred":[
        "\u90a3\u8fc1"
    ],
    "wof:name":"Naqian",
    "wof:placetype":"locality"
},
  "geometry": {"coordinates":[100.941,22.9517],"type":"Point"}
}