{
  "type": "Feature",
  "properties": {
    "gn:admin1_code":"30",
    "gn:asciiname":"Jiaotangxia",
    "gn:country_code":"CN",
    "gn:dem":32,
    "gn:feature_class":"P",
    "gn:feature_code":"PPL",
    "gn:name":"Jiaotangxia",
    "gn:population":0,
    "gn:timezone":"Asia/Shanghai",
    "iso:country":"CN",
    "name:zho_x_preferred":[
        "\u8f83\u5858\u4e0b"
    ],
    "wof:name":"Jiaotangxia",
    "wof:placetype":"locality"
},
  "geometry": {"coordinates":[116.15821,23.67317],"type":"Point"}
}