{
  "type": "Feature",
  "properties": {
    "gn:admin1_code":"14.0",
    "gn:asciiname":"Sibudacun",
    "gn:country_code":"CN",
    "gn:dem":4123,
    "gn:feature_class":"P",
    "gn:feature_code":"PPL",
    "gn:name":"Sibudacun",
    "gn:population":0,
    "gn:timezone":"Asia/Urumqi",
    "iso:country":"CN",
    "name:zho_x_preferred":[
        "\u65af\u5e03\u8fbe\u6751"
    ],
    "wof:name":"Sibudacun",
    "wof:placetype":"locality"
},
  "geometry": {"coordinates":[93.97132999999999,31.92416],"type":"Point"}
}