{
  "type": "Feature",
  "properties": {
    "gn:admin1_code":"26.0",
    "gn:asciiname":"Wangjiayuan",
    "gn:country_code":"CN",
    "gn:dem":1291,
    "gn:feature_class":"P",
    "gn:feature_code":"PPL",
    "gn:name":"Wangjiayuan",
    "gn:population":0,
    "gn:timezone":"Asia/Shanghai",
    "iso:country":"CN",
    "name:und_x_variant":[
        "\u738b\u5bb6\u56ed"
    ],
    "wof:name":"Wangjiayuan",
    "wof:placetype":"locality"
},
  "geometry": {"coordinates":[106.77478000000001,32.75763],"type":"Point"}
}