{
  "type": "Feature",
  "properties": {
    "gn:admin1_code":"3.0",
    "gn:asciiname":"Shuinanduan",
    "gn:country_code":"CN",
    "gn:dem":84,
    "gn:feature_class":"P",
    "gn:feature_code":"PPL",
    "gn:name":"Shuinanduan",
    "gn:population":0,
    "gn:timezone":"Asia/Shanghai",
    "iso:country":"CN",
    "name:und_x_variant":[
        "\u6c34\u5357\u5845"
    ],
    "wof:name":"Shuinanduan",
    "wof:placetype":"locality"
},
  "geometry": {"coordinates":[114.65528999999999,27.26116],"type":"Point"}
}