{
  "type": "Feature",
  "properties": {
    "gn:admin1_code":"12.0",
    "gn:asciiname":"Yangshulin",
    "gn:country_code":"CN",
    "gn:dem":26,
    "gn:feature_class":"P",
    "gn:feature_code":"PPL",
    "gn:name":"Yangshulin",
    "gn:population":0,
    "gn:timezone":"Asia/Shanghai",
    "iso:country":"CN",
    "name:und_x_variant":[
        "\u6768\u6811\u6797"
    ],
    "wof:name":"Yangshulin",
    "wof:placetype":"locality"
},
  "geometry": {"coordinates":[114.22007000000001,30.43526],"type":"Point"}
}