{
  "type": "Feature",
  "properties": {
    "gn:admin1_code":"11",
    "gn:asciiname":"Kuzhuchongkou",
    "gn:country_code":"CN",
    "gn:dem":336,
    "gn:feature_class":"P",
    "gn:feature_code":"PPL",
    "gn:name":"Kuzhuchongkou",
    "gn:population":0,
    "gn:timezone":"Asia/Shanghai",
    "iso:country":"CN",
    "name:zho_x_preferred":[
        "\u82e6\u7af9\u51b2\u53e3"
    ],
    "wof:name":"Kuzhuchongkou",
    "wof:placetype":"locality"
},
  "geometry": {"coordinates":[112.03883,25.40364],"type":"Point"}
}