{
  "type": "Feature",
  "properties": {
    "gn:admin1_code":"30",
    "gn:asciiname":"Wangsha",
    "gn:country_code":"CN",
    "gn:dem":189,
    "gn:feature_class":"P",
    "gn:feature_code":"PPL",
    "gn:name":"Wangsha",
    "gn:population":0,
    "gn:timezone":"Asia/Urumqi",
    "iso:country":"CN",
    "name:zho_x_preferred":[
        "\u65fa\u6c99"
    ],
    "wof:name":"Wangsha",
    "wof:placetype":"locality"
},
  "geometry": {"coordinates":[111.04064,22.58748],"type":"Point"}
}