{
  "type": "Feature",
  "properties": {
    "gn:admin1_code":"3.0",
    "gn:asciiname":"Yangjiang",
    "gn:country_code":"CN",
    "gn:dem":81,
    "gn:feature_class":"P",
    "gn:feature_code":"PPLA4",
    "gn:name":"Yangjiang",
    "gn:population":0,
    "gn:timezone":"Asia/Shanghai",
    "iso:country":"CN",
    "name:afr_x_preferred":[
        "Yangjiang"
    ],
    "name:ara_x_preferred":[
        "\u064a\u0627\u0646\u063a\u062c\u064a\u0627\u0646\u063a"
    ],
    "name:cdo_x_preferred":[
        "I\u00f2ng-g\u014fng"
    ],
    "name:ceb_x_preferred":[
        "Yangjiang"
    ],
    "name:ces_x_preferred":[
        "Jang-\u0165iang"
    ],
    "name:cym_x_preferred":[
        "Yangjiang"
    ],
    "name:dan_x_preferred":[
        "Yangjiang"
    ],
    "name:deu_x_preferred":[
        "Yangjiang"
    ],
    "name:eus_x_preferred":[
        "Yangjiang"
    ],
    "name:fas_x_preferred":[
        "\u06cc\u0627\u0646\u06af\u0698\u06cc\u0627\u0646\u06af"
    ],
    "name:fin_x_preferred":[
        "Yangjiang"
    ],
    "name:fra_x_preferred":[
        "Yangjiang"
    ],
    "name:hak_x_preferred":[
        "Y\u00f2ng-k\u00f4ng-s\u1e73"
    ],
    "name:ind_x_preferred":[
        "Yangjiang"
    ],
    "name:ita_x_preferred":[
        "Yangjiang"
    ],
    "name:jpn_x_preferred":[
        "\u967d\u6c5f"
    ],
    "name:jpn_x_variant":[
        "\u967d\u6c5f\u5e02"
    ],
    "name:kik_x_preferred":[
        "Yangjiang"
    ],
    "name:kor_x_preferred":[
        "\uc591\uc7a5\uc2dc"
    ],
    "name:mlg_x_preferred":[
        "Yangjiang"
    ],
    "name:nld_x_preferred":[
        "Yangjiang"
    ],
    "name:nno_x_preferred":[
        "Yangjiang"
    ],
    "name:nor_x_preferred":[
        "Yangjiang"
    ],
    "name:pam_x_preferred":[
        "Yangjiang"
    ],
    "name:pnb_x_preferred":[
        "\u06cc\u0627\u0646\u06af \u062c\u06cc\u0627\u0646\u06af"
    ],
    "name:pol_x_preferred":[
        "Yangjiang"
    ],
    "name:por_x_preferred":[
        "Yangjiang"
    ],
    "name:rus_x_preferred":[
        "\u042f\u043d\u0446\u0437\u044f\u043d"
    ],
    "name:spa_x_preferred":[
        "Yangjiang"
    ],
    "name:srp_x_preferred":[
        "\u0408\u0430\u043d\u0433\u0452\u0430\u043d\u0433"
    ],
    "name:swa_x_preferred":[
        "Yangjiang"
    ],
    "name:swe_x_preferred":[
        "Yangjiang"
    ],
    "name:tur_x_preferred":[
        "Yangjiang"
    ],
    "name:und_x_variant":[
        "Yang-chiang",
        "\u6d0b\u6c5f",
        "Yangjiang Xiang",
        "\u6d0b\u6c5f\u4e61"
    ],
    "name:urd_x_preferred":[
        "\u06cc\u0646\u06af\u062c\u06cc\u0627\u0646\u06af"
    ],
    "name:vie_x_preferred":[
        "D\u01b0\u01a1ng Giang"
    ],
    "name:war_x_preferred":[
        "Yangjiang"
    ],
    "name:zho_x_preferred":[
        "\u9633\u6c5f\u5e02"
    ],
    "wof:name":"Yangjiang",
    "wof:placetype":"locality"
},
  "geometry": {"coordinates":[114.53404999999999,27.85658],"type":"Point"}
}