{
  "type": "Feature",
  "properties": {
    "gn:admin1_code":"3.0",
    "gn:asciiname":"Yangjiang",
    "gn:country_code":"CN",
    "gn:dem":81,
    "gn:feature_class":"P",
    "gn:feature_code":"PPLA4",
    "gn:name":"Yangjiang",
    "gn:population":0,
    "gn:timezone":"Asia/Shanghai",
    "iso:country":"CN",
    "name:und_x_variant":[
        "Yang-chiang",
        "Yangjiang",
        "\u6d0b\u6c5f",
        "Yangjiang Xiang",
        "\u6d0b\u6c5f\u4e61"
    ],
    "wof:name":"Yangjiang",
    "wof:placetype":"locality"
},
  "geometry": {"coordinates":[114.53404999999999,27.85658],"type":"Point"}
}