{
  "type": "Feature",
  "properties": {
    "gn:admin1_code":"9",
    "gn:asciiname":"Jingangji",
    "gn:country_code":"CN",
    "gn:dem":56,
    "gn:feature_class":"P",
    "gn:feature_code":"PPL",
    "gn:name":"Jingangji",
    "gn:population":0,
    "gn:timezone":"Asia/Shanghai",
    "iso:country":"CN",
    "name:zho_x_preferred":[
        "\u91d1\u5c97\u96c6"
    ],
    "wof:name":"Jingangji",
    "wof:placetype":"locality"
},
  "geometry": {"coordinates":[115.221,35.5859],"type":"Point"}
}