{
  "type": "Feature",
  "properties": {
    "gn:admin1_code":"16.0",
    "gn:asciiname":"Napeng",
    "gn:country_code":"CN",
    "gn:dem":41,
    "gn:feature_class":"P",
    "gn:feature_code":"PPL",
    "gn:name":"Napeng",
    "gn:population":0,
    "gn:timezone":"Asia/Shanghai",
    "iso:country":"CN",
    "name:zho_x_preferred":[
        "\u90a3\u84ec"
    ],
    "wof:name":"Napeng",
    "wof:placetype":"locality"
},
  "geometry": {"coordinates":[108.58799999999999,22.1448],"type":"Point"}
}