{
  "type": "Feature",
  "properties": {
    "gn:admin1_code":"26",
    "gn:asciiname":"Gushan",
    "gn:cc2":"CN",
    "gn:country_code":"CN",
    "gn:dem":951,
    "gn:feature_class":"P",
    "gn:feature_code":"PPL",
    "gn:name":"Gushan",
    "gn:population":0,
    "gn:timezone":"Asia/Shanghai",
    "iso:country":"CN",
    "name:und_x_variant":[
        "Ku-shan",
        "Ku-shan-pu",
        "Gushan"
    ],
    "wof:name":"Gushan",
    "wof:placetype":"locality"
},
  "geometry": {"coordinates":[110.88972,39.08111],"type":"Point"}
}