{
  "type": "Feature",
  "properties": {
    "gn:admin1_code":"18.0",
    "gn:asciiname":"Xiaoshan",
    "gn:country_code":"CN",
    "gn:dem":2229,
    "gn:feature_class":"P",
    "gn:feature_code":"PPL",
    "gn:name":"Xiaoshan",
    "gn:population":0,
    "gn:timezone":"Asia/Shanghai",
    "iso:country":"CN",
    "wof:name":"Xiaoshan",
    "wof:placetype":"locality"
},
  "geometry": {"coordinates":[104.24167,26.91667],"type":"Point"}
}