{
  "type": "Feature",
  "properties": {
    "gn:admin1_code":"1.0",
    "gn:asciiname":"Cangxu",
    "gn:country_code":"CN",
    "gn:dem":161,
    "gn:feature_class":"P",
    "gn:feature_code":"PPL",
    "gn:name":"Cangxu",
    "gn:population":0,
    "gn:timezone":"Asia/Shanghai",
    "iso:country":"CN",
    "name:zho_x_preferred":[
        "\u85cf\u5729"
    ],
    "wof:name":"Cangxu",
    "wof:placetype":"locality"
},
  "geometry": {"coordinates":[118.35653000000001,29.65999],"type":"Point"}
}