{
  "type": "Feature",
  "properties": {
    "gn:admin1_code":"14.0",
    "gn:asciiname":"Azire",
    "gn:country_code":"CN",
    "gn:dem":4217,
    "gn:feature_class":"P",
    "gn:feature_code":"PPL",
    "gn:name":"Azire",
    "gn:population":0,
    "gn:timezone":"Asia/Shanghai",
    "iso:country":"CN",
    "name:zho_x_preferred":[
        "\u963f\u5b5c\u70ed"
    ],
    "wof:name":"Azire",
    "wof:placetype":"locality"
},
  "geometry": {"coordinates":[78.87090000000001,32.2249],"type":"Point"}
}