{
  "type": "Feature",
  "properties": {
    "gn:admin1_code":"30",
    "gn:asciiname":"Xishang",
    "gn:country_code":"CN",
    "gn:dem":344,
    "gn:feature_class":"P",
    "gn:feature_code":"PPL",
    "gn:name":"Xishang",
    "gn:population":0,
    "gn:timezone":"Asia/Shanghai",
    "iso:country":"CN",
    "name:zho_x_preferred":[
        "\u6eaa\u4e0a"
    ],
    "wof:name":"Xishang",
    "wof:placetype":"locality"
},
  "geometry": {"coordinates":[116.83859,24.13642],"type":"Point"}
}