{
  "type": "Feature",
  "properties": {
    "gn:admin1_code":"11.0",
    "gn:asciiname":"Jiangjiawan",
    "gn:country_code":"CN",
    "gn:dem":100,
    "gn:feature_class":"P",
    "gn:feature_code":"PPL",
    "gn:name":"Jiangjiawan",
    "gn:population":0,
    "gn:timezone":"Asia/Shanghai",
    "iso:country":"CN",
    "name:zho_x_preferred":[
        "Jiangjiawan"
    ],
    "name:zho_x_variant":[
        "\u848b\u5bb6\u6e7e"
    ],
    "wof:name":"Jiangjiawan",
    "wof:placetype":"locality"
},
  "geometry": {"coordinates":[111.41437999999999,29.45606],"type":"Point"}
}