{
  "type": "Feature",
  "properties": {
    "gn:admin1_code":"8.0",
    "gn:asciiname":"Hongjiatun",
    "gn:country_code":"CN",
    "gn:dem":161,
    "gn:feature_class":"P",
    "gn:feature_code":"PPL",
    "gn:name":"Hongjiatun",
    "gn:population":0,
    "gn:timezone":"Asia/Shanghai",
    "iso:country":"CN",
    "name:zho_x_preferred":[
        "\u6d2a\u5bb6\u5c6f"
    ],
    "wof:name":"Hongjiatun",
    "wof:placetype":"locality"
},
  "geometry": {"coordinates":[126.48213,46.77732],"type":"Point"}
}