{
  "type": "Feature",
  "properties": {
    "gn:admin1_code":"2.0",
    "gn:asciiname":"Dongqiao",
    "gn:country_code":"CN",
    "gn:dem":59,
    "gn:feature_class":"P",
    "gn:feature_code":"PPLA4",
    "gn:name":"Dongqiao",
    "gn:population":0,
    "gn:timezone":"Asia/Shanghai",
    "iso:country":"CN",
    "name:und_x_variant":[
        "\u6d1e\u6865",
        "Dongqiao Zhen",
        "\u6d1e\u6865\u9547"
    ],
    "wof:name":"Dongqiao",
    "wof:placetype":"locality"
},
  "geometry": {"coordinates":[119.58308,30.07605],"type":"Point"}
}