{
  "type": "Feature",
  "properties": {
    "gn:admin1_code":"16",
    "gn:asciiname":"Henglingchong",
    "gn:country_code":"CN",
    "gn:dem":240,
    "gn:feature_class":"P",
    "gn:feature_code":"PPL",
    "gn:name":"Henglingchong",
    "gn:population":0,
    "gn:timezone":"Asia/Shanghai",
    "iso:country":"CN",
    "name:zho_x_preferred":[
        "\u6a2a\u5cad\u51b2"
    ],
    "wof:name":"Henglingchong",
    "wof:placetype":"locality"
},
  "geometry": {"coordinates":[110.658,24.5808],"type":"Point"}
}