{
  "type": "Feature",
  "properties": {
    "gn:admin1_code":"26.0",
    "gn:asciiname":"Yayaocun",
    "gn:country_code":"CN",
    "gn:dem":1178,
    "gn:feature_class":"P",
    "gn:feature_code":"PPL",
    "gn:name":"Yayaocun",
    "gn:population":0,
    "gn:timezone":"Asia/Shanghai",
    "iso:country":"CN",
    "name:zho_x_preferred":[
        "\u5d16\u7a91\u6751"
    ],
    "wof:name":"Yayaocun",
    "wof:placetype":"locality"
},
  "geometry": {"coordinates":[109.29574,36.7308],"type":"Point"}
}