{
  "type": "Feature",
  "properties": {
    "gn:admin1_code":"14.0",
    "gn:asciiname":"Xixie",
    "gn:country_code":"CN",
    "gn:dem":4067,
    "gn:feature_class":"P",
    "gn:feature_code":"PPL",
    "gn:name":"Xixie",
    "gn:population":0,
    "gn:timezone":"Asia/Shanghai",
    "iso:country":"CN",
    "name:zho_x_preferred":[
        "\u897f\u8c22"
    ],
    "wof:name":"Xixie",
    "wof:placetype":"locality"
},
  "geometry": {"coordinates":[79.51730000000001,31.7923],"type":"Point"}
}