{
  "type": "Feature",
  "properties": {
    "gn:admin1_code":"1.0",
    "gn:asciiname":"Huai'ancun",
    "gn:country_code":"CN",
    "gn:dem":22,
    "gn:feature_class":"P",
    "gn:feature_code":"PPL",
    "gn:name":"Huai\u2019ancun",
    "gn:population":0,
    "gn:timezone":"Asia/Shanghai",
    "iso:country":"CN",
    "name:und_x_variant":[
        "Huai\u2019ancun"
    ],
    "name:zho_x_preferred":[
        "\u6dee\u5b89\u6751"
    ],
    "wof:name":"Huai'ancun",
    "wof:placetype":"locality"
},
  "geometry": {"coordinates":[117.19767,32.63993],"type":"Point"}
}