{
  "type": "Feature",
  "properties": {
    "gn:admin1_code":"32.0",
    "gn:asciiname":"Bailintou",
    "gn:country_code":"CN",
    "gn:dem":1009,
    "gn:feature_class":"P",
    "gn:feature_code":"PPL",
    "gn:name":"Bailintou",
    "gn:population":0,
    "gn:timezone":"Asia/Shanghai",
    "iso:country":"CN",
    "name:zho_x_preferred":[
        "\u67cf\u6797\u5934"
    ],
    "wof:name":"Bailintou",
    "wof:placetype":"locality"
},
  "geometry": {"coordinates":[105.91293,32.60074],"type":"Point"}
}