{
  "type": "Feature",
  "properties": {
    "gn:admin1_code":"2.0",
    "gn:asciiname":"Maoyang",
    "gn:country_code":"CN",
    "gn:dem":77,
    "gn:feature_class":"P",
    "gn:feature_code":"PPL",
    "gn:name":"Maoyang",
    "gn:population":0,
    "gn:timezone":"Asia/Shanghai",
    "iso:country":"CN",
    "name:und_x_variant":[
        "\u8305\u6d0b"
    ],
    "wof:name":"Maoyang",
    "wof:placetype":"locality"
},
  "geometry": {"coordinates":[119.81954,30.48156],"type":"Point"}
}