{
  "type": "Feature",
  "properties": {
    "gn:admin1_code":"14",
    "gn:asciiname":"Shigamu",
    "gn:country_code":"CN",
    "gn:dem":4676,
    "gn:feature_class":"P",
    "gn:feature_code":"PPL",
    "gn:name":"Shigamu",
    "gn:population":0,
    "gn:timezone":"Asia/Urumqi",
    "iso:country":"CN",
    "name:zho_x_preferred":[
        "\u77f3\u560e\u6728"
    ],
    "wof:name":"Shigamu",
    "wof:placetype":"locality"
},
  "geometry": {"coordinates":[87.77079999999999,31.2332],"type":"Point"}
}