{
  "type": "Feature",
  "properties": {
    "gn:admin1_code":"01",
    "gn:asciiname":"Hualinduzhu",
    "gn:cc2":"CN",
    "gn:country_code":"CN",
    "gn:dem":38,
    "gn:feature_class":"P",
    "gn:feature_code":"PPL",
    "gn:name":"Hualinduzhu",
    "gn:population":0,
    "gn:timezone":"Asia/Shanghai",
    "iso:country":"CN",
    "name:und_x_variant":[
        "Hua-lin-tu-chu",
        "Hua-ling-tu-chu",
        "Hua-lin-tu",
        "Hualinduzhu"
    ],
    "wof:name":"Hualinduzhu",
    "wof:placetype":"locality"
},
  "geometry": {"coordinates":[118.31667,30.63333],"type":"Point"}
}