{
  "type": "Feature",
  "properties": {
    "gn:admin1_code":"11.0",
    "gn:asciiname":"Shangyanbei",
    "gn:country_code":"CN",
    "gn:dem":307,
    "gn:feature_class":"P",
    "gn:feature_code":"PPL",
    "gn:name":"Shangyanbei",
    "gn:population":0,
    "gn:timezone":"Asia/Shanghai",
    "iso:country":"CN",
    "name:zho_x_preferred":[
        "\u4e0a\u5ca9\u80cc"
    ],
    "wof:name":"Shangyanbei",
    "wof:placetype":"locality"
},
  "geometry": {"coordinates":[111.05932,26.93088],"type":"Point"}
}