{
  "type": "Feature",
  "properties": {
    "gn:admin1_code":"7.0",
    "gn:asciiname":"Lixikeng",
    "gn:country_code":"CN",
    "gn:dem":425,
    "gn:feature_class":"P",
    "gn:feature_code":"PPL",
    "gn:name":"Lixikeng",
    "gn:population":0,
    "gn:timezone":"Asia/Shanghai",
    "iso:country":"CN",
    "name:und_x_variant":[
        "\u91cc\u897f\u5751",
        "Lixikeng"
    ],
    "wof:name":"Lixikeng",
    "wof:placetype":"locality"
},
  "geometry": {"coordinates":[119.84832,27.07606],"type":"Point"}
}