{
  "type": "Feature",
  "properties": {
    "gn:admin1_code":"24.0",
    "gn:asciiname":"Jianban",
    "gn:country_code":"CN",
    "gn:dem":1471,
    "gn:feature_class":"P",
    "gn:feature_code":"PPL",
    "gn:name":"Jianban",
    "gn:population":0,
    "gn:timezone":"Asia/Shanghai",
    "iso:country":"CN",
    "name:zho_x_preferred":[
        "\u95f4\u677f"
    ],
    "wof:name":"Jianban",
    "wof:placetype":"locality"
},
  "geometry": {"coordinates":[110.96311,35.87814],"type":"Point"}
}