{
  "type": "Feature",
  "properties": {
    "gn:admin1_code":"15.0",
    "gn:asciiname":"Xiwangjiazhuang",
    "gn:country_code":"CN",
    "gn:dem":1970,
    "gn:feature_class":"P",
    "gn:feature_code":"PPL",
    "gn:name":"Xiwangjiazhuang",
    "gn:population":0,
    "gn:timezone":"Asia/Shanghai",
    "iso:country":"CN",
    "name:zho_x_preferred":[
        "\u897f\u738b\u5bb6\u5e84"
    ],
    "wof:name":"Xiwangjiazhuang",
    "wof:placetype":"locality"
},
  "geometry": {"coordinates":[100.812,38.5899],"type":"Point"}
}