{
  "type": "Feature",
  "properties": {
    "gn:admin1_code":"19.0",
    "gn:asciiname":"Zhanglouzi",
    "gn:country_code":"CN",
    "gn:dem":82,
    "gn:feature_class":"P",
    "gn:feature_code":"PPL",
    "gn:name":"Zhanglouzi",
    "gn:population":0,
    "gn:timezone":"Asia/Shanghai",
    "iso:country":"CN",
    "name:zho_x_preferred":[
        "\u5f20\u697c\u5b50"
    ],
    "wof:name":"Zhanglouzi",
    "wof:placetype":"locality"
},
  "geometry": {"coordinates":[123.87358,42.18603],"type":"Point"}
}