{
  "type": "Feature",
  "properties": {
    "gn:admin1_code":"16.0",
    "gn:asciiname":"Yuli",
    "gn:country_code":"CN",
    "gn:dem":500,
    "gn:feature_class":"P",
    "gn:feature_code":"PPL",
    "gn:name":"Yuli",
    "gn:population":0,
    "gn:timezone":"Asia/Shanghai",
    "iso:country":"CN",
    "name:ceb_x_preferred":[
        "Yuli"
    ],
    "name:deu_x_preferred":[
        "Yuli"
    ],
    "name:fra_x_preferred":[
        "Yuli"
    ],
    "name:zho_x_preferred":[
        "\u7389\u91cc"
    ],
    "wof:name":"Yuli",
    "wof:placetype":"locality"
},
  "geometry": {"coordinates":[107.15900000000001,25.162],"type":"Point"}
}