{
  "type": "Feature",
  "properties": {
    "gn:admin1_code":"19",
    "gn:asciiname":"Shizhangzi",
    "gn:country_code":"CN",
    "gn:dem":524,
    "gn:feature_class":"P",
    "gn:feature_code":"PPL",
    "gn:name":"Shizhangzi",
    "gn:population":0,
    "gn:timezone":"Asia/Shanghai",
    "iso:country":"CN",
    "name:zho_x_preferred":[
        "\u53f2\u6756\u5b50"
    ],
    "wof:name":"Shizhangzi",
    "wof:placetype":"locality"
},
  "geometry": {"coordinates":[120.158,41.1333],"type":"Point"}
}