{
  "type": "Feature",
  "properties": {
    "gn:admin1_code":"18.0",
    "gn:asciiname":"Dangni",
    "gn:country_code":"CN",
    "gn:dem":826,
    "gn:feature_class":"P",
    "gn:feature_code":"PPL",
    "gn:name":"Dangni",
    "gn:population":0,
    "gn:timezone":"Asia/Shanghai",
    "iso:country":"CN",
    "name:zho_x_preferred":[
        "\u515a\u4f60"
    ],
    "wof:name":"Dangni",
    "wof:placetype":"locality"
},
  "geometry": {"coordinates":[108.124,26.0331],"type":"Point"}
}