{
  "type": "Feature",
  "properties": {
    "gn:admin1_code":"25",
    "gn:asciiname":"Huangdun",
    "gn:cc2":"CN",
    "gn:country_code":"CN",
    "gn:dem":165,
    "gn:feature_class":"P",
    "gn:feature_code":"PPL",
    "gn:name":"Huangdun",
    "gn:population":0,
    "gn:timezone":"Asia/Shanghai",
    "iso:country":"CN",
    "name:und_x_variant":[
        "Huang-tun-chen",
        "Huang-tun",
        "Huang-tun-tzu",
        "Huangdun"
    ],
    "wof:name":"Huangdun",
    "wof:placetype":"locality"
},
  "geometry": {"coordinates":[119.12111000000002,35.4025],"type":"Point"}
}