{
  "type": "Feature",
  "properties": {
    "gn:admin1_code":"5.0",
    "gn:asciiname":"Jiangjia Gangzi",
    "gn:country_code":"CN",
    "gn:dem":128,
    "gn:feature_class":"P",
    "gn:feature_code":"PPL",
    "gn:name":"Jiangjia Gangzi",
    "gn:population":0,
    "gn:timezone":"Asia/Shanghai",
    "iso:country":"CN",
    "name:zho_x_preferred":[
        "\u59dc\u5bb6\u5c97\u5b50"
    ],
    "wof:name":"Jiangjia Gangzi",
    "wof:placetype":"locality"
},
  "geometry": {"coordinates":[124.92533,45.39319],"type":"Point"}
}