{
  "type": "Feature",
  "properties": {
    "gn:admin1_code":"32.0",
    "gn:asciiname":"Dabaoshang",
    "gn:country_code":"CN",
    "gn:dem":1390,
    "gn:feature_class":"P",
    "gn:feature_code":"PPL",
    "gn:name":"Dabaoshang",
    "gn:population":0,
    "gn:timezone":"Asia/Shanghai",
    "iso:country":"CN",
    "name:zho_x_preferred":[
        "\u5927\u5305\u4e0a"
    ],
    "wof:name":"Dabaoshang",
    "wof:placetype":"locality"
},
  "geometry": {"coordinates":[102.58799999999999,29.49],"type":"Point"}
}