{
  "type": "Feature",
  "properties": {
    "gn:admin1_code":"24.0",
    "gn:asciiname":"Qiaotoucun",
    "gn:country_code":"CN",
    "gn:dem":748,
    "gn:feature_class":"P",
    "gn:feature_code":"PPL",
    "gn:name":"Qiaotoucun",
    "gn:population":0,
    "gn:timezone":"Asia/Shanghai",
    "iso:country":"CN",
    "name:zho_x_preferred":[
        "\u6865\u5934\u6751"
    ],
    "wof:name":"Qiaotoucun",
    "wof:placetype":"locality"
},
  "geometry": {"coordinates":[112.02427,37.40284000000001],"type":"Point"}
}