{
  "type": "Feature",
  "properties": {
    "gn:admin1_code":"32.0",
    "gn:asciiname":"Nanba",
    "gn:country_code":"CN",
    "gn:dem":306,
    "gn:feature_class":"P",
    "gn:feature_code":"PPL",
    "gn:name":"Nanba",
    "gn:population":0,
    "gn:timezone":"Asia/Shanghai",
    "iso:country":"CN",
    "name:zho_x_preferred":[
        "\u5357\u575d"
    ],
    "wof:name":"Nanba",
    "wof:placetype":"locality"
},
  "geometry": {"coordinates":[107.194,30.3096],"type":"Point"}
}