{
  "type": "Feature",
  "properties": {
    "gn:admin1_code":"13.0",
    "gn:asciiname":"Bayitou Lixin",
    "gn:country_code":"CN",
    "gn:dem":1545,
    "gn:feature_class":"P",
    "gn:feature_code":"PPL",
    "gn:name":"Bayitou Lixin",
    "gn:population":0,
    "gn:timezone":"Asia/Shanghai",
    "iso:country":"CN",
    "name:und_x_variant":[
        "\u5df4\u4f9d\u5934\u91cc\u65b0"
    ],
    "wof:name":"Bayitou Lixin",
    "wof:placetype":"locality"
},
  "geometry": {"coordinates":[75.89059,38.98759],"type":"Point"}
}