{
  "type": "Feature",
  "properties": {
    "gn:admin1_code":"25",
    "gn:asciiname":"Zhengchenghou",
    "gn:country_code":"CN",
    "gn:dem":70,
    "gn:feature_class":"P",
    "gn:feature_code":"PPL",
    "gn:name":"Zhengchenghou",
    "gn:population":0,
    "gn:timezone":"Asia/Shanghai",
    "iso:country":"CN",
    "name:zho_x_preferred":[
        "\u90d1\u57ce\u540e"
    ],
    "wof:name":"Zhengchenghou",
    "wof:placetype":"locality"
},
  "geometry": {"coordinates":[116.65900000000001,35.7907],"type":"Point"}
}