{
  "type": "Feature",
  "properties": {
    "gn:admin1_code":"29.0",
    "gn:asciiname":"Tuohai Pingzi",
    "gn:country_code":"CN",
    "gn:dem":1740,
    "gn:feature_class":"P",
    "gn:feature_code":"PPL",
    "gn:name":"Tuohai Pingzi",
    "gn:population":0,
    "gn:timezone":"Asia/Shanghai",
    "iso:country":"CN",
    "name:zho_x_preferred":[
        "\u62d6\u6d77\u576a\u5b50"
    ],
    "wof:name":"Tuohai Pingzi",
    "wof:placetype":"locality"
},
  "geometry": {"coordinates":[103.31999999999999,27.6352],"type":"Point"}
}