{
  "type": "Feature",
  "properties": {
    "gn:admin1_code":"2.0",
    "gn:asciiname":"Maoling",
    "gn:country_code":"CN",
    "gn:dem":95,
    "gn:feature_class":"P",
    "gn:feature_code":"PPL",
    "gn:name":"Maoling",
    "gn:population":0,
    "gn:timezone":"Asia/Shanghai",
    "iso:country":"CN",
    "name:und_x_variant":[
        "Maolingtou"
    ],
    "name:zho_x_preferred":[
        "\u5e3d\u5cad"
    ],
    "name:zho_x_variant":[
        "\u5e3d\u5cad\u5934"
    ],
    "wof:name":"Maoling",
    "wof:placetype":"locality"
},
  "geometry": {"coordinates":[121.26945000000001,28.4112],"type":"Point"}
}