{
  "type": "Feature",
  "properties": {
    "gn:admin1_code":"3",
    "gn:asciiname":"Qishan",
    "gn:country_code":"CN",
    "gn:dem":151,
    "gn:feature_class":"P",
    "gn:feature_code":"PPL",
    "gn:name":"Qishan",
    "gn:population":0,
    "gn:timezone":"Asia/Shanghai",
    "iso:country":"CN",
    "name:ceb_x_preferred":[
        "Qishan"
    ],
    "name:deu_x_preferred":[
        "Qishan"
    ],
    "name:fra_x_preferred":[
        "Qishan"
    ],
    "name:nld_x_preferred":[
        "Qishan"
    ],
    "name:zho_x_preferred":[
        "\u65d7\u5c71"
    ],
    "wof:name":"Qishan",
    "wof:placetype":"locality"
},
  "geometry": {"coordinates":[114.624,25.6459],"type":"Point"}
}