{
  "type": "Feature",
  "properties": {
    "gn:admin1_code":"32.0",
    "gn:asciiname":"Jinggou",
    "gn:country_code":"CN",
    "gn:dem":600,
    "gn:feature_class":"P",
    "gn:feature_code":"PPL",
    "gn:name":"Jinggou",
    "gn:population":0,
    "gn:timezone":"Asia/Shanghai",
    "iso:country":"CN",
    "name:zho_x_preferred":[
        "\u666f\u6c9f"
    ],
    "wof:name":"Jinggou",
    "wof:placetype":"locality"
},
  "geometry": {"coordinates":[103.34399999999999,30.5253],"type":"Point"}
}