{
  "type": "Feature",
  "properties": {
    "gn:admin1_code":"15.0",
    "gn:asciiname":"Yangwa",
    "gn:country_code":"CN",
    "gn:dem":2035,
    "gn:feature_class":"P",
    "gn:feature_code":"PPL",
    "gn:name":"Yangwa",
    "gn:population":0,
    "gn:timezone":"Asia/Shanghai",
    "iso:country":"CN",
    "name:zho_x_preferred":[
        "\u9633\u5c72"
    ],
    "wof:name":"Yangwa",
    "wof:placetype":"locality"
},
  "geometry": {"coordinates":[103.342,35.6617],"type":"Point"}
}