{
  "type": "Feature",
  "properties": {
    "gn:admin1_code":"7",
    "gn:asciiname":"Shanche",
    "gn:country_code":"CN",
    "gn:dem":626,
    "gn:feature_class":"P",
    "gn:feature_code":"PPL",
    "gn:name":"Shanche",
    "gn:population":0,
    "gn:timezone":"Asia/Shanghai",
    "iso:country":"CN",
    "name:und_x_variant":[
        "\u5c71\u8f66"
    ],
    "wof:name":"Shanche",
    "wof:placetype":"locality"
},
  "geometry": {"coordinates":[116.11503999999999,25.43651],"type":"Point"}
}