{
  "type": "Feature",
  "properties": {
    "gn:admin1_code":"9.0",
    "gn:asciiname":"Daxingpo",
    "gn:country_code":"CN",
    "gn:dem":106,
    "gn:feature_class":"P",
    "gn:feature_code":"PPL",
    "gn:name":"Daxingpo",
    "gn:population":0,
    "gn:timezone":"Asia/Shanghai",
    "iso:country":"CN",
    "name:zho_x_preferred":[
        "\u5927\u90a2\u5761"
    ],
    "wof:name":"Daxingpo",
    "wof:placetype":"locality"
},
  "geometry": {"coordinates":[112.5772,32.75857],"type":"Point"}
}