{
  "type": "Feature",
  "properties": {
    "gn:admin1_code":"04",
    "gn:asciiname":"Qiwei",
    "gn:cc2":"CN",
    "gn:country_code":"CN",
    "gn:dem":2,
    "gn:feature_class":"P",
    "gn:feature_code":"PPL",
    "gn:name":"Qiwei",
    "gn:population":0,
    "gn:timezone":"Asia/Shanghai",
    "iso:country":"CN",
    "name:und_x_variant":[
        "Ch\u2019i-wei-kang",
        "Qiweigang",
        "Ch\u2019i-y\u00fc-chiang",
        "Qiwei"
    ],
    "wof:name":"Qiwei",
    "wof:placetype":"locality"
},
  "geometry": {"coordinates":[120.00749999999999,32.02361],"type":"Point"}
}