{
  "type": "Feature",
  "properties": {
    "gn:admin1_code":"3",
    "gn:asciiname":"Zuokeng",
    "gn:country_code":"CN",
    "gn:dem":289,
    "gn:feature_class":"P",
    "gn:feature_code":"PPL",
    "gn:name":"Zuokeng",
    "gn:population":0,
    "gn:timezone":"Asia/Shanghai",
    "iso:country":"CN",
    "name:zho_x_preferred":[
        "\u67de\u5751"
    ],
    "wof:name":"Zuokeng",
    "wof:placetype":"locality"
},
  "geometry": {"coordinates":[114.10299999999999,26.9638],"type":"Point"}
}