{
  "type": "Feature",
  "properties": {
    "gn:admin1_code":"10",
    "gn:asciiname":"Tangzimiao",
    "gn:country_code":"CN",
    "gn:dem":802,
    "gn:feature_class":"P",
    "gn:feature_code":"PPL",
    "gn:name":"Tangzimiao",
    "gn:population":0,
    "gn:timezone":"Asia/Shanghai",
    "iso:country":"CN",
    "name:zho_x_preferred":[
        "\u5858\u5b50\u5e99"
    ],
    "wof:name":"Tangzimiao",
    "wof:placetype":"locality"
},
  "geometry": {"coordinates":[116.08672,40.9587],"type":"Point"}
}