{
  "type": "Feature",
  "properties": {
    "gn:admin1_code":"14.0",
    "gn:asciiname":"Bozong Songguocun",
    "gn:country_code":"CN",
    "gn:dem":4477,
    "gn:feature_class":"P",
    "gn:feature_code":"PPL",
    "gn:name":"Bozong Songguocun",
    "gn:population":0,
    "gn:timezone":"Asia/Urumqi",
    "iso:country":"CN",
    "name:zho_x_preferred":[
        "\u6ce2\u5b97\u677e\u679c\u6751"
    ],
    "wof:name":"Bozong Songguocun",
    "wof:placetype":"locality"
},
  "geometry": {"coordinates":[92.36578,31.36503],"type":"Point"}
}