{
  "type": "Feature",
  "properties": {
    "gn:admin1_code":"12.0",
    "gn:asciiname":"Sanjiadian",
    "gn:country_code":"CN",
    "gn:dem":79,
    "gn:feature_class":"P",
    "gn:feature_code":"PPL",
    "gn:name":"Sanjiadian",
    "gn:population":0,
    "gn:timezone":"Asia/Shanghai",
    "iso:country":"CN",
    "name:zho_x_preferred":[
        "Sanjiadian"
    ],
    "name:zho_x_variant":[
        "\u4e09\u5bb6\u5e97"
    ],
    "wof:name":"Sanjiadian",
    "wof:placetype":"locality"
},
  "geometry": {"coordinates":[115.2602,30.56488],"type":"Point"}
}