{
  "type": "Feature",
  "properties": {
    "gn:admin1_code":"26.0",
    "gn:asciiname":"Jiepingcun",
    "gn:country_code":"CN",
    "gn:dem":965,
    "gn:feature_class":"P",
    "gn:feature_code":"PPL",
    "gn:name":"Jiepingcun",
    "gn:population":0,
    "gn:timezone":"Asia/Shanghai",
    "iso:country":"CN",
    "name:zho_x_preferred":[
        "\u8857\u576a\u6751"
    ],
    "wof:name":"Jiepingcun",
    "wof:placetype":"locality"
},
  "geometry": {"coordinates":[110.68937,33.76128],"type":"Point"}
}