{
  "type": "Feature",
  "properties": {
    "gn:admin1_code":"18.0",
    "gn:asciiname":"Chongdang",
    "gn:country_code":"CN",
    "gn:dem":492,
    "gn:feature_class":"P",
    "gn:feature_code":"PPL",
    "gn:name":"Chongdang",
    "gn:population":0,
    "gn:timezone":"Asia/Shanghai",
    "iso:country":"CN",
    "name:zho_x_preferred":[
        "\u51b2\u5f53"
    ],
    "wof:name":"Chongdang",
    "wof:placetype":"locality"
},
  "geometry": {"coordinates":[109.27200000000001,26.9503],"type":"Point"}
}