{
  "type": "Feature",
  "properties": {
    "gn:admin1_code":"3.0",
    "gn:asciiname":"Datanzui",
    "gn:country_code":"CN",
    "gn:dem":470,
    "gn:feature_class":"P",
    "gn:feature_code":"PPL",
    "gn:name":"Datanzui",
    "gn:population":0,
    "gn:timezone":"Asia/Shanghai",
    "iso:country":"CN",
    "name:und_x_variant":[
        "\u5927\u6f6d\u5634"
    ],
    "wof:name":"Datanzui",
    "wof:placetype":"locality"
},
  "geometry": {"coordinates":[114.76403999999999,28.75002000000001],"type":"Point"}
}