{
  "type": "Feature",
  "properties": {
    "gn:admin1_code":"10.0",
    "gn:asciiname":"Shijiatai",
    "gn:country_code":"CN",
    "gn:dem":682,
    "gn:feature_class":"P",
    "gn:feature_code":"PPL",
    "gn:name":"Shijiatai",
    "gn:population":0,
    "gn:timezone":"Asia/Shanghai",
    "iso:country":"CN",
    "name:und_x_variant":[
        "\u77f3\u5bb6\u53f0"
    ],
    "wof:name":"Shijiatai",
    "wof:placetype":"locality"
},
  "geometry": {"coordinates":[114.03597000000001,38.52887],"type":"Point"}
}