{
  "type": "Feature",
  "properties": {
    "gn:admin1_code":"16.0",
    "gn:asciiname":"Shijiaokou",
    "gn:country_code":"CN",
    "gn:dem":97,
    "gn:feature_class":"P",
    "gn:feature_code":"PPL",
    "gn:name":"Shijiaokou",
    "gn:population":0,
    "gn:timezone":"Asia/Shanghai",
    "iso:country":"CN",
    "name:zho_x_preferred":[
        "\u77f3\u89d2\u53e3"
    ],
    "wof:name":"Shijiaokou",
    "wof:placetype":"locality"
},
  "geometry": {"coordinates":[109.24299999999999,24.5268],"type":"Point"}
}