{
  "type": "Feature",
  "properties": {
    "gn:admin1_code":"30.0",
    "gn:asciiname":"Shebeipu",
    "gn:country_code":"CN",
    "gn:dem":73,
    "gn:feature_class":"P",
    "gn:feature_code":"PPL",
    "gn:name":"Shebeipu",
    "gn:population":0,
    "gn:timezone":"Asia/Shanghai",
    "iso:country":"CN",
    "name:zho_x_preferred":[
        "\u793e\u80cc\u57d4"
    ],
    "wof:name":"Shebeipu",
    "wof:placetype":"locality"
},
  "geometry": {"coordinates":[115.95849,23.23303],"type":"Point"}
}