{
  "type": "Feature",
  "properties": {
    "gn:admin1_code":"16",
    "gn:asciiname":"Lishujiao",
    "gn:country_code":"CN",
    "gn:dem":381,
    "gn:feature_class":"P",
    "gn:feature_code":"PPL",
    "gn:name":"Lishujiao",
    "gn:population":0,
    "gn:timezone":"Asia/Shanghai",
    "iso:country":"CN",
    "name:zho_x_preferred":[
        "\u68a8\u6811\u811a"
    ],
    "wof:name":"Lishujiao",
    "wof:placetype":"locality"
},
  "geometry": {"coordinates":[110.664,25.7987],"type":"Point"}
}