{
  "type": "Feature",
  "properties": {
    "gn:admin1_code":"30",
    "gn:asciiname":"Zhuziping",
    "gn:country_code":"CN",
    "gn:dem":166,
    "gn:feature_class":"P",
    "gn:feature_code":"PPL",
    "gn:name":"Zhuziping",
    "gn:population":0,
    "gn:timezone":"Asia/Shanghai",
    "iso:country":"CN",
    "name:zho_x_preferred":[
        "\u7af9\u5b50\u576a"
    ],
    "wof:name":"Zhuziping",
    "wof:placetype":"locality"
},
  "geometry": {"coordinates":[115.84014999999999,24.17016],"type":"Point"}
}