{
  "type": "Feature",
  "properties": {
    "gn:admin1_code":"11.0",
    "gn:asciiname":"Zhaijiang Dawu",
    "gn:country_code":"CN",
    "gn:dem":109,
    "gn:feature_class":"P",
    "gn:feature_code":"PPL",
    "gn:name":"Zhaijiang Dawu",
    "gn:population":0,
    "gn:timezone":"Asia/Shanghai",
    "iso:country":"CN",
    "name:zho_x_preferred":[
        "\u658b\u6c5f\u5927\u5c4b"
    ],
    "wof:name":"Zhaijiang Dawu",
    "wof:placetype":"locality"
},
  "geometry": {"coordinates":[113.36471,27.50877],"type":"Point"}
}