{
  "type": "Feature",
  "properties": {
    "gn:admin1_code":"23.0",
    "gn:asciiname":"Pujiang",
    "gn:country_code":"CN",
    "gn:dem":6,
    "gn:feature_class":"P",
    "gn:feature_code":"PPLA4",
    "gn:name":"Pujiang",
    "gn:population":0,
    "gn:timezone":"Asia/Shanghai",
    "iso:country":"CN",
    "name:deu_x_preferred":[
        "Pujiang"
    ],
    "name:und_x_variant":[
        "\u6d66\u6c5f"
    ],
    "name:zho_x_preferred":[
        "Pujiang Zhen"
    ],
    "name:zho_x_variant":[
        "\u6d66\u6c5f\u9547"
    ],
    "wof:name":"Pujiang",
    "wof:placetype":"locality"
},
  "geometry": {"coordinates":[121.49581000000001,31.09357],"type":"Point"}
}