{
  "type": "Feature",
  "properties": {
    "gn:admin1_code":"19.0",
    "gn:asciiname":"Qianwazi",
    "gn:country_code":"CN",
    "gn:dem":22,
    "gn:feature_class":"P",
    "gn:feature_code":"PPL",
    "gn:name":"Qianwazi",
    "gn:population":0,
    "gn:timezone":"Asia/Shanghai",
    "iso:country":"CN",
    "name:und_x_variant":[
        "\u524d\u6d3c\u5b50"
    ],
    "name:zho_x_preferred":[
        "\u524d\u6d3c\u5b50"
    ],
    "wof:name":"Qianwazi",
    "wof:placetype":"locality"
},
  "geometry": {"coordinates":[122.66568999999998,39.64979],"type":"Point"}
}