{
  "type": "Feature",
  "properties": {
    "gn:admin1_code":"24.0",
    "gn:asciiname":"Yutiaogou",
    "gn:country_code":"CN",
    "gn:dem":932,
    "gn:feature_class":"P",
    "gn:feature_code":"PPL",
    "gn:name":"Yutiaogou",
    "gn:population":0,
    "gn:timezone":"Asia/Shanghai",
    "iso:country":"CN",
    "name:zho_x_preferred":[
        "\u4e8e\u6761\u6c9f"
    ],
    "wof:name":"Yutiaogou",
    "wof:placetype":"locality"
},
  "geometry": {"coordinates":[112.64917,38.26462],"type":"Point"}
}