{
  "type": "Feature",
  "properties": {
    "gn:admin1_code":"32.0",
    "gn:asciiname":"Yin'en",
    "gn:country_code":"CN",
    "gn:dem":3526,
    "gn:feature_class":"P",
    "gn:feature_code":"PPL",
    "gn:name":"Yin\u2019en",
    "gn:population":0,
    "gn:timezone":"Asia/Shanghai",
    "iso:country":"CN",
    "name:zho_x_preferred":[
        "\u94f6\u6069"
    ],
    "name:zho_x_variant":[
        "Yin\u2019en"
    ],
    "wof:name":"Yin'en",
    "wof:placetype":"locality"
},
  "geometry": {"coordinates":[101.15734,31.36561],"type":"Point"}
}