{
  "type": "Feature",
  "properties": {
    "gn:admin1_code":"5.0",
    "gn:asciiname":"Liushugou",
    "gn:country_code":"CN",
    "gn:dem":484,
    "gn:feature_class":"P",
    "gn:feature_code":"PPL",
    "gn:name":"Liushugou",
    "gn:population":0,
    "gn:timezone":"Asia/Shanghai",
    "iso:country":"CN",
    "name:und_x_variant":[
        "\u67f3\u6811\u6c9f"
    ],
    "wof:name":"Liushugou",
    "wof:placetype":"locality"
},
  "geometry": {"coordinates":[128.9727,42.76523],"type":"Point"}
}