{
  "type": "Feature",
  "properties": {
    "gn:admin1_code":"11.0",
    "gn:asciiname":"Yuanjiawan",
    "gn:country_code":"CN",
    "gn:dem":646,
    "gn:feature_class":"P",
    "gn:feature_code":"PPL",
    "gn:name":"Yuanjiawan",
    "gn:population":0,
    "gn:timezone":"Asia/Shanghai",
    "iso:country":"CN",
    "name:zho_x_preferred":[
        "Yuanjiawan"
    ],
    "name:zho_x_variant":[
        "\u8881\u5bb6\u6e7e"
    ],
    "wof:name":"Yuanjiawan",
    "wof:placetype":"locality"
},
  "geometry": {"coordinates":[111.06716000000002,29.80701],"type":"Point"}
}