{
  "type": "Feature",
  "properties": {
    "gn:admin1_code":"25.0",
    "gn:asciiname":"Sanjiatuan",
    "gn:country_code":"CN",
    "gn:dem":20,
    "gn:feature_class":"P",
    "gn:feature_code":"PPL",
    "gn:name":"Sanjiatuan",
    "gn:population":0,
    "gn:timezone":"Asia/Shanghai",
    "iso:country":"CN",
    "name:zho_x_preferred":[
        "\u4e09\u7532\u7583"
    ],
    "wof:name":"Sanjiatuan",
    "wof:placetype":"locality"
},
  "geometry": {"coordinates":[121.57133,36.80943],"type":"Point"}
}