{
  "type": "Feature",
  "properties": {
    "gn:admin1_code":"26.0",
    "gn:asciiname":"Xugoutai",
    "gn:country_code":"CN",
    "gn:dem":1341,
    "gn:feature_class":"P",
    "gn:feature_code":"PPL",
    "gn:name":"Xugoutai",
    "gn:population":0,
    "gn:timezone":"Asia/Shanghai",
    "iso:country":"CN",
    "name:und_x_variant":[
        "\u5f90\u6c9f\u53f0"
    ],
    "wof:name":"Xugoutai",
    "wof:placetype":"locality"
},
  "geometry": {"coordinates":[107.28852999999999,36.97908],"type":"Point"}
}