{
  "type": "Feature",
  "properties": {
    "gn:admin1_code":"19.0",
    "gn:asciiname":"Xiadian Hedong",
    "gn:country_code":"CN",
    "gn:dem":337,
    "gn:feature_class":"P",
    "gn:feature_code":"PPL",
    "gn:name":"Xiadian Hedong",
    "gn:population":0,
    "gn:timezone":"Asia/Shanghai",
    "iso:country":"CN",
    "name:zho_x_preferred":[
        "\u4e0b\u5e97\u6cb3\u4e1c"
    ],
    "wof:name":"Xiadian Hedong",
    "wof:placetype":"locality"
},
  "geometry": {"coordinates":[119.82611,41.26437],"type":"Point"}
}