{
  "type": "Feature",
  "properties": {
    "gn:admin1_code":"8.0",
    "gn:asciiname":"Houmaojia",
    "gn:country_code":"CN",
    "gn:dem":210,
    "gn:feature_class":"P",
    "gn:feature_code":"PPL",
    "gn:name":"Houmaojia",
    "gn:population":0,
    "gn:timezone":"Asia/Shanghai",
    "iso:country":"CN",
    "name:zho_x_preferred":[
        "\u540e\u6bdb\u5bb6"
    ],
    "wof:name":"Houmaojia",
    "wof:placetype":"locality"
},
  "geometry": {"coordinates":[123.21505000000001,47.64761],"type":"Point"}
}