{
  "type": "Feature",
  "properties": {
    "gn:admin1_code":"24",
    "gn:asciiname":"Hezhu",
    "gn:country_code":"CN",
    "gn:dem":1019,
    "gn:feature_class":"P",
    "gn:feature_code":"PPL",
    "gn:name":"Hezhu",
    "gn:population":0,
    "gn:timezone":"Asia/Shanghai",
    "iso:country":"CN",
    "name:und_x_variant":[
        "Xingyu",
        "Hsing-y\u00fc",
        "Ho-chu",
        "Hezhu"
    ],
    "name:zho_x_preferred":[
        "\u6cb3\u6e1a"
    ],
    "wof:name":"Hezhu",
    "wof:placetype":"locality"
},
  "geometry": {"coordinates":[112.07753,35.66500999999999],"type":"Point"}
}