{
  "type": "Feature",
  "properties": {
    "gn:admin1_code":"29.0",
    "gn:asciiname":"Xinguanzhang",
    "gn:country_code":"CN",
    "gn:dem":1363,
    "gn:feature_class":"P",
    "gn:feature_code":"PPL",
    "gn:name":"Xinguanzhang",
    "gn:population":0,
    "gn:timezone":"Asia/Shanghai",
    "iso:country":"CN",
    "name:zho_x_preferred":[
        "\u65b0\u5173\u748b"
    ],
    "wof:name":"Xinguanzhang",
    "wof:placetype":"locality"
},
  "geometry": {"coordinates":[98.39870000000001,24.8897],"type":"Point"}
}