{
  "type": "Feature",
  "properties": {
    "gn:admin1_code":"10.0",
    "gn:asciiname":"Xiwangzhuang",
    "gn:country_code":"CN",
    "gn:dem":491,
    "gn:feature_class":"P",
    "gn:feature_code":"PPL",
    "gn:name":"Xiwangzhuang",
    "gn:population":0,
    "gn:timezone":"Asia/Shanghai",
    "iso:country":"CN",
    "name:zho_x_preferred":[
        "\u897f\u738b\u5e84"
    ],
    "wof:name":"Xiwangzhuang",
    "wof:placetype":"locality"
},
  "geometry": {"coordinates":[113.68917999999999,38.32071],"type":"Point"}
}