{
  "type": "Feature",
  "properties": {
    "gn:admin1_code":"19.0",
    "gn:asciiname":"Maodeyingzi",
    "gn:country_code":"CN",
    "gn:dem":294,
    "gn:feature_class":"P",
    "gn:feature_code":"PPL",
    "gn:name":"Maodeyingzi",
    "gn:population":0,
    "gn:timezone":"Asia/Shanghai",
    "iso:country":"CN",
    "name:und_x_variant":[
        "\u6bdb\u5fb7\u8425\u5b50"
    ],
    "name:zho_x_preferred":[
        "\u6bdb\u5fb7\u8425\u5b50"
    ],
    "wof:name":"Maodeyingzi",
    "wof:placetype":"locality"
},
  "geometry": {"coordinates":[121.22801,41.99819],"type":"Point"}
}