{
  "type": "Feature",
  "properties": {
    "gn:admin1_code":"12.0",
    "gn:asciiname":"Wangchenzhou",
    "gn:country_code":"CN",
    "gn:dem":21,
    "gn:feature_class":"P",
    "gn:feature_code":"PPL",
    "gn:name":"Wangchenzhou",
    "gn:population":0,
    "gn:timezone":"Asia/Shanghai",
    "iso:country":"CN",
    "name:und_x_variant":[
        "\u738b\u9648\u6d32"
    ],
    "wof:name":"Wangchenzhou",
    "wof:placetype":"locality"
},
  "geometry": {"coordinates":[114.80275,30.37897],"type":"Point"}
}