{
  "type": "Feature",
  "properties": {
    "gn:admin1_code":"26.0",
    "gn:asciiname":"Shuimoping",
    "gn:country_code":"CN",
    "gn:dem":1488,
    "gn:feature_class":"P",
    "gn:feature_code":"PPL",
    "gn:name":"Shuimoping",
    "gn:population":0,
    "gn:timezone":"Asia/Shanghai",
    "iso:country":"CN",
    "name:und_x_variant":[
        "\u6c34\u78e8\u576a"
    ],
    "wof:name":"Shuimoping",
    "wof:placetype":"locality"
},
  "geometry": {"coordinates":[107.97272,33.76884],"type":"Point"}
}