{
  "type": "Feature",
  "properties": {
    "gn:admin1_code":"26.0",
    "gn:asciiname":"Qili Miaocun",
    "gn:country_code":"CN",
    "gn:dem":1218,
    "gn:feature_class":"P",
    "gn:feature_code":"PPL",
    "gn:name":"Qili Miaocun",
    "gn:population":0,
    "gn:timezone":"Asia/Shanghai",
    "iso:country":"CN",
    "name:zho_x_preferred":[
        "\u4e03\u91cc\u5e99\u6751"
    ],
    "wof:name":"Qili Miaocun",
    "wof:placetype":"locality"
},
  "geometry": {"coordinates":[110.61199999999999,38.9897],"type":"Point"}
}