{
  "type": "Feature",
  "properties": {
    "gn:admin1_code":"7.0",
    "gn:asciiname":"Shangdongshan",
    "gn:country_code":"CN",
    "gn:dem":369,
    "gn:feature_class":"P",
    "gn:feature_code":"PPL",
    "gn:name":"Shangdongshan",
    "gn:population":0,
    "gn:timezone":"Asia/Shanghai",
    "iso:country":"CN",
    "name:zho_x_preferred":[
        "\u4e0a\u4e1c\u5c71"
    ],
    "wof:name":"Shangdongshan",
    "wof:placetype":"locality"
},
  "geometry": {"coordinates":[119.35375000000001,26.36112],"type":"Point"}
}