{
  "type": "Feature",
  "properties": {
    "gn:admin1_code":"07",
    "gn:asciiname":"Chenkengwei",
    "gn:country_code":"CN",
    "gn:dem":703,
    "gn:feature_class":"P",
    "gn:feature_code":"PPL",
    "gn:name":"Chenkengwei",
    "gn:population":0,
    "gn:timezone":"Asia/Shanghai",
    "iso:country":"CN",
    "name:zho_x_preferred":[
        "\u9648\u5751\u5c3e"
    ],
    "wof:name":"Chenkengwei",
    "wof:placetype":"locality"
},
  "geometry": {"coordinates":[117.08741000000001,25.46136],"type":"Point"}
}