{
  "type": "Feature",
  "properties": {
    "gn:admin1_code":"07",
    "gn:asciiname":"Poshui",
    "gn:country_code":"CN",
    "gn:dem":622,
    "gn:feature_class":"P",
    "gn:feature_code":"PPL",
    "gn:name":"Poshui",
    "gn:population":0,
    "gn:timezone":"Asia/Shanghai",
    "iso:country":"CN",
    "name:zho_x_preferred":[
        "\u6cfc\u6c34"
    ],
    "wof:name":"Poshui",
    "wof:placetype":"locality"
},
  "geometry": {"coordinates":[117.59139,25.825],"type":"Point"}
}