{
  "type": "Feature",
  "properties": {
    "gn:admin1_code":"8.0",
    "gn:asciiname":"Hengshan",
    "gn:country_code":"CN",
    "gn:dem":440,
    "gn:feature_class":"P",
    "gn:feature_code":"PPL",
    "gn:name":"Hengshan",
    "gn:population":0,
    "gn:timezone":"Asia/Shanghai",
    "iso:country":"CN",
    "name:zho_x_preferred":[
        "\u6a2a\u5c71"
    ],
    "wof:name":"Hengshan",
    "wof:placetype":"locality"
},
  "geometry": {"coordinates":[126.38240999999999,49.27157],"type":"Point"}
}