{
  "type": "Feature",
  "properties": {
    "gn:admin1_code":"32.0",
    "gn:asciiname":"Yinjia Wanzi",
    "gn:country_code":"CN",
    "gn:dem":2012,
    "gn:feature_class":"P",
    "gn:feature_code":"PPL",
    "gn:name":"Yinjia Wanzi",
    "gn:population":0,
    "gn:timezone":"Asia/Shanghai",
    "iso:country":"CN",
    "name:zho_x_preferred":[
        "\u6bb7\u5bb6\u5f2f\u5b50"
    ],
    "wof:name":"Yinjia Wanzi",
    "wof:placetype":"locality"
},
  "geometry": {"coordinates":[102.52500000000001,26.6576],"type":"Point"}
}