{
  "type": "Feature",
  "properties": {
    "gn:admin1_code":"11.0",
    "gn:asciiname":"Liuzhai",
    "gn:country_code":"CN",
    "gn:dem":423,
    "gn:feature_class":"P",
    "gn:feature_code":"PPL",
    "gn:name":"Liuzhai",
    "gn:population":0,
    "gn:timezone":"Asia/Shanghai",
    "iso:country":"CN",
    "name:zho_x_preferred":[
        "\u67f3\u5be8"
    ],
    "wof:name":"Liuzhai",
    "wof:placetype":"locality"
},
  "geometry": {"coordinates":[110.23138,26.39457],"type":"Point"}
}