{
  "type": "Feature",
  "properties": {
    "gn:admin1_code":"4.0",
    "gn:asciiname":"Xibei",
    "gn:country_code":"CN",
    "gn:dem":6,
    "gn:feature_class":"P",
    "gn:feature_code":"PPLA4",
    "gn:name":"Xibei",
    "gn:population":0,
    "gn:timezone":"Asia/Shanghai",
    "iso:country":"CN",
    "name:und_x_variant":[
        "Xibei Zhen"
    ],
    "name:zho_x_preferred":[
        "\u9521\u5317"
    ],
    "name:zho_x_variant":[
        "\u9521\u5317\u9547"
    ],
    "wof:name":"Xibei",
    "wof:placetype":"locality"
},
  "geometry": {"coordinates":[120.43219999999999,31.65759000000001],"type":"Point"}
}