{
  "type": "Feature",
  "properties": {
    "gn:admin1_code":"30",
    "gn:asciiname":"Xincun",
    "gn:country_code":"CN",
    "gn:dem":117,
    "gn:feature_class":"P",
    "gn:feature_code":"PPL",
    "gn:name":"Xincun",
    "gn:population":0,
    "gn:timezone":"Asia/Shanghai",
    "iso:country":"CN",
    "name:zho_x_preferred":[
        "\u65b0\u6751"
    ],
    "wof:name":"Xincun",
    "wof:placetype":"locality"
},
  "geometry": {"coordinates":[115.68989999999999,23.73793],"type":"Point"}
}