{
  "type": "Feature",
  "properties": {
    "gn:admin1_code":"30.0",
    "gn:asciiname":"Huanshi",
    "gn:country_code":"CN",
    "gn:dem":4,
    "gn:feature_class":"P",
    "gn:feature_code":"PPLA4",
    "gn:name":"Huanshi",
    "gn:population":0,
    "gn:timezone":"Asia/Shanghai",
    "iso:country":"CN",
    "name:und_x_variant":[
        "Huanshi Jiedao",
        "\u73af\u5e02\u8857\u9053"
    ],
    "name:zho_x_preferred":[
        "\u73af\u5e02"
    ],
    "wof:name":"Huanshi",
    "wof:placetype":"locality"
},
  "geometry": {"coordinates":[113.06659999999999,22.59357],"type":"Point"}
}