{
  "type": "Feature",
  "properties": {
    "gn:admin1_code":"33.0",
    "gn:asciiname":"Mojiagou",
    "gn:country_code":"CN",
    "gn:dem":713,
    "gn:feature_class":"P",
    "gn:feature_code":"PPL",
    "gn:name":"Mojiagou",
    "gn:population":0,
    "gn:timezone":"Asia/Shanghai",
    "iso:country":"CN",
    "name:zho_x_preferred":[
        "\u83ab\u5bb6\u6c9f"
    ],
    "wof:name":"Mojiagou",
    "wof:placetype":"locality"
},
  "geometry": {"coordinates":[107.04900000000001,29.0673],"type":"Point"}
}