{
  "type": "Feature",
  "properties": {
    "gn:admin1_code":"4.0",
    "gn:asciiname":"Changdongcun",
    "gn:country_code":"CN",
    "gn:dem":5,
    "gn:feature_class":"P",
    "gn:feature_code":"PPL",
    "gn:name":"Changdongcun",
    "gn:population":0,
    "gn:timezone":"Asia/Shanghai",
    "iso:country":"CN",
    "name:und_x_variant":[
        "Changdong",
        "Changdongcun"
    ],
    "name:zho_x_preferred":[
        "\u5382\u4e1c"
    ],
    "name:zho_x_variant":[
        "\u5382\u4e1c\u6751"
    ],
    "wof:name":"Changdongcun",
    "wof:placetype":"locality"
},
  "geometry": {"coordinates":[121.28798999999999,31.8939],"type":"Point"}
}