{
  "type": "Feature",
  "properties": {
    "gn:admin1_code":"4.0",
    "gn:asciiname":"Beiliuxiang",
    "gn:country_code":"CN",
    "gn:dem":22,
    "gn:feature_class":"P",
    "gn:feature_code":"PPL",
    "gn:name":"Beiliuxiang",
    "gn:population":0,
    "gn:timezone":"Asia/Shanghai",
    "iso:country":"CN",
    "name:zho_x_preferred":[
        "\u5317\u5218\u5df7"
    ],
    "wof:name":"Beiliuxiang",
    "wof:placetype":"locality"
},
  "geometry": {"coordinates":[119.36747,31.85815],"type":"Point"}
}