{
  "type": "Feature",
  "properties": {
    "gn:admin1_code":"08",
    "gn:asciiname":"Qianshao Nongchang",
    "gn:country_code":"CN",
    "gn:dem":45,
    "gn:feature_class":"P",
    "gn:feature_code":"PPLF",
    "gn:name":"Qianshao Nongchang",
    "gn:population":0,
    "gn:timezone":"Asia/Shanghai",
    "iso:country":"CN",
    "wof:name":"Qianshao Nongchang",
    "wof:placetype":"locality"
},
  "geometry": {"coordinates":[134.10917000000001,47.99806],"type":"Point"}
}