{
  "type": "Feature",
  "properties": {
    "gn:admin1_code":"25.0",
    "gn:asciiname":"Heya",
    "gn:country_code":"CN",
    "gn:dem":107,
    "gn:feature_class":"P",
    "gn:feature_code":"PPL",
    "gn:name":"Heya",
    "gn:population":0,
    "gn:timezone":"Asia/Shanghai",
    "iso:country":"CN",
    "name:ceb_x_preferred":[
        "Heya"
    ],
    "name:swe_x_preferred":[
        "Heya"
    ],
    "name:zho_x_preferred":[
        "\u6cb3\u5d16"
    ],
    "wof:name":"Heya",
    "wof:placetype":"locality"
},
  "geometry": {"coordinates":[120.65974,37.22619],"type":"Point"}
}