{
  "type": "Feature",
  "properties": {
    "gn:admin1_code":"9.0",
    "gn:asciiname":"Beiwangjialing",
    "gn:country_code":"CN",
    "gn:dem":312,
    "gn:feature_class":"P",
    "gn:feature_code":"PPL",
    "gn:name":"Beiwangjialing",
    "gn:population":0,
    "gn:timezone":"Asia/Shanghai",
    "iso:country":"CN",
    "name:zho_x_preferred":[
        "\u5317\u738b\u5bb6\u5cad"
    ],
    "wof:name":"Beiwangjialing",
    "wof:placetype":"locality"
},
  "geometry": {"coordinates":[112.39995,34.87048],"type":"Point"}
}