{
  "type": "Feature",
  "properties": {
    "gn:admin1_code":"30.0",
    "gn:asciiname":"Chadiping",
    "gn:country_code":"CN",
    "gn:dem":54,
    "gn:feature_class":"P",
    "gn:feature_code":"PPL",
    "gn:name":"Chadiping",
    "gn:population":0,
    "gn:timezone":"Asia/Shanghai",
    "iso:country":"CN",
    "name:zho_x_preferred":[
        "\u8336\u5730\u576a"
    ],
    "wof:name":"Chadiping",
    "wof:placetype":"locality"
},
  "geometry": {"coordinates":[112.33208999999999,23.64256],"type":"Point"}
}