{
  "type": "Feature",
  "properties": {
    "gn:admin1_code":"3.0",
    "gn:asciiname":"Laohuwo",
    "gn:country_code":"CN",
    "gn:dem":98,
    "gn:feature_class":"P",
    "gn:feature_code":"PPL",
    "gn:name":"Laohuwo",
    "gn:population":0,
    "gn:timezone":"Asia/Shanghai",
    "iso:country":"CN",
    "name:zho_x_preferred":[
        "\u8001\u864e\u7a9d"
    ],
    "wof:name":"Laohuwo",
    "wof:placetype":"locality"
},
  "geometry": {"coordinates":[118.29035,28.68848],"type":"Point"}
}