{
  "type": "Feature",
  "properties": {
    "gn:admin1_code":"32.0",
    "gn:asciiname":"Xiayingba",
    "gn:country_code":"CN",
    "gn:dem":432,
    "gn:feature_class":"P",
    "gn:feature_code":"PPL",
    "gn:name":"Xiayingba",
    "gn:population":0,
    "gn:timezone":"Asia/Shanghai",
    "iso:country":"CN",
    "name:zho_x_preferred":[
        "\u4e0b\u8425\u575d"
    ],
    "wof:name":"Xiayingba",
    "wof:placetype":"locality"
},
  "geometry": {"coordinates":[105.33,28.1097],"type":"Point"}
}