{
  "type": "Feature",
  "properties": {
    "gn:admin1_code":"14.0",
    "gn:asciiname":"Bogagunba",
    "gn:country_code":"CN",
    "gn:dem":4092,
    "gn:feature_class":"P",
    "gn:feature_code":"PPL",
    "gn:name":"Bogagunba",
    "gn:population":0,
    "gn:timezone":"Asia/Urumqi",
    "iso:country":"CN",
    "name:zho_x_preferred":[
        "\u6ce2\u560e\u68cd\u5df4"
    ],
    "wof:name":"Bogagunba",
    "wof:placetype":"locality"
},
  "geometry": {"coordinates":[91.41826,28.38859],"type":"Point"}
}