{
  "type": "Feature",
  "properties": {
    "gn:admin1_code":"12.0",
    "gn:asciiname":"Tongxinyuan",
    "gn:country_code":"CN",
    "gn:dem":30,
    "gn:feature_class":"P",
    "gn:feature_code":"PPL",
    "gn:name":"Tongxinyuan",
    "gn:population":0,
    "gn:timezone":"Asia/Shanghai",
    "iso:country":"CN",
    "name:zho_x_preferred":[
        "\u540c\u5fc3\u57b8"
    ],
    "wof:name":"Tongxinyuan",
    "wof:placetype":"locality"
},
  "geometry": {"coordinates":[113.63782,29.87237],"type":"Point"}
}