{
  "type": "Feature",
  "properties": {
    "gn:admin1_code":"18",
    "gn:asciiname":"Duanjia Taizi",
    "gn:country_code":"CN",
    "gn:dem":1369,
    "gn:feature_class":"P",
    "gn:feature_code":"PPL",
    "gn:name":"Duanjia Taizi",
    "gn:population":0,
    "gn:timezone":"Asia/Shanghai",
    "iso:country":"CN",
    "name:zho_x_preferred":[
        "\u6bb5\u5bb6\u53f0\u5b50"
    ],
    "wof:name":"Duanjia Taizi",
    "wof:placetype":"locality"
},
  "geometry": {"coordinates":[104.648,25.3868],"type":"Point"}
}