{
  "type": "Feature",
  "properties": {
    "gn:admin1_code":"24.0",
    "gn:asciiname":"Niangou",
    "gn:country_code":"CN",
    "gn:dem":1159,
    "gn:feature_class":"P",
    "gn:feature_code":"PPL",
    "gn:name":"Niangou",
    "gn:population":0,
    "gn:timezone":"Asia/Shanghai",
    "iso:country":"CN",
    "name:zho_x_preferred":[
        "\u78be\u6c9f"
    ],
    "wof:name":"Niangou",
    "wof:placetype":"locality"
},
  "geometry": {"coordinates":[112.48408999999999,38.29563],"type":"Point"}
}