{
  "type": "Feature",
  "properties": {
    "gn:admin1_code":"14.0",
    "gn:asciiname":"Yongya",
    "gn:country_code":"CN",
    "gn:dem":4565,
    "gn:feature_class":"P",
    "gn:feature_code":"PPL",
    "gn:name":"Yongya",
    "gn:population":0,
    "gn:timezone":"Asia/Urumqi",
    "iso:country":"CN",
    "name:zho_x_preferred":[
        "\u62e5\u4e9a"
    ],
    "wof:name":"Yongya",
    "wof:placetype":"locality"
},
  "geometry": {"coordinates":[97.04652,30.84895],"type":"Point"}
}