{
  "type": "Feature",
  "properties": {
    "gn:admin1_code":"5.0",
    "gn:asciiname":"Xingxi",
    "gn:country_code":"CN",
    "gn:dem":437,
    "gn:feature_class":"P",
    "gn:feature_code":"PPL",
    "gn:name":"Xingxi",
    "gn:population":0,
    "gn:timezone":"Asia/Shanghai",
    "iso:country":"CN",
    "name:und_x_variant":[
        "\u5174\u897f",
        "Xingxicun",
        "\u5174\u897f\u6751"
    ],
    "wof:name":"Xingxi",
    "wof:placetype":"locality"
},
  "geometry": {"coordinates":[128.99132,42.59057],"type":"Point"}
}