{
  "type": "Feature",
  "properties": {
    "gn:admin1_code":"10",
    "gn:asciiname":"Dongyaogou",
    "gn:country_code":"CN",
    "gn:dem":681,
    "gn:feature_class":"P",
    "gn:feature_code":"PPL",
    "gn:name":"Dongyaogou",
    "gn:population":0,
    "gn:timezone":"Asia/Shanghai",
    "iso:country":"CN",
    "name:zho_x_preferred":[
        "\u4e1c\u7a91\u6c9f"
    ],
    "wof:name":"Dongyaogou",
    "wof:placetype":"locality"
},
  "geometry": {"coordinates":[114.98633999999998,40.32478],"type":"Point"}
}