{
  "type": "Feature",
  "properties": {
    "gn:admin1_code":"26.0",
    "gn:asciiname":"Guoshangounao",
    "gn:country_code":"CN",
    "gn:dem":1128,
    "gn:feature_class":"P",
    "gn:feature_code":"PPL",
    "gn:name":"Guoshangounao",
    "gn:population":0,
    "gn:timezone":"Asia/Shanghai",
    "iso:country":"CN",
    "name:zho_x_preferred":[
        "\u90ed\u5c71\u6c9f\u8111"
    ],
    "wof:name":"Guoshangounao",
    "wof:placetype":"locality"
},
  "geometry": {"coordinates":[109.58965000000001,32.71477],"type":"Point"}
}