{
  "type": "Feature",
  "properties": {
    "gn:admin1_code":"29.0",
    "gn:asciiname":"Yangbachong",
    "gn:country_code":"CN",
    "gn:dem":2166,
    "gn:feature_class":"P",
    "gn:feature_code":"PPL",
    "gn:name":"Yangbachong",
    "gn:population":0,
    "gn:timezone":"Asia/Shanghai",
    "iso:country":"CN",
    "name:zho_x_preferred":[
        "\u7f8a\u575d\u51b2"
    ],
    "wof:name":"Yangbachong",
    "wof:placetype":"locality"
},
  "geometry": {"coordinates":[102.95999999999999,25.0494],"type":"Point"}
}