{
  "type": "Feature",
  "properties": {
    "gn:admin1_code":"19.0",
    "gn:asciiname":"Wukunzhangzi",
    "gn:country_code":"CN",
    "gn:dem":542,
    "gn:feature_class":"P",
    "gn:feature_code":"PPL",
    "gn:name":"Wukunzhangzi",
    "gn:population":0,
    "gn:timezone":"Asia/Shanghai",
    "iso:country":"CN",
    "name:und_x_variant":[
        "\u5434\u5764\u6756\u5b50"
    ],
    "name:zho_x_preferred":[
        "\u5434\u5764\u6756\u5b50"
    ],
    "wof:name":"Wukunzhangzi",
    "wof:placetype":"locality"
},
  "geometry": {"coordinates":[119.42719,40.56658],"type":"Point"}
}