{
  "type": "Feature",
  "properties": {
    "gn:admin1_code":"32.0",
    "gn:asciiname":"Xingangping",
    "gn:country_code":"CN",
    "gn:dem":487,
    "gn:feature_class":"P",
    "gn:feature_code":"PPL",
    "gn:name":"Xingangping",
    "gn:population":0,
    "gn:timezone":"Asia/Shanghai",
    "iso:country":"CN",
    "name:zho_x_preferred":[
        "\u65b0\u5c97\u576a"
    ],
    "wof:name":"Xingangping",
    "wof:placetype":"locality"
},
  "geometry": {"coordinates":[106.59399999999999,31.8269],"type":"Point"}
}