{
  "type": "Feature",
  "properties": {
    "gn:admin1_code":"04",
    "gn:asciiname":"Xiaoyangang",
    "gn:cc2":"CN",
    "gn:country_code":"CN",
    "gn:dem":3,
    "gn:feature_class":"P",
    "gn:feature_code":"PPL",
    "gn:name":"Xiaoyangang",
    "gn:population":0,
    "gn:timezone":"Asia/Shanghai",
    "iso:country":"CN",
    "name:und_x_variant":[
        "Hsiao-yu-kang",
        "Xiaoyangang"
    ],
    "wof:name":"Xiaoyangang",
    "wof:placetype":"locality"
},
  "geometry": {"coordinates":[120.71417,31.12722],"type":"Point"}
}