{
  "type": "Feature",
  "properties": {
    "gn:admin1_code":"7.0",
    "gn:asciiname":"Zouhuan",
    "gn:country_code":"CN",
    "gn:dem":776,
    "gn:feature_class":"P",
    "gn:feature_code":"PPL",
    "gn:name":"Zouhuan",
    "gn:population":0,
    "gn:timezone":"Asia/Shanghai",
    "iso:country":"CN",
    "name:zho_x_preferred":[
        "\u90b9\u5ba6"
    ],
    "wof:name":"Zouhuan",
    "wof:placetype":"locality"
},
  "geometry": {"coordinates":[118.46167,26.04122000000001],"type":"Point"}
}