{
  "type": "Feature",
  "properties": {
    "gn:admin1_code":"12.0",
    "gn:asciiname":"Lujiaqiao",
    "gn:country_code":"CN",
    "gn:dem":28,
    "gn:feature_class":"P",
    "gn:feature_code":"PPL",
    "gn:name":"L\u00fcjiaqiao",
    "gn:population":0,
    "gn:timezone":"Asia/Shanghai",
    "iso:country":"CN",
    "name:und_x_variant":[
        "L\u00fcjiaqiao"
    ],
    "name:zho_x_preferred":[
        "\u5415\u5bb6\u6865"
    ],
    "wof:name":"Lujiaqiao",
    "wof:placetype":"locality"
},
  "geometry": {"coordinates":[113.35669,30.13096],"type":"Point"}
}