{
  "type": "Feature",
  "properties": {
    "gn:admin1_code":"29.0",
    "gn:asciiname":"Huajiaoyuan",
    "gn:country_code":"CN",
    "gn:dem":2303,
    "gn:feature_class":"P",
    "gn:feature_code":"PPL",
    "gn:name":"Huajiaoyuan",
    "gn:population":0,
    "gn:timezone":"Asia/Shanghai",
    "iso:country":"CN",
    "name:zho_x_preferred":[
        "\u82b1\u6912\u56ed"
    ],
    "wof:name":"Huajiaoyuan",
    "wof:placetype":"locality"
},
  "geometry": {"coordinates":[99.8907,25.6611],"type":"Point"}
}