{
  "type": "Feature",
  "properties": {
    "gn:admin1_code":"25.0",
    "gn:asciiname":"Qianchangwancun",
    "gn:country_code":"CN",
    "gn:dem":63,
    "gn:feature_class":"P",
    "gn:feature_code":"PPL",
    "gn:name":"Qianchangwancun",
    "gn:population":0,
    "gn:timezone":"Asia/Shanghai",
    "iso:country":"CN",
    "name:zho_x_preferred":[
        "\u524d\u957f\u6e7e\u6751"
    ],
    "wof:name":"Qianchangwancun",
    "wof:placetype":"locality"
},
  "geometry": {"coordinates":[122.26183,37.25669],"type":"Point"}
}