{
  "type": "Feature",
  "properties": {
    "gn:admin1_code":"16.0",
    "gn:asciiname":"Shanglongjiang",
    "gn:country_code":"CN",
    "gn:dem":843,
    "gn:feature_class":"P",
    "gn:feature_code":"PPL",
    "gn:name":"Shanglongjiang",
    "gn:population":0,
    "gn:timezone":"Asia/Shanghai",
    "iso:country":"CN",
    "name:zho_x_preferred":[
        "\u4e0a\u9647\u6c5f"
    ],
    "wof:name":"Shanglongjiang",
    "wof:placetype":"locality"
},
  "geometry": {"coordinates":[106.709,24.4985],"type":"Point"}
}