{
  "type": "Feature",
  "properties": {
    "gn:admin1_code":"16.0",
    "gn:asciiname":"Nalan",
    "gn:country_code":"CN",
    "gn:dem":111,
    "gn:feature_class":"P",
    "gn:feature_code":"PPL",
    "gn:name":"Nalan",
    "gn:population":0,
    "gn:timezone":"Asia/Shanghai",
    "iso:country":"CN",
    "name:tur_x_preferred":[
        "Nalan"
    ],
    "name:zho_x_preferred":[
        "\u90a3\u5170"
    ],
    "wof:name":"Nalan",
    "wof:placetype":"locality"
},
  "geometry": {"coordinates":[108.703,22.855],"type":"Point"}
}