{
  "type": "Feature",
  "properties": {
    "gn:admin1_code":"26.0",
    "gn:asciiname":"Dayuan",
    "gn:country_code":"CN",
    "gn:dem":806,
    "gn:feature_class":"P",
    "gn:feature_code":"PPL",
    "gn:name":"Dayuan",
    "gn:population":0,
    "gn:timezone":"Asia/Shanghai",
    "iso:country":"CN",
    "name:und_x_variant":[
        "\u5927\u586c"
    ],
    "wof:name":"Dayuan",
    "wof:placetype":"locality"
},
  "geometry": {"coordinates":[107.49514000000001,34.52789],"type":"Point"}
}