{
  "type": "Feature",
  "properties": {
    "gn:admin1_code":"1.0",
    "gn:asciiname":"Xianglicun",
    "gn:country_code":"CN",
    "gn:dem":157,
    "gn:feature_class":"P",
    "gn:feature_code":"PPL",
    "gn:name":"Xianglicun",
    "gn:population":0,
    "gn:timezone":"Asia/Shanghai",
    "iso:country":"CN",
    "name:zho_x_preferred":[
        "\u7965\u91cc\u6751"
    ],
    "wof:name":"Xianglicun",
    "wof:placetype":"locality"
},
  "geometry": {"coordinates":[117.78333000000001,29.86951],"type":"Point"}
}