{
  "type": "Feature",
  "properties": {
    "gn:admin1_code":"32.0",
    "gn:asciiname":"Qiamang",
    "gn:country_code":"CN",
    "gn:dem":3525,
    "gn:feature_class":"P",
    "gn:feature_code":"PPL",
    "gn:name":"Qiamang",
    "gn:population":0,
    "gn:timezone":"Asia/Shanghai",
    "iso:country":"CN",
    "name:zho_x_preferred":[
        "\u6070\u8292"
    ],
    "wof:name":"Qiamang",
    "wof:placetype":"locality"
},
  "geometry": {"coordinates":[101.03700000000001,32.5224],"type":"Point"}
}