{
  "type": "Feature",
  "properties": {
    "gn:admin1_code":"21.0",
    "gn:asciiname":"Chelugou",
    "gn:country_code":"CN",
    "gn:dem":1812,
    "gn:feature_class":"P",
    "gn:feature_code":"PPL",
    "gn:name":"Chelugou",
    "gn:population":0,
    "gn:timezone":"Asia/Shanghai",
    "iso:country":"CN",
    "name:zho_x_preferred":[
        "\u8f66\u8def\u6c9f"
    ],
    "wof:name":"Chelugou",
    "wof:placetype":"locality"
},
  "geometry": {"coordinates":[106.4314,36.2662],"type":"Point"}
}