{
  "type": "Feature",
  "properties": {
    "gn:admin1_code":"11.0",
    "gn:asciiname":"Yanquanxu",
    "gn:country_code":"CN",
    "gn:dem":209,
    "gn:feature_class":"P",
    "gn:feature_code":"PPL",
    "gn:name":"Yanquanxu",
    "gn:population":0,
    "gn:timezone":"Asia/Shanghai",
    "iso:country":"CN",
    "name:zho_x_preferred":[
        "\u5ca9\u6cc9\u5729"
    ],
    "wof:name":"Yanquanxu",
    "wof:placetype":"locality"
},
  "geometry": {"coordinates":[112.90452000000001,25.18357],"type":"Point"}
}