{
  "type": "Feature",
  "properties": {
    "gn:admin1_code":"10",
    "gn:asciiname":"Houjiudian",
    "gn:country_code":"CN",
    "gn:dem":37,
    "gn:feature_class":"P",
    "gn:feature_code":"PPL",
    "gn:name":"Houjiudian",
    "gn:population":0,
    "gn:timezone":"Asia/Shanghai",
    "iso:country":"CN",
    "name:zho_x_preferred":[
        "\u540e\u65e7\u5e97"
    ],
    "wof:name":"Houjiudian",
    "wof:placetype":"locality"
},
  "geometry": {"coordinates":[115.17768,36.89973],"type":"Point"}
}