{
  "type": "Feature",
  "properties": {
    "gn:admin1_code":"11.0",
    "gn:asciiname":"Nanyuanci",
    "gn:country_code":"CN",
    "gn:dem":122,
    "gn:feature_class":"P",
    "gn:feature_code":"PPL",
    "gn:name":"Nanyuanci",
    "gn:population":0,
    "gn:timezone":"Asia/Shanghai",
    "iso:country":"CN",
    "name:zho_x_preferred":[
        "\u5357\u6e90\u7960"
    ],
    "wof:name":"Nanyuanci",
    "wof:placetype":"locality"
},
  "geometry": {"coordinates":[113.37849,27.5656],"type":"Point"}
}