{
  "type": "Feature",
  "properties": {
    "gn:admin1_code":"11.0",
    "gn:asciiname":"Chujiachong",
    "gn:country_code":"CN",
    "gn:dem":58,
    "gn:feature_class":"P",
    "gn:feature_code":"PPL",
    "gn:name":"Chujiachong",
    "gn:population":0,
    "gn:timezone":"Asia/Shanghai",
    "iso:country":"CN",
    "name:zho_x_preferred":[
        "\u695a\u5bb6\u51b2"
    ],
    "wof:name":"Chujiachong",
    "wof:placetype":"locality"
},
  "geometry": {"coordinates":[113.31753,29.14766],"type":"Point"}
}