{
  "type": "Feature",
  "properties": {
    "gn:admin1_code":"9.0",
    "gn:asciiname":"Daming",
    "gn:country_code":"CN",
    "gn:dem":467,
    "gn:feature_class":"P",
    "gn:feature_code":"PPL",
    "gn:name":"Daming",
    "gn:population":0,
    "gn:timezone":"Asia/Shanghai",
    "iso:country":"CN",
    "name:ceb_x_preferred":[
        "Daming"
    ],
    "name:ces_x_preferred":[
        "Ta-ming"
    ],
    "name:deu_x_preferred":[
        "Daming"
    ],
    "name:nor_x_preferred":[
        "Daming"
    ],
    "name:swe_x_preferred":[
        "Daming"
    ],
    "name:zho_x_preferred":[
        "\u5927\u660e"
    ],
    "wof:name":"Daming",
    "wof:placetype":"locality"
},
  "geometry": {"coordinates":[111.75942000000001,34.51264],"type":"Point"}
}