{
  "type": "Feature",
  "properties": {
    "gn:admin1_code":"32.0",
    "gn:asciiname":"Luchang",
    "gn:country_code":"CN",
    "gn:dem":459,
    "gn:feature_class":"P",
    "gn:feature_code":"PPL",
    "gn:name":"Luchang",
    "gn:population":0,
    "gn:timezone":"Asia/Shanghai",
    "iso:country":"CN",
    "name:zho_x_preferred":[
        "\u7089\u5382"
    ],
    "wof:name":"Luchang",
    "wof:placetype":"locality"
},
  "geometry": {"coordinates":[106.667,31.4406],"type":"Point"}
}