{
  "type": "Feature",
  "properties": {
    "gn:admin1_code":"5.0",
    "gn:asciiname":"Huanmintun",
    "gn:country_code":"CN",
    "gn:dem":130,
    "gn:feature_class":"P",
    "gn:feature_code":"PPL",
    "gn:name":"Huanmintun",
    "gn:population":0,
    "gn:timezone":"Asia/Shanghai",
    "iso:country":"CN",
    "name:zho_x_preferred":[
        "\u6b22\u6c11\u5c6f"
    ],
    "wof:name":"Huanmintun",
    "wof:placetype":"locality"
},
  "geometry": {"coordinates":[123.90705,45.40874],"type":"Point"}
}