{
  "type": "Feature",
  "properties": {
    "gn:admin1_code":"30.0",
    "gn:asciiname":"Fengtangmian",
    "gn:country_code":"CN",
    "gn:dem":592,
    "gn:feature_class":"P",
    "gn:feature_code":"PPL",
    "gn:name":"Fengtangmian",
    "gn:population":0,
    "gn:timezone":"Asia/Shanghai",
    "iso:country":"CN",
    "name:zho_x_preferred":[
        "Fengtangmian"
    ],
    "name:zho_x_variant":[
        "\u4e30\u5858\u9762"
    ],
    "wof:name":"Fengtangmian",
    "wof:placetype":"locality"
},
  "geometry": {"coordinates":[115.26917,24.27306],"type":"Point"}
}