{
  "type": "Feature",
  "properties": {
    "gn:admin1_code":"19.0",
    "gn:asciiname":"Sanjia Wobucun",
    "gn:country_code":"CN",
    "gn:dem":115,
    "gn:feature_class":"P",
    "gn:feature_code":"PPL",
    "gn:name":"Sanjia Wobucun",
    "gn:population":0,
    "gn:timezone":"Asia/Shanghai",
    "iso:country":"CN",
    "name:zho_x_preferred":[
        "\u4e09\u5bb6\u7a9d\u5821\u6751"
    ],
    "wof:name":"Sanjia Wobucun",
    "wof:placetype":"locality"
},
  "geometry": {"coordinates":[123.25911000000001,42.88305],"type":"Point"}
}