{
  "type": "Feature",
  "properties": {
    "gn:admin1_code":"20.0",
    "gn:asciiname":"Shimenkou",
    "gn:country_code":"CN",
    "gn:dem":1416,
    "gn:feature_class":"P",
    "gn:feature_code":"PPLA4",
    "gn:name":"Shimenkou",
    "gn:population":0,
    "gn:timezone":"Asia/Shanghai",
    "iso:country":"CN",
    "name:und_x_variant":[
        "\u77f3\u95e8\u53e3"
    ],
    "wof:name":"Shimenkou",
    "wof:placetype":"locality"
},
  "geometry": {"coordinates":[113.30121,41.37241],"type":"Point"}
}