{
  "type": "Feature",
  "properties": {
    "gn:admin1_code":"18.0",
    "gn:asciiname":"Bizha",
    "gn:country_code":"CN",
    "gn:dem":859,
    "gn:feature_class":"P",
    "gn:feature_code":"PPL",
    "gn:name":"Bizha",
    "gn:population":0,
    "gn:timezone":"Asia/Shanghai",
    "iso:country":"CN",
    "name:zho_x_preferred":[
        "\u4ffe\u70b8"
    ],
    "wof:name":"Bizha",
    "wof:placetype":"locality"
},
  "geometry": {"coordinates":[108.83199999999999,26.4727],"type":"Point"}
}