{
  "type": "Feature",
  "properties": {
    "gn:admin1_code":"30.0",
    "gn:asciiname":"Xiaojiawan",
    "gn:country_code":"CN",
    "gn:dem":663,
    "gn:feature_class":"P",
    "gn:feature_code":"PPL",
    "gn:name":"Xiaojiawan",
    "gn:population":0,
    "gn:timezone":"Asia/Shanghai",
    "iso:country":"CN",
    "name:zho_x_preferred":[
        "Xiaojiawan"
    ],
    "name:zho_x_variant":[
        "\u8096\u5bb6\u6e7e"
    ],
    "wof:name":"Xiaojiawan",
    "wof:placetype":"locality"
},
  "geometry": {"coordinates":[113.23027999999999,25.39833],"type":"Point"}
}