{
  "type": "Feature",
  "properties": {
    "gn:admin1_code":"8.0",
    "gn:asciiname":"Lianxincun",
    "gn:country_code":"CN",
    "gn:dem":213,
    "gn:feature_class":"P",
    "gn:feature_code":"PPL",
    "gn:name":"Lianxincun",
    "gn:population":0,
    "gn:timezone":"Asia/Shanghai",
    "iso:country":"CN",
    "name:zho_x_preferred":[
        "\u8054\u5fc3\u6751"
    ],
    "wof:name":"Lianxincun",
    "wof:placetype":"locality"
},
  "geometry": {"coordinates":[125.84999999999999,47.95596],"type":"Point"}
}