{
  "type": "Feature",
  "properties": {
    "gn:admin1_code":"30",
    "gn:asciiname":"Dongtou",
    "gn:country_code":"CN",
    "gn:dem":112,
    "gn:feature_class":"P",
    "gn:feature_code":"PPL",
    "gn:name":"Dongtou",
    "gn:population":0,
    "gn:timezone":"Asia/Urumqi",
    "iso:country":"CN",
    "name:zho_x_preferred":[
        "\u578c\u5934"
    ],
    "wof:name":"Dongtou",
    "wof:placetype":"locality"
},
  "geometry": {"coordinates":[111.18568999999999,21.91504],"type":"Point"}
}