{
  "type": "Feature",
  "properties": {
    "gn:admin1_code":"29.0",
    "gn:asciiname":"Lianhe",
    "gn:country_code":"CN",
    "gn:dem":2247,
    "gn:feature_class":"P",
    "gn:feature_code":"PPL",
    "gn:name":"Lianhe",
    "gn:population":0,
    "gn:timezone":"Asia/Shanghai",
    "iso:country":"CN",
    "name:und_x_variant":[
        "\u8054\u5408"
    ],
    "wof:name":"Lianhe",
    "wof:placetype":"locality"
},
  "geometry": {"coordinates":[102.41424000000001,25.93294],"type":"Point"}
}