{
  "type": "Feature",
  "properties": {
    "gn:admin1_code":"8.0",
    "gn:asciiname":"Nenjiang Wufenchang Sandui",
    "gn:country_code":"CN",
    "gn:dem":328,
    "gn:feature_class":"P",
    "gn:feature_code":"PPLF",
    "gn:name":"Nenjiang Wufenchang Sandui",
    "gn:population":0,
    "gn:timezone":"Asia/Shanghai",
    "iso:country":"CN",
    "name:zho_x_preferred":[
        "\u5ae9\u6c5f\u4e94\u5206\u573a\u4e09\u961f"
    ],
    "wof:name":"Nenjiang Wufenchang Sandui",
    "wof:placetype":"locality"
},
  "geometry": {"coordinates":[125.78084,49.07496],"type":"Point"}
}