{
  "type": "Feature",
  "properties": {
    "gn:admin1_code":"16",
    "gn:asciiname":"Dongwei",
    "gn:country_code":"CN",
    "gn:dem":389,
    "gn:feature_class":"P",
    "gn:feature_code":"PPL",
    "gn:name":"Dongwei",
    "gn:population":0,
    "gn:timezone":"Asia/Shanghai",
    "iso:country":"CN",
    "name:zho_x_preferred":[
        "\u6d1e\u5c3e"
    ],
    "wof:name":"Dongwei",
    "wof:placetype":"locality"
},
  "geometry": {"coordinates":[109.798,25.5362],"type":"Point"}
}