{
  "type": "Feature",
  "properties": {
    "gn:admin1_code":"12.0",
    "gn:asciiname":"Yangjia Xinwu",
    "gn:country_code":"CN",
    "gn:dem":53,
    "gn:feature_class":"P",
    "gn:feature_code":"PPL",
    "gn:name":"Yangjia Xinwu",
    "gn:population":0,
    "gn:timezone":"Asia/Shanghai",
    "iso:country":"CN",
    "name:zho_x_preferred":[
        "Yangjia Xinwu"
    ],
    "name:zho_x_variant":[
        "\u6768\u5bb6\u65b0\u5c4b"
    ],
    "wof:name":"Yangjia Xinwu",
    "wof:placetype":"locality"
},
  "geometry": {"coordinates":[115.16898,30.65894],"type":"Point"}
}