{
  "type": "Feature",
  "properties": {
    "gn:admin1_code":"30.0",
    "gn:asciiname":"Waxitian",
    "gn:country_code":"CN",
    "gn:dem":56,
    "gn:feature_class":"P",
    "gn:feature_code":"PPL",
    "gn:name":"Waxitian",
    "gn:population":0,
    "gn:timezone":"Asia/Shanghai",
    "iso:country":"CN",
    "name:zho_x_preferred":[
        "\u74e6\u9521\u7530"
    ],
    "wof:name":"Waxitian",
    "wof:placetype":"locality"
},
  "geometry": {"coordinates":[113.56729,23.75107],"type":"Point"}
}