{
  "type": "Feature",
  "properties": {
    "gn:admin1_code":"8.0",
    "gn:asciiname":"Xiachazi Linchang",
    "gn:country_code":"CN",
    "gn:dem":191,
    "gn:feature_class":"P",
    "gn:feature_code":"PPLF",
    "gn:name":"Xiachazi Linchang",
    "gn:population":0,
    "gn:timezone":"Asia/Shanghai",
    "iso:country":"CN",
    "name:zho_x_preferred":[
        "\u4e0b\u5c94\u5b50\u6797\u573a"
    ],
    "wof:name":"Xiachazi Linchang",
    "wof:placetype":"locality"
},
  "geometry": {"coordinates":[128.14826000000002,49.44121],"type":"Point"}
}