{
  "type": "Feature",
  "properties": {
    "gn:admin1_code":"1.0",
    "gn:asciiname":"Shengjiaxiao",
    "gn:country_code":"CN",
    "gn:dem":29,
    "gn:feature_class":"P",
    "gn:feature_code":"PPL",
    "gn:name":"Shengjiaxiao",
    "gn:population":0,
    "gn:timezone":"Asia/Shanghai",
    "iso:country":"CN",
    "name:zho_x_preferred":[
        "Shengjiaxiao"
    ],
    "name:zho_x_variant":[
        "\u76db\u5bb6\u5c0f"
    ],
    "wof:name":"Shengjiaxiao",
    "wof:placetype":"locality"
},
  "geometry": {"coordinates":[119.35402000000001,30.97829],"type":"Point"}
}