{
  "type": "Feature",
  "properties": {
    "gn:admin1_code":"21.0",
    "gn:asciiname":"Hanbobu",
    "gn:country_code":"CN",
    "gn:dem":1131,
    "gn:feature_class":"P",
    "gn:feature_code":"PPL",
    "gn:name":"Hanbobu",
    "gn:population":0,
    "gn:timezone":"Asia/Shanghai",
    "iso:country":"CN",
    "name:zho_x_preferred":[
        "\u6c49\u4f2f\u5821"
    ],
    "wof:name":"Hanbobu",
    "wof:placetype":"locality"
},
  "geometry": {"coordinates":[106.18899999999999,37.9171],"type":"Point"}
}