{
  "type": "Feature",
  "properties": {
    "gn:admin1_code":"30",
    "gn:asciiname":"Shenzheliao",
    "gn:country_code":"CN",
    "gn:dem":280,
    "gn:feature_class":"P",
    "gn:feature_code":"PPL",
    "gn:name":"Shenzheliao",
    "gn:population":0,
    "gn:timezone":"Asia/Shanghai",
    "iso:country":"CN",
    "name:zho_x_preferred":[
        "\u5ba1\u8005\u5bee"
    ],
    "wof:name":"Shenzheliao",
    "wof:placetype":"locality"
},
  "geometry": {"coordinates":[116.30186,23.11813],"type":"Point"}
}