{
  "type": "Feature",
  "properties": {
    "gn:admin1_code":"16.0",
    "gn:asciiname":"Xinleiqiang",
    "gn:country_code":"CN",
    "gn:dem":122,
    "gn:feature_class":"P",
    "gn:feature_code":"PPL",
    "gn:name":"Xinleiqiang",
    "gn:population":0,
    "gn:timezone":"Asia/Shanghai",
    "iso:country":"CN",
    "name:zho_x_preferred":[
        "\u65b0\u857e\u7f8c"
    ],
    "wof:name":"Xinleiqiang",
    "wof:placetype":"locality"
},
  "geometry": {"coordinates":[108.241,22.585],"type":"Point"}
}