{
  "type": "Feature",
  "properties": {
    "gn:admin1_code":"29.0",
    "gn:asciiname":"Shibuqi",
    "gn:country_code":"CN",
    "gn:dem":2987,
    "gn:feature_class":"P",
    "gn:feature_code":"PPL",
    "gn:name":"Shibuqi",
    "gn:population":0,
    "gn:timezone":"Asia/Shanghai",
    "iso:country":"CN",
    "name:zho_x_preferred":[
        "\u58eb\u5e03\u8d77"
    ],
    "wof:name":"Shibuqi",
    "wof:placetype":"locality"
},
  "geometry": {"coordinates":[100.83199999999999,27.1022],"type":"Point"}
}