{
  "type": "Feature",
  "properties": {
    "gn:admin1_code":"29.0",
    "gn:asciiname":"Guniangzhai",
    "gn:country_code":"CN",
    "gn:dem":1614,
    "gn:feature_class":"P",
    "gn:feature_code":"PPL",
    "gn:name":"Guniangzhai",
    "gn:population":0,
    "gn:timezone":"Asia/Shanghai",
    "iso:country":"CN",
    "name:zho_x_preferred":[
        "\u59d1\u5a18\u5be8"
    ],
    "wof:name":"Guniangzhai",
    "wof:placetype":"locality"
},
  "geometry": {"coordinates":[100.596,21.948],"type":"Point"}
}