{
  "type": "Feature",
  "properties": {
    "gn:admin1_code":"30.0",
    "gn:asciiname":"Fengmugen",
    "gn:country_code":"CN",
    "gn:dem":200,
    "gn:feature_class":"P",
    "gn:feature_code":"PPL",
    "gn:name":"Fengmugen",
    "gn:population":0,
    "gn:timezone":"Asia/Shanghai",
    "iso:country":"CN",
    "name:zho_x_preferred":[
        "\u67ab\u6728\u6839"
    ],
    "wof:name":"Fengmugen",
    "wof:placetype":"locality"
},
  "geometry": {"coordinates":[111.89968,23.68564],"type":"Point"}
}