{
  "type": "Feature",
  "properties": {
    "gn:admin1_code":"8.0",
    "gn:asciiname":"Hezuoshetun",
    "gn:country_code":"CN",
    "gn:dem":130,
    "gn:feature_class":"P",
    "gn:feature_code":"PPL",
    "gn:name":"Hezuoshetun",
    "gn:population":0,
    "gn:timezone":"Asia/Shanghai",
    "iso:country":"CN",
    "name:zho_x_preferred":[
        "\u5408\u4f5c\u793e\u5c6f"
    ],
    "wof:name":"Hezuoshetun",
    "wof:placetype":"locality"
},
  "geometry": {"coordinates":[124.50979,45.59874],"type":"Point"}
}