{
  "type": "Feature",
  "properties": {
    "gn:admin1_code":"8.0",
    "gn:asciiname":"Jiangbing Ershisidui",
    "gn:country_code":"CN",
    "gn:dem":62,
    "gn:feature_class":"P",
    "gn:feature_code":"PPLF",
    "gn:name":"Jiangbing Ershisidui",
    "gn:population":0,
    "gn:timezone":"Asia/Shanghai",
    "iso:country":"CN",
    "name:zho_x_preferred":[
        "\u6c5f\u6ee8\u4e8c\u5341\u56db\u961f"
    ],
    "wof:name":"Jiangbing Ershisidui",
    "wof:placetype":"locality"
},
  "geometry": {"coordinates":[131.52077,47.5723],"type":"Point"}
}