{
  "type": "Feature",
  "properties": {
    "gn:admin1_code":"19.0",
    "gn:asciiname":"Toudao Shansong",
    "gn:country_code":"CN",
    "gn:dem":389,
    "gn:feature_class":"P",
    "gn:feature_code":"PPL",
    "gn:name":"Toudao Shansong",
    "gn:population":0,
    "gn:timezone":"Asia/Shanghai",
    "iso:country":"CN",
    "name:und_x_variant":[
        "\u5934\u9053\u6749\u677e"
    ],
    "name:zho_x_preferred":[
        "\u5934\u9053\u6749\u677e"
    ],
    "wof:name":"Toudao Shansong",
    "wof:placetype":"locality"
},
  "geometry": {"coordinates":[125.03672,40.7157],"type":"Point"}
}