{
  "type": "Feature",
  "properties": {
    "gn:admin1_code":"19.0",
    "gn:asciiname":"Wanghu",
    "gn:country_code":"CN",
    "gn:dem":19,
    "gn:feature_class":"P",
    "gn:feature_code":"PPL",
    "gn:name":"Wanghu",
    "gn:population":0,
    "gn:timezone":"Asia/Shanghai",
    "iso:country":"CN",
    "name:zho_x_preferred":[
        "\u7f51\u6237"
    ],
    "wof:name":"Wanghu",
    "wof:placetype":"locality"
},
  "geometry": {"coordinates":[120.19018,40.19125],"type":"Point"}
}