{
  "type": "Feature",
  "properties": {
    "gn:admin1_code":"14.0",
    "gn:asciiname":"Maire",
    "gn:country_code":"CN",
    "gn:dem":5267,
    "gn:feature_class":"P",
    "gn:feature_code":"PPLF",
    "gn:name":"Maire",
    "gn:population":0,
    "gn:timezone":"Asia/Urumqi",
    "iso:country":"CN",
    "name:bod_x_preferred":[
        "M\u00eara"
    ],
    "name:cat_x_preferred":[
        "Maire"
    ],
    "name:ceb_x_preferred":[
        "Maire"
    ],
    "name:deu_x_preferred":[
        "Maire"
    ],
    "name:fra_x_preferred":[
        "Maire"
    ],
    "name:fry_x_preferred":[
        "Maire"
    ],
    "name:nld_x_preferred":[
        "Maire"
    ],
    "name:oci_x_preferred":[
        "Maire"
    ],
    "name:pol_x_preferred":[
        "Maire"
    ],
    "name:spa_x_preferred":[
        "Maire"
    ],
    "name:swe_x_preferred":[
        "Maire"
    ],
    "name:ukr_x_preferred":[
        "\u041c\u0435\u0440"
    ],
    "name:zho_x_preferred":[
        "Maire"
    ],
    "name:zho_x_variant":[
        "\u9ea6\u70ed"
    ],
    "wof:name":"Maire",
    "wof:placetype":"locality"
},
  "geometry": {"coordinates":[88.40100000000002,29.601],"type":"Point"}
}