{
  "type": "Feature",
  "properties": {
    "gn:admin1_code":"10.0",
    "gn:asciiname":"Shangfa",
    "gn:country_code":"CN",
    "gn:dem":26,
    "gn:feature_class":"P",
    "gn:feature_code":"PPL",
    "gn:name":"Shangfa",
    "gn:population":0,
    "gn:timezone":"Asia/Shanghai",
    "iso:country":"CN",
    "name:zho_x_preferred":[
        "\u5c1a\u57a1"
    ],
    "wof:name":"Shangfa",
    "wof:placetype":"locality"
},
  "geometry": {"coordinates":[116.07161000000001,39.30623],"type":"Point"}
}