{
  "type": "Feature",
  "properties": {
    "gn:admin1_code":"16.0",
    "gn:asciiname":"Hualuo",
    "gn:country_code":"CN",
    "gn:dem":122,
    "gn:feature_class":"P",
    "gn:feature_code":"PPL",
    "gn:name":"Hualuo",
    "gn:population":0,
    "gn:timezone":"Asia/Shanghai",
    "iso:country":"CN",
    "name:zho_x_preferred":[
        "\u534e\u7f57"
    ],
    "wof:name":"Hualuo",
    "wof:placetype":"locality"
},
  "geometry": {"coordinates":[109.22199999999999,23.2625],"type":"Point"}
}