{
  "type": "Feature",
  "properties": {
    "gn:admin1_code":"24",
    "gn:asciiname":"Anshangcun",
    "gn:country_code":"CN",
    "gn:dem":809,
    "gn:feature_class":"P",
    "gn:feature_code":"PPL",
    "gn:name":"Anshangcun",
    "gn:population":0,
    "gn:timezone":"Asia/Shanghai",
    "iso:country":"CN",
    "name:zho_x_preferred":[
        "\u5b89\u4e0a\u6751"
    ],
    "wof:name":"Anshangcun",
    "wof:placetype":"locality"
},
  "geometry": {"coordinates":[111.89769,37.36612],"type":"Point"}
}