{
  "type": "Feature",
  "properties": {
    "gn:admin1_code":"02",
    "gn:asciiname":"Panshizhen",
    "gn:country_code":"CN",
    "gn:dem":-9999,
    "gn:feature_class":"P",
    "gn:feature_code":"PPL",
    "gn:name":"Panshizhen",
    "gn:population":0,
    "gn:timezone":"Asia/Shanghai",
    "iso:country":"CN",
    "name:und_x_variant":[
        "Panshi",
        "Panshizhen",
        "Ancient Panchu"
    ],
    "name:zho_x_preferred":[
        "P\u2019an-hou-wei"
    ],
    "name:zho_x_variant":[
        "P\u2019an-shih-wei",
        "\u78d0\u77f3\u9547",
        "P\u2019an-shih"
    ],
    "wof:name":"Panshizhen",
    "wof:placetype":"locality"
},
  "geometry": {"coordinates":[120.82201000000001,27.98617],"type":"Point"}
}