{
  "type": "Feature",
  "properties": {
    "gn:admin1_code":"29.0",
    "gn:asciiname":"Sankezhuang",
    "gn:country_code":"CN",
    "gn:dem":1278,
    "gn:feature_class":"P",
    "gn:feature_code":"PPL",
    "gn:name":"Sankezhuang",
    "gn:population":0,
    "gn:timezone":"Asia/Shanghai",
    "iso:country":"CN",
    "name:zho_x_preferred":[
        "\u4e09\u68f5\u6869"
    ],
    "wof:name":"Sankezhuang",
    "wof:placetype":"locality"
},
  "geometry": {"coordinates":[101.08199999999999,22.9867],"type":"Point"}
}