{
  "type": "Feature",
  "properties": {
    "gn:admin1_code":"7",
    "gn:asciiname":"Shankouwei",
    "gn:country_code":"CN",
    "gn:dem":240,
    "gn:feature_class":"P",
    "gn:feature_code":"PPL",
    "gn:name":"Shankouwei",
    "gn:population":0,
    "gn:timezone":"Asia/Shanghai",
    "iso:country":"CN",
    "name:und_x_variant":[
        "\u6749\u53e3\u5c3e"
    ],
    "wof:name":"Shankouwei",
    "wof:placetype":"locality"
},
  "geometry": {"coordinates":[118.34896000000001,26.69306],"type":"Point"}
}