{
  "type": "Feature",
  "properties": {
    "gn:admin1_code":"4.0",
    "gn:asciiname":"Nankan Yizu",
    "gn:country_code":"CN",
    "gn:dem":2,
    "gn:feature_class":"P",
    "gn:feature_code":"PPL",
    "gn:name":"Nankan Yizu",
    "gn:population":0,
    "gn:timezone":"Asia/Shanghai",
    "iso:country":"CN",
    "name:und_x_variant":[
        "\u5357\u574e\u4e00\u7ec4"
    ],
    "name:zho_x_preferred":[
        "\u5357\u574e\u4e00\u7ec4"
    ],
    "wof:name":"Nankan Yizu",
    "wof:placetype":"locality"
},
  "geometry": {"coordinates":[120.4868,32.92504],"type":"Point"}
}