{
  "type": "Feature",
  "properties": {
    "gn:admin1_code":"18",
    "gn:asciiname":"Xiaotianba",
    "gn:country_code":"CN",
    "gn:dem":942,
    "gn:feature_class":"P",
    "gn:feature_code":"PPL",
    "gn:name":"Xiaotianba",
    "gn:population":0,
    "gn:timezone":"Asia/Shanghai",
    "iso:country":"CN",
    "name:zho_x_preferred":[
        "\u5c0f\u7530\u575d"
    ],
    "wof:name":"Xiaotianba",
    "wof:placetype":"locality"
},
  "geometry": {"coordinates":[106.70399999999999,25.7766],"type":"Point"}
}