{
  "type": "Feature",
  "properties": {
    "gn:admin1_code":"7",
    "gn:asciiname":"Zhaocuo",
    "gn:country_code":"CN",
    "gn:dem":17,
    "gn:feature_class":"P",
    "gn:feature_code":"PPL",
    "gn:name":"Zhaocuo",
    "gn:population":0,
    "gn:timezone":"Asia/Shanghai",
    "iso:country":"CN",
    "name:und_x_variant":[
        "Licuo",
        "Zhaocuo",
        "\u8d75\u539d"
    ],
    "wof:name":"Zhaocuo",
    "wof:placetype":"locality"
},
  "geometry": {"coordinates":[118.20474,24.65805],"type":"Point"}
}