{
  "type": "Feature",
  "properties": {
    "gn:admin1_code":"24.0",
    "gn:asciiname":"Nansicun",
    "gn:country_code":"CN",
    "gn:dem":1243,
    "gn:feature_class":"P",
    "gn:feature_code":"PPL",
    "gn:name":"Nansicun",
    "gn:population":0,
    "gn:timezone":"Asia/Shanghai",
    "iso:country":"CN",
    "name:und_x_variant":[
        "\u5357\u5bfa\u6751"
    ],
    "name:zho_x_preferred":[
        "\u5357\u5bfa\u6751"
    ],
    "wof:name":"Nansicun",
    "wof:placetype":"locality"
},
  "geometry": {"coordinates":[112.83447,39.23941],"type":"Point"}
}