{
  "type": "Feature",
  "properties": {
    "gn:admin1_code":"32.0",
    "gn:asciiname":"Qiaokou",
    "gn:country_code":"CN",
    "gn:dem":523,
    "gn:feature_class":"P",
    "gn:feature_code":"PPL",
    "gn:name":"Qiaokou",
    "gn:population":0,
    "gn:timezone":"Asia/Shanghai",
    "iso:country":"CN",
    "name:zho_x_preferred":[
        "\u6865\u53e3"
    ],
    "wof:name":"Qiaokou",
    "wof:placetype":"locality"
},
  "geometry": {"coordinates":[103.2608,29.7621],"type":"Point"}
}