{
  "type": "Feature",
  "properties": {
    "gn:admin1_code":"29.0",
    "gn:asciiname":"Pasha Laozhai",
    "gn:country_code":"CN",
    "gn:dem":1639,
    "gn:feature_class":"P",
    "gn:feature_code":"PPL",
    "gn:name":"Pasha Laozhai",
    "gn:population":0,
    "gn:timezone":"Asia/Shanghai",
    "iso:country":"CN",
    "name:zho_x_preferred":[
        "\u5e15\u6c99 \u8001\u5be8"
    ],
    "wof:name":"Pasha Laozhai",
    "wof:placetype":"locality"
},
  "geometry": {"coordinates":[100.553,21.8352],"type":"Point"}
}