{
  "type": "Feature",
  "properties": {
    "gn:admin1_code":"8.0",
    "gn:asciiname":"Nanlincun",
    "gn:country_code":"CN",
    "gn:dem":60,
    "gn:feature_class":"P",
    "gn:feature_code":"PPL",
    "gn:name":"Nanlincun",
    "gn:population":0,
    "gn:timezone":"Asia/Shanghai",
    "iso:country":"CN",
    "name:zho_x_preferred":[
        "\u5357\u6797\u6751"
    ],
    "wof:name":"Nanlincun",
    "wof:placetype":"locality"
},
  "geometry": {"coordinates":[132.64588999999998,46.854],"type":"Point"}
}