{
  "type": "Feature",
  "properties": {
    "gn:admin1_code":"29.0",
    "gn:asciiname":"Langzhu",
    "gn:country_code":"CN",
    "gn:dem":1163,
    "gn:feature_class":"P",
    "gn:feature_code":"PPL",
    "gn:name":"Langzhu",
    "gn:population":0,
    "gn:timezone":"Asia/Shanghai",
    "iso:country":"CN",
    "name:zho_x_preferred":[
        "\u6d6a\u73e0"
    ],
    "wof:name":"Langzhu",
    "wof:placetype":"locality"
},
  "geometry": {"coordinates":[101.917,23.2501],"type":"Point"}
}