{
  "type": "Feature",
  "properties": {
    "gn:admin1_code":"12",
    "gn:asciiname":"Changtan",
    "gn:country_code":"CN",
    "gn:dem":44,
    "gn:feature_class":"P",
    "gn:feature_code":"PPLA4",
    "gn:name":"Changtan",
    "gn:population":0,
    "gn:timezone":"Asia/Shanghai",
    "iso:country":"CN",
    "name:und_x_variant":[
        "\u957f\u6ee9",
        "Changtan Zhen",
        "\u957f\u6ee9\u9547"
    ],
    "wof:name":"Changtan",
    "wof:placetype":"locality"
},
  "geometry": {"coordinates":[112.73289,31.00214],"type":"Point"}
}