{
  "type": "Feature",
  "properties": {
    "gn:admin1_code":"29.0",
    "gn:asciiname":"Longbaochong",
    "gn:country_code":"CN",
    "gn:dem":1754,
    "gn:feature_class":"P",
    "gn:feature_code":"PPL",
    "gn:name":"Longbaochong",
    "gn:population":0,
    "gn:timezone":"Asia/Shanghai",
    "iso:country":"CN",
    "name:zho_x_preferred":[
        "\u9f99\u4fdd\u51b2"
    ],
    "wof:name":"Longbaochong",
    "wof:placetype":"locality"
},
  "geometry": {"coordinates":[102.05,25.0086],"type":"Point"}
}