{
  "type": "Feature",
  "properties": {
    "gn:admin1_code":"4.0",
    "gn:asciiname":"Yanduncun",
    "gn:country_code":"CN",
    "gn:dem":37,
    "gn:feature_class":"P",
    "gn:feature_code":"PPL",
    "gn:name":"Yanduncun",
    "gn:population":0,
    "gn:timezone":"Asia/Shanghai",
    "iso:country":"CN",
    "name:zho_x_preferred":[
        "\u70df\u58a9\u6751"
    ],
    "wof:name":"Yanduncun",
    "wof:placetype":"locality"
},
  "geometry": {"coordinates":[118.63928,32.51349],"type":"Point"}
}