{
  "type": "Feature",
  "properties": {
    "gn:admin1_code":"32.0",
    "gn:asciiname":"Jingzigou Shanli",
    "gn:country_code":"CN",
    "gn:dem":1043,
    "gn:feature_class":"P",
    "gn:feature_code":"PPL",
    "gn:name":"Jingzigou Shanli",
    "gn:population":0,
    "gn:timezone":"Asia/Shanghai",
    "iso:country":"CN",
    "name:zho_x_preferred":[
        "\u4e95\u5b50\u6c9f\u5c71\u91cc"
    ],
    "wof:name":"Jingzigou Shanli",
    "wof:placetype":"locality"
},
  "geometry": {"coordinates":[105.143,32.4843],"type":"Point"}
}