{
  "type": "Feature",
  "properties": {
    "gn:admin1_code":"4.0",
    "gn:asciiname":"Gedazhuang",
    "gn:country_code":"CN",
    "gn:dem":17,
    "gn:feature_class":"P",
    "gn:feature_code":"PPL",
    "gn:name":"Gedazhuang",
    "gn:population":0,
    "gn:timezone":"Asia/Shanghai",
    "iso:country":"CN",
    "name:zho_x_preferred":[
        "\u845b\u5927\u5e84"
    ],
    "wof:name":"Gedazhuang",
    "wof:placetype":"locality"
},
  "geometry": {"coordinates":[118.71899999999999,33.7507],"type":"Point"}
}