{
  "type": "Feature",
  "properties": {
    "gn:admin1_code":"32.0",
    "gn:asciiname":"Jiugunian Xicun",
    "gn:country_code":"CN",
    "gn:dem":2793,
    "gn:feature_class":"P",
    "gn:feature_code":"PPL",
    "gn:name":"Jiugunian Xicun",
    "gn:population":0,
    "gn:timezone":"Asia/Shanghai",
    "iso:country":"CN",
    "name:zho_x_preferred":[
        "\u4e5d\u53e4\u78be\u897f\u6751"
    ],
    "wof:name":"Jiugunian Xicun",
    "wof:placetype":"locality"
},
  "geometry": {"coordinates":[101.928,28.0876],"type":"Point"}
}