{
  "type": "Feature",
  "properties": {
    "gn:admin1_code":"30.0",
    "gn:asciiname":"Longfucun",
    "gn:country_code":"CN",
    "gn:dem":69,
    "gn:feature_class":"P",
    "gn:feature_code":"PPL",
    "gn:name":"Longfucun",
    "gn:population":0,
    "gn:timezone":"Asia/Shanghai",
    "iso:country":"CN",
    "name:zho_x_preferred":[
        "\u9f99\u798f\u6751"
    ],
    "wof:name":"Longfucun",
    "wof:placetype":"locality"
},
  "geometry": {"coordinates":[112.11556000000002,23.85981],"type":"Point"}
}