{
  "type": "Feature",
  "properties": {
    "gn:admin1_code":"32.0",
    "gn:asciiname":"Zhengluo",
    "gn:country_code":"CN",
    "gn:dem":2659,
    "gn:feature_class":"P",
    "gn:feature_code":"PPL",
    "gn:name":"Zhengluo",
    "gn:population":0,
    "gn:timezone":"Asia/Shanghai",
    "iso:country":"CN",
    "name:zho_x_preferred":[
        "\u6b63\u6d1b"
    ],
    "wof:name":"Zhengluo",
    "wof:placetype":"locality"
},
  "geometry": {"coordinates":[102.51900000000001,28.0259],"type":"Point"}
}