{
  "type": "Feature",
  "properties": {
    "gn:admin1_code":"30",
    "gn:asciiname":"Sanmenkeng",
    "gn:country_code":"CN",
    "gn:dem":175,
    "gn:feature_class":"P",
    "gn:feature_code":"PPL",
    "gn:name":"Sanmenkeng",
    "gn:population":0,
    "gn:timezone":"Asia/Shanghai",
    "iso:country":"CN",
    "name:zho_x_preferred":[
        "\u4e09\u95e8\u5751"
    ],
    "wof:name":"Sanmenkeng",
    "wof:placetype":"locality"
},
  "geometry": {"coordinates":[116.32301,23.9928],"type":"Point"}
}