{
  "type": "Feature",
  "properties": {
    "gn:admin1_code":"3.0",
    "gn:asciiname":"Wangjia Shanjiao",
    "gn:country_code":"CN",
    "gn:dem":116,
    "gn:feature_class":"P",
    "gn:feature_code":"PPL",
    "gn:name":"Wangjia Shanjiao",
    "gn:population":0,
    "gn:timezone":"Asia/Shanghai",
    "iso:country":"CN",
    "name:zho_x_preferred":[
        "\u738b\u5bb6\u5c71\u811a"
    ],
    "wof:name":"Wangjia Shanjiao",
    "wof:placetype":"locality"
},
  "geometry": {"coordinates":[117.80138999999998,28.20763],"type":"Point"}
}