{
  "type": "Feature",
  "properties": {
    "gn:admin1_code":"25",
    "gn:asciiname":"Maizhudun",
    "gn:country_code":"CN",
    "gn:dem":102,
    "gn:feature_class":"P",
    "gn:feature_code":"PPL",
    "gn:name":"Maizhudun",
    "gn:population":0,
    "gn:timezone":"Asia/Shanghai",
    "iso:country":"CN",
    "name:zho_x_preferred":[
        "\u8109\u4f4f\u58a9"
    ],
    "wof:name":"Maizhudun",
    "wof:placetype":"locality"
},
  "geometry": {"coordinates":[118.753,35.3986],"type":"Point"}
}