{
  "type": "Feature",
  "properties": {
    "gn:admin1_code":"11.0",
    "gn:asciiname":"Feishui",
    "gn:country_code":"CN",
    "gn:dem":197,
    "gn:feature_class":"P",
    "gn:feature_code":"PPL",
    "gn:name":"Feishui",
    "gn:population":0,
    "gn:timezone":"Asia/Shanghai",
    "iso:country":"CN",
    "name:zho_x_preferred":[
        "\u6cb8\u6c34"
    ],
    "wof:name":"Feishui",
    "wof:placetype":"locality"
},
  "geometry": {"coordinates":[109.73211999999999,27.13197000000001],"type":"Point"}
}