{
  "type": "Feature",
  "properties": {
    "gn:admin1_code":"29.0",
    "gn:asciiname":"Bandeng Shangzhai",
    "gn:country_code":"CN",
    "gn:dem":1376,
    "gn:feature_class":"P",
    "gn:feature_code":"PPL",
    "gn:name":"Bandeng Shangzhai",
    "gn:population":0,
    "gn:timezone":"Asia/Shanghai",
    "iso:country":"CN",
    "name:zho_x_preferred":[
        "\u73ed\u767b\u4e0a\u5be8"
    ],
    "wof:name":"Bandeng Shangzhai",
    "wof:placetype":"locality"
},
  "geometry": {"coordinates":[99.8627,22.6185],"type":"Point"}
}