{
  "type": "Feature",
  "properties": {
    "gn:admin1_code":"14",
    "gn:asciiname":"Xiaxia",
    "gn:country_code":"CN",
    "gn:dem":4713,
    "gn:feature_class":"P",
    "gn:feature_code":"PPL",
    "gn:name":"Xiaxia",
    "gn:population":0,
    "gn:timezone":"Asia/Urumqi",
    "iso:country":"CN",
    "name:zho_x_preferred":[
        "\u867e\u590f"
    ],
    "wof:name":"Xiaxia",
    "wof:placetype":"locality"
},
  "geometry": {"coordinates":[89.9726,28.9191],"type":"Point"}
}