{
  "type": "Feature",
  "properties": {
    "gn:admin1_code":"16.0",
    "gn:asciiname":"Dayaozhai",
    "gn:country_code":"CN",
    "gn:dem":1015,
    "gn:feature_class":"P",
    "gn:feature_code":"PPL",
    "gn:name":"Dayaozhai",
    "gn:population":0,
    "gn:timezone":"Asia/Shanghai",
    "iso:country":"CN",
    "name:zho_x_preferred":[
        "\u5927\u7476\u5be8"
    ],
    "wof:name":"Dayaozhai",
    "wof:placetype":"locality"
},
  "geometry": {"coordinates":[105.65000000000001,24.5031],"type":"Point"}
}