{
  "type": "Feature",
  "properties": {
    "gn:admin1_code":"21.0",
    "gn:asciiname":"Longdegou",
    "gn:country_code":"CN",
    "gn:dem":2212,
    "gn:feature_class":"P",
    "gn:feature_code":"PPL",
    "gn:name":"Longdegou",
    "gn:population":0,
    "gn:timezone":"Asia/Shanghai",
    "iso:country":"CN",
    "name:zho_x_preferred":[
        "\u9686\u5fb7\u6c9f"
    ],
    "wof:name":"Longdegou",
    "wof:placetype":"locality"
},
  "geometry": {"coordinates":[106.117,35.773],"type":"Point"}
}