{
  "type": "Feature",
  "properties": {
    "gn:admin1_code":"8.0",
    "gn:asciiname":"Hailundui",
    "gn:country_code":"CN",
    "gn:dem":279,
    "gn:feature_class":"P",
    "gn:feature_code":"PPLF",
    "gn:name":"Hailundui",
    "gn:population":0,
    "gn:timezone":"Asia/Shanghai",
    "iso:country":"CN",
    "name:zho_x_preferred":[
        "\u6d77\u4f26\u961f"
    ],
    "wof:name":"Hailundui",
    "wof:placetype":"locality"
},
  "geometry": {"coordinates":[127.87724,47.70759],"type":"Point"}
}