{
  "type": "Feature",
  "properties": {
    "gn:admin1_code":"3.0",
    "gn:asciiname":"Shuibutou",
    "gn:country_code":"CN",
    "gn:dem":71,
    "gn:feature_class":"P",
    "gn:feature_code":"PPL",
    "gn:name":"Shuibutou",
    "gn:population":0,
    "gn:timezone":"Asia/Shanghai",
    "iso:country":"CN",
    "name:und_x_variant":[
        "\u6c34\u57e0\u5934"
    ],
    "wof:name":"Shuibutou",
    "wof:placetype":"locality"
},
  "geometry": {"coordinates":[117.52961000000001,29.10991],"type":"Point"}
}