{
  "type": "Feature",
  "properties": {
    "gn:admin1_code":"19.0",
    "gn:asciiname":"Daliangdong",
    "gn:country_code":"CN",
    "gn:dem":73,
    "gn:feature_class":"P",
    "gn:feature_code":"PPL",
    "gn:name":"Daliangdong",
    "gn:population":0,
    "gn:timezone":"Asia/Shanghai",
    "iso:country":"CN",
    "name:und_x_variant":[
        "\u5927\u7cae\u6d1e"
    ],
    "name:zho_x_preferred":[
        "\u5927\u7cae\u6d1e"
    ],
    "wof:name":"Daliangdong",
    "wof:placetype":"locality"
},
  "geometry": {"coordinates":[123.40017,42.25261],"type":"Point"}
}