{
  "type": "Feature",
  "properties": {
    "gn:admin1_code":"3.0",
    "gn:asciiname":"Shangnanyuan",
    "gn:country_code":"CN",
    "gn:dem":222,
    "gn:feature_class":"P",
    "gn:feature_code":"PPL",
    "gn:name":"Shangnanyuan",
    "gn:population":0,
    "gn:timezone":"Asia/Shanghai",
    "iso:country":"CN",
    "name:und_x_variant":[
        "\u4e0a\u5357\u6e90"
    ],
    "wof:name":"Shangnanyuan",
    "wof:placetype":"locality"
},
  "geometry": {"coordinates":[116.111,27.39811],"type":"Point"}
}