{
  "type": "Feature",
  "properties": {
    "gn:admin1_code":"24",
    "gn:asciiname":"Baitang",
    "gn:country_code":"CN",
    "gn:dem":1320,
    "gn:feature_class":"P",
    "gn:feature_code":"PPLA4",
    "gn:name":"Baitang",
    "gn:population":0,
    "gn:timezone":"Asia/Shanghai",
    "iso:country":"CN",
    "name:und_x_variant":[
        "Pai-t\u2019ang-wa",
        "Pai-t\u2019ang",
        "Pai-t\u2019ang-tzu",
        "Baitang Xiang",
        "Baitang",
        "\u767d\u5802",
        "\u767d\u5802\u4e61"
    ],
    "wof:name":"Baitang",
    "wof:placetype":"locality"
},
  "geometry": {"coordinates":[112.32626,39.44615],"type":"Point"}
}