{
  "type": "Feature",
  "properties": {
    "gn:admin1_code":"30",
    "gn:asciiname":"Xialiheshe",
    "gn:country_code":"CN",
    "gn:dem":423,
    "gn:feature_class":"P",
    "gn:feature_code":"PPL",
    "gn:name":"Xialiheshe",
    "gn:population":0,
    "gn:timezone":"Asia/Shanghai",
    "iso:country":"CN",
    "name:zho_x_preferred":[
        "\u4e0b\u7acb\u79be\u756c"
    ],
    "wof:name":"Xialiheshe",
    "wof:placetype":"locality"
},
  "geometry": {"coordinates":[116.30166,24.80839],"type":"Point"}
}