{
  "type": "Feature",
  "properties": {
    "gn:admin1_code":"1.0",
    "gn:asciiname":"Fengxiangcun",
    "gn:country_code":"CN",
    "gn:dem":619,
    "gn:feature_class":"P",
    "gn:feature_code":"PPL",
    "gn:name":"Fengxiangcun",
    "gn:population":0,
    "gn:timezone":"Asia/Shanghai",
    "iso:country":"CN",
    "name:zho_x_preferred":[
        "\u67ab\u9999\u6751"
    ],
    "wof:name":"Fengxiangcun",
    "wof:placetype":"locality"
},
  "geometry": {"coordinates":[116.25095,30.81033],"type":"Point"}
}