{
  "type": "Feature",
  "properties": {
    "gn:admin1_code":"5.0",
    "gn:asciiname":"Dongyuanzi",
    "gn:country_code":"CN",
    "gn:dem":179,
    "gn:feature_class":"P",
    "gn:feature_code":"PPL",
    "gn:name":"Dongyuanzi",
    "gn:population":0,
    "gn:timezone":"Asia/Shanghai",
    "iso:country":"CN",
    "name:zho_x_preferred":[
        "\u4e1c\u56ed\u5b50"
    ],
    "wof:name":"Dongyuanzi",
    "wof:placetype":"locality"
},
  "geometry": {"coordinates":[126.08126,44.58679],"type":"Point"}
}