{
  "type": "Feature",
  "properties": {
    "gn:admin1_code":"9.0",
    "gn:asciiname":"Shenzhuang",
    "gn:country_code":"CN",
    "gn:dem":127,
    "gn:feature_class":"P",
    "gn:feature_code":"PPL",
    "gn:name":"Shenzhuang",
    "gn:population":0,
    "gn:timezone":"Asia/Shanghai",
    "iso:country":"CN",
    "name:und_x_variant":[
        "\u7533\u5e84",
        "Shenzhuang"
    ],
    "wof:name":"Shenzhuang",
    "wof:placetype":"locality"
},
  "geometry": {"coordinates":[112.92881,33.08309000000001],"type":"Point"}
}