{
  "type": "Feature",
  "properties": {
    "gn:admin1_code":"14.0",
    "gn:asciiname":"Debacun",
    "gn:country_code":"CN",
    "gn:dem":2830,
    "gn:feature_class":"P",
    "gn:feature_code":"PPL",
    "gn:name":"Debacun",
    "gn:population":0,
    "gn:timezone":"Asia/Urumqi",
    "iso:country":"CN",
    "name:zho_x_preferred":[
        "\u5fb7\u5df4\u6751"
    ],
    "wof:name":"Debacun",
    "wof:placetype":"locality"
},
  "geometry": {"coordinates":[95.84692,29.80834],"type":"Point"}
}