{
  "type": "Feature",
  "properties": {
    "gn:admin1_code":"7.0",
    "gn:asciiname":"Ruilonggang",
    "gn:country_code":"CN",
    "gn:dem":758,
    "gn:feature_class":"P",
    "gn:feature_code":"PPL",
    "gn:name":"Ruilonggang",
    "gn:population":0,
    "gn:timezone":"Asia/Shanghai",
    "iso:country":"CN",
    "name:zho_x_preferred":[
        "\u745e\u9f99\u5188"
    ],
    "wof:name":"Ruilonggang",
    "wof:placetype":"locality"
},
  "geometry": {"coordinates":[119.25668,26.9912],"type":"Point"}
}