{
  "type": "Feature",
  "properties": {
    "gn:admin1_code":"4.0",
    "gn:asciiname":"Taixi",
    "gn:country_code":"CN",
    "gn:dem":5,
    "gn:feature_class":"P",
    "gn:feature_code":"PPL",
    "gn:name":"Taixi",
    "gn:population":0,
    "gn:timezone":"Asia/Shanghai",
    "iso:country":"CN",
    "name:und_x_variant":[
        "\u6cf0\u897f"
    ],
    "wof:name":"Taixi",
    "wof:placetype":"locality"
},
  "geometry": {"coordinates":[120.46768,33.17397],"type":"Point"}
}