{
  "type": "Feature",
  "properties": {
    "gn:admin1_code":"32.0",
    "gn:asciiname":"Mazengyiwu",
    "gn:country_code":"CN",
    "gn:dem":2144,
    "gn:feature_class":"P",
    "gn:feature_code":"PPL",
    "gn:name":"Mazengyiwu",
    "gn:population":0,
    "gn:timezone":"Asia/Shanghai",
    "iso:country":"CN",
    "name:zho_x_preferred":[
        "\u9a6c\u589e\u4f9d\u4e4c"
    ],
    "wof:name":"Mazengyiwu",
    "wof:placetype":"locality"
},
  "geometry": {"coordinates":[102.42180999999999,27.82859],"type":"Point"}
}