{
  "type": "Feature",
  "properties": {
    "gn:admin1_code":"30",
    "gn:asciiname":"Shanghuang Caotian",
    "gn:country_code":"CN",
    "gn:dem":518,
    "gn:feature_class":"P",
    "gn:feature_code":"PPL",
    "gn:name":"Shanghuang Caotian",
    "gn:population":0,
    "gn:timezone":"Asia/Shanghai",
    "iso:country":"CN",
    "name:zho_x_preferred":[
        "\u4e0a\u9ec4\u8349\u7530"
    ],
    "wof:name":"Shanghuang Caotian",
    "wof:placetype":"locality"
},
  "geometry": {"coordinates":[116.23317,24.06562000000001],"type":"Point"}
}