{
  "type": "Feature",
  "properties": {
    "gn:admin1_code":"33.0",
    "gn:asciiname":"Bei'aikou",
    "gn:country_code":"CN",
    "gn:dem":547,
    "gn:feature_class":"P",
    "gn:feature_code":"PPL",
    "gn:name":"Bei\u2019aikou",
    "gn:population":0,
    "gn:timezone":"Asia/Shanghai",
    "iso:country":"CN",
    "name:und_x_variant":[
        "Bei\u2019aikou"
    ],
    "name:zho_x_preferred":[
        "\u5317\u9698\u53e3"
    ],
    "wof:name":"Bei'aikou",
    "wof:placetype":"locality"
},
  "geometry": {"coordinates":[106.932,29.585],"type":"Point"}
}