{
  "type": "Feature",
  "properties": {
    "gn:admin1_code":"29",
    "gn:asciiname":"Xiaotaohua",
    "gn:country_code":"CN",
    "gn:dem":1882,
    "gn:feature_class":"P",
    "gn:feature_code":"PPL",
    "gn:name":"Xiaotaohua",
    "gn:population":0,
    "gn:timezone":"Asia/Shanghai",
    "iso:country":"CN",
    "name:zho_x_preferred":[
        "\u5c0f\u6843\u82b1"
    ],
    "wof:name":"Xiaotaohua",
    "wof:placetype":"locality"
},
  "geometry": {"coordinates":[102.529,24.9277],"type":"Point"}
}