{
  "type": "Feature",
  "properties": {
    "gn:admin1_code":"19.0",
    "gn:asciiname":"Minjiacun",
    "gn:country_code":"CN",
    "gn:dem":74,
    "gn:feature_class":"P",
    "gn:feature_code":"PPL",
    "gn:name":"Minjiacun",
    "gn:population":0,
    "gn:timezone":"Asia/Shanghai",
    "iso:country":"CN",
    "name:und_x_variant":[
        "Minjia Dianzi"
    ],
    "name:zho_x_preferred":[
        "\u95f5\u5bb6\u6751"
    ],
    "name:zho_x_variant":[
        "\u95f5\u5bb6\u5e97\u5b50"
    ],
    "wof:name":"Minjiacun",
    "wof:placetype":"locality"
},
  "geometry": {"coordinates":[121.675,41.5727],"type":"Point"}
}