{
  "type": "Feature",
  "properties": {
    "gn:admin1_code":"7",
    "gn:asciiname":"Hongban",
    "gn:country_code":"CN",
    "gn:dem":7,
    "gn:feature_class":"P",
    "gn:feature_code":"PPL",
    "gn:name":"Hongban",
    "gn:population":0,
    "gn:timezone":"Asia/Shanghai",
    "iso:country":"CN",
    "name:zho_x_preferred":[
        "\u6d2a\u5742"
    ],
    "wof:name":"Hongban",
    "wof:placetype":"locality"
},
  "geometry": {"coordinates":[117.71738000000001,24.47026],"type":"Point"}
}