{
  "type": "Feature",
  "properties": {
    "gn:admin1_code":"3",
    "gn:asciiname":"Shang'ao",
    "gn:country_code":"CN",
    "gn:dem":846,
    "gn:feature_class":"P",
    "gn:feature_code":"PPL",
    "gn:name":"Shang\u2019ao",
    "gn:population":0,
    "gn:timezone":"Asia/Shanghai",
    "iso:country":"CN",
    "name:und_x_variant":[
        "Shang\u2019ao"
    ],
    "name:zho_x_preferred":[
        "\u4e0a\u5773"
    ],
    "wof:name":"Shang'ao",
    "wof:placetype":"locality"
},
  "geometry": {"coordinates":[114.10769000000001,26.38829],"type":"Point"}
}