{
  "type": "Feature",
  "properties": {
    "gn:admin1_code":"02",
    "gn:asciiname":"Dingzuimen",
    "gn:country_code":"CN",
    "gn:dem":13,
    "gn:feature_class":"P",
    "gn:feature_code":"PPL",
    "gn:name":"Dingzuimen",
    "gn:population":0,
    "gn:timezone":"Asia/Shanghai",
    "iso:country":"CN",
    "name:und_x_variant":[
        "Ting-tzu-men",
        "Dingzuimen"
    ],
    "name:zho_x_preferred":[
        "\u9489\u5480\u95e8"
    ],
    "wof:name":"Dingzuimen",
    "wof:placetype":"locality"
},
  "geometry": {"coordinates":[122.32465999999999,30.23739],"type":"Point"}
}