{
  "type": "Feature",
  "properties": {
    "gn:admin1_code":"29.0",
    "gn:asciiname":"Jipakan",
    "gn:country_code":"CN",
    "gn:dem":1937,
    "gn:feature_class":"P",
    "gn:feature_code":"PPL",
    "gn:name":"Jipakan",
    "gn:population":0,
    "gn:timezone":"Asia/Shanghai",
    "iso:country":"CN",
    "name:zho_x_preferred":[
        "\u9e21\u722c\u574e"
    ],
    "wof:name":"Jipakan",
    "wof:placetype":"locality"
},
  "geometry": {"coordinates":[101.568,26.1631],"type":"Point"}
}