{
  "type": "Feature",
  "properties": {
    "gn:admin1_code":"32.0",
    "gn:asciiname":"Bomo'eze",
    "gn:country_code":"CN",
    "gn:dem":1903,
    "gn:feature_class":"P",
    "gn:feature_code":"PPL",
    "gn:name":"Bomo\u2019eze",
    "gn:population":0,
    "gn:timezone":"Asia/Shanghai",
    "iso:country":"CN",
    "name:und_x_variant":[
        "Bomo\u2019eze"
    ],
    "name:zho_x_preferred":[
        "\u6ce2\u83ab\u5ce8\u6cfd"
    ],
    "wof:name":"Bomo'eze",
    "wof:placetype":"locality"
},
  "geometry": {"coordinates":[103.241,28.1307],"type":"Point"}
}