{
  "type": "Feature",
  "properties": {
    "gn:admin1_code":"20.0",
    "gn:asciiname":"Shiren Goukou",
    "gn:country_code":"CN",
    "gn:dem":385,
    "gn:feature_class":"P",
    "gn:feature_code":"PPL",
    "gn:name":"Shiren Goukou",
    "gn:population":0,
    "gn:timezone":"Asia/Shanghai",
    "iso:country":"CN",
    "name:zho_x_preferred":[
        "\u77f3\u4eba\u6c9f\u53e3"
    ],
    "wof:name":"Shiren Goukou",
    "wof:placetype":"locality"
},
  "geometry": {"coordinates":[122.21462,47.37974000000001],"type":"Point"}
}