{
  "type": "Feature",
  "properties": {
    "gn:admin1_code":"32.0",
    "gn:asciiname":"Xiaoqiaozi",
    "gn:country_code":"CN",
    "gn:dem":549,
    "gn:feature_class":"P",
    "gn:feature_code":"PPL",
    "gn:name":"Xiaoqiaozi",
    "gn:population":0,
    "gn:timezone":"Asia/Shanghai",
    "iso:country":"CN",
    "name:zho_x_preferred":[
        "\u5c0f\u6865\u5b50"
    ],
    "wof:name":"Xiaoqiaozi",
    "wof:placetype":"locality"
},
  "geometry": {"coordinates":[103.48795,29.76037],"type":"Point"}
}