{
  "type": "Feature",
  "properties": {
    "gn:admin1_code":"12.0",
    "gn:asciiname":"Yangqueba",
    "gn:country_code":"CN",
    "gn:dem":506,
    "gn:feature_class":"P",
    "gn:feature_code":"PPL",
    "gn:name":"Yangqueba",
    "gn:population":0,
    "gn:timezone":"Asia/Shanghai",
    "iso:country":"CN",
    "name:zho_x_preferred":[
        "\u9633\u9e4a\u575d"
    ],
    "wof:name":"Yangqueba",
    "wof:placetype":"locality"
},
  "geometry": {"coordinates":[109.54195,30.31233],"type":"Point"}
}