{
  "type": "Feature",
  "properties": {
    "gn:admin1_code":"7.0",
    "gn:asciiname":"Sanzhoucun",
    "gn:country_code":"CN",
    "gn:dem":269,
    "gn:feature_class":"P",
    "gn:feature_code":"PPL",
    "gn:name":"Sanzhoucun",
    "gn:population":0,
    "gn:timezone":"Asia/Shanghai",
    "iso:country":"CN",
    "name:zho_x_preferred":[
        "\u4e09\u6d32\u6751"
    ],
    "wof:name":"Sanzhoucun",
    "wof:placetype":"locality"
},
  "geometry": {"coordinates":[116.37898,25.59466],"type":"Point"}
}