{
  "type": "Feature",
  "properties": {
    "gn:admin1_code":"10",
    "gn:asciiname":"Dongyin Shigou",
    "gn:country_code":"CN",
    "gn:dem":1369,
    "gn:feature_class":"P",
    "gn:feature_code":"PPL",
    "gn:name":"Dongyin Shigou",
    "gn:population":0,
    "gn:timezone":"Asia/Shanghai",
    "iso:country":"CN",
    "name:zho_x_preferred":[
        "\u4e1c\u94f6\u77f3\u6c9f"
    ],
    "wof:name":"Dongyin Shigou",
    "wof:placetype":"locality"
},
  "geometry": {"coordinates":[115.15882000000001,41.01161],"type":"Point"}
}