{
  "type": "Feature",
  "properties": {
    "gn:admin1_code":"29.0",
    "gn:asciiname":"Dizipeng",
    "gn:country_code":"CN",
    "gn:dem":2023,
    "gn:feature_class":"P",
    "gn:feature_code":"PPL",
    "gn:name":"Dizipeng",
    "gn:population":0,
    "gn:timezone":"Asia/Shanghai",
    "iso:country":"CN",
    "name:zho_x_preferred":[
        "\u5f1f\u5b50\u68da"
    ],
    "wof:name":"Dizipeng",
    "wof:placetype":"locality"
},
  "geometry": {"coordinates":[100.697,25.7077],"type":"Point"}
}