{
  "type": "Feature",
  "properties": {
    "gn:admin1_code":"21.0",
    "gn:asciiname":"Liujia Kouzi",
    "gn:country_code":"CN",
    "gn:dem":1702,
    "gn:feature_class":"P",
    "gn:feature_code":"PPL",
    "gn:name":"Liujia Kouzi",
    "gn:population":0,
    "gn:timezone":"Asia/Shanghai",
    "iso:country":"CN",
    "name:zho_x_preferred":[
        "\u5218\u5bb6\u53e3\u5b50"
    ],
    "wof:name":"Liujia Kouzi",
    "wof:placetype":"locality"
},
  "geometry": {"coordinates":[107.01900000000001,37.1736],"type":"Point"}
}