{
  "type": "Feature",
  "properties": {
    "gn:admin1_code":"8.0",
    "gn:asciiname":"Pengshengcun",
    "gn:country_code":"CN",
    "gn:dem":69,
    "gn:feature_class":"P",
    "gn:feature_code":"PPL",
    "gn:name":"Pengshengcun",
    "gn:population":0,
    "gn:timezone":"Asia/Shanghai",
    "iso:country":"CN",
    "name:zho_x_preferred":[
        "\u5f6d\u751f\u6751"
    ],
    "wof:name":"Pengshengcun",
    "wof:placetype":"locality"
},
  "geometry": {"coordinates":[131.49511999999999,46.75656],"type":"Point"}
}