{
  "type": "Feature",
  "properties": {
    "gn:admin1_code":"32.0",
    "gn:asciiname":"Buyizuo",
    "gn:country_code":"CN",
    "gn:dem":1251,
    "gn:feature_class":"P",
    "gn:feature_code":"PPL",
    "gn:name":"Buyizuo",
    "gn:population":0,
    "gn:timezone":"Asia/Shanghai",
    "iso:country":"CN",
    "name:zho_x_preferred":[
        "\u8865\u8863\u4f5c"
    ],
    "wof:name":"Buyizuo",
    "wof:placetype":"locality"
},
  "geometry": {"coordinates":[103.39,28.68],"type":"Point"}
}