{
  "type": "Feature",
  "properties": {
    "gn:admin1_code":"16.0",
    "gn:asciiname":"Danian",
    "gn:country_code":"CN",
    "gn:dem":130,
    "gn:feature_class":"P",
    "gn:feature_code":"PPL",
    "gn:name":"Danian",
    "gn:population":0,
    "gn:timezone":"Asia/Shanghai",
    "iso:country":"CN",
    "name:zho_x_preferred":[
        "\u5927\u5e74"
    ],
    "wof:name":"Danian",
    "wof:placetype":"locality"
},
  "geometry": {"coordinates":[109.098,23.8955],"type":"Point"}
}