{
  "type": "Feature",
  "properties": {
    "gn:admin1_code":"29.0",
    "gn:asciiname":"Guanposi",
    "gn:country_code":"CN",
    "gn:dem":1877,
    "gn:feature_class":"P",
    "gn:feature_code":"PPL",
    "gn:name":"Guanposi",
    "gn:population":0,
    "gn:timezone":"Asia/Shanghai",
    "iso:country":"CN",
    "name:zho_x_preferred":[
        "\u5b98\u5761\u5bfa"
    ],
    "wof:name":"Guanposi",
    "wof:placetype":"locality"
},
  "geometry": {"coordinates":[103.80500000000001,25.5044],"type":"Point"}
}