{
  "type": "Feature",
  "properties": {
    "gn:admin1_code":"29",
    "gn:asciiname":"Shangquanfu",
    "gn:country_code":"CN",
    "gn:dem":1905,
    "gn:feature_class":"P",
    "gn:feature_code":"PPL",
    "gn:name":"Shangquanfu",
    "gn:population":0,
    "gn:timezone":"Asia/Shanghai",
    "iso:country":"CN",
    "name:zho_x_preferred":[
        "\u4e0a\u6743\u752b"
    ],
    "wof:name":"Shangquanfu",
    "wof:placetype":"locality"
},
  "geometry": {"coordinates":[102.383,24.9096],"type":"Point"}
}