{
  "type": "Feature",
  "properties": {
    "gn:admin1_code":"12.0",
    "gn:asciiname":"Panxiang Dawu",
    "gn:country_code":"CN",
    "gn:dem":96,
    "gn:feature_class":"P",
    "gn:feature_code":"PPL",
    "gn:name":"Panxiang Dawu",
    "gn:population":0,
    "gn:timezone":"Asia/Shanghai",
    "iso:country":"CN",
    "name:zho_x_preferred":[
        "Panxiang Dawu"
    ],
    "name:zho_x_variant":[
        "\u6f58\u7965\u5927\u5c4b"
    ],
    "wof:name":"Panxiang Dawu",
    "wof:placetype":"locality"
},
  "geometry": {"coordinates":[115.02958999999998,29.96585],"type":"Point"}
}