{
  "type": "Feature",
  "properties": {
    "gn:admin1_code":"15.0",
    "gn:asciiname":"Nanba Erdui",
    "gn:country_code":"CN",
    "gn:dem":1411,
    "gn:feature_class":"P",
    "gn:feature_code":"PPLF",
    "gn:name":"Nanba Erdui",
    "gn:population":0,
    "gn:timezone":"Asia/Shanghai",
    "iso:country":"CN",
    "name:zho_x_preferred":[
        "\u5357\u575d\u4e8c\u961f"
    ],
    "wof:name":"Nanba Erdui",
    "wof:placetype":"locality"
},
  "geometry": {"coordinates":[98.6078,39.9109],"type":"Point"}
}