{
  "type": "Feature",
  "properties": {
    "gn:admin1_code":"14.0",
    "gn:asciiname":"Kulung",
    "gn:country_code":"CN",
    "gn:dem":4119,
    "gn:feature_class":"P",
    "gn:feature_code":"PPLF",
    "gn:name":"Kulung",
    "gn:population":0,
    "gn:timezone":"Asia/Urumqi",
    "iso:country":"CN",
    "name:bod_x_preferred":[
        "Kulung"
    ],
    "name:zho_x_preferred":[
        "Kulong"
    ],
    "name:zho_x_variant":[
        "\u82e6\u9f99"
    ],
    "wof:name":"Kulung",
    "wof:placetype":"locality"
},
  "geometry": {"coordinates":[89.67723000000002,29.31075],"type":"Point"}
}