{
  "type": "Feature",
  "properties": {
    "gn:admin1_code":"4.0",
    "gn:asciiname":"Huajiazhuang",
    "gn:country_code":"CN",
    "gn:dem":4,
    "gn:feature_class":"P",
    "gn:feature_code":"PPL",
    "gn:name":"Huajiazhuang",
    "gn:population":0,
    "gn:timezone":"Asia/Shanghai",
    "iso:country":"CN",
    "name:zho_x_preferred":[
        "Huajiazhuang"
    ],
    "name:zho_x_variant":[
        "\u82b1\u5bb6\u5e84"
    ],
    "wof:name":"Huajiazhuang",
    "wof:placetype":"locality"
},
  "geometry": {"coordinates":[119.32129999999999,33.25918],"type":"Point"}
}