{
  "type": "Feature",
  "properties": {
    "gn:admin1_code":"4.0",
    "gn:asciiname":"Ganquancun",
    "gn:country_code":"CN",
    "gn:dem":21,
    "gn:feature_class":"P",
    "gn:feature_code":"PPL",
    "gn:name":"Ganquancun",
    "gn:population":0,
    "gn:timezone":"Asia/Shanghai",
    "iso:country":"CN",
    "name:zho_x_preferred":[
        "\u7518\u6cc9\u6751"
    ],
    "wof:name":"Ganquancun",
    "wof:placetype":"locality"
},
  "geometry": {"coordinates":[118.54651,33.06952],"type":"Point"}
}