{
  "type": "Feature",
  "properties": {
    "gn:admin1_code":"15.0",
    "gn:asciiname":"Xingjiawan",
    "gn:country_code":"CN",
    "gn:dem":2147,
    "gn:feature_class":"P",
    "gn:feature_code":"PPL",
    "gn:name":"Xingjiawan",
    "gn:population":0,
    "gn:timezone":"Asia/Shanghai",
    "iso:country":"CN",
    "name:zho_x_preferred":[
        "\u90a2\u5bb6\u6e7e"
    ],
    "wof:name":"Xingjiawan",
    "wof:placetype":"locality"
},
  "geometry": {"coordinates":[103.223,36.7572],"type":"Point"}
}