{
  "type": "Feature",
  "properties": {
    "gn:admin1_code":"8.0",
    "gn:asciiname":"Xigoutun",
    "gn:country_code":"CN",
    "gn:dem":177,
    "gn:feature_class":"P",
    "gn:feature_code":"PPL",
    "gn:name":"Xigoutun",
    "gn:population":0,
    "gn:timezone":"Asia/Shanghai",
    "iso:country":"CN",
    "name:zho_x_preferred":[
        "\u897f\u6c9f\u5c6f"
    ],
    "wof:name":"Xigoutun",
    "wof:placetype":"locality"
},
  "geometry": {"coordinates":[123.09193999999999,47.00832],"type":"Point"}
}