{
  "type": "Feature",
  "properties": {
    "gn:admin1_code":"4.0",
    "gn:asciiname":"Shiloucun",
    "gn:country_code":"CN",
    "gn:dem":43,
    "gn:feature_class":"P",
    "gn:feature_code":"PPL",
    "gn:name":"Shiloucun",
    "gn:population":0,
    "gn:timezone":"Asia/Shanghai",
    "iso:country":"CN",
    "name:zho_x_preferred":[
        "\u77f3\u697c\u6751"
    ],
    "wof:name":"Shiloucun",
    "wof:placetype":"locality"
},
  "geometry": {"coordinates":[116.70269999999999,34.63788],"type":"Point"}
}