{
  "type": "Feature",
  "properties": {
    "gn:admin1_code":"4.0",
    "gn:asciiname":"Xudongcun",
    "gn:country_code":"CN",
    "gn:dem":22,
    "gn:feature_class":"P",
    "gn:feature_code":"PPL",
    "gn:name":"Xudongcun",
    "gn:population":0,
    "gn:timezone":"Asia/Shanghai",
    "iso:country":"CN",
    "name:zho_x_preferred":[
        "\u5729\u4e1c\u6751"
    ],
    "wof:name":"Xudongcun",
    "wof:placetype":"locality"
},
  "geometry": {"coordinates":[118.038,33.7875],"type":"Point"}
}