{
  "type": "Feature",
  "properties": {
    "gn:admin1_code":"9.0",
    "gn:asciiname":"Daqianduo",
    "gn:country_code":"CN",
    "gn:dem":631,
    "gn:feature_class":"P",
    "gn:feature_code":"PPL",
    "gn:name":"Daqianduo",
    "gn:population":0,
    "gn:timezone":"Asia/Shanghai",
    "iso:country":"CN",
    "name:zho_x_preferred":[
        "\u5927\u524d\u579b"
    ],
    "wof:name":"Daqianduo",
    "wof:placetype":"locality"
},
  "geometry": {"coordinates":[112.44229,33.78973],"type":"Point"}
}