{
  "type": "Feature",
  "properties": {
    "gn:admin1_code":"11",
    "gn:asciiname":"Dawanling",
    "gn:country_code":"CN",
    "gn:dem":922,
    "gn:feature_class":"P",
    "gn:feature_code":"PPL",
    "gn:name":"Dawanling",
    "gn:population":0,
    "gn:timezone":"Asia/Shanghai",
    "iso:country":"CN",
    "name:und_x_variant":[
        "\u5927\u6e7e\u5cad",
        "Dawanling"
    ],
    "wof:name":"Dawanling",
    "wof:placetype":"locality"
},
  "geometry": {"coordinates":[111.95278,25.97667],"type":"Point"}
}