{
  "type": "Feature",
  "properties": {
    "gn:admin1_code":"1.0",
    "gn:asciiname":"Luotiancun",
    "gn:country_code":"CN",
    "gn:dem":24,
    "gn:feature_class":"P",
    "gn:feature_code":"PPL",
    "gn:name":"Luotiancun",
    "gn:population":0,
    "gn:timezone":"Asia/Shanghai",
    "iso:country":"CN",
    "name:zho_x_preferred":[
        "\u7f57\u7530\u6751"
    ],
    "wof:name":"Luotiancun",
    "wof:placetype":"locality"
},
  "geometry": {"coordinates":[117.52544,33.48755999999999],"type":"Point"}
}