{
  "type": "Feature",
  "properties": {
    "gn:admin1_code":"21.0",
    "gn:asciiname":"Bafengou",
    "gn:country_code":"CN",
    "gn:dem":1102,
    "gn:feature_class":"P",
    "gn:feature_code":"PPL",
    "gn:name":"Bafengou",
    "gn:population":0,
    "gn:timezone":"Asia/Shanghai",
    "iso:country":"CN",
    "name:zho_x_preferred":[
        "\u516b\u5206\u6c9f"
    ],
    "wof:name":"Bafengou",
    "wof:placetype":"locality"
},
  "geometry": {"coordinates":[106.395,38.9181],"type":"Point"}
}