{
  "type": "Feature",
  "properties": {
    "gn:admin1_code":"10",
    "gn:asciiname":"Zhuanjia Fangzi",
    "gn:country_code":"CN",
    "gn:dem":770,
    "gn:feature_class":"P",
    "gn:feature_code":"PPL",
    "gn:name":"Zhuanjia Fangzi",
    "gn:population":0,
    "gn:timezone":"Asia/Shanghai",
    "iso:country":"CN",
    "name:zho_x_preferred":[
        "\u8f6c\u5bb6\u623f\u5b50"
    ],
    "wof:name":"Zhuanjia Fangzi",
    "wof:placetype":"locality"
},
  "geometry": {"coordinates":[118.95628000000001,41.16665],"type":"Point"}
}