{
  "type": "Feature",
  "properties": {
    "gn:admin1_code":"11.0",
    "gn:asciiname":"Taiyangpo",
    "gn:country_code":"CN",
    "gn:dem":318,
    "gn:feature_class":"P",
    "gn:feature_code":"PPL",
    "gn:name":"Taiyangpo",
    "gn:population":0,
    "gn:timezone":"Asia/Shanghai",
    "iso:country":"CN",
    "name:zho_x_preferred":[
        "Taiyangpo"
    ],
    "name:zho_x_variant":[
        "\u592a\u9633\u5761"
    ],
    "wof:name":"Taiyangpo",
    "wof:placetype":"locality"
},
  "geometry": {"coordinates":[111.02279,29.51603],"type":"Point"}
}