{
  "type": "Feature",
  "properties": {
    "gn:admin1_code":"5.0",
    "gn:asciiname":"Yingbishancun",
    "gn:country_code":"CN",
    "gn:dem":372,
    "gn:feature_class":"P",
    "gn:feature_code":"PPL",
    "gn:name":"Yingbishancun",
    "gn:population":0,
    "gn:timezone":"Asia/Shanghai",
    "iso:country":"CN",
    "name:zho_x_preferred":[
        "\u5f71\u58c1\u5c71\u6751"
    ],
    "wof:name":"Yingbishancun",
    "wof:placetype":"locality"
},
  "geometry": {"coordinates":[126.51306,43.127],"type":"Point"}
}