{
  "type": "Feature",
  "properties": {
    "gn:admin1_code":"30.0",
    "gn:asciiname":"Dashipai",
    "gn:country_code":"CN",
    "gn:dem":259,
    "gn:feature_class":"P",
    "gn:feature_code":"PPL",
    "gn:name":"Dashipai",
    "gn:population":0,
    "gn:timezone":"Asia/Shanghai",
    "iso:country":"CN",
    "name:und_x_variant":[
        "\u6253\u77f3\u6392"
    ],
    "name:zho_x_preferred":[
        "\u6253\u77f3\u6392"
    ],
    "wof:name":"Dashipai",
    "wof:placetype":"locality"
},
  "geometry": {"coordinates":[115.29227,23.80314],"type":"Point"}
}