{
  "type": "Feature",
  "properties": {
    "gn:admin1_code":"23.0",
    "gn:asciiname":"Heyou Chetou",
    "gn:country_code":"CN",
    "gn:dem":5,
    "gn:feature_class":"P",
    "gn:feature_code":"PPL",
    "gn:name":"Heyou Chetou",
    "gn:population":0,
    "gn:timezone":"Asia/Shanghai",
    "iso:country":"CN",
    "name:und_x_variant":[
        "\u4f55\u6cb9\u8f66\u5934"
    ],
    "wof:name":"Heyou Chetou",
    "wof:placetype":"locality"
},
  "geometry": {"coordinates":[121.49083,30.89771],"type":"Point"}
}