{
  "type": "Feature",
  "properties": {
    "gn:admin1_code":"19",
    "gn:asciiname":"Zheng'an",
    "gn:country_code":"CN",
    "gn:dem":45,
    "gn:elevation":"0.0",
    "gn:feature_class":"P",
    "gn:feature_code":"PPLA4",
    "gn:name":"Zheng\u2019an",
    "gn:population":0,
    "gn:timezone":"Asia/Shanghai",
    "iso:country":"CN",
    "name:und_x_variant":[
        "Cheng-an-p\u2019u",
        "Cheng-an-pao-ts\u2019un",
        "Zheng\u2019anpu",
        "Cheng-an-p\u2019u-ts\u2019un",
        "Cheng-an",
        "Cheng-an-pao",
        "Zheng\u2019an",
        "Zheng\u2019an Zhen"
    ],
    "name:zho_x_preferred":[
        "\u6b63\u5b89"
    ],
    "name:zho_x_variant":[
        "\u6b63\u5b89\u9547"
    ],
    "wof:name":"Zheng'an",
    "wof:placetype":"locality"
},
  "geometry": {"coordinates":[121.93044,41.70423],"type":"Point"}
}