{
  "type": "Feature",
  "properties": {
    "gn:admin1_code":"26.0",
    "gn:asciiname":"Chuanzilingcun",
    "gn:country_code":"CN",
    "gn:dem":1198,
    "gn:feature_class":"P",
    "gn:feature_code":"PPL",
    "gn:name":"Chuanzilingcun",
    "gn:population":0,
    "gn:timezone":"Asia/Shanghai",
    "iso:country":"CN",
    "name:zho_x_preferred":[
        "\u5ddd\u5b50\u5cad\u6751"
    ],
    "wof:name":"Chuanzilingcun",
    "wof:placetype":"locality"
},
  "geometry": {"coordinates":[108.20867,35.13123],"type":"Point"}
}