{
  "type": "Feature",
  "properties": {
    "gn:admin1_code":"26",
    "gn:asciiname":"Xinxingzhuang",
    "gn:country_code":"CN",
    "gn:dem":390,
    "gn:feature_class":"P",
    "gn:feature_code":"PPL",
    "gn:name":"Xinxingzhuang",
    "gn:population":0,
    "gn:timezone":"Asia/Shanghai",
    "iso:country":"CN",
    "name:und_x_variant":[
        "\u65b0\u5174\u5e84",
        "Xinxingzhuang"
    ],
    "wof:name":"Xinxingzhuang",
    "wof:placetype":"locality"
},
  "geometry": {"coordinates":[109.08581,34.60762],"type":"Point"}
}