{
  "type": "Feature",
  "properties": {
    "gn:admin1_code":"32.0",
    "gn:asciiname":"Xiping",
    "gn:country_code":"CN",
    "gn:dem":533,
    "gn:feature_class":"P",
    "gn:feature_code":"PPL",
    "gn:name":"Xiping",
    "gn:population":0,
    "gn:timezone":"Asia/Shanghai",
    "iso:country":"CN",
    "name:ceb_x_preferred":[
        "Xiping"
    ],
    "name:deu_x_preferred":[
        "Xiping"
    ],
    "name:nor_x_preferred":[
        "Xiping"
    ],
    "name:zho_x_preferred":[
        "\u897f\u5c4f"
    ],
    "wof:name":"Xiping",
    "wof:placetype":"locality"
},
  "geometry": {"coordinates":[104.61834,31.71616],"type":"Point"}
}