{
  "type": "Feature",
  "properties": {
    "gn:admin1_code":"4.0",
    "gn:asciiname":"Zhuangjidi",
    "gn:country_code":"CN",
    "gn:dem":12,
    "gn:feature_class":"P",
    "gn:feature_code":"PPL",
    "gn:name":"Zhuangjidi",
    "gn:population":0,
    "gn:timezone":"Asia/Shanghai",
    "iso:country":"CN",
    "name:zho_x_preferred":[
        "\u5e84\u57fa\u5730"
    ],
    "wof:name":"Zhuangjidi",
    "wof:placetype":"locality"
},
  "geometry": {"coordinates":[119.28609,31.33506],"type":"Point"}
}