{
  "type": "Feature",
  "properties": {
    "gn:admin1_code":"14.0",
    "gn:asciiname":"Liewacun",
    "gn:country_code":"CN",
    "gn:dem":4247,
    "gn:feature_class":"P",
    "gn:feature_code":"PPL",
    "gn:name":"Liewacun",
    "gn:population":0,
    "gn:timezone":"Asia/Urumqi",
    "iso:country":"CN",
    "name:zho_x_preferred":[
        "\u5217\u74e6\u6751"
    ],
    "wof:name":"Liewacun",
    "wof:placetype":"locality"
},
  "geometry": {"coordinates":[94.27082,31.33144],"type":"Point"}
}