{
  "type": "Feature",
  "properties": {
    "gn:admin1_code":"15.0",
    "gn:asciiname":"Yangzhuangzi",
    "gn:country_code":"CN",
    "gn:dem":2120,
    "gn:feature_class":"P",
    "gn:feature_code":"PPL",
    "gn:name":"Yangzhuangzi",
    "gn:population":0,
    "gn:timezone":"Asia/Shanghai",
    "iso:country":"CN",
    "name:zho_x_preferred":[
        "\u7f8a\u5e84\u5b50"
    ],
    "wof:name":"Yangzhuangzi",
    "wof:placetype":"locality"
},
  "geometry": {"coordinates":[101.73399999999999,38.3437],"type":"Point"}
}