{
  "type": "Feature",
  "properties": {
    "gn:admin1_code":"32.0",
    "gn:asciiname":"Juekelong",
    "gn:country_code":"CN",
    "gn:dem":3479,
    "gn:feature_class":"P",
    "gn:feature_code":"PPL",
    "gn:name":"Juekelong",
    "gn:population":0,
    "gn:timezone":"Asia/Shanghai",
    "iso:country":"CN",
    "name:zho_x_preferred":[
        "\u89c9\u67ef\u9686"
    ],
    "wof:name":"Juekelong",
    "wof:placetype":"locality"
},
  "geometry": {"coordinates":[100.089,31.5723],"type":"Point"}
}