{
  "type": "Feature",
  "properties": {
    "gn:admin1_code":"19.0",
    "gn:asciiname":"Xiaodonggou",
    "gn:country_code":"CN",
    "gn:dem":145,
    "gn:feature_class":"P",
    "gn:feature_code":"PPL",
    "gn:name":"Xiaodonggou",
    "gn:population":0,
    "gn:timezone":"Asia/Shanghai",
    "iso:country":"CN",
    "name:zho_x_preferred":[
        "\u5c0f\u4e1c\u6c9f"
    ],
    "wof:name":"Xiaodonggou",
    "wof:placetype":"locality"
},
  "geometry": {"coordinates":[120.65300000000001,41.227],"type":"Point"}
}