{
  "type": "Feature",
  "properties": {
    "gn:admin1_code":"31",
    "gn:asciiname":"Fantong",
    "gn:country_code":"CN",
    "gn:dem":604,
    "gn:feature_class":"P",
    "gn:feature_code":"PPL",
    "gn:name":"Fantong",
    "gn:population":0,
    "gn:timezone":"Asia/Shanghai",
    "iso:country":"CN",
    "name:und_x_variant":[
        "\u65b9\u901a",
        "Fanlong"
    ],
    "wof:name":"Fantong",
    "wof:placetype":"locality"
},
  "geometry": {"coordinates":[109.648,18.8614],"type":"Point"}
}