{
  "type": "Feature",
  "properties": {
    "gn:admin1_code":"18.0",
    "gn:asciiname":"Yatuo",
    "gn:country_code":"CN",
    "gn:dem":610,
    "gn:feature_class":"P",
    "gn:feature_code":"PPL",
    "gn:name":"Yatuo",
    "gn:population":0,
    "gn:timezone":"Asia/Shanghai",
    "iso:country":"CN",
    "name:zho_x_preferred":[
        "\u4e9a\u9640"
    ],
    "wof:name":"Yatuo",
    "wof:placetype":"locality"
},
  "geometry": {"coordinates":[109.05200000000001,27.0388],"type":"Point"}
}