{
  "type": "Feature",
  "properties": {
    "gn:admin1_code":"5.0",
    "gn:asciiname":"Xishan Dongwang",
    "gn:country_code":"CN",
    "gn:dem":131,
    "gn:feature_class":"P",
    "gn:feature_code":"PPL",
    "gn:name":"Xishan Dongwang",
    "gn:population":0,
    "gn:timezone":"Asia/Shanghai",
    "iso:country":"CN",
    "name:zho_x_preferred":[
        "\u897f\u5c71\u4e1c\u738b"
    ],
    "wof:name":"Xishan Dongwang",
    "wof:placetype":"locality"
},
  "geometry": {"coordinates":[123.83934000000001,45.43428],"type":"Point"}
}