{
  "type": "Feature",
  "properties": {
    "gn:admin1_code":"11.0",
    "gn:asciiname":"Longqian Zhoujia",
    "gn:country_code":"CN",
    "gn:dem":36,
    "gn:feature_class":"P",
    "gn:feature_code":"PPL",
    "gn:name":"Longqian Zhoujia",
    "gn:population":0,
    "gn:timezone":"Asia/Shanghai",
    "iso:country":"CN",
    "name:zho_x_preferred":[
        "Longqian Zhoujia"
    ],
    "name:zho_x_variant":[
        "\u9f99\u524d\u5468\u5bb6"
    ],
    "wof:name":"Longqian Zhoujia",
    "wof:placetype":"locality"
},
  "geometry": {"coordinates":[111.81491,29.15479],"type":"Point"}
}