{
  "type": "Feature",
  "properties": {
    "gn:admin1_code":"10",
    "gn:asciiname":"Dongwanzi",
    "gn:country_code":"CN",
    "gn:dem":1055,
    "gn:feature_class":"P",
    "gn:feature_code":"PPL",
    "gn:name":"Dongwanzi",
    "gn:population":0,
    "gn:timezone":"Asia/Shanghai",
    "iso:country":"CN",
    "name:zho_x_preferred":[
        "\u4e1c\u6e7e\u5b50"
    ],
    "wof:name":"Dongwanzi",
    "wof:placetype":"locality"
},
  "geometry": {"coordinates":[116.54102,41.67875],"type":"Point"}
}