{
  "type": "Feature",
  "properties": {
    "gn:admin1_code":"7.0",
    "gn:asciiname":"Lisidou",
    "gn:country_code":"CN",
    "gn:dem":846,
    "gn:feature_class":"P",
    "gn:feature_code":"PPL",
    "gn:name":"Lisidou",
    "gn:population":0,
    "gn:timezone":"Asia/Shanghai",
    "iso:country":"CN",
    "name:zho_x_preferred":[
        "\u91cc\u56db\u6597"
    ],
    "wof:name":"Lisidou",
    "wof:placetype":"locality"
},
  "geometry": {"coordinates":[119.33553999999999,26.77122],"type":"Point"}
}