{
  "type": "Feature",
  "properties": {
    "gn:admin1_code":"10",
    "gn:asciiname":"Gaozhazi",
    "gn:country_code":"CN",
    "gn:dem":1313,
    "gn:feature_class":"P",
    "gn:feature_code":"PPL",
    "gn:name":"Gaozhazi",
    "gn:population":0,
    "gn:timezone":"Asia/Shanghai",
    "iso:country":"CN",
    "name:zho_x_preferred":[
        "\u9ad8\u6805\u5b50"
    ],
    "wof:name":"Gaozhazi",
    "wof:placetype":"locality"
},
  "geometry": {"coordinates":[115.58187,40.6175],"type":"Point"}
}