{
  "type": "Feature",
  "properties": {
    "gn:admin1_code":"25",
    "gn:asciiname":"Gaoliuzhuang",
    "gn:country_code":"CN",
    "gn:dem":59,
    "gn:feature_class":"P",
    "gn:feature_code":"PPL",
    "gn:name":"Gaoliuzhuang",
    "gn:population":0,
    "gn:timezone":"Asia/Shanghai",
    "iso:country":"CN",
    "name:zho_x_preferred":[
        "\u9ad8\u5218\u5e84"
    ],
    "wof:name":"Gaoliuzhuang",
    "wof:placetype":"locality"
},
  "geometry": {"coordinates":[115.851,34.6351],"type":"Point"}
}