{
  "type": "Feature",
  "properties": {
    "gn:admin1_code":"18",
    "gn:asciiname":"Wenjiaba",
    "gn:country_code":"CN",
    "gn:dem":863,
    "gn:feature_class":"P",
    "gn:feature_code":"PPL",
    "gn:name":"Wenjiaba",
    "gn:population":0,
    "gn:timezone":"Asia/Shanghai",
    "iso:country":"CN",
    "name:zho_x_preferred":[
        "\u6587\u5bb6\u575d"
    ],
    "wof:name":"Wenjiaba",
    "wof:placetype":"locality"
},
  "geometry": {"coordinates":[107.42100000000001,29.0255],"type":"Point"}
}