{
  "type": "Feature",
  "properties": {
    "gn:admin1_code":"3.0",
    "gn:asciiname":"Xintang Linchang",
    "gn:country_code":"CN",
    "gn:dem":118,
    "gn:feature_class":"P",
    "gn:feature_code":"PPLF",
    "gn:name":"Xintang Linchang",
    "gn:population":0,
    "gn:timezone":"Asia/Shanghai",
    "iso:country":"CN",
    "name:und_x_variant":[
        "\u65b0\u5858\u6797\u573a"
    ],
    "wof:name":"Xintang Linchang",
    "wof:placetype":"locality"
},
  "geometry": {"coordinates":[114.52646,27.95719],"type":"Point"}
}