{
  "type": "Feature",
  "properties": {
    "gn:admin1_code":"29.0",
    "gn:asciiname":"Gengdiying",
    "gn:country_code":"CN",
    "gn:dem":1941,
    "gn:feature_class":"P",
    "gn:feature_code":"PPL",
    "gn:name":"Gengdiying",
    "gn:population":0,
    "gn:timezone":"Asia/Shanghai",
    "iso:country":"CN",
    "name:zho_x_preferred":[
        "\u66f4\u5e95\u8425"
    ],
    "wof:name":"Gengdiying",
    "wof:placetype":"locality"
},
  "geometry": {"coordinates":[104.462,26.1477],"type":"Point"}
}