{
  "type": "Feature",
  "properties": {
    "gn:admin1_code":"29",
    "gn:asciiname":"Chahuaqing",
    "gn:country_code":"CN",
    "gn:dem":2202,
    "gn:feature_class":"P",
    "gn:feature_code":"PPL",
    "gn:name":"Chahuaqing",
    "gn:population":0,
    "gn:timezone":"Asia/Shanghai",
    "iso:country":"CN",
    "name:zho_x_preferred":[
        "\u8336\u82b1\u7b90"
    ],
    "wof:name":"Chahuaqing",
    "wof:placetype":"locality"
},
  "geometry": {"coordinates":[103.024,24.2163],"type":"Point"}
}