{
  "type": "Feature",
  "properties": {
    "gn:admin1_code":"7.0",
    "gn:asciiname":"Meixicun",
    "gn:country_code":"CN",
    "gn:dem":17,
    "gn:feature_class":"P",
    "gn:feature_code":"PPL",
    "gn:name":"Meixicun",
    "gn:population":0,
    "gn:timezone":"Asia/Shanghai",
    "iso:country":"CN",
    "name:zho_x_preferred":[
        "\u6885\u897f\u6751"
    ],
    "wof:name":"Meixicun",
    "wof:placetype":"locality"
},
  "geometry": {"coordinates":[117.55916000000001,24.12113],"type":"Point"}
}