{
  "type": "Feature",
  "properties": {
    "gn:admin1_code":"1.0",
    "gn:asciiname":"Nanfeng",
    "gn:country_code":"CN",
    "gn:dem":15,
    "gn:feature_class":"P",
    "gn:feature_code":"PPLA4",
    "gn:name":"Nanfeng",
    "gn:population":0,
    "gn:timezone":"Asia/Shanghai",
    "iso:country":"CN",
    "name:und_x_variant":[
        "Quantoushan",
        "\u62f3\u5934\u5c71",
        "Nanfeng Zhen",
        "Nanfeng",
        "\u5357\u4e30\u9547",
        "\u5357\u4e30"
    ],
    "wof:name":"Nanfeng",
    "wof:placetype":"locality"
},
  "geometry": {"coordinates":[119.21508,31.06918],"type":"Point"}
}