{
  "type": "Feature",
  "properties": {
    "gn:admin1_code":"26.0",
    "gn:asciiname":"Huanghaoliangcun",
    "gn:country_code":"CN",
    "gn:dem":1058,
    "gn:feature_class":"P",
    "gn:feature_code":"PPL",
    "gn:name":"Huanghaoliangcun",
    "gn:population":0,
    "gn:timezone":"Asia/Shanghai",
    "iso:country":"CN",
    "name:zho_x_preferred":[
        "\u9ec4\u84bf\u6881\u6751"
    ],
    "wof:name":"Huanghaoliangcun",
    "wof:placetype":"locality"
},
  "geometry": {"coordinates":[110.35653000000001,38.50776],"type":"Point"}
}