{
  "type": "Feature",
  "properties": {
    "gn:admin1_code":"29.0",
    "gn:asciiname":"Tuozhe",
    "gn:country_code":"CN",
    "gn:dem":1832,
    "gn:feature_class":"P",
    "gn:feature_code":"PPL",
    "gn:name":"Tuozhe",
    "gn:population":0,
    "gn:timezone":"Asia/Shanghai",
    "iso:country":"CN",
    "name:zho_x_preferred":[
        "\u59a5\u8005"
    ],
    "wof:name":"Tuozhe",
    "wof:placetype":"locality"
},
  "geometry": {"coordinates":[104.062,24.9989],"type":"Point"}
}