{
  "type": "Feature",
  "properties": {
    "gn:admin1_code":"12.0",
    "gn:asciiname":"Caijiamen",
    "gn:country_code":"CN",
    "gn:dem":29,
    "gn:feature_class":"P",
    "gn:feature_code":"PPL",
    "gn:name":"Caijiamen",
    "gn:population":0,
    "gn:timezone":"Asia/Shanghai",
    "iso:country":"CN",
    "name:zho_x_preferred":[
        "\u8521\u5bb6\u95e8"
    ],
    "wof:name":"Caijiamen",
    "wof:placetype":"locality"
},
  "geometry": {"coordinates":[112.84724,29.86727],"type":"Point"}
}