{
  "type": "Feature",
  "properties": {
    "gn:admin1_code":"7",
    "gn:asciiname":"Caifang",
    "gn:country_code":"CN",
    "gn:dem":280,
    "gn:feature_class":"P",
    "gn:feature_code":"PPL",
    "gn:name":"Caifang",
    "gn:population":0,
    "gn:timezone":"Asia/Shanghai",
    "iso:country":"CN",
    "name:und_x_variant":[
        "\u8521\u574a"
    ],
    "wof:name":"Caifang",
    "wof:placetype":"locality"
},
  "geometry": {"coordinates":[116.39368,25.69851],"type":"Point"}
}