{
  "type": "Feature",
  "properties": {
    "gn:admin1_code":"30.0",
    "gn:asciiname":"Wangjialing",
    "gn:country_code":"CN",
    "gn:dem":249,
    "gn:feature_class":"P",
    "gn:feature_code":"PPL",
    "gn:name":"Wangjialing",
    "gn:population":0,
    "gn:timezone":"Asia/Shanghai",
    "iso:country":"CN",
    "name:zho_x_preferred":[
        "Wangjialing"
    ],
    "name:zho_x_variant":[
        "\u671b\u4f73\u5cad"
    ],
    "wof:name":"Wangjialing",
    "wof:placetype":"locality"
},
  "geometry": {"coordinates":[112.30861000000002,24.52917],"type":"Point"}
}