{
  "type": "Feature",
  "properties": {
    "gn:admin1_code":"14",
    "gn:asciiname":"Quecun",
    "gn:country_code":"CN",
    "gn:dem":3932,
    "gn:feature_class":"P",
    "gn:feature_code":"PPL",
    "gn:name":"Quecun",
    "gn:population":0,
    "gn:timezone":"Asia/Urumqi",
    "iso:country":"CN",
    "name:zho_x_preferred":[
        "\u786e\u6751"
    ],
    "wof:name":"Quecun",
    "wof:placetype":"locality"
},
  "geometry": {"coordinates":[88.9723,27.7293],"type":"Point"}
}