{
  "type": "Feature",
  "properties": {
    "gn:admin1_code":"15.0",
    "gn:asciiname":"Dabazui",
    "gn:country_code":"CN",
    "gn:dem":1662,
    "gn:feature_class":"P",
    "gn:feature_code":"PPL",
    "gn:name":"Dabazui",
    "gn:population":0,
    "gn:timezone":"Asia/Shanghai",
    "iso:country":"CN",
    "name:zho_x_preferred":[
        "\u5927\u5df4\u5480"
    ],
    "wof:name":"Dabazui",
    "wof:placetype":"locality"
},
  "geometry": {"coordinates":[107.151,37.0627],"type":"Point"}
}