{
  "type": "Feature",
  "properties": {
    "gn:admin1_code":"25",
    "gn:asciiname":"Muchangjian",
    "gn:country_code":"CN",
    "gn:dem":163,
    "gn:feature_class":"P",
    "gn:feature_code":"PPL",
    "gn:name":"Muchangjian",
    "gn:population":0,
    "gn:timezone":"Asia/Shanghai",
    "iso:country":"CN",
    "name:zho_x_preferred":[
        "\u6728\u5382\u6da7"
    ],
    "wof:name":"Muchangjian",
    "wof:placetype":"locality"
},
  "geometry": {"coordinates":[117.498,36.6243],"type":"Point"}
}