{
  "type": "Feature",
  "properties": {
    "gn:admin1_code":"21.0",
    "gn:asciiname":"Yijiagou",
    "gn:country_code":"CN",
    "gn:dem":1924,
    "gn:feature_class":"P",
    "gn:feature_code":"PPL",
    "gn:name":"Yijiagou",
    "gn:population":0,
    "gn:timezone":"Asia/Shanghai",
    "iso:country":"CN",
    "name:zho_x_preferred":[
        "\u5f0b\u5bb6\u6c9f"
    ],
    "wof:name":"Yijiagou",
    "wof:placetype":"locality"
},
  "geometry": {"coordinates":[106.407,35.6987],"type":"Point"}
}