{
  "type": "Feature",
  "properties": {
    "gn:admin1_code":"25.0",
    "gn:asciiname":"Shangyinjia",
    "gn:country_code":"CN",
    "gn:dem":219,
    "gn:feature_class":"P",
    "gn:feature_code":"PPL",
    "gn:name":"Shangyinjia",
    "gn:population":0,
    "gn:timezone":"Asia/Shanghai",
    "iso:country":"CN",
    "name:zho_x_preferred":[
        "\u4e0a\u5c39\u5bb6"
    ],
    "wof:name":"Shangyinjia",
    "wof:placetype":"locality"
},
  "geometry": {"coordinates":[121.2276,36.94294],"type":"Point"}
}