{
  "type": "Feature",
  "properties": {
    "gn:admin1_code":"14.0",
    "gn:asciiname":"Wolongtangga",
    "gn:country_code":"CN",
    "gn:dem":4415,
    "gn:feature_class":"P",
    "gn:feature_code":"PPL",
    "gn:name":"Wolongtangga",
    "gn:population":0,
    "gn:timezone":"Asia/Urumqi",
    "iso:country":"CN",
    "name:zho_x_preferred":[
        "\u5367\u9f99\u6dcc\u5c15"
    ],
    "wof:name":"Wolongtangga",
    "wof:placetype":"locality"
},
  "geometry": {"coordinates":[86.89619999999999,28.4821],"type":"Point"}
}