{
  "type": "Feature",
  "properties": {
    "gn:admin1_code":"16.0",
    "gn:asciiname":"Maxiang",
    "gn:country_code":"CN",
    "gn:dem":702,
    "gn:feature_class":"P",
    "gn:feature_code":"PPL",
    "gn:name":"Maxiang",
    "gn:population":0,
    "gn:timezone":"Asia/Shanghai",
    "iso:country":"CN",
    "name:zho_x_preferred":[
        "\u9a6c\u5df7"
    ],
    "wof:name":"Maxiang",
    "wof:placetype":"locality"
},
  "geometry": {"coordinates":[106.55,23.1985],"type":"Point"}
}