{
  "type": "Feature",
  "properties": {
    "gn:admin1_code":"24.0",
    "gn:asciiname":"Meidong",
    "gn:country_code":"CN",
    "gn:dem":1657,
    "gn:feature_class":"P",
    "gn:feature_code":"PPL",
    "gn:name":"Meidong",
    "gn:population":0,
    "gn:timezone":"Asia/Shanghai",
    "iso:country":"CN",
    "name:und_x_variant":[
        "\u6885\u6d1e"
    ],
    "name:zho_x_preferred":[
        "\u6885\u6d1e"
    ],
    "wof:name":"Meidong",
    "wof:placetype":"locality"
},
  "geometry": {"coordinates":[111.98256000000001,38.71186],"type":"Point"}
}