{
  "type": "Feature",
  "properties": {
    "gn:admin1_code":"4.0",
    "gn:asciiname":"Nianhecun",
    "gn:country_code":"CN",
    "gn:dem":4,
    "gn:feature_class":"P",
    "gn:feature_code":"PPL",
    "gn:name":"Nianhecun",
    "gn:population":0,
    "gn:timezone":"Asia/Shanghai",
    "iso:country":"CN",
    "name:zho_x_preferred":[
        "\u5e74\u5408\u6751"
    ],
    "wof:name":"Nianhecun",
    "wof:placetype":"locality"
},
  "geometry": {"coordinates":[119.68810999999999,32.75653],"type":"Point"}
}