{
  "type": "Feature",
  "properties": {
    "gn:admin1_code":"18.0",
    "gn:asciiname":"Gaodong Xiazhai",
    "gn:country_code":"CN",
    "gn:dem":622,
    "gn:feature_class":"P",
    "gn:feature_code":"PPL",
    "gn:name":"Gaodong Xiazhai",
    "gn:population":0,
    "gn:timezone":"Asia/Shanghai",
    "iso:country":"CN",
    "name:zho_x_preferred":[
        "\u9ad8\u6d1e\u4e0b\u5be8"
    ],
    "wof:name":"Gaodong Xiazhai",
    "wof:placetype":"locality"
},
  "geometry": {"coordinates":[108.416,25.8764],"type":"Point"}
}