{
  "type": "Feature",
  "properties": {
    "gn:admin1_code":"4.0",
    "gn:asciiname":"Huinongcun",
    "gn:country_code":"CN",
    "gn:dem":5,
    "gn:feature_class":"P",
    "gn:feature_code":"PPL",
    "gn:name":"Huinongcun",
    "gn:population":0,
    "gn:timezone":"Asia/Shanghai",
    "iso:country":"CN",
    "name:zho_x_preferred":[
        "\u4f1a\u519c\u6751"
    ],
    "wof:name":"Huinongcun",
    "wof:placetype":"locality"
},
  "geometry": {"coordinates":[119.86011000000001,34.06073],"type":"Point"}
}