{
  "type": "Feature",
  "properties": {
    "gn:admin1_code":"21.0",
    "gn:asciiname":"Yangzhai",
    "gn:country_code":"CN",
    "gn:dem":1714,
    "gn:feature_class":"P",
    "gn:feature_code":"PPL",
    "gn:name":"Yangzhai",
    "gn:population":0,
    "gn:timezone":"Asia/Shanghai",
    "iso:country":"CN",
    "name:und_x_variant":[
        "\u6768\u5be8"
    ],
    "name:zho_x_preferred":[
        "\u6768\u5be8"
    ],
    "wof:name":"Yangzhai",
    "wof:placetype":"locality"
},
  "geometry": {"coordinates":[106.60231,36.06024],"type":"Point"}
}