{
  "type": "Feature",
  "properties": {
    "gn:admin1_code":"3.0",
    "gn:asciiname":"Xiatongjia",
    "gn:country_code":"CN",
    "gn:dem":299,
    "gn:feature_class":"P",
    "gn:feature_code":"PPL",
    "gn:name":"Xiatongjia",
    "gn:population":0,
    "gn:timezone":"Asia/Shanghai",
    "iso:country":"CN",
    "name:und_x_variant":[
        "\u4e0b\u7ae5\u5bb6"
    ],
    "wof:name":"Xiatongjia",
    "wof:placetype":"locality"
},
  "geometry": {"coordinates":[115.23165,29.02328],"type":"Point"}
}