{
  "type": "Feature",
  "properties": {
    "gn:admin1_code":"15.0",
    "gn:asciiname":"Yuandixia",
    "gn:country_code":"CN",
    "gn:dem":1827,
    "gn:feature_class":"P",
    "gn:feature_code":"PPL",
    "gn:name":"Yuandixia",
    "gn:population":0,
    "gn:timezone":"Asia/Shanghai",
    "iso:country":"CN",
    "name:und_x_variant":[
        "\u5706\u5730\u4e0b"
    ],
    "wof:name":"Yuandixia",
    "wof:placetype":"locality"
},
  "geometry": {"coordinates":[104.78189999999999,34.90083],"type":"Point"}
}