{
  "type": "Feature",
  "properties": {
    "gn:admin1_code":"7.0",
    "gn:asciiname":"Qiuyuantou",
    "gn:country_code":"CN",
    "gn:dem":192,
    "gn:feature_class":"P",
    "gn:feature_code":"PPL",
    "gn:name":"Qiuyuantou",
    "gn:population":0,
    "gn:timezone":"Asia/Shanghai",
    "iso:country":"CN",
    "name:zho_x_preferred":[
        "\u90b1\u5143\u5934"
    ],
    "wof:name":"Qiuyuantou",
    "wof:placetype":"locality"
},
  "geometry": {"coordinates":[117.67801,27.12531],"type":"Point"}
}