{
  "type": "Feature",
  "properties": {
    "gn:admin1_code":"29",
    "gn:asciiname":"Badi",
    "gn:country_code":"CN",
    "gn:dem":3930,
    "gn:feature_class":"P",
    "gn:feature_code":"PPLA4",
    "gn:name":"Badi",
    "gn:population":0,
    "gn:timezone":"Asia/Shanghai",
    "iso:country":"CN",
    "name:ceb_x_preferred":[
        "Badi"
    ],
    "name:deu_x_preferred":[
        "Badi"
    ],
    "name:ita_x_preferred":[
        "Badi"
    ],
    "name:rus_x_preferred":[
        "\u0411\u0430\u0434\u0438"
    ],
    "name:swe_x_preferred":[
        "Badi"
    ],
    "name:tur_x_preferred":[
        "Badi"
    ],
    "name:und_x_variant":[
        "Badi Xiang",
        "\u5df4\u8fea\u4e61",
        "Badi"
    ],
    "name:zho_x_preferred":[
        "\u5df4\u8fea"
    ],
    "wof:name":"Badi",
    "wof:placetype":"locality"
},
  "geometry": {"coordinates":[99.09076,27.88013],"type":"Point"}
}