{
  "type": "Feature",
  "properties": {
    "gn:admin1_code":"14.0",
    "gn:asciiname":"Nagjog",
    "gn:country_code":"CN",
    "gn:dem":4665,
    "gn:feature_class":"P",
    "gn:feature_code":"PPLF",
    "gn:name":"Nagjog",
    "gn:population":0,
    "gn:timezone":"Asia/Urumqi",
    "iso:country":"CN",
    "name:bod_x_preferred":[
        "Nagjog"
    ],
    "name:msa_x_preferred":[
        "Nagjog"
    ],
    "name:zho_x_preferred":[
        "Lajiu"
    ],
    "name:zho_x_variant":[
        "\u814a\u4e45",
        "Yuding",
        "\u9c7c\u9876"
    ],
    "wof:name":"Nagjog",
    "wof:placetype":"locality"
},
  "geometry": {"coordinates":[96.11667,30.53333],"type":"Point"}
}