{
  "type": "Feature",
  "properties": {
    "gn:admin1_code":"29.0",
    "gn:asciiname":"Sishituo",
    "gn:country_code":"CN",
    "gn:dem":2580,
    "gn:feature_class":"P",
    "gn:feature_code":"PPL",
    "gn:name":"Sishituo",
    "gn:population":0,
    "gn:timezone":"Asia/Shanghai",
    "iso:country":"CN",
    "name:zho_x_preferred":[
        "\u56db\u5341\u9a6e"
    ],
    "wof:name":"Sishituo",
    "wof:placetype":"locality"
},
  "geometry": {"coordinates":[99.3484,27.0201],"type":"Point"}
}