{
  "type": "Feature",
  "properties": {
    "gn:admin1_code":"18",
    "gn:asciiname":"Datie",
    "gn:country_code":"CN",
    "gn:dem":993,
    "gn:feature_class":"P",
    "gn:feature_code":"PPL",
    "gn:name":"Datie",
    "gn:population":0,
    "gn:timezone":"Asia/Shanghai",
    "iso:country":"CN",
    "wof:name":"Datie",
    "wof:placetype":"locality"
},
  "geometry": {"coordinates":[107.27861,26.31639],"type":"Point"}
}