{
  "type": "Feature",
  "properties": {
    "gn:admin1_code":"4.0",
    "gn:asciiname":"Liuyuan",
    "gn:country_code":"CN",
    "gn:dem":5,
    "gn:feature_class":"P",
    "gn:feature_code":"PPL",
    "gn:name":"Liuyuan",
    "gn:population":0,
    "gn:timezone":"Asia/Shanghai",
    "iso:country":"CN",
    "name:zho_x_preferred":[
        "Liuyuan"
    ],
    "name:zho_x_variant":[
        "\u67f3\u56ed"
    ],
    "wof:name":"Liuyuan",
    "wof:placetype":"locality"
},
  "geometry": {"coordinates":[121.11048999999998,31.57793],"type":"Point"}
}