{
  "type": "Feature",
  "properties": {
    "gn:admin1_code":"4.0",
    "gn:asciiname":"Shelu",
    "gn:country_code":"CN",
    "gn:dem":9,
    "gn:feature_class":"P",
    "gn:feature_code":"PPL",
    "gn:name":"Shelu",
    "gn:population":0,
    "gn:timezone":"Asia/Shanghai",
    "iso:country":"CN",
    "name:mar_x_preferred":[
        "\u0936\u0947\u0932\u0942"
    ],
    "name:urd_x_preferred":[
        "\u0634\u06cc\u0644\u0648"
    ],
    "name:zho_x_preferred":[
        "\u820d\u9646"
    ],
    "wof:name":"Shelu",
    "wof:placetype":"locality"
},
  "geometry": {"coordinates":[120.17798000000001,32.2964],"type":"Point"}
}