{
  "type": "Feature",
  "properties": {
    "gn:admin1_code":"26.0",
    "gn:asciiname":"Xincaiwancun",
    "gn:country_code":"CN",
    "gn:dem":927,
    "gn:feature_class":"P",
    "gn:feature_code":"PPL",
    "gn:name":"Xincaiwancun",
    "gn:population":0,
    "gn:timezone":"Asia/Shanghai",
    "iso:country":"CN",
    "name:zho_x_preferred":[
        "\u65b0\u624d\u6e7e\u6751"
    ],
    "wof:name":"Xincaiwancun",
    "wof:placetype":"locality"
},
  "geometry": {"coordinates":[110.52842,38.2461],"type":"Point"}
}