{
  "type": "Feature",
  "properties": {
    "gn:admin1_code":"11.0",
    "gn:asciiname":"Xiadu",
    "gn:country_code":"CN",
    "gn:dem":149,
    "gn:feature_class":"P",
    "gn:feature_code":"PPL",
    "gn:name":"Xiadu",
    "gn:population":0,
    "gn:timezone":"Asia/Shanghai",
    "iso:country":"CN",
    "name:ita_x_preferred":[
        "Xiadu"
    ],
    "name:kor_x_preferred":[
        "\ud558\ub3c4"
    ],
    "name:swe_x_preferred":[
        "Xiadu"
    ],
    "name:zho_x_preferred":[
        "\u4e0b\u90fd"
    ],
    "name:zho_x_variant":[
        "\u71d5\u4e0b\u90fd"
    ],
    "wof:name":"Xiadu",
    "wof:placetype":"locality"
},
  "geometry": {"coordinates":[109.9669,28.25745],"type":"Point"}
}