{
  "type": "Feature",
  "properties": {
    "gn:admin1_code":"13",
    "gn:asciiname":"Tuogela Keleke",
    "gn:country_code":"CN",
    "gn:dem":1279,
    "gn:feature_class":"P",
    "gn:feature_code":"PPL",
    "gn:name":"Tuogela Keleke",
    "gn:population":0,
    "gn:timezone":"Asia/Shanghai",
    "iso:country":"CN",
    "name:und_x_variant":[
        "\u6258\u683c\u62c9\u514b\u52d2\u514b"
    ],
    "wof:name":"Tuogela Keleke",
    "wof:placetype":"locality"
},
  "geometry": {"coordinates":[77.30169000000002,38.07867],"type":"Point"}
}