{
  "type": "Feature",
  "properties": {
    "gn:admin1_code":"29.0",
    "gn:asciiname":"Shansongshu",
    "gn:country_code":"CN",
    "gn:dem":2780,
    "gn:feature_class":"P",
    "gn:feature_code":"PPL",
    "gn:name":"Shansongshu",
    "gn:population":0,
    "gn:timezone":"Asia/Shanghai",
    "iso:country":"CN",
    "name:zho_x_preferred":[
        "\u6749\u677e\u6811"
    ],
    "wof:name":"Shansongshu",
    "wof:placetype":"locality"
},
  "geometry": {"coordinates":[99.541,25.9238],"type":"Point"}
}