{
  "type": "Feature",
  "properties": {
    "gn:admin1_code":"02",
    "gn:asciiname":"Songqiao",
    "gn:country_code":"CN",
    "gn:dem":7,
    "gn:feature_class":"P",
    "gn:feature_code":"PPL",
    "gn:name":"Songqiao",
    "gn:population":0,
    "gn:timezone":"Asia/Shanghai",
    "iso:country":"CN",
    "name:und_x_variant":[
        "Songqiaozhen",
        "Daitou",
        "Songqiao"
    ],
    "name:zho_x_preferred":[
        "\u5b8b\u6865"
    ],
    "wof:name":"Songqiao",
    "wof:placetype":"locality"
},
  "geometry": {"coordinates":[120.5813,27.73197],"type":"Point"}
}