{
  "type": "Feature",
  "properties": {
    "gn:admin1_code":"30",
    "gn:asciiname":"Jiufukeng",
    "gn:country_code":"CN",
    "gn:dem":17,
    "gn:feature_class":"P",
    "gn:feature_code":"PPL",
    "gn:name":"Jiufukeng",
    "gn:population":0,
    "gn:timezone":"Asia/Shanghai",
    "iso:country":"CN",
    "name:zho_x_preferred":[
        "\u65e7\u5bcc\u5751"
    ],
    "wof:name":"Jiufukeng",
    "wof:placetype":"locality"
},
  "geometry": {"coordinates":[112.45922,21.99381],"type":"Point"}
}