{
  "type": "Feature",
  "properties": {
    "gn:admin1_code":"29.0",
    "gn:asciiname":"Tumu",
    "gn:country_code":"CN",
    "gn:dem":1927,
    "gn:feature_class":"P",
    "gn:feature_code":"PPL",
    "gn:name":"Tumu",
    "gn:population":0,
    "gn:timezone":"Asia/Shanghai",
    "iso:country":"CN",
    "name:ceb_x_preferred":[
        "Tumu"
    ],
    "name:deu_x_preferred":[
        "Tumu"
    ],
    "name:ind_x_preferred":[
        "Tumu"
    ],
    "name:nld_x_preferred":[
        "Tumu"
    ],
    "name:swe_x_preferred":[
        "Tumu"
    ],
    "name:und_x_variant":[
        "\u571f\u6728"
    ],
    "wof:name":"Tumu",
    "wof:placetype":"locality"
},
  "geometry": {"coordinates":[104.46655,26.15376],"type":"Point"}
}