{
  "type": "Feature",
  "properties": {
    "gn:admin1_code":"19.0",
    "gn:asciiname":"Chenjiawobu",
    "gn:country_code":"CN",
    "gn:dem":38,
    "gn:feature_class":"P",
    "gn:feature_code":"PPL",
    "gn:name":"Chenjiawobu",
    "gn:population":0,
    "gn:timezone":"Asia/Shanghai",
    "iso:country":"CN",
    "name:zho_x_preferred":[
        "\u9648\u5bb6\u7a9d\u5821"
    ],
    "wof:name":"Chenjiawobu",
    "wof:placetype":"locality"
},
  "geometry": {"coordinates":[122.648,42.0033],"type":"Point"}
}