{
  "type": "Feature",
  "properties": {
    "gn:admin1_code":"30",
    "gn:asciiname":"Huage",
    "gn:country_code":"CN",
    "gn:dem":125,
    "gn:feature_class":"P",
    "gn:feature_code":"PPL",
    "gn:name":"Huage",
    "gn:population":0,
    "gn:timezone":"Asia/Shanghai",
    "iso:country":"CN",
    "name:zho_x_preferred":[
        "\u534e\u9601"
    ],
    "name:zho_x_variant":[
        "\u534e\u9601\u9547"
    ],
    "wof:name":"Huage",
    "wof:placetype":"locality"
},
  "geometry": {"coordinates":[115.73699000000001,23.84335],"type":"Point"}
}