{
  "type": "Feature",
  "properties": {
    "gn:admin1_code":"25",
    "gn:asciiname":"Luguanzhuang",
    "gn:country_code":"CN",
    "gn:dem":67,
    "gn:feature_class":"P",
    "gn:feature_code":"PPL",
    "gn:name":"Luguanzhuang",
    "gn:population":0,
    "gn:timezone":"Asia/Shanghai",
    "iso:country":"CN",
    "name:zho_x_preferred":[
        "\u5362\u5b98\u5e84"
    ],
    "wof:name":"Luguanzhuang",
    "wof:placetype":"locality"
},
  "geometry": {"coordinates":[118.63200000000001,35.0653],"type":"Point"}
}