{
  "type": "Feature",
  "properties": {
    "gn:admin1_code":"10.0",
    "gn:asciiname":"Dongchengzai",
    "gn:country_code":"CN",
    "gn:dem":167,
    "gn:feature_class":"P",
    "gn:feature_code":"PPL",
    "gn:name":"Dongchengzai",
    "gn:population":0,
    "gn:timezone":"Asia/Shanghai",
    "iso:country":"CN",
    "name:und_x_variant":[
        "\u4e1c\u57ce\u4ed4"
    ],
    "wof:name":"Dongchengzai",
    "wof:placetype":"locality"
},
  "geometry": {"coordinates":[114.45372999999999,38.59161],"type":"Point"}
}