{
  "type": "Feature",
  "properties": {
    "gn:admin1_code":"30.0",
    "gn:asciiname":"Hudong",
    "gn:country_code":"CN",
    "gn:dem":326,
    "gn:feature_class":"P",
    "gn:feature_code":"PPL",
    "gn:name":"Hudong",
    "gn:population":0,
    "gn:timezone":"Asia/Shanghai",
    "iso:country":"CN",
    "name:zho_x_preferred":[
        "Hudong"
    ],
    "name:zho_x_variant":[
        "\u6e56\u6d1e"
    ],
    "wof:name":"Hudong",
    "wof:placetype":"locality"
},
  "geometry": {"coordinates":[112.47667,24.20083],"type":"Point"}
}