{
  "type": "Feature",
  "properties": {
    "gn:admin1_code":"26.0",
    "gn:asciiname":"Pangjiagou",
    "gn:country_code":"CN",
    "gn:dem":1173,
    "gn:feature_class":"P",
    "gn:feature_code":"PPL",
    "gn:name":"Pangjiagou",
    "gn:population":0,
    "gn:timezone":"Asia/Shanghai",
    "iso:country":"CN",
    "name:und_x_variant":[
        "\u5e9e\u5bb6\u6c9f"
    ],
    "wof:name":"Pangjiagou",
    "wof:placetype":"locality"
},
  "geometry": {"coordinates":[107.43245,34.9004],"type":"Point"}
}