{
  "type": "Feature",
  "properties": {
    "gn:admin1_code":"15.0",
    "gn:asciiname":"Gongjiazhuang",
    "gn:country_code":"CN",
    "gn:dem":2202,
    "gn:feature_class":"P",
    "gn:feature_code":"PPL",
    "gn:name":"Gongjiazhuang",
    "gn:population":0,
    "gn:timezone":"Asia/Shanghai",
    "iso:country":"CN",
    "name:und_x_variant":[
        "\u9f9a\u5bb6\u5e84"
    ],
    "wof:name":"Gongjiazhuang",
    "wof:placetype":"locality"
},
  "geometry": {"coordinates":[102.86135,35.7709],"type":"Point"}
}