{
  "type": "Feature",
  "properties": {
    "gn:admin1_code":"30",
    "gn:asciiname":"Dajiaozhai",
    "gn:country_code":"CN",
    "gn:dem":60,
    "gn:feature_class":"P",
    "gn:feature_code":"PPL",
    "gn:name":"Dajiaozhai",
    "gn:population":0,
    "gn:timezone":"Asia/Shanghai",
    "iso:country":"CN",
    "name:zho_x_preferred":[
        "\u5927\u89d2\u5be8"
    ],
    "wof:name":"Dajiaozhai",
    "wof:placetype":"locality"
},
  "geometry": {"coordinates":[115.58152,23.26683],"type":"Point"}
}