{
  "type": "Feature",
  "properties": {
    "gn:admin1_code":"32.0",
    "gn:asciiname":"Jiagetuo",
    "gn:country_code":"CN",
    "gn:dem":3498,
    "gn:feature_class":"P",
    "gn:feature_code":"PPL",
    "gn:name":"Jiagetuo",
    "gn:population":0,
    "gn:timezone":"Asia/Shanghai",
    "iso:country":"CN",
    "name:zho_x_preferred":[
        "\u94be\u5404\u6258"
    ],
    "wof:name":"Jiagetuo",
    "wof:placetype":"locality"
},
  "geometry": {"coordinates":[101.613,33.0228],"type":"Point"}
}