{
  "type": "Feature",
  "properties": {
    "gn:admin1_code":"15.0",
    "gn:asciiname":"Guolianghe",
    "gn:country_code":"CN",
    "gn:dem":1516,
    "gn:feature_class":"P",
    "gn:feature_code":"PPL",
    "gn:name":"Guolianghe",
    "gn:population":0,
    "gn:timezone":"Asia/Shanghai",
    "iso:country":"CN",
    "name:und_x_variant":[
        "\u90ed\u6881\u6cb3"
    ],
    "wof:name":"Guolianghe",
    "wof:placetype":"locality"
},
  "geometry": {"coordinates":[106.90647,36.52388],"type":"Point"}
}