{
  "type": "Feature",
  "properties": {
    "gn:admin1_code":"19.0",
    "gn:asciiname":"Daquanyan",
    "gn:country_code":"CN",
    "gn:dem":565,
    "gn:feature_class":"P",
    "gn:feature_code":"PPL",
    "gn:name":"Daquanyan",
    "gn:population":0,
    "gn:timezone":"Asia/Shanghai",
    "iso:country":"CN",
    "name:und_x_variant":[
        "\u5927\u6cc9\u773c"
    ],
    "wof:name":"Daquanyan",
    "wof:placetype":"locality"
},
  "geometry": {"coordinates":[124.69025000000001,41.54308],"type":"Point"}
}