{
  "type": "Feature",
  "properties": {
    "gn:admin1_code":"2.0",
    "gn:asciiname":"Mache",
    "gn:country_code":"CN",
    "gn:dem":67,
    "gn:feature_class":"P",
    "gn:feature_code":"PPL",
    "gn:name":"Mache",
    "gn:population":0,
    "gn:timezone":"Asia/Shanghai",
    "iso:country":"CN",
    "name:und_x_variant":[
        "\u9ebb\u8f66",
        "Mache"
    ],
    "wof:name":"Mache",
    "wof:placetype":"locality"
},
  "geometry": {"coordinates":[119.95272,29.4167],"type":"Point"}
}