{
  "type": "Feature",
  "properties": {
    "gn:admin1_code":"3.0",
    "gn:asciiname":"Majiadeng",
    "gn:country_code":"CN",
    "gn:dem":88,
    "gn:feature_class":"P",
    "gn:feature_code":"PPL",
    "gn:name":"Majiadeng",
    "gn:population":0,
    "gn:timezone":"Asia/Shanghai",
    "iso:country":"CN",
    "name:und_x_variant":[
        "\u9a6c\u5bb6\u706f"
    ],
    "wof:name":"Majiadeng",
    "wof:placetype":"locality"
},
  "geometry": {"coordinates":[115.55259,27.7807],"type":"Point"}
}