{
  "type": "Feature",
  "properties": {
    "gn:admin1_code":"22.0",
    "gn:asciiname":"Tixiazhuangcun",
    "gn:country_code":"CN",
    "gn:dem":80,
    "gn:feature_class":"P",
    "gn:feature_code":"PPL",
    "gn:name":"Tixiazhuangcun",
    "gn:population":0,
    "gn:timezone":"Asia/Shanghai",
    "iso:country":"CN",
    "name:zho_x_preferred":[
        "\u63d0\u8f96\u5e84\u6751"
    ],
    "wof:name":"Tixiazhuangcun",
    "wof:placetype":"locality"
},
  "geometry": {"coordinates":[116.87023000000001,40.35036],"type":"Point"}
}