{
  "type": "Feature",
  "properties": {
    "gn:admin1_code":"02",
    "gn:asciiname":"Qingliang'an",
    "gn:country_code":"CN",
    "gn:dem":6,
    "gn:feature_class":"P",
    "gn:feature_code":"PPL",
    "gn:name":"Qingliang\u2019an",
    "gn:population":0,
    "gn:timezone":"Asia/Shanghai",
    "iso:country":"CN",
    "name:und_x_variant":[
        "Qingliang\u2019an",
        "\u6e05\u51c9\u5eb5"
    ],
    "wof:name":"Qingliang'an",
    "wof:placetype":"locality"
},
  "geometry": {"coordinates":[120.98900999999999,30.91146],"type":"Point"}
}