{
  "type": "Feature",
  "properties": {
    "gn:admin1_code":"12.0",
    "gn:asciiname":"Yujia",
    "gn:country_code":"CN",
    "gn:dem":90,
    "gn:feature_class":"P",
    "gn:feature_code":"PPL",
    "gn:name":"Yujia",
    "gn:population":0,
    "gn:timezone":"Asia/Shanghai",
    "iso:country":"CN",
    "name:zho_x_preferred":[
        "Yujia"
    ],
    "name:zho_x_variant":[
        "\u4fde\u5bb6"
    ],
    "wof:name":"Yujia",
    "wof:placetype":"locality"
},
  "geometry": {"coordinates":[114.67739,29.68552],"type":"Point"}
}