{
  "type": "Feature",
  "properties": {
    "gn:admin1_code":"5.0",
    "gn:asciiname":"Yumin",
    "gn:country_code":"CN",
    "gn:dem":443,
    "gn:feature_class":"P",
    "gn:feature_code":"PPL",
    "gn:name":"Yumin",
    "gn:population":0,
    "gn:timezone":"Asia/Shanghai",
    "iso:country":"CN",
    "name:ceb_x_preferred":[
        "Yumin"
    ],
    "name:und_x_variant":[
        "\u6d74\u6c11"
    ],
    "wof:name":"Yumin",
    "wof:placetype":"locality"
},
  "geometry": {"coordinates":[127.81923,42.79342000000001],"type":"Point"}
}