{
  "type": "Feature",
  "properties": {
    "gn:admin1_code":"30.0",
    "gn:asciiname":"Shanghesheng",
    "gn:country_code":"CN",
    "gn:dem":-3,
    "gn:feature_class":"P",
    "gn:feature_code":"PPL",
    "gn:name":"Shanghesheng",
    "gn:population":0,
    "gn:timezone":"Asia/Shanghai",
    "iso:country":"CN",
    "name:zho_x_preferred":[
        "\u4e0a\u548c\u80dc"
    ],
    "wof:name":"Shanghesheng",
    "wof:placetype":"locality"
},
  "geometry": {"coordinates":[113.43419,22.22986],"type":"Point"}
}