{
  "type": "Feature",
  "properties": {
    "gn:admin1_code":"10",
    "gn:asciiname":"Jiulianggou",
    "gn:country_code":"CN",
    "gn:dem":723,
    "gn:feature_class":"P",
    "gn:feature_code":"PPL",
    "gn:name":"Jiulianggou",
    "gn:population":0,
    "gn:timezone":"Asia/Shanghai",
    "iso:country":"CN",
    "name:zho_x_preferred":[
        "\u4e5d\u6881\u6c9f"
    ],
    "wof:name":"Jiulianggou",
    "wof:placetype":"locality"
},
  "geometry": {"coordinates":[117.33317,41.1882],"type":"Point"}
}