{
  "type": "Feature",
  "properties": {
    "gn:admin1_code":"26",
    "gn:asciiname":"Daniucun",
    "gn:country_code":"CN",
    "gn:dem":447,
    "gn:feature_class":"P",
    "gn:feature_code":"PPL",
    "gn:name":"Daniucun",
    "gn:population":0,
    "gn:timezone":"Asia/Shanghai",
    "iso:country":"CN",
    "name:zho_x_preferred":[
        "\u5927\u725b\u6751"
    ],
    "wof:name":"Daniucun",
    "wof:placetype":"locality"
},
  "geometry": {"coordinates":[109.16538,34.72863],"type":"Point"}
}