{
  "type": "Feature",
  "properties": {
    "gn:admin1_code":"12.0",
    "gn:asciiname":"Lijiadabao",
    "gn:country_code":"CN",
    "gn:dem":1188,
    "gn:feature_class":"P",
    "gn:feature_code":"PPL",
    "gn:name":"Lijiadabao",
    "gn:population":0,
    "gn:timezone":"Asia/Shanghai",
    "iso:country":"CN",
    "name:zho_x_preferred":[
        "\u674e\u5bb6\u5927\u5305"
    ],
    "wof:name":"Lijiadabao",
    "wof:placetype":"locality"
},
  "geometry": {"coordinates":[110.83922,30.64263],"type":"Point"}
}