{
  "type": "Feature",
  "properties": {
    "gn:admin1_code":"33.0",
    "gn:asciiname":"Shuangnian",
    "gn:country_code":"CN",
    "gn:dem":614,
    "gn:feature_class":"P",
    "gn:feature_code":"PPL",
    "gn:name":"Shuangnian",
    "gn:population":0,
    "gn:timezone":"Asia/Shanghai",
    "iso:country":"CN",
    "name:zho_x_preferred":[
        "\u53cc\u78be"
    ],
    "wof:name":"Shuangnian",
    "wof:placetype":"locality"
},
  "geometry": {"coordinates":[108.00613,29.74848],"type":"Point"}
}