{
  "type": "Feature",
  "properties": {
    "gn:admin1_code":"4.0",
    "gn:asciiname":"Qusanzuolou",
    "gn:country_code":"CN",
    "gn:dem":40,
    "gn:feature_class":"P",
    "gn:feature_code":"PPL",
    "gn:name":"Qusanzuolou",
    "gn:population":0,
    "gn:timezone":"Asia/Shanghai",
    "iso:country":"CN",
    "name:zho_x_preferred":[
        "\u6e20\u4e09\u5ea7\u697c"
    ],
    "wof:name":"Qusanzuolou",
    "wof:placetype":"locality"
},
  "geometry": {"coordinates":[116.432,34.8309],"type":"Point"}
}