{
  "type": "Feature",
  "properties": {
    "gn:admin1_code":"10.0",
    "gn:asciiname":"Dingjiazhuang",
    "gn:country_code":"CN",
    "gn:dem":465,
    "gn:feature_class":"P",
    "gn:feature_code":"PPL",
    "gn:name":"Dingjiazhuang",
    "gn:population":0,
    "gn:timezone":"Asia/Shanghai",
    "iso:country":"CN",
    "name:und_x_variant":[
        "\u4e01\u5bb6\u5e84"
    ],
    "wof:name":"Dingjiazhuang",
    "wof:placetype":"locality"
},
  "geometry": {"coordinates":[114.16543,38.96256],"type":"Point"}
}