{
  "type": "Feature",
  "properties": {
    "gn:admin1_code":"18",
    "gn:asciiname":"Longjiangping",
    "gn:country_code":"CN",
    "gn:dem":1276,
    "gn:feature_class":"P",
    "gn:feature_code":"PPL",
    "gn:name":"Longjiangping",
    "gn:population":0,
    "gn:timezone":"Asia/Shanghai",
    "iso:country":"CN",
    "name:zho_x_preferred":[
        "\u9f99\u6c5f\u5e73"
    ],
    "wof:name":"Longjiangping",
    "wof:placetype":"locality"
},
  "geometry": {"coordinates":[105.566,24.9593],"type":"Point"}
}