{
  "type": "Feature",
  "properties": {
    "gn:admin1_code":"4.0",
    "gn:asciiname":"Taqiao",
    "gn:country_code":"CN",
    "gn:dem":33,
    "gn:feature_class":"P",
    "gn:feature_code":"PPL",
    "gn:name":"Taqiao",
    "gn:population":0,
    "gn:timezone":"Asia/Shanghai",
    "iso:country":"CN",
    "name:und_x_variant":[
        "\u5854\u6865"
    ],
    "wof:name":"Taqiao",
    "wof:placetype":"locality"
},
  "geometry": {"coordinates":[118.57074,34.46085],"type":"Point"}
}