{
  "type": "Feature",
  "properties": {
    "gn:admin1_code":"15.0",
    "gn:asciiname":"Heigou",
    "gn:country_code":"CN",
    "gn:dem":2318,
    "gn:feature_class":"P",
    "gn:feature_code":"PPL",
    "gn:name":"Heigou",
    "gn:population":0,
    "gn:timezone":"Asia/Shanghai",
    "iso:country":"CN",
    "name:zho_x_preferred":[
        "\u9ed1\u6c9f"
    ],
    "wof:name":"Heigou",
    "wof:placetype":"locality"
},
  "geometry": {"coordinates":[105.148,34.59],"type":"Point"}
}