{
  "type": "Feature",
  "properties": {
    "gn:admin1_code":"9.0",
    "gn:asciiname":"Waguanji",
    "gn:country_code":"CN",
    "gn:dem":50,
    "gn:feature_class":"P",
    "gn:feature_code":"PPL",
    "gn:name":"Waguanji",
    "gn:population":0,
    "gn:timezone":"Asia/Shanghai",
    "iso:country":"CN",
    "name:zho_x_preferred":[
        "\u74e6\u7f50\u96c6"
    ],
    "wof:name":"Waguanji",
    "wof:placetype":"locality"
},
  "geometry": {"coordinates":[114.84756000000002,33.63123],"type":"Point"}
}