{
  "type": "Feature",
  "properties": {
    "gn:admin1_code":"15.0",
    "gn:asciiname":"Koutouba",
    "gn:country_code":"CN",
    "gn:dem":860,
    "gn:feature_class":"P",
    "gn:feature_code":"PPLA4",
    "gn:name":"Koutouba",
    "gn:population":0,
    "gn:timezone":"Asia/Shanghai",
    "iso:country":"CN",
    "name:und_x_variant":[
        "\u53e3\u5934\u575d"
    ],
    "name:zho_x_preferred":[
        "\u53e3\u5934\u575d"
    ],
    "wof:name":"Koutouba",
    "wof:placetype":"locality"
},
  "geometry": {"coordinates":[104.94223999999998,32.93999],"type":"Point"}
}