{
  "type": "Feature",
  "properties": {
    "gn:admin1_code":"8.0",
    "gn:asciiname":"Huayang Jingyingsuo",
    "gn:country_code":"CN",
    "gn:dem":148,
    "gn:feature_class":"P",
    "gn:feature_code":"PPLF",
    "gn:name":"Huayang Jingyingsuo",
    "gn:population":0,
    "gn:timezone":"Asia/Shanghai",
    "iso:country":"CN",
    "name:zho_x_preferred":[
        "\u6866\u9633\u7ecf\u8425\u6240"
    ],
    "wof:name":"Huayang Jingyingsuo",
    "wof:placetype":"locality"
},
  "geometry": {"coordinates":[129.51586,47.05755],"type":"Point"}
}