{
  "type": "Feature",
  "properties": {
    "gn:admin1_code":"19.0",
    "gn:asciiname":"Ditai",
    "gn:country_code":"CN",
    "gn:dem":317,
    "gn:feature_class":"P",
    "gn:feature_code":"PPL",
    "gn:name":"Ditai",
    "gn:population":0,
    "gn:timezone":"Asia/Shanghai",
    "iso:country":"CN",
    "name:und_x_variant":[
        "\u6ef4\u53f0"
    ],
    "name:zho_x_preferred":[
        "\u6ef4\u53f0"
    ],
    "wof:name":"Ditai",
    "wof:placetype":"locality"
},
  "geometry": {"coordinates":[124.61583,41.83819],"type":"Point"}
}