{
  "type": "Feature",
  "properties": {
    "gn:admin1_code":"8.0",
    "gn:asciiname":"Hongweicun",
    "gn:country_code":"CN",
    "gn:dem":78,
    "gn:feature_class":"P",
    "gn:feature_code":"PPL",
    "gn:name":"Hongweicun",
    "gn:population":0,
    "gn:timezone":"Asia/Shanghai",
    "iso:country":"CN",
    "name:zho_x_preferred":[
        "\u5b8f\u4f1f\u6751"
    ],
    "wof:name":"Hongweicun",
    "wof:placetype":"locality"
},
  "geometry": {"coordinates":[131.03243000000001,47.0348],"type":"Point"}
}