{
  "type": "Feature",
  "properties": {
    "gn:admin1_code":"4.0",
    "gn:asciiname":"Daijia Xuzi",
    "gn:country_code":"CN",
    "gn:dem":3,
    "gn:feature_class":"P",
    "gn:feature_code":"PPL",
    "gn:name":"Daijia Xuzi",
    "gn:population":0,
    "gn:timezone":"Asia/Shanghai",
    "iso:country":"CN",
    "name:zho_x_preferred":[
        "\u6234\u5bb6\u5729\u5b50"
    ],
    "wof:name":"Daijia Xuzi",
    "wof:placetype":"locality"
},
  "geometry": {"coordinates":[120.761,32.4192],"type":"Point"}
}