{
  "type": "Feature",
  "properties": {
    "gn:admin1_code":"32.0",
    "gn:asciiname":"Wenjiazui",
    "gn:country_code":"CN",
    "gn:dem":720,
    "gn:feature_class":"P",
    "gn:feature_code":"PPL",
    "gn:name":"Wenjiazui",
    "gn:population":0,
    "gn:timezone":"Asia/Shanghai",
    "iso:country":"CN",
    "name:zho_x_preferred":[
        "\u6587\u5bb6\u5480"
    ],
    "wof:name":"Wenjiazui",
    "wof:placetype":"locality"
},
  "geometry": {"coordinates":[106.89400000000001,31.336],"type":"Point"}
}