{
  "type": "Feature",
  "properties": {
    "gn:admin1_code":"7.0",
    "gn:asciiname":"Duijikengcun",
    "gn:country_code":"CN",
    "gn:dem":641,
    "gn:feature_class":"P",
    "gn:feature_code":"PPL",
    "gn:name":"Duijikengcun",
    "gn:population":0,
    "gn:timezone":"Asia/Shanghai",
    "iso:country":"CN",
    "name:und_x_variant":[
        "\u5806\u79ef\u5751\u6751"
    ],
    "name:zho_x_preferred":[
        "\u5806\u79ef\u5751\u6751"
    ],
    "wof:name":"Duijikengcun",
    "wof:placetype":"locality"
},
  "geometry": {"coordinates":[117.62721000000001,26.45525],"type":"Point"}
}