{
  "type": "Feature",
  "properties": {
    "gn:admin1_code":"7.0",
    "gn:asciiname":"Shafang",
    "gn:country_code":"CN",
    "gn:dem":515,
    "gn:feature_class":"P",
    "gn:feature_code":"PPL",
    "gn:name":"Shafang",
    "gn:population":0,
    "gn:timezone":"Asia/Shanghai",
    "iso:country":"CN",
    "name:zho_x_preferred":[
        "\u6749\u574a"
    ],
    "wof:name":"Shafang",
    "wof:placetype":"locality"
},
  "geometry": {"coordinates":[118.47028,28.13421],"type":"Point"}
}