{
  "type": "Feature",
  "properties": {
    "gn:admin1_code":"19.0",
    "gn:asciiname":"Beishi",
    "gn:country_code":"CN",
    "gn:dem":22,
    "gn:feature_class":"P",
    "gn:feature_code":"PPL",
    "gn:name":"Beishi",
    "gn:population":0,
    "gn:timezone":"Asia/Shanghai",
    "iso:country":"CN",
    "name:ceb_x_preferred":[
        "Beishi"
    ],
    "name:deu_x_preferred":[
        "Beishi"
    ],
    "name:swe_x_preferred":[
        "Beishi"
    ],
    "name:und_x_variant":[
        "\u5317\u77f3"
    ],
    "wof:name":"Beishi",
    "wof:placetype":"locality"
},
  "geometry": {"coordinates":[122.68253,40.85654],"type":"Point"}
}