{
  "type": "Feature",
  "properties": {
    "gn:admin1_code":"04",
    "gn:asciiname":"Chi'ancun",
    "gn:country_code":"CN",
    "gn:dem":5,
    "gn:feature_class":"P",
    "gn:feature_code":"PPL",
    "gn:name":"Chi\u2019ancun",
    "gn:population":0,
    "gn:timezone":"Asia/Shanghai",
    "iso:country":"CN",
    "name:und_x_variant":[
        "Ch\u2019ih-an",
        "Chi\u2019an",
        "\u8d64\u5cb8",
        "Chi\u2019ancun"
    ],
    "name:zho_x_preferred":[
        "\u8d64\u5cb8\u6751"
    ],
    "wof:name":"Chi'ancun",
    "wof:placetype":"locality"
},
  "geometry": {"coordinates":[120.57208,31.77808],"type":"Point"}
}