{
  "type": "Feature",
  "properties": {
    "gn:admin1_code":"30",
    "gn:asciiname":"Baishuidai",
    "gn:country_code":"CN",
    "gn:dem":399,
    "gn:feature_class":"P",
    "gn:feature_code":"PPL",
    "gn:name":"Baishuidai",
    "gn:population":0,
    "gn:timezone":"Asia/Shanghai",
    "iso:country":"CN",
    "name:und_x_variant":[
        "\u767d\u6c34\u5e26"
    ],
    "name:zho_x_preferred":[
        "\u767d\u6c34\u5e26"
    ],
    "wof:name":"Baishuidai",
    "wof:placetype":"locality"
},
  "geometry": {"coordinates":[112.715,22.68889],"type":"Point"}
}