{
  "type": "Feature",
  "properties": {
    "gn:admin1_code":"12.0",
    "gn:asciiname":"Xiadijiapo",
    "gn:country_code":"CN",
    "gn:dem":645,
    "gn:feature_class":"P",
    "gn:feature_code":"PPL",
    "gn:name":"Xiadijiapo",
    "gn:population":0,
    "gn:timezone":"Asia/Shanghai",
    "iso:country":"CN",
    "name:zho_x_preferred":[
        "\u4e0b\u7fdf\u5bb6\u5761"
    ],
    "wof:name":"Xiadijiapo",
    "wof:placetype":"locality"
},
  "geometry": {"coordinates":[110.73757999999999,32.5731],"type":"Point"}
}