{
  "type": "Feature",
  "properties": {
    "gn:admin1_code":"7.0",
    "gn:asciiname":"Gaofeng",
    "gn:country_code":"CN",
    "gn:dem":489,
    "gn:feature_class":"P",
    "gn:feature_code":"PPL",
    "gn:name":"Gaofeng",
    "gn:population":0,
    "gn:timezone":"Asia/Shanghai",
    "iso:country":"CN",
    "name:zho_x_preferred":[
        "\u9ad8\u5cf0"
    ],
    "wof:name":"Gaofeng",
    "wof:placetype":"locality"
},
  "geometry": {"coordinates":[117.54415,27.2491],"type":"Point"}
}