{
  "type": "Feature",
  "properties": {
    "gn:admin1_code":"11.0",
    "gn:asciiname":"Tuojiaxi",
    "gn:country_code":"CN",
    "gn:dem":127,
    "gn:feature_class":"P",
    "gn:feature_code":"PPL",
    "gn:name":"Tuojiaxi",
    "gn:population":0,
    "gn:timezone":"Asia/Shanghai",
    "iso:country":"CN",
    "name:und_x_variant":[
        "\u6258\u5bb6\u6eaa"
    ],
    "wof:name":"Tuojiaxi",
    "wof:placetype":"locality"
},
  "geometry": {"coordinates":[111.13705,29.08424],"type":"Point"}
}