{
  "type": "Feature",
  "properties": {
    "gn:admin1_code":"29.0",
    "gn:asciiname":"Shangyubi",
    "gn:country_code":"CN",
    "gn:dem":1212,
    "gn:feature_class":"P",
    "gn:feature_code":"PPL",
    "gn:name":"Shangyubi",
    "gn:population":0,
    "gn:timezone":"Asia/Shanghai",
    "iso:country":"CN",
    "name:zho_x_preferred":[
        "\u4e0a\u7389\u78a7"
    ],
    "wof:name":"Shangyubi",
    "wof:placetype":"locality"
},
  "geometry": {"coordinates":[101.52,23.4415],"type":"Point"}
}