{
  "type": "Feature",
  "properties": {
    "gn:admin1_code":"14.0",
    "gn:asciiname":"Wojiaoma",
    "gn:country_code":"CN",
    "gn:dem":4397,
    "gn:feature_class":"P",
    "gn:feature_code":"PPL",
    "gn:name":"Wojiaoma",
    "gn:population":0,
    "gn:timezone":"Asia/Urumqi",
    "iso:country":"CN",
    "name:zho_x_preferred":[
        "\u6211\u811a\u9a6c"
    ],
    "wof:name":"Wojiaoma",
    "wof:placetype":"locality"
},
  "geometry": {"coordinates":[95.12629,31.23273],"type":"Point"}
}