{
  "type": "Feature",
  "properties": {
    "gn:admin1_code":"14.0",
    "gn:asciiname":"Zongweng",
    "gn:country_code":"CN",
    "gn:dem":4030,
    "gn:feature_class":"P",
    "gn:feature_code":"PPL",
    "gn:name":"Zongweng",
    "gn:population":0,
    "gn:timezone":"Asia/Urumqi",
    "iso:country":"CN",
    "name:zho_x_preferred":[
        "\u5b97\u7fc1"
    ],
    "wof:name":"Zongweng",
    "wof:placetype":"locality"
},
  "geometry": {"coordinates":[96.00136999999999,30.42461],"type":"Point"}
}