{
  "type": "Feature",
  "properties": {
    "gn:admin1_code":"1.0",
    "gn:asciiname":"Chungangcun",
    "gn:country_code":"CN",
    "gn:dem":77,
    "gn:feature_class":"P",
    "gn:feature_code":"PPL",
    "gn:name":"Chungangcun",
    "gn:population":0,
    "gn:timezone":"Asia/Shanghai",
    "iso:country":"CN",
    "name:zho_x_preferred":[
        "\u693f\u5c97\u6751"
    ],
    "wof:name":"Chungangcun",
    "wof:placetype":"locality"
},
  "geometry": {"coordinates":[116.51794,31.58035],"type":"Point"}
}