{
  "type": "Feature",
  "properties": {
    "gn:admin1_code":"30.0",
    "gn:asciiname":"Feng'ercun",
    "gn:country_code":"CN",
    "gn:dem":187,
    "gn:feature_class":"P",
    "gn:feature_code":"PPL",
    "gn:name":"Feng\u2019ercun",
    "gn:population":0,
    "gn:timezone":"Asia/Shanghai",
    "iso:country":"CN",
    "name:und_x_variant":[
        "Feng\u2019ercun"
    ],
    "name:zho_x_preferred":[
        "\u51e4\u4e8c\u6751"
    ],
    "wof:name":"Feng'ercun",
    "wof:placetype":"locality"
},
  "geometry": {"coordinates":[115.84650999999999,24.58275],"type":"Point"}
}