{
  "type": "Feature",
  "properties": {
    "gn:admin1_code":"04",
    "gn:asciiname":"Fanshui",
    "gn:cc2":"CN",
    "gn:country_code":"CN",
    "gn:dem":9,
    "gn:feature_class":"P",
    "gn:feature_code":"PPL",
    "gn:name":"Fanshui",
    "gn:population":0,
    "gn:timezone":"Asia/Shanghai",
    "iso:country":"CN",
    "name:und_x_variant":[
        "Ssu-shui-chen",
        "Fan-shui-chen",
        "Ssu-shui",
        "Fanshui"
    ],
    "wof:name":"Fanshui",
    "wof:placetype":"locality"
},
  "geometry": {"coordinates":[119.39055999999999,33.09167],"type":"Point"}
}