{
  "type": "Feature",
  "properties": {
    "gn:admin1_code":"13",
    "gn:asciiname":"Quanshuidi",
    "gn:country_code":"CN",
    "gn:dem":1805,
    "gn:feature_class":"P",
    "gn:feature_code":"PPL",
    "gn:name":"Quanshuidi",
    "gn:population":0,
    "gn:timezone":"Asia/Urumqi",
    "iso:country":"CN",
    "name:und_x_variant":[
        "\u6cc9\u6c34\u5730"
    ],
    "wof:name":"Quanshuidi",
    "wof:placetype":"locality"
},
  "geometry": {"coordinates":[93.4218,43.56396],"type":"Point"}
}