{
  "type": "Feature",
  "properties": {
    "gn:admin1_code":"9.0",
    "gn:asciiname":"Shangnian Pangou",
    "gn:country_code":"CN",
    "gn:dem":297,
    "gn:feature_class":"P",
    "gn:feature_code":"PPL",
    "gn:name":"Shangnian Pangou",
    "gn:population":0,
    "gn:timezone":"Asia/Shanghai",
    "iso:country":"CN",
    "name:zho_x_preferred":[
        "\u4e0a\u78be\u76d8\u6c9f"
    ],
    "wof:name":"Shangnian Pangou",
    "wof:placetype":"locality"
},
  "geometry": {"coordinates":[113.32772,32.56475],"type":"Point"}
}