{
  "type": "Feature",
  "properties": {
    "gn:admin1_code":"11",
    "gn:asciiname":"Sanjing",
    "gn:country_code":"CN",
    "gn:dem":267,
    "gn:feature_class":"P",
    "gn:feature_code":"PPLA4",
    "gn:name":"Sanjing",
    "gn:population":0,
    "gn:timezone":"Asia/Shanghai",
    "iso:country":"CN",
    "name:und_x_variant":[
        "Sanjing Xiang",
        "\u4e09\u4e95\u4e61",
        "Sanjing"
    ],
    "name:zho_x_preferred":[
        "\u4e09\u4e95"
    ],
    "wof:name":"Sanjing",
    "wof:placetype":"locality"
},
  "geometry": {"coordinates":[112.21056000000002,25.78944],"type":"Point"}
}