{
  "type": "Feature",
  "properties": {
    "gn:admin1_code":"32.0",
    "gn:asciiname":"Shiyuanqiang",
    "gn:country_code":"CN",
    "gn:dem":367,
    "gn:feature_class":"P",
    "gn:feature_code":"PPL",
    "gn:name":"Shiyuanqiang",
    "gn:population":0,
    "gn:timezone":"Asia/Shanghai",
    "iso:country":"CN",
    "name:zho_x_preferred":[
        "\u77f3\u56ed\u5899"
    ],
    "wof:name":"Shiyuanqiang",
    "wof:placetype":"locality"
},
  "geometry": {"coordinates":[104.681,30.1687],"type":"Point"}
}