{
  "type": "Feature",
  "properties": {
    "gn:admin1_code":"19.0",
    "gn:asciiname":"Henan",
    "gn:country_code":"CN",
    "gn:dem":60,
    "gn:feature_class":"P",
    "gn:feature_code":"PPL",
    "gn:name":"Henan",
    "gn:population":0,
    "gn:timezone":"Asia/Shanghai",
    "iso:country":"CN",
    "name:und_x_variant":[
        "\u6cb3\u5357"
    ],
    "wof:name":"Henan",
    "wof:placetype":"locality"
},
  "geometry": {"coordinates":[122.121,40.0708],"type":"Point"}
}