{
  "type": "Feature",
  "properties": {
    "gn:admin1_code":"16.0",
    "gn:asciiname":"Jiaosai",
    "gn:country_code":"CN",
    "gn:dem":864,
    "gn:feature_class":"P",
    "gn:feature_code":"PPL",
    "gn:name":"Jiaosai",
    "gn:population":0,
    "gn:timezone":"Asia/Shanghai",
    "iso:country":"CN",
    "name:zho_x_preferred":[
        "\u4ea4\u816e"
    ],
    "wof:name":"Jiaosai",
    "wof:placetype":"locality"
},
  "geometry": {"coordinates":[107.08199999999999,25.0557],"type":"Point"}
}