{
  "type": "Feature",
  "properties": {
    "gn:admin1_code":"8.0",
    "gn:asciiname":"Zhonghuacun",
    "gn:country_code":"CN",
    "gn:dem":132,
    "gn:feature_class":"P",
    "gn:feature_code":"PPL",
    "gn:name":"Zhonghuacun",
    "gn:population":0,
    "gn:timezone":"Asia/Shanghai",
    "iso:country":"CN",
    "name:zho_x_preferred":[
        "\u4e2d\u534e\u6751"
    ],
    "wof:name":"Zhonghuacun",
    "wof:placetype":"locality"
},
  "geometry": {"coordinates":[125.12735000000001,45.65782],"type":"Point"}
}