{
  "type": "Feature",
  "properties": {
    "gn:admin1_code":"4.0",
    "gn:asciiname":"Xuying",
    "gn:country_code":"CN",
    "gn:dem":44,
    "gn:feature_class":"P",
    "gn:feature_code":"PPL",
    "gn:name":"Xuying",
    "gn:population":0,
    "gn:timezone":"Asia/Shanghai",
    "iso:country":"CN",
    "name:zho_x_preferred":[
        "\u5f90\u90e2"
    ],
    "wof:name":"Xuying",
    "wof:placetype":"locality"
},
  "geometry": {"coordinates":[118.58853000000001,32.76135],"type":"Point"}
}