{
  "type": "Feature",
  "properties": {
    "gn:admin1_code":"15.0",
    "gn:asciiname":"Mudanzui",
    "gn:country_code":"CN",
    "gn:dem":1896,
    "gn:feature_class":"P",
    "gn:feature_code":"PPL",
    "gn:name":"Mudanzui",
    "gn:population":0,
    "gn:timezone":"Asia/Shanghai",
    "iso:country":"CN",
    "name:zho_x_preferred":[
        "\u7261\u4e39\u5634"
    ],
    "wof:name":"Mudanzui",
    "wof:placetype":"locality"
},
  "geometry": {"coordinates":[106.169,35.2103],"type":"Point"}
}