{
  "type": "Feature",
  "properties": {
    "gn:admin1_code":"18",
    "gn:asciiname":"Yabazhai",
    "gn:country_code":"CN",
    "gn:dem":2340,
    "gn:feature_class":"P",
    "gn:feature_code":"PPL",
    "gn:name":"Yabazhai",
    "gn:population":0,
    "gn:timezone":"Asia/Shanghai",
    "iso:country":"CN",
    "name:zho_x_preferred":[
        "\u54d1\u5427\u5be8"
    ],
    "wof:name":"Yabazhai",
    "wof:placetype":"locality"
},
  "geometry": {"coordinates":[104.13500000000001,27.1801],"type":"Point"}
}