{
  "type": "Feature",
  "properties": {
    "gn:admin1_code":"30",
    "gn:asciiname":"Jinzao",
    "gn:country_code":"CN",
    "gn:dem":5,
    "gn:feature_class":"P",
    "gn:feature_code":"PPLA4",
    "gn:name":"Jinzao",
    "gn:population":0,
    "gn:timezone":"Asia/Shanghai",
    "iso:country":"CN",
    "name:und_x_variant":[
        "Jinyu",
        "Jinyu Zhen",
        "\u91d1\u7389",
        "Jinzao"
    ],
    "wof:name":"Jinzao",
    "wof:placetype":"locality"
},
  "geometry": {"coordinates":[116.39039,23.4541],"type":"Point"}
}