{
  "type": "Feature",
  "properties": {
    "gn:admin1_code":"19.0",
    "gn:asciiname":"Yangshuxingcun",
    "gn:country_code":"CN",
    "gn:dem":389,
    "gn:feature_class":"P",
    "gn:feature_code":"PPL",
    "gn:name":"Yangshuxingcun",
    "gn:population":0,
    "gn:timezone":"Asia/Shanghai",
    "iso:country":"CN",
    "name:zho_x_preferred":[
        "\u6768\u6811\u884c\u6751"
    ],
    "wof:name":"Yangshuxingcun",
    "wof:placetype":"locality"
},
  "geometry": {"coordinates":[119.521,40.9686],"type":"Point"}
}