{
  "type": "Feature",
  "properties": {
    "gn:admin1_code":"3",
    "gn:asciiname":"Baishun",
    "gn:country_code":"CN",
    "gn:dem":136,
    "gn:feature_class":"P",
    "gn:feature_code":"PPL",
    "gn:name":"Baishun",
    "gn:population":0,
    "gn:timezone":"Asia/Shanghai",
    "iso:country":"CN",
    "name:und_x_variant":[
        "\u767e\u987a"
    ],
    "wof:name":"Baishun",
    "wof:placetype":"locality"
},
  "geometry": {"coordinates":[116.8704,27.35846],"type":"Point"}
}