{
  "type": "Feature",
  "properties": {
    "gn:admin1_code":"25.0",
    "gn:asciiname":"Lingshandao",
    "gn:country_code":"CN",
    "gn:dem":282,
    "gn:feature_class":"P",
    "gn:feature_code":"PPL",
    "gn:name":"Lingshandao",
    "gn:population":0,
    "gn:timezone":"Asia/Shanghai",
    "iso:country":"CN",
    "name:zho_x_preferred":[
        "\u7075\u5c71\u5c9b"
    ],
    "wof:name":"Lingshandao",
    "wof:placetype":"locality"
},
  "geometry": {"coordinates":[120.16413,35.76379],"type":"Point"}
}