{
  "type": "Feature",
  "properties": {
    "gn:admin1_code":"16",
    "gn:asciiname":"Daluo",
    "gn:country_code":"CN",
    "gn:dem":363,
    "gn:feature_class":"P",
    "gn:feature_code":"PPL",
    "gn:name":"Daluo",
    "gn:population":0,
    "gn:timezone":"Asia/Shanghai",
    "iso:country":"CN",
    "name:zho_x_preferred":[
        "\u5927\u7f57"
    ],
    "wof:name":"Daluo",
    "wof:placetype":"locality"
},
  "geometry": {"coordinates":[110.32299999999999,24.7376],"type":"Point"}
}