{
  "type": "Feature",
  "properties": {
    "gn:country":"CN",
    "gn:fcode":"ADM3",
    "gn:population":0,
    "iso:country":"CN",
    "name:cdo_x_preferred":[
        "C\u012dk-m\u012b"
    ],
    "name:ceb_x_preferred":[
        "Jimei Qu"
    ],
    "name:cym_x_preferred":[
        "Ardal Jimei"
    ],
    "name:deu_x_preferred":[
        "Jimei"
    ],
    "name:eng_x_preferred":[
        "Jimei District"
    ],
    "name:fas_x_preferred":[
        "\u062c\u06cc\u0645\u0627\u06cc"
    ],
    "name:gan_x_preferred":[
        "\u96c6\u7f8e\u533a"
    ],
    "name:hak_x_preferred":[
        "Si\u030dp-m\u00ee-kh\u00ee"
    ],
    "name:jpn_x_preferred":[
        "\u96c6\u7f8e\u533a"
    ],
    "name:kor_x_preferred":[
        "\uc9c0\uba54\uc774\uad6c"
    ],
    "name:mwl_x_preferred":[
        "Jimei"
    ],
    "name:nan_x_preferred":[
        "Chi\u030dp-b\u00ed-khu"
    ],
    "name:nld_x_preferred":[
        "Jimei"
    ],
    "name:nob_x_preferred":[
        "Jimei"
    ],
    "name:rus_x_preferred":[
        "\u0426\u0437\u0438\u043c\u044d\u0439"
    ],
    "name:spa_x_preferred":[
        "Jimei"
    ],
    "name:swe_x_preferred":[
        "Jimei"
    ],
    "name:vie_x_preferred":[
        "T\u1eadp M\u1ef9"
    ],
    "name:wuu_x_preferred":[
        "\u96c6\u7f8e\u533a"
    ],
    "name:yue_x_preferred":[
        "\u96c6\u7f8e"
    ],
    "name:zho_x_preferred":[
        "\u96c6\u7f8e\u533a"
    ],
    "name:zho_x_variant":[
        "\u96c6\u7f8e"
    ],
    "qs:name":"Jimei Qu",
    "qs:photos_9r":0,
    "qs:photos_sr":0,
    "qs:pop_sr":"0",
    "wd:wordcount":510,
    "wof:name":"Jimei Qu",
    "wof:placetype":"localadmin",
    "wof:population":0
},
  "geometry": {"coordinates":[118.09305000000001,24.57766],"type":"Point"}
}