{
  "type": "Feature",
  "properties": {
    "gn:country":"CN",
    "gn:fcode":"ADM3",
    "gn:pop":0,
    "iso:country":"CN",
    "name:unk_x_variant":[
        "Jimei"
    ],
    "name:zho_x_preferred":[
        "\u96c6\u7f8e\u533a"
    ],
    "name:zho_x_variant":[
        "\u96c6\u7f8e"
    ],
    "qs:name":"Jimei Qu",
    "qs:photos_9r":0,
    "qs:photos_sr":0,
    "qs:pop_sr":"0",
    "wd:wordcount":510,
    "wof:name":"Jimei Qu",
    "wof:placetype":"localadmin",
    "wof:population":0
},
  "geometry": {"coordinates":[118.09305000000001,24.57766],"type":"Point"}
}