{
  "type": "Feature",
  "properties": {
    "gn:admin1_code":"29",
    "gn:asciiname":"Niumodaying",
    "gn:country_code":"CN",
    "gn:dem":1735,
    "gn:feature_class":"P",
    "gn:feature_code":"PPL",
    "gn:name":"Niumodaying",
    "gn:population":0,
    "gn:timezone":"Asia/Shanghai",
    "iso:country":"CN",
    "name:zho_x_preferred":[
        "\u725b\u6469\u5927\u8425"
    ],
    "wof:name":"Niumodaying",
    "wof:placetype":"locality"
},
  "geometry": {"coordinates":[102.855,24.4586],"type":"Point"}
}