{
  "type": "Feature",
  "properties": {
    "gn:admin1_code":"4.0",
    "gn:asciiname":"Yongtancun",
    "gn:country_code":"CN",
    "gn:dem":-2,
    "gn:feature_class":"P",
    "gn:feature_code":"PPL",
    "gn:name":"Yongtancun",
    "gn:population":0,
    "gn:timezone":"Asia/Shanghai",
    "iso:country":"CN",
    "name:zho_x_preferred":[
        "\u6c38\u575b\u6751"
    ],
    "wof:name":"Yongtancun",
    "wof:placetype":"locality"
},
  "geometry": {"coordinates":[119.97711,33.77050999999999],"type":"Point"}
}