{
  "type": "Feature",
  "properties": {
    "gn:admin1_code":"14.0",
    "gn:asciiname":"Wotongyong",
    "gn:country_code":"CN",
    "gn:dem":4270,
    "gn:feature_class":"P",
    "gn:feature_code":"PPL",
    "gn:name":"Wotongyong",
    "gn:population":0,
    "gn:timezone":"Asia/Urumqi",
    "iso:country":"CN",
    "name:zho_x_preferred":[
        "\u6211\u901a\u52c7"
    ],
    "wof:name":"Wotongyong",
    "wof:placetype":"locality"
},
  "geometry": {"coordinates":[93.98685999999999,31.909],"type":"Point"}
}