{
  "type": "Feature",
  "properties": {
    "gn:admin1_code":"29.0",
    "gn:asciiname":"Yipaimu",
    "gn:country_code":"CN",
    "gn:dem":1586,
    "gn:feature_class":"P",
    "gn:feature_code":"PPL",
    "gn:name":"Yipaimu",
    "gn:population":0,
    "gn:timezone":"Asia/Shanghai",
    "iso:country":"CN",
    "name:zho_x_preferred":[
        "\u4e00\u6392\u6bcd"
    ],
    "wof:name":"Yipaimu",
    "wof:placetype":"locality"
},
  "geometry": {"coordinates":[100.256,22.4576],"type":"Point"}
}