{
  "type": "Feature",
  "properties": {
    "gn:admin1_code":"9.0",
    "gn:asciiname":"Nanchaitun",
    "gn:country_code":"CN",
    "gn:dem":74,
    "gn:feature_class":"P",
    "gn:feature_code":"PPL",
    "gn:name":"Nanchaitun",
    "gn:population":0,
    "gn:timezone":"Asia/Shanghai",
    "iso:country":"CN",
    "name:zho_x_preferred":[
        "\u5357\u67f4\u5c6f"
    ],
    "wof:name":"Nanchaitun",
    "wof:placetype":"locality"
},
  "geometry": {"coordinates":[114.32885,34.76219],"type":"Point"}
}