{
  "type": "Feature",
  "properties": {
    "gn:admin1_code":"29.0",
    "gn:asciiname":"Mojiaolong",
    "gn:country_code":"CN",
    "gn:dem":1930,
    "gn:feature_class":"P",
    "gn:feature_code":"PPL",
    "gn:name":"Mojiaolong",
    "gn:population":0,
    "gn:timezone":"Asia/Shanghai",
    "iso:country":"CN",
    "name:zho_x_preferred":[
        "\u78e8\u811a\u9f99"
    ],
    "wof:name":"Mojiaolong",
    "wof:placetype":"locality"
},
  "geometry": {"coordinates":[104.154,24.9672],"type":"Point"}
}