{
  "type": "Feature",
  "properties": {
    "gn:admin1_code":"25",
    "gn:asciiname":"Lipaizhuang",
    "gn:country_code":"CN",
    "gn:dem":23,
    "gn:feature_class":"P",
    "gn:feature_code":"PPL",
    "gn:name":"Lipaizhuang",
    "gn:population":0,
    "gn:timezone":"Asia/Shanghai",
    "iso:country":"CN",
    "name:zho_x_preferred":[
        "\u674e\u724c\u5e84"
    ],
    "wof:name":"Lipaizhuang",
    "wof:placetype":"locality"
},
  "geometry": {"coordinates":[116.48099999999999,37.5169],"type":"Point"}
}