{
  "type": "Feature",
  "properties": {
    "gn:admin1_code":"29.0",
    "gn:asciiname":"Juejiba",
    "gn:country_code":"CN",
    "gn:dem":1495,
    "gn:feature_class":"P",
    "gn:feature_code":"PPL",
    "gn:name":"Juejiba",
    "gn:population":0,
    "gn:timezone":"Asia/Shanghai",
    "iso:country":"CN",
    "name:zho_x_preferred":[
        "\u8568\u57fa\u575d"
    ],
    "wof:name":"Juejiba",
    "wof:placetype":"locality"
},
  "geometry": {"coordinates":[101.057,22.7397],"type":"Point"}
}