{
  "type": "Feature",
  "properties": {
    "gn:admin1_code":"24.0",
    "gn:asciiname":"Taipinggou",
    "gn:country_code":"CN",
    "gn:dem":1246,
    "gn:feature_class":"P",
    "gn:feature_code":"PPL",
    "gn:name":"Taipinggou",
    "gn:population":0,
    "gn:timezone":"Asia/Shanghai",
    "iso:country":"CN",
    "name:zho_x_preferred":[
        "\u592a\u5e73\u6c9f"
    ],
    "wof:name":"Taipinggou",
    "wof:placetype":"locality"
},
  "geometry": {"coordinates":[111.21307,38.8327],"type":"Point"}
}