{
  "type": "Feature",
  "properties": {
    "gn:admin1_code":"12.0",
    "gn:asciiname":"Yeju'ao",
    "gn:country_code":"CN",
    "gn:dem":220,
    "gn:feature_class":"P",
    "gn:feature_code":"PPL",
    "gn:name":"Yeju\u2019ao",
    "gn:population":0,
    "gn:timezone":"Asia/Shanghai",
    "iso:country":"CN",
    "name:und_x_variant":[
        "Yeju\u2019ao"
    ],
    "name:zho_x_preferred":[
        "\u91ce\u83ca\u5773"
    ],
    "wof:name":"Yeju'ao",
    "wof:placetype":"locality"
},
  "geometry": {"coordinates":[115.47913,31.19614],"type":"Point"}
}