{
  "type": "Feature",
  "properties": {
    "gn:admin1_code":"29.0",
    "gn:asciiname":"Nasai",
    "gn:country_code":"CN",
    "gn:dem":1756,
    "gn:feature_class":"P",
    "gn:feature_code":"PPL",
    "gn:name":"Nasai",
    "gn:population":0,
    "gn:timezone":"Asia/Shanghai",
    "iso:country":"CN",
    "name:zho_x_preferred":[
        "\u90a3\u8d5b"
    ],
    "wof:name":"Nasai",
    "wof:placetype":"locality"
},
  "geometry": {"coordinates":[99.9768,23.6344],"type":"Point"}
}