{
  "type": "Feature",
  "properties": {
    "gn:admin1_code":"19.0",
    "gn:asciiname":"Banlamiaocun",
    "gn:country_code":"CN",
    "gn:dem":168,
    "gn:feature_class":"P",
    "gn:feature_code":"PPL",
    "gn:name":"Banlamiaocun",
    "gn:population":0,
    "gn:timezone":"Asia/Shanghai",
    "iso:country":"CN",
    "name:zho_x_preferred":[
        "\u534a\u62c9\u5e99\u6751"
    ],
    "wof:name":"Banlamiaocun",
    "wof:placetype":"locality"
},
  "geometry": {"coordinates":[122.581,40.2362],"type":"Point"}
}