{
  "type": "Feature",
  "properties": {
    "gn:admin1_code":"19.0",
    "gn:asciiname":"Beigoutou",
    "gn:country_code":"CN",
    "gn:dem":188,
    "gn:feature_class":"P",
    "gn:feature_code":"PPL",
    "gn:name":"Beigoutou",
    "gn:population":0,
    "gn:timezone":"Asia/Shanghai",
    "iso:country":"CN",
    "name:zho_x_preferred":[
        "\u5317\u6c9f\u5934"
    ],
    "wof:name":"Beigoutou",
    "wof:placetype":"locality"
},
  "geometry": {"coordinates":[122.309,39.7894],"type":"Point"}
}