{
  "type": "Feature",
  "properties": {
    "gn:admin1_code":"15.0",
    "gn:asciiname":"Zhangjia Buzi",
    "gn:country_code":"CN",
    "gn:dem":1702,
    "gn:feature_class":"P",
    "gn:feature_code":"PPL",
    "gn:name":"Zhangjia Buzi",
    "gn:population":0,
    "gn:timezone":"Asia/Shanghai",
    "iso:country":"CN",
    "name:und_x_variant":[
        "\u5f20\u5bb6\u5821\u5b50"
    ],
    "wof:name":"Zhangjia Buzi",
    "wof:placetype":"locality"
},
  "geometry": {"coordinates":[105.68040999999999,35.58332],"type":"Point"}
}