{
  "type": "Feature",
  "properties": {
    "gn:admin1_code":"19.0",
    "gn:asciiname":"Sigou",
    "gn:country_code":"CN",
    "gn:dem":-1,
    "gn:feature_class":"P",
    "gn:feature_code":"PPL",
    "gn:name":"Sigou",
    "gn:population":0,
    "gn:timezone":"Asia/Shanghai",
    "iso:country":"CN",
    "name:zho_x_preferred":[
        "\u56db\u6c9f"
    ],
    "wof:name":"Sigou",
    "wof:placetype":"locality"
},
  "geometry": {"coordinates":[121.35299999999999,40.9216],"type":"Point"}
}