{
  "type": "Feature",
  "properties": {
    "gn:admin1_code":"32.0",
    "gn:asciiname":"Genagui",
    "gn:country_code":"CN",
    "gn:dem":3078,
    "gn:feature_class":"P",
    "gn:feature_code":"PPL",
    "gn:name":"Genagui",
    "gn:population":0,
    "gn:timezone":"Asia/Shanghai",
    "iso:country":"CN",
    "name:zho_x_preferred":[
        "\u683c\u7eb3\u572d"
    ],
    "wof:name":"Genagui",
    "wof:placetype":"locality"
},
  "geometry": {"coordinates":[101.98699999999999,31.123],"type":"Point"}
}