{
  "type": "Feature",
  "properties": {
    "gn:admin1_code":"4.0",
    "gn:asciiname":"Gongqicun",
    "gn:country_code":"CN",
    "gn:dem":17,
    "gn:feature_class":"P",
    "gn:feature_code":"PPL",
    "gn:name":"Gongqicun",
    "gn:population":0,
    "gn:timezone":"Asia/Shanghai",
    "iso:country":"CN",
    "name:zho_x_preferred":[
        "\u62f1\u9f50\u6751"
    ],
    "wof:name":"Gongqicun",
    "wof:placetype":"locality"
},
  "geometry": {"coordinates":[119.13648000000001,35.01471],"type":"Point"}
}