{
  "type": "Feature",
  "properties": {
    "gn:admin1_code":"4.0",
    "gn:asciiname":"Lingmengcun",
    "gn:country_code":"CN",
    "gn:dem":18,
    "gn:feature_class":"P",
    "gn:feature_code":"PPL",
    "gn:name":"Lingmengcun",
    "gn:population":0,
    "gn:timezone":"Asia/Shanghai",
    "iso:country":"CN",
    "name:zho_x_preferred":[
        "\u51cc\u5b5f\u6751"
    ],
    "wof:name":"Lingmengcun",
    "wof:placetype":"locality"
},
  "geometry": {"coordinates":[118.72490999999999,33.60071],"type":"Point"}
}