{
  "type": "Feature",
  "properties": {
    "gn:admin1_code":"5.0",
    "gn:asciiname":"Shenglicun",
    "gn:country_code":"CN",
    "gn:dem":462,
    "gn:feature_class":"P",
    "gn:feature_code":"PPL",
    "gn:name":"Shenglicun",
    "gn:population":0,
    "gn:timezone":"Asia/Shanghai",
    "iso:country":"CN",
    "name:und_x_variant":[
        "\u80dc\u5229\u6751",
        "Shengli"
    ],
    "name:zho_x_preferred":[
        "\u80dc\u5229"
    ],
    "wof:name":"Shenglicun",
    "wof:placetype":"locality"
},
  "geometry": {"coordinates":[126.8548,41.85739],"type":"Point"}
}