{
  "type": "Feature",
  "properties": {
    "gn:admin1_code":"15.0",
    "gn:asciiname":"Jili",
    "gn:country_code":"CN",
    "gn:dem":3247,
    "gn:feature_class":"P",
    "gn:feature_code":"PPL",
    "gn:name":"Jili",
    "gn:population":0,
    "gn:timezone":"Asia/Shanghai",
    "iso:country":"CN",
    "name:bre_x_preferred":[
        "Jili"
    ],
    "name:ceb_x_preferred":[
        "Jili"
    ],
    "name:deu_x_preferred":[
        "Jili"
    ],
    "name:fra_x_preferred":[
        "Jili"
    ],
    "name:swe_x_preferred":[
        "Jili"
    ],
    "name:und_x_variant":[
        "\u5409\u5229"
    ],
    "wof:name":"Jili",
    "wof:placetype":"locality"
},
  "geometry": {"coordinates":[102.982,35.0951],"type":"Point"}
}