{
  "type": "Feature",
  "properties": {
    "gn:admin1_code":"12.0",
    "gn:asciiname":"Qinjialing",
    "gn:country_code":"CN",
    "gn:dem":41,
    "gn:feature_class":"P",
    "gn:feature_code":"PPL",
    "gn:name":"Qinjialing",
    "gn:population":0,
    "gn:timezone":"Asia/Shanghai",
    "iso:country":"CN",
    "name:zho_x_preferred":[
        "Qinjialing"
    ],
    "name:zho_x_variant":[
        "\u8983\u5bb6\u5cad"
    ],
    "wof:name":"Qinjialing",
    "wof:placetype":"locality"
},
  "geometry": {"coordinates":[111.65973,30.42117],"type":"Point"}
}