{
  "type": "Feature",
  "properties": {
    "gn:admin1_code":"10",
    "gn:asciiname":"Maweigou",
    "gn:country_code":"CN",
    "gn:dem":462,
    "gn:feature_class":"P",
    "gn:feature_code":"PPL",
    "gn:name":"Maweigou",
    "gn:population":0,
    "gn:timezone":"Asia/Shanghai",
    "iso:country":"CN",
    "name:zho_x_preferred":[
        "\u9a6c\u5c3e\u6c9f"
    ],
    "wof:name":"Maweigou",
    "wof:placetype":"locality"
},
  "geometry": {"coordinates":[118.61485,40.36173],"type":"Point"}
}