{
  "type": "Feature",
  "properties": {
    "gn:admin1_code":"24.0",
    "gn:asciiname":"Shipingzi",
    "gn:country_code":"CN",
    "gn:dem":1705,
    "gn:feature_class":"P",
    "gn:feature_code":"PPL",
    "gn:name":"Shipingzi",
    "gn:population":0,
    "gn:timezone":"Asia/Shanghai",
    "iso:country":"CN",
    "name:und_x_variant":[
        "\u77f3\u576a\u5b50"
    ],
    "name:zho_x_preferred":[
        "\u77f3\u576a\u5b50"
    ],
    "wof:name":"Shipingzi",
    "wof:placetype":"locality"
},
  "geometry": {"coordinates":[112.08887,39.00897],"type":"Point"}
}