{
  "type": "Feature",
  "properties": {
    "gn:admin1_code":"15.0",
    "gn:asciiname":"Xigoudi",
    "gn:country_code":"CN",
    "gn:dem":2391,
    "gn:feature_class":"P",
    "gn:feature_code":"PPL",
    "gn:name":"Xigoudi",
    "gn:population":0,
    "gn:timezone":"Asia/Shanghai",
    "iso:country":"CN",
    "name:zho_x_preferred":[
        "\u897f\u6c9f\u5730"
    ],
    "wof:name":"Xigoudi",
    "wof:placetype":"locality"
},
  "geometry": {"coordinates":[97.9093,39.6581],"type":"Point"}
}