{
  "type": "Feature",
  "properties": {
    "gn:admin1_code":"1.0",
    "gn:asciiname":"Jinjialingcun",
    "gn:country_code":"CN",
    "gn:dem":297,
    "gn:feature_class":"P",
    "gn:feature_code":"PPL",
    "gn:name":"Jinjialingcun",
    "gn:population":0,
    "gn:timezone":"Asia/Shanghai",
    "iso:country":"CN",
    "name:zho_x_preferred":[
        "\u91d1\u5bb6\u5cad\u6751"
    ],
    "wof:name":"Jinjialingcun",
    "wof:placetype":"locality"
},
  "geometry": {"coordinates":[117.99187999999999,29.95892000000001],"type":"Point"}
}