{
  "type": "Feature",
  "properties": {
    "gn:admin1_code":"11.0",
    "gn:asciiname":"Jinpenwo",
    "gn:country_code":"CN",
    "gn:dem":182,
    "gn:feature_class":"P",
    "gn:feature_code":"PPL",
    "gn:name":"Jinpenwo",
    "gn:population":0,
    "gn:timezone":"Asia/Shanghai",
    "iso:country":"CN",
    "name:zho_x_preferred":[
        "\u91d1\u76c6\u7a9d"
    ],
    "wof:name":"Jinpenwo",
    "wof:placetype":"locality"
},
  "geometry": {"coordinates":[113.0097,25.96122],"type":"Point"}
}