{
  "type": "Feature",
  "properties": {
    "gn:admin1_code":"22.0",
    "gn:asciiname":"Dongliangcun",
    "gn:country_code":"CN",
    "gn:dem":716,
    "gn:feature_class":"P",
    "gn:feature_code":"PPL",
    "gn:name":"Dongliangcun",
    "gn:population":0,
    "gn:timezone":"Asia/Shanghai",
    "iso:country":"CN",
    "name:zho_x_preferred":[
        "\u4e1c\u6881\u6751"
    ],
    "wof:name":"Dongliangcun",
    "wof:placetype":"locality"
},
  "geometry": {"coordinates":[117.3278,40.5898],"type":"Point"}
}