{
  "type": "Feature",
  "properties": {
    "gn:admin1_code":"4.0",
    "gn:asciiname":"Erdadui",
    "gn:country_code":"CN",
    "gn:dem":2,
    "gn:feature_class":"P",
    "gn:feature_code":"PPLF",
    "gn:name":"Erdadui",
    "gn:population":0,
    "gn:timezone":"Asia/Shanghai",
    "iso:country":"CN",
    "name:und_x_variant":[
        "\u4e8c\u5927\u961f"
    ],
    "wof:name":"Erdadui",
    "wof:placetype":"locality"
},
  "geometry": {"coordinates":[120.70378999999998,33.11573],"type":"Point"}
}