{
  "type": "Feature",
  "properties": {
    "gn:admin1_code":"12.0",
    "gn:asciiname":"Shigangzi",
    "gn:country_code":"CN",
    "gn:dem":50,
    "gn:feature_class":"P",
    "gn:feature_code":"PPL",
    "gn:name":"Shigangzi",
    "gn:population":0,
    "gn:timezone":"Asia/Shanghai",
    "iso:country":"CN",
    "name:zho_x_preferred":[
        "Shigangzi"
    ],
    "name:zho_x_variant":[
        "\u77f3\u5c97\u5b50"
    ],
    "wof:name":"Shigangzi",
    "wof:placetype":"locality"
},
  "geometry": {"coordinates":[111.5176,30.31546],"type":"Point"}
}