{
  "type": "Feature",
  "properties": {
    "gn:admin1_code":"11",
    "gn:asciiname":"Dongtian",
    "gn:country_code":"CN",
    "gn:dem":221,
    "gn:feature_class":"P",
    "gn:feature_code":"PPL",
    "gn:name":"Dongtian",
    "gn:population":0,
    "gn:timezone":"Asia/Shanghai",
    "iso:country":"CN",
    "name:und_x_variant":[
        "\u4e1c\u7530",
        "Dongtian"
    ],
    "wof:name":"Dongtian",
    "wof:placetype":"locality"
},
  "geometry": {"coordinates":[112.26917,25.75861],"type":"Point"}
}