{
  "type": "Feature",
  "properties": {
    "gn:admin1_code":"6.0",
    "gn:asciiname":"Gandujie",
    "gn:country_code":"CN",
    "gn:dem":1941,
    "gn:feature_class":"P",
    "gn:feature_code":"PPL",
    "gn:name":"Gandujie",
    "gn:population":0,
    "gn:timezone":"Asia/Shanghai",
    "iso:country":"CN",
    "name:und_x_variant":[
        "\u7518\u90fd\u8857"
    ],
    "wof:name":"Gandujie",
    "wof:placetype":"locality"
},
  "geometry": {"coordinates":[102.31574999999999,35.88525999999999],"type":"Point"}
}