{
  "type": "Feature",
  "properties": {
    "gn:admin1_code":"5.0",
    "gn:asciiname":"Xinyandong",
    "gn:country_code":"CN",
    "gn:dem":596,
    "gn:feature_class":"P",
    "gn:feature_code":"PPL",
    "gn:name":"Xinyandong",
    "gn:population":0,
    "gn:timezone":"Asia/Shanghai",
    "iso:country":"CN",
    "name:und_x_variant":[
        "\u65b0\u5ca9\u6d1e"
    ],
    "wof:name":"Xinyandong",
    "wof:placetype":"locality"
},
  "geometry": {"coordinates":[128.94066000000001,42.53592],"type":"Point"}
}