{
  "type": "Feature",
  "properties": {
    "gn:admin1_code":"8.0",
    "gn:asciiname":"Dongdagang",
    "gn:country_code":"CN",
    "gn:dem":82,
    "gn:feature_class":"P",
    "gn:feature_code":"PPL",
    "gn:name":"Dongdagang",
    "gn:population":0,
    "gn:timezone":"Asia/Shanghai",
    "iso:country":"CN",
    "name:zho_x_preferred":[
        "\u4e1c\u5927\u5c97"
    ],
    "wof:name":"Dongdagang",
    "wof:placetype":"locality"
},
  "geometry": {"coordinates":[133.09578999999999,46.12707],"type":"Point"}
}