{
  "type": "Feature",
  "properties": {
    "gn:admin1_code":"13.0",
    "gn:asciiname":"Balemasi",
    "gn:country_code":"CN",
    "gn:dem":1325,
    "gn:feature_class":"P",
    "gn:feature_code":"PPL",
    "gn:name":"Balemasi",
    "gn:population":0,
    "gn:timezone":"Asia/Shanghai",
    "iso:country":"CN",
    "name:zho_x_preferred":[
        "\u5df4\u52d2\u739b\u65af"
    ],
    "wof:name":"Balemasi",
    "wof:placetype":"locality"
},
  "geometry": {"coordinates":[79.83456,37.21072],"type":"Point"}
}