{
  "type": "Feature",
  "properties": {
    "gn:admin1_code":"4.0",
    "gn:asciiname":"Hailin",
    "gn:country_code":"CN",
    "gn:dem":6,
    "gn:feature_class":"P",
    "gn:feature_code":"PPL",
    "gn:name":"Hailin",
    "gn:population":0,
    "gn:timezone":"Asia/Shanghai",
    "iso:country":"CN",
    "name:ara_x_preferred":[
        "\u0647\u0627\u064a\u0644\u064a\u0646"
    ],
    "name:ceb_x_preferred":[
        "Hailin"
    ],
    "name:deu_x_preferred":[
        "Hailin"
    ],
    "name:fra_x_preferred":[
        "Hailin"
    ],
    "name:ita_x_preferred":[
        "Hailin"
    ],
    "name:jpn_x_preferred":[
        "\u6d77\u6797\u5e02"
    ],
    "name:kik_x_preferred":[
        "Hailin"
    ],
    "name:kor_x_preferred":[
        "\ud558\uc774\ub9b0\uc2dc"
    ],
    "name:mlg_x_preferred":[
        "Hailin"
    ],
    "name:nor_x_preferred":[
        "Hailin"
    ],
    "name:pam_x_preferred":[
        "Hailin"
    ],
    "name:rus_x_preferred":[
        "\u0425\u0430\u0439\u043b\u0438\u043d\u044c"
    ],
    "name:swe_x_preferred":[
        "Hailin"
    ],
    "name:urd_x_preferred":[
        "\u06c1\u0627\u0626\u0644\u0646"
    ],
    "name:vie_x_preferred":[
        "H\u1ea3i L\u00e2m"
    ],
    "name:zho_x_preferred":[
        "\u6d77\u6797"
    ],
    "name:zho_x_variant":[
        "\u6d77\u6797\u5e02"
    ],
    "wof:name":"Hailin",
    "wof:placetype":"locality"
},
  "geometry": {"coordinates":[120.17622,32.26866],"type":"Point"}
}