{
  "type": "Feature",
  "properties": {
    "gn:admin1_code":"1.0",
    "gn:asciiname":"Shangmaqiaocun",
    "gn:country_code":"CN",
    "gn:dem":33,
    "gn:feature_class":"P",
    "gn:feature_code":"PPL",
    "gn:name":"Shangmaqiaocun",
    "gn:population":0,
    "gn:timezone":"Asia/Shanghai",
    "iso:country":"CN",
    "name:zho_x_preferred":[
        "\u4e0a\u9a6c\u6865\u6751"
    ],
    "wof:name":"Shangmaqiaocun",
    "wof:placetype":"locality"
},
  "geometry": {"coordinates":[116.25933999999999,33.36955],"type":"Point"}
}