{
  "type": "Feature",
  "properties": {
    "gn:admin1_code":"15.0",
    "gn:asciiname":"Yuanjiashang",
    "gn:country_code":"CN",
    "gn:dem":2156,
    "gn:feature_class":"P",
    "gn:feature_code":"PPL",
    "gn:name":"Yuanjiashang",
    "gn:population":0,
    "gn:timezone":"Asia/Shanghai",
    "iso:country":"CN",
    "name:zho_x_preferred":[
        "\u8881\u5bb6\u57eb"
    ],
    "wof:name":"Yuanjiashang",
    "wof:placetype":"locality"
},
  "geometry": {"coordinates":[105.36199999999999,36.2328],"type":"Point"}
}