{
  "type": "Feature",
  "properties": {
    "gn:admin1_code":"16.0",
    "gn:asciiname":"Shanglongtang",
    "gn:country_code":"CN",
    "gn:dem":192,
    "gn:feature_class":"P",
    "gn:feature_code":"PPL",
    "gn:name":"Shanglongtang",
    "gn:population":0,
    "gn:timezone":"Asia/Shanghai",
    "iso:country":"CN",
    "name:zho_x_preferred":[
        "\u4e0a\u9f99\u5858"
    ],
    "wof:name":"Shanglongtang",
    "wof:placetype":"locality"
},
  "geometry": {"coordinates":[108.777,24.5889],"type":"Point"}
}