{
  "type": "Feature",
  "properties": {
    "gn:admin1_code":"10",
    "gn:asciiname":"Lingyunce",
    "gn:cc2":"CN",
    "gn:country_code":"CN",
    "gn:dem":51,
    "gn:feature_class":"P",
    "gn:feature_code":"PPL",
    "gn:name":"Lingyunce",
    "gn:population":0,
    "gn:timezone":"Asia/Shanghai",
    "iso:country":"CN",
    "name:und_x_variant":[
        "Lingyunce Manzu Huizu Xiang",
        "Ling-y\u00fcn-ts\u2019e-chen",
        "Lingxuezha",
        "Ling-hs\u00fceh-cha",
        "Lingyunce"
    ],
    "wof:name":"Lingyunce",
    "wof:placetype":"locality"
},
  "geometry": {"coordinates":[115.49917000000001,39.23639],"type":"Point"}
}