{
  "type": "Feature",
  "properties": {
    "gn:admin1_code":"12.0",
    "gn:asciiname":"Bijiazhou",
    "gn:country_code":"CN",
    "gn:dem":30,
    "gn:feature_class":"P",
    "gn:feature_code":"PPL",
    "gn:name":"Bijiazhou",
    "gn:population":0,
    "gn:timezone":"Asia/Shanghai",
    "iso:country":"CN",
    "name:zho_x_preferred":[
        "Bijiazhou"
    ],
    "name:zho_x_variant":[
        "\u6bd5\u5bb6\u6d32"
    ],
    "wof:name":"Bijiazhou",
    "wof:placetype":"locality"
},
  "geometry": {"coordinates":[115.09439999999999,30.31076],"type":"Point"}
}