{
  "type": "Feature",
  "properties": {
    "gn:admin1_code":"3.0",
    "gn:asciiname":"Tuzikeng",
    "gn:country_code":"CN",
    "gn:dem":362,
    "gn:feature_class":"P",
    "gn:feature_code":"PPL",
    "gn:name":"Tuzikeng",
    "gn:population":0,
    "gn:timezone":"Asia/Shanghai",
    "iso:country":"CN",
    "name:und_x_variant":[
        "\u5154\u5b50\u5751"
    ],
    "wof:name":"Tuzikeng",
    "wof:placetype":"locality"
},
  "geometry": {"coordinates":[115.97557,26.01444],"type":"Point"}
}