{
  "type": "Feature",
  "properties": {
    "gn:admin1_code":"7.0",
    "gn:asciiname":"Zhuangyuanmu",
    "gn:country_code":"CN",
    "gn:dem":547,
    "gn:feature_class":"P",
    "gn:feature_code":"PPL",
    "gn:name":"Zhuangyuanmu",
    "gn:population":0,
    "gn:timezone":"Asia/Shanghai",
    "iso:country":"CN",
    "name:zho_x_preferred":[
        "\u72b6\u5143\u5893"
    ],
    "wof:name":"Zhuangyuanmu",
    "wof:placetype":"locality"
},
  "geometry": {"coordinates":[119.45887,26.03624],"type":"Point"}
}