{
  "type": "Feature",
  "properties": {
    "gn:admin1_code":"24.0",
    "gn:asciiname":"Hongyaoshang",
    "gn:country_code":"CN",
    "gn:dem":1777,
    "gn:feature_class":"P",
    "gn:feature_code":"PPL",
    "gn:name":"Hongyaoshang",
    "gn:population":0,
    "gn:timezone":"Asia/Shanghai",
    "iso:country":"CN",
    "name:zho_x_preferred":[
        "\u7ea2\u7a91\u4e0a"
    ],
    "wof:name":"Hongyaoshang",
    "wof:placetype":"locality"
},
  "geometry": {"coordinates":[112.07298,36.72044],"type":"Point"}
}