{
  "type": "Feature",
  "properties": {
    "gn:admin1_code":"11.0",
    "gn:asciiname":"Dashuping",
    "gn:country_code":"CN",
    "gn:dem":323,
    "gn:feature_class":"P",
    "gn:feature_code":"PPL",
    "gn:name":"Dashuping",
    "gn:population":0,
    "gn:timezone":"Asia/Shanghai",
    "iso:country":"CN",
    "name:zho_x_preferred":[
        "\u5927\u6811\u576a"
    ],
    "wof:name":"Dashuping",
    "wof:placetype":"locality"
},
  "geometry": {"coordinates":[109.61382999999999,27.34334],"type":"Point"}
}