{
  "type": "Feature",
  "properties": {
    "gn:admin1_code":"11",
    "gn:asciiname":"Huangniwan",
    "gn:country_code":"CN",
    "gn:dem":518,
    "gn:feature_class":"P",
    "gn:feature_code":"PPL",
    "gn:name":"Huangniwan",
    "gn:population":0,
    "gn:timezone":"Asia/Shanghai",
    "iso:country":"CN",
    "name:und_x_variant":[
        "\u9ec4\u6ce5\u6e7e",
        "Huangniwan"
    ],
    "wof:name":"Huangniwan",
    "wof:placetype":"locality"
},
  "geometry": {"coordinates":[111.84166999999999,25.84639],"type":"Point"}
}