{
  "type": "Feature",
  "properties": {
    "gn:admin1_code":"21.0",
    "gn:asciiname":"Zhanglipan",
    "gn:country_code":"CN",
    "gn:dem":1868,
    "gn:feature_class":"P",
    "gn:feature_code":"PPL",
    "gn:name":"Zhanglipan",
    "gn:population":0,
    "gn:timezone":"Asia/Shanghai",
    "iso:country":"CN",
    "name:und_x_variant":[
        "\u5f20\u674e\u76d8"
    ],
    "name:zho_x_preferred":[
        "\u5f20\u674e\u76d8"
    ],
    "wof:name":"Zhanglipan",
    "wof:placetype":"locality"
},
  "geometry": {"coordinates":[105.97087000000001,35.57424],"type":"Point"}
}