{
  "type": "Feature",
  "properties": {
    "gn:admin1_code":"20",
    "gn:asciiname":"Baliang",
    "gn:country_code":"CN",
    "gn:dem":1571,
    "gn:feature_class":"P",
    "gn:feature_code":"PPLA4",
    "gn:name":"Baliang",
    "gn:population":0,
    "gn:timezone":"Asia/Shanghai",
    "iso:country":"CN",
    "name:und_x_variant":[
        "\u575d\u6881",
        "Da\u2019erfenzi",
        "\u5927\u4e8c\u5206\u5b50"
    ],
    "wof:name":"Baliang",
    "wof:placetype":"locality"
},
  "geometry": {"coordinates":[109.7593,41.09131],"type":"Point"}
}