{
  "type": "Feature",
  "properties": {
    "gn:admin1_code":"12.0",
    "gn:asciiname":"Shuangshiling",
    "gn:country_code":"CN",
    "gn:dem":441,
    "gn:feature_class":"P",
    "gn:feature_code":"PPL",
    "gn:name":"Shuangshiling",
    "gn:population":0,
    "gn:timezone":"Asia/Shanghai",
    "iso:country":"CN",
    "name:zho_x_preferred":[
        "Shuangshiling"
    ],
    "name:zho_x_variant":[
        "\u53cc\u72ee\u5cad"
    ],
    "wof:name":"Shuangshiling",
    "wof:placetype":"locality"
},
  "geometry": {"coordinates":[111.03126,30.86904],"type":"Point"}
}