{
  "type": "Feature",
  "properties": {
    "gn:admin1_code":"30.0",
    "gn:asciiname":"Jiangcunli",
    "gn:country_code":"CN",
    "gn:dem":34,
    "gn:feature_class":"P",
    "gn:feature_code":"PPL",
    "gn:name":"Jiangcunli",
    "gn:population":0,
    "gn:timezone":"Asia/Shanghai",
    "iso:country":"CN",
    "name:zho_x_preferred":[
        "\u6c5f\u6751\u91cc"
    ],
    "wof:name":"Jiangcunli",
    "wof:placetype":"locality"
},
  "geometry": {"coordinates":[113.61056000000001,23.57111],"type":"Point"}
}