{
  "type": "Feature",
  "properties": {
    "gn:admin1_code":"07",
    "gn:asciiname":"Gancuo",
    "gn:country_code":"CN",
    "gn:dem":64,
    "gn:feature_class":"P",
    "gn:feature_code":"PPL",
    "gn:name":"Gancuo",
    "gn:population":0,
    "gn:timezone":"Asia/Shanghai",
    "iso:country":"CN",
    "name:zho_x_preferred":[
        "\u7518\u539d"
    ],
    "wof:name":"Gancuo",
    "wof:placetype":"locality"
},
  "geometry": {"coordinates":[120.39943999999998,27.22972],"type":"Point"}
}