{
  "type": "Feature",
  "properties": {
    "gn:admin1_code":"29.0",
    "gn:asciiname":"Mannong",
    "gn:country_code":"CN",
    "gn:dem":1422,
    "gn:feature_class":"P",
    "gn:feature_code":"PPL",
    "gn:name":"Mannong",
    "gn:population":0,
    "gn:timezone":"Asia/Shanghai",
    "iso:country":"CN",
    "name:zho_x_preferred":[
        "\u66fc\u5f04"
    ],
    "wof:name":"Mannong",
    "wof:placetype":"locality"
},
  "geometry": {"coordinates":[97.914,24.4786],"type":"Point"}
}