{
  "type": "Feature",
  "properties": {
    "gn:admin1_code":"15.0",
    "gn:asciiname":"Likou",
    "gn:country_code":"CN",
    "gn:dem":1059,
    "gn:feature_class":"P",
    "gn:feature_code":"PPL",
    "gn:name":"Likou",
    "gn:population":0,
    "gn:timezone":"Asia/Shanghai",
    "iso:country":"CN",
    "name:fas_x_preferred":[
        "\u0644\u06cc\u06a9\u0648\u0648"
    ],
    "name:zho_x_preferred":[
        "\u91cc\u53e3"
    ],
    "name:zho_x_variant":[
        "\u5386\u53e3\u9547"
    ],
    "wof:name":"Likou",
    "wof:placetype":"locality"
},
  "geometry": {"coordinates":[107.48699999999999,35.2195],"type":"Point"}
}