{
  "type": "Feature",
  "properties": {
    "gn:admin1_code":"11.0",
    "gn:asciiname":"Huo'erya",
    "gn:country_code":"CN",
    "gn:dem":327,
    "gn:feature_class":"P",
    "gn:feature_code":"PPL",
    "gn:name":"Huo\u2019erya",
    "gn:population":0,
    "gn:timezone":"Asia/Shanghai",
    "iso:country":"CN",
    "name:zho_x_preferred":[
        "\u706b\u513f\u57ad"
    ],
    "name:zho_x_variant":[
        "Huo\u2019erya"
    ],
    "wof:name":"Huo'erya",
    "wof:placetype":"locality"
},
  "geometry": {"coordinates":[110.72967,29.4697],"type":"Point"}
}