{
  "type": "Feature",
  "properties": {
    "gn:admin1_code":"19.0",
    "gn:asciiname":"Jiatuncun",
    "gn:country_code":"CN",
    "gn:dem":90,
    "gn:feature_class":"P",
    "gn:feature_code":"PPL",
    "gn:name":"Jiatuncun",
    "gn:population":0,
    "gn:timezone":"Asia/Shanghai",
    "iso:country":"CN",
    "name:zho_x_preferred":[
        "\u8d3e\u5c6f\u6751"
    ],
    "wof:name":"Jiatuncun",
    "wof:placetype":"locality"
},
  "geometry": {"coordinates":[122.021,39.9072],"type":"Point"}
}