{
  "type": "Feature",
  "properties": {
    "gn:admin1_code":"11.0",
    "gn:asciiname":"Yaogongpo",
    "gn:country_code":"CN",
    "gn:dem":361,
    "gn:feature_class":"P",
    "gn:feature_code":"PPL",
    "gn:name":"Yaogongpo",
    "gn:population":0,
    "gn:timezone":"Asia/Shanghai",
    "iso:country":"CN",
    "name:und_x_variant":[
        "Megongpo",
        "Yaogongpo"
    ],
    "name:zho_x_preferred":[
        "\u4e48\u516c\u5761"
    ],
    "wof:name":"Yaogongpo",
    "wof:placetype":"locality"
},
  "geometry": {"coordinates":[110.56276,29.09791],"type":"Point"}
}