{
  "type": "Feature",
  "properties": {
    "gn:admin1_code":"29.0",
    "gn:asciiname":"Bubuzhai",
    "gn:country_code":"CN",
    "gn:dem":864,
    "gn:feature_class":"P",
    "gn:feature_code":"PPL",
    "gn:name":"Bubuzhai",
    "gn:population":0,
    "gn:timezone":"Asia/Shanghai",
    "iso:country":"CN",
    "name:zho_x_preferred":[
        "\u5821\u5821\u5be8"
    ],
    "wof:name":"Bubuzhai",
    "wof:placetype":"locality"
},
  "geometry": {"coordinates":[104.18300000000001,22.8871],"type":"Point"}
}