{
  "type": "Feature",
  "properties": {
    "gn:admin1_code":"30",
    "gn:asciiname":"Dianhou",
    "gn:country_code":"CN",
    "gn:dem":10,
    "gn:feature_class":"P",
    "gn:feature_code":"PPL",
    "gn:name":"Dianhou",
    "gn:population":0,
    "gn:timezone":"Asia/Shanghai",
    "iso:country":"CN",
    "name:zho_x_preferred":[
        "\u5e97\u540e"
    ],
    "wof:name":"Dianhou",
    "wof:placetype":"locality"
},
  "geometry": {"coordinates":[116.46156999999999,23.38283],"type":"Point"}
}