{
  "type": "Feature",
  "properties": {
    "gn:admin1_code":"25.0",
    "gn:asciiname":"Dongwujia",
    "gn:country_code":"CN",
    "gn:dem":31,
    "gn:feature_class":"P",
    "gn:feature_code":"PPL",
    "gn:name":"Dongwujia",
    "gn:population":0,
    "gn:timezone":"Asia/Shanghai",
    "iso:country":"CN",
    "name:zho_x_preferred":[
        "\u4e1c\u5434\u5bb6"
    ],
    "wof:name":"Dongwujia",
    "wof:placetype":"locality"
},
  "geometry": {"coordinates":[119.9538,36.71367],"type":"Point"}
}