{
  "type": "Feature",
  "properties": {
    "gn:admin1_code":"11.0",
    "gn:asciiname":"Huangniwan",
    "gn:country_code":"CN",
    "gn:dem":92,
    "gn:feature_class":"P",
    "gn:feature_code":"PPL",
    "gn:name":"Huangniwan",
    "gn:population":0,
    "gn:timezone":"Asia/Shanghai",
    "iso:country":"CN",
    "name:zho_x_preferred":[
        "\u9ec4\u6ce5\u6e7e"
    ],
    "wof:name":"Huangniwan",
    "wof:placetype":"locality"
},
  "geometry": {"coordinates":[113.67283999999999,27.82752],"type":"Point"}
}