{
  "type": "Feature",
  "properties": {
    "gn:admin1_code":"19.0",
    "gn:asciiname":"Zhuanwanzi",
    "gn:country_code":"CN",
    "gn:dem":237,
    "gn:feature_class":"P",
    "gn:feature_code":"PPL",
    "gn:name":"Zhuanwanzi",
    "gn:population":0,
    "gn:timezone":"Asia/Shanghai",
    "iso:country":"CN",
    "name:zho_x_preferred":[
        "\u8f6c\u5f2f\u5b50"
    ],
    "wof:name":"Zhuanwanzi",
    "wof:placetype":"locality"
},
  "geometry": {"coordinates":[123.68600000000001,41.3911],"type":"Point"}
}