{
  "type": "Feature",
  "properties": {
    "gn:admin1_code":"08",
    "gn:asciiname":"Jianxing",
    "gn:country_code":"CN",
    "gn:dem":290,
    "gn:feature_class":"P",
    "gn:feature_code":"PPL",
    "gn:name":"Jianxing",
    "gn:population":0,
    "gn:timezone":"Asia/Shanghai",
    "iso:country":"CN",
    "name:deu_x_preferred":[
        "Jianxing"
    ],
    "wof:name":"Jianxing",
    "wof:placetype":"locality"
},
  "geometry": {"coordinates":[127.90000000000001,47.75],"type":"Point"}
}