{
  "type": "Feature",
  "properties": {
    "gn:admin1_code":"26.0",
    "gn:asciiname":"Chuankoucun",
    "gn:country_code":"CN",
    "gn:dem":710,
    "gn:feature_class":"P",
    "gn:feature_code":"PPL",
    "gn:name":"Chuankoucun",
    "gn:population":0,
    "gn:timezone":"Asia/Shanghai",
    "iso:country":"CN",
    "name:zho_x_preferred":[
        "\u5ddd\u53e3\u6751"
    ],
    "wof:name":"Chuankoucun",
    "wof:placetype":"locality"
},
  "geometry": {"coordinates":[110.72266,37.68474000000001],"type":"Point"}
}