{
  "type": "Feature",
  "properties": {
    "gn:admin1_code":"22.0",
    "gn:asciiname":"Xiaohuangtangcun",
    "gn:country_code":"CN",
    "gn:dem":279,
    "gn:feature_class":"P",
    "gn:feature_code":"PPL",
    "gn:name":"Xiaohuangtangcun",
    "gn:population":0,
    "gn:timezone":"Asia/Shanghai",
    "iso:country":"CN",
    "name:zho_x_preferred":[
        "\u5c0f\u9ec4\u5858\u6751"
    ],
    "wof:name":"Xiaohuangtangcun",
    "wof:placetype":"locality"
},
  "geometry": {"coordinates":[116.65065,40.70213],"type":"Point"}
}