{
  "type": "Feature",
  "properties": {
    "gn:admin1_code":"25",
    "gn:asciiname":"Bogewang",
    "gn:country_code":"CN",
    "gn:dem":9,
    "gn:feature_class":"P",
    "gn:feature_code":"PPL",
    "gn:name":"Bogewang",
    "gn:population":0,
    "gn:timezone":"Asia/Shanghai",
    "iso:country":"CN",
    "name:zho_x_preferred":[
        "\u9e41\u9e3d\u738b"
    ],
    "wof:name":"Bogewang",
    "wof:placetype":"locality"
},
  "geometry": {"coordinates":[117.589,37.8863],"type":"Point"}
}