{
  "type": "Feature",
  "properties": {
    "gn:admin1_code":"01",
    "gn:asciiname":"Xinmen",
    "gn:country_code":"CN",
    "gn:dem":154,
    "gn:feature_class":"P",
    "gn:feature_code":"PPLA4",
    "gn:name":"Xinmen",
    "gn:population":0,
    "gn:timezone":"Asia/Shanghai",
    "iso:country":"CN",
    "name:und_x_variant":[
        "Chieh-k\u2019ou",
        "Kaikowchen",
        "Chiehkouchen",
        "Kaikow",
        "Jiekou",
        "Jiekou Zhen",
        "Xinmen"
    ],
    "name:zho_x_preferred":[
        "\u65b0\u95e8"
    ],
    "name:zho_x_variant":[
        "\u8857\u53e3\u9547",
        "\u8857\u53e3"
    ],
    "wof:name":"Xinmen",
    "wof:placetype":"locality"
},
  "geometry": {"coordinates":[118.72378,29.75184],"type":"Point"}
}