{
  "type": "Feature",
  "properties": {
    "gn:admin1_code":"11.0",
    "gn:asciiname":"Caomenwan",
    "gn:country_code":"CN",
    "gn:dem":63,
    "gn:feature_class":"P",
    "gn:feature_code":"PPL",
    "gn:name":"Caomenwan",
    "gn:population":0,
    "gn:timezone":"Asia/Shanghai",
    "iso:country":"CN",
    "name:zho_x_preferred":[
        "\u69fd\u95e8\u6e7e"
    ],
    "wof:name":"Caomenwan",
    "wof:placetype":"locality"
},
  "geometry": {"coordinates":[112.53870999999999,28.35518],"type":"Point"}
}