{
  "type": "Feature",
  "properties": {
    "gn:admin1_code":"32.0",
    "gn:asciiname":"Xiaohuodi",
    "gn:country_code":"CN",
    "gn:dem":1473,
    "gn:feature_class":"P",
    "gn:feature_code":"PPL",
    "gn:name":"Xiaohuodi",
    "gn:population":0,
    "gn:timezone":"Asia/Shanghai",
    "iso:country":"CN",
    "name:zho_x_preferred":[
        "\u5c0f\u706b\u5730"
    ],
    "wof:name":"Xiaohuodi",
    "wof:placetype":"locality"
},
  "geometry": {"coordinates":[102.18899999999999,26.9973],"type":"Point"}
}