{
  "type": "Feature",
  "properties": {
    "gn:admin1_code":"14.0",
    "gn:asciiname":"Laiwa",
    "gn:country_code":"CN",
    "gn:dem":5258,
    "gn:feature_class":"P",
    "gn:feature_code":"PPLF",
    "gn:name":"Laiwa",
    "gn:population":0,
    "gn:timezone":"Asia/Urumqi",
    "iso:country":"CN",
    "name:bod_x_preferred":[
        "L\u00eaba"
    ],
    "name:und_x_variant":[
        "L\u00eaba"
    ],
    "name:zho_x_preferred":[
        "Laiwa"
    ],
    "name:zho_x_variant":[
        "\u6765\u5a03",
        "Maxiong",
        "\u9a6c\u96c4"
    ],
    "wof:name":"Laiwa",
    "wof:placetype":"locality"
},
  "geometry": {"coordinates":[87.40000000000001,29.86667000000001],"type":"Point"}
}