{
  "type": "Feature",
  "properties": {
    "gn:admin1_code":"11.0",
    "gn:asciiname":"Matianhu",
    "gn:country_code":"CN",
    "gn:dem":252,
    "gn:feature_class":"P",
    "gn:feature_code":"PPL",
    "gn:name":"Matianhu",
    "gn:population":0,
    "gn:timezone":"Asia/Shanghai",
    "iso:country":"CN",
    "name:zho_x_preferred":[
        "Matianhu"
    ],
    "name:zho_x_variant":[
        "\u9ebb\u7530\u6e56"
    ],
    "wof:name":"Matianhu",
    "wof:placetype":"locality"
},
  "geometry": {"coordinates":[111.12163,29.02922],"type":"Point"}
}