{
  "type": "Feature",
  "properties": {
    "gn:admin1_code":"11.0",
    "gn:asciiname":"Xinglongjie",
    "gn:cc2":"CN",
    "gn:country_code":"CN",
    "gn:dem":74,
    "gn:feature_class":"P",
    "gn:feature_code":"PPL",
    "gn:name":"Xinglongjie",
    "gn:population":0,
    "gn:timezone":"Asia/Shanghai",
    "iso:country":"CN",
    "name:und_x_variant":[
        "Hsing-lung-chieh",
        "Xinglongjie"
    ],
    "wof:name":"Xinglongjie",
    "wof:placetype":"locality"
},
  "geometry": {"coordinates":[111.18667000000001,28.80611],"type":"Point"}
}