{
  "type": "Feature",
  "properties": {
    "gn:admin1_code":"29.0",
    "gn:asciiname":"Maobacun",
    "gn:country_code":"CN",
    "gn:dem":1497,
    "gn:feature_class":"P",
    "gn:feature_code":"PPL",
    "gn:name":"Maobacun",
    "gn:population":0,
    "gn:timezone":"Asia/Shanghai",
    "iso:country":"CN",
    "name:zho_x_preferred":[
        "\u6bdb\u575d\u6751"
    ],
    "wof:name":"Maobacun",
    "wof:placetype":"locality"
},
  "geometry": {"coordinates":[105.102,27.6491],"type":"Point"}
}