{
  "type": "Feature",
  "properties": {
    "gn:admin1_code":"30",
    "gn:asciiname":"Tangukeng",
    "gn:country_code":"CN",
    "gn:dem":196,
    "gn:feature_class":"P",
    "gn:feature_code":"PPL",
    "gn:name":"Tangukeng",
    "gn:population":0,
    "gn:timezone":"Asia/Shanghai",
    "iso:country":"CN",
    "name:zho_x_preferred":[
        "\u6f6d\u8c37\u5751"
    ],
    "wof:name":"Tangukeng",
    "wof:placetype":"locality"
},
  "geometry": {"coordinates":[115.62593,24.3302],"type":"Point"}
}