{
  "type": "Feature",
  "properties": {
    "gn:admin1_code":"3.0",
    "gn:asciiname":"Zhaiqiancun",
    "gn:country_code":"CN",
    "gn:dem":109,
    "gn:feature_class":"P",
    "gn:feature_code":"PPL",
    "gn:name":"Zhaiqiancun",
    "gn:population":0,
    "gn:timezone":"Asia/Shanghai",
    "iso:country":"CN",
    "name:zho_x_preferred":[
        "\u5b85\u524d\u6751"
    ],
    "wof:name":"Zhaiqiancun",
    "wof:placetype":"locality"
},
  "geometry": {"coordinates":[118.315,28.6892],"type":"Point"}
}