{
  "type": "Feature",
  "properties": {
    "gn:admin1_code":"15.0",
    "gn:asciiname":"Zhaike",
    "gn:country_code":"CN",
    "gn:dem":1914,
    "gn:feature_class":"P",
    "gn:feature_code":"PPL",
    "gn:name":"Zhaike",
    "gn:population":0,
    "gn:timezone":"Asia/Shanghai",
    "iso:country":"CN",
    "name:zho_x_preferred":[
        "\u5be8\u67ef"
    ],
    "wof:name":"Zhaike",
    "wof:placetype":"locality"
},
  "geometry": {"coordinates":[105.371,36.2934],"type":"Point"}
}