{
  "type": "Feature",
  "properties": {
    "gn:admin1_code":"32.0",
    "gn:asciiname":"Tai'an",
    "gn:country_code":"CN",
    "gn:dem":450,
    "gn:feature_class":"P",
    "gn:feature_code":"PPL",
    "gn:name":"Tai\u2019an",
    "gn:population":0,
    "gn:timezone":"Asia/Shanghai",
    "iso:country":"CN",
    "name:und_x_variant":[
        "Tai\u2019an"
    ],
    "name:zho_x_preferred":[
        "\u592a\u5b89"
    ],
    "wof:name":"Tai'an",
    "wof:placetype":"locality"
},
  "geometry": {"coordinates":[104.834,30.3372],"type":"Point"}
}