{
  "type": "Feature",
  "properties": {
    "gn:admin1_code":"12",
    "gn:asciiname":"Jiangxidian",
    "gn:country_code":"CN",
    "gn:dem":181,
    "gn:feature_class":"P",
    "gn:feature_code":"PPL",
    "gn:name":"Jiangxidian",
    "gn:population":0,
    "gn:timezone":"Asia/Shanghai",
    "iso:country":"CN",
    "name:und_x_variant":[
        "Chiang-ch\u2019i-tien",
        "Jiangxidian",
        "\u6d46\u6eaa\u5e97"
    ],
    "wof:name":"Jiangxidian",
    "wof:placetype":"locality"
},
  "geometry": {"coordinates":[113.70461,31.99098],"type":"Point"}
}