{
  "type": "Feature",
  "properties": {
    "gn:admin1_code":"4.0",
    "gn:asciiname":"Fan'nan",
    "gn:country_code":"CN",
    "gn:dem":5,
    "gn:feature_class":"P",
    "gn:feature_code":"PPL",
    "gn:name":"Fan\u2019nan",
    "gn:population":0,
    "gn:timezone":"Asia/Shanghai",
    "iso:country":"CN",
    "name:und_x_variant":[
        "Fan\u2019nan"
    ],
    "name:zho_x_preferred":[
        "\u8303\u5357"
    ],
    "wof:name":"Fan'nan",
    "wof:placetype":"locality"
},
  "geometry": {"coordinates":[121.29583999999998,32.03459],"type":"Point"}
}