{
  "type": "Feature",
  "properties": {
    "gn:admin1_code":"07",
    "gn:asciiname":"Liankengwei",
    "gn:country_code":"CN",
    "gn:dem":222,
    "gn:feature_class":"P",
    "gn:feature_code":"PPL",
    "gn:name":"Liankengwei",
    "gn:population":0,
    "gn:timezone":"Asia/Shanghai",
    "iso:country":"CN",
    "name:und_x_variant":[
        "Linkengwei"
    ],
    "name:zho_x_preferred":[
        "\u83b2\u5751\u5c3e"
    ],
    "wof:name":"Liankengwei",
    "wof:placetype":"locality"
},
  "geometry": {"coordinates":[118.01194,25.21833],"type":"Point"}
}