{
  "type": "Feature",
  "properties": {
    "gn:admin1_code":"24.0",
    "gn:asciiname":"Diantoucun",
    "gn:country_code":"CN",
    "gn:dem":1247,
    "gn:feature_class":"P",
    "gn:feature_code":"PPL",
    "gn:name":"Diantoucun",
    "gn:population":0,
    "gn:timezone":"Asia/Shanghai",
    "iso:country":"CN",
    "name:zho_x_preferred":[
        "\u6bbf\u5934\u6751"
    ],
    "wof:name":"Diantoucun",
    "wof:placetype":"locality"
},
  "geometry": {"coordinates":[113.08193,38.84981],"type":"Point"}
}