{
  "type": "Feature",
  "properties": {
    "gn:admin1_code":"12.0",
    "gn:asciiname":"Xiashe",
    "gn:country_code":"CN",
    "gn:dem":524,
    "gn:feature_class":"P",
    "gn:feature_code":"PPL",
    "gn:name":"Xiashe",
    "gn:population":0,
    "gn:timezone":"Asia/Shanghai",
    "iso:country":"CN",
    "name:zho_x_preferred":[
        "Xiashe"
    ],
    "name:zho_x_variant":[
        "\u4e0b\u820d"
    ],
    "wof:name":"Xiashe",
    "wof:placetype":"locality"
},
  "geometry": {"coordinates":[114.90595999999999,29.44415],"type":"Point"}
}