{
  "type": "Feature",
  "properties": {
    "gn:admin1_code":"3.0",
    "gn:asciiname":"Ganjia",
    "gn:country_code":"CN",
    "gn:dem":31,
    "gn:feature_class":"P",
    "gn:feature_code":"PPL",
    "gn:name":"Ganjia",
    "gn:population":0,
    "gn:timezone":"Asia/Shanghai",
    "iso:country":"CN",
    "name:und_x_variant":[
        "\u7518\u5bb6"
    ],
    "wof:name":"Ganjia",
    "wof:placetype":"locality"
},
  "geometry": {"coordinates":[116.50834999999999,29.38],"type":"Point"}
}