{
  "type": "Feature",
  "properties": {
    "gn:admin1_code":"12.0",
    "gn:asciiname":"Kangjiatai",
    "gn:country_code":"CN",
    "gn:dem":37,
    "gn:feature_class":"P",
    "gn:feature_code":"PPL",
    "gn:name":"Kangjiatai",
    "gn:population":0,
    "gn:timezone":"Asia/Shanghai",
    "iso:country":"CN",
    "name:zho_x_preferred":[
        "\u5eb7\u5bb6\u53f0"
    ],
    "wof:name":"Kangjiatai",
    "wof:placetype":"locality"
},
  "geometry": {"coordinates":[112.71195,30.84172],"type":"Point"}
}