{
  "type": "Feature",
  "properties": {
    "gn:admin1_code":"3.0",
    "gn:asciiname":"Zhaiwuling",
    "gn:country_code":"CN",
    "gn:dem":180,
    "gn:feature_class":"P",
    "gn:feature_code":"PPL",
    "gn:name":"Zhaiwuling",
    "gn:population":0,
    "gn:timezone":"Asia/Shanghai",
    "iso:country":"CN",
    "name:und_x_variant":[
        "\u5be8\u5c4b\u5cad"
    ],
    "wof:name":"Zhaiwuling",
    "wof:placetype":"locality"
},
  "geometry": {"coordinates":[115.7835,25.44583],"type":"Point"}
}