{
  "type": "Feature",
  "properties": {
    "gn:admin1_code":"29.0",
    "gn:asciiname":"Suozuoni",
    "gn:country_code":"CN",
    "gn:dem":2014,
    "gn:feature_class":"P",
    "gn:feature_code":"PPL",
    "gn:name":"Suozuoni",
    "gn:population":0,
    "gn:timezone":"Asia/Shanghai",
    "iso:country":"CN",
    "name:zho_x_preferred":[
        "\u6240\u4f5c\u6ce5"
    ],
    "wof:name":"Suozuoni",
    "wof:placetype":"locality"
},
  "geometry": {"coordinates":[103.806,23.3707],"type":"Point"}
}