{
  "type": "Feature",
  "properties": {
    "gn:admin1_code":"30.0",
    "gn:asciiname":"Xialoucun",
    "gn:country_code":"CN",
    "gn:dem":44,
    "gn:feature_class":"P",
    "gn:feature_code":"PPL",
    "gn:name":"Xialoucun",
    "gn:population":0,
    "gn:timezone":"Asia/Shanghai",
    "iso:country":"CN",
    "name:zho_x_preferred":[
        "\u4e0b\u697c\u6751"
    ],
    "wof:name":"Xialoucun",
    "wof:placetype":"locality"
},
  "geometry": {"coordinates":[116.92355000000001,23.84085],"type":"Point"}
}