{
  "type": "Feature",
  "properties": {
    "gn:admin1_code":"8.0",
    "gn:asciiname":"Bei'ancun",
    "gn:country_code":"CN",
    "gn:dem":302,
    "gn:feature_class":"P",
    "gn:feature_code":"PPL",
    "gn:name":"Bei\u2019ancun",
    "gn:population":0,
    "gn:timezone":"Asia/Shanghai",
    "iso:country":"CN",
    "name:und_x_variant":[
        "Bei\u2019ancun"
    ],
    "name:zho_x_preferred":[
        "\u5317\u5b89\u6751"
    ],
    "wof:name":"Bei'ancun",
    "wof:placetype":"locality"
},
  "geometry": {"coordinates":[129.10235,44.06858],"type":"Point"}
}