{
  "type": "Feature",
  "properties": {
    "gn:admin1_code":"8.0",
    "gn:asciiname":"Wanbao Yicun",
    "gn:country_code":"CN",
    "gn:dem":287,
    "gn:feature_class":"P",
    "gn:feature_code":"PPL",
    "gn:name":"Wanbao Yicun",
    "gn:population":0,
    "gn:timezone":"Asia/Shanghai",
    "iso:country":"CN",
    "name:zho_x_preferred":[
        "\u4e07\u5b9d\u4e00\u6751"
    ],
    "wof:name":"Wanbao Yicun",
    "wof:placetype":"locality"
},
  "geometry": {"coordinates":[130.76242999999999,43.77117],"type":"Point"}
}