{
  "type": "Feature",
  "properties": {
    "gn:admin1_code":"26.0",
    "gn:asciiname":"Zhailiangshang",
    "gn:country_code":"CN",
    "gn:dem":780,
    "gn:feature_class":"P",
    "gn:feature_code":"PPL",
    "gn:name":"Zhailiangshang",
    "gn:population":0,
    "gn:timezone":"Asia/Shanghai",
    "iso:country":"CN",
    "name:zho_x_preferred":[
        "\u5be8\u6881\u4e0a"
    ],
    "wof:name":"Zhailiangshang",
    "wof:placetype":"locality"
},
  "geometry": {"coordinates":[107.84683,32.62544],"type":"Point"}
}