{
  "type": "Feature",
  "properties": {
    "gn:admin1_code":"29.0",
    "gn:asciiname":"Wenshan",
    "gn:country_code":"CN",
    "gn:dem":1972,
    "gn:feature_class":"P",
    "gn:feature_code":"PPL",
    "gn:name":"Wenshan",
    "gn:population":0,
    "gn:timezone":"Asia/Shanghai",
    "iso:country":"CN",
    "name:ceb_x_preferred":[
        "Wenshan"
    ],
    "name:deu_x_preferred":[
        "Wenshan"
    ],
    "name:nld_x_preferred":[
        "Wenshan"
    ],
    "name:pol_x_preferred":[
        "Wenshan"
    ],
    "name:rus_x_preferred":[
        "\u0412\u044d\u043d\u044c\u0448\u0430\u043d\u044c"
    ],
    "name:und_x_variant":[
        "\u6587\u5c71"
    ],
    "wof:name":"Wenshan",
    "wof:placetype":"locality"
},
  "geometry": {"coordinates":[103.74306,27.66305],"type":"Point"}
}