{
  "type": "Feature",
  "properties": {
    "gn:admin1_code":"8.0",
    "gn:asciiname":"Weikangcun",
    "gn:country_code":"CN",
    "gn:dem":157,
    "gn:feature_class":"P",
    "gn:feature_code":"PPL",
    "gn:name":"Weikangcun",
    "gn:population":0,
    "gn:timezone":"Asia/Shanghai",
    "iso:country":"CN",
    "name:zho_x_preferred":[
        "\u536b\u5eb7\u6751"
    ],
    "wof:name":"Weikangcun",
    "wof:placetype":"locality"
},
  "geometry": {"coordinates":[126.24644000000001,46.16963],"type":"Point"}
}