{
  "type": "Feature",
  "properties": {
    "gn:admin1_code":"30",
    "gn:asciiname":"Diaojicun",
    "gn:country_code":"CN",
    "gn:dem":26,
    "gn:feature_class":"P",
    "gn:feature_code":"PPL",
    "gn:name":"Diaojicun",
    "gn:population":0,
    "gn:timezone":"Asia/Urumqi",
    "iso:country":"CN",
    "name:zho_x_preferred":[
        "\u540a\u9e21\u6751"
    ],
    "wof:name":"Diaojicun",
    "wof:placetype":"locality"
},
  "geometry": {"coordinates":[110.98732,21.59799],"type":"Point"}
}