{
  "type": "Feature",
  "properties": {
    "gn:admin1_code":"29.0",
    "gn:asciiname":"Dipanguan",
    "gn:country_code":"CN",
    "gn:dem":1994,
    "gn:feature_class":"P",
    "gn:feature_code":"PPL",
    "gn:name":"Dipanguan",
    "gn:population":0,
    "gn:timezone":"Asia/Shanghai",
    "iso:country":"CN",
    "name:zho_x_preferred":[
        "\u5730\u76d8\u5173"
    ],
    "wof:name":"Dipanguan",
    "wof:placetype":"locality"
},
  "geometry": {"coordinates":[98.5672,25.7315],"type":"Point"}
}