{
  "type": "Feature",
  "properties": {
    "gn:admin1_code":"26",
    "gn:asciiname":"Wawuping",
    "gn:country_code":"CN",
    "gn:dem":1393,
    "gn:feature_class":"P",
    "gn:feature_code":"PPL",
    "gn:name":"Wawuping",
    "gn:population":0,
    "gn:timezone":"Asia/Shanghai",
    "iso:country":"CN",
    "wof:name":"Wawuping",
    "wof:placetype":"locality"
},
  "geometry": {"coordinates":[108.57361000000002,33.56556],"type":"Point"}
}