{
  "type": "Feature",
  "properties": {
    "gn:admin1_code":"1.0",
    "gn:asciiname":"Duanlaojiacun",
    "gn:country_code":"CN",
    "gn:dem":41,
    "gn:feature_class":"P",
    "gn:feature_code":"PPL",
    "gn:name":"Duanlaojiacun",
    "gn:population":0,
    "gn:timezone":"Asia/Shanghai",
    "iso:country":"CN",
    "name:zho_x_preferred":[
        "\u6bb5\u8001\u5bb6\u6751"
    ],
    "wof:name":"Duanlaojiacun",
    "wof:placetype":"locality"
},
  "geometry": {"coordinates":[115.9541,33.99432],"type":"Point"}
}