{
  "type": "Feature",
  "properties": {
    "gn:admin1_code":"26.0",
    "gn:asciiname":"Yanyutao",
    "gn:cc2":"CN",
    "gn:country_code":"CN",
    "gn:dem":529,
    "gn:feature_class":"P",
    "gn:feature_code":"PPL",
    "gn:name":"Yanyutao",
    "gn:population":0,
    "gn:timezone":"Asia/Shanghai",
    "iso:country":"CN",
    "name:und_x_variant":[
        "Yen-y\u00fc-t\u2019ao",
        "Yanyutao"
    ],
    "wof:name":"Yanyutao",
    "wof:placetype":"locality"
},
  "geometry": {"coordinates":[109.75,32.73333],"type":"Point"}
}