{
  "type": "Feature",
  "properties": {
    "gn:admin1_code":"19.0",
    "gn:asciiname":"Laomajia",
    "gn:country_code":"CN",
    "gn:dem":344,
    "gn:feature_class":"P",
    "gn:feature_code":"PPL",
    "gn:name":"Laomajia",
    "gn:population":0,
    "gn:timezone":"Asia/Shanghai",
    "iso:country":"CN",
    "name:und_x_variant":[
        "\u8001\u9a6c\u5bb6"
    ],
    "name:zho_x_preferred":[
        "\u8001\u9a6c\u5bb6"
    ],
    "wof:name":"Laomajia",
    "wof:placetype":"locality"
},
  "geometry": {"coordinates":[119.81928000000001,40.58931],"type":"Point"}
}