{
  "type": "Feature",
  "properties": {
    "gn:admin1_code":"11.0",
    "gn:asciiname":"Xianrenzhang",
    "gn:country_code":"CN",
    "gn:dem":300,
    "gn:feature_class":"P",
    "gn:feature_code":"PPL",
    "gn:name":"Xianrenzhang",
    "gn:population":0,
    "gn:timezone":"Asia/Shanghai",
    "iso:country":"CN",
    "name:zho_x_preferred":[
        "\u4ed9\u4eba\u638c"
    ],
    "wof:name":"Xianrenzhang",
    "wof:placetype":"locality"
},
  "geometry": {"coordinates":[113.70749000000001,28.34853],"type":"Point"}
}