{
  "type": "Feature",
  "properties": {
    "gn:admin1_code":"29.0",
    "gn:asciiname":"Xiaolishao",
    "gn:country_code":"CN",
    "gn:dem":1780,
    "gn:feature_class":"P",
    "gn:feature_code":"PPL",
    "gn:name":"Xiaolishao",
    "gn:population":0,
    "gn:timezone":"Asia/Shanghai",
    "iso:country":"CN",
    "name:zho_x_preferred":[
        "\u5c0f\u6817\u54e8"
    ],
    "wof:name":"Xiaolishao",
    "wof:placetype":"locality"
},
  "geometry": {"coordinates":[101.881,25.0718],"type":"Point"}
}