{
  "type": "Feature",
  "properties": {
    "gn:admin1_code":"5.0",
    "gn:asciiname":"Nandagou",
    "gn:country_code":"CN",
    "gn:dem":166,
    "gn:feature_class":"P",
    "gn:feature_code":"PPL",
    "gn:name":"Nandagou",
    "gn:population":0,
    "gn:timezone":"Asia/Shanghai",
    "iso:country":"CN",
    "name:zho_x_preferred":[
        "\u5357\u5927\u6c9f"
    ],
    "wof:name":"Nandagou",
    "wof:placetype":"locality"
},
  "geometry": {"coordinates":[126.60048,44.99224],"type":"Point"}
}