{
  "type": "Feature",
  "properties": {
    "gn:admin1_code":"09",
    "gn:asciiname":"Changling",
    "gn:cc2":"CN",
    "gn:country_code":"CN",
    "gn:dem":35,
    "gn:feature_class":"P",
    "gn:feature_code":"PPL",
    "gn:name":"Changling",
    "gn:population":0,
    "gn:timezone":"Asia/Shanghai",
    "iso:country":"CN",
    "name:ceb_x_preferred":[
        "Changling"
    ],
    "name:deu_x_preferred":[
        "Changling"
    ],
    "name:mlg_x_preferred":[
        "Changling"
    ],
    "name:swe_x_preferred":[
        "Changling"
    ],
    "name:ukr_x_preferred":[
        "\u0427\u0430\u043d\u043b\u0456\u043d"
    ],
    "name:und_x_variant":[
        "Ch\u2019ang-ling-chi",
        "Changlingji"
    ],
    "wof:name":"Changling",
    "wof:placetype":"locality"
},
  "geometry": {"coordinates":[115.09833,32.37583],"type":"Point"}
}