{
  "type": "Feature",
  "properties": {
    "gn:admin1_code":"11",
    "gn:asciiname":"Shuren",
    "gn:country_code":"CN",
    "gn:dem":772,
    "gn:feature_class":"P",
    "gn:feature_code":"PPL",
    "gn:name":"Shuren",
    "gn:population":0,
    "gn:timezone":"Asia/Shanghai",
    "iso:country":"CN",
    "name:zho_x_preferred":[
        "\u6811\u4ec1"
    ],
    "wof:name":"Shuren",
    "wof:placetype":"locality"
},
  "geometry": {"coordinates":[110.89003,27.61367000000001],"type":"Point"}
}