{
  "type": "Feature",
  "properties": {
    "gn:admin1_code":"31.0",
    "gn:asciiname":"Maonao",
    "gn:country_code":"CN",
    "gn:dem":553,
    "gn:feature_class":"P",
    "gn:feature_code":"PPL",
    "gn:name":"Maonao",
    "gn:population":0,
    "gn:timezone":"Asia/Shanghai",
    "iso:country":"CN",
    "name:zho_x_preferred":[
        "\u6bdb\u8111"
    ],
    "wof:name":"Maonao",
    "wof:placetype":"locality"
},
  "geometry": {"coordinates":[109.64069000000001,18.8982],"type":"Point"}
}