{
  "type": "Feature",
  "properties": {
    "gn:admin1_code":"2.0",
    "gn:asciiname":"Zhangzhai",
    "gn:country_code":"CN",
    "gn:dem":67,
    "gn:feature_class":"P",
    "gn:feature_code":"PPL",
    "gn:name":"Zhangzhai",
    "gn:population":0,
    "gn:timezone":"Asia/Shanghai",
    "iso:country":"CN",
    "name:und_x_variant":[
        "\u5f20\u5b85",
        "Zhangzhai"
    ],
    "wof:name":"Zhangzhai",
    "wof:placetype":"locality"
},
  "geometry": {"coordinates":[119.97659,29.21],"type":"Point"}
}