{
  "type": "Feature",
  "properties": {
    "gn:admin1_code":"1.0",
    "gn:asciiname":"Weidongcun",
    "gn:country_code":"CN",
    "gn:dem":9,
    "gn:feature_class":"P",
    "gn:feature_code":"PPL",
    "gn:name":"Weidongcun",
    "gn:population":0,
    "gn:timezone":"Asia/Shanghai",
    "iso:country":"CN",
    "name:zho_x_preferred":[
        "\u536b\u4e1c\u6751"
    ],
    "wof:name":"Weidongcun",
    "wof:placetype":"locality"
},
  "geometry": {"coordinates":[118.79828000000001,31.23053],"type":"Point"}
}