{
  "type": "Feature",
  "properties": {
    "gn:admin1_code":"32.0",
    "gn:asciiname":"Jiadang",
    "gn:country_code":"CN",
    "gn:dem":3431,
    "gn:feature_class":"P",
    "gn:feature_code":"PPL",
    "gn:name":"Jiadang",
    "gn:population":0,
    "gn:timezone":"Asia/Shanghai",
    "iso:country":"CN",
    "name:zho_x_preferred":[
        "\u7532\u5f53"
    ],
    "wof:name":"Jiadang",
    "wof:placetype":"locality"
},
  "geometry": {"coordinates":[101.53100000000001,32.9978],"type":"Point"}
}