{
  "type": "Feature",
  "properties": {
    "gn:admin1_code":"12.0",
    "gn:asciiname":"Xinwuping",
    "gn:country_code":"CN",
    "gn:dem":1094,
    "gn:feature_class":"P",
    "gn:feature_code":"PPL",
    "gn:name":"Xinwuping",
    "gn:population":0,
    "gn:timezone":"Asia/Shanghai",
    "iso:country":"CN",
    "name:zho_x_preferred":[
        "Xinwuping"
    ],
    "name:zho_x_variant":[
        "\u65b0\u5c4b\u576a"
    ],
    "wof:name":"Xinwuping",
    "wof:placetype":"locality"
},
  "geometry": {"coordinates":[110.15845,29.95676],"type":"Point"}
}