{
  "type": "Feature",
  "properties": {
    "gn:admin1_code":"7",
    "gn:asciiname":"Jitou",
    "gn:country_code":"CN",
    "gn:dem":309,
    "gn:feature_class":"P",
    "gn:feature_code":"PPL",
    "gn:name":"Jitou",
    "gn:population":0,
    "gn:timezone":"Asia/Shanghai",
    "iso:country":"CN",
    "name:und_x_variant":[
        "\u57fa\u5934"
    ],
    "wof:name":"Jitou",
    "wof:placetype":"locality"
},
  "geometry": {"coordinates":[116.78301999999999,26.2167],"type":"Point"}
}