{
  "type": "Feature",
  "properties": {
    "gn:admin1_code":"11.0",
    "gn:asciiname":"Lemashan",
    "gn:country_code":"CN",
    "gn:dem":58,
    "gn:feature_class":"P",
    "gn:feature_code":"PPL",
    "gn:name":"Lemashan",
    "gn:population":0,
    "gn:timezone":"Asia/Shanghai",
    "iso:country":"CN",
    "name:zho_x_preferred":[
        "\u52d2\u9a6c\u5c71"
    ],
    "wof:name":"Lemashan",
    "wof:placetype":"locality"
},
  "geometry": {"coordinates":[112.82993999999999,28.50654],"type":"Point"}
}