{
  "type": "Feature",
  "properties": {
    "gn:admin1_code":"16.0",
    "gn:asciiname":"Jiu Zhen",
    "gn:country_code":"CN",
    "gn:dem":158,
    "gn:feature_class":"P",
    "gn:feature_code":"PPL",
    "gn:name":"Jiu Zhen",
    "gn:population":0,
    "gn:timezone":"Asia/Shanghai",
    "iso:country":"CN",
    "name:zho_x_preferred":[
        "\u65e7\u9547"
    ],
    "wof:name":"Jiu Zhen",
    "wof:placetype":"locality"
},
  "geometry": {"coordinates":[108.604,23.8493],"type":"Point"}
}