{
  "type": "Feature",
  "properties": {
    "gn:admin1_code":"4.0",
    "gn:asciiname":"Jiexicun",
    "gn:country_code":"CN",
    "gn:dem":24,
    "gn:feature_class":"P",
    "gn:feature_code":"PPL",
    "gn:name":"Jiexicun",
    "gn:population":0,
    "gn:timezone":"Asia/Shanghai",
    "iso:country":"CN",
    "name:zho_x_preferred":[
        "\u8857\u897f\u6751"
    ],
    "wof:name":"Jiexicun",
    "wof:placetype":"locality"
},
  "geometry": {"coordinates":[117.95050000000001,34.2381],"type":"Point"}
}