{
  "type": "Feature",
  "properties": {
    "gn:admin1_code":"15.0",
    "gn:asciiname":"Bajiao",
    "gn:country_code":"CN",
    "gn:dem":2306,
    "gn:feature_class":"P",
    "gn:feature_code":"PPLA4",
    "gn:name":"Bajiao",
    "gn:population":0,
    "gn:timezone":"Asia/Shanghai",
    "iso:country":"CN",
    "name:und_x_variant":[
        "\u516b\u89d2"
    ],
    "wof:name":"Bajiao",
    "wof:placetype":"locality"
},
  "geometry": {"coordinates":[103.69692999999999,35.02825],"type":"Point"}
}