{
  "type": "Feature",
  "properties": {
    "gn:admin1_code":"26.0",
    "gn:asciiname":"Mianzhanglingcun",
    "gn:country_code":"CN",
    "gn:dem":877,
    "gn:feature_class":"P",
    "gn:feature_code":"PPL",
    "gn:name":"Mianzhanglingcun",
    "gn:population":0,
    "gn:timezone":"Asia/Shanghai",
    "iso:country":"CN",
    "name:und_x_variant":[
        "\u9762\u5f20\u5cad\u6751"
    ],
    "wof:name":"Mianzhanglingcun",
    "wof:placetype":"locality"
},
  "geometry": {"coordinates":[109.42336,34.21927],"type":"Point"}
}