{
  "type": "Feature",
  "properties": {
    "gn:admin1_code":"8.0",
    "gn:asciiname":"Fengniancun",
    "gn:country_code":"CN",
    "gn:dem":231,
    "gn:feature_class":"P",
    "gn:feature_code":"PPL",
    "gn:name":"Fengniancun",
    "gn:population":0,
    "gn:timezone":"Asia/Shanghai",
    "iso:country":"CN",
    "name:zho_x_preferred":[
        "\u4e30\u5e74\u6751"
    ],
    "wof:name":"Fengniancun",
    "wof:placetype":"locality"
},
  "geometry": {"coordinates":[125.39924000000001,48.45842],"type":"Point"}
}