{
  "type": "Feature",
  "properties": {
    "gn:admin1_code":"24.0",
    "gn:asciiname":"Loujiazhuang",
    "gn:country_code":"CN",
    "gn:dem":1185,
    "gn:feature_class":"P",
    "gn:feature_code":"PPL",
    "gn:name":"Loujiazhuang",
    "gn:population":0,
    "gn:timezone":"Asia/Shanghai",
    "iso:country":"CN",
    "name:zho_x_preferred":[
        "\u5a04\u5bb6\u5e84"
    ],
    "wof:name":"Loujiazhuang",
    "wof:placetype":"locality"
},
  "geometry": {"coordinates":[111.78388,38.05901],"type":"Point"}
}