{
  "type": "Feature",
  "properties": {
    "gn:admin1_code":"16.0",
    "gn:asciiname":"Zhefa",
    "gn:country_code":"CN",
    "gn:dem":810,
    "gn:feature_class":"P",
    "gn:feature_code":"PPL",
    "gn:name":"Zhefa",
    "gn:population":0,
    "gn:timezone":"Asia/Shanghai",
    "iso:country":"CN",
    "name:zho_x_preferred":[
        "\u8005\u6cd5"
    ],
    "wof:name":"Zhefa",
    "wof:placetype":"locality"
},
  "geometry": {"coordinates":[106.48,23.3535],"type":"Point"}
}