{
  "type": "Feature",
  "properties": {
    "gn:admin1_code":"5.0",
    "gn:asciiname":"Diaoyutaicun",
    "gn:country_code":"CN",
    "gn:dem":152,
    "gn:feature_class":"P",
    "gn:feature_code":"PPL",
    "gn:name":"Diaoyutaicun",
    "gn:population":0,
    "gn:timezone":"Asia/Shanghai",
    "iso:country":"CN",
    "name:zho_x_preferred":[
        "\u9493\u9c7c\u53f0\u6751"
    ],
    "wof:name":"Diaoyutaicun",
    "wof:placetype":"locality"
},
  "geometry": {"coordinates":[125.4286,44.80859],"type":"Point"}
}