{
  "type": "Feature",
  "properties": {
    "gn:admin1_code":"29.0",
    "gn:asciiname":"Nilihei",
    "gn:country_code":"CN",
    "gn:dem":2471,
    "gn:feature_class":"P",
    "gn:feature_code":"PPL",
    "gn:name":"Nilihei",
    "gn:population":0,
    "gn:timezone":"Asia/Shanghai",
    "iso:country":"CN",
    "name:zho_x_preferred":[
        "\u5c3c\u4e3d\u9ed1"
    ],
    "wof:name":"Nilihei",
    "wof:placetype":"locality"
},
  "geometry": {"coordinates":[101.379,26.0967],"type":"Point"}
}