{
  "type": "Feature",
  "properties": {
    "gn:admin1_code":"2.0",
    "gn:asciiname":"Kuzhuping",
    "gn:country_code":"CN",
    "gn:dem":512,
    "gn:feature_class":"P",
    "gn:feature_code":"PPL",
    "gn:name":"Kuzhuping",
    "gn:population":0,
    "gn:timezone":"Asia/Shanghai",
    "iso:country":"CN",
    "name:und_x_variant":[
        "\u82e6\u7af9\u576a",
        "Kuzhuping"
    ],
    "name:zho_x_preferred":[
        "\u82e6\u7af9\u576a\u4e61"
    ],
    "wof:name":"Kuzhuping",
    "wof:placetype":"locality"
},
  "geometry": {"coordinates":[119.60590000000001,29.65115],"type":"Point"}
}