{
  "type": "Feature",
  "properties": {
    "gn:admin1_code":"26",
    "gn:asciiname":"Qiaoxi",
    "gn:country_code":"CN",
    "gn:dem":922,
    "gn:feature_class":"P",
    "gn:feature_code":"PPL",
    "gn:name":"Qiaoxi",
    "gn:population":0,
    "gn:timezone":"Asia/Shanghai",
    "iso:country":"CN",
    "name:und_x_variant":[
        "\u6865\u897f"
    ],
    "name:zho_x_preferred":[
        "\u6865\u897f"
    ],
    "wof:name":"Qiaoxi",
    "wof:placetype":"locality"
},
  "geometry": {"coordinates":[108.72750000000001,34.8225],"type":"Point"}
}