{
  "type": "Feature",
  "properties": {
    "gn:admin1_code":"8.0",
    "gn:asciiname":"Shihe Daweizi",
    "gn:country_code":"CN",
    "gn:dem":217,
    "gn:feature_class":"P",
    "gn:feature_code":"PPL",
    "gn:name":"Shihe Daweizi",
    "gn:population":0,
    "gn:timezone":"Asia/Shanghai",
    "iso:country":"CN",
    "name:zho_x_preferred":[
        "\u77f3\u6cb3\u5927\u56f4\u5b50"
    ],
    "wof:name":"Shihe Daweizi",
    "wof:placetype":"locality"
},
  "geometry": {"coordinates":[127.20596999999999,45.29633],"type":"Point"}
}