{
  "type": "Feature",
  "properties": {
    "gn:admin1_code":"5.0",
    "gn:asciiname":"Louzigouxiang Renshenchang",
    "gn:country_code":"CN",
    "gn:dem":499,
    "gn:feature_class":"P",
    "gn:feature_code":"PPLF",
    "gn:name":"Louzigouxiang Renshenchang",
    "gn:population":0,
    "gn:timezone":"Asia/Shanghai",
    "iso:country":"CN",
    "name:und_x_variant":[
        "\u7f57\u5b50\u6c9f\u4e61\u4eba\u53c2\u573a"
    ],
    "wof:name":"Louzigouxiang Renshenchang",
    "wof:placetype":"locality"
},
  "geometry": {"coordinates":[130.28014999999999,43.64699],"type":"Point"}
}