{
  "type": "Feature",
  "properties": {
    "gn:admin1_code":"19.0",
    "gn:asciiname":"Xiyancun",
    "gn:country_code":"CN",
    "gn:dem":82,
    "gn:feature_class":"P",
    "gn:feature_code":"PPL",
    "gn:name":"Xiyancun",
    "gn:population":0,
    "gn:timezone":"Asia/Shanghai",
    "iso:country":"CN",
    "name:zho_x_preferred":[
        "\u897f\u960e\u6751"
    ],
    "wof:name":"Xiyancun",
    "wof:placetype":"locality"
},
  "geometry": {"coordinates":[123.377,42.4704],"type":"Point"}
}