{
  "type": "Feature",
  "properties": {
    "gn:admin1_code":"15.0",
    "gn:asciiname":"Heiwo",
    "gn:country_code":"CN",
    "gn:dem":3014,
    "gn:feature_class":"P",
    "gn:feature_code":"PPL",
    "gn:name":"Heiwo",
    "gn:population":0,
    "gn:timezone":"Asia/Shanghai",
    "iso:country":"CN",
    "name:zho_x_preferred":[
        "\u9ed1\u7a9d"
    ],
    "wof:name":"Heiwo",
    "wof:placetype":"locality"
},
  "geometry": {"coordinates":[101.60899999999999,38.0737],"type":"Point"}
}