{
  "type": "Feature",
  "properties": {
    "gn:admin1_code":"4.0",
    "gn:asciiname":"Fanshenhecun",
    "gn:country_code":"CN",
    "gn:dem":2,
    "gn:feature_class":"P",
    "gn:feature_code":"PPL",
    "gn:name":"Fanshenhecun",
    "gn:population":0,
    "gn:timezone":"Asia/Shanghai",
    "iso:country":"CN",
    "name:zho_x_preferred":[
        "\u7ffb\u8eab\u6cb3\u6751"
    ],
    "wof:name":"Fanshenhecun",
    "wof:placetype":"locality"
},
  "geometry": {"coordinates":[120.22729,34.27692],"type":"Point"}
}