{
  "type": "Feature",
  "properties": {
    "gn:admin1_code":"25",
    "gn:asciiname":"Yanzhuang",
    "gn:country_code":"CN",
    "gn:dem":41,
    "gn:feature_class":"P",
    "gn:feature_code":"PPL",
    "gn:name":"Yanzhuang",
    "gn:population":0,
    "gn:timezone":"Asia/Shanghai",
    "iso:country":"CN",
    "name:ceb_x_preferred":[
        "Yanzhuang"
    ],
    "name:swe_x_preferred":[
        "Yanzhuang"
    ],
    "name:zho_x_preferred":[
        "\u71d5\u5e84"
    ],
    "wof:name":"Yanzhuang",
    "wof:placetype":"locality"
},
  "geometry": {"coordinates":[116.538,36.4005],"type":"Point"}
}