{
  "type": "Feature",
  "properties": {
    "gn:admin1_code":"11.0",
    "gn:asciiname":"Xiaoliangxi",
    "gn:country_code":"CN",
    "gn:dem":440,
    "gn:feature_class":"P",
    "gn:feature_code":"PPL",
    "gn:name":"Xiaoliangxi",
    "gn:population":0,
    "gn:timezone":"Asia/Shanghai",
    "iso:country":"CN",
    "name:zho_x_preferred":[
        "\u5c0f\u826f\u6eaa"
    ],
    "wof:name":"Xiaoliangxi",
    "wof:placetype":"locality"
},
  "geometry": {"coordinates":[110.47789,28.03614],"type":"Point"}
}