{
  "type": "Feature",
  "properties": {
    "gn:admin1_code":"19",
    "gn:asciiname":"Wu-chia-chieh",
    "gn:country_code":"CN",
    "gn:dem":291,
    "gn:feature_class":"P",
    "gn:feature_code":"PPL",
    "gn:name":"Wu-chia-chieh",
    "gn:population":0,
    "gn:timezone":"Asia/Shanghai",
    "iso:country":"CN",
    "wof:name":"Wu-chia-chieh",
    "wof:placetype":"locality"
},
  "geometry": {"coordinates":[125.37056,41.32278],"type":"Point"}
}