{
  "type": "Feature",
  "properties": {
    "gn:admin1_code":"1.0",
    "gn:asciiname":"Changfengcun",
    "gn:country_code":"CN",
    "gn:dem":11,
    "gn:feature_class":"P",
    "gn:feature_code":"PPL",
    "gn:name":"Changfengcun",
    "gn:population":0,
    "gn:timezone":"Asia/Shanghai",
    "iso:country":"CN",
    "name:zho_x_preferred":[
        "\u5e38\u4e30\u6751"
    ],
    "wof:name":"Changfengcun",
    "wof:placetype":"locality"
},
  "geometry": {"coordinates":[117.30455000000001,31.46613],"type":"Point"}
}