{
  "type": "Feature",
  "properties": {
    "gn:admin1_code":"15.0",
    "gn:asciiname":"Mengjiamen",
    "gn:country_code":"CN",
    "gn:dem":1791,
    "gn:feature_class":"P",
    "gn:feature_code":"PPL",
    "gn:name":"Mengjiamen",
    "gn:population":0,
    "gn:timezone":"Asia/Shanghai",
    "iso:country":"CN",
    "name:und_x_variant":[
        "\u5b5f\u5bb6\u95e8"
    ],
    "wof:name":"Mengjiamen",
    "wof:placetype":"locality"
},
  "geometry": {"coordinates":[104.65076000000001,34.9348],"type":"Point"}
}