{
  "type": "Feature",
  "properties": {
    "gn:admin1_code":"4.0",
    "gn:asciiname":"Xiaolin",
    "gn:country_code":"CN",
    "gn:dem":7,
    "gn:feature_class":"P",
    "gn:feature_code":"PPL",
    "gn:name":"Xiaolin",
    "gn:population":0,
    "gn:timezone":"Asia/Shanghai",
    "iso:country":"CN",
    "name:und_x_variant":[
        "\u8096\u6797"
    ],
    "name:zho_x_preferred":[
        "\u8096\u6797"
    ],
    "wof:name":"Xiaolin",
    "wof:placetype":"locality"
},
  "geometry": {"coordinates":[120.0042,32.32371],"type":"Point"}
}