{
  "type": "Feature",
  "properties": {
    "gn:admin1_code":"18",
    "gn:asciiname":"Ningjiaping",
    "gn:country_code":"CN",
    "gn:dem":658,
    "gn:feature_class":"P",
    "gn:feature_code":"PPL",
    "gn:name":"Ningjiaping",
    "gn:population":0,
    "gn:timezone":"Asia/Shanghai",
    "iso:country":"CN",
    "name:zho_x_preferred":[
        "\u5b81\u5bb6\u576a"
    ],
    "wof:name":"Ningjiaping",
    "wof:placetype":"locality"
},
  "geometry": {"coordinates":[108.449,28.2268],"type":"Point"}
}