{
  "type": "Feature",
  "properties": {
    "gn:admin1_code":"25.0",
    "gn:asciiname":"Lujiaqiu",
    "gn:country_code":"CN",
    "gn:dem":26,
    "gn:feature_class":"P",
    "gn:feature_code":"PPL",
    "gn:name":"Lujiaqiu",
    "gn:population":0,
    "gn:timezone":"Asia/Shanghai",
    "iso:country":"CN",
    "name:zho_x_preferred":[
        "\u9c81\u5bb6\u4e18"
    ],
    "wof:name":"Lujiaqiu",
    "wof:placetype":"locality"
},
  "geometry": {"coordinates":[120.11968,36.64153],"type":"Point"}
}