{
  "type": "Feature",
  "properties": {
    "gn:admin1_code":"24",
    "gn:asciiname":"Shiliang",
    "gn:cc2":"CN",
    "gn:country_code":"CN",
    "gn:dem":710,
    "gn:feature_class":"P",
    "gn:feature_code":"PPL",
    "gn:name":"Shiliang",
    "gn:population":0,
    "gn:timezone":"Asia/Shanghai",
    "iso:country":"CN",
    "name:und_x_variant":[
        "Shih-liang",
        "Shih-liang-ts\u2019un",
        "Shiliang"
    ],
    "wof:name":"Shiliang",
    "wof:placetype":"locality"
},
  "geometry": {"coordinates":[113.30861000000002,36.45417],"type":"Point"}
}