{
  "type": "Feature",
  "properties": {
    "gn:admin1_code":"4.0",
    "gn:asciiname":"Zhengdongcun",
    "gn:country_code":"CN",
    "gn:dem":-1,
    "gn:feature_class":"P",
    "gn:feature_code":"PPL",
    "gn:name":"Zhengdongcun",
    "gn:population":0,
    "gn:timezone":"Asia/Shanghai",
    "iso:country":"CN",
    "name:zho_x_preferred":[
        "\u6b63\u4e1c\u6751"
    ],
    "wof:name":"Zhengdongcun",
    "wof:placetype":"locality"
},
  "geometry": {"coordinates":[120.12567,33.49268],"type":"Point"}
}