{
  "type": "Feature",
  "properties": {
    "gn:admin1_code":"33.0",
    "gn:asciiname":"Lanchong",
    "gn:country_code":"CN",
    "gn:dem":718,
    "gn:feature_class":"P",
    "gn:feature_code":"PPL",
    "gn:name":"Lanchong",
    "gn:population":0,
    "gn:timezone":"Asia/Shanghai",
    "iso:country":"CN",
    "name:zho_x_preferred":[
        "\u5170\u51b2"
    ],
    "wof:name":"Lanchong",
    "wof:placetype":"locality"
},
  "geometry": {"coordinates":[107.73583000000001,30.53279],"type":"Point"}
}