{
  "type": "Feature",
  "properties": {
    "gn:admin1_code":"15.0",
    "gn:asciiname":"Maotiaojing",
    "gn:country_code":"CN",
    "gn:dem":1348,
    "gn:feature_class":"P",
    "gn:feature_code":"PPL",
    "gn:name":"Maotiaojing",
    "gn:population":0,
    "gn:timezone":"Asia/Shanghai",
    "iso:country":"CN",
    "name:zho_x_preferred":[
        "\u6bdb\u6761\u4e95"
    ],
    "wof:name":"Maotiaojing",
    "wof:placetype":"locality"
},
  "geometry": {"coordinates":[103.85899999999999,38.6471],"type":"Point"}
}