{
  "type": "Feature",
  "properties": {
    "gn:admin1_code":"12.0",
    "gn:asciiname":"Zhujia Laowan",
    "gn:country_code":"CN",
    "gn:dem":229,
    "gn:feature_class":"P",
    "gn:feature_code":"PPL",
    "gn:name":"Zhujia Laowan",
    "gn:population":0,
    "gn:timezone":"Asia/Shanghai",
    "iso:country":"CN",
    "name:zho_x_preferred":[
        "\u6731\u5bb6\u8001\u5846"
    ],
    "wof:name":"Zhujia Laowan",
    "wof:placetype":"locality"
},
  "geometry": {"coordinates":[113.6328,32.09901],"type":"Point"}
}