{
  "type": "Feature",
  "properties": {
    "gn:admin1_code":"16.0",
    "gn:asciiname":"Dadu",
    "gn:country_code":"CN",
    "gn:dem":610,
    "gn:feature_class":"P",
    "gn:feature_code":"PPL",
    "gn:name":"Dadu",
    "gn:population":0,
    "gn:timezone":"Asia/Shanghai",
    "iso:country":"CN",
    "name:ceb_x_preferred":[
        "Dadu"
    ],
    "name:ces_x_preferred":[
        "Ta-tu"
    ],
    "name:deu_x_preferred":[
        "Dadu"
    ],
    "name:fra_x_preferred":[
        "Dadu"
    ],
    "name:ind_x_preferred":[
        "Dadu"
    ],
    "name:nld_x_preferred":[
        "Dadu"
    ],
    "name:nor_x_preferred":[
        "Dadu"
    ],
    "name:scn_x_preferred":[
        "Dadu"
    ],
    "name:swe_x_preferred":[
        "Dadu"
    ],
    "name:zho_x_preferred":[
        "\u5927\u7b03"
    ],
    "wof:name":"Dadu",
    "wof:placetype":"locality"
},
  "geometry": {"coordinates":[106.467,22.9386],"type":"Point"}
}