{
  "type": "Feature",
  "properties": {
    "gn:admin1_code":"8.0",
    "gn:asciiname":"Tonghecun",
    "gn:country_code":"CN",
    "gn:dem":188,
    "gn:feature_class":"P",
    "gn:feature_code":"PPL",
    "gn:name":"Tonghecun",
    "gn:population":0,
    "gn:timezone":"Asia/Shanghai",
    "iso:country":"CN",
    "name:zho_x_preferred":[
        "\u901a\u6cb3\u6751"
    ],
    "wof:name":"Tonghecun",
    "wof:placetype":"locality"
},
  "geometry": {"coordinates":[126.54243999999998,47.6082],"type":"Point"}
}