{
  "type": "Feature",
  "properties": {
    "gn:admin1_code":"30.0",
    "gn:asciiname":"Xiaoshashui",
    "gn:country_code":"CN",
    "gn:dem":409,
    "gn:feature_class":"P",
    "gn:feature_code":"PPL",
    "gn:name":"Xiaoshashui",
    "gn:population":0,
    "gn:timezone":"Asia/Shanghai",
    "iso:country":"CN",
    "name:zho_x_preferred":[
        "Xiaoshashui"
    ],
    "name:zho_x_variant":[
        "\u785d\u6c99\u6c34"
    ],
    "wof:name":"Xiaoshashui",
    "wof:placetype":"locality"
},
  "geometry": {"coordinates":[115.31471999999999,24.73139],"type":"Point"}
}