{
  "type": "Feature",
  "properties": {
    "gn:admin1_code":"20",
    "gn:asciiname":"Huang-yang-t'an",
    "gn:country_code":"CN",
    "gn:dem":1431,
    "gn:feature_class":"P",
    "gn:feature_code":"PPL",
    "gn:name":"Huang-yang-t\u2019an",
    "gn:population":0,
    "gn:timezone":"Asia/Shanghai",
    "iso:country":"CN",
    "wof:name":"Huang-yang-t'an",
    "wof:placetype":"locality"
},
  "geometry": {"coordinates":[116.00444,41.90333],"type":"Point"}
}