{
  "type": "Feature",
  "properties": {
    "gn:admin1_code":"4.0",
    "gn:asciiname":"Shachi",
    "gn:country_code":"CN",
    "gn:dem":9,
    "gn:feature_class":"P",
    "gn:feature_code":"PPL",
    "gn:name":"Shachi",
    "gn:population":0,
    "gn:timezone":"Asia/Shanghai",
    "iso:country":"CN",
    "name:ben_x_preferred":[
        "\u09b6\u099a\u09c0"
    ],
    "name:ces_x_preferred":[
        "\u0160a\u010d\u00ed"
    ],
    "name:hin_x_preferred":[
        "\u0936\u091a\u0940"
    ],
    "name:hrv_x_preferred":[
        "Shachi"
    ],
    "name:ind_x_preferred":[
        "Saci"
    ],
    "name:jpn_x_preferred":[
        "\u30b7\u30e3\u30c1\u30fc"
    ],
    "name:kan_x_preferred":[
        "\u0c87\u0c82\u0ca6\u0ccd\u0cb0\u0cbe\u0ca3\u0cbf"
    ],
    "name:mar_x_preferred":[
        "\u0907\u0902\u0926\u094d\u0930\u093e\u0923\u0940"
    ],
    "name:nep_x_preferred":[
        "\u0936\u091a\u0940"
    ],
    "name:nld_x_preferred":[
        "Sachi"
    ],
    "name:pan_x_preferred":[
        "\u0a38\u0a3c\u0a1a\u0a40"
    ],
    "name:rus_x_preferred":[
        "\u0428\u0430\u0447\u0438"
    ],
    "name:san_x_preferred":[
        "\u0936\u091a\u0940"
    ],
    "name:sin_x_preferred":[
        "\u0dc1\u0da0\u0dd3"
    ],
    "name:swe_x_preferred":[
        "Indrani"
    ],
    "name:tam_x_preferred":[
        "\u0b87\u0ba8\u0bcd\u0ba4\u0bbf\u0bb0\u0bbe\u0ba3\u0bbf"
    ],
    "name:zho_x_preferred":[
        "\u6c99\u6c60"
    ],
    "wof:name":"Shachi",
    "wof:placetype":"locality"
},
  "geometry": {"coordinates":[119.22425,32.17182],"type":"Point"}
}