{
  "type": "Feature",
  "properties": {
    "gn:admin1_code":"12.0",
    "gn:asciiname":"Nianyudi",
    "gn:country_code":"CN",
    "gn:dem":286,
    "gn:feature_class":"P",
    "gn:feature_code":"PPL",
    "gn:name":"Nianyudi",
    "gn:population":0,
    "gn:timezone":"Asia/Shanghai",
    "iso:country":"CN",
    "name:zho_x_preferred":[
        "\u9c87\u9c7c\u5730"
    ],
    "wof:name":"Nianyudi",
    "wof:placetype":"locality"
},
  "geometry": {"coordinates":[115.63239,30.48808],"type":"Point"}
}