{
  "type": "Feature",
  "properties": {
    "gn:admin1_code":"26.0",
    "gn:asciiname":"Lichuangou",
    "gn:country_code":"CN",
    "gn:dem":946,
    "gn:feature_class":"P",
    "gn:feature_code":"PPL",
    "gn:name":"Lichuangou",
    "gn:population":0,
    "gn:timezone":"Asia/Shanghai",
    "iso:country":"CN",
    "name:und_x_variant":[
        "\u7acb\u8239\u6c9f"
    ],
    "wof:name":"Lichuangou",
    "wof:placetype":"locality"
},
  "geometry": {"coordinates":[108.08599,33.37908],"type":"Point"}
}