{
  "type": "Feature",
  "properties": {
    "gn:admin1_code":"5.0",
    "gn:asciiname":"Guangxingdang",
    "gn:country_code":"CN",
    "gn:dem":191,
    "gn:feature_class":"P",
    "gn:feature_code":"PPL",
    "gn:name":"Guangxingdang",
    "gn:population":0,
    "gn:timezone":"Asia/Shanghai",
    "iso:country":"CN",
    "name:zho_x_preferred":[
        "\u5e7f\u5174\u5f53"
    ],
    "wof:name":"Guangxingdang",
    "wof:placetype":"locality"
},
  "geometry": {"coordinates":[126.13612000000001,44.50993],"type":"Point"}
}