{
  "type": "Feature",
  "properties": {
    "gn:admin1_code":"12.0",
    "gn:asciiname":"Tuanbao",
    "gn:country_code":"CN",
    "gn:dem":708,
    "gn:feature_class":"P",
    "gn:feature_code":"PPL",
    "gn:name":"Tuanbao",
    "gn:population":0,
    "gn:timezone":"Asia/Shanghai",
    "iso:country":"CN",
    "name:zho_x_preferred":[
        "\u56e2\u5305"
    ],
    "wof:name":"Tuanbao",
    "wof:placetype":"locality"
},
  "geometry": {"coordinates":[111.10034,31.07652],"type":"Point"}
}