{
  "type": "Feature",
  "properties": {
    "gn:country":"CN",
    "gn:fcode":"PPL",
    "gn:population":896,
    "iso:country":"CN",
    "name:ceb_x_preferred":[
        "Dongshigu"
    ],
    "name:swe_x_preferred":[
        "Dongshigu"
    ],
    "name:zho_x_preferred":[
        "\u4e1c\u5e08\u53e4\u6751"
    ],
    "qs:name":"Dongshigu",
    "qs:photos_9r":0,
    "qs:photos_sr":0,
    "qs:pop_sr":"2",
    "wof:name":"Dongshigu",
    "wof:placetype":"locality",
    "wof:population":896
},
  "geometry": {"coordinates":[117.33028,39.87889],"type":"Point"}
}