{
  "type": "Feature",
  "properties": {
    "gn:admin1_code":"32.0",
    "gn:asciiname":"Qinjia Yuanzi",
    "gn:country_code":"CN",
    "gn:dem":454,
    "gn:feature_class":"P",
    "gn:feature_code":"PPL",
    "gn:name":"Qinjia Yuanzi",
    "gn:population":0,
    "gn:timezone":"Asia/Shanghai",
    "iso:country":"CN",
    "name:zho_x_preferred":[
        "\u79e6\u5bb6\u9662\u5b50"
    ],
    "wof:name":"Qinjia Yuanzi",
    "wof:placetype":"locality"
},
  "geometry": {"coordinates":[104.39275000000001,30.95396],"type":"Point"}
}