{
  "type": "Feature",
  "properties": {
    "gn:admin1_code":"6.0",
    "gn:asciiname":"Chuxi",
    "gn:country_code":"CN",
    "gn:dem":4696,
    "gn:feature_class":"P",
    "gn:feature_code":"PPL",
    "gn:name":"Chuxi",
    "gn:population":0,
    "gn:timezone":"Asia/Urumqi",
    "iso:country":"CN",
    "wof:name":"Chuxi",
    "wof:placetype":"locality"
},
  "geometry": {"coordinates":[92.56667,33.83333],"type":"Point"}
}