{
  "type": "Feature",
  "properties": {
    "gn:admin1_code":"32.0",
    "gn:asciiname":"Guihua Wuji",
    "gn:country_code":"CN",
    "gn:dem":691,
    "gn:feature_class":"P",
    "gn:feature_code":"PPL",
    "gn:name":"Guihua Wuji",
    "gn:population":0,
    "gn:timezone":"Asia/Shanghai",
    "iso:country":"CN",
    "name:zho_x_preferred":[
        "\u6842\u82b1\u5c4b\u57fa"
    ],
    "wof:name":"Guihua Wuji",
    "wof:placetype":"locality"
},
  "geometry": {"coordinates":[105.43640000000001,28.45061],"type":"Point"}
}