{
  "type": "Feature",
  "properties": {
    "gn:admin1_code":"8.0",
    "gn:asciiname":"Fenglianguitun",
    "gn:country_code":"CN",
    "gn:dem":146,
    "gn:feature_class":"P",
    "gn:feature_code":"PPL",
    "gn:name":"Fenglianguitun",
    "gn:population":0,
    "gn:timezone":"Asia/Shanghai",
    "iso:country":"CN",
    "name:zho_x_preferred":[
        "\u51af\u8fde\u8d35\u5c6f"
    ],
    "wof:name":"Fenglianguitun",
    "wof:placetype":"locality"
},
  "geometry": {"coordinates":[125.15922999999999,46.36401],"type":"Point"}
}