{
  "type": "Feature",
  "properties": {
    "gn:admin1_code":"19.0",
    "gn:asciiname":"Anzigou",
    "gn:country_code":"CN",
    "gn:dem":48,
    "gn:feature_class":"P",
    "gn:feature_code":"PPL",
    "gn:name":"Anzigou",
    "gn:population":0,
    "gn:timezone":"Asia/Shanghai",
    "iso:country":"CN",
    "name:zho_x_preferred":[
        "\u978d\u5b50\u6c9f"
    ],
    "wof:name":"Anzigou",
    "wof:placetype":"locality"
},
  "geometry": {"coordinates":[124.39100000000001,40.3353],"type":"Point"}
}