{
  "type": "Feature",
  "properties": {
    "gn:admin1_code":"10",
    "gn:asciiname":"Sibozi",
    "gn:country_code":"CN",
    "gn:dem":360,
    "gn:feature_class":"P",
    "gn:feature_code":"PPL",
    "gn:name":"Sibozi",
    "gn:population":0,
    "gn:timezone":"Asia/Shanghai",
    "iso:country":"CN",
    "name:zho_x_preferred":[
        "\u56db\u62e8\u5b50"
    ],
    "wof:name":"Sibozi",
    "wof:placetype":"locality"
},
  "geometry": {"coordinates":[117.56964000000001,40.24935],"type":"Point"}
}