{
  "type": "Feature",
  "properties": {
    "gn:admin1_code":"11.0",
    "gn:asciiname":"Gaoziling",
    "gn:country_code":"CN",
    "gn:dem":100,
    "gn:feature_class":"P",
    "gn:feature_code":"PPL",
    "gn:name":"Gaoziling",
    "gn:population":0,
    "gn:timezone":"Asia/Shanghai",
    "iso:country":"CN",
    "name:zho_x_preferred":[
        "\u9ad8\u5b50\u5cad"
    ],
    "wof:name":"Gaoziling",
    "wof:placetype":"locality"
},
  "geometry": {"coordinates":[113.41674999999999,27.06774],"type":"Point"}
}