{
  "type": "Feature",
  "properties": {
    "gn:admin1_code":"16",
    "gn:asciiname":"Guban",
    "gn:country_code":"CN",
    "gn:dem":264,
    "gn:feature_class":"P",
    "gn:feature_code":"PPL",
    "gn:name":"Guban",
    "gn:population":0,
    "gn:timezone":"Asia/Shanghai",
    "iso:country":"CN",
    "name:deu_x_preferred":[
        "Guban"
    ],
    "name:som_x_preferred":[
        "Guban"
    ],
    "name:zho_x_preferred":[
        "\u53e4\u677f"
    ],
    "wof:name":"Guban",
    "wof:placetype":"locality"
},
  "geometry": {"coordinates":[110.44799999999999,24.8569],"type":"Point"}
}