{
  "type": "Feature",
  "properties": {
    "gn:admin1_code":"11.0",
    "gn:asciiname":"Daniao'ao",
    "gn:country_code":"CN",
    "gn:dem":767,
    "gn:feature_class":"P",
    "gn:feature_code":"PPL",
    "gn:name":"Daniao\u2019ao",
    "gn:population":0,
    "gn:timezone":"Asia/Shanghai",
    "iso:country":"CN",
    "name:und_x_variant":[
        "Daniao\u2019ao"
    ],
    "name:zho_x_preferred":[
        "\u6253\u9e1f\u5773"
    ],
    "wof:name":"Daniao'ao",
    "wof:placetype":"locality"
},
  "geometry": {"coordinates":[110.82495,27.45229],"type":"Point"}
}