{
  "type": "Feature",
  "properties": {
    "gn:admin1_code":"12.0",
    "gn:asciiname":"Yanjia'ao",
    "gn:country_code":"CN",
    "gn:dem":160,
    "gn:feature_class":"P",
    "gn:feature_code":"PPL",
    "gn:name":"Yanjia\u2019ao",
    "gn:population":0,
    "gn:timezone":"Asia/Shanghai",
    "iso:country":"CN",
    "name:zho_x_preferred":[
        "Yanjia\u2019ao"
    ],
    "name:zho_x_variant":[
        "\u4e25\u5bb6\u5773"
    ],
    "wof:name":"Yanjia'ao",
    "wof:placetype":"locality"
},
  "geometry": {"coordinates":[113.23473,31.35014],"type":"Point"}
}