{
  "type": "Feature",
  "properties": {
    "gn:admin1_code":"29.0",
    "gn:asciiname":"Yaoxiangzha",
    "gn:country_code":"CN",
    "gn:dem":2381,
    "gn:feature_class":"P",
    "gn:feature_code":"PPL",
    "gn:name":"Yaoxiangzha",
    "gn:population":0,
    "gn:timezone":"Asia/Shanghai",
    "iso:country":"CN",
    "name:und_x_variant":[
        "Mexiangzha"
    ],
    "name:zho_x_preferred":[
        "\u4e48\u54cd\u4e4d"
    ],
    "wof:name":"Yaoxiangzha",
    "wof:placetype":"locality"
},
  "geometry": {"coordinates":[101.32899999999999,26.0332],"type":"Point"}
}