{
  "type": "Feature",
  "properties": {
    "gn:admin1_code":"11.0",
    "gn:asciiname":"Sifenchang Yidui",
    "gn:country_code":"CN",
    "gn:dem":30,
    "gn:feature_class":"P",
    "gn:feature_code":"PPLF",
    "gn:name":"Sifenchang Yidui",
    "gn:population":0,
    "gn:timezone":"Asia/Shanghai",
    "iso:country":"CN",
    "name:zho_x_preferred":[
        "\u56db\u5206\u573a\u4e00\u961f"
    ],
    "wof:name":"Sifenchang Yidui",
    "wof:placetype":"locality"
},
  "geometry": {"coordinates":[112.6465,29.14329],"type":"Point"}
}