{
  "type": "Feature",
  "properties": {
    "gn:admin1_code":"11",
    "gn:asciiname":"Maluodai",
    "gn:country_code":"CN",
    "gn:dem":402,
    "gn:feature_class":"P",
    "gn:feature_code":"PPL",
    "gn:name":"Maluodai",
    "gn:population":0,
    "gn:timezone":"Asia/Shanghai",
    "iso:country":"CN",
    "name:zho_x_preferred":[
        "\u9a6c\u7f57\u5e26"
    ],
    "wof:name":"Maluodai",
    "wof:placetype":"locality"
},
  "geometry": {"coordinates":[112.15967000000001,25.31278],"type":"Point"}
}