{
  "type": "Feature",
  "properties": {
    "gn:admin1_code":"9.0",
    "gn:asciiname":"Shangguangang",
    "gn:country_code":"CN",
    "gn:dem":71,
    "gn:feature_class":"P",
    "gn:feature_code":"PPL",
    "gn:name":"Shangguangang",
    "gn:population":0,
    "gn:timezone":"Asia/Shanghai",
    "iso:country":"CN",
    "name:zho_x_preferred":[
        "\u4e0a\u5b98\u5c97"
    ],
    "wof:name":"Shangguangang",
    "wof:placetype":"locality"
},
  "geometry": {"coordinates":[114.86991,32.01984],"type":"Point"}
}