{
  "type": "Feature",
  "properties": {
    "gn:admin1_code":"32.0",
    "gn:asciiname":"Duiwojing",
    "gn:country_code":"CN",
    "gn:dem":421,
    "gn:feature_class":"P",
    "gn:feature_code":"PPL",
    "gn:name":"Duiwojing",
    "gn:population":0,
    "gn:timezone":"Asia/Shanghai",
    "iso:country":"CN",
    "name:zho_x_preferred":[
        "\u5bf9\u7a9d\u4e95"
    ],
    "wof:name":"Duiwojing",
    "wof:placetype":"locality"
},
  "geometry": {"coordinates":[104.261,30.1905],"type":"Point"}
}