{
  "type": "Feature",
  "properties": {
    "gn:admin1_code":"19.0",
    "gn:asciiname":"Xujiacun",
    "gn:country_code":"CN",
    "gn:dem":148,
    "gn:feature_class":"P",
    "gn:feature_code":"PPL",
    "gn:name":"Xujiacun",
    "gn:population":0,
    "gn:timezone":"Asia/Shanghai",
    "iso:country":"CN",
    "name:zho_x_preferred":[
        "\u8bb8\u5bb6\u6751"
    ],
    "wof:name":"Xujiacun",
    "wof:placetype":"locality"
},
  "geometry": {"coordinates":[124.15600000000001,42.99166],"type":"Point"}
}