{
  "type": "Feature",
  "properties": {
    "gn:admin1_code":"11.0",
    "gn:asciiname":"Wanrongjiang",
    "gn:country_code":"CN",
    "gn:dem":346,
    "gn:feature_class":"P",
    "gn:feature_code":"PPL",
    "gn:name":"Wanrongjiang",
    "gn:population":0,
    "gn:timezone":"Asia/Shanghai",
    "iso:country":"CN",
    "name:zho_x_preferred":[
        "\u4e07\u6eb6\u6c5f"
    ],
    "wof:name":"Wanrongjiang",
    "wof:placetype":"locality"
},
  "geometry": {"coordinates":[109.56274999999999,28.10085],"type":"Point"}
}