{
  "type": "Feature",
  "properties": {
    "gn:admin1_code":"1.0",
    "gn:asciiname":"Gaohu",
    "gn:country_code":"CN",
    "gn:dem":36,
    "gn:feature_class":"P",
    "gn:feature_code":"PPL",
    "gn:name":"Gaohu",
    "gn:population":0,
    "gn:timezone":"Asia/Shanghai",
    "iso:country":"CN",
    "name:ara_x_preferred":[
        "\u0642\u0627\u0648 \u0647\u0648"
    ],
    "name:epo_x_preferred":[
        "Ga\u016dhuo"
    ],
    "name:fra_x_preferred":[
        "Gaohu"
    ],
    "name:hun_x_preferred":[
        "Kao-hu"
    ],
    "name:hye_x_preferred":[
        "\u0533\u0561\u0578\u0570\u0578\u0582"
    ],
    "name:ind_x_preferred":[
        "Gaohu"
    ],
    "name:und_x_variant":[
        "\u9ad8\u6e56"
    ],
    "wof:name":"Gaohu",
    "wof:placetype":"locality"
},
  "geometry": {"coordinates":[119.41651,30.95567],"type":"Point"}
}