{
  "type": "Feature",
  "properties": {
    "gn:admin1_code":"21.0",
    "gn:asciiname":"Lijia Dazhuang",
    "gn:country_code":"CN",
    "gn:dem":1453,
    "gn:feature_class":"P",
    "gn:feature_code":"PPL",
    "gn:name":"Lijia Dazhuang",
    "gn:population":0,
    "gn:timezone":"Asia/Shanghai",
    "iso:country":"CN",
    "name:zho_x_preferred":[
        "\u674e\u5bb6\u5927\u5e84"
    ],
    "wof:name":"Lijia Dazhuang",
    "wof:placetype":"locality"
},
  "geometry": {"coordinates":[106.753,37.3066],"type":"Point"}
}