{
  "type": "Feature",
  "properties": {
    "gn:admin1_code":"3.0",
    "gn:asciiname":"Lilin Pengjia",
    "gn:country_code":"CN",
    "gn:dem":32,
    "gn:feature_class":"P",
    "gn:feature_code":"PPL",
    "gn:name":"Lilin Pengjia",
    "gn:population":0,
    "gn:timezone":"Asia/Shanghai",
    "iso:country":"CN",
    "name:und_x_variant":[
        "\u6817\u6797\u5f6d\u5bb6"
    ],
    "wof:name":"Lilin Pengjia",
    "wof:placetype":"locality"
},
  "geometry": {"coordinates":[115.3115,28.1354],"type":"Point"}
}