{
  "type": "Feature",
  "properties": {
    "gn:admin1_code":"8.0",
    "gn:asciiname":"Sanxingtun",
    "gn:country_code":"CN",
    "gn:dem":180,
    "gn:feature_class":"P",
    "gn:feature_code":"PPL",
    "gn:name":"Sanxingtun",
    "gn:population":0,
    "gn:timezone":"Asia/Shanghai",
    "iso:country":"CN",
    "name:zho_x_preferred":[
        "\u4e09\u661f\u5c6f"
    ],
    "wof:name":"Sanxingtun",
    "wof:placetype":"locality"
},
  "geometry": {"coordinates":[126.30533,45.43595],"type":"Point"}
}