{
  "type": "Feature",
  "properties": {
    "gn:admin1_code":"3",
    "gn:asciiname":"Wunitang",
    "gn:country_code":"CN",
    "gn:dem":217,
    "gn:feature_class":"P",
    "gn:feature_code":"PPL",
    "gn:name":"Wunitang",
    "gn:population":0,
    "gn:timezone":"Asia/Shanghai",
    "iso:country":"CN",
    "name:zho_x_preferred":[
        "\u4e4c\u6ce5\u5858"
    ],
    "wof:name":"Wunitang",
    "wof:placetype":"locality"
},
  "geometry": {"coordinates":[114.184,26.8541],"type":"Point"}
}