{
  "type": "Feature",
  "properties": {
    "gn:admin1_code":"7.0",
    "gn:asciiname":"Xieji",
    "gn:country_code":"CN",
    "gn:dem":426,
    "gn:feature_class":"P",
    "gn:feature_code":"PPL",
    "gn:name":"Xieji",
    "gn:population":0,
    "gn:timezone":"Asia/Shanghai",
    "iso:country":"CN",
    "name:und_x_variant":[
        "\u8c22\u9645"
    ],
    "name:zho_x_preferred":[
        "\u8c22\u9645"
    ],
    "wof:name":"Xieji",
    "wof:placetype":"locality"
},
  "geometry": {"coordinates":[117.87806,26.96106],"type":"Point"}
}