{
  "type": "Feature",
  "properties": {
    "gn:admin1_code":"7",
    "gn:asciiname":"Liuyang",
    "gn:country_code":"CN",
    "gn:dem":572,
    "gn:feature_class":"P",
    "gn:feature_code":"PPL",
    "gn:name":"Liuyang",
    "gn:population":0,
    "gn:timezone":"Asia/Shanghai",
    "iso:country":"CN",
    "name:ceb_x_preferred":[
        "Liuyang Shi"
    ],
    "name:deu_x_preferred":[
        "Liuyang"
    ],
    "name:eus_x_preferred":[
        "Liuyang"
    ],
    "name:fra_x_preferred":[
        "Liuyang"
    ],
    "name:hak_x_preferred":[
        "Li\u00f9-y\u00f2ng-s\u1e73"
    ],
    "name:ita_x_preferred":[
        "Liuyang"
    ],
    "name:jpn_x_preferred":[
        "\u700f\u967d\u5e02"
    ],
    "name:kik_x_preferred":[
        "Liuyang"
    ],
    "name:kor_x_preferred":[
        "\ub958\uc591\uc2dc"
    ],
    "name:mlg_x_preferred":[
        "Liuyang"
    ],
    "name:nld_x_preferred":[
        "Liuyang"
    ],
    "name:nor_x_preferred":[
        "Liuyang"
    ],
    "name:pam_x_preferred":[
        "Liuyang"
    ],
    "name:spa_x_preferred":[
        "Liuyang"
    ],
    "name:swe_x_preferred":[
        "Liuyang"
    ],
    "name:und_x_variant":[
        "\u5218\u6d0b",
        "Liuyang"
    ],
    "name:vie_x_preferred":[
        "L\u01b0u D\u01b0\u01a1ng"
    ],
    "name:wuu_x_preferred":[
        "\u6d4f\u9633\u5e02"
    ],
    "name:zho_x_preferred":[
        "\u6d4f\u9633\u5e02"
    ],
    "wof:name":"Liuyang",
    "wof:placetype":"locality"
},
  "geometry": {"coordinates":[119.98044,27.28461],"type":"Point"}
}