{
  "type": "Feature",
  "properties": {
    "gn:admin1_code":"29.0",
    "gn:asciiname":"Lishu",
    "gn:country_code":"CN",
    "gn:dem":1174,
    "gn:feature_class":"P",
    "gn:feature_code":"PPL",
    "gn:name":"Lishu",
    "gn:population":0,
    "gn:timezone":"Asia/Shanghai",
    "iso:country":"CN",
    "name:und_x_variant":[
        "\u68a8\u6811"
    ],
    "wof:name":"Lishu",
    "wof:placetype":"locality"
},
  "geometry": {"coordinates":[102.99299999999999,26.81],"type":"Point"}
}