{
  "type": "Feature",
  "properties": {
    "gn:admin1_code":"2.0",
    "gn:asciiname":"Taojinqiao",
    "gn:country_code":"CN",
    "gn:dem":9,
    "gn:feature_class":"P",
    "gn:feature_code":"PPL",
    "gn:name":"Taojinqiao",
    "gn:population":0,
    "gn:timezone":"Asia/Shanghai",
    "iso:country":"CN",
    "name:und_x_variant":[
        "\u6dd8\u91d1\u6865"
    ],
    "wof:name":"Taojinqiao",
    "wof:placetype":"locality"
},
  "geometry": {"coordinates":[120.75855,30.60922],"type":"Point"}
}