{
  "type": "Feature",
  "properties": {
    "gn:admin1_code":"30.0",
    "gn:asciiname":"Jianxia",
    "gn:country_code":"CN",
    "gn:dem":110,
    "gn:feature_class":"P",
    "gn:feature_code":"PPL",
    "gn:name":"Jianxia",
    "gn:population":0,
    "gn:timezone":"Asia/Shanghai",
    "iso:country":"CN",
    "name:zho_x_preferred":[
        "Jianxia"
    ],
    "name:zho_x_variant":[
        "\u6da7\u4e0b"
    ],
    "wof:name":"Jianxia",
    "wof:placetype":"locality"
},
  "geometry": {"coordinates":[115.29306,24.10583],"type":"Point"}
}