{
  "type": "Feature",
  "properties": {
    "gn:admin1_code":"25",
    "gn:asciiname":"Lishantun",
    "gn:country_code":"CN",
    "gn:dem":31,
    "gn:feature_class":"P",
    "gn:feature_code":"PPL",
    "gn:name":"Lishantun",
    "gn:population":0,
    "gn:timezone":"Asia/Shanghai",
    "iso:country":"CN",
    "name:zho_x_preferred":[
        "\u674e\u5584\u5c6f"
    ],
    "wof:name":"Lishantun",
    "wof:placetype":"locality"
},
  "geometry": {"coordinates":[116.212,37.1886],"type":"Point"}
}