{
  "type": "Feature",
  "properties": {
    "gn:admin1_code":"19.0",
    "gn:asciiname":"Yaodongzi",
    "gn:country_code":"CN",
    "gn:dem":359,
    "gn:feature_class":"P",
    "gn:feature_code":"PPL",
    "gn:name":"Yaodongzi",
    "gn:population":0,
    "gn:timezone":"Asia/Shanghai",
    "iso:country":"CN",
    "name:zho_x_preferred":[
        "\u7a91\u6d1e\u5b50"
    ],
    "wof:name":"Yaodongzi",
    "wof:placetype":"locality"
},
  "geometry": {"coordinates":[119.88994,41.07263],"type":"Point"}
}