{
  "type": "Feature",
  "properties": {
    "gn:admin1_code":"26.0",
    "gn:asciiname":"Erlintu",
    "gn:country_code":"CN",
    "gn:dem":1221,
    "gn:feature_class":"P",
    "gn:feature_code":"PPL",
    "gn:name":"Erlintu",
    "gn:population":0,
    "gn:timezone":"Asia/Shanghai",
    "iso:country":"CN",
    "name:zho_x_preferred":[
        "\u5c14\u6797\u5154"
    ],
    "wof:name":"Erlintu",
    "wof:placetype":"locality"
},
  "geometry": {"coordinates":[110.25524,39.08206],"type":"Point"}
}