{
  "type": "Feature",
  "properties": {
    "gn:admin1_code":"15.0",
    "gn:asciiname":"Houjiatang",
    "gn:country_code":"CN",
    "gn:dem":2055,
    "gn:feature_class":"P",
    "gn:feature_code":"PPL",
    "gn:name":"Houjiatang",
    "gn:population":0,
    "gn:timezone":"Asia/Shanghai",
    "iso:country":"CN",
    "name:zho_x_preferred":[
        "\u540e\u6d43\u5858"
    ],
    "wof:name":"Houjiatang",
    "wof:placetype":"locality"
},
  "geometry": {"coordinates":[103.06100000000001,35.5006],"type":"Point"}
}