{
  "type": "Feature",
  "properties": {
    "gn:admin1_code":"19.0",
    "gn:asciiname":"Zao'er Shanqian",
    "gn:country_code":"CN",
    "gn:dem":7,
    "gn:feature_class":"P",
    "gn:feature_code":"PPL",
    "gn:name":"Zao\u2019er Shanqian",
    "gn:population":0,
    "gn:timezone":"Asia/Shanghai",
    "iso:country":"CN",
    "name:und_x_variant":[
        "Zao\u2019er Shanqian"
    ],
    "name:zho_x_preferred":[
        "\u67a3\u513f\u5c71\u524d"
    ],
    "wof:name":"Zao'er Shanqian",
    "wof:placetype":"locality"
},
  "geometry": {"coordinates":[123.81569,39.86344],"type":"Point"}
}