{
  "type": "Feature",
  "properties": {
    "gn:admin1_code":"3.0",
    "gn:asciiname":"Xiaxingli",
    "gn:country_code":"CN",
    "gn:dem":182,
    "gn:feature_class":"P",
    "gn:feature_code":"PPL",
    "gn:name":"Xiaxingli",
    "gn:population":0,
    "gn:timezone":"Asia/Shanghai",
    "iso:country":"CN",
    "name:und_x_variant":[
        "\u867e\u5f62\u91cc"
    ],
    "wof:name":"Xiaxingli",
    "wof:placetype":"locality"
},
  "geometry": {"coordinates":[114.99254000000001,28.64468],"type":"Point"}
}