{
  "type": "Feature",
  "properties": {
    "gn:admin1_code":"25.0",
    "gn:asciiname":"Xinzhuangtoucun",
    "gn:country_code":"CN",
    "gn:dem":71,
    "gn:feature_class":"P",
    "gn:feature_code":"PPL",
    "gn:name":"Xinzhuangtoucun",
    "gn:population":0,
    "gn:timezone":"Asia/Shanghai",
    "iso:country":"CN",
    "name:zho_x_preferred":[
        "\u8f9b\u5e84\u5934\u6751"
    ],
    "wof:name":"Xinzhuangtoucun",
    "wof:placetype":"locality"
},
  "geometry": {"coordinates":[122.18420999999999,37.19881],"type":"Point"}
}