{
  "type": "Feature",
  "properties": {
    "gn:admin1_code":"10.0",
    "gn:asciiname":"Dachaizhuang",
    "gn:country_code":"CN",
    "gn:dem":13,
    "gn:feature_class":"P",
    "gn:feature_code":"PPL",
    "gn:name":"Dachaizhuang",
    "gn:population":0,
    "gn:timezone":"Asia/Shanghai",
    "iso:country":"CN",
    "name:zho_x_preferred":[
        "\u5927\u67f4\u5e84"
    ],
    "wof:name":"Dachaizhuang",
    "wof:placetype":"locality"
},
  "geometry": {"coordinates":[116.6429,37.95931],"type":"Point"}
}