{
  "type": "Feature",
  "properties": {
    "gn:admin1_code":"3.0",
    "gn:asciiname":"Jiuju",
    "gn:country_code":"CN",
    "gn:dem":61,
    "gn:feature_class":"P",
    "gn:feature_code":"PPL",
    "gn:name":"Jiuju",
    "gn:population":0,
    "gn:timezone":"Asia/Shanghai",
    "iso:country":"CN",
    "name:und_x_variant":[
        "\u65e7\u5c45"
    ],
    "wof:name":"Jiuju",
    "wof:placetype":"locality"
},
  "geometry": {"coordinates":[114.79183999999999,27.16469],"type":"Point"}
}