{
  "type": "Feature",
  "properties": {
    "gn:admin1_code":"29.0",
    "gn:asciiname":"Weihei Zhongzhai",
    "gn:country_code":"CN",
    "gn:dem":2055,
    "gn:feature_class":"P",
    "gn:feature_code":"PPL",
    "gn:name":"Weihei Zhongzhai",
    "gn:population":0,
    "gn:timezone":"Asia/Shanghai",
    "iso:country":"CN",
    "name:zho_x_preferred":[
        "\u5a01\u9ed1\u4e2d\u5be8"
    ],
    "wof:name":"Weihei Zhongzhai",
    "wof:placetype":"locality"
},
  "geometry": {"coordinates":[103.569,24.8101],"type":"Point"}
}