{
  "type": "Feature",
  "properties": {
    "gn:admin1_code":"18.0",
    "gn:asciiname":"Baisha",
    "gn:country_code":"CN",
    "gn:dem":731,
    "gn:feature_class":"P",
    "gn:feature_code":"PPL",
    "gn:name":"Baisha",
    "gn:population":0,
    "gn:timezone":"Asia/Shanghai",
    "iso:country":"CN",
    "name:ceb_x_preferred":[
        "Baisha"
    ],
    "name:deu_x_preferred":[
        "Baisha"
    ],
    "name:fra_x_preferred":[
        "Baisha"
    ],
    "name:nld_x_preferred":[
        "Baisha"
    ],
    "name:zho_x_preferred":[
        "\u767d\u6c99"
    ],
    "wof:name":"Baisha",
    "wof:placetype":"locality"
},
  "geometry": {"coordinates":[108.702,26.6328],"type":"Point"}
}