{
  "type": "Feature",
  "properties": {
    "gn:admin1_code":"29.0",
    "gn:asciiname":"Luoduo",
    "gn:country_code":"CN",
    "gn:dem":1513,
    "gn:feature_class":"P",
    "gn:feature_code":"PPL",
    "gn:name":"Luoduo",
    "gn:population":0,
    "gn:timezone":"Asia/Shanghai",
    "iso:country":"CN",
    "name:zho_x_preferred":[
        "\u7f57\u593a"
    ],
    "wof:name":"Luoduo",
    "wof:placetype":"locality"
},
  "geometry": {"coordinates":[99.6473,23.2464],"type":"Point"}
}