{
  "type": "Feature",
  "properties": {
    "gn:admin1_code":"26",
    "gn:asciiname":"Mutouyu",
    "gn:cc2":"CN",
    "gn:country_code":"CN",
    "gn:dem":790,
    "gn:feature_class":"P",
    "gn:feature_code":"PPL",
    "gn:name":"Mutouyu",
    "gn:population":0,
    "gn:timezone":"Asia/Shanghai",
    "iso:country":"CN",
    "name:und_x_variant":[
        "Ta-t\u2019ou-y\u00fc",
        "Shui-t\u2019ou-y\u00fc",
        "Mutouyu"
    ],
    "wof:name":"Mutouyu",
    "wof:placetype":"locality"
},
  "geometry": {"coordinates":[110.55694,37.91972],"type":"Point"}
}