{
  "type": "Feature",
  "properties": {
    "gn:admin1_code":"19.0",
    "gn:asciiname":"Yaosijiazi",
    "gn:country_code":"CN",
    "gn:dem":54,
    "gn:feature_class":"P",
    "gn:feature_code":"PPL",
    "gn:name":"Yaosijiazi",
    "gn:population":0,
    "gn:timezone":"Asia/Shanghai",
    "iso:country":"CN",
    "name:und_x_variant":[
        "\u8170\u56db\u5bb6\u5b50"
    ],
    "name:zho_x_preferred":[
        "\u8170\u56db\u5bb6\u5b50"
    ],
    "wof:name":"Yaosijiazi",
    "wof:placetype":"locality"
},
  "geometry": {"coordinates":[122.48369,42.0922],"type":"Point"}
}