{
  "type": "Feature",
  "properties": {
    "gn:admin1_code":"15.0",
    "gn:asciiname":"Shengli Qidui",
    "gn:country_code":"CN",
    "gn:dem":1594,
    "gn:feature_class":"P",
    "gn:feature_code":"PPLF",
    "gn:name":"Shengli Qidui",
    "gn:population":0,
    "gn:timezone":"Asia/Shanghai",
    "iso:country":"CN",
    "name:zho_x_preferred":[
        "\u80dc\u5229\u4e03\u961f"
    ],
    "wof:name":"Shengli Qidui",
    "wof:placetype":"locality"
},
  "geometry": {"coordinates":[98.2333,39.9109],"type":"Point"}
}