{
  "type": "Feature",
  "properties": {
    "gn:admin1_code":"5.0",
    "gn:asciiname":"Chengdongtun",
    "gn:country_code":"CN",
    "gn:dem":318,
    "gn:feature_class":"P",
    "gn:feature_code":"PPL",
    "gn:name":"Chengdongtun",
    "gn:population":0,
    "gn:timezone":"Asia/Shanghai",
    "iso:country":"CN",
    "name:und_x_variant":[
        "\u57ce\u4e1c\u5c6f"
    ],
    "wof:name":"Chengdongtun",
    "wof:placetype":"locality"
},
  "geometry": {"coordinates":[129.02378999999999,43.02931],"type":"Point"}
}