{
  "type": "Feature",
  "properties": {
    "gn:admin1_code":"30",
    "gn:asciiname":"Lianhua",
    "gn:country_code":"CN",
    "gn:dem":21,
    "gn:feature_class":"P",
    "gn:feature_code":"PPL",
    "gn:name":"Lianhua",
    "gn:population":0,
    "gn:timezone":"Asia/Shanghai",
    "iso:country":"CN",
    "name:und_x_variant":[
        "Lien-hua",
        "Lianhua"
    ],
    "wof:name":"Lianhua",
    "wof:placetype":"locality"
},
  "geometry": {"coordinates":[112.81667,22.51667],"type":"Point"}
}