{
  "type": "Feature",
  "properties": {
    "gn:admin1_code":"2.0",
    "gn:asciiname":"Xitouchen",
    "gn:country_code":"CN",
    "gn:dem":45,
    "gn:feature_class":"P",
    "gn:feature_code":"PPL",
    "gn:name":"Xitouchen",
    "gn:population":0,
    "gn:timezone":"Asia/Shanghai",
    "iso:country":"CN",
    "name:zho_x_preferred":[
        "\u6eaa\u5934\u9648"
    ],
    "wof:name":"Xitouchen",
    "wof:placetype":"locality"
},
  "geometry": {"coordinates":[121.36761,29.29166],"type":"Point"}
}