{
  "type": "Feature",
  "properties": {
    "gn:admin1_code":"4.0",
    "gn:asciiname":"Huanlianggang",
    "gn:country_code":"CN",
    "gn:dem":6,
    "gn:feature_class":"P",
    "gn:feature_code":"PPL",
    "gn:name":"Huanlianggang",
    "gn:population":0,
    "gn:timezone":"Asia/Shanghai",
    "iso:country":"CN",
    "name:und_x_variant":[
        "\u73af\u826f\u6e2f"
    ],
    "name:zho_x_preferred":[
        "\u73af\u826f\u6e2f"
    ],
    "wof:name":"Huanlianggang",
    "wof:placetype":"locality"
},
  "geometry": {"coordinates":[120.47995,31.00625],"type":"Point"}
}