{
  "type": "Feature",
  "properties": {
    "gn:admin1_code":"14.0",
    "gn:asciiname":"Tongzika",
    "gn:country_code":"CN",
    "gn:dem":3183,
    "gn:feature_class":"P",
    "gn:feature_code":"PPL",
    "gn:name":"Tongzika",
    "gn:population":0,
    "gn:timezone":"Asia/Urumqi",
    "iso:country":"CN",
    "name:zho_x_preferred":[
        "\u6850\u5b50\u5361"
    ],
    "wof:name":"Tongzika",
    "wof:placetype":"locality"
},
  "geometry": {"coordinates":[98.88111000000001,29.14237],"type":"Point"}
}