{
  "type": "Feature",
  "properties": {
    "gn:admin1_code":"11.0",
    "gn:asciiname":"Dinghechong",
    "gn:country_code":"CN",
    "gn:dem":366,
    "gn:feature_class":"P",
    "gn:feature_code":"PPL",
    "gn:name":"Dinghechong",
    "gn:population":0,
    "gn:timezone":"Asia/Shanghai",
    "iso:country":"CN",
    "name:zho_x_preferred":[
        "\u5b9a\u6cb3\u51b2"
    ],
    "wof:name":"Dinghechong",
    "wof:placetype":"locality"
},
  "geometry": {"coordinates":[111.27231,27.41593],"type":"Point"}
}