{
  "type": "Feature",
  "properties": {
    "gn:admin1_code":"4.0",
    "gn:asciiname":"Zhongzhai Yicun",
    "gn:country_code":"CN",
    "gn:dem":5,
    "gn:feature_class":"P",
    "gn:feature_code":"PPL",
    "gn:name":"Zhongzhai Yicun",
    "gn:population":0,
    "gn:timezone":"Asia/Shanghai",
    "iso:country":"CN",
    "name:zho_x_preferred":[
        "\u4ef2\u5be8\u4e00\u6751"
    ],
    "wof:name":"Zhongzhai Yicun",
    "wof:placetype":"locality"
},
  "geometry": {"coordinates":[119.68519000000001,33.11236],"type":"Point"}
}