{
  "type": "Feature",
  "properties": {
    "gn:admin1_code":"7.0",
    "gn:asciiname":"Fuqingtian",
    "gn:country_code":"CN",
    "gn:dem":360,
    "gn:feature_class":"P",
    "gn:feature_code":"PPL",
    "gn:name":"Fuqingtian",
    "gn:population":0,
    "gn:timezone":"Asia/Shanghai",
    "iso:country":"CN",
    "name:zho_x_preferred":[
        "\u798f\u9752\u7530"
    ],
    "wof:name":"Fuqingtian",
    "wof:placetype":"locality"
},
  "geometry": {"coordinates":[119.33052000000001,26.39361],"type":"Point"}
}