{
  "type": "Feature",
  "properties": {
    "gn:admin1_code":"26.0",
    "gn:asciiname":"Baixicun",
    "gn:country_code":"CN",
    "gn:dem":895,
    "gn:feature_class":"P",
    "gn:feature_code":"PPL",
    "gn:name":"Baixicun",
    "gn:population":0,
    "gn:timezone":"Asia/Shanghai",
    "iso:country":"CN",
    "name:zho_x_preferred":[
        "\u767d\u6eaa\u6751"
    ],
    "wof:name":"Baixicun",
    "wof:placetype":"locality"
},
  "geometry": {"coordinates":[107.57532,32.48112],"type":"Point"}
}