{
  "type": "Feature",
  "properties": {
    "gn:admin1_code":"9.0",
    "gn:asciiname":"Shiweizi",
    "gn:country_code":"CN",
    "gn:dem":54,
    "gn:feature_class":"P",
    "gn:feature_code":"PPL",
    "gn:name":"Shiweizi",
    "gn:population":0,
    "gn:timezone":"Asia/Shanghai",
    "iso:country":"CN",
    "name:zho_x_preferred":[
        "\u65f6\u56f4\u5b5c"
    ],
    "wof:name":"Shiweizi",
    "wof:placetype":"locality"
},
  "geometry": {"coordinates":[114.79653999999999,32.44829],"type":"Point"}
}