{
  "type": "Feature",
  "properties": {
    "gn:admin1_code":"8.0",
    "gn:asciiname":"Yicuomaogoukou",
    "gn:country_code":"CN",
    "gn:dem":291,
    "gn:feature_class":"P",
    "gn:feature_code":"PPL",
    "gn:name":"Yicuomaogoukou",
    "gn:population":0,
    "gn:timezone":"Asia/Shanghai",
    "iso:country":"CN",
    "name:zho_x_preferred":[
        "\u4e00\u64ae\u6bdb\u6c9f\u53e3"
    ],
    "wof:name":"Yicuomaogoukou",
    "wof:placetype":"locality"
},
  "geometry": {"coordinates":[128.40128999999999,46.92847],"type":"Point"}
}