{
  "type": "Feature",
  "properties": {
    "gn:admin1_code":"08",
    "gn:asciiname":"Bawujiu Nongchang San Fenchang Ershi'er Dui",
    "gn:country_code":"CN",
    "gn:dem":47,
    "gn:feature_class":"P",
    "gn:feature_code":"PPL",
    "gn:name":"Bawujiu Nongchang San Fenchang Ershi\u2019er Dui",
    "gn:population":0,
    "gn:timezone":"Asia/Shanghai",
    "iso:country":"CN",
    "wof:name":"Bawujiu Nongchang San Fenchang Ershi'er Dui",
    "wof:placetype":"locality"
},
  "geometry": {"coordinates":[134.06861000000001,47.53139],"type":"Point"}
}