{
  "type": "Feature",
  "properties": {
    "gn:admin1_code":"14.0",
    "gn:asciiname":"Xangba",
    "gn:country_code":"CN",
    "gn:dem":4357,
    "gn:feature_class":"P",
    "gn:feature_code":"PPL",
    "gn:name":"Xangba",
    "gn:population":0,
    "gn:timezone":"Asia/Shanghai",
    "iso:country":"CN",
    "name:bod_x_preferred":[
        "Xangba"
    ],
    "name:zho_x_preferred":[
        "Xiangba"
    ],
    "name:zho_x_variant":[
        "\u9999\u5df4"
    ],
    "wof:name":"Xangba",
    "wof:placetype":"locality"
},
  "geometry": {"coordinates":[79.7208,31.885],"type":"Point"}
}