{
  "type": "Feature",
  "properties": {
    "gn:admin1_code":"24.0",
    "gn:asciiname":"Houchuan",
    "gn:country_code":"CN",
    "gn:dem":874,
    "gn:feature_class":"P",
    "gn:feature_code":"PPL",
    "gn:name":"Houchuan",
    "gn:population":0,
    "gn:timezone":"Asia/Shanghai",
    "iso:country":"CN",
    "name:und_x_variant":[
        "\u540e\u5ddd"
    ],
    "wof:name":"Houchuan",
    "wof:placetype":"locality"
},
  "geometry": {"coordinates":[111.51985000000001,35.25595999999999],"type":"Point"}
}