{
  "type": "Feature",
  "properties": {
    "gn:admin1_code":"33",
    "gn:asciiname":"Gulu",
    "gn:country_code":"CN",
    "gn:dem":721,
    "gn:feature_class":"P",
    "gn:feature_code":"PPLA4",
    "gn:name":"Gulu",
    "gn:population":0,
    "gn:timezone":"Asia/Shanghai",
    "iso:country":"CN",
    "name:und_x_variant":[
        "Gulu Zhen"
    ],
    "name:zho_x_preferred":[
        "\u53e4\u8def"
    ],
    "name:zho_x_variant":[
        "\u53e4\u8def\u9547"
    ],
    "wof:name":"Gulu",
    "wof:placetype":"locality"
},
  "geometry": {"coordinates":[109.43991,31.3301],"type":"Point"}
}