{
  "type": "Feature",
  "properties": {
    "gn:admin1_code":"32.0",
    "gn:asciiname":"Dongcao",
    "gn:country_code":"CN",
    "gn:dem":561,
    "gn:feature_class":"P",
    "gn:feature_code":"PPL",
    "gn:name":"Dongcao",
    "gn:population":0,
    "gn:timezone":"Asia/Shanghai",
    "iso:country":"CN",
    "name:zho_x_preferred":[
        "\u4e1c\u66f9"
    ],
    "wof:name":"Dongcao",
    "wof:placetype":"locality"
},
  "geometry": {"coordinates":[105.36499999999999,32.2593],"type":"Point"}
}