{
  "type": "Feature",
  "properties": {
    "gn:admin1_code":"24.0",
    "gn:asciiname":"Huahongcun",
    "gn:country_code":"CN",
    "gn:dem":1153,
    "gn:feature_class":"P",
    "gn:feature_code":"PPL",
    "gn:name":"Huahongcun",
    "gn:population":0,
    "gn:timezone":"Asia/Shanghai",
    "iso:country":"CN",
    "name:zho_x_preferred":[
        "\u5316\u7ea2\u6751"
    ],
    "wof:name":"Huahongcun",
    "wof:placetype":"locality"
},
  "geometry": {"coordinates":[114.27291,39.28915],"type":"Point"}
}