{
  "type": "Feature",
  "properties": {
    "gn:admin1_code":"26.0",
    "gn:asciiname":"Angou",
    "gn:country_code":"CN",
    "gn:dem":1078,
    "gn:feature_class":"P",
    "gn:feature_code":"PPL",
    "gn:name":"Angou",
    "gn:population":0,
    "gn:timezone":"Asia/Shanghai",
    "iso:country":"CN",
    "name:zho_x_preferred":[
        "\u5b89\u6c9f"
    ],
    "wof:name":"Angou",
    "wof:placetype":"locality"
},
  "geometry": {"coordinates":[108.75769,34.96978],"type":"Point"}
}