{
  "type": "Feature",
  "properties": {
    "gn:admin1_code":"19.0",
    "gn:asciiname":"Jiyupao",
    "gn:country_code":"CN",
    "gn:dem":25,
    "gn:feature_class":"P",
    "gn:feature_code":"PPL",
    "gn:name":"Jiyupao",
    "gn:population":0,
    "gn:timezone":"Asia/Shanghai",
    "iso:country":"CN",
    "name:zho_x_preferred":[
        "\u9cab\u9c7c\u6ce1"
    ],
    "wof:name":"Jiyupao",
    "wof:placetype":"locality"
},
  "geometry": {"coordinates":[122.74151000000001,41.80774],"type":"Point"}
}