{
  "type": "Feature",
  "properties": {
    "gn:admin1_code":"10.0",
    "gn:asciiname":"Junmazhan",
    "gn:country_code":"CN",
    "gn:dem":8,
    "gn:feature_class":"P",
    "gn:feature_code":"PPL",
    "gn:name":"Junmazhan",
    "gn:population":0,
    "gn:timezone":"Asia/Shanghai",
    "iso:country":"CN",
    "name:zho_x_preferred":[
        "\u519b\u9a6c\u7ad9"
    ],
    "wof:name":"Junmazhan",
    "wof:placetype":"locality"
},
  "geometry": {"coordinates":[117.081,38.3498],"type":"Point"}
}