{
  "type": "Feature",
  "properties": {
    "gn:admin1_code":"30.0",
    "gn:asciiname":"Pengugen",
    "gn:country_code":"CN",
    "gn:dem":176,
    "gn:feature_class":"P",
    "gn:feature_code":"PPL",
    "gn:name":"Pengugen",
    "gn:population":0,
    "gn:timezone":"Asia/Shanghai",
    "iso:country":"CN",
    "name:zho_x_preferred":[
        "\u76c6\u53e4\u6839"
    ],
    "wof:name":"Pengugen",
    "wof:placetype":"locality"
},
  "geometry": {"coordinates":[112.15273999999999,23.6277],"type":"Point"}
}