{
  "type": "Feature",
  "properties": {
    "gn:admin1_code":"19.0",
    "gn:asciiname":"Hejia Wopu",
    "gn:country_code":"CN",
    "gn:dem":176,
    "gn:feature_class":"P",
    "gn:feature_code":"PPL",
    "gn:name":"Hejia Wopu",
    "gn:population":0,
    "gn:timezone":"Asia/Shanghai",
    "iso:country":"CN",
    "name:zho_x_preferred":[
        "\u4f55\u5bb6\u7a9d\u94fa"
    ],
    "wof:name":"Hejia Wopu",
    "wof:placetype":"locality"
},
  "geometry": {"coordinates":[120.655,41.3309],"type":"Point"}
}