{
  "type": "Feature",
  "properties": {
    "gn:admin1_code":"2.0",
    "gn:asciiname":"Shizhukou",
    "gn:country_code":"CN",
    "gn:dem":591,
    "gn:feature_class":"P",
    "gn:feature_code":"PPL",
    "gn:name":"Shizhukou",
    "gn:population":0,
    "gn:timezone":"Asia/Shanghai",
    "iso:country":"CN",
    "name:zho_x_preferred":[
        "\u77f3\u67f1\u53e3"
    ],
    "wof:name":"Shizhukou",
    "wof:placetype":"locality"
},
  "geometry": {"coordinates":[119.09211999999999,28.63887],"type":"Point"}
}