{
  "type": "Feature",
  "properties": {
    "gn:admin1_code":"02",
    "gn:asciiname":"Shuangjia'ao",
    "gn:country_code":"CN",
    "gn:dem":35,
    "gn:feature_class":"P",
    "gn:feature_code":"PPL",
    "gn:name":"Shuangjia\u2019ao",
    "gn:population":0,
    "gn:timezone":"Asia/Shanghai",
    "iso:country":"CN",
    "name:zho_x_preferred":[
        "Shuangjia\u2019ao"
    ],
    "name:zho_x_variant":[
        "\u53cc\u67b6\u5c99"
    ],
    "wof:name":"Shuangjia'ao",
    "wof:placetype":"locality"
},
  "geometry": {"coordinates":[121.87079,28.49989],"type":"Point"}
}