{
  "type": "Feature",
  "properties": {
    "gn:admin1_code":"9",
    "gn:asciiname":"Maliji",
    "gn:country_code":"CN",
    "gn:dem":65,
    "gn:feature_class":"P",
    "gn:feature_code":"PPL",
    "gn:name":"Maliji",
    "gn:population":0,
    "gn:timezone":"Asia/Shanghai",
    "iso:country":"CN",
    "name:zho_x_preferred":[
        "\u9a6c\u674e\u96c6"
    ],
    "wof:name":"Maliji",
    "wof:placetype":"locality"
},
  "geometry": {"coordinates":[115.28,35.4886],"type":"Point"}
}