{
  "type": "Feature",
  "properties": {
    "gn:admin1_code":"26.0",
    "gn:asciiname":"Dahuodiancun",
    "gn:country_code":"CN",
    "gn:dem":1026,
    "gn:feature_class":"P",
    "gn:feature_code":"PPL",
    "gn:name":"Dahuodiancun",
    "gn:population":0,
    "gn:timezone":"Asia/Shanghai",
    "iso:country":"CN",
    "name:zho_x_preferred":[
        "\u6253\u706b\u5e97\u6751"
    ],
    "wof:name":"Dahuodiancun",
    "wof:placetype":"locality"
},
  "geometry": {"coordinates":[110.28351000000001,38.21587],"type":"Point"}
}