{
  "type": "Feature",
  "properties": {
    "gn:admin1_code":"8.0",
    "gn:asciiname":"Yaotun",
    "gn:country_code":"CN",
    "gn:dem":309,
    "gn:feature_class":"P",
    "gn:feature_code":"PPL",
    "gn:name":"Yaotun",
    "gn:population":0,
    "gn:timezone":"Asia/Shanghai",
    "iso:country":"CN",
    "name:zho_x_preferred":[
        "\u7a91\u5c6f"
    ],
    "wof:name":"Yaotun",
    "wof:placetype":"locality"
},
  "geometry": {"coordinates":[125.60371000000001,49.19747],"type":"Point"}
}