{
  "type": "Feature",
  "properties": {
    "gn:admin1_code":"12.0",
    "gn:asciiname":"Huatudi",
    "gn:country_code":"CN",
    "gn:dem":37,
    "gn:feature_class":"P",
    "gn:feature_code":"PPL",
    "gn:name":"Huatudi",
    "gn:population":0,
    "gn:timezone":"Asia/Shanghai",
    "iso:country":"CN",
    "name:zho_x_preferred":[
        "Huatudi"
    ],
    "name:zho_x_variant":[
        "\u82b1\u571f\u5730"
    ],
    "wof:name":"Huatudi",
    "wof:placetype":"locality"
},
  "geometry": {"coordinates":[111.92198999999999,30.16136],"type":"Point"}
}