{
  "type": "Feature",
  "properties": {
    "gn:admin1_code":"20.0",
    "gn:asciiname":"Ageta Tudi",
    "gn:country_code":"CN",
    "gn:dem":728,
    "gn:feature_class":"P",
    "gn:feature_code":"PPL",
    "gn:name":"Ageta Tudi",
    "gn:population":0,
    "gn:timezone":"Asia/Shanghai",
    "iso:country":"CN",
    "name:zho_x_preferred":[
        "\u963f\u683c\u5854\u56fe\u5730"
    ],
    "wof:name":"Ageta Tudi",
    "wof:placetype":"locality"
},
  "geometry": {"coordinates":[116.56735,49.17151],"type":"Point"}
}