{
  "type": "Feature",
  "properties": {
    "gn:admin1_code":"5.0",
    "gn:asciiname":"Qikecun",
    "gn:country_code":"CN",
    "gn:dem":117,
    "gn:feature_class":"P",
    "gn:feature_code":"PPL",
    "gn:name":"Qikecun",
    "gn:population":0,
    "gn:timezone":"Asia/Shanghai",
    "iso:country":"CN",
    "name:zho_x_preferred":[
        "\u4e03\u68f5\u6751"
    ],
    "wof:name":"Qikecun",
    "wof:placetype":"locality"
},
  "geometry": {"coordinates":[123.75476,43.55329],"type":"Point"}
}