{
  "type": "Feature",
  "properties": {
    "gn:admin1_code":"24",
    "gn:asciiname":"Jinzhang",
    "gn:country_code":"CN",
    "gn:dem":481,
    "gn:feature_class":"P",
    "gn:feature_code":"PPL",
    "gn:name":"Jinzhang",
    "gn:population":0,
    "gn:timezone":"Asia/Shanghai",
    "iso:country":"CN",
    "name:und_x_variant":[
        "Chin-chang",
        "Lung-tz\u2019u",
        "Chin-chang-ts\u2019un",
        "Lung-tzu-tz\u2019u",
        "Longci"
    ],
    "name:zho_x_preferred":[
        "\u664b\u638c"
    ],
    "wof:name":"Jinzhang",
    "wof:placetype":"locality"
},
  "geometry": {"coordinates":[111.36778,36.06763],"type":"Point"}
}