{
  "type": "Feature",
  "properties": {
    "gn:admin1_code":"30.0",
    "gn:asciiname":"Keshuxia",
    "gn:country_code":"CN",
    "gn:dem":89,
    "gn:feature_class":"P",
    "gn:feature_code":"PPL",
    "gn:name":"Keshuxia",
    "gn:population":0,
    "gn:timezone":"Asia/Shanghai",
    "iso:country":"CN",
    "name:zho_x_preferred":[
        "\u67ef\u6811\u4e0b"
    ],
    "wof:name":"Keshuxia",
    "wof:placetype":"locality"
},
  "geometry": {"coordinates":[115.1767,23.13716],"type":"Point"}
}