{
  "type": "Feature",
  "properties": {
    "gn:admin1_code":"10.0",
    "gn:asciiname":"Bailuoya",
    "gn:country_code":"CN",
    "gn:dem":16,
    "gn:feature_class":"P",
    "gn:feature_code":"PPL",
    "gn:name":"Bailuoya",
    "gn:population":0,
    "gn:timezone":"Asia/Shanghai",
    "iso:country":"CN",
    "name:zho_x_preferred":[
        "\u767d\u843d\u9e26"
    ],
    "wof:name":"Bailuoya",
    "wof:placetype":"locality"
},
  "geometry": {"coordinates":[116.38,38.0929],"type":"Point"}
}