{
  "type": "Feature",
  "properties": {
    "gn:admin1_code":"2.0",
    "gn:asciiname":"Shibu'ao",
    "gn:country_code":"CN",
    "gn:dem":1053,
    "gn:feature_class":"P",
    "gn:feature_code":"PPL",
    "gn:name":"Shibu\u2019ao",
    "gn:population":0,
    "gn:timezone":"Asia/Shanghai",
    "iso:country":"CN",
    "name:und_x_variant":[
        "Shibu\u2019ao"
    ],
    "name:zho_x_preferred":[
        "\u77f3\u57e0\u5773"
    ],
    "wof:name":"Shibu'ao",
    "wof:placetype":"locality"
},
  "geometry": {"coordinates":[119.02557,28.24303],"type":"Point"}
}