{
  "type": "Feature",
  "properties": {
    "gn:admin1_code":"26.0",
    "gn:asciiname":"Zhongleicun",
    "gn:country_code":"CN",
    "gn:dem":569,
    "gn:feature_class":"P",
    "gn:feature_code":"PPL",
    "gn:name":"Zhongleicun",
    "gn:population":0,
    "gn:timezone":"Asia/Shanghai",
    "iso:country":"CN",
    "name:zho_x_preferred":[
        "\u4e2d\u96f7\u6751"
    ],
    "wof:name":"Zhongleicun",
    "wof:placetype":"locality"
},
  "geometry": {"coordinates":[110.34135999999999,35.23338],"type":"Point"}
}