{
  "type": "Feature",
  "properties": {
    "gn:admin1_code":"5.0",
    "gn:asciiname":"Yalucun",
    "gn:country_code":"CN",
    "gn:dem":362,
    "gn:feature_class":"P",
    "gn:feature_code":"PPL",
    "gn:name":"Yal\u00fccun",
    "gn:population":0,
    "gn:timezone":"Asia/Shanghai",
    "iso:country":"CN",
    "name:und_x_variant":[
        "Yal\u00fccun"
    ],
    "name:zho_x_preferred":[
        "\u9e2d\u7eff\u6751"
    ],
    "wof:name":"Yalucun",
    "wof:placetype":"locality"
},
  "geometry": {"coordinates":[125.75196,42.43959],"type":"Point"}
}