{
  "type": "Feature",
  "properties": {
    "gn:admin1_code":"12.0",
    "gn:asciiname":"Tianshangping",
    "gn:country_code":"CN",
    "gn:dem":1047,
    "gn:feature_class":"P",
    "gn:feature_code":"PPL",
    "gn:name":"Tianshangping",
    "gn:population":0,
    "gn:timezone":"Asia/Shanghai",
    "iso:country":"CN",
    "name:zho_x_preferred":[
        "Tianshangping"
    ],
    "name:zho_x_variant":[
        "\u5929\u4e0a\u576a"
    ],
    "wof:name":"Tianshangping",
    "wof:placetype":"locality"
},
  "geometry": {"coordinates":[109.18170000000001,29.59304],"type":"Point"}
}