{
  "type": "Feature",
  "properties": {
    "gn:admin1_code":"14.0",
    "gn:asciiname":"Jiaqiancun",
    "gn:country_code":"CN",
    "gn:dem":4703,
    "gn:feature_class":"P",
    "gn:feature_code":"PPL",
    "gn:name":"Jiaqiancun",
    "gn:population":0,
    "gn:timezone":"Asia/Urumqi",
    "iso:country":"CN",
    "name:zho_x_preferred":[
        "\u52a0\u524d\u6751"
    ],
    "wof:name":"Jiaqiancun",
    "wof:placetype":"locality"
},
  "geometry": {"coordinates":[89.41463,31.54516],"type":"Point"}
}