{
  "type": "Feature",
  "properties": {
    "gn:admin1_code":"15.0",
    "gn:asciiname":"Zengjiacha",
    "gn:country_code":"CN",
    "gn:dem":1562,
    "gn:feature_class":"P",
    "gn:feature_code":"PPL",
    "gn:name":"Zengjiacha",
    "gn:population":0,
    "gn:timezone":"Asia/Shanghai",
    "iso:country":"CN",
    "name:zho_x_preferred":[
        "\u66fe\u5bb6\u5c94"
    ],
    "wof:name":"Zengjiacha",
    "wof:placetype":"locality"
},
  "geometry": {"coordinates":[104.246,36.4219],"type":"Point"}
}