{
  "type": "Feature",
  "properties": {
    "gn:admin1_code":"9.0",
    "gn:asciiname":"Hezhuang",
    "gn:country_code":"CN",
    "gn:dem":267,
    "gn:feature_class":"P",
    "gn:feature_code":"PPL",
    "gn:name":"Hezhuang",
    "gn:population":0,
    "gn:timezone":"Asia/Shanghai",
    "iso:country":"CN",
    "name:ceb_x_preferred":[
        "Hezhuang"
    ],
    "name:swe_x_preferred":[
        "Hezhuang"
    ],
    "name:zho_x_preferred":[
        "\u5408\u5e84"
    ],
    "wof:name":"Hezhuang",
    "wof:placetype":"locality"
},
  "geometry": {"coordinates":[113.48976,34.2896],"type":"Point"}
}