{
  "type": "Feature",
  "properties": {
    "gn:admin1_code":"6.0",
    "gn:asciiname":"Cairiwa",
    "gn:country_code":"CN",
    "gn:dem":4168,
    "gn:feature_class":"P",
    "gn:feature_code":"PPL",
    "gn:name":"Cairiwa",
    "gn:population":0,
    "gn:timezone":"Asia/Urumqi",
    "iso:country":"CN",
    "wof:name":"Cairiwa",
    "wof:placetype":"locality"
},
  "geometry": {"coordinates":[98.83333,34.46667],"type":"Point"}
}