{
  "type": "Feature",
  "properties": {
    "gn:admin1_code":"14.0",
    "gn:asciiname":"Goinbachacang",
    "gn:country_code":"CN",
    "gn:dem":4813,
    "gn:feature_class":"P",
    "gn:feature_code":"PPL",
    "gn:name":"Goinbachacang",
    "gn:population":0,
    "gn:timezone":"Asia/Urumqi",
    "iso:country":"CN",
    "name:bod_x_preferred":[
        "Goinbachacang"
    ],
    "name:zho_x_preferred":[
        "Gongbachacang"
    ],
    "name:zho_x_variant":[
        "\u8d21\u5df4\u67e5\u4ed3",
        "Takexun",
        "\u5854\u514b\u900a"
    ],
    "wof:name":"Goinbachacang",
    "wof:placetype":"locality"
},
  "geometry": {"coordinates":[88.7876,28.2121],"type":"Point"}
}