{
  "type": "Feature",
  "properties": {
    "gn:admin1_code":"26.0",
    "gn:asciiname":"Xuetangping",
    "gn:country_code":"CN",
    "gn:dem":1348,
    "gn:feature_class":"P",
    "gn:feature_code":"PPL",
    "gn:name":"Xuetangping",
    "gn:population":0,
    "gn:timezone":"Asia/Shanghai",
    "iso:country":"CN",
    "name:zho_x_preferred":[
        "\u5b66\u5802\u576a"
    ],
    "wof:name":"Xuetangping",
    "wof:placetype":"locality"
},
  "geometry": {"coordinates":[108.39066,32.29069],"type":"Point"}
}