{
  "type": "Feature",
  "properties": {
    "gn:admin1_code":"32.0",
    "gn:asciiname":"Muxiamo",
    "gn:country_code":"CN",
    "gn:dem":3021,
    "gn:feature_class":"P",
    "gn:feature_code":"PPL",
    "gn:name":"Muxiamo",
    "gn:population":0,
    "gn:timezone":"Asia/Shanghai",
    "iso:country":"CN",
    "name:zho_x_preferred":[
        "\u7267\u5477\u83ab"
    ],
    "wof:name":"Muxiamo",
    "wof:placetype":"locality"
},
  "geometry": {"coordinates":[102.584,27.9234],"type":"Point"}
}