{
  "type": "Feature",
  "properties": {
    "gn:admin1_code":"02",
    "gn:asciiname":"Jiangjiabang",
    "gn:country_code":"CN",
    "gn:dem":5,
    "gn:feature_class":"P",
    "gn:feature_code":"PPL",
    "gn:name":"Jiangjiabang",
    "gn:population":0,
    "gn:timezone":"Asia/Shanghai",
    "iso:country":"CN",
    "name:und_x_variant":[
        "\u848b\u5bb6\u6d5c"
    ],
    "wof:name":"Jiangjiabang",
    "wof:placetype":"locality"
},
  "geometry": {"coordinates":[121.04709,30.73282],"type":"Point"}
}