{
  "type": "Feature",
  "properties": {
    "gn:admin1_code":"32.0",
    "gn:asciiname":"Wutongtang",
    "gn:country_code":"CN",
    "gn:dem":331,
    "gn:feature_class":"P",
    "gn:feature_code":"PPL",
    "gn:name":"Wutongtang",
    "gn:population":0,
    "gn:timezone":"Asia/Shanghai",
    "iso:country":"CN",
    "name:zho_x_preferred":[
        "\u4e94\u901a\u5858"
    ],
    "wof:name":"Wutongtang",
    "wof:placetype":"locality"
},
  "geometry": {"coordinates":[106.233,30.6219],"type":"Point"}
}