{
  "type": "Feature",
  "properties": {
    "gn:admin1_code":"1.0",
    "gn:asciiname":"Liutaocun",
    "gn:country_code":"CN",
    "gn:dem":46,
    "gn:feature_class":"P",
    "gn:feature_code":"PPL",
    "gn:name":"Liutaocun",
    "gn:population":0,
    "gn:timezone":"Asia/Shanghai",
    "iso:country":"CN",
    "name:zho_x_preferred":[
        "\u5218\u5957\u6751"
    ],
    "wof:name":"Liutaocun",
    "wof:placetype":"locality"
},
  "geometry": {"coordinates":[116.91732,34.34125],"type":"Point"}
}