{
  "type": "Feature",
  "properties": {
    "gn:admin1_code":"32.0",
    "gn:asciiname":"Gaomiaozi",
    "gn:country_code":"CN",
    "gn:dem":553,
    "gn:feature_class":"P",
    "gn:feature_code":"PPL",
    "gn:name":"Gaomiaozi",
    "gn:population":0,
    "gn:timezone":"Asia/Shanghai",
    "iso:country":"CN",
    "name:zho_x_preferred":[
        "\u9ad8\u5e99\u5b50"
    ],
    "wof:name":"Gaomiaozi",
    "wof:placetype":"locality"
},
  "geometry": {"coordinates":[104.90158,31.71476],"type":"Point"}
}