{
  "type": "Feature",
  "properties": {
    "gn:admin1_code":"07",
    "gn:asciiname":"Jiangweixia",
    "gn:country_code":"CN",
    "gn:dem":314,
    "gn:feature_class":"P",
    "gn:feature_code":"PPL",
    "gn:name":"Jiangweixia",
    "gn:population":0,
    "gn:timezone":"Asia/Shanghai",
    "iso:country":"CN",
    "name:zho_x_preferred":[
        "\u6c5f\u5c3e\u4e0b"
    ],
    "wof:name":"Jiangweixia",
    "wof:placetype":"locality"
},
  "geometry": {"coordinates":[116.90791000000002,24.81555],"type":"Point"}
}