{
  "type": "Feature",
  "properties": {
    "gn:admin1_code":"9.0",
    "gn:asciiname":"Xiapogaocun",
    "gn:country_code":"CN",
    "gn:dem":57,
    "gn:feature_class":"P",
    "gn:feature_code":"PPL",
    "gn:name":"Xiapogaocun",
    "gn:population":0,
    "gn:timezone":"Asia/Shanghai",
    "iso:country":"CN",
    "name:zho_x_preferred":[
        "\u4e0b\u5761\u9ad8\u6751"
    ],
    "wof:name":"Xiapogaocun",
    "wof:placetype":"locality"
},
  "geometry": {"coordinates":[114.03812000000001,33.78385],"type":"Point"}
}