{
  "type": "Feature",
  "properties": {
    "gn:admin1_code":"19.0",
    "gn:asciiname":"Kongjiayao",
    "gn:country_code":"CN",
    "gn:dem":87,
    "gn:feature_class":"P",
    "gn:feature_code":"PPL",
    "gn:name":"Kongjiayao",
    "gn:population":0,
    "gn:timezone":"Asia/Shanghai",
    "iso:country":"CN",
    "name:und_x_variant":[
        "\u5b54\u5bb6\u7a91"
    ],
    "name:zho_x_preferred":[
        "\u5b54\u5bb6\u7a91"
    ],
    "wof:name":"Kongjiayao",
    "wof:placetype":"locality"
},
  "geometry": {"coordinates":[122.45756000000002,42.34647],"type":"Point"}
}