{
  "type": "Feature",
  "properties": {
    "gn:admin1_code":"10",
    "gn:asciiname":"Shangdingjialing",
    "gn:country_code":"CN",
    "gn:dem":153,
    "gn:feature_class":"P",
    "gn:feature_code":"PPL",
    "gn:name":"Shangdingjialing",
    "gn:population":0,
    "gn:timezone":"Asia/Shanghai",
    "iso:country":"CN",
    "name:zho_x_preferred":[
        "\u4e0a\u4e01\u7532\u5cad"
    ],
    "wof:name":"Shangdingjialing",
    "wof:placetype":"locality"
},
  "geometry": {"coordinates":[118.1095,40.06526],"type":"Point"}
}