{
  "type": "Feature",
  "properties": {
    "gn:admin1_code":"07",
    "gn:asciiname":"Yuzi",
    "gn:country_code":"CN",
    "gn:dem":317,
    "gn:feature_class":"P",
    "gn:feature_code":"PPL",
    "gn:name":"Yuzi",
    "gn:population":0,
    "gn:timezone":"Asia/Shanghai",
    "iso:country":"CN",
    "name:zho_x_preferred":[
        "\u90c1\u5b50"
    ],
    "wof:name":"Yuzi",
    "wof:placetype":"locality"
},
  "geometry": {"coordinates":[118.06167000000001,25.12194],"type":"Point"}
}