{
  "type": "Feature",
  "properties": {
    "gn:admin1_code":"15.0",
    "gn:asciiname":"Kongzicha",
    "gn:country_code":"CN",
    "gn:dem":2044,
    "gn:feature_class":"P",
    "gn:feature_code":"PPL",
    "gn:name":"Kongzicha",
    "gn:population":0,
    "gn:timezone":"Asia/Shanghai",
    "iso:country":"CN",
    "name:zho_x_preferred":[
        "\u5b54\u5b50\u5c94"
    ],
    "wof:name":"Kongzicha",
    "wof:placetype":"locality"
},
  "geometry": {"coordinates":[104.196,36.0758],"type":"Point"}
}