{
  "type": "Feature",
  "properties": {
    "gn:admin1_code":"32.0",
    "gn:asciiname":"Xiongshi",
    "gn:country_code":"CN",
    "gn:dem":367,
    "gn:feature_class":"P",
    "gn:feature_code":"PPL",
    "gn:name":"Xiongshi",
    "gn:population":0,
    "gn:timezone":"Asia/Shanghai",
    "iso:country":"CN",
    "name:zho_x_preferred":[
        "\u96c4\u72ee"
    ],
    "wof:name":"Xiongshi",
    "wof:placetype":"locality"
},
  "geometry": {"coordinates":[105.80566,31.38941],"type":"Point"}
}