{
  "type": "Feature",
  "properties": {
    "gn:admin1_code":"15.0",
    "gn:asciiname":"Tuanzhuang",
    "gn:country_code":"CN",
    "gn:dem":1929,
    "gn:feature_class":"P",
    "gn:feature_code":"PPL",
    "gn:name":"Tuanzhuang",
    "gn:population":0,
    "gn:timezone":"Asia/Shanghai",
    "iso:country":"CN",
    "name:zho_x_preferred":[
        "\u56e2\u5e84"
    ],
    "wof:name":"Tuanzhuang",
    "wof:placetype":"locality"
},
  "geometry": {"coordinates":[102.291,37.9366],"type":"Point"}
}