{
  "type": "Feature",
  "properties": {
    "gn:admin1_code":"16.0",
    "gn:asciiname":"Fozijing",
    "gn:country_code":"CN",
    "gn:dem":382,
    "gn:feature_class":"P",
    "gn:feature_code":"PPL",
    "gn:name":"Fozijing",
    "gn:population":0,
    "gn:timezone":"Asia/Shanghai",
    "iso:country":"CN",
    "name:zho_x_preferred":[
        "\u4f5b\u5b50\u666f"
    ],
    "wof:name":"Fozijing",
    "wof:placetype":"locality"
},
  "geometry": {"coordinates":[109.65900000000001,22.4064],"type":"Point"}
}