{
  "type": "Feature",
  "properties": {
    "gn:admin1_code":"26.0",
    "gn:asciiname":"Zhaojia Shan",
    "gn:country_code":"CN",
    "gn:dem":721,
    "gn:feature_class":"P",
    "gn:feature_code":"PPL",
    "gn:name":"Zhaojia Shan",
    "gn:population":0,
    "gn:timezone":"Asia/Shanghai",
    "iso:country":"CN",
    "name:und_x_variant":[
        "\u8d75\u5bb6\u5c71"
    ],
    "wof:name":"Zhaojia Shan",
    "wof:placetype":"locality"
},
  "geometry": {"coordinates":[107.16249999999999,32.99704000000001],"type":"Point"}
}