{
  "type": "Feature",
  "properties": {
    "gn:admin1_code":"31.0",
    "gn:asciiname":"Lingmen Erdui",
    "gn:country_code":"CN",
    "gn:dem":257,
    "gn:feature_class":"P",
    "gn:feature_code":"PPLF",
    "gn:name":"Lingmen Erdui",
    "gn:population":0,
    "gn:timezone":"Asia/Shanghai",
    "iso:country":"CN",
    "name:und_x_variant":[
        "\u5cad\u95e8\u4e8c\u961f"
    ],
    "wof:name":"Lingmen Erdui",
    "wof:placetype":"locality"
},
  "geometry": {"coordinates":[110.05886,18.64281],"type":"Point"}
}