{
  "type": "Feature",
  "properties": {
    "gn:admin1_code":"22.0",
    "gn:asciiname":"Tunjunyingcun",
    "gn:country_code":"CN",
    "gn:dem":494,
    "gn:feature_class":"P",
    "gn:feature_code":"PPL",
    "gn:name":"Tunjunyingcun",
    "gn:population":0,
    "gn:timezone":"Asia/Shanghai",
    "iso:country":"CN",
    "name:zho_x_preferred":[
        "\u5c6f\u519b\u8425\u6751"
    ],
    "wof:name":"Tunjunyingcun",
    "wof:placetype":"locality"
},
  "geometry": {"coordinates":[115.87186,40.38876],"type":"Point"}
}