{
  "type": "Feature",
  "properties": {
    "gn:admin1_code":"24",
    "gn:asciiname":"Qiaotianchi",
    "gn:country_code":"CN",
    "gn:dem":1205,
    "gn:feature_class":"P",
    "gn:feature_code":"PPL",
    "gn:name":"Qiaotianchi",
    "gn:population":0,
    "gn:timezone":"Asia/Shanghai",
    "iso:country":"CN",
    "wof:name":"Qiaotianchi",
    "wof:placetype":"locality"
},
  "geometry": {"coordinates":[112.26222,37.67778],"type":"Point"}
}