{
  "type": "Feature",
  "properties": {
    "gn:admin1_code":"32.0",
    "gn:asciiname":"Heshuigou",
    "gn:country_code":"CN",
    "gn:dem":1775,
    "gn:feature_class":"P",
    "gn:feature_code":"PPL",
    "gn:name":"Heshuigou",
    "gn:population":0,
    "gn:timezone":"Asia/Shanghai",
    "iso:country":"CN",
    "name:zho_x_preferred":[
        "\u6cb3\u6c34\u6c9f"
    ],
    "wof:name":"Heshuigou",
    "wof:placetype":"locality"
},
  "geometry": {"coordinates":[102.33499999999999,26.5156],"type":"Point"}
}