{
  "type": "Feature",
  "properties": {
    "gn:admin1_code":"2.0",
    "gn:asciiname":"Tiandong",
    "gn:country_code":"CN",
    "gn:dem":401,
    "gn:feature_class":"P",
    "gn:feature_code":"PPL",
    "gn:name":"Tiandong",
    "gn:population":0,
    "gn:timezone":"Asia/Shanghai",
    "iso:country":"CN",
    "name:und_x_variant":[
        "\u5929\u6d1e"
    ],
    "name:zho_x_preferred":[
        "Tiandong"
    ],
    "wof:name":"Tiandong",
    "wof:placetype":"locality"
},
  "geometry": {"coordinates":[119.55983999999999,29.94194],"type":"Point"}
}