{
  "type": "Feature",
  "properties": {
    "gn:admin1_code":"29.0",
    "gn:asciiname":"Luoyaojing",
    "gn:country_code":"CN",
    "gn:dem":1964,
    "gn:feature_class":"P",
    "gn:feature_code":"PPL",
    "gn:name":"Luoyaojing",
    "gn:population":0,
    "gn:timezone":"Asia/Shanghai",
    "iso:country":"CN",
    "name:und_x_variant":[
        "Luomejing"
    ],
    "name:zho_x_preferred":[
        "\u502e\u4e48\u9631"
    ],
    "wof:name":"Luoyaojing",
    "wof:placetype":"locality"
},
  "geometry": {"coordinates":[101.04900000000001,25.7629],"type":"Point"}
}