{
  "type": "Feature",
  "properties": {
    "gn:admin1_code":"29",
    "gn:asciiname":"Dalishu",
    "gn:country_code":"CN",
    "gn:dem":1358,
    "gn:feature_class":"P",
    "gn:feature_code":"PPL",
    "gn:name":"Dalishu",
    "gn:population":0,
    "gn:timezone":"Asia/Shanghai",
    "iso:country":"CN",
    "name:zho_x_preferred":[
        "\u5927\u6817\u6811"
    ],
    "wof:name":"Dalishu",
    "wof:placetype":"locality"
},
  "geometry": {"coordinates":[102.003,24.9286],"type":"Point"}
}