{
  "type": "Feature",
  "properties": {
    "gn:admin1_code":"26.0",
    "gn:asciiname":"Anmenkoucun",
    "gn:country_code":"CN",
    "gn:dem":599,
    "gn:feature_class":"P",
    "gn:feature_code":"PPL",
    "gn:name":"Anmenkoucun",
    "gn:population":0,
    "gn:timezone":"Asia/Shanghai",
    "iso:country":"CN",
    "name:zho_x_preferred":[
        "\u5b89\u95e8\u53e3\u6751"
    ],
    "wof:name":"Anmenkoucun",
    "wof:placetype":"locality"
},
  "geometry": {"coordinates":[109.74355,33.41458],"type":"Point"}
}