{
  "type": "Feature",
  "properties": {
    "gn:admin1_code":"19.0",
    "gn:asciiname":"Duanshulingzi",
    "gn:country_code":"CN",
    "gn:dem":282,
    "gn:feature_class":"P",
    "gn:feature_code":"PPL",
    "gn:name":"Duanshulingzi",
    "gn:population":0,
    "gn:timezone":"Asia/Shanghai",
    "iso:country":"CN",
    "name:und_x_variant":[
        "\u6934\u6811\u5cad\u5b50"
    ],
    "name:zho_x_preferred":[
        "\u6934\u6811\u5cad\u5b50"
    ],
    "wof:name":"Duanshulingzi",
    "wof:placetype":"locality"
},
  "geometry": {"coordinates":[125.38590000000001,40.90986],"type":"Point"}
}