{
  "type": "Feature",
  "properties": {
    "gn:admin1_code":"1.0",
    "gn:asciiname":"Xin'an",
    "gn:country_code":"CN",
    "gn:dem":113,
    "gn:feature_class":"P",
    "gn:feature_code":"PPLA4",
    "gn:name":"Xin\u2019an",
    "gn:population":0,
    "gn:timezone":"Asia/Shanghai",
    "iso:country":"CN",
    "name:und_x_variant":[
        "Xin\u2019anzhou",
        "Xin\u2019an",
        "\u65b0\u5b89",
        "Xin\u2019an Xiang",
        "\u65b0\u5b89\u4e61"
    ],
    "wof:name":"Xin'an",
    "wof:placetype":"locality"
},
  "geometry": {"coordinates":[117.28037999999999,29.88755],"type":"Point"}
}