{
  "type": "Feature",
  "properties": {
    "gn:admin1_code":"4.0",
    "gn:asciiname":"Liuyuancun",
    "gn:country_code":"CN",
    "gn:dem":36,
    "gn:feature_class":"P",
    "gn:feature_code":"PPL",
    "gn:name":"Liuyuancun",
    "gn:population":0,
    "gn:timezone":"Asia/Shanghai",
    "iso:country":"CN",
    "name:zho_x_preferred":[
        "\u67f3\u56ed\u6751"
    ],
    "wof:name":"Liuyuancun",
    "wof:placetype":"locality"
},
  "geometry": {"coordinates":[117.58947999999999,34.09473],"type":"Point"}
}