{
  "type": "Feature",
  "properties": {
    "gn:admin1_code":"3.0",
    "gn:asciiname":"Xitangfan",
    "gn:country_code":"CN",
    "gn:dem":64,
    "gn:feature_class":"P",
    "gn:feature_code":"PPL",
    "gn:name":"Xitangfan",
    "gn:population":0,
    "gn:timezone":"Asia/Shanghai",
    "iso:country":"CN",
    "name:zho_x_preferred":[
        "\u6614\u5858\u7548"
    ],
    "wof:name":"Xitangfan",
    "wof:placetype":"locality"
},
  "geometry": {"coordinates":[117.548,28.7742],"type":"Point"}
}