{
  "type": "Feature",
  "properties": {
    "gn:admin1_code":"11.0",
    "gn:asciiname":"Dupochong",
    "gn:country_code":"CN",
    "gn:dem":63,
    "gn:feature_class":"P",
    "gn:feature_code":"PPL",
    "gn:name":"Dupochong",
    "gn:population":0,
    "gn:timezone":"Asia/Shanghai",
    "iso:country":"CN",
    "name:zho_x_preferred":[
        "\u675c\u5a46\u51b2"
    ],
    "wof:name":"Dupochong",
    "wof:placetype":"locality"
},
  "geometry": {"coordinates":[112.16956,28.77551],"type":"Point"}
}