{
  "type": "Feature",
  "properties": {
    "gn:admin1_code":"11.0",
    "gn:asciiname":"Chemeng",
    "gn:country_code":"CN",
    "gn:dem":717,
    "gn:feature_class":"P",
    "gn:feature_code":"PPL",
    "gn:name":"Chemeng",
    "gn:population":0,
    "gn:timezone":"Asia/Shanghai",
    "iso:country":"CN",
    "name:zho_x_preferred":[
        "\u626f\u5b5f"
    ],
    "wof:name":"Chemeng",
    "wof:placetype":"locality"
},
  "geometry": {"coordinates":[109.60491,29.04045],"type":"Point"}
}