{
  "type": "Feature",
  "properties": {
    "gn:admin1_code":"14.0",
    "gn:asciiname":"Urmai",
    "gn:country_code":"CN",
    "gn:dem":4717,
    "gn:feature_class":"P",
    "gn:feature_code":"PPLF",
    "gn:name":"Urmai",
    "gn:population":0,
    "gn:timezone":"Asia/Urumqi",
    "iso:country":"CN",
    "name:bod_x_preferred":[
        "Urmai"
    ],
    "name:msa_x_preferred":[
        "Urmai"
    ],
    "name:zho_x_preferred":[
        "Wu\u2019ermai"
    ],
    "name:zho_x_variant":[
        "\u5434\u5c14\u5356"
    ],
    "wof:name":"Urmai",
    "wof:placetype":"locality"
},
  "geometry": {"coordinates":[87.59999999999999,31.78333],"type":"Point"}
}