{
  "type": "Feature",
  "properties": {
    "gn:admin1_code":"1.0",
    "gn:asciiname":"Maotancun",
    "gn:country_code":"CN",
    "gn:dem":456,
    "gn:feature_class":"P",
    "gn:feature_code":"PPL",
    "gn:name":"Maotancun",
    "gn:population":0,
    "gn:timezone":"Asia/Shanghai",
    "iso:country":"CN",
    "name:zho_x_preferred":[
        "\u6bdb\u5766\u6751"
    ],
    "wof:name":"Maotancun",
    "wof:placetype":"locality"
},
  "geometry": {"coordinates":[119.34802999999999,30.37088],"type":"Point"}
}