{
  "type": "Feature",
  "properties": {
    "gn:admin1_code":"9.0",
    "gn:asciiname":"Xikuduo",
    "gn:country_code":"CN",
    "gn:dem":579,
    "gn:feature_class":"P",
    "gn:feature_code":"PPL",
    "gn:name":"Xikuduo",
    "gn:population":0,
    "gn:timezone":"Asia/Shanghai",
    "iso:country":"CN",
    "name:und_x_variant":[
        "\u897f\u82e6\u579b",
        "Xikuduo"
    ],
    "wof:name":"Xikuduo",
    "wof:placetype":"locality"
},
  "geometry": {"coordinates":[112.06905999999999,33.50668],"type":"Point"}
}