{
  "type": "Feature",
  "properties": {
    "gn:admin1_code":"7.0",
    "gn:asciiname":"Liudi",
    "gn:country_code":"CN",
    "gn:dem":498,
    "gn:feature_class":"P",
    "gn:feature_code":"PPL",
    "gn:name":"Liudi",
    "gn:population":0,
    "gn:timezone":"Asia/Shanghai",
    "iso:country":"CN",
    "name:und_x_variant":[
        "\u7559\u5730"
    ],
    "name:zho_x_preferred":[
        "\u7559\u5730"
    ],
    "wof:name":"Liudi",
    "wof:placetype":"locality"
},
  "geometry": {"coordinates":[116.80641,26.33693],"type":"Point"}
}