{
  "type": "Feature",
  "properties": {
    "gn:admin1_code":"9.0",
    "gn:asciiname":"Chenwancun",
    "gn:country_code":"CN",
    "gn:dem":68,
    "gn:feature_class":"P",
    "gn:feature_code":"PPL",
    "gn:name":"Chenwancun",
    "gn:population":0,
    "gn:timezone":"Asia/Shanghai",
    "iso:country":"CN",
    "name:und_x_variant":[
        "\u9648\u6e7e\u6751"
    ],
    "name:zho_x_preferred":[
        "\u9648\u6e7e\u6751"
    ],
    "wof:name":"Chenwancun",
    "wof:placetype":"locality"
},
  "geometry": {"coordinates":[113.94473000000001,33.58651],"type":"Point"}
}