{
  "type": "Feature",
  "properties": {
    "gn:admin1_code":"12",
    "gn:asciiname":"Jiepaidian",
    "gn:cc2":"CN",
    "gn:country_code":"CN",
    "gn:dem":40,
    "gn:feature_class":"P",
    "gn:feature_code":"PPL",
    "gn:name":"Jiepaidian",
    "gn:population":0,
    "gn:timezone":"Asia/Shanghai",
    "iso:country":"CN",
    "name:und_x_variant":[
        "Chieh-p\u2019ai-tien",
        "Jiepai",
        "Chieh-p\u2019ai",
        "Jiepaidian"
    ],
    "wof:name":"Jiepaidian",
    "wof:placetype":"locality"
},
  "geometry": {"coordinates":[113.69194,31.17028],"type":"Point"}
}