{
  "type": "Feature",
  "properties": {
    "gn:admin1_code":"5.0",
    "gn:asciiname":"Nanchagan Daixicun",
    "gn:country_code":"CN",
    "gn:dem":171,
    "gn:feature_class":"P",
    "gn:feature_code":"PPL",
    "gn:name":"Nanchagan Daixicun",
    "gn:population":0,
    "gn:timezone":"Asia/Shanghai",
    "iso:country":"CN",
    "name:zho_x_preferred":[
        "\u5357\u67e5\u5e72\u4ee3\u897f\u6751"
    ],
    "wof:name":"Nanchagan Daixicun",
    "wof:placetype":"locality"
},
  "geometry": {"coordinates":[122.20501000000002,45.14157],"type":"Point"}
}