{
  "type": "Feature",
  "properties": {
    "gn:admin1_code":"5.0",
    "gn:asciiname":"Yuda Fangzi",
    "gn:country_code":"CN",
    "gn:dem":160,
    "gn:feature_class":"P",
    "gn:feature_code":"PPL",
    "gn:name":"Yuda Fangzi",
    "gn:population":0,
    "gn:timezone":"Asia/Shanghai",
    "iso:country":"CN",
    "name:zho_x_preferred":[
        "\u4e8e\u5927\u623f\u5b50"
    ],
    "wof:name":"Yuda Fangzi",
    "wof:placetype":"locality"
},
  "geometry": {"coordinates":[125.57980999999999,45.21751],"type":"Point"}
}