{
  "type": "Feature",
  "properties": {
    "gn:admin1_code":"1.0",
    "gn:asciiname":"Taiping'ancun",
    "gn:country_code":"CN",
    "gn:dem":46,
    "gn:feature_class":"P",
    "gn:feature_code":"PPL",
    "gn:name":"Taiping\u2019ancun",
    "gn:population":0,
    "gn:timezone":"Asia/Shanghai",
    "iso:country":"CN",
    "name:und_x_variant":[
        "Taiping\u2019ancun"
    ],
    "name:zho_x_preferred":[
        "\u592a\u5e73\u5eb5\u6751"
    ],
    "wof:name":"Taiping'ancun",
    "wof:placetype":"locality"
},
  "geometry": {"coordinates":[116.43792999999999,31.68478],"type":"Point"}
}