{
  "type": "Feature",
  "properties": {
    "gn:admin1_code":"29",
    "gn:asciiname":"Zhezu",
    "gn:country_code":"CN",
    "gn:dem":1813,
    "gn:feature_class":"P",
    "gn:feature_code":"PPL",
    "gn:name":"Zhezu",
    "gn:population":0,
    "gn:timezone":"Asia/Shanghai",
    "iso:country":"CN",
    "name:zho_x_preferred":[
        "\u6298\u8db3"
    ],
    "wof:name":"Zhezu",
    "wof:placetype":"locality"
},
  "geometry": {"coordinates":[104.925,23.7784],"type":"Point"}
}