{
  "type": "Feature",
  "properties": {
    "gn:admin1_code":"7.0",
    "gn:asciiname":"Wengcuo",
    "gn:country_code":"CN",
    "gn:dem":323,
    "gn:feature_class":"P",
    "gn:feature_code":"PPL",
    "gn:name":"Wengcuo",
    "gn:population":0,
    "gn:timezone":"Asia/Shanghai",
    "iso:country":"CN",
    "name:zho_x_preferred":[
        "\u7fc1\u539d"
    ],
    "wof:name":"Wengcuo",
    "wof:placetype":"locality"
},
  "geometry": {"coordinates":[117.17644,26.61992],"type":"Point"}
}