{
  "type": "Feature",
  "properties": {
    "gn:admin1_code":"6.0",
    "gn:asciiname":"Qarhan",
    "gn:cc2":"CN",
    "gn:country_code":"CN",
    "gn:dem":2690,
    "gn:feature_class":"P",
    "gn:feature_code":"PPL",
    "gn:name":"Qarhan",
    "gn:population":0,
    "gn:timezone":"Asia/Urumqi",
    "iso:country":"CN",
    "name:und_x_variant":[
        "Ch\u2019a-erh-han",
        "Ha-erh-ma-kang",
        "Qarhan"
    ],
    "wof:name":"Qarhan",
    "wof:placetype":"locality"
},
  "geometry": {"coordinates":[95.09999999999999,36.75],"type":"Point"}
}