{
  "type": "Feature",
  "properties": {
    "gn:admin1_code":"5.0",
    "gn:asciiname":"Diyinzicun",
    "gn:country_code":"CN",
    "gn:dem":412,
    "gn:feature_class":"P",
    "gn:feature_code":"PPL",
    "gn:name":"Diyinzicun",
    "gn:population":0,
    "gn:timezone":"Asia/Shanghai",
    "iso:country":"CN",
    "name:zho_x_preferred":[
        "\u5730\u7aa8\u5b50\u6751"
    ],
    "wof:name":"Diyinzicun",
    "wof:placetype":"locality"
},
  "geometry": {"coordinates":[126.40192,42.65325],"type":"Point"}
}