{
  "type": "Feature",
  "properties": {
    "gn:admin1_code":"19.0",
    "gn:asciiname":"Zengjiazhai",
    "gn:country_code":"CN",
    "gn:dem":165,
    "gn:feature_class":"P",
    "gn:feature_code":"PPL",
    "gn:name":"Zengjiazhai",
    "gn:population":0,
    "gn:timezone":"Asia/Shanghai",
    "iso:country":"CN",
    "name:und_x_variant":[
        "\u66fe\u5bb6\u5be8"
    ],
    "name:zho_x_preferred":[
        "\u66fe\u5bb6\u5be8"
    ],
    "wof:name":"Zengjiazhai",
    "wof:placetype":"locality"
},
  "geometry": {"coordinates":[124.36006,42.21579000000001],"type":"Point"}
}