{
  "type": "Feature",
  "properties": {
    "gn:admin1_code":"9.0",
    "gn:asciiname":"Daogutian",
    "gn:country_code":"CN",
    "gn:dem":241,
    "gn:feature_class":"P",
    "gn:feature_code":"PPL",
    "gn:name":"Daogutian",
    "gn:population":0,
    "gn:timezone":"Asia/Shanghai",
    "iso:country":"CN",
    "name:und_x_variant":[
        "\u7a3b\u8c37\u7530",
        "Daogutian"
    ],
    "wof:name":"Daogutian",
    "wof:placetype":"locality"
},
  "geometry": {"coordinates":[112.75409999999999,33.67974],"type":"Point"}
}