{
  "type": "Feature",
  "properties": {
    "gn:admin1_code":"1.0",
    "gn:asciiname":"Dakuicun",
    "gn:country_code":"CN",
    "gn:dem":25,
    "gn:feature_class":"P",
    "gn:feature_code":"PPL",
    "gn:name":"Dakuicun",
    "gn:population":0,
    "gn:timezone":"Asia/Shanghai",
    "iso:country":"CN",
    "name:zho_x_preferred":[
        "\u5927\u9697\u6751"
    ],
    "wof:name":"Dakuicun",
    "wof:placetype":"locality"
},
  "geometry": {"coordinates":[116.76002,32.50177],"type":"Point"}
}