{
  "type": "Feature",
  "properties": {
    "gn:admin1_code":"29.0",
    "gn:asciiname":"Daheishu",
    "gn:country_code":"CN",
    "gn:dem":1842,
    "gn:feature_class":"P",
    "gn:feature_code":"PPL",
    "gn:name":"Daheishu",
    "gn:population":0,
    "gn:timezone":"Asia/Shanghai",
    "iso:country":"CN",
    "name:zho_x_preferred":[
        "\u5927\u9ed1\u6811"
    ],
    "wof:name":"Daheishu",
    "wof:placetype":"locality"
},
  "geometry": {"coordinates":[100.68600000000001,25.0307],"type":"Point"}
}