{
  "type": "Feature",
  "properties": {
    "gn:admin1_code":"9.0",
    "gn:asciiname":"Wangjiabiancun",
    "gn:country_code":"CN",
    "gn:dem":247,
    "gn:feature_class":"P",
    "gn:feature_code":"PPL",
    "gn:name":"Wangjiabiancun",
    "gn:population":0,
    "gn:timezone":"Asia/Shanghai",
    "iso:country":"CN",
    "name:zho_x_preferred":[
        "\u738b\u5bb6\u8fb9\u6751"
    ],
    "wof:name":"Wangjiabiancun",
    "wof:placetype":"locality"
},
  "geometry": {"coordinates":[115.04165999999999,31.64913],"type":"Point"}
}