{
  "type": "Feature",
  "properties": {
    "gn:admin1_code":"29.0",
    "gn:asciiname":"Nanbodibankao",
    "gn:country_code":"CN",
    "gn:dem":1407,
    "gn:feature_class":"P",
    "gn:feature_code":"PPL",
    "gn:name":"Nanbodibankao",
    "gn:population":0,
    "gn:timezone":"Asia/Shanghai",
    "iso:country":"CN",
    "name:zho_x_preferred":[
        "\u5357\u6ce2\u5730\u73ed\u9760"
    ],
    "wof:name":"Nanbodibankao",
    "wof:placetype":"locality"
},
  "geometry": {"coordinates":[99.9076,22.1643],"type":"Point"}
}