{
  "type": "Feature",
  "properties": {
    "gn:admin1_code":"15.0",
    "gn:asciiname":"Taowuka",
    "gn:country_code":"CN",
    "gn:dem":2383,
    "gn:feature_class":"P",
    "gn:feature_code":"PPL",
    "gn:name":"Taowuka",
    "gn:population":0,
    "gn:timezone":"Asia/Shanghai",
    "iso:country":"CN",
    "name:und_x_variant":[
        "\u6843\u543e\u5361"
    ],
    "wof:name":"Taowuka",
    "wof:placetype":"locality"
},
  "geometry": {"coordinates":[103.48114,34.01345],"type":"Point"}
}