{
  "type": "Feature",
  "properties": {
    "gn:admin1_code":"10",
    "gn:asciiname":"Huiyu",
    "gn:country_code":"CN",
    "gn:dem":617,
    "gn:feature_class":"P",
    "gn:feature_code":"PPL",
    "gn:name":"Huiyu",
    "gn:population":0,
    "gn:timezone":"Asia/Shanghai",
    "iso:country":"CN",
    "name:zho_x_preferred":[
        "\u5f57\u5cea"
    ],
    "wof:name":"Huiyu",
    "wof:placetype":"locality"
},
  "geometry": {"coordinates":[113.974,36.4014],"type":"Point"}
}