{
  "type": "Feature",
  "properties": {
    "gn:admin1_code":"18",
    "gn:asciiname":"Jishanpo",
    "gn:country_code":"CN",
    "gn:dem":1684,
    "gn:feature_class":"P",
    "gn:feature_code":"PPL",
    "gn:name":"Jishanpo",
    "gn:population":0,
    "gn:timezone":"Asia/Shanghai",
    "iso:country":"CN",
    "name:zho_x_preferred":[
        "\u796d\u5c71\u5761"
    ],
    "wof:name":"Jishanpo",
    "wof:placetype":"locality"
},
  "geometry": {"coordinates":[104.97499999999999,25.3811],"type":"Point"}
}