{
  "type": "Feature",
  "properties": {
    "gn:admin1_code":"1.0",
    "gn:asciiname":"Sencun",
    "gn:country_code":"CN",
    "gn:dem":147,
    "gn:feature_class":"P",
    "gn:feature_code":"PPLA4",
    "gn:name":"Sencun",
    "gn:population":0,
    "gn:timezone":"Asia/Shanghai",
    "iso:country":"CN",
    "name:und_x_variant":[
        "Sencun Xiang"
    ],
    "name:zho_x_preferred":[
        "\u68ee\u6751"
    ],
    "name:zho_x_variant":[
        "\u68ee\u6751\u4e61"
    ],
    "wof:name":"Sencun",
    "wof:placetype":"locality"
},
  "geometry": {"coordinates":[118.47861,29.75818],"type":"Point"}
}