{
  "type": "Feature",
  "properties": {
    "gn:admin1_code":"14.0",
    "gn:asciiname":"Tebo'ngori",
    "gn:country_code":"CN",
    "gn:dem":4771,
    "gn:feature_class":"P",
    "gn:feature_code":"PPL",
    "gn:name":"T\u00eabo\u2019ngori",
    "gn:population":0,
    "gn:timezone":"Asia/Urumqi",
    "iso:country":"CN",
    "name:bod_x_preferred":[
        "T\u00eabo\u2019ngori"
    ],
    "name:zho_x_preferred":[
        "Tiebo\u2019eli"
    ],
    "name:zho_x_variant":[
        "\u94c1\u6ce2\u4fc4\u91cc"
    ],
    "wof:name":"Tebo'ngori",
    "wof:placetype":"locality"
},
  "geometry": {"coordinates":[90.503,31.603],"type":"Point"}
}