{
  "type": "Feature",
  "properties": {
    "gn:admin1_code":"24",
    "gn:asciiname":"Houxiaoyu",
    "gn:country_code":"CN",
    "gn:dem":973,
    "gn:feature_class":"P",
    "gn:feature_code":"PPL",
    "gn:name":"Houxiaoyu",
    "gn:population":0,
    "gn:timezone":"Asia/Shanghai",
    "iso:country":"CN",
    "name:und_x_variant":[
        "Hou-hsiao-y\u00fc",
        "Houxiaoyu"
    ],
    "name:zho_x_preferred":[
        "\u540e\u5c0f\u5cea"
    ],
    "wof:name":"Houxiaoyu",
    "wof:placetype":"locality"
},
  "geometry": {"coordinates":[111.05448,37.8506],"type":"Point"}
}