{
  "type": "Feature",
  "properties": {
    "gn:admin1_code":"29",
    "gn:asciiname":"Qingmushu",
    "gn:country_code":"CN",
    "gn:dem":1936,
    "gn:feature_class":"P",
    "gn:feature_code":"PPL",
    "gn:name":"Qingmushu",
    "gn:population":0,
    "gn:timezone":"Asia/Shanghai",
    "iso:country":"CN",
    "name:zho_x_preferred":[
        "\u8f7b\u6728\u6811"
    ],
    "wof:name":"Qingmushu",
    "wof:placetype":"locality"
},
  "geometry": {"coordinates":[101.045,24.8126],"type":"Point"}
}