{
  "type": "Feature",
  "properties": {
    "gn:admin1_code":"1.0",
    "gn:asciiname":"Xiaoyiji",
    "gn:cc2":"CN",
    "gn:country_code":"CN",
    "gn:dem":21,
    "gn:feature_class":"P",
    "gn:feature_code":"PPL",
    "gn:name":"Xiaoyiji",
    "gn:population":0,
    "gn:timezone":"Asia/Shanghai",
    "iso:country":"CN",
    "name:und_x_variant":[
        "Hsiao-i-chi",
        "Xiaoyiji"
    ],
    "wof:name":"Xiaoyiji",
    "wof:placetype":"locality"
},
  "geometry": {"coordinates":[117.15000000000001,32.81667],"type":"Point"}
}