{
  "type": "Feature",
  "properties": {
    "gn:admin1_code":"2.0",
    "gn:asciiname":"Xiaguan",
    "gn:country_code":"CN",
    "gn:dem":16,
    "gn:feature_class":"P",
    "gn:feature_code":"PPL",
    "gn:name":"Xiaguan",
    "gn:population":0,
    "gn:timezone":"Asia/Shanghai",
    "iso:country":"CN",
    "name:ceb_x_preferred":[
        "Xiaguan"
    ],
    "name:swe_x_preferred":[
        "Xiaguan"
    ],
    "name:zho_x_preferred":[
        "\u4e0b\u7ba1"
    ],
    "wof:name":"Xiaguan",
    "wof:placetype":"locality"
},
  "geometry": {"coordinates":[121.25442,28.88984],"type":"Point"}
}