{
  "type": "Feature",
  "properties": {
    "gn:admin1_code":"5.0",
    "gn:asciiname":"Xiaoshahetun",
    "gn:country_code":"CN",
    "gn:dem":552,
    "gn:feature_class":"P",
    "gn:feature_code":"PPL",
    "gn:name":"Xiaoshahetun",
    "gn:population":0,
    "gn:timezone":"Asia/Shanghai",
    "iso:country":"CN",
    "name:und_x_variant":[
        "\u5c0f\u6c99\u6cb3\u5c6f"
    ],
    "wof:name":"Xiaoshahetun",
    "wof:placetype":"locality"
},
  "geometry": {"coordinates":[126.89685,42.47867],"type":"Point"}
}