{
  "type": "Feature",
  "properties": {
    "gn:admin1_code":"11.0",
    "gn:asciiname":"Tangchangpu",
    "gn:country_code":"CN",
    "gn:dem":248,
    "gn:feature_class":"P",
    "gn:feature_code":"PPL",
    "gn:name":"Tangchangpu",
    "gn:population":0,
    "gn:timezone":"Asia/Shanghai",
    "iso:country":"CN",
    "name:zho_x_preferred":[
        "\u5858\u660c\u94fa"
    ],
    "wof:name":"Tangchangpu",
    "wof:placetype":"locality"
},
  "geometry": {"coordinates":[112.92619999999999,25.77911],"type":"Point"}
}