{
  "type": "Feature",
  "properties": {
    "gn:admin1_code":"15.0",
    "gn:asciiname":"Xiayaoxian",
    "gn:country_code":"CN",
    "gn:dem":1412,
    "gn:feature_class":"P",
    "gn:feature_code":"PPL",
    "gn:name":"Xiayaoxian",
    "gn:population":0,
    "gn:timezone":"Asia/Shanghai",
    "iso:country":"CN",
    "name:und_x_variant":[
        "\u4e0b\u5d3e\u5c98"
    ],
    "wof:name":"Xiayaoxian",
    "wof:placetype":"locality"
},
  "geometry": {"coordinates":[107.34868,36.35942],"type":"Point"}
}