{
  "type": "Feature",
  "properties": {
    "gn:admin1_code":"23.0",
    "gn:asciiname":"Yongsheng",
    "gn:country_code":"CN",
    "gn:dem":4,
    "gn:feature_class":"P",
    "gn:feature_code":"PPL",
    "gn:name":"Yongsheng",
    "gn:population":0,
    "gn:timezone":"Asia/Shanghai",
    "iso:country":"CN",
    "name:und_x_variant":[
        "\u6c38\u80dc"
    ],
    "wof:name":"Yongsheng",
    "wof:placetype":"locality"
},
  "geometry": {"coordinates":[121.25388999999998,31.40243],"type":"Point"}
}