{
  "type": "Feature",
  "properties": {
    "gn:admin1_code":"12.0",
    "gn:asciiname":"Xiaolujiafan",
    "gn:country_code":"CN",
    "gn:dem":72,
    "gn:feature_class":"P",
    "gn:feature_code":"PPL",
    "gn:name":"Xiaolujiafan",
    "gn:population":0,
    "gn:timezone":"Asia/Shanghai",
    "iso:country":"CN",
    "name:zho_x_preferred":[
        "\u5c0f\u5362\u5bb6\u7548"
    ],
    "wof:name":"Xiaolujiafan",
    "wof:placetype":"locality"
},
  "geometry": {"coordinates":[112.08329999999999,31.84675],"type":"Point"}
}