{
  "type": "Feature",
  "properties": {
    "gn:admin1_code":"25.0",
    "gn:asciiname":"Nanwodaocun",
    "gn:country_code":"CN",
    "gn:dem":14,
    "gn:feature_class":"P",
    "gn:feature_code":"PPL",
    "gn:name":"Nanwodaocun",
    "gn:population":0,
    "gn:timezone":"Asia/Shanghai",
    "iso:country":"CN",
    "name:zho_x_preferred":[
        "\u5357\u6211\u5c9b\u6751"
    ],
    "wof:name":"Nanwodaocun",
    "wof:placetype":"locality"
},
  "geometry": {"coordinates":[122.58529,37.19495],"type":"Point"}
}