{
  "type": "Feature",
  "properties": {
    "gn:admin1_code":"7.0",
    "gn:asciiname":"Dayanli",
    "gn:country_code":"CN",
    "gn:dem":752,
    "gn:feature_class":"P",
    "gn:feature_code":"PPL",
    "gn:name":"Dayanli",
    "gn:population":0,
    "gn:timezone":"Asia/Shanghai",
    "iso:country":"CN",
    "name:und_x_variant":[
        "\u5927\u71d5\u91cc"
    ],
    "name:zho_x_preferred":[
        "\u5927\u71d5\u91cc"
    ],
    "wof:name":"Dayanli",
    "wof:placetype":"locality"
},
  "geometry": {"coordinates":[116.53111,26.01615],"type":"Point"}
}