{
  "type": "Feature",
  "properties": {
    "gn:admin1_code":"29.0",
    "gn:asciiname":"Songping",
    "gn:country_code":"CN",
    "gn:dem":1946,
    "gn:feature_class":"P",
    "gn:feature_code":"PPL",
    "gn:name":"Songping",
    "gn:population":0,
    "gn:timezone":"Asia/Shanghai",
    "iso:country":"CN",
    "name:zho_x_preferred":[
        "\u677e\u576a"
    ],
    "wof:name":"Songping",
    "wof:placetype":"locality"
},
  "geometry": {"coordinates":[100.919,26.2179],"type":"Point"}
}