{
  "type": "Feature",
  "properties": {
    "gn:admin1_code":"15.0",
    "gn:asciiname":"Chendong",
    "gn:country_code":"CN",
    "gn:dem":1725,
    "gn:feature_class":"P",
    "gn:feature_code":"PPL",
    "gn:name":"Chendong",
    "gn:population":0,
    "gn:timezone":"Asia/Shanghai",
    "iso:country":"CN",
    "name:und_x_variant":[
        "\u9648\u6d1e"
    ],
    "wof:name":"Chendong",
    "wof:placetype":"locality"
},
  "geometry": {"coordinates":[105.98797,35.19847],"type":"Point"}
}