{
  "type": "Feature",
  "properties": {
    "gn:admin1_code":"12.0",
    "gn:asciiname":"Henglubianzi",
    "gn:country_code":"CN",
    "gn:dem":1468,
    "gn:feature_class":"P",
    "gn:feature_code":"PPL",
    "gn:name":"Henglubianzi",
    "gn:population":0,
    "gn:timezone":"Asia/Shanghai",
    "iso:country":"CN",
    "name:zho_x_preferred":[
        "\u6a2a\u8def\u890a\u5b50"
    ],
    "wof:name":"Henglubianzi",
    "wof:placetype":"locality"
},
  "geometry": {"coordinates":[109.62414,33.22454],"type":"Point"}
}