{
  "type": "Feature",
  "properties": {
    "gn:admin1_code":"16.0",
    "gn:asciiname":"Duoliucun",
    "gn:country_code":"CN",
    "gn:dem":992,
    "gn:feature_class":"P",
    "gn:feature_code":"PPL",
    "gn:name":"Duoliucun",
    "gn:population":0,
    "gn:timezone":"Asia/Shanghai",
    "iso:country":"CN",
    "name:zho_x_preferred":[
        "\u591a\u516d\u6751"
    ],
    "wof:name":"Duoliucun",
    "wof:placetype":"locality"
},
  "geometry": {"coordinates":[106.46299999999999,23.5182],"type":"Point"}
}