{
  "type": "Feature",
  "properties": {
    "gn:admin1_code":"3",
    "gn:asciiname":"Guanqiao",
    "gn:country_code":"CN",
    "gn:dem":68,
    "gn:feature_class":"P",
    "gn:feature_code":"PPL",
    "gn:name":"Guanqiao",
    "gn:population":0,
    "gn:timezone":"Asia/Shanghai",
    "iso:country":"CN",
    "name:ceb_x_preferred":[
        "Guanqiao"
    ],
    "name:deu_x_preferred":[
        "Guanqiao"
    ],
    "name:swe_x_preferred":[
        "Guanqiao"
    ],
    "name:und_x_variant":[
        "\u5b98\u6865"
    ],
    "wof:name":"Guanqiao",
    "wof:placetype":"locality"
},
  "geometry": {"coordinates":[116.82221,27.98861],"type":"Point"}
}