{
  "type": "Feature",
  "properties": {
    "gn:admin1_code":"11.0",
    "gn:asciiname":"Laohugeng",
    "gn:country_code":"CN",
    "gn:dem":982,
    "gn:feature_class":"P",
    "gn:feature_code":"PPL",
    "gn:name":"Laohugeng",
    "gn:population":0,
    "gn:timezone":"Asia/Shanghai",
    "iso:country":"CN",
    "name:zho_x_preferred":[
        "\u8001\u864e\u57c2"
    ],
    "wof:name":"Laohugeng",
    "wof:placetype":"locality"
},
  "geometry": {"coordinates":[113.35905,25.44341],"type":"Point"}
}