{
  "type": "Feature",
  "properties": {
    "gn:admin1_code":"11.0",
    "gn:asciiname":"Xiaodong",
    "gn:country_code":"CN",
    "gn:dem":778,
    "gn:feature_class":"P",
    "gn:feature_code":"PPL",
    "gn:name":"Xiaodong",
    "gn:population":0,
    "gn:timezone":"Asia/Shanghai",
    "iso:country":"CN",
    "name:zho_x_preferred":[
        "\u785d\u6d1e"
    ],
    "wof:name":"Xiaodong",
    "wof:placetype":"locality"
},
  "geometry": {"coordinates":[109.4552,29.3563],"type":"Point"}
}