{
  "type": "Feature",
  "properties": {
    "gn:admin1_code":"21.0",
    "gn:asciiname":"Xiagan Goutan",
    "gn:country_code":"CN",
    "gn:dem":1809,
    "gn:feature_class":"P",
    "gn:feature_code":"PPL",
    "gn:name":"Xiagan Goutan",
    "gn:population":0,
    "gn:timezone":"Asia/Shanghai",
    "iso:country":"CN",
    "name:zho_x_preferred":[
        "\u4e0b\u7518\u6c9f\u6ee9"
    ],
    "wof:name":"Xiagan Goutan",
    "wof:placetype":"locality"
},
  "geometry": {"coordinates":[105.914,36.1843],"type":"Point"}
}