{
  "type": "Feature",
  "properties": {
    "gn:admin1_code":"11.0",
    "gn:asciiname":"Tianchong",
    "gn:country_code":"CN",
    "gn:dem":292,
    "gn:feature_class":"P",
    "gn:feature_code":"PPL",
    "gn:name":"Tianchong",
    "gn:population":0,
    "gn:timezone":"Asia/Shanghai",
    "iso:country":"CN",
    "name:zho_x_preferred":[
        "\u7530\u51b2"
    ],
    "wof:name":"Tianchong",
    "wof:placetype":"locality"
},
  "geometry": {"coordinates":[113.00162,25.44109],"type":"Point"}
}