{
  "type": "Feature",
  "properties": {
    "gn:admin1_code":"25.0",
    "gn:asciiname":"Dongyujiabu",
    "gn:country_code":"CN",
    "gn:dem":41,
    "gn:feature_class":"P",
    "gn:feature_code":"PPL",
    "gn:name":"Dongyujiabu",
    "gn:population":0,
    "gn:timezone":"Asia/Shanghai",
    "iso:country":"CN",
    "name:zho_x_preferred":[
        "\u4e1c\u4e8e\u5bb6\u57e0"
    ],
    "wof:name":"Dongyujiabu",
    "wof:placetype":"locality"
},
  "geometry": {"coordinates":[119.51197000000001,36.35541],"type":"Point"}
}