{
  "type": "Feature",
  "properties": {
    "gn:country":"CN",
    "gn:fcode":"PPL",
    "gn:pop":540,
    "iso:country":"CN",
    "qs:name":"Liujiading",
    "qs:photos_9r":0,
    "qs:photos_sr":0,
    "qs:pop_sr":"2",
    "wof:name":"Liujiading",
    "wof:placetype":"locality",
    "wof:population":540
},
  "geometry": {"coordinates":[117.19110999999999,39.96306],"type":"Point"}
}