{
  "type": "Feature",
  "properties": {
    "gn:admin1_code":"2.0",
    "gn:asciiname":"Xushanxia",
    "gn:country_code":"CN",
    "gn:dem":13,
    "gn:feature_class":"P",
    "gn:feature_code":"PPL",
    "gn:name":"Xushanxia",
    "gn:population":0,
    "gn:timezone":"Asia/Shanghai",
    "iso:country":"CN",
    "name:zho_x_preferred":[
        "\u5f90\u5c71\u4e0b"
    ],
    "wof:name":"Xushanxia",
    "wof:placetype":"locality"
},
  "geometry": {"coordinates":[120.28198,29.76966],"type":"Point"}
}