{
  "type": "Feature",
  "properties": {
    "gn:admin1_code":"02",
    "gn:asciiname":"Guancai'ao",
    "gn:country_code":"CN",
    "gn:dem":7,
    "gn:feature_class":"P",
    "gn:feature_code":"PPL",
    "gn:name":"Guancai\u2019ao",
    "gn:population":0,
    "gn:timezone":"Asia/Shanghai",
    "iso:country":"CN",
    "name:zho_x_preferred":[
        "\u5b98\u8d22\u5c99"
    ],
    "name:zho_x_variant":[
        "Guancai\u2019ao"
    ],
    "wof:name":"Guancai'ao",
    "wof:placetype":"locality"
},
  "geometry": {"coordinates":[121.06098,27.84852],"type":"Point"}
}