{
  "type": "Feature",
  "properties": {
    "gn:admin1_code":"16",
    "gn:asciiname":"Youzhugen",
    "gn:country_code":"CN",
    "gn:dem":932,
    "gn:feature_class":"P",
    "gn:feature_code":"PPL",
    "gn:name":"Youzhugen",
    "gn:population":0,
    "gn:timezone":"Asia/Shanghai",
    "iso:country":"CN",
    "name:zho_x_preferred":[
        "\u6cb9\u7af9\u6839"
    ],
    "wof:name":"Youzhugen",
    "wof:placetype":"locality"
},
  "geometry": {"coordinates":[110.791,25.2789],"type":"Point"}
}