{
  "type": "Feature",
  "properties": {
    "gn:country":"CN",
    "gn:fcode":"ADM3",
    "gn:pop":0,
    "iso:country":"CN",
    "name:ceb_x_preferred":[
        "L\u00fceyang Xian"
    ],
    "name:deu_x_preferred":[
        "L\u00fceyang"
    ],
    "name:eng_x_preferred":[
        "Lueyang County"
    ],
    "name:fas_x_preferred":[
        "\u0634\u0647\u0631\u0633\u062a\u0627\u0646 \u0644\u0648\u06cc\u0627\u0646\u06af"
    ],
    "name:gan_x_preferred":[
        "\u7565\u9633\u53bf"
    ],
    "name:jpn_x_preferred":[
        "\u7565\u967d\u770c"
    ],
    "name:kor_x_preferred":[
        "\ub920\uc591\ud604"
    ],
    "name:nan_x_preferred":[
        "Lio\u030dk-i\u00f4ng-ko\u0101n"
    ],
    "name:nld_x_preferred":[
        "L\u00fceyang"
    ],
    "name:nob_x_preferred":[
        "Lueyang"
    ],
    "name:rus_x_preferred":[
        "\u041b\u044e\u044d\u044f\u043d"
    ],
    "name:swe_x_preferred":[
        "L\u00fceyang"
    ],
    "name:unk_x_variant":[
        "L\u00fceh-yang Hsien"
    ],
    "name:vie_x_preferred":[
        "L\u01b0\u1ee3c D\u01b0\u01a1ng"
    ],
    "name:wuu_x_preferred":[
        "\u7565\u9633\u53bf"
    ],
    "name:yue_x_preferred":[
        "\u7565\u967d"
    ],
    "name:zho_x_preferred":[
        "\u7565\u9633\u53bf"
    ],
    "name:zho_x_variant":[
        "L\u00fceyang Xian",
        "\u7565\u9633"
    ],
    "qs:name":"L\u00fceyang Xian",
    "qs:photos_9r":0,
    "qs:photos_sr":0,
    "qs:pop_sr":"0",
    "wd:wordcount":35,
    "wof:name":"L\u00fceyang Xian",
    "wof:placetype":"localadmin",
    "wof:population":0
},
  "geometry": {"coordinates":[106.14833,33.39306],"type":"Point"}
}