{
  "type": "Feature",
  "properties": {
    "gn:country":"CN",
    "gn:fcode":"ADM3",
    "gn:pop":0,
    "iso:country":"CN",
    "name:unk_x_variant":[
        "L\u00fceh-yang Hsien"
    ],
    "name:zho_x_preferred":[
        "\u7565\u9633\u53bf"
    ],
    "name:zho_x_variant":[
        "L\u00fceyang Xian",
        "\u7565\u9633"
    ],
    "qs:name":"L\u00fceyang Xian",
    "qs:photos_9r":0,
    "qs:photos_sr":0,
    "qs:pop_sr":"0",
    "wd:wordcount":35,
    "wof:name":"L\u00fceyang Xian",
    "wof:placetype":"localadmin",
    "wof:population":0
},
  "geometry": {"coordinates":[106.14833,33.39306],"type":"Point"}
}