{
  "type": "Feature",
  "properties": {
    "gn:admin1_code":"25",
    "gn:asciiname":"Xiaogaizi",
    "gn:country_code":"CN",
    "gn:dem":47,
    "gn:feature_class":"P",
    "gn:feature_code":"PPL",
    "gn:name":"Xiaogaizi",
    "gn:population":0,
    "gn:timezone":"Asia/Shanghai",
    "iso:country":"CN",
    "name:zho_x_preferred":[
        "\u5c0f\u5793\u5b50"
    ],
    "wof:name":"Xiaogaizi",
    "wof:placetype":"locality"
},
  "geometry": {"coordinates":[115.834,35.3138],"type":"Point"}
}