{
  "type": "Feature",
  "properties": {
    "gn:admin1_code":"30.0",
    "gn:asciiname":"Xincun",
    "gn:country_code":"CN",
    "gn:dem":68,
    "gn:feature_class":"P",
    "gn:feature_code":"PPL",
    "gn:name":"Xincun",
    "gn:population":0,
    "gn:timezone":"Asia/Urumqi",
    "iso:country":"CN",
    "name:zho_x_preferred":[
        "\u65b0\u6751"
    ],
    "wof:name":"Xincun",
    "wof:placetype":"locality"
},
  "geometry": {"coordinates":[110.28017,20.60055],"type":"Point"}
}