{
  "type": "Feature",
  "properties": {
    "gn:admin1_code":"9.0",
    "gn:asciiname":"Donglonghua",
    "gn:country_code":"CN",
    "gn:dem":71,
    "gn:feature_class":"P",
    "gn:feature_code":"PPL",
    "gn:name":"Donglonghua",
    "gn:population":0,
    "gn:timezone":"Asia/Shanghai",
    "iso:country":"CN",
    "name:zho_x_preferred":[
        "\u4e1c\u9686\u5316"
    ],
    "wof:name":"Donglonghua",
    "wof:placetype":"locality"
},
  "geometry": {"coordinates":[114.44418,35.95579],"type":"Point"}
}