{
  "type": "Feature",
  "properties": {
    "gn:admin1_code":"09",
    "gn:asciiname":"Jiugongxian",
    "gn:cc2":"CN",
    "gn:country_code":"CN",
    "gn:dem":118,
    "gn:feature_class":"P",
    "gn:feature_code":"PPL",
    "gn:name":"Jiugongxian",
    "gn:population":0,
    "gn:timezone":"Asia/Shanghai",
    "iso:country":"CN",
    "name:und_x_variant":[
        "Kung",
        "Kung-hsien",
        "Chiu-kung-hsien",
        "Jiugongxian"
    ],
    "wof:name":"Jiugongxian",
    "wof:placetype":"locality"
},
  "geometry": {"coordinates":[113.05306000000002,34.79361],"type":"Point"}
}