{
  "type": "Feature",
  "properties": {
    "gn:admin1_code":"8.0",
    "gn:asciiname":"Songhonglutun",
    "gn:country_code":"CN",
    "gn:dem":194,
    "gn:feature_class":"P",
    "gn:feature_code":"PPL",
    "gn:name":"Songhonglutun",
    "gn:population":0,
    "gn:timezone":"Asia/Shanghai",
    "iso:country":"CN",
    "name:zho_x_preferred":[
        "\u5b8b\u6d2a\u5f55\u5c6f"
    ],
    "wof:name":"Songhonglutun",
    "wof:placetype":"locality"
},
  "geometry": {"coordinates":[126.68966,47.50216],"type":"Point"}
}