{
  "type": "Feature",
  "properties": {
    "gn:admin1_code":"4.0",
    "gn:asciiname":"Xialaohu",
    "gn:country_code":"CN",
    "gn:dem":8,
    "gn:feature_class":"P",
    "gn:feature_code":"PPL",
    "gn:name":"Xialaohu",
    "gn:population":0,
    "gn:timezone":"Asia/Shanghai",
    "iso:country":"CN",
    "name:zho_x_preferred":[
        "Xialaohu"
    ],
    "name:zho_x_variant":[
        "\u4e0b\u8001\u6e56"
    ],
    "wof:name":"Xialaohu",
    "wof:placetype":"locality"
},
  "geometry": {"coordinates":[119.13133000000001,34.01865],"type":"Point"}
}