{
  "type": "Feature",
  "properties": {
    "gn:admin1_code":"14.0",
    "gn:asciiname":"Bushengcaka",
    "gn:cc2":"CN",
    "gn:country_code":"CN",
    "gn:dem":4854,
    "gn:feature_class":"P",
    "gn:feature_code":"PPL",
    "gn:name":"Bush\u00eangcaka",
    "gn:population":0,
    "gn:timezone":"Asia/Shanghai",
    "iso:country":"CN",
    "name:mal_x_preferred":[
        "Bush\u00eangcaka"
    ],
    "name:msa_x_preferred":[
        "Bush\u00eangcaka"
    ],
    "name:und_x_variant":[
        "Pu-lan-cha-k\u2019a",
        "Purang Tsaka",
        "Bush\u00eangcaka"
    ],
    "wof:name":"Bushengcaka",
    "wof:placetype":"locality"
},
  "geometry": {"coordinates":[82.23333000000002,32.91667],"type":"Point"}
}