{
  "type": "Feature",
  "properties": {
    "gn:admin1_code":"2.0",
    "gn:asciiname":"Shijiadong",
    "gn:country_code":"CN",
    "gn:dem":66,
    "gn:feature_class":"P",
    "gn:feature_code":"PPL",
    "gn:name":"Shijiadong",
    "gn:population":0,
    "gn:timezone":"Asia/Shanghai",
    "iso:country":"CN",
    "name:zho_x_preferred":[
        "\u77f3\u7532\u6d1e"
    ],
    "wof:name":"Shijiadong",
    "wof:placetype":"locality"
},
  "geometry": {"coordinates":[119.82129,28.95009000000001],"type":"Point"}
}