{
  "type": "Feature",
  "properties": {
    "gn:admin1_code":"15.0",
    "gn:asciiname":"Xizhujiazhuang",
    "gn:country_code":"CN",
    "gn:dem":2127,
    "gn:feature_class":"P",
    "gn:feature_code":"PPL",
    "gn:name":"Xizhujiazhuang",
    "gn:population":0,
    "gn:timezone":"Asia/Shanghai",
    "iso:country":"CN",
    "name:zho_x_preferred":[
        "\u897f\u6731\u5bb6\u5e84"
    ],
    "wof:name":"Xizhujiazhuang",
    "wof:placetype":"locality"
},
  "geometry": {"coordinates":[100.502,38.5606],"type":"Point"}
}