{
  "type": "Feature",
  "properties": {
    "gn:admin1_code":"26.0",
    "gn:asciiname":"Biegaizigou",
    "gn:country_code":"CN",
    "gn:dem":1110,
    "gn:feature_class":"P",
    "gn:feature_code":"PPL",
    "gn:name":"Biegaizigou",
    "gn:population":0,
    "gn:timezone":"Asia/Shanghai",
    "iso:country":"CN",
    "name:zho_x_preferred":[
        "\u9cd6\u76d6\u5b50\u6c9f"
    ],
    "wof:name":"Biegaizigou",
    "wof:placetype":"locality"
},
  "geometry": {"coordinates":[110.33163999999999,34.43226],"type":"Point"}
}