{
  "type": "Feature",
  "properties": {
    "gn:admin1_code":"07",
    "gn:asciiname":"Lefeng",
    "gn:country_code":"CN",
    "gn:dem":74,
    "gn:feature_class":"P",
    "gn:feature_code":"PPL",
    "gn:name":"Lefeng",
    "gn:population":0,
    "gn:timezone":"Asia/Shanghai",
    "iso:country":"CN",
    "name:zho_x_preferred":[
        "\u4e50\u5cf0"
    ],
    "wof:name":"Lefeng",
    "wof:placetype":"locality"
},
  "geometry": {"coordinates":[118.55034000000001,25.2064],"type":"Point"}
}