{
  "type": "Feature",
  "properties": {
    "gn:admin1_code":"25",
    "gn:asciiname":"Yandian",
    "gn:cc2":"CN",
    "gn:country_code":"CN",
    "gn:dem":48,
    "gn:feature_class":"P",
    "gn:feature_code":"PPL",
    "gn:name":"Yandian",
    "gn:population":0,
    "gn:timezone":"Asia/Shanghai",
    "iso:country":"CN",
    "name:und_x_variant":[
        "Yen-ts\u2019un-tien",
        "Yandian"
    ],
    "wof:name":"Yandian",
    "wof:placetype":"locality"
},
  "geometry": {"coordinates":[116.64778,35.55583],"type":"Point"}
}