{
  "type": "Feature",
  "properties": {
    "gn:admin1_code":"11.0",
    "gn:asciiname":"Tianjiafang",
    "gn:country_code":"CN",
    "gn:dem":180,
    "gn:feature_class":"P",
    "gn:feature_code":"PPL",
    "gn:name":"Tianjiafang",
    "gn:population":0,
    "gn:timezone":"Asia/Shanghai",
    "iso:country":"CN",
    "name:zho_x_preferred":[
        "Tianjiafang"
    ],
    "name:zho_x_variant":[
        "\u7530\u5bb6\u574a"
    ],
    "wof:name":"Tianjiafang",
    "wof:placetype":"locality"
},
  "geometry": {"coordinates":[111.34961,29.7379],"type":"Point"}
}