{
  "type": "Feature",
  "properties": {
    "gn:admin1_code":"29.0",
    "gn:asciiname":"Yanhoutou",
    "gn:country_code":"CN",
    "gn:dem":2118,
    "gn:feature_class":"P",
    "gn:feature_code":"PPL",
    "gn:name":"Yanhoutou",
    "gn:population":0,
    "gn:timezone":"Asia/Shanghai",
    "iso:country":"CN",
    "name:zho_x_preferred":[
        "\u5ca9\u540e\u5934"
    ],
    "wof:name":"Yanhoutou",
    "wof:placetype":"locality"
},
  "geometry": {"coordinates":[104.02500000000001,26.2076],"type":"Point"}
}