{
  "type": "Feature",
  "properties": {
    "gn:admin1_code":"1.0",
    "gn:asciiname":"Tianmiaocun",
    "gn:country_code":"CN",
    "gn:dem":31,
    "gn:feature_class":"P",
    "gn:feature_code":"PPL",
    "gn:name":"Tianmiaocun",
    "gn:population":0,
    "gn:timezone":"Asia/Shanghai",
    "iso:country":"CN",
    "name:zho_x_preferred":[
        "\u7530\u5e99\u6751"
    ],
    "wof:name":"Tianmiaocun",
    "wof:placetype":"locality"
},
  "geometry": {"coordinates":[115.95801000000002,33.16002],"type":"Point"}
}