{
  "type": "Feature",
  "properties": {
    "gn:admin1_code":"25",
    "gn:asciiname":"Zhangjiaji",
    "gn:country_code":"CN",
    "gn:dem":22,
    "gn:feature_class":"P",
    "gn:feature_code":"PPL",
    "gn:name":"Zhangjiaji",
    "gn:population":0,
    "gn:timezone":"Asia/Shanghai",
    "iso:country":"CN",
    "name:zho_x_preferred":[
        "\u5f20\u5bb6\u96c6"
    ],
    "wof:name":"Zhangjiaji",
    "wof:placetype":"locality"
},
  "geometry": {"coordinates":[116.53682000000001,37.30043],"type":"Point"}
}