{
  "type": "Feature",
  "properties": {
    "gn:admin1_code":"20.0",
    "gn:asciiname":"Erlidihao",
    "gn:country_code":"CN",
    "gn:dem":1637,
    "gn:feature_class":"P",
    "gn:feature_code":"PPL",
    "gn:name":"Erlidihao",
    "gn:population":0,
    "gn:timezone":"Asia/Shanghai",
    "iso:country":"CN",
    "name:und_x_variant":[
        "\u4e8c\u91cc\u5730\u58d5"
    ],
    "wof:name":"Erlidihao",
    "wof:placetype":"locality"
},
  "geometry": {"coordinates":[109.7799,41.44734],"type":"Point"}
}