{
  "type": "Feature",
  "properties": {
    "gn:admin1_code":"26.0",
    "gn:asciiname":"Xianjincun",
    "gn:country_code":"CN",
    "gn:dem":1361,
    "gn:feature_class":"P",
    "gn:feature_code":"PPL",
    "gn:name":"Xianjincun",
    "gn:population":0,
    "gn:timezone":"Asia/Shanghai",
    "iso:country":"CN",
    "name:zho_x_preferred":[
        "\u5148\u8fdb\u6751"
    ],
    "wof:name":"Xianjincun",
    "wof:placetype":"locality"
},
  "geometry": {"coordinates":[107.82398000000001,37.7088],"type":"Point"}
}