{
  "type": "Feature",
  "properties": {
    "gn:admin1_code":"3.0",
    "gn:asciiname":"Shimenlou",
    "gn:country_code":"CN",
    "gn:dem":257,
    "gn:feature_class":"P",
    "gn:feature_code":"PPL",
    "gn:name":"Shimenlou",
    "gn:population":0,
    "gn:timezone":"Asia/Shanghai",
    "iso:country":"CN",
    "name:und_x_variant":[
        "\u77f3\u95e8\u697c"
    ],
    "wof:name":"Shimenlou",
    "wof:placetype":"locality"
},
  "geometry": {"coordinates":[115.72093999999998,24.82997],"type":"Point"}
}