{
  "type": "Feature",
  "properties": {
    "gn:admin1_code":"7",
    "gn:asciiname":"Shimenkeng",
    "gn:country_code":"CN",
    "gn:dem":986,
    "gn:feature_class":"P",
    "gn:feature_code":"PPL",
    "gn:name":"Shimenkeng",
    "gn:population":0,
    "gn:timezone":"Asia/Shanghai",
    "iso:country":"CN",
    "name:zho_x_preferred":[
        "\u77f3\u95e8\u5751"
    ],
    "wof:name":"Shimenkeng",
    "wof:placetype":"locality"
},
  "geometry": {"coordinates":[118.56064000000001,25.7232],"type":"Point"}
}