{
  "type": "Feature",
  "properties": {
    "gn:admin1_code":"3.0",
    "gn:asciiname":"Budekou",
    "gn:country_code":"CN",
    "gn:dem":110,
    "gn:feature_class":"P",
    "gn:feature_code":"PPL",
    "gn:name":"Budekou",
    "gn:population":0,
    "gn:timezone":"Asia/Shanghai",
    "iso:country":"CN",
    "name:zho_x_preferred":[
        "\u5e03\u5fb7\u53e3"
    ],
    "wof:name":"Budekou",
    "wof:placetype":"locality"
},
  "geometry": {"coordinates":[114.64100000000001,29.2142],"type":"Point"}
}