{
  "type": "Feature",
  "properties": {
    "gn:admin1_code":"19",
    "gn:asciiname":"Yongling",
    "gn:country_code":"CN",
    "gn:dem":271,
    "gn:feature_class":"P",
    "gn:feature_code":"PPLA4",
    "gn:name":"Yongling",
    "gn:population":0,
    "gn:timezone":"Asia/Shanghai",
    "iso:country":"CN",
    "name:deu_x_preferred":[
        "Yongling"
    ],
    "name:und_x_variant":[
        "Yunlin",
        "Yung-ling-kai",
        "Yung-ling",
        "Yung-ling-chieh",
        "Yongling",
        "\u6c38\u9675",
        "Yongling Zhen",
        "\u6c38\u9675\u9547"
    ],
    "wof:name":"Yongling",
    "wof:placetype":"locality"
},
  "geometry": {"coordinates":[124.82105,41.70804],"type":"Point"}
}