{
  "type": "Feature",
  "properties": {
    "gn:admin1_code":"32.0",
    "gn:asciiname":"Shangniuchang",
    "gn:country_code":"CN",
    "gn:dem":2849,
    "gn:feature_class":"P",
    "gn:feature_code":"PPLF",
    "gn:name":"Shangniuchang",
    "gn:population":0,
    "gn:timezone":"Asia/Shanghai",
    "iso:country":"CN",
    "name:zho_x_preferred":[
        "\u4e0a\u725b\u573a"
    ],
    "wof:name":"Shangniuchang",
    "wof:placetype":"locality"
},
  "geometry": {"coordinates":[103.80042,33.49953],"type":"Point"}
}