{
  "type": "Feature",
  "properties": {
    "gn:admin1_code":"10",
    "gn:asciiname":"Suqiao",
    "gn:cc2":"CN",
    "gn:country_code":"CN",
    "gn:dem":7,
    "gn:feature_class":"P",
    "gn:feature_code":"PPL",
    "gn:name":"Suqiao",
    "gn:population":0,
    "gn:timezone":"Asia/Shanghai",
    "iso:country":"CN",
    "name:und_x_variant":[
        "Su-ch\u2019iao",
        "Suqiao"
    ],
    "wof:name":"Suqiao",
    "wof:placetype":"locality"
},
  "geometry": {"coordinates":[116.48166999999999,39.03167],"type":"Point"}
}