{
  "type": "Feature",
  "properties": {
    "gn:admin1_code":"19.0",
    "gn:asciiname":"Shanqiantun",
    "gn:country_code":"CN",
    "gn:dem":128,
    "gn:feature_class":"P",
    "gn:feature_code":"PPL",
    "gn:name":"Shanqiantun",
    "gn:population":0,
    "gn:timezone":"Asia/Shanghai",
    "iso:country":"CN",
    "name:zho_x_preferred":[
        "\u5c71\u524d\u5c6f"
    ],
    "wof:name":"Shanqiantun",
    "wof:placetype":"locality"
},
  "geometry": {"coordinates":[124.205,43.0776],"type":"Point"}
}