{
  "type": "Feature",
  "properties": {
    "gn:admin1_code":"12.0",
    "gn:asciiname":"Shangchen",
    "gn:country_code":"CN",
    "gn:dem":55,
    "gn:feature_class":"P",
    "gn:feature_code":"PPL",
    "gn:name":"Shangchen",
    "gn:population":0,
    "gn:timezone":"Asia/Shanghai",
    "iso:country":"CN",
    "name:ara_x_preferred":[
        "\u0634\u0627\u0646\u063a\u0634\u0646"
    ],
    "name:fas_x_preferred":[
        "\u0634\u0627\u0646\u06af\u0686\u0646"
    ],
    "name:ind_x_preferred":[
        "Shangchen"
    ],
    "name:spa_x_preferred":[
        "Shangchen"
    ],
    "name:vie_x_preferred":[
        "Th\u01b0\u1ee3ng Tr\u1ea7n"
    ],
    "name:zho_x_preferred":[
        "Shangchen"
    ],
    "name:zho_x_variant":[
        "\u4e0a\u9648",
        "\u4e0a\u9648\u9057\u5740"
    ],
    "wof:name":"Shangchen",
    "wof:placetype":"locality"
},
  "geometry": {"coordinates":[115.30744,29.67887],"type":"Point"}
}