{
  "type": "Feature",
  "properties": {
    "gn:admin1_code":"19.0",
    "gn:asciiname":"Shatuguo",
    "gn:country_code":"CN",
    "gn:dem":21,
    "gn:feature_class":"P",
    "gn:feature_code":"PPL",
    "gn:name":"Shatuguo",
    "gn:population":0,
    "gn:timezone":"Asia/Shanghai",
    "iso:country":"CN",
    "name:zho_x_preferred":[
        "\u6c99\u571f\u56fd"
    ],
    "wof:name":"Shatuguo",
    "wof:placetype":"locality"
},
  "geometry": {"coordinates":[122.136,39.3799],"type":"Point"}
}