{
  "type": "Feature",
  "properties": {
    "gn:admin1_code":"24",
    "gn:asciiname":"Limin",
    "gn:country_code":"CN",
    "gn:dem":1688,
    "gn:feature_class":"P",
    "gn:feature_code":"PPLA4",
    "gn:name":"Limin",
    "gn:population":0,
    "gn:timezone":"Asia/Shanghai",
    "iso:country":"CN",
    "name:und_x_variant":[
        "Li-min-pao",
        "Limin",
        "\u5229\u6c11",
        "Limin Zhen",
        "\u5229\u6c11\u9547"
    ],
    "wof:name":"Limin",
    "wof:placetype":"locality"
},
  "geometry": {"coordinates":[112.12035,39.30777],"type":"Point"}
}