{
  "type": "Feature",
  "properties": {
    "gn:admin1_code":"3.0",
    "gn:asciiname":"Zhiyuankeng",
    "gn:country_code":"CN",
    "gn:dem":205,
    "gn:feature_class":"P",
    "gn:feature_code":"PPL",
    "gn:name":"Zhiyuankeng",
    "gn:population":0,
    "gn:timezone":"Asia/Shanghai",
    "iso:country":"CN",
    "name:und_x_variant":[
        "\u6b62\u6c85\u5751"
    ],
    "wof:name":"Zhiyuankeng",
    "wof:placetype":"locality"
},
  "geometry": {"coordinates":[114.84748999999999,27.58576],"type":"Point"}
}