{
  "type": "Feature",
  "properties": {
    "gn:admin1_code":"1.0",
    "gn:asciiname":"Tsin Kia Ching (historical)",
    "gn:country_code":"CN",
    "gn:dem":8,
    "gn:feature_class":"P",
    "gn:feature_code":"PPL",
    "gn:name":"Tsin Kia Ching (historical)",
    "gn:population":0,
    "gn:timezone":"Asia/Shanghai",
    "iso:country":"CN",
    "wof:name":"Tsin Kia Ching (historical)",
    "wof:placetype":"locality"
},
  "geometry": {"coordinates":[117.85532000000001,31.05014000000001],"type":"Point"}
}