{
  "type": "Feature",
  "properties": {
    "gn:admin1_code":"28",
    "gn:asciiname":"Bijiaquan",
    "gn:cc2":"CN",
    "gn:country_code":"CN",
    "gn:dem":1,
    "gn:feature_class":"P",
    "gn:feature_code":"PPL",
    "gn:name":"Bijiaquan",
    "gn:population":0,
    "gn:timezone":"Asia/Shanghai",
    "iso:country":"CN",
    "name:und_x_variant":[
        "Pi-chia-ch\u2019\u00fcan",
        "Bijiaquan"
    ],
    "wof:name":"Bijiaquan",
    "wof:placetype":"locality"
},
  "geometry": {"coordinates":[118.05,39.23333],"type":"Point"}
}