{
  "type": "Feature",
  "properties": {
    "gn:admin1_code":"3.0",
    "gn:asciiname":"Dingjiazhou",
    "gn:country_code":"CN",
    "gn:dem":451,
    "gn:feature_class":"P",
    "gn:feature_code":"PPL",
    "gn:name":"Dingjiazhou",
    "gn:population":0,
    "gn:timezone":"Asia/Shanghai",
    "iso:country":"CN",
    "name:und_x_variant":[
        "\u4e01\u5bb6\u6d32"
    ],
    "wof:name":"Dingjiazhou",
    "wof:placetype":"locality"
},
  "geometry": {"coordinates":[115.97022,27.31216],"type":"Point"}
}