{
  "type": "Feature",
  "properties": {
    "gn:admin1_code":"26.0",
    "gn:asciiname":"Baihuogou",
    "gn:country_code":"CN",
    "gn:dem":626,
    "gn:feature_class":"P",
    "gn:feature_code":"PPL",
    "gn:name":"Baihuogou",
    "gn:population":0,
    "gn:timezone":"Asia/Shanghai",
    "iso:country":"CN",
    "name:und_x_variant":[
        "\u767d\u706b\u6c9f"
    ],
    "wof:name":"Baihuogou",
    "wof:placetype":"locality"
},
  "geometry": {"coordinates":[107.49714,33.32565],"type":"Point"}
}