{
  "type": "Feature",
  "properties": {
    "gn:admin1_code":"7",
    "gn:asciiname":"Maodian",
    "gn:country_code":"CN",
    "gn:dem":309,
    "gn:feature_class":"P",
    "gn:feature_code":"PPL",
    "gn:name":"Maodian",
    "gn:population":0,
    "gn:timezone":"Asia/Shanghai",
    "iso:country":"CN",
    "name:und_x_variant":[
        "\u8305\u5e97"
    ],
    "wof:name":"Maodian",
    "wof:placetype":"locality"
},
  "geometry": {"coordinates":[116.98138,26.8474],"type":"Point"}
}