{
  "type": "Feature",
  "properties": {
    "gn:admin1_code":"5.0",
    "gn:asciiname":"Jinchengcun",
    "gn:country_code":"CN",
    "gn:dem":256,
    "gn:feature_class":"P",
    "gn:feature_code":"PPL",
    "gn:name":"Jinchengcun",
    "gn:population":0,
    "gn:timezone":"Asia/Shanghai",
    "iso:country":"CN",
    "name:zho_x_preferred":[
        "\u91d1\u57ce\u6751"
    ],
    "wof:name":"Jinchengcun",
    "wof:placetype":"locality"
},
  "geometry": {"coordinates":[129.81892999999999,43.29817],"type":"Point"}
}