{
  "type": "Feature",
  "properties": {
    "gn:admin1_code":"16",
    "gn:asciiname":"Pingman",
    "gn:country_code":"CN",
    "gn:dem":428,
    "gn:feature_class":"P",
    "gn:feature_code":"PPL",
    "gn:name":"Pingman",
    "gn:population":0,
    "gn:timezone":"Asia/Shanghai",
    "iso:country":"CN",
    "name:zho_x_preferred":[
        "\u5e73\u6162"
    ],
    "wof:name":"Pingman",
    "wof:placetype":"locality"
},
  "geometry": {"coordinates":[106.435,23.7204],"type":"Point"}
}