{
  "type": "Feature",
  "properties": {
    "gn:admin1_code":"14.0",
    "gn:asciiname":"Duimukangda",
    "gn:country_code":"CN",
    "gn:dem":4029,
    "gn:feature_class":"P",
    "gn:feature_code":"PPL",
    "gn:name":"Duimukangda",
    "gn:population":0,
    "gn:timezone":"Asia/Urumqi",
    "iso:country":"CN",
    "name:zho_x_preferred":[
        "\u5806\u6728\u5eb7\u8fbe"
    ],
    "wof:name":"Duimukangda",
    "wof:placetype":"locality"
},
  "geometry": {"coordinates":[92.55578,28.91905],"type":"Point"}
}