{
  "type": "Feature",
  "properties": {
    "gn:admin1_code":"30",
    "gn:asciiname":"Duanfen",
    "gn:country_code":"CN",
    "gn:dem":4,
    "gn:feature_class":"P",
    "gn:feature_code":"PPLA4",
    "gn:name":"Duanfen",
    "gn:population":0,
    "gn:timezone":"Asia/Shanghai",
    "iso:country":"CN",
    "name:und_x_variant":[
        "Tuan-fen",
        "Duanfen",
        "Duanfen Zhen",
        "\u7aef\u82ac\u9547"
    ],
    "name:zho_x_preferred":[
        "\u7aef\u82ac"
    ],
    "wof:name":"Duanfen",
    "wof:placetype":"locality"
},
  "geometry": {"coordinates":[112.75421,22.05852],"type":"Point"}
}