{
  "type": "Feature",
  "properties": {
    "gn:admin1_code":"4.0",
    "gn:asciiname":"Dongliu Xudai",
    "gn:country_code":"CN",
    "gn:dem":5,
    "gn:feature_class":"P",
    "gn:feature_code":"PPL",
    "gn:name":"Dongliu Xudai",
    "gn:population":0,
    "gn:timezone":"Asia/Shanghai",
    "iso:country":"CN",
    "name:zho_x_preferred":[
        "\u4e1c\u516d\u5729\u5788"
    ],
    "wof:name":"Dongliu Xudai",
    "wof:placetype":"locality"
},
  "geometry": {"coordinates":[120.3331,32.13089],"type":"Point"}
}