{
  "type": "Feature",
  "properties": {
    "gn:admin1_code":"9",
    "gn:asciiname":"Yaocaichang",
    "gn:country_code":"CN",
    "gn:dem":53,
    "gn:feature_class":"P",
    "gn:feature_code":"PPL",
    "gn:name":"Yaocaichang",
    "gn:population":0,
    "gn:timezone":"Asia/Shanghai",
    "iso:country":"CN",
    "name:zho_x_preferred":[
        "\u836f\u6750\u573a"
    ],
    "wof:name":"Yaocaichang",
    "wof:placetype":"locality"
},
  "geometry": {"coordinates":[115.297,34.1288],"type":"Point"}
}