{
  "type": "Feature",
  "properties": {
    "gn:admin1_code":"29.0",
    "gn:asciiname":"Mali",
    "gn:country_code":"CN",
    "gn:dem":1706,
    "gn:feature_class":"P",
    "gn:feature_code":"PPL",
    "gn:name":"Mali",
    "gn:population":0,
    "gn:timezone":"Asia/Shanghai",
    "iso:country":"CN",
    "name:zho_x_preferred":[
        "\u5417\u54e9"
    ],
    "wof:name":"Mali",
    "wof:placetype":"locality"
},
  "geometry": {"coordinates":[104.14400000000001,23.2099],"type":"Point"}
}