{
  "type": "Feature",
  "properties": {
    "gn:admin1_code":"19.0",
    "gn:asciiname":"Taishan",
    "gn:country_code":"CN",
    "gn:dem":84,
    "gn:feature_class":"P",
    "gn:feature_code":"PPL",
    "gn:name":"Taishan",
    "gn:population":0,
    "gn:timezone":"Asia/Shanghai",
    "iso:country":"CN",
    "name:ceb_x_preferred":[
        "Taishan"
    ],
    "name:deu_x_preferred":[
        "Taishan"
    ],
    "name:fra_x_preferred":[
        "Taishan"
    ],
    "name:mlg_x_preferred":[
        "Taishan"
    ],
    "name:nld_x_preferred":[
        "Taishan"
    ],
    "name:nor_x_preferred":[
        "Taishan"
    ],
    "name:pol_x_preferred":[
        "Taishan"
    ],
    "name:rus_x_preferred":[
        "\u0422\u0430\u0439\u0448\u0430\u043d\u044c"
    ],
    "name:zho_x_preferred":[
        "\u53f0\u5c71"
    ],
    "wof:name":"Taishan",
    "wof:placetype":"locality"
},
  "geometry": {"coordinates":[121.777,39.2054],"type":"Point"}
}