{
  "type": "Feature",
  "properties": {
    "gn:admin1_code":"11",
    "gn:asciiname":"Sanwumeikuang",
    "gn:country_code":"CN",
    "gn:dem":500,
    "gn:feature_class":"P",
    "gn:feature_code":"PPL",
    "gn:name":"Sanwumeikuang",
    "gn:population":0,
    "gn:timezone":"Asia/Shanghai",
    "iso:country":"CN",
    "wof:name":"Sanwumeikuang",
    "wof:placetype":"locality"
},
  "geometry": {"coordinates":[112.60666999999999,25.57528],"type":"Point"}
}