{
  "type": "Feature",
  "properties": {
    "gn:admin1_code":"26.0",
    "gn:asciiname":"Tianshan",
    "gn:country_code":"CN",
    "gn:dem":1380,
    "gn:feature_class":"P",
    "gn:feature_code":"PPL",
    "gn:name":"Tianshan",
    "gn:population":0,
    "gn:timezone":"Asia/Shanghai",
    "iso:country":"CN",
    "name:zho_x_preferred":[
        "\u7530\u5c71"
    ],
    "wof:name":"Tianshan",
    "wof:placetype":"locality"
},
  "geometry": {"coordinates":[109.30494,37.64786],"type":"Point"}
}