{
  "type": "Feature",
  "properties": {
    "gn:admin1_code":"15.0",
    "gn:asciiname":"Yujiacheng",
    "gn:country_code":"CN",
    "gn:dem":2011,
    "gn:feature_class":"P",
    "gn:feature_code":"PPL",
    "gn:name":"Yujiacheng",
    "gn:population":0,
    "gn:timezone":"Asia/Shanghai",
    "iso:country":"CN",
    "name:zho_x_preferred":[
        "\u4f59\u5bb6\u57ce"
    ],
    "wof:name":"Yujiacheng",
    "wof:placetype":"locality"
},
  "geometry": {"coordinates":[100.38800000000001,38.6513],"type":"Point"}
}