{
  "type": "Feature",
  "properties": {
    "gn:admin1_code":"26.0",
    "gn:asciiname":"Weizhoucun",
    "gn:country_code":"CN",
    "gn:dem":430,
    "gn:feature_class":"P",
    "gn:feature_code":"PPL",
    "gn:name":"Weizhoucun",
    "gn:population":0,
    "gn:timezone":"Asia/Shanghai",
    "iso:country":"CN",
    "name:zho_x_preferred":[
        "\u6e2d\u5dde\u6751"
    ],
    "wof:name":"Weizhoucun",
    "wof:placetype":"locality"
},
  "geometry": {"coordinates":[108.18111,34.20258],"type":"Point"}
}