{
  "type": "Feature",
  "properties": {
    "gn:admin1_code":"8.0",
    "gn:asciiname":"Xiaojia Wobu",
    "gn:country_code":"CN",
    "gn:dem":190,
    "gn:feature_class":"P",
    "gn:feature_code":"PPL",
    "gn:name":"Xiaojia Wobu",
    "gn:population":0,
    "gn:timezone":"Asia/Shanghai",
    "iso:country":"CN",
    "name:zho_x_preferred":[
        "\u8096\u5bb6\u7a9d\u5821"
    ],
    "wof:name":"Xiaojia Wobu",
    "wof:placetype":"locality"
},
  "geometry": {"coordinates":[127.19598000000001,44.75875],"type":"Point"}
}