{
  "type": "Feature",
  "properties": {
    "gn:admin1_code":"12.0",
    "gn:asciiname":"Fushui",
    "gn:country_code":"CN",
    "gn:dem":66,
    "gn:feature_class":"P",
    "gn:feature_code":"PPL",
    "gn:name":"Fushui",
    "gn:population":0,
    "gn:timezone":"Asia/Shanghai",
    "iso:country":"CN",
    "name:zho_x_preferred":[
        "Fushui"
    ],
    "name:zho_x_variant":[
        "\u5bcc\u6c34"
    ],
    "wof:name":"Fushui",
    "wof:placetype":"locality"
},
  "geometry": {"coordinates":[114.89395,29.70456],"type":"Point"}
}