{
  "type": "Feature",
  "properties": {
    "gn:admin1_code":"4.0",
    "gn:asciiname":"Suxucun",
    "gn:country_code":"CN",
    "gn:dem":21,
    "gn:feature_class":"P",
    "gn:feature_code":"PPL",
    "gn:name":"Suxucun",
    "gn:population":0,
    "gn:timezone":"Asia/Shanghai",
    "iso:country":"CN",
    "name:zho_x_preferred":[
        "\u82cf\u5729\u6751"
    ],
    "wof:name":"Suxucun",
    "wof:placetype":"locality"
},
  "geometry": {"coordinates":[118.27428999999999,33.8183],"type":"Point"}
}