{
  "type": "Feature",
  "properties": {
    "gn:admin1_code":"24.0",
    "gn:asciiname":"Mopangou",
    "gn:country_code":"CN",
    "gn:dem":1762,
    "gn:feature_class":"P",
    "gn:feature_code":"PPL",
    "gn:name":"Mopangou",
    "gn:population":0,
    "gn:timezone":"Asia/Shanghai",
    "iso:country":"CN",
    "name:zho_x_preferred":[
        "\u78e8\u76d8\u6c9f"
    ],
    "wof:name":"Mopangou",
    "wof:placetype":"locality"
},
  "geometry": {"coordinates":[112.27921000000001,38.50594],"type":"Point"}
}