{
  "type": "Feature",
  "properties": {
    "gn:admin1_code":"14.0",
    "gn:asciiname":"Wengmendaguo",
    "gn:country_code":"CN",
    "gn:dem":4217,
    "gn:feature_class":"P",
    "gn:feature_code":"PPL",
    "gn:name":"Wengmendaguo",
    "gn:population":0,
    "gn:timezone":"Asia/Urumqi",
    "iso:country":"CN",
    "name:zho_x_preferred":[
        "\u7fc1\u95e8\u8fbe\u679c"
    ],
    "wof:name":"Wengmendaguo",
    "wof:placetype":"locality"
},
  "geometry": {"coordinates":[94.5534,31.70139],"type":"Point"}
}