{
  "type": "Feature",
  "properties": {
    "gn:admin1_code":"25.0",
    "gn:asciiname":"Zuoshan",
    "gn:cc2":"CN",
    "gn:country_code":"CN",
    "gn:dem":31,
    "gn:feature_class":"P",
    "gn:feature_code":"PPL",
    "gn:name":"Zuoshan",
    "gn:population":0,
    "gn:timezone":"Asia/Shanghai",
    "iso:country":"CN",
    "name:und_x_variant":[
        "Tso-shan",
        "Chai-shan",
        "Tso-shan-chuang",
        "Tse-shan",
        "Zuoshan"
    ],
    "wof:name":"Zuoshan",
    "wof:placetype":"locality"
},
  "geometry": {"coordinates":[119.38861,36.57083],"type":"Point"}
}