{
  "type": "Feature",
  "properties": {
    "gn:admin1_code":"32.0",
    "gn:asciiname":"Qingchengshan",
    "gn:country_code":"CN",
    "gn:dem":701,
    "gn:feature_class":"P",
    "gn:feature_code":"PPL",
    "gn:name":"Qingchengshan",
    "gn:population":0,
    "gn:timezone":"Asia/Shanghai",
    "iso:country":"CN",
    "name:zho_x_preferred":[
        "\u9752\u57ce\u5c71"
    ],
    "wof:name":"Qingchengshan",
    "wof:placetype":"locality"
},
  "geometry": {"coordinates":[103.58414,30.89764000000001],"type":"Point"}
}