{
  "type": "Feature",
  "properties": {
    "gn:admin1_code":"13",
    "gn:asciiname":"Hongshanzui",
    "gn:country_code":"CN",
    "gn:dem":537,
    "gn:feature_class":"P",
    "gn:feature_code":"PPL",
    "gn:name":"Hongshanzui",
    "gn:population":0,
    "gn:timezone":"Asia/Urumqi",
    "iso:country":"CN",
    "name:und_x_variant":[
        "\u7ea2\u5c71\u5480"
    ],
    "wof:name":"Hongshanzui",
    "wof:placetype":"locality"
},
  "geometry": {"coordinates":[90.21297,42.94481],"type":"Point"}
}