{
  "type": "Feature",
  "properties": {
    "gn:admin1_code":"12.0",
    "gn:asciiname":"Songziya",
    "gn:country_code":"CN",
    "gn:dem":906,
    "gn:feature_class":"P",
    "gn:feature_code":"PPL",
    "gn:name":"Songziya",
    "gn:population":0,
    "gn:timezone":"Asia/Shanghai",
    "iso:country":"CN",
    "name:zho_x_preferred":[
        "Songziya"
    ],
    "name:zho_x_variant":[
        "\u5d69\u5b50\u57ad"
    ],
    "wof:name":"Songziya",
    "wof:placetype":"locality"
},
  "geometry": {"coordinates":[111.08414,30.81848],"type":"Point"}
}