{
  "type": "Feature",
  "properties": {
    "gn:admin1_code":"14",
    "gn:asciiname":"Lumai",
    "gn:country_code":"CN",
    "gn:dem":4354,
    "gn:feature_class":"P",
    "gn:feature_code":"PPL",
    "gn:name":"Lumai",
    "gn:population":0,
    "gn:timezone":"Asia/Urumqi",
    "iso:country":"CN",
    "name:bod_x_preferred":[
        "\u0f40\u0fb3\u0f74\u0f0b\u0f66\u0fa8\u0f51"
    ],
    "name:por_x_preferred":[
        "Lumai"
    ],
    "name:und_x_variant":[
        "Lumei"
    ],
    "name:zho_x_preferred":[
        "\u9c81\u9ea6"
    ],
    "name:zho_x_variant":[
        "\u8def\u7f8e"
    ],
    "wof:name":"Lumai",
    "wof:placetype":"locality"
},
  "geometry": {"coordinates":[91.21854,28.29531],"type":"Point"}
}