{
  "type": "Feature",
  "properties": {
    "gn:admin1_code":"3.0",
    "gn:asciiname":"Guoli",
    "gn:country_code":"CN",
    "gn:dem":15,
    "gn:feature_class":"P",
    "gn:feature_code":"PPL",
    "gn:name":"Guoli",
    "gn:population":0,
    "gn:timezone":"Asia/Shanghai",
    "iso:country":"CN",
    "name:ceb_x_preferred":[
        "Guoli"
    ],
    "name:swe_x_preferred":[
        "Guoli"
    ],
    "name:und_x_variant":[
        "\u57da\u91cc"
    ],
    "wof:name":"Guoli",
    "wof:placetype":"locality"
},
  "geometry": {"coordinates":[115.89854,29.05313],"type":"Point"}
}