{
  "type": "Feature",
  "properties": {
    "gn:admin1_code":"8.0",
    "gn:asciiname":"Yaowopengtun",
    "gn:country_code":"CN",
    "gn:dem":120,
    "gn:feature_class":"P",
    "gn:feature_code":"PPL",
    "gn:name":"Yaowopengtun",
    "gn:population":0,
    "gn:timezone":"Asia/Shanghai",
    "iso:country":"CN",
    "name:zho_x_preferred":[
        "\u8170\u7a9d\u68da\u5c6f"
    ],
    "wof:name":"Yaowopengtun",
    "wof:placetype":"locality"
},
  "geometry": {"coordinates":[127.69065000000001,45.89079],"type":"Point"}
}