{
  "type": "Feature",
  "properties": {
    "gn:admin1_code":"1.0",
    "gn:asciiname":"Tanlicun",
    "gn:country_code":"CN",
    "gn:dem":40,
    "gn:feature_class":"P",
    "gn:feature_code":"PPL",
    "gn:name":"Tanlicun",
    "gn:population":0,
    "gn:timezone":"Asia/Shanghai",
    "iso:country":"CN",
    "name:zho_x_preferred":[
        "\u8c08\u91cc\u6751"
    ],
    "wof:name":"Tanlicun",
    "wof:placetype":"locality"
},
  "geometry": {"coordinates":[119.38030999999999,31.00427],"type":"Point"}
}