{
  "type": "Feature",
  "properties": {
    "gn:admin1_code":"13.0",
    "gn:asciiname":"A'yi Take",
    "gn:country_code":"CN",
    "gn:dem":2235,
    "gn:feature_class":"P",
    "gn:feature_code":"PPLA4",
    "gn:name":"A\u2019yi Take",
    "gn:population":0,
    "gn:timezone":"Asia/Shanghai",
    "iso:country":"CN",
    "name:und_x_variant":[
        "A\u2019yi Take",
        "\u963f\u4f9d\u5854\u514b",
        "Oytar",
        "A\u2019yi Take Xiang",
        "\u963f\u4f9d\u5854\u514b\u4e61"
    ],
    "wof:name":"A'yi Take",
    "wof:placetype":"locality"
},
  "geometry": {"coordinates":[75.42783,38.95303],"type":"Point"}
}