{
  "type": "Feature",
  "properties": {
    "gn:admin1_code":"25.0",
    "gn:asciiname":"Ditouyuancun",
    "gn:country_code":"CN",
    "gn:dem":37,
    "gn:feature_class":"P",
    "gn:feature_code":"PPL",
    "gn:name":"Ditouyuancun",
    "gn:population":0,
    "gn:timezone":"Asia/Shanghai",
    "iso:country":"CN",
    "name:zho_x_preferred":[
        "\u5824\u5934\u8881\u6751"
    ],
    "wof:name":"Ditouyuancun",
    "wof:placetype":"locality"
},
  "geometry": {"coordinates":[115.92336,36.61666],"type":"Point"}
}