{
  "type": "Feature",
  "properties": {
    "gn:admin1_code":"6.0",
    "gn:asciiname":"Tuanguo",
    "gn:country_code":"CN",
    "gn:dem":2712,
    "gn:feature_class":"P",
    "gn:feature_code":"PPL",
    "gn:name":"Tuanguo",
    "gn:population":0,
    "gn:timezone":"Asia/Shanghai",
    "iso:country":"CN",
    "name:zho_x_preferred":[
        "\u56e2\u679c"
    ],
    "wof:name":"Tuanguo",
    "wof:placetype":"locality"
},
  "geometry": {"coordinates":[101.55016000000001,35.86378],"type":"Point"}
}