{
  "type": "Feature",
  "properties": {
    "gn:admin1_code":"13.0",
    "gn:asciiname":"Yalike",
    "gn:country_code":"CN",
    "gn:dem":1695,
    "gn:feature_class":"P",
    "gn:feature_code":"PPL",
    "gn:name":"Yalike",
    "gn:population":0,
    "gn:timezone":"Asia/Shanghai",
    "iso:country":"CN",
    "name:zho_x_preferred":[
        "\u4e9a\u529b\u514b"
    ],
    "wof:name":"Yalike",
    "wof:placetype":"locality"
},
  "geometry": {"coordinates":[78.54751999999998,37.26814],"type":"Point"}
}