{
  "type": "Feature",
  "properties": {
    "gn:admin1_code":"32.0",
    "gn:asciiname":"Daqing",
    "gn:country_code":"CN",
    "gn:dem":557,
    "gn:feature_class":"P",
    "gn:feature_code":"PPL",
    "gn:name":"Daqing",
    "gn:population":0,
    "gn:timezone":"Asia/Shanghai",
    "iso:country":"CN",
    "name:rus_x_preferred":[
        "\u0414\u0430\u0446\u0438\u043d"
    ],
    "name:zho_x_preferred":[
        "\u5927\u5e86"
    ],
    "wof:name":"Daqing",
    "wof:placetype":"locality"
},
  "geometry": {"coordinates":[106.14152,31.58051],"type":"Point"}
}