{
  "type": "Feature",
  "properties": {
    "gn:admin1_code":"11.0",
    "gn:asciiname":"Chusong",
    "gn:country_code":"CN",
    "gn:dem":549,
    "gn:feature_class":"P",
    "gn:feature_code":"PPL",
    "gn:name":"Chusong",
    "gn:population":0,
    "gn:timezone":"Asia/Shanghai",
    "iso:country":"CN",
    "name:zho_x_preferred":[
        "\u51fa\u677e"
    ],
    "wof:name":"Chusong",
    "wof:placetype":"locality"
},
  "geometry": {"coordinates":[109.02952000000001,27.15787000000001],"type":"Point"}
}