{
  "type": "Feature",
  "properties": {
    "gn:admin1_code":"32.0",
    "gn:asciiname":"Siping",
    "gn:country_code":"CN",
    "gn:dem":313,
    "gn:feature_class":"P",
    "gn:feature_code":"PPL",
    "gn:name":"Siping",
    "gn:population":0,
    "gn:timezone":"Asia/Shanghai",
    "iso:country":"CN",
    "name:ceb_x_preferred":[
        "Siping"
    ],
    "name:zho_x_preferred":[
        "\u56db\u576a"
    ],
    "wof:name":"Siping",
    "wof:placetype":"locality"
},
  "geometry": {"coordinates":[105.593,30.2606],"type":"Point"}
}