{
  "type": "Feature",
  "properties": {
    "gn:admin1_code":"29.0",
    "gn:asciiname":"Wenlin",
    "gn:country_code":"CN",
    "gn:dem":2273,
    "gn:feature_class":"P",
    "gn:feature_code":"PPL",
    "gn:name":"Wenlin",
    "gn:population":0,
    "gn:timezone":"Asia/Shanghai",
    "iso:country":"CN",
    "name:und_x_variant":[
        "\u6587\u6797"
    ],
    "wof:name":"Wenlin",
    "wof:placetype":"locality"
},
  "geometry": {"coordinates":[102.70989,25.74631],"type":"Point"}
}