{
  "type": "Feature",
  "properties": {
    "gn:admin1_code":"16.0",
    "gn:asciiname":"Balian",
    "gn:country_code":"CN",
    "gn:dem":86,
    "gn:feature_class":"P",
    "gn:feature_code":"PPL",
    "gn:name":"Balian",
    "gn:population":0,
    "gn:timezone":"Asia/Shanghai",
    "iso:country":"CN",
    "name:deu_x_preferred":[
        "Balian"
    ],
    "name:zho_x_preferred":[
        "\u516b\u8054"
    ],
    "wof:name":"Balian",
    "wof:placetype":"locality"
},
  "geometry": {"coordinates":[108.898,22.8793],"type":"Point"}
}