{
  "type": "Feature",
  "properties": {
    "gn:admin1_code":"15.0",
    "gn:asciiname":"Yuanzili",
    "gn:country_code":"CN",
    "gn:dem":1454,
    "gn:feature_class":"P",
    "gn:feature_code":"PPL",
    "gn:name":"Yuanzili",
    "gn:population":0,
    "gn:timezone":"Asia/Shanghai",
    "iso:country":"CN",
    "name:zho_x_preferred":[
        "\u9662\u5b50\u91cc"
    ],
    "wof:name":"Yuanzili",
    "wof:placetype":"locality"
},
  "geometry": {"coordinates":[106.35899999999999,34.1312],"type":"Point"}
}