{
  "type": "Feature",
  "properties": {
    "gn:admin1_code":"19.0",
    "gn:asciiname":"Liangjiazi",
    "gn:country_code":"CN",
    "gn:dem":86,
    "gn:feature_class":"P",
    "gn:feature_code":"PPLA4",
    "gn:name":"Liangjiazi",
    "gn:population":0,
    "gn:timezone":"Asia/Shanghai",
    "iso:country":"CN",
    "name:und_x_variant":[
        "Liangjiazi Xiang",
        "Liangjiazi"
    ],
    "name:zho_x_preferred":[
        "\u4e24\u5bb6\u5b50"
    ],
    "name:zho_x_variant":[
        "\u4e24\u5bb6\u5b50\u4e61"
    ],
    "wof:name":"Liangjiazi",
    "wof:placetype":"locality"
},
  "geometry": {"coordinates":[123.48538000000001,42.77835],"type":"Point"}
}