{
  "type": "Feature",
  "properties": {
    "gn:admin1_code":"14.0",
    "gn:asciiname":"Zhuricun",
    "gn:country_code":"CN",
    "gn:dem":4577,
    "gn:feature_class":"P",
    "gn:feature_code":"PPL",
    "gn:name":"Zhuricun",
    "gn:population":0,
    "gn:timezone":"Asia/Urumqi",
    "iso:country":"CN",
    "name:zho_x_preferred":[
        "\u73e0\u65e5\u6751"
    ],
    "wof:name":"Zhuricun",
    "wof:placetype":"locality"
},
  "geometry": {"coordinates":[92.8117,32.14613],"type":"Point"}
}