{
  "type": "Feature",
  "properties": {
    "gn:admin1_code":"14.0",
    "gn:asciiname":"Langzhang",
    "gn:country_code":"CN",
    "gn:dem":4328,
    "gn:feature_class":"P",
    "gn:feature_code":"PPL",
    "gn:name":"Langzhang",
    "gn:population":0,
    "gn:timezone":"Asia/Urumqi",
    "iso:country":"CN",
    "name:zho_x_preferred":[
        "\u6d6a\u7ae0"
    ],
    "wof:name":"Langzhang",
    "wof:placetype":"locality"
},
  "geometry": {"coordinates":[92.22114000000001,28.18536],"type":"Point"}
}