{
  "type": "Feature",
  "properties": {
    "gn:admin1_code":"15.0",
    "gn:asciiname":"Qingcaowan",
    "gn:country_code":"CN",
    "gn:dem":2007,
    "gn:feature_class":"P",
    "gn:feature_code":"PPL",
    "gn:name":"Qingcaowan",
    "gn:population":0,
    "gn:timezone":"Asia/Shanghai",
    "iso:country":"CN",
    "name:zho_x_preferred":[
        "\u9752\u8349\u6e7e"
    ],
    "wof:name":"Qingcaowan",
    "wof:placetype":"locality"
},
  "geometry": {"coordinates":[97.4104,39.8802],"type":"Point"}
}