{
  "type": "Feature",
  "properties": {
    "gn:admin1_code":"29.0",
    "gn:asciiname":"Damangwai",
    "gn:country_code":"CN",
    "gn:dem":1637,
    "gn:feature_class":"P",
    "gn:feature_code":"PPL",
    "gn:name":"Damangwai",
    "gn:population":0,
    "gn:timezone":"Asia/Shanghai",
    "iso:country":"CN",
    "name:zho_x_preferred":[
        "\u5927\u8292\u6b6a"
    ],
    "wof:name":"Damangwai",
    "wof:placetype":"locality"
},
  "geometry": {"coordinates":[100.191,22.0893],"type":"Point"}
}