{
  "type": "Feature",
  "properties": {
    "gn:admin1_code":"12",
    "gn:asciiname":"Hanyang",
    "gn:cc2":"CN",
    "gn:country_code":"CN",
    "gn:dem":37,
    "gn:feature_class":"P",
    "gn:feature_code":"PPL",
    "gn:name":"Hanyang",
    "gn:population":0,
    "gn:timezone":"Asia/Shanghai",
    "iso:country":"CN",
    "name:eng_x_historical":[
        "Hanyang Fu",
        "Walled City"
    ],
    "name:eng_x_preferred":[
        "Hanyang Fu"
    ],
    "name:eng_x_variant":[
        "Walled City"
    ],
    "name:und_x_variant":[
        "Han-yang-hsien",
        "Hanyang"
    ],
    "wof:name":"Hanyang",
    "wof:placetype":"locality"
},
  "geometry": {"coordinates":[114.26667,30.55],"type":"Point"}
}