{
  "type": "Feature",
  "properties": {
    "gn:admin1_code":"12",
    "gn:asciiname":"Hanyang",
    "gn:cc2":"CN",
    "gn:country_code":"CN",
    "gn:dem":37,
    "gn:feature_class":"P",
    "gn:feature_code":"PPL",
    "gn:name":"Hanyang",
    "gn:population":0,
    "gn:timezone":"Asia/Shanghai",
    "iso:country":"CN",
    "name:ceb_x_preferred":[
        "Hanyang District"
    ],
    "name:deu_x_preferred":[
        "Hanyang"
    ],
    "name:eng_x_historical":[
        "Hanyang Fu",
        "Walled City"
    ],
    "name:eng_x_preferred":[
        "Hanyang Fu"
    ],
    "name:eng_x_variant":[
        "Walled City"
    ],
    "name:eus_x_preferred":[
        "Hanyang Barrutia"
    ],
    "name:ita_x_preferred":[
        "Hanyang"
    ],
    "name:jpn_x_preferred":[
        "\u6f22\u967d\u533a"
    ],
    "name:kor_x_preferred":[
        "\ud55c\uc591\uad6c"
    ],
    "name:nor_x_preferred":[
        "Hanyang"
    ],
    "name:pol_x_preferred":[
        "Hanyang"
    ],
    "name:spa_x_preferred":[
        "Hanyang"
    ],
    "name:swe_x_preferred":[
        "Hanyang"
    ],
    "name:und_x_variant":[
        "Han-yang-hsien",
        "Hanyang"
    ],
    "name:vie_x_preferred":[
        "H\u00e1n D\u01b0\u01a1ng"
    ],
    "name:zho_x_preferred":[
        "\u6c49\u9633\u533a"
    ],
    "wof:name":"Hanyang",
    "wof:placetype":"locality"
},
  "geometry": {"coordinates":[114.26667,30.55],"type":"Point"}
}