{
  "type": "Feature",
  "properties": {
    "gn:admin1_code":"1.0",
    "gn:asciiname":"Yanyancun",
    "gn:country_code":"CN",
    "gn:dem":423,
    "gn:feature_class":"P",
    "gn:feature_code":"PPL",
    "gn:name":"Yanyancun",
    "gn:population":0,
    "gn:timezone":"Asia/Shanghai",
    "iso:country":"CN",
    "name:zho_x_preferred":[
        "\u71d5\u5ca9\u6751"
    ],
    "wof:name":"Yanyancun",
    "wof:placetype":"locality"
},
  "geometry": {"coordinates":[115.93644,31.29726],"type":"Point"}
}