{
  "type": "Feature",
  "properties": {
    "gn:admin1_code":"16.0",
    "gn:asciiname":"Yaneng",
    "gn:country_code":"CN",
    "gn:dem":459,
    "gn:feature_class":"P",
    "gn:feature_code":"PPL",
    "gn:name":"Yaneng",
    "gn:population":0,
    "gn:timezone":"Asia/Shanghai",
    "iso:country":"CN",
    "name:zho_x_preferred":[
        "\u7259\u80fd"
    ],
    "wof:name":"Yaneng",
    "wof:placetype":"locality"
},
  "geometry": {"coordinates":[107.23699999999999,24.8124],"type":"Point"}
}