{
  "type": "Feature",
  "properties": {
    "gn:admin1_code":"33",
    "gn:asciiname":"Jiaoshi",
    "gn:country_code":"CN",
    "gn:dem":610,
    "gn:feature_class":"P",
    "gn:feature_code":"PPLA4",
    "gn:name":"Jiaoshi",
    "gn:population":0,
    "gn:timezone":"Asia/Shanghai",
    "iso:country":"CN",
    "name:und_x_variant":[
        "Chiao-shih-pa",
        "Jiaoshi",
        "Jiaoshiba",
        "Jiaoshi Zhen"
    ],
    "name:zho_x_preferred":[
        "\u7126\u77f3"
    ],
    "name:zho_x_variant":[
        "\u7126\u77f3\u9547"
    ],
    "wof:name":"Jiaoshi",
    "wof:placetype":"locality"
},
  "geometry": {"coordinates":[107.5976,29.71607],"type":"Point"}
}