{
  "type": "Feature",
  "properties": {
    "gn:admin1_code":"16.0",
    "gn:asciiname":"Zhangkou",
    "gn:country_code":"CN",
    "gn:dem":201,
    "gn:feature_class":"P",
    "gn:feature_code":"PPL",
    "gn:name":"Zhangkou",
    "gn:population":0,
    "gn:timezone":"Asia/Shanghai",
    "iso:country":"CN",
    "name:zho_x_preferred":[
        "\u7ae0\u53e3"
    ],
    "wof:name":"Zhangkou",
    "wof:placetype":"locality"
},
  "geometry": {"coordinates":[109.622,25.3034],"type":"Point"}
}