{
  "type": "Feature",
  "properties": {
    "gn:admin1_code":"4.0",
    "gn:asciiname":"Detaicun",
    "gn:country_code":"CN",
    "gn:dem":20,
    "gn:feature_class":"P",
    "gn:feature_code":"PPL",
    "gn:name":"Detaicun",
    "gn:population":0,
    "gn:timezone":"Asia/Shanghai",
    "iso:country":"CN",
    "name:zho_x_preferred":[
        "\u5fb7\u592a\u6751"
    ],
    "wof:name":"Detaicun",
    "wof:placetype":"locality"
},
  "geometry": {"coordinates":[118.36468000000001,33.86688],"type":"Point"}
}