{
  "type": "Feature",
  "properties": {
    "gn:admin1_code":"26.0",
    "gn:asciiname":"Nianpanshi",
    "gn:country_code":"CN",
    "gn:dem":801,
    "gn:feature_class":"P",
    "gn:feature_code":"PPL",
    "gn:name":"Nianpanshi",
    "gn:population":0,
    "gn:timezone":"Asia/Shanghai",
    "iso:country":"CN",
    "name:zho_x_preferred":[
        "\u78be\u76d8\u77f3"
    ],
    "wof:name":"Nianpanshi",
    "wof:placetype":"locality"
},
  "geometry": {"coordinates":[109.06757,32.47152],"type":"Point"}
}