{
  "type": "Feature",
  "properties": {
    "gn:admin1_code":"25",
    "gn:asciiname":"Magezhuang",
    "gn:cc2":"CN",
    "gn:country_code":"CN",
    "gn:dem":82,
    "gn:feature_class":"P",
    "gn:feature_code":"PPL",
    "gn:name":"Magezhuang",
    "gn:population":0,
    "gn:timezone":"Asia/Shanghai",
    "iso:country":"CN",
    "name:und_x_variant":[
        "Ma-ko-chuang",
        "Magezhuang"
    ],
    "name:zho_x_preferred":[
        "\u9a6c\u6208\u5e84"
    ],
    "wof:name":"Magezhuang",
    "wof:placetype":"locality"
},
  "geometry": {"coordinates":[120.60083,36.86833],"type":"Point"}
}