{
  "type": "Feature",
  "properties": {
    "gn:admin1_code":"29.0",
    "gn:asciiname":"Xinlu",
    "gn:country_code":"CN",
    "gn:dem":2535,
    "gn:feature_class":"P",
    "gn:feature_code":"PPL",
    "gn:name":"Xinlu",
    "gn:population":0,
    "gn:timezone":"Asia/Shanghai",
    "iso:country":"CN",
    "name:zho_x_preferred":[
        "\u65b0\u7089"
    ],
    "wof:name":"Xinlu",
    "wof:placetype":"locality"
},
  "geometry": {"coordinates":[99.6092,25.011],"type":"Point"}
}