{
  "type": "Feature",
  "properties": {
    "gn:admin1_code":"19.0",
    "gn:asciiname":"Hanjiatuncun",
    "gn:country_code":"CN",
    "gn:dem":188,
    "gn:feature_class":"P",
    "gn:feature_code":"PPL",
    "gn:name":"Hanjiatuncun",
    "gn:population":0,
    "gn:timezone":"Asia/Shanghai",
    "iso:country":"CN",
    "name:zho_x_preferred":[
        "\u97e9\u5bb6\u5c6f\u6751"
    ],
    "wof:name":"Hanjiatuncun",
    "wof:placetype":"locality"
},
  "geometry": {"coordinates":[120.52500000000001,40.9843],"type":"Point"}
}