{
  "type": "Feature",
  "properties": {
    "gn:admin1_code":"11.0",
    "gn:asciiname":"Maogongqiao",
    "gn:country_code":"CN",
    "gn:dem":136,
    "gn:feature_class":"P",
    "gn:feature_code":"PPL",
    "gn:name":"Maogongqiao",
    "gn:population":0,
    "gn:timezone":"Asia/Shanghai",
    "iso:country":"CN",
    "name:zho_x_preferred":[
        "\u6bdb\u516c\u6865"
    ],
    "wof:name":"Maogongqiao",
    "wof:placetype":"locality"
},
  "geometry": {"coordinates":[112.14892,28.07677],"type":"Point"}
}