{
  "type": "Feature",
  "properties": {
    "gn:admin1_code":"24.0",
    "gn:asciiname":"Xiaowaqiu",
    "gn:country_code":"CN",
    "gn:dem":854,
    "gn:feature_class":"P",
    "gn:feature_code":"PPL",
    "gn:name":"Xiaowaqiu",
    "gn:population":0,
    "gn:timezone":"Asia/Shanghai",
    "iso:country":"CN",
    "name:zho_x_preferred":[
        "\u5c0f\u74e6\u90b1"
    ],
    "wof:name":"Xiaowaqiu",
    "wof:placetype":"locality"
},
  "geometry": {"coordinates":[113.86633,37.59611],"type":"Point"}
}