{
  "type": "Feature",
  "properties": {
    "gn:admin1_code":"10.0",
    "gn:asciiname":"Yinniudian",
    "gn:country_code":"CN",
    "gn:dem":6,
    "gn:feature_class":"P",
    "gn:feature_code":"PPL",
    "gn:name":"Yinniudian",
    "gn:population":0,
    "gn:timezone":"Asia/Shanghai",
    "iso:country":"CN",
    "name:zho_x_preferred":[
        "\u5591\u725b\u6dc0"
    ],
    "wof:name":"Yinniudian",
    "wof:placetype":"locality"
},
  "geometry": {"coordinates":[118.56723,39.36215],"type":"Point"}
}