{
  "type": "Feature",
  "properties": {
    "gn:admin1_code":"11.0",
    "gn:asciiname":"Bawanshan",
    "gn:country_code":"CN",
    "gn:dem":803,
    "gn:feature_class":"P",
    "gn:feature_code":"PPL",
    "gn:name":"Bawanshan",
    "gn:population":0,
    "gn:timezone":"Asia/Shanghai",
    "iso:country":"CN",
    "name:zho_x_preferred":[
        "\u516b\u4e07\u5c71"
    ],
    "wof:name":"Bawanshan",
    "wof:placetype":"locality"
},
  "geometry": {"coordinates":[110.62224000000001,26.40061],"type":"Point"}
}