{
  "type": "Feature",
  "properties": {
    "gn:admin1_code":"6.0",
    "gn:asciiname":"Kenaga",
    "gn:country_code":"CN",
    "gn:dem":2504,
    "gn:feature_class":"P",
    "gn:feature_code":"PPL",
    "gn:name":"Kenaga",
    "gn:population":0,
    "gn:timezone":"Asia/Shanghai",
    "iso:country":"CN",
    "name:und_x_variant":[
        "\u79d1\u90a3\u5c15"
    ],
    "wof:name":"Kenaga",
    "wof:placetype":"locality"
},
  "geometry": {"coordinates":[102.52708,35.93411],"type":"Point"}
}