{
  "type": "Feature",
  "properties": {
    "gn:admin1_code":"30",
    "gn:asciiname":"Yewuwo",
    "gn:country_code":"CN",
    "gn:dem":146,
    "gn:feature_class":"P",
    "gn:feature_code":"PPL",
    "gn:name":"Yewuwo",
    "gn:population":0,
    "gn:timezone":"Asia/Shanghai",
    "iso:country":"CN",
    "name:zho_x_preferred":[
        "\u53f6\u5c4b\u7a9d"
    ],
    "wof:name":"Yewuwo",
    "wof:placetype":"locality"
},
  "geometry": {"coordinates":[116.04864000000001,24.05017],"type":"Point"}
}