{
  "type": "Feature",
  "properties": {
    "gn:admin1_code":"19.0",
    "gn:asciiname":"Lalatuncun",
    "gn:country_code":"CN",
    "gn:dem":69,
    "gn:feature_class":"P",
    "gn:feature_code":"PPL",
    "gn:name":"Lalatuncun",
    "gn:population":0,
    "gn:timezone":"Asia/Shanghai",
    "iso:country":"CN",
    "name:zho_x_preferred":[
        "\u62c9\u62c9\u5c6f\u6751"
    ],
    "wof:name":"Lalatuncun",
    "wof:placetype":"locality"
},
  "geometry": {"coordinates":[121.16785,41.52829000000001],"type":"Point"}
}