{
  "type": "Feature",
  "properties": {
    "gn:admin1_code":"07",
    "gn:asciiname":"Houpu",
    "gn:country_code":"CN",
    "gn:dem":14,
    "gn:feature_class":"P",
    "gn:feature_code":"PPL",
    "gn:name":"Houpu",
    "gn:population":0,
    "gn:timezone":"Asia/Shanghai",
    "iso:country":"CN",
    "name:und_x_variant":[
        "Fashi",
        "Houpu"
    ],
    "name:zho_x_preferred":[
        "\u540e\u57d4"
    ],
    "wof:name":"Houpu",
    "wof:placetype":"locality"
},
  "geometry": {"coordinates":[118.64427000000001,24.87057],"type":"Point"}
}