{
  "type": "Feature",
  "properties": {
    "gn:admin1_code":"29.0",
    "gn:asciiname":"Lixianqing",
    "gn:country_code":"CN",
    "gn:dem":2635,
    "gn:feature_class":"P",
    "gn:feature_code":"PPL",
    "gn:name":"Lixianqing",
    "gn:population":0,
    "gn:timezone":"Asia/Shanghai",
    "iso:country":"CN",
    "name:zho_x_preferred":[
        "\u7acb\u8d24\u7b90"
    ],
    "wof:name":"Lixianqing",
    "wof:placetype":"locality"
},
  "geometry": {"coordinates":[100.136,26.4137],"type":"Point"}
}