{
  "type": "Feature",
  "properties": {
    "gn:admin1_code":"29.0",
    "gn:asciiname":"Lanchang",
    "gn:country_code":"CN",
    "gn:dem":1221,
    "gn:feature_class":"P",
    "gn:feature_code":"PPL",
    "gn:name":"Lanchang",
    "gn:population":0,
    "gn:timezone":"Asia/Shanghai",
    "iso:country":"CN",
    "name:msa_x_preferred":[
        "Lanchang"
    ],
    "name:zho_x_preferred":[
        "\u5170\u5382"
    ],
    "wof:name":"Lanchang",
    "wof:placetype":"locality"
},
  "geometry": {"coordinates":[103.98099999999999,27.7453],"type":"Point"}
}