{
  "type": "Feature",
  "properties": {
    "gn:admin1_code":"16.0",
    "gn:asciiname":"Xiangxian",
    "gn:cc2":"CN",
    "gn:country_code":"CN",
    "gn:dem":125,
    "gn:feature_class":"P",
    "gn:feature_code":"PPL",
    "gn:name":"Xiangxian",
    "gn:population":0,
    "gn:timezone":"Asia/Shanghai",
    "iso:country":"CN",
    "name:und_x_variant":[
        "Hsiang-hsien-hs\u00fc",
        "Hsiang-hsien",
        "Xiangxian"
    ],
    "wof:name":"Xiangxian",
    "wof:placetype":"locality"
},
  "geometry": {"coordinates":[108.68333,23.26667],"type":"Point"}
}