{
  "type": "Feature",
  "properties": {
    "gn:admin1_code":"29.0",
    "gn:asciiname":"Zanzu",
    "gn:country_code":"CN",
    "gn:dem":2020,
    "gn:feature_class":"P",
    "gn:feature_code":"PPL",
    "gn:name":"Zanzu",
    "gn:population":0,
    "gn:timezone":"Asia/Shanghai",
    "iso:country":"CN",
    "name:zho_x_preferred":[
        "\u54b1\u79df"
    ],
    "wof:name":"Zanzu",
    "wof:placetype":"locality"
},
  "geometry": {"coordinates":[100.932,25.1224],"type":"Point"}
}