{
  "type": "Feature",
  "properties": {
    "gn:admin1_code":"29.0",
    "gn:asciiname":"Dashantou",
    "gn:country_code":"CN",
    "gn:dem":1239,
    "gn:feature_class":"P",
    "gn:feature_code":"PPL",
    "gn:name":"Dashantou",
    "gn:population":0,
    "gn:timezone":"Asia/Shanghai",
    "iso:country":"CN",
    "name:zho_x_preferred":[
        "\u5927\u5c71\u5934"
    ],
    "wof:name":"Dashantou",
    "wof:placetype":"locality"
},
  "geometry": {"coordinates":[98.9203,24.794],"type":"Point"}
}