{
  "type": "Feature",
  "properties": {
    "gn:admin1_code":"32.0",
    "gn:asciiname":"Dezhizhai",
    "gn:country_code":"CN",
    "gn:dem":2502,
    "gn:feature_class":"P",
    "gn:feature_code":"PPL",
    "gn:name":"Dezhizhai",
    "gn:population":0,
    "gn:timezone":"Asia/Shanghai",
    "iso:country":"CN",
    "name:zho_x_preferred":[
        "\u5f97\u4e4b\u5be8"
    ],
    "wof:name":"Dezhizhai",
    "wof:placetype":"locality"
},
  "geometry": {"coordinates":[103.28,31.5888],"type":"Point"}
}