{
  "type": "Feature",
  "properties": {
    "gn:admin1_code":"31",
    "gn:asciiname":"Diaocai",
    "gn:country_code":"CN",
    "gn:dem":129,
    "gn:feature_class":"P",
    "gn:feature_code":"PPL",
    "gn:name":"Diaocai",
    "gn:population":0,
    "gn:timezone":"Asia/Shanghai",
    "iso:country":"CN",
    "name:und_x_variant":[
        "\u540a\u83dc"
    ],
    "wof:name":"Diaocai",
    "wof:placetype":"locality"
},
  "geometry": {"coordinates":[109.904,19.6134],"type":"Point"}
}