{
  "type": "Feature",
  "properties": {
    "gn:admin1_code":"15.0",
    "gn:asciiname":"Tudigou",
    "gn:country_code":"CN",
    "gn:dem":1565,
    "gn:feature_class":"P",
    "gn:feature_code":"PPL",
    "gn:name":"Tudigou",
    "gn:population":0,
    "gn:timezone":"Asia/Shanghai",
    "iso:country":"CN",
    "name:und_x_variant":[
        "\u571f\u5730\u6c9f"
    ],
    "name:zho_x_preferred":[
        "\u571f\u5730\u6c9f"
    ],
    "wof:name":"Tudigou",
    "wof:placetype":"locality"
},
  "geometry": {"coordinates":[105.08134,33.06432],"type":"Point"}
}