{
  "type": "Feature",
  "properties": {
    "gn:admin1_code":"30.0",
    "gn:asciiname":"Juntianwei",
    "gn:country_code":"CN",
    "gn:dem":367,
    "gn:feature_class":"P",
    "gn:feature_code":"PPL",
    "gn:name":"Juntianwei",
    "gn:population":0,
    "gn:timezone":"Asia/Shanghai",
    "iso:country":"CN",
    "name:zho_x_preferred":[
        "Juntianwei"
    ],
    "name:zho_x_variant":[
        "\u519b\u7530\u5c3e"
    ],
    "wof:name":"Juntianwei",
    "wof:placetype":"locality"
},
  "geometry": {"coordinates":[114.10198,24.02166],"type":"Point"}
}