{
  "type": "Feature",
  "properties": {
    "gn:admin1_code":"10.0",
    "gn:asciiname":"Shenjia'an",
    "gn:country_code":"CN",
    "gn:dem":127,
    "gn:feature_class":"P",
    "gn:feature_code":"PPL",
    "gn:name":"Shenjia\u2019an",
    "gn:population":0,
    "gn:timezone":"Asia/Shanghai",
    "iso:country":"CN",
    "name:und_x_variant":[
        "Shenjia\u2019an"
    ],
    "name:zho_x_preferred":[
        "\u6c88\u5bb6\u5eb5"
    ],
    "wof:name":"Shenjia'an",
    "wof:placetype":"locality"
},
  "geometry": {"coordinates":[115.67677,39.59482],"type":"Point"}
}