{
  "type": "Feature",
  "properties": {
    "gn:admin1_code":"25",
    "gn:asciiname":"Beiliu Zhaizi",
    "gn:country_code":"CN",
    "gn:dem":44,
    "gn:feature_class":"P",
    "gn:feature_code":"PPL",
    "gn:name":"Beiliu Zhaizi",
    "gn:population":0,
    "gn:timezone":"Asia/Shanghai",
    "iso:country":"CN",
    "name:zho_x_preferred":[
        "\u5317\u5218\u5b85\u5b50"
    ],
    "wof:name":"Beiliu Zhaizi",
    "wof:placetype":"locality"
},
  "geometry": {"coordinates":[118.254,34.7391],"type":"Point"}
}