{
  "type": "Feature",
  "properties": {
    "gn:admin1_code":"8.0",
    "gn:asciiname":"Shaodiancun",
    "gn:country_code":"CN",
    "gn:dem":58,
    "gn:feature_class":"P",
    "gn:feature_code":"PPL",
    "gn:name":"Shaodiancun",
    "gn:population":0,
    "gn:timezone":"Asia/Shanghai",
    "iso:country":"CN",
    "name:zho_x_preferred":[
        "\u90b5\u5e97\u6751"
    ],
    "wof:name":"Shaodiancun",
    "wof:placetype":"locality"
},
  "geometry": {"coordinates":[132.12190000000001,47.31578],"type":"Point"}
}