{
  "type": "Feature",
  "properties": {
    "gn:admin1_code":"9.0",
    "gn:asciiname":"Zhuyaozhuang",
    "gn:country_code":"CN",
    "gn:dem":74,
    "gn:feature_class":"P",
    "gn:feature_code":"PPL",
    "gn:name":"Zhuyaozhuang",
    "gn:population":0,
    "gn:timezone":"Asia/Shanghai",
    "iso:country":"CN",
    "name:zho_x_preferred":[
        "\u6731\u8170\u5e84"
    ],
    "wof:name":"Zhuyaozhuang",
    "wof:placetype":"locality"
},
  "geometry": {"coordinates":[114.41567999999999,32.53681],"type":"Point"}
}