{
  "type": "Feature",
  "properties": {
    "gn:admin1_code":"32.0",
    "gn:asciiname":"Fuxingchang",
    "gn:country_code":"CN",
    "gn:dem":494,
    "gn:feature_class":"P",
    "gn:feature_code":"PPL",
    "gn:name":"Fuxingchang",
    "gn:population":0,
    "gn:timezone":"Asia/Shanghai",
    "iso:country":"CN",
    "name:zho_x_preferred":[
        "\u590d\u5174\u573a"
    ],
    "wof:name":"Fuxingchang",
    "wof:placetype":"locality"
},
  "geometry": {"coordinates":[103.80762,30.5672],"type":"Point"}
}