{
  "type": "Feature",
  "properties": {
    "gn:admin1_code":"9.0",
    "gn:asciiname":"Yanshouli",
    "gn:country_code":"CN",
    "gn:dem":81,
    "gn:feature_class":"P",
    "gn:feature_code":"PPL",
    "gn:name":"Yanshouli",
    "gn:population":0,
    "gn:timezone":"Asia/Shanghai",
    "iso:country":"CN",
    "name:zho_x_preferred":[
        "\u5ef6\u5bff\u674e"
    ],
    "wof:name":"Yanshouli",
    "wof:placetype":"locality"
},
  "geometry": {"coordinates":[113.56206,33.81537],"type":"Point"}
}