{
  "type": "Feature",
  "properties": {
    "gn:admin1_code":"32.0",
    "gn:asciiname":"Deda Muye",
    "gn:country_code":"CN",
    "gn:dem":4268,
    "gn:feature_class":"P",
    "gn:feature_code":"PPLF",
    "gn:name":"Deda Muye",
    "gn:population":0,
    "gn:timezone":"Asia/Shanghai",
    "iso:country":"CN",
    "name:zho_x_preferred":[
        "\u5fb7\u8fbe\u7267\u4e1a"
    ],
    "wof:name":"Deda Muye",
    "wof:placetype":"locality"
},
  "geometry": {"coordinates":[99.7011,30.2605],"type":"Point"}
}