{
  "type": "Feature",
  "properties": {
    "gn:admin1_code":"12.0",
    "gn:asciiname":"Qianjingping",
    "gn:country_code":"CN",
    "gn:dem":631,
    "gn:feature_class":"P",
    "gn:feature_code":"PPL",
    "gn:name":"Qianjingping",
    "gn:population":0,
    "gn:timezone":"Asia/Shanghai",
    "iso:country":"CN",
    "name:zho_x_preferred":[
        "Qianjingping"
    ],
    "name:zho_x_variant":[
        "\u8c26\u656c\u576a"
    ],
    "wof:name":"Qianjingping",
    "wof:placetype":"locality"
},
  "geometry": {"coordinates":[111.01018999999999,30.07707000000001],"type":"Point"}
}