{
  "type": "Feature",
  "properties": {
    "gn:admin1_code":"26.0",
    "gn:asciiname":"Zhuangfang",
    "gn:country_code":"CN",
    "gn:dem":1373,
    "gn:feature_class":"P",
    "gn:feature_code":"PPL",
    "gn:name":"Zhuangfang",
    "gn:population":0,
    "gn:timezone":"Asia/Shanghai",
    "iso:country":"CN",
    "name:zho_x_preferred":[
        "\u5e84\u623f"
    ],
    "wof:name":"Zhuangfang",
    "wof:placetype":"locality"
},
  "geometry": {"coordinates":[108.42131999999999,33.22028],"type":"Point"}
}