{
  "type": "Feature",
  "properties": {
    "gn:admin1_code":"4.0",
    "gn:asciiname":"Houqiaotou",
    "gn:country_code":"CN",
    "gn:dem":3,
    "gn:feature_class":"P",
    "gn:feature_code":"PPL",
    "gn:name":"Houqiaotou",
    "gn:population":0,
    "gn:timezone":"Asia/Shanghai",
    "iso:country":"CN",
    "name:und_x_variant":[
        "\u540e\u6865\u5934"
    ],
    "name:zho_x_preferred":[
        "\u540e\u6865\u5934"
    ],
    "wof:name":"Houqiaotou",
    "wof:placetype":"locality"
},
  "geometry": {"coordinates":[119.93953999999999,31.71726],"type":"Point"}
}