{
  "type": "Feature",
  "properties": {
    "gn:admin1_code":"10.0",
    "gn:asciiname":"Cheye Xinzhuang",
    "gn:country_code":"CN",
    "gn:dem":1080,
    "gn:feature_class":"P",
    "gn:feature_code":"PPL",
    "gn:name":"Cheye Xinzhuang",
    "gn:population":0,
    "gn:timezone":"Asia/Shanghai",
    "iso:country":"CN",
    "name:zho_x_preferred":[
        "\u626f\u4e1a\u8f9b\u5e84"
    ],
    "wof:name":"Cheye Xinzhuang",
    "wof:placetype":"locality"
},
  "geometry": {"coordinates":[115.00691999999999,40.02107],"type":"Point"}
}