{
  "type": "Feature",
  "properties": {
    "gn:admin1_code":"30.0",
    "gn:asciiname":"Yanzishui",
    "gn:country_code":"CN",
    "gn:dem":211,
    "gn:feature_class":"P",
    "gn:feature_code":"PPL",
    "gn:name":"Yanzishui",
    "gn:population":0,
    "gn:timezone":"Asia/Shanghai",
    "iso:country":"CN",
    "name:zho_x_preferred":[
        "\u71d5\u5b50\u6c34"
    ],
    "wof:name":"Yanzishui",
    "wof:placetype":"locality"
},
  "geometry": {"coordinates":[111.80025999999999,22.72943],"type":"Point"}
}