{
  "type": "Feature",
  "properties": {
    "gn:admin1_code":"11.0",
    "gn:asciiname":"Baiyanling",
    "gn:country_code":"CN",
    "gn:dem":922,
    "gn:feature_class":"P",
    "gn:feature_code":"PPL",
    "gn:name":"Baiyanling",
    "gn:population":0,
    "gn:timezone":"Asia/Shanghai",
    "iso:country":"CN",
    "name:zho_x_preferred":[
        "\u767d\u5ca9\u5cad"
    ],
    "wof:name":"Baiyanling",
    "wof:placetype":"locality"
},
  "geometry": {"coordinates":[110.03667,26.30223],"type":"Point"}
}