{
  "type": "Feature",
  "properties": {
    "gn:admin1_code":"31",
    "gn:asciiname":"Shilu",
    "gn:country_code":"CN",
    "gn:dem":89,
    "gn:feature_class":"P",
    "gn:feature_code":"PPLA3",
    "gn:name":"Shilu",
    "gn:population":0,
    "gn:timezone":"Asia/Shanghai",
    "iso:country":"CN",
    "name:und_x_variant":[
        "Changjiang",
        "Shih-lu",
        "Ch\u2019ang-chiang",
        "Shih-liu",
        "Shih-lu-chen",
        "Shih-lu-ling",
        "Shiliu",
        "Shilu",
        "\u77f3\u788c",
        "Changjiang Lizu Zizhi Xian",
        "Shilu Zhen",
        "\u660c\u6c5f\u9ece\u65cf\u81ea\u6cbb\u53bf"
    ],
    "name:zho_x_preferred":[
        "\u77f3\u788c\u9547"
    ],
    "wof:name":"Shilu",
    "wof:placetype":"locality"
},
  "geometry": {"coordinates":[109.04883999999998,19.25984],"type":"Point"}
}