{
  "type": "Feature",
  "properties": {
    "gn:admin1_code":"11",
    "gn:asciiname":"Gaoping",
    "gn:country_code":"CN",
    "gn:dem":1103,
    "gn:feature_class":"P",
    "gn:feature_code":"PPL",
    "gn:name":"Gaoping",
    "gn:population":0,
    "gn:timezone":"Asia/Shanghai",
    "iso:country":"CN",
    "wof:name":"Gaoping",
    "wof:placetype":"locality"
},
  "geometry": {"coordinates":[110.79361000000002,27.75306],"type":"Point"}
}