{
  "type": "Feature",
  "properties": {
    "gn:admin1_code":"24",
    "gn:asciiname":"Huagetuo",
    "gn:country_code":"CN",
    "gn:dem":1325,
    "gn:feature_class":"P",
    "gn:feature_code":"PPL",
    "gn:name":"Huagetuo",
    "gn:population":0,
    "gn:timezone":"Asia/Shanghai",
    "iso:country":"CN",
    "name:und_x_variant":[
        "Hua-ko-she",
        "Hua-ko-t\u2019o",
        "Huagetuo",
        "\u82b1\u572a\u5768"
    ],
    "wof:name":"Huagetuo",
    "wof:placetype":"locality"
},
  "geometry": {"coordinates":[112.57474000000001,39.48414],"type":"Point"}
}