{
  "type": "Feature",
  "properties": {
    "gn:admin1_code":"15.0",
    "gn:asciiname":"Leijiadun",
    "gn:country_code":"CN",
    "gn:dem":1134,
    "gn:feature_class":"P",
    "gn:feature_code":"PPL",
    "gn:name":"Leijiadun",
    "gn:population":0,
    "gn:timezone":"Asia/Urumqi",
    "iso:country":"CN",
    "name:zho_x_preferred":[
        "\u96f7\u5bb6\u58a9"
    ],
    "wof:name":"Leijiadun",
    "wof:placetype":"locality"
},
  "geometry": {"coordinates":[94.6887,40.1674],"type":"Point"}
}