{
  "type": "Feature",
  "properties": {
    "gn:admin1_code":"16.0",
    "gn:asciiname":"Gupichong",
    "gn:country_code":"CN",
    "gn:dem":259,
    "gn:feature_class":"P",
    "gn:feature_code":"PPL",
    "gn:name":"Gupichong",
    "gn:population":0,
    "gn:timezone":"Asia/Shanghai",
    "iso:country":"CN",
    "name:zho_x_preferred":[
        "\u53e4\u76ae\u51b2"
    ],
    "wof:name":"Gupichong",
    "wof:placetype":"locality"
},
  "geometry": {"coordinates":[110.39,24.3193],"type":"Point"}
}