{
  "type": "Feature",
  "properties": {
    "gn:admin1_code":"21.0",
    "gn:asciiname":"Yongfengtan",
    "gn:country_code":"CN",
    "gn:dem":1214,
    "gn:feature_class":"P",
    "gn:feature_code":"PPL",
    "gn:name":"Yongfengtan",
    "gn:population":0,
    "gn:timezone":"Asia/Shanghai",
    "iso:country":"CN",
    "name:zho_x_preferred":[
        "\u6c38\u4e30\u6ee9"
    ],
    "wof:name":"Yongfengtan",
    "wof:placetype":"locality"
},
  "geometry": {"coordinates":[105.316,37.4815],"type":"Point"}
}