{
  "type": "Feature",
  "properties": {
    "gn:admin1_code":"2.0",
    "gn:asciiname":"Shangguanyuan",
    "gn:country_code":"CN",
    "gn:dem":212,
    "gn:feature_class":"P",
    "gn:feature_code":"PPL",
    "gn:name":"Shangguanyuan",
    "gn:population":0,
    "gn:timezone":"Asia/Shanghai",
    "iso:country":"CN",
    "name:zho_x_preferred":[
        "\u4e0a\u5b98\u6e90"
    ],
    "wof:name":"Shangguanyuan",
    "wof:placetype":"locality"
},
  "geometry": {"coordinates":[118.61754999999999,29.40219],"type":"Point"}
}