{
  "type": "Feature",
  "properties": {
    "gn:admin1_code":"31.0",
    "gn:asciiname":"Zhubijiang Nongchang Wudui",
    "gn:country_code":"CN",
    "gn:dem":126,
    "gn:feature_class":"P",
    "gn:feature_code":"PPLF",
    "gn:name":"Zhubijiang Nongchang Wudui",
    "gn:population":0,
    "gn:timezone":"Asia/Shanghai",
    "iso:country":"CN",
    "name:und_x_variant":[
        "\u73e0\u78a7\u6c5f\u519c\u573a\u4e94 \u961f"
    ],
    "wof:name":"Zhubijiang Nongchang Wudui",
    "wof:placetype":"locality"
},
  "geometry": {"coordinates":[109.30645,19.38441],"type":"Point"}
}