{
  "type": "Feature",
  "properties": {
    "gn:admin1_code":"12.0",
    "gn:asciiname":"Shangchen",
    "gn:country_code":"CN",
    "gn:dem":206,
    "gn:feature_class":"P",
    "gn:feature_code":"PPL",
    "gn:name":"Shangchen",
    "gn:population":0,
    "gn:timezone":"Asia/Shanghai",
    "iso:country":"CN",
    "name:zho_x_preferred":[
        "Shangchen"
    ],
    "name:zho_x_variant":[
        "\u4e0a\u9648"
    ],
    "wof:name":"Shangchen",
    "wof:placetype":"locality"
},
  "geometry": {"coordinates":[114.66318,29.44761],"type":"Point"}
}