{
  "type": "Feature",
  "properties": {
    "gn:admin1_code":"8.0",
    "gn:asciiname":"Hualicun",
    "gn:country_code":"CN",
    "gn:dem":146,
    "gn:feature_class":"P",
    "gn:feature_code":"PPL",
    "gn:name":"Hualicun",
    "gn:population":0,
    "gn:timezone":"Asia/Shanghai",
    "iso:country":"CN",
    "name:zho_x_preferred":[
        "\u82b1\u529b\u6751"
    ],
    "wof:name":"Hualicun",
    "wof:placetype":"locality"
},
  "geometry": {"coordinates":[123.94419000000001,47.25963],"type":"Point"}
}