{
  "type": "Feature",
  "properties": {
    "gn:admin1_code":"16.0",
    "gn:asciiname":"Lajia",
    "gn:country_code":"CN",
    "gn:dem":676,
    "gn:feature_class":"P",
    "gn:feature_code":"PPL",
    "gn:name":"Lajia",
    "gn:population":0,
    "gn:timezone":"Asia/Shanghai",
    "iso:country":"CN",
    "name:cat_x_preferred":[
        "Lajia"
    ],
    "name:dan_x_preferred":[
        "Lajia"
    ],
    "name:deu_x_preferred":[
        "Lajia"
    ],
    "name:fra_x_preferred":[
        "Lajia"
    ],
    "name:hun_x_preferred":[
        "Lacsia"
    ],
    "name:jpn_x_preferred":[
        "\u5587\u5bb6\u907a\u8de1"
    ],
    "name:lat_x_preferred":[
        "Lajia"
    ],
    "name:nor_x_preferred":[
        "Lajia"
    ],
    "name:zho_x_preferred":[
        "\u62c9\u67b6"
    ],
    "name:zho_x_variant":[
        "\u5587\u5bb6\u9057\u5740"
    ],
    "wof:name":"Lajia",
    "wof:placetype":"locality"
},
  "geometry": {"coordinates":[107.687,24.4641],"type":"Point"}
}