{
  "type": "Feature",
  "properties": {
    "gn:admin1_code":"13",
    "gn:asciiname":"Shuigongchu Erlian",
    "gn:country_code":"CN",
    "gn:dem":503,
    "gn:feature_class":"P",
    "gn:feature_code":"PPL",
    "gn:name":"Shuigongchu Erlian",
    "gn:population":0,
    "gn:timezone":"Asia/Urumqi",
    "iso:country":"CN",
    "name:zho_x_preferred":[
        "\u6c34\u5de5\u5904\u4e8c\u8fde"
    ],
    "wof:name":"Shuigongchu Erlian",
    "wof:placetype":"locality"
},
  "geometry": {"coordinates":[87.50360999999999,44.07008],"type":"Point"}
}