{
  "type": "Feature",
  "properties": {
    "gn:admin1_code":"32.0",
    "gn:asciiname":"Gongke",
    "gn:country_code":"CN",
    "gn:dem":3108,
    "gn:feature_class":"P",
    "gn:feature_code":"PPL",
    "gn:name":"Gongke",
    "gn:population":0,
    "gn:timezone":"Asia/Shanghai",
    "iso:country":"CN",
    "name:zho_x_preferred":[
        "\u5171\u79d1"
    ],
    "wof:name":"Gongke",
    "wof:placetype":"locality"
},
  "geometry": {"coordinates":[100.19335,30.73107000000001],"type":"Point"}
}