{
  "type": "Feature",
  "properties": {
    "gn:admin1_code":"1.0",
    "gn:asciiname":"Yejiashancun",
    "gn:country_code":"CN",
    "gn:dem":11,
    "gn:feature_class":"P",
    "gn:feature_code":"PPL",
    "gn:name":"Yejiashancun",
    "gn:population":0,
    "gn:timezone":"Asia/Shanghai",
    "iso:country":"CN",
    "name:und_x_variant":[
        "Yejiashan",
        "Yejiashancun"
    ],
    "name:zho_x_preferred":[
        "\u53f6\u5bb6\u5c71"
    ],
    "name:zho_x_variant":[
        "\u53f6\u5bb6\u5c71\u6751"
    ],
    "wof:name":"Yejiashancun",
    "wof:placetype":"locality"
},
  "geometry": {"coordinates":[118.86176,31.08646],"type":"Point"}
}