{
  "type": "Feature",
  "properties": {
    "gn:admin1_code":"30.0",
    "gn:asciiname":"Changputang",
    "gn:country_code":"CN",
    "gn:dem":461,
    "gn:feature_class":"P",
    "gn:feature_code":"PPL",
    "gn:name":"Changputang",
    "gn:population":0,
    "gn:timezone":"Asia/Shanghai",
    "iso:country":"CN",
    "name:zho_x_preferred":[
        "Changputang"
    ],
    "name:zho_x_variant":[
        "\u83d6\u84b2\u5858"
    ],
    "wof:name":"Changputang",
    "wof:placetype":"locality"
},
  "geometry": {"coordinates":[113.29389,25.26056],"type":"Point"}
}