{
  "type": "Feature",
  "properties": {
    "gn:admin1_code":"3.0",
    "gn:asciiname":"Huangzhu Shuxia",
    "gn:country_code":"CN",
    "gn:dem":19,
    "gn:feature_class":"P",
    "gn:feature_code":"PPL",
    "gn:name":"Huangzhu Shuxia",
    "gn:population":0,
    "gn:timezone":"Asia/Shanghai",
    "iso:country":"CN",
    "name:und_x_variant":[
        "\u9ec4\u682a\u6811\u4e0b"
    ],
    "wof:name":"Huangzhu Shuxia",
    "wof:placetype":"locality"
},
  "geometry": {"coordinates":[115.94727,28.76814],"type":"Point"}
}