{
  "type": "Feature",
  "properties": {
    "gn:admin1_code":"4.0",
    "gn:asciiname":"Xuehucun",
    "gn:country_code":"CN",
    "gn:dem":33,
    "gn:feature_class":"P",
    "gn:feature_code":"PPL",
    "gn:name":"Xuehucun",
    "gn:population":0,
    "gn:timezone":"Asia/Shanghai",
    "iso:country":"CN",
    "name:zho_x_preferred":[
        "\u859b\u6e56\u6751"
    ],
    "wof:name":"Xuehucun",
    "wof:placetype":"locality"
},
  "geometry": {"coordinates":[117.50568,34.22968],"type":"Point"}
}