{
  "type": "Feature",
  "properties": {
    "gn:admin1_code":"32.0",
    "gn:asciiname":"Zhuojiaba",
    "gn:country_code":"CN",
    "gn:dem":602,
    "gn:feature_class":"P",
    "gn:feature_code":"PPL",
    "gn:name":"Zhuojiaba",
    "gn:population":0,
    "gn:timezone":"Asia/Shanghai",
    "iso:country":"CN",
    "name:zho_x_preferred":[
        "\u5353\u5bb6\u575d"
    ],
    "wof:name":"Zhuojiaba",
    "wof:placetype":"locality"
},
  "geometry": {"coordinates":[103.56688,30.75591],"type":"Point"}
}