{
  "type": "Feature",
  "properties": {
    "gn:admin1_code":"3.0",
    "gn:asciiname":"Baishuxia",
    "gn:country_code":"CN",
    "gn:dem":68,
    "gn:feature_class":"P",
    "gn:feature_code":"PPL",
    "gn:name":"Baishuxia",
    "gn:population":0,
    "gn:timezone":"Asia/Shanghai",
    "iso:country":"CN",
    "name:und_x_variant":[
        "\u67cf\u6811\u4e0b"
    ],
    "wof:name":"Baishuxia",
    "wof:placetype":"locality"
},
  "geometry": {"coordinates":[117.41880999999999,29.48163],"type":"Point"}
}