{
  "type": "Feature",
  "properties": {
    "gn:admin1_code":"32.0",
    "gn:asciiname":"Dashuiba",
    "gn:country_code":"CN",
    "gn:dem":1187,
    "gn:feature_class":"P",
    "gn:feature_code":"PPL",
    "gn:name":"Dashuiba",
    "gn:population":0,
    "gn:timezone":"Asia/Shanghai",
    "iso:country":"CN",
    "name:zho_x_preferred":[
        "\u5927\u6c34\u575d"
    ],
    "wof:name":"Dashuiba",
    "wof:placetype":"locality"
},
  "geometry": {"coordinates":[108.27224,31.70058],"type":"Point"}
}