{
  "type": "Feature",
  "properties": {
    "gn:admin1_code":"32.0",
    "gn:asciiname":"Jingzhuba",
    "gn:country_code":"CN",
    "gn:dem":830,
    "gn:feature_class":"P",
    "gn:feature_code":"PPL",
    "gn:name":"Jingzhuba",
    "gn:population":0,
    "gn:timezone":"Asia/Shanghai",
    "iso:country":"CN",
    "name:zho_x_preferred":[
        "\u8346\u7af9\u575d"
    ],
    "wof:name":"Jingzhuba",
    "wof:placetype":"locality"
},
  "geometry": {"coordinates":[108.10124,32.20195],"type":"Point"}
}