{
  "type": "Feature",
  "properties": {
    "gn:admin1_code":"26.0",
    "gn:asciiname":"Xiliangge",
    "gn:country_code":"CN",
    "gn:dem":597,
    "gn:feature_class":"P",
    "gn:feature_code":"PPL",
    "gn:name":"Xiliangge",
    "gn:population":0,
    "gn:timezone":"Asia/Shanghai",
    "iso:country":"CN",
    "name:und_x_variant":[
        "\u897f\u51c9\u9601"
    ],
    "wof:name":"Xiliangge",
    "wof:placetype":"locality"
},
  "geometry": {"coordinates":[107.73245,34.21191],"type":"Point"}
}