{
  "type": "Feature",
  "properties": {
    "gn:admin1_code":"5.0",
    "gn:asciiname":"Dujia",
    "gn:country_code":"CN",
    "gn:dem":491,
    "gn:feature_class":"P",
    "gn:feature_code":"PPLA4",
    "gn:name":"Dujia",
    "gn:population":0,
    "gn:timezone":"Asia/Shanghai",
    "iso:country":"CN",
    "name:und_x_variant":[
        "\u675c\u5bb6",
        "Xinancha",
        "Xinancha Zhen",
        "\u897f\u5357\u5c94",
        "\u897f\u5357\u5c94\u9547"
    ],
    "wof:name":"Dujia",
    "wof:placetype":"locality"
},
  "geometry": {"coordinates":[126.89333000000001,42.65086],"type":"Point"}
}