{
  "type": "Feature",
  "properties": {
    "gn:admin1_code":"11.0",
    "gn:asciiname":"Yangongjie",
    "gn:country_code":"CN",
    "gn:dem":946,
    "gn:feature_class":"P",
    "gn:feature_code":"PPL",
    "gn:name":"Yangongjie",
    "gn:population":0,
    "gn:timezone":"Asia/Shanghai",
    "iso:country":"CN",
    "name:zho_x_preferred":[
        "\u71d5\u516c\u754c"
    ],
    "wof:name":"Yangongjie",
    "wof:placetype":"locality"
},
  "geometry": {"coordinates":[110.99573999999998,27.83081],"type":"Point"}
}