{
  "type": "Feature",
  "properties": {
    "gn:admin1_code":"33.0",
    "gn:asciiname":"Lianhe",
    "gn:country_code":"CN",
    "gn:dem":421,
    "gn:feature_class":"P",
    "gn:feature_code":"PPL",
    "gn:name":"Lianhe",
    "gn:population":0,
    "gn:timezone":"Asia/Shanghai",
    "iso:country":"CN",
    "name:ceb_x_preferred":[
        "Lianhe"
    ],
    "name:deu_x_preferred":[
        "Lianhe"
    ],
    "name:swe_x_preferred":[
        "Lianhe"
    ],
    "name:zho_x_preferred":[
        "\u8054\u5408"
    ],
    "wof:name":"Lianhe",
    "wof:placetype":"locality"
},
  "geometry": {"coordinates":[105.5196,29.60242],"type":"Point"}
}