{
  "type": "Feature",
  "properties": {
    "gn:admin1_code":"29.0",
    "gn:asciiname":"Yingpanpo",
    "gn:country_code":"CN",
    "gn:dem":1684,
    "gn:feature_class":"P",
    "gn:feature_code":"PPL",
    "gn:name":"Yingpanpo",
    "gn:population":0,
    "gn:timezone":"Asia/Shanghai",
    "iso:country":"CN",
    "name:zho_x_preferred":[
        "\u8425\u76d8\u5761"
    ],
    "wof:name":"Yingpanpo",
    "wof:placetype":"locality"
},
  "geometry": {"coordinates":[97.70010000000001,24.7771],"type":"Point"}
}