{
  "type": "Feature",
  "properties": {
    "gn:admin1_code":"29",
    "gn:asciiname":"Gaochongmenkou",
    "gn:country_code":"CN",
    "gn:dem":1442,
    "gn:feature_class":"P",
    "gn:feature_code":"PPL",
    "gn:name":"Gaochongmenkou",
    "gn:population":0,
    "gn:timezone":"Asia/Shanghai",
    "iso:country":"CN",
    "name:zho_x_preferred":[
        "\u9ad8\u51b2\u95e8\u53e3"
    ],
    "wof:name":"Gaochongmenkou",
    "wof:placetype":"locality"
},
  "geometry": {"coordinates":[102.44199999999999,23.7454],"type":"Point"}
}