{
  "type": "Feature",
  "properties": {
    "gn:admin1_code":"5.0",
    "gn:asciiname":"Taodongcun",
    "gn:country_code":"CN",
    "gn:dem":136,
    "gn:feature_class":"P",
    "gn:feature_code":"PPL",
    "gn:name":"Taodongcun",
    "gn:population":0,
    "gn:timezone":"Asia/Shanghai",
    "iso:country":"CN",
    "name:zho_x_preferred":[
        "\u6d2e\u4e1c\u6751"
    ],
    "wof:name":"Taodongcun",
    "wof:placetype":"locality"
},
  "geometry": {"coordinates":[123.33004,45.65975],"type":"Point"}
}