{
  "type": "Feature",
  "properties": {
    "gn:admin1_code":"25",
    "gn:asciiname":"Niujiaodian",
    "gn:cc2":"CN",
    "gn:country_code":"CN",
    "gn:dem":34,
    "gn:feature_class":"P",
    "gn:feature_code":"PPL",
    "gn:name":"Niujiaodian",
    "gn:population":0,
    "gn:timezone":"Asia/Shanghai",
    "iso:country":"CN",
    "name:und_x_variant":[
        "Niuchuehtien",
        "Niu-chiao-tien",
        "Niujiaodian"
    ],
    "name:zho_x_preferred":[
        "\u725b\u89d2\u5e97\u9547"
    ],
    "wof:name":"Niujiaodian",
    "wof:placetype":"locality"
},
  "geometry": {"coordinates":[116.43917,36.3975],"type":"Point"}
}