{
  "type": "Feature",
  "properties": {
    "gn:admin1_code":"7",
    "gn:asciiname":"Qishe Linchang",
    "gn:country_code":"CN",
    "gn:dem":419,
    "gn:feature_class":"P",
    "gn:feature_code":"PPLF",
    "gn:name":"Qishe Linchang",
    "gn:population":0,
    "gn:timezone":"Asia/Shanghai",
    "iso:country":"CN",
    "wof:name":"Qishe Linchang",
    "wof:placetype":"locality"
},
  "geometry": {"coordinates":[119.53055999999999,25.78806],"type":"Point"}
}