{
  "type": "Feature",
  "properties": {
    "gn:admin1_code":"07",
    "gn:asciiname":"Nanwang",
    "gn:country_code":"CN",
    "gn:dem":182,
    "gn:feature_class":"P",
    "gn:feature_code":"PPL",
    "gn:name":"Nanwang",
    "gn:population":0,
    "gn:timezone":"Asia/Shanghai",
    "iso:country":"CN",
    "name:zho_x_preferred":[
        "\u5357\u5f80"
    ],
    "wof:name":"Nanwang",
    "wof:placetype":"locality"
},
  "geometry": {"coordinates":[120.34815,27.20491],"type":"Point"}
}