{
  "type": "Feature",
  "properties": {
    "gn:admin1_code":"26.0",
    "gn:asciiname":"Sifangshigou",
    "gn:country_code":"CN",
    "gn:dem":786,
    "gn:feature_class":"P",
    "gn:feature_code":"PPL",
    "gn:name":"Sifangshigou",
    "gn:population":0,
    "gn:timezone":"Asia/Shanghai",
    "iso:country":"CN",
    "name:zho_x_preferred":[
        "\u56db\u65b9\u77f3\u6c9f"
    ],
    "wof:name":"Sifangshigou",
    "wof:placetype":"locality"
},
  "geometry": {"coordinates":[109.41181,32.32283],"type":"Point"}
}