{
  "type": "Feature",
  "properties": {
    "gn:admin1_code":"1.0",
    "gn:asciiname":"Shunhecun",
    "gn:country_code":"CN",
    "gn:dem":27,
    "gn:feature_class":"P",
    "gn:feature_code":"PPL",
    "gn:name":"Shunhecun",
    "gn:population":0,
    "gn:timezone":"Asia/Shanghai",
    "iso:country":"CN",
    "name:zho_x_preferred":[
        "\u987a\u6cb3\u6751"
    ],
    "wof:name":"Shunhecun",
    "wof:placetype":"locality"
},
  "geometry": {"coordinates":[116.82787999999999,33.28052],"type":"Point"}
}