{
  "type": "Feature",
  "properties": {
    "gn:admin1_code":"26.0",
    "gn:asciiname":"Qianjia Hecun",
    "gn:country_code":"CN",
    "gn:dem":978,
    "gn:feature_class":"P",
    "gn:feature_code":"PPL",
    "gn:name":"Qianjia Hecun",
    "gn:population":0,
    "gn:timezone":"Asia/Shanghai",
    "iso:country":"CN",
    "name:zho_x_preferred":[
        "\u94b1\u5bb6\u6cb3\u6751"
    ],
    "wof:name":"Qianjia Hecun",
    "wof:placetype":"locality"
},
  "geometry": {"coordinates":[110.282,37.6864],"type":"Point"}
}