{
  "type": "Feature",
  "properties": {
    "gn:admin1_code":"9.0",
    "gn:asciiname":"Hongdonggou",
    "gn:country_code":"CN",
    "gn:dem":1057,
    "gn:feature_class":"P",
    "gn:feature_code":"PPL",
    "gn:name":"Hongdonggou",
    "gn:population":0,
    "gn:timezone":"Asia/Shanghai",
    "iso:country":"CN",
    "name:zho_x_preferred":[
        "\u7ea2\u6d1e\u6c9f"
    ],
    "wof:name":"Hongdonggou",
    "wof:placetype":"locality"
},
  "geometry": {"coordinates":[111.41431,33.85828],"type":"Point"}
}