{
  "type": "Feature",
  "properties": {
    "gn:admin1_code":"31.0",
    "gn:asciiname":"Shankoumen",
    "gn:country_code":"CN",
    "gn:dem":28,
    "gn:feature_class":"P",
    "gn:feature_code":"PPL",
    "gn:name":"Shankoumen",
    "gn:population":0,
    "gn:timezone":"Asia/Shanghai",
    "iso:country":"CN",
    "name:zho_x_preferred":[
        "\u5c71\u53e3\u95e8"
    ],
    "wof:name":"Shankoumen",
    "wof:placetype":"locality"
},
  "geometry": {"coordinates":[110.37353,19.65746],"type":"Point"}
}