{
  "type": "Feature",
  "properties": {
    "gn:admin1_code":"9.0",
    "gn:asciiname":"Dong'anzhuang",
    "gn:country_code":"CN",
    "gn:dem":60,
    "gn:feature_class":"P",
    "gn:feature_code":"PPL",
    "gn:name":"Dong\u2019anzhuang",
    "gn:population":0,
    "gn:timezone":"Asia/Shanghai",
    "iso:country":"CN",
    "name:und_x_variant":[
        "Dong\u2019anzhuang"
    ],
    "name:zho_x_preferred":[
        "\u4e1c\u5b89\u5e84"
    ],
    "wof:name":"Dong'anzhuang",
    "wof:placetype":"locality"
},
  "geometry": {"coordinates":[114.09714,33.83096],"type":"Point"}
}