{
  "type": "Feature",
  "properties": {
    "gn:admin1_code":"18.0",
    "gn:asciiname":"Bocuan",
    "gn:country_code":"CN",
    "gn:dem":1665,
    "gn:feature_class":"P",
    "gn:feature_code":"PPL",
    "gn:name":"Bocuan",
    "gn:population":0,
    "gn:timezone":"Asia/Shanghai",
    "iso:country":"CN",
    "wof:name":"Bocuan",
    "wof:placetype":"locality"
},
  "geometry": {"coordinates":[105.00833,25.65833],"type":"Point"}
}