{
  "type": "Feature",
  "properties": {
    "gn:admin1_code":"19.0",
    "gn:asciiname":"Beifangshen",
    "gn:country_code":"CN",
    "gn:dem":94,
    "gn:feature_class":"P",
    "gn:feature_code":"PPL",
    "gn:name":"Beifangshen",
    "gn:population":0,
    "gn:timezone":"Asia/Shanghai",
    "iso:country":"CN",
    "name:und_x_variant":[
        "\u5317\u623f\u8eab"
    ],
    "wof:name":"Beifangshen",
    "wof:placetype":"locality"
},
  "geometry": {"coordinates":[122.94381,40.71777],"type":"Point"}
}