{
  "type": "Feature",
  "properties": {
    "gn:admin1_code":"2.0",
    "gn:asciiname":"Shenkengjiao",
    "gn:country_code":"CN",
    "gn:dem":745,
    "gn:feature_class":"P",
    "gn:feature_code":"PPL",
    "gn:name":"Shenkengjiao",
    "gn:population":0,
    "gn:timezone":"Asia/Shanghai",
    "iso:country":"CN",
    "name:und_x_variant":[
        "\u6df1\u5751\u811a"
    ],
    "wof:name":"Shenkengjiao",
    "wof:placetype":"locality"
},
  "geometry": {"coordinates":[119.05029999999999,30.04439],"type":"Point"}
}