{
  "type": "Feature",
  "properties": {
    "gn:admin1_code":"10.0",
    "gn:asciiname":"Liulaoren",
    "gn:country_code":"CN",
    "gn:dem":5,
    "gn:feature_class":"P",
    "gn:feature_code":"PPL",
    "gn:name":"Liulaoren",
    "gn:population":0,
    "gn:timezone":"Asia/Shanghai",
    "iso:country":"CN",
    "name:zho_x_preferred":[
        "\u7559\u8001\u4ec1"
    ],
    "wof:name":"Liulaoren",
    "wof:placetype":"locality"
},
  "geometry": {"coordinates":[117.229,38.3862],"type":"Point"}
}