{
  "type": "Feature",
  "properties": {
    "gn:admin1_code":"5.0",
    "gn:asciiname":"Delincun",
    "gn:country_code":"CN",
    "gn:dem":337,
    "gn:feature_class":"P",
    "gn:feature_code":"PPL",
    "gn:name":"Delincun",
    "gn:population":0,
    "gn:timezone":"Asia/Shanghai",
    "iso:country":"CN",
    "name:zho_x_preferred":[
        "\u5fb7\u6797\u6751"
    ],
    "wof:name":"Delincun",
    "wof:placetype":"locality"
},
  "geometry": {"coordinates":[125.32398000000001,43.07722],"type":"Point"}
}