{
  "type": "Feature",
  "properties": {
    "gn:admin1_code":"14.0",
    "gn:asciiname":"Toigar",
    "gn:country_code":"CN",
    "gn:dem":3670,
    "gn:feature_class":"P",
    "gn:feature_code":"PPLF",
    "gn:name":"Toigar",
    "gn:population":0,
    "gn:timezone":"Asia/Urumqi",
    "iso:country":"CN",
    "name:bod_x_preferred":[
        "Toigar"
    ],
    "name:und_x_variant":[
        "Tuoga"
    ],
    "name:zho_x_preferred":[
        "\u6258\u560e"
    ],
    "wof:name":"Toigar",
    "wof:placetype":"locality"
},
  "geometry": {"coordinates":[90.81596,29.23127],"type":"Point"}
}