{
  "type": "Feature",
  "properties": {
    "gn:admin1_code":"24",
    "gn:asciiname":"Donglucun",
    "gn:country_code":"CN",
    "gn:dem":527,
    "gn:feature_class":"P",
    "gn:feature_code":"PPL",
    "gn:name":"Donglucun",
    "gn:population":0,
    "gn:timezone":"Asia/Shanghai",
    "iso:country":"CN",
    "name:und_x_variant":[
        "Tung-l\u00fc-ts\u2019un",
        "Tung-l\u00fc",
        "Dongl\u00fc",
        "Donglucun"
    ],
    "name:zho_x_preferred":[
        "\u4e1c\u5786\u6751"
    ],
    "wof:name":"Donglucun",
    "wof:placetype":"locality"
},
  "geometry": {"coordinates":[110.80944,34.7132],"type":"Point"}
}