{
  "type": "Feature",
  "properties": {
    "gn:admin1_code":"18",
    "gn:asciiname":"Danaopo",
    "gn:country_code":"CN",
    "gn:dem":791,
    "gn:feature_class":"P",
    "gn:feature_code":"PPL",
    "gn:name":"Danaopo",
    "gn:population":0,
    "gn:timezone":"Asia/Shanghai",
    "iso:country":"CN",
    "name:zho_x_preferred":[
        "\u6253\u95f9\u5761"
    ],
    "wof:name":"Danaopo",
    "wof:placetype":"locality"
},
  "geometry": {"coordinates":[107.157,27.2198],"type":"Point"}
}