{
  "type": "Feature",
  "properties": {
    "gn:admin1_code":"18",
    "gn:asciiname":"Yandi",
    "gn:country_code":"CN",
    "gn:dem":1242,
    "gn:feature_class":"P",
    "gn:feature_code":"PPL",
    "gn:name":"Yandi",
    "gn:population":0,
    "gn:timezone":"Asia/Shanghai",
    "iso:country":"CN",
    "name:ceb_x_preferred":[
        "Yandi"
    ],
    "name:swe_x_preferred":[
        "Yandi"
    ],
    "name:zho_x_preferred":[
        "\u70df\u5730"
    ],
    "wof:name":"Yandi",
    "wof:placetype":"locality"
},
  "geometry": {"coordinates":[105.32599999999999,25.5626],"type":"Point"}
}