{
  "type": "Feature",
  "properties": {
    "gn:admin1_code":"29",
    "gn:asciiname":"Shadong Shangzhai",
    "gn:country_code":"CN",
    "gn:dem":1886,
    "gn:feature_class":"P",
    "gn:feature_code":"PPL",
    "gn:name":"Shadong Shangzhai",
    "gn:population":0,
    "gn:timezone":"Asia/Shanghai",
    "iso:country":"CN",
    "name:zho_x_preferred":[
        "\u6c99\u6d1e\u4e0a\u5be8"
    ],
    "wof:name":"Shadong Shangzhai",
    "wof:placetype":"locality"
},
  "geometry": {"coordinates":[101.68300000000001,24.2194],"type":"Point"}
}