{
  "type": "Feature",
  "properties": {
    "gn:admin1_code":"29.0",
    "gn:asciiname":"Zhongwa",
    "gn:country_code":"CN",
    "gn:dem":2638,
    "gn:feature_class":"P",
    "gn:feature_code":"PPL",
    "gn:name":"Zhongwa",
    "gn:population":0,
    "gn:timezone":"Asia/Shanghai",
    "iso:country":"CN",
    "name:zho_x_preferred":[
        "\u4e2d\u74e6"
    ],
    "wof:name":"Zhongwa",
    "wof:placetype":"locality"
},
  "geometry": {"coordinates":[100.688,27.7539],"type":"Point"}
}