{
  "type": "Feature",
  "properties": {
    "gn:admin1_code":"12.0",
    "gn:asciiname":"Xiaowuzhou",
    "gn:country_code":"CN",
    "gn:dem":37,
    "gn:feature_class":"P",
    "gn:feature_code":"PPL",
    "gn:name":"Xiaowuzhou",
    "gn:population":0,
    "gn:timezone":"Asia/Shanghai",
    "iso:country":"CN",
    "name:zho_x_preferred":[
        "\u5c0f\u5c4b\u5468"
    ],
    "wof:name":"Xiaowuzhou",
    "wof:placetype":"locality"
},
  "geometry": {"coordinates":[113.90980999999999,29.874],"type":"Point"}
}