{
  "type": "Feature",
  "properties": {
    "gn:admin1_code":"30",
    "gn:asciiname":"Luokeng",
    "gn:country_code":"CN",
    "gn:dem":8,
    "gn:feature_class":"P",
    "gn:feature_code":"PPLA4",
    "gn:name":"Luokeng",
    "gn:population":0,
    "gn:timezone":"Asia/Shanghai",
    "iso:country":"CN",
    "name:und_x_variant":[
        "Luokeng Zhen",
        "\u7f57\u5751\u9547"
    ],
    "name:zho_x_preferred":[
        "\u7f57\u5751"
    ],
    "wof:name":"Luokeng",
    "wof:placetype":"locality"
},
  "geometry": {"coordinates":[112.91977,22.46265],"type":"Point"}
}