{
  "type": "Feature",
  "properties": {
    "gn:admin1_code":"25",
    "gn:asciiname":"Shiliquancun",
    "gn:country_code":"CN",
    "gn:dem":60,
    "gn:feature_class":"P",
    "gn:feature_code":"PPL",
    "gn:name":"Shiliquancun",
    "gn:population":0,
    "gn:timezone":"Asia/Shanghai",
    "iso:country":"CN",
    "name:und_x_variant":[
        "Shiliquan",
        "Shiliquancun"
    ],
    "name:zho_x_preferred":[
        "\u5341\u91cc\u6cc9"
    ],
    "name:zho_x_variant":[
        "\u5341\u91cc\u6cc9\u6751"
    ],
    "wof:name":"Shiliquancun",
    "wof:placetype":"locality"
},
  "geometry": {"coordinates":[117.55119999999999,34.81002],"type":"Point"}
}