{
  "type": "Feature",
  "properties": {
    "gn:admin1_code":"16.0",
    "gn:asciiname":"Baoshangcun",
    "gn:country_code":"CN",
    "gn:dem":1540,
    "gn:feature_class":"P",
    "gn:feature_code":"PPL",
    "gn:name":"Baoshangcun",
    "gn:population":0,
    "gn:timezone":"Asia/Shanghai",
    "iso:country":"CN",
    "name:zho_x_preferred":[
        "\u4fdd\u4e0a\u6751"
    ],
    "wof:name":"Baoshangcun",
    "wof:placetype":"locality"
},
  "geometry": {"coordinates":[105.131,24.6534],"type":"Point"}
}