{
  "type": "Feature",
  "properties": {
    "gn:admin1_code":"18",
    "gn:asciiname":"Yudong",
    "gn:country_code":"CN",
    "gn:dem":401,
    "gn:feature_class":"P",
    "gn:feature_code":"PPL",
    "gn:name":"Yudong",
    "gn:population":0,
    "gn:timezone":"Asia/Shanghai",
    "iso:country":"CN",
    "name:ceb_x_preferred":[
        "Yudong"
    ],
    "name:swe_x_preferred":[
        "Yudong"
    ],
    "name:zho_x_preferred":[
        "\u80b2\u6d1e"
    ],
    "wof:name":"Yudong",
    "wof:placetype":"locality"
},
  "geometry": {"coordinates":[108.654,26.2549],"type":"Point"}
}