{
  "type": "Feature",
  "properties": {
    "gn:admin1_code":"26.0",
    "gn:asciiname":"Dadongwan",
    "gn:country_code":"CN",
    "gn:dem":1354,
    "gn:feature_class":"P",
    "gn:feature_code":"PPL",
    "gn:name":"Dadongwan",
    "gn:population":0,
    "gn:timezone":"Asia/Shanghai",
    "iso:country":"CN",
    "name:zho_x_preferred":[
        "\u5927\u4e1c\u6e7e"
    ],
    "wof:name":"Dadongwan",
    "wof:placetype":"locality"
},
  "geometry": {"coordinates":[108.63321999999999,33.19757],"type":"Point"}
}