{
  "type": "Feature",
  "properties": {
    "gn:admin1_code":"23.0",
    "gn:asciiname":"Gongmaqiao",
    "gn:country_code":"CN",
    "gn:dem":4,
    "gn:feature_class":"P",
    "gn:feature_code":"PPL",
    "gn:name":"Gongmaqiao",
    "gn:population":0,
    "gn:timezone":"Asia/Shanghai",
    "iso:country":"CN",
    "name:und_x_variant":[
        "\u516c\u9a6c\u6865"
    ],
    "wof:name":"Gongmaqiao",
    "wof:placetype":"locality"
},
  "geometry": {"coordinates":[121.27070000000001,30.90952],"type":"Point"}
}