{
  "type": "Feature",
  "properties": {
    "gn:admin1_code":"12.0",
    "gn:asciiname":"Xiashakou",
    "gn:country_code":"CN",
    "gn:dem":25,
    "gn:feature_class":"P",
    "gn:feature_code":"PPL",
    "gn:name":"Xiashakou",
    "gn:population":0,
    "gn:timezone":"Asia/Shanghai",
    "iso:country":"CN",
    "name:zho_x_preferred":[
        "\u4e0b\u6c99\u53e3"
    ],
    "wof:name":"Xiashakou",
    "wof:placetype":"locality"
},
  "geometry": {"coordinates":[113.97044,30.24218],"type":"Point"}
}