{
  "type": "Feature",
  "properties": {
    "gn:admin1_code":"19.0",
    "gn:asciiname":"Shijianggou",
    "gn:country_code":"CN",
    "gn:dem":264,
    "gn:feature_class":"P",
    "gn:feature_code":"PPL",
    "gn:name":"Shijianggou",
    "gn:population":0,
    "gn:timezone":"Asia/Shanghai",
    "iso:country":"CN",
    "name:zho_x_preferred":[
        "\u77f3\u5320\u6c9f"
    ],
    "wof:name":"Shijianggou",
    "wof:placetype":"locality"
},
  "geometry": {"coordinates":[120.297,41.1598],"type":"Point"}
}