{
  "type": "Feature",
  "properties": {
    "gn:admin1_code":"32.0",
    "gn:asciiname":"Waitasi",
    "gn:country_code":"CN",
    "gn:dem":457,
    "gn:feature_class":"P",
    "gn:feature_code":"PPL",
    "gn:name":"Waitasi",
    "gn:population":0,
    "gn:timezone":"Asia/Shanghai",
    "iso:country":"CN",
    "name:zho_x_preferred":[
        "\u6b6a\u5854\u5bfa"
    ],
    "wof:name":"Waitasi",
    "wof:placetype":"locality"
},
  "geometry": {"coordinates":[104.73099999999999,31.1639],"type":"Point"}
}