{
  "type": "Feature",
  "properties": {
    "gn:admin1_code":"11",
    "gn:asciiname":"Zushanwan",
    "gn:country_code":"CN",
    "gn:dem":78,
    "gn:feature_class":"P",
    "gn:feature_code":"PPL",
    "gn:name":"Zushanwan",
    "gn:population":0,
    "gn:timezone":"Asia/Shanghai",
    "iso:country":"CN",
    "name:zho_x_preferred":[
        "\u7956\u5c71\u6e7e"
    ],
    "wof:name":"Zushanwan",
    "wof:placetype":"locality"
},
  "geometry": {"coordinates":[112.40085000000001,26.66239],"type":"Point"}
}