{
  "type": "Feature",
  "properties": {
    "gn:admin1_code":"14.0",
    "gn:asciiname":"Jiamacun",
    "gn:country_code":"CN",
    "gn:dem":3991,
    "gn:feature_class":"P",
    "gn:feature_code":"PPL",
    "gn:name":"Jiamacun",
    "gn:population":0,
    "gn:timezone":"Asia/Urumqi",
    "iso:country":"CN",
    "name:zho_x_preferred":[
        "\u52a0\u9ebb\u6751"
    ],
    "wof:name":"Jiamacun",
    "wof:placetype":"locality"
},
  "geometry": {"coordinates":[91.54675,28.97378],"type":"Point"}
}