{
  "type": "Feature",
  "properties": {
    "gn:admin1_code":"9.0",
    "gn:asciiname":"Yusun",
    "gn:country_code":"CN",
    "gn:dem":79,
    "gn:feature_class":"P",
    "gn:feature_code":"PPL",
    "gn:name":"Yusun",
    "gn:population":0,
    "gn:timezone":"Asia/Shanghai",
    "iso:country":"CN",
    "name:zho_x_preferred":[
        "\u6986\u5b59"
    ],
    "wof:name":"Yusun",
    "wof:placetype":"locality"
},
  "geometry": {"coordinates":[113.58856000000002,33.77483],"type":"Point"}
}