{
  "type": "Feature",
  "properties": {
    "gn:admin1_code":"32.0",
    "gn:asciiname":"Baoyan",
    "gn:country_code":"CN",
    "gn:dem":2239,
    "gn:feature_class":"P",
    "gn:feature_code":"PPL",
    "gn:name":"Baoyan",
    "gn:population":0,
    "gn:timezone":"Asia/Shanghai",
    "iso:country":"CN",
    "name:zho_x_preferred":[
        "\u5b9d\u5ca9"
    ],
    "wof:name":"Baoyan",
    "wof:placetype":"locality"
},
  "geometry": {"coordinates":[103.20099999999999,27.6852],"type":"Point"}
}