{
  "type": "Feature",
  "properties": {
    "gn:admin1_code":"14.0",
    "gn:asciiname":"Galai",
    "gn:country_code":"CN",
    "gn:dem":4218,
    "gn:feature_class":"P",
    "gn:feature_code":"PPL",
    "gn:name":"Galai",
    "gn:population":0,
    "gn:timezone":"Asia/Urumqi",
    "iso:country":"CN",
    "name:bod_x_preferred":[
        "Gal\u00eab"
    ],
    "name:und_x_variant":[
        "Alang Qu"
    ],
    "name:zho_x_preferred":[
        "\u560e\u6765"
    ],
    "name:zho_x_variant":[
        "\u963f\u6717\u533a"
    ],
    "wof:name":"Galai",
    "wof:placetype":"locality"
},
  "geometry": {"coordinates":[91.401,30.001],"type":"Point"}
}