{
  "type": "Feature",
  "properties": {
    "gn:admin1_code":"14.0",
    "gn:asciiname":"Qinda",
    "gn:country_code":"CN",
    "gn:dem":4084,
    "gn:feature_class":"P",
    "gn:feature_code":"PPL",
    "gn:name":"Qinda",
    "gn:population":0,
    "gn:timezone":"Asia/Urumqi",
    "iso:country":"CN",
    "name:bod_x_preferred":[
        "Qinda"
    ],
    "name:zho_x_preferred":[
        "Jinda"
    ],
    "name:zho_x_variant":[
        "\u91d1\u8fbe"
    ],
    "wof:name":"Qinda",
    "wof:placetype":"locality"
},
  "geometry": {"coordinates":[97.57655,29.9355],"type":"Point"}
}