{
  "type": "Feature",
  "properties": {
    "gn:admin1_code":"29.0",
    "gn:asciiname":"Baodaoshan",
    "gn:country_code":"CN",
    "gn:dem":1798,
    "gn:feature_class":"P",
    "gn:feature_code":"PPL",
    "gn:name":"Baodaoshan",
    "gn:population":0,
    "gn:timezone":"Asia/Shanghai",
    "iso:country":"CN",
    "name:zho_x_preferred":[
        "\u8584\u5200\u5c71"
    ],
    "wof:name":"Baodaoshan",
    "wof:placetype":"locality"
},
  "geometry": {"coordinates":[99.0359,24.4567],"type":"Point"}
}