{
  "type": "Feature",
  "properties": {
    "gn:admin1_code":"7.0",
    "gn:asciiname":"Shangluopai",
    "gn:country_code":"CN",
    "gn:dem":408,
    "gn:feature_class":"P",
    "gn:feature_code":"PPL",
    "gn:name":"Shangluopai",
    "gn:population":0,
    "gn:timezone":"Asia/Shanghai",
    "iso:country":"CN",
    "name:zho_x_preferred":[
        "\u4e0a\u7f57\u6392"
    ],
    "wof:name":"Shangluopai",
    "wof:placetype":"locality"
},
  "geometry": {"coordinates":[116.77298,26.51085],"type":"Point"}
}