{
  "type": "Feature",
  "properties": {
    "gn:admin1_code":"8.0",
    "gn:asciiname":"Liangfengcun",
    "gn:country_code":"CN",
    "gn:dem":207,
    "gn:feature_class":"P",
    "gn:feature_code":"PPL",
    "gn:name":"Liangfengcun",
    "gn:population":0,
    "gn:timezone":"Asia/Shanghai",
    "iso:country":"CN",
    "name:zho_x_preferred":[
        "\u4e24\u4e30\u6751"
    ],
    "wof:name":"Liangfengcun",
    "wof:placetype":"locality"
},
  "geometry": {"coordinates":[125.855,46.89395],"type":"Point"}
}