{
  "type": "Feature",
  "properties": {
    "gn:admin1_code":"16.0",
    "gn:asciiname":"Dedian",
    "gn:country_code":"CN",
    "gn:dem":831,
    "gn:feature_class":"P",
    "gn:feature_code":"PPL",
    "gn:name":"Dedian",
    "gn:population":0,
    "gn:timezone":"Asia/Shanghai",
    "iso:country":"CN",
    "name:zho_x_preferred":[
        "\u5fb7\u5178"
    ],
    "wof:name":"Dedian",
    "wof:placetype":"locality"
},
  "geometry": {"coordinates":[106.426,23.3417],"type":"Point"}
}