{
  "type": "Feature",
  "properties": {
    "gn:admin1_code":"32.0",
    "gn:asciiname":"Shengzu",
    "gn:country_code":"CN",
    "gn:dem":2492,
    "gn:feature_class":"P",
    "gn:feature_code":"PPL",
    "gn:name":"Shengzu",
    "gn:population":0,
    "gn:timezone":"Asia/Shanghai",
    "iso:country":"CN",
    "name:zho_x_preferred":[
        "\u7701\u7956"
    ],
    "wof:name":"Shengzu",
    "wof:placetype":"locality"
},
  "geometry": {"coordinates":[103.15000000000001,27.6736],"type":"Point"}
}