{
  "type": "Feature",
  "properties": {
    "gn:admin1_code":"23.0",
    "gn:asciiname":"Tangjiaxiang",
    "gn:country_code":"CN",
    "gn:dem":3,
    "gn:feature_class":"P",
    "gn:feature_code":"PPL",
    "gn:name":"Tangjiaxiang",
    "gn:population":0,
    "gn:timezone":"Asia/Shanghai",
    "iso:country":"CN",
    "name:zho_x_preferred":[
        "Tangjiaxiang"
    ],
    "name:zho_x_variant":[
        "\u5510\u5bb6\u5df7"
    ],
    "wof:name":"Tangjiaxiang",
    "wof:placetype":"locality"
},
  "geometry": {"coordinates":[121.30809000000001,31.27683],"type":"Point"}
}