{
  "type": "Feature",
  "properties": {
    "gn:admin1_code":"19.0",
    "gn:asciiname":"Aohai",
    "gn:country_code":"CN",
    "gn:dem":98,
    "gn:feature_class":"P",
    "gn:feature_code":"PPL",
    "gn:name":"Aohai",
    "gn:population":0,
    "gn:timezone":"Asia/Shanghai",
    "iso:country":"CN",
    "name:zho_x_preferred":[
        "\u6556\u6d77"
    ],
    "wof:name":"Aohai",
    "wof:placetype":"locality"
},
  "geometry": {"coordinates":[123.79300000000001,43.0092],"type":"Point"}
}