{
  "type": "Feature",
  "properties": {
    "gn:admin1_code":"18.0",
    "gn:asciiname":"Tongtaping",
    "gn:country_code":"CN",
    "gn:dem":844,
    "gn:feature_class":"P",
    "gn:feature_code":"PPL",
    "gn:name":"Tongtaping",
    "gn:population":0,
    "gn:timezone":"Asia/Shanghai",
    "iso:country":"CN",
    "name:zho_x_preferred":[
        "\u901a\u5854\u576a"
    ],
    "wof:name":"Tongtaping",
    "wof:placetype":"locality"
},
  "geometry": {"coordinates":[108.907,28.1741],"type":"Point"}
}