{
  "type": "Feature",
  "properties": {
    "gn:admin1_code":"18.0",
    "gn:asciiname":"Zhangzhai",
    "gn:country_code":"CN",
    "gn:dem":622,
    "gn:feature_class":"P",
    "gn:feature_code":"PPL",
    "gn:name":"Zhangzhai",
    "gn:population":0,
    "gn:timezone":"Asia/Shanghai",
    "iso:country":"CN",
    "name:zho_x_preferred":[
        "\u7ae0\u5be8"
    ],
    "wof:name":"Zhangzhai",
    "wof:placetype":"locality"
},
  "geometry": {"coordinates":[109.15900000000001,26.8407],"type":"Point"}
}