{
  "type": "Feature",
  "properties": {
    "gn:admin1_code":"1.0",
    "gn:asciiname":"Weijiashan",
    "gn:country_code":"CN",
    "gn:dem":16,
    "gn:feature_class":"P",
    "gn:feature_code":"PPL",
    "gn:name":"Weijiashan",
    "gn:population":0,
    "gn:timezone":"Asia/Shanghai",
    "iso:country":"CN",
    "name:und_x_variant":[
        "\u9b4f\u5bb6\u5c71"
    ],
    "name:zho_x_preferred":[
        "\u9b4f\u5bb6\u5c71"
    ],
    "wof:name":"Weijiashan",
    "wof:placetype":"locality"
},
  "geometry": {"coordinates":[118.34128,31.19321],"type":"Point"}
}