{
  "type": "Feature",
  "properties": {
    "gn:admin1_code":"32.0",
    "gn:asciiname":"Luobuqian",
    "gn:country_code":"CN",
    "gn:dem":1231,
    "gn:feature_class":"P",
    "gn:feature_code":"PPL",
    "gn:name":"Luobuqian",
    "gn:population":0,
    "gn:timezone":"Asia/Shanghai",
    "iso:country":"CN",
    "name:zho_x_preferred":[
        "\u7f57\u5e03\u6b20"
    ],
    "wof:name":"Luobuqian",
    "wof:placetype":"locality"
},
  "geometry": {"coordinates":[103.64671,28.31066],"type":"Point"}
}