{
  "type": "Feature",
  "properties": {
    "gn:admin1_code":"32.0",
    "gn:asciiname":"Qingheqiao",
    "gn:country_code":"CN",
    "gn:dem":391,
    "gn:feature_class":"P",
    "gn:feature_code":"PPL",
    "gn:name":"Qingheqiao",
    "gn:population":0,
    "gn:timezone":"Asia/Shanghai",
    "iso:country":"CN",
    "name:zho_x_preferred":[
        "\u6e05\u6cb3\u6865"
    ],
    "wof:name":"Qingheqiao",
    "wof:placetype":"locality"
},
  "geometry": {"coordinates":[105.914,30.949],"type":"Point"}
}