{
  "type": "Feature",
  "properties": {
    "gn:admin1_code":"26.0",
    "gn:asciiname":"Xihejiagoucun",
    "gn:country_code":"CN",
    "gn:dem":959,
    "gn:feature_class":"P",
    "gn:feature_code":"PPL",
    "gn:name":"Xihejiagoucun",
    "gn:population":0,
    "gn:timezone":"Asia/Shanghai",
    "iso:country":"CN",
    "name:zho_x_preferred":[
        "\u897f\u8d3a\u5bb6\u6c9f\u6751"
    ],
    "wof:name":"Xihejiagoucun",
    "wof:placetype":"locality"
},
  "geometry": {"coordinates":[110.06947,37.14095],"type":"Point"}
}