{
  "type": "Feature",
  "properties": {
    "gn:admin1_code":"24.0",
    "gn:asciiname":"Mengjiaping",
    "gn:country_code":"CN",
    "gn:dem":1162,
    "gn:feature_class":"P",
    "gn:feature_code":"PPL",
    "gn:name":"Mengjiaping",
    "gn:population":0,
    "gn:timezone":"Asia/Shanghai",
    "iso:country":"CN",
    "name:zho_x_preferred":[
        "\u5b5f\u5bb6\u576a"
    ],
    "wof:name":"Mengjiaping",
    "wof:placetype":"locality"
},
  "geometry": {"coordinates":[113.16517,38.79818],"type":"Point"}
}