{
  "type": "Feature",
  "properties": {
    "gn:admin1_code":"22.0",
    "gn:asciiname":"Xinzhuangcun",
    "gn:country_code":"CN",
    "gn:dem":172,
    "gn:feature_class":"P",
    "gn:feature_code":"PPL",
    "gn:name":"Xinzhuangcun",
    "gn:population":0,
    "gn:timezone":"Asia/Shanghai",
    "iso:country":"CN",
    "name:zho_x_preferred":[
        "\u8f9b\u5e84\u6751"
    ],
    "wof:name":"Xinzhuangcun",
    "wof:placetype":"locality"
},
  "geometry": {"coordinates":[117.14287,40.58915],"type":"Point"}
}