{
  "type": "Feature",
  "properties": {
    "gn:admin1_code":"15.0",
    "gn:asciiname":"Shangsiwan",
    "gn:country_code":"CN",
    "gn:dem":2574,
    "gn:feature_class":"P",
    "gn:feature_code":"PPL",
    "gn:name":"Shangsiwan",
    "gn:population":0,
    "gn:timezone":"Asia/Shanghai",
    "iso:country":"CN",
    "name:zho_x_preferred":[
        "\u4e0a\u5bfa\u6e7e"
    ],
    "wof:name":"Shangsiwan",
    "wof:placetype":"locality"
},
  "geometry": {"coordinates":[102.657,37.4075],"type":"Point"}
}