{
  "type": "Feature",
  "properties": {
    "gn:admin1_code":"30.0",
    "gn:asciiname":"Tianmenlingjiao",
    "gn:country_code":"CN",
    "gn:dem":253,
    "gn:feature_class":"P",
    "gn:feature_code":"PPL",
    "gn:name":"Tianmenlingjiao",
    "gn:population":0,
    "gn:timezone":"Asia/Shanghai",
    "iso:country":"CN",
    "name:zho_x_preferred":[
        "Tianmenlingjiao"
    ],
    "name:zho_x_variant":[
        "\u5929\u95e8\u5cad\u811a"
    ],
    "wof:name":"Tianmenlingjiao",
    "wof:placetype":"locality"
},
  "geometry": {"coordinates":[112.87139000000001,24.82222],"type":"Point"}
}