{
  "type": "Feature",
  "properties": {
    "gn:admin1_code":"29.0",
    "gn:asciiname":"Jiangxicun",
    "gn:country_code":"CN",
    "gn:dem":2002,
    "gn:feature_class":"P",
    "gn:feature_code":"PPL",
    "gn:name":"Jiangxicun",
    "gn:population":0,
    "gn:timezone":"Asia/Shanghai",
    "iso:country":"CN",
    "name:zho_x_preferred":[
        "\u6c5f\u897f\u6751"
    ],
    "wof:name":"Jiangxicun",
    "wof:placetype":"locality"
},
  "geometry": {"coordinates":[103.069,26.2874],"type":"Point"}
}