{
  "type": "Feature",
  "properties": {
    "gn:admin1_code":"1.0",
    "gn:asciiname":"Huzhancun",
    "gn:country_code":"CN",
    "gn:dem":98,
    "gn:feature_class":"P",
    "gn:feature_code":"PPL",
    "gn:name":"Huzhancun",
    "gn:population":0,
    "gn:timezone":"Asia/Shanghai",
    "iso:country":"CN",
    "name:zho_x_preferred":[
        "\u864e\u6808\u6751"
    ],
    "wof:name":"Huzhancun",
    "wof:placetype":"locality"
},
  "geometry": {"coordinates":[117.45753999999999,30.97287],"type":"Point"}
}