{
  "type": "Feature",
  "properties": {
    "gn:admin1_code":"29.0",
    "gn:asciiname":"Dengzhanwo",
    "gn:country_code":"CN",
    "gn:dem":1784,
    "gn:feature_class":"P",
    "gn:feature_code":"PPL",
    "gn:name":"Dengzhanwo",
    "gn:population":0,
    "gn:timezone":"Asia/Shanghai",
    "iso:country":"CN",
    "name:zho_x_preferred":[
        "\u706f\u76cf\u7a9d"
    ],
    "wof:name":"Dengzhanwo",
    "wof:placetype":"locality"
},
  "geometry": {"coordinates":[103.56699999999999,27.8921],"type":"Point"}
}