{
  "type": "Feature",
  "properties": {
    "gn:admin1_code":"30",
    "gn:asciiname":"Jingtang",
    "gn:country_code":"CN",
    "gn:dem":430,
    "gn:feature_class":"P",
    "gn:feature_code":"PPL",
    "gn:name":"Jingtang",
    "gn:population":0,
    "gn:timezone":"Asia/Shanghai",
    "iso:country":"CN",
    "name:zho_x_preferred":[
        "\u5f84\u5858"
    ],
    "wof:name":"Jingtang",
    "wof:placetype":"locality"
},
  "geometry": {"coordinates":[115.57966,24.45575],"type":"Point"}
}