{
  "type": "Feature",
  "properties": {
    "gn:admin1_code":"4.0",
    "gn:asciiname":"Zhengtuannanshe",
    "gn:country_code":"CN",
    "gn:dem":3,
    "gn:feature_class":"P",
    "gn:feature_code":"PPL",
    "gn:name":"Zhengtuannanshe",
    "gn:population":0,
    "gn:timezone":"Asia/Shanghai",
    "iso:country":"CN",
    "name:und_x_variant":[
        "\u6b63\u56e2\u5357\u820d"
    ],
    "name:zho_x_preferred":[
        "\u6b63\u56e2\u5357\u820d"
    ],
    "wof:name":"Zhengtuannanshe",
    "wof:placetype":"locality"
},
  "geometry": {"coordinates":[120.36742,32.89365],"type":"Point"}
}