{
  "type": "Feature",
  "properties": {
    "gn:admin1_code":"25",
    "gn:asciiname":"Baishiya",
    "gn:country_code":"CN",
    "gn:dem":153,
    "gn:feature_class":"P",
    "gn:feature_code":"PPL",
    "gn:name":"Baishiya",
    "gn:population":0,
    "gn:timezone":"Asia/Shanghai",
    "iso:country":"CN",
    "name:zho_x_preferred":[
        "\u767d\u77f3\u5d16"
    ],
    "wof:name":"Baishiya",
    "wof:placetype":"locality"
},
  "geometry": {"coordinates":[116.81699999999999,36.3083],"type":"Point"}
}