{
  "type": "Feature",
  "properties": {
    "gn:admin1_code":"29.0",
    "gn:asciiname":"Laopaoshan",
    "gn:country_code":"CN",
    "gn:dem":1707,
    "gn:feature_class":"P",
    "gn:feature_code":"PPL",
    "gn:name":"Laopaoshan",
    "gn:population":0,
    "gn:timezone":"Asia/Shanghai",
    "iso:country":"CN",
    "name:zho_x_preferred":[
        "\u8001\u6ce1\u5c71"
    ],
    "wof:name":"Laopaoshan",
    "wof:placetype":"locality"
},
  "geometry": {"coordinates":[98.1056,24.7053],"type":"Point"}
}