{
  "type": "Feature",
  "properties": {
    "gn:admin1_code":"19.0",
    "gn:asciiname":"Qianliu",
    "gn:country_code":"CN",
    "gn:dem":18,
    "gn:feature_class":"P",
    "gn:feature_code":"PPLA4",
    "gn:name":"Qianliu",
    "gn:population":0,
    "gn:timezone":"Asia/Shanghai",
    "iso:country":"CN",
    "name:und_x_variant":[
        "\u524d\u67f3",
        "Qianliu Jiedao",
        "\u524d\u67f3\u8857\u9053"
    ],
    "wof:name":"Qianliu",
    "wof:placetype":"locality"
},
  "geometry": {"coordinates":[122.6344,40.84171],"type":"Point"}
}