{
  "type": "Feature",
  "properties": {
    "gn:admin1_code":"9",
    "gn:asciiname":"Dongzhuang",
    "gn:country_code":"CN",
    "gn:dem":53,
    "gn:feature_class":"P",
    "gn:feature_code":"PPL",
    "gn:name":"Dongzhuang",
    "gn:population":0,
    "gn:timezone":"Asia/Shanghai",
    "iso:country":"CN",
    "name:zho_x_preferred":[
        "\u4e1c\u5e84"
    ],
    "wof:name":"Dongzhuang",
    "wof:placetype":"locality"
},
  "geometry": {"coordinates":[115.1066,36.07859000000001],"type":"Point"}
}