{
  "type": "Feature",
  "properties": {
    "gn:admin1_code":"32.0",
    "gn:asciiname":"Gegong",
    "gn:country_code":"CN",
    "gn:dem":4121,
    "gn:feature_class":"P",
    "gn:feature_code":"PPL",
    "gn:name":"Gegong",
    "gn:population":0,
    "gn:timezone":"Asia/Shanghai",
    "iso:country":"CN",
    "name:zho_x_preferred":[
        "\u683c\u8d21"
    ],
    "wof:name":"Gegong",
    "wof:placetype":"locality"
},
  "geometry": {"coordinates":[98.04689999999999,33.2599],"type":"Point"}
}