{
  "type": "Feature",
  "properties": {
    "gn:admin1_code":"19.0",
    "gn:asciiname":"Yixingcun",
    "gn:country_code":"CN",
    "gn:dem":75,
    "gn:feature_class":"P",
    "gn:feature_code":"PPL",
    "gn:name":"Yixingcun",
    "gn:population":0,
    "gn:timezone":"Asia/Shanghai",
    "iso:country":"CN",
    "name:zho_x_preferred":[
        "\u4e49\u5174\u6751"
    ],
    "wof:name":"Yixingcun",
    "wof:placetype":"locality"
},
  "geometry": {"coordinates":[123.67023,42.64668],"type":"Point"}
}