{
  "type": "Feature",
  "properties": {
    "gn:admin1_code":"15.0",
    "gn:asciiname":"Heimawan",
    "gn:country_code":"CN",
    "gn:dem":1625,
    "gn:feature_class":"P",
    "gn:feature_code":"PPL",
    "gn:name":"Heimawan",
    "gn:population":0,
    "gn:timezone":"Asia/Shanghai",
    "iso:country":"CN",
    "name:zho_x_preferred":[
        "\u9ed1\u9a6c\u6e7e"
    ],
    "wof:name":"Heimawan",
    "wof:placetype":"locality"
},
  "geometry": {"coordinates":[108.605,35.3555],"type":"Point"}
}