{
  "type": "Feature",
  "properties": {
    "gn:admin1_code":"8.0",
    "gn:asciiname":"Banzifangcun",
    "gn:country_code":"CN",
    "gn:dem":148,
    "gn:feature_class":"P",
    "gn:feature_code":"PPL",
    "gn:name":"Banzifangcun",
    "gn:population":0,
    "gn:timezone":"Asia/Shanghai",
    "iso:country":"CN",
    "name:zho_x_preferred":[
        "\u677f\u5b50\u623f\u6751"
    ],
    "wof:name":"Banzifangcun",
    "wof:placetype":"locality"
},
  "geometry": {"coordinates":[125.19883,46.21018],"type":"Point"}
}