{
  "type": "Feature",
  "properties": {
    "gn:admin1_code":"26.0",
    "gn:asciiname":"Asicun",
    "gn:country_code":"CN",
    "gn:dem":1190,
    "gn:feature_class":"P",
    "gn:feature_code":"PPL",
    "gn:name":"Asicun",
    "gn:population":0,
    "gn:timezone":"Asia/Shanghai",
    "iso:country":"CN",
    "name:zho_x_preferred":[
        "\u963f\u5bfa\u6751"
    ],
    "wof:name":"Asicun",
    "wof:placetype":"locality"
},
  "geometry": {"coordinates":[109.50918,35.79699],"type":"Point"}
}