{
  "type": "Feature",
  "properties": {
    "gn:admin1_code":"21.0",
    "gn:asciiname":"Tianjiagoumen",
    "gn:country_code":"CN",
    "gn:dem":1873,
    "gn:feature_class":"P",
    "gn:feature_code":"PPL",
    "gn:name":"Tianjiagoumen",
    "gn:population":0,
    "gn:timezone":"Asia/Shanghai",
    "iso:country":"CN",
    "name:zho_x_preferred":[
        "\u7530\u5bb6\u6c9f\u95e8"
    ],
    "wof:name":"Tianjiagoumen",
    "wof:placetype":"locality"
},
  "geometry": {"coordinates":[105.97123999999999,35.58866],"type":"Point"}
}