{
  "type": "Feature",
  "properties": {
    "gn:admin1_code":"4.0",
    "gn:asciiname":"Lianwangcun",
    "gn:country_code":"CN",
    "gn:dem":57,
    "gn:feature_class":"P",
    "gn:feature_code":"PPL",
    "gn:name":"Lianwangcun",
    "gn:population":0,
    "gn:timezone":"Asia/Shanghai",
    "iso:country":"CN",
    "name:zho_x_preferred":[
        "\u8fde\u6c6a\u6751"
    ],
    "wof:name":"Lianwangcun",
    "wof:placetype":"locality"
},
  "geometry": {"coordinates":[118.61029000000001,34.67969],"type":"Point"}
}