{
  "type": "Feature",
  "properties": {
    "gn:admin1_code":"3.0",
    "gn:asciiname":"Fenglingcun",
    "gn:country_code":"CN",
    "gn:dem":39,
    "gn:feature_class":"P",
    "gn:feature_code":"PPL",
    "gn:name":"Fenglingcun",
    "gn:population":0,
    "gn:timezone":"Asia/Shanghai",
    "iso:country":"CN",
    "name:und_x_variant":[
        "\u51e4\u5cad\u6751"
    ],
    "wof:name":"Fenglingcun",
    "wof:placetype":"locality"
},
  "geometry": {"coordinates":[116.24007,28.38897],"type":"Point"}
}