{
  "type": "Feature",
  "properties": {
    "gn:admin1_code":"7.0",
    "gn:asciiname":"Dengshan",
    "gn:country_code":"CN",
    "gn:dem":485,
    "gn:feature_class":"P",
    "gn:feature_code":"PPL",
    "gn:name":"Dengshan",
    "gn:population":0,
    "gn:timezone":"Asia/Shanghai",
    "iso:country":"CN",
    "name:zho_x_preferred":[
        "\u767b\u5c71"
    ],
    "wof:name":"Dengshan",
    "wof:placetype":"locality"
},
  "geometry": {"coordinates":[118.06956,25.09522],"type":"Point"}
}