{
  "type": "Feature",
  "properties": {
    "gn:admin1_code":"01",
    "gn:asciiname":"Gubei",
    "gn:cc2":"CN",
    "gn:country_code":"CN",
    "gn:dem":203,
    "gn:feature_class":"P",
    "gn:feature_code":"PPL",
    "gn:name":"Gubei",
    "gn:population":0,
    "gn:timezone":"Asia/Shanghai",
    "iso:country":"CN",
    "name:fra_x_preferred":[
        "Gubei"
    ],
    "name:und_x_variant":[
        "Ku-pei",
        "Ku-pei-ch\u2019ung",
        "Gubei"
    ],
    "wof:name":"Gubei",
    "wof:placetype":"locality"
},
  "geometry": {"coordinates":[115.79639,31.46639],"type":"Point"}
}