{
  "type": "Feature",
  "properties": {
    "gn:admin1_code":"5.0",
    "gn:asciiname":"Sanpucun",
    "gn:country_code":"CN",
    "gn:dem":854,
    "gn:feature_class":"P",
    "gn:feature_code":"PPL",
    "gn:name":"Sanpucun",
    "gn:population":0,
    "gn:timezone":"Asia/Shanghai",
    "iso:country":"CN",
    "name:und_x_variant":[
        "\u4e09\u6d66\u6751"
    ],
    "wof:name":"Sanpucun",
    "wof:placetype":"locality"
},
  "geometry": {"coordinates":[128.06502,41.49457],"type":"Point"}
}