{
  "type": "Feature",
  "properties": {
    "gn:admin1_code":"30.0",
    "gn:asciiname":"Changzhukeng",
    "gn:country_code":"CN",
    "gn:dem":650,
    "gn:feature_class":"P",
    "gn:feature_code":"PPL",
    "gn:name":"Changzhukeng",
    "gn:population":0,
    "gn:timezone":"Asia/Shanghai",
    "iso:country":"CN",
    "name:zho_x_preferred":[
        "Changzhukeng"
    ],
    "name:zho_x_variant":[
        "\u957f\u73e0\u5751"
    ],
    "wof:name":"Changzhukeng",
    "wof:placetype":"locality"
},
  "geometry": {"coordinates":[113.5825,25.27167],"type":"Point"}
}