{
  "type": "Feature",
  "properties": {
    "gn:admin1_code":"02",
    "gn:asciiname":"Zhutucun",
    "gn:country_code":"CN",
    "gn:dem":20,
    "gn:feature_class":"P",
    "gn:feature_code":"PPL",
    "gn:name":"Zhutucun",
    "gn:population":0,
    "gn:timezone":"Asia/Shanghai",
    "iso:country":"CN",
    "name:und_x_variant":[
        "Zhutu",
        "Zhutucun"
    ],
    "name:zho_x_preferred":[
        "\u6731\u6d82"
    ],
    "name:zho_x_variant":[
        "\u6731\u6d82\u6751"
    ],
    "wof:name":"Zhutucun",
    "wof:placetype":"locality"
},
  "geometry": {"coordinates":[120.48927,28.1491],"type":"Point"}
}