{
  "type": "Feature",
  "properties": {
    "gn:admin1_code":"19.0",
    "gn:asciiname":"Xialouzi",
    "gn:country_code":"CN",
    "gn:dem":84,
    "gn:feature_class":"P",
    "gn:feature_code":"PPL",
    "gn:name":"Xialouzi",
    "gn:population":0,
    "gn:timezone":"Asia/Shanghai",
    "iso:country":"CN",
    "name:und_x_variant":[
        "\u4e0b\u697c\u5b50"
    ],
    "name:zho_x_preferred":[
        "\u4e0b\u697c\u5b50"
    ],
    "wof:name":"Xialouzi",
    "wof:placetype":"locality"
},
  "geometry": {"coordinates":[123.67328999999999,41.71093],"type":"Point"}
}