{
  "type": "Feature",
  "properties": {
    "gn:admin1_code":"12.0",
    "gn:asciiname":"Cheliaoba",
    "gn:country_code":"CN",
    "gn:dem":1318,
    "gn:feature_class":"P",
    "gn:feature_code":"PPL",
    "gn:name":"Cheliaoba",
    "gn:population":0,
    "gn:timezone":"Asia/Shanghai",
    "iso:country":"CN",
    "name:zho_x_preferred":[
        "Cheliaoba"
    ],
    "name:zho_x_variant":[
        "\u8f66\u84fc\u575d"
    ],
    "wof:name":"Cheliaoba",
    "wof:placetype":"locality"
},
  "geometry": {"coordinates":[109.23096,29.91728],"type":"Point"}
}