{
  "type": "Feature",
  "properties": {
    "gn:admin1_code":"12.0",
    "gn:asciiname":"Guanzhuang Zhujia",
    "gn:country_code":"CN",
    "gn:dem":40,
    "gn:feature_class":"P",
    "gn:feature_code":"PPL",
    "gn:name":"Guanzhuang Zhujia",
    "gn:population":0,
    "gn:timezone":"Asia/Shanghai",
    "iso:country":"CN",
    "name:zho_x_preferred":[
        "Guanzhuang Zhujia"
    ],
    "name:zho_x_variant":[
        "\u5b98\u5e84\u795d\u5bb6"
    ],
    "wof:name":"Guanzhuang Zhujia",
    "wof:placetype":"locality"
},
  "geometry": {"coordinates":[114.05096,29.82878],"type":"Point"}
}