{
  "type": "Feature",
  "properties": {
    "gn:admin1_code":"19.0",
    "gn:asciiname":"Shangyinghubei",
    "gn:country_code":"CN",
    "gn:dem":496,
    "gn:feature_class":"P",
    "gn:feature_code":"PPL",
    "gn:name":"Shangyinghubei",
    "gn:population":0,
    "gn:timezone":"Asia/Shanghai",
    "iso:country":"CN",
    "name:und_x_variant":[
        "\u4e0a\u9e66\u864e\u80cc"
    ],
    "wof:name":"Shangyinghubei",
    "wof:placetype":"locality"
},
  "geometry": {"coordinates":[124.30089,41.27083],"type":"Point"}
}