{
  "type": "Feature",
  "properties": {
    "gn:admin1_code":"14.0",
    "gn:asciiname":"Tangba",
    "gn:country_code":"CN",
    "gn:dem":3121,
    "gn:feature_class":"P",
    "gn:feature_code":"PPL",
    "gn:name":"Tangba",
    "gn:population":0,
    "gn:timezone":"Asia/Urumqi",
    "iso:country":"CN",
    "name:bod_x_preferred":[
        "Tangba"
    ],
    "name:zho_x_preferred":[
        "Tongba"
    ],
    "name:zho_x_variant":[
        "\u6876\u5df4"
    ],
    "wof:name":"Tangba",
    "wof:placetype":"locality"
},
  "geometry": {"coordinates":[98.28198,29.82569],"type":"Point"}
}