{
  "type": "Feature",
  "properties": {
    "gn:admin1_code":"29.0",
    "gn:asciiname":"Xiaonaka",
    "gn:country_code":"CN",
    "gn:dem":2032,
    "gn:feature_class":"P",
    "gn:feature_code":"PPL",
    "gn:name":"Xiaonaka",
    "gn:population":0,
    "gn:timezone":"Asia/Shanghai",
    "iso:country":"CN",
    "name:zho_x_preferred":[
        "\u5c0f\u90a3\u5361"
    ],
    "wof:name":"Xiaonaka",
    "wof:placetype":"locality"
},
  "geometry": {"coordinates":[101.375,26.8452],"type":"Point"}
}