{
  "type": "Feature",
  "properties": {
    "gn:admin1_code":"15.0",
    "gn:asciiname":"Pengjiahe",
    "gn:country_code":"CN",
    "gn:dem":1803,
    "gn:feature_class":"P",
    "gn:feature_code":"PPL",
    "gn:name":"Pengjiahe",
    "gn:population":0,
    "gn:timezone":"Asia/Shanghai",
    "iso:country":"CN",
    "name:und_x_variant":[
        "\u5f6d\u5bb6\u6cb3"
    ],
    "wof:name":"Pengjiahe",
    "wof:placetype":"locality"
},
  "geometry": {"coordinates":[105.07143000000001,35.54868],"type":"Point"}
}