{
  "type": "Feature",
  "properties": {
    "gn:admin1_code":"4.0",
    "gn:asciiname":"Xiaojian",
    "gn:country_code":"CN",
    "gn:dem":4,
    "gn:feature_class":"P",
    "gn:feature_code":"PPL",
    "gn:name":"Xiaojian",
    "gn:population":0,
    "gn:timezone":"Asia/Shanghai",
    "iso:country":"CN",
    "name:zho_x_preferred":[
        "Xiaojian"
    ],
    "name:zho_x_variant":[
        "\u5c0f\u5c16"
    ],
    "wof:name":"Xiaojian",
    "wof:placetype":"locality"
},
  "geometry": {"coordinates":[121.12085999999999,32.12989],"type":"Point"}
}