{
  "type": "Feature",
  "properties": {
    "gn:admin1_code":"2.0",
    "gn:asciiname":"Xi'ao",
    "gn:country_code":"CN",
    "gn:dem":55,
    "gn:feature_class":"P",
    "gn:feature_code":"PPL",
    "gn:name":"Xi\u2019ao",
    "gn:population":0,
    "gn:timezone":"Asia/Shanghai",
    "iso:country":"CN",
    "name:zho_x_preferred":[
        "\u897f\u5c99"
    ],
    "name:zho_x_variant":[
        "Xi\u2019ao"
    ],
    "wof:name":"Xi'ao",
    "wof:placetype":"locality"
},
  "geometry": {"coordinates":[120.57556,29.90142],"type":"Point"}
}