{
  "type": "Feature",
  "properties": {
    "gn:admin1_code":"4.0",
    "gn:asciiname":"Chengzhuang",
    "gn:country_code":"CN",
    "gn:dem":19,
    "gn:feature_class":"P",
    "gn:feature_code":"PPL",
    "gn:name":"Chengzhuang",
    "gn:population":0,
    "gn:timezone":"Asia/Shanghai",
    "iso:country":"CN",
    "name:zho_x_preferred":[
        "\u7a0b\u5e84"
    ],
    "wof:name":"Chengzhuang",
    "wof:placetype":"locality"
},
  "geometry": {"coordinates":[118.91494,32.98251],"type":"Point"}
}