{
  "type": "Feature",
  "properties": {
    "gn:admin1_code":"30",
    "gn:asciiname":"Dijiang",
    "gn:country_code":"CN",
    "gn:dem":35,
    "gn:feature_class":"P",
    "gn:feature_code":"PPL",
    "gn:name":"Dijiang",
    "gn:population":0,
    "gn:timezone":"Asia/Urumqi",
    "iso:country":"CN",
    "name:zho_x_preferred":[
        "\u4f4e\u6c5f"
    ],
    "wof:name":"Dijiang",
    "wof:placetype":"locality"
},
  "geometry": {"coordinates":[109.96727,21.69695],"type":"Point"}
}