{
  "type": "Feature",
  "properties": {
    "gn:admin1_code":"18",
    "gn:asciiname":"Guanwen",
    "gn:country_code":"CN",
    "gn:dem":605,
    "gn:feature_class":"P",
    "gn:feature_code":"PPL",
    "gn:name":"Guanwen",
    "gn:population":0,
    "gn:timezone":"Asia/Shanghai",
    "iso:country":"CN",
    "name:fra_x_preferred":[
        "Guan Wen"
    ],
    "name:zho_x_preferred":[
        "\u89c2\u6587"
    ],
    "wof:name":"Guanwen",
    "wof:placetype":"locality"
},
  "geometry": {"coordinates":[106.039,25.5048],"type":"Point"}
}