{
  "type": "Feature",
  "properties": {
    "gn:admin1_code":"3.0",
    "gn:asciiname":"Dacangxia",
    "gn:country_code":"CN",
    "gn:dem":102,
    "gn:feature_class":"P",
    "gn:feature_code":"PPL",
    "gn:name":"Dacangxia",
    "gn:population":0,
    "gn:timezone":"Asia/Shanghai",
    "iso:country":"CN",
    "name:und_x_variant":[
        "\u5927\u4ed3\u4e0b"
    ],
    "wof:name":"Dacangxia",
    "wof:placetype":"locality"
},
  "geometry": {"coordinates":[116.51267,27.10499],"type":"Point"}
}