{
  "type": "Feature",
  "properties": {
    "gn:admin1_code":"4.0",
    "gn:asciiname":"Daxiangli",
    "gn:country_code":"CN",
    "gn:dem":5,
    "gn:feature_class":"P",
    "gn:feature_code":"PPL",
    "gn:name":"Daxiangli",
    "gn:population":0,
    "gn:timezone":"Asia/Shanghai",
    "iso:country":"CN",
    "name:zho_x_preferred":[
        "\u5927\u7965\u91cc"
    ],
    "wof:name":"Daxiangli",
    "wof:placetype":"locality"
},
  "geometry": {"coordinates":[119.60545,31.8643],"type":"Point"}
}