{
  "type": "Feature",
  "properties": {
    "gn:admin1_code":"22.0",
    "gn:asciiname":"Shangfangcun",
    "gn:country_code":"CN",
    "gn:dem":627,
    "gn:feature_class":"P",
    "gn:feature_code":"PPL",
    "gn:name":"Shangfangcun",
    "gn:population":0,
    "gn:timezone":"Asia/Shanghai",
    "iso:country":"CN",
    "name:zho_x_preferred":[
        "\u4e0a\u623f\u6751"
    ],
    "wof:name":"Shangfangcun",
    "wof:placetype":"locality"
},
  "geometry": {"coordinates":[116.53846,40.79328],"type":"Point"}
}