{
  "type": "Feature",
  "properties": {
    "gn:admin1_code":"12",
    "gn:asciiname":"Kuzhu Goukou",
    "gn:country_code":"CN",
    "gn:dem":520,
    "gn:feature_class":"P",
    "gn:feature_code":"PPL",
    "gn:name":"Kuzhu Goukou",
    "gn:population":0,
    "gn:timezone":"Asia/Shanghai",
    "iso:country":"CN",
    "name:zho_x_preferred":[
        "\u82e6\u7af9\u6c9f\u53e3"
    ],
    "wof:name":"Kuzhu Goukou",
    "wof:placetype":"locality"
},
  "geometry": {"coordinates":[110.16623,32.47000999999999],"type":"Point"}
}