{
  "type": "Feature",
  "properties": {
    "gn:admin1_code":"32.0",
    "gn:asciiname":"Xianhua",
    "gn:country_code":"CN",
    "gn:dem":390,
    "gn:feature_class":"P",
    "gn:feature_code":"PPL",
    "gn:name":"Xianhua",
    "gn:population":0,
    "gn:timezone":"Asia/Shanghai",
    "iso:country":"CN",
    "name:zho_x_preferred":[
        "\u9c9c\u82b1"
    ],
    "wof:name":"Xianhua",
    "wof:placetype":"locality"
},
  "geometry": {"coordinates":[105.387,29.4352],"type":"Point"}
}