{
  "type": "Feature",
  "properties": {
    "gn:admin1_code":"16",
    "gn:asciiname":"Shang'anli",
    "gn:country_code":"CN",
    "gn:dem":616,
    "gn:feature_class":"P",
    "gn:feature_code":"PPL",
    "gn:name":"Shang\u2019anli",
    "gn:population":0,
    "gn:timezone":"Asia/Shanghai",
    "iso:country":"CN",
    "name:und_x_variant":[
        "Shang\u2019anli"
    ],
    "name:zho_x_preferred":[
        "\u4e0a\u5eb5\u91cc"
    ],
    "wof:name":"Shang'anli",
    "wof:placetype":"locality"
},
  "geometry": {"coordinates":[110.63800000000001,25.9006],"type":"Point"}
}