{
  "type": "Feature",
  "properties": {
    "gn:admin1_code":"18.0",
    "gn:asciiname":"Zixin",
    "gn:country_code":"CN",
    "gn:dem":2103,
    "gn:feature_class":"P",
    "gn:feature_code":"PPL",
    "gn:name":"Zixin",
    "gn:population":0,
    "gn:timezone":"Asia/Shanghai",
    "iso:country":"CN",
    "wof:name":"Zixin",
    "wof:placetype":"locality"
},
  "geometry": {"coordinates":[105.15000000000001,26.80833],"type":"Point"}
}