{
  "type": "Feature",
  "properties": {
    "gn:admin1_code":"10.0",
    "gn:asciiname":"Huguanzhuang",
    "gn:country_code":"CN",
    "gn:dem":12,
    "gn:feature_class":"P",
    "gn:feature_code":"PPL",
    "gn:name":"Huguanzhuang",
    "gn:population":0,
    "gn:timezone":"Asia/Shanghai",
    "iso:country":"CN",
    "name:zho_x_preferred":[
        "\u80e1\u5b98\u5e84"
    ],
    "wof:name":"Huguanzhuang",
    "wof:placetype":"locality"
},
  "geometry": {"coordinates":[116.30800000000001,38.4172],"type":"Point"}
}