{
  "type": "Feature",
  "properties": {
    "gn:admin1_code":"10.0",
    "gn:asciiname":"Xiangshuigou",
    "gn:country_code":"CN",
    "gn:dem":1404,
    "gn:feature_class":"P",
    "gn:feature_code":"PPL",
    "gn:name":"Xiangshuigou",
    "gn:population":0,
    "gn:timezone":"Asia/Shanghai",
    "iso:country":"CN",
    "name:zho_x_preferred":[
        "\u54cd\u6c34\u6c9f"
    ],
    "wof:name":"Xiangshuigou",
    "wof:placetype":"locality"
},
  "geometry": {"coordinates":[115.34272,40.77874],"type":"Point"}
}