{
  "type": "Feature",
  "properties": {
    "gn:admin1_code":"31.0",
    "gn:asciiname":"Xinglong Erqu",
    "gn:country_code":"CN",
    "gn:dem":79,
    "gn:feature_class":"P",
    "gn:feature_code":"PPL",
    "gn:name":"Xinglong Erqu",
    "gn:population":0,
    "gn:timezone":"Asia/Shanghai",
    "iso:country":"CN",
    "name:und_x_variant":[
        "\u5174\u9686\u4e8c\u533a"
    ],
    "wof:name":"Xinglong Erqu",
    "wof:placetype":"locality"
},
  "geometry": {"coordinates":[110.15210999999999,18.76819],"type":"Point"}
}