{
  "type": "Feature",
  "properties": {
    "gn:admin1_code":"3.0",
    "gn:asciiname":"Xiazhujing",
    "gn:country_code":"CN",
    "gn:dem":101,
    "gn:feature_class":"P",
    "gn:feature_code":"PPL",
    "gn:name":"Xiazhujing",
    "gn:population":0,
    "gn:timezone":"Asia/Shanghai",
    "iso:country":"CN",
    "name:und_x_variant":[
        "\u4e0b\u7af9\u5f84"
    ],
    "wof:name":"Xiazhujing",
    "wof:placetype":"locality"
},
  "geometry": {"coordinates":[114.41562999999999,27.79817],"type":"Point"}
}