{
  "type": "Feature",
  "properties": {
    "gn:admin1_code":"16",
    "gn:asciiname":"Datangkou",
    "gn:country_code":"CN",
    "gn:dem":178,
    "gn:feature_class":"P",
    "gn:feature_code":"PPL",
    "gn:name":"Datangkou",
    "gn:population":0,
    "gn:timezone":"Asia/Shanghai",
    "iso:country":"CN",
    "name:zho_x_preferred":[
        "\u5927\u5858\u53e3"
    ],
    "wof:name":"Datangkou",
    "wof:placetype":"locality"
},
  "geometry": {"coordinates":[110.39100000000001,24.75800000000001],"type":"Point"}
}