{
  "type": "Feature",
  "properties": {
    "gn:admin1_code":"19.0",
    "gn:asciiname":"Gusao Shigou",
    "gn:country_code":"CN",
    "gn:dem":120,
    "gn:feature_class":"P",
    "gn:feature_code":"PPL",
    "gn:name":"Gusao Shigou",
    "gn:population":0,
    "gn:timezone":"Asia/Shanghai",
    "iso:country":"CN",
    "name:und_x_variant":[
        "\u59d1\u5ac2\u77f3\u6c9f"
    ],
    "wof:name":"Gusao Shigou",
    "wof:placetype":"locality"
},
  "geometry": {"coordinates":[123.30540000000001,40.31594000000001],"type":"Point"}
}