{
  "type": "Feature",
  "properties": {
    "gn:admin1_code":"29.0",
    "gn:asciiname":"Niufengdui",
    "gn:country_code":"CN",
    "gn:dem":1412,
    "gn:feature_class":"P",
    "gn:feature_code":"PPL",
    "gn:name":"Niufengdui",
    "gn:population":0,
    "gn:timezone":"Asia/Shanghai",
    "iso:country":"CN",
    "name:zho_x_preferred":[
        "\u725b\u5cf0\u5806"
    ],
    "wof:name":"Niufengdui",
    "wof:placetype":"locality"
},
  "geometry": {"coordinates":[100.44,26.2572],"type":"Point"}
}