{
  "type": "Feature",
  "properties": {
    "gn:admin1_code":"4.0",
    "gn:asciiname":"Fengzhuang",
    "gn:country_code":"CN",
    "gn:dem":4,
    "gn:feature_class":"P",
    "gn:feature_code":"PPL",
    "gn:name":"Fengzhuang",
    "gn:population":0,
    "gn:timezone":"Asia/Shanghai",
    "iso:country":"CN",
    "name:und_x_variant":[
        "\u8451\u5e84"
    ],
    "name:zho_x_preferred":[
        "\u8451\u5e84"
    ],
    "wof:name":"Fengzhuang",
    "wof:placetype":"locality"
},
  "geometry": {"coordinates":[120.16114,31.69087],"type":"Point"}
}