{
  "type": "Feature",
  "properties": {
    "gn:admin1_code":"1.0",
    "gn:asciiname":"Qiaohecun",
    "gn:country_code":"CN",
    "gn:dem":47,
    "gn:feature_class":"P",
    "gn:feature_code":"PPL",
    "gn:name":"Qiaohecun",
    "gn:population":0,
    "gn:timezone":"Asia/Shanghai",
    "iso:country":"CN",
    "name:zho_x_preferred":[
        "\u6865\u6cb3\u6751"
    ],
    "wof:name":"Qiaohecun",
    "wof:placetype":"locality"
},
  "geometry": {"coordinates":[117.13652,31.21322],"type":"Point"}
}