{
  "type": "Feature",
  "properties": {
    "gn:admin1_code":"3.0",
    "gn:asciiname":"Luxi",
    "gn:country_code":"CN",
    "gn:dem":112,
    "gn:feature_class":"P",
    "gn:feature_code":"PPL",
    "gn:name":"Luxi",
    "gn:population":0,
    "gn:timezone":"Asia/Shanghai",
    "iso:country":"CN",
    "name:ceb_x_preferred":[
        "Luxi"
    ],
    "name:deu_x_preferred":[
        "Luxi"
    ],
    "name:fra_x_preferred":[
        "Luxi"
    ],
    "name:kor_x_preferred":[
        "\ub8e8\uc2dc\ud604"
    ],
    "name:nor_x_preferred":[
        "Luxi"
    ],
    "name:swe_x_preferred":[
        "Luxi"
    ],
    "name:und_x_variant":[
        "\u82a6\u6eaa",
        "Luxi Xiang",
        "\u82a6\u6eaa\u4e61"
    ],
    "wof:name":"Luxi",
    "wof:placetype":"locality"
},
  "geometry": {"coordinates":[114.32689999999999,27.1512],"type":"Point"}
}