{
  "type": "Feature",
  "properties": {
    "gn:admin1_code":"3.0",
    "gn:asciiname":"Caotoukeng",
    "gn:country_code":"CN",
    "gn:dem":254,
    "gn:feature_class":"P",
    "gn:feature_code":"PPL",
    "gn:name":"Caotoukeng",
    "gn:population":0,
    "gn:timezone":"Asia/Shanghai",
    "iso:country":"CN",
    "name:und_x_variant":[
        "\u8349\u5934\u5751"
    ],
    "wof:name":"Caotoukeng",
    "wof:placetype":"locality"
},
  "geometry": {"coordinates":[115.85827,26.45613],"type":"Point"}
}