{
  "type": "Feature",
  "properties": {
    "gn:admin1_code":"19.0",
    "gn:asciiname":"Zhumintuncun",
    "gn:country_code":"CN",
    "gn:dem":53,
    "gn:feature_class":"P",
    "gn:feature_code":"PPL",
    "gn:name":"Zhumintuncun",
    "gn:population":0,
    "gn:timezone":"Asia/Shanghai",
    "iso:country":"CN",
    "name:zho_x_preferred":[
        "\u8bf8\u6c11\u5c6f\u6751"
    ],
    "wof:name":"Zhumintuncun",
    "wof:placetype":"locality"
},
  "geometry": {"coordinates":[123.562,42.1292],"type":"Point"}
}