{
  "type": "Feature",
  "properties": {
    "gn:admin1_code":"16.0",
    "gn:asciiname":"Tangshi Xiaba",
    "gn:country_code":"CN",
    "gn:dem":1335,
    "gn:feature_class":"P",
    "gn:feature_code":"PPL",
    "gn:name":"Tangshi Xiaba",
    "gn:population":0,
    "gn:timezone":"Asia/Shanghai",
    "iso:country":"CN",
    "name:zho_x_preferred":[
        "\u5858\u77f3\u4e0b\u575d"
    ],
    "wof:name":"Tangshi Xiaba",
    "wof:placetype":"locality"
},
  "geometry": {"coordinates":[105.233,24.6105],"type":"Point"}
}