{
  "type": "Feature",
  "properties": {
    "gn:admin1_code":"16.0",
    "gn:asciiname":"Tianchi",
    "gn:country_code":"CN",
    "gn:dem":584,
    "gn:feature_class":"P",
    "gn:feature_code":"PPL",
    "gn:name":"Tianchi",
    "gn:population":0,
    "gn:timezone":"Asia/Shanghai",
    "iso:country":"CN",
    "name:ceb_x_preferred":[
        "Tianchi"
    ],
    "name:deu_x_preferred":[
        "Tian Chi"
    ],
    "name:fra_x_preferred":[
        "Tianchi"
    ],
    "name:jpn_x_preferred":[
        "\u5929\u6c60"
    ],
    "name:nld_x_preferred":[
        "Tianchi"
    ],
    "name:vie_x_preferred":[
        "Thi\u00ean Tr\u00ec"
    ],
    "name:zho_x_preferred":[
        "\u5929\u6c60"
    ],
    "wof:name":"Tianchi",
    "wof:placetype":"locality"
},
  "geometry": {"coordinates":[105.991,22.9848],"type":"Point"}
}