{
  "type": "Feature",
  "properties": {
    "gn:admin1_code":"33",
    "gn:asciiname":"Tailong",
    "gn:country_code":"CN",
    "gn:dem":315,
    "gn:feature_class":"P",
    "gn:feature_code":"PPLA4",
    "gn:name":"Tailong",
    "gn:population":0,
    "gn:timezone":"Asia/Shanghai",
    "iso:country":"CN",
    "name:und_x_variant":[
        "Tailong Zhen"
    ],
    "name:zho_x_preferred":[
        "\u592a\u9f99"
    ],
    "name:zho_x_variant":[
        "\u592a\u9f99\u9547"
    ],
    "wof:name":"Tailong",
    "wof:placetype":"locality"
},
  "geometry": {"coordinates":[108.52415000000001,30.89791],"type":"Point"}
}