{
  "type": "Feature",
  "properties": {
    "gn:admin1_code":"4.0",
    "gn:asciiname":"Zhongzhaicun",
    "gn:country_code":"CN",
    "gn:dem":46,
    "gn:feature_class":"P",
    "gn:feature_code":"PPL",
    "gn:name":"Zhongzhaicun",
    "gn:population":0,
    "gn:timezone":"Asia/Shanghai",
    "iso:country":"CN",
    "name:zho_x_preferred":[
        "\u4e2d\u5be8\u6751"
    ],
    "wof:name":"Zhongzhaicun",
    "wof:placetype":"locality"
},
  "geometry": {"coordinates":[118.45929,34.61627],"type":"Point"}
}