{
  "type": "Feature",
  "properties": {
    "gn:admin1_code":"29.0",
    "gn:asciiname":"Laochengchai",
    "gn:country_code":"CN",
    "gn:dem":1755,
    "gn:feature_class":"P",
    "gn:feature_code":"PPL",
    "gn:name":"Laochengchai",
    "gn:population":0,
    "gn:timezone":"Asia/Shanghai",
    "iso:country":"CN",
    "name:zho_x_preferred":[
        "\u8001\u7a0b\u67f4"
    ],
    "wof:name":"Laochengchai",
    "wof:placetype":"locality"
},
  "geometry": {"coordinates":[103.36799999999999,23.7704],"type":"Point"}
}