{
  "type": "Feature",
  "properties": {
    "gn:admin1_code":"25",
    "gn:asciiname":"Wupinglou",
    "gn:country_code":"CN",
    "gn:dem":52,
    "gn:feature_class":"P",
    "gn:feature_code":"PPL",
    "gn:name":"Wupinglou",
    "gn:population":0,
    "gn:timezone":"Asia/Shanghai",
    "iso:country":"CN",
    "name:zho_x_preferred":[
        "\u6b66\u5e73\u697c"
    ],
    "wof:name":"Wupinglou",
    "wof:placetype":"locality"
},
  "geometry": {"coordinates":[115.592,34.8928],"type":"Point"}
}