{
  "type": "Feature",
  "properties": {
    "gn:admin1_code":"3.0",
    "gn:asciiname":"Honghuashan",
    "gn:country_code":"CN",
    "gn:dem":640,
    "gn:feature_class":"P",
    "gn:feature_code":"PPL",
    "gn:name":"Honghuashan",
    "gn:population":0,
    "gn:timezone":"Asia/Shanghai",
    "iso:country":"CN",
    "name:und_x_variant":[
        "\u7ea2\u82b1\u5c71"
    ],
    "wof:name":"Honghuashan",
    "wof:placetype":"locality"
},
  "geometry": {"coordinates":[114.56520999999999,27.71096],"type":"Point"}
}