{
  "type": "Feature",
  "properties": {
    "gn:admin1_code":"26.0",
    "gn:asciiname":"Nanyangmucun",
    "gn:country_code":"CN",
    "gn:dem":812,
    "gn:feature_class":"P",
    "gn:feature_code":"PPLF",
    "gn:name":"Nanyangmucun",
    "gn:population":0,
    "gn:timezone":"Asia/Shanghai",
    "iso:country":"CN",
    "name:zho_x_preferred":[
        "\u5357\u7f8a\u7267\u6751"
    ],
    "wof:name":"Nanyangmucun",
    "wof:placetype":"locality"
},
  "geometry": {"coordinates":[108.30788,34.60045],"type":"Point"}
}