{
  "type": "Feature",
  "properties": {
    "gn:admin1_code":"32.0",
    "gn:asciiname":"Xiang'e",
    "gn:country_code":"CN",
    "gn:dem":770,
    "gn:feature_class":"P",
    "gn:feature_code":"PPL",
    "gn:name":"Xiang\u2019e",
    "gn:population":0,
    "gn:timezone":"Asia/Shanghai",
    "iso:country":"CN",
    "name:zho_x_preferred":[
        "\u5411\u5ce8"
    ],
    "name:zho_x_variant":[
        "Xiang\u2019e"
    ],
    "wof:name":"Xiang'e",
    "wof:placetype":"locality"
},
  "geometry": {"coordinates":[103.71563999999999,31.08505],"type":"Point"}
}