{
  "type": "Feature",
  "properties": {
    "gn:admin1_code":"3.0",
    "gn:asciiname":"Huaini",
    "gn:country_code":"CN",
    "gn:dem":38,
    "gn:feature_class":"P",
    "gn:feature_code":"PPL",
    "gn:name":"Huaini",
    "gn:population":0,
    "gn:timezone":"Asia/Shanghai",
    "iso:country":"CN",
    "name:und_x_variant":[
        "\u6dee\u6ce5"
    ],
    "wof:name":"Huaini",
    "wof:placetype":"locality"
},
  "geometry": {"coordinates":[115.10024,27.84163],"type":"Point"}
}