{
  "type": "Feature",
  "properties": {
    "gn:admin1_code":"26.0",
    "gn:asciiname":"Xujiabucun",
    "gn:country_code":"CN",
    "gn:dem":483,
    "gn:feature_class":"P",
    "gn:feature_code":"PPL",
    "gn:name":"Xujiabucun",
    "gn:population":0,
    "gn:timezone":"Asia/Shanghai",
    "iso:country":"CN",
    "name:und_x_variant":[
        "\u5f90\u5bb6\u5821\u6751"
    ],
    "wof:name":"Xujiabucun",
    "wof:placetype":"locality"
},
  "geometry": {"coordinates":[107.25845,33.09138],"type":"Point"}
}