{
  "type": "Feature",
  "properties": {
    "gn:admin1_code":"3.0",
    "gn:asciiname":"Guancaochi",
    "gn:country_code":"CN",
    "gn:dem":92,
    "gn:feature_class":"P",
    "gn:feature_code":"PPL",
    "gn:name":"Guancaochi",
    "gn:population":0,
    "gn:timezone":"Asia/Shanghai",
    "iso:country":"CN",
    "name:zho_x_preferred":[
        "\u839e\u8349\u6c60"
    ],
    "wof:name":"Guancaochi",
    "wof:placetype":"locality"
},
  "geometry": {"coordinates":[117.73175999999999,28.39925],"type":"Point"}
}