{
  "type": "Feature",
  "properties": {
    "gn:admin1_code":"12",
    "gn:asciiname":"Zhuchang",
    "gn:country_code":"CN",
    "gn:dem":31,
    "gn:feature_class":"P",
    "gn:feature_code":"PPL",
    "gn:name":"Zhuchang",
    "gn:population":0,
    "gn:timezone":"Asia/Shanghai",
    "iso:country":"CN",
    "name:und_x_variant":[
        "Chu-chia-ch\u2019ang",
        "Zhuchang",
        "\u6731\u573a"
    ],
    "wof:name":"Zhuchang",
    "wof:placetype":"locality"
},
  "geometry": {"coordinates":[112.40537999999999,30.39919],"type":"Point"}
}