{
  "type": "Feature",
  "properties": {
    "gn:admin1_code":"7",
    "gn:asciiname":"Changtaiyang",
    "gn:country_code":"CN",
    "gn:dem":146,
    "gn:feature_class":"P",
    "gn:feature_code":"PPL",
    "gn:name":"Changtaiyang",
    "gn:population":0,
    "gn:timezone":"Asia/Shanghai",
    "iso:country":"CN",
    "name:zho_x_preferred":[
        "\u957f\u592a\u6d0b"
    ],
    "wof:name":"Changtaiyang",
    "wof:placetype":"locality"
},
  "geometry": {"coordinates":[118.72926,25.72157],"type":"Point"}
}