{
  "type": "Feature",
  "properties": {
    "gn:admin1_code":"30.0",
    "gn:asciiname":"Fangtiankeng",
    "gn:country_code":"CN",
    "gn:dem":227,
    "gn:feature_class":"P",
    "gn:feature_code":"PPL",
    "gn:name":"Fangtiankeng",
    "gn:population":0,
    "gn:timezone":"Asia/Shanghai",
    "iso:country":"CN",
    "name:und_x_variant":[
        "\u65b9\u7530\u5751"
    ],
    "name:zho_x_preferred":[
        "\u65b9\u7530\u5751"
    ],
    "wof:name":"Fangtiankeng",
    "wof:placetype":"locality"
},
  "geometry": {"coordinates":[115.00766000000002,23.99621],"type":"Point"}
}