{
  "type": "Feature",
  "properties": {
    "gn:admin1_code":"26.0",
    "gn:asciiname":"Qiwanzicun",
    "gn:country_code":"CN",
    "gn:dem":1388,
    "gn:feature_class":"P",
    "gn:feature_code":"PPL",
    "gn:name":"Qiwanzicun",
    "gn:population":0,
    "gn:timezone":"Asia/Shanghai",
    "iso:country":"CN",
    "name:zho_x_preferred":[
        "\u9f50\u6e7e\u5b50\u6751"
    ],
    "wof:name":"Qiwanzicun",
    "wof:placetype":"locality"
},
  "geometry": {"coordinates":[108.04904999999999,36.91473],"type":"Point"}
}