{
  "type": "Feature",
  "properties": {
    "gn:admin1_code":"15.0",
    "gn:asciiname":"Weikouyuan",
    "gn:country_code":"CN",
    "gn:dem":1086,
    "gn:feature_class":"P",
    "gn:feature_code":"PPL",
    "gn:name":"Weikouyuan",
    "gn:population":0,
    "gn:timezone":"Asia/Shanghai",
    "iso:country":"CN",
    "name:zho_x_preferred":[
        "\u6e2d\u53e3\u586c"
    ],
    "wof:name":"Weikouyuan",
    "wof:placetype":"locality"
},
  "geometry": {"coordinates":[107.876,35.4359],"type":"Point"}
}