{
  "type": "Feature",
  "properties": {
    "gn:admin1_code":"25",
    "gn:asciiname":"Beiyuanzhuang",
    "gn:country_code":"CN",
    "gn:dem":148,
    "gn:feature_class":"P",
    "gn:feature_code":"PPL",
    "gn:name":"Beiyuanzhuang",
    "gn:population":0,
    "gn:timezone":"Asia/Shanghai",
    "iso:country":"CN",
    "name:zho_x_preferred":[
        "\u5317\u82d1\u5e84"
    ],
    "wof:name":"Beiyuanzhuang",
    "wof:placetype":"locality"
},
  "geometry": {"coordinates":[117.374,35.3026],"type":"Point"}
}