{
  "type": "Feature",
  "properties": {
    "gn:admin1_code":"19.0",
    "gn:asciiname":"Tongjiajie",
    "gn:country_code":"CN",
    "gn:dem":184,
    "gn:feature_class":"P",
    "gn:feature_code":"PPL",
    "gn:name":"Tongjiajie",
    "gn:population":0,
    "gn:timezone":"Asia/Shanghai",
    "iso:country":"CN",
    "name:zho_x_preferred":[
        "\u4f5f\u5bb6\u8857"
    ],
    "wof:name":"Tongjiajie",
    "wof:placetype":"locality"
},
  "geometry": {"coordinates":[123.83035,41.52139],"type":"Point"}
}