{
  "type": "Feature",
  "properties": {
    "gn:admin1_code":"32.0",
    "gn:asciiname":"Futiansi",
    "gn:country_code":"CN",
    "gn:dem":638,
    "gn:feature_class":"P",
    "gn:feature_code":"PPL",
    "gn:name":"Futiansi",
    "gn:population":0,
    "gn:timezone":"Asia/Shanghai",
    "iso:country":"CN",
    "name:zho_x_preferred":[
        "\u798f\u7530\u5bfa"
    ],
    "wof:name":"Futiansi",
    "wof:placetype":"locality"
},
  "geometry": {"coordinates":[104.4868,31.62641],"type":"Point"}
}