{
  "type": "Feature",
  "properties": {
    "gn:admin1_code":"30",
    "gn:asciiname":"Songtou'ao",
    "gn:country_code":"CN",
    "gn:dem":509,
    "gn:feature_class":"P",
    "gn:feature_code":"PPL",
    "gn:name":"Songtou\u2019ao",
    "gn:population":0,
    "gn:timezone":"Asia/Shanghai",
    "iso:country":"CN",
    "name:zho_x_preferred":[
        "Songtou\u2019ao"
    ],
    "wof:name":"Songtou'ao",
    "wof:placetype":"locality"
},
  "geometry": {"coordinates":[115.80777999999999,23.21722],"type":"Point"}
}