{
  "type": "Feature",
  "properties": {
    "gn:admin1_code":"1.0",
    "gn:asciiname":"Zhangzhaicun",
    "gn:country_code":"CN",
    "gn:dem":32,
    "gn:feature_class":"P",
    "gn:feature_code":"PPL",
    "gn:name":"Zhangzhaicun",
    "gn:population":0,
    "gn:timezone":"Asia/Shanghai",
    "iso:country":"CN",
    "name:zho_x_preferred":[
        "\u5f20\u5be8\u6751"
    ],
    "wof:name":"Zhangzhaicun",
    "wof:placetype":"locality"
},
  "geometry": {"coordinates":[116.23386000000001,33.45746],"type":"Point"}
}