{
  "type": "Feature",
  "properties": {
    "gn:admin1_code":"8.0",
    "gn:asciiname":"Shunxingcun",
    "gn:country_code":"CN",
    "gn:dem":185,
    "gn:feature_class":"P",
    "gn:feature_code":"PPL",
    "gn:name":"Shunxingcun",
    "gn:population":0,
    "gn:timezone":"Asia/Shanghai",
    "iso:country":"CN",
    "name:zho_x_preferred":[
        "\u987a\u5174\u6751"
    ],
    "wof:name":"Shunxingcun",
    "wof:placetype":"locality"
},
  "geometry": {"coordinates":[123.22662,47.57612],"type":"Point"}
}