{
  "type": "Feature",
  "properties": {
    "gn:admin1_code":"9.0",
    "gn:asciiname":"Hupan",
    "gn:country_code":"CN",
    "gn:dem":650,
    "gn:feature_class":"P",
    "gn:feature_code":"PPL",
    "gn:name":"Hupan",
    "gn:population":0,
    "gn:timezone":"Asia/Shanghai",
    "iso:country":"CN",
    "name:und_x_variant":[
        "\u864e\u76d8",
        "Hupan"
    ],
    "wof:name":"Hupan",
    "wof:placetype":"locality"
},
  "geometry": {"coordinates":[112.45706,33.90838],"type":"Point"}
}