{
  "type": "Feature",
  "properties": {
    "gn:admin1_code":"19.0",
    "gn:asciiname":"Langjiatun",
    "gn:country_code":"CN",
    "gn:dem":149,
    "gn:feature_class":"P",
    "gn:feature_code":"PPL",
    "gn:name":"Langjiatun",
    "gn:population":0,
    "gn:timezone":"Asia/Shanghai",
    "iso:country":"CN",
    "name:zho_x_preferred":[
        "\u90ce\u5bb6\u5c6f"
    ],
    "wof:name":"Langjiatun",
    "wof:placetype":"locality"
},
  "geometry": {"coordinates":[124.23139999999999,43.22239],"type":"Point"}
}