{
  "type": "Feature",
  "properties": {
    "gn:admin1_code":"19.0",
    "gn:asciiname":"Dabatuncun",
    "gn:country_code":"CN",
    "gn:dem":56,
    "gn:feature_class":"P",
    "gn:feature_code":"PPL",
    "gn:name":"Dabatuncun",
    "gn:population":0,
    "gn:timezone":"Asia/Shanghai",
    "iso:country":"CN",
    "name:zho_x_preferred":[
        "\u5927\u5df4\u5c6f\u6751"
    ],
    "wof:name":"Dabatuncun",
    "wof:placetype":"locality"
},
  "geometry": {"coordinates":[122.758,42.2129],"type":"Point"}
}