{
  "type": "Feature",
  "properties": {
    "gn:admin1_code":"16.0",
    "gn:asciiname":"Long'an",
    "gn:country_code":"CN",
    "gn:dem":115,
    "gn:feature_class":"P",
    "gn:feature_code":"PPL",
    "gn:name":"Long\u2019an",
    "gn:population":0,
    "gn:timezone":"Asia/Shanghai",
    "iso:country":"CN",
    "name:ceb_x_preferred":[
        "Long'an"
    ],
    "name:fra_x_preferred":[
        "Long'an"
    ],
    "name:nor_x_preferred":[
        "Long'an"
    ],
    "name:swe_x_preferred":[
        "Long'an"
    ],
    "name:und_x_variant":[
        "Long\u2019an"
    ],
    "name:zho_x_preferred":[
        "\u9f99\u5b89"
    ],
    "wof:name":"Long'an",
    "wof:placetype":"locality"
},
  "geometry": {"coordinates":[110.364,22.6394],"type":"Point"}
}