{
  "type": "Feature",
  "properties": {
    "gn:admin1_code":"3.0",
    "gn:asciiname":"Zhuping",
    "gn:country_code":"CN",
    "gn:dem":120,
    "gn:feature_class":"P",
    "gn:feature_code":"PPLA4",
    "gn:name":"Zhuping",
    "gn:population":0,
    "gn:timezone":"Asia/Shanghai",
    "iso:country":"CN",
    "name:und_x_variant":[
        "\u7af9\u576a",
        "Zhuping Xiang",
        "\u7af9\u576a\u4e61"
    ],
    "wof:name":"Zhuping",
    "wof:placetype":"locality"
},
  "geometry": {"coordinates":[114.47481999999999,29.01161],"type":"Point"}
}