{
  "type": "Feature",
  "properties": {
    "gn:admin1_code":"32.0",
    "gn:asciiname":"Shalangba",
    "gn:country_code":"CN",
    "gn:dem":1291,
    "gn:feature_class":"P",
    "gn:feature_code":"PPL",
    "gn:name":"Shalangba",
    "gn:population":0,
    "gn:timezone":"Asia/Shanghai",
    "iso:country":"CN",
    "name:zho_x_preferred":[
        "\u6c99\u6d6a\u575d"
    ],
    "wof:name":"Shalangba",
    "wof:placetype":"locality"
},
  "geometry": {"coordinates":[106.149,27.8556],"type":"Point"}
}