{
  "type": "Feature",
  "properties": {
    "gn:admin1_code":"20",
    "gn:asciiname":"Ih",
    "gn:country_code":"CN",
    "gn:dem":354,
    "gn:feature_class":"P",
    "gn:feature_code":"PPL",
    "gn:name":"Ih",
    "gn:population":0,
    "gn:timezone":"Asia/Shanghai",
    "iso:country":"CN",
    "wof:name":"Ih",
    "wof:placetype":"locality"
},
  "geometry": {"coordinates":[121.08333,44.71667],"type":"Point"}
}