{
  "type": "Feature",
  "properties": {
    "gn:admin1_code":"15.0",
    "gn:asciiname":"Yangmajia",
    "gn:country_code":"CN",
    "gn:dem":1684,
    "gn:feature_class":"P",
    "gn:feature_code":"PPL",
    "gn:name":"Yangmajia",
    "gn:population":0,
    "gn:timezone":"Asia/Shanghai",
    "iso:country":"CN",
    "name:zho_x_preferred":[
        "\u9633\u9a6c\u5bb6"
    ],
    "wof:name":"Yangmajia",
    "wof:placetype":"locality"
},
  "geometry": {"coordinates":[105.93600000000001,34.9261],"type":"Point"}
}