{
  "type": "Feature",
  "properties": {
    "gn:admin1_code":"15.0",
    "gn:asciiname":"Panluhe",
    "gn:country_code":"CN",
    "gn:dem":2600,
    "gn:feature_class":"P",
    "gn:feature_code":"PPL",
    "gn:name":"Panluhe",
    "gn:population":0,
    "gn:timezone":"Asia/Shanghai",
    "iso:country":"CN",
    "name:und_x_variant":[
        "\u76d8\u8def\u6cb3"
    ],
    "wof:name":"Panluhe",
    "wof:placetype":"locality"
},
  "geometry": {"coordinates":[104.03506,34.33524],"type":"Point"}
}