{
  "type": "Feature",
  "properties": {
    "gn:admin1_code":"12.0",
    "gn:asciiname":"Ningjiawan",
    "gn:country_code":"CN",
    "gn:dem":135,
    "gn:feature_class":"P",
    "gn:feature_code":"PPL",
    "gn:name":"Ningjiawan",
    "gn:population":0,
    "gn:timezone":"Asia/Shanghai",
    "iso:country":"CN",
    "name:zho_x_preferred":[
        "\u5b81\u5bb6\u6e7e"
    ],
    "wof:name":"Ningjiawan",
    "wof:placetype":"locality"
},
  "geometry": {"coordinates":[111.83416,31.88321],"type":"Point"}
}