{
  "type": "Feature",
  "properties": {
    "gn:admin1_code":"4.0",
    "gn:asciiname":"Zushidian",
    "gn:country_code":"CN",
    "gn:dem":6,
    "gn:feature_class":"P",
    "gn:feature_code":"PPL",
    "gn:name":"Zushidian",
    "gn:population":0,
    "gn:timezone":"Asia/Shanghai",
    "iso:country":"CN",
    "name:zho_x_preferred":[
        "\u7956\u5e08\u6bbf"
    ],
    "wof:name":"Zushidian",
    "wof:placetype":"locality"
},
  "geometry": {"coordinates":[120.78971,32.11543],"type":"Point"}
}