{
  "type": "Feature",
  "properties": {
    "gn:admin1_code":"1.0",
    "gn:asciiname":"Shengpucun",
    "gn:country_code":"CN",
    "gn:dem":58,
    "gn:feature_class":"P",
    "gn:feature_code":"PPL",
    "gn:name":"Shengpucun",
    "gn:population":0,
    "gn:timezone":"Asia/Shanghai",
    "iso:country":"CN",
    "name:zho_x_preferred":[
        "\u7ef3\u94fa\u6751"
    ],
    "wof:name":"Shengpucun",
    "wof:placetype":"locality"
},
  "geometry": {"coordinates":[115.89172000000001,31.84949000000001],"type":"Point"}
}