{
  "type": "Feature",
  "properties": {
    "gn:admin1_code":"4.0",
    "gn:asciiname":"Jiangningcun",
    "gn:country_code":"CN",
    "gn:dem":11,
    "gn:feature_class":"P",
    "gn:feature_code":"PPL",
    "gn:name":"Jiangningcun",
    "gn:population":0,
    "gn:timezone":"Asia/Shanghai",
    "iso:country":"CN",
    "name:zho_x_preferred":[
        "\u6c5f\u5b81\u6751"
    ],
    "wof:name":"Jiangningcun",
    "wof:placetype":"locality"
},
  "geometry": {"coordinates":[119.29327000000001,32.39191],"type":"Point"}
}