{
  "type": "Feature",
  "properties": {
    "gn:admin1_code":"18",
    "gn:asciiname":"Panxiong",
    "gn:country_code":"CN",
    "gn:dem":1913,
    "gn:feature_class":"P",
    "gn:feature_code":"PPL",
    "gn:name":"Panxiong",
    "gn:population":0,
    "gn:timezone":"Asia/Shanghai",
    "iso:country":"CN",
    "wof:name":"Panxiong",
    "wof:placetype":"locality"
},
  "geometry": {"coordinates":[104.78333000000001,26.83333],"type":"Point"}
}