{
  "type": "Feature",
  "properties": {
    "gn:admin1_code":"32.0",
    "gn:asciiname":"Ganhaizi",
    "gn:country_code":"CN",
    "gn:dem":1892,
    "gn:feature_class":"P",
    "gn:feature_code":"PPL",
    "gn:name":"Ganhaizi",
    "gn:population":0,
    "gn:timezone":"Asia/Shanghai",
    "iso:country":"CN",
    "name:zho_x_preferred":[
        "\u5e72\u6d77\u5b50"
    ],
    "wof:name":"Ganhaizi",
    "wof:placetype":"locality"
},
  "geometry": {"coordinates":[102.44973,30.16701],"type":"Point"}
}