{
  "type": "Feature",
  "properties": {
    "gn:admin1_code":"11.0",
    "gn:asciiname":"Liangchong",
    "gn:country_code":"CN",
    "gn:dem":111,
    "gn:feature_class":"P",
    "gn:feature_code":"PPL",
    "gn:name":"Liangchong",
    "gn:population":0,
    "gn:timezone":"Asia/Shanghai",
    "iso:country":"CN",
    "name:zho_x_preferred":[
        "\u826f\u51b2"
    ],
    "wof:name":"Liangchong",
    "wof:placetype":"locality"
},
  "geometry": {"coordinates":[112.79567,26.4543],"type":"Point"}
}