{
  "type": "Feature",
  "properties": {
    "gn:admin1_code":"05",
    "gn:asciiname":"Wenzigou",
    "gn:country_code":"CN",
    "gn:dem":844,
    "gn:feature_class":"P",
    "gn:feature_code":"PPL",
    "gn:name":"Wenzigou",
    "gn:population":0,
    "gn:timezone":"Asia/Shanghai",
    "iso:country":"CN",
    "name:und_x_variant":[
        "Ta-wen-tzu-kou",
        "Dawenzigou",
        "Wenzigou",
        "\u6587\u5b57\u6c9f"
    ],
    "wof:name":"Wenzigou",
    "wof:placetype":"locality"
},
  "geometry": {"coordinates":[126.05204000000001,41.31601],"type":"Point"}
}