{
  "type": "Feature",
  "properties": {
    "gn:admin1_code":"11.0",
    "gn:asciiname":"Mayaodong",
    "gn:country_code":"CN",
    "gn:dem":258,
    "gn:feature_class":"P",
    "gn:feature_code":"PPL",
    "gn:name":"Mayaodong",
    "gn:population":0,
    "gn:timezone":"Asia/Shanghai",
    "iso:country":"CN",
    "name:zho_x_preferred":[
        "\u9a6c\u5996\u6d1e"
    ],
    "wof:name":"Mayaodong",
    "wof:placetype":"locality"
},
  "geometry": {"coordinates":[110.82919,28.2191],"type":"Point"}
}