{
  "type": "Feature",
  "properties": {
    "gn:admin1_code":"25",
    "gn:asciiname":"Duanqiao",
    "gn:country_code":"CN",
    "gn:dem":21,
    "gn:feature_class":"P",
    "gn:feature_code":"PPL",
    "gn:name":"Duanqiao",
    "gn:population":0,
    "gn:timezone":"Asia/Shanghai",
    "iso:country":"CN",
    "name:zho_x_preferred":[
        "\u6bb5\u6865"
    ],
    "name:zho_x_variant":[
        "\u65b7\u6a4b"
    ],
    "wof:name":"Duanqiao",
    "wof:placetype":"locality"
},
  "geometry": {"coordinates":[117.577,36.9146],"type":"Point"}
}