{
  "type": "Feature",
  "properties": {
    "gn:admin1_code":"3.0",
    "gn:asciiname":"Ejingli",
    "gn:country_code":"CN",
    "gn:dem":254,
    "gn:feature_class":"P",
    "gn:feature_code":"PPL",
    "gn:name":"Ejingli",
    "gn:population":0,
    "gn:timezone":"Asia/Shanghai",
    "iso:country":"CN",
    "name:und_x_variant":[
        "\u9e45\u9888\u91cc"
    ],
    "wof:name":"Ejingli",
    "wof:placetype":"locality"
},
  "geometry": {"coordinates":[114.02424999999999,28.12104],"type":"Point"}
}