{
  "type": "Feature",
  "properties": {
    "gn:admin1_code":"18",
    "gn:asciiname":"Houbawan",
    "gn:country_code":"CN",
    "gn:dem":1044,
    "gn:feature_class":"P",
    "gn:feature_code":"PPL",
    "gn:name":"Houbawan",
    "gn:population":0,
    "gn:timezone":"Asia/Shanghai",
    "iso:country":"CN",
    "name:zho_x_preferred":[
        "\u540e\u575d\u6e7e"
    ],
    "wof:name":"Houbawan",
    "wof:placetype":"locality"
},
  "geometry": {"coordinates":[106.738,28.004],"type":"Point"}
}