{
  "type": "Feature",
  "properties": {
    "gn:admin1_code":"3.0",
    "gn:asciiname":"Laoguanshi",
    "gn:country_code":"CN",
    "gn:dem":69,
    "gn:feature_class":"P",
    "gn:feature_code":"PPL",
    "gn:name":"Laoguanshi",
    "gn:population":0,
    "gn:timezone":"Asia/Shanghai",
    "iso:country":"CN",
    "name:und_x_variant":[
        "\u8001\u5b98\u77f3"
    ],
    "wof:name":"Laoguanshi",
    "wof:placetype":"locality"
},
  "geometry": {"coordinates":[114.93312,28.27022],"type":"Point"}
}