{
  "type": "Feature",
  "properties": {
    "gn:admin1_code":"16.0",
    "gn:asciiname":"Daduichong",
    "gn:country_code":"CN",
    "gn:dem":409,
    "gn:feature_class":"P",
    "gn:feature_code":"PPL",
    "gn:name":"Daduichong",
    "gn:population":0,
    "gn:timezone":"Asia/Shanghai",
    "iso:country":"CN",
    "name:zho_x_preferred":[
        "\u5927\u5bf9\u51b2"
    ],
    "wof:name":"Daduichong",
    "wof:placetype":"locality"
},
  "geometry": {"coordinates":[110.395,22.9563],"type":"Point"}
}