{
  "type": "Feature",
  "properties": {
    "gn:admin1_code":"4.0",
    "gn:asciiname":"Banjiamen",
    "gn:country_code":"CN",
    "gn:dem":3,
    "gn:feature_class":"P",
    "gn:feature_code":"PPL",
    "gn:name":"Banjiamen",
    "gn:population":0,
    "gn:timezone":"Asia/Shanghai",
    "iso:country":"CN",
    "name:zho_x_preferred":[
        "\u534a\u5bb6\u95e8"
    ],
    "wof:name":"Banjiamen",
    "wof:placetype":"locality"
},
  "geometry": {"coordinates":[120.72376,31.46597],"type":"Point"}
}