{
  "type": "Feature",
  "properties": {
    "gn:admin1_code":"3.0",
    "gn:asciiname":"Jinqiannao",
    "gn:country_code":"CN",
    "gn:dem":244,
    "gn:feature_class":"P",
    "gn:feature_code":"PPL",
    "gn:name":"Jinqiannao",
    "gn:population":0,
    "gn:timezone":"Asia/Shanghai",
    "iso:country":"CN",
    "name:und_x_variant":[
        "\u91d1\u94b1\u8111"
    ],
    "wof:name":"Jinqiannao",
    "wof:placetype":"locality"
},
  "geometry": {"coordinates":[115.39147,25.4859],"type":"Point"}
}