{
  "type": "Feature",
  "properties": {
    "gn:admin1_code":"16.0",
    "gn:asciiname":"Lansha",
    "gn:country_code":"CN",
    "gn:dem":40,
    "gn:feature_class":"P",
    "gn:feature_code":"PPL",
    "gn:name":"Lansha",
    "gn:population":0,
    "gn:timezone":"Asia/Shanghai",
    "iso:country":"CN",
    "name:zho_x_preferred":[
        "\u6984\u6c99"
    ],
    "wof:name":"Lansha",
    "wof:placetype":"locality"
},
  "geometry": {"coordinates":[110.14100000000001,23.4578],"type":"Point"}
}