{
  "type": "Feature",
  "properties": {
    "gn:admin1_code":"1.0",
    "gn:asciiname":"Xiamiaocun",
    "gn:country_code":"CN",
    "gn:dem":43,
    "gn:feature_class":"P",
    "gn:feature_code":"PPL",
    "gn:name":"Xiamiaocun",
    "gn:population":0,
    "gn:timezone":"Asia/Shanghai",
    "iso:country":"CN",
    "name:zho_x_preferred":[
        "\u590f\u5e99\u6751"
    ],
    "wof:name":"Xiamiaocun",
    "wof:placetype":"locality"
},
  "geometry": {"coordinates":[117.58112,32.25694],"type":"Point"}
}