{
  "type": "Feature",
  "properties": {
    "gn:admin1_code":"32.0",
    "gn:asciiname":"Qiaofengba",
    "gn:country_code":"CN",
    "gn:dem":374,
    "gn:feature_class":"P",
    "gn:feature_code":"PPL",
    "gn:name":"Qiaofengba",
    "gn:population":0,
    "gn:timezone":"Asia/Shanghai",
    "iso:country":"CN",
    "name:zho_x_preferred":[
        "\u6865\u51e4\u575d"
    ],
    "wof:name":"Qiaofengba",
    "wof:placetype":"locality"
},
  "geometry": {"coordinates":[106.00700000000001,31.0617],"type":"Point"}
}