{
  "type": "Feature",
  "properties": {
    "gn:admin1_code":"26.0",
    "gn:asciiname":"Maiziping",
    "gn:country_code":"CN",
    "gn:dem":1129,
    "gn:feature_class":"P",
    "gn:feature_code":"PPL",
    "gn:name":"Maiziping",
    "gn:population":0,
    "gn:timezone":"Asia/Shanghai",
    "iso:country":"CN",
    "name:zho_x_preferred":[
        "\u9ea6\u5b50\u576a"
    ],
    "wof:name":"Maiziping",
    "wof:placetype":"locality"
},
  "geometry": {"coordinates":[108.7884,32.45865999999999],"type":"Point"}
}