{
  "type": "Feature",
  "properties": {
    "gn:admin1_code":"11",
    "gn:asciiname":"Huage",
    "gn:country_code":"CN",
    "gn:dem":29,
    "gn:feature_class":"P",
    "gn:feature_code":"PPLA4",
    "gn:name":"Huage",
    "gn:population":0,
    "gn:timezone":"Asia/Shanghai",
    "iso:country":"CN",
    "name:und_x_variant":[
        "Huage Zhen"
    ],
    "name:zho_x_preferred":[
        "\u534e\u9601"
    ],
    "name:zho_x_variant":[
        "\u534e\u9601\u9547"
    ],
    "wof:name":"Huage",
    "wof:placetype":"locality"
},
  "geometry": {"coordinates":[112.65833000000001,29.29778],"type":"Point"}
}