{
  "type": "Feature",
  "properties": {
    "gn:admin1_code":"25.0",
    "gn:asciiname":"Dong'anjiagou",
    "gn:cc2":"CN",
    "gn:country_code":"CN",
    "gn:dem":43,
    "gn:feature_class":"P",
    "gn:feature_code":"PPL",
    "gn:name":"Dong\u2019anjiagou",
    "gn:population":0,
    "gn:timezone":"Asia/Shanghai",
    "iso:country":"CN",
    "name:und_x_variant":[
        "Dong\u2019anjiagou"
    ],
    "name:zho_x_preferred":[
        "\u4e1c\u5b89\u5bb6\u6c9f"
    ],
    "wof:name":"Dong'anjiagou",
    "wof:placetype":"locality"
},
  "geometry": {"coordinates":[119.83051,36.13061],"type":"Point"}
}