{
  "type": "Feature",
  "properties": {
    "iso:country":"CN",
    "qs:name":"\u5e03\u5c14\u6d25\u53bf",
    "qs:name_adm0":"\u4e2d\u570b",
    "qs:name_adm1":"\u65b0\u7586\u7ef4\u543e\u5c14\u81ea\u6cbb\u533a",
    "qs:photos":186,
    "qs:photos_1k":38,
    "qs:photos_9k":1,
    "qs:photos_9r":4,
    "qs:photos_all":269,
    "qs:photos_sr":4,
    "qs:placetype":"LocalAdmin",
    "qs:pop_sr":"0",
    "wd:wordcount":362,
    "wof:name":"\u5e03\u5c14\u6d25\u53bf",
    "wof:placetype":"localadmin"
},
  "geometry": {"coordinates":[86.848983,47.69896],"type":"Point"}
}