{
  "type": "Feature",
  "properties": {
    "iso:country":"CN",
    "name:deu_x_preferred":[
        "Burqin"
    ],
    "name:ell_x_preferred":[
        "\u039a\u03bf\u03bc\u03b7\u03c4\u03b5\u03af\u03b1 \u039c\u03c0\u03bf\u03c5\u03c1\u03c4\u03c3\u03af\u03bd"
    ],
    "name:eng_x_preferred":[
        "Burqin County"
    ],
    "name:fas_x_preferred":[
        "\u0634\u0647\u0631\u0633\u062a\u0627\u0646 \u0628\u0648\u0631\u0686\u06cc\u0646"
    ],
    "name:gan_x_preferred":[
        "\u5e03\u5c14\u6d25\u53bf"
    ],
    "name:jpn_x_preferred":[
        "\u30d6\u30eb\u30c1\u30f3\u770c"
    ],
    "name:kaz_x_preferred":[
        "\u0411\u0443\u044b\u0440\u0448\u044b\u043d"
    ],
    "name:kor_x_preferred":[
        "\ubd80\uc5bc\uc9c4\ud604"
    ],
    "name:nan_x_preferred":[
        "Burqin-ko\u0101n"
    ],
    "name:nld_x_preferred":[
        "Burqin"
    ],
    "name:nob_x_preferred":[
        "Burqin"
    ],
    "name:rus_x_preferred":[
        "\u0411\u0443\u0440\u0447\u0443\u043d"
    ],
    "name:swe_x_preferred":[
        "Burqin"
    ],
    "name:tur_x_preferred":[
        "Bur\u00e7in \u0130l\u00e7esi"
    ],
    "name:uig_x_preferred":[
        "\u0628\u06c7\u0631\u0686\u0649\u0646 \u0646\u0627\u06be\u0649\u064a\u0649\u0633\u0649"
    ],
    "name:urd_x_preferred":[
        "\u0628\u0648\u0631\u0686\u06cc\u0646 \u06a9\u0627\u0624\u0646\u0679\u06cc"
    ],
    "name:vie_x_preferred":[
        "Burqin"
    ],
    "name:wuu_x_preferred":[
        "\u5e03\u5c14\u6d25\u53bf"
    ],
    "name:zho_x_preferred":[
        "\u5e03\u5c14\u6d25\u53bf"
    ],
    "qs:name":"\u5e03\u5c14\u6d25\u53bf",
    "qs:name_adm0":"\u4e2d\u570b",
    "qs:name_adm1":"\u65b0\u7586\u7ef4\u543e\u5c14\u81ea\u6cbb\u533a",
    "qs:photos":186,
    "qs:photos_1k":38,
    "qs:photos_9k":1,
    "qs:photos_9r":4,
    "qs:photos_all":269,
    "qs:photos_sr":4,
    "qs:placetype":"LocalAdmin",
    "qs:pop_sr":"0",
    "wd:wordcount":362,
    "wof:name":"\u5e03\u5c14\u6d25\u53bf",
    "wof:placetype":"localadmin"
},
  "geometry": {"coordinates":[86.848983,47.69896],"type":"Point"}
}