{
  "type": "Feature",
  "properties": {
    "gn:admin1_code":"15.0",
    "gn:asciiname":"Jinping",
    "gn:country_code":"CN",
    "gn:dem":1323,
    "gn:feature_class":"P",
    "gn:feature_code":"PPL",
    "gn:name":"Jinping",
    "gn:population":0,
    "gn:timezone":"Asia/Shanghai",
    "iso:country":"CN",
    "name:zho_x_preferred":[
        "\u91d1\u576a"
    ],
    "wof:name":"Jinping",
    "wof:placetype":"locality"
},
  "geometry": {"coordinates":[104.428,37.1938],"type":"Point"}
}