{
  "type": "Feature",
  "properties": {
    "gn:admin1_code":"31.0",
    "gn:asciiname":"Longchupo",
    "gn:country_code":"CN",
    "gn:dem":117,
    "gn:feature_class":"P",
    "gn:feature_code":"PPL",
    "gn:name":"Longchupo",
    "gn:population":0,
    "gn:timezone":"Asia/Shanghai",
    "iso:country":"CN",
    "name:zho_x_preferred":[
        "\u9f99\u51fa\u5761"
    ],
    "wof:name":"Longchupo",
    "wof:placetype":"locality"
},
  "geometry": {"coordinates":[110.12000999999999,19.45154],"type":"Point"}
}