{
  "type": "Feature",
  "properties": {
    "gn:admin1_code":"7.0",
    "gn:asciiname":"Jinshi",
    "gn:country_code":"CN",
    "gn:dem":133,
    "gn:feature_class":"P",
    "gn:feature_code":"PPL",
    "gn:name":"Jinshi",
    "gn:population":0,
    "gn:timezone":"Asia/Shanghai",
    "iso:country":"CN",
    "name:kor_x_preferred":[
        "\uc9c4\uc0ac"
    ],
    "name:mlg_x_preferred":[
        "Jinshi"
    ],
    "name:nld_x_preferred":[
        "Jinshi"
    ],
    "name:zho_x_preferred":[
        "\u91d1\u72ee"
    ],
    "wof:name":"Jinshi",
    "wof:placetype":"locality"
},
  "geometry": {"coordinates":[118.08231000000001,24.95621],"type":"Point"}
}