{
  "type": "Feature",
  "properties": {
    "gn:admin1_code":"1.0",
    "gn:asciiname":"Guanjuncun",
    "gn:country_code":"CN",
    "gn:dem":7,
    "gn:feature_class":"P",
    "gn:feature_code":"PPL",
    "gn:name":"Guanjuncun",
    "gn:population":0,
    "gn:timezone":"Asia/Shanghai",
    "iso:country":"CN",
    "name:zho_x_preferred":[
        "\u51a0\u519b\u6751"
    ],
    "wof:name":"Guanjuncun",
    "wof:placetype":"locality"
},
  "geometry": {"coordinates":[118.22181999999999,31.32488],"type":"Point"}
}