{
  "type": "Feature",
  "properties": {
    "gn:admin1_code":"14.0",
    "gn:asciiname":"Boluocun",
    "gn:country_code":"CN",
    "gn:dem":4044,
    "gn:feature_class":"P",
    "gn:feature_code":"PPL",
    "gn:name":"Boluocun",
    "gn:population":0,
    "gn:timezone":"Asia/Urumqi",
    "iso:country":"CN",
    "name:zho_x_preferred":[
        "\u535a\u7f57\u6751"
    ],
    "wof:name":"Boluocun",
    "wof:placetype":"locality"
},
  "geometry": {"coordinates":[94.96613000000001,31.16658],"type":"Point"}
}