{
  "type": "Feature",
  "properties": {
    "gn:admin1_code":"5.0",
    "gn:asciiname":"Yaoxuzi",
    "gn:country_code":"CN",
    "gn:dem":134,
    "gn:feature_class":"P",
    "gn:feature_code":"PPL",
    "gn:name":"Yaoxuzi",
    "gn:population":0,
    "gn:timezone":"Asia/Shanghai",
    "iso:country":"CN",
    "name:zho_x_preferred":[
        "\u8170\u5729\u5b50"
    ],
    "wof:name":"Yaoxuzi",
    "wof:placetype":"locality"
},
  "geometry": {"coordinates":[124.2007,45.43339],"type":"Point"}
}