{
  "type": "Feature",
  "properties": {
    "gn:admin1_code":"14.0",
    "gn:asciiname":"Layu",
    "gn:country_code":"CN",
    "gn:dem":3597,
    "gn:feature_class":"P",
    "gn:feature_code":"PPL",
    "gn:name":"Layu",
    "gn:population":0,
    "gn:timezone":"Asia/Shanghai",
    "iso:country":"CN",
    "name:und_x_variant":[
        "Leyou",
        "Layu"
    ],
    "name:zho_x_preferred":[
        "\u52d2\u53cb"
    ],
    "name:zho_x_variant":[
        "\u62c9\u7389"
    ],
    "wof:name":"Layu",
    "wof:placetype":"locality"
},
  "geometry": {"coordinates":[78.9842,31.6419],"type":"Point"}
}