{
  "type": "Feature",
  "properties": {
    "gn:admin1_code":"9",
    "gn:asciiname":"Yuemai",
    "gn:country_code":"CN",
    "gn:dem":52,
    "gn:feature_class":"P",
    "gn:feature_code":"PPL",
    "gn:name":"Yuemai",
    "gn:population":0,
    "gn:timezone":"Asia/Shanghai",
    "iso:country":"CN",
    "name:zho_x_preferred":[
        "\u5cb3\u9ea6"
    ],
    "wof:name":"Yuemai",
    "wof:placetype":"locality"
},
  "geometry": {"coordinates":[115.25503,35.93554],"type":"Point"}
}