{
  "type": "Feature",
  "properties": {
    "gn:admin1_code":"15.0",
    "gn:asciiname":"Sumeng",
    "gn:country_code":"CN",
    "gn:dem":1762,
    "gn:feature_class":"P",
    "gn:feature_code":"PPL",
    "gn:name":"Sumeng",
    "gn:population":0,
    "gn:timezone":"Asia/Shanghai",
    "iso:country":"CN",
    "name:zho_x_preferred":[
        "\u82cf\u5b5f"
    ],
    "wof:name":"Sumeng",
    "wof:placetype":"locality"
},
  "geometry": {"coordinates":[103.224,35.7354],"type":"Point"}
}