{
  "type": "Feature",
  "properties": {
    "gn:admin1_code":"3.0",
    "gn:asciiname":"Shujiagang",
    "gn:country_code":"CN",
    "gn:dem":44,
    "gn:feature_class":"P",
    "gn:feature_code":"PPL",
    "gn:name":"Shujiagang",
    "gn:population":0,
    "gn:timezone":"Asia/Shanghai",
    "iso:country":"CN",
    "name:zho_x_preferred":[
        "\u8212\u5bb6\u6e2f"
    ],
    "wof:name":"Shujiagang",
    "wof:placetype":"locality"
},
  "geometry": {"coordinates":[117.38737999999999,28.34554],"type":"Point"}
}