{
  "type": "Feature",
  "properties": {
    "gn:admin1_code":"3.0",
    "gn:asciiname":"Suoyiling",
    "gn:country_code":"CN",
    "gn:dem":118,
    "gn:feature_class":"P",
    "gn:feature_code":"PPL",
    "gn:name":"Suoyiling",
    "gn:population":0,
    "gn:timezone":"Asia/Shanghai",
    "iso:country":"CN",
    "name:und_x_variant":[
        "\u84d1\u8863\u5cad"
    ],
    "wof:name":"Suoyiling",
    "wof:placetype":"locality"
},
  "geometry": {"coordinates":[114.54170999999999,29.02708],"type":"Point"}
}