{
  "type": "Feature",
  "properties": {
    "gn:admin1_code":"30.0",
    "gn:asciiname":"Jiaokeng",
    "gn:country_code":"CN",
    "gn:dem":208,
    "gn:feature_class":"P",
    "gn:feature_code":"PPL",
    "gn:name":"Jiaokeng",
    "gn:population":0,
    "gn:timezone":"Asia/Shanghai",
    "iso:country":"CN",
    "name:zho_x_preferred":[
        "\u8549\u5751"
    ],
    "wof:name":"Jiaokeng",
    "wof:placetype":"locality"
},
  "geometry": {"coordinates":[114.20063,24.56065],"type":"Point"}
}