{
  "type": "Feature",
  "properties": {
    "gn:admin1_code":"26.0",
    "gn:asciiname":"Damaidiwan",
    "gn:country_code":"CN",
    "gn:dem":1266,
    "gn:feature_class":"P",
    "gn:feature_code":"PPL",
    "gn:name":"Damaidiwan",
    "gn:population":0,
    "gn:timezone":"Asia/Shanghai",
    "iso:country":"CN",
    "name:zho_x_preferred":[
        "\u5927\u9ea6\u5730\u6e7e"
    ],
    "wof:name":"Damaidiwan",
    "wof:placetype":"locality"
},
  "geometry": {"coordinates":[106.78362,34.9983],"type":"Point"}
}