{
  "type": "Feature",
  "properties": {
    "gn:admin1_code":"9",
    "gn:asciiname":"Guibaishi",
    "gn:country_code":"CN",
    "gn:dem":1438,
    "gn:feature_class":"P",
    "gn:feature_code":"PPL",
    "gn:name":"Guibaishi",
    "gn:population":0,
    "gn:timezone":"Asia/Shanghai",
    "iso:country":"CN",
    "wof:name":"Guibaishi",
    "wof:placetype":"locality"
},
  "geometry": {"coordinates":[112.03,33.71417],"type":"Point"}
}