{
  "type": "Feature",
  "properties": {
    "gn:admin1_code":"4.0",
    "gn:asciiname":"Yanglaoshe",
    "gn:country_code":"CN",
    "gn:dem":3,
    "gn:feature_class":"P",
    "gn:feature_code":"PPL",
    "gn:name":"Yanglaoshe",
    "gn:population":0,
    "gn:timezone":"Asia/Shanghai",
    "iso:country":"CN",
    "name:zho_x_preferred":[
        "Yanglaoshe"
    ],
    "name:zho_x_variant":[
        "\u6768\u8001\u820d"
    ],
    "wof:name":"Yanglaoshe",
    "wof:placetype":"locality"
},
  "geometry": {"coordinates":[119.75896000000002,33.77108],"type":"Point"}
}