{
  "type": "Feature",
  "properties": {
    "gn:admin1_code":"19.0",
    "gn:asciiname":"Santaizi",
    "gn:country_code":"CN",
    "gn:dem":51,
    "gn:feature_class":"P",
    "gn:feature_code":"PPL",
    "gn:name":"Santaizi",
    "gn:population":0,
    "gn:timezone":"Asia/Shanghai",
    "iso:country":"CN",
    "name:und_x_variant":[
        "\u4e09\u53f0\u5b50"
    ],
    "name:zho_x_preferred":[
        "\u4e09\u53f0\u5b50"
    ],
    "wof:name":"Santaizi",
    "wof:placetype":"locality"
},
  "geometry": {"coordinates":[123.27347,42.20189],"type":"Point"}
}