{
  "type": "Feature",
  "properties": {
    "gn:admin1_code":"4.0",
    "gn:asciiname":"Yuehe",
    "gn:country_code":"CN",
    "gn:dem":7,
    "gn:feature_class":"P",
    "gn:feature_code":"PPL",
    "gn:name":"Yuehe",
    "gn:population":0,
    "gn:timezone":"Asia/Shanghai",
    "iso:country":"CN",
    "name:zho_x_preferred":[
        "Yuehe"
    ],
    "name:zho_x_variant":[
        "\u6708\u6cb3"
    ],
    "wof:name":"Yuehe",
    "wof:placetype":"locality"
},
  "geometry": {"coordinates":[121.05013,32.42504],"type":"Point"}
}