{
  "type": "Feature",
  "properties": {
    "gn:admin1_code":"19.0",
    "gn:asciiname":"Yongyihao",
    "gn:country_code":"CN",
    "gn:dem":82,
    "gn:feature_class":"P",
    "gn:feature_code":"PPL",
    "gn:name":"Yongyihao",
    "gn:population":0,
    "gn:timezone":"Asia/Shanghai",
    "iso:country":"CN",
    "name:und_x_variant":[
        "\u6c38\u4e49\u53f7"
    ],
    "name:zho_x_preferred":[
        "\u6c38\u4e49\u53f7"
    ],
    "wof:name":"Yongyihao",
    "wof:placetype":"locality"
},
  "geometry": {"coordinates":[122.90243999999998,42.44023],"type":"Point"}
}