{
  "type": "Feature",
  "properties": {
    "gn:admin1_code":"2.0",
    "gn:asciiname":"Shangwang",
    "gn:country_code":"CN",
    "gn:dem":498,
    "gn:feature_class":"P",
    "gn:feature_code":"PPL",
    "gn:name":"Shangwang",
    "gn:population":0,
    "gn:timezone":"Asia/Shanghai",
    "iso:country":"CN",
    "name:zho_x_preferred":[
        "\u4e0a\u738b"
    ],
    "wof:name":"Shangwang",
    "wof:placetype":"locality"
},
  "geometry": {"coordinates":[121.16426,29.92741],"type":"Point"}
}