{
  "type": "Feature",
  "properties": {
    "gn:admin1_code":"18",
    "gn:asciiname":"Hongshuiba",
    "gn:country_code":"CN",
    "gn:dem":788,
    "gn:feature_class":"P",
    "gn:feature_code":"PPL",
    "gn:name":"Hongshuiba",
    "gn:population":0,
    "gn:timezone":"Asia/Shanghai",
    "iso:country":"CN",
    "name:zho_x_preferred":[
        "\u6d2a\u6c34\u575d"
    ],
    "wof:name":"Hongshuiba",
    "wof:placetype":"locality"
},
  "geometry": {"coordinates":[106.864,27.2216],"type":"Point"}
}