{
  "type": "Feature",
  "properties": {
    "gn:admin1_code":"15.0",
    "gn:asciiname":"Weijiacha",
    "gn:country_code":"CN",
    "gn:dem":2120,
    "gn:feature_class":"P",
    "gn:feature_code":"PPL",
    "gn:name":"Weijiacha",
    "gn:population":0,
    "gn:timezone":"Asia/Shanghai",
    "iso:country":"CN",
    "name:und_x_variant":[
        "\u9b4f\u5bb6\u5c94"
    ],
    "wof:name":"Weijiacha",
    "wof:placetype":"locality"
},
  "geometry": {"coordinates":[105.40770999999999,35.53582],"type":"Point"}
}