{
  "type": "Feature",
  "properties": {
    "gn:admin1_code":"22.0",
    "gn:asciiname":"Hujiafa",
    "gn:country_code":"CN",
    "gn:dem":28,
    "gn:feature_class":"P",
    "gn:feature_code":"PPL",
    "gn:name":"Hujiafa",
    "gn:population":0,
    "gn:timezone":"Asia/Shanghai",
    "iso:country":"CN",
    "name:zho_x_preferred":[
        "\u80e1\u5bb6\u57a1"
    ],
    "wof:name":"Hujiafa",
    "wof:placetype":"locality"
},
  "geometry": {"coordinates":[116.60583,39.83228],"type":"Point"}
}