{
  "type": "Feature",
  "properties": {
    "gn:admin1_code":"2.0",
    "gn:asciiname":"Yangdachang",
    "gn:country_code":"CN",
    "gn:dem":59,
    "gn:feature_class":"P",
    "gn:feature_code":"PPL",
    "gn:name":"Yangdachang",
    "gn:population":0,
    "gn:timezone":"Asia/Shanghai",
    "iso:country":"CN",
    "name:zho_x_preferred":[
        "\u6768\u5927\u573a"
    ],
    "wof:name":"Yangdachang",
    "wof:placetype":"locality"
},
  "geometry": {"coordinates":[121.73314999999999,29.40521],"type":"Point"}
}