{
  "type": "Feature",
  "properties": {
    "gn:admin1_code":"30.0",
    "gn:asciiname":"Renhou",
    "gn:country_code":"CN",
    "gn:dem":0,
    "gn:feature_class":"P",
    "gn:feature_code":"PPL",
    "gn:name":"Renhou",
    "gn:population":0,
    "gn:timezone":"Asia/Shanghai",
    "iso:country":"CN",
    "name:zho_x_preferred":[
        "\u4ec1\u539a"
    ],
    "wof:name":"Renhou",
    "wof:placetype":"locality"
},
  "geometry": {"coordinates":[113.08747,22.69297000000001],"type":"Point"}
}