{
  "type": "Feature",
  "properties": {
    "gn:admin1_code":"24.0",
    "gn:asciiname":"Gaojiazhuang",
    "gn:country_code":"CN",
    "gn:dem":1448,
    "gn:feature_class":"P",
    "gn:feature_code":"PPL",
    "gn:name":"Gaojiazhuang",
    "gn:population":0,
    "gn:timezone":"Asia/Shanghai",
    "iso:country":"CN",
    "name:zho_x_preferred":[
        "\u9ad8\u5bb6\u5e84"
    ],
    "wof:name":"Gaojiazhuang",
    "wof:placetype":"locality"
},
  "geometry": {"coordinates":[111.04406000000002,36.97768],"type":"Point"}
}