{
  "type": "Feature",
  "properties": {
    "gn:admin1_code":"18",
    "gn:asciiname":"Muchangcun",
    "gn:country_code":"CN",
    "gn:dem":2489,
    "gn:feature_class":"P",
    "gn:feature_code":"PPLF",
    "gn:name":"Muchangcun",
    "gn:population":0,
    "gn:timezone":"Asia/Shanghai",
    "iso:country":"CN",
    "name:zho_x_preferred":[
        "\u7267\u573a\u6751"
    ],
    "wof:name":"Muchangcun",
    "wof:placetype":"locality"
},
  "geometry": {"coordinates":[104.631,26.7061],"type":"Point"}
}