{
  "type": "Feature",
  "properties": {
    "gn:admin1_code":"32.0",
    "gn:asciiname":"Guanmenshan",
    "gn:country_code":"CN",
    "gn:dem":3233,
    "gn:feature_class":"P",
    "gn:feature_code":"PPL",
    "gn:name":"Guanmenshan",
    "gn:population":0,
    "gn:timezone":"Asia/Shanghai",
    "iso:country":"CN",
    "name:zho_x_preferred":[
        "\u5173\u95e8\u5c71"
    ],
    "wof:name":"Guanmenshan",
    "wof:placetype":"locality"
},
  "geometry": {"coordinates":[101.577,28.2221],"type":"Point"}
}