{
  "type": "Feature",
  "properties": {
    "gn:admin1_code":"12.0",
    "gn:asciiname":"Yangbeitang",
    "gn:country_code":"CN",
    "gn:dem":69,
    "gn:feature_class":"P",
    "gn:feature_code":"PPL",
    "gn:name":"Yangbeitang",
    "gn:population":0,
    "gn:timezone":"Asia/Shanghai",
    "iso:country":"CN",
    "name:zho_x_preferred":[
        "Yangbeitang"
    ],
    "name:zho_x_variant":[
        "\u6768\u80cc\u5858"
    ],
    "wof:name":"Yangbeitang",
    "wof:placetype":"locality"
},
  "geometry": {"coordinates":[114.72284000000001,29.99525],"type":"Point"}
}