{
  "type": "Feature",
  "properties": {
    "gn:admin1_code":"16.0",
    "gn:asciiname":"Weidongkou",
    "gn:country_code":"CN",
    "gn:dem":243,
    "gn:feature_class":"P",
    "gn:feature_code":"PPL",
    "gn:name":"Weidongkou",
    "gn:population":0,
    "gn:timezone":"Asia/Shanghai",
    "iso:country":"CN",
    "name:zho_x_preferred":[
        "\u97e6\u6d1e\u53e3"
    ],
    "wof:name":"Weidongkou",
    "wof:placetype":"locality"
},
  "geometry": {"coordinates":[108.20099999999999,24.6382],"type":"Point"}
}