{
  "type": "Feature",
  "properties": {
    "gn:admin1_code":"02",
    "gn:asciiname":"Niutaicun",
    "gn:country_code":"CN",
    "gn:dem":14,
    "gn:feature_class":"P",
    "gn:feature_code":"PPL",
    "gn:name":"Niutaicun",
    "gn:population":0,
    "gn:timezone":"Asia/Shanghai",
    "iso:country":"CN",
    "name:und_x_variant":[
        "Niu-t\u2019ui-ts\u2019un",
        "Niutai",
        "Niutaicun"
    ],
    "name:zho_x_preferred":[
        "\u725b\u53f0"
    ],
    "name:zho_x_variant":[
        "\u725b\u53f0\u6751"
    ],
    "wof:name":"Niutaicun",
    "wof:placetype":"locality"
},
  "geometry": {"coordinates":[121.48108000000001,29.16913],"type":"Point"}
}