{
  "type": "Feature",
  "properties": {
    "gn:admin1_code":"15.0",
    "gn:asciiname":"Reguoxiuma",
    "gn:country_code":"CN",
    "gn:dem":2945,
    "gn:feature_class":"P",
    "gn:feature_code":"PPL",
    "gn:name":"Reguoxiuma",
    "gn:population":0,
    "gn:timezone":"Asia/Shanghai",
    "iso:country":"CN",
    "name:und_x_variant":[
        "\u70ed\u679c\u79c0\u739b"
    ],
    "wof:name":"Reguoxiuma",
    "wof:placetype":"locality"
},
  "geometry": {"coordinates":[102.75914,35.22573],"type":"Point"}
}