{
  "type": "Feature",
  "properties": {
    "gn:admin1_code":"26.0",
    "gn:asciiname":"Huochangliang",
    "gn:country_code":"CN",
    "gn:dem":1541,
    "gn:feature_class":"P",
    "gn:feature_code":"PPL",
    "gn:name":"Huochangliang",
    "gn:population":0,
    "gn:timezone":"Asia/Shanghai",
    "iso:country":"CN",
    "name:zho_x_preferred":[
        "\u4f19\u573a\u6881"
    ],
    "wof:name":"Huochangliang",
    "wof:placetype":"locality"
},
  "geometry": {"coordinates":[107.39031,37.2043],"type":"Point"}
}