{
  "type": "Feature",
  "properties": {
    "gn:admin1_code":"1.0",
    "gn:asciiname":"Shihuicun",
    "gn:country_code":"CN",
    "gn:dem":19,
    "gn:feature_class":"P",
    "gn:feature_code":"PPL",
    "gn:name":"Shihuicun",
    "gn:population":0,
    "gn:timezone":"Asia/Shanghai",
    "iso:country":"CN",
    "name:zho_x_preferred":[
        "\u77f3\u4f1a\u6751"
    ],
    "wof:name":"Shihuicun",
    "wof:placetype":"locality"
},
  "geometry": {"coordinates":[117.1234,30.77263],"type":"Point"}
}