{
  "type": "Feature",
  "properties": {
    "gn:admin1_code":"18",
    "gn:asciiname":"Shuiluodong",
    "gn:country_code":"CN",
    "gn:dem":1225,
    "gn:feature_class":"P",
    "gn:feature_code":"PPL",
    "gn:name":"Shuiluodong",
    "gn:population":0,
    "gn:timezone":"Asia/Shanghai",
    "iso:country":"CN",
    "name:zho_x_preferred":[
        "\u6c34\u843d\u6d1e"
    ],
    "wof:name":"Shuiluodong",
    "wof:placetype":"locality"
},
  "geometry": {"coordinates":[106.027,27.065],"type":"Point"}
}