{
  "type": "Feature",
  "properties": {
    "gn:admin1_code":"2",
    "gn:asciiname":"Mache",
    "gn:country_code":"CN",
    "gn:dem":39,
    "gn:feature_class":"P",
    "gn:feature_code":"PPL",
    "gn:name":"Mache",
    "gn:population":0,
    "gn:timezone":"Asia/Shanghai",
    "iso:country":"CN",
    "name:ceb_x_preferred":[
        "Mache"
    ],
    "name:deu_x_preferred":[
        "Mache"
    ],
    "name:fra_x_preferred":[
        "Mache"
    ],
    "name:hat_x_preferred":[
        "Mache"
    ],
    "name:nld_x_preferred":[
        "Mache"
    ],
    "name:spa_x_preferred":[
        "Mache"
    ],
    "name:swe_x_preferred":[
        "Mache"
    ],
    "name:zho_x_preferred":[
        "\u9ebb\u8f66"
    ],
    "wof:name":"Mache",
    "wof:placetype":"locality"
},
  "geometry": {"coordinates":[119.53983999999998,29.4233],"type":"Point"}
}