{
  "type": "Feature",
  "properties": {
    "gn:admin1_code":"24.0",
    "gn:asciiname":"Mapo",
    "gn:country_code":"CN",
    "gn:dem":1134,
    "gn:feature_class":"P",
    "gn:feature_code":"PPL",
    "gn:name":"Mapo",
    "gn:population":0,
    "gn:timezone":"Asia/Shanghai",
    "iso:country":"CN",
    "name:ceb_x_preferred":[
        "Mapo"
    ],
    "name:deu_x_preferred":[
        "Mapo"
    ],
    "name:swe_x_preferred":[
        "Mapo"
    ],
    "name:zho_x_preferred":[
        "\u9a6c\u5761"
    ],
    "wof:name":"Mapo",
    "wof:placetype":"locality"
},
  "geometry": {"coordinates":[111.68039,35.39699],"type":"Point"}
}