{
  "type": "Feature",
  "properties": {
    "gn:admin1_code":"1.0",
    "gn:asciiname":"Nanpeicun",
    "gn:country_code":"CN",
    "gn:dem":37,
    "gn:feature_class":"P",
    "gn:feature_code":"PPL",
    "gn:name":"Nanpeicun",
    "gn:population":0,
    "gn:timezone":"Asia/Shanghai",
    "iso:country":"CN",
    "name:zho_x_preferred":[
        "\u5357\u6c9b\u6751"
    ],
    "wof:name":"Nanpeicun",
    "wof:placetype":"locality"
},
  "geometry": {"coordinates":[118.46514999999999,32.42834000000001],"type":"Point"}
}