{
  "type": "Feature",
  "properties": {
    "gn:admin1_code":"1.0",
    "gn:asciiname":"Baizi'ancun",
    "gn:country_code":"CN",
    "gn:dem":75,
    "gn:feature_class":"P",
    "gn:feature_code":"PPL",
    "gn:name":"Baizi\u2019ancun",
    "gn:population":0,
    "gn:timezone":"Asia/Shanghai",
    "iso:country":"CN",
    "name:und_x_variant":[
        "Baizi\u2019ancun"
    ],
    "name:zho_x_preferred":[
        "\u767e\u5b50\u5eb5\u6751"
    ],
    "wof:name":"Baizi'ancun",
    "wof:placetype":"locality"
},
  "geometry": {"coordinates":[116.49823000000001,31.56093],"type":"Point"}
}