{
  "type": "Feature",
  "properties": {
    "gn:admin1_code":"19.0",
    "gn:asciiname":"Shanjiatun",
    "gn:country_code":"CN",
    "gn:dem":108,
    "gn:feature_class":"P",
    "gn:feature_code":"PPL",
    "gn:name":"Shanjiatun",
    "gn:population":0,
    "gn:timezone":"Asia/Shanghai",
    "iso:country":"CN",
    "name:zho_x_preferred":[
        "\u5355\u5bb6\u5c6f"
    ],
    "wof:name":"Shanjiatun",
    "wof:placetype":"locality"
},
  "geometry": {"coordinates":[120.45083,40.66344],"type":"Point"}
}