{
  "type": "Feature",
  "properties": {
    "gn:admin1_code":"1.0",
    "gn:asciiname":"Changgoucun",
    "gn:country_code":"CN",
    "gn:dem":10,
    "gn:feature_class":"P",
    "gn:feature_code":"PPL",
    "gn:name":"Changgoucun",
    "gn:population":0,
    "gn:timezone":"Asia/Shanghai",
    "iso:country":"CN",
    "name:zho_x_preferred":[
        "\u957f\u6c9f\u6751"
    ],
    "wof:name":"Changgoucun",
    "wof:placetype":"locality"
},
  "geometry": {"coordinates":[118.6875,31.23749],"type":"Point"}
}