{
  "type": "Feature",
  "properties": {
    "gn:admin1_code":"3.0",
    "gn:asciiname":"Chuankengwei",
    "gn:country_code":"CN",
    "gn:dem":104,
    "gn:feature_class":"P",
    "gn:feature_code":"PPL",
    "gn:name":"Chuankengwei",
    "gn:population":0,
    "gn:timezone":"Asia/Shanghai",
    "iso:country":"CN",
    "name:und_x_variant":[
        "\u8239\u5751\u5c3e"
    ],
    "wof:name":"Chuankengwei",
    "wof:placetype":"locality"
},
  "geometry": {"coordinates":[115.12188999999999,26.70862],"type":"Point"}
}