{
  "type": "Feature",
  "properties": {
    "gn:admin1_code":"2.0",
    "gn:asciiname":"Dongxu",
    "gn:country_code":"CN",
    "gn:dem":62,
    "gn:feature_class":"P",
    "gn:feature_code":"PPL",
    "gn:name":"Dongxu",
    "gn:population":0,
    "gn:timezone":"Asia/Shanghai",
    "iso:country":"CN",
    "name:und_x_variant":[
        "\u4e1c\u5f90",
        "Dongxu"
    ],
    "wof:name":"Dongxu",
    "wof:placetype":"locality"
},
  "geometry": {"coordinates":[119.21905,29.11394],"type":"Point"}
}