{
  "type": "Feature",
  "properties": {
    "gn:admin1_code":"29.0",
    "gn:asciiname":"Shangwengban",
    "gn:country_code":"CN",
    "gn:dem":1145,
    "gn:feature_class":"P",
    "gn:feature_code":"PPL",
    "gn:name":"Shangwengban",
    "gn:population":0,
    "gn:timezone":"Asia/Shanghai",
    "iso:country":"CN",
    "name:zho_x_preferred":[
        "\u4e0a\u7fc1\u677f"
    ],
    "wof:name":"Shangwengban",
    "wof:placetype":"locality"
},
  "geometry": {"coordinates":[99.7747,23.0845],"type":"Point"}
}