{
  "type": "Feature",
  "properties": {
    "gn:admin1_code":"30.0",
    "gn:asciiname":"Dulou",
    "gn:country_code":"CN",
    "gn:dem":389,
    "gn:feature_class":"P",
    "gn:feature_code":"PPL",
    "gn:name":"Dulou",
    "gn:population":0,
    "gn:timezone":"Asia/Shanghai",
    "iso:country":"CN",
    "name:zho_x_preferred":[
        "Dulou"
    ],
    "name:zho_x_variant":[
        "\u8bfb\u697c"
    ],
    "wof:name":"Dulou",
    "wof:placetype":"locality"
},
  "geometry": {"coordinates":[112.08583,24.36167],"type":"Point"}
}