{
  "type": "Feature",
  "properties": {
    "gn:admin1_code":"08",
    "gn:asciiname":"Xichangfa",
    "gn:country_code":"CN",
    "gn:dem":148,
    "gn:feature_class":"P",
    "gn:feature_code":"PPLA4",
    "gn:name":"Xichangfa",
    "gn:population":0,
    "gn:timezone":"Asia/Shanghai",
    "iso:country":"CN",
    "name:und_x_variant":[
        "Changfa",
        "Xichangfa Zhen"
    ],
    "name:zho_x_preferred":[
        "\u897f\u957f\u53d1"
    ],
    "name:zho_x_variant":[
        "\u897f\u957f\u53d1\u9547"
    ],
    "wof:name":"Xichangfa",
    "wof:placetype":"locality"
},
  "geometry": {"coordinates":[126.69237,46.42346],"type":"Point"}
}