{
  "type": "Feature",
  "properties": {
    "gn:admin1_code":"33.0",
    "gn:asciiname":"Shizao",
    "gn:country_code":"CN",
    "gn:dem":412,
    "gn:feature_class":"P",
    "gn:feature_code":"PPL",
    "gn:name":"Shizao",
    "gn:population":0,
    "gn:timezone":"Asia/Shanghai",
    "iso:country":"CN",
    "name:zho_x_preferred":[
        "\u77f3\u7076"
    ],
    "wof:name":"Shizao",
    "wof:placetype":"locality"
},
  "geometry": {"coordinates":[105.97614,29.34889],"type":"Point"}
}