{
  "type": "Feature",
  "properties": {
    "gn:admin1_code":"11.0",
    "gn:asciiname":"Dongxiping",
    "gn:country_code":"CN",
    "gn:dem":82,
    "gn:feature_class":"P",
    "gn:feature_code":"PPL",
    "gn:name":"Dongxiping",
    "gn:population":0,
    "gn:timezone":"Asia/Shanghai",
    "iso:country":"CN",
    "name:zho_x_preferred":[
        "Dongxiping"
    ],
    "name:zho_x_variant":[
        "\u6d1e\u6eaa\u576a"
    ],
    "wof:name":"Dongxiping",
    "wof:placetype":"locality"
},
  "geometry": {"coordinates":[111.21917000000001,28.90595],"type":"Point"}
}