{
  "type": "Feature",
  "properties": {
    "gn:admin1_code":"25",
    "gn:asciiname":"Tianhe",
    "gn:country_code":"CN",
    "gn:dem":11,
    "gn:feature_class":"P",
    "gn:feature_code":"PPLA4",
    "gn:name":"Tianhe",
    "gn:population":0,
    "gn:timezone":"Asia/Shanghai",
    "iso:country":"CN",
    "name:ceb_x_preferred":[
        "Tianhe"
    ],
    "name:deu_x_preferred":[
        "Tianhe"
    ],
    "name:fra_x_preferred":[
        "Tianhe"
    ],
    "name:rus_x_preferred":[
        "\u0422\u044f\u043d\u044c\u0445\u044d"
    ],
    "name:und_x_variant":[
        "Tiancun",
        "Tianhe Jiedao"
    ],
    "name:zho_x_preferred":[
        "\u7530\u548c"
    ],
    "name:zho_x_variant":[
        "\u7530\u548c\u8857\u9053"
    ],
    "wof:name":"Tianhe",
    "wof:placetype":"locality"
},
  "geometry": {"coordinates":[122.05401999999999,37.50013],"type":"Point"}
}