{
  "type": "Feature",
  "properties": {
    "gn:admin1_code":"29.0",
    "gn:asciiname":"Hexicun",
    "gn:country_code":"CN",
    "gn:dem":1918,
    "gn:feature_class":"P",
    "gn:feature_code":"PPL",
    "gn:name":"Hexicun",
    "gn:population":0,
    "gn:timezone":"Asia/Shanghai",
    "iso:country":"CN",
    "name:zho_x_preferred":[
        "\u6cb3\u897f\u6751"
    ],
    "wof:name":"Hexicun",
    "wof:placetype":"locality"
},
  "geometry": {"coordinates":[103.703,25.6161],"type":"Point"}
}