{
  "type": "Feature",
  "properties": {
    "gn:admin1_code":"15.0",
    "gn:asciiname":"Lijia Buzi",
    "gn:country_code":"CN",
    "gn:dem":1162,
    "gn:feature_class":"P",
    "gn:feature_code":"PPL",
    "gn:name":"Lijia Buzi",
    "gn:population":0,
    "gn:timezone":"Asia/Urumqi",
    "iso:country":"CN",
    "name:zho_x_preferred":[
        "\u674e\u5bb6\u5821\u5b50"
    ],
    "wof:name":"Lijia Buzi",
    "wof:placetype":"locality"
},
  "geometry": {"coordinates":[95.7081,40.4203],"type":"Point"}
}