{
  "type": "Feature",
  "properties": {
    "gn:admin1_code":"18",
    "gn:asciiname":"Jiuceng",
    "gn:country_code":"CN",
    "gn:dem":725,
    "gn:feature_class":"P",
    "gn:feature_code":"PPL",
    "gn:name":"Jiuceng",
    "gn:population":0,
    "gn:timezone":"Asia/Shanghai",
    "iso:country":"CN",
    "name:zho_x_preferred":[
        "\u4e5d\u5c42"
    ],
    "wof:name":"Jiuceng",
    "wof:placetype":"locality"
},
  "geometry": {"coordinates":[108.97799999999999,26.3075],"type":"Point"}
}