{
  "type": "Feature",
  "properties": {
    "gn:admin1_code":"32.0",
    "gn:asciiname":"Shibazi",
    "gn:country_code":"CN",
    "gn:dem":312,
    "gn:feature_class":"P",
    "gn:feature_code":"PPL",
    "gn:name":"Shibazi",
    "gn:population":0,
    "gn:timezone":"Asia/Shanghai",
    "iso:country":"CN",
    "name:zho_x_preferred":[
        "\u77f3\u575d\u5b50"
    ],
    "wof:name":"Shibazi",
    "wof:placetype":"locality"
},
  "geometry": {"coordinates":[105.15300000000001,28.8262],"type":"Point"}
}