{
  "type": "Feature",
  "properties": {
    "gn:admin1_code":"29.0",
    "gn:asciiname":"Nongmu",
    "gn:country_code":"CN",
    "gn:dem":936,
    "gn:feature_class":"P",
    "gn:feature_code":"PPL",
    "gn:name":"Nongmu",
    "gn:population":0,
    "gn:timezone":"Asia/Yangon",
    "iso:country":"CN",
    "name:zho_x_preferred":[
        "\u5f04\u6bcd"
    ],
    "wof:name":"Nongmu",
    "wof:placetype":"locality"
},
  "geometry": {"coordinates":[97.7376,24.1503],"type":"Point"}
}