{
  "type": "Feature",
  "properties": {
    "gn:admin1_code":"7",
    "gn:asciiname":"Neishiqin",
    "gn:country_code":"CN",
    "gn:dem":92,
    "gn:feature_class":"P",
    "gn:feature_code":"PPL",
    "gn:name":"Neishiqin",
    "gn:population":0,
    "gn:timezone":"Asia/Shanghai",
    "iso:country":"CN",
    "name:zho_x_preferred":[
        "\u5185\u77f3\u82b9"
    ],
    "wof:name":"Neishiqin",
    "wof:placetype":"locality"
},
  "geometry": {"coordinates":[117.28833,24.13333],"type":"Point"}
}