{
  "type": "Feature",
  "properties": {
    "gn:admin1_code":"2.0",
    "gn:asciiname":"Baojia'ao",
    "gn:country_code":"CN",
    "gn:dem":7,
    "gn:feature_class":"P",
    "gn:feature_code":"PPL",
    "gn:name":"Baojia\u2019ao",
    "gn:population":0,
    "gn:timezone":"Asia/Shanghai",
    "iso:country":"CN",
    "name:und_x_variant":[
        "Baojia\u2019ao"
    ],
    "name:zho_x_preferred":[
        "\u5305\u5bb6\u5c99"
    ],
    "wof:name":"Baojia'ao",
    "wof:placetype":"locality"
},
  "geometry": {"coordinates":[121.85242,30.02265],"type":"Point"}
}