{
  "type": "Feature",
  "properties": {
    "gn:admin1_code":"5.0",
    "gn:asciiname":"Hougahai",
    "gn:country_code":"CN",
    "gn:dem":138,
    "gn:feature_class":"P",
    "gn:feature_code":"PPL",
    "gn:name":"Hougahai",
    "gn:population":0,
    "gn:timezone":"Asia/Shanghai",
    "iso:country":"CN",
    "name:zho_x_preferred":[
        "\u540e\u560e\u6d77"
    ],
    "wof:name":"Hougahai",
    "wof:placetype":"locality"
},
  "geometry": {"coordinates":[123.35006,45.8052],"type":"Point"}
}