{
  "type": "Feature",
  "properties": {
    "gn:admin1_code":"20",
    "gn:asciiname":"I-ma-t'u",
    "gn:country_code":"CN",
    "gn:dem":679,
    "gn:feature_class":"P",
    "gn:feature_code":"PPL",
    "gn:name":"I-ma-t\u2019u",
    "gn:population":0,
    "gn:timezone":"Asia/Shanghai",
    "iso:country":"CN",
    "wof:name":"I-ma-t'u",
    "wof:placetype":"locality"
},
  "geometry": {"coordinates":[118.92278,42.84167],"type":"Point"}
}