{
  "type": "Feature",
  "properties": {
    "gn:admin1_code":"26.0",
    "gn:asciiname":"Huangguata",
    "gn:country_code":"CN",
    "gn:dem":1222,
    "gn:feature_class":"P",
    "gn:feature_code":"PPL",
    "gn:name":"Huangguata",
    "gn:population":0,
    "gn:timezone":"Asia/Shanghai",
    "iso:country":"CN",
    "name:zho_x_preferred":[
        "\u9ec4\u74dc\u584c"
    ],
    "wof:name":"Huangguata",
    "wof:placetype":"locality"
},
  "geometry": {"coordinates":[109.27761,36.82384],"type":"Point"}
}