{
  "type": "Feature",
  "properties": {
    "gn:admin1_code":"31",
    "gn:asciiname":"Shisheng",
    "gn:country_code":"CN",
    "gn:dem":55,
    "gn:feature_class":"P",
    "gn:feature_code":"PPL",
    "gn:name":"Shisheng",
    "gn:population":0,
    "gn:timezone":"Asia/Shanghai",
    "iso:country":"CN",
    "name:und_x_variant":[
        "\u4ec0\u80dc"
    ],
    "wof:name":"Shisheng",
    "wof:placetype":"locality"
},
  "geometry": {"coordinates":[109.794,18.6368],"type":"Point"}
}