{
  "type": "Feature",
  "properties": {
    "gn:admin1_code":"28.0",
    "gn:asciiname":"Xizhaizhuang",
    "gn:country_code":"CN",
    "gn:dem":6,
    "gn:feature_class":"P",
    "gn:feature_code":"PPLA4",
    "gn:name":"Xizhaizhuang",
    "gn:population":0,
    "gn:timezone":"Asia/Shanghai",
    "iso:country":"CN",
    "name:und_x_variant":[
        "Xizhaizhuang Zhen"
    ],
    "name:zho_x_preferred":[
        "\u897f\u7fdf\u5e84"
    ],
    "name:zho_x_variant":[
        "\u897f\u7fdf\u5e84\u9547"
    ],
    "wof:name":"Xizhaizhuang",
    "wof:placetype":"locality"
},
  "geometry": {"coordinates":[117.00167,38.77028],"type":"Point"}
}