{
  "type": "Feature",
  "properties": {
    "gn:admin1_code":"32.0",
    "gn:asciiname":"Yaojinggou",
    "gn:country_code":"CN",
    "gn:dem":2769,
    "gn:feature_class":"P",
    "gn:feature_code":"PPL",
    "gn:name":"Yaojinggou",
    "gn:population":0,
    "gn:timezone":"Asia/Shanghai",
    "iso:country":"CN",
    "name:zho_x_preferred":[
        "\u5996\u7cbe\u6c9f"
    ],
    "wof:name":"Yaojinggou",
    "wof:placetype":"locality"
},
  "geometry": {"coordinates":[102.429,30.9026],"type":"Point"}
}