{
  "type": "Feature",
  "properties": {
    "gn:admin1_code":"29.0",
    "gn:asciiname":"Shedian",
    "gn:country_code":"CN",
    "gn:dem":1721,
    "gn:feature_class":"P",
    "gn:feature_code":"PPL",
    "gn:name":"Shedian",
    "gn:population":0,
    "gn:timezone":"Asia/Shanghai",
    "iso:country":"CN",
    "name:zho_x_preferred":[
        "\u8bbe\u7538"
    ],
    "wof:name":"Shedian",
    "wof:placetype":"locality"
},
  "geometry": {"coordinates":[101.55200000000001,25.6779],"type":"Point"}
}