{
  "type": "Feature",
  "properties": {
    "gn:admin1_code":"18",
    "gn:asciiname":"Zhengjiagou",
    "gn:country_code":"CN",
    "gn:dem":724,
    "gn:feature_class":"P",
    "gn:feature_code":"PPL",
    "gn:name":"Zhengjiagou",
    "gn:population":0,
    "gn:timezone":"Asia/Shanghai",
    "iso:country":"CN",
    "name:zho_x_preferred":[
        "\u90d1\u5bb6\u6c9f"
    ],
    "wof:name":"Zhengjiagou",
    "wof:placetype":"locality"
},
  "geometry": {"coordinates":[107.79900000000001,27.8797],"type":"Point"}
}