{
  "type": "Feature",
  "properties": {
    "gn:admin1_code":"18",
    "gn:asciiname":"Pipo",
    "gn:country_code":"CN",
    "gn:dem":1218,
    "gn:feature_class":"P",
    "gn:feature_code":"PPL",
    "gn:name":"Pipo",
    "gn:population":0,
    "gn:timezone":"Asia/Shanghai",
    "iso:country":"CN",
    "name:deu_x_preferred":[
        "Pipo"
    ],
    "name:epo_x_preferred":[
        "Pipo"
    ],
    "name:fra_x_preferred":[
        "Pipo"
    ],
    "name:pol_x_preferred":[
        "Pipo"
    ],
    "name:por_x_preferred":[
        "Pipo"
    ],
    "name:spa_x_preferred":[
        "Pipo"
    ],
    "name:zho_x_preferred":[
        "\u76ae\u5761"
    ],
    "wof:name":"Pipo",
    "wof:placetype":"locality"
},
  "geometry": {"coordinates":[106.75700000000001,27.9178],"type":"Point"}
}