{
  "type": "Feature",
  "properties": {
    "gn:admin1_code":"24.0",
    "gn:asciiname":"Xinbu",
    "gn:country_code":"CN",
    "gn:dem":422,
    "gn:feature_class":"P",
    "gn:feature_code":"PPL",
    "gn:name":"Xinbu",
    "gn:population":0,
    "gn:timezone":"Asia/Shanghai",
    "iso:country":"CN",
    "name:und_x_variant":[
        "\u8f9b\u5821"
    ],
    "wof:name":"Xinbu",
    "wof:placetype":"locality"
},
  "geometry": {"coordinates":[111.09913,35.63032000000001],"type":"Point"}
}