{
  "type": "Feature",
  "properties": {
    "gn:admin1_code":"11.0",
    "gn:asciiname":"Pailoushan",
    "gn:country_code":"CN",
    "gn:dem":122,
    "gn:feature_class":"P",
    "gn:feature_code":"PPL",
    "gn:name":"Pailoushan",
    "gn:population":0,
    "gn:timezone":"Asia/Shanghai",
    "iso:country":"CN",
    "name:zho_x_preferred":[
        "\u724c\u697c\u5c71"
    ],
    "wof:name":"Pailoushan",
    "wof:placetype":"locality"
},
  "geometry": {"coordinates":[112.53671,27.30131],"type":"Point"}
}