{
  "type": "Feature",
  "properties": {
    "gn:admin1_code":"4.0",
    "gn:asciiname":"Jianhua",
    "gn:country_code":"CN",
    "gn:dem":2,
    "gn:feature_class":"P",
    "gn:feature_code":"PPL",
    "gn:name":"Jianhua",
    "gn:population":0,
    "gn:timezone":"Asia/Shanghai",
    "iso:country":"CN",
    "name:zho_x_preferred":[
        "Jianhua"
    ],
    "name:zho_x_variant":[
        "\u5efa\u534e"
    ],
    "wof:name":"Jianhua",
    "wof:placetype":"locality"
},
  "geometry": {"coordinates":[119.62709,33.83054],"type":"Point"}
}