{
  "type": "Feature",
  "properties": {
    "gn:admin1_code":"29.0",
    "gn:asciiname":"Jiufangcun",
    "gn:country_code":"CN",
    "gn:dem":2141,
    "gn:feature_class":"P",
    "gn:feature_code":"PPL",
    "gn:name":"Jiufangcun",
    "gn:population":0,
    "gn:timezone":"Asia/Shanghai",
    "iso:country":"CN",
    "name:zho_x_preferred":[
        "\u9152\u623f\u6751"
    ],
    "wof:name":"Jiufangcun",
    "wof:placetype":"locality"
},
  "geometry": {"coordinates":[103.434,27.4089],"type":"Point"}
}