{
  "type": "Feature",
  "properties": {
    "gn:admin1_code":"29.0",
    "gn:asciiname":"Woyang",
    "gn:country_code":"CN",
    "gn:dem":1530,
    "gn:feature_class":"P",
    "gn:feature_code":"PPL",
    "gn:name":"Woyang",
    "gn:population":0,
    "gn:timezone":"Asia/Shanghai",
    "iso:country":"CN",
    "name:zho_x_preferred":[
        "\u7a9d\u7f8a"
    ],
    "wof:name":"Woyang",
    "wof:placetype":"locality"
},
  "geometry": {"coordinates":[99.50830000000001,22.8226],"type":"Point"}
}