{
  "type": "Feature",
  "properties": {
    "gn:admin1_code":"08",
    "gn:asciiname":"Xinhuacun",
    "gn:country_code":"CN",
    "gn:dem":357,
    "gn:feature_class":"P",
    "gn:feature_code":"PPL",
    "gn:name":"Xinhuacun",
    "gn:population":0,
    "gn:timezone":"Asia/Shanghai",
    "iso:country":"CN",
    "name:und_x_variant":[
        "Xinhua",
        "Xinhuacun"
    ],
    "name:zho_x_preferred":[
        "\u65b0\u534e"
    ],
    "name:zho_x_variant":[
        "\u65b0\u534e\u6751"
    ],
    "wof:name":"Xinhuacun",
    "wof:placetype":"locality"
},
  "geometry": {"coordinates":[126.89165,49.97714000000001],"type":"Point"}
}