{
  "type": "Feature",
  "properties": {
    "gn:admin1_code":"3.0",
    "gn:asciiname":"Luling",
    "gn:country_code":"CN",
    "gn:dem":60,
    "gn:feature_class":"P",
    "gn:feature_code":"PPL",
    "gn:name":"Luling",
    "gn:population":0,
    "gn:timezone":"Asia/Shanghai",
    "iso:country":"CN",
    "name:ceb_x_preferred":[
        "Luling"
    ],
    "name:deu_x_preferred":[
        "Luling"
    ],
    "name:fra_x_preferred":[
        "Luling"
    ],
    "name:ita_x_preferred":[
        "Luling"
    ],
    "name:nld_x_preferred":[
        "Luling"
    ],
    "name:pol_x_preferred":[
        "Luling"
    ],
    "name:srp_x_preferred":[
        "\u041b\u0443\u043b\u0438\u043d\u0433"
    ],
    "name:swe_x_preferred":[
        "Luling"
    ],
    "name:und_x_variant":[
        "\u5362\u5cad"
    ],
    "wof:name":"Luling",
    "wof:placetype":"locality"
},
  "geometry": {"coordinates":[116.3989,29.73786],"type":"Point"}
}