{
  "type": "Feature",
  "properties": {
    "gn:admin1_code":"07",
    "gn:asciiname":"Nanzhao",
    "gn:country_code":"CN",
    "gn:dem":20,
    "gn:feature_class":"P",
    "gn:feature_code":"PPLA3",
    "gn:name":"Nanzhao",
    "gn:population":0,
    "gn:timezone":"Asia/Shanghai",
    "iso:country":"CN",
    "name:fas_x_preferred":[
        "\u0646\u0627\u0646\u0698\u0627\u0626\u0648"
    ],
    "name:und_x_variant":[
        "Chao-an",
        "Chao-an-hsien",
        "Nanzhao",
        "Nanzhao Zhen"
    ],
    "name:zho_x_preferred":[
        "Zhao\u2019an"
    ],
    "name:zho_x_variant":[
        "\u5357\u8bcf\u9547"
    ],
    "wof:name":"Nanzhao",
    "wof:placetype":"locality"
},
  "geometry": {"coordinates":[117.17103,23.7199],"type":"Point"}
}