{
  "type": "Feature",
  "properties": {
    "gn:admin1_code":"26",
    "gn:asciiname":"Shangdancun",
    "gn:country_code":"CN",
    "gn:dem":664,
    "gn:feature_class":"P",
    "gn:feature_code":"PPL",
    "gn:name":"Shangdancun",
    "gn:population":0,
    "gn:timezone":"Asia/Shanghai",
    "iso:country":"CN",
    "name:und_x_variant":[
        "Shangdan",
        "Shangdancun"
    ],
    "name:zho_x_preferred":[
        "\u4e0a\u65e6"
    ],
    "name:zho_x_variant":[
        "\u4e0a\u65e6\u6751"
    ],
    "wof:name":"Shangdancun",
    "wof:placetype":"locality"
},
  "geometry": {"coordinates":[108.27675000000001,34.55103],"type":"Point"}
}