{
  "type": "Feature",
  "properties": {
    "gn:admin1_code":"32.0",
    "gn:asciiname":"Waxi",
    "gn:country_code":"CN",
    "gn:dem":2360,
    "gn:feature_class":"P",
    "gn:feature_code":"PPL",
    "gn:name":"Waxi",
    "gn:population":0,
    "gn:timezone":"Asia/Shanghai",
    "iso:country":"CN",
    "name:zho_x_preferred":[
        "\u74e6\u897f"
    ],
    "wof:name":"Waxi",
    "wof:placetype":"locality"
},
  "geometry": {"coordinates":[103.15488000000001,28.56191],"type":"Point"}
}