{
  "type": "Feature",
  "properties": {
    "gn:admin1_code":"10",
    "gn:asciiname":"Dabeizhang",
    "gn:cc2":"CN",
    "gn:country_code":"CN",
    "gn:dem":41,
    "gn:feature_class":"P",
    "gn:feature_code":"PPL",
    "gn:name":"Dabeizhang",
    "gn:population":0,
    "gn:timezone":"Asia/Shanghai",
    "iso:country":"CN",
    "name:und_x_variant":[
        "Ta-pei-chang",
        "Ta-pei-chuang",
        "Dabeizhang"
    ],
    "wof:name":"Dabeizhang",
    "wof:placetype":"locality"
},
  "geometry": {"coordinates":[114.67749999999999,37.18333],"type":"Point"}
}