{
  "type": "Feature",
  "properties": {
    "gn:admin1_code":"9.0",
    "gn:asciiname":"Dongzhang",
    "gn:country_code":"CN",
    "gn:dem":446,
    "gn:feature_class":"P",
    "gn:feature_code":"PPL",
    "gn:name":"Dongzhang",
    "gn:population":0,
    "gn:timezone":"Asia/Shanghai",
    "iso:country":"CN",
    "name:zho_x_preferred":[
        "\u4e1c\u5f20"
    ],
    "wof:name":"Dongzhang",
    "wof:placetype":"locality"
},
  "geometry": {"coordinates":[111.94279,34.78406],"type":"Point"}
}