{
  "type": "Feature",
  "properties": {
    "gn:admin1_code":"2.0",
    "gn:asciiname":"Jingtou",
    "gn:country_code":"CN",
    "gn:dem":68,
    "gn:feature_class":"P",
    "gn:feature_code":"PPL",
    "gn:name":"Jingtou",
    "gn:population":0,
    "gn:timezone":"Asia/Shanghai",
    "iso:country":"CN",
    "name:und_x_variant":[
        "\u4e95\u5934",
        "Jingtou"
    ],
    "wof:name":"Jingtou",
    "wof:placetype":"locality"
},
  "geometry": {"coordinates":[119.64533,29.33243],"type":"Point"}
}