{
  "type": "Feature",
  "properties": {
    "gn:admin1_code":"3",
    "gn:asciiname":"Sheguanwan",
    "gn:country_code":"CN",
    "gn:dem":226,
    "gn:feature_class":"P",
    "gn:feature_code":"PPL",
    "gn:name":"Sheguanwan",
    "gn:population":0,
    "gn:timezone":"Asia/Shanghai",
    "iso:country":"CN",
    "name:zho_x_preferred":[
        "\u793e\u5b98\u5f2f"
    ],
    "wof:name":"Sheguanwan",
    "wof:placetype":"locality"
},
  "geometry": {"coordinates":[114.264,25.8247],"type":"Point"}
}