{
  "type": "Feature",
  "properties": {
    "gn:admin1_code":"32.0",
    "gn:asciiname":"Lizishu",
    "gn:country_code":"CN",
    "gn:dem":2492,
    "gn:feature_class":"P",
    "gn:feature_code":"PPL",
    "gn:name":"Lizishu",
    "gn:population":0,
    "gn:timezone":"Asia/Shanghai",
    "iso:country":"CN",
    "name:zho_x_preferred":[
        "\u674e\u5b50\u6811"
    ],
    "wof:name":"Lizishu",
    "wof:placetype":"locality"
},
  "geometry": {"coordinates":[102.011,26.6506],"type":"Point"}
}