{
  "type": "Feature",
  "properties": {
    "gn:admin1_code":"33.0",
    "gn:asciiname":"Gulong",
    "gn:country_code":"CN",
    "gn:dem":401,
    "gn:feature_class":"P",
    "gn:feature_code":"PPLA4",
    "gn:name":"Gulong",
    "gn:population":0,
    "gn:timezone":"Asia/Shanghai",
    "iso:country":"CN",
    "name:und_x_variant":[
        "Gulong Xiang",
        "Longjia Shuijing Wuji"
    ],
    "name:zho_x_preferred":[
        "\u53e4\u9f99"
    ],
    "name:zho_x_variant":[
        "\u53e4\u9f99\u4e61",
        "\u9f99\u5bb6\u6c34\u4e95\u5c4b\u57fa"
    ],
    "wof:name":"Gulong",
    "wof:placetype":"locality"
},
  "geometry": {"coordinates":[106.00382999999999,29.70472],"type":"Point"}
}