{
  "type": "Feature",
  "properties": {
    "gn:admin1_code":"10.0",
    "gn:asciiname":"Guangshuituo",
    "gn:country_code":"CN",
    "gn:dem":37,
    "gn:feature_class":"P",
    "gn:feature_code":"PPL",
    "gn:name":"Guangshuituo",
    "gn:population":0,
    "gn:timezone":"Asia/Shanghai",
    "iso:country":"CN",
    "name:zho_x_preferred":[
        "\u5149\u6c34\u5768"
    ],
    "wof:name":"Guangshuituo",
    "wof:placetype":"locality"
},
  "geometry": {"coordinates":[118.52943,39.66268],"type":"Point"}
}