{
  "type": "Feature",
  "properties": {
    "gn:admin1_code":"32.0",
    "gn:asciiname":"Puche Yanwo",
    "gn:country_code":"CN",
    "gn:dem":2117,
    "gn:feature_class":"P",
    "gn:feature_code":"PPL",
    "gn:name":"Puche Yanwo",
    "gn:population":0,
    "gn:timezone":"Asia/Shanghai",
    "iso:country":"CN",
    "name:zho_x_preferred":[
        "\u666e\u8f66\u71d5\u7a9d"
    ],
    "wof:name":"Puche Yanwo",
    "wof:placetype":"locality"
},
  "geometry": {"coordinates":[102.77469000000001,27.97817],"type":"Point"}
}