{
  "type": "Feature",
  "properties": {
    "gn:admin1_code":"29.0",
    "gn:asciiname":"Dushitou",
    "gn:country_code":"CN",
    "gn:dem":1286,
    "gn:feature_class":"P",
    "gn:feature_code":"PPL",
    "gn:name":"Dushitou",
    "gn:population":0,
    "gn:timezone":"Asia/Shanghai",
    "iso:country":"CN",
    "name:zho_x_preferred":[
        "\u72ec\u77f3\u5934"
    ],
    "wof:name":"Dushitou",
    "wof:placetype":"locality"
},
  "geometry": {"coordinates":[104.199,23.4106],"type":"Point"}
}