{
  "type": "Feature",
  "properties": {
    "gn:admin1_code":"29.0",
    "gn:asciiname":"Pangjiagou",
    "gn:country_code":"CN",
    "gn:dem":2233,
    "gn:feature_class":"P",
    "gn:feature_code":"PPL",
    "gn:name":"Pangjiagou",
    "gn:population":0,
    "gn:timezone":"Asia/Shanghai",
    "iso:country":"CN",
    "name:zho_x_preferred":[
        "\u5e9e\u5bb6\u6c9f"
    ],
    "wof:name":"Pangjiagou",
    "wof:placetype":"locality"
},
  "geometry": {"coordinates":[102.919,27.2904],"type":"Point"}
}