{
  "type": "Feature",
  "properties": {
    "gn:admin1_code":"7.0",
    "gn:asciiname":"Luohan",
    "gn:country_code":"CN",
    "gn:dem":566,
    "gn:feature_class":"P",
    "gn:feature_code":"PPL",
    "gn:name":"Luohan",
    "gn:population":0,
    "gn:timezone":"Asia/Shanghai",
    "iso:country":"CN",
    "name:und_x_variant":[
        "\u7f57\u6c49"
    ],
    "name:zho_x_preferred":[
        "\u7f57\u6c49"
    ],
    "wof:name":"Luohan",
    "wof:placetype":"locality"
},
  "geometry": {"coordinates":[117.19629999999999,26.28654],"type":"Point"}
}