{
  "type": "Feature",
  "properties": {
    "gn:admin1_code":"10",
    "gn:asciiname":"Songjiayao",
    "gn:country_code":"CN",
    "gn:dem":1198,
    "gn:feature_class":"P",
    "gn:feature_code":"PPL",
    "gn:name":"Songjiayao",
    "gn:population":0,
    "gn:timezone":"Asia/Shanghai",
    "iso:country":"CN",
    "name:zho_x_preferred":[
        "\u5b8b\u5bb6\u7a91"
    ],
    "wof:name":"Songjiayao",
    "wof:placetype":"locality"
},
  "geometry": {"coordinates":[115.65129,40.88331],"type":"Point"}
}