{
  "type": "Feature",
  "properties": {
    "gn:admin1_code":"4.0",
    "gn:asciiname":"Wutan",
    "gn:country_code":"CN",
    "gn:dem":2,
    "gn:feature_class":"P",
    "gn:feature_code":"PPL",
    "gn:name":"Wutan",
    "gn:population":0,
    "gn:timezone":"Asia/Shanghai",
    "iso:country":"CN",
    "name:zho_x_preferred":[
        "Wutan"
    ],
    "name:zho_x_variant":[
        "\u5434\u6ee9"
    ],
    "wof:name":"Wutan",
    "wof:placetype":"locality"
},
  "geometry": {"coordinates":[119.42389,34.43452],"type":"Point"}
}