{
  "type": "Feature",
  "properties": {
    "gn:admin1_code":"1.0",
    "gn:asciiname":"Henggangcun",
    "gn:country_code":"CN",
    "gn:dem":181,
    "gn:feature_class":"P",
    "gn:feature_code":"PPL",
    "gn:name":"Henggangcun",
    "gn:population":0,
    "gn:timezone":"Asia/Shanghai",
    "iso:country":"CN",
    "name:zho_x_preferred":[
        "\u6a2a\u5c97\u6751"
    ],
    "wof:name":"Henggangcun",
    "wof:placetype":"locality"
},
  "geometry": {"coordinates":[119.5307,31.14648],"type":"Point"}
}