{
  "type": "Feature",
  "properties": {
    "gn:admin1_code":"3.0",
    "gn:asciiname":"Yushuijian",
    "gn:country_code":"CN",
    "gn:dem":997,
    "gn:feature_class":"P",
    "gn:feature_code":"PPL",
    "gn:name":"Yushuijian",
    "gn:population":0,
    "gn:timezone":"Asia/Shanghai",
    "iso:country":"CN",
    "name:und_x_variant":[
        "\u96e8\u6c34\u5c16"
    ],
    "wof:name":"Yushuijian",
    "wof:placetype":"locality"
},
  "geometry": {"coordinates":[114.13352999999999,29.15944],"type":"Point"}
}