{
  "type": "Feature",
  "properties": {
    "gn:admin1_code":"19.0",
    "gn:asciiname":"Dachagou",
    "gn:country_code":"CN",
    "gn:dem":602,
    "gn:feature_class":"P",
    "gn:feature_code":"PPL",
    "gn:name":"Dachagou",
    "gn:population":0,
    "gn:timezone":"Asia/Shanghai",
    "iso:country":"CN",
    "name:und_x_variant":[
        "\u5927\u5c94\u6c9f"
    ],
    "wof:name":"Dachagou",
    "wof:placetype":"locality"
},
  "geometry": {"coordinates":[122.95047,40.35075],"type":"Point"}
}