{
  "type": "Feature",
  "properties": {
    "gn:admin1_code":"3.0",
    "gn:asciiname":"Shelingguan",
    "gn:country_code":"CN",
    "gn:dem":77,
    "gn:feature_class":"P",
    "gn:feature_code":"PPL",
    "gn:name":"Shelingguan",
    "gn:population":0,
    "gn:timezone":"Asia/Shanghai",
    "iso:country":"CN",
    "name:und_x_variant":[
        "\u793e\u4ee4\u5173"
    ],
    "wof:name":"Shelingguan",
    "wof:placetype":"locality"
},
  "geometry": {"coordinates":[116.63943,28.12772],"type":"Point"}
}