{
  "type": "Feature",
  "properties": {
    "gn:admin1_code":"2.0",
    "gn:asciiname":"Dusong",
    "gn:country_code":"CN",
    "gn:dem":184,
    "gn:feature_class":"P",
    "gn:feature_code":"PPL",
    "gn:name":"Dusong",
    "gn:population":0,
    "gn:timezone":"Asia/Shanghai",
    "iso:country":"CN",
    "name:und_x_variant":[
        "\u72ec\u677e"
    ],
    "wof:name":"Dusong",
    "wof:placetype":"locality"
},
  "geometry": {"coordinates":[119.70911,30.55953],"type":"Point"}
}