{
  "type": "Feature",
  "properties": {
    "gn:admin1_code":"29.0",
    "gn:asciiname":"Xiatu",
    "gn:country_code":"CN",
    "gn:dem":3277,
    "gn:feature_class":"P",
    "gn:feature_code":"PPL",
    "gn:name":"Xiatu",
    "gn:population":0,
    "gn:timezone":"Asia/Shanghai",
    "iso:country":"CN",
    "name:zho_x_preferred":[
        "\u5413\u571f"
    ],
    "wof:name":"Xiatu",
    "wof:placetype":"locality"
},
  "geometry": {"coordinates":[99.6865,27.8109],"type":"Point"}
}