{
  "type": "Feature",
  "properties": {
    "gn:admin1_code":"12.0",
    "gn:asciiname":"Zhonghetai",
    "gn:country_code":"CN",
    "gn:dem":36,
    "gn:feature_class":"P",
    "gn:feature_code":"PPL",
    "gn:name":"Zhonghetai",
    "gn:population":0,
    "gn:timezone":"Asia/Shanghai",
    "iso:country":"CN",
    "name:zho_x_preferred":[
        "\u4e2d\u548c\u53f0"
    ],
    "wof:name":"Zhonghetai",
    "wof:placetype":"locality"
},
  "geometry": {"coordinates":[112.77054,30.64396],"type":"Point"}
}