{
  "type": "Feature",
  "properties": {
    "gn:admin1_code":"19.0",
    "gn:asciiname":"Chebuzi",
    "gn:country_code":"CN",
    "gn:dem":21,
    "gn:feature_class":"P",
    "gn:feature_code":"PPL",
    "gn:name":"Chebuzi",
    "gn:population":0,
    "gn:timezone":"Asia/Shanghai",
    "iso:country":"CN",
    "name:und_x_variant":[
        "Chebaozi",
        "Chebuzi"
    ],
    "name:zho_x_preferred":[
        "\u8f66\u5821\u5b50"
    ],
    "wof:name":"Chebuzi",
    "wof:placetype":"locality"
},
  "geometry": {"coordinates":[121.84913,41.48398],"type":"Point"}
}