{
  "type": "Feature",
  "properties": {
    "gn:admin1_code":"30",
    "gn:asciiname":"Yunxiao'an",
    "gn:country_code":"CN",
    "gn:dem":530,
    "gn:feature_class":"P",
    "gn:feature_code":"PPL",
    "gn:name":"Yunxiao\u2019an",
    "gn:population":0,
    "gn:timezone":"Asia/Shanghai",
    "iso:country":"CN",
    "name:zho_x_preferred":[
        "\u4e91\u9704\u5eb5"
    ],
    "name:zho_x_variant":[
        "Yunxiao\u2019an"
    ],
    "wof:name":"Yunxiao'an",
    "wof:placetype":"locality"
},
  "geometry": {"coordinates":[116.10869,24.82684],"type":"Point"}
}