{
  "type": "Feature",
  "properties": {
    "gn:admin1_code":"15.0",
    "gn:asciiname":"Junmachang",
    "gn:country_code":"CN",
    "gn:dem":3283,
    "gn:feature_class":"P",
    "gn:feature_code":"PPL",
    "gn:name":"Junmachang",
    "gn:population":0,
    "gn:timezone":"Asia/Shanghai",
    "iso:country":"CN",
    "name:und_x_variant":[
        "\u519b\u9a6c\u573a"
    ],
    "wof:name":"Junmachang",
    "wof:placetype":"locality"
},
  "geometry": {"coordinates":[103.10317000000001,34.85309],"type":"Point"}
}