{
  "type": "Feature",
  "properties": {
    "gn:admin1_code":"19.0",
    "gn:asciiname":"Baijiaxiaozhuang",
    "gn:country_code":"CN",
    "gn:dem":49,
    "gn:feature_class":"P",
    "gn:feature_code":"PPL",
    "gn:name":"Baijiaxiaozhuang",
    "gn:population":0,
    "gn:timezone":"Asia/Shanghai",
    "iso:country":"CN",
    "name:und_x_variant":[
        "Baijia Xiaozhuang"
    ],
    "name:zho_x_preferred":[
        "\u767d\u5bb6\u5c0f\u5e84"
    ],
    "wof:name":"Baijiaxiaozhuang",
    "wof:placetype":"locality"
},
  "geometry": {"coordinates":[121.449,41.4739],"type":"Point"}
}