{
  "type": "Feature",
  "properties": {
    "gn:admin1_code":"16.0",
    "gn:asciiname":"Fengtouling",
    "gn:country_code":"CN",
    "gn:dem":12,
    "gn:feature_class":"P",
    "gn:feature_code":"PPL",
    "gn:name":"Fengtouling",
    "gn:population":0,
    "gn:timezone":"Asia/Shanghai",
    "iso:country":"CN",
    "name:zho_x_preferred":[
        "\u98ce\u5934\u5cad"
    ],
    "wof:name":"Fengtouling",
    "wof:placetype":"locality"
},
  "geometry": {"coordinates":[108.898,21.6779],"type":"Point"}
}