{
  "type": "Feature",
  "properties": {
    "gn:admin1_code":"4.0",
    "gn:asciiname":"Kaiyuancun",
    "gn:country_code":"CN",
    "gn:dem":1,
    "gn:feature_class":"P",
    "gn:feature_code":"PPL",
    "gn:name":"Kaiyuancun",
    "gn:population":0,
    "gn:timezone":"Asia/Shanghai",
    "iso:country":"CN",
    "name:zho_x_preferred":[
        "\u5f00\u6e90\u6751"
    ],
    "wof:name":"Kaiyuancun",
    "wof:placetype":"locality"
},
  "geometry": {"coordinates":[119.80389,32.89587],"type":"Point"}
}