{
  "type": "Feature",
  "properties": {
    "gn:admin1_code":"10",
    "gn:asciiname":"Dingjiazhai",
    "gn:country_code":"CN",
    "gn:dem":34,
    "gn:feature_class":"P",
    "gn:feature_code":"PPL",
    "gn:name":"Dingjiazhai",
    "gn:population":0,
    "gn:timezone":"Asia/Shanghai",
    "iso:country":"CN",
    "name:zho_x_preferred":[
        "\u4e01\u5bb6\u5be8"
    ],
    "wof:name":"Dingjiazhai",
    "wof:placetype":"locality"
},
  "geometry": {"coordinates":[115.52309,36.96718],"type":"Point"}
}