{
  "type": "Feature",
  "properties": {
    "gn:admin1_code":"5.0",
    "gn:asciiname":"Jinjiangtun",
    "gn:country_code":"CN",
    "gn:dem":370,
    "gn:feature_class":"P",
    "gn:feature_code":"PPL",
    "gn:name":"Jinjiangtun",
    "gn:population":0,
    "gn:timezone":"Asia/Shanghai",
    "iso:country":"CN",
    "name:zho_x_preferred":[
        "\u9526\u6c5f\u5c6f"
    ],
    "wof:name":"Jinjiangtun",
    "wof:placetype":"locality"
},
  "geometry": {"coordinates":[128.66186999999999,43.71477],"type":"Point"}
}