{
  "type": "Feature",
  "properties": {
    "gn:admin1_code":"1.0",
    "gn:asciiname":"Yecun",
    "gn:country_code":"CN",
    "gn:dem":187,
    "gn:feature_class":"P",
    "gn:feature_code":"PPL",
    "gn:name":"Yecun",
    "gn:population":0,
    "gn:timezone":"Asia/Shanghai",
    "iso:country":"CN",
    "name:zho_x_preferred":[
        "Yecun"
    ],
    "name:zho_x_variant":[
        "\u53f6\u6751"
    ],
    "wof:name":"Yecun",
    "wof:placetype":"locality"
},
  "geometry": {"coordinates":[119.27159,30.41201],"type":"Point"}
}