{
  "type": "Feature",
  "properties": {
    "gn:admin1_code":"24.0",
    "gn:asciiname":"Nanwulaocun",
    "gn:country_code":"CN",
    "gn:dem":744,
    "gn:feature_class":"P",
    "gn:feature_code":"PPL",
    "gn:name":"Nanwulaocun",
    "gn:population":0,
    "gn:timezone":"Asia/Shanghai",
    "iso:country":"CN",
    "name:zho_x_preferred":[
        "\u5357\u6b66\u6d9d\u6751"
    ],
    "wof:name":"Nanwulaocun",
    "wof:placetype":"locality"
},
  "geometry": {"coordinates":[112.0226,37.36164],"type":"Point"}
}