{
  "type": "Feature",
  "properties": {
    "gn:admin1_code":"7.0",
    "gn:asciiname":"Xijilou",
    "gn:country_code":"CN",
    "gn:dem":327,
    "gn:feature_class":"P",
    "gn:feature_code":"PPL",
    "gn:name":"Xijilou",
    "gn:population":0,
    "gn:timezone":"Asia/Shanghai",
    "iso:country":"CN",
    "name:zho_x_preferred":[
        "\u6eaa\u6d4e\u697c"
    ],
    "wof:name":"Xijilou",
    "wof:placetype":"locality"
},
  "geometry": {"coordinates":[116.79783999999999,24.8731],"type":"Point"}
}