{
  "type": "Feature",
  "properties": {
    "gn:admin1_code":"33.0",
    "gn:asciiname":"Anwen",
    "gn:country_code":"CN",
    "gn:dem":746,
    "gn:feature_class":"P",
    "gn:feature_code":"PPLA4",
    "gn:name":"Anwen",
    "gn:population":0,
    "gn:timezone":"Asia/Shanghai",
    "iso:country":"CN",
    "name:und_x_variant":[
        "Anwen Zhen"
    ],
    "name:zho_x_preferred":[
        "\u5b89\u7a33"
    ],
    "name:zho_x_variant":[
        "\u5b89\u7a33\u9547"
    ],
    "wof:name":"Anwen",
    "wof:placetype":"locality"
},
  "geometry": {"coordinates":[106.75651000000001,28.68001],"type":"Point"}
}