{
  "type": "Feature",
  "properties": {
    "gn:admin1_code":"24.0",
    "gn:asciiname":"Beizhaocun",
    "gn:country_code":"CN",
    "gn:dem":911,
    "gn:feature_class":"P",
    "gn:feature_code":"PPL",
    "gn:name":"Beizhaocun",
    "gn:population":0,
    "gn:timezone":"Asia/Shanghai",
    "iso:country":"CN",
    "name:zho_x_preferred":[
        "\u5317\u8d75\u6751"
    ],
    "wof:name":"Beizhaocun",
    "wof:placetype":"locality"
},
  "geometry": {"coordinates":[112.81665,37.6413],"type":"Point"}
}