{
  "type": "Feature",
  "properties": {
    "gn:admin1_code":"32.0",
    "gn:asciiname":"Shangbaka",
    "gn:country_code":"CN",
    "gn:dem":3296,
    "gn:feature_class":"P",
    "gn:feature_code":"PPL",
    "gn:name":"Shangbaka",
    "gn:population":0,
    "gn:timezone":"Asia/Shanghai",
    "iso:country":"CN",
    "name:zho_x_preferred":[
        "\u4e0a\u5df4\u5361"
    ],
    "wof:name":"Shangbaka",
    "wof:placetype":"locality"
},
  "geometry": {"coordinates":[99.3218,31.4752],"type":"Point"}
}