{
  "type": "Feature",
  "properties": {
    "gn:admin1_code":"26",
    "gn:asciiname":"Caocun",
    "gn:country_code":"CN",
    "gn:dem":505,
    "gn:feature_class":"P",
    "gn:feature_code":"PPL",
    "gn:name":"Caocun",
    "gn:population":0,
    "gn:timezone":"Asia/Shanghai",
    "iso:country":"CN",
    "name:zho_x_preferred":[
        "\u66f9\u6751"
    ],
    "wof:name":"Caocun",
    "wof:placetype":"locality"
},
  "geometry": {"coordinates":[108.92471999999999,34.055],"type":"Point"}
}