{
  "type": "Feature",
  "properties": {
    "gn:admin1_code":"4.0",
    "gn:asciiname":"Yanjiazao",
    "gn:country_code":"CN",
    "gn:dem":3,
    "gn:feature_class":"P",
    "gn:feature_code":"PPL",
    "gn:name":"Yanjiazao",
    "gn:population":0,
    "gn:timezone":"Asia/Shanghai",
    "iso:country":"CN",
    "name:und_x_variant":[
        "\u4e25\u5bb6\u7076"
    ],
    "wof:name":"Yanjiazao",
    "wof:placetype":"locality"
},
  "geometry": {"coordinates":[121.13737999999999,32.12132],"type":"Point"}
}