{
  "type": "Feature",
  "properties": {
    "gn:admin1_code":"8.0",
    "gn:asciiname":"Xiduibaocun",
    "gn:country_code":"CN",
    "gn:dem":211,
    "gn:feature_class":"P",
    "gn:feature_code":"PPL",
    "gn:name":"Xiduibaocun",
    "gn:population":0,
    "gn:timezone":"Asia/Shanghai",
    "iso:country":"CN",
    "name:zho_x_preferred":[
        "\u897f\u5bf9\u5b9d\u6751"
    ],
    "wof:name":"Xiduibaocun",
    "wof:placetype":"locality"
},
  "geometry": {"coordinates":[123.05459,47.24314],"type":"Point"}
}