{
  "type": "Feature",
  "properties": {
    "gn:admin1_code":"24",
    "gn:asciiname":"Zhaojiayao",
    "gn:country_code":"CN",
    "gn:dem":1191,
    "gn:feature_class":"P",
    "gn:feature_code":"PPL",
    "gn:name":"Zhaojiayao",
    "gn:population":0,
    "gn:timezone":"Asia/Shanghai",
    "iso:country":"CN",
    "name:und_x_variant":[
        "Chao-chia-yao",
        "Zhaojiayao"
    ],
    "wof:name":"Zhaojiayao",
    "wof:placetype":"locality"
},
  "geometry": {"coordinates":[113.28333000000001,40.25],"type":"Point"}
}