{
  "type": "Feature",
  "properties": {
    "gn:admin1_code":"25",
    "gn:asciiname":"Liushizhuang",
    "gn:country_code":"CN",
    "gn:dem":39,
    "gn:feature_class":"P",
    "gn:feature_code":"PPL",
    "gn:name":"Liushizhuang",
    "gn:population":0,
    "gn:timezone":"Asia/Shanghai",
    "iso:country":"CN",
    "name:zho_x_preferred":[
        "\u5218\u4ec0\u5e84"
    ],
    "wof:name":"Liushizhuang",
    "wof:placetype":"locality"
},
  "geometry": {"coordinates":[116.06,36.1266],"type":"Point"}
}