{
  "type": "Feature",
  "properties": {
    "gn:admin1_code":"1.0",
    "gn:asciiname":"Baiduncun",
    "gn:country_code":"CN",
    "gn:dem":19,
    "gn:feature_class":"P",
    "gn:feature_code":"PPL",
    "gn:name":"Baiduncun",
    "gn:population":0,
    "gn:timezone":"Asia/Shanghai",
    "iso:country":"CN",
    "name:und_x_variant":[
        "Baidun"
    ],
    "name:zho_x_preferred":[
        "\u767d\u58a9\u6751"
    ],
    "wof:name":"Baiduncun",
    "wof:placetype":"locality"
},
  "geometry": {"coordinates":[117.89167,33.27222],"type":"Point"}
}