{
  "type": "Feature",
  "properties": {
    "gn:admin1_code":"15.0",
    "gn:asciiname":"Hongtuzhuang",
    "gn:country_code":"CN",
    "gn:dem":2457,
    "gn:feature_class":"P",
    "gn:feature_code":"PPL",
    "gn:name":"Hongtuzhuang",
    "gn:population":0,
    "gn:timezone":"Asia/Shanghai",
    "iso:country":"CN",
    "name:zho_x_preferred":[
        "\u7ea2\u571f\u5e84"
    ],
    "wof:name":"Hongtuzhuang",
    "wof:placetype":"locality"
},
  "geometry": {"coordinates":[104.03100000000001,35.188],"type":"Point"}
}