{
  "type": "Feature",
  "properties": {
    "gn:admin1_code":"30.0",
    "gn:asciiname":"Dafuba",
    "gn:country_code":"CN",
    "gn:dem":33,
    "gn:feature_class":"P",
    "gn:feature_code":"PPL",
    "gn:name":"Dafuba",
    "gn:population":0,
    "gn:timezone":"Asia/Shanghai",
    "iso:country":"CN",
    "name:zho_x_preferred":[
        "\u5927\u798f\u575d"
    ],
    "wof:name":"Dafuba",
    "wof:placetype":"locality"
},
  "geometry": {"coordinates":[114.5235,22.89053],"type":"Point"}
}