{
  "type": "Feature",
  "properties": {
    "gn:admin1_code":"3.0",
    "gn:asciiname":"Lao'anli",
    "gn:country_code":"CN",
    "gn:dem":331,
    "gn:feature_class":"P",
    "gn:feature_code":"PPL",
    "gn:name":"Lao\u2019anli",
    "gn:population":0,
    "gn:timezone":"Asia/Shanghai",
    "iso:country":"CN",
    "name:und_x_variant":[
        "Lao\u2019anli",
        "\u8001\u5b89\u91cc"
    ],
    "wof:name":"Lao'anli",
    "wof:placetype":"locality"
},
  "geometry": {"coordinates":[114.36623,27.27567],"type":"Point"}
}