{
  "type": "Feature",
  "properties": {
    "gn:admin1_code":"19.0",
    "gn:asciiname":"Tianjia Wobu",
    "gn:country_code":"CN",
    "gn:dem":91,
    "gn:feature_class":"P",
    "gn:feature_code":"PPL",
    "gn:name":"Tianjia Wobu",
    "gn:population":0,
    "gn:timezone":"Asia/Shanghai",
    "iso:country":"CN",
    "name:und_x_variant":[
        "Tianjiawobao",
        "Tianjia Wobu"
    ],
    "name:zho_x_preferred":[
        "\u7530\u5bb6\u7a9d\u5821"
    ],
    "wof:name":"Tianjia Wobu",
    "wof:placetype":"locality"
},
  "geometry": {"coordinates":[123.48256000000001,42.93049],"type":"Point"}
}