{
  "type": "Feature",
  "properties": {
    "gn:admin1_code":"6.0",
    "gn:asciiname":"Shanglaxiu",
    "gn:country_code":"CN",
    "gn:dem":4230,
    "gn:feature_class":"P",
    "gn:feature_code":"PPLA4",
    "gn:name":"Shanglaxiu",
    "gn:population":0,
    "gn:timezone":"Asia/Urumqi",
    "iso:country":"CN",
    "name:und_x_variant":[
        "Shanglaxiu Xiang",
        "Duola Make"
    ],
    "name:zho_x_preferred":[
        "\u4e0a\u62c9\u79c0"
    ],
    "name:zho_x_variant":[
        "\u4e0a\u62c9\u79c0\u4e61",
        "\u591a\u62c9\u9ebb\u79d1"
    ],
    "wof:name":"Shanglaxiu",
    "wof:placetype":"locality"
},
  "geometry": {"coordinates":[96.58426,32.85399],"type":"Point"}
}