{
  "type": "Feature",
  "properties": {
    "gn:admin1_code":"15.0",
    "gn:asciiname":"Pochengzi Sandui",
    "gn:country_code":"CN",
    "gn:dem":1304,
    "gn:feature_class":"P",
    "gn:feature_code":"PPLF",
    "gn:name":"Pochengzi Sandui",
    "gn:population":0,
    "gn:timezone":"Asia/Urumqi",
    "iso:country":"CN",
    "name:zho_x_preferred":[
        "\u7834\u57ce\u5b50\u4e09\u961f"
    ],
    "wof:name":"Pochengzi Sandui",
    "wof:placetype":"locality"
},
  "geometry": {"coordinates":[95.9118,40.2989],"type":"Point"}
}