{
  "type": "Feature",
  "properties": {
    "gn:admin1_code":"14.0",
    "gn:asciiname":"Zhongranlong",
    "gn:country_code":"CN",
    "gn:dem":4667,
    "gn:feature_class":"P",
    "gn:feature_code":"PPL",
    "gn:name":"Zhongranlong",
    "gn:population":0,
    "gn:timezone":"Asia/Urumqi",
    "iso:country":"CN",
    "name:zho_x_preferred":[
        "\u4ef2\u7136\u9f99"
    ],
    "wof:name":"Zhongranlong",
    "wof:placetype":"locality"
},
  "geometry": {"coordinates":[94.87761999999999,30.93333],"type":"Point"}
}