{
  "type": "Feature",
  "properties": {
    "gn:admin1_code":"14.0",
    "gn:asciiname":"Pajuka",
    "gn:country_code":"CN",
    "gn:dem":4339,
    "gn:feature_class":"P",
    "gn:feature_code":"PPL",
    "gn:name":"Pajuka",
    "gn:population":0,
    "gn:timezone":"Asia/Urumqi",
    "iso:country":"CN",
    "name:zho_x_preferred":[
        "\u6015\u5c45\u5361"
    ],
    "wof:name":"Pajuka",
    "wof:placetype":"locality"
},
  "geometry": {"coordinates":[94.69028,31.1685],"type":"Point"}
}