{
  "type": "Feature",
  "properties": {
    "gn:admin1_code":"7.0",
    "gn:asciiname":"Bapu",
    "gn:country_code":"CN",
    "gn:dem":560,
    "gn:feature_class":"P",
    "gn:feature_code":"PPL",
    "gn:name":"Bapu",
    "gn:population":0,
    "gn:timezone":"Asia/Shanghai",
    "iso:country":"CN",
    "name:deu_x_preferred":[
        "Bapu"
    ],
    "name:fra_x_preferred":[
        "Bapu"
    ],
    "name:hin_x_preferred":[
        "\u092c\u093e\u092a\u0942"
    ],
    "name:pol_x_preferred":[
        "Bapu"
    ],
    "name:zho_x_preferred":[
        "\u516b\u84b2"
    ],
    "wof:name":"Bapu",
    "wof:placetype":"locality"
},
  "geometry": {"coordinates":[119.37045000000001,27.04955],"type":"Point"}
}