{
  "type": "Feature",
  "properties": {
    "gn:admin1_code":"04",
    "gn:asciiname":"Sanlong",
    "gn:country_code":"CN",
    "gn:dem":2,
    "gn:feature_class":"P",
    "gn:feature_code":"PPLA4",
    "gn:name":"Sanlong",
    "gn:population":0,
    "gn:timezone":"Asia/Shanghai",
    "iso:country":"CN",
    "name:und_x_variant":[
        "Lung-wang-miao",
        "San-lung",
        "Sanlong",
        "\u4e09\u9f99",
        "Sanlong Zhen",
        "\u4e09\u9f99\u9547"
    ],
    "wof:name":"Sanlong",
    "wof:placetype":"locality"
},
  "geometry": {"coordinates":[120.51085,33.41849000000001],"type":"Point"}
}