{
  "type": "Feature",
  "properties": {
    "gn:admin1_code":"21.0",
    "gn:asciiname":"Huangcaotan",
    "gn:country_code":"CN",
    "gn:dem":1350,
    "gn:feature_class":"P",
    "gn:feature_code":"PPL",
    "gn:name":"Huangcaotan",
    "gn:population":0,
    "gn:timezone":"Asia/Shanghai",
    "iso:country":"CN",
    "name:zho_x_preferred":[
        "\u9ec4\u8349\u6ee9"
    ],
    "wof:name":"Huangcaotan",
    "wof:placetype":"locality"
},
  "geometry": {"coordinates":[106.21299999999999,38.9749],"type":"Point"}
}