{
  "type": "Feature",
  "properties": {
    "gn:admin1_code":"29.0",
    "gn:asciiname":"Manhuohui",
    "gn:country_code":"CN",
    "gn:dem":1266,
    "gn:feature_class":"P",
    "gn:feature_code":"PPL",
    "gn:name":"Manhuohui",
    "gn:population":0,
    "gn:timezone":"Asia/Shanghai",
    "iso:country":"CN",
    "name:zho_x_preferred":[
        "\u66fc\u706b\u56de"
    ],
    "wof:name":"Manhuohui",
    "wof:placetype":"locality"
},
  "geometry": {"coordinates":[100.27800000000001,21.8162],"type":"Point"}
}