{
  "type": "Feature",
  "properties": {
    "gn:admin1_code":"26.0",
    "gn:asciiname":"Sanchahecun",
    "gn:country_code":"CN",
    "gn:dem":841,
    "gn:feature_class":"P",
    "gn:feature_code":"PPL",
    "gn:name":"Sanchahecun",
    "gn:population":0,
    "gn:timezone":"Asia/Shanghai",
    "iso:country":"CN",
    "name:zho_x_preferred":[
        "\u4e09\u5c94\u6cb3\u6751"
    ],
    "wof:name":"Sanchahecun",
    "wof:placetype":"locality"
},
  "geometry": {"coordinates":[110.91656999999999,33.60204],"type":"Point"}
}