{
  "type": "Feature",
  "properties": {
    "gn:admin1_code":"15.0",
    "gn:asciiname":"Ningma",
    "gn:country_code":"CN",
    "gn:dem":1146,
    "gn:feature_class":"P",
    "gn:feature_code":"PPL",
    "gn:name":"Ningma",
    "gn:population":0,
    "gn:timezone":"Asia/Shanghai",
    "iso:country":"CN",
    "name:und_x_variant":[
        "\u5b81\u9a6c"
    ],
    "wof:name":"Ningma",
    "wof:placetype":"locality"
},
  "geometry": {"coordinates":[106.1674,34.08717],"type":"Point"}
}