{
  "type": "Feature",
  "properties": {
    "gn:admin1_code":"32.0",
    "gn:asciiname":"Xia Zimei",
    "gn:country_code":"CN",
    "gn:dem":3278,
    "gn:feature_class":"P",
    "gn:feature_code":"PPL",
    "gn:name":"Xia Zimei",
    "gn:population":0,
    "gn:timezone":"Asia/Shanghai",
    "iso:country":"CN",
    "name:und_x_variant":[
        "Zimei"
    ],
    "name:zho_x_preferred":[
        "\u5b50\u6885"
    ],
    "wof:name":"Xia Zimei",
    "wof:placetype":"locality"
},
  "geometry": {"coordinates":[101.77194,29.52336],"type":"Point"}
}