{
  "type": "Feature",
  "properties": {
    "gn:admin1_code":"19.0",
    "gn:asciiname":"Yaodai",
    "gn:country_code":"CN",
    "gn:dem":279,
    "gn:feature_class":"P",
    "gn:feature_code":"PPL",
    "gn:name":"Yaodai",
    "gn:population":0,
    "gn:timezone":"Asia/Shanghai",
    "iso:country":"CN",
    "name:und_x_variant":[
        "\u8170\u5e26"
    ],
    "wof:name":"Yaodai",
    "wof:placetype":"locality"
},
  "geometry": {"coordinates":[125.34537,40.83725],"type":"Point"}
}