{
  "type": "Feature",
  "properties": {
    "gn:admin1_code":"10.0",
    "gn:asciiname":"Yanhaili",
    "gn:country_code":"CN",
    "gn:dem":5,
    "gn:feature_class":"P",
    "gn:feature_code":"PPL",
    "gn:name":"Yanhaili",
    "gn:population":0,
    "gn:timezone":"Asia/Shanghai",
    "iso:country":"CN",
    "name:zho_x_preferred":[
        "\u71d5\u6d77\u91cc"
    ],
    "wof:name":"Yanhaili",
    "wof:placetype":"locality"
},
  "geometry": {"coordinates":[119.61203,39.94995],"type":"Point"}
}