{
  "type": "Feature",
  "properties": {
    "gn:admin1_code":"15.0",
    "gn:asciiname":"Hecha",
    "gn:country_code":"CN",
    "gn:dem":1881,
    "gn:feature_class":"P",
    "gn:feature_code":"PPL",
    "gn:name":"Hecha",
    "gn:population":0,
    "gn:timezone":"Asia/Shanghai",
    "iso:country":"CN",
    "name:und_x_variant":[
        "\u4f55\u5c94"
    ],
    "wof:name":"Hecha",
    "wof:placetype":"locality"
},
  "geometry": {"coordinates":[105.89051000000001,35.40468],"type":"Point"}
}