{
  "type": "Feature",
  "properties": {
    "gn:admin1_code":"32.0",
    "gn:asciiname":"Cegen",
    "gn:country_code":"CN",
    "gn:dem":3194,
    "gn:feature_class":"P",
    "gn:feature_code":"PPL",
    "gn:name":"Cegen",
    "gn:population":0,
    "gn:timezone":"Asia/Shanghai",
    "iso:country":"CN",
    "name:zho_x_preferred":[
        "\u6d4b\u4e98"
    ],
    "wof:name":"Cegen",
    "wof:placetype":"locality"
},
  "geometry": {"coordinates":[100.804,31.1907],"type":"Point"}
}