{
  "type": "Feature",
  "properties": {
    "gn:admin1_code":"11.0",
    "gn:asciiname":"Hanjiang",
    "gn:country_code":"CN",
    "gn:dem":340,
    "gn:feature_class":"P",
    "gn:feature_code":"PPL",
    "gn:name":"Hanjiang",
    "gn:population":0,
    "gn:timezone":"Asia/Shanghai",
    "iso:country":"CN",
    "name:dan_x_preferred":[
        "Hanjiang"
    ],
    "name:deu_x_preferred":[
        "Hanjiang"
    ],
    "name:fra_x_preferred":[
        "Hanjiang"
    ],
    "name:nor_x_preferred":[
        "Hanjiang"
    ],
    "name:swe_x_preferred":[
        "Hanjiang"
    ],
    "name:zho_x_preferred":[
        "\u6db5\u6c5f"
    ],
    "wof:name":"Hanjiang",
    "wof:placetype":"locality"
},
  "geometry": {"coordinates":[112.41069,25.41091],"type":"Point"}
}