{
  "type": "Feature",
  "properties": {
    "gn:admin1_code":"18.0",
    "gn:asciiname":"Yaojia",
    "gn:country_code":"CN",
    "gn:dem":645,
    "gn:feature_class":"P",
    "gn:feature_code":"PPL",
    "gn:name":"Yaojia",
    "gn:population":0,
    "gn:timezone":"Asia/Shanghai",
    "iso:country":"CN",
    "name:zho_x_preferred":[
        "\u7476\u5bb6"
    ],
    "wof:name":"Yaojia",
    "wof:placetype":"locality"
},
  "geometry": {"coordinates":[108.01600000000001,25.2313],"type":"Point"}
}