{
  "type": "Feature",
  "properties": {
    "gn:admin1_code":"1.0",
    "gn:asciiname":"Gaoyan",
    "gn:country_code":"CN",
    "gn:dem":367,
    "gn:feature_class":"P",
    "gn:feature_code":"PPL",
    "gn:name":"Gaoyan",
    "gn:population":0,
    "gn:timezone":"Asia/Shanghai",
    "iso:country":"CN",
    "name:zho_x_preferred":[
        "\u9ad8\u6f14"
    ],
    "wof:name":"Gaoyan",
    "wof:placetype":"locality"
},
  "geometry": {"coordinates":[118.70078999999998,29.86478],"type":"Point"}
}