{
  "type": "Feature",
  "properties": {
    "gn:admin1_code":"11.0",
    "gn:asciiname":"Shanghebei",
    "gn:country_code":"CN",
    "gn:dem":75,
    "gn:feature_class":"P",
    "gn:feature_code":"PPL",
    "gn:name":"Shanghebei",
    "gn:population":0,
    "gn:timezone":"Asia/Shanghai",
    "iso:country":"CN",
    "name:zho_x_preferred":[
        "\u4e0a\u79be\u80cc"
    ],
    "wof:name":"Shanghebei",
    "wof:placetype":"locality"
},
  "geometry": {"coordinates":[113.24254000000001,26.89344],"type":"Point"}
}