{
  "type": "Feature",
  "properties": {
    "gn:admin1_code":"29.0",
    "gn:asciiname":"Achi",
    "gn:country_code":"CN",
    "gn:dem":2379,
    "gn:feature_class":"P",
    "gn:feature_code":"PPL",
    "gn:name":"Achi",
    "gn:population":0,
    "gn:timezone":"Asia/Shanghai",
    "iso:country":"CN",
    "name:ceb_x_preferred":[
        "Achi"
    ],
    "name:deu_x_preferred":[
        "Achi"
    ],
    "name:lim_x_preferred":[
        "Achi"
    ],
    "name:nld_x_preferred":[
        "Achi"
    ],
    "name:por_x_preferred":[
        "Achi"
    ],
    "name:spa_x_preferred":[
        "Ach\u00ed"
    ],
    "name:swe_x_preferred":[
        "Achi"
    ],
    "name:tur_x_preferred":[
        "A\u00e7i"
    ],
    "name:zho_x_preferred":[
        "\u963f\u75f4"
    ],
    "wof:name":"Achi",
    "wof:placetype":"locality"
},
  "geometry": {"coordinates":[103.504,23.6732],"type":"Point"}
}