{
  "type": "Feature",
  "properties": {
    "gn:admin1_code":"7.0",
    "gn:asciiname":"Xingxicun",
    "gn:country_code":"CN",
    "gn:dem":284,
    "gn:feature_class":"P",
    "gn:feature_code":"PPL",
    "gn:name":"Xingxicun",
    "gn:population":0,
    "gn:timezone":"Asia/Shanghai",
    "iso:country":"CN",
    "name:und_x_variant":[
        "\u674f\u6eaa\u6751"
    ],
    "name:zho_x_preferred":[
        "\u674f\u6eaa\u6751"
    ],
    "wof:name":"Xingxicun",
    "wof:placetype":"locality"
},
  "geometry": {"coordinates":[117.22323,26.69671],"type":"Point"}
}