{
  "type": "Feature",
  "properties": {
    "gn:admin1_code":"11.0",
    "gn:asciiname":"Mingfengxi",
    "gn:country_code":"CN",
    "gn:dem":628,
    "gn:feature_class":"P",
    "gn:feature_code":"PPL",
    "gn:name":"Mingfengxi",
    "gn:population":0,
    "gn:timezone":"Asia/Shanghai",
    "iso:country":"CN",
    "name:zho_x_preferred":[
        "\u9e23\u51e4\u6eaa"
    ],
    "name:zho_x_variant":[
        "\u9e23\u98ce\u6eaa"
    ],
    "wof:name":"Mingfengxi",
    "wof:placetype":"locality"
},
  "geometry": {"coordinates":[110.08708,29.13803],"type":"Point"}
}