{
  "type": "Feature",
  "properties": {
    "gn:admin1_code":"13",
    "gn:asciiname":"Kumu Maza",
    "gn:country_code":"CN",
    "gn:dem":1242,
    "gn:feature_class":"P",
    "gn:feature_code":"PPL",
    "gn:name":"Kumu Maza",
    "gn:population":0,
    "gn:timezone":"Asia/Shanghai",
    "iso:country":"CN",
    "name:und_x_variant":[
        "\u5e93\u6728\u9ebb\u624e"
    ],
    "wof:name":"Kumu Maza",
    "wof:placetype":"locality"
},
  "geometry": {"coordinates":[77.38634,38.22861],"type":"Point"}
}