{
  "type": "Feature",
  "properties": {
    "gn:admin1_code":"23.0",
    "gn:asciiname":"Chendong",
    "gn:country_code":"CN",
    "gn:dem":4,
    "gn:feature_class":"P",
    "gn:feature_code":"PPL",
    "gn:name":"Chendong",
    "gn:population":0,
    "gn:timezone":"Asia/Shanghai",
    "iso:country":"CN",
    "name:zho_x_preferred":[
        "Chendong"
    ],
    "name:zho_x_variant":[
        "\u9648\u4e1c"
    ],
    "wof:name":"Chendong",
    "wof:placetype":"locality"
},
  "geometry": {"coordinates":[121.81789000000001,31.49312],"type":"Point"}
}