{
  "type": "Feature",
  "properties": {
    "gn:admin1_code":"16.0",
    "gn:asciiname":"Zhitian",
    "gn:country_code":"CN",
    "gn:dem":311,
    "gn:feature_class":"P",
    "gn:feature_code":"PPL",
    "gn:name":"Zhitian",
    "gn:population":0,
    "gn:timezone":"Asia/Shanghai",
    "iso:country":"CN",
    "name:zho_x_preferred":[
        "\u652f\u7530"
    ],
    "wof:name":"Zhitian",
    "wof:placetype":"locality"
},
  "geometry": {"coordinates":[109.83199999999999,22.4214],"type":"Point"}
}