{
  "type": "Feature",
  "properties": {
    "gn:admin1_code":"19.0",
    "gn:asciiname":"Dalongwangtang",
    "gn:country_code":"CN",
    "gn:dem":7,
    "gn:feature_class":"P",
    "gn:feature_code":"PPL",
    "gn:name":"Dalongwangtang",
    "gn:population":0,
    "gn:timezone":"Asia/Shanghai",
    "iso:country":"CN",
    "name:und_x_variant":[
        "\u5927\u9f99\u738b\u5858"
    ],
    "name:zho_x_preferred":[
        "\u5927\u9f99\u738b\u5858"
    ],
    "wof:name":"Dalongwangtang",
    "wof:placetype":"locality"
},
  "geometry": {"coordinates":[121.39479,38.82352],"type":"Point"}
}