{
  "type": "Feature",
  "properties": {
    "gn:admin1_code":"16.0",
    "gn:asciiname":"Banzhai Xincun",
    "gn:country_code":"CN",
    "gn:dem":213,
    "gn:feature_class":"P",
    "gn:feature_code":"PPL",
    "gn:name":"Banzhai Xincun",
    "gn:population":0,
    "gn:timezone":"Asia/Shanghai",
    "iso:country":"CN",
    "name:zho_x_preferred":[
        "\u677f\u5be8\u65b0\u6751"
    ],
    "wof:name":"Banzhai Xincun",
    "wof:placetype":"locality"
},
  "geometry": {"coordinates":[109.515,24.7352],"type":"Point"}
}