{
  "type": "Feature",
  "properties": {
    "gn:admin1_code":"10.0",
    "gn:asciiname":"Dongfuliu",
    "gn:country_code":"CN",
    "gn:dem":121,
    "gn:feature_class":"P",
    "gn:feature_code":"PPL",
    "gn:name":"Dongfuliu",
    "gn:population":0,
    "gn:timezone":"Asia/Shanghai",
    "iso:country":"CN",
    "name:und_x_variant":[
        "\u4e1c\u4f0f\u6d41"
    ],
    "wof:name":"Dongfuliu",
    "wof:placetype":"locality"
},
  "geometry": {"coordinates":[114.45205,38.39468],"type":"Point"}
}