{
  "type": "Feature",
  "properties": {
    "gn:admin1_code":"12.0",
    "gn:asciiname":"Gejing",
    "gn:country_code":"CN",
    "gn:dem":1197,
    "gn:feature_class":"P",
    "gn:feature_code":"PPL",
    "gn:name":"Gejing",
    "gn:population":0,
    "gn:timezone":"Asia/Shanghai",
    "iso:country":"CN",
    "name:zho_x_preferred":[
        "\u5404\u4e95"
    ],
    "wof:name":"Gejing",
    "wof:placetype":"locality"
},
  "geometry": {"coordinates":[110.56894,30.39421],"type":"Point"}
}