{
  "type": "Feature",
  "properties": {
    "gn:admin1_code":"05",
    "gn:asciiname":"Xiaosiping",
    "gn:cc2":"CN",
    "gn:country_code":"CN",
    "gn:dem":415,
    "gn:feature_class":"P",
    "gn:feature_code":"PPL",
    "gn:name":"Xiaosiping",
    "gn:population":0,
    "gn:timezone":"Asia/Shanghai",
    "iso:country":"CN",
    "name:und_x_variant":[
        "Hsiao-ssu-p\u2019ing",
        "Xiaosiping",
        "Ssu-p\u2019ing-chieh",
        "Siping"
    ],
    "wof:name":"Xiaosiping",
    "wof:placetype":"locality"
},
  "geometry": {"coordinates":[125.17139,42.53222],"type":"Point"}
}