{
  "type": "Feature",
  "properties": {
    "gn:admin1_code":"32.0",
    "gn:asciiname":"Tianyuan",
    "gn:country_code":"CN",
    "gn:dem":337,
    "gn:feature_class":"P",
    "gn:feature_code":"PPL",
    "gn:name":"Tianyuan",
    "gn:population":0,
    "gn:timezone":"Asia/Shanghai",
    "iso:country":"CN",
    "name:deu_x_preferred":[
        "Tianyuan"
    ],
    "name:fra_x_preferred":[
        "Tianyuan"
    ],
    "name:zho_x_preferred":[
        "\u5929\u5143"
    ],
    "wof:name":"Tianyuan",
    "wof:placetype":"locality"
},
  "geometry": {"coordinates":[104.77200000000001,29.3865],"type":"Point"}
}