{
  "type": "Feature",
  "properties": {
    "gn:admin1_code":"31",
    "gn:asciiname":"Changtu",
    "gn:country_code":"CN",
    "gn:dem":27,
    "gn:feature_class":"P",
    "gn:feature_code":"PPL",
    "gn:name":"Changtu",
    "gn:population":0,
    "gn:timezone":"Asia/Shanghai",
    "iso:country":"CN",
    "name:und_x_variant":[
        "\u660c\u56fe"
    ],
    "wof:name":"Changtu",
    "wof:placetype":"locality"
},
  "geometry": {"coordinates":[110.92361,19.78889],"type":"Point"}
}