{
  "type": "Feature",
  "properties": {
    "gn:admin1_code":"3.0",
    "gn:asciiname":"Chuanxing",
    "gn:country_code":"CN",
    "gn:dem":148,
    "gn:feature_class":"P",
    "gn:feature_code":"PPL",
    "gn:name":"Chuanxing",
    "gn:population":0,
    "gn:timezone":"Asia/Shanghai",
    "iso:country":"CN",
    "name:und_x_variant":[
        "\u8239\u5f62"
    ],
    "wof:name":"Chuanxing",
    "wof:placetype":"locality"
},
  "geometry": {"coordinates":[115.40163,26.87543],"type":"Point"}
}