{
  "type": "Feature",
  "properties": {
    "gn:admin1_code":"2.0",
    "gn:asciiname":"Xiashibu",
    "gn:country_code":"CN",
    "gn:dem":93,
    "gn:feature_class":"P",
    "gn:feature_code":"PPL",
    "gn:name":"Xiashibu",
    "gn:population":0,
    "gn:timezone":"Asia/Shanghai",
    "iso:country":"CN",
    "name:zho_x_preferred":[
        "\u4e0b\u77f3\u57e0"
    ],
    "wof:name":"Xiashibu",
    "wof:placetype":"locality"
},
  "geometry": {"coordinates":[118.90093,28.84306],"type":"Point"}
}