{
  "type": "Feature",
  "properties": {
    "gn:admin1_code":"18",
    "gn:asciiname":"Yong'anzhuang",
    "gn:country_code":"CN",
    "gn:dem":903,
    "gn:feature_class":"P",
    "gn:feature_code":"PPL",
    "gn:name":"Yong\u2019anzhuang",
    "gn:population":0,
    "gn:timezone":"Asia/Shanghai",
    "iso:country":"CN",
    "name:und_x_variant":[
        "Yong\u2019anzhuang"
    ],
    "name:zho_x_preferred":[
        "\u6c38\u5b89\u5e84"
    ],
    "wof:name":"Yong'anzhuang",
    "wof:placetype":"locality"
},
  "geometry": {"coordinates":[106.93600000000001,27.9514],"type":"Point"}
}