{
  "type": "Feature",
  "properties": {
    "gn:admin1_code":"30",
    "gn:asciiname":"Xinancun",
    "gn:country_code":"CN",
    "gn:dem":33,
    "gn:feature_class":"P",
    "gn:feature_code":"PPL",
    "gn:name":"Xinancun",
    "gn:population":0,
    "gn:timezone":"Asia/Shanghai",
    "iso:country":"CN",
    "name:zho_x_preferred":[
        "\u65b0\u5b89\u6751"
    ],
    "wof:name":"Xinancun",
    "wof:placetype":"locality"
},
  "geometry": {"coordinates":[116.18407999999999,23.78338],"type":"Point"}
}