{
  "type": "Feature",
  "properties": {
    "gn:admin1_code":"15.0",
    "gn:asciiname":"Xiasunjiamo",
    "gn:country_code":"CN",
    "gn:dem":2674,
    "gn:feature_class":"P",
    "gn:feature_code":"PPL",
    "gn:name":"Xiasunjiamo",
    "gn:population":0,
    "gn:timezone":"Asia/Shanghai",
    "iso:country":"CN",
    "name:und_x_variant":[
        "\u4e0b\u5b59\u5bb6\u78e8"
    ],
    "wof:name":"Xiasunjiamo",
    "wof:placetype":"locality"
},
  "geometry": {"coordinates":[103.47109,34.64009],"type":"Point"}
}