{
  "type": "Feature",
  "properties": {
    "gn:admin1_code":"32.0",
    "gn:asciiname":"Menggesi",
    "gn:country_code":"CN",
    "gn:dem":4221,
    "gn:feature_class":"P",
    "gn:feature_code":"PPL",
    "gn:name":"Menggesi",
    "gn:population":0,
    "gn:timezone":"Asia/Shanghai",
    "iso:country":"CN",
    "name:zho_x_preferred":[
        "\u8499\u683c\u5bfa"
    ],
    "wof:name":"Menggesi",
    "wof:placetype":"locality"
},
  "geometry": {"coordinates":[98.23779999999999,32.9459],"type":"Point"}
}