{
  "type": "Feature",
  "properties": {
    "gn:admin1_code":"32.0",
    "gn:asciiname":"Jiangdehuo",
    "gn:country_code":"CN",
    "gn:dem":2644,
    "gn:feature_class":"P",
    "gn:feature_code":"PPL",
    "gn:name":"Jiangdehuo",
    "gn:population":0,
    "gn:timezone":"Asia/Shanghai",
    "iso:country":"CN",
    "name:zho_x_preferred":[
        "\u59dc\u5fb7\u970d"
    ],
    "wof:name":"Jiangdehuo",
    "wof:placetype":"locality"
},
  "geometry": {"coordinates":[101.149,29.4739],"type":"Point"}
}