{
  "type": "Feature",
  "properties": {
    "gn:admin1_code":"4.0",
    "gn:asciiname":"Qianluloucun",
    "gn:country_code":"CN",
    "gn:dem":37,
    "gn:feature_class":"P",
    "gn:feature_code":"PPL",
    "gn:name":"Qianluloucun",
    "gn:population":0,
    "gn:timezone":"Asia/Shanghai",
    "iso:country":"CN",
    "name:zho_x_preferred":[
        "\u524d\u9e7f\u697c\u6751"
    ],
    "wof:name":"Qianluloucun",
    "wof:placetype":"locality"
},
  "geometry": {"coordinates":[117.03131,34.40729],"type":"Point"}
}