{
  "type": "Feature",
  "properties": {
    "gn:admin1_code":"8.0",
    "gn:asciiname":"Longhucun",
    "gn:country_code":"CN",
    "gn:dem":214,
    "gn:feature_class":"P",
    "gn:feature_code":"PPL",
    "gn:name":"Longhucun",
    "gn:population":0,
    "gn:timezone":"Asia/Shanghai",
    "iso:country":"CN",
    "name:zho_x_preferred":[
        "\u9f99\u6e56\u6751"
    ],
    "wof:name":"Longhucun",
    "wof:placetype":"locality"
},
  "geometry": {"coordinates":[131.26651000000001,45.8211],"type":"Point"}
}