{
  "type": "Feature",
  "properties": {
    "gn:admin1_code":"31.0",
    "gn:asciiname":"Diaonancun Nongchang",
    "gn:country_code":"CN",
    "gn:dem":106,
    "gn:feature_class":"P",
    "gn:feature_code":"PPLF",
    "gn:name":"Diaonancun Nongchang",
    "gn:population":0,
    "gn:timezone":"Asia/Shanghai",
    "iso:country":"CN",
    "name:zho_x_preferred":[
        "\u8c03\u5357\u6751\u519c\u573a"
    ],
    "wof:name":"Diaonancun Nongchang",
    "wof:placetype":"locality"
},
  "geometry": {"coordinates":[109.37269000000001,19.49108],"type":"Point"}
}