{
  "type": "Feature",
  "properties": {
    "gn:admin1_code":"26.0",
    "gn:asciiname":"Lijia Wuchang",
    "gn:country_code":"CN",
    "gn:dem":593,
    "gn:feature_class":"P",
    "gn:feature_code":"PPL",
    "gn:name":"Lijia Wuchang",
    "gn:population":0,
    "gn:timezone":"Asia/Shanghai",
    "iso:country":"CN",
    "name:zho_x_preferred":[
        "\u674e\u5bb6\u5c4b\u573a"
    ],
    "wof:name":"Lijia Wuchang",
    "wof:placetype":"locality"
},
  "geometry": {"coordinates":[110.91457,33.34936],"type":"Point"}
}