{
  "type": "Feature",
  "properties": {
    "gn:admin1_code":"1.0",
    "gn:asciiname":"Chenjiabucun",
    "gn:country_code":"CN",
    "gn:dem":28,
    "gn:feature_class":"P",
    "gn:feature_code":"PPL",
    "gn:name":"Chenjiabucun",
    "gn:population":0,
    "gn:timezone":"Asia/Shanghai",
    "iso:country":"CN",
    "name:und_x_variant":[
        "Chenjiabu"
    ],
    "name:zho_x_preferred":[
        "\u9648\u5bb6\u57e0\u6751"
    ],
    "wof:name":"Chenjiabucun",
    "wof:placetype":"locality"
},
  "geometry": {"coordinates":[116.30423999999999,32.37090999999999],"type":"Point"}
}