{
  "type": "Feature",
  "properties": {
    "gn:admin1_code":"18",
    "gn:asciiname":"Muliangping",
    "gn:country_code":"CN",
    "gn:dem":907,
    "gn:feature_class":"P",
    "gn:feature_code":"PPL",
    "gn:name":"Muliangping",
    "gn:population":0,
    "gn:timezone":"Asia/Shanghai",
    "iso:country":"CN",
    "name:zho_x_preferred":[
        "\u6728\u6881\u576a"
    ],
    "wof:name":"Muliangping",
    "wof:placetype":"locality"
},
  "geometry": {"coordinates":[107.84699999999999,28.4536],"type":"Point"}
}