{
  "type": "Feature",
  "properties": {
    "gn:admin1_code":"19.0",
    "gn:asciiname":"Yushu",
    "gn:country_code":"CN",
    "gn:dem":47,
    "gn:feature_class":"P",
    "gn:feature_code":"PPL",
    "gn:name":"Yushu",
    "gn:population":0,
    "gn:timezone":"Asia/Shanghai",
    "iso:country":"CN",
    "name:ceb_x_preferred":[
        "Yushu"
    ],
    "name:deu_x_preferred":[
        "Yushu"
    ],
    "name:fra_x_preferred":[
        "Yushu"
    ],
    "name:ita_x_preferred":[
        "Yushu"
    ],
    "name:kor_x_preferred":[
        "\uc704\uc218\uc2dc"
    ],
    "name:mlg_x_preferred":[
        "Yushu"
    ],
    "name:nld_x_preferred":[
        "Yushu"
    ],
    "name:nor_x_preferred":[
        "Yushu"
    ],
    "name:pol_x_preferred":[
        "Yushu"
    ],
    "name:rus_x_preferred":[
        "\u042e\u0439\u0448\u0443"
    ],
    "name:zho_x_preferred":[
        "Yushu"
    ],
    "name:zho_x_variant":[
        "\u6986\u6811"
    ],
    "wof:name":"Yushu",
    "wof:placetype":"locality"
},
  "geometry": {"coordinates":[122.7989,40.82406],"type":"Point"}
}