{
  "type": "Feature",
  "properties": {
    "gn:admin1_code":"15.0",
    "gn:asciiname":"Lagagou",
    "gn:country_code":"CN",
    "gn:dem":2026,
    "gn:feature_class":"P",
    "gn:feature_code":"PPL",
    "gn:name":"Lagagou",
    "gn:population":0,
    "gn:timezone":"Asia/Shanghai",
    "iso:country":"CN",
    "name:und_x_variant":[
        "\u62c9\u5c15\u6c9f"
    ],
    "name:zho_x_preferred":[
        "\u62c9\u5c15\u6c9f"
    ],
    "wof:name":"Lagagou",
    "wof:placetype":"locality"
},
  "geometry": {"coordinates":[104.08812,33.86033],"type":"Point"}
}