{
  "type": "Feature",
  "properties": {
    "gn:admin1_code":"12.0",
    "gn:asciiname":"Zheshulin",
    "gn:country_code":"CN",
    "gn:dem":87,
    "gn:feature_class":"P",
    "gn:feature_code":"PPL",
    "gn:name":"Zheshulin",
    "gn:population":0,
    "gn:timezone":"Asia/Shanghai",
    "iso:country":"CN",
    "name:zho_x_preferred":[
        "\u67d8\u6811\u6797"
    ],
    "wof:name":"Zheshulin",
    "wof:placetype":"locality"
},
  "geometry": {"coordinates":[112.33058,31.35613],"type":"Point"}
}