{
  "type": "Feature",
  "properties": {
    "gn:admin1_code":"19.0",
    "gn:asciiname":"Dalinjiawobu",
    "gn:country_code":"CN",
    "gn:dem":214,
    "gn:feature_class":"P",
    "gn:feature_code":"PPL",
    "gn:name":"Dalinjiawobu",
    "gn:population":0,
    "gn:timezone":"Asia/Shanghai",
    "iso:country":"CN",
    "name:zho_x_preferred":[
        "\u5927\u6797\u5bb6\u7a9d\u5821"
    ],
    "wof:name":"Dalinjiawobu",
    "wof:placetype":"locality"
},
  "geometry": {"coordinates":[122.011,42.6716],"type":"Point"}
}