{
  "type": "Feature",
  "properties": {
    "gn:admin1_code":"4.0",
    "gn:asciiname":"Huangpu",
    "gn:country_code":"CN",
    "gn:dem":4,
    "gn:feature_class":"P",
    "gn:feature_code":"PPL",
    "gn:name":"Huangpu",
    "gn:population":0,
    "gn:timezone":"Asia/Shanghai",
    "iso:country":"CN",
    "name:ceb_x_preferred":[
        "Huangpu"
    ],
    "name:deu_x_preferred":[
        "Huangpu"
    ],
    "name:eus_x_preferred":[
        "Huangpu"
    ],
    "name:fra_x_preferred":[
        "Huangpu"
    ],
    "name:kor_x_preferred":[
        "\ud669\ud478\uad6c"
    ],
    "name:nor_x_preferred":[
        "Huangpu"
    ],
    "name:pol_x_preferred":[
        "Huangpu"
    ],
    "name:ron_x_preferred":[
        "Huangpu"
    ],
    "name:swe_x_preferred":[
        "Huangpu"
    ],
    "name:vie_x_preferred":[
        "Ho\u00e0ng Ph\u1ed1"
    ],
    "name:zho_x_preferred":[
        "\u9ec4\u666e"
    ],
    "wof:name":"Huangpu",
    "wof:placetype":"locality"
},
  "geometry": {"coordinates":[120.35092,32.01847],"type":"Point"}
}