{
  "type": "Feature",
  "properties": {
    "gn:admin1_code":"12.0",
    "gn:asciiname":"Yingzhuashan",
    "gn:country_code":"CN",
    "gn:dem":197,
    "gn:feature_class":"P",
    "gn:feature_code":"PPL",
    "gn:name":"Yingzhuashan",
    "gn:population":0,
    "gn:timezone":"Asia/Shanghai",
    "iso:country":"CN",
    "name:zho_x_preferred":[
        "\u9e70\u722a\u5c71"
    ],
    "wof:name":"Yingzhuashan",
    "wof:placetype":"locality"
},
  "geometry": {"coordinates":[111.91797,31.5383],"type":"Point"}
}