{
  "type": "Feature",
  "properties": {
    "gn:admin1_code":"2.0",
    "gn:asciiname":"Loudi",
    "gn:country_code":"CN",
    "gn:dem":73,
    "gn:feature_class":"P",
    "gn:feature_code":"PPL",
    "gn:name":"Loudi",
    "gn:population":0,
    "gn:timezone":"Asia/Shanghai",
    "iso:country":"CN",
    "name:ara_x_preferred":[
        "\u0644\u0648\u062f\u0649"
    ],
    "name:cdo_x_preferred":[
        "L\u00e8u-d\u012b"
    ],
    "name:ces_x_preferred":[
        "Lou-ti"
    ],
    "name:dan_x_preferred":[
        "Loudi"
    ],
    "name:deu_x_preferred":[
        "Loudi"
    ],
    "name:eus_x_preferred":[
        "Loudi"
    ],
    "name:fas_x_preferred":[
        "\u0644\u0648\u0627\u062f\u06cc"
    ],
    "name:fin_x_preferred":[
        "Loudi"
    ],
    "name:fra_x_preferred":[
        "Loudi"
    ],
    "name:ita_x_preferred":[
        "Loudi"
    ],
    "name:jpn_x_preferred":[
        "\u5a41\u5e95\u5e02"
    ],
    "name:kik_x_preferred":[
        "Loudi"
    ],
    "name:kor_x_preferred":[
        "\ub904\ub514\uc2dc"
    ],
    "name:ltz_x_preferred":[
        "Loudi"
    ],
    "name:mlg_x_preferred":[
        "Loudi"
    ],
    "name:nld_x_preferred":[
        "Loudi"
    ],
    "name:nno_x_preferred":[
        "Loudi"
    ],
    "name:nor_x_preferred":[
        "Loudi"
    ],
    "name:pam_x_preferred":[
        "Loudi"
    ],
    "name:pol_x_preferred":[
        "Loudi"
    ],
    "name:por_x_preferred":[
        "Loudi"
    ],
    "name:rus_x_preferred":[
        "\u041b\u043e\u0443\u0434\u0438"
    ],
    "name:spa_x_preferred":[
        "Loudi"
    ],
    "name:swe_x_preferred":[
        "Loudi"
    ],
    "name:tur_x_preferred":[
        "Loudi"
    ],
    "name:urd_x_preferred":[
        "\u0644\u0624\u062f\u06cc"
    ],
    "name:vie_x_preferred":[
        "L\u00e2u \u0110\u1ec3"
    ],
    "name:war_x_preferred":[
        "Loudi"
    ],
    "name:zho_x_preferred":[
        "\u697c\u5e95"
    ],
    "name:zho_x_variant":[
        "\u5a04\u5e95\u5e02"
    ],
    "wof:name":"Loudi",
    "wof:placetype":"locality"
},
  "geometry": {"coordinates":[121.98803999999998,29.2789],"type":"Point"}
}