{
  "type": "Feature",
  "properties": {
    "gn:admin1_code":"3.0",
    "gn:asciiname":"Longbei",
    "gn:country_code":"CN",
    "gn:dem":128,
    "gn:feature_class":"P",
    "gn:feature_code":"PPL",
    "gn:name":"Longbei",
    "gn:population":0,
    "gn:timezone":"Asia/Shanghai",
    "iso:country":"CN",
    "name:und_x_variant":[
        "\u9f99\u9642"
    ],
    "wof:name":"Longbei",
    "wof:placetype":"locality"
},
  "geometry": {"coordinates":[114.09726000000001,27.67457000000001],"type":"Point"}
}