{
  "type": "Feature",
  "properties": {
    "gn:admin1_code":"02",
    "gn:asciiname":"Zhuangyuan'aocun",
    "gn:country_code":"CN",
    "gn:dem":32,
    "gn:feature_class":"P",
    "gn:feature_code":"PPL",
    "gn:name":"Zhuangyuan\u2019aocun",
    "gn:population":0,
    "gn:timezone":"Asia/Shanghai",
    "iso:country":"CN",
    "name:und_x_variant":[
        "\u72b6\u5143\u5c99",
        "Zhuangyuan\u2019aocun"
    ],
    "name:zho_x_preferred":[
        "Zhuangyuan\u2019ao"
    ],
    "name:zho_x_variant":[
        "\u72b6\u5143\u5c99",
        "\u72b6\u5143\u5c99\u6751"
    ],
    "wof:name":"Zhuangyuan'aocun",
    "wof:placetype":"locality"
},
  "geometry": {"coordinates":[121.28219,29.71419],"type":"Point"}
}