{
  "type": "Feature",
  "properties": {
    "gn:admin1_code":"12.0",
    "gn:asciiname":"Shenjiawan",
    "gn:country_code":"CN",
    "gn:dem":141,
    "gn:feature_class":"P",
    "gn:feature_code":"PPL",
    "gn:name":"Shenjiawan",
    "gn:population":0,
    "gn:timezone":"Asia/Shanghai",
    "iso:country":"CN",
    "name:und_x_variant":[
        "\u6c88\u5bb6\u5846"
    ],
    "wof:name":"Shenjiawan",
    "wof:placetype":"locality"
},
  "geometry": {"coordinates":[115.47761,30.65216],"type":"Point"}
}