{
  "type": "Feature",
  "properties": {
    "gn:admin1_code":"26.0",
    "gn:asciiname":"Haobasi",
    "gn:country_code":"CN",
    "gn:dem":1326,
    "gn:feature_class":"P",
    "gn:feature_code":"PPL",
    "gn:name":"Haobasi",
    "gn:population":0,
    "gn:timezone":"Asia/Shanghai",
    "iso:country":"CN",
    "name:zho_x_preferred":[
        "\u84bf\u5df4\u5bfa"
    ],
    "wof:name":"Haobasi",
    "wof:placetype":"locality"
},
  "geometry": {"coordinates":[108.79523,35.81924],"type":"Point"}
}