{
  "type": "Feature",
  "properties": {
    "gn:admin1_code":"19.0",
    "gn:asciiname":"Lishugou",
    "gn:country_code":"CN",
    "gn:dem":177,
    "gn:feature_class":"P",
    "gn:feature_code":"PPL",
    "gn:name":"Lishugou",
    "gn:population":0,
    "gn:timezone":"Asia/Shanghai",
    "iso:country":"CN",
    "name:zho_x_preferred":[
        "\u68a8\u6811\u6c9f"
    ],
    "wof:name":"Lishugou",
    "wof:placetype":"locality"
},
  "geometry": {"coordinates":[120.41200000000001,40.7948],"type":"Point"}
}