{
  "type": "Feature",
  "properties": {
    "gn:admin1_code":"2",
    "gn:asciiname":"Juetang",
    "gn:country_code":"CN",
    "gn:dem":78,
    "gn:feature_class":"P",
    "gn:feature_code":"PPL",
    "gn:name":"Juetang",
    "gn:population":0,
    "gn:timezone":"Asia/Shanghai",
    "iso:country":"CN",
    "name:zho_x_preferred":[
        "\u73cf\u5858"
    ],
    "wof:name":"Juetang",
    "wof:placetype":"locality"
},
  "geometry": {"coordinates":[119.178,29.21581],"type":"Point"}
}