{
  "type": "Feature",
  "properties": {
    "gn:admin1_code":"9.0",
    "gn:asciiname":"Maqiying",
    "gn:country_code":"CN",
    "gn:dem":116,
    "gn:feature_class":"P",
    "gn:feature_code":"PPL",
    "gn:name":"Maqiying",
    "gn:population":0,
    "gn:timezone":"Asia/Shanghai",
    "iso:country":"CN",
    "name:zho_x_preferred":[
        "\u9a6c\u65d7\u8425"
    ],
    "wof:name":"Maqiying",
    "wof:placetype":"locality"
},
  "geometry": {"coordinates":[113.10921,33.83682],"type":"Point"}
}