{
  "type": "Feature",
  "properties": {
    "gn:admin1_code":"07",
    "gn:asciiname":"Dake",
    "gn:country_code":"CN",
    "gn:dem":319,
    "gn:feature_class":"P",
    "gn:feature_code":"PPL",
    "gn:name":"Dake",
    "gn:population":0,
    "gn:timezone":"Asia/Shanghai",
    "iso:country":"CN",
    "name:deu_x_preferred":[
        "Dake"
    ],
    "name:zho_x_preferred":[
        "\u5927\u7aa0"
    ],
    "name:zho_x_variant":[
        "\u5927\u79d1"
    ],
    "wof:name":"Dake",
    "wof:placetype":"locality"
},
  "geometry": {"coordinates":[117.18731,25.79864],"type":"Point"}
}