{
  "type": "Feature",
  "properties": {
    "gn:admin1_code":"9",
    "gn:asciiname":"Houzhaolou",
    "gn:country_code":"CN",
    "gn:dem":46,
    "gn:feature_class":"P",
    "gn:feature_code":"PPL",
    "gn:name":"Houzhaolou",
    "gn:population":0,
    "gn:timezone":"Asia/Shanghai",
    "iso:country":"CN",
    "name:zho_x_preferred":[
        "\u540e\u8d75\u697c"
    ],
    "wof:name":"Houzhaolou",
    "wof:placetype":"locality"
},
  "geometry": {"coordinates":[115.709,34.1552],"type":"Point"}
}