{
  "type": "Feature",
  "properties": {
    "gn:admin1_code":"4.0",
    "gn:asciiname":"Caohong",
    "gn:country_code":"CN",
    "gn:dem":5,
    "gn:feature_class":"P",
    "gn:feature_code":"PPL",
    "gn:name":"Caohong",
    "gn:population":0,
    "gn:timezone":"Asia/Shanghai",
    "iso:country":"CN",
    "name:zho_x_preferred":[
        "\u6f15\u7ea2"
    ],
    "wof:name":"Caohong",
    "wof:placetype":"locality"
},
  "geometry": {"coordinates":[119.78164,32.19073],"type":"Point"}
}