{
  "type": "Feature",
  "properties": {
    "gn:admin1_code":"32.0",
    "gn:asciiname":"Baiyansi",
    "gn:country_code":"CN",
    "gn:dem":323,
    "gn:feature_class":"P",
    "gn:feature_code":"PPL",
    "gn:name":"Baiyansi",
    "gn:population":0,
    "gn:timezone":"Asia/Shanghai",
    "iso:country":"CN",
    "name:zho_x_preferred":[
        "\u767d\u5ca9\u5bfa"
    ],
    "wof:name":"Baiyansi",
    "wof:placetype":"locality"
},
  "geometry": {"coordinates":[104.58946,28.79994000000001],"type":"Point"}
}