{
  "type": "Feature",
  "properties": {
    "gn:admin1_code":"12.0",
    "gn:asciiname":"Luanshijiao",
    "gn:country_code":"CN",
    "gn:dem":857,
    "gn:feature_class":"P",
    "gn:feature_code":"PPL",
    "gn:name":"Luanshijiao",
    "gn:population":0,
    "gn:timezone":"Asia/Shanghai",
    "iso:country":"CN",
    "name:zho_x_preferred":[
        "\u4e71\u77f3\u7a96"
    ],
    "wof:name":"Luanshijiao",
    "wof:placetype":"locality"
},
  "geometry": {"coordinates":[108.89767999999999,29.7208],"type":"Point"}
}