{
  "type": "Feature",
  "properties": {
    "gn:admin1_code":"1.0",
    "gn:asciiname":"Maoshicun",
    "gn:country_code":"CN",
    "gn:dem":191,
    "gn:feature_class":"P",
    "gn:feature_code":"PPL",
    "gn:name":"Maoshicun",
    "gn:population":0,
    "gn:timezone":"Asia/Shanghai",
    "iso:country":"CN",
    "name:zho_x_preferred":[
        "\u732b\u77f3\u6751"
    ],
    "wof:name":"Maoshicun",
    "wof:placetype":"locality"
},
  "geometry": {"coordinates":[116.17055999999999,30.61639000000001],"type":"Point"}
}