{
  "type": "Feature",
  "properties": {
    "gn:admin1_code":"32.0",
    "gn:asciiname":"Huahongshu",
    "gn:country_code":"CN",
    "gn:dem":2257,
    "gn:feature_class":"P",
    "gn:feature_code":"PPL",
    "gn:name":"Huahongshu",
    "gn:population":0,
    "gn:timezone":"Asia/Shanghai",
    "iso:country":"CN",
    "name:zho_x_preferred":[
        "\u82b1\u7ea2\u6811"
    ],
    "wof:name":"Huahongshu",
    "wof:placetype":"locality"
},
  "geometry": {"coordinates":[101.821,27.6825],"type":"Point"}
}