{
  "type": "Feature",
  "properties": {
    "gn:admin1_code":"14.0",
    "gn:asciiname":"Quxam",
    "gn:country_code":"CN",
    "gn:dem":3339,
    "gn:feature_class":"P",
    "gn:feature_code":"PPL",
    "gn:name":"Quxam",
    "gn:population":0,
    "gn:timezone":"Asia/Urumqi",
    "iso:country":"CN",
    "name:bod_x_preferred":[
        "Quxam"
    ],
    "name:zho_x_preferred":[
        "Quxiang"
    ],
    "name:zho_x_variant":[
        "\u66f2\u9999",
        "\u66f2\u4e61"
    ],
    "wof:name":"Quxam",
    "wof:placetype":"locality"
},
  "geometry": {"coordinates":[85.99600000000002,28.0795],"type":"Point"}
}