{
  "type": "Feature",
  "properties": {
    "gn:admin1_code":"0.0",
    "gn:asciiname":"Hulu",
    "gn:country_code":"CN",
    "gn:dem":455,
    "gn:feature_class":"P",
    "gn:feature_code":"PPL",
    "gn:name":"Hulu",
    "gn:population":0,
    "gn:timezone":"Asia/Shanghai",
    "iso:country":"CN",
    "name:ara_x_preferred":[
        "\u0647\u0648\u0644\u0648"
    ],
    "name:ast_x_preferred":[
        "Hulu"
    ],
    "name:azb_x_preferred":[
        "\u0647\u0648\u0644\u0648"
    ],
    "name:cat_x_preferred":[
        "Hulu"
    ],
    "name:cym_x_preferred":[
        "Hulu"
    ],
    "name:deu_x_preferred":[
        "Hulu"
    ],
    "name:ell_x_preferred":[
        "Hulu"
    ],
    "name:fas_x_preferred":[
        "\u0647\u0648\u0644\u0648"
    ],
    "name:fin_x_preferred":[
        "Hulu"
    ],
    "name:fra_x_preferred":[
        "Hulu"
    ],
    "name:heb_x_preferred":[
        "\u05d4\u05d5\u05dc\u05d5"
    ],
    "name:hun_x_preferred":[
        "Hulu"
    ],
    "name:ind_x_preferred":[
        "Hulu"
    ],
    "name:ita_x_preferred":[
        "Hulu"
    ],
    "name:jpn_x_preferred":[
        "Hulu"
    ],
    "name:lit_x_preferred":[
        "Hulu"
    ],
    "name:msa_x_preferred":[
        "Hulu"
    ],
    "name:nld_x_preferred":[
        "Hulu"
    ],
    "name:nor_x_preferred":[
        "Hulu"
    ],
    "name:por_x_preferred":[
        "Hulu"
    ],
    "name:rus_x_preferred":[
        "Hulu"
    ],
    "name:spa_x_preferred":[
        "Hulu"
    ],
    "name:srp_x_preferred":[
        "\u0425\u0443\u043b\u0443"
    ],
    "name:swe_x_preferred":[
        "Hulu"
    ],
    "name:tur_x_preferred":[
        "Hulu"
    ],
    "name:ukr_x_preferred":[
        "Hulu"
    ],
    "name:vie_x_preferred":[
        "Hulu"
    ],
    "name:zho_x_preferred":[
        "\u846b\u82a6"
    ],
    "name:zho_x_variant":[
        "Hulu"
    ],
    "wof:name":"Hulu",
    "wof:placetype":"locality"
},
  "geometry": {"coordinates":[103.59959000000001,29.3198],"type":"Point"}
}