{
  "type": "Feature",
  "properties": {
    "gn:admin1_code":"0.0",
    "gn:asciiname":"Hulu",
    "gn:country_code":"CN",
    "gn:dem":455,
    "gn:feature_class":"P",
    "gn:feature_code":"PPL",
    "gn:name":"Hulu",
    "gn:population":0,
    "gn:timezone":"Asia/Shanghai",
    "iso:country":"CN",
    "name:zho_x_preferred":[
        "\u846b\u82a6"
    ],
    "wof:name":"Hulu",
    "wof:placetype":"locality"
},
  "geometry": {"coordinates":[103.59959000000001,29.3198],"type":"Point"}
}