{
  "type": "Feature",
  "properties": {
    "gn:admin1_code":"32.0",
    "gn:asciiname":"Gujinggou",
    "gn:country_code":"CN",
    "gn:dem":489,
    "gn:feature_class":"P",
    "gn:feature_code":"PPL",
    "gn:name":"Gujinggou",
    "gn:population":0,
    "gn:timezone":"Asia/Shanghai",
    "iso:country":"CN",
    "name:zho_x_preferred":[
        "\u53e4\u4e95\u6c9f"
    ],
    "wof:name":"Gujinggou",
    "wof:placetype":"locality"
},
  "geometry": {"coordinates":[104.11194999999999,30.35599],"type":"Point"}
}