{
  "type": "Feature",
  "properties": {
    "gn:admin1_code":"3.0",
    "gn:asciiname":"Lukou",
    "gn:country_code":"CN",
    "gn:dem":196,
    "gn:feature_class":"P",
    "gn:feature_code":"PPLA4",
    "gn:name":"Lukou",
    "gn:population":0,
    "gn:timezone":"Asia/Shanghai",
    "iso:country":"CN",
    "name:deu_x_preferred":[
        "Lukou"
    ],
    "name:und_x_variant":[
        "\u8def\u53e3",
        "Lukou Xiang",
        "\u8def\u53e3\u4e61"
    ],
    "wof:name":"Lukou",
    "wof:placetype":"locality"
},
  "geometry": {"coordinates":[114.08846,29.08076],"type":"Point"}
}