{
  "type": "Feature",
  "properties": {
    "gn:admin1_code":"2.0",
    "gn:asciiname":"Xinmiaoqian",
    "gn:country_code":"CN",
    "gn:dem":13,
    "gn:feature_class":"P",
    "gn:feature_code":"PPL",
    "gn:name":"Xinmiaoqian",
    "gn:population":0,
    "gn:timezone":"Asia/Shanghai",
    "iso:country":"CN",
    "name:zho_x_preferred":[
        "\u65b0\u5e99\u524d"
    ],
    "wof:name":"Xinmiaoqian",
    "wof:placetype":"locality"
},
  "geometry": {"coordinates":[121.38493,28.73513],"type":"Point"}
}