{
  "type": "Feature",
  "properties": {
    "gn:admin1_code":"14.0",
    "gn:asciiname":"Tabuduo",
    "gn:country_code":"CN",
    "gn:dem":3680,
    "gn:feature_class":"P",
    "gn:feature_code":"PPL",
    "gn:name":"Tabuduo",
    "gn:population":0,
    "gn:timezone":"Asia/Urumqi",
    "iso:country":"CN",
    "name:zho_x_preferred":[
        "\u584c\u4e0d\u591a"
    ],
    "wof:name":"Tabuduo",
    "wof:placetype":"locality"
},
  "geometry": {"coordinates":[97.03818,31.62799],"type":"Point"}
}