{
  "type": "Feature",
  "properties": {
    "gn:admin1_code":"25",
    "gn:asciiname":"Liuzi",
    "gn:country_code":"CN",
    "gn:dem":190,
    "gn:feature_class":"P",
    "gn:feature_code":"PPL",
    "gn:name":"Liuzi",
    "gn:population":0,
    "gn:timezone":"Asia/Shanghai",
    "iso:country":"CN",
    "name:zho_x_preferred":[
        "\u67f3\u5b50"
    ],
    "wof:name":"Liuzi",
    "wof:placetype":"locality"
},
  "geometry": {"coordinates":[118.51600000000001,36.2584],"type":"Point"}
}