{
  "type": "Feature",
  "properties": {
    "gn:admin1_code":"11.0",
    "gn:asciiname":"Beijie",
    "gn:country_code":"CN",
    "gn:dem":656,
    "gn:feature_class":"P",
    "gn:feature_code":"PPL",
    "gn:name":"Beijie",
    "gn:population":0,
    "gn:timezone":"Asia/Shanghai",
    "iso:country":"CN",
    "name:zho_x_preferred":[
        "\u5317\u754c"
    ],
    "wof:name":"Beijie",
    "wof:placetype":"locality"
},
  "geometry": {"coordinates":[110.89645,29.58801],"type":"Point"}
}