{
  "type": "Feature",
  "properties": {
    "gn:admin1_code":"07",
    "gn:asciiname":"Dalian",
    "gn:country_code":"CN",
    "gn:dem":194,
    "gn:feature_class":"P",
    "gn:feature_code":"PPL",
    "gn:name":"Dalian",
    "gn:population":0,
    "gn:timezone":"Asia/Shanghai",
    "iso:country":"CN",
    "name:zho_x_preferred":[
        "\u5927\u70bc"
    ],
    "wof:name":"Dalian",
    "wof:placetype":"locality"
},
  "geometry": {"coordinates":[117.30164000000001,25.92033],"type":"Point"}
}