{
  "type": "Feature",
  "properties": {
    "gn:admin1_code":"11",
    "gn:asciiname":"Shenjiatang",
    "gn:country_code":"CN",
    "gn:dem":394,
    "gn:feature_class":"P",
    "gn:feature_code":"PPL",
    "gn:name":"Shenjiatang",
    "gn:population":0,
    "gn:timezone":"Asia/Shanghai",
    "iso:country":"CN",
    "wof:name":"Shenjiatang",
    "wof:placetype":"locality"
},
  "geometry": {"coordinates":[111.34972,27.45361],"type":"Point"}
}