{
  "type": "Feature",
  "properties": {
    "gn:admin1_code":"29.0",
    "gn:asciiname":"Yangwozi",
    "gn:country_code":"CN",
    "gn:dem":2387,
    "gn:feature_class":"P",
    "gn:feature_code":"PPL",
    "gn:name":"Yangwozi",
    "gn:population":0,
    "gn:timezone":"Asia/Shanghai",
    "iso:country":"CN",
    "name:zho_x_preferred":[
        "\u7f8a\u7a9d\u5b50"
    ],
    "wof:name":"Yangwozi",
    "wof:placetype":"locality"
},
  "geometry": {"coordinates":[100.51300000000001,26.1054],"type":"Point"}
}