{
  "type": "Feature",
  "properties": {
    "gn:admin1_code":"32.0",
    "gn:asciiname":"Damotan",
    "gn:country_code":"CN",
    "gn:dem":415,
    "gn:feature_class":"P",
    "gn:feature_code":"PPL",
    "gn:name":"Damotan",
    "gn:population":0,
    "gn:timezone":"Asia/Shanghai",
    "iso:country":"CN",
    "name:zho_x_preferred":[
        "\u5927\u78e8\u6ee9"
    ],
    "wof:name":"Damotan",
    "wof:placetype":"locality"
},
  "geometry": {"coordinates":[107.59885,30.89688],"type":"Point"}
}