{
  "type": "Feature",
  "properties": {
    "gn:admin1_code":"16.0",
    "gn:asciiname":"Weizhou",
    "gn:country_code":"CN",
    "gn:dem":72,
    "gn:feature_class":"P",
    "gn:feature_code":"PPL",
    "gn:name":"Weizhou",
    "gn:population":0,
    "gn:timezone":"Asia/Urumqi",
    "iso:country":"CN",
    "name:deu_x_preferred":[
        "Weizhou"
    ],
    "wof:name":"Weizhou",
    "wof:placetype":"locality"
},
  "geometry": {"coordinates":[109.11083000000001,21.02944],"type":"Point"}
}