{
  "type": "Feature",
  "properties": {
    "gn:admin1_code":"9.0",
    "gn:asciiname":"Jiushengying",
    "gn:country_code":"CN",
    "gn:dem":86,
    "gn:feature_class":"P",
    "gn:feature_code":"PPL",
    "gn:name":"Jiushengying",
    "gn:population":0,
    "gn:timezone":"Asia/Shanghai",
    "iso:country":"CN",
    "name:zho_x_preferred":[
        "\u4e5d\u5723\u8425"
    ],
    "wof:name":"Jiushengying",
    "wof:placetype":"locality"
},
  "geometry": {"coordinates":[113.73847000000001,35.44927],"type":"Point"}
}