{
  "type": "Feature",
  "properties": {
    "gn:admin1_code":"19.0",
    "gn:asciiname":"Xibeigou",
    "gn:country_code":"CN",
    "gn:dem":262,
    "gn:feature_class":"P",
    "gn:feature_code":"PPL",
    "gn:name":"Xibeigou",
    "gn:population":0,
    "gn:timezone":"Asia/Shanghai",
    "iso:country":"CN",
    "name:und_x_variant":[
        "\u897f\u5317\u6c9f"
    ],
    "wof:name":"Xibeigou",
    "wof:placetype":"locality"
},
  "geometry": {"coordinates":[122.47875999999999,40.27977],"type":"Point"}
}