{
  "type": "Feature",
  "properties": {
    "gn:admin1_code":"26.0",
    "gn:asciiname":"Luotuoxiang",
    "gn:country_code":"CN",
    "gn:dem":1120,
    "gn:feature_class":"P",
    "gn:feature_code":"PPL",
    "gn:name":"Luotuoxiang",
    "gn:population":0,
    "gn:timezone":"Asia/Shanghai",
    "iso:country":"CN",
    "name:zho_x_preferred":[
        "\u9a86\u9a7c\u9879"
    ],
    "wof:name":"Luotuoxiang",
    "wof:placetype":"locality"
},
  "geometry": {"coordinates":[110.22447,33.96926],"type":"Point"}
}