{
  "type": "Feature",
  "properties": {
    "gn:admin1_code":"25.0",
    "gn:asciiname":"Beixiaoping",
    "gn:country_code":"CN",
    "gn:dem":88,
    "gn:feature_class":"P",
    "gn:feature_code":"PPL",
    "gn:name":"Beixiaoping",
    "gn:population":0,
    "gn:timezone":"Asia/Shanghai",
    "iso:country":"CN",
    "name:zho_x_preferred":[
        "\u5317\u5c0f\u5e73"
    ],
    "wof:name":"Beixiaoping",
    "wof:placetype":"locality"
},
  "geometry": {"coordinates":[120.65403999999999,37.03635],"type":"Point"}
}