{
  "type": "Feature",
  "properties": {
    "gn:admin1_code":"3.0",
    "gn:asciiname":"Shipiling",
    "gn:country_code":"CN",
    "gn:dem":550,
    "gn:feature_class":"P",
    "gn:feature_code":"PPL",
    "gn:name":"Shipiling",
    "gn:population":0,
    "gn:timezone":"Asia/Shanghai",
    "iso:country":"CN",
    "name:zho_x_preferred":[
        "\u77f3\u76ae\u5cad"
    ],
    "wof:name":"Shipiling",
    "wof:placetype":"locality"
},
  "geometry": {"coordinates":[114.092,29.1155],"type":"Point"}
}