{
  "type": "Feature",
  "properties": {
    "gn:admin1_code":"1.0",
    "gn:asciiname":"Zhoudacun",
    "gn:country_code":"CN",
    "gn:dem":39,
    "gn:feature_class":"P",
    "gn:feature_code":"PPL",
    "gn:name":"Zhoudacun",
    "gn:population":0,
    "gn:timezone":"Asia/Shanghai",
    "iso:country":"CN",
    "name:zho_x_preferred":[
        "\u5468\u5927\u6751"
    ],
    "wof:name":"Zhoudacun",
    "wof:placetype":"locality"
},
  "geometry": {"coordinates":[115.75946999999999,33.69507],"type":"Point"}
}