{
  "type": "Feature",
  "properties": {
    "gn:admin1_code":"12.0",
    "gn:asciiname":"Siheping",
    "gn:country_code":"CN",
    "gn:dem":304,
    "gn:feature_class":"P",
    "gn:feature_code":"PPL",
    "gn:name":"Siheping",
    "gn:population":0,
    "gn:timezone":"Asia/Shanghai",
    "iso:country":"CN",
    "name:zho_x_preferred":[
        "\u6cd7\u6cb3\u576a"
    ],
    "wof:name":"Siheping",
    "wof:placetype":"locality"
},
  "geometry": {"coordinates":[110.11626,32.15082],"type":"Point"}
}