{
  "type": "Feature",
  "properties": {
    "gn:admin1_code":"14.0",
    "gn:asciiname":"Katong",
    "gn:country_code":"CN",
    "gn:dem":3953,
    "gn:feature_class":"P",
    "gn:feature_code":"PPL",
    "gn:name":"Katong",
    "gn:population":0,
    "gn:timezone":"Asia/Urumqi",
    "iso:country":"CN",
    "name:zho_x_preferred":[
        "\u5361\u901a"
    ],
    "wof:name":"Katong",
    "wof:placetype":"locality"
},
  "geometry": {"coordinates":[95.59662,31.44119],"type":"Point"}
}