{
  "type": "Feature",
  "properties": {
    "gn:admin1_code":"26.0",
    "gn:asciiname":"Wangmacun",
    "gn:country_code":"CN",
    "gn:dem":353,
    "gn:feature_class":"P",
    "gn:feature_code":"PPL",
    "gn:name":"Wangmacun",
    "gn:population":0,
    "gn:timezone":"Asia/Shanghai",
    "iso:country":"CN",
    "name:zho_x_preferred":[
        "\u738b\u9a6c\u6751"
    ],
    "wof:name":"Wangmacun",
    "wof:placetype":"locality"
},
  "geometry": {"coordinates":[109.88942,34.74166],"type":"Point"}
}