{
  "type": "Feature",
  "properties": {
    "gn:admin1_code":"1.0",
    "gn:asciiname":"Baijiadun",
    "gn:country_code":"CN",
    "gn:dem":12,
    "gn:feature_class":"P",
    "gn:feature_code":"PPL",
    "gn:name":"Baijiadun",
    "gn:population":0,
    "gn:timezone":"Asia/Shanghai",
    "iso:country":"CN",
    "name:zho_x_preferred":[
        "\u767e\u5bb6\u58a9"
    ],
    "wof:name":"Baijiadun",
    "wof:placetype":"locality"
},
  "geometry": {"coordinates":[119.10796999999999,32.66979],"type":"Point"}
}