{
  "type": "Feature",
  "properties": {
    "gn:admin1_code":"21.0",
    "gn:asciiname":"Shapozi",
    "gn:country_code":"CN",
    "gn:dem":1581,
    "gn:feature_class":"P",
    "gn:feature_code":"PPL",
    "gn:name":"Shapozi",
    "gn:population":0,
    "gn:timezone":"Asia/Shanghai",
    "iso:country":"CN",
    "name:zho_x_preferred":[
        "\u6c99\u5761\u5b50"
    ],
    "wof:name":"Shapozi",
    "wof:placetype":"locality"
},
  "geometry": {"coordinates":[106.976,37.127],"type":"Point"}
}