{
  "type": "Feature",
  "properties": {
    "gn:admin1_code":"32.0",
    "gn:asciiname":"Ruohashede",
    "gn:country_code":"CN",
    "gn:dem":1992,
    "gn:feature_class":"P",
    "gn:feature_code":"PPL",
    "gn:name":"Ruohashede",
    "gn:population":0,
    "gn:timezone":"Asia/Shanghai",
    "iso:country":"CN",
    "name:zho_x_preferred":[
        "\u82e5\u54c8\u793e\u5fb7"
    ],
    "wof:name":"Ruohashede",
    "wof:placetype":"locality"
},
  "geometry": {"coordinates":[103.20107,28.75114],"type":"Point"}
}