{
  "type": "Feature",
  "properties": {
    "gn:admin1_code":"30.0",
    "gn:asciiname":"Changmei",
    "gn:country_code":"CN",
    "gn:dem":21,
    "gn:feature_class":"P",
    "gn:feature_code":"PPL",
    "gn:name":"Changmei",
    "gn:population":0,
    "gn:timezone":"Asia/Shanghai",
    "iso:country":"CN",
    "name:zho_x_preferred":[
        "\u660c\u6885"
    ],
    "wof:name":"Changmei",
    "wof:placetype":"locality"
},
  "geometry": {"coordinates":[112.38008000000001,22.36628],"type":"Point"}
}