{
  "type": "Feature",
  "properties": {
    "gn:admin1_code":"15.0",
    "gn:asciiname":"Linjiawan",
    "gn:country_code":"CN",
    "gn:dem":2117,
    "gn:feature_class":"P",
    "gn:feature_code":"PPL",
    "gn:name":"Linjiawan",
    "gn:population":0,
    "gn:timezone":"Asia/Shanghai",
    "iso:country":"CN",
    "name:und_x_variant":[
        "\u853a\u5bb6\u6e7e"
    ],
    "wof:name":"Linjiawan",
    "wof:placetype":"locality"
},
  "geometry": {"coordinates":[104.56196,34.82060999999999],"type":"Point"}
}