{
  "type": "Feature",
  "properties": {
    "gn:admin1_code":"2.0",
    "gn:asciiname":"Xiayangtian",
    "gn:country_code":"CN",
    "gn:dem":77,
    "gn:feature_class":"P",
    "gn:feature_code":"PPL",
    "gn:name":"Xiayangtian",
    "gn:population":0,
    "gn:timezone":"Asia/Shanghai",
    "iso:country":"CN",
    "name:zho_x_preferred":[
        "\u4e0b\u79e7\u7530"
    ],
    "wof:name":"Xiayangtian",
    "wof:placetype":"locality"
},
  "geometry": {"coordinates":[120.90004999999999,29.15914],"type":"Point"}
}