{
  "type": "Feature",
  "properties": {
    "gn:admin1_code":"32.0",
    "gn:asciiname":"Shuigouli",
    "gn:country_code":"CN",
    "gn:dem":1319,
    "gn:feature_class":"P",
    "gn:feature_code":"PPL",
    "gn:name":"Shuigouli",
    "gn:population":0,
    "gn:timezone":"Asia/Shanghai",
    "iso:country":"CN",
    "name:zho_x_preferred":[
        "\u6c34\u6c9f\u91cc"
    ],
    "wof:name":"Shuigouli",
    "wof:placetype":"locality"
},
  "geometry": {"coordinates":[104.94,32.2667],"type":"Point"}
}