{
  "type": "Feature",
  "properties": {
    "gn:admin1_code":"19.0",
    "gn:asciiname":"Haoyan",
    "gn:country_code":"CN",
    "gn:dem":9,
    "gn:feature_class":"P",
    "gn:feature_code":"PPL",
    "gn:name":"Haoyan",
    "gn:population":0,
    "gn:timezone":"Asia/Shanghai",
    "iso:country":"CN",
    "name:und_x_variant":[
        "\u58d5\u6cbf"
    ],
    "name:zho_x_preferred":[
        "\u58d5\u6cbf"
    ],
    "wof:name":"Haoyan",
    "wof:placetype":"locality"
},
  "geometry": {"coordinates":[121.41509000000001,41.02862],"type":"Point"}
}