{
  "type": "Feature",
  "properties": {
    "gn:admin1_code":"11.0",
    "gn:asciiname":"Shamuping",
    "gn:country_code":"CN",
    "gn:dem":312,
    "gn:feature_class":"P",
    "gn:feature_code":"PPL",
    "gn:name":"Shamuping",
    "gn:population":0,
    "gn:timezone":"Asia/Shanghai",
    "iso:country":"CN",
    "name:zho_x_preferred":[
        "\u6749\u6728\u576a"
    ],
    "wof:name":"Shamuping",
    "wof:placetype":"locality"
},
  "geometry": {"coordinates":[111.06909,24.98784],"type":"Point"}
}