{
  "type": "Feature",
  "properties": {
    "gn:admin1_code":"25.0",
    "gn:asciiname":"Huanghai",
    "gn:country_code":"CN",
    "gn:dem":20,
    "gn:feature_class":"P",
    "gn:feature_code":"PPLA3",
    "gn:name":"Huanghai",
    "gn:population":0,
    "gn:timezone":"Asia/Shanghai",
    "iso:country":"CN",
    "name:und_x_variant":[
        "Huanghai Jiedao",
        "Laishan",
        "Laishan Qu"
    ],
    "name:zho_x_preferred":[
        "\u9ec4\u6d77"
    ],
    "name:zho_x_variant":[
        "\u9ec4\u6d77\u8857\u9053",
        "\u83b1\u5c71",
        "\u83b1\u5c71\u533a"
    ],
    "wof:name":"Huanghai",
    "wof:placetype":"locality"
},
  "geometry": {"coordinates":[121.44038,37.4887],"type":"Point"}
}