{
  "type": "Feature",
  "properties": {
    "gn:admin1_code":"12.0",
    "gn:asciiname":"Taihejie",
    "gn:country_code":"CN",
    "gn:dem":1416,
    "gn:feature_class":"P",
    "gn:feature_code":"PPL",
    "gn:name":"Taihejie",
    "gn:population":0,
    "gn:timezone":"Asia/Shanghai",
    "iso:country":"CN",
    "name:zho_x_preferred":[
        "\u592a\u548c\u8857"
    ],
    "wof:name":"Taihejie",
    "wof:placetype":"locality"
},
  "geometry": {"coordinates":[109.9032,30.7582],"type":"Point"}
}