{
  "type": "Feature",
  "properties": {
    "gn:admin1_code":"32.0",
    "gn:asciiname":"Beiyanhe",
    "gn:country_code":"CN",
    "gn:dem":1001,
    "gn:feature_class":"P",
    "gn:feature_code":"PPL",
    "gn:name":"Beiyanhe",
    "gn:population":0,
    "gn:timezone":"Asia/Shanghai",
    "iso:country":"CN",
    "name:zho_x_preferred":[
        "\u7891\u5ca9\u6cb3"
    ],
    "wof:name":"Beiyanhe",
    "wof:placetype":"locality"
},
  "geometry": {"coordinates":[107.75452,32.09735],"type":"Point"}
}