{
  "type": "Feature",
  "properties": {
    "gn:admin1_code":"4.0",
    "gn:asciiname":"Houluocun",
    "gn:country_code":"CN",
    "gn:dem":-1,
    "gn:feature_class":"P",
    "gn:feature_code":"PPL",
    "gn:name":"Houluocun",
    "gn:population":0,
    "gn:timezone":"Asia/Shanghai",
    "iso:country":"CN",
    "name:und_x_variant":[
        "\u540e\u7f57\u6751"
    ],
    "name:zho_x_preferred":[
        "\u540e\u7f57\u6751"
    ],
    "wof:name":"Houluocun",
    "wof:placetype":"locality"
},
  "geometry": {"coordinates":[120.56867,31.61498],"type":"Point"}
}