{
  "type": "Feature",
  "properties": {
    "gn:admin1_code":"29.0",
    "gn:asciiname":"Ludongjie",
    "gn:country_code":"CN",
    "gn:dem":1493,
    "gn:feature_class":"P",
    "gn:feature_code":"PPL",
    "gn:name":"Ludongjie",
    "gn:population":0,
    "gn:timezone":"Asia/Shanghai",
    "iso:country":"CN",
    "name:zho_x_preferred":[
        "\u8def\u4e1c\u8857"
    ],
    "wof:name":"Ludongjie",
    "wof:placetype":"locality"
},
  "geometry": {"coordinates":[100.923,24.1452],"type":"Point"}
}