{
  "type": "Feature",
  "properties": {
    "gn:admin1_code":"32.0",
    "gn:asciiname":"Tiquan",
    "gn:country_code":"CN",
    "gn:dem":576,
    "gn:feature_class":"P",
    "gn:feature_code":"PPL",
    "gn:name":"Tiquan",
    "gn:population":0,
    "gn:timezone":"Asia/Shanghai",
    "iso:country":"CN",
    "name:zho_x_preferred":[
        "\u4f53\u6cc9"
    ],
    "wof:name":"Tiquan",
    "wof:placetype":"locality"
},
  "geometry": {"coordinates":[103.494,30.2267],"type":"Point"}
}