{
  "type": "Feature",
  "properties": {
    "gn:admin1_code":"32.0",
    "gn:asciiname":"Zhao'ao",
    "gn:country_code":"CN",
    "gn:dem":474,
    "gn:feature_class":"P",
    "gn:feature_code":"PPL",
    "gn:name":"Zhao\u2019ao",
    "gn:population":0,
    "gn:timezone":"Asia/Shanghai",
    "iso:country":"CN",
    "name:zho_x_preferred":[
        "\u8d75\u5787"
    ],
    "name:zho_x_variant":[
        "Zhao\u2019ao"
    ],
    "wof:name":"Zhao'ao",
    "wof:placetype":"locality"
},
  "geometry": {"coordinates":[104.47396999999999,28.72442],"type":"Point"}
}