{
  "type": "Feature",
  "properties": {
    "gn:admin1_code":"9.0",
    "gn:asciiname":"Liuxing Dongzhai",
    "gn:country_code":"CN",
    "gn:dem":259,
    "gn:feature_class":"P",
    "gn:feature_code":"PPL",
    "gn:name":"Liuxing Dongzhai",
    "gn:population":0,
    "gn:timezone":"Asia/Shanghai",
    "iso:country":"CN",
    "name:zho_x_preferred":[
        "\u67f3\u884c\u4e1c\u5be8"
    ],
    "wof:name":"Liuxing Dongzhai",
    "wof:placetype":"locality"
},
  "geometry": {"coordinates":[112.29686,34.60287],"type":"Point"}
}