{
  "type": "Feature",
  "properties": {
    "gn:admin1_code":"14.0",
    "gn:asciiname":"Quenong",
    "gn:country_code":"CN",
    "gn:dem":3726,
    "gn:feature_class":"P",
    "gn:feature_code":"PPL",
    "gn:name":"Quenong",
    "gn:population":0,
    "gn:timezone":"Asia/Urumqi",
    "iso:country":"CN",
    "name:zho_x_preferred":[
        "\u5374\u5f04"
    ],
    "wof:name":"Quenong",
    "wof:placetype":"locality"
},
  "geometry": {"coordinates":[98.01054999999999,29.35469],"type":"Point"}
}