{
  "type": "Feature",
  "properties": {
    "gn:admin1_code":"15.0",
    "gn:asciiname":"Zhangba",
    "gn:country_code":"CN",
    "gn:dem":1299,
    "gn:feature_class":"P",
    "gn:feature_code":"PPL",
    "gn:name":"Zhangba",
    "gn:population":0,
    "gn:timezone":"Asia/Shanghai",
    "iso:country":"CN",
    "name:und_x_variant":[
        "\u5f20\u575d"
    ],
    "name:zho_x_preferred":[
        "\u5f20\u575d"
    ],
    "wof:name":"Zhangba",
    "wof:placetype":"locality"
},
  "geometry": {"coordinates":[105.04703000000001,33.75913],"type":"Point"}
}