{
  "type": "Feature",
  "properties": {
    "gn:admin1_code":"14",
    "gn:asciiname":"Bangkang",
    "gn:country_code":"CN",
    "gn:dem":4045,
    "gn:feature_class":"P",
    "gn:feature_code":"PPL",
    "gn:name":"Bangkang",
    "gn:population":0,
    "gn:timezone":"Asia/Urumqi",
    "iso:country":"CN",
    "name:zho_x_preferred":[
        "\u5e2e\u5eb7"
    ],
    "wof:name":"Bangkang",
    "wof:placetype":"locality"
},
  "geometry": {"coordinates":[89.03579999999999,29.2439],"type":"Point"}
}