{
  "type": "Feature",
  "properties": {
    "gn:admin1_code":"24.0",
    "gn:asciiname":"Xiaye",
    "gn:country_code":"CN",
    "gn:dem":850,
    "gn:feature_class":"P",
    "gn:feature_code":"PPL",
    "gn:name":"Xiaye",
    "gn:population":0,
    "gn:timezone":"Asia/Shanghai",
    "iso:country":"CN",
    "name:und_x_variant":[
        "Hsia-yeh",
        "Hsia-y\u00fcan-ts\u2019un",
        "Xiaye"
    ],
    "name:zho_x_preferred":[
        "\u4e0b\u51b6"
    ],
    "wof:name":"Xiaye",
    "wof:placetype":"locality"
},
  "geometry": {"coordinates":[111.98503999999998,36.35169000000001],"type":"Point"}
}