{
  "type": "Feature",
  "properties": {
    "gn:admin1_code":"29.0",
    "gn:asciiname":"Yulong",
    "gn:country_code":"CN",
    "gn:dem":1110,
    "gn:feature_class":"P",
    "gn:feature_code":"PPL",
    "gn:name":"Yulong",
    "gn:population":0,
    "gn:timezone":"Asia/Shanghai",
    "iso:country":"CN",
    "name:ceb_x_preferred":[
        "Yulong"
    ],
    "name:deu_x_preferred":[
        "Yulong"
    ],
    "name:ita_x_preferred":[
        "Yulong"
    ],
    "name:nld_x_preferred":[
        "Yulong"
    ],
    "name:vie_x_preferred":[
        "Yulong"
    ],
    "name:zho_x_preferred":[
        "\u96e8\u9f99"
    ],
    "wof:name":"Yulong",
    "wof:placetype":"locality"
},
  "geometry": {"coordinates":[104.03700000000001,24.4657],"type":"Point"}
}