{
  "type": "Feature",
  "properties": {
    "gn:admin1_code":"26.0",
    "gn:asciiname":"Haizewan",
    "gn:country_code":"CN",
    "gn:dem":1061,
    "gn:feature_class":"P",
    "gn:feature_code":"PPL",
    "gn:name":"Haizewan",
    "gn:population":0,
    "gn:timezone":"Asia/Shanghai",
    "iso:country":"CN",
    "name:zho_x_preferred":[
        "\u6d77\u5219\u6e7e"
    ],
    "wof:name":"Haizewan",
    "wof:placetype":"locality"
},
  "geometry": {"coordinates":[109.23326000000002,38.04725],"type":"Point"}
}