{
  "type": "Feature",
  "properties": {
    "gn:admin1_code":"24.0",
    "gn:asciiname":"Baijiaxinzhuang",
    "gn:country_code":"CN",
    "gn:dem":1069,
    "gn:feature_class":"P",
    "gn:feature_code":"PPL",
    "gn:name":"Baijiaxinzhuang",
    "gn:population":0,
    "gn:timezone":"Asia/Shanghai",
    "iso:country":"CN",
    "name:zho_x_preferred":[
        "\u767d\u5bb6\u8f9b\u5e84"
    ],
    "wof:name":"Baijiaxinzhuang",
    "wof:placetype":"locality"
},
  "geometry": {"coordinates":[110.69938999999999,37.00711],"type":"Point"}
}