{
  "type": "Feature",
  "properties": {
    "gn:admin1_code":"9",
    "gn:asciiname":"Huanglu",
    "gn:country_code":"CN",
    "gn:dem":50,
    "gn:feature_class":"P",
    "gn:feature_code":"PPL",
    "gn:name":"Huangl\u00fc",
    "gn:population":0,
    "gn:timezone":"Asia/Shanghai",
    "iso:country":"CN",
    "name:und_x_variant":[
        "Huangl\u00fc"
    ],
    "name:zho_x_preferred":[
        "\u9ec4\u5415"
    ],
    "wof:name":"Huanglu",
    "wof:placetype":"locality"
},
  "geometry": {"coordinates":[115.66687,35.84878],"type":"Point"}
}