{
  "type": "Feature",
  "properties": {
    "gn:admin1_code":"4.0",
    "gn:asciiname":"Zhoushe",
    "gn:country_code":"CN",
    "gn:dem":6,
    "gn:feature_class":"P",
    "gn:feature_code":"PPL",
    "gn:name":"Zhoushe",
    "gn:population":0,
    "gn:timezone":"Asia/Shanghai",
    "iso:country":"CN",
    "name:zho_x_preferred":[
        "Zhoushe"
    ],
    "name:zho_x_variant":[
        "\u5468\u820d"
    ],
    "wof:name":"Zhoushe",
    "wof:placetype":"locality"
},
  "geometry": {"coordinates":[121.53597000000001,32.05301],"type":"Point"}
}