{
  "type": "Feature",
  "properties": {
    "gn:admin1_code":"25.0",
    "gn:asciiname":"Beijiang",
    "gn:country_code":"CN",
    "gn:dem":19,
    "gn:feature_class":"P",
    "gn:feature_code":"PPL",
    "gn:name":"Beijiang",
    "gn:population":0,
    "gn:timezone":"Asia/Shanghai",
    "iso:country":"CN",
    "name:zho_x_preferred":[
        "\u5317\u6c5f"
    ],
    "wof:name":"Beijiang",
    "wof:placetype":"locality"
},
  "geometry": {"coordinates":[121.52943999999999,36.93377],"type":"Point"}
}