{
  "type": "Feature",
  "properties": {
    "gn:admin1_code":"12.0",
    "gn:asciiname":"Shangpaidi",
    "gn:country_code":"CN",
    "gn:dem":128,
    "gn:feature_class":"P",
    "gn:feature_code":"PPL",
    "gn:name":"Shangpaidi",
    "gn:population":0,
    "gn:timezone":"Asia/Shanghai",
    "iso:country":"CN",
    "name:zho_x_preferred":[
        "Shangpaidi"
    ],
    "name:zho_x_variant":[
        "\u4e0a\u724c\u5730"
    ],
    "wof:name":"Shangpaidi",
    "wof:placetype":"locality"
},
  "geometry": {"coordinates":[114.36216,29.71379],"type":"Point"}
}