{
  "type": "Feature",
  "properties": {
    "gn:admin1_code":"15.0",
    "gn:asciiname":"Shiwozi",
    "gn:country_code":"CN",
    "gn:dem":2513,
    "gn:feature_class":"P",
    "gn:feature_code":"PPL",
    "gn:name":"Shiwozi",
    "gn:population":0,
    "gn:timezone":"Asia/Shanghai",
    "iso:country":"CN",
    "name:zho_x_preferred":[
        "\u77f3\u7a9d\u5b50"
    ],
    "wof:name":"Shiwozi",
    "wof:placetype":"locality"
},
  "geometry": {"coordinates":[103.598,37.169],"type":"Point"}
}