{
  "type": "Feature",
  "properties": {
    "gn:admin1_code":"29",
    "gn:asciiname":"Guangtengba",
    "gn:country_code":"CN",
    "gn:dem":1406,
    "gn:feature_class":"P",
    "gn:feature_code":"PPL",
    "gn:name":"Guangtengba",
    "gn:population":0,
    "gn:timezone":"Asia/Shanghai",
    "iso:country":"CN",
    "name:zho_x_preferred":[
        "\u5e7f\u85e4\u575d"
    ],
    "wof:name":"Guangtengba",
    "wof:placetype":"locality"
},
  "geometry": {"coordinates":[104.84699999999999,23.4539],"type":"Point"}
}