{
  "type": "Feature",
  "properties": {
    "gn:admin1_code":"10",
    "gn:asciiname":"Zhanggeji",
    "gn:country_code":"CN",
    "gn:dem":37,
    "gn:feature_class":"P",
    "gn:feature_code":"PPL",
    "gn:name":"Zhanggeji",
    "gn:population":0,
    "gn:timezone":"Asia/Shanghai",
    "iso:country":"CN",
    "name:zho_x_preferred":[
        "\u5f20\u845b\u96c6"
    ],
    "wof:name":"Zhanggeji",
    "wof:placetype":"locality"
},
  "geometry": {"coordinates":[115.14951000000001,36.92034],"type":"Point"}
}