{
  "type": "Feature",
  "properties": {
    "gn:admin1_code":"11.0",
    "gn:asciiname":"Nanshandong",
    "gn:country_code":"CN",
    "gn:dem":112,
    "gn:feature_class":"P",
    "gn:feature_code":"PPL",
    "gn:name":"Nanshandong",
    "gn:population":0,
    "gn:timezone":"Asia/Shanghai",
    "iso:country":"CN",
    "name:zho_x_preferred":[
        "\u5357\u5c71\u6d1e"
    ],
    "wof:name":"Nanshandong",
    "wof:placetype":"locality"
},
  "geometry": {"coordinates":[111.84962,28.40534],"type":"Point"}
}