{
  "type": "Feature",
  "properties": {
    "gn:admin1_code":"30.0",
    "gn:asciiname":"Bei'an",
    "gn:country_code":"CN",
    "gn:dem":11,
    "gn:feature_class":"P",
    "gn:feature_code":"PPL",
    "gn:name":"Bei\u2019an",
    "gn:population":0,
    "gn:timezone":"Asia/Shanghai",
    "iso:country":"CN",
    "name:und_x_variant":[
        "Bei\u2019an"
    ],
    "name:zho_x_preferred":[
        "\u5317\u5b89"
    ],
    "wof:name":"Bei'an",
    "wof:placetype":"locality"
},
  "geometry": {"coordinates":[112.49456000000001,22.32277],"type":"Point"}
}