{
  "type": "Feature",
  "properties": {
    "gn:admin1_code":"30.0",
    "gn:asciiname":"Bei'an",
    "gn:country_code":"CN",
    "gn:dem":11,
    "gn:feature_class":"P",
    "gn:feature_code":"PPL",
    "gn:name":"Bei\u2019an",
    "gn:population":0,
    "gn:timezone":"Asia/Shanghai",
    "iso:country":"CN",
    "name:ara_x_preferred":[
        "\u0628\u064a\u0624\u0627\u0646"
    ],
    "name:deu_x_preferred":[
        "Bei\u2019an"
    ],
    "name:fra_x_preferred":[
        "Bei'an"
    ],
    "name:ita_x_preferred":[
        "Bei'an"
    ],
    "name:jpn_x_preferred":[
        "\u5317\u5b89\u5e02"
    ],
    "name:kik_x_preferred":[
        "Bei'an"
    ],
    "name:kor_x_preferred":[
        "\ubca0\uc774\uc548\uc2dc"
    ],
    "name:mlg_x_preferred":[
        "Bei'an"
    ],
    "name:nor_x_preferred":[
        "Bei'an"
    ],
    "name:pam_x_preferred":[
        "Bei'an"
    ],
    "name:rus_x_preferred":[
        "\u0411\u044d\u0439\u0430\u043d\u044c"
    ],
    "name:swe_x_preferred":[
        "Bei'an"
    ],
    "name:und_x_variant":[
        "Bei\u2019an"
    ],
    "name:urd_x_preferred":[
        "\u0628\u06cc\u0626\u0622\u0646"
    ],
    "name:vie_x_preferred":[
        "B\u1eafc An"
    ],
    "name:war_x_preferred":[
        "Beian"
    ],
    "name:zho_x_preferred":[
        "\u5317\u5b89"
    ],
    "name:zho_x_variant":[
        "\u5317\u5b89\u5e02"
    ],
    "wof:name":"Bei'an",
    "wof:placetype":"locality"
},
  "geometry": {"coordinates":[112.49456000000001,22.32277],"type":"Point"}
}