{
  "type": "Feature",
  "properties": {
    "gn:admin1_code":"29",
    "gn:asciiname":"Bafei",
    "gn:country_code":"CN",
    "gn:dem":611,
    "gn:feature_class":"P",
    "gn:feature_code":"PPL",
    "gn:name":"Bafei",
    "gn:population":0,
    "gn:timezone":"Asia/Shanghai",
    "iso:country":"CN",
    "name:zho_x_preferred":[
        "\u53ed\u98de"
    ],
    "wof:name":"Bafei",
    "wof:placetype":"locality"
},
  "geometry": {"coordinates":[105.524,24.0783],"type":"Point"}
}