{
  "type": "Feature",
  "properties": {
    "gn:admin1_code":"04",
    "gn:asciiname":"Dongshicun",
    "gn:country_code":"CN",
    "gn:dem":6,
    "gn:feature_class":"P",
    "gn:feature_code":"PPL",
    "gn:name":"Dongshicun",
    "gn:population":0,
    "gn:timezone":"Asia/Shanghai",
    "iso:country":"CN",
    "name:und_x_variant":[
        "Dongshi"
    ],
    "name:zho_x_preferred":[
        "\u4e1c\u59cb\u6751"
    ],
    "wof:name":"Dongshicun",
    "wof:placetype":"locality"
},
  "geometry": {"coordinates":[120.6955,31.58331],"type":"Point"}
}