{
  "type": "Feature",
  "properties": {
    "gn:admin1_code":"19.0",
    "gn:asciiname":"Tongtiancun",
    "gn:country_code":"CN",
    "gn:dem":52,
    "gn:feature_class":"P",
    "gn:feature_code":"PPL",
    "gn:name":"Tongtiancun",
    "gn:population":0,
    "gn:timezone":"Asia/Shanghai",
    "iso:country":"CN",
    "name:zho_x_preferred":[
        "\u901a\u5929\u6751"
    ],
    "wof:name":"Tongtiancun",
    "wof:placetype":"locality"
},
  "geometry": {"coordinates":[124.06999999999999,40.0585],"type":"Point"}
}