{
  "type": "Feature",
  "properties": {
    "gn:admin1_code":"26.0",
    "gn:asciiname":"Baijiagou",
    "gn:country_code":"CN",
    "gn:dem":552,
    "gn:feature_class":"P",
    "gn:feature_code":"PPL",
    "gn:name":"Baijiagou",
    "gn:population":0,
    "gn:timezone":"Asia/Shanghai",
    "iso:country":"CN",
    "name:zho_x_preferred":[
        "\u67cf\u5bb6\u6c9f"
    ],
    "wof:name":"Baijiagou",
    "wof:placetype":"locality"
},
  "geometry": {"coordinates":[109.49016,32.83654],"type":"Point"}
}