{
  "type": "Feature",
  "properties": {
    "gn:admin1_code":"32.0",
    "gn:asciiname":"Tujiayuan",
    "gn:country_code":"CN",
    "gn:dem":472,
    "gn:feature_class":"P",
    "gn:feature_code":"PPL",
    "gn:name":"Tujiayuan",
    "gn:population":0,
    "gn:timezone":"Asia/Shanghai",
    "iso:country":"CN",
    "name:zho_x_preferred":[
        "\u6d82\u5bb6\u56ed"
    ],
    "wof:name":"Tujiayuan",
    "wof:placetype":"locality"
},
  "geometry": {"coordinates":[104.31815,29.77303],"type":"Point"}
}