{
  "type": "Feature",
  "properties": {
    "iso:country":"CN",
    "name:eng_x_preferred":[
        "Wuhan"
    ],
    "name:zho_x_preferred":[
        "\u6b66\u6c49\u5e02"
    ],
    "qs:name":"\u6b66\u6c49\u5e02",
    "qs:name_adm0":"\u4e2d\u570b",
    "qs:name_adm1":"\u6e56\u5317\u7701",
    "qs:photos":1151,
    "qs:photos_1k":233,
    "qs:photos_9k":27,
    "qs:photos_9r":14,
    "qs:photos_all":6151,
    "qs:photos_sr":11,
    "qs:placetype":"LocalAdmin",
    "qs:pop_sr":"0",
    "wof:name":"Wuhan",
    "wof:placetype":"localadmin"
},
  "geometry": {"coordinates":[114.28699400000001,30.568148],"type":"Point"}
}