{
  "type": "Feature",
  "properties": {
    "gn:admin1_code":"26.0",
    "gn:asciiname":"Dangzhuangcun",
    "gn:country_code":"CN",
    "gn:dem":1050,
    "gn:feature_class":"P",
    "gn:feature_code":"PPL",
    "gn:name":"Dangzhuangcun",
    "gn:population":0,
    "gn:timezone":"Asia/Shanghai",
    "iso:country":"CN",
    "name:zho_x_preferred":[
        "\u515a\u5e84\u6751"
    ],
    "wof:name":"Dangzhuangcun",
    "wof:placetype":"locality"
},
  "geometry": {"coordinates":[109.71696,38.08113],"type":"Point"}
}