{
  "type": "Feature",
  "properties": {
    "gn:admin1_code":"29.0",
    "gn:asciiname":"Xiawazhadi",
    "gn:country_code":"CN",
    "gn:dem":1588,
    "gn:feature_class":"P",
    "gn:feature_code":"PPL",
    "gn:name":"Xiawazhadi",
    "gn:population":0,
    "gn:timezone":"Asia/Shanghai",
    "iso:country":"CN",
    "name:zho_x_preferred":[
        "\u4e0b\u74e6\u781f\u5730"
    ],
    "wof:name":"Xiawazhadi",
    "wof:placetype":"locality"
},
  "geometry": {"coordinates":[100.807,24.706],"type":"Point"}
}