{
  "type": "Feature",
  "properties": {
    "gn:admin1_code":"29.0",
    "gn:asciiname":"Shijiazhuang",
    "gn:country_code":"CN",
    "gn:dem":2071,
    "gn:feature_class":"P",
    "gn:feature_code":"PPL",
    "gn:name":"Shijiazhuang",
    "gn:population":0,
    "gn:timezone":"Asia/Shanghai",
    "iso:country":"CN",
    "name:zho_x_preferred":[
        "\u77f3\u5bb6\u5e84"
    ],
    "wof:name":"Shijiazhuang",
    "wof:placetype":"locality"
},
  "geometry": {"coordinates":[100.804,25.5681],"type":"Point"}
}