{
  "type": "Feature",
  "properties": {
    "gn:admin1_code":"2.0",
    "gn:asciiname":"Pengjiabang",
    "gn:country_code":"CN",
    "gn:dem":5,
    "gn:feature_class":"P",
    "gn:feature_code":"PPL",
    "gn:name":"Pengjiabang",
    "gn:population":0,
    "gn:timezone":"Asia/Shanghai",
    "iso:country":"CN",
    "name:und_x_variant":[
        "\u5f6d\u5bb6\u6d5c"
    ],
    "wof:name":"Pengjiabang",
    "wof:placetype":"locality"
},
  "geometry": {"coordinates":[120.46818,30.67468],"type":"Point"}
}