{
  "type": "Feature",
  "properties": {
    "gn:admin1_code":"26.0",
    "gn:asciiname":"Qingqiaoyixiang",
    "gn:country_code":"CN",
    "gn:dem":695,
    "gn:feature_class":"P",
    "gn:feature_code":"PPL",
    "gn:name":"Qingqiaoyixiang",
    "gn:population":0,
    "gn:timezone":"Asia/Shanghai",
    "iso:country":"CN",
    "name:und_x_variant":[
        "\u9752\u6865\u9a7f\u4e61"
    ],
    "wof:name":"Qingqiaoyixiang",
    "wof:placetype":"locality"
},
  "geometry": {"coordinates":[106.96232999999999,33.33474],"type":"Point"}
}