{
  "type": "Feature",
  "properties": {
    "gn:admin1_code":"1.0",
    "gn:asciiname":"Xiaohe",
    "gn:country_code":"CN",
    "gn:dem":28,
    "gn:feature_class":"P",
    "gn:feature_code":"PPL",
    "gn:name":"Xiaohe",
    "gn:population":0,
    "gn:timezone":"Asia/Shanghai",
    "iso:country":"CN",
    "name:ceb_x_preferred":[
        "Xiaohe"
    ],
    "name:deu_x_preferred":[
        "Xiaohe"
    ],
    "name:nor_x_preferred":[
        "Xiaohe"
    ],
    "name:swe_x_preferred":[
        "Xiaohe"
    ],
    "name:und_x_variant":[
        "\u5c0f\u6cb3",
        "\u5c0f\u6cb3\u6751"
    ],
    "name:zho_x_preferred":[
        "Xiaohecun"
    ],
    "wof:name":"Xiaohe",
    "wof:placetype":"locality"
},
  "geometry": {"coordinates":[119.39512000000001,31.00435],"type":"Point"}
}