{
  "type": "Feature",
  "properties": {
    "gn:admin1_code":"10",
    "gn:asciiname":"Chiyingzi",
    "gn:country_code":"CN",
    "gn:dem":547,
    "gn:feature_class":"P",
    "gn:feature_code":"PPL",
    "gn:name":"Chiyingzi",
    "gn:population":0,
    "gn:timezone":"Asia/Shanghai",
    "iso:country":"CN",
    "name:zho_x_preferred":[
        "\u6c60\u8425\u5b50"
    ],
    "wof:name":"Chiyingzi",
    "wof:placetype":"locality"
},
  "geometry": {"coordinates":[118.12043,41.16333],"type":"Point"}
}