{
  "type": "Feature",
  "properties": {
    "gn:admin1_code":"8.0",
    "gn:asciiname":"Shaojiatun",
    "gn:country_code":"CN",
    "gn:dem":142,
    "gn:feature_class":"P",
    "gn:feature_code":"PPL",
    "gn:name":"Shaojiatun",
    "gn:population":0,
    "gn:timezone":"Asia/Shanghai",
    "iso:country":"CN",
    "name:zho_x_preferred":[
        "\u90b5\u5bb6\u5c6f"
    ],
    "wof:name":"Shaojiatun",
    "wof:placetype":"locality"
},
  "geometry": {"coordinates":[123.28888999999999,46.53056],"type":"Point"}
}