{
  "type": "Feature",
  "properties": {
    "gn:admin1_code":"18",
    "gn:asciiname":"Sanjiaoba",
    "gn:country_code":"CN",
    "gn:dem":936,
    "gn:feature_class":"P",
    "gn:feature_code":"PPL",
    "gn:name":"Sanjiaoba",
    "gn:population":0,
    "gn:timezone":"Asia/Shanghai",
    "iso:country":"CN",
    "name:zho_x_preferred":[
        "\u4e09\u89d2\u575d"
    ],
    "wof:name":"Sanjiaoba",
    "wof:placetype":"locality"
},
  "geometry": {"coordinates":[107.437,28.9965],"type":"Point"}
}