{
  "type": "Feature",
  "properties": {
    "gn:admin1_code":"7.0",
    "gn:asciiname":"Dongfeng",
    "gn:country_code":"CN",
    "gn:dem":11,
    "gn:feature_class":"P",
    "gn:feature_code":"PPL",
    "gn:name":"Dongfeng",
    "gn:population":0,
    "gn:timezone":"Asia/Shanghai",
    "iso:country":"CN",
    "name:und_x_variant":[
        "\u4e1c\u5cf0"
    ],
    "wof:name":"Dongfeng",
    "wof:placetype":"locality"
},
  "geometry": {"coordinates":[119.39931,25.62526],"type":"Point"}
}