{
  "type": "Feature",
  "properties": {
    "gn:admin1_code":"29.0",
    "gn:asciiname":"Moshiyi",
    "gn:country_code":"CN",
    "gn:dem":1274,
    "gn:feature_class":"P",
    "gn:feature_code":"PPLA4",
    "gn:name":"Moshiyi",
    "gn:population":0,
    "gn:timezone":"Asia/Shanghai",
    "iso:country":"CN",
    "name:und_x_variant":[
        "\u58a8\u77f3\u9a7f",
        "Mohan",
        "Mohan Zhen",
        "\u58a8\u7ff0",
        "\u58a8\u7ff0\u9547"
    ],
    "wof:name":"Moshiyi",
    "wof:placetype":"locality"
},
  "geometry": {"coordinates":[103.72828,27.8277],"type":"Point"}
}