{
  "type": "Feature",
  "properties": {
    "gn:admin1_code":"30.0",
    "gn:asciiname":"Beikeng",
    "gn:country_code":"CN",
    "gn:dem":82,
    "gn:feature_class":"P",
    "gn:feature_code":"PPL",
    "gn:name":"Beikeng",
    "gn:population":0,
    "gn:timezone":"Asia/Shanghai",
    "iso:country":"CN",
    "name:zho_x_preferred":[
        "Beikeng"
    ],
    "name:zho_x_variant":[
        "\u5317\u5751"
    ],
    "wof:name":"Beikeng",
    "wof:placetype":"locality"
},
  "geometry": {"coordinates":[112.82250000000001,23.675],"type":"Point"}
}