{
  "type": "Feature",
  "properties": {
    "gn:admin1_code":"15.0",
    "gn:asciiname":"Caojia",
    "gn:country_code":"CN",
    "gn:dem":812,
    "gn:feature_class":"P",
    "gn:feature_code":"PPL",
    "gn:name":"Caojia",
    "gn:population":0,
    "gn:timezone":"Asia/Shanghai",
    "iso:country":"CN",
    "name:zho_x_preferred":[
        "\u66f9\u5bb6"
    ],
    "wof:name":"Caojia",
    "wof:placetype":"locality"
},
  "geometry": {"coordinates":[104.935,32.8414],"type":"Point"}
}