{
  "type": "Feature",
  "properties": {
    "gn:admin1_code":"9.0",
    "gn:asciiname":"Xiekuang",
    "gn:country_code":"CN",
    "gn:dem":283,
    "gn:feature_class":"P",
    "gn:feature_code":"PPL",
    "gn:name":"Xiekuang",
    "gn:population":0,
    "gn:timezone":"Asia/Shanghai",
    "iso:country":"CN",
    "name:zho_x_preferred":[
        "\u90aa\u5739"
    ],
    "wof:name":"Xiekuang",
    "wof:placetype":"locality"
},
  "geometry": {"coordinates":[114.13127,35.85403],"type":"Point"}
}