{
  "type": "Feature",
  "properties": {
    "gn:admin1_code":"11.0",
    "gn:asciiname":"Jianshanling",
    "gn:country_code":"CN",
    "gn:dem":425,
    "gn:feature_class":"P",
    "gn:feature_code":"PPL",
    "gn:name":"Jianshanling",
    "gn:population":0,
    "gn:timezone":"Asia/Shanghai",
    "iso:country":"CN",
    "name:zho_x_preferred":[
        "\u5c16\u5c71\u5cad"
    ],
    "wof:name":"Jianshanling",
    "wof:placetype":"locality"
},
  "geometry": {"coordinates":[111.67224,27.62786],"type":"Point"}
}