{
  "type": "Feature",
  "properties": {
    "gn:admin1_code":"19.0",
    "gn:asciiname":"Dongmiaocun",
    "gn:country_code":"CN",
    "gn:dem":477,
    "gn:feature_class":"P",
    "gn:feature_code":"PPL",
    "gn:name":"Dongmiaocun",
    "gn:population":0,
    "gn:timezone":"Asia/Shanghai",
    "iso:country":"CN",
    "name:zho_x_preferred":[
        "\u4e1c\u5e99\u6751"
    ],
    "wof:name":"Dongmiaocun",
    "wof:placetype":"locality"
},
  "geometry": {"coordinates":[125.18600000000001,42.037],"type":"Point"}
}