{
  "type": "Feature",
  "properties": {
    "gn:admin1_code":"20.0",
    "gn:asciiname":"Qinghechang",
    "gn:country_code":"CN",
    "gn:dem":1798,
    "gn:feature_class":"P",
    "gn:feature_code":"PPL",
    "gn:name":"Qinghechang",
    "gn:population":0,
    "gn:timezone":"Asia/Shanghai",
    "iso:country":"CN",
    "name:und_x_variant":[
        "\u5e86\u548c\u660c"
    ],
    "wof:name":"Qinghechang",
    "wof:placetype":"locality"
},
  "geometry": {"coordinates":[110.81258,41.16793],"type":"Point"}
}