{
  "type": "Feature",
  "properties": {
    "gn:admin1_code":"29.0",
    "gn:asciiname":"Yakouwai",
    "gn:country_code":"CN",
    "gn:dem":1302,
    "gn:feature_class":"P",
    "gn:feature_code":"PPL",
    "gn:name":"Yakouwai",
    "gn:population":0,
    "gn:timezone":"Asia/Shanghai",
    "iso:country":"CN",
    "name:zho_x_preferred":[
        "\u57ad\u53e3\u5916"
    ],
    "wof:name":"Yakouwai",
    "wof:placetype":"locality"
},
  "geometry": {"coordinates":[99.0164,24.6575],"type":"Point"}
}