{
  "type": "Feature",
  "properties": {
    "gn:admin1_code":"29",
    "gn:asciiname":"Xuanwobai",
    "gn:country_code":"CN",
    "gn:dem":1895,
    "gn:feature_class":"P",
    "gn:feature_code":"PPL",
    "gn:name":"Xuanwobai",
    "gn:population":0,
    "gn:timezone":"Asia/Shanghai",
    "iso:country":"CN",
    "name:zho_x_preferred":[
        "\u65cb\u6da1\u6446"
    ],
    "wof:name":"Xuanwobai",
    "wof:placetype":"locality"
},
  "geometry": {"coordinates":[101.482,24.9312],"type":"Point"}
}