{
  "type": "Feature",
  "properties": {
    "gn:admin1_code":"8.0",
    "gn:asciiname":"Xilingcun",
    "gn:country_code":"CN",
    "gn:dem":165,
    "gn:feature_class":"P",
    "gn:feature_code":"PPL",
    "gn:name":"Xilingcun",
    "gn:population":0,
    "gn:timezone":"Asia/Shanghai",
    "iso:country":"CN",
    "name:zho_x_preferred":[
        "\u897f\u5cad\u6751"
    ],
    "wof:name":"Xilingcun",
    "wof:placetype":"locality"
},
  "geometry": {"coordinates":[126.93264000000001,46.17229],"type":"Point"}
}