{
  "type": "Feature",
  "properties": {
    "gn:admin1_code":"20.0",
    "gn:asciiname":"Qiantaba",
    "gn:country_code":"CN",
    "gn:dem":1883,
    "gn:feature_class":"P",
    "gn:feature_code":"PPL",
    "gn:name":"Qiantaba",
    "gn:population":0,
    "gn:timezone":"Asia/Shanghai",
    "iso:country":"CN",
    "name:und_x_variant":[
        "\u524d\u5854\u575d"
    ],
    "wof:name":"Qiantaba",
    "wof:placetype":"locality"
},
  "geometry": {"coordinates":[110.80781,40.82092],"type":"Point"}
}