{
  "type": "Feature",
  "properties": {
    "gn:admin1_code":"3.0",
    "gn:asciiname":"Jianwan",
    "gn:country_code":"CN",
    "gn:dem":67,
    "gn:feature_class":"P",
    "gn:feature_code":"PPL",
    "gn:name":"Jianwan",
    "gn:population":0,
    "gn:timezone":"Asia/Shanghai",
    "iso:country":"CN",
    "name:und_x_variant":[
        "\u7b80\u6e7e"
    ],
    "wof:name":"Jianwan",
    "wof:placetype":"locality"
},
  "geometry": {"coordinates":[115.32196,27.75733],"type":"Point"}
}