{
  "type": "Feature",
  "properties": {
    "gn:admin1_code":"25",
    "gn:asciiname":"Zhengwangzhuang",
    "gn:country_code":"CN",
    "gn:dem":250,
    "gn:feature_class":"P",
    "gn:feature_code":"PPL",
    "gn:name":"Zhengwangzhuang",
    "gn:population":0,
    "gn:timezone":"Asia/Shanghai",
    "iso:country":"CN",
    "name:zho_x_preferred":[
        "\u90d1\u738b\u5e84"
    ],
    "wof:name":"Zhengwangzhuang",
    "wof:placetype":"locality"
},
  "geometry": {"coordinates":[117.827,36.1368],"type":"Point"}
}