{
  "type": "Feature",
  "properties": {
    "gn:admin1_code":"29",
    "gn:asciiname":"Pangxieqing",
    "gn:country_code":"CN",
    "gn:dem":1792,
    "gn:feature_class":"P",
    "gn:feature_code":"PPL",
    "gn:name":"Pangxieqing",
    "gn:population":0,
    "gn:timezone":"Asia/Shanghai",
    "iso:country":"CN",
    "name:zho_x_preferred":[
        "\u8783\u87f9\u7b90"
    ],
    "wof:name":"Pangxieqing",
    "wof:placetype":"locality"
},
  "geometry": {"coordinates":[102.18300000000001,24.74],"type":"Point"}
}