{
  "type": "Feature",
  "properties": {
    "gn:admin1_code":"10.0",
    "gn:asciiname":"Hutudi",
    "gn:country_code":"CN",
    "gn:dem":657,
    "gn:feature_class":"P",
    "gn:feature_code":"PPL",
    "gn:name":"Hutudi",
    "gn:population":0,
    "gn:timezone":"Asia/Shanghai",
    "iso:country":"CN",
    "name:zho_x_preferred":[
        "\u9e44\u7a81\u5730"
    ],
    "wof:name":"Hutudi",
    "wof:placetype":"locality"
},
  "geometry": {"coordinates":[114.85601,40.68493],"type":"Point"}
}