{
  "type": "Feature",
  "properties": {
    "gn:admin1_code":"25",
    "gn:asciiname":"Bailongwan",
    "gn:country_code":"CN",
    "gn:dem":25,
    "gn:feature_class":"P",
    "gn:feature_code":"PPL",
    "gn:name":"Bailongwan",
    "gn:population":0,
    "gn:timezone":"Asia/Shanghai",
    "iso:country":"CN",
    "name:zho_x_preferred":[
        "\u767d\u9f99\u6e7e"
    ],
    "wof:name":"Bailongwan",
    "wof:placetype":"locality"
},
  "geometry": {"coordinates":[117.65000000000001,37.2636],"type":"Point"}
}