{
  "type": "Feature",
  "properties": {
    "gn:admin1_code":"9.0",
    "gn:asciiname":"Buyang",
    "gn:country_code":"CN",
    "gn:dem":80,
    "gn:feature_class":"P",
    "gn:feature_code":"PPL",
    "gn:name":"Buyang",
    "gn:population":0,
    "gn:timezone":"Asia/Shanghai",
    "iso:country":"CN",
    "name:fin_x_preferred":[
        "Buyang"
    ],
    "name:zho_x_preferred":[
        "\u57e0\u9633"
    ],
    "wof:name":"Buyang",
    "wof:placetype":"locality"
},
  "geometry": {"coordinates":[114.06461000000002,32.2917],"type":"Point"}
}