{
  "type": "Feature",
  "properties": {
    "gn:admin1_code":"24.0",
    "gn:asciiname":"Dacuijiazhuang",
    "gn:country_code":"CN",
    "gn:dem":432,
    "gn:feature_class":"P",
    "gn:feature_code":"PPL",
    "gn:name":"Dacuijiazhuang",
    "gn:population":0,
    "gn:timezone":"Asia/Shanghai",
    "iso:country":"CN",
    "name:zho_x_preferred":[
        "\u5927\u5d14\u5bb6\u5e84"
    ],
    "wof:name":"Dacuijiazhuang",
    "wof:placetype":"locality"
},
  "geometry": {"coordinates":[113.46293,38.4491],"type":"Point"}
}