{
  "type": "Feature",
  "properties": {
    "gn:admin1_code":"31.0",
    "gn:asciiname":"Xinglong Sanshidui",
    "gn:country_code":"CN",
    "gn:dem":35,
    "gn:feature_class":"P",
    "gn:feature_code":"PPLF",
    "gn:name":"Xinglong Sanshidui",
    "gn:population":0,
    "gn:timezone":"Asia/Shanghai",
    "iso:country":"CN",
    "name:und_x_variant":[
        "\u5174\u9686\u4e09\u5341\u961f"
    ],
    "wof:name":"Xinglong Sanshidui",
    "wof:placetype":"locality"
},
  "geometry": {"coordinates":[110.21495,18.72663],"type":"Point"}
}