{
  "type": "Feature",
  "properties": {
    "gn:admin1_code":"15.0",
    "gn:asciiname":"Huadaozi",
    "gn:country_code":"CN",
    "gn:dem":1958,
    "gn:feature_class":"P",
    "gn:feature_code":"PPL",
    "gn:name":"Huadaozi",
    "gn:population":0,
    "gn:timezone":"Asia/Shanghai",
    "iso:country":"CN",
    "name:zho_x_preferred":[
        "\u82b1\u9053\u5b50"
    ],
    "wof:name":"Huadaozi",
    "wof:placetype":"locality"
},
  "geometry": {"coordinates":[104.947,36.817],"type":"Point"}
}