{
  "type": "Feature",
  "properties": {
    "gn:admin1_code":"07",
    "gn:asciiname":"Zhuqitou",
    "gn:country_code":"CN",
    "gn:dem":186,
    "gn:feature_class":"P",
    "gn:feature_code":"PPL",
    "gn:name":"Zhuqitou",
    "gn:population":0,
    "gn:timezone":"Asia/Shanghai",
    "iso:country":"CN",
    "name:zho_x_preferred":[
        "\u7af9\u6b67\u5934"
    ],
    "name:zho_x_variant":[
        "\u7af9\u5c90\u5934"
    ],
    "wof:name":"Zhuqitou",
    "wof:placetype":"locality"
},
  "geometry": {"coordinates":[116.43917,25.01869],"type":"Point"}
}