{
  "type": "Feature",
  "properties": {
    "gn:admin1_code":"25.0",
    "gn:asciiname":"Malingxujiacun",
    "gn:country_code":"CN",
    "gn:dem":21,
    "gn:feature_class":"P",
    "gn:feature_code":"PPL",
    "gn:name":"Malingxujiacun",
    "gn:population":0,
    "gn:timezone":"Asia/Shanghai",
    "iso:country":"CN",
    "name:zho_x_preferred":[
        "\u9a6c\u5cad\u8bb8\u5bb6\u6751"
    ],
    "wof:name":"Malingxujiacun",
    "wof:placetype":"locality"
},
  "geometry": {"coordinates":[122.33887,36.961],"type":"Point"}
}