{
  "type": "Feature",
  "properties": {
    "gn:admin1_code":"15.0",
    "gn:asciiname":"Nianjiawan",
    "gn:country_code":"CN",
    "gn:dem":2415,
    "gn:feature_class":"P",
    "gn:feature_code":"PPL",
    "gn:name":"Nianjiawan",
    "gn:population":0,
    "gn:timezone":"Asia/Shanghai",
    "iso:country":"CN",
    "name:zho_x_preferred":[
        "\u5e74\u5bb6\u6e7e"
    ],
    "wof:name":"Nianjiawan",
    "wof:placetype":"locality"
},
  "geometry": {"coordinates":[103.46599999999999,36.0241],"type":"Point"}
}