{
  "type": "Feature",
  "properties": {
    "gn:admin1_code":"4.0",
    "gn:asciiname":"Wangdouzhuang",
    "gn:country_code":"CN",
    "gn:dem":2,
    "gn:feature_class":"P",
    "gn:feature_code":"PPL",
    "gn:name":"Wangdouzhuang",
    "gn:population":0,
    "gn:timezone":"Asia/Shanghai",
    "iso:country":"CN",
    "name:zho_x_preferred":[
        "Wangdouzhuang"
    ],
    "name:zho_x_variant":[
        "\u738b\u7aa6\u5e84"
    ],
    "wof:name":"Wangdouzhuang",
    "wof:placetype":"locality"
},
  "geometry": {"coordinates":[120.02204999999999,34.11197],"type":"Point"}
}