{
  "type": "Feature",
  "properties": {
    "gn:admin1_code":"10.0",
    "gn:asciiname":"Fangjiagou",
    "gn:country_code":"CN",
    "gn:dem":629,
    "gn:feature_class":"P",
    "gn:feature_code":"PPL",
    "gn:name":"Fangjiagou",
    "gn:population":0,
    "gn:timezone":"Asia/Shanghai",
    "iso:country":"CN",
    "name:zho_x_preferred":[
        "\u65b9\u5bb6\u6c9f"
    ],
    "wof:name":"Fangjiagou",
    "wof:placetype":"locality"
},
  "geometry": {"coordinates":[115.12842000000001,40.32989],"type":"Point"}
}