{
  "type": "Feature",
  "properties": {
    "gn:admin1_code":"8.0",
    "gn:asciiname":"Lianshancun",
    "gn:country_code":"CN",
    "gn:dem":190,
    "gn:feature_class":"P",
    "gn:feature_code":"PPL",
    "gn:name":"Lianshancun",
    "gn:population":0,
    "gn:timezone":"Asia/Shanghai",
    "iso:country":"CN",
    "name:zho_x_preferred":[
        "\u8054\u5c71\u6751"
    ],
    "wof:name":"Lianshancun",
    "wof:placetype":"locality"
},
  "geometry": {"coordinates":[130.64543,47.73084],"type":"Point"}
}