{
  "type": "Feature",
  "properties": {
    "gn:admin1_code":"19",
    "gn:asciiname":"Beisanjia",
    "gn:cc2":"CN",
    "gn:country_code":"CN",
    "gn:dem":193,
    "gn:feature_class":"P",
    "gn:feature_code":"PPL",
    "gn:name":"Beisanjia",
    "gn:population":0,
    "gn:timezone":"Asia/Shanghai",
    "iso:country":"CN",
    "name:und_x_variant":[
        "San-chia-tzu",
        "Pei-san-chia",
        "Pei-san-chia-tzu",
        "Beisanjia"
    ],
    "wof:name":"Beisanjia",
    "wof:placetype":"locality"
},
  "geometry": {"coordinates":[124.71028,42.04611],"type":"Point"}
}