{
  "type": "Feature",
  "properties": {
    "gn:admin1_code":"32.0",
    "gn:asciiname":"Sandaoyan",
    "gn:country_code":"CN",
    "gn:dem":321,
    "gn:feature_class":"P",
    "gn:feature_code":"PPL",
    "gn:name":"Sandaoyan",
    "gn:population":0,
    "gn:timezone":"Asia/Shanghai",
    "iso:country":"CN",
    "name:zho_x_preferred":[
        "\u4e09\u9053\u5830"
    ],
    "wof:name":"Sandaoyan",
    "wof:placetype":"locality"
},
  "geometry": {"coordinates":[105.32682,30.17298],"type":"Point"}
}