{
  "type": "Feature",
  "properties": {
    "gn:admin1_code":"32.0",
    "gn:asciiname":"Zhajiao",
    "gn:country_code":"CN",
    "gn:dem":3343,
    "gn:feature_class":"P",
    "gn:feature_code":"PPL",
    "gn:name":"Zhajiao",
    "gn:population":0,
    "gn:timezone":"Asia/Shanghai",
    "iso:country":"CN",
    "name:zho_x_preferred":[
        "\u624e\u4ea4"
    ],
    "wof:name":"Zhajiao",
    "wof:placetype":"locality"
},
  "geometry": {"coordinates":[100.712,31.3563],"type":"Point"}
}