{
  "type": "Feature",
  "properties": {
    "gn:admin1_code":"14.0",
    "gn:asciiname":"Xiaboli",
    "gn:country_code":"CN",
    "gn:dem":4297,
    "gn:feature_class":"P",
    "gn:feature_code":"PPL",
    "gn:name":"Xiaboli",
    "gn:population":0,
    "gn:timezone":"Asia/Urumqi",
    "iso:country":"CN",
    "name:zho_x_preferred":[
        "\u4e0b\u6ce2\u529b"
    ],
    "wof:name":"Xiaboli",
    "wof:placetype":"locality"
},
  "geometry": {"coordinates":[97.16866,30.79051],"type":"Point"}
}