{
  "type": "Feature",
  "properties": {
    "gn:admin1_code":"26.0",
    "gn:asciiname":"Shibizecun",
    "gn:country_code":"CN",
    "gn:dem":1126,
    "gn:feature_class":"P",
    "gn:feature_code":"PPL",
    "gn:name":"Shibizecun",
    "gn:population":0,
    "gn:timezone":"Asia/Shanghai",
    "iso:country":"CN",
    "name:zho_x_preferred":[
        "\u77f3\u78a7\u5219\u6751"
    ],
    "wof:name":"Shibizecun",
    "wof:placetype":"locality"
},
  "geometry": {"coordinates":[109.42577,37.91529],"type":"Point"}
}