{
  "type": "Feature",
  "properties": {
    "gn:admin1_code":"25.0",
    "gn:asciiname":"Yinzhuangcun",
    "gn:country_code":"CN",
    "gn:dem":37,
    "gn:feature_class":"P",
    "gn:feature_code":"PPL",
    "gn:name":"Yinzhuangcun",
    "gn:population":0,
    "gn:timezone":"Asia/Shanghai",
    "iso:country":"CN",
    "name:zho_x_preferred":[
        "\u5c39\u5e84\u6751"
    ],
    "wof:name":"Yinzhuangcun",
    "wof:placetype":"locality"
},
  "geometry": {"coordinates":[115.76737,36.76859],"type":"Point"}
}