{
  "type": "Feature",
  "properties": {
    "gn:admin1_code":"02",
    "gn:asciiname":"Dayin",
    "gn:country_code":"CN",
    "gn:dem":1,
    "gn:feature_class":"P",
    "gn:feature_code":"PPLA4",
    "gn:name":"Dayin",
    "gn:population":0,
    "gn:timezone":"Asia/Shanghai",
    "iso:country":"CN",
    "name:fas_x_preferred":[
        "\u062f\u0627\u06cc\u06cc\u0646"
    ],
    "name:und_x_variant":[
        "Ta-yin",
        "Dayin",
        "Dayin Zhen"
    ],
    "name:zho_x_preferred":[
        "\u5927\u9690"
    ],
    "name:zho_x_variant":[
        "\u5927\u9690\u9547"
    ],
    "wof:name":"Dayin",
    "wof:placetype":"locality"
},
  "geometry": {"coordinates":[121.37107,29.94005],"type":"Point"}
}