{
  "type": "Feature",
  "properties": {
    "gn:admin1_code":"10.0",
    "gn:asciiname":"Zaoqiang",
    "gn:cc2":"CN",
    "gn:country_code":"CN",
    "gn:dem":28,
    "gn:feature_class":"P",
    "gn:feature_code":"PPL",
    "gn:name":"Zaoqiang",
    "gn:population":0,
    "gn:timezone":"Asia/Shanghai",
    "iso:country":"CN",
    "name:deu_x_preferred":[
        "Zaoqiang"
    ],
    "name:fas_x_preferred":[
        "\u0634\u0647\u0631\u0633\u062a\u0627\u0646 \u0632\u0627\u0648\u0686\u06cc\u0627\u0646\u06af"
    ],
    "name:jpn_x_preferred":[
        "\u68d7\u5f37\u770c"
    ],
    "name:kor_x_preferred":[
        "\uc9dc\uc624\ucc3d\ud604"
    ],
    "name:nor_x_preferred":[
        "Zaoqiang"
    ],
    "name:rus_x_preferred":[
        "\u0426\u0437\u0430\u043e\u0446\u044f\u043d"
    ],
    "name:swe_x_preferred":[
        "Zaoqiang"
    ],
    "name:und_x_variant":[
        "Tsao-ch\u2019iang-ch\u2019eng-kuan",
        "Ts\u2019ao-ch\u2019iang",
        "Tsaokianghsien",
        "Tsao-ch\u2019iang-hsien",
        "Tszaotsyan",
        "Zaoqiang"
    ],
    "name:urd_x_preferred":[
        "\u0632\u0627\u0648\u0686\u06cc\u0627\u0646\u06af \u06a9\u0627\u0624\u0646\u0679\u06cc"
    ],
    "name:vie_x_preferred":[
        "T\u1ea3o C\u01b0\u1eddng"
    ],
    "name:zho_x_preferred":[
        "\u67a3\u5f3a\u53bf"
    ],
    "wof:name":"Zaoqiang",
    "wof:placetype":"locality"
},
  "geometry": {"coordinates":[115.71583,37.50611],"type":"Point"}
}