{
  "type": "Feature",
  "properties": {
    "gn:admin1_code":"10.0",
    "gn:asciiname":"Zaoqiang",
    "gn:cc2":"CN",
    "gn:country_code":"CN",
    "gn:dem":28,
    "gn:feature_class":"P",
    "gn:feature_code":"PPL",
    "gn:name":"Zaoqiang",
    "gn:population":0,
    "gn:timezone":"Asia/Shanghai",
    "iso:country":"CN",
    "name:und_x_variant":[
        "Tsao-ch\u2019iang-ch\u2019eng-kuan",
        "Ts\u2019ao-ch\u2019iang",
        "Tsaokianghsien",
        "Tsao-ch\u2019iang-hsien",
        "Tszaotsyan",
        "Zaoqiang"
    ],
    "wof:name":"Zaoqiang",
    "wof:placetype":"locality"
},
  "geometry": {"coordinates":[115.71583,37.50611],"type":"Point"}
}