{
  "type": "Feature",
  "properties": {
    "gn:admin1_code":"29.0",
    "gn:asciiname":"Mobu",
    "gn:country_code":"CN",
    "gn:dem":1675,
    "gn:feature_class":"P",
    "gn:feature_code":"PPL",
    "gn:name":"Mobu",
    "gn:population":0,
    "gn:timezone":"Asia/Shanghai",
    "iso:country":"CN",
    "name:zho_x_preferred":[
        "\u83ab\u535c"
    ],
    "wof:name":"Mobu",
    "wof:placetype":"locality"
},
  "geometry": {"coordinates":[102.343,23.1229],"type":"Point"}
}