{
  "type": "Feature",
  "properties": {
    "gn:admin1_code":"25",
    "gn:asciiname":"Waliwang",
    "gn:country_code":"CN",
    "gn:dem":13,
    "gn:feature_class":"P",
    "gn:feature_code":"PPL",
    "gn:name":"Waliwang",
    "gn:population":0,
    "gn:timezone":"Asia/Shanghai",
    "iso:country":"CN",
    "name:zho_x_preferred":[
        "\u6d3c\u91cc\u738b"
    ],
    "wof:name":"Waliwang",
    "wof:placetype":"locality"
},
  "geometry": {"coordinates":[117.03,37.544],"type":"Point"}
}