{
  "type": "Feature",
  "properties": {
    "gn:admin1_code":"19.0",
    "gn:asciiname":"Heping",
    "gn:country_code":"CN",
    "gn:dem":30,
    "gn:feature_class":"P",
    "gn:feature_code":"PPL",
    "gn:name":"Heping",
    "gn:population":0,
    "gn:timezone":"Asia/Shanghai",
    "iso:country":"CN",
    "name:und_x_variant":[
        "\u548c\u5e73"
    ],
    "name:zho_x_preferred":[
        "\u548c\u5e73"
    ],
    "wof:name":"Heping",
    "wof:placetype":"locality"
},
  "geometry": {"coordinates":[122.34811000000001,41.86018],"type":"Point"}
}