{
  "type": "Feature",
  "properties": {
    "gn:admin1_code":"2.0",
    "gn:asciiname":"Yangxi",
    "gn:country_code":"CN",
    "gn:dem":1,
    "gn:feature_class":"P",
    "gn:feature_code":"PPL",
    "gn:name":"Yangxi",
    "gn:population":0,
    "gn:timezone":"Asia/Shanghai",
    "iso:country":"CN",
    "name:ceb_x_preferred":[
        "Yangxi"
    ],
    "name:deu_x_preferred":[
        "Yangxi"
    ],
    "name:und_x_variant":[
        "Yang-hsi",
        "\u6d0b\u6eaa"
    ],
    "name:zho_x_preferred":[
        "\u6d0b\u6eaa\u9547"
    ],
    "wof:name":"Yangxi",
    "wof:placetype":"locality"
},
  "geometry": {"coordinates":[119.30943000000001,29.51104],"type":"Point"}
}