{
  "type": "Feature",
  "properties": {
    "gn:admin1_code":"29.0",
    "gn:asciiname":"Lijiaba",
    "gn:country_code":"CN",
    "gn:dem":1837,
    "gn:feature_class":"P",
    "gn:feature_code":"PPL",
    "gn:name":"Lijiaba",
    "gn:population":0,
    "gn:timezone":"Asia/Shanghai",
    "iso:country":"CN",
    "name:zho_x_preferred":[
        "\u9ece\u5bb6\u575d"
    ],
    "wof:name":"Lijiaba",
    "wof:placetype":"locality"
},
  "geometry": {"coordinates":[103.77200000000001,24.741],"type":"Point"}
}