{
  "type": "Feature",
  "properties": {
    "gn:admin1_code":"5.0",
    "gn:asciiname":"Piaoyangcun",
    "gn:country_code":"CN",
    "gn:dem":185,
    "gn:feature_class":"P",
    "gn:feature_code":"PPL",
    "gn:name":"Piaoyangcun",
    "gn:population":0,
    "gn:timezone":"Asia/Shanghai",
    "iso:country":"CN",
    "name:zho_x_preferred":[
        "\u6f02\u6d0b\u6751"
    ],
    "wof:name":"Piaoyangcun",
    "wof:placetype":"locality"
},
  "geometry": {"coordinates":[126.27911,43.96456],"type":"Point"}
}