{
  "type": "Feature",
  "properties": {
    "gn:admin1_code":"16.0",
    "gn:asciiname":"Dachuanlong",
    "gn:country_code":"CN",
    "gn:dem":24,
    "gn:feature_class":"P",
    "gn:feature_code":"PPL",
    "gn:name":"Dachuanlong",
    "gn:population":0,
    "gn:timezone":"Asia/Shanghai",
    "iso:country":"CN",
    "name:zho_x_preferred":[
        "\u6253\u8239\u7abf"
    ],
    "wof:name":"Dachuanlong",
    "wof:placetype":"locality"
},
  "geometry": {"coordinates":[108.449,21.7678],"type":"Point"}
}