{
  "type": "Feature",
  "properties": {
    "gn:admin1_code":"26.0",
    "gn:asciiname":"Zhujiahe",
    "gn:country_code":"CN",
    "gn:dem":1100,
    "gn:feature_class":"P",
    "gn:feature_code":"PPL",
    "gn:name":"Zhujiahe",
    "gn:population":0,
    "gn:timezone":"Asia/Shanghai",
    "iso:country":"CN",
    "name:und_x_variant":[
        "\u6731\u5bb6\u6cb3"
    ],
    "wof:name":"Zhujiahe",
    "wof:placetype":"locality"
},
  "geometry": {"coordinates":[106.12547000000001,32.81662],"type":"Point"}
}