{
  "type": "Feature",
  "properties": {
    "gn:admin1_code":"09",
    "gn:asciiname":"Dawangji",
    "gn:cc2":"CN",
    "gn:country_code":"CN",
    "gn:dem":128,
    "gn:feature_class":"P",
    "gn:feature_code":"PPL",
    "gn:name":"Dawangji",
    "gn:population":0,
    "gn:timezone":"Asia/Shanghai",
    "iso:country":"CN",
    "name:und_x_variant":[
        "Ta-wang-chi",
        "Dawangji"
    ],
    "wof:name":"Dawangji",
    "wof:placetype":"locality"
},
  "geometry": {"coordinates":[112.88306,32.83028],"type":"Point"}
}