{
  "type": "Feature",
  "properties": {
    "gn:admin1_code":"32.0",
    "gn:asciiname":"Rijing",
    "gn:country_code":"CN",
    "gn:dem":2378,
    "gn:feature_class":"P",
    "gn:feature_code":"PPL",
    "gn:name":"Rijing",
    "gn:population":0,
    "gn:timezone":"Asia/Shanghai",
    "iso:country":"CN",
    "name:zho_x_preferred":[
        "\u65e5\u4eac"
    ],
    "wof:name":"Rijing",
    "wof:placetype":"locality"
},
  "geometry": {"coordinates":[103.155,31.6618],"type":"Point"}
}