{
  "type": "Feature",
  "properties": {
    "gn:admin1_code":"14.0",
    "gn:asciiname":"Zequnuomacun",
    "gn:country_code":"CN",
    "gn:dem":4044,
    "gn:feature_class":"P",
    "gn:feature_code":"PPL",
    "gn:name":"Zequnuomacun",
    "gn:population":0,
    "gn:timezone":"Asia/Urumqi",
    "iso:country":"CN",
    "name:zho_x_preferred":[
        "\u5219\u66f2\u632a\u739b\u6751"
    ],
    "wof:name":"Zequnuomacun",
    "wof:placetype":"locality"
},
  "geometry": {"coordinates":[97.54272,30.97418],"type":"Point"}
}