{
  "type": "Feature",
  "properties": {
    "gn:admin1_code":"14.0",
    "gn:asciiname":"Guozhacun",
    "gn:country_code":"CN",
    "gn:dem":3296,
    "gn:feature_class":"P",
    "gn:feature_code":"PPL",
    "gn:name":"Guozhacun",
    "gn:population":0,
    "gn:timezone":"Asia/Urumqi",
    "iso:country":"CN",
    "name:zho_x_preferred":[
        "\u90ed\u624e\u6751"
    ],
    "wof:name":"Guozhacun",
    "wof:placetype":"locality"
},
  "geometry": {"coordinates":[92.57899999999999,29.15317000000001],"type":"Point"}
}