{
  "type": "Feature",
  "properties": {
    "gn:admin1_code":"16.0",
    "gn:asciiname":"Yaozuo",
    "gn:country_code":"CN",
    "gn:dem":386,
    "gn:feature_class":"P",
    "gn:feature_code":"PPL",
    "gn:name":"Yaozuo",
    "gn:population":0,
    "gn:timezone":"Asia/Shanghai",
    "iso:country":"CN",
    "name:zho_x_preferred":[
        "\u5c27\u4f50"
    ],
    "wof:name":"Yaozuo",
    "wof:placetype":"locality"
},
  "geometry": {"coordinates":[108.932,25.3727],"type":"Point"}
}