{
  "type": "Feature",
  "properties": {
    "gn:admin1_code":"04",
    "gn:asciiname":"Ligangcun",
    "gn:country_code":"CN",
    "gn:dem":6,
    "gn:feature_class":"P",
    "gn:feature_code":"PPL",
    "gn:name":"Ligangcun",
    "gn:population":0,
    "gn:timezone":"Asia/Shanghai",
    "iso:country":"CN",
    "name:und_x_variant":[
        "Ligang"
    ],
    "name:zho_x_preferred":[
        "\u674e\u6e2f\u6751"
    ],
    "name:zho_x_variant":[
        "\u674e\u6e2f"
    ],
    "wof:name":"Ligangcun",
    "wof:placetype":"locality"
},
  "geometry": {"coordinates":[120.69329999999999,32.07031],"type":"Point"}
}