{
  "type": "Feature",
  "properties": {
    "gn:admin1_code":"30.0",
    "gn:asciiname":"Ba'ercun",
    "gn:country_code":"CN",
    "gn:dem":3,
    "gn:feature_class":"P",
    "gn:feature_code":"PPL",
    "gn:name":"Ba\u2019ercun",
    "gn:population":0,
    "gn:timezone":"Asia/Shanghai",
    "iso:country":"CN",
    "name:zho_x_preferred":[
        "\u516b\u4e8c\u6751"
    ],
    "name:zho_x_variant":[
        "Ba\u2019ercun"
    ],
    "wof:name":"Ba'ercun",
    "wof:placetype":"locality"
},
  "geometry": {"coordinates":[112.05909,21.80302],"type":"Point"}
}