{
  "type": "Feature",
  "properties": {
    "gn:admin1_code":"25.0",
    "gn:asciiname":"Tiangezhuang",
    "gn:country_code":"CN",
    "gn:dem":16,
    "gn:feature_class":"P",
    "gn:feature_code":"PPL",
    "gn:name":"Tiangezhuang",
    "gn:population":0,
    "gn:timezone":"Asia/Shanghai",
    "iso:country":"CN",
    "name:zho_x_preferred":[
        "\u7530\u6208\u5e84"
    ],
    "wof:name":"Tiangezhuang",
    "wof:placetype":"locality"
},
  "geometry": {"coordinates":[119.57648,36.54907],"type":"Point"}
}