{
  "type": "Feature",
  "properties": {
    "gn:admin1_code":"20.0",
    "gn:asciiname":"Majia Lindi",
    "gn:country_code":"CN",
    "gn:dem":1484,
    "gn:feature_class":"P",
    "gn:feature_code":"PPL",
    "gn:name":"Majia Lindi",
    "gn:population":0,
    "gn:timezone":"Asia/Shanghai",
    "iso:country":"CN",
    "name:und_x_variant":[
        "\u9a6c\u5bb6\u6797\u5730"
    ],
    "wof:name":"Majia Lindi",
    "wof:placetype":"locality"
},
  "geometry": {"coordinates":[113.55051,40.72785],"type":"Point"}
}