{
  "type": "Feature",
  "properties": {
    "gn:admin1_code":"33.0",
    "gn:asciiname":"Guanqing",
    "gn:country_code":"CN",
    "gn:dem":391,
    "gn:feature_class":"P",
    "gn:feature_code":"PPLA4",
    "gn:name":"Guanqing",
    "gn:population":0,
    "gn:timezone":"Asia/Shanghai",
    "iso:country":"CN",
    "name:und_x_variant":[
        "Guanqing Xiang",
        "Jinjiaba"
    ],
    "name:zho_x_preferred":[
        "\u5b98\u6e05"
    ],
    "name:zho_x_variant":[
        "\u5b98\u6e05\u4e61",
        "\u91d1\u5bb6\u575d"
    ],
    "wof:name":"Guanqing",
    "wof:placetype":"locality"
},
  "geometry": {"coordinates":[108.68674,28.61946],"type":"Point"}
}