{
  "type": "Feature",
  "properties": {
    "gn:admin1_code":"18",
    "gn:asciiname":"Banyan",
    "gn:country_code":"CN",
    "gn:dem":1428,
    "gn:feature_class":"P",
    "gn:feature_code":"PPL",
    "gn:name":"Banyan",
    "gn:population":0,
    "gn:timezone":"Asia/Shanghai",
    "iso:country":"CN",
    "name:zho_x_preferred":[
        "\u677f\u70df"
    ],
    "wof:name":"Banyan",
    "wof:placetype":"locality"
},
  "geometry": {"coordinates":[105.301,25.2473],"type":"Point"}
}