{
  "type": "Feature",
  "properties": {
    "gn:admin1_code":"18",
    "gn:asciiname":"Banyan",
    "gn:country_code":"CN",
    "gn:dem":1428,
    "gn:feature_class":"P",
    "gn:feature_code":"PPL",
    "gn:name":"Banyan",
    "gn:population":0,
    "gn:timezone":"Asia/Shanghai",
    "iso:country":"CN",
    "name:ara_x_preferred":[
        "\u062a\u064a\u0646 \u0627\u0644\u0647\u0646\u062f"
    ],
    "name:bis_x_preferred":[
        "Banian"
    ],
    "name:cat_x_preferred":[
        "Bani\u00e0"
    ],
    "name:cdo_x_preferred":[
        "S\u1e73\u0300ng-ch\u00e9u"
    ],
    "name:div_x_preferred":[
        "\u0784\u07a6\u0782\u07b0\u0794\u07a6\u0782\u07b0"
    ],
    "name:epo_x_preferred":[
        "Banjano"
    ],
    "name:fas_x_preferred":[
        "\u0627\u0646\u062c\u06cc\u0631 \u0647\u0646\u062f\u06cc"
    ],
    "name:hin_x_preferred":[
        "\u092c\u0930\u0917\u0926"
    ],
    "name:hun_x_preferred":[
        "Bany\u00e1n"
    ],
    "name:kan_x_preferred":[
        "\u0c86\u0cb2\u0ca6 \u0cae\u0cb0"
    ],
    "name:kir_x_preferred":[
        "\u0411\u0430\u043d\u044c\u044f\u043d"
    ],
    "name:mal_x_preferred":[
        "\u0d06\u0d7d\u0d2e\u0d30\u0d02"
    ],
    "name:mya_x_preferred":[
        "\u100a\u1031\u102c\u1004\u103a\u1015\u1004\u103a"
    ],
    "name:nno_x_preferred":[
        "Banyan"
    ],
    "name:nor_x_preferred":[
        "Banyan"
    ],
    "name:ori_x_preferred":[
        "\u0b2c\u0b30\u0b17\u0b1b"
    ],
    "name:pan_x_preferred":[
        "\u0a2c\u0a4b\u0a39\u0a5c"
    ],
    "name:pnb_x_preferred":[
        "\u0628\u0648\u06c1\u0691"
    ],
    "name:ron_x_preferred":[
        "Banian"
    ],
    "name:san_x_preferred":[
        "\u0935\u0943\u0924\u094d\u0924\u093f\u0938\u093e\u0930\u0942\u092a\u094d\u092f\u092e\u093f\u0924\u0930\u0924\u094d\u0930"
    ],
    "name:spa_x_preferred":[
        "Baniano"
    ],
    "name:swe_x_preferred":[
        "Banjantr\u00e4d"
    ],
    "name:tgl_x_preferred":[
        "Balite"
    ],
    "name:tha_x_preferred":[
        "\u0e1a\u0e31\u0e19\u0e22\u0e31\u0e19"
    ],
    "name:urd_x_preferred":[
        "\u0628\u0631\u06af\u062f"
    ],
    "name:uzb_x_preferred":[
        "Banyan"
    ],
    "name:zho_x_preferred":[
        "\u677f\u70df"
    ],
    "name:zho_x_variant":[
        "\u6995\u4e9e\u5c6c"
    ],
    "wof:name":"Banyan",
    "wof:placetype":"locality"
},
  "geometry": {"coordinates":[105.301,25.2473],"type":"Point"}
}