{
  "type": "Feature",
  "properties": {
    "gn:admin1_code":"19.0",
    "gn:asciiname":"Shizilingcun",
    "gn:country_code":"CN",
    "gn:dem":80,
    "gn:feature_class":"P",
    "gn:feature_code":"PPL",
    "gn:name":"Shizilingcun",
    "gn:population":0,
    "gn:timezone":"Asia/Shanghai",
    "iso:country":"CN",
    "name:zho_x_preferred":[
        "\u72ee\u5b50\u5cad\u6751"
    ],
    "wof:name":"Shizilingcun",
    "wof:placetype":"locality"
},
  "geometry": {"coordinates":[120.93886999999999,41.15734000000001],"type":"Point"}
}