{
  "type": "Feature",
  "properties": {
    "gn:admin1_code":"19.0",
    "gn:asciiname":"Nanzhangjiacun",
    "gn:country_code":"CN",
    "gn:dem":104,
    "gn:feature_class":"P",
    "gn:feature_code":"PPL",
    "gn:name":"Nanzhangjiacun",
    "gn:population":0,
    "gn:timezone":"Asia/Shanghai",
    "iso:country":"CN",
    "name:zho_x_preferred":[
        "\u5357\u5f20\u5bb6\u6751"
    ],
    "wof:name":"Nanzhangjiacun",
    "wof:placetype":"locality"
},
  "geometry": {"coordinates":[124.06388,42.7429],"type":"Point"}
}