{
  "type": "Feature",
  "properties": {
    "gn:admin1_code":"21.0",
    "gn:asciiname":"Laoguanwan",
    "gn:country_code":"CN",
    "gn:dem":1911,
    "gn:feature_class":"P",
    "gn:feature_code":"PPL",
    "gn:name":"Laoguanwan",
    "gn:population":0,
    "gn:timezone":"Asia/Shanghai",
    "iso:country":"CN",
    "name:zho_x_preferred":[
        "\u8001\u5173\u6e7e"
    ],
    "wof:name":"Laoguanwan",
    "wof:placetype":"locality"
},
  "geometry": {"coordinates":[105.98999999999999,36.0267],"type":"Point"}
}