{
  "type": "Feature",
  "properties": {
    "gn:admin1_code":"1.0",
    "gn:asciiname":"Nanwangzhaicun",
    "gn:country_code":"CN",
    "gn:dem":35,
    "gn:feature_class":"P",
    "gn:feature_code":"PPL",
    "gn:name":"Nanwangzhaicun",
    "gn:population":0,
    "gn:timezone":"Asia/Shanghai",
    "iso:country":"CN",
    "name:zho_x_preferred":[
        "\u5357\u738b\u5be8\u6751"
    ],
    "wof:name":"Nanwangzhaicun",
    "wof:placetype":"locality"
},
  "geometry": {"coordinates":[115.81592999999999,33.30503],"type":"Point"}
}