{
  "type": "Feature",
  "properties": {
    "gn:admin1_code":"11",
    "gn:asciiname":"Maogou",
    "gn:country_code":"CN",
    "gn:dem":297,
    "gn:feature_class":"P",
    "gn:feature_code":"PPLA4",
    "gn:name":"Maogou",
    "gn:population":0,
    "gn:timezone":"Asia/Shanghai",
    "iso:country":"CN",
    "name:und_x_variant":[
        "Mao-kou-chai",
        "Maogou",
        "Maogou Zhen"
    ],
    "name:zho_x_preferred":[
        "\u6bdb\u6c9f"
    ],
    "name:zho_x_variant":[
        "\u6bdb\u6c9f\u9547"
    ],
    "wof:name":"Maogou",
    "wof:placetype":"locality"
},
  "geometry": {"coordinates":[109.37430999999999,28.60098],"type":"Point"}
}