{
  "type": "Feature",
  "properties": {
    "gn:admin1_code":"9.0",
    "gn:asciiname":"Wangjiaya",
    "gn:country_code":"CN",
    "gn:dem":801,
    "gn:feature_class":"P",
    "gn:feature_code":"PPL",
    "gn:name":"Wangjiaya",
    "gn:population":0,
    "gn:timezone":"Asia/Shanghai",
    "iso:country":"CN",
    "name:zho_x_preferred":[
        "\u738b\u5bb6\u5d16"
    ],
    "wof:name":"Wangjiaya",
    "wof:placetype":"locality"
},
  "geometry": {"coordinates":[111.03561999999999,34.53363],"type":"Point"}
}