{
  "type": "Feature",
  "properties": {
    "gn:admin1_code":"32.0",
    "gn:asciiname":"Nianyin'an",
    "gn:country_code":"CN",
    "gn:dem":320,
    "gn:feature_class":"P",
    "gn:feature_code":"PPL",
    "gn:name":"Nianyin\u2019an",
    "gn:population":0,
    "gn:timezone":"Asia/Shanghai",
    "iso:country":"CN",
    "name:zho_x_preferred":[
        "\u5e74\u94f6\u5b89"
    ],
    "name:zho_x_variant":[
        "Nianyin\u2019an"
    ],
    "wof:name":"Nianyin'an",
    "wof:placetype":"locality"
},
  "geometry": {"coordinates":[107.21952,30.33053],"type":"Point"}
}