{
  "type": "Feature",
  "properties": {
    "gn:admin1_code":"1.0",
    "gn:asciiname":"Xiangpucun",
    "gn:country_code":"CN",
    "gn:dem":302,
    "gn:feature_class":"P",
    "gn:feature_code":"PPL",
    "gn:name":"Xiangpucun",
    "gn:population":0,
    "gn:timezone":"Asia/Shanghai",
    "iso:country":"CN",
    "name:zho_x_preferred":[
        "\u9999\u94fa\u6751"
    ],
    "wof:name":"Xiangpucun",
    "wof:placetype":"locality"
},
  "geometry": {"coordinates":[115.49292,31.43707],"type":"Point"}
}