{
  "type": "Feature",
  "properties": {
    "gn:admin1_code":"19.0",
    "gn:asciiname":"Mangniuyingzicun",
    "gn:country_code":"CN",
    "gn:dem":155,
    "gn:feature_class":"P",
    "gn:feature_code":"PPL",
    "gn:name":"Mangniuyingzicun",
    "gn:population":0,
    "gn:timezone":"Asia/Shanghai",
    "iso:country":"CN",
    "name:zho_x_preferred":[
        "\u7264\u725b\u8425\u5b50\u6751"
    ],
    "wof:name":"Mangniuyingzicun",
    "wof:placetype":"locality"
},
  "geometry": {"coordinates":[120.64400000000001,41.581],"type":"Point"}
}