{
  "type": "Feature",
  "properties": {
    "gn:admin1_code":"12.0",
    "gn:asciiname":"Xiayang",
    "gn:country_code":"CN",
    "gn:dem":35,
    "gn:feature_class":"P",
    "gn:feature_code":"PPL",
    "gn:name":"Xiayang",
    "gn:population":0,
    "gn:timezone":"Asia/Shanghai",
    "iso:country":"CN",
    "name:zho_x_preferred":[
        "Xiayang"
    ],
    "name:zho_x_variant":[
        "\u4e0b\u7f8a"
    ],
    "wof:name":"Xiayang",
    "wof:placetype":"locality"
},
  "geometry": {"coordinates":[115.35321,29.81316],"type":"Point"}
}