{
  "type": "Feature",
  "properties": {
    "gn:admin1_code":"11",
    "gn:asciiname":"Taipingxu",
    "gn:country_code":"CN",
    "gn:dem":263,
    "gn:feature_class":"P",
    "gn:feature_code":"PPLA4",
    "gn:name":"Taipingxu",
    "gn:population":0,
    "gn:timezone":"Asia/Shanghai",
    "iso:country":"CN",
    "name:und_x_variant":[
        "T\u2019ai-p\u2019ing-hs\u00fc",
        "Taiping",
        "Taipingxu",
        "\u592a\u5e73\u5729",
        "Taipingxu Xiang",
        "\u592a\u5e73\u5729\u4e61"
    ],
    "wof:name":"Taipingxu",
    "wof:placetype":"locality"
},
  "geometry": {"coordinates":[112.32805999999999,25.47444],"type":"Point"}
}