{
  "type": "Feature",
  "properties": {
    "gn:admin1_code":"24.0",
    "gn:asciiname":"Sigou",
    "gn:country_code":"CN",
    "gn:dem":974,
    "gn:feature_class":"P",
    "gn:feature_code":"PPL",
    "gn:name":"Sigou",
    "gn:population":0,
    "gn:timezone":"Asia/Shanghai",
    "iso:country":"CN",
    "name:zho_x_preferred":[
        "\u5bfa\u6c9f"
    ],
    "wof:name":"Sigou",
    "wof:placetype":"locality"
},
  "geometry": {"coordinates":[112.76716,35.81180999999999],"type":"Point"}
}