{
  "type": "Feature",
  "properties": {
    "gn:admin1_code":"3.0",
    "gn:asciiname":"Huapengdi",
    "gn:country_code":"CN",
    "gn:dem":126,
    "gn:feature_class":"P",
    "gn:feature_code":"PPL",
    "gn:name":"Huapengdi",
    "gn:population":0,
    "gn:timezone":"Asia/Shanghai",
    "iso:country":"CN",
    "name:zho_x_preferred":[
        "\u82b1\u68da\u5e95"
    ],
    "wof:name":"Huapengdi",
    "wof:placetype":"locality"
},
  "geometry": {"coordinates":[118.232,28.3781],"type":"Point"}
}