{
  "type": "Feature",
  "properties": {
    "gn:admin1_code":"11.0",
    "gn:asciiname":"Yanchaomen",
    "gn:country_code":"CN",
    "gn:dem":109,
    "gn:feature_class":"P",
    "gn:feature_code":"PPL",
    "gn:name":"Yanchaomen",
    "gn:population":0,
    "gn:timezone":"Asia/Shanghai",
    "iso:country":"CN",
    "name:zho_x_preferred":[
        "Yanchaomen"
    ],
    "name:zho_x_variant":[
        "\u5ca9\u671d\u95e8"
    ],
    "wof:name":"Yanchaomen",
    "wof:placetype":"locality"
},
  "geometry": {"coordinates":[111.21827,28.96858],"type":"Point"}
}