{
  "type": "Feature",
  "properties": {
    "gn:admin1_code":"5.0",
    "gn:asciiname":"Dasanduan",
    "gn:country_code":"CN",
    "gn:dem":183,
    "gn:feature_class":"P",
    "gn:feature_code":"PPL",
    "gn:name":"Dasanduan",
    "gn:population":0,
    "gn:timezone":"Asia/Shanghai",
    "iso:country":"CN",
    "name:zho_x_preferred":[
        "\u5927\u4e09\u6bb5"
    ],
    "wof:name":"Dasanduan",
    "wof:placetype":"locality"
},
  "geometry": {"coordinates":[122.3206,45.57718],"type":"Point"}
}