{
  "type": "Feature",
  "properties": {
    "gn:admin1_code":"29.0",
    "gn:asciiname":"Anfeng",
    "gn:country_code":"CN",
    "gn:dem":1702,
    "gn:feature_class":"P",
    "gn:feature_code":"PPL",
    "gn:name":"Anfeng",
    "gn:population":0,
    "gn:timezone":"Asia/Shanghai",
    "iso:country":"CN",
    "name:zho_x_preferred":[
        "\u5b89\u4e30"
    ],
    "wof:name":"Anfeng",
    "wof:placetype":"locality"
},
  "geometry": {"coordinates":[103.10899999999999,25.7917],"type":"Point"}
}