{
  "type": "Feature",
  "properties": {
    "gn:admin1_code":"16.0",
    "gn:asciiname":"Jiangfeng",
    "gn:country_code":"CN",
    "gn:dem":127,
    "gn:feature_class":"P",
    "gn:feature_code":"PPL",
    "gn:name":"Jiangfeng",
    "gn:population":0,
    "gn:timezone":"Asia/Shanghai",
    "iso:country":"CN",
    "name:zho_x_preferred":[
        "\u6c5f\u51e4"
    ],
    "wof:name":"Jiangfeng",
    "wof:placetype":"locality"
},
  "geometry": {"coordinates":[106.64100000000001,23.8346],"type":"Point"}
}