{
  "type": "Feature",
  "properties": {
    "gn:admin1_code":"21.0",
    "gn:asciiname":"Dongjiawan",
    "gn:country_code":"CN",
    "gn:dem":1563,
    "gn:feature_class":"P",
    "gn:feature_code":"PPL",
    "gn:name":"Dongjiawan",
    "gn:population":0,
    "gn:timezone":"Asia/Shanghai",
    "iso:country":"CN",
    "name:zho_x_preferred":[
        "\u8463\u5bb6\u6e7e"
    ],
    "wof:name":"Dongjiawan",
    "wof:placetype":"locality"
},
  "geometry": {"coordinates":[106.47799999999999,35.985],"type":"Point"}
}