{
  "type": "Feature",
  "properties": {
    "gn:admin1_code":"29.0",
    "gn:asciiname":"Lizi",
    "gn:country_code":"CN",
    "gn:dem":1523,
    "gn:feature_class":"P",
    "gn:feature_code":"PPL",
    "gn:name":"Lizi",
    "gn:population":0,
    "gn:timezone":"Asia/Shanghai",
    "iso:country":"CN",
    "name:azb_x_preferred":[
        "\u0644\u06cc\u0632\u06cc"
    ],
    "name:fas_x_preferred":[
        "\u0644\u06cc\u0632\u06cc"
    ],
    "name:zho_x_preferred":[
        "\u674e\u5b50"
    ],
    "wof:name":"Lizi",
    "wof:placetype":"locality"
},
  "geometry": {"coordinates":[100.42,24.5768],"type":"Point"}
}