{
  "type": "Feature",
  "properties": {
    "gn:admin1_code":"21.0",
    "gn:asciiname":"Nanbuzi",
    "gn:country_code":"CN",
    "gn:dem":1974,
    "gn:feature_class":"P",
    "gn:feature_code":"PPL",
    "gn:name":"Nanbuzi",
    "gn:population":0,
    "gn:timezone":"Asia/Shanghai",
    "iso:country":"CN",
    "name:zho_x_preferred":[
        "\u5357\u5821\u5b50"
    ],
    "wof:name":"Nanbuzi",
    "wof:placetype":"locality"
},
  "geometry": {"coordinates":[106.009,35.8015],"type":"Point"}
}