{
  "type": "Feature",
  "properties": {
    "gn:admin1_code":"1.0",
    "gn:asciiname":"Sili Zhongcun",
    "gn:country_code":"CN",
    "gn:dem":32,
    "gn:feature_class":"P",
    "gn:feature_code":"PPL",
    "gn:name":"Sili Zhongcun",
    "gn:population":0,
    "gn:timezone":"Asia/Shanghai",
    "iso:country":"CN",
    "name:zho_x_preferred":[
        "\u56db\u91cc\u4e2d\u6751"
    ],
    "wof:name":"Sili Zhongcun",
    "wof:placetype":"locality"
},
  "geometry": {"coordinates":[117.09862,33.76494],"type":"Point"}
}