{
  "type": "Feature",
  "properties": {
    "gn:admin1_code":"11.0",
    "gn:asciiname":"Zongmuqiao",
    "gn:country_code":"CN",
    "gn:dem":138,
    "gn:feature_class":"P",
    "gn:feature_code":"PPL",
    "gn:name":"Zongmuqiao",
    "gn:population":0,
    "gn:timezone":"Asia/Shanghai",
    "iso:country":"CN",
    "name:zho_x_preferred":[
        "\u68d5\u6728\u6865"
    ],
    "wof:name":"Zongmuqiao",
    "wof:placetype":"locality"
},
  "geometry": {"coordinates":[112.54367000000001,27.28893],"type":"Point"}
}