{
  "type": "Feature",
  "properties": {
    "gn:admin1_code":"5.0",
    "gn:asciiname":"Qianshuang Yushu",
    "gn:country_code":"CN",
    "gn:dem":185,
    "gn:feature_class":"P",
    "gn:feature_code":"PPL",
    "gn:name":"Qianshuang Yushu",
    "gn:population":0,
    "gn:timezone":"Asia/Shanghai",
    "iso:country":"CN",
    "name:zho_x_preferred":[
        "\u524d\u53cc\u6986\u6811"
    ],
    "wof:name":"Qianshuang Yushu",
    "wof:placetype":"locality"
},
  "geometry": {"coordinates":[125.22769,44.21056],"type":"Point"}
}