{
  "type": "Feature",
  "properties": {
    "gn:admin1_code":"8.0",
    "gn:asciiname":"Yongfengcun",
    "gn:country_code":"CN",
    "gn:dem":64,
    "gn:feature_class":"P",
    "gn:feature_code":"PPL",
    "gn:name":"Yongfengcun",
    "gn:population":0,
    "gn:timezone":"Asia/Shanghai",
    "iso:country":"CN",
    "name:zho_x_preferred":[
        "\u6c38\u4e30\u6751"
    ],
    "wof:name":"Yongfengcun",
    "wof:placetype":"locality"
},
  "geometry": {"coordinates":[131.66723000000002,47.4394],"type":"Point"}
}