{
  "type": "Feature",
  "properties": {
    "gn:admin1_code":"30.0",
    "gn:asciiname":"Bangtang",
    "gn:country_code":"CN",
    "gn:dem":111,
    "gn:feature_class":"P",
    "gn:feature_code":"PPL",
    "gn:name":"Bangtang",
    "gn:population":0,
    "gn:timezone":"Asia/Shanghai",
    "iso:country":"CN",
    "name:zho_x_preferred":[
        "\u699c\u5858"
    ],
    "wof:name":"Bangtang",
    "wof:placetype":"locality"
},
  "geometry": {"coordinates":[113.72,24.11944],"type":"Point"}
}