{
  "type": "Feature",
  "properties": {
    "gn:admin1_code":"32.0",
    "gn:asciiname":"Shigangba",
    "gn:country_code":"CN",
    "gn:dem":739,
    "gn:feature_class":"P",
    "gn:feature_code":"PPL",
    "gn:name":"Shigangba",
    "gn:population":0,
    "gn:timezone":"Asia/Shanghai",
    "iso:country":"CN",
    "name:zho_x_preferred":[
        "\u77f3\u5c97\u575d"
    ],
    "wof:name":"Shigangba",
    "wof:placetype":"locality"
},
  "geometry": {"coordinates":[103.47797,28.89086],"type":"Point"}
}