{
  "type": "Feature",
  "properties": {
    "gn:admin1_code":"12.0",
    "gn:asciiname":"Quanjiaoping",
    "gn:country_code":"CN",
    "gn:dem":300,
    "gn:feature_class":"P",
    "gn:feature_code":"PPL",
    "gn:name":"Quanjiaoping",
    "gn:population":0,
    "gn:timezone":"Asia/Shanghai",
    "iso:country":"CN",
    "name:zho_x_preferred":[
        "Quanjiaoping"
    ],
    "name:zho_x_variant":[
        "\u5168\u89d2\u576a"
    ],
    "wof:name":"Quanjiaoping",
    "wof:placetype":"locality"
},
  "geometry": {"coordinates":[111.09148,30.62513],"type":"Point"}
}