{
  "type": "Feature",
  "properties": {
    "gn:admin1_code":"10",
    "gn:asciiname":"Beigoumen",
    "gn:country_code":"CN",
    "gn:dem":492,
    "gn:feature_class":"P",
    "gn:feature_code":"PPL",
    "gn:name":"Beigoumen",
    "gn:population":0,
    "gn:timezone":"Asia/Shanghai",
    "iso:country":"CN",
    "name:zho_x_preferred":[
        "\u5317\u6c9f\u95e8"
    ],
    "wof:name":"Beigoumen",
    "wof:placetype":"locality"
},
  "geometry": {"coordinates":[117.34183,41.04245],"type":"Point"}
}