{
  "type": "Feature",
  "properties": {
    "gn:admin1_code":"18",
    "gn:asciiname":"Luoyan",
    "gn:country_code":"CN",
    "gn:dem":740,
    "gn:feature_class":"P",
    "gn:feature_code":"PPL",
    "gn:name":"Luoyan",
    "gn:population":0,
    "gn:timezone":"Asia/Shanghai",
    "iso:country":"CN",
    "name:zho_x_preferred":[
        "\u843d\u70df"
    ],
    "wof:name":"Luoyan",
    "wof:placetype":"locality"
},
  "geometry": {"coordinates":[105.833,25.4048],"type":"Point"}
}