{
  "type": "Feature",
  "properties": {
    "gn:admin1_code":"3.0",
    "gn:asciiname":"Mansi'ao",
    "gn:country_code":"CN",
    "gn:dem":626,
    "gn:feature_class":"P",
    "gn:feature_code":"PPL",
    "gn:name":"Mansi\u2019ao",
    "gn:population":0,
    "gn:timezone":"Asia/Shanghai",
    "iso:country":"CN",
    "name:und_x_variant":[
        "Mansi\u2019ao"
    ],
    "name:zho_x_preferred":[
        "\u6162\u601d\u5773"
    ],
    "wof:name":"Mansi'ao",
    "wof:placetype":"locality"
},
  "geometry": {"coordinates":[114.684,28.9696],"type":"Point"}
}