{
  "type": "Feature",
  "properties": {
    "gn:admin1_code":"4.0",
    "gn:asciiname":"Zhangsong",
    "gn:country_code":"CN",
    "gn:dem":2,
    "gn:feature_class":"P",
    "gn:feature_code":"PPL",
    "gn:name":"Zhangsong",
    "gn:population":0,
    "gn:timezone":"Asia/Shanghai",
    "iso:country":"CN",
    "name:zho_x_preferred":[
        "Zhangsong"
    ],
    "name:zho_x_variant":[
        "\u5f20\u5b8b"
    ],
    "wof:name":"Zhangsong",
    "wof:placetype":"locality"
},
  "geometry": {"coordinates":[119.78004,33.15929000000001],"type":"Point"}
}