{
  "type": "Feature",
  "properties": {
    "gn:admin1_code":"8.0",
    "gn:asciiname":"Fangchengcun",
    "gn:country_code":"CN",
    "gn:dem":159,
    "gn:feature_class":"P",
    "gn:feature_code":"PPL",
    "gn:name":"Fangchengcun",
    "gn:population":0,
    "gn:timezone":"Asia/Shanghai",
    "iso:country":"CN",
    "name:zho_x_preferred":[
        "\u65b9\u57ce\u6751"
    ],
    "wof:name":"Fangchengcun",
    "wof:placetype":"locality"
},
  "geometry": {"coordinates":[126.8686,46.56677],"type":"Point"}
}