{
  "type": "Feature",
  "properties": {
    "gn:admin1_code":"7",
    "gn:asciiname":"Shenhu",
    "gn:country_code":"CN",
    "gn:dem":38,
    "gn:feature_class":"P",
    "gn:feature_code":"PPL",
    "gn:name":"Shenhu",
    "gn:population":0,
    "gn:timezone":"Asia/Shanghai",
    "iso:country":"CN",
    "name:zho_x_preferred":[
        "\u6df1\u6e56"
    ],
    "name:zho_x_variant":[
        "\u6df1\u6caa\u9547"
    ],
    "wof:name":"Shenhu",
    "wof:placetype":"locality"
},
  "geometry": {"coordinates":[117.04772,23.75574],"type":"Point"}
}