{
  "type": "Feature",
  "properties": {
    "gn:admin1_code":"3",
    "gn:asciiname":"Liulong",
    "gn:country_code":"CN",
    "gn:dem":347,
    "gn:feature_class":"P",
    "gn:feature_code":"PPL",
    "gn:name":"Liulong",
    "gn:population":0,
    "gn:timezone":"Asia/Shanghai",
    "iso:country":"CN",
    "name:und_x_variant":[
        "\u7559\u9f99"
    ],
    "wof:name":"Liulong",
    "wof:placetype":"locality"
},
  "geometry": {"coordinates":[115.44022,26.12521],"type":"Point"}
}