{
  "type": "Feature",
  "properties": {
    "gn:admin1_code":"5.0",
    "gn:asciiname":"Gaojiu Juzi",
    "gn:country_code":"CN",
    "gn:dem":159,
    "gn:feature_class":"P",
    "gn:feature_code":"PPL",
    "gn:name":"Gaojiu Juzi",
    "gn:population":0,
    "gn:timezone":"Asia/Shanghai",
    "iso:country":"CN",
    "name:zho_x_preferred":[
        "\u9ad8\u9152\u5c40\u5b50"
    ],
    "wof:name":"Gaojiu Juzi",
    "wof:placetype":"locality"
},
  "geometry": {"coordinates":[124.46147000000001,43.64366],"type":"Point"}
}