{
  "type": "Feature",
  "properties": {
    "gn:admin1_code":"19.0",
    "gn:asciiname":"Dongganhe",
    "gn:country_code":"CN",
    "gn:dem":10,
    "gn:feature_class":"P",
    "gn:feature_code":"PPL",
    "gn:name":"Dongganhe",
    "gn:population":0,
    "gn:timezone":"Asia/Shanghai",
    "iso:country":"CN",
    "name:und_x_variant":[
        "\u4e1c\u7518\u6cb3"
    ],
    "wof:name":"Dongganhe",
    "wof:placetype":"locality"
},
  "geometry": {"coordinates":[122.58262000000001,40.90702],"type":"Point"}
}