{
  "type": "Feature",
  "properties": {
    "gn:admin1_code":"10",
    "gn:asciiname":"Xiaosonglou",
    "gn:country_code":"CN",
    "gn:dem":97,
    "gn:feature_class":"P",
    "gn:feature_code":"PPL",
    "gn:name":"Xiaosonglou",
    "gn:population":0,
    "gn:timezone":"Asia/Shanghai",
    "iso:country":"CN",
    "name:zho_x_preferred":[
        "\u5c0f\u5b8b\u697c"
    ],
    "wof:name":"Xiaosonglou",
    "wof:placetype":"locality"
},
  "geometry": {"coordinates":[114.36799999999999,37.9933],"type":"Point"}
}