{
  "type": "Feature",
  "properties": {
    "gn:admin1_code":"8.0",
    "gn:asciiname":"Datangcun",
    "gn:country_code":"CN",
    "gn:dem":298,
    "gn:feature_class":"P",
    "gn:feature_code":"PPL",
    "gn:name":"Datangcun",
    "gn:population":0,
    "gn:timezone":"Asia/Shanghai",
    "iso:country":"CN",
    "name:zho_x_preferred":[
        "\u5927\u5510\u6751"
    ],
    "wof:name":"Datangcun",
    "wof:placetype":"locality"
},
  "geometry": {"coordinates":[129.53616,44.28021],"type":"Point"}
}