{
  "type": "Feature",
  "properties": {
    "gn:admin1_code":"3.0",
    "gn:asciiname":"Tongyuanli",
    "gn:country_code":"CN",
    "gn:dem":271,
    "gn:feature_class":"P",
    "gn:feature_code":"PPL",
    "gn:name":"Tongyuanli",
    "gn:population":0,
    "gn:timezone":"Asia/Shanghai",
    "iso:country":"CN",
    "name:und_x_variant":[
        "\u540c\u5143\u91cc"
    ],
    "wof:name":"Tongyuanli",
    "wof:placetype":"locality"
},
  "geometry": {"coordinates":[116.14682000000001,26.62616],"type":"Point"}
}