{
  "type": "Feature",
  "properties": {
    "gn:admin1_code":"16",
    "gn:asciiname":"Huangtu",
    "gn:country_code":"CN",
    "gn:dem":154,
    "gn:feature_class":"P",
    "gn:feature_code":"PPL",
    "gn:name":"Huangtu",
    "gn:population":0,
    "gn:timezone":"Asia/Shanghai",
    "iso:country":"CN",
    "name:zho_x_preferred":[
        "\u9ec4\u571f"
    ],
    "wof:name":"Huangtu",
    "wof:placetype":"locality"
},
  "geometry": {"coordinates":[110.083,25.1214],"type":"Point"}
}