{
  "type": "Feature",
  "properties": {
    "gn:admin1_code":"9",
    "gn:asciiname":"Dishangliu",
    "gn:country_code":"CN",
    "gn:dem":52,
    "gn:feature_class":"P",
    "gn:feature_code":"PPL",
    "gn:name":"Dishangliu",
    "gn:population":0,
    "gn:timezone":"Asia/Shanghai",
    "iso:country":"CN",
    "name:zho_x_preferred":[
        "\u5824\u4e0a\u5218"
    ],
    "wof:name":"Dishangliu",
    "wof:placetype":"locality"
},
  "geometry": {"coordinates":[115.28473,35.92804],"type":"Point"}
}