{
  "type": "Feature",
  "properties": {
    "gn:admin1_code":"8.0",
    "gn:asciiname":"Boniangou",
    "gn:country_code":"CN",
    "gn:dem":169,
    "gn:feature_class":"P",
    "gn:feature_code":"PPL",
    "gn:name":"Boniangou",
    "gn:population":0,
    "gn:timezone":"Asia/Shanghai",
    "iso:country":"CN",
    "name:zho_x_preferred":[
        "\u535a\u78be\u6c9f"
    ],
    "wof:name":"Boniangou",
    "wof:placetype":"locality"
},
  "geometry": {"coordinates":[127.12513,45.30572],"type":"Point"}
}