{
  "type": "Feature",
  "properties": {
    "gn:admin1_code":"16.0",
    "gn:asciiname":"Wangbutang",
    "gn:country_code":"CN",
    "gn:dem":164,
    "gn:feature_class":"P",
    "gn:feature_code":"PPL",
    "gn:name":"Wangbutang",
    "gn:population":0,
    "gn:timezone":"Asia/Shanghai",
    "iso:country":"CN",
    "name:zho_x_preferred":[
        "\u65fa\u6b65\u5858"
    ],
    "wof:name":"Wangbutang",
    "wof:placetype":"locality"
},
  "geometry": {"coordinates":[110.31999999999999,23.049],"type":"Point"}
}