{
  "type": "Feature",
  "properties": {
    "gn:admin1_code":"31",
    "gn:asciiname":"Qinfeng",
    "gn:country_code":"CN",
    "gn:dem":7,
    "gn:feature_class":"P",
    "gn:feature_code":"PPL",
    "gn:name":"Qinfeng",
    "gn:population":0,
    "gn:timezone":"Asia/Shanghai",
    "iso:country":"CN",
    "name:und_x_variant":[
        "\u52e4\u4e30"
    ],
    "wof:name":"Qinfeng",
    "wof:placetype":"locality"
},
  "geometry": {"coordinates":[110.04159,18.50088],"type":"Point"}
}