{
  "type": "Feature",
  "properties": {
    "gn:admin1_code":"14.0",
    "gn:asciiname":"La'encun",
    "gn:country_code":"CN",
    "gn:dem":4463,
    "gn:feature_class":"P",
    "gn:feature_code":"PPL",
    "gn:name":"La\u2019encun",
    "gn:population":0,
    "gn:timezone":"Asia/Urumqi",
    "iso:country":"CN",
    "name:und_x_variant":[
        "La\u2019encun"
    ],
    "name:zho_x_preferred":[
        "\u62c9\u6069\u6751"
    ],
    "wof:name":"La'encun",
    "wof:placetype":"locality"
},
  "geometry": {"coordinates":[96.27677,31.49319],"type":"Point"}
}