{
  "type": "Feature",
  "properties": {
    "gn:admin1_code":"19.0",
    "gn:asciiname":"Xibeitian",
    "gn:country_code":"CN",
    "gn:dem":239,
    "gn:feature_class":"P",
    "gn:feature_code":"PPL",
    "gn:name":"Xibeitian",
    "gn:population":0,
    "gn:timezone":"Asia/Shanghai",
    "iso:country":"CN",
    "name:und_x_variant":[
        "\u897f\u5317\u5929"
    ],
    "wof:name":"Xibeitian",
    "wof:placetype":"locality"
},
  "geometry": {"coordinates":[122.807,40.01300000000001],"type":"Point"}
}