{
  "type": "Feature",
  "properties": {
    "gn:admin1_code":"4.0",
    "gn:asciiname":"Zhouxingzhuang",
    "gn:country_code":"CN",
    "gn:dem":1,
    "gn:feature_class":"P",
    "gn:feature_code":"PPL",
    "gn:name":"Zhouxingzhuang",
    "gn:population":0,
    "gn:timezone":"Asia/Shanghai",
    "iso:country":"CN",
    "name:und_x_variant":[
        "\u5468\u59d3\u5e84"
    ],
    "name:zho_x_preferred":[
        "\u5468\u59d3\u5e84"
    ],
    "wof:name":"Zhouxingzhuang",
    "wof:placetype":"locality"
},
  "geometry": {"coordinates":[120.4037,32.80954000000001],"type":"Point"}
}