{
  "type": "Feature",
  "properties": {
    "gn:admin1_code":"32.0",
    "gn:asciiname":"Dashi Bao'erzhai",
    "gn:country_code":"CN",
    "gn:dem":2048,
    "gn:feature_class":"P",
    "gn:feature_code":"PPL",
    "gn:name":"Dashi Bao\u2019erzhai",
    "gn:population":0,
    "gn:timezone":"Asia/Shanghai",
    "iso:country":"CN",
    "name:und_x_variant":[
        "Dashi Bao\u2019erzhai"
    ],
    "name:zho_x_preferred":[
        "\u5927\u77f3\u5305\u513f\u5be8"
    ],
    "wof:name":"Dashi Bao'erzhai",
    "wof:placetype":"locality"
},
  "geometry": {"coordinates":[103.178,31.4283],"type":"Point"}
}