{
  "type": "Feature",
  "properties": {
    "gn:admin1_code":"26.0",
    "gn:asciiname":"Yongning",
    "gn:cc2":"CN",
    "gn:country_code":"CN",
    "gn:dem":1318,
    "gn:feature_class":"P",
    "gn:feature_code":"PPL",
    "gn:name":"Yongning",
    "gn:population":0,
    "gn:timezone":"Asia/Shanghai",
    "iso:country":"CN",
    "name:und_x_variant":[
        "Yung-ning-chai",
        "Yung-ning",
        "Yung-ning-chen",
        "Yongning"
    ],
    "wof:name":"Yongning",
    "wof:placetype":"locality"
},
  "geometry": {"coordinates":[108.76667,36.56667],"type":"Point"}
}