{
  "type": "Feature",
  "properties": {
    "gn:admin1_code":"29",
    "gn:asciiname":"Laoshuijing",
    "gn:country_code":"CN",
    "gn:dem":1667,
    "gn:feature_class":"P",
    "gn:feature_code":"PPL",
    "gn:name":"Laoshuijing",
    "gn:population":0,
    "gn:timezone":"Asia/Shanghai",
    "iso:country":"CN",
    "name:zho_x_preferred":[
        "\u8001\u6c34\u4e95"
    ],
    "wof:name":"Laoshuijing",
    "wof:placetype":"locality"
},
  "geometry": {"coordinates":[105.06,23.7198],"type":"Point"}
}