{
  "type": "Feature",
  "properties": {
    "gn:admin1_code":"4.0",
    "gn:asciiname":"Ludongcun",
    "gn:country_code":"CN",
    "gn:dem":27,
    "gn:feature_class":"P",
    "gn:feature_code":"PPL",
    "gn:name":"Ludongcun",
    "gn:population":0,
    "gn:timezone":"Asia/Shanghai",
    "iso:country":"CN",
    "name:zho_x_preferred":[
        "\u9c81\u4e1c\u6751"
    ],
    "wof:name":"Ludongcun",
    "wof:placetype":"locality"
},
  "geometry": {"coordinates":[117.72499999999999,33.9988],"type":"Point"}
}