{
  "type": "Feature",
  "properties": {
    "gn:admin1_code":"1.0",
    "gn:asciiname":"Goushangcun",
    "gn:country_code":"CN",
    "gn:dem":41,
    "gn:feature_class":"P",
    "gn:feature_code":"PPL",
    "gn:name":"Goushangcun",
    "gn:population":0,
    "gn:timezone":"Asia/Shanghai",
    "iso:country":"CN",
    "name:zho_x_preferred":[
        "\u6c9f\u4e0a\u6751"
    ],
    "wof:name":"Goushangcun",
    "wof:placetype":"locality"
},
  "geometry": {"coordinates":[117.33078999999999,33.94579],"type":"Point"}
}