{
  "type": "Feature",
  "properties": {
    "gn:admin1_code":"14.0",
    "gn:asciiname":"Ranyong",
    "gn:country_code":"CN",
    "gn:dem":3729,
    "gn:feature_class":"P",
    "gn:feature_code":"PPL",
    "gn:name":"Ranyong",
    "gn:population":0,
    "gn:timezone":"Asia/Urumqi",
    "iso:country":"CN",
    "name:zho_x_preferred":[
        "\u7136\u52c7"
    ],
    "wof:name":"Ranyong",
    "wof:placetype":"locality"
},
  "geometry": {"coordinates":[97.40637,30.89435],"type":"Point"}
}