{
  "type": "Feature",
  "properties": {
    "gn:admin1_code":"15.0",
    "gn:asciiname":"Tuoshuigou",
    "gn:country_code":"CN",
    "gn:dem":2305,
    "gn:feature_class":"P",
    "gn:feature_code":"PPL",
    "gn:name":"Tuoshuigou",
    "gn:population":0,
    "gn:timezone":"Asia/Shanghai",
    "iso:country":"CN",
    "name:zho_x_preferred":[
        "\u9a6e\u6c34\u6c9f"
    ],
    "wof:name":"Tuoshuigou",
    "wof:placetype":"locality"
},
  "geometry": {"coordinates":[104.23099999999999,35.6702],"type":"Point"}
}