{
  "type": "Feature",
  "properties": {
    "gn:admin1_code":"7.0",
    "gn:asciiname":"Shanzailai",
    "gn:country_code":"CN",
    "gn:dem":143,
    "gn:feature_class":"P",
    "gn:feature_code":"PPL",
    "gn:name":"Shanzailai",
    "gn:population":0,
    "gn:timezone":"Asia/Shanghai",
    "iso:country":"CN",
    "name:zho_x_preferred":[
        "\u5c71\u4ed4\u6fd1"
    ],
    "wof:name":"Shanzailai",
    "wof:placetype":"locality"
},
  "geometry": {"coordinates":[119.33923,26.32392],"type":"Point"}
}