{
  "type": "Feature",
  "properties": {
    "gn:admin1_code":"18",
    "gn:asciiname":"Huilongcun",
    "gn:cc2":"CN",
    "gn:country_code":"CN",
    "gn:dem":722,
    "gn:feature_class":"P",
    "gn:feature_code":"PPL",
    "gn:name":"Huilongcun",
    "gn:population":0,
    "gn:timezone":"Asia/Shanghai",
    "iso:country":"CN",
    "name:und_x_variant":[
        "Taibai",
        "Qinggangtang",
        "Ch\u2019ing-kang-t\u2019ang",
        "Huilongcun"
    ],
    "wof:name":"Huilongcun",
    "wof:placetype":"locality"
},
  "geometry": {"coordinates":[107.14943999999998,28.33139000000001],"type":"Point"}
}