{
  "type": "Feature",
  "properties": {
    "gn:admin1_code":"11.0",
    "gn:asciiname":"Yanghetian",
    "gn:country_code":"CN",
    "gn:dem":258,
    "gn:feature_class":"P",
    "gn:feature_code":"PPL",
    "gn:name":"Yanghetian",
    "gn:population":0,
    "gn:timezone":"Asia/Shanghai",
    "iso:country":"CN",
    "name:zho_x_preferred":[
        "\u9633\u548c\u7530"
    ],
    "wof:name":"Yanghetian",
    "wof:placetype":"locality"
},
  "geometry": {"coordinates":[109.81283000000001,27.46055],"type":"Point"}
}