{
  "type": "Feature",
  "properties": {
    "gn:admin1_code":"1.0",
    "gn:asciiname":"Chawan",
    "gn:country_code":"CN",
    "gn:dem":119,
    "gn:feature_class":"P",
    "gn:feature_code":"PPL",
    "gn:name":"Chawan",
    "gn:population":0,
    "gn:timezone":"Asia/Shanghai",
    "iso:country":"CN",
    "name:deu_x_preferred":[
        "Chawan"
    ],
    "name:fra_x_preferred":[
        "Chawan"
    ],
    "name:pol_x_preferred":[
        "Chawan"
    ],
    "name:por_x_preferred":[
        "Chawan"
    ],
    "name:rus_x_preferred":[
        "\u0422\u044f\u0432\u0430\u043d"
    ],
    "name:ukr_x_preferred":[
        "\u0427\u0430\u0432\u0430\u043d"
    ],
    "name:und_x_variant":[
        "Ch\u2019e-wan",
        "Zhawan",
        "Chawan",
        "\u67e5\u6e7e"
    ],
    "wof:name":"Chawan",
    "wof:placetype":"locality"
},
  "geometry": {"coordinates":[117.54155,29.66999],"type":"Point"}
}