{
  "type": "Feature",
  "properties": {
    "gn:admin1_code":"26.0",
    "gn:asciiname":"Yujia Goukou",
    "gn:country_code":"CN",
    "gn:dem":1535,
    "gn:feature_class":"P",
    "gn:feature_code":"PPL",
    "gn:name":"Yujia Goukou",
    "gn:population":0,
    "gn:timezone":"Asia/Shanghai",
    "iso:country":"CN",
    "name:zho_x_preferred":[
        "\u4e8e\u5bb6\u6c9f\u53e3"
    ],
    "wof:name":"Yujia Goukou",
    "wof:placetype":"locality"
},
  "geometry": {"coordinates":[109.45646000000001,33.92799],"type":"Point"}
}