{
  "type": "Feature",
  "properties": {
    "gn:admin1_code":"15.0",
    "gn:asciiname":"Guangluzhou",
    "gn:country_code":"CN",
    "gn:dem":1502,
    "gn:feature_class":"P",
    "gn:feature_code":"PPL",
    "gn:name":"Guangluzhou",
    "gn:population":0,
    "gn:timezone":"Asia/Shanghai",
    "iso:country":"CN",
    "name:und_x_variant":[
        "\u5149\u788c\u78a1"
    ],
    "wof:name":"Guangluzhou",
    "wof:placetype":"locality"
},
  "geometry": {"coordinates":[106.47141999999999,34.06301],"type":"Point"}
}