{
  "type": "Feature",
  "properties": {
    "gn:admin1_code":"19.0",
    "gn:asciiname":"Wangjiabu",
    "gn:country_code":"CN",
    "gn:dem":32,
    "gn:feature_class":"P",
    "gn:feature_code":"PPL",
    "gn:name":"Wangjiabu",
    "gn:population":0,
    "gn:timezone":"Asia/Shanghai",
    "iso:country":"CN",
    "name:und_x_variant":[
        "Wangjiabao",
        "Wangjiabu"
    ],
    "name:zho_x_preferred":[
        "\u6c6a\u5bb6\u5821"
    ],
    "wof:name":"Wangjiabu",
    "wof:placetype":"locality"
},
  "geometry": {"coordinates":[123.6189,40.14656],"type":"Point"}
}