{
  "type": "Feature",
  "properties": {
    "gn:admin1_code":"1.0",
    "gn:asciiname":"Yangfangcun",
    "gn:country_code":"CN",
    "gn:dem":33,
    "gn:feature_class":"P",
    "gn:feature_code":"PPL",
    "gn:name":"Yangfangcun",
    "gn:population":0,
    "gn:timezone":"Asia/Shanghai",
    "iso:country":"CN",
    "name:zho_x_preferred":[
        "\u6768\u65b9\u6751"
    ],
    "wof:name":"Yangfangcun",
    "wof:placetype":"locality"
},
  "geometry": {"coordinates":[115.48907,32.76709],"type":"Point"}
}