{
  "type": "Feature",
  "properties": {
    "gn:admin1_code":"11.0",
    "gn:asciiname":"Qinglongshan",
    "gn:country_code":"CN",
    "gn:dem":488,
    "gn:feature_class":"P",
    "gn:feature_code":"PPL",
    "gn:name":"Qinglongshan",
    "gn:population":0,
    "gn:timezone":"Asia/Shanghai",
    "iso:country":"CN",
    "name:zho_x_preferred":[
        "\u9752\u9f99\u5c71"
    ],
    "wof:name":"Qinglongshan",
    "wof:placetype":"locality"
},
  "geometry": {"coordinates":[109.34061,28.66912],"type":"Point"}
}