{
  "type": "Feature",
  "properties": {
    "gn:admin1_code":"24",
    "gn:asciiname":"Manqing",
    "gn:cc2":"CN",
    "gn:country_code":"CN",
    "gn:dem":1457,
    "gn:feature_class":"P",
    "gn:feature_code":"PPL",
    "gn:name":"Manqing",
    "gn:population":0,
    "gn:timezone":"Asia/Shanghai",
    "iso:country":"CN",
    "name:und_x_variant":[
        "Man-ch\u2019ing",
        "Man-ch\u2019ing-ts\u2019un",
        "Manqing"
    ],
    "wof:name":"Manqing",
    "wof:placetype":"locality"
},
  "geometry": {"coordinates":[112.31361,38.19444],"type":"Point"}
}