{
  "type": "Feature",
  "properties": {
    "gn:admin1_code":"8.0",
    "gn:asciiname":"Hongzhoucun",
    "gn:country_code":"CN",
    "gn:dem":66,
    "gn:feature_class":"P",
    "gn:feature_code":"PPL",
    "gn:name":"Hongzhoucun",
    "gn:population":0,
    "gn:timezone":"Asia/Shanghai",
    "iso:country":"CN",
    "name:zho_x_preferred":[
        "\u6d2a\u6d32\u6751"
    ],
    "wof:name":"Hongzhoucun",
    "wof:placetype":"locality"
},
  "geometry": {"coordinates":[131.69155000000001,46.96889],"type":"Point"}
}