{
  "type": "Feature",
  "properties": {
    "gn:admin1_code":"4.0",
    "gn:asciiname":"Yanzhuang",
    "gn:country_code":"CN",
    "gn:dem":28,
    "gn:feature_class":"P",
    "gn:feature_code":"PPL",
    "gn:name":"Yanzhuang",
    "gn:population":0,
    "gn:timezone":"Asia/Shanghai",
    "iso:country":"CN",
    "name:zho_x_preferred":[
        "\u95eb\u5e84"
    ],
    "wof:name":"Yanzhuang",
    "wof:placetype":"locality"
},
  "geometry": {"coordinates":[118.31826,34.14581],"type":"Point"}
}