{
  "type": "Feature",
  "properties": {
    "gn:admin1_code":"5.0",
    "gn:asciiname":"Dongma Shangtai",
    "gn:country_code":"CN",
    "gn:dem":206,
    "gn:feature_class":"P",
    "gn:feature_code":"PPL",
    "gn:name":"Dongma Shangtai",
    "gn:population":0,
    "gn:timezone":"Asia/Shanghai",
    "iso:country":"CN",
    "name:zho_x_preferred":[
        "\u4e1c\u9a6c\u4e0a\u53f0"
    ],
    "wof:name":"Dongma Shangtai",
    "wof:placetype":"locality"
},
  "geometry": {"coordinates":[124.80410999999999,43.71938],"type":"Point"}
}