{
  "type": "Feature",
  "properties": {
    "gn:admin1_code":"11",
    "gn:asciiname":"Dafumiao",
    "gn:country_code":"CN",
    "gn:dem":112,
    "gn:feature_class":"P",
    "gn:feature_code":"PPL",
    "gn:name":"Dafumiao",
    "gn:population":0,
    "gn:timezone":"Asia/Shanghai",
    "iso:country":"CN",
    "name:zho_x_preferred":[
        "\u5927\u592b\u5e99"
    ],
    "wof:name":"Dafumiao",
    "wof:placetype":"locality"
},
  "geometry": {"coordinates":[111.56185000000001,26.25553],"type":"Point"}
}