{
  "type": "Feature",
  "properties": {
    "gn:admin1_code":"07",
    "gn:asciiname":"Pingxiao",
    "gn:country_code":"CN",
    "gn:dem":639,
    "gn:feature_class":"P",
    "gn:feature_code":"PPL",
    "gn:name":"Pingxiao",
    "gn:population":0,
    "gn:timezone":"Asia/Shanghai",
    "iso:country":"CN",
    "name:zho_x_preferred":[
        "\u576a\u7b11"
    ],
    "wof:name":"Pingxiao",
    "wof:placetype":"locality"
},
  "geometry": {"coordinates":[117.15333,25.92222000000001],"type":"Point"}
}