{
  "type": "Feature",
  "properties": {
    "gn:admin1_code":"12.0",
    "gn:asciiname":"Zhawan",
    "gn:country_code":"CN",
    "gn:dem":50,
    "gn:feature_class":"P",
    "gn:feature_code":"PPL",
    "gn:name":"Zhawan",
    "gn:population":0,
    "gn:timezone":"Asia/Shanghai",
    "iso:country":"CN",
    "name:zho_x_preferred":[
        "\u69a8\u6e7e"
    ],
    "wof:name":"Zhawan",
    "wof:placetype":"locality"
},
  "geometry": {"coordinates":[112.27528999999998,30.59116],"type":"Point"}
}