{
  "type": "Feature",
  "properties": {
    "gn:admin1_code":"25",
    "gn:asciiname":"Jiulingpo",
    "gn:country_code":"CN",
    "gn:dem":248,
    "gn:feature_class":"P",
    "gn:feature_code":"PPL",
    "gn:name":"Jiulingpo",
    "gn:population":0,
    "gn:timezone":"Asia/Shanghai",
    "iso:country":"CN",
    "name:zho_x_preferred":[
        "\u4e5d\u5cad\u5761"
    ],
    "wof:name":"Jiulingpo",
    "wof:placetype":"locality"
},
  "geometry": {"coordinates":[118.63800000000001,36.0868],"type":"Point"}
}