{
  "type": "Feature",
  "properties": {
    "gn:admin1_code":"30",
    "gn:asciiname":"Shibeitou",
    "gn:country_code":"CN",
    "gn:dem":41,
    "gn:feature_class":"P",
    "gn:feature_code":"PPL",
    "gn:name":"Shibeitou",
    "gn:population":0,
    "gn:timezone":"Asia/Urumqi",
    "iso:country":"CN",
    "name:zho_x_preferred":[
        "\u77f3\u9642\u5934"
    ],
    "wof:name":"Shibeitou",
    "wof:placetype":"locality"
},
  "geometry": {"coordinates":[111.19095,21.74653],"type":"Point"}
}