{
  "type": "Feature",
  "properties": {
    "gn:admin1_code":"16.0",
    "gn:asciiname":"Shitang",
    "gn:country_code":"CN",
    "gn:dem":110,
    "gn:feature_class":"P",
    "gn:feature_code":"PPL",
    "gn:name":"Shitang",
    "gn:population":0,
    "gn:timezone":"Asia/Shanghai",
    "iso:country":"CN",
    "name:zho_x_preferred":[
        "\u77f3\u5858"
    ],
    "wof:name":"Shitang",
    "wof:placetype":"locality"
},
  "geometry": {"coordinates":[109.985,21.9578],"type":"Point"}
}