{
  "type": "Feature",
  "properties": {
    "gn:admin1_code":"15.0",
    "gn:asciiname":"Guojixiang",
    "gn:country_code":"CN",
    "gn:dem":1942,
    "gn:feature_class":"P",
    "gn:feature_code":"PPL",
    "gn:name":"Guojixiang",
    "gn:population":0,
    "gn:timezone":"Asia/Shanghai",
    "iso:country":"CN",
    "name:und_x_variant":[
        "\u90ed\u96c6\u4e61"
    ],
    "wof:name":"Guojixiang",
    "wof:placetype":"locality"
},
  "geometry": {"coordinates":[105.38500999999999,35.02650999999999],"type":"Point"}
}