{
  "type": "Feature",
  "properties": {
    "gn:admin1_code":"16.0",
    "gn:asciiname":"Naji",
    "gn:country_code":"CN",
    "gn:dem":389,
    "gn:feature_class":"P",
    "gn:feature_code":"PPL",
    "gn:name":"Naji",
    "gn:population":0,
    "gn:timezone":"Asia/Shanghai",
    "iso:country":"CN",
    "name:ara_x_preferred":[
        "\u0646\u0627\u062c\u064a"
    ],
    "name:zho_x_preferred":[
        "\u7eb3\u5409"
    ],
    "wof:name":"Naji",
    "wof:placetype":"locality"
},
  "geometry": {"coordinates":[107.291,24.8119],"type":"Point"}
}