{
  "type": "Feature",
  "properties": {
    "gn:admin1_code":"02",
    "gn:asciiname":"Furongcun",
    "gn:country_code":"CN",
    "gn:dem":21,
    "gn:feature_class":"P",
    "gn:feature_code":"PPL",
    "gn:name":"Furongcun",
    "gn:population":0,
    "gn:timezone":"Asia/Shanghai",
    "iso:country":"CN",
    "name:und_x_variant":[
        "Fu-jung-hsia-chai",
        "Furong",
        "Furongcun"
    ],
    "name:zho_x_preferred":[
        "\u8299\u84c9\u6751"
    ],
    "wof:name":"Furongcun",
    "wof:placetype":"locality"
},
  "geometry": {"coordinates":[121.52064,28.82896],"type":"Point"}
}