{
  "type": "Feature",
  "properties": {
    "gn:admin1_code":"6.0",
    "gn:asciiname":"Dulong",
    "gn:country_code":"CN",
    "gn:dem":2958,
    "gn:feature_class":"P",
    "gn:feature_code":"PPL",
    "gn:name":"Dulong",
    "gn:population":0,
    "gn:timezone":"Asia/Shanghai",
    "iso:country":"CN",
    "name:zho_x_preferred":[
        "\u90fd\u9686"
    ],
    "wof:name":"Dulong",
    "wof:placetype":"locality"
},
  "geometry": {"coordinates":[101.744,35.70563],"type":"Point"}
}