{
  "type": "Feature",
  "properties": {
    "gn:admin1_code":"4.0",
    "gn:asciiname":"Xiangxi",
    "gn:country_code":"CN",
    "gn:dem":3,
    "gn:feature_class":"P",
    "gn:feature_code":"PPL",
    "gn:name":"Xiangxi",
    "gn:population":0,
    "gn:timezone":"Asia/Shanghai",
    "iso:country":"CN",
    "name:und_x_variant":[
        "\u7965\u897f"
    ],
    "wof:name":"Xiangxi",
    "wof:placetype":"locality"
},
  "geometry": {"coordinates":[120.52246,33.11669000000001],"type":"Point"}
}