{
  "type": "Feature",
  "properties": {
    "gn:admin1_code":"16.0",
    "gn:asciiname":"Wangjing",
    "gn:country_code":"CN",
    "gn:dem":69,
    "gn:feature_class":"P",
    "gn:feature_code":"PPL",
    "gn:name":"Wangjing",
    "gn:population":0,
    "gn:timezone":"Asia/Shanghai",
    "iso:country":"CN",
    "name:ceb_x_preferred":[
        "Wangjing"
    ],
    "name:swe_x_preferred":[
        "Wangjing"
    ],
    "name:zho_x_preferred":[
        "\u738b\u5883"
    ],
    "wof:name":"Wangjing",
    "wof:placetype":"locality"
},
  "geometry": {"coordinates":[109.443,23.7204],"type":"Point"}
}