{
  "type": "Feature",
  "properties": {
    "gn:admin1_code":"19.0",
    "gn:asciiname":"Qijiawei",
    "gn:country_code":"CN",
    "gn:dem":4,
    "gn:feature_class":"P",
    "gn:feature_code":"PPL",
    "gn:name":"Qijiawei",
    "gn:population":0,
    "gn:timezone":"Asia/Shanghai",
    "iso:country":"CN",
    "name:und_x_variant":[
        "\u9f50\u5bb6\u56f4"
    ],
    "name:zho_x_preferred":[
        "\u9f50\u5bb6\u56f4"
    ],
    "wof:name":"Qijiawei",
    "wof:placetype":"locality"
},
  "geometry": {"coordinates":[122.46212,40.83413],"type":"Point"}
}