{
  "type": "Feature",
  "properties": {
    "gn:admin1_code":"18.0",
    "gn:asciiname":"Hunquan",
    "gn:country_code":"CN",
    "gn:dem":627,
    "gn:feature_class":"P",
    "gn:feature_code":"PPL",
    "gn:name":"Hunquan",
    "gn:population":0,
    "gn:timezone":"Asia/Shanghai",
    "iso:country":"CN",
    "name:zho_x_preferred":[
        "\u6d51\u6cc9"
    ],
    "wof:name":"Hunquan",
    "wof:placetype":"locality"
},
  "geometry": {"coordinates":[108.69799999999999,28.3638],"type":"Point"}
}