{
  "type": "Feature",
  "properties": {
    "gn:admin1_code":"26.0",
    "gn:asciiname":"Shiyanta",
    "gn:country_code":"CN",
    "gn:dem":1090,
    "gn:feature_class":"P",
    "gn:feature_code":"PPL",
    "gn:name":"Shiyanta",
    "gn:population":0,
    "gn:timezone":"Asia/Shanghai",
    "iso:country":"CN",
    "name:zho_x_preferred":[
        "\u77f3\u5ca9\u5854"
    ],
    "wof:name":"Shiyanta",
    "wof:placetype":"locality"
},
  "geometry": {"coordinates":[110.38818000000001,39.28636],"type":"Point"}
}