{
  "type": "Feature",
  "properties": {
    "gn:admin1_code":"2",
    "gn:asciiname":"Kengdiyang",
    "gn:country_code":"CN",
    "gn:dem":358,
    "gn:feature_class":"P",
    "gn:feature_code":"PPL",
    "gn:name":"Kengdiyang",
    "gn:population":0,
    "gn:timezone":"Asia/Shanghai",
    "iso:country":"CN",
    "name:zho_x_preferred":[
        "\u5751\u5e95\u579f"
    ],
    "wof:name":"Kengdiyang",
    "wof:placetype":"locality"
},
  "geometry": {"coordinates":[119.54833000000001,27.86889],"type":"Point"}
}