{
  "type": "Feature",
  "properties": {
    "gn:admin1_code":"25",
    "gn:asciiname":"Lingdong",
    "gn:country_code":"CN",
    "gn:dem":265,
    "gn:feature_class":"P",
    "gn:feature_code":"PPL",
    "gn:name":"Lingdong",
    "gn:population":0,
    "gn:timezone":"Asia/Shanghai",
    "iso:country":"CN",
    "name:ceb_x_preferred":[
        "Lingdong"
    ],
    "name:deu_x_preferred":[
        "Lingdong"
    ],
    "name:zho_x_preferred":[
        "\u5cad\u4e1c"
    ],
    "wof:name":"Lingdong",
    "wof:placetype":"locality"
},
  "geometry": {"coordinates":[117.56100000000001,36.4799],"type":"Point"}
}