{
  "type": "Feature",
  "properties": {
    "gn:admin1_code":"24.0",
    "gn:asciiname":"Shangjiao",
    "gn:country_code":"CN",
    "gn:dem":1064,
    "gn:feature_class":"P",
    "gn:feature_code":"PPL",
    "gn:name":"Shangjiao",
    "gn:population":0,
    "gn:timezone":"Asia/Shanghai",
    "iso:country":"CN",
    "name:zho_x_preferred":[
        "\u4e0a\u4ea4"
    ],
    "wof:name":"Shangjiao",
    "wof:placetype":"locality"
},
  "geometry": {"coordinates":[111.98432,35.70745],"type":"Point"}
}