{
  "type": "Feature",
  "properties": {
    "gn:admin1_code":"33",
    "gn:asciiname":"Dapuzi",
    "gn:cc2":"CN",
    "gn:country_code":"CN",
    "gn:dem":683,
    "gn:feature_class":"P",
    "gn:feature_code":"PPL",
    "gn:name":"Dapuzi",
    "gn:population":0,
    "gn:timezone":"Asia/Shanghai",
    "iso:country":"CN",
    "name:und_x_variant":[
        "Ta-p\u2019u-tzu",
        "Dapuzi"
    ],
    "name:zho_x_preferred":[
        "\u5927\u94fa\u5b50"
    ],
    "wof:name":"Dapuzi",
    "wof:placetype":"locality"
},
  "geometry": {"coordinates":[107.16667,29.16667],"type":"Point"}
}