{
  "type": "Feature",
  "properties": {
    "gn:admin1_code":"20.0",
    "gn:asciiname":"Nandayao",
    "gn:country_code":"CN",
    "gn:dem":1591,
    "gn:feature_class":"P",
    "gn:feature_code":"PPL",
    "gn:name":"Nandayao",
    "gn:population":0,
    "gn:timezone":"Asia/Shanghai",
    "iso:country":"CN",
    "name:und_x_variant":[
        "\u5357\u5927\u7a91"
    ],
    "wof:name":"Nandayao",
    "wof:placetype":"locality"
},
  "geometry": {"coordinates":[110.03451,41.39459],"type":"Point"}
}