{
  "type": "Feature",
  "properties": {
    "gn:admin1_code":"29.0",
    "gn:asciiname":"Lianping",
    "gn:country_code":"CN",
    "gn:dem":2497,
    "gn:feature_class":"P",
    "gn:feature_code":"PPL",
    "gn:name":"Lianping",
    "gn:population":0,
    "gn:timezone":"Asia/Shanghai",
    "iso:country":"CN",
    "name:zho_x_preferred":[
        "\u70bc\u576a"
    ],
    "wof:name":"Lianping",
    "wof:placetype":"locality"
},
  "geometry": {"coordinates":[99.2072,25.9454],"type":"Point"}
}