{
  "type": "Feature",
  "properties": {
    "gn:admin1_code":"2.0",
    "gn:asciiname":"Xuanshanxia",
    "gn:country_code":"CN",
    "gn:dem":33,
    "gn:feature_class":"P",
    "gn:feature_code":"PPL",
    "gn:name":"Xuanshanxia",
    "gn:population":0,
    "gn:timezone":"Asia/Shanghai",
    "iso:country":"CN",
    "name:zho_x_preferred":[
        "\u7487\u5c71\u4e0b"
    ],
    "wof:name":"Xuanshanxia",
    "wof:placetype":"locality"
},
  "geometry": {"coordinates":[120.20298,29.95208],"type":"Point"}
}