{
  "type": "Feature",
  "properties": {
    "gn:admin1_code":"3.0",
    "gn:asciiname":"Chenmeikeng",
    "gn:country_code":"CN",
    "gn:dem":447,
    "gn:feature_class":"P",
    "gn:feature_code":"PPL",
    "gn:name":"Chenmeikeng",
    "gn:population":0,
    "gn:timezone":"Asia/Shanghai",
    "iso:country":"CN",
    "name:zho_x_preferred":[
        "\u9648\u7f8e\u5751"
    ],
    "wof:name":"Chenmeikeng",
    "wof:placetype":"locality"
},
  "geometry": {"coordinates":[115.40766000000001,24.86234],"type":"Point"}
}