{
  "type": "Feature",
  "properties": {
    "gn:admin1_code":"5",
    "gn:asciiname":"Longwangmiaocun",
    "gn:country_code":"CN",
    "gn:dem":296,
    "gn:feature_class":"P",
    "gn:feature_code":"PPL",
    "gn:name":"Longwangmiaocun",
    "gn:population":0,
    "gn:timezone":"Asia/Shanghai",
    "iso:country":"CN",
    "name:zho_x_preferred":[
        "\u9f99\u738b\u5e99\u6751"
    ],
    "wof:name":"Longwangmiaocun",
    "wof:placetype":"locality"
},
  "geometry": {"coordinates":[127.0256,43.64795],"type":"Point"}
}