{
  "type": "Feature",
  "properties": {
    "gn:admin1_code":"30",
    "gn:asciiname":"Tiantoucun",
    "gn:country_code":"CN",
    "gn:dem":7,
    "gn:feature_class":"P",
    "gn:feature_code":"PPL",
    "gn:name":"Tiantoucun",
    "gn:population":0,
    "gn:timezone":"Asia/Urumqi",
    "iso:country":"CN",
    "name:zho_x_preferred":[
        "\u7530\u5934\u6751"
    ],
    "wof:name":"Tiantoucun",
    "wof:placetype":"locality"
},
  "geometry": {"coordinates":[110.44087,20.64569],"type":"Point"}
}