{
  "type": "Feature",
  "properties": {
    "gn:admin1_code":"13.0",
    "gn:asciiname":"Kuoshimakeya",
    "gn:country_code":"CN",
    "gn:dem":1345,
    "gn:feature_class":"P",
    "gn:feature_code":"PPL",
    "gn:name":"Kuoshimakeya",
    "gn:population":0,
    "gn:timezone":"Asia/Shanghai",
    "iso:country":"CN",
    "name:zho_x_preferred":[
        "\u9614\u4ec0\u739b\u514b\u4e9a"
    ],
    "wof:name":"Kuoshimakeya",
    "wof:placetype":"locality"
},
  "geometry": {"coordinates":[79.16195999999999,37.31392],"type":"Point"}
}