{
  "type": "Feature",
  "properties": {
    "gn:admin1_code":"26.0",
    "gn:asciiname":"Qujiahecun",
    "gn:country_code":"CN",
    "gn:dem":946,
    "gn:feature_class":"P",
    "gn:feature_code":"PPL",
    "gn:name":"Qujiahecun",
    "gn:population":0,
    "gn:timezone":"Asia/Shanghai",
    "iso:country":"CN",
    "name:zho_x_preferred":[
        "\u5c48\u5bb6\u6cb3\u6751"
    ],
    "wof:name":"Qujiahecun",
    "wof:placetype":"locality"
},
  "geometry": {"coordinates":[109.45813,35.70985],"type":"Point"}
}