{
  "type": "Feature",
  "properties": {
    "gn:admin1_code":"28.0",
    "gn:asciiname":"Xianfeng",
    "gn:country_code":"CN",
    "gn:dem":6,
    "gn:feature_class":"P",
    "gn:feature_code":"PPL",
    "gn:name":"Xianfeng",
    "gn:population":0,
    "gn:timezone":"Asia/Shanghai",
    "iso:country":"CN",
    "name:ceb_x_preferred":[
        "Xianfeng"
    ],
    "name:deu_x_preferred":[
        "Xianfeng"
    ],
    "name:fra_x_preferred":[
        "Xianfeng"
    ],
    "name:nor_x_preferred":[
        "Xianfeng"
    ],
    "wof:name":"Xianfeng",
    "wof:placetype":"locality"
},
  "geometry": {"coordinates":[117.21503,39.12088],"type":"Point"}
}