{
  "type": "Feature",
  "properties": {
    "gn:admin1_code":"2.0",
    "gn:asciiname":"Zhamengdian",
    "gn:country_code":"CN",
    "gn:dem":308,
    "gn:feature_class":"P",
    "gn:feature_code":"PPL",
    "gn:name":"Zhamengdian",
    "gn:population":0,
    "gn:timezone":"Asia/Shanghai",
    "iso:country":"CN",
    "name:zho_x_preferred":[
        "\u86b1\u8722\u6bbf"
    ],
    "wof:name":"Zhamengdian",
    "wof:placetype":"locality"
},
  "geometry": {"coordinates":[119.32818,28.71197],"type":"Point"}
}