{
  "type": "Feature",
  "properties": {
    "gn:admin1_code":"4.0",
    "gn:asciiname":"Sihoucun",
    "gn:country_code":"CN",
    "gn:dem":7,
    "gn:feature_class":"P",
    "gn:feature_code":"PPL",
    "gn:name":"Sihoucun",
    "gn:population":0,
    "gn:timezone":"Asia/Shanghai",
    "iso:country":"CN",
    "name:und_x_variant":[
        "Sihou"
    ],
    "name:zho_x_preferred":[
        "\u5bfa\u540e\u6751"
    ],
    "wof:name":"Sihoucun",
    "wof:placetype":"locality"
},
  "geometry": {"coordinates":[119.04546999999999,34.80872],"type":"Point"}
}