{
  "type": "Feature",
  "properties": {
    "gn:admin1_code":"19.0",
    "gn:asciiname":"Zhalanchengcun",
    "gn:country_code":"CN",
    "gn:dem":558,
    "gn:feature_class":"P",
    "gn:feature_code":"PPL",
    "gn:name":"Zhalanchengcun",
    "gn:population":0,
    "gn:timezone":"Asia/Shanghai",
    "iso:country":"CN",
    "name:zho_x_preferred":[
        "\u624e\u5170\u57ce\u6751"
    ],
    "wof:name":"Zhalanchengcun",
    "wof:placetype":"locality"
},
  "geometry": {"coordinates":[119.47,41.7329],"type":"Point"}
}