{
  "type": "Feature",
  "properties": {
    "gn:admin1_code":"14.0",
    "gn:asciiname":"Etuosi",
    "gn:country_code":"CN",
    "gn:dem":3728,
    "gn:feature_class":"P",
    "gn:feature_code":"PPL",
    "gn:name":"Etuosi",
    "gn:population":0,
    "gn:timezone":"Asia/Urumqi",
    "iso:country":"CN",
    "name:zho_x_preferred":[
        "\u4fc4\u6258\u5bfa"
    ],
    "wof:name":"Etuosi",
    "wof:placetype":"locality"
},
  "geometry": {"coordinates":[98.2741,31.92669],"type":"Point"}
}