{
  "type": "Feature",
  "properties": {
    "gn:admin1_code":"12.0",
    "gn:asciiname":"Dazhoujiamen",
    "gn:country_code":"CN",
    "gn:dem":28,
    "gn:feature_class":"P",
    "gn:feature_code":"PPL",
    "gn:name":"Dazhoujiamen",
    "gn:population":0,
    "gn:timezone":"Asia/Shanghai",
    "iso:country":"CN",
    "name:zho_x_preferred":[
        "\u5927\u5468\u5bb6\u95e8"
    ],
    "wof:name":"Dazhoujiamen",
    "wof:placetype":"locality"
},
  "geometry": {"coordinates":[113.81975,30.47145],"type":"Point"}
}