{
  "type": "Feature",
  "properties": {
    "gn:admin1_code":"26",
    "gn:asciiname":"Shuangchazi",
    "gn:country_code":"CN",
    "gn:dem":1427,
    "gn:feature_class":"P",
    "gn:feature_code":"PPL",
    "gn:name":"Shuangchazi",
    "gn:population":0,
    "gn:timezone":"Asia/Shanghai",
    "iso:country":"CN",
    "name:und_x_variant":[
        "\u53cc\u5c94\u5b50"
    ],
    "wof:name":"Shuangchazi",
    "wof:placetype":"locality"
},
  "geometry": {"coordinates":[107.44347,34.05337],"type":"Point"}
}