{
  "type": "Feature",
  "properties": {
    "gn:admin1_code":"19.0",
    "gn:asciiname":"Famen Sanxianchang",
    "gn:country_code":"CN",
    "gn:dem":256,
    "gn:feature_class":"P",
    "gn:feature_code":"PPL",
    "gn:name":"Famen Sanxianchang",
    "gn:population":0,
    "gn:timezone":"Asia/Shanghai",
    "iso:country":"CN",
    "name:und_x_variant":[
        "\u9600\u95e8\u4e09\u7ebf\u5382"
    ],
    "name:zho_x_preferred":[
        "\u9600\u95e8\u4e09\u7ebf\u5382"
    ],
    "wof:name":"Famen Sanxianchang",
    "wof:placetype":"locality"
},
  "geometry": {"coordinates":[122.30408,39.90667],"type":"Point"}
}