{
  "type": "Feature",
  "properties": {
    "gn:admin1_code":"26.0",
    "gn:asciiname":"Shitahan",
    "gn:country_code":"CN",
    "gn:dem":1240,
    "gn:feature_class":"P",
    "gn:feature_code":"PPL",
    "gn:name":"Shitahan",
    "gn:population":0,
    "gn:timezone":"Asia/Shanghai",
    "iso:country":"CN",
    "name:zho_x_preferred":[
        "\u4ec0\u5b83\u6c49"
    ],
    "wof:name":"Shitahan",
    "wof:placetype":"locality"
},
  "geometry": {"coordinates":[109.43626999999999,38.63238],"type":"Point"}
}