{
  "type": "Feature",
  "properties": {
    "gn:admin1_code":"08",
    "gn:asciiname":"Bayan Qagan",
    "gn:country_code":"CN",
    "gn:dem":151,
    "gn:feature_class":"P",
    "gn:feature_code":"PPLA4",
    "gn:name":"Bayan Qagan",
    "gn:population":0,
    "gn:timezone":"Asia/Shanghai",
    "iso:country":"CN",
    "name:und_x_variant":[
        "Pai-yin-ch\u2019a-kan",
        "Bayan Qagan",
        "Bayan Chagan",
        "Bayan Chagan Xiang"
    ],
    "name:zho_x_preferred":[
        "\u5df4\u5f66\u67e5\u5e72"
    ],
    "name:zho_x_variant":[
        "\u5df4\u5f66\u67e5\u5e72\u4e61"
    ],
    "wof:name":"Bayan Qagan",
    "wof:placetype":"locality"
},
  "geometry": {"coordinates":[124.04539,46.33854],"type":"Point"}
}