{
  "type": "Feature",
  "properties": {
    "gn:admin1_code":"4.0",
    "gn:asciiname":"Yuanzhuang",
    "gn:country_code":"CN",
    "gn:dem":4,
    "gn:feature_class":"P",
    "gn:feature_code":"PPL",
    "gn:name":"Yuanzhuang",
    "gn:population":0,
    "gn:timezone":"Asia/Shanghai",
    "iso:country":"CN",
    "name:zho_x_preferred":[
        "\u8881\u5e84"
    ],
    "wof:name":"Yuanzhuang",
    "wof:placetype":"locality"
},
  "geometry": {"coordinates":[120.18293,32.84441],"type":"Point"}
}