{
  "type": "Feature",
  "properties": {
    "gn:admin1_code":"33.0",
    "gn:asciiname":"Tiechangping",
    "gn:country_code":"CN",
    "gn:dem":1485,
    "gn:feature_class":"P",
    "gn:feature_code":"PPL",
    "gn:name":"Tiechangping",
    "gn:population":0,
    "gn:timezone":"Asia/Shanghai",
    "iso:country":"CN",
    "name:zho_x_preferred":[
        "\u94c1\u5382\u576a"
    ],
    "wof:name":"Tiechangping",
    "wof:placetype":"locality"
},
  "geometry": {"coordinates":[107.354,29.1346],"type":"Point"}
}