{
  "type": "Feature",
  "properties": {
    "gn:admin1_code":"32.0",
    "gn:asciiname":"Wugaoyan",
    "gn:country_code":"CN",
    "gn:dem":393,
    "gn:feature_class":"P",
    "gn:feature_code":"PPL",
    "gn:name":"Wugaoyan",
    "gn:population":0,
    "gn:timezone":"Asia/Shanghai",
    "iso:country":"CN",
    "name:zho_x_preferred":[
        "\u6b66\u9ad8\u5830"
    ],
    "wof:name":"Wugaoyan",
    "wof:placetype":"locality"
},
  "geometry": {"coordinates":[103.89543,29.58938],"type":"Point"}
}