{
  "type": "Feature",
  "properties": {
    "gn:admin1_code":"9.0",
    "gn:asciiname":"Yuhuangmiaowang",
    "gn:country_code":"CN",
    "gn:dem":112,
    "gn:feature_class":"P",
    "gn:feature_code":"PPL",
    "gn:name":"Yuhuangmiaowang",
    "gn:population":0,
    "gn:timezone":"Asia/Shanghai",
    "iso:country":"CN",
    "name:zho_x_preferred":[
        "\u79b9\u7687\u5e99\u738b"
    ],
    "wof:name":"Yuhuangmiaowang",
    "wof:placetype":"locality"
},
  "geometry": {"coordinates":[113.48031,33.98405],"type":"Point"}
}