{
  "type": "Feature",
  "properties": {
    "gn:admin1_code":"29.0",
    "gn:asciiname":"Yaojiazhai",
    "gn:country_code":"CN",
    "gn:dem":1575,
    "gn:feature_class":"P",
    "gn:feature_code":"PPL",
    "gn:name":"Yaojiazhai",
    "gn:population":0,
    "gn:timezone":"Asia/Shanghai",
    "iso:country":"CN",
    "name:zho_x_preferred":[
        "\u59da\u5bb6\u5be8"
    ],
    "wof:name":"Yaojiazhai",
    "wof:placetype":"locality"
},
  "geometry": {"coordinates":[105.157,27.4369],"type":"Point"}
}