{
  "type": "Feature",
  "properties": {
    "gn:admin1_code":"18",
    "gn:asciiname":"Nateng",
    "gn:country_code":"CN",
    "gn:dem":717,
    "gn:feature_class":"P",
    "gn:feature_code":"PPL",
    "gn:name":"Nateng",
    "gn:population":0,
    "gn:timezone":"Asia/Shanghai",
    "iso:country":"CN",
    "name:zho_x_preferred":[
        "\u7eb3\u85e4"
    ],
    "wof:name":"Nateng",
    "wof:placetype":"locality"
},
  "geometry": {"coordinates":[105.95399999999999,25.0053],"type":"Point"}
}