{
  "type": "Feature",
  "properties": {
    "gn:admin1_code":"2.0",
    "gn:asciiname":"Shidiandu",
    "gn:country_code":"CN",
    "gn:dem":6,
    "gn:feature_class":"P",
    "gn:feature_code":"PPL",
    "gn:name":"Shidiandu",
    "gn:population":0,
    "gn:timezone":"Asia/Shanghai",
    "iso:country":"CN",
    "name:und_x_variant":[
        "\u77f3\u70b9\u6e21"
    ],
    "wof:name":"Shidiandu",
    "wof:placetype":"locality"
},
  "geometry": {"coordinates":[119.70287999999999,30.81278],"type":"Point"}
}