{
  "type": "Feature",
  "properties": {
    "gn:admin1_code":"2.0",
    "gn:asciiname":"Huangshuidui",
    "gn:country_code":"CN",
    "gn:dem":143,
    "gn:feature_class":"P",
    "gn:feature_code":"PPL",
    "gn:name":"Huangshuidui",
    "gn:population":0,
    "gn:timezone":"Asia/Shanghai",
    "iso:country":"CN",
    "name:zho_x_preferred":[
        "\u9ec4\u6c34\u7893"
    ],
    "wof:name":"Huangshuidui",
    "wof:placetype":"locality"
},
  "geometry": {"coordinates":[119.56556999999999,28.09956],"type":"Point"}
}