{
  "type": "Feature",
  "properties": {
    "gn:admin1_code":"04",
    "gn:asciiname":"Diaoyumiao",
    "gn:country_code":"CN",
    "gn:dem":3,
    "gn:feature_class":"P",
    "gn:feature_code":"PPLA4",
    "gn:name":"Diaoyumiao",
    "gn:population":0,
    "gn:timezone":"Asia/Shanghai",
    "iso:country":"CN",
    "name:und_x_variant":[
        "\u9493\u9c7c\u5e99",
        "Diaoyu",
        "Diaoyu Zhen",
        "\u9493\u9c7c",
        "\u9493\u9c7c\u9547"
    ],
    "wof:name":"Diaoyumiao",
    "wof:placetype":"locality"
},
  "geometry": {"coordinates":[119.97342999999999,33.08595],"type":"Point"}
}