{
  "type": "Feature",
  "properties": {
    "gn:admin1_code":"25.0",
    "gn:asciiname":"Guzhuangtoucun",
    "gn:country_code":"CN",
    "gn:dem":10,
    "gn:feature_class":"P",
    "gn:feature_code":"PPL",
    "gn:name":"Guzhuangtoucun",
    "gn:population":0,
    "gn:timezone":"Asia/Shanghai",
    "iso:country":"CN",
    "name:zho_x_preferred":[
        "\u53e4\u5e84\u5934\u6751"
    ],
    "wof:name":"Guzhuangtoucun",
    "wof:placetype":"locality"
},
  "geometry": {"coordinates":[121.00266000000001,36.61721],"type":"Point"}
}