{
  "type": "Feature",
  "properties": {
    "gn:admin1_code":"32.0",
    "gn:asciiname":"Pujiaping",
    "gn:country_code":"CN",
    "gn:dem":1320,
    "gn:feature_class":"P",
    "gn:feature_code":"PPL",
    "gn:name":"Pujiaping",
    "gn:population":0,
    "gn:timezone":"Asia/Shanghai",
    "iso:country":"CN",
    "name:zho_x_preferred":[
        "\u84b2\u5bb6\u576a"
    ],
    "wof:name":"Pujiaping",
    "wof:placetype":"locality"
},
  "geometry": {"coordinates":[104.54843,32.05213],"type":"Point"}
}