{
  "type": "Feature",
  "properties": {
    "gn:admin1_code":"10.0",
    "gn:asciiname":"Gongren Nanli",
    "gn:country_code":"CN",
    "gn:dem":5,
    "gn:feature_class":"P",
    "gn:feature_code":"PPL",
    "gn:name":"Gongren Nanli",
    "gn:population":0,
    "gn:timezone":"Asia/Shanghai",
    "iso:country":"CN",
    "name:zho_x_preferred":[
        "\u5de5\u4eba\u5357\u91cc"
    ],
    "wof:name":"Gongren Nanli",
    "wof:placetype":"locality"
},
  "geometry": {"coordinates":[119.62572,39.92524],"type":"Point"}
}