{
  "type": "Feature",
  "properties": {
    "gn:admin1_code":"11.0",
    "gn:asciiname":"Ehuangmiao",
    "gn:country_code":"CN",
    "gn:dem":292,
    "gn:feature_class":"P",
    "gn:feature_code":"PPL",
    "gn:name":"Ehuangmiao",
    "gn:population":0,
    "gn:timezone":"Asia/Shanghai",
    "iso:country":"CN",
    "name:zho_x_preferred":[
        "\u9e45\u714c\u5e99"
    ],
    "wof:name":"Ehuangmiao",
    "wof:placetype":"locality"
},
  "geometry": {"coordinates":[110.87179,27.04173],"type":"Point"}
}