{
  "type": "Feature",
  "properties": {
    "gn:admin1_code":"25",
    "gn:asciiname":"Gongkoucun",
    "gn:country_code":"CN",
    "gn:dem":9,
    "gn:feature_class":"P",
    "gn:feature_code":"PPL",
    "gn:name":"Gongkoucun",
    "gn:population":0,
    "gn:timezone":"Asia/Shanghai",
    "iso:country":"CN",
    "name:und_x_variant":[
        "Gongkou",
        "Gongkoucun"
    ],
    "name:zho_x_preferred":[
        "\u8d21\u53e3"
    ],
    "name:zho_x_variant":[
        "\u8d21\u53e3\u6751"
    ],
    "wof:name":"Gongkoucun",
    "wof:placetype":"locality"
},
  "geometry": {"coordinates":[119.81021,35.64713],"type":"Point"}
}