{
  "type": "Feature",
  "properties": {
    "gn:admin1_code":"18",
    "gn:asciiname":"Xinqiaoying",
    "gn:country_code":"CN",
    "gn:dem":937,
    "gn:feature_class":"P",
    "gn:feature_code":"PPL",
    "gn:name":"Xinqiaoying",
    "gn:population":0,
    "gn:timezone":"Asia/Shanghai",
    "iso:country":"CN",
    "name:zho_x_preferred":[
        "\u65b0\u6865\u8425"
    ],
    "wof:name":"Xinqiaoying",
    "wof:placetype":"locality"
},
  "geometry": {"coordinates":[107.627,26.6736],"type":"Point"}
}