{
  "type": "Feature",
  "properties": {
    "gn:admin1_code":"20",
    "gn:asciiname":"Chang-chia-ying-tzu",
    "gn:country_code":"CN",
    "gn:dem":561,
    "gn:feature_class":"P",
    "gn:feature_code":"PPL",
    "gn:name":"Chang-chia-ying-tzu",
    "gn:population":0,
    "gn:timezone":"Asia/Shanghai",
    "iso:country":"CN",
    "wof:name":"Chang-chia-ying-tzu",
    "wof:placetype":"locality"
},
  "geometry": {"coordinates":[119.46444,42.63639000000001],"type":"Point"}
}