{
  "type": "Feature",
  "properties": {
    "gn:admin1_code":"15.0",
    "gn:asciiname":"Miaojia Hetan",
    "gn:country_code":"CN",
    "gn:dem":1931,
    "gn:feature_class":"P",
    "gn:feature_code":"PPL",
    "gn:name":"Miaojia Hetan",
    "gn:population":0,
    "gn:timezone":"Asia/Shanghai",
    "iso:country":"CN",
    "name:zho_x_preferred":[
        "\u82d7\u5bb6\u6cb3\u6ee9"
    ],
    "wof:name":"Miaojia Hetan",
    "wof:placetype":"locality"
},
  "geometry": {"coordinates":[106.43000000000001,34.6697],"type":"Point"}
}