{
  "type": "Feature",
  "properties": {
    "gn:admin1_code":"32.0",
    "gn:asciiname":"Guanyemiao",
    "gn:country_code":"CN",
    "gn:dem":577,
    "gn:feature_class":"P",
    "gn:feature_code":"PPL",
    "gn:name":"Guanyemiao",
    "gn:population":0,
    "gn:timezone":"Asia/Shanghai",
    "iso:country":"CN",
    "name:zho_x_preferred":[
        "\u5b98\u7237\u5e99"
    ],
    "wof:name":"Guanyemiao",
    "wof:placetype":"locality"
},
  "geometry": {"coordinates":[103.83788,30.83105],"type":"Point"}
}