{
  "type": "Feature",
  "properties": {
    "gn:admin1_code":"29.0",
    "gn:asciiname":"Gunpengyang",
    "gn:country_code":"CN",
    "gn:dem":1627,
    "gn:feature_class":"P",
    "gn:feature_code":"PPL",
    "gn:name":"Gunpengyang",
    "gn:population":0,
    "gn:timezone":"Asia/Shanghai",
    "iso:country":"CN",
    "name:zho_x_preferred":[
        "\u6eda\u670b\u7f8a"
    ],
    "wof:name":"Gunpengyang",
    "wof:placetype":"locality"
},
  "geometry": {"coordinates":[97.7456,24.9509],"type":"Point"}
}