{
  "type": "Feature",
  "properties": {
    "gn:admin1_code":"4.0",
    "gn:asciiname":"Wangjia Dingdai",
    "gn:country_code":"CN",
    "gn:dem":2,
    "gn:feature_class":"P",
    "gn:feature_code":"PPL",
    "gn:name":"Wangjia Dingdai",
    "gn:population":0,
    "gn:timezone":"Asia/Shanghai",
    "iso:country":"CN",
    "name:zho_x_preferred":[
        "\u738b\u5bb6\u9876\u5788"
    ],
    "wof:name":"Wangjia Dingdai",
    "wof:placetype":"locality"
},
  "geometry": {"coordinates":[120.24379,32.03637],"type":"Point"}
}