{
  "type": "Feature",
  "properties": {
    "gn:admin1_code":"29.0",
    "gn:asciiname":"Luzhang",
    "gn:country_code":"CN",
    "gn:dem":1641,
    "gn:feature_class":"P",
    "gn:feature_code":"PPL",
    "gn:name":"Luzhang",
    "gn:population":0,
    "gn:timezone":"Asia/Shanghai",
    "iso:country":"CN",
    "name:zho_x_preferred":[
        "\u9c81\u7ae0"
    ],
    "wof:name":"Luzhang",
    "wof:placetype":"locality"
},
  "geometry": {"coordinates":[101.943,23.3125],"type":"Point"}
}