{
  "type": "Feature",
  "properties": {
    "gn:country":"CN",
    "gn:fcode":"PPL",
    "gn:population":3670,
    "iso:country":"CN",
    "name:eng_x_preferred":[
        "Xinan"
    ],
    "name:gan_x_preferred":[
        "\u6eaa\u5357\u9547"
    ],
    "name:jpn_x_preferred":[
        "\u6e13\u5357\u93ae"
    ],
    "name:und_x_variant":[
        "Nan-an"
    ],
    "name:wuu_x_preferred":[
        "\u6eaa\u5357\u9547"
    ],
    "name:zho_x_preferred":[
        "\u6eaa\u5357\u9547"
    ],
    "qs:name":"Xinan",
    "qs:photos_9r":0,
    "qs:photos_sr":0,
    "qs:pop_sr":"4",
    "wd:wordcount":303,
    "wof:name":"Xinan",
    "wof:placetype":"locality",
    "wof:population":3670
},
  "geometry": {"coordinates":[119.85556,26.72],"type":"Point"}
}