{
  "type": "Feature",
  "properties": {
    "gn:admin1_code":"18",
    "gn:asciiname":"Lamiguan",
    "gn:country_code":"CN",
    "gn:dem":969,
    "gn:feature_class":"P",
    "gn:feature_code":"PPL",
    "gn:name":"Lamiguan",
    "gn:population":0,
    "gn:timezone":"Asia/Shanghai",
    "iso:country":"CN",
    "name:zho_x_preferred":[
        "\u62c9\u7c73\u5173"
    ],
    "wof:name":"Lamiguan",
    "wof:placetype":"locality"
},
  "geometry": {"coordinates":[107.185,25.8347],"type":"Point"}
}