{
  "type": "Feature",
  "properties": {
    "gn:admin1_code":"13.0",
    "gn:asciiname":"Tuire Jiuriti",
    "gn:country_code":"CN",
    "gn:dem":4223,
    "gn:feature_class":"P",
    "gn:feature_code":"PPL",
    "gn:name":"Tuire Jiuriti",
    "gn:population":0,
    "gn:timezone":"Asia/Shanghai",
    "iso:country":"CN",
    "name:und_x_variant":[
        "\u63a8\u70ed\u5c31\u65e5\u63d0"
    ],
    "wof:name":"Tuire Jiuriti",
    "wof:placetype":"locality"
},
  "geometry": {"coordinates":[76.04607,38.25712],"type":"Point"}
}