{
  "type": "Feature",
  "properties": {
    "gn:admin1_code":"6.0",
    "gn:asciiname":"Nanshankou",
    "gn:country_code":"CN",
    "gn:dem":3103,
    "gn:feature_class":"P",
    "gn:feature_code":"PPL",
    "gn:name":"Nanshankou",
    "gn:population":0,
    "gn:timezone":"Asia/Urumqi",
    "iso:country":"CN",
    "name:und_x_variant":[
        "\u5357\u5c71\u53e3"
    ],
    "wof:name":"Nanshankou",
    "wof:placetype":"locality"
},
  "geometry": {"coordinates":[94.77535,36.16884],"type":"Point"}
}