{
  "type": "Feature",
  "properties": {
    "gn:admin1_code":"8.0",
    "gn:asciiname":"Liujingzi",
    "gn:country_code":"CN",
    "gn:dem":139,
    "gn:feature_class":"P",
    "gn:feature_code":"PPL",
    "gn:name":"Liujingzi",
    "gn:population":0,
    "gn:timezone":"Asia/Shanghai",
    "iso:country":"CN",
    "name:zha_x_preferred":[
        "\u516d\u4e95\u5b50"
    ],
    "wof:name":"Liujingzi",
    "wof:placetype":"locality"
},
  "geometry": {"coordinates":[124.65028,46.40657],"type":"Point"}
}