{
  "type": "Feature",
  "properties": {
    "gn:admin1_code":"10.0",
    "gn:asciiname":"Nanhuning",
    "gn:country_code":"CN",
    "gn:dem":48,
    "gn:feature_class":"P",
    "gn:feature_code":"PPL",
    "gn:name":"Nanhuning",
    "gn:population":0,
    "gn:timezone":"Asia/Shanghai",
    "iso:country":"CN",
    "name:zho_x_preferred":[
        "\u5357\u80e1\u5b81"
    ],
    "wof:name":"Nanhuning",
    "wof:placetype":"locality"
},
  "geometry": {"coordinates":[115.77676,39.42988],"type":"Point"}
}