{
  "type": "Feature",
  "properties": {
    "gn:admin1_code":"33.0",
    "gn:asciiname":"Yinglong",
    "gn:country_code":"CN",
    "gn:dem":681,
    "gn:feature_class":"P",
    "gn:feature_code":"PPL",
    "gn:name":"Yinglong",
    "gn:population":0,
    "gn:timezone":"Asia/Shanghai",
    "iso:country":"CN",
    "name:zho_x_preferred":[
        "\u8fce\u9f99"
    ],
    "wof:name":"Yinglong",
    "wof:placetype":"locality"
},
  "geometry": {"coordinates":[107.14821000000001,29.54781],"type":"Point"}
}