{
  "type": "Feature",
  "properties": {
    "gn:admin1_code":"33.0",
    "gn:asciiname":"Yinglong",
    "gn:country_code":"CN",
    "gn:dem":681,
    "gn:feature_class":"P",
    "gn:feature_code":"PPL",
    "gn:name":"Yinglong",
    "gn:population":0,
    "gn:timezone":"Asia/Shanghai",
    "iso:country":"CN",
    "name:fas_x_preferred":[
        "\u06cc\u06cc\u0646\u06af \u0644\u0627\u0646\u06af"
    ],
    "name:ita_x_preferred":[
        "Yinglong"
    ],
    "name:msa_x_preferred":[
        "Yinglong"
    ],
    "name:pol_x_preferred":[
        "Yinglong"
    ],
    "name:rus_x_preferred":[
        "\u0418\u043d\u043b\u0443\u043d"
    ],
    "name:sco_x_preferred":[
        "Yinglong"
    ],
    "name:spa_x_preferred":[
        "Yinglong"
    ],
    "name:vie_x_preferred":[
        "\u1ee8ng Long"
    ],
    "name:zho_x_preferred":[
        "\u8fce\u9f99"
    ],
    "wof:name":"Yinglong",
    "wof:placetype":"locality"
},
  "geometry": {"coordinates":[107.14821000000001,29.54781],"type":"Point"}
}