{
  "type": "Feature",
  "properties": {
    "gn:admin1_code":"11.0",
    "gn:asciiname":"Leijialun",
    "gn:country_code":"CN",
    "gn:dem":168,
    "gn:feature_class":"P",
    "gn:feature_code":"PPL",
    "gn:name":"Leijialun",
    "gn:population":0,
    "gn:timezone":"Asia/Shanghai",
    "iso:country":"CN",
    "name:zho_x_preferred":[
        "\u96f7\u5bb6\u4ed1"
    ],
    "wof:name":"Leijialun",
    "wof:placetype":"locality"
},
  "geometry": {"coordinates":[111.50109,28.41766],"type":"Point"}
}