{
  "type": "Feature",
  "properties": {
    "gn:admin1_code":"4.0",
    "gn:asciiname":"Gaomiaocun",
    "gn:country_code":"CN",
    "gn:dem":13,
    "gn:feature_class":"P",
    "gn:feature_code":"PPL",
    "gn:name":"Gaomiaocun",
    "gn:population":0,
    "gn:timezone":"Asia/Shanghai",
    "iso:country":"CN",
    "name:zho_x_preferred":[
        "\u9ad8\u5e99\u6751"
    ],
    "wof:name":"Gaomiaocun",
    "wof:placetype":"locality"
},
  "geometry": {"coordinates":[119.25512999999999,32.68152],"type":"Point"}
}