{
  "type": "Feature",
  "properties": {
    "gn:admin1_code":"4.0",
    "gn:asciiname":"Henghuacun",
    "gn:country_code":"CN",
    "gn:dem":16,
    "gn:feature_class":"P",
    "gn:feature_code":"PPL",
    "gn:name":"Henghuacun",
    "gn:population":0,
    "gn:timezone":"Asia/Shanghai",
    "iso:country":"CN",
    "name:zho_x_preferred":[
        "\u6052\u534e\u6751"
    ],
    "wof:name":"Henghuacun",
    "wof:placetype":"locality"
},
  "geometry": {"coordinates":[119.21887,32.3653],"type":"Point"}
}