{
  "type": "Feature",
  "properties": {
    "gn:admin1_code":"30.0",
    "gn:asciiname":"Lishuxia",
    "gn:country_code":"CN",
    "gn:dem":246,
    "gn:feature_class":"P",
    "gn:feature_code":"PPL",
    "gn:name":"Lishuxia",
    "gn:population":0,
    "gn:timezone":"Asia/Shanghai",
    "iso:country":"CN",
    "name:und_x_variant":[
        "\u68a8\u6811\u4e0b"
    ],
    "name:zho_x_preferred":[
        "\u68a8\u6811\u4e0b"
    ],
    "wof:name":"Lishuxia",
    "wof:placetype":"locality"
},
  "geometry": {"coordinates":[115.36387000000001,23.56931],"type":"Point"}
}