{
  "type": "Feature",
  "properties": {
    "gn:admin1_code":"9.0",
    "gn:asciiname":"Liuzhuang",
    "gn:country_code":"CN",
    "gn:dem":154,
    "gn:feature_class":"P",
    "gn:feature_code":"PPL",
    "gn:name":"Liuzhuang",
    "gn:population":0,
    "gn:timezone":"Asia/Shanghai",
    "iso:country":"CN",
    "name:und_x_variant":[
        "\u5218\u5e84",
        "Liuzhuang"
    ],
    "wof:name":"Liuzhuang",
    "wof:placetype":"locality"
},
  "geometry": {"coordinates":[112.47308,33.07736],"type":"Point"}
}