{
  "type": "Feature",
  "properties": {
    "gn:admin1_code":"30",
    "gn:asciiname":"Heshan",
    "gn:country_code":"CN",
    "gn:dem":13,
    "gn:feature_class":"P",
    "gn:feature_code":"PPLA4",
    "gn:name":"Heshan",
    "gn:population":0,
    "gn:timezone":"Asia/Shanghai",
    "iso:country":"CN",
    "name:ceb_x_preferred":[
        "Heshan"
    ],
    "name:deu_x_preferred":[
        "Heshan"
    ],
    "name:fra_x_preferred":[
        "Heshan"
    ],
    "name:kor_x_preferred":[
        "\ud5c8\uc0b0\uc2dc"
    ],
    "name:nor_x_preferred":[
        "Heshan"
    ],
    "name:rus_x_preferred":[
        "\u0425\u044d\u0448\u0430\u043d\u044c"
    ],
    "name:swe_x_preferred":[
        "Heshan"
    ],
    "name:und_x_variant":[
        "Hopshan",
        "Ho-shan",
        "Ho-shan-hs\u00fc",
        "Heshan Zhen",
        "\u5408\u5c71\u9547"
    ],
    "name:zho_x_preferred":[
        "\u5408\u5c71"
    ],
    "wof:name":"Heshan",
    "wof:placetype":"locality"
},
  "geometry": {"coordinates":[112.128,21.96518],"type":"Point"}
}