{
  "type": "Feature",
  "properties": {
    "gn:admin1_code":"32.0",
    "gn:asciiname":"Ganzichang",
    "gn:country_code":"CN",
    "gn:dem":470,
    "gn:feature_class":"P",
    "gn:feature_code":"PPL",
    "gn:name":"Ganzichang",
    "gn:population":0,
    "gn:timezone":"Asia/Shanghai",
    "iso:country":"CN",
    "name:zho_x_preferred":[
        "\u67d1\u5b50\u573a"
    ],
    "wof:name":"Ganzichang",
    "wof:placetype":"locality"
},
  "geometry": {"coordinates":[103.3364,29.89679000000001],"type":"Point"}
}