{
  "type": "Feature",
  "properties": {
    "gn:admin1_code":"15.0",
    "gn:asciiname":"Kejiacha",
    "gn:country_code":"CN",
    "gn:dem":1883,
    "gn:feature_class":"P",
    "gn:feature_code":"PPL",
    "gn:name":"Kejiacha",
    "gn:population":0,
    "gn:timezone":"Asia/Shanghai",
    "iso:country":"CN",
    "name:zho_x_preferred":[
        "\u7aa0\u5bb6\u5c94"
    ],
    "wof:name":"Kejiacha",
    "wof:placetype":"locality"
},
  "geometry": {"coordinates":[104.595,35.9257],"type":"Point"}
}