{
  "type": "Feature",
  "properties": {
    "gn:admin1_code":"5.0",
    "gn:asciiname":"Zhaofutun",
    "gn:country_code":"CN",
    "gn:dem":170,
    "gn:feature_class":"P",
    "gn:feature_code":"PPL",
    "gn:name":"Zhaofutun",
    "gn:population":0,
    "gn:timezone":"Asia/Shanghai",
    "iso:country":"CN",
    "name:zho_x_preferred":[
        "\u8d75\u798f\u5c6f"
    ],
    "wof:name":"Zhaofutun",
    "wof:placetype":"locality"
},
  "geometry": {"coordinates":[124.78771999999999,44.46647],"type":"Point"}
}