{
  "type": "Feature",
  "properties": {
    "gn:admin1_code":"10",
    "gn:asciiname":"Zhuanyougou",
    "gn:country_code":"CN",
    "gn:dem":546,
    "gn:feature_class":"P",
    "gn:feature_code":"PPL",
    "gn:name":"Zhuanyougou",
    "gn:population":0,
    "gn:timezone":"Asia/Shanghai",
    "iso:country":"CN",
    "name:zho_x_preferred":[
        "\u8f6c\u6709\u6c9f"
    ],
    "wof:name":"Zhuanyougou",
    "wof:placetype":"locality"
},
  "geometry": {"coordinates":[117.63909,40.56618],"type":"Point"}
}