{
  "type": "Feature",
  "properties": {
    "gn:admin1_code":"15.0",
    "gn:asciiname":"Zhangjia Buzi",
    "gn:country_code":"CN",
    "gn:dem":1151,
    "gn:feature_class":"P",
    "gn:feature_code":"PPL",
    "gn:name":"Zhangjia Buzi",
    "gn:population":0,
    "gn:timezone":"Asia/Urumqi",
    "iso:country":"CN",
    "name:zho_x_preferred":[
        "\u5f20\u5bb6\u5821\u5b50"
    ],
    "wof:name":"Zhangjia Buzi",
    "wof:placetype":"locality"
},
  "geometry": {"coordinates":[95.64570000000001,40.4528],"type":"Point"}
}