{
  "type": "Feature",
  "properties": {
    "gn:admin1_code":"16.0",
    "gn:asciiname":"Danzhushui",
    "gn:country_code":"CN",
    "gn:dem":142,
    "gn:feature_class":"P",
    "gn:feature_code":"PPL",
    "gn:name":"Danzhushui",
    "gn:population":0,
    "gn:timezone":"Asia/Shanghai",
    "iso:country":"CN",
    "name:zho_x_preferred":[
        "\u5355\u7af9\u6c34"
    ],
    "wof:name":"Danzhushui",
    "wof:placetype":"locality"
},
  "geometry": {"coordinates":[110.145,22.3793],"type":"Point"}
}