{
  "type": "Feature",
  "properties": {
    "gn:admin1_code":"3.0",
    "gn:asciiname":"Yingxiacun",
    "gn:country_code":"CN",
    "gn:dem":195,
    "gn:feature_class":"P",
    "gn:feature_code":"PPL",
    "gn:name":"Yingxiacun",
    "gn:population":0,
    "gn:timezone":"Asia/Shanghai",
    "iso:country":"CN",
    "name:und_x_variant":[
        "\u8425\u4e0b\u6751"
    ],
    "wof:name":"Yingxiacun",
    "wof:placetype":"locality"
},
  "geometry": {"coordinates":[115.6395,26.23092],"type":"Point"}
}