{
  "type": "Feature",
  "properties": {
    "gn:admin1_code":"22.0",
    "gn:asciiname":"Nantaoyuan",
    "gn:country_code":"CN",
    "gn:dem":27,
    "gn:feature_class":"P",
    "gn:feature_code":"PPL",
    "gn:name":"Nantaoyuan",
    "gn:population":0,
    "gn:timezone":"Asia/Shanghai",
    "iso:country":"CN",
    "name:zho_x_preferred":[
        "\u5357\u6843\u56ed"
    ],
    "wof:name":"Nantaoyuan",
    "wof:placetype":"locality"
},
  "geometry": {"coordinates":[116.72263999999998,40.02351],"type":"Point"}
}