{
  "type": "Feature",
  "properties": {
    "gn:admin1_code":"25",
    "gn:asciiname":"Lijiayu",
    "gn:country_code":"CN",
    "gn:dem":307,
    "gn:feature_class":"P",
    "gn:feature_code":"PPL",
    "gn:name":"Lijiayu",
    "gn:population":0,
    "gn:timezone":"Asia/Shanghai",
    "iso:country":"CN",
    "name:zho_x_preferred":[
        "\u6817\u5bb6\u5cea"
    ],
    "wof:name":"Lijiayu",
    "wof:placetype":"locality"
},
  "geometry": {"coordinates":[117.58499999999999,36.6231],"type":"Point"}
}