{
  "type": "Feature",
  "properties": {
    "gn:admin1_code":"32.0",
    "gn:asciiname":"Tudi Yakou",
    "gn:country_code":"CN",
    "gn:dem":307,
    "gn:feature_class":"P",
    "gn:feature_code":"PPL",
    "gn:name":"Tudi Yakou",
    "gn:population":0,
    "gn:timezone":"Asia/Shanghai",
    "iso:country":"CN",
    "name:zho_x_preferred":[
        "\u571f\u5730\u57ad\u53e3"
    ],
    "wof:name":"Tudi Yakou",
    "wof:placetype":"locality"
},
  "geometry": {"coordinates":[106.69199999999999,30.4352],"type":"Point"}
}