{
  "type": "Feature",
  "properties": {
    "gn:admin1_code":"32.0",
    "gn:asciiname":"Siwanpo",
    "gn:country_code":"CN",
    "gn:dem":314,
    "gn:feature_class":"P",
    "gn:feature_code":"PPL",
    "gn:name":"Siwanpo",
    "gn:population":0,
    "gn:timezone":"Asia/Shanghai",
    "iso:country":"CN",
    "name:zho_x_preferred":[
        "\u56db\u4e07\u5761"
    ],
    "wof:name":"Siwanpo",
    "wof:placetype":"locality"
},
  "geometry": {"coordinates":[106.123,30.5989],"type":"Point"}
}