{
  "type": "Feature",
  "properties": {
    "gn:admin1_code":"18",
    "gn:asciiname":"Yangmazhai",
    "gn:country_code":"CN",
    "gn:dem":1565,
    "gn:feature_class":"P",
    "gn:feature_code":"PPL",
    "gn:name":"Yangmazhai",
    "gn:population":0,
    "gn:timezone":"Asia/Shanghai",
    "iso:country":"CN",
    "name:zho_x_preferred":[
        "\u517b\u9a6c\u5be8"
    ],
    "wof:name":"Yangmazhai",
    "wof:placetype":"locality"
},
  "geometry": {"coordinates":[105.533,25.7935],"type":"Point"}
}