{
  "type": "Feature",
  "properties": {
    "gn:admin1_code":"18",
    "gn:asciiname":"Fanpo",
    "gn:country_code":"CN",
    "gn:dem":1942,
    "gn:feature_class":"P",
    "gn:feature_code":"PPL",
    "gn:name":"Fanpo",
    "gn:population":0,
    "gn:timezone":"Asia/Shanghai",
    "iso:country":"CN",
    "name:zho_x_preferred":[
        "\u7ffb\u5761"
    ],
    "wof:name":"Fanpo",
    "wof:placetype":"locality"
},
  "geometry": {"coordinates":[104.417,25.6929],"type":"Point"}
}