{
  "type": "Feature",
  "properties": {
    "gn:admin1_code":"24.0",
    "gn:asciiname":"Leijiagoucun",
    "gn:country_code":"CN",
    "gn:dem":1086,
    "gn:feature_class":"P",
    "gn:feature_code":"PPL",
    "gn:name":"Leijiagoucun",
    "gn:population":0,
    "gn:timezone":"Asia/Shanghai",
    "iso:country":"CN",
    "name:zho_x_preferred":[
        "\u96f7\u5bb6\u6c9f\u6751"
    ],
    "wof:name":"Leijiagoucun",
    "wof:placetype":"locality"
},
  "geometry": {"coordinates":[110.95975,37.23954000000001],"type":"Point"}
}