{
  "type": "Feature",
  "properties": {
    "gn:admin1_code":"4.0",
    "gn:asciiname":"Jiangjiahe",
    "gn:country_code":"CN",
    "gn:dem":5,
    "gn:feature_class":"P",
    "gn:feature_code":"PPL",
    "gn:name":"Jiangjiahe",
    "gn:population":0,
    "gn:timezone":"Asia/Shanghai",
    "iso:country":"CN",
    "name:zho_x_preferred":[
        "Jiangjiahe"
    ],
    "name:zho_x_variant":[
        "\u848b\u5bb6\u6cb3"
    ],
    "wof:name":"Jiangjiahe",
    "wof:placetype":"locality"
},
  "geometry": {"coordinates":[119.50158,33.93479],"type":"Point"}
}