{
  "type": "Feature",
  "properties": {
    "gn:admin1_code":"25",
    "gn:asciiname":"Lianwuliang",
    "gn:country_code":"CN",
    "gn:dem":18,
    "gn:feature_class":"P",
    "gn:feature_code":"PPL",
    "gn:name":"Lianwuliang",
    "gn:population":0,
    "gn:timezone":"Asia/Shanghai",
    "iso:country":"CN",
    "name:zho_x_preferred":[
        "\u8054\u4e94\u6881"
    ],
    "wof:name":"Lianwuliang",
    "wof:placetype":"locality"
},
  "geometry": {"coordinates":[117.404,37.2363],"type":"Point"}
}