{
  "type": "Feature",
  "properties": {
    "gn:admin1_code":"8.0",
    "gn:asciiname":"Yibuluo",
    "gn:country_code":"CN",
    "gn:dem":114,
    "gn:feature_class":"P",
    "gn:feature_code":"PPL",
    "gn:name":"Yibuluo",
    "gn:population":0,
    "gn:timezone":"Asia/Shanghai",
    "iso:country":"CN",
    "name:zho_x_preferred":[
        "\u4e00\u90e8\u843d"
    ],
    "wof:name":"Yibuluo",
    "wof:placetype":"locality"
},
  "geometry": {"coordinates":[129.31243000000001,46.2216],"type":"Point"}
}