{
  "type": "Feature",
  "properties": {
    "gn:admin1_code":"19.0",
    "gn:asciiname":"Chenpantun",
    "gn:country_code":"CN",
    "gn:dem":57,
    "gn:feature_class":"P",
    "gn:feature_code":"PPL",
    "gn:name":"Chenpantun",
    "gn:population":0,
    "gn:timezone":"Asia/Shanghai",
    "iso:country":"CN",
    "name:zho_x_preferred":[
        "\u9648\u80d6\u5c6f"
    ],
    "wof:name":"Chenpantun",
    "wof:placetype":"locality"
},
  "geometry": {"coordinates":[120.431,40.5604],"type":"Point"}
}