{
  "type": "Feature",
  "properties": {
    "gn:admin1_code":"25",
    "gn:asciiname":"Xiwudou",
    "gn:country_code":"CN",
    "gn:dem":382,
    "gn:feature_class":"P",
    "gn:feature_code":"PPL",
    "gn:name":"Xiwudou",
    "gn:population":0,
    "gn:timezone":"Asia/Shanghai",
    "iso:country":"CN",
    "name:zho_x_preferred":[
        "\u897f\u4e94\u9661"
    ],
    "wof:name":"Xiwudou",
    "wof:placetype":"locality"
},
  "geometry": {"coordinates":[117.99299999999999,36.1595],"type":"Point"}
}