{
  "type": "Feature",
  "properties": {
    "gn:admin1_code":"7",
    "gn:asciiname":"Liping",
    "gn:country_code":"CN",
    "gn:dem":651,
    "gn:feature_class":"P",
    "gn:feature_code":"PPL",
    "gn:name":"Liping",
    "gn:population":0,
    "gn:timezone":"Asia/Shanghai",
    "iso:country":"CN",
    "name:und_x_variant":[
        "\u68a8\u576a",
        "Liping"
    ],
    "wof:name":"Liping",
    "wof:placetype":"locality"
},
  "geometry": {"coordinates":[119.71040000000001,27.14815],"type":"Point"}
}