{
  "type": "Feature",
  "properties": {
    "gn:admin1_code":"19.0",
    "gn:asciiname":"Dongsandaogang",
    "gn:country_code":"CN",
    "gn:dem":109,
    "gn:feature_class":"P",
    "gn:feature_code":"PPL",
    "gn:name":"Dongsandaogang",
    "gn:population":0,
    "gn:timezone":"Asia/Shanghai",
    "iso:country":"CN",
    "name:zho_x_preferred":[
        "\u4e1c\u4e09\u9053\u5c97"
    ],
    "wof:name":"Dongsandaogang",
    "wof:placetype":"locality"
},
  "geometry": {"coordinates":[123.871,43.2058],"type":"Point"}
}