{
  "type": "Feature",
  "properties": {
    "gn:admin1_code":"4.0",
    "gn:asciiname":"Zhunan",
    "gn:country_code":"CN",
    "gn:dem":51,
    "gn:feature_class":"P",
    "gn:feature_code":"PPL",
    "gn:name":"Zhunan",
    "gn:population":0,
    "gn:timezone":"Asia/Shanghai",
    "iso:country":"CN",
    "name:ceb_x_preferred":[
        "Zhunan Zhen"
    ],
    "name:fra_x_preferred":[
        "Zhunan"
    ],
    "name:hak_x_preferred":[
        "Tsuk-n\u00e0m-ch\u1e73\u0301n"
    ],
    "name:ita_x_preferred":[
        "Zhunan"
    ],
    "name:jpn_x_preferred":[
        "\u7af9\u5357\u93ae"
    ],
    "name:kor_x_preferred":[
        "\uc8fc\ub09c\uc9c4"
    ],
    "name:und_x_variant":[
        "\u7af9\u5357"
    ],
    "name:vie_x_preferred":[
        "Tr\u00fac Nam"
    ],
    "name:zho_x_preferred":[
        "\u7af9\u5357\u93ae"
    ],
    "wof:name":"Zhunan",
    "wof:placetype":"locality"
},
  "geometry": {"coordinates":[118.57653999999999,34.54604],"type":"Point"}
}