{
  "type": "Feature",
  "properties": {
    "gn:admin1_code":"4.0",
    "gn:asciiname":"Xintangcun",
    "gn:country_code":"CN",
    "gn:dem":5,
    "gn:feature_class":"P",
    "gn:feature_code":"PPL",
    "gn:name":"Xintangcun",
    "gn:population":0,
    "gn:timezone":"Asia/Shanghai",
    "iso:country":"CN",
    "name:und_x_variant":[
        "Hsin-t\u2019ang",
        "Hsin-t\u2019ang-shih",
        "Xintang",
        "\u65b0\u5858",
        "Xintangcun"
    ],
    "name:zho_x_preferred":[
        "\u65b0\u5858\u6751"
    ],
    "wof:name":"Xintangcun",
    "wof:placetype":"locality"
},
  "geometry": {"coordinates":[121.20189999999999,31.52808],"type":"Point"}
}