{
  "type": "Feature",
  "properties": {
    "gn:admin1_code":"3.0",
    "gn:asciiname":"Gantianwan",
    "gn:country_code":"CN",
    "gn:dem":232,
    "gn:feature_class":"P",
    "gn:feature_code":"PPL",
    "gn:name":"Gantianwan",
    "gn:population":0,
    "gn:timezone":"Asia/Shanghai",
    "iso:country":"CN",
    "name:und_x_variant":[
        "\u5e72\u7530\u6e7e"
    ],
    "wof:name":"Gantianwan",
    "wof:placetype":"locality"
},
  "geometry": {"coordinates":[115.93197000000001,26.11441],"type":"Point"}
}