{
  "type": "Feature",
  "properties": {
    "gn:admin1_code":"29",
    "gn:asciiname":"Weijing",
    "gn:country_code":"CN",
    "gn:dem":1647,
    "gn:feature_class":"P",
    "gn:feature_code":"PPL",
    "gn:name":"Weijing",
    "gn:population":0,
    "gn:timezone":"Asia/Shanghai",
    "iso:country":"CN",
    "name:zho_x_preferred":[
        "\u5dcd\u4e95"
    ],
    "wof:name":"Weijing",
    "wof:placetype":"locality"
},
  "geometry": {"coordinates":[102.56574000000001,24.40768],"type":"Point"}
}