{
  "type": "Feature",
  "properties": {
    "gn:admin1_code":"14.0",
    "gn:asciiname":"Zhongyicun",
    "gn:country_code":"CN",
    "gn:dem":1726,
    "gn:feature_class":"P",
    "gn:feature_code":"PPL",
    "gn:name":"Zhongyicun",
    "gn:population":0,
    "gn:timezone":"Asia/Urumqi",
    "iso:country":"CN",
    "name:zho_x_preferred":[
        "\u4e2d\u4e00\u6751"
    ],
    "wof:name":"Zhongyicun",
    "wof:placetype":"locality"
},
  "geometry": {"coordinates":[97.01196,28.49604],"type":"Point"}
}