{
  "type": "Feature",
  "properties": {
    "gn:admin1_code":"5.0",
    "gn:asciiname":"Yuanjia Wopeng",
    "gn:country_code":"CN",
    "gn:dem":153,
    "gn:feature_class":"P",
    "gn:feature_code":"PPL",
    "gn:name":"Yuanjia Wopeng",
    "gn:population":0,
    "gn:timezone":"Asia/Shanghai",
    "iso:country":"CN",
    "name:zho_x_preferred":[
        "\u82d1\u5bb6\u7a9d\u68da"
    ],
    "wof:name":"Yuanjia Wopeng",
    "wof:placetype":"locality"
},
  "geometry": {"coordinates":[122.79198999999998,44.52931],"type":"Point"}
}