{
  "type": "Feature",
  "properties": {
    "gn:admin1_code":"22.0",
    "gn:asciiname":"Dongbanbidiancun",
    "gn:country_code":"CN",
    "gn:dem":22,
    "gn:feature_class":"P",
    "gn:feature_code":"PPL",
    "gn:name":"Dongbanbidiancun",
    "gn:population":0,
    "gn:timezone":"Asia/Shanghai",
    "iso:country":"CN",
    "name:zho_x_preferred":[
        "\u4e1c\u534a\u58c1\u5e97\u6751"
    ],
    "wof:name":"Dongbanbidiancun",
    "wof:placetype":"locality"
},
  "geometry": {"coordinates":[116.68028,39.63834],"type":"Point"}
}