{
  "type": "Feature",
  "properties": {
    "gn:admin1_code":"5.0",
    "gn:asciiname":"Zhongshengcun",
    "gn:country_code":"CN",
    "gn:dem":310,
    "gn:feature_class":"P",
    "gn:feature_code":"PPL",
    "gn:name":"Zhongshengcun",
    "gn:population":0,
    "gn:timezone":"Asia/Shanghai",
    "iso:country":"CN",
    "name:zho_x_preferred":[
        "\u4e2d\u80dc\u6751"
    ],
    "wof:name":"Zhongshengcun",
    "wof:placetype":"locality"
},
  "geometry": {"coordinates":[127.22799999999999,43.15065],"type":"Point"}
}