{
  "type": "Feature",
  "properties": {
    "gn:admin1_code":"22.0",
    "gn:asciiname":"Nanshulincun",
    "gn:country_code":"CN",
    "gn:dem":499,
    "gn:feature_class":"P",
    "gn:feature_code":"PPL",
    "gn:name":"Nanshulincun",
    "gn:population":0,
    "gn:timezone":"Asia/Shanghai",
    "iso:country":"CN",
    "name:zho_x_preferred":[
        "\u5357\u6811\u6797\u6751"
    ],
    "wof:name":"Nanshulincun",
    "wof:placetype":"locality"
},
  "geometry": {"coordinates":[117.19459999999999,40.30047],"type":"Point"}
}