{
  "type": "Feature",
  "properties": {
    "gn:admin1_code":"4.0",
    "gn:asciiname":"Sunxing",
    "gn:country_code":"CN",
    "gn:dem":3,
    "gn:feature_class":"P",
    "gn:feature_code":"PPL",
    "gn:name":"Sunxing",
    "gn:population":0,
    "gn:timezone":"Asia/Shanghai",
    "iso:country":"CN",
    "name:zho_x_preferred":[
        "Sunxing"
    ],
    "name:zho_x_variant":[
        "\u5b59\u5174"
    ],
    "wof:name":"Sunxing",
    "wof:placetype":"locality"
},
  "geometry": {"coordinates":[119.44123999999999,34.3631],"type":"Point"}
}