{
  "type": "Feature",
  "properties": {
    "gn:admin1_code":"10",
    "gn:asciiname":"Liucun",
    "gn:cc2":"CN",
    "gn:country_code":"CN",
    "gn:dem":30,
    "gn:feature_class":"P",
    "gn:feature_code":"PPL",
    "gn:name":"Liucun",
    "gn:population":0,
    "gn:timezone":"Asia/Shanghai",
    "iso:country":"CN",
    "name:und_x_variant":[
        "Liu-ts\u2019un",
        "Liucun"
    ],
    "wof:name":"Liucun",
    "wof:placetype":"locality"
},
  "geometry": {"coordinates":[115.3275,38.43528],"type":"Point"}
}