{
  "type": "Feature",
  "properties": {
    "gn:admin1_code":"8.0",
    "gn:asciiname":"Zhongyicun",
    "gn:country_code":"CN",
    "gn:dem":178,
    "gn:feature_class":"P",
    "gn:feature_code":"PPL",
    "gn:name":"Zhongyicun",
    "gn:population":0,
    "gn:timezone":"Asia/Shanghai",
    "iso:country":"CN",
    "name:zho_x_preferred":[
        "\u5fe0\u4e49\u6751"
    ],
    "wof:name":"Zhongyicun",
    "wof:placetype":"locality"
},
  "geometry": {"coordinates":[130.42526000000001,45.91224],"type":"Point"}
}