{
  "type": "Feature",
  "properties": {
    "gn:admin1_code":"25",
    "gn:asciiname":"Shangweicheng",
    "gn:country_code":"CN",
    "gn:dem":275,
    "gn:feature_class":"P",
    "gn:feature_code":"PPL",
    "gn:name":"Shangweicheng",
    "gn:population":0,
    "gn:timezone":"Asia/Shanghai",
    "iso:country":"CN",
    "name:zho_x_preferred":[
        "\u4e0a\u82c7\u57ce"
    ],
    "wof:name":"Shangweicheng",
    "wof:placetype":"locality"
},
  "geometry": {"coordinates":[120.899,37.2475],"type":"Point"}
}