{
  "type": "Feature",
  "properties": {
    "gn:admin1_code":"18",
    "gn:asciiname":"Gaojiazui",
    "gn:country_code":"CN",
    "gn:dem":784,
    "gn:feature_class":"P",
    "gn:feature_code":"PPL",
    "gn:name":"Gaojiazui",
    "gn:population":0,
    "gn:timezone":"Asia/Shanghai",
    "iso:country":"CN",
    "name:zho_x_preferred":[
        "\u9ad8\u5bb6\u5480"
    ],
    "wof:name":"Gaojiazui",
    "wof:placetype":"locality"
},
  "geometry": {"coordinates":[107.306,28.0567],"type":"Point"}
}