{
  "type": "Feature",
  "properties": {
    "gn:admin1_code":"2.0",
    "gn:asciiname":"Shanjiaoyuan",
    "gn:country_code":"CN",
    "gn:dem":660,
    "gn:feature_class":"P",
    "gn:feature_code":"PPL",
    "gn:name":"Shanjiaoyuan",
    "gn:population":0,
    "gn:timezone":"Asia/Shanghai",
    "iso:country":"CN",
    "name:zho_x_preferred":[
        "\u5c71\u89d2\u56ed"
    ],
    "wof:name":"Shanjiaoyuan",
    "wof:placetype":"locality"
},
  "geometry": {"coordinates":[120.49113,28.94357],"type":"Point"}
}