{
  "type": "Feature",
  "properties": {
    "gn:admin1_code":"3.0",
    "gn:asciiname":"Yuanxilong",
    "gn:country_code":"CN",
    "gn:dem":34,
    "gn:feature_class":"P",
    "gn:feature_code":"PPL",
    "gn:name":"Yuanxilong",
    "gn:population":0,
    "gn:timezone":"Asia/Shanghai",
    "iso:country":"CN",
    "name:und_x_variant":[
        "\u6c85\u897f\u5784"
    ],
    "wof:name":"Yuanxilong",
    "wof:placetype":"locality"
},
  "geometry": {"coordinates":[115.98726000000001,28.33792],"type":"Point"}
}