{
  "type": "Feature",
  "properties": {
    "gn:admin1_code":"32.0",
    "gn:asciiname":"Doujiaying",
    "gn:country_code":"CN",
    "gn:dem":763,
    "gn:feature_class":"P",
    "gn:feature_code":"PPL",
    "gn:name":"Doujiaying",
    "gn:population":0,
    "gn:timezone":"Asia/Shanghai",
    "iso:country":"CN",
    "name:zho_x_preferred":[
        "\u8c46\u5bb6\u8425"
    ],
    "wof:name":"Doujiaying",
    "wof:placetype":"locality"
},
  "geometry": {"coordinates":[107.876,32.0407],"type":"Point"}
}