{
  "type": "Feature",
  "properties": {
    "gn:admin1_code":"3.0",
    "gn:asciiname":"Shangxiaxi",
    "gn:country_code":"CN",
    "gn:dem":313,
    "gn:feature_class":"P",
    "gn:feature_code":"PPL",
    "gn:name":"Shangxiaxi",
    "gn:population":0,
    "gn:timezone":"Asia/Shanghai",
    "iso:country":"CN",
    "name:und_x_variant":[
        "\u4e0a\u4e0b\u6eaa"
    ],
    "wof:name":"Shangxiaxi",
    "wof:placetype":"locality"
},
  "geometry": {"coordinates":[115.72041000000002,26.93316],"type":"Point"}
}