{
  "type": "Feature",
  "properties": {
    "gn:admin1_code":"32",
    "gn:asciiname":"Qinjia Miaozi",
    "gn:country_code":"CN",
    "gn:dem":382,
    "gn:feature_class":"P",
    "gn:feature_code":"PPL",
    "gn:name":"Qinjia Miaozi",
    "gn:population":0,
    "gn:timezone":"Asia/Shanghai",
    "iso:country":"CN",
    "name:zho_x_preferred":[
        "\u79e6\u5bb6\u5e99\u5b50"
    ],
    "wof:name":"Qinjia Miaozi",
    "wof:placetype":"locality"
},
  "geometry": {"coordinates":[106.42874,30.48854],"type":"Point"}
}