{
  "type": "Feature",
  "properties": {
    "gn:admin1_code":"7.0",
    "gn:asciiname":"Wucuoshan",
    "gn:country_code":"CN",
    "gn:dem":738,
    "gn:feature_class":"P",
    "gn:feature_code":"PPL",
    "gn:name":"Wucuoshan",
    "gn:population":0,
    "gn:timezone":"Asia/Shanghai",
    "iso:country":"CN",
    "name:zho_x_preferred":[
        "\u5434\u539d\u5c71"
    ],
    "wof:name":"Wucuoshan",
    "wof:placetype":"locality"
},
  "geometry": {"coordinates":[117.48772,27.14996],"type":"Point"}
}