{
  "type": "Feature",
  "properties": {
    "gn:admin1_code":"18",
    "gn:asciiname":"Niuyue",
    "gn:country_code":"CN",
    "gn:dem":1333,
    "gn:feature_class":"P",
    "gn:feature_code":"PPL",
    "gn:name":"Niuyue",
    "gn:population":0,
    "gn:timezone":"Asia/Shanghai",
    "iso:country":"CN",
    "name:zho_x_preferred":[
        "\u725b\u6708"
    ],
    "wof:name":"Niuyue",
    "wof:placetype":"locality"
},
  "geometry": {"coordinates":[106.172,25.5034],"type":"Point"}
}