{
  "type": "Feature",
  "properties": {
    "gn:admin1_code":"32.0",
    "gn:asciiname":"Amitang",
    "gn:country_code":"CN",
    "gn:dem":3106,
    "gn:feature_class":"P",
    "gn:feature_code":"PPL",
    "gn:name":"Amitang",
    "gn:population":0,
    "gn:timezone":"Asia/Shanghai",
    "iso:country":"CN",
    "name:zho_x_preferred":[
        "\u963f\u7c73\u5858"
    ],
    "wof:name":"Amitang",
    "wof:placetype":"locality"
},
  "geometry": {"coordinates":[102.90061,34.09012],"type":"Point"}
}