{
  "type": "Feature",
  "properties": {
    "gn:admin1_code":"2.0",
    "gn:asciiname":"Meiliangqiao",
    "gn:country_code":"CN",
    "gn:dem":12,
    "gn:feature_class":"P",
    "gn:feature_code":"PPL",
    "gn:name":"Meiliangqiao",
    "gn:population":0,
    "gn:timezone":"Asia/Shanghai",
    "iso:country":"CN",
    "name:zho_x_preferred":[
        "\u6885\u6881\u6865"
    ],
    "wof:name":"Meiliangqiao",
    "wof:placetype":"locality"
},
  "geometry": {"coordinates":[121.37528,29.84333],"type":"Point"}
}