{
  "type": "Feature",
  "properties": {
    "gn:admin1_code":"04",
    "gn:asciiname":"Xiehe",
    "gn:country_code":"CN",
    "gn:dem":1,
    "gn:feature_class":"P",
    "gn:feature_code":"PPL",
    "gn:name":"Xiehe",
    "gn:population":0,
    "gn:timezone":"Asia/Shanghai",
    "iso:country":"CN",
    "name:und_x_variant":[
        "Xiehezhen"
    ],
    "name:zho_x_preferred":[
        "\u534f\u548c"
    ],
    "wof:name":"Xiehe",
    "wof:placetype":"locality"
},
  "geometry": {"coordinates":[121.30500000000001,32.24444],"type":"Point"}
}