{
  "type": "Feature",
  "properties": {
    "gn:admin1_code":"07",
    "gn:asciiname":"Taihua",
    "gn:country_code":"CN",
    "gn:dem":528,
    "gn:feature_class":"P",
    "gn:feature_code":"PPLA4",
    "gn:name":"Taihua",
    "gn:population":0,
    "gn:timezone":"Asia/Shanghai",
    "iso:country":"CN",
    "name:und_x_variant":[
        "Taihua Zhen"
    ],
    "name:zho_x_preferred":[
        "\u592a\u534e"
    ],
    "wof:name":"Taihua",
    "wof:placetype":"locality"
},
  "geometry": {"coordinates":[117.71787,25.81489],"type":"Point"}
}