{
  "type": "Feature",
  "properties": {
    "gn:admin1_code":"30.0",
    "gn:asciiname":"Rongzhou",
    "gn:country_code":"CN",
    "gn:dem":10,
    "gn:feature_class":"P",
    "gn:feature_code":"PPL",
    "gn:name":"Rongzhou",
    "gn:population":0,
    "gn:timezone":"Asia/Shanghai",
    "iso:country":"CN",
    "name:zho_x_preferred":[
        "\u7194\u5dde"
    ],
    "wof:name":"Rongzhou",
    "wof:placetype":"locality"
},
  "geometry": {"coordinates":[113.05037,22.99636],"type":"Point"}
}