{
  "type": "Feature",
  "properties": {
    "gn:admin1_code":"12.0",
    "gn:asciiname":"Yangguba",
    "gn:country_code":"CN",
    "gn:dem":1245,
    "gn:feature_class":"P",
    "gn:feature_code":"PPL",
    "gn:name":"Yangguba",
    "gn:population":0,
    "gn:timezone":"Asia/Shanghai",
    "iso:country":"CN",
    "name:zho_x_preferred":[
        "\u517b\u59d1\u575d"
    ],
    "wof:name":"Yangguba",
    "wof:placetype":"locality"
},
  "geometry": {"coordinates":[109.68205,30.1602],"type":"Point"}
}