{
  "type": "Feature",
  "properties": {
    "gn:admin1_code":"30",
    "gn:asciiname":"Jiaoliao",
    "gn:country_code":"CN",
    "gn:dem":10,
    "gn:feature_class":"P",
    "gn:feature_code":"PPL",
    "gn:name":"Jiaoliao",
    "gn:population":0,
    "gn:timezone":"Asia/Urumqi",
    "iso:country":"CN",
    "name:zho_x_preferred":[
        "Chiao-liao-ts\u2019un"
    ],
    "name:zho_x_variant":[
        "\u4ea4\u5bee"
    ],
    "wof:name":"Jiaoliao",
    "wof:placetype":"locality"
},
  "geometry": {"coordinates":[109.83575,20.60117],"type":"Point"}
}