{
  "type": "Feature",
  "properties": {
    "gn:admin1_code":"14.0",
    "gn:asciiname":"Jiarangcun",
    "gn:country_code":"CN",
    "gn:dem":4033,
    "gn:feature_class":"P",
    "gn:feature_code":"PPL",
    "gn:name":"Jiarangcun",
    "gn:population":0,
    "gn:timezone":"Asia/Urumqi",
    "iso:country":"CN",
    "name:zho_x_preferred":[
        "\u52a0\u8ba9\u6751"
    ],
    "wof:name":"Jiarangcun",
    "wof:placetype":"locality"
},
  "geometry": {"coordinates":[92.62112999999999,29.05857],"type":"Point"}
}