{
  "type": "Feature",
  "properties": {
    "gn:admin1_code":"26.0",
    "gn:asciiname":"Lijia Yuanzi",
    "gn:country_code":"CN",
    "gn:dem":970,
    "gn:feature_class":"P",
    "gn:feature_code":"PPL",
    "gn:name":"Lijia Yuanzi",
    "gn:population":0,
    "gn:timezone":"Asia/Shanghai",
    "iso:country":"CN",
    "name:zho_x_preferred":[
        "\u674e\u5bb6\u9662\u5b50"
    ],
    "wof:name":"Lijia Yuanzi",
    "wof:placetype":"locality"
},
  "geometry": {"coordinates":[108.07424,32.43036],"type":"Point"}
}