{
  "type": "Feature",
  "properties": {
    "gn:admin1_code":"15.0",
    "gn:asciiname":"Dongfeng Nongchang Erzhan",
    "gn:country_code":"CN",
    "gn:dem":1089,
    "gn:feature_class":"P",
    "gn:feature_code":"PPLF",
    "gn:name":"Dongfeng Nongchang Erzhan",
    "gn:population":0,
    "gn:timezone":"Asia/Urumqi",
    "iso:country":"CN",
    "name:eng_x_preferred":[
        "Dongfeng Nongchang Second Station"
    ],
    "name:zho_x_preferred":[
        "\u4e1c\u98ce\u519c\u573a\u4e8c\u7ad9"
    ],
    "wof:name":"Dongfeng Nongchang Erzhan",
    "wof:placetype":"locality"
},
  "geometry": {"coordinates":[94.84592000000001,40.22954],"type":"Point"}
}