{
  "type": "Feature",
  "properties": {
    "gn:admin1_code":"19.0",
    "gn:asciiname":"Zhaoweizi",
    "gn:country_code":"CN",
    "gn:dem":116,
    "gn:feature_class":"P",
    "gn:feature_code":"PPL",
    "gn:name":"Zhaoweizi",
    "gn:population":0,
    "gn:timezone":"Asia/Shanghai",
    "iso:country":"CN",
    "name:zho_x_preferred":[
        "\u8d75\u5d34\u5b50"
    ],
    "wof:name":"Zhaoweizi",
    "wof:placetype":"locality"
},
  "geometry": {"coordinates":[122.14049,39.85516],"type":"Point"}
}