{
  "type": "Feature",
  "properties": {
    "gn:admin1_code":"32.0",
    "gn:asciiname":"Lantiangou",
    "gn:country_code":"CN",
    "gn:dem":1668,
    "gn:feature_class":"P",
    "gn:feature_code":"PPL",
    "gn:name":"Lantiangou",
    "gn:population":0,
    "gn:timezone":"Asia/Shanghai",
    "iso:country":"CN",
    "name:zho_x_preferred":[
        "\u70c2\u7530\u6c9f"
    ],
    "wof:name":"Lantiangou",
    "wof:placetype":"locality"
},
  "geometry": {"coordinates":[102.66188,29.53352000000001],"type":"Point"}
}