{
  "type": "Feature",
  "properties": {
    "gn:admin1_code":"26.0",
    "gn:asciiname":"Wangtangcun",
    "gn:country_code":"CN",
    "gn:dem":424,
    "gn:feature_class":"P",
    "gn:feature_code":"PPL",
    "gn:name":"Wangtangcun",
    "gn:population":0,
    "gn:timezone":"Asia/Shanghai",
    "iso:country":"CN",
    "name:zho_x_preferred":[
        "\u738b\u5510\u6751"
    ],
    "wof:name":"Wangtangcun",
    "wof:placetype":"locality"
},
  "geometry": {"coordinates":[108.26177,34.16206],"type":"Point"}
}