{
  "type": "Feature",
  "properties": {
    "gn:admin1_code":"10.0",
    "gn:asciiname":"Dingcun",
    "gn:country_code":"CN",
    "gn:dem":8,
    "gn:feature_class":"P",
    "gn:feature_code":"PPL",
    "gn:name":"Dingcun",
    "gn:population":0,
    "gn:timezone":"Asia/Shanghai",
    "iso:country":"CN",
    "name:swe_x_preferred":[
        "Dingcun"
    ],
    "name:uzb_x_preferred":[
        "Dinsun"
    ],
    "name:zho_x_preferred":[
        "\u4e01\u6751"
    ],
    "wof:name":"Dingcun",
    "wof:placetype":"locality"
},
  "geometry": {"coordinates":[117.41200000000001,38.1852],"type":"Point"}
}