{
  "type": "Feature",
  "properties": {
    "gn:admin1_code":"29.0",
    "gn:asciiname":"Qidui",
    "gn:country_code":"CN",
    "gn:dem":1059,
    "gn:feature_class":"P",
    "gn:feature_code":"PPL",
    "gn:name":"Qidui",
    "gn:population":0,
    "gn:timezone":"Asia/Shanghai",
    "iso:country":"CN",
    "name:zho_x_preferred":[
        "\u4e03\u961f"
    ],
    "wof:name":"Qidui",
    "wof:placetype":"locality"
},
  "geometry": {"coordinates":[100.379,22.2557],"type":"Point"}
}