{
  "type": "Feature",
  "properties": {
    "gn:admin1_code":"15.0",
    "gn:asciiname":"Lujiaquan",
    "gn:country_code":"CN",
    "gn:dem":1837,
    "gn:feature_class":"P",
    "gn:feature_code":"PPL",
    "gn:name":"L\u00fcjiaquan",
    "gn:population":0,
    "gn:timezone":"Asia/Shanghai",
    "iso:country":"CN",
    "name:und_x_variant":[
        "L\u00fcjiaquan"
    ],
    "name:zho_x_preferred":[
        "\u5415\u5bb6\u6cc9"
    ],
    "wof:name":"Lujiaquan",
    "wof:placetype":"locality"
},
  "geometry": {"coordinates":[98.958,39.3348],"type":"Point"}
}