{
  "type": "Feature",
  "properties": {
    "gn:admin1_code":"16.0",
    "gn:asciiname":"Qinbi",
    "gn:country_code":"CN",
    "gn:dem":328,
    "gn:feature_class":"P",
    "gn:feature_code":"PPL",
    "gn:name":"Qinbi",
    "gn:population":0,
    "gn:timezone":"Asia/Shanghai",
    "iso:country":"CN",
    "name:zho_x_preferred":[
        "\u4fb5\u7b14"
    ],
    "wof:name":"Qinbi",
    "wof:placetype":"locality"
},
  "geometry": {"coordinates":[106.845,22.6029],"type":"Point"}
}