{
  "type": "Feature",
  "properties": {
    "gn:admin1_code":"10",
    "gn:asciiname":"Menzhai",
    "gn:country_code":"CN",
    "gn:dem":47,
    "gn:feature_class":"P",
    "gn:feature_code":"PPL",
    "gn:name":"Menzhai",
    "gn:population":0,
    "gn:timezone":"Asia/Shanghai",
    "iso:country":"CN",
    "name:zho_x_preferred":[
        "\u95e8\u5be8"
    ],
    "wof:name":"Menzhai",
    "wof:placetype":"locality"
},
  "geometry": {"coordinates":[114.81,36.6992],"type":"Point"}
}