{
  "type": "Feature",
  "properties": {
    "gn:admin1_code":"30.0",
    "gn:asciiname":"Xianbian",
    "gn:country_code":"CN",
    "gn:dem":2,
    "gn:feature_class":"P",
    "gn:feature_code":"PPL",
    "gn:name":"Xianbian",
    "gn:population":0,
    "gn:timezone":"Asia/Shanghai",
    "iso:country":"CN",
    "name:zho_x_preferred":[
        "\u51bc\u8fb9"
    ],
    "wof:name":"Xianbian",
    "wof:placetype":"locality"
},
  "geometry": {"coordinates":[113.02382,23.08924],"type":"Point"}
}