{
  "type": "Feature",
  "properties": {
    "gn:admin1_code":"6.0",
    "gn:asciiname":"Longgesi",
    "gn:country_code":"CN",
    "gn:dem":4279,
    "gn:feature_class":"P",
    "gn:feature_code":"PPL",
    "gn:name":"Longgesi",
    "gn:population":0,
    "gn:timezone":"Asia/Shanghai",
    "iso:country":"CN",
    "name:zho_x_preferred":[
        "\u9686\u683c\u5bfa"
    ],
    "wof:name":"Longgesi",
    "wof:placetype":"locality"
},
  "geometry": {"coordinates":[100.88612000000001,33.27818],"type":"Point"}
}