{
  "type": "Feature",
  "properties": {
    "gn:admin1_code":"24.0",
    "gn:asciiname":"Zhaihoucun",
    "gn:country_code":"CN",
    "gn:dem":462,
    "gn:feature_class":"P",
    "gn:feature_code":"PPL",
    "gn:name":"Zhaihoucun",
    "gn:population":0,
    "gn:timezone":"Asia/Shanghai",
    "iso:country":"CN",
    "name:zho_x_preferred":[
        "\u5be8\u540e\u6751"
    ],
    "wof:name":"Zhaihoucun",
    "wof:placetype":"locality"
},
  "geometry": {"coordinates":[111.35625,34.83468],"type":"Point"}
}