{
  "type": "Feature",
  "properties": {
    "gn:admin1_code":"26",
    "gn:asciiname":"Pengtancun",
    "gn:country_code":"CN",
    "gn:dem":1416,
    "gn:feature_class":"P",
    "gn:feature_code":"PPL",
    "gn:name":"Pengtancun",
    "gn:population":0,
    "gn:timezone":"Asia/Shanghai",
    "iso:country":"CN",
    "name:und_x_variant":[
        "P\u2019eng-chia-t\u2019an",
        "Pengtan",
        "Pengtancun"
    ],
    "name:zho_x_preferred":[
        "\u5f6d\u6ee9\u6751"
    ],
    "wof:name":"Pengtancun",
    "wof:placetype":"locality"
},
  "geometry": {"coordinates":[107.65649000000001,37.51707],"type":"Point"}
}