{
  "type": "Feature",
  "properties": {
    "gn:admin1_code":"15.0",
    "gn:asciiname":"Yangsheng",
    "gn:country_code":"CN",
    "gn:dem":2759,
    "gn:feature_class":"P",
    "gn:feature_code":"PPL",
    "gn:name":"Yangsheng",
    "gn:population":0,
    "gn:timezone":"Asia/Shanghai",
    "iso:country":"CN",
    "name:und_x_variant":[
        "\u6768\u5347"
    ],
    "wof:name":"Yangsheng",
    "wof:placetype":"locality"
},
  "geometry": {"coordinates":[103.40931999999999,34.65243],"type":"Point"}
}