{
  "type": "Feature",
  "properties": {
    "gn:admin1_code":"12.0",
    "gn:asciiname":"Dongmenshan",
    "gn:country_code":"CN",
    "gn:dem":894,
    "gn:feature_class":"P",
    "gn:feature_code":"PPL",
    "gn:name":"Dongmenshan",
    "gn:population":0,
    "gn:timezone":"Asia/Shanghai",
    "iso:country":"CN",
    "name:zho_x_preferred":[
        "\u4e1c\u95e8\u5c71"
    ],
    "wof:name":"Dongmenshan",
    "wof:placetype":"locality"
},
  "geometry": {"coordinates":[110.22874,30.38356],"type":"Point"}
}