{
  "type": "Feature",
  "properties": {
    "gn:admin1_code":"3.0",
    "gn:asciiname":"Panjiacun",
    "gn:country_code":"CN",
    "gn:dem":45,
    "gn:feature_class":"P",
    "gn:feature_code":"PPL",
    "gn:name":"Panjiacun",
    "gn:population":0,
    "gn:timezone":"Asia/Shanghai",
    "iso:country":"CN",
    "name:und_x_variant":[
        "\u6f58\u5bb6\u6751"
    ],
    "wof:name":"Panjiacun",
    "wof:placetype":"locality"
},
  "geometry": {"coordinates":[115.57795,28.69758],"type":"Point"}
}