{
  "type": "Feature",
  "properties": {
    "gn:admin1_code":"19.0",
    "gn:asciiname":"Liangshuihecun",
    "gn:country_code":"CN",
    "gn:dem":150,
    "gn:feature_class":"P",
    "gn:feature_code":"PPL",
    "gn:name":"Liangshuihecun",
    "gn:population":0,
    "gn:timezone":"Asia/Shanghai",
    "iso:country":"CN",
    "name:zho_x_preferred":[
        "\u51c9\u6c34\u6cb3\u6751"
    ],
    "wof:name":"Liangshuihecun",
    "wof:placetype":"locality"
},
  "geometry": {"coordinates":[120.77656,41.7594],"type":"Point"}
}