{
  "type": "Feature",
  "properties": {
    "gn:admin1_code":"32.0",
    "gn:asciiname":"Ganbawang",
    "gn:country_code":"CN",
    "gn:dem":488,
    "gn:feature_class":"P",
    "gn:feature_code":"PPL",
    "gn:name":"Ganbawang",
    "gn:population":0,
    "gn:timezone":"Asia/Shanghai",
    "iso:country":"CN",
    "name:zho_x_preferred":[
        "\u5e72\u575d\u738b"
    ],
    "wof:name":"Ganbawang",
    "wof:placetype":"locality"
},
  "geometry": {"coordinates":[103.58799999999999,30.4304],"type":"Point"}
}