{
  "type": "Feature",
  "properties": {
    "gn:admin1_code":"19.0",
    "gn:asciiname":"Suntaitun",
    "gn:country_code":"CN",
    "gn:dem":13,
    "gn:feature_class":"P",
    "gn:feature_code":"PPL",
    "gn:name":"Suntaitun",
    "gn:population":0,
    "gn:timezone":"Asia/Shanghai",
    "iso:country":"CN",
    "name:zho_x_preferred":[
        "\u5b59\u53f0\u5c6f"
    ],
    "wof:name":"Suntaitun",
    "wof:placetype":"locality"
},
  "geometry": {"coordinates":[122.545,39.5251],"type":"Point"}
}