{
  "type": "Feature",
  "properties": {
    "gn:admin1_code":"32.0",
    "gn:asciiname":"Degong",
    "gn:country_code":"CN",
    "gn:dem":3243,
    "gn:feature_class":"P",
    "gn:feature_code":"PPL",
    "gn:name":"Degong",
    "gn:population":0,
    "gn:timezone":"Asia/Shanghai",
    "iso:country":"CN",
    "name:zho_x_preferred":[
        "\u5fb7\u5de5"
    ],
    "wof:name":"Degong",
    "wof:placetype":"locality"
},
  "geometry": {"coordinates":[98.70113000000001,31.31557],"type":"Point"}
}