{
  "type": "Feature",
  "properties": {
    "gn:admin1_code":"15.0",
    "gn:asciiname":"Laoya",
    "gn:country_code":"CN",
    "gn:dem":2310,
    "gn:feature_class":"P",
    "gn:feature_code":"PPL",
    "gn:name":"Laoya",
    "gn:population":0,
    "gn:timezone":"Asia/Shanghai",
    "iso:country":"CN",
    "name:zho_x_preferred":[
        "\u8001\u5d16"
    ],
    "wof:name":"Laoya",
    "wof:placetype":"locality"
},
  "geometry": {"coordinates":[104.438,36.9917],"type":"Point"}
}