{
  "type": "Feature",
  "properties": {
    "gn:admin1_code":"18.0",
    "gn:asciiname":"Rongbei",
    "gn:country_code":"CN",
    "gn:dem":1128,
    "gn:feature_class":"P",
    "gn:feature_code":"PPL",
    "gn:name":"Rongbei",
    "gn:population":0,
    "gn:timezone":"Asia/Shanghai",
    "iso:country":"CN",
    "name:zho_x_preferred":[
        "\u5197\u8d1d"
    ],
    "wof:name":"Rongbei",
    "wof:placetype":"locality"
},
  "geometry": {"coordinates":[105.678,25.0442],"type":"Point"}
}