{
  "type": "Feature",
  "properties": {
    "gn:admin1_code":"3.0",
    "gn:asciiname":"Qingtangshan",
    "gn:country_code":"CN",
    "gn:dem":101,
    "gn:feature_class":"P",
    "gn:feature_code":"PPL",
    "gn:name":"Qingtangshan",
    "gn:population":0,
    "gn:timezone":"Asia/Shanghai",
    "iso:country":"CN",
    "name:und_x_variant":[
        "\u9752\u5858\u5c71"
    ],
    "wof:name":"Qingtangshan",
    "wof:placetype":"locality"
},
  "geometry": {"coordinates":[114.48692,27.12149],"type":"Point"}
}