{
  "type": "Feature",
  "properties": {
    "gn:admin1_code":"15.0",
    "gn:asciiname":"Xiakualang",
    "gn:country_code":"CN",
    "gn:dem":3257,
    "gn:feature_class":"P",
    "gn:feature_code":"PPL",
    "gn:name":"Xiakualang",
    "gn:population":0,
    "gn:timezone":"Asia/Shanghai",
    "iso:country":"CN",
    "name:zho_x_preferred":[
        "\u4e0b\u57ae\u7405"
    ],
    "wof:name":"Xiakualang",
    "wof:placetype":"locality"
},
  "geometry": {"coordinates":[102.68000000000001,37.1556],"type":"Point"}
}