{
  "type": "Feature",
  "properties": {
    "gn:admin1_code":"5.0",
    "gn:asciiname":"Shaojia Wobu",
    "gn:country_code":"CN",
    "gn:dem":154,
    "gn:feature_class":"P",
    "gn:feature_code":"PPL",
    "gn:name":"Shaojia Wobu",
    "gn:population":0,
    "gn:timezone":"Asia/Shanghai",
    "iso:country":"CN",
    "name:zho_x_preferred":[
        "\u90b5\u5bb6\u7a9d\u5821"
    ],
    "wof:name":"Shaojia Wobu",
    "wof:placetype":"locality"
},
  "geometry": {"coordinates":[124.31237,43.19759000000001],"type":"Point"}
}