{
  "type": "Feature",
  "properties": {
    "gn:admin1_code":"24",
    "gn:asciiname":"Guolicun",
    "gn:country_code":"CN",
    "gn:dem":362,
    "gn:feature_class":"P",
    "gn:feature_code":"PPL",
    "gn:name":"Guolicun",
    "gn:population":0,
    "gn:timezone":"Asia/Shanghai",
    "iso:country":"CN",
    "name:und_x_variant":[
        "Kuo-li-ts\u2019un",
        "Kuo-li",
        "Guoli",
        "Guolicun"
    ],
    "name:zho_x_preferred":[
        "\u90ed\u674e\u6751"
    ],
    "wof:name":"Guolicun",
    "wof:placetype":"locality"
},
  "geometry": {"coordinates":[110.53608,34.87274],"type":"Point"}
}