{
  "type": "Feature",
  "properties": {
    "gn:admin1_code":"4.0",
    "gn:asciiname":"Shuangtan",
    "gn:country_code":"CN",
    "gn:dem":40,
    "gn:feature_class":"P",
    "gn:feature_code":"PPL",
    "gn:name":"Shuangtan",
    "gn:population":0,
    "gn:timezone":"Asia/Shanghai",
    "iso:country":"CN",
    "name:zho_x_preferred":[
        "\u53cc\u6ee9"
    ],
    "wof:name":"Shuangtan",
    "wof:placetype":"locality"
},
  "geometry": {"coordinates":[118.33714999999999,34.2526],"type":"Point"}
}