{
  "type": "Feature",
  "properties": {
    "gn:admin1_code":"11.0",
    "gn:asciiname":"Shumuling",
    "gn:country_code":"CN",
    "gn:dem":78,
    "gn:feature_class":"P",
    "gn:feature_code":"PPL",
    "gn:name":"Shumuling",
    "gn:population":0,
    "gn:timezone":"Asia/Shanghai",
    "iso:country":"CN",
    "name:zho_x_preferred":[
        "Shumuling"
    ],
    "name:zho_x_variant":[
        "\u68b3\u6728\u5cad"
    ],
    "wof:name":"Shumuling",
    "wof:placetype":"locality"
},
  "geometry": {"coordinates":[111.34474,29.09841],"type":"Point"}
}