{
  "type": "Feature",
  "properties": {
    "gn:admin1_code":"7.0",
    "gn:asciiname":"Gaoyangcun",
    "gn:country_code":"CN",
    "gn:dem":432,
    "gn:feature_class":"P",
    "gn:feature_code":"PPL",
    "gn:name":"Gaoyangcun",
    "gn:population":0,
    "gn:timezone":"Asia/Shanghai",
    "iso:country":"CN",
    "name:zho_x_preferred":[
        "\u9ad8\u6d0b\u6751"
    ],
    "wof:name":"Gaoyangcun",
    "wof:placetype":"locality"
},
  "geometry": {"coordinates":[116.90269000000001,26.55867000000001],"type":"Point"}
}