{
  "type": "Feature",
  "properties": {
    "gn:admin1_code":"18",
    "gn:asciiname":"Feiga",
    "gn:country_code":"CN",
    "gn:dem":1480,
    "gn:feature_class":"P",
    "gn:feature_code":"PPL",
    "gn:name":"Feiga",
    "gn:population":0,
    "gn:timezone":"Asia/Shanghai",
    "iso:country":"CN",
    "name:zho_x_preferred":[
        "\u8d39\u560e"
    ],
    "wof:name":"Feiga",
    "wof:placetype":"locality"
},
  "geometry": {"coordinates":[105.304,26.1464],"type":"Point"}
}