{
  "type": "Feature",
  "properties": {
    "gn:admin1_code":"26.0",
    "gn:asciiname":"Majia Shancun",
    "gn:country_code":"CN",
    "gn:dem":1035,
    "gn:feature_class":"P",
    "gn:feature_code":"PPL",
    "gn:name":"Majia Shancun",
    "gn:population":0,
    "gn:timezone":"Asia/Shanghai",
    "iso:country":"CN",
    "name:zho_x_preferred":[
        "\u9ebb\u5bb6\u5c71\u6751"
    ],
    "wof:name":"Majia Shancun",
    "wof:placetype":"locality"
},
  "geometry": {"coordinates":[110.02800000000001,37.8233],"type":"Point"}
}