{
  "type": "Feature",
  "properties": {
    "gn:admin1_code":"14.0",
    "gn:asciiname":"Yazonglong",
    "gn:country_code":"CN",
    "gn:dem":3693,
    "gn:feature_class":"P",
    "gn:feature_code":"PPL",
    "gn:name":"Yazonglong",
    "gn:population":0,
    "gn:timezone":"Asia/Urumqi",
    "iso:country":"CN",
    "name:zho_x_preferred":[
        "\u7259\u5b97\u9f99"
    ],
    "wof:name":"Yazonglong",
    "wof:placetype":"locality"
},
  "geometry": {"coordinates":[98.63285999999999,29.4834],"type":"Point"}
}