{
  "type": "Feature",
  "properties": {
    "gn:admin1_code":"16",
    "gn:asciiname":"Linglong",
    "gn:country_code":"CN",
    "gn:dem":581,
    "gn:feature_class":"P",
    "gn:feature_code":"PPL",
    "gn:name":"Linglong",
    "gn:population":0,
    "gn:timezone":"Asia/Shanghai",
    "iso:country":"CN",
    "name:zho_x_preferred":[
        "\u7075\u9f99"
    ],
    "wof:name":"Linglong",
    "wof:placetype":"locality"
},
  "geometry": {"coordinates":[110.70099999999999,25.3741],"type":"Point"}
}