{
  "type": "Feature",
  "properties": {
    "gn:admin1_code":"29.0",
    "gn:asciiname":"Kese",
    "gn:country_code":"CN",
    "gn:dem":2444,
    "gn:feature_class":"P",
    "gn:feature_code":"PPL",
    "gn:name":"Kese",
    "gn:population":0,
    "gn:timezone":"Asia/Shanghai",
    "iso:country":"CN",
    "name:zho_x_preferred":[
        "\u79d1\u8272"
    ],
    "wof:name":"Kese",
    "wof:placetype":"locality"
},
  "geometry": {"coordinates":[99.9341,26.9507],"type":"Point"}
}