{
  "type": "Feature",
  "properties": {
    "gn:admin1_code":"10",
    "gn:asciiname":"Liangdixia",
    "gn:country_code":"CN",
    "gn:dem":1511,
    "gn:feature_class":"P",
    "gn:feature_code":"PPL",
    "gn:name":"Liangdixia",
    "gn:population":0,
    "gn:timezone":"Asia/Shanghai",
    "iso:country":"CN",
    "name:zho_x_preferred":[
        "\u6881\u5e95\u4e0b"
    ],
    "wof:name":"Liangdixia",
    "wof:placetype":"locality"
},
  "geometry": {"coordinates":[116.0239,41.67147],"type":"Point"}
}