{
  "type": "Feature",
  "properties": {
    "gn:admin1_code":"15.0",
    "gn:asciiname":"Zouzheng",
    "gn:country_code":"CN",
    "gn:dem":3344,
    "gn:feature_class":"P",
    "gn:feature_code":"PPL",
    "gn:name":"Zouzheng",
    "gn:population":0,
    "gn:timezone":"Asia/Shanghai",
    "iso:country":"CN",
    "name:zho_x_preferred":[
        "\u594f\u653f"
    ],
    "wof:name":"Zouzheng",
    "wof:placetype":"locality"
},
  "geometry": {"coordinates":[102.193,34.7015],"type":"Point"}
}