{
  "type": "Feature",
  "properties": {
    "gn:admin1_code":"24",
    "gn:asciiname":"Dingyu",
    "gn:cc2":"CN",
    "gn:country_code":"CN",
    "gn:dem":646,
    "gn:feature_class":"P",
    "gn:feature_code":"PPL",
    "gn:name":"Dingyu",
    "gn:population":0,
    "gn:timezone":"Asia/Shanghai",
    "iso:country":"CN",
    "name:und_x_variant":[
        "Shih-tzu-y\u00fc",
        "Daobakou",
        "Tao-pa-k\u2019ou",
        "Ting-y\u00fc",
        "Ting-tzu-y\u00fc",
        "Dingyu"
    ],
    "name:zho_x_preferred":[
        "\u4e01\u5cea"
    ],
    "wof:name":"Dingyu",
    "wof:placetype":"locality"
},
  "geometry": {"coordinates":[114.01472,37.65667],"type":"Point"}
}