{
  "type": "Feature",
  "properties": {
    "gn:admin1_code":"14",
    "gn:asciiname":"Reka",
    "gn:country_code":"CN",
    "gn:dem":4732,
    "gn:feature_class":"P",
    "gn:feature_code":"PPL",
    "gn:name":"Reka",
    "gn:population":0,
    "gn:timezone":"Asia/Urumqi",
    "iso:country":"CN",
    "name:ceb_x_preferred":[
        "Reka"
    ],
    "name:ces_x_preferred":[
        "\u0158eka"
    ],
    "name:deu_x_preferred":[
        "Reka"
    ],
    "name:fra_x_preferred":[
        "Reka"
    ],
    "name:hrv_x_preferred":[
        "Reka"
    ],
    "name:hun_x_preferred":[
        "Reka"
    ],
    "name:nld_x_preferred":[
        "Reka"
    ],
    "name:por_x_preferred":[
        "Reka"
    ],
    "name:slv_x_preferred":[
        "Reka"
    ],
    "name:srp_x_preferred":[
        "\u0420\u0435\u043a\u0430"
    ],
    "name:swe_x_preferred":[
        "Reka"
    ],
    "name:zho_x_preferred":[
        "\u70ed\u5361"
    ],
    "wof:name":"Reka",
    "wof:placetype":"locality"
},
  "geometry": {"coordinates":[88.9111,29.6508],"type":"Point"}
}