{
  "type": "Feature",
  "properties": {
    "gn:admin1_code":"9.0",
    "gn:asciiname":"Yanggouling",
    "gn:country_code":"CN",
    "gn:dem":993,
    "gn:feature_class":"P",
    "gn:feature_code":"PPL",
    "gn:name":"Yanggouling",
    "gn:population":0,
    "gn:timezone":"Asia/Shanghai",
    "iso:country":"CN",
    "name:zho_x_preferred":[
        "\u6768\u6c9f\u5cad"
    ],
    "wof:name":"Yanggouling",
    "wof:placetype":"locality"
},
  "geometry": {"coordinates":[111.78440000000001,33.94795],"type":"Point"}
}