{
  "type": "Feature",
  "properties": {
    "gn:admin1_code":"26.0",
    "gn:asciiname":"Mashangwan",
    "gn:country_code":"CN",
    "gn:dem":932,
    "gn:feature_class":"P",
    "gn:feature_code":"PPL",
    "gn:name":"Mashangwan",
    "gn:population":0,
    "gn:timezone":"Asia/Shanghai",
    "iso:country":"CN",
    "name:und_x_variant":[
        "\u9a6c\u4e0a\u6e7e"
    ],
    "wof:name":"Mashangwan",
    "wof:placetype":"locality"
},
  "geometry": {"coordinates":[106.20799,33.07878],"type":"Point"}
}