{
  "type": "Feature",
  "properties": {
    "gn:admin1_code":"26.0",
    "gn:asciiname":"Weijiayanwo",
    "gn:country_code":"CN",
    "gn:dem":443,
    "gn:feature_class":"P",
    "gn:feature_code":"PPL",
    "gn:name":"Weijiayanwo",
    "gn:population":0,
    "gn:timezone":"Asia/Shanghai",
    "iso:country":"CN",
    "name:zho_x_preferred":[
        "\u9b4f\u5bb6\u5ca9\u7a9d"
    ],
    "wof:name":"Weijiayanwo",
    "wof:placetype":"locality"
},
  "geometry": {"coordinates":[108.97042999999999,32.58673],"type":"Point"}
}