{
  "type": "Feature",
  "properties": {
    "gn:admin1_code":"10",
    "gn:asciiname":"Zhangjiakounan",
    "gn:cc2":"CN",
    "gn:country_code":"CN",
    "gn:dem":671,
    "gn:feature_class":"P",
    "gn:feature_code":"PPL",
    "gn:name":"Zhangjiakounan",
    "gn:population":0,
    "gn:timezone":"Asia/Shanghai",
    "iso:country":"CN",
    "name:und_x_variant":[
        "Chang-chia-k\u2019ou",
        "Zhangjiakounan"
    ],
    "wof:name":"Zhangjiakounan",
    "wof:placetype":"locality"
},
  "geometry": {"coordinates":[114.78417,40.71],"type":"Point"}
}