{
  "type": "Feature",
  "properties": {
    "gn:admin1_code":"1.0",
    "gn:asciiname":"Tongzhencun",
    "gn:country_code":"CN",
    "gn:dem":698,
    "gn:feature_class":"P",
    "gn:feature_code":"PPL",
    "gn:name":"Tongzhencun",
    "gn:population":0,
    "gn:timezone":"Asia/Shanghai",
    "iso:country":"CN",
    "name:zho_x_preferred":[
        "\u901a\u771f\u6751"
    ],
    "wof:name":"Tongzhencun",
    "wof:placetype":"locality"
},
  "geometry": {"coordinates":[116.27549999999999,30.91798],"type":"Point"}
}