{
  "type": "Feature",
  "properties": {
    "gn:admin1_code":"22.0",
    "gn:asciiname":"Shuitangzicun",
    "gn:country_code":"CN",
    "gn:dem":639,
    "gn:feature_class":"P",
    "gn:feature_code":"PPL",
    "gn:name":"Shuitangzicun",
    "gn:population":0,
    "gn:timezone":"Asia/Shanghai",
    "iso:country":"CN",
    "name:zho_x_preferred":[
        "\u6c34\u5858\u5b50\u6751"
    ],
    "wof:name":"Shuitangzicun",
    "wof:placetype":"locality"
},
  "geometry": {"coordinates":[116.3852,40.43282],"type":"Point"}
}