{
  "type": "Feature",
  "properties": {
    "gn:admin1_code":"9.0",
    "gn:asciiname":"Dongfanzhuang",
    "gn:country_code":"CN",
    "gn:dem":66,
    "gn:feature_class":"P",
    "gn:feature_code":"PPL",
    "gn:name":"Dongfanzhuang",
    "gn:population":0,
    "gn:timezone":"Asia/Shanghai",
    "iso:country":"CN",
    "name:zho_x_preferred":[
        "\u4e1c\u8303\u5e84"
    ],
    "wof:name":"Dongfanzhuang",
    "wof:placetype":"locality"
},
  "geometry": {"coordinates":[114.35531,34.27772],"type":"Point"}
}