{
  "type": "Feature",
  "properties": {
    "gn:admin1_code":"19",
    "gn:asciiname":"Beiyanggou",
    "gn:country_code":"CN",
    "gn:dem":329,
    "gn:feature_class":"P",
    "gn:feature_code":"PPL",
    "gn:name":"Beiyanggou",
    "gn:population":0,
    "gn:timezone":"Asia/Shanghai",
    "iso:country":"CN",
    "name:und_x_variant":[
        "\u5317\u9633\u6c9f",
        "Pei-yang-kou"
    ],
    "wof:name":"Beiyanggou",
    "wof:placetype":"locality"
},
  "geometry": {"coordinates":[125.4675,40.85056],"type":"Point"}
}