{
  "type": "Feature",
  "properties": {
    "gn:admin1_code":"30.0",
    "gn:asciiname":"Gongbei",
    "gn:country_code":"CN",
    "gn:dem":125,
    "gn:feature_class":"P",
    "gn:feature_code":"PPL",
    "gn:name":"Gongbei",
    "gn:population":0,
    "gn:timezone":"Asia/Shanghai",
    "iso:country":"CN",
    "name:deu_x_preferred":[
        "Gongbei"
    ],
    "name:zho_x_preferred":[
        "\u5f13\u80cc"
    ],
    "wof:name":"Gongbei",
    "wof:placetype":"locality"
},
  "geometry": {"coordinates":[115.84193,23.99621],"type":"Point"}
}