{
  "type": "Feature",
  "properties": {
    "gn:admin1_code":"1.0",
    "gn:asciiname":"Gaodiancun",
    "gn:country_code":"CN",
    "gn:dem":33,
    "gn:feature_class":"P",
    "gn:feature_code":"PPL",
    "gn:name":"Gaodiancun",
    "gn:population":0,
    "gn:timezone":"Asia/Shanghai",
    "iso:country":"CN",
    "name:zho_x_preferred":[
        "\u9ad8\u5e97\u6751"
    ],
    "wof:name":"Gaodiancun",
    "wof:placetype":"locality"
},
  "geometry": {"coordinates":[115.89851000000002,32.64033],"type":"Point"}
}