{
  "type": "Feature",
  "properties": {
    "gn:admin1_code":"7.0",
    "gn:asciiname":"Qingmei",
    "gn:country_code":"CN",
    "gn:dem":67,
    "gn:feature_class":"P",
    "gn:feature_code":"PPL",
    "gn:name":"Qingmei",
    "gn:population":0,
    "gn:timezone":"Asia/Shanghai",
    "iso:country":"CN",
    "name:zho_x_preferred":[
        "\u9752\u7f8e"
    ],
    "wof:name":"Qingmei",
    "wof:placetype":"locality"
},
  "geometry": {"coordinates":[117.30771,24.06687],"type":"Point"}
}