{
  "type": "Feature",
  "properties": {
    "gn:admin1_code":"11.0",
    "gn:asciiname":"Shaojia",
    "gn:country_code":"CN",
    "gn:dem":323,
    "gn:feature_class":"P",
    "gn:feature_code":"PPL",
    "gn:name":"Shaojia",
    "gn:population":0,
    "gn:timezone":"Asia/Shanghai",
    "iso:country":"CN",
    "name:zho_x_preferred":[
        "\u52fa\u5bb6"
    ],
    "wof:name":"Shaojia",
    "wof:placetype":"locality"
},
  "geometry": {"coordinates":[109.78331,29.04339],"type":"Point"}
}