{
  "type": "Feature",
  "properties": {
    "gn:admin1_code":"13.0",
    "gn:asciiname":"Qindel",
    "gn:cc2":"CN",
    "gn:country_code":"CN",
    "gn:dem":557,
    "gn:feature_class":"P",
    "gn:feature_code":"PPL",
    "gn:name":"Qindel",
    "gn:population":0,
    "gn:timezone":"Asia/Shanghai",
    "iso:country":"CN",
    "name:uig_x_preferred":[
        "Chind\u00e9l"
    ],
    "name:uig_x_variant":[
        "\u0686\u0649\u0646\u062f\u06d0\u0644",
        "\u0427\u0438\u043d\u0434\u0435\u043b"
    ],
    "name:und_x_variant":[
        "Qindel Xiang",
        "Qindel"
    ],
    "wof:name":"Qindel",
    "wof:placetype":"locality"
},
  "geometry": {"coordinates":[82.00055999999999,44.92],"type":"Point"}
}