{
  "type": "Feature",
  "properties": {
    "gn:admin1_code":"25",
    "gn:asciiname":"Nanye",
    "gn:country_code":"CN",
    "gn:dem":40,
    "gn:feature_class":"P",
    "gn:feature_code":"PPL",
    "gn:name":"Nanye",
    "gn:population":0,
    "gn:timezone":"Asia/Shanghai",
    "iso:country":"CN",
    "name:zho_x_preferred":[
        "\u5357\u91ce"
    ],
    "wof:name":"Nanye",
    "wof:placetype":"locality"
},
  "geometry": {"coordinates":[115.62327999999999,36.60916],"type":"Point"}
}