{
  "type": "Feature",
  "properties": {
    "gn:admin1_code":"20.0",
    "gn:asciiname":"Yongsheng",
    "gn:country_code":"CN",
    "gn:dem":256,
    "gn:feature_class":"P",
    "gn:feature_code":"PPL",
    "gn:name":"Yongsheng",
    "gn:population":0,
    "gn:timezone":"Asia/Shanghai",
    "iso:country":"CN",
    "name:zho_x_preferred":[
        "\u6c38\u80dc"
    ],
    "wof:name":"Yongsheng",
    "wof:placetype":"locality"
},
  "geometry": {"coordinates":[123.67198999999999,48.36909],"type":"Point"}
}