{
  "type": "Feature",
  "properties": {
    "gn:admin1_code":"10",
    "gn:asciiname":"Dazhaimen",
    "gn:country_code":"CN",
    "gn:dem":342,
    "gn:feature_class":"P",
    "gn:feature_code":"PPL",
    "gn:name":"Dazhaimen",
    "gn:population":0,
    "gn:timezone":"Asia/Shanghai",
    "iso:country":"CN",
    "name:zho_x_preferred":[
        "\u5927\u5be8\u95e8"
    ],
    "wof:name":"Dazhaimen",
    "wof:placetype":"locality"
},
  "geometry": {"coordinates":[114.128,37.0256],"type":"Point"}
}