{
  "type": "Feature",
  "properties": {
    "gn:admin1_code":"7.0",
    "gn:asciiname":"Xiachi'ao",
    "gn:country_code":"CN",
    "gn:dem":134,
    "gn:feature_class":"P",
    "gn:feature_code":"PPL",
    "gn:name":"Xiachi\u2019ao",
    "gn:population":0,
    "gn:timezone":"Asia/Shanghai",
    "iso:country":"CN",
    "name:und_x_variant":[
        "Xiachi\u2019ao"
    ],
    "name:zho_x_preferred":[
        "\u4e0b\u6c60\u5c99"
    ],
    "wof:name":"Xiachi'ao",
    "wof:placetype":"locality"
},
  "geometry": {"coordinates":[120.25261,27.0026],"type":"Point"}
}