{
  "type": "Feature",
  "properties": {
    "gn:admin1_code":"9.0",
    "gn:asciiname":"Shenweizi",
    "gn:country_code":"CN",
    "gn:dem":37,
    "gn:feature_class":"P",
    "gn:feature_code":"PPL",
    "gn:name":"Shenweizi",
    "gn:population":0,
    "gn:timezone":"Asia/Shanghai",
    "iso:country":"CN",
    "name:zho_x_preferred":[
        "\u6c88\u56f4\u5b50"
    ],
    "wof:name":"Shenweizi",
    "wof:placetype":"locality"
},
  "geometry": {"coordinates":[115.71437,32.34034],"type":"Point"}
}