{
  "type": "Feature",
  "properties": {
    "gn:admin1_code":"9.0",
    "gn:asciiname":"Xiangchang",
    "gn:country_code":"CN",
    "gn:dem":228,
    "gn:elevation":"507.0",
    "gn:feature_class":"P",
    "gn:feature_code":"PPL",
    "gn:name":"Xiangchang",
    "gn:population":0,
    "gn:timezone":"Asia/Shanghai",
    "iso:country":"CN",
    "name:und_x_variant":[
        "\u76f8\u5382",
        "Xiangchang"
    ],
    "wof:name":"Xiangchang",
    "wof:placetype":"locality"
},
  "geometry": {"coordinates":[112.87485,33.92265],"type":"Point"}
}