{
  "type": "Feature",
  "properties": {
    "gn:admin1_code":"10",
    "gn:asciiname":"Nanxiaolu",
    "gn:country_code":"CN",
    "gn:dem":35,
    "gn:feature_class":"P",
    "gn:feature_code":"PPL",
    "gn:name":"Nanxiaolu",
    "gn:population":0,
    "gn:timezone":"Asia/Shanghai",
    "iso:country":"CN",
    "name:zho_x_preferred":[
        "\u5357\u5b5d\u8def"
    ],
    "wof:name":"Nanxiaolu",
    "wof:placetype":"locality"
},
  "geometry": {"coordinates":[115.15242000000001,36.96405],"type":"Point"}
}