{
  "type": "Feature",
  "properties": {
    "gn:admin1_code":"1.0",
    "gn:asciiname":"Huliancun",
    "gn:country_code":"CN",
    "gn:dem":117,
    "gn:feature_class":"P",
    "gn:feature_code":"PPL",
    "gn:name":"Huliancun",
    "gn:population":0,
    "gn:timezone":"Asia/Shanghai",
    "iso:country":"CN",
    "name:zho_x_preferred":[
        "\u4e92\u8054\u6751"
    ],
    "wof:name":"Huliancun",
    "wof:placetype":"locality"
},
  "geometry": {"coordinates":[117.5325,30.11895],"type":"Point"}
}