{
  "type": "Feature",
  "properties": {
    "gn:admin1_code":"19.0",
    "gn:asciiname":"Xiaoyingzi",
    "gn:country_code":"CN",
    "gn:dem":248,
    "gn:feature_class":"P",
    "gn:feature_code":"PPL",
    "gn:name":"Xiaoyingzi",
    "gn:population":0,
    "gn:timezone":"Asia/Shanghai",
    "iso:country":"CN",
    "name:zho_x_preferred":[
        "\u5c0f\u8425\u5b50"
    ],
    "wof:name":"Xiaoyingzi",
    "wof:placetype":"locality"
},
  "geometry": {"coordinates":[120.38151999999999,41.70039000000001],"type":"Point"}
}