{
  "type": "Feature",
  "properties": {
    "gn:admin1_code":"7.0",
    "gn:asciiname":"Dayangping",
    "gn:country_code":"CN",
    "gn:dem":303,
    "gn:feature_class":"P",
    "gn:feature_code":"PPL",
    "gn:name":"Dayangping",
    "gn:population":0,
    "gn:timezone":"Asia/Shanghai",
    "iso:country":"CN",
    "name:zho_x_preferred":[
        "\u5927\u6d0b\u576a"
    ],
    "wof:name":"Dayangping",
    "wof:placetype":"locality"
},
  "geometry": {"coordinates":[117.25888999999999,27.62111],"type":"Point"}
}