{
  "type": "Feature",
  "properties": {
    "gn:admin1_code":"32.0",
    "gn:asciiname":"Baruosi",
    "gn:country_code":"CN",
    "gn:dem":4778,
    "gn:feature_class":"P",
    "gn:feature_code":"PPL",
    "gn:name":"Baruosi",
    "gn:population":0,
    "gn:timezone":"Asia/Shanghai",
    "iso:country":"CN",
    "name:zho_x_preferred":[
        "\u5df4\u82e5\u5bfa"
    ],
    "wof:name":"Baruosi",
    "wof:placetype":"locality"
},
  "geometry": {"coordinates":[97.67440999999999,33.51272],"type":"Point"}
}