{
  "type": "Feature",
  "properties": {
    "gn:admin1_code":"18",
    "gn:asciiname":"Xinfaruo",
    "gn:country_code":"CN",
    "gn:dem":901,
    "gn:feature_class":"P",
    "gn:feature_code":"PPL",
    "gn:name":"Xinfaruo",
    "gn:population":0,
    "gn:timezone":"Asia/Shanghai",
    "iso:country":"CN",
    "name:zho_x_preferred":[
        "\u65b0\u53d1\u82e5"
    ],
    "wof:name":"Xinfaruo",
    "wof:placetype":"locality"
},
  "geometry": {"coordinates":[104.68600000000001,24.6948],"type":"Point"}
}