{
  "type": "Feature",
  "properties": {
    "gn:admin1_code":"16.0",
    "gn:asciiname":"Denglai",
    "gn:country_code":"CN",
    "gn:dem":334,
    "gn:feature_class":"P",
    "gn:feature_code":"PPL",
    "gn:name":"Denglai",
    "gn:population":0,
    "gn:timezone":"Asia/Shanghai",
    "iso:country":"CN",
    "name:zho_x_preferred":[
        "\u9093\u6765"
    ],
    "wof:name":"Denglai",
    "wof:placetype":"locality"
},
  "geometry": {"coordinates":[106.807,22.8597],"type":"Point"}
}