{
  "type": "Feature",
  "properties": {
    "gn:admin1_code":"18",
    "gn:asciiname":"Danglao",
    "gn:country_code":"CN",
    "gn:dem":882,
    "gn:feature_class":"P",
    "gn:feature_code":"PPL",
    "gn:name":"Danglao",
    "gn:population":0,
    "gn:timezone":"Asia/Shanghai",
    "iso:country":"CN",
    "name:zho_x_preferred":[
        "\u5f53\u52b3"
    ],
    "wof:name":"Danglao",
    "wof:placetype":"locality"
},
  "geometry": {"coordinates":[106.518,25.7073],"type":"Point"}
}