{
  "type": "Feature",
  "properties": {
    "gn:admin1_code":"10",
    "gn:asciiname":"Nanxingguo",
    "gn:cc2":"CN",
    "gn:country_code":"CN",
    "gn:dem":74,
    "gn:feature_class":"P",
    "gn:feature_code":"PPL",
    "gn:name":"Nanxingguo",
    "gn:population":0,
    "gn:timezone":"Asia/Shanghai",
    "iso:country":"CN",
    "name:und_x_variant":[
        "Nan-hsing-kuo-ts\u2019un",
        "Nan-hsing-kuo",
        "Nanxingguo"
    ],
    "wof:name":"Nanxingguo",
    "wof:placetype":"locality"
},
  "geometry": {"coordinates":[114.46889,37.61972],"type":"Point"}
}