{
  "type": "Feature",
  "properties": {
    "gn:admin1_code":"3",
    "gn:asciiname":"Dengyuan",
    "gn:country_code":"CN",
    "gn:dem":207,
    "gn:feature_class":"P",
    "gn:feature_code":"PPL",
    "gn:name":"Dengyuan",
    "gn:population":0,
    "gn:timezone":"Asia/Shanghai",
    "iso:country":"CN",
    "name:und_x_variant":[
        "\u6f84\u6e90"
    ],
    "wof:name":"Dengyuan",
    "wof:placetype":"locality"
},
  "geometry": {"coordinates":[116.24768,27.46321],"type":"Point"}
}