{
  "type": "Feature",
  "properties": {
    "gn:admin1_code":"30",
    "gn:asciiname":"Xihe",
    "gn:country_code":"CN",
    "gn:dem":92,
    "gn:feature_class":"P",
    "gn:feature_code":"PPLA4",
    "gn:name":"Xihe",
    "gn:population":0,
    "gn:timezone":"Asia/Shanghai",
    "iso:country":"CN",
    "name:ceb_x_preferred":[
        "Xihe"
    ],
    "name:deu_x_preferred":[
        "Xihe"
    ],
    "name:fra_x_preferred":[
        "Xihe"
    ],
    "name:nor_x_preferred":[
        "Xihe"
    ],
    "name:swe_x_preferred":[
        "Xihe"
    ],
    "name:und_x_variant":[
        "Xihe Zhen",
        "\u897f\u6cb3\u9547"
    ],
    "name:zho_x_preferred":[
        "\u897f\u6cb3"
    ],
    "wof:name":"Xihe",
    "wof:placetype":"locality"
},
  "geometry": {"coordinates":[116.74804,24.48543],"type":"Point"}
}