{
  "type": "Feature",
  "properties": {
    "gn:admin1_code":"13.0",
    "gn:asciiname":"Puka",
    "gn:country_code":"CN",
    "gn:dem":1648,
    "gn:feature_class":"P",
    "gn:feature_code":"PPL",
    "gn:name":"Puka",
    "gn:population":0,
    "gn:timezone":"Asia/Shanghai",
    "iso:country":"CN",
    "name:ceb_x_preferred":[
        "Puka"
    ],
    "name:deu_x_preferred":[
        "Puka"
    ],
    "name:est_x_preferred":[
        "Puka"
    ],
    "name:heb_x_preferred":[
        "\u05e4\u05d5\u05e7\u05d4"
    ],
    "name:hun_x_preferred":[
        "Puka"
    ],
    "name:hye_x_preferred":[
        "\u054a\u0578\u0582\u056f\u0561"
    ],
    "name:mri_x_preferred":[
        "Puka"
    ],
    "name:nld_x_preferred":[
        "Puka"
    ],
    "name:por_x_preferred":[
        "Puka"
    ],
    "name:ron_x_preferred":[
        "Puka"
    ],
    "name:swe_x_preferred":[
        "Puka"
    ],
    "name:ukr_x_preferred":[
        "\u041f\u0443\u043a\u0430"
    ],
    "name:vol_x_preferred":[
        "Puka"
    ],
    "name:zho_x_preferred":[
        "\u666e\u5580"
    ],
    "wof:name":"Puka",
    "wof:placetype":"locality"
},
  "geometry": {"coordinates":[79.55360999999998,36.94324],"type":"Point"}
}