{
  "type": "Feature",
  "properties": {
    "gn:admin1_code":"6.0",
    "gn:asciiname":"Duoshaoka",
    "gn:country_code":"CN",
    "gn:dem":3635,
    "gn:feature_class":"P",
    "gn:feature_code":"PPL",
    "gn:name":"Duoshaoka",
    "gn:population":0,
    "gn:timezone":"Asia/Urumqi",
    "iso:country":"CN",
    "name:zho_x_preferred":[
        "\u591a\u5c11\u5361"
    ],
    "wof:name":"Duoshaoka",
    "wof:placetype":"locality"
},
  "geometry": {"coordinates":[96.86921,32.23265],"type":"Point"}
}