{
  "type": "Feature",
  "properties": {
    "gn:admin1_code":"10",
    "gn:asciiname":"Lujiawa",
    "gn:country_code":"CN",
    "gn:dem":19,
    "gn:feature_class":"P",
    "gn:feature_code":"PPL",
    "gn:name":"Lujiawa",
    "gn:population":0,
    "gn:timezone":"Asia/Shanghai",
    "iso:country":"CN",
    "name:zho_x_preferred":[
        "\u8def\u5bb6\u6d3c"
    ],
    "wof:name":"Lujiawa",
    "wof:placetype":"locality"
},
  "geometry": {"coordinates":[116.41476000000002,37.8474],"type":"Point"}
}