{
  "type": "Feature",
  "properties": {
    "gn:admin1_code":"4.0",
    "gn:asciiname":"Kuangkoucun",
    "gn:country_code":"CN",
    "gn:dem":3,
    "gn:feature_class":"P",
    "gn:feature_code":"PPL",
    "gn:name":"Kuangkoucun",
    "gn:population":0,
    "gn:timezone":"Asia/Shanghai",
    "iso:country":"CN",
    "name:zho_x_preferred":[
        "\u5321\u53e3\u6751"
    ],
    "wof:name":"Kuangkoucun",
    "wof:placetype":"locality"
},
  "geometry": {"coordinates":[119.17968999999999,34.90808],"type":"Point"}
}