{
  "type": "Feature",
  "properties": {
    "gn:admin1_code":"30.0",
    "gn:asciiname":"Daoliushui",
    "gn:country_code":"CN",
    "gn:dem":306,
    "gn:feature_class":"P",
    "gn:feature_code":"PPL",
    "gn:name":"Daoliushui",
    "gn:population":0,
    "gn:timezone":"Asia/Shanghai",
    "iso:country":"CN",
    "name:zho_x_preferred":[
        "Daoliushui"
    ],
    "name:zho_x_variant":[
        "\u5012\u6d41\u6c34"
    ],
    "wof:name":"Daoliushui",
    "wof:placetype":"locality"
},
  "geometry": {"coordinates":[113.89388999999998,25.26583],"type":"Point"}
}