{
  "type": "Feature",
  "properties": {
    "gn:admin1_code":"14.0",
    "gn:asciiname":"Xiarenma",
    "gn:country_code":"CN",
    "gn:dem":4671,
    "gn:feature_class":"P",
    "gn:feature_code":"PPL",
    "gn:name":"Xiarenma",
    "gn:population":0,
    "gn:timezone":"Asia/Urumqi",
    "iso:country":"CN",
    "name:zho_x_preferred":[
        "\u590f\u4eba\u739b"
    ],
    "wof:name":"Xiarenma",
    "wof:placetype":"locality"
},
  "geometry": {"coordinates":[96.73442,30.8755],"type":"Point"}
}