{
  "type": "Feature",
  "properties": {
    "gn:admin1_code":"26.0",
    "gn:asciiname":"Huangyingcun",
    "gn:country_code":"CN",
    "gn:dem":514,
    "gn:feature_class":"P",
    "gn:feature_code":"PPL",
    "gn:name":"Huangyingcun",
    "gn:population":0,
    "gn:timezone":"Asia/Shanghai",
    "iso:country":"CN",
    "name:und_x_variant":[
        "\u9ec4\u8425\u6751"
    ],
    "wof:name":"Huangyingcun",
    "wof:placetype":"locality"
},
  "geometry": {"coordinates":[106.96982,33.10482],"type":"Point"}
}