{
  "type": "Feature",
  "properties": {
    "gn:admin1_code":"29.0",
    "gn:asciiname":"Wupai",
    "gn:country_code":"CN",
    "gn:dem":1651,
    "gn:feature_class":"P",
    "gn:feature_code":"PPL",
    "gn:name":"Wupai",
    "gn:population":0,
    "gn:timezone":"Asia/Shanghai",
    "iso:country":"CN",
    "name:zho_x_preferred":[
        "\u4e94\u6392"
    ],
    "wof:name":"Wupai",
    "wof:placetype":"locality"
},
  "geometry": {"coordinates":[97.8212,24.9413],"type":"Point"}
}