{
  "type": "Feature",
  "properties": {
    "gn:admin1_code":"33.0",
    "gn:asciiname":"Linchang",
    "gn:country_code":"CN",
    "gn:dem":682,
    "gn:feature_class":"P",
    "gn:feature_code":"PPL",
    "gn:name":"Linchang",
    "gn:population":0,
    "gn:timezone":"Asia/Shanghai",
    "iso:country":"CN",
    "name:zho_x_preferred":[
        "\u6797\u573a"
    ],
    "wof:name":"Linchang",
    "wof:placetype":"locality"
},
  "geometry": {"coordinates":[108.57088,30.72359],"type":"Point"}
}