{
  "type": "Feature",
  "properties": {
    "gn:admin1_code":"32.0",
    "gn:asciiname":"Wenxing",
    "gn:country_code":"CN",
    "gn:dem":744,
    "gn:feature_class":"P",
    "gn:feature_code":"PPL",
    "gn:name":"Wenxing",
    "gn:population":0,
    "gn:timezone":"Asia/Shanghai",
    "iso:country":"CN",
    "name:zho_x_preferred":[
        "\u6587\u661f"
    ],
    "wof:name":"Wenxing",
    "wof:placetype":"locality"
},
  "geometry": {"coordinates":[107.092,30.8052],"type":"Point"}
}