{
  "type": "Feature",
  "properties": {
    "gn:admin1_code":"9.0",
    "gn:asciiname":"Situdi",
    "gn:country_code":"CN",
    "gn:dem":317,
    "gn:feature_class":"P",
    "gn:feature_code":"PPL",
    "gn:name":"Situdi",
    "gn:population":0,
    "gn:timezone":"Asia/Shanghai",
    "iso:country":"CN",
    "name:zho_x_preferred":[
        "\u56db\u571f\u5730"
    ],
    "wof:name":"Situdi",
    "wof:placetype":"locality"
},
  "geometry": {"coordinates":[111.85756000000001,34.54206],"type":"Point"}
}