{
  "type": "Feature",
  "properties": {
    "gn:admin1_code":"12.0",
    "gn:asciiname":"Xiongjia Huawu",
    "gn:country_code":"CN",
    "gn:dem":739,
    "gn:feature_class":"P",
    "gn:feature_code":"PPL",
    "gn:name":"Xiongjia Huawu",
    "gn:population":0,
    "gn:timezone":"Asia/Shanghai",
    "iso:country":"CN",
    "name:zho_x_preferred":[
        "\u718a\u5bb6\u82b1\u5c4b"
    ],
    "wof:name":"Xiongjia Huawu",
    "wof:placetype":"locality"
},
  "geometry": {"coordinates":[109.77941,32.54434000000001],"type":"Point"}
}