{
  "type": "Feature",
  "properties": {
    "gn:admin1_code":"32.0",
    "gn:asciiname":"Jinzishan",
    "gn:country_code":"CN",
    "gn:dem":366,
    "gn:feature_class":"P",
    "gn:feature_code":"PPL",
    "gn:name":"Jinzishan",
    "gn:population":0,
    "gn:timezone":"Asia/Shanghai",
    "iso:country":"CN",
    "name:zho_x_preferred":[
        "\u91d1\u5b50\u5c71"
    ],
    "wof:name":"Jinzishan",
    "wof:placetype":"locality"
},
  "geometry": {"coordinates":[104.134,29.0512],"type":"Point"}
}