{
  "type": "Feature",
  "properties": {
    "gn:admin1_code":"32.0",
    "gn:asciiname":"Zhagu",
    "gn:country_code":"CN",
    "gn:dem":3283,
    "gn:feature_class":"P",
    "gn:feature_code":"PPL",
    "gn:name":"Zhagu",
    "gn:population":0,
    "gn:timezone":"Asia/Shanghai",
    "iso:country":"CN",
    "name:zho_x_preferred":[
        "\u624e\u53e4"
    ],
    "wof:name":"Zhagu",
    "wof:placetype":"locality"
},
  "geometry": {"coordinates":[99.6648,28.9402],"type":"Point"}
}