{
  "type": "Feature",
  "properties": {
    "gn:admin1_code":"26",
    "gn:asciiname":"Pingxin",
    "gn:country_code":"CN",
    "gn:dem":364,
    "gn:feature_class":"P",
    "gn:feature_code":"PPL",
    "gn:name":"Pingxin",
    "gn:population":0,
    "gn:timezone":"Asia/Shanghai",
    "iso:country":"CN",
    "name:und_x_variant":[
        "P\u2019ing-hsin-chen",
        "Pingxin"
    ],
    "name:zho_x_preferred":[
        "\u51ed\u4fe1"
    ],
    "wof:name":"Pingxin",
    "wof:placetype":"locality"
},
  "geometry": {"coordinates":[109.65434,34.7617],"type":"Point"}
}