{
  "type": "Feature",
  "properties": {
    "gn:admin1_code":"8.0",
    "gn:asciiname":"Songdiancun",
    "gn:country_code":"CN",
    "gn:dem":63,
    "gn:feature_class":"P",
    "gn:feature_code":"PPL",
    "gn:name":"Songdiancun",
    "gn:population":0,
    "gn:timezone":"Asia/Shanghai",
    "iso:country":"CN",
    "name:zho_x_preferred":[
        "\u5b8b\u5e97\u6751"
    ],
    "wof:name":"Songdiancun",
    "wof:placetype":"locality"
},
  "geometry": {"coordinates":[131.78484,47.17619000000001],"type":"Point"}
}