{
  "type": "Feature",
  "properties": {
    "gn:admin1_code":"14.0",
    "gn:asciiname":"Chajia",
    "gn:country_code":"CN",
    "gn:dem":4440,
    "gn:feature_class":"P",
    "gn:feature_code":"PPL",
    "gn:name":"Chajia",
    "gn:population":0,
    "gn:timezone":"Asia/Urumqi",
    "iso:country":"CN",
    "name:zho_x_preferred":[
        "\u8336\u7532"
    ],
    "wof:name":"Chajia",
    "wof:placetype":"locality"
},
  "geometry": {"coordinates":[94.82698000000001,31.46606],"type":"Point"}
}