{
  "type": "Feature",
  "properties": {
    "gn:admin1_code":"5.0",
    "gn:asciiname":"Xisi Hetang",
    "gn:country_code":"CN",
    "gn:dem":137,
    "gn:feature_class":"P",
    "gn:feature_code":"PPL",
    "gn:name":"Xisi Hetang",
    "gn:population":0,
    "gn:timezone":"Asia/Shanghai",
    "iso:country":"CN",
    "name:zho_x_preferred":[
        "\u897f\u56db\u5408\u5802"
    ],
    "wof:name":"Xisi Hetang",
    "wof:placetype":"locality"
},
  "geometry": {"coordinates":[123.50149,45.46229],"type":"Point"}
}