{
  "type": "Feature",
  "properties": {
    "gn:admin1_code":"24.0",
    "gn:asciiname":"Heishigoucun",
    "gn:country_code":"CN",
    "gn:dem":1450,
    "gn:feature_class":"P",
    "gn:feature_code":"PPL",
    "gn:name":"Heishigoucun",
    "gn:population":0,
    "gn:timezone":"Asia/Shanghai",
    "iso:country":"CN",
    "name:zho_x_preferred":[
        "\u9ed1\u77f3\u6c9f\u6751"
    ],
    "wof:name":"Heishigoucun",
    "wof:placetype":"locality"
},
  "geometry": {"coordinates":[114.44369,40.27087],"type":"Point"}
}