{
  "type": "Feature",
  "properties": {
    "gn:admin1_code":"2.0",
    "gn:asciiname":"Jiandi",
    "gn:country_code":"CN",
    "gn:dem":710,
    "gn:feature_class":"P",
    "gn:feature_code":"PPL",
    "gn:name":"Jiandi",
    "gn:population":0,
    "gn:timezone":"Asia/Shanghai",
    "iso:country":"CN",
    "name:zho_x_preferred":[
        "\u5c16\u5730"
    ],
    "wof:name":"Jiandi",
    "wof:placetype":"locality"
},
  "geometry": {"coordinates":[119.05726,28.05734],"type":"Point"}
}