{
  "type": "Feature",
  "properties": {
    "gn:admin1_code":"25",
    "gn:asciiname":"Quanyuan",
    "gn:country_code":"CN",
    "gn:dem":65,
    "gn:feature_class":"P",
    "gn:feature_code":"PPL",
    "gn:name":"Quanyuan",
    "gn:population":0,
    "gn:timezone":"Asia/Shanghai",
    "iso:country":"CN",
    "name:und_x_variant":[
        "\u94e8\u56ed"
    ],
    "wof:name":"Quanyuan",
    "wof:placetype":"locality"
},
  "geometry": {"coordinates":[119.19,35.4412],"type":"Point"}
}