{
  "type": "Feature",
  "properties": {
    "gn:admin1_code":"24.0",
    "gn:asciiname":"Xiaoyuanmao",
    "gn:country_code":"CN",
    "gn:dem":1237,
    "gn:feature_class":"P",
    "gn:feature_code":"PPL",
    "gn:name":"Xiaoyuanmao",
    "gn:population":0,
    "gn:timezone":"Asia/Shanghai",
    "iso:country":"CN",
    "name:zho_x_preferred":[
        "\u5c0f\u5143\u5cc1"
    ],
    "wof:name":"Xiaoyuanmao",
    "wof:placetype":"locality"
},
  "geometry": {"coordinates":[111.5018,39.50418],"type":"Point"}
}