{
  "type": "Feature",
  "properties": {
    "gn:admin1_code":"7.0",
    "gn:asciiname":"Huishicun",
    "gn:country_code":"CN",
    "gn:dem":501,
    "gn:feature_class":"P",
    "gn:feature_code":"PPL",
    "gn:name":"Huishicun",
    "gn:population":0,
    "gn:timezone":"Asia/Shanghai",
    "iso:country":"CN",
    "name:zho_x_preferred":[
        "\u4f1a\u77f3\u6751"
    ],
    "wof:name":"Huishicun",
    "wof:placetype":"locality"
},
  "geometry": {"coordinates":[117.58138999999998,26.74298],"type":"Point"}
}