{
  "type": "Feature",
  "properties": {
    "gn:admin1_code":"16.0",
    "gn:asciiname":"Bawang",
    "gn:country_code":"CN",
    "gn:dem":142,
    "gn:feature_class":"P",
    "gn:feature_code":"PPL",
    "gn:name":"Bawang",
    "gn:population":0,
    "gn:timezone":"Asia/Shanghai",
    "iso:country":"CN",
    "name:zho_x_preferred":[
        "\u5c9c\u65fa"
    ],
    "wof:name":"Bawang",
    "wof:placetype":"locality"
},
  "geometry": {"coordinates":[108.345,24.1371],"type":"Point"}
}