{
  "type": "Feature",
  "properties": {
    "gn:admin1_code":"32.0",
    "gn:asciiname":"Mofangba",
    "gn:country_code":"CN",
    "gn:dem":1617,
    "gn:feature_class":"P",
    "gn:feature_code":"PPL",
    "gn:name":"Mofangba",
    "gn:population":0,
    "gn:timezone":"Asia/Shanghai",
    "iso:country":"CN",
    "name:zho_x_preferred":[
        "\u78e8\u623f\u575d"
    ],
    "wof:name":"Mofangba",
    "wof:placetype":"locality"
},
  "geometry": {"coordinates":[104.90965,32.21143],"type":"Point"}
}