{
  "type": "Feature",
  "properties": {
    "gn:admin1_code":"32.0",
    "gn:asciiname":"Jinong",
    "gn:country_code":"CN",
    "gn:dem":3720,
    "gn:feature_class":"P",
    "gn:feature_code":"PPL",
    "gn:name":"Jinong",
    "gn:population":0,
    "gn:timezone":"Asia/Shanghai",
    "iso:country":"CN",
    "name:zho_x_preferred":[
        "\u5409\u5f04"
    ],
    "wof:name":"Jinong",
    "wof:placetype":"locality"
},
  "geometry": {"coordinates":[100.962,32.0289],"type":"Point"}
}