{
  "type": "Feature",
  "properties": {
    "gn:admin1_code":"19.0",
    "gn:asciiname":"Gaoyingqiang",
    "gn:country_code":"CN",
    "gn:dem":24,
    "gn:feature_class":"P",
    "gn:feature_code":"PPL",
    "gn:name":"Gaoyingqiang",
    "gn:population":0,
    "gn:timezone":"Asia/Shanghai",
    "iso:country":"CN",
    "name:und_x_variant":[
        "\u9ad8\u8425\u5899"
    ],
    "name:zho_x_preferred":[
        "\u9ad8\u8425\u5899"
    ],
    "wof:name":"Gaoyingqiang",
    "wof:placetype":"locality"
},
  "geometry": {"coordinates":[123.23677000000001,41.32524],"type":"Point"}
}