{
  "type": "Feature",
  "properties": {
    "gn:admin1_code":"20.0",
    "gn:asciiname":"Daqinghe",
    "gn:country_code":"CN",
    "gn:dem":1669,
    "gn:feature_class":"P",
    "gn:feature_code":"PPL",
    "gn:name":"Daqinghe",
    "gn:population":0,
    "gn:timezone":"Asia/Shanghai",
    "iso:country":"CN",
    "name:und_x_variant":[
        "\u5927\u6e05\u6cb3"
    ],
    "wof:name":"Daqinghe",
    "wof:placetype":"locality"
},
  "geometry": {"coordinates":[112.3488,41.66463],"type":"Point"}
}