{
  "type": "Feature",
  "properties": {
    "gn:admin1_code":"32.0",
    "gn:asciiname":"Ca'eryan",
    "gn:country_code":"CN",
    "gn:dem":1007,
    "gn:feature_class":"P",
    "gn:feature_code":"PPL",
    "gn:name":"Ca\u2019eryan",
    "gn:population":0,
    "gn:timezone":"Asia/Shanghai",
    "iso:country":"CN",
    "name:und_x_variant":[
        "Ca\u2019eryan",
        "\u64e6\u8033\u5ca9"
    ],
    "wof:name":"Ca'eryan",
    "wof:placetype":"locality"
},
  "geometry": {"coordinates":[106.86233,32.24351],"type":"Point"}
}