{
  "type": "Feature",
  "properties": {
    "gn:admin1_code":"9.0",
    "gn:asciiname":"Liaokou",
    "gn:country_code":"CN",
    "gn:dem":97,
    "gn:feature_class":"P",
    "gn:feature_code":"PPL",
    "gn:name":"Liaokou",
    "gn:population":0,
    "gn:timezone":"Asia/Shanghai",
    "iso:country":"CN",
    "name:zho_x_preferred":[
        "\u6f66\u53e3"
    ],
    "wof:name":"Liaokou",
    "wof:placetype":"locality"
},
  "geometry": {"coordinates":[112.41531000000001,32.60969],"type":"Point"}
}