{
  "type": "Feature",
  "properties": {
    "gn:admin1_code":"32.0",
    "gn:asciiname":"Azhibaxia",
    "gn:country_code":"CN",
    "gn:dem":2690,
    "gn:feature_class":"P",
    "gn:feature_code":"PPL",
    "gn:name":"Azhibaxia",
    "gn:population":0,
    "gn:timezone":"Asia/Shanghai",
    "iso:country":"CN",
    "name:zho_x_preferred":[
        "\u963f\u652f\u516b\u5477"
    ],
    "wof:name":"Azhibaxia",
    "wof:placetype":"locality"
},
  "geometry": {"coordinates":[102.904,28.3837],"type":"Point"}
}