{
  "type": "Feature",
  "properties": {
    "gn:admin1_code":"32.0",
    "gn:asciiname":"Lingguisi",
    "gn:country_code":"CN",
    "gn:dem":309,
    "gn:feature_class":"P",
    "gn:feature_code":"PPL",
    "gn:name":"Lingguisi",
    "gn:population":0,
    "gn:timezone":"Asia/Shanghai",
    "iso:country":"CN",
    "name:zho_x_preferred":[
        "\u7075\u5f52\u5bfa"
    ],
    "wof:name":"Lingguisi",
    "wof:placetype":"locality"
},
  "geometry": {"coordinates":[105.64357,30.40059],"type":"Point"}
}