{
  "type": "Feature",
  "properties": {
    "gn:admin1_code":"3.0",
    "gn:asciiname":"Qupeng",
    "gn:country_code":"CN",
    "gn:dem":193,
    "gn:feature_class":"P",
    "gn:feature_code":"PPL",
    "gn:name":"Qupeng",
    "gn:population":0,
    "gn:timezone":"Asia/Shanghai",
    "iso:country":"CN",
    "name:und_x_variant":[
        "\u66f2\u68da"
    ],
    "wof:name":"Qupeng",
    "wof:placetype":"locality"
},
  "geometry": {"coordinates":[114.47905,28.27898],"type":"Point"}
}