{
  "type": "Feature",
  "properties": {
    "gn:admin1_code":"15.0",
    "gn:asciiname":"Heishuwo",
    "gn:country_code":"CN",
    "gn:dem":1252,
    "gn:feature_class":"P",
    "gn:feature_code":"PPL",
    "gn:name":"Heishuwo",
    "gn:population":0,
    "gn:timezone":"Asia/Shanghai",
    "iso:country":"CN",
    "name:zho_x_preferred":[
        "\u9ed1\u6811\u7a9d"
    ],
    "wof:name":"Heishuwo",
    "wof:placetype":"locality"
},
  "geometry": {"coordinates":[98.85850000000001,40.0736],"type":"Point"}
}