{
  "type": "Feature",
  "properties": {
    "gn:admin1_code":"3.0",
    "gn:asciiname":"Dawang",
    "gn:country_code":"CN",
    "gn:dem":448,
    "gn:feature_class":"P",
    "gn:feature_code":"PPL",
    "gn:name":"Dawang",
    "gn:population":0,
    "gn:timezone":"Asia/Shanghai",
    "iso:country":"CN",
    "name:und_x_variant":[
        "\u5927\u65fa"
    ],
    "wof:name":"Dawang",
    "wof:placetype":"locality"
},
  "geometry": {"coordinates":[114.70453999999999,24.57859],"type":"Point"}
}