{
  "type": "Feature",
  "properties": {
    "gn:admin1_code":"33",
    "gn:asciiname":"Guandu",
    "gn:country_code":"CN",
    "gn:dem":257,
    "gn:feature_class":"P",
    "gn:feature_code":"PPLA4",
    "gn:name":"Guandu",
    "gn:population":0,
    "gn:timezone":"Asia/Shanghai",
    "iso:country":"CN",
    "name:und_x_variant":[
        "Kuan-tu",
        "Guandu",
        "Guandu Zhen"
    ],
    "name:zho_x_preferred":[
        "\u5b98\u6e21"
    ],
    "name:zho_x_variant":[
        "\u5b98\u6e21\u9547"
    ],
    "wof:name":"Guandu",
    "wof:placetype":"locality"
},
  "geometry": {"coordinates":[106.42897000000001,30.08101],"type":"Point"}
}