{
  "type": "Feature",
  "properties": {
    "gn:admin1_code":"14.0",
    "gn:asciiname":"Saina",
    "gn:country_code":"CN",
    "gn:dem":4838,
    "gn:feature_class":"P",
    "gn:feature_code":"PPL",
    "gn:name":"Saina",
    "gn:population":0,
    "gn:timezone":"Asia/Urumqi",
    "iso:country":"CN",
    "name:zho_x_preferred":[
        "\u8d5b\u90a3"
    ],
    "wof:name":"Saina",
    "wof:placetype":"locality"
},
  "geometry": {"coordinates":[90.1601,31.68701],"type":"Point"}
}