{
  "type": "Feature",
  "properties": {
    "gn:admin1_code":"8.0",
    "gn:asciiname":"Guotong Liangzi",
    "gn:country_code":"CN",
    "gn:dem":58,
    "gn:feature_class":"P",
    "gn:feature_code":"PPL",
    "gn:name":"Guotong Liangzi",
    "gn:population":0,
    "gn:timezone":"Asia/Shanghai",
    "iso:country":"CN",
    "name:zho_x_preferred":[
        "\u90ed\u901a\u4eae\u5b50"
    ],
    "wof:name":"Guotong Liangzi",
    "wof:placetype":"locality"
},
  "geometry": {"coordinates":[132.50808000000001,46.6576],"type":"Point"}
}