{
  "type": "Feature",
  "properties": {
    "gn:admin1_code":"20.0",
    "gn:asciiname":"Zhaluomei",
    "gn:country_code":"CN",
    "gn:dem":329,
    "gn:feature_class":"P",
    "gn:feature_code":"PPL",
    "gn:name":"Zhaluomei",
    "gn:population":0,
    "gn:timezone":"Asia/Shanghai",
    "iso:country":"CN",
    "name:zho_x_preferred":[
        "\u624e\u7f57\u6885"
    ],
    "wof:name":"Zhaluomei",
    "wof:placetype":"locality"
},
  "geometry": {"coordinates":[124.42786,49.20199],"type":"Point"}
}