{
  "type": "Feature",
  "properties": {
    "gn:admin1_code":"4.0",
    "gn:asciiname":"Fangwan",
    "gn:country_code":"CN",
    "gn:dem":2,
    "gn:feature_class":"P",
    "gn:feature_code":"PPL",
    "gn:name":"Fangwan",
    "gn:population":0,
    "gn:timezone":"Asia/Shanghai",
    "iso:country":"CN",
    "name:zho_x_preferred":[
        "Fangwan"
    ],
    "name:zho_x_variant":[
        "\u623f\u6e7e"
    ],
    "wof:name":"Fangwan",
    "wof:placetype":"locality"
},
  "geometry": {"coordinates":[119.41792,34.2869],"type":"Point"}
}