{
  "type": "Feature",
  "properties": {
    "gn:admin1_code":"01",
    "gn:asciiname":"Shengongfan",
    "gn:cc2":"CN",
    "gn:country_code":"CN",
    "gn:dem":769,
    "gn:feature_class":"P",
    "gn:feature_code":"PPL",
    "gn:name":"Shengongfan",
    "gn:population":0,
    "gn:timezone":"Asia/Shanghai",
    "iso:country":"CN",
    "name:und_x_variant":[
        "Shen-kung-fan",
        "Shengongfan"
    ],
    "wof:name":"Shengongfan",
    "wof:placetype":"locality"
},
  "geometry": {"coordinates":[115.46666999999999,31.35],"type":"Point"}
}