{
  "type": "Feature",
  "properties": {
    "gn:admin1_code":"30.0",
    "gn:asciiname":"Luomibeicun",
    "gn:country_code":"CN",
    "gn:dem":120,
    "gn:feature_class":"P",
    "gn:feature_code":"PPL",
    "gn:name":"Luomibeicun",
    "gn:population":0,
    "gn:timezone":"Asia/Shanghai",
    "iso:country":"CN",
    "name:und_x_variant":[
        "Luomibei",
        "Luomibeicun"
    ],
    "name:zho_x_preferred":[
        "\u7f57\u5bc6\u5317"
    ],
    "name:zho_x_variant":[
        "\u7f57\u5bc6\u5317\u6751"
    ],
    "wof:name":"Luomibeicun",
    "wof:placetype":"locality"
},
  "geometry": {"coordinates":[112.36956000000001,23.93762000000001],"type":"Point"}
}