{
  "type": "Feature",
  "properties": {
    "gn:admin1_code":"10.0",
    "gn:asciiname":"Zhongzhuang",
    "gn:country_code":"CN",
    "gn:dem":956,
    "gn:feature_class":"P",
    "gn:feature_code":"PPL",
    "gn:name":"Zhongzhuang",
    "gn:population":0,
    "gn:timezone":"Asia/Shanghai",
    "iso:country":"CN",
    "name:und_x_variant":[
        "Chung-chuang",
        "Zhongzhuang"
    ],
    "name:zho_x_preferred":[
        "\u4e2d\u5e84"
    ],
    "wof:name":"Zhongzhuang",
    "wof:placetype":"locality"
},
  "geometry": {"coordinates":[114.7625,39.45779],"type":"Point"}
}