{
  "type": "Feature",
  "properties": {
    "gn:admin1_code":"19.0",
    "gn:asciiname":"Shantou",
    "gn:country_code":"CN",
    "gn:dem":117,
    "gn:feature_class":"P",
    "gn:feature_code":"PPL",
    "gn:name":"Shantou",
    "gn:population":0,
    "gn:timezone":"Asia/Shanghai",
    "iso:country":"CN",
    "name:und_x_variant":[
        "\u5c71\u5934"
    ],
    "name:zho_x_preferred":[
        "\u5c71\u5934"
    ],
    "wof:name":"Shantou",
    "wof:placetype":"locality"
},
  "geometry": {"coordinates":[123.15624,40.19453],"type":"Point"}
}