{
  "type": "Feature",
  "properties": {
    "gn:admin1_code":"7",
    "gn:asciiname":"Xikengli",
    "gn:country_code":"CN",
    "gn:dem":548,
    "gn:feature_class":"P",
    "gn:feature_code":"PPL",
    "gn:name":"Xikengli",
    "gn:population":0,
    "gn:timezone":"Asia/Shanghai",
    "iso:country":"CN",
    "name:und_x_variant":[
        "\u897f\u5751\u91cc",
        "Xikengli"
    ],
    "wof:name":"Xikengli",
    "wof:placetype":"locality"
},
  "geometry": {"coordinates":[119.98244,27.27235],"type":"Point"}
}