{
  "type": "Feature",
  "properties": {
    "gn:admin1_code":"16.0",
    "gn:asciiname":"Yangtiantang",
    "gn:country_code":"CN",
    "gn:dem":46,
    "gn:feature_class":"P",
    "gn:feature_code":"PPL",
    "gn:name":"Yangtiantang",
    "gn:population":0,
    "gn:timezone":"Asia/Shanghai",
    "iso:country":"CN",
    "name:zho_x_preferred":[
        "\u4ef0\u5929\u5802"
    ],
    "wof:name":"Yangtiantang",
    "wof:placetype":"locality"
},
  "geometry": {"coordinates":[110.206,23.6352],"type":"Point"}
}