{
  "type": "Feature",
  "properties": {
    "gn:admin1_code":"30",
    "gn:asciiname":"Jinpanzai",
    "gn:country_code":"CN",
    "gn:dem":36,
    "gn:feature_class":"P",
    "gn:feature_code":"PPL",
    "gn:name":"Jinpanzai",
    "gn:population":0,
    "gn:timezone":"Asia/Urumqi",
    "iso:country":"CN",
    "name:zho_x_preferred":[
        "\u9526\u76d8\u4ed4"
    ],
    "wof:name":"Jinpanzai",
    "wof:placetype":"locality"
},
  "geometry": {"coordinates":[109.78055999999999,20.91708],"type":"Point"}
}