{
  "type": "Feature",
  "properties": {
    "gn:admin1_code":"7.0",
    "gn:asciiname":"Luyuan",
    "gn:country_code":"CN",
    "gn:dem":73,
    "gn:feature_class":"P",
    "gn:feature_code":"PPL",
    "gn:name":"Luyuan",
    "gn:population":0,
    "gn:timezone":"Asia/Shanghai",
    "iso:country":"CN",
    "name:zho_x_preferred":[
        "\u82a6\u9662"
    ],
    "wof:name":"Luyuan",
    "wof:placetype":"locality"
},
  "geometry": {"coordinates":[119.36083000000001,25.78523],"type":"Point"}
}