{
  "type": "Feature",
  "properties": {
    "gn:admin1_code":"15.0",
    "gn:asciiname":"Hujiazhuang",
    "gn:country_code":"CN",
    "gn:dem":1765,
    "gn:feature_class":"P",
    "gn:feature_code":"PPL",
    "gn:name":"Hujiazhuang",
    "gn:population":0,
    "gn:timezone":"Asia/Shanghai",
    "iso:country":"CN",
    "name:zho_x_preferred":[
        "\u80e1\u5bb6\u5e84"
    ],
    "wof:name":"Hujiazhuang",
    "wof:placetype":"locality"
},
  "geometry": {"coordinates":[103.051,37.6234],"type":"Point"}
}