{
  "type": "Feature",
  "properties": {
    "gn:admin1_code":"1.0",
    "gn:asciiname":"Simaoling",
    "gn:country_code":"CN",
    "gn:dem":226,
    "gn:feature_class":"P",
    "gn:feature_code":"PPL",
    "gn:name":"Simaoling",
    "gn:population":0,
    "gn:timezone":"Asia/Shanghai",
    "iso:country":"CN",
    "name:zho_x_preferred":[
        "\u53f8\u8305\u5cad"
    ],
    "wof:name":"Simaoling",
    "wof:placetype":"locality"
},
  "geometry": {"coordinates":[118.68013999999999,30.48035],"type":"Point"}
}