{
  "type": "Feature",
  "properties": {
    "gn:admin1_code":"4.0",
    "gn:asciiname":"Zhuyuancun",
    "gn:country_code":"CN",
    "gn:dem":52,
    "gn:feature_class":"P",
    "gn:feature_code":"PPL",
    "gn:name":"Zhuyuancun",
    "gn:population":0,
    "gn:timezone":"Asia/Shanghai",
    "iso:country":"CN",
    "name:zho_x_preferred":[
        "\u7af9\u5143\u6751"
    ],
    "wof:name":"Zhuyuancun",
    "wof:placetype":"locality"
},
  "geometry": {"coordinates":[117.37712999999999,34.47606],"type":"Point"}
}