{
  "type": "Feature",
  "properties": {
    "gn:country":"CN",
    "gn:fcode":"PPLA2",
    "gn:population":218427,
    "iso:country":"CN",
    "name:cdo_x_preferred":[
        "\u016c-h\u0101i"
    ],
    "name:ces_x_preferred":[
        "Wu-chaj"
    ],
    "name:epo_x_preferred":[
        "Vuhajo"
    ],
    "name:fas_x_preferred":[
        "\u0648\u0648\u0647\u0627\u06cc"
    ],
    "name:hak_x_preferred":[
        "V\u00fb-h\u00f3i-s\u1e73"
    ],
    "name:jpn_x_preferred":[
        "\u70cf\u6d77\u5e02"
    ],
    "name:kor_x_preferred":[
        "\uc6b0\ud558\uc774 \uc2dc"
    ],
    "name:lit_x_preferred":[
        "Uhajus"
    ],
    "name:mon_x_preferred":[
        "\u04ae\u0445\u0430\u0439 \u0445\u043e\u0442"
    ],
    "name:nan_x_preferred":[
        "O\u0358-h\u00e1i-chh\u012b"
    ],
    "name:rus_x_preferred":[
        "\u0423\u0445\u0430\u0439"
    ],
    "name:und_x_variant":[
        "Hai-po-wan"
    ],
    "name:urd_x_preferred":[
        "\u0648\u0648\u06c1\u0627\u0626\u06cc"
    ],
    "name:vie_x_preferred":[
        "\u00d4 H\u1ea3i"
    ],
    "name:yue_x_preferred":[
        "\u70cf\u6d77"
    ],
    "qs_pg:aaroncc":"CN",
    "qs_pg:gn_country":"CN",
    "qs_pg:gn_fcode":"PPLA2",
    "qs_pg:gn_pop":218427,
    "qs_pg:name":"\u4e4c\u6d77\u5e02",
    "qs_pg:name_adm0":"\u4e2d\u570b",
    "qs_pg:name_adm1":"\u5185\u8499\u53e4\u81ea\u6cbb\u533a",
    "qs_pg:photos":8,
    "qs_pg:photos_1k":2,
    "qs_pg:photos_9k":1,
    "qs_pg:photos_9r":3,
    "qs_pg:photos_all":82,
    "qs_pg:photos_sr":1,
    "qs_pg:pop_sr":10,
    "qs_pg:qs_pg_placetype":"localadmin",
    "qs_pg:qs_pg_placetype_gp":"LocalAdmin",
    "qs_pg:woe_adm0":23424781,
    "woe:adm0_id":23424781,
    "woe:name_adm0":"\u4e2d\u570b",
    "woe:name_adm1":"\u5185\u8499\u53e4\u81ea\u6cbb\u533a",
    "woe:placetype":"LocalAdmin",
    "wof:name":"\u4e4c\u6d77\u5e02",
    "wof:placetype":"localadmin",
    "wof:population":218427
},
  "geometry": {"coordinates":[106.81222,39.66472],"type":"Point"}
}