{
  "type": "Feature",
  "properties": {
    "gn:admin1_code":"14.0",
    "gn:asciiname":"Cuobang",
    "gn:country_code":"CN",
    "gn:dem":4362,
    "gn:feature_class":"P",
    "gn:feature_code":"PPL",
    "gn:name":"Cuobang",
    "gn:population":0,
    "gn:timezone":"Asia/Urumqi",
    "iso:country":"CN",
    "name:zho_x_preferred":[
        "\u9519\u5e2e"
    ],
    "wof:name":"Cuobang",
    "wof:placetype":"locality"
},
  "geometry": {"coordinates":[93.61861,29.50647],"type":"Point"}
}