{
  "type": "Feature",
  "properties": {
    "gn:admin1_code":"26.0",
    "gn:asciiname":"Shiping",
    "gn:country_code":"CN",
    "gn:dem":998,
    "gn:feature_class":"P",
    "gn:feature_code":"PPL",
    "gn:name":"Shiping",
    "gn:population":0,
    "gn:timezone":"Asia/Shanghai",
    "iso:country":"CN",
    "name:zho_x_preferred":[
        "\u5e08\u576a"
    ],
    "wof:name":"Shiping",
    "wof:placetype":"locality"
},
  "geometry": {"coordinates":[110.11695,34.0375],"type":"Point"}
}