{
  "type": "Feature",
  "properties": {
    "gn:admin1_code":"7",
    "gn:asciiname":"Taqian",
    "gn:cc2":"CN",
    "gn:country_code":"CN",
    "gn:dem":10,
    "gn:feature_class":"P",
    "gn:feature_code":"PPL",
    "gn:name":"Taqian",
    "gn:population":0,
    "gn:timezone":"Asia/Shanghai",
    "iso:country":"CN",
    "name:zho_x_preferred":[
        "T\u2019a-ch\u2019ien"
    ],
    "wof:name":"Taqian",
    "wof:placetype":"locality"
},
  "geometry": {"coordinates":[118.61778,24.75083],"type":"Point"}
}