{
  "type": "Feature",
  "properties": {
    "gn:admin1_code":"25.0",
    "gn:asciiname":"Dagaolan",
    "gn:country_code":"CN",
    "gn:dem":60,
    "gn:feature_class":"P",
    "gn:feature_code":"PPL",
    "gn:name":"Dagaolan",
    "gn:population":0,
    "gn:timezone":"Asia/Shanghai",
    "iso:country":"CN",
    "name:zho_x_preferred":[
        "\u5927\u9ad8\u5c9a"
    ],
    "wof:name":"Dagaolan",
    "wof:placetype":"locality"
},
  "geometry": {"coordinates":[120.3693,36.81075],"type":"Point"}
}