{
  "type": "Feature",
  "properties": {
    "gn:admin1_code":"18.0",
    "gn:asciiname":"Niedong",
    "gn:country_code":"CN",
    "gn:dem":588,
    "gn:feature_class":"P",
    "gn:feature_code":"PPL",
    "gn:name":"Niedong",
    "gn:population":0,
    "gn:timezone":"Asia/Shanghai",
    "iso:country":"CN",
    "name:zho_x_preferred":[
        "\u4e5c\u6d1e"
    ],
    "wof:name":"Niedong",
    "wof:placetype":"locality"
},
  "geometry": {"coordinates":[108.995,26.2049],"type":"Point"}
}