{
  "type": "Feature",
  "properties": {
    "gn:admin1_code":"31.0",
    "gn:asciiname":"Ruweng",
    "gn:country_code":"CN",
    "gn:dem":203,
    "gn:feature_class":"P",
    "gn:feature_code":"PPL",
    "gn:name":"Ruweng",
    "gn:population":0,
    "gn:timezone":"Asia/Shanghai",
    "iso:country":"CN",
    "name:zho_x_preferred":[
        "\u5982\u7fc1"
    ],
    "wof:name":"Ruweng",
    "wof:placetype":"locality"
},
  "geometry": {"coordinates":[109.13200000000001,19.1879],"type":"Point"}
}