{
  "type": "Feature",
  "properties": {
    "gn:admin1_code":"30",
    "gn:asciiname":"Wangzhucun",
    "gn:country_code":"CN",
    "gn:dem":76,
    "gn:feature_class":"P",
    "gn:feature_code":"PPL",
    "gn:name":"Wangzhucun",
    "gn:population":0,
    "gn:timezone":"Asia/Urumqi",
    "iso:country":"CN",
    "name:zho_x_preferred":[
        "\u65fa\u7af9\u6751"
    ],
    "wof:name":"Wangzhucun",
    "wof:placetype":"locality"
},
  "geometry": {"coordinates":[110.49142999999999,22.10342],"type":"Point"}
}