{
  "type": "Feature",
  "properties": {
    "gn:admin1_code":"4.0",
    "gn:asciiname":"Luhe Sizu",
    "gn:country_code":"CN",
    "gn:dem":5,
    "gn:feature_class":"P",
    "gn:feature_code":"PPLF",
    "gn:name":"Luhe Sizu",
    "gn:population":0,
    "gn:timezone":"Asia/Shanghai",
    "iso:country":"CN",
    "name:zho_x_preferred":[
        "Luhe Sizu"
    ],
    "name:zho_x_variant":[
        "\u82a6\u6cb3\u56db\u7ec4"
    ],
    "wof:name":"Luhe Sizu",
    "wof:placetype":"locality"
},
  "geometry": {"coordinates":[119.01347,34.77714],"type":"Point"}
}