{
  "type": "Feature",
  "properties": {
    "gn:admin1_code":"15.0",
    "gn:asciiname":"Sifu",
    "gn:country_code":"CN",
    "gn:dem":1830,
    "gn:feature_class":"P",
    "gn:feature_code":"PPL",
    "gn:name":"Sifu",
    "gn:population":0,
    "gn:timezone":"Asia/Shanghai",
    "iso:country":"CN",
    "name:und_x_variant":[
        "\u56db\u798f"
    ],
    "wof:name":"Sifu",
    "wof:placetype":"locality"
},
  "geometry": {"coordinates":[105.57615,35.56740999999999],"type":"Point"}
}