{
  "type": "Feature",
  "properties": {
    "gn:admin1_code":"2.0",
    "gn:asciiname":"Shijiaqiao",
    "gn:country_code":"CN",
    "gn:dem":8,
    "gn:feature_class":"P",
    "gn:feature_code":"PPL",
    "gn:name":"Shijiaqiao",
    "gn:population":0,
    "gn:timezone":"Asia/Shanghai",
    "iso:country":"CN",
    "name:und_x_variant":[
        "\u53f2\u5bb6\u6865"
    ],
    "wof:name":"Shijiaqiao",
    "wof:placetype":"locality"
},
  "geometry": {"coordinates":[120.54642,30.57632000000001],"type":"Point"}
}