{
  "type": "Feature",
  "properties": {
    "gn:admin1_code":"9.0",
    "gn:asciiname":"Jingshui",
    "gn:country_code":"CN",
    "gn:dem":92,
    "gn:feature_class":"P",
    "gn:feature_code":"PPL",
    "gn:name":"Jingshui",
    "gn:population":0,
    "gn:timezone":"Asia/Shanghai",
    "iso:country":"CN",
    "name:zho_x_preferred":[
        "\u4eac\u6c34"
    ],
    "wof:name":"Jingshui",
    "wof:placetype":"locality"
},
  "geometry": {"coordinates":[113.69197,34.87793],"type":"Point"}
}