{
  "type": "Feature",
  "properties": {
    "gn:admin1_code":"10",
    "gn:asciiname":"Fenshuikou",
    "gn:country_code":"CN",
    "gn:dem":721,
    "gn:feature_class":"P",
    "gn:feature_code":"PPL",
    "gn:name":"Fenshuikou",
    "gn:population":0,
    "gn:timezone":"Asia/Shanghai",
    "iso:country":"CN",
    "name:zho_x_preferred":[
        "\u5206\u6c34\u53e3"
    ],
    "wof:name":"Fenshuikou",
    "wof:placetype":"locality"
},
  "geometry": {"coordinates":[114.99142999999999,40.52071],"type":"Point"}
}