{
  "type": "Feature",
  "properties": {
    "gn:admin1_code":"20.0",
    "gn:asciiname":"Zhongchun Tingge",
    "gn:country_code":"CN",
    "gn:dem":363,
    "gn:feature_class":"P",
    "gn:feature_code":"PPL",
    "gn:name":"Zhongchun Tingge",
    "gn:population":0,
    "gn:timezone":"Asia/Shanghai",
    "iso:country":"CN",
    "name:zho_x_preferred":[
        "\u4e2d\u6625\u4ead\u9601"
    ],
    "wof:name":"Zhongchun Tingge",
    "wof:placetype":"locality"
},
  "geometry": {"coordinates":[124.50653,49.92497],"type":"Point"}
}