{
  "type": "Feature",
  "properties": {
    "gn:admin1_code":"3.0",
    "gn:asciiname":"Zixi",
    "gn:country_code":"CN",
    "gn:dem":211,
    "gn:feature_class":"P",
    "gn:feature_code":"PPLA4",
    "gn:name":"Zixi",
    "gn:population":0,
    "gn:timezone":"Asia/Shanghai",
    "iso:country":"CN",
    "name:und_x_variant":[
        "Tzu-chi",
        "Tzu-ch\u2019i-chieh",
        "Tzu-hsi",
        "Zixi",
        "\u7d2b\u6eaa",
        "Zixi Xiang",
        "\u7d2b\u6eaa\u4e61"
    ],
    "wof:name":"Zixi",
    "wof:placetype":"locality"
},
  "geometry": {"coordinates":[117.78400000000001,28.06949],"type":"Point"}
}