{
  "type": "Feature",
  "properties": {
    "gn:admin1_code":"32.0",
    "gn:asciiname":"Qipanshi",
    "gn:country_code":"CN",
    "gn:dem":464,
    "gn:feature_class":"P",
    "gn:feature_code":"PPL",
    "gn:name":"Qipanshi",
    "gn:population":0,
    "gn:timezone":"Asia/Shanghai",
    "iso:country":"CN",
    "name:zho_x_preferred":[
        "\u68cb\u76d8\u77f3"
    ],
    "wof:name":"Qipanshi",
    "wof:placetype":"locality"
},
  "geometry": {"coordinates":[105.3776,28.6488],"type":"Point"}
}