{
  "type": "Feature",
  "properties": {
    "gn:admin1_code":"29.0",
    "gn:asciiname":"Xiaoxuepo",
    "gn:country_code":"CN",
    "gn:dem":2368,
    "gn:feature_class":"P",
    "gn:feature_code":"PPL",
    "gn:name":"Xiaoxuepo",
    "gn:population":0,
    "gn:timezone":"Asia/Shanghai",
    "iso:country":"CN",
    "name:zho_x_preferred":[
        "\u5c0f\u96ea\u5761"
    ],
    "wof:name":"Xiaoxuepo",
    "wof:placetype":"locality"
},
  "geometry": {"coordinates":[101.93600000000001,25.8905],"type":"Point"}
}