{
  "type": "Feature",
  "properties": {
    "gn:admin1_code":"32.0",
    "gn:asciiname":"Huoran",
    "gn:country_code":"CN",
    "gn:dem":4153,
    "gn:feature_class":"P",
    "gn:feature_code":"PPL",
    "gn:name":"Huoran",
    "gn:population":0,
    "gn:timezone":"Asia/Shanghai",
    "iso:country":"CN",
    "name:zho_x_preferred":[
        "\u706b\u7136"
    ],
    "wof:name":"Huoran",
    "wof:placetype":"locality"
},
  "geometry": {"coordinates":[98.2444,33.2564],"type":"Point"}
}