{
  "type": "Feature",
  "properties": {
    "gn:admin1_code":"25",
    "gn:asciiname":"Zhangjia'aiqu",
    "gn:country_code":"CN",
    "gn:dem":40,
    "gn:feature_class":"P",
    "gn:feature_code":"PPL",
    "gn:name":"Zhangjia\u2019aiqu",
    "gn:population":0,
    "gn:timezone":"Asia/Shanghai",
    "iso:country":"CN",
    "name:und_x_variant":[
        "Zhangjia\u2019aiqu"
    ],
    "name:zho_x_preferred":[
        "\u5f20\u5bb6\u827e\u66f2"
    ],
    "wof:name":"Zhangjia'aiqu",
    "wof:placetype":"locality"
},
  "geometry": {"coordinates":[117.899,34.7861],"type":"Point"}
}