{
  "type": "Feature",
  "properties": {
    "gn:admin1_code":"3.0",
    "gn:asciiname":"Yangyutang Lijia",
    "gn:country_code":"CN",
    "gn:dem":32,
    "gn:feature_class":"P",
    "gn:feature_code":"PPL",
    "gn:name":"Yangyutang Lijia",
    "gn:population":0,
    "gn:timezone":"Asia/Shanghai",
    "iso:country":"CN",
    "name:und_x_variant":[
        "\u517b\u9c7c\u5858\u674e\u5bb6"
    ],
    "wof:name":"Yangyutang Lijia",
    "wof:placetype":"locality"
},
  "geometry": {"coordinates":[116.24694,28.4582],"type":"Point"}
}