{
  "type": "Feature",
  "properties": {
    "gn:admin1_code":"2.0",
    "gn:asciiname":"Dangli",
    "gn:country_code":"CN",
    "gn:dem":10,
    "gn:feature_class":"P",
    "gn:feature_code":"PPL",
    "gn:name":"Dangli",
    "gn:population":0,
    "gn:timezone":"Asia/Shanghai",
    "iso:country":"CN",
    "name:und_x_variant":[
        "\u8361\u91cc"
    ],
    "wof:name":"Dangli",
    "wof:placetype":"locality"
},
  "geometry": {"coordinates":[120.78888000000001,30.34433],"type":"Point"}
}