{
  "type": "Feature",
  "properties": {
    "gn:admin1_code":"1.0",
    "gn:asciiname":"Zhujiafancun",
    "gn:country_code":"CN",
    "gn:dem":98,
    "gn:feature_class":"P",
    "gn:feature_code":"PPL",
    "gn:name":"Zhujiafancun",
    "gn:population":0,
    "gn:timezone":"Asia/Shanghai",
    "iso:country":"CN",
    "name:zho_x_preferred":[
        "\u6731\u5bb6\u7548\u6751"
    ],
    "wof:name":"Zhujiafancun",
    "wof:placetype":"locality"
},
  "geometry": {"coordinates":[116.22589000000001,31.3845],"type":"Point"}
}