{
  "type": "Feature",
  "properties": {
    "gn:admin1_code":"3.0",
    "gn:asciiname":"Xiamiankeng",
    "gn:country_code":"CN",
    "gn:dem":292,
    "gn:feature_class":"P",
    "gn:feature_code":"PPL",
    "gn:name":"Xiamiankeng",
    "gn:population":0,
    "gn:timezone":"Asia/Shanghai",
    "iso:country":"CN",
    "name:und_x_variant":[
        "\u4e0b\u68c9\u5751"
    ],
    "wof:name":"Xiamiankeng",
    "wof:placetype":"locality"
},
  "geometry": {"coordinates":[116.42328000000001,26.47239],"type":"Point"}
}