{
  "type": "Feature",
  "properties": {
    "gn:admin1_code":"21.0",
    "gn:asciiname":"Xingshuwan",
    "gn:country_code":"CN",
    "gn:dem":1778,
    "gn:feature_class":"P",
    "gn:feature_code":"PPL",
    "gn:name":"Xingshuwan",
    "gn:population":0,
    "gn:timezone":"Asia/Shanghai",
    "iso:country":"CN",
    "name:und_x_variant":[
        "\u674f\u6811\u6e7e"
    ],
    "name:zho_x_preferred":[
        "\u674f\u6811\u6e7e"
    ],
    "wof:name":"Xingshuwan",
    "wof:placetype":"locality"
},
  "geometry": {"coordinates":[105.83049,35.60694],"type":"Point"}
}