{
  "type": "Feature",
  "properties": {
    "gn:admin1_code":"1.0",
    "gn:asciiname":"Tangbeicun",
    "gn:country_code":"CN",
    "gn:dem":27,
    "gn:feature_class":"P",
    "gn:feature_code":"PPL",
    "gn:name":"Tangbeicun",
    "gn:population":0,
    "gn:timezone":"Asia/Shanghai",
    "iso:country":"CN",
    "name:zho_x_preferred":[
        "\u5858\u5317\u6751"
    ],
    "wof:name":"Tangbeicun",
    "wof:placetype":"locality"
},
  "geometry": {"coordinates":[116.55426,32.26081],"type":"Point"}
}