{
  "type": "Feature",
  "properties": {
    "gn:admin1_code":"1.0",
    "gn:asciiname":"Magang",
    "gn:country_code":"CN",
    "gn:dem":38,
    "gn:feature_class":"P",
    "gn:feature_code":"PPL",
    "gn:name":"Magang",
    "gn:population":0,
    "gn:timezone":"Asia/Shanghai",
    "iso:country":"CN",
    "name:ceb_x_preferred":[
        "Magang"
    ],
    "name:swe_x_preferred":[
        "Magang"
    ],
    "wof:name":"Magang",
    "wof:placetype":"locality"
},
  "geometry": {"coordinates":[117.95556000000001,32.75],"type":"Point"}
}