{
  "type": "Feature",
  "properties": {
    "gn:admin1_code":"30.0",
    "gn:asciiname":"Gongkeng",
    "gn:country_code":"CN",
    "gn:dem":172,
    "gn:feature_class":"P",
    "gn:feature_code":"PPL",
    "gn:name":"Gongkeng",
    "gn:population":0,
    "gn:timezone":"Asia/Shanghai",
    "iso:country":"CN",
    "name:zho_x_preferred":[
        "\u516c\u5751"
    ],
    "wof:name":"Gongkeng",
    "wof:placetype":"locality"
},
  "geometry": {"coordinates":[113.85936,24.37492],"type":"Point"}
}