{
  "type": "Feature",
  "properties": {
    "gn:admin1_code":"19",
    "gn:asciiname":"Nangou",
    "gn:country_code":"CN",
    "gn:dem":582,
    "gn:feature_class":"P",
    "gn:feature_code":"PPL",
    "gn:name":"Nangou",
    "gn:population":0,
    "gn:timezone":"Asia/Shanghai",
    "iso:country":"CN",
    "wof:name":"Nangou",
    "wof:placetype":"locality"
},
  "geometry": {"coordinates":[123.91528,41.10139],"type":"Point"}
}