{
  "type": "Feature",
  "properties": {
    "gn:admin1_code":"13.0",
    "gn:asciiname":"Tuogela Keruike",
    "gn:country_code":"CN",
    "gn:dem":1910,
    "gn:feature_class":"P",
    "gn:feature_code":"PPL",
    "gn:name":"Tuogela Keruike",
    "gn:population":0,
    "gn:timezone":"Asia/Shanghai",
    "iso:country":"CN",
    "name:zho_x_preferred":[
        "\u6258\u683c\u62c9\u514b\u745e\u514b"
    ],
    "wof:name":"Tuogela Keruike",
    "wof:placetype":"locality"
},
  "geometry": {"coordinates":[77.80755000000001,37.41529],"type":"Point"}
}