{
  "type": "Feature",
  "properties": {
    "gn:admin1_code":"5.0",
    "gn:asciiname":"Xinglong",
    "gn:country_code":"CN",
    "gn:dem":275,
    "gn:feature_class":"P",
    "gn:feature_code":"PPL",
    "gn:name":"Xinglong",
    "gn:population":0,
    "gn:timezone":"Asia/Shanghai",
    "iso:country":"CN",
    "name:zho_x_preferred":[
        "\u5174\u9686"
    ],
    "wof:name":"Xinglong",
    "wof:placetype":"locality"
},
  "geometry": {"coordinates":[126.82695,43.05685],"type":"Point"}
}