{
  "type": "Feature",
  "properties": {
    "gn:admin1_code":"4.0",
    "gn:asciiname":"Sihe",
    "gn:country_code":"CN",
    "gn:dem":18,
    "gn:feature_class":"P",
    "gn:feature_code":"PPL",
    "gn:name":"Sihe",
    "gn:population":0,
    "gn:timezone":"Asia/Shanghai",
    "iso:country":"CN",
    "name:zho_x_preferred":[
        "\u6cd7\u6cb3"
    ],
    "wof:name":"Sihe",
    "wof:placetype":"locality"
},
  "geometry": {"coordinates":[118.23399999999999,33.678],"type":"Point"}
}