{
  "type": "Feature",
  "properties": {
    "gn:admin1_code":"8.0",
    "gn:asciiname":"Jinchangcun",
    "gn:country_code":"CN",
    "gn:dem":290,
    "gn:feature_class":"P",
    "gn:feature_code":"PPL",
    "gn:name":"Jinchangcun",
    "gn:population":0,
    "gn:timezone":"Asia/Shanghai",
    "iso:country":"CN",
    "name:zho_x_preferred":[
        "\u91d1\u573a\u6751"
    ],
    "wof:name":"Jinchangcun",
    "wof:placetype":"locality"
},
  "geometry": {"coordinates":[129.84863000000001,44.7598],"type":"Point"}
}