{
  "type": "Feature",
  "properties": {
    "gn:admin1_code":"29.0",
    "gn:asciiname":"Laowangshan",
    "gn:country_code":"CN",
    "gn:dem":1011,
    "gn:feature_class":"P",
    "gn:feature_code":"PPL",
    "gn:name":"Laowangshan",
    "gn:population":0,
    "gn:timezone":"Asia/Shanghai",
    "iso:country":"CN",
    "name:zho_x_preferred":[
        "\u8001\u6c6a\u5c71"
    ],
    "wof:name":"Laowangshan",
    "wof:placetype":"locality"
},
  "geometry": {"coordinates":[104.117,22.8477],"type":"Point"}
}