{
  "type": "Feature",
  "properties": {
    "gn:admin1_code":"26.0",
    "gn:asciiname":"Zhaolangou",
    "gn:country_code":"CN",
    "gn:dem":1350,
    "gn:feature_class":"P",
    "gn:feature_code":"PPL",
    "gn:name":"Zhaolangou",
    "gn:population":0,
    "gn:timezone":"Asia/Shanghai",
    "iso:country":"CN",
    "name:zho_x_preferred":[
        "\u8d75\u5170\u6c9f"
    ],
    "wof:name":"Zhaolangou",
    "wof:placetype":"locality"
},
  "geometry": {"coordinates":[108.33027,36.63800000000001],"type":"Point"}
}