{
  "type": "Feature",
  "properties": {
    "gn:admin1_code":"5.0",
    "gn:asciiname":"Qiantuozicun",
    "gn:country_code":"CN",
    "gn:dem":140,
    "gn:feature_class":"P",
    "gn:feature_code":"PPL",
    "gn:name":"Qiantuozicun",
    "gn:population":0,
    "gn:timezone":"Asia/Shanghai",
    "iso:country":"CN",
    "name:zho_x_preferred":[
        "\u524d\u5768\u5b50\u6751"
    ],
    "wof:name":"Qiantuozicun",
    "wof:placetype":"locality"
},
  "geometry": {"coordinates":[125.28225999999999,45.35171],"type":"Point"}
}