{
  "type": "Feature",
  "properties": {
    "gn:admin1_code":"22.0",
    "gn:asciiname":"Duijintaicun",
    "gn:country_code":"CN",
    "gn:dem":1140,
    "gn:feature_class":"P",
    "gn:feature_code":"PPL",
    "gn:name":"Duijintaicun",
    "gn:population":0,
    "gn:timezone":"Asia/Shanghai",
    "iso:country":"CN",
    "name:zho_x_preferred":[
        "\u5806\u91d1\u53f0\u6751"
    ],
    "wof:name":"Duijintaicun",
    "wof:placetype":"locality"
},
  "geometry": {"coordinates":[115.53825999999999,39.7817],"type":"Point"}
}