{
  "type": "Feature",
  "properties": {
    "gn:admin1_code":"1.0",
    "gn:asciiname":"Shizhaicun",
    "gn:country_code":"CN",
    "gn:dem":33,
    "gn:feature_class":"P",
    "gn:feature_code":"PPL",
    "gn:name":"Shizhaicun",
    "gn:population":0,
    "gn:timezone":"Asia/Shanghai",
    "iso:country":"CN",
    "name:zho_x_preferred":[
        "\u77f3\u5be8\u6751"
    ],
    "wof:name":"Shizhaicun",
    "wof:placetype":"locality"
},
  "geometry": {"coordinates":[115.57349000000001,32.78009],"type":"Point"}
}