{
  "type": "Feature",
  "properties": {
    "gn:admin1_code":"09",
    "gn:asciiname":"Liulin",
    "gn:cc2":"CN",
    "gn:country_code":"CN",
    "gn:dem":168,
    "gn:feature_class":"P",
    "gn:feature_code":"PPL",
    "gn:name":"Liulin",
    "gn:population":0,
    "gn:timezone":"Asia/Shanghai",
    "iso:country":"CN",
    "name:und_x_variant":[
        "Liu-lin-shih",
        "Liu-lin-chen",
        "Liulin"
    ],
    "wof:name":"Liulin",
    "wof:placetype":"locality"
},
  "geometry": {"coordinates":[114.08360999999999,31.92306],"type":"Point"}
}