{
  "type": "Feature",
  "properties": {
    "gn:country":"CN",
    "gn:fcode":"PPLA3",
    "gn:population":188602,
    "iso:country":"CN",
    "name:ceb_x_preferred":[
        "Donghai"
    ],
    "name:deu_x_preferred":[
        "Donghai"
    ],
    "name:mlg_x_preferred":[
        "Donghai"
    ],
    "name:nor_x_preferred":[
        "Donghai"
    ],
    "name:und_x_variant":[
        "Lufeng"
    ],
    "name:vie_x_preferred":[
        "\u0110\u00f4ng H\u1ea3i"
    ],
    "name:zho_x_preferred":[
        "\u4e1c\u6d77"
    ],
    "qs:name":"Donghai",
    "qs:photos_9r":0,
    "qs:photos_sr":0,
    "qs:pop_sr":"9",
    "wd:wordcount":155,
    "wof:name":"Donghai",
    "wof:placetype":"locality",
    "wof:population":188602
},
  "geometry": {"coordinates":[115.64203999999999,22.94594],"type":"Point"}
}