{
  "type": "Feature",
  "properties": {
    "gn:country":"CN",
    "gn:fcode":"PPLA3",
    "gn:pop":188602,
    "iso:country":"CN",
    "name:unk_x_variant":[
        "Lufeng"
    ],
    "name:zho_x_preferred":[
        "\u4e1c\u6d77"
    ],
    "qs:name":"Donghai",
    "qs:photos_9r":0,
    "qs:photos_sr":0,
    "qs:pop_sr":"9",
    "wd:wordcount":155,
    "wof:name":"Donghai",
    "wof:placetype":"locality",
    "wof:population":188602
},
  "geometry": {"coordinates":[115.64203999999999,22.94594],"type":"Point"}
}