{
  "type": "Feature",
  "properties": {
    "gn:admin1_code":"02",
    "gn:asciiname":"Nanpu",
    "gn:country_code":"CN",
    "gn:dem":8,
    "gn:feature_class":"P",
    "gn:feature_code":"PPL",
    "gn:name":"Nanpu",
    "gn:population":0,
    "gn:timezone":"Asia/Shanghai",
    "iso:country":"CN",
    "name:deu_x_preferred":[
        "Nanpu"
    ],
    "wof:name":"Nanpu",
    "wof:placetype":"locality"
},
  "geometry": {"coordinates":[121.43444,29.71167],"type":"Point"}
}