{
  "type": "Feature",
  "properties": {
    "gn:admin1_code":"21.0",
    "gn:asciiname":"Bianjichang",
    "gn:country_code":"CN",
    "gn:dem":1511,
    "gn:feature_class":"P",
    "gn:feature_code":"PPL",
    "gn:name":"Bianjichang",
    "gn:population":0,
    "gn:timezone":"Asia/Shanghai",
    "iso:country":"CN",
    "name:zho_x_preferred":[
        "\u8fb9\u8bb0\u573a"
    ],
    "wof:name":"Bianjichang",
    "wof:placetype":"locality"
},
  "geometry": {"coordinates":[107.188,38.1386],"type":"Point"}
}