{
  "type": "Feature",
  "properties": {
    "gn:admin1_code":"3.0",
    "gn:asciiname":"Xiajialong",
    "gn:country_code":"CN",
    "gn:dem":317,
    "gn:feature_class":"P",
    "gn:feature_code":"PPL",
    "gn:name":"Xiajialong",
    "gn:population":0,
    "gn:timezone":"Asia/Shanghai",
    "iso:country":"CN",
    "name:und_x_variant":[
        "\u590f\u5bb6\u5785"
    ],
    "wof:name":"Xiajialong",
    "wof:placetype":"locality"
},
  "geometry": {"coordinates":[114.01690000000001,29.03268],"type":"Point"}
}