{
  "type": "Feature",
  "properties": {
    "gn:admin1_code":"11.0",
    "gn:asciiname":"Dianchong",
    "gn:country_code":"CN",
    "gn:dem":326,
    "gn:feature_class":"P",
    "gn:feature_code":"PPL",
    "gn:name":"Dianchong",
    "gn:population":0,
    "gn:timezone":"Asia/Shanghai",
    "iso:country":"CN",
    "name:zho_x_preferred":[
        "\u7535\u51b2"
    ],
    "wof:name":"Dianchong",
    "wof:placetype":"locality"
},
  "geometry": {"coordinates":[109.6096,27.31342],"type":"Point"}
}