{
  "type": "Feature",
  "properties": {
    "gn:admin1_code":"15.0",
    "gn:asciiname":"Xiaheishuwo",
    "gn:country_code":"CN",
    "gn:dem":1229,
    "gn:feature_class":"P",
    "gn:feature_code":"PPL",
    "gn:name":"Xiaheishuwo",
    "gn:population":0,
    "gn:timezone":"Asia/Shanghai",
    "iso:country":"CN",
    "name:zho_x_preferred":[
        "\u4e0b\u9ed1\u6811\u7a9d"
    ],
    "wof:name":"Xiaheishuwo",
    "wof:placetype":"locality"
},
  "geometry": {"coordinates":[98.95310000000001,40.2165],"type":"Point"}
}