{
  "type": "Feature",
  "properties": {
    "gn:admin1_code":"12.0",
    "gn:asciiname":"Dongwanshan",
    "gn:country_code":"CN",
    "gn:dem":438,
    "gn:feature_class":"P",
    "gn:feature_code":"PPL",
    "gn:name":"Dongwanshan",
    "gn:population":0,
    "gn:timezone":"Asia/Shanghai",
    "iso:country":"CN",
    "name:und_x_variant":[
        "\u4e1c\u4e07\u5c71"
    ],
    "wof:name":"Dongwanshan",
    "wof:placetype":"locality"
},
  "geometry": {"coordinates":[114.9405,30.20871],"type":"Point"}
}