{
  "type": "Feature",
  "properties": {
    "gn:admin1_code":"15.0",
    "gn:asciiname":"Xianshuigou",
    "gn:country_code":"CN",
    "gn:dem":2004,
    "gn:feature_class":"P",
    "gn:feature_code":"PPL",
    "gn:name":"Xianshuigou",
    "gn:population":0,
    "gn:timezone":"Asia/Shanghai",
    "iso:country":"CN",
    "name:zho_x_preferred":[
        "\u54b8\u6c34\u6c9f"
    ],
    "wof:name":"Xianshuigou",
    "wof:placetype":"locality"
},
  "geometry": {"coordinates":[104.40300000000001,35.195],"type":"Point"}
}