{
  "type": "Feature",
  "properties": {
    "gn:admin1_code":"30",
    "gn:asciiname":"Wang'an",
    "gn:country_code":"CN",
    "gn:dem":147,
    "gn:feature_class":"P",
    "gn:feature_code":"PPL",
    "gn:name":"Wang\u2019an",
    "gn:population":0,
    "gn:timezone":"Asia/Urumqi",
    "iso:country":"CN",
    "name:zho_x_preferred":[
        "\u65fa\u5cb8"
    ],
    "name:zho_x_variant":[
        "Wang\u2019an"
    ],
    "wof:name":"Wang'an",
    "wof:placetype":"locality"
},
  "geometry": {"coordinates":[111.20819,22.05778],"type":"Point"}
}