{
  "type": "Feature",
  "properties": {
    "gn:admin1_code":"18",
    "gn:asciiname":"Baruo",
    "gn:country_code":"CN",
    "gn:dem":511,
    "gn:feature_class":"P",
    "gn:feature_code":"PPL",
    "gn:name":"Baruo",
    "gn:population":0,
    "gn:timezone":"Asia/Shanghai",
    "iso:country":"CN",
    "name:zho_x_preferred":[
        "\u5df4\u82e5"
    ],
    "wof:name":"Baruo",
    "wof:placetype":"locality"
},
  "geometry": {"coordinates":[105.92400000000001,25.291],"type":"Point"}
}