{
  "type": "Feature",
  "properties": {
    "gn:admin1_code":"23.0",
    "gn:asciiname":"Xingxing",
    "gn:country_code":"CN",
    "gn:dem":5,
    "gn:feature_class":"P",
    "gn:feature_code":"PPL",
    "gn:name":"Xingxing",
    "gn:population":0,
    "gn:timezone":"Asia/Shanghai",
    "iso:country":"CN",
    "name:und_x_variant":[
        "\u661f\u661f"
    ],
    "wof:name":"Xingxing",
    "wof:placetype":"locality"
},
  "geometry": {"coordinates":[121.3695,31.05228],"type":"Point"}
}