{
  "type": "Feature",
  "properties": {
    "gn:admin1_code":"26.0",
    "gn:asciiname":"Dayudong",
    "gn:country_code":"CN",
    "gn:dem":873,
    "gn:feature_class":"P",
    "gn:feature_code":"PPL",
    "gn:name":"Dayudong",
    "gn:population":0,
    "gn:timezone":"Asia/Shanghai",
    "iso:country":"CN",
    "name:und_x_variant":[
        "\u5927\u9c7c\u7850"
    ],
    "wof:name":"Dayudong",
    "wof:placetype":"locality"
},
  "geometry": {"coordinates":[106.2933,33.12165],"type":"Point"}
}