{
  "type": "Feature",
  "properties": {
    "gn:admin1_code":"3",
    "gn:asciiname":"Luomukeng",
    "gn:country_code":"CN",
    "gn:dem":559,
    "gn:feature_class":"P",
    "gn:feature_code":"PPL",
    "gn:name":"Luomukeng",
    "gn:population":0,
    "gn:timezone":"Asia/Shanghai",
    "iso:country":"CN",
    "name:zho_x_preferred":[
        "\u843d\u6728\u5751"
    ],
    "wof:name":"Luomukeng",
    "wof:placetype":"locality"
},
  "geometry": {"coordinates":[114.404,25.4852],"type":"Point"}
}