{
  "type": "Feature",
  "properties": {
    "gn:admin1_code":"29",
    "gn:asciiname":"Dongxiaying",
    "gn:country_code":"CN",
    "gn:dem":1964,
    "gn:feature_class":"P",
    "gn:feature_code":"PPL",
    "gn:name":"Dongxiaying",
    "gn:population":0,
    "gn:timezone":"Asia/Shanghai",
    "iso:country":"CN",
    "name:zho_x_preferred":[
        "\u4e1c\u4e0b\u8425"
    ],
    "wof:name":"Dongxiaying",
    "wof:placetype":"locality"
},
  "geometry": {"coordinates":[102.68899999999999,24.5742],"type":"Point"}
}