{
  "type": "Feature",
  "properties": {
    "gn:admin1_code":"18",
    "gn:asciiname":"Xiayanwan",
    "gn:country_code":"CN",
    "gn:dem":883,
    "gn:feature_class":"P",
    "gn:feature_code":"PPL",
    "gn:name":"Xiayanwan",
    "gn:population":0,
    "gn:timezone":"Asia/Shanghai",
    "iso:country":"CN",
    "name:zho_x_preferred":[
        "\u4e0b\u5ca9\u6e7e"
    ],
    "wof:name":"Xiayanwan",
    "wof:placetype":"locality"
},
  "geometry": {"coordinates":[106.197,26.8686],"type":"Point"}
}