{
  "type": "Feature",
  "properties": {
    "gn:admin1_code":"30.0",
    "gn:asciiname":"Dianchang",
    "gn:country_code":"CN",
    "gn:dem":86,
    "gn:feature_class":"P",
    "gn:feature_code":"PPL",
    "gn:name":"Dianchang",
    "gn:population":0,
    "gn:timezone":"Asia/Shanghai",
    "iso:country":"CN",
    "name:zho_x_preferred":[
        "Dianchang"
    ],
    "name:zho_x_variant":[
        "\u5e97\u573a"
    ],
    "wof:name":"Dianchang",
    "wof:placetype":"locality"
},
  "geometry": {"coordinates":[115.15278000000001,24.27778],"type":"Point"}
}