{
  "type": "Feature",
  "properties": {
    "gn:admin1_code":"25",
    "gn:asciiname":"Jiangmazhuang",
    "gn:country_code":"CN",
    "gn:dem":51,
    "gn:feature_class":"P",
    "gn:feature_code":"PPL",
    "gn:name":"Jiangmazhuang",
    "gn:population":0,
    "gn:timezone":"Asia/Shanghai",
    "iso:country":"CN",
    "name:zho_x_preferred":[
        "\u59dc\u9a6c\u5e84"
    ],
    "wof:name":"Jiangmazhuang",
    "wof:placetype":"locality"
},
  "geometry": {"coordinates":[116.316,34.6102],"type":"Point"}
}