{
  "type": "Feature",
  "properties": {
    "gn:admin1_code":"16",
    "gn:asciiname":"Gaomiao",
    "gn:country_code":"CN",
    "gn:dem":164,
    "gn:feature_class":"P",
    "gn:feature_code":"PPL",
    "gn:name":"Gaomiao",
    "gn:population":0,
    "gn:timezone":"Asia/Shanghai",
    "iso:country":"CN",
    "name:zho_x_preferred":[
        "\u9ad8\u5999"
    ],
    "wof:name":"Gaomiao",
    "wof:placetype":"locality"
},
  "geometry": {"coordinates":[110.04300000000001,25.2137],"type":"Point"}
}