{
  "type": "Feature",
  "properties": {
    "gn:admin1_code":"08",
    "gn:asciiname":"Mashan",
    "gn:country_code":"CN",
    "gn:dem":272,
    "gn:feature_class":"P",
    "gn:feature_code":"PPLA3",
    "gn:name":"Mashan",
    "gn:population":0,
    "gn:timezone":"Asia/Shanghai",
    "iso:country":"CN",
    "name:deu_x_preferred":[
        "Mashan"
    ],
    "name:jpn_x_preferred":[
        "\u9ebb\u5c71\u533a"
    ],
    "name:kor_x_preferred":[
        "\ub9c8\uc0b0\uad6c"
    ],
    "name:nor_x_preferred":[
        "Mashan"
    ],
    "name:rus_x_preferred":[
        "\u041c\u0430\u0448\u0430\u043d\u044c"
    ],
    "name:swe_x_preferred":[
        "Mashan"
    ],
    "name:und_x_variant":[
        "Ma-shan-t\u2019un",
        "Mashan",
        "Mashan Qu"
    ],
    "name:vie_x_preferred":[
        "Ma S\u01a1n"
    ],
    "name:zho_x_preferred":[
        "\u9ebb\u5c71"
    ],
    "name:zho_x_variant":[
        "\u9ebb\u5c71\u533a"
    ],
    "wof:name":"Mashan",
    "wof:placetype":"locality"
},
  "geometry": {"coordinates":[130.52614,45.20508],"type":"Point"}
}