{
  "type": "Feature",
  "properties": {
    "gn:admin1_code":"14.0",
    "gn:asciiname":"Shelong",
    "gn:country_code":"CN",
    "gn:dem":4294,
    "gn:feature_class":"P",
    "gn:feature_code":"PPL",
    "gn:name":"Shelong",
    "gn:population":0,
    "gn:timezone":"Asia/Urumqi",
    "iso:country":"CN",
    "name:zho_x_preferred":[
        "\u5962\u9f99"
    ],
    "wof:name":"Shelong",
    "wof:placetype":"locality"
},
  "geometry": {"coordinates":[86.4859,29.212],"type":"Point"}
}