{
  "type": "Feature",
  "properties": {
    "gn:admin1_code":"15.0",
    "gn:asciiname":"Yuanjiaping",
    "gn:country_code":"CN",
    "gn:dem":1790,
    "gn:feature_class":"P",
    "gn:feature_code":"PPL",
    "gn:name":"Yuanjiaping",
    "gn:population":0,
    "gn:timezone":"Asia/Shanghai",
    "iso:country":"CN",
    "name:und_x_variant":[
        "\u8881\u5bb6\u576a"
    ],
    "wof:name":"Yuanjiaping",
    "wof:placetype":"locality"
},
  "geometry": {"coordinates":[105.11,35.9188],"type":"Point"}
}