{
  "type": "Feature",
  "properties": {
    "gn:admin1_code":"15.0",
    "gn:asciiname":"Wujiaxiamian",
    "gn:country_code":"CN",
    "gn:dem":1798,
    "gn:feature_class":"P",
    "gn:feature_code":"PPL",
    "gn:name":"Wujiaxiamian",
    "gn:population":0,
    "gn:timezone":"Asia/Shanghai",
    "iso:country":"CN",
    "name:und_x_variant":[
        "\u6b66\u5bb6\u4e0b\u9762"
    ],
    "wof:name":"Wujiaxiamian",
    "wof:placetype":"locality"
},
  "geometry": {"coordinates":[105.13670999999999,35.69379],"type":"Point"}
}