{
  "type": "Feature",
  "properties": {
    "gn:admin1_code":"32.0",
    "gn:asciiname":"Niuquanfang",
    "gn:country_code":"CN",
    "gn:dem":1792,
    "gn:feature_class":"P",
    "gn:feature_code":"PPL",
    "gn:name":"Niuquanfang",
    "gn:population":0,
    "gn:timezone":"Asia/Shanghai",
    "iso:country":"CN",
    "name:zho_x_preferred":[
        "\u725b\u5708\u623f"
    ],
    "wof:name":"Niuquanfang",
    "wof:placetype":"locality"
},
  "geometry": {"coordinates":[102.11324999999999,26.39071],"type":"Point"}
}