{
  "type": "Feature",
  "properties": {
    "gn:admin1_code":"12.0",
    "gn:asciiname":"Mozizhuang",
    "gn:country_code":"CN",
    "gn:dem":453,
    "gn:feature_class":"P",
    "gn:feature_code":"PPL",
    "gn:name":"Mozizhuang",
    "gn:population":0,
    "gn:timezone":"Asia/Shanghai",
    "iso:country":"CN",
    "name:zho_x_preferred":[
        "\u78e8\u5b50\u5e84"
    ],
    "wof:name":"Mozizhuang",
    "wof:placetype":"locality"
},
  "geometry": {"coordinates":[110.57698000000001,30.43455],"type":"Point"}
}