{
  "type": "Feature",
  "properties": {
    "gn:admin1_code":"29",
    "gn:asciiname":"Xiaoyundian",
    "gn:country_code":"CN",
    "gn:dem":1682,
    "gn:feature_class":"P",
    "gn:feature_code":"PPL",
    "gn:name":"Xiaoyundian",
    "gn:population":0,
    "gn:timezone":"Asia/Shanghai",
    "iso:country":"CN",
    "name:zho_x_preferred":[
        "\u5c0f\u4e91\u7538"
    ],
    "wof:name":"Xiaoyundian",
    "wof:placetype":"locality"
},
  "geometry": {"coordinates":[101.711,25.0193],"type":"Point"}
}