{
  "type": "Feature",
  "properties": {
    "gn:admin1_code":"11.0",
    "gn:asciiname":"Yankanzhai",
    "gn:country_code":"CN",
    "gn:dem":572,
    "gn:feature_class":"P",
    "gn:feature_code":"PPL",
    "gn:name":"Yankanzhai",
    "gn:population":0,
    "gn:timezone":"Asia/Shanghai",
    "iso:country":"CN",
    "name:zho_x_preferred":[
        "\u5ca9\u574e\u5be8"
    ],
    "wof:name":"Yankanzhai",
    "wof:placetype":"locality"
},
  "geometry": {"coordinates":[109.97138,28.55434],"type":"Point"}
}