{
  "type": "Feature",
  "properties": {
    "gn:admin1_code":"18",
    "gn:asciiname":"Mogedang",
    "gn:country_code":"CN",
    "gn:dem":1775,
    "gn:feature_class":"P",
    "gn:feature_code":"PPL",
    "gn:name":"Mogedang",
    "gn:population":0,
    "gn:timezone":"Asia/Shanghai",
    "iso:country":"CN",
    "name:zho_x_preferred":[
        "\u78e8\u683c\u5f53"
    ],
    "wof:name":"Mogedang",
    "wof:placetype":"locality"
},
  "geometry": {"coordinates":[104.44499999999999,25.7553],"type":"Point"}
}