{
  "type": "Feature",
  "properties": {
    "gn:admin1_code":"15",
    "gn:asciiname":"Tianchi",
    "gn:country_code":"CN",
    "gn:dem":1458,
    "gn:feature_class":"P",
    "gn:feature_code":"PPLA4",
    "gn:name":"Tianchi",
    "gn:population":0,
    "gn:timezone":"Asia/Shanghai",
    "iso:country":"CN",
    "name:ceb_x_preferred":[
        "Tianchi"
    ],
    "name:deu_x_preferred":[
        "Tian Chi"
    ],
    "name:fra_x_preferred":[
        "Tianchi"
    ],
    "name:jpn_x_preferred":[
        "\u5929\u6c60"
    ],
    "name:nld_x_preferred":[
        "Tianchi"
    ],
    "name:und_x_variant":[
        "Tianchi Xiang",
        "\u5929\u6c60\u4e61"
    ],
    "name:vie_x_preferred":[
        "Thi\u00ean Tr\u00ec"
    ],
    "wof:name":"Tianchi",
    "wof:placetype":"locality"
},
  "geometry": {"coordinates":[107.31155,36.23639],"type":"Point"}
}