{
  "type": "Feature",
  "properties": {
    "gn:admin1_code":"32.0",
    "gn:asciiname":"Houbazi",
    "gn:country_code":"CN",
    "gn:dem":1284,
    "gn:feature_class":"P",
    "gn:feature_code":"PPL",
    "gn:name":"Houbazi",
    "gn:population":0,
    "gn:timezone":"Asia/Shanghai",
    "iso:country":"CN",
    "name:zho_x_preferred":[
        "\u540e\u575d\u5b50"
    ],
    "wof:name":"Houbazi",
    "wof:placetype":"locality"
},
  "geometry": {"coordinates":[106.78663,32.56674],"type":"Point"}
}