{
  "type": "Feature",
  "properties": {
    "gn:admin1_code":"29.0",
    "gn:asciiname":"Gulu",
    "gn:country_code":"CN",
    "gn:dem":2877,
    "gn:feature_class":"P",
    "gn:feature_code":"PPL",
    "gn:name":"Gulu",
    "gn:population":0,
    "gn:timezone":"Asia/Shanghai",
    "iso:country":"CN",
    "name:zho_x_preferred":[
        "\u8c37\u9c81"
    ],
    "wof:name":"Gulu",
    "wof:placetype":"locality"
},
  "geometry": {"coordinates":[100.69799999999999,26.8707],"type":"Point"}
}