{
  "type": "Feature",
  "properties": {
    "gn:admin1_code":"29.0",
    "gn:asciiname":"Gulu",
    "gn:country_code":"CN",
    "gn:dem":2877,
    "gn:feature_class":"P",
    "gn:feature_code":"PPL",
    "gn:name":"Gulu",
    "gn:population":0,
    "gn:timezone":"Asia/Shanghai",
    "iso:country":"CN",
    "name:ara_x_preferred":[
        "\u063a\u0648\u0644\u0648"
    ],
    "name:azb_x_preferred":[
        "\u0642\u0648\u0644\u0648"
    ],
    "name:ceb_x_preferred":[
        "Gulu"
    ],
    "name:dan_x_preferred":[
        "Gulu"
    ],
    "name:deu_x_preferred":[
        "Gulu"
    ],
    "name:ell_x_preferred":[
        "\u0393\u03ba\u03bf\u03c5\u03bb\u03bf\u03cd"
    ],
    "name:epo_x_preferred":[
        "Gulu"
    ],
    "name:eus_x_preferred":[
        "Gulu"
    ],
    "name:fas_x_preferred":[
        "\u06af\u0648\u0644\u0648"
    ],
    "name:fin_x_preferred":[
        "Gulu"
    ],
    "name:fra_x_preferred":[
        "Gulu"
    ],
    "name:heb_x_preferred":[
        "\u05d2\u05d5\u05dc\u05d5"
    ],
    "name:hrv_x_preferred":[
        "Gulu"
    ],
    "name:hun_x_preferred":[
        "Gulu"
    ],
    "name:ind_x_preferred":[
        "Gulu"
    ],
    "name:ita_x_preferred":[
        "Gulu"
    ],
    "name:jpn_x_preferred":[
        "\u30b0\u30eb"
    ],
    "name:kal_x_preferred":[
        "Gulu"
    ],
    "name:kat_x_preferred":[
        "\u10d2\u10e3\u10da\u10e3"
    ],
    "name:lit_x_preferred":[
        "Gulu"
    ],
    "name:lug_x_preferred":[
        "Gulu"
    ],
    "name:mal_x_preferred":[
        "\u0d17\u0d41\u0d32\u0d41"
    ],
    "name:mri_x_preferred":[
        "Gulu"
    ],
    "name:nld_x_preferred":[
        "Gulu"
    ],
    "name:pol_x_preferred":[
        "Gulu"
    ],
    "name:por_x_preferred":[
        "Gulu"
    ],
    "name:ron_x_preferred":[
        "Gulu"
    ],
    "name:rus_x_preferred":[
        "\u0413\u0443\u043b\u0443"
    ],
    "name:spa_x_preferred":[
        "Gulu"
    ],
    "name:swa_x_preferred":[
        "Gulu"
    ],
    "name:swe_x_preferred":[
        "Gulu"
    ],
    "name:urd_x_preferred":[
        "\u06af\u0648\u0644\u0648"
    ],
    "name:zho_x_preferred":[
        "\u8c37\u9c81"
    ],
    "name:zho_x_variant":[
        "\u53e4\u76e7"
    ],
    "wof:name":"Gulu",
    "wof:placetype":"locality"
},
  "geometry": {"coordinates":[100.69799999999999,26.8707],"type":"Point"}
}