{
  "type": "Feature",
  "properties": {
    "gn:admin1_code":"15.0",
    "gn:asciiname":"Liujiawan",
    "gn:country_code":"CN",
    "gn:dem":1460,
    "gn:feature_class":"P",
    "gn:feature_code":"PPL",
    "gn:name":"Liujiawan",
    "gn:population":0,
    "gn:timezone":"Asia/Shanghai",
    "iso:country":"CN",
    "name:und_x_variant":[
        "\u5218\u5bb6\u6e7e"
    ],
    "wof:name":"Liujiawan",
    "wof:placetype":"locality"
},
  "geometry": {"coordinates":[107.72422,36.33635],"type":"Point"}
}