{
  "type": "Feature",
  "properties": {
    "gn:admin1_code":"5.0",
    "gn:asciiname":"Jishancun",
    "gn:country_code":"CN",
    "gn:dem":150,
    "gn:feature_class":"P",
    "gn:feature_code":"PPL",
    "gn:name":"Jishancun",
    "gn:population":0,
    "gn:timezone":"Asia/Shanghai",
    "iso:country":"CN",
    "name:zho_x_preferred":[
        "\u79ef\u5584\u6751"
    ],
    "wof:name":"Jishancun",
    "wof:placetype":"locality"
},
  "geometry": {"coordinates":[123.83488,43.71878],"type":"Point"}
}