{
  "type": "Feature",
  "properties": {
    "gn:admin1_code":"07",
    "gn:asciiname":"Jiu'an",
    "gn:country_code":"CN",
    "gn:dem":62,
    "gn:feature_class":"P",
    "gn:feature_code":"PPL",
    "gn:name":"Jiu\u2019an",
    "gn:population":0,
    "gn:timezone":"Asia/Shanghai",
    "iso:country":"CN",
    "name:und_x_variant":[
        "Jiu\u2019an"
    ],
    "name:zho_x_preferred":[
        "\u4e5d\u57b5"
    ],
    "wof:name":"Jiu'an",
    "wof:placetype":"locality"
},
  "geometry": {"coordinates":[118.13972,25.08028],"type":"Point"}
}