{
  "type": "Feature",
  "properties": {
    "gn:admin1_code":"14.0",
    "gn:asciiname":"Magong",
    "gn:country_code":"CN",
    "gn:dem":4040,
    "gn:feature_class":"P",
    "gn:feature_code":"PPL",
    "gn:name":"Magong",
    "gn:population":0,
    "gn:timezone":"Asia/Urumqi",
    "iso:country":"CN",
    "name:zho_x_preferred":[
        "\u739b\u8d21"
    ],
    "wof:name":"Magong",
    "wof:placetype":"locality"
},
  "geometry": {"coordinates":[95.11575000000001,31.27905],"type":"Point"}
}