{
  "type": "Feature",
  "properties": {
    "gn:admin1_code":"16.0",
    "gn:asciiname":"Fuliang",
    "gn:country_code":"CN",
    "gn:dem":701,
    "gn:feature_class":"P",
    "gn:feature_code":"PPL",
    "gn:name":"Fuliang",
    "gn:population":0,
    "gn:timezone":"Asia/Shanghai",
    "iso:country":"CN",
    "name:zho_x_preferred":[
        "\u798f\u826f"
    ],
    "wof:name":"Fuliang",
    "wof:placetype":"locality"
},
  "geometry": {"coordinates":[106.482,23.0901],"type":"Point"}
}