{
  "type": "Feature",
  "properties": {
    "gn:admin1_code":"5.0",
    "gn:asciiname":"Xidapo",
    "gn:country_code":"CN",
    "gn:dem":685,
    "gn:feature_class":"P",
    "gn:feature_code":"PPL",
    "gn:name":"Xidapo",
    "gn:population":0,
    "gn:timezone":"Asia/Shanghai",
    "iso:country":"CN",
    "name:und_x_variant":[
        "\u897f\u5927\u5761"
    ],
    "wof:name":"Xidapo",
    "wof:placetype":"locality"
},
  "geometry": {"coordinates":[126.0761,41.49568],"type":"Point"}
}