{
  "type": "Feature",
  "properties": {
    "gn:admin1_code":"2.0",
    "gn:asciiname":"Zhaitang",
    "gn:country_code":"CN",
    "gn:dem":153,
    "gn:feature_class":"P",
    "gn:feature_code":"PPL",
    "gn:name":"Zhaitang",
    "gn:population":0,
    "gn:timezone":"Asia/Shanghai",
    "iso:country":"CN",
    "name:zho_x_preferred":[
        "\u658b\u5802"
    ],
    "wof:name":"Zhaitang",
    "wof:placetype":"locality"
},
  "geometry": {"coordinates":[118.99387,29.65885],"type":"Point"}
}