{
  "type": "Feature",
  "properties": {
    "gn:admin1_code":"26.0",
    "gn:asciiname":"Shandongcun",
    "gn:country_code":"CN",
    "gn:dem":791,
    "gn:feature_class":"P",
    "gn:feature_code":"PPL",
    "gn:name":"Shandongcun",
    "gn:population":0,
    "gn:timezone":"Asia/Shanghai",
    "iso:country":"CN",
    "name:zho_x_preferred":[
        "\u5c71\u4e1c\u6751"
    ],
    "wof:name":"Shandongcun",
    "wof:placetype":"locality"
},
  "geometry": {"coordinates":[109.58707,35.08855],"type":"Point"}
}