{
  "type": "Feature",
  "properties": {
    "gn:admin1_code":"32.0",
    "gn:asciiname":"Wangjiagou",
    "gn:country_code":"CN",
    "gn:dem":749,
    "gn:feature_class":"P",
    "gn:feature_code":"PPL",
    "gn:name":"Wangjiagou",
    "gn:population":0,
    "gn:timezone":"Asia/Shanghai",
    "iso:country":"CN",
    "name:und_x_variant":[
        "\u6c6a\u5bb6\u6c9f"
    ],
    "wof:name":"Wangjiagou",
    "wof:placetype":"locality"
},
  "geometry": {"coordinates":[106.31665,32.27277],"type":"Point"}
}