{
  "type": "Feature",
  "properties": {
    "gn:admin1_code":"26.0",
    "gn:asciiname":"Xiaojiapobei",
    "gn:country_code":"CN",
    "gn:dem":604,
    "gn:feature_class":"P",
    "gn:feature_code":"PPL",
    "gn:name":"Xiaojiapobei",
    "gn:population":0,
    "gn:timezone":"Asia/Shanghai",
    "iso:country":"CN",
    "name:zho_x_preferred":[
        "\u8096\u5bb6\u5761\u5317"
    ],
    "wof:name":"Xiaojiapobei",
    "wof:placetype":"locality"
},
  "geometry": {"coordinates":[109.16936,34.05082],"type":"Point"}
}