{
  "type": "Feature",
  "properties": {
    "gn:admin1_code":"26.0",
    "gn:asciiname":"Xichahe",
    "gn:cc2":"CN",
    "gn:country_code":"CN",
    "gn:dem":812,
    "gn:feature_class":"P",
    "gn:feature_code":"PPL",
    "gn:name":"Xichahe",
    "gn:population":0,
    "gn:timezone":"Asia/Shanghai",
    "iso:country":"CN",
    "name:und_x_variant":[
        "Hsi-ch\u2019a-ho-chieh",
        "Hsi-p\u2019en-ho",
        "Hsi-ch\u2019a-ho",
        "Xichahe"
    ],
    "name:zho_x_preferred":[
        "\u897f\u5c94\u6cb3"
    ],
    "wof:name":"Xichahe",
    "wof:placetype":"locality"
},
  "geometry": {"coordinates":[107.96778,33.42778],"type":"Point"}
}