{
  "type": "Feature",
  "properties": {
    "gn:admin1_code":"5.0",
    "gn:asciiname":"Chengjia Weizi",
    "gn:country_code":"CN",
    "gn:dem":162,
    "gn:feature_class":"P",
    "gn:feature_code":"PPL",
    "gn:name":"Chengjia Weizi",
    "gn:population":0,
    "gn:timezone":"Asia/Shanghai",
    "iso:country":"CN",
    "name:zho_x_preferred":[
        "\u7a0b\u5bb6\u56f4\u5b50"
    ],
    "wof:name":"Chengjia Weizi",
    "wof:placetype":"locality"
},
  "geometry": {"coordinates":[125.58271000000001,45.1875],"type":"Point"}
}