{
  "type": "Feature",
  "properties": {
    "gn:admin1_code":"7.0",
    "gn:asciiname":"Zhujunshan",
    "gn:country_code":"CN",
    "gn:dem":658,
    "gn:feature_class":"P",
    "gn:feature_code":"PPL",
    "gn:name":"Zhujunshan",
    "gn:population":0,
    "gn:timezone":"Asia/Shanghai",
    "iso:country":"CN",
    "name:zho_x_preferred":[
        "\u7af9\u7b60\u5c71"
    ],
    "wof:name":"Zhujunshan",
    "wof:placetype":"locality"
},
  "geometry": {"coordinates":[116.65725999999999,25.92407],"type":"Point"}
}