{
  "type": "Feature",
  "properties": {
    "gn:admin1_code":"2.0",
    "gn:asciiname":"Lushang",
    "gn:country_code":"CN",
    "gn:dem":7,
    "gn:feature_class":"P",
    "gn:feature_code":"PPL",
    "gn:name":"Lushang",
    "gn:population":0,
    "gn:timezone":"Asia/Shanghai",
    "iso:country":"CN",
    "name:und_x_variant":[
        "\u8def\u4e0a"
    ],
    "wof:name":"Lushang",
    "wof:placetype":"locality"
},
  "geometry": {"coordinates":[120.44016000000001,30.50166],"type":"Point"}
}