{
  "type": "Feature",
  "properties": {
    "gn:admin1_code":"25",
    "gn:asciiname":"Dongxuecun",
    "gn:country_code":"CN",
    "gn:dem":26,
    "gn:feature_class":"P",
    "gn:feature_code":"PPL",
    "gn:name":"Dongxuecun",
    "gn:population":0,
    "gn:timezone":"Asia/Shanghai",
    "iso:country":"CN",
    "name:zho_x_preferred":[
        "\u4e1c\u859b\u6751"
    ],
    "wof:name":"Dongxuecun",
    "wof:placetype":"locality"
},
  "geometry": {"coordinates":[120.78100000000001,36.7066],"type":"Point"}
}