{
  "type": "Feature",
  "properties": {
    "gn:admin1_code":"9.0",
    "gn:asciiname":"Quanshangcun",
    "gn:country_code":"CN",
    "gn:dem":214,
    "gn:feature_class":"P",
    "gn:feature_code":"PPL",
    "gn:name":"Quanshangcun",
    "gn:population":0,
    "gn:timezone":"Asia/Shanghai",
    "iso:country":"CN",
    "name:zho_x_preferred":[
        "\u6cc9\u4e0a\u6751"
    ],
    "wof:name":"Quanshangcun",
    "wof:placetype":"locality"
},
  "geometry": {"coordinates":[112.8766,33.84869],"type":"Point"}
}