{
  "type": "Feature",
  "properties": {
    "gn:admin1_code":"26.0",
    "gn:asciiname":"Qiaoze Goucun",
    "gn:country_code":"CN",
    "gn:dem":1056,
    "gn:feature_class":"P",
    "gn:feature_code":"PPL",
    "gn:name":"Qiaoze Goucun",
    "gn:population":0,
    "gn:timezone":"Asia/Shanghai",
    "iso:country":"CN",
    "name:zho_x_preferred":[
        "\u6865\u5219\u6c9f\u6751"
    ],
    "wof:name":"Qiaoze Goucun",
    "wof:placetype":"locality"
},
  "geometry": {"coordinates":[109.857,37.8742],"type":"Point"}
}