{
  "type": "Feature",
  "properties": {
    "gn:admin1_code":"10",
    "gn:asciiname":"Weijiayu",
    "gn:country_code":"CN",
    "gn:dem":39,
    "gn:feature_class":"P",
    "gn:feature_code":"PPL",
    "gn:name":"Weijiayu",
    "gn:population":0,
    "gn:timezone":"Asia/Shanghai",
    "iso:country":"CN",
    "name:zho_x_preferred":[
        "\u97e6\u5bb6\u5cea"
    ],
    "wof:name":"Weijiayu",
    "wof:placetype":"locality"
},
  "geometry": {"coordinates":[117.66410999999999,40.1035],"type":"Point"}
}