{
  "type": "Feature",
  "properties": {
    "gn:admin1_code":"32.0",
    "gn:asciiname":"Eba",
    "gn:country_code":"CN",
    "gn:dem":3375,
    "gn:feature_class":"P",
    "gn:feature_code":"PPL",
    "gn:name":"Eba",
    "gn:population":0,
    "gn:timezone":"Asia/Shanghai",
    "iso:country":"CN",
    "name:ibo_x_preferred":[
        "Eba"
    ],
    "name:zho_x_preferred":[
        "\u989d\u5df4"
    ],
    "wof:name":"Eba",
    "wof:placetype":"locality"
},
  "geometry": {"coordinates":[100.14700000000001,31.4284],"type":"Point"}
}