{
  "type": "Feature",
  "properties": {
    "gn:admin1_code":"11",
    "gn:asciiname":"Luojiaqiao",
    "gn:country_code":"CN",
    "gn:dem":254,
    "gn:feature_class":"P",
    "gn:feature_code":"PPL",
    "gn:name":"Luojiaqiao",
    "gn:population":0,
    "gn:timezone":"Asia/Shanghai",
    "iso:country":"CN",
    "name:zho_x_preferred":[
        "\u7f57\u5bb6\u6865"
    ],
    "wof:name":"Luojiaqiao",
    "wof:placetype":"locality"
},
  "geometry": {"coordinates":[111.116,26.81734],"type":"Point"}
}