{
  "type": "Feature",
  "properties": {
    "gn:admin1_code":"29.0",
    "gn:asciiname":"Dengcao",
    "gn:country_code":"CN",
    "gn:dem":956,
    "gn:feature_class":"P",
    "gn:feature_code":"PPL",
    "gn:name":"Dengcao",
    "gn:population":0,
    "gn:timezone":"Asia/Shanghai",
    "iso:country":"CN",
    "name:zho_x_preferred":[
        "\u706f\u8349"
    ],
    "wof:name":"Dengcao",
    "wof:placetype":"locality"
},
  "geometry": {"coordinates":[104.11094,28.26954000000001],"type":"Point"}
}