{
  "type": "Feature",
  "properties": {
    "gn:admin1_code":"11.0",
    "gn:asciiname":"Laizhou",
    "gn:country_code":"CN",
    "gn:dem":400,
    "gn:feature_class":"P",
    "gn:feature_code":"PPL",
    "gn:name":"Laizhou",
    "gn:population":0,
    "gn:timezone":"Asia/Shanghai",
    "iso:country":"CN",
    "name:deu_x_preferred":[
        "Laizhou"
    ],
    "name:fra_x_preferred":[
        "Laizhou"
    ],
    "name:ita_x_preferred":[
        "Laizhou"
    ],
    "name:jpn_x_preferred":[
        "\u83b1\u5dde\u5e02"
    ],
    "name:kik_x_preferred":[
        "Laizhou"
    ],
    "name:kor_x_preferred":[
        "\ub77c\uc774\uc800\uc6b0\uc2dc"
    ],
    "name:mlg_x_preferred":[
        "Laizhou"
    ],
    "name:nld_x_preferred":[
        "Laizhou"
    ],
    "name:nor_x_preferred":[
        "Laizhou"
    ],
    "name:rus_x_preferred":[
        "\u041b\u0430\u0439\u0447\u0436\u043e\u0443"
    ],
    "name:swe_x_preferred":[
        "Laizhou"
    ],
    "name:urd_x_preferred":[
        "\u0644\u0627\u0626\u0632\u06c1\u0648"
    ],
    "name:vie_x_preferred":[
        "Lai Ch\u00e2u"
    ],
    "name:war_x_preferred":[
        "Laizhou"
    ],
    "name:zho_x_preferred":[
        "\u6765\u6d32"
    ],
    "name:zho_x_variant":[
        "\u83b1\u5dde\u5e02"
    ],
    "wof:name":"Laizhou",
    "wof:placetype":"locality"
},
  "geometry": {"coordinates":[109.50521999999999,28.81965],"type":"Point"}
}