{
  "type": "Feature",
  "properties": {
    "gn:admin1_code":"26.0",
    "gn:asciiname":"Sujiapo",
    "gn:country_code":"CN",
    "gn:dem":1023,
    "gn:feature_class":"P",
    "gn:feature_code":"PPL",
    "gn:name":"Sujiapo",
    "gn:population":0,
    "gn:timezone":"Asia/Shanghai",
    "iso:country":"CN",
    "name:zho_x_preferred":[
        "\u82cf\u5bb6\u5761"
    ],
    "wof:name":"Sujiapo",
    "wof:placetype":"locality"
},
  "geometry": {"coordinates":[107.67874,32.42307],"type":"Point"}
}