{
  "type": "Feature",
  "properties": {
    "gn:admin1_code":"32.0",
    "gn:asciiname":"Etiehaluo",
    "gn:country_code":"CN",
    "gn:dem":3028,
    "gn:feature_class":"P",
    "gn:feature_code":"PPL",
    "gn:name":"Etiehaluo",
    "gn:population":0,
    "gn:timezone":"Asia/Shanghai",
    "iso:country":"CN",
    "name:zho_x_preferred":[
        "\u989d\u94c1\u54c8\u6d1b"
    ],
    "wof:name":"Etiehaluo",
    "wof:placetype":"locality"
},
  "geometry": {"coordinates":[102.783,28.5198],"type":"Point"}
}