{
  "type": "Feature",
  "properties": {
    "gn:admin1_code":"32.0",
    "gn:asciiname":"Lengba",
    "gn:country_code":"CN",
    "gn:dem":3902,
    "gn:feature_class":"P",
    "gn:feature_code":"PPL",
    "gn:name":"Lengba",
    "gn:population":0,
    "gn:timezone":"Asia/Shanghai",
    "iso:country":"CN",
    "name:zho_x_preferred":[
        "\u51b7\u5df4"
    ],
    "wof:name":"Lengba",
    "wof:placetype":"locality"
},
  "geometry": {"coordinates":[100.351,29.0741],"type":"Point"}
}