{
  "type": "Feature",
  "properties": {
    "gn:admin1_code":"29.0",
    "gn:asciiname":"Laopalian Xiazhai",
    "gn:country_code":"CN",
    "gn:dem":1465,
    "gn:feature_class":"P",
    "gn:feature_code":"PPL",
    "gn:name":"Laopalian Xiazhai",
    "gn:population":0,
    "gn:timezone":"Asia/Shanghai",
    "iso:country":"CN",
    "name:zho_x_preferred":[
        "\u8001\u6015\u83b2\u4e0b\u5be8"
    ],
    "wof:name":"Laopalian Xiazhai",
    "wof:placetype":"locality"
},
  "geometry": {"coordinates":[98.3181,24.1995],"type":"Point"}
}