{
  "type": "Feature",
  "properties": {
    "gn:admin1_code":"29.0",
    "gn:asciiname":"Lishiyao",
    "gn:country_code":"CN",
    "gn:dem":1545,
    "gn:feature_class":"P",
    "gn:feature_code":"PPL",
    "gn:name":"Lishiyao",
    "gn:population":0,
    "gn:timezone":"Asia/Shanghai",
    "iso:country":"CN",
    "name:und_x_variant":[
        "Lishime",
        "Lishiyao"
    ],
    "name:zho_x_preferred":[
        "\u529b\u77f3\u4e48"
    ],
    "wof:name":"Lishiyao",
    "wof:placetype":"locality"
},
  "geometry": {"coordinates":[100.468,25.0988],"type":"Point"}
}