{
  "type": "Feature",
  "properties": {
    "gn:admin1_code":"7.0",
    "gn:asciiname":"Shangsifang",
    "gn:country_code":"CN",
    "gn:dem":651,
    "gn:feature_class":"P",
    "gn:feature_code":"PPL",
    "gn:name":"Shangsifang",
    "gn:population":0,
    "gn:timezone":"Asia/Shanghai",
    "iso:country":"CN",
    "name:zho_x_preferred":[
        "\u4e0a\u56db\u574a"
    ],
    "wof:name":"Shangsifang",
    "wof:placetype":"locality"
},
  "geometry": {"coordinates":[117.37629,27.87923],"type":"Point"}
}