{
  "type": "Feature",
  "properties": {
    "gn:admin1_code":"29.0",
    "gn:asciiname":"Mengjia Dazhai",
    "gn:country_code":"CN",
    "gn:dem":1075,
    "gn:feature_class":"P",
    "gn:feature_code":"PPL",
    "gn:name":"Mengjia Dazhai",
    "gn:population":0,
    "gn:timezone":"Asia/Shanghai",
    "iso:country":"CN",
    "name:zho_x_preferred":[
        "\u52d0\u621b\u5927\u5be8"
    ],
    "wof:name":"Mengjia Dazhai",
    "wof:placetype":"locality"
},
  "geometry": {"coordinates":[100.386,23.4187],"type":"Point"}
}