{
  "type": "Feature",
  "properties": {
    "gn:admin1_code":"29",
    "gn:asciiname":"Manghuai",
    "gn:country_code":"CN",
    "gn:dem":1182,
    "gn:feature_class":"P",
    "gn:feature_code":"PPL",
    "gn:name":"Manghuai",
    "gn:population":0,
    "gn:timezone":"Asia/Shanghai",
    "iso:country":"CN",
    "name:zho_x_preferred":[
        "\u5fd9\u6000"
    ],
    "wof:name":"Manghuai",
    "wof:placetype":"locality"
},
  "geometry": {"coordinates":[100.471,24.5262],"type":"Point"}
}