{
  "type": "Feature",
  "properties": {
    "gn:admin1_code":"19.0",
    "gn:asciiname":"Qiantun",
    "gn:country_code":"CN",
    "gn:dem":72,
    "gn:feature_class":"P",
    "gn:feature_code":"PPL",
    "gn:name":"Qiantun",
    "gn:population":0,
    "gn:timezone":"Asia/Shanghai",
    "iso:country":"CN",
    "name:und_x_variant":[
        "\u524d\u5c6f"
    ],
    "name:zho_x_preferred":[
        "\u524d\u5c6f"
    ],
    "wof:name":"Qiantun",
    "wof:placetype":"locality"
},
  "geometry": {"coordinates":[123.59811999999999,42.06855],"type":"Point"}
}