{
  "type": "Feature",
  "properties": {
    "gn:admin1_code":"30.0",
    "gn:asciiname":"Gaomingcun",
    "gn:country_code":"CN",
    "gn:dem":27,
    "gn:feature_class":"P",
    "gn:feature_code":"PPL",
    "gn:name":"Gaomingcun",
    "gn:population":0,
    "gn:timezone":"Asia/Shanghai",
    "iso:country":"CN",
    "name:zho_x_preferred":[
        "\u9ad8\u660e\u6751"
    ],
    "wof:name":"Gaomingcun",
    "wof:placetype":"locality"
},
  "geometry": {"coordinates":[116.23678999999998,23.23163],"type":"Point"}
}