{
  "type": "Feature",
  "properties": {
    "gn:admin1_code":"19.0",
    "gn:asciiname":"Wangheshanggou",
    "gn:country_code":"CN",
    "gn:dem":307,
    "gn:feature_class":"P",
    "gn:feature_code":"PPL",
    "gn:name":"Wangheshanggou",
    "gn:population":0,
    "gn:timezone":"Asia/Shanghai",
    "iso:country":"CN",
    "name:und_x_variant":[
        "\u738b\u548c\u5c1a\u6c9f"
    ],
    "name:zho_x_preferred":[
        "\u738b\u548c\u5c1a\u6c9f"
    ],
    "wof:name":"Wangheshanggou",
    "wof:placetype":"locality"
},
  "geometry": {"coordinates":[121.22190000000001,41.85276],"type":"Point"}
}