{
  "type": "Feature",
  "properties": {
    "gn:admin1_code":"12.0",
    "gn:asciiname":"Zhoujiakou",
    "gn:country_code":"CN",
    "gn:dem":30,
    "gn:feature_class":"P",
    "gn:feature_code":"PPL",
    "gn:name":"Zhoujiakou",
    "gn:population":0,
    "gn:timezone":"Asia/Shanghai",
    "iso:country":"CN",
    "name:zho_x_preferred":[
        "\u5468\u5bb6\u53e3"
    ],
    "wof:name":"Zhoujiakou",
    "wof:placetype":"locality"
},
  "geometry": {"coordinates":[113.39313,30.52609],"type":"Point"}
}