{
  "type": "Feature",
  "properties": {
    "gn:admin1_code":"32.0",
    "gn:asciiname":"Gongqiaowan",
    "gn:country_code":"CN",
    "gn:dem":1005,
    "gn:feature_class":"P",
    "gn:feature_code":"PPL",
    "gn:name":"Gongqiaowan",
    "gn:population":0,
    "gn:timezone":"Asia/Shanghai",
    "iso:country":"CN",
    "name:zho_x_preferred":[
        "\u62f1\u6865\u6e7e"
    ],
    "wof:name":"Gongqiaowan",
    "wof:placetype":"locality"
},
  "geometry": {"coordinates":[103.63052999999999,28.82166],"type":"Point"}
}