{
  "type": "Feature",
  "properties": {
    "gn:admin1_code":"14",
    "gn:asciiname":"Laduo",
    "gn:country_code":"CN",
    "gn:dem":4771,
    "gn:feature_class":"P",
    "gn:feature_code":"PPL",
    "gn:name":"Laduo",
    "gn:population":0,
    "gn:timezone":"Asia/Urumqi",
    "iso:country":"CN",
    "name:zho_x_preferred":[
        "\u62c9\u593a"
    ],
    "wof:name":"Laduo",
    "wof:placetype":"locality"
},
  "geometry": {"coordinates":[88.7304,30.679],"type":"Point"}
}