{
  "type": "Feature",
  "properties": {
    "gn:admin1_code":"16.0",
    "gn:asciiname":"Ejing",
    "gn:country_code":"CN",
    "gn:dem":96,
    "gn:feature_class":"P",
    "gn:feature_code":"PPL",
    "gn:name":"Ejing",
    "gn:population":0,
    "gn:timezone":"Asia/Shanghai",
    "iso:country":"CN",
    "name:zho_x_preferred":[
        "\u9e45\u666f"
    ],
    "wof:name":"Ejing",
    "wof:placetype":"locality"
},
  "geometry": {"coordinates":[109.78700000000001,24.1154],"type":"Point"}
}