{
  "type": "Feature",
  "properties": {
    "gn:admin1_code":"4.0",
    "gn:asciiname":"Dongfang Yizu",
    "gn:country_code":"CN",
    "gn:dem":5,
    "gn:feature_class":"P",
    "gn:feature_code":"PPL",
    "gn:name":"Dongfang Yizu",
    "gn:population":0,
    "gn:timezone":"Asia/Shanghai",
    "iso:country":"CN",
    "name:und_x_variant":[
        "\u4e1c\u65b9\u4e00\u7ec4"
    ],
    "name:zho_x_preferred":[
        "\u4e1c\u65b9\u4e00\u7ec4"
    ],
    "wof:name":"Dongfang Yizu",
    "wof:placetype":"locality"
},
  "geometry": {"coordinates":[120.77952000000001,32.92155],"type":"Point"}
}