{
  "type": "Feature",
  "properties": {
    "gn:admin1_code":"19.0",
    "gn:asciiname":"Shiqiaogangcun",
    "gn:country_code":"CN",
    "gn:dem":15,
    "gn:feature_class":"P",
    "gn:feature_code":"PPL",
    "gn:name":"Shiqiaogangcun",
    "gn:population":0,
    "gn:timezone":"Asia/Shanghai",
    "iso:country":"CN",
    "name:zho_x_preferred":[
        "\u77f3\u6865\u5c97\u6751"
    ],
    "wof:name":"Shiqiaogangcun",
    "wof:placetype":"locality"
},
  "geometry": {"coordinates":[124.15885,39.96308],"type":"Point"}
}