{
  "type": "Feature",
  "properties": {
    "gn:admin1_code":"19.0",
    "gn:asciiname":"Majiayao",
    "gn:country_code":"CN",
    "gn:dem":137,
    "gn:feature_class":"P",
    "gn:feature_code":"PPL",
    "gn:name":"Majiayao",
    "gn:population":0,
    "gn:timezone":"Asia/Shanghai",
    "iso:country":"CN",
    "name:zho_x_preferred":[
        "\u9a6c\u5bb6\u7a91"
    ],
    "wof:name":"Majiayao",
    "wof:placetype":"locality"
},
  "geometry": {"coordinates":[122.667,39.8817],"type":"Point"}
}