{
  "type": "Feature",
  "properties": {
    "gn:admin1_code":"14.0",
    "gn:asciiname":"Muzhuangmei",
    "gn:country_code":"CN",
    "gn:dem":3890,
    "gn:feature_class":"P",
    "gn:feature_code":"PPL",
    "gn:name":"Muzhuangmei",
    "gn:population":0,
    "gn:timezone":"Asia/Urumqi",
    "iso:country":"CN",
    "name:zho_x_preferred":[
        "\u6728\u58ee\u7f8e"
    ],
    "wof:name":"Muzhuangmei",
    "wof:placetype":"locality"
},
  "geometry": {"coordinates":[98.16888,31.86877],"type":"Point"}
}