{
  "type": "Feature",
  "properties": {
    "gn:admin1_code":"26.0",
    "gn:asciiname":"Caoyuanzhan",
    "gn:country_code":"CN",
    "gn:dem":1251,
    "gn:feature_class":"P",
    "gn:feature_code":"PPL",
    "gn:name":"Caoyuanzhan",
    "gn:population":0,
    "gn:timezone":"Asia/Shanghai",
    "iso:country":"CN",
    "name:zho_x_preferred":[
        "\u8349\u539f\u7ad9"
    ],
    "wof:name":"Caoyuanzhan",
    "wof:placetype":"locality"
},
  "geometry": {"coordinates":[109.34023999999999,38.54832],"type":"Point"}
}