{
  "type": "Feature",
  "properties": {
    "gn:admin1_code":"9.0",
    "gn:asciiname":"Shizhai",
    "gn:country_code":"CN",
    "gn:dem":45,
    "gn:feature_class":"P",
    "gn:feature_code":"PPL",
    "gn:name":"Shizhai",
    "gn:population":0,
    "gn:timezone":"Asia/Shanghai",
    "iso:country":"CN",
    "name:zho_x_preferred":[
        "\u5e08\u5be8"
    ],
    "wof:name":"Shizhai",
    "wof:placetype":"locality"
},
  "geometry": {"coordinates":[115.04423,33.3737],"type":"Point"}
}