{
  "type": "Feature",
  "properties": {
    "gn:admin1_code":"29.0",
    "gn:asciiname":"Laoyingpan",
    "gn:country_code":"CN",
    "gn:dem":1862,
    "gn:feature_class":"P",
    "gn:feature_code":"PPL",
    "gn:name":"Laoyingpan",
    "gn:population":0,
    "gn:timezone":"Asia/Shanghai",
    "iso:country":"CN",
    "name:und_x_variant":[
        "\u8001\u8425\u76d8"
    ],
    "wof:name":"Laoyingpan",
    "wof:placetype":"locality"
},
  "geometry": {"coordinates":[103.49209,27.23976],"type":"Point"}
}