{
  "type": "Feature",
  "properties": {
    "gn:admin1_code":"32.0",
    "gn:asciiname":"Mengzigou",
    "gn:country_code":"CN",
    "gn:dem":277,
    "gn:feature_class":"P",
    "gn:feature_code":"PPL",
    "gn:name":"Mengzigou",
    "gn:population":0,
    "gn:timezone":"Asia/Shanghai",
    "iso:country":"CN",
    "name:zho_x_preferred":[
        "\u6aac\u5b50\u6c9f"
    ],
    "wof:name":"Mengzigou",
    "wof:placetype":"locality"
},
  "geometry": {"coordinates":[105.60417,30.1915],"type":"Point"}
}