{
  "type": "Feature",
  "properties": {
    "gn:admin1_code":"04",
    "gn:asciiname":"Ganlu",
    "gn:country_code":"CN",
    "gn:dem":11,
    "gn:feature_class":"P",
    "gn:feature_code":"PPL",
    "gn:name":"Ganlu",
    "gn:population":0,
    "gn:timezone":"Asia/Shanghai",
    "iso:country":"CN",
    "name:deu_x_preferred":[
        "Ganlu"
    ],
    "name:und_x_variant":[
        "Kan-lu-chen"
    ],
    "name:zho_x_preferred":[
        "\u7518\u9732"
    ],
    "wof:name":"Ganlu",
    "wof:placetype":"locality"
},
  "geometry": {"coordinates":[120.57425000000001,31.54632],"type":"Point"}
}