{
  "type": "Feature",
  "properties": {
    "gn:admin1_code":"19.0",
    "gn:asciiname":"Fujia Buzi",
    "gn:country_code":"CN",
    "gn:dem":334,
    "gn:feature_class":"P",
    "gn:feature_code":"PPL",
    "gn:name":"Fujia Buzi",
    "gn:population":0,
    "gn:timezone":"Asia/Shanghai",
    "iso:country":"CN",
    "name:zho_x_preferred":[
        "\u5085\u5bb6\u5821\u5b50"
    ],
    "wof:name":"Fujia Buzi",
    "wof:placetype":"locality"
},
  "geometry": {"coordinates":[123.01300000000001,40.4319],"type":"Point"}
}