{
  "type": "Feature",
  "properties": {
    "gn:admin1_code":"3.0",
    "gn:asciiname":"Zhoujiabian",
    "gn:country_code":"CN",
    "gn:dem":58,
    "gn:feature_class":"P",
    "gn:feature_code":"PPL",
    "gn:name":"Zhoujiabian",
    "gn:population":0,
    "gn:timezone":"Asia/Shanghai",
    "iso:country":"CN",
    "name:und_x_variant":[
        "\u5468\u5bb6\u8fb9"
    ],
    "wof:name":"Zhoujiabian",
    "wof:placetype":"locality"
},
  "geometry": {"coordinates":[115.10387,27.26101],"type":"Point"}
}