{
  "type": "Feature",
  "properties": {
    "gn:admin1_code":"4.0",
    "gn:asciiname":"Shenjiazhai",
    "gn:country_code":"CN",
    "gn:dem":23,
    "gn:feature_class":"P",
    "gn:feature_code":"PPL",
    "gn:name":"Shenjiazhai",
    "gn:population":0,
    "gn:timezone":"Asia/Shanghai",
    "iso:country":"CN",
    "name:zho_x_preferred":[
        "\u6c88\u5bb6\u5b85"
    ],
    "wof:name":"Shenjiazhai",
    "wof:placetype":"locality"
},
  "geometry": {"coordinates":[119.34388,31.34631],"type":"Point"}
}