{
  "type": "Feature",
  "properties": {
    "gn:admin1_code":"3.0",
    "gn:asciiname":"Dagui Chenjia",
    "gn:country_code":"CN",
    "gn:dem":83,
    "gn:feature_class":"P",
    "gn:feature_code":"PPL",
    "gn:name":"Dagui Chenjia",
    "gn:population":0,
    "gn:timezone":"Asia/Shanghai",
    "iso:country":"CN",
    "name:und_x_variant":[
        "\u5927\u6842\u9648\u5bb6"
    ],
    "wof:name":"Dagui Chenjia",
    "wof:placetype":"locality"
},
  "geometry": {"coordinates":[116.78097,29.93645],"type":"Point"}
}