{
  "type": "Feature",
  "properties": {
    "gn:admin1_code":"02",
    "gn:asciiname":"Shihuang",
    "gn:country_code":"CN",
    "gn:dem":42,
    "gn:feature_class":"P",
    "gn:feature_code":"PPLA4",
    "gn:name":"Shihuang",
    "gn:population":0,
    "gn:timezone":"Asia/Shanghai",
    "iso:country":"CN",
    "name:und_x_variant":[
        "Shih-huang",
        "Shih-huang-shih",
        "Shihuang",
        "Shihuang Zhen"
    ],
    "name:zho_x_preferred":[
        "\u77f3\u749c"
    ],
    "name:zho_x_variant":[
        "\u77f3\u749c\u9547"
    ],
    "wof:name":"Shihuang",
    "wof:placetype":"locality"
},
  "geometry": {"coordinates":[120.65236000000002,29.53934000000001],"type":"Point"}
}