{
  "type": "Feature",
  "properties": {
    "gn:admin1_code":"3",
    "gn:asciiname":"Chunhe",
    "gn:country_code":"CN",
    "gn:dem":188,
    "gn:feature_class":"P",
    "gn:feature_code":"PPL",
    "gn:name":"Chunhe",
    "gn:population":0,
    "gn:timezone":"Asia/Shanghai",
    "iso:country":"CN",
    "name:zho_x_preferred":[
        "\u6625\u548c"
    ],
    "wof:name":"Chunhe",
    "wof:placetype":"locality"
},
  "geometry": {"coordinates":[114.48095000000001,26.70834],"type":"Point"}
}