{
  "type": "Feature",
  "properties": {
    "gn:admin1_code":"9.0",
    "gn:asciiname":"Dawangjiashan",
    "gn:country_code":"CN",
    "gn:dem":391,
    "gn:feature_class":"P",
    "gn:feature_code":"PPL",
    "gn:name":"Dawangjiashan",
    "gn:population":0,
    "gn:timezone":"Asia/Shanghai",
    "iso:country":"CN",
    "name:zho_x_preferred":[
        "\u5927\u6c6a\u5bb6\u5c71"
    ],
    "wof:name":"Dawangjiashan",
    "wof:placetype":"locality"
},
  "geometry": {"coordinates":[114.66453,31.63279],"type":"Point"}
}