{
  "type": "Feature",
  "properties": {
    "gn:admin1_code":"30.0",
    "gn:asciiname":"Xiuren",
    "gn:country_code":"CN",
    "gn:dem":117,
    "gn:feature_class":"P",
    "gn:feature_code":"PPL",
    "gn:name":"Xiuren",
    "gn:population":0,
    "gn:timezone":"Asia/Shanghai",
    "iso:country":"CN",
    "name:zho_x_preferred":[
        "\u4fee\u4ec1"
    ],
    "wof:name":"Xiuren",
    "wof:placetype":"locality"
},
  "geometry": {"coordinates":[114.25178,25.09363],"type":"Point"}
}