{
  "type": "Feature",
  "properties": {
    "gn:admin1_code":"3.0",
    "gn:asciiname":"Shinaoli",
    "gn:country_code":"CN",
    "gn:dem":311,
    "gn:feature_class":"P",
    "gn:feature_code":"PPL",
    "gn:name":"Shinaoli",
    "gn:population":0,
    "gn:timezone":"Asia/Shanghai",
    "iso:country":"CN",
    "name:und_x_variant":[
        "\u77f3\u57b4\u91cc"
    ],
    "wof:name":"Shinaoli",
    "wof:placetype":"locality"
},
  "geometry": {"coordinates":[114.81847,28.85699],"type":"Point"}
}