{
  "type": "Feature",
  "properties": {
    "gn:admin1_code":"4.0",
    "gn:asciiname":"Xiao'aocun",
    "gn:country_code":"CN",
    "gn:dem":2,
    "gn:feature_class":"P",
    "gn:feature_code":"PPL",
    "gn:name":"Xiao\u2019aocun",
    "gn:population":0,
    "gn:timezone":"Asia/Shanghai",
    "iso:country":"CN",
    "name:und_x_variant":[
        "Xiao\u2019aocun"
    ],
    "name:zho_x_preferred":[
        "\u8096\u5773\u6751"
    ],
    "wof:name":"Xiao'aocun",
    "wof:placetype":"locality"
},
  "geometry": {"coordinates":[120.39490000000001,32.99652],"type":"Point"}
}