{
  "type": "Feature",
  "properties": {
    "gn:admin1_code":"04",
    "gn:asciiname":"Huitongcun",
    "gn:country_code":"CN",
    "gn:dem":7,
    "gn:feature_class":"P",
    "gn:feature_code":"PPL",
    "gn:name":"Huitongcun",
    "gn:population":0,
    "gn:timezone":"Asia/Shanghai",
    "iso:country":"CN",
    "name:und_x_variant":[
        "Hui-t\u2019ung-chen",
        "Huitongzhen",
        "Huitong",
        "\u6c47\u901a",
        "Huitongcun"
    ],
    "name:zho_x_preferred":[
        "\u6c47\u901a\u9547"
    ],
    "name:zho_x_variant":[
        "\u6c47\u901a\u6751"
    ],
    "wof:name":"Huitongcun",
    "wof:placetype":"locality"
},
  "geometry": {"coordinates":[121.13500000000001,31.9774],"type":"Point"}
}