{
  "type": "Feature",
  "properties": {
    "gn:admin1_code":"9.0",
    "gn:asciiname":"Shainongshan",
    "gn:country_code":"CN",
    "gn:dem":266,
    "gn:feature_class":"P",
    "gn:feature_code":"PPL",
    "gn:name":"Shainongshan",
    "gn:population":0,
    "gn:timezone":"Asia/Shanghai",
    "iso:country":"CN",
    "name:und_x_variant":[
        "\u6652\u519c\u5c71",
        "Shainongshan"
    ],
    "wof:name":"Shainongshan",
    "wof:placetype":"locality"
},
  "geometry": {"coordinates":[112.83893999999999,33.62222],"type":"Point"}
}