{
  "type": "Feature",
  "properties": {
    "gn:admin1_code":"7",
    "gn:asciiname":"Gongci",
    "gn:country_code":"CN",
    "gn:dem":877,
    "gn:feature_class":"P",
    "gn:feature_code":"PPL",
    "gn:name":"Gongci",
    "gn:population":0,
    "gn:timezone":"Asia/Shanghai",
    "iso:country":"CN",
    "name:zho_x_preferred":[
        "\u516c\u7960"
    ],
    "wof:name":"Gongci",
    "wof:placetype":"locality"
},
  "geometry": {"coordinates":[117.1341,24.95696],"type":"Point"}
}