{
  "type": "Feature",
  "properties": {
    "gn:admin1_code":"08",
    "gn:asciiname":"Wang-chia-fen-fang",
    "gn:country_code":"CN",
    "gn:dem":267,
    "gn:feature_class":"P",
    "gn:feature_code":"PPL",
    "gn:name":"Wang-chia-fen-fang",
    "gn:population":0,
    "gn:timezone":"Asia/Shanghai",
    "iso:country":"CN",
    "wof:name":"Wang-chia-fen-fang",
    "wof:placetype":"locality"
},
  "geometry": {"coordinates":[126.37389,48.06806],"type":"Point"}
}