{
  "type": "Feature",
  "properties": {
    "gn:admin1_code":"24.0",
    "gn:asciiname":"Qizishan",
    "gn:country_code":"CN",
    "gn:dem":1006,
    "gn:feature_class":"P",
    "gn:feature_code":"PPL",
    "gn:name":"Qizishan",
    "gn:population":0,
    "gn:timezone":"Asia/Shanghai",
    "iso:country":"CN",
    "name:zho_x_preferred":[
        "\u68cb\u5b50\u5c71"
    ],
    "wof:name":"Qizishan",
    "wof:placetype":"locality"
},
  "geometry": {"coordinates":[112.59054,38.03773],"type":"Point"}
}