{
  "type": "Feature",
  "properties": {
    "gn:admin1_code":"32.0",
    "gn:asciiname":"Yekebaga",
    "gn:country_code":"CN",
    "gn:dem":2642,
    "gn:feature_class":"P",
    "gn:feature_code":"PPL",
    "gn:name":"Yekebaga",
    "gn:population":0,
    "gn:timezone":"Asia/Shanghai",
    "iso:country":"CN",
    "name:zho_x_preferred":[
        "\u4e5f\u514b\u516b\u560e"
    ],
    "wof:name":"Yekebaga",
    "wof:placetype":"locality"
},
  "geometry": {"coordinates":[102.43714,28.16459],"type":"Point"}
}