{
  "type": "Feature",
  "properties": {
    "gn:admin1_code":"29.0",
    "gn:asciiname":"Dalang",
    "gn:country_code":"CN",
    "gn:dem":1585,
    "gn:feature_class":"P",
    "gn:feature_code":"PPL",
    "gn:name":"Dalang",
    "gn:population":0,
    "gn:timezone":"Asia/Shanghai",
    "iso:country":"CN",
    "name:zho_x_preferred":[
        "\u5927\u6994"
    ],
    "wof:name":"Dalang",
    "wof:placetype":"locality"
},
  "geometry": {"coordinates":[104.446,23.9162],"type":"Point"}
}