{
  "type": "Feature",
  "properties": {
    "gn:admin1_code":"15.0",
    "gn:asciiname":"Wolongshi",
    "gn:country_code":"CN",
    "gn:dem":1648,
    "gn:feature_class":"P",
    "gn:feature_code":"PPL",
    "gn:name":"Wolongshi",
    "gn:population":0,
    "gn:timezone":"Asia/Shanghai",
    "iso:country":"CN",
    "name:und_x_variant":[
        "\u5367\u9f99\u77f3"
    ],
    "wof:name":"Wolongshi",
    "wof:placetype":"locality"
},
  "geometry": {"coordinates":[105.61579999999999,33.94018],"type":"Point"}
}