{
  "type": "Feature",
  "properties": {
    "gn:admin1_code":"32.0",
    "gn:asciiname":"Jinyujing",
    "gn:country_code":"CN",
    "gn:dem":347,
    "gn:feature_class":"P",
    "gn:feature_code":"PPL",
    "gn:name":"Jinyujing",
    "gn:population":0,
    "gn:timezone":"Asia/Shanghai",
    "iso:country":"CN",
    "name:zho_x_preferred":[
        "\u91d1\u9c7c\u4e95"
    ],
    "wof:name":"Jinyujing",
    "wof:placetype":"locality"
},
  "geometry": {"coordinates":[104.63411000000001,28.88276],"type":"Point"}
}