{
  "type": "Feature",
  "properties": {
    "gn:admin1_code":"10.0",
    "gn:asciiname":"Shangnianzigou",
    "gn:country_code":"CN",
    "gn:dem":1083,
    "gn:feature_class":"P",
    "gn:feature_code":"PPL",
    "gn:name":"Shangnianzigou",
    "gn:population":0,
    "gn:timezone":"Asia/Shanghai",
    "iso:country":"CN",
    "name:zho_x_preferred":[
        "\u4e0a\u78be\u5b50\u6c9f"
    ],
    "wof:name":"Shangnianzigou",
    "wof:placetype":"locality"
},
  "geometry": {"coordinates":[114.89422,39.47245],"type":"Point"}
}