{
  "type": "Feature",
  "properties": {
    "gn:admin1_code":"15.0",
    "gn:asciiname":"Huashishan",
    "gn:country_code":"CN",
    "gn:dem":1742,
    "gn:feature_class":"P",
    "gn:feature_code":"PPL",
    "gn:name":"Huashishan",
    "gn:population":0,
    "gn:timezone":"Asia/Shanghai",
    "iso:country":"CN",
    "name:zho_x_preferred":[
        "\u82b1\u77f3\u5c71"
    ],
    "wof:name":"Huashishan",
    "wof:placetype":"locality"
},
  "geometry": {"coordinates":[106.22499999999999,34.3302],"type":"Point"}
}