{
  "type": "Feature",
  "properties": {
    "gn:admin1_code":"9.0",
    "gn:asciiname":"Hecun",
    "gn:country_code":"CN",
    "gn:dem":539,
    "gn:feature_class":"P",
    "gn:feature_code":"PPL",
    "gn:name":"Hecun",
    "gn:population":0,
    "gn:timezone":"Asia/Shanghai",
    "iso:country":"CN",
    "name:ceb_x_preferred":[
        "Hecun"
    ],
    "name:swe_x_preferred":[
        "Hecun"
    ],
    "name:zho_x_preferred":[
        "\u4f55\u6751"
    ],
    "wof:name":"Hecun",
    "wof:placetype":"locality"
},
  "geometry": {"coordinates":[111.71456999999999,34.00924000000001],"type":"Point"}
}