{
  "type": "Feature",
  "properties": {
    "gn:admin1_code":"33.0",
    "gn:asciiname":"Yongyi",
    "gn:country_code":"CN",
    "gn:dem":272,
    "gn:feature_class":"P",
    "gn:feature_code":"PPL",
    "gn:name":"Yongyi",
    "gn:population":0,
    "gn:timezone":"Asia/Shanghai",
    "iso:country":"CN",
    "name:zho_x_preferred":[
        "\u6c38\u4e49"
    ],
    "wof:name":"Yongyi",
    "wof:placetype":"locality"
},
  "geometry": {"coordinates":[107.46764,29.95759],"type":"Point"}
}