{
  "type": "Feature",
  "properties": {
    "gn:admin1_code":"11",
    "gn:asciiname":"Haishengyuan",
    "gn:country_code":"CN",
    "gn:dem":113,
    "gn:feature_class":"P",
    "gn:feature_code":"PPL",
    "gn:name":"Haishengyuan",
    "gn:population":0,
    "gn:timezone":"Asia/Shanghai",
    "iso:country":"CN",
    "name:zho_x_preferred":[
        "\u6d77\u751f\u9662"
    ],
    "wof:name":"Haishengyuan",
    "wof:placetype":"locality"
},
  "geometry": {"coordinates":[112.08233,26.70391],"type":"Point"}
}