{
  "type": "Feature",
  "properties": {
    "gn:admin1_code":"1.0",
    "gn:asciiname":"Xiaoxuzhuangcun",
    "gn:country_code":"CN",
    "gn:dem":30,
    "gn:feature_class":"P",
    "gn:feature_code":"PPL",
    "gn:name":"Xiaoxuzhuangcun",
    "gn:population":0,
    "gn:timezone":"Asia/Shanghai",
    "iso:country":"CN",
    "name:zho_x_preferred":[
        "\u5c0f\u8bb8\u5e84\u6751"
    ],
    "wof:name":"Xiaoxuzhuangcun",
    "wof:placetype":"locality"
},
  "geometry": {"coordinates":[115.96823000000001,32.6228],"type":"Point"}
}