{
  "type": "Feature",
  "properties": {
    "gn:admin1_code":"30.0",
    "gn:asciiname":"Heshuidian",
    "gn:country_code":"CN",
    "gn:dem":51,
    "gn:feature_class":"P",
    "gn:feature_code":"PPL",
    "gn:name":"Heshuidian",
    "gn:population":0,
    "gn:timezone":"Asia/Shanghai",
    "iso:country":"CN",
    "name:zho_x_preferred":[
        "\u5408\u6c34\u5e97"
    ],
    "wof:name":"Heshuidian",
    "wof:placetype":"locality"
},
  "geometry": {"coordinates":[113.94449,23.43128],"type":"Point"}
}