{
  "type": "Feature",
  "properties": {
    "gn:admin1_code":"19.0",
    "gn:asciiname":"Meiyaoshanqian",
    "gn:country_code":"CN",
    "gn:dem":361,
    "gn:feature_class":"P",
    "gn:feature_code":"PPL",
    "gn:name":"Meiyaoshanqian",
    "gn:population":0,
    "gn:timezone":"Asia/Shanghai",
    "iso:country":"CN",
    "name:und_x_variant":[
        "\u7164\u7a91\u5c71\u524d"
    ],
    "name:zho_x_preferred":[
        "\u7164\u7a91\u5c71\u524d"
    ],
    "wof:name":"Meiyaoshanqian",
    "wof:placetype":"locality"
},
  "geometry": {"coordinates":[119.89561999999999,41.36945],"type":"Point"}
}