{
  "type": "Feature",
  "properties": {
    "gn:admin1_code":"26.0",
    "gn:asciiname":"Miaogoucun",
    "gn:country_code":"CN",
    "gn:dem":919,
    "gn:feature_class":"P",
    "gn:feature_code":"PPL",
    "gn:name":"Miaogoucun",
    "gn:population":0,
    "gn:timezone":"Asia/Shanghai",
    "iso:country":"CN",
    "name:zho_x_preferred":[
        "\u5e99\u6c9f\u6751"
    ],
    "wof:name":"Miaogoucun",
    "wof:placetype":"locality"
},
  "geometry": {"coordinates":[108.22477000000001,33.34006],"type":"Point"}
}