{
  "type": "Feature",
  "properties": {
    "gn:admin1_code":"14.0",
    "gn:asciiname":"Xiema",
    "gn:country_code":"CN",
    "gn:dem":4490,
    "gn:feature_class":"P",
    "gn:feature_code":"PPLF",
    "gn:name":"Xiema",
    "gn:population":0,
    "gn:timezone":"Asia/Urumqi",
    "iso:country":"CN",
    "name:bod_x_preferred":[
        "X\u00eama"
    ],
    "name:und_x_variant":[
        "Nalongda"
    ],
    "name:zho_x_preferred":[
        "\u534f\u9a6c"
    ],
    "name:zho_x_variant":[
        "\u90a3\u9f99\u8fbe"
    ],
    "wof:name":"Xiema",
    "wof:placetype":"locality"
},
  "geometry": {"coordinates":[96.37259,31.04779000000001],"type":"Point"}
}