{
  "type": "Feature",
  "properties": {
    "gn:admin1_code":"9.0",
    "gn:asciiname":"Gaolaozhuang",
    "gn:country_code":"CN",
    "gn:dem":106,
    "gn:feature_class":"P",
    "gn:feature_code":"PPL",
    "gn:name":"Gaolaozhuang",
    "gn:population":0,
    "gn:timezone":"Asia/Shanghai",
    "iso:country":"CN",
    "name:zho_x_preferred":[
        "\u9ad8\u8001\u5e84"
    ],
    "wof:name":"Gaolaozhuang",
    "wof:placetype":"locality"
},
  "geometry": {"coordinates":[113.92196,32.20515],"type":"Point"}
}