{
  "type": "Feature",
  "properties": {
    "gn:admin1_code":"25.0",
    "gn:asciiname":"Shanliwujiacun",
    "gn:country_code":"CN",
    "gn:dem":144,
    "gn:feature_class":"P",
    "gn:feature_code":"PPL",
    "gn:name":"Shanliwujiacun",
    "gn:population":0,
    "gn:timezone":"Asia/Shanghai",
    "iso:country":"CN",
    "name:zho_x_preferred":[
        "\u5c71\u91cc\u5434\u5bb6\u6751"
    ],
    "wof:name":"Shanliwujiacun",
    "wof:placetype":"locality"
},
  "geometry": {"coordinates":[120.24782999999999,37.05523],"type":"Point"}
}