{
  "type": "Feature",
  "properties": {
    "gn:admin1_code":"26.0",
    "gn:asciiname":"Shijiagou",
    "gn:country_code":"CN",
    "gn:dem":1106,
    "gn:feature_class":"P",
    "gn:feature_code":"PPL",
    "gn:name":"Shijiagou",
    "gn:population":0,
    "gn:timezone":"Asia/Shanghai",
    "iso:country":"CN",
    "name:zho_x_preferred":[
        "\u5e08\u5bb6\u6c9f"
    ],
    "wof:name":"Shijiagou",
    "wof:placetype":"locality"
},
  "geometry": {"coordinates":[108.76824999999999,35.19689],"type":"Point"}
}