{
  "type": "Feature",
  "properties": {
    "gn:admin1_code":"2.0",
    "gn:asciiname":"Guanluyan",
    "gn:country_code":"CN",
    "gn:dem":7,
    "gn:feature_class":"P",
    "gn:feature_code":"PPL",
    "gn:name":"Guanluyan",
    "gn:population":0,
    "gn:timezone":"Asia/Shanghai",
    "iso:country":"CN",
    "name:zho_x_preferred":[
        "\u5b98\u8def\u6cbf"
    ],
    "wof:name":"Guanluyan",
    "wof:placetype":"locality"
},
  "geometry": {"coordinates":[121.27567000000001,29.98841],"type":"Point"}
}