{
  "type": "Feature",
  "properties": {
    "gn:admin1_code":"20.0",
    "gn:asciiname":"Liulaopoyao",
    "gn:country_code":"CN",
    "gn:dem":1196,
    "gn:feature_class":"P",
    "gn:feature_code":"PPL",
    "gn:name":"Liulaopoyao",
    "gn:population":0,
    "gn:timezone":"Asia/Shanghai",
    "iso:country":"CN",
    "name:und_x_variant":[
        "\u5218\u8001\u5a46\u7a91"
    ],
    "wof:name":"Liulaopoyao",
    "wof:placetype":"locality"
},
  "geometry": {"coordinates":[111.89490000000001,40.09638],"type":"Point"}
}