{
  "type": "Feature",
  "properties": {
    "gn:admin1_code":"19.0",
    "gn:asciiname":"Yaowo Penggou",
    "gn:country_code":"CN",
    "gn:dem":68,
    "gn:feature_class":"P",
    "gn:feature_code":"PPL",
    "gn:name":"Yaowo Penggou",
    "gn:population":0,
    "gn:timezone":"Asia/Shanghai",
    "iso:country":"CN",
    "name:zho_x_preferred":[
        "\u8170\u7a9d\u68da\u6c9f"
    ],
    "wof:name":"Yaowo Penggou",
    "wof:placetype":"locality"
},
  "geometry": {"coordinates":[120.16132,40.52945],"type":"Point"}
}