{
  "type": "Feature",
  "properties": {
    "gn:admin1_code":"18",
    "gn:asciiname":"Gongjiapo",
    "gn:country_code":"CN",
    "gn:dem":1323,
    "gn:feature_class":"P",
    "gn:feature_code":"PPL",
    "gn:name":"Gongjiapo",
    "gn:population":0,
    "gn:timezone":"Asia/Shanghai",
    "iso:country":"CN",
    "name:zho_x_preferred":[
        "\u9f9a\u5bb6\u5761"
    ],
    "wof:name":"Gongjiapo",
    "wof:placetype":"locality"
},
  "geometry": {"coordinates":[107.18300000000001,28.252],"type":"Point"}
}