{
  "type": "Feature",
  "properties": {
    "gn:admin1_code":"29.0",
    "gn:asciiname":"Nadiancun",
    "gn:country_code":"CN",
    "gn:dem":1949,
    "gn:feature_class":"P",
    "gn:feature_code":"PPL",
    "gn:name":"Nadiancun",
    "gn:population":0,
    "gn:timezone":"Asia/Shanghai",
    "iso:country":"CN",
    "name:zho_x_preferred":[
        "\u7eb3\u7538\u6751"
    ],
    "wof:name":"Nadiancun",
    "wof:placetype":"locality"
},
  "geometry": {"coordinates":[101.854,25.2357],"type":"Point"}
}