{
  "type": "Feature",
  "properties": {
    "gn:admin1_code":"3.0",
    "gn:asciiname":"Zhoujiawan",
    "gn:country_code":"CN",
    "gn:dem":292,
    "gn:feature_class":"P",
    "gn:feature_code":"PPL",
    "gn:name":"Zhoujiawan",
    "gn:population":0,
    "gn:timezone":"Asia/Shanghai",
    "iso:country":"CN",
    "name:und_x_variant":[
        "\u5468\u5bb6\u6e7e"
    ],
    "wof:name":"Zhoujiawan",
    "wof:placetype":"locality"
},
  "geometry": {"coordinates":[114.42238999999999,29.17514000000001],"type":"Point"}
}