{
  "type": "Feature",
  "properties": {
    "gn:admin1_code":"02",
    "gn:asciiname":"Qiaotoucun",
    "gn:country_code":"CN",
    "gn:dem":15,
    "gn:feature_class":"P",
    "gn:feature_code":"PPL",
    "gn:name":"Qiaotoucun",
    "gn:population":0,
    "gn:timezone":"Asia/Shanghai",
    "iso:country":"CN",
    "name:und_x_variant":[
        "Shih-ch\u2019iao-chen",
        "Qiaotoujian",
        "Qiaotou",
        "\u6865\u5934",
        "Qiaotoucun"
    ],
    "name:zho_x_preferred":[
        "\u6865\u5934\u6751"
    ],
    "wof:name":"Qiaotoucun",
    "wof:placetype":"locality"
},
  "geometry": {"coordinates":[122.15228,30.30353],"type":"Point"}
}