{
  "type": "Feature",
  "properties": {
    "gn:admin1_code":"9.0",
    "gn:asciiname":"Xiaduisiyao",
    "gn:country_code":"CN",
    "gn:dem":437,
    "gn:feature_class":"P",
    "gn:feature_code":"PPL",
    "gn:name":"Xiaduisiyao",
    "gn:population":0,
    "gn:timezone":"Asia/Shanghai",
    "iso:country":"CN",
    "name:zho_x_preferred":[
        "\u4e0b\u5bf9\u5bfa\u7a91"
    ],
    "wof:name":"Xiaduisiyao",
    "wof:placetype":"locality"
},
  "geometry": {"coordinates":[114.0296,35.69757],"type":"Point"}
}