{
  "type": "Feature",
  "properties": {
    "gn:admin1_code":"31.0",
    "gn:asciiname":"Wangwu",
    "gn:country_code":"CN",
    "gn:dem":27,
    "gn:feature_class":"P",
    "gn:feature_code":"PPLA4",
    "gn:name":"Wangwu",
    "gn:population":0,
    "gn:timezone":"Asia/Shanghai",
    "iso:country":"CN",
    "name:und_x_variant":[
        "Wang-wu-shih",
        "Wangwu",
        "\u738b\u4e94",
        "Wangwu Zhen",
        "\u738b\u4e94\u9547"
    ],
    "wof:name":"Wangwu",
    "wof:placetype":"locality"
},
  "geometry": {"coordinates":[109.29071,19.65623],"type":"Point"}
}