{
  "type": "Feature",
  "properties": {
    "gn:admin1_code":"8.0",
    "gn:asciiname":"Yushanggangzi",
    "gn:country_code":"CN",
    "gn:dem":193,
    "gn:feature_class":"P",
    "gn:feature_code":"PPL",
    "gn:name":"Yushanggangzi",
    "gn:population":0,
    "gn:timezone":"Asia/Shanghai",
    "iso:country":"CN",
    "name:zho_x_preferred":[
        "\u4e8e\u4e0a\u5c97\u5b50"
    ],
    "wof:name":"Yushanggangzi",
    "wof:placetype":"locality"
},
  "geometry": {"coordinates":[125.21926999999999,47.63838],"type":"Point"}
}