{
  "type": "Feature",
  "properties": {
    "gn:admin1_code":"10",
    "gn:asciiname":"Sanlaohan",
    "gn:country_code":"CN",
    "gn:dem":1410,
    "gn:feature_class":"P",
    "gn:feature_code":"PPL",
    "gn:name":"Sanlaohan",
    "gn:population":0,
    "gn:timezone":"Asia/Shanghai",
    "iso:country":"CN",
    "name:zho_x_preferred":[
        "\u4e09\u8001\u6c49"
    ],
    "wof:name":"Sanlaohan",
    "wof:placetype":"locality"
},
  "geometry": {"coordinates":[114.51730999999999,41.73791],"type":"Point"}
}