{
  "type": "Feature",
  "properties": {
    "gn:admin1_code":"18",
    "gn:asciiname":"Nanbao",
    "gn:country_code":"CN",
    "gn:dem":561,
    "gn:feature_class":"P",
    "gn:feature_code":"PPL",
    "gn:name":"Nanbao",
    "gn:population":0,
    "gn:timezone":"Asia/Shanghai",
    "iso:country":"CN",
    "name:ceb_x_preferred":[
        "Nanbao"
    ],
    "name:swe_x_preferred":[
        "Nanbao"
    ],
    "name:zho_x_preferred":[
        "\u5357\u5305"
    ],
    "wof:name":"Nanbao",
    "wof:placetype":"locality"
},
  "geometry": {"coordinates":[108.676,26.6646],"type":"Point"}
}