{
  "type": "Feature",
  "properties": {
    "gn:admin1_code":"21.0",
    "gn:asciiname":"Xubingshui",
    "gn:country_code":"CN",
    "gn:dem":1675,
    "gn:feature_class":"P",
    "gn:feature_code":"PPL",
    "gn:name":"Xubingshui",
    "gn:population":0,
    "gn:timezone":"Asia/Shanghai",
    "iso:country":"CN",
    "name:zho_x_preferred":[
        "\u5f90\u51b0\u6c34"
    ],
    "wof:name":"Xubingshui",
    "wof:placetype":"locality"
},
  "geometry": {"coordinates":[106.248,37.1286],"type":"Point"}
}