{
  "type": "Feature",
  "properties": {
    "gn:admin1_code":"14.0",
    "gn:asciiname":"Gongna",
    "gn:country_code":"CN",
    "gn:dem":3651,
    "gn:feature_class":"P",
    "gn:feature_code":"PPL",
    "gn:name":"Gongna",
    "gn:population":0,
    "gn:timezone":"Asia/Urumqi",
    "iso:country":"CN",
    "name:zho_x_preferred":[
        "\u8d21\u7eb3"
    ],
    "wof:name":"Gongna",
    "wof:placetype":"locality"
},
  "geometry": {"coordinates":[98.67324000000001,29.23704],"type":"Point"}
}