{
  "type": "Feature",
  "properties": {
    "gn:admin1_code":"4.0",
    "gn:asciiname":"Dongtan",
    "gn:country_code":"CN",
    "gn:dem":6,
    "gn:feature_class":"P",
    "gn:feature_code":"PPL",
    "gn:name":"Dongtan",
    "gn:population":0,
    "gn:timezone":"Asia/Shanghai",
    "iso:country":"CN",
    "name:deu_x_preferred":[
        "Dongtan"
    ],
    "name:zho_x_preferred":[
        "\u4e1c\u574d"
    ],
    "wof:name":"Dongtan",
    "wof:placetype":"locality"
},
  "geometry": {"coordinates":[120.18258,32.23959],"type":"Point"}
}