{
  "type": "Feature",
  "properties": {
    "gn:admin1_code":"21.0",
    "gn:asciiname":"Nantai",
    "gn:country_code":"CN",
    "gn:dem":1667,
    "gn:feature_class":"P",
    "gn:feature_code":"PPL",
    "gn:name":"Nantai",
    "gn:population":0,
    "gn:timezone":"Asia/Shanghai",
    "iso:country":"CN",
    "name:zho_x_preferred":[
        "\u5357\u53f0"
    ],
    "wof:name":"Nantai",
    "wof:placetype":"locality"
},
  "geometry": {"coordinates":[105.54600000000001,36.6622],"type":"Point"}
}