{
  "type": "Feature",
  "properties": {
    "gn:admin1_code":"16.0",
    "gn:asciiname":"Renzipai",
    "gn:country_code":"CN",
    "gn:dem":69,
    "gn:feature_class":"P",
    "gn:feature_code":"PPL",
    "gn:name":"Renzipai",
    "gn:population":0,
    "gn:timezone":"Asia/Shanghai",
    "iso:country":"CN",
    "name:zho_x_preferred":[
        "\u7a14\u5b50\u6392"
    ],
    "wof:name":"Renzipai",
    "wof:placetype":"locality"
},
  "geometry": {"coordinates":[109.145,22.1574],"type":"Point"}
}