{
  "type": "Feature",
  "properties": {
    "gn:admin1_code":"16.0",
    "gn:asciiname":"Kunancun",
    "gn:country_code":"CN",
    "gn:dem":516,
    "gn:feature_class":"P",
    "gn:feature_code":"PPL",
    "gn:name":"Kunancun",
    "gn:population":0,
    "gn:timezone":"Asia/Shanghai",
    "iso:country":"CN",
    "name:zho_x_preferred":[
        "\u67af\u5357\u6751"
    ],
    "wof:name":"Kunancun",
    "wof:placetype":"locality"
},
  "geometry": {"coordinates":[107.44,21.7143],"type":"Point"}
}