{
  "type": "Feature",
  "properties": {
    "gn:admin1_code":"7",
    "gn:asciiname":"Waishan",
    "gn:country_code":"CN",
    "gn:dem":256,
    "gn:feature_class":"P",
    "gn:feature_code":"PPLA4",
    "gn:name":"Waishan",
    "gn:population":0,
    "gn:timezone":"Asia/Shanghai",
    "iso:country":"CN",
    "name:und_x_variant":[
        "Songxi",
        "Waishan",
        "Waishan Xiang"
    ],
    "name:zho_x_preferred":[
        "\u5916\u5c71"
    ],
    "name:zho_x_variant":[
        "\u5916\u5c71\u4e61"
    ],
    "wof:name":"Waishan",
    "wof:placetype":"locality"
},
  "geometry": {"coordinates":[118.47251,25.32086],"type":"Point"}
}