{
  "type": "Feature",
  "properties": {
    "gn:admin1_code":"11.0",
    "gn:asciiname":"Fengshuwan",
    "gn:country_code":"CN",
    "gn:dem":88,
    "gn:feature_class":"P",
    "gn:feature_code":"PPL",
    "gn:name":"Fengshuwan",
    "gn:population":0,
    "gn:timezone":"Asia/Shanghai",
    "iso:country":"CN",
    "name:zho_x_preferred":[
        "Fengshuwan"
    ],
    "name:zho_x_variant":[
        "\u67ab\u6811\u6e7e"
    ],
    "wof:name":"Fengshuwan",
    "wof:placetype":"locality"
},
  "geometry": {"coordinates":[111.59439999999999,29.06526],"type":"Point"}
}