{
  "type": "Feature",
  "properties": {
    "gn:admin1_code":"32.0",
    "gn:asciiname":"Qingming",
    "gn:country_code":"CN",
    "gn:dem":1425,
    "gn:feature_class":"P",
    "gn:feature_code":"PPL",
    "gn:name":"Qingming",
    "gn:population":0,
    "gn:timezone":"Asia/Shanghai",
    "iso:country":"CN",
    "name:zho_x_preferred":[
        "\u6e05\u660e"
    ],
    "wof:name":"Qingming",
    "wof:placetype":"locality"
},
  "geometry": {"coordinates":[103.495,28.225],"type":"Point"}
}