{
  "type": "Feature",
  "properties": {
    "gn:admin1_code":"28.0",
    "gn:asciiname":"Liumazhuang",
    "gn:country_code":"CN",
    "gn:dem":5,
    "gn:feature_class":"P",
    "gn:feature_code":"PPL",
    "gn:name":"Liumazhuang",
    "gn:population":0,
    "gn:timezone":"Asia/Shanghai",
    "iso:country":"CN",
    "name:zho_x_preferred":[
        "\u5218\u9a6c\u5e84"
    ],
    "wof:name":"Liumazhuang",
    "wof:placetype":"locality"
},
  "geometry": {"coordinates":[117.1559,39.30324],"type":"Point"}
}