{
  "type": "Feature",
  "properties": {
    "gn:admin1_code":"15.0",
    "gn:asciiname":"Sunjia Wanzi",
    "gn:country_code":"CN",
    "gn:dem":1405,
    "gn:feature_class":"P",
    "gn:feature_code":"PPL",
    "gn:name":"Sunjia Wanzi",
    "gn:population":0,
    "gn:timezone":"Asia/Shanghai",
    "iso:country":"CN",
    "name:und_x_variant":[
        "\u5b59\u5bb6\u6e7e\u5b50"
    ],
    "wof:name":"Sunjia Wanzi",
    "wof:placetype":"locality"
},
  "geometry": {"coordinates":[107.88352999999999,36.60882],"type":"Point"}
}