{
  "type": "Feature",
  "properties": {
    "gn:admin1_code":"1.0",
    "gn:asciiname":"Xiaoxucun",
    "gn:country_code":"CN",
    "gn:dem":27,
    "gn:feature_class":"P",
    "gn:feature_code":"PPL",
    "gn:name":"Xiaoxucun",
    "gn:population":0,
    "gn:timezone":"Asia/Shanghai",
    "iso:country":"CN",
    "name:zho_x_preferred":[
        "\u5c0f\u5729\u6751"
    ],
    "wof:name":"Xiaoxucun",
    "wof:placetype":"locality"
},
  "geometry": {"coordinates":[117.04993,33.33148],"type":"Point"}
}