{
  "type": "Feature",
  "properties": {
    "gn:admin1_code":"32.0",
    "gn:asciiname":"Dama'er",
    "gn:country_code":"CN",
    "gn:dem":2492,
    "gn:feature_class":"P",
    "gn:feature_code":"PPL",
    "gn:name":"Dama\u2019er",
    "gn:population":0,
    "gn:timezone":"Asia/Shanghai",
    "iso:country":"CN",
    "name:und_x_variant":[
        "Dama\u2019er"
    ],
    "name:zho_x_preferred":[
        "\u5927\u9a6c\u5c14"
    ],
    "wof:name":"Dama'er",
    "wof:placetype":"locality"
},
  "geometry": {"coordinates":[101.998,30.7742],"type":"Point"}
}