{
  "type": "Feature",
  "properties": {
    "gn:admin1_code":"9.0",
    "gn:asciiname":"Xiayu",
    "gn:cc2":"CN",
    "gn:country_code":"CN",
    "gn:dem":684,
    "gn:feature_class":"P",
    "gn:feature_code":"PPL",
    "gn:name":"Xiayu",
    "gn:population":0,
    "gn:timezone":"Asia/Shanghai",
    "iso:country":"CN",
    "name:und_x_variant":[
        "Hsia-y\u00fc",
        "Xiayu"
    ],
    "wof:name":"Xiayu",
    "wof:placetype":"locality"
},
  "geometry": {"coordinates":[111.30444,34.21444],"type":"Point"}
}