{
  "type": "Feature",
  "properties": {
    "gn:admin1_code":"11.0",
    "gn:asciiname":"Wufenchang Qidui",
    "gn:country_code":"CN",
    "gn:dem":26,
    "gn:feature_class":"P",
    "gn:feature_code":"PPLF",
    "gn:name":"Wufenchang Qidui",
    "gn:population":0,
    "gn:timezone":"Asia/Shanghai",
    "iso:country":"CN",
    "name:zho_x_preferred":[
        "\u4e94\u5206\u573a\u4e03\u961f"
    ],
    "wof:name":"Wufenchang Qidui",
    "wof:placetype":"locality"
},
  "geometry": {"coordinates":[112.45899,29.18052],"type":"Point"}
}