{
  "type": "Feature",
  "properties": {
    "gn:admin1_code":"29.0",
    "gn:asciiname":"Huangcaoping",
    "gn:country_code":"CN",
    "gn:dem":2206,
    "gn:feature_class":"P",
    "gn:feature_code":"PPL",
    "gn:name":"Huangcaoping",
    "gn:population":0,
    "gn:timezone":"Asia/Shanghai",
    "iso:country":"CN",
    "name:zho_x_preferred":[
        "\u9ec4\u8349\u576a"
    ],
    "wof:name":"Huangcaoping",
    "wof:placetype":"locality"
},
  "geometry": {"coordinates":[100.64700000000001,26.1201],"type":"Point"}
}