{
  "type": "Feature",
  "properties": {
    "gn:admin1_code":"31",
    "gn:asciiname":"Longgun",
    "gn:country_code":"CN",
    "gn:dem":13,
    "gn:feature_class":"P",
    "gn:feature_code":"PPLA4",
    "gn:name":"Longgun",
    "gn:population":0,
    "gn:timezone":"Asia/Shanghai",
    "iso:country":"CN",
    "name:und_x_variant":[
        "Lung-kun",
        "Longgun",
        "\u9f99\u6eda",
        "Longgun Zhen",
        "\u9f99\u6eda\u9547"
    ],
    "wof:name":"Longgun",
    "wof:placetype":"locality"
},
  "geometry": {"coordinates":[110.52473000000001,19.0512],"type":"Point"}
}