{
  "type": "Feature",
  "properties": {
    "gn:admin1_code":"25.0",
    "gn:asciiname":"Linquancun",
    "gn:country_code":"CN",
    "gn:dem":24,
    "gn:feature_class":"P",
    "gn:feature_code":"PPL",
    "gn:name":"Linquancun",
    "gn:population":0,
    "gn:timezone":"Asia/Shanghai",
    "iso:country":"CN",
    "name:zho_x_preferred":[
        "\u6797\u6cc9\u6751"
    ],
    "wof:name":"Linquancun",
    "wof:placetype":"locality"
},
  "geometry": {"coordinates":[119.49823000000001,35.62710999999999],"type":"Point"}
}