{
  "type": "Feature",
  "properties": {
    "gn:admin1_code":"19.0",
    "gn:asciiname":"Qianzhaojiatun",
    "gn:country_code":"CN",
    "gn:dem":36,
    "gn:feature_class":"P",
    "gn:feature_code":"PPL",
    "gn:name":"Qianzhaojiatun",
    "gn:population":0,
    "gn:timezone":"Asia/Shanghai",
    "iso:country":"CN",
    "name:zho_x_preferred":[
        "\u524d\u8d75\u5bb6\u5c6f"
    ],
    "wof:name":"Qianzhaojiatun",
    "wof:placetype":"locality"
},
  "geometry": {"coordinates":[123.215,39.9625],"type":"Point"}
}