{
  "type": "Feature",
  "properties": {
    "gn:admin1_code":"6.0",
    "gn:asciiname":"Tebh",
    "gn:country_code":"CN",
    "gn:dem":2847,
    "gn:feature_class":"P",
    "gn:feature_code":"PPL",
    "gn:name":"Tebh",
    "gn:population":0,
    "gn:timezone":"Asia/Urumqi",
    "iso:country":"CN",
    "wof:name":"Tebh",
    "wof:placetype":"locality"
},
  "geometry": {"coordinates":[97.59999999999999,36.36667],"type":"Point"}
}