{
  "type": "Feature",
  "properties": {
    "gn:admin1_code":"15.0",
    "gn:asciiname":"Renjiazhuang",
    "gn:country_code":"CN",
    "gn:dem":1403,
    "gn:feature_class":"P",
    "gn:feature_code":"PPL",
    "gn:name":"Renjiazhuang",
    "gn:population":0,
    "gn:timezone":"Asia/Shanghai",
    "iso:country":"CN",
    "name:zho_x_preferred":[
        "\u4efb\u5bb6\u5e84"
    ],
    "wof:name":"Renjiazhuang",
    "wof:placetype":"locality"
},
  "geometry": {"coordinates":[98.6563,39.7318],"type":"Point"}
}