{
  "type": "Feature",
  "properties": {
    "gn:admin1_code":"14.0",
    "gn:asciiname":"Binbariwa",
    "gn:country_code":"CN",
    "gn:dem":3647,
    "gn:feature_class":"P",
    "gn:feature_code":"PPL",
    "gn:name":"Binbariwa",
    "gn:population":0,
    "gn:timezone":"Asia/Urumqi",
    "iso:country":"CN",
    "name:zho_x_preferred":[
        "\u6ee8\u5df4\u65e5\u74e6"
    ],
    "wof:name":"Binbariwa",
    "wof:placetype":"locality"
},
  "geometry": {"coordinates":[98.3462,31.9166],"type":"Point"}
}