{
  "type": "Feature",
  "properties": {
    "gn:admin1_code":"11.0",
    "gn:asciiname":"Laohuangshan",
    "gn:country_code":"CN",
    "gn:dem":303,
    "gn:feature_class":"P",
    "gn:feature_code":"PPL",
    "gn:name":"Laohuangshan",
    "gn:population":0,
    "gn:timezone":"Asia/Shanghai",
    "iso:country":"CN",
    "name:zho_x_preferred":[
        "\u8001\u9ec4\u5c71"
    ],
    "wof:name":"Laohuangshan",
    "wof:placetype":"locality"
},
  "geometry": {"coordinates":[109.77443999999998,28.00803],"type":"Point"}
}