{
  "type": "Feature",
  "properties": {
    "gn:admin1_code":"30.0",
    "gn:asciiname":"Ganyuan",
    "gn:country_code":"CN",
    "gn:dem":10,
    "gn:feature_class":"P",
    "gn:feature_code":"PPL",
    "gn:name":"Ganyuan",
    "gn:population":0,
    "gn:timezone":"Asia/Shanghai",
    "iso:country":"CN",
    "name:zho_x_preferred":[
        "\u67d1\u5712"
    ],
    "wof:name":"Ganyuan",
    "wof:placetype":"locality"
},
  "geometry": {"coordinates":[112.45847000000001,22.94961],"type":"Point"}
}