{
  "type": "Feature",
  "properties": {
    "gn:admin1_code":"30.0",
    "gn:asciiname":"Yezhoushan",
    "gn:country_code":"CN",
    "gn:dem":13,
    "gn:feature_class":"P",
    "gn:feature_code":"PPL",
    "gn:name":"Yezhoushan",
    "gn:population":0,
    "gn:timezone":"Asia/Shanghai",
    "iso:country":"CN",
    "name:zho_x_preferred":[
        "\u53f6\u821f\u5c71"
    ],
    "wof:name":"Yezhoushan",
    "wof:placetype":"locality"
},
  "geometry": {"coordinates":[115.02058999999998,22.74528],"type":"Point"}
}