{
  "type": "Feature",
  "properties": {
    "gn:admin1_code":"10",
    "gn:asciiname":"Dayushu",
    "gn:country_code":"CN",
    "gn:dem":949,
    "gn:feature_class":"P",
    "gn:feature_code":"PPL",
    "gn:name":"Dayushu",
    "gn:population":0,
    "gn:timezone":"Asia/Shanghai",
    "iso:country":"CN",
    "name:zho_x_preferred":[
        "\u5927\u6986\u6811"
    ],
    "wof:name":"Dayushu",
    "wof:placetype":"locality"
},
  "geometry": {"coordinates":[115.70480999999999,40.71754],"type":"Point"}
}