{
  "type": "Feature",
  "properties": {
    "gn:admin1_code":"12.0",
    "gn:asciiname":"Riyueping",
    "gn:country_code":"CN",
    "gn:dem":314,
    "gn:feature_class":"P",
    "gn:feature_code":"PPL",
    "gn:name":"Riyueping",
    "gn:population":0,
    "gn:timezone":"Asia/Shanghai",
    "iso:country":"CN",
    "name:zho_x_preferred":[
        "\u65e5\u6708\u576a"
    ],
    "wof:name":"Riyueping",
    "wof:placetype":"locality"
},
  "geometry": {"coordinates":[110.93048,30.7583],"type":"Point"}
}