{
  "type": "Feature",
  "properties": {
    "gn:admin1_code":"29.0",
    "gn:asciiname":"Yicun",
    "gn:country_code":"CN",
    "gn:dem":2156,
    "gn:feature_class":"P",
    "gn:feature_code":"PPL",
    "gn:name":"Yicun",
    "gn:population":0,
    "gn:timezone":"Asia/Shanghai",
    "iso:country":"CN",
    "name:zho_x_preferred":[
        "\u8fe4\u6751"
    ],
    "wof:name":"Yicun",
    "wof:placetype":"locality"
},
  "geometry": {"coordinates":[102.72,25.374],"type":"Point"}
}