{
  "type": "Feature",
  "properties": {
    "gn:admin1_code":"29.0",
    "gn:asciiname":"Damiaozhai",
    "gn:country_code":"CN",
    "gn:dem":1642,
    "gn:feature_class":"P",
    "gn:feature_code":"PPL",
    "gn:name":"Damiaozhai",
    "gn:population":0,
    "gn:timezone":"Asia/Shanghai",
    "iso:country":"CN",
    "name:zho_x_preferred":[
        "\u5927\u82d7\u5be8"
    ],
    "wof:name":"Damiaozhai",
    "wof:placetype":"locality"
},
  "geometry": {"coordinates":[103.91,27.478],"type":"Point"}
}