{
  "type": "Feature",
  "properties": {
    "gn:admin1_code":"32.0",
    "gn:asciiname":"Cuorong",
    "gn:country_code":"CN",
    "gn:dem":3630,
    "gn:feature_class":"P",
    "gn:feature_code":"PPL",
    "gn:name":"Cuorong",
    "gn:population":0,
    "gn:timezone":"Asia/Shanghai",
    "iso:country":"CN",
    "name:zho_x_preferred":[
        "\u63aa\u7ed2"
    ],
    "wof:name":"Cuorong",
    "wof:placetype":"locality"
},
  "geometry": {"coordinates":[100.616,29.649],"type":"Point"}
}