{
  "type": "Feature",
  "properties": {
    "gn:admin1_code":"15.0",
    "gn:asciiname":"Chaizhuang",
    "gn:country_code":"CN",
    "gn:dem":1690,
    "gn:feature_class":"P",
    "gn:feature_code":"PPL",
    "gn:name":"Chaizhuang",
    "gn:population":0,
    "gn:timezone":"Asia/Shanghai",
    "iso:country":"CN",
    "name:und_x_variant":[
        "\u67f4\u5e84"
    ],
    "wof:name":"Chaizhuang",
    "wof:placetype":"locality"
},
  "geometry": {"coordinates":[104.64537,34.66185],"type":"Point"}
}