{
  "type": "Feature",
  "properties": {
    "gn:admin1_code":"30.0",
    "gn:asciiname":"Yaku",
    "gn:country_code":"CN",
    "gn:dem":35,
    "gn:feature_class":"P",
    "gn:feature_code":"PPL",
    "gn:name":"Yaku",
    "gn:population":0,
    "gn:timezone":"Asia/Shanghai",
    "iso:country":"CN",
    "name:ceb_x_preferred":[
        "Yaku"
    ],
    "name:swe_x_preferred":[
        "Yaku"
    ],
    "name:zho_x_preferred":[
        "\u9e2d\u5800"
    ],
    "wof:name":"Yaku",
    "wof:placetype":"locality"
},
  "geometry": {"coordinates":[115.96793999999998,23.44605],"type":"Point"}
}