{
  "type": "Feature",
  "properties": {
    "gn:admin1_code":"18",
    "gn:asciiname":"Lanjiaba",
    "gn:country_code":"CN",
    "gn:dem":809,
    "gn:feature_class":"P",
    "gn:feature_code":"PPL",
    "gn:name":"Lanjiaba",
    "gn:population":0,
    "gn:timezone":"Asia/Shanghai",
    "iso:country":"CN",
    "name:zho_x_preferred":[
        "\u5170\u5bb6\u575d"
    ],
    "wof:name":"Lanjiaba",
    "wof:placetype":"locality"
},
  "geometry": {"coordinates":[107.54900000000001,28.415],"type":"Point"}
}