{
  "type": "Feature",
  "properties": {
    "gn:admin1_code":"26",
    "gn:asciiname":"Zaoshuping",
    "gn:country_code":"CN",
    "gn:dem":882,
    "gn:feature_class":"P",
    "gn:feature_code":"PPL",
    "gn:name":"Zaoshuping",
    "gn:population":0,
    "gn:timezone":"Asia/Shanghai",
    "iso:country":"CN",
    "wof:name":"Zaoshuping",
    "wof:placetype":"locality"
},
  "geometry": {"coordinates":[107.85250000000001,32.32667],"type":"Point"}
}