{
  "type": "Feature",
  "properties": {
    "gn:admin1_code":"8.0",
    "gn:asciiname":"Shoushan",
    "gn:country_code":"CN",
    "gn:dem":162,
    "gn:feature_class":"P",
    "gn:feature_code":"PPLA4",
    "gn:name":"Shoushan",
    "gn:population":0,
    "gn:timezone":"Asia/Shanghai",
    "iso:country":"CN",
    "name:deu_x_preferred":[
        "Shoushan"
    ],
    "name:und_x_variant":[
        "Shoushan Xiang"
    ],
    "name:zho_x_preferred":[
        "\u5bff\u5c71"
    ],
    "name:zho_x_variant":[
        "\u5bff\u5c71\u4e61"
    ],
    "wof:name":"Shoushan",
    "wof:placetype":"locality"
},
  "geometry": {"coordinates":[128.43943999999999,45.44631],"type":"Point"}
}