{
  "type": "Feature",
  "properties": {
    "gn:admin1_code":"26.0",
    "gn:asciiname":"Liuxigou",
    "gn:country_code":"CN",
    "gn:dem":1470,
    "gn:feature_class":"P",
    "gn:feature_code":"PPL",
    "gn:name":"Liuxigou",
    "gn:population":0,
    "gn:timezone":"Asia/Shanghai",
    "iso:country":"CN",
    "name:zho_x_preferred":[
        "\u6d41\u6eaa\u6c9f"
    ],
    "wof:name":"Liuxigou",
    "wof:placetype":"locality"
},
  "geometry": {"coordinates":[109.14239000000001,32.0417],"type":"Point"}
}