{
  "type": "Feature",
  "properties": {
    "gn:admin1_code":"11",
    "gn:asciiname":"Xintangpu",
    "gn:country_code":"CN",
    "gn:dem":304,
    "gn:feature_class":"P",
    "gn:feature_code":"PPL",
    "gn:name":"Xintangpu",
    "gn:population":0,
    "gn:timezone":"Asia/Shanghai",
    "iso:country":"CN",
    "name:und_x_variant":[
        "\u65b0\u5858\u94fa",
        "Xintangpu"
    ],
    "wof:name":"Xintangpu",
    "wof:placetype":"locality"
},
  "geometry": {"coordinates":[112.16222,25.80444],"type":"Point"}
}