{
  "type": "Feature",
  "properties": {
    "gn:admin1_code":"7.0",
    "gn:asciiname":"Yangchi",
    "gn:country_code":"CN",
    "gn:dem":531,
    "gn:feature_class":"P",
    "gn:feature_code":"PPL",
    "gn:name":"Yangchi",
    "gn:population":0,
    "gn:timezone":"Asia/Shanghai",
    "iso:country":"CN",
    "name:und_x_variant":[
        "\u7f8a\u8d64"
    ],
    "name:zho_x_preferred":[
        "\u7f8a\u8d64"
    ],
    "wof:name":"Yangchi",
    "wof:placetype":"locality"
},
  "geometry": {"coordinates":[116.27087,25.67966],"type":"Point"}
}