{
  "type": "Feature",
  "properties": {
    "gn:admin1_code":"19.0",
    "gn:asciiname":"Shaojiawopeng",
    "gn:country_code":"CN",
    "gn:dem":109,
    "gn:feature_class":"P",
    "gn:feature_code":"PPL",
    "gn:name":"Shaojiawopeng",
    "gn:population":0,
    "gn:timezone":"Asia/Shanghai",
    "iso:country":"CN",
    "name:zho_x_preferred":[
        "\u90b5\u5bb6\u7a9d\u68da"
    ],
    "wof:name":"Shaojiawopeng",
    "wof:placetype":"locality"
},
  "geometry": {"coordinates":[123.40300000000001,42.9995],"type":"Point"}
}