{
  "type": "Feature",
  "properties": {
    "iso:country":"CN",
    "name:eng_x_preferred":[
        "Pengbu"
    ],
    "name:zho_x_preferred":[
        "\u5f6d\u57e0\u9547"
    ],
    "qs:name":"\u5f6d\u57e0\u9547",
    "qs:name_adm0":"\u4e2d\u570b",
    "qs:name_adm1":"\u6d59\u6c5f\u7701",
    "qs:photos":32,
    "qs:photos_1k":6,
    "qs:photos_9k":1,
    "qs:photos_9r":2,
    "qs:photos_all":32,
    "qs:photos_sr":2,
    "qs:placetype":"Town",
    "qs:pop_sr":"0",
    "wof:name":"Pengbu",
    "wof:placetype":"locality"
},
  "geometry": {"coordinates":[120.224789,30.3034615],"type":"Point"}
}