{
  "type": "Feature",
  "properties": {
    "gn:admin1_code":"2",
    "gn:asciiname":"Wangyuan",
    "gn:country_code":"CN",
    "gn:dem":327,
    "gn:feature_class":"P",
    "gn:feature_code":"PPL",
    "gn:name":"Wangyuan",
    "gn:population":0,
    "gn:timezone":"Asia/Shanghai",
    "iso:country":"CN",
    "name:und_x_variant":[
        "\u738b\u9662"
    ],
    "name:zho_x_preferred":[
        "\u738b\u9662"
    ],
    "wof:name":"Wangyuan",
    "wof:placetype":"locality"
},
  "geometry": {"coordinates":[120.60527999999999,29.6325],"type":"Point"}
}