{
  "type": "Feature",
  "properties": {
    "gn:admin1_code":"24.0",
    "gn:asciiname":"Nanpo",
    "gn:country_code":"CN",
    "gn:dem":686,
    "gn:feature_class":"P",
    "gn:feature_code":"PPL",
    "gn:name":"Nanpo",
    "gn:population":0,
    "gn:timezone":"Asia/Shanghai",
    "iso:country":"CN",
    "name:und_x_variant":[
        "\u5357\u5761"
    ],
    "name:zho_x_preferred":[
        "\u5357\u5761"
    ],
    "wof:name":"Nanpo",
    "wof:placetype":"locality"
},
  "geometry": {"coordinates":[111.35605,35.2692],"type":"Point"}
}