{
  "type": "Feature",
  "properties": {
    "gn:admin1_code":"32.0",
    "gn:asciiname":"Huaichunyuan",
    "gn:country_code":"CN",
    "gn:dem":899,
    "gn:feature_class":"P",
    "gn:feature_code":"PPL",
    "gn:name":"Huaichunyuan",
    "gn:population":0,
    "gn:timezone":"Asia/Shanghai",
    "iso:country":"CN",
    "name:zho_x_preferred":[
        "\u69d0\u6625\u56ed"
    ],
    "wof:name":"Huaichunyuan",
    "wof:placetype":"locality"
},
  "geometry": {"coordinates":[105.45227,28.41562],"type":"Point"}
}