{
  "type": "Feature",
  "properties": {
    "gn:admin1_code":"1.0",
    "gn:asciiname":"Wangzhaicun",
    "gn:country_code":"CN",
    "gn:dem":27,
    "gn:feature_class":"P",
    "gn:feature_code":"PPL",
    "gn:name":"Wangzhaicun",
    "gn:population":0,
    "gn:timezone":"Asia/Shanghai",
    "iso:country":"CN",
    "name:zho_x_preferred":[
        "\u7f51\u5be8\u6751"
    ],
    "wof:name":"Wangzhaicun",
    "wof:placetype":"locality"
},
  "geometry": {"coordinates":[117.36861,33.78334],"type":"Point"}
}