{
  "type": "Feature",
  "properties": {
    "gn:admin1_code":"18",
    "gn:asciiname":"Minziqian",
    "gn:country_code":"CN",
    "gn:dem":481,
    "gn:feature_class":"P",
    "gn:feature_code":"PPL",
    "gn:name":"Minziqian",
    "gn:population":0,
    "gn:timezone":"Asia/Shanghai",
    "iso:country":"CN",
    "name:zho_x_preferred":[
        "\u95f5\u5b50\u9a9e"
    ],
    "wof:name":"Minziqian",
    "wof:placetype":"locality"
},
  "geometry": {"coordinates":[108.31,28.3857],"type":"Point"}
}