{
  "type": "Feature",
  "properties": {
    "gn:admin1_code":"1.0",
    "gn:asciiname":"Fushancun",
    "gn:country_code":"CN",
    "gn:dem":21,
    "gn:feature_class":"P",
    "gn:feature_code":"PPL",
    "gn:name":"Fushancun",
    "gn:population":0,
    "gn:timezone":"Asia/Shanghai",
    "iso:country":"CN",
    "name:und_x_variant":[
        "Fushan",
        "Fushancun"
    ],
    "name:zho_x_preferred":[
        "\u798f\u5c71\u6751"
    ],
    "wof:name":"Fushancun",
    "wof:placetype":"locality"
},
  "geometry": {"coordinates":[118.01391,31.56518],"type":"Point"}
}