{
  "type": "Feature",
  "properties": {
    "gn:admin1_code":"07",
    "gn:asciiname":"Xiaxikeng",
    "gn:country_code":"CN",
    "gn:dem":494,
    "gn:feature_class":"P",
    "gn:feature_code":"PPL",
    "gn:name":"Xiaxikeng",
    "gn:population":0,
    "gn:timezone":"Asia/Shanghai",
    "iso:country":"CN",
    "name:zho_x_preferred":[
        "\u4e0b\u897f\u5751"
    ],
    "wof:name":"Xiaxikeng",
    "wof:placetype":"locality"
},
  "geometry": {"coordinates":[117.91663,25.46636],"type":"Point"}
}