{
  "type": "Feature",
  "properties": {
    "gn:admin1_code":"18",
    "gn:asciiname":"Tiechang Longchang",
    "gn:country_code":"CN",
    "gn:dem":1701,
    "gn:feature_class":"P",
    "gn:feature_code":"PPL",
    "gn:name":"Tiechang Longchang",
    "gn:population":0,
    "gn:timezone":"Asia/Shanghai",
    "iso:country":"CN",
    "name:zho_x_preferred":[
        "\u94c1\u5382\u9f99\u573a"
    ],
    "wof:name":"Tiechang Longchang",
    "wof:placetype":"locality"
},
  "geometry": {"coordinates":[105.658,26.751],"type":"Point"}
}