{
  "type": "Feature",
  "properties": {
    "gn:admin1_code":"29.0",
    "gn:asciiname":"Banpo",
    "gn:country_code":"CN",
    "gn:dem":1290,
    "gn:feature_class":"P",
    "gn:feature_code":"PPL",
    "gn:name":"Banpo",
    "gn:population":0,
    "gn:timezone":"Asia/Shanghai",
    "iso:country":"CN",
    "name:zho_x_preferred":[
        "\u534a\u5761"
    ],
    "wof:name":"Banpo",
    "wof:placetype":"locality"
},
  "geometry": {"coordinates":[103.67700000000001,22.9978],"type":"Point"}
}