{
  "type": "Feature",
  "properties": {
    "gn:admin1_code":"7.0",
    "gn:asciiname":"Zhangli",
    "gn:country_code":"CN",
    "gn:dem":624,
    "gn:feature_class":"P",
    "gn:feature_code":"PPL",
    "gn:name":"Zhangli",
    "gn:population":0,
    "gn:timezone":"Asia/Shanghai",
    "iso:country":"CN",
    "name:zho_x_preferred":[
        "\u6a1f\u91cc"
    ],
    "wof:name":"Zhangli",
    "wof:placetype":"locality"
},
  "geometry": {"coordinates":[118.57653000000001,26.03604],"type":"Point"}
}