{
  "type": "Feature",
  "properties": {
    "gn:admin1_code":"31.0",
    "gn:asciiname":"Baowo",
    "gn:country_code":"CN",
    "gn:dem":158,
    "gn:feature_class":"P",
    "gn:feature_code":"PPL",
    "gn:name":"Baowo",
    "gn:population":0,
    "gn:timezone":"Asia/Shanghai",
    "iso:country":"CN",
    "name:und_x_variant":[
        "\u62b1\u7a9d"
    ],
    "wof:name":"Baowo",
    "wof:placetype":"locality"
},
  "geometry": {"coordinates":[109.14391999999999,18.79564],"type":"Point"}
}