{
  "type": "Feature",
  "properties": {
    "gn:admin1_code":"9",
    "gn:asciiname":"Houzhang Liucun",
    "gn:country_code":"CN",
    "gn:dem":55,
    "gn:feature_class":"P",
    "gn:feature_code":"PPL",
    "gn:name":"Houzhang Liucun",
    "gn:population":0,
    "gn:timezone":"Asia/Shanghai",
    "iso:country":"CN",
    "name:zho_x_preferred":[
        "\u540e\u5f20\u516d\u6751"
    ],
    "wof:name":"Houzhang Liucun",
    "wof:placetype":"locality"
},
  "geometry": {"coordinates":[115.0377,35.98639],"type":"Point"}
}