{
  "type": "Feature",
  "properties": {
    "gn:admin1_code":"12.0",
    "gn:asciiname":"Qinjiashan",
    "gn:country_code":"CN",
    "gn:dem":310,
    "gn:feature_class":"P",
    "gn:feature_code":"PPL",
    "gn:name":"Qinjiashan",
    "gn:population":0,
    "gn:timezone":"Asia/Shanghai",
    "iso:country":"CN",
    "name:zho_x_preferred":[
        "Qinjiashan"
    ],
    "name:zho_x_variant":[
        "\u79e6\u5bb6\u5c71"
    ],
    "wof:name":"Qinjiashan",
    "wof:placetype":"locality"
},
  "geometry": {"coordinates":[114.98732,29.9417],"type":"Point"}
}