{
  "type": "Feature",
  "properties": {
    "gn:admin1_code":"19.0",
    "gn:asciiname":"Xinnong",
    "gn:country_code":"CN",
    "gn:dem":22,
    "gn:feature_class":"P",
    "gn:feature_code":"PPL",
    "gn:name":"Xinnong",
    "gn:population":0,
    "gn:timezone":"Asia/Shanghai",
    "iso:country":"CN",
    "name:und_x_variant":[
        "\u65b0\u519c"
    ],
    "name:zho_x_preferred":[
        "\u65b0\u519c"
    ],
    "wof:name":"Xinnong",
    "wof:placetype":"locality"
},
  "geometry": {"coordinates":[123.46013000000001,39.9515],"type":"Point"}
}