{
  "type": "Feature",
  "properties": {
    "gn:admin1_code":"1.0",
    "gn:asciiname":"Bohucun",
    "gn:country_code":"CN",
    "gn:dem":14,
    "gn:feature_class":"P",
    "gn:feature_code":"PPL",
    "gn:name":"Bohucun",
    "gn:population":0,
    "gn:timezone":"Asia/Shanghai",
    "iso:country":"CN",
    "name:zho_x_preferred":[
        "\u6cca\u6e56\u6751"
    ],
    "wof:name":"Bohucun",
    "wof:placetype":"locality"
},
  "geometry": {"coordinates":[116.52149,30.12388],"type":"Point"}
}