{
  "type": "Feature",
  "properties": {
    "gn:admin1_code":"26.0",
    "gn:asciiname":"Huangshawocun",
    "gn:country_code":"CN",
    "gn:dem":1386,
    "gn:feature_class":"P",
    "gn:feature_code":"PPL",
    "gn:name":"Huangshawocun",
    "gn:population":0,
    "gn:timezone":"Asia/Shanghai",
    "iso:country":"CN",
    "name:zho_x_preferred":[
        "\u9ec4\u6c99\u7a9d\u6751"
    ],
    "wof:name":"Huangshawocun",
    "wof:placetype":"locality"
},
  "geometry": {"coordinates":[107.35066999999999,37.48498],"type":"Point"}
}