{
  "type": "Feature",
  "properties": {
    "gn:admin1_code":"14.0",
    "gn:asciiname":"Darangcun",
    "gn:country_code":"CN",
    "gn:dem":4456,
    "gn:feature_class":"P",
    "gn:feature_code":"PPL",
    "gn:name":"Darangcun",
    "gn:population":0,
    "gn:timezone":"Asia/Urumqi",
    "iso:country":"CN",
    "name:zho_x_preferred":[
        "\u8fbe\u58e4\u6751"
    ],
    "wof:name":"Darangcun",
    "wof:placetype":"locality"
},
  "geometry": {"coordinates":[92.30092999999999,31.29087],"type":"Point"}
}