{
  "type": "Feature",
  "properties": {
    "gn:admin1_code":"29.0",
    "gn:asciiname":"Jiuzhaichong",
    "gn:country_code":"CN",
    "gn:dem":1473,
    "gn:feature_class":"P",
    "gn:feature_code":"PPL",
    "gn:name":"Jiuzhaichong",
    "gn:population":0,
    "gn:timezone":"Asia/Shanghai",
    "iso:country":"CN",
    "name:zho_x_preferred":[
        "\u65e7\u5be8\u51b2"
    ],
    "wof:name":"Jiuzhaichong",
    "wof:placetype":"locality"
},
  "geometry": {"coordinates":[104.411,23.4046],"type":"Point"}
}