{
  "type": "Feature",
  "properties": {
    "gn:admin1_code":"11",
    "gn:asciiname":"Qingshan'ao",
    "gn:country_code":"CN",
    "gn:dem":1199,
    "gn:feature_class":"P",
    "gn:feature_code":"PPL",
    "gn:name":"Qingshan\u2019ao",
    "gn:population":0,
    "gn:timezone":"Asia/Shanghai",
    "iso:country":"CN",
    "name:und_x_variant":[
        "Qingshan\u2019ao"
    ],
    "name:zho_x_preferred":[
        "\u9752\u5c71\u5773"
    ],
    "wof:name":"Qingshan'ao",
    "wof:placetype":"locality"
},
  "geometry": {"coordinates":[110.74778000000001,27.58389],"type":"Point"}
}