{
  "type": "Feature",
  "properties": {
    "gn:admin1_code":"26.0",
    "gn:asciiname":"Yangtiangou",
    "gn:country_code":"CN",
    "gn:dem":747,
    "gn:feature_class":"P",
    "gn:feature_code":"PPL",
    "gn:name":"Yangtiangou",
    "gn:population":0,
    "gn:timezone":"Asia/Shanghai",
    "iso:country":"CN",
    "name:und_x_variant":[
        "\u79e7\u7530\u6c9f"
    ],
    "wof:name":"Yangtiangou",
    "wof:placetype":"locality"
},
  "geometry": {"coordinates":[108.09322,33.24007],"type":"Point"}
}