{
  "type": "Feature",
  "properties": {
    "gn:admin1_code":"2.0",
    "gn:asciiname":"Pu'ai",
    "gn:country_code":"CN",
    "gn:dem":500,
    "gn:feature_class":"P",
    "gn:feature_code":"PPL",
    "gn:name":"Pu\u2019ai",
    "gn:population":0,
    "gn:timezone":"Asia/Shanghai",
    "iso:country":"CN",
    "name:zho_x_preferred":[
        "\u666e\u7231"
    ],
    "name:zho_x_variant":[
        "Pu\u2019ai"
    ],
    "wof:name":"Pu'ai",
    "wof:placetype":"locality"
},
  "geometry": {"coordinates":[119.76385000000001,28.62774000000001],"type":"Point"}
}