{
  "type": "Feature",
  "properties": {
    "gn:admin1_code":"6.0",
    "gn:asciiname":"Xiangride",
    "gn:country_code":"CN",
    "gn:dem":3086,
    "gn:feature_class":"P",
    "gn:feature_code":"PPL",
    "gn:name":"Xiangride",
    "gn:population":0,
    "gn:timezone":"Asia/Urumqi",
    "iso:country":"CN",
    "name:zho_x_preferred":[
        "\u9999\u65e5\u5fb7"
    ],
    "wof:name":"Xiangride",
    "wof:placetype":"locality"
},
  "geometry": {"coordinates":[97.85802,35.98579],"type":"Point"}
}