{
  "type": "Feature",
  "properties": {
    "gn:admin1_code":"19.0",
    "gn:asciiname":"Guadigou",
    "gn:country_code":"CN",
    "gn:dem":349,
    "gn:feature_class":"P",
    "gn:feature_code":"PPL",
    "gn:name":"Guadigou",
    "gn:population":0,
    "gn:timezone":"Asia/Shanghai",
    "iso:country":"CN",
    "name:und_x_variant":[
        "\u74dc\u5730\u6c9f"
    ],
    "wof:name":"Guadigou",
    "wof:placetype":"locality"
},
  "geometry": {"coordinates":[123.685,40.9174],"type":"Point"}
}