{
  "type": "Feature",
  "properties": {
    "gn:admin1_code":"32.0",
    "gn:asciiname":"Lianyucun",
    "gn:country_code":"CN",
    "gn:dem":370,
    "gn:feature_class":"P",
    "gn:feature_code":"PPL",
    "gn:name":"Lianyucun",
    "gn:population":0,
    "gn:timezone":"Asia/Shanghai",
    "iso:country":"CN",
    "name:zho_x_preferred":[
        "\u9ca2\u9c7c\u6751"
    ],
    "wof:name":"Lianyucun",
    "wof:placetype":"locality"
},
  "geometry": {"coordinates":[104.69338,29.97321],"type":"Point"}
}