{
  "type": "Feature",
  "properties": {
    "gn:admin1_code":"14.0",
    "gn:asciiname":"Mayingnong",
    "gn:country_code":"CN",
    "gn:dem":4051,
    "gn:feature_class":"P",
    "gn:feature_code":"PPL",
    "gn:name":"Mayingnong",
    "gn:population":0,
    "gn:timezone":"Asia/Urumqi",
    "iso:country":"CN",
    "name:zho_x_preferred":[
        "\u561b\u5e94\u5f04"
    ],
    "wof:name":"Mayingnong",
    "wof:placetype":"locality"
},
  "geometry": {"coordinates":[96.54889,31.56596],"type":"Point"}
}