{
  "type": "Feature",
  "properties": {
    "gn:admin1_code":"7",
    "gn:asciiname":"Shuangxi Famuchang",
    "gn:country_code":"CN",
    "gn:dem":308,
    "gn:feature_class":"P",
    "gn:feature_code":"PPLF",
    "gn:name":"Shuangxi Famuchang",
    "gn:population":0,
    "gn:timezone":"Asia/Shanghai",
    "iso:country":"CN",
    "wof:name":"Shuangxi Famuchang",
    "wof:placetype":"locality"
},
  "geometry": {"coordinates":[117.86861,26.33889000000001],"type":"Point"}
}