{
  "type": "Feature",
  "properties": {
    "gn:admin1_code":"6.0",
    "gn:asciiname":"Rangning Gongba",
    "gn:country_code":"CN",
    "gn:dem":3960,
    "gn:feature_class":"P",
    "gn:feature_code":"PPL",
    "gn:name":"Rangning Gongba",
    "gn:population":0,
    "gn:timezone":"Asia/Urumqi",
    "iso:country":"CN",
    "name:zho_x_preferred":[
        "\u8ba9\u5b81\u8d21\u5df4"
    ],
    "wof:name":"Rangning Gongba",
    "wof:placetype":"locality"
},
  "geometry": {"coordinates":[96.92165,33.15097],"type":"Point"}
}