{
  "type": "Feature",
  "properties": {
    "gn:admin1_code":"26.0",
    "gn:asciiname":"Houcaogou",
    "gn:country_code":"CN",
    "gn:dem":1107,
    "gn:feature_class":"P",
    "gn:feature_code":"PPL",
    "gn:name":"Houcaogou",
    "gn:population":0,
    "gn:timezone":"Asia/Shanghai",
    "iso:country":"CN",
    "name:zho_x_preferred":[
        "\u540e\u69fd\u6c9f"
    ],
    "wof:name":"Houcaogou",
    "wof:placetype":"locality"
},
  "geometry": {"coordinates":[108.08687999999999,32.62407],"type":"Point"}
}