{
  "type": "Feature",
  "properties": {
    "gn:admin1_code":"9.0",
    "gn:asciiname":"Liuputou",
    "gn:country_code":"CN",
    "gn:dem":139,
    "gn:feature_class":"P",
    "gn:feature_code":"PPL",
    "gn:name":"Liuputou",
    "gn:population":0,
    "gn:timezone":"Asia/Shanghai",
    "iso:country":"CN",
    "name:zho_x_preferred":[
        "\u5218\u94fa\u5934"
    ],
    "wof:name":"Liuputou",
    "wof:placetype":"locality"
},
  "geometry": {"coordinates":[113.35046,34.9173],"type":"Point"}
}