{
  "type": "Feature",
  "properties": {
    "gn:admin1_code":"16.0",
    "gn:asciiname":"Nianjing",
    "gn:country_code":"CN",
    "gn:dem":837,
    "gn:feature_class":"P",
    "gn:feature_code":"PPL",
    "gn:name":"Nianjing",
    "gn:population":0,
    "gn:timezone":"Asia/Shanghai",
    "iso:country":"CN",
    "name:zho_x_preferred":[
        "\u5ff5\u5883"
    ],
    "wof:name":"Nianjing",
    "wof:placetype":"locality"
},
  "geometry": {"coordinates":[106.27200000000001,23.1838],"type":"Point"}
}