{
  "type": "Feature",
  "properties": {
    "gn:admin1_code":"9.0",
    "gn:asciiname":"Yiliu Wangzhuang",
    "gn:country_code":"CN",
    "gn:dem":53,
    "gn:feature_class":"P",
    "gn:feature_code":"PPL",
    "gn:name":"Yiliu Wangzhuang",
    "gn:population":0,
    "gn:timezone":"Asia/Shanghai",
    "iso:country":"CN",
    "name:zho_x_preferred":[
        "\u4e00\u516d\u738b\u5e84"
    ],
    "wof:name":"Yiliu Wangzhuang",
    "wof:placetype":"locality"
},
  "geometry": {"coordinates":[114.48900999999999,33.16782],"type":"Point"}
}