{
  "type": "Feature",
  "properties": {
    "gn:admin1_code":"11.0",
    "gn:asciiname":"Chengjiawan",
    "gn:country_code":"CN",
    "gn:dem":61,
    "gn:feature_class":"P",
    "gn:feature_code":"PPL",
    "gn:name":"Chengjiawan",
    "gn:population":0,
    "gn:timezone":"Asia/Shanghai",
    "iso:country":"CN",
    "name:zho_x_preferred":[
        "\u7a0b\u5bb6\u6e7e"
    ],
    "wof:name":"Chengjiawan",
    "wof:placetype":"locality"
},
  "geometry": {"coordinates":[113.24315,27.61879],"type":"Point"}
}