{
  "type": "Feature",
  "properties": {
    "gn:admin1_code":"12.0",
    "gn:asciiname":"Kuangjiawuchang",
    "gn:country_code":"CN",
    "gn:dem":1795,
    "gn:feature_class":"P",
    "gn:feature_code":"PPL",
    "gn:name":"Kuangjiawuchang",
    "gn:population":0,
    "gn:timezone":"Asia/Shanghai",
    "iso:country":"CN",
    "name:zho_x_preferred":[
        "\u5321\u5bb6\u5c4b\u573a"
    ],
    "wof:name":"Kuangjiawuchang",
    "wof:placetype":"locality"
},
  "geometry": {"coordinates":[110.58517000000001,30.74084],"type":"Point"}
}