{
  "type": "Feature",
  "properties": {
    "gn:admin1_code":"18",
    "gn:asciiname":"Tiankanjiao",
    "gn:country_code":"CN",
    "gn:dem":1945,
    "gn:feature_class":"P",
    "gn:feature_code":"PPL",
    "gn:name":"Tiankanjiao",
    "gn:population":0,
    "gn:timezone":"Asia/Shanghai",
    "iso:country":"CN",
    "name:zho_x_preferred":[
        "\u7530\u574e\u811a"
    ],
    "wof:name":"Tiankanjiao",
    "wof:placetype":"locality"
},
  "geometry": {"coordinates":[105.247,26.7944],"type":"Point"}
}