{
  "type": "Feature",
  "properties": {
    "gn:admin1_code":"7",
    "gn:asciiname":"Dameixi",
    "gn:country_code":"CN",
    "gn:dem":14,
    "gn:feature_class":"P",
    "gn:feature_code":"PPL",
    "gn:name":"Dameixi",
    "gn:population":0,
    "gn:timezone":"Asia/Shanghai",
    "iso:country":"CN",
    "name:zho_x_preferred":[
        "\u5927\u6885\u6eaa"
    ],
    "wof:name":"Dameixi",
    "wof:placetype":"locality"
},
  "geometry": {"coordinates":[117.62428,24.50211],"type":"Point"}
}