{
  "type": "Feature",
  "properties": {
    "gn:admin1_code":"25",
    "gn:asciiname":"Mengdian",
    "gn:country_code":"CN",
    "gn:dem":38,
    "gn:feature_class":"P",
    "gn:feature_code":"PPL",
    "gn:name":"Mengdian",
    "gn:population":0,
    "gn:timezone":"Asia/Shanghai",
    "iso:country":"CN",
    "name:zho_x_preferred":[
        "\u5b5f\u5e97"
    ],
    "wof:name":"Mengdian",
    "wof:placetype":"locality"
},
  "geometry": {"coordinates":[115.82186000000002,36.89351],"type":"Point"}
}