{
  "type": "Feature",
  "properties": {
    "gn:admin1_code":"32.0",
    "gn:asciiname":"Zhuangzi",
    "gn:country_code":"CN",
    "gn:dem":611,
    "gn:feature_class":"P",
    "gn:feature_code":"PPL",
    "gn:name":"Zhuangzi",
    "gn:population":0,
    "gn:timezone":"Asia/Shanghai",
    "iso:country":"CN",
    "name:oci_x_preferred":[
        "Zhuangzi"
    ],
    "name:pol_x_preferred":[
        "Zhuangzi"
    ],
    "name:ukr_x_preferred":[
        "\u0427\u0436\u0443\u0430\u043d-\u0446\u0437\u0438"
    ],
    "name:zho_x_preferred":[
        "\u5e84\u5b50"
    ],
    "wof:name":"Zhuangzi",
    "wof:placetype":"locality"
},
  "geometry": {"coordinates":[107.471,31.6168],"type":"Point"}
}