{
  "type": "Feature",
  "properties": {
    "gn:admin1_code":"18.0",
    "gn:asciiname":"Xindong",
    "gn:country_code":"CN",
    "gn:dem":786,
    "gn:feature_class":"P",
    "gn:feature_code":"PPL",
    "gn:name":"Xindong",
    "gn:population":0,
    "gn:timezone":"Asia/Shanghai",
    "iso:country":"CN",
    "name:zho_x_preferred":[
        "\u65b0\u6d1e"
    ],
    "wof:name":"Xindong",
    "wof:placetype":"locality"
},
  "geometry": {"coordinates":[109.01000000000001,26.1148],"type":"Point"}
}