{
  "type": "Feature",
  "properties": {
    "gn:admin1_code":"1.0",
    "gn:asciiname":"Yangwacun",
    "gn:country_code":"CN",
    "gn:dem":38,
    "gn:feature_class":"P",
    "gn:feature_code":"PPL",
    "gn:name":"Yangwacun",
    "gn:population":0,
    "gn:timezone":"Asia/Shanghai",
    "iso:country":"CN",
    "name:zho_x_preferred":[
        "\u6768\u6d3c\u6751"
    ],
    "wof:name":"Yangwacun",
    "wof:placetype":"locality"
},
  "geometry": {"coordinates":[115.30410999999999,32.84187],"type":"Point"}
}