{
  "type": "Feature",
  "properties": {
    "gn:admin1_code":"24.0",
    "gn:asciiname":"Nan'ao",
    "gn:country_code":"CN",
    "gn:dem":1222,
    "gn:feature_class":"P",
    "gn:feature_code":"PPL",
    "gn:name":"Nan\u2019ao",
    "gn:population":0,
    "gn:timezone":"Asia/Shanghai",
    "iso:country":"CN",
    "name:und_x_variant":[
        "Nan\u2019ao"
    ],
    "name:zho_x_preferred":[
        "\u5357\u51f9"
    ],
    "wof:name":"Nan'ao",
    "wof:placetype":"locality"
},
  "geometry": {"coordinates":[112.92270000000001,37.48825],"type":"Point"}
}