{
  "type": "Feature",
  "properties": {
    "gn:admin1_code":"4.0",
    "gn:asciiname":"Shangpei",
    "gn:country_code":"CN",
    "gn:dem":11,
    "gn:feature_class":"P",
    "gn:feature_code":"PPLA4",
    "gn:name":"Shangpei",
    "gn:population":0,
    "gn:timezone":"Asia/Shanghai",
    "iso:country":"CN",
    "name:und_x_variant":[
        "Shangpei Zhen",
        "\u4e0a\u6c9b\u9547",
        "Shangpei"
    ],
    "name:zho_x_preferred":[
        "\u4e0a\u6c9b"
    ],
    "wof:name":"Shangpei",
    "wof:placetype":"locality"
},
  "geometry": {"coordinates":[119.21768,31.47435],"type":"Point"}
}