{
  "type": "Feature",
  "properties": {
    "gn:admin1_code":"12.0",
    "gn:asciiname":"Qilichong",
    "gn:country_code":"CN",
    "gn:dem":124,
    "gn:feature_class":"P",
    "gn:feature_code":"PPL",
    "gn:name":"Qilichong",
    "gn:population":0,
    "gn:timezone":"Asia/Shanghai",
    "iso:country":"CN",
    "name:zho_x_preferred":[
        "\u4e03\u91cc\u51b2"
    ],
    "wof:name":"Qilichong",
    "wof:placetype":"locality"
},
  "geometry": {"coordinates":[113.70631000000002,32.31776],"type":"Point"}
}