{
  "type": "Feature",
  "properties": {
    "gn:admin1_code":"25",
    "gn:asciiname":"Shanghuang'an",
    "gn:country_code":"CN",
    "gn:dem":434,
    "gn:feature_class":"P",
    "gn:feature_code":"PPL",
    "gn:name":"Shanghuang\u2019an",
    "gn:population":0,
    "gn:timezone":"Asia/Shanghai",
    "iso:country":"CN",
    "name:und_x_variant":[
        "Shanghuang\u2019an"
    ],
    "name:zho_x_preferred":[
        "\u4e0a\u9ec4\u5b89"
    ],
    "wof:name":"Shanghuang'an",
    "wof:placetype":"locality"
},
  "geometry": {"coordinates":[118.31699999999999,36.1292],"type":"Point"}
}