{
  "type": "Feature",
  "properties": {
    "gn:admin1_code":"12.0",
    "gn:asciiname":"Shilichong",
    "gn:country_code":"CN",
    "gn:dem":91,
    "gn:feature_class":"P",
    "gn:feature_code":"PPL",
    "gn:name":"Shilichong",
    "gn:population":0,
    "gn:timezone":"Asia/Shanghai",
    "iso:country":"CN",
    "name:zho_x_preferred":[
        "\u77f3\u91cc\u51b2"
    ],
    "wof:name":"Shilichong",
    "wof:placetype":"locality"
},
  "geometry": {"coordinates":[113.90092,29.37101],"type":"Point"}
}