{
  "type": "Feature",
  "properties": {
    "gn:admin1_code":"5.0",
    "gn:asciiname":"Xixinglong",
    "gn:country_code":"CN",
    "gn:dem":154,
    "gn:feature_class":"P",
    "gn:feature_code":"PPL",
    "gn:name":"Xixinglong",
    "gn:population":0,
    "gn:timezone":"Asia/Shanghai",
    "iso:country":"CN",
    "name:zho_x_preferred":[
        "\u897f\u5174\u9686"
    ],
    "wof:name":"Xixinglong",
    "wof:placetype":"locality"
},
  "geometry": {"coordinates":[122.76031,44.813],"type":"Point"}
}