{
  "type": "Feature",
  "properties": {
    "gn:admin1_code":"11.0",
    "gn:asciiname":"Shadeqiao",
    "gn:country_code":"CN",
    "gn:dem":146,
    "gn:feature_class":"P",
    "gn:feature_code":"PPL",
    "gn:name":"Shadeqiao",
    "gn:population":0,
    "gn:timezone":"Asia/Shanghai",
    "iso:country":"CN",
    "name:zho_x_preferred":[
        "\u6c99\u5fb7\u6865"
    ],
    "wof:name":"Shadeqiao",
    "wof:placetype":"locality"
},
  "geometry": {"coordinates":[113.54170000000001,28.22725],"type":"Point"}
}