{
  "type": "Feature",
  "properties": {
    "gn:admin1_code":"3",
    "gn:asciiname":"Paixi",
    "gn:country_code":"CN",
    "gn:dem":227,
    "gn:feature_class":"P",
    "gn:feature_code":"PPL",
    "gn:name":"Paixi",
    "gn:population":0,
    "gn:timezone":"Asia/Shanghai",
    "iso:country":"CN",
    "name:zho_x_preferred":[
        "\u6392\u6eaa"
    ],
    "wof:name":"Paixi",
    "wof:placetype":"locality"
},
  "geometry": {"coordinates":[114.315,26.1755],"type":"Point"}
}