{
  "type": "Feature",
  "properties": {
    "gn:admin1_code":"30.0",
    "gn:asciiname":"Shanglilangcun",
    "gn:country_code":"CN",
    "gn:dem":72,
    "gn:feature_class":"P",
    "gn:feature_code":"PPL",
    "gn:name":"Shanglilangcun",
    "gn:population":0,
    "gn:timezone":"Asia/Shanghai",
    "iso:country":"CN",
    "name:zho_x_preferred":[
        "\u4e0a\u674e\u6717\u6751"
    ],
    "wof:name":"Shanglilangcun",
    "wof:placetype":"locality"
},
  "geometry": {"coordinates":[114.11539999999999,22.65546],"type":"Point"}
}