{
  "type": "Feature",
  "properties": {
    "gn:admin1_code":"4.0",
    "gn:asciiname":"Suhecun",
    "gn:country_code":"CN",
    "gn:dem":3,
    "gn:feature_class":"P",
    "gn:feature_code":"PPL",
    "gn:name":"Suhecun",
    "gn:population":0,
    "gn:timezone":"Asia/Shanghai",
    "iso:country":"CN",
    "name:zho_x_preferred":[
        "\u82cf\u4f55\u6751"
    ],
    "wof:name":"Suhecun",
    "wof:placetype":"locality"
},
  "geometry": {"coordinates":[120.44287,32.8855],"type":"Point"}
}