{
  "type": "Feature",
  "properties": {
    "gn:admin1_code":"18",
    "gn:asciiname":"Yanjiaoxia",
    "gn:country_code":"CN",
    "gn:dem":665,
    "gn:feature_class":"P",
    "gn:feature_code":"PPL",
    "gn:name":"Yanjiaoxia",
    "gn:population":0,
    "gn:timezone":"Asia/Shanghai",
    "iso:country":"CN",
    "name:zho_x_preferred":[
        "\u5ca9\u811a\u4e0b"
    ],
    "wof:name":"Yanjiaoxia",
    "wof:placetype":"locality"
},
  "geometry": {"coordinates":[108.20999999999999,27.8382],"type":"Point"}
}