{
  "type": "Feature",
  "properties": {
    "gn:admin1_code":"25.0",
    "gn:asciiname":"Chuxiancun",
    "gn:country_code":"CN",
    "gn:dem":75,
    "gn:feature_class":"P",
    "gn:feature_code":"PPL",
    "gn:name":"Chuxiancun",
    "gn:population":0,
    "gn:timezone":"Asia/Shanghai",
    "iso:country":"CN",
    "name:zho_x_preferred":[
        "\u695a\u5c98\u6751"
    ],
    "wof:name":"Chuxiancun",
    "wof:placetype":"locality"
},
  "geometry": {"coordinates":[121.82958000000001,37.2284],"type":"Point"}
}