{
  "type": "Feature",
  "properties": {
    "gn:admin1_code":"2.0",
    "gn:asciiname":"Nanniuchang",
    "gn:country_code":"CN",
    "gn:dem":7,
    "gn:feature_class":"P",
    "gn:feature_code":"PPLF",
    "gn:name":"Nanniuchang",
    "gn:population":0,
    "gn:timezone":"Asia/Shanghai",
    "iso:country":"CN",
    "name:und_x_variant":[
        "\u5357\u725b\u573a"
    ],
    "wof:name":"Nanniuchang",
    "wof:placetype":"locality"
},
  "geometry": {"coordinates":[121.13397999999999,30.63204],"type":"Point"}
}