{
  "type": "Feature",
  "properties": {
    "gn:admin1_code":"19.0",
    "gn:asciiname":"Wangjia Datun",
    "gn:country_code":"CN",
    "gn:dem":86,
    "gn:feature_class":"P",
    "gn:feature_code":"PPL",
    "gn:name":"Wangjia Datun",
    "gn:population":0,
    "gn:timezone":"Asia/Shanghai",
    "iso:country":"CN",
    "name:zho_x_preferred":[
        "\u738b\u5bb6\u5927\u5c6f"
    ],
    "wof:name":"Wangjia Datun",
    "wof:placetype":"locality"
},
  "geometry": {"coordinates":[122.69456,39.82063],"type":"Point"}
}