{
  "type": "Feature",
  "properties": {
    "gn:admin1_code":"19.0",
    "gn:asciiname":"Nancha",
    "gn:country_code":"CN",
    "gn:dem":298,
    "gn:feature_class":"P",
    "gn:feature_code":"PPL",
    "gn:name":"Nancha",
    "gn:population":0,
    "gn:timezone":"Asia/Shanghai",
    "iso:country":"CN",
    "name:und_x_variant":[
        "\u5357\u5c94"
    ],
    "wof:name":"Nancha",
    "wof:placetype":"locality"
},
  "geometry": {"coordinates":[124.13418,41.63045],"type":"Point"}
}