{
  "type": "Feature",
  "properties": {
    "gn:admin1_code":"29",
    "gn:asciiname":"Jiancaoying",
    "gn:country_code":"CN",
    "gn:dem":1912,
    "gn:feature_class":"P",
    "gn:feature_code":"PPL",
    "gn:name":"Jiancaoying",
    "gn:population":0,
    "gn:timezone":"Asia/Shanghai",
    "iso:country":"CN",
    "name:zho_x_preferred":[
        "\u67a7\u69fd\u8425"
    ],
    "wof:name":"Jiancaoying",
    "wof:placetype":"locality"
},
  "geometry": {"coordinates":[102.371,24.6751],"type":"Point"}
}