{
  "type": "Feature",
  "properties": {
    "gn:admin1_code":"18",
    "gn:asciiname":"Qingshui",
    "gn:country_code":"CN",
    "gn:dem":2059,
    "gn:feature_class":"P",
    "gn:feature_code":"PPL",
    "gn:name":"Qingshui",
    "gn:population":0,
    "gn:timezone":"Asia/Shanghai",
    "iso:country":"CN",
    "name:ceb_x_preferred":[
        "Qingshui"
    ],
    "name:deu_x_preferred":[
        "Qingshui"
    ],
    "wof:name":"Qingshui",
    "wof:placetype":"locality"
},
  "geometry": {"coordinates":[104.46666999999999,25.95],"type":"Point"}
}