{
  "type": "Feature",
  "properties": {
    "gn:admin1_code":"13.0",
    "gn:asciiname":"Langan",
    "gn:country_code":"CN",
    "gn:dem":3128,
    "gn:feature_class":"P",
    "gn:feature_code":"PPL",
    "gn:name":"Langan",
    "gn:population":0,
    "gn:timezone":"Asia/Shanghai",
    "iso:country":"CN",
    "name:und_x_variant":[
        "\u5170\u5e72"
    ],
    "wof:name":"Langan",
    "wof:placetype":"locality"
},
  "geometry": {"coordinates":[76.01092,38.40503],"type":"Point"}
}