{
  "type": "Feature",
  "properties": {
    "gn:admin1_code":"15.0",
    "gn:asciiname":"Wenjia Gougou",
    "gn:country_code":"CN",
    "gn:dem":1428,
    "gn:feature_class":"P",
    "gn:feature_code":"PPL",
    "gn:name":"Wenjia Gougou",
    "gn:population":0,
    "gn:timezone":"Asia/Shanghai",
    "iso:country":"CN",
    "name:zho_x_preferred":[
        "\u6e29\u5bb6\u6c9f\u6c9f"
    ],
    "wof:name":"Wenjia Gougou",
    "wof:placetype":"locality"
},
  "geometry": {"coordinates":[106.947,35.2346],"type":"Point"}
}