{
  "type": "Feature",
  "properties": {
    "gn:admin1_code":"8.0",
    "gn:asciiname":"Xitunzi",
    "gn:country_code":"CN",
    "gn:dem":468,
    "gn:feature_class":"P",
    "gn:feature_code":"PPL",
    "gn:name":"Xitunzi",
    "gn:population":0,
    "gn:timezone":"Asia/Shanghai",
    "iso:country":"CN",
    "name:zho_x_preferred":[
        "\u897f\u5c6f\u5b50"
    ],
    "wof:name":"Xitunzi",
    "wof:placetype":"locality"
},
  "geometry": {"coordinates":[130.1995,44.53077],"type":"Point"}
}