{
  "type": "Feature",
  "properties": {
    "gn:admin1_code":"30",
    "gn:asciiname":"Jijipo",
    "gn:country_code":"CN",
    "gn:dem":15,
    "gn:feature_class":"P",
    "gn:feature_code":"PPL",
    "gn:name":"Jijipo",
    "gn:population":0,
    "gn:timezone":"Asia/Shanghai",
    "iso:country":"CN",
    "name:zho_x_preferred":[
        "\u6025\u9e21\u5761"
    ],
    "wof:name":"Jijipo",
    "wof:placetype":"locality"
},
  "geometry": {"coordinates":[111.73390999999999,21.98181],"type":"Point"}
}