{
  "type": "Feature",
  "properties": {
    "gn:admin1_code":"11",
    "gn:asciiname":"Ceyuan",
    "gn:country_code":"CN",
    "gn:dem":690,
    "gn:feature_class":"P",
    "gn:feature_code":"PPL",
    "gn:name":"Ceyuan",
    "gn:population":0,
    "gn:timezone":"Asia/Shanghai",
    "iso:country":"CN",
    "wof:name":"Ceyuan",
    "wof:placetype":"locality"
},
  "geometry": {"coordinates":[113.90000000000001,26.35],"type":"Point"}
}