{
  "type": "Feature",
  "properties": {
    "gn:admin1_code":"30.0",
    "gn:asciiname":"Xiangchong",
    "gn:country_code":"CN",
    "gn:dem":5,
    "gn:feature_class":"P",
    "gn:feature_code":"PPL",
    "gn:name":"Xiangchong",
    "gn:population":0,
    "gn:timezone":"Asia/Shanghai",
    "iso:country":"CN",
    "name:zho_x_preferred":[
        "\u964d\u6c96"
    ],
    "wof:name":"Xiangchong",
    "wof:placetype":"locality"
},
  "geometry": {"coordinates":[112.69762,22.33188],"type":"Point"}
}