{
  "type": "Feature",
  "properties": {
    "gn:admin1_code":"11.0",
    "gn:asciiname":"Pingshanpo",
    "gn:country_code":"CN",
    "gn:dem":320,
    "gn:feature_class":"P",
    "gn:feature_code":"PPL",
    "gn:name":"Pingshanpo",
    "gn:population":0,
    "gn:timezone":"Asia/Shanghai",
    "iso:country":"CN",
    "name:zho_x_preferred":[
        "\u576a\u5c71\u5761"
    ],
    "wof:name":"Pingshanpo",
    "wof:placetype":"locality"
},
  "geometry": {"coordinates":[109.74062000000001,28.29404000000001],"type":"Point"}
}