{
  "type": "Feature",
  "properties": {
    "gn:admin1_code":"2.0",
    "gn:asciiname":"Luojiatou",
    "gn:country_code":"CN",
    "gn:dem":10,
    "gn:feature_class":"P",
    "gn:feature_code":"PPL",
    "gn:name":"Luojiatou",
    "gn:population":0,
    "gn:timezone":"Asia/Shanghai",
    "iso:country":"CN",
    "name:und_x_variant":[
        "\u7f57\u5bb6\u5934"
    ],
    "wof:name":"Luojiatou",
    "wof:placetype":"locality"
},
  "geometry": {"coordinates":[119.89624999999999,30.37305],"type":"Point"}
}