{
  "type": "Feature",
  "properties": {
    "gn:admin1_code":"11",
    "gn:asciiname":"Nanmuchong",
    "gn:country_code":"CN",
    "gn:dem":127,
    "gn:feature_class":"P",
    "gn:feature_code":"PPL",
    "gn:name":"Nanmuchong",
    "gn:population":0,
    "gn:timezone":"Asia/Shanghai",
    "iso:country":"CN",
    "name:zho_x_preferred":[
        "\u6960\u6728\u51b2"
    ],
    "wof:name":"Nanmuchong",
    "wof:placetype":"locality"
},
  "geometry": {"coordinates":[112.49155,26.68372],"type":"Point"}
}