{
  "type": "Feature",
  "properties": {
    "gn:admin1_code":"5.0",
    "gn:asciiname":"Yinchang Liudui",
    "gn:country_code":"CN",
    "gn:dem":465,
    "gn:feature_class":"P",
    "gn:feature_code":"PPLF",
    "gn:name":"Yinchang Liudui",
    "gn:population":0,
    "gn:timezone":"Asia/Shanghai",
    "iso:country":"CN",
    "name:zho_x_preferred":[
        "\u94f6\u5382\u516d\u961f"
    ],
    "wof:name":"Yinchang Liudui",
    "wof:placetype":"locality"
},
  "geometry": {"coordinates":[126.01094999999999,41.69581],"type":"Point"}
}