{
  "type": "Feature",
  "properties": {
    "gn:admin1_code":"19.0",
    "gn:asciiname":"Xiamiaocun",
    "gn:country_code":"CN",
    "gn:dem":109,
    "gn:feature_class":"P",
    "gn:feature_code":"PPL",
    "gn:name":"Xiamiaocun",
    "gn:population":0,
    "gn:timezone":"Asia/Shanghai",
    "iso:country":"CN",
    "name:zho_x_preferred":[
        "\u4e0b\u5e99\u6751"
    ],
    "wof:name":"Xiamiaocun",
    "wof:placetype":"locality"
},
  "geometry": {"coordinates":[122.16200000000001,39.6898],"type":"Point"}
}