{
  "type": "Feature",
  "properties": {
    "gn:admin1_code":"12.0",
    "gn:asciiname":"Laoguandu",
    "gn:country_code":"CN",
    "gn:dem":22,
    "gn:feature_class":"P",
    "gn:feature_code":"PPL",
    "gn:name":"Laoguandu",
    "gn:population":0,
    "gn:timezone":"Asia/Shanghai",
    "iso:country":"CN",
    "name:zho_x_preferred":[
        "\u8001\u5b98\u6e21"
    ],
    "wof:name":"Laoguandu",
    "wof:placetype":"locality"
},
  "geometry": {"coordinates":[113.91538,30.50926],"type":"Point"}
}