{
  "type": "Feature",
  "properties": {
    "gn:admin1_code":"30.0",
    "gn:asciiname":"Niqiutang",
    "gn:country_code":"CN",
    "gn:dem":805,
    "gn:feature_class":"P",
    "gn:feature_code":"PPL",
    "gn:name":"Niqiutang",
    "gn:population":0,
    "gn:timezone":"Asia/Shanghai",
    "iso:country":"CN",
    "name:zho_x_preferred":[
        "Niqiutang"
    ],
    "name:zho_x_variant":[
        "\u6ce5\u79cb\u5858"
    ],
    "wof:name":"Niqiutang",
    "wof:placetype":"locality"
},
  "geometry": {"coordinates":[113.09246,25.03042],"type":"Point"}
}