{
  "type": "Feature",
  "properties": {
    "gn:admin1_code":"12.0",
    "gn:asciiname":"Shatangwan",
    "gn:country_code":"CN",
    "gn:dem":106,
    "gn:feature_class":"P",
    "gn:feature_code":"PPL",
    "gn:name":"Shatangwan",
    "gn:population":0,
    "gn:timezone":"Asia/Shanghai",
    "iso:country":"CN",
    "name:und_x_variant":[
        "\u6c99\u5858\u5846"
    ],
    "wof:name":"Shatangwan",
    "wof:placetype":"locality"
},
  "geometry": {"coordinates":[115.37712999999999,30.34527000000001],"type":"Point"}
}