{
  "type": "Feature",
  "properties": {
    "gn:admin1_code":"5.0",
    "gn:asciiname":"Zhuangjiacun",
    "gn:country_code":"CN",
    "gn:dem":231,
    "gn:feature_class":"P",
    "gn:feature_code":"PPL",
    "gn:name":"Zhuangjiacun",
    "gn:population":0,
    "gn:timezone":"Asia/Shanghai",
    "iso:country":"CN",
    "name:zho_x_preferred":[
        "\u5e84\u5bb6\u6751"
    ],
    "wof:name":"Zhuangjiacun",
    "wof:placetype":"locality"
},
  "geometry": {"coordinates":[125.03977999999999,43.3427],"type":"Point"}
}