{
  "type": "Feature",
  "properties": {
    "gn:admin1_code":"3.0",
    "gn:asciiname":"Yanwocun",
    "gn:country_code":"CN",
    "gn:dem":51,
    "gn:feature_class":"P",
    "gn:feature_code":"PPL",
    "gn:name":"Yanwocun",
    "gn:population":0,
    "gn:timezone":"Asia/Shanghai",
    "iso:country":"CN",
    "name:und_x_variant":[
        "\u71d5\u7a9d\u6751"
    ],
    "wof:name":"Yanwocun",
    "wof:placetype":"locality"
},
  "geometry": {"coordinates":[115.60328,28.53102],"type":"Point"}
}