{
  "type": "Feature",
  "properties": {
    "gn:admin1_code":"18",
    "gn:asciiname":"Shangnuoge",
    "gn:country_code":"CN",
    "gn:dem":1574,
    "gn:feature_class":"P",
    "gn:feature_code":"PPL",
    "gn:name":"Shangnuoge",
    "gn:population":0,
    "gn:timezone":"Asia/Shanghai",
    "iso:country":"CN",
    "name:zho_x_preferred":[
        "\u4e0a\u7cef\u683c"
    ],
    "wof:name":"Shangnuoge",
    "wof:placetype":"locality"
},
  "geometry": {"coordinates":[104.797,25.3779],"type":"Point"}
}