{
  "type": "Feature",
  "properties": {
    "gn:admin1_code":"4.0",
    "gn:asciiname":"Shantangjie",
    "gn:country_code":"CN",
    "gn:dem":5,
    "gn:feature_class":"P",
    "gn:feature_code":"PPL",
    "gn:name":"Shantangjie",
    "gn:population":0,
    "gn:timezone":"Asia/Shanghai",
    "iso:country":"CN",
    "name:zho_x_preferred":[
        "Shantangjie"
    ],
    "name:zho_x_variant":[
        "\u5c71\u5858\u8857"
    ],
    "wof:name":"Shantangjie",
    "wof:placetype":"locality"
},
  "geometry": {"coordinates":[120.62409,30.92081],"type":"Point"}
}