{
  "type": "Feature",
  "properties": {
    "gn:admin1_code":"12.0",
    "gn:asciiname":"Zhangshuwan",
    "gn:country_code":"CN",
    "gn:dem":125,
    "gn:feature_class":"P",
    "gn:feature_code":"PPL",
    "gn:name":"Zhangshuwan",
    "gn:population":0,
    "gn:timezone":"Asia/Shanghai",
    "iso:country":"CN",
    "name:und_x_variant":[
        "\u6a1f\u6811\u5846"
    ],
    "wof:name":"Zhangshuwan",
    "wof:placetype":"locality"
},
  "geometry": {"coordinates":[115.19853999999999,30.87894],"type":"Point"}
}