{
  "type": "Feature",
  "properties": {
    "gn:admin1_code":"7",
    "gn:asciiname":"Chitouting",
    "gn:country_code":"CN",
    "gn:dem":405,
    "gn:feature_class":"P",
    "gn:feature_code":"PPL",
    "gn:name":"Chitouting",
    "gn:population":0,
    "gn:timezone":"Asia/Shanghai",
    "iso:country":"CN",
    "name:zho_x_preferred":[
        "\u6c60\u5934\u4ead"
    ],
    "wof:name":"Chitouting",
    "wof:placetype":"locality"
},
  "geometry": {"coordinates":[118.98159,25.72062],"type":"Point"}
}