{
  "type": "Feature",
  "properties": {
    "gn:admin1_code":"7",
    "gn:asciiname":"Zhuanglin",
    "gn:country_code":"CN",
    "gn:dem":16,
    "gn:feature_class":"P",
    "gn:feature_code":"PPL",
    "gn:name":"Zhuanglin",
    "gn:population":0,
    "gn:timezone":"Asia/Shanghai",
    "iso:country":"CN",
    "name:zho_x_preferred":[
        "\u5e84\u6797"
    ],
    "wof:name":"Zhuanglin",
    "wof:placetype":"locality"
},
  "geometry": {"coordinates":[117.83262000000001,24.34015],"type":"Point"}
}