{
  "type": "Feature",
  "properties": {
    "gn:admin1_code":"10",
    "gn:asciiname":"Zhongyicun",
    "gn:cc2":"CN",
    "gn:country_code":"CN",
    "gn:dem":1359,
    "gn:feature_class":"P",
    "gn:feature_code":"PPL",
    "gn:name":"Zhongyicun",
    "gn:population":0,
    "gn:timezone":"Asia/Shanghai",
    "iso:country":"CN",
    "name:und_x_variant":[
        "Chong-i",
        "Zhongyi",
        "Chung-i-ts\u2019un",
        "Zhongyicun"
    ],
    "wof:name":"Zhongyicun",
    "wof:placetype":"locality"
},
  "geometry": {"coordinates":[114.46778,41.6475],"type":"Point"}
}