{
  "type": "Feature",
  "properties": {
    "gn:admin1_code":"26.0",
    "gn:asciiname":"Dabuling",
    "gn:country_code":"CN",
    "gn:dem":748,
    "gn:feature_class":"P",
    "gn:feature_code":"PPL",
    "gn:name":"Dabuling",
    "gn:population":0,
    "gn:timezone":"Asia/Shanghai",
    "iso:country":"CN",
    "name:zho_x_preferred":[
        "\u6253\u5821\u5cad"
    ],
    "wof:name":"Dabuling",
    "wof:placetype":"locality"
},
  "geometry": {"coordinates":[107.12497999999999,32.82348],"type":"Point"}
}