{
  "type": "Feature",
  "properties": {
    "gn:admin1_code":"19.0",
    "gn:asciiname":"Banchangyucun",
    "gn:country_code":"CN",
    "gn:dem":416,
    "gn:feature_class":"P",
    "gn:feature_code":"PPL",
    "gn:name":"Banchangyucun",
    "gn:population":0,
    "gn:timezone":"Asia/Shanghai",
    "iso:country":"CN",
    "name:zho_x_preferred":[
        "\u677f\u957f\u5cea\u6751"
    ],
    "wof:name":"Banchangyucun",
    "wof:placetype":"locality"
},
  "geometry": {"coordinates":[122.968,40.43156],"type":"Point"}
}