{
  "type": "Feature",
  "properties": {
    "gn:admin1_code":"29",
    "gn:asciiname":"Hamazhai",
    "gn:country_code":"CN",
    "gn:dem":2220,
    "gn:feature_class":"P",
    "gn:feature_code":"PPL",
    "gn:name":"Hamazhai",
    "gn:population":0,
    "gn:timezone":"Asia/Shanghai",
    "iso:country":"CN",
    "name:und_x_variant":[
        "\u54c8\u9a6c\u5be8"
    ],
    "wof:name":"Hamazhai",
    "wof:placetype":"locality"
},
  "geometry": {"coordinates":[104.00054,25.43149],"type":"Point"}
}