{
  "type": "Feature",
  "properties": {
    "gn:admin1_code":"30.0",
    "gn:asciiname":"Baishuitang",
    "gn:country_code":"CN",
    "gn:dem":146,
    "gn:feature_class":"P",
    "gn:feature_code":"PPL",
    "gn:name":"Baishuitang",
    "gn:population":0,
    "gn:timezone":"Asia/Shanghai",
    "iso:country":"CN",
    "name:zho_x_preferred":[
        "Baishuitang"
    ],
    "name:zho_x_variant":[
        "\u767d\u6c34\u5858"
    ],
    "wof:name":"Baishuitang",
    "wof:placetype":"locality"
},
  "geometry": {"coordinates":[114.91865,24.19503],"type":"Point"}
}