{
  "type": "Feature",
  "properties": {
    "gn:admin1_code":"29.0",
    "gn:asciiname":"Yangjiufang",
    "gn:country_code":"CN",
    "gn:dem":1690,
    "gn:feature_class":"P",
    "gn:feature_code":"PPL",
    "gn:name":"Yangjiufang",
    "gn:population":0,
    "gn:timezone":"Asia/Shanghai",
    "iso:country":"CN",
    "name:zho_x_preferred":[
        "\u7f8a\u53a9\u623f"
    ],
    "wof:name":"Yangjiufang",
    "wof:placetype":"locality"
},
  "geometry": {"coordinates":[100.90300000000001,26.0973],"type":"Point"}
}