{
  "type": "Feature",
  "properties": {
    "gn:admin1_code":"18.0",
    "gn:asciiname":"Fengxiang",
    "gn:country_code":"CN",
    "gn:dem":888,
    "gn:feature_class":"P",
    "gn:feature_code":"PPL",
    "gn:name":"Fengxiang",
    "gn:population":0,
    "gn:timezone":"Asia/Shanghai",
    "iso:country":"CN",
    "wof:name":"Fengxiang",
    "wof:placetype":"locality"
},
  "geometry": {"coordinates":[108.30667,27.48389],"type":"Point"}
}