{
  "type": "Feature",
  "properties": {
    "gn:admin1_code":"19.0",
    "gn:asciiname":"Houxiujiangcun",
    "gn:country_code":"CN",
    "gn:dem":15,
    "gn:feature_class":"P",
    "gn:feature_code":"PPL",
    "gn:name":"Houxiujiangcun",
    "gn:population":0,
    "gn:timezone":"Asia/Shanghai",
    "iso:country":"CN",
    "name:zho_x_preferred":[
        "\u540e\u7ee3\u6c5f\u6751"
    ],
    "wof:name":"Houxiujiangcun",
    "wof:placetype":"locality"
},
  "geometry": {"coordinates":[123.04131,41.29035],"type":"Point"}
}