{
  "type": "Feature",
  "properties": {
    "gn:admin1_code":"2.0",
    "gn:asciiname":"Wangchuantou",
    "gn:country_code":"CN",
    "gn:dem":5,
    "gn:feature_class":"P",
    "gn:feature_code":"PPL",
    "gn:name":"Wangchuantou",
    "gn:population":0,
    "gn:timezone":"Asia/Shanghai",
    "iso:country":"CN",
    "name:und_x_variant":[
        "\u7f51\u8239\u5934"
    ],
    "wof:name":"Wangchuantou",
    "wof:placetype":"locality"
},
  "geometry": {"coordinates":[120.99499,30.73843],"type":"Point"}
}