{
  "type": "Feature",
  "properties": {
    "gn:admin1_code":"16.0",
    "gn:asciiname":"Ping'en",
    "gn:country_code":"CN",
    "gn:dem":946,
    "gn:feature_class":"P",
    "gn:feature_code":"PPL",
    "gn:name":"Ping\u2019en",
    "gn:population":0,
    "gn:timezone":"Asia/Shanghai",
    "iso:country":"CN",
    "name:und_x_variant":[
        "Ping\u2019en"
    ],
    "name:zho_x_preferred":[
        "\u5e73\u6069"
    ],
    "wof:name":"Ping'en",
    "wof:placetype":"locality"
},
  "geometry": {"coordinates":[105.95999999999999,23.2824],"type":"Point"}
}