{
  "type": "Feature",
  "properties": {
    "gn:admin1_code":"18",
    "gn:asciiname":"Huangkengba",
    "gn:country_code":"CN",
    "gn:dem":1208,
    "gn:feature_class":"P",
    "gn:feature_code":"PPL",
    "gn:name":"Huangkengba",
    "gn:population":0,
    "gn:timezone":"Asia/Shanghai",
    "iso:country":"CN",
    "name:zho_x_preferred":[
        "\u9ec4\u5751\u575d"
    ],
    "wof:name":"Huangkengba",
    "wof:placetype":"locality"
},
  "geometry": {"coordinates":[108.099,28.6184],"type":"Point"}
}