{
  "type": "Feature",
  "properties": {
    "gn:admin1_code":"18.0",
    "gn:asciiname":"Jiaodong",
    "gn:country_code":"CN",
    "gn:dem":620,
    "gn:feature_class":"P",
    "gn:feature_code":"PPL",
    "gn:name":"Jiaodong",
    "gn:population":0,
    "gn:timezone":"Asia/Shanghai",
    "iso:country":"CN",
    "name:zho_x_preferred":[
        "\u768e\u6d1e"
    ],
    "wof:name":"Jiaodong",
    "wof:placetype":"locality"
},
  "geometry": {"coordinates":[109.128,26.5482],"type":"Point"}
}