{
  "type": "Feature",
  "properties": {
    "gn:admin1_code":"1.0",
    "gn:asciiname":"Xiachuancun",
    "gn:country_code":"CN",
    "gn:dem":91,
    "gn:feature_class":"P",
    "gn:feature_code":"PPL",
    "gn:name":"Xiachuancun",
    "gn:population":0,
    "gn:timezone":"Asia/Shanghai",
    "iso:country":"CN",
    "name:zho_x_preferred":[
        "\u5ce1\u5ddd\u6751"
    ],
    "wof:name":"Xiachuancun",
    "wof:placetype":"locality"
},
  "geometry": {"coordinates":[117.60281999999999,30.47009000000001],"type":"Point"}
}