{
  "type": "Feature",
  "properties": {
    "gn:admin1_code":"7.0",
    "gn:asciiname":"Huangbei",
    "gn:country_code":"CN",
    "gn:dem":425,
    "gn:feature_class":"P",
    "gn:feature_code":"PPL",
    "gn:name":"Huangbei",
    "gn:population":0,
    "gn:timezone":"Asia/Shanghai",
    "iso:country":"CN",
    "name:und_x_variant":[
        "\u9ec4\u9642"
    ],
    "name:zho_x_preferred":[
        "\u9ec4\u9642"
    ],
    "wof:name":"Huangbei",
    "wof:placetype":"locality"
},
  "geometry": {"coordinates":[116.28224,25.77941],"type":"Point"}
}