{
  "type": "Feature",
  "properties": {
    "gn:admin1_code":"16.0",
    "gn:asciiname":"Sheyi",
    "gn:country_code":"CN",
    "gn:dem":308,
    "gn:feature_class":"P",
    "gn:feature_code":"PPL",
    "gn:name":"Sheyi",
    "gn:population":0,
    "gn:timezone":"Asia/Shanghai",
    "iso:country":"CN",
    "name:zho_x_preferred":[
        "\u793e\u5b9c"
    ],
    "wof:name":"Sheyi",
    "wof:placetype":"locality"
},
  "geometry": {"coordinates":[109.48399999999999,24.9521],"type":"Point"}
}