{
  "type": "Feature",
  "properties": {
    "gn:admin1_code":"26.0",
    "gn:asciiname":"Wowodian",
    "gn:country_code":"CN",
    "gn:dem":1515,
    "gn:feature_class":"P",
    "gn:feature_code":"PPL",
    "gn:name":"Wowodian",
    "gn:population":0,
    "gn:timezone":"Asia/Shanghai",
    "iso:country":"CN",
    "name:und_x_variant":[
        "\u7a9d\u7a9d\u5e97"
    ],
    "wof:name":"Wowodian",
    "wof:placetype":"locality"
},
  "geometry": {"coordinates":[107.07120999999999,33.65956],"type":"Point"}
}