{
  "type": "Feature",
  "properties": {
    "gn:admin1_code":"12.0",
    "gn:asciiname":"Xipanjia",
    "gn:country_code":"CN",
    "gn:dem":27,
    "gn:feature_class":"P",
    "gn:feature_code":"PPL",
    "gn:name":"Xipanjia",
    "gn:population":0,
    "gn:timezone":"Asia/Shanghai",
    "iso:country":"CN",
    "name:zho_x_preferred":[
        "\u7ec6\u6f58\u5bb6"
    ],
    "wof:name":"Xipanjia",
    "wof:placetype":"locality"
},
  "geometry": {"coordinates":[115.59378999999998,29.97853],"type":"Point"}
}