{
  "type": "Feature",
  "properties": {
    "gn:admin1_code":"11.0",
    "gn:asciiname":"Duishang",
    "gn:country_code":"CN",
    "gn:dem":169,
    "gn:feature_class":"P",
    "gn:feature_code":"PPL",
    "gn:name":"Duishang",
    "gn:population":0,
    "gn:timezone":"Asia/Shanghai",
    "iso:country":"CN",
    "name:zho_x_preferred":[
        "\u5806\u4e0a"
    ],
    "wof:name":"Duishang",
    "wof:placetype":"locality"
},
  "geometry": {"coordinates":[113.04704,25.77389],"type":"Point"}
}