{
  "type": "Feature",
  "properties": {
    "gn:admin1_code":"12.0",
    "gn:asciiname":"Kezhongbai",
    "gn:country_code":"CN",
    "gn:dem":24,
    "gn:feature_class":"P",
    "gn:feature_code":"PPL",
    "gn:name":"Kezhongbai",
    "gn:population":0,
    "gn:timezone":"Asia/Shanghai",
    "iso:country":"CN",
    "name:und_x_variant":[
        "\u67ef\u91cd\u767d"
    ],
    "wof:name":"Kezhongbai",
    "wof:placetype":"locality"
},
  "geometry": {"coordinates":[114.86311000000001,30.10151],"type":"Point"}
}