{
  "type": "Feature",
  "properties": {
    "gn:admin1_code":"19.0",
    "gn:asciiname":"Maojiadian",
    "gn:country_code":"CN",
    "gn:dem":157,
    "gn:feature_class":"P",
    "gn:feature_code":"PPLA4",
    "gn:name":"Maojiadian",
    "gn:population":0,
    "gn:timezone":"Asia/Shanghai",
    "iso:country":"CN",
    "name:und_x_variant":[
        "Maojiadian Zhen",
        "Maojiadian"
    ],
    "name:zho_x_preferred":[
        "\u6bdb\u5bb6\u5e97"
    ],
    "name:zho_x_variant":[
        "\u6bdb\u5bb6\u5e97\u9547"
    ],
    "wof:name":"Maojiadian",
    "wof:placetype":"locality"
},
  "geometry": {"coordinates":[124.29300000000001,43.04208],"type":"Point"}
}