{
  "type": "Feature",
  "properties": {
    "gn:admin1_code":"01",
    "gn:asciiname":"Gufotangcun",
    "gn:country_code":"CN",
    "gn:dem":361,
    "gn:feature_class":"P",
    "gn:feature_code":"PPL",
    "gn:name":"Gufotangcun",
    "gn:population":0,
    "gn:timezone":"Asia/Shanghai",
    "iso:country":"CN",
    "name:und_x_variant":[
        "Gufotang"
    ],
    "name:zho_x_preferred":[
        "\u53e4\u4f5b\u5802\u6751"
    ],
    "wof:name":"Gufotangcun",
    "wof:placetype":"locality"
},
  "geometry": {"coordinates":[115.92792,31.11609],"type":"Point"}
}