{
  "type": "Feature",
  "properties": {
    "gn:admin1_code":"26",
    "gn:asciiname":"Banjia",
    "gn:country_code":"CN",
    "gn:dem":365,
    "gn:feature_class":"P",
    "gn:feature_code":"PPL",
    "gn:name":"Banjia",
    "gn:population":0,
    "gn:timezone":"Asia/Shanghai",
    "iso:country":"CN",
    "name:und_x_variant":[
        "\u73ed\u5bb6",
        "Banjia"
    ],
    "wof:name":"Banjia",
    "wof:placetype":"locality"
},
  "geometry": {"coordinates":[109.03655999999999,34.4271],"type":"Point"}
}