{
  "type": "Feature",
  "properties": {
    "gn:admin1_code":"26.0",
    "gn:asciiname":"Jijia Jiecun",
    "gn:country_code":"CN",
    "gn:dem":1086,
    "gn:feature_class":"P",
    "gn:feature_code":"PPL",
    "gn:name":"Jijia Jiecun",
    "gn:population":0,
    "gn:timezone":"Asia/Shanghai",
    "iso:country":"CN",
    "name:zho_x_preferred":[
        "\u59ec\u5bb6\u754c\u6751"
    ],
    "wof:name":"Jijia Jiecun",
    "wof:placetype":"locality"
},
  "geometry": {"coordinates":[109.97,37.7093],"type":"Point"}
}