{
  "type": "Feature",
  "properties": {
    "gn:admin1_code":"1.0",
    "gn:asciiname":"Xiliancun",
    "gn:country_code":"CN",
    "gn:dem":591,
    "gn:feature_class":"P",
    "gn:feature_code":"PPL",
    "gn:name":"Xiliancun",
    "gn:population":0,
    "gn:timezone":"Asia/Shanghai",
    "iso:country":"CN",
    "name:zho_x_preferred":[
        "\u897f\u83b2\u6751"
    ],
    "wof:name":"Xiliancun",
    "wof:placetype":"locality"
},
  "geometry": {"coordinates":[115.89146,31.53787],"type":"Point"}
}