{
  "type": "Feature",
  "properties": {
    "gn:admin1_code":"8.0",
    "gn:asciiname":"Hongguangcun",
    "gn:country_code":"CN",
    "gn:dem":53,
    "gn:feature_class":"P",
    "gn:feature_code":"PPL",
    "gn:name":"Hongguangcun",
    "gn:population":0,
    "gn:timezone":"Asia/Shanghai",
    "iso:country":"CN",
    "name:zho_x_preferred":[
        "\u7ea2\u5149\u6751"
    ],
    "wof:name":"Hongguangcun",
    "wof:placetype":"locality"
},
  "geometry": {"coordinates":[132.68613999999999,47.69907],"type":"Point"}
}