{
  "type": "Feature",
  "properties": {
    "gn:admin1_code":"18",
    "gn:asciiname":"Yimuga",
    "gn:country_code":"CN",
    "gn:dem":1190,
    "gn:feature_class":"P",
    "gn:feature_code":"PPL",
    "gn:name":"Yimuga",
    "gn:population":0,
    "gn:timezone":"Asia/Shanghai",
    "iso:country":"CN",
    "name:zho_x_preferred":[
        "\u6613\u6728\u560e"
    ],
    "wof:name":"Yimuga",
    "wof:placetype":"locality"
},
  "geometry": {"coordinates":[106.21299999999999,27.3118],"type":"Point"}
}