{
  "type": "Feature",
  "properties": {
    "gn:admin1_code":"4.0",
    "gn:asciiname":"Zhangjia Laoyuan",
    "gn:country_code":"CN",
    "gn:dem":5,
    "gn:feature_class":"P",
    "gn:feature_code":"PPL",
    "gn:name":"Zhangjia Laoyuan",
    "gn:population":0,
    "gn:timezone":"Asia/Shanghai",
    "iso:country":"CN",
    "name:zho_x_preferred":[
        "\u5f20\u5bb6\u8001\u9662"
    ],
    "wof:name":"Zhangjia Laoyuan",
    "wof:placetype":"locality"
},
  "geometry": {"coordinates":[120.90300000000001,32.008],"type":"Point"}
}