{
  "type": "Feature",
  "properties": {
    "gn:admin1_code":"8.0",
    "gn:asciiname":"Xinshancun",
    "gn:country_code":"CN",
    "gn:dem":170,
    "gn:feature_class":"P",
    "gn:feature_code":"PPL",
    "gn:name":"Xinshancun",
    "gn:population":0,
    "gn:timezone":"Asia/Shanghai",
    "iso:country":"CN",
    "name:zho_x_preferred":[
        "\u65b0\u5c71\u6751"
    ],
    "wof:name":"Xinshancun",
    "wof:placetype":"locality"
},
  "geometry": {"coordinates":[131.55153000000001,46.04134000000001],"type":"Point"}
}