{
  "type": "Feature",
  "properties": {
    "gn:admin1_code":"26.0",
    "gn:asciiname":"Baishigoumenshang",
    "gn:country_code":"CN",
    "gn:dem":884,
    "gn:feature_class":"P",
    "gn:feature_code":"PPL",
    "gn:name":"Baishigoumenshang",
    "gn:population":0,
    "gn:timezone":"Asia/Shanghai",
    "iso:country":"CN",
    "name:und_x_variant":[
        "\u767d\u77f3\u6c9f\u95e8\u4e0a"
    ],
    "wof:name":"Baishigoumenshang",
    "wof:placetype":"locality"
},
  "geometry": {"coordinates":[106.18913000000001,33.37379],"type":"Point"}
}