{
  "type": "Feature",
  "properties": {
    "gn:admin1_code":"9.0",
    "gn:asciiname":"Jianxi",
    "gn:country_code":"CN",
    "gn:dem":380,
    "gn:feature_class":"P",
    "gn:feature_code":"PPL",
    "gn:name":"Jianxi",
    "gn:population":0,
    "gn:timezone":"Asia/Shanghai",
    "iso:country":"CN",
    "name:zho_x_preferred":[
        "\u51bf\u897f"
    ],
    "wof:name":"Jianxi",
    "wof:placetype":"locality"
},
  "geometry": {"coordinates":[112.26384,34.92276],"type":"Point"}
}