{
  "type": "Feature",
  "properties": {
    "gn:admin1_code":"02",
    "gn:asciiname":"Leishikengcun",
    "gn:country_code":"CN",
    "gn:dem":8,
    "gn:feature_class":"P",
    "gn:feature_code":"PPL",
    "gn:name":"Leishikengcun",
    "gn:population":0,
    "gn:timezone":"Asia/Shanghai",
    "iso:country":"CN",
    "name:und_x_variant":[
        "Leishikeng",
        "Leishikengcun"
    ],
    "name:zho_x_preferred":[
        "\u78ca\u77f3\u5751"
    ],
    "name:zho_x_variant":[
        "\u78ca\u77f3\u5751\u6751"
    ],
    "wof:name":"Leishikengcun",
    "wof:placetype":"locality"
},
  "geometry": {"coordinates":[121.62048,28.77032],"type":"Point"}
}