{
  "type": "Feature",
  "properties": {
    "gn:admin1_code":"12.0",
    "gn:asciiname":"Yangzhou",
    "gn:country_code":"CN",
    "gn:dem":31,
    "gn:feature_class":"P",
    "gn:feature_code":"PPL",
    "gn:name":"Yangzhou",
    "gn:population":0,
    "gn:timezone":"Asia/Shanghai",
    "iso:country":"CN",
    "name:afr_x_preferred":[
        "Yangzhou"
    ],
    "name:als_x_preferred":[
        "Yangzhou"
    ],
    "name:ara_x_preferred":[
        "\u064a\u0627\u0646\u063a\u062a\u0634\u0648"
    ],
    "name:ast_x_preferred":[
        "Yangzhou"
    ],
    "name:bod_x_preferred":[
        "\u0f61\u0fb0\u0f44\u0f0b\u0f40\u0fb2\u0f7c\u0f60\u0f74\u0f0d"
    ],
    "name:bre_x_preferred":[
        "Yangzhou"
    ],
    "name:bul_x_preferred":[
        "\u042f\u043d\u0434\u0436\u043e\u0443"
    ],
    "name:cat_x_preferred":[
        "Yangzhou"
    ],
    "name:cdo_x_preferred":[
        "I\u00f2ng-ci\u016d"
    ],
    "name:ceb_x_preferred":[
        "Yangzhou"
    ],
    "name:ces_x_preferred":[
        "Jang-\u010dou"
    ],
    "name:cym_x_preferred":[
        "Yangzhou"
    ],
    "name:dan_x_preferred":[
        "Yangzhou"
    ],
    "name:deu_x_preferred":[
        "Yangzhou"
    ],
    "name:epo_x_preferred":[
        "Jan\u0109\u0135ou"
    ],
    "name:eus_x_preferred":[
        "Yangzhou"
    ],
    "name:fas_x_preferred":[
        "\u06cc\u0627\u0646\u06af\u0698\u0648"
    ],
    "name:fin_x_preferred":[
        "Yangzhou"
    ],
    "name:fra_x_preferred":[
        "Yangzhou"
    ],
    "name:heb_x_preferred":[
        "\u05d9\u05d0\u05e0\u05d2\u05d2'\u05d5\u05d0\u05d5"
    ],
    "name:ind_x_preferred":[
        "Yangzhou"
    ],
    "name:ita_x_preferred":[
        "Yangzhou"
    ],
    "name:jpn_x_preferred":[
        "\u63da\u5dde\u5e02"
    ],
    "name:kik_x_preferred":[
        "Yangzhou"
    ],
    "name:kor_x_preferred":[
        "\uc591\uc800\uc6b0\uc2dc"
    ],
    "name:mlg_x_preferred":[
        "Yangzhou"
    ],
    "name:nld_x_preferred":[
        "Yangzhou"
    ],
    "name:nno_x_preferred":[
        "Yangzhou"
    ],
    "name:nor_x_preferred":[
        "Yangzhou"
    ],
    "name:pol_x_preferred":[
        "Yangzhou"
    ],
    "name:por_x_preferred":[
        "Yangzhou"
    ],
    "name:rus_x_preferred":[
        "\u042f\u043d\u0447\u0436\u043e\u0443"
    ],
    "name:spa_x_preferred":[
        "Yangzhou"
    ],
    "name:srp_x_preferred":[
        "\u0408\u0430\u043d\u0433\u045f\u043e\u0443"
    ],
    "name:swe_x_preferred":[
        "Yangzhou"
    ],
    "name:tgl_x_preferred":[
        "Yangzhou"
    ],
    "name:tur_x_preferred":[
        "Yangzhou"
    ],
    "name:uig_x_preferred":[
        "Yangjo shehiri"
    ],
    "name:ukr_x_preferred":[
        "\u042f\u043d\u0447\u0436\u043e\u0443"
    ],
    "name:urd_x_preferred":[
        "\u06cc\u0627\u0646\u06af\u0698\u0648"
    ],
    "name:vie_x_preferred":[
        "D\u01b0\u01a1ng Ch\u00e2u"
    ],
    "name:war_x_preferred":[
        "Yangzhou"
    ],
    "name:wuu_x_preferred":[
        "\u626c\u5dde\u5e02"
    ],
    "name:zho_x_preferred":[
        "\u6768\u6d32"
    ],
    "name:zho_x_variant":[
        "\u626c\u5dde\u5e02"
    ],
    "wof:name":"Yangzhou",
    "wof:placetype":"locality"
},
  "geometry": {"coordinates":[113.29604,30.27187],"type":"Point"}
}