{
  "type": "Feature",
  "properties": {
    "gn:admin1_code":"12.0",
    "gn:asciiname":"Yangzhou",
    "gn:country_code":"CN",
    "gn:dem":31,
    "gn:feature_class":"P",
    "gn:feature_code":"PPL",
    "gn:name":"Yangzhou",
    "gn:population":0,
    "gn:timezone":"Asia/Shanghai",
    "iso:country":"CN",
    "name:zho_x_preferred":[
        "\u6768\u6d32"
    ],
    "wof:name":"Yangzhou",
    "wof:placetype":"locality"
},
  "geometry": {"coordinates":[113.29604,30.27187],"type":"Point"}
}