{
  "type": "Feature",
  "properties": {
    "gn:admin1_code":"11.0",
    "gn:asciiname":"Chengqianpu",
    "gn:country_code":"CN",
    "gn:dem":79,
    "gn:feature_class":"P",
    "gn:feature_code":"PPL",
    "gn:name":"Chengqianpu",
    "gn:population":0,
    "gn:timezone":"Asia/Shanghai",
    "iso:country":"CN",
    "name:zho_x_preferred":[
        "\u57ce\u524d\u94fa"
    ],
    "wof:name":"Chengqianpu",
    "wof:placetype":"locality"
},
  "geometry": {"coordinates":[112.52276000000001,27.87047],"type":"Point"}
}