{
  "type": "Feature",
  "properties": {
    "gn:admin1_code":"30.0",
    "gn:asciiname":"Dawenkou",
    "gn:country_code":"CN",
    "gn:dem":144,
    "gn:feature_class":"P",
    "gn:feature_code":"PPL",
    "gn:name":"Dawenkou",
    "gn:population":0,
    "gn:timezone":"Asia/Shanghai",
    "iso:country":"CN",
    "name:zho_x_preferred":[
        "\u5927\u6c76\u53e3"
    ],
    "wof:name":"Dawenkou",
    "wof:placetype":"locality"
},
  "geometry": {"coordinates":[112.42768,23.83229],"type":"Point"}
}