{
  "type": "Feature",
  "properties": {
    "gn:admin1_code":"29.0",
    "gn:asciiname":"Zhangfacun",
    "gn:country_code":"CN",
    "gn:dem":2157,
    "gn:feature_class":"P",
    "gn:feature_code":"PPL",
    "gn:name":"Zhangfacun",
    "gn:population":0,
    "gn:timezone":"Asia/Shanghai",
    "iso:country":"CN",
    "name:zho_x_preferred":[
        "\u5f20\u53d1\u6751"
    ],
    "wof:name":"Zhangfacun",
    "wof:placetype":"locality"
},
  "geometry": {"coordinates":[104.053,25.8902],"type":"Point"}
}