{
  "type": "Feature",
  "properties": {
    "gn:admin1_code":"8.0",
    "gn:asciiname":"Xiao'erlongtun",
    "gn:country_code":"CN",
    "gn:dem":133,
    "gn:feature_class":"P",
    "gn:feature_code":"PPL",
    "gn:name":"Xiao\u2019erlongtun",
    "gn:population":0,
    "gn:timezone":"Asia/Shanghai",
    "iso:country":"CN",
    "name:und_x_variant":[
        "Xiao\u2019erlongtun"
    ],
    "name:zho_x_preferred":[
        "\u5c0f\u4e8c\u9f99\u5c6f"
    ],
    "wof:name":"Xiao'erlongtun",
    "wof:placetype":"locality"
},
  "geometry": {"coordinates":[123.72018,46.39383],"type":"Point"}
}