{
  "type": "Feature",
  "properties": {
    "gn:admin1_code":"11.0",
    "gn:asciiname":"Xianghua Shujiao",
    "gn:country_code":"CN",
    "gn:dem":436,
    "gn:feature_class":"P",
    "gn:feature_code":"PPL",
    "gn:name":"Xianghua Shujiao",
    "gn:population":0,
    "gn:timezone":"Asia/Shanghai",
    "iso:country":"CN",
    "name:zho_x_preferred":[
        "\u9999\u82b1\u6811\u811a"
    ],
    "wof:name":"Xianghua Shujiao",
    "wof:placetype":"locality"
},
  "geometry": {"coordinates":[112.13533,25.26742],"type":"Point"}
}