{
  "type": "Feature",
  "properties": {
    "gn:admin1_code":"32",
    "gn:asciiname":"Houjiaping",
    "gn:cc2":"CN",
    "gn:country_code":"CN",
    "gn:dem":395,
    "gn:feature_class":"P",
    "gn:feature_code":"PPL",
    "gn:name":"Houjiaping",
    "gn:population":0,
    "gn:timezone":"Asia/Shanghai",
    "iso:country":"CN",
    "name:und_x_variant":[
        "Hou-chia-p\u2019ing",
        "Houjiaping"
    ],
    "wof:name":"Houjiaping",
    "wof:placetype":"locality"
},
  "geometry": {"coordinates":[104.63333,30.03333],"type":"Point"}
}