{
  "type": "Feature",
  "properties": {
    "gn:admin1_code":"9.0",
    "gn:asciiname":"Shuangtaizhencun",
    "gn:country_code":"CN",
    "gn:dem":65,
    "gn:feature_class":"P",
    "gn:feature_code":"PPL",
    "gn:name":"Shuangtaizhencun",
    "gn:population":0,
    "gn:timezone":"Asia/Shanghai",
    "iso:country":"CN",
    "name:zho_x_preferred":[
        "\u53cc\u53f0\u9547\u6751"
    ],
    "wof:name":"Shuangtaizhencun",
    "wof:placetype":"locality"
},
  "geometry": {"coordinates":[114.43411999999999,32.65868],"type":"Point"}
}