{
  "type": "Feature",
  "properties": {
    "gn:admin1_code":"26.0",
    "gn:asciiname":"Doupozi",
    "gn:country_code":"CN",
    "gn:dem":1747,
    "gn:feature_class":"P",
    "gn:feature_code":"PPL",
    "gn:name":"Doupozi",
    "gn:population":0,
    "gn:timezone":"Asia/Shanghai",
    "iso:country":"CN",
    "name:zho_x_preferred":[
        "\u9661\u5761\u5b50"
    ],
    "wof:name":"Doupozi",
    "wof:placetype":"locality"
},
  "geometry": {"coordinates":[107.56947,37.41926],"type":"Point"}
}