{
  "type": "Feature",
  "properties": {
    "gn:admin1_code":"24.0",
    "gn:asciiname":"Dongsuzhuang",
    "gn:country_code":"CN",
    "gn:dem":594,
    "gn:feature_class":"P",
    "gn:feature_code":"PPL",
    "gn:name":"Dongsuzhuang",
    "gn:population":0,
    "gn:timezone":"Asia/Shanghai",
    "iso:country":"CN",
    "name:zho_x_preferred":[
        "\u4e1c\u82cf\u5e84"
    ],
    "wof:name":"Dongsuzhuang",
    "wof:placetype":"locality"
},
  "geometry": {"coordinates":[112.53478,35.6917],"type":"Point"}
}