{
  "type": "Feature",
  "properties": {
    "gn:admin1_code":"30.0",
    "gn:asciiname":"Shangmei",
    "gn:country_code":"CN",
    "gn:dem":337,
    "gn:feature_class":"P",
    "gn:feature_code":"PPL",
    "gn:name":"Shangmei",
    "gn:population":0,
    "gn:timezone":"Asia/Shanghai",
    "iso:country":"CN",
    "name:zho_x_preferred":[
        "Shangmei"
    ],
    "name:zho_x_variant":[
        "\u4e0a\u679a"
    ],
    "wof:name":"Shangmei",
    "wof:placetype":"locality"
},
  "geometry": {"coordinates":[112.71138999999999,24.32583],"type":"Point"}
}