{
  "type": "Feature",
  "properties": {
    "gn:admin1_code":"19.0",
    "gn:asciiname":"Xiaomidongzi",
    "gn:country_code":"CN",
    "gn:dem":684,
    "gn:feature_class":"P",
    "gn:feature_code":"PPL",
    "gn:name":"Xiaomidongzi",
    "gn:population":0,
    "gn:timezone":"Asia/Shanghai",
    "iso:country":"CN",
    "name:und_x_variant":[
        "\u5c0f\u7c73\u6d1e\u5b50"
    ],
    "name:zho_x_preferred":[
        "\u5c0f\u7c73\u6d1e\u5b50"
    ],
    "wof:name":"Xiaomidongzi",
    "wof:placetype":"locality"
},
  "geometry": {"coordinates":[119.313,40.636],"type":"Point"}
}