{
  "type": "Feature",
  "properties": {
    "gn:admin1_code":"18",
    "gn:asciiname":"Buzuo",
    "gn:country_code":"CN",
    "gn:dem":1244,
    "gn:feature_class":"P",
    "gn:feature_code":"PPL",
    "gn:name":"Buzuo",
    "gn:population":0,
    "gn:timezone":"Asia/Shanghai",
    "iso:country":"CN",
    "name:zho_x_preferred":[
        "\u8865\u4f5c"
    ],
    "wof:name":"Buzuo",
    "wof:placetype":"locality"
},
  "geometry": {"coordinates":[104.69499999999999,24.9903],"type":"Point"}
}