{
  "type": "Feature",
  "properties": {
    "gn:admin1_code":"25.0",
    "gn:asciiname":"Qiancaogezhuang",
    "gn:country_code":"CN",
    "gn:dem":44,
    "gn:feature_class":"P",
    "gn:feature_code":"PPL",
    "gn:name":"Qiancaogezhuang",
    "gn:population":0,
    "gn:timezone":"Asia/Shanghai",
    "iso:country":"CN",
    "name:zho_x_preferred":[
        "\u524d\u66f9\u6208\u5e84"
    ],
    "wof:name":"Qiancaogezhuang",
    "wof:placetype":"locality"
},
  "geometry": {"coordinates":[119.57044999999999,36.25635],"type":"Point"}
}