{
  "type": "Feature",
  "properties": {
    "gn:admin1_code":"29.0",
    "gn:asciiname":"Milabo",
    "gn:country_code":"CN",
    "gn:dem":1346,
    "gn:feature_class":"P",
    "gn:feature_code":"PPL",
    "gn:name":"Milabo",
    "gn:population":0,
    "gn:timezone":"Asia/Shanghai",
    "iso:country":"CN",
    "name:zho_x_preferred":[
        "\u7c73\u62c9\u4f2f"
    ],
    "wof:name":"Milabo",
    "wof:placetype":"locality"
},
  "geometry": {"coordinates":[99.2839,22.1396],"type":"Point"}
}