{
  "type": "Feature",
  "properties": {
    "gn:admin1_code":"32.0",
    "gn:asciiname":"Xizhuang",
    "gn:country_code":"CN",
    "gn:dem":1513,
    "gn:feature_class":"P",
    "gn:feature_code":"PPL",
    "gn:name":"Xizhuang",
    "gn:population":0,
    "gn:timezone":"Asia/Shanghai",
    "iso:country":"CN",
    "name:zho_x_preferred":[
        "\u897f\u5e84"
    ],
    "wof:name":"Xizhuang",
    "wof:placetype":"locality"
},
  "geometry": {"coordinates":[102.25700000000001,27.8641],"type":"Point"}
}