{
  "type": "Feature",
  "properties": {
    "gn:admin1_code":"15.0",
    "gn:asciiname":"Yemajing",
    "gn:country_code":"CN",
    "gn:dem":1519,
    "gn:feature_class":"P",
    "gn:feature_code":"PPL",
    "gn:name":"Yemajing",
    "gn:population":0,
    "gn:timezone":"Asia/Shanghai",
    "iso:country":"CN",
    "name:zho_x_preferred":[
        "\u91ce\u9a6c\u4e95"
    ],
    "wof:name":"Yemajing",
    "wof:placetype":"locality"
},
  "geometry": {"coordinates":[98.85469999999999,40.4691],"type":"Point"}
}