{
  "type": "Feature",
  "properties": {
    "gn:admin1_code":"11.0",
    "gn:asciiname":"Yougang",
    "gn:cc2":"CN",
    "gn:country_code":"CN",
    "gn:dem":29,
    "gn:feature_class":"P",
    "gn:feature_code":"PPL",
    "gn:name":"Yougang",
    "gn:population":0,
    "gn:timezone":"Asia/Shanghai",
    "iso:country":"CN",
    "name:und_x_variant":[
        "Yu-Kang",
        "Yougang"
    ],
    "wof:name":"Yougang",
    "wof:placetype":"locality"
},
  "geometry": {"coordinates":[112.19611,29.08889000000001],"type":"Point"}
}