{
  "type": "Feature",
  "properties": {
    "gn:admin1_code":"4.0",
    "gn:asciiname":"Guangfu",
    "gn:country_code":"CN",
    "gn:dem":4,
    "gn:feature_class":"P",
    "gn:feature_code":"PPL",
    "gn:name":"Guangfu",
    "gn:population":0,
    "gn:timezone":"Asia/Shanghai",
    "iso:country":"CN",
    "name:fra_x_preferred":[
        "Guangfu"
    ],
    "name:swe_x_preferred":[
        "Guangfu"
    ],
    "name:zho_x_preferred":[
        "\u5e7f\u798f"
    ],
    "wof:name":"Guangfu",
    "wof:placetype":"locality"
},
  "geometry": {"coordinates":[120.35097,32.03082],"type":"Point"}
}