{
  "type": "Feature",
  "properties": {
    "gn:admin1_code":"2.0",
    "gn:asciiname":"Yaoshan",
    "gn:country_code":"CN",
    "gn:dem":188,
    "gn:feature_class":"P",
    "gn:feature_code":"PPLA4",
    "gn:name":"Yaoshan",
    "gn:population":0,
    "gn:timezone":"Asia/Shanghai",
    "iso:country":"CN",
    "name:ceb_x_preferred":[
        "Yaoshan"
    ],
    "name:swe_x_preferred":[
        "Yaoshan"
    ],
    "name:und_x_variant":[
        "\u7476\u5c71",
        "Yaoshan Xiang",
        "\u7476\u5c71\u4e61"
    ],
    "wof:name":"Yaoshan",
    "wof:placetype":"locality"
},
  "geometry": {"coordinates":[119.06653,29.96444],"type":"Point"}
}