{
  "type": "Feature",
  "properties": {
    "iso:country":"CN",
    "name:eng_x_preferred":[
        "Nankou"
    ],
    "name:zho_x_preferred":[
        "\u5357\u53e3"
    ],
    "qs:name":"\u5357\u53e3",
    "qs:name_adm0":"\u4e2d\u570b",
    "qs:name_adm1":"\u5317\u4eac\u76f4\u8f96\u5e02",
    "qs:photos":261,
    "qs:photos_1k":53,
    "qs:photos_9k":1,
    "qs:photos_9r":4,
    "qs:photos_all":261,
    "qs:photos_sr":5,
    "qs:placetype":"Town",
    "qs:pop_sr":"0",
    "wof:name":"Nankou",
    "wof:placetype":"locality"
},
  "geometry": {"coordinates":[116.12686100000001,40.241705],"type":"Point"}
}