{
  "type": "Feature",
  "properties": {
    "gn:admin1_code":"12.0",
    "gn:asciiname":"Wujia Laowu",
    "gn:country_code":"CN",
    "gn:dem":1193,
    "gn:feature_class":"P",
    "gn:feature_code":"PPL",
    "gn:name":"Wujia Laowu",
    "gn:population":0,
    "gn:timezone":"Asia/Shanghai",
    "iso:country":"CN",
    "name:zho_x_preferred":[
        "\u4f0d\u5bb6\u8001\u5c4b"
    ],
    "wof:name":"Wujia Laowu",
    "wof:placetype":"locality"
},
  "geometry": {"coordinates":[111.426,31.87894],"type":"Point"}
}