{
  "type": "Feature",
  "properties": {
    "gn:admin1_code":"32.0",
    "gn:asciiname":"Tuantianba",
    "gn:country_code":"CN",
    "gn:dem":369,
    "gn:feature_class":"P",
    "gn:feature_code":"PPL",
    "gn:name":"Tuantianba",
    "gn:population":0,
    "gn:timezone":"Asia/Shanghai",
    "iso:country":"CN",
    "name:zho_x_preferred":[
        "\u56e2\u7530\u575d"
    ],
    "wof:name":"Tuantianba",
    "wof:placetype":"locality"
},
  "geometry": {"coordinates":[107.52800000000001,30.9741],"type":"Point"}
}