{
  "type": "Feature",
  "properties": {
    "gn:admin1_code":"25",
    "gn:asciiname":"Linpuji",
    "gn:cc2":"CN",
    "gn:country_code":"CN",
    "gn:dem":55,
    "gn:feature_class":"P",
    "gn:feature_code":"PPL",
    "gn:name":"Linpuji",
    "gn:population":0,
    "gn:timezone":"Asia/Shanghai",
    "iso:country":"CN",
    "name:und_x_variant":[
        "Lin-p\u2019u-chi",
        "Linpuji"
    ],
    "wof:name":"Linpuji",
    "wof:placetype":"locality"
},
  "geometry": {"coordinates":[115.36861,35.46694],"type":"Point"}
}