{
  "type": "Feature",
  "properties": {
    "gn:admin1_code":"3.0",
    "gn:asciiname":"Longfukeng",
    "gn:country_code":"CN",
    "gn:dem":272,
    "gn:feature_class":"P",
    "gn:feature_code":"PPL",
    "gn:name":"Longfukeng",
    "gn:population":0,
    "gn:timezone":"Asia/Shanghai",
    "iso:country":"CN",
    "name:und_x_variant":[
        "\u9f99\u5bcc\u5751"
    ],
    "wof:name":"Longfukeng",
    "wof:placetype":"locality"
},
  "geometry": {"coordinates":[115.73545,24.81837],"type":"Point"}
}