{
  "type": "Feature",
  "properties": {
    "gn:admin1_code":"32.0",
    "gn:asciiname":"Baotangsi",
    "gn:country_code":"CN",
    "gn:dem":421,
    "gn:feature_class":"P",
    "gn:feature_code":"PPL",
    "gn:name":"Baotangsi",
    "gn:population":0,
    "gn:timezone":"Asia/Shanghai",
    "iso:country":"CN",
    "name:zho_x_preferred":[
        "\u5b9d\u5802\u5bfa"
    ],
    "wof:name":"Baotangsi",
    "wof:placetype":"locality"
},
  "geometry": {"coordinates":[105.093,30.1514],"type":"Point"}
}