{
  "type": "Feature",
  "properties": {
    "gn:admin1_code":"25.0",
    "gn:asciiname":"Wasunjia",
    "gn:country_code":"CN",
    "gn:dem":46,
    "gn:feature_class":"P",
    "gn:feature_code":"PPL",
    "gn:name":"Wasunjia",
    "gn:population":0,
    "gn:timezone":"Asia/Shanghai",
    "iso:country":"CN",
    "name:zho_x_preferred":[
        "\u6d3c\u5b59\u5bb6"
    ],
    "wof:name":"Wasunjia",
    "wof:placetype":"locality"
},
  "geometry": {"coordinates":[120.21151,37.44724],"type":"Point"}
}