{
  "type": "Feature",
  "properties": {
    "gn:admin1_code":"15.0",
    "gn:asciiname":"Zhouyuanping",
    "gn:country_code":"CN",
    "gn:dem":2146,
    "gn:feature_class":"P",
    "gn:feature_code":"PPL",
    "gn:name":"Zhouyuanping",
    "gn:population":0,
    "gn:timezone":"Asia/Shanghai",
    "iso:country":"CN",
    "name:zho_x_preferred":[
        "\u5468\u539f\u576a"
    ],
    "wof:name":"Zhouyuanping",
    "wof:placetype":"locality"
},
  "geometry": {"coordinates":[105.199,34.6367],"type":"Point"}
}