{
  "type": "Feature",
  "properties": {
    "gn:admin1_code":"29",
    "gn:asciiname":"Tingda",
    "gn:country_code":"CN",
    "gn:dem":1410,
    "gn:feature_class":"P",
    "gn:feature_code":"PPL",
    "gn:name":"Tingda",
    "gn:population":0,
    "gn:timezone":"Asia/Shanghai",
    "iso:country":"CN",
    "name:zho_x_preferred":[
        "\u542c\u8fbe"
    ],
    "wof:name":"Tingda",
    "wof:placetype":"locality"
},
  "geometry": {"coordinates":[104.899,24.1572],"type":"Point"}
}