{
  "type": "Feature",
  "properties": {
    "gn:admin1_code":"19.0",
    "gn:asciiname":"Ming'an Nangou",
    "gn:country_code":"CN",
    "gn:dem":350,
    "gn:feature_class":"P",
    "gn:feature_code":"PPL",
    "gn:name":"Ming\u2019an Nangou",
    "gn:population":0,
    "gn:timezone":"Asia/Shanghai",
    "iso:country":"CN",
    "name:und_x_variant":[
        "Ming\u2019an Nangou"
    ],
    "name:zho_x_preferred":[
        "\u660e\u5b89\u5357\u6c9f"
    ],
    "wof:name":"Ming'an Nangou",
    "wof:placetype":"locality"
},
  "geometry": {"coordinates":[125.20723,40.77285],"type":"Point"}
}