{
  "type": "Feature",
  "properties": {
    "gn:admin1_code":"20.0",
    "gn:asciiname":"Yuanshanzi",
    "gn:country_code":"CN",
    "gn:dem":1528,
    "gn:feature_class":"P",
    "gn:feature_code":"PPL",
    "gn:name":"Yuanshanzi",
    "gn:population":0,
    "gn:timezone":"Asia/Shanghai",
    "iso:country":"CN",
    "name:und_x_variant":[
        "\u5143\u5c71\u5b50"
    ],
    "wof:name":"Yuanshanzi",
    "wof:placetype":"locality"
},
  "geometry": {"coordinates":[112.44344,41.54243],"type":"Point"}
}