{
  "type": "Feature",
  "properties": {
    "gn:admin1_code":"29.0",
    "gn:asciiname":"Shaodixia",
    "gn:country_code":"CN",
    "gn:dem":2185,
    "gn:feature_class":"P",
    "gn:feature_code":"PPL",
    "gn:name":"Shaodixia",
    "gn:population":0,
    "gn:timezone":"Asia/Shanghai",
    "iso:country":"CN",
    "name:zho_x_preferred":[
        "\u54e8\u5e95\u4e0b"
    ],
    "wof:name":"Shaodixia",
    "wof:placetype":"locality"
},
  "geometry": {"coordinates":[99.3145,25.2442],"type":"Point"}
}