{
  "type": "Feature",
  "properties": {
    "gn:admin1_code":"26.0",
    "gn:asciiname":"Chunshugou",
    "gn:country_code":"CN",
    "gn:dem":1192,
    "gn:feature_class":"P",
    "gn:feature_code":"PPL",
    "gn:name":"Chunshugou",
    "gn:population":0,
    "gn:timezone":"Asia/Shanghai",
    "iso:country":"CN",
    "name:zho_x_preferred":[
        "\u693f\u6811\u6c9f"
    ],
    "wof:name":"Chunshugou",
    "wof:placetype":"locality"
},
  "geometry": {"coordinates":[110.01286,33.44329],"type":"Point"}
}