{
  "type": "Feature",
  "properties": {
    "gn:admin1_code":"26.0",
    "gn:asciiname":"Huachazi",
    "gn:country_code":"CN",
    "gn:dem":820,
    "gn:feature_class":"P",
    "gn:feature_code":"PPL",
    "gn:name":"Huachazi",
    "gn:population":0,
    "gn:timezone":"Asia/Shanghai",
    "iso:country":"CN",
    "name:zho_x_preferred":[
        "\u82b1\u8336\u5b50"
    ],
    "wof:name":"Huachazi",
    "wof:placetype":"locality"
},
  "geometry": {"coordinates":[107.52366000000001,32.46181],"type":"Point"}
}