{
  "type": "Feature",
  "properties": {
    "gn:admin1_code":"32.0",
    "gn:asciiname":"Eside",
    "gn:country_code":"CN",
    "gn:dem":2954,
    "gn:feature_class":"P",
    "gn:feature_code":"PPL",
    "gn:name":"Eside",
    "gn:population":0,
    "gn:timezone":"Asia/Shanghai",
    "iso:country":"CN",
    "name:zho_x_preferred":[
        "\u4fc4\u56db\u5fb7"
    ],
    "wof:name":"Eside",
    "wof:placetype":"locality"
},
  "geometry": {"coordinates":[101.973,31.753],"type":"Point"}
}