{
  "type": "Feature",
  "properties": {
    "gn:admin1_code":"26.0",
    "gn:asciiname":"Dengjialiang",
    "gn:country_code":"CN",
    "gn:dem":876,
    "gn:feature_class":"P",
    "gn:feature_code":"PPL",
    "gn:name":"Dengjialiang",
    "gn:population":0,
    "gn:timezone":"Asia/Shanghai",
    "iso:country":"CN",
    "name:zho_x_preferred":[
        "\u9093\u5bb6\u6881"
    ],
    "wof:name":"Dengjialiang",
    "wof:placetype":"locality"
},
  "geometry": {"coordinates":[109.13811,32.40359],"type":"Point"}
}