{
  "type": "Feature",
  "properties": {
    "gn:admin1_code":"22.0",
    "gn:asciiname":"Baozishicun",
    "gn:country_code":"CN",
    "gn:dem":802,
    "gn:feature_class":"P",
    "gn:feature_code":"PPL",
    "gn:name":"Baozishicun",
    "gn:population":0,
    "gn:timezone":"Asia/Shanghai",
    "iso:country":"CN",
    "name:zho_x_preferred":[
        "\u5305\u5b50\u77f3\u6751"
    ],
    "wof:name":"Baozishicun",
    "wof:placetype":"locality"
},
  "geometry": {"coordinates":[116.29658999999999,40.47221],"type":"Point"}
}