{
  "type": "Feature",
  "properties": {
    "gn:admin1_code":"26.0",
    "gn:asciiname":"Hanjiahecun",
    "gn:country_code":"CN",
    "gn:dem":915,
    "gn:feature_class":"P",
    "gn:feature_code":"PPL",
    "gn:name":"Hanjiahecun",
    "gn:population":0,
    "gn:timezone":"Asia/Shanghai",
    "iso:country":"CN",
    "name:zho_x_preferred":[
        "\u97e9\u5bb6\u6cb3\u6751"
    ],
    "wof:name":"Hanjiahecun",
    "wof:placetype":"locality"
},
  "geometry": {"coordinates":[110.21902,33.77301],"type":"Point"}
}