{
  "type": "Feature",
  "properties": {
    "gn:admin1_code":"32.0",
    "gn:asciiname":"Shixiazi",
    "gn:country_code":"CN",
    "gn:dem":1111,
    "gn:feature_class":"P",
    "gn:feature_code":"PPL",
    "gn:name":"Shixiazi",
    "gn:population":0,
    "gn:timezone":"Asia/Shanghai",
    "iso:country":"CN",
    "name:zho_x_preferred":[
        "\u77f3\u5ce1\u5b50"
    ],
    "wof:name":"Shixiazi",
    "wof:placetype":"locality"
},
  "geometry": {"coordinates":[106.31538,32.42902],"type":"Point"}
}