{
  "type": "Feature",
  "properties": {
    "gn:admin1_code":"12.0",
    "gn:asciiname":"Yuchangbai",
    "gn:country_code":"CN",
    "gn:dem":45,
    "gn:feature_class":"P",
    "gn:feature_code":"PPL",
    "gn:name":"Yuchangbai",
    "gn:population":0,
    "gn:timezone":"Asia/Shanghai",
    "iso:country":"CN",
    "name:zho_x_preferred":[
        "\u4f59\u957f\u67cf"
    ],
    "wof:name":"Yuchangbai",
    "wof:placetype":"locality"
},
  "geometry": {"coordinates":[114.36433,30.00314],"type":"Point"}
}