{
  "type": "Feature",
  "properties": {
    "gn:admin1_code":"3.0",
    "gn:asciiname":"Yanghuxiang",
    "gn:country_code":"CN",
    "gn:dem":34,
    "gn:feature_class":"P",
    "gn:feature_code":"PPLA4",
    "gn:name":"Yanghuxiang",
    "gn:population":0,
    "gn:timezone":"Asia/Shanghai",
    "iso:country":"CN",
    "name:und_x_variant":[
        "\u6d0b\u6e56\u4e61"
    ],
    "wof:name":"Yanghuxiang",
    "wof:placetype":"locality"
},
  "geometry": {"coordinates":[115.49325,28.0229],"type":"Point"}
}