{
  "type": "Feature",
  "properties": {
    "gn:admin1_code":"02",
    "gn:asciiname":"Xiazhengcun",
    "gn:country_code":"CN",
    "gn:dem":6,
    "gn:feature_class":"P",
    "gn:feature_code":"PPL",
    "gn:name":"Xiazhengcun",
    "gn:population":0,
    "gn:timezone":"Asia/Shanghai",
    "iso:country":"CN",
    "name:und_x_variant":[
        "Xiazheng",
        "Xiazhengcun"
    ],
    "name:zho_x_preferred":[
        "\u4e0b\u90d1"
    ],
    "name:zho_x_variant":[
        "\u4e0b\u90d1\u6751"
    ],
    "wof:name":"Xiazhengcun",
    "wof:placetype":"locality"
},
  "geometry": {"coordinates":[121.39892999999999,28.49379],"type":"Point"}
}