{
  "type": "Feature",
  "properties": {
    "gn:admin1_code":"26.0",
    "gn:asciiname":"Lingyansi",
    "gn:country_code":"CN",
    "gn:dem":949,
    "gn:feature_class":"P",
    "gn:feature_code":"PPL",
    "gn:name":"Lingyansi",
    "gn:population":0,
    "gn:timezone":"Asia/Shanghai",
    "iso:country":"CN",
    "name:und_x_variant":[
        "\u7075\u5ca9\u5bfa"
    ],
    "wof:name":"Lingyansi",
    "wof:placetype":"locality"
},
  "geometry": {"coordinates":[106.14518,33.29544],"type":"Point"}
}