{
  "type": "Feature",
  "properties": {
    "gn:admin1_code":"11.0",
    "gn:asciiname":"Luoxing'ao",
    "gn:country_code":"CN",
    "gn:dem":512,
    "gn:feature_class":"P",
    "gn:feature_code":"PPL",
    "gn:name":"Luoxing\u2019ao",
    "gn:population":0,
    "gn:timezone":"Asia/Shanghai",
    "iso:country":"CN",
    "name:und_x_variant":[
        "Luoxing\u2019ao"
    ],
    "name:zho_x_preferred":[
        "\u7f57\u5f62\u5773"
    ],
    "wof:name":"Luoxing'ao",
    "wof:placetype":"locality"
},
  "geometry": {"coordinates":[111.48753000000001,28.04422000000001],"type":"Point"}
}