{
  "type": "Feature",
  "properties": {
    "gn:admin1_code":"33.0",
    "gn:asciiname":"Heilongwan",
    "gn:country_code":"CN",
    "gn:dem":248,
    "gn:feature_class":"P",
    "gn:feature_code":"PPL",
    "gn:name":"Heilongwan",
    "gn:population":0,
    "gn:timezone":"Asia/Shanghai",
    "iso:country":"CN",
    "name:zho_x_preferred":[
        "\u9ed1\u9f99\u6e7e"
    ],
    "wof:name":"Heilongwan",
    "wof:placetype":"locality"
},
  "geometry": {"coordinates":[107.66781,30.09436],"type":"Point"}
}