{
  "type": "Feature",
  "properties": {
    "gn:admin1_code":"3.0",
    "gn:asciiname":"Laowuxia",
    "gn:country_code":"CN",
    "gn:dem":126,
    "gn:feature_class":"P",
    "gn:feature_code":"PPL",
    "gn:name":"Laowuxia",
    "gn:population":0,
    "gn:timezone":"Asia/Shanghai",
    "iso:country":"CN",
    "name:und_x_variant":[
        "\u8001\u5c4b\u4e0b"
    ],
    "wof:name":"Laowuxia",
    "wof:placetype":"locality"
},
  "geometry": {"coordinates":[115.35344000000001,29.60679],"type":"Point"}
}