{
  "type": "Feature",
  "properties": {
    "gn:admin1_code":"12.0",
    "gn:asciiname":"Guanwutai",
    "gn:country_code":"CN",
    "gn:dem":28,
    "gn:feature_class":"P",
    "gn:feature_code":"PPL",
    "gn:name":"Guanwutai",
    "gn:population":0,
    "gn:timezone":"Asia/Shanghai",
    "iso:country":"CN",
    "name:zho_x_preferred":[
        "\u5b98\u5c4b\u53f0"
    ],
    "wof:name":"Guanwutai",
    "wof:placetype":"locality"
},
  "geometry": {"coordinates":[112.92644,29.86481],"type":"Point"}
}