{
  "type": "Feature",
  "properties": {
    "gn:admin1_code":"16",
    "gn:asciiname":"Da'an",
    "gn:country_code":"CN",
    "gn:dem":35,
    "gn:feature_class":"P",
    "gn:feature_code":"PPL",
    "gn:name":"Da\u2019an",
    "gn:population":0,
    "gn:timezone":"Asia/Shanghai",
    "iso:country":"CN",
    "name:und_x_variant":[
        "Ta-wu",
        "Ta-an",
        "Ta-wu-hs\u00fc",
        "Ta-an-shan",
        "Taiwu",
        "Ta-an-hs\u00fc",
        "Da\u2019an"
    ],
    "wof:name":"Da'an",
    "wof:placetype":"locality"
},
  "geometry": {"coordinates":[110.50888999999999,23.38861],"type":"Point"}
}