{
  "type": "Feature",
  "properties": {
    "gn:admin1_code":"04",
    "gn:asciiname":"Tanggou",
    "gn:cc2":"CN",
    "gn:country_code":"CN",
    "gn:dem":7,
    "gn:feature_class":"P",
    "gn:feature_code":"PPL",
    "gn:name":"Tanggou",
    "gn:population":0,
    "gn:timezone":"Asia/Shanghai",
    "iso:country":"CN",
    "name:und_x_variant":[
        "T\u2019ang-kou",
        "Tanggou"
    ],
    "wof:name":"Tanggou",
    "wof:placetype":"locality"
},
  "geometry": {"coordinates":[118.95,33.98333],"type":"Point"}
}