{
  "type": "Feature",
  "properties": {
    "gn:admin1_code":"29.0",
    "gn:asciiname":"Dajialu",
    "gn:country_code":"CN",
    "gn:dem":1309,
    "gn:feature_class":"P",
    "gn:feature_code":"PPL",
    "gn:name":"Dajialu",
    "gn:population":0,
    "gn:timezone":"Asia/Shanghai",
    "iso:country":"CN",
    "name:zho_x_preferred":[
        "\u8fbe\u621b\u8def"
    ],
    "wof:name":"Dajialu",
    "wof:placetype":"locality"
},
  "geometry": {"coordinates":[99.5778,22.4165],"type":"Point"}
}