{
  "type": "Feature",
  "properties": {
    "iso:country":"CN",
    "name:ara_x_preferred":[
        "\u0645\u062d\u0627\u0641\u0638\u0629 \u0648\u0648\u064a\u0648\u0627\u0646"
    ],
    "name:ceb_x_preferred":[
        "Wuyuan Xian"
    ],
    "name:deu_x_preferred":[
        "Wuyuan"
    ],
    "name:eng_x_preferred":[
        "Wuyuan County"
    ],
    "name:fas_x_preferred":[
        "\u0634\u0647\u0631\u0633\u062a\u0627\u0646 \u0648\u0648\u06cc\u0648\u0627\u0646"
    ],
    "name:gan_x_preferred":[
        "\u5a7a\u6e90"
    ],
    "name:jpn_x_preferred":[
        "\u30d6\u6e90\u770c"
    ],
    "name:kor_x_preferred":[
        "\uc6b0\uc704\uc548\ud604"
    ],
    "name:nan_x_preferred":[
        "B\u016b-go\u00e2n-ko\u0101n"
    ],
    "name:nld_x_preferred":[
        "Wuyuan"
    ],
    "name:nob_x_preferred":[
        "Wuyuan"
    ],
    "name:swe_x_preferred":[
        "Wuyuan"
    ],
    "name:vie_x_preferred":[
        "V\u1ee5 Nguy\u00ean"
    ],
    "name:wuu_x_preferred":[
        "\u5a7a\u6e90\u53bf"
    ],
    "name:yue_x_preferred":[
        "\u5a7a\u6e90"
    ],
    "name:zho_x_preferred":[
        "\u5a7a\u6e90\u53bf"
    ],
    "qs:name":"\u5a7a\u6e90\u53bf",
    "qs:name_adm0":"\u4e2d\u570b",
    "qs:name_adm1":"\u6c5f\u897f\u7701",
    "qs:photos":243,
    "qs:photos_1k":49,
    "qs:photos_9k":6,
    "qs:photos_9r":7,
    "qs:photos_all":1336,
    "qs:photos_sr":4,
    "qs:placetype":"LocalAdmin",
    "qs:pop_sr":"0",
    "wd:wordcount":212,
    "wof:name":"\u5a7a\u6e90\u53bf",
    "wof:placetype":"localadmin"
},
  "geometry": {"coordinates":[117.85840899999999,29.24986],"type":"Point"}
}