{
  "type": "Feature",
  "properties": {
    "iso:country":"CN",
    "qs:name":"\u5a7a\u6e90\u53bf",
    "qs:name_adm0":"\u4e2d\u570b",
    "qs:name_adm1":"\u6c5f\u897f\u7701",
    "qs:photos":243,
    "qs:photos_1k":49,
    "qs:photos_9k":6,
    "qs:photos_9r":7,
    "qs:photos_all":1336,
    "qs:photos_sr":4,
    "qs:placetype":"LocalAdmin",
    "qs:pop_sr":"0",
    "wd:wordcount":212,
    "wof:name":"\u5a7a\u6e90\u53bf",
    "wof:placetype":"localadmin"
},
  "geometry": {"coordinates":[117.85840899999999,29.24986],"type":"Point"}
}