{
  "type": "Feature",
  "properties": {
    "gn:admin1_code":"9",
    "gn:asciiname":"Wangcun",
    "gn:country_code":"CN",
    "gn:dem":48,
    "gn:feature_class":"P",
    "gn:feature_code":"PPL",
    "gn:name":"Wangcun",
    "gn:population":0,
    "gn:timezone":"Asia/Shanghai",
    "iso:country":"CN",
    "name:deu_x_preferred":[
        "Wangcun"
    ],
    "name:zho_x_preferred":[
        "\u738b\u6751"
    ],
    "wof:name":"Wangcun",
    "wof:placetype":"locality"
},
  "geometry": {"coordinates":[115.14660000000001,36.07645],"type":"Point"}
}