{
  "type": "Feature",
  "properties": {
    "gn:admin1_code":"30.0",
    "gn:asciiname":"Tanjiangcun",
    "gn:country_code":"CN",
    "gn:dem":188,
    "gn:feature_class":"P",
    "gn:feature_code":"PPL",
    "gn:name":"Tanjiangcun",
    "gn:population":0,
    "gn:timezone":"Asia/Shanghai",
    "iso:country":"CN",
    "name:zho_x_preferred":[
        "\u6f6d\u6c5f\u6751"
    ],
    "wof:name":"Tanjiangcun",
    "wof:placetype":"locality"
},
  "geometry": {"coordinates":[115.93764,24.24921],"type":"Point"}
}