{
  "type": "Feature",
  "properties": {
    "gn:admin1_code":"30.0",
    "gn:asciiname":"Meishan",
    "gn:country_code":"CN",
    "gn:dem":19,
    "gn:feature_class":"P",
    "gn:feature_code":"PPL",
    "gn:name":"Meishan",
    "gn:population":0,
    "gn:timezone":"Asia/Shanghai",
    "iso:country":"CN",
    "name:und_x_variant":[
        "\u7709\u5c71"
    ],
    "name:zho_x_preferred":[
        "\u7709\u5c71"
    ],
    "wof:name":"Meishan",
    "wof:placetype":"locality"
},
  "geometry": {"coordinates":[113.42304,23.00392],"type":"Point"}
}