{
  "type": "Feature",
  "properties": {
    "gn:admin1_code":"30.0",
    "gn:asciiname":"Longjiacun",
    "gn:country_code":"CN",
    "gn:dem":6,
    "gn:feature_class":"P",
    "gn:feature_code":"PPL",
    "gn:name":"Longjiacun",
    "gn:population":0,
    "gn:timezone":"Asia/Shanghai",
    "iso:country":"CN",
    "name:zho_x_preferred":[
        "\u9f99\u7532\u6751"
    ],
    "wof:name":"Longjiacun",
    "wof:placetype":"locality"
},
  "geometry": {"coordinates":[116.68465999999999,23.49813],"type":"Point"}
}