{
  "type": "Feature",
  "properties": {
    "gn:admin1_code":"32.0",
    "gn:asciiname":"Maowan",
    "gn:country_code":"CN",
    "gn:dem":1076,
    "gn:feature_class":"P",
    "gn:feature_code":"PPL",
    "gn:name":"Maowan",
    "gn:population":0,
    "gn:timezone":"Asia/Shanghai",
    "iso:country":"CN",
    "name:zho_x_preferred":[
        "\u8305\u6e7e"
    ],
    "wof:name":"Maowan",
    "wof:placetype":"locality"
},
  "geometry": {"coordinates":[104.76600000000001,32.1696],"type":"Point"}
}