{
  "type": "Feature",
  "properties": {
    "gn:admin1_code":"15.0",
    "gn:asciiname":"Dajingzi Goukou",
    "gn:country_code":"CN",
    "gn:dem":1795,
    "gn:feature_class":"P",
    "gn:feature_code":"PPL",
    "gn:name":"Dajingzi Goukou",
    "gn:population":0,
    "gn:timezone":"Asia/Shanghai",
    "iso:country":"CN",
    "name:zho_x_preferred":[
        "\u5927\u4e95\u5b50\u6c9f\u53e3"
    ],
    "wof:name":"Dajingzi Goukou",
    "wof:placetype":"locality"
},
  "geometry": {"coordinates":[104.22199999999999,36.6161],"type":"Point"}
}