{
  "type": "Feature",
  "properties": {
    "gn:admin1_code":"1.0",
    "gn:asciiname":"Wangtaoyuancun",
    "gn:country_code":"CN",
    "gn:dem":37,
    "gn:feature_class":"P",
    "gn:feature_code":"PPL",
    "gn:name":"Wangtaoyuancun",
    "gn:population":0,
    "gn:timezone":"Asia/Shanghai",
    "iso:country":"CN",
    "name:zho_x_preferred":[
        "\u738b\u6843\u56ed\u6751"
    ],
    "wof:name":"Wangtaoyuancun",
    "wof:placetype":"locality"
},
  "geometry": {"coordinates":[116.79187,34.09252],"type":"Point"}
}