{
  "type": "Feature",
  "properties": {
    "gn:admin1_code":"33.0",
    "gn:asciiname":"Renshouqiao",
    "gn:country_code":"CN",
    "gn:dem":295,
    "gn:feature_class":"P",
    "gn:feature_code":"PPL",
    "gn:name":"Renshouqiao",
    "gn:population":0,
    "gn:timezone":"Asia/Shanghai",
    "iso:country":"CN",
    "name:zho_x_preferred":[
        "\u4eba\u5bff\u6865"
    ],
    "wof:name":"Renshouqiao",
    "wof:placetype":"locality"
},
  "geometry": {"coordinates":[105.90056,30.06567],"type":"Point"}
}