{
  "type": "Feature",
  "properties": {
    "gn:admin1_code":"5.0",
    "gn:asciiname":"Chaijiatun",
    "gn:country_code":"CN",
    "gn:dem":205,
    "gn:feature_class":"P",
    "gn:feature_code":"PPL",
    "gn:name":"Chaijiatun",
    "gn:population":0,
    "gn:timezone":"Asia/Shanghai",
    "iso:country":"CN",
    "name:zho_x_preferred":[
        "\u67f4\u5bb6\u5c6f"
    ],
    "wof:name":"Chaijiatun",
    "wof:placetype":"locality"
},
  "geometry": {"coordinates":[124.6996,44.32673],"type":"Point"}
}