{
  "type": "Feature",
  "properties": {
    "gn:admin1_code":"29.0",
    "gn:asciiname":"Hujiatun",
    "gn:country_code":"CN",
    "gn:dem":1647,
    "gn:feature_class":"P",
    "gn:feature_code":"PPL",
    "gn:name":"Hujiatun",
    "gn:population":0,
    "gn:timezone":"Asia/Shanghai",
    "iso:country":"CN",
    "name:zho_x_preferred":[
        "\u80e1\u5bb6\u5c6f"
    ],
    "wof:name":"Hujiatun",
    "wof:placetype":"locality"
},
  "geometry": {"coordinates":[99.20059999999999,25.0412],"type":"Point"}
}