{
  "type": "Feature",
  "properties": {
    "gn:admin1_code":"18.0",
    "gn:asciiname":"Chuijiao",
    "gn:country_code":"CN",
    "gn:dem":1340,
    "gn:feature_class":"P",
    "gn:feature_code":"PPL",
    "gn:name":"Chuijiao",
    "gn:population":0,
    "gn:timezone":"Asia/Shanghai",
    "iso:country":"CN",
    "name:zho_x_preferred":[
        "\u5439\u89d2"
    ],
    "wof:name":"Chuijiao",
    "wof:placetype":"locality"
},
  "geometry": {"coordinates":[107.316,26.9958],"type":"Point"}
}