{
  "type": "Feature",
  "properties": {
    "gn:admin1_code":"32.0",
    "gn:asciiname":"Dongdi",
    "gn:country_code":"CN",
    "gn:dem":378,
    "gn:feature_class":"P",
    "gn:feature_code":"PPL",
    "gn:name":"Dongdi",
    "gn:population":0,
    "gn:timezone":"Asia/Shanghai",
    "iso:country":"CN",
    "name:zho_x_preferred":[
        "\u7850\u5e95"
    ],
    "wof:name":"Dongdi",
    "wof:placetype":"locality"
},
  "geometry": {"coordinates":[104.80131,28.45779000000001],"type":"Point"}
}