{
  "type": "Feature",
  "properties": {
    "gn:admin1_code":"8.0",
    "gn:asciiname":"Shuguangcun",
    "gn:country_code":"CN",
    "gn:dem":218,
    "gn:feature_class":"P",
    "gn:feature_code":"PPL",
    "gn:name":"Shuguangcun",
    "gn:population":0,
    "gn:timezone":"Asia/Shanghai",
    "iso:country":"CN",
    "name:zho_x_preferred":[
        "\u66d9\u5149\u6751"
    ],
    "wof:name":"Shuguangcun",
    "wof:placetype":"locality"
},
  "geometry": {"coordinates":[126.66167,47.33554],"type":"Point"}
}