{
  "type": "Feature",
  "properties": {
    "gn:admin1_code":"7.0",
    "gn:asciiname":"Yanlicun",
    "gn:country_code":"CN",
    "gn:dem":362,
    "gn:feature_class":"P",
    "gn:feature_code":"PPL",
    "gn:name":"Yanlicun",
    "gn:population":0,
    "gn:timezone":"Asia/Shanghai",
    "iso:country":"CN",
    "name:und_x_variant":[
        "\u5ca9\u91cc\u6751"
    ],
    "name:zho_x_preferred":[
        "\u5ca9\u91cc\u6751"
    ],
    "wof:name":"Yanlicun",
    "wof:placetype":"locality"
},
  "geometry": {"coordinates":[117.22602999999999,26.37645],"type":"Point"}
}