{
  "type": "Feature",
  "properties": {
    "gn:admin1_code":"19.0",
    "gn:asciiname":"Wangjia Buzi",
    "gn:country_code":"CN",
    "gn:dem":103,
    "gn:feature_class":"P",
    "gn:feature_code":"PPL",
    "gn:name":"Wangjia Buzi",
    "gn:population":0,
    "gn:timezone":"Asia/Shanghai",
    "iso:country":"CN",
    "name:und_x_variant":[
        "Wangjiabaozi",
        "\u6c6a\u5bb6\u5821\u5b50",
        "Wangjia Puzi",
        "Wangjia Buzi"
    ],
    "name:zho_x_preferred":[
        "\u6c6a\u5bb6\u5821\u5b50"
    ],
    "wof:name":"Wangjia Buzi",
    "wof:placetype":"locality"
},
  "geometry": {"coordinates":[124.06865999999999,40.60544],"type":"Point"}
}