{
  "type": "Feature",
  "properties": {
    "gn:admin1_code":"8.0",
    "gn:asciiname":"Xibaoshancun",
    "gn:country_code":"CN",
    "gn:dem":78,
    "gn:feature_class":"P",
    "gn:feature_code":"PPL",
    "gn:name":"Xibaoshancun",
    "gn:population":0,
    "gn:timezone":"Asia/Shanghai",
    "iso:country":"CN",
    "name:zho_x_preferred":[
        "\u897f\u5b9d\u5c71\u6751"
    ],
    "wof:name":"Xibaoshancun",
    "wof:placetype":"locality"
},
  "geometry": {"coordinates":[130.94364999999999,46.96253],"type":"Point"}
}