{
  "type": "Feature",
  "properties": {
    "gn:admin1_code":"7.0",
    "gn:asciiname":"Qingfeng",
    "gn:country_code":"CN",
    "gn:dem":645,
    "gn:feature_class":"P",
    "gn:feature_code":"PPL",
    "gn:name":"Qingfeng",
    "gn:population":0,
    "gn:timezone":"Asia/Shanghai",
    "iso:country":"CN",
    "name:zho_x_preferred":[
        "\u9752\u5cf0"
    ],
    "wof:name":"Qingfeng",
    "wof:placetype":"locality"
},
  "geometry": {"coordinates":[118.85659,25.89707000000001],"type":"Point"}
}