{
  "type": "Feature",
  "properties": {
    "gn:admin1_code":"20",
    "gn:asciiname":"Mend",
    "gn:cc2":"CN",
    "gn:country_code":"CN",
    "gn:dem":147,
    "gn:feature_class":"P",
    "gn:feature_code":"PPL",
    "gn:name":"Mend",
    "gn:population":0,
    "gn:timezone":"Asia/Shanghai",
    "iso:country":"CN",
    "name:und_x_variant":[
        "Men-ta",
        "Men-ta-ying-tzu",
        "Mend"
    ],
    "wof:name":"Mend",
    "wof:placetype":"locality"
},
  "geometry": {"coordinates":[123.11667,43.65],"type":"Point"}
}