{
  "type": "Feature",
  "properties": {
    "gn:admin1_code":"32.0",
    "gn:asciiname":"Anfosi",
    "gn:country_code":"CN",
    "gn:dem":441,
    "gn:feature_class":"P",
    "gn:feature_code":"PPL",
    "gn:name":"Anfosi",
    "gn:population":0,
    "gn:timezone":"Asia/Shanghai",
    "iso:country":"CN",
    "name:zho_x_preferred":[
        "\u5b89\u4f5b\u5bfa"
    ],
    "wof:name":"Anfosi",
    "wof:placetype":"locality"
},
  "geometry": {"coordinates":[104.66719000000001,30.45861],"type":"Point"}
}