{
  "type": "Feature",
  "properties": {
    "gn:admin1_code":"30.0",
    "gn:asciiname":"Quhe",
    "gn:country_code":"CN",
    "gn:dem":88,
    "gn:feature_class":"P",
    "gn:feature_code":"PPL",
    "gn:name":"Quhe",
    "gn:population":0,
    "gn:timezone":"Asia/Shanghai",
    "iso:country":"CN",
    "name:zho_x_preferred":[
        "Quhe"
    ],
    "name:zho_x_variant":[
        "\u66f2\u5408"
    ],
    "wof:name":"Quhe",
    "wof:placetype":"locality"
},
  "geometry": {"coordinates":[113.39167,25.07222],"type":"Point"}
}