{
  "type": "Feature",
  "properties": {
    "gn:admin1_code":"9.0",
    "gn:asciiname":"Yugang",
    "gn:country_code":"CN",
    "gn:dem":61,
    "gn:feature_class":"P",
    "gn:feature_code":"PPL",
    "gn:name":"Yugang",
    "gn:population":0,
    "gn:timezone":"Asia/Shanghai",
    "iso:country":"CN",
    "name:zho_x_preferred":[
        "\u90c1\u5c97"
    ],
    "wof:name":"Yugang",
    "wof:placetype":"locality"
},
  "geometry": {"coordinates":[114.43003,34.1459],"type":"Point"}
}