{
  "type": "Feature",
  "properties": {
    "gn:admin1_code":"24",
    "gn:asciiname":"Dingchang",
    "gn:country_code":"CN",
    "gn:dem":957,
    "gn:feature_class":"P",
    "gn:feature_code":"PPLA3",
    "gn:name":"Dingchang",
    "gn:population":0,
    "gn:timezone":"Asia/Shanghai",
    "iso:country":"CN",
    "name:und_x_variant":[
        "Qinxian",
        "Dingchang",
        "Qin Xian",
        "Dingchang Zhen",
        "\u6c81\u53bf",
        "\u5b9a\u660c\u9547"
    ],
    "name:zho_x_preferred":[
        "Ch\u2019in-hsien"
    ],
    "name:zho_x_variant":[
        "\u5b9a\u660c"
    ],
    "wof:name":"Dingchang",
    "wof:placetype":"locality"
},
  "geometry": {"coordinates":[112.68722,36.76306],"type":"Point"}
}