{
  "type": "Feature",
  "properties": {
    "gn:admin1_code":"11.0",
    "gn:asciiname":"Zhongxingyuan",
    "gn:country_code":"CN",
    "gn:dem":31,
    "gn:feature_class":"P",
    "gn:feature_code":"PPL",
    "gn:name":"Zhongxingyuan",
    "gn:population":0,
    "gn:timezone":"Asia/Shanghai",
    "iso:country":"CN",
    "name:zho_x_preferred":[
        "\u4e2d\u5174\u57b8"
    ],
    "wof:name":"Zhongxingyuan",
    "wof:placetype":"locality"
},
  "geometry": {"coordinates":[112.13965,29.53121],"type":"Point"}
}