{
  "type": "Feature",
  "properties": {
    "gn:admin1_code":"19.0",
    "gn:asciiname":"Dawanggou",
    "gn:country_code":"CN",
    "gn:dem":468,
    "gn:feature_class":"P",
    "gn:feature_code":"PPL",
    "gn:name":"Dawanggou",
    "gn:population":0,
    "gn:timezone":"Asia/Shanghai",
    "iso:country":"CN",
    "name:zho_x_preferred":[
        "\u5927\u6789\u6c9f"
    ],
    "wof:name":"Dawanggou",
    "wof:placetype":"locality"
},
  "geometry": {"coordinates":[125.30865,42.01944],"type":"Point"}
}