{
  "type": "Feature",
  "properties": {
    "gn:admin1_code":"10.0",
    "gn:asciiname":"Yinhecun",
    "gn:country_code":"CN",
    "gn:dem":1391,
    "gn:feature_class":"P",
    "gn:feature_code":"PPL",
    "gn:name":"Yinhecun",
    "gn:population":0,
    "gn:timezone":"Asia/Shanghai",
    "iso:country":"CN",
    "name:und_x_variant":[
        "\u94f6\u6cb3\u6751"
    ],
    "wof:name":"Yinhecun",
    "wof:placetype":"locality"
},
  "geometry": {"coordinates":[113.89033999999999,39.01051],"type":"Point"}
}