{
  "type": "Feature",
  "properties": {
    "gn:admin1_code":"19.0",
    "gn:asciiname":"Xigoulicun",
    "gn:country_code":"CN",
    "gn:dem":528,
    "gn:feature_class":"P",
    "gn:feature_code":"PPL",
    "gn:name":"Xigoulicun",
    "gn:population":0,
    "gn:timezone":"Asia/Shanghai",
    "iso:country":"CN",
    "name:zho_x_preferred":[
        "\u897f\u6c9f\u91cc\u6751"
    ],
    "wof:name":"Xigoulicun",
    "wof:placetype":"locality"
},
  "geometry": {"coordinates":[120.057,41.1282],"type":"Point"}
}