{
  "type": "Feature",
  "properties": {
    "gn:admin1_code":"18.0",
    "gn:asciiname":"Shidapo",
    "gn:country_code":"CN",
    "gn:dem":483,
    "gn:feature_class":"P",
    "gn:feature_code":"PPL",
    "gn:name":"Shidapo",
    "gn:population":0,
    "gn:timezone":"Asia/Shanghai",
    "iso:country":"CN",
    "name:zho_x_preferred":[
        "\u77f3\u5927\u5761"
    ],
    "wof:name":"Shidapo",
    "wof:placetype":"locality"
},
  "geometry": {"coordinates":[109.014,28.1619],"type":"Point"}
}