{
  "type": "Feature",
  "properties": {
    "gn:admin1_code":"14.0",
    "gn:asciiname":"Gewukongjian",
    "gn:country_code":"CN",
    "gn:dem":4423,
    "gn:feature_class":"P",
    "gn:feature_code":"PPL",
    "gn:name":"Gewukongjian",
    "gn:population":0,
    "gn:timezone":"Asia/Shanghai",
    "iso:country":"CN",
    "name:und_x_variant":[
        "Gegongjian",
        "Gewukongjian"
    ],
    "name:zho_x_preferred":[
        "\u683c\u516c\u95f4"
    ],
    "name:zho_x_variant":[
        "\u683c\u543e\u5b54\u95f4"
    ],
    "wof:name":"Gewukongjian",
    "wof:placetype":"locality"
},
  "geometry": {"coordinates":[79.4148,32.2018],"type":"Point"}
}