{
  "type": "Feature",
  "properties": {
    "gn:admin1_code":"32.0",
    "gn:asciiname":"Zhandi",
    "gn:country_code":"CN",
    "gn:dem":1002,
    "gn:feature_class":"P",
    "gn:feature_code":"PPL",
    "gn:name":"Zhandi",
    "gn:population":0,
    "gn:timezone":"Asia/Shanghai",
    "iso:country":"CN",
    "name:zho_x_preferred":[
        "\u7ad9\u5e95"
    ],
    "wof:name":"Zhandi",
    "wof:placetype":"locality"
},
  "geometry": {"coordinates":[105.55839,27.99076],"type":"Point"}
}