{
  "type": "Feature",
  "properties": {
    "gn:admin1_code":"32.0",
    "gn:asciiname":"Yade",
    "gn:country_code":"CN",
    "gn:dem":3272,
    "gn:feature_class":"P",
    "gn:feature_code":"PPL",
    "gn:name":"Yade",
    "gn:population":0,
    "gn:timezone":"Asia/Shanghai",
    "iso:country":"CN",
    "name:fra_x_preferred":[
        "Yade"
    ],
    "name:urd_x_preferred":[
        "\u06cc\u062f\u06d2"
    ],
    "name:zho_x_preferred":[
        "\u96c5\u5fb7"
    ],
    "wof:name":"Yade",
    "wof:placetype":"locality"
},
  "geometry": {"coordinates":[100.55889000000001,31.4661],"type":"Point"}
}