{
  "type": "Feature",
  "properties": {
    "gn:admin1_code":"11.0",
    "gn:asciiname":"Nuoxi",
    "gn:country_code":"CN",
    "gn:dem":698,
    "gn:feature_class":"P",
    "gn:feature_code":"PPL",
    "gn:name":"Nuoxi",
    "gn:population":0,
    "gn:timezone":"Asia/Shanghai",
    "iso:country":"CN",
    "name:zho_x_preferred":[
        "\u558f\u6eaa"
    ],
    "wof:name":"Nuoxi",
    "wof:placetype":"locality"
},
  "geometry": {"coordinates":[109.13842,27.26889000000001],"type":"Point"}
}