{
  "type": "Feature",
  "properties": {
    "gn:admin1_code":"29.0",
    "gn:asciiname":"Shangzuoyi",
    "gn:country_code":"CN",
    "gn:dem":1982,
    "gn:feature_class":"P",
    "gn:feature_code":"PPL",
    "gn:name":"Shangzuoyi",
    "gn:population":0,
    "gn:timezone":"Asia/Shanghai",
    "iso:country":"CN",
    "name:zho_x_preferred":[
        "\u4e0a\u4f5c\u9091"
    ],
    "wof:name":"Shangzuoyi",
    "wof:placetype":"locality"
},
  "geometry": {"coordinates":[100.122,25.8287],"type":"Point"}
}