{
  "type": "Feature",
  "properties": {
    "gn:admin1_code":"11.0",
    "gn:asciiname":"Shangmiaoxia",
    "gn:country_code":"CN",
    "gn:dem":401,
    "gn:feature_class":"P",
    "gn:feature_code":"PPL",
    "gn:name":"Shangmiaoxia",
    "gn:population":0,
    "gn:timezone":"Asia/Shanghai",
    "iso:country":"CN",
    "name:zho_x_preferred":[
        "\u4e0a\u5e99\u4e0b"
    ],
    "wof:name":"Shangmiaoxia",
    "wof:placetype":"locality"
},
  "geometry": {"coordinates":[113.05938,25.63435],"type":"Point"}
}