{
  "type": "Feature",
  "properties": {
    "gn:admin1_code":"19",
    "gn:asciiname":"Shicheng",
    "gn:country_code":"CN",
    "gn:dem":37,
    "gn:feature_class":"P",
    "gn:feature_code":"PPL",
    "gn:name":"Shicheng",
    "gn:population":0,
    "gn:timezone":"Asia/Shanghai",
    "iso:country":"CN",
    "wof:name":"Shicheng",
    "wof:placetype":"locality"
},
  "geometry": {"coordinates":[123.00667,39.52306],"type":"Point"}
}