{
  "type": "Feature",
  "properties": {
    "gn:admin1_code":"26.0",
    "gn:asciiname":"Cuijiagoucun",
    "gn:country_code":"CN",
    "gn:dem":974,
    "gn:feature_class":"P",
    "gn:feature_code":"PPL",
    "gn:name":"Cuijiagoucun",
    "gn:population":0,
    "gn:timezone":"Asia/Shanghai",
    "iso:country":"CN",
    "name:zho_x_preferred":[
        "\u5d14\u5bb6\u6c9f\u6751"
    ],
    "wof:name":"Cuijiagoucun",
    "wof:placetype":"locality"
},
  "geometry": {"coordinates":[110.07041,37.0216],"type":"Point"}
}