{
  "type": "Feature",
  "properties": {
    "gn:admin1_code":"4.0",
    "gn:asciiname":"Houchenjiashi",
    "gn:country_code":"CN",
    "gn:dem":7,
    "gn:feature_class":"P",
    "gn:feature_code":"PPL",
    "gn:name":"Houchenjiashi",
    "gn:population":0,
    "gn:timezone":"Asia/Shanghai",
    "iso:country":"CN",
    "name:und_x_variant":[
        "\u540e\u9648\u5bb6\u5e02"
    ],
    "name:zho_x_preferred":[
        "\u540e\u9648\u5bb6\u5e02"
    ],
    "wof:name":"Houchenjiashi",
    "wof:placetype":"locality"
},
  "geometry": {"coordinates":[120.17019000000001,32.31423],"type":"Point"}
}