{
  "type": "Feature",
  "properties": {
    "gn:admin1_code":"29.0",
    "gn:asciiname":"Laomangdan",
    "gn:country_code":"CN",
    "gn:dem":836,
    "gn:feature_class":"P",
    "gn:feature_code":"PPL",
    "gn:name":"Laomangdan",
    "gn:population":0,
    "gn:timezone":"Asia/Shanghai",
    "iso:country":"CN",
    "name:zho_x_preferred":[
        "\u8001\u8292\u80c6"
    ],
    "wof:name":"Laomangdan",
    "wof:placetype":"locality"
},
  "geometry": {"coordinates":[98.0348,24.7456],"type":"Point"}
}