{
  "type": "Feature",
  "properties": {
    "gn:admin1_code":"6.0",
    "gn:asciiname":"Banjiutong",
    "gn:country_code":"CN",
    "gn:dem":3879,
    "gn:feature_class":"P",
    "gn:feature_code":"PPL",
    "gn:name":"Banjiutong",
    "gn:population":0,
    "gn:timezone":"Asia/Urumqi",
    "iso:country":"CN",
    "name:zho_x_preferred":[
        "\u73ed\u4e45\u540c"
    ],
    "wof:name":"Banjiutong",
    "wof:placetype":"locality"
},
  "geometry": {"coordinates":[96.39363,33.69712],"type":"Point"}
}