{
  "type": "Feature",
  "properties": {
    "gn:admin1_code":"31",
    "gn:asciiname":"Wugongli",
    "gn:country_code":"CN",
    "gn:dem":287,
    "gn:feature_class":"P",
    "gn:feature_code":"PPL",
    "gn:name":"Wugongli",
    "gn:population":0,
    "gn:timezone":"Asia/Shanghai",
    "iso:country":"CN",
    "name:und_x_variant":[
        "\u4e94\u516c\u91cc"
    ],
    "wof:name":"Wugongli",
    "wof:placetype":"locality"
},
  "geometry": {"coordinates":[109.879,19.1781],"type":"Point"}
}