{
  "type": "Feature",
  "properties": {
    "gn:admin1_code":"3.0",
    "gn:asciiname":"Kankeng",
    "gn:country_code":"CN",
    "gn:dem":390,
    "gn:feature_class":"P",
    "gn:feature_code":"PPL",
    "gn:name":"Kankeng",
    "gn:population":0,
    "gn:timezone":"Asia/Shanghai",
    "iso:country":"CN",
    "name:und_x_variant":[
        "\u574e\u5751"
    ],
    "wof:name":"Kankeng",
    "wof:placetype":"locality"
},
  "geometry": {"coordinates":[114.09308,27.52371],"type":"Point"}
}