{
  "type": "Feature",
  "properties": {
    "gn:admin1_code":"12.0",
    "gn:asciiname":"Dengtongfu",
    "gn:country_code":"CN",
    "gn:dem":56,
    "gn:feature_class":"P",
    "gn:feature_code":"PPL",
    "gn:name":"Dengtongfu",
    "gn:population":0,
    "gn:timezone":"Asia/Shanghai",
    "iso:country":"CN",
    "name:zho_x_preferred":[
        "Dengtongfu"
    ],
    "name:zho_x_variant":[
        "\u9093\u901a\u5e9c"
    ],
    "wof:name":"Dengtongfu",
    "wof:placetype":"locality"
},
  "geometry": {"coordinates":[115.03737,29.89552],"type":"Point"}
}