{
  "type": "Feature",
  "properties": {
    "gn:admin1_code":"8.0",
    "gn:asciiname":"Jianxincun",
    "gn:country_code":"CN",
    "gn:dem":126,
    "gn:feature_class":"P",
    "gn:feature_code":"PPL",
    "gn:name":"Jianxincun",
    "gn:population":0,
    "gn:timezone":"Asia/Shanghai",
    "iso:country":"CN",
    "name:zho_x_preferred":[
        "\u5efa\u65b0\u6751"
    ],
    "wof:name":"Jianxincun",
    "wof:placetype":"locality"
},
  "geometry": {"coordinates":[127.89606000000001,46.03064000000001],"type":"Point"}
}