{
  "type": "Feature",
  "properties": {
    "gn:admin1_code":"24.0",
    "gn:asciiname":"Yuping",
    "gn:cc2":"CN",
    "gn:country_code":"CN",
    "gn:dem":1031,
    "gn:feature_class":"P",
    "gn:feature_code":"PPL",
    "gn:name":"Yuping",
    "gn:population":0,
    "gn:timezone":"Asia/Shanghai",
    "iso:country":"CN",
    "name:und_x_variant":[
        "Y\u00fc-ch\u2019ien-ts\u2019un",
        "Y\u00fc-p\u2019ing-ts\u2019un",
        "Yuping"
    ],
    "wof:name":"Yuping",
    "wof:placetype":"locality"
},
  "geometry": {"coordinates":[111.07889,37.92861],"type":"Point"}
}