{
  "type": "Feature",
  "properties": {
    "gn:admin1_code":"11.0",
    "gn:asciiname":"Gaoyuan",
    "gn:country_code":"CN",
    "gn:dem":123,
    "gn:feature_class":"P",
    "gn:feature_code":"PPL",
    "gn:name":"Gaoyuan",
    "gn:population":0,
    "gn:timezone":"Asia/Shanghai",
    "iso:country":"CN",
    "name:zho_x_preferred":[
        "\u768b\u82ab"
    ],
    "wof:name":"Gaoyuan",
    "wof:placetype":"locality"
},
  "geometry": {"coordinates":[113.5539,26.6998],"type":"Point"}
}