{
  "type": "Feature",
  "properties": {
    "gn:admin1_code":"22.0",
    "gn:asciiname":"Taishituncun",
    "gn:country_code":"CN",
    "gn:dem":172,
    "gn:feature_class":"P",
    "gn:feature_code":"PPL",
    "gn:name":"Taishituncun",
    "gn:population":0,
    "gn:timezone":"Asia/Shanghai",
    "iso:country":"CN",
    "name:zho_x_preferred":[
        "\u592a\u5e08\u5c6f\u6751"
    ],
    "wof:name":"Taishituncun",
    "wof:placetype":"locality"
},
  "geometry": {"coordinates":[117.11337,40.53968],"type":"Point"}
}