{
  "type": "Feature",
  "properties": {
    "gn:admin1_code":"33.0",
    "gn:asciiname":"Shili",
    "gn:country_code":"CN",
    "gn:dem":537,
    "gn:feature_class":"P",
    "gn:feature_code":"PPL",
    "gn:name":"Shili",
    "gn:population":0,
    "gn:timezone":"Asia/Shanghai",
    "iso:country":"CN",
    "name:ara_x_preferred":[
        "\u0634\u064a\u0644\u064a"
    ],
    "name:fas_x_preferred":[
        "\u0634\u06cc\u0644\u06cc"
    ],
    "name:msa_x_preferred":[
        "Shili"
    ],
    "name:zho_x_preferred":[
        "\u77f3\u9ca4"
    ],
    "wof:name":"Shili",
    "wof:placetype":"locality"
},
  "geometry": {"coordinates":[107.82301,30.49903],"type":"Point"}
}