{
  "type": "Feature",
  "properties": {
    "gn:admin1_code":"7.0",
    "gn:asciiname":"Xinanban",
    "gn:country_code":"CN",
    "gn:dem":27,
    "gn:feature_class":"P",
    "gn:feature_code":"PPL",
    "gn:name":"Xinanban",
    "gn:population":0,
    "gn:timezone":"Asia/Shanghai",
    "iso:country":"CN",
    "name:und_x_variant":[
        "Hsin-an-pan",
        "Xinanban"
    ],
    "name:zho_x_preferred":[
        "\u6eaa\u5357\u5742"
    ],
    "wof:name":"Xinanban",
    "wof:placetype":"locality"
},
  "geometry": {"coordinates":[117.55414,24.90143],"type":"Point"}
}