{
  "type": "Feature",
  "properties": {
    "gn:admin1_code":"9.0",
    "gn:asciiname":"Zheshan",
    "gn:country_code":"CN",
    "gn:dem":182,
    "gn:feature_class":"P",
    "gn:feature_code":"PPLA4",
    "gn:name":"Zheshan",
    "gn:population":0,
    "gn:timezone":"Asia/Shanghai",
    "iso:country":"CN",
    "name:und_x_variant":[
        "\u906e\u5c71",
        "Zheshan Zhen",
        "\u906e\u5c71\u9547",
        "Zheshan"
    ],
    "wof:name":"Zheshan",
    "wof:placetype":"locality"
},
  "geometry": {"coordinates":[112.35167,33.04464],"type":"Point"}
}