{
  "type": "Feature",
  "properties": {
    "gn:admin1_code":"33.0",
    "gn:asciiname":"Xingjia",
    "gn:country_code":"CN",
    "gn:dem":257,
    "gn:feature_class":"P",
    "gn:feature_code":"PPL",
    "gn:name":"Xingjia",
    "gn:population":0,
    "gn:timezone":"Asia/Shanghai",
    "iso:country":"CN",
    "name:zho_x_preferred":[
        "\u5211\u5bb6"
    ],
    "wof:name":"Xingjia",
    "wof:placetype":"locality"
},
  "geometry": {"coordinates":[106.05544,29.26642],"type":"Point"}
}