{
  "type": "Feature",
  "properties": {
    "gn:admin1_code":"07",
    "gn:asciiname":"Shanqian",
    "gn:cc2":"CN",
    "gn:country_code":"CN",
    "gn:dem":234,
    "gn:feature_class":"P",
    "gn:feature_code":"PPL",
    "gn:name":"Shanqian",
    "gn:population":0,
    "gn:timezone":"Asia/Shanghai",
    "iso:country":"CN",
    "name:und_x_variant":[
        "Shan-ch\u2019ien",
        "Shanqian"
    ],
    "wof:name":"Shanqian",
    "wof:placetype":"locality"
},
  "geometry": {"coordinates":[117.96666999999999,27.63333],"type":"Point"}
}