{
  "type": "Feature",
  "properties": {
    "gn:admin1_code":"29",
    "gn:asciiname":"Zhonghe",
    "gn:country_code":"CN",
    "gn:dem":1353,
    "gn:feature_class":"P",
    "gn:feature_code":"PPL",
    "gn:name":"Zhonghe",
    "gn:population":0,
    "gn:timezone":"Asia/Shanghai",
    "iso:country":"CN",
    "name:zho_x_preferred":[
        "\u4e2d\u548c"
    ],
    "wof:name":"Zhonghe",
    "wof:placetype":"locality"
},
  "geometry": {"coordinates":[105.49299999999999,23.2373],"type":"Point"}
}