{
  "type": "Feature",
  "properties": {
    "gn:admin1_code":"25.0",
    "gn:asciiname":"Liangxiang",
    "gn:cc2":"CN",
    "gn:country_code":"CN",
    "gn:dem":70,
    "gn:feature_class":"P",
    "gn:feature_code":"PPL",
    "gn:name":"Liangxiang",
    "gn:population":0,
    "gn:timezone":"Asia/Shanghai",
    "iso:country":"CN",
    "name:zho_x_preferred":[
        "\u826f\u4e61"
    ],
    "wof:name":"Liangxiang",
    "wof:placetype":"locality"
},
  "geometry": {"coordinates":[119.70931000000002,36.06382],"type":"Point"}
}