{
  "type": "Feature",
  "properties": {
    "gn:admin1_code":"19.0",
    "gn:asciiname":"Manjianghong",
    "gn:country_code":"CN",
    "gn:dem":145,
    "gn:feature_class":"P",
    "gn:feature_code":"PPL",
    "gn:name":"Manjianghong",
    "gn:population":0,
    "gn:timezone":"Asia/Shanghai",
    "iso:country":"CN",
    "name:zho_x_preferred":[
        "\u6ee1\u6c5f\u7ea2"
    ],
    "wof:name":"Manjianghong",
    "wof:placetype":"locality"
},
  "geometry": {"coordinates":[125.44,40.6717],"type":"Point"}
}