{
  "type": "Feature",
  "properties": {
    "gn:admin1_code":"9.0",
    "gn:asciiname":"Houzhuang",
    "gn:country_code":"CN",
    "gn:dem":220,
    "gn:feature_class":"P",
    "gn:feature_code":"PPL",
    "gn:name":"Houzhuang",
    "gn:population":0,
    "gn:timezone":"Asia/Shanghai",
    "iso:country":"CN",
    "name:und_x_variant":[
        "\u540e\u5e84",
        "Houzhuang"
    ],
    "wof:name":"Houzhuang",
    "wof:placetype":"locality"
},
  "geometry": {"coordinates":[112.54702,33.43364],"type":"Point"}
}