{
  "type": "Feature",
  "properties": {
    "gn:admin1_code":"30",
    "gn:asciiname":"Chilingcun",
    "gn:country_code":"CN",
    "gn:dem":41,
    "gn:feature_class":"P",
    "gn:feature_code":"PPL",
    "gn:name":"Chilingcun",
    "gn:population":0,
    "gn:timezone":"Asia/Urumqi",
    "iso:country":"CN",
    "name:zho_x_preferred":[
        "\u8d64\u5cad\u6751"
    ],
    "wof:name":"Chilingcun",
    "wof:placetype":"locality"
},
  "geometry": {"coordinates":[111.03077,21.7117],"type":"Point"}
}