{
  "type": "Feature",
  "properties": {
    "gn:admin1_code":"14.0",
    "gn:asciiname":"Ge'e",
    "gn:country_code":"CN",
    "gn:dem":4834,
    "gn:feature_class":"P",
    "gn:feature_code":"PPL",
    "gn:name":"Ge\u2019e",
    "gn:population":0,
    "gn:timezone":"Asia/Urumqi",
    "iso:country":"CN",
    "name:und_x_variant":[
        "Ge\u2019e"
    ],
    "name:zho_x_preferred":[
        "\u9769\u5a25"
    ],
    "wof:name":"Ge'e",
    "wof:placetype":"locality"
},
  "geometry": {"coordinates":[85.2089,30.5201],"type":"Point"}
}