{
  "type": "Feature",
  "properties": {
    "gn:admin1_code":"3.0",
    "gn:asciiname":"Heyetang",
    "gn:country_code":"CN",
    "gn:dem":106,
    "gn:feature_class":"P",
    "gn:feature_code":"PPL",
    "gn:name":"Heyetang",
    "gn:population":0,
    "gn:timezone":"Asia/Shanghai",
    "iso:country":"CN",
    "name:zho_x_preferred":[
        "\u8377\u53f6\u5858"
    ],
    "wof:name":"Heyetang",
    "wof:placetype":"locality"
},
  "geometry": {"coordinates":[113.80200000000001,27.5713],"type":"Point"}
}