{
  "type": "Feature",
  "properties": {
    "gn:admin1_code":"4.0",
    "gn:asciiname":"Changxicun",
    "gn:country_code":"CN",
    "gn:dem":6,
    "gn:feature_class":"P",
    "gn:feature_code":"PPL",
    "gn:name":"Changxicun",
    "gn:population":0,
    "gn:timezone":"Asia/Shanghai",
    "iso:country":"CN",
    "name:und_x_variant":[
        "\u5e38\u9521\u6751"
    ],
    "name:zho_x_preferred":[
        "\u5e38\u9521\u6751"
    ],
    "wof:name":"Changxicun",
    "wof:placetype":"locality"
},
  "geometry": {"coordinates":[120.57557,31.57485],"type":"Point"}
}