{
  "type": "Feature",
  "properties": {
    "gn:admin1_code":"5.0",
    "gn:asciiname":"Houmozijing",
    "gn:country_code":"CN",
    "gn:dem":146,
    "gn:feature_class":"P",
    "gn:feature_code":"PPL",
    "gn:name":"Houmozijing",
    "gn:population":0,
    "gn:timezone":"Asia/Shanghai",
    "iso:country":"CN",
    "name:zho_x_preferred":[
        "\u540e\u58a8\u5b57\u4e95"
    ],
    "wof:name":"Houmozijing",
    "wof:placetype":"locality"
},
  "geometry": {"coordinates":[124.13912999999999,44.92368],"type":"Point"}
}