{
  "type": "Feature",
  "properties": {
    "gn:admin1_code":"11",
    "gn:asciiname":"Longjiawan",
    "gn:country_code":"CN",
    "gn:dem":105,
    "gn:feature_class":"P",
    "gn:feature_code":"PPL",
    "gn:name":"Longjiawan",
    "gn:population":0,
    "gn:timezone":"Asia/Shanghai",
    "iso:country":"CN",
    "name:zho_x_preferred":[
        "\u9f99\u5bb6\u6e7e"
    ],
    "wof:name":"Longjiawan",
    "wof:placetype":"locality"
},
  "geometry": {"coordinates":[112.26944,27.61578],"type":"Point"}
}