{
  "type": "Feature",
  "properties": {
    "gn:admin1_code":"11.0",
    "gn:asciiname":"Mulinjiao",
    "gn:country_code":"CN",
    "gn:dem":335,
    "gn:feature_class":"P",
    "gn:feature_code":"PPL",
    "gn:name":"Mulinjiao",
    "gn:population":0,
    "gn:timezone":"Asia/Shanghai",
    "iso:country":"CN",
    "name:zho_x_preferred":[
        "\u6728\u6797\u811a"
    ],
    "wof:name":"Mulinjiao",
    "wof:placetype":"locality"
},
  "geometry": {"coordinates":[109.80579,26.62157],"type":"Point"}
}