{
  "type": "Feature",
  "properties": {
    "gn:admin1_code":"08",
    "gn:asciiname":"Kaidaocun",
    "gn:country_code":"CN",
    "gn:dem":396,
    "gn:feature_class":"P",
    "gn:feature_code":"PPL",
    "gn:name":"Kaidaocun",
    "gn:population":0,
    "gn:timezone":"Asia/Shanghai",
    "iso:country":"CN",
    "name:und_x_variant":[
        "K\u2019ai-tao",
        "Kaidao",
        "Kaidaocun"
    ],
    "name:zho_x_preferred":[
        "\u5f00\u9053"
    ],
    "name:zho_x_variant":[
        "\u5f00\u9053\u6751"
    ],
    "wof:name":"Kaidaocun",
    "wof:placetype":"locality"
},
  "geometry": {"coordinates":[128.90469999999999,44.93009],"type":"Point"}
}