{
  "type": "Feature",
  "properties": {
    "gn:admin1_code":"15.0",
    "gn:asciiname":"Jiaowan",
    "gn:country_code":"CN",
    "gn:dem":2197,
    "gn:feature_class":"P",
    "gn:feature_code":"PPL",
    "gn:name":"Jiaowan",
    "gn:population":0,
    "gn:timezone":"Asia/Shanghai",
    "iso:country":"CN",
    "name:zho_x_preferred":[
        "\u7126\u6e7e"
    ],
    "wof:name":"Jiaowan",
    "wof:placetype":"locality"
},
  "geometry": {"coordinates":[101.292,38.5259],"type":"Point"}
}