{
  "type": "Feature",
  "properties": {
    "gn:admin1_code":"11.0",
    "gn:asciiname":"Shangjintang",
    "gn:country_code":"CN",
    "gn:dem":292,
    "gn:feature_class":"P",
    "gn:feature_code":"PPL",
    "gn:name":"Shangjintang",
    "gn:population":0,
    "gn:timezone":"Asia/Shanghai",
    "iso:country":"CN",
    "name:zho_x_preferred":[
        "\u4e0a\u91d1\u5858"
    ],
    "wof:name":"Shangjintang",
    "wof:placetype":"locality"
},
  "geometry": {"coordinates":[110.83452,27.11108],"type":"Point"}
}