{
  "type": "Feature",
  "properties": {
    "gn:admin1_code":"30",
    "gn:asciiname":"Chachang",
    "gn:country_code":"CN",
    "gn:dem":363,
    "gn:feature_class":"P",
    "gn:feature_code":"PPL",
    "gn:name":"Chachang",
    "gn:population":0,
    "gn:timezone":"Asia/Shanghai",
    "iso:country":"CN",
    "name:rus_x_preferred":[
        "\u0427\u0430\u043d\u0447\u0443\u043d\u044c"
    ],
    "name:zho_x_preferred":[
        "\u8336\u573a"
    ],
    "wof:name":"Chachang",
    "wof:placetype":"locality"
},
  "geometry": {"coordinates":[116.94161,24.1759],"type":"Point"}
}