{
  "type": "Feature",
  "properties": {
    "gn:admin1_code":"16.0",
    "gn:asciiname":"Dalachao",
    "gn:country_code":"CN",
    "gn:dem":656,
    "gn:feature_class":"P",
    "gn:feature_code":"PPL",
    "gn:name":"Dalachao",
    "gn:population":0,
    "gn:timezone":"Asia/Shanghai",
    "iso:country":"CN",
    "name:zho_x_preferred":[
        "\u6253\u62c9\u671d"
    ],
    "wof:name":"Dalachao",
    "wof:placetype":"locality"
},
  "geometry": {"coordinates":[107.113,25.4634],"type":"Point"}
}