{
  "type": "Feature",
  "properties": {
    "gn:admin1_code":"29",
    "gn:asciiname":"Jingang",
    "gn:country_code":"CN",
    "gn:dem":1893,
    "gn:feature_class":"P",
    "gn:feature_code":"PPL",
    "gn:name":"Jingang",
    "gn:population":0,
    "gn:timezone":"Asia/Shanghai",
    "iso:country":"CN",
    "name:zho_x_preferred":[
        "\u91d1\u521a"
    ],
    "wof:name":"Jingang",
    "wof:placetype":"locality"
},
  "geometry": {"coordinates":[102.74755,24.97326],"type":"Point"}
}