{
  "type": "Feature",
  "properties": {
    "gn:admin1_code":"29.0",
    "gn:asciiname":"Xuehua Xicun",
    "gn:country_code":"CN",
    "gn:dem":3030,
    "gn:feature_class":"P",
    "gn:feature_code":"PPL",
    "gn:name":"Xuehua Xicun",
    "gn:population":0,
    "gn:timezone":"Asia/Shanghai",
    "iso:country":"CN",
    "name:zho_x_preferred":[
        "\u96ea\u82b1\u897f\u6751"
    ],
    "wof:name":"Xuehua Xicun",
    "wof:placetype":"locality"
},
  "geometry": {"coordinates":[100.14,27.0242],"type":"Point"}
}