{
  "type": "Feature",
  "properties": {
    "gn:admin1_code":"14.0",
    "gn:asciiname":"Luo'enze",
    "gn:country_code":"CN",
    "gn:dem":4659,
    "gn:feature_class":"P",
    "gn:feature_code":"PPL",
    "gn:name":"Luo\u2019enze",
    "gn:population":0,
    "gn:timezone":"Asia/Urumqi",
    "iso:country":"CN",
    "name:und_x_variant":[
        "Luo\u2019enze"
    ],
    "name:zho_x_preferred":[
        "\u7f57\u6069\u6cfd"
    ],
    "wof:name":"Luo'enze",
    "wof:placetype":"locality"
},
  "geometry": {"coordinates":[94.23371,31.11086],"type":"Point"}
}