{
  "type": "Feature",
  "properties": {
    "gn:admin1_code":"21.0",
    "gn:asciiname":"Kongjiagou",
    "gn:country_code":"CN",
    "gn:dem":2105,
    "gn:feature_class":"P",
    "gn:feature_code":"PPL",
    "gn:name":"Kongjiagou",
    "gn:population":0,
    "gn:timezone":"Asia/Shanghai",
    "iso:country":"CN",
    "name:zho_x_preferred":[
        "\u5b54\u5bb6\u6c9f"
    ],
    "wof:name":"Kongjiagou",
    "wof:placetype":"locality"
},
  "geometry": {"coordinates":[105.22799999999999,36.7191],"type":"Point"}
}