{
  "type": "Feature",
  "properties": {
    "gn:admin1_code":"10",
    "gn:asciiname":"Guanchang Goumen",
    "gn:country_code":"CN",
    "gn:dem":946,
    "gn:feature_class":"P",
    "gn:feature_code":"PPL",
    "gn:name":"Guanchang Goumen",
    "gn:population":0,
    "gn:timezone":"Asia/Shanghai",
    "iso:country":"CN",
    "name:zho_x_preferred":[
        "\u5b98\u573a\u6c9f\u95e8"
    ],
    "wof:name":"Guanchang Goumen",
    "wof:placetype":"locality"
},
  "geometry": {"coordinates":[116.39712,40.99581],"type":"Point"}
}