{
  "type": "Feature",
  "properties": {
    "gn:admin1_code":"10",
    "gn:asciiname":"Zhangjiawa",
    "gn:country_code":"CN",
    "gn:dem":46,
    "gn:feature_class":"P",
    "gn:feature_code":"PPL",
    "gn:name":"Zhangjiawa",
    "gn:population":0,
    "gn:timezone":"Asia/Shanghai",
    "iso:country":"CN",
    "name:und_x_variant":[
        "Chang-chia-wa",
        "Zhangjiawa"
    ],
    "name:zho_x_preferred":[
        "\u5f20\u5bb6\u6d3c"
    ],
    "wof:name":"Zhangjiawa",
    "wof:placetype":"locality"
},
  "geometry": {"coordinates":[117.85581000000001,40.1717],"type":"Point"}
}