{
  "type": "Feature",
  "properties": {
    "gn:admin1_code":"19.0",
    "gn:asciiname":"Qujiatai",
    "gn:country_code":"CN",
    "gn:dem":67,
    "gn:feature_class":"P",
    "gn:feature_code":"PPL",
    "gn:name":"Qujiatai",
    "gn:population":0,
    "gn:timezone":"Asia/Shanghai",
    "iso:country":"CN",
    "name:zho_x_preferred":[
        "\u66f2\u5bb6\u53f0"
    ],
    "wof:name":"Qujiatai",
    "wof:placetype":"locality"
},
  "geometry": {"coordinates":[122.11869,39.62592],"type":"Point"}
}