{
  "type": "Feature",
  "properties": {
    "gn:admin1_code":"10",
    "gn:asciiname":"Bujiadian",
    "gn:country_code":"CN",
    "gn:dem":1035,
    "gn:feature_class":"P",
    "gn:feature_code":"PPL",
    "gn:name":"Bujiadian",
    "gn:population":0,
    "gn:timezone":"Asia/Shanghai",
    "iso:country":"CN",
    "name:zho_x_preferred":[
        "\u6b65\u5bb6\u5e97"
    ],
    "wof:name":"Bujiadian",
    "wof:placetype":"locality"
},
  "geometry": {"coordinates":[118.04582000000001,41.71554],"type":"Point"}
}