{
  "type": "Feature",
  "properties": {
    "gn:admin1_code":"11.0",
    "gn:asciiname":"Bainiushan",
    "gn:country_code":"CN",
    "gn:dem":196,
    "gn:feature_class":"P",
    "gn:feature_code":"PPL",
    "gn:name":"Bainiushan",
    "gn:population":0,
    "gn:timezone":"Asia/Shanghai",
    "iso:country":"CN",
    "name:zho_x_preferred":[
        "\u767d\u725b\u5c71"
    ],
    "wof:name":"Bainiushan",
    "wof:placetype":"locality"
},
  "geometry": {"coordinates":[111.93317999999999,27.29434],"type":"Point"}
}