{
  "type": "Feature",
  "properties": {
    "gn:admin1_code":"18",
    "gn:asciiname":"Nuozhe",
    "gn:country_code":"CN",
    "gn:dem":1929,
    "gn:feature_class":"P",
    "gn:feature_code":"PPL",
    "gn:name":"Nuozhe",
    "gn:population":0,
    "gn:timezone":"Asia/Shanghai",
    "iso:country":"CN",
    "name:zho_x_preferred":[
        "\u8bfa\u7740"
    ],
    "wof:name":"Nuozhe",
    "wof:placetype":"locality"
},
  "geometry": {"coordinates":[103.872,26.7014],"type":"Point"}
}