{
  "type": "Feature",
  "properties": {
    "gn:admin1_code":"26.0",
    "gn:asciiname":"Wujiacun",
    "gn:country_code":"CN",
    "gn:dem":1026,
    "gn:feature_class":"P",
    "gn:feature_code":"PPL",
    "gn:name":"Wujiacun",
    "gn:population":0,
    "gn:timezone":"Asia/Shanghai",
    "iso:country":"CN",
    "name:zho_x_preferred":[
        "\u6b66\u5bb6\u6751"
    ],
    "wof:name":"Wujiacun",
    "wof:placetype":"locality"
},
  "geometry": {"coordinates":[108.31348,34.90439],"type":"Point"}
}