{
  "type": "Feature",
  "properties": {
    "gn:admin1_code":"15.0",
    "gn:asciiname":"Yangjia Caozhuang",
    "gn:country_code":"CN",
    "gn:dem":1806,
    "gn:feature_class":"P",
    "gn:feature_code":"PPL",
    "gn:name":"Yangjia Caozhuang",
    "gn:population":0,
    "gn:timezone":"Asia/Shanghai",
    "iso:country":"CN",
    "name:zho_x_preferred":[
        "\u6768\u5bb6\u8349\u5e84"
    ],
    "wof:name":"Yangjia Caozhuang",
    "wof:placetype":"locality"
},
  "geometry": {"coordinates":[102.247,38.1643],"type":"Point"}
}