{
  "type": "Feature",
  "properties": {
    "gn:admin1_code":"30.0",
    "gn:asciiname":"Xinqiao",
    "gn:country_code":"CN",
    "gn:dem":15,
    "gn:feature_class":"P",
    "gn:feature_code":"PPLA4",
    "gn:name":"Xinqiao",
    "gn:population":0,
    "gn:timezone":"Asia/Shanghai",
    "iso:country":"CN",
    "name:fas_x_preferred":[
        "\u0634\u06cc\u0646\u06a9\u06cc\u0627\u0648"
    ],
    "name:und_x_variant":[
        "Hsin-ch\u2019iao",
        "Hsin-ch\u2019iao-hs\u00fc",
        "Xinqiao",
        "Xinqiao Zhen",
        "\u65b0\u6865\u9547"
    ],
    "name:zho_x_preferred":[
        "\u65b0\u6865"
    ],
    "name:zho_x_variant":[
        "\u65b0\u6865\u9547"
    ],
    "wof:name":"Xinqiao",
    "wof:placetype":"locality"
},
  "geometry": {"coordinates":[112.41025999999999,22.95447],"type":"Point"}
}