{
  "type": "Feature",
  "properties": {
    "gn:admin1_code":"29",
    "gn:asciiname":"Shabagou",
    "gn:country_code":"CN",
    "gn:dem":1935,
    "gn:feature_class":"P",
    "gn:feature_code":"PPL",
    "gn:name":"Shabagou",
    "gn:population":0,
    "gn:timezone":"Asia/Shanghai",
    "iso:country":"CN",
    "name:zho_x_preferred":[
        "\u6c99\u575d\u6c9f"
    ],
    "wof:name":"Shabagou",
    "wof:placetype":"locality"
},
  "geometry": {"coordinates":[102.80200000000001,24.0582],"type":"Point"}
}