{
  "type": "Feature",
  "properties": {
    "gn:admin1_code":"8.0",
    "gn:asciiname":"Pingyanghekou",
    "gn:country_code":"CN",
    "gn:dem":112,
    "gn:feature_class":"P",
    "gn:feature_code":"PPL",
    "gn:name":"Pingyanghekou",
    "gn:population":0,
    "gn:timezone":"Asia/Shanghai",
    "iso:country":"CN",
    "name:zho_x_preferred":[
        "\u5e73\u9633\u6cb3\u53e3"
    ],
    "wof:name":"Pingyanghekou",
    "wof:placetype":"locality"
},
  "geometry": {"coordinates":[129.35858999999999,49.34515],"type":"Point"}
}