{
  "type": "Feature",
  "properties": {
    "gn:admin1_code":"33.0",
    "gn:asciiname":"Qinggang",
    "gn:country_code":"CN",
    "gn:dem":689,
    "gn:feature_class":"P",
    "gn:feature_code":"PPL",
    "gn:name":"Qinggang",
    "gn:population":0,
    "gn:timezone":"Asia/Shanghai",
    "iso:country":"CN",
    "name:zho_x_preferred":[
        "\u9752\u6760"
    ],
    "wof:name":"Qinggang",
    "wof:placetype":"locality"
},
  "geometry": {"coordinates":[108.58857999999999,31.26785],"type":"Point"}
}