{
  "type": "Feature",
  "properties": {
    "gn:admin1_code":"29.0",
    "gn:asciiname":"Dazhangjing",
    "gn:country_code":"CN",
    "gn:dem":1402,
    "gn:feature_class":"P",
    "gn:feature_code":"PPL",
    "gn:name":"Dazhangjing",
    "gn:population":0,
    "gn:timezone":"Asia/Shanghai",
    "iso:country":"CN",
    "name:zho_x_preferred":[
        "\u5927\u7ae0\u666f"
    ],
    "wof:name":"Dazhangjing",
    "wof:placetype":"locality"
},
  "geometry": {"coordinates":[100.477,24.2257],"type":"Point"}
}