{
  "type": "Feature",
  "properties": {
    "gn:admin1_code":"18.0",
    "gn:asciiname":"Gangcun",
    "gn:country_code":"CN",
    "gn:dem":1504,
    "gn:feature_class":"P",
    "gn:feature_code":"PPL",
    "gn:name":"Gangcun",
    "gn:population":0,
    "gn:timezone":"Asia/Shanghai",
    "iso:country":"CN",
    "wof:name":"Gangcun",
    "wof:placetype":"locality"
},
  "geometry": {"coordinates":[107.52889,29.17806],"type":"Point"}
}