{
  "type": "Feature",
  "properties": {
    "gn:admin1_code":"26.0",
    "gn:asciiname":"Jiashangoucun",
    "gn:country_code":"CN",
    "gn:dem":1267,
    "gn:feature_class":"P",
    "gn:feature_code":"PPL",
    "gn:name":"Jiashangoucun",
    "gn:population":0,
    "gn:timezone":"Asia/Shanghai",
    "iso:country":"CN",
    "name:und_x_variant":[
        "\u5939\u5c71\u6c9f\u6751"
    ],
    "wof:name":"Jiashangoucun",
    "wof:placetype":"locality"
},
  "geometry": {"coordinates":[107.05571999999999,33.83276],"type":"Point"}
}