{
  "type": "Feature",
  "properties": {
    "gn:admin1_code":"4.0",
    "gn:asciiname":"Lukou",
    "gn:country_code":"CN",
    "gn:dem":28,
    "gn:feature_class":"P",
    "gn:feature_code":"PPL",
    "gn:name":"Lukou",
    "gn:population":0,
    "gn:timezone":"Asia/Shanghai",
    "iso:country":"CN",
    "name:deu_x_preferred":[
        "Lukou"
    ],
    "name:zho_x_preferred":[
        "\u9646\u53e3"
    ],
    "wof:name":"Lukou",
    "wof:placetype":"locality"
},
  "geometry": {"coordinates":[118.08280000000001,34.26945],"type":"Point"}
}