{
  "type": "Feature",
  "properties": {
    "gn:admin1_code":"8.0",
    "gn:asciiname":"Daliangzi",
    "gn:country_code":"CN",
    "gn:dem":110,
    "gn:feature_class":"P",
    "gn:feature_code":"PPL",
    "gn:name":"Daliangzi",
    "gn:population":0,
    "gn:timezone":"Asia/Shanghai",
    "iso:country":"CN",
    "name:zho_x_preferred":[
        "\u5927\u4eae\u5b50"
    ],
    "wof:name":"Daliangzi",
    "wof:placetype":"locality"
},
  "geometry": {"coordinates":[126.85160999999999,45.95914000000001],"type":"Point"}
}