{
  "type": "Feature",
  "properties": {
    "gn:admin1_code":"32.0",
    "gn:asciiname":"Refuwu",
    "gn:country_code":"CN",
    "gn:dem":2742,
    "gn:feature_class":"P",
    "gn:feature_code":"PPL",
    "gn:name":"Refuwu",
    "gn:population":0,
    "gn:timezone":"Asia/Shanghai",
    "iso:country":"CN",
    "name:zho_x_preferred":[
        "\u70ed\u592b\u5c4b"
    ],
    "wof:name":"Refuwu",
    "wof:placetype":"locality"
},
  "geometry": {"coordinates":[102.81,28.5903],"type":"Point"}
}