{
  "type": "Feature",
  "properties": {
    "gn:admin1_code":"1.0",
    "gn:asciiname":"Tiemencun",
    "gn:country_code":"CN",
    "gn:dem":13,
    "gn:feature_class":"P",
    "gn:feature_code":"PPL",
    "gn:name":"Tiemencun",
    "gn:population":0,
    "gn:timezone":"Asia/Shanghai",
    "iso:country":"CN",
    "name:zho_x_preferred":[
        "\u94c1\u95e8\u6751"
    ],
    "wof:name":"Tiemencun",
    "wof:placetype":"locality"
},
  "geometry": {"coordinates":[118.18808,31.07172000000001],"type":"Point"}
}