{
  "type": "Feature",
  "properties": {
    "gn:admin1_code":"12.0",
    "gn:asciiname":"Weizhou",
    "gn:country_code":"CN",
    "gn:dem":24,
    "gn:feature_class":"P",
    "gn:feature_code":"PPL",
    "gn:name":"Weizhou",
    "gn:population":0,
    "gn:timezone":"Asia/Shanghai",
    "iso:country":"CN",
    "name:deu_x_preferred":[
        "Weizhou"
    ],
    "name:zho_x_preferred":[
        "\u536b\u6d32"
    ],
    "wof:name":"Weizhou",
    "wof:placetype":"locality"
},
  "geometry": {"coordinates":[113.34506,30.18873],"type":"Point"}
}