{
  "type": "Feature",
  "properties": {
    "gn:admin1_code":"30.0",
    "gn:asciiname":"Da'ao",
    "gn:country_code":"CN",
    "gn:dem":197,
    "gn:feature_class":"P",
    "gn:feature_code":"PPL",
    "gn:name":"Da\u2019ao",
    "gn:population":0,
    "gn:timezone":"Asia/Shanghai",
    "iso:country":"CN",
    "name:zho_x_preferred":[
        "\u5927\u5773"
    ],
    "name:zho_x_variant":[
        "Da\u2019ao"
    ],
    "wof:name":"Da'ao",
    "wof:placetype":"locality"
},
  "geometry": {"coordinates":[111.97469,22.99613],"type":"Point"}
}