{
  "type": "Feature",
  "properties": {
    "gn:admin1_code":"30",
    "gn:asciiname":"Guotian Nongchang",
    "gn:country_code":"CN",
    "gn:dem":385,
    "gn:feature_class":"P",
    "gn:feature_code":"PPLF",
    "gn:name":"Guotian Nongchang",
    "gn:population":0,
    "gn:timezone":"Asia/Shanghai",
    "iso:country":"CN",
    "wof:name":"Guotian Nongchang",
    "wof:placetype":"locality"
},
  "geometry": {"coordinates":[115.92989,23.81126],"type":"Point"}
}