{
  "type": "Feature",
  "properties": {
    "gn:admin1_code":"24",
    "gn:asciiname":"Zhongwadi",
    "gn:country_code":"CN",
    "gn:dem":683,
    "gn:feature_class":"P",
    "gn:feature_code":"PPLA4",
    "gn:name":"Zhongwadi",
    "gn:population":0,
    "gn:timezone":"Asia/Shanghai",
    "iso:country":"CN",
    "name:und_x_variant":[
        "Hsi-wa-ti",
        "Tung-yen-ts\u2019un",
        "Chung-wa-ti",
        "Wa-ti",
        "Tung-wa-ti",
        "Wadi Zhen",
        "Zhongwadi",
        "\u4e2d\u7556\u5e95",
        "\u7556\u5e95\u9547"
    ],
    "wof:name":"Zhongwadi",
    "wof:placetype":"locality"
},
  "geometry": {"coordinates":[111.15222,35.44333],"type":"Point"}
}