{
  "type": "Feature",
  "properties": {
    "gn:admin1_code":"3.0",
    "gn:asciiname":"Lijiashan",
    "gn:country_code":"CN",
    "gn:dem":162,
    "gn:feature_class":"P",
    "gn:feature_code":"PPL",
    "gn:name":"Lijiashan",
    "gn:population":0,
    "gn:timezone":"Asia/Shanghai",
    "iso:country":"CN",
    "name:und_x_variant":[
        "\u91cc\u5bb6\u5c71"
    ],
    "wof:name":"Lijiashan",
    "wof:placetype":"locality"
},
  "geometry": {"coordinates":[114.09032999999999,28.0949],"type":"Point"}
}