{
  "type": "Feature",
  "properties": {
    "iso:country":"CN",
    "name:eng_x_preferred":[
        "Xiaducun"
    ],
    "qs:gn_adm0_cc":"CN",
    "qs:gn_local":1809858,
    "qs:gn_nam_loc":"\u5e7f\u5dde\u5e02, \u5e7f\u5dde\u5e02, \u5e7f\u5dde, \u5e7f\u4e1c\u7701, CN",
    "qs:gn_namadm1":"30",
    "qs:local_max":9142,
    "qs:local_sum":30614,
    "qs:localhoods":22,
    "qs:name":"Xiaducun",
    "qs:name_adm0":"\u4e2d\u570b",
    "qs:name_adm1":"\u5e7f\u4e1c\u7701",
    "qs:name_adm2":"\u5e7f\u5dde\u5e02",
    "qs:name_lau":"\u5e7f\u5dde\u5e02",
    "qs:name_local":"\u5e7f\u5dde",
    "qs:photo_max":74,
    "qs:photo_sum":493,
    "qs:placetype":"Suburb",
    "qs:quad_count":35,
    "qs:woe_adm0":23424781,
    "qs:woe_adm1":12578019,
    "qs:woe_adm2":26198245,
    "qs:woe_lau":12687611,
    "qs:woe_local":2161838,
    "qs:woe_ver":"7.10.0",
    "wof:lang":[
        "eng"
    ],
    "wof:name":"Xiaducun",
    "wof:placetype":"neighbourhood"
},
  "geometry": {"coordinates":[113.297625,23.099499],"type":"Point"}
}