{
  "type": "Feature",
  "properties": {
    "gn:admin1_code":"14.0",
    "gn:asciiname":"Chama",
    "gn:country_code":"CN",
    "gn:dem":4265,
    "gn:feature_class":"P",
    "gn:feature_code":"PPL",
    "gn:name":"Chama",
    "gn:population":0,
    "gn:timezone":"Asia/Urumqi",
    "iso:country":"CN",
    "name:ceb_x_preferred":[
        "Chama"
    ],
    "name:deu_x_preferred":[
        "Chama"
    ],
    "name:ita_x_preferred":[
        "Chama"
    ],
    "name:nld_x_preferred":[
        "Chama"
    ],
    "name:pol_x_preferred":[
        "Chama"
    ],
    "name:por_x_preferred":[
        "Chama"
    ],
    "name:spa_x_preferred":[
        "Chama"
    ],
    "name:swa_x_preferred":[
        "Chama"
    ],
    "name:swe_x_preferred":[
        "Chama"
    ],
    "name:vol_x_preferred":[
        "Chama"
    ],
    "name:zho_x_preferred":[
        "\u67e5\u9a6c"
    ],
    "wof:name":"Chama",
    "wof:placetype":"locality"
},
  "geometry": {"coordinates":[87.9807,28.9191],"type":"Point"}
}