{
  "type": "Feature",
  "properties": {
    "gn:admin1_code":"18",
    "gn:asciiname":"Guniangzhuang",
    "gn:country_code":"CN",
    "gn:dem":1072,
    "gn:feature_class":"P",
    "gn:feature_code":"PPL",
    "gn:name":"Guniangzhuang",
    "gn:population":0,
    "gn:timezone":"Asia/Shanghai",
    "iso:country":"CN",
    "name:zho_x_preferred":[
        "\u6545\u5a18\u5e84"
    ],
    "wof:name":"Guniangzhuang",
    "wof:placetype":"locality"
},
  "geometry": {"coordinates":[105.755,25.9242],"type":"Point"}
}