{
  "type": "Feature",
  "properties": {
    "gn:admin1_code":"15.0",
    "gn:asciiname":"Hongyawa",
    "gn:country_code":"CN",
    "gn:dem":1323,
    "gn:feature_class":"P",
    "gn:feature_code":"PPL",
    "gn:name":"Hongyawa",
    "gn:population":0,
    "gn:timezone":"Asia/Shanghai",
    "iso:country":"CN",
    "name:und_x_variant":[
        "\u7ea2\u5d16\u6d3c"
    ],
    "wof:name":"Hongyawa",
    "wof:placetype":"locality"
},
  "geometry": {"coordinates":[107.19804000000001,36.29668],"type":"Point"}
}