{
  "type": "Feature",
  "properties": {
    "gn:admin1_code":"18.0",
    "gn:asciiname":"Huanglang",
    "gn:country_code":"CN",
    "gn:dem":801,
    "gn:feature_class":"P",
    "gn:feature_code":"PPL",
    "gn:name":"Huanglang",
    "gn:population":0,
    "gn:timezone":"Asia/Shanghai",
    "iso:country":"CN",
    "name:zho_x_preferred":[
        "\u9ec4\u90ce"
    ],
    "wof:name":"Huanglang",
    "wof:placetype":"locality"
},
  "geometry": {"coordinates":[108.627,25.6888],"type":"Point"}
}