{
  "type": "Feature",
  "properties": {
    "gn:admin1_code":"11.0",
    "gn:asciiname":"Zhongqiaogang",
    "gn:country_code":"CN",
    "gn:dem":311,
    "gn:feature_class":"P",
    "gn:feature_code":"PPL",
    "gn:name":"Zhongqiaogang",
    "gn:population":0,
    "gn:timezone":"Asia/Shanghai",
    "iso:country":"CN",
    "name:zho_x_preferred":[
        "\u4e2d\u6865\u5c97"
    ],
    "wof:name":"Zhongqiaogang",
    "wof:placetype":"locality"
},
  "geometry": {"coordinates":[110.71284,29.16424],"type":"Point"}
}