{
  "type": "Feature",
  "properties": {
    "gn:admin1_code":"11",
    "gn:asciiname":"Lianhetang",
    "gn:country_code":"CN",
    "gn:dem":258,
    "gn:feature_class":"P",
    "gn:feature_code":"PPL",
    "gn:name":"Lianhetang",
    "gn:population":0,
    "gn:timezone":"Asia/Shanghai",
    "iso:country":"CN",
    "name:zho_x_preferred":[
        "\u83b2\u8377\u5858"
    ],
    "wof:name":"Lianhetang",
    "wof:placetype":"locality"
},
  "geometry": {"coordinates":[111.09639,27.04139],"type":"Point"}
}