{
  "type": "Feature",
  "properties": {
    "gn:admin1_code":"19.0",
    "gn:asciiname":"Daweituncun",
    "gn:country_code":"CN",
    "gn:dem":231,
    "gn:feature_class":"P",
    "gn:feature_code":"PPL",
    "gn:name":"Daweituncun",
    "gn:population":0,
    "gn:timezone":"Asia/Shanghai",
    "iso:country":"CN",
    "name:zho_x_preferred":[
        "\u5927\u9b4f\u5c6f\u6751"
    ],
    "wof:name":"Daweituncun",
    "wof:placetype":"locality"
},
  "geometry": {"coordinates":[123.07223999999999,40.42689],"type":"Point"}
}