{
  "type": "Feature",
  "properties": {
    "gn:country":"CN",
    "gn:fcode":"PPL",
    "gn:population":2254,
    "iso:country":"CN",
    "qs:name":"Datianzhuang",
    "qs:photos_9r":0,
    "qs:photos_sr":0,
    "qs:pop_sr":"4",
    "wof:name":"Datianzhuang",
    "wof:placetype":"locality",
    "wof:population":2254
},
  "geometry": {"coordinates":[117.75360999999999,39.2725],"type":"Point"}
}