{
  "type": "Feature",
  "properties": {
    "gn:admin1_code":"7.0",
    "gn:asciiname":"Xihu",
    "gn:country_code":"CN",
    "gn:dem":659,
    "gn:feature_class":"P",
    "gn:feature_code":"PPL",
    "gn:name":"Xihu",
    "gn:population":0,
    "gn:timezone":"Asia/Shanghai",
    "iso:country":"CN",
    "name:ceb_x_preferred":[
        "Xihu"
    ],
    "name:dan_x_preferred":[
        "Xihu"
    ],
    "name:deu_x_preferred":[
        "Xihu"
    ],
    "name:eus_x_preferred":[
        "Xihu"
    ],
    "name:fra_x_preferred":[
        "Xihu"
    ],
    "name:jpn_x_preferred":[
        "\u897f\u6e56\u533a"
    ],
    "name:kor_x_preferred":[
        "\uc2dc\ud6c4\uad6c"
    ],
    "name:nor_x_preferred":[
        "Xihu"
    ],
    "name:pol_x_preferred":[
        "Xihu"
    ],
    "name:spa_x_preferred":[
        "Xihu"
    ],
    "name:zho_x_preferred":[
        "\u897f\u6e56"
    ],
    "name:zho_x_variant":[
        "\u897f\u6e56\u533a"
    ],
    "wof:name":"Xihu",
    "wof:placetype":"locality"
},
  "geometry": {"coordinates":[117.35326999999999,26.53744],"type":"Point"}
}