{
  "type": "Feature",
  "properties": {
    "gn:admin1_code":"31.0",
    "gn:asciiname":"Liuhegou",
    "gn:country_code":"CN",
    "gn:dem":40,
    "gn:feature_class":"P",
    "gn:feature_code":"PPL",
    "gn:name":"Liuhegou",
    "gn:population":0,
    "gn:timezone":"Asia/Shanghai",
    "iso:country":"CN",
    "name:zho_x_preferred":[
        "\u516d\u5408\u6c9f"
    ],
    "wof:name":"Liuhegou",
    "wof:placetype":"locality"
},
  "geometry": {"coordinates":[110.22929000000001,19.11875],"type":"Point"}
}