{
  "type": "Feature",
  "properties": {
    "gn:admin1_code":"4.0",
    "gn:asciiname":"Jinjizxu",
    "gn:country_code":"CN",
    "gn:dem":5,
    "gn:feature_class":"P",
    "gn:feature_code":"PPL",
    "gn:name":"Jinjizxu",
    "gn:population":0,
    "gn:timezone":"Asia/Shanghai",
    "iso:country":"CN",
    "name:zho_x_preferred":[
        "\u91d1\u5bb6\u5729"
    ],
    "wof:name":"Jinjizxu",
    "wof:placetype":"locality"
},
  "geometry": {"coordinates":[119.52431,32.80443],"type":"Point"}
}