{
  "type": "Feature",
  "properties": {
    "gn:admin1_code":"23.0",
    "gn:asciiname":"Ximen",
    "gn:country_code":"CN",
    "gn:dem":8,
    "gn:feature_class":"P",
    "gn:feature_code":"PPL",
    "gn:name":"Ximen",
    "gn:population":0,
    "gn:timezone":"Asia/Shanghai",
    "iso:country":"CN",
    "name:und_x_variant":[
        "\u897f\u95e8"
    ],
    "wof:name":"Ximen",
    "wof:placetype":"locality"
},
  "geometry": {"coordinates":[121.30589999999999,30.72651],"type":"Point"}
}