{
  "type": "Feature",
  "properties": {
    "gn:admin1_code":"29.0",
    "gn:asciiname":"Xianguang",
    "gn:country_code":"CN",
    "gn:dem":1321,
    "gn:feature_class":"P",
    "gn:feature_code":"PPL",
    "gn:name":"Xianguang",
    "gn:population":0,
    "gn:timezone":"Asia/Shanghai",
    "iso:country":"CN",
    "name:zho_x_preferred":[
        "\u8d24\u5149"
    ],
    "wof:name":"Xianguang",
    "wof:placetype":"locality"
},
  "geometry": {"coordinates":[100.13,23.0146],"type":"Point"}
}