{
  "type": "Feature",
  "properties": {
    "gn:admin1_code":"26.0",
    "gn:asciiname":"Hongliuqu",
    "gn:country_code":"CN",
    "gn:dem":1325,
    "gn:feature_class":"P",
    "gn:feature_code":"PPL",
    "gn:name":"Hongliuqu",
    "gn:population":0,
    "gn:timezone":"Asia/Shanghai",
    "iso:country":"CN",
    "name:zho_x_preferred":[
        "\u7ea2\u67f3\u6e20"
    ],
    "wof:name":"Hongliuqu",
    "wof:placetype":"locality"
},
  "geometry": {"coordinates":[109.21343,36.91098],"type":"Point"}
}