{
  "type": "Feature",
  "properties": {
    "gn:admin1_code":"18",
    "gn:asciiname":"Hongbanqiao",
    "gn:country_code":"CN",
    "gn:dem":1364,
    "gn:feature_class":"P",
    "gn:feature_code":"PPL",
    "gn:name":"Hongbanqiao",
    "gn:population":0,
    "gn:timezone":"Asia/Shanghai",
    "iso:country":"CN",
    "name:zho_x_preferred":[
        "\u7ea2\u677f\u6865"
    ],
    "wof:name":"Hongbanqiao",
    "wof:placetype":"locality"
},
  "geometry": {"coordinates":[104.81399999999999,25.2239],"type":"Point"}
}