{
  "type": "Feature",
  "properties": {
    "gn:admin1_code":"7.0",
    "gn:asciiname":"Dongjiao",
    "gn:country_code":"CN",
    "gn:dem":6,
    "gn:feature_class":"P",
    "gn:feature_code":"PPL",
    "gn:name":"Dongjiao",
    "gn:population":0,
    "gn:timezone":"Asia/Shanghai",
    "iso:country":"CN",
    "name:ceb_x_preferred":[
        "Dongjiao"
    ],
    "name:swe_x_preferred":[
        "Dongjiao"
    ],
    "name:zho_x_preferred":[
        "\u4e1c\u90ca"
    ],
    "wof:name":"Dongjiao",
    "wof:placetype":"locality"
},
  "geometry": {"coordinates":[119.04125999999999,25.37448],"type":"Point"}
}