{
  "type": "Feature",
  "properties": {
    "gn:admin1_code":"16.0",
    "gn:asciiname":"Zhelongtun",
    "gn:country_code":"CN",
    "gn:dem":510,
    "gn:feature_class":"P",
    "gn:feature_code":"PPL",
    "gn:name":"Zhelongtun",
    "gn:population":0,
    "gn:timezone":"Asia/Shanghai",
    "iso:country":"CN",
    "name:zho_x_preferred":[
        "\u8005\u9f99\u5c6f"
    ],
    "wof:name":"Zhelongtun",
    "wof:placetype":"locality"
},
  "geometry": {"coordinates":[107.285,25.0124],"type":"Point"}
}