{
  "type": "Feature",
  "properties": {
    "gn:admin1_code":"12.0",
    "gn:asciiname":"Louziwan",
    "gn:country_code":"CN",
    "gn:dem":59,
    "gn:feature_class":"P",
    "gn:feature_code":"PPL",
    "gn:name":"Louziwan",
    "gn:population":0,
    "gn:timezone":"Asia/Shanghai",
    "iso:country":"CN",
    "name:zho_x_preferred":[
        "\u697c\u5b50\u6e7e"
    ],
    "wof:name":"Louziwan",
    "wof:placetype":"locality"
},
  "geometry": {"coordinates":[112.11436999999999,30.70098],"type":"Point"}
}