{
  "type": "Feature",
  "properties": {
    "gn:admin1_code":"5.0",
    "gn:asciiname":"Xinfutun",
    "gn:country_code":"CN",
    "gn:dem":151,
    "gn:feature_class":"P",
    "gn:feature_code":"PPL",
    "gn:name":"Xinfutun",
    "gn:population":0,
    "gn:timezone":"Asia/Shanghai",
    "iso:country":"CN",
    "name:zho_x_preferred":[
        "\u65b0\u5bcc\u5c6f"
    ],
    "wof:name":"Xinfutun",
    "wof:placetype":"locality"
},
  "geometry": {"coordinates":[123.0517,44.78911],"type":"Point"}
}