{
  "type": "Feature",
  "properties": {
    "gn:admin1_code":"11.0",
    "gn:asciiname":"Changjiayu",
    "gn:country_code":"CN",
    "gn:dem":278,
    "gn:feature_class":"P",
    "gn:feature_code":"PPL",
    "gn:name":"Changjiayu",
    "gn:population":0,
    "gn:timezone":"Asia/Shanghai",
    "iso:country":"CN",
    "name:zho_x_preferred":[
        "Changjiayu"
    ],
    "name:zho_x_variant":[
        "\u957f\u5bb6\u5cea"
    ],
    "wof:name":"Changjiayu",
    "wof:placetype":"locality"
},
  "geometry": {"coordinates":[111.23644,29.88965],"type":"Point"}
}