{
  "type": "Feature",
  "properties": {
    "gn:admin1_code":"18",
    "gn:asciiname":"Wulukai",
    "gn:country_code":"CN",
    "gn:dem":1634,
    "gn:feature_class":"P",
    "gn:feature_code":"PPL",
    "gn:name":"Wulukai",
    "gn:population":0,
    "gn:timezone":"Asia/Shanghai",
    "iso:country":"CN",
    "name:zho_x_preferred":[
        "\u4e4c\u8def\u5f00"
    ],
    "wof:name":"Wulukai",
    "wof:placetype":"locality"
},
  "geometry": {"coordinates":[105.20699999999999,26.9928],"type":"Point"}
}