{
  "type": "Feature",
  "properties": {
    "gn:admin1_code":"10",
    "gn:asciiname":"Miaonangou",
    "gn:country_code":"CN",
    "gn:dem":1106,
    "gn:feature_class":"P",
    "gn:feature_code":"PPL",
    "gn:name":"Miaonangou",
    "gn:population":0,
    "gn:timezone":"Asia/Shanghai",
    "iso:country":"CN",
    "name:zho_x_preferred":[
        "\u5e99\u5357\u6c9f"
    ],
    "wof:name":"Miaonangou",
    "wof:placetype":"locality"
},
  "geometry": {"coordinates":[114.20701,40.86369000000001],"type":"Point"}
}