{
  "type": "Feature",
  "properties": {
    "gn:admin1_code":"19.0",
    "gn:asciiname":"Fengjiatuncun",
    "gn:country_code":"CN",
    "gn:dem":112,
    "gn:feature_class":"P",
    "gn:feature_code":"PPL",
    "gn:name":"Fengjiatuncun",
    "gn:population":0,
    "gn:timezone":"Asia/Shanghai",
    "iso:country":"CN",
    "name:zho_x_preferred":[
        "\u51af\u5bb6\u5c6f\u6751"
    ],
    "wof:name":"Fengjiatuncun",
    "wof:placetype":"locality"
},
  "geometry": {"coordinates":[120.90625,41.32209],"type":"Point"}
}