{
  "type": "Feature",
  "properties": {
    "gn:admin1_code":"16.0",
    "gn:asciiname":"Youtian",
    "gn:country_code":"CN",
    "gn:dem":159,
    "gn:feature_class":"P",
    "gn:feature_code":"PPL",
    "gn:name":"Youtian",
    "gn:population":0,
    "gn:timezone":"Asia/Shanghai",
    "iso:country":"CN",
    "name:zho_x_preferred":[
        "\u6709\u7530"
    ],
    "wof:name":"Youtian",
    "wof:placetype":"locality"
},
  "geometry": {"coordinates":[111.369,23.9849],"type":"Point"}
}