{
  "type": "Feature",
  "properties": {
    "gn:admin1_code":"15.0",
    "gn:asciiname":"Yin'aoxia",
    "gn:country_code":"CN",
    "gn:dem":1954,
    "gn:feature_class":"P",
    "gn:feature_code":"PPL",
    "gn:name":"Yin\u2019aoxia",
    "gn:population":0,
    "gn:timezone":"Asia/Urumqi",
    "iso:country":"CN",
    "name:und_x_variant":[
        "Yin\u2019aoxia"
    ],
    "name:zho_x_preferred":[
        "\u97f3\u51f9\u5ce1"
    ],
    "wof:name":"Yin'aoxia",
    "wof:placetype":"locality"
},
  "geometry": {"coordinates":[96.8832,41.1297],"type":"Point"}
}