{
  "type": "Feature",
  "properties": {
    "gn:admin1_code":"18.0",
    "gn:asciiname":"Xiangjiawan",
    "gn:country_code":"CN",
    "gn:dem":781,
    "gn:feature_class":"P",
    "gn:feature_code":"PPL",
    "gn:name":"Xiangjiawan",
    "gn:population":0,
    "gn:timezone":"Asia/Shanghai",
    "iso:country":"CN",
    "name:zho_x_preferred":[
        "\u9999\u5bb6\u6e7e"
    ],
    "wof:name":"Xiangjiawan",
    "wof:placetype":"locality"
},
  "geometry": {"coordinates":[108.06100000000001,28.0411],"type":"Point"}
}