{
  "type": "Feature",
  "properties": {
    "gn:admin1_code":"15.0",
    "gn:asciiname":"Xing'erzhang",
    "gn:country_code":"CN",
    "gn:dem":1638,
    "gn:feature_class":"P",
    "gn:feature_code":"PPL",
    "gn:name":"Xing\u2019erzhang",
    "gn:population":0,
    "gn:timezone":"Asia/Shanghai",
    "iso:country":"CN",
    "name:und_x_variant":[
        "Xing\u2019erzhang"
    ],
    "name:zho_x_preferred":[
        "\u674f\u513f\u638c"
    ],
    "wof:name":"Xing'erzhang",
    "wof:placetype":"locality"
},
  "geometry": {"coordinates":[107.083,37.0324],"type":"Point"}
}