{
  "type": "Feature",
  "properties": {
    "gn:admin1_code":"21.0",
    "gn:asciiname":"Yuejin Erdui",
    "gn:country_code":"CN",
    "gn:dem":1177,
    "gn:feature_class":"P",
    "gn:feature_code":"PPLF",
    "gn:name":"Yuejin Erdui",
    "gn:population":0,
    "gn:timezone":"Asia/Shanghai",
    "iso:country":"CN",
    "name:zho_x_preferred":[
        "\u8dc3\u8fdb\u4e8c\u961f"
    ],
    "wof:name":"Yuejin Erdui",
    "wof:placetype":"locality"
},
  "geometry": {"coordinates":[105.94799999999999,37.6631],"type":"Point"}
}