{
  "type": "Feature",
  "properties": {
    "gn:admin1_code":"4.0",
    "gn:asciiname":"Jinghan",
    "gn:country_code":"CN",
    "gn:dem":3,
    "gn:feature_class":"P",
    "gn:feature_code":"PPL",
    "gn:name":"Jinghan",
    "gn:population":0,
    "gn:timezone":"Asia/Shanghai",
    "iso:country":"CN",
    "name:zho_x_preferred":[
        "\u4eac\u6c49"
    ],
    "wof:name":"Jinghan",
    "wof:placetype":"locality"
},
  "geometry": {"coordinates":[119.63618999999998,32.72476],"type":"Point"}
}