{
  "type": "Feature",
  "properties": {
    "gn:admin1_code":"24.0",
    "gn:asciiname":"Xiayu",
    "gn:country_code":"CN",
    "gn:dem":1178,
    "gn:feature_class":"P",
    "gn:feature_code":"PPL",
    "gn:name":"Xiayu",
    "gn:population":0,
    "gn:timezone":"Asia/Shanghai",
    "iso:country":"CN",
    "name:zho_x_preferred":[
        "\u4e0b\u5cea"
    ],
    "wof:name":"Xiayu",
    "wof:placetype":"locality"
},
  "geometry": {"coordinates":[111.96669,35.55383],"type":"Point"}
}