{
  "type": "Feature",
  "properties": {
    "gn:admin1_code":"1.0",
    "gn:asciiname":"Liudadui Erdian",
    "gn:country_code":"CN",
    "gn:dem":7,
    "gn:feature_class":"P",
    "gn:feature_code":"PPLF",
    "gn:name":"Liudadui Erdian",
    "gn:population":0,
    "gn:timezone":"Asia/Shanghai",
    "iso:country":"CN",
    "name:zho_x_preferred":[
        "\u516d\u5927\u961f\u4e8c\u70b9"
    ],
    "wof:name":"Liudadui Erdian",
    "wof:placetype":"locality"
},
  "geometry": {"coordinates":[117.45824,31.30429],"type":"Point"}
}