{
  "type": "Feature",
  "properties": {
    "gn:admin1_code":"7.0",
    "gn:asciiname":"Sanhu Kengxia",
    "gn:country_code":"CN",
    "gn:dem":418,
    "gn:feature_class":"P",
    "gn:feature_code":"PPL",
    "gn:name":"Sanhu Kengxia",
    "gn:population":0,
    "gn:timezone":"Asia/Shanghai",
    "iso:country":"CN",
    "name:und_x_variant":[
        "\u4e09\u80e1\u5751\u4e0b"
    ],
    "name:zho_x_preferred":[
        "\u4e09\u80e1\u5751\u4e0b"
    ],
    "wof:name":"Sanhu Kengxia",
    "wof:placetype":"locality"
},
  "geometry": {"coordinates":[117.30208,26.24183],"type":"Point"}
}