{
  "type": "Feature",
  "properties": {
    "gn:admin1_code":"30.0",
    "gn:asciiname":"Shanglidong",
    "gn:country_code":"CN",
    "gn:dem":594,
    "gn:feature_class":"P",
    "gn:feature_code":"PPL",
    "gn:name":"Shanglidong",
    "gn:population":0,
    "gn:timezone":"Asia/Shanghai",
    "iso:country":"CN",
    "name:zho_x_preferred":[
        "\u4e0a\u91cc\u6d1e"
    ],
    "wof:name":"Shanglidong",
    "wof:placetype":"locality"
},
  "geometry": {"coordinates":[114.12526,25.30994],"type":"Point"}
}