{
  "type": "Feature",
  "properties": {
    "gn:admin1_code":"10.0",
    "gn:asciiname":"Fengzhuangzi",
    "gn:country_code":"CN",
    "gn:dem":2,
    "gn:feature_class":"P",
    "gn:feature_code":"PPL",
    "gn:name":"Fengzhuangzi",
    "gn:population":0,
    "gn:timezone":"Asia/Shanghai",
    "iso:country":"CN",
    "name:zho_x_preferred":[
        "\u51af\u5e84\u5b50"
    ],
    "wof:name":"Fengzhuangzi",
    "wof:placetype":"locality"
},
  "geometry": {"coordinates":[118.64373999999999,39.25132],"type":"Point"}
}