{
  "type": "Feature",
  "properties": {
    "gn:admin1_code":"14.0",
    "gn:asciiname":"Zoicun",
    "gn:country_code":"CN",
    "gn:dem":3791,
    "gn:feature_class":"P",
    "gn:feature_code":"PPL",
    "gn:name":"Zoicun",
    "gn:population":0,
    "gn:timezone":"Asia/Urumqi",
    "iso:country":"CN",
    "name:bod_x_preferred":[
        "Zoicun"
    ],
    "name:und_x_variant":[
        "Zuocun"
    ],
    "name:zho_x_preferred":[
        "\u4f50\u6751"
    ],
    "wof:name":"Zoicun",
    "wof:placetype":"locality"
},
  "geometry": {"coordinates":[97.203,31.003],"type":"Point"}
}