{
  "type": "Feature",
  "properties": {
    "gn:admin1_code":"30",
    "gn:asciiname":"Encun",
    "gn:country_code":"CN",
    "gn:dem":142,
    "gn:feature_class":"P",
    "gn:feature_code":"PPL",
    "gn:name":"Encun",
    "gn:population":0,
    "gn:timezone":"Asia/Shanghai",
    "iso:country":"CN",
    "name:und_x_variant":[
        "\u6069\u6751"
    ],
    "wof:name":"Encun",
    "wof:placetype":"locality"
},
  "geometry": {"coordinates":[113.73072000000001,25.26159],"type":"Point"}
}