{
  "type": "Feature",
  "properties": {
    "gn:admin1_code":"1.0",
    "gn:asciiname":"Daguyuncun",
    "gn:country_code":"CN",
    "gn:dem":347,
    "gn:feature_class":"P",
    "gn:feature_code":"PPL",
    "gn:name":"Daguyuncun",
    "gn:population":0,
    "gn:timezone":"Asia/Shanghai",
    "iso:country":"CN",
    "name:zho_x_preferred":[
        "\u5927\u8c37\u8fd0\u6751"
    ],
    "wof:name":"Daguyuncun",
    "wof:placetype":"locality"
},
  "geometry": {"coordinates":[118.42168999999998,30.05829],"type":"Point"}
}