{
  "type": "Feature",
  "properties": {
    "gn:admin1_code":"32.0",
    "gn:asciiname":"Dazhaizi",
    "gn:country_code":"CN",
    "gn:dem":3547,
    "gn:feature_class":"P",
    "gn:feature_code":"PPL",
    "gn:name":"Dazhaizi",
    "gn:population":0,
    "gn:timezone":"Asia/Shanghai",
    "iso:country":"CN",
    "name:zho_x_preferred":[
        "\u5927\u5be8\u5b50"
    ],
    "wof:name":"Dazhaizi",
    "wof:placetype":"locality"
},
  "geometry": {"coordinates":[103.77800000000001,32.2988],"type":"Point"}
}