{
  "type": "Feature",
  "properties": {
    "gn:admin1_code":"9.0",
    "gn:asciiname":"Duanzhai",
    "gn:country_code":"CN",
    "gn:dem":48,
    "gn:feature_class":"P",
    "gn:feature_code":"PPL",
    "gn:name":"Duanzhai",
    "gn:population":0,
    "gn:timezone":"Asia/Shanghai",
    "iso:country":"CN",
    "name:zho_x_preferred":[
        "\u6bb5\u5be8"
    ],
    "wof:name":"Duanzhai",
    "wof:placetype":"locality"
},
  "geometry": {"coordinates":[114.81323999999999,32.07602],"type":"Point"}
}