{
  "type": "Feature",
  "properties": {
    "gn:admin1_code":"26.0",
    "gn:asciiname":"Xinpuzi",
    "gn:country_code":"CN",
    "gn:dem":1122,
    "gn:feature_class":"P",
    "gn:feature_code":"PPL",
    "gn:name":"Xinpuzi",
    "gn:population":0,
    "gn:timezone":"Asia/Shanghai",
    "iso:country":"CN",
    "name:zho_x_preferred":[
        "\u65b0\u94fa\u5b50"
    ],
    "wof:name":"Xinpuzi",
    "wof:placetype":"locality"
},
  "geometry": {"coordinates":[108.72147,33.64635],"type":"Point"}
}