{
  "type": "Feature",
  "properties": {
    "gn:admin1_code":"15.0",
    "gn:asciiname":"Miaojiayuan",
    "gn:country_code":"CN",
    "gn:dem":1589,
    "gn:feature_class":"P",
    "gn:feature_code":"PPL",
    "gn:name":"Miaojiayuan",
    "gn:population":0,
    "gn:timezone":"Asia/Shanghai",
    "iso:country":"CN",
    "name:und_x_variant":[
        "\u7f2a\u5bb6\u586c"
    ],
    "wof:name":"Miaojiayuan",
    "wof:placetype":"locality"
},
  "geometry": {"coordinates":[107.08981,36.68454000000001],"type":"Point"}
}