{
  "type": "Feature",
  "properties": {
    "gn:admin1_code":"3.0",
    "gn:asciiname":"Xiajietou",
    "gn:country_code":"CN",
    "gn:dem":132,
    "gn:feature_class":"P",
    "gn:feature_code":"PPL",
    "gn:name":"Xiajietou",
    "gn:population":0,
    "gn:timezone":"Asia/Shanghai",
    "iso:country":"CN",
    "name:und_x_variant":[
        "\u4e0b\u754c\u5934"
    ],
    "wof:name":"Xiajietou",
    "wof:placetype":"locality"
},
  "geometry": {"coordinates":[114.95690999999999,27.65379],"type":"Point"}
}