{
  "type": "Feature",
  "properties": {
    "gn:admin1_code":"9.0",
    "gn:asciiname":"Erhaoqiao",
    "gn:country_code":"CN",
    "gn:dem":94,
    "gn:feature_class":"P",
    "gn:feature_code":"PPL",
    "gn:name":"Erhaoqiao",
    "gn:population":0,
    "gn:timezone":"Asia/Shanghai",
    "iso:country":"CN",
    "name:zho_x_preferred":[
        "\u4e8c\u53f7\u6865"
    ],
    "wof:name":"Erhaoqiao",
    "wof:placetype":"locality"
},
  "geometry": {"coordinates":[114.01560000000001,32.14353],"type":"Point"}
}