{
  "type": "Feature",
  "properties": {
    "gn:admin1_code":"16",
    "gn:asciiname":"Jiaolinjiang",
    "gn:country_code":"CN",
    "gn:dem":925,
    "gn:feature_class":"P",
    "gn:feature_code":"PPL",
    "gn:name":"Jiaolinjiang",
    "gn:population":0,
    "gn:timezone":"Asia/Shanghai",
    "iso:country":"CN",
    "name:zho_x_preferred":[
        "\u8549\u6797\u6c5f"
    ],
    "wof:name":"Jiaolinjiang",
    "wof:placetype":"locality"
},
  "geometry": {"coordinates":[110.279,25.7119],"type":"Point"}
}