{
  "type": "Feature",
  "properties": {
    "gn:admin1_code":"9.0",
    "gn:asciiname":"Guihe",
    "gn:country_code":"CN",
    "gn:dem":138,
    "gn:feature_class":"P",
    "gn:feature_code":"PPL",
    "gn:name":"Guihe",
    "gn:population":0,
    "gn:timezone":"Asia/Shanghai",
    "iso:country":"CN",
    "name:und_x_variant":[
        "\u6842\u6cb3"
    ],
    "name:zho_x_preferred":[
        "\u6842\u6cb3"
    ],
    "wof:name":"Guihe",
    "wof:placetype":"locality"
},
  "geometry": {"coordinates":[113.29715,33.13882],"type":"Point"}
}