{
  "type": "Feature",
  "properties": {
    "gn:admin1_code":"5.0",
    "gn:asciiname":"Xujia Youfang",
    "gn:country_code":"CN",
    "gn:dem":185,
    "gn:feature_class":"P",
    "gn:feature_code":"PPL",
    "gn:name":"Xujia Youfang",
    "gn:population":0,
    "gn:timezone":"Asia/Shanghai",
    "iso:country":"CN",
    "name:zho_x_preferred":[
        "\u5f90\u5bb6\u6cb9\u574a"
    ],
    "wof:name":"Xujia Youfang",
    "wof:placetype":"locality"
},
  "geometry": {"coordinates":[125.13885999999999,44.40239],"type":"Point"}
}