{
  "type": "Feature",
  "properties": {
    "gn:admin1_code":"31.0",
    "gn:asciiname":"Qiantou",
    "gn:country_code":"CN",
    "gn:dem":64,
    "gn:feature_class":"P",
    "gn:feature_code":"PPL",
    "gn:name":"Qiantou",
    "gn:population":0,
    "gn:timezone":"Asia/Shanghai",
    "iso:country":"CN",
    "name:zho_x_preferred":[
        "\u4e7e\u5934"
    ],
    "wof:name":"Qiantou",
    "wof:placetype":"locality"
},
  "geometry": {"coordinates":[109.05986,19.56657],"type":"Point"}
}