{
  "type": "Feature",
  "properties": {
    "gn:admin1_code":"14.0",
    "gn:asciiname":"Yoiqag",
    "gn:country_code":"CN",
    "gn:dem":4576,
    "gn:feature_class":"P",
    "gn:feature_code":"PPLA4",
    "gn:name":"Yoiqag",
    "gn:population":0,
    "gn:timezone":"Asia/Urumqi",
    "iso:country":"CN",
    "name:bod_x_preferred":[
        "Yoiqag"
    ],
    "name:und_x_variant":[
        "Youqia Xiang"
    ],
    "name:zho_x_preferred":[
        "Youqia"
    ],
    "name:zho_x_variant":[
        "\u6cb9\u6070",
        "Gedeng\u2019ema",
        "\u683c\u767b\u4fc4\u9a6c",
        "\u6cb9\u6070\u4e61"
    ],
    "wof:name":"Yoiqag",
    "wof:placetype":"locality"
},
  "geometry": {"coordinates":[91.85939,30.61136],"type":"Point"}
}