{
  "type": "Feature",
  "properties": {
    "gn:admin1_code":"15.0",
    "gn:asciiname":"Malianshan",
    "gn:country_code":"CN",
    "gn:dem":1394,
    "gn:feature_class":"P",
    "gn:feature_code":"PPL",
    "gn:name":"Malianshan",
    "gn:population":0,
    "gn:timezone":"Asia/Shanghai",
    "iso:country":"CN",
    "name:und_x_variant":[
        "\u9a6c\u83b2\u5c71"
    ],
    "wof:name":"Malianshan",
    "wof:placetype":"locality"
},
  "geometry": {"coordinates":[107.63827999999999,36.56262],"type":"Point"}
}