{
  "type": "Feature",
  "properties": {
    "gn:admin1_code":"3.0",
    "gn:asciiname":"Tanjiangcun",
    "gn:country_code":"CN",
    "gn:dem":37,
    "gn:feature_class":"P",
    "gn:feature_code":"PPL",
    "gn:name":"Tanjiangcun",
    "gn:population":0,
    "gn:timezone":"Asia/Shanghai",
    "iso:country":"CN",
    "name:und_x_variant":[
        "\u6f6d\u6c5f\u6751"
    ],
    "wof:name":"Tanjiangcun",
    "wof:placetype":"locality"
},
  "geometry": {"coordinates":[115.56067,28.16439],"type":"Point"}
}