{
  "type": "Feature",
  "properties": {
    "gn:admin1_code":"32.0",
    "gn:asciiname":"Maluzhai",
    "gn:country_code":"CN",
    "gn:dem":2674,
    "gn:feature_class":"P",
    "gn:feature_code":"PPL",
    "gn:name":"Maluzhai",
    "gn:population":0,
    "gn:timezone":"Asia/Shanghai",
    "iso:country":"CN",
    "name:zho_x_preferred":[
        "\u9a6c\u9e7f\u5be8"
    ],
    "wof:name":"Maluzhai",
    "wof:placetype":"locality"
},
  "geometry": {"coordinates":[101.76000000000001,26.8987],"type":"Point"}
}