{
  "type": "Feature",
  "properties": {
    "gn:admin1_code":"29.0",
    "gn:asciiname":"Nianmila",
    "gn:country_code":"CN",
    "gn:dem":2251,
    "gn:feature_class":"P",
    "gn:feature_code":"PPL",
    "gn:name":"Nianmila",
    "gn:population":0,
    "gn:timezone":"Asia/Shanghai",
    "iso:country":"CN",
    "name:zho_x_preferred":[
        "\u5ff5\u7c73\u814a"
    ],
    "wof:name":"Nianmila",
    "wof:placetype":"locality"
},
  "geometry": {"coordinates":[99.0933,26.3671],"type":"Point"}
}