{
  "type": "Feature",
  "properties": {
    "gn:admin1_code":"32.0",
    "gn:asciiname":"Luotang",
    "gn:country_code":"CN",
    "gn:dem":1310,
    "gn:feature_class":"P",
    "gn:feature_code":"PPL",
    "gn:name":"Luotang",
    "gn:population":0,
    "gn:timezone":"Asia/Shanghai",
    "iso:country":"CN",
    "name:zho_x_preferred":[
        "\u9a86\u5802"
    ],
    "wof:name":"Luotang",
    "wof:placetype":"locality"
},
  "geometry": {"coordinates":[103.27198,29.41266],"type":"Point"}
}