{
  "type": "Feature",
  "properties": {
    "gn:admin1_code":"4.0",
    "gn:asciiname":"Xiaolizhuangcun",
    "gn:country_code":"CN",
    "gn:dem":38,
    "gn:feature_class":"P",
    "gn:feature_code":"PPL",
    "gn:name":"Xiaolizhuangcun",
    "gn:population":0,
    "gn:timezone":"Asia/Shanghai",
    "iso:country":"CN",
    "name:zho_x_preferred":[
        "\u5c0f\u674e\u5e84\u6751"
    ],
    "wof:name":"Xiaolizhuangcun",
    "wof:placetype":"locality"
},
  "geometry": {"coordinates":[116.66107,34.83832],"type":"Point"}
}