{
  "type": "Feature",
  "properties": {
    "gn:admin1_code":"16.0",
    "gn:asciiname":"Rongshan",
    "gn:country_code":"CN",
    "gn:dem":131,
    "gn:feature_class":"P",
    "gn:feature_code":"PPL",
    "gn:name":"Rongshan",
    "gn:population":0,
    "gn:timezone":"Asia/Shanghai",
    "iso:country":"CN",
    "name:zho_x_preferred":[
        "\u6995\u5c71"
    ],
    "wof:name":"Rongshan",
    "wof:placetype":"locality"
},
  "geometry": {"coordinates":[108.98699999999999,25.0167],"type":"Point"}
}