{
  "type": "Feature",
  "properties": {
    "gn:country":"CN",
    "gn:fcode":"PPL",
    "gn:pop":1470,
    "iso:country":"CN",
    "name:deu_x_preferred":[
        "Shoushan"
    ],
    "qs:name":"Shoushan",
    "qs:photos_9r":0,
    "qs:photos_sr":0,
    "qs:pop_sr":"3",
    "wd:wordcount":8,
    "wof:name":"Shoushan",
    "wof:placetype":"locality",
    "wof:population":1470
},
  "geometry": {"coordinates":[119.16167,26.96444],"type":"Point"}
}