{
  "type": "Feature",
  "properties": {
    "gn:admin1_code":"1.0",
    "gn:asciiname":"Xigengcun",
    "gn:country_code":"CN",
    "gn:dem":7,
    "gn:feature_class":"P",
    "gn:feature_code":"PPL",
    "gn:name":"Xigengcun",
    "gn:population":0,
    "gn:timezone":"Asia/Shanghai",
    "iso:country":"CN",
    "name:zho_x_preferred":[
        "\u897f\u57c2\u6751"
    ],
    "wof:name":"Xigengcun",
    "wof:placetype":"locality"
},
  "geometry": {"coordinates":[118.25668,31.36375],"type":"Point"}
}