{
  "type": "Feature",
  "properties": {
    "gn:admin1_code":"7.0",
    "gn:asciiname":"Dabeitou",
    "gn:country_code":"CN",
    "gn:dem":375,
    "gn:feature_class":"P",
    "gn:feature_code":"PPL",
    "gn:name":"Dabeitou",
    "gn:population":0,
    "gn:timezone":"Asia/Shanghai",
    "iso:country":"CN",
    "name:und_x_variant":[
        "\u5927\u9642\u5934"
    ],
    "name:zho_x_preferred":[
        "\u5927\u9642\u5934"
    ],
    "wof:name":"Dabeitou",
    "wof:placetype":"locality"
},
  "geometry": {"coordinates":[116.75708,25.50274],"type":"Point"}
}