{
  "type": "Feature",
  "properties": {
    "gn:admin1_code":"14.0",
    "gn:asciiname":"Macuo",
    "gn:country_code":"CN",
    "gn:dem":4259,
    "gn:feature_class":"P",
    "gn:feature_code":"PPL",
    "gn:name":"Macuo",
    "gn:population":0,
    "gn:timezone":"Asia/Urumqi",
    "iso:country":"CN",
    "name:zho_x_preferred":[
        "\u739b\u63aa"
    ],
    "wof:name":"Macuo",
    "wof:placetype":"locality"
},
  "geometry": {"coordinates":[87.13549999999999,29.1134],"type":"Point"}
}