{
  "type": "Feature",
  "properties": {
    "gn:admin1_code":"15.0",
    "gn:asciiname":"Siba Shiyidui",
    "gn:country_code":"CN",
    "gn:dem":1421,
    "gn:feature_class":"P",
    "gn:feature_code":"PPLF",
    "gn:name":"Siba Shiyidui",
    "gn:population":0,
    "gn:timezone":"Asia/Shanghai",
    "iso:country":"CN",
    "name:zho_x_preferred":[
        "\u56db\u575d\u5341\u4e00\u961f"
    ],
    "wof:name":"Siba Shiyidui",
    "wof:placetype":"locality"
},
  "geometry": {"coordinates":[98.6133,39.7282],"type":"Point"}
}