{
  "type": "Feature",
  "properties": {
    "gn:admin1_code":"14.0",
    "gn:asciiname":"Langpu",
    "gn:country_code":"CN",
    "gn:dem":4448,
    "gn:feature_class":"P",
    "gn:feature_code":"PPL",
    "gn:name":"Langpu",
    "gn:population":0,
    "gn:timezone":"Asia/Urumqi",
    "iso:country":"CN",
    "name:zho_x_preferred":[
        "\u90ce\u666e"
    ],
    "wof:name":"Langpu",
    "wof:placetype":"locality"
},
  "geometry": {"coordinates":[86.9453,29.4343],"type":"Point"}
}