{
  "type": "Feature",
  "properties": {
    "gn:admin1_code":"10",
    "gn:asciiname":"Liumacao",
    "gn:country_code":"CN",
    "gn:dem":18,
    "gn:feature_class":"P",
    "gn:feature_code":"PPL",
    "gn:name":"Liumacao",
    "gn:population":0,
    "gn:timezone":"Asia/Shanghai",
    "iso:country":"CN",
    "name:zho_x_preferred":[
        "\u67f3\u9a6c\u66f9"
    ],
    "wof:name":"Liumacao",
    "wof:placetype":"locality"
},
  "geometry": {"coordinates":[116.47044,37.93171],"type":"Point"}
}