{
  "type": "Feature",
  "properties": {
    "gn:admin1_code":"3.0",
    "gn:asciiname":"Chizhukeng",
    "gn:country_code":"CN",
    "gn:dem":276,
    "gn:feature_class":"P",
    "gn:feature_code":"PPL",
    "gn:name":"Chizhukeng",
    "gn:population":0,
    "gn:timezone":"Asia/Shanghai",
    "iso:country":"CN",
    "name:und_x_variant":[
        "\u8d64\u7af9\u5751"
    ],
    "wof:name":"Chizhukeng",
    "wof:placetype":"locality"
},
  "geometry": {"coordinates":[115.58304,26.27245],"type":"Point"}
}