{
  "type": "Feature",
  "properties": {
    "gn:admin1_code":"24",
    "gn:asciiname":"Gangou",
    "gn:country_code":"CN",
    "gn:dem":1645,
    "gn:feature_class":"P",
    "gn:feature_code":"PPL",
    "gn:name":"Gangou",
    "gn:population":0,
    "gn:timezone":"Asia/Shanghai",
    "iso:country":"CN",
    "wof:name":"Gangou",
    "wof:placetype":"locality"
},
  "geometry": {"coordinates":[113.74527999999999,39.85722],"type":"Point"}
}