{
  "type": "Feature",
  "properties": {
    "gn:admin1_code":"19.0",
    "gn:asciiname":"Xiaozilitun",
    "gn:country_code":"CN",
    "gn:dem":89,
    "gn:feature_class":"P",
    "gn:feature_code":"PPL",
    "gn:name":"Xiaozilitun",
    "gn:population":0,
    "gn:timezone":"Asia/Shanghai",
    "iso:country":"CN",
    "name:und_x_variant":[
        "\u5c0f\u7c7d\u7c92\u5c6f"
    ],
    "name:zho_x_preferred":[
        "\u5c0f\u7c7d\u7c92\u5c6f"
    ],
    "wof:name":"Xiaozilitun",
    "wof:placetype":"locality"
},
  "geometry": {"coordinates":[121.50196,41.53387],"type":"Point"}
}