{
  "type": "Feature",
  "properties": {
    "gn:admin1_code":"16.0",
    "gn:asciiname":"Xiawujiang",
    "gn:country_code":"CN",
    "gn:dem":246,
    "gn:feature_class":"P",
    "gn:feature_code":"PPL",
    "gn:name":"Xiawujiang",
    "gn:population":0,
    "gn:timezone":"Asia/Shanghai",
    "iso:country":"CN",
    "name:zho_x_preferred":[
        "\u4e0b\u5434\u6c5f"
    ],
    "wof:name":"Xiawujiang",
    "wof:placetype":"locality"
},
  "geometry": {"coordinates":[108.267,24.9246],"type":"Point"}
}