{
  "type": "Feature",
  "properties": {
    "gn:admin1_code":"26.0",
    "gn:asciiname":"Heijiagou",
    "gn:country_code":"CN",
    "gn:dem":1115,
    "gn:feature_class":"P",
    "gn:feature_code":"PPL",
    "gn:name":"Heijiagou",
    "gn:population":0,
    "gn:timezone":"Asia/Shanghai",
    "iso:country":"CN",
    "name:zho_x_preferred":[
        "\u9ed1\u5bb6\u6c9f"
    ],
    "wof:name":"Heijiagou",
    "wof:placetype":"locality"
},
  "geometry": {"coordinates":[110.01685999999999,36.17246],"type":"Point"}
}