{
  "type": "Feature",
  "properties": {
    "gn:admin1_code":"16.0",
    "gn:asciiname":"Jinbu",
    "gn:country_code":"CN",
    "gn:dem":123,
    "gn:feature_class":"P",
    "gn:feature_code":"PPL",
    "gn:name":"Jinbu",
    "gn:population":0,
    "gn:timezone":"Asia/Shanghai",
    "iso:country":"CN",
    "name:zho_x_preferred":[
        "\u8fdb\u6b65"
    ],
    "wof:name":"Jinbu",
    "wof:placetype":"locality"
},
  "geometry": {"coordinates":[109.53,23.3811],"type":"Point"}
}