{
  "type": "Feature",
  "properties": {
    "gn:admin1_code":"31.0",
    "gn:asciiname":"Shuiyangjue",
    "gn:country_code":"CN",
    "gn:dem":24,
    "gn:feature_class":"P",
    "gn:feature_code":"PPL",
    "gn:name":"Shuiyangjue",
    "gn:population":0,
    "gn:timezone":"Asia/Shanghai",
    "iso:country":"CN",
    "name:und_x_variant":[
        "\u6c34\u592e\u6398"
    ],
    "wof:name":"Shuiyangjue",
    "wof:placetype":"locality"
},
  "geometry": {"coordinates":[110.47226999999999,18.98342],"type":"Point"}
}