{
  "type": "Feature",
  "properties": {
    "iso:country":"CN",
    "name:ara_x_preferred":[
        "\u062f\u0627\u0644\u064a\u0627\u0646"
    ],
    "name:ell_x_preferred":[
        "\u039d\u03c4\u03b1\u03bb\u03b9\u03ac\u03bd"
    ],
    "name:eng_x_preferred":[
        "Dalian"
    ],
    "name:fas_x_preferred":[
        "\u062f\u0627\u0644\u06cc\u0627\u0646"
    ],
    "name:heb_x_preferred":[
        "\u05d3\u05d0\u05dc\u05d9\u05d9\u05df"
    ],
    "name:jpn_x_preferred":[
        "\u5927\u9023\u5e02"
    ],
    "name:kor_x_preferred":[
        "\ub2e4\ub844 \uc2dc"
    ],
    "name:kor_x_variant":[
        "\ub300\ub828"
    ],
    "name:rus_x_preferred":[
        "\u0414\u0430\u043b\u044f\u043d\u044c"
    ],
    "name:tha_x_preferred":[
        "\u0e15\u0e49\u0e32\u0e40\u0e2b\u0e25\u0e35\u0e22\u0e19"
    ],
    "name:ukr_x_preferred":[
        "\u0414\u0430\u043b\u044f\u043d\u044c"
    ],
    "name:unk_x_variant":[
        "Dairen"
    ],
    "name:yue_x_preferred":[
        "\u5927\u9023"
    ],
    "name:zho_x_preferred":[
        "\u5927\u8fde\u5e02"
    ],
    "qs:name":"\u5927\u8fde\u5e02",
    "qs:name_adm0":"\u4e2d\u570b",
    "qs:name_adm1":"\u8fbd\u5b81\u7701",
    "qs:photos":1,
    "qs:photos_1k":1,
    "qs:photos_9k":26,
    "qs:photos_9r":14,
    "qs:photos_all":5787,
    "qs:photos_sr":1,
    "qs:placetype":"LocalAdmin",
    "qs:pop_sr":"0",
    "wof:name":"\u5927\u8fde\u5e02",
    "wof:placetype":"localadmin"
},
  "geometry": {"coordinates":[121.588268,38.9085965],"type":"Point"}
}