{
  "type": "Feature",
  "properties": {
    "gn:admin1_code":"11.0",
    "gn:asciiname":"Shanniutang",
    "gn:country_code":"CN",
    "gn:dem":206,
    "gn:feature_class":"P",
    "gn:feature_code":"PPL",
    "gn:name":"Shanniutang",
    "gn:population":0,
    "gn:timezone":"Asia/Shanghai",
    "iso:country":"CN",
    "name:zho_x_preferred":[
        "\u5c71\u725b\u5858"
    ],
    "wof:name":"Shanniutang",
    "wof:placetype":"locality"
},
  "geometry": {"coordinates":[111.62871,28.27422],"type":"Point"}
}