{
  "type": "Feature",
  "properties": {
    "gn:admin1_code":"33.0",
    "gn:asciiname":"Tangliping",
    "gn:country_code":"CN",
    "gn:dem":1751,
    "gn:feature_class":"P",
    "gn:feature_code":"PPL",
    "gn:name":"Tangliping",
    "gn:population":0,
    "gn:timezone":"Asia/Shanghai",
    "iso:country":"CN",
    "name:zho_x_preferred":[
        "\u7cd6\u68a8\u576a"
    ],
    "wof:name":"Tangliping",
    "wof:placetype":"locality"
},
  "geometry": {"coordinates":[110.06608,30.81771],"type":"Point"}
}