{
  "type": "Feature",
  "properties": {
    "gn:admin1_code":"4.0",
    "gn:asciiname":"Houhegou",
    "gn:country_code":"CN",
    "gn:dem":5,
    "gn:feature_class":"P",
    "gn:feature_code":"PPL",
    "gn:name":"Houhegou",
    "gn:population":0,
    "gn:timezone":"Asia/Shanghai",
    "iso:country":"CN",
    "name:zho_x_preferred":[
        "Houhegou"
    ],
    "name:zho_x_variant":[
        "\u540e\u4f55\u6c9f"
    ],
    "wof:name":"Houhegou",
    "wof:placetype":"locality"
},
  "geometry": {"coordinates":[119.61172999999999,34.04714],"type":"Point"}
}