{
  "type": "Feature",
  "properties": {
    "gn:admin1_code":"25.0",
    "gn:asciiname":"Huowangcun",
    "gn:country_code":"CN",
    "gn:dem":13,
    "gn:feature_class":"P",
    "gn:feature_code":"PPL",
    "gn:name":"Huowangcun",
    "gn:population":0,
    "gn:timezone":"Asia/Shanghai",
    "iso:country":"CN",
    "name:zho_x_preferred":[
        "\u970d\u65fa\u6751"
    ],
    "wof:name":"Huowangcun",
    "wof:placetype":"locality"
},
  "geometry": {"coordinates":[119.94459999999999,37.27902],"type":"Point"}
}