{
  "type": "Feature",
  "properties": {
    "gn:admin1_code":"10",
    "gn:asciiname":"Meitugou",
    "gn:country_code":"CN",
    "gn:dem":1396,
    "gn:feature_class":"P",
    "gn:feature_code":"PPL",
    "gn:name":"Meitugou",
    "gn:population":0,
    "gn:timezone":"Asia/Shanghai",
    "iso:country":"CN",
    "name:zho_x_preferred":[
        "\u6885\u571f\u6c9f"
    ],
    "wof:name":"Meitugou",
    "wof:placetype":"locality"
},
  "geometry": {"coordinates":[116.33947000000001,41.62719],"type":"Point"}
}