{
  "type": "Feature",
  "properties": {
    "gn:admin1_code":"14.0",
    "gn:asciiname":"Guoqinglong",
    "gn:country_code":"CN",
    "gn:dem":4593,
    "gn:feature_class":"P",
    "gn:feature_code":"PPL",
    "gn:name":"Guoqinglong",
    "gn:population":0,
    "gn:timezone":"Asia/Urumqi",
    "iso:country":"CN",
    "name:zho_x_preferred":[
        "\u8fc7\u9752\u9f99"
    ],
    "wof:name":"Guoqinglong",
    "wof:placetype":"locality"
},
  "geometry": {"coordinates":[94.89351000000001,30.97362],"type":"Point"}
}