{
  "type": "Feature",
  "properties": {
    "gn:admin1_code":"11.0",
    "gn:asciiname":"Chengshantou",
    "gn:country_code":"CN",
    "gn:dem":246,
    "gn:feature_class":"P",
    "gn:feature_code":"PPL",
    "gn:name":"Chengshantou",
    "gn:population":0,
    "gn:timezone":"Asia/Shanghai",
    "iso:country":"CN",
    "name:zho_x_preferred":[
        "\u57ce\u5c71\u5934"
    ],
    "wof:name":"Chengshantou",
    "wof:placetype":"locality"
},
  "geometry": {"coordinates":[111.23674,27.30822],"type":"Point"}
}