{
  "type": "Feature",
  "properties": {
    "gn:admin1_code":"30.0",
    "gn:asciiname":"Jixi",
    "gn:country_code":"CN",
    "gn:dem":9,
    "gn:feature_class":"P",
    "gn:feature_code":"PPL",
    "gn:name":"Jixi",
    "gn:population":0,
    "gn:timezone":"Asia/Shanghai",
    "iso:country":"CN",
    "name:zho_x_preferred":[
        "\u79ef\u6eaa"
    ],
    "wof:name":"Jixi",
    "wof:placetype":"locality"
},
  "geometry": {"coordinates":[113.03521000000001,22.74828],"type":"Point"}
}