{
  "type": "Feature",
  "properties": {
    "gn:admin1_code":"30.0",
    "gn:asciiname":"Jixi",
    "gn:country_code":"CN",
    "gn:dem":9,
    "gn:feature_class":"P",
    "gn:feature_code":"PPL",
    "gn:name":"Jixi",
    "gn:population":0,
    "gn:timezone":"Asia/Shanghai",
    "iso:country":"CN",
    "name:ara_x_preferred":[
        "\u062c\u064a\u0634\u0649"
    ],
    "name:cdo_x_preferred":[
        "Gi\u0115-s\u0103\u0324"
    ],
    "name:ceb_x_preferred":[
        "Jixi"
    ],
    "name:ces_x_preferred":[
        "\u0164i-si"
    ],
    "name:dan_x_preferred":[
        "Jixi"
    ],
    "name:deu_x_preferred":[
        "Jixi"
    ],
    "name:eus_x_preferred":[
        "Jixi"
    ],
    "name:fas_x_preferred":[
        "\u062c\u06cc\u0634\u06cc"
    ],
    "name:fin_x_preferred":[
        "Jixi"
    ],
    "name:fra_x_preferred":[
        "Jixi"
    ],
    "name:ind_x_preferred":[
        "Jixi"
    ],
    "name:ita_x_preferred":[
        "Jixi"
    ],
    "name:jpn_x_preferred":[
        "\u9d8f\u897f\u5e02"
    ],
    "name:kik_x_preferred":[
        "Jixi"
    ],
    "name:kor_x_preferred":[
        "\uc9c0\uc2dc\uc2dc"
    ],
    "name:lit_x_preferred":[
        "Dzisi"
    ],
    "name:mlg_x_preferred":[
        "Jixi"
    ],
    "name:nld_x_preferred":[
        "Jixi"
    ],
    "name:nno_x_preferred":[
        "Jixi"
    ],
    "name:nor_x_preferred":[
        "Jixi"
    ],
    "name:pam_x_preferred":[
        "Jixi"
    ],
    "name:pol_x_preferred":[
        "Jixi"
    ],
    "name:por_x_preferred":[
        "Jixi"
    ],
    "name:rus_x_preferred":[
        "\u0426\u0437\u0438\u0441\u0438"
    ],
    "name:spa_x_preferred":[
        "Jixi"
    ],
    "name:srp_x_preferred":[
        "\u0402\u0438\u0441\u0438"
    ],
    "name:swe_x_preferred":[
        "Jixi"
    ],
    "name:tgl_x_preferred":[
        "Jixi"
    ],
    "name:tur_x_preferred":[
        "Jixi"
    ],
    "name:urd_x_preferred":[
        "\u062c\u06cc\u0634\u06cc"
    ],
    "name:vie_x_preferred":[
        "K\u00ea T\u00e2y"
    ],
    "name:war_x_preferred":[
        "Jixi"
    ],
    "name:wuu_x_preferred":[
        "\u9e21\u897f\u5e02"
    ],
    "name:zho_x_preferred":[
        "\u79ef\u6eaa"
    ],
    "name:zho_x_variant":[
        "\u9e21\u897f\u5e02"
    ],
    "wof:name":"Jixi",
    "wof:placetype":"locality"
},
  "geometry": {"coordinates":[113.03521000000001,22.74828],"type":"Point"}
}