{
  "type": "Feature",
  "properties": {
    "gn:admin1_code":"30.0",
    "gn:asciiname":"Weibei",
    "gn:country_code":"CN",
    "gn:dem":193,
    "gn:feature_class":"P",
    "gn:feature_code":"PPL",
    "gn:name":"Weibei",
    "gn:population":0,
    "gn:timezone":"Asia/Shanghai",
    "iso:country":"CN",
    "name:zho_x_preferred":[
        "Weibei"
    ],
    "name:zho_x_variant":[
        "\u56f4\u80cc"
    ],
    "wof:name":"Weibei",
    "wof:placetype":"locality"
},
  "geometry": {"coordinates":[115.21028,24.48],"type":"Point"}
}