{
  "type": "Feature",
  "properties": {
    "gn:admin1_code":"3.0",
    "gn:asciiname":"Yuxian",
    "gn:country_code":"CN",
    "gn:dem":76,
    "gn:feature_class":"P",
    "gn:feature_code":"PPL",
    "gn:name":"Yuxian",
    "gn:population":0,
    "gn:timezone":"Asia/Shanghai",
    "iso:country":"CN",
    "name:ceb_x_preferred":[
        "Yuxian"
    ],
    "name:zho_x_preferred":[
        "\u80b2\u8d24"
    ],
    "wof:name":"Yuxian",
    "wof:placetype":"locality"
},
  "geometry": {"coordinates":[114.895,27.482],"type":"Point"}
}