{
  "type": "Feature",
  "properties": {
    "gn:admin1_code":"32.0",
    "gn:asciiname":"Shuimogou",
    "gn:country_code":"CN",
    "gn:dem":713,
    "gn:feature_class":"P",
    "gn:feature_code":"PPL",
    "gn:name":"Shuimogou",
    "gn:population":0,
    "gn:timezone":"Asia/Shanghai",
    "iso:country":"CN",
    "name:zho_x_preferred":[
        "\u6c34\u78e8\u6c9f"
    ],
    "wof:name":"Shuimogou",
    "wof:placetype":"locality"
},
  "geometry": {"coordinates":[107.414,32.1343],"type":"Point"}
}