{
  "type": "Feature",
  "properties": {
    "gn:admin1_code":"2.0",
    "gn:asciiname":"Huitang",
    "gn:country_code":"CN",
    "gn:dem":42,
    "gn:feature_class":"P",
    "gn:feature_code":"PPL",
    "gn:name":"Huitang",
    "gn:population":0,
    "gn:timezone":"Asia/Shanghai",
    "iso:country":"CN",
    "name:und_x_variant":[
        "\u7070\u5858",
        "Huitang"
    ],
    "wof:name":"Huitang",
    "wof:placetype":"locality"
},
  "geometry": {"coordinates":[119.67335,29.97312],"type":"Point"}
}