{
  "type": "Feature",
  "properties": {
    "gn:admin1_code":"16.0",
    "gn:asciiname":"Longbeishan",
    "gn:country_code":"CN",
    "gn:dem":216,
    "gn:feature_class":"P",
    "gn:feature_code":"PPL",
    "gn:name":"Longbeishan",
    "gn:population":0,
    "gn:timezone":"Asia/Shanghai",
    "iso:country":"CN",
    "name:zho_x_preferred":[
        "\u9f99\u80cc\u5c71"
    ],
    "wof:name":"Longbeishan",
    "wof:placetype":"locality"
},
  "geometry": {"coordinates":[110.93000000000001,24.5542],"type":"Point"}
}