{
  "type": "Feature",
  "properties": {
    "gn:admin1_code":"4.0",
    "gn:asciiname":"Yangmiaozi",
    "gn:country_code":"CN",
    "gn:dem":4,
    "gn:feature_class":"P",
    "gn:feature_code":"PPL",
    "gn:name":"Yangmiaozi",
    "gn:population":0,
    "gn:timezone":"Asia/Shanghai",
    "iso:country":"CN",
    "name:zho_x_preferred":[
        "\u6768\u5e99\u5b50"
    ],
    "wof:name":"Yangmiaozi",
    "wof:placetype":"locality"
},
  "geometry": {"coordinates":[119.43836,32.93351],"type":"Point"}
}