{
  "type": "Feature",
  "properties": {
    "gn:admin1_code":"11.0",
    "gn:asciiname":"Dianwubei",
    "gn:country_code":"CN",
    "gn:dem":443,
    "gn:feature_class":"P",
    "gn:feature_code":"PPL",
    "gn:name":"Dianwubei",
    "gn:population":0,
    "gn:timezone":"Asia/Shanghai",
    "iso:country":"CN",
    "name:zho_x_preferred":[
        "\u5e97\u5c4b\u80cc"
    ],
    "wof:name":"Dianwubei",
    "wof:placetype":"locality"
},
  "geometry": {"coordinates":[109.55898999999999,27.33829],"type":"Point"}
}