{
  "type": "Feature",
  "properties": {
    "gn:admin1_code":"4.0",
    "gn:asciiname":"Hexing",
    "gn:country_code":"CN",
    "gn:dem":1,
    "gn:feature_class":"P",
    "gn:feature_code":"PPL",
    "gn:name":"Hexing",
    "gn:population":0,
    "gn:timezone":"Asia/Shanghai",
    "iso:country":"CN",
    "name:zho_x_preferred":[
        "Hexing"
    ],
    "name:zho_x_variant":[
        "\u4f55\u884c"
    ],
    "wof:name":"Hexing",
    "wof:placetype":"locality"
},
  "geometry": {"coordinates":[119.57861,34.04384],"type":"Point"}
}