{
  "type": "Feature",
  "properties": {
    "gn:admin1_code":"14.0",
    "gn:asciiname":"Tamadun",
    "gn:country_code":"CN",
    "gn:dem":3855,
    "gn:feature_class":"P",
    "gn:feature_code":"PPL",
    "gn:name":"Tamadun",
    "gn:population":0,
    "gn:timezone":"Asia/Urumqi",
    "iso:country":"CN",
    "name:bod_x_preferred":[
        "Dagmad\u00eam"
    ],
    "name:zho_x_preferred":[
        "Tamadun"
    ],
    "name:zho_x_variant":[
        "\u5854\u9a6c\u987f",
        "\u5854\u9a6c\u58a9"
    ],
    "wof:name":"Tamadun",
    "wof:placetype":"locality"
},
  "geometry": {"coordinates":[93.91606,28.81218],"type":"Point"}
}