{
  "type": "Feature",
  "properties": {
    "gn:admin1_code":"15.0",
    "gn:asciiname":"Shangsanjie",
    "gn:country_code":"CN",
    "gn:dem":1745,
    "gn:feature_class":"P",
    "gn:feature_code":"PPL",
    "gn:name":"Shangsanjie",
    "gn:population":0,
    "gn:timezone":"Asia/Shanghai",
    "iso:country":"CN",
    "name:zho_x_preferred":[
        "\u4e0a\u4e09\u622a"
    ],
    "wof:name":"Shangsanjie",
    "wof:placetype":"locality"
},
  "geometry": {"coordinates":[98.7908,39.4327],"type":"Point"}
}