{
  "type": "Feature",
  "properties": {
    "gn:admin1_code":"14.0",
    "gn:asciiname":"Gonghe",
    "gn:country_code":"CN",
    "gn:dem":3596,
    "gn:feature_class":"P",
    "gn:feature_code":"PPL",
    "gn:name":"Gonghe",
    "gn:population":0,
    "gn:timezone":"Asia/Urumqi",
    "iso:country":"CN",
    "name:zho_x_preferred":[
        "\u8d21\u6cb3"
    ],
    "wof:name":"Gonghe",
    "wof:placetype":"locality"
},
  "geometry": {"coordinates":[93.45026,30.07668],"type":"Point"}
}