{
  "type": "Feature",
  "properties": {
    "gn:admin1_code":"32.0",
    "gn:asciiname":"Changcaoping",
    "gn:country_code":"CN",
    "gn:dem":2980,
    "gn:feature_class":"P",
    "gn:feature_code":"PPL",
    "gn:name":"Changcaoping",
    "gn:population":0,
    "gn:timezone":"Asia/Shanghai",
    "iso:country":"CN",
    "name:zho_x_preferred":[
        "\u957f\u8349\u576a"
    ],
    "wof:name":"Changcaoping",
    "wof:placetype":"locality"
},
  "geometry": {"coordinates":[101.32113,29.4989],"type":"Point"}
}