{
  "type": "Feature",
  "properties": {
    "gn:admin1_code":"14.0",
    "gn:asciiname":"Doqung",
    "gn:country_code":"CN",
    "gn:dem":4942,
    "gn:feature_class":"P",
    "gn:feature_code":"PPL",
    "gn:name":"Doqung",
    "gn:population":0,
    "gn:timezone":"Asia/Urumqi",
    "iso:country":"CN",
    "name:bod_x_preferred":[
        "Doqung"
    ],
    "name:zho_x_preferred":[
        "Duoqiong"
    ],
    "name:zho_x_variant":[
        "\u593a\u743c"
    ],
    "wof:name":"Doqung",
    "wof:placetype":"locality"
},
  "geometry": {"coordinates":[89.15715,30.48327],"type":"Point"}
}