{
  "type": "Feature",
  "properties": {
    "gn:admin1_code":"19.0",
    "gn:asciiname":"Xiaotao Huatucun",
    "gn:country_code":"CN",
    "gn:dem":183,
    "gn:feature_class":"P",
    "gn:feature_code":"PPL",
    "gn:name":"Xiaotao Huatucun",
    "gn:population":0,
    "gn:timezone":"Asia/Shanghai",
    "iso:country":"CN",
    "name:und_x_variant":[
        "Xiaotaohuatucun",
        "Xiaotao Huatucun"
    ],
    "name:zho_x_preferred":[
        "\u5c0f\u6843\u82b1\u5410\u6751"
    ],
    "wof:name":"Xiaotao Huatucun",
    "wof:placetype":"locality"
},
  "geometry": {"coordinates":[120.56543000000001,41.64962],"type":"Point"}
}