{
  "type": "Feature",
  "properties": {
    "gn:admin1_code":"2",
    "gn:asciiname":"Guzhucun",
    "gn:country_code":"CN",
    "gn:dem":86,
    "gn:feature_class":"P",
    "gn:feature_code":"PPL",
    "gn:name":"Guzhucun",
    "gn:population":0,
    "gn:timezone":"Asia/Shanghai",
    "iso:country":"CN",
    "name:und_x_variant":[
        "Guzhu"
    ],
    "name:zho_x_preferred":[
        "\u987e\u6e1a\u6751"
    ],
    "wof:name":"Guzhucun",
    "wof:placetype":"locality"
},
  "geometry": {"coordinates":[119.81012,31.12708],"type":"Point"}
}