{
  "type": "Feature",
  "properties": {
    "gn:admin1_code":"30.0",
    "gn:asciiname":"Zhenzhugang",
    "gn:country_code":"CN",
    "gn:dem":11,
    "gn:feature_class":"P",
    "gn:feature_code":"PPL",
    "gn:name":"Zhenzhugang",
    "gn:population":0,
    "gn:timezone":"Asia/Shanghai",
    "iso:country":"CN",
    "name:zho_x_preferred":[
        "\u73cd\u73e0\u5188"
    ],
    "wof:name":"Zhenzhugang",
    "wof:placetype":"locality"
},
  "geometry": {"coordinates":[111.93058000000001,21.95888],"type":"Point"}
}