{
  "type": "Feature",
  "properties": {
    "gn:admin1_code":"14.0",
    "gn:asciiname":"Maguocun",
    "gn:country_code":"CN",
    "gn:dem":4931,
    "gn:feature_class":"P",
    "gn:feature_code":"PPL",
    "gn:name":"Maguocun",
    "gn:population":0,
    "gn:timezone":"Asia/Urumqi",
    "iso:country":"CN",
    "name:zho_x_preferred":[
        "\u739b\u679c\u6751"
    ],
    "wof:name":"Maguocun",
    "wof:placetype":"locality"
},
  "geometry": {"coordinates":[91.90423,32.00897],"type":"Point"}
}