{
  "type": "Feature",
  "properties": {
    "gn:admin1_code":"3.0",
    "gn:asciiname":"Chencun",
    "gn:country_code":"CN",
    "gn:dem":67,
    "gn:feature_class":"P",
    "gn:feature_code":"PPL",
    "gn:name":"Chencun",
    "gn:population":0,
    "gn:timezone":"Asia/Shanghai",
    "iso:country":"CN",
    "name:und_x_variant":[
        "\u9648\u6751"
    ],
    "wof:name":"Chencun",
    "wof:placetype":"locality"
},
  "geometry": {"coordinates":[115.04901,28.11237],"type":"Point"}
}