{
  "type": "Feature",
  "properties": {
    "gn:admin1_code":"15.0",
    "gn:asciiname":"Beiyuanbian",
    "gn:country_code":"CN",
    "gn:dem":1838,
    "gn:feature_class":"P",
    "gn:feature_code":"PPL",
    "gn:name":"Beiyuanbian",
    "gn:population":0,
    "gn:timezone":"Asia/Shanghai",
    "iso:country":"CN",
    "name:zho_x_preferred":[
        "\u5317\u586c\u8fb9"
    ],
    "wof:name":"Beiyuanbian",
    "wof:placetype":"locality"
},
  "geometry": {"coordinates":[105.00700000000001,36.2272],"type":"Point"}
}