{
  "type": "Feature",
  "properties": {
    "gn:admin1_code":"14.0",
    "gn:asciiname":"Coka",
    "gn:country_code":"CN",
    "gn:dem":3751,
    "gn:feature_class":"P",
    "gn:feature_code":"PPLA3",
    "gn:name":"Coka",
    "gn:population":0,
    "gn:timezone":"Asia/Urumqi",
    "iso:country":"CN",
    "name:bod_x_preferred":[
        "Coka"
    ],
    "name:bod_x_variant":[
        "Coka Zhen"
    ],
    "name:und_x_variant":[
        "Caoka Zhen"
    ],
    "name:zho_x_preferred":[
        "Caoka"
    ],
    "name:zho_x_variant":[
        "\u8349\u5361",
        "Guochitang",
        "\u90ed\u8d64\u5858",
        "\u8349\u5361\u9547"
    ],
    "wof:name":"Coka",
    "wof:placetype":"locality"
},
  "geometry": {"coordinates":[94.6695,30.9054],"type":"Point"}
}