{
  "type": "Feature",
  "properties": {
    "gn:admin1_code":"31.0",
    "gn:asciiname":"Qichacun",
    "gn:country_code":"CN",
    "gn:dem":123,
    "gn:feature_class":"P",
    "gn:feature_code":"PPL",
    "gn:name":"Qichacun",
    "gn:population":0,
    "gn:timezone":"Asia/Shanghai",
    "iso:country":"CN",
    "name:zho_x_preferred":[
        "Qichacun"
    ],
    "name:zho_x_variant":[
        "\u4e03\u5dee\u6751"
    ],
    "wof:name":"Qichacun",
    "wof:placetype":"locality"
},
  "geometry": {"coordinates":[109.06686000000001,19.11543],"type":"Point"}
}