{
  "type": "Feature",
  "properties": {
    "gn:admin1_code":"33.0",
    "gn:asciiname":"Lesheng",
    "gn:country_code":"CN",
    "gn:dem":759,
    "gn:feature_class":"P",
    "gn:feature_code":"PPL",
    "gn:name":"Lesheng",
    "gn:population":0,
    "gn:timezone":"Asia/Shanghai",
    "iso:country":"CN",
    "name:zho_x_preferred":[
        "\u4e50\u80dc"
    ],
    "wof:name":"Lesheng",
    "wof:placetype":"locality"
},
  "geometry": {"coordinates":[106.43000000000001,28.9732],"type":"Point"}
}