{
  "type": "Feature",
  "properties": {
    "gn:admin1_code":"11.0",
    "gn:asciiname":"Yangjiazhuang",
    "gn:country_code":"CN",
    "gn:dem":112,
    "gn:feature_class":"P",
    "gn:feature_code":"PPL",
    "gn:name":"Yangjiazhuang",
    "gn:population":0,
    "gn:timezone":"Asia/Shanghai",
    "iso:country":"CN",
    "name:zho_x_preferred":[
        "Yangjiazhuang"
    ],
    "name:zho_x_variant":[
        "\u6768\u5bb6\u5e84"
    ],
    "wof:name":"Yangjiazhuang",
    "wof:placetype":"locality"
},
  "geometry": {"coordinates":[111.24617000000001,29.06297],"type":"Point"}
}