{
  "type": "Feature",
  "properties": {
    "gn:admin1_code":"14.0",
    "gn:asciiname":"Yuebacun",
    "gn:country_code":"CN",
    "gn:dem":4331,
    "gn:feature_class":"P",
    "gn:feature_code":"PPL",
    "gn:name":"Yuebacun",
    "gn:population":0,
    "gn:timezone":"Asia/Urumqi",
    "iso:country":"CN",
    "name:zho_x_preferred":[
        "\u7ea6\u5df4\u6751"
    ],
    "wof:name":"Yuebacun",
    "wof:placetype":"locality"
},
  "geometry": {"coordinates":[96.88759,30.17435],"type":"Point"}
}