{
  "type": "Feature",
  "properties": {
    "gn:admin1_code":"13.0",
    "gn:asciiname":"Tusala",
    "gn:country_code":"CN",
    "gn:dem":1264,
    "gn:feature_class":"P",
    "gn:feature_code":"PPL",
    "gn:name":"Tusala",
    "gn:population":0,
    "gn:timezone":"Asia/Shanghai",
    "iso:country":"CN",
    "name:zho_x_preferred":[
        "\u5410\u8428\u62c9"
    ],
    "wof:name":"Tusala",
    "wof:placetype":"locality"
},
  "geometry": {"coordinates":[80.31744999999999,37.60926],"type":"Point"}
}