{
  "type": "Feature",
  "properties": {
    "gn:admin1_code":"29.0",
    "gn:asciiname":"Xingyuan",
    "gn:country_code":"CN",
    "gn:dem":1861,
    "gn:feature_class":"P",
    "gn:feature_code":"PPL",
    "gn:name":"Xingyuan",
    "gn:population":0,
    "gn:timezone":"Asia/Shanghai",
    "iso:country":"CN",
    "name:zho_x_preferred":[
        "\u5174\u56ed"
    ],
    "wof:name":"Xingyuan",
    "wof:placetype":"locality"
},
  "geometry": {"coordinates":[100.069,26.9951],"type":"Point"}
}