{
  "type": "Feature",
  "properties": {
    "gn:admin1_code":"1.0",
    "gn:asciiname":"Huimincun",
    "gn:country_code":"CN",
    "gn:dem":7,
    "gn:feature_class":"P",
    "gn:feature_code":"PPL",
    "gn:name":"Huimincun",
    "gn:population":0,
    "gn:timezone":"Asia/Shanghai",
    "iso:country":"CN",
    "name:zho_x_preferred":[
        "\u60e0\u6c11\u6751"
    ],
    "wof:name":"Huimincun",
    "wof:placetype":"locality"
},
  "geometry": {"coordinates":[118.69287,31.25189],"type":"Point"}
}