{
  "type": "Feature",
  "properties": {
    "gn:admin1_code":"2",
    "gn:asciiname":"Jiekou",
    "gn:country_code":"CN",
    "gn:dem":154,
    "gn:feature_class":"P",
    "gn:feature_code":"PPL",
    "gn:name":"Jiekou",
    "gn:population":0,
    "gn:timezone":"Asia/Shanghai",
    "iso:country":"CN",
    "name:und_x_variant":[
        "\u82a5\u53e3"
    ],
    "wof:name":"Jiekou",
    "wof:placetype":"locality"
},
  "geometry": {"coordinates":[119.64592,31.03434],"type":"Point"}
}