{
  "type": "Feature",
  "properties": {
    "gn:admin1_code":"9.0",
    "gn:asciiname":"Matun",
    "gn:country_code":"CN",
    "gn:dem":81,
    "gn:feature_class":"P",
    "gn:feature_code":"PPL",
    "gn:name":"Matun",
    "gn:population":0,
    "gn:timezone":"Asia/Shanghai",
    "iso:country":"CN",
    "name:ceb_x_preferred":[
        "Matun"
    ],
    "name:swe_x_preferred":[
        "Matun"
    ],
    "name:zho_x_preferred":[
        "\u9a6c\u5c6f"
    ],
    "wof:name":"Matun",
    "wof:placetype":"locality"
},
  "geometry": {"coordinates":[114.36696000000001,35.82818],"type":"Point"}
}