{
  "type": "Feature",
  "properties": {
    "gn:admin1_code":"5.0",
    "gn:asciiname":"Donghetun",
    "gn:country_code":"CN",
    "gn:dem":169,
    "gn:feature_class":"P",
    "gn:feature_code":"PPL",
    "gn:name":"Donghetun",
    "gn:population":0,
    "gn:timezone":"Asia/Shanghai",
    "iso:country":"CN",
    "name:zho_x_preferred":[
        "\u4e1c\u6cb3\u5c6f"
    ],
    "wof:name":"Donghetun",
    "wof:placetype":"locality"
},
  "geometry": {"coordinates":[122.23283000000001,44.7128],"type":"Point"}
}