{
  "type": "Feature",
  "properties": {
    "gn:admin1_code":"9",
    "gn:asciiname":"Duomidian",
    "gn:country_code":"CN",
    "gn:dem":41,
    "gn:feature_class":"P",
    "gn:feature_code":"PPL",
    "gn:name":"Duomidian",
    "gn:population":0,
    "gn:timezone":"Asia/Shanghai",
    "iso:country":"CN",
    "name:zho_x_preferred":[
        "\u591a\u8ff7\u5e97"
    ],
    "wof:name":"Duomidian",
    "wof:placetype":"locality"
},
  "geometry": {"coordinates":[115.55,33.7145],"type":"Point"}
}