{
  "type": "Feature",
  "properties": {
    "gn:admin1_code":"8.0",
    "gn:asciiname":"Gaidayancong",
    "gn:country_code":"CN",
    "gn:dem":250,
    "gn:feature_class":"P",
    "gn:feature_code":"PPL",
    "gn:name":"Gaidayancong",
    "gn:population":0,
    "gn:timezone":"Asia/Shanghai",
    "iso:country":"CN",
    "name:zho_x_preferred":[
        "\u76d6\u5927\u70df\u56f1"
    ],
    "wof:name":"Gaidayancong",
    "wof:placetype":"locality"
},
  "geometry": {"coordinates":[126.20659999999999,47.80206],"type":"Point"}
}