{
  "type": "Feature",
  "properties": {
    "gn:admin1_code":"30",
    "gn:asciiname":"Shangjishe",
    "gn:country_code":"CN",
    "gn:dem":253,
    "gn:feature_class":"P",
    "gn:feature_code":"PPL",
    "gn:name":"Shangjishe",
    "gn:population":0,
    "gn:timezone":"Asia/Shanghai",
    "iso:country":"CN",
    "wof:name":"Shangjishe",
    "wof:placetype":"locality"
},
  "geometry": {"coordinates":[116.3537,23.86728],"type":"Point"}
}