{
  "type": "Feature",
  "properties": {
    "gn:admin1_code":"33.0",
    "gn:asciiname":"Beijiyan",
    "gn:country_code":"CN",
    "gn:dem":658,
    "gn:feature_class":"P",
    "gn:feature_code":"PPL",
    "gn:name":"Beijiyan",
    "gn:population":0,
    "gn:timezone":"Asia/Shanghai",
    "iso:country":"CN",
    "name:zho_x_preferred":[
        "\u7891\u8bb0\u5ca9"
    ],
    "wof:name":"Beijiyan",
    "wof:placetype":"locality"
},
  "geometry": {"coordinates":[106.39197,28.7144],"type":"Point"}
}