{
  "type": "Feature",
  "properties": {
    "gn:admin1_code":"25.0",
    "gn:asciiname":"Tieshancun",
    "gn:country_code":"CN",
    "gn:dem":96,
    "gn:feature_class":"P",
    "gn:feature_code":"PPL",
    "gn:name":"Tieshancun",
    "gn:population":0,
    "gn:timezone":"Asia/Shanghai",
    "iso:country":"CN",
    "name:zho_x_preferred":[
        "\u94c1\u5c71\u6751"
    ],
    "wof:name":"Tieshancun",
    "wof:placetype":"locality"
},
  "geometry": {"coordinates":[121.27384000000001,36.93457],"type":"Point"}
}