{
  "type": "Feature",
  "properties": {
    "gn:admin1_code":"02",
    "gn:asciiname":"Guantou",
    "gn:country_code":"CN",
    "gn:dem":47,
    "gn:feature_class":"P",
    "gn:feature_code":"PPL",
    "gn:name":"Guantou",
    "gn:population":0,
    "gn:timezone":"Asia/Shanghai",
    "iso:country":"CN",
    "name:und_x_variant":[
        "Kuan-t\u2019ou",
        "Guantou",
        "\u5173\u5934",
        "Guantoucun",
        "\u5173\u5934\u6751"
    ],
    "wof:name":"Guantou",
    "wof:placetype":"locality"
},
  "geometry": {"coordinates":[121.42717,30.06853],"type":"Point"}
}