{
  "type": "Feature",
  "properties": {
    "gn:admin1_code":"1.0",
    "gn:asciiname":"Luozhaicun",
    "gn:country_code":"CN",
    "gn:dem":55,
    "gn:feature_class":"P",
    "gn:feature_code":"PPL",
    "gn:name":"Luozhaicun",
    "gn:population":0,
    "gn:timezone":"Asia/Shanghai",
    "iso:country":"CN",
    "name:zho_x_preferred":[
        "\u7f57\u5be8\u6751"
    ],
    "wof:name":"Luozhaicun",
    "wof:placetype":"locality"
},
  "geometry": {"coordinates":[116.35491,34.55119000000001],"type":"Point"}
}