{
  "type": "Feature",
  "properties": {
    "gn:admin1_code":"12.0",
    "gn:asciiname":"Daya",
    "gn:country_code":"CN",
    "gn:dem":1431,
    "gn:feature_class":"P",
    "gn:feature_code":"PPL",
    "gn:name":"Daya",
    "gn:population":0,
    "gn:timezone":"Asia/Shanghai",
    "iso:country":"CN",
    "name:ceb_x_preferred":[
        "Daya"
    ],
    "name:heb_x_preferred":[
        "\u05d3\u05d9\u05d4"
    ],
    "name:pol_x_preferred":[
        "Daya"
    ],
    "name:swe_x_preferred":[
        "Daya"
    ],
    "name:vie_x_preferred":[
        "Daya"
    ],
    "name:zho_x_preferred":[
        "\u5927\u57ad"
    ],
    "wof:name":"Daya",
    "wof:placetype":"locality"
},
  "geometry": {"coordinates":[110.45241,30.74031],"type":"Point"}
}