{
  "type": "Feature",
  "properties": {
    "gn:admin1_code":"29.0",
    "gn:asciiname":"Damaidi",
    "gn:country_code":"CN",
    "gn:dem":2177,
    "gn:feature_class":"P",
    "gn:feature_code":"PPL",
    "gn:name":"Damaidi",
    "gn:population":0,
    "gn:timezone":"Asia/Shanghai",
    "iso:country":"CN",
    "name:zho_x_preferred":[
        "\u5927\u9ea6\u5730"
    ],
    "wof:name":"Damaidi",
    "wof:placetype":"locality"
},
  "geometry": {"coordinates":[103.843,25.9202],"type":"Point"}
}