{
  "type": "Feature",
  "properties": {
    "gn:admin1_code":"7.0",
    "gn:asciiname":"Dingyuan",
    "gn:country_code":"CN",
    "gn:dem":429,
    "gn:feature_class":"P",
    "gn:feature_code":"PPL",
    "gn:name":"Dingyuan",
    "gn:population":0,
    "gn:timezone":"Asia/Shanghai",
    "iso:country":"CN",
    "name:ceb_x_preferred":[
        "Dingyuan"
    ],
    "name:ces_x_preferred":[
        "Ting-j\u00fcan"
    ],
    "name:deu_x_preferred":[
        "Dingyuan"
    ],
    "name:swe_x_preferred":[
        "Dingyuan"
    ],
    "name:zho_x_preferred":[
        "\u5b9a\u6e90"
    ],
    "wof:name":"Dingyuan",
    "wof:placetype":"locality"
},
  "geometry": {"coordinates":[117.27387,27.63662],"type":"Point"}
}