{
  "type": "Feature",
  "properties": {
    "gn:admin1_code":"2.0",
    "gn:asciiname":"Huanglingtou",
    "gn:country_code":"CN",
    "gn:dem":505,
    "gn:feature_class":"P",
    "gn:feature_code":"PPL",
    "gn:name":"Huanglingtou",
    "gn:population":0,
    "gn:timezone":"Asia/Shanghai",
    "iso:country":"CN",
    "name:zho_x_preferred":[
        "\u9ec4\u5cad\u5934"
    ],
    "wof:name":"Huanglingtou",
    "wof:placetype":"locality"
},
  "geometry": {"coordinates":[119.65572,28.41466],"type":"Point"}
}