{
  "type": "Feature",
  "properties": {
    "gn:admin1_code":"1.0",
    "gn:asciiname":"Wulijingcun",
    "gn:country_code":"CN",
    "gn:dem":23,
    "gn:feature_class":"P",
    "gn:feature_code":"PPL",
    "gn:name":"Wulijingcun",
    "gn:population":0,
    "gn:timezone":"Asia/Shanghai",
    "iso:country":"CN",
    "name:zho_x_preferred":[
        "\u4e94\u91cc\u4e95\u6751"
    ],
    "wof:name":"Wulijingcun",
    "wof:placetype":"locality"
},
  "geometry": {"coordinates":[117.33789,33.33368],"type":"Point"}
}