{
  "type": "Feature",
  "properties": {
    "gn:admin1_code":"4.0",
    "gn:asciiname":"Xichengcun",
    "gn:country_code":"CN",
    "gn:dem":15,
    "gn:feature_class":"P",
    "gn:feature_code":"PPL",
    "gn:name":"Xichengcun",
    "gn:population":0,
    "gn:timezone":"Asia/Shanghai",
    "iso:country":"CN",
    "name:zho_x_preferred":[
        "\u897f\u57ce\u6751"
    ],
    "wof:name":"Xichengcun",
    "wof:placetype":"locality"
},
  "geometry": {"coordinates":[119.17328000000001,31.84692],"type":"Point"}
}