{
  "type": "Feature",
  "properties": {
    "gn:admin1_code":"4.0",
    "gn:asciiname":"Fengle",
    "gn:country_code":"CN",
    "gn:dem":4,
    "gn:feature_class":"P",
    "gn:feature_code":"PPL",
    "gn:name":"Fengle",
    "gn:population":0,
    "gn:timezone":"Asia/Shanghai",
    "iso:country":"CN",
    "name:zho_x_preferred":[
        "\u4e30\u4e50"
    ],
    "wof:name":"Fengle",
    "wof:placetype":"locality"
},
  "geometry": {"coordinates":[119.74207,32.28371],"type":"Point"}
}