{
  "type": "Feature",
  "properties": {
    "gn:admin1_code":"26.0",
    "gn:asciiname":"Aijia Maodicun",
    "gn:country_code":"CN",
    "gn:dem":1036,
    "gn:feature_class":"P",
    "gn:feature_code":"PPL",
    "gn:name":"Aijia Maodicun",
    "gn:population":0,
    "gn:timezone":"Asia/Shanghai",
    "iso:country":"CN",
    "name:zho_x_preferred":[
        "\u827e\u5bb6\u5cc1\u5e95\u6751"
    ],
    "wof:name":"Aijia Maodicun",
    "wof:placetype":"locality"
},
  "geometry": {"coordinates":[110.295,37.7715],"type":"Point"}
}