{
  "type": "Feature",
  "properties": {
    "gn:admin1_code":"30.0",
    "gn:asciiname":"Niwei",
    "gn:country_code":"CN",
    "gn:dem":12,
    "gn:feature_class":"P",
    "gn:feature_code":"PPL",
    "gn:name":"Niwei",
    "gn:population":0,
    "gn:timezone":"Asia/Shanghai",
    "iso:country":"CN",
    "name:zho_x_preferred":[
        "\u576d\u56f4"
    ],
    "wof:name":"Niwei",
    "wof:placetype":"locality"
},
  "geometry": {"coordinates":[112.89176999999999,23.55804],"type":"Point"}
}