{
  "type": "Feature",
  "properties": {
    "gn:admin1_code":"1.0",
    "gn:asciiname":"Xingliu",
    "gn:cc2":"CN",
    "gn:country_code":"CN",
    "gn:dem":34,
    "gn:feature_class":"P",
    "gn:feature_code":"PPL",
    "gn:name":"Xingliu",
    "gn:population":0,
    "gn:timezone":"Asia/Shanghai",
    "iso:country":"CN",
    "name:und_x_variant":[
        "Hsing-liu",
        "Hsing-liu-chi",
        "Xingliu"
    ],
    "wof:name":"Xingliu",
    "wof:placetype":"locality"
},
  "geometry": {"coordinates":[115.71666999999999,33.05],"type":"Point"}
}