{
  "type": "Feature",
  "properties": {
    "gn:admin1_code":"3.0",
    "gn:asciiname":"Zhuzhuling",
    "gn:country_code":"CN",
    "gn:dem":84,
    "gn:feature_class":"P",
    "gn:feature_code":"PPL",
    "gn:name":"Zhuzhuling",
    "gn:population":0,
    "gn:timezone":"Asia/Shanghai",
    "iso:country":"CN",
    "name:zho_x_preferred":[
        "\u682a\u69e0\u5cad"
    ],
    "wof:name":"Zhuzhuling",
    "wof:placetype":"locality"
},
  "geometry": {"coordinates":[117.545,28.5036],"type":"Point"}
}