{
  "type": "Feature",
  "properties": {
    "gn:admin1_code":"25",
    "gn:asciiname":"Gadao",
    "gn:country_code":"CN",
    "gn:dem":35,
    "gn:feature_class":"P",
    "gn:feature_code":"PPL",
    "gn:name":"Gadao",
    "gn:population":0,
    "gn:timezone":"Asia/Shanghai",
    "iso:country":"CN",
    "name:cha_x_preferred":[
        "Gadao"
    ],
    "name:por_x_preferred":[
        "Gadao"
    ],
    "wof:name":"Gadao",
    "wof:placetype":"locality"
},
  "geometry": {"coordinates":[116.82472,35.28528],"type":"Point"}
}