{
  "type": "Feature",
  "properties": {
    "gn:admin1_code":"1.0",
    "gn:asciiname":"Gaoxiaozhuangcun",
    "gn:country_code":"CN",
    "gn:dem":36,
    "gn:feature_class":"P",
    "gn:feature_code":"PPL",
    "gn:name":"Gaoxiaozhuangcun",
    "gn:population":0,
    "gn:timezone":"Asia/Shanghai",
    "iso:country":"CN",
    "name:und_x_variant":[
        "Gaoxiaozhuang"
    ],
    "name:zho_x_preferred":[
        "\u9ad8\u5c0f\u5e84\u6751"
    ],
    "wof:name":"Gaoxiaozhuangcun",
    "wof:placetype":"locality"
},
  "geometry": {"coordinates":[115.95,33.78333],"type":"Point"}
}