{
  "type": "Feature",
  "properties": {
    "gn:admin1_code":"18",
    "gn:asciiname":"Jiatou",
    "gn:country_code":"CN",
    "gn:dem":871,
    "gn:feature_class":"P",
    "gn:feature_code":"PPL",
    "gn:name":"Jiatou",
    "gn:population":0,
    "gn:timezone":"Asia/Shanghai",
    "iso:country":"CN",
    "name:zho_x_preferred":[
        "\u7532\u5934"
    ],
    "wof:name":"Jiatou",
    "wof:placetype":"locality"
},
  "geometry": {"coordinates":[107.267,25.7587],"type":"Point"}
}