{
  "type": "Feature",
  "properties": {
    "gn:admin1_code":"16.0",
    "gn:asciiname":"Liulu",
    "gn:country_code":"CN",
    "gn:dem":1048,
    "gn:feature_class":"P",
    "gn:feature_code":"PPL",
    "gn:name":"Liulu",
    "gn:population":0,
    "gn:timezone":"Asia/Shanghai",
    "iso:country":"CN",
    "name:zho_x_preferred":[
        "\u516d\u9c81"
    ],
    "wof:name":"Liulu",
    "wof:placetype":"locality"
},
  "geometry": {"coordinates":[105.176,24.7993],"type":"Point"}
}