{
  "type": "Feature",
  "properties": {
    "gn:admin1_code":"32.0",
    "gn:asciiname":"Wenchangmaio",
    "gn:country_code":"CN",
    "gn:dem":382,
    "gn:feature_class":"P",
    "gn:feature_code":"PPL",
    "gn:name":"Wenchangmaio",
    "gn:population":0,
    "gn:timezone":"Asia/Shanghai",
    "iso:country":"CN",
    "name:zho_x_preferred":[
        "\u6587\u660c\u5e99"
    ],
    "wof:name":"Wenchangmaio",
    "wof:placetype":"locality"
},
  "geometry": {"coordinates":[105.68903,29.12146],"type":"Point"}
}