{
  "type": "Feature",
  "properties": {
    "gn:admin1_code":"24.0",
    "gn:asciiname":"Caojia Yadicun",
    "gn:country_code":"CN",
    "gn:dem":993,
    "gn:feature_class":"P",
    "gn:feature_code":"PPL",
    "gn:name":"Caojia Yadicun",
    "gn:population":0,
    "gn:timezone":"Asia/Shanghai",
    "iso:country":"CN",
    "name:zho_x_preferred":[
        "\u66f9\u5bb6\u5d16\u5e95\u6751"
    ],
    "wof:name":"Caojia Yadicun",
    "wof:placetype":"locality"
},
  "geometry": {"coordinates":[110.95878999999999,37.31411],"type":"Point"}
}