{
  "type": "Feature",
  "properties": {
    "gn:admin1_code":"12.0",
    "gn:asciiname":"Hulitang",
    "gn:country_code":"CN",
    "gn:dem":29,
    "gn:feature_class":"P",
    "gn:feature_code":"PPL",
    "gn:name":"Hulitang",
    "gn:population":0,
    "gn:timezone":"Asia/Shanghai",
    "iso:country":"CN",
    "name:zho_x_preferred":[
        "\u547c\u5229\u5802"
    ],
    "wof:name":"Hulitang",
    "wof:placetype":"locality"
},
  "geometry": {"coordinates":[113.33019,30.1466],"type":"Point"}
}