{
  "type": "Feature",
  "properties": {
    "gn:admin1_code":"1.0",
    "gn:asciiname":"Laowangmiao",
    "gn:country_code":"CN",
    "gn:dem":10,
    "gn:feature_class":"P",
    "gn:feature_code":"PPL",
    "gn:name":"Laowangmiao",
    "gn:population":0,
    "gn:timezone":"Asia/Shanghai",
    "iso:country":"CN",
    "name:zho_x_preferred":[
        "\u8001\u738b\u5e99"
    ],
    "wof:name":"Laowangmiao",
    "wof:placetype":"locality"
},
  "geometry": {"coordinates":[118.23336,31.24975],"type":"Point"}
}