{
  "type": "Feature",
  "properties": {
    "gn:admin1_code":"4.0",
    "gn:asciiname":"Xuanxi",
    "gn:country_code":"CN",
    "gn:dem":9,
    "gn:feature_class":"P",
    "gn:feature_code":"PPL",
    "gn:name":"Xuanxi",
    "gn:population":0,
    "gn:timezone":"Asia/Shanghai",
    "iso:country":"CN",
    "name:zho_x_preferred":[
        "\u5ba3\u897f"
    ],
    "wof:name":"Xuanxi",
    "wof:placetype":"locality"
},
  "geometry": {"coordinates":[119.98502999999999,32.29141],"type":"Point"}
}