{
  "type": "Feature",
  "properties": {
    "gn:admin1_code":"20",
    "gn:asciiname":"Xangd",
    "gn:cc2":"CN",
    "gn:country_code":"CN",
    "gn:dem":992,
    "gn:feature_class":"P",
    "gn:feature_code":"PPL",
    "gn:name":"Xangd",
    "gn:population":0,
    "gn:timezone":"Asia/Shanghai",
    "iso:country":"CN",
    "name:und_x_variant":[
        "Shan-tan",
        "Xangd Zhen",
        "Xangd"
    ],
    "wof:name":"Xangd",
    "wof:placetype":"locality"
},
  "geometry": {"coordinates":[111.08972,40.53556],"type":"Point"}
}