{
  "type": "Feature",
  "properties": {
    "gn:admin1_code":"15.0",
    "gn:asciiname":"Shiwanzi",
    "gn:country_code":"CN",
    "gn:dem":2170,
    "gn:feature_class":"P",
    "gn:feature_code":"PPL",
    "gn:name":"Shiwanzi",
    "gn:population":0,
    "gn:timezone":"Asia/Shanghai",
    "iso:country":"CN",
    "name:zho_x_preferred":[
        "\u77f3\u6e7e\u5b50"
    ],
    "wof:name":"Shiwanzi",
    "wof:placetype":"locality"
},
  "geometry": {"coordinates":[101.462,38.5595],"type":"Point"}
}