{
  "type": "Feature",
  "properties": {
    "gn:admin1_code":"4.0",
    "gn:asciiname":"Kongcun",
    "gn:country_code":"CN",
    "gn:dem":25,
    "gn:feature_class":"P",
    "gn:feature_code":"PPL",
    "gn:name":"Kongcun",
    "gn:population":0,
    "gn:timezone":"Asia/Shanghai",
    "iso:country":"CN",
    "name:zho_x_preferred":[
        "\u5b54\u6751"
    ],
    "wof:name":"Kongcun",
    "wof:placetype":"locality"
},
  "geometry": {"coordinates":[119.23108000000001,31.76694],"type":"Point"}
}