{
  "type": "Feature",
  "properties": {
    "gn:admin1_code":"16",
    "gn:asciiname":"Buyang",
    "gn:country_code":"CN",
    "gn:dem":525,
    "gn:feature_class":"P",
    "gn:feature_code":"PPL",
    "gn:name":"Buyang",
    "gn:population":0,
    "gn:timezone":"Asia/Shanghai",
    "iso:country":"CN",
    "name:zho_x_preferred":[
        "\u5e03\u592e"
    ],
    "wof:name":"Buyang",
    "wof:placetype":"locality"
},
  "geometry": {"coordinates":[109.512,25.8579],"type":"Point"}
}