{
  "type": "Feature",
  "properties": {
    "gn:admin1_code":"3.0",
    "gn:asciiname":"Xitou",
    "gn:country_code":"CN",
    "gn:dem":222,
    "gn:feature_class":"P",
    "gn:feature_code":"PPLA4",
    "gn:name":"Xitou",
    "gn:population":0,
    "gn:timezone":"Asia/Shanghai",
    "iso:country":"CN",
    "name:deu_x_preferred":[
        "Xitou"
    ],
    "name:und_x_variant":[
        "Xitou Xiang"
    ],
    "name:zho_x_preferred":[
        "\u6eaa\u5934"
    ],
    "name:zho_x_variant":[
        "\u6eaa\u5934\u4e61"
    ],
    "wof:name":"Xitou",
    "wof:placetype":"locality"
},
  "geometry": {"coordinates":[118.07942,29.45404000000001],"type":"Point"}
}