{
  "type": "Feature",
  "properties": {
    "gn:admin1_code":"14.0",
    "gn:asciiname":"Zhiba",
    "gn:country_code":"CN",
    "gn:dem":3919,
    "gn:feature_class":"P",
    "gn:feature_code":"PPLF",
    "gn:name":"Zhiba",
    "gn:population":0,
    "gn:timezone":"Asia/Urumqi",
    "iso:country":"CN",
    "name:bod_x_preferred":[
        "Zhiba"
    ],
    "name:zho_x_preferred":[
        "\u652f\u5df4"
    ],
    "wof:name":"Zhiba",
    "wof:placetype":"locality"
},
  "geometry": {"coordinates":[98.74644000000001,30.27715],"type":"Point"}
}