{
  "type": "Feature",
  "properties": {
    "gn:admin1_code":"3",
    "gn:asciiname":"Lintang",
    "gn:country_code":"CN",
    "gn:dem":252,
    "gn:feature_class":"P",
    "gn:feature_code":"PPLA4",
    "gn:name":"Lintang",
    "gn:population":0,
    "gn:timezone":"Asia/Shanghai",
    "iso:country":"CN",
    "name:ceb_x_preferred":[
        "Lintang"
    ],
    "name:ind_x_preferred":[
        "Lintang"
    ],
    "name:msa_x_preferred":[
        "Lintang"
    ],
    "name:swe_x_preferred":[
        "Lintang"
    ],
    "name:und_x_variant":[
        "\u4e34\u5858",
        "Lintang Xiang",
        "\u4e34\u5858\u4e61"
    ],
    "wof:name":"Lintang",
    "wof:placetype":"locality"
},
  "geometry": {"coordinates":[114.79687,24.79095],"type":"Point"}
}