{
  "type": "Feature",
  "properties": {
    "gn:admin1_code":"18.0",
    "gn:asciiname":"Leigongjing",
    "gn:country_code":"CN",
    "gn:dem":499,
    "gn:feature_class":"P",
    "gn:feature_code":"PPL",
    "gn:name":"Leigongjing",
    "gn:population":0,
    "gn:timezone":"Asia/Shanghai",
    "iso:country":"CN",
    "name:zho_x_preferred":[
        "\u96f7\u516c\u4e95"
    ],
    "wof:name":"Leigongjing",
    "wof:placetype":"locality"
},
  "geometry": {"coordinates":[108.94499999999999,27.9917],"type":"Point"}
}