{
  "type": "Feature",
  "properties": {
    "gn:admin1_code":"18",
    "gn:asciiname":"Weima",
    "gn:country_code":"CN",
    "gn:dem":774,
    "gn:feature_class":"P",
    "gn:feature_code":"PPL",
    "gn:name":"Weima",
    "gn:population":0,
    "gn:timezone":"Asia/Shanghai",
    "iso:country":"CN",
    "name:zho_x_preferred":[
        "\u5c3e\u9ebb"
    ],
    "wof:name":"Weima",
    "wof:placetype":"locality"
},
  "geometry": {"coordinates":[105.794,24.7744],"type":"Point"}
}