{
  "type": "Feature",
  "properties": {
    "gn:admin1_code":"30.0",
    "gn:asciiname":"Litou'an",
    "gn:country_code":"CN",
    "gn:dem":319,
    "gn:feature_class":"P",
    "gn:feature_code":"PPL",
    "gn:name":"Litou\u2019an",
    "gn:population":0,
    "gn:timezone":"Asia/Shanghai",
    "iso:country":"CN",
    "name:und_x_variant":[
        "Litou\u2019an"
    ],
    "name:zho_x_preferred":[
        "\u9ece\u5934\u5eb5"
    ],
    "wof:name":"Litou'an",
    "wof:placetype":"locality"
},
  "geometry": {"coordinates":[116.15900999999999,23.80464],"type":"Point"}
}