{
  "type": "Feature",
  "properties": {
    "gn:admin1_code":"14.0",
    "gn:asciiname":"Ze'a",
    "gn:country_code":"CN",
    "gn:dem":3901,
    "gn:feature_class":"P",
    "gn:feature_code":"PPL",
    "gn:name":"Ze\u2019a",
    "gn:population":0,
    "gn:timezone":"Asia/Urumqi",
    "iso:country":"CN",
    "name:und_x_variant":[
        "Ze\u2019a"
    ],
    "name:zho_x_preferred":[
        "\u5219\u554a"
    ],
    "wof:name":"Ze'a",
    "wof:placetype":"locality"
},
  "geometry": {"coordinates":[95.68944999999999,30.77446],"type":"Point"}
}