{
  "type": "Feature",
  "properties": {
    "gn:admin1_code":"29.0",
    "gn:asciiname":"Yongjiu",
    "gn:country_code":"CN",
    "gn:dem":2523,
    "gn:feature_class":"P",
    "gn:feature_code":"PPL",
    "gn:name":"Yongjiu",
    "gn:population":0,
    "gn:timezone":"Asia/Shanghai",
    "iso:country":"CN",
    "name:zho_x_preferred":[
        "\u6c38\u4e45"
    ],
    "wof:name":"Yongjiu",
    "wof:placetype":"locality"
},
  "geometry": {"coordinates":[98.8433,28.2295],"type":"Point"}
}