{
  "type": "Feature",
  "properties": {
    "gn:admin1_code":"2.0",
    "gn:asciiname":"Lingxiaji",
    "gn:country_code":"CN",
    "gn:dem":345,
    "gn:feature_class":"P",
    "gn:feature_code":"PPL",
    "gn:name":"Lingxiaji",
    "gn:population":0,
    "gn:timezone":"Asia/Shanghai",
    "iso:country":"CN",
    "name:zho_x_preferred":[
        "\u5cad\u4e0b\u57fa"
    ],
    "wof:name":"Lingxiaji",
    "wof:placetype":"locality"
},
  "geometry": {"coordinates":[121.03149999999999,28.75742],"type":"Point"}
}