{
  "type": "Feature",
  "properties": {
    "gn:admin1_code":"19.0",
    "gn:asciiname":"Chuangouzi Yidui",
    "gn:country_code":"CN",
    "gn:dem":242,
    "gn:feature_class":"P",
    "gn:feature_code":"PPLF",
    "gn:name":"Chuangouzi Yidui",
    "gn:population":0,
    "gn:timezone":"Asia/Shanghai",
    "iso:country":"CN",
    "name:zho_x_preferred":[
        "\u5ddd\u6c9f\u5b50\u4e00\u961f"
    ],
    "wof:name":"Chuangouzi Yidui",
    "wof:placetype":"locality"
},
  "geometry": {"coordinates":[125.59099999999999,40.8484],"type":"Point"}
}