{
  "type": "Feature",
  "properties": {
    "gn:admin1_code":"21.0",
    "gn:asciiname":"Kangmatou",
    "gn:country_code":"CN",
    "gn:dem":1440,
    "gn:feature_class":"P",
    "gn:feature_code":"PPL",
    "gn:name":"Kangmatou",
    "gn:population":0,
    "gn:timezone":"Asia/Shanghai",
    "iso:country":"CN",
    "name:zho_x_preferred":[
        "\u5eb7\u9ebb\u5934"
    ],
    "wof:name":"Kangmatou",
    "wof:placetype":"locality"
},
  "geometry": {"coordinates":[105.958,37.3052],"type":"Point"}
}