{
  "type": "Feature",
  "properties": {
    "gn:admin1_code":"32.0",
    "gn:asciiname":"Shiziba",
    "gn:country_code":"CN",
    "gn:dem":842,
    "gn:feature_class":"P",
    "gn:feature_code":"PPL",
    "gn:name":"Shiziba",
    "gn:population":0,
    "gn:timezone":"Asia/Shanghai",
    "iso:country":"CN",
    "name:zho_x_preferred":[
        "\u67ff\u5b50\u575d"
    ],
    "wof:name":"Shiziba",
    "wof:placetype":"locality"
},
  "geometry": {"coordinates":[108.19499999999999,32.2341],"type":"Point"}
}