{
  "type": "Feature",
  "properties": {
    "gn:admin1_code":"11.0",
    "gn:asciiname":"Huangmaoping",
    "gn:country_code":"CN",
    "gn:dem":411,
    "gn:feature_class":"P",
    "gn:feature_code":"PPL",
    "gn:name":"Huangmaoping",
    "gn:population":0,
    "gn:timezone":"Asia/Shanghai",
    "iso:country":"CN",
    "name:zho_x_preferred":[
        "\u9ec4\u6bdb\u576a"
    ],
    "wof:name":"Huangmaoping",
    "wof:placetype":"locality"
},
  "geometry": {"coordinates":[110.31292999999999,27.59772],"type":"Point"}
}