{
  "type": "Feature",
  "properties": {
    "gn:admin1_code":"4.0",
    "gn:asciiname":"Weijia Dazhuang",
    "gn:country_code":"CN",
    "gn:dem":17,
    "gn:feature_class":"P",
    "gn:feature_code":"PPL",
    "gn:name":"Weijia Dazhuang",
    "gn:population":0,
    "gn:timezone":"Asia/Shanghai",
    "iso:country":"CN",
    "name:zho_x_preferred":[
        "\u97e6\u5bb6\u5927\u5e84"
    ],
    "wof:name":"Weijia Dazhuang",
    "wof:placetype":"locality"
},
  "geometry": {"coordinates":[119.00315999999999,32.98913],"type":"Point"}
}