{
  "type": "Feature",
  "properties": {
    "gn:admin1_code":"19.0",
    "gn:asciiname":"Xiahenan",
    "gn:country_code":"CN",
    "gn:dem":311,
    "gn:feature_class":"P",
    "gn:feature_code":"PPL",
    "gn:name":"Xiahenan",
    "gn:population":0,
    "gn:timezone":"Asia/Shanghai",
    "iso:country":"CN",
    "name:und_x_variant":[
        "\u4e0b\u6cb3\u5357"
    ],
    "wof:name":"Xiahenan",
    "wof:placetype":"locality"
},
  "geometry": {"coordinates":[124.81559,41.63748],"type":"Point"}
}