{
  "type": "Feature",
  "properties": {
    "gn:admin1_code":"32.0",
    "gn:asciiname":"Putisi",
    "gn:country_code":"CN",
    "gn:dem":393,
    "gn:feature_class":"P",
    "gn:feature_code":"PPL",
    "gn:name":"Putisi",
    "gn:population":0,
    "gn:timezone":"Asia/Shanghai",
    "iso:country":"CN",
    "name:zho_x_preferred":[
        "\u83e9\u63d0\u5bfa"
    ],
    "wof:name":"Putisi",
    "wof:placetype":"locality"
},
  "geometry": {"coordinates":[104.81399999999999,29.6225],"type":"Point"}
}