{
  "type": "Feature",
  "properties": {
    "gn:admin1_code":"33.0",
    "gn:asciiname":"Jiulinggang",
    "gn:country_code":"CN",
    "gn:dem":386,
    "gn:feature_class":"P",
    "gn:feature_code":"PPL",
    "gn:name":"Jiulinggang",
    "gn:population":0,
    "gn:timezone":"Asia/Shanghai",
    "iso:country":"CN",
    "name:zho_x_preferred":[
        "\u4e5d\u5cad\u5188"
    ],
    "wof:name":"Jiulinggang",
    "wof:placetype":"locality"
},
  "geometry": {"coordinates":[105.71756000000001,29.2434],"type":"Point"}
}