{
  "type": "Feature",
  "properties": {
    "gn:admin1_code":"11.0",
    "gn:asciiname":"Longmenquan",
    "gn:country_code":"CN",
    "gn:dem":78,
    "gn:feature_class":"P",
    "gn:feature_code":"PPL",
    "gn:name":"Longmenquan",
    "gn:population":0,
    "gn:timezone":"Asia/Shanghai",
    "iso:country":"CN",
    "name:zho_x_preferred":[
        "\u9f99\u95e8\u6cc9"
    ],
    "wof:name":"Longmenquan",
    "wof:placetype":"locality"
},
  "geometry": {"coordinates":[112.94356000000001,27.05516],"type":"Point"}
}