{
  "type": "Feature",
  "properties": {
    "gn:admin1_code":"7",
    "gn:asciiname":"Shanxi",
    "gn:country_code":"CN",
    "gn:dem":261,
    "gn:feature_class":"P",
    "gn:feature_code":"PPL",
    "gn:name":"Shanxi",
    "gn:population":0,
    "gn:timezone":"Asia/Shanghai",
    "iso:country":"CN",
    "name:und_x_variant":[
        "\u5c71\u6eaa"
    ],
    "wof:name":"Shanxi",
    "wof:placetype":"locality"
},
  "geometry": {"coordinates":[118.61499999999999,27.42944],"type":"Point"}
}