{
  "type": "Feature",
  "properties": {
    "gn:admin1_code":"7",
    "gn:asciiname":"Dong'anxia",
    "gn:country_code":"CN",
    "gn:dem":10,
    "gn:feature_class":"P",
    "gn:feature_code":"PPL",
    "gn:name":"Dong\u2019anxia",
    "gn:population":0,
    "gn:timezone":"Asia/Shanghai",
    "iso:country":"CN",
    "name:und_x_variant":[
        "\u4e1c\u5b89\u4e0b",
        "Dong\u2019anxia"
    ],
    "wof:name":"Dong'anxia",
    "wof:placetype":"locality"
},
  "geometry": {"coordinates":[118.38077,24.61863],"type":"Point"}
}