{
  "type": "Feature",
  "properties": {
    "gn:admin1_code":"30.0",
    "gn:asciiname":"Hengshui",
    "gn:country_code":"CN",
    "gn:dem":556,
    "gn:feature_class":"P",
    "gn:feature_code":"PPL",
    "gn:name":"Hengshui",
    "gn:population":0,
    "gn:timezone":"Asia/Shanghai",
    "iso:country":"CN",
    "name:ara_x_preferred":[
        "\u0647\u0646\u063a\u0634\u0648\u064a"
    ],
    "name:cdo_x_preferred":[
        "H\u00e8ng-c\u016bi"
    ],
    "name:ces_x_preferred":[
        "Cheng-\u0161uej"
    ],
    "name:cym_x_preferred":[
        "Hengshui"
    ],
    "name:dan_x_preferred":[
        "Hengshui"
    ],
    "name:deu_x_preferred":[
        "Hengshui"
    ],
    "name:eus_x_preferred":[
        "Hengshui"
    ],
    "name:fas_x_preferred":[
        "\u0647\u0646\u06af\u0634\u0648\u06cc"
    ],
    "name:fin_x_preferred":[
        "Hengshui"
    ],
    "name:fra_x_preferred":[
        "Hengshui"
    ],
    "name:heb_x_preferred":[
        "\u05d7\u05e0\u05d2\u05e9\u05d5\u05d0\u05d9"
    ],
    "name:ind_x_preferred":[
        "Hengshui"
    ],
    "name:ita_x_preferred":[
        "Hengshui"
    ],
    "name:jpn_x_preferred":[
        "\u8861\u6c34\u5e02"
    ],
    "name:kik_x_preferred":[
        "Hengshui"
    ],
    "name:kor_x_preferred":[
        "\ud5dd\uc218\uc774\uc2dc"
    ],
    "name:mlg_x_preferred":[
        "Hengshui"
    ],
    "name:nld_x_preferred":[
        "Hengshui"
    ],
    "name:nno_x_preferred":[
        "Hengshui"
    ],
    "name:nor_x_preferred":[
        "Hengshui"
    ],
    "name:pam_x_preferred":[
        "Hengshui"
    ],
    "name:pol_x_preferred":[
        "Hengshui"
    ],
    "name:por_x_preferred":[
        "Hengshui"
    ],
    "name:rus_x_preferred":[
        "\u0425\u044d\u043d\u0448\u0443\u0439"
    ],
    "name:spa_x_preferred":[
        "Hengshui"
    ],
    "name:srp_x_preferred":[
        "\u0425\u0435\u043d\u0433\u0448\u0443\u0435\u0458"
    ],
    "name:swe_x_preferred":[
        "Hengshui"
    ],
    "name:tur_x_preferred":[
        "Hengshui"
    ],
    "name:urd_x_preferred":[
        "\u06c1\u06cc\u0646\u06af\u0634\u0648\u0626\u06cc"
    ],
    "name:vie_x_preferred":[
        "H\u00e0nh Th\u1ee7y"
    ],
    "name:war_x_preferred":[
        "Hengshui"
    ],
    "name:wuu_x_preferred":[
        "\u8861\u6c34\u5e02"
    ],
    "name:zho_x_preferred":[
        "Hengshui"
    ],
    "name:zho_x_variant":[
        "\u6a2a\u6c34",
        "\u8861\u6c34\u5e02"
    ],
    "wof:name":"Hengshui",
    "wof:placetype":"locality"
},
  "geometry": {"coordinates":[112.85583,24.87694],"type":"Point"}
}