{
  "type": "Feature",
  "properties": {
    "gn:admin1_code":"32.0",
    "gn:asciiname":"Shawu",
    "gn:country_code":"CN",
    "gn:dem":2723,
    "gn:feature_class":"P",
    "gn:feature_code":"PPL",
    "gn:name":"Shawu",
    "gn:population":0,
    "gn:timezone":"Asia/Shanghai",
    "iso:country":"CN",
    "name:zho_x_preferred":[
        "\u6c99\u52ff"
    ],
    "wof:name":"Shawu",
    "wof:placetype":"locality"
},
  "geometry": {"coordinates":[103.66,33.5817],"type":"Point"}
}