{
  "type": "Feature",
  "properties": {
    "gn:admin1_code":"32.0",
    "gn:asciiname":"Gougoudi",
    "gn:country_code":"CN",
    "gn:dem":1921,
    "gn:feature_class":"P",
    "gn:feature_code":"PPL",
    "gn:name":"Gougoudi",
    "gn:population":0,
    "gn:timezone":"Asia/Shanghai",
    "iso:country":"CN",
    "name:zho_x_preferred":[
        "\u6c9f\u6c9f\u5730"
    ],
    "wof:name":"Gougoudi",
    "wof:placetype":"locality"
},
  "geometry": {"coordinates":[102.96599999999999,28.1068],"type":"Point"}
}