{
  "type": "Feature",
  "properties": {
    "gn:admin1_code":"33.0",
    "gn:asciiname":"Bajiaoshui",
    "gn:country_code":"CN",
    "gn:dem":670,
    "gn:feature_class":"P",
    "gn:feature_code":"PPL",
    "gn:name":"Bajiaoshui",
    "gn:population":0,
    "gn:timezone":"Asia/Shanghai",
    "iso:country":"CN",
    "name:zho_x_preferred":[
        "\u82ad\u8549\u6c34"
    ],
    "wof:name":"Bajiaoshui",
    "wof:placetype":"locality"
},
  "geometry": {"coordinates":[108.94638999999999,28.55527],"type":"Point"}
}