{
  "type": "Feature",
  "properties": {
    "gn:admin1_code":"21.0",
    "gn:asciiname":"Xialuzigou",
    "gn:country_code":"CN",
    "gn:dem":2044,
    "gn:feature_class":"P",
    "gn:feature_code":"PPL",
    "gn:name":"Xialuzigou",
    "gn:population":0,
    "gn:timezone":"Asia/Shanghai",
    "iso:country":"CN",
    "name:zho_x_preferred":[
        "\u4e0b\u82a6\u5b50\u6c9f"
    ],
    "wof:name":"Xialuzigou",
    "wof:placetype":"locality"
},
  "geometry": {"coordinates":[105.649,36.0325],"type":"Point"}
}