{
  "type": "Feature",
  "properties": {
    "gn:admin1_code":"32.0",
    "gn:asciiname":"Gongyi",
    "gn:country_code":"CN",
    "gn:dem":569,
    "gn:feature_class":"P",
    "gn:feature_code":"PPL",
    "gn:name":"Gongyi",
    "gn:population":0,
    "gn:timezone":"Asia/Shanghai",
    "iso:country":"CN",
    "name:ara_x_preferred":[
        "\u063a\u0648\u0646\u063a\u064a\u064a"
    ],
    "name:deu_x_preferred":[
        "Gongyi"
    ],
    "name:eus_x_preferred":[
        "Gongyi"
    ],
    "name:fra_x_preferred":[
        "Gongyi"
    ],
    "name:ita_x_preferred":[
        "Gongyi"
    ],
    "name:jpn_x_preferred":[
        "\u978f\u7fa9\u5e02"
    ],
    "name:kik_x_preferred":[
        "Gongyi"
    ],
    "name:kor_x_preferred":[
        "\uad81\uc774\uc2dc"
    ],
    "name:nor_x_preferred":[
        "Gongyi"
    ],
    "name:pam_x_preferred":[
        "Gongyi"
    ],
    "name:rus_x_preferred":[
        "\u0413\u0443\u043d\u044a\u0438"
    ],
    "name:swe_x_preferred":[
        "Gongyi"
    ],
    "name:ukr_x_preferred":[
        "\u0490\u0443\u043d'\u0457"
    ],
    "name:urd_x_preferred":[
        "\u06af\u0648\u0646\u06af\u06cc\u06cc"
    ],
    "name:vie_x_preferred":[
        "C\u1ee7ng Ngh\u0129a"
    ],
    "name:zho_x_preferred":[
        "\u516c\u8bae"
    ],
    "name:zho_x_variant":[
        "\u5de9\u4e49\u5e02"
    ],
    "wof:name":"Gongyi",
    "wof:placetype":"locality"
},
  "geometry": {"coordinates":[103.61172999999999,30.70962],"type":"Point"}
}