{
  "type": "Feature",
  "properties": {
    "gn:admin1_code":"02",
    "gn:asciiname":"Houyangzeng",
    "gn:cc2":"CN",
    "gn:country_code":"CN",
    "gn:dem":6,
    "gn:feature_class":"P",
    "gn:feature_code":"PPL",
    "gn:name":"Houyangzeng",
    "gn:population":0,
    "gn:timezone":"Asia/Shanghai",
    "iso:country":"CN",
    "name:und_x_variant":[
        "Hou-yang-tseng",
        "Houyangzeng"
    ],
    "wof:name":"Houyangzeng",
    "wof:placetype":"locality"
},
  "geometry": {"coordinates":[120.52916999999999,27.52944],"type":"Point"}
}