{
  "type": "Feature",
  "properties": {
    "gn:admin1_code":"5.0",
    "gn:asciiname":"Zhaowanlu",
    "gn:country_code":"CN",
    "gn:dem":235,
    "gn:feature_class":"P",
    "gn:feature_code":"PPL",
    "gn:name":"Zhaowanlu",
    "gn:population":0,
    "gn:timezone":"Asia/Shanghai",
    "iso:country":"CN",
    "name:zho_x_preferred":[
        "\u8d75\u4e07\u7984"
    ],
    "wof:name":"Zhaowanlu",
    "wof:placetype":"locality"
},
  "geometry": {"coordinates":[125.03231,44.7377],"type":"Point"}
}