{
  "type": "Feature",
  "properties": {
    "gn:admin1_code":"9.0",
    "gn:asciiname":"Tongkuangchang",
    "gn:country_code":"CN",
    "gn:dem":122,
    "gn:feature_class":"P",
    "gn:feature_code":"PPL",
    "gn:name":"Tongkuangchang",
    "gn:population":0,
    "gn:timezone":"Asia/Shanghai",
    "iso:country":"CN",
    "name:zho_x_preferred":[
        "\u94dc\u77ff\u5382"
    ],
    "wof:name":"Tongkuangchang",
    "wof:placetype":"locality"
},
  "geometry": {"coordinates":[114.7132,31.73874],"type":"Point"}
}