{
  "type": "Feature",
  "properties": {
    "gn:admin1_code":"32.0",
    "gn:asciiname":"Shizi",
    "gn:country_code":"CN",
    "gn:dem":591,
    "gn:feature_class":"P",
    "gn:feature_code":"PPL",
    "gn:name":"Shizi",
    "gn:population":0,
    "gn:timezone":"Asia/Shanghai",
    "iso:country":"CN",
    "name:ceb_x_preferred":[
        "Shizi"
    ],
    "name:swe_x_preferred":[
        "Shizi"
    ],
    "name:zho_x_preferred":[
        "\u72ee\u5b50"
    ],
    "wof:name":"Shizi",
    "wof:placetype":"locality"
},
  "geometry": {"coordinates":[105.502,31.8012],"type":"Point"}
}