{
  "type": "Feature",
  "properties": {
    "gn:admin1_code":"2.0",
    "gn:asciiname":"Zhangshanhou",
    "gn:country_code":"CN",
    "gn:dem":279,
    "gn:feature_class":"P",
    "gn:feature_code":"PPL",
    "gn:name":"Zhangshanhou",
    "gn:population":0,
    "gn:timezone":"Asia/Shanghai",
    "iso:country":"CN",
    "name:zho_x_preferred":[
        "\u5f20\u5c71\u540e"
    ],
    "wof:name":"Zhangshanhou",
    "wof:placetype":"locality"
},
  "geometry": {"coordinates":[119.92762999999999,28.57709],"type":"Point"}
}