{
  "type": "Feature",
  "properties": {
    "gn:admin1_code":"20.0",
    "gn:asciiname":"Sandaogoumen",
    "gn:country_code":"CN",
    "gn:dem":352,
    "gn:feature_class":"P",
    "gn:feature_code":"PPL",
    "gn:name":"Sandaogoumen",
    "gn:population":0,
    "gn:timezone":"Asia/Shanghai",
    "iso:country":"CN",
    "name:zho_x_preferred":[
        "\u4e09\u9053\u6c9f\u95e8"
    ],
    "wof:name":"Sandaogoumen",
    "wof:placetype":"locality"
},
  "geometry": {"coordinates":[122.43810999999999,47.55889000000001],"type":"Point"}
}