{
  "type": "Feature",
  "properties": {
    "gn:admin1_code":"16.0",
    "gn:asciiname":"Huangshantang",
    "gn:country_code":"CN",
    "gn:dem":68,
    "gn:feature_class":"P",
    "gn:feature_code":"PPL",
    "gn:name":"Huangshantang",
    "gn:population":0,
    "gn:timezone":"Asia/Shanghai",
    "iso:country":"CN",
    "name:zho_x_preferred":[
        "\u9ec4\u9cdd\u5858"
    ],
    "wof:name":"Huangshantang",
    "wof:placetype":"locality"
},
  "geometry": {"coordinates":[109.48999999999999,22.0121],"type":"Point"}
}