{
  "type": "Feature",
  "properties": {
    "gn:admin1_code":"7.0",
    "gn:asciiname":"Longshan",
    "gn:country_code":"CN",
    "gn:dem":61,
    "gn:feature_class":"P",
    "gn:feature_code":"PPL",
    "gn:name":"Longshan",
    "gn:population":0,
    "gn:timezone":"Asia/Shanghai",
    "iso:country":"CN",
    "name:ceb_x_preferred":[
        "Longshan"
    ],
    "name:deu_x_preferred":[
        "Longshan"
    ],
    "name:fra_x_preferred":[
        "Longshan"
    ],
    "name:nor_x_preferred":[
        "Longshan"
    ],
    "name:pol_x_preferred":[
        "Longshan"
    ],
    "name:rus_x_preferred":[
        "\u041b\u0443\u043d\u0448\u0430\u043d\u044c"
    ],
    "name:swe_x_preferred":[
        "Longshan"
    ],
    "name:zho_x_preferred":[
        "\u9f99\u5c71"
    ],
    "wof:name":"Longshan",
    "wof:placetype":"locality"
},
  "geometry": {"coordinates":[118.2289,24.9656],"type":"Point"}
}