{
  "type": "Feature",
  "properties": {
    "gn:admin1_code":"32.0",
    "gn:asciiname":"Yangquangou",
    "gn:country_code":"CN",
    "gn:dem":1452,
    "gn:feature_class":"P",
    "gn:feature_code":"PPL",
    "gn:name":"Yangquangou",
    "gn:population":0,
    "gn:timezone":"Asia/Shanghai",
    "iso:country":"CN",
    "name:zho_x_preferred":[
        "\u7f8a\u5708\u6c9f"
    ],
    "wof:name":"Yangquangou",
    "wof:placetype":"locality"
},
  "geometry": {"coordinates":[103.08799999999999,27.4438],"type":"Point"}
}