{
  "type": "Feature",
  "properties": {
    "gn:admin1_code":"4.0",
    "gn:asciiname":"Jiaoyong",
    "gn:country_code":"CN",
    "gn:dem":6,
    "gn:feature_class":"P",
    "gn:feature_code":"PPL",
    "gn:name":"Jiaoyong",
    "gn:population":0,
    "gn:timezone":"Asia/Shanghai",
    "iso:country":"CN",
    "name:zho_x_preferred":[
        "\u7126\u52c7"
    ],
    "wof:name":"Jiaoyong",
    "wof:placetype":"locality"
},
  "geometry": {"coordinates":[120.11624999999999,32.94589000000001],"type":"Point"}
}