{
  "type": "Feature",
  "properties": {
    "gn:admin1_code":"33.0",
    "gn:asciiname":"Yuanmengou",
    "gn:country_code":"CN",
    "gn:dem":1242,
    "gn:feature_class":"P",
    "gn:feature_code":"PPL",
    "gn:name":"Yuanmengou",
    "gn:population":0,
    "gn:timezone":"Asia/Shanghai",
    "iso:country":"CN",
    "name:zho_x_preferred":[
        "\u5706\u95e8\u6c9f"
    ],
    "wof:name":"Yuanmengou",
    "wof:placetype":"locality"
},
  "geometry": {"coordinates":[110.07937,31.24313],"type":"Point"}
}