{
  "type": "Feature",
  "properties": {
    "gn:admin1_code":"19.0",
    "gn:asciiname":"Xidaihaiyingzi",
    "gn:country_code":"CN",
    "gn:dem":326,
    "gn:feature_class":"P",
    "gn:feature_code":"PPL",
    "gn:name":"Xidaihaiyingzi",
    "gn:population":0,
    "gn:timezone":"Asia/Shanghai",
    "iso:country":"CN",
    "name:zho_x_preferred":[
        "\u897f\u4ee3\u6d77\u8425\u5b50"
    ],
    "wof:name":"Xidaihaiyingzi",
    "wof:placetype":"locality"
},
  "geometry": {"coordinates":[121.53557000000001,42.41517],"type":"Point"}
}