{
  "type": "Feature",
  "properties": {
    "gn:admin1_code":"29.0",
    "gn:asciiname":"Chala",
    "gn:country_code":"CN",
    "gn:dem":1782,
    "gn:feature_class":"P",
    "gn:feature_code":"PPL",
    "gn:name":"Chala",
    "gn:population":0,
    "gn:timezone":"Asia/Shanghai",
    "iso:country":"CN",
    "name:aym_x_preferred":[
        "Ch'alla"
    ],
    "name:ces_x_preferred":[
        "Chala"
    ],
    "name:deu_x_preferred":[
        "Chala"
    ],
    "name:lit_x_preferred":[
        "\u010cala"
    ],
    "name:que_x_preferred":[
        "Chala"
    ],
    "name:ukr_x_preferred":[
        "\u0427\u0430\u043b\u0430"
    ],
    "name:zho_x_preferred":[
        "\u67e5\u814a"
    ],
    "wof:name":"Chala",
    "wof:placetype":"locality"
},
  "geometry": {"coordinates":[102.877,23.3785],"type":"Point"}
}