{
  "type": "Feature",
  "properties": {
    "gn:admin1_code":"4.0",
    "gn:asciiname":"Zhaodian",
    "gn:country_code":"CN",
    "gn:dem":14,
    "gn:feature_class":"P",
    "gn:feature_code":"PPL",
    "gn:name":"Zhaodian",
    "gn:population":0,
    "gn:timezone":"Asia/Shanghai",
    "iso:country":"CN",
    "name:zho_x_preferred":[
        "\u62db\u7538"
    ],
    "wof:name":"Zhaodian",
    "wof:placetype":"locality"
},
  "geometry": {"coordinates":[119.31895,32.15387],"type":"Point"}
}