{
  "type": "Feature",
  "properties": {
    "gn:admin1_code":"30.0",
    "gn:asciiname":"Yamashui",
    "gn:country_code":"CN",
    "gn:dem":670,
    "gn:feature_class":"P",
    "gn:feature_code":"PPL",
    "gn:name":"Yamashui",
    "gn:population":0,
    "gn:timezone":"Asia/Shanghai",
    "iso:country":"CN",
    "name:zho_x_preferred":[
        "Yamashui"
    ],
    "name:zho_x_variant":[
        "\u9e2d\u9ebb\u6c34"
    ],
    "wof:name":"Yamashui",
    "wof:placetype":"locality"
},
  "geometry": {"coordinates":[112.17278,24.8975],"type":"Point"}
}