{
  "type": "Feature",
  "properties": {
    "gn:admin1_code":"24",
    "gn:asciiname":"Dahui",
    "gn:cc2":"CN",
    "gn:country_code":"CN",
    "gn:dem":1661,
    "gn:feature_class":"P",
    "gn:feature_code":"PPL",
    "gn:name":"Dahui",
    "gn:population":0,
    "gn:timezone":"Asia/Shanghai",
    "iso:country":"CN",
    "name:und_x_variant":[
        "Ta-hui",
        "Ta-hui-ts\u2019un",
        "Dahui"
    ],
    "wof:name":"Dahui",
    "wof:placetype":"locality"
},
  "geometry": {"coordinates":[112.24944000000001,38.45028],"type":"Point"}
}