{
  "type": "Feature",
  "properties": {
    "gn:admin1_code":"32.0",
    "gn:asciiname":"Changkoulin",
    "gn:country_code":"CN",
    "gn:dem":511,
    "gn:feature_class":"P",
    "gn:feature_code":"PPL",
    "gn:name":"Changkoulin",
    "gn:population":0,
    "gn:timezone":"Asia/Shanghai",
    "iso:country":"CN",
    "name:zho_x_preferred":[
        "\u573a\u53e3\u6797"
    ],
    "wof:name":"Changkoulin",
    "wof:placetype":"locality"
},
  "geometry": {"coordinates":[104.10534,30.85593],"type":"Point"}
}