{
  "type": "Feature",
  "properties": {
    "gn:admin1_code":"11.0",
    "gn:asciiname":"Fenghuogang",
    "gn:country_code":"CN",
    "gn:dem":91,
    "gn:feature_class":"P",
    "gn:feature_code":"PPL",
    "gn:name":"Fenghuogang",
    "gn:population":0,
    "gn:timezone":"Asia/Shanghai",
    "iso:country":"CN",
    "name:zho_x_preferred":[
        "Fenghuogang"
    ],
    "name:zho_x_variant":[
        "\u5cf0\u706b\u5c97"
    ],
    "wof:name":"Fenghuogang",
    "wof:placetype":"locality"
},
  "geometry": {"coordinates":[111.39337,29.26765],"type":"Point"}
}