{
  "type": "Feature",
  "properties": {
    "gn:admin1_code":"30",
    "gn:asciiname":"Duanbenju",
    "gn:country_code":"CN",
    "gn:dem":118,
    "gn:feature_class":"P",
    "gn:feature_code":"PPL",
    "gn:name":"Duanbenju",
    "gn:population":0,
    "gn:timezone":"Asia/Shanghai",
    "iso:country":"CN",
    "name:zho_x_preferred":[
        "\u7aef\u672c\u5c45"
    ],
    "wof:name":"Duanbenju",
    "wof:placetype":"locality"
},
  "geometry": {"coordinates":[116.04348,24.0864],"type":"Point"}
}