{
  "type": "Feature",
  "properties": {
    "gn:admin1_code":"3.0",
    "gn:asciiname":"Yanshan",
    "gn:country_code":"CN",
    "gn:dem":160,
    "gn:feature_class":"P",
    "gn:feature_code":"PPL",
    "gn:name":"Yanshan",
    "gn:population":0,
    "gn:timezone":"Asia/Shanghai",
    "iso:country":"CN",
    "name:ceb_x_preferred":[
        "Yanshan"
    ],
    "name:deu_x_preferred":[
        "Yanshan"
    ],
    "name:fra_x_preferred":[
        "Yanshan"
    ],
    "name:nor_x_preferred":[
        "Yanshan"
    ],
    "name:rus_x_preferred":[
        "\u042f\u043d\u044c\u0448\u0430\u043d\u044c"
    ],
    "name:swe_x_preferred":[
        "Yanshan"
    ],
    "name:und_x_variant":[
        "\u71d5\u5c71"
    ],
    "wof:name":"Yanshan",
    "wof:placetype":"locality"
},
  "geometry": {"coordinates":[114.90192999999999,29.24449000000001],"type":"Point"}
}