{
  "type": "Feature",
  "properties": {
    "gn:admin1_code":"29",
    "gn:asciiname":"Linchang",
    "gn:country_code":"CN",
    "gn:dem":2004,
    "gn:feature_class":"P",
    "gn:feature_code":"PPL",
    "gn:name":"Linchang",
    "gn:population":0,
    "gn:timezone":"Asia/Shanghai",
    "iso:country":"CN",
    "name:zho_x_preferred":[
        "\u6797\u573a"
    ],
    "wof:name":"Linchang",
    "wof:placetype":"locality"
},
  "geometry": {"coordinates":[103.062,24.5181],"type":"Point"}
}