{
  "type": "Feature",
  "properties": {
    "gn:admin1_code":"25.0",
    "gn:asciiname":"Dongdongmencun",
    "gn:country_code":"CN",
    "gn:dem":44,
    "gn:feature_class":"P",
    "gn:feature_code":"PPL",
    "gn:name":"Dongdongmencun",
    "gn:population":0,
    "gn:timezone":"Asia/Shanghai",
    "iso:country":"CN",
    "name:zho_x_preferred":[
        "\u4e1c\u6d1e\u95e8\u6751"
    ],
    "wof:name":"Dongdongmencun",
    "wof:placetype":"locality"
},
  "geometry": {"coordinates":[120.10878,36.00455],"type":"Point"}
}