{
  "type": "Feature",
  "properties": {
    "gn:admin1_code":"30",
    "gn:asciiname":"Shidong",
    "gn:country_code":"CN",
    "gn:dem":146,
    "gn:feature_class":"P",
    "gn:feature_code":"PPLA4",
    "gn:name":"Shidong",
    "gn:population":0,
    "gn:timezone":"Asia/Shanghai",
    "iso:country":"CN",
    "name:und_x_variant":[
        "Shih-tung",
        "Shidong",
        "Shidong Zhen",
        "\u8bd7\u6d1e\u9547"
    ],
    "name:zho_x_preferred":[
        "\u8bd7\u6d1e"
    ],
    "name:zho_x_variant":[
        "\u8bd7\u6d1e\u9547"
    ],
    "wof:name":"Shidong",
    "wof:placetype":"locality"
},
  "geometry": {"coordinates":[112.06722000000001,23.62056],"type":"Point"}
}