{
  "type": "Feature",
  "properties": {
    "gn:admin1_code":"16.0",
    "gn:asciiname":"Miaotun",
    "gn:country_code":"CN",
    "gn:dem":225,
    "gn:feature_class":"P",
    "gn:feature_code":"PPL",
    "gn:name":"Miaotun",
    "gn:population":0,
    "gn:timezone":"Asia/Shanghai",
    "iso:country":"CN",
    "name:zho_x_preferred":[
        "\u82d7\u5c6f"
    ],
    "wof:name":"Miaotun",
    "wof:placetype":"locality"
},
  "geometry": {"coordinates":[107.242,24.1712],"type":"Point"}
}