{
  "type": "Feature",
  "properties": {
    "gn:admin1_code":"8.0",
    "gn:asciiname":"Huangjia Wobu",
    "gn:country_code":"CN",
    "gn:dem":146,
    "gn:feature_class":"P",
    "gn:feature_code":"PPL",
    "gn:name":"Huangjia Wobu",
    "gn:population":0,
    "gn:timezone":"Asia/Shanghai",
    "iso:country":"CN",
    "name:zho_x_preferred":[
        "\u9ec4\u5bb6\u7a9d\u5821"
    ],
    "wof:name":"Huangjia Wobu",
    "wof:placetype":"locality"
},
  "geometry": {"coordinates":[126.8828,46.7404],"type":"Point"}
}