{
  "type": "Feature",
  "properties": {
    "gn:admin1_code":"7.0",
    "gn:asciiname":"Waike",
    "gn:country_code":"CN",
    "gn:dem":198,
    "gn:feature_class":"P",
    "gn:feature_code":"PPL",
    "gn:name":"Waike",
    "gn:population":0,
    "gn:timezone":"Asia/Shanghai",
    "iso:country":"CN",
    "name:zho_x_preferred":[
        "\u5916\u7aa0"
    ],
    "wof:name":"Waike",
    "wof:placetype":"locality"
},
  "geometry": {"coordinates":[118.75781000000001,27.22558],"type":"Point"}
}