{
  "type": "Feature",
  "properties": {
    "gn:admin1_code":"12.0",
    "gn:asciiname":"Liujia Louzi",
    "gn:country_code":"CN",
    "gn:dem":95,
    "gn:feature_class":"P",
    "gn:feature_code":"PPL",
    "gn:name":"Liujia Louzi",
    "gn:population":0,
    "gn:timezone":"Asia/Shanghai",
    "iso:country":"CN",
    "name:zho_x_preferred":[
        "\u5218\u5bb6\u697c\u5b50"
    ],
    "wof:name":"Liujia Louzi",
    "wof:placetype":"locality"
},
  "geometry": {"coordinates":[113.28128,31.59489],"type":"Point"}
}