{
  "type": "Feature",
  "properties": {
    "gn:admin1_code":"1.0",
    "gn:asciiname":"Miaoqianxincun",
    "gn:country_code":"CN",
    "gn:dem":22,
    "gn:feature_class":"P",
    "gn:feature_code":"PPL",
    "gn:name":"Miaoqianxincun",
    "gn:population":0,
    "gn:timezone":"Asia/Shanghai",
    "iso:country":"CN",
    "name:zho_x_preferred":[
        "\u5e99\u524d\u65b0\u6751"
    ],
    "wof:name":"Miaoqianxincun",
    "wof:placetype":"locality"
},
  "geometry": {"coordinates":[117.21271000000002,32.81189000000001],"type":"Point"}
}