{
  "type": "Feature",
  "properties": {
    "gn:admin1_code":"29.0",
    "gn:asciiname":"Xiaochahe",
    "gn:country_code":"CN",
    "gn:dem":1510,
    "gn:feature_class":"P",
    "gn:feature_code":"PPL",
    "gn:name":"Xiaochahe",
    "gn:population":0,
    "gn:timezone":"Asia/Shanghai",
    "iso:country":"CN",
    "name:zho_x_preferred":[
        "\u5c0f\u5c94\u6cb3"
    ],
    "wof:name":"Xiaochahe",
    "wof:placetype":"locality"
},
  "geometry": {"coordinates":[104.39400000000001,26.6314],"type":"Point"}
}