{
  "type": "Feature",
  "properties": {
    "gn:admin1_code":"4.0",
    "gn:asciiname":"Sanshibalian",
    "gn:country_code":"CN",
    "gn:dem":2,
    "gn:feature_class":"P",
    "gn:feature_code":"PPL",
    "gn:name":"Sanshibalian",
    "gn:population":0,
    "gn:timezone":"Asia/Shanghai",
    "iso:country":"CN",
    "name:zho_x_preferred":[
        "Sanshibalian"
    ],
    "name:zho_x_variant":[
        "\u4e09\u5341\u516b\u8fde"
    ],
    "wof:name":"Sanshibalian",
    "wof:placetype":"locality"
},
  "geometry": {"coordinates":[119.89492,34.30393],"type":"Point"}
}