{
  "type": "Feature",
  "properties": {
    "gn:admin1_code":"24.0",
    "gn:asciiname":"Baibeibucun",
    "gn:country_code":"CN",
    "gn:dem":1386,
    "gn:feature_class":"P",
    "gn:feature_code":"PPL",
    "gn:name":"Baibeibucun",
    "gn:population":0,
    "gn:timezone":"Asia/Shanghai",
    "iso:country":"CN",
    "name:zho_x_preferred":[
        "\u767d\u5317\u5821\u6751"
    ],
    "wof:name":"Baibeibucun",
    "wof:placetype":"locality"
},
  "geometry": {"coordinates":[114.35630999999999,39.61844],"type":"Point"}
}