{
  "type": "Feature",
  "properties": {
    "gn:admin1_code":"32.0",
    "gn:asciiname":"Zhelou",
    "gn:country_code":"CN",
    "gn:dem":4024,
    "gn:feature_class":"P",
    "gn:feature_code":"PPL",
    "gn:name":"Zhelou",
    "gn:population":0,
    "gn:timezone":"Asia/Shanghai",
    "iso:country":"CN",
    "name:zho_x_preferred":[
        "\u8fd9\u5a04"
    ],
    "wof:name":"Zhelou",
    "wof:placetype":"locality"
},
  "geometry": {"coordinates":[100.46907,31.11933],"type":"Point"}
}