{
  "type": "Feature",
  "properties": {
    "gn:admin1_code":"30.0",
    "gn:asciiname":"Qiling",
    "gn:country_code":"CN",
    "gn:dem":14,
    "gn:feature_class":"P",
    "gn:feature_code":"PPL",
    "gn:name":"Qiling",
    "gn:population":0,
    "gn:timezone":"Asia/Shanghai",
    "iso:country":"CN",
    "name:zho_x_preferred":[
        "\u4f01\u5dba"
    ],
    "name:zho_x_variant":[
        "\u5c90\u5cad\u9547"
    ],
    "wof:name":"Qiling",
    "wof:placetype":"locality"
},
  "geometry": {"coordinates":[112.62573999999999,22.90339],"type":"Point"}
}