{
  "type": "Feature",
  "properties": {
    "gn:admin1_code":"11",
    "gn:asciiname":"Kongjiawan",
    "gn:country_code":"CN",
    "gn:dem":78,
    "gn:feature_class":"P",
    "gn:feature_code":"PPL",
    "gn:name":"Kongjiawan",
    "gn:population":0,
    "gn:timezone":"Asia/Shanghai",
    "iso:country":"CN",
    "name:zho_x_preferred":[
        "\u5b54\u5bb6\u6e7e"
    ],
    "wof:name":"Kongjiawan",
    "wof:placetype":"locality"
},
  "geometry": {"coordinates":[112.41951,27.64203],"type":"Point"}
}