{
  "type": "Feature",
  "properties": {
    "gn:admin1_code":"9",
    "gn:asciiname":"Liluyuan",
    "gn:country_code":"CN",
    "gn:dem":48,
    "gn:feature_class":"P",
    "gn:feature_code":"PPL",
    "gn:name":"Liluyuan",
    "gn:population":0,
    "gn:timezone":"Asia/Shanghai",
    "iso:country":"CN",
    "name:zho_x_preferred":[
        "\u674e\u9c81\u5143"
    ],
    "wof:name":"Liluyuan",
    "wof:placetype":"locality"
},
  "geometry": {"coordinates":[115.60271000000002,35.82518],"type":"Point"}
}