{
  "type": "Feature",
  "properties": {
    "gn:admin1_code":"18",
    "gn:asciiname":"Qingganglin",
    "gn:country_code":"CN",
    "gn:dem":2033,
    "gn:feature_class":"P",
    "gn:feature_code":"PPL",
    "gn:name":"Qingganglin",
    "gn:population":0,
    "gn:timezone":"Asia/Shanghai",
    "iso:country":"CN",
    "name:zho_x_preferred":[
        "\u9752\u5188\u6797"
    ],
    "wof:name":"Qingganglin",
    "wof:placetype":"locality"
},
  "geometry": {"coordinates":[104.29900000000001,27.2387],"type":"Point"}
}