{
  "type": "Feature",
  "properties": {
    "gn:admin1_code":"10",
    "gn:asciiname":"Shangboluotai",
    "gn:country_code":"CN",
    "gn:dem":273,
    "gn:feature_class":"P",
    "gn:feature_code":"PPL",
    "gn:name":"Shangboluotai",
    "gn:population":0,
    "gn:timezone":"Asia/Shanghai",
    "iso:country":"CN",
    "name:zho_x_preferred":[
        "\u4e0a\u6872\u7f57\u53f0"
    ],
    "wof:name":"Shangboluotai",
    "wof:placetype":"locality"
},
  "geometry": {"coordinates":[118.37520000000001,40.48317],"type":"Point"}
}