{
  "type": "Feature",
  "properties": {
    "gn:admin1_code":"19.0",
    "gn:asciiname":"Xilamahecun",
    "gn:country_code":"CN",
    "gn:dem":62,
    "gn:feature_class":"P",
    "gn:feature_code":"PPL",
    "gn:name":"Xilamahecun",
    "gn:population":0,
    "gn:timezone":"Asia/Shanghai",
    "iso:country":"CN",
    "name:zho_x_preferred":[
        "\u897f\u62c9\u9a6c\u6cb3\u6751"
    ],
    "wof:name":"Xilamahecun",
    "wof:placetype":"locality"
},
  "geometry": {"coordinates":[123.422,42.2386],"type":"Point"}
}