{
  "type": "Feature",
  "properties": {
    "gn:admin1_code":"19",
    "gn:asciiname":"Hunjiang",
    "gn:cc2":"CN",
    "gn:country_code":"CN",
    "gn:dem":133,
    "gn:feature_class":"P",
    "gn:feature_code":"PPL",
    "gn:name":"Hunjiang",
    "gn:population":0,
    "gn:timezone":"Asia/Shanghai",
    "iso:country":"CN",
    "name:und_x_variant":[
        "Hunjiangkou",
        "Hun-chiang-k\u2019ou",
        "Hunjiang"
    ],
    "wof:name":"Hunjiang",
    "wof:placetype":"locality"
},
  "geometry": {"coordinates":[125.68194,40.86889],"type":"Point"}
}