{
  "type": "Feature",
  "properties": {
    "gn:admin1_code":"2.0",
    "gn:asciiname":"Tamentou",
    "gn:country_code":"CN",
    "gn:dem":6,
    "gn:feature_class":"P",
    "gn:feature_code":"PPL",
    "gn:name":"Tamentou",
    "gn:population":0,
    "gn:timezone":"Asia/Shanghai",
    "iso:country":"CN",
    "name:und_x_variant":[
        "\u5854\u95e8\u5934"
    ],
    "wof:name":"Tamentou",
    "wof:placetype":"locality"
},
  "geometry": {"coordinates":[120.62560000000001,30.82077],"type":"Point"}
}