{
  "type": "Feature",
  "properties": {
    "gn:admin1_code":"11.0",
    "gn:asciiname":"Yangliutan",
    "gn:country_code":"CN",
    "gn:dem":223,
    "gn:feature_class":"P",
    "gn:feature_code":"PPL",
    "gn:name":"Yangliutan",
    "gn:population":0,
    "gn:timezone":"Asia/Shanghai",
    "iso:country":"CN",
    "name:zho_x_preferred":[
        "\u6768\u67f3\u6ee9"
    ],
    "wof:name":"Yangliutan",
    "wof:placetype":"locality"
},
  "geometry": {"coordinates":[113.84744999999999,26.62671],"type":"Point"}
}