{
  "type": "Feature",
  "properties": {
    "gn:admin1_code":"31.0",
    "gn:asciiname":"Zhachu",
    "gn:country_code":"CN",
    "gn:dem":281,
    "gn:feature_class":"P",
    "gn:feature_code":"PPL",
    "gn:name":"Zhachu",
    "gn:population":0,
    "gn:timezone":"Asia/Shanghai",
    "iso:country":"CN",
    "name:und_x_variant":[
        "\u624e\u521d"
    ],
    "wof:name":"Zhachu",
    "wof:placetype":"locality"
},
  "geometry": {"coordinates":[109.42314,18.49956],"type":"Point"}
}