{
  "type": "Feature",
  "properties": {
    "gn:admin1_code":"29.0",
    "gn:asciiname":"Xiadaping",
    "gn:country_code":"CN",
    "gn:dem":1714,
    "gn:feature_class":"P",
    "gn:feature_code":"PPL",
    "gn:name":"Xiadaping",
    "gn:population":0,
    "gn:timezone":"Asia/Shanghai",
    "iso:country":"CN",
    "name:zho_x_preferred":[
        "\u4e0b\u5927\u576a"
    ],
    "wof:name":"Xiadaping",
    "wof:placetype":"locality"
},
  "geometry": {"coordinates":[103.072,26.3217],"type":"Point"}
}