{
  "type": "Feature",
  "properties": {
    "gn:admin1_code":"4.0",
    "gn:asciiname":"Suntangcun",
    "gn:country_code":"CN",
    "gn:dem":1,
    "gn:feature_class":"P",
    "gn:feature_code":"PPL",
    "gn:name":"Suntangcun",
    "gn:population":0,
    "gn:timezone":"Asia/Shanghai",
    "iso:country":"CN",
    "name:zho_x_preferred":[
        "\u5b59\u5510\u6751"
    ],
    "wof:name":"Suntangcun",
    "wof:placetype":"locality"
},
  "geometry": {"coordinates":[119.89331,32.98291],"type":"Point"}
}