{
  "type": "Feature",
  "properties": {
    "gn:admin1_code":"1.0",
    "gn:asciiname":"Datongcun",
    "gn:country_code":"CN",
    "gn:dem":56,
    "gn:feature_class":"P",
    "gn:feature_code":"PPL",
    "gn:name":"Datongcun",
    "gn:population":0,
    "gn:timezone":"Asia/Shanghai",
    "iso:country":"CN",
    "name:zho_x_preferred":[
        "\u5927\u7ae5\u6751"
    ],
    "wof:name":"Datongcun",
    "wof:placetype":"locality"
},
  "geometry": {"coordinates":[117.01479999999999,32.1507],"type":"Point"}
}