{
  "type": "Feature",
  "properties": {
    "gn:admin1_code":"29.0",
    "gn:asciiname":"Liutiaoban",
    "gn:country_code":"CN",
    "gn:dem":131,
    "gn:feature_class":"P",
    "gn:feature_code":"PPL",
    "gn:name":"Liutiaoban",
    "gn:population":0,
    "gn:timezone":"Asia/Shanghai",
    "iso:country":"CN",
    "name:zho_x_preferred":[
        "\u516d\u6761\u534a"
    ],
    "wof:name":"Liutiaoban",
    "wof:placetype":"locality"
},
  "geometry": {"coordinates":[104.006,22.5289],"type":"Point"}
}