{
  "type": "Feature",
  "properties": {
    "gn:admin1_code":"15",
    "gn:asciiname":"Taoyang",
    "gn:country_code":"CN",
    "gn:dem":1870,
    "gn:feature_class":"P",
    "gn:feature_code":"PPLA3",
    "gn:name":"Taoyang",
    "gn:population":0,
    "gn:timezone":"Asia/Shanghai",
    "iso:country":"CN",
    "name:und_x_variant":[
        "Didao",
        "Ti-tao",
        "Lin-t\u2019ao",
        "Taoyang",
        "Lintao Xian"
    ],
    "name:zho_x_preferred":[
        "\u6d2e\u9633"
    ],
    "name:zho_x_variant":[
        "\u4e34\u6d2e\u53bf"
    ],
    "wof:name":"Taoyang",
    "wof:placetype":"locality"
},
  "geometry": {"coordinates":[103.85325,35.40135],"type":"Point"}
}