{
  "type": "Feature",
  "properties": {
    "gn:admin1_code":"29.0",
    "gn:asciiname":"Bainidi",
    "gn:country_code":"CN",
    "gn:dem":2292,
    "gn:feature_class":"P",
    "gn:feature_code":"PPL",
    "gn:name":"Bainidi",
    "gn:population":0,
    "gn:timezone":"Asia/Shanghai",
    "iso:country":"CN",
    "name:zho_x_preferred":[
        "\u767d\u6ce5\u5730"
    ],
    "wof:name":"Bainidi",
    "wof:placetype":"locality"
},
  "geometry": {"coordinates":[103.393,26.1903],"type":"Point"}
}