{
  "type": "Feature",
  "properties": {
    "gn:admin1_code":"30.0",
    "gn:asciiname":"Oukeng",
    "gn:country_code":"CN",
    "gn:dem":193,
    "gn:feature_class":"P",
    "gn:feature_code":"PPL",
    "gn:name":"Oukeng",
    "gn:population":0,
    "gn:timezone":"Asia/Shanghai",
    "iso:country":"CN",
    "name:zho_x_preferred":[
        "Oukeng"
    ],
    "name:zho_x_variant":[
        "\u6b27\u5751"
    ],
    "wof:name":"Oukeng",
    "wof:placetype":"locality"
},
  "geometry": {"coordinates":[115.27583,24.45722],"type":"Point"}
}