{
  "type": "Feature",
  "properties": {
    "gn:admin1_code":"29.0",
    "gn:asciiname":"Xiawawei",
    "gn:country_code":"CN",
    "gn:dem":1436,
    "gn:feature_class":"P",
    "gn:feature_code":"PPL",
    "gn:name":"Xiawawei",
    "gn:population":0,
    "gn:timezone":"Asia/Shanghai",
    "iso:country":"CN",
    "name:zho_x_preferred":[
        "\u4e0b\u74e6\u4f1f"
    ],
    "wof:name":"Xiawawei",
    "wof:placetype":"locality"
},
  "geometry": {"coordinates":[100.77500000000001,24.6519],"type":"Point"}
}