{
  "type": "Feature",
  "properties": {
    "gn:admin1_code":"9.0",
    "gn:asciiname":"Ciyuan",
    "gn:country_code":"CN",
    "gn:dem":106,
    "gn:feature_class":"P",
    "gn:feature_code":"PPL",
    "gn:name":"Ciyuan",
    "gn:population":0,
    "gn:timezone":"Asia/Shanghai",
    "iso:country":"CN",
    "name:und_x_variant":[
        "\u8328\u56ed"
    ],
    "name:zho_x_preferred":[
        "\u8328\u56ed"
    ],
    "wof:name":"Ciyuan",
    "wof:placetype":"locality"
},
  "geometry": {"coordinates":[113.92794000000001,33.00079],"type":"Point"}
}