{
  "type": "Feature",
  "properties": {
    "gn:admin1_code":"16.0",
    "gn:asciiname":"Wangbu",
    "gn:country_code":"CN",
    "gn:dem":76,
    "gn:feature_class":"P",
    "gn:feature_code":"PPL",
    "gn:name":"Wangbu",
    "gn:population":0,
    "gn:timezone":"Asia/Shanghai",
    "iso:country":"CN",
    "name:zho_x_preferred":[
        "\u671b\u6b65"
    ],
    "wof:name":"Wangbu",
    "wof:placetype":"locality"
},
  "geometry": {"coordinates":[108.93899999999999,22.9197],"type":"Point"}
}