{
  "type": "Feature",
  "properties": {
    "gn:admin1_code":"1.0",
    "gn:asciiname":"Xiaoluo",
    "gn:country_code":"CN",
    "gn:dem":11,
    "gn:feature_class":"P",
    "gn:feature_code":"PPL",
    "gn:name":"Xiaoluo",
    "gn:population":0,
    "gn:timezone":"Asia/Shanghai",
    "iso:country":"CN",
    "name:zho_x_preferred":[
        "\u5c0f\u6d1b"
    ],
    "wof:name":"Xiaoluo",
    "wof:placetype":"locality"
},
  "geometry": {"coordinates":[118.79633,31.40974000000001],"type":"Point"}
}