{
  "type": "Feature",
  "properties": {
    "gn:admin1_code":"10",
    "gn:asciiname":"Baiyazhuang",
    "gn:country_code":"CN",
    "gn:dem":31,
    "gn:feature_class":"P",
    "gn:feature_code":"PPL",
    "gn:name":"Baiyazhuang",
    "gn:population":0,
    "gn:timezone":"Asia/Shanghai",
    "iso:country":"CN",
    "name:zho_x_preferred":[
        "\u67cf\u82bd\u5e84"
    ],
    "wof:name":"Baiyazhuang",
    "wof:placetype":"locality"
},
  "geometry": {"coordinates":[115.249,37.5897],"type":"Point"}
}