{
  "type": "Feature",
  "properties": {
    "gn:admin1_code":"10.0",
    "gn:asciiname":"Zhaoduanzhuang",
    "gn:country_code":"CN",
    "gn:dem":20,
    "gn:feature_class":"P",
    "gn:feature_code":"PPL",
    "gn:name":"Zhaoduanzhuang",
    "gn:population":0,
    "gn:timezone":"Asia/Shanghai",
    "iso:country":"CN",
    "name:zho_x_preferred":[
        "\u8d75\u953b\u5e84"
    ],
    "wof:name":"Zhaoduanzhuang",
    "wof:placetype":"locality"
},
  "geometry": {"coordinates":[115.64100000000001,38.5367],"type":"Point"}
}