{
  "type": "Feature",
  "properties": {
    "gn:admin1_code":"2",
    "gn:asciiname":"Tiebulingwei",
    "gn:country_code":"CN",
    "gn:dem":418,
    "gn:feature_class":"P",
    "gn:feature_code":"PPL",
    "gn:name":"Tiebulingwei",
    "gn:population":0,
    "gn:timezone":"Asia/Shanghai",
    "iso:country":"CN",
    "name:zho_x_preferred":[
        "\u94c1\u535c\u5cad\u5c3e"
    ],
    "wof:name":"Tiebulingwei",
    "wof:placetype":"locality"
},
  "geometry": {"coordinates":[119.36278,27.77944],"type":"Point"}
}