{
  "type": "Feature",
  "properties": {
    "gn:admin1_code":"19",
    "gn:asciiname":"Quangou",
    "gn:country_code":"CN",
    "gn:dem":174,
    "gn:feature_class":"P",
    "gn:feature_code":"PPLA4",
    "gn:name":"Quangou",
    "gn:population":0,
    "gn:timezone":"Asia/Shanghai",
    "iso:country":"CN",
    "name:und_x_variant":[
        "Laosiping Zhen",
        "Laosiping",
        "Quangou"
    ],
    "name:zho_x_preferred":[
        "\u6cc9\u6c9f"
    ],
    "name:zho_x_variant":[
        "\u8001\u56db\u5e73\u9547",
        "\u8001\u56db\u5e73"
    ],
    "wof:name":"Quangou",
    "wof:placetype":"locality"
},
  "geometry": {"coordinates":[124.26121000000001,43.18198],"type":"Point"}
}