{
  "type": "Feature",
  "properties": {
    "gn:admin1_code":"33.0",
    "gn:asciiname":"Shifeng",
    "gn:country_code":"CN",
    "gn:dem":407,
    "gn:feature_class":"P",
    "gn:feature_code":"PPL",
    "gn:name":"Shifeng",
    "gn:population":0,
    "gn:timezone":"Asia/Shanghai",
    "iso:country":"CN",
    "name:zho_x_preferred":[
        "\u77f3\u4e30"
    ],
    "wof:name":"Shifeng",
    "wof:placetype":"locality"
},
  "geometry": {"coordinates":[107.82971999999999,30.28933],"type":"Point"}
}