{
  "type": "Feature",
  "properties": {
    "gn:admin1_code":"19.0",
    "gn:asciiname":"Nantaicun",
    "gn:country_code":"CN",
    "gn:dem":52,
    "gn:feature_class":"P",
    "gn:feature_code":"PPL",
    "gn:name":"Nantaicun",
    "gn:population":0,
    "gn:timezone":"Asia/Shanghai",
    "iso:country":"CN",
    "name:zho_x_preferred":[
        "\u5357\u53f0\u6751"
    ],
    "wof:name":"Nantaicun",
    "wof:placetype":"locality"
},
  "geometry": {"coordinates":[122.05800000000001,39.355],"type":"Point"}
}