{
  "type": "Feature",
  "properties": {
    "gn:admin1_code":"4.0",
    "gn:asciiname":"Gaoliucun",
    "gn:country_code":"CN",
    "gn:dem":2,
    "gn:feature_class":"P",
    "gn:feature_code":"PPL",
    "gn:name":"Gaoliucun",
    "gn:population":0,
    "gn:timezone":"Asia/Shanghai",
    "iso:country":"CN",
    "name:zho_x_preferred":[
        "\u9ad8\u67f3\u6751"
    ],
    "wof:name":"Gaoliucun",
    "wof:placetype":"locality"
},
  "geometry": {"coordinates":[120.39227,32.79449],"type":"Point"}
}