{
  "type": "Feature",
  "properties": {
    "gn:admin1_code":"4.0",
    "gn:asciiname":"Yuanxiang",
    "gn:country_code":"CN",
    "gn:dem":51,
    "gn:feature_class":"P",
    "gn:feature_code":"PPL",
    "gn:name":"Yuanxiang",
    "gn:population":0,
    "gn:timezone":"Asia/Shanghai",
    "iso:country":"CN",
    "name:und_x_variant":[
        "Yuanxiangtou",
        "Y\u00fcan-hsiang-t\u2019ou",
        "Y\u00fcan-hsiang",
        "Y\u00fcan-hsiang-chen",
        "Yuanxiang"
    ],
    "name:zho_x_preferred":[
        "\u8881\u5df7"
    ],
    "wof:name":"Yuanxiang",
    "wof:placetype":"locality"
},
  "geometry": {"coordinates":[119.22709999999999,31.65924],"type":"Point"}
}