{
  "type": "Feature",
  "properties": {
    "gn:admin1_code":"26.0",
    "gn:asciiname":"Qiao'ergou",
    "gn:country_code":"CN",
    "gn:dem":1188,
    "gn:feature_class":"P",
    "gn:feature_code":"PPL",
    "gn:name":"Qiao\u2019ergou",
    "gn:population":0,
    "gn:timezone":"Asia/Shanghai",
    "iso:country":"CN",
    "name:und_x_variant":[
        "Qiao\u2019ergou"
    ],
    "name:zho_x_preferred":[
        "\u4e54\u513f\u6c9f"
    ],
    "wof:name":"Qiao'ergou",
    "wof:placetype":"locality"
},
  "geometry": {"coordinates":[109.79031000000001,33.46038],"type":"Point"}
}