{
  "type": "Feature",
  "properties": {
    "gn:admin1_code":"14.0",
    "gn:asciiname":"Butuocun",
    "gn:country_code":"CN",
    "gn:dem":3430,
    "gn:feature_class":"P",
    "gn:feature_code":"PPL",
    "gn:name":"Butuocun",
    "gn:population":0,
    "gn:timezone":"Asia/Urumqi",
    "iso:country":"CN",
    "name:zho_x_preferred":[
        "\u5e03\u59a5\u6751"
    ],
    "wof:name":"Butuocun",
    "wof:placetype":"locality"
},
  "geometry": {"coordinates":[97.20225000000001,31.34239],"type":"Point"}
}