{
  "type": "Feature",
  "properties": {
    "gn:admin1_code":"32.0",
    "gn:asciiname":"Daijia'ao",
    "gn:country_code":"CN",
    "gn:dem":362,
    "gn:feature_class":"P",
    "gn:feature_code":"PPL",
    "gn:name":"Daijia\u2019ao",
    "gn:population":0,
    "gn:timezone":"Asia/Shanghai",
    "iso:country":"CN",
    "name:zho_x_preferred":[
        "\u4ee3\u5bb6\u5787"
    ],
    "name:zho_x_variant":[
        "Daijia\u2019ao"
    ],
    "wof:name":"Daijia'ao",
    "wof:placetype":"locality"
},
  "geometry": {"coordinates":[104.40170000000001,29.04993],"type":"Point"}
}