{
  "type": "Feature",
  "properties": {
    "gn:admin1_code":"24.0",
    "gn:asciiname":"Xiaoyukou",
    "gn:country_code":"CN",
    "gn:dem":1149,
    "gn:feature_class":"P",
    "gn:feature_code":"PPL",
    "gn:name":"Xiaoyukou",
    "gn:population":0,
    "gn:timezone":"Asia/Shanghai",
    "iso:country":"CN",
    "name:und_x_variant":[
        "Hsiao-y\u00fc-k\u2019ou",
        "Xiaoyukou",
        "\u5c0f\u5cea\u53e3"
    ],
    "wof:name":"Xiaoyukou",
    "wof:placetype":"locality"
},
  "geometry": {"coordinates":[112.94701999999999,39.79552],"type":"Point"}
}