{
  "type": "Feature",
  "properties": {
    "gn:admin1_code":"1.0",
    "gn:asciiname":"Qiandongzhuangcun",
    "gn:country_code":"CN",
    "gn:dem":36,
    "gn:feature_class":"P",
    "gn:feature_code":"PPL",
    "gn:name":"Qiandongzhuangcun",
    "gn:population":0,
    "gn:timezone":"Asia/Shanghai",
    "iso:country":"CN",
    "name:zho_x_preferred":[
        "\u524d\u8463\u5e84\u6751"
    ],
    "wof:name":"Qiandongzhuangcun",
    "wof:placetype":"locality"
},
  "geometry": {"coordinates":[115.84089,33.62073],"type":"Point"}
}