{
  "type": "Feature",
  "properties": {
    "gn:admin1_code":"32.0",
    "gn:asciiname":"Shiyaoshan",
    "gn:country_code":"CN",
    "gn:dem":1301,
    "gn:feature_class":"P",
    "gn:feature_code":"PPL",
    "gn:name":"Shiyaoshan",
    "gn:population":0,
    "gn:timezone":"Asia/Shanghai",
    "iso:country":"CN",
    "name:zho_x_preferred":[
        "\u77f3\u5c27\u5c71"
    ],
    "wof:name":"Shiyaoshan",
    "wof:placetype":"locality"
},
  "geometry": {"coordinates":[105.71878999999998,27.80515],"type":"Point"}
}