{
  "type": "Feature",
  "properties": {
    "iso:country":"CN",
    "name:ceb_x_preferred":[
        "Yangshuo Xian"
    ],
    "name:deu_x_preferred":[
        "Yangshuo"
    ],
    "name:eng_x_preferred":[
        "Yangshuo County"
    ],
    "name:fas_x_preferred":[
        "\u06cc\u0627\u0646\u06af\u0634\u0627\u0648"
    ],
    "name:fin_x_preferred":[
        "Yangshuo"
    ],
    "name:gan_x_preferred":[
        "\u9633\u6714\u53bf"
    ],
    "name:hak_x_preferred":[
        "Y\u00f2ng-suk-yen"
    ],
    "name:heb_x_preferred":[
        "\u05d9\u05d0\u05e0\u05d2\u05e9\u05d5\u05d0\u05d5"
    ],
    "name:jpn_x_preferred":[
        "\u967d\u6714\u770c"
    ],
    "name:kor_x_preferred":[
        "\uc591\uc234\ud604"
    ],
    "name:nan_x_preferred":[
        "I\u00f4ng-sok-ko\u0101n"
    ],
    "name:nld_x_preferred":[
        "Yangshuo"
    ],
    "name:nob_x_preferred":[
        "Yangshuo"
    ],
    "name:pol_x_preferred":[
        "Yangshuo"
    ],
    "name:spa_x_preferred":[
        "Yangshuo"
    ],
    "name:swe_x_preferred":[
        "Yangshuo"
    ],
    "name:vie_x_preferred":[
        "D\u01b0\u01a1ng S\u00f3c"
    ],
    "name:wuu_x_preferred":[
        "\u9633\u6714\u53bf"
    ],
    "name:yue_x_preferred":[
        "\u967d\u6714"
    ],
    "name:zho_x_preferred":[
        "\u9633\u6714\u53bf"
    ],
    "qs:name":"\u9633\u6714\u53bf",
    "qs:name_adm0":"\u4e2d\u570b",
    "qs:name_adm1":"\u5e7f\u897f\u7701",
    "qs:photos":188,
    "qs:photos_1k":38,
    "qs:photos_9k":23,
    "qs:photos_9r":14,
    "qs:photos_all":5188,
    "qs:photos_sr":4,
    "qs:placetype":"LocalAdmin",
    "qs:pop_sr":"0",
    "wd:wordcount":382,
    "wof:name":"\u9633\u6714\u53bf",
    "wof:placetype":"localadmin"
},
  "geometry": {"coordinates":[110.484301,24.7740005],"type":"Point"}
}