{
  "type": "Feature",
  "properties": {
    "iso:country":"CN",
    "qs:name":"\u9633\u6714\u53bf",
    "qs:name_adm0":"\u4e2d\u570b",
    "qs:name_adm1":"\u5e7f\u897f\u7701",
    "qs:photos":188,
    "qs:photos_1k":38,
    "qs:photos_9k":23,
    "qs:photos_9r":14,
    "qs:photos_all":5188,
    "qs:photos_sr":4,
    "qs:placetype":"LocalAdmin",
    "qs:pop_sr":"0",
    "wd:wordcount":382,
    "wof:name":"\u9633\u6714\u53bf",
    "wof:placetype":"localadmin"
},
  "geometry": {"coordinates":[110.484301,24.7740005],"type":"Point"}
}