{
  "type": "Feature",
  "properties": {
    "gn:admin1_code":"21.0",
    "gn:asciiname":"Sanzha Wudui",
    "gn:country_code":"CN",
    "gn:dem":1111,
    "gn:feature_class":"P",
    "gn:feature_code":"PPLF",
    "gn:name":"Sanzha Wudui",
    "gn:population":0,
    "gn:timezone":"Asia/Shanghai",
    "iso:country":"CN",
    "name:zho_x_preferred":[
        "\u4e09\u95f8\u4e94\u961f"
    ],
    "wof:name":"Sanzha Wudui",
    "wof:placetype":"locality"
},
  "geometry": {"coordinates":[106.193,38.5735],"type":"Point"}
}