{
  "type": "Feature",
  "properties": {
    "gn:admin1_code":"29.0",
    "gn:asciiname":"Mali",
    "gn:country_code":"CN",
    "gn:dem":1246,
    "gn:feature_class":"P",
    "gn:feature_code":"PPL",
    "gn:name":"Mali",
    "gn:population":0,
    "gn:timezone":"Asia/Shanghai",
    "iso:country":"CN",
    "name:zho_x_preferred":[
        "\u9ebb\u6817"
    ],
    "wof:name":"Mali",
    "wof:placetype":"locality"
},
  "geometry": {"coordinates":[100.155,22.6548],"type":"Point"}
}