{
  "type": "Feature",
  "properties": {
    "gn:admin1_code":"33.0",
    "gn:asciiname":"Henghe",
    "gn:country_code":"CN",
    "gn:dem":1214,
    "gn:feature_class":"P",
    "gn:feature_code":"PPLA4",
    "gn:name":"Henghe",
    "gn:population":0,
    "gn:timezone":"Asia/Shanghai",
    "iso:country":"CN",
    "name:und_x_variant":[
        "Henghe Tujiazu Xiang"
    ],
    "name:zho_x_preferred":[
        "\u6052\u5408"
    ],
    "name:zho_x_variant":[
        "\u6052\u5408\u571f\u5bb6\u65cf\u4e61"
    ],
    "wof:name":"Henghe",
    "wof:placetype":"locality"
},
  "geometry": {"coordinates":[108.75415,30.53147],"type":"Point"}
}