{
  "type": "Feature",
  "properties": {
    "gn:admin1_code":"19.0",
    "gn:asciiname":"Houyuantaicun",
    "gn:country_code":"CN",
    "gn:dem":49,
    "gn:feature_class":"P",
    "gn:feature_code":"PPL",
    "gn:name":"Houyuantaicun",
    "gn:population":0,
    "gn:timezone":"Asia/Shanghai",
    "iso:country":"CN",
    "name:zho_x_preferred":[
        "\u540e\u5143\u53f0\u6751"
    ],
    "wof:name":"Houyuantaicun",
    "wof:placetype":"locality"
},
  "geometry": {"coordinates":[122.06,39.6387],"type":"Point"}
}