{
  "type": "Feature",
  "properties": {
    "gn:admin1_code":"32.0",
    "gn:asciiname":"Chaya",
    "gn:country_code":"CN",
    "gn:dem":3966,
    "gn:feature_class":"P",
    "gn:feature_code":"PPL",
    "gn:name":"Chaya",
    "gn:population":0,
    "gn:timezone":"Asia/Shanghai",
    "iso:country":"CN",
    "name:ceb_x_preferred":[
        "Chaya"
    ],
    "name:deu_x_preferred":[
        "Chaya"
    ],
    "name:fra_x_preferred":[
        "Chaya"
    ],
    "name:ita_x_preferred":[
        "Chaya"
    ],
    "name:swe_x_preferred":[
        "Chaya"
    ],
    "name:zho_x_preferred":[
        "\u8336\u57ad"
    ],
    "wof:name":"Chaya",
    "wof:placetype":"locality"
},
  "geometry": {"coordinates":[101.416,30.4076],"type":"Point"}
}