{
  "type": "Feature",
  "properties": {
    "gn:admin1_code":"10.0",
    "gn:asciiname":"Qianbian Gezhuang",
    "gn:country_code":"CN",
    "gn:dem":10,
    "gn:feature_class":"P",
    "gn:feature_code":"PPL",
    "gn:name":"Qianbian Gezhuang",
    "gn:population":0,
    "gn:timezone":"Asia/Shanghai",
    "iso:country":"CN",
    "name:zho_x_preferred":[
        "\u524d\u8fb9\u5404\u5e84"
    ],
    "wof:name":"Qianbian Gezhuang",
    "wof:placetype":"locality"
},
  "geometry": {"coordinates":[116.456,38.5289],"type":"Point"}
}