{
  "type": "Feature",
  "properties": {
    "gn:admin1_code":"26.0",
    "gn:asciiname":"Dongshaobulang",
    "gn:country_code":"CN",
    "gn:dem":1220,
    "gn:feature_class":"P",
    "gn:feature_code":"PPL",
    "gn:name":"Dongshaobulang",
    "gn:population":0,
    "gn:timezone":"Asia/Shanghai",
    "iso:country":"CN",
    "name:zho_x_preferred":[
        "\u4e1c\u70e7\u4e0d\u6d6a"
    ],
    "wof:name":"Dongshaobulang",
    "wof:placetype":"locality"
},
  "geometry": {"coordinates":[109.43471,38.3076],"type":"Point"}
}