{
  "type": "Feature",
  "properties": {
    "gn:admin1_code":"32.0",
    "gn:asciiname":"Baihuawan",
    "gn:country_code":"CN",
    "gn:dem":272,
    "gn:feature_class":"P",
    "gn:feature_code":"PPL",
    "gn:name":"Baihuawan",
    "gn:population":0,
    "gn:timezone":"Asia/Shanghai",
    "iso:country":"CN",
    "name:zho_x_preferred":[
        "\u767d\u82b1\u5846"
    ],
    "wof:name":"Baihuawan",
    "wof:placetype":"locality"
},
  "geometry": {"coordinates":[105.09614999999999,29.06949],"type":"Point"}
}