{
  "type": "Feature",
  "properties": {
    "gn:admin1_code":"25",
    "gn:asciiname":"Jiangjiahe",
    "gn:country_code":"CN",
    "gn:dem":78,
    "gn:feature_class":"P",
    "gn:feature_code":"PPL",
    "gn:name":"Jiangjiahe",
    "gn:population":0,
    "gn:timezone":"Asia/Shanghai",
    "iso:country":"CN",
    "name:zho_x_preferred":[
        "\u59dc\u5bb6\u6cb3"
    ],
    "wof:name":"Jiangjiahe",
    "wof:placetype":"locality"
},
  "geometry": {"coordinates":[119.01300000000001,36.5748],"type":"Point"}
}