{
  "type": "Feature",
  "properties": {
    "gn:admin1_code":"26.0",
    "gn:asciiname":"Xiasanguantang",
    "gn:country_code":"CN",
    "gn:dem":532,
    "gn:feature_class":"P",
    "gn:feature_code":"PPL",
    "gn:name":"Xiasanguantang",
    "gn:population":0,
    "gn:timezone":"Asia/Shanghai",
    "iso:country":"CN",
    "name:zho_x_preferred":[
        "\u4e0b\u4e09\u5b98\u5802"
    ],
    "wof:name":"Xiasanguantang",
    "wof:placetype":"locality"
},
  "geometry": {"coordinates":[109.04479000000001,34.04977],"type":"Point"}
}