{
  "type": "Feature",
  "properties": {
    "gn:admin1_code":"18.0",
    "gn:asciiname":"Shangbeilue",
    "gn:country_code":"CN",
    "gn:dem":783,
    "gn:feature_class":"P",
    "gn:feature_code":"PPL",
    "gn:name":"Shangbeilue",
    "gn:population":0,
    "gn:timezone":"Asia/Shanghai",
    "iso:country":"CN",
    "name:zho_x_preferred":[
        "\u4e0a\u80cc\u7565"
    ],
    "wof:name":"Shangbeilue",
    "wof:placetype":"locality"
},
  "geometry": {"coordinates":[108.197,26.1007],"type":"Point"}
}