{
  "type": "Feature",
  "properties": {
    "gn:admin1_code":"29.0",
    "gn:asciiname":"Nanzhang",
    "gn:country_code":"CN",
    "gn:dem":1519,
    "gn:feature_class":"P",
    "gn:feature_code":"PPL",
    "gn:name":"Nanzhang",
    "gn:population":0,
    "gn:timezone":"Asia/Shanghai",
    "iso:country":"CN",
    "name:zho_x_preferred":[
        "\u5357\u638c"
    ],
    "wof:name":"Nanzhang",
    "wof:placetype":"locality"
},
  "geometry": {"coordinates":[99.3282,23.4968],"type":"Point"}
}