{
  "type": "Feature",
  "properties": {
    "gn:admin1_code":"33.0",
    "gn:asciiname":"Shengping",
    "gn:country_code":"CN",
    "gn:dem":297,
    "gn:feature_class":"P",
    "gn:feature_code":"PPL",
    "gn:name":"Shengping",
    "gn:population":0,
    "gn:timezone":"Asia/Shanghai",
    "iso:country":"CN",
    "name:zho_x_preferred":[
        "\u5347\u5e73"
    ],
    "wof:name":"Shengping",
    "wof:placetype":"locality"
},
  "geometry": {"coordinates":[108.13849999999999,31.137],"type":"Point"}
}