{
  "type": "Feature",
  "properties": {
    "gn:admin1_code":"26.0",
    "gn:asciiname":"Shanghejia Guacun",
    "gn:country_code":"CN",
    "gn:dem":971,
    "gn:feature_class":"P",
    "gn:feature_code":"PPL",
    "gn:name":"Shanghejia Guacun",
    "gn:population":0,
    "gn:timezone":"Asia/Shanghai",
    "iso:country":"CN",
    "name:zho_x_preferred":[
        "\u4e0a\u4f55\u5bb6\u576c\u6751"
    ],
    "wof:name":"Shanghejia Guacun",
    "wof:placetype":"locality"
},
  "geometry": {"coordinates":[110.417,38.2124],"type":"Point"}
}