{
  "type": "Feature",
  "properties": {
    "gn:admin1_code":"16",
    "gn:asciiname":"Lujiadong",
    "gn:country_code":"CN",
    "gn:dem":221,
    "gn:feature_class":"P",
    "gn:feature_code":"PPL",
    "gn:name":"L\u00fcjiadong",
    "gn:population":0,
    "gn:timezone":"Asia/Shanghai",
    "iso:country":"CN",
    "name:und_x_variant":[
        "L\u00fcjiadong"
    ],
    "name:zho_x_preferred":[
        "\u5415\u5bb6\u578c"
    ],
    "wof:name":"Lujiadong",
    "wof:placetype":"locality"
},
  "geometry": {"coordinates":[110.93167,25.74028],"type":"Point"}
}