{
  "type": "Feature",
  "properties": {
    "gn:admin1_code":"09",
    "gn:asciiname":"Laodian",
    "gn:country_code":"CN",
    "gn:dem":73,
    "gn:feature_class":"P",
    "gn:feature_code":"PPL",
    "gn:name":"Laodian",
    "gn:population":0,
    "gn:timezone":"Asia/Shanghai",
    "iso:country":"CN",
    "name:zho_x_preferred":[
        "\u8001\u5e97"
    ],
    "wof:name":"Laodian",
    "wof:placetype":"locality"
},
  "geometry": {"coordinates":[114.37452999999999,32.44033],"type":"Point"}
}