{
  "type": "Feature",
  "properties": {
    "gn:admin1_code":"18.0",
    "gn:asciiname":"Dianmu",
    "gn:country_code":"CN",
    "gn:dem":1326,
    "gn:feature_class":"P",
    "gn:feature_code":"PPL",
    "gn:name":"Dianmu",
    "gn:population":0,
    "gn:timezone":"Asia/Shanghai",
    "iso:country":"CN",
    "wof:name":"Dianmu",
    "wof:placetype":"locality"
},
  "geometry": {"coordinates":[105.27500000000001,25.55],"type":"Point"}
}