{
  "type": "Feature",
  "properties": {
    "gn:admin1_code":"19.0",
    "gn:asciiname":"Jingshangcun",
    "gn:country_code":"CN",
    "gn:dem":470,
    "gn:feature_class":"P",
    "gn:feature_code":"PPL",
    "gn:name":"Jingshangcun",
    "gn:population":0,
    "gn:timezone":"Asia/Shanghai",
    "iso:country":"CN",
    "name:zho_x_preferred":[
        "\u4e95\u4e0a\u6751"
    ],
    "wof:name":"Jingshangcun",
    "wof:placetype":"locality"
},
  "geometry": {"coordinates":[119.736,41.3311],"type":"Point"}
}