{
  "type": "Feature",
  "properties": {
    "gn:admin1_code":"29.0",
    "gn:asciiname":"Guangrong",
    "gn:country_code":"CN",
    "gn:dem":1449,
    "gn:feature_class":"P",
    "gn:feature_code":"PPL",
    "gn:name":"Guangrong",
    "gn:population":0,
    "gn:timezone":"Asia/Shanghai",
    "iso:country":"CN",
    "name:zho_x_preferred":[
        "\u5149\u8363"
    ],
    "wof:name":"Guangrong",
    "wof:placetype":"locality"
},
  "geometry": {"coordinates":[98.3984,24.5576],"type":"Point"}
}