{
  "type": "Feature",
  "properties": {
    "gn:admin1_code":"4.0",
    "gn:asciiname":"Zhanglou",
    "gn:country_code":"CN",
    "gn:dem":3,
    "gn:feature_class":"P",
    "gn:feature_code":"PPL",
    "gn:name":"Zhanglou",
    "gn:population":0,
    "gn:timezone":"Asia/Shanghai",
    "iso:country":"CN",
    "name:zho_x_preferred":[
        "Zhanglou"
    ],
    "name:zho_x_variant":[
        "\u5f20\u697c"
    ],
    "wof:name":"Zhanglou",
    "wof:placetype":"locality"
},
  "geometry": {"coordinates":[119.25118000000001,34.17621],"type":"Point"}
}