{
  "type": "Feature",
  "properties": {
    "gn:admin1_code":"5.0",
    "gn:asciiname":"Jufacun",
    "gn:country_code":"CN",
    "gn:dem":143,
    "gn:feature_class":"P",
    "gn:feature_code":"PPL",
    "gn:name":"Jufacun",
    "gn:population":0,
    "gn:timezone":"Asia/Shanghai",
    "iso:country":"CN",
    "name:zho_x_preferred":[
        "\u5de8\u53d1\u6751"
    ],
    "wof:name":"Jufacun",
    "wof:placetype":"locality"
},
  "geometry": {"coordinates":[125.29438,45.31135],"type":"Point"}
}