{
  "type": "Feature",
  "properties": {
    "gn:admin1_code":"10",
    "gn:asciiname":"Motun",
    "gn:cc2":"CN",
    "gn:country_code":"CN",
    "gn:dem":102,
    "gn:feature_class":"P",
    "gn:feature_code":"PPL",
    "gn:name":"Motun",
    "gn:population":0,
    "gn:timezone":"Asia/Shanghai",
    "iso:country":"CN",
    "name:und_x_variant":[
        "Mo-chia-t\u2019un",
        "Motun"
    ],
    "wof:name":"Motun",
    "wof:placetype":"locality"
},
  "geometry": {"coordinates":[118.15278000000001,40.08111],"type":"Point"}
}