{
  "type": "Feature",
  "properties": {
    "gn:admin1_code":"4.0",
    "gn:asciiname":"Yuanshe",
    "gn:country_code":"CN",
    "gn:dem":2,
    "gn:feature_class":"P",
    "gn:feature_code":"PPL",
    "gn:name":"Yuanshe",
    "gn:population":0,
    "gn:timezone":"Asia/Shanghai",
    "iso:country":"CN",
    "name:zho_x_preferred":[
        "Yuanshe"
    ],
    "name:zho_x_variant":[
        "\u8881\u820d"
    ],
    "wof:name":"Yuanshe",
    "wof:placetype":"locality"
},
  "geometry": {"coordinates":[119.30597,33.50409000000001],"type":"Point"}
}