{
  "type": "Feature",
  "properties": {
    "gn:admin1_code":"26.0",
    "gn:asciiname":"Xiahexi",
    "gn:country_code":"CN",
    "gn:dem":769,
    "gn:feature_class":"P",
    "gn:feature_code":"PPL",
    "gn:name":"Xiahexi",
    "gn:population":0,
    "gn:timezone":"Asia/Shanghai",
    "iso:country":"CN",
    "name:und_x_variant":[
        "\u4e0b\u6cb3\u897f"
    ],
    "wof:name":"Xiahexi",
    "wof:placetype":"locality"
},
  "geometry": {"coordinates":[107.06347,34.51783],"type":"Point"}
}