{
  "type": "Feature",
  "properties": {
    "gn:admin1_code":"22.0",
    "gn:asciiname":"Baitacun",
    "gn:country_code":"CN",
    "gn:dem":43,
    "gn:feature_class":"P",
    "gn:feature_code":"PPL",
    "gn:name":"Baitacun",
    "gn:population":0,
    "gn:timezone":"Asia/Shanghai",
    "iso:country":"CN",
    "name:zho_x_preferred":[
        "\u767d\u5854\u6751"
    ],
    "wof:name":"Baitacun",
    "wof:placetype":"locality"
},
  "geometry": {"coordinates":[116.88655,40.16453],"type":"Point"}
}