{
  "type": "Feature",
  "properties": {
    "gn:admin1_code":"25.0",
    "gn:asciiname":"Yingzitun",
    "gn:country_code":"CN",
    "gn:dem":11,
    "gn:feature_class":"P",
    "gn:feature_code":"PPL",
    "gn:name":"Yingzitun",
    "gn:population":0,
    "gn:timezone":"Asia/Shanghai",
    "iso:country":"CN",
    "name:zho_x_preferred":[
        "\u8425\u5b50\u5c6f"
    ],
    "wof:name":"Yingzitun",
    "wof:placetype":"locality"
},
  "geometry": {"coordinates":[119.76761999999999,36.63534],"type":"Point"}
}