{
  "type": "Feature",
  "properties": {
    "gn:admin1_code":"02",
    "gn:asciiname":"Lingxia",
    "gn:country_code":"CN",
    "gn:dem":360,
    "gn:feature_class":"P",
    "gn:feature_code":"PPL",
    "gn:name":"Lingxia",
    "gn:population":0,
    "gn:timezone":"Asia/Shanghai",
    "iso:country":"CN",
    "name:und_x_variant":[
        "Ling-hsia",
        "Lingxia"
    ],
    "name:zho_x_preferred":[
        "\u5cad\u4e0b"
    ],
    "wof:name":"Lingxia",
    "wof:placetype":"locality"
},
  "geometry": {"coordinates":[120.73548,27.91346],"type":"Point"}
}