{
  "type": "Feature",
  "properties": {
    "gn:admin1_code":"26.0",
    "gn:asciiname":"Zhongwangcun",
    "gn:country_code":"CN",
    "gn:dem":376,
    "gn:feature_class":"P",
    "gn:feature_code":"PPL",
    "gn:name":"Zhongwangcun",
    "gn:population":0,
    "gn:timezone":"Asia/Shanghai",
    "iso:country":"CN",
    "name:und_x_variant":[
        "Chung-wang-ts\u2019un",
        "Zhongwangcun"
    ],
    "wof:name":"Zhongwangcun",
    "wof:placetype":"locality"
},
  "geometry": {"coordinates":[109.12532,34.5399],"type":"Point"}
}