{
  "type": "Feature",
  "properties": {
    "gn:admin1_code":"32.0",
    "gn:asciiname":"Luobaiya",
    "gn:country_code":"CN",
    "gn:dem":526,
    "gn:feature_class":"P",
    "gn:feature_code":"PPL",
    "gn:name":"Luobaiya",
    "gn:population":0,
    "gn:timezone":"Asia/Shanghai",
    "iso:country":"CN",
    "name:zho_x_preferred":[
        "\u7f57\u67cf\u57ad"
    ],
    "wof:name":"Luobaiya",
    "wof:placetype":"locality"
},
  "geometry": {"coordinates":[105.77,31.6003],"type":"Point"}
}