{
  "type": "Feature",
  "properties": {
    "gn:admin1_code":"15.0",
    "gn:asciiname":"Bare",
    "gn:country_code":"CN",
    "gn:dem":2837,
    "gn:feature_class":"P",
    "gn:feature_code":"PPL",
    "gn:name":"Bare",
    "gn:population":0,
    "gn:timezone":"Asia/Shanghai",
    "iso:country":"CN",
    "name:zho_x_preferred":[
        "\u5df4\u70ed"
    ],
    "wof:name":"Bare",
    "wof:placetype":"locality"
},
  "geometry": {"coordinates":[103.39700000000001,33.7849],"type":"Point"}
}