{
  "type": "Feature",
  "properties": {
    "gn:admin1_code":"33.0",
    "gn:asciiname":"Pingle",
    "gn:country_code":"CN",
    "gn:dem":686,
    "gn:feature_class":"P",
    "gn:feature_code":"PPL",
    "gn:name":"Pingle",
    "gn:population":0,
    "gn:timezone":"Asia/Shanghai",
    "iso:country":"CN",
    "name:ceb_x_preferred":[
        "Pingle"
    ],
    "name:deu_x_preferred":[
        "Pingle"
    ],
    "name:zho_x_preferred":[
        "\u5e73\u4e50"
    ],
    "wof:name":"Pingle",
    "wof:placetype":"locality"
},
  "geometry": {"coordinates":[108.26255,31.37735],"type":"Point"}
}