{
  "type": "Feature",
  "properties": {
    "gn:admin1_code":"10",
    "gn:asciiname":"Dacao Gezhai",
    "gn:country_code":"CN",
    "gn:dem":41,
    "gn:feature_class":"P",
    "gn:feature_code":"PPL",
    "gn:name":"Dacao Gezhai",
    "gn:population":0,
    "gn:timezone":"Asia/Shanghai",
    "iso:country":"CN",
    "name:zho_x_preferred":[
        "\u5927\u66f9\u5404\u5be8"
    ],
    "wof:name":"Dacao Gezhai",
    "wof:placetype":"locality"
},
  "geometry": {"coordinates":[117.82761000000001,40.14089],"type":"Point"}
}