{
  "type": "Feature",
  "properties": {
    "gn:admin1_code":"2.0",
    "gn:asciiname":"Erbaijiufan",
    "gn:country_code":"CN",
    "gn:dem":283,
    "gn:feature_class":"P",
    "gn:feature_code":"PPL",
    "gn:name":"Erbaijiufan",
    "gn:population":0,
    "gn:timezone":"Asia/Shanghai",
    "iso:country":"CN",
    "name:zho_x_preferred":[
        "\u4e8c\u767e\u4e5d\u7548"
    ],
    "wof:name":"Erbaijiufan",
    "wof:placetype":"locality"
},
  "geometry": {"coordinates":[120.01423,28.63205],"type":"Point"}
}