{
  "type": "Feature",
  "properties": {
    "gn:admin1_code":"25",
    "gn:asciiname":"Yejiagou",
    "gn:country_code":"CN",
    "gn:dem":194,
    "gn:feature_class":"P",
    "gn:feature_code":"PPL",
    "gn:name":"Yejiagou",
    "gn:population":0,
    "gn:timezone":"Asia/Shanghai",
    "iso:country":"CN",
    "name:zho_x_preferred":[
        "\u4e1a\u5bb6\u6c9f"
    ],
    "wof:name":"Yejiagou",
    "wof:placetype":"locality"
},
  "geometry": {"coordinates":[118.169,35.5747],"type":"Point"}
}