{
  "type": "Feature",
  "properties": {
    "gn:admin1_code":"07",
    "gn:asciiname":"Dawudi",
    "gn:country_code":"CN",
    "gn:dem":970,
    "gn:feature_class":"P",
    "gn:feature_code":"PPL",
    "gn:name":"Dawudi",
    "gn:population":0,
    "gn:timezone":"Asia/Shanghai",
    "iso:country":"CN",
    "name:zho_x_preferred":[
        "\u5927\u5434\u5730"
    ],
    "wof:name":"Dawudi",
    "wof:placetype":"locality"
},
  "geometry": {"coordinates":[117.21674,25.64661],"type":"Point"}
}