{
  "type": "Feature",
  "properties": {
    "gn:admin1_code":"5.0",
    "gn:asciiname":"Hewacun",
    "gn:country_code":"CN",
    "gn:dem":316,
    "gn:feature_class":"P",
    "gn:feature_code":"PPL",
    "gn:name":"Hewacun",
    "gn:population":0,
    "gn:timezone":"Asia/Shanghai",
    "iso:country":"CN",
    "name:zho_x_preferred":[
        "\u6cb3\u6d3c\u6751"
    ],
    "wof:name":"Hewacun",
    "wof:placetype":"locality"
},
  "geometry": {"coordinates":[125.96856,42.59233],"type":"Point"}
}