{
  "type": "Feature",
  "properties": {
    "gn:admin1_code":"14.0",
    "gn:asciiname":"Lhalung",
    "gn:country_code":"CN",
    "gn:dem":4401,
    "gn:feature_class":"P",
    "gn:feature_code":"PPL",
    "gn:name":"Lhalung",
    "gn:population":0,
    "gn:timezone":"Asia/Urumqi",
    "iso:country":"CN",
    "name:bod_x_preferred":[
        "Lhalung"
    ],
    "name:zho_x_preferred":[
        "Lalong"
    ],
    "name:zho_x_variant":[
        "\u62c9\u9686"
    ],
    "wof:name":"Lhalung",
    "wof:placetype":"locality"
},
  "geometry": {"coordinates":[92.20099999999999,29.201],"type":"Point"}
}