{
  "type": "Feature",
  "properties": {
    "gn:admin1_code":"1.0",
    "gn:asciiname":"Xuchangcun",
    "gn:country_code":"CN",
    "gn:dem":35,
    "gn:feature_class":"P",
    "gn:feature_code":"PPL",
    "gn:name":"Xuchangcun",
    "gn:population":0,
    "gn:timezone":"Asia/Shanghai",
    "iso:country":"CN",
    "name:zho_x_preferred":[
        "\u5f90\u5e38\u6751"
    ],
    "wof:name":"Xuchangcun",
    "wof:placetype":"locality"
},
  "geometry": {"coordinates":[116.69092000000001,33.83104],"type":"Point"}
}