{
  "type": "Feature",
  "properties": {
    "gn:admin1_code":"15.0",
    "gn:asciiname":"Huwatan",
    "gn:country_code":"CN",
    "gn:dem":2554,
    "gn:feature_class":"P",
    "gn:feature_code":"PPL",
    "gn:name":"Huwatan",
    "gn:population":0,
    "gn:timezone":"Asia/Shanghai",
    "iso:country":"CN",
    "name:und_x_variant":[
        "\u864e\u5a03\u6ee9"
    ],
    "wof:name":"Huwatan",
    "wof:placetype":"locality"
},
  "geometry": {"coordinates":[103.78176000000001,34.4549],"type":"Point"}
}