{
  "type": "Feature",
  "properties": {
    "gn:admin1_code":"5.0",
    "gn:asciiname":"Zhanglibentun",
    "gn:country_code":"CN",
    "gn:dem":210,
    "gn:feature_class":"P",
    "gn:feature_code":"PPL",
    "gn:name":"Zhanglibentun",
    "gn:population":0,
    "gn:timezone":"Asia/Shanghai",
    "iso:country":"CN",
    "name:zho_x_preferred":[
        "\u5f20\u7acb\u672c\u5c6f"
    ],
    "wof:name":"Zhanglibentun",
    "wof:placetype":"locality"
},
  "geometry": {"coordinates":[124.20104000000001,44.16947],"type":"Point"}
}