{
  "type": "Feature",
  "properties": {
    "gn:admin1_code":"4.0",
    "gn:asciiname":"Chenluwei",
    "gn:country_code":"CN",
    "gn:dem":8,
    "gn:feature_class":"P",
    "gn:feature_code":"PPL",
    "gn:name":"Chenluwei",
    "gn:population":0,
    "gn:timezone":"Asia/Shanghai",
    "iso:country":"CN",
    "name:zho_x_preferred":[
        "\u9648\u9646\u9b4f"
    ],
    "wof:name":"Chenluwei",
    "wof:placetype":"locality"
},
  "geometry": {"coordinates":[118.83799999999999,34.0476],"type":"Point"}
}