{
  "type": "Feature",
  "properties": {
    "gn:admin1_code":"29.0",
    "gn:asciiname":"Xingde",
    "gn:country_code":"CN",
    "gn:dem":1831,
    "gn:feature_class":"P",
    "gn:feature_code":"PPL",
    "gn:name":"Xingde",
    "gn:population":0,
    "gn:timezone":"Asia/Shanghai",
    "iso:country":"CN",
    "name:zho_x_preferred":[
        "\u5174\u5f97"
    ],
    "wof:name":"Xingde",
    "wof:placetype":"locality"
},
  "geometry": {"coordinates":[103.67700000000001,26.359],"type":"Point"}
}