{
  "type": "Feature",
  "properties": {
    "gn:admin1_code":"15.0",
    "gn:asciiname":"Yangpodagou",
    "gn:country_code":"CN",
    "gn:dem":2708,
    "gn:feature_class":"P",
    "gn:feature_code":"PPL",
    "gn:name":"Yangpodagou",
    "gn:population":0,
    "gn:timezone":"Asia/Shanghai",
    "iso:country":"CN",
    "name:und_x_variant":[
        "\u9633\u5761\u5927\u6c9f"
    ],
    "wof:name":"Yangpodagou",
    "wof:placetype":"locality"
},
  "geometry": {"coordinates":[103.96483000000001,34.29977],"type":"Point"}
}