{
  "type": "Feature",
  "properties": {
    "gn:admin1_code":"14.0",
    "gn:asciiname":"Dazicun",
    "gn:country_code":"CN",
    "gn:dem":3937,
    "gn:feature_class":"P",
    "gn:feature_code":"PPL",
    "gn:name":"Dazicun",
    "gn:population":0,
    "gn:timezone":"Asia/Urumqi",
    "iso:country":"CN",
    "name:zho_x_preferred":[
        "\u8fbe\u5b5c\u6751"
    ],
    "wof:name":"Dazicun",
    "wof:placetype":"locality"
},
  "geometry": {"coordinates":[94.99290000000001,30.92271],"type":"Point"}
}