{
  "type": "Feature",
  "properties": {
    "gn:admin1_code":"32.0",
    "gn:asciiname":"Haonieduo",
    "gn:country_code":"CN",
    "gn:dem":4216,
    "gn:feature_class":"P",
    "gn:feature_code":"PPL",
    "gn:name":"Haonieduo",
    "gn:population":0,
    "gn:timezone":"Asia/Shanghai",
    "iso:country":"CN",
    "name:zho_x_preferred":[
        "\u6d69\u6d85\u591a"
    ],
    "wof:name":"Haonieduo",
    "wof:placetype":"locality"
},
  "geometry": {"coordinates":[99.47441000000001,31.19727],"type":"Point"}
}