{
  "type": "Feature",
  "properties": {
    "gn:admin1_code":"26.0",
    "gn:asciiname":"Tuwozi",
    "gn:country_code":"CN",
    "gn:dem":1603,
    "gn:feature_class":"P",
    "gn:feature_code":"PPL",
    "gn:name":"Tuwozi",
    "gn:population":0,
    "gn:timezone":"Asia/Shanghai",
    "iso:country":"CN",
    "name:zho_x_preferred":[
        "\u5154\u7a9d\u5b50"
    ],
    "wof:name":"Tuwozi",
    "wof:placetype":"locality"
},
  "geometry": {"coordinates":[107.83901000000002,37.32406],"type":"Point"}
}