{
  "type": "Feature",
  "properties": {
    "gn:admin1_code":"8.0",
    "gn:asciiname":"Genghuoli",
    "gn:country_code":"CN",
    "gn:dem":256,
    "gn:feature_class":"P",
    "gn:feature_code":"PPL",
    "gn:name":"Genghuoli",
    "gn:population":0,
    "gn:timezone":"Asia/Shanghai",
    "iso:country":"CN",
    "name:zho_x_preferred":[
        "\u803f\u706b\u529b"
    ],
    "wof:name":"Genghuoli",
    "wof:placetype":"locality"
},
  "geometry": {"coordinates":[123.15022999999999,47.65025],"type":"Point"}
}