{
  "type": "Feature",
  "properties": {
    "gn:admin1_code":"29.0",
    "gn:asciiname":"Dawenhai",
    "gn:country_code":"CN",
    "gn:dem":1216,
    "gn:feature_class":"P",
    "gn:feature_code":"PPL",
    "gn:name":"Dawenhai",
    "gn:population":0,
    "gn:timezone":"Asia/Shanghai",
    "iso:country":"CN",
    "name:zho_x_preferred":[
        "\u5927\u6587\u6d77"
    ],
    "wof:name":"Dawenhai",
    "wof:placetype":"locality"
},
  "geometry": {"coordinates":[101.145,23.6748],"type":"Point"}
}