{
  "type": "Feature",
  "properties": {
    "gn:admin1_code":"02",
    "gn:asciiname":"Songjialou",
    "gn:country_code":"CN",
    "gn:dem":13,
    "gn:feature_class":"P",
    "gn:feature_code":"PPL",
    "gn:name":"Songjialou",
    "gn:population":0,
    "gn:timezone":"Asia/Shanghai",
    "iso:country":"CN",
    "name:und_x_variant":[
        "Sung-chia-l\u00fc",
        "Songjial\u00fc",
        "Songjialou",
        "\u5b8b\u5bb6\u6e87"
    ],
    "wof:name":"Songjialou",
    "wof:placetype":"locality"
},
  "geometry": {"coordinates":[120.64091999999999,30.09707],"type":"Point"}
}