{
  "type": "Feature",
  "properties": {
    "gn:admin1_code":"01",
    "gn:asciiname":"Guilin",
    "gn:country_code":"CN",
    "gn:dem":127,
    "gn:feature_class":"P",
    "gn:feature_code":"PPLA4",
    "gn:name":"Guilin",
    "gn:population":0,
    "gn:timezone":"Asia/Shanghai",
    "iso:country":"CN",
    "name:und_x_variant":[
        "Kuei-lin",
        "Kuei-lin-chen",
        "Guilin Zhen",
        "Guilin"
    ],
    "name:zho_x_preferred":[
        "\u6842\u6797"
    ],
    "name:zho_x_variant":[
        "\u6842\u6797\u9547"
    ],
    "wof:name":"Guilin",
    "wof:placetype":"locality"
},
  "geometry": {"coordinates":[118.46802,29.922],"type":"Point"}
}