{
  "type": "Feature",
  "properties": {
    "gn:admin1_code":"26",
    "gn:asciiname":"Malitan",
    "gn:country_code":"CN",
    "gn:dem":351,
    "gn:feature_class":"P",
    "gn:feature_code":"PPL",
    "gn:name":"Malitan",
    "gn:population":0,
    "gn:timezone":"Asia/Shanghai",
    "iso:country":"CN",
    "name:und_x_variant":[
        "\u9ebb\u674e\u6ee9",
        "Malitan"
    ],
    "name:zho_x_preferred":[
        "\u9ebb\u674e\u6ee9"
    ],
    "wof:name":"Malitan",
    "wof:placetype":"locality"
},
  "geometry": {"coordinates":[109.43665,34.50484],"type":"Point"}
}