{
  "type": "Feature",
  "properties": {
    "gn:admin1_code":"5.0",
    "gn:asciiname":"Tingzijing",
    "gn:country_code":"CN",
    "gn:dem":148,
    "gn:feature_class":"P",
    "gn:feature_code":"PPL",
    "gn:name":"Tingzijing",
    "gn:population":0,
    "gn:timezone":"Asia/Shanghai",
    "iso:country":"CN",
    "name:zho_x_preferred":[
        "\u542c\u5b57\u4e95"
    ],
    "wof:name":"Tingzijing",
    "wof:placetype":"locality"
},
  "geometry": {"coordinates":[124.42193,44.90471],"type":"Point"}
}