{
  "type": "Feature",
  "properties": {
    "gn:admin1_code":"3.0",
    "gn:asciiname":"Chenfang Wanjia",
    "gn:country_code":"CN",
    "gn:dem":23,
    "gn:feature_class":"P",
    "gn:feature_code":"PPL",
    "gn:name":"Chenfang Wanjia",
    "gn:population":0,
    "gn:timezone":"Asia/Shanghai",
    "iso:country":"CN",
    "name:und_x_variant":[
        "\u9648\u574a\u4e07\u5bb6"
    ],
    "wof:name":"Chenfang Wanjia",
    "wof:placetype":"locality"
},
  "geometry": {"coordinates":[116.71492000000001,28.67467000000001],"type":"Point"}
}