{
  "type": "Feature",
  "properties": {
    "gn:admin1_code":"7.0",
    "gn:asciiname":"Tieling Xiacun",
    "gn:country_code":"CN",
    "gn:dem":278,
    "gn:feature_class":"P",
    "gn:feature_code":"PPL",
    "gn:name":"Tieling Xiacun",
    "gn:population":0,
    "gn:timezone":"Asia/Shanghai",
    "iso:country":"CN",
    "name:zho_x_preferred":[
        "\u94c1\u5cad\u4e0b\u6751"
    ],
    "wof:name":"Tieling Xiacun",
    "wof:placetype":"locality"
},
  "geometry": {"coordinates":[118.02688999999999,27.69218],"type":"Point"}
}