{
  "type": "Feature",
  "properties": {
    "gn:admin1_code":"21.0",
    "gn:asciiname":"Xiashuidangou",
    "gn:country_code":"CN",
    "gn:dem":2287,
    "gn:feature_class":"P",
    "gn:feature_code":"PPL",
    "gn:name":"Xiashuidangou",
    "gn:population":0,
    "gn:timezone":"Asia/Shanghai",
    "iso:country":"CN",
    "name:zho_x_preferred":[
        "\u4e0b\u6c34\u62c5\u6c9f"
    ],
    "wof:name":"Xiashuidangou",
    "wof:placetype":"locality"
},
  "geometry": {"coordinates":[105.563,36.4101],"type":"Point"}
}