{
  "type": "Feature",
  "properties": {
    "gn:admin1_code":"8.0",
    "gn:asciiname":"Lirangtun",
    "gn:country_code":"CN",
    "gn:dem":286,
    "gn:feature_class":"P",
    "gn:feature_code":"PPL",
    "gn:name":"Lirangtun",
    "gn:population":0,
    "gn:timezone":"Asia/Shanghai",
    "iso:country":"CN",
    "name:zho_x_preferred":[
        "\u793c\u8ba9\u5c6f"
    ],
    "wof:name":"Lirangtun",
    "wof:placetype":"locality"
},
  "geometry": {"coordinates":[126.29012,48.01836],"type":"Point"}
}