{
  "type": "Feature",
  "properties": {
    "gn:admin1_code":"14.0",
    "gn:asciiname":"Kangbacun",
    "gn:country_code":"CN",
    "gn:dem":4507,
    "gn:feature_class":"P",
    "gn:feature_code":"PPL",
    "gn:name":"Kangbacun",
    "gn:population":0,
    "gn:timezone":"Asia/Urumqi",
    "iso:country":"CN",
    "name:zho_x_preferred":[
        "\u5eb7\u5df4\u6751"
    ],
    "wof:name":"Kangbacun",
    "wof:placetype":"locality"
},
  "geometry": {"coordinates":[90.57605,28.90502],"type":"Point"}
}