{
  "type": "Feature",
  "properties": {
    "gn:admin1_code":"7",
    "gn:asciiname":"Shanglou",
    "gn:country_code":"CN",
    "gn:dem":705,
    "gn:feature_class":"P",
    "gn:feature_code":"PPL",
    "gn:name":"Shanglou",
    "gn:population":0,
    "gn:timezone":"Asia/Shanghai",
    "iso:country":"CN",
    "name:zho_x_preferred":[
        "\u4e0a\u697c"
    ],
    "wof:name":"Shanglou",
    "wof:placetype":"locality"
},
  "geometry": {"coordinates":[117.17846000000002,24.55729],"type":"Point"}
}