{
  "type": "Feature",
  "properties": {
    "gn:admin1_code":"25",
    "gn:asciiname":"Zhangjiapuwang",
    "gn:country_code":"CN",
    "gn:dem":179,
    "gn:feature_class":"P",
    "gn:feature_code":"PPL",
    "gn:name":"Zhangjiapuwang",
    "gn:population":0,
    "gn:timezone":"Asia/Shanghai",
    "iso:country":"CN",
    "name:zho_x_preferred":[
        "\u5f20\u5bb6\u84b2\u6c6a"
    ],
    "wof:name":"Zhangjiapuwang",
    "wof:placetype":"locality"
},
  "geometry": {"coordinates":[119.09699999999999,35.3491],"type":"Point"}
}