{
  "type": "Feature",
  "properties": {
    "gn:admin1_code":"16.0",
    "gn:asciiname":"Tuogua",
    "gn:country_code":"CN",
    "gn:dem":280,
    "gn:feature_class":"P",
    "gn:feature_code":"PPL",
    "gn:name":"Tuogua",
    "gn:population":0,
    "gn:timezone":"Asia/Shanghai",
    "iso:country":"CN",
    "name:zho_x_preferred":[
        "\u9a6e\u74dc"
    ],
    "wof:name":"Tuogua",
    "wof:placetype":"locality"
},
  "geometry": {"coordinates":[106.961,23.3857],"type":"Point"}
}