{
  "type": "Feature",
  "properties": {
    "gn:admin1_code":"15.0",
    "gn:asciiname":"Changwanli",
    "gn:country_code":"CN",
    "gn:dem":1917,
    "gn:feature_class":"P",
    "gn:feature_code":"PPL",
    "gn:name":"Changwanli",
    "gn:population":0,
    "gn:timezone":"Asia/Shanghai",
    "iso:country":"CN",
    "name:zho_x_preferred":[
        "\u957f\u6e7e\u91cc"
    ],
    "wof:name":"Changwanli",
    "wof:placetype":"locality"
},
  "geometry": {"coordinates":[104.59,32.784],"type":"Point"}
}