{
  "type": "Feature",
  "properties": {
    "gn:admin1_code":"15.0",
    "gn:asciiname":"Zhangjiayuan",
    "gn:country_code":"CN",
    "gn:dem":1685,
    "gn:feature_class":"P",
    "gn:feature_code":"PPL",
    "gn:name":"Zhangjiayuan",
    "gn:population":0,
    "gn:timezone":"Asia/Shanghai",
    "iso:country":"CN",
    "name:und_x_variant":[
        "\u5f20\u5bb6\u586c"
    ],
    "wof:name":"Zhangjiayuan",
    "wof:placetype":"locality"
},
  "geometry": {"coordinates":[107.35453,36.86941],"type":"Point"}
}