{
  "type": "Feature",
  "properties": {
    "gn:admin1_code":"9",
    "gn:asciiname":"Xingzhuang",
    "gn:country_code":"CN",
    "gn:dem":286,
    "gn:feature_class":"P",
    "gn:feature_code":"PPL",
    "gn:name":"Xingzhuang",
    "gn:population":0,
    "gn:timezone":"Asia/Shanghai",
    "iso:country":"CN",
    "name:und_x_variant":[
        "Xingjiazhuang"
    ],
    "name:zho_x_preferred":[
        "\u90a2\u5e84"
    ],
    "wof:name":"Xingzhuang",
    "wof:placetype":"locality"
},
  "geometry": {"coordinates":[112.24306,34.31111],"type":"Point"}
}