{
  "type": "Feature",
  "properties": {
    "gn:admin1_code":"11",
    "gn:asciiname":"Liandonggang",
    "gn:country_code":"CN",
    "gn:dem":348,
    "gn:feature_class":"P",
    "gn:feature_code":"PPLA4",
    "gn:name":"Liandonggang",
    "gn:population":0,
    "gn:timezone":"Asia/Shanghai",
    "iso:country":"CN",
    "name:und_x_variant":[
        "Liandong",
        "Liandong Xiang",
        "Liandonggang"
    ],
    "name:zho_x_preferred":[
        "\u8fde\u6d1e\u5c97"
    ],
    "wof:name":"Liandonggang",
    "wof:placetype":"locality"
},
  "geometry": {"coordinates":[109.88227000000001,29.00751],"type":"Point"}
}