{
  "type": "Feature",
  "properties": {
    "gn:admin1_code":"4.0",
    "gn:asciiname":"Xilinzhuang",
    "gn:country_code":"CN",
    "gn:dem":28,
    "gn:feature_class":"P",
    "gn:feature_code":"PPL",
    "gn:name":"Xilinzhuang",
    "gn:population":0,
    "gn:timezone":"Asia/Shanghai",
    "iso:country":"CN",
    "name:zho_x_preferred":[
        "\u897f\u6797\u5e84"
    ],
    "wof:name":"Xilinzhuang",
    "wof:placetype":"locality"
},
  "geometry": {"coordinates":[118.91594000000001,32.96162],"type":"Point"}
}