{
  "type": "Feature",
  "properties": {
    "gn:admin1_code":"30",
    "gn:asciiname":"Guitou",
    "gn:country_code":"CN",
    "gn:dem":79,
    "gn:feature_class":"P",
    "gn:feature_code":"PPLA4",
    "gn:name":"Guitou",
    "gn:population":0,
    "gn:timezone":"Asia/Shanghai",
    "iso:country":"CN",
    "name:und_x_variant":[
        "Kuei-t\u2019ou",
        "Kuei-t\u2019ou-hs\u00fc",
        "Guitou",
        "Guitou Zhen",
        "\u6842\u5934\u9547"
    ],
    "name:zho_x_preferred":[
        "\u6842\u5934"
    ],
    "wof:name":"Guitou",
    "wof:placetype":"locality"
},
  "geometry": {"coordinates":[113.41667,24.93333],"type":"Point"}
}