{
  "type": "Feature",
  "properties": {
    "gn:admin1_code":"30.0",
    "gn:asciiname":"Pantiandong",
    "gn:country_code":"CN",
    "gn:dem":224,
    "gn:feature_class":"P",
    "gn:feature_code":"PPL",
    "gn:name":"Pantiandong",
    "gn:population":0,
    "gn:timezone":"Asia/Shanghai",
    "iso:country":"CN",
    "name:zho_x_preferred":[
        "Pantiandong"
    ],
    "name:zho_x_variant":[
        "\u7554\u7530\u6d1e"
    ],
    "wof:name":"Pantiandong",
    "wof:placetype":"locality"
},
  "geometry": {"coordinates":[112.21778,25.04111],"type":"Point"}
}