{
  "type": "Feature",
  "properties": {
    "gn:admin1_code":"25.0",
    "gn:asciiname":"Zhongce",
    "gn:cc2":"CN",
    "gn:country_code":"CN",
    "gn:dem":96,
    "gn:feature_class":"P",
    "gn:feature_code":"PPL",
    "gn:name":"Zhongce",
    "gn:population":0,
    "gn:timezone":"Asia/Shanghai",
    "iso:country":"CN",
    "name:und_x_variant":[
        "Chung-t\u2019se",
        "Zhongce"
    ],
    "wof:name":"Zhongce",
    "wof:placetype":"locality"
},
  "geometry": {"coordinates":[117.23333,35.71667],"type":"Point"}
}