{
  "type": "Feature",
  "properties": {
    "gn:admin1_code":"10.0",
    "gn:asciiname":"Haishentang",
    "gn:country_code":"CN",
    "gn:dem":38,
    "gn:feature_class":"P",
    "gn:feature_code":"PPL",
    "gn:name":"Haishentang",
    "gn:population":0,
    "gn:timezone":"Asia/Shanghai",
    "iso:country":"CN",
    "name:zho_x_preferred":[
        "\u6d77\u6df1\u5858"
    ],
    "wof:name":"Haishentang",
    "wof:placetype":"locality"
},
  "geometry": {"coordinates":[116.01600000000001,39.42594],"type":"Point"}
}