{
  "type": "Feature",
  "properties": {
    "gn:admin1_code":"30",
    "gn:asciiname":"Xinniangshan",
    "gn:country_code":"CN",
    "gn:dem":379,
    "gn:feature_class":"P",
    "gn:feature_code":"PPL",
    "gn:name":"Xinniangshan",
    "gn:population":0,
    "gn:timezone":"Asia/Shanghai",
    "iso:country":"CN",
    "name:zho_x_preferred":[
        "\u65b0\u5a18\u5c71"
    ],
    "wof:name":"Xinniangshan",
    "wof:placetype":"locality"
},
  "geometry": {"coordinates":[116.18735,24.7925],"type":"Point"}
}