{
  "type": "Feature",
  "properties": {
    "gn:admin1_code":"10",
    "gn:asciiname":"Jinqianmoli",
    "gn:country_code":"CN",
    "gn:dem":1097,
    "gn:feature_class":"P",
    "gn:feature_code":"PPL",
    "gn:name":"Jinqianmoli",
    "gn:population":0,
    "gn:timezone":"Asia/Shanghai",
    "iso:country":"CN",
    "name:zho_x_preferred":[
        "\u91d1\u94b1\u83ab\u91cc"
    ],
    "wof:name":"Jinqianmoli",
    "wof:placetype":"locality"
},
  "geometry": {"coordinates":[117.75817000000001,42.02981],"type":"Point"}
}