{
  "type": "Feature",
  "properties": {
    "gn:country":"CN",
    "gn:fcode":"PPL",
    "gn:pop":0,
    "iso:country":"CN",
    "name:unk_x_variant":[
        "Yushu"
    ],
    "qs:name":"\u7ed3\u53e4",
    "qs:name_adm0":"\u4e2d\u570b",
    "qs:name_adm1":"\u9752\u6d77\u7701",
    "qs:photos":151,
    "qs:photos_1k":31,
    "qs:photos_9k":1,
    "qs:photos_9r":4,
    "qs:photos_all":151,
    "qs:photos_sr":4,
    "qs:placetype":"Town",
    "qs:pop_sr":"4",
    "wof:name":"\u7ed3\u53e4",
    "wof:placetype":"locality",
    "wof:population":0
},
  "geometry": {"coordinates":[97.00893000000001,33.00118],"type":"Point"}
}