{
  "type": "Feature",
  "properties": {
    "gn:admin1_code":"15.0",
    "gn:asciiname":"Yaomaodong",
    "gn:country_code":"CN",
    "gn:dem":2093,
    "gn:feature_class":"P",
    "gn:feature_code":"PPL",
    "gn:name":"Yaomaodong",
    "gn:population":0,
    "gn:timezone":"Asia/Shanghai",
    "iso:country":"CN",
    "name:zho_x_preferred":[
        "\u5996\u6bdb\u6d1e"
    ],
    "wof:name":"Yaomaodong",
    "wof:placetype":"locality"
},
  "geometry": {"coordinates":[103.143,36.4493],"type":"Point"}
}