{
  "type": "Feature",
  "properties": {
    "gn:admin1_code":"15.0",
    "gn:asciiname":"Qiabu",
    "gn:country_code":"CN",
    "gn:dem":2701,
    "gn:feature_class":"P",
    "gn:feature_code":"PPL",
    "gn:name":"Qiabu",
    "gn:population":0,
    "gn:timezone":"Asia/Shanghai",
    "iso:country":"CN",
    "name:und_x_variant":[
        "\u6070\u5e03"
    ],
    "wof:name":"Qiabu",
    "wof:placetype":"locality"
},
  "geometry": {"coordinates":[103.94302,34.81512],"type":"Point"}
}