{
  "type": "Feature",
  "properties": {
    "gn:admin1_code":"5.0",
    "gn:asciiname":"Renshucun",
    "gn:country_code":"CN",
    "gn:dem":292,
    "gn:feature_class":"P",
    "gn:feature_code":"PPL",
    "gn:name":"Renshucun",
    "gn:population":0,
    "gn:timezone":"Asia/Shanghai",
    "iso:country":"CN",
    "name:zho_x_preferred":[
        "\u4ec1\u6055\u6751"
    ],
    "wof:name":"Renshucun",
    "wof:placetype":"locality"
},
  "geometry": {"coordinates":[125.25941,42.8459],"type":"Point"}
}