{
  "type": "Feature",
  "properties": {
    "gn:admin1_code":"30.0",
    "gn:asciiname":"Haokeng",
    "gn:country_code":"CN",
    "gn:dem":40,
    "gn:feature_class":"P",
    "gn:feature_code":"PPL",
    "gn:name":"Haokeng",
    "gn:population":0,
    "gn:timezone":"Asia/Shanghai",
    "iso:country":"CN",
    "name:zho_x_preferred":[
        "\u597d\u5751"
    ],
    "wof:name":"Haokeng",
    "wof:placetype":"locality"
},
  "geometry": {"coordinates":[112.32578999999998,22.88697],"type":"Point"}
}