{
  "type": "Feature",
  "properties": {
    "gn:admin1_code":"15.0",
    "gn:asciiname":"Nanhe",
    "gn:country_code":"CN",
    "gn:dem":1605,
    "gn:feature_class":"P",
    "gn:feature_code":"PPL",
    "gn:name":"Nanhe",
    "gn:population":0,
    "gn:timezone":"Asia/Shanghai",
    "iso:country":"CN",
    "name:zho_x_preferred":[
        "\u5357\u6cb3"
    ],
    "wof:name":"Nanhe",
    "wof:placetype":"locality"
},
  "geometry": {"coordinates":[102.52,37.9457],"type":"Point"}
}