{
  "type": "Feature",
  "properties": {
    "gn:admin1_code":"1.0",
    "gn:asciiname":"Gouyacun",
    "gn:country_code":"CN",
    "gn:dem":26,
    "gn:feature_class":"P",
    "gn:feature_code":"PPL",
    "gn:name":"Gouyacun",
    "gn:population":0,
    "gn:timezone":"Asia/Shanghai",
    "iso:country":"CN",
    "name:zho_x_preferred":[
        "\u6c9f\u6daf\u6751"
    ],
    "wof:name":"Gouyacun",
    "wof:placetype":"locality"
},
  "geometry": {"coordinates":[117.61853000000001,33.73328],"type":"Point"}
}