{
  "type": "Feature",
  "properties": {
    "gn:admin1_code":"7.0",
    "gn:asciiname":"Xuefeng",
    "gn:country_code":"CN",
    "gn:dem":405,
    "gn:feature_class":"P",
    "gn:feature_code":"PPL",
    "gn:name":"Xuefeng",
    "gn:population":0,
    "gn:timezone":"Asia/Shanghai",
    "iso:country":"CN",
    "name:zho_x_preferred":[
        "\u96ea\u5cf0"
    ],
    "wof:name":"Xuefeng",
    "wof:placetype":"locality"
},
  "geometry": {"coordinates":[118.22319,24.90747],"type":"Point"}
}