{
  "type": "Feature",
  "properties": {
    "gn:admin1_code":"32.0",
    "gn:asciiname":"Kada",
    "gn:country_code":"CN",
    "gn:dem":3430,
    "gn:feature_class":"P",
    "gn:feature_code":"PPL",
    "gn:name":"Kada",
    "gn:population":0,
    "gn:timezone":"Asia/Shanghai",
    "iso:country":"CN",
    "name:zho_x_preferred":[
        "\u5361\u8fbe"
    ],
    "wof:name":"Kada",
    "wof:placetype":"locality"
},
  "geometry": {"coordinates":[100.095,30.4193],"type":"Point"}
}