{
  "type": "Feature",
  "properties": {
    "gn:admin1_code":"11.0",
    "gn:asciiname":"Wujiapu",
    "gn:country_code":"CN",
    "gn:dem":77,
    "gn:feature_class":"P",
    "gn:feature_code":"PPL",
    "gn:name":"Wujiapu",
    "gn:population":0,
    "gn:timezone":"Asia/Shanghai",
    "iso:country":"CN",
    "name:zho_x_preferred":[
        "\u90ac\u5bb6\u94fa"
    ],
    "wof:name":"Wujiapu",
    "wof:placetype":"locality"
},
  "geometry": {"coordinates":[111.74803,28.82596],"type":"Point"}
}