{
  "type": "Feature",
  "properties": {
    "gn:admin1_code":"32.0",
    "gn:asciiname":"Longtuocao",
    "gn:country_code":"CN",
    "gn:dem":434,
    "gn:feature_class":"P",
    "gn:feature_code":"PPL",
    "gn:name":"Longtuocao",
    "gn:population":0,
    "gn:timezone":"Asia/Shanghai",
    "iso:country":"CN",
    "name:zho_x_preferred":[
        "\u9f99\u62d6\u6f15"
    ],
    "wof:name":"Longtuocao",
    "wof:placetype":"locality"
},
  "geometry": {"coordinates":[104.282,28.8502],"type":"Point"}
}