{
  "type": "Feature",
  "properties": {
    "gn:admin1_code":"26",
    "gn:asciiname":"Beijingtou",
    "gn:cc2":"CN",
    "gn:country_code":"CN",
    "gn:dem":790,
    "gn:feature_class":"P",
    "gn:feature_code":"PPL",
    "gn:name":"Beijingtou",
    "gn:population":0,
    "gn:timezone":"Asia/Shanghai",
    "iso:country":"CN",
    "name:und_x_variant":[
        "Pei-ching-t\u2019ou",
        "Beijingtou"
    ],
    "wof:name":"Beijingtou",
    "wof:placetype":"locality"
},
  "geometry": {"coordinates":[109.58083000000001,35.19389],"type":"Point"}
}