{
  "type": "Feature",
  "properties": {
    "gn:admin1_code":"30",
    "gn:asciiname":"Fangpocun",
    "gn:country_code":"CN",
    "gn:dem":7,
    "gn:feature_class":"P",
    "gn:feature_code":"PPL",
    "gn:name":"Fangpocun",
    "gn:population":0,
    "gn:timezone":"Asia/Urumqi",
    "iso:country":"CN",
    "name:zho_x_preferred":[
        "\u653e\u5761\u6751"
    ],
    "wof:name":"Fangpocun",
    "wof:placetype":"locality"
},
  "geometry": {"coordinates":[109.92383999999998,20.25931],"type":"Point"}
}