{
  "type": "Feature",
  "properties": {
    "gn:admin1_code":"10",
    "gn:asciiname":"Shangzhudian",
    "gn:country_code":"CN",
    "gn:dem":439,
    "gn:feature_class":"P",
    "gn:feature_code":"PPL",
    "gn:name":"Shangzhudian",
    "gn:population":0,
    "gn:timezone":"Asia/Shanghai",
    "iso:country":"CN",
    "name:zho_x_preferred":[
        "\u4e0a\u732a\u5e97"
    ],
    "wof:name":"Shangzhudian",
    "wof:placetype":"locality"
},
  "geometry": {"coordinates":[117.51098,41.00311],"type":"Point"}
}