{
  "type": "Feature",
  "properties": {
    "gn:admin1_code":"24.0",
    "gn:asciiname":"Aoziyuan",
    "gn:country_code":"CN",
    "gn:dem":1279,
    "gn:feature_class":"P",
    "gn:feature_code":"PPL",
    "gn:name":"Aoziyuan",
    "gn:population":0,
    "gn:timezone":"Asia/Shanghai",
    "iso:country":"CN",
    "name:zho_x_preferred":[
        "\u6556\u5b50\u539f"
    ],
    "wof:name":"Aoziyuan",
    "wof:placetype":"locality"
},
  "geometry": {"coordinates":[110.73184999999999,36.29621],"type":"Point"}
}