{
  "type": "Feature",
  "properties": {
    "gn:admin1_code":"30",
    "gn:asciiname":"Fenghuangxu",
    "gn:country_code":"CN",
    "gn:dem":20,
    "gn:feature_class":"P",
    "gn:feature_code":"PPL",
    "gn:name":"Fenghuangxu",
    "gn:population":0,
    "gn:timezone":"Asia/Shanghai",
    "iso:country":"CN",
    "name:und_x_variant":[
        "Fenghuangwei",
        "Fenghuangxu"
    ],
    "name:zho_x_preferred":[
        "\u51e4\u51f0\u5729"
    ],
    "wof:name":"Fenghuangxu",
    "wof:placetype":"locality"
},
  "geometry": {"coordinates":[113.82527,22.69729],"type":"Point"}
}