{
  "type": "Feature",
  "properties": {
    "gn:admin1_code":"7",
    "gn:asciiname":"Huntou",
    "gn:country_code":"CN",
    "gn:dem":261,
    "gn:feature_class":"P",
    "gn:feature_code":"PPL",
    "gn:name":"Huntou",
    "gn:population":0,
    "gn:timezone":"Asia/Shanghai",
    "iso:country":"CN",
    "name:und_x_variant":[
        "\u6d51\u5934"
    ],
    "wof:name":"Huntou",
    "wof:placetype":"locality"
},
  "geometry": {"coordinates":[118.86556000000002,27.59194],"type":"Point"}
}