{
  "type": "Feature",
  "properties": {
    "gn:admin1_code":"7.0",
    "gn:asciiname":"Yangxi",
    "gn:country_code":"CN",
    "gn:dem":10,
    "gn:feature_class":"P",
    "gn:feature_code":"PPL",
    "gn:name":"Yangxi",
    "gn:population":0,
    "gn:timezone":"Asia/Shanghai",
    "iso:country":"CN",
    "name:ceb_x_preferred":[
        "Yangxi"
    ],
    "name:deu_x_preferred":[
        "Yangxi"
    ],
    "name:zho_x_preferred":[
        "\u6d0b\u897f"
    ],
    "name:zho_x_variant":[
        "\u6d0b\u6eaa\u9547"
    ],
    "wof:name":"Yangxi",
    "wof:placetype":"locality"
},
  "geometry": {"coordinates":[119.61654,26.22222],"type":"Point"}
}