{
  "type": "Feature",
  "properties": {
    "gn:admin1_code":"32.0",
    "gn:asciiname":"Luoxueri",
    "gn:country_code":"CN",
    "gn:dem":3567,
    "gn:feature_class":"P",
    "gn:feature_code":"PPL",
    "gn:name":"Luoxueri",
    "gn:population":0,
    "gn:timezone":"Asia/Shanghai",
    "iso:country":"CN",
    "name:zho_x_preferred":[
        "\u6d1b\u5b66\u65e5"
    ],
    "wof:name":"Luoxueri",
    "wof:placetype":"locality"
},
  "geometry": {"coordinates":[100.71599999999999,32.5107],"type":"Point"}
}