{
  "type": "Feature",
  "properties": {
    "gn:admin1_code":"14.0",
    "gn:asciiname":"Duozhaji",
    "gn:country_code":"CN",
    "gn:dem":4364,
    "gn:feature_class":"P",
    "gn:feature_code":"PPL",
    "gn:name":"Duozhaji",
    "gn:population":0,
    "gn:timezone":"Asia/Urumqi",
    "iso:country":"CN",
    "name:zho_x_preferred":[
        "\u591a\u624e\u7ed9"
    ],
    "wof:name":"Duozhaji",
    "wof:placetype":"locality"
},
  "geometry": {"coordinates":[92.86405000000001,31.69191],"type":"Point"}
}