{
  "type": "Feature",
  "properties": {
    "gn:admin1_code":"12.0",
    "gn:asciiname":"Xiongjiapo",
    "gn:country_code":"CN",
    "gn:dem":25,
    "gn:feature_class":"P",
    "gn:feature_code":"PPL",
    "gn:name":"Xiongjiapo",
    "gn:population":0,
    "gn:timezone":"Asia/Shanghai",
    "iso:country":"CN",
    "name:und_x_variant":[
        "\u718a\u5bb6\u5761"
    ],
    "wof:name":"Xiongjiapo",
    "wof:placetype":"locality"
},
  "geometry": {"coordinates":[114.26843,30.44886],"type":"Point"}
}