{
  "type": "Feature",
  "properties": {
    "gn:admin1_code":"19.0",
    "gn:asciiname":"Sunjia Buzi",
    "gn:country_code":"CN",
    "gn:dem":347,
    "gn:feature_class":"P",
    "gn:feature_code":"PPL",
    "gn:name":"Sunjia Buzi",
    "gn:population":0,
    "gn:timezone":"Asia/Shanghai",
    "iso:country":"CN",
    "name:und_x_variant":[
        "Sunjiabaozi",
        "Sunjia Buzi"
    ],
    "name:zho_x_preferred":[
        "\u5b59\u5bb6\u5821\u5b50"
    ],
    "wof:name":"Sunjia Buzi",
    "wof:placetype":"locality"
},
  "geometry": {"coordinates":[124.97937,40.77443],"type":"Point"}
}