{
  "type": "Feature",
  "properties": {
    "gn:admin1_code":"25.0",
    "gn:asciiname":"Xuwacun",
    "gn:country_code":"CN",
    "gn:dem":33,
    "gn:feature_class":"P",
    "gn:feature_code":"PPL",
    "gn:name":"Xuwacun",
    "gn:population":0,
    "gn:timezone":"Asia/Shanghai",
    "iso:country":"CN",
    "name:zho_x_preferred":[
        "\u5f90\u6d3c\u6751"
    ],
    "wof:name":"Xuwacun",
    "wof:placetype":"locality"
},
  "geometry": {"coordinates":[116.51347,36.59517],"type":"Point"}
}