{
  "type": "Feature",
  "properties": {
    "gn:admin1_code":"25",
    "gn:asciiname":"Yanjiamatou",
    "gn:country_code":"CN",
    "gn:dem":25,
    "gn:feature_class":"P",
    "gn:feature_code":"PPL",
    "gn:name":"Yanjiamatou",
    "gn:population":0,
    "gn:timezone":"Asia/Shanghai",
    "iso:country":"CN",
    "name:zho_x_preferred":[
        "\u95eb\u5bb6\u7801\u5934"
    ],
    "wof:name":"Yanjiamatou",
    "wof:placetype":"locality"
},
  "geometry": {"coordinates":[117.446,36.8318],"type":"Point"}
}