{
  "type": "Feature",
  "properties": {
    "gn:admin1_code":"5.0",
    "gn:asciiname":"Bali Dingzi",
    "gn:country_code":"CN",
    "gn:dem":219,
    "gn:feature_class":"P",
    "gn:feature_code":"PPL",
    "gn:name":"Bali Dingzi",
    "gn:population":0,
    "gn:timezone":"Asia/Shanghai",
    "iso:country":"CN",
    "name:zho_x_preferred":[
        "\u516b\u91cc\u9876\u5b50"
    ],
    "wof:name":"Bali Dingzi",
    "wof:placetype":"locality"
},
  "geometry": {"coordinates":[126.98802000000001,44.59041],"type":"Point"}
}