{
  "type": "Feature",
  "properties": {
    "gn:admin1_code":"3.0",
    "gn:asciiname":"Dahelin",
    "gn:country_code":"CN",
    "gn:dem":312,
    "gn:feature_class":"P",
    "gn:feature_code":"PPL",
    "gn:name":"Dahelin",
    "gn:population":0,
    "gn:timezone":"Asia/Shanghai",
    "iso:country":"CN",
    "name:und_x_variant":[
        "\u5927\u4f55\u6797"
    ],
    "wof:name":"Dahelin",
    "wof:placetype":"locality"
},
  "geometry": {"coordinates":[115.20296,25.47665],"type":"Point"}
}