{
  "type": "Feature",
  "properties": {
    "gn:admin1_code":"16.0",
    "gn:asciiname":"Liangmupo",
    "gn:country_code":"CN",
    "gn:dem":96,
    "gn:feature_class":"P",
    "gn:feature_code":"PPL",
    "gn:name":"Liangmupo",
    "gn:population":0,
    "gn:timezone":"Asia/Shanghai",
    "iso:country":"CN",
    "name:zho_x_preferred":[
        "\u4e24\u6728\u5761"
    ],
    "wof:name":"Liangmupo",
    "wof:placetype":"locality"
},
  "geometry": {"coordinates":[108.081,22.9614],"type":"Point"}
}