{
  "type": "Feature",
  "properties": {
    "gn:admin1_code":"18",
    "gn:asciiname":"Modaoshi",
    "gn:country_code":"CN",
    "gn:dem":1669,
    "gn:feature_class":"P",
    "gn:feature_code":"PPL",
    "gn:name":"Modaoshi",
    "gn:population":0,
    "gn:timezone":"Asia/Shanghai",
    "iso:country":"CN",
    "name:zho_x_preferred":[
        "\u78e8\u5200\u77f3"
    ],
    "wof:name":"Modaoshi",
    "wof:placetype":"locality"
},
  "geometry": {"coordinates":[104.96899999999999,25.358],"type":"Point"}
}