{
  "type": "Feature",
  "properties": {
    "gn:admin1_code":"33.0",
    "gn:asciiname":"Zongshu",
    "gn:country_code":"CN",
    "gn:dem":701,
    "gn:feature_class":"P",
    "gn:feature_code":"PPL",
    "gn:name":"Zongshu",
    "gn:population":0,
    "gn:timezone":"Asia/Shanghai",
    "iso:country":"CN",
    "name:zho_x_preferred":[
        "\u679e\u6811"
    ],
    "wof:name":"Zongshu",
    "wof:placetype":"locality"
},
  "geometry": {"coordinates":[108.93048,31.29633],"type":"Point"}
}