{
  "type": "Feature",
  "properties": {
    "gn:admin1_code":"16.0",
    "gn:asciiname":"Qiaosang",
    "gn:country_code":"CN",
    "gn:dem":142,
    "gn:feature_class":"P",
    "gn:feature_code":"PPL",
    "gn:name":"Qiaosang",
    "gn:population":0,
    "gn:timezone":"Asia/Shanghai",
    "iso:country":"CN",
    "name:zho_x_preferred":[
        "\u6865\u6851"
    ],
    "wof:name":"Qiaosang",
    "wof:placetype":"locality"
},
  "geometry": {"coordinates":[108.13500000000001,23.0363],"type":"Point"}
}