{
  "type": "Feature",
  "properties": {
    "gn:admin1_code":"26.0",
    "gn:asciiname":"Renjiayuan",
    "gn:country_code":"CN",
    "gn:dem":1039,
    "gn:feature_class":"P",
    "gn:feature_code":"PPL",
    "gn:name":"Renjiayuan",
    "gn:population":0,
    "gn:timezone":"Asia/Shanghai",
    "iso:country":"CN",
    "name:zho_x_preferred":[
        "\u4ec1\u5bb6\u586c"
    ],
    "wof:name":"Renjiayuan",
    "wof:placetype":"locality"
},
  "geometry": {"coordinates":[109.35533999999998,35.15108],"type":"Point"}
}