{
  "type": "Feature",
  "properties": {
    "gn:admin1_code":"12.0",
    "gn:asciiname":"Zhoujiagang",
    "gn:country_code":"CN",
    "gn:dem":63,
    "gn:feature_class":"P",
    "gn:feature_code":"PPL",
    "gn:name":"Zhoujiagang",
    "gn:population":0,
    "gn:timezone":"Asia/Shanghai",
    "iso:country":"CN",
    "name:zho_x_preferred":[
        "Zhoujiagang"
    ],
    "name:zho_x_variant":[
        "\u5468\u5bb6\u5c97"
    ],
    "wof:name":"Zhoujiagang",
    "wof:placetype":"locality"
},
  "geometry": {"coordinates":[111.95278999999999,30.93778],"type":"Point"}
}