{
  "type": "Feature",
  "properties": {
    "gn:admin1_code":"15.0",
    "gn:asciiname":"Wangshanpan",
    "gn:country_code":"CN",
    "gn:dem":1792,
    "gn:feature_class":"P",
    "gn:feature_code":"PPL",
    "gn:name":"Wangshanpan",
    "gn:population":0,
    "gn:timezone":"Asia/Shanghai",
    "iso:country":"CN",
    "name:und_x_variant":[
        "\u738b\u5c71\u7554"
    ],
    "wof:name":"Wangshanpan",
    "wof:placetype":"locality"
},
  "geometry": {"coordinates":[106.84043,36.60472],"type":"Point"}
}