{
  "type": "Feature",
  "properties": {
    "gn:admin1_code":"25",
    "gn:asciiname":"Yingzi",
    "gn:country_code":"CN",
    "gn:dem":41,
    "gn:feature_class":"P",
    "gn:feature_code":"PPL",
    "gn:name":"Yingzi",
    "gn:population":0,
    "gn:timezone":"Asia/Shanghai",
    "iso:country":"CN",
    "name:zho_x_preferred":[
        "\u8425\u5b50"
    ],
    "wof:name":"Yingzi",
    "wof:placetype":"locality"
},
  "geometry": {"coordinates":[115.61221999999999,36.73311],"type":"Point"}
}