{
  "type": "Feature",
  "properties": {
    "gn:admin1_code":"24",
    "gn:asciiname":"Hekou",
    "gn:cc2":"CN",
    "gn:country_code":"CN",
    "gn:dem":999,
    "gn:feature_class":"P",
    "gn:feature_code":"PPL",
    "gn:name":"Hekou",
    "gn:population":0,
    "gn:timezone":"Asia/Shanghai",
    "iso:country":"CN",
    "name:ceb_x_preferred":[
        "Hekou"
    ],
    "name:deu_x_preferred":[
        "Hekou"
    ],
    "name:fra_x_preferred":[
        "Hekou"
    ],
    "name:nor_x_preferred":[
        "Hekou"
    ],
    "name:rus_x_preferred":[
        "\u0425\u044d\u043a\u043e\u0443"
    ],
    "name:swe_x_preferred":[
        "Hekou"
    ],
    "name:und_x_variant":[
        "Ho-k\u2019ou-chen",
        "Ho-k\u2019ou",
        "Hekou"
    ],
    "wof:name":"Hekou",
    "wof:placetype":"locality"
},
  "geometry": {"coordinates":[112.20944,37.92361],"type":"Point"}
}