{
  "type": "Feature",
  "properties": {
    "gn:admin1_code":"12.0",
    "gn:asciiname":"Dazhuyuan",
    "gn:country_code":"CN",
    "gn:dem":588,
    "gn:feature_class":"P",
    "gn:feature_code":"PPL",
    "gn:name":"Dazhuyuan",
    "gn:population":0,
    "gn:timezone":"Asia/Shanghai",
    "iso:country":"CN",
    "name:zho_x_preferred":[
        "\u5927\u7af9\u56ed"
    ],
    "wof:name":"Dazhuyuan",
    "wof:placetype":"locality"
},
  "geometry": {"coordinates":[110.24566000000002,32.69247],"type":"Point"}
}