{
  "type": "Feature",
  "properties": {
    "gn:admin1_code":"15.0",
    "gn:asciiname":"Longmagou",
    "gn:country_code":"CN",
    "gn:dem":2729,
    "gn:feature_class":"P",
    "gn:feature_code":"PPL",
    "gn:name":"Longmagou",
    "gn:population":0,
    "gn:timezone":"Asia/Shanghai",
    "iso:country":"CN",
    "name:und_x_variant":[
        "\u9f99\u9a6c\u6c9f"
    ],
    "wof:name":"Longmagou",
    "wof:placetype":"locality"
},
  "geometry": {"coordinates":[103.5613,34.62508],"type":"Point"}
}