{
  "type": "Feature",
  "properties": {
    "gn:admin1_code":"26.0",
    "gn:asciiname":"Qingshuigou",
    "gn:country_code":"CN",
    "gn:dem":1469,
    "gn:feature_class":"P",
    "gn:feature_code":"PPL",
    "gn:name":"Qingshuigou",
    "gn:population":0,
    "gn:timezone":"Asia/Shanghai",
    "iso:country":"CN",
    "name:und_x_variant":[
        "\u6e05\u6c34\u6c9f"
    ],
    "wof:name":"Qingshuigou",
    "wof:placetype":"locality"
},
  "geometry": {"coordinates":[107.9943,36.81374],"type":"Point"}
}