{
  "type": "Feature",
  "properties": {
    "gn:admin1_code":"24.0",
    "gn:asciiname":"Xixiaoping",
    "gn:country_code":"CN",
    "gn:dem":1051,
    "gn:feature_class":"P",
    "gn:feature_code":"PPL",
    "gn:name":"Xixiaoping",
    "gn:population":0,
    "gn:timezone":"Asia/Shanghai",
    "iso:country":"CN",
    "name:und_x_variant":[
        "Hsi-hsiao-p\u2019ing",
        "Xixiaoping"
    ],
    "name:zho_x_preferred":[
        "\u897f\u5c0f\u576a"
    ],
    "wof:name":"Xixiaoping",
    "wof:placetype":"locality"
},
  "geometry": {"coordinates":[113.33523,38.09877],"type":"Point"}
}