{
  "type": "Feature",
  "properties": {
    "gn:admin1_code":"14.0",
    "gn:asciiname":"Dachige",
    "gn:country_code":"CN",
    "gn:dem":4017,
    "gn:feature_class":"P",
    "gn:feature_code":"PPL",
    "gn:name":"Dachige",
    "gn:population":0,
    "gn:timezone":"Asia/Urumqi",
    "iso:country":"CN",
    "name:zho_x_preferred":[
        "\u8fbe\u8fdf\u683c"
    ],
    "wof:name":"Dachige",
    "wof:placetype":"locality"
},
  "geometry": {"coordinates":[97.62636999999999,31.99619],"type":"Point"}
}