{
  "type": "Feature",
  "properties": {
    "gn:admin1_code":"12.0",
    "gn:asciiname":"Neihu",
    "gn:country_code":"CN",
    "gn:dem":122,
    "gn:feature_class":"P",
    "gn:feature_code":"PPLA4",
    "gn:name":"Neihu",
    "gn:population":0,
    "gn:timezone":"Asia/Shanghai",
    "iso:country":"CN",
    "name:und_x_variant":[
        "\u5185\u80e1",
        "Neihu Zhen",
        "\u5185\u80e1\u9547"
    ],
    "wof:name":"Neihu",
    "wof:placetype":"locality"
},
  "geometry": {"coordinates":[115.40552,29.71872],"type":"Point"}
}