{
  "type": "Feature",
  "properties": {
    "gn:admin1_code":"2.0",
    "gn:asciiname":"Meili",
    "gn:country_code":"CN",
    "gn:dem":20,
    "gn:feature_class":"P",
    "gn:feature_code":"PPL",
    "gn:name":"Meili",
    "gn:population":0,
    "gn:timezone":"Asia/Shanghai",
    "iso:country":"CN",
    "name:cat_x_preferred":[
        "Meili"
    ],
    "name:ces_x_preferred":[
        "Meili"
    ],
    "name:deu_x_preferred":[
        "Meili"
    ],
    "name:eus_x_preferred":[
        "Meili"
    ],
    "name:fra_x_preferred":[
        "Meili"
    ],
    "name:glg_x_preferred":[
        "Meili"
    ],
    "name:hrv_x_preferred":[
        "Meili"
    ],
    "name:kor_x_preferred":[
        "\uba54\uc77c\ub9ac"
    ],
    "name:nor_x_preferred":[
        "Meile"
    ],
    "name:por_x_preferred":[
        "Meili"
    ],
    "name:rus_x_preferred":[
        "\u041c\u0435\u0438\u043b\u0438"
    ],
    "name:spa_x_preferred":[
        "Meili"
    ],
    "name:srp_x_preferred":[
        "\u041c\u0435\u0458\u043b\u0438"
    ],
    "name:swe_x_preferred":[
        "Meile"
    ],
    "name:tur_x_preferred":[
        "Meili"
    ],
    "name:zho_x_preferred":[
        "\u6885\u91cc"
    ],
    "wof:name":"Meili",
    "wof:placetype":"locality"
},
  "geometry": {"coordinates":[120.46478999999999,29.98354],"type":"Point"}
}