{
  "type": "Feature",
  "properties": {
    "gn:admin1_code":"10.0",
    "gn:asciiname":"Xuezhuangzi",
    "gn:country_code":"CN",
    "gn:dem":10,
    "gn:feature_class":"P",
    "gn:feature_code":"PPL",
    "gn:name":"Xuezhuangzi",
    "gn:population":0,
    "gn:timezone":"Asia/Shanghai",
    "iso:country":"CN",
    "name:zho_x_preferred":[
        "\u8e05\u5e84\u5b50"
    ],
    "wof:name":"Xuezhuangzi",
    "wof:placetype":"locality"
},
  "geometry": {"coordinates":[116.952,38.207],"type":"Point"}
}