{
  "type": "Feature",
  "properties": {
    "gn:admin1_code":"2.0",
    "gn:asciiname":"Lujia",
    "gn:country_code":"CN",
    "gn:dem":7,
    "gn:feature_class":"P",
    "gn:feature_code":"PPL",
    "gn:name":"Lujia",
    "gn:population":0,
    "gn:timezone":"Asia/Shanghai",
    "iso:country":"CN",
    "name:und_x_variant":[
        "\u9646\u5bb6",
        "\u9646\u5bb6\u6751"
    ],
    "name:zho_x_preferred":[
        "Lujiacun"
    ],
    "wof:name":"Lujia",
    "wof:placetype":"locality"
},
  "geometry": {"coordinates":[119.91804,30.89573],"type":"Point"}
}