{
  "type": "Feature",
  "properties": {
    "gn:admin1_code":"32.0",
    "gn:asciiname":"Zhuba",
    "gn:country_code":"CN",
    "gn:dem":472,
    "gn:feature_class":"P",
    "gn:feature_code":"PPL",
    "gn:name":"Zhuba",
    "gn:population":0,
    "gn:timezone":"Asia/Shanghai",
    "iso:country":"CN",
    "name:zho_x_preferred":[
        "\u7af9\u575d"
    ],
    "wof:name":"Zhuba",
    "wof:placetype":"locality"
},
  "geometry": {"coordinates":[103.61351999999999,30.26639],"type":"Point"}
}