{
  "type": "Feature",
  "properties": {
    "gn:admin1_code":"4.0",
    "gn:asciiname":"Yuxiangcun",
    "gn:country_code":"CN",
    "gn:dem":20,
    "gn:feature_class":"P",
    "gn:feature_code":"PPL",
    "gn:name":"Yuxiangcun",
    "gn:population":0,
    "gn:timezone":"Asia/Shanghai",
    "iso:country":"CN",
    "name:zho_x_preferred":[
        "\u4f59\u5df7\u6751"
    ],
    "wof:name":"Yuxiangcun",
    "wof:placetype":"locality"
},
  "geometry": {"coordinates":[119.21832000000001,31.51031],"type":"Point"}
}