{
  "type": "Feature",
  "properties": {
    "gn:admin1_code":"32.0",
    "gn:asciiname":"Zhangguniangqiao",
    "gn:country_code":"CN",
    "gn:dem":1797,
    "gn:feature_class":"P",
    "gn:feature_code":"PPL",
    "gn:name":"Zhangguniangqiao",
    "gn:population":0,
    "gn:timezone":"Asia/Shanghai",
    "iso:country":"CN",
    "name:zho_x_preferred":[
        "\u5f20\u59d1\u5a18\u6865"
    ],
    "wof:name":"Zhangguniangqiao",
    "wof:placetype":"locality"
},
  "geometry": {"coordinates":[102.267,26.5209],"type":"Point"}
}