{
  "type": "Feature",
  "properties": {
    "gn:admin1_code":"32",
    "gn:asciiname":"Yingshui",
    "gn:country_code":"CN",
    "gn:dem":455,
    "gn:feature_class":"P",
    "gn:feature_code":"PPL",
    "gn:name":"Yingshui",
    "gn:population":0,
    "gn:timezone":"Asia/Shanghai",
    "iso:country":"CN",
    "name:und_x_variant":[
        "Yingshuichang",
        "Yingshui"
    ],
    "name:zho_x_preferred":[
        "\u8fce\u6c34"
    ],
    "wof:name":"Yingshui",
    "wof:placetype":"locality"
},
  "geometry": {"coordinates":[105.48860000000001,31.75027],"type":"Point"}
}