{
  "type": "Feature",
  "properties": {
    "gn:admin1_code":"25.0",
    "gn:asciiname":"Xilianchicun",
    "gn:country_code":"CN",
    "gn:dem":60,
    "gn:feature_class":"P",
    "gn:feature_code":"PPL",
    "gn:name":"Xilianchicun",
    "gn:population":0,
    "gn:timezone":"Asia/Shanghai",
    "iso:country":"CN",
    "name:zho_x_preferred":[
        "\u897f\u83b2\u6c60\u6751"
    ],
    "wof:name":"Xilianchicun",
    "wof:placetype":"locality"
},
  "geometry": {"coordinates":[119.34532,36.38951],"type":"Point"}
}