{
  "type": "Feature",
  "properties": {
    "gn:admin1_code":"30.0",
    "gn:asciiname":"Nazhou",
    "gn:country_code":"CN",
    "gn:dem":3,
    "gn:feature_class":"P",
    "gn:feature_code":"PPL",
    "gn:name":"Nazhou",
    "gn:population":0,
    "gn:timezone":"Asia/Shanghai",
    "iso:country":"CN",
    "name:zho_x_preferred":[
        "\u90a3\u6d32"
    ],
    "wof:name":"Nazhou",
    "wof:placetype":"locality"
},
  "geometry": {"coordinates":[112.79273999999999,22.03658],"type":"Point"}
}