{
  "type": "Feature",
  "properties": {
    "gn:admin1_code":"2.0",
    "gn:asciiname":"Banguyue",
    "gn:country_code":"CN",
    "gn:dem":164,
    "gn:feature_class":"P",
    "gn:feature_code":"PPL",
    "gn:name":"Banguyue",
    "gn:population":0,
    "gn:timezone":"Asia/Shanghai",
    "iso:country":"CN",
    "name:zho_x_preferred":[
        "\u534a\u53e4\u6708"
    ],
    "wof:name":"Banguyue",
    "wof:placetype":"locality"
},
  "geometry": {"coordinates":[119.38275,28.56524000000001],"type":"Point"}
}