{
  "type": "Feature",
  "properties": {
    "gn:admin1_code":"3.0",
    "gn:asciiname":"Dukou Lijia",
    "gn:country_code":"CN",
    "gn:dem":24,
    "gn:feature_class":"P",
    "gn:feature_code":"PPL",
    "gn:name":"Dukou Lijia",
    "gn:population":0,
    "gn:timezone":"Asia/Shanghai",
    "iso:country":"CN",
    "name:und_x_variant":[
        "\u6e21\u53e3\u674e\u5bb6"
    ],
    "wof:name":"Dukou Lijia",
    "wof:placetype":"locality"
},
  "geometry": {"coordinates":[116.40648,28.52128],"type":"Point"}
}