{
  "type": "Feature",
  "properties": {
    "gn:admin1_code":"26.0",
    "gn:asciiname":"Chutiancun",
    "gn:country_code":"CN",
    "gn:dem":425,
    "gn:feature_class":"P",
    "gn:feature_code":"PPL",
    "gn:name":"Chutiancun",
    "gn:population":0,
    "gn:timezone":"Asia/Shanghai",
    "iso:country":"CN",
    "name:zho_x_preferred":[
        "\u891a\u7530\u6751"
    ],
    "wof:name":"Chutiancun",
    "wof:placetype":"locality"
},
  "geometry": {"coordinates":[109.19843,34.71378],"type":"Point"}
}