{
  "type": "Feature",
  "properties": {
    "gn:admin1_code":"12.0",
    "gn:asciiname":"Chayuanwan",
    "gn:country_code":"CN",
    "gn:dem":520,
    "gn:feature_class":"P",
    "gn:feature_code":"PPL",
    "gn:name":"Chayuanwan",
    "gn:population":0,
    "gn:timezone":"Asia/Shanghai",
    "iso:country":"CN",
    "name:zho_x_preferred":[
        "\u8336\u56ed\u6e7e"
    ],
    "wof:name":"Chayuanwan",
    "wof:placetype":"locality"
},
  "geometry": {"coordinates":[110.03816,29.85741],"type":"Point"}
}