{
  "type": "Feature",
  "properties": {
    "gn:admin1_code":"26.0",
    "gn:asciiname":"Taijiabang",
    "gn:country_code":"CN",
    "gn:dem":516,
    "gn:feature_class":"P",
    "gn:feature_code":"PPL",
    "gn:name":"Taijiabang",
    "gn:population":0,
    "gn:timezone":"Asia/Shanghai",
    "iso:country":"CN",
    "name:und_x_variant":[
        "\u6cf0\u5bb6\u585d"
    ],
    "wof:name":"Taijiabang",
    "wof:placetype":"locality"
},
  "geometry": {"coordinates":[106.94699,33.03827],"type":"Point"}
}