{
  "type": "Feature",
  "properties": {
    "gn:admin1_code":"4.0",
    "gn:asciiname":"Wangsi",
    "gn:country_code":"CN",
    "gn:dem":4,
    "gn:feature_class":"P",
    "gn:feature_code":"PPL",
    "gn:name":"Wangsi",
    "gn:population":0,
    "gn:timezone":"Asia/Shanghai",
    "iso:country":"CN",
    "name:und_x_variant":[
        "\u5fd8\u79c1"
    ],
    "name:zho_x_preferred":[
        "\u5fd8\u79c1"
    ],
    "wof:name":"Wangsi",
    "wof:placetype":"locality"
},
  "geometry": {"coordinates":[120.23654999999999,32.97193],"type":"Point"}
}