{
  "type": "Feature",
  "properties": {
    "gn:admin1_code":"3.0",
    "gn:asciiname":"Xiashantian",
    "gn:country_code":"CN",
    "gn:dem":328,
    "gn:feature_class":"P",
    "gn:feature_code":"PPL",
    "gn:name":"Xiashantian",
    "gn:population":0,
    "gn:timezone":"Asia/Shanghai",
    "iso:country":"CN",
    "name:und_x_variant":[
        "\u4e0b\u5c71\u7530"
    ],
    "wof:name":"Xiashantian",
    "wof:placetype":"locality"
},
  "geometry": {"coordinates":[115.80491000000001,26.75504],"type":"Point"}
}