{
  "type": "Feature",
  "properties": {
    "gn:admin1_code":"19.0",
    "gn:asciiname":"Kuixingcun",
    "gn:country_code":"CN",
    "gn:dem":118,
    "gn:feature_class":"P",
    "gn:feature_code":"PPL",
    "gn:name":"Kuixingcun",
    "gn:population":0,
    "gn:timezone":"Asia/Shanghai",
    "iso:country":"CN",
    "name:zho_x_preferred":[
        "\u594e\u5174\u6751"
    ],
    "wof:name":"Kuixingcun",
    "wof:placetype":"locality"
},
  "geometry": {"coordinates":[122.26221,39.69182],"type":"Point"}
}