{
  "type": "Feature",
  "properties": {
    "gn:admin1_code":"32.0",
    "gn:asciiname":"Ani",
    "gn:country_code":"CN",
    "gn:dem":3512,
    "gn:feature_class":"P",
    "gn:feature_code":"PPL",
    "gn:name":"Ani",
    "gn:population":0,
    "gn:timezone":"Asia/Shanghai",
    "iso:country":"CN",
    "name:zho_x_preferred":[
        "\u54ce\u5c3c"
    ],
    "wof:name":"Ani",
    "wof:placetype":"locality"
},
  "geometry": {"coordinates":[99.7689,31.6816],"type":"Point"}
}