{
  "type": "Feature",
  "properties": {
    "gn:admin1_code":"32.0",
    "gn:asciiname":"Ani",
    "gn:country_code":"CN",
    "gn:dem":3512,
    "gn:feature_class":"P",
    "gn:feature_code":"PPL",
    "gn:name":"Ani",
    "gn:population":0,
    "gn:timezone":"Asia/Shanghai",
    "iso:country":"CN",
    "name:ara_x_preferred":[
        "\u0622\u0646\u064a"
    ],
    "name:ast_x_preferred":[
        "Ani"
    ],
    "name:aze_x_preferred":[
        "Ani"
    ],
    "name:bel_x_preferred":[
        "\u0410\u043d\u0456"
    ],
    "name:bul_x_preferred":[
        "\u0410\u043d\u0438"
    ],
    "name:cat_x_preferred":[
        "Ani"
    ],
    "name:ces_x_preferred":[
        "Ani"
    ],
    "name:deu_x_preferred":[
        "Ani"
    ],
    "name:ell_x_preferred":[
        "\u0391\u03bd\u03af"
    ],
    "name:epo_x_preferred":[
        "Anio"
    ],
    "name:fas_x_preferred":[
        "\u0622\u0646\u06cc"
    ],
    "name:fin_x_preferred":[
        "Ani"
    ],
    "name:fra_x_preferred":[
        "Ani"
    ],
    "name:hrv_x_preferred":[
        "Ani"
    ],
    "name:hun_x_preferred":[
        "Ani"
    ],
    "name:hye_x_preferred":[
        "\u0531\u0576\u056b"
    ],
    "name:ita_x_preferred":[
        "Ani"
    ],
    "name:jpn_x_preferred":[
        "\u30a2\u30cb"
    ],
    "name:kat_x_preferred":[
        "\u10d0\u10dc\u10d8\u10e1\u10d8"
    ],
    "name:kaz_x_preferred":[
        "\u0410\u043d\u0438"
    ],
    "name:kur_x_preferred":[
        "An\u00ee"
    ],
    "name:lav_x_preferred":[
        "Ani"
    ],
    "name:lit_x_preferred":[
        "Ani"
    ],
    "name:nld_x_preferred":[
        "Ani"
    ],
    "name:nor_x_preferred":[
        "Ani"
    ],
    "name:pol_x_preferred":[
        "Ani"
    ],
    "name:por_x_preferred":[
        "Ani"
    ],
    "name:rus_x_preferred":[
        "\u0410\u043d\u0438"
    ],
    "name:slk_x_preferred":[
        "Ani"
    ],
    "name:spa_x_preferred":[
        "Ani"
    ],
    "name:swe_x_preferred":[
        "Ani"
    ],
    "name:tgk_x_preferred":[
        "\u0410\u043d\u0438"
    ],
    "name:tur_x_preferred":[
        "Ani"
    ],
    "name:ukr_x_preferred":[
        "\u0410\u043d\u0456"
    ],
    "name:vie_x_preferred":[
        "Ani"
    ],
    "name:zho_x_preferred":[
        "\u54ce\u5c3c"
    ],
    "name:zho_x_variant":[
        "\u963f\u5c3c"
    ],
    "wof:name":"Ani",
    "wof:placetype":"locality"
},
  "geometry": {"coordinates":[99.7689,31.6816],"type":"Point"}
}