{
  "type": "Feature",
  "properties": {
    "gn:admin1_code":"18",
    "gn:asciiname":"Chaijiaba",
    "gn:country_code":"CN",
    "gn:dem":557,
    "gn:feature_class":"P",
    "gn:feature_code":"PPL",
    "gn:name":"Chaijiaba",
    "gn:population":0,
    "gn:timezone":"Asia/Shanghai",
    "iso:country":"CN",
    "name:zho_x_preferred":[
        "\u67f4\u5bb6\u575d"
    ],
    "wof:name":"Chaijiaba",
    "wof:placetype":"locality"
},
  "geometry": {"coordinates":[108.157,27.6423],"type":"Point"}
}