{
  "type": "Feature",
  "properties": {
    "gn:admin1_code":"12.0",
    "gn:asciiname":"Lijiapo",
    "gn:country_code":"CN",
    "gn:dem":1295,
    "gn:feature_class":"P",
    "gn:feature_code":"PPL",
    "gn:name":"Lijiapo",
    "gn:population":0,
    "gn:timezone":"Asia/Shanghai",
    "iso:country":"CN",
    "name:zho_x_preferred":[
        "\u674e\u5bb6\u5761"
    ],
    "wof:name":"Lijiapo",
    "wof:placetype":"locality"
},
  "geometry": {"coordinates":[111.29204,31.70349],"type":"Point"}
}