{
  "type": "Feature",
  "properties": {
    "gn:admin1_code":"26.0",
    "gn:asciiname":"Nanshanwan",
    "gn:country_code":"CN",
    "gn:dem":1292,
    "gn:feature_class":"P",
    "gn:feature_code":"PPL",
    "gn:name":"Nanshanwan",
    "gn:population":0,
    "gn:timezone":"Asia/Shanghai",
    "iso:country":"CN",
    "name:und_x_variant":[
        "\u5357\u5c71\u6e7e"
    ],
    "wof:name":"Nanshanwan",
    "wof:placetype":"locality"
},
  "geometry": {"coordinates":[106.59784000000001,33.92238],"type":"Point"}
}