{
  "type": "Feature",
  "properties": {
    "gn:admin1_code":"16.0",
    "gn:asciiname":"Qinyi",
    "gn:country_code":"CN",
    "gn:dem":105,
    "gn:feature_class":"P",
    "gn:feature_code":"PPL",
    "gn:name":"Qinyi",
    "gn:population":0,
    "gn:timezone":"Asia/Shanghai",
    "iso:country":"CN",
    "name:zho_x_preferred":[
        "\u7434\u4e59"
    ],
    "wof:name":"Qinyi",
    "wof:placetype":"locality"
},
  "geometry": {"coordinates":[107.577,22.5371],"type":"Point"}
}