{
  "type": "Feature",
  "properties": {
    "gn:admin1_code":"3.0",
    "gn:asciiname":"Daheba",
    "gn:country_code":"CN",
    "gn:dem":318,
    "gn:feature_class":"P",
    "gn:feature_code":"PPL",
    "gn:name":"Daheba",
    "gn:population":0,
    "gn:timezone":"Asia/Shanghai",
    "iso:country":"CN",
    "name:und_x_variant":[
        "\u5927\u6cb3\u575d"
    ],
    "wof:name":"Daheba",
    "wof:placetype":"locality"
},
  "geometry": {"coordinates":[115.79034,25.89739],"type":"Point"}
}