{
  "type": "Feature",
  "properties": {
    "gn:admin1_code":"7.0",
    "gn:asciiname":"Shitashan",
    "gn:country_code":"CN",
    "gn:dem":1540,
    "gn:feature_class":"P",
    "gn:feature_code":"PPL",
    "gn:name":"Shitashan",
    "gn:population":0,
    "gn:timezone":"Asia/Shanghai",
    "iso:country":"CN",
    "name:und_x_variant":[
        "\u77f3\u5854\u5c71"
    ],
    "wof:name":"Shitashan",
    "wof:placetype":"locality"
},
  "geometry": {"coordinates":[118.64043999999998,26.8353],"type":"Point"}
}