{
  "type": "Feature",
  "properties": {
    "gn:admin1_code":"19.0",
    "gn:asciiname":"Biangou",
    "gn:country_code":"CN",
    "gn:dem":214,
    "gn:feature_class":"P",
    "gn:feature_code":"PPL",
    "gn:name":"Biangou",
    "gn:population":0,
    "gn:timezone":"Asia/Shanghai",
    "iso:country":"CN",
    "name:zho_x_preferred":[
        "\u8fb9\u6c9f"
    ],
    "wof:name":"Biangou",
    "wof:placetype":"locality"
},
  "geometry": {"coordinates":[124.45929,40.47526],"type":"Point"}
}