{
  "type": "Feature",
  "properties": {
    "gn:admin1_code":"2",
    "gn:asciiname":"Dumu",
    "gn:country_code":"CN",
    "gn:dem":125,
    "gn:feature_class":"P",
    "gn:feature_code":"PPL",
    "gn:name":"Dumu",
    "gn:population":0,
    "gn:timezone":"Asia/Shanghai",
    "iso:country":"CN",
    "name:und_x_variant":[
        "\u675c\u5893"
    ],
    "wof:name":"Dumu",
    "wof:placetype":"locality"
},
  "geometry": {"coordinates":[119.87166999999999,30.16361],"type":"Point"}
}