{
  "type": "Feature",
  "properties": {
    "gn:admin1_code":"16.0",
    "gn:asciiname":"Macaoliao",
    "gn:country_code":"CN",
    "gn:dem":507,
    "gn:feature_class":"P",
    "gn:feature_code":"PPL",
    "gn:name":"Macaoliao",
    "gn:population":0,
    "gn:timezone":"Asia/Shanghai",
    "iso:country":"CN",
    "name:zho_x_preferred":[
        "\u9a6c\u8349\u8fbd"
    ],
    "wof:name":"Macaoliao",
    "wof:placetype":"locality"
},
  "geometry": {"coordinates":[111.755,24.5833],"type":"Point"}
}