{
  "type": "Feature",
  "properties": {
    "gn:admin1_code":"29.0",
    "gn:asciiname":"Nadi",
    "gn:country_code":"CN",
    "gn:dem":2174,
    "gn:feature_class":"P",
    "gn:feature_code":"PPL",
    "gn:name":"Nadi",
    "gn:population":0,
    "gn:timezone":"Asia/Shanghai",
    "iso:country":"CN",
    "name:zho_x_preferred":[
        "\u90a3\u8fea"
    ],
    "wof:name":"Nadi",
    "wof:placetype":"locality"
},
  "geometry": {"coordinates":[101.962,25.7043],"type":"Point"}
}