{
  "type": "Feature",
  "properties": {
    "gn:admin1_code":"19.0",
    "gn:asciiname":"Xingyangqi",
    "gn:country_code":"CN",
    "gn:dem":18,
    "gn:feature_class":"P",
    "gn:feature_code":"PPL",
    "gn:name":"Xingyangqi",
    "gn:population":0,
    "gn:timezone":"Asia/Shanghai",
    "iso:country":"CN",
    "name:und_x_variant":[
        "\u90a2\u9633\u6c14"
    ],
    "name:zho_x_preferred":[
        "\u90a2\u9633\u6c14"
    ],
    "wof:name":"Xingyangqi",
    "wof:placetype":"locality"
},
  "geometry": {"coordinates":[122.90723,41.14016],"type":"Point"}
}