{
  "type": "Feature",
  "properties": {
    "gn:admin1_code":"22.0",
    "gn:asciiname":"Yihecun",
    "gn:country_code":"CN",
    "gn:dem":435,
    "gn:feature_class":"P",
    "gn:feature_code":"PPL",
    "gn:name":"Yihecun",
    "gn:population":0,
    "gn:timezone":"Asia/Shanghai",
    "iso:country":"CN",
    "name:zho_x_preferred":[
        "\u8bae\u548c\u6751"
    ],
    "wof:name":"Yihecun",
    "wof:placetype":"locality"
},
  "geometry": {"coordinates":[115.5337,39.71253],"type":"Point"}
}