{
  "type": "Feature",
  "properties": {
    "gn:admin1_code":"1.0",
    "gn:asciiname":"Xinwancun",
    "gn:country_code":"CN",
    "gn:dem":21,
    "gn:feature_class":"P",
    "gn:feature_code":"PPL",
    "gn:name":"Xinwancun",
    "gn:population":0,
    "gn:timezone":"Asia/Shanghai",
    "iso:country":"CN",
    "name:zho_x_preferred":[
        "\u4fe1\u6e7e\u6751"
    ],
    "wof:name":"Xinwancun",
    "wof:placetype":"locality"
},
  "geometry": {"coordinates":[117.4757,32.98778],"type":"Point"}
}