{
  "type": "Feature",
  "properties": {
    "gn:admin1_code":"11.0",
    "gn:asciiname":"Oucaitang",
    "gn:country_code":"CN",
    "gn:dem":763,
    "gn:feature_class":"P",
    "gn:feature_code":"PPL",
    "gn:name":"Oucaitang",
    "gn:population":0,
    "gn:timezone":"Asia/Shanghai",
    "iso:country":"CN",
    "name:zho_x_preferred":[
        "\u6b27\u83dc\u5858"
    ],
    "wof:name":"Oucaitang",
    "wof:placetype":"locality"
},
  "geometry": {"coordinates":[110.52018,27.49905],"type":"Point"}
}