{
  "type": "Feature",
  "properties": {
    "gn:admin1_code":"2.0",
    "gn:asciiname":"Tiangong'ao",
    "gn:country_code":"CN",
    "gn:dem":25,
    "gn:feature_class":"P",
    "gn:feature_code":"PPL",
    "gn:name":"Tiangong\u2019ao",
    "gn:population":0,
    "gn:timezone":"Asia/Shanghai",
    "iso:country":"CN",
    "name:und_x_variant":[
        "Tiangong\u2019ao"
    ],
    "name:zho_x_preferred":[
        "\u7530\u516c\u5c99"
    ],
    "wof:name":"Tiangong'ao",
    "wof:placetype":"locality"
},
  "geometry": {"coordinates":[122.29198999999998,30.02048],"type":"Point"}
}