{
  "type": "Feature",
  "properties": {
    "gn:admin1_code":"11",
    "gn:asciiname":"Shuitianba",
    "gn:country_code":"CN",
    "gn:dem":644,
    "gn:feature_class":"P",
    "gn:feature_code":"PPLA4",
    "gn:name":"Shuitianba",
    "gn:population":0,
    "gn:timezone":"Asia/Shanghai",
    "iso:country":"CN",
    "name:und_x_variant":[
        "Shui-t\u2019ien-pa",
        "Shuitianba Xiang",
        "Shuitianba"
    ],
    "name:zho_x_preferred":[
        "\u6c34\u7530\u575d"
    ],
    "name:zho_x_variant":[
        "\u6c34\u7530\u575d\u4e61"
    ],
    "wof:name":"Shuitianba",
    "wof:placetype":"locality"
},
  "geometry": {"coordinates":[109.72055,29.45291],"type":"Point"}
}