{
  "type": "Feature",
  "properties": {
    "gn:admin1_code":"7.0",
    "gn:asciiname":"Heling",
    "gn:country_code":"CN",
    "gn:dem":367,
    "gn:feature_class":"P",
    "gn:feature_code":"PPL",
    "gn:name":"Heling",
    "gn:population":0,
    "gn:timezone":"Asia/Shanghai",
    "iso:country":"CN",
    "name:zho_x_preferred":[
        "\u79be\u5cad"
    ],
    "wof:name":"Heling",
    "wof:placetype":"locality"
},
  "geometry": {"coordinates":[116.50878,26.19341],"type":"Point"}
}