{
  "type": "Feature",
  "properties": {
    "gn:admin1_code":"16.0",
    "gn:asciiname":"Shebeitang",
    "gn:country_code":"CN",
    "gn:dem":102,
    "gn:feature_class":"P",
    "gn:feature_code":"PPL",
    "gn:name":"Shebeitang",
    "gn:population":0,
    "gn:timezone":"Asia/Shanghai",
    "iso:country":"CN",
    "name:zho_x_preferred":[
        "\u793e\u80cc\u5858"
    ],
    "wof:name":"Shebeitang",
    "wof:placetype":"locality"
},
  "geometry": {"coordinates":[110.03400000000001,22.2753],"type":"Point"}
}