{
  "type": "Feature",
  "properties": {
    "gn:admin1_code":"30",
    "gn:asciiname":"Shibadao",
    "gn:country_code":"CN",
    "gn:dem":513,
    "gn:feature_class":"P",
    "gn:feature_code":"PPL",
    "gn:name":"Shibadao",
    "gn:population":0,
    "gn:timezone":"Asia/Shanghai",
    "iso:country":"CN",
    "name:zho_x_preferred":[
        "\u5341\u516b\u5230"
    ],
    "wof:name":"Shibadao",
    "wof:placetype":"locality"
},
  "geometry": {"coordinates":[116.57077,24.08333],"type":"Point"}
}