{
  "type": "Feature",
  "properties": {
    "gn:admin1_code":"32.0",
    "gn:asciiname":"Huinancun",
    "gn:country_code":"CN",
    "gn:dem":344,
    "gn:feature_class":"P",
    "gn:feature_code":"PPL",
    "gn:name":"Huinancun",
    "gn:population":0,
    "gn:timezone":"Asia/Shanghai",
    "iso:country":"CN",
    "name:zho_x_preferred":[
        "\u56de\u5357\u6751"
    ],
    "wof:name":"Huinancun",
    "wof:placetype":"locality"
},
  "geometry": {"coordinates":[105.15900000000001,29.6064],"type":"Point"}
}