{
  "type": "Feature",
  "properties": {
    "gn:admin1_code":"32.0",
    "gn:asciiname":"Laoxiongqiao",
    "gn:country_code":"CN",
    "gn:dem":1487,
    "gn:feature_class":"P",
    "gn:feature_code":"PPL",
    "gn:name":"Laoxiongqiao",
    "gn:population":0,
    "gn:timezone":"Asia/Shanghai",
    "iso:country":"CN",
    "name:zho_x_preferred":[
        "\u8001\u718a\u6865"
    ],
    "wof:name":"Laoxiongqiao",
    "wof:placetype":"locality"
},
  "geometry": {"coordinates":[103.003,30.4008],"type":"Point"}
}