{
  "type": "Feature",
  "properties": {
    "gn:admin1_code":"2.0",
    "gn:asciiname":"Nanbeiqiao",
    "gn:country_code":"CN",
    "gn:dem":334,
    "gn:feature_class":"P",
    "gn:feature_code":"PPL",
    "gn:name":"Nanbeiqiao",
    "gn:population":0,
    "gn:timezone":"Asia/Shanghai",
    "iso:country":"CN",
    "name:zho_x_preferred":[
        "\u5357\u5317\u6865"
    ],
    "wof:name":"Nanbeiqiao",
    "wof:placetype":"locality"
},
  "geometry": {"coordinates":[121.18671000000001,29.37639],"type":"Point"}
}