{
  "type": "Feature",
  "properties": {
    "gn:admin1_code":"30.0",
    "gn:asciiname":"Huashicun",
    "gn:country_code":"CN",
    "gn:dem":15,
    "gn:feature_class":"P",
    "gn:feature_code":"PPL",
    "gn:name":"Huashicun",
    "gn:population":0,
    "gn:timezone":"Asia/Shanghai",
    "iso:country":"CN",
    "name:zho_x_preferred":[
        "\u534e\u5e02\u6751"
    ],
    "wof:name":"Huashicun",
    "wof:placetype":"locality"
},
  "geometry": {"coordinates":[116.15322,23.31115],"type":"Point"}
}