{
  "type": "Feature",
  "properties": {
    "gn:admin1_code":"1.0",
    "gn:asciiname":"Dakengli",
    "gn:country_code":"CN",
    "gn:dem":116,
    "gn:feature_class":"P",
    "gn:feature_code":"PPL",
    "gn:name":"Dakengli",
    "gn:population":0,
    "gn:timezone":"Asia/Shanghai",
    "iso:country":"CN",
    "name:und_x_variant":[
        "\u5927\u5751\u91cc"
    ],
    "wof:name":"Dakengli",
    "wof:placetype":"locality"
},
  "geometry": {"coordinates":[118.05929999999999,30.92508],"type":"Point"}
}