{
  "type": "Feature",
  "properties": {
    "gn:admin1_code":"11.0",
    "gn:asciiname":"Chenjiayu",
    "gn:country_code":"CN",
    "gn:dem":131,
    "gn:feature_class":"P",
    "gn:feature_code":"PPL",
    "gn:name":"Chenjiayu",
    "gn:population":0,
    "gn:timezone":"Asia/Shanghai",
    "iso:country":"CN",
    "name:zho_x_preferred":[
        "Chenjiayu"
    ],
    "name:zho_x_variant":[
        "\u9648\u5bb6\u5cea"
    ],
    "wof:name":"Chenjiayu",
    "wof:placetype":"locality"
},
  "geometry": {"coordinates":[111.39939,29.44368],"type":"Point"}
}