{
  "type": "Feature",
  "properties": {
    "gn:admin1_code":"19.0",
    "gn:asciiname":"Shijiadian",
    "gn:country_code":"CN",
    "gn:dem":13,
    "gn:feature_class":"P",
    "gn:feature_code":"PPL",
    "gn:name":"Shijiadian",
    "gn:population":0,
    "gn:timezone":"Asia/Shanghai",
    "iso:country":"CN",
    "name:zho_x_preferred":[
        "\u65bd\u5bb6\u5e97"
    ],
    "wof:name":"Shijiadian",
    "wof:placetype":"locality"
},
  "geometry": {"coordinates":[123.006,39.75694],"type":"Point"}
}