{
  "type": "Feature",
  "properties": {
    "gn:admin1_code":"12.0",
    "gn:asciiname":"Zhangjiachang",
    "gn:country_code":"CN",
    "gn:dem":32,
    "gn:feature_class":"P",
    "gn:feature_code":"PPL",
    "gn:name":"Zhangjiachang",
    "gn:population":0,
    "gn:timezone":"Asia/Shanghai",
    "iso:country":"CN",
    "name:zho_x_preferred":[
        "Zhangjiachang"
    ],
    "name:zho_x_variant":[
        "\u5f20\u5bb6\u573a"
    ],
    "wof:name":"Zhangjiachang",
    "wof:placetype":"locality"
},
  "geometry": {"coordinates":[112.48551,30.30507],"type":"Point"}
}