{
  "type": "Feature",
  "properties": {
    "gn:admin1_code":"29.0",
    "gn:asciiname":"Kuangjiazhai",
    "gn:country_code":"CN",
    "gn:dem":1597,
    "gn:feature_class":"P",
    "gn:feature_code":"PPL",
    "gn:name":"Kuangjiazhai",
    "gn:population":0,
    "gn:timezone":"Asia/Shanghai",
    "iso:country":"CN",
    "name:zho_x_preferred":[
        "\u5321\u5bb6\u5be8"
    ],
    "wof:name":"Kuangjiazhai",
    "wof:placetype":"locality"
},
  "geometry": {"coordinates":[98.93429999999999,24.3187],"type":"Point"}
}