{
  "type": "Feature",
  "properties": {
    "gn:admin1_code":"8.0",
    "gn:asciiname":"Rongfengcun",
    "gn:country_code":"CN",
    "gn:dem":91,
    "gn:feature_class":"P",
    "gn:feature_code":"PPL",
    "gn:name":"Rongfengcun",
    "gn:population":0,
    "gn:timezone":"Asia/Shanghai",
    "iso:country":"CN",
    "name:zho_x_preferred":[
        "\u8363\u4e30\u6751"
    ],
    "wof:name":"Rongfengcun",
    "wof:placetype":"locality"
},
  "geometry": {"coordinates":[130.01464000000001,46.85315],"type":"Point"}
}