{
  "type": "Feature",
  "properties": {
    "gn:admin1_code":"08",
    "gn:asciiname":"Longmen",
    "gn:cc2":"CN",
    "gn:country_code":"CN",
    "gn:dem":373,
    "gn:feature_class":"P",
    "gn:feature_code":"PPL",
    "gn:name":"Longmen",
    "gn:population":0,
    "gn:timezone":"Asia/Shanghai",
    "iso:country":"CN",
    "name:und_x_variant":[
        "Lung-men",
        "Longmen"
    ],
    "wof:name":"Longmen",
    "wof:placetype":"locality"
},
  "geometry": {"coordinates":[126.93333,48.95],"type":"Point"}
}