{
  "type": "Feature",
  "properties": {
    "gn:admin1_code":"25",
    "gn:asciiname":"Nanshu",
    "gn:country_code":"CN",
    "gn:dem":111,
    "gn:feature_class":"P",
    "gn:feature_code":"PPLA4",
    "gn:name":"Nanshu",
    "gn:population":0,
    "gn:timezone":"Asia/Shanghai",
    "iso:country":"CN",
    "name:und_x_variant":[
        "Nanshu Zhen"
    ],
    "name:zho_x_preferred":[
        "\u5357\u5885"
    ],
    "name:zho_x_variant":[
        "\u5357\u5885\u9547"
    ],
    "wof:name":"Nanshu",
    "wof:placetype":"locality"
},
  "geometry": {"coordinates":[120.33731,37.02014000000001],"type":"Point"}
}