{
  "type": "Feature",
  "properties": {
    "gn:admin1_code":"11.0",
    "gn:asciiname":"Baiyangchong",
    "gn:country_code":"CN",
    "gn:dem":38,
    "gn:feature_class":"P",
    "gn:feature_code":"PPL",
    "gn:name":"Baiyangchong",
    "gn:population":0,
    "gn:timezone":"Asia/Shanghai",
    "iso:country":"CN",
    "name:zho_x_preferred":[
        "\u767d\u7f8a\u51b2"
    ],
    "wof:name":"Baiyangchong",
    "wof:placetype":"locality"
},
  "geometry": {"coordinates":[112.99111000000001,27.93095],"type":"Point"}
}