{
  "type": "Feature",
  "properties": {
    "gn:admin1_code":"12.0",
    "gn:asciiname":"Shangwuling",
    "gn:country_code":"CN",
    "gn:dem":617,
    "gn:feature_class":"P",
    "gn:feature_code":"PPL",
    "gn:name":"Shangwuling",
    "gn:population":0,
    "gn:timezone":"Asia/Shanghai",
    "iso:country":"CN",
    "name:zho_x_preferred":[
        "Shangwuling"
    ],
    "name:zho_x_variant":[
        "\u4e0a\u5deb\u5cad"
    ],
    "wof:name":"Shangwuling",
    "wof:placetype":"locality"
},
  "geometry": {"coordinates":[111.09148,30.44761],"type":"Point"}
}