{
  "type": "Feature",
  "properties": {
    "gn:admin1_code":"30",
    "gn:asciiname":"Tanggexu",
    "gn:country_code":"CN",
    "gn:dem":38,
    "gn:feature_class":"P",
    "gn:feature_code":"PPL",
    "gn:name":"Tanggexu",
    "gn:population":0,
    "gn:timezone":"Asia/Shanghai",
    "iso:country":"CN",
    "name:zho_x_preferred":[
        "\u68e0\u9601\u5729"
    ],
    "wof:name":"Tanggexu",
    "wof:placetype":"locality"
},
  "geometry": {"coordinates":[114.78362,23.05042000000001],"type":"Point"}
}