{
  "type": "Feature",
  "properties": {
    "gn:admin1_code":"32.0",
    "gn:asciiname":"Qianbaling",
    "gn:country_code":"CN",
    "gn:dem":696,
    "gn:feature_class":"P",
    "gn:feature_code":"PPL",
    "gn:name":"Qianbaling",
    "gn:population":0,
    "gn:timezone":"Asia/Shanghai",
    "iso:country":"CN",
    "name:zho_x_preferred":[
        "\u4e7e\u5df4\u5cad"
    ],
    "wof:name":"Qianbaling",
    "wof:placetype":"locality"
},
  "geometry": {"coordinates":[107.37463,31.90374000000001],"type":"Point"}
}