{
  "type": "Feature",
  "properties": {
    "gn:admin1_code":"10",
    "gn:asciiname":"Huangmazhai",
    "gn:country_code":"CN",
    "gn:dem":45,
    "gn:feature_class":"P",
    "gn:feature_code":"PPL",
    "gn:name":"Huangmazhai",
    "gn:population":0,
    "gn:timezone":"Asia/Shanghai",
    "iso:country":"CN",
    "name:zho_x_preferred":[
        "\u9ec4\u9a6c\u5be8"
    ],
    "wof:name":"Huangmazhai",
    "wof:placetype":"locality"
},
  "geometry": {"coordinates":[115.15217,36.43373],"type":"Point"}
}