{
  "type": "Feature",
  "properties": {
    "gn:admin1_code":"10",
    "gn:asciiname":"Xiaohuangqicha",
    "gn:country_code":"CN",
    "gn:dem":1459,
    "gn:feature_class":"P",
    "gn:feature_code":"PPL",
    "gn:name":"Xiaohuangqicha",
    "gn:population":0,
    "gn:timezone":"Asia/Shanghai",
    "iso:country":"CN",
    "name:zho_x_preferred":[
        "\u5c0f\u9ec4\u65d7\u5c94"
    ],
    "wof:name":"Xiaohuangqicha",
    "wof:placetype":"locality"
},
  "geometry": {"coordinates":[114.2299,41.26595],"type":"Point"}
}