{
  "type": "Feature",
  "properties": {
    "gn:admin1_code":"21.0",
    "gn:asciiname":"Yuejia Shadi",
    "gn:country_code":"CN",
    "gn:dem":1713,
    "gn:feature_class":"P",
    "gn:feature_code":"PPL",
    "gn:name":"Yuejia Shadi",
    "gn:population":0,
    "gn:timezone":"Asia/Shanghai",
    "iso:country":"CN",
    "name:zho_x_preferred":[
        "\u5cb3\u5bb6\u6c99\u5730"
    ],
    "wof:name":"Yuejia Shadi",
    "wof:placetype":"locality"
},
  "geometry": {"coordinates":[105.235,36.9882],"type":"Point"}
}