{
  "type": "Feature",
  "properties": {
    "gn:admin1_code":"8.0",
    "gn:asciiname":"Wailangtun",
    "gn:country_code":"CN",
    "gn:dem":125,
    "gn:feature_class":"P",
    "gn:feature_code":"PPL",
    "gn:name":"Wailangtun",
    "gn:population":0,
    "gn:timezone":"Asia/Shanghai",
    "iso:country":"CN",
    "name:zho_x_preferred":[
        "\u5916\u6717\u5c6f"
    ],
    "wof:name":"Wailangtun",
    "wof:placetype":"locality"
},
  "geometry": {"coordinates":[125.26517,45.50872],"type":"Point"}
}