{
  "type": "Feature",
  "properties": {
    "gn:admin1_code":"5.0",
    "gn:asciiname":"Dafangcun",
    "gn:country_code":"CN",
    "gn:dem":294,
    "gn:feature_class":"P",
    "gn:feature_code":"PPL",
    "gn:name":"Dafangcun",
    "gn:population":0,
    "gn:timezone":"Asia/Shanghai",
    "iso:country":"CN",
    "name:zho_x_preferred":[
        "\u5927\u623f\u6751"
    ],
    "wof:name":"Dafangcun",
    "wof:placetype":"locality"
},
  "geometry": {"coordinates":[125.16587,43.04713],"type":"Point"}
}