{
  "type": "Feature",
  "properties": {
    "gn:admin1_code":"09",
    "gn:asciiname":"Guanpo",
    "gn:cc2":"CN",
    "gn:country_code":"CN",
    "gn:dem":942,
    "gn:feature_class":"P",
    "gn:feature_code":"PPL",
    "gn:name":"Guanpo",
    "gn:population":0,
    "gn:timezone":"Asia/Shanghai",
    "iso:country":"CN",
    "name:und_x_variant":[
        "Kuan-p\u2019o",
        "Guanpo"
    ],
    "wof:name":"Guanpo",
    "wof:placetype":"locality"
},
  "geometry": {"coordinates":[110.73972000000001,33.87417],"type":"Point"}
}