{
  "type": "Feature",
  "properties": {
    "gn:admin1_code":"29.0",
    "gn:asciiname":"Weizhahei",
    "gn:country_code":"CN",
    "gn:dem":1868,
    "gn:feature_class":"P",
    "gn:feature_code":"PPL",
    "gn:name":"Weizhahei",
    "gn:population":0,
    "gn:timezone":"Asia/Shanghai",
    "iso:country":"CN",
    "name:zho_x_preferred":[
        "\u5c3e\u4e4d\u9ed1"
    ],
    "wof:name":"Weizhahei",
    "wof:placetype":"locality"
},
  "geometry": {"coordinates":[103.505,24.5748],"type":"Point"}
}