{
  "type": "Feature",
  "properties": {
    "gn:admin1_code":"12.0",
    "gn:asciiname":"Guolutan",
    "gn:country_code":"CN",
    "gn:dem":49,
    "gn:feature_class":"P",
    "gn:feature_code":"PPL",
    "gn:name":"Guolutan",
    "gn:population":0,
    "gn:timezone":"Asia/Shanghai",
    "iso:country":"CN",
    "name:zho_x_preferred":[
        "Guolutan"
    ],
    "name:zho_x_variant":[
        "\u8fc7\u8def\u6ee9"
    ],
    "wof:name":"Guolutan",
    "wof:placetype":"locality"
},
  "geometry": {"coordinates":[111.40845,30.37388],"type":"Point"}
}