{
  "type": "Feature",
  "properties": {
    "gn:admin1_code":"29.0",
    "gn:asciiname":"Xiaoganba",
    "gn:country_code":"CN",
    "gn:dem":2074,
    "gn:feature_class":"P",
    "gn:feature_code":"PPL",
    "gn:name":"Xiaoganba",
    "gn:population":0,
    "gn:timezone":"Asia/Shanghai",
    "iso:country":"CN",
    "name:zho_x_preferred":[
        "\u5c0f\u5e72\u575d"
    ],
    "wof:name":"Xiaoganba",
    "wof:placetype":"locality"
},
  "geometry": {"coordinates":[100.785,24.9814],"type":"Point"}
}