{
  "type": "Feature",
  "properties": {
    "gn:admin1_code":"24.0",
    "gn:asciiname":"Guoziyuan",
    "gn:country_code":"CN",
    "gn:dem":1516,
    "gn:feature_class":"P",
    "gn:feature_code":"PPL",
    "gn:name":"Guoziyuan",
    "gn:population":0,
    "gn:timezone":"Asia/Shanghai",
    "iso:country":"CN",
    "name:und_x_variant":[
        "\u679c\u5b50\u56ed"
    ],
    "name:zho_x_preferred":[
        "\u679c\u5b50\u56ed"
    ],
    "wof:name":"Guoziyuan",
    "wof:placetype":"locality"
},
  "geometry": {"coordinates":[113.73985,39.65582],"type":"Point"}
}