{
  "type": "Feature",
  "properties": {
    "gn:admin1_code":"32.0",
    "gn:asciiname":"Zhagu",
    "gn:country_code":"CN",
    "gn:dem":2372,
    "gn:feature_class":"P",
    "gn:feature_code":"PPL",
    "gn:name":"Zhagu",
    "gn:population":0,
    "gn:timezone":"Asia/Shanghai",
    "iso:country":"CN",
    "name:zho_x_preferred":[
        "\u672d\u53e4"
    ],
    "wof:name":"Zhagu",
    "wof:placetype":"locality"
},
  "geometry": {"coordinates":[103.15600000000001,28.0969],"type":"Point"}
}