{
  "type": "Feature",
  "properties": {
    "gn:country":"CN",
    "gn:fcode":"PPLA4",
    "gn:pop":7071,
    "iso:country":"CN",
    "name:unk_x_variant":[
        "Zaojiacheng Zhen"
    ],
    "name:zho_x_preferred":[
        "\u9020\u7532\u57ce"
    ],
    "name:zho_x_variant":[
        "\u9020\u7532\u57ce\u9547"
    ],
    "qs:name":"Zaojiacheng",
    "qs:photos_9r":0,
    "qs:photos_sr":0,
    "qs:pop_sr":"5",
    "wd:wordcount":173,
    "wof:name":"Zaojiacheng",
    "wof:placetype":"locality",
    "wof:population":7071
},
  "geometry": {"coordinates":[117.43574,39.27706],"type":"Point"}
}