{
  "type": "Feature",
  "properties": {
    "gn:country":"CN",
    "gn:fcode":"PPLA4",
    "gn:pop":7071,
    "iso:country":"CN",
    "name:ceb_x_preferred":[
        "Ninghe Xian"
    ],
    "name:cym_x_preferred":[
        "Ardal Ninghe"
    ],
    "name:deu_x_preferred":[
        "Ninghe"
    ],
    "name:eng_x_preferred":[
        "Ninghe District"
    ],
    "name:eus_x_preferred":[
        "Ninghe konderria"
    ],
    "name:fas_x_preferred":[
        "\u0634\u0647\u0631\u0633\u062a\u0627\u0646 \u0646\u06cc\u0646\u06af\u0647\u0647"
    ],
    "name:gan_x_preferred":[
        "\u5b81\u6cb3\u533a"
    ],
    "name:jpn_x_preferred":[
        "\u5be7\u6cb3\u533a"
    ],
    "name:kor_x_preferred":[
        "\ub2dd\ud5c8\uad6c"
    ],
    "name:nan_x_preferred":[
        "L\u00eang-h\u00f4-khu"
    ],
    "name:nld_x_preferred":[
        "Ninghe"
    ],
    "name:nob_x_preferred":[
        "Ninghe"
    ],
    "name:rus_x_preferred":[
        "\u041d\u0438\u043d\u0445\u044d"
    ],
    "name:swe_x_preferred":[
        "Ninghe"
    ],
    "name:unk_x_variant":[
        "Zaojiacheng Zhen"
    ],
    "name:urd_x_preferred":[
        "\u0646\u06cc\u0646\u06af\u06c1\u06d2 \u0636\u0644\u0639"
    ],
    "name:vie_x_preferred":[
        "Ninh H\u00e0"
    ],
    "name:wuu_x_preferred":[
        "\u5b81\u6cb3\u533a"
    ],
    "name:zho_x_preferred":[
        "\u9020\u7532\u57ce"
    ],
    "name:zho_x_variant":[
        "\u9020\u7532\u57ce\u9547",
        "\u5b81\u6cb3\u533a"
    ],
    "qs:name":"Zaojiacheng",
    "qs:photos_9r":0,
    "qs:photos_sr":0,
    "qs:pop_sr":"5",
    "wd:wordcount":173,
    "wof:name":"Zaojiacheng",
    "wof:placetype":"locality",
    "wof:population":7071
},
  "geometry": {"coordinates":[117.43574,39.27706],"type":"Point"}
}