{
  "type": "Feature",
  "properties": {
    "gn:admin1_code":"9.0",
    "gn:asciiname":"Shanglaohugou",
    "gn:country_code":"CN",
    "gn:dem":507,
    "gn:feature_class":"P",
    "gn:feature_code":"PPL",
    "gn:name":"Shanglaohugou",
    "gn:population":0,
    "gn:timezone":"Asia/Shanghai",
    "iso:country":"CN",
    "name:zho_x_preferred":[
        "\u4e0a\u8001\u864e\u6c9f"
    ],
    "wof:name":"Shanglaohugou",
    "wof:placetype":"locality"
},
  "geometry": {"coordinates":[112.21818,33.55248],"type":"Point"}
}