{
  "type": "Feature",
  "properties": {
    "gn:admin1_code":"29.0",
    "gn:asciiname":"Pengyicun",
    "gn:country_code":"CN",
    "gn:dem":1143,
    "gn:feature_class":"P",
    "gn:feature_code":"PPL",
    "gn:name":"Pengyicun",
    "gn:population":0,
    "gn:timezone":"Asia/Shanghai",
    "iso:country":"CN",
    "name:zho_x_preferred":[
        "\u670b\u4e00\u6751"
    ],
    "wof:name":"Pengyicun",
    "wof:placetype":"locality"
},
  "geometry": {"coordinates":[103.355,23.9709],"type":"Point"}
}