{
  "type": "Feature",
  "properties": {
    "gn:admin1_code":"32.0",
    "gn:asciiname":"Biji",
    "gn:country_code":"CN",
    "gn:dem":1248,
    "gn:feature_class":"P",
    "gn:feature_code":"PPL",
    "gn:name":"Biji",
    "gn:population":0,
    "gn:timezone":"Asia/Shanghai",
    "iso:country":"CN",
    "name:zho_x_preferred":[
        "\u78a7\u673a"
    ],
    "wof:name":"Biji",
    "wof:placetype":"locality"
},
  "geometry": {"coordinates":[102.879,27.1597],"type":"Point"}
}