{
  "type": "Feature",
  "properties": {
    "gn:admin1_code":"15.0",
    "gn:asciiname":"Hongxing",
    "gn:country_code":"CN",
    "gn:dem":1772,
    "gn:feature_class":"P",
    "gn:feature_code":"PPL",
    "gn:name":"Hongxing",
    "gn:population":0,
    "gn:timezone":"Asia/Shanghai",
    "iso:country":"CN",
    "name:zho_x_preferred":[
        "\u7ea2\u661f"
    ],
    "wof:name":"Hongxing",
    "wof:placetype":"locality"
},
  "geometry": {"coordinates":[102.43600000000001,37.9649],"type":"Point"}
}