{
  "type": "Feature",
  "properties": {
    "gn:admin1_code":"26.0",
    "gn:asciiname":"Gutuncun",
    "gn:country_code":"CN",
    "gn:dem":1016,
    "gn:feature_class":"P",
    "gn:feature_code":"PPL",
    "gn:name":"Gutuncun",
    "gn:population":0,
    "gn:timezone":"Asia/Shanghai",
    "iso:country":"CN",
    "name:zho_x_preferred":[
        "\u987e\u5c6f\u6751"
    ],
    "wof:name":"Gutuncun",
    "wof:placetype":"locality"
},
  "geometry": {"coordinates":[109.83413,36.76809],"type":"Point"}
}