{
  "type": "Feature",
  "properties": {
    "gn:admin1_code":"21.0",
    "gn:asciiname":"Wei'ercun",
    "gn:country_code":"CN",
    "gn:dem":1386,
    "gn:feature_class":"P",
    "gn:feature_code":"PPL",
    "gn:name":"Wei\u2019ercun",
    "gn:population":0,
    "gn:timezone":"Asia/Shanghai",
    "iso:country":"CN",
    "name:und_x_variant":[
        "Wei\u2019ercun"
    ],
    "name:zho_x_preferred":[
        "\u97e6\u4e8c\u6751"
    ],
    "wof:name":"Wei'ercun",
    "wof:placetype":"locality"
},
  "geometry": {"coordinates":[106.48,37.286],"type":"Point"}
}