{
  "type": "Feature",
  "properties": {
    "gn:admin1_code":"3.0",
    "gn:asciiname":"Wushi",
    "gn:country_code":"CN",
    "gn:dem":340,
    "gn:feature_class":"P",
    "gn:feature_code":"PPL",
    "gn:name":"Wushi",
    "gn:population":0,
    "gn:timezone":"Asia/Shanghai",
    "iso:country":"CN",
    "name:ceb_x_preferred":[
        "Wushi"
    ],
    "name:deu_x_preferred":[
        "Wushi"
    ],
    "name:fra_x_preferred":[
        "Wushi"
    ],
    "name:swe_x_preferred":[
        "Wushi"
    ],
    "name:und_x_variant":[
        "Xiawushi"
    ],
    "name:zho_x_preferred":[
        "\u4e4c\u77f3"
    ],
    "name:zho_x_variant":[
        "\u4e0b\u4e4c\u77f3"
    ],
    "wof:name":"Wushi",
    "wof:placetype":"locality"
},
  "geometry": {"coordinates":[117.806,27.9692],"type":"Point"}
}