{
  "type": "Feature",
  "properties": {
    "gn:admin1_code":"04",
    "gn:asciiname":"Laoyezhuang",
    "gn:cc2":"CN",
    "gn:country_code":"CN",
    "gn:dem":8,
    "gn:feature_class":"P",
    "gn:feature_code":"PPL",
    "gn:name":"Laoyezhuang",
    "gn:population":0,
    "gn:timezone":"Asia/Shanghai",
    "iso:country":"CN",
    "name:und_x_variant":[
        "Lao-yeh-chuang",
        "Laoyezhuang",
        "\u8001\u53f6\u5e84"
    ],
    "wof:name":"Laoyezhuang",
    "wof:placetype":"locality"
},
  "geometry": {"coordinates":[120.08333,32.26667],"type":"Point"}
}