{
  "type": "Feature",
  "properties": {
    "gn:admin1_code":"11.0",
    "gn:asciiname":"Xiaodongpo",
    "gn:country_code":"CN",
    "gn:dem":812,
    "gn:feature_class":"P",
    "gn:feature_code":"PPL",
    "gn:name":"Xiaodongpo",
    "gn:population":0,
    "gn:timezone":"Asia/Shanghai",
    "iso:country":"CN",
    "name:zho_x_preferred":[
        "\u785d\u6d1e\u5761"
    ],
    "wof:name":"Xiaodongpo",
    "wof:placetype":"locality"
},
  "geometry": {"coordinates":[109.45671000000002,29.35916],"type":"Point"}
}