{
  "type": "Feature",
  "properties": {
    "gn:admin1_code":"5.0",
    "gn:asciiname":"Longxing",
    "gn:country_code":"CN",
    "gn:dem":363,
    "gn:feature_class":"P",
    "gn:feature_code":"PPL",
    "gn:name":"Longxing",
    "gn:population":0,
    "gn:timezone":"Asia/Shanghai",
    "iso:country":"CN",
    "name:deu_x_preferred":[
        "Longxing"
    ],
    "name:und_x_variant":[
        "\u9f99\u5174"
    ],
    "wof:name":"Longxing",
    "wof:placetype":"locality"
},
  "geometry": {"coordinates":[129.03852000000001,43.05392],"type":"Point"}
}