{
  "type": "Feature",
  "properties": {
    "gn:admin1_code":"9",
    "gn:asciiname":"Dabeizhang",
    "gn:country_code":"CN",
    "gn:dem":50,
    "gn:feature_class":"P",
    "gn:feature_code":"PPL",
    "gn:name":"Dabeizhang",
    "gn:population":0,
    "gn:timezone":"Asia/Shanghai",
    "iso:country":"CN",
    "name:zho_x_preferred":[
        "\u5927\u5317\u5f20"
    ],
    "wof:name":"Dabeizhang",
    "wof:placetype":"locality"
},
  "geometry": {"coordinates":[115.16116,36.19081],"type":"Point"}
}