{
  "type": "Feature",
  "properties": {
    "gn:admin1_code":"32.0",
    "gn:asciiname":"Yingshengsi",
    "gn:country_code":"CN",
    "gn:dem":299,
    "gn:feature_class":"P",
    "gn:feature_code":"PPL",
    "gn:name":"Yingshengsi",
    "gn:population":0,
    "gn:timezone":"Asia/Shanghai",
    "iso:country":"CN",
    "name:zho_x_preferred":[
        "\u5e94\u5723\u5bfa"
    ],
    "wof:name":"Yingshengsi",
    "wof:placetype":"locality"
},
  "geometry": {"coordinates":[106.16095,30.64467],"type":"Point"}
}