{
  "type": "Feature",
  "properties": {
    "gn:admin1_code":"5.0",
    "gn:asciiname":"Ershihaocun",
    "gn:country_code":"CN",
    "gn:dem":207,
    "gn:feature_class":"P",
    "gn:feature_code":"PPLF",
    "gn:name":"Ershihaocun",
    "gn:population":0,
    "gn:timezone":"Asia/Shanghai",
    "iso:country":"CN",
    "name:zho_x_preferred":[
        "\u4e8c\u5341\u53f7\u6751"
    ],
    "wof:name":"Ershihaocun",
    "wof:placetype":"locality"
},
  "geometry": {"coordinates":[126.31023,45.03937],"type":"Point"}
}