{
  "type": "Feature",
  "properties": {
    "gn:admin1_code":"4.0",
    "gn:asciiname":"Lixiucun",
    "gn:country_code":"CN",
    "gn:dem":4,
    "gn:feature_class":"P",
    "gn:feature_code":"PPL",
    "gn:name":"Lixiucun",
    "gn:population":0,
    "gn:timezone":"Asia/Shanghai",
    "iso:country":"CN",
    "name:zho_x_preferred":[
        "\u674e\u79c0\u6751"
    ],
    "wof:name":"Lixiucun",
    "wof:placetype":"locality"
},
  "geometry": {"coordinates":[120.25348,32.99707],"type":"Point"}
}