{
  "type": "Feature",
  "properties": {
    "gn:admin1_code":"29",
    "gn:asciiname":"Zhongtianchong",
    "gn:country_code":"CN",
    "gn:dem":1990,
    "gn:feature_class":"P",
    "gn:feature_code":"PPL",
    "gn:name":"Zhongtianchong",
    "gn:population":0,
    "gn:timezone":"Asia/Shanghai",
    "iso:country":"CN",
    "name:zho_x_preferred":[
        "\u79cd\u7530\u51b2"
    ],
    "wof:name":"Zhongtianchong",
    "wof:placetype":"locality"
},
  "geometry": {"coordinates":[102.26506999999999,24.93583],"type":"Point"}
}