{
  "type": "Feature",
  "properties": {
    "gn:admin1_code":"19.0",
    "gn:asciiname":"Jixiangbu",
    "gn:country_code":"CN",
    "gn:dem":35,
    "gn:feature_class":"P",
    "gn:feature_code":"PPL",
    "gn:name":"Jixiangbu",
    "gn:population":0,
    "gn:timezone":"Asia/Shanghai",
    "iso:country":"CN",
    "name:und_x_variant":[
        "Jixiangbao",
        "Jixiangbu"
    ],
    "name:zho_x_preferred":[
        "\u5409\u7965\u5821"
    ],
    "wof:name":"Jixiangbu",
    "wof:placetype":"locality"
},
  "geometry": {"coordinates":[122.94799999999999,42.0714],"type":"Point"}
}