{
  "type": "Feature",
  "properties": {
    "gn:admin1_code":"19.0",
    "gn:asciiname":"Xiaoyanggou",
    "gn:country_code":"CN",
    "gn:dem":242,
    "gn:feature_class":"P",
    "gn:feature_code":"PPL",
    "gn:name":"Xiaoyanggou",
    "gn:population":0,
    "gn:timezone":"Asia/Shanghai",
    "iso:country":"CN",
    "name:und_x_variant":[
        "\u5c0f\u9633\u6c9f"
    ],
    "name:zho_x_preferred":[
        "\u5c0f\u9633\u6c9f"
    ],
    "wof:name":"Xiaoyanggou",
    "wof:placetype":"locality"
},
  "geometry": {"coordinates":[125.44164000000001,40.90302],"type":"Point"}
}