{
  "type": "Feature",
  "properties": {
    "gn:admin1_code":"7.0",
    "gn:asciiname":"Wangkeng",
    "gn:country_code":"CN",
    "gn:dem":187,
    "gn:feature_class":"P",
    "gn:feature_code":"PPL",
    "gn:name":"Wangkeng",
    "gn:population":0,
    "gn:timezone":"Asia/Shanghai",
    "iso:country":"CN",
    "name:und_x_variant":[
        "\u738b\u5751"
    ],
    "name:zho_x_preferred":[
        "\u738b\u5751"
    ],
    "wof:name":"Wangkeng",
    "wof:placetype":"locality"
},
  "geometry": {"coordinates":[118.49011000000002,26.28219],"type":"Point"}
}