{
  "type": "Feature",
  "properties": {
    "gn:admin1_code":"29",
    "gn:asciiname":"Xiaoshao",
    "gn:country_code":"CN",
    "gn:dem":2004,
    "gn:feature_class":"P",
    "gn:feature_code":"PPL",
    "gn:name":"Xiaoshao",
    "gn:population":0,
    "gn:timezone":"Asia/Shanghai",
    "iso:country":"CN",
    "name:und_x_variant":[
        "\u5c0f\u54e8"
    ],
    "wof:name":"Xiaoshao",
    "wof:placetype":"locality"
},
  "geometry": {"coordinates":[103.83027,25.23259],"type":"Point"}
}