{
  "type": "Feature",
  "properties": {
    "gn:admin1_code":"14.0",
    "gn:asciiname":"Parlong",
    "gn:country_code":"CN",
    "gn:dem":3793,
    "gn:feature_class":"P",
    "gn:feature_code":"PPLF",
    "gn:name":"Parlong",
    "gn:population":0,
    "gn:timezone":"Asia/Urumqi",
    "iso:country":"CN",
    "name:bod_x_preferred":[
        "Parlong"
    ],
    "name:zho_x_preferred":[
        "Balong"
    ],
    "name:zho_x_variant":[
        "\u5df4\u9f99"
    ],
    "wof:name":"Parlong",
    "wof:placetype":"locality"
},
  "geometry": {"coordinates":[97.00824,31.281],"type":"Point"}
}