{
  "type": "Feature",
  "properties": {
    "gn:admin1_code":"24.0",
    "gn:asciiname":"Xishizi",
    "gn:country_code":"CN",
    "gn:dem":1788,
    "gn:feature_class":"P",
    "gn:feature_code":"PPL",
    "gn:name":"Xishizi",
    "gn:population":0,
    "gn:timezone":"Asia/Shanghai",
    "iso:country":"CN",
    "name:und_x_variant":[
        "\u897f\u5341\u5b57"
    ],
    "name:zho_x_preferred":[
        "\u897f\u5341\u5b57"
    ],
    "wof:name":"Xishizi",
    "wof:placetype":"locality"
},
  "geometry": {"coordinates":[113.59479,39.5306],"type":"Point"}
}