{
  "type": "Feature",
  "properties": {
    "gn:admin1_code":"11.0",
    "gn:asciiname":"Xinwunei",
    "gn:country_code":"CN",
    "gn:dem":104,
    "gn:feature_class":"P",
    "gn:feature_code":"PPL",
    "gn:name":"Xinwunei",
    "gn:population":0,
    "gn:timezone":"Asia/Shanghai",
    "iso:country":"CN",
    "name:zho_x_preferred":[
        "\u65b0\u5c4b\u5185"
    ],
    "wof:name":"Xinwunei",
    "wof:placetype":"locality"
},
  "geometry": {"coordinates":[113.67438,28.54938],"type":"Point"}
}