{
  "type": "Feature",
  "properties": {
    "gn:admin1_code":"31",
    "gn:asciiname":"Lao'Ou",
    "gn:country_code":"CN",
    "gn:dem":31,
    "gn:feature_class":"P",
    "gn:feature_code":"PPL",
    "gn:name":"Lao\u2019Ou",
    "gn:population":0,
    "gn:timezone":"Asia/Shanghai",
    "iso:country":"CN",
    "name:und_x_variant":[
        "Lao\u2019Ou",
        "\u8001\u6bb4"
    ],
    "wof:name":"Lao'Ou",
    "wof:placetype":"locality"
},
  "geometry": {"coordinates":[108.71599999999999,19.0144],"type":"Point"}
}