{
  "type": "Feature",
  "properties": {
    "gn:admin1_code":"5.0",
    "gn:asciiname":"Heqincun",
    "gn:country_code":"CN",
    "gn:dem":149,
    "gn:feature_class":"P",
    "gn:feature_code":"PPL",
    "gn:name":"Heqincun",
    "gn:population":0,
    "gn:timezone":"Asia/Shanghai",
    "iso:country":"CN",
    "name:zho_x_preferred":[
        "\u548c\u4eb2\u6751"
    ],
    "wof:name":"Heqincun",
    "wof:placetype":"locality"
},
  "geometry": {"coordinates":[123.87956,43.72117],"type":"Point"}
}