{
  "type": "Feature",
  "properties": {
    "gn:admin1_code":"32.0",
    "gn:asciiname":"Mumuguo",
    "gn:country_code":"CN",
    "gn:dem":2633,
    "gn:feature_class":"P",
    "gn:feature_code":"PPL",
    "gn:name":"Mumuguo",
    "gn:population":0,
    "gn:timezone":"Asia/Shanghai",
    "iso:country":"CN",
    "name:zho_x_preferred":[
        "\u7261\u76ee\u8fc7"
    ],
    "wof:name":"Mumuguo",
    "wof:placetype":"locality"
},
  "geometry": {"coordinates":[103.1281,27.88179],"type":"Point"}
}