{
  "type": "Feature",
  "properties": {
    "gn:admin1_code":"19.0",
    "gn:asciiname":"Gujiazi",
    "gn:country_code":"CN",
    "gn:dem":299,
    "gn:feature_class":"P",
    "gn:feature_code":"PPL",
    "gn:name":"Gujiazi",
    "gn:population":0,
    "gn:timezone":"Asia/Shanghai",
    "iso:country":"CN",
    "name:zho_x_preferred":[
        "\u5b64\u5bb6\u5b50"
    ],
    "wof:name":"Gujiazi",
    "wof:placetype":"locality"
},
  "geometry": {"coordinates":[124.41153,42.10909],"type":"Point"}
}