{
  "type": "Feature",
  "properties": {
    "gn:admin1_code":"24.0",
    "gn:asciiname":"Badun",
    "gn:country_code":"CN",
    "gn:dem":1615,
    "gn:feature_class":"P",
    "gn:feature_code":"PPL",
    "gn:name":"Badun",
    "gn:population":0,
    "gn:timezone":"Asia/Shanghai",
    "iso:country":"CN",
    "name:und_x_variant":[
        "\u516b\u58a9"
    ],
    "name:zho_x_preferred":[
        "\u516b\u58a9"
    ],
    "wof:name":"Badun",
    "wof:placetype":"locality"
},
  "geometry": {"coordinates":[112.02705,39.84711],"type":"Point"}
}