{
  "type": "Feature",
  "properties": {
    "gn:admin1_code":"19.0",
    "gn:asciiname":"Datanggou",
    "gn:country_code":"CN",
    "gn:dem":444,
    "gn:feature_class":"P",
    "gn:feature_code":"PPL",
    "gn:name":"Datanggou",
    "gn:population":0,
    "gn:timezone":"Asia/Shanghai",
    "iso:country":"CN",
    "name:zho_x_preferred":[
        "\u5927\u6c64\u6c9f"
    ],
    "wof:name":"Datanggou",
    "wof:placetype":"locality"
},
  "geometry": {"coordinates":[119.41412,40.93787],"type":"Point"}
}