{
  "type": "Feature",
  "properties": {
    "gn:admin1_code":"3.0",
    "gn:asciiname":"Lishuping",
    "gn:country_code":"CN",
    "gn:dem":102,
    "gn:feature_class":"P",
    "gn:feature_code":"PPL",
    "gn:name":"Lishuping",
    "gn:population":0,
    "gn:timezone":"Asia/Shanghai",
    "iso:country":"CN",
    "name:und_x_variant":[
        "\u68a8\u6811\u576a"
    ],
    "wof:name":"Lishuping",
    "wof:placetype":"locality"
},
  "geometry": {"coordinates":[114.54895,28.31261],"type":"Point"}
}