{
  "type": "Feature",
  "properties": {
    "gn:admin1_code":"1.0",
    "gn:asciiname":"Zouloucun",
    "gn:country_code":"CN",
    "gn:dem":28,
    "gn:feature_class":"P",
    "gn:feature_code":"PPL",
    "gn:name":"Zouloucun",
    "gn:population":0,
    "gn:timezone":"Asia/Shanghai",
    "iso:country":"CN",
    "name:und_x_variant":[
        "Zoulou"
    ],
    "name:zho_x_preferred":[
        "\u90b9\u697c\u6751"
    ],
    "wof:name":"Zouloucun",
    "wof:placetype":"locality"
},
  "geometry": {"coordinates":[116.51667,33.775],"type":"Point"}
}