{
  "type": "Feature",
  "properties": {
    "gn:admin1_code":"4.0",
    "gn:asciiname":"Wangxiaonian",
    "gn:country_code":"CN",
    "gn:dem":3,
    "gn:feature_class":"P",
    "gn:feature_code":"PPL",
    "gn:name":"Wangxiaonian",
    "gn:population":0,
    "gn:timezone":"Asia/Shanghai",
    "iso:country":"CN",
    "name:und_x_variant":[
        "\u738b\u5c0f\u78be"
    ],
    "name:zho_x_preferred":[
        "\u738b\u5c0f\u78be"
    ],
    "wof:name":"Wangxiaonian",
    "wof:placetype":"locality"
},
  "geometry": {"coordinates":[120.00333999999999,33.08566],"type":"Point"}
}