{
  "type": "Feature",
  "properties": {
    "gn:admin1_code":"26.0",
    "gn:asciiname":"Zhoujia Dayuanzi",
    "gn:country_code":"CN",
    "gn:dem":671,
    "gn:feature_class":"P",
    "gn:feature_code":"PPL",
    "gn:name":"Zhoujia Dayuanzi",
    "gn:population":0,
    "gn:timezone":"Asia/Shanghai",
    "iso:country":"CN",
    "name:zho_x_preferred":[
        "\u5468\u5bb6\u5927\u9662\u5b50"
    ],
    "wof:name":"Zhoujia Dayuanzi",
    "wof:placetype":"locality"
},
  "geometry": {"coordinates":[109.78449999999999,32.70732],"type":"Point"}
}