{
  "type": "Feature",
  "properties": {
    "gn:admin1_code":"10",
    "gn:asciiname":"Qianhecha",
    "gn:country_code":"CN",
    "gn:dem":383,
    "gn:feature_class":"P",
    "gn:feature_code":"PPL",
    "gn:name":"Qianhecha",
    "gn:population":0,
    "gn:timezone":"Asia/Shanghai",
    "iso:country":"CN",
    "name:zho_x_preferred":[
        "\u524d\u6cb3\u5c94"
    ],
    "wof:name":"Qianhecha",
    "wof:placetype":"locality"
},
  "geometry": {"coordinates":[114.114,37.1869],"type":"Point"}
}