{
  "type": "Feature",
  "properties": {
    "gn:admin1_code":"05",
    "gn:asciiname":"Santaicun",
    "gn:country_code":"CN",
    "gn:dem":171,
    "gn:feature_class":"P",
    "gn:feature_code":"PPL",
    "gn:name":"Santaicun",
    "gn:population":0,
    "gn:timezone":"Asia/Shanghai",
    "iso:country":"CN",
    "name:und_x_variant":[
        "San-t\u2019ai-t\u2019un",
        "Santai",
        "Santaicun"
    ],
    "name:zho_x_preferred":[
        "\u4e09\u53f0\u6751"
    ],
    "wof:name":"Santaicun",
    "wof:placetype":"locality"
},
  "geometry": {"coordinates":[126.37073999999998,44.5016],"type":"Point"}
}