{
  "type": "Feature",
  "properties": {
    "gn:admin1_code":"30.0",
    "gn:asciiname":"Shangdongcun",
    "gn:country_code":"CN",
    "gn:dem":306,
    "gn:feature_class":"P",
    "gn:feature_code":"PPL",
    "gn:name":"Shangdongcun",
    "gn:population":0,
    "gn:timezone":"Asia/Shanghai",
    "iso:country":"CN",
    "name:zho_x_preferred":[
        "\u4e0a\u6d1e\u6751"
    ],
    "wof:name":"Shangdongcun",
    "wof:placetype":"locality"
},
  "geometry": {"coordinates":[113.74593,23.89724],"type":"Point"}
}