{
  "type": "Feature",
  "properties": {
    "gn:admin1_code":"11.0",
    "gn:asciiname":"Suozhai",
    "gn:country_code":"CN",
    "gn:dem":601,
    "gn:feature_class":"P",
    "gn:feature_code":"PPL",
    "gn:name":"Suozhai",
    "gn:population":0,
    "gn:timezone":"Asia/Shanghai",
    "iso:country":"CN",
    "name:zho_x_preferred":[
        "\u6240\u5b85"
    ],
    "wof:name":"Suozhai",
    "wof:placetype":"locality"
},
  "geometry": {"coordinates":[109.99021,29.1272],"type":"Point"}
}