{
  "type": "Feature",
  "properties": {
    "gn:admin1_code":"30.0",
    "gn:asciiname":"Dong'ao",
    "gn:country_code":"CN",
    "gn:dem":36,
    "gn:feature_class":"P",
    "gn:feature_code":"PPL",
    "gn:name":"Dong\u2019ao",
    "gn:population":0,
    "gn:timezone":"Asia/Shanghai",
    "iso:country":"CN",
    "name:zho_x_preferred":[
        "\u4e1c\u6fb3"
    ],
    "name:zho_x_variant":[
        "Dong\u2019ao"
    ],
    "wof:name":"Dong'ao",
    "wof:placetype":"locality"
},
  "geometry": {"coordinates":[117.11756,23.40346],"type":"Point"}
}