{
  "type": "Feature",
  "properties": {
    "gn:admin1_code":"26.0",
    "gn:asciiname":"Fenwangcun",
    "gn:country_code":"CN",
    "gn:dem":642,
    "gn:feature_class":"P",
    "gn:feature_code":"PPL",
    "gn:name":"Fenwangcun",
    "gn:population":0,
    "gn:timezone":"Asia/Shanghai",
    "iso:country":"CN",
    "name:zho_x_preferred":[
        "\u7c89\u738b\u6751"
    ],
    "wof:name":"Fenwangcun",
    "wof:placetype":"locality"
},
  "geometry": {"coordinates":[107.60030999999999,34.39872],"type":"Point"}
}