{
  "type": "Feature",
  "properties": {
    "gn:admin1_code":"1.0",
    "gn:asciiname":"Xinshengcun",
    "gn:country_code":"CN",
    "gn:dem":19,
    "gn:feature_class":"P",
    "gn:feature_code":"PPL",
    "gn:name":"Xinshengcun",
    "gn:population":0,
    "gn:timezone":"Asia/Shanghai",
    "iso:country":"CN",
    "name:zho_x_preferred":[
        "\u65b0\u751f\u6751"
    ],
    "wof:name":"Xinshengcun",
    "wof:placetype":"locality"
},
  "geometry": {"coordinates":[117.76868,31.22449000000001],"type":"Point"}
}