{
  "type": "Feature",
  "properties": {
    "gn:admin1_code":"26.0",
    "gn:asciiname":"Fengjiayuancun",
    "gn:country_code":"CN",
    "gn:dem":1042,
    "gn:feature_class":"P",
    "gn:feature_code":"PPL",
    "gn:name":"Fengjiayuancun",
    "gn:population":0,
    "gn:timezone":"Asia/Shanghai",
    "iso:country":"CN",
    "name:zho_x_preferred":[
        "\u51af\u5bb6\u586c\u6751"
    ],
    "wof:name":"Fengjiayuancun",
    "wof:placetype":"locality"
},
  "geometry": {"coordinates":[109.27134,35.16112],"type":"Point"}
}