{
  "type": "Feature",
  "properties": {
    "gn:admin1_code":"25.0",
    "gn:asciiname":"Liujiashiqiaocun",
    "gn:country_code":"CN",
    "gn:dem":33,
    "gn:feature_class":"P",
    "gn:feature_code":"PPL",
    "gn:name":"Liujiashiqiaocun",
    "gn:population":0,
    "gn:timezone":"Asia/Shanghai",
    "iso:country":"CN",
    "name:zho_x_preferred":[
        "\u5218\u5bb6\u77f3\u6865\u6751"
    ],
    "wof:name":"Liujiashiqiaocun",
    "wof:placetype":"locality"
},
  "geometry": {"coordinates":[119.33474,36.52564],"type":"Point"}
}