{
  "type": "Feature",
  "properties": {
    "gn:admin1_code":"10.0",
    "gn:asciiname":"Wuchangfeng",
    "gn:country_code":"CN",
    "gn:dem":7,
    "gn:feature_class":"P",
    "gn:feature_code":"PPL",
    "gn:name":"Wuchangfeng",
    "gn:population":0,
    "gn:timezone":"Asia/Shanghai",
    "iso:country":"CN",
    "name:zho_x_preferred":[
        "\u6b66\u5e38\u4e30"
    ],
    "wof:name":"Wuchangfeng",
    "wof:placetype":"locality"
},
  "geometry": {"coordinates":[117.488,38.1237],"type":"Point"}
}