{
  "type": "Feature",
  "properties": {
    "gn:admin1_code":"4.0",
    "gn:asciiname":"Huangxucun",
    "gn:country_code":"CN",
    "gn:dem":7,
    "gn:feature_class":"P",
    "gn:feature_code":"PPL",
    "gn:name":"Huangxucun",
    "gn:population":0,
    "gn:timezone":"Asia/Shanghai",
    "iso:country":"CN",
    "name:zho_x_preferred":[
        "\u7687\u5729\u6751"
    ],
    "wof:name":"Huangxucun",
    "wof:placetype":"locality"
},
  "geometry": {"coordinates":[119.42749000000001,33.84473],"type":"Point"}
}