{
  "type": "Feature",
  "properties": {
    "gn:admin1_code":"11.0",
    "gn:asciiname":"Zengjia Citang",
    "gn:country_code":"CN",
    "gn:dem":33,
    "gn:feature_class":"P",
    "gn:feature_code":"PPL",
    "gn:name":"Zengjia Citang",
    "gn:population":0,
    "gn:timezone":"Asia/Shanghai",
    "iso:country":"CN",
    "name:zho_x_preferred":[
        "Zengjia Citang"
    ],
    "name:zho_x_variant":[
        "\u66fe\u5bb6\u7960\u5802"
    ],
    "wof:name":"Zengjia Citang",
    "wof:placetype":"locality"
},
  "geometry": {"coordinates":[111.83317,29.01434],"type":"Point"}
}