{
  "type": "Feature",
  "properties": {
    "gn:admin1_code":"25",
    "gn:asciiname":"Dangaixin",
    "gn:country_code":"CN",
    "gn:dem":47,
    "gn:feature_class":"P",
    "gn:feature_code":"PPL",
    "gn:name":"Dangaixin",
    "gn:population":0,
    "gn:timezone":"Asia/Shanghai",
    "iso:country":"CN",
    "name:zho_x_preferred":[
        "\u5355\u8be5\u65b0"
    ],
    "wof:name":"Dangaixin",
    "wof:placetype":"locality"
},
  "geometry": {"coordinates":[115.94895,35.52241],"type":"Point"}
}