{
  "type": "Feature",
  "properties": {
    "gn:admin1_code":"25",
    "gn:asciiname":"Ruanlou",
    "gn:country_code":"CN",
    "gn:dem":46,
    "gn:feature_class":"P",
    "gn:feature_code":"PPL",
    "gn:name":"Ruanlou",
    "gn:population":0,
    "gn:timezone":"Asia/Shanghai",
    "iso:country":"CN",
    "name:zho_x_preferred":[
        "\u962e\u697c"
    ],
    "wof:name":"Ruanlou",
    "wof:placetype":"locality"
},
  "geometry": {"coordinates":[116.194,34.8223],"type":"Point"}
}