{
  "type": "Feature",
  "properties": {
    "gn:admin1_code":"4.0",
    "gn:asciiname":"Wanzili",
    "gn:country_code":"CN",
    "gn:dem":4,
    "gn:feature_class":"P",
    "gn:feature_code":"PPL",
    "gn:name":"Wanzili",
    "gn:population":0,
    "gn:timezone":"Asia/Shanghai",
    "iso:country":"CN",
    "name:und_x_variant":[
        "\u4e07\u5b50\u91cc"
    ],
    "wof:name":"Wanzili",
    "wof:placetype":"locality"
},
  "geometry": {"coordinates":[120.09968000000001,32.90985],"type":"Point"}
}