{
  "type": "Feature",
  "properties": {
    "gn:admin1_code":"3.0",
    "gn:asciiname":"Hezhou",
    "gn:country_code":"CN",
    "gn:dem":84,
    "gn:feature_class":"P",
    "gn:feature_code":"PPL",
    "gn:name":"Hezhou",
    "gn:population":0,
    "gn:timezone":"Asia/Shanghai",
    "iso:country":"CN",
    "name:afr_x_preferred":[
        "Hezhou"
    ],
    "name:ara_x_preferred":[
        "\u0647\u064a\u0634\u0648"
    ],
    "name:cat_x_preferred":[
        "Hezhou"
    ],
    "name:cdo_x_preferred":[
        "H\u00f4\u0324-ci\u016d"
    ],
    "name:ces_x_preferred":[
        "Che-\u010dou"
    ],
    "name:dan_x_preferred":[
        "Hezhou"
    ],
    "name:deu_x_preferred":[
        "Hezhou"
    ],
    "name:eus_x_preferred":[
        "Hezhou"
    ],
    "name:fas_x_preferred":[
        "\u0647\u06cc\u0698\u0648"
    ],
    "name:fin_x_preferred":[
        "Hezhou"
    ],
    "name:fra_x_preferred":[
        "Hezhou"
    ],
    "name:hak_x_preferred":[
        "Fo-ch\u00fb-s\u1e73"
    ],
    "name:ita_x_preferred":[
        "Hezhou"
    ],
    "name:jpn_x_preferred":[
        "\u8cc0\u5dde\u5e02"
    ],
    "name:kik_x_preferred":[
        "Hezhou"
    ],
    "name:kor_x_preferred":[
        "\ud5c8\uc800\uc6b0\uc2dc"
    ],
    "name:nld_x_preferred":[
        "Hezhou"
    ],
    "name:nor_x_preferred":[
        "Hezhou"
    ],
    "name:pnb_x_preferred":[
        "\u06c1\u06cc\u0698\u0648\u0624"
    ],
    "name:pol_x_preferred":[
        "Hezhou"
    ],
    "name:por_x_preferred":[
        "Hezhou"
    ],
    "name:rus_x_preferred":[
        "\u0425\u044d\u0447\u0436\u043e\u0443"
    ],
    "name:spa_x_preferred":[
        "Hezhou"
    ],
    "name:swe_x_preferred":[
        "Hezhou"
    ],
    "name:tur_x_preferred":[
        "Hezhou"
    ],
    "name:ukr_x_preferred":[
        "\u0425\u0435\u0447\u0436\u043e\u0443"
    ],
    "name:und_x_variant":[
        "\u8377\u6d32"
    ],
    "name:urd_x_preferred":[
        "\u06c1\u06cc\u0698\u0648\u0648"
    ],
    "name:vie_x_preferred":[
        "H\u1ea1 Ch\u00e2u"
    ],
    "name:zha_x_preferred":[
        "Hohcouh"
    ],
    "name:zho_x_preferred":[
        "\u8d3a\u5dde\u5e02"
    ],
    "wof:name":"Hezhou",
    "wof:placetype":"locality"
},
  "geometry": {"coordinates":[115.16346,29.45188],"type":"Point"}
}