{
  "type": "Feature",
  "properties": {
    "gn:admin1_code":"3.0",
    "gn:asciiname":"Hezhou",
    "gn:country_code":"CN",
    "gn:dem":84,
    "gn:feature_class":"P",
    "gn:feature_code":"PPL",
    "gn:name":"Hezhou",
    "gn:population":0,
    "gn:timezone":"Asia/Shanghai",
    "iso:country":"CN",
    "name:und_x_variant":[
        "\u8377\u6d32"
    ],
    "wof:name":"Hezhou",
    "wof:placetype":"locality"
},
  "geometry": {"coordinates":[115.16346,29.45188],"type":"Point"}
}