{
  "type": "Feature",
  "properties": {
    "gn:admin1_code":"32.0",
    "gn:asciiname":"Guanwuzui",
    "gn:country_code":"CN",
    "gn:dem":324,
    "gn:feature_class":"P",
    "gn:feature_code":"PPL",
    "gn:name":"Guanwuzui",
    "gn:population":0,
    "gn:timezone":"Asia/Shanghai",
    "iso:country":"CN",
    "name:zho_x_preferred":[
        "\u89c2\u5c4b\u5480"
    ],
    "wof:name":"Guanwuzui",
    "wof:placetype":"locality"
},
  "geometry": {"coordinates":[107.20149000000001,30.35887],"type":"Point"}
}