{
  "type": "Feature",
  "properties": {
    "gn:admin1_code":"14.0",
    "gn:asciiname":"Xialuoniangcun",
    "gn:country_code":"CN",
    "gn:dem":3212,
    "gn:feature_class":"P",
    "gn:feature_code":"PPL",
    "gn:name":"Xialuoniangcun",
    "gn:population":0,
    "gn:timezone":"Asia/Urumqi",
    "iso:country":"CN",
    "name:zho_x_preferred":[
        "\u4e0b\u6d1b\u5a18\u6751"
    ],
    "wof:name":"Xialuoniangcun",
    "wof:placetype":"locality"
},
  "geometry": {"coordinates":[98.87808,30.43042],"type":"Point"}
}