{
  "type": "Feature",
  "properties": {
    "gn:admin1_code":"04",
    "gn:asciiname":"Picheng",
    "gn:cc2":"CN",
    "gn:country_code":"CN",
    "gn:dem":29,
    "gn:feature_class":"P",
    "gn:feature_code":"PPL",
    "gn:name":"Picheng",
    "gn:population":0,
    "gn:timezone":"Asia/Shanghai",
    "iso:country":"CN",
    "name:und_x_variant":[
        "P\u2019ei",
        "Sunpeichow",
        "Peichow",
        "Pihsien",
        "Peicheng",
        "Chiu-p\u2019ei-hsien",
        "P\u2019ei-hsien",
        "Peixian",
        "P\u2019ei-hsien-ch\u2019eng",
        "Picheng"
    ],
    "wof:name":"Picheng",
    "wof:placetype":"locality"
},
  "geometry": {"coordinates":[117.96666999999999,34.46667],"type":"Point"}
}