{
  "type": "Feature",
  "properties": {
    "gn:admin1_code":"30.0",
    "gn:asciiname":"Xinzhaicun",
    "gn:country_code":"CN",
    "gn:dem":73,
    "gn:feature_class":"P",
    "gn:feature_code":"PPL",
    "gn:name":"Xinzhaicun",
    "gn:population":0,
    "gn:timezone":"Asia/Shanghai",
    "iso:country":"CN",
    "name:zho_x_preferred":[
        "\u65b0\u5be8\u6751"
    ],
    "wof:name":"Xinzhaicun",
    "wof:placetype":"locality"
},
  "geometry": {"coordinates":[116.69808,24.3659],"type":"Point"}
}