{
  "type": "Feature",
  "properties": {
    "gn:admin1_code":"19.0",
    "gn:asciiname":"Dongtaipingzhuangcun",
    "gn:country_code":"CN",
    "gn:dem":159,
    "gn:feature_class":"P",
    "gn:feature_code":"PPL",
    "gn:name":"Dongtaipingzhuangcun",
    "gn:population":0,
    "gn:timezone":"Asia/Shanghai",
    "iso:country":"CN",
    "name:zho_x_preferred":[
        "\u4e1c\u592a\u5e73\u5e84\u6751"
    ],
    "wof:name":"Dongtaipingzhuangcun",
    "wof:placetype":"locality"
},
  "geometry": {"coordinates":[121.956,42.0558],"type":"Point"}
}