{
  "type": "Feature",
  "properties": {
    "gn:admin1_code":"15.0",
    "gn:asciiname":"Dagoutan",
    "gn:country_code":"CN",
    "gn:dem":2623,
    "gn:feature_class":"P",
    "gn:feature_code":"PPL",
    "gn:name":"Dagoutan",
    "gn:population":0,
    "gn:timezone":"Asia/Shanghai",
    "iso:country":"CN",
    "name:zho_x_preferred":[
        "\u5927\u6c9f\u6ee9"
    ],
    "wof:name":"Dagoutan",
    "wof:placetype":"locality"
},
  "geometry": {"coordinates":[103.47799999999999,36.9967],"type":"Point"}
}