{
  "type": "Feature",
  "properties": {
    "gn:admin1_code":"16.0",
    "gn:asciiname":"Jiaoyechong",
    "gn:country_code":"CN",
    "gn:dem":174,
    "gn:feature_class":"P",
    "gn:feature_code":"PPL",
    "gn:name":"Jiaoyechong",
    "gn:population":0,
    "gn:timezone":"Asia/Shanghai",
    "iso:country":"CN",
    "name:zho_x_preferred":[
        "\u8549\u53f6\u51b2"
    ],
    "wof:name":"Jiaoyechong",
    "wof:placetype":"locality"
},
  "geometry": {"coordinates":[111.157,24.3781],"type":"Point"}
}