{
  "type": "Feature",
  "properties": {
    "gn:admin1_code":"12.0",
    "gn:asciiname":"Xiazigou",
    "gn:country_code":"CN",
    "gn:dem":28,
    "gn:feature_class":"P",
    "gn:feature_code":"PPL",
    "gn:name":"Xiazigou",
    "gn:population":0,
    "gn:timezone":"Asia/Shanghai",
    "iso:country":"CN",
    "name:zho_x_preferred":[
        "\u867e\u5b50\u6c9f"
    ],
    "wof:name":"Xiazigou",
    "wof:placetype":"locality"
},
  "geometry": {"coordinates":[113.60756000000001,30.70848],"type":"Point"}
}