{
  "type": "Feature",
  "properties": {
    "gn:admin1_code":"2.0",
    "gn:asciiname":"Houshange",
    "gn:country_code":"CN",
    "gn:dem":96,
    "gn:feature_class":"P",
    "gn:feature_code":"PPL",
    "gn:name":"Houshange",
    "gn:population":0,
    "gn:timezone":"Asia/Shanghai",
    "iso:country":"CN",
    "name:zho_x_preferred":[
        "\u540e\u5c71\u845b"
    ],
    "wof:name":"Houshange",
    "wof:placetype":"locality"
},
  "geometry": {"coordinates":[121.29752000000001,29.20856],"type":"Point"}
}