{
  "type": "Feature",
  "properties": {
    "gn:admin1_code":"04",
    "gn:asciiname":"Baimu",
    "gn:cc2":"CN",
    "gn:country_code":"CN",
    "gn:dem":3,
    "gn:feature_class":"P",
    "gn:feature_code":"PPL",
    "gn:name":"Baimu",
    "gn:population":0,
    "gn:timezone":"Asia/Shanghai",
    "iso:country":"CN",
    "name:und_x_variant":[
        "Pai-mu-ch\u2019iao",
        "Baimu"
    ],
    "wof:name":"Baimu",
    "wof:placetype":"locality"
},
  "geometry": {"coordinates":[120.31667,32.01667],"type":"Point"}
}