{
  "type": "Feature",
  "properties": {
    "gn:admin1_code":"30",
    "gn:asciiname":"Ganzi Shuxia",
    "gn:country_code":"CN",
    "gn:dem":225,
    "gn:feature_class":"P",
    "gn:feature_code":"PPL",
    "gn:name":"Ganzi Shuxia",
    "gn:population":0,
    "gn:timezone":"Asia/Shanghai",
    "iso:country":"CN",
    "name:zho_x_preferred":[
        "\u67d1\u5b50\u6811\u4e0b"
    ],
    "wof:name":"Ganzi Shuxia",
    "wof:placetype":"locality"
},
  "geometry": {"coordinates":[115.81480000000001,24.3998],"type":"Point"}
}