{
  "type": "Feature",
  "properties": {
    "gn:admin1_code":"8.0",
    "gn:asciiname":"Xubao",
    "gn:country_code":"CN",
    "gn:dem":133,
    "gn:feature_class":"P",
    "gn:feature_code":"PPLA4",
    "gn:name":"Xubao",
    "gn:population":0,
    "gn:timezone":"Asia/Shanghai",
    "iso:country":"CN",
    "name:und_x_variant":[
        "Xubao Xiang"
    ],
    "name:zho_x_preferred":[
        "\u8bb8\u5821"
    ],
    "name:zho_x_variant":[
        "\u8bb8\u5821\u4e61"
    ],
    "wof:name":"Xubao",
    "wof:placetype":"locality"
},
  "geometry": {"coordinates":[126.67901000000001,46.1631],"type":"Point"}
}