{
  "type": "Feature",
  "properties": {
    "gn:admin1_code":"2.0",
    "gn:asciiname":"Changpuyang",
    "gn:country_code":"CN",
    "gn:dem":620,
    "gn:feature_class":"P",
    "gn:feature_code":"PPL",
    "gn:name":"Changpuyang",
    "gn:population":0,
    "gn:timezone":"Asia/Shanghai",
    "iso:country":"CN",
    "name:zho_x_preferred":[
        "\u83d6\u6d66\u6d0b"
    ],
    "wof:name":"Changpuyang",
    "wof:placetype":"locality"
},
  "geometry": {"coordinates":[119.38781000000002,27.74977],"type":"Point"}
}