{
  "type": "Feature",
  "properties": {
    "gn:admin1_code":"15.0",
    "gn:asciiname":"Dangjiagou",
    "gn:country_code":"CN",
    "gn:dem":1837,
    "gn:feature_class":"P",
    "gn:feature_code":"PPL",
    "gn:name":"Dangjiagou",
    "gn:population":0,
    "gn:timezone":"Asia/Shanghai",
    "iso:country":"CN",
    "name:zho_x_preferred":[
        "\u515a\u5bb6\u6c9f"
    ],
    "wof:name":"Dangjiagou",
    "wof:placetype":"locality"
},
  "geometry": {"coordinates":[106.28100000000001,34.9948],"type":"Point"}
}