{
  "type": "Feature",
  "properties": {
    "gn:admin1_code":"14.0",
    "gn:asciiname":"Shengelong",
    "gn:country_code":"CN",
    "gn:dem":4106,
    "gn:feature_class":"P",
    "gn:feature_code":"PPL",
    "gn:name":"Shengelong",
    "gn:population":0,
    "gn:timezone":"Asia/Urumqi",
    "iso:country":"CN",
    "name:zho_x_preferred":[
        "\u7533\u683c\u9f99"
    ],
    "wof:name":"Shengelong",
    "wof:placetype":"locality"
},
  "geometry": {"coordinates":[87.52200000000001,29.1631],"type":"Point"}
}