{
  "type": "Feature",
  "properties": {
    "gn:admin1_code":"2.0",
    "gn:asciiname":"Niubidong",
    "gn:country_code":"CN",
    "gn:dem":53,
    "gn:feature_class":"P",
    "gn:feature_code":"PPL",
    "gn:name":"Niubidong",
    "gn:population":0,
    "gn:timezone":"Asia/Shanghai",
    "iso:country":"CN",
    "name:zho_x_preferred":[
        "\u725b\u9f3b\u6d1e"
    ],
    "wof:name":"Niubidong",
    "wof:placetype":"locality"
},
  "geometry": {"coordinates":[121.00673999999999,28.15377],"type":"Point"}
}