{
  "type": "Feature",
  "properties": {
    "gn:admin1_code":"09",
    "gn:asciiname":"Lixindian",
    "gn:cc2":"CN",
    "gn:country_code":"CN",
    "gn:dem":95,
    "gn:feature_class":"P",
    "gn:feature_code":"PPL",
    "gn:name":"Lixindian",
    "gn:population":0,
    "gn:timezone":"Asia/Shanghai",
    "iso:country":"CN",
    "name:und_x_variant":[
        "Li-hsin-tien",
        "Lixindian"
    ],
    "wof:name":"Lixindian",
    "wof:placetype":"locality"
},
  "geometry": {"coordinates":[114.0025,32.53361],"type":"Point"}
}