{
  "type": "Feature",
  "properties": {
    "gn:admin1_code":"20.0",
    "gn:asciiname":"Wubaoshan",
    "gn:country_code":"CN",
    "gn:dem":1446,
    "gn:feature_class":"P",
    "gn:feature_code":"PPL",
    "gn:name":"Wubaoshan",
    "gn:population":0,
    "gn:timezone":"Asia/Shanghai",
    "iso:country":"CN",
    "name:und_x_variant":[
        "\u4e94\u5b9d\u5c71"
    ],
    "wof:name":"Wubaoshan",
    "wof:placetype":"locality"
},
  "geometry": {"coordinates":[113.02847,41.92891],"type":"Point"}
}