{
  "type": "Feature",
  "properties": {
    "gn:admin1_code":"12.0",
    "gn:asciiname":"Zhengjiaping",
    "gn:country_code":"CN",
    "gn:dem":1156,
    "gn:feature_class":"P",
    "gn:feature_code":"PPL",
    "gn:name":"Zhengjiaping",
    "gn:population":0,
    "gn:timezone":"Asia/Shanghai",
    "iso:country":"CN",
    "name:zho_x_preferred":[
        "\u90d1\u5bb6\u576a"
    ],
    "wof:name":"Zhengjiaping",
    "wof:placetype":"locality"
},
  "geometry": {"coordinates":[109.79619,31.71153],"type":"Point"}
}