{
  "type": "Feature",
  "properties": {
    "gn:admin1_code":"32.0",
    "gn:asciiname":"Erba",
    "gn:country_code":"CN",
    "gn:dem":1501,
    "gn:feature_class":"P",
    "gn:feature_code":"PPL",
    "gn:name":"Erba",
    "gn:population":0,
    "gn:timezone":"Asia/Shanghai",
    "iso:country":"CN",
    "name:ceb_x_preferred":[
        "Erba"
    ],
    "name:deu_x_preferred":[
        "Erba"
    ],
    "name:ita_x_preferred":[
        "Erba"
    ],
    "name:pol_x_preferred":[
        "Erba"
    ],
    "name:rus_x_preferred":[
        "\u042d\u0440\u0431\u0430"
    ],
    "name:spa_x_preferred":[
        "Erba"
    ],
    "name:swe_x_preferred":[
        "Erba"
    ],
    "name:zho_x_preferred":[
        "\u4e8c\u575d"
    ],
    "wof:name":"Erba",
    "wof:placetype":"locality"
},
  "geometry": {"coordinates":[103.46829,28.54016],"type":"Point"}
}