{
  "type": "Feature",
  "properties": {
    "gn:admin1_code":"29.0",
    "gn:asciiname":"Xiaomaidi",
    "gn:country_code":"CN",
    "gn:dem":1488,
    "gn:feature_class":"P",
    "gn:feature_code":"PPL",
    "gn:name":"Xiaomaidi",
    "gn:population":0,
    "gn:timezone":"Asia/Shanghai",
    "iso:country":"CN",
    "name:zho_x_preferred":[
        "\u5c0f\u9ea6\u5730"
    ],
    "wof:name":"Xiaomaidi",
    "wof:placetype":"locality"
},
  "geometry": {"coordinates":[100.58199999999999,24.4238],"type":"Point"}
}