{
  "type": "Feature",
  "properties": {
    "gn:admin1_code":"7.0",
    "gn:asciiname":"Longdongcun",
    "gn:country_code":"CN",
    "gn:dem":293,
    "gn:feature_class":"P",
    "gn:feature_code":"PPL",
    "gn:name":"Longdongcun",
    "gn:population":0,
    "gn:timezone":"Asia/Shanghai",
    "iso:country":"CN",
    "name:zho_x_preferred":[
        "\u9f99\u4e1c\u6751"
    ],
    "wof:name":"Longdongcun",
    "wof:placetype":"locality"
},
  "geometry": {"coordinates":[117.44226999999999,24.33144],"type":"Point"}
}