{
  "type": "Feature",
  "properties": {
    "gn:admin1_code":"9",
    "gn:asciiname":"Xianfang",
    "gn:country_code":"CN",
    "gn:dem":443,
    "gn:feature_class":"P",
    "gn:feature_code":"PPL",
    "gn:name":"Xianfang",
    "gn:population":0,
    "gn:timezone":"Asia/Shanghai",
    "iso:country":"CN",
    "name:und_x_variant":[
        "\u732e\u623f",
        "Xianfang"
    ],
    "wof:name":"Xianfang",
    "wof:placetype":"locality"
},
  "geometry": {"coordinates":[112.06789000000001,33.5487],"type":"Point"}
}