{
  "type": "Feature",
  "properties": {
    "gn:admin1_code":"24.0",
    "gn:asciiname":"Xiaohejiabucun",
    "gn:country_code":"CN",
    "gn:dem":1710,
    "gn:feature_class":"P",
    "gn:feature_code":"PPL",
    "gn:name":"Xiaohejiabucun",
    "gn:population":0,
    "gn:timezone":"Asia/Shanghai",
    "iso:country":"CN",
    "name:und_x_variant":[
        "\u5c0f\u8d3a\u5bb6\u5821\u6751"
    ],
    "name:zho_x_preferred":[
        "\u5c0f\u8d3a\u5bb6\u5821\u6751"
    ],
    "wof:name":"Xiaohejiabucun",
    "wof:placetype":"locality"
},
  "geometry": {"coordinates":[114.01215000000001,39.85558],"type":"Point"}
}