{
  "type": "Feature",
  "properties": {
    "gn:admin1_code":"32.0",
    "gn:asciiname":"Gongminxin",
    "gn:country_code":"CN",
    "gn:dem":765,
    "gn:feature_class":"P",
    "gn:feature_code":"PPL",
    "gn:name":"Gongminxin",
    "gn:population":0,
    "gn:timezone":"Asia/Shanghai",
    "iso:country":"CN",
    "name:zho_x_preferred":[
        "\u516c\u6c11\u65b0"
    ],
    "wof:name":"Gongminxin",
    "wof:placetype":"locality"
},
  "geometry": {"coordinates":[105.81082000000001,27.72463],"type":"Point"}
}