{
  "type": "Feature",
  "properties": {
    "gn:admin1_code":"7.0",
    "gn:asciiname":"Shuangfeng",
    "gn:country_code":"CN",
    "gn:dem":776,
    "gn:feature_class":"P",
    "gn:feature_code":"PPL",
    "gn:name":"Shuangfeng",
    "gn:population":0,
    "gn:timezone":"Asia/Shanghai",
    "iso:country":"CN",
    "name:zho_x_preferred":[
        "\u53cc\u5cf0"
    ],
    "wof:name":"Shuangfeng",
    "wof:placetype":"locality"
},
  "geometry": {"coordinates":[117.09704000000001,24.55246],"type":"Point"}
}