{
  "type": "Feature",
  "properties": {
    "gn:admin1_code":"13",
    "gn:asciiname":"Yiling Tuanchang",
    "gn:country_code":"CN",
    "gn:dem":1013,
    "gn:feature_class":"P",
    "gn:feature_code":"PPLF",
    "gn:name":"Yiling Tuanchang",
    "gn:population":0,
    "gn:timezone":"Asia/Shanghai",
    "iso:country":"CN",
    "name:und_x_variant":[
        "\u4e00\u96f6\u56e2\u573a"
    ],
    "wof:name":"Yiling Tuanchang",
    "wof:placetype":"locality"
},
  "geometry": {"coordinates":[81.32737,40.60715],"type":"Point"}
}