{
  "type": "Feature",
  "properties": {
    "gn:admin1_code":"19.0",
    "gn:asciiname":"Zhangweizi",
    "gn:country_code":"CN",
    "gn:dem":137,
    "gn:feature_class":"P",
    "gn:feature_code":"PPL",
    "gn:name":"Zhangweizi",
    "gn:population":0,
    "gn:timezone":"Asia/Shanghai",
    "iso:country":"CN",
    "name:und_x_variant":[
        "\u5f20\u5d34\u5b50"
    ],
    "name:zho_x_preferred":[
        "\u5f20\u5d34\u5b50"
    ],
    "wof:name":"Zhangweizi",
    "wof:placetype":"locality"
},
  "geometry": {"coordinates":[122.14885,39.87356],"type":"Point"}
}