{
  "type": "Feature",
  "properties": {
    "gn:admin1_code":"14.0",
    "gn:asciiname":"Luojiang",
    "gn:country_code":"CN",
    "gn:dem":3898,
    "gn:feature_class":"P",
    "gn:feature_code":"PPLA4",
    "gn:name":"Luojiang",
    "gn:population":0,
    "gn:timezone":"Asia/Urumqi",
    "iso:country":"CN",
    "name:und_x_variant":[
        "Luojiang Zhen"
    ],
    "name:zho_x_preferred":[
        "\u6d1b\u6c5f"
    ],
    "name:zho_x_variant":[
        "\u6d1b\u6c5f\u9547"
    ],
    "wof:name":"Luojiang",
    "wof:placetype":"locality"
},
  "geometry": {"coordinates":[89.26443,29.10568],"type":"Point"}
}