{
  "type": "Feature",
  "properties": {
    "gn:admin1_code":"5.0",
    "gn:asciiname":"Daxigou",
    "gn:country_code":"CN",
    "gn:dem":287,
    "gn:feature_class":"P",
    "gn:feature_code":"PPL",
    "gn:name":"Daxigou",
    "gn:population":0,
    "gn:timezone":"Asia/Shanghai",
    "iso:country":"CN",
    "name:und_x_variant":[
        "\u5927\u897f\u6c9f"
    ],
    "wof:name":"Daxigou",
    "wof:placetype":"locality"
},
  "geometry": {"coordinates":[129.28715,42.97928],"type":"Point"}
}