{
  "type": "Feature",
  "properties": {
    "gn:admin1_code":"4.0",
    "gn:asciiname":"Gaodangjie",
    "gn:country_code":"CN",
    "gn:dem":13,
    "gn:feature_class":"P",
    "gn:feature_code":"PPL",
    "gn:name":"Gaodangjie",
    "gn:population":0,
    "gn:timezone":"Asia/Shanghai",
    "iso:country":"CN",
    "name:zho_x_preferred":[
        "Gaodangjie"
    ],
    "name:zho_x_variant":[
        "\u9ad8\u8361\u8857"
    ],
    "wof:name":"Gaodangjie",
    "wof:placetype":"locality"
},
  "geometry": {"coordinates":[119.08257999999999,33.72997],"type":"Point"}
}