{
  "type": "Feature",
  "properties": {
    "gn:admin1_code":"3.0",
    "gn:asciiname":"Hulu'an",
    "gn:country_code":"CN",
    "gn:dem":124,
    "gn:feature_class":"P",
    "gn:feature_code":"PPL",
    "gn:name":"Hulu\u2019an",
    "gn:population":0,
    "gn:timezone":"Asia/Shanghai",
    "iso:country":"CN",
    "name:und_x_variant":[
        "Hulu\u2019an",
        "\u846b\u82a6\u5eb5"
    ],
    "wof:name":"Hulu'an",
    "wof:placetype":"locality"
},
  "geometry": {"coordinates":[116.86466,27.79995],"type":"Point"}
}