{
  "type": "Feature",
  "properties": {
    "gn:admin1_code":"30.0",
    "gn:asciiname":"Hongshuikeng",
    "gn:country_code":"CN",
    "gn:dem":562,
    "gn:feature_class":"P",
    "gn:feature_code":"PPL",
    "gn:name":"Hongshuikeng",
    "gn:population":0,
    "gn:timezone":"Asia/Shanghai",
    "iso:country":"CN",
    "name:zho_x_preferred":[
        "Hongshuikeng"
    ],
    "name:zho_x_variant":[
        "\u6d2a\u6c34\u5751"
    ],
    "wof:name":"Hongshuikeng",
    "wof:placetype":"locality"
},
  "geometry": {"coordinates":[114.45966,24.17993],"type":"Point"}
}