{
  "type": "Feature",
  "properties": {
    "gn:admin1_code":"26.0",
    "gn:asciiname":"Kangchacun",
    "gn:country_code":"CN",
    "gn:dem":1255,
    "gn:feature_class":"P",
    "gn:feature_code":"PPL",
    "gn:name":"Kangchacun",
    "gn:population":0,
    "gn:timezone":"Asia/Shanghai",
    "iso:country":"CN",
    "name:zho_x_preferred":[
        "\u5eb7\u5c94\u6751"
    ],
    "wof:name":"Kangchacun",
    "wof:placetype":"locality"
},
  "geometry": {"coordinates":[109.05904,36.79112],"type":"Point"}
}