{
  "type": "Feature",
  "properties": {
    "gn:admin1_code":"8.0",
    "gn:asciiname":"Zhaodiyingzicun",
    "gn:country_code":"CN",
    "gn:dem":266,
    "gn:feature_class":"P",
    "gn:feature_code":"PPL",
    "gn:name":"Zhaodiyingzicun",
    "gn:population":0,
    "gn:timezone":"Asia/Shanghai",
    "iso:country":"CN",
    "name:zho_x_preferred":[
        "\u8d75\u5730\u8425\u5b50\u6751"
    ],
    "wof:name":"Zhaodiyingzicun",
    "wof:placetype":"locality"
},
  "geometry": {"coordinates":[127.22002000000001,49.55029],"type":"Point"}
}