{
  "type": "Feature",
  "properties": {
    "gn:admin1_code":"7",
    "gn:asciiname":"Yangdunping",
    "gn:country_code":"CN",
    "gn:dem":222,
    "gn:feature_class":"P",
    "gn:feature_code":"PPL",
    "gn:name":"Yangdunping",
    "gn:population":0,
    "gn:timezone":"Asia/Shanghai",
    "iso:country":"CN",
    "name:und_x_variant":[
        "\u6d0b\u58a9\u576a"
    ],
    "wof:name":"Yangdunping",
    "wof:placetype":"locality"
},
  "geometry": {"coordinates":[118.72472,27.54278],"type":"Point"}
}