{
  "type": "Feature",
  "properties": {
    "gn:admin1_code":"30.0",
    "gn:asciiname":"Diaokeng",
    "gn:country_code":"CN",
    "gn:dem":346,
    "gn:feature_class":"P",
    "gn:feature_code":"PPL",
    "gn:name":"Diaokeng",
    "gn:population":0,
    "gn:timezone":"Asia/Shanghai",
    "iso:country":"CN",
    "name:zho_x_preferred":[
        "Diaokeng"
    ],
    "name:zho_x_variant":[
        "\u540a\u5751"
    ],
    "wof:name":"Diaokeng",
    "wof:placetype":"locality"
},
  "geometry": {"coordinates":[114.50826000000001,24.08841],"type":"Point"}
}