{
  "type": "Feature",
  "properties": {
    "gn:admin1_code":"29.0",
    "gn:asciiname":"Caozipo",
    "gn:country_code":"CN",
    "gn:dem":2180,
    "gn:feature_class":"P",
    "gn:feature_code":"PPL",
    "gn:name":"Caozipo",
    "gn:population":0,
    "gn:timezone":"Asia/Shanghai",
    "iso:country":"CN",
    "name:zho_x_preferred":[
        "\u8349\u5b50\u5761"
    ],
    "wof:name":"Caozipo",
    "wof:placetype":"locality"
},
  "geometry": {"coordinates":[103.09,25.1286],"type":"Point"}
}