{
  "type": "Feature",
  "properties": {
    "gn:admin1_code":"18",
    "gn:asciiname":"Doushanpo",
    "gn:country_code":"CN",
    "gn:dem":734,
    "gn:feature_class":"P",
    "gn:feature_code":"PPL",
    "gn:name":"Doushanpo",
    "gn:population":0,
    "gn:timezone":"Asia/Shanghai",
    "iso:country":"CN",
    "name:zho_x_preferred":[
        "\u9661\u5c71\u5761"
    ],
    "wof:name":"Doushanpo",
    "wof:placetype":"locality"
},
  "geometry": {"coordinates":[108.452,27.2831],"type":"Point"}
}