{
  "type": "Feature",
  "properties": {
    "gn:admin1_code":"25",
    "gn:asciiname":"Lishan",
    "gn:country_code":"CN",
    "gn:dem":43,
    "gn:feature_class":"P",
    "gn:feature_code":"PPL",
    "gn:name":"Lishan",
    "gn:population":0,
    "gn:timezone":"Asia/Shanghai",
    "iso:country":"CN",
    "name:ceb_x_preferred":[
        "Lishan"
    ],
    "name:deu_x_preferred":[
        "Lishan"
    ],
    "name:nor_x_preferred":[
        "Lishan"
    ],
    "name:zho_x_preferred":[
        "\u674e\u5c71"
    ],
    "wof:name":"Lishan",
    "wof:placetype":"locality"
},
  "geometry": {"coordinates":[116.255,35.3097],"type":"Point"}
}