{
  "type": "Feature",
  "properties": {
    "gn:admin1_code":"29.0",
    "gn:asciiname":"Longzizhai",
    "gn:country_code":"CN",
    "gn:dem":1308,
    "gn:feature_class":"P",
    "gn:feature_code":"PPL",
    "gn:name":"Longzizhai",
    "gn:population":0,
    "gn:timezone":"Asia/Shanghai",
    "iso:country":"CN",
    "name:zho_x_preferred":[
        "\u9f99\u5b50\u5be8"
    ],
    "wof:name":"Longzizhai",
    "wof:placetype":"locality"
},
  "geometry": {"coordinates":[100.129,22.9745],"type":"Point"}
}