{
  "type": "Feature",
  "properties": {
    "gn:admin1_code":"26.0",
    "gn:asciiname":"Tianjiakoucun",
    "gn:country_code":"CN",
    "gn:dem":881,
    "gn:feature_class":"P",
    "gn:feature_code":"PPL",
    "gn:name":"Tianjiakoucun",
    "gn:population":0,
    "gn:timezone":"Asia/Shanghai",
    "iso:country":"CN",
    "name:zho_x_preferred":[
        "\u7530\u5bb6\u53e3\u6751"
    ],
    "wof:name":"Tianjiakoucun",
    "wof:placetype":"locality"
},
  "geometry": {"coordinates":[109.50843999999999,33.59506],"type":"Point"}
}