{
  "type": "Feature",
  "properties": {
    "gn:admin1_code":"11.0",
    "gn:asciiname":"Yangmujiang",
    "gn:country_code":"CN",
    "gn:dem":287,
    "gn:feature_class":"P",
    "gn:feature_code":"PPL",
    "gn:name":"Yangmujiang",
    "gn:population":0,
    "gn:timezone":"Asia/Shanghai",
    "iso:country":"CN",
    "name:zho_x_preferred":[
        "\u6768\u6728\u6c5f"
    ],
    "wof:name":"Yangmujiang",
    "wof:placetype":"locality"
},
  "geometry": {"coordinates":[113.91583,26.5597],"type":"Point"}
}