{
  "type": "Feature",
  "properties": {
    "gn:admin1_code":"7",
    "gn:asciiname":"Zhuxian",
    "gn:country_code":"CN",
    "gn:dem":293,
    "gn:feature_class":"P",
    "gn:feature_code":"PPL",
    "gn:name":"Zhuxian",
    "gn:population":0,
    "gn:timezone":"Asia/Shanghai",
    "iso:country":"CN",
    "name:swe_x_preferred":[
        "Zhuxian"
    ],
    "name:und_x_variant":[
        "\u7af9\u8d24"
    ],
    "name:zho_x_preferred":[
        "\u6731\u4ed9\u9547"
    ],
    "wof:name":"Zhuxian",
    "wof:placetype":"locality"
},
  "geometry": {"coordinates":[118.74505000000001,27.71418],"type":"Point"}
}