{
  "type": "Feature",
  "properties": {
    "gn:admin1_code":"5.0",
    "gn:asciiname":"Xiaoliushimianjing",
    "gn:country_code":"CN",
    "gn:dem":144,
    "gn:feature_class":"P",
    "gn:feature_code":"PPL",
    "gn:name":"Xiaoliushimianjing",
    "gn:population":0,
    "gn:timezone":"Asia/Shanghai",
    "iso:country":"CN",
    "name:zho_x_preferred":[
        "\u5c0f\u516d\u5341\u9762\u4e95"
    ],
    "wof:name":"Xiaoliushimianjing",
    "wof:placetype":"locality"
},
  "geometry": {"coordinates":[124.11458,43.53438],"type":"Point"}
}