{
  "type": "Feature",
  "properties": {
    "gn:admin1_code":"1.0",
    "gn:asciiname":"Meisongsun",
    "gn:country_code":"CN",
    "gn:dem":49,
    "gn:feature_class":"P",
    "gn:feature_code":"PPL",
    "gn:name":"Meisongsun",
    "gn:population":0,
    "gn:timezone":"Asia/Shanghai",
    "iso:country":"CN",
    "wof:name":"Meisongsun",
    "wof:placetype":"locality"
},
  "geometry": {"coordinates":[117.575,32.675],"type":"Point"}
}