{
  "type": "Feature",
  "properties": {
    "gn:admin1_code":"32.0",
    "gn:asciiname":"Shiduiwo",
    "gn:country_code":"CN",
    "gn:dem":977,
    "gn:feature_class":"P",
    "gn:feature_code":"PPL",
    "gn:name":"Shiduiwo",
    "gn:population":0,
    "gn:timezone":"Asia/Shanghai",
    "iso:country":"CN",
    "name:zho_x_preferred":[
        "\u77f3\u5bf9\u7a9d"
    ],
    "wof:name":"Shiduiwo",
    "wof:placetype":"locality"
},
  "geometry": {"coordinates":[107.85671000000001,31.56758],"type":"Point"}
}