{
  "type": "Feature",
  "properties": {
    "gn:admin1_code":"5.0",
    "gn:asciiname":"Jiqingcun",
    "gn:country_code":"CN",
    "gn:dem":391,
    "gn:feature_class":"P",
    "gn:feature_code":"PPL",
    "gn:name":"Jiqingcun",
    "gn:population":0,
    "gn:timezone":"Asia/Shanghai",
    "iso:country":"CN",
    "name:zho_x_preferred":[
        "\u96c6\u6e05\u6751"
    ],
    "wof:name":"Jiqingcun",
    "wof:placetype":"locality"
},
  "geometry": {"coordinates":[125.65188000000001,42.19639],"type":"Point"}
}