{
  "type": "Feature",
  "properties": {
    "gn:admin1_code":"19.0",
    "gn:asciiname":"Dabuzi",
    "gn:country_code":"CN",
    "gn:dem":126,
    "gn:feature_class":"P",
    "gn:feature_code":"PPL",
    "gn:name":"Dabuzi",
    "gn:population":0,
    "gn:timezone":"Asia/Shanghai",
    "iso:country":"CN",
    "name:und_x_variant":[
        "Dapuzi",
        "\u5927\u5821\u5b50",
        "Dabuzi"
    ],
    "wof:name":"Dabuzi",
    "wof:placetype":"locality"
},
  "geometry": {"coordinates":[122.97221999999999,40.62808],"type":"Point"}
}