{
  "type": "Feature",
  "properties": {
    "gn:admin1_code":"14.0",
    "gn:asciiname":"Langmai",
    "gn:country_code":"CN",
    "gn:dem":4441,
    "gn:feature_class":"P",
    "gn:feature_code":"PPLF",
    "gn:name":"Langmai",
    "gn:population":0,
    "gn:timezone":"Asia/Urumqi",
    "iso:country":"CN",
    "name:bod_x_preferred":[
        "Langmai"
    ],
    "name:zho_x_preferred":[
        "Luomai"
    ],
    "name:zho_x_variant":[
        "\u7f57\u9ea6"
    ],
    "wof:name":"Langmai",
    "wof:placetype":"locality"
},
  "geometry": {"coordinates":[98.86667,30.73333],"type":"Point"}
}