{
  "type": "Feature",
  "properties": {
    "gn:admin1_code":"29",
    "gn:asciiname":"P'ing-t'an-chieh",
    "gn:country_code":"CN",
    "gn:dem":1028,
    "gn:feature_class":"P",
    "gn:feature_code":"PPL",
    "gn:name":"P\u2019ing-t\u2019an-chieh",
    "gn:population":0,
    "gn:timezone":"Asia/Shanghai",
    "iso:country":"CN",
    "wof:name":"P'ing-t'an-chieh",
    "wof:placetype":"locality"
},
  "geometry": {"coordinates":[103.95611,22.92556],"type":"Point"}
}