{
  "type": "Feature",
  "properties": {
    "gn:admin1_code":"29",
    "gn:asciiname":"Lushuitang",
    "gn:country_code":"CN",
    "gn:dem":1920,
    "gn:feature_class":"P",
    "gn:feature_code":"PPL",
    "gn:name":"L\u00fcshuitang",
    "gn:population":0,
    "gn:timezone":"Asia/Shanghai",
    "iso:country":"CN",
    "name:zho_x_preferred":[
        "\u7eff\u6c34\u5858"
    ],
    "name:zho_x_variant":[
        "L\u00fcshuitang"
    ],
    "wof:name":"Lushuitang",
    "wof:placetype":"locality"
},
  "geometry": {"coordinates":[103.48366,24.82523],"type":"Point"}
}