{
  "type": "Feature",
  "properties": {
    "gn:admin1_code":"8.0",
    "gn:asciiname":"Jianxingcun",
    "gn:country_code":"CN",
    "gn:dem":143,
    "gn:feature_class":"P",
    "gn:feature_code":"PPL",
    "gn:name":"Jianxingcun",
    "gn:population":0,
    "gn:timezone":"Asia/Shanghai",
    "iso:country":"CN",
    "name:zho_x_preferred":[
        "\u5efa\u5174\u6751"
    ],
    "wof:name":"Jianxingcun",
    "wof:placetype":"locality"
},
  "geometry": {"coordinates":[128.60843,45.61177],"type":"Point"}
}