{
  "type": "Feature",
  "properties": {
    "gn:admin1_code":"32",
    "gn:asciiname":"Misang",
    "gn:country_code":"CN",
    "gn:dem":4190,
    "gn:feature_class":"P",
    "gn:feature_code":"PPL",
    "gn:name":"Misang",
    "gn:population":0,
    "gn:timezone":"Asia/Shanghai",
    "iso:country":"CN",
    "wof:name":"Misang",
    "wof:placetype":"locality"
},
  "geometry": {"coordinates":[101.11667,30.36667000000001],"type":"Point"}
}