{
  "type": "Feature",
  "properties": {
    "gn:admin1_code":"32.0",
    "gn:asciiname":"Abingluogu",
    "gn:country_code":"CN",
    "gn:dem":1939,
    "gn:feature_class":"P",
    "gn:feature_code":"PPL",
    "gn:name":"Abingluogu",
    "gn:population":0,
    "gn:timezone":"Asia/Shanghai",
    "iso:country":"CN",
    "name:zho_x_preferred":[
        "\u963f\u5e76\u6d1b\u53e4"
    ],
    "wof:name":"Abingluogu",
    "wof:placetype":"locality"
},
  "geometry": {"coordinates":[102.93770000000001,28.04932],"type":"Point"}
}