{
  "type": "Feature",
  "properties": {
    "gn:admin1_code":"26.0",
    "gn:asciiname":"Tuannenpo",
    "gn:country_code":"CN",
    "gn:dem":921,
    "gn:feature_class":"P",
    "gn:feature_code":"PPL",
    "gn:name":"Tuannenpo",
    "gn:population":0,
    "gn:timezone":"Asia/Shanghai",
    "iso:country":"CN",
    "name:zho_x_preferred":[
        "\u56e2\u5ae9\u5761"
    ],
    "wof:name":"Tuannenpo",
    "wof:placetype":"locality"
},
  "geometry": {"coordinates":[109.4295,33.60383],"type":"Point"}
}