{
  "type": "Feature",
  "properties": {
    "gn:admin1_code":"14.0",
    "gn:asciiname":"Buni",
    "gn:country_code":"CN",
    "gn:dem":3779,
    "gn:feature_class":"P",
    "gn:feature_code":"PPL",
    "gn:name":"Buni",
    "gn:population":0,
    "gn:timezone":"Asia/Shanghai",
    "iso:country":"CN",
    "name:fas_x_preferred":[
        "\u0628\u0648\u0646\u06cc"
    ],
    "name:urd_x_preferred":[
        "\u0628\u0648\u0646\u06cc"
    ],
    "name:zho_x_preferred":[
        "\u5e03\u5c3c"
    ],
    "wof:name":"Buni",
    "wof:placetype":"locality"
},
  "geometry": {"coordinates":[78.7653,31.8307],"type":"Point"}
}