{
  "type": "Feature",
  "properties": {
    "gn:admin1_code":"30.0",
    "gn:asciiname":"Tangpuxin",
    "gn:country_code":"CN",
    "gn:dem":41,
    "gn:feature_class":"P",
    "gn:feature_code":"PPL",
    "gn:name":"Tangpuxin",
    "gn:population":0,
    "gn:timezone":"Asia/Shanghai",
    "iso:country":"CN",
    "name:zho_x_preferred":[
        "\u6c64\u57d4\u5fc3"
    ],
    "wof:name":"Tangpuxin",
    "wof:placetype":"locality"
},
  "geometry": {"coordinates":[113.54465,23.35293],"type":"Point"}
}