{
  "type": "Feature",
  "properties": {
    "gn:admin1_code":"8.0",
    "gn:asciiname":"Jingyicun",
    "gn:country_code":"CN",
    "gn:dem":212,
    "gn:feature_class":"P",
    "gn:feature_code":"PPL",
    "gn:name":"Jingyicun",
    "gn:population":0,
    "gn:timezone":"Asia/Shanghai",
    "iso:country":"CN",
    "name:zho_x_preferred":[
        "\u656c\u4e49\u6751"
    ],
    "wof:name":"Jingyicun",
    "wof:placetype":"locality"
},
  "geometry": {"coordinates":[125.61048999999998,47.45954],"type":"Point"}
}