{
  "type": "Feature",
  "properties": {
    "gn:admin1_code":"5.0",
    "gn:asciiname":"Heiyucun",
    "gn:country_code":"CN",
    "gn:dem":160,
    "gn:feature_class":"P",
    "gn:feature_code":"PPL",
    "gn:name":"Heiyucun",
    "gn:population":0,
    "gn:timezone":"Asia/Shanghai",
    "iso:country":"CN",
    "name:zho_x_preferred":[
        "\u9ed1\u9c7c\u6751"
    ],
    "wof:name":"Heiyucun",
    "wof:placetype":"locality"
},
  "geometry": {"coordinates":[126.07832000000001,44.62998],"type":"Point"}
}