{
  "type": "Feature",
  "properties": {
    "gn:admin1_code":"18",
    "gn:asciiname":"Chenjia Yuanzi",
    "gn:country_code":"CN",
    "gn:dem":2394,
    "gn:feature_class":"P",
    "gn:feature_code":"PPL",
    "gn:name":"Chenjia Yuanzi",
    "gn:population":0,
    "gn:timezone":"Asia/Shanghai",
    "iso:country":"CN",
    "name:zho_x_preferred":[
        "\u9648\u5bb6\u9662\u5b50"
    ],
    "wof:name":"Chenjia Yuanzi",
    "wof:placetype":"locality"
},
  "geometry": {"coordinates":[104.18000000000001,27.0916],"type":"Point"}
}