{
  "type": "Feature",
  "properties": {
    "gn:admin1_code":"33.0",
    "gn:asciiname":"Miaotang",
    "gn:country_code":"CN",
    "gn:dem":1102,
    "gn:feature_class":"P",
    "gn:feature_code":"PPLA4",
    "gn:name":"Miaotang",
    "gn:population":0,
    "gn:timezone":"Asia/Shanghai",
    "iso:country":"CN",
    "name:und_x_variant":[
        "Miaotang Xiang",
        "Wenchanggong"
    ],
    "name:zho_x_preferred":[
        "\u5e99\u5802"
    ],
    "name:zho_x_variant":[
        "\u5e99\u5802\u4e61",
        "\u6587\u660c\u5bab"
    ],
    "wof:name":"Miaotang",
    "wof:placetype":"locality"
},
  "geometry": {"coordinates":[110.10226000000002,31.36187],"type":"Point"}
}