{
  "type": "Feature",
  "properties": {
    "gn:admin1_code":"22.0",
    "gn:asciiname":"Fengzhuangcun",
    "gn:country_code":"CN",
    "gn:dem":500,
    "gn:feature_class":"P",
    "gn:feature_code":"PPL",
    "gn:name":"Fengzhuangcun",
    "gn:population":0,
    "gn:timezone":"Asia/Shanghai",
    "iso:country":"CN",
    "name:zho_x_preferred":[
        "\u51af\u5e84\u6751"
    ],
    "wof:name":"Fengzhuangcun",
    "wof:placetype":"locality"
},
  "geometry": {"coordinates":[116.03995999999999,40.47742],"type":"Point"}
}