{
  "type": "Feature",
  "properties": {
    "gn:admin1_code":"26.0",
    "gn:asciiname":"Gaozhuang",
    "gn:country_code":"CN",
    "gn:dem":1387,
    "gn:feature_class":"P",
    "gn:feature_code":"PPL",
    "gn:name":"Gaozhuang",
    "gn:population":0,
    "gn:timezone":"Asia/Shanghai",
    "iso:country":"CN",
    "name:und_x_variant":[
        "\u9ad8\u5e84"
    ],
    "wof:name":"Gaozhuang",
    "wof:placetype":"locality"
},
  "geometry": {"coordinates":[107.79456,34.60146],"type":"Point"}
}