{
  "type": "Feature",
  "properties": {
    "gn:admin1_code":"21.0",
    "gn:asciiname":"Hanwa",
    "gn:country_code":"CN",
    "gn:dem":1128,
    "gn:feature_class":"P",
    "gn:feature_code":"PPL",
    "gn:name":"Hanwa",
    "gn:population":0,
    "gn:timezone":"Asia/Shanghai",
    "iso:country":"CN",
    "name:zho_x_preferred":[
        "\u65f1\u6d3c"
    ],
    "wof:name":"Hanwa",
    "wof:placetype":"locality"
},
  "geometry": {"coordinates":[106.09999999999999,38.288],"type":"Point"}
}