{
  "type": "Feature",
  "properties": {
    "gn:admin1_code":"13.0",
    "gn:asciiname":"Yingnu'er",
    "gn:country_code":"CN",
    "gn:dem":890,
    "gn:feature_class":"P",
    "gn:feature_code":"PPL",
    "gn:name":"Yingnu\u2019er",
    "gn:population":0,
    "gn:timezone":"Asia/Urumqi",
    "iso:country":"CN",
    "name:und_x_variant":[
        "Yingnu\u2019er"
    ],
    "name:zho_x_preferred":[
        "\u82f1\u5974\u5c14"
    ],
    "wof:name":"Yingnu'er",
    "wof:placetype":"locality"
},
  "geometry": {"coordinates":[86.30183000000002,41.26372],"type":"Point"}
}