{
  "type": "Feature",
  "properties": {
    "gn:admin1_code":"8.0",
    "gn:asciiname":"Xipangjia Weizi",
    "gn:country_code":"CN",
    "gn:dem":159,
    "gn:feature_class":"P",
    "gn:feature_code":"PPL",
    "gn:name":"Xipangjia Weizi",
    "gn:population":0,
    "gn:timezone":"Asia/Shanghai",
    "iso:country":"CN",
    "name:zho_x_preferred":[
        "\u897f\u5e9e\u5bb6\u5d34\u5b50"
    ],
    "wof:name":"Xipangjia Weizi",
    "wof:placetype":"locality"
},
  "geometry": {"coordinates":[126.99362000000001,46.717],"type":"Point"}
}