{
  "type": "Feature",
  "properties": {
    "gn:admin1_code":"13",
    "gn:asciiname":"Aketa Shikuotan",
    "gn:country_code":"CN",
    "gn:dem":2309,
    "gn:feature_class":"P",
    "gn:feature_code":"PPL",
    "gn:name":"Aketa Shikuotan",
    "gn:population":0,
    "gn:timezone":"Asia/Urumqi",
    "iso:country":"CN",
    "name:und_x_variant":[
        "\u963f\u514b\u5854\u4ec0\u9614\u5766",
        "Aketashikuotan"
    ],
    "wof:name":"Aketa Shikuotan",
    "wof:placetype":"locality"
},
  "geometry": {"coordinates":[94.02734,43.40532],"type":"Point"}
}