{
  "type": "Feature",
  "properties": {
    "gn:admin1_code":"19.0",
    "gn:asciiname":"Wujiabu",
    "gn:country_code":"CN",
    "gn:dem":9,
    "gn:feature_class":"P",
    "gn:feature_code":"PPL",
    "gn:name":"Wujiabu",
    "gn:population":0,
    "gn:timezone":"Asia/Shanghai",
    "iso:country":"CN",
    "name:und_x_variant":[
        "Wujiabao",
        "\u5434\u5bb6\u5821",
        "Wujiabu"
    ],
    "name:zho_x_preferred":[
        "\u5434\u5bb6\u5821"
    ],
    "wof:name":"Wujiabu",
    "wof:placetype":"locality"
},
  "geometry": {"coordinates":[124.10283,39.95059000000001],"type":"Point"}
}