{
  "type": "Feature",
  "properties": {
    "gn:admin1_code":"26.0",
    "gn:asciiname":"Zaojiaoshudixia",
    "gn:country_code":"CN",
    "gn:dem":1027,
    "gn:feature_class":"P",
    "gn:feature_code":"PPL",
    "gn:name":"Zaojiaoshudixia",
    "gn:population":0,
    "gn:timezone":"Asia/Shanghai",
    "iso:country":"CN",
    "name:und_x_variant":[
        "\u7682\u89d2\u6811\u5e95\u4e0b"
    ],
    "wof:name":"Zaojiaoshudixia",
    "wof:placetype":"locality"
},
  "geometry": {"coordinates":[106.20529000000001,33.53212],"type":"Point"}
}