{
  "type": "Feature",
  "properties": {
    "gn:admin1_code":"9.0",
    "gn:asciiname":"Bidian",
    "gn:country_code":"CN",
    "gn:dem":49,
    "gn:feature_class":"P",
    "gn:feature_code":"PPL",
    "gn:name":"Bidian",
    "gn:population":0,
    "gn:timezone":"Asia/Shanghai",
    "iso:country":"CN",
    "name:zho_x_preferred":[
        "\u6bd5\u5e97"
    ],
    "wof:name":"Bidian",
    "wof:placetype":"locality"
},
  "geometry": {"coordinates":[115.86439,31.96096],"type":"Point"}
}