{
  "type": "Feature",
  "properties": {
    "gn:admin1_code":"4.0",
    "gn:asciiname":"Kaizhuangcun",
    "gn:country_code":"CN",
    "gn:dem":12,
    "gn:feature_class":"P",
    "gn:feature_code":"PPL",
    "gn:name":"Kaizhuangcun",
    "gn:population":0,
    "gn:timezone":"Asia/Shanghai",
    "iso:country":"CN",
    "name:zho_x_preferred":[
        "\u5f00\u5e84\u6751"
    ],
    "wof:name":"Kaizhuangcun",
    "wof:placetype":"locality"
},
  "geometry": {"coordinates":[119.07787999999999,33.7135],"type":"Point"}
}