{
  "type": "Feature",
  "properties": {
    "gn:admin1_code":"31.0",
    "gn:asciiname":"Luoding",
    "gn:country_code":"CN",
    "gn:dem":6,
    "gn:feature_class":"P",
    "gn:feature_code":"PPL",
    "gn:name":"Luoding",
    "gn:population":0,
    "gn:timezone":"Asia/Shanghai",
    "iso:country":"CN",
    "name:ara_x_preferred":[
        "\u0644\u0648\u062f\u064a\u0646\u063a"
    ],
    "name:deu_x_preferred":[
        "Luoding"
    ],
    "name:fas_x_preferred":[
        "\u0644\u0648\u062f\u06cc\u0646\u06af"
    ],
    "name:fra_x_preferred":[
        "Luoding"
    ],
    "name:ita_x_preferred":[
        "Luoding"
    ],
    "name:jpn_x_preferred":[
        "\u7f85\u5b9a\u5e02"
    ],
    "name:kik_x_preferred":[
        "Luoding"
    ],
    "name:kor_x_preferred":[
        "\ub904\ub529\uc2dc"
    ],
    "name:mwl_x_preferred":[
        "Luoding"
    ],
    "name:nld_x_preferred":[
        "Luoding"
    ],
    "name:nor_x_preferred":[
        "Luoding"
    ],
    "name:pam_x_preferred":[
        "Luoding"
    ],
    "name:pnb_x_preferred":[
        "\u0644\u0648\u0624\u0688\u06cc\u0646\u06af"
    ],
    "name:swe_x_preferred":[
        "Luoding"
    ],
    "name:urd_x_preferred":[
        "\u0644\u0624\u0648\u062f\u0646\u06af"
    ],
    "name:vie_x_preferred":[
        "La \u0110\u1ecbnh"
    ],
    "name:zho_x_preferred":[
        "Luoding"
    ],
    "name:zho_x_variant":[
        "\u7f57\u4e01",
        "\u7f57\u5b9a\u5e02"
    ],
    "wof:name":"Luoding",
    "wof:placetype":"locality"
},
  "geometry": {"coordinates":[110.55687,19.97221],"type":"Point"}
}