{
  "type": "Feature",
  "properties": {
    "gn:admin1_code":"8.0",
    "gn:asciiname":"Anletunhe Dongtun",
    "gn:country_code":"CN",
    "gn:dem":203,
    "gn:feature_class":"P",
    "gn:feature_code":"PPL",
    "gn:name":"Anletunhe Dongtun",
    "gn:population":0,
    "gn:timezone":"Asia/Shanghai",
    "iso:country":"CN",
    "name:zho_x_preferred":[
        "\u5b89\u4e50\u5c6f\u6cb3\u4e1c\u5c6f"
    ],
    "wof:name":"Anletunhe Dongtun",
    "wof:placetype":"locality"
},
  "geometry": {"coordinates":[128.16541000000001,45.18595],"type":"Point"}
}