{
  "type": "Feature",
  "properties": {
    "gn:admin1_code":"25.0",
    "gn:asciiname":"Yujiakuangcun",
    "gn:country_code":"CN",
    "gn:dem":87,
    "gn:feature_class":"P",
    "gn:feature_code":"PPL",
    "gn:name":"Yujiakuangcun",
    "gn:population":0,
    "gn:timezone":"Asia/Shanghai",
    "iso:country":"CN",
    "name:zho_x_preferred":[
        "\u9047\u9a7e\u593c\u6751"
    ],
    "wof:name":"Yujiakuangcun",
    "wof:placetype":"locality"
},
  "geometry": {"coordinates":[120.91652000000001,37.56003],"type":"Point"}
}