{
  "type": "Feature",
  "properties": {
    "gn:admin1_code":"4.0",
    "gn:asciiname":"Pushan",
    "gn:country_code":"CN",
    "gn:dem":2,
    "gn:feature_class":"P",
    "gn:feature_code":"PPL",
    "gn:name":"Pushan",
    "gn:population":0,
    "gn:timezone":"Asia/Shanghai",
    "iso:country":"CN",
    "name:als_x_preferred":[
        "Pushan"
    ],
    "name:deu_x_preferred":[
        "Pushan"
    ],
    "name:fra_x_preferred":[
        "Pushan"
    ],
    "name:jpn_x_preferred":[
        "\u30d7\u30fc\u30b7\u30e3\u30f3"
    ],
    "name:lit_x_preferred":[
        "P\u016b\u0161anas"
    ],
    "name:pol_x_preferred":[
        "Puszan"
    ],
    "name:por_x_preferred":[
        "Puchan"
    ],
    "name:rus_x_preferred":[
        "\u041f\u0443\u0448\u0430\u043d"
    ],
    "name:spa_x_preferred":[
        "Push\u00e1n"
    ],
    "name:swe_x_preferred":[
        "Pushan"
    ],
    "name:zho_x_preferred":[
        "Pushan"
    ],
    "name:zho_x_variant":[
        "\u666e\u5c71"
    ],
    "wof:name":"Pushan",
    "wof:placetype":"locality"
},
  "geometry": {"coordinates":[119.27585000000001,34.57623],"type":"Point"}
}