{
  "type": "Feature",
  "properties": {
    "gn:admin1_code":"4.0",
    "gn:asciiname":"Pushan",
    "gn:country_code":"CN",
    "gn:dem":2,
    "gn:feature_class":"P",
    "gn:feature_code":"PPL",
    "gn:name":"Pushan",
    "gn:population":0,
    "gn:timezone":"Asia/Shanghai",
    "iso:country":"CN",
    "name:zho_x_preferred":[
        "Pushan"
    ],
    "name:zho_x_variant":[
        "\u666e\u5c71"
    ],
    "wof:name":"Pushan",
    "wof:placetype":"locality"
},
  "geometry": {"coordinates":[119.27585000000001,34.57623],"type":"Point"}
}