{
  "type": "Feature",
  "properties": {
    "gn:admin1_code":"26.0",
    "gn:asciiname":"Zaoyuan",
    "gn:country_code":"CN",
    "gn:dem":1179,
    "gn:feature_class":"P",
    "gn:feature_code":"PPL",
    "gn:name":"Zaoyuan",
    "gn:population":0,
    "gn:timezone":"Asia/Shanghai",
    "iso:country":"CN",
    "name:und_x_variant":[
        "Tsao-y\u00fcan",
        "Zaoyuan"
    ],
    "name:zho_x_preferred":[
        "\u67a3\u56ed"
    ],
    "wof:name":"Zaoyuan",
    "wof:placetype":"locality"
},
  "geometry": {"coordinates":[107.73705,35.1367],"type":"Point"}
}