{
  "type": "Feature",
  "properties": {
    "gn:admin1_code":"10.0",
    "gn:asciiname":"Longxingzhuang",
    "gn:country_code":"CN",
    "gn:dem":180,
    "gn:feature_class":"P",
    "gn:feature_code":"PPL",
    "gn:name":"Longxingzhuang",
    "gn:population":0,
    "gn:timezone":"Asia/Shanghai",
    "iso:country":"CN",
    "name:und_x_variant":[
        "\u9f99\u5174\u5e84"
    ],
    "wof:name":"Longxingzhuang",
    "wof:placetype":"locality"
},
  "geometry": {"coordinates":[114.46669,38.60804],"type":"Point"}
}