{
  "type": "Feature",
  "properties": {
    "gn:admin1_code":"21.0",
    "gn:asciiname":"Shiwangou",
    "gn:country_code":"CN",
    "gn:dem":1619,
    "gn:feature_class":"P",
    "gn:feature_code":"PPL",
    "gn:name":"Shiwangou",
    "gn:population":0,
    "gn:timezone":"Asia/Shanghai",
    "iso:country":"CN",
    "name:zho_x_preferred":[
        "\u77f3\u6e7e\u6c9f"
    ],
    "wof:name":"Shiwangou",
    "wof:placetype":"locality"
},
  "geometry": {"coordinates":[106.63200000000001,37.1538],"type":"Point"}
}