{
  "type": "Feature",
  "properties": {
    "gn:admin1_code":"14.0",
    "gn:asciiname":"Galing",
    "gn:country_code":"CN",
    "gn:dem":3397,
    "gn:feature_class":"P",
    "gn:feature_code":"PPL",
    "gn:name":"Galing",
    "gn:population":0,
    "gn:timezone":"Asia/Urumqi",
    "iso:country":"CN",
    "name:zho_x_preferred":[
        "\u560e\u5cad"
    ],
    "wof:name":"Galing",
    "wof:placetype":"locality"
},
  "geometry": {"coordinates":[98.16061999999999,29.15795],"type":"Point"}
}