{
  "type": "Feature",
  "properties": {
    "gn:admin1_code":"26",
    "gn:asciiname":"Shuangyangxi",
    "gn:country_code":"CN",
    "gn:dem":598,
    "gn:feature_class":"P",
    "gn:feature_code":"PPL",
    "gn:name":"Shuangyangxi",
    "gn:population":0,
    "gn:timezone":"Asia/Shanghai",
    "iso:country":"CN",
    "name:und_x_variant":[
        "\u53cc\u7f8a\u897f"
    ],
    "name:zho_x_preferred":[
        "\u53cc\u7f8a\u897f"
    ],
    "wof:name":"Shuangyangxi",
    "wof:placetype":"locality"
},
  "geometry": {"coordinates":[108.23888999999998,34.41222],"type":"Point"}
}