{
  "type": "Feature",
  "properties": {
    "gn:admin1_code":"5.0",
    "gn:asciiname":"Yumintun",
    "gn:country_code":"CN",
    "gn:dem":303,
    "gn:feature_class":"P",
    "gn:feature_code":"PPL",
    "gn:name":"Yumintun",
    "gn:population":0,
    "gn:timezone":"Asia/Shanghai",
    "iso:country":"CN",
    "name:zho_x_preferred":[
        "\u80b2\u6c11\u5c6f"
    ],
    "wof:name":"Yumintun",
    "wof:placetype":"locality"
},
  "geometry": {"coordinates":[126.66574,42.88653],"type":"Point"}
}