{
  "type": "Feature",
  "properties": {
    "gn:admin1_code":"30.0",
    "gn:asciiname":"Rongshuwei",
    "gn:country_code":"CN",
    "gn:dem":136,
    "gn:feature_class":"P",
    "gn:feature_code":"PPL",
    "gn:name":"Rongshuwei",
    "gn:population":0,
    "gn:timezone":"Asia/Shanghai",
    "iso:country":"CN",
    "name:zho_x_preferred":[
        "\u6995\u6811\u56f4"
    ],
    "wof:name":"Rongshuwei",
    "wof:placetype":"locality"
},
  "geometry": {"coordinates":[112.01652,22.87544],"type":"Point"}
}