{
  "type": "Feature",
  "properties": {
    "gn:admin1_code":"7.0",
    "gn:asciiname":"Ceshang",
    "gn:country_code":"CN",
    "gn:dem":171,
    "gn:feature_class":"P",
    "gn:feature_code":"PPL",
    "gn:name":"Ceshang",
    "gn:population":0,
    "gn:timezone":"Asia/Shanghai",
    "iso:country":"CN",
    "name:zho_x_preferred":[
        "\u7b56\u4e0a"
    ],
    "wof:name":"Ceshang",
    "wof:placetype":"locality"
},
  "geometry": {"coordinates":[117.65069,26.97988],"type":"Point"}
}