{
  "type": "Feature",
  "properties": {
    "gn:admin1_code":"12.0",
    "gn:asciiname":"Zhangzhang",
    "gn:cc2":"CN",
    "gn:country_code":"CN",
    "gn:dem":630,
    "gn:feature_class":"P",
    "gn:feature_code":"PPL",
    "gn:name":"Zhangzhang",
    "gn:population":0,
    "gn:timezone":"Asia/Shanghai",
    "iso:country":"CN",
    "name:und_x_variant":[
        "Zhangwan",
        "Zhangzhang"
    ],
    "wof:name":"Zhangzhang",
    "wof:placetype":"locality"
},
  "geometry": {"coordinates":[111.31556,32.68194],"type":"Point"}
}