{
  "type": "Feature",
  "properties": {
    "gn:admin1_code":"14.0",
    "gn:asciiname":"Galacun",
    "gn:country_code":"CN",
    "gn:dem":3382,
    "gn:feature_class":"P",
    "gn:feature_code":"PPL",
    "gn:name":"Galacun",
    "gn:population":0,
    "gn:timezone":"Asia/Urumqi",
    "iso:country":"CN",
    "name:zho_x_preferred":[
        "\u560e\u62c9\u6751"
    ],
    "wof:name":"Galacun",
    "wof:placetype":"locality"
},
  "geometry": {"coordinates":[93.75333999999999,29.9844],"type":"Point"}
}