{
  "type": "Feature",
  "properties": {
    "gn:admin1_code":"3.0",
    "gn:asciiname":"Yangchun",
    "gn:country_code":"CN",
    "gn:dem":311,
    "gn:feature_class":"P",
    "gn:feature_code":"PPL",
    "gn:name":"Yangchun",
    "gn:population":0,
    "gn:timezone":"Asia/Shanghai",
    "iso:country":"CN",
    "name:ara_x_preferred":[
        "\u064a\u0627\u0646\u063a\u0634\u0648\u0646"
    ],
    "name:ceb_x_preferred":[
        "Yangchun"
    ],
    "name:deu_x_preferred":[
        "Yangchun"
    ],
    "name:fas_x_preferred":[
        "\u06cc\u0627\u0646\u06af\u0686\u0648\u0646"
    ],
    "name:fra_x_preferred":[
        "Yangchun"
    ],
    "name:hak_x_preferred":[
        "Y\u00f2ng-chh\u00fbn-s\u1e73"
    ],
    "name:ita_x_preferred":[
        "Yangchun"
    ],
    "name:jpn_x_preferred":[
        "\u967d\u6625\u5e02"
    ],
    "name:kik_x_preferred":[
        "Yangchun"
    ],
    "name:kor_x_preferred":[
        "\uc591\ucd98\uc2dc"
    ],
    "name:mlg_x_preferred":[
        "Yangchun"
    ],
    "name:mwl_x_preferred":[
        "Yangchun"
    ],
    "name:nld_x_preferred":[
        "Yangchun"
    ],
    "name:nor_x_preferred":[
        "Yangchun"
    ],
    "name:pam_x_preferred":[
        "Yangchun"
    ],
    "name:pnb_x_preferred":[
        "\u06cc\u0627\u0646\u06af\u0686\u0646"
    ],
    "name:swe_x_preferred":[
        "Yangchun"
    ],
    "name:und_x_variant":[
        "\u9633\u6625"
    ],
    "name:urd_x_preferred":[
        "\u06cc\u0646\u06af\u0686\u0646"
    ],
    "name:vie_x_preferred":[
        "D\u01b0\u01a1ng Xu\u00e2n"
    ],
    "name:zho_x_preferred":[
        "\u9633\u6625\u5e02"
    ],
    "wof:name":"Yangchun",
    "wof:placetype":"locality"
},
  "geometry": {"coordinates":[114.12549,27.26753],"type":"Point"}
}