{
  "type": "Feature",
  "properties": {
    "gn:admin1_code":"32.0",
    "gn:asciiname":"Taipingshan",
    "gn:country_code":"CN",
    "gn:dem":676,
    "gn:feature_class":"P",
    "gn:feature_code":"PPL",
    "gn:name":"Taipingshan",
    "gn:population":0,
    "gn:timezone":"Asia/Shanghai",
    "iso:country":"CN",
    "name:zho_x_preferred":[
        "\u592a\u5e73\u5c71"
    ],
    "wof:name":"Taipingshan",
    "wof:placetype":"locality"
},
  "geometry": {"coordinates":[104.48972999999999,31.68964],"type":"Point"}
}