{
  "type": "Feature",
  "properties": {
    "gn:admin1_code":"32.0",
    "gn:asciiname":"Shuangtudi",
    "gn:country_code":"CN",
    "gn:dem":672,
    "gn:feature_class":"P",
    "gn:feature_code":"PPL",
    "gn:name":"Shuangtudi",
    "gn:population":0,
    "gn:timezone":"Asia/Shanghai",
    "iso:country":"CN",
    "name:zho_x_preferred":[
        "\u53cc\u571f\u5730"
    ],
    "wof:name":"Shuangtudi",
    "wof:placetype":"locality"
},
  "geometry": {"coordinates":[103.747,31.0397],"type":"Point"}
}