{
  "type": "Feature",
  "properties": {
    "gn:admin1_code":"15.0",
    "gn:asciiname":"Lijieshan",
    "gn:country_code":"CN",
    "gn:dem":1953,
    "gn:feature_class":"P",
    "gn:feature_code":"PPL",
    "gn:name":"Lijieshan",
    "gn:population":0,
    "gn:timezone":"Asia/Shanghai",
    "iso:country":"CN",
    "name:zho_x_preferred":[
        "\u7acb\u754c\u5c71"
    ],
    "wof:name":"Lijieshan",
    "wof:placetype":"locality"
},
  "geometry": {"coordinates":[104.36484,33.97991],"type":"Point"}
}