{
  "type": "Feature",
  "properties": {
    "gn:admin1_code":"25.0",
    "gn:asciiname":"Yanglanling",
    "gn:country_code":"CN",
    "gn:dem":54,
    "gn:feature_class":"P",
    "gn:feature_code":"PPL",
    "gn:name":"Yanglanling",
    "gn:population":0,
    "gn:timezone":"Asia/Shanghai",
    "iso:country":"CN",
    "name:zho_x_preferred":[
        "\u4ef0\u5c9a\u5cad"
    ],
    "wof:name":"Yanglanling",
    "wof:placetype":"locality"
},
  "geometry": {"coordinates":[120.61172000000001,36.65311],"type":"Point"}
}