{
  "type": "Feature",
  "properties": {
    "gn:admin1_code":"14.0",
    "gn:asciiname":"Chaxia'ercun",
    "gn:country_code":"CN",
    "gn:dem":4087,
    "gn:feature_class":"P",
    "gn:feature_code":"PPL",
    "gn:name":"Chaxia\u2019ercun",
    "gn:population":0,
    "gn:timezone":"Asia/Urumqi",
    "iso:country":"CN",
    "name:und_x_variant":[
        "Chaxia\u2019ercun"
    ],
    "name:zho_x_preferred":[
        "\u67e5\u590f\u5c14\u6751"
    ],
    "wof:name":"Chaxia'ercun",
    "wof:placetype":"locality"
},
  "geometry": {"coordinates":[94.78483,31.51778],"type":"Point"}
}