{
  "type": "Feature",
  "properties": {
    "gn:admin1_code":"9.0",
    "gn:asciiname":"Yindonggou",
    "gn:country_code":"CN",
    "gn:dem":661,
    "gn:feature_class":"P",
    "gn:feature_code":"PPL",
    "gn:name":"Yindonggou",
    "gn:population":0,
    "gn:timezone":"Asia/Shanghai",
    "iso:country":"CN",
    "name:zho_x_preferred":[
        "\u94f6\u6d1e\u6c9f"
    ],
    "wof:name":"Yindonggou",
    "wof:placetype":"locality"
},
  "geometry": {"coordinates":[111.37904,32.82322],"type":"Point"}
}