{
  "type": "Feature",
  "properties": {
    "gn:admin1_code":"30.0",
    "gn:asciiname":"Xiaxipucun",
    "gn:country_code":"CN",
    "gn:dem":22,
    "gn:feature_class":"P",
    "gn:feature_code":"PPL",
    "gn:name":"Xiaxipucun",
    "gn:population":0,
    "gn:timezone":"Asia/Shanghai",
    "iso:country":"CN",
    "name:zho_x_preferred":[
        "\u4e0b\u897f\u57d4\u6751"
    ],
    "wof:name":"Xiaxipucun",
    "wof:placetype":"locality"
},
  "geometry": {"coordinates":[116.23566,23.23964],"type":"Point"}
}