{
  "type": "Feature",
  "properties": {
    "gn:admin1_code":"12.0",
    "gn:asciiname":"Hefengdian",
    "gn:country_code":"CN",
    "gn:dem":30,
    "gn:feature_class":"P",
    "gn:feature_code":"PPL",
    "gn:name":"Hefengdian",
    "gn:population":0,
    "gn:timezone":"Asia/Shanghai",
    "iso:country":"CN",
    "name:zho_x_preferred":[
        "\u5408\u4e30\u5e97"
    ],
    "wof:name":"Hefengdian",
    "wof:placetype":"locality"
},
  "geometry": {"coordinates":[113.35352,30.82502],"type":"Point"}
}