{
  "type": "Feature",
  "properties": {
    "gn:admin1_code":"26.0",
    "gn:asciiname":"Xihucun",
    "gn:country_code":"CN",
    "gn:dem":397,
    "gn:feature_class":"P",
    "gn:feature_code":"PPL",
    "gn:name":"Xihucun",
    "gn:population":0,
    "gn:timezone":"Asia/Shanghai",
    "iso:country":"CN",
    "name:zho_x_preferred":[
        "\u897f\u80e1\u6751"
    ],
    "wof:name":"Xihucun",
    "wof:placetype":"locality"
},
  "geometry": {"coordinates":[109.35481,34.80844],"type":"Point"}
}