{
  "type": "Feature",
  "properties": {
    "gn:admin1_code":"9.0",
    "gn:asciiname":"Liangyuzhuang",
    "gn:country_code":"CN",
    "gn:dem":131,
    "gn:feature_class":"P",
    "gn:feature_code":"PPL",
    "gn:name":"Liangyuzhuang",
    "gn:population":0,
    "gn:timezone":"Asia/Shanghai",
    "iso:country":"CN",
    "name:zho_x_preferred":[
        "\u826f\u4e8e\u5e84"
    ],
    "wof:name":"Liangyuzhuang",
    "wof:placetype":"locality"
},
  "geometry": {"coordinates":[112.86241,32.83045],"type":"Point"}
}