{
  "type": "Feature",
  "properties": {
    "gn:admin1_code":"3.0",
    "gn:asciiname":"Lucun",
    "gn:country_code":"CN",
    "gn:dem":108,
    "gn:feature_class":"P",
    "gn:feature_code":"PPLA4",
    "gn:name":"Lucun",
    "gn:population":0,
    "gn:timezone":"Asia/Shanghai",
    "iso:country":"CN",
    "name:und_x_variant":[
        "\u82a6\u6751",
        "Lucun Xiang",
        "\u82a6\u6751\u4e61"
    ],
    "wof:name":"Lucun",
    "wof:placetype":"locality"
},
  "geometry": {"coordinates":[114.45541,27.92751],"type":"Point"}
}