{
  "type": "Feature",
  "properties": {
    "gn:admin1_code":"4.0",
    "gn:asciiname":"Linshecun",
    "gn:country_code":"CN",
    "gn:dem":2,
    "gn:feature_class":"P",
    "gn:feature_code":"PPL",
    "gn:name":"Linshecun",
    "gn:population":0,
    "gn:timezone":"Asia/Shanghai",
    "iso:country":"CN",
    "name:zho_x_preferred":[
        "\u6797\u820d\u6751"
    ],
    "wof:name":"Linshecun",
    "wof:placetype":"locality"
},
  "geometry": {"coordinates":[119.56787,33.51093],"type":"Point"}
}