{
  "type": "Feature",
  "properties": {
    "gn:admin1_code":"05",
    "gn:asciiname":"Jiqingcun",
    "gn:country_code":"CN",
    "gn:dem":380,
    "gn:feature_class":"P",
    "gn:feature_code":"PPL",
    "gn:name":"Jiqingcun",
    "gn:population":0,
    "gn:timezone":"Asia/Shanghai",
    "iso:country":"CN",
    "name:und_x_variant":[
        "Jiqing"
    ],
    "name:zho_x_preferred":[
        "\u5409\u5e86\u6751"
    ],
    "wof:name":"Jiqingcun",
    "wof:placetype":"locality"
},
  "geometry": {"coordinates":[125.44468000000001,42.2723],"type":"Point"}
}