{
  "type": "Feature",
  "properties": {
    "gn:admin1_code":"15.0",
    "gn:asciiname":"Wangzigou",
    "gn:country_code":"CN",
    "gn:dem":2687,
    "gn:feature_class":"P",
    "gn:feature_code":"PPL",
    "gn:name":"Wangzigou",
    "gn:population":0,
    "gn:timezone":"Asia/Shanghai",
    "iso:country":"CN",
    "name:und_x_variant":[
        "\u671b\u5b50\u6c9f",
        "Wangzigoucun",
        "\u671b\u5b50\u6c9f\u6751"
    ],
    "wof:name":"Wangzigou",
    "wof:placetype":"locality"
},
  "geometry": {"coordinates":[103.89197,34.54255999999999],"type":"Point"}
}