{
  "type": "Feature",
  "properties": {
    "gn:admin1_code":"30",
    "gn:asciiname":"Liangpengdong",
    "gn:country_code":"CN",
    "gn:dem":298,
    "gn:feature_class":"P",
    "gn:feature_code":"PPL",
    "gn:name":"Liangpengdong",
    "gn:population":0,
    "gn:timezone":"Asia/Shanghai",
    "iso:country":"CN",
    "name:zho_x_preferred":[
        "\u826f\u670b\u578c"
    ],
    "wof:name":"Liangpengdong",
    "wof:placetype":"locality"
},
  "geometry": {"coordinates":[112.13871,22.3984],"type":"Point"}
}