{
  "type": "Feature",
  "properties": {
    "gn:admin1_code":"12.0",
    "gn:asciiname":"Taipingji",
    "gn:country_code":"CN",
    "gn:dem":92,
    "gn:feature_class":"P",
    "gn:feature_code":"PPL",
    "gn:name":"Taipingji",
    "gn:population":0,
    "gn:timezone":"Asia/Shanghai",
    "iso:country":"CN",
    "name:zho_x_preferred":[
        "\u592a\u5e73\u96c6"
    ],
    "wof:name":"Taipingji",
    "wof:placetype":"locality"
},
  "geometry": {"coordinates":[111.86733999999998,31.73657],"type":"Point"}
}