{
  "type": "Feature",
  "properties": {
    "gn:admin1_code":"2.0",
    "gn:asciiname":"Xiaodie",
    "gn:country_code":"CN",
    "gn:dem":12,
    "gn:feature_class":"P",
    "gn:feature_code":"PPL",
    "gn:name":"Xiaodie",
    "gn:population":0,
    "gn:timezone":"Asia/Shanghai",
    "iso:country":"CN",
    "name:und_x_variant":[
        "Xiandiezhen"
    ],
    "name:zho_x_preferred":[
        "Hsiao-tieh-ts\u2019un"
    ],
    "wof:name":"Xiaodie",
    "wof:placetype":"locality"
},
  "geometry": {"coordinates":[121.17896,28.04613],"type":"Point"}
}