{
  "type": "Feature",
  "properties": {
    "gn:admin1_code":"1.0",
    "gn:asciiname":"Pangloucun",
    "gn:country_code":"CN",
    "gn:dem":37,
    "gn:feature_class":"P",
    "gn:feature_code":"PPL",
    "gn:name":"Pangloucun",
    "gn:population":0,
    "gn:timezone":"Asia/Shanghai",
    "iso:country":"CN",
    "name:zho_x_preferred":[
        "\u5e9e\u697c\u6751"
    ],
    "wof:name":"Pangloucun",
    "wof:placetype":"locality"
},
  "geometry": {"coordinates":[115.22320000000001,33.07598],"type":"Point"}
}