{
  "type": "Feature",
  "properties": {
    "gn:admin1_code":"2.0",
    "gn:asciiname":"Damingshan",
    "gn:country_code":"CN",
    "gn:dem":53,
    "gn:feature_class":"P",
    "gn:feature_code":"PPL",
    "gn:name":"Damingshan",
    "gn:population":0,
    "gn:timezone":"Asia/Shanghai",
    "iso:country":"CN",
    "name:zho_x_preferred":[
        "\u5927\u660e\u5c71"
    ],
    "wof:name":"Damingshan",
    "wof:placetype":"locality"
},
  "geometry": {"coordinates":[119.37444000000001,29.21989],"type":"Point"}
}