{
  "type": "Feature",
  "properties": {
    "gn:admin1_code":"26.0",
    "gn:asciiname":"Muguayuan",
    "gn:country_code":"CN",
    "gn:dem":1305,
    "gn:feature_class":"P",
    "gn:feature_code":"PPL",
    "gn:name":"Muguayuan",
    "gn:population":0,
    "gn:timezone":"Asia/Shanghai",
    "iso:country":"CN",
    "name:zho_x_preferred":[
        "\u6728\u74dc\u56ed"
    ],
    "wof:name":"Muguayuan",
    "wof:placetype":"locality"
},
  "geometry": {"coordinates":[108.40094000000001,33.59384],"type":"Point"}
}