{
  "type": "Feature",
  "properties": {
    "gn:admin1_code":"4.0",
    "gn:asciiname":"Yun'an Wuzu",
    "gn:country_code":"CN",
    "gn:dem":0,
    "gn:feature_class":"P",
    "gn:feature_code":"PPLF",
    "gn:name":"Yun\u2019an Wuzu",
    "gn:population":0,
    "gn:timezone":"Asia/Shanghai",
    "iso:country":"CN",
    "name:und_x_variant":[
        "Yun\u2019an Wuzu"
    ],
    "name:zho_x_preferred":[
        "\u4e91\u5b89\u4e94\u7ec4"
    ],
    "wof:name":"Yun'an Wuzu",
    "wof:placetype":"locality"
},
  "geometry": {"coordinates":[120.06999999999999,33.5442],"type":"Point"}
}