{
  "type": "Feature",
  "properties": {
    "gn:admin1_code":"10",
    "gn:asciiname":"Nanshaoguo",
    "gn:country_code":"CN",
    "gn:dem":612,
    "gn:feature_class":"P",
    "gn:feature_code":"PPL",
    "gn:name":"Nanshaoguo",
    "gn:population":0,
    "gn:timezone":"Asia/Shanghai",
    "iso:country":"CN",
    "name:zho_x_preferred":[
        "\u5357\u70e7\u9505"
    ],
    "wof:name":"Nanshaoguo",
    "wof:placetype":"locality"
},
  "geometry": {"coordinates":[118.15843,41.33004],"type":"Point"}
}