{
  "type": "Feature",
  "properties": {
    "gn:admin1_code":"29",
    "gn:asciiname":"Hongshiyan Xiaozhai",
    "gn:country_code":"CN",
    "gn:dem":1233,
    "gn:feature_class":"P",
    "gn:feature_code":"PPL",
    "gn:name":"Hongshiyan Xiaozhai",
    "gn:population":0,
    "gn:timezone":"Asia/Shanghai",
    "iso:country":"CN",
    "name:zho_x_preferred":[
        "\u7ea2\u77f3\u5ca9\u5c0f\u5be8"
    ],
    "wof:name":"Hongshiyan Xiaozhai",
    "wof:placetype":"locality"
},
  "geometry": {"coordinates":[104.833,24.0084],"type":"Point"}
}