{
  "type": "Feature",
  "properties": {
    "gn:admin1_code":"16.0",
    "gn:asciiname":"Xingwang",
    "gn:country_code":"CN",
    "gn:dem":425,
    "gn:feature_class":"P",
    "gn:feature_code":"PPL",
    "gn:name":"Xingwang",
    "gn:population":0,
    "gn:timezone":"Asia/Shanghai",
    "iso:country":"CN",
    "name:zho_x_preferred":[
        "\u5174\u65fa"
    ],
    "wof:name":"Xingwang",
    "wof:placetype":"locality"
},
  "geometry": {"coordinates":[107.967,24.2483],"type":"Point"}
}