{
  "type": "Feature",
  "properties": {
    "gn:admin1_code":"29.0",
    "gn:asciiname":"Hongbi",
    "gn:country_code":"CN",
    "gn:dem":1325,
    "gn:feature_class":"P",
    "gn:feature_code":"PPL",
    "gn:name":"Hongbi",
    "gn:population":0,
    "gn:timezone":"Asia/Shanghai",
    "iso:country":"CN",
    "name:zho_x_preferred":[
        "\u7ea2\u78a7"
    ],
    "wof:name":"Hongbi",
    "wof:placetype":"locality"
},
  "geometry": {"coordinates":[104.27397999999999,27.89097000000001],"type":"Point"}
}