{
  "type": "Feature",
  "properties": {
    "gn:admin1_code":"29.0",
    "gn:asciiname":"Wuguitan",
    "gn:country_code":"CN",
    "gn:dem":192,
    "gn:feature_class":"P",
    "gn:feature_code":"PPL",
    "gn:name":"Wuguitan",
    "gn:population":0,
    "gn:timezone":"Asia/Shanghai",
    "iso:country":"CN",
    "name:zho_x_preferred":[
        "\u4e4c\u9f9f\u6ee9"
    ],
    "wof:name":"Wuguitan",
    "wof:placetype":"locality"
},
  "geometry": {"coordinates":[103.60299999999999,22.827],"type":"Point"}
}