{
  "type": "Feature",
  "properties": {
    "gn:admin1_code":"02",
    "gn:asciiname":"Yaokengcun",
    "gn:country_code":"CN",
    "gn:dem":21,
    "gn:feature_class":"P",
    "gn:feature_code":"PPL",
    "gn:name":"Yaokengcun",
    "gn:population":0,
    "gn:timezone":"Asia/Shanghai",
    "iso:country":"CN",
    "name:und_x_variant":[
        "Yaokeng"
    ],
    "name:zho_x_preferred":[
        "\u7476\u5751\u6751"
    ],
    "wof:name":"Yaokengcun",
    "wof:placetype":"locality"
},
  "geometry": {"coordinates":[121.39895,28.2622],"type":"Point"}
}