{
  "type": "Feature",
  "properties": {
    "gn:admin1_code":"15.0",
    "gn:asciiname":"Yanjiacha",
    "gn:country_code":"CN",
    "gn:dem":1844,
    "gn:feature_class":"P",
    "gn:feature_code":"PPL",
    "gn:name":"Yanjiacha",
    "gn:population":0,
    "gn:timezone":"Asia/Shanghai",
    "iso:country":"CN",
    "name:und_x_variant":[
        "\u71d5\u5bb6\u5c94"
    ],
    "wof:name":"Yanjiacha",
    "wof:placetype":"locality"
},
  "geometry": {"coordinates":[105.024,35.6566],"type":"Point"}
}