{
  "type": "Feature",
  "properties": {
    "gn:admin1_code":"29.0",
    "gn:asciiname":"Wazuo",
    "gn:country_code":"CN",
    "gn:dem":2096,
    "gn:feature_class":"P",
    "gn:feature_code":"PPL",
    "gn:name":"Wazuo",
    "gn:population":0,
    "gn:timezone":"Asia/Shanghai",
    "iso:country":"CN",
    "name:zho_x_preferred":[
        "\u5a03\u5de6"
    ],
    "wof:name":"Wazuo",
    "wof:placetype":"locality"
},
  "geometry": {"coordinates":[100.961,26.2586],"type":"Point"}
}