{
  "type": "Feature",
  "properties": {
    "gn:admin1_code":"16.0",
    "gn:asciiname":"Caigui",
    "gn:country_code":"CN",
    "gn:dem":240,
    "gn:feature_class":"P",
    "gn:feature_code":"PPL",
    "gn:name":"Caigui",
    "gn:population":0,
    "gn:timezone":"Asia/Shanghai",
    "iso:country":"CN",
    "name:zho_x_preferred":[
        "\u624d\u8d35"
    ],
    "wof:name":"Caigui",
    "wof:placetype":"locality"
},
  "geometry": {"coordinates":[108.18899999999999,25.0052],"type":"Point"}
}