{
  "type": "Feature",
  "properties": {
    "gn:admin1_code":"8.0",
    "gn:asciiname":"Xinfengcun",
    "gn:country_code":"CN",
    "gn:dem":285,
    "gn:feature_class":"P",
    "gn:feature_code":"PPL",
    "gn:name":"Xinfengcun",
    "gn:population":0,
    "gn:timezone":"Asia/Shanghai",
    "iso:country":"CN",
    "name:zho_x_preferred":[
        "\u65b0\u98ce\u6751"
    ],
    "wof:name":"Xinfengcun",
    "wof:placetype":"locality"
},
  "geometry": {"coordinates":[130.72281000000001,45.38083],"type":"Point"}
}