{
  "type": "Feature",
  "properties": {
    "gn:admin1_code":"10",
    "gn:asciiname":"Yangsonggu",
    "gn:country_code":"CN",
    "gn:dem":54,
    "gn:feature_class":"P",
    "gn:feature_code":"PPL",
    "gn:name":"Yangsonggu",
    "gn:population":0,
    "gn:timezone":"Asia/Shanghai",
    "iso:country":"CN",
    "name:zho_x_preferred":[
        "\u6768\u5b8b\u56fa"
    ],
    "wof:name":"Yangsonggu",
    "wof:placetype":"locality"
},
  "geometry": {"coordinates":[114.878,36.4436],"type":"Point"}
}