{
  "type": "Feature",
  "properties": {
    "gn:admin1_code":"30.0",
    "gn:asciiname":"Yuliangtan",
    "gn:country_code":"CN",
    "gn:dem":172,
    "gn:feature_class":"P",
    "gn:feature_code":"PPL",
    "gn:name":"Yuliangtan",
    "gn:population":0,
    "gn:timezone":"Asia/Shanghai",
    "iso:country":"CN",
    "name:zho_x_preferred":[
        "Yuliangtan"
    ],
    "name:zho_x_variant":[
        "\u9c7c\u7cae\u6ee9"
    ],
    "wof:name":"Yuliangtan",
    "wof:placetype":"locality"
},
  "geometry": {"coordinates":[113.07917,25.27194],"type":"Point"}
}