{
  "type": "Feature",
  "properties": {
    "gn:admin1_code":"30",
    "gn:asciiname":"Weilun",
    "gn:country_code":"CN",
    "gn:dem":33,
    "gn:feature_class":"P",
    "gn:feature_code":"PPL",
    "gn:name":"Weilun",
    "gn:population":0,
    "gn:timezone":"Asia/Urumqi",
    "iso:country":"CN",
    "name:zho_x_preferred":[
        "\u5c3e\u8f6e"
    ],
    "wof:name":"Weilun",
    "wof:placetype":"locality"
},
  "geometry": {"coordinates":[111.10809,21.70333],"type":"Point"}
}