{
  "type": "Feature",
  "properties": {
    "gn:admin1_code":"12.0",
    "gn:asciiname":"Tianpu",
    "gn:country_code":"CN",
    "gn:dem":85,
    "gn:feature_class":"P",
    "gn:feature_code":"PPL",
    "gn:name":"Tianpu",
    "gn:population":0,
    "gn:timezone":"Asia/Shanghai",
    "iso:country":"CN",
    "name:zho_x_preferred":[
        "Tianpu"
    ],
    "name:zho_x_variant":[
        "\u7530\u94fa"
    ],
    "wof:name":"Tianpu",
    "wof:placetype":"locality"
},
  "geometry": {"coordinates":[114.66363,29.51294],"type":"Point"}
}