{
  "type": "Feature",
  "properties": {
    "gn:admin1_code":"14",
    "gn:asciiname":"Zhaqiongquba",
    "gn:country_code":"CN",
    "gn:dem":4682,
    "gn:feature_class":"P",
    "gn:feature_code":"PPL",
    "gn:name":"Zhaqiongquba",
    "gn:population":0,
    "gn:timezone":"Asia/Urumqi",
    "iso:country":"CN",
    "name:zho_x_preferred":[
        "\u624e\u743c\u66f2\u5df4"
    ],
    "wof:name":"Zhaqiongquba",
    "wof:placetype":"locality"
},
  "geometry": {"coordinates":[89.1088,31.0413],"type":"Point"}
}