{
  "type": "Feature",
  "properties": {
    "gn:admin1_code":"8.0",
    "gn:asciiname":"Nanchacun",
    "gn:country_code":"CN",
    "gn:dem":287,
    "gn:feature_class":"P",
    "gn:feature_code":"PPL",
    "gn:name":"Nanchacun",
    "gn:population":0,
    "gn:timezone":"Asia/Shanghai",
    "iso:country":"CN",
    "name:zho_x_preferred":[
        "\u5357\u5c94\u6751"
    ],
    "wof:name":"Nanchacun",
    "wof:placetype":"locality"
},
  "geometry": {"coordinates":[129.74311,44.63344],"type":"Point"}
}