{
  "type": "Feature",
  "properties": {
    "gn:admin1_code":"30.0",
    "gn:asciiname":"Suzikeng",
    "gn:country_code":"CN",
    "gn:dem":177,
    "gn:feature_class":"P",
    "gn:feature_code":"PPL",
    "gn:name":"Suzikeng",
    "gn:population":0,
    "gn:timezone":"Asia/Shanghai",
    "iso:country":"CN",
    "name:zho_x_preferred":[
        "\u7c9f\u5b50\u5751"
    ],
    "wof:name":"Suzikeng",
    "wof:placetype":"locality"
},
  "geometry": {"coordinates":[115.26427,23.2688],"type":"Point"}
}