{
  "type": "Feature",
  "properties": {
    "gn:admin1_code":"26.0",
    "gn:asciiname":"Changbali",
    "gn:country_code":"CN",
    "gn:dem":1027,
    "gn:feature_class":"P",
    "gn:feature_code":"PPL",
    "gn:name":"Changbali",
    "gn:population":0,
    "gn:timezone":"Asia/Shanghai",
    "iso:country":"CN",
    "name:und_x_variant":[
        "\u957f\u575d\u91cc"
    ],
    "wof:name":"Changbali",
    "wof:placetype":"locality"
},
  "geometry": {"coordinates":[106.41313999999998,33.41399000000001],"type":"Point"}
}