{
  "type": "Feature",
  "properties": {
    "gn:admin1_code":"16.0",
    "gn:asciiname":"Liuyicun",
    "gn:country_code":"CN",
    "gn:dem":245,
    "gn:feature_class":"P",
    "gn:feature_code":"PPL",
    "gn:name":"Liuyicun",
    "gn:population":0,
    "gn:timezone":"Asia/Shanghai",
    "iso:country":"CN",
    "name:zho_x_preferred":[
        "\u516d\u4e00\u6751"
    ],
    "wof:name":"Liuyicun",
    "wof:placetype":"locality"
},
  "geometry": {"coordinates":[107.251,23.9061],"type":"Point"}
}