{
  "type": "Feature",
  "properties": {
    "gn:admin1_code":"26.0",
    "gn:asciiname":"Longjiang",
    "gn:country_code":"CN",
    "gn:dem":1440,
    "gn:feature_class":"P",
    "gn:feature_code":"PPL",
    "gn:name":"Longjiang",
    "gn:population":0,
    "gn:timezone":"Asia/Shanghai",
    "iso:country":"CN",
    "name:ara_x_preferred":[
        "\u0644\u0648\u0646\u062a\u0634\u0648\u0646\u063a"
    ],
    "name:ben_x_preferred":[
        "\u09b2\u0982\u099c\u09bf\u09df\u09be\u0982"
    ],
    "name:ceb_x_preferred":[
        "Longjiang"
    ],
    "name:deu_x_preferred":[
        "Longjiang"
    ],
    "name:ell_x_preferred":[
        "\u039b\u03bf\u03bd\u03b3\u03ba\u03c4\u03b6\u03b9\u03ac\u03bd\u03b3\u03ba"
    ],
    "name:eng_x_preferred":[
        "Longjiang"
    ],
    "name:fas_x_preferred":[
        "\u0644\u0627\u0646\u06af \u062c\u06cc\u0627\u0646\u06af"
    ],
    "name:fra_x_preferred":[
        "Longjiang"
    ],
    "name:heb_x_preferred":[
        "\u05dc\u05d5\u05e0\u05d2\u05d2'\u05d9\u05d0\u05e0\u05d2"
    ],
    "name:hin_x_preferred":[
        "\u0932\u093e\u0902\u0917\u091c\u093f\u092f\u093e\u0902\u0917"
    ],
    "name:hun_x_preferred":[
        "Longjiang"
    ],
    "name:ind_x_preferred":[
        "Longjiang"
    ],
    "name:ita_x_preferred":[
        "Longjiang"
    ],
    "name:kor_x_preferred":[
        "\ub8fd\uc7a5"
    ],
    "name:mlg_x_preferred":[
        "Longjiang"
    ],
    "name:nld_x_preferred":[
        "Longjiang"
    ],
    "name:pol_x_preferred":[
        "Longjiang"
    ],
    "name:por_x_preferred":[
        "Longjiang"
    ],
    "name:rus_x_preferred":[
        "\u041b\u0443\u043d\u0446\u0437\u044f\u043d"
    ],
    "name:spa_x_preferred":[
        "Longjiang"
    ],
    "name:swe_x_preferred":[
        "Longjiang"
    ],
    "name:tur_x_preferred":[
        "Longjiang"
    ],
    "name:ukr_x_preferred":[
        "\u041b\u0443\u043d\u0446\u0437\u044f\u043d"
    ],
    "name:urd_x_preferred":[
        "\u0644\u0627\u0646\u06af\u062c\u06cc\u0627\u0646"
    ],
    "name:vie_x_preferred":[
        "Long Giang"
    ],
    "name:zho_x_preferred":[
        "\u9f99\u6c5f"
    ],
    "wof:name":"Longjiang",
    "wof:placetype":"locality"
},
  "geometry": {"coordinates":[109.80798,34.31971],"type":"Point"}
}