{
  "type": "Feature",
  "properties": {
    "gn:country":"CN",
    "gn:fcode":"PPLA3",
    "gn:pop":55841,
    "iso:country":"CN",
    "name:unk_x_variant":[
        "Changling"
    ],
    "name:zho_x_preferred":[
        "Ch\u2019ang-ling-chen"
    ],
    "name:zho_x_variant":[
        "Ch\u2019ang-ling-tzu",
        "Ch\u2019ang-ling-hsien",
        "\u957f\u5cad"
    ],
    "ne:ADM0CAP":0.0,
    "ne:ADM0NAME":"China",
    "ne:ADM0_A3":"CHN",
    "ne:ADM1NAME":"Jilin",
    "ne:ADMIN1_COD":5,
    "ne:CAPALT":0,
    "ne:CHANGED":0,
    "ne:CHECKME":0,
    "ne:COMPARE":0,
    "ne:DIFFASCII":0,
    "ne:ELEVATION":0.0,
    "ne:FEATURECLA":"Populated place",
    "ne:FEATURE_CL":"P",
    "ne:FEATURE_CO":"PPLA3",
    "ne:GEONAMEID":2038158,
    "ne:GEONAMESNO":"Geonames ascii name + lat.d + long.d matching.",
    "ne:GN_ASCII":"Changling",
    "ne:GN_POP":55841,
    "ne:GTOPO30":190.0,
    "ne:ISO_A2":"CN",
    "ne:LABELRANK":1,
    "ne:LATITUDE":44.269997,
    "ne:LONGITUDE":123.989992,
    "ne:LS_MATCH":1,
    "ne:LS_NAME":"Changling",
    "ne:MAX_AREAKM":25.0,
    "ne:MAX_AREAMI":10.0,
    "ne:MAX_BBXMAX":124.041667,
    "ne:MAX_BBXMIN":123.941667,
    "ne:MAX_BBYMAX":44.316667,
    "ne:MAX_BBYMIN":44.25,
    "ne:MAX_NATSCA":10.0,
    "ne:MAX_PERKM":40.0,
    "ne:MAX_PERMI":25.0,
    "ne:MAX_POP10":37566,
    "ne:MAX_POP20":0,
    "ne:MAX_POP300":0,
    "ne:MAX_POP310":0,
    "ne:MAX_POP50":0,
    "ne:MEAN_BBXC":123.985,
    "ne:MEAN_BBYC":44.2775,
    "ne:MEGACITY":0,
    "ne:MIN_AREAKM":25.0,
    "ne:MIN_AREAMI":10.0,
    "ne:MIN_BBXMAX":124.041667,
    "ne:MIN_BBXMIN":123.941667,
    "ne:MIN_BBYMAX":44.316667,
    "ne:MIN_BBYMIN":44.25,
    "ne:MIN_PERKM":40.0,
    "ne:MIN_PERMI":25.0,
    "ne:NAME":"Changling",
    "ne:NAMEASCII":"Changling",
    "ne:NAMEDIFF":0,
    "ne:NATSCALE":10,
    "ne:POP1950":0,
    "ne:POP1955":0,
    "ne:POP1960":0,
    "ne:POP1965":0,
    "ne:POP1970":0,
    "ne:POP1975":0,
    "ne:POP1980":0,
    "ne:POP1985":0,
    "ne:POP1990":0,
    "ne:POP1995":0,
    "ne:POP2000":0,
    "ne:POP2005":0,
    "ne:POP2010":0,
    "ne:POP2015":0,
    "ne:POP2020":0,
    "ne:POP2025":0,
    "ne:POP2050":0,
    "ne:POP_MAX":55841,
    "ne:POP_MIN":37566,
    "ne:POP_OTHER":32918,
    "ne:RANK_MAX":8,
    "ne:RANK_MIN":7,
    "ne:SCALERANK":8,
    "ne:SOV0NAME":"China",
    "ne:SOV_A3":"CHN",
    "ne:TIMEZONE":"Asia/Harbin",
    "ne:UN_FID":0,
    "ne:UN_LAT":0.0,
    "ne:UN_LONG":0.0,
    "ne:WORLDCITY":0,
    "qs:name":"\u957f\u5cad\u53bf",
    "qs:name_adm0":"\u4e2d\u570b",
    "qs:name_adm1":"\u5409\u6797\u7701",
    "qs:photos_9k":1,
    "qs:photos_9r":1,
    "qs:photos_all":1,
    "qs:photos_sr":0,
    "qs:placetype":"LocalAdmin",
    "qs:pop_sr":"8",
    "wd:wordcount":225,
    "wof:name":"\u957f\u5cad\u53bf",
    "wof:placetype":"localadmin",
    "wof:population":55841
},
  "geometry": {"coordinates":[124.00045,44.26532],"type":"Point"}
}