{
  "type": "Feature",
  "properties": {
    "gn:admin1_code":"8.0",
    "gn:asciiname":"Qinglingcun",
    "gn:country_code":"CN",
    "gn:dem":330,
    "gn:feature_class":"P",
    "gn:feature_code":"PPL",
    "gn:name":"Qinglingcun",
    "gn:population":0,
    "gn:timezone":"Asia/Shanghai",
    "iso:country":"CN",
    "name:zho_x_preferred":[
        "\u9752\u5cad\u6751"
    ],
    "wof:name":"Qinglingcun",
    "wof:placetype":"locality"
},
  "geometry": {"coordinates":[126.11266999999999,49.19978],"type":"Point"}
}