{
  "type": "Feature",
  "properties": {
    "gn:admin1_code":"16.0",
    "gn:asciiname":"Yiwu",
    "gn:country_code":"CN",
    "gn:dem":260,
    "gn:feature_class":"P",
    "gn:feature_code":"PPL",
    "gn:name":"Yiwu",
    "gn:population":0,
    "gn:timezone":"Asia/Shanghai",
    "iso:country":"CN",
    "name:zho_x_preferred":[
        "\u4e49\u4f0d"
    ],
    "wof:name":"Yiwu",
    "wof:placetype":"locality"
},
  "geometry": {"coordinates":[111.285,24.33],"type":"Point"}
}