{
  "type": "Feature",
  "properties": {
    "gn:admin1_code":"16.0",
    "gn:asciiname":"Yiwu",
    "gn:country_code":"CN",
    "gn:dem":260,
    "gn:feature_class":"P",
    "gn:feature_code":"PPL",
    "gn:name":"Yiwu",
    "gn:population":0,
    "gn:timezone":"Asia/Shanghai",
    "iso:country":"CN",
    "name:ara_x_preferred":[
        "\u064a\u064a\u0648\u0648"
    ],
    "name:cat_x_preferred":[
        "Yiwu"
    ],
    "name:ceb_x_preferred":[
        "Yiwu"
    ],
    "name:ces_x_preferred":[
        "I-wu"
    ],
    "name:deu_x_preferred":[
        "Yiwu"
    ],
    "name:fas_x_preferred":[
        "\u0627\u06cc\u0648\u0648"
    ],
    "name:fra_x_preferred":[
        "Yiwu"
    ],
    "name:heb_x_preferred":[
        "\u05d9\u05d9-\u05d5\u05d5"
    ],
    "name:hin_x_preferred":[
        "\u092f\u0940\u0935\u0942"
    ],
    "name:ita_x_preferred":[
        "Yiwu"
    ],
    "name:jpn_x_preferred":[
        "\u7fa9\u70cf\u5e02"
    ],
    "name:kik_x_preferred":[
        "Yiwu"
    ],
    "name:kor_x_preferred":[
        "\uc774\uc6b0\uc2dc"
    ],
    "name:mlg_x_preferred":[
        "Yiwu"
    ],
    "name:nld_x_preferred":[
        "Yiwu"
    ],
    "name:nor_x_preferred":[
        "Yiwu"
    ],
    "name:pol_x_preferred":[
        "Yiwu"
    ],
    "name:por_x_preferred":[
        "Y\u00ecw\u016b"
    ],
    "name:rus_x_preferred":[
        "\u0418\u0443"
    ],
    "name:spa_x_preferred":[
        "Yiwu"
    ],
    "name:swe_x_preferred":[
        "Yiwu"
    ],
    "name:tgl_x_preferred":[
        "Yiwu"
    ],
    "name:tur_x_preferred":[
        "Yiwu"
    ],
    "name:urd_x_preferred":[
        "\u06cc\u0648\u0648"
    ],
    "name:vie_x_preferred":[
        "Ngh\u0129a"
    ],
    "name:war_x_preferred":[
        "Yiwu"
    ],
    "name:wuu_x_preferred":[
        "\u7fa9\u70cf\u5e02"
    ],
    "name:zho_x_preferred":[
        "\u4e49\u4f0d"
    ],
    "name:zho_x_variant":[
        "\u4e49\u4e4c\u5e02"
    ],
    "wof:name":"Yiwu",
    "wof:placetype":"locality"
},
  "geometry": {"coordinates":[111.285,24.33],"type":"Point"}
}