{
  "type": "Feature",
  "properties": {
    "gn:admin1_code":"21.0",
    "gn:asciiname":"Fengdeng",
    "gn:country_code":"CN",
    "gn:dem":1122,
    "gn:feature_class":"P",
    "gn:feature_code":"PPL",
    "gn:name":"Fengdeng",
    "gn:population":0,
    "gn:timezone":"Asia/Shanghai",
    "iso:country":"CN",
    "name:zho_x_preferred":[
        "\u4e30\u767b"
    ],
    "name:zho_x_variant":[
        "\u4e30\u767b\u9547"
    ],
    "wof:name":"Fengdeng",
    "wof:placetype":"locality"
},
  "geometry": {"coordinates":[106.19499999999999,38.173],"type":"Point"}
}