{
  "type": "Feature",
  "properties": {
    "gn:admin1_code":"26.0",
    "gn:asciiname":"Yanmiguacun",
    "gn:country_code":"CN",
    "gn:dem":1539,
    "gn:feature_class":"P",
    "gn:feature_code":"PPL",
    "gn:name":"Yanmiguacun",
    "gn:population":0,
    "gn:timezone":"Asia/Shanghai",
    "iso:country":"CN",
    "name:zho_x_preferred":[
        "\u95eb\u7c73\u576c\u6751"
    ],
    "wof:name":"Yanmiguacun",
    "wof:placetype":"locality"
},
  "geometry": {"coordinates":[108.57227,37.41423],"type":"Point"}
}