{
  "type": "Feature",
  "properties": {
    "gn:admin1_code":"30.0",
    "gn:asciiname":"Caidongwei",
    "gn:country_code":"CN",
    "gn:dem":160,
    "gn:feature_class":"P",
    "gn:feature_code":"PPL",
    "gn:name":"Caidongwei",
    "gn:population":0,
    "gn:timezone":"Asia/Shanghai",
    "iso:country":"CN",
    "name:zho_x_preferred":[
        "\u83dc\u6d1e\u5c3e"
    ],
    "wof:name":"Caidongwei",
    "wof:placetype":"locality"
},
  "geometry": {"coordinates":[113.70715,23.97913],"type":"Point"}
}