{
  "type": "Feature",
  "properties": {
    "gn:admin1_code":"19.0",
    "gn:asciiname":"Shuangshutuocun",
    "gn:country_code":"CN",
    "gn:dem":13,
    "gn:feature_class":"P",
    "gn:feature_code":"PPL",
    "gn:name":"Shuangshutuocun",
    "gn:population":0,
    "gn:timezone":"Asia/Shanghai",
    "iso:country":"CN",
    "name:zho_x_preferred":[
        "\u53cc\u6811\u5768\u6751"
    ],
    "wof:name":"Shuangshutuocun",
    "wof:placetype":"locality"
},
  "geometry": {"coordinates":[122.81494000000001,41.43453],"type":"Point"}
}