{
  "type": "Feature",
  "properties": {
    "gn:admin1_code":"29.0",
    "gn:asciiname":"Shangcaopi",
    "gn:country_code":"CN",
    "gn:dem":2167,
    "gn:feature_class":"P",
    "gn:feature_code":"PPL",
    "gn:name":"Shangcaopi",
    "gn:population":0,
    "gn:timezone":"Asia/Shanghai",
    "iso:country":"CN",
    "name:zho_x_preferred":[
        "\u4e0a\u8349\u76ae"
    ],
    "wof:name":"Shangcaopi",
    "wof:placetype":"locality"
},
  "geometry": {"coordinates":[100.26900000000001,24.8055],"type":"Point"}
}