{
  "type": "Feature",
  "properties": {
    "gn:admin1_code":"26.0",
    "gn:asciiname":"Liutianchicun",
    "gn:country_code":"CN",
    "gn:dem":1633,
    "gn:feature_class":"P",
    "gn:feature_code":"PPL",
    "gn:name":"Liutianchicun",
    "gn:population":0,
    "gn:timezone":"Asia/Shanghai",
    "iso:country":"CN",
    "name:zho_x_preferred":[
        "\u5218\u5929\u6c60\u6751"
    ],
    "wof:name":"Liutianchicun",
    "wof:placetype":"locality"
},
  "geometry": {"coordinates":[107.62201,37.12152],"type":"Point"}
}