{
  "type": "Feature",
  "properties": {
    "gn:admin1_code":"20.0",
    "gn:asciiname":"Houbuzi",
    "gn:country_code":"CN",
    "gn:dem":1749,
    "gn:feature_class":"P",
    "gn:feature_code":"PPL",
    "gn:name":"Houbuzi",
    "gn:population":0,
    "gn:timezone":"Asia/Shanghai",
    "iso:country":"CN",
    "name:und_x_variant":[
        "\u540e\u535c\u5b50"
    ],
    "wof:name":"Houbuzi",
    "wof:placetype":"locality"
},
  "geometry": {"coordinates":[112.14503000000001,41.50836],"type":"Point"}
}