{
  "type": "Feature",
  "properties": {
    "gn:admin1_code":"10",
    "gn:asciiname":"Zhouzhai",
    "gn:country_code":"CN",
    "gn:dem":51,
    "gn:feature_class":"P",
    "gn:feature_code":"PPL",
    "gn:name":"Zhouzhai",
    "gn:population":0,
    "gn:timezone":"Asia/Shanghai",
    "iso:country":"CN",
    "name:zho_x_preferred":[
        "\u5468\u5be8"
    ],
    "wof:name":"Zhouzhai",
    "wof:placetype":"locality"
},
  "geometry": {"coordinates":[114.68300000000001,36.6364],"type":"Point"}
}