{
  "type": "Feature",
  "properties": {
    "gn:admin1_code":"13",
    "gn:asciiname":"Dalaotan",
    "gn:country_code":"CN",
    "gn:dem":1089,
    "gn:feature_class":"P",
    "gn:feature_code":"PPL",
    "gn:name":"Dalaotan",
    "gn:population":0,
    "gn:timezone":"Asia/Urumqi",
    "iso:country":"CN",
    "name:und_x_variant":[
        "\u5927\u6d9d\u5766"
    ],
    "wof:name":"Dalaotan",
    "wof:placetype":"locality"
},
  "geometry": {"coordinates":[87.37246999999998,42.14814000000001],"type":"Point"}
}