{
  "type": "Feature",
  "properties": {
    "gn:admin1_code":"19.0",
    "gn:asciiname":"Jishuncun",
    "gn:country_code":"CN",
    "gn:dem":104,
    "gn:feature_class":"P",
    "gn:feature_code":"PPL",
    "gn:name":"Jishuncun",
    "gn:population":0,
    "gn:timezone":"Asia/Shanghai",
    "iso:country":"CN",
    "name:zho_x_preferred":[
        "\u5409\u987a\u6751"
    ],
    "wof:name":"Jishuncun",
    "wof:placetype":"locality"
},
  "geometry": {"coordinates":[122.56726999999999,39.84037],"type":"Point"}
}