{
  "type": "Feature",
  "properties": {
    "gn:admin1_code":"19.0",
    "gn:asciiname":"Pingsheng",
    "gn:country_code":"CN",
    "gn:dem":2,
    "gn:feature_class":"P",
    "gn:feature_code":"PPL",
    "gn:name":"Pingsheng",
    "gn:population":0,
    "gn:timezone":"Asia/Shanghai",
    "iso:country":"CN",
    "name:und_x_variant":[
        "\u5e73\u76db"
    ],
    "wof:name":"Pingsheng",
    "wof:placetype":"locality"
},
  "geometry": {"coordinates":[122.05658,40.78072],"type":"Point"}
}