{
  "type": "Feature",
  "properties": {
    "gn:admin1_code":"25",
    "gn:asciiname":"Leishigou",
    "gn:country_code":"CN",
    "gn:dem":157,
    "gn:feature_class":"P",
    "gn:feature_code":"PPL",
    "gn:name":"Leishigou",
    "gn:population":0,
    "gn:timezone":"Asia/Shanghai",
    "iso:country":"CN",
    "name:zho_x_preferred":[
        "\u78ca\u77f3\u6c9f"
    ],
    "wof:name":"Leishigou",
    "wof:placetype":"locality"
},
  "geometry": {"coordinates":[118.246,35.4936],"type":"Point"}
}