{
  "type": "Feature",
  "properties": {
    "gn:admin1_code":"25",
    "gn:asciiname":"Baishui Niushi Qiancun",
    "gn:country_code":"CN",
    "gn:dem":80,
    "gn:feature_class":"P",
    "gn:feature_code":"PPL",
    "gn:name":"Baishui Niushi Qiancun",
    "gn:population":0,
    "gn:timezone":"Asia/Shanghai",
    "iso:country":"CN",
    "name:zho_x_preferred":[
        "\u767d\u6c34\u725b\u77f3\u524d\u6751"
    ],
    "wof:name":"Baishui Niushi Qiancun",
    "wof:placetype":"locality"
},
  "geometry": {"coordinates":[117.81699999999999,34.8523],"type":"Point"}
}