{
  "type": "Feature",
  "properties": {
    "gn:admin1_code":"12.0",
    "gn:asciiname":"Wantian",
    "gn:country_code":"CN",
    "gn:dem":762,
    "gn:feature_class":"P",
    "gn:feature_code":"PPL",
    "gn:name":"Wantian",
    "gn:population":0,
    "gn:timezone":"Asia/Shanghai",
    "iso:country":"CN",
    "name:zho_x_preferred":[
        "Wantian"
    ],
    "name:zho_x_variant":[
        "\u5f2f\u7530"
    ],
    "wof:name":"Wantian",
    "wof:placetype":"locality"
},
  "geometry": {"coordinates":[109.17565999999999,29.89027],"type":"Point"}
}