{
  "type": "Feature",
  "properties": {
    "gn:admin1_code":"29.0",
    "gn:asciiname":"Daxinzhai",
    "gn:country_code":"CN",
    "gn:dem":1736,
    "gn:feature_class":"P",
    "gn:feature_code":"PPL",
    "gn:name":"Daxinzhai",
    "gn:population":0,
    "gn:timezone":"Asia/Shanghai",
    "iso:country":"CN",
    "name:zho_x_preferred":[
        "\u5927\u65b0\u5be8"
    ],
    "wof:name":"Daxinzhai",
    "wof:placetype":"locality"
},
  "geometry": {"coordinates":[102.739,23.1214],"type":"Point"}
}