{
  "type": "Feature",
  "properties": {
    "gn:admin1_code":"32.0",
    "gn:asciiname":"Gelang",
    "gn:country_code":"CN",
    "gn:dem":3339,
    "gn:feature_class":"P",
    "gn:feature_code":"PPL",
    "gn:name":"Gelang",
    "gn:population":0,
    "gn:timezone":"Asia/Shanghai",
    "iso:country":"CN",
    "name:zho_x_preferred":[
        "\u6208\u90ce"
    ],
    "wof:name":"Gelang",
    "wof:placetype":"locality"
},
  "geometry": {"coordinates":[99.1339,29.3115],"type":"Point"}
}