{
  "type": "Feature",
  "properties": {
    "gn:admin1_code":"2.0",
    "gn:asciiname":"Zhipu",
    "gn:country_code":"CN",
    "gn:dem":261,
    "gn:feature_class":"P",
    "gn:feature_code":"PPL",
    "gn:name":"Zhipu",
    "gn:population":0,
    "gn:timezone":"Asia/Shanghai",
    "iso:country":"CN",
    "name:zho_x_preferred":[
        "\u7eb8\u94fa"
    ],
    "wof:name":"Zhipu",
    "wof:placetype":"locality"
},
  "geometry": {"coordinates":[120.53859,29.21277000000001],"type":"Point"}
}