{
  "type": "Feature",
  "properties": {
    "gn:admin1_code":"9",
    "gn:asciiname":"Fanzhanglou",
    "gn:country_code":"CN",
    "gn:dem":48,
    "gn:feature_class":"P",
    "gn:feature_code":"PPL",
    "gn:name":"Fanzhanglou",
    "gn:population":0,
    "gn:timezone":"Asia/Shanghai",
    "iso:country":"CN",
    "name:zho_x_preferred":[
        "\u8303\u5f20\u697c"
    ],
    "wof:name":"Fanzhanglou",
    "wof:placetype":"locality"
},
  "geometry": {"coordinates":[115.69136,35.90339],"type":"Point"}
}