{
  "type": "Feature",
  "properties": {
    "gn:admin1_code":"18.0",
    "gn:asciiname":"Yangtaozhai",
    "gn:country_code":"CN",
    "gn:dem":502,
    "gn:feature_class":"P",
    "gn:feature_code":"PPL",
    "gn:name":"Yangtaozhai",
    "gn:population":0,
    "gn:timezone":"Asia/Shanghai",
    "iso:country":"CN",
    "name:zho_x_preferred":[
        "\u7f8a\u6843\u5be8"
    ],
    "wof:name":"Yangtaozhai",
    "wof:placetype":"locality"
},
  "geometry": {"coordinates":[108.119,25.8207],"type":"Point"}
}