{
  "type": "Feature",
  "properties": {
    "gn:admin1_code":"12.0",
    "gn:asciiname":"Tangjia Dawan",
    "gn:country_code":"CN",
    "gn:dem":65,
    "gn:feature_class":"P",
    "gn:feature_code":"PPL",
    "gn:name":"Tangjia Dawan",
    "gn:population":0,
    "gn:timezone":"Asia/Shanghai",
    "iso:country":"CN",
    "name:zho_x_preferred":[
        "Tangjia Dawan"
    ],
    "name:zho_x_variant":[
        "\u5510\u5bb6\u5927\u6e7e"
    ],
    "wof:name":"Tangjia Dawan",
    "wof:placetype":"locality"
},
  "geometry": {"coordinates":[111.42306000000001,30.48802],"type":"Point"}
}