{
  "type": "Feature",
  "properties": {
    "gn:admin1_code":"26.0",
    "gn:asciiname":"Liujia Yayaocun",
    "gn:country_code":"CN",
    "gn:dem":1071,
    "gn:feature_class":"P",
    "gn:feature_code":"PPL",
    "gn:name":"Liujia Yayaocun",
    "gn:population":0,
    "gn:timezone":"Asia/Shanghai",
    "iso:country":"CN",
    "name:zho_x_preferred":[
        "\u5218\u5bb6\u5d16\u7a91\u6751"
    ],
    "wof:name":"Liujia Yayaocun",
    "wof:placetype":"locality"
},
  "geometry": {"coordinates":[110.825,38.7739],"type":"Point"}
}