{
  "type": "Feature",
  "properties": {
    "gn:admin1_code":"32.0",
    "gn:asciiname":"Bieliedajue",
    "gn:country_code":"CN",
    "gn:dem":2159,
    "gn:feature_class":"P",
    "gn:feature_code":"PPL",
    "gn:name":"Bieliedajue",
    "gn:population":0,
    "gn:timezone":"Asia/Shanghai",
    "iso:country":"CN",
    "name:zho_x_preferred":[
        "\u522b\u54a7\u6253\u89c9"
    ],
    "wof:name":"Bieliedajue",
    "wof:placetype":"locality"
},
  "geometry": {"coordinates":[103.185,28.7339],"type":"Point"}
}