{
  "type": "Feature",
  "properties": {
    "gn:admin1_code":"26.0",
    "gn:asciiname":"Dashucun",
    "gn:country_code":"CN",
    "gn:dem":1096,
    "gn:feature_class":"P",
    "gn:feature_code":"PPL",
    "gn:name":"Dashucun",
    "gn:population":0,
    "gn:timezone":"Asia/Shanghai",
    "iso:country":"CN",
    "name:zho_x_preferred":[
        "\u5927\u6811\u6751"
    ],
    "wof:name":"Dashucun",
    "wof:placetype":"locality"
},
  "geometry": {"coordinates":[109.37582999999999,33.39925],"type":"Point"}
}