{
  "type": "Feature",
  "properties": {
    "gn:admin1_code":"8.0",
    "gn:asciiname":"Jianshancun",
    "gn:country_code":"CN",
    "gn:dem":292,
    "gn:feature_class":"P",
    "gn:feature_code":"PPL",
    "gn:name":"Jianshancun",
    "gn:population":0,
    "gn:timezone":"Asia/Shanghai",
    "iso:country":"CN",
    "name:zho_x_preferred":[
        "\u5c16\u5c71\u6751"
    ],
    "wof:name":"Jianshancun",
    "wof:placetype":"locality"
},
  "geometry": {"coordinates":[125.79161999999999,48.43383],"type":"Point"}
}