{
  "type": "Feature",
  "properties": {
    "gn:admin1_code":"20",
    "gn:asciiname":"Hantai",
    "gn:country_code":"CN",
    "gn:dem":1468,
    "gn:feature_class":"P",
    "gn:feature_code":"PPL",
    "gn:name":"Hantai",
    "gn:population":0,
    "gn:timezone":"Asia/Shanghai",
    "iso:country":"CN",
    "name:deu_x_preferred":[
        "Hanta\u00ef"
    ],
    "name:fra_x_preferred":[
        "Hantai"
    ],
    "name:nds_x_preferred":[
        "Hanta\u00ef"
    ],
    "wof:name":"Hantai",
    "wof:placetype":"locality"
},
  "geometry": {"coordinates":[109.80694,39.84083],"type":"Point"}
}