{
  "type": "Feature",
  "properties": {
    "gn:admin1_code":"30.0",
    "gn:asciiname":"Pingfu",
    "gn:country_code":"CN",
    "gn:dem":76,
    "gn:feature_class":"P",
    "gn:feature_code":"PPL",
    "gn:name":"Pingfu",
    "gn:population":0,
    "gn:timezone":"Asia/Shanghai",
    "iso:country":"CN",
    "name:zho_x_preferred":[
        "\u5e73\u752b"
    ],
    "wof:name":"Pingfu",
    "wof:placetype":"locality"
},
  "geometry": {"coordinates":[113.79179000000001,24.94853],"type":"Point"}
}