{
  "type": "Feature",
  "properties": {
    "gn:admin1_code":"11.0",
    "gn:asciiname":"Zhaojialong",
    "gn:country_code":"CN",
    "gn:dem":433,
    "gn:feature_class":"P",
    "gn:feature_code":"PPL",
    "gn:name":"Zhaojialong",
    "gn:population":0,
    "gn:timezone":"Asia/Shanghai",
    "iso:country":"CN",
    "name:zho_x_preferred":[
        "\u8d75\u5bb6\u5785"
    ],
    "wof:name":"Zhaojialong",
    "wof:placetype":"locality"
},
  "geometry": {"coordinates":[110.91562999999999,27.44356],"type":"Point"}
}