{
  "type": "Feature",
  "properties": {
    "gn:admin1_code":"32.0",
    "gn:asciiname":"Qingquansi",
    "gn:country_code":"CN",
    "gn:dem":933,
    "gn:feature_class":"P",
    "gn:feature_code":"PPL",
    "gn:name":"Qingquansi",
    "gn:population":0,
    "gn:timezone":"Asia/Shanghai",
    "iso:country":"CN",
    "name:zho_x_preferred":[
        "\u6e05\u6cc9\u5bfa"
    ],
    "wof:name":"Qingquansi",
    "wof:placetype":"locality"
},
  "geometry": {"coordinates":[104.129,31.4158],"type":"Point"}
}