{
  "type": "Feature",
  "properties": {
    "gn:admin1_code":"9.0",
    "gn:asciiname":"Hejiazhuang",
    "gn:country_code":"CN",
    "gn:dem":142,
    "gn:feature_class":"P",
    "gn:feature_code":"PPL",
    "gn:name":"Hejiazhuang",
    "gn:population":0,
    "gn:timezone":"Asia/Shanghai",
    "iso:country":"CN",
    "name:und_x_variant":[
        "\u8d3a\u5bb6\u5e84",
        "Hejiazhuang"
    ],
    "wof:name":"Hejiazhuang",
    "wof:placetype":"locality"
},
  "geometry": {"coordinates":[112.85420999999999,33.19165],"type":"Point"}
}