{
  "type": "Feature",
  "properties": {
    "gn:admin1_code":"25",
    "gn:asciiname":"Anqiufu",
    "gn:country_code":"CN",
    "gn:dem":53,
    "gn:feature_class":"P",
    "gn:feature_code":"PPL",
    "gn:name":"Anqiufu",
    "gn:population":0,
    "gn:timezone":"Asia/Shanghai",
    "iso:country":"CN",
    "name:zho_x_preferred":[
        "\u5b89\u90b1\u5e9c"
    ],
    "wof:name":"Anqiufu",
    "wof:placetype":"locality"
},
  "geometry": {"coordinates":[116.818,35.5976],"type":"Point"}
}