{
  "type": "Feature",
  "properties": {
    "gn:admin1_code":"32.0",
    "gn:asciiname":"Shuijinggou",
    "gn:country_code":"CN",
    "gn:dem":317,
    "gn:feature_class":"P",
    "gn:feature_code":"PPL",
    "gn:name":"Shuijinggou",
    "gn:population":0,
    "gn:timezone":"Asia/Shanghai",
    "iso:country":"CN",
    "name:zho_x_preferred":[
        "\u6c34\u4e95\u6c9f"
    ],
    "wof:name":"Shuijinggou",
    "wof:placetype":"locality"
},
  "geometry": {"coordinates":[105.75055999999999,28.88732000000001],"type":"Point"}
}