{
  "type": "Feature",
  "properties": {
    "gn:admin1_code":"15.0",
    "gn:asciiname":"Wangjia Xinzhuang",
    "gn:country_code":"CN",
    "gn:dem":2037,
    "gn:feature_class":"P",
    "gn:feature_code":"PPL",
    "gn:name":"Wangjia Xinzhuang",
    "gn:population":0,
    "gn:timezone":"Asia/Shanghai",
    "iso:country":"CN",
    "name:zho_x_preferred":[
        "\u738b\u5bb6\u65b0\u5e84"
    ],
    "wof:name":"Wangjia Xinzhuang",
    "wof:placetype":"locality"
},
  "geometry": {"coordinates":[104.746,35.6405],"type":"Point"}
}