{
  "type": "Feature",
  "properties": {
    "gn:admin1_code":"26",
    "gn:asciiname":"Xujiahe",
    "gn:country_code":"CN",
    "gn:dem":522,
    "gn:feature_class":"P",
    "gn:feature_code":"PPL",
    "gn:name":"Xujiahe",
    "gn:population":0,
    "gn:timezone":"Asia/Shanghai",
    "iso:country":"CN",
    "wof:name":"Xujiahe",
    "wof:placetype":"locality"
},
  "geometry": {"coordinates":[109.15833000000001,32.68639],"type":"Point"}
}