{
  "type": "Feature",
  "properties": {
    "gn:admin1_code":"23.0",
    "gn:asciiname":"Fanjiazhai",
    "gn:country_code":"CN",
    "gn:dem":5,
    "gn:feature_class":"P",
    "gn:feature_code":"PPL",
    "gn:name":"Fanjiazhai",
    "gn:population":0,
    "gn:timezone":"Asia/Shanghai",
    "iso:country":"CN",
    "name:zho_x_preferred":[
        "Fanjiazhai"
    ],
    "name:zho_x_variant":[
        "\u6a0a\u5bb6\u5b85"
    ],
    "wof:name":"Fanjiazhai",
    "wof:placetype":"locality"
},
  "geometry": {"coordinates":[121.31556,31.467],"type":"Point"}
}