{
  "type": "Feature",
  "properties": {
    "gn:admin1_code":"11.0",
    "gn:asciiname":"Daishutang",
    "gn:country_code":"CN",
    "gn:dem":88,
    "gn:feature_class":"P",
    "gn:feature_code":"PPL",
    "gn:name":"Daishutang",
    "gn:population":0,
    "gn:timezone":"Asia/Shanghai",
    "iso:country":"CN",
    "name:zho_x_preferred":[
        "\u4ee3\u4e66\u5802"
    ],
    "wof:name":"Daishutang",
    "wof:placetype":"locality"
},
  "geometry": {"coordinates":[112.32617,27.02594],"type":"Point"}
}