{
  "type": "Feature",
  "properties": {
    "gn:admin1_code":"29.0",
    "gn:asciiname":"Laojiuzhai",
    "gn:country_code":"CN",
    "gn:dem":1224,
    "gn:feature_class":"P",
    "gn:feature_code":"PPL",
    "gn:name":"Laojiuzhai",
    "gn:population":0,
    "gn:timezone":"Asia/Shanghai",
    "iso:country":"CN",
    "name:zho_x_preferred":[
        "\u8001\u65e7\u5be8"
    ],
    "wof:name":"Laojiuzhai",
    "wof:placetype":"locality"
},
  "geometry": {"coordinates":[98.9212,23.9916],"type":"Point"}
}