{
  "type": "Feature",
  "properties": {
    "gn:admin1_code":"19.0",
    "gn:asciiname":"Shengzongmiao",
    "gn:country_code":"CN",
    "gn:dem":226,
    "gn:feature_class":"P",
    "gn:feature_code":"PPL",
    "gn:name":"Shengzongmiao",
    "gn:population":0,
    "gn:timezone":"Asia/Shanghai",
    "iso:country":"CN",
    "name:zho_x_preferred":[
        "\u5723\u5b97\u5e99"
    ],
    "wof:name":"Shengzongmiao",
    "wof:placetype":"locality"
},
  "geometry": {"coordinates":[120.223,40.788],"type":"Point"}
}