{
  "type": "Feature",
  "properties": {
    "gn:admin1_code":"25",
    "gn:asciiname":"Guloudian",
    "gn:country_code":"CN",
    "gn:dem":22,
    "gn:feature_class":"P",
    "gn:feature_code":"PPL",
    "gn:name":"Guloudian",
    "gn:population":0,
    "gn:timezone":"Asia/Shanghai",
    "iso:country":"CN",
    "name:zho_x_preferred":[
        "\u53e4\u697c\u5e97"
    ],
    "wof:name":"Guloudian",
    "wof:placetype":"locality"
},
  "geometry": {"coordinates":[116.54600000000001,37.2396],"type":"Point"}
}