{
  "type": "Feature",
  "properties": {
    "gn:admin1_code":"9.0",
    "gn:asciiname":"Guolaozhuang",
    "gn:country_code":"CN",
    "gn:dem":149,
    "gn:feature_class":"P",
    "gn:feature_code":"PPL",
    "gn:name":"Guolaozhuang",
    "gn:population":0,
    "gn:timezone":"Asia/Shanghai",
    "iso:country":"CN",
    "name:und_x_variant":[
        "\u90ed\u8001\u5e84",
        "Guolaozhuang"
    ],
    "wof:name":"Guolaozhuang",
    "wof:placetype":"locality"
},
  "geometry": {"coordinates":[112.76577,33.15065999999999],"type":"Point"}
}