{
  "type": "Feature",
  "properties": {
    "gn:admin1_code":"5.0",
    "gn:asciiname":"Jinxingcun",
    "gn:country_code":"CN",
    "gn:dem":348,
    "gn:feature_class":"P",
    "gn:feature_code":"PPL",
    "gn:name":"Jinxingcun",
    "gn:population":0,
    "gn:timezone":"Asia/Shanghai",
    "iso:country":"CN",
    "name:zho_x_preferred":[
        "\u91d1\u661f\u6751"
    ],
    "wof:name":"Jinxingcun",
    "wof:placetype":"locality"
},
  "geometry": {"coordinates":[125.50631,42.40507],"type":"Point"}
}