{
  "type": "Feature",
  "properties": {
    "gn:admin1_code":"12.0",
    "gn:asciiname":"Zhouzhuang",
    "gn:country_code":"CN",
    "gn:dem":382,
    "gn:feature_class":"P",
    "gn:feature_code":"PPL",
    "gn:name":"Zhouzhuang",
    "gn:population":0,
    "gn:timezone":"Asia/Shanghai",
    "iso:country":"CN",
    "name:ceb_x_preferred":[
        "Zhouzhuang"
    ],
    "name:deu_x_preferred":[
        "Zhouzhuang"
    ],
    "name:fas_x_preferred":[
        "\u0698\u0648\u0698\u0648\u0627\u0646\u06af"
    ],
    "name:fra_x_preferred":[
        "Zhouzhuang"
    ],
    "name:ita_x_preferred":[
        "Zhouzhuang"
    ],
    "name:jpn_x_preferred":[
        "\u5468\u8358\u93ae"
    ],
    "name:kor_x_preferred":[
        "\uc800\uc6b0\uc7a5 \uc9c4"
    ],
    "name:nor_x_preferred":[
        "Zhouzhuang"
    ],
    "name:spa_x_preferred":[
        "Zhouzhuang"
    ],
    "name:sqi_x_preferred":[
        "Zhouzhuan"
    ],
    "name:swe_x_preferred":[
        "Zhouzhuang"
    ],
    "name:ukr_x_preferred":[
        "\u0427\u0436\u043e\u0443\u0447\u0436\u0443\u0430\u043d"
    ],
    "name:vie_x_preferred":[
        "Chu Trang"
    ],
    "name:wuu_x_preferred":[
        "\u5468\u5e84\u9547"
    ],
    "name:zho_x_preferred":[
        "\u5468\u5e84"
    ],
    "name:zho_x_variant":[
        "\u5468\u5e84\u9547"
    ],
    "wof:name":"Zhouzhuang",
    "wof:placetype":"locality"
},
  "geometry": {"coordinates":[111.0659,33.08315],"type":"Point"}
}