{
  "type": "Feature",
  "properties": {
    "gn:admin1_code":"11.0",
    "gn:asciiname":"Xingqiping",
    "gn:country_code":"CN",
    "gn:dem":1020,
    "gn:feature_class":"P",
    "gn:feature_code":"PPL",
    "gn:name":"Xingqiping",
    "gn:population":0,
    "gn:timezone":"Asia/Shanghai",
    "iso:country":"CN",
    "name:zho_x_preferred":[
        "Xingqiping"
    ],
    "name:zho_x_variant":[
        "\u661f\u671f\u576a"
    ],
    "wof:name":"Xingqiping",
    "wof:placetype":"locality"
},
  "geometry": {"coordinates":[110.16070000000001,28.92866],"type":"Point"}
}