{
  "type": "Feature",
  "properties": {
    "gn:admin1_code":"30.0",
    "gn:asciiname":"Meihuazhai",
    "gn:country_code":"CN",
    "gn:dem":669,
    "gn:feature_class":"P",
    "gn:feature_code":"PPL",
    "gn:name":"Meihuazhai",
    "gn:population":0,
    "gn:timezone":"Asia/Shanghai",
    "iso:country":"CN",
    "name:zho_x_preferred":[
        "\u6885\u82b1\u5be8"
    ],
    "wof:name":"Meihuazhai",
    "wof:placetype":"locality"
},
  "geometry": {"coordinates":[114.58642,25.37332],"type":"Point"}
}