{
  "type": "Feature",
  "properties": {
    "gn:admin1_code":"15.0",
    "gn:asciiname":"Yubo",
    "gn:country_code":"CN",
    "gn:dem":1722,
    "gn:feature_class":"P",
    "gn:feature_code":"PPL",
    "gn:name":"Yubo",
    "gn:population":0,
    "gn:timezone":"Asia/Shanghai",
    "iso:country":"CN",
    "name:fra_x_preferred":[
        "Yubo"
    ],
    "name:zho_x_preferred":[
        "\u96e8\u4f2f"
    ],
    "wof:name":"Yubo",
    "wof:placetype":"locality"
},
  "geometry": {"coordinates":[105.54600000000001,34.8469],"type":"Point"}
}