{
  "type": "Feature",
  "properties": {
    "gn:admin1_code":"29.0",
    "gn:asciiname":"Laofengzhai",
    "gn:country_code":"CN",
    "gn:dem":1283,
    "gn:feature_class":"P",
    "gn:feature_code":"PPL",
    "gn:name":"Laofengzhai",
    "gn:population":0,
    "gn:timezone":"Asia/Shanghai",
    "iso:country":"CN",
    "name:zho_x_preferred":[
        "\u8001\u5c01\u5be8"
    ],
    "wof:name":"Laofengzhai",
    "wof:placetype":"locality"
},
  "geometry": {"coordinates":[101.23999999999999,22.9011],"type":"Point"}
}