{
  "type": "Feature",
  "properties": {
    "gn:admin1_code":"26.0",
    "gn:asciiname":"Qiaogou",
    "gn:country_code":"CN",
    "gn:dem":1069,
    "gn:feature_class":"P",
    "gn:feature_code":"PPL",
    "gn:name":"Qiaogou",
    "gn:population":0,
    "gn:timezone":"Asia/Shanghai",
    "iso:country":"CN",
    "name:und_x_variant":[
        "\u6865\u6c9f"
    ],
    "wof:name":"Qiaogou",
    "wof:placetype":"locality"
},
  "geometry": {"coordinates":[107.10420999999999,34.84533],"type":"Point"}
}