{
  "type": "Feature",
  "properties": {
    "gn:admin1_code":"4.0",
    "gn:asciiname":"Liudayingcun",
    "gn:country_code":"CN",
    "gn:dem":38,
    "gn:feature_class":"P",
    "gn:feature_code":"PPL",
    "gn:name":"Liudayingcun",
    "gn:population":0,
    "gn:timezone":"Asia/Shanghai",
    "iso:country":"CN",
    "name:zho_x_preferred":[
        "\u5218\u5927\u8425\u6751"
    ],
    "wof:name":"Liudayingcun",
    "wof:placetype":"locality"
},
  "geometry": {"coordinates":[116.63648000000001,34.86047],"type":"Point"}
}