{
  "type": "Feature",
  "properties": {
    "gn:admin1_code":"30",
    "gn:asciiname":"Yueping",
    "gn:country_code":"CN",
    "gn:dem":318,
    "gn:feature_class":"P",
    "gn:feature_code":"PPL",
    "gn:name":"Yueping",
    "gn:population":0,
    "gn:timezone":"Asia/Shanghai",
    "iso:country":"CN",
    "name:zho_x_preferred":[
        "\u6708\u576a"
    ],
    "wof:name":"Yueping",
    "wof:placetype":"locality"
},
  "geometry": {"coordinates":[112.95413000000001,24.62519],"type":"Point"}
}