{
  "type": "Feature",
  "properties": {
    "gn:admin1_code":"3.0",
    "gn:asciiname":"Shiyuan",
    "gn:country_code":"CN",
    "gn:dem":152,
    "gn:feature_class":"P",
    "gn:feature_code":"PPL",
    "gn:name":"Shiyuan",
    "gn:population":0,
    "gn:timezone":"Asia/Shanghai",
    "iso:country":"CN",
    "name:fra_x_preferred":[
        "Shiyuan"
    ],
    "name:zho_x_preferred":[
        "\u77f3\u6e90"
    ],
    "wof:name":"Shiyuan",
    "wof:placetype":"locality"
},
  "geometry": {"coordinates":[113.904,27.8152],"type":"Point"}
}