{
  "type": "Feature",
  "properties": {
    "gn:admin1_code":"4.0",
    "gn:asciiname":"Linfeng",
    "gn:country_code":"CN",
    "gn:dem":7,
    "gn:feature_class":"P",
    "gn:feature_code":"PPL",
    "gn:name":"Linfeng",
    "gn:population":0,
    "gn:timezone":"Asia/Shanghai",
    "iso:country":"CN",
    "name:zho_x_preferred":[
        "\u90bb\u4e30"
    ],
    "wof:name":"Linfeng",
    "wof:placetype":"locality"
},
  "geometry": {"coordinates":[119.8244,32.17852],"type":"Point"}
}