{
  "type": "Feature",
  "properties": {
    "gn:admin1_code":"4.0",
    "gn:asciiname":"Tangdong",
    "gn:country_code":"CN",
    "gn:dem":3,
    "gn:feature_class":"P",
    "gn:feature_code":"PPL",
    "gn:name":"Tangdong",
    "gn:population":0,
    "gn:timezone":"Asia/Shanghai",
    "iso:country":"CN",
    "name:und_x_variant":[
        "Tangdongcun",
        "Tangdong",
        "\u5858\u4e1c"
    ],
    "name:zho_x_preferred":[
        "\u5858\u4e1c\u6751"
    ],
    "name:zho_x_variant":[
        "\u5510\u6d1e\u8857\u9053"
    ],
    "wof:name":"Tangdong",
    "wof:placetype":"locality"
},
  "geometry": {"coordinates":[121.04875,31.52777],"type":"Point"}
}