{
  "type": "Feature",
  "properties": {
    "gn:admin1_code":"9",
    "gn:asciiname":"Beigao",
    "gn:country_code":"CN",
    "gn:dem":54,
    "gn:feature_class":"P",
    "gn:feature_code":"PPL",
    "gn:name":"Beigao",
    "gn:population":0,
    "gn:timezone":"Asia/Shanghai",
    "iso:country":"CN",
    "name:zho_x_preferred":[
        "\u5317\u9ad8"
    ],
    "wof:name":"Beigao",
    "wof:placetype":"locality"
},
  "geometry": {"coordinates":[115.08548999999999,36.0164],"type":"Point"}
}