{
  "type": "Feature",
  "properties": {
    "gn:admin1_code":"10",
    "gn:asciiname":"Zhangsanying",
    "gn:cc2":"CN",
    "gn:country_code":"CN",
    "gn:dem":652,
    "gn:feature_class":"P",
    "gn:feature_code":"PPL",
    "gn:name":"Zhangsanying",
    "gn:population":0,
    "gn:timezone":"Asia/Shanghai",
    "iso:country":"CN",
    "name:und_x_variant":[
        "Chang-san-ying",
        "Zhangsanying"
    ],
    "wof:name":"Zhangsanying",
    "wof:placetype":"locality"
},
  "geometry": {"coordinates":[117.74694,41.56889],"type":"Point"}
}