{
  "type": "Feature",
  "properties": {
    "gn:admin1_code":"19.0",
    "gn:asciiname":"Tianqiao Liudui",
    "gn:country_code":"CN",
    "gn:dem":349,
    "gn:feature_class":"P",
    "gn:feature_code":"PPLF",
    "gn:name":"Tianqiao Liudui",
    "gn:population":0,
    "gn:timezone":"Asia/Shanghai",
    "iso:country":"CN",
    "name:und_x_variant":[
        "Tianqiao"
    ],
    "name:zho_x_preferred":[
        "\u5929\u6865\u516d\u961f"
    ],
    "name:zho_x_variant":[
        "\u5929\u6865"
    ],
    "wof:name":"Tianqiao Liudui",
    "wof:placetype":"locality"
},
  "geometry": {"coordinates":[124.736,42.3055],"type":"Point"}
}