{
  "type": "Feature",
  "properties": {
    "gn:admin1_code":"32.0",
    "gn:asciiname":"Yuhuangguan",
    "gn:country_code":"CN",
    "gn:dem":370,
    "gn:feature_class":"P",
    "gn:feature_code":"PPL",
    "gn:name":"Yuhuangguan",
    "gn:population":0,
    "gn:timezone":"Asia/Shanghai",
    "iso:country":"CN",
    "name:zho_x_preferred":[
        "\u7389\u7687\u89c2"
    ],
    "wof:name":"Yuhuangguan",
    "wof:placetype":"locality"
},
  "geometry": {"coordinates":[104.86842,29.58993],"type":"Point"}
}