{
  "type": "Feature",
  "properties": {
    "gn:admin1_code":"25.0",
    "gn:asciiname":"Shiduitoucun",
    "gn:country_code":"CN",
    "gn:dem":49,
    "gn:feature_class":"P",
    "gn:feature_code":"PPL",
    "gn:name":"Shiduitoucun",
    "gn:population":0,
    "gn:timezone":"Asia/Shanghai",
    "iso:country":"CN",
    "name:zho_x_preferred":[
        "\u77f3\u5bf9\u5934\u6751"
    ],
    "wof:name":"Shiduitoucun",
    "wof:placetype":"locality"
},
  "geometry": {"coordinates":[120.38435,37.4226],"type":"Point"}
}