{
  "type": "Feature",
  "properties": {
    "gn:admin1_code":"29.0",
    "gn:asciiname":"Yikede",
    "gn:country_code":"CN",
    "gn:dem":1792,
    "gn:feature_class":"P",
    "gn:feature_code":"PPL",
    "gn:name":"Yikede",
    "gn:population":0,
    "gn:timezone":"Asia/Shanghai",
    "iso:country":"CN",
    "name:zho_x_preferred":[
        "\u4e49\u53ef\u7684"
    ],
    "wof:name":"Yikede",
    "wof:placetype":"locality"
},
  "geometry": {"coordinates":[101.538,26.0912],"type":"Point"}
}