{
  "type": "Feature",
  "properties": {
    "gn:admin1_code":"30",
    "gn:asciiname":"Baiyin'e",
    "gn:country_code":"CN",
    "gn:dem":198,
    "gn:feature_class":"P",
    "gn:feature_code":"PPL",
    "gn:name":"Baiyin\u2019e",
    "gn:population":0,
    "gn:timezone":"Asia/Shanghai",
    "iso:country":"CN",
    "name:zho_x_preferred":[
        "\u767d\u94f6\u5384"
    ],
    "name:zho_x_variant":[
        "Baiyin\u2019e"
    ],
    "wof:name":"Baiyin'e",
    "wof:placetype":"locality"
},
  "geometry": {"coordinates":[111.61748,22.31038],"type":"Point"}
}