{
  "type": "Feature",
  "properties": {
    "gn:admin1_code":"12.0",
    "gn:asciiname":"Taoyuansi",
    "gn:country_code":"CN",
    "gn:dem":1127,
    "gn:feature_class":"P",
    "gn:feature_code":"PPL",
    "gn:name":"Taoyuansi",
    "gn:population":0,
    "gn:timezone":"Asia/Shanghai",
    "iso:country":"CN",
    "name:zho_x_preferred":[
        "\u6843\u56ed\u5bfa"
    ],
    "wof:name":"Taoyuansi",
    "wof:placetype":"locality"
},
  "geometry": {"coordinates":[109.81455,31.64009],"type":"Point"}
}