{
  "type": "Feature",
  "properties": {
    "gn:admin1_code":"12.0",
    "gn:asciiname":"Diaotaixia",
    "gn:country_code":"CN",
    "gn:dem":294,
    "gn:feature_class":"P",
    "gn:feature_code":"PPL",
    "gn:name":"Diaotaixia",
    "gn:population":0,
    "gn:timezone":"Asia/Shanghai",
    "iso:country":"CN",
    "name:zho_x_preferred":[
        "\u540a\u53f0\u4e0b"
    ],
    "wof:name":"Diaotaixia",
    "wof:placetype":"locality"
},
  "geometry": {"coordinates":[113.78464,29.43542],"type":"Point"}
}