{
  "type": "Feature",
  "properties": {
    "gn:admin1_code":"11.0",
    "gn:asciiname":"Zhentouyan",
    "gn:country_code":"CN",
    "gn:dem":105,
    "gn:feature_class":"P",
    "gn:feature_code":"PPL",
    "gn:name":"Zhentouyan",
    "gn:population":0,
    "gn:timezone":"Asia/Shanghai",
    "iso:country":"CN",
    "name:zho_x_preferred":[
        "\u6795\u5934\u5ca9"
    ],
    "wof:name":"Zhentouyan",
    "wof:placetype":"locality"
},
  "geometry": {"coordinates":[111.25659,28.84031],"type":"Point"}
}