{
  "type": "Feature",
  "properties": {
    "gn:admin1_code":"20",
    "gn:asciiname":"Wenquan",
    "gn:country_code":"CN",
    "gn:dem":1170,
    "gn:feature_class":"P",
    "gn:feature_code":"PPLA3",
    "gn:name":"Wenquan",
    "gn:population":0,
    "gn:timezone":"Asia/Shanghai",
    "iso:country":"CN",
    "name:und_x_variant":[
        "Khalin-Arshan",
        "Arshan",
        "Khalun-Arshan",
        "A-erh-shan-wen-ch\u2019\u00fcan",
        "Ven\u2019tsyuan\u2019",
        "A-erh-shan",
        "Wen-ch\u2019\u00fcan",
        "A-erh-shan-k\u2019uang-ch\u2019\u00fcan",
        "A-erh-shan-k\u2019uang-shui-y\u00fcan",
        "Arxan",
        "\u963f\u5c14\u5c71",
        "Wenquan Jiedao",
        "A\u2019ershan Shi",
        "Arxan Shi",
        "\u6e29\u6cc9\u8857\u9053",
        "\u963f\u5c14\u5c71\u5e02",
        "Wenquan"
    ],
    "name:zho_x_preferred":[
        "\u6e29\u6cc9"
    ],
    "wof:name":"Wenquan",
    "wof:placetype":"locality"
},
  "geometry": {"coordinates":[119.96666999999999,47.18333],"type":"Point"}
}