{
  "type": "Feature",
  "properties": {
    "gn:admin1_code":"24.0",
    "gn:asciiname":"Gaoduicun",
    "gn:country_code":"CN",
    "gn:dem":557,
    "gn:feature_class":"P",
    "gn:feature_code":"PPL",
    "gn:name":"Gaoduicun",
    "gn:population":0,
    "gn:timezone":"Asia/Shanghai",
    "iso:country":"CN",
    "name:zho_x_preferred":[
        "\u9ad8\u5806\u6751"
    ],
    "wof:name":"Gaoduicun",
    "wof:placetype":"locality"
},
  "geometry": {"coordinates":[110.53924000000001,35.20208],"type":"Point"}
}