{
  "type": "Feature",
  "properties": {
    "gn:admin1_code":"10",
    "gn:asciiname":"Xiaomazhuang",
    "gn:country_code":"CN",
    "gn:dem":34,
    "gn:feature_class":"P",
    "gn:feature_code":"PPL",
    "gn:name":"Xiaomazhuang",
    "gn:population":0,
    "gn:timezone":"Asia/Shanghai",
    "iso:country":"CN",
    "name:zho_x_preferred":[
        "\u5c0f\u9a6c\u5e84"
    ],
    "wof:name":"Xiaomazhuang",
    "wof:placetype":"locality"
},
  "geometry": {"coordinates":[115.62278999999999,36.89408],"type":"Point"}
}