{
  "type": "Feature",
  "properties": {
    "gn:admin1_code":"29.0",
    "gn:asciiname":"Shangmanggang",
    "gn:country_code":"CN",
    "gn:dem":956,
    "gn:feature_class":"P",
    "gn:feature_code":"PPL",
    "gn:name":"Shangmanggang",
    "gn:population":0,
    "gn:timezone":"Asia/Shanghai",
    "iso:country":"CN",
    "name:zho_x_preferred":[
        "\u4e0a\u8292\u5c97"
    ],
    "wof:name":"Shangmanggang",
    "wof:placetype":"locality"
},
  "geometry": {"coordinates":[98.8562,25.4676],"type":"Point"}
}