{
  "type": "Feature",
  "properties": {
    "gn:admin1_code":"30",
    "gn:asciiname":"Fuzaitang",
    "gn:country_code":"CN",
    "gn:dem":338,
    "gn:feature_class":"P",
    "gn:feature_code":"PPL",
    "gn:name":"Fuzaitang",
    "gn:population":0,
    "gn:timezone":"Asia/Shanghai",
    "iso:country":"CN",
    "name:zho_x_preferred":[
        "\u5bcc\u54c9\u5802"
    ],
    "wof:name":"Fuzaitang",
    "wof:placetype":"locality"
},
  "geometry": {"coordinates":[116.77131,24.44872],"type":"Point"}
}