{
  "type": "Feature",
  "properties": {
    "gn:admin1_code":"3.0",
    "gn:asciiname":"Houxi Hejia",
    "gn:country_code":"CN",
    "gn:dem":25,
    "gn:feature_class":"P",
    "gn:feature_code":"PPL",
    "gn:name":"Houxi Hejia",
    "gn:population":0,
    "gn:timezone":"Asia/Shanghai",
    "iso:country":"CN",
    "name:und_x_variant":[
        "\u540e\u6eaa\u4f55\u5bb6"
    ],
    "wof:name":"Houxi Hejia",
    "wof:placetype":"locality"
},
  "geometry": {"coordinates":[115.81572,28.72905],"type":"Point"}
}