{
  "type": "Feature",
  "properties": {
    "gn:admin1_code":"3.0",
    "gn:asciiname":"Yanzhou",
    "gn:country_code":"CN",
    "gn:dem":376,
    "gn:feature_class":"P",
    "gn:feature_code":"PPL",
    "gn:name":"Yanzhou",
    "gn:population":0,
    "gn:timezone":"Asia/Shanghai",
    "iso:country":"CN",
    "name:und_x_variant":[
        "\u70df\u6d32"
    ],
    "wof:name":"Yanzhou",
    "wof:placetype":"locality"
},
  "geometry": {"coordinates":[114.4272,27.6502],"type":"Point"}
}