{
  "type": "Feature",
  "properties": {
    "gn:admin1_code":"18.0",
    "gn:asciiname":"Yanana",
    "gn:country_code":"CN",
    "gn:dem":536,
    "gn:feature_class":"P",
    "gn:feature_code":"PPL",
    "gn:name":"Yanana",
    "gn:population":0,
    "gn:timezone":"Asia/Shanghai",
    "iso:country":"CN",
    "name:zho_x_preferred":[
        "\u4e9a\u90a3\u7eb3"
    ],
    "wof:name":"Yanana",
    "wof:placetype":"locality"
},
  "geometry": {"coordinates":[109.026,27.055],"type":"Point"}
}