{
  "type": "Feature",
  "properties": {
    "gn:admin1_code":"1.0",
    "gn:asciiname":"Xiniuzhuangcun",
    "gn:country_code":"CN",
    "gn:dem":37,
    "gn:feature_class":"P",
    "gn:feature_code":"PPL",
    "gn:name":"Xiniuzhuangcun",
    "gn:population":0,
    "gn:timezone":"Asia/Shanghai",
    "iso:country":"CN",
    "name:zho_x_preferred":[
        "\u897f\u725b\u5e84\u6751"
    ],
    "wof:name":"Xiniuzhuangcun",
    "wof:placetype":"locality"
},
  "geometry": {"coordinates":[115.69146000000001,33.44025],"type":"Point"}
}