{
  "type": "Feature",
  "properties": {
    "gn:admin1_code":"4.0",
    "gn:asciiname":"Xiangdun",
    "gn:country_code":"CN",
    "gn:dem":18,
    "gn:feature_class":"P",
    "gn:feature_code":"PPL",
    "gn:name":"Xiangdun",
    "gn:population":0,
    "gn:timezone":"Asia/Shanghai",
    "iso:country":"CN",
    "name:zho_x_preferred":[
        "\u54cd\u58a9"
    ],
    "wof:name":"Xiangdun",
    "wof:placetype":"locality"
},
  "geometry": {"coordinates":[118.9847,32.97877],"type":"Point"}
}