{
  "type": "Feature",
  "properties": {
    "gn:admin1_code":"8.0",
    "gn:asciiname":"Mingshancun",
    "gn:country_code":"CN",
    "gn:dem":176,
    "gn:feature_class":"P",
    "gn:feature_code":"PPL",
    "gn:name":"Mingshancun",
    "gn:population":0,
    "gn:timezone":"Asia/Shanghai",
    "iso:country":"CN",
    "name:zho_x_preferred":[
        "\u660e\u5c71\u6751"
    ],
    "wof:name":"Mingshancun",
    "wof:placetype":"locality"
},
  "geometry": {"coordinates":[131.54443999999998,46.05589000000001],"type":"Point"}
}