{
  "type": "Feature",
  "properties": {
    "gn:admin1_code":"32.0",
    "gn:asciiname":"Donglang",
    "gn:country_code":"CN",
    "gn:dem":2815,
    "gn:feature_class":"P",
    "gn:feature_code":"PPL",
    "gn:name":"Donglang",
    "gn:population":0,
    "gn:timezone":"Asia/Shanghai",
    "iso:country":"CN",
    "name:zho_x_preferred":[
        "\u4e1c\u6717"
    ],
    "wof:name":"Donglang",
    "wof:placetype":"locality"
},
  "geometry": {"coordinates":[100.67022,28.85064],"type":"Point"}
}