{
  "type": "Feature",
  "properties": {
    "gn:admin1_code":"26.0",
    "gn:asciiname":"Shangyahulu",
    "gn:country_code":"CN",
    "gn:dem":1337,
    "gn:feature_class":"P",
    "gn:feature_code":"PPL",
    "gn:name":"Shangyahulu",
    "gn:population":0,
    "gn:timezone":"Asia/Shanghai",
    "iso:country":"CN",
    "name:zho_x_preferred":[
        "\u4e0a\u9e2d\u846b\u82a6"
    ],
    "wof:name":"Shangyahulu",
    "wof:placetype":"locality"
},
  "geometry": {"coordinates":[109.18652,35.24336],"type":"Point"}
}