{
  "type": "Feature",
  "properties": {
    "gn:admin1_code":"10.0",
    "gn:asciiname":"Beiwangtuan",
    "gn:country_code":"CN",
    "gn:dem":42,
    "gn:feature_class":"P",
    "gn:feature_code":"PPL",
    "gn:name":"Beiwangtuan",
    "gn:population":0,
    "gn:timezone":"Asia/Shanghai",
    "iso:country":"CN",
    "name:zho_x_preferred":[
        "\u5317\u738b\u7583"
    ],
    "wof:name":"Beiwangtuan",
    "wof:placetype":"locality"
},
  "geometry": {"coordinates":[115.205,38.6425],"type":"Point"}
}