{
  "type": "Feature",
  "properties": {
    "gn:admin1_code":"2.0",
    "gn:asciiname":"Xinqiao",
    "gn:country_code":"CN",
    "gn:dem":201,
    "gn:feature_class":"P",
    "gn:feature_code":"PPL",
    "gn:name":"Xinqiao",
    "gn:population":0,
    "gn:timezone":"Asia/Shanghai",
    "iso:country":"CN",
    "name:ceb_x_preferred":[
        "Xinqiao"
    ],
    "name:deu_x_preferred":[
        "Xinqiao"
    ],
    "name:swe_x_preferred":[
        "Xinqiao"
    ],
    "name:zho_x_preferred":[
        "\u65b0\u6865"
    ],
    "wof:name":"Xinqiao",
    "wof:placetype":"locality"
},
  "geometry": {"coordinates":[119.03009,29.3509],"type":"Point"}
}