{
  "type": "Feature",
  "properties": {
    "gn:admin1_code":"8.0",
    "gn:asciiname":"Honghugou",
    "gn:country_code":"CN",
    "gn:dem":191,
    "gn:feature_class":"P",
    "gn:feature_code":"PPL",
    "gn:name":"Honghugou",
    "gn:population":0,
    "gn:timezone":"Asia/Shanghai",
    "iso:country":"CN",
    "name:zho_x_preferred":[
        "\u6d2a\u6237\u6c9f"
    ],
    "wof:name":"Honghugou",
    "wof:placetype":"locality"
},
  "geometry": {"coordinates":[127.35096,46.77634000000001],"type":"Point"}
}