{
  "type": "Feature",
  "properties": {
    "gn:admin1_code":"20.0",
    "gn:asciiname":"Taobuliang",
    "gn:country_code":"CN",
    "gn:dem":1356,
    "gn:feature_class":"P",
    "gn:feature_code":"PPL",
    "gn:name":"Taobuliang",
    "gn:population":0,
    "gn:timezone":"Asia/Shanghai",
    "iso:country":"CN",
    "name:und_x_variant":[
        "\u6843\u535c\u6881"
    ],
    "wof:name":"Taobuliang",
    "wof:placetype":"locality"
},
  "geometry": {"coordinates":[111.59654999999999,39.64766],"type":"Point"}
}