{
  "type": "Feature",
  "properties": {
    "gn:admin1_code":"18.0",
    "gn:asciiname":"Shangtangmao",
    "gn:country_code":"CN",
    "gn:dem":883,
    "gn:feature_class":"P",
    "gn:feature_code":"PPL",
    "gn:name":"Shangtangmao",
    "gn:population":0,
    "gn:timezone":"Asia/Shanghai",
    "iso:country":"CN",
    "name:zho_x_preferred":[
        "\u4e0a\u5858\u8302"
    ],
    "wof:name":"Shangtangmao",
    "wof:placetype":"locality"
},
  "geometry": {"coordinates":[107.40000000000001,25.7463],"type":"Point"}
}