{
  "type": "Feature",
  "properties": {
    "gn:admin1_code":"10",
    "gn:asciiname":"Dengchang",
    "gn:country_code":"CN",
    "gn:dem":1303,
    "gn:feature_class":"P",
    "gn:feature_code":"PPL",
    "gn:name":"Dengchang",
    "gn:population":0,
    "gn:timezone":"Asia/Shanghai",
    "iso:country":"CN",
    "name:zho_x_preferred":[
        "\u9093\u5382"
    ],
    "wof:name":"Dengchang",
    "wof:placetype":"locality"
},
  "geometry": {"coordinates":[116.09309,41.28395],"type":"Point"}
}