{
  "type": "Feature",
  "properties": {
    "gn:admin1_code":"16",
    "gn:asciiname":"Xingujie",
    "gn:country_code":"CN",
    "gn:dem":931,
    "gn:feature_class":"P",
    "gn:feature_code":"PPL",
    "gn:name":"Xingujie",
    "gn:population":0,
    "gn:timezone":"Asia/Shanghai",
    "iso:country":"CN",
    "name:zho_x_preferred":[
        "\u65b0\u59d1\u754c"
    ],
    "wof:name":"Xingujie",
    "wof:placetype":"locality"
},
  "geometry": {"coordinates":[110.502,25.9955],"type":"Point"}
}