{
  "type": "Feature",
  "properties": {
    "gn:admin1_code":"25.0",
    "gn:asciiname":"Xinshangzhuang",
    "gn:country_code":"CN",
    "gn:dem":49,
    "gn:feature_class":"P",
    "gn:feature_code":"PPL",
    "gn:name":"Xinshangzhuang",
    "gn:population":0,
    "gn:timezone":"Asia/Shanghai",
    "iso:country":"CN",
    "name:zho_x_preferred":[
        "\u65b0\u4e0a\u5e84"
    ],
    "wof:name":"Xinshangzhuang",
    "wof:placetype":"locality"
},
  "geometry": {"coordinates":[121.94031,37.19577],"type":"Point"}
}