{
  "type": "Feature",
  "properties": {
    "gn:admin1_code":"5.0",
    "gn:asciiname":"Qingluo",
    "gn:country_code":"CN",
    "gn:dem":646,
    "gn:feature_class":"P",
    "gn:feature_code":"PPL",
    "gn:name":"Qingluo",
    "gn:population":0,
    "gn:timezone":"Asia/Shanghai",
    "iso:country":"CN",
    "name:und_x_variant":[
        "\u6e05\u841d"
    ],
    "wof:name":"Qingluo",
    "wof:placetype":"locality"
},
  "geometry": {"coordinates":[129.47982999999999,42.59124],"type":"Point"}
}