{
  "type": "Feature",
  "properties": {
    "gn:admin1_code":"9.0",
    "gn:asciiname":"Zuoli",
    "gn:country_code":"CN",
    "gn:dem":119,
    "gn:feature_class":"P",
    "gn:feature_code":"PPL",
    "gn:name":"Zuoli",
    "gn:population":0,
    "gn:timezone":"Asia/Shanghai",
    "iso:country":"CN",
    "name:zho_x_preferred":[
        "\u5de6\u5229"
    ],
    "wof:name":"Zuoli",
    "wof:placetype":"locality"
},
  "geometry": {"coordinates":[114.01115,32.02774],"type":"Point"}
}