{
  "type": "Feature",
  "properties": {
    "gn:admin1_code":"7.0",
    "gn:asciiname":"Xinzheng",
    "gn:country_code":"CN",
    "gn:dem":69,
    "gn:feature_class":"P",
    "gn:feature_code":"PPL",
    "gn:name":"Xinzheng",
    "gn:population":0,
    "gn:timezone":"Asia/Shanghai",
    "iso:country":"CN",
    "name:zho_x_preferred":[
        "\u65b0\u90d1"
    ],
    "wof:name":"Xinzheng",
    "wof:placetype":"locality"
},
  "geometry": {"coordinates":[118.77970999999999,25.43407],"type":"Point"}
}