{
  "type": "Feature",
  "properties": {
    "gn:admin1_code":"19.0",
    "gn:asciiname":"Qianchangzicun",
    "gn:country_code":"CN",
    "gn:dem":174,
    "gn:feature_class":"P",
    "gn:feature_code":"PPL",
    "gn:name":"Qianchangzicun",
    "gn:population":0,
    "gn:timezone":"Asia/Shanghai",
    "iso:country":"CN",
    "name:zho_x_preferred":[
        "\u524d\u5382\u5b50\u6751"
    ],
    "wof:name":"Qianchangzicun",
    "wof:placetype":"locality"
},
  "geometry": {"coordinates":[123.83199999999999,41.3843],"type":"Point"}
}