{
  "type": "Feature",
  "properties": {
    "gn:admin1_code":"11.0",
    "gn:asciiname":"Jiyudong",
    "gn:country_code":"CN",
    "gn:dem":437,
    "gn:feature_class":"P",
    "gn:feature_code":"PPL",
    "gn:name":"Jiyudong",
    "gn:population":0,
    "gn:timezone":"Asia/Shanghai",
    "iso:country":"CN",
    "name:zho_x_preferred":[
        "\u9cab\u9c7c\u6d1e"
    ],
    "wof:name":"Jiyudong",
    "wof:placetype":"locality"
},
  "geometry": {"coordinates":[111.59696,28.16967],"type":"Point"}
}