{
  "type": "Feature",
  "properties": {
    "gn:admin1_code":"8.0",
    "gn:asciiname":"Fengshoucun",
    "gn:country_code":"CN",
    "gn:dem":119,
    "gn:feature_class":"P",
    "gn:feature_code":"PPL",
    "gn:name":"Fengshoucun",
    "gn:population":0,
    "gn:timezone":"Asia/Shanghai",
    "iso:country":"CN",
    "name:zho_x_preferred":[
        "\u4e30\u6536\u6751"
    ],
    "wof:name":"Fengshoucun",
    "wof:placetype":"locality"
},
  "geometry": {"coordinates":[128.43034,46.02507],"type":"Point"}
}