{
  "type": "Feature",
  "properties": {
    "gn:admin1_code":"1.0",
    "gn:asciiname":"Shuangchongcun",
    "gn:country_code":"CN",
    "gn:dem":44,
    "gn:feature_class":"P",
    "gn:feature_code":"PPL",
    "gn:name":"Shuangchongcun",
    "gn:population":0,
    "gn:timezone":"Asia/Shanghai",
    "iso:country":"CN",
    "name:zho_x_preferred":[
        "\u53cc\u51b2\u6751"
    ],
    "wof:name":"Shuangchongcun",
    "wof:placetype":"locality"
},
  "geometry": {"coordinates":[117.99126,30.66766],"type":"Point"}
}