{
  "type": "Feature",
  "properties": {
    "gn:admin1_code":"26.0",
    "gn:asciiname":"Ye'erzhuang",
    "gn:country_code":"CN",
    "gn:dem":1403,
    "gn:feature_class":"P",
    "gn:feature_code":"PPL",
    "gn:name":"Ye\u2019erzhuang",
    "gn:population":0,
    "gn:timezone":"Asia/Shanghai",
    "iso:country":"CN",
    "name:und_x_variant":[
        "Ye\u2019erzhuang"
    ],
    "name:zho_x_preferred":[
        "\u53f6\u513f\u5e84"
    ],
    "wof:name":"Ye'erzhuang",
    "wof:placetype":"locality"
},
  "geometry": {"coordinates":[107.38384000000001,37.47341],"type":"Point"}
}