{
  "type": "Feature",
  "properties": {
    "gn:admin1_code":"13.0",
    "gn:asciiname":"K'u-lan-ssu-k'u-erh-sa-k'o",
    "gn:country_code":"CN",
    "gn:dem":851,
    "gn:feature_class":"P",
    "gn:feature_code":"PPL",
    "gn:name":"K\u2019u-lan-ssu-k\u2019u-erh-sa-k\u2019o",
    "gn:population":0,
    "gn:timezone":"Asia/Urumqi",
    "iso:country":"CN",
    "wof:name":"K'u-lan-ssu-k'u-erh-sa-k'o",
    "wof:placetype":"locality"
},
  "geometry": {"coordinates":[87.64639,40.70222],"type":"Point"}
}