{
  "type": "Feature",
  "properties": {
    "gn:admin1_code":"15.0",
    "gn:asciiname":"Baitupo",
    "gn:country_code":"CN",
    "gn:dem":2405,
    "gn:feature_class":"P",
    "gn:feature_code":"PPL",
    "gn:name":"Baitupo",
    "gn:population":0,
    "gn:timezone":"Asia/Shanghai",
    "iso:country":"CN",
    "name:und_x_variant":[
        "\u767d\u571f\u5761"
    ],
    "wof:name":"Baitupo",
    "wof:placetype":"locality"
},
  "geometry": {"coordinates":[104.08172,34.39683],"type":"Point"}
}