{
  "type": "Feature",
  "properties": {
    "gn:admin1_code":"8.0",
    "gn:asciiname":"Mahuitun",
    "gn:country_code":"CN",
    "gn:dem":130,
    "gn:feature_class":"P",
    "gn:feature_code":"PPL",
    "gn:name":"Mahuitun",
    "gn:population":0,
    "gn:timezone":"Asia/Shanghai",
    "iso:country":"CN",
    "name:zho_x_preferred":[
        "\u9a6c\u56de\u5c6f"
    ],
    "wof:name":"Mahuitun",
    "wof:placetype":"locality"
},
  "geometry": {"coordinates":[126.9282,45.69844000000001],"type":"Point"}
}