{
  "type": "Feature",
  "properties": {
    "gn:admin1_code":"29.0",
    "gn:asciiname":"Baichang",
    "gn:country_code":"CN",
    "gn:dem":2020,
    "gn:feature_class":"P",
    "gn:feature_code":"PPL",
    "gn:name":"Baichang",
    "gn:population":0,
    "gn:timezone":"Asia/Shanghai",
    "iso:country":"CN",
    "name:zho_x_preferred":[
        "\u767e\u957f"
    ],
    "wof:name":"Baichang",
    "wof:placetype":"locality"
},
  "geometry": {"coordinates":[100.652,25.3713],"type":"Point"}
}