{
  "type": "Feature",
  "properties": {
    "gn:admin1_code":"9.0",
    "gn:asciiname":"Dapengzhuang",
    "gn:country_code":"CN",
    "gn:dem":44,
    "gn:feature_class":"P",
    "gn:feature_code":"PPL",
    "gn:name":"Dapengzhuang",
    "gn:population":0,
    "gn:timezone":"Asia/Shanghai",
    "iso:country":"CN",
    "name:zho_x_preferred":[
        "\u5927\u5f6d\u5e84"
    ],
    "wof:name":"Dapengzhuang",
    "wof:placetype":"locality"
},
  "geometry": {"coordinates":[114.95341000000001,32.59325],"type":"Point"}
}