{
  "type": "Feature",
  "properties": {
    "gn:admin1_code":"12.0",
    "gn:asciiname":"Chajiakou",
    "gn:country_code":"CN",
    "gn:dem":34,
    "gn:feature_class":"P",
    "gn:feature_code":"PPL",
    "gn:name":"Chajiakou",
    "gn:population":0,
    "gn:timezone":"Asia/Shanghai",
    "iso:country":"CN",
    "name:zho_x_preferred":[
        "\u8336\u5bb6\u53e3"
    ],
    "wof:name":"Chajiakou",
    "wof:placetype":"locality"
},
  "geometry": {"coordinates":[112.93015,30.67587],"type":"Point"}
}