{
  "type": "Feature",
  "properties": {
    "gn:admin1_code":"11.0",
    "gn:asciiname":"Shenwo",
    "gn:country_code":"CN",
    "gn:dem":858,
    "gn:feature_class":"P",
    "gn:feature_code":"PPL",
    "gn:name":"Shenwo",
    "gn:population":0,
    "gn:timezone":"Asia/Shanghai",
    "iso:country":"CN",
    "name:zho_x_preferred":[
        "\u6df1\u7a9d"
    ],
    "wof:name":"Shenwo",
    "wof:placetype":"locality"
},
  "geometry": {"coordinates":[113.49621,25.389],"type":"Point"}
}