{
  "type": "Feature",
  "properties": {
    "gn:admin1_code":"7",
    "gn:asciiname":"Luxia",
    "gn:country_code":"CN",
    "gn:dem":94,
    "gn:feature_class":"P",
    "gn:feature_code":"PPLA4",
    "gn:name":"Luxia",
    "gn:population":0,
    "gn:timezone":"Asia/Shanghai",
    "iso:country":"CN",
    "name:und_x_variant":[
        "\u7089\u4e0b",
        "Luxia Zhen",
        "\u7089\u4e0b\u9547"
    ],
    "wof:name":"Luxia",
    "wof:placetype":"locality"
},
  "geometry": {"coordinates":[118.29611,26.49004],"type":"Point"}
}