{
  "type": "Feature",
  "properties": {
    "gn:admin1_code":"1.0",
    "gn:asciiname":"Qiuchengcun",
    "gn:country_code":"CN",
    "gn:dem":8,
    "gn:feature_class":"P",
    "gn:feature_code":"PPL",
    "gn:name":"Qiuchengcun",
    "gn:population":0,
    "gn:timezone":"Asia/Shanghai",
    "iso:country":"CN",
    "name:zho_x_preferred":[
        "\u5775\u57ce\u6751"
    ],
    "wof:name":"Qiuchengcun",
    "wof:placetype":"locality"
},
  "geometry": {"coordinates":[117.75873,31.1449],"type":"Point"}
}