{
  "type": "Feature",
  "properties": {
    "gn:admin1_code":"29.0",
    "gn:asciiname":"Liangzitou",
    "gn:country_code":"CN",
    "gn:dem":1674,
    "gn:feature_class":"P",
    "gn:feature_code":"PPL",
    "gn:name":"Liangzitou",
    "gn:population":0,
    "gn:timezone":"Asia/Shanghai",
    "iso:country":"CN",
    "name:zho_x_preferred":[
        "\u6881\u5b50\u5934"
    ],
    "wof:name":"Liangzitou",
    "wof:placetype":"locality"
},
  "geometry": {"coordinates":[100.18899999999999,24.2542],"type":"Point"}
}