{
  "type": "Feature",
  "properties": {
    "gn:admin1_code":"18",
    "gn:asciiname":"Laoyaying",
    "gn:country_code":"CN",
    "gn:dem":2364,
    "gn:feature_class":"P",
    "gn:feature_code":"PPL",
    "gn:name":"Laoyaying",
    "gn:population":0,
    "gn:timezone":"Asia/Shanghai",
    "iso:country":"CN",
    "name:zho_x_preferred":[
        "\u8001\u9e26\u8425"
    ],
    "wof:name":"Laoyaying",
    "wof:placetype":"locality"
},
  "geometry": {"coordinates":[103.783,26.8073],"type":"Point"}
}