{
  "type": "Feature",
  "properties": {
    "gn:admin1_code":"05",
    "gn:asciiname":"Beigangcanchang Erfenchang",
    "gn:country_code":"CN",
    "gn:dem":867,
    "gn:feature_class":"P",
    "gn:feature_code":"PPLF",
    "gn:name":"Beigangcanchang Erfenchang",
    "gn:population":0,
    "gn:timezone":"Asia/Shanghai",
    "iso:country":"CN",
    "name:und_x_variant":[
        "\u5317\u5c97\u53c2\u573a\u4e8c\u5206\u573a"
    ],
    "wof:name":"Beigangcanchang Erfenchang",
    "wof:placetype":"locality"
},
  "geometry": {"coordinates":[127.41777,41.61499],"type":"Point"}
}