{
  "type": "Feature",
  "properties": {
    "gn:admin1_code":"30",
    "gn:asciiname":"Nantou",
    "gn:country_code":"CN",
    "gn:dem":9,
    "gn:feature_class":"P",
    "gn:feature_code":"PPLA4",
    "gn:name":"Nantou",
    "gn:population":0,
    "gn:timezone":"Asia/Shanghai",
    "iso:country":"CN",
    "name:und_x_variant":[
        "Pao-an",
        "Namtau",
        "Ta-hsin-chieh",
        "Namtow",
        "Nantou",
        "Nantou Jiedao",
        "\u5357\u5934\u8857\u9053"
    ],
    "wof:name":"Nantou",
    "wof:placetype":"locality"
},
  "geometry": {"coordinates":[113.91564,22.53557],"type":"Point"}
}