{
  "type": "Feature",
  "properties": {
    "gn:admin1_code":"9.0",
    "gn:asciiname":"Houluying",
    "gn:country_code":"CN",
    "gn:dem":67,
    "gn:feature_class":"P",
    "gn:feature_code":"PPL",
    "gn:name":"Houluying",
    "gn:population":0,
    "gn:timezone":"Asia/Shanghai",
    "iso:country":"CN",
    "name:zho_x_preferred":[
        "\u540e\u9646\u8425"
    ],
    "wof:name":"Houluying",
    "wof:placetype":"locality"
},
  "geometry": {"coordinates":[114.52097000000001,34.47458],"type":"Point"}
}