{
  "type": "Feature",
  "properties": {
    "gn:admin1_code":"4.0",
    "gn:asciiname":"Foxinxu",
    "gn:country_code":"CN",
    "gn:dem":8,
    "gn:feature_class":"P",
    "gn:feature_code":"PPL",
    "gn:name":"Foxinxu",
    "gn:population":0,
    "gn:timezone":"Asia/Shanghai",
    "iso:country":"CN",
    "name:zho_x_preferred":[
        "\u4f5b\u65b0\u5729"
    ],
    "wof:name":"Foxinxu",
    "wof:placetype":"locality"
},
  "geometry": {"coordinates":[120.52256,31.99863],"type":"Point"}
}