{
  "type": "Feature",
  "properties": {
    "gn:admin1_code":"9.0",
    "gn:asciiname":"Jinshui'ao",
    "gn:country_code":"CN",
    "gn:dem":1263,
    "gn:feature_class":"P",
    "gn:feature_code":"PPL",
    "gn:name":"Jinshui\u2019ao",
    "gn:population":0,
    "gn:timezone":"Asia/Shanghai",
    "iso:country":"CN",
    "name:und_x_variant":[
        "Jinshui\u2019ao"
    ],
    "name:zho_x_preferred":[
        "\u91d1\u6c34\u51f9"
    ],
    "wof:name":"Jinshui'ao",
    "wof:placetype":"locality"
},
  "geometry": {"coordinates":[111.21464,34.43697],"type":"Point"}
}