{
  "type": "Feature",
  "properties": {
    "gn:admin1_code":"8.0",
    "gn:asciiname":"Xinfeng Nongchang",
    "gn:country_code":"CN",
    "gn:dem":309,
    "gn:feature_class":"P",
    "gn:feature_code":"PPLF",
    "gn:name":"Xinfeng Nongchang",
    "gn:population":0,
    "gn:timezone":"Asia/Shanghai",
    "iso:country":"CN",
    "name:zho_x_preferred":[
        "\u65b0\u4e30\u519c\u573a"
    ],
    "wof:name":"Xinfeng Nongchang",
    "wof:placetype":"locality"
},
  "geometry": {"coordinates":[129.56583000000001,48.31166],"type":"Point"}
}