{
  "type": "Feature",
  "properties": {
    "gn:admin1_code":"23.0",
    "gn:asciiname":"Yemaodun",
    "gn:country_code":"CN",
    "gn:dem":3,
    "gn:feature_class":"P",
    "gn:feature_code":"PPL",
    "gn:name":"Yemaodun",
    "gn:population":0,
    "gn:timezone":"Asia/Shanghai",
    "iso:country":"CN",
    "name:zho_x_preferred":[
        "Yemaodun"
    ],
    "name:zho_x_variant":[
        "\u91ce\u732b\u58a9"
    ],
    "wof:name":"Yemaodun",
    "wof:placetype":"locality"
},
  "geometry": {"coordinates":[121.42794000000001,31.33587],"type":"Point"}
}