{
  "type": "Feature",
  "properties": {
    "iso:country":"CN",
    "qs:name":"\u8d3a\u7e23",
    "qs:name_adm0":"\u4e2d\u570b",
    "qs:name_adm1":"\u5e7f\u897f\u7701",
    "qs:photos":11,
    "qs:photos_1k":2,
    "qs:photos_9k":1,
    "qs:photos_9r":2,
    "qs:photos_all":72,
    "qs:photos_sr":1,
    "qs:placetype":"LocalAdmin",
    "qs:pop_sr":"0",
    "wof:name":"\u8d3a\u7e23",
    "wof:placetype":"localadmin"
},
  "geometry": {"coordinates":[111.522903,24.411202],"type":"Point"}
}