{
  "type": "Feature",
  "properties": {
    "gn:admin1_code":"23.0",
    "gn:asciiname":"Laozhaijiao",
    "gn:country_code":"CN",
    "gn:dem":8,
    "gn:feature_class":"P",
    "gn:feature_code":"PPL",
    "gn:name":"Laozhaijiao",
    "gn:population":0,
    "gn:timezone":"Asia/Shanghai",
    "iso:country":"CN",
    "name:zho_x_preferred":[
        "Laozhaijiao"
    ],
    "name:zho_x_variant":[
        "\u8001\u5b85\u89d2"
    ],
    "wof:name":"Laozhaijiao",
    "wof:placetype":"locality"
},
  "geometry": {"coordinates":[121.34819,31.1538],"type":"Point"}
}