{
  "type": "Feature",
  "properties": {
    "gn:admin1_code":"4.0",
    "gn:asciiname":"Shanxucun",
    "gn:country_code":"CN",
    "gn:dem":42,
    "gn:feature_class":"P",
    "gn:feature_code":"PPL",
    "gn:name":"Shanxucun",
    "gn:population":0,
    "gn:timezone":"Asia/Shanghai",
    "iso:country":"CN",
    "name:zho_x_preferred":[
        "\u5c71\u5f90\u6751"
    ],
    "wof:name":"Shanxucun",
    "wof:placetype":"locality"
},
  "geometry": {"coordinates":[118.25830000000001,34.24707],"type":"Point"}
}