{
  "type": "Feature",
  "properties": {
    "gn:admin1_code":"30.0",
    "gn:asciiname":"Jinfeng",
    "gn:country_code":"CN",
    "gn:dem":29,
    "gn:feature_class":"P",
    "gn:feature_code":"PPL",
    "gn:name":"Jinfeng",
    "gn:population":0,
    "gn:timezone":"Asia/Urumqi",
    "iso:country":"CN",
    "name:zho_x_preferred":[
        "\u9526\u4e30"
    ],
    "wof:name":"Jinfeng",
    "wof:placetype":"locality"
},
  "geometry": {"coordinates":[110.42068,20.57024],"type":"Point"}
}