{
  "type": "Feature",
  "properties": {
    "gn:admin1_code":"3.0",
    "gn:asciiname":"Kongmucun",
    "gn:country_code":"CN",
    "gn:dem":373,
    "gn:feature_class":"P",
    "gn:feature_code":"PPL",
    "gn:name":"Kongmucun",
    "gn:population":0,
    "gn:timezone":"Asia/Shanghai",
    "iso:country":"CN",
    "name:und_x_variant":[
        "\u5b54\u76ee\u6751"
    ],
    "wof:name":"Kongmucun",
    "wof:placetype":"locality"
},
  "geometry": {"coordinates":[115.14536,26.45602],"type":"Point"}
}