{
  "type": "Feature",
  "properties": {
    "gn:admin1_code":"24.0",
    "gn:asciiname":"Puchi",
    "gn:country_code":"CN",
    "gn:dem":998,
    "gn:feature_class":"P",
    "gn:feature_code":"PPL",
    "gn:name":"Puchi",
    "gn:population":0,
    "gn:timezone":"Asia/Shanghai",
    "iso:country":"CN",
    "name:zho_x_preferred":[
        "\u84b2\u6c60"
    ],
    "wof:name":"Puchi",
    "wof:placetype":"locality"
},
  "geometry": {"coordinates":[112.86715,37.50691],"type":"Point"}
}