{
  "type": "Feature",
  "properties": {
    "gn:admin1_code":"10",
    "gn:asciiname":"Xidi",
    "gn:country_code":"CN",
    "gn:dem":439,
    "gn:feature_class":"P",
    "gn:feature_code":"PPL",
    "gn:name":"Xidi",
    "gn:population":0,
    "gn:timezone":"Asia/Shanghai",
    "iso:country":"CN",
    "name:zho_x_preferred":[
        "\u897f\u5730"
    ],
    "wof:name":"Xidi",
    "wof:placetype":"locality"
},
  "geometry": {"coordinates":[118.01093,41.15093],"type":"Point"}
}