{
  "type": "Feature",
  "properties": {
    "gn:admin1_code":"12.0",
    "gn:asciiname":"Wangjiagang",
    "gn:country_code":"CN",
    "gn:dem":36,
    "gn:feature_class":"P",
    "gn:feature_code":"PPL",
    "gn:name":"Wangjiagang",
    "gn:population":0,
    "gn:timezone":"Asia/Shanghai",
    "iso:country":"CN",
    "name:zho_x_preferred":[
        "Wangjiagang"
    ],
    "name:zho_x_variant":[
        "\u738b\u5bb6\u5c97"
    ],
    "wof:name":"Wangjiagang",
    "wof:placetype":"locality"
},
  "geometry": {"coordinates":[115.04073,30.55173],"type":"Point"}
}