{
  "type": "Feature",
  "properties": {
    "gn:admin1_code":"12.0",
    "gn:asciiname":"Hejiadawu",
    "gn:country_code":"CN",
    "gn:dem":43,
    "gn:feature_class":"P",
    "gn:feature_code":"PPL",
    "gn:name":"Hejiadawu",
    "gn:population":0,
    "gn:timezone":"Asia/Shanghai",
    "iso:country":"CN",
    "name:zho_x_preferred":[
        "\u4f55\u5bb6\u5927\u5c4b"
    ],
    "wof:name":"Hejiadawu",
    "wof:placetype":"locality"
},
  "geometry": {"coordinates":[113.63795,29.72835],"type":"Point"}
}