{
  "type": "Feature",
  "properties": {
    "gn:admin1_code":"26.0",
    "gn:asciiname":"Jiashiqu",
    "gn:country_code":"CN",
    "gn:dem":1454,
    "gn:feature_class":"P",
    "gn:feature_code":"PPL",
    "gn:name":"Jiashiqu",
    "gn:population":0,
    "gn:timezone":"Asia/Shanghai",
    "iso:country":"CN",
    "name:zho_x_preferred":[
        "\u8d3e\u77f3\u6e20"
    ],
    "wof:name":"Jiashiqu",
    "wof:placetype":"locality"
},
  "geometry": {"coordinates":[108.39666,37.46289],"type":"Point"}
}