{
  "type": "Feature",
  "properties": {
    "gn:admin1_code":"32.0",
    "gn:asciiname":"Jiancaogou",
    "gn:country_code":"CN",
    "gn:dem":1134,
    "gn:feature_class":"P",
    "gn:feature_code":"PPL",
    "gn:name":"Jiancaogou",
    "gn:population":0,
    "gn:timezone":"Asia/Shanghai",
    "iso:country":"CN",
    "name:zho_x_preferred":[
        "\u67a7\u69fd\u6c9f"
    ],
    "wof:name":"Jiancaogou",
    "wof:placetype":"locality"
},
  "geometry": {"coordinates":[105.44703,27.88908],"type":"Point"}
}