{
  "type": "Feature",
  "properties": {
    "gn:admin1_code":"15.0",
    "gn:asciiname":"Mudian",
    "gn:country_code":"CN",
    "gn:dem":2589,
    "gn:feature_class":"P",
    "gn:feature_code":"PPL",
    "gn:name":"Mudian",
    "gn:population":0,
    "gn:timezone":"Asia/Shanghai",
    "iso:country":"CN",
    "name:zho_x_preferred":[
        "\u7267\u70b9"
    ],
    "wof:name":"Mudian",
    "wof:placetype":"locality"
},
  "geometry": {"coordinates":[103.20399999999999,36.916],"type":"Point"}
}