{
  "type": "Feature",
  "properties": {
    "gn:admin1_code":"16.0",
    "gn:asciiname":"Waifu",
    "gn:country_code":"CN",
    "gn:dem":105,
    "gn:feature_class":"P",
    "gn:feature_code":"PPL",
    "gn:name":"Waifu",
    "gn:population":0,
    "gn:timezone":"Asia/Shanghai",
    "iso:country":"CN",
    "name:deu_x_preferred":[
        "Waifu"
    ],
    "name:jpn_x_preferred":[
        "\u4ffa\u306e\u5ac1"
    ],
    "name:zho_x_preferred":[
        "\u5916\u670d"
    ],
    "wof:name":"Waifu",
    "wof:placetype":"locality"
},
  "geometry": {"coordinates":[109.158,22.8165],"type":"Point"}
}