{
  "type": "Feature",
  "properties": {
    "gn:admin1_code":"25.0",
    "gn:asciiname":"Huangjintuncun",
    "gn:country_code":"CN",
    "gn:dem":42,
    "gn:feature_class":"P",
    "gn:feature_code":"PPL",
    "gn:name":"Huangjintuncun",
    "gn:population":0,
    "gn:timezone":"Asia/Shanghai",
    "iso:country":"CN",
    "name:zho_x_preferred":[
        "\u9ec4\u91d1\u5c6f\u6751"
    ],
    "wof:name":"Huangjintuncun",
    "wof:placetype":"locality"
},
  "geometry": {"coordinates":[116.74509999999999,35.4897],"type":"Point"}
}