{
  "type": "Feature",
  "properties": {
    "gn:admin1_code":"24.0",
    "gn:asciiname":"Yanwo",
    "gn:country_code":"CN",
    "gn:dem":1513,
    "gn:feature_class":"P",
    "gn:feature_code":"PPL",
    "gn:name":"Yanwo",
    "gn:population":0,
    "gn:timezone":"Asia/Shanghai",
    "iso:country":"CN",
    "name:zho_x_preferred":[
        "\u96c1\u7a9d"
    ],
    "wof:name":"Yanwo",
    "wof:placetype":"locality"
},
  "geometry": {"coordinates":[111.48238000000001,37.48977],"type":"Point"}
}