{
  "type": "Feature",
  "properties": {
    "gn:admin1_code":"32.0",
    "gn:asciiname":"Changying",
    "gn:country_code":"CN",
    "gn:dem":1720,
    "gn:feature_class":"P",
    "gn:feature_code":"PPL",
    "gn:name":"Changying",
    "gn:population":0,
    "gn:timezone":"Asia/Shanghai",
    "iso:country":"CN",
    "name:zho_x_preferred":[
        "\u957f\u8425"
    ],
    "wof:name":"Changying",
    "wof:placetype":"locality"
},
  "geometry": {"coordinates":[101.97476,26.72653],"type":"Point"}
}