{
  "type": "Feature",
  "properties": {
    "gn:admin1_code":"24.0",
    "gn:asciiname":"Caojiayu",
    "gn:country_code":"CN",
    "gn:dem":1479,
    "gn:feature_class":"P",
    "gn:feature_code":"PPL",
    "gn:name":"Caojiayu",
    "gn:population":0,
    "gn:timezone":"Asia/Shanghai",
    "iso:country":"CN",
    "name:zho_x_preferred":[
        "\u66f9\u5bb6\u5cea"
    ],
    "wof:name":"Caojiayu",
    "wof:placetype":"locality"
},
  "geometry": {"coordinates":[111.18875,37.13842],"type":"Point"}
}