{
  "type": "Feature",
  "properties": {
    "gn:country":"CN",
    "gn:fcode":"PPL",
    "gn:pop":68442,
    "iso:country":"CN",
    "name:unk_x_variant":[
        "Penchenchzhen\u2019"
    ],
    "qs:name":"\u5f6d\u57ce\u9547",
    "qs:name_adm0":"\u4e2d\u570b",
    "qs:name_adm1":"\u6cb3\u5317\u7701",
    "qs:photos_9k":1,
    "qs:photos_9r":1,
    "qs:photos_all":2,
    "qs:photos_sr":0,
    "qs:placetype":"Town",
    "qs:pop_sr":"8",
    "wd:wordcount":77,
    "wof:name":"\u5f6d\u57ce\u9547",
    "wof:placetype":"locality",
    "wof:population":68442
},
  "geometry": {"coordinates":[114.17,36.43111],"type":"Point"}
}