{
  "type": "Feature",
  "properties": {
    "gn:country":"CN",
    "gn:fcode":"PPL",
    "gn:pop":68442,
    "iso:country":"CN",
    "name:ceb_x_preferred":[
        "Fengfeng Kuangqu"
    ],
    "name:deu_x_preferred":[
        "Fengfeng Kuang"
    ],
    "name:fin_x_preferred":[
        "Fengfeng"
    ],
    "name:gan_x_preferred":[
        "\u5cf0\u5cf0\u77ff\u533a"
    ],
    "name:jpn_x_preferred":[
        "\u5cf0\u5cf0\u9271\u533a"
    ],
    "name:kor_x_preferred":[
        "\ud391\ud391\ucf85 \uad6c"
    ],
    "name:nan_x_preferred":[
        "Hong-hong-kh\u00f2ng-khu"
    ],
    "name:nld_x_preferred":[
        "Fengfeng Kuang"
    ],
    "name:nob_x_preferred":[
        "Fengfeng gruvedistrikt"
    ],
    "name:rus_x_preferred":[
        "\u0424\u044d\u043d\u0444\u044d\u043d"
    ],
    "name:swe_x_preferred":[
        "Fengfeng Kuangqu"
    ],
    "name:unk_x_variant":[
        "Penchenchzhen\u2019"
    ],
    "name:vie_x_preferred":[
        "Phong Phong"
    ],
    "name:wuu_x_preferred":[
        "\u5cf0\u5cf0\u77ff\u533a"
    ],
    "name:zho_x_preferred":[
        "\u5cf0\u5cf0\u77ff\u533a"
    ],
    "qs:name":"\u5f6d\u57ce\u9547",
    "qs:name_adm0":"\u4e2d\u570b",
    "qs:name_adm1":"\u6cb3\u5317\u7701",
    "qs:photos_9k":1,
    "qs:photos_9r":1,
    "qs:photos_all":2,
    "qs:photos_sr":0,
    "qs:placetype":"Town",
    "qs:pop_sr":"8",
    "wd:wordcount":77,
    "wof:name":"\u5f6d\u57ce\u9547",
    "wof:placetype":"locality",
    "wof:population":68442
},
  "geometry": {"coordinates":[114.17,36.43111],"type":"Point"}
}