{
  "type": "Feature",
  "properties": {
    "gn:admin1_code":"24.0",
    "gn:asciiname":"Yiwang",
    "gn:country_code":"CN",
    "gn:dem":936,
    "gn:feature_class":"P",
    "gn:feature_code":"PPL",
    "gn:name":"Yiwang",
    "gn:population":0,
    "gn:timezone":"Asia/Shanghai",
    "iso:country":"CN",
    "name:und_x_variant":[
        "I-wang",
        "Yiwang"
    ],
    "name:zho_x_preferred":[
        "\u4e49\u65fa"
    ],
    "wof:name":"Yiwang",
    "wof:placetype":"locality"
},
  "geometry": {"coordinates":[111.78794000000001,36.46325],"type":"Point"}
}