{
  "type": "Feature",
  "properties": {
    "gn:admin1_code":"18.0",
    "gn:asciiname":"Dubaoyuan",
    "gn:country_code":"CN",
    "gn:dem":1099,
    "gn:feature_class":"P",
    "gn:feature_code":"PPL",
    "gn:name":"Dubaoyuan",
    "gn:population":0,
    "gn:timezone":"Asia/Shanghai",
    "iso:country":"CN",
    "name:zho_x_preferred":[
        "\u90fd\u5b9d\u9662"
    ],
    "wof:name":"Dubaoyuan",
    "wof:placetype":"locality"
},
  "geometry": {"coordinates":[107.419,26.9869],"type":"Point"}
}