{
  "type": "Feature",
  "properties": {
    "gn:admin1_code":"19.0",
    "gn:asciiname":"Shitaizi",
    "gn:country_code":"CN",
    "gn:dem":439,
    "gn:feature_class":"P",
    "gn:feature_code":"PPL",
    "gn:name":"Shitaizi",
    "gn:population":0,
    "gn:timezone":"Asia/Shanghai",
    "iso:country":"CN",
    "name:zho_x_preferred":[
        "\u53f2\u53f0\u5b50"
    ],
    "wof:name":"Shitaizi",
    "wof:placetype":"locality"
},
  "geometry": {"coordinates":[119.60899999999999,40.607],"type":"Point"}
}