{
  "type": "Feature",
  "properties": {
    "gn:admin1_code":"11.0",
    "gn:asciiname":"Dashentang Zhangjia",
    "gn:country_code":"CN",
    "gn:dem":117,
    "gn:feature_class":"P",
    "gn:feature_code":"PPL",
    "gn:name":"Dashentang Zhangjia",
    "gn:population":0,
    "gn:timezone":"Asia/Shanghai",
    "iso:country":"CN",
    "name:zho_x_preferred":[
        "\u5927\u6df1\u5858\u5f20\u5bb6"
    ],
    "wof:name":"Dashentang Zhangjia",
    "wof:placetype":"locality"
},
  "geometry": {"coordinates":[111.63351000000002,26.29203],"type":"Point"}
}