{
  "type": "Feature",
  "properties": {
    "gn:admin1_code":"11.0",
    "gn:asciiname":"Xigutai",
    "gn:country_code":"CN",
    "gn:dem":83,
    "gn:feature_class":"P",
    "gn:feature_code":"PPL",
    "gn:name":"Xigutai",
    "gn:population":0,
    "gn:timezone":"Asia/Shanghai",
    "iso:country":"CN",
    "name:zho_x_preferred":[
        "\u5e0c\u53e4\u53f0"
    ],
    "wof:name":"Xigutai",
    "wof:placetype":"locality"
},
  "geometry": {"coordinates":[113.19861000000002,28.5505],"type":"Point"}
}