{
  "type": "Feature",
  "properties": {
    "gn:admin1_code":"10.0",
    "gn:asciiname":"Chenggezhuang",
    "gn:country_code":"CN",
    "gn:dem":31,
    "gn:feature_class":"P",
    "gn:feature_code":"PPL",
    "gn:name":"Chenggezhuang",
    "gn:population":0,
    "gn:timezone":"Asia/Shanghai",
    "iso:country":"CN",
    "name:zho_x_preferred":[
        "\u7a0b\u5404\u5e84"
    ],
    "wof:name":"Chenggezhuang",
    "wof:placetype":"locality"
},
  "geometry": {"coordinates":[119.21719,39.93036],"type":"Point"}
}