{
  "type": "Feature",
  "properties": {
    "gn:admin1_code":"8.0",
    "gn:asciiname":"Yanjun Shijiudui",
    "gn:country_code":"CN",
    "gn:dem":81,
    "gn:feature_class":"P",
    "gn:feature_code":"PPLF",
    "gn:name":"Yanjun Shijiudui",
    "gn:population":0,
    "gn:timezone":"Asia/Shanghai",
    "iso:country":"CN",
    "name:zho_x_preferred":[
        "\u5ef6\u519b\u5341\u4e5d\u961f"
    ],
    "wof:name":"Yanjun Shijiudui",
    "wof:placetype":"locality"
},
  "geometry": {"coordinates":[130.85387,47.6379],"type":"Point"}
}