{
  "type": "Feature",
  "properties": {
    "gn:admin1_code":"26.0",
    "gn:asciiname":"Liujia Shizi",
    "gn:country_code":"CN",
    "gn:dem":681,
    "gn:feature_class":"P",
    "gn:feature_code":"PPL",
    "gn:name":"Liujia Shizi",
    "gn:population":0,
    "gn:timezone":"Asia/Shanghai",
    "iso:country":"CN",
    "name:zho_x_preferred":[
        "\u5218\u5bb6\u5341\u5b57"
    ],
    "wof:name":"Liujia Shizi",
    "wof:placetype":"locality"
},
  "geometry": {"coordinates":[108.44553000000001,34.57876],"type":"Point"}
}