{
  "type": "Feature",
  "properties": {
    "gn:admin1_code":"7.0",
    "gn:asciiname":"Xiqin",
    "gn:country_code":"CN",
    "gn:dem":87,
    "gn:feature_class":"P",
    "gn:feature_code":"PPLA4",
    "gn:name":"Xiqin",
    "gn:population":0,
    "gn:timezone":"Asia/Shanghai",
    "iso:country":"CN",
    "name:deu_x_preferred":[
        "Xiqin"
    ],
    "name:und_x_variant":[
        "Hsi-ch\u2019in",
        "Sikin",
        "\u897f\u82b9",
        "Xiqin Zhen",
        "\u897f\u82b9\u9547"
    ],
    "wof:name":"Xiqin",
    "wof:placetype":"locality"
},
  "geometry": {"coordinates":[118.10993000000001,26.57207],"type":"Point"}
}