{
  "type": "Feature",
  "properties": {
    "gn:admin1_code":"32.0",
    "gn:asciiname":"Liujiaying",
    "gn:country_code":"CN",
    "gn:dem":1268,
    "gn:feature_class":"P",
    "gn:feature_code":"PPL",
    "gn:name":"Liujiaying",
    "gn:population":0,
    "gn:timezone":"Asia/Shanghai",
    "iso:country":"CN",
    "name:zho_x_preferred":[
        "\u5218\u5bb6\u8425"
    ],
    "wof:name":"Liujiaying",
    "wof:placetype":"locality"
},
  "geometry": {"coordinates":[105.598,28.1605],"type":"Point"}
}