{
  "type": "Feature",
  "properties": {
    "gn:admin1_code":"29",
    "gn:asciiname":"Bajiaotang",
    "gn:country_code":"CN",
    "gn:dem":1481,
    "gn:feature_class":"P",
    "gn:feature_code":"PPL",
    "gn:name":"Bajiaotang",
    "gn:population":0,
    "gn:timezone":"Asia/Shanghai",
    "iso:country":"CN",
    "name:zho_x_preferred":[
        "\u82ad\u8549\u5858"
    ],
    "wof:name":"Bajiaotang",
    "wof:placetype":"locality"
},
  "geometry": {"coordinates":[104.973,23.8406],"type":"Point"}
}