{
  "type": "Feature",
  "properties": {
    "gn:admin1_code":"22",
    "gn:asciiname":"Sihai",
    "gn:country_code":"CN",
    "gn:dem":667,
    "gn:feature_class":"P",
    "gn:feature_code":"PPLA4",
    "gn:name":"Sihai",
    "gn:population":0,
    "gn:timezone":"Asia/Shanghai",
    "iso:country":"CN",
    "name:und_x_variant":[
        "Ssu-hai-yeh",
        "Ssu-hai",
        "Ssu-hai-pao",
        "Sihai",
        "Sihai Zhen"
    ],
    "name:zho_x_preferred":[
        "\u56db\u6d77"
    ],
    "name:zho_x_variant":[
        "\u56db\u6d77\u9547"
    ],
    "wof:name":"Sihai",
    "wof:placetype":"locality"
},
  "geometry": {"coordinates":[116.40514,40.52458],"type":"Point"}
}