{
  "type": "Feature",
  "properties": {
    "gn:admin1_code":"12.0",
    "gn:asciiname":"Sanchagou",
    "gn:country_code":"CN",
    "gn:dem":821,
    "gn:feature_class":"P",
    "gn:feature_code":"PPL",
    "gn:name":"Sanchagou",
    "gn:population":0,
    "gn:timezone":"Asia/Shanghai",
    "iso:country":"CN",
    "name:zho_x_preferred":[
        "\u4e09\u5c94\u6c9f"
    ],
    "wof:name":"Sanchagou",
    "wof:placetype":"locality"
},
  "geometry": {"coordinates":[109.83262000000001,30.72639],"type":"Point"}
}