{
  "type": "Feature",
  "properties": {
    "gn:admin1_code":"29.0",
    "gn:asciiname":"Shuicao",
    "gn:country_code":"CN",
    "gn:dem":1950,
    "gn:feature_class":"P",
    "gn:feature_code":"PPL",
    "gn:name":"Shuicao",
    "gn:population":0,
    "gn:timezone":"Asia/Shanghai",
    "iso:country":"CN",
    "name:zho_x_preferred":[
        "\u6c34\u69fd"
    ],
    "wof:name":"Shuicao",
    "wof:placetype":"locality"
},
  "geometry": {"coordinates":[99.9179,24.7188],"type":"Point"}
}