{
  "type": "Feature",
  "properties": {
    "gn:admin1_code":"11.0",
    "gn:asciiname":"Tuhaochong",
    "gn:country_code":"CN",
    "gn:dem":108,
    "gn:feature_class":"P",
    "gn:feature_code":"PPL",
    "gn:name":"Tuhaochong",
    "gn:population":0,
    "gn:timezone":"Asia/Shanghai",
    "iso:country":"CN",
    "name:zho_x_preferred":[
        "\u571f\u58d5\u51b2"
    ],
    "wof:name":"Tuhaochong",
    "wof:placetype":"locality"
},
  "geometry": {"coordinates":[113.71861,27.89103],"type":"Point"}
}