{
  "type": "Feature",
  "properties": {
    "gn:admin1_code":"16.0",
    "gn:asciiname":"Chadang",
    "gn:country_code":"CN",
    "gn:dem":364,
    "gn:feature_class":"P",
    "gn:feature_code":"PPL",
    "gn:name":"Chadang",
    "gn:population":0,
    "gn:timezone":"Asia/Shanghai",
    "iso:country":"CN",
    "name:zho_x_preferred":[
        "\u8336\u5f53"
    ],
    "wof:name":"Chadang",
    "wof:placetype":"locality"
},
  "geometry": {"coordinates":[108.18600000000001,24.2953],"type":"Point"}
}