{
  "type": "Feature",
  "properties": {
    "gn:admin1_code":"26.0",
    "gn:asciiname":"Zuoxinzhuang",
    "gn:country_code":"CN",
    "gn:dem":1189,
    "gn:feature_class":"P",
    "gn:feature_code":"PPL",
    "gn:name":"Zuoxinzhuang",
    "gn:population":0,
    "gn:timezone":"Asia/Shanghai",
    "iso:country":"CN",
    "name:zho_x_preferred":[
        "\u5de6\u65b0\u5e84"
    ],
    "wof:name":"Zuoxinzhuang",
    "wof:placetype":"locality"
},
  "geometry": {"coordinates":[109.71068,37.80076],"type":"Point"}
}