{
  "type": "Feature",
  "properties": {
    "iso:country":"CN",
    "name:eng_x_preferred":[
        "Chongdui"
    ],
    "name:zho_x_preferred":[
        "\u51b2\u5806"
    ],
    "qs:name":"\u51b2\u5806",
    "qs:name_adm0":"\u4e2d\u570b",
    "qs:name_adm1":"\u897f\u85cf\u81ea\u6cbb\u533a",
    "qs:photos":23,
    "qs:photos_1k":5,
    "qs:photos_9k":1,
    "qs:photos_9r":1,
    "qs:photos_all":23,
    "qs:photos_sr":1,
    "qs:placetype":"Town",
    "qs:pop_sr":"0",
    "wof:name":"Chongdui",
    "wof:placetype":"locality"
},
  "geometry": {"coordinates":[85.97852,28.14517],"type":"Point"}
}