{
  "type": "Feature",
  "properties": {
    "gn:admin1_code":"30",
    "gn:asciiname":"Liwuzhai",
    "gn:country_code":"CN",
    "gn:dem":93,
    "gn:feature_class":"P",
    "gn:feature_code":"PPL",
    "gn:name":"Liwuzhai",
    "gn:population":0,
    "gn:timezone":"Asia/Shanghai",
    "iso:country":"CN",
    "wof:name":"Liwuzhai",
    "wof:placetype":"locality"
},
  "geometry": {"coordinates":[115.93944,23.51361],"type":"Point"}
}