{
  "type": "Feature",
  "properties": {
    "gn:admin1_code":"12.0",
    "gn:asciiname":"Shiziyan",
    "gn:country_code":"CN",
    "gn:dem":135,
    "gn:feature_class":"P",
    "gn:feature_code":"PPL",
    "gn:name":"Shiziyan",
    "gn:population":0,
    "gn:timezone":"Asia/Shanghai",
    "iso:country":"CN",
    "name:zho_x_preferred":[
        "\u72ee\u5b50\u5ca9"
    ],
    "wof:name":"Shiziyan",
    "wof:placetype":"locality"
},
  "geometry": {"coordinates":[111.45668999999999,32.47958],"type":"Point"}
}