{
  "type": "Feature",
  "properties": {
    "gn:admin1_code":"32.0",
    "gn:asciiname":"Shihuopen",
    "gn:country_code":"CN",
    "gn:dem":341,
    "gn:feature_class":"P",
    "gn:feature_code":"PPL",
    "gn:name":"Shihuopen",
    "gn:population":0,
    "gn:timezone":"Asia/Shanghai",
    "iso:country":"CN",
    "name:zho_x_preferred":[
        "\u77f3\u706b\u76c6"
    ],
    "wof:name":"Shihuopen",
    "wof:placetype":"locality"
},
  "geometry": {"coordinates":[103.84220000000001,29.32432],"type":"Point"}
}