{
  "type": "Feature",
  "properties": {
    "gn:admin1_code":"10",
    "gn:asciiname":"Jiangfang",
    "gn:country_code":"CN",
    "gn:dem":18,
    "gn:feature_class":"P",
    "gn:feature_code":"PPL",
    "gn:name":"Jiangfang",
    "gn:population":0,
    "gn:timezone":"Asia/Shanghai",
    "iso:country":"CN",
    "name:zho_x_preferred":[
        "\u848b\u574a\u4e61"
    ],
    "wof:name":"Jiangfang",
    "wof:placetype":"locality"
},
  "geometry": {"coordinates":[116.18944,37.93694],"type":"Point"}
}