{
  "type": "Feature",
  "properties": {
    "gn:admin1_code":"16",
    "gn:asciiname":"Shuiyouzha",
    "gn:country_code":"CN",
    "gn:dem":158,
    "gn:feature_class":"P",
    "gn:feature_code":"PPL",
    "gn:name":"Shuiyouzha",
    "gn:population":0,
    "gn:timezone":"Asia/Shanghai",
    "iso:country":"CN",
    "name:zho_x_preferred":[
        "\u6c34\u6cb9\u69a8"
    ],
    "wof:name":"Shuiyouzha",
    "wof:placetype":"locality"
},
  "geometry": {"coordinates":[110.64700000000001,24.5756],"type":"Point"}
}