{
  "type": "Feature",
  "properties": {
    "gn:admin1_code":"8.0",
    "gn:asciiname":"Minhecun",
    "gn:country_code":"CN",
    "gn:dem":195,
    "gn:feature_class":"P",
    "gn:feature_code":"PPL",
    "gn:name":"Minhecun",
    "gn:population":0,
    "gn:timezone":"Asia/Shanghai",
    "iso:country":"CN",
    "name:zho_x_preferred":[
        "\u6c11\u548c\u6751"
    ],
    "wof:name":"Minhecun",
    "wof:placetype":"locality"
},
  "geometry": {"coordinates":[125.69289000000001,46.95267],"type":"Point"}
}