{
  "type": "Feature",
  "properties": {
    "gn:admin1_code":"29.0",
    "gn:asciiname":"Lichangsi",
    "gn:country_code":"CN",
    "gn:dem":2290,
    "gn:feature_class":"P",
    "gn:feature_code":"PPL",
    "gn:name":"Lichangsi",
    "gn:population":0,
    "gn:timezone":"Asia/Shanghai",
    "iso:country":"CN",
    "name:zho_x_preferred":[
        "\u91cc\u957f\u5bfa"
    ],
    "wof:name":"Lichangsi",
    "wof:placetype":"locality"
},
  "geometry": {"coordinates":[100.985,25.3418],"type":"Point"}
}