{
  "type": "Feature",
  "properties": {
    "gn:admin1_code":"3.0",
    "gn:asciiname":"Dingjiaji",
    "gn:country_code":"CN",
    "gn:dem":474,
    "gn:feature_class":"P",
    "gn:feature_code":"PPL",
    "gn:name":"Dingjiaji",
    "gn:population":0,
    "gn:timezone":"Asia/Shanghai",
    "iso:country":"CN",
    "name:und_x_variant":[
        "\u4e01\u5bb6\u9645"
    ],
    "wof:name":"Dingjiaji",
    "wof:placetype":"locality"
},
  "geometry": {"coordinates":[116.95292999999999,27.67281],"type":"Point"}
}