{
  "type": "Feature",
  "properties": {
    "gn:admin1_code":"11.0",
    "gn:asciiname":"Yajili",
    "gn:country_code":"CN",
    "gn:dem":938,
    "gn:feature_class":"P",
    "gn:feature_code":"PPL",
    "gn:name":"Yajili",
    "gn:population":0,
    "gn:timezone":"Asia/Shanghai",
    "iso:country":"CN",
    "name:zho_x_preferred":[
        "\u96c5\u5409\u91cc"
    ],
    "wof:name":"Yajili",
    "wof:placetype":"locality"
},
  "geometry": {"coordinates":[110.56583000000001,29.86935],"type":"Point"}
}