{
  "type": "Feature",
  "properties": {
    "gn:admin1_code":"13.0",
    "gn:asciiname":"Tuokuzikule",
    "gn:country_code":"CN",
    "gn:dem":1319,
    "gn:feature_class":"P",
    "gn:feature_code":"PPL",
    "gn:name":"Tuokuzikule",
    "gn:population":0,
    "gn:timezone":"Asia/Urumqi",
    "iso:country":"CN",
    "name:zho_x_preferred":[
        "\u6258\u5e93\u5b5c\u5e93\u52d2"
    ],
    "wof:name":"Tuokuzikule",
    "wof:placetype":"locality"
},
  "geometry": {"coordinates":[83.72892,37.68735],"type":"Point"}
}