{
  "type": "Feature",
  "properties": {
    "gn:admin1_code":"24.0",
    "gn:asciiname":"Laiyuan",
    "gn:country_code":"CN",
    "gn:dem":1016,
    "gn:feature_class":"P",
    "gn:feature_code":"PPL",
    "gn:name":"Laiyuan",
    "gn:population":0,
    "gn:timezone":"Asia/Shanghai",
    "iso:country":"CN",
    "name:und_x_variant":[
        "\u6765\u8fdc"
    ],
    "wof:name":"Laiyuan",
    "wof:placetype":"locality"
},
  "geometry": {"coordinates":[112.91167,39.59634000000001],"type":"Point"}
}