{
  "type": "Feature",
  "properties": {
    "gn:admin1_code":"10",
    "gn:asciiname":"Baimutai",
    "gn:country_code":"CN",
    "gn:dem":421,
    "gn:feature_class":"P",
    "gn:feature_code":"PPL",
    "gn:name":"Baimutai",
    "gn:population":0,
    "gn:timezone":"Asia/Shanghai",
    "iso:country":"CN",
    "name:und_x_variant":[
        "\u767e\u4ea9\u53f0"
    ],
    "wof:name":"Baimutai",
    "wof:placetype":"locality"
},
  "geometry": {"coordinates":[114.07274,38.941],"type":"Point"}
}