{
  "type": "Feature",
  "properties": {
    "gn:admin1_code":"32.0",
    "gn:asciiname":"Maizigou",
    "gn:country_code":"CN",
    "gn:dem":2734,
    "gn:feature_class":"P",
    "gn:feature_code":"PPL",
    "gn:name":"Maizigou",
    "gn:population":0,
    "gn:timezone":"Asia/Shanghai",
    "iso:country":"CN",
    "name:zho_x_preferred":[
        "\u9ea6\u5b50\u6c9f"
    ],
    "wof:name":"Maizigou",
    "wof:placetype":"locality"
},
  "geometry": {"coordinates":[101.827,27.7277],"type":"Point"}
}