{
  "type": "Feature",
  "properties": {
    "gn:admin1_code":"11",
    "gn:asciiname":"Xianlinkesuo",
    "gn:country_code":"CN",
    "gn:dem":266,
    "gn:feature_class":"P",
    "gn:feature_code":"PPL",
    "gn:name":"Xianlinkesuo",
    "gn:population":0,
    "gn:timezone":"Asia/Shanghai",
    "iso:country":"CN",
    "wof:name":"Xianlinkesuo",
    "wof:placetype":"locality"
},
  "geometry": {"coordinates":[111.31305999999999,25.25167],"type":"Point"}
}