{
  "type": "Feature",
  "properties": {
    "gn:admin1_code":"32.0",
    "gn:asciiname":"Yingjie",
    "gn:country_code":"CN",
    "gn:dem":418,
    "gn:feature_class":"P",
    "gn:feature_code":"PPL",
    "gn:name":"Yingjie",
    "gn:population":0,
    "gn:timezone":"Asia/Shanghai",
    "iso:country":"CN",
    "name:zho_x_preferred":[
        "\u8fce\u63a5"
    ],
    "wof:name":"Yingjie",
    "wof:placetype":"locality"
},
  "geometry": {"coordinates":[104.58329000000001,30.07031],"type":"Point"}
}