{
  "type": "Feature",
  "properties": {
    "gn:admin1_code":"32.0",
    "gn:asciiname":"Dengzi",
    "gn:country_code":"CN",
    "gn:dem":326,
    "gn:feature_class":"P",
    "gn:feature_code":"PPL",
    "gn:name":"Dengzi",
    "gn:population":0,
    "gn:timezone":"Asia/Shanghai",
    "iso:country":"CN",
    "name:zho_x_preferred":[
        "\u78f4\u5b50"
    ],
    "wof:name":"Dengzi",
    "wof:placetype":"locality"
},
  "geometry": {"coordinates":[107.07836,31.41876],"type":"Point"}
}