{
  "type": "Feature",
  "properties": {
    "gn:admin1_code":"2.0",
    "gn:asciiname":"Pingtiantang",
    "gn:country_code":"CN",
    "gn:dem":3,
    "gn:feature_class":"P",
    "gn:feature_code":"PPL",
    "gn:name":"Pingtiantang",
    "gn:population":0,
    "gn:timezone":"Asia/Shanghai",
    "iso:country":"CN",
    "name:zho_x_preferred":[
        "\u5e73\u5929\u5802"
    ],
    "wof:name":"Pingtiantang",
    "wof:placetype":"locality"
},
  "geometry": {"coordinates":[121.50118000000001,28.46024],"type":"Point"}
}