{
  "type": "Feature",
  "properties": {
    "gn:admin1_code":"2.0",
    "gn:asciiname":"Ruolingbei",
    "gn:country_code":"CN",
    "gn:dem":560,
    "gn:feature_class":"P",
    "gn:feature_code":"PPL",
    "gn:name":"Ruolingbei",
    "gn:population":0,
    "gn:timezone":"Asia/Shanghai",
    "iso:country":"CN",
    "name:zho_x_preferred":[
        "\u7bac\u5cad\u80cc"
    ],
    "wof:name":"Ruolingbei",
    "wof:placetype":"locality"
},
  "geometry": {"coordinates":[118.83857999999999,29.23914000000001],"type":"Point"}
}