{
  "type": "Feature",
  "properties": {
    "gn:admin1_code":"15.0",
    "gn:asciiname":"Linshanfu",
    "gn:country_code":"CN",
    "gn:dem":2005,
    "gn:feature_class":"P",
    "gn:feature_code":"PPL",
    "gn:name":"Linshanfu",
    "gn:population":0,
    "gn:timezone":"Asia/Shanghai",
    "iso:country":"CN",
    "name:zho_x_preferred":[
        "\u6797\u5c71\u5e9c"
    ],
    "wof:name":"Linshanfu",
    "wof:placetype":"locality"
},
  "geometry": {"coordinates":[100.58199999999999,38.5917],"type":"Point"}
}