{
  "type": "Feature",
  "properties": {
    "gn:admin1_code":"32.0",
    "gn:asciiname":"Tiangengshang",
    "gn:country_code":"CN",
    "gn:dem":545,
    "gn:feature_class":"P",
    "gn:feature_code":"PPL",
    "gn:name":"Tiangengshang",
    "gn:population":0,
    "gn:timezone":"Asia/Shanghai",
    "iso:country":"CN",
    "name:zho_x_preferred":[
        "\u7530\u57c2\u4e0a"
    ],
    "wof:name":"Tiangengshang",
    "wof:placetype":"locality"
},
  "geometry": {"coordinates":[105.72698,27.71333],"type":"Point"}
}