{
  "type": "Feature",
  "properties": {
    "gn:admin1_code":"5.0",
    "gn:asciiname":"Shitanggou",
    "gn:country_code":"CN",
    "gn:dem":236,
    "gn:feature_class":"P",
    "gn:feature_code":"PPL",
    "gn:name":"Shitanggou",
    "gn:population":0,
    "gn:timezone":"Asia/Shanghai",
    "iso:country":"CN",
    "name:zho_x_preferred":[
        "\u77f3\u5858\u6c9f"
    ],
    "wof:name":"Shitanggou",
    "wof:placetype":"locality"
},
  "geometry": {"coordinates":[126.94919,44.50491],"type":"Point"}
}