{
  "type": "Feature",
  "properties": {
    "gn:admin1_code":"3.0",
    "gn:asciiname":"Dongshao",
    "gn:country_code":"CN",
    "gn:dem":154,
    "gn:feature_class":"P",
    "gn:feature_code":"PPL",
    "gn:name":"Dongshao",
    "gn:population":0,
    "gn:timezone":"Asia/Shanghai",
    "iso:country":"CN",
    "name:und_x_variant":[
        "\u4e1c\u97f6"
    ],
    "wof:name":"Dongshao",
    "wof:placetype":"locality"
},
  "geometry": {"coordinates":[114.35347,27.86304],"type":"Point"}
}