{
  "type": "Feature",
  "properties": {
    "gn:admin1_code":"21.0",
    "gn:asciiname":"Tongjia Manpo",
    "gn:country_code":"CN",
    "gn:dem":1574,
    "gn:feature_class":"P",
    "gn:feature_code":"PPL",
    "gn:name":"Tongjia Manpo",
    "gn:population":0,
    "gn:timezone":"Asia/Shanghai",
    "iso:country":"CN",
    "name:zho_x_preferred":[
        "\u7ae5\u5bb6\u6162\u5761"
    ],
    "wof:name":"Tongjia Manpo",
    "wof:placetype":"locality"
},
  "geometry": {"coordinates":[106.617,37.1937],"type":"Point"}
}