{
  "type": "Feature",
  "properties": {
    "gn:admin1_code":"29",
    "gn:asciiname":"Longchi",
    "gn:country_code":"CN",
    "gn:dem":1867,
    "gn:feature_class":"P",
    "gn:feature_code":"PPL",
    "gn:name":"Longchi",
    "gn:population":0,
    "gn:timezone":"Asia/Shanghai",
    "iso:country":"CN",
    "name:zho_x_preferred":[
        "\u9f99\u6c60"
    ],
    "wof:name":"Longchi",
    "wof:placetype":"locality"
},
  "geometry": {"coordinates":[103.065,24.8814],"type":"Point"}
}