{
  "type": "Feature",
  "properties": {
    "gn:admin1_code":"26.0",
    "gn:asciiname":"Houjiawa",
    "gn:country_code":"CN",
    "gn:dem":1125,
    "gn:feature_class":"P",
    "gn:feature_code":"PPL",
    "gn:name":"Houjiawa",
    "gn:population":0,
    "gn:timezone":"Asia/Shanghai",
    "iso:country":"CN",
    "name:zho_x_preferred":[
        "\u5019\u5bb6\u6d3c"
    ],
    "wof:name":"Houjiawa",
    "wof:placetype":"locality"
},
  "geometry": {"coordinates":[107.91540000000001,35.04917],"type":"Point"}
}