{
  "type": "Feature",
  "properties": {
    "gn:admin1_code":"14.0",
    "gn:asciiname":"Biqingcun",
    "gn:country_code":"CN",
    "gn:dem":4238,
    "gn:feature_class":"P",
    "gn:feature_code":"PPL",
    "gn:name":"Biqingcun",
    "gn:population":0,
    "gn:timezone":"Asia/Urumqi",
    "iso:country":"CN",
    "name:zho_x_preferred":[
        "\u6bd5\u9752\u6751"
    ],
    "wof:name":"Biqingcun",
    "wof:placetype":"locality"
},
  "geometry": {"coordinates":[97.24307,30.40729],"type":"Point"}
}