{
  "type": "Feature",
  "properties": {
    "gn:admin1_code":"14.0",
    "gn:asciiname":"Jinlongpu",
    "gn:country_code":"CN",
    "gn:dem":4452,
    "gn:feature_class":"P",
    "gn:feature_code":"PPL",
    "gn:name":"Jinlongpu",
    "gn:population":0,
    "gn:timezone":"Asia/Urumqi",
    "iso:country":"CN",
    "name:bod_x_preferred":[
        "J\u00eanlungpu"
    ],
    "name:zho_x_preferred":[
        "Jinlongpu"
    ],
    "name:zho_x_variant":[
        "\u91d1\u9f99\u666e"
    ],
    "wof:name":"Jinlongpu",
    "wof:placetype":"locality"
},
  "geometry": {"coordinates":[88.101,28.501],"type":"Point"}
}