{
  "type": "Feature",
  "properties": {
    "gn:admin1_code":"29.0",
    "gn:asciiname":"Mutoudi",
    "gn:country_code":"CN",
    "gn:dem":1327,
    "gn:feature_class":"P",
    "gn:feature_code":"PPL",
    "gn:name":"Mutoudi",
    "gn:population":0,
    "gn:timezone":"Asia/Shanghai",
    "iso:country":"CN",
    "name:zho_x_preferred":[
        "\u6728\u5934\u5e95"
    ],
    "wof:name":"Mutoudi",
    "wof:placetype":"locality"
},
  "geometry": {"coordinates":[104.41200000000001,23.0138],"type":"Point"}
}