{
  "type": "Feature",
  "properties": {
    "gn:admin1_code":"4.0",
    "gn:asciiname":"Yanqiao",
    "gn:country_code":"CN",
    "gn:dem":2,
    "gn:feature_class":"P",
    "gn:feature_code":"PPLA3",
    "gn:name":"Yanqiao",
    "gn:population":0,
    "gn:timezone":"Asia/Shanghai",
    "iso:country":"CN",
    "name:und_x_variant":[
        "Yanqiao Jiedao",
        "Huishan Qu"
    ],
    "name:zho_x_preferred":[
        "\u5830\u6865"
    ],
    "name:zho_x_variant":[
        "\u5830\u6865\u8857\u9053",
        "\u60e0\u5c71\u533a"
    ],
    "wof:name":"Yanqiao",
    "wof:placetype":"locality"
},
  "geometry": {"coordinates":[120.27800000000001,31.68918],"type":"Point"}
}