{
  "type": "Feature",
  "properties": {
    "gn:admin1_code":"26.0",
    "gn:asciiname":"Qinjiacun",
    "gn:country_code":"CN",
    "gn:dem":364,
    "gn:feature_class":"P",
    "gn:feature_code":"PPL",
    "gn:name":"Qinjiacun",
    "gn:population":0,
    "gn:timezone":"Asia/Shanghai",
    "iso:country":"CN",
    "name:und_x_variant":[
        "Qinjia"
    ],
    "name:zho_x_preferred":[
        "\u79e6\u5bb6\u6751"
    ],
    "name:zho_x_variant":[
        "\u79e6\u5bb6"
    ],
    "wof:name":"Qinjiacun",
    "wof:placetype":"locality"
},
  "geometry": {"coordinates":[109.60357,34.78085],"type":"Point"}
}