{
  "type": "Feature",
  "properties": {
    "gn:admin1_code":"29",
    "gn:asciiname":"Nashi",
    "gn:country_code":"CN",
    "gn:dem":661,
    "gn:feature_class":"P",
    "gn:feature_code":"PPL",
    "gn:name":"Nashi",
    "gn:population":0,
    "gn:timezone":"Asia/Shanghai",
    "iso:country":"CN",
    "name:ces_x_preferred":[
        "Na\u0161i"
    ],
    "name:fin_x_preferred":[
        "Nashi"
    ],
    "name:jpn_x_preferred":[
        "\u30ca\u30b7"
    ],
    "name:nld_x_preferred":[
        "Nashi"
    ],
    "name:rus_x_preferred":[
        "\u041d\u0430\u0448\u0438"
    ],
    "name:slk_x_preferred":[
        "Na\u0161i"
    ],
    "name:spa_x_preferred":[
        "Nashi"
    ],
    "name:ukr_x_preferred":[
        "\u041d\u0430\u0448\u0456"
    ],
    "name:zho_x_preferred":[
        "\u90a3\u4ec0"
    ],
    "wof:name":"Nashi",
    "wof:placetype":"locality"
},
  "geometry": {"coordinates":[105.858,23.7096],"type":"Point"}
}