{
  "type": "Feature",
  "properties": {
    "gn:admin1_code":"29",
    "gn:asciiname":"Nashi",
    "gn:country_code":"CN",
    "gn:dem":661,
    "gn:feature_class":"P",
    "gn:feature_code":"PPL",
    "gn:name":"Nashi",
    "gn:population":0,
    "gn:timezone":"Asia/Shanghai",
    "iso:country":"CN",
    "name:zho_x_preferred":[
        "\u90a3\u4ec0"
    ],
    "wof:name":"Nashi",
    "wof:placetype":"locality"
},
  "geometry": {"coordinates":[105.858,23.7096],"type":"Point"}
}