{
  "type": "Feature",
  "properties": {
    "gn:admin1_code":"16.0",
    "gn:asciiname":"Pingxiang",
    "gn:country_code":"CN",
    "gn:dem":656,
    "gn:feature_class":"P",
    "gn:feature_code":"PPL",
    "gn:name":"Pingxiang",
    "gn:population":0,
    "gn:timezone":"Asia/Shanghai",
    "iso:country":"CN",
    "name:ara_x_preferred":[
        "\u0628\u064a\u0646\u063a\u0634\u064a\u0627\u0646\u063a"
    ],
    "name:cdo_x_preferred":[
        "B\u00ecng-hi\u014fng"
    ],
    "name:ceb_x_preferred":[
        "Pingxiang"
    ],
    "name:ces_x_preferred":[
        "Pching-siang"
    ],
    "name:cym_x_preferred":[
        "Pingxiang"
    ],
    "name:dan_x_preferred":[
        "Pingxiang"
    ],
    "name:deu_x_preferred":[
        "Pingxiang"
    ],
    "name:eus_x_preferred":[
        "Pingxiang"
    ],
    "name:fas_x_preferred":[
        "\u067e\u06cc\u0646\u06af\u0634\u06cc\u0627\u0646\u06af"
    ],
    "name:fin_x_preferred":[
        "Pingxiang"
    ],
    "name:fra_x_preferred":[
        "Pingxiang"
    ],
    "name:hak_x_preferred":[
        "Ph\u00ecn-hi\u00f4ng-s\u1e73"
    ],
    "name:ita_x_preferred":[
        "Pingxiang"
    ],
    "name:jpn_x_preferred":[
        "\u840d\u90f7\u5e02"
    ],
    "name:kik_x_preferred":[
        "Pingxiang"
    ],
    "name:kor_x_preferred":[
        "\ud551\uc0f9\uc2dc"
    ],
    "name:mlg_x_preferred":[
        "Pingxiang"
    ],
    "name:nld_x_preferred":[
        "Pingxiang"
    ],
    "name:nno_x_preferred":[
        "Pingxiang"
    ],
    "name:nor_x_preferred":[
        "Pingxiang"
    ],
    "name:pol_x_preferred":[
        "Pingxiang"
    ],
    "name:por_x_preferred":[
        "Pingxiang"
    ],
    "name:rus_x_preferred":[
        "\u041f\u0438\u043d\u0441\u044f\u043d"
    ],
    "name:spa_x_preferred":[
        "Pingxiang"
    ],
    "name:srp_x_preferred":[
        "\u041f\u0438\u043d\u0433\u0441\u0458\u0430\u043d\u0433"
    ],
    "name:swe_x_preferred":[
        "Pingxiang"
    ],
    "name:tur_x_preferred":[
        "Pingxiang"
    ],
    "name:urd_x_preferred":[
        "\u067e\u0646\u06af\u0634\u06cc\u0627\u0646\u06af"
    ],
    "name:vie_x_preferred":[
        "B\u00ecnh H\u01b0\u01a1ng"
    ],
    "name:war_x_preferred":[
        "Pingxiang"
    ],
    "name:wuu_x_preferred":[
        "\u840d\u4e61\u5e02"
    ],
    "name:zho_x_preferred":[
        "\u5e73\u7965"
    ],
    "name:zho_x_variant":[
        "\u840d\u4e61\u5e02"
    ],
    "wof:name":"Pingxiang",
    "wof:placetype":"locality"
},
  "geometry": {"coordinates":[106.96299999999999,24.4467],"type":"Point"}
}