{
  "type": "Feature",
  "properties": {
    "gn:admin1_code":"11",
    "gn:asciiname":"Zhumutang",
    "gn:country_code":"CN",
    "gn:dem":190,
    "gn:feature_class":"P",
    "gn:feature_code":"PPL",
    "gn:name":"Zhumutang",
    "gn:population":0,
    "gn:timezone":"Asia/Shanghai",
    "iso:country":"CN",
    "name:zho_x_preferred":[
        "\u682a\u6728\u5858"
    ],
    "wof:name":"Zhumutang",
    "wof:placetype":"locality"
},
  "geometry": {"coordinates":[112.15168,26.82322000000001],"type":"Point"}
}