{
  "type": "Feature",
  "properties": {
    "gn:admin1_code":"3.0",
    "gn:asciiname":"Zhelin",
    "gn:country_code":"CN",
    "gn:dem":23,
    "gn:feature_class":"P",
    "gn:feature_code":"PPL",
    "gn:name":"Zhelin",
    "gn:population":0,
    "gn:timezone":"Asia/Shanghai",
    "iso:country":"CN",
    "name:und_x_variant":[
        "\u67d8\u6797"
    ],
    "wof:name":"Zhelin",
    "wof:placetype":"locality"
},
  "geometry": {"coordinates":[116.47918,29.8089],"type":"Point"}
}