{
  "type": "Feature",
  "properties": {
    "gn:admin1_code":"14.0",
    "gn:asciiname":"Sere",
    "gn:country_code":"CN",
    "gn:dem":4280,
    "gn:feature_class":"P",
    "gn:feature_code":"PPL",
    "gn:name":"Sere",
    "gn:population":0,
    "gn:timezone":"Asia/Urumqi",
    "iso:country":"CN",
    "name:ceb_x_preferred":[
        "Sere"
    ],
    "name:spa_x_preferred":[
        "Sere"
    ],
    "name:swe_x_preferred":[
        "Sere"
    ],
    "name:wln_x_preferred":[
        "Sere"
    ],
    "name:zho_x_preferred":[
        "\u8272\u70ed"
    ],
    "wof:name":"Sere",
    "wof:placetype":"locality"
},
  "geometry": {"coordinates":[91.89003,29.14558],"type":"Point"}
}