{
  "type": "Feature",
  "properties": {
    "gn:admin1_code":"16.0",
    "gn:asciiname":"Guangqin",
    "gn:country_code":"CN",
    "gn:dem":278,
    "gn:feature_class":"P",
    "gn:feature_code":"PPL",
    "gn:name":"Guangqin",
    "gn:population":0,
    "gn:timezone":"Asia/Shanghai",
    "iso:country":"CN",
    "name:zho_x_preferred":[
        "\u5149\u7434"
    ],
    "wof:name":"Guangqin",
    "wof:placetype":"locality"
},
  "geometry": {"coordinates":[106.911,23.6151],"type":"Point"}
}