{
  "type": "Feature",
  "properties": {
    "gn:admin1_code":"25.0",
    "gn:asciiname":"Xibaimahecun",
    "gn:country_code":"CN",
    "gn:dem":24,
    "gn:feature_class":"P",
    "gn:feature_code":"PPL",
    "gn:name":"Xibaimahecun",
    "gn:population":0,
    "gn:timezone":"Asia/Shanghai",
    "iso:country":"CN",
    "name:zho_x_preferred":[
        "\u897f\u767d\u9a6c\u6cb3\u6751"
    ],
    "wof:name":"Xibaimahecun",
    "wof:placetype":"locality"
},
  "geometry": {"coordinates":[119.69947000000001,35.76324],"type":"Point"}
}