{
  "type": "Feature",
  "properties": {
    "gn:admin1_code":"16.0",
    "gn:asciiname":"Shangzai",
    "gn:country_code":"CN",
    "gn:dem":183,
    "gn:feature_class":"P",
    "gn:feature_code":"PPL",
    "gn:name":"Shangzai",
    "gn:population":0,
    "gn:timezone":"Asia/Shanghai",
    "iso:country":"CN",
    "name:zho_x_preferred":[
        "\u4e0a\u518d"
    ],
    "wof:name":"Shangzai",
    "wof:placetype":"locality"
},
  "geometry": {"coordinates":[111.16200000000001,23.6981],"type":"Point"}
}