{
  "type": "Feature",
  "properties": {
    "gn:admin1_code":"26.0",
    "gn:asciiname":"Wujia Wancun",
    "gn:country_code":"CN",
    "gn:dem":979,
    "gn:feature_class":"P",
    "gn:feature_code":"PPL",
    "gn:name":"Wujia Wancun",
    "gn:population":0,
    "gn:timezone":"Asia/Shanghai",
    "iso:country":"CN",
    "name:zho_x_preferred":[
        "\u6b66\u5bb6\u6e7e\u6751"
    ],
    "wof:name":"Wujia Wancun",
    "wof:placetype":"locality"
},
  "geometry": {"coordinates":[110.59099999999999,38.3614],"type":"Point"}
}