{
  "type": "Feature",
  "properties": {
    "gn:admin1_code":"20.0",
    "gn:asciiname":"Mengwuzi Cangku",
    "gn:country_code":"CN",
    "gn:dem":394,
    "gn:feature_class":"P",
    "gn:feature_code":"PPL",
    "gn:name":"Mengwuzi Cangku",
    "gn:population":0,
    "gn:timezone":"Asia/Shanghai",
    "iso:country":"CN",
    "name:zho_x_preferred":[
        "\u76df\u7269\u8d44\u4ed3\u5e93"
    ],
    "wof:name":"Mengwuzi Cangku",
    "wof:placetype":"locality"
},
  "geometry": {"coordinates":[122.77746999999999,48.01298],"type":"Point"}
}