{
  "type": "Feature",
  "properties": {
    "gn:admin1_code":"15.0",
    "gn:asciiname":"Qinghe",
    "gn:country_code":"CN",
    "gn:dem":1687,
    "gn:feature_class":"P",
    "gn:feature_code":"PPL",
    "gn:name":"Qinghe",
    "gn:population":0,
    "gn:timezone":"Asia/Shanghai",
    "iso:country":"CN",
    "name:ceb_x_preferred":[
        "Qinghe"
    ],
    "name:deu_x_preferred":[
        "Qinghe"
    ],
    "name:fra_x_preferred":[
        "Qinghe"
    ],
    "name:nor_x_preferred":[
        "Qinghe"
    ],
    "name:rus_x_preferred":[
        "\u0426\u0438\u043d\u0445\u044d"
    ],
    "name:swe_x_preferred":[
        "Qinghe"
    ],
    "name:zho_x_preferred":[
        "\u6e05\u6cb3"
    ],
    "wof:name":"Qinghe",
    "wof:placetype":"locality"
},
  "geometry": {"coordinates":[103.854,37.5777],"type":"Point"}
}