{
  "type": "Feature",
  "properties": {
    "gn:admin1_code":"09",
    "gn:asciiname":"Chengzhuangzhai",
    "gn:cc2":"CN",
    "gn:country_code":"CN",
    "gn:dem":69,
    "gn:feature_class":"P",
    "gn:feature_code":"PPL",
    "gn:name":"Chengzhuangzhai",
    "gn:population":0,
    "gn:timezone":"Asia/Shanghai",
    "iso:country":"CN",
    "name:und_x_variant":[
        "Ch\u2019eng-chuang-chai",
        "Chengzhuangzhai"
    ],
    "wof:name":"Chengzhuangzhai",
    "wof:placetype":"locality"
},
  "geometry": {"coordinates":[115.13333,34.86667],"type":"Point"}
}