{
  "type": "Feature",
  "properties": {
    "gn:admin1_code":"33.0",
    "gn:asciiname":"Xialuoguquan",
    "gn:country_code":"CN",
    "gn:dem":1513,
    "gn:feature_class":"P",
    "gn:feature_code":"PPL",
    "gn:name":"Xialuoguquan",
    "gn:population":0,
    "gn:timezone":"Asia/Shanghai",
    "iso:country":"CN",
    "name:zho_x_preferred":[
        "\u4e0b\u9523\u9f13\u5708"
    ],
    "wof:name":"Xialuoguquan",
    "wof:placetype":"locality"
},
  "geometry": {"coordinates":[109.82946,31.54572000000001],"type":"Point"}
}