{
  "type": "Feature",
  "properties": {
    "gn:admin1_code":"19.0",
    "gn:asciiname":"Wanshengde",
    "gn:country_code":"CN",
    "gn:dem":149,
    "gn:feature_class":"P",
    "gn:feature_code":"PPL",
    "gn:name":"Wanshengde",
    "gn:population":0,
    "gn:timezone":"Asia/Shanghai",
    "iso:country":"CN",
    "name:zho_x_preferred":[
        "\u4e07\u80dc\u5fb7"
    ],
    "wof:name":"Wanshengde",
    "wof:placetype":"locality"
},
  "geometry": {"coordinates":[122.583,39.8536],"type":"Point"}
}