{
  "type": "Feature",
  "properties": {
    "gn:admin1_code":"30.0",
    "gn:asciiname":"Rongshuxia",
    "gn:country_code":"CN",
    "gn:dem":82,
    "gn:feature_class":"P",
    "gn:feature_code":"PPL",
    "gn:name":"Rongshuxia",
    "gn:population":0,
    "gn:timezone":"Asia/Shanghai",
    "iso:country":"CN",
    "name:zho_x_preferred":[
        "\u6995\u6811\u4e0b"
    ],
    "wof:name":"Rongshuxia",
    "wof:placetype":"locality"
},
  "geometry": {"coordinates":[113.41464000000001,24.65654],"type":"Point"}
}