{
  "type": "Feature",
  "properties": {
    "gn:admin1_code":"18",
    "gn:asciiname":"Yangchaba",
    "gn:country_code":"CN",
    "gn:dem":802,
    "gn:feature_class":"P",
    "gn:feature_code":"PPL",
    "gn:name":"Yangchaba",
    "gn:population":0,
    "gn:timezone":"Asia/Shanghai",
    "iso:country":"CN",
    "name:zho_x_preferred":[
        "\u7f8a\u53c9\u575d"
    ],
    "wof:name":"Yangchaba",
    "wof:placetype":"locality"
},
  "geometry": {"coordinates":[107.214,27.7754],"type":"Point"}
}