{
  "type": "Feature",
  "properties": {
    "gn:admin1_code":"32.0",
    "gn:asciiname":"Azhujianwu",
    "gn:country_code":"CN",
    "gn:dem":2200,
    "gn:feature_class":"P",
    "gn:feature_code":"PPL",
    "gn:name":"Azhujianwu",
    "gn:population":0,
    "gn:timezone":"Asia/Shanghai",
    "iso:country":"CN",
    "name:zho_x_preferred":[
        "\u554a\u52a9\u68c0\u4f0d"
    ],
    "wof:name":"Azhujianwu",
    "wof:placetype":"locality"
},
  "geometry": {"coordinates":[102.25960000000001,28.67552],"type":"Point"}
}