{
  "type": "Feature",
  "properties": {
    "gn:admin1_code":"12.0",
    "gn:asciiname":"Balihu Nongchang",
    "gn:country_code":"CN",
    "gn:dem":24,
    "gn:feature_class":"P",
    "gn:feature_code":"PPLF",
    "gn:name":"Balihu Nongchang",
    "gn:population":0,
    "gn:timezone":"Asia/Shanghai",
    "iso:country":"CN",
    "name:und_x_variant":[
        "\u575d\u91cc\u519c\u573a"
    ],
    "wof:name":"Balihu Nongchang",
    "wof:placetype":"locality"
},
  "geometry": {"coordinates":[115.34263,30.13243],"type":"Point"}
}