{
  "type": "Feature",
  "properties": {
    "gn:admin1_code":"26",
    "gn:asciiname":"Mujiangwang",
    "gn:country_code":"CN",
    "gn:dem":421,
    "gn:feature_class":"P",
    "gn:feature_code":"PPL",
    "gn:name":"Mujiangwang",
    "gn:population":0,
    "gn:timezone":"Asia/Shanghai",
    "iso:country":"CN",
    "name:und_x_variant":[
        "\u6728\u5320\u738b"
    ],
    "wof:name":"Mujiangwang",
    "wof:placetype":"locality"
},
  "geometry": {"coordinates":[109.05361000000001,34.25528],"type":"Point"}
}