{
  "type": "Feature",
  "properties": {
    "gn:admin1_code":"32.0",
    "gn:asciiname":"Jibuluo",
    "gn:country_code":"CN",
    "gn:dem":2549,
    "gn:feature_class":"P",
    "gn:feature_code":"PPL",
    "gn:name":"Jibuluo",
    "gn:population":0,
    "gn:timezone":"Asia/Shanghai",
    "iso:country":"CN",
    "name:zho_x_preferred":[
        "\u57fa\u8865\u7f57"
    ],
    "wof:name":"Jibuluo",
    "wof:placetype":"locality"
},
  "geometry": {"coordinates":[103.111,28.4892],"type":"Point"}
}