{
  "type": "Feature",
  "properties": {
    "gn:admin1_code":"15.0",
    "gn:asciiname":"Junma Erchang Sandui",
    "gn:country_code":"CN",
    "gn:dem":2947,
    "gn:feature_class":"P",
    "gn:feature_code":"PPLF",
    "gn:name":"Junma Erchang Sandui",
    "gn:population":0,
    "gn:timezone":"Asia/Shanghai",
    "iso:country":"CN",
    "name:zho_x_preferred":[
        "\u519b\u9a6c\u4e8c\u573a\u4e09\u961f"
    ],
    "wof:name":"Junma Erchang Sandui",
    "wof:placetype":"locality"
},
  "geometry": {"coordinates":[101.16200000000001,38.1688],"type":"Point"}
}