{
  "type": "Feature",
  "properties": {
    "gn:admin1_code":"30.0",
    "gn:asciiname":"Dongwei",
    "gn:country_code":"CN",
    "gn:dem":11,
    "gn:feature_class":"P",
    "gn:feature_code":"PPL",
    "gn:name":"Dongwei",
    "gn:population":0,
    "gn:timezone":"Asia/Shanghai",
    "iso:country":"CN",
    "name:zho_x_preferred":[
        "\u6771\u570d"
    ],
    "wof:name":"Dongwei",
    "wof:placetype":"locality"
},
  "geometry": {"coordinates":[112.78104999999999,23.04289],"type":"Point"}
}