{
  "type": "Feature",
  "properties": {
    "gn:admin1_code":"02",
    "gn:asciiname":"Gushancun",
    "gn:country_code":"CN",
    "gn:dem":73,
    "gn:feature_class":"P",
    "gn:feature_code":"PPL",
    "gn:name":"Gushancun",
    "gn:population":0,
    "gn:timezone":"Asia/Shanghai",
    "iso:country":"CN",
    "name:und_x_variant":[
        "Chin-shan-t\u2019ou",
        "Gushan",
        "Gushancun"
    ],
    "name:zho_x_preferred":[
        "\u5b64\u5c71"
    ],
    "name:zho_x_variant":[
        "\u5b64\u5c71\u6751"
    ],
    "wof:name":"Gushancun",
    "wof:placetype":"locality"
},
  "geometry": {"coordinates":[120.79107999999999,28.32312],"type":"Point"}
}