{
  "type": "Feature",
  "properties": {
    "gn:admin1_code":"24.0",
    "gn:asciiname":"Xixingzhuang",
    "gn:country_code":"CN",
    "gn:dem":478,
    "gn:feature_class":"P",
    "gn:feature_code":"PPL",
    "gn:name":"Xixingzhuang",
    "gn:population":0,
    "gn:timezone":"Asia/Shanghai",
    "iso:country":"CN",
    "name:und_x_variant":[
        "\u897f\u884c\u5e84"
    ],
    "wof:name":"Xixingzhuang",
    "wof:placetype":"locality"
},
  "geometry": {"coordinates":[111.10025,35.69045],"type":"Point"}
}