{
  "type": "Feature",
  "properties": {
    "gn:admin1_code":"3.0",
    "gn:asciiname":"Meitangcun",
    "gn:country_code":"CN",
    "gn:dem":25,
    "gn:feature_class":"P",
    "gn:feature_code":"PPL",
    "gn:name":"Meitangcun",
    "gn:population":0,
    "gn:timezone":"Asia/Shanghai",
    "iso:country":"CN",
    "name:und_x_variant":[
        "\u6885\u5858\u6751"
    ],
    "wof:name":"Meitangcun",
    "wof:placetype":"locality"
},
  "geometry": {"coordinates":[116.62548,28.80465],"type":"Point"}
}