{
  "type": "Feature",
  "properties": {
    "gn:admin1_code":"02",
    "gn:asciiname":"Zha Muchang",
    "gn:country_code":"CN",
    "gn:dem":27,
    "gn:feature_class":"P",
    "gn:feature_code":"PPLF",
    "gn:name":"Zha Muchang",
    "gn:population":0,
    "gn:timezone":"Asia/Shanghai",
    "iso:country":"CN",
    "name:zho_x_preferred":[
        "\u86b1\u76ee\u5382"
    ],
    "wof:name":"Zha Muchang",
    "wof:placetype":"locality"
},
  "geometry": {"coordinates":[121.09268,27.82092],"type":"Point"}
}