{
  "type": "Feature",
  "properties": {
    "gn:admin1_code":"5.0",
    "gn:asciiname":"Wurenban",
    "gn:country_code":"CN",
    "gn:dem":348,
    "gn:feature_class":"P",
    "gn:feature_code":"PPL",
    "gn:name":"Wurenban",
    "gn:population":0,
    "gn:timezone":"Asia/Shanghai",
    "iso:country":"CN",
    "name:und_x_variant":[
        "\u4e94\u4eba\u73ed"
    ],
    "wof:name":"Wurenban",
    "wof:placetype":"locality"
},
  "geometry": {"coordinates":[125.66952999999999,41.41725],"type":"Point"}
}