{
  "type": "Feature",
  "properties": {
    "gn:admin1_code":"9.0",
    "gn:asciiname":"Hualiba",
    "gn:country_code":"CN",
    "gn:dem":164,
    "gn:feature_class":"P",
    "gn:feature_code":"PPL",
    "gn:name":"Hualiba",
    "gn:population":0,
    "gn:timezone":"Asia/Shanghai",
    "iso:country":"CN",
    "name:zho_x_preferred":[
        "\u6866\u680e\u6252"
    ],
    "wof:name":"Hualiba",
    "wof:placetype":"locality"
},
  "geometry": {"coordinates":[111.70419,32.65503],"type":"Point"}
}