{
  "type": "Feature",
  "properties": {
    "gn:admin1_code":"15.0",
    "gn:asciiname":"Shaocha",
    "gn:country_code":"CN",
    "gn:dem":1994,
    "gn:feature_class":"P",
    "gn:feature_code":"PPL",
    "gn:name":"Shaocha",
    "gn:population":0,
    "gn:timezone":"Asia/Shanghai",
    "iso:country":"CN",
    "name:und_x_variant":[
        "\u7a0d\u5c94"
    ],
    "wof:name":"Shaocha",
    "wof:placetype":"locality"
},
  "geometry": {"coordinates":[105.08175,35.72153],"type":"Point"}
}