{
  "type": "Feature",
  "properties": {
    "gn:admin1_code":"11",
    "gn:asciiname":"Jinjiachong",
    "gn:country_code":"CN",
    "gn:dem":247,
    "gn:feature_class":"P",
    "gn:feature_code":"PPL",
    "gn:name":"Jinjiachong",
    "gn:population":0,
    "gn:timezone":"Asia/Shanghai",
    "iso:country":"CN",
    "name:und_x_variant":[
        "Chin-chia",
        "Jinjia",
        "Jinjiachong"
    ],
    "name:zho_x_preferred":[
        "\u91d1\u5bb6\u51b2"
    ],
    "wof:name":"Jinjiachong",
    "wof:placetype":"locality"
},
  "geometry": {"coordinates":[111.9859,27.25208],"type":"Point"}
}