{
  "type": "Feature",
  "properties": {
    "gn:admin1_code":"24.0",
    "gn:asciiname":"Shenyugou",
    "gn:country_code":"CN",
    "gn:dem":940,
    "gn:feature_class":"P",
    "gn:feature_code":"PPL",
    "gn:name":"Shenyugou",
    "gn:population":0,
    "gn:timezone":"Asia/Shanghai",
    "iso:country":"CN",
    "name:zho_x_preferred":[
        "\u795e\u5cea\u6c9f"
    ],
    "wof:name":"Shenyugou",
    "wof:placetype":"locality"
},
  "geometry": {"coordinates":[111.02528999999998,37.80438],"type":"Point"}
}