{
  "type": "Feature",
  "properties": {
    "gn:admin1_code":"30.0",
    "gn:asciiname":"Chatangxia",
    "gn:country_code":"CN",
    "gn:dem":421,
    "gn:feature_class":"P",
    "gn:feature_code":"PPL",
    "gn:name":"Chatangxia",
    "gn:population":0,
    "gn:timezone":"Asia/Shanghai",
    "iso:country":"CN",
    "name:zho_x_preferred":[
        "\u8336\u5858\u4e0b"
    ],
    "wof:name":"Chatangxia",
    "wof:placetype":"locality"
},
  "geometry": {"coordinates":[114.64068,25.15285],"type":"Point"}
}