{
  "type": "Feature",
  "properties": {
    "gn:admin1_code":"14.0",
    "gn:asciiname":"Zhalongtangcun",
    "gn:country_code":"CN",
    "gn:dem":4532,
    "gn:feature_class":"P",
    "gn:feature_code":"PPL",
    "gn:name":"Zhalongtangcun",
    "gn:population":0,
    "gn:timezone":"Asia/Urumqi",
    "iso:country":"CN",
    "name:zho_x_preferred":[
        "\u624e\u9686\u5858\u6751"
    ],
    "wof:name":"Zhalongtangcun",
    "wof:placetype":"locality"
},
  "geometry": {"coordinates":[93.56433,32.19464],"type":"Point"}
}