{
  "type": "Feature",
  "properties": {
    "gn:admin1_code":"29",
    "gn:asciiname":"Juwei",
    "gn:country_code":"CN",
    "gn:dem":1730,
    "gn:feature_class":"P",
    "gn:feature_code":"PPL",
    "gn:name":"Juwei",
    "gn:population":0,
    "gn:timezone":"Asia/Shanghai",
    "iso:country":"CN",
    "name:zho_x_preferred":[
        "\u5c45\u536b"
    ],
    "wof:name":"Juwei",
    "wof:placetype":"locality"
},
  "geometry": {"coordinates":[102.7432,24.32772000000001],"type":"Point"}
}