{
  "type": "Feature",
  "properties": {
    "gn:admin1_code":"25.0",
    "gn:asciiname":"Tangshantoucun",
    "gn:country_code":"CN",
    "gn:dem":181,
    "gn:feature_class":"P",
    "gn:feature_code":"PPL",
    "gn:name":"Tangshantoucun",
    "gn:population":0,
    "gn:timezone":"Asia/Shanghai",
    "iso:country":"CN",
    "name:zho_x_preferred":[
        "\u5510\u5c71\u5934\u6751"
    ],
    "wof:name":"Tangshantoucun",
    "wof:placetype":"locality"
},
  "geometry": {"coordinates":[120.85223999999999,37.231],"type":"Point"}
}