{
  "type": "Feature",
  "properties": {
    "gn:admin1_code":"16",
    "gn:asciiname":"Sishantou",
    "gn:country_code":"CN",
    "gn:dem":190,
    "gn:feature_class":"P",
    "gn:feature_code":"PPL",
    "gn:name":"Sishantou",
    "gn:population":0,
    "gn:timezone":"Asia/Shanghai",
    "iso:country":"CN",
    "name:zho_x_preferred":[
        "\u56db\u5c71\u5934"
    ],
    "wof:name":"Sishantou",
    "wof:placetype":"locality"
},
  "geometry": {"coordinates":[110.976,26.0351],"type":"Point"}
}