{
  "type": "Feature",
  "properties": {
    "gn:admin1_code":"4.0",
    "gn:asciiname":"Liujia Xuzhuang",
    "gn:country_code":"CN",
    "gn:dem":10,
    "gn:feature_class":"P",
    "gn:feature_code":"PPL",
    "gn:name":"Liujia Xuzhuang",
    "gn:population":0,
    "gn:timezone":"Asia/Shanghai",
    "iso:country":"CN",
    "name:zho_x_preferred":[
        "\u5218\u5bb6\u5729\u5e84"
    ],
    "wof:name":"Liujia Xuzhuang",
    "wof:placetype":"locality"
},
  "geometry": {"coordinates":[119.10655,32.85931],"type":"Point"}
}