{
  "type": "Feature",
  "properties": {
    "gn:admin1_code":"25",
    "gn:asciiname":"Shiqiaogoudong",
    "gn:country_code":"CN",
    "gn:dem":31,
    "gn:feature_class":"P",
    "gn:feature_code":"PPL",
    "gn:name":"Shiqiaogoudong",
    "gn:population":0,
    "gn:timezone":"Asia/Shanghai",
    "iso:country":"CN",
    "name:zho_x_preferred":[
        "\u77f3\u6865\u6c9f\u4e1c"
    ],
    "wof:name":"Shiqiaogoudong",
    "wof:placetype":"locality"
},
  "geometry": {"coordinates":[119.789,36.9082],"type":"Point"}
}