{
  "type": "Feature",
  "properties": {
    "gn:admin1_code":"23.0",
    "gn:asciiname":"Dishan",
    "gn:country_code":"CN",
    "gn:dem":11,
    "gn:feature_class":"P",
    "gn:feature_code":"PPL",
    "gn:name":"Dishan",
    "gn:population":0,
    "gn:timezone":"Asia/Shanghai",
    "iso:country":"CN",
    "name:zho_x_preferred":[
        "Dishan"
    ],
    "name:zho_x_variant":[
        "\u837b\u5c71"
    ],
    "wof:name":"Dishan",
    "wof:placetype":"locality"
},
  "geometry": {"coordinates":[121.52531999999999,31.14504],"type":"Point"}
}