{
  "type": "Feature",
  "properties": {
    "gn:admin1_code":"9.0",
    "gn:asciiname":"Renqiao",
    "gn:country_code":"CN",
    "gn:dem":66,
    "gn:feature_class":"P",
    "gn:feature_code":"PPL",
    "gn:name":"Renqiao",
    "gn:population":0,
    "gn:timezone":"Asia/Shanghai",
    "iso:country":"CN",
    "name:und_x_variant":[
        "\u4efb\u6865"
    ],
    "name:zho_x_preferred":[
        "\u4efb\u6865"
    ],
    "wof:name":"Renqiao",
    "wof:placetype":"locality"
},
  "geometry": {"coordinates":[114.01112999999999,33.20282],"type":"Point"}
}