{
  "type": "Feature",
  "properties": {
    "gn:admin1_code":"05",
    "gn:asciiname":"Liujiajie",
    "gn:cc2":"CN",
    "gn:country_code":"CN",
    "gn:dem":413,
    "gn:feature_class":"P",
    "gn:feature_code":"PPL",
    "gn:name":"Liujiajie",
    "gn:population":0,
    "gn:timezone":"Asia/Shanghai",
    "iso:country":"CN",
    "name:und_x_variant":[
        "Erdaogou",
        "Liujiajie"
    ],
    "wof:name":"Liujiajie",
    "wof:placetype":"locality"
},
  "geometry": {"coordinates":[125.74333,42.08361],"type":"Point"}
}