{
  "type": "Feature",
  "properties": {
    "gn:admin1_code":"29.0",
    "gn:asciiname":"Songzishu",
    "gn:country_code":"CN",
    "gn:dem":2048,
    "gn:feature_class":"P",
    "gn:feature_code":"PPL",
    "gn:name":"Songzishu",
    "gn:population":0,
    "gn:timezone":"Asia/Shanghai",
    "iso:country":"CN",
    "name:zho_x_preferred":[
        "\u677e\u5b50\u6811"
    ],
    "wof:name":"Songzishu",
    "wof:placetype":"locality"
},
  "geometry": {"coordinates":[99.92059999999999,24.6617],"type":"Point"}
}