{
  "type": "Feature",
  "properties": {
    "gn:admin1_code":"3",
    "gn:asciiname":"Shangbeitou",
    "gn:country_code":"CN",
    "gn:dem":170,
    "gn:feature_class":"P",
    "gn:feature_code":"PPL",
    "gn:name":"Shangbeitou",
    "gn:population":0,
    "gn:timezone":"Asia/Shanghai",
    "iso:country":"CN",
    "name:zho_x_preferred":[
        "\u4e0a\u9642\u5934"
    ],
    "wof:name":"Shangbeitou",
    "wof:placetype":"locality"
},
  "geometry": {"coordinates":[114.937,25.2796],"type":"Point"}
}