{
  "type": "Feature",
  "properties": {
    "gn:admin1_code":"4.0",
    "gn:asciiname":"Qinfengcun",
    "gn:country_code":"CN",
    "gn:dem":1,
    "gn:feature_class":"P",
    "gn:feature_code":"PPL",
    "gn:name":"Qinfengcun",
    "gn:population":0,
    "gn:timezone":"Asia/Shanghai",
    "iso:country":"CN",
    "name:zho_x_preferred":[
        "\u52e4\u4e30\u6751"
    ],
    "wof:name":"Qinfengcun",
    "wof:placetype":"locality"
},
  "geometry": {"coordinates":[119.30871999999999,32.1817],"type":"Point"}
}