{
  "type": "Feature",
  "properties": {
    "gn:admin1_code":"11.0",
    "gn:asciiname":"Yuanzhushan",
    "gn:country_code":"CN",
    "gn:dem":153,
    "gn:feature_class":"P",
    "gn:feature_code":"PPL",
    "gn:name":"Yuanzhushan",
    "gn:population":0,
    "gn:timezone":"Asia/Shanghai",
    "iso:country":"CN",
    "name:zho_x_preferred":[
        "\u56ed\u682a\u5c71"
    ],
    "wof:name":"Yuanzhushan",
    "wof:placetype":"locality"
},
  "geometry": {"coordinates":[111.80197,26.8297],"type":"Point"}
}