{
  "type": "Feature",
  "properties": {
    "gn:admin1_code":"26.0",
    "gn:asciiname":"Yangjiayuan",
    "gn:country_code":"CN",
    "gn:dem":995,
    "gn:feature_class":"P",
    "gn:feature_code":"PPL",
    "gn:name":"Yangjiayuan",
    "gn:population":0,
    "gn:timezone":"Asia/Shanghai",
    "iso:country":"CN",
    "name:und_x_variant":[
        "\u6768\u5bb6\u9662"
    ],
    "wof:name":"Yangjiayuan",
    "wof:placetype":"locality"
},
  "geometry": {"coordinates":[105.95884,33.08932],"type":"Point"}
}