{
  "type": "Feature",
  "properties": {
    "gn:admin1_code":"16.0",
    "gn:asciiname":"Pailing",
    "gn:country_code":"CN",
    "gn:dem":47,
    "gn:feature_class":"P",
    "gn:feature_code":"PPL",
    "gn:name":"Pailing",
    "gn:population":0,
    "gn:timezone":"Asia/Shanghai",
    "iso:country":"CN",
    "name:zho_x_preferred":[
        "\u6392\u5cad"
    ],
    "wof:name":"Pailing",
    "wof:placetype":"locality"
},
  "geometry": {"coordinates":[109.756,22.1035],"type":"Point"}
}