{
  "type": "Feature",
  "properties": {
    "gn:admin1_code":"30.0",
    "gn:asciiname":"Xiazhongcun",
    "gn:country_code":"CN",
    "gn:dem":10,
    "gn:feature_class":"P",
    "gn:feature_code":"PPL",
    "gn:name":"Xiazhongcun",
    "gn:population":0,
    "gn:timezone":"Asia/Shanghai",
    "iso:country":"CN",
    "name:zho_x_preferred":[
        "\u971e\u4e2d\u6751"
    ],
    "wof:name":"Xiazhongcun",
    "wof:placetype":"locality"
},
  "geometry": {"coordinates":[117.01627999999999,23.66851],"type":"Point"}
}