{
  "type": "Feature",
  "properties": {
    "gn:admin1_code":"16.0",
    "gn:asciiname":"Zhangu",
    "gn:country_code":"CN",
    "gn:dem":280,
    "gn:feature_class":"P",
    "gn:feature_code":"PPL",
    "gn:name":"Zhangu",
    "gn:population":0,
    "gn:timezone":"Asia/Shanghai",
    "iso:country":"CN",
    "name:zho_x_preferred":[
        "\u77bb\u987e"
    ],
    "wof:name":"Zhangu",
    "wof:placetype":"locality"
},
  "geometry": {"coordinates":[109.17100000000001,22.8473],"type":"Point"}
}