{
  "type": "Feature",
  "properties": {
    "gn:admin1_code":"32.0",
    "gn:asciiname":"Shizi Shuping",
    "gn:country_code":"CN",
    "gn:dem":1089,
    "gn:feature_class":"P",
    "gn:feature_code":"PPL",
    "gn:name":"Shizi Shuping",
    "gn:population":0,
    "gn:timezone":"Asia/Shanghai",
    "iso:country":"CN",
    "name:zho_x_preferred":[
        "\u67ff\u5b50\u6811\u576a"
    ],
    "wof:name":"Shizi Shuping",
    "wof:placetype":"locality"
},
  "geometry": {"coordinates":[107.685,31.7603],"type":"Point"}
}