{
  "type": "Feature",
  "properties": {
    "gn:admin1_code":"10",
    "gn:asciiname":"Yizhuang",
    "gn:country_code":"CN",
    "gn:dem":46,
    "gn:feature_class":"P",
    "gn:feature_code":"PPL",
    "gn:name":"Yizhuang",
    "gn:population":0,
    "gn:timezone":"Asia/Shanghai",
    "iso:country":"CN",
    "name:zho_x_preferred":[
        "\u8fe4\u5e84"
    ],
    "wof:name":"Yizhuang",
    "wof:placetype":"locality"
},
  "geometry": {"coordinates":[115.20253,36.40693],"type":"Point"}
}