{
  "type": "Feature",
  "properties": {
    "gn:admin1_code":"9.0",
    "gn:asciiname":"Wozheng",
    "gn:country_code":"CN",
    "gn:dem":166,
    "gn:feature_class":"P",
    "gn:feature_code":"PPL",
    "gn:name":"Wozheng",
    "gn:population":0,
    "gn:timezone":"Asia/Shanghai",
    "iso:country":"CN",
    "name:zho_x_preferred":[
        "\u7a9d\u90d1"
    ],
    "wof:name":"Wozheng",
    "wof:placetype":"locality"
},
  "geometry": {"coordinates":[113.58076,34.48093],"type":"Point"}
}