{
  "type": "Feature",
  "properties": {
    "gn:admin1_code":"8.0",
    "gn:asciiname":"Yongshengcun",
    "gn:country_code":"CN",
    "gn:dem":164,
    "gn:feature_class":"P",
    "gn:feature_code":"PPL",
    "gn:name":"Yongshengcun",
    "gn:population":0,
    "gn:timezone":"Asia/Shanghai",
    "iso:country":"CN",
    "name:zho_x_preferred":[
        "\u6c38\u751f\u6751"
    ],
    "wof:name":"Yongshengcun",
    "wof:placetype":"locality"
},
  "geometry": {"coordinates":[131.39396000000002,45.30343],"type":"Point"}
}