{
  "type": "Feature",
  "properties": {
    "gn:admin1_code":"4.0",
    "gn:asciiname":"Songchaocun",
    "gn:country_code":"CN",
    "gn:dem":7,
    "gn:feature_class":"P",
    "gn:feature_code":"PPL",
    "gn:name":"Songchaocun",
    "gn:population":0,
    "gn:timezone":"Asia/Shanghai",
    "iso:country":"CN",
    "name:zho_x_preferred":[
        "\u5b8b\u6f6e\u6751"
    ],
    "wof:name":"Songchaocun",
    "wof:placetype":"locality"
},
  "geometry": {"coordinates":[119.01691,33.42188],"type":"Point"}
}