{
  "type": "Feature",
  "properties": {
    "gn:admin1_code":"31",
    "gn:asciiname":"Guangba Nongchang",
    "gn:country_code":"CN",
    "gn:dem":153,
    "gn:feature_class":"P",
    "gn:feature_code":"PPLF",
    "gn:name":"Guangba Nongchang",
    "gn:population":0,
    "gn:timezone":"Asia/Shanghai",
    "iso:country":"CN",
    "name:und_x_variant":[
        "\u5e7f\u575d\u519c\u573a"
    ],
    "wof:name":"Guangba Nongchang",
    "wof:placetype":"locality"
},
  "geometry": {"coordinates":[108.91722,19.07722],"type":"Point"}
}