{
  "type": "Feature",
  "properties": {
    "gn:admin1_code":"3.0",
    "gn:asciiname":"Yangmeigang",
    "gn:country_code":"CN",
    "gn:dem":88,
    "gn:feature_class":"P",
    "gn:feature_code":"PPL",
    "gn:name":"Yangmeigang",
    "gn:population":0,
    "gn:timezone":"Asia/Shanghai",
    "iso:country":"CN",
    "name:und_x_variant":[
        "\u6768\u6885\u5c97"
    ],
    "wof:name":"Yangmeigang",
    "wof:placetype":"locality"
},
  "geometry": {"coordinates":[115.86967,27.67242],"type":"Point"}
}