{
  "type": "Feature",
  "properties": {
    "gn:admin1_code":"29.0",
    "gn:asciiname":"Mayuangou",
    "gn:country_code":"CN",
    "gn:dem":810,
    "gn:feature_class":"P",
    "gn:feature_code":"PPL",
    "gn:name":"Mayuangou",
    "gn:population":0,
    "gn:timezone":"Asia/Shanghai",
    "iso:country":"CN",
    "name:zho_x_preferred":[
        "\u9ebb\u56ed\u6c9f"
    ],
    "wof:name":"Mayuangou",
    "wof:placetype":"locality"
},
  "geometry": {"coordinates":[104.625,27.7903],"type":"Point"}
}