{
  "type": "Feature",
  "properties": {
    "gn:admin1_code":"32.0",
    "gn:asciiname":"Gongjiagou",
    "gn:country_code":"CN",
    "gn:dem":346,
    "gn:feature_class":"P",
    "gn:feature_code":"PPL",
    "gn:name":"Gongjiagou",
    "gn:population":0,
    "gn:timezone":"Asia/Shanghai",
    "iso:country":"CN",
    "name:zho_x_preferred":[
        "\u9f9a\u5bb6\u6c9f"
    ],
    "wof:name":"Gongjiagou",
    "wof:placetype":"locality"
},
  "geometry": {"coordinates":[105.21899999999999,30.1578],"type":"Point"}
}