{
  "type": "Feature",
  "properties": {
    "gn:admin1_code":"31",
    "gn:asciiname":"Hewen",
    "gn:country_code":"CN",
    "gn:dem":94,
    "gn:feature_class":"P",
    "gn:feature_code":"PPL",
    "gn:name":"Hewen",
    "gn:population":0,
    "gn:timezone":"Asia/Shanghai",
    "iso:country":"CN",
    "name:und_x_variant":[
        "\u548c\u6587"
    ],
    "wof:name":"Hewen",
    "wof:placetype":"locality"
},
  "geometry": {"coordinates":[109.89796,19.79173],"type":"Point"}
}