{
  "type": "Feature",
  "properties": {
    "gn:admin1_code":"15.0",
    "gn:asciiname":"Houzhi",
    "gn:country_code":"CN",
    "gn:dem":2789,
    "gn:feature_class":"P",
    "gn:feature_code":"PPL",
    "gn:name":"Houzhi",
    "gn:population":0,
    "gn:timezone":"Asia/Shanghai",
    "iso:country":"CN",
    "name:und_x_variant":[
        "\u540e\u6cbb"
    ],
    "wof:name":"Houzhi",
    "wof:placetype":"locality"
},
  "geometry": {"coordinates":[104.62567,34.33962],"type":"Point"}
}