{
  "type": "Feature",
  "properties": {
    "gn:admin1_code":"19.0",
    "gn:asciiname":"Lamaban",
    "gn:country_code":"CN",
    "gn:dem":192,
    "gn:feature_class":"P",
    "gn:feature_code":"PPL",
    "gn:name":"Lamaban",
    "gn:population":0,
    "gn:timezone":"Asia/Shanghai",
    "iso:country":"CN",
    "name:und_x_variant":[
        "\u5587\u561b\u677f"
    ],
    "name:zho_x_preferred":[
        "\u5587\u561b\u677f"
    ],
    "wof:name":"Lamaban",
    "wof:placetype":"locality"
},
  "geometry": {"coordinates":[121.3489,41.96241],"type":"Point"}
}