{
  "type": "Feature",
  "properties": {
    "gn:admin1_code":"3.0",
    "gn:asciiname":"Xiaxiongcun",
    "gn:country_code":"CN",
    "gn:dem":23,
    "gn:feature_class":"P",
    "gn:feature_code":"PPL",
    "gn:name":"Xiaxiongcun",
    "gn:population":0,
    "gn:timezone":"Asia/Shanghai",
    "iso:country":"CN",
    "name:und_x_variant":[
        "\u4e0b\u718a\u6751"
    ],
    "wof:name":"Xiaxiongcun",
    "wof:placetype":"locality"
},
  "geometry": {"coordinates":[116.1422,28.47169],"type":"Point"}
}