{
  "type": "Feature",
  "properties": {
    "gn:admin1_code":"3",
    "gn:asciiname":"Nanmushi",
    "gn:country_code":"CN",
    "gn:dem":193,
    "gn:feature_class":"P",
    "gn:feature_code":"PPL",
    "gn:name":"Nanmushi",
    "gn:population":0,
    "gn:timezone":"Asia/Shanghai",
    "iso:country":"CN",
    "name:zho_x_preferred":[
        "\u5357\u6728\u77f3"
    ],
    "wof:name":"Nanmushi",
    "wof:placetype":"locality"
},
  "geometry": {"coordinates":[114.55,26.6724],"type":"Point"}
}