{
  "type": "Feature",
  "properties": {
    "gn:admin1_code":"14.0",
    "gn:asciiname":"Niangdacun",
    "gn:country_code":"CN",
    "gn:dem":4033,
    "gn:feature_class":"P",
    "gn:feature_code":"PPL",
    "gn:name":"Niangdacun",
    "gn:population":0,
    "gn:timezone":"Asia/Urumqi",
    "iso:country":"CN",
    "name:zho_x_preferred":[
        "\u5a18\u8fbe\u6751"
    ],
    "wof:name":"Niangdacun",
    "wof:placetype":"locality"
},
  "geometry": {"coordinates":[93.44647999999999,31.51816],"type":"Point"}
}