{
  "type": "Feature",
  "properties": {
    "gn:admin1_code":"22.0",
    "gn:asciiname":"Caijiazhuangcun",
    "gn:country_code":"CN",
    "gn:dem":96,
    "gn:feature_class":"P",
    "gn:feature_code":"PPL",
    "gn:name":"Caijiazhuangcun",
    "gn:population":0,
    "gn:timezone":"Asia/Shanghai",
    "iso:country":"CN",
    "name:zho_x_preferred":[
        "\u8521\u5bb6\u5e84\u6751"
    ],
    "wof:name":"Caijiazhuangcun",
    "wof:placetype":"locality"
},
  "geometry": {"coordinates":[115.72355,39.54823],"type":"Point"}
}