{
  "type": "Feature",
  "properties": {
    "gn:admin1_code":"19.0",
    "gn:asciiname":"Jixiancun",
    "gn:country_code":"CN",
    "gn:dem":34,
    "gn:feature_class":"P",
    "gn:feature_code":"PPL",
    "gn:name":"Jixiancun",
    "gn:population":0,
    "gn:timezone":"Asia/Shanghai",
    "iso:country":"CN",
    "name:zho_x_preferred":[
        "\u96c6\u8d24\u6751"
    ],
    "wof:name":"Jixiancun",
    "wof:placetype":"locality"
},
  "geometry": {"coordinates":[123.178,41.8138],"type":"Point"}
}