{
  "type": "Feature",
  "properties": {
    "gn:admin1_code":"15.0",
    "gn:asciiname":"Tangda",
    "gn:country_code":"CN",
    "gn:dem":3178,
    "gn:feature_class":"P",
    "gn:feature_code":"PPL",
    "gn:name":"Tangda",
    "gn:population":0,
    "gn:timezone":"Asia/Shanghai",
    "iso:country":"CN",
    "name:und_x_variant":[
        "\u5510\u8fbe"
    ],
    "wof:name":"Tangda",
    "wof:placetype":"locality"
},
  "geometry": {"coordinates":[102.91224,35.19929000000001],"type":"Point"}
}