{
  "type": "Feature",
  "properties": {
    "gn:admin1_code":"25",
    "gn:asciiname":"Dongshimen",
    "gn:country_code":"CN",
    "gn:dem":238,
    "gn:feature_class":"P",
    "gn:feature_code":"PPL",
    "gn:name":"Dongshimen",
    "gn:population":0,
    "gn:timezone":"Asia/Shanghai",
    "iso:country":"CN",
    "name:zho_x_preferred":[
        "\u4e1c\u77f3\u95e8"
    ],
    "wof:name":"Dongshimen",
    "wof:placetype":"locality"
},
  "geometry": {"coordinates":[119.13,35.6175],"type":"Point"}
}