{
  "type": "Feature",
  "properties": {
    "gn:admin1_code":"07",
    "gn:asciiname":"Luofang",
    "gn:country_code":"CN",
    "gn:dem":372,
    "gn:feature_class":"P",
    "gn:feature_code":"PPLA4",
    "gn:name":"Luofang",
    "gn:population":0,
    "gn:timezone":"Asia/Shanghai",
    "iso:country":"CN",
    "name:und_x_variant":[
        "Lo-fang",
        "Luofang",
        "\u7f57\u574a",
        "Luofang Xiang",
        "\u7f57\u574a\u4e61"
    ],
    "wof:name":"Luofang",
    "wof:placetype":"locality"
},
  "geometry": {"coordinates":[116.68368999999998,25.75068],"type":"Point"}
}