{
  "type": "Feature",
  "properties": {
    "gn:admin1_code":"4.0",
    "gn:asciiname":"Qiangaocun",
    "gn:country_code":"CN",
    "gn:dem":60,
    "gn:feature_class":"P",
    "gn:feature_code":"PPL",
    "gn:name":"Qiangaocun",
    "gn:population":0,
    "gn:timezone":"Asia/Shanghai",
    "iso:country":"CN",
    "name:zho_x_preferred":[
        "\u524d\u9ad8\u6751"
    ],
    "wof:name":"Qiangaocun",
    "wof:placetype":"locality"
},
  "geometry": {"coordinates":[117.352,34.4727],"type":"Point"}
}