{
  "type": "Feature",
  "properties": {
    "gn:admin1_code":"26.0",
    "gn:asciiname":"Houxigou",
    "gn:country_code":"CN",
    "gn:dem":1064,
    "gn:feature_class":"P",
    "gn:feature_code":"PPL",
    "gn:name":"Houxigou",
    "gn:population":0,
    "gn:timezone":"Asia/Shanghai",
    "iso:country":"CN",
    "name:zho_x_preferred":[
        "\u540e\u897f\u6c9f"
    ],
    "wof:name":"Houxigou",
    "wof:placetype":"locality"
},
  "geometry": {"coordinates":[109.90192999999999,36.40925],"type":"Point"}
}