{
  "type": "Feature",
  "properties": {
    "gn:admin1_code":"30",
    "gn:asciiname":"Zhengdong",
    "gn:country_code":"CN",
    "gn:dem":624,
    "gn:feature_class":"P",
    "gn:feature_code":"PPL",
    "gn:name":"Zhengdong",
    "gn:population":0,
    "gn:timezone":"Asia/Urumqi",
    "iso:country":"CN",
    "name:zho_x_preferred":[
        "\u6b63\u578c"
    ],
    "wof:name":"Zhengdong",
    "wof:placetype":"locality"
},
  "geometry": {"coordinates":[111.15013999999999,21.98452],"type":"Point"}
}