{
  "type": "Feature",
  "properties": {
    "gn:admin1_code":"4.0",
    "gn:asciiname":"Yabachi",
    "gn:country_code":"CN",
    "gn:dem":3,
    "gn:feature_class":"P",
    "gn:feature_code":"PPL",
    "gn:name":"Yabachi",
    "gn:population":0,
    "gn:timezone":"Asia/Shanghai",
    "iso:country":"CN",
    "name:und_x_variant":[
        "\u54d1\u5df4\u6c60"
    ],
    "wof:name":"Yabachi",
    "wof:placetype":"locality"
},
  "geometry": {"coordinates":[121.01689,32.45257],"type":"Point"}
}