{
  "type": "Feature",
  "properties": {
    "gn:admin1_code":"9.0",
    "gn:asciiname":"Xinzhuang",
    "gn:country_code":"CN",
    "gn:dem":121,
    "gn:feature_class":"P",
    "gn:feature_code":"PPL",
    "gn:name":"Xinzhuang",
    "gn:population":0,
    "gn:timezone":"Asia/Shanghai",
    "iso:country":"CN",
    "name:ceb_x_preferred":[
        "Xinzhuang"
    ],
    "name:deu_x_preferred":[
        "Xinzhuang"
    ],
    "name:und_x_variant":[
        "\u8f9b\u5e84",
        "Xinzhuang"
    ],
    "wof:name":"Xinzhuang",
    "wof:placetype":"locality"
},
  "geometry": {"coordinates":[112.96733999999999,33.07349],"type":"Point"}
}