{
  "type": "Feature",
  "properties": {
    "gn:admin1_code":"11.0",
    "gn:asciiname":"Niuxingmiao",
    "gn:country_code":"CN",
    "gn:dem":787,
    "gn:feature_class":"P",
    "gn:feature_code":"PPL",
    "gn:name":"Niuxingmiao",
    "gn:population":0,
    "gn:timezone":"Asia/Shanghai",
    "iso:country":"CN",
    "name:zho_x_preferred":[
        "\u725b\u5f62\u5e99"
    ],
    "wof:name":"Niuxingmiao",
    "wof:placetype":"locality"
},
  "geometry": {"coordinates":[113.56694,25.38043],"type":"Point"}
}