{
  "type": "Feature",
  "properties": {
    "gn:country":"CN",
    "gn:fcode":"PPL",
    "gn:population":1552,
    "iso:country":"CN",
    "name:und_x_variant":[
        "Li-kuan-t\u2019un"
    ],
    "qs:name":"Xiliguantun",
    "qs:photos_9r":0,
    "qs:photos_sr":0,
    "qs:pop_sr":"3",
    "wof:name":"Xiliguantun",
    "wof:placetype":"locality",
    "wof:population":1552
},
  "geometry": {"coordinates":[115.94139,37.07833],"type":"Point"}
}