{
  "type": "Feature",
  "properties": {
    "gn:admin1_code":"4.0",
    "gn:asciiname":"Youjiapeng",
    "gn:country_code":"CN",
    "gn:dem":11,
    "gn:feature_class":"P",
    "gn:feature_code":"PPL",
    "gn:name":"Youjiapeng",
    "gn:population":0,
    "gn:timezone":"Asia/Shanghai",
    "iso:country":"CN",
    "name:zho_x_preferred":[
        "\u6e38\u5bb6\u68da"
    ],
    "wof:name":"Youjiapeng",
    "wof:placetype":"locality"
},
  "geometry": {"coordinates":[119.31943,31.50315],"type":"Point"}
}