{
  "type": "Feature",
  "properties": {
    "gn:admin1_code":"7.0",
    "gn:asciiname":"Peixie",
    "gn:country_code":"CN",
    "gn:dem":661,
    "gn:feature_class":"P",
    "gn:feature_code":"PPL",
    "gn:name":"Peixie",
    "gn:population":0,
    "gn:timezone":"Asia/Shanghai",
    "iso:country":"CN",
    "name:zho_x_preferred":[
        "\u57f9\u659c"
    ],
    "wof:name":"Peixie",
    "wof:placetype":"locality"
},
  "geometry": {"coordinates":[116.84990999999999,25.11738],"type":"Point"}
}