{
  "type": "Feature",
  "properties": {
    "gn:admin1_code":"32.0",
    "gn:asciiname":"Hongchunping",
    "gn:country_code":"CN",
    "gn:dem":1221,
    "gn:feature_class":"P",
    "gn:feature_code":"PPL",
    "gn:name":"Hongchunping",
    "gn:population":0,
    "gn:timezone":"Asia/Shanghai",
    "iso:country":"CN",
    "name:zho_x_preferred":[
        "\u7ea2\u693f\u576a"
    ],
    "wof:name":"Hongchunping",
    "wof:placetype":"locality"
},
  "geometry": {"coordinates":[104.09229999999999,31.42327],"type":"Point"}
}