{
  "type": "Feature",
  "properties": {
    "gn:admin1_code":"8.0",
    "gn:asciiname":"Dong'ercun",
    "gn:country_code":"CN",
    "gn:dem":77,
    "gn:feature_class":"P",
    "gn:feature_code":"PPL",
    "gn:name":"Dong\u2019ercun",
    "gn:population":0,
    "gn:timezone":"Asia/Shanghai",
    "iso:country":"CN",
    "name:und_x_variant":[
        "Dong\u2019ercun"
    ],
    "name:zho_x_preferred":[
        "\u4e1c\u4e8c\u6751"
    ],
    "wof:name":"Dong'ercun",
    "wof:placetype":"locality"
},
  "geometry": {"coordinates":[130.88019,46.89071],"type":"Point"}
}