{
  "type": "Feature",
  "properties": {
    "gn:admin1_code":"8.0",
    "gn:asciiname":"Caiyuanzicun",
    "gn:country_code":"CN",
    "gn:dem":121,
    "gn:feature_class":"P",
    "gn:feature_code":"PPL",
    "gn:name":"Caiyuanzicun",
    "gn:population":0,
    "gn:timezone":"Asia/Shanghai",
    "iso:country":"CN",
    "name:zho_x_preferred":[
        "\u83dc\u56ed\u5b50\u6751"
    ],
    "wof:name":"Caiyuanzicun",
    "wof:placetype":"locality"
},
  "geometry": {"coordinates":[125.91473000000001,45.66164000000001],"type":"Point"}
}