{
  "type": "Feature",
  "properties": {
    "gn:admin1_code":"15.0",
    "gn:asciiname":"Podi Xiacun",
    "gn:country_code":"CN",
    "gn:dem":1897,
    "gn:feature_class":"P",
    "gn:feature_code":"PPL",
    "gn:name":"Podi Xiacun",
    "gn:population":0,
    "gn:timezone":"Asia/Shanghai",
    "iso:country":"CN",
    "name:zho_x_preferred":[
        "\u5761\u5e95\u4e0b\u6751"
    ],
    "wof:name":"Podi Xiacun",
    "wof:placetype":"locality"
},
  "geometry": {"coordinates":[106.496,35.1924],"type":"Point"}
}