{
  "type": "Feature",
  "properties": {
    "gn:admin1_code":"32.0",
    "gn:asciiname":"Gongqiao",
    "gn:country_code":"CN",
    "gn:dem":349,
    "gn:feature_class":"P",
    "gn:feature_code":"PPL",
    "gn:name":"Gongqiao",
    "gn:population":0,
    "gn:timezone":"Asia/Shanghai",
    "iso:country":"CN",
    "name:zho_x_preferred":[
        "\u62f1\u6865"
    ],
    "wof:name":"Gongqiao",
    "wof:placetype":"locality"
},
  "geometry": {"coordinates":[106.863,30.5075],"type":"Point"}
}