{
  "type": "Feature",
  "properties": {
    "gn:admin1_code":"14.0",
    "gn:asciiname":"Rimarna",
    "gn:country_code":"CN",
    "gn:dem":5027,
    "gn:feature_class":"P",
    "gn:feature_code":"PPL",
    "gn:name":"Rimarna",
    "gn:population":0,
    "gn:timezone":"Asia/Urumqi",
    "iso:country":"CN",
    "name:bod_x_preferred":[
        "Rimarna"
    ],
    "name:zho_x_preferred":[
        "Rimana"
    ],
    "name:zho_x_variant":[
        "\u65e5\u9a6c\u7eb3",
        "Chalong Gongshe",
        "\u67e5\u9686\u516c\u793e"
    ],
    "wof:name":"Rimarna",
    "wof:placetype":"locality"
},
  "geometry": {"coordinates":[95.504,31.404],"type":"Point"}
}