{
  "type": "Feature",
  "properties": {
    "gn:admin1_code":"7",
    "gn:asciiname":"Shikeng",
    "gn:country_code":"CN",
    "gn:dem":330,
    "gn:feature_class":"P",
    "gn:feature_code":"PPL",
    "gn:name":"Shikeng",
    "gn:population":0,
    "gn:timezone":"Asia/Shanghai",
    "iso:country":"CN",
    "name:zho_x_preferred":[
        "\u8bd7\u5751"
    ],
    "wof:name":"Shikeng",
    "wof:placetype":"locality"
},
  "geometry": {"coordinates":[117.06383,24.30487],"type":"Point"}
}