{
  "type": "Feature",
  "properties": {
    "gn:admin1_code":"26",
    "gn:asciiname":"Micang",
    "gn:country_code":"CN",
    "gn:dem":891,
    "gn:feature_class":"P",
    "gn:feature_code":"PPL",
    "gn:name":"Micang",
    "gn:population":0,
    "gn:timezone":"Asia/Shanghai",
    "iso:country":"CN",
    "name:zho_x_preferred":[
        "\u7c73\u4ed3"
    ],
    "wof:name":"Micang",
    "wof:placetype":"locality"
},
  "geometry": {"coordinates":[108.67806000000002,34.81889],"type":"Point"}
}