{
  "type": "Feature",
  "properties": {
    "gn:admin1_code":"8.0",
    "gn:asciiname":"Yongjiutuncun",
    "gn:country_code":"CN",
    "gn:dem":284,
    "gn:feature_class":"P",
    "gn:feature_code":"PPL",
    "gn:name":"Yongjiutuncun",
    "gn:population":0,
    "gn:timezone":"Asia/Shanghai",
    "iso:country":"CN",
    "name:zho_x_preferred":[
        "\u6c38\u4e45\u5c6f\u6751"
    ],
    "wof:name":"Yongjiutuncun",
    "wof:placetype":"locality"
},
  "geometry": {"coordinates":[125.45641000000001,49.37452],"type":"Point"}
}