{
  "type": "Feature",
  "properties": {
    "gn:admin1_code":"16.0",
    "gn:asciiname":"Shadanju",
    "gn:country_code":"CN",
    "gn:dem":34,
    "gn:feature_class":"P",
    "gn:feature_code":"PPL",
    "gn:name":"Shadanju",
    "gn:population":0,
    "gn:timezone":"Asia/Shanghai",
    "iso:country":"CN",
    "name:zho_x_preferred":[
        "\u6749\u6de1\u5c40"
    ],
    "wof:name":"Shadanju",
    "wof:placetype":"locality"
},
  "geometry": {"coordinates":[108.956,21.9784],"type":"Point"}
}