{
  "type": "Feature",
  "properties": {
    "gn:admin1_code":"11",
    "gn:asciiname":"Baishui",
    "gn:country_code":"CN",
    "gn:dem":226,
    "gn:feature_class":"P",
    "gn:feature_code":"PPL",
    "gn:name":"Baishui",
    "gn:population":0,
    "gn:timezone":"Asia/Shanghai",
    "iso:country":"CN",
    "name:deu_x_preferred":[
        "Baishui"
    ],
    "name:kor_x_preferred":[
        "\ubc14\uc774\uc218\uc774"
    ],
    "wof:name":"Baishui",
    "wof:placetype":"locality"
},
  "geometry": {"coordinates":[111.37833000000001,25.26667],"type":"Point"}
}