{
  "type": "Feature",
  "properties": {
    "gn:admin1_code":"18",
    "gn:asciiname":"Henglushang",
    "gn:country_code":"CN",
    "gn:dem":1470,
    "gn:feature_class":"P",
    "gn:feature_code":"PPL",
    "gn:name":"Henglushang",
    "gn:population":0,
    "gn:timezone":"Asia/Shanghai",
    "iso:country":"CN",
    "name:zho_x_preferred":[
        "\u6a2a\u8def\u4e0a"
    ],
    "wof:name":"Henglushang",
    "wof:placetype":"locality"
},
  "geometry": {"coordinates":[107.03,26.5497],"type":"Point"}
}