{
  "type": "Feature",
  "properties": {
    "gn:admin1_code":"25",
    "gn:asciiname":"Beiyangzhuang",
    "gn:country_code":"CN",
    "gn:dem":41,
    "gn:feature_class":"P",
    "gn:feature_code":"PPL",
    "gn:name":"Beiyangzhuang",
    "gn:population":0,
    "gn:timezone":"Asia/Shanghai",
    "iso:country":"CN",
    "name:zho_x_preferred":[
        "\u5317\u6768\u5e84"
    ],
    "wof:name":"Beiyangzhuang",
    "wof:placetype":"locality"
},
  "geometry": {"coordinates":[117.72,34.7384],"type":"Point"}
}