{
  "type": "Feature",
  "properties": {
    "gn:admin1_code":"25",
    "gn:asciiname":"Donglizhuang",
    "gn:country_code":"CN",
    "gn:dem":182,
    "gn:feature_class":"P",
    "gn:feature_code":"PPL",
    "gn:name":"Donglizhuang",
    "gn:population":0,
    "gn:timezone":"Asia/Shanghai",
    "iso:country":"CN",
    "name:zho_x_preferred":[
        "\u4e1c\u91cc\u5e84"
    ],
    "wof:name":"Donglizhuang",
    "wof:placetype":"locality"
},
  "geometry": {"coordinates":[118.05500000000001,35.7729],"type":"Point"}
}