{
  "type": "Feature",
  "properties": {
    "gn:admin1_code":"26.0",
    "gn:asciiname":"Sunjia Goukou",
    "gn:country_code":"CN",
    "gn:dem":954,
    "gn:feature_class":"P",
    "gn:feature_code":"PPL",
    "gn:name":"Sunjia Goukou",
    "gn:population":0,
    "gn:timezone":"Asia/Shanghai",
    "iso:country":"CN",
    "name:zho_x_preferred":[
        "\u5b59\u5bb6\u6c9f\u53e3"
    ],
    "wof:name":"Sunjia Goukou",
    "wof:placetype":"locality"
},
  "geometry": {"coordinates":[108.85363,33.1397],"type":"Point"}
}