{
  "type": "Feature",
  "properties": {
    "gn:admin1_code":"11.0",
    "gn:asciiname":"Hejiatian",
    "gn:country_code":"CN",
    "gn:dem":359,
    "gn:feature_class":"P",
    "gn:feature_code":"PPL",
    "gn:name":"Hejiatian",
    "gn:population":0,
    "gn:timezone":"Asia/Shanghai",
    "iso:country":"CN",
    "name:zho_x_preferred":[
        "\u79be\u5bb6\u7530"
    ],
    "wof:name":"Hejiatian",
    "wof:placetype":"locality"
},
  "geometry": {"coordinates":[112.30542,25.33905],"type":"Point"}
}