{
  "type": "Feature",
  "properties": {
    "gn:admin1_code":"16.0",
    "gn:asciiname":"Dashangcun",
    "gn:country_code":"CN",
    "gn:dem":99,
    "gn:feature_class":"P",
    "gn:feature_code":"PPL",
    "gn:name":"Dashangcun",
    "gn:population":0,
    "gn:timezone":"Asia/Shanghai",
    "iso:country":"CN",
    "name:zho_x_preferred":[
        "\u5927\u4e0a\u6751"
    ],
    "wof:name":"Dashangcun",
    "wof:placetype":"locality"
},
  "geometry": {"coordinates":[110.149,23.1178],"type":"Point"}
}