{
  "type": "Feature",
  "properties": {
    "gn:admin1_code":"16",
    "gn:asciiname":"Shangyangjia",
    "gn:country_code":"CN",
    "gn:dem":157,
    "gn:feature_class":"P",
    "gn:feature_code":"PPL",
    "gn:name":"Shangyangjia",
    "gn:population":0,
    "gn:timezone":"Asia/Shanghai",
    "iso:country":"CN",
    "name:zho_x_preferred":[
        "\u4e0a\u9633\u5bb6"
    ],
    "wof:name":"Shangyangjia",
    "wof:placetype":"locality"
},
  "geometry": {"coordinates":[110.33799999999999,25.3243],"type":"Point"}
}