{
  "type": "Feature",
  "properties": {
    "gn:admin1_code":"32.0",
    "gn:asciiname":"Luojia'an",
    "gn:country_code":"CN",
    "gn:dem":457,
    "gn:feature_class":"P",
    "gn:feature_code":"PPL",
    "gn:name":"Luojia\u2019an",
    "gn:population":0,
    "gn:timezone":"Asia/Shanghai",
    "iso:country":"CN",
    "name:zho_x_preferred":[
        "\u7f57\u5bb6\u5eb5"
    ],
    "name:zho_x_variant":[
        "Luojia\u2019an"
    ],
    "wof:name":"Luojia'an",
    "wof:placetype":"locality"
},
  "geometry": {"coordinates":[104.34235,29.81604],"type":"Point"}
}