{
  "type": "Feature",
  "properties": {
    "gn:admin1_code":"29",
    "gn:asciiname":"Fangzhang",
    "gn:country_code":"CN",
    "gn:dem":1611,
    "gn:feature_class":"P",
    "gn:feature_code":"PPL",
    "gn:name":"Fangzhang",
    "gn:population":0,
    "gn:timezone":"Asia/Shanghai",
    "iso:country":"CN",
    "name:zho_x_preferred":[
        "\u65b9\u4e08"
    ],
    "wof:name":"Fangzhang",
    "wof:placetype":"locality"
},
  "geometry": {"coordinates":[102.29640000000001,24.01968],"type":"Point"}
}