{
  "type": "Feature",
  "properties": {
    "gn:admin1_code":"29.0",
    "gn:asciiname":"Shangyou",
    "gn:country_code":"CN",
    "gn:dem":2549,
    "gn:feature_class":"P",
    "gn:feature_code":"PPL",
    "gn:name":"Shangyou",
    "gn:population":0,
    "gn:timezone":"Asia/Shanghai",
    "iso:country":"CN",
    "name:zho_x_preferred":[
        "\u4e0a\u6e38"
    ],
    "wof:name":"Shangyou",
    "wof:placetype":"locality"
},
  "geometry": {"coordinates":[99.71151,28.67491],"type":"Point"}
}