{
  "type": "Feature",
  "properties": {
    "gn:admin1_code":"16.0",
    "gn:asciiname":"Xialanpo",
    "gn:country_code":"CN",
    "gn:dem":72,
    "gn:feature_class":"P",
    "gn:feature_code":"PPL",
    "gn:name":"Xialanpo",
    "gn:population":0,
    "gn:timezone":"Asia/Shanghai",
    "iso:country":"CN",
    "name:zho_x_preferred":[
        "\u4e0b\u5170\u5761"
    ],
    "wof:name":"Xialanpo",
    "wof:placetype":"locality"
},
  "geometry": {"coordinates":[110.122,21.9138],"type":"Point"}
}