{
  "type": "Feature",
  "properties": {
    "gn:admin1_code":"30.0",
    "gn:asciiname":"Wanshan",
    "gn:country_code":"CN",
    "gn:dem":39,
    "gn:feature_class":"P",
    "gn:feature_code":"PPL",
    "gn:name":"Wanshan",
    "gn:population":0,
    "gn:timezone":"Asia/Shanghai",
    "iso:country":"CN",
    "name:ceb_x_preferred":[
        "Wanshan"
    ],
    "name:deu_x_preferred":[
        "Wanshan"
    ],
    "name:fra_x_preferred":[
        "Wanshan"
    ],
    "name:nor_x_preferred":[
        "Wanshan"
    ],
    "name:zho_x_preferred":[
        "\u4e07\u5c71"
    ],
    "wof:name":"Wanshan",
    "wof:placetype":"locality"
},
  "geometry": {"coordinates":[113.7205,21.93439],"type":"Point"}
}