{
  "type": "Feature",
  "properties": {
    "gn:admin1_code":"11.0",
    "gn:asciiname":"Changtouping",
    "gn:country_code":"CN",
    "gn:dem":495,
    "gn:feature_class":"P",
    "gn:feature_code":"PPL",
    "gn:name":"Changtouping",
    "gn:population":0,
    "gn:timezone":"Asia/Shanghai",
    "iso:country":"CN",
    "name:zho_x_preferred":[
        "\u660c\u5934\u576a"
    ],
    "wof:name":"Changtouping",
    "wof:placetype":"locality"
},
  "geometry": {"coordinates":[113.50972,26.11241],"type":"Point"}
}