{
  "type": "Feature",
  "properties": {
    "gn:admin1_code":"10.0",
    "gn:asciiname":"Yangchengzi",
    "gn:country_code":"CN",
    "gn:dem":1206,
    "gn:feature_class":"P",
    "gn:feature_code":"PPL",
    "gn:name":"Yangchengzi",
    "gn:population":0,
    "gn:timezone":"Asia/Shanghai",
    "iso:country":"CN",
    "name:zho_x_preferred":[
        "\u9633\u57ce\u5b50"
    ],
    "wof:name":"Yangchengzi",
    "wof:placetype":"locality"
},
  "geometry": {"coordinates":[114.94444,40.39484],"type":"Point"}
}