{
  "type": "Feature",
  "properties": {
    "gn:admin1_code":"3.0",
    "gn:asciiname":"Xuezi",
    "gn:country_code":"CN",
    "gn:dem":213,
    "gn:feature_class":"P",
    "gn:feature_code":"PPL",
    "gn:name":"Xuezi",
    "gn:population":0,
    "gn:timezone":"Asia/Shanghai",
    "iso:country":"CN",
    "name:und_x_variant":[
        "\u5b66\u5b50"
    ],
    "wof:name":"Xuezi",
    "wof:placetype":"locality"
},
  "geometry": {"coordinates":[115.73145,25.27372],"type":"Point"}
}