{
  "type": "Feature",
  "properties": {
    "gn:admin1_code":"19.0",
    "gn:asciiname":"Qiantuozicun",
    "gn:country_code":"CN",
    "gn:dem":6,
    "gn:feature_class":"P",
    "gn:feature_code":"PPL",
    "gn:name":"Qiantuozicun",
    "gn:population":0,
    "gn:timezone":"Asia/Shanghai",
    "iso:country":"CN",
    "name:zho_x_preferred":[
        "\u94b1\u5768\u5b50\u6751"
    ],
    "wof:name":"Qiantuozicun",
    "wof:placetype":"locality"
},
  "geometry": {"coordinates":[122.226,41.282],"type":"Point"}
}