{
  "type": "Feature",
  "properties": {
    "gn:admin1_code":"19.0",
    "gn:asciiname":"Hujiangtun",
    "gn:country_code":"CN",
    "gn:dem":6,
    "gn:feature_class":"P",
    "gn:feature_code":"PPL",
    "gn:name":"Hujiangtun",
    "gn:population":0,
    "gn:timezone":"Asia/Shanghai",
    "iso:country":"CN",
    "name:zho_x_preferred":[
        "\u864e\u5c06\u5c6f"
    ],
    "wof:name":"Hujiangtun",
    "wof:placetype":"locality"
},
  "geometry": {"coordinates":[120.14870000000001,40.1344],"type":"Point"}
}