{
  "type": "Feature",
  "properties": {
    "gn:admin1_code":"4.0",
    "gn:asciiname":"Xiaochoucun",
    "gn:country_code":"CN",
    "gn:dem":12,
    "gn:feature_class":"P",
    "gn:feature_code":"PPL",
    "gn:name":"Xiaochoucun",
    "gn:population":0,
    "gn:timezone":"Asia/Shanghai",
    "iso:country":"CN",
    "name:zho_x_preferred":[
        "\u5c0f\u7a20\u6751"
    ],
    "wof:name":"Xiaochoucun",
    "wof:placetype":"locality"
},
  "geometry": {"coordinates":[118.68671000000001,34.35712],"type":"Point"}
}