{
  "type": "Feature",
  "properties": {
    "gn:country":"CN",
    "gn:fcode":"PPL",
    "gn:population":59338,
    "iso:country":"CN",
    "name:und_x_variant":[
        "Teng"
    ],
    "name:zho_x_preferred":[
        "\u82b1\u6d32"
    ],
    "ne:ADM0CAP":0.0,
    "ne:ADM0NAME":"China",
    "ne:ADM0_A3":"CHN",
    "ne:ADM1NAME":"Henan",
    "ne:ADMIN1_COD":9,
    "ne:CAPALT":0,
    "ne:CHANGED":0,
    "ne:CHECKME":0,
    "ne:COMPARE":0,
    "ne:DIFFASCII":0,
    "ne:ELEVATION":0.0,
    "ne:FEATURECLA":"Populated place",
    "ne:FEATURE_CL":"P",
    "ne:FEATURE_CO":"PPL",
    "ne:GEONAMEID":1812990,
    "ne:GEONAMESNO":"Geonames ascii name + lat.d + long.d matching.",
    "ne:GN_ASCII":"Dengzhou",
    "ne:GN_POP":59338,
    "ne:GTOPO30":115.0,
    "ne:ISO_A2":"CN",
    "ne:LABELRANK":1,
    "ne:LATITUDE":32.680368,
    "ne:LONGITUDE":112.080022,
    "ne:LS_MATCH":1,
    "ne:LS_NAME":"Dengzhou",
    "ne:MAX_AREAKM":4243.0,
    "ne:MAX_AREAMI":1638.0,
    "ne:MAX_BBXMAX":112.534941,
    "ne:MAX_BBXMIN":111.596951,
    "ne:MAX_BBYMAX":33.353576,
    "ne:MAX_BBYMIN":32.331736,
    "ne:MAX_NATSCA":20.0,
    "ne:MAX_PERKM":3318.0,
    "ne:MAX_PERMI":2062.0,
    "ne:MAX_POP10":2918729,
    "ne:MAX_POP20":3363980,
    "ne:MAX_POP300":0,
    "ne:MAX_POP310":0,
    "ne:MAX_POP50":0,
    "ne:MEAN_BBXC":112.035562,
    "ne:MEAN_BBYC":32.74035,
    "ne:MEGACITY":0,
    "ne:MIN_AREAKM":3657.0,
    "ne:MIN_AREAMI":1412.0,
    "ne:MIN_BBXMAX":112.534941,
    "ne:MIN_BBXMIN":111.498724,
    "ne:MIN_BBYMAX":33.3,
    "ne:MIN_BBYMIN":32.317412,
    "ne:MIN_PERKM":2801.0,
    "ne:MIN_PERMI":1740.0,
    "ne:NAME":"Dengzhou",
    "ne:NAMEASCII":"Dengzhou",
    "ne:NAMEDIFF":0,
    "ne:NATSCALE":20,
    "ne:POP1950":0,
    "ne:POP1955":0,
    "ne:POP1960":0,
    "ne:POP1965":0,
    "ne:POP1970":0,
    "ne:POP1975":0,
    "ne:POP1980":0,
    "ne:POP1985":0,
    "ne:POP1990":0,
    "ne:POP1995":0,
    "ne:POP2000":0,
    "ne:POP2005":0,
    "ne:POP2010":0,
    "ne:POP2015":0,
    "ne:POP2020":0,
    "ne:POP2025":0,
    "ne:POP2050":0,
    "ne:POP_MAX":59338,
    "ne:POP_MIN":59338,
    "ne:POP_OTHER":2835938,
    "ne:RANK_MAX":8,
    "ne:RANK_MIN":8,
    "ne:SCALERANK":7,
    "ne:SOV0NAME":"China",
    "ne:SOV_A3":"CHN",
    "ne:TIMEZONE":"Asia/Chongqing",
    "ne:UN_FID":0,
    "ne:UN_LAT":0.0,
    "ne:UN_LONG":0.0,
    "ne:WORLDCITY":0,
    "qs:name":"\u9093\u5dde",
    "qs:name_adm0":"\u4e2d\u570b",
    "qs:name_adm1":"\u6cb3\u5357\u7701",
    "qs:photos_9k":1,
    "qs:photos_9r":3,
    "qs:photos_all":96,
    "qs:photos_sr":0,
    "qs:placetype":"Town",
    "qs:pop_sr":"8",
    "wof:name":"\u9093\u5dde",
    "wof:placetype":"locality",
    "wof:population":59338
},
  "geometry": {"coordinates":[112.08194,32.68222],"type":"Point"}
}