{
  "type": "Feature",
  "properties": {
    "gn:admin1_code":"30",
    "gn:asciiname":"Beishui Xincun",
    "gn:country_code":"CN",
    "gn:dem":8,
    "gn:feature_class":"P",
    "gn:feature_code":"PPL",
    "gn:name":"Beishui Xincun",
    "gn:population":0,
    "gn:timezone":"Asia/Shanghai",
    "iso:country":"CN",
    "name:und_x_variant":[
        "Baishui",
        "Beishui Xincun"
    ],
    "name:zho_x_preferred":[
        "\u5317\u6c34\u65b0\u6751"
    ],
    "wof:name":"Beishui Xincun",
    "wof:placetype":"locality"
},
  "geometry": {"coordinates":[113.22093999999998,22.04257],"type":"Point"}
}