{
  "type": "Feature",
  "properties": {
    "gn:admin1_code":"4.0",
    "gn:asciiname":"Huanghai Gongqu Xiaoqu",
    "gn:country_code":"CN",
    "gn:dem":0,
    "gn:feature_class":"P",
    "gn:feature_code":"PPLF",
    "gn:name":"Huanghai Gongqu Xiaoqu",
    "gn:population":0,
    "gn:timezone":"Asia/Shanghai",
    "iso:country":"CN",
    "name:zho_x_preferred":[
        "\u9ec4\u6d77\u5de5\u533a\u5c0f\u533a"
    ],
    "wof:name":"Huanghai Gongqu Xiaoqu",
    "wof:placetype":"locality"
},
  "geometry": {"coordinates":[119.74109,34.49127],"type":"Point"}
}