{
  "type": "Feature",
  "properties": {
    "gn:admin1_code":"2.0",
    "gn:asciiname":"Luoxi",
    "gn:country_code":"CN",
    "gn:dem":66,
    "gn:feature_class":"P",
    "gn:feature_code":"PPL",
    "gn:name":"Luoxi",
    "gn:population":0,
    "gn:timezone":"Asia/Shanghai",
    "iso:country":"CN",
    "name:zho_x_preferred":[
        "\u87ba\u6eaa"
    ],
    "wof:name":"Luoxi",
    "wof:placetype":"locality"
},
  "geometry": {"coordinates":[121.04819000000001,29.14421],"type":"Point"}
}