{
  "type": "Feature",
  "properties": {
    "gn:admin1_code":"3.0",
    "gn:asciiname":"Xiaba Maoshan",
    "gn:country_code":"CN",
    "gn:dem":240,
    "gn:feature_class":"P",
    "gn:feature_code":"PPL",
    "gn:name":"Xiaba Maoshan",
    "gn:population":0,
    "gn:timezone":"Asia/Shanghai",
    "iso:country":"CN",
    "name:und_x_variant":[
        "\u4e0b\u82ad\u8305\u5c71"
    ],
    "wof:name":"Xiaba Maoshan",
    "wof:placetype":"locality"
},
  "geometry": {"coordinates":[115.40976000000001,29.10438],"type":"Point"}
}