{
  "type": "Feature",
  "properties": {
    "gn:admin1_code":"26.0",
    "gn:asciiname":"Dayinwan",
    "gn:country_code":"CN",
    "gn:dem":1009,
    "gn:feature_class":"P",
    "gn:feature_code":"PPL",
    "gn:name":"Dayinwan",
    "gn:population":0,
    "gn:timezone":"Asia/Shanghai",
    "iso:country":"CN",
    "name:zho_x_preferred":[
        "\u5927\u9634\u6e7e"
    ],
    "wof:name":"Dayinwan",
    "wof:placetype":"locality"
},
  "geometry": {"coordinates":[110.99533999999998,39.32159],"type":"Point"}
}