{
  "type": "Feature",
  "properties": {
    "gn:admin1_code":"32.0",
    "gn:asciiname":"Rexin",
    "gn:country_code":"CN",
    "gn:dem":3850,
    "gn:feature_class":"P",
    "gn:feature_code":"PPL",
    "gn:name":"Rexin",
    "gn:population":0,
    "gn:timezone":"Asia/Shanghai",
    "iso:country":"CN",
    "name:zho_x_preferred":[
        "\u70ed\u4fe1"
    ],
    "wof:name":"Rexin",
    "wof:placetype":"locality"
},
  "geometry": {"coordinates":[98.2313,32.2557],"type":"Point"}
}