{
  "type": "Feature",
  "properties": {
    "gn:admin1_code":"26.0",
    "gn:asciiname":"Lezihecun",
    "gn:country_code":"CN",
    "gn:dem":1213,
    "gn:feature_class":"P",
    "gn:feature_code":"PPL",
    "gn:name":"Lezihecun",
    "gn:population":0,
    "gn:timezone":"Asia/Shanghai",
    "iso:country":"CN",
    "name:und_x_variant":[
        "\u4e86\u5b50\u6cb3\u6751"
    ],
    "wof:name":"Lezihecun",
    "wof:placetype":"locality"
},
  "geometry": {"coordinates":[109.57956,34.18749],"type":"Point"}
}