{
  "type": "Feature",
  "properties": {
    "gn:admin1_code":"4.0",
    "gn:asciiname":"Basanxu",
    "gn:country_code":"CN",
    "gn:dem":4,
    "gn:feature_class":"P",
    "gn:feature_code":"PPLF",
    "gn:name":"Basanxu",
    "gn:population":0,
    "gn:timezone":"Asia/Shanghai",
    "iso:country":"CN",
    "name:zho_x_preferred":[
        "\u5df4\u4e09\u5729"
    ],
    "wof:name":"Basanxu",
    "wof:placetype":"locality"
},
  "geometry": {"coordinates":[120.06502999999999,32.03058],"type":"Point"}
}