{
  "type": "Feature",
  "properties": {
    "gn:admin1_code":"13",
    "gn:asciiname":"Xiaobai Shitou",
    "gn:country_code":"CN",
    "gn:dem":2027,
    "gn:feature_class":"P",
    "gn:feature_code":"PPL",
    "gn:name":"Xiaobai Shitou",
    "gn:population":0,
    "gn:timezone":"Asia/Urumqi",
    "iso:country":"CN",
    "name:zho_x_preferred":[
        "\u5c0f\u767d\u77f3\u5934"
    ],
    "wof:name":"Xiaobai Shitou",
    "wof:placetype":"locality"
},
  "geometry": {"coordinates":[95.33695,41.91368],"type":"Point"}
}