{
  "type": "Feature",
  "properties": {
    "gn:admin1_code":"29",
    "gn:asciiname":"Hailuotian",
    "gn:country_code":"CN",
    "gn:dem":1351,
    "gn:feature_class":"P",
    "gn:feature_code":"PPL",
    "gn:name":"Hailuotian",
    "gn:population":0,
    "gn:timezone":"Asia/Shanghai",
    "iso:country":"CN",
    "name:zho_x_preferred":[
        "\u6d77\u6d1b\u7530"
    ],
    "wof:name":"Hailuotian",
    "wof:placetype":"locality"
},
  "geometry": {"coordinates":[103.042,24.5948],"type":"Point"}
}