{
  "type": "Feature",
  "properties": {
    "gn:admin1_code":"11.0",
    "gn:asciiname":"Linmubang",
    "gn:country_code":"CN",
    "gn:dem":504,
    "gn:feature_class":"P",
    "gn:feature_code":"PPL",
    "gn:name":"Linmubang",
    "gn:population":0,
    "gn:timezone":"Asia/Shanghai",
    "iso:country":"CN",
    "name:zho_x_preferred":[
        "\u6797\u6728\u699c"
    ],
    "wof:name":"Linmubang",
    "wof:placetype":"locality"
},
  "geometry": {"coordinates":[112.1181,24.89739],"type":"Point"}
}