{
  "type": "Feature",
  "properties": {
    "gn:admin1_code":"15.0",
    "gn:asciiname":"Zansa",
    "gn:country_code":"CN",
    "gn:dem":3062,
    "gn:feature_class":"P",
    "gn:feature_code":"PPL",
    "gn:name":"Zansa",
    "gn:population":0,
    "gn:timezone":"Asia/Shanghai",
    "iso:country":"CN",
    "name:und_x_variant":[
        "\u54b1\u6d12"
    ],
    "wof:name":"Zansa",
    "wof:placetype":"locality"
},
  "geometry": {"coordinates":[102.92698,34.9422],"type":"Point"}
}