{
  "type": "Feature",
  "properties": {
    "gn:admin1_code":"26.0",
    "gn:asciiname":"Xizaowan",
    "gn:country_code":"CN",
    "gn:dem":1528,
    "gn:feature_class":"P",
    "gn:feature_code":"PPL",
    "gn:name":"Xizaowan",
    "gn:population":0,
    "gn:timezone":"Asia/Shanghai",
    "iso:country":"CN",
    "name:zho_x_preferred":[
        "\u897f\u67a3\u6e7e"
    ],
    "wof:name":"Xizaowan",
    "wof:placetype":"locality"
},
  "geometry": {"coordinates":[108.61236,36.74616],"type":"Point"}
}