{
  "type": "Feature",
  "properties": {
    "gn:admin1_code":"16.0",
    "gn:asciiname":"Gaolan",
    "gn:country_code":"CN",
    "gn:dem":477,
    "gn:feature_class":"P",
    "gn:feature_code":"PPL",
    "gn:name":"Gaolan",
    "gn:population":0,
    "gn:timezone":"Asia/Shanghai",
    "iso:country":"CN",
    "name:zho_x_preferred":[
        "\u9ad8\u5170"
    ],
    "wof:name":"Gaolan",
    "wof:placetype":"locality"
},
  "geometry": {"coordinates":[109.351,25.6029],"type":"Point"}
}