{
  "type": "Feature",
  "properties": {
    "gn:admin1_code":"10.0",
    "gn:asciiname":"Tanquetun",
    "gn:country_code":"CN",
    "gn:dem":10,
    "gn:feature_class":"P",
    "gn:feature_code":"PPL",
    "gn:name":"Tanquetun",
    "gn:population":0,
    "gn:timezone":"Asia/Shanghai",
    "iso:country":"CN",
    "name:zho_x_preferred":[
        "\u8c2d\u7f3a\u5c6f"
    ],
    "wof:name":"Tanquetun",
    "wof:placetype":"locality"
},
  "geometry": {"coordinates":[116.846,38.5403],"type":"Point"}
}