{
  "type": "Feature",
  "properties": {
    "gn:admin1_code":"18",
    "gn:asciiname":"Shanglinba",
    "gn:country_code":"CN",
    "gn:dem":608,
    "gn:feature_class":"P",
    "gn:feature_code":"PPL",
    "gn:name":"Shanglinba",
    "gn:population":0,
    "gn:timezone":"Asia/Shanghai",
    "iso:country":"CN",
    "name:zho_x_preferred":[
        "\u4e0a\u6797\u575d"
    ],
    "wof:name":"Shanglinba",
    "wof:placetype":"locality"
},
  "geometry": {"coordinates":[108.33499999999999,27.6533],"type":"Point"}
}