{
  "type": "Feature",
  "properties": {
    "gn:admin1_code":"3.0",
    "gn:asciiname":"Xiwei",
    "gn:country_code":"CN",
    "gn:dem":344,
    "gn:feature_class":"P",
    "gn:feature_code":"PPL",
    "gn:name":"Xiwei",
    "gn:population":0,
    "gn:timezone":"Asia/Shanghai",
    "iso:country":"CN",
    "name:ceb_x_preferred":[
        "Xiwei"
    ],
    "name:swe_x_preferred":[
        "Xiwei"
    ],
    "name:und_x_variant":[
        "\u6eaa\u5c3e"
    ],
    "wof:name":"Xiwei",
    "wof:placetype":"locality"
},
  "geometry": {"coordinates":[115.79049999999999,25.06533],"type":"Point"}
}