{
  "type": "Feature",
  "properties": {
    "gn:admin1_code":"1.0",
    "gn:asciiname":"Wangdian",
    "gn:country_code":"CN",
    "gn:dem":26,
    "gn:feature_class":"P",
    "gn:feature_code":"PPL",
    "gn:name":"Wangdian",
    "gn:population":0,
    "gn:timezone":"Asia/Shanghai",
    "iso:country":"CN",
    "name:ceb_x_preferred":[
        "Wangdian"
    ],
    "name:swe_x_preferred":[
        "Wangdian"
    ],
    "name:zho_x_preferred":[
        "\u6c6a\u5e97"
    ],
    "wof:name":"Wangdian",
    "wof:placetype":"locality"
},
  "geometry": {"coordinates":[118.44165,30.78714],"type":"Point"}
}