{
  "type": "Feature",
  "properties": {
    "gn:admin1_code":"8.0",
    "gn:asciiname":"Qianjiangjia",
    "gn:country_code":"CN",
    "gn:dem":125,
    "gn:feature_class":"P",
    "gn:feature_code":"PPL",
    "gn:name":"Qianjiangjia",
    "gn:population":0,
    "gn:timezone":"Asia/Shanghai",
    "iso:country":"CN",
    "name:zho_x_preferred":[
        "\u524d\u59dc\u5bb6"
    ],
    "wof:name":"Qianjiangjia",
    "wof:placetype":"locality"
},
  "geometry": {"coordinates":[126.54124,46.20789],"type":"Point"}
}