{
  "type": "Feature",
  "properties": {
    "gn:admin1_code":"18.0",
    "gn:asciiname":"Zhangpai",
    "gn:country_code":"CN",
    "gn:dem":989,
    "gn:feature_class":"P",
    "gn:feature_code":"PPL",
    "gn:name":"Zhangpai",
    "gn:population":0,
    "gn:timezone":"Asia/Shanghai",
    "iso:country":"CN",
    "name:zho_x_preferred":[
        "\u638c\u6392"
    ],
    "wof:name":"Zhangpai",
    "wof:placetype":"locality"
},
  "geometry": {"coordinates":[108.057,26.3815],"type":"Point"}
}