{
  "type": "Feature",
  "properties": {
    "gn:admin1_code":"4.0",
    "gn:asciiname":"Tuyuan",
    "gn:country_code":"CN",
    "gn:dem":5,
    "gn:feature_class":"P",
    "gn:feature_code":"PPL",
    "gn:name":"Tuyuan",
    "gn:population":0,
    "gn:timezone":"Asia/Shanghai",
    "iso:country":"CN",
    "name:zho_x_preferred":[
        "Tuyuan"
    ],
    "name:zho_x_variant":[
        "\u571f\u56ed"
    ],
    "wof:name":"Tuyuan",
    "wof:placetype":"locality"
},
  "geometry": {"coordinates":[121.03512000000001,32.46376],"type":"Point"}
}