{
  "type": "Feature",
  "properties": {
    "gn:admin1_code":"1.0",
    "gn:asciiname":"Wanggengcun",
    "gn:country_code":"CN",
    "gn:dem":7,
    "gn:feature_class":"P",
    "gn:feature_code":"PPL",
    "gn:name":"Wanggengcun",
    "gn:population":0,
    "gn:timezone":"Asia/Shanghai",
    "iso:country":"CN",
    "name:zho_x_preferred":[
        "\u738b\u57c2\u6751"
    ],
    "wof:name":"Wanggengcun",
    "wof:placetype":"locality"
},
  "geometry": {"coordinates":[118.44669,31.16418],"type":"Point"}
}