{
  "type": "Feature",
  "properties": {
    "gn:admin1_code":"19.0",
    "gn:asciiname":"Hougoucun",
    "gn:country_code":"CN",
    "gn:dem":85,
    "gn:feature_class":"P",
    "gn:feature_code":"PPL",
    "gn:name":"Hougoucun",
    "gn:population":0,
    "gn:timezone":"Asia/Shanghai",
    "iso:country":"CN",
    "name:zho_x_preferred":[
        "\u540e\u6c9f\u6751"
    ],
    "wof:name":"Hougoucun",
    "wof:placetype":"locality"
},
  "geometry": {"coordinates":[123.77119,41.73658],"type":"Point"}
}