{
  "type": "Feature",
  "properties": {
    "gn:admin1_code":"8.0",
    "gn:asciiname":"Shizhanpu",
    "gn:country_code":"CN",
    "gn:dem":130,
    "gn:feature_class":"P",
    "gn:feature_code":"PPL",
    "gn:name":"Shizhanpu",
    "gn:population":0,
    "gn:timezone":"Asia/Shanghai",
    "iso:country":"CN",
    "name:zho_x_preferred":[
        "\u77f3\u6be1\u94fa"
    ],
    "wof:name":"Shizhanpu",
    "wof:placetype":"locality"
},
  "geometry": {"coordinates":[123.82656,46.52072],"type":"Point"}
}