{
  "type": "Feature",
  "properties": {
    "gn:admin1_code":"23.0",
    "gn:asciiname":"Wuqiao",
    "gn:country_code":"CN",
    "gn:dem":6,
    "gn:feature_class":"P",
    "gn:feature_code":"PPL",
    "gn:name":"Wuqiao",
    "gn:population":0,
    "gn:timezone":"Asia/Shanghai",
    "iso:country":"CN",
    "name:und_x_variant":[
        "Wu-chia-ch\u2019iao",
        "Wuqiao",
        "\u90ac\u6865"
    ],
    "wof:name":"Wuqiao",
    "wof:placetype":"locality"
},
  "geometry": {"coordinates":[121.39567,30.96175],"type":"Point"}
}