{
  "type": "Feature",
  "properties": {
    "gn:admin1_code":"1.0",
    "gn:asciiname":"Qingyuanling",
    "gn:country_code":"CN",
    "gn:dem":110,
    "gn:feature_class":"P",
    "gn:feature_code":"PPL",
    "gn:name":"Qingyuanling",
    "gn:population":0,
    "gn:timezone":"Asia/Shanghai",
    "iso:country":"CN",
    "name:zho_x_preferred":[
        "Qingyuanling"
    ],
    "name:zho_x_variant":[
        "\u9752\u5143\u5cad"
    ],
    "wof:name":"Qingyuanling",
    "wof:placetype":"locality"
},
  "geometry": {"coordinates":[119.61427,31.04976],"type":"Point"}
}