{
  "type": "Feature",
  "properties": {
    "gn:admin1_code":"29",
    "gn:asciiname":"Madingwu",
    "gn:country_code":"CN",
    "gn:dem":1403,
    "gn:feature_class":"P",
    "gn:feature_code":"PPL",
    "gn:name":"Madingwu",
    "gn:population":0,
    "gn:timezone":"Asia/Shanghai",
    "iso:country":"CN",
    "name:zho_x_preferred":[
        "\u9a6c\u5b9a\u5c4b"
    ],
    "wof:name":"Madingwu",
    "wof:placetype":"locality"
},
  "geometry": {"coordinates":[101.556,24.2805],"type":"Point"}
}