{
  "type": "Feature",
  "properties": {
    "gn:admin1_code":"18",
    "gn:asciiname":"Youzhawan",
    "gn:country_code":"CN",
    "gn:dem":1000,
    "gn:feature_class":"P",
    "gn:feature_code":"PPL",
    "gn:name":"Youzhawan",
    "gn:population":0,
    "gn:timezone":"Asia/Shanghai",
    "iso:country":"CN",
    "name:zho_x_preferred":[
        "\u6cb9\u69a8\u6e7e"
    ],
    "wof:name":"Youzhawan",
    "wof:placetype":"locality"
},
  "geometry": {"coordinates":[107.53,28.2694],"type":"Point"}
}