{
  "type": "Feature",
  "properties": {
    "gn:admin1_code":"12.0",
    "gn:asciiname":"Lianhua",
    "gn:country_code":"CN",
    "gn:dem":210,
    "gn:feature_class":"P",
    "gn:feature_code":"PPL",
    "gn:name":"Lianhua",
    "gn:population":0,
    "gn:timezone":"Asia/Shanghai",
    "iso:country":"CN",
    "name:ceb_x_preferred":[
        "Lianhua"
    ],
    "name:deu_x_preferred":[
        "Lianhua"
    ],
    "name:nor_x_preferred":[
        "Lianhua"
    ],
    "name:zho_x_preferred":[
        "\u8054\u534e"
    ],
    "wof:name":"Lianhua",
    "wof:placetype":"locality"
},
  "geometry": {"coordinates":[113.14516,32.15388],"type":"Point"}
}