{
  "type": "Feature",
  "properties": {
    "gn:admin1_code":"19.0",
    "gn:asciiname":"Qianlanganpao",
    "gn:country_code":"CN",
    "gn:dem":28,
    "gn:feature_class":"P",
    "gn:feature_code":"PPL",
    "gn:name":"Qianlanganpao",
    "gn:population":0,
    "gn:timezone":"Asia/Shanghai",
    "iso:country":"CN",
    "name:zho_x_preferred":[
        "\u524d\u680f\u6746\u6ce1"
    ],
    "wof:name":"Qianlanganpao",
    "wof:placetype":"locality"
},
  "geometry": {"coordinates":[122.96594,41.87343],"type":"Point"}
}