{
  "type": "Feature",
  "properties": {
    "gn:admin1_code":"3",
    "gn:asciiname":"Wailong",
    "gn:country_code":"CN",
    "gn:dem":538,
    "gn:feature_class":"P",
    "gn:feature_code":"PPL",
    "gn:name":"Wailong",
    "gn:population":0,
    "gn:timezone":"Asia/Shanghai",
    "iso:country":"CN",
    "name:zho_x_preferred":[
        "\u5916\u9f99"
    ],
    "wof:name":"Wailong",
    "wof:placetype":"locality"
},
  "geometry": {"coordinates":[114.73699999999999,26.2957],"type":"Point"}
}