{
  "type": "Feature",
  "properties": {
    "gn:admin1_code":"1.0",
    "gn:asciiname":"Shecun",
    "gn:country_code":"CN",
    "gn:dem":12,
    "gn:feature_class":"P",
    "gn:feature_code":"PPL",
    "gn:name":"Shecun",
    "gn:population":0,
    "gn:timezone":"Asia/Shanghai",
    "iso:country":"CN",
    "name:zho_x_preferred":[
        "\u4f58\u6751"
    ],
    "wof:name":"Shecun",
    "wof:placetype":"locality"
},
  "geometry": {"coordinates":[118.34945999999999,31.18034],"type":"Point"}
}