{
  "type": "Feature",
  "properties": {
    "gn:admin1_code":"4.0",
    "gn:asciiname":"Wuhaogou",
    "gn:country_code":"CN",
    "gn:dem":3,
    "gn:feature_class":"P",
    "gn:feature_code":"PPL",
    "gn:name":"Wuhaogou",
    "gn:population":0,
    "gn:timezone":"Asia/Shanghai",
    "iso:country":"CN",
    "name:und_x_variant":[
        "\u620a\u53f7\u6c9f"
    ],
    "wof:name":"Wuhaogou",
    "wof:placetype":"locality"
},
  "geometry": {"coordinates":[119.01449,32.22228],"type":"Point"}
}