{
  "type": "Feature",
  "properties": {
    "gn:admin1_code":"29.0",
    "gn:asciiname":"Xiachu",
    "gn:country_code":"CN",
    "gn:dem":1157,
    "gn:feature_class":"P",
    "gn:feature_code":"PPL",
    "gn:name":"Xiachu",
    "gn:population":0,
    "gn:timezone":"Asia/Shanghai",
    "iso:country":"CN",
    "name:zho_x_preferred":[
        "\u867e\u5904"
    ],
    "name:zho_x_variant":[
        "\u4e0b\u521d\u9547"
    ],
    "wof:name":"Xiachu",
    "wof:placetype":"locality"
},
  "geometry": {"coordinates":[102.358,22.8115],"type":"Point"}
}