{
  "type": "Feature",
  "properties": {
    "gn:admin1_code":"19.0",
    "gn:asciiname":"Zhangdaocun",
    "gn:country_code":"CN",
    "gn:dem":-9999,
    "gn:feature_class":"P",
    "gn:feature_code":"PPL",
    "gn:name":"Zhangdaocun",
    "gn:population":0,
    "gn:timezone":"Asia/Shanghai",
    "iso:country":"CN",
    "name:zho_x_preferred":[
        "\u7350\u5c9b\u6751"
    ],
    "wof:name":"Zhangdaocun",
    "wof:placetype":"locality"
},
  "geometry": {"coordinates":[123.81364000000001,39.79098],"type":"Point"}
}