{
  "type": "Feature",
  "properties": {
    "gn:admin1_code":"20.0",
    "gn:asciiname":"Shisifenzi",
    "gn:country_code":"CN",
    "gn:dem":1630,
    "gn:feature_class":"P",
    "gn:feature_code":"PPL",
    "gn:name":"Shisifenzi",
    "gn:population":0,
    "gn:timezone":"Asia/Shanghai",
    "iso:country":"CN",
    "name:und_x_variant":[
        "\u5341\u56db\u5206\u5b50"
    ],
    "wof:name":"Shisifenzi",
    "wof:placetype":"locality"
},
  "geometry": {"coordinates":[109.69815,41.41163],"type":"Point"}
}