{
  "type": "Feature",
  "properties": {
    "gn:admin1_code":"13",
    "gn:asciiname":"Taga'erqicun",
    "gn:country_code":"CN",
    "gn:dem":1212,
    "gn:feature_class":"P",
    "gn:feature_code":"PPL",
    "gn:name":"Taga\u2019erqicun",
    "gn:population":0,
    "gn:timezone":"Asia/Shanghai",
    "iso:country":"CN",
    "name:und_x_variant":[
        "Taga\u2019erqicun"
    ],
    "name:zho_x_preferred":[
        "\u5854\u5c15\u5c14\u5176\u6751"
    ],
    "wof:name":"Taga'erqicun",
    "wof:placetype":"locality"
},
  "geometry": {"coordinates":[76.45948,39.33471],"type":"Point"}
}