{
  "type": "Feature",
  "properties": {
    "gn:admin1_code":"3.0",
    "gn:asciiname":"Muqiaoxia",
    "gn:country_code":"CN",
    "gn:dem":89,
    "gn:feature_class":"P",
    "gn:feature_code":"PPL",
    "gn:name":"Muqiaoxia",
    "gn:population":0,
    "gn:timezone":"Asia/Shanghai",
    "iso:country":"CN",
    "name:und_x_variant":[
        "\u6728\u6865\u4e0b"
    ],
    "wof:name":"Muqiaoxia",
    "wof:placetype":"locality"
},
  "geometry": {"coordinates":[115.41553999999999,29.43835],"type":"Point"}
}