{
  "type": "Feature",
  "properties": {
    "gn:admin1_code":"30",
    "gn:asciiname":"Zoujiawei",
    "gn:country_code":"CN",
    "gn:dem":151,
    "gn:feature_class":"P",
    "gn:feature_code":"PPL",
    "gn:name":"Zoujiawei",
    "gn:population":0,
    "gn:timezone":"Asia/Shanghai",
    "iso:country":"CN",
    "name:zho_x_preferred":[
        "\u90b9\u5bb6\u56f4"
    ],
    "wof:name":"Zoujiawei",
    "wof:placetype":"locality"
},
  "geometry": {"coordinates":[116.18608,23.89899],"type":"Point"}
}