{
  "type": "Feature",
  "properties": {
    "gn:admin1_code":"25",
    "gn:asciiname":"Hetoudian",
    "gn:country_code":"CN",
    "gn:dem":91,
    "gn:feature_class":"P",
    "gn:feature_code":"PPLA4",
    "gn:name":"Hetoudian",
    "gn:population":0,
    "gn:timezone":"Asia/Shanghai",
    "iso:country":"CN",
    "name:und_x_variant":[
        "Ho-t\u2019ou-tien",
        "Hetoudian",
        "Hetoudian Zhen"
    ],
    "name:zho_x_preferred":[
        "\u6cb3\u5934\u5e97"
    ],
    "name:zho_x_variant":[
        "\u6cb3\u5934\u5e97\u9547"
    ],
    "wof:name":"Hetoudian",
    "wof:placetype":"locality"
},
  "geometry": {"coordinates":[120.57371999999999,37.01837],"type":"Point"}
}