{
  "type": "Feature",
  "properties": {
    "gn:admin1_code":"20.0",
    "gn:asciiname":"Huoduqi",
    "gn:country_code":"CN",
    "gn:dem":687,
    "gn:feature_class":"P",
    "gn:feature_code":"PPL",
    "gn:name":"Huoduqi",
    "gn:population":0,
    "gn:timezone":"Asia/Shanghai",
    "iso:country":"CN",
    "name:zho_x_preferred":[
        "\u970d\u90fd\u5947"
    ],
    "wof:name":"Huoduqi",
    "wof:placetype":"locality"
},
  "geometry": {"coordinates":[122.49211,50.65193],"type":"Point"}
}