{
  "type": "Feature",
  "properties": {
    "gn:admin1_code":"3.0",
    "gn:asciiname":"Helin",
    "gn:country_code":"CN",
    "gn:dem":305,
    "gn:feature_class":"P",
    "gn:feature_code":"PPL",
    "gn:name":"Helin",
    "gn:population":0,
    "gn:timezone":"Asia/Shanghai",
    "iso:country":"CN",
    "name:und_x_variant":[
        "\u8377\u6797"
    ],
    "wof:name":"Helin",
    "wof:placetype":"locality"
},
  "geometry": {"coordinates":[115.46831,26.49085],"type":"Point"}
}