{
  "type": "Feature",
  "properties": {
    "gn:admin1_code":"4.0",
    "gn:asciiname":"Sundongfenchang Ershiwudadui",
    "gn:country_code":"CN",
    "gn:dem":9,
    "gn:feature_class":"P",
    "gn:feature_code":"PPLF",
    "gn:name":"Sundongfenchang Ershiwudadui",
    "gn:population":0,
    "gn:timezone":"Asia/Shanghai",
    "iso:country":"CN",
    "name:zho_x_preferred":[
        "\u5b59\u4e1c\u5206\u573a\u4e8c\u5341\u4e94\u5927\u961f"
    ],
    "wof:name":"Sundongfenchang Ershiwudadui",
    "wof:placetype":"locality"
},
  "geometry": {"coordinates":[120.69159000000001,32.91874],"type":"Point"}
}