{
  "type": "Feature",
  "properties": {
    "gn:admin1_code":"25.0",
    "gn:asciiname":"Dachuliu",
    "gn:country_code":"CN",
    "gn:dem":67,
    "gn:feature_class":"P",
    "gn:feature_code":"PPL",
    "gn:name":"Dachuliu",
    "gn:population":0,
    "gn:timezone":"Asia/Shanghai",
    "iso:country":"CN",
    "name:zho_x_preferred":[
        "\u5927\u695a\u7559"
    ],
    "wof:name":"Dachuliu",
    "wof:placetype":"locality"
},
  "geometry": {"coordinates":[121.16924,37.21444],"type":"Point"}
}