{
  "type": "Feature",
  "properties": {
    "gn:admin1_code":"3.0",
    "gn:asciiname":"Sasidou Zhujia",
    "gn:country_code":"CN",
    "gn:dem":59,
    "gn:feature_class":"P",
    "gn:feature_code":"PPL",
    "gn:name":"Sasidou Zhujia",
    "gn:population":0,
    "gn:timezone":"Asia/Shanghai",
    "iso:country":"CN",
    "name:zho_x_preferred":[
        "\u5345\u56db\u90fd\u795d\u5bb6"
    ],
    "wof:name":"Sasidou Zhujia",
    "wof:placetype":"locality"
},
  "geometry": {"coordinates":[117.40192999999999,28.44346],"type":"Point"}
}