{
  "type": "Feature",
  "properties": {
    "gn:admin1_code":"29.0",
    "gn:asciiname":"Tatu",
    "gn:country_code":"CN",
    "gn:dem":1787,
    "gn:feature_class":"P",
    "gn:feature_code":"PPL",
    "gn:name":"Tatu",
    "gn:population":0,
    "gn:timezone":"Asia/Shanghai",
    "iso:country":"CN",
    "name:und_x_variant":[
        "\u584c\u571f"
    ],
    "wof:name":"Tatu",
    "wof:placetype":"locality"
},
  "geometry": {"coordinates":[104.47571000000001,26.45939000000001],"type":"Point"}
}