{
  "type": "Feature",
  "properties": {
    "gn:admin1_code":"5.0",
    "gn:asciiname":"Tanpingcun",
    "gn:country_code":"CN",
    "gn:dem":427,
    "gn:feature_class":"P",
    "gn:feature_code":"PPL",
    "gn:name":"Tanpingcun",
    "gn:population":0,
    "gn:timezone":"Asia/Shanghai",
    "iso:country":"CN",
    "name:zho_x_preferred":[
        "\u5766\u5e73\u6751"
    ],
    "wof:name":"Tanpingcun",
    "wof:placetype":"locality"
},
  "geometry": {"coordinates":[126.36562000000001,42.4276],"type":"Point"}
}