{
  "type": "Feature",
  "properties": {
    "gn:admin1_code":"25.0",
    "gn:asciiname":"Houshilongtuncun",
    "gn:country_code":"CN",
    "gn:dem":6,
    "gn:feature_class":"P",
    "gn:feature_code":"PPL",
    "gn:name":"Houshilongtuncun",
    "gn:population":0,
    "gn:timezone":"Asia/Shanghai",
    "iso:country":"CN",
    "name:zho_x_preferred":[
        "\u540e\u77f3\u9f99\u5c6f\u6751"
    ],
    "wof:name":"Houshilongtuncun",
    "wof:placetype":"locality"
},
  "geometry": {"coordinates":[120.14085,36.30853],"type":"Point"}
}