{
  "type": "Feature",
  "properties": {
    "gn:admin1_code":"32.0",
    "gn:asciiname":"Wajing",
    "gn:country_code":"CN",
    "gn:dem":2084,
    "gn:feature_class":"P",
    "gn:feature_code":"PPL",
    "gn:name":"Wajing",
    "gn:population":0,
    "gn:timezone":"Asia/Shanghai",
    "iso:country":"CN",
    "name:zho_x_preferred":[
        "\u74e6\u4e95"
    ],
    "wof:name":"Wajing",
    "wof:placetype":"locality"
},
  "geometry": {"coordinates":[102.89619,28.08333],"type":"Point"}
}