{
  "type": "Feature",
  "properties": {
    "gn:admin1_code":"16.0",
    "gn:asciiname":"Dongkou",
    "gn:country_code":"CN",
    "gn:dem":215,
    "gn:feature_class":"P",
    "gn:feature_code":"PPL",
    "gn:name":"Dongkou",
    "gn:population":0,
    "gn:timezone":"Asia/Shanghai",
    "iso:country":"CN",
    "name:zho_x_preferred":[
        "\u578c\u53e3"
    ],
    "wof:name":"Dongkou",
    "wof:placetype":"locality"
},
  "geometry": {"coordinates":[109.66800000000001,22.3936],"type":"Point"}
}