{
  "type": "Feature",
  "properties": {
    "gn:admin1_code":"32.0",
    "gn:asciiname":"Yilie",
    "gn:country_code":"CN",
    "gn:dem":3457,
    "gn:feature_class":"P",
    "gn:feature_code":"PPL",
    "gn:name":"Yilie",
    "gn:population":0,
    "gn:timezone":"Asia/Shanghai",
    "iso:country":"CN",
    "name:zho_x_preferred":[
        "\u8863\u52a3"
    ],
    "wof:name":"Yilie",
    "wof:placetype":"locality"
},
  "geometry": {"coordinates":[100.28273,30.61691],"type":"Point"}
}