{
  "type": "Feature",
  "properties": {
    "gn:admin1_code":"30.0",
    "gn:asciiname":"Dongwang",
    "gn:country_code":"CN",
    "gn:dem":120,
    "gn:feature_class":"P",
    "gn:feature_code":"PPL",
    "gn:name":"Dongwang",
    "gn:population":0,
    "gn:timezone":"Asia/Shanghai",
    "iso:country":"CN",
    "name:deu_x_preferred":[
        "Dongwang"
    ],
    "name:zho_x_preferred":[
        "Dongwang"
    ],
    "name:zho_x_variant":[
        "\u4e1c\u7f51"
    ],
    "wof:name":"Dongwang",
    "wof:placetype":"locality"
},
  "geometry": {"coordinates":[115.35028,24.17889],"type":"Point"}
}