{
  "type": "Feature",
  "properties": {
    "gn:admin1_code":"9.0",
    "gn:asciiname":"Tiesuogou",
    "gn:country_code":"CN",
    "gn:dem":621,
    "gn:feature_class":"P",
    "gn:feature_code":"PPL",
    "gn:name":"Tiesuogou",
    "gn:population":0,
    "gn:timezone":"Asia/Shanghai",
    "iso:country":"CN",
    "name:zho_x_preferred":[
        "\u94c1\u9501\u6c9f"
    ],
    "wof:name":"Tiesuogou",
    "wof:placetype":"locality"
},
  "geometry": {"coordinates":[111.81094,33.96427],"type":"Point"}
}