{
  "type": "Feature",
  "properties": {
    "gn:admin1_code":"8.0",
    "gn:asciiname":"Xingxingcun",
    "gn:country_code":"CN",
    "gn:dem":164,
    "gn:feature_class":"P",
    "gn:feature_code":"PPL",
    "gn:name":"Xingxingcun",
    "gn:population":0,
    "gn:timezone":"Asia/Shanghai",
    "iso:country":"CN",
    "name:zho_x_preferred":[
        "\u661f\u661f\u6751"
    ],
    "wof:name":"Xingxingcun",
    "wof:placetype":"locality"
},
  "geometry": {"coordinates":[129.44933,46.95954],"type":"Point"}
}