{
  "type": "Feature",
  "properties": {
    "gn:admin1_code":"25",
    "gn:asciiname":"Liupu",
    "gn:country_code":"CN",
    "gn:dem":42,
    "gn:feature_class":"P",
    "gn:feature_code":"PPL",
    "gn:name":"Liupu",
    "gn:population":0,
    "gn:timezone":"Asia/Shanghai",
    "iso:country":"CN",
    "name:zho_x_preferred":[
        "\u5218\u94fa"
    ],
    "wof:name":"Liupu",
    "wof:placetype":"locality"
},
  "geometry": {"coordinates":[115.87815000000001,36.18924000000001],"type":"Point"}
}