{
  "type": "Feature",
  "properties": {
    "gn:admin1_code":"26.0",
    "gn:asciiname":"Koujia",
    "gn:country_code":"CN",
    "gn:dem":1223,
    "gn:feature_class":"P",
    "gn:feature_code":"PPL",
    "gn:name":"Koujia",
    "gn:population":0,
    "gn:timezone":"Asia/Shanghai",
    "iso:country":"CN",
    "name:zho_x_preferred":[
        "\u5bc7\u5bb6"
    ],
    "wof:name":"Koujia",
    "wof:placetype":"locality"
},
  "geometry": {"coordinates":[110.07817,34.25579],"type":"Point"}
}