{
  "type": "Feature",
  "properties": {
    "gn:admin1_code":"26.0",
    "gn:asciiname":"Wakoucun",
    "gn:country_code":"CN",
    "gn:dem":1180,
    "gn:feature_class":"P",
    "gn:feature_code":"PPL",
    "gn:name":"Wakoucun",
    "gn:population":0,
    "gn:timezone":"Asia/Shanghai",
    "iso:country":"CN",
    "name:zho_x_preferred":[
        "\u6d3c\u53e3\u6751"
    ],
    "wof:name":"Wakoucun",
    "wof:placetype":"locality"
},
  "geometry": {"coordinates":[110.46623999999998,33.39211],"type":"Point"}
}