{
  "type": "Feature",
  "properties": {
    "gn:admin1_code":"25",
    "gn:asciiname":"Liangdongcun",
    "gn:country_code":"CN",
    "gn:dem":15,
    "gn:feature_class":"P",
    "gn:feature_code":"PPL",
    "gn:name":"Liangdongcun",
    "gn:population":0,
    "gn:timezone":"Asia/Shanghai",
    "iso:country":"CN",
    "name:zho_x_preferred":[
        "\u6881\u4e1c\u6751"
    ],
    "wof:name":"Liangdongcun",
    "wof:placetype":"locality"
},
  "geometry": {"coordinates":[120.15300000000001,36.4914],"type":"Point"}
}