{
  "type": "Feature",
  "properties": {
    "gn:admin1_code":"26",
    "gn:asciiname":"Budi",
    "gn:cc2":"CN",
    "gn:country_code":"CN",
    "gn:dem":1278,
    "gn:feature_class":"P",
    "gn:feature_code":"PPL",
    "gn:name":"Budi",
    "gn:population":0,
    "gn:timezone":"Asia/Shanghai",
    "iso:country":"CN",
    "name:ceb_x_preferred":[
        "Budi"
    ],
    "name:ind_x_preferred":[
        "Budi"
    ],
    "name:swe_x_preferred":[
        "Budi"
    ],
    "name:und_x_variant":[
        "Pu-ti",
        "Budi"
    ],
    "wof:name":"Budi",
    "wof:placetype":"locality"
},
  "geometry": {"coordinates":[109.53306000000001,36.00167000000001],"type":"Point"}
}