{
  "type": "Feature",
  "properties": {
    "gn:admin1_code":"15.0",
    "gn:asciiname":"Zarina",
    "gn:country_code":"CN",
    "gn:dem":3413,
    "gn:feature_class":"P",
    "gn:feature_code":"PPL",
    "gn:name":"Zarina",
    "gn:population":0,
    "gn:timezone":"Asia/Shanghai",
    "iso:country":"CN",
    "name:zho_x_preferred":[
        "\u6742\u65e5\u7eb3"
    ],
    "wof:name":"Zarina",
    "wof:placetype":"locality"
},
  "geometry": {"coordinates":[102.845,34.3976],"type":"Point"}
}