{
  "type": "Feature",
  "properties": {
    "gn:admin1_code":"7",
    "gn:asciiname":"Xiaxidi",
    "gn:country_code":"CN",
    "gn:dem":381,
    "gn:feature_class":"P",
    "gn:feature_code":"PPL",
    "gn:name":"Xiaxidi",
    "gn:population":0,
    "gn:timezone":"Asia/Shanghai",
    "iso:country":"CN",
    "name:zho_x_preferred":[
        "\u4e0b\u6eaa\u5e95"
    ],
    "wof:name":"Xiaxidi",
    "wof:placetype":"locality"
},
  "geometry": {"coordinates":[119.15073,25.60631],"type":"Point"}
}