{
  "type": "Feature",
  "properties": {
    "gn:admin1_code":"6.0",
    "gn:asciiname":"Song'ekao",
    "gn:country_code":"CN",
    "gn:dem":3950,
    "gn:feature_class":"P",
    "gn:feature_code":"PPL",
    "gn:name":"Song\u2019ekao",
    "gn:population":0,
    "gn:timezone":"Asia/Urumqi",
    "iso:country":"CN",
    "name:und_x_variant":[
        "Song\u2019ekao"
    ],
    "name:zho_x_preferred":[
        "\u677e\u4fc4\u8003"
    ],
    "wof:name":"Song'ekao",
    "wof:placetype":"locality"
},
  "geometry": {"coordinates":[95.98039,32.54663],"type":"Point"}
}