{
  "type": "Feature",
  "properties": {
    "gn:admin1_code":"12.0",
    "gn:asciiname":"Damaopo",
    "gn:country_code":"CN",
    "gn:dem":966,
    "gn:feature_class":"P",
    "gn:feature_code":"PPL",
    "gn:name":"Damaopo",
    "gn:population":0,
    "gn:timezone":"Asia/Shanghai",
    "iso:country":"CN",
    "name:zho_x_preferred":[
        "Damaopo"
    ],
    "name:zho_x_variant":[
        "\u5927\u8305\u5761"
    ],
    "wof:name":"Damaopo",
    "wof:placetype":"locality"
},
  "geometry": {"coordinates":[109.24175,29.95174],"type":"Point"}
}