{
  "type": "Feature",
  "properties": {
    "gn:admin1_code":"5.0",
    "gn:asciiname":"Danjiacun",
    "gn:country_code":"CN",
    "gn:dem":155,
    "gn:feature_class":"P",
    "gn:feature_code":"PPL",
    "gn:name":"Danjiacun",
    "gn:population":0,
    "gn:timezone":"Asia/Shanghai",
    "iso:country":"CN",
    "name:zho_x_preferred":[
        "\u5355\u5bb6\u6751"
    ],
    "wof:name":"Danjiacun",
    "wof:placetype":"locality"
},
  "geometry": {"coordinates":[125.05311,45.09201],"type":"Point"}
}