{
  "type": "Feature",
  "properties": {
    "gn:admin1_code":"11.0",
    "gn:asciiname":"Xialongwangqiao",
    "gn:country_code":"CN",
    "gn:dem":74,
    "gn:feature_class":"P",
    "gn:feature_code":"PPL",
    "gn:name":"Xialongwangqiao",
    "gn:population":0,
    "gn:timezone":"Asia/Shanghai",
    "iso:country":"CN",
    "name:zho_x_preferred":[
        "\u4e0b\u9f99\u738b\u6865"
    ],
    "wof:name":"Xialongwangqiao",
    "wof:placetype":"locality"
},
  "geometry": {"coordinates":[112.61167,27.3774],"type":"Point"}
}