{
  "type": "Feature",
  "properties": {
    "gn:admin1_code":"11.0",
    "gn:asciiname":"Xinwu Maojia",
    "gn:country_code":"CN",
    "gn:dem":82,
    "gn:feature_class":"P",
    "gn:feature_code":"PPL",
    "gn:name":"Xinwu Maojia",
    "gn:population":0,
    "gn:timezone":"Asia/Shanghai",
    "iso:country":"CN",
    "name:zho_x_preferred":[
        "\u65b0\u5c4b\u6bdb\u5bb6"
    ],
    "wof:name":"Xinwu Maojia",
    "wof:placetype":"locality"
},
  "geometry": {"coordinates":[113.36038000000001,29.22089],"type":"Point"}
}