{
  "type": "Feature",
  "properties": {
    "gn:admin1_code":"29.0",
    "gn:asciiname":"Hali",
    "gn:country_code":"CN",
    "gn:dem":715,
    "gn:feature_class":"P",
    "gn:feature_code":"PPL",
    "gn:name":"Hali",
    "gn:population":0,
    "gn:timezone":"Asia/Shanghai",
    "iso:country":"CN",
    "name:ceb_x_preferred":[
        "Hali"
    ],
    "name:deu_x_preferred":[
        "Hali"
    ],
    "name:zho_x_preferred":[
        "\u54c8\u91cc"
    ],
    "wof:name":"Hali",
    "wof:placetype":"locality"
},
  "geometry": {"coordinates":[98.93470000000001,23.7277],"type":"Point"}
}