{
  "type": "Feature",
  "properties": {
    "gn:admin1_code":"19.0",
    "gn:asciiname":"Zaojiaocun",
    "gn:country_code":"CN",
    "gn:dem":22,
    "gn:feature_class":"P",
    "gn:feature_code":"PPL",
    "gn:name":"Zaojiaocun",
    "gn:population":0,
    "gn:timezone":"Asia/Shanghai",
    "iso:country":"CN",
    "name:zho_x_preferred":[
        "\u7682\u89d2\u6751"
    ],
    "wof:name":"Zaojiaocun",
    "wof:placetype":"locality"
},
  "geometry": {"coordinates":[122.735,41.7756],"type":"Point"}
}