{
  "type": "Feature",
  "properties": {
    "gn:admin1_code":"01",
    "gn:asciiname":"Nianwulipu",
    "gn:cc2":"CN",
    "gn:country_code":"CN",
    "gn:dem":68,
    "gn:feature_class":"P",
    "gn:feature_code":"PPL",
    "gn:name":"Nianwulipu",
    "gn:population":0,
    "gn:timezone":"Asia/Shanghai",
    "iso:country":"CN",
    "name:und_x_variant":[
        "Erh-shih-wu-li-p\u2019u",
        "Nien-wu-li-p\u2019u",
        "Nianwulipu"
    ],
    "wof:name":"Nianwulipu",
    "wof:placetype":"locality"
},
  "geometry": {"coordinates":[116.66667,31.76667],"type":"Point"}
}