{
  "type": "Feature",
  "properties": {
    "gn:admin1_code":"26.0",
    "gn:asciiname":"Taiyangling",
    "gn:country_code":"CN",
    "gn:dem":993,
    "gn:feature_class":"P",
    "gn:feature_code":"PPLA4",
    "gn:name":"Taiyangling",
    "gn:population":0,
    "gn:timezone":"Asia/Shanghai",
    "iso:country":"CN",
    "name:und_x_variant":[
        "\u592a\u9633\u5cad"
    ],
    "wof:name":"Taiyangling",
    "wof:placetype":"locality"
},
  "geometry": {"coordinates":[106.00312,33.03648],"type":"Point"}
}