{
  "type": "Feature",
  "properties": {
    "gn:admin1_code":"4.0",
    "gn:asciiname":"Nangangzhuang",
    "gn:country_code":"CN",
    "gn:dem":14,
    "gn:feature_class":"P",
    "gn:feature_code":"PPL",
    "gn:name":"Nangangzhuang",
    "gn:population":0,
    "gn:timezone":"Asia/Shanghai",
    "iso:country":"CN",
    "name:zho_x_preferred":[
        "\u5357\u5c97\u5e84"
    ],
    "wof:name":"Nangangzhuang",
    "wof:placetype":"locality"
},
  "geometry": {"coordinates":[118.60281999999999,33.97251],"type":"Point"}
}