{
  "type": "Feature",
  "properties": {
    "gn:admin1_code":"08",
    "gn:asciiname":"Cangshan",
    "gn:country_code":"CN",
    "gn:dem":594,
    "gn:feature_class":"P",
    "gn:feature_code":"PPLA4",
    "gn:name":"Cangshan",
    "gn:population":0,
    "gn:timezone":"Asia/Shanghai",
    "iso:country":"CN",
    "name:ceb_x_preferred":[
        "Cangshan"
    ],
    "name:deu_x_preferred":[
        "Cangshan"
    ],
    "name:fra_x_preferred":[
        "Cangshan"
    ],
    "name:nor_x_preferred":[
        "Cangshan"
    ],
    "name:swe_x_preferred":[
        "Cangshan"
    ],
    "name:und_x_variant":[
        "Ts\u2019ang-shan",
        "Cangshan Zhen"
    ],
    "name:zho_x_preferred":[
        "\u82cd\u5c71"
    ],
    "name:zho_x_variant":[
        "\u82cd\u5c71\u9547"
    ],
    "wof:name":"Cangshan",
    "wof:placetype":"locality"
},
  "geometry": {"coordinates":[123.59227,51.78804],"type":"Point"}
}