{
  "type": "Feature",
  "properties": {
    "gn:admin1_code":"19.0",
    "gn:asciiname":"Nianyuwancun",
    "gn:country_code":"CN",
    "gn:dem":21,
    "gn:feature_class":"P",
    "gn:feature_code":"PPL",
    "gn:name":"Nianyuwancun",
    "gn:population":0,
    "gn:timezone":"Asia/Shanghai",
    "iso:country":"CN",
    "name:zho_x_preferred":[
        "\u9c87\u9c7c\u6e7e\u6751"
    ],
    "wof:name":"Nianyuwancun",
    "wof:placetype":"locality"
},
  "geometry": {"coordinates":[121.8905,38.97034],"type":"Point"}
}