{
  "type": "Feature",
  "properties": {
    "gn:admin1_code":"12.0",
    "gn:asciiname":"Xiongjiawan",
    "gn:country_code":"CN",
    "gn:dem":19,
    "gn:feature_class":"P",
    "gn:feature_code":"PPL",
    "gn:name":"Xiongjiawan",
    "gn:population":0,
    "gn:timezone":"Asia/Shanghai",
    "iso:country":"CN",
    "name:zho_x_preferred":[
        "Xiongjiawan"
    ],
    "name:zho_x_variant":[
        "\u718a\u5bb6\u6e7e"
    ],
    "wof:name":"Xiongjiawan",
    "wof:placetype":"locality"
},
  "geometry": {"coordinates":[115.12988,29.78728],"type":"Point"}
}