{
  "type": "Feature",
  "properties": {
    "gn:admin1_code":"3.0",
    "gn:asciiname":"Dahekeng",
    "gn:country_code":"CN",
    "gn:dem":588,
    "gn:feature_class":"P",
    "gn:feature_code":"PPL",
    "gn:name":"Dahekeng",
    "gn:population":0,
    "gn:timezone":"Asia/Shanghai",
    "iso:country":"CN",
    "name:und_x_variant":[
        "\u5927\u79be\u5751"
    ],
    "wof:name":"Dahekeng",
    "wof:placetype":"locality"
},
  "geometry": {"coordinates":[115.51777,25.30723],"type":"Point"}
}