{
  "type": "Feature",
  "properties": {
    "gn:admin1_code":"4.0",
    "gn:asciiname":"Tangyangcun",
    "gn:country_code":"CN",
    "gn:dem":18,
    "gn:feature_class":"P",
    "gn:feature_code":"PPL",
    "gn:name":"Tangyangcun",
    "gn:population":0,
    "gn:timezone":"Asia/Shanghai",
    "iso:country":"CN",
    "name:zho_x_preferred":[
        "\u5510\u6768\u6751"
    ],
    "wof:name":"Tangyangcun",
    "wof:placetype":"locality"
},
  "geometry": {"coordinates":[118.43231000000002,33.66070999999999],"type":"Point"}
}