{
  "type": "Feature",
  "properties": {
    "gn:admin1_code":"30.0",
    "gn:asciiname":"Hamashicun",
    "gn:country_code":"CN",
    "gn:dem":6,
    "gn:feature_class":"P",
    "gn:feature_code":"PPL",
    "gn:name":"Hamashicun",
    "gn:population":0,
    "gn:timezone":"Asia/Shanghai",
    "iso:country":"CN",
    "name:zho_x_preferred":[
        "\u86e4\u87c6\u77f3\u6751"
    ],
    "wof:name":"Hamashicun",
    "wof:placetype":"locality"
},
  "geometry": {"coordinates":[116.97351999999999,23.64639],"type":"Point"}
}