{
  "type": "Feature",
  "properties": {
    "gn:admin1_code":"11.0",
    "gn:asciiname":"Fujiaping",
    "gn:country_code":"CN",
    "gn:dem":70,
    "gn:feature_class":"P",
    "gn:feature_code":"PPL",
    "gn:name":"Fujiaping",
    "gn:population":0,
    "gn:timezone":"Asia/Shanghai",
    "iso:country":"CN",
    "name:zho_x_preferred":[
        "\u5bcc\u5bb6\u576a"
    ],
    "wof:name":"Fujiaping",
    "wof:placetype":"locality"
},
  "geometry": {"coordinates":[112.8214,26.68724000000001],"type":"Point"}
}