{
  "type": "Feature",
  "properties": {
    "gn:admin1_code":"10.0",
    "gn:asciiname":"Yangjiagou",
    "gn:cc2":"CN",
    "gn:country_code":"CN",
    "gn:dem":804,
    "gn:feature_class":"P",
    "gn:feature_code":"PPL",
    "gn:name":"Yangjiagou",
    "gn:population":0,
    "gn:timezone":"Asia/Shanghai",
    "iso:country":"CN",
    "name:und_x_variant":[
        "Yang-chia-kou",
        "Yangjiagou"
    ],
    "wof:name":"Yangjiagou",
    "wof:placetype":"locality"
},
  "geometry": {"coordinates":[114.03333000000001,38.48333],"type":"Point"}
}