{
  "type": "Feature",
  "properties": {
    "gn:admin1_code":"4.0",
    "gn:asciiname":"Qiandaxizhuang",
    "gn:country_code":"CN",
    "gn:dem":4,
    "gn:feature_class":"P",
    "gn:feature_code":"PPL",
    "gn:name":"Qiandaxizhuang",
    "gn:population":0,
    "gn:timezone":"Asia/Shanghai",
    "iso:country":"CN",
    "name:zho_x_preferred":[
        "\u524d\u5927\u897f\u5e84"
    ],
    "wof:name":"Qiandaxizhuang",
    "wof:placetype":"locality"
},
  "geometry": {"coordinates":[120.402,32.2356],"type":"Point"}
}