{
  "type": "Feature",
  "properties": {
    "gn:admin1_code":"11.0",
    "gn:asciiname":"Zaohetang",
    "gn:country_code":"CN",
    "gn:dem":108,
    "gn:feature_class":"P",
    "gn:feature_code":"PPL",
    "gn:name":"Zaohetang",
    "gn:population":0,
    "gn:timezone":"Asia/Shanghai",
    "iso:country":"CN",
    "name:zho_x_preferred":[
        "\u65e9\u79be\u5858"
    ],
    "wof:name":"Zaohetang",
    "wof:placetype":"locality"
},
  "geometry": {"coordinates":[112.68854,27.38378],"type":"Point"}
}