{
  "type": "Feature",
  "properties": {
    "gn:admin1_code":"07",
    "gn:asciiname":"Changting",
    "gn:country_code":"CN",
    "gn:dem":394,
    "gn:feature_class":"P",
    "gn:feature_code":"PPL",
    "gn:name":"Changting",
    "gn:population":0,
    "gn:timezone":"Asia/Shanghai",
    "iso:country":"CN",
    "name:ara_x_preferred":[
        "\u062a\u0634\u0627\u0646\u063a\u062a\u064a\u0646\u063a"
    ],
    "name:ben_x_preferred":[
        "\u099a\u09cd\u09af\u09be\u0982\u09a4\u09bf\u0982"
    ],
    "name:deu_x_preferred":[
        "Changting"
    ],
    "name:ell_x_preferred":[
        "\u03a4\u03c3\u03b1\u03bd\u03b3\u03ba\u03c4\u03af\u03bd\u03b3\u03ba"
    ],
    "name:eng_x_preferred":[
        "Changting"
    ],
    "name:fas_x_preferred":[
        "\u0686\u0627\u0646\u06af \u062a\u06cc\u0646\u06af"
    ],
    "name:fra_x_preferred":[
        "Changting"
    ],
    "name:heb_x_preferred":[
        "\u05e6'\u05e0\u05d2\u05d8\u05d9\u05e0\u05d2"
    ],
    "name:hin_x_preferred":[
        "\u091a\u0948\u0902\u0917\u091f\u093f\u0902\u0917"
    ],
    "name:hun_x_preferred":[
        "Changting"
    ],
    "name:ind_x_preferred":[
        "Changting"
    ],
    "name:ita_x_preferred":[
        "Changting"
    ],
    "name:jpn_x_preferred":[
        "\u9577\u6c40"
    ],
    "name:kor_x_preferred":[
        "\ucc3d\ud305"
    ],
    "name:nld_x_preferred":[
        "Changting"
    ],
    "name:pol_x_preferred":[
        "Changting"
    ],
    "name:por_x_preferred":[
        "Changting"
    ],
    "name:rus_x_preferred":[
        "\u0427\u0430\u043d\u0442\u0438\u043d"
    ],
    "name:spa_x_preferred":[
        "Changting"
    ],
    "name:swe_x_preferred":[
        "Changting"
    ],
    "name:tur_x_preferred":[
        "Changting"
    ],
    "name:ukr_x_preferred":[
        "\u0427\u0436\u0430\u043d\u0442\u0456\u043d"
    ],
    "name:urd_x_preferred":[
        "\u0686\u06cc\u0646\u06af\u0679\u0646\u06af"
    ],
    "name:vie_x_preferred":[
        "Tr\u01b0\u1eddng \u0110inh"
    ],
    "name:zho_cn_x_preferred":[
        "\u957f\u6c40\u53bf"
    ],
    "name:zho_tw_x_preferred":[
        "\u9577\u6c40"
    ],
    "name:zho_x_preferred":[
        "\u957f\u6c40"
    ],
    "wof:name":"Changting",
    "wof:placetype":"locality"
},
  "geometry": {"coordinates":[117.92067,25.43284],"type":"Point"}
}