{
  "type": "Feature",
  "properties": {
    "gn:admin1_code":"25",
    "gn:asciiname":"Siqicang",
    "gn:country_code":"CN",
    "gn:dem":8,
    "gn:feature_class":"P",
    "gn:feature_code":"PPL",
    "gn:name":"Siqicang",
    "gn:population":0,
    "gn:timezone":"Asia/Shanghai",
    "iso:country":"CN",
    "name:zho_x_preferred":[
        "\u56db\u5c90\u4ed3"
    ],
    "wof:name":"Siqicang",
    "wof:placetype":"locality"
},
  "geometry": {"coordinates":[118.934,37.0071],"type":"Point"}
}