{
  "type": "Feature",
  "properties": {
    "gn:admin1_code":"30.0",
    "gn:asciiname":"Zhuhuatang",
    "gn:country_code":"CN",
    "gn:dem":114,
    "gn:feature_class":"P",
    "gn:feature_code":"PPL",
    "gn:name":"Zhuhuatang",
    "gn:population":0,
    "gn:timezone":"Asia/Shanghai",
    "iso:country":"CN",
    "name:zho_x_preferred":[
        "\u7af9\u534e\u5858"
    ],
    "wof:name":"Zhuhuatang",
    "wof:placetype":"locality"
},
  "geometry": {"coordinates":[115.70775999999999,23.98579],"type":"Point"}
}