{
  "type": "Feature",
  "properties": {
    "gn:admin1_code":"30.0",
    "gn:asciiname":"Zhangcun",
    "gn:country_code":"CN",
    "gn:dem":461,
    "gn:feature_class":"P",
    "gn:feature_code":"PPL",
    "gn:name":"Zhangcun",
    "gn:population":0,
    "gn:timezone":"Asia/Shanghai",
    "iso:country":"CN",
    "name:und_x_variant":[
        "\u5d82\u6751"
    ],
    "name:zho_x_preferred":[
        "\u5d82\u6751"
    ],
    "wof:name":"Zhangcun",
    "wof:placetype":"locality"
},
  "geometry": {"coordinates":[115.44429,23.91081],"type":"Point"}
}