{
  "type": "Feature",
  "properties": {
    "gn:admin1_code":"2.0",
    "gn:asciiname":"Shangtang",
    "gn:country_code":"CN",
    "gn:dem":99,
    "gn:feature_class":"P",
    "gn:feature_code":"PPL",
    "gn:name":"Shangtang",
    "gn:population":0,
    "gn:timezone":"Asia/Shanghai",
    "iso:country":"CN",
    "name:und_x_variant":[
        "\u4e0a\u5510",
        "Shangtang"
    ],
    "wof:name":"Shangtang",
    "wof:placetype":"locality"
},
  "geometry": {"coordinates":[119.35276,29.33025],"type":"Point"}
}