{
  "type": "Feature",
  "properties": {
    "gn:admin1_code":"1.0",
    "gn:asciiname":"Xianrenchongcun",
    "gn:country_code":"CN",
    "gn:dem":352,
    "gn:feature_class":"P",
    "gn:feature_code":"PPL",
    "gn:name":"Xianrenchongcun",
    "gn:population":0,
    "gn:timezone":"Asia/Shanghai",
    "iso:country":"CN",
    "name:zho_x_preferred":[
        "\u4ed9\u4eba\u51b2\u6751"
    ],
    "wof:name":"Xianrenchongcun",
    "wof:placetype":"locality"
},
  "geometry": {"coordinates":[116.15124,31.38338],"type":"Point"}
}