{
  "type": "Feature",
  "properties": {
    "gn:admin1_code":"8.0",
    "gn:asciiname":"Qiankuangcun",
    "gn:country_code":"CN",
    "gn:dem":212,
    "gn:feature_class":"P",
    "gn:feature_code":"PPL",
    "gn:name":"Qiankuangcun",
    "gn:population":0,
    "gn:timezone":"Asia/Shanghai",
    "iso:country":"CN",
    "name:zho_x_preferred":[
        "\u94c5\u77ff\u6751"
    ],
    "wof:name":"Qiankuangcun",
    "wof:placetype":"locality"
},
  "geometry": {"coordinates":[130.81071,45.2615],"type":"Point"}
}