{
  "type": "Feature",
  "properties": {
    "gn:admin1_code":"11",
    "gn:asciiname":"Wuluo",
    "gn:country_code":"CN",
    "gn:dem":509,
    "gn:feature_class":"P",
    "gn:feature_code":"PPL",
    "gn:name":"Wuluo",
    "gn:population":0,
    "gn:timezone":"Asia/Shanghai",
    "iso:country":"CN",
    "name:zho_x_preferred":[
        "\u4e94\u7f57"
    ],
    "wof:name":"Wuluo",
    "wof:placetype":"locality"
},
  "geometry": {"coordinates":[110.90582999999999,27.58083],"type":"Point"}
}