{
  "type": "Feature",
  "properties": {
    "gn:admin1_code":"5.0",
    "gn:asciiname":"Yongqingcun",
    "gn:country_code":"CN",
    "gn:dem":132,
    "gn:feature_class":"P",
    "gn:feature_code":"PPL",
    "gn:name":"Yongqingcun",
    "gn:population":0,
    "gn:timezone":"Asia/Shanghai",
    "iso:country":"CN",
    "name:zho_x_preferred":[
        "\u6c38\u5e86\u6751"
    ],
    "wof:name":"Yongqingcun",
    "wof:placetype":"locality"
},
  "geometry": {"coordinates":[123.79340000000001,45.61912],"type":"Point"}
}