{
  "type": "Feature",
  "properties": {
    "gn:admin1_code":"16.0",
    "gn:asciiname":"Liugui",
    "gn:country_code":"CN",
    "gn:dem":184,
    "gn:feature_class":"P",
    "gn:feature_code":"PPL",
    "gn:name":"Liugui",
    "gn:population":0,
    "gn:timezone":"Asia/Shanghai",
    "iso:country":"CN",
    "name:zho_x_preferred":[
        "\u516d\u8d35"
    ],
    "wof:name":"Liugui",
    "wof:placetype":"locality"
},
  "geometry": {"coordinates":[110.01000000000001,24.1221],"type":"Point"}
}