{
  "type": "Feature",
  "properties": {
    "gn:admin1_code":"9",
    "gn:asciiname":"Liugutong",
    "gn:country_code":"CN",
    "gn:dem":47,
    "gn:feature_class":"P",
    "gn:feature_code":"PPL",
    "gn:name":"Liugutong",
    "gn:population":0,
    "gn:timezone":"Asia/Shanghai",
    "iso:country":"CN",
    "name:zho_x_preferred":[
        "\u5218\u53e4\u540c"
    ],
    "wof:name":"Liugutong",
    "wof:placetype":"locality"
},
  "geometry": {"coordinates":[115.898,34.1568],"type":"Point"}
}