{
  "type": "Feature",
  "properties": {
    "gn:admin1_code":"14.0",
    "gn:asciiname":"Zongra",
    "gn:country_code":"CN",
    "gn:dem":3726,
    "gn:feature_class":"P",
    "gn:feature_code":"PPL",
    "gn:name":"Zongra",
    "gn:population":0,
    "gn:timezone":"Asia/Urumqi",
    "iso:country":"CN",
    "name:bod_x_preferred":[
        "Zongra"
    ],
    "name:zho_x_preferred":[
        "Zongre"
    ],
    "name:zho_x_variant":[
        "\u5b97\u70ed"
    ],
    "wof:name":"Zongra",
    "wof:placetype":"locality"
},
  "geometry": {"coordinates":[96.43321,30.23344],"type":"Point"}
}