{
  "type": "Feature",
  "properties": {
    "gn:admin1_code":"15.0",
    "gn:asciiname":"Jinjiazhuang",
    "gn:country_code":"CN",
    "gn:dem":2557,
    "gn:feature_class":"P",
    "gn:feature_code":"PPL",
    "gn:name":"Jinjiazhuang",
    "gn:population":0,
    "gn:timezone":"Asia/Shanghai",
    "iso:country":"CN",
    "name:zho_x_preferred":[
        "\u9773\u5bb6\u5e84"
    ],
    "wof:name":"Jinjiazhuang",
    "wof:placetype":"locality"
},
  "geometry": {"coordinates":[101.22799999999999,38.3174],"type":"Point"}
}