{
  "type": "Feature",
  "properties": {
    "gn:admin1_code":"1.0",
    "gn:asciiname":"Jidazhaicun",
    "gn:country_code":"CN",
    "gn:dem":32,
    "gn:feature_class":"P",
    "gn:feature_code":"PPL",
    "gn:name":"Jidazhaicun",
    "gn:population":0,
    "gn:timezone":"Asia/Shanghai",
    "iso:country":"CN",
    "name:zho_x_preferred":[
        "\u7eaa\u5927\u5be8\u6751"
    ],
    "wof:name":"Jidazhaicun",
    "wof:placetype":"locality"
},
  "geometry": {"coordinates":[116.10424999999999,33.32292],"type":"Point"}
}