{
  "type": "Feature",
  "properties": {
    "gn:admin1_code":"32.0",
    "gn:asciiname":"Linjiayan",
    "gn:country_code":"CN",
    "gn:dem":794,
    "gn:feature_class":"P",
    "gn:feature_code":"PPL",
    "gn:name":"Linjiayan",
    "gn:population":0,
    "gn:timezone":"Asia/Shanghai",
    "iso:country":"CN",
    "name:zho_x_preferred":[
        "\u6797\u5bb6\u5ca9"
    ],
    "wof:name":"Linjiayan",
    "wof:placetype":"locality"
},
  "geometry": {"coordinates":[107.02222999999999,30.52862],"type":"Point"}
}