{
  "type": "Feature",
  "properties": {
    "gn:admin1_code":"15.0",
    "gn:asciiname":"Yaogoupo",
    "gn:country_code":"CN",
    "gn:dem":2709,
    "gn:feature_class":"P",
    "gn:feature_code":"PPL",
    "gn:name":"Yaogoupo",
    "gn:population":0,
    "gn:timezone":"Asia/Shanghai",
    "iso:country":"CN",
    "name:und_x_variant":[
        "\u7a91\u6c9f\u5761"
    ],
    "wof:name":"Yaogoupo",
    "wof:placetype":"locality"
},
  "geometry": {"coordinates":[103.93761000000001,34.55871],"type":"Point"}
}