{
  "type": "Feature",
  "properties": {
    "gn:admin1_code":"30.0",
    "gn:asciiname":"Shikeng",
    "gn:country_code":"CN",
    "gn:dem":353,
    "gn:feature_class":"P",
    "gn:feature_code":"PPL",
    "gn:name":"Shikeng",
    "gn:population":0,
    "gn:timezone":"Asia/Shanghai",
    "iso:country":"CN",
    "name:zho_x_preferred":[
        "\u65f6\u5751"
    ],
    "wof:name":"Shikeng",
    "wof:placetype":"locality"
},
  "geometry": {"coordinates":[115.27058999999998,23.38962],"type":"Point"}
}