{
  "type": "Feature",
  "properties": {
    "gn:admin1_code":"24",
    "gn:asciiname":"Dalianhua",
    "gn:country_code":"CN",
    "gn:dem":1322,
    "gn:feature_class":"P",
    "gn:feature_code":"PPL",
    "gn:name":"Dalianhua",
    "gn:population":0,
    "gn:timezone":"Asia/Shanghai",
    "iso:country":"CN",
    "name:und_x_variant":[
        "Ta-lien-hua",
        "Dalianhua",
        "\u5927\u83b2\u82b1"
    ],
    "wof:name":"Dalianhua",
    "wof:placetype":"locality"
},
  "geometry": {"coordinates":[112.61348,39.13025],"type":"Point"}
}