{
  "type": "Feature",
  "properties": {
    "gn:admin1_code":"04",
    "gn:asciiname":"Shixiang",
    "gn:country_code":"CN",
    "gn:dem":43,
    "gn:feature_class":"P",
    "gn:feature_code":"PPL",
    "gn:name":"Shixiang",
    "gn:population":0,
    "gn:timezone":"Asia/Shanghai",
    "iso:country":"CN",
    "name:und_x_variant":[
        "Shih-hsiang",
        "Shixiang"
    ],
    "name:zho_x_preferred":[
        "\u77f3\u5df7"
    ],
    "wof:name":"Shixiang",
    "wof:placetype":"locality"
},
  "geometry": {"coordinates":[119.27431,31.75438],"type":"Point"}
}