{
  "type": "Feature",
  "properties": {
    "gn:admin1_code":"30",
    "gn:asciiname":"Tangjia",
    "gn:country_code":"CN",
    "gn:dem":44,
    "gn:feature_class":"P",
    "gn:feature_code":"PPLA4",
    "gn:name":"Tangjia",
    "gn:population":0,
    "gn:timezone":"Asia/Urumqi",
    "iso:country":"CN",
    "name:und_x_variant":[
        "Tangjia Zhen",
        "\u5510\u5bb6\u9547"
    ],
    "name:zho_x_preferred":[
        "T\u2019ang-chia"
    ],
    "name:zho_x_variant":[
        "\u5510\u5bb6"
    ],
    "wof:name":"Tangjia",
    "wof:placetype":"locality"
},
  "geometry": {"coordinates":[109.84694,20.8425],"type":"Point"}
}