{
  "type": "Feature",
  "properties": {
    "gn:admin1_code":"32.0",
    "gn:asciiname":"Yuba",
    "gn:country_code":"CN",
    "gn:dem":723,
    "gn:feature_class":"P",
    "gn:feature_code":"PPL",
    "gn:name":"Yuba",
    "gn:population":0,
    "gn:timezone":"Asia/Shanghai",
    "iso:country":"CN",
    "name:zho_x_preferred":[
        "\u4f59\u575d"
    ],
    "wof:name":"Yuba",
    "wof:placetype":"locality"
},
  "geometry": {"coordinates":[105.441,32.4927],"type":"Point"}
}