{
  "type": "Feature",
  "properties": {
    "gn:admin1_code":"33.0",
    "gn:asciiname":"Huoshao Baimiao",
    "gn:country_code":"CN",
    "gn:dem":918,
    "gn:feature_class":"P",
    "gn:feature_code":"PPL",
    "gn:name":"Huoshao Baimiao",
    "gn:population":0,
    "gn:timezone":"Asia/Shanghai",
    "iso:country":"CN",
    "name:zho_x_preferred":[
        "\u706b\u70e7\u767d\u5e99"
    ],
    "wof:name":"Huoshao Baimiao",
    "wof:placetype":"locality"
},
  "geometry": {"coordinates":[108.74146,28.79098],"type":"Point"}
}