{
  "type": "Feature",
  "properties": {
    "gn:admin1_code":"19.0",
    "gn:asciiname":"Hadayingzi",
    "gn:country_code":"CN",
    "gn:dem":256,
    "gn:feature_class":"P",
    "gn:feature_code":"PPL",
    "gn:name":"Hadayingzi",
    "gn:population":0,
    "gn:timezone":"Asia/Shanghai",
    "iso:country":"CN",
    "name:und_x_variant":[
        "\u54c8\u8fbe\u8425\u5b50"
    ],
    "name:zho_x_preferred":[
        "\u54c8\u8fbe\u8425\u5b50"
    ],
    "wof:name":"Hadayingzi",
    "wof:placetype":"locality"
},
  "geometry": {"coordinates":[121.67045,42.37491],"type":"Point"}
}