{
  "type": "Feature",
  "properties": {
    "gn:admin1_code":"32.0",
    "gn:asciiname":"Dengta",
    "gn:country_code":"CN",
    "gn:dem":358,
    "gn:feature_class":"P",
    "gn:feature_code":"PPL",
    "gn:name":"Dengta",
    "gn:population":0,
    "gn:timezone":"Asia/Shanghai",
    "iso:country":"CN",
    "name:ara_x_preferred":[
        "\u062f\u064a\u0646\u063a\u062a\u0627"
    ],
    "name:deu_x_preferred":[
        "Dengta"
    ],
    "name:fra_x_preferred":[
        "Dengta"
    ],
    "name:ita_x_preferred":[
        "Dengta"
    ],
    "name:jpn_x_preferred":[
        "\u706f\u5854\u5e02"
    ],
    "name:kik_x_preferred":[
        "Dengta"
    ],
    "name:kor_x_preferred":[
        "\ub369\ud0c0\uc2dc"
    ],
    "name:nor_x_preferred":[
        "Dengta"
    ],
    "name:rus_x_preferred":[
        "\u0414\u044d\u043d\u0442\u0430"
    ],
    "name:swe_x_preferred":[
        "Dengta"
    ],
    "name:urd_x_preferred":[
        "\u062f\u06cc\u0646\u06af\u062a\u0627"
    ],
    "name:vie_x_preferred":[
        "\u0110\u0103ng Th\u00e1p"
    ],
    "name:zho_x_preferred":[
        "\u706f\u5854"
    ],
    "name:zho_x_variant":[
        "\u706f\u5854\u5e02"
    ],
    "wof:name":"Dengta",
    "wof:placetype":"locality"
},
  "geometry": {"coordinates":[106.66578,31.38724],"type":"Point"}
}