{
  "type": "Feature",
  "properties": {
    "gn:admin1_code":"32.0",
    "gn:asciiname":"Baimu",
    "gn:country_code":"CN",
    "gn:dem":1204,
    "gn:feature_class":"P",
    "gn:feature_code":"PPL",
    "gn:name":"Baimu",
    "gn:population":0,
    "gn:timezone":"Asia/Shanghai",
    "iso:country":"CN",
    "name:zho_x_preferred":[
        "\u67cf\u6728"
    ],
    "wof:name":"Baimu",
    "wof:placetype":"locality"
},
  "geometry": {"coordinates":[103.83499999999999,28.376],"type":"Point"}
}