{
  "type": "Feature",
  "properties": {
    "gn:admin1_code":"26.0",
    "gn:asciiname":"Niancun",
    "gn:country_code":"CN",
    "gn:dem":638,
    "gn:feature_class":"P",
    "gn:feature_code":"PPL",
    "gn:name":"Niancun",
    "gn:population":0,
    "gn:timezone":"Asia/Shanghai",
    "iso:country":"CN",
    "name:zho_x_preferred":[
        "\u57dd\u6751"
    ],
    "wof:name":"Niancun",
    "wof:placetype":"locality"
},
  "geometry": {"coordinates":[109.89359,35.12134],"type":"Point"}
}