{
  "type": "Feature",
  "properties": {
    "gn:admin1_code":"12.0",
    "gn:asciiname":"Mayanghe",
    "gn:country_code":"CN",
    "gn:dem":285,
    "gn:feature_class":"P",
    "gn:feature_code":"PPL",
    "gn:name":"Mayanghe",
    "gn:population":0,
    "gn:timezone":"Asia/Shanghai",
    "iso:country":"CN",
    "name:zho_x_preferred":[
        "Mayanghe"
    ],
    "name:zho_x_variant":[
        "\u9ebb\u7f8a\u6cb3"
    ],
    "wof:name":"Mayanghe",
    "wof:placetype":"locality"
},
  "geometry": {"coordinates":[111.59535,30.92384],"type":"Point"}
}