{
  "type": "Feature",
  "properties": {
    "gn:admin1_code":"18.0",
    "gn:asciiname":"Qianjin",
    "gn:country_code":"CN",
    "gn:dem":738,
    "gn:feature_class":"P",
    "gn:feature_code":"PPL",
    "gn:name":"Qianjin",
    "gn:population":0,
    "gn:timezone":"Asia/Shanghai",
    "iso:country":"CN",
    "name:zho_x_preferred":[
        "\u524d\u8fdb"
    ],
    "wof:name":"Qianjin",
    "wof:placetype":"locality"
},
  "geometry": {"coordinates":[108.741,25.8224],"type":"Point"}
}