{
  "type": "Feature",
  "properties": {
    "gn:admin1_code":"32.0",
    "gn:asciiname":"Huachangtou",
    "gn:country_code":"CN",
    "gn:dem":638,
    "gn:feature_class":"P",
    "gn:feature_code":"PPL",
    "gn:name":"Huachangtou",
    "gn:population":0,
    "gn:timezone":"Asia/Shanghai",
    "iso:country":"CN",
    "name:zho_x_preferred":[
        "\u94e7\u5382\u5934"
    ],
    "wof:name":"Huachangtou",
    "wof:placetype":"locality"
},
  "geometry": {"coordinates":[105.42700000000001,32.2492],"type":"Point"}
}