{
  "type": "Feature",
  "properties": {
    "gn:admin1_code":"1.0",
    "gn:asciiname":"Nongzhuangcun",
    "gn:country_code":"CN",
    "gn:dem":15,
    "gn:feature_class":"P",
    "gn:feature_code":"PPL",
    "gn:name":"Nongzhuangcun",
    "gn:population":0,
    "gn:timezone":"Asia/Shanghai",
    "iso:country":"CN",
    "name:zho_x_preferred":[
        "\u519c\u5e84\u6751"
    ],
    "wof:name":"Nongzhuangcun",
    "wof:placetype":"locality"
},
  "geometry": {"coordinates":[118.21263,33.07549],"type":"Point"}
}