{
  "type": "Feature",
  "properties": {
    "gn:admin1_code":"16.0",
    "gn:asciiname":"Zhaibeicun",
    "gn:country_code":"CN",
    "gn:dem":248,
    "gn:feature_class":"P",
    "gn:feature_code":"PPL",
    "gn:name":"Zhaibeicun",
    "gn:population":0,
    "gn:timezone":"Asia/Shanghai",
    "iso:country":"CN",
    "name:zho_x_preferred":[
        "\u5be8\u5317\u6751"
    ],
    "wof:name":"Zhaibeicun",
    "wof:placetype":"locality"
},
  "geometry": {"coordinates":[108.989,24.1164],"type":"Point"}
}