{
  "type": "Feature",
  "properties": {
    "gn:admin1_code":"30.0",
    "gn:asciiname":"Jiaobei",
    "gn:country_code":"CN",
    "gn:dem":0,
    "gn:feature_class":"P",
    "gn:feature_code":"PPLA4",
    "gn:name":"Jiaobei",
    "gn:population":0,
    "gn:timezone":"Asia/Shanghai",
    "iso:country":"CN",
    "name:und_x_variant":[
        "Jiaobei Jiedao"
    ],
    "name:zho_x_preferred":[
        "\u6ed8\u5317"
    ],
    "name:zho_x_variant":[
        "\u6ed8\u5317\u8857\u9053"
    ],
    "wof:name":"Jiaobei",
    "wof:placetype":"locality"
},
  "geometry": {"coordinates":[113.10266,22.59653],"type":"Point"}
}