{
  "type": "Feature",
  "properties": {
    "gn:admin1_code":"31.0",
    "gn:asciiname":"Wengguo",
    "gn:country_code":"CN",
    "gn:dem":48,
    "gn:feature_class":"P",
    "gn:feature_code":"PPL",
    "gn:name":"Wengguo",
    "gn:population":0,
    "gn:timezone":"Asia/Shanghai",
    "iso:country":"CN",
    "name:zho_x_preferred":[
        "\u7fc1\u90ed"
    ],
    "wof:name":"Wengguo",
    "wof:placetype":"locality"
},
  "geometry": {"coordinates":[110.24576999999999,19.63039],"type":"Point"}
}