{
  "type": "Feature",
  "properties": {
    "gn:admin1_code":"25.0",
    "gn:asciiname":"Duixujia",
    "gn:country_code":"CN",
    "gn:dem":69,
    "gn:feature_class":"P",
    "gn:feature_code":"PPL",
    "gn:name":"Duixujia",
    "gn:population":0,
    "gn:timezone":"Asia/Shanghai",
    "iso:country":"CN",
    "name:zho_x_preferred":[
        "\u7893\u5f90\u5bb6"
    ],
    "wof:name":"Duixujia",
    "wof:placetype":"locality"
},
  "geometry": {"coordinates":[120.52330000000001,37.60285],"type":"Point"}
}