{
  "type": "Feature",
  "properties": {
    "gn:admin1_code":"29.0",
    "gn:asciiname":"Dabaishiyan",
    "gn:country_code":"CN",
    "gn:dem":1994,
    "gn:feature_class":"P",
    "gn:feature_code":"PPL",
    "gn:name":"Dabaishiyan",
    "gn:population":0,
    "gn:timezone":"Asia/Shanghai",
    "iso:country":"CN",
    "name:zho_x_preferred":[
        "\u5927\u767d\u77f3\u5ca9"
    ],
    "wof:name":"Dabaishiyan",
    "wof:placetype":"locality"
},
  "geometry": {"coordinates":[102.148,25.3155],"type":"Point"}
}