{
  "type": "Feature",
  "properties": {
    "gn:admin1_code":"18",
    "gn:asciiname":"Baimujia",
    "gn:country_code":"CN",
    "gn:dem":1862,
    "gn:feature_class":"P",
    "gn:feature_code":"PPL",
    "gn:name":"Baimujia",
    "gn:population":0,
    "gn:timezone":"Asia/Shanghai",
    "iso:country":"CN",
    "name:zho_x_preferred":[
        "\u767d\u6728\u621b"
    ],
    "wof:name":"Baimujia",
    "wof:placetype":"locality"
},
  "geometry": {"coordinates":[104.581,26.1643],"type":"Point"}
}