{
  "type": "Feature",
  "properties": {
    "gn:admin1_code":"29",
    "gn:asciiname":"Langdaoshu",
    "gn:country_code":"CN",
    "gn:dem":2093,
    "gn:feature_class":"P",
    "gn:feature_code":"PPL",
    "gn:name":"Langdaoshu",
    "gn:population":0,
    "gn:timezone":"Asia/Shanghai",
    "iso:country":"CN",
    "name:zho_x_preferred":[
        "\u6d6a\u5012\u6811"
    ],
    "wof:name":"Langdaoshu",
    "wof:placetype":"locality"
},
  "geometry": {"coordinates":[101.334,24.99],"type":"Point"}
}