{
  "type": "Feature",
  "properties": {
    "gn:admin1_code":"26.0",
    "gn:asciiname":"Xinyaotai",
    "gn:country_code":"CN",
    "gn:dem":1217,
    "gn:feature_class":"P",
    "gn:feature_code":"PPL",
    "gn:name":"Xinyaotai",
    "gn:population":0,
    "gn:timezone":"Asia/Shanghai",
    "iso:country":"CN",
    "name:zho_x_preferred":[
        "\u65b0\u7a91\u53f0"
    ],
    "wof:name":"Xinyaotai",
    "wof:placetype":"locality"
},
  "geometry": {"coordinates":[109.76871,37.75318],"type":"Point"}
}