{
  "type": "Feature",
  "properties": {
    "gn:admin1_code":"14.0",
    "gn:asciiname":"Senmu",
    "gn:country_code":"CN",
    "gn:dem":4992,
    "gn:feature_class":"P",
    "gn:feature_code":"PPLF",
    "gn:name":"Senmu",
    "gn:population":0,
    "gn:timezone":"Asia/Urumqi",
    "iso:country":"CN",
    "name:bod_x_preferred":[
        "S\u00eam"
    ],
    "name:zho_x_preferred":[
        "Senmu"
    ],
    "name:zho_x_variant":[
        "\u68ee\u6728"
    ],
    "wof:name":"Senmu",
    "wof:placetype":"locality"
},
  "geometry": {"coordinates":[92.801,28.801],"type":"Point"}
}