{
  "type": "Feature",
  "properties": {
    "gn:admin1_code":"28.0",
    "gn:asciiname":"Wangguantun",
    "gn:country_code":"CN",
    "gn:dem":8,
    "gn:feature_class":"P",
    "gn:feature_code":"PPL",
    "gn:name":"Wangguantun",
    "gn:population":0,
    "gn:timezone":"Asia/Shanghai",
    "iso:country":"CN",
    "name:zho_x_preferred":[
        "\u738b\u5b98\u5c6f"
    ],
    "wof:name":"Wangguantun",
    "wof:placetype":"locality"
},
  "geometry": {"coordinates":[116.91733000000001,38.77285],"type":"Point"}
}