{
  "type": "Feature",
  "properties": {
    "gn:admin1_code":"26.0",
    "gn:asciiname":"Mengjiayaozi",
    "gn:country_code":"CN",
    "gn:dem":964,
    "gn:feature_class":"P",
    "gn:feature_code":"PPL",
    "gn:name":"Mengjiayaozi",
    "gn:population":0,
    "gn:timezone":"Asia/Shanghai",
    "iso:country":"CN",
    "name:zho_x_preferred":[
        "\u5b5f\u5bb6\u7a91\u5b50"
    ],
    "wof:name":"Mengjiayaozi",
    "wof:placetype":"locality"
},
  "geometry": {"coordinates":[110.31270000000001,36.62012],"type":"Point"}
}