{
  "type": "Feature",
  "properties": {
    "gn:admin1_code":"19.0",
    "gn:asciiname":"Songjiagou",
    "gn:country_code":"CN",
    "gn:dem":124,
    "gn:feature_class":"P",
    "gn:feature_code":"PPL",
    "gn:name":"Songjiagou",
    "gn:population":0,
    "gn:timezone":"Asia/Shanghai",
    "iso:country":"CN",
    "name:und_x_variant":[
        "\u5b8b\u5bb6\u6c9f"
    ],
    "name:zho_x_preferred":[
        "\u5b8b\u5bb6\u6c9f"
    ],
    "wof:name":"Songjiagou",
    "wof:placetype":"locality"
},
  "geometry": {"coordinates":[123.83122,42.14612],"type":"Point"}
}