{
  "type": "Feature",
  "properties": {
    "gn:admin1_code":"7.0",
    "gn:asciiname":"Qiapu",
    "gn:country_code":"CN",
    "gn:dem":16,
    "gn:feature_class":"P",
    "gn:feature_code":"PPL",
    "gn:name":"Qiapu",
    "gn:population":0,
    "gn:timezone":"Asia/Shanghai",
    "iso:country":"CN",
    "name:zho_x_preferred":[
        "\u6d3d\u6d66"
    ],
    "wof:name":"Qiapu",
    "wof:placetype":"locality"
},
  "geometry": {"coordinates":[119.1546,26.14023],"type":"Point"}
}