{
  "type": "Feature",
  "properties": {
    "gn:admin1_code":"14.0",
    "gn:asciiname":"Garnga",
    "gn:country_code":"CN",
    "gn:dem":4184,
    "gn:feature_class":"P",
    "gn:feature_code":"PPLF",
    "gn:name":"Garnga",
    "gn:population":0,
    "gn:timezone":"Asia/Urumqi",
    "iso:country":"CN",
    "name:bod_x_preferred":[
        "Garnga"
    ],
    "name:zho_x_preferred":[
        "Wuxing"
    ],
    "name:zho_x_variant":[
        "\u4e94\u661f",
        "Maya",
        "\u9a6c\u4e9a"
    ],
    "wof:name":"Garnga",
    "wof:placetype":"locality"
},
  "geometry": {"coordinates":[89.40299999999998,29.103],"type":"Point"}
}