{
  "type": "Feature",
  "properties": {
    "gn:admin1_code":"32.0",
    "gn:asciiname":"Wujia Yuanzi",
    "gn:country_code":"CN",
    "gn:dem":331,
    "gn:feature_class":"P",
    "gn:feature_code":"PPL",
    "gn:name":"Wujia Yuanzi",
    "gn:population":0,
    "gn:timezone":"Asia/Shanghai",
    "iso:country":"CN",
    "name:zho_x_preferred":[
        "\u5434\u5bb6\u9662\u5b50"
    ],
    "wof:name":"Wujia Yuanzi",
    "wof:placetype":"locality"
},
  "geometry": {"coordinates":[105.42164,30.82969000000001],"type":"Point"}
}