{
  "type": "Feature",
  "properties": {
    "gn:country":"CN",
    "gn:fcode":"ADM3",
    "gn:population":0,
    "iso:country":"CN",
    "name:und_x_variant":[
        "Hui-an Hsien"
    ],
    "name:zho_x_preferred":[
        "\u60e0\u5b89\u53bf"
    ],
    "name:zho_x_variant":[
        "Hui\u2019an Xian",
        "\u60e0\u5b89"
    ],
    "qs:name":"Hui\u2019an Xian",
    "qs:photos_9r":0,
    "qs:photos_sr":0,
    "qs:pop_sr":"0",
    "wof:name":"Hui\u2019an Xian",
    "wof:placetype":"localadmin",
    "wof:population":0
},
  "geometry": {"coordinates":[118.80177999999999,24.98068],"type":"Point"}
}