{
  "type": "Feature",
  "properties": {
    "gn:admin1_code":"11",
    "gn:asciiname":"Jiangkou",
    "gn:country_code":"CN",
    "gn:dem":536,
    "gn:feature_class":"P",
    "gn:feature_code":"PPL",
    "gn:name":"Jiangkou",
    "gn:population":0,
    "gn:timezone":"Asia/Shanghai",
    "iso:country":"CN",
    "wof:name":"Jiangkou",
    "wof:placetype":"locality"
},
  "geometry": {"coordinates":[109.67222,26.34667],"type":"Point"}
}