{
  "type": "Feature",
  "properties": {
    "gn:admin1_code":"4.0",
    "gn:asciiname":"Zhujiawan",
    "gn:country_code":"CN",
    "gn:dem":6,
    "gn:feature_class":"P",
    "gn:feature_code":"PPL",
    "gn:name":"Zhujiawan",
    "gn:population":0,
    "gn:timezone":"Asia/Shanghai",
    "iso:country":"CN",
    "name:und_x_variant":[
        "\u6731\u5bb6\u6e7e"
    ],
    "name:zho_x_preferred":[
        "\u6731\u5bb6\u6e7e"
    ],
    "wof:name":"Zhujiawan",
    "wof:placetype":"locality"
},
  "geometry": {"coordinates":[120.54595,31.60497],"type":"Point"}
}