{
  "type": "Feature",
  "properties": {
    "gn:admin1_code":"14.0",
    "gn:asciiname":"Wangbo Muchang",
    "gn:country_code":"CN",
    "gn:dem":3851,
    "gn:feature_class":"P",
    "gn:feature_code":"PPLF",
    "gn:name":"Wangbo Muchang",
    "gn:population":0,
    "gn:timezone":"Asia/Kolkata",
    "iso:country":"CN",
    "name:zho_x_preferred":[
        "\u6c6a\u6ce2\u7267\u573a"
    ],
    "wof:name":"Wangbo Muchang",
    "wof:placetype":"locality"
},
  "geometry": {"coordinates":[94.66607,29.32186],"type":"Point"}
}