{
  "type": "Feature",
  "properties": {
    "gn:admin1_code":"1.0",
    "gn:asciiname":"Kehucun",
    "gn:country_code":"CN",
    "gn:dem":20,
    "gn:feature_class":"P",
    "gn:feature_code":"PPL",
    "gn:name":"Kehucun",
    "gn:population":0,
    "gn:timezone":"Asia/Shanghai",
    "iso:country":"CN",
    "name:zho_x_preferred":[
        "\u67ef\u6e56\u6751"
    ],
    "wof:name":"Kehucun",
    "wof:placetype":"locality"
},
  "geometry": {"coordinates":[118.40322999999999,32.21802],"type":"Point"}
}