{
  "type": "Feature",
  "properties": {
    "gn:admin1_code":"4.0",
    "gn:asciiname":"Weiying",
    "gn:cc2":"CN",
    "gn:country_code":"CN",
    "gn:dem":25,
    "gn:feature_class":"P",
    "gn:feature_code":"PPL",
    "gn:name":"Weiying",
    "gn:population":0,
    "gn:timezone":"Asia/Shanghai",
    "iso:country":"CN",
    "name:und_x_variant":[
        "Wei-ying-tzu",
        "Weiying"
    ],
    "wof:name":"Weiying",
    "wof:placetype":"locality"
},
  "geometry": {"coordinates":[118.11167,33.33556],"type":"Point"}
}