{
  "type": "Feature",
  "properties": {
    "gn:admin1_code":"6.0",
    "gn:asciiname":"Geri",
    "gn:country_code":"CN",
    "gn:dem":3771,
    "gn:feature_class":"P",
    "gn:feature_code":"PPL",
    "gn:name":"Geri",
    "gn:population":0,
    "gn:timezone":"Asia/Urumqi",
    "iso:country":"CN",
    "name:ceb_x_preferred":[
        "Geri"
    ],
    "name:deu_x_preferred":[
        "Geri"
    ],
    "name:fra_x_preferred":[
        "Geri"
    ],
    "name:kat_x_preferred":[
        "\u10d2\u10d4\u10e0\u10d8"
    ],
    "name:pol_x_preferred":[
        "Geri"
    ],
    "name:por_x_preferred":[
        "Geri"
    ],
    "name:swe_x_preferred":[
        "Geri"
    ],
    "name:zho_x_preferred":[
        "\u5404\u65e5"
    ],
    "wof:name":"Geri",
    "wof:placetype":"locality"
},
  "geometry": {"coordinates":[97.35312999999999,32.8848],"type":"Point"}
}