{
  "type": "Feature",
  "properties": {
    "gn:admin1_code":"5.0",
    "gn:asciiname":"Lujiadian",
    "gn:country_code":"CN",
    "gn:dem":199,
    "gn:feature_class":"P",
    "gn:feature_code":"PPL",
    "gn:name":"L\u00fcjiadian",
    "gn:population":0,
    "gn:timezone":"Asia/Shanghai",
    "iso:country":"CN",
    "name:und_x_variant":[
        "L\u00fcjiadian"
    ],
    "name:zho_x_preferred":[
        "\u5415\u5bb6\u5e97"
    ],
    "wof:name":"Lujiadian",
    "wof:placetype":"locality"
},
  "geometry": {"coordinates":[125.30213000000001,44.01466],"type":"Point"}
}