{
  "type": "Feature",
  "properties": {
    "gn:admin1_code":"29",
    "gn:asciiname":"Shalatuo",
    "gn:country_code":"CN",
    "gn:dem":1619,
    "gn:feature_class":"P",
    "gn:feature_code":"PPL",
    "gn:name":"Shalatuo",
    "gn:population":0,
    "gn:timezone":"Asia/Shanghai",
    "iso:country":"CN",
    "wof:name":"Shalatuo",
    "wof:placetype":"locality"
},
  "geometry": {"coordinates":[102.57167,23.09361],"type":"Point"}
}