{
  "type": "Feature",
  "properties": {
    "gn:admin1_code":"33.0",
    "gn:asciiname":"Chaqi",
    "gn:country_code":"CN",
    "gn:dem":315,
    "gn:feature_class":"P",
    "gn:feature_code":"PPL",
    "gn:name":"Chaqi",
    "gn:population":0,
    "gn:timezone":"Asia/Shanghai",
    "iso:country":"CN",
    "name:zho_x_preferred":[
        "\u63d2\u65d7"
    ],
    "wof:name":"Chaqi",
    "wof:placetype":"locality"
},
  "geometry": {"coordinates":[108.10854,31.09428],"type":"Point"}
}