{
  "type": "Feature",
  "properties": {
    "gn:admin1_code":"10.0",
    "gn:asciiname":"Xihushe",
    "gn:country_code":"CN",
    "gn:dem":201,
    "gn:feature_class":"P",
    "gn:feature_code":"PPL",
    "gn:name":"Xihushe",
    "gn:population":0,
    "gn:timezone":"Asia/Shanghai",
    "iso:country":"CN",
    "name:und_x_variant":[
        "\u897f\u6e56\u793e"
    ],
    "wof:name":"Xihushe",
    "wof:placetype":"locality"
},
  "geometry": {"coordinates":[114.19579,38.47129],"type":"Point"}
}