{
  "type": "Feature",
  "properties": {
    "gn:admin1_code":"29",
    "gn:asciiname":"Daiwei Zhongzhai",
    "gn:country_code":"CN",
    "gn:dem":1858,
    "gn:feature_class":"P",
    "gn:feature_code":"PPL",
    "gn:name":"Daiwei Zhongzhai",
    "gn:population":0,
    "gn:timezone":"Asia/Shanghai",
    "iso:country":"CN",
    "name:zho_x_preferred":[
        "\u4ee3\u5473\u4e2d\u5be8"
    ],
    "wof:name":"Daiwei Zhongzhai",
    "wof:placetype":"locality"
},
  "geometry": {"coordinates":[101.84999999999999,24.1789],"type":"Point"}
}