{
  "type": "Feature",
  "properties": {
    "gn:admin1_code":"3.0",
    "gn:asciiname":"Zaomu",
    "gn:country_code":"CN",
    "gn:dem":140,
    "gn:feature_class":"P",
    "gn:feature_code":"PPL",
    "gn:name":"Zaomu",
    "gn:population":0,
    "gn:timezone":"Asia/Shanghai",
    "iso:country":"CN",
    "name:und_x_variant":[
        "\u67a3\u6728"
    ],
    "wof:name":"Zaomu",
    "wof:placetype":"locality"
},
  "geometry": {"coordinates":[114.10208,28.03693],"type":"Point"}
}