{
  "type": "Feature",
  "properties": {
    "gn:admin1_code":"11.0",
    "gn:asciiname":"Youjia'ao",
    "gn:country_code":"CN",
    "gn:dem":217,
    "gn:feature_class":"P",
    "gn:feature_code":"PPL",
    "gn:name":"Youjia\u2019ao",
    "gn:population":0,
    "gn:timezone":"Asia/Shanghai",
    "iso:country":"CN",
    "name:und_x_variant":[
        "Youjia\u2019ao"
    ],
    "name:zho_x_preferred":[
        "\u6e38\u5bb6\u5773"
    ],
    "wof:name":"Youjia'ao",
    "wof:placetype":"locality"
},
  "geometry": {"coordinates":[110.14575000000001,27.73681],"type":"Point"}
}