{
  "type": "Feature",
  "properties": {
    "gn:admin1_code":"32.0",
    "gn:asciiname":"Longdingshan",
    "gn:country_code":"CN",
    "gn:dem":353,
    "gn:feature_class":"P",
    "gn:feature_code":"PPL",
    "gn:name":"Longdingshan",
    "gn:population":0,
    "gn:timezone":"Asia/Shanghai",
    "iso:country":"CN",
    "name:zho_x_preferred":[
        "\u9f99\u9876\u5c71"
    ],
    "wof:name":"Longdingshan",
    "wof:placetype":"locality"
},
  "geometry": {"coordinates":[105.74078,28.93856],"type":"Point"}
}