{
  "type": "Feature",
  "properties": {
    "gn:admin1_code":"3.0",
    "gn:asciiname":"Zhonghe",
    "gn:country_code":"CN",
    "gn:dem":129,
    "gn:feature_class":"P",
    "gn:feature_code":"PPL",
    "gn:name":"Zhonghe",
    "gn:population":0,
    "gn:timezone":"Asia/Shanghai",
    "iso:country":"CN",
    "name:ceb_x_preferred":[
        "Zhonghe"
    ],
    "name:deu_x_preferred":[
        "Zhonghe"
    ],
    "name:swe_x_preferred":[
        "Zhonghe"
    ],
    "name:und_x_variant":[
        "\u4e2d\u548c",
        "Zhonghexiang",
        "\u4e2d\u548c\u4e61"
    ],
    "wof:name":"Zhonghe",
    "wof:placetype":"locality"
},
  "geometry": {"coordinates":[116.48399000000001,27.03096],"type":"Point"}
}