{
  "type": "Feature",
  "properties": {
    "gn:admin1_code":"11",
    "gn:asciiname":"Huacaomen",
    "gn:country_code":"CN",
    "gn:dem":382,
    "gn:feature_class":"P",
    "gn:feature_code":"PPL",
    "gn:name":"Huacaomen",
    "gn:population":0,
    "gn:timezone":"Asia/Shanghai",
    "iso:country":"CN",
    "name:zho_x_preferred":[
        "\u82b1\u69fd\u95e8"
    ],
    "wof:name":"Huacaomen",
    "wof:placetype":"locality"
},
  "geometry": {"coordinates":[111.91703,26.30707],"type":"Point"}
}