{
  "type": "Feature",
  "properties": {
    "gn:admin1_code":"9.0",
    "gn:asciiname":"Guotulou",
    "gn:country_code":"CN",
    "gn:dem":39,
    "gn:feature_class":"P",
    "gn:feature_code":"PPL",
    "gn:name":"Guotulou",
    "gn:population":0,
    "gn:timezone":"Asia/Shanghai",
    "iso:country":"CN",
    "name:zho_x_preferred":[
        "\u90ed\u571f\u697c"
    ],
    "wof:name":"Guotulou",
    "wof:placetype":"locality"
},
  "geometry": {"coordinates":[115.41670999999999,33.65261],"type":"Point"}
}