{
  "type": "Feature",
  "properties": {
    "gn:admin1_code":"32.0",
    "gn:asciiname":"Caiya",
    "gn:country_code":"CN",
    "gn:dem":337,
    "gn:feature_class":"P",
    "gn:feature_code":"PPL",
    "gn:name":"Caiya",
    "gn:population":0,
    "gn:timezone":"Asia/Shanghai",
    "iso:country":"CN",
    "name:zho_x_preferred":[
        "\u83dc\u57ad"
    ],
    "wof:name":"Caiya",
    "wof:placetype":"locality"
},
  "geometry": {"coordinates":[107.065,30.4819],"type":"Point"}
}