{
  "type": "Feature",
  "properties": {
    "gn:admin1_code":"29.0",
    "gn:asciiname":"Gaojiaqing",
    "gn:country_code":"CN",
    "gn:dem":2299,
    "gn:feature_class":"P",
    "gn:feature_code":"PPL",
    "gn:name":"Gaojiaqing",
    "gn:population":0,
    "gn:timezone":"Asia/Shanghai",
    "iso:country":"CN",
    "name:zho_x_preferred":[
        "\u9ad8\u5bb6\u7b90"
    ],
    "wof:name":"Gaojiaqing",
    "wof:placetype":"locality"
},
  "geometry": {"coordinates":[103.25700000000001,26.3375],"type":"Point"}
}