{
  "type": "Feature",
  "properties": {
    "gn:admin1_code":"7.0",
    "gn:asciiname":"Dongkengku",
    "gn:country_code":"CN",
    "gn:dem":596,
    "gn:feature_class":"P",
    "gn:feature_code":"PPL",
    "gn:name":"Dongkengku",
    "gn:population":0,
    "gn:timezone":"Asia/Shanghai",
    "iso:country":"CN",
    "name:und_x_variant":[
        "\u4e1c\u5751\u5800"
    ],
    "name:zho_x_preferred":[
        "\u4e1c\u5751\u5800"
    ],
    "wof:name":"Dongkengku",
    "wof:placetype":"locality"
},
  "geometry": {"coordinates":[118.11866000000001,26.73832],"type":"Point"}
}