{
  "type": "Feature",
  "properties": {
    "gn:admin1_code":"11",
    "gn:asciiname":"Gangzitou",
    "gn:country_code":"CN",
    "gn:dem":279,
    "gn:feature_class":"P",
    "gn:feature_code":"PPL",
    "gn:name":"Gangzitou",
    "gn:population":0,
    "gn:timezone":"Asia/Shanghai",
    "iso:country":"CN",
    "name:und_x_variant":[
        "\u5c97\u5b50\u5934",
        "Gangzitou"
    ],
    "wof:name":"Gangzitou",
    "wof:placetype":"locality"
},
  "geometry": {"coordinates":[111.96917000000001,25.80083],"type":"Point"}
}