{
  "type": "Feature",
  "properties": {
    "gn:admin1_code":"5.0",
    "gn:asciiname":"Langtoushancun",
    "gn:country_code":"CN",
    "gn:dem":191,
    "gn:feature_class":"P",
    "gn:feature_code":"PPL",
    "gn:name":"Langtoushancun",
    "gn:population":0,
    "gn:timezone":"Asia/Shanghai",
    "iso:country":"CN",
    "name:zho_x_preferred":[
        "\u72fc\u5934\u5c71\u6751"
    ],
    "wof:name":"Langtoushancun",
    "wof:placetype":"locality"
},
  "geometry": {"coordinates":[125.85399,43.84369],"type":"Point"}
}