{
  "type": "Feature",
  "properties": {
    "gn:admin1_code":"29",
    "gn:asciiname":"Xiazhenwu",
    "gn:country_code":"CN",
    "gn:dem":1130,
    "gn:feature_class":"P",
    "gn:feature_code":"PPL",
    "gn:name":"Xiazhenwu",
    "gn:population":0,
    "gn:timezone":"Asia/Shanghai",
    "iso:country":"CN",
    "name:zho_x_preferred":[
        "\u4e0b\u771f\u6b66"
    ],
    "wof:name":"Xiazhenwu",
    "wof:placetype":"locality"
},
  "geometry": {"coordinates":[104.84399999999999,23.5359],"type":"Point"}
}