{
  "type": "Feature",
  "properties": {
    "gn:admin1_code":"13.0",
    "gn:asciiname":"Tuofu",
    "gn:country_code":"CN",
    "gn:dem":3958,
    "gn:feature_class":"P",
    "gn:feature_code":"PPL",
    "gn:name":"Tuofu",
    "gn:population":0,
    "gn:timezone":"Asia/Shanghai",
    "iso:country":"CN",
    "name:und_x_variant":[
        "\u6258\u752b"
    ],
    "wof:name":"Tuofu",
    "wof:placetype":"locality"
},
  "geometry": {"coordinates":[75.21938,38.87599],"type":"Point"}
}