{
  "type": "Feature",
  "properties": {
    "gn:admin1_code":"12.0",
    "gn:asciiname":"Luo'eryan",
    "gn:country_code":"CN",
    "gn:dem":1073,
    "gn:feature_class":"P",
    "gn:feature_code":"PPL",
    "gn:name":"Luo\u2019eryan",
    "gn:population":0,
    "gn:timezone":"Asia/Shanghai",
    "iso:country":"CN",
    "name:zho_x_preferred":[
        "\u843d\u8033\u5ca9"
    ],
    "name:zho_x_variant":[
        "Luo\u2019eryan"
    ],
    "wof:name":"Luo'eryan",
    "wof:placetype":"locality"
},
  "geometry": {"coordinates":[109.00695,29.50333],"type":"Point"}
}