{
  "type": "Feature",
  "properties": {
    "gn:admin1_code":"30.0",
    "gn:asciiname":"Changzhenkeng",
    "gn:country_code":"CN",
    "gn:dem":53,
    "gn:feature_class":"P",
    "gn:feature_code":"PPL",
    "gn:name":"Changzhenkeng",
    "gn:population":0,
    "gn:timezone":"Asia/Shanghai",
    "iso:country":"CN",
    "name:zho_x_preferred":[
        "\u957f\u5733\u5751"
    ],
    "wof:name":"Changzhenkeng",
    "wof:placetype":"locality"
},
  "geometry": {"coordinates":[112.63248,23.32882],"type":"Point"}
}