{
  "type": "Feature",
  "properties": {
    "gn:admin1_code":"4.0",
    "gn:asciiname":"Buhucun",
    "gn:country_code":"CN",
    "gn:dem":25,
    "gn:feature_class":"P",
    "gn:feature_code":"PPL",
    "gn:name":"Buhucun",
    "gn:population":0,
    "gn:timezone":"Asia/Shanghai",
    "iso:country":"CN",
    "name:zho_x_preferred":[
        "\u57e0\u6e56\u6751"
    ],
    "wof:name":"Buhucun",
    "wof:placetype":"locality"
},
  "geometry": {"coordinates":[118.23828,34.15411],"type":"Point"}
}