{
  "type": "Feature",
  "properties": {
    "gn:admin1_code":"10",
    "gn:asciiname":"Hexidian",
    "gn:country_code":"CN",
    "gn:dem":27,
    "gn:feature_class":"P",
    "gn:feature_code":"PPL",
    "gn:name":"Hexidian",
    "gn:population":0,
    "gn:timezone":"Asia/Shanghai",
    "iso:country":"CN",
    "name:zho_x_preferred":[
        "\u6cb3\u897f\u5e97"
    ],
    "wof:name":"Hexidian",
    "wof:placetype":"locality"
},
  "geometry": {"coordinates":[115.70999999999999,37.5672],"type":"Point"}
}