{
  "type": "Feature",
  "properties": {
    "gn:admin1_code":"26.0",
    "gn:asciiname":"Haoxinzhuang",
    "gn:country_code":"CN",
    "gn:dem":1682,
    "gn:feature_class":"P",
    "gn:feature_code":"PPL",
    "gn:name":"Haoxinzhuang",
    "gn:population":0,
    "gn:timezone":"Asia/Shanghai",
    "iso:country":"CN",
    "name:zho_x_preferred":[
        "\u90dd\u65b0\u5e84"
    ],
    "wof:name":"Haoxinzhuang",
    "wof:placetype":"locality"
},
  "geometry": {"coordinates":[107.58873,37.10961],"type":"Point"}
}