{
  "type": "Feature",
  "properties": {
    "gn:admin1_code":"16",
    "gn:asciiname":"Tiandong",
    "gn:country_code":"CN",
    "gn:dem":195,
    "gn:feature_class":"P",
    "gn:feature_code":"PPL",
    "gn:name":"Tiandong",
    "gn:population":0,
    "gn:timezone":"Asia/Shanghai",
    "iso:country":"CN",
    "name:zho_x_preferred":[
        "\u7530\u6d1e"
    ],
    "wof:name":"Tiandong",
    "wof:placetype":"locality"
},
  "geometry": {"coordinates":[109.78100000000001,25.854],"type":"Point"}
}