{
  "type": "Feature",
  "properties": {
    "gn:admin1_code":"5.0",
    "gn:asciiname":"Yangwenjin",
    "gn:country_code":"CN",
    "gn:dem":202,
    "gn:feature_class":"P",
    "gn:feature_code":"PPL",
    "gn:name":"Yangwenjin",
    "gn:population":0,
    "gn:timezone":"Asia/Shanghai",
    "iso:country":"CN",
    "name:zho_x_preferred":[
        "\u6768\u6587\u9526"
    ],
    "wof:name":"Yangwenjin",
    "wof:placetype":"locality"
},
  "geometry": {"coordinates":[126.93292,44.98644],"type":"Point"}
}