{
  "type": "Feature",
  "properties": {
    "gn:admin1_code":"12.0",
    "gn:asciiname":"Baiheziwan",
    "gn:country_code":"CN",
    "gn:dem":86,
    "gn:feature_class":"P",
    "gn:feature_code":"PPL",
    "gn:name":"Baiheziwan",
    "gn:population":0,
    "gn:timezone":"Asia/Shanghai",
    "iso:country":"CN",
    "name:zho_x_preferred":[
        "Baiheziwan"
    ],
    "name:zho_x_variant":[
        "\u767d\u9e64\u5b50\u6e7e"
    ],
    "wof:name":"Baiheziwan",
    "wof:placetype":"locality"
},
  "geometry": {"coordinates":[112.13198,30.81412000000001],"type":"Point"}
}