{
  "type": "Feature",
  "properties": {
    "gn:admin1_code":"26.0",
    "gn:asciiname":"Yangtaicun",
    "gn:country_code":"CN",
    "gn:dem":959,
    "gn:feature_class":"P",
    "gn:feature_code":"PPL",
    "gn:name":"Yangtaicun",
    "gn:population":0,
    "gn:timezone":"Asia/Shanghai",
    "iso:country":"CN",
    "name:zho_x_preferred":[
        "\u6768\u53f0\u6751"
    ],
    "wof:name":"Yangtaicun",
    "wof:placetype":"locality"
},
  "geometry": {"coordinates":[109.20313,35.64715],"type":"Point"}
}