{
  "type": "Feature",
  "properties": {
    "gn:admin1_code":"2",
    "gn:asciiname":"Lanju",
    "gn:cc2":"CN",
    "gn:country_code":"CN",
    "gn:dem":242,
    "gn:feature_class":"P",
    "gn:feature_code":"PPL",
    "gn:name":"Lanju",
    "gn:population":0,
    "gn:timezone":"Asia/Shanghai",
    "iso:country":"CN",
    "name:und_x_variant":[
        "Wumeiyang",
        "Lanju",
        "\u5170\u5de8",
        "Lanju Xiang"
    ],
    "name:zho_x_preferred":[
        "\u4e94\u6885\u579f"
    ],
    "name:zho_x_variant":[
        "\u5170\u5de8\u4e61"
    ],
    "wof:name":"Lanju",
    "wof:placetype":"locality"
},
  "geometry": {"coordinates":[119.09389,27.9875],"type":"Point"}
}