{
  "type": "Feature",
  "properties": {
    "gn:admin1_code":"25",
    "gn:asciiname":"Wuseya",
    "gn:country_code":"CN",
    "gn:dem":265,
    "gn:feature_class":"P",
    "gn:feature_code":"PPL",
    "gn:name":"Wuseya",
    "gn:population":0,
    "gn:timezone":"Asia/Shanghai",
    "iso:country":"CN",
    "name:zho_x_preferred":[
        "\u4e94\u8272\u5d16"
    ],
    "wof:name":"Wuseya",
    "wof:placetype":"locality"
},
  "geometry": {"coordinates":[117.706,36.3829],"type":"Point"}
}