{
  "type": "Feature",
  "properties": {
    "gn:admin1_code":"3.0",
    "gn:asciiname":"Zhouyuancun",
    "gn:country_code":"CN",
    "gn:dem":141,
    "gn:feature_class":"P",
    "gn:feature_code":"PPL",
    "gn:name":"Zhouyuancun",
    "gn:population":0,
    "gn:timezone":"Asia/Shanghai",
    "iso:country":"CN",
    "name:und_x_variant":[
        "\u5468\u6e90\u6751"
    ],
    "wof:name":"Zhouyuancun",
    "wof:placetype":"locality"
},
  "geometry": {"coordinates":[116.43248,26.98261],"type":"Point"}
}