{
  "type": "Feature",
  "properties": {
    "gn:admin1_code":"12.0",
    "gn:asciiname":"Caijia",
    "gn:country_code":"CN",
    "gn:dem":1007,
    "gn:feature_class":"P",
    "gn:feature_code":"PPL",
    "gn:name":"Caijia",
    "gn:population":0,
    "gn:timezone":"Asia/Shanghai",
    "iso:country":"CN",
    "name:zho_x_preferred":[
        "\u8521\u5bb6"
    ],
    "wof:name":"Caijia",
    "wof:placetype":"locality"
},
  "geometry": {"coordinates":[110.27342,31.128],"type":"Point"}
}