{
  "type": "Feature",
  "properties": {
    "gn:admin1_code":"29.0",
    "gn:asciiname":"Nuowucun",
    "gn:country_code":"CN",
    "gn:dem":1555,
    "gn:feature_class":"P",
    "gn:feature_code":"PPL",
    "gn:name":"Nuowucun",
    "gn:population":0,
    "gn:timezone":"Asia/Shanghai",
    "iso:country":"CN",
    "name:zho_x_preferred":[
        "\u7cef\u4e94\u6751"
    ],
    "wof:name":"Nuowucun",
    "wof:placetype":"locality"
},
  "geometry": {"coordinates":[100.36,23.9656],"type":"Point"}
}