{
  "type": "Feature",
  "properties": {
    "gn:admin1_code":"25",
    "gn:asciiname":"Baoji",
    "gn:country_code":"CN",
    "gn:dem":7,
    "gn:feature_class":"P",
    "gn:feature_code":"PPL",
    "gn:name":"Baoji",
    "gn:population":0,
    "gn:timezone":"Asia/Shanghai",
    "iso:country":"CN",
    "name:ara_x_preferred":[
        "\u0628\u0627\u0648\u062c\u0649"
    ],
    "name:bxr_x_preferred":[
        "\u0411\u0430\u043e\u0446\u0437\u0438"
    ],
    "name:cdo_x_preferred":[
        "B\u014d\u0324-gi\u0115"
    ],
    "name:ceb_x_preferred":[
        "Baoji Shi"
    ],
    "name:ces_x_preferred":[
        "Pao-\u0165i"
    ],
    "name:dan_x_preferred":[
        "Baoji"
    ],
    "name:deu_x_preferred":[
        "Baoji"
    ],
    "name:eus_x_preferred":[
        "Baoji"
    ],
    "name:fas_x_preferred":[
        "\u0628\u0627\u0648\u0698\u06cc"
    ],
    "name:fin_x_preferred":[
        "Baoji"
    ],
    "name:fra_x_preferred":[
        "Baoji"
    ],
    "name:hye_x_preferred":[
        "\u0532\u0578\u0561\u0581\u0566\u056b"
    ],
    "name:ita_x_preferred":[
        "Baoji"
    ],
    "name:jpn_x_preferred":[
        "\u5b9d\u9d8f\u5e02"
    ],
    "name:kaz_x_preferred":[
        "\u0411\u0430\u043e\u0446\u0437\u0438"
    ],
    "name:kik_x_preferred":[
        "Baoji"
    ],
    "name:kor_x_preferred":[
        "\ubc14\uc624\uc9c0\uc2dc"
    ],
    "name:lit_x_preferred":[
        "Baodzi"
    ],
    "name:mlg_x_preferred":[
        "Baoji"
    ],
    "name:nld_x_preferred":[
        "Baoji"
    ],
    "name:nno_x_preferred":[
        "Baoji"
    ],
    "name:nor_x_preferred":[
        "Baoji"
    ],
    "name:pol_x_preferred":[
        "Baoji"
    ],
    "name:rus_x_preferred":[
        "\u0411\u0430\u043e\u0446\u0437\u0438"
    ],
    "name:spa_x_preferred":[
        "Baoji"
    ],
    "name:srp_x_preferred":[
        "\u0411\u0430\u043e\u0452\u0438"
    ],
    "name:swe_x_preferred":[
        "Baoji"
    ],
    "name:tur_x_preferred":[
        "Baoji"
    ],
    "name:urd_x_preferred":[
        "\u0628\u0627\u0648\u062c\u06cc"
    ],
    "name:vie_x_preferred":[
        "B\u1ea3o K\u00ea"
    ],
    "name:war_x_preferred":[
        "Baoji"
    ],
    "name:zho_x_preferred":[
        "\u5b9d\u9e21\u5e02"
    ],
    "wof:name":"Baoji",
    "wof:placetype":"locality"
},
  "geometry": {"coordinates":[117.85917000000001,37.50389000000001],"type":"Point"}
}