{
  "type": "Feature",
  "properties": {
    "gn:admin1_code":"12.0",
    "gn:asciiname":"Hongguang Wudui",
    "gn:country_code":"CN",
    "gn:dem":54,
    "gn:feature_class":"P",
    "gn:feature_code":"PPLF",
    "gn:name":"Hongguang Wudui",
    "gn:population":0,
    "gn:timezone":"Asia/Shanghai",
    "iso:country":"CN",
    "name:zho_x_preferred":[
        "Hongguang Wudui"
    ],
    "name:zho_x_variant":[
        "\u7ea2\u5149\u4e94\u961f"
    ],
    "wof:name":"Hongguang Wudui",
    "wof:placetype":"locality"
},
  "geometry": {"coordinates":[114.42456,29.97771],"type":"Point"}
}