{
  "type": "Feature",
  "properties": {
    "gn:admin1_code":"04",
    "gn:asciiname":"Gengwan",
    "gn:country_code":"CN",
    "gn:dem":11,
    "gn:feature_class":"P",
    "gn:feature_code":"PPL",
    "gn:name":"Gengwan",
    "gn:population":0,
    "gn:timezone":"Asia/Shanghai",
    "iso:country":"CN",
    "name:und_x_variant":[
        "Keng-wan",
        "Gengwan"
    ],
    "name:zho_x_preferred":[
        "\u803f\u6e7e"
    ],
    "wof:name":"Gengwan",
    "wof:placetype":"locality"
},
  "geometry": {"coordinates":[120.07459,31.42391],"type":"Point"}
}