{
  "type": "Feature",
  "properties": {
    "gn:admin1_code":"5.0",
    "gn:asciiname":"Lianjiagou",
    "gn:country_code":"CN",
    "gn:dem":261,
    "gn:feature_class":"P",
    "gn:feature_code":"PPL",
    "gn:name":"Lianjiagou",
    "gn:population":0,
    "gn:timezone":"Asia/Shanghai",
    "iso:country":"CN",
    "name:zho_x_preferred":[
        "\u5ec9\u5bb6\u6c9f"
    ],
    "wof:name":"Lianjiagou",
    "wof:placetype":"locality"
},
  "geometry": {"coordinates":[125.93447,44.00621],"type":"Point"}
}