{
  "type": "Feature",
  "properties": {
    "gn:admin1_code":"1.0",
    "gn:asciiname":"Jianquancun",
    "gn:country_code":"CN",
    "gn:dem":8,
    "gn:feature_class":"P",
    "gn:feature_code":"PPL",
    "gn:name":"Jianquancun",
    "gn:population":0,
    "gn:timezone":"Asia/Shanghai",
    "iso:country":"CN",
    "name:zho_x_preferred":[
        "\u5065\u5168\u6751"
    ],
    "wof:name":"Jianquancun",
    "wof:placetype":"locality"
},
  "geometry": {"coordinates":[117.92310000000001,31.12469],"type":"Point"}
}