{
  "type": "Feature",
  "properties": {
    "gn:admin1_code":"10",
    "gn:asciiname":"Guoleizhuang",
    "gn:cc2":"CN",
    "gn:country_code":"CN",
    "gn:dem":775,
    "gn:feature_class":"P",
    "gn:feature_code":"PPL",
    "gn:name":"Guoleizhuang",
    "gn:population":0,
    "gn:timezone":"Asia/Shanghai",
    "iso:country":"CN",
    "name:und_x_variant":[
        "Kuo-lei-chuang",
        "Guoleizhuang"
    ],
    "wof:name":"Guoleizhuang",
    "wof:placetype":"locality"
},
  "geometry": {"coordinates":[114.54639,40.71667],"type":"Point"}
}