{
  "type": "Feature",
  "properties": {
    "gn:admin1_code":"19.0",
    "gn:asciiname":"Tangquanzigou",
    "gn:country_code":"CN",
    "gn:dem":393,
    "gn:feature_class":"P",
    "gn:feature_code":"PPL",
    "gn:name":"Tangquanzigou",
    "gn:population":0,
    "gn:timezone":"Asia/Shanghai",
    "iso:country":"CN",
    "name:zho_x_preferred":[
        "\u6c64\u6cc9\u5b50\u6c9f"
    ],
    "wof:name":"Tangquanzigou",
    "wof:placetype":"locality"
},
  "geometry": {"coordinates":[120.57923,42.00316],"type":"Point"}
}