{
  "type": "Feature",
  "properties": {
    "gn:admin1_code":"15.0",
    "gn:asciiname":"Xuechuan",
    "gn:country_code":"CN",
    "gn:dem":2046,
    "gn:feature_class":"P",
    "gn:feature_code":"PPL",
    "gn:name":"Xuechuan",
    "gn:population":0,
    "gn:timezone":"Asia/Shanghai",
    "iso:country":"CN",
    "name:zho_x_preferred":[
        "\u859b\u5ddd"
    ],
    "wof:name":"Xuechuan",
    "wof:placetype":"locality"
},
  "geometry": {"coordinates":[104.934,35.4632],"type":"Point"}
}