{
  "type": "Feature",
  "properties": {
    "gn:admin1_code":"29.0",
    "gn:asciiname":"Zengjiashan",
    "gn:country_code":"CN",
    "gn:dem":1983,
    "gn:feature_class":"P",
    "gn:feature_code":"PPL",
    "gn:name":"Zengjiashan",
    "gn:population":0,
    "gn:timezone":"Asia/Shanghai",
    "iso:country":"CN",
    "name:zho_x_preferred":[
        "\u66fe\u5bb6\u5c71"
    ],
    "wof:name":"Zengjiashan",
    "wof:placetype":"locality"
},
  "geometry": {"coordinates":[100.224,24.2117],"type":"Point"}
}