{
  "type": "Feature",
  "properties": {
    "gn:admin1_code":"25",
    "gn:asciiname":"Nanchangshan",
    "gn:country_code":"CN",
    "gn:dem":11,
    "gn:feature_class":"P",
    "gn:feature_code":"PPLA3",
    "gn:name":"Nanchangshan",
    "gn:population":0,
    "gn:timezone":"Asia/Shanghai",
    "iso:country":"CN",
    "name:und_x_variant":[
        "Sihou",
        "Ch\u2019ang-tao",
        "Ssu-hou-ts\u2019un",
        "Changdao",
        "Nanchangshan",
        "Changdao Xian"
    ],
    "name:zho_x_preferred":[
        "\u5357\u957f\u5c71"
    ],
    "name:zho_x_variant":[
        "\u957f\u5c9b\u53bf"
    ],
    "wof:name":"Nanchangshan",
    "wof:placetype":"locality"
},
  "geometry": {"coordinates":[120.73247000000001,37.91522],"type":"Point"}
}