{
  "type": "Feature",
  "properties": {
    "gn:admin1_code":"29.0",
    "gn:asciiname":"Ande",
    "gn:country_code":"CN",
    "gn:dem":1927,
    "gn:feature_class":"P",
    "gn:feature_code":"PPL",
    "gn:name":"Ande",
    "gn:population":0,
    "gn:timezone":"Asia/Shanghai",
    "iso:country":"CN",
    "name:zho_x_preferred":[
        "\u5b89\u5fb7"
    ],
    "wof:name":"Ande",
    "wof:placetype":"locality"
},
  "geometry": {"coordinates":[101.11799999999999,25.2546],"type":"Point"}
}