{
  "type": "Feature",
  "properties": {
    "gn:admin1_code":"9",
    "gn:asciiname":"Liuhe",
    "gn:country_code":"CN",
    "gn:dem":53,
    "gn:feature_class":"P",
    "gn:feature_code":"PPL",
    "gn:name":"Liuhe",
    "gn:population":0,
    "gn:timezone":"Asia/Shanghai",
    "iso:country":"CN",
    "name:ceb_x_preferred":[
        "Liuhe"
    ],
    "name:deu_x_preferred":[
        "Liuhe"
    ],
    "name:zho_x_preferred":[
        "\u67f3\u6cb3"
    ],
    "wof:name":"Liuhe",
    "wof:placetype":"locality"
},
  "geometry": {"coordinates":[115.03700000000001,34.2194],"type":"Point"}
}