{
  "type": "Feature",
  "properties": {
    "gn:admin1_code":"26.0",
    "gn:asciiname":"Shangzimeitan",
    "gn:country_code":"CN",
    "gn:dem":1237,
    "gn:feature_class":"P",
    "gn:feature_code":"PPL",
    "gn:name":"Shangzimeitan",
    "gn:population":0,
    "gn:timezone":"Asia/Shanghai",
    "iso:country":"CN",
    "name:zho_x_preferred":[
        "\u4e0a\u59ca\u59b9\u6f6d"
    ],
    "wof:name":"Shangzimeitan",
    "wof:placetype":"locality"
},
  "geometry": {"coordinates":[108.61342,33.53671],"type":"Point"}
}