{
  "type": "Feature",
  "properties": {
    "gn:admin1_code":"30.0",
    "gn:asciiname":"Shijiaoxia",
    "gn:country_code":"CN",
    "gn:dem":89,
    "gn:feature_class":"P",
    "gn:feature_code":"PPL",
    "gn:name":"Shijiaoxia",
    "gn:population":0,
    "gn:timezone":"Asia/Shanghai",
    "iso:country":"CN",
    "name:zho_x_preferred":[
        "\u77f3\u811a\u4e0b"
    ],
    "wof:name":"Shijiaoxia",
    "wof:placetype":"locality"
},
  "geometry": {"coordinates":[113.50194999999999,24.94788],"type":"Point"}
}