{
  "type": "Feature",
  "properties": {
    "gn:admin1_code":"16",
    "gn:asciiname":"Liuqi",
    "gn:country_code":"CN",
    "gn:dem":177,
    "gn:feature_class":"P",
    "gn:feature_code":"PPL",
    "gn:name":"Liuqi",
    "gn:population":0,
    "gn:timezone":"Asia/Shanghai",
    "iso:country":"CN",
    "name:zho_x_preferred":[
        "\u7559\u65d7"
    ],
    "wof:name":"Liuqi",
    "wof:placetype":"locality"
},
  "geometry": {"coordinates":[110.56999999999999,24.8397],"type":"Point"}
}