{
  "type": "Feature",
  "properties": {
    "gn:admin1_code":"15.0",
    "gn:asciiname":"Nandangou",
    "gn:country_code":"CN",
    "gn:dem":1559,
    "gn:feature_class":"P",
    "gn:feature_code":"PPL",
    "gn:name":"Nandangou",
    "gn:population":0,
    "gn:timezone":"Asia/Shanghai",
    "iso:country":"CN",
    "name:zho_x_preferred":[
        "\u5357\u4e39\u6c9f"
    ],
    "wof:name":"Nandangou",
    "wof:placetype":"locality"
},
  "geometry": {"coordinates":[105.405,34.2583],"type":"Point"}
}