{
  "type": "Feature",
  "properties": {
    "gn:admin1_code":"4.0",
    "gn:asciiname":"Zhafeng Wuzu",
    "gn:country_code":"CN",
    "gn:dem":4,
    "gn:feature_class":"P",
    "gn:feature_code":"PPLF",
    "gn:name":"Zhafeng Wuzu",
    "gn:population":0,
    "gn:timezone":"Asia/Shanghai",
    "iso:country":"CN",
    "name:zho_x_preferred":[
        "Zhafeng Wuzu"
    ],
    "name:zho_x_variant":[
        "\u95f8\u4e30\u4e94\u7ec4"
    ],
    "wof:name":"Zhafeng Wuzu",
    "wof:placetype":"locality"
},
  "geometry": {"coordinates":[121.26682,32.27914000000001],"type":"Point"}
}