{
  "type": "Feature",
  "properties": {
    "gn:admin1_code":"32.0",
    "gn:asciiname":"Oujia Pingzi",
    "gn:country_code":"CN",
    "gn:dem":2571,
    "gn:feature_class":"P",
    "gn:feature_code":"PPL",
    "gn:name":"Oujia Pingzi",
    "gn:population":0,
    "gn:timezone":"Asia/Shanghai",
    "iso:country":"CN",
    "name:zho_x_preferred":[
        "\u6b27\u5bb6\u576a\u5b50"
    ],
    "wof:name":"Oujia Pingzi",
    "wof:placetype":"locality"
},
  "geometry": {"coordinates":[101.765,27.2802],"type":"Point"}
}