{
  "type": "Feature",
  "properties": {
    "gn:admin1_code":"2.0",
    "gn:asciiname":"Shamaolu",
    "gn:country_code":"CN",
    "gn:dem":5,
    "gn:feature_class":"P",
    "gn:feature_code":"PPL",
    "gn:name":"Shamaol\u00fc",
    "gn:population":0,
    "gn:timezone":"Asia/Shanghai",
    "iso:country":"CN",
    "name:und_x_variant":[
        "Shamaol\u00fc"
    ],
    "name:zho_x_preferred":[
        "\u7eb1\u5e3d\u7eff"
    ],
    "wof:name":"Shamaolu",
    "wof:placetype":"locality"
},
  "geometry": {"coordinates":[121.78961,29.13996],"type":"Point"}
}