{
  "type": "Feature",
  "properties": {
    "gn:admin1_code":"16",
    "gn:asciiname":"Shuixiu",
    "gn:country_code":"CN",
    "gn:dem":128,
    "gn:feature_class":"P",
    "gn:feature_code":"PPL",
    "gn:name":"Shuixiu",
    "gn:population":0,
    "gn:timezone":"Asia/Shanghai",
    "iso:country":"CN",
    "name:zho_x_preferred":[
        "\u6c34\u79c0"
    ],
    "wof:name":"Shuixiu",
    "wof:placetype":"locality"
},
  "geometry": {"coordinates":[110.56399999999999,24.1434],"type":"Point"}
}