{
  "type": "Feature",
  "properties": {
    "gn:admin1_code":"15.0",
    "gn:asciiname":"Zuogaiduoma",
    "gn:country_code":"CN",
    "gn:dem":3422,
    "gn:feature_class":"P",
    "gn:feature_code":"PPLA4",
    "gn:name":"Zuogaiduoma",
    "gn:population":0,
    "gn:timezone":"Asia/Shanghai",
    "iso:country":"CN",
    "name:und_x_variant":[
        "\u4f50\u76d6\u591a\u739b",
        "Zuogaiduomaxiang",
        "\u4f50\u76d6\u591a\u739b\u4e61"
    ],
    "wof:name":"Zuogaiduoma",
    "wof:placetype":"locality"
},
  "geometry": {"coordinates":[103.12599,35.05587],"type":"Point"}
}