{
  "type": "Feature",
  "properties": {
    "gn:admin1_code":"23.0",
    "gn:asciiname":"Shuzhong",
    "gn:country_code":"CN",
    "gn:dem":4,
    "gn:feature_class":"P",
    "gn:feature_code":"PPL",
    "gn:name":"Shuzhong",
    "gn:population":0,
    "gn:timezone":"Asia/Shanghai",
    "iso:country":"CN",
    "name:zho_x_preferred":[
        "Shuzhong"
    ],
    "name:zho_x_variant":[
        "\u7ad6\u4e2d"
    ],
    "wof:name":"Shuzhong",
    "wof:placetype":"locality"
},
  "geometry": {"coordinates":[121.47163999999999,31.60391],"type":"Point"}
}