{
  "type": "Feature",
  "properties": {
    "gn:admin1_code":"19",
    "gn:asciiname":"Shahezhen",
    "gn:cc2":"CN",
    "gn:country_code":"CN",
    "gn:dem":9,
    "gn:feature_class":"P",
    "gn:feature_code":"PPL",
    "gn:name":"Shahezhen",
    "gn:population":0,
    "gn:timezone":"Asia/Shanghai",
    "iso:country":"CN",
    "name:und_x_variant":[
        "Sha-ho",
        "Sha-ho-chen",
        "Shahezhen"
    ],
    "wof:name":"Shahezhen",
    "wof:placetype":"locality"
},
  "geometry": {"coordinates":[124.43889,40.16861],"type":"Point"}
}