{
  "type": "Feature",
  "properties": {
    "gn:admin1_code":"5.0",
    "gn:asciiname":"Yaoduan",
    "gn:country_code":"CN",
    "gn:dem":556,
    "gn:feature_class":"P",
    "gn:feature_code":"PPL",
    "gn:name":"Yaoduan",
    "gn:population":0,
    "gn:timezone":"Asia/Shanghai",
    "iso:country":"CN",
    "name:und_x_variant":[
        "\u8170\u6bb5"
    ],
    "wof:name":"Yaoduan",
    "wof:placetype":"locality"
},
  "geometry": {"coordinates":[125.48775999999999,41.79395],"type":"Point"}
}