{
  "type": "Feature",
  "properties": {
    "gn:admin1_code":"16",
    "gn:asciiname":"Baishi",
    "gn:country_code":"CN",
    "gn:dem":471,
    "gn:feature_class":"P",
    "gn:feature_code":"PPL",
    "gn:name":"Baishi",
    "gn:population":0,
    "gn:timezone":"Asia/Shanghai",
    "iso:country":"CN",
    "wof:name":"Baishi",
    "wof:placetype":"locality"
},
  "geometry": {"coordinates":[106.44611,23.82222],"type":"Point"}
}