{
  "type": "Feature",
  "properties": {
    "gn:admin1_code":"22.0",
    "gn:asciiname":"Baojiazhuangcun",
    "gn:country_code":"CN",
    "gn:dem":30,
    "gn:feature_class":"P",
    "gn:feature_code":"PPL",
    "gn:name":"Baojiazhuangcun",
    "gn:population":0,
    "gn:timezone":"Asia/Shanghai",
    "iso:country":"CN",
    "name:zho_x_preferred":[
        "\u9c8d\u5bb6\u5e84\u6751"
    ],
    "wof:name":"Baojiazhuangcun",
    "wof:placetype":"locality"
},
  "geometry": {"coordinates":[117.07317999999999,40.07177],"type":"Point"}
}