{
  "type": "Feature",
  "properties": {
    "gn:admin1_code":"19.0",
    "gn:asciiname":"Dongjia",
    "gn:country_code":"CN",
    "gn:dem":6,
    "gn:feature_class":"P",
    "gn:feature_code":"PPL",
    "gn:name":"Dongjia",
    "gn:population":0,
    "gn:timezone":"Asia/Shanghai",
    "iso:country":"CN",
    "name:und_x_variant":[
        "\u8463\u5bb6"
    ],
    "wof:name":"Dongjia",
    "wof:placetype":"locality"
},
  "geometry": {"coordinates":[122.46408,40.77856],"type":"Point"}
}