{
  "type": "Feature",
  "properties": {
    "gn:admin1_code":"33.0",
    "gn:asciiname":"Baiyun",
    "gn:country_code":"CN",
    "gn:dem":438,
    "gn:feature_class":"P",
    "gn:feature_code":"PPL",
    "gn:name":"Baiyun",
    "gn:population":0,
    "gn:timezone":"Asia/Shanghai",
    "iso:country":"CN",
    "name:zho_x_preferred":[
        "\u767d\u4e91"
    ],
    "wof:name":"Baiyun",
    "wof:placetype":"locality"
},
  "geometry": {"coordinates":[106.22718999999999,29.0571],"type":"Point"}
}