{
  "type": "Feature",
  "properties": {
    "gn:admin1_code":"30.0",
    "gn:asciiname":"Yaoxincun",
    "gn:country_code":"CN",
    "gn:dem":362,
    "gn:feature_class":"P",
    "gn:feature_code":"PPL",
    "gn:name":"Yaoxincun",
    "gn:population":0,
    "gn:timezone":"Asia/Shanghai",
    "iso:country":"CN",
    "name:zho_x_preferred":[
        "\u7476\u897f\u6751"
    ],
    "wof:name":"Yaoxincun",
    "wof:placetype":"locality"
},
  "geometry": {"coordinates":[115.88536000000001,24.33294],"type":"Point"}
}