{
  "type": "Feature",
  "properties": {
    "gn:admin1_code":"32.0",
    "gn:asciiname":"Maipu",
    "gn:country_code":"CN",
    "gn:dem":2773,
    "gn:feature_class":"P",
    "gn:feature_code":"PPL",
    "gn:name":"Maipu",
    "gn:population":0,
    "gn:timezone":"Asia/Shanghai",
    "iso:country":"CN",
    "name:zho_x_preferred":[
        "\u9ea6\u94fa"
    ],
    "wof:name":"Maipu",
    "wof:placetype":"locality"
},
  "geometry": {"coordinates":[101.548,28.9303],"type":"Point"}
}