{
  "type": "Feature",
  "properties": {
    "gn:admin1_code":"15.0",
    "gn:asciiname":"Guanlushang",
    "gn:country_code":"CN",
    "gn:dem":1082,
    "gn:feature_class":"P",
    "gn:feature_code":"PPL",
    "gn:name":"Guanlushang",
    "gn:population":0,
    "gn:timezone":"Asia/Shanghai",
    "iso:country":"CN",
    "name:und_x_variant":[
        "\u5173\u8def\u4e0a"
    ],
    "wof:name":"Guanlushang",
    "wof:placetype":"locality"
},
  "geometry": {"coordinates":[107.3169,34.97701],"type":"Point"}
}