{
  "type": "Feature",
  "properties": {
    "gn:admin1_code":"4.0",
    "gn:asciiname":"Yaomucun",
    "gn:country_code":"CN",
    "gn:dem":4,
    "gn:feature_class":"P",
    "gn:feature_code":"PPL",
    "gn:name":"Yaomucun",
    "gn:population":0,
    "gn:timezone":"Asia/Shanghai",
    "iso:country":"CN",
    "name:und_x_variant":[
        "\u59da\u5893\u6751"
    ],
    "name:zho_x_preferred":[
        "\u59da\u5893\u6751"
    ],
    "wof:name":"Yaomucun",
    "wof:placetype":"locality"
},
  "geometry": {"coordinates":[120.75239999999999,31.3071],"type":"Point"}
}