{
  "type": "Feature",
  "properties": {
    "gn:admin1_code":"32.0",
    "gn:asciiname":"Lingjiaoyan",
    "gn:country_code":"CN",
    "gn:dem":514,
    "gn:feature_class":"P",
    "gn:feature_code":"PPL",
    "gn:name":"Lingjiaoyan",
    "gn:population":0,
    "gn:timezone":"Asia/Shanghai",
    "iso:country":"CN",
    "name:zho_x_preferred":[
        "\u83f1\u89d2\u5830"
    ],
    "wof:name":"Lingjiaoyan",
    "wof:placetype":"locality"
},
  "geometry": {"coordinates":[104.145,30.5873],"type":"Point"}
}