{
  "type": "Feature",
  "properties": {
    "gn:admin1_code":"18.0",
    "gn:asciiname":"Yangjialing",
    "gn:country_code":"CN",
    "gn:dem":675,
    "gn:feature_class":"P",
    "gn:feature_code":"PPL",
    "gn:name":"Yangjialing",
    "gn:population":0,
    "gn:timezone":"Asia/Shanghai",
    "iso:country":"CN",
    "name:zho_x_preferred":[
        "\u6768\u5bb6\u5cad"
    ],
    "wof:name":"Yangjialing",
    "wof:placetype":"locality"
},
  "geometry": {"coordinates":[108.569,27.7837],"type":"Point"}
}