{
  "type": "Feature",
  "properties": {
    "gn:admin1_code":"26.0",
    "gn:asciiname":"Anziling",
    "gn:country_code":"CN",
    "gn:dem":573,
    "gn:feature_class":"P",
    "gn:feature_code":"PPL",
    "gn:name":"Anziling",
    "gn:population":0,
    "gn:timezone":"Asia/Shanghai",
    "iso:country":"CN",
    "name:und_x_variant":[
        "\u5eb5\u5b50\u5cad"
    ],
    "wof:name":"Anziling",
    "wof:placetype":"locality"
},
  "geometry": {"coordinates":[106.80816000000002,33.03484],"type":"Point"}
}