{
  "type": "Feature",
  "properties": {
    "gn:admin1_code":"02",
    "gn:asciiname":"Wan-ti-ts'un",
    "gn:country_code":"CN",
    "gn:dem":11,
    "gn:feature_class":"P",
    "gn:feature_code":"PPL",
    "gn:name":"Wan-ti-ts\u2019un",
    "gn:population":0,
    "gn:timezone":"Asia/Shanghai",
    "iso:country":"CN",
    "wof:name":"Wan-ti-ts'un",
    "wof:placetype":"locality"
},
  "geometry": {"coordinates":[120.77110999999999,28.16861],"type":"Point"}
}