{
  "type": "Feature",
  "properties": {
    "gn:admin1_code":"8.0",
    "gn:asciiname":"Longchengcun",
    "gn:country_code":"CN",
    "gn:dem":308,
    "gn:feature_class":"P",
    "gn:feature_code":"PPL",
    "gn:name":"Longchengcun",
    "gn:population":0,
    "gn:timezone":"Asia/Shanghai",
    "iso:country":"CN",
    "name:zho_x_preferred":[
        "\u9f99\u57ce\u6751"
    ],
    "wof:name":"Longchengcun",
    "wof:placetype":"locality"
},
  "geometry": {"coordinates":[122.46529,47.35463],"type":"Point"}
}