{
  "type": "Feature",
  "properties": {
    "gn:admin1_code":"14.0",
    "gn:asciiname":"Xixiadatacun",
    "gn:country_code":"CN",
    "gn:dem":4717,
    "gn:feature_class":"P",
    "gn:feature_code":"PPL",
    "gn:name":"Xixiadatacun",
    "gn:population":0,
    "gn:timezone":"Asia/Urumqi",
    "iso:country":"CN",
    "name:zho_x_preferred":[
        "\u897f\u590f\u8fbe\u5854\u6751"
    ],
    "wof:name":"Xixiadatacun",
    "wof:placetype":"locality"
},
  "geometry": {"coordinates":[91.30561,32.11257],"type":"Point"}
}