{
  "type": "Feature",
  "properties": {
    "gn:admin1_code":"19.0",
    "gn:asciiname":"Qiandian",
    "gn:country_code":"CN",
    "gn:dem":138,
    "gn:feature_class":"P",
    "gn:feature_code":"PPL",
    "gn:name":"Qiandian",
    "gn:population":0,
    "gn:timezone":"Asia/Shanghai",
    "iso:country":"CN",
    "name:und_x_variant":[
        "\u524d\u5e97"
    ],
    "name:zho_x_preferred":[
        "\u524d\u5e97"
    ],
    "wof:name":"Qiandian",
    "wof:placetype":"locality"
},
  "geometry": {"coordinates":[123.81717,41.35987],"type":"Point"}
}