{
  "type": "Feature",
  "properties": {
    "gn:admin1_code":"11",
    "gn:asciiname":"Liujiadong",
    "gn:country_code":"CN",
    "gn:dem":240,
    "gn:feature_class":"P",
    "gn:feature_code":"PPL",
    "gn:name":"Liujiadong",
    "gn:population":0,
    "gn:timezone":"Asia/Shanghai",
    "iso:country":"CN",
    "name:zho_x_preferred":[
        "\u5218\u5bb6\u6d1e"
    ],
    "wof:name":"Liujiadong",
    "wof:placetype":"locality"
},
  "geometry": {"coordinates":[113.75371,29.05029],"type":"Point"}
}