{
  "type": "Feature",
  "properties": {
    "gn:admin1_code":"18",
    "gn:asciiname":"Wanfoshan",
    "gn:country_code":"CN",
    "gn:dem":1082,
    "gn:feature_class":"P",
    "gn:feature_code":"PPL",
    "gn:name":"Wanfoshan",
    "gn:population":0,
    "gn:timezone":"Asia/Shanghai",
    "iso:country":"CN",
    "name:zho_x_preferred":[
        "\u4e07\u4f5b\u5c71"
    ],
    "wof:name":"Wanfoshan",
    "wof:placetype":"locality"
},
  "geometry": {"coordinates":[107.99299999999999,27.3181],"type":"Point"}
}