{
  "type": "Feature",
  "properties": {
    "gn:admin1_code":"30.0",
    "gn:asciiname":"Jingbei",
    "gn:country_code":"CN",
    "gn:dem":195,
    "gn:feature_class":"P",
    "gn:feature_code":"PPL",
    "gn:name":"Jingbei",
    "gn:population":0,
    "gn:timezone":"Asia/Shanghai",
    "iso:country":"CN",
    "name:zho_x_preferred":[
        "Jingbei"
    ],
    "name:zho_x_variant":[
        "\u5f84\u8d1d"
    ],
    "wof:name":"Jingbei",
    "wof:placetype":"locality"
},
  "geometry": {"coordinates":[115.46861,24.52722],"type":"Point"}
}