{
  "type": "Feature",
  "properties": {
    "gn:admin1_code":"33.0",
    "gn:asciiname":"Cuandong",
    "gn:country_code":"CN",
    "gn:dem":501,
    "gn:feature_class":"P",
    "gn:feature_code":"PPL",
    "gn:name":"Cuandong",
    "gn:population":0,
    "gn:timezone":"Asia/Shanghai",
    "iso:country":"CN",
    "name:zho_x_preferred":[
        "\u6c46\u6d1e"
    ],
    "wof:name":"Cuandong",
    "wof:placetype":"locality"
},
  "geometry": {"coordinates":[108.24706999999999,29.5202],"type":"Point"}
}