{
  "type": "Feature",
  "properties": {
    "gn:admin1_code":"32.0",
    "gn:asciiname":"Guna",
    "gn:country_code":"CN",
    "gn:dem":3082,
    "gn:feature_class":"P",
    "gn:feature_code":"PPL",
    "gn:name":"Guna",
    "gn:population":0,
    "gn:timezone":"Asia/Shanghai",
    "iso:country":"CN",
    "name:zho_x_preferred":[
        "\u59d1\u7eb3"
    ],
    "wof:name":"Guna",
    "wof:placetype":"locality"
},
  "geometry": {"coordinates":[103.622,32.391],"type":"Point"}
}