{
  "type": "Feature",
  "properties": {
    "gn:admin1_code":"14.0",
    "gn:asciiname":"Guoqingcun",
    "gn:country_code":"CN",
    "gn:dem":4374,
    "gn:feature_class":"P",
    "gn:feature_code":"PPL",
    "gn:name":"Guoqingcun",
    "gn:population":0,
    "gn:timezone":"Asia/Urumqi",
    "iso:country":"CN",
    "name:zho_x_preferred":[
        "\u90ed\u5e86\u6751"
    ],
    "wof:name":"Guoqingcun",
    "wof:placetype":"locality"
},
  "geometry": {"coordinates":[91.31695999999999,30.59845],"type":"Point"}
}