{
  "type": "Feature",
  "properties": {
    "gn:admin1_code":"32.0",
    "gn:asciiname":"Ganxigou",
    "gn:country_code":"CN",
    "gn:dem":696,
    "gn:feature_class":"P",
    "gn:feature_code":"PPL",
    "gn:name":"Ganxigou",
    "gn:population":0,
    "gn:timezone":"Asia/Shanghai",
    "iso:country":"CN",
    "name:zho_x_preferred":[
        "\u7518\u6eaa\u6c9f"
    ],
    "wof:name":"Ganxigou",
    "wof:placetype":"locality"
},
  "geometry": {"coordinates":[102.965,29.993],"type":"Point"}
}