{
  "type": "Feature",
  "properties": {
    "gn:admin1_code":"22.0",
    "gn:asciiname":"Shangzhizhaicun",
    "gn:country_code":"CN",
    "gn:dem":37,
    "gn:feature_class":"P",
    "gn:feature_code":"PPL",
    "gn:name":"Shangzhizhaicun",
    "gn:population":0,
    "gn:timezone":"Asia/Shanghai",
    "iso:country":"CN",
    "name:zho_x_preferred":[
        "\u4e0a\u7eb8\u5be8\u6751"
    ],
    "wof:name":"Shangzhizhaicun",
    "wof:placetype":"locality"
},
  "geometry": {"coordinates":[117.13132,40.15252],"type":"Point"}
}