{
  "type": "Feature",
  "properties": {
    "gn:admin1_code":"26.0",
    "gn:asciiname":"Haojia Guacun",
    "gn:country_code":"CN",
    "gn:dem":1001,
    "gn:feature_class":"P",
    "gn:feature_code":"PPL",
    "gn:name":"Haojia Guacun",
    "gn:population":0,
    "gn:timezone":"Asia/Shanghai",
    "iso:country":"CN",
    "name:zho_x_preferred":[
        "\u90dd\u5bb6\u576c\u6751"
    ],
    "wof:name":"Haojia Guacun",
    "wof:placetype":"locality"
},
  "geometry": {"coordinates":[110.348,38.3053],"type":"Point"}
}