{
  "type": "Feature",
  "properties": {
    "gn:admin1_code":"14.0",
    "gn:asciiname":"Guoba",
    "gn:country_code":"CN",
    "gn:dem":4386,
    "gn:feature_class":"P",
    "gn:feature_code":"PPL",
    "gn:name":"Guoba",
    "gn:population":0,
    "gn:timezone":"Asia/Shanghai",
    "iso:country":"CN",
    "name:bod_x_preferred":[
        "K\u00fcba"
    ],
    "name:fas_x_preferred":[
        "\u06a9\u0648\u0628\u0627"
    ],
    "name:msa_x_preferred":[
        "K\u00fcba"
    ],
    "name:und_x_variant":[
        "Kuo-pa",
        "Guoba",
        "K\u00fcba",
        "Guobacun"
    ],
    "name:zho_x_preferred":[
        "\u8fc7\u5df4"
    ],
    "name:zho_x_variant":[
        "Cilong",
        "\u6b21\u9f99",
        "\u8fc7\u5df4\u6751"
    ],
    "wof:name":"Guoba",
    "wof:placetype":"locality"
},
  "geometry": {"coordinates":[80.05703000000003,33.1157],"type":"Point"}
}