{
  "type": "Feature",
  "properties": {
    "gn:admin1_code":"3.0",
    "gn:asciiname":"Neikeng",
    "gn:country_code":"CN",
    "gn:dem":128,
    "gn:feature_class":"P",
    "gn:feature_code":"PPL",
    "gn:name":"Neikeng",
    "gn:population":0,
    "gn:timezone":"Asia/Shanghai",
    "iso:country":"CN",
    "name:und_x_variant":[
        "\u5185\u5751"
    ],
    "wof:name":"Neikeng",
    "wof:placetype":"locality"
},
  "geometry": {"coordinates":[115.13428999999999,29.39596],"type":"Point"}
}