{
  "type": "Feature",
  "properties": {
    "gn:admin1_code":"30",
    "gn:asciiname":"Leni",
    "gn:country_code":"CN",
    "gn:dem":37,
    "gn:feature_class":"P",
    "gn:feature_code":"PPL",
    "gn:name":"Leni",
    "gn:population":0,
    "gn:timezone":"Asia/Urumqi",
    "iso:country":"CN",
    "name:ara_x_preferred":[
        "\u0644\u064a\u0646\u064a"
    ],
    "name:azb_x_preferred":[
        "\u0644\u0646\u06cc"
    ],
    "name:bel_x_preferred":[
        "\u041b\u0435\u043d\u0456"
    ],
    "name:bul_x_preferred":[
        "\u041b\u0435\u043d\u0438"
    ],
    "name:cat_x_preferred":[
        "Leni"
    ],
    "name:ceb_x_preferred":[
        "Leni"
    ],
    "name:deu_x_preferred":[
        "Leni"
    ],
    "name:epo_x_preferred":[
        "Leni"
    ],
    "name:eus_x_preferred":[
        "Leni"
    ],
    "name:fas_x_preferred":[
        "\u0644\u0646\u06cc"
    ],
    "name:fra_x_preferred":[
        "Leni"
    ],
    "name:hun_x_preferred":[
        "Leni"
    ],
    "name:hye_x_preferred":[
        "\u053c\u0565\u0576\u056b"
    ],
    "name:ita_x_preferred":[
        "Leni"
    ],
    "name:jpn_x_preferred":[
        "\u30ec\u30fc\u30cb"
    ],
    "name:kaz_x_preferred":[
        "\u041b\u0435\u043d\u0438"
    ],
    "name:lat_x_preferred":[
        "Lenae"
    ],
    "name:lmo_x_preferred":[
        "Leni"
    ],
    "name:msa_x_preferred":[
        "Leni"
    ],
    "name:nap_x_preferred":[
        "Leni"
    ],
    "name:nld_x_preferred":[
        "Leni"
    ],
    "name:pms_x_preferred":[
        "Leni"
    ],
    "name:pol_x_preferred":[
        "Leni"
    ],
    "name:por_x_preferred":[
        "Leni"
    ],
    "name:ron_x_preferred":[
        "Leni"
    ],
    "name:rus_x_preferred":[
        "\u041b\u0435\u043d\u0438"
    ],
    "name:scn_x_preferred":[
        "Leni"
    ],
    "name:spa_x_preferred":[
        "Leni"
    ],
    "name:srp_x_preferred":[
        "\u041b\u0435\u043d\u0438"
    ],
    "name:swe_x_preferred":[
        "Leni"
    ],
    "name:tgl_x_preferred":[
        "Leni"
    ],
    "name:ukr_x_preferred":[
        "\u041b\u0435\u043d\u0456"
    ],
    "name:uzb_x_preferred":[
        "Leni"
    ],
    "name:vie_x_preferred":[
        "Leni"
    ],
    "name:vol_x_preferred":[
        "Leni"
    ],
    "name:war_x_preferred":[
        "Leni"
    ],
    "name:zho_x_preferred":[
        "\u4e50\u576d"
    ],
    "wof:name":"Leni",
    "wof:placetype":"locality"
},
  "geometry": {"coordinates":[111.12917,21.5423],"type":"Point"}
}