{
  "type": "Feature",
  "properties": {
    "gn:admin1_code":"26.0",
    "gn:asciiname":"Yueliangping",
    "gn:country_code":"CN",
    "gn:dem":1696,
    "gn:feature_class":"P",
    "gn:feature_code":"PPL",
    "gn:name":"Yueliangping",
    "gn:population":0,
    "gn:timezone":"Asia/Shanghai",
    "iso:country":"CN",
    "name:und_x_variant":[
        "\u6708\u4eae\u576a"
    ],
    "wof:name":"Yueliangping",
    "wof:placetype":"locality"
},
  "geometry": {"coordinates":[106.71371000000001,33.58969],"type":"Point"}
}