{
  "type": "Feature",
  "properties": {
    "gn:admin1_code":"2.0",
    "gn:asciiname":"Dahuangcun",
    "gn:country_code":"CN",
    "gn:dem":69,
    "gn:feature_class":"P",
    "gn:feature_code":"PPL",
    "gn:name":"Dahuangcun",
    "gn:population":0,
    "gn:timezone":"Asia/Shanghai",
    "iso:country":"CN",
    "name:und_x_variant":[
        "\u5927\u9ec4\u6751",
        "Dahuangcun"
    ],
    "wof:name":"Dahuangcun",
    "wof:placetype":"locality"
},
  "geometry": {"coordinates":[119.7359,29.18848],"type":"Point"}
}