{
  "type": "Feature",
  "properties": {
    "gn:admin1_code":"11.0",
    "gn:asciiname":"Sanguitang Liujia",
    "gn:country_code":"CN",
    "gn:dem":398,
    "gn:feature_class":"P",
    "gn:feature_code":"PPL",
    "gn:name":"Sanguitang Liujia",
    "gn:population":0,
    "gn:timezone":"Asia/Shanghai",
    "iso:country":"CN",
    "name:zho_x_preferred":[
        "\u4e09\u6842\u5858\u5218\u5bb6"
    ],
    "wof:name":"Sanguitang Liujia",
    "wof:placetype":"locality"
},
  "geometry": {"coordinates":[110.50996000000001,26.7049],"type":"Point"}
}