{
  "type": "Feature",
  "properties": {
    "gn:admin1_code":"30.0",
    "gn:asciiname":"Weicuoloucun",
    "gn:country_code":"CN",
    "gn:dem":34,
    "gn:feature_class":"P",
    "gn:feature_code":"PPL",
    "gn:name":"Weicuoloucun",
    "gn:population":0,
    "gn:timezone":"Asia/Shanghai",
    "iso:country":"CN",
    "name:zho_x_preferred":[
        "\u9b4f\u539d\u697c\u6751"
    ],
    "wof:name":"Weicuoloucun",
    "wof:placetype":"locality"
},
  "geometry": {"coordinates":[116.86284999999999,23.73116],"type":"Point"}
}