{
  "type": "Feature",
  "properties": {
    "gn:admin1_code":"2.0",
    "gn:asciiname":"Qianjia",
    "gn:country_code":"CN",
    "gn:dem":83,
    "gn:feature_class":"P",
    "gn:feature_code":"PPL",
    "gn:name":"Qianjia",
    "gn:population":0,
    "gn:timezone":"Asia/Shanghai",
    "iso:country":"CN",
    "name:und_x_variant":[
        "\u5343\u5bb6",
        "Qianjia"
    ],
    "wof:name":"Qianjia",
    "wof:placetype":"locality"
},
  "geometry": {"coordinates":[119.16737999999999,29.29188],"type":"Point"}
}