{
  "type": "Feature",
  "properties": {
    "gn:admin1_code":"11.0",
    "gn:asciiname":"Jinbaochong",
    "gn:country_code":"CN",
    "gn:dem":579,
    "gn:feature_class":"P",
    "gn:feature_code":"PPL",
    "gn:name":"Jinbaochong",
    "gn:population":0,
    "gn:timezone":"Asia/Shanghai",
    "iso:country":"CN",
    "name:zho_x_preferred":[
        "\u8fdb\u5b9d\u51b2"
    ],
    "wof:name":"Jinbaochong",
    "wof:placetype":"locality"
},
  "geometry": {"coordinates":[113.16204999999999,26.56016],"type":"Point"}
}