{
  "type": "Feature",
  "properties": {
    "gn:admin1_code":"3",
    "gn:asciiname":"Fengtianzhou",
    "gn:country_code":"CN",
    "gn:dem":507,
    "gn:feature_class":"P",
    "gn:feature_code":"PPL",
    "gn:name":"Fengtianzhou",
    "gn:population":0,
    "gn:timezone":"Asia/Shanghai",
    "iso:country":"CN",
    "name:zho_x_preferred":[
        "\u4e30\u7530\u6d32"
    ],
    "wof:name":"Fengtianzhou",
    "wof:placetype":"locality"
},
  "geometry": {"coordinates":[114.254,26.5514],"type":"Point"}
}