{
  "type": "Feature",
  "properties": {
    "gn:admin1_code":"15.0",
    "gn:asciiname":"Muyoufang",
    "gn:country_code":"CN",
    "gn:dem":1439,
    "gn:feature_class":"P",
    "gn:feature_code":"PPL",
    "gn:name":"Muyoufang",
    "gn:population":0,
    "gn:timezone":"Asia/Shanghai",
    "iso:country":"CN",
    "name:und_x_variant":[
        "\u6155\u6cb9\u574a"
    ],
    "wof:name":"Muyoufang",
    "wof:placetype":"locality"
},
  "geometry": {"coordinates":[107.45325,36.89143],"type":"Point"}
}