{
  "type": "Feature",
  "properties": {
    "gn:admin1_code":"14.0",
    "gn:asciiname":"Woluobangga",
    "gn:country_code":"CN",
    "gn:dem":3004,
    "gn:feature_class":"P",
    "gn:feature_code":"PPL",
    "gn:name":"Woluobangga",
    "gn:population":0,
    "gn:timezone":"Asia/Urumqi",
    "iso:country":"CN",
    "name:zho_x_preferred":[
        "\u5594\u7f57\u5e2e\u560e"
    ],
    "wof:name":"Woluobangga",
    "wof:placetype":"locality"
},
  "geometry": {"coordinates":[94.35799,29.5973],"type":"Point"}
}