{
  "type": "Feature",
  "properties": {
    "gn:admin1_code":"11.0",
    "gn:asciiname":"Shangliangjia",
    "gn:country_code":"CN",
    "gn:dem":192,
    "gn:feature_class":"P",
    "gn:feature_code":"PPL",
    "gn:name":"Shangliangjia",
    "gn:population":0,
    "gn:timezone":"Asia/Shanghai",
    "iso:country":"CN",
    "name:zho_x_preferred":[
        "\u4e0a\u6881\u5bb6"
    ],
    "wof:name":"Shangliangjia",
    "wof:placetype":"locality"
},
  "geometry": {"coordinates":[112.53909,25.85777],"type":"Point"}
}