{
  "type": "Feature",
  "properties": {
    "gn:admin1_code":"18",
    "gn:asciiname":"Shangdali",
    "gn:country_code":"CN",
    "gn:dem":906,
    "gn:feature_class":"P",
    "gn:feature_code":"PPL",
    "gn:name":"Shangdali",
    "gn:population":0,
    "gn:timezone":"Asia/Shanghai",
    "iso:country":"CN",
    "name:zho_x_preferred":[
        "\u4e0a\u8fbe\u529b"
    ],
    "wof:name":"Shangdali",
    "wof:placetype":"locality"
},
  "geometry": {"coordinates":[104.837,24.7767],"type":"Point"}
}