{
  "type": "Feature",
  "properties": {
    "gn:admin1_code":"25",
    "gn:asciiname":"Beishangren",
    "gn:country_code":"CN",
    "gn:dem":83,
    "gn:feature_class":"P",
    "gn:feature_code":"PPL",
    "gn:name":"Beishangren",
    "gn:population":0,
    "gn:timezone":"Asia/Shanghai",
    "iso:country":"CN",
    "name:zho_x_preferred":[
        "\u5317\u5c1a\u4efb"
    ],
    "wof:name":"Beishangren",
    "wof:placetype":"locality"
},
  "geometry": {"coordinates":[116.633,36.0756],"type":"Point"}
}