{
  "type": "Feature",
  "properties": {
    "gn:admin1_code":"16.0",
    "gn:asciiname":"Hecha",
    "gn:country_code":"CN",
    "gn:dem":380,
    "gn:feature_class":"P",
    "gn:feature_code":"PPL",
    "gn:name":"Hecha",
    "gn:population":0,
    "gn:timezone":"Asia/Shanghai",
    "iso:country":"CN",
    "name:zho_x_preferred":[
        "\u6cb3\u5c94"
    ],
    "wof:name":"Hecha",
    "wof:placetype":"locality"
},
  "geometry": {"coordinates":[109.994,23.8571],"type":"Point"}
}