{
  "type": "Feature",
  "properties": {
    "gn:admin1_code":"7.0",
    "gn:asciiname":"Diaohe",
    "gn:country_code":"CN",
    "gn:dem":321,
    "gn:feature_class":"P",
    "gn:feature_code":"PPL",
    "gn:name":"Diaohe",
    "gn:population":0,
    "gn:timezone":"Asia/Shanghai",
    "iso:country":"CN",
    "name:zho_x_preferred":[
        "\u8c03\u548c"
    ],
    "wof:name":"Diaohe",
    "wof:placetype":"locality"
},
  "geometry": {"coordinates":[116.60992,25.03119],"type":"Point"}
}