{
  "type": "Feature",
  "properties": {
    "gn:admin1_code":"8.0",
    "gn:asciiname":"Kanglecun",
    "gn:country_code":"CN",
    "gn:dem":212,
    "gn:feature_class":"P",
    "gn:feature_code":"PPL",
    "gn:name":"Kanglecun",
    "gn:population":0,
    "gn:timezone":"Asia/Shanghai",
    "iso:country":"CN",
    "name:zho_x_preferred":[
        "\u5eb7\u4e50\u6751"
    ],
    "wof:name":"Kanglecun",
    "wof:placetype":"locality"
},
  "geometry": {"coordinates":[124.63478000000001,48.07095],"type":"Point"}
}