{
  "type": "Feature",
  "properties": {
    "gn:admin1_code":"3.0",
    "gn:asciiname":"Guantangli",
    "gn:country_code":"CN",
    "gn:dem":271,
    "gn:feature_class":"P",
    "gn:feature_code":"PPL",
    "gn:name":"Guantangli",
    "gn:population":0,
    "gn:timezone":"Asia/Shanghai",
    "iso:country":"CN",
    "name:zho_x_preferred":[
        "\u704c\u5802\u91cc"
    ],
    "wof:name":"Guantangli",
    "wof:placetype":"locality"
},
  "geometry": {"coordinates":[114.767,29.1223],"type":"Point"}
}