{
  "type": "Feature",
  "properties": {
    "gn:admin1_code":"18",
    "gn:asciiname":"Meizishui",
    "gn:country_code":"CN",
    "gn:dem":1301,
    "gn:feature_class":"P",
    "gn:feature_code":"PPL",
    "gn:name":"Meizishui",
    "gn:population":0,
    "gn:timezone":"Asia/Shanghai",
    "iso:country":"CN",
    "name:zho_x_preferred":[
        "\u6885\u5b50\u6c34"
    ],
    "wof:name":"Meizishui",
    "wof:placetype":"locality"
},
  "geometry": {"coordinates":[106.937,28.265],"type":"Point"}
}