{
  "type": "Feature",
  "properties": {
    "gn:admin1_code":"12.0",
    "gn:asciiname":"Huangjiaya",
    "gn:country_code":"CN",
    "gn:dem":1243,
    "gn:feature_class":"P",
    "gn:feature_code":"PPL",
    "gn:name":"Huangjiaya",
    "gn:population":0,
    "gn:timezone":"Asia/Shanghai",
    "iso:country":"CN",
    "name:zho_x_preferred":[
        "\u9ec4\u5bb6\u57ad"
    ],
    "wof:name":"Huangjiaya",
    "wof:placetype":"locality"
},
  "geometry": {"coordinates":[110.69704,30.76688],"type":"Point"}
}