{
  "type": "Feature",
  "properties": {
    "gn:admin1_code":"16.0",
    "gn:asciiname":"Gongcun",
    "gn:country_code":"CN",
    "gn:dem":125,
    "gn:feature_class":"P",
    "gn:feature_code":"PPL",
    "gn:name":"Gongcun",
    "gn:population":0,
    "gn:timezone":"Asia/Shanghai",
    "iso:country":"CN",
    "name:zho_x_preferred":[
        "\u606d\u6751"
    ],
    "wof:name":"Gongcun",
    "wof:placetype":"locality"
},
  "geometry": {"coordinates":[109.32899999999999,24.1411],"type":"Point"}
}