{
  "type": "Feature",
  "properties": {
    "gn:admin1_code":"05",
    "gn:asciiname":"Pizhou",
    "gn:country_code":"CN",
    "gn:dem":352,
    "gn:feature_class":"P",
    "gn:feature_code":"PPL",
    "gn:name":"Pizhou",
    "gn:population":0,
    "gn:timezone":"Asia/Shanghai",
    "iso:country":"CN",
    "name:deu_x_preferred":[
        "Pizhou"
    ],
    "name:fra_x_preferred":[
        "Pizhou"
    ],
    "name:ita_x_preferred":[
        "Pizhou"
    ],
    "name:jpn_x_preferred":[
        "\u30d2\u5dde\u5e02"
    ],
    "name:kik_x_preferred":[
        "Pizhou"
    ],
    "name:kor_x_preferred":[
        "\ud53c\uc800\uc6b0\uc2dc"
    ],
    "name:mlg_x_preferred":[
        "Pizhou"
    ],
    "name:nor_x_preferred":[
        "Pizhou"
    ],
    "name:rus_x_preferred":[
        "\u041f\u0438\u0447\u0436\u043e\u0443"
    ],
    "name:swe_x_preferred":[
        "Pizhou"
    ],
    "name:tgl_x_preferred":[
        "Pizhou"
    ],
    "name:und_x_variant":[
        "\u6279\u6d32"
    ],
    "name:urd_x_preferred":[
        "\u067e\u06cc\u0698\u0648"
    ],
    "name:vie_x_preferred":[
        "Bi Ch\u00e2u"
    ],
    "name:zho_x_preferred":[
        "\u90b3\u5dde\u5e02"
    ],
    "wof:name":"Pizhou",
    "wof:placetype":"locality"
},
  "geometry": {"coordinates":[127.19611,42.81472],"type":"Point"}
}