{
  "type": "Feature",
  "properties": {
    "gn:admin1_code":"05",
    "gn:asciiname":"Pizhou",
    "gn:country_code":"CN",
    "gn:dem":352,
    "gn:feature_class":"P",
    "gn:feature_code":"PPL",
    "gn:name":"Pizhou",
    "gn:population":0,
    "gn:timezone":"Asia/Shanghai",
    "iso:country":"CN",
    "name:und_x_variant":[
        "\u6279\u6d32"
    ],
    "wof:name":"Pizhou",
    "wof:placetype":"locality"
},
  "geometry": {"coordinates":[127.19611,42.81472],"type":"Point"}
}