{
  "type": "Feature",
  "properties": {
    "gn:admin1_code":"32.0",
    "gn:asciiname":"Ciliwan",
    "gn:country_code":"CN",
    "gn:dem":703,
    "gn:feature_class":"P",
    "gn:feature_code":"PPL",
    "gn:name":"Ciliwan",
    "gn:population":0,
    "gn:timezone":"Asia/Shanghai",
    "iso:country":"CN",
    "name:zho_x_preferred":[
        "\u8328\u68a8\u6e7e"
    ],
    "wof:name":"Ciliwan",
    "wof:placetype":"locality"
},
  "geometry": {"coordinates":[103.64306000000001,30.97374000000001],"type":"Point"}
}