{
  "type": "Feature",
  "properties": {
    "gn:admin1_code":"11.0",
    "gn:asciiname":"Yangmeilong",
    "gn:country_code":"CN",
    "gn:dem":554,
    "gn:feature_class":"P",
    "gn:feature_code":"PPL",
    "gn:name":"Yangmeilong",
    "gn:population":0,
    "gn:timezone":"Asia/Shanghai",
    "iso:country":"CN",
    "name:zho_x_preferred":[
        "\u6768\u6885\u5785"
    ],
    "wof:name":"Yangmeilong",
    "wof:placetype":"locality"
},
  "geometry": {"coordinates":[113.52428,25.608],"type":"Point"}
}