{
  "type": "Feature",
  "properties": {
    "gn:admin1_code":"8.0",
    "gn:asciiname":"Qianliucuo",
    "gn:country_code":"CN",
    "gn:dem":170,
    "gn:feature_class":"P",
    "gn:feature_code":"PPL",
    "gn:name":"Qianliucuo",
    "gn:population":0,
    "gn:timezone":"Asia/Shanghai",
    "iso:country":"CN",
    "name:zho_x_preferred":[
        "\u524d\u516d\u64ae"
    ],
    "wof:name":"Qianliucuo",
    "wof:placetype":"locality"
},
  "geometry": {"coordinates":[125.87848,45.96874],"type":"Point"}
}