{
  "type": "Feature",
  "properties": {
    "gn:admin1_code":"13.0",
    "gn:asciiname":"Kegeqi Sikuotan",
    "gn:country_code":"CN",
    "gn:dem":898,
    "gn:feature_class":"P",
    "gn:feature_code":"PPL",
    "gn:name":"Kegeqi Sikuotan",
    "gn:population":0,
    "gn:timezone":"Asia/Urumqi",
    "iso:country":"CN",
    "name:zho_x_preferred":[
        "\u514b\u4e2a\u5947\u601d\u9614\u5766"
    ],
    "wof:name":"Kegeqi Sikuotan",
    "wof:placetype":"locality"
},
  "geometry": {"coordinates":[85.62013,41.14039],"type":"Point"}
}