{
  "type": "Feature",
  "properties": {
    "gn:admin1_code":"9.0",
    "gn:asciiname":"Gumen",
    "gn:country_code":"CN",
    "gn:dem":76,
    "gn:feature_class":"P",
    "gn:feature_code":"PPL",
    "gn:name":"Gumen",
    "gn:population":0,
    "gn:timezone":"Asia/Shanghai",
    "iso:country":"CN",
    "name:zho_x_preferred":[
        "\u580c\u95e8"
    ],
    "wof:name":"Gumen",
    "wof:placetype":"locality"
},
  "geometry": {"coordinates":[114.31014999999999,34.81851],"type":"Point"}
}