{
  "type": "Feature",
  "properties": {
    "gn:admin1_code":"01",
    "gn:asciiname":"Dingjiabucun",
    "gn:country_code":"CN",
    "gn:dem":148,
    "gn:feature_class":"P",
    "gn:feature_code":"PPL",
    "gn:name":"Dingjiabucun",
    "gn:population":0,
    "gn:timezone":"Asia/Shanghai",
    "iso:country":"CN",
    "name:und_x_variant":[
        "Ting-chia-p\u2019u",
        "Dingbujie",
        "Ting-pu",
        "Ting-pu-chieh",
        "Dingjiabu",
        "Dingjiabucun"
    ],
    "name:zho_x_preferred":[
        "\u4e01\u5bb6\u57e0\u6751"
    ],
    "wof:name":"Dingjiabucun",
    "wof:placetype":"locality"
},
  "geometry": {"coordinates":[115.64306999999999,31.46569],"type":"Point"}
}