{
  "type": "Feature",
  "properties": {
    "gn:admin1_code":"3.0",
    "gn:asciiname":"Damujiang",
    "gn:country_code":"CN",
    "gn:dem":91,
    "gn:feature_class":"P",
    "gn:feature_code":"PPL",
    "gn:name":"Damujiang",
    "gn:population":0,
    "gn:timezone":"Asia/Shanghai",
    "iso:country":"CN",
    "name:und_x_variant":[
        "\u5927\u7766\u6c5f"
    ],
    "wof:name":"Damujiang",
    "wof:placetype":"locality"
},
  "geometry": {"coordinates":[115.41012000000001,27.3616],"type":"Point"}
}