{
  "type": "Feature",
  "properties": {
    "gn:admin1_code":"19.0",
    "gn:asciiname":"Shangjiucaiyu",
    "gn:country_code":"CN",
    "gn:dem":249,
    "gn:feature_class":"P",
    "gn:feature_code":"PPL",
    "gn:name":"Shangjiucaiyu",
    "gn:population":0,
    "gn:timezone":"Asia/Shanghai",
    "iso:country":"CN",
    "name:zho_x_preferred":[
        "\u4e0a\u97ed\u83dc\u5cea"
    ],
    "wof:name":"Shangjiucaiyu",
    "wof:placetype":"locality"
},
  "geometry": {"coordinates":[124.36032,42.13264],"type":"Point"}
}