{
  "type": "Feature",
  "properties": {
    "gn:admin1_code":"30.0",
    "gn:asciiname":"Zhutougang",
    "gn:country_code":"CN",
    "gn:dem":23,
    "gn:feature_class":"P",
    "gn:feature_code":"PPL",
    "gn:name":"Zhutougang",
    "gn:population":0,
    "gn:timezone":"Asia/Shanghai",
    "iso:country":"CN",
    "name:zho_x_preferred":[
        "\u73e0\u5934\u5c97"
    ],
    "wof:name":"Zhutougang",
    "wof:placetype":"locality"
},
  "geometry": {"coordinates":[111.71453,22.91389],"type":"Point"}
}