{
  "type": "Feature",
  "properties": {
    "gn:admin1_code":"20.0",
    "gn:asciiname":"Yaotouliang",
    "gn:country_code":"CN",
    "gn:dem":1267,
    "gn:feature_class":"P",
    "gn:feature_code":"PPL",
    "gn:name":"Yaotouliang",
    "gn:population":0,
    "gn:timezone":"Asia/Shanghai",
    "iso:country":"CN",
    "name:und_x_variant":[
        "\u7a91\u5934\u6881"
    ],
    "wof:name":"Yaotouliang",
    "wof:placetype":"locality"
},
  "geometry": {"coordinates":[111.68995,39.97165],"type":"Point"}
}