{
  "type": "Feature",
  "properties": {
    "gn:admin1_code":"9.0",
    "gn:asciiname":"Shanghuangye",
    "gn:country_code":"CN",
    "gn:dem":930,
    "gn:feature_class":"P",
    "gn:feature_code":"PPL",
    "gn:name":"Shanghuangye",
    "gn:population":0,
    "gn:timezone":"Asia/Shanghai",
    "iso:country":"CN",
    "name:zho_x_preferred":[
        "\u4e0a\u9ec4\u53f6"
    ],
    "wof:name":"Shanghuangye",
    "wof:placetype":"locality"
},
  "geometry": {"coordinates":[110.87169,34.06602],"type":"Point"}
}