{
  "type": "Feature",
  "properties": {
    "gn:admin1_code":"30.0",
    "gn:asciiname":"Aotou",
    "gn:country_code":"CN",
    "gn:dem":544,
    "gn:feature_class":"P",
    "gn:feature_code":"PPL",
    "gn:name":"Aotou",
    "gn:population":0,
    "gn:timezone":"Asia/Shanghai",
    "iso:country":"CN",
    "name:zho_x_preferred":[
        "Aotou"
    ],
    "name:zho_x_variant":[
        "\u5773\u5934"
    ],
    "wof:name":"Aotou",
    "wof:placetype":"locality"
},
  "geometry": {"coordinates":[113.24194,25.16639],"type":"Point"}
}