{
  "type": "Feature",
  "properties": {
    "gn:admin1_code":"2.0",
    "gn:asciiname":"Diaobideng",
    "gn:country_code":"CN",
    "gn:dem":300,
    "gn:feature_class":"P",
    "gn:feature_code":"PPL",
    "gn:name":"Diaobideng",
    "gn:population":0,
    "gn:timezone":"Asia/Shanghai",
    "iso:country":"CN",
    "name:zho_x_preferred":[
        "\u540a\u58c1\u706f"
    ],
    "wof:name":"Diaobideng",
    "wof:placetype":"locality"
},
  "geometry": {"coordinates":[120.50693,27.40961],"type":"Point"}
}