{
  "type": "Feature",
  "properties": {
    "gn:admin1_code":"10.0",
    "gn:asciiname":"Guotatou",
    "gn:country_code":"CN",
    "gn:dem":22,
    "gn:feature_class":"P",
    "gn:feature_code":"PPL",
    "gn:name":"Guotatou",
    "gn:population":0,
    "gn:timezone":"Asia/Shanghai",
    "iso:country":"CN",
    "name:zho_x_preferred":[
        "\u90ed\u5854\u5934"
    ],
    "wof:name":"Guotatou",
    "wof:placetype":"locality"
},
  "geometry": {"coordinates":[116.10923,37.8511],"type":"Point"}
}