{
  "type": "Feature",
  "properties": {
    "gn:admin1_code":"5.0",
    "gn:asciiname":"Xiaohaoli",
    "gn:country_code":"CN",
    "gn:dem":125,
    "gn:feature_class":"P",
    "gn:feature_code":"PPL",
    "gn:name":"Xiaohaoli",
    "gn:population":0,
    "gn:timezone":"Asia/Shanghai",
    "iso:country":"CN",
    "name:zho_x_preferred":[
        "\u5c0f\u58d5\u91cc"
    ],
    "wof:name":"Xiaohaoli",
    "wof:placetype":"locality"
},
  "geometry": {"coordinates":[124.04716000000001,43.31576],"type":"Point"}
}