{
  "type": "Feature",
  "properties": {
    "gn:admin1_code":"02",
    "gn:asciiname":"Pacao",
    "gn:country_code":"CN",
    "gn:dem":2,
    "gn:feature_class":"P",
    "gn:feature_code":"PPL",
    "gn:name":"Pacao",
    "gn:population":0,
    "gn:timezone":"Asia/Shanghai",
    "iso:country":"CN",
    "name:zho_x_preferred":[
        "\u8225\u825a"
    ],
    "name:zho_x_variant":[
        "Pacao"
    ],
    "wof:name":"Pacao",
    "wof:placetype":"locality"
},
  "geometry": {"coordinates":[120.62752,27.48722],"type":"Point"}
}