{
  "type": "Feature",
  "properties": {
    "gn:admin1_code":"7",
    "gn:asciiname":"Yingdun",
    "gn:cc2":"CN",
    "gn:country_code":"CN",
    "gn:dem":33,
    "gn:feature_class":"P",
    "gn:feature_code":"PPL",
    "gn:name":"Yingdun",
    "gn:population":0,
    "gn:timezone":"Asia/Shanghai",
    "iso:country":"CN",
    "name:und_x_variant":[
        "Ying-tun",
        "Yingdun"
    ],
    "name:zho_x_preferred":[
        "\u82f1\u58a9"
    ],
    "wof:name":"Yingdun",
    "wof:placetype":"locality"
},
  "geometry": {"coordinates":[118.55389,24.72861],"type":"Point"}
}