{
  "type": "Feature",
  "properties": {
    "gn:admin1_code":"24.0",
    "gn:asciiname":"Xialiyangquan",
    "gn:country_code":"CN",
    "gn:dem":1600,
    "gn:feature_class":"P",
    "gn:feature_code":"PPL",
    "gn:name":"Xialiyangquan",
    "gn:population":0,
    "gn:timezone":"Asia/Shanghai",
    "iso:country":"CN",
    "name:und_x_variant":[
        "\u4e0b\u7acb\u7f8a\u6cc9"
    ],
    "wof:name":"Xialiyangquan",
    "wof:placetype":"locality"
},
  "geometry": {"coordinates":[112.61132000000001,39.58777],"type":"Point"}
}