{
  "type": "Feature",
  "properties": {
    "gn:admin1_code":"26.0",
    "gn:asciiname":"Nianlipu",
    "gn:country_code":"CN",
    "gn:dem":941,
    "gn:feature_class":"P",
    "gn:feature_code":"PPL",
    "gn:name":"Nianlipu",
    "gn:population":0,
    "gn:timezone":"Asia/Shanghai",
    "iso:country":"CN",
    "name:und_x_variant":[
        "\u5eff\u91cc\u94fa"
    ],
    "wof:name":"Nianlipu",
    "wof:placetype":"locality"
},
  "geometry": {"coordinates":[106.99946,33.37365],"type":"Point"}
}