{
  "type": "Feature",
  "properties": {
    "gn:admin1_code":"29.0",
    "gn:asciiname":"Yejiacun",
    "gn:country_code":"CN",
    "gn:dem":2055,
    "gn:feature_class":"P",
    "gn:feature_code":"PPL",
    "gn:name":"Yejiacun",
    "gn:population":0,
    "gn:timezone":"Asia/Shanghai",
    "iso:country":"CN",
    "name:zho_x_preferred":[
        "\u53f6\u5bb6\u6751"
    ],
    "wof:name":"Yejiacun",
    "wof:placetype":"locality"
},
  "geometry": {"coordinates":[103.71899999999999,26.2315],"type":"Point"}
}