{
  "type": "Feature",
  "properties": {
    "gn:admin1_code":"12.0",
    "gn:asciiname":"Renzong Bacun",
    "gn:country_code":"CN",
    "gn:dem":25,
    "gn:feature_class":"P",
    "gn:feature_code":"PPL",
    "gn:name":"Renzong Bacun",
    "gn:population":0,
    "gn:timezone":"Asia/Shanghai",
    "iso:country":"CN",
    "name:zho_x_preferred":[
        "\u4efb\u5b97\u516b\u6751"
    ],
    "wof:name":"Renzong Bacun",
    "wof:placetype":"locality"
},
  "geometry": {"coordinates":[114.34557,30.20711],"type":"Point"}
}