{
  "type": "Feature",
  "properties": {
    "gn:admin1_code":"3.0",
    "gn:asciiname":"Zhuashi",
    "gn:country_code":"CN",
    "gn:dem":64,
    "gn:feature_class":"P",
    "gn:feature_code":"PPL",
    "gn:name":"Zhuashi",
    "gn:population":0,
    "gn:timezone":"Asia/Shanghai",
    "iso:country":"CN",
    "name:und_x_variant":[
        "\u722a\u77f3"
    ],
    "wof:name":"Zhuashi",
    "wof:placetype":"locality"
},
  "geometry": {"coordinates":[116.10735,27.90398],"type":"Point"}
}