{
  "type": "Feature",
  "properties": {
    "gn:admin1_code":"5",
    "gn:asciiname":"Wudaogou",
    "gn:country_code":"CN",
    "gn:dem":452,
    "gn:feature_class":"P",
    "gn:feature_code":"PPL",
    "gn:name":"Wudaogou",
    "gn:population":0,
    "gn:timezone":"Asia/Shanghai",
    "iso:country":"CN",
    "name:zho_x_preferred":[
        "\u4e94\u9053\u6c9f"
    ],
    "wof:name":"Wudaogou",
    "wof:placetype":"locality"
},
  "geometry": {"coordinates":[127.773,43.6804],"type":"Point"}
}