{
  "type": "Feature",
  "properties": {
    "gn:admin1_code":"12.0",
    "gn:asciiname":"Wujia Dawan",
    "gn:country_code":"CN",
    "gn:dem":27,
    "gn:feature_class":"P",
    "gn:feature_code":"PPL",
    "gn:name":"Wujia Dawan",
    "gn:population":0,
    "gn:timezone":"Asia/Shanghai",
    "iso:country":"CN",
    "name:und_x_variant":[
        "\u5434\u5bb6\u5927\u5846"
    ],
    "wof:name":"Wujia Dawan",
    "wof:placetype":"locality"
},
  "geometry": {"coordinates":[114.39252999999999,30.92685],"type":"Point"}
}