{
  "type": "Feature",
  "properties": {
    "gn:admin1_code":"8.0",
    "gn:asciiname":"Xiaoliujingzi",
    "gn:country_code":"CN",
    "gn:dem":197,
    "gn:feature_class":"P",
    "gn:feature_code":"PPL",
    "gn:name":"Xiaoliujingzi",
    "gn:population":0,
    "gn:timezone":"Asia/Shanghai",
    "iso:country":"CN",
    "name:zho_x_preferred":[
        "\u5c0f\u516d\u4e95\u5b50"
    ],
    "wof:name":"Xiaoliujingzi",
    "wof:placetype":"locality"
},
  "geometry": {"coordinates":[126.74561,47.04035],"type":"Point"}
}