{
  "type": "Feature",
  "properties": {
    "gn:admin1_code":"14.0",
    "gn:asciiname":"Jingzhoichong",
    "gn:country_code":"CN",
    "gn:dem":4273,
    "gn:feature_class":"P",
    "gn:feature_code":"PPL",
    "gn:name":"Jingzhoichong",
    "gn:population":0,
    "gn:timezone":"Asia/Urumqi",
    "iso:country":"CN",
    "name:bod_x_preferred":[
        "Jingzhoichong"
    ],
    "name:zho_x_preferred":[
        "Jinzhuchong"
    ],
    "name:zho_x_variant":[
        "\u91d1\u73e0\u51b2",
        "Ziga Qu",
        "\u5b57\u560e\u533a"
    ],
    "wof:name":"Jingzhoichong",
    "wof:placetype":"locality"
},
  "geometry": {"coordinates":[97.90300000000001,31.603],"type":"Point"}
}