{
  "type": "Feature",
  "properties": {
    "gn:admin1_code":"33.0",
    "gn:asciiname":"Xianlong",
    "gn:country_code":"CN",
    "gn:dem":366,
    "gn:feature_class":"P",
    "gn:feature_code":"PPL",
    "gn:name":"Xianlong",
    "gn:population":0,
    "gn:timezone":"Asia/Shanghai",
    "iso:country":"CN",
    "name:zho_x_preferred":[
        "\u73b0\u9f99"
    ],
    "wof:name":"Xianlong",
    "wof:placetype":"locality"
},
  "geometry": {"coordinates":[105.64321,29.61862],"type":"Point"}
}