{
  "type": "Feature",
  "properties": {
    "gn:admin1_code":"11.0",
    "gn:asciiname":"Zexiwan",
    "gn:country_code":"CN",
    "gn:dem":123,
    "gn:feature_class":"P",
    "gn:feature_code":"PPL",
    "gn:name":"Zexiwan",
    "gn:population":0,
    "gn:timezone":"Asia/Shanghai",
    "iso:country":"CN",
    "name:zho_x_preferred":[
        "\u6cfd\u6eaa\u6e7e"
    ],
    "wof:name":"Zexiwan",
    "wof:placetype":"locality"
},
  "geometry": {"coordinates":[111.92628000000001,27.79298],"type":"Point"}
}