{
  "type": "Feature",
  "properties": {
    "gn:admin1_code":"18.0",
    "gn:asciiname":"Luohexi",
    "gn:country_code":"CN",
    "gn:dem":357,
    "gn:feature_class":"P",
    "gn:feature_code":"PPL",
    "gn:name":"Luohexi",
    "gn:population":0,
    "gn:timezone":"Asia/Shanghai",
    "iso:country":"CN",
    "name:zho_x_preferred":[
        "\u7f57\u6cb3\u6eaa"
    ],
    "wof:name":"Luohexi",
    "wof:placetype":"locality"
},
  "geometry": {"coordinates":[109.15600000000001,27.7493],"type":"Point"}
}