{
  "type": "Feature",
  "properties": {
    "gn:admin1_code":"02",
    "gn:asciiname":"Muli",
    "gn:country_code":"CN",
    "gn:dem":733,
    "gn:feature_class":"P",
    "gn:feature_code":"PPLA4",
    "gn:name":"Muli",
    "gn:population":0,
    "gn:timezone":"Asia/Shanghai",
    "iso:country":"CN",
    "name:und_x_variant":[
        "Muli Xiang"
    ],
    "name:zho_x_preferred":[
        "\u6728\u6817"
    ],
    "name:zho_x_variant":[
        "\u6728\u6817\u4e61"
    ],
    "wof:name":"Muli",
    "wof:placetype":"locality"
},
  "geometry": {"coordinates":[120.34098,28.44918],"type":"Point"}
}