{
  "type": "Feature",
  "properties": {
    "gn:admin1_code":"02",
    "gn:asciiname":"Muli",
    "gn:country_code":"CN",
    "gn:dem":733,
    "gn:feature_class":"P",
    "gn:feature_code":"PPLA4",
    "gn:name":"Muli",
    "gn:population":0,
    "gn:timezone":"Asia/Shanghai",
    "iso:country":"CN",
    "name:ceb_x_preferred":[
        "Muli"
    ],
    "name:deu_x_preferred":[
        "Muli"
    ],
    "name:div_x_preferred":[
        "\u0789\u07aa\u078d\u07a8"
    ],
    "name:fas_x_preferred":[
        "\u0645\u0648\u0644\u06cc"
    ],
    "name:nld_x_preferred":[
        "Muli"
    ],
    "name:swe_x_preferred":[
        "Muli"
    ],
    "name:und_x_variant":[
        "Muli Xiang"
    ],
    "name:zho_x_preferred":[
        "\u6728\u6817"
    ],
    "name:zho_x_variant":[
        "\u6728\u6817\u4e61"
    ],
    "wof:name":"Muli",
    "wof:placetype":"locality"
},
  "geometry": {"coordinates":[120.34098,28.44918],"type":"Point"}
}