{
  "type": "Feature",
  "properties": {
    "gn:admin1_code":"16.0",
    "gn:asciiname":"Ruidong",
    "gn:country_code":"CN",
    "gn:dem":79,
    "gn:feature_class":"P",
    "gn:feature_code":"PPL",
    "gn:name":"Ruidong",
    "gn:population":0,
    "gn:timezone":"Asia/Shanghai",
    "iso:country":"CN",
    "name:zho_x_preferred":[
        "\u745e\u578c"
    ],
    "wof:name":"Ruidong",
    "wof:placetype":"locality"
},
  "geometry": {"coordinates":[110.018,22.4256],"type":"Point"}
}