{
  "type": "Feature",
  "properties": {
    "gn:admin1_code":"14.0",
    "gn:asciiname":"Rangla",
    "gn:country_code":"CN",
    "gn:dem":3966,
    "gn:feature_class":"P",
    "gn:feature_code":"PPL",
    "gn:name":"Rangla",
    "gn:population":0,
    "gn:timezone":"Asia/Urumqi",
    "iso:country":"CN",
    "name:zho_x_preferred":[
        "\u8ba9\u62c9"
    ],
    "wof:name":"Rangla",
    "wof:placetype":"locality"
},
  "geometry": {"coordinates":[93.17771999999999,30.20284],"type":"Point"}
}