{
  "type": "Feature",
  "properties": {
    "gn:admin1_code":"11",
    "gn:asciiname":"Xuejie",
    "gn:country_code":"CN",
    "gn:dem":345,
    "gn:feature_class":"P",
    "gn:feature_code":"PPL",
    "gn:name":"Xuejie",
    "gn:population":0,
    "gn:timezone":"Asia/Shanghai",
    "iso:country":"CN",
    "name:zho_x_preferred":[
        "\u96ea\u754c"
    ],
    "wof:name":"Xuejie",
    "wof:placetype":"locality"
},
  "geometry": {"coordinates":[111.11699,27.50562],"type":"Point"}
}