{
  "type": "Feature",
  "properties": {
    "gn:admin1_code":"4.0",
    "gn:asciiname":"Mazhuangcun",
    "gn:country_code":"CN",
    "gn:dem":42,
    "gn:feature_class":"P",
    "gn:feature_code":"PPL",
    "gn:name":"Mazhuangcun",
    "gn:population":0,
    "gn:timezone":"Asia/Shanghai",
    "iso:country":"CN",
    "name:und_x_variant":[
        "Mazhuang",
        "Mazhuangcun"
    ],
    "name:zho_x_preferred":[
        "\u9a6c\u5e84"
    ],
    "name:zho_x_variant":[
        "\u9a6c\u5e84\u6751"
    ],
    "wof:name":"Mazhuangcun",
    "wof:placetype":"locality"
},
  "geometry": {"coordinates":[116.73529000000001,34.87268],"type":"Point"}
}