{
  "type": "Feature",
  "properties": {
    "gn:admin1_code":"10.0",
    "gn:asciiname":"Baimao Dianzi",
    "gn:country_code":"CN",
    "gn:dem":582,
    "gn:feature_class":"P",
    "gn:feature_code":"PPL",
    "gn:name":"Baimao Dianzi",
    "gn:population":0,
    "gn:timezone":"Asia/Shanghai",
    "iso:country":"CN",
    "name:zho_x_preferred":[
        "\u767d\u8305\u7538\u5b50"
    ],
    "wof:name":"Baimao Dianzi",
    "wof:placetype":"locality"
},
  "geometry": {"coordinates":[117.55492,40.4986],"type":"Point"}
}