{
  "type": "Feature",
  "properties": {
    "gn:admin1_code":"26.0",
    "gn:asciiname":"Maqu Goukou",
    "gn:country_code":"CN",
    "gn:dem":867,
    "gn:feature_class":"P",
    "gn:feature_code":"PPL",
    "gn:name":"Maqu Goukou",
    "gn:population":0,
    "gn:timezone":"Asia/Shanghai",
    "iso:country":"CN",
    "name:zho_x_preferred":[
        "\u9a6c\u6e20\u6c9f\u53e3"
    ],
    "wof:name":"Maqu Goukou",
    "wof:placetype":"locality"
},
  "geometry": {"coordinates":[110.60324,34.0178],"type":"Point"}
}