{
  "type": "Feature",
  "properties": {
    "gn:admin1_code":"7.0",
    "gn:asciiname":"Huangmaoyuan",
    "gn:country_code":"CN",
    "gn:dem":271,
    "gn:feature_class":"P",
    "gn:feature_code":"PPL",
    "gn:name":"Huangmaoyuan",
    "gn:population":0,
    "gn:timezone":"Asia/Shanghai",
    "iso:country":"CN",
    "name:zho_x_preferred":[
        "\u9ec4\u8305\u56ed"
    ],
    "wof:name":"Huangmaoyuan",
    "wof:placetype":"locality"
},
  "geometry": {"coordinates":[117.38845000000001,27.67697],"type":"Point"}
}