{
  "type": "Feature",
  "properties": {
    "gn:admin1_code":"6.0",
    "gn:asciiname":"Heihe",
    "gn:country_code":"CN",
    "gn:dem":4302,
    "gn:feature_class":"P",
    "gn:feature_code":"PPLA4",
    "gn:name":"Heihe",
    "gn:population":0,
    "gn:timezone":"Asia/Urumqi",
    "iso:country":"CN",
    "name:und_x_variant":[
        "Heihe Xiang",
        "Zuowei Longwa"
    ],
    "name:zho_x_preferred":[
        "\u9ed1\u6cb3"
    ],
    "name:zho_x_variant":[
        "\u9ed1\u6cb3\u4e61",
        "\u4f5c\u7ef4\u9686\u54c7"
    ],
    "wof:name":"Heihe",
    "wof:placetype":"locality"
},
  "geometry": {"coordinates":[98.12923000000001,34.79677],"type":"Point"}
}