{
  "type": "Feature",
  "properties": {
    "gn:admin1_code":"21.0",
    "gn:asciiname":"Zhenshuo Sandui",
    "gn:country_code":"CN",
    "gn:dem":1101,
    "gn:feature_class":"P",
    "gn:feature_code":"PPLF",
    "gn:name":"Zhenshuo Sandui",
    "gn:population":0,
    "gn:timezone":"Asia/Shanghai",
    "iso:country":"CN",
    "name:zho_x_preferred":[
        "\u9547\u6714\u4e09\u961f"
    ],
    "wof:name":"Zhenshuo Sandui",
    "wof:placetype":"locality"
},
  "geometry": {"coordinates":[106.256,38.8192],"type":"Point"}
}