{
  "type": "Feature",
  "properties": {
    "gn:admin1_code":"8.0",
    "gn:asciiname":"Houwupaisan",
    "gn:country_code":"CN",
    "gn:dem":199,
    "gn:feature_class":"P",
    "gn:feature_code":"PPL",
    "gn:name":"Houwupaisan",
    "gn:population":0,
    "gn:timezone":"Asia/Shanghai",
    "iso:country":"CN",
    "name:zho_x_preferred":[
        "\u540e\u4e94\u6392\u4e09"
    ],
    "wof:name":"Houwupaisan",
    "wof:placetype":"locality"
},
  "geometry": {"coordinates":[125.85138000000001,46.94996],"type":"Point"}
}