{
  "type": "Feature",
  "properties": {
    "gn:admin1_code":"26.0",
    "gn:asciiname":"Tunlicun",
    "gn:country_code":"CN",
    "gn:dem":727,
    "gn:feature_class":"P",
    "gn:feature_code":"PPL",
    "gn:name":"Tunlicun",
    "gn:population":0,
    "gn:timezone":"Asia/Shanghai",
    "iso:country":"CN",
    "name:zho_x_preferred":[
        "\u5c6f\u91cc\u6751"
    ],
    "wof:name":"Tunlicun",
    "wof:placetype":"locality"
},
  "geometry": {"coordinates":[108.88567999999999,34.82056],"type":"Point"}
}