{
  "type": "Feature",
  "properties": {
    "gn:admin1_code":"32.0",
    "gn:asciiname":"Shisunping",
    "gn:country_code":"CN",
    "gn:dem":955,
    "gn:feature_class":"P",
    "gn:feature_code":"PPL",
    "gn:name":"Shisunping",
    "gn:population":0,
    "gn:timezone":"Asia/Shanghai",
    "iso:country":"CN",
    "name:zho_x_preferred":[
        "\u77f3\u7b0b\u576a"
    ],
    "wof:name":"Shisunping",
    "wof:placetype":"locality"
},
  "geometry": {"coordinates":[107.93000000000001,31.9213],"type":"Point"}
}