{
  "type": "Feature",
  "properties": {
    "gn:admin1_code":"10.0",
    "gn:asciiname":"Weibo",
    "gn:cc2":"CN",
    "gn:country_code":"CN",
    "gn:dem":40,
    "gn:feature_class":"P",
    "gn:feature_code":"PPL",
    "gn:name":"Weibo",
    "gn:population":0,
    "gn:timezone":"Asia/Shanghai",
    "iso:country":"CN",
    "name:deu_x_preferred":[
        "Weibo"
    ],
    "name:fin_x_preferred":[
        "Weibo"
    ],
    "name:kor_x_preferred":[
        "\uc6e8\uc774\ubcf4"
    ],
    "name:und_x_variant":[
        "Veybochzhen\u2019",
        "Wei-po",
        "Wei-po-chen"
    ],
    "wof:name":"Weibo",
    "wof:placetype":"locality"
},
  "geometry": {"coordinates":[115.17222,38.02528],"type":"Point"}
}