{
  "type": "Feature",
  "properties": {
    "gn:admin1_code":"12",
    "gn:asciiname":"Longgang",
    "gn:country_code":"CN",
    "gn:dem":38,
    "gn:feature_class":"P",
    "gn:feature_code":"PPLA4",
    "gn:name":"Longgang",
    "gn:population":0,
    "gn:timezone":"Asia/Shanghai",
    "iso:country":"CN",
    "name:ceb_x_preferred":[
        "Longgang"
    ],
    "name:deu_x_preferred":[
        "Longgang"
    ],
    "name:fra_x_preferred":[
        "Longgang"
    ],
    "name:kor_x_preferred":[
        "\ub8fd\uac15\uad6c"
    ],
    "name:mlg_x_preferred":[
        "Longgang"
    ],
    "name:nor_x_preferred":[
        "Longgang"
    ],
    "name:pol_x_preferred":[
        "Longgang"
    ],
    "name:und_x_variant":[
        "Lung-kang",
        "Longgang",
        "\u9f99\u6e2f",
        "Longgang Zhen",
        "\u9f99\u6e2f\u9547"
    ],
    "wof:name":"Longgang",
    "wof:placetype":"locality"
},
  "geometry": {"coordinates":[114.95028000000001,29.62558],"type":"Point"}
}