{
  "type": "Feature",
  "properties": {
    "gn:admin1_code":"5.0",
    "gn:asciiname":"Houyinjiatun",
    "gn:country_code":"CN",
    "gn:dem":144,
    "gn:feature_class":"P",
    "gn:feature_code":"PPL",
    "gn:name":"Houyinjiatun",
    "gn:population":0,
    "gn:timezone":"Asia/Shanghai",
    "iso:country":"CN",
    "name:zho_x_preferred":[
        "\u540e\u6bb7\u5bb6\u5c6f"
    ],
    "wof:name":"Houyinjiatun",
    "wof:placetype":"locality"
},
  "geometry": {"coordinates":[123.09748999999999,45.28313],"type":"Point"}
}