{
  "type": "Feature",
  "properties": {
    "gn:admin1_code":"14.0",
    "gn:asciiname":"Meiba Ercun",
    "gn:country_code":"CN",
    "gn:dem":4761,
    "gn:feature_class":"P",
    "gn:feature_code":"PPL",
    "gn:name":"Meiba Ercun",
    "gn:population":0,
    "gn:timezone":"Asia/Urumqi",
    "iso:country":"CN",
    "name:zho_x_preferred":[
        "\u7f8e\u5df4\u5c14\u6751"
    ],
    "wof:name":"Meiba Ercun",
    "wof:placetype":"locality"
},
  "geometry": {"coordinates":[92.40295999999999,30.6472],"type":"Point"}
}