{
  "type": "Feature",
  "properties": {
    "gn:admin1_code":"26.0",
    "gn:asciiname":"Baiguoshu'ao",
    "gn:country_code":"CN",
    "gn:dem":1096,
    "gn:feature_class":"P",
    "gn:feature_code":"PPL",
    "gn:name":"Baiguoshu\u2019ao",
    "gn:population":0,
    "gn:timezone":"Asia/Shanghai",
    "iso:country":"CN",
    "name:und_x_variant":[
        "Baiguoshu\u2019ao"
    ],
    "name:zho_x_preferred":[
        "\u767d\u679c\u6811\u51f9"
    ],
    "wof:name":"Baiguoshu'ao",
    "wof:placetype":"locality"
},
  "geometry": {"coordinates":[110.70515,33.29685],"type":"Point"}
}