{
  "type": "Feature",
  "properties": {
    "gn:admin1_code":"24.0",
    "gn:asciiname":"Xizhangjiagou",
    "gn:country_code":"CN",
    "gn:dem":1776,
    "gn:feature_class":"P",
    "gn:feature_code":"PPL",
    "gn:name":"Xizhangjiagou",
    "gn:population":0,
    "gn:timezone":"Asia/Shanghai",
    "iso:country":"CN",
    "name:zho_x_preferred":[
        "\u897f\u5f20\u5bb6\u6c9f"
    ],
    "wof:name":"Xizhangjiagou",
    "wof:placetype":"locality"
},
  "geometry": {"coordinates":[112.20780000000001,38.95668],"type":"Point"}
}