{
  "type": "Feature",
  "properties": {
    "gn:admin1_code":"18",
    "gn:asciiname":"Moujiawo",
    "gn:country_code":"CN",
    "gn:dem":942,
    "gn:feature_class":"P",
    "gn:feature_code":"PPL",
    "gn:name":"Moujiawo",
    "gn:population":0,
    "gn:timezone":"Asia/Shanghai",
    "iso:country":"CN",
    "name:zho_x_preferred":[
        "\u725f\u5bb6\u7a9d"
    ],
    "wof:name":"Moujiawo",
    "wof:placetype":"locality"
},
  "geometry": {"coordinates":[107.40000000000001,27.5808],"type":"Point"}
}