{
  "type": "Feature",
  "properties": {
    "gn:admin1_code":"3.0",
    "gn:asciiname":"Shangkengshui",
    "gn:country_code":"CN",
    "gn:dem":113,
    "gn:feature_class":"P",
    "gn:feature_code":"PPL",
    "gn:name":"Shangkengshui",
    "gn:population":0,
    "gn:timezone":"Asia/Shanghai",
    "iso:country":"CN",
    "name:und_x_variant":[
        "\u4e0a\u5751\u6c34"
    ],
    "wof:name":"Shangkengshui",
    "wof:placetype":"locality"
},
  "geometry": {"coordinates":[114.41403,27.74368],"type":"Point"}
}