{
  "type": "Feature",
  "properties": {
    "gn:admin1_code":"05",
    "gn:asciiname":"Caojiatun",
    "gn:country_code":"CN",
    "gn:dem":230,
    "gn:feature_class":"P",
    "gn:feature_code":"PPL",
    "gn:name":"Caojiatun",
    "gn:population":0,
    "gn:timezone":"Asia/Shanghai",
    "iso:country":"CN",
    "wof:name":"Caojiatun",
    "wof:placetype":"locality"
},
  "geometry": {"coordinates":[125.24556,43.51028],"type":"Point"}
}