{
  "type": "Feature",
  "properties": {
    "gn:admin1_code":"4.0",
    "gn:asciiname":"Huajiagang",
    "gn:country_code":"CN",
    "gn:dem":51,
    "gn:feature_class":"P",
    "gn:feature_code":"PPL",
    "gn:name":"Huajiagang",
    "gn:population":0,
    "gn:timezone":"Asia/Shanghai",
    "iso:country":"CN",
    "name:zho_x_preferred":[
        "\u82b1\u5bb6\u5c97"
    ],
    "wof:name":"Huajiagang",
    "wof:placetype":"locality"
},
  "geometry": {"coordinates":[118.51779999999999,32.9106],"type":"Point"}
}