{
  "type": "Feature",
  "properties": {
    "gn:admin1_code":"30.0",
    "gn:asciiname":"Paibiancun",
    "gn:country_code":"CN",
    "gn:dem":21,
    "gn:feature_class":"P",
    "gn:feature_code":"PPL",
    "gn:name":"Paibiancun",
    "gn:population":0,
    "gn:timezone":"Asia/Shanghai",
    "iso:country":"CN",
    "name:zho_x_preferred":[
        "\u724c\u8fb9\u6751"
    ],
    "wof:name":"Paibiancun",
    "wof:placetype":"locality"
},
  "geometry": {"coordinates":[116.39379,23.61516],"type":"Point"}
}