{
  "type": "Feature",
  "properties": {
    "gn:admin1_code":"29.0",
    "gn:asciiname":"Heisonglin",
    "gn:country_code":"CN",
    "gn:dem":1970,
    "gn:feature_class":"P",
    "gn:feature_code":"PPL",
    "gn:name":"Heisonglin",
    "gn:population":0,
    "gn:timezone":"Asia/Shanghai",
    "iso:country":"CN",
    "name:zho_x_preferred":[
        "\u9ed1\u677e\u6797"
    ],
    "wof:name":"Heisonglin",
    "wof:placetype":"locality"
},
  "geometry": {"coordinates":[104.101,26.091],"type":"Point"}
}