{
  "type": "Feature",
  "properties": {
    "gn:admin1_code":"9.0",
    "gn:asciiname":"Heishangou",
    "gn:country_code":"CN",
    "gn:dem":672,
    "gn:feature_class":"P",
    "gn:feature_code":"PPL",
    "gn:name":"Heishangou",
    "gn:population":0,
    "gn:timezone":"Asia/Shanghai",
    "iso:country":"CN",
    "name:zho_x_preferred":[
        "\u9ed1\u5c71\u6c9f"
    ],
    "wof:name":"Heishangou",
    "wof:placetype":"locality"
},
  "geometry": {"coordinates":[111.4973,34.57996],"type":"Point"}
}