{
  "type": "Feature",
  "properties": {
    "gn:admin1_code":"14.0",
    "gn:asciiname":"Toding",
    "gn:country_code":"CN",
    "gn:dem":3729,
    "gn:feature_class":"P",
    "gn:feature_code":"PPLA3",
    "gn:name":"Toding",
    "gn:population":0,
    "gn:timezone":"Asia/Shanghai",
    "iso:country":"CN",
    "name:bod_x_preferred":[
        "Toding"
    ],
    "name:und_x_variant":[
        "Cha-ta",
        "Totling",
        "Zanda",
        "Tuling",
        "Ta-ting",
        "T\u2019o-lin-ma-ssu",
        "T\u2019o-lin",
        "Tolingmath",
        "T\u2019o-t\u2019e-lin-ko-ma",
        "Totling-gompa",
        "Toling",
        "Tuolin Juweihui"
    ],
    "name:zho_x_preferred":[
        "Tuolin"
    ],
    "name:zho_x_variant":[
        "\u6258\u6797",
        "Zhada Xian",
        "\u672d\u8fbe\u53bf",
        "\u6258\u6797\u5c45\u59d4\u4f1a"
    ],
    "wof:name":"Toding",
    "wof:placetype":"locality"
},
  "geometry": {"coordinates":[79.79803000000003,31.48056],"type":"Point"}
}