{
  "type": "Feature",
  "properties": {
    "gn:admin1_code":"29.0",
    "gn:asciiname":"Ludi",
    "gn:country_code":"CN",
    "gn:dem":1521,
    "gn:feature_class":"P",
    "gn:feature_code":"PPL",
    "gn:name":"L\u00fcdi",
    "gn:population":0,
    "gn:timezone":"Asia/Shanghai",
    "iso:country":"CN",
    "name:und_x_variant":[
        "L\u00fcdi"
    ],
    "name:zho_x_preferred":[
        "\u5415\u5730"
    ],
    "wof:name":"Ludi",
    "wof:placetype":"locality"
},
  "geometry": {"coordinates":[100.886,23.7595],"type":"Point"}
}