{
  "type": "Feature",
  "properties": {
    "gn:admin1_code":"30.0",
    "gn:asciiname":"Nantangli",
    "gn:country_code":"CN",
    "gn:dem":9,
    "gn:feature_class":"P",
    "gn:feature_code":"PPL",
    "gn:name":"Nantangli",
    "gn:population":0,
    "gn:timezone":"Asia/Shanghai",
    "iso:country":"CN",
    "name:zho_x_preferred":[
        "\u5357\u5858\u91cc"
    ],
    "wof:name":"Nantangli",
    "wof:placetype":"locality"
},
  "geometry": {"coordinates":[112.70708,22.4825],"type":"Point"}
}