{
  "type": "Feature",
  "properties": {
    "gn:admin1_code":"18.0",
    "gn:asciiname":"Huoshi",
    "gn:country_code":"CN",
    "gn:dem":994,
    "gn:feature_class":"P",
    "gn:feature_code":"PPL",
    "gn:name":"Huoshi",
    "gn:population":0,
    "gn:timezone":"Asia/Shanghai",
    "iso:country":"CN",
    "name:zho_x_preferred":[
        "\u706b\u77f3"
    ],
    "wof:name":"Huoshi",
    "wof:placetype":"locality"
},
  "geometry": {"coordinates":[106.491,28.0771],"type":"Point"}
}