{
  "type": "Feature",
  "properties": {
    "gn:admin1_code":"11",
    "gn:asciiname":"Nantangwan",
    "gn:country_code":"CN",
    "gn:dem":84,
    "gn:feature_class":"P",
    "gn:feature_code":"PPL",
    "gn:name":"Nantangwan",
    "gn:population":0,
    "gn:timezone":"Asia/Shanghai",
    "iso:country":"CN",
    "name:zho_x_preferred":[
        "\u5357\u5858\u6e7e"
    ],
    "wof:name":"Nantangwan",
    "wof:placetype":"locality"
},
  "geometry": {"coordinates":[112.42093,26.45193],"type":"Point"}
}