{
  "type": "Feature",
  "properties": {
    "gn:admin1_code":"5.0",
    "gn:asciiname":"Yushancun",
    "gn:country_code":"CN",
    "gn:dem":545,
    "gn:feature_class":"P",
    "gn:feature_code":"PPL",
    "gn:name":"Yushancun",
    "gn:population":0,
    "gn:timezone":"Asia/Shanghai",
    "iso:country":"CN",
    "name:zho_x_preferred":[
        "\u88d5\u5c71\u6751"
    ],
    "wof:name":"Yushancun",
    "wof:placetype":"locality"
},
  "geometry": {"coordinates":[128.51519999999999,43.39292],"type":"Point"}
}