{
  "type": "Feature",
  "properties": {
    "gn:admin1_code":"1.0",
    "gn:asciiname":"Xianrui",
    "gn:country_code":"CN",
    "gn:dem":157,
    "gn:feature_class":"P",
    "gn:feature_code":"PPL",
    "gn:name":"Xianrui",
    "gn:population":0,
    "gn:timezone":"Asia/Shanghai",
    "iso:country":"CN",
    "name:zho_x_preferred":[
        "\u5f26\u745e"
    ],
    "wof:name":"Xianrui",
    "wof:placetype":"locality"
},
  "geometry": {"coordinates":[118.14953,30.30209],"type":"Point"}
}