{
  "type": "Feature",
  "properties": {
    "gn:admin1_code":"3.0",
    "gn:asciiname":"Huwu",
    "gn:country_code":"CN",
    "gn:dem":419,
    "gn:feature_class":"P",
    "gn:feature_code":"PPL",
    "gn:name":"Huwu",
    "gn:population":0,
    "gn:timezone":"Asia/Shanghai",
    "iso:country":"CN",
    "name:und_x_variant":[
        "\u80e1\u5c4b"
    ],
    "wof:name":"Huwu",
    "wof:placetype":"locality"
},
  "geometry": {"coordinates":[115.58969999999999,25.05534],"type":"Point"}
}