{
  "type": "Feature",
  "properties": {
    "gn:admin1_code":"24.0",
    "gn:asciiname":"Huzhong",
    "gn:country_code":"CN",
    "gn:dem":460,
    "gn:feature_class":"P",
    "gn:feature_code":"PPL",
    "gn:name":"Huzhong",
    "gn:population":0,
    "gn:timezone":"Asia/Shanghai",
    "iso:country":"CN",
    "name:und_x_variant":[
        "\u659b\u585a"
    ],
    "wof:name":"Huzhong",
    "wof:placetype":"locality"
},
  "geometry": {"coordinates":[111.48386000000001,35.97883],"type":"Point"}
}