{
  "type": "Feature",
  "properties": {
    "gn:admin1_code":"14.0",
    "gn:asciiname":"Cexia",
    "gn:country_code":"CN",
    "gn:dem":3886,
    "gn:feature_class":"P",
    "gn:feature_code":"PPL",
    "gn:name":"Cexia",
    "gn:population":0,
    "gn:timezone":"Asia/Urumqi",
    "iso:country":"CN",
    "name:zho_x_preferred":[
        "\u6d4b\u8f96"
    ],
    "wof:name":"Cexia",
    "wof:placetype":"locality"
},
  "geometry": {"coordinates":[96.43223,29.45881],"type":"Point"}
}