{
  "type": "Feature",
  "properties": {
    "gn:admin1_code":"29.0",
    "gn:asciiname":"Xianggang",
    "gn:country_code":"CN",
    "gn:dem":807,
    "gn:feature_class":"P",
    "gn:feature_code":"PPL",
    "gn:name":"Xianggang",
    "gn:population":0,
    "gn:timezone":"Asia/Shanghai",
    "iso:country":"CN",
    "name:zho_x_preferred":[
        "\u9879\u5c97"
    ],
    "wof:name":"Xianggang",
    "wof:placetype":"locality"
},
  "geometry": {"coordinates":[97.7501,24.5285],"type":"Point"}
}