{
  "type": "Feature",
  "properties": {
    "gn:admin1_code":"18",
    "gn:asciiname":"Xinming",
    "gn:country_code":"CN",
    "gn:dem":872,
    "gn:feature_class":"P",
    "gn:feature_code":"PPL",
    "gn:name":"Xinming",
    "gn:population":0,
    "gn:timezone":"Asia/Shanghai",
    "iso:country":"CN",
    "name:zho_x_preferred":[
        "\u65b0\u660e"
    ],
    "wof:name":"Xinming",
    "wof:placetype":"locality"
},
  "geometry": {"coordinates":[107.48099999999999,29.0188],"type":"Point"}
}