{
  "type": "Feature",
  "properties": {
    "gn:admin1_code":"24.0",
    "gn:asciiname":"Yixieta",
    "gn:country_code":"CN",
    "gn:dem":1036,
    "gn:feature_class":"P",
    "gn:feature_code":"PPL",
    "gn:name":"Yixieta",
    "gn:population":0,
    "gn:timezone":"Asia/Shanghai",
    "iso:country":"CN",
    "name:zho_x_preferred":[
        "\u4f9d\u8c22\u5854"
    ],
    "wof:name":"Yixieta",
    "wof:placetype":"locality"
},
  "geometry": {"coordinates":[111.03061,38.71746],"type":"Point"}
}