{
  "type": "Feature",
  "properties": {
    "gn:admin1_code":"18",
    "gn:asciiname":"Tongjiazhai",
    "gn:country_code":"CN",
    "gn:dem":1085,
    "gn:feature_class":"P",
    "gn:feature_code":"PPL",
    "gn:name":"Tongjiazhai",
    "gn:population":0,
    "gn:timezone":"Asia/Shanghai",
    "iso:country":"CN",
    "name:zho_x_preferred":[
        "\u7ae5\u5bb6\u5be8"
    ],
    "wof:name":"Tongjiazhai",
    "wof:placetype":"locality"
},
  "geometry": {"coordinates":[107.497,27.2676],"type":"Point"}
}