{
  "type": "Feature",
  "properties": {
    "gn:admin1_code":"14.0",
    "gn:asciiname":"Jiabu",
    "gn:country_code":"CN",
    "gn:dem":4668,
    "gn:feature_class":"P",
    "gn:feature_code":"PPL",
    "gn:name":"Jiabu",
    "gn:population":0,
    "gn:timezone":"Asia/Urumqi",
    "iso:country":"CN",
    "name:zho_x_preferred":[
        "\u52a0\u5e03"
    ],
    "wof:name":"Jiabu",
    "wof:placetype":"locality"
},
  "geometry": {"coordinates":[87.0805,28.802],"type":"Point"}
}