{
  "type": "Feature",
  "properties": {
    "gn:admin1_code":"15",
    "gn:asciiname":"Gaoba",
    "gn:country_code":"CN",
    "gn:dem":2225,
    "gn:feature_class":"P",
    "gn:feature_code":"PPL",
    "gn:name":"Gaoba",
    "gn:population":0,
    "gn:timezone":"Asia/Shanghai",
    "iso:country":"CN",
    "wof:name":"Gaoba",
    "wof:placetype":"locality"
},
  "geometry": {"coordinates":[102.31667,37.93333],"type":"Point"}
}