{
  "type": "Feature",
  "properties": {
    "gn:admin1_code":"26.0",
    "gn:asciiname":"SongjiaShan",
    "gn:country_code":"CN",
    "gn:dem":1181,
    "gn:feature_class":"P",
    "gn:feature_code":"PPL",
    "gn:name":"SongjiaShan",
    "gn:population":0,
    "gn:timezone":"Asia/Shanghai",
    "iso:country":"CN",
    "name:zho_x_preferred":[
        "\u5b8b\u5bb6\u5c71"
    ],
    "wof:name":"SongjiaShan",
    "wof:placetype":"locality"
},
  "geometry": {"coordinates":[106.78100000000001,34.43015],"type":"Point"}
}