{
  "type": "Feature",
  "properties": {
    "gn:admin1_code":"26.0",
    "gn:asciiname":"Dachacun",
    "gn:country_code":"CN",
    "gn:dem":1402,
    "gn:feature_class":"P",
    "gn:feature_code":"PPL",
    "gn:name":"Dachacun",
    "gn:population":0,
    "gn:timezone":"Asia/Shanghai",
    "iso:country":"CN",
    "name:zho_x_preferred":[
        "\u5927\u5c94\u6751"
    ],
    "wof:name":"Dachacun",
    "wof:placetype":"locality"
},
  "geometry": {"coordinates":[108.06014999999999,36.82137],"type":"Point"}
}