{
  "type": "Feature",
  "properties": {
    "gn:admin1_code":"19.0",
    "gn:asciiname":"Bijia",
    "gn:country_code":"CN",
    "gn:dem":5,
    "gn:feature_class":"P",
    "gn:feature_code":"PPL",
    "gn:name":"Bijia",
    "gn:population":0,
    "gn:timezone":"Asia/Shanghai",
    "iso:country":"CN",
    "name:und_x_variant":[
        "\u6bd5\u5bb6"
    ],
    "wof:name":"Bijia",
    "wof:placetype":"locality"
},
  "geometry": {"coordinates":[122.44946000000002,40.73874],"type":"Point"}
}