{
  "type": "Feature",
  "properties": {
    "gn:admin1_code":"32.0",
    "gn:asciiname":"Baixiangshu",
    "gn:country_code":"CN",
    "gn:dem":1144,
    "gn:feature_class":"P",
    "gn:feature_code":"PPL",
    "gn:name":"Baixiangshu",
    "gn:population":0,
    "gn:timezone":"Asia/Shanghai",
    "iso:country":"CN",
    "name:zho_x_preferred":[
        "\u67cf\u9999\u6811"
    ],
    "wof:name":"Baixiangshu",
    "wof:placetype":"locality"
},
  "geometry": {"coordinates":[106.295,27.9046],"type":"Point"}
}