{
  "type": "Feature",
  "properties": {
    "gn:admin1_code":"18.0",
    "gn:asciiname":"Jialiao",
    "gn:country_code":"CN",
    "gn:dem":667,
    "gn:feature_class":"P",
    "gn:feature_code":"PPL",
    "gn:name":"Jialiao",
    "gn:population":0,
    "gn:timezone":"Asia/Shanghai",
    "iso:country":"CN",
    "name:zho_x_preferred":[
        "\u7532\u6599"
    ],
    "wof:name":"Jialiao",
    "wof:placetype":"locality"
},
  "geometry": {"coordinates":[108.27800000000001,25.4978],"type":"Point"}
}