{
  "type": "Feature",
  "properties": {
    "gn:admin1_code":"25",
    "gn:asciiname":"Shuilongdong",
    "gn:country_code":"CN",
    "gn:dem":344,
    "gn:feature_class":"P",
    "gn:feature_code":"PPL",
    "gn:name":"Shuilongdong",
    "gn:population":0,
    "gn:timezone":"Asia/Shanghai",
    "iso:country":"CN",
    "name:zho_x_preferred":[
        "\u6c34\u9f99\u6d1e"
    ],
    "wof:name":"Shuilongdong",
    "wof:placetype":"locality"
},
  "geometry": {"coordinates":[117.553,36.5563],"type":"Point"}
}