{
  "type": "Feature",
  "properties": {
    "gn:admin1_code":"22.0",
    "gn:asciiname":"Xifa",
    "gn:country_code":"CN",
    "gn:dem":20,
    "gn:feature_class":"P",
    "gn:feature_code":"PPL",
    "gn:name":"Xifa",
    "gn:population":0,
    "gn:timezone":"Asia/Shanghai",
    "iso:country":"CN",
    "name:zho_x_preferred":[
        "\u897f\u57a1"
    ],
    "wof:name":"Xifa",
    "wof:placetype":"locality"
},
  "geometry": {"coordinates":[116.69083999999999,39.6876],"type":"Point"}
}