{
  "type": "Feature",
  "properties": {
    "gn:admin1_code":"24.0",
    "gn:asciiname":"Xilingjing",
    "gn:cc2":"CN",
    "gn:country_code":"CN",
    "gn:dem":1163,
    "gn:feature_class":"P",
    "gn:feature_code":"PPL",
    "gn:name":"Xilingjing",
    "gn:population":0,
    "gn:timezone":"Asia/Shanghai",
    "iso:country":"CN",
    "name:und_x_variant":[
        "Ling-ching",
        "Hsi-ling-ching",
        "Ling-ching-ts\u2019un",
        "Xilingjing"
    ],
    "wof:name":"Xilingjing",
    "wof:placetype":"locality"
},
  "geometry": {"coordinates":[112.41472,38.13417000000001],"type":"Point"}
}