{
  "type": "Feature",
  "properties": {
    "gn:admin1_code":"33.0",
    "gn:asciiname":"Cizhu",
    "gn:country_code":"CN",
    "gn:dem":266,
    "gn:feature_class":"P",
    "gn:feature_code":"PPL",
    "gn:name":"Cizhu",
    "gn:population":0,
    "gn:timezone":"Asia/Shanghai",
    "iso:country":"CN",
    "name:zho_x_preferred":[
        "\u6148\u7af9"
    ],
    "wof:name":"Cizhu",
    "wof:placetype":"locality"
},
  "geometry": {"coordinates":[106.852,29.4965],"type":"Point"}
}