{
  "type": "Feature",
  "properties": {
    "gn:admin1_code":"24.0",
    "gn:asciiname":"Wangbicun",
    "gn:country_code":"CN",
    "gn:dem":1263,
    "gn:feature_class":"P",
    "gn:feature_code":"PPL",
    "gn:name":"Wangbicun",
    "gn:population":0,
    "gn:timezone":"Asia/Shanghai",
    "iso:country":"CN",
    "name:zho_x_preferred":[
        "\u738b\u58c1\u6751"
    ],
    "wof:name":"Wangbicun",
    "wof:placetype":"locality"
},
  "geometry": {"coordinates":[112.23033999999998,36.64908],"type":"Point"}
}