{
  "type": "Feature",
  "properties": {
    "gn:admin1_code":"10",
    "gn:asciiname":"Luguozhai",
    "gn:country_code":"CN",
    "gn:dem":245,
    "gn:feature_class":"P",
    "gn:feature_code":"PPL",
    "gn:name":"Luguozhai",
    "gn:population":0,
    "gn:timezone":"Asia/Shanghai",
    "iso:country":"CN",
    "name:zho_x_preferred":[
        "\u9e7f\u8fc7\u5be8"
    ],
    "wof:name":"Luguozhai",
    "wof:placetype":"locality"
},
  "geometry": {"coordinates":[118.46306,40.37165],"type":"Point"}
}