{
  "type": "Feature",
  "properties": {
    "gn:admin1_code":"1.0",
    "gn:asciiname":"Huikengcun",
    "gn:country_code":"CN",
    "gn:dem":42,
    "gn:feature_class":"P",
    "gn:feature_code":"PPL",
    "gn:name":"Huikengcun",
    "gn:population":0,
    "gn:timezone":"Asia/Shanghai",
    "iso:country":"CN",
    "name:zho_x_preferred":[
        "\u5fbd\u5751\u6751"
    ],
    "wof:name":"Huikengcun",
    "wof:placetype":"locality"
},
  "geometry": {"coordinates":[117.46903,30.44022],"type":"Point"}
}