{
  "type": "Feature",
  "properties": {
    "gn:admin1_code":"19.0",
    "gn:asciiname":"Tamuban",
    "gn:country_code":"CN",
    "gn:dem":232,
    "gn:feature_class":"P",
    "gn:feature_code":"PPL",
    "gn:name":"Tamuban",
    "gn:population":0,
    "gn:timezone":"Asia/Shanghai",
    "iso:country":"CN",
    "name:zho_x_preferred":[
        "\u4ed6\u6728\u677f"
    ],
    "wof:name":"Tamuban",
    "wof:placetype":"locality"
},
  "geometry": {"coordinates":[121.83199999999999,42.3326],"type":"Point"}
}