{
  "type": "Feature",
  "properties": {
    "gn:admin1_code":"30",
    "gn:asciiname":"Datangwei",
    "gn:country_code":"CN",
    "gn:dem":39,
    "gn:feature_class":"P",
    "gn:feature_code":"PPL",
    "gn:name":"Datangwei",
    "gn:population":0,
    "gn:timezone":"Asia/Urumqi",
    "iso:country":"CN",
    "name:zho_x_preferred":[
        "\u5927\u5858\u5c3e"
    ],
    "wof:name":"Datangwei",
    "wof:placetype":"locality"
},
  "geometry": {"coordinates":[110.86512999999999,21.77892],"type":"Point"}
}