{
  "type": "Feature",
  "properties": {
    "gn:admin1_code":"14.0",
    "gn:asciiname":"Ribu",
    "gn:country_code":"CN",
    "gn:dem":3784,
    "gn:feature_class":"P",
    "gn:feature_code":"PPL",
    "gn:name":"Ribu",
    "gn:population":0,
    "gn:timezone":"Asia/Urumqi",
    "iso:country":"CN",
    "name:ind_x_preferred":[
        "Ribu"
    ],
    "name:tur_x_preferred":[
        "Ribu"
    ],
    "name:zho_x_preferred":[
        "\u65e5\u7c3f"
    ],
    "wof:name":"Ribu",
    "wof:placetype":"locality"
},
  "geometry": {"coordinates":[98.36536,31.76188],"type":"Point"}
}