{
  "type": "Feature",
  "properties": {
    "gn:admin1_code":"19.0",
    "gn:asciiname":"Jiangjiatun",
    "gn:country_code":"CN",
    "gn:dem":43,
    "gn:feature_class":"P",
    "gn:feature_code":"PPL",
    "gn:name":"Jiangjiatun",
    "gn:population":0,
    "gn:timezone":"Asia/Shanghai",
    "iso:country":"CN",
    "name:und_x_variant":[
        "\u59dc\u5bb6\u5c6f"
    ],
    "name:zho_x_preferred":[
        "\u59dc\u5bb6\u5c6f"
    ],
    "wof:name":"Jiangjiatun",
    "wof:placetype":"locality"
},
  "geometry": {"coordinates":[121.00288,41.10554000000001],"type":"Point"}
}