{
  "type": "Feature",
  "properties": {
    "gn:admin1_code":"3.0",
    "gn:asciiname":"Yuxi",
    "gn:country_code":"CN",
    "gn:dem":320,
    "gn:feature_class":"P",
    "gn:feature_code":"PPL",
    "gn:name":"Yuxi",
    "gn:population":0,
    "gn:timezone":"Asia/Shanghai",
    "iso:country":"CN",
    "name:zho_x_preferred":[
        "\u6e14\u6eaa"
    ],
    "wof:name":"Yuxi",
    "wof:placetype":"locality"
},
  "geometry": {"coordinates":[115.78700000000001,25.0427],"type":"Point"}
}