{
  "type": "Feature",
  "properties": {
    "gn:admin1_code":"3.0",
    "gn:asciiname":"Yuxi",
    "gn:country_code":"CN",
    "gn:dem":320,
    "gn:feature_class":"P",
    "gn:feature_code":"PPL",
    "gn:name":"Yuxi",
    "gn:population":0,
    "gn:timezone":"Asia/Shanghai",
    "iso:country":"CN",
    "name:ara_x_preferred":[
        "\u064a\u0648\u0634\u0649"
    ],
    "name:aze_x_preferred":[
        "Yuxi"
    ],
    "name:cdo_x_preferred":[
        "Ng\u1e73\u0306k-k\u0103\u0324"
    ],
    "name:ceb_x_preferred":[
        "Yuxi"
    ],
    "name:ces_x_preferred":[
        "J\u00fc-si"
    ],
    "name:cym_x_preferred":[
        "Yuxi"
    ],
    "name:dan_x_preferred":[
        "Yuxi"
    ],
    "name:deu_x_preferred":[
        "Yuxi"
    ],
    "name:est_x_preferred":[
        "Yuxi"
    ],
    "name:eus_x_preferred":[
        "Yuxi"
    ],
    "name:fas_x_preferred":[
        "\u06cc\u0648\u06a9\u0633\u06cc"
    ],
    "name:fin_x_preferred":[
        "Yuxi"
    ],
    "name:fra_x_preferred":[
        "Yuxi"
    ],
    "name:ita_x_preferred":[
        "Yuxi"
    ],
    "name:jpn_x_preferred":[
        "\u7389\u6e13\u5e02"
    ],
    "name:kik_x_preferred":[
        "Yuxi"
    ],
    "name:kor_x_preferred":[
        "\uc704\uc2dc\uc2dc"
    ],
    "name:mlg_x_preferred":[
        "Yuxi"
    ],
    "name:nld_x_preferred":[
        "Yuxi"
    ],
    "name:nno_x_preferred":[
        "Yuxi"
    ],
    "name:nor_x_preferred":[
        "Yuxi"
    ],
    "name:pol_x_preferred":[
        "Yuxi"
    ],
    "name:por_x_preferred":[
        "Yuxi"
    ],
    "name:rus_x_preferred":[
        "\u042e\u0439\u0441\u0438"
    ],
    "name:spa_x_preferred":[
        "Yuxi"
    ],
    "name:swe_x_preferred":[
        "Yuxi"
    ],
    "name:tgl_x_preferred":[
        "Yuxi"
    ],
    "name:tha_x_preferred":[
        "\u0e2d\u0e3a\u0e27\u0e35\u0e49\u0e0b\u0e35"
    ],
    "name:tur_x_preferred":[
        "Yuxi"
    ],
    "name:urd_x_preferred":[
        "\u06cc\u06af\u0632\u06cc"
    ],
    "name:vie_x_preferred":[
        "Ng\u1ecdc Kh\u00ea"
    ],
    "name:war_x_preferred":[
        "Yuxi"
    ],
    "name:zho_x_preferred":[
        "\u6e14\u6eaa"
    ],
    "name:zho_x_variant":[
        "\u7389\u6eaa\u5e02"
    ],
    "wof:name":"Yuxi",
    "wof:placetype":"locality"
},
  "geometry": {"coordinates":[115.78700000000001,25.0427],"type":"Point"}
}