{
  "type": "Feature",
  "properties": {
    "gn:admin1_code":"10",
    "gn:asciiname":"Hugezhuang",
    "gn:cc2":"CN",
    "gn:country_code":"CN",
    "gn:dem":6,
    "gn:feature_class":"P",
    "gn:feature_code":"PPL",
    "gn:name":"Hugezhuang",
    "gn:population":0,
    "gn:timezone":"Asia/Shanghai",
    "iso:country":"CN",
    "name:und_x_variant":[
        "Huko",
        "Hu-ko-chuang-chen",
        "Hu-ko-chuang",
        "Hugezhuang"
    ],
    "wof:name":"Hugezhuang",
    "wof:placetype":"locality"
},
  "geometry": {"coordinates":[118.65000000000001,39.38333],"type":"Point"}
}