{
  "type": "Feature",
  "properties": {
    "gn:admin1_code":"21.0",
    "gn:asciiname":"Suojiacha",
    "gn:country_code":"CN",
    "gn:dem":1638,
    "gn:feature_class":"P",
    "gn:feature_code":"PPL",
    "gn:name":"Suojiacha",
    "gn:population":0,
    "gn:timezone":"Asia/Shanghai",
    "iso:country":"CN",
    "name:und_x_variant":[
        "\u9501\u5bb6\u5c94"
    ],
    "name:zho_x_preferred":[
        "\u9501\u5bb6\u5c94"
    ],
    "wof:name":"Suojiacha",
    "wof:placetype":"locality"
},
  "geometry": {"coordinates":[106.35980000000001,36.99555],"type":"Point"}
}