{
  "type": "Feature",
  "properties": {
    "gn:admin1_code":"20.0",
    "gn:asciiname":"Chongzihao",
    "gn:country_code":"CN",
    "gn:dem":1672,
    "gn:feature_class":"P",
    "gn:feature_code":"PPL",
    "gn:name":"Chongzihao",
    "gn:population":0,
    "gn:timezone":"Asia/Shanghai",
    "iso:country":"CN",
    "name:und_x_variant":[
        "\u5145\u5b57\u53f7"
    ],
    "wof:name":"Chongzihao",
    "wof:placetype":"locality"
},
  "geometry": {"coordinates":[111.43170000000001,41.19331],"type":"Point"}
}