{
  "type": "Feature",
  "properties": {
    "gn:admin1_code":"16",
    "gn:asciiname":"Longtanjiao",
    "gn:country_code":"CN",
    "gn:dem":161,
    "gn:feature_class":"P",
    "gn:feature_code":"PPL",
    "gn:name":"Longtanjiao",
    "gn:population":0,
    "gn:timezone":"Asia/Shanghai",
    "iso:country":"CN",
    "name:zho_x_preferred":[
        "\u9f99\u6ee9\u89d2"
    ],
    "wof:name":"Longtanjiao",
    "wof:placetype":"locality"
},
  "geometry": {"coordinates":[109.59399999999999,25.766],"type":"Point"}
}