{
  "type": "Feature",
  "properties": {
    "gn:admin1_code":"14.0",
    "gn:asciiname":"Dagengcun",
    "gn:country_code":"CN",
    "gn:dem":4548,
    "gn:feature_class":"P",
    "gn:feature_code":"PPL",
    "gn:name":"Dagengcun",
    "gn:population":0,
    "gn:timezone":"Asia/Urumqi",
    "iso:country":"CN",
    "name:zho_x_preferred":[
        "\u8fbe\u66f4\u6751"
    ],
    "wof:name":"Dagengcun",
    "wof:placetype":"locality"
},
  "geometry": {"coordinates":[94.85867,30.93306],"type":"Point"}
}