{
  "type": "Feature",
  "properties": {
    "gn:admin1_code":"18",
    "gn:asciiname":"Shaba",
    "gn:country_code":"CN",
    "gn:dem":1391,
    "gn:feature_class":"P",
    "gn:feature_code":"PPL",
    "gn:name":"Shaba",
    "gn:population":0,
    "gn:timezone":"Asia/Shanghai",
    "iso:country":"CN",
    "name:bar_x_preferred":[
        "Shaba"
    ],
    "name:ceb_x_preferred":[
        "Shaba"
    ],
    "name:deu_x_preferred":[
        "Shaba"
    ],
    "name:ita_x_preferred":[
        "Shaba"
    ],
    "name:swe_x_preferred":[
        "Shaba"
    ],
    "name:zho_x_preferred":[
        "\u6c99\u575d"
    ],
    "wof:name":"Shaba",
    "wof:placetype":"locality"
},
  "geometry": {"coordinates":[106.949,28.04300000000001],"type":"Point"}
}