{
  "type": "Feature",
  "properties": {
    "gn:admin1_code":"18",
    "gn:asciiname":"Mawangpeng",
    "gn:country_code":"CN",
    "gn:dem":922,
    "gn:feature_class":"P",
    "gn:feature_code":"PPL",
    "gn:name":"Mawangpeng",
    "gn:population":0,
    "gn:timezone":"Asia/Shanghai",
    "iso:country":"CN",
    "name:zho_x_preferred":[
        "\u9a6c\u738b\u68da"
    ],
    "wof:name":"Mawangpeng",
    "wof:placetype":"locality"
},
  "geometry": {"coordinates":[106.67,27.2124],"type":"Point"}
}