{
  "type": "Feature",
  "properties": {
    "gn:admin1_code":"30.0",
    "gn:asciiname":"Fuguangcun",
    "gn:country_code":"CN",
    "gn:dem":165,
    "gn:feature_class":"P",
    "gn:feature_code":"PPL",
    "gn:name":"Fuguangcun",
    "gn:population":0,
    "gn:timezone":"Asia/Shanghai",
    "iso:country":"CN",
    "name:zho_x_preferred":[
        "\u798f\u5149\u6751"
    ],
    "wof:name":"Fuguangcun",
    "wof:placetype":"locality"
},
  "geometry": {"coordinates":[116.90125,24.27189],"type":"Point"}
}