{
  "type": "Feature",
  "properties": {
    "gn:admin1_code":"26.0",
    "gn:asciiname":"Niuhuling",
    "gn:country_code":"CN",
    "gn:dem":1309,
    "gn:feature_class":"P",
    "gn:feature_code":"PPL",
    "gn:name":"Niuhuling",
    "gn:population":0,
    "gn:timezone":"Asia/Shanghai",
    "iso:country":"CN",
    "name:zho_x_preferred":[
        "\u725b\u864e\u5cad"
    ],
    "wof:name":"Niuhuling",
    "wof:placetype":"locality"
},
  "geometry": {"coordinates":[109.22512999999999,35.31315],"type":"Point"}
}