{
  "type": "Feature",
  "properties": {
    "gn:admin1_code":"30",
    "gn:asciiname":"Haiwei",
    "gn:country_code":"CN",
    "gn:dem":3,
    "gn:feature_class":"P",
    "gn:feature_code":"PPL",
    "gn:name":"Haiwei",
    "gn:population":0,
    "gn:timezone":"Asia/Urumqi",
    "iso:country":"CN",
    "name:und_x_variant":[
        "\u6d77\u5c3e",
        "Haiwei"
    ],
    "wof:name":"Haiwei",
    "wof:placetype":"locality"
},
  "geometry": {"coordinates":[109.94774,20.44252],"type":"Point"}
}