{
  "type": "Feature",
  "properties": {
    "gn:admin1_code":"29.0",
    "gn:asciiname":"Shiping",
    "gn:country_code":"CN",
    "gn:dem":1650,
    "gn:feature_class":"P",
    "gn:feature_code":"PPL",
    "gn:name":"Shiping",
    "gn:population":0,
    "gn:timezone":"Asia/Shanghai",
    "iso:country":"CN",
    "name:und_x_variant":[
        "\u77f3\u576a"
    ],
    "wof:name":"Shiping",
    "wof:placetype":"locality"
},
  "geometry": {"coordinates":[103.93926,28.26802],"type":"Point"}
}