{
  "type": "Feature",
  "properties": {
    "gn:admin1_code":"9.0",
    "gn:asciiname":"Ligang",
    "gn:country_code":"CN",
    "gn:dem":109,
    "gn:feature_class":"P",
    "gn:feature_code":"PPL",
    "gn:name":"Ligang",
    "gn:population":0,
    "gn:timezone":"Asia/Shanghai",
    "iso:country":"CN",
    "name:hak_x_preferred":[
        "L\u00ee-k\u00f3ng-hi\u00f4ng"
    ],
    "name:jpn_x_preferred":[
        "\u91cc\u6e2f\u90f7"
    ],
    "name:kor_x_preferred":[
        "\ub9ac\uac15\ud5a5"
    ],
    "name:vie_x_preferred":[
        "L\u00ed C\u1ea3ng"
    ],
    "name:zho_x_preferred":[
        "\u674e\u5c97"
    ],
    "name:zho_x_variant":[
        "\u91cc\u6e2f\u9109"
    ],
    "wof:name":"Ligang",
    "wof:placetype":"locality"
},
  "geometry": {"coordinates":[113.93507,32.65932],"type":"Point"}
}