{
  "type": "Feature",
  "properties": {
    "gn:admin1_code":"22.0",
    "gn:asciiname":"Dayucun",
    "gn:country_code":"CN",
    "gn:dem":169,
    "gn:feature_class":"P",
    "gn:feature_code":"PPL",
    "gn:name":"Dayucun",
    "gn:population":0,
    "gn:timezone":"Asia/Shanghai",
    "iso:country":"CN",
    "name:zho_x_preferred":[
        "\u8fbe\u5cea\u6751"
    ],
    "wof:name":"Dayucun",
    "wof:placetype":"locality"
},
  "geometry": {"coordinates":[117.04639,40.39579000000001],"type":"Point"}
}