{
  "type": "Feature",
  "properties": {
    "gn:admin1_code":"26.0",
    "gn:asciiname":"Luopangyuan",
    "gn:country_code":"CN",
    "gn:dem":1746,
    "gn:feature_class":"P",
    "gn:feature_code":"PPL",
    "gn:name":"Luopangyuan",
    "gn:population":0,
    "gn:timezone":"Asia/Shanghai",
    "iso:country":"CN",
    "name:und_x_variant":[
        "\u7f57\u5e9e\u586c"
    ],
    "wof:name":"Luopangyuan",
    "wof:placetype":"locality"
},
  "geometry": {"coordinates":[107.43949000000001,36.93926],"type":"Point"}
}