{
  "type": "Feature",
  "properties": {
    "gn:admin1_code":"18.0",
    "gn:asciiname":"Panshangou",
    "gn:country_code":"CN",
    "gn:dem":940,
    "gn:feature_class":"P",
    "gn:feature_code":"PPL",
    "gn:name":"Panshangou",
    "gn:population":0,
    "gn:timezone":"Asia/Shanghai",
    "iso:country":"CN",
    "name:zho_x_preferred":[
        "\u76d8\u5c71\u6c9f"
    ],
    "wof:name":"Panshangou",
    "wof:placetype":"locality"
},
  "geometry": {"coordinates":[108.541,27.0127],"type":"Point"}
}