{
  "type": "Feature",
  "properties": {
    "gn:admin1_code":"32.0",
    "gn:asciiname":"Panzhihuashu",
    "gn:country_code":"CN",
    "gn:dem":1210,
    "gn:feature_class":"P",
    "gn:feature_code":"PPL",
    "gn:name":"Panzhihuashu",
    "gn:population":0,
    "gn:timezone":"Asia/Shanghai",
    "iso:country":"CN",
    "name:zho_x_preferred":[
        "\u6500\u679d\u82b1\u6811"
    ],
    "wof:name":"Panzhihuashu",
    "wof:placetype":"locality"
},
  "geometry": {"coordinates":[102.06235,26.23231],"type":"Point"}
}