{
  "type": "Feature",
  "properties": {
    "gn:admin1_code":"29.0",
    "gn:asciiname":"Hetaoqing",
    "gn:country_code":"CN",
    "gn:dem":1838,
    "gn:feature_class":"P",
    "gn:feature_code":"PPL",
    "gn:name":"Hetaoqing",
    "gn:population":0,
    "gn:timezone":"Asia/Shanghai",
    "iso:country":"CN",
    "name:zho_x_preferred":[
        "\u6838\u6843\u7b90"
    ],
    "wof:name":"Hetaoqing",
    "wof:placetype":"locality"
},
  "geometry": {"coordinates":[99.2775,24.0816],"type":"Point"}
}