{
  "type": "Feature",
  "properties": {
    "gn:admin1_code":"19.0",
    "gn:asciiname":"Donghanjiacun",
    "gn:country_code":"CN",
    "gn:dem":324,
    "gn:feature_class":"P",
    "gn:feature_code":"PPL",
    "gn:name":"Donghanjiacun",
    "gn:population":0,
    "gn:timezone":"Asia/Shanghai",
    "iso:country":"CN",
    "name:zho_x_preferred":[
        "\u4e1c\u97e9\u5bb6\u6751"
    ],
    "wof:name":"Donghanjiacun",
    "wof:placetype":"locality"
},
  "geometry": {"coordinates":[124.55038999999999,41.70508],"type":"Point"}
}