{
  "type": "Feature",
  "properties": {
    "gn:admin1_code":"2.0",
    "gn:asciiname":"Dawangqiao",
    "gn:country_code":"CN",
    "gn:dem":5,
    "gn:feature_class":"P",
    "gn:feature_code":"PPL",
    "gn:name":"Dawangqiao",
    "gn:population":0,
    "gn:timezone":"Asia/Shanghai",
    "iso:country":"CN",
    "name:und_x_variant":[
        "\u5927\u738b\u6865"
    ],
    "wof:name":"Dawangqiao",
    "wof:placetype":"locality"
},
  "geometry": {"coordinates":[120.91003000000001,30.42565],"type":"Point"}
}