{
  "type": "Feature",
  "properties": {
    "gn:admin1_code":"4.0",
    "gn:asciiname":"Xichang",
    "gn:country_code":"CN",
    "gn:dem":3,
    "gn:feature_class":"P",
    "gn:feature_code":"PPL",
    "gn:name":"Xichang",
    "gn:population":0,
    "gn:timezone":"Asia/Shanghai",
    "iso:country":"CN",
    "name:und_x_variant":[
        "\u897f\u573a"
    ],
    "name:zho_x_preferred":[
        "\u897f\u573a"
    ],
    "wof:name":"Xichang",
    "wof:placetype":"locality"
},
  "geometry": {"coordinates":[120.91306000000002,31.30805],"type":"Point"}
}