{
  "type": "Feature",
  "properties": {
    "gn:admin1_code":"4.0",
    "gn:asciiname":"Xichang",
    "gn:country_code":"CN",
    "gn:dem":3,
    "gn:feature_class":"P",
    "gn:feature_code":"PPL",
    "gn:name":"Xichang",
    "gn:population":0,
    "gn:timezone":"Asia/Shanghai",
    "iso:country":"CN",
    "name:ara_x_preferred":[
        "\u0634\u064a\u062a\u0634\u0627\u0646\u063a"
    ],
    "name:ceb_x_preferred":[
        "Xichang"
    ],
    "name:ces_x_preferred":[
        "Si-\u010dchang"
    ],
    "name:dan_x_preferred":[
        "Xichang"
    ],
    "name:deu_x_preferred":[
        "Xichang"
    ],
    "name:fas_x_preferred":[
        "\u0634\u06cc\u0686\u0627\u0646\u06af"
    ],
    "name:fin_x_preferred":[
        "Xichang"
    ],
    "name:fra_x_preferred":[
        "Xichang"
    ],
    "name:hak_x_preferred":[
        "S\u00ee-chh\u00f4ng-s\u1e73"
    ],
    "name:heb_x_preferred":[
        "\u05e7\u05e1\u05d9\u05e6'\u05d0\u05e0\u05d2"
    ],
    "name:hun_x_preferred":[
        "Hszicsang"
    ],
    "name:ind_x_preferred":[
        "Xichang"
    ],
    "name:ita_x_preferred":[
        "Xichang"
    ],
    "name:jpn_x_preferred":[
        "\u897f\u660c\u5e02"
    ],
    "name:kik_x_preferred":[
        "Xichang"
    ],
    "name:kor_x_preferred":[
        "\uc2dc\ucc3d\uc2dc"
    ],
    "name:mlg_x_preferred":[
        "Xichang"
    ],
    "name:nld_x_preferred":[
        "Xichang"
    ],
    "name:nor_x_preferred":[
        "Xichang"
    ],
    "name:pol_x_preferred":[
        "Xichang"
    ],
    "name:por_x_preferred":[
        "Xichang"
    ],
    "name:ron_x_preferred":[
        "Xichang"
    ],
    "name:rus_x_preferred":[
        "\u0421\u0438\u0447\u0430\u043d"
    ],
    "name:spa_x_preferred":[
        "Xichang"
    ],
    "name:swe_x_preferred":[
        "Xichang"
    ],
    "name:urd_x_preferred":[
        "\u0634\u06cc\u06a9\u0686\u0627\u0646\u06af"
    ],
    "name:vie_x_preferred":[
        "T\u00e2y X\u01b0\u01a1ng"
    ],
    "name:war_x_preferred":[
        "Xichang"
    ],
    "name:zho_x_preferred":[
        "\u897f\u573a"
    ],
    "name:zho_x_variant":[
        "\u897f\u660c\u5e02"
    ],
    "wof:name":"Xichang",
    "wof:placetype":"locality"
},
  "geometry": {"coordinates":[120.91306,31.30805],"type":"Point"}
}