{
  "type": "Feature",
  "properties": {
    "gn:admin1_code":"11.0",
    "gn:asciiname":"Laopushang",
    "gn:country_code":"CN",
    "gn:dem":370,
    "gn:feature_class":"P",
    "gn:feature_code":"PPL",
    "gn:name":"Laopushang",
    "gn:population":0,
    "gn:timezone":"Asia/Shanghai",
    "iso:country":"CN",
    "name:zho_x_preferred":[
        "\u8001\u94fa\u4e0a"
    ],
    "wof:name":"Laopushang",
    "wof:placetype":"locality"
},
  "geometry": {"coordinates":[110.9931,26.76348],"type":"Point"}
}