{
  "type": "Feature",
  "properties": {
    "gn:admin1_code":"25",
    "gn:asciiname":"Qianxunfeng",
    "gn:country_code":"CN",
    "gn:dem":114,
    "gn:feature_class":"P",
    "gn:feature_code":"PPL",
    "gn:name":"Qianxunfeng",
    "gn:population":0,
    "gn:timezone":"Asia/Shanghai",
    "iso:country":"CN",
    "name:und_x_variant":[
        "\u524d\u900a\u5cf0"
    ],
    "wof:name":"Qianxunfeng",
    "wof:placetype":"locality"
},
  "geometry": {"coordinates":[119.07216,35.87625],"type":"Point"}
}