{
  "type": "Feature",
  "properties": {
    "gn:admin1_code":"29.0",
    "gn:asciiname":"Xishali",
    "gn:country_code":"CN",
    "gn:dem":1459,
    "gn:feature_class":"P",
    "gn:feature_code":"PPL",
    "gn:name":"Xishali",
    "gn:population":0,
    "gn:timezone":"Asia/Shanghai",
    "iso:country":"CN",
    "name:zho_x_preferred":[
        "\u897f\u6c99\u91cc"
    ],
    "wof:name":"Xishali",
    "wof:placetype":"locality"
},
  "geometry": {"coordinates":[104.40000000000001,23.8874],"type":"Point"}
}