{
  "type": "Feature",
  "properties": {
    "gn:admin1_code":"10",
    "gn:asciiname":"Donghua Yugou",
    "gn:country_code":"CN",
    "gn:dem":273,
    "gn:feature_class":"P",
    "gn:feature_code":"PPL",
    "gn:name":"Donghua Yugou",
    "gn:population":0,
    "gn:timezone":"Asia/Shanghai",
    "iso:country":"CN",
    "name:zho_x_preferred":[
        "\u4e1c\u5316\u9c7c\u6c9f"
    ],
    "wof:name":"Donghua Yugou",
    "wof:placetype":"locality"
},
  "geometry": {"coordinates":[118.07821,40.61639],"type":"Point"}
}