{
  "type": "Feature",
  "properties": {
    "gn:admin1_code":"11.0",
    "gn:asciiname":"Jielao",
    "gn:country_code":"CN",
    "gn:dem":759,
    "gn:feature_class":"P",
    "gn:feature_code":"PPL",
    "gn:name":"Jielao",
    "gn:population":0,
    "gn:timezone":"Asia/Shanghai",
    "iso:country":"CN",
    "name:zho_x_preferred":[
        "\u501f\u8001"
    ],
    "wof:name":"Jielao",
    "wof:placetype":"locality"
},
  "geometry": {"coordinates":[109.8895,28.68392],"type":"Point"}
}