{
  "type": "Feature",
  "properties": {
    "gn:admin1_code":"14.0",
    "gn:asciiname":"Naiqiongda",
    "gn:country_code":"CN",
    "gn:dem":4208,
    "gn:feature_class":"P",
    "gn:feature_code":"PPL",
    "gn:name":"Naiqiongda",
    "gn:population":0,
    "gn:timezone":"Asia/Urumqi",
    "iso:country":"CN",
    "name:bod_x_preferred":[
        "L\u00eaqungda"
    ],
    "name:zho_x_preferred":[
        "Naiqiongda"
    ],
    "name:zho_x_variant":[
        "\u4e43\u7a77\u8fbe"
    ],
    "wof:name":"Naiqiongda",
    "wof:placetype":"locality"
},
  "geometry": {"coordinates":[97.402,32.002],"type":"Point"}
}