{
  "type": "Feature",
  "properties": {
    "gn:admin1_code":"18.0",
    "gn:asciiname":"Moziyan",
    "gn:country_code":"CN",
    "gn:dem":638,
    "gn:feature_class":"P",
    "gn:feature_code":"PPL",
    "gn:name":"Moziyan",
    "gn:population":0,
    "gn:timezone":"Asia/Shanghai",
    "iso:country":"CN",
    "name:zho_x_preferred":[
        "\u78e8\u5b50\u5ca9"
    ],
    "wof:name":"Moziyan",
    "wof:placetype":"locality"
},
  "geometry": {"coordinates":[109.152,28.0525],"type":"Point"}
}