{
  "type": "Feature",
  "properties": {
    "gn:admin1_code":"2.0",
    "gn:asciiname":"Wudu",
    "gn:cc2":"CN",
    "gn:country_code":"CN",
    "gn:dem":334,
    "gn:feature_class":"P",
    "gn:feature_code":"PPL",
    "gn:name":"Wudu",
    "gn:population":0,
    "gn:timezone":"Asia/Shanghai",
    "iso:country":"CN",
    "name:und_x_variant":[
        "Wu-tu",
        "Wudu"
    ],
    "name:zho_x_preferred":[
        "\u4e94\u90fd"
    ],
    "wof:name":"Wudu",
    "wof:placetype":"locality"
},
  "geometry": {"coordinates":[119.00194,27.62],"type":"Point"}
}