{
  "type": "Feature",
  "properties": {
    "gn:admin1_code":"9.0",
    "gn:asciiname":"Luo'ao",
    "gn:country_code":"CN",
    "gn:dem":650,
    "gn:feature_class":"P",
    "gn:feature_code":"PPL",
    "gn:name":"Luo\u2019ao",
    "gn:population":0,
    "gn:timezone":"Asia/Shanghai",
    "iso:country":"CN",
    "name:und_x_variant":[
        "Luo\u2019ao"
    ],
    "name:zho_x_preferred":[
        "\u7f57\u51f9"
    ],
    "wof:name":"Luo'ao",
    "wof:placetype":"locality"
},
  "geometry": {"coordinates":[111.40723,34.37334],"type":"Point"}
}