{
  "type": "Feature",
  "properties": {
    "gn:admin1_code":"8.0",
    "gn:asciiname":"Guolu Fangzi",
    "gn:country_code":"CN",
    "gn:dem":219,
    "gn:feature_class":"P",
    "gn:feature_code":"PPL",
    "gn:name":"Guol\u00fc Fangzi",
    "gn:population":0,
    "gn:timezone":"Asia/Shanghai",
    "iso:country":"CN",
    "name:und_x_variant":[
        "Guol\u00fc Fangzi"
    ],
    "name:zho_x_preferred":[
        "\u90ed\u7eff\u623f\u5b50"
    ],
    "wof:name":"Guolu Fangzi",
    "wof:placetype":"locality"
},
  "geometry": {"coordinates":[127.66266,46.79377],"type":"Point"}
}