{
  "type": "Feature",
  "properties": {
    "gn:admin1_code":"4.0",
    "gn:asciiname":"Dongye",
    "gn:country_code":"CN",
    "gn:dem":8,
    "gn:feature_class":"P",
    "gn:feature_code":"PPL",
    "gn:name":"Dongye",
    "gn:population":0,
    "gn:timezone":"Asia/Shanghai",
    "iso:country":"CN",
    "name:dan_x_preferred":[
        "Dongye"
    ],
    "name:ell_x_preferred":[
        "\u039d\u03c4\u03cc\u03bd\u03b3\u03ba\u03b9\u03b5"
    ],
    "name:fas_x_preferred":[
        "\u062f\u0648\u0646\u06af\u0627\u06cc\u06cc"
    ],
    "name:fra_x_preferred":[
        "Tongye"
    ],
    "name:hun_x_preferred":[
        "Tongje"
    ],
    "name:ind_x_preferred":[
        "Dongye"
    ],
    "name:jpn_x_preferred":[
        "\u30ef\u30a4\u4eba"
    ],
    "name:kat_x_preferred":[
        "\u10e2\u10dd\u10dc\u10d8\u10d4"
    ],
    "name:mon_x_preferred":[
        "\u0422\u0443\u043d\u044a\u0435"
    ],
    "name:msa_x_preferred":[
        "Dongye"
    ],
    "name:nor_x_preferred":[
        "Dongye"
    ],
    "name:pol_x_preferred":[
        "Tongye"
    ],
    "name:rus_x_preferred":[
        "\u0422\u043e\u043d\u044a\u0435"
    ],
    "name:spa_x_preferred":[
        "Dongye"
    ],
    "name:swa_x_preferred":[
        "Dongye"
    ],
    "name:und_x_variant":[
        "\u4e1c\u53f6"
    ],
    "name:vie_x_preferred":[
        "\u0110\u00f4ng U\u1ebf"
    ],
    "name:zho_x_preferred":[
        "\u4e1c\u53f6"
    ],
    "wof:name":"Dongye",
    "wof:placetype":"locality"
},
  "geometry": {"coordinates":[120.1609,32.4753],"type":"Point"}
}