{
  "type": "Feature",
  "properties": {
    "gn:admin1_code":"4.0",
    "gn:asciiname":"Dongye",
    "gn:country_code":"CN",
    "gn:dem":8,
    "gn:feature_class":"P",
    "gn:feature_code":"PPL",
    "gn:name":"Dongye",
    "gn:population":0,
    "gn:timezone":"Asia/Shanghai",
    "iso:country":"CN",
    "name:und_x_variant":[
        "\u4e1c\u53f6"
    ],
    "name:zho_x_preferred":[
        "\u4e1c\u53f6"
    ],
    "wof:name":"Dongye",
    "wof:placetype":"locality"
},
  "geometry": {"coordinates":[120.1609,32.4753],"type":"Point"}
}