{
  "type": "Feature",
  "properties": {
    "gn:admin1_code":"19.0",
    "gn:asciiname":"Houzuo Jiagou",
    "gn:country_code":"CN",
    "gn:dem":139,
    "gn:feature_class":"P",
    "gn:feature_code":"PPL",
    "gn:name":"Houzuo Jiagou",
    "gn:population":0,
    "gn:timezone":"Asia/Shanghai",
    "iso:country":"CN",
    "name:zho_x_preferred":[
        "\u540e\u5de6\u5bb6\u6c9f"
    ],
    "wof:name":"Houzuo Jiagou",
    "wof:placetype":"locality"
},
  "geometry": {"coordinates":[124.18600000000001,43.0941],"type":"Point"}
}