{
  "type": "Feature",
  "properties": {
    "gn:admin1_code":"1.0",
    "gn:asciiname":"Bingtan",
    "gn:country_code":"CN",
    "gn:dem":247,
    "gn:feature_class":"P",
    "gn:feature_code":"PPLA4",
    "gn:name":"Bingtan",
    "gn:population":0,
    "gn:timezone":"Asia/Shanghai",
    "iso:country":"CN",
    "name:und_x_variant":[
        "\u51b0\u6f6d",
        "Bingtan Xiang",
        "\u51b0\u6f6d\u4e61"
    ],
    "wof:name":"Bingtan",
    "wof:placetype":"locality"
},
  "geometry": {"coordinates":[117.91658,29.72258],"type":"Point"}
}