{
  "type": "Feature",
  "properties": {
    "gn:admin1_code":"7.0",
    "gn:asciiname":"Shanmenli",
    "gn:country_code":"CN",
    "gn:dem":81,
    "gn:feature_class":"P",
    "gn:feature_code":"PPL",
    "gn:name":"Shanmenli",
    "gn:population":0,
    "gn:timezone":"Asia/Shanghai",
    "iso:country":"CN",
    "name:zho_x_preferred":[
        "\u5c71\u95e8\u91cc"
    ],
    "wof:name":"Shanmenli",
    "wof:placetype":"locality"
},
  "geometry": {"coordinates":[118.98945999999999,25.33113],"type":"Point"}
}