{
  "type": "Feature",
  "properties": {
    "gn:admin1_code":"26.0",
    "gn:asciiname":"Dongqucun",
    "gn:country_code":"CN",
    "gn:dem":490,
    "gn:feature_class":"P",
    "gn:feature_code":"PPL",
    "gn:name":"Dongqucun",
    "gn:population":0,
    "gn:timezone":"Asia/Shanghai",
    "iso:country":"CN",
    "name:zho_x_preferred":[
        "\u4e1c\u6e20\u6751"
    ],
    "wof:name":"Dongqucun",
    "wof:placetype":"locality"
},
  "geometry": {"coordinates":[109.12025,34.72888],"type":"Point"}
}