{
  "type": "Feature",
  "properties": {
    "gn:admin1_code":"08",
    "gn:asciiname":"Sanzhan",
    "gn:country_code":"CN",
    "gn:dem":385,
    "gn:feature_class":"P",
    "gn:feature_code":"PPL",
    "gn:name":"Sanzhan",
    "gn:population":0,
    "gn:timezone":"Asia/Shanghai",
    "iso:country":"CN",
    "name:eng_x_preferred":[
        "Sanzhan"
    ],
    "name:rus_x_preferred":[
        "\u0421\u0430\u043d\u044c\u0447\u0436\u0430\u043d\u044c"
    ],
    "name:und_x_variant":[
        "San-chan"
    ],
    "wof:name":"Sanzhan",
    "wof:placetype":"locality"
},
  "geometry": {"coordinates":[126.79611,49.62762],"type":"Point"}
}