{
  "type": "Feature",
  "properties": {
    "gn:admin1_code":"14.0",
    "gn:asciiname":"Yagxoi",
    "gn:country_code":"CN",
    "gn:dem":5116,
    "gn:feature_class":"P",
    "gn:feature_code":"PPLF",
    "gn:name":"Yagxoi",
    "gn:population":0,
    "gn:timezone":"Asia/Urumqi",
    "iso:country":"CN",
    "name:bod_x_preferred":[
        "Yagxoi"
    ],
    "name:zho_x_preferred":[
        "Yaxue"
    ],
    "name:zho_x_variant":[
        "\u4e9a\u96ea"
    ],
    "wof:name":"Yagxoi",
    "wof:placetype":"locality"
},
  "geometry": {"coordinates":[92.901,28.801],"type":"Point"}
}