{
  "type": "Feature",
  "properties": {
    "gn:admin1_code":"4.0",
    "gn:asciiname":"Dongduncun",
    "gn:country_code":"CN",
    "gn:dem":13,
    "gn:feature_class":"P",
    "gn:feature_code":"PPL",
    "gn:name":"Dongduncun",
    "gn:population":0,
    "gn:timezone":"Asia/Shanghai",
    "iso:country":"CN",
    "name:zho_x_preferred":[
        "\u8463\u58a9\u6751"
    ],
    "wof:name":"Dongduncun",
    "wof:placetype":"locality"
},
  "geometry": {"coordinates":[118.55670000000001,33.98993],"type":"Point"}
}