{
  "type": "Feature",
  "properties": {
    "gn:admin1_code":"4.0",
    "gn:asciiname":"Sanmen",
    "gn:country_code":"CN",
    "gn:dem":4,
    "gn:feature_class":"P",
    "gn:feature_code":"PPL",
    "gn:name":"Sanmen",
    "gn:population":0,
    "gn:timezone":"Asia/Shanghai",
    "iso:country":"CN",
    "name:zho_x_preferred":[
        "Sanmen"
    ],
    "name:zho_x_variant":[
        "\u4e09\u95e8"
    ],
    "wof:name":"Sanmen",
    "wof:placetype":"locality"
},
  "geometry": {"coordinates":[119.31207000000001,33.64554],"type":"Point"}
}