{
  "type": "Feature",
  "properties": {
    "gn:admin1_code":"20",
    "gn:asciiname":"Jargalangt",
    "gn:country_code":"CN",
    "gn:dem":1295,
    "gn:feature_class":"P",
    "gn:feature_code":"PPL",
    "gn:name":"Jargalangt",
    "gn:population":0,
    "gn:timezone":"Asia/Shanghai",
    "iso:country":"CN",
    "wof:name":"Jargalangt",
    "wof:placetype":"locality"
},
  "geometry": {"coordinates":[115.16667,45.01667],"type":"Point"}
}