{
  "type": "Feature",
  "properties": {
    "gn:admin1_code":"26.0",
    "gn:asciiname":"Jinhuacun",
    "gn:country_code":"CN",
    "gn:dem":722,
    "gn:feature_class":"P",
    "gn:feature_code":"PPL",
    "gn:name":"Jinhuacun",
    "gn:population":0,
    "gn:timezone":"Asia/Shanghai",
    "iso:country":"CN",
    "name:zho_x_preferred":[
        "\u91d1\u82b1\u6751"
    ],
    "wof:name":"Jinhuacun",
    "wof:placetype":"locality"
},
  "geometry": {"coordinates":[109.20135000000001,33.45637],"type":"Point"}
}