{
  "type": "Feature",
  "properties": {
    "gn:admin1_code":"29.0",
    "gn:asciiname":"Dianzishang",
    "gn:country_code":"CN",
    "gn:dem":2310,
    "gn:feature_class":"P",
    "gn:feature_code":"PPL",
    "gn:name":"Dianzishang",
    "gn:population":0,
    "gn:timezone":"Asia/Shanghai",
    "iso:country":"CN",
    "name:und_x_variant":[
        "\u5e97\u5b50\u4e0a"
    ],
    "wof:name":"Dianzishang",
    "wof:placetype":"locality"
},
  "geometry": {"coordinates":[103.371,26.8797],"type":"Point"}
}