{
  "type": "Feature",
  "properties": {
    "gn:admin1_code":"29.0",
    "gn:asciiname":"Liedi",
    "gn:country_code":"CN",
    "gn:dem":1521,
    "gn:feature_class":"P",
    "gn:feature_code":"PPL",
    "gn:name":"Liedi",
    "gn:population":0,
    "gn:timezone":"Asia/Shanghai",
    "iso:country":"CN",
    "name:zho_x_preferred":[
        "\u5217\u5e95"
    ],
    "wof:name":"Liedi",
    "wof:placetype":"locality"
},
  "geometry": {"coordinates":[101.114,24.216],"type":"Point"}
}