{
  "type": "Feature",
  "properties": {
    "gn:admin1_code":"32.0",
    "gn:asciiname":"Naituo",
    "gn:country_code":"CN",
    "gn:dem":1737,
    "gn:feature_class":"P",
    "gn:feature_code":"PPL",
    "gn:name":"Naituo",
    "gn:population":0,
    "gn:timezone":"Asia/Shanghai",
    "iso:country":"CN",
    "name:zho_x_preferred":[
        "\u4e43\u6258"
    ],
    "wof:name":"Naituo",
    "wof:placetype":"locality"
},
  "geometry": {"coordinates":[102.60912,28.72593],"type":"Point"}
}