{
  "type": "Feature",
  "properties": {
    "gn:admin1_code":"30",
    "gn:asciiname":"Xinqiao",
    "gn:country_code":"CN",
    "gn:dem":92,
    "gn:feature_class":"P",
    "gn:feature_code":"PPL",
    "gn:name":"Xinqiao",
    "gn:population":0,
    "gn:timezone":"Asia/Urumqi",
    "iso:country":"CN",
    "name:zho_x_preferred":[
        "\u65b0\u6865"
    ],
    "name:zho_x_variant":[
        "\u4fe1\u6865"
    ],
    "wof:name":"Xinqiao",
    "wof:placetype":"locality"
},
  "geometry": {"coordinates":[110.21323,20.42442],"type":"Point"}
}