{
  "type": "Feature",
  "properties": {
    "gn:admin1_code":"12.0",
    "gn:asciiname":"Baiguoshu",
    "gn:country_code":"CN",
    "gn:dem":1051,
    "gn:feature_class":"P",
    "gn:feature_code":"PPL",
    "gn:name":"Baiguoshu",
    "gn:population":0,
    "gn:timezone":"Asia/Shanghai",
    "iso:country":"CN",
    "name:zho_x_preferred":[
        "\u767d\u679c\u6811"
    ],
    "wof:name":"Baiguoshu",
    "wof:placetype":"locality"
},
  "geometry": {"coordinates":[110.82031000000001,31.78853],"type":"Point"}
}