{
  "type": "Feature",
  "properties": {
    "gn:admin1_code":"4.0",
    "gn:asciiname":"Huangquan",
    "gn:country_code":"CN",
    "gn:dem":60,
    "gn:feature_class":"P",
    "gn:feature_code":"PPL",
    "gn:name":"Huangquan",
    "gn:population":0,
    "gn:timezone":"Asia/Shanghai",
    "iso:country":"CN",
    "name:zho_x_preferred":[
        "\u9ec4\u6cc9"
    ],
    "wof:name":"Huangquan",
    "wof:placetype":"locality"
},
  "geometry": {"coordinates":[117.253,34.4105],"type":"Point"}
}