{
  "type": "Feature",
  "properties": {
    "gn:admin1_code":"01",
    "gn:asciiname":"Kaoxicun",
    "gn:country_code":"CN",
    "gn:dem":33,
    "gn:feature_class":"P",
    "gn:feature_code":"PPL",
    "gn:name":"Kaoxicun",
    "gn:population":0,
    "gn:timezone":"Asia/Shanghai",
    "iso:country":"CN",
    "name:und_x_variant":[
        "Kaoxi",
        "Kaocheng",
        "Kaoxicun"
    ],
    "name:zho_x_preferred":[
        "\u8003\u897f"
    ],
    "name:zho_x_variant":[
        "\u8003\u57ce",
        "\u8003\u897f\u6751"
    ],
    "wof:name":"Kaoxicun",
    "wof:placetype":"locality"
},
  "geometry": {"coordinates":[117.22748,32.74872],"type":"Point"}
}