{
  "type": "Feature",
  "properties": {
    "gn:admin1_code":"2.0",
    "gn:asciiname":"Yuantou",
    "gn:country_code":"CN",
    "gn:dem":354,
    "gn:feature_class":"P",
    "gn:feature_code":"PPL",
    "gn:name":"Yuantou",
    "gn:population":0,
    "gn:timezone":"Asia/Shanghai",
    "iso:country":"CN",
    "name:und_x_variant":[
        "\u6e90\u5934",
        "Yuantou"
    ],
    "wof:name":"Yuantou",
    "wof:placetype":"locality"
},
  "geometry": {"coordinates":[119.05515,29.89671],"type":"Point"}
}