{
  "type": "Feature",
  "properties": {
    "gn:admin1_code":"19.0",
    "gn:asciiname":"Beimadao",
    "gn:country_code":"CN",
    "gn:dem":12,
    "gn:feature_class":"P",
    "gn:feature_code":"PPL",
    "gn:name":"Beimadao",
    "gn:population":0,
    "gn:timezone":"Asia/Shanghai",
    "iso:country":"CN",
    "name:und_x_variant":[
        "Beimacun"
    ],
    "name:zho_x_preferred":[
        "\u5317\u9a6c\u9053"
    ],
    "name:zho_x_variant":[
        "\u5317\u9a6c\u6751"
    ],
    "wof:name":"Beimadao",
    "wof:placetype":"locality"
},
  "geometry": {"coordinates":[121.40966,41.06976],"type":"Point"}
}