{
  "type": "Feature",
  "properties": {
    "gn:admin1_code":"18.0",
    "gn:asciiname":"Xiadangweng",
    "gn:country_code":"CN",
    "gn:dem":886,
    "gn:feature_class":"P",
    "gn:feature_code":"PPL",
    "gn:name":"Xiadangweng",
    "gn:population":0,
    "gn:timezone":"Asia/Shanghai",
    "iso:country":"CN",
    "name:zho_x_preferred":[
        "\u4e0b\u515a\u7fc1"
    ],
    "wof:name":"Xiadangweng",
    "wof:placetype":"locality"
},
  "geometry": {"coordinates":[108.56,26.7129],"type":"Point"}
}