{
  "type": "Feature",
  "properties": {
    "gn:admin1_code":"15.0",
    "gn:asciiname":"Duntai",
    "gn:country_code":"CN",
    "gn:dem":1140,
    "gn:feature_class":"P",
    "gn:feature_code":"PPL",
    "gn:name":"Duntai",
    "gn:population":0,
    "gn:timezone":"Asia/Shanghai",
    "iso:country":"CN",
    "name:zho_x_preferred":[
        "\u58a9\u53f0"
    ],
    "wof:name":"Duntai",
    "wof:placetype":"locality"
},
  "geometry": {"coordinates":[107.13,35.3881],"type":"Point"}
}