{
  "type": "Feature",
  "properties": {
    "gn:admin1_code":"11.0",
    "gn:asciiname":"Mengqitu",
    "gn:country_code":"CN",
    "gn:dem":541,
    "gn:feature_class":"P",
    "gn:feature_code":"PPL",
    "gn:name":"Mengqitu",
    "gn:population":0,
    "gn:timezone":"Asia/Shanghai",
    "iso:country":"CN",
    "name:zho_x_preferred":[
        "\u8499\u68cb\u56fe"
    ],
    "wof:name":"Mengqitu",
    "wof:placetype":"locality"
},
  "geometry": {"coordinates":[111.10463,28.18276],"type":"Point"}
}