{
  "type": "Feature",
  "properties": {
    "gn:admin1_code":"11.0",
    "gn:asciiname":"Jinjiachong",
    "gn:country_code":"CN",
    "gn:dem":198,
    "gn:feature_class":"P",
    "gn:feature_code":"PPL",
    "gn:name":"Jinjiachong",
    "gn:population":0,
    "gn:timezone":"Asia/Shanghai",
    "iso:country":"CN",
    "name:zho_x_preferred":[
        "Jinjiachong"
    ],
    "name:zho_x_variant":[
        "\u91d1\u5bb6\u51b2"
    ],
    "wof:name":"Jinjiachong",
    "wof:placetype":"locality"
},
  "geometry": {"coordinates":[111.45225000000001,29.73642000000001],"type":"Point"}
}