{
  "type": "Feature",
  "properties": {
    "gn:admin1_code":"11",
    "gn:asciiname":"Shanmuqiao",
    "gn:country_code":"CN",
    "gn:dem":172,
    "gn:feature_class":"P",
    "gn:feature_code":"PPLA4",
    "gn:name":"Shanmuqiao",
    "gn:population":0,
    "gn:timezone":"Asia/Shanghai",
    "iso:country":"CN",
    "name:und_x_variant":[
        "Shanmuqiao Zhen",
        "Shanmuqiao"
    ],
    "name:zho_x_preferred":[
        "\u6749\u6728\u6865"
    ],
    "name:zho_x_variant":[
        "\u6749\u6728\u6865\u9547"
    ],
    "wof:name":"Shanmuqiao",
    "wof:placetype":"locality"
},
  "geometry": {"coordinates":[110.93214999999999,29.53811],"type":"Point"}
}