{
  "type": "Feature",
  "properties": {
    "gn:admin1_code":"11.0",
    "gn:asciiname":"Tianjiachong",
    "gn:country_code":"CN",
    "gn:dem":352,
    "gn:feature_class":"P",
    "gn:feature_code":"PPL",
    "gn:name":"Tianjiachong",
    "gn:population":0,
    "gn:timezone":"Asia/Shanghai",
    "iso:country":"CN",
    "name:zho_x_preferred":[
        "\u7530\u5bb6\u51b2"
    ],
    "wof:name":"Tianjiachong",
    "wof:placetype":"locality"
},
  "geometry": {"coordinates":[110.65223,26.81218],"type":"Point"}
}