{
  "type": "Feature",
  "properties": {
    "gn:admin1_code":"5.0",
    "gn:asciiname":"Tuyaozicun",
    "gn:country_code":"CN",
    "gn:dem":178,
    "gn:feature_class":"P",
    "gn:feature_code":"PPL",
    "gn:name":"Tuyaozicun",
    "gn:population":0,
    "gn:timezone":"Asia/Shanghai",
    "iso:country":"CN",
    "name:zho_x_preferred":[
        "\u571f\u7a91\u5b50\u6751"
    ],
    "wof:name":"Tuyaozicun",
    "wof:placetype":"locality"
},
  "geometry": {"coordinates":[126.21062999999999,44.92689],"type":"Point"}
}