{
  "type": "Feature",
  "properties": {
    "gn:admin1_code":"3.0",
    "gn:asciiname":"Xianxia",
    "gn:country_code":"CN",
    "gn:dem":156,
    "gn:feature_class":"P",
    "gn:feature_code":"PPLA4",
    "gn:name":"Xianxia",
    "gn:population":0,
    "gn:timezone":"Asia/Shanghai",
    "iso:country":"CN",
    "name:und_x_variant":[
        "Shan-hsia-kuan",
        "Hsien-hsia",
        "Hsien-hsia-kuan",
        "Xianxia",
        "\u4ed9\u4e0b",
        "Xianxia Xiang",
        "\u4ed9\u4e0b\u4e61"
    ],
    "wof:name":"Xianxia",
    "wof:placetype":"locality"
},
  "geometry": {"coordinates":[115.56313,26.11312],"type":"Point"}
}