{
  "type": "Feature",
  "properties": {
    "gn:admin1_code":"25",
    "gn:asciiname":"Rizhuang",
    "gn:cc2":"CN",
    "gn:country_code":"CN",
    "gn:dem":79,
    "gn:feature_class":"P",
    "gn:feature_code":"PPL",
    "gn:name":"Rizhuang",
    "gn:population":0,
    "gn:timezone":"Asia/Shanghai",
    "iso:country":"CN",
    "name:und_x_variant":[
        "Jih-chuang",
        "Rizhuang"
    ],
    "wof:name":"Rizhuang",
    "wof:placetype":"locality"
},
  "geometry": {"coordinates":[120.38306,36.95083],"type":"Point"}
}