{
  "type": "Feature",
  "properties": {
    "gn:admin1_code":"11.0",
    "gn:asciiname":"Leijia",
    "gn:country_code":"CN",
    "gn:dem":255,
    "gn:feature_class":"P",
    "gn:feature_code":"PPL",
    "gn:name":"Leijia",
    "gn:population":0,
    "gn:timezone":"Asia/Shanghai",
    "iso:country":"CN",
    "name:zho_x_preferred":[
        "\u96f7\u5bb6"
    ],
    "wof:name":"Leijia",
    "wof:placetype":"locality"
},
  "geometry": {"coordinates":[112.47992000000001,26.04438],"type":"Point"}
}