{
  "type": "Feature",
  "properties": {
    "gn:admin1_code":"05",
    "gn:asciiname":"Wohutun",
    "gn:cc2":"CN",
    "gn:country_code":"CN",
    "gn:dem":134,
    "gn:feature_class":"P",
    "gn:feature_code":"PPL",
    "gn:name":"Wohutun",
    "gn:population":0,
    "gn:timezone":"Asia/Shanghai",
    "iso:country":"CN",
    "name:und_x_variant":[
        "Wo-hu-shan",
        "Wohutun"
    ],
    "wof:name":"Wohutun",
    "wof:placetype":"locality"
},
  "geometry": {"coordinates":[123.55167,43.70222],"type":"Point"}
}