{
  "type": "Feature",
  "properties": {
    "gn:admin1_code":"4.0",
    "gn:asciiname":"Cangwuzhuang",
    "gn:country_code":"CN",
    "gn:dem":18,
    "gn:feature_class":"P",
    "gn:feature_code":"PPL",
    "gn:name":"Cangwuzhuang",
    "gn:population":0,
    "gn:timezone":"Asia/Shanghai",
    "iso:country":"CN",
    "name:zho_x_preferred":[
        "\u4ed3\u5c4b\u5e84"
    ],
    "wof:name":"Cangwuzhuang",
    "wof:placetype":"locality"
},
  "geometry": {"coordinates":[118.94553000000001,32.9944],"type":"Point"}
}