{
  "type": "Feature",
  "properties": {
    "gn:admin1_code":"20",
    "gn:asciiname":"Hongqi",
    "gn:cc2":"CN",
    "gn:country_code":"CN",
    "gn:dem":1421,
    "gn:feature_class":"P",
    "gn:feature_code":"PPL",
    "gn:name":"Hongqi",
    "gn:population":0,
    "gn:timezone":"Asia/Shanghai",
    "iso:country":"CN",
    "name:ceb_x_preferred":[
        "Hongqi"
    ],
    "name:deu_x_preferred":[
        "Hongqi"
    ],
    "name:fra_x_preferred":[
        "Hongqi"
    ],
    "name:nor_x_preferred":[
        "Hongqi"
    ],
    "name:und_x_variant":[
        "Chao-ta-pao",
        "Hongqi Xiang"
    ],
    "name:zho_x_preferred":[
        "\u7ea2\u65d7"
    ],
    "wof:name":"Hongqi",
    "wof:placetype":"locality"
},
  "geometry": {"coordinates":[115.04000000000001,42.01806],"type":"Point"}
}