{
  "type": "Feature",
  "properties": {
    "gn:admin1_code":"29.0",
    "gn:asciiname":"Shanbaocun",
    "gn:country_code":"CN",
    "gn:dem":2185,
    "gn:feature_class":"P",
    "gn:feature_code":"PPL",
    "gn:name":"Shanbaocun",
    "gn:population":0,
    "gn:timezone":"Asia/Shanghai",
    "iso:country":"CN",
    "name:zho_x_preferred":[
        "\u5c71\u4fdd\u6751"
    ],
    "wof:name":"Shanbaocun",
    "wof:placetype":"locality"
},
  "geometry": {"coordinates":[103.126,27.2614],"type":"Point"}
}