{
  "type": "Feature",
  "properties": {
    "gn:admin1_code":"15.0",
    "gn:asciiname":"Zhangmalu",
    "gn:country_code":"CN",
    "gn:dem":2547,
    "gn:feature_class":"P",
    "gn:feature_code":"PPL",
    "gn:name":"Zhangmalu",
    "gn:population":0,
    "gn:timezone":"Asia/Shanghai",
    "iso:country":"CN",
    "name:und_x_variant":[
        "\u5f20\u9a6c\u8def"
    ],
    "wof:name":"Zhangmalu",
    "wof:placetype":"locality"
},
  "geometry": {"coordinates":[104.12013,34.35605],"type":"Point"}
}