{
  "type": "Feature",
  "properties": {
    "gn:admin1_code":"10",
    "gn:asciiname":"Sujiliang",
    "gn:country_code":"CN",
    "gn:dem":1402,
    "gn:feature_class":"P",
    "gn:feature_code":"PPL",
    "gn:name":"Sujiliang",
    "gn:population":0,
    "gn:timezone":"Asia/Shanghai",
    "iso:country":"CN",
    "name:zho_x_preferred":[
        "\u82cf\u8ba1\u6881"
    ],
    "wof:name":"Sujiliang",
    "wof:placetype":"locality"
},
  "geometry": {"coordinates":[114.4164,41.49378],"type":"Point"}
}