{
  "type": "Feature",
  "properties": {
    "gn:admin1_code":"19",
    "gn:asciiname":"Jinshanwan",
    "gn:cc2":"CN",
    "gn:country_code":"CN",
    "gn:dem":43,
    "gn:feature_class":"P",
    "gn:feature_code":"PPL",
    "gn:name":"Jinshanwan",
    "gn:population":0,
    "gn:timezone":"Asia/Shanghai",
    "iso:country":"CN",
    "name:und_x_variant":[
        "Chin-shan-wan",
        "Jinshanwan"
    ],
    "wof:name":"Jinshanwan",
    "wof:placetype":"locality"
},
  "geometry": {"coordinates":[124.33333,40.21667],"type":"Point"}
}