{
  "type": "Feature",
  "properties": {
    "gn:admin1_code":"20.0",
    "gn:asciiname":"Xihetun",
    "gn:country_code":"CN",
    "gn:dem":321,
    "gn:feature_class":"P",
    "gn:feature_code":"PPL",
    "gn:name":"Xihetun",
    "gn:population":0,
    "gn:timezone":"Asia/Shanghai",
    "iso:country":"CN",
    "name:zho_x_preferred":[
        "\u897f\u6cb3\u5c6f"
    ],
    "wof:name":"Xihetun",
    "wof:placetype":"locality"
},
  "geometry": {"coordinates":[123.18226,48.48589000000001],"type":"Point"}
}