{
  "type": "Feature",
  "properties": {
    "gn:admin1_code":"32.0",
    "gn:asciiname":"Zipawan",
    "gn:country_code":"CN",
    "gn:dem":1378,
    "gn:feature_class":"P",
    "gn:feature_code":"PPL",
    "gn:name":"Zipawan",
    "gn:population":0,
    "gn:timezone":"Asia/Shanghai",
    "iso:country":"CN",
    "name:zho_x_preferred":[
        "\u6dc4\u722c\u6e7e"
    ],
    "wof:name":"Zipawan",
    "wof:placetype":"locality"
},
  "geometry": {"coordinates":[101.87203,27.12487],"type":"Point"}
}