{
  "type": "Feature",
  "properties": {
    "gn:admin1_code":"29.0",
    "gn:asciiname":"Chenjia Dazhai",
    "gn:country_code":"CN",
    "gn:dem":1785,
    "gn:feature_class":"P",
    "gn:feature_code":"PPL",
    "gn:name":"Chenjia Dazhai",
    "gn:population":0,
    "gn:timezone":"Asia/Shanghai",
    "iso:country":"CN",
    "name:zho_x_preferred":[
        "\u9648\u5bb6\u5927\u5be8"
    ],
    "wof:name":"Chenjia Dazhai",
    "wof:placetype":"locality"
},
  "geometry": {"coordinates":[98.68689999999999,25.5271],"type":"Point"}
}