{
  "type": "Feature",
  "properties": {
    "gn:admin1_code":"23.0",
    "gn:asciiname":"Xiexing",
    "gn:country_code":"CN",
    "gn:dem":5,
    "gn:feature_class":"P",
    "gn:feature_code":"PPL",
    "gn:name":"Xiexing",
    "gn:population":0,
    "gn:timezone":"Asia/Shanghai",
    "iso:country":"CN",
    "name:zho_x_preferred":[
        "Xiexing"
    ],
    "name:zho_x_variant":[
        "\u534f\u5174"
    ],
    "wof:name":"Xiexing",
    "wof:placetype":"locality"
},
  "geometry": {"coordinates":[121.41468999999999,31.708],"type":"Point"}
}