{
  "type": "Feature",
  "properties": {
    "gn:admin1_code":"8.0",
    "gn:asciiname":"Xujiangtun",
    "gn:country_code":"CN",
    "gn:dem":126,
    "gn:feature_class":"P",
    "gn:feature_code":"PPL",
    "gn:name":"Xujiangtun",
    "gn:population":0,
    "gn:timezone":"Asia/Shanghai",
    "iso:country":"CN",
    "name:zho_x_preferred":[
        "\u5f90\u6c5f\u5c6f"
    ],
    "wof:name":"Xujiangtun",
    "wof:placetype":"locality"
},
  "geometry": {"coordinates":[125.63845999999999,45.54362],"type":"Point"}
}