{
  "type": "Feature",
  "properties": {
    "gn:admin1_code":"15.0",
    "gn:asciiname":"Shuangjingzi",
    "gn:country_code":"CN",
    "gn:dem":1746,
    "gn:feature_class":"P",
    "gn:feature_code":"PPL",
    "gn:name":"Shuangjingzi",
    "gn:population":0,
    "gn:timezone":"Asia/Shanghai",
    "iso:country":"CN",
    "name:und_x_variant":[
        "\u53cc\u4e95\u5b50"
    ],
    "wof:name":"Shuangjingzi",
    "wof:placetype":"locality"
},
  "geometry": {"coordinates":[106.65804,36.80129],"type":"Point"}
}