{
  "type": "Feature",
  "properties": {
    "gn:admin1_code":"15.0",
    "gn:asciiname":"Dangzhuang",
    "gn:country_code":"CN",
    "gn:dem":2047,
    "gn:feature_class":"P",
    "gn:feature_code":"PPL",
    "gn:name":"Dangzhuang",
    "gn:population":0,
    "gn:timezone":"Asia/Shanghai",
    "iso:country":"CN",
    "name:und_x_variant":[
        "\u5f53\u5e84"
    ],
    "wof:name":"Dangzhuang",
    "wof:placetype":"locality"
},
  "geometry": {"coordinates":[105.17511,35.36288],"type":"Point"}
}