{
  "type": "Feature",
  "properties": {
    "gn:admin1_code":"15.0",
    "gn:asciiname":"Nanpan",
    "gn:country_code":"CN",
    "gn:dem":1381,
    "gn:feature_class":"P",
    "gn:feature_code":"PPL",
    "gn:name":"Nanpan",
    "gn:population":0,
    "gn:timezone":"Asia/Shanghai",
    "iso:country":"CN",
    "name:ara_x_preferred":[
        "\u0646\u0627\u0646\u0628\u0627\u0646"
    ],
    "name:ben_x_preferred":[
        "\u09a8\u09be\u09a8\u09aa\u09be\u09a8"
    ],
    "name:ell_x_preferred":[
        "\u039d\u03b1\u03bd\u03c0\u03ac\u03bd"
    ],
    "name:fas_x_preferred":[
        "\u0646\u0627\u0646\u067e\u0627\u0646"
    ],
    "name:heb_x_preferred":[
        "\u05e0\u05d0\u05e0\u05e4\u05d0\u05df"
    ],
    "name:hin_x_preferred":[
        "\u0928\u093e\u0928\u092a\u0928"
    ],
    "name:hun_x_preferred":[
        "Nanpan"
    ],
    "name:ind_x_preferred":[
        "Nanpan"
    ],
    "name:ita_x_preferred":[
        "Nanpan"
    ],
    "name:kor_x_preferred":[
        "\ub09c\ud310"
    ],
    "name:nld_x_preferred":[
        "Nanpan"
    ],
    "name:pol_x_preferred":[
        "Nanpan"
    ],
    "name:por_x_preferred":[
        "Nanpan"
    ],
    "name:spa_x_preferred":[
        "Nanpan"
    ],
    "name:tur_x_preferred":[
        "Nanpan"
    ],
    "name:ukr_x_preferred":[
        "\u041d\u0430\u043d\u043f\u0430\u043d"
    ],
    "name:urd_x_preferred":[
        "\u0646\u0627\u0646\u067e\u0627\u0646"
    ],
    "name:zho_x_preferred":[
        "\u5357\u7554"
    ],
    "wof:name":"Nanpan",
    "wof:placetype":"locality"
},
  "geometry": {"coordinates":[108.355,35.3314],"type":"Point"}
}