{
  "type": "Feature",
  "properties": {
    "gn:admin1_code":"3.0",
    "gn:asciiname":"Anyuan",
    "gn:country_code":"CN",
    "gn:dem":611,
    "gn:feature_class":"P",
    "gn:feature_code":"PPL",
    "gn:name":"Anyuan",
    "gn:population":0,
    "gn:timezone":"Asia/Shanghai",
    "iso:country":"CN",
    "name:und_x_variant":[
        "\u5b89\u6e90"
    ],
    "wof:name":"Anyuan",
    "wof:placetype":"locality"
},
  "geometry": {"coordinates":[114.30853999999999,27.48785],"type":"Point"}
}