{
  "type": "Feature",
  "properties": {
    "gn:admin1_code":"11.0",
    "gn:asciiname":"Xiaheyezhou",
    "gn:country_code":"CN",
    "gn:dem":30,
    "gn:feature_class":"P",
    "gn:feature_code":"PPL",
    "gn:name":"Xiaheyezhou",
    "gn:population":0,
    "gn:timezone":"Asia/Shanghai",
    "iso:country":"CN",
    "name:zho_x_preferred":[
        "\u4e0b\u8377\u53f6\u6d32"
    ],
    "wof:name":"Xiaheyezhou",
    "wof:placetype":"locality"
},
  "geometry": {"coordinates":[113.39234999999999,29.69611],"type":"Point"}
}