{
  "type": "Feature",
  "properties": {
    "gn:admin1_code":"31",
    "gn:asciiname":"Bitang",
    "gn:country_code":"CN",
    "gn:dem":126,
    "gn:feature_class":"P",
    "gn:feature_code":"PPL",
    "gn:name":"Bitang",
    "gn:population":0,
    "gn:timezone":"Asia/Shanghai",
    "iso:country":"CN",
    "wof:name":"Bitang",
    "wof:placetype":"locality"
},
  "geometry": {"coordinates":[110.19750000000001,18.94472],"type":"Point"}
}