{
  "type": "Feature",
  "properties": {
    "gn:admin1_code":"14.0",
    "gn:asciiname":"Gongbuwo",
    "gn:country_code":"CN",
    "gn:dem":3139,
    "gn:feature_class":"P",
    "gn:feature_code":"PPL",
    "gn:name":"Gongbuwo",
    "gn:population":0,
    "gn:timezone":"Asia/Urumqi",
    "iso:country":"CN",
    "name:zho_x_preferred":[
        "\u5de5\u5e03\u7a9d"
    ],
    "wof:name":"Gongbuwo",
    "wof:placetype":"locality"
},
  "geometry": {"coordinates":[94.28052,29.28368],"type":"Point"}
}