{
  "type": "Feature",
  "properties": {
    "gn:admin1_code":"9.0",
    "gn:asciiname":"Jingzigou",
    "gn:country_code":"CN",
    "gn:dem":508,
    "gn:feature_class":"P",
    "gn:feature_code":"PPL",
    "gn:name":"Jingzigou",
    "gn:population":0,
    "gn:timezone":"Asia/Shanghai",
    "iso:country":"CN",
    "name:zho_x_preferred":[
        "\u4e95\u5b57\u6c9f"
    ],
    "wof:name":"Jingzigou",
    "wof:placetype":"locality"
},
  "geometry": {"coordinates":[112.03102,34.7759],"type":"Point"}
}