{
  "type": "Feature",
  "properties": {
    "gn:admin1_code":"24.0",
    "gn:asciiname":"Xinglinping",
    "gn:cc2":"CN",
    "gn:country_code":"CN",
    "gn:dem":1293,
    "gn:feature_class":"P",
    "gn:feature_code":"PPL",
    "gn:name":"Xinglinping",
    "gn:population":0,
    "gn:timezone":"Asia/Shanghai",
    "iso:country":"CN",
    "name:und_x_variant":[
        "Hsing-shu-p\u2019ing",
        "Hsing-lin-p\u2019ing",
        "Xinglinping"
    ],
    "wof:name":"Xinglinping",
    "wof:placetype":"locality"
},
  "geometry": {"coordinates":[112.13333,37.98333],"type":"Point"}
}