{
  "type": "Feature",
  "properties": {
    "gn:admin1_code":"14.0",
    "gn:asciiname":"Zhelincun",
    "gn:country_code":"CN",
    "gn:dem":3874,
    "gn:feature_class":"P",
    "gn:feature_code":"PPL",
    "gn:name":"Zhelincun",
    "gn:population":0,
    "gn:timezone":"Asia/Urumqi",
    "iso:country":"CN",
    "name:zho_x_preferred":[
        "\u8005\u6797\u6751"
    ],
    "wof:name":"Zhelincun",
    "wof:placetype":"locality"
},
  "geometry": {"coordinates":[92.59659000000001,28.93603],"type":"Point"}
}