{
  "type": "Feature",
  "properties": {
    "gn:admin1_code":"7",
    "gn:asciiname":"Nanyang Linchang",
    "gn:country_code":"CN",
    "gn:dem":682,
    "gn:feature_class":"P",
    "gn:feature_code":"PPLF",
    "gn:name":"Nanyang Linchang",
    "gn:population":0,
    "gn:timezone":"Asia/Shanghai",
    "iso:country":"CN",
    "wof:name":"Nanyang Linchang",
    "wof:placetype":"locality"
},
  "geometry": {"coordinates":[119.27388999999999,25.87722],"type":"Point"}
}