{
  "type": "Feature",
  "properties": {
    "gn:admin1_code":"14.0",
    "gn:asciiname":"Xian'ecun",
    "gn:country_code":"CN",
    "gn:dem":4014,
    "gn:feature_class":"P",
    "gn:feature_code":"PPL",
    "gn:name":"Xian\u2019ecun",
    "gn:population":0,
    "gn:timezone":"Asia/Urumqi",
    "iso:country":"CN",
    "name:und_x_variant":[
        "Xian\u2019ecun"
    ],
    "name:zho_x_preferred":[
        "\u663e\u4fc4\u6751"
    ],
    "wof:name":"Xian'ecun",
    "wof:placetype":"locality"
},
  "geometry": {"coordinates":[94.87445,30.79364],"type":"Point"}
}