{
  "type": "Feature",
  "properties": {
    "gn:admin1_code":"1.0",
    "gn:asciiname":"Liudicun",
    "gn:country_code":"CN",
    "gn:dem":26,
    "gn:feature_class":"P",
    "gn:feature_code":"PPL",
    "gn:name":"Liudicun",
    "gn:population":0,
    "gn:timezone":"Asia/Shanghai",
    "iso:country":"CN",
    "name:zho_x_preferred":[
        "\u5218\u5e1d\u6751"
    ],
    "wof:name":"Liudicun",
    "wof:placetype":"locality"
},
  "geometry": {"coordinates":[116.56652,32.46232],"type":"Point"}
}