{
  "type": "Feature",
  "properties": {
    "gn:admin1_code":"10",
    "gn:asciiname":"Guzuizi",
    "gn:country_code":"CN",
    "gn:dem":1237,
    "gn:feature_class":"P",
    "gn:feature_code":"PPL",
    "gn:name":"Guzuizi",
    "gn:population":0,
    "gn:timezone":"Asia/Shanghai",
    "iso:country":"CN",
    "name:zho_x_preferred":[
        "\u8c37\u5634\u5b50"
    ],
    "wof:name":"Guzuizi",
    "wof:placetype":"locality"
},
  "geometry": {"coordinates":[115.20372999999999,40.82439],"type":"Point"}
}