{
  "type": "Feature",
  "properties": {
    "gn:admin1_code":"7",
    "gn:asciiname":"Shuangfeng",
    "gn:country_code":"CN",
    "gn:dem":26,
    "gn:feature_class":"P",
    "gn:feature_code":"PPL",
    "gn:name":"Shuangfeng",
    "gn:population":0,
    "gn:timezone":"Asia/Shanghai",
    "iso:country":"CN",
    "name:ceb_x_preferred":[
        "Shuangfeng"
    ],
    "name:deu_x_preferred":[
        "Shuangfeng"
    ],
    "name:und_x_variant":[
        "\u53cc\u5cf0",
        "Shuangfeng"
    ],
    "wof:name":"Shuangfeng",
    "wof:placetype":"locality"
},
  "geometry": {"coordinates":[119.60250000000001,27.03216],"type":"Point"}
}