{
  "type": "Feature",
  "properties": {
    "gn:admin1_code":"16.0",
    "gn:asciiname":"Dasheng",
    "gn:country_code":"CN",
    "gn:dem":860,
    "gn:feature_class":"P",
    "gn:feature_code":"PPL",
    "gn:name":"Dasheng",
    "gn:population":0,
    "gn:timezone":"Asia/Shanghai",
    "iso:country":"CN",
    "name:zho_x_preferred":[
        "\u5927\u751f"
    ],
    "wof:name":"Dasheng",
    "wof:placetype":"locality"
},
  "geometry": {"coordinates":[106.29000000000001,23.3946],"type":"Point"}
}