{
  "type": "Feature",
  "properties": {
    "gn:admin1_code":"8.0",
    "gn:asciiname":"Taipingchuantun",
    "gn:country_code":"CN",
    "gn:dem":202,
    "gn:feature_class":"P",
    "gn:feature_code":"PPL",
    "gn:name":"Taipingchuantun",
    "gn:population":0,
    "gn:timezone":"Asia/Shanghai",
    "iso:country":"CN",
    "name:zho_x_preferred":[
        "\u592a\u5e73\u5ddd\u5c6f"
    ],
    "wof:name":"Taipingchuantun",
    "wof:placetype":"locality"
},
  "geometry": {"coordinates":[128.31417999999999,45.61553],"type":"Point"}
}