{
  "type": "Feature",
  "properties": {
    "gn:admin1_code":"31",
    "gn:asciiname":"Tafeng",
    "gn:country_code":"CN",
    "gn:dem":227,
    "gn:feature_class":"P",
    "gn:feature_code":"PPL",
    "gn:name":"Tafeng",
    "gn:population":0,
    "gn:timezone":"Asia/Shanghai",
    "iso:country":"CN",
    "name:und_x_variant":[
        "\u5854\u4e30",
        "Dafeng"
    ],
    "wof:name":"Tafeng",
    "wof:placetype":"locality"
},
  "geometry": {"coordinates":[109.23999999999999,18.5833],"type":"Point"}
}