{
  "type": "Feature",
  "properties": {
    "gn:admin1_code":"4.0",
    "gn:asciiname":"Nixu",
    "gn:country_code":"CN",
    "gn:dem":12,
    "gn:feature_class":"P",
    "gn:feature_code":"PPL",
    "gn:name":"Nixu",
    "gn:population":0,
    "gn:timezone":"Asia/Shanghai",
    "iso:country":"CN",
    "name:zho_x_preferred":[
        "\u502a\u5729"
    ],
    "wof:name":"Nixu",
    "wof:placetype":"locality"
},
  "geometry": {"coordinates":[118.68300000000001,33.9429],"type":"Point"}
}