{
  "type": "Feature",
  "properties": {
    "gn:admin1_code":"7.0",
    "gn:asciiname":"Pengjiashan",
    "gn:country_code":"CN",
    "gn:dem":817,
    "gn:feature_class":"P",
    "gn:feature_code":"PPL",
    "gn:name":"Pengjiashan",
    "gn:population":0,
    "gn:timezone":"Asia/Shanghai",
    "iso:country":"CN",
    "name:und_x_variant":[
        "\u5f6d\u5bb6\u5c71"
    ],
    "wof:name":"Pengjiashan",
    "wof:placetype":"locality"
},
  "geometry": {"coordinates":[119.91979000000001,27.07919],"type":"Point"}
}