{
  "type": "Feature",
  "properties": {
    "gn:admin1_code":"1.0",
    "gn:asciiname":"Dongyuecun",
    "gn:country_code":"CN",
    "gn:dem":303,
    "gn:feature_class":"P",
    "gn:feature_code":"PPL",
    "gn:name":"Dongyuecun",
    "gn:population":0,
    "gn:timezone":"Asia/Shanghai",
    "iso:country":"CN",
    "name:zho_x_preferred":[
        "\u4e1c\u5cb3\u6751"
    ],
    "wof:name":"Dongyuecun",
    "wof:placetype":"locality"
},
  "geometry": {"coordinates":[115.91912000000001,31.50567],"type":"Point"}
}