{
  "type": "Feature",
  "properties": {
    "gn:admin1_code":"10.0",
    "gn:asciiname":"Shibaiyan",
    "gn:country_code":"CN",
    "gn:dem":156,
    "gn:feature_class":"P",
    "gn:feature_code":"PPL",
    "gn:name":"Shibaiyan",
    "gn:population":0,
    "gn:timezone":"Asia/Shanghai",
    "iso:country":"CN",
    "name:und_x_variant":[
        "\u53f2\u767d\u96c1"
    ],
    "wof:name":"Shibaiyan",
    "wof:placetype":"locality"
},
  "geometry": {"coordinates":[114.10142,38.37948],"type":"Point"}
}