{
  "type": "Feature",
  "properties": {
    "gn:admin1_code":"3.0",
    "gn:asciiname":"Xiagucun",
    "gn:country_code":"CN",
    "gn:dem":127,
    "gn:feature_class":"P",
    "gn:feature_code":"PPL",
    "gn:name":"Xiagucun",
    "gn:population":0,
    "gn:timezone":"Asia/Shanghai",
    "iso:country":"CN",
    "name:und_x_variant":[
        "\u4e0b\u56fa\u6751"
    ],
    "wof:name":"Xiagucun",
    "wof:placetype":"locality"
},
  "geometry": {"coordinates":[115.5442,26.82595],"type":"Point"}
}