{
  "type": "Feature",
  "properties": {
    "gn:admin1_code":"10",
    "gn:asciiname":"Jingtanggou",
    "gn:country_code":"CN",
    "gn:dem":681,
    "gn:feature_class":"P",
    "gn:feature_code":"PPL",
    "gn:name":"Jingtanggou",
    "gn:population":0,
    "gn:timezone":"Asia/Shanghai",
    "iso:country":"CN",
    "name:zho_x_preferred":[
        "\u4eac\u5802\u6c9f"
    ],
    "wof:name":"Jingtanggou",
    "wof:placetype":"locality"
},
  "geometry": {"coordinates":[117.82398000000001,41.31705],"type":"Point"}
}