{
  "type": "Feature",
  "properties": {
    "gn:admin1_code":"18",
    "gn:asciiname":"Longjiachang",
    "gn:country_code":"CN",
    "gn:dem":1192,
    "gn:feature_class":"P",
    "gn:feature_code":"PPL",
    "gn:name":"Longjiachang",
    "gn:population":0,
    "gn:timezone":"Asia/Shanghai",
    "iso:country":"CN",
    "name:zho_x_preferred":[
        "\u9f99\u5bb6\u573a"
    ],
    "wof:name":"Longjiachang",
    "wof:placetype":"locality"
},
  "geometry": {"coordinates":[106.083,27.0185],"type":"Point"}
}