{
  "type": "Feature",
  "properties": {
    "gn:admin1_code":"29.0",
    "gn:asciiname":"Lunaga",
    "gn:country_code":"CN",
    "gn:dem":1063,
    "gn:feature_class":"P",
    "gn:feature_code":"PPL",
    "gn:name":"Lunaga",
    "gn:population":0,
    "gn:timezone":"Asia/Shanghai",
    "iso:country":"CN",
    "name:zho_x_preferred":[
        "\u9c81\u7eb3\u560e"
    ],
    "wof:name":"Lunaga",
    "wof:placetype":"locality"
},
  "geometry": {"coordinates":[102.65900000000001,26.2019],"type":"Point"}
}