{
  "type": "Feature",
  "properties": {
    "gn:admin1_code":"3.0",
    "gn:asciiname":"Cengjia",
    "gn:country_code":"CN",
    "gn:dem":362,
    "gn:feature_class":"P",
    "gn:feature_code":"PPLA4",
    "gn:name":"Cengjia",
    "gn:population":0,
    "gn:timezone":"Asia/Shanghai",
    "iso:country":"CN",
    "name:und_x_variant":[
        "\u66fe\u5bb6"
    ],
    "wof:name":"Cengjia",
    "wof:placetype":"locality"
},
  "geometry": {"coordinates":[115.22255,29.01981],"type":"Point"}
}