{
  "type": "Feature",
  "properties": {
    "gn:admin1_code":"11",
    "gn:asciiname":"Wangjiapan",
    "gn:country_code":"CN",
    "gn:dem":409,
    "gn:feature_class":"P",
    "gn:feature_code":"PPL",
    "gn:name":"Wangjiapan",
    "gn:population":0,
    "gn:timezone":"Asia/Shanghai",
    "iso:country":"CN",
    "name:zho_x_preferred":[
        "\u738b\u5bb6\u76d8"
    ],
    "wof:name":"Wangjiapan",
    "wof:placetype":"locality"
},
  "geometry": {"coordinates":[109.55338,26.88767],"type":"Point"}
}