{
  "type": "Feature",
  "properties": {
    "gn:admin1_code":"29.0",
    "gn:asciiname":"Hemu",
    "gn:country_code":"CN",
    "gn:dem":1018,
    "gn:feature_class":"P",
    "gn:feature_code":"PPL",
    "gn:name":"Hemu",
    "gn:population":0,
    "gn:timezone":"Asia/Shanghai",
    "iso:country":"CN",
    "name:ara_x_preferred":[
        "\u0647\u064a\u0645\u0648 \u0627\u0644\u0628\u0642\u0627\u0644"
    ],
    "name:deu_x_preferred":[
        "Hemu"
    ],
    "name:epo_x_preferred":[
        "Hemu"
    ],
    "name:hin_x_preferred":[
        "\u0939\u0947\u092e\u091a\u0928\u094d\u0926\u094d\u0930 \u0935\u093f\u0915\u094d\u0930\u092e\u093e\u0926\u093f\u0924\u094d\u092f"
    ],
    "name:ita_x_preferred":[
        "Hemu"
    ],
    "name:jpn_x_preferred":[
        "\u30d8\u30fc\u30e0\u30fc"
    ],
    "name:kat_x_preferred":[
        "\u10f0\u10d4\u10db\u10e3"
    ],
    "name:mar_x_preferred":[
        "\u0939\u0947\u092e\u091a\u0902\u0926\u094d\u0930 \u0935\u093f\u0915\u094d\u0930\u092e\u093e\u0926\u093f\u0924\u094d\u092f"
    ],
    "name:nld_x_preferred":[
        "Hemu"
    ],
    "name:pan_x_preferred":[
        "\u0a39\u0a47\u0a2e\u0a42"
    ],
    "name:pnb_x_preferred":[
        "\u06c1\u06cc\u0645\u0648 \u0628\u0642\u0627\u0644"
    ],
    "name:rus_x_preferred":[
        "\u0425\u0435\u043c\u0443"
    ],
    "name:tam_x_preferred":[
        "\u0bb9\u0bc6\u0bae\u0bc1"
    ],
    "name:ukr_x_preferred":[
        "\u0425\u0435\u043c\u0443 \u0412\u0456\u043a\u0440\u0430\u043c\u0430\u0434\u0456\u0442\u044c\u044f"
    ],
    "name:zho_x_preferred":[
        "\u79be\u6728"
    ],
    "wof:name":"Hemu",
    "wof:placetype":"locality"
},
  "geometry": {"coordinates":[98.8339,24.9725],"type":"Point"}
}