{
  "type": "Feature",
  "properties": {
    "gn:admin1_code":"11.0",
    "gn:asciiname":"Baimentou",
    "gn:country_code":"CN",
    "gn:dem":71,
    "gn:feature_class":"P",
    "gn:feature_code":"PPL",
    "gn:name":"Baimentou",
    "gn:population":0,
    "gn:timezone":"Asia/Shanghai",
    "iso:country":"CN",
    "name:zho_x_preferred":[
        "\u767d\u95e8\u5934"
    ],
    "wof:name":"Baimentou",
    "wof:placetype":"locality"
},
  "geometry": {"coordinates":[112.57876,27.89439],"type":"Point"}
}