{
  "type": "Feature",
  "properties": {
    "gn:admin1_code":"3.0",
    "gn:asciiname":"Meishanxia",
    "gn:country_code":"CN",
    "gn:dem":125,
    "gn:feature_class":"P",
    "gn:feature_code":"PPL",
    "gn:name":"Meishanxia",
    "gn:population":0,
    "gn:timezone":"Asia/Shanghai",
    "iso:country":"CN",
    "name:zho_x_preferred":[
        "\u6885\u5c71\u4e0b"
    ],
    "wof:name":"Meishanxia",
    "wof:placetype":"locality"
},
  "geometry": {"coordinates":[114.592,29.0632],"type":"Point"}
}