{
  "type": "Feature",
  "properties": {
    "gn:admin1_code":"3.0",
    "gn:asciiname":"Shadui",
    "gn:country_code":"CN",
    "gn:dem":250,
    "gn:feature_class":"P",
    "gn:feature_code":"PPL",
    "gn:name":"Shadui",
    "gn:population":0,
    "gn:timezone":"Asia/Shanghai",
    "iso:country":"CN",
    "name:und_x_variant":[
        "\u6c99\u5806"
    ],
    "wof:name":"Shadui",
    "wof:placetype":"locality"
},
  "geometry": {"coordinates":[115.77495999999999,25.74744],"type":"Point"}
}