{
  "type": "Feature",
  "properties": {
    "gn:admin1_code":"11",
    "gn:asciiname":"Tianjiawan",
    "gn:country_code":"CN",
    "gn:dem":342,
    "gn:feature_class":"P",
    "gn:feature_code":"PPL",
    "gn:name":"Tianjiawan",
    "gn:population":0,
    "gn:timezone":"Asia/Shanghai",
    "iso:country":"CN",
    "name:und_x_variant":[
        "\u7530\u5bb6\u6e7e"
    ],
    "wof:name":"Tianjiawan",
    "wof:placetype":"locality"
},
  "geometry": {"coordinates":[111.03100999999999,29.23275],"type":"Point"}
}