{
  "type": "Feature",
  "properties": {
    "gn:admin1_code":"1.0",
    "gn:asciiname":"Xuzhaicun",
    "gn:country_code":"CN",
    "gn:dem":31,
    "gn:feature_class":"P",
    "gn:feature_code":"PPL",
    "gn:name":"Xuzhaicun",
    "gn:population":0,
    "gn:timezone":"Asia/Shanghai",
    "iso:country":"CN",
    "name:zho_x_preferred":[
        "\u8bb8\u5be8\u6751"
    ],
    "wof:name":"Xuzhaicun",
    "wof:placetype":"locality"
},
  "geometry": {"coordinates":[115.7735,32.73767],"type":"Point"}
}