{
  "type": "Feature",
  "properties": {
    "gn:admin1_code":"1.0",
    "gn:asciiname":"Wangjinkeng",
    "gn:country_code":"CN",
    "gn:dem":301,
    "gn:feature_class":"P",
    "gn:feature_code":"PPL",
    "gn:name":"Wangjinkeng",
    "gn:population":0,
    "gn:timezone":"Asia/Shanghai",
    "iso:country":"CN",
    "name:zho_x_preferred":[
        "\u738b\u8fdb\u5751"
    ],
    "wof:name":"Wangjinkeng",
    "wof:placetype":"locality"
},
  "geometry": {"coordinates":[118.3603,30.0573],"type":"Point"}
}