{
  "type": "Feature",
  "properties": {
    "gn:admin1_code":"26",
    "gn:asciiname":"Ximazhai",
    "gn:country_code":"CN",
    "gn:dem":390,
    "gn:feature_class":"P",
    "gn:feature_code":"PPL",
    "gn:name":"Ximazhai",
    "gn:population":0,
    "gn:timezone":"Asia/Shanghai",
    "iso:country":"CN",
    "name:zho_x_preferred":[
        "\u897f\u9a6c\u5be8"
    ],
    "wof:name":"Ximazhai",
    "wof:placetype":"locality"
},
  "geometry": {"coordinates":[108.87006,34.29675],"type":"Point"}
}