{
  "type": "Feature",
  "properties": {
    "gn:admin1_code":"10",
    "gn:asciiname":"Tangsanying",
    "gn:cc2":"CN",
    "gn:country_code":"CN",
    "gn:dem":663,
    "gn:feature_class":"P",
    "gn:feature_code":"PPL",
    "gn:name":"Tangsanying",
    "gn:population":0,
    "gn:timezone":"Asia/Shanghai",
    "iso:country":"CN",
    "name:und_x_variant":[
        "T\u2019ang-shan-ying-tzu",
        "Tangsanying"
    ],
    "wof:name":"Tangsanying",
    "wof:placetype":"locality"
},
  "geometry": {"coordinates":[117.77222,41.60028],"type":"Point"}
}