{
  "type": "Feature",
  "properties": {
    "gn:admin1_code":"14.0",
    "gn:asciiname":"Chuqiong",
    "gn:country_code":"CN",
    "gn:dem":4460,
    "gn:feature_class":"P",
    "gn:feature_code":"PPL",
    "gn:name":"Chuqiong",
    "gn:population":0,
    "gn:timezone":"Asia/Urumqi",
    "iso:country":"CN",
    "name:zho_x_preferred":[
        "\u9664\u7a77"
    ],
    "wof:name":"Chuqiong",
    "wof:placetype":"locality"
},
  "geometry": {"coordinates":[88.11660000000001,28.2732],"type":"Point"}
}