{
  "type": "Feature",
  "properties": {
    "gn:admin1_code":"16.0",
    "gn:asciiname":"Qiaobu",
    "gn:country_code":"CN",
    "gn:dem":202,
    "gn:feature_class":"P",
    "gn:feature_code":"PPL",
    "gn:name":"Qiaobu",
    "gn:population":0,
    "gn:timezone":"Asia/Shanghai",
    "iso:country":"CN",
    "name:zho_x_preferred":[
        "\u6865\u535c"
    ],
    "wof:name":"Qiaobu",
    "wof:placetype":"locality"
},
  "geometry": {"coordinates":[108.07899999999999,24.7027],"type":"Point"}
}