{
  "type": "Feature",
  "properties": {
    "gn:admin1_code":"4.0",
    "gn:asciiname":"Chefushancun",
    "gn:country_code":"CN",
    "gn:dem":27,
    "gn:feature_class":"P",
    "gn:feature_code":"PPL",
    "gn:name":"Chefushancun",
    "gn:population":0,
    "gn:timezone":"Asia/Shanghai",
    "iso:country":"CN",
    "name:zho_x_preferred":[
        "\u8f66\u8f90\u5c71\u6751"
    ],
    "wof:name":"Chefushancun",
    "wof:placetype":"locality"
},
  "geometry": {"coordinates":[117.75189,34.47711],"type":"Point"}
}