{
  "type": "Feature",
  "properties": {
    "gn:admin1_code":"14.0",
    "gn:asciiname":"Diwi",
    "gn:country_code":"CN",
    "gn:dem":5117,
    "gn:feature_class":"P",
    "gn:feature_code":"PPL",
    "gn:name":"Diwi",
    "gn:population":0,
    "gn:timezone":"Asia/Shanghai",
    "iso:country":"CN",
    "name:und_x_variant":[
        "Diwucun",
        "Diwi"
    ],
    "name:zho_x_preferred":[
        "\u8fea\u543e\u6751"
    ],
    "name:zho_x_variant":[
        "\u8fea\u543e"
    ],
    "wof:name":"Diwi",
    "wof:placetype":"locality"
},
  "geometry": {"coordinates":[82.80046,32.21283],"type":"Point"}
}