{
  "type": "Feature",
  "properties": {
    "gn:admin1_code":"12.0",
    "gn:asciiname":"Yexuejiawan",
    "gn:country_code":"CN",
    "gn:dem":32,
    "gn:feature_class":"P",
    "gn:feature_code":"PPL",
    "gn:name":"Yexuejiawan",
    "gn:population":0,
    "gn:timezone":"Asia/Shanghai",
    "iso:country":"CN",
    "name:und_x_variant":[
        "\u53f6\u96ea\u5bb6\u5846"
    ],
    "wof:name":"Yexuejiawan",
    "wof:placetype":"locality"
},
  "geometry": {"coordinates":[114.61218,30.73462],"type":"Point"}
}