{
  "type": "Feature",
  "properties": {
    "gn:admin1_code":"30",
    "gn:asciiname":"Nihezai",
    "gn:country_code":"CN",
    "gn:dem":20,
    "gn:feature_class":"P",
    "gn:feature_code":"PPL",
    "gn:name":"Nihezai",
    "gn:population":0,
    "gn:timezone":"Asia/Shanghai",
    "iso:country":"CN",
    "name:zho_x_preferred":[
        "\u576d\u6cb3\u4ed4"
    ],
    "wof:name":"Nihezai",
    "wof:placetype":"locality"
},
  "geometry": {"coordinates":[111.59220000000001,21.68755],"type":"Point"}
}