{
  "type": "Feature",
  "properties": {
    "gn:admin1_code":"32.0",
    "gn:asciiname":"Maliuwan",
    "gn:country_code":"CN",
    "gn:dem":814,
    "gn:feature_class":"P",
    "gn:feature_code":"PPL",
    "gn:name":"Maliuwan",
    "gn:population":0,
    "gn:timezone":"Asia/Shanghai",
    "iso:country":"CN",
    "name:zho_x_preferred":[
        "\u9ebb\u67f3\u6e7e"
    ],
    "wof:name":"Maliuwan",
    "wof:placetype":"locality"
},
  "geometry": {"coordinates":[103.68241,29.24182],"type":"Point"}
}