{
  "type": "Feature",
  "properties": {
    "gn:admin1_code":"26",
    "gn:asciiname":"Zhuangzitou",
    "gn:country_code":"CN",
    "gn:dem":1032,
    "gn:feature_class":"P",
    "gn:feature_code":"PPL",
    "gn:name":"Zhuangzitou",
    "gn:population":0,
    "gn:timezone":"Asia/Shanghai",
    "iso:country":"CN",
    "name:und_x_variant":[
        "\u5e84\u5b50\u5934"
    ],
    "name:zho_x_preferred":[
        "\u5e84\u5b50\u5934"
    ],
    "wof:name":"Zhuangzitou",
    "wof:placetype":"locality"
},
  "geometry": {"coordinates":[108.40167,34.86778],"type":"Point"}
}