{
  "type": "Feature",
  "properties": {
    "gn:admin1_code":"29.0",
    "gn:asciiname":"Nanluan",
    "gn:country_code":"CN",
    "gn:dem":819,
    "gn:feature_class":"P",
    "gn:feature_code":"PPL",
    "gn:name":"Nanluan",
    "gn:population":0,
    "gn:timezone":"Asia/Shanghai",
    "iso:country":"CN",
    "name:zho_x_preferred":[
        "\u5357\u5ce6"
    ],
    "wof:name":"Nanluan",
    "wof:placetype":"locality"
},
  "geometry": {"coordinates":[97.9134,24.6879],"type":"Point"}
}