{
  "type": "Feature",
  "properties": {
    "gn:admin1_code":"18",
    "gn:asciiname":"Zhelong",
    "gn:country_code":"CN",
    "gn:dem":966,
    "gn:feature_class":"P",
    "gn:feature_code":"PPL",
    "gn:name":"Zhelong",
    "gn:population":0,
    "gn:timezone":"Asia/Shanghai",
    "iso:country":"CN",
    "name:zho_x_preferred":[
        "\u8005\u9f99"
    ],
    "wof:name":"Zhelong",
    "wof:placetype":"locality"
},
  "geometry": {"coordinates":[106.05800000000001,25.6508],"type":"Point"}
}