{
  "type": "Feature",
  "properties": {
    "gn:admin1_code":"16.0",
    "gn:asciiname":"Gou'erling",
    "gn:country_code":"CN",
    "gn:dem":486,
    "gn:feature_class":"P",
    "gn:feature_code":"PPL",
    "gn:name":"Gou\u2019erling",
    "gn:population":0,
    "gn:timezone":"Asia/Shanghai",
    "iso:country":"CN",
    "name:und_x_variant":[
        "Gou\u2019erling"
    ],
    "name:zho_x_preferred":[
        "\u72d7\u8033\u5cad"
    ],
    "wof:name":"Gou'erling",
    "wof:placetype":"locality"
},
  "geometry": {"coordinates":[111.63800000000001,24.5022],"type":"Point"}
}