{
  "type": "Feature",
  "properties": {
    "gn:admin1_code":"11.0",
    "gn:asciiname":"Zhaozaimao",
    "gn:country_code":"CN",
    "gn:dem":40,
    "gn:feature_class":"P",
    "gn:feature_code":"PPL",
    "gn:name":"Zhaozaimao",
    "gn:population":0,
    "gn:timezone":"Asia/Shanghai",
    "iso:country":"CN",
    "name:zho_x_preferred":[
        "\u8d75\u518d\u8302"
    ],
    "wof:name":"Zhaozaimao",
    "wof:placetype":"locality"
},
  "geometry": {"coordinates":[113.12524000000001,29.04719],"type":"Point"}
}