{
  "type": "Feature",
  "properties": {
    "gn:admin1_code":"30.0",
    "gn:asciiname":"Liyuping",
    "gn:country_code":"CN",
    "gn:dem":445,
    "gn:feature_class":"P",
    "gn:feature_code":"PPL",
    "gn:name":"Liyuping",
    "gn:population":0,
    "gn:timezone":"Asia/Shanghai",
    "iso:country":"CN",
    "name:zho_x_preferred":[
        "\u9ca4\u9c7c\u576a"
    ],
    "wof:name":"Liyuping",
    "wof:placetype":"locality"
},
  "geometry": {"coordinates":[111.67773,23.06757],"type":"Point"}
}