{
  "type": "Feature",
  "properties": {
    "gn:admin1_code":"20.0",
    "gn:asciiname":"Chaoyanggang",
    "gn:country_code":"CN",
    "gn:dem":334,
    "gn:feature_class":"P",
    "gn:feature_code":"PPL",
    "gn:name":"Chaoyanggang",
    "gn:population":0,
    "gn:timezone":"Asia/Shanghai",
    "iso:country":"CN",
    "name:zho_x_preferred":[
        "\u671d\u9633\u5c97"
    ],
    "wof:name":"Chaoyanggang",
    "wof:placetype":"locality"
},
  "geometry": {"coordinates":[122.82590999999999,47.89855],"type":"Point"}
}