{
  "type": "Feature",
  "properties": {
    "gn:admin1_code":"32.0",
    "gn:asciiname":"Yiliucun",
    "gn:country_code":"CN",
    "gn:dem":3599,
    "gn:feature_class":"P",
    "gn:feature_code":"PPL",
    "gn:name":"Yiliucun",
    "gn:population":0,
    "gn:timezone":"Asia/Shanghai",
    "iso:country":"CN",
    "name:zho_x_preferred":[
        "\u4f9d\u516d\u6751"
    ],
    "wof:name":"Yiliucun",
    "wof:placetype":"locality"
},
  "geometry": {"coordinates":[100.292,30.8922],"type":"Point"}
}