{
  "type": "Feature",
  "properties": {
    "gn:admin1_code":"11.0",
    "gn:asciiname":"Dangtianqiu",
    "gn:country_code":"CN",
    "gn:dem":396,
    "gn:feature_class":"P",
    "gn:feature_code":"PPL",
    "gn:name":"Dangtianqiu",
    "gn:population":0,
    "gn:timezone":"Asia/Shanghai",
    "iso:country":"CN",
    "name:zho_x_preferred":[
        "\u5f53\u5929\u5775"
    ],
    "name:zho_x_variant":[
        "\u5f53\u5929\u4e18"
    ],
    "wof:name":"Dangtianqiu",
    "wof:placetype":"locality"
},
  "geometry": {"coordinates":[113.72836,26.88746],"type":"Point"}
}