{
  "type": "Feature",
  "properties": {
    "gn:admin1_code":"8.0",
    "gn:asciiname":"Minlicun",
    "gn:country_code":"CN",
    "gn:dem":249,
    "gn:feature_class":"P",
    "gn:feature_code":"PPL",
    "gn:name":"Minlicun",
    "gn:population":0,
    "gn:timezone":"Asia/Shanghai",
    "iso:country":"CN",
    "name:zho_x_preferred":[
        "\u6c11\u529b\u6751"
    ],
    "wof:name":"Minlicun",
    "wof:placetype":"locality"
},
  "geometry": {"coordinates":[125.54386,47.75759],"type":"Point"}
}