{
  "type": "Feature",
  "properties": {
    "gn:admin1_code":"16",
    "gn:asciiname":"Chuanshanyuan",
    "gn:country_code":"CN",
    "gn:dem":148,
    "gn:feature_class":"P",
    "gn:feature_code":"PPL",
    "gn:name":"Chuanshanyuan",
    "gn:population":0,
    "gn:timezone":"Asia/Shanghai",
    "iso:country":"CN",
    "name:zho_x_preferred":[
        "\u7a7f\u5c71\u56ed"
    ],
    "wof:name":"Chuanshanyuan",
    "wof:placetype":"locality"
},
  "geometry": {"coordinates":[110.297,25.2511],"type":"Point"}
}