{
  "type": "Feature",
  "properties": {
    "gn:admin1_code":"25",
    "gn:asciiname":"Dongmajialin",
    "gn:country_code":"CN",
    "gn:dem":177,
    "gn:feature_class":"P",
    "gn:feature_code":"PPL",
    "gn:name":"Dongmajialin",
    "gn:population":0,
    "gn:timezone":"Asia/Shanghai",
    "iso:country":"CN",
    "name:zho_x_preferred":[
        "\u4e1c\u9a6c\u5bb6\u6797"
    ],
    "wof:name":"Dongmajialin",
    "wof:placetype":"locality"
},
  "geometry": {"coordinates":[117.581,35.7099],"type":"Point"}
}