{
  "type": "Feature",
  "properties": {
    "gn:admin1_code":"29.0",
    "gn:asciiname":"Sanjiaoping",
    "gn:country_code":"CN",
    "gn:dem":1706,
    "gn:feature_class":"P",
    "gn:feature_code":"PPL",
    "gn:name":"Sanjiaoping",
    "gn:population":0,
    "gn:timezone":"Asia/Shanghai",
    "iso:country":"CN",
    "name:zho_x_preferred":[
        "\u4e09\u89d2\u576a"
    ],
    "wof:name":"Sanjiaoping",
    "wof:placetype":"locality"
},
  "geometry": {"coordinates":[100.313,25.1823],"type":"Point"}
}