{
  "type": "Feature",
  "properties": {
    "gn:admin1_code":"26.0",
    "gn:asciiname":"Badouchacun",
    "gn:country_code":"CN",
    "gn:dem":943,
    "gn:feature_class":"P",
    "gn:feature_code":"PPL",
    "gn:name":"Badouchacun",
    "gn:population":0,
    "gn:timezone":"Asia/Shanghai",
    "iso:country":"CN",
    "name:zho_x_preferred":[
        "\u516b\u6597\u5c94\u6751"
    ],
    "wof:name":"Badouchacun",
    "wof:placetype":"locality"
},
  "geometry": {"coordinates":[110.08781999999999,37.02004],"type":"Point"}
}