{
  "type": "Feature",
  "properties": {
    "gn:admin1_code":"9.0",
    "gn:asciiname":"Fanshengang",
    "gn:country_code":"CN",
    "gn:dem":62,
    "gn:feature_class":"P",
    "gn:feature_code":"PPL",
    "gn:name":"Fanshengang",
    "gn:population":0,
    "gn:timezone":"Asia/Shanghai",
    "iso:country":"CN",
    "name:zho_x_preferred":[
        "\u7ffb\u8eab\u5c97"
    ],
    "wof:name":"Fanshengang",
    "wof:placetype":"locality"
},
  "geometry": {"coordinates":[115.16764000000001,31.98823],"type":"Point"}
}