{
  "type": "Feature",
  "properties": {
    "gn:admin1_code":"32.0",
    "gn:asciiname":"Riduo",
    "gn:country_code":"CN",
    "gn:dem":2936,
    "gn:feature_class":"P",
    "gn:feature_code":"PPL",
    "gn:name":"Riduo",
    "gn:population":0,
    "gn:timezone":"Asia/Shanghai",
    "iso:country":"CN",
    "name:zho_x_preferred":[
        "\u65e5\u591a"
    ],
    "wof:name":"Riduo",
    "wof:placetype":"locality"
},
  "geometry": {"coordinates":[103.02500000000001,32.0767],"type":"Point"}
}