{
  "type": "Feature",
  "properties": {
    "gn:admin1_code":"16",
    "gn:asciiname":"Congping",
    "gn:country_code":"CN",
    "gn:dem":663,
    "gn:feature_class":"P",
    "gn:feature_code":"PPL",
    "gn:name":"Congping",
    "gn:population":0,
    "gn:timezone":"Asia/Shanghai",
    "iso:country":"CN",
    "name:zho_x_preferred":[
        "\u8471\u576a"
    ],
    "wof:name":"Congping",
    "wof:placetype":"locality"
},
  "geometry": {"coordinates":[110.349,25.9324],"type":"Point"}
}