{
  "type": "Feature",
  "properties": {
    "gn:admin1_code":"15.0",
    "gn:asciiname":"Laogou",
    "gn:country_code":"CN",
    "gn:dem":2063,
    "gn:feature_class":"P",
    "gn:feature_code":"PPL",
    "gn:name":"Laogou",
    "gn:population":0,
    "gn:timezone":"Asia/Shanghai",
    "iso:country":"CN",
    "name:zho_x_preferred":[
        "\u8001\u6c9f"
    ],
    "wof:name":"Laogou",
    "wof:placetype":"locality"
},
  "geometry": {"coordinates":[104.19696,33.91392],"type":"Point"}
}