{
  "type": "Feature",
  "properties": {
    "gn:admin1_code":"26.0",
    "gn:asciiname":"Xiaotanze",
    "gn:country_code":"CN",
    "gn:dem":1320,
    "gn:feature_class":"P",
    "gn:feature_code":"PPL",
    "gn:name":"Xiaotanze",
    "gn:population":0,
    "gn:timezone":"Asia/Shanghai",
    "iso:country":"CN",
    "name:zho_x_preferred":[
        "\u5c0f\u6ee9\u5219"
    ],
    "wof:name":"Xiaotanze",
    "wof:placetype":"locality"
},
  "geometry": {"coordinates":[108.48067,37.65162],"type":"Point"}
}