{
  "type": "Feature",
  "properties": {
    "gn:admin1_code":"18.0",
    "gn:asciiname":"Lantianwan",
    "gn:country_code":"CN",
    "gn:dem":1131,
    "gn:feature_class":"P",
    "gn:feature_code":"PPL",
    "gn:name":"Lantianwan",
    "gn:population":0,
    "gn:timezone":"Asia/Shanghai",
    "iso:country":"CN",
    "name:zho_x_preferred":[
        "\u70c2\u7530\u6e7e"
    ],
    "wof:name":"Lantianwan",
    "wof:placetype":"locality"
},
  "geometry": {"coordinates":[107.18000000000001,26.7549],"type":"Point"}
}