{
  "type": "Feature",
  "properties": {
    "gn:admin1_code":"10",
    "gn:asciiname":"Muchang Daliangdi",
    "gn:country_code":"CN",
    "gn:dem":1370,
    "gn:feature_class":"P",
    "gn:feature_code":"PPL",
    "gn:name":"Muchang Daliangdi",
    "gn:population":0,
    "gn:timezone":"Asia/Shanghai",
    "iso:country":"CN",
    "name:zho_x_preferred":[
        "\u7267\u573a\u5927\u6881\u5e95"
    ],
    "wof:name":"Muchang Daliangdi",
    "wof:placetype":"locality"
},
  "geometry": {"coordinates":[115.88777,41.8811],"type":"Point"}
}