{
  "type": "Feature",
  "properties": {
    "gn:admin1_code":"29.0",
    "gn:asciiname":"Nongke",
    "gn:country_code":"CN",
    "gn:dem":1534,
    "gn:feature_class":"P",
    "gn:feature_code":"PPL",
    "gn:name":"Nongke",
    "gn:population":0,
    "gn:timezone":"Asia/Shanghai",
    "iso:country":"CN",
    "name:zho_x_preferred":[
        "\u519c\u514b"
    ],
    "wof:name":"Nongke",
    "wof:placetype":"locality"
},
  "geometry": {"coordinates":[99.5016,23.3098],"type":"Point"}
}