{
  "type": "Feature",
  "properties": {
    "gn:admin1_code":"19.0",
    "gn:asciiname":"Xiawanzi",
    "gn:country_code":"CN",
    "gn:dem":218,
    "gn:feature_class":"P",
    "gn:feature_code":"PPL",
    "gn:name":"Xiawanzi",
    "gn:population":0,
    "gn:timezone":"Asia/Shanghai",
    "iso:country":"CN",
    "name:zho_x_preferred":[
        "\u4e0b\u6e7e\u5b50"
    ],
    "wof:name":"Xiawanzi",
    "wof:placetype":"locality"
},
  "geometry": {"coordinates":[120.837,41.9322],"type":"Point"}
}