{
  "type": "Feature",
  "properties": {
    "gn:admin1_code":"20",
    "gn:asciiname":"Tung-san-yen-ching",
    "gn:country_code":"CN",
    "gn:dem":619,
    "gn:feature_class":"P",
    "gn:feature_code":"PPL",
    "gn:name":"Tung-san-yen-ching",
    "gn:population":0,
    "gn:timezone":"Asia/Shanghai",
    "iso:country":"CN",
    "wof:name":"Tung-san-yen-ching",
    "wof:placetype":"locality"
},
  "geometry": {"coordinates":[118.99583,42.20389],"type":"Point"}
}