{
  "type": "Feature",
  "properties": {
    "gn:admin1_code":"02",
    "gn:asciiname":"Zheng'aocun",
    "gn:country_code":"CN",
    "gn:dem":10,
    "gn:feature_class":"P",
    "gn:feature_code":"PPL",
    "gn:name":"Zheng\u2019aocun",
    "gn:population":0,
    "gn:timezone":"Asia/Shanghai",
    "iso:country":"CN",
    "name:und_x_variant":[
        "Cheng-ao",
        "Zheng\u2019aocun"
    ],
    "name:zho_x_preferred":[
        "\u90d1\u5c99"
    ],
    "name:zho_x_variant":[
        "Zheng\u2019ao",
        "\u90d1\u5c99\u6751"
    ],
    "wof:name":"Zheng'aocun",
    "wof:placetype":"locality"
},
  "geometry": {"coordinates":[120.76031999999999,27.86529],"type":"Point"}
}