{
  "type": "Feature",
  "properties": {
    "gn:admin1_code":"14",
    "gn:asciiname":"Duen'gyoi",
    "gn:country_code":"CN",
    "gn:dem":4740,
    "gn:feature_class":"P",
    "gn:feature_code":"PPL",
    "gn:name":"D\u00fcn'gyoi",
    "gn:population":0,
    "gn:timezone":"Asia/Urumqi",
    "iso:country":"CN",
    "name:bod_x_preferred":[
        "\u0f58\u0f51\u0f74\u0f53\u0f0b\u0f66\u0f90\u0fb1\u0f7c\u0f51"
    ],
    "wof:name":"Duen'gyoi",
    "wof:placetype":"locality"
},
  "geometry": {"coordinates":[92.75275999999999,29.00454],"type":"Point"}
}