{
  "type": "Feature",
  "properties": {
    "gn:admin1_code":"30",
    "gn:asciiname":"Zhuyutang",
    "gn:country_code":"CN",
    "gn:dem":588,
    "gn:feature_class":"P",
    "gn:feature_code":"PPL",
    "gn:name":"Zhuyutang",
    "gn:population":0,
    "gn:timezone":"Asia/Shanghai",
    "iso:country":"CN",
    "name:und_x_variant":[
        "\u73e0\u7389\u5858"
    ],
    "wof:name":"Zhuyutang",
    "wof:placetype":"locality"
},
  "geometry": {"coordinates":[112.49028,24.67139],"type":"Point"}
}