{
  "type": "Feature",
  "properties": {
    "gn:admin1_code":"26.0",
    "gn:asciiname":"Chengjiazhifangcun",
    "gn:country_code":"CN",
    "gn:dem":1075,
    "gn:feature_class":"P",
    "gn:feature_code":"PPL",
    "gn:name":"Chengjiazhifangcun",
    "gn:population":0,
    "gn:timezone":"Asia/Shanghai",
    "iso:country":"CN",
    "name:zho_x_preferred":[
        "\u7a0b\u5bb6\u7eb8\u574a\u6751"
    ],
    "wof:name":"Chengjiazhifangcun",
    "wof:placetype":"locality"
},
  "geometry": {"coordinates":[109.05571999999999,36.44876],"type":"Point"}
}