{
  "type": "Feature",
  "properties": {
    "gn:admin1_code":"30.0",
    "gn:asciiname":"Shenwan",
    "gn:country_code":"CN",
    "gn:dem":11,
    "gn:feature_class":"P",
    "gn:feature_code":"PPL",
    "gn:name":"Shenwan",
    "gn:population":0,
    "gn:timezone":"Asia/Shanghai",
    "iso:country":"CN",
    "name:fas_x_preferred":[
        "\u0634\u0646\u0648\u0627\u0646"
    ],
    "name:swe_x_preferred":[
        "Shenwan"
    ],
    "name:zho_x_preferred":[
        "\u6df1\u6e7e"
    ],
    "name:zho_x_variant":[
        "\u795e\u6e7e\u9547"
    ],
    "wof:name":"Shenwan",
    "wof:placetype":"locality"
},
  "geometry": {"coordinates":[113.57285,22.76613],"type":"Point"}
}