{
  "type": "Feature",
  "properties": {
    "gn:admin1_code":"15.0",
    "gn:asciiname":"Shizuizi",
    "gn:country_code":"CN",
    "gn:dem":1222,
    "gn:feature_class":"P",
    "gn:feature_code":"PPL",
    "gn:name":"Shizuizi",
    "gn:population":0,
    "gn:timezone":"Asia/Shanghai",
    "iso:country":"CN",
    "name:zho_x_preferred":[
        "\u77f3\u5480\u5b50"
    ],
    "wof:name":"Shizuizi",
    "wof:placetype":"locality"
},
  "geometry": {"coordinates":[108.035,36.2619],"type":"Point"}
}