{
  "type": "Feature",
  "properties": {
    "gn:admin1_code":"15.0",
    "gn:asciiname":"Mo'erping",
    "gn:country_code":"CN",
    "gn:dem":1875,
    "gn:feature_class":"P",
    "gn:feature_code":"PPL",
    "gn:name":"Mo\u2019erping",
    "gn:population":0,
    "gn:timezone":"Asia/Shanghai",
    "iso:country":"CN",
    "name:zho_x_preferred":[
        "Mo\u2019erping"
    ],
    "name:zho_x_variant":[
        "\u78e8\u513f\u576a"
    ],
    "wof:name":"Mo'erping",
    "wof:placetype":"locality"
},
  "geometry": {"coordinates":[104.37858,33.68759],"type":"Point"}
}