{
  "type": "Feature",
  "properties": {
    "gn:admin1_code":"13",
    "gn:asciiname":"Weijiaquan",
    "gn:country_code":"CN",
    "gn:dem":883,
    "gn:feature_class":"P",
    "gn:feature_code":"PPL",
    "gn:name":"Weijiaquan",
    "gn:population":0,
    "gn:timezone":"Asia/Urumqi",
    "iso:country":"CN",
    "name:zho_x_preferred":[
        "\u9b4f\u5bb6\u6cc9"
    ],
    "wof:name":"Weijiaquan",
    "wof:placetype":"locality"
},
  "geometry": {"coordinates":[87.93393,44.0092],"type":"Point"}
}