{
  "type": "Feature",
  "properties": {
    "gn:admin1_code":"2.0",
    "gn:asciiname":"Dingshan",
    "gn:country_code":"CN",
    "gn:dem":13,
    "gn:feature_class":"P",
    "gn:feature_code":"PPL",
    "gn:name":"Dingshan",
    "gn:population":0,
    "gn:timezone":"Asia/Shanghai",
    "iso:country":"CN",
    "name:und_x_variant":[
        "\u5b9a\u5c71"
    ],
    "wof:name":"Dingshan",
    "wof:placetype":"locality"
},
  "geometry": {"coordinates":[120.19459999999999,30.11871],"type":"Point"}
}