{
  "type": "Feature",
  "properties": {
    "gn:admin1_code":"25.0",
    "gn:asciiname":"Houheshancun",
    "gn:country_code":"CN",
    "gn:dem":108,
    "gn:feature_class":"P",
    "gn:feature_code":"PPL",
    "gn:name":"Houheshancun",
    "gn:population":0,
    "gn:timezone":"Asia/Shanghai",
    "iso:country":"CN",
    "name:zho_x_preferred":[
        "\u540e\u6cb3\u5c71\u6751"
    ],
    "wof:name":"Houheshancun",
    "wof:placetype":"locality"
},
  "geometry": {"coordinates":[120.92274,36.80027000000001],"type":"Point"}
}