{
  "type": "Feature",
  "properties": {
    "gn:admin1_code":"30.0",
    "gn:asciiname":"Huangnitang",
    "gn:country_code":"CN",
    "gn:dem":80,
    "gn:feature_class":"P",
    "gn:feature_code":"PPL",
    "gn:name":"Huangnitang",
    "gn:population":0,
    "gn:timezone":"Asia/Shanghai",
    "iso:country":"CN",
    "name:zho_x_preferred":[
        "\u9ec4\u576d\u5858"
    ],
    "wof:name":"Huangnitang",
    "wof:placetype":"locality"
},
  "geometry": {"coordinates":[114.24066999999999,22.86009],"type":"Point"}
}