{
  "type": "Feature",
  "properties": {
    "gn:admin1_code":"11.0",
    "gn:asciiname":"Zhukenglong",
    "gn:country_code":"CN",
    "gn:dem":684,
    "gn:feature_class":"P",
    "gn:feature_code":"PPL",
    "gn:name":"Zhukenglong",
    "gn:population":0,
    "gn:timezone":"Asia/Shanghai",
    "iso:country":"CN",
    "name:zho_x_preferred":[
        "\u7af9\u5751\u5785"
    ],
    "wof:name":"Zhukenglong",
    "wof:placetype":"locality"
},
  "geometry": {"coordinates":[113.85826000000002,25.88069],"type":"Point"}
}