{
  "type": "Feature",
  "properties": {
    "gn:admin1_code":"29.0",
    "gn:asciiname":"Xiaoshiqiao",
    "gn:country_code":"CN",
    "gn:dem":1516,
    "gn:feature_class":"P",
    "gn:feature_code":"PPL",
    "gn:name":"Xiaoshiqiao",
    "gn:population":0,
    "gn:timezone":"Asia/Shanghai",
    "iso:country":"CN",
    "name:zho_x_preferred":[
        "\u5c0f\u77f3\u6865"
    ],
    "wof:name":"Xiaoshiqiao",
    "wof:placetype":"locality"
},
  "geometry": {"coordinates":[103.577,26.9764],"type":"Point"}
}