{
  "type": "Feature",
  "properties": {
    "gn:admin1_code":"11.0",
    "gn:asciiname":"Maguannao",
    "gn:country_code":"CN",
    "gn:dem":491,
    "gn:feature_class":"P",
    "gn:feature_code":"PPL",
    "gn:name":"Maguannao",
    "gn:population":0,
    "gn:timezone":"Asia/Shanghai",
    "iso:country":"CN",
    "name:zho_x_preferred":[
        "Maguannao"
    ],
    "name:zho_x_variant":[
        "\u9a6c\u5173\u8111"
    ],
    "wof:name":"Maguannao",
    "wof:placetype":"locality"
},
  "geometry": {"coordinates":[110.61578,28.9379],"type":"Point"}
}