{
  "type": "Feature",
  "properties": {
    "gn:admin1_code":"16.0",
    "gn:asciiname":"Bamei",
    "gn:country_code":"CN",
    "gn:dem":500,
    "gn:feature_class":"P",
    "gn:feature_code":"PPL",
    "gn:name":"Bamei",
    "gn:population":0,
    "gn:timezone":"Asia/Shanghai",
    "iso:country":"CN",
    "name:zho_x_preferred":[
        "\u628a\u7709"
    ],
    "name:zho_x_variant":[
        "\u575d\u7f8e\u9547"
    ],
    "wof:name":"Bamei",
    "wof:placetype":"locality"
},
  "geometry": {"coordinates":[107.092,23.126],"type":"Point"}
}