{
  "type": "Feature",
  "properties": {
    "gn:admin1_code":"32.0",
    "gn:asciiname":"Changtanhe",
    "gn:country_code":"CN",
    "gn:dem":442,
    "gn:feature_class":"P",
    "gn:feature_code":"PPL",
    "gn:name":"Changtanhe",
    "gn:population":0,
    "gn:timezone":"Asia/Shanghai",
    "iso:country":"CN",
    "name:zho_x_preferred":[
        "\u957f\u6ee9\u6cb3"
    ],
    "wof:name":"Changtanhe",
    "wof:placetype":"locality"
},
  "geometry": {"coordinates":[107.23699999999999,31.0097],"type":"Point"}
}