{
  "type": "Feature",
  "properties": {
    "gn:admin1_code":"11.0",
    "gn:asciiname":"Zhaoxi",
    "gn:country_code":"CN",
    "gn:dem":322,
    "gn:feature_class":"P",
    "gn:feature_code":"PPL",
    "gn:name":"Zhaoxi",
    "gn:population":0,
    "gn:timezone":"Asia/Shanghai",
    "iso:country":"CN",
    "name:zho_x_preferred":[
        "\u62db\u6eaa"
    ],
    "wof:name":"Zhaoxi",
    "wof:placetype":"locality"
},
  "geometry": {"coordinates":[110.28343,27.40532],"type":"Point"}
}