{
  "type": "Feature",
  "properties": {
    "gn:admin1_code":"14.0",
    "gn:asciiname":"Baisang",
    "gn:country_code":"CN",
    "gn:dem":4558,
    "gn:feature_class":"P",
    "gn:feature_code":"PPL",
    "gn:name":"Baisang",
    "gn:population":0,
    "gn:timezone":"Asia/Urumqi",
    "iso:country":"CN",
    "name:zho_x_preferred":[
        "\u767d\u6851"
    ],
    "wof:name":"Baisang",
    "wof:placetype":"locality"
},
  "geometry": {"coordinates":[92.64782,31.75294],"type":"Point"}
}