{
  "type": "Feature",
  "properties": {
    "gn:admin1_code":"8.0",
    "gn:asciiname":"Quanzigou",
    "gn:country_code":"CN",
    "gn:dem":149,
    "gn:feature_class":"P",
    "gn:feature_code":"PPL",
    "gn:name":"Quanzigou",
    "gn:population":0,
    "gn:timezone":"Asia/Shanghai",
    "iso:country":"CN",
    "name:zho_x_preferred":[
        "\u6cc9\u5b50\u6c9f"
    ],
    "wof:name":"Quanzigou",
    "wof:placetype":"locality"
},
  "geometry": {"coordinates":[127.53498,45.85569],"type":"Point"}
}