{
  "type": "Feature",
  "properties": {
    "gn:admin1_code":"8.0",
    "gn:asciiname":"Dawengcun",
    "gn:country_code":"CN",
    "gn:dem":128,
    "gn:feature_class":"P",
    "gn:feature_code":"PPL",
    "gn:name":"Dawengcun",
    "gn:population":0,
    "gn:timezone":"Asia/Shanghai",
    "iso:country":"CN",
    "name:zho_x_preferred":[
        "\u5927\u74ee\u6751"
    ],
    "wof:name":"Dawengcun",
    "wof:placetype":"locality"
},
  "geometry": {"coordinates":[126.30262999999999,45.88218],"type":"Point"}
}