{
  "type": "Feature",
  "properties": {
    "gn:admin1_code":"1.0",
    "gn:asciiname":"Yiliucun",
    "gn:country_code":"CN",
    "gn:dem":21,
    "gn:feature_class":"P",
    "gn:feature_code":"PPL",
    "gn:name":"Yiliucun",
    "gn:population":0,
    "gn:timezone":"Asia/Shanghai",
    "iso:country":"CN",
    "name:zho_x_preferred":[
        "\u6613\u5218\u6751"
    ],
    "wof:name":"Yiliucun",
    "wof:placetype":"locality"
},
  "geometry": {"coordinates":[117.07047,32.82445],"type":"Point"}
}