{
  "type": "Feature",
  "properties": {
    "gn:admin1_code":"29.0",
    "gn:asciiname":"Dadichu",
    "gn:country_code":"CN",
    "gn:dem":1969,
    "gn:feature_class":"P",
    "gn:feature_code":"PPL",
    "gn:name":"Dadichu",
    "gn:population":0,
    "gn:timezone":"Asia/Shanghai",
    "iso:country":"CN",
    "name:zho_x_preferred":[
        "\u5927\u5730\u5904"
    ],
    "wof:name":"Dadichu",
    "wof:placetype":"locality"
},
  "geometry": {"coordinates":[99.4387,26.1042],"type":"Point"}
}