{
  "type": "Feature",
  "properties": {
    "gn:admin1_code":"10.0",
    "gn:asciiname":"Donghuanli",
    "gn:country_code":"CN",
    "gn:dem":6,
    "gn:feature_class":"P",
    "gn:feature_code":"PPL",
    "gn:name":"Donghuanli",
    "gn:population":0,
    "gn:timezone":"Asia/Shanghai",
    "iso:country":"CN",
    "name:zho_x_preferred":[
        "\u4e1c\u73af\u91cc"
    ],
    "wof:name":"Donghuanli",
    "wof:placetype":"locality"
},
  "geometry": {"coordinates":[119.6189,39.94983],"type":"Point"}
}