{
  "type": "Feature",
  "properties": {
    "gn:admin1_code":"10.0",
    "gn:asciiname":"Baoziyu",
    "gn:country_code":"CN",
    "gn:dem":263,
    "gn:feature_class":"P",
    "gn:feature_code":"PPL",
    "gn:name":"Baoziyu",
    "gn:population":0,
    "gn:timezone":"Asia/Shanghai",
    "iso:country":"CN",
    "name:zho_x_preferred":[
        "\u8c79\u5b50\u5cea"
    ],
    "wof:name":"Baoziyu",
    "wof:placetype":"locality"
},
  "geometry": {"coordinates":[115.2825,39.40816],"type":"Point"}
}