{
  "type": "Feature",
  "properties": {
    "gn:admin1_code":"30",
    "gn:asciiname":"Dina",
    "gn:country_code":"CN",
    "gn:dem":10,
    "gn:feature_class":"P",
    "gn:feature_code":"PPL",
    "gn:name":"Dina",
    "gn:population":0,
    "gn:timezone":"Asia/Shanghai",
    "iso:country":"CN",
    "name:als_x_preferred":[
        "Dina"
    ],
    "name:ces_x_preferred":[
        "Dina"
    ],
    "name:dan_x_preferred":[
        "Dina"
    ],
    "name:deu_x_preferred":[
        "Dina"
    ],
    "name:hun_x_preferred":[
        "Dina"
    ],
    "name:ita_x_preferred":[
        "Dina"
    ],
    "name:nno_x_preferred":[
        "Dina"
    ],
    "name:nor_x_preferred":[
        "Dina"
    ],
    "name:pol_x_preferred":[
        "Dina"
    ],
    "name:rus_x_preferred":[
        "\u0414\u0438\u043d\u0430"
    ],
    "name:swe_x_preferred":[
        "Dina"
    ],
    "name:zho_x_preferred":[
        "\u5730\u62ff"
    ],
    "wof:name":"Dina",
    "wof:placetype":"locality"
},
  "geometry": {"coordinates":[111.95498000000001,21.61404],"type":"Point"}
}