{
  "type": "Feature",
  "properties": {
    "gn:admin1_code":"19.0",
    "gn:asciiname":"Anjia Wopu",
    "gn:country_code":"CN",
    "gn:dem":222,
    "gn:feature_class":"P",
    "gn:feature_code":"PPL",
    "gn:name":"Anjia Wopu",
    "gn:population":0,
    "gn:timezone":"Asia/Shanghai",
    "iso:country":"CN",
    "name:zho_x_preferred":[
        "\u5b89\u5bb6\u7a9d\u94fa"
    ],
    "wof:name":"Anjia Wopu",
    "wof:placetype":"locality"
},
  "geometry": {"coordinates":[120.85599999999999,41.4175],"type":"Point"}
}