{
  "type": "Feature",
  "properties": {
    "gn:admin1_code":"15.0",
    "gn:asciiname":"Mojiazhuang",
    "gn:country_code":"CN",
    "gn:dem":1883,
    "gn:feature_class":"P",
    "gn:feature_code":"PPL",
    "gn:name":"Mojiazhuang",
    "gn:population":0,
    "gn:timezone":"Asia/Shanghai",
    "iso:country":"CN",
    "name:zho_x_preferred":[
        "\u83ab\u5bb6\u5e84"
    ],
    "wof:name":"Mojiazhuang",
    "wof:placetype":"locality"
},
  "geometry": {"coordinates":[102.88800000000001,37.5854],"type":"Point"}
}