{
  "type": "Feature",
  "properties": {
    "gn:admin1_code":"4.0",
    "gn:asciiname":"Chengmaxucun",
    "gn:country_code":"CN",
    "gn:dem":5,
    "gn:feature_class":"P",
    "gn:feature_code":"PPL",
    "gn:name":"Chengmaxucun",
    "gn:population":0,
    "gn:timezone":"Asia/Shanghai",
    "iso:country":"CN",
    "name:zho_x_preferred":[
        "\u4e58\u9a6c\u5729\u6751"
    ],
    "wof:name":"Chengmaxucun",
    "wof:placetype":"locality"
},
  "geometry": {"coordinates":[119.22247,31.36688],"type":"Point"}
}