{
  "type": "Feature",
  "properties": {
    "gn:admin1_code":"33.0",
    "gn:asciiname":"Dawan",
    "gn:country_code":"CN",
    "gn:dem":660,
    "gn:feature_class":"P",
    "gn:feature_code":"PPL",
    "gn:name":"Dawan",
    "gn:population":0,
    "gn:timezone":"Asia/Shanghai",
    "iso:country":"CN",
    "name:zho_x_preferred":[
        "\u5927\u5f2f"
    ],
    "wof:name":"Dawan",
    "wof:placetype":"locality"
},
  "geometry": {"coordinates":[108.69283,29.11403],"type":"Point"}
}