{
  "type": "Feature",
  "properties": {
    "gn:admin1_code":"16",
    "gn:asciiname":"Debao Chengguanzhen",
    "gn:country_code":"CN",
    "gn:dem":688,
    "gn:feature_class":"P",
    "gn:feature_code":"PPLA3",
    "gn:name":"Debao Chengguanzhen",
    "gn:population":0,
    "gn:timezone":"Asia/Shanghai",
    "iso:country":"CN",
    "name:und_x_variant":[
        "Chenan",
        "Chenanfu",
        "Te-pao",
        "Debao",
        "Debao Chengguanzhen"
    ],
    "name:zho_x_preferred":[
        "T\u2019ien-pao"
    ],
    "name:zho_x_variant":[
        "T\u2019ien-pao-hsien-ch\u2019eng",
        "T\u2019ien-pao-hsien"
    ],
    "wof:name":"Debao Chengguanzhen",
    "wof:placetype":"locality"
},
  "geometry": {"coordinates":[106.57352,23.38471],"type":"Point"}
}