{
  "type": "Feature",
  "properties": {
    "gn:admin1_code":"16",
    "gn:asciiname":"Debao Chengguanzhen",
    "gn:country_code":"CN",
    "gn:dem":688,
    "gn:feature_class":"P",
    "gn:feature_code":"PPLA3",
    "gn:name":"Debao Chengguanzhen",
    "gn:population":0,
    "gn:timezone":"Asia/Shanghai",
    "iso:country":"CN",
    "name:deu_x_preferred":[
        "Debao"
    ],
    "name:fas_x_preferred":[
        "\u0634\u0647\u0631\u0633\u062a\u0627\u0646 \u062f\u0628\u0627\u0648"
    ],
    "name:hak_x_preferred":[
        "Tet-p\u00f3-yen"
    ],
    "name:jpn_x_preferred":[
        "\u5fb3\u4fdd\u770c"
    ],
    "name:kor_x_preferred":[
        "\ub354\ubc14\uc624\ud604"
    ],
    "name:nor_x_preferred":[
        "Debao"
    ],
    "name:swe_x_preferred":[
        "Debao"
    ],
    "name:und_x_variant":[
        "Chenan",
        "Chenanfu",
        "Te-pao",
        "Debao",
        "Debao Chengguanzhen"
    ],
    "name:vie_x_preferred":[
        "\u0110\u1ee9c B\u1ea3o"
    ],
    "name:zho_x_preferred":[
        "T\u2019ien-pao"
    ],
    "name:zho_x_variant":[
        "T\u2019ien-pao-hsien-ch\u2019eng",
        "T\u2019ien-pao-hsien",
        "\u5fb7\u4fdd\u53bf"
    ],
    "wof:name":"Debao Chengguanzhen",
    "wof:placetype":"locality"
},
  "geometry": {"coordinates":[106.57352,23.38471],"type":"Point"}
}