{
  "type": "Feature",
  "properties": {
    "gn:admin1_code":"15.0",
    "gn:asciiname":"Gaolouzi",
    "gn:country_code":"CN",
    "gn:dem":2542,
    "gn:feature_class":"P",
    "gn:feature_code":"PPL",
    "gn:name":"Gaolouzi",
    "gn:population":0,
    "gn:timezone":"Asia/Shanghai",
    "iso:country":"CN",
    "name:und_x_variant":[
        "\u9ad8\u697c\u5b50"
    ],
    "wof:name":"Gaolouzi",
    "wof:placetype":"locality"
},
  "geometry": {"coordinates":[103.77949,34.55442],"type":"Point"}
}