{
  "type": "Feature",
  "properties": {
    "gn:admin1_code":"29.0",
    "gn:asciiname":"Jiangshantou",
    "gn:country_code":"CN",
    "gn:dem":1954,
    "gn:feature_class":"P",
    "gn:feature_code":"PPL",
    "gn:name":"Jiangshantou",
    "gn:population":0,
    "gn:timezone":"Asia/Shanghai",
    "iso:country":"CN",
    "name:zho_x_preferred":[
        "\u6c5f\u5c71\u5934"
    ],
    "wof:name":"Jiangshantou",
    "wof:placetype":"locality"
},
  "geometry": {"coordinates":[101.833,25.2898],"type":"Point"}
}