{
  "type": "Feature",
  "properties": {
    "gn:admin1_code":"1.0",
    "gn:asciiname":"Shuanggoucun",
    "gn:country_code":"CN",
    "gn:dem":30,
    "gn:feature_class":"P",
    "gn:feature_code":"PPL",
    "gn:name":"Shuanggoucun",
    "gn:population":0,
    "gn:timezone":"Asia/Shanghai",
    "iso:country":"CN",
    "name:und_x_variant":[
        "Shuanggou"
    ],
    "name:zho_x_preferred":[
        "\u53cc\u6c9f\u6751"
    ],
    "wof:name":"Shuanggoucun",
    "wof:placetype":"locality"
},
  "geometry": {"coordinates":[116.19167,33.06667],"type":"Point"}
}