{
  "type": "Feature",
  "properties": {
    "gn:admin1_code":"30",
    "gn:asciiname":"Puzhushan",
    "gn:country_code":"CN",
    "gn:dem":50,
    "gn:feature_class":"P",
    "gn:feature_code":"PPL",
    "gn:name":"Puzhushan",
    "gn:population":0,
    "gn:timezone":"Asia/Urumqi",
    "iso:country":"CN",
    "name:zho_x_preferred":[
        "\u84b2\u7af9\u5c71"
    ],
    "wof:name":"Puzhushan",
    "wof:placetype":"locality"
},
  "geometry": {"coordinates":[110.38778000000001,21.77594],"type":"Point"}
}