{
  "type": "Feature",
  "properties": {
    "gn:admin1_code":"14.0",
    "gn:asciiname":"Yalaga",
    "gn:country_code":"CN",
    "gn:dem":3963,
    "gn:feature_class":"P",
    "gn:feature_code":"PPL",
    "gn:name":"Yalaga",
    "gn:population":0,
    "gn:timezone":"Asia/Urumqi",
    "iso:country":"CN",
    "name:zho_x_preferred":[
        "\u54d1\u814a\u560e"
    ],
    "wof:name":"Yalaga",
    "wof:placetype":"locality"
},
  "geometry": {"coordinates":[95.16405,31.22023],"type":"Point"}
}