{
  "type": "Feature",
  "properties": {
    "gn:admin1_code":"29.0",
    "gn:asciiname":"Liushucun",
    "gn:country_code":"CN",
    "gn:dem":1889,
    "gn:feature_class":"P",
    "gn:feature_code":"PPL",
    "gn:name":"Liushucun",
    "gn:population":0,
    "gn:timezone":"Asia/Shanghai",
    "iso:country":"CN",
    "name:zho_x_preferred":[
        "\u67f3\u6811\u6751"
    ],
    "wof:name":"Liushucun",
    "wof:placetype":"locality"
},
  "geometry": {"coordinates":[102.36499999999999,24.9414],"type":"Point"}
}