{
  "type": "Feature",
  "properties": {
    "gn:admin1_code":"4.0",
    "gn:asciiname":"Changsheng",
    "gn:country_code":"CN",
    "gn:dem":6,
    "gn:feature_class":"P",
    "gn:feature_code":"PPL",
    "gn:name":"Changsheng",
    "gn:population":0,
    "gn:timezone":"Asia/Shanghai",
    "iso:country":"CN",
    "name:ceb_x_preferred":[
        "Changsheng"
    ],
    "name:deu_x_preferred":[
        "Changsheng"
    ],
    "name:swe_x_preferred":[
        "Changsheng"
    ],
    "name:und_x_variant":[
        "\u5e38\u80dc"
    ],
    "wof:name":"Changsheng",
    "wof:placetype":"locality"
},
  "geometry": {"coordinates":[121.26958999999999,31.96991],"type":"Point"}
}