{
  "type": "Feature",
  "properties": {
    "gn:admin1_code":"29",
    "gn:asciiname":"Taijitian",
    "gn:country_code":"CN",
    "gn:dem":1839,
    "gn:feature_class":"P",
    "gn:feature_code":"PPL",
    "gn:name":"Taijitian",
    "gn:population":0,
    "gn:timezone":"Asia/Shanghai",
    "iso:country":"CN",
    "name:zho_x_preferred":[
        "\u592a\u6781\u7530"
    ],
    "wof:name":"Taijitian",
    "wof:placetype":"locality"
},
  "geometry": {"coordinates":[102.84099999999999,24.6499],"type":"Point"}
}