{
  "type": "Feature",
  "properties": {
    "gn:admin1_code":"20.0",
    "gn:asciiname":"Liudajiazitun",
    "gn:country_code":"CN",
    "gn:dem":289,
    "gn:feature_class":"P",
    "gn:feature_code":"PPL",
    "gn:name":"Liudajiazitun",
    "gn:population":0,
    "gn:timezone":"Asia/Shanghai",
    "iso:country":"CN",
    "name:zho_x_preferred":[
        "\u5218\u5927\u67b6\u5b50\u5c6f"
    ],
    "wof:name":"Liudajiazitun",
    "wof:placetype":"locality"
},
  "geometry": {"coordinates":[122.76220000000001,47.8872],"type":"Point"}
}