{
  "type": "Feature",
  "properties": {
    "gn:admin1_code":"12.0",
    "gn:asciiname":"Zhangwangjia",
    "gn:country_code":"CN",
    "gn:dem":40,
    "gn:feature_class":"P",
    "gn:feature_code":"PPL",
    "gn:name":"Zhangwangjia",
    "gn:population":0,
    "gn:timezone":"Asia/Shanghai",
    "iso:country":"CN",
    "name:und_x_variant":[
        "\u5f20\u738b\u5bb6"
    ],
    "wof:name":"Zhangwangjia",
    "wof:placetype":"locality"
},
  "geometry": {"coordinates":[114.34938,30.05241],"type":"Point"}
}