{
  "type": "Feature",
  "properties": {
    "gn:admin1_code":"25",
    "gn:asciiname":"Dongshi",
    "gn:country_code":"CN",
    "gn:dem":389,
    "gn:feature_class":"P",
    "gn:feature_code":"PPL",
    "gn:name":"Dongshi",
    "gn:population":0,
    "gn:timezone":"Asia/Shanghai",
    "iso:country":"CN",
    "name:deu_x_preferred":[
        "Dongshi"
    ],
    "name:kor_x_preferred":[
        "\ub465\uc2a4 \ud5a5"
    ],
    "name:zho_x_preferred":[
        "\u4e1c\u77f3"
    ],
    "wof:name":"Dongshi",
    "wof:placetype":"locality"
},
  "geometry": {"coordinates":[117.916,36.4108],"type":"Point"}
}