{
  "type": "Feature",
  "properties": {
    "gn:admin1_code":"8.0",
    "gn:asciiname":"Tongzhicun",
    "gn:country_code":"CN",
    "gn:dem":228,
    "gn:feature_class":"P",
    "gn:feature_code":"PPL",
    "gn:name":"Tongzhicun",
    "gn:population":0,
    "gn:timezone":"Asia/Shanghai",
    "iso:country":"CN",
    "name:zho_x_preferred":[
        "\u540c\u5fd7\u6751"
    ],
    "wof:name":"Tongzhicun",
    "wof:placetype":"locality"
},
  "geometry": {"coordinates":[125.63871,47.99816],"type":"Point"}
}