{
  "type": "Feature",
  "properties": {
    "gn:admin1_code":"30.0",
    "gn:asciiname":"Dawangcun",
    "gn:country_code":"CN",
    "gn:dem":28,
    "gn:feature_class":"P",
    "gn:feature_code":"PPL",
    "gn:name":"Dawangcun",
    "gn:population":0,
    "gn:timezone":"Asia/Shanghai",
    "iso:country":"CN",
    "name:zho_x_preferred":[
        "\u5927\u65fa\u6751"
    ],
    "wof:name":"Dawangcun",
    "wof:placetype":"locality"
},
  "geometry": {"coordinates":[111.45780000000001,23.46609],"type":"Point"}
}