{
  "type": "Feature",
  "properties": {
    "gn:admin1_code":"1.0",
    "gn:asciiname":"Xuhuangcun",
    "gn:country_code":"CN",
    "gn:dem":18,
    "gn:feature_class":"P",
    "gn:feature_code":"PPL",
    "gn:name":"Xuhuangcun",
    "gn:population":0,
    "gn:timezone":"Asia/Shanghai",
    "iso:country":"CN",
    "name:zho_x_preferred":[
        "\u8bb8\u9ec4\u6751"
    ],
    "wof:name":"Xuhuangcun",
    "wof:placetype":"locality"
},
  "geometry": {"coordinates":[117.97871000000001,31.64262],"type":"Point"}
}