{
  "type": "Feature",
  "properties": {
    "gn:admin1_code":"30.0",
    "gn:asciiname":"Darenping",
    "gn:country_code":"CN",
    "gn:dem":115,
    "gn:feature_class":"P",
    "gn:feature_code":"PPL",
    "gn:name":"Darenping",
    "gn:population":0,
    "gn:timezone":"Asia/Shanghai",
    "iso:country":"CN",
    "name:zho_x_preferred":[
        "\u5927\u4ec1\u576a"
    ],
    "wof:name":"Darenping",
    "wof:placetype":"locality"
},
  "geometry": {"coordinates":[113.59256000000001,24.93076],"type":"Point"}
}