{
  "type": "Feature",
  "properties": {
    "gn:country":"CN",
    "gn:fcode":"PPL",
    "gn:population":72038,
    "iso:country":"CN",
    "name:ceb_x_preferred":[
        "Fuyuan"
    ],
    "name:deu_x_preferred":[
        "Fuyuan"
    ],
    "name:eus_x_preferred":[
        "Fuyuan"
    ],
    "name:fra_x_preferred":[
        "Fuyuan"
    ],
    "name:kor_x_preferred":[
        "\ud478\uc704\uc548"
    ],
    "name:mlg_x_preferred":[
        "Fuyuan"
    ],
    "name:nor_x_preferred":[
        "Fuyuan"
    ],
    "name:rus_x_preferred":[
        "\u0424\u0443\u044e\u0430\u043d\u044c"
    ],
    "name:swe_x_preferred":[
        "Fuyuan"
    ],
    "qs:name":"Fuyuan",
    "qs:photos_9r":0,
    "qs:photos_sr":0,
    "qs:pop_sr":"8",
    "wd:wordcount":37,
    "wof:name":"Fuyuan",
    "wof:placetype":"locality",
    "wof:population":72038
},
  "geometry": {"coordinates":[127.08333,46.43333],"type":"Point"}
}