{
  "type": "Feature",
  "properties": {
    "gn:admin1_code":"02",
    "gn:asciiname":"Tonglingjiaocun",
    "gn:country_code":"CN",
    "gn:dem":75,
    "gn:feature_class":"P",
    "gn:feature_code":"PPL",
    "gn:name":"Tonglingjiaocun",
    "gn:population":0,
    "gn:timezone":"Asia/Shanghai",
    "iso:country":"CN",
    "name:und_x_variant":[
        "T\u2019ung-ling-chiao-ts\u2019un",
        "Tonglingjiao",
        "\u94dc\u5cad\u811a",
        "Tonglingjiaocun"
    ],
    "name:zho_x_preferred":[
        "\u94dc\u5cad\u811a"
    ],
    "name:zho_x_variant":[
        "\u94dc\u5cad\u811a\u6751"
    ],
    "wof:name":"Tonglingjiaocun",
    "wof:placetype":"locality"
},
  "geometry": {"coordinates":[121.54668999999998,29.33313],"type":"Point"}
}