{
  "type": "Feature",
  "properties": {
    "gn:admin1_code":"03",
    "gn:asciiname":"Tianfanjie",
    "gn:country_code":"CN",
    "gn:dem":25,
    "gn:feature_class":"P",
    "gn:feature_code":"PPL",
    "gn:name":"Tianfanjie",
    "gn:population":0,
    "gn:timezone":"Asia/Shanghai",
    "iso:country":"CN",
    "name:und_x_variant":[
        "T\u2019ien-fan-hsiao-shih-mien",
        "T\u2019ien-fan-chieh",
        "Tianfanjie",
        "\u7530\u7548\u8857",
        "Tianfanjiezhen",
        "\u7530\u7548\u8857\u9547"
    ],
    "wof:name":"Tianfanjie",
    "wof:placetype":"locality"
},
  "geometry": {"coordinates":[116.86838,29.35361],"type":"Point"}
}