{
  "type": "Feature",
  "properties": {
    "gn:admin1_code":"04",
    "gn:asciiname":"Lianyun",
    "gn:country_code":"CN",
    "gn:dem":238,
    "gn:feature_class":"P",
    "gn:feature_code":"PPLA4",
    "gn:name":"Lianyun",
    "gn:population":0,
    "gn:timezone":"Asia/Shanghai",
    "iso:country":"CN",
    "name:und_x_variant":[
        "Lianyungang Shi",
        "Lien-y\u00fcn-shih",
        "Lien-y\u00fcn",
        "Lao-yao",
        "Lien-y\u00fcn-kang",
        "Lien-y\u00fcn-chiang",
        "Lianyungang",
        "Lianyun",
        "\u8fde\u4e91",
        "Lianyun Jiedao",
        "\u8fde\u4e91\u8857\u9053",
        "\u8fde\u4e91\u6e2f"
    ],
    "wof:name":"Lianyun",
    "wof:placetype":"locality"
},
  "geometry": {"coordinates":[119.4425,34.73194],"type":"Point"}
}