{
  "type": "Feature",
  "properties": {
    "gn:admin1_code":"2.0",
    "gn:admin4_code":"8634156.0",
    "gn:asciiname":"Suzhuangcun",
    "gn:country_code":"CN",
    "gn:dem":185,
    "gn:feature_class":"P",
    "gn:feature_code":"PPL",
    "gn:name":"Suzhuangcun",
    "gn:population":0,
    "gn:timezone":"Asia/Shanghai",
    "iso:country":"CN",
    "name:zho_x_preferred":[
        "\u82cf\u5e84\u6751"
    ],
    "wof:name":"Suzhuangcun",
    "wof:placetype":"locality"
},
  "geometry": {"coordinates":[118.11987000000001,29.19251],"type":"Point"}
}