{
  "type": "Feature",
  "properties": {
    "gn:admin1_code":"2.0",
    "gn:asciiname":"Yekengxia",
    "gn:country_code":"CN",
    "gn:dem":789,
    "gn:feature_class":"P",
    "gn:feature_code":"PPL",
    "gn:name":"Yekengxia",
    "gn:population":0,
    "gn:timezone":"Asia/Shanghai",
    "iso:country":"CN",
    "name:und_x_variant":[
        "\u53f6\u5751\u4e0b",
        "Yekengxia"
    ],
    "wof:name":"Yekengxia",
    "wof:placetype":"locality"
},
  "geometry": {"coordinates":[119.47776,27.78046],"type":"Point"}
}