{
  "type": "Feature",
  "properties": {
    "gn:admin1_code":"12.0",
    "gn:asciiname":"Gaoyang",
    "gn:country_code":"CN",
    "gn:dem":915,
    "gn:feature_class":"P",
    "gn:feature_code":"PPL",
    "gn:name":"Gaoyang",
    "gn:population":0,
    "gn:timezone":"Asia/Shanghai",
    "iso:country":"CN",
    "name:zho_x_preferred":[
        "\u9ad8\u4ef0"
    ],
    "wof:name":"Gaoyang",
    "wof:placetype":"locality"
},
  "geometry": {"coordinates":[109.05983000000001,30.60222000000001],"type":"Point"}
}