{
  "type": "Feature",
  "properties": {
    "gn:admin1_code":"1.0",
    "gn:asciiname":"Huishancun",
    "gn:country_code":"CN",
    "gn:dem":46,
    "gn:feature_class":"P",
    "gn:feature_code":"PPL",
    "gn:name":"Huishancun",
    "gn:population":0,
    "gn:timezone":"Asia/Shanghai",
    "iso:country":"CN",
    "name:zho_x_preferred":[
        "\u7070\u5c71\u6751"
    ],
    "wof:name":"Huishancun",
    "wof:placetype":"locality"
},
  "geometry": {"coordinates":[118.91412,30.71033],"type":"Point"}
}