{
  "type": "Feature",
  "properties": {
    "gn:admin1_code":"32.0",
    "gn:asciiname":"Dayou",
    "gn:country_code":"CN",
    "gn:dem":358,
    "gn:feature_class":"P",
    "gn:feature_code":"PPL",
    "gn:name":"Dayou",
    "gn:population":0,
    "gn:timezone":"Asia/Shanghai",
    "iso:country":"CN",
    "name:zho_x_preferred":[
        "\u5927\u6709"
    ],
    "wof:name":"Dayou",
    "wof:placetype":"locality"
},
  "geometry": {"coordinates":[106.69419000000001,30.81947000000001],"type":"Point"}
}