{
  "type": "Feature",
  "properties": {
    "gn:admin1_code":"21.0",
    "gn:asciiname":"Shashi Taizi",
    "gn:country_code":"CN",
    "gn:dem":1539,
    "gn:feature_class":"P",
    "gn:feature_code":"PPL",
    "gn:name":"Shashi Taizi",
    "gn:population":0,
    "gn:timezone":"Asia/Shanghai",
    "iso:country":"CN",
    "name:zho_x_preferred":[
        "\u6c99\u77f3\u53f0\u5b50"
    ],
    "wof:name":"Shashi Taizi",
    "wof:placetype":"locality"
},
  "geometry": {"coordinates":[106.13200000000001,38.9491],"type":"Point"}
}