{
  "type": "Feature",
  "properties": {
    "gn:admin1_code":"16",
    "gn:asciiname":"Yankouzhai",
    "gn:country_code":"CN",
    "gn:dem":229,
    "gn:feature_class":"P",
    "gn:feature_code":"PPL",
    "gn:name":"Yankouzhai",
    "gn:population":0,
    "gn:timezone":"Asia/Shanghai",
    "iso:country":"CN",
    "name:zho_x_preferred":[
        "\u5ca9\u53e3\u5be8"
    ],
    "wof:name":"Yankouzhai",
    "wof:placetype":"locality"
},
  "geometry": {"coordinates":[110.441,25.597],"type":"Point"}
}