{
  "type": "Feature",
  "properties": {
    "gn:admin1_code":"16",
    "gn:asciiname":"Dalayou",
    "gn:country_code":"CN",
    "gn:dem":602,
    "gn:feature_class":"P",
    "gn:feature_code":"PPL",
    "gn:name":"Dalayou",
    "gn:population":0,
    "gn:timezone":"Asia/Shanghai",
    "iso:country":"CN",
    "name:zho_x_preferred":[
        "\u5927\u5587\u53cb"
    ],
    "wof:name":"Dalayou",
    "wof:placetype":"locality"
},
  "geometry": {"coordinates":[109.779,25.4729],"type":"Point"}
}