{
  "type": "Feature",
  "properties": {
    "gn:admin1_code":"32.0",
    "gn:asciiname":"Xiaogoutou",
    "gn:country_code":"CN",
    "gn:dem":4368,
    "gn:feature_class":"P",
    "gn:feature_code":"PPL",
    "gn:name":"Xiaogoutou",
    "gn:population":0,
    "gn:timezone":"Asia/Shanghai",
    "iso:country":"CN",
    "name:zho_x_preferred":[
        "\u5c0f\u6c9f\u5934"
    ],
    "wof:name":"Xiaogoutou",
    "wof:placetype":"locality"
},
  "geometry": {"coordinates":[102.12873,31.15194],"type":"Point"}
}