{
  "type": "Feature",
  "properties": {
    "gn:admin1_code":"8.0",
    "gn:asciiname":"Daoxiangcun",
    "gn:country_code":"CN",
    "gn:dem":197,
    "gn:feature_class":"P",
    "gn:feature_code":"PPL",
    "gn:name":"Daoxiangcun",
    "gn:population":0,
    "gn:timezone":"Asia/Shanghai",
    "iso:country":"CN",
    "name:zho_x_preferred":[
        "\u7a3b\u9999\u6751"
    ],
    "wof:name":"Daoxiangcun",
    "wof:placetype":"locality"
},
  "geometry": {"coordinates":[127.31074,47.16483],"type":"Point"}
}