{
  "type": "Feature",
  "properties": {
    "gn:admin1_code":"30",
    "gn:asciiname":"Guangtai",
    "gn:country_code":"CN",
    "gn:dem":125,
    "gn:feature_class":"P",
    "gn:feature_code":"PPLA4",
    "gn:name":"Guangtai",
    "gn:population":0,
    "gn:timezone":"Asia/Shanghai",
    "iso:country":"CN",
    "name:und_x_variant":[
        "Guangtai Zhen",
        "\u5e7f\u592a\u9547"
    ],
    "wof:name":"Guangtai",
    "wof:placetype":"locality"
},
  "geometry": {"coordinates":[116.28075,23.47302],"type":"Point"}
}