{
  "type": "Feature",
  "properties": {
    "gn:admin1_code":"12.0",
    "gn:asciiname":"Tongjiagang",
    "gn:country_code":"CN",
    "gn:dem":48,
    "gn:feature_class":"P",
    "gn:feature_code":"PPL",
    "gn:name":"Tongjiagang",
    "gn:population":0,
    "gn:timezone":"Asia/Shanghai",
    "iso:country":"CN",
    "name:zho_x_preferred":[
        "\u4f5f\u5bb6\u5c97"
    ],
    "wof:name":"Tongjiagang",
    "wof:placetype":"locality"
},
  "geometry": {"coordinates":[112.0008,30.67488],"type":"Point"}
}