{
  "type": "Feature",
  "properties": {
    "gn:admin1_code":"9.0",
    "gn:asciiname":"Menzhang",
    "gn:country_code":"CN",
    "gn:dem":95,
    "gn:feature_class":"P",
    "gn:feature_code":"PPL",
    "gn:name":"Menzhang",
    "gn:population":0,
    "gn:timezone":"Asia/Shanghai",
    "iso:country":"CN",
    "name:zho_x_preferred":[
        "\u95e8\u5f20"
    ],
    "wof:name":"Menzhang",
    "wof:placetype":"locality"
},
  "geometry": {"coordinates":[113.95663999999999,34.37788],"type":"Point"}
}