{
  "type": "Feature",
  "properties": {
    "gn:admin1_code":"14.0",
    "gn:asciiname":"Karuo",
    "gn:country_code":"CN",
    "gn:dem":3586,
    "gn:feature_class":"P",
    "gn:feature_code":"PPL",
    "gn:name":"Karuo",
    "gn:population":0,
    "gn:timezone":"Asia/Urumqi",
    "iso:country":"CN",
    "name:bod_x_preferred":[
        "Karub"
    ],
    "name:zho_x_preferred":[
        "\u5361\u82e5"
    ],
    "wof:name":"Karuo",
    "wof:placetype":"locality"
},
  "geometry": {"coordinates":[93.79292,30.44131],"type":"Point"}
}