{
  "type": "Feature",
  "properties": {
    "gn:admin1_code":"32.0",
    "gn:asciiname":"Wangwayao",
    "gn:country_code":"CN",
    "gn:dem":497,
    "gn:feature_class":"P",
    "gn:feature_code":"PPL",
    "gn:name":"Wangwayao",
    "gn:population":0,
    "gn:timezone":"Asia/Shanghai",
    "iso:country":"CN",
    "name:zho_x_preferred":[
        "\u738b\u74e6\u7a91"
    ],
    "wof:name":"Wangwayao",
    "wof:placetype":"locality"
},
  "geometry": {"coordinates":[103.95999999999999,30.4245],"type":"Point"}
}