{
  "type": "Feature",
  "properties": {
    "gn:admin1_code":"32.0",
    "gn:asciiname":"Alaigong",
    "gn:country_code":"CN",
    "gn:dem":3407,
    "gn:feature_class":"P",
    "gn:feature_code":"PPL",
    "gn:name":"Alaigong",
    "gn:population":0,
    "gn:timezone":"Asia/Shanghai",
    "iso:country":"CN",
    "name:zho_x_preferred":[
        "\u788d\u6765\u8d21"
    ],
    "wof:name":"Alaigong",
    "wof:placetype":"locality"
},
  "geometry": {"coordinates":[101.184,28.2191],"type":"Point"}
}