{
  "type": "Feature",
  "properties": {
    "gn:admin1_code":"25",
    "gn:asciiname":"Baizuihong",
    "gn:country_code":"CN",
    "gn:dem":258,
    "gn:feature_class":"P",
    "gn:feature_code":"PPL",
    "gn:name":"Baizuihong",
    "gn:population":0,
    "gn:timezone":"Asia/Shanghai",
    "iso:country":"CN",
    "name:zho_x_preferred":[
        "\u767e\u5480\u7ea2"
    ],
    "wof:name":"Baizuihong",
    "wof:placetype":"locality"
},
  "geometry": {"coordinates":[117.76900000000001,36.1982],"type":"Point"}
}