{
  "type": "Feature",
  "properties": {
    "gn:admin1_code":"29.0",
    "gn:asciiname":"Jihegu",
    "gn:country_code":"CN",
    "gn:dem":2288,
    "gn:feature_class":"P",
    "gn:feature_code":"PPL",
    "gn:name":"Jihegu",
    "gn:population":0,
    "gn:timezone":"Asia/Shanghai",
    "iso:country":"CN",
    "name:zho_x_preferred":[
        "\u6324\u5408\u8c37"
    ],
    "wof:name":"Jihegu",
    "wof:placetype":"locality"
},
  "geometry": {"coordinates":[99.169,25.9729],"type":"Point"}
}