{
  "type": "Feature",
  "properties": {
    "gn:admin1_code":"29",
    "gn:asciiname":"Yulaijiu",
    "gn:country_code":"CN",
    "gn:dem":1911,
    "gn:feature_class":"P",
    "gn:feature_code":"PPL",
    "gn:name":"Yulaijiu",
    "gn:population":0,
    "gn:timezone":"Asia/Shanghai",
    "iso:country":"CN",
    "name:zho_x_preferred":[
        "\u96e8\u6765\u6551"
    ],
    "wof:name":"Yulaijiu",
    "wof:placetype":"locality"
},
  "geometry": {"coordinates":[102.51436,24.06914],"type":"Point"}
}