{
  "type": "Feature",
  "properties": {
    "gn:admin1_code":"10.0",
    "gn:asciiname":"Maguantun",
    "gn:country_code":"CN",
    "gn:dem":29,
    "gn:feature_class":"P",
    "gn:feature_code":"PPL",
    "gn:name":"Maguantun",
    "gn:population":0,
    "gn:timezone":"Asia/Shanghai",
    "iso:country":"CN",
    "name:zho_x_preferred":[
        "\u9a6c\u5b98\u5c6f"
    ],
    "wof:name":"Maguantun",
    "wof:placetype":"locality"
},
  "geometry": {"coordinates":[116.01685000000001,39.30942],"type":"Point"}
}