{
  "type": "Feature",
  "properties": {
    "gn:admin1_code":"19.0",
    "gn:asciiname":"Zhuanshanzi",
    "gn:country_code":"CN",
    "gn:dem":74,
    "gn:feature_class":"P",
    "gn:feature_code":"PPL",
    "gn:name":"Zhuanshanzi",
    "gn:population":0,
    "gn:timezone":"Asia/Shanghai",
    "iso:country":"CN",
    "name:und_x_variant":[
        "\u8f6c\u5c71\u5b50"
    ],
    "name:zho_x_preferred":[
        "\u8f6c\u5c71\u5b50"
    ],
    "wof:name":"Zhuanshanzi",
    "wof:placetype":"locality"
},
  "geometry": {"coordinates":[123.13625,42.44963],"type":"Point"}
}