{
  "type": "Feature",
  "properties": {
    "gn:admin1_code":"15.0",
    "gn:asciiname":"Gajia",
    "gn:country_code":"CN",
    "gn:dem":3472,
    "gn:feature_class":"P",
    "gn:feature_code":"PPL",
    "gn:name":"Gajia",
    "gn:population":0,
    "gn:timezone":"Asia/Shanghai",
    "iso:country":"CN",
    "name:zho_x_preferred":[
        "\u5c15\u52a0"
    ],
    "wof:name":"Gajia",
    "wof:placetype":"locality"
},
  "geometry": {"coordinates":[102.02334999999999,33.6473],"type":"Point"}
}