{
  "type": "Feature",
  "properties": {
    "gn:admin1_code":"12.0",
    "gn:asciiname":"Datangchen",
    "gn:country_code":"CN",
    "gn:dem":42,
    "gn:feature_class":"P",
    "gn:feature_code":"PPL",
    "gn:name":"Datangchen",
    "gn:population":0,
    "gn:timezone":"Asia/Shanghai",
    "iso:country":"CN",
    "name:und_x_variant":[
        "\u5927\u5858\u8c0c"
    ],
    "wof:name":"Datangchen",
    "wof:placetype":"locality"
},
  "geometry": {"coordinates":[114.34923000000001,30.25926],"type":"Point"}
}