{
  "type": "Feature",
  "properties": {
    "gn:admin1_code":"7",
    "gn:asciiname":"Xincuo",
    "gn:country_code":"CN",
    "gn:dem":372,
    "gn:feature_class":"P",
    "gn:feature_code":"PPL",
    "gn:name":"Xincuo",
    "gn:population":0,
    "gn:timezone":"Asia/Shanghai",
    "iso:country":"CN",
    "name:zho_x_preferred":[
        "\u65b0\u539d"
    ],
    "wof:name":"Xincuo",
    "wof:placetype":"locality"
},
  "geometry": {"coordinates":[117.53598999999998,24.97652],"type":"Point"}
}