{
  "type": "Feature",
  "properties": {
    "gn:admin1_code":"07",
    "gn:asciiname":"Hulinkou",
    "gn:country_code":"CN",
    "gn:dem":912,
    "gn:feature_class":"P",
    "gn:feature_code":"PPL",
    "gn:name":"Hulinkou",
    "gn:population":0,
    "gn:timezone":"Asia/Shanghai",
    "iso:country":"CN",
    "name:zho_x_preferred":[
        "\u864e\u6797\u53e3"
    ],
    "wof:name":"Hulinkou",
    "wof:placetype":"locality"
},
  "geometry": {"coordinates":[117.82168,25.06445],"type":"Point"}
}