{
  "type": "Feature",
  "properties": {
    "gn:admin1_code":"2.0",
    "gn:asciiname":"Dantou",
    "gn:country_code":"CN",
    "gn:dem":4,
    "gn:feature_class":"P",
    "gn:feature_code":"PPL",
    "gn:name":"Dantou",
    "gn:population":0,
    "gn:timezone":"Asia/Shanghai",
    "iso:country":"CN",
    "name:und_x_variant":[
        "\u65e6\u5934"
    ],
    "wof:name":"Dantou",
    "wof:placetype":"locality"
},
  "geometry": {"coordinates":[120.18153999999998,30.76843],"type":"Point"}
}