{
  "type": "Feature",
  "properties": {
    "gn:admin1_code":"2.0",
    "gn:asciiname":"Jianshan",
    "gn:country_code":"CN",
    "gn:dem":817,
    "gn:feature_class":"P",
    "gn:feature_code":"PPL",
    "gn:name":"Jianshan",
    "gn:population":0,
    "gn:timezone":"Asia/Shanghai",
    "iso:country":"CN",
    "name:und_x_variant":[
        "\u5c16\u5c71"
    ],
    "wof:name":"Jianshan",
    "wof:placetype":"locality"
},
  "geometry": {"coordinates":[118.89081000000002,30.24847],"type":"Point"}
}