{
  "type": "Feature",
  "properties": {
    "gn:admin1_code":"14.0",
    "gn:asciiname":"Bangcuocun",
    "gn:country_code":"CN",
    "gn:dem":3803,
    "gn:feature_class":"P",
    "gn:feature_code":"PPL",
    "gn:name":"Bangcuocun",
    "gn:population":0,
    "gn:timezone":"Asia/Urumqi",
    "iso:country":"CN",
    "name:zho_x_preferred":[
        "\u5e2e\u63aa\u6751"
    ],
    "wof:name":"Bangcuocun",
    "wof:placetype":"locality"
},
  "geometry": {"coordinates":[98.16167,30.91577],"type":"Point"}
}