{
  "type": "Feature",
  "properties": {
    "gn:admin1_code":"33.0",
    "gn:asciiname":"Chayuanba",
    "gn:country_code":"CN",
    "gn:dem":490,
    "gn:feature_class":"P",
    "gn:feature_code":"PPL",
    "gn:name":"Chayuanba",
    "gn:population":0,
    "gn:timezone":"Asia/Shanghai",
    "iso:country":"CN",
    "name:zho_x_preferred":[
        "\u8336\u56ed\u575d"
    ],
    "wof:name":"Chayuanba",
    "wof:placetype":"locality"
},
  "geometry": {"coordinates":[107.88108,29.222],"type":"Point"}
}