{
  "type": "Feature",
  "properties": {
    "gn:admin1_code":"9",
    "gn:asciiname":"Xiaozhangzhuang",
    "gn:country_code":"CN",
    "gn:dem":40,
    "gn:feature_class":"P",
    "gn:feature_code":"PPL",
    "gn:name":"Xiaozhangzhuang",
    "gn:population":0,
    "gn:timezone":"Asia/Shanghai",
    "iso:country":"CN",
    "name:zho_x_preferred":[
        "\u5c0f\u5f20\u5e84"
    ],
    "wof:name":"Xiaozhangzhuang",
    "wof:placetype":"locality"
},
  "geometry": {"coordinates":[115.52500000000001,33.7054],"type":"Point"}
}