{
  "type": "Feature",
  "properties": {
    "gn:admin1_code":"24",
    "gn:asciiname":"Shuiposhi",
    "gn:cc2":"CN",
    "gn:country_code":"CN",
    "gn:dem":1052,
    "gn:feature_class":"P",
    "gn:feature_code":"PPL",
    "gn:name":"Shuiposhi",
    "gn:population":0,
    "gn:timezone":"Asia/Shanghai",
    "iso:country":"CN",
    "name:und_x_variant":[
        "Shui-p\u2019o-ssu",
        "Shuiposhi"
    ],
    "wof:name":"Shuiposhi",
    "wof:placetype":"locality"
},
  "geometry": {"coordinates":[113.35861,40.07083],"type":"Point"}
}