{
  "type": "Feature",
  "properties": {
    "gn:admin1_code":"3.0",
    "gn:asciiname":"Shangdamaling",
    "gn:country_code":"CN",
    "gn:dem":553,
    "gn:feature_class":"P",
    "gn:feature_code":"PPL",
    "gn:name":"Shangdamaling",
    "gn:population":0,
    "gn:timezone":"Asia/Shanghai",
    "iso:country":"CN",
    "name:und_x_variant":[
        "\u4e0a\u5927\u9a6c\u5cad"
    ],
    "wof:name":"Shangdamaling",
    "wof:placetype":"locality"
},
  "geometry": {"coordinates":[115.49155,26.64473],"type":"Point"}
}