{
  "type": "Feature",
  "properties": {
    "gn:admin1_code":"3",
    "gn:asciiname":"Qiagang",
    "gn:country_code":"CN",
    "gn:dem":301,
    "gn:feature_class":"P",
    "gn:feature_code":"PPL",
    "gn:name":"Qiagang",
    "gn:population":0,
    "gn:timezone":"Asia/Shanghai",
    "iso:country":"CN",
    "wof:name":"Qiagang",
    "wof:placetype":"locality"
},
  "geometry": {"coordinates":[116.17361,26.925],"type":"Point"}
}