{
  "type": "Feature",
  "properties": {
    "gn:admin1_code":"2.0",
    "gn:asciiname":"Tangcao",
    "gn:country_code":"CN",
    "gn:dem":6,
    "gn:feature_class":"P",
    "gn:feature_code":"PPL",
    "gn:name":"Tangcao",
    "gn:population":0,
    "gn:timezone":"Asia/Shanghai",
    "iso:country":"CN",
    "name:und_x_variant":[
        "\u6c64\u66f9"
    ],
    "wof:name":"Tangcao",
    "wof:placetype":"locality"
},
  "geometry": {"coordinates":[120.90845,30.74128],"type":"Point"}
}