{
  "type": "Feature",
  "properties": {
    "gn:admin1_code":"14.0",
    "gn:asciiname":"Jialang",
    "gn:country_code":"CN",
    "gn:dem":4278,
    "gn:feature_class":"P",
    "gn:feature_code":"PPL",
    "gn:name":"Jialang",
    "gn:population":0,
    "gn:timezone":"Asia/Urumqi",
    "iso:country":"CN",
    "name:zho_x_preferred":[
        "\u7532\u6717"
    ],
    "wof:name":"Jialang",
    "wof:placetype":"locality"
},
  "geometry": {"coordinates":[91.90411,28.8631],"type":"Point"}
}