{
  "type": "Feature",
  "properties": {
    "gn:admin1_code":"4.0",
    "gn:asciiname":"Xiaoliuchang",
    "gn:country_code":"CN",
    "gn:dem":8,
    "gn:feature_class":"P",
    "gn:feature_code":"PPL",
    "gn:name":"Xiaoliuchang",
    "gn:population":0,
    "gn:timezone":"Asia/Shanghai",
    "iso:country":"CN",
    "name:zho_x_preferred":[
        "Xiaoliuchang"
    ],
    "name:zho_x_variant":[
        "\u5c0f\u5218\u573a"
    ],
    "wof:name":"Xiaoliuchang",
    "wof:placetype":"locality"
},
  "geometry": {"coordinates":[119.38232000000001,33.98333],"type":"Point"}
}