{
  "type": "Feature",
  "properties": {
    "gn:admin1_code":"32.0",
    "gn:asciiname":"Gualuchi",
    "gn:country_code":"CN",
    "gn:dem":1143,
    "gn:feature_class":"P",
    "gn:feature_code":"PPL",
    "gn:name":"Gualuchi",
    "gn:population":0,
    "gn:timezone":"Asia/Shanghai",
    "iso:country":"CN",
    "name:zho_x_preferred":[
        "\u74dc\u82a6\u6c60"
    ],
    "wof:name":"Gualuchi",
    "wof:placetype":"locality"
},
  "geometry": {"coordinates":[103.221,29.2106],"type":"Point"}
}