{
  "type": "Feature",
  "properties": {
    "gn:admin1_code":"24.0",
    "gn:asciiname":"Xiashecun",
    "gn:country_code":"CN",
    "gn:dem":813,
    "gn:feature_class":"P",
    "gn:feature_code":"PPL",
    "gn:name":"Xiashecun",
    "gn:population":0,
    "gn:timezone":"Asia/Shanghai",
    "iso:country":"CN",
    "name:zho_x_preferred":[
        "\u4e0b\u793e\u6751"
    ],
    "wof:name":"Xiashecun",
    "wof:placetype":"locality"
},
  "geometry": {"coordinates":[112.77639000000001,38.79297],"type":"Point"}
}