{
  "type": "Feature",
  "properties": {
    "gn:admin1_code":"32.0",
    "gn:asciiname":"Teji",
    "gn:country_code":"CN",
    "gn:dem":2740,
    "gn:feature_class":"P",
    "gn:feature_code":"PPL",
    "gn:name":"Teji",
    "gn:population":0,
    "gn:timezone":"Asia/Shanghai",
    "iso:country":"CN",
    "name:zho_x_preferred":[
        "\u7279\u673a"
    ],
    "wof:name":"Teji",
    "wof:placetype":"locality"
},
  "geometry": {"coordinates":[102.68600000000001,27.8057],"type":"Point"}
}