{
  "type": "Feature",
  "properties": {
    "gn:admin1_code":"32.0",
    "gn:asciiname":"Xianghuagang",
    "gn:country_code":"CN",
    "gn:dem":1513,
    "gn:feature_class":"P",
    "gn:feature_code":"PPL",
    "gn:name":"Xianghuagang",
    "gn:population":0,
    "gn:timezone":"Asia/Shanghai",
    "iso:country":"CN",
    "name:zho_x_preferred":[
        "\u9999\u82b1\u5c97"
    ],
    "wof:name":"Xianghuagang",
    "wof:placetype":"locality"
},
  "geometry": {"coordinates":[103.07052,29.36212],"type":"Point"}
}