{
  "type": "Feature",
  "properties": {
    "gn:admin1_code":"4.0",
    "gn:asciiname":"Yanghu",
    "gn:country_code":"CN",
    "gn:dem":34,
    "gn:feature_class":"P",
    "gn:feature_code":"PPL",
    "gn:name":"Yanghu",
    "gn:population":0,
    "gn:timezone":"Asia/Shanghai",
    "iso:country":"CN",
    "name:zho_x_preferred":[
        "\u6768\u6e56"
    ],
    "wof:name":"Yanghu",
    "wof:placetype":"locality"
},
  "geometry": {"coordinates":[118.76300000000001,32.934],"type":"Point"}
}