{
  "type": "Feature",
  "properties": {
    "gn:admin1_code":"25.0",
    "gn:asciiname":"Maqu",
    "gn:country_code":"CN",
    "gn:dem":8,
    "gn:feature_class":"P",
    "gn:feature_code":"PPL",
    "gn:name":"Maqu",
    "gn:population":0,
    "gn:timezone":"Asia/Shanghai",
    "iso:country":"CN",
    "name:jpn_x_preferred":[
        "\u30de\u30c1\u30e5"
    ],
    "name:zho_x_preferred":[
        "\u9a6c\u6e20"
    ],
    "wof:name":"Maqu",
    "wof:placetype":"locality"
},
  "geometry": {"coordinates":[119.33422,36.91849000000001],"type":"Point"}
}