{
  "type": "Feature",
  "properties": {
    "gn:admin1_code":"10.0",
    "gn:asciiname":"Lanmazhuang",
    "gn:country_code":"CN",
    "gn:dem":112,
    "gn:feature_class":"P",
    "gn:feature_code":"PPL",
    "gn:name":"Lanmazhuang",
    "gn:population":0,
    "gn:timezone":"Asia/Shanghai",
    "iso:country":"CN",
    "name:zho_x_preferred":[
        "\u62e6\u9a6c\u5e84"
    ],
    "wof:name":"Lanmazhuang",
    "wof:placetype":"locality"
},
  "geometry": {"coordinates":[119.59967,40.04771],"type":"Point"}
}