{
  "type": "Feature",
  "properties": {
    "gn:admin1_code":"25",
    "gn:asciiname":"Wutai",
    "gn:country_code":"CN",
    "gn:dem":14,
    "gn:feature_class":"P",
    "gn:feature_code":"PPL",
    "gn:name":"Wutai",
    "gn:population":0,
    "gn:timezone":"Asia/Shanghai",
    "iso:country":"CN",
    "name:ceb_x_preferred":[
        "Wutai"
    ],
    "name:fra_x_preferred":[
        "Wutai"
    ],
    "name:nor_x_preferred":[
        "Wutai"
    ],
    "name:zho_x_preferred":[
        "\u5348\u53f0"
    ],
    "wof:name":"Wutai",
    "wof:placetype":"locality"
},
  "geometry": {"coordinates":[121.42400000000001,37.4468],"type":"Point"}
}