{
  "type": "Feature",
  "properties": {
    "gn:admin1_code":"8.0",
    "gn:asciiname":"Damiaocun",
    "gn:country_code":"CN",
    "gn:dem":131,
    "gn:feature_class":"P",
    "gn:feature_code":"PPL",
    "gn:name":"Damiaocun",
    "gn:population":0,
    "gn:timezone":"Asia/Shanghai",
    "iso:country":"CN",
    "name:zho_x_preferred":[
        "\u5927\u5e99\u6751"
    ],
    "wof:name":"Damiaocun",
    "wof:placetype":"locality"
},
  "geometry": {"coordinates":[124.47051999999999,45.47158],"type":"Point"}
}