{
  "type": "Feature",
  "properties": {
    "gn:admin1_code":"9.0",
    "gn:asciiname":"Guanshangcun",
    "gn:country_code":"CN",
    "gn:dem":736,
    "gn:feature_class":"P",
    "gn:feature_code":"PPL",
    "gn:name":"Guanshangcun",
    "gn:population":0,
    "gn:timezone":"Asia/Shanghai",
    "iso:country":"CN",
    "name:zho_x_preferred":[
        "\u5173\u4e0a\u6751"
    ],
    "wof:name":"Guanshangcun",
    "wof:placetype":"locality"
},
  "geometry": {"coordinates":[111.4075,34.67118],"type":"Point"}
}