{
  "type": "Feature",
  "properties": {
    "gn:admin1_code":"30.0",
    "gn:asciiname":"Gezai",
    "gn:country_code":"CN",
    "gn:dem":357,
    "gn:feature_class":"P",
    "gn:feature_code":"PPL",
    "gn:name":"Gezai",
    "gn:population":0,
    "gn:timezone":"Asia/Shanghai",
    "iso:country":"CN",
    "name:und_x_variant":[
        "\u683c\u4ed4"
    ],
    "name:zho_x_preferred":[
        "\u683c\u4ed4"
    ],
    "wof:name":"Gezai",
    "wof:placetype":"locality"
},
  "geometry": {"coordinates":[115.25884000000001,23.42458],"type":"Point"}
}