{
  "type": "Feature",
  "properties": {
    "gn:admin1_code":"29.0",
    "gn:asciiname":"Qingmingchang",
    "gn:country_code":"CN",
    "gn:dem":2245,
    "gn:feature_class":"P",
    "gn:feature_code":"PPL",
    "gn:name":"Qingmingchang",
    "gn:population":0,
    "gn:timezone":"Asia/Shanghai",
    "iso:country":"CN",
    "name:zho_x_preferred":[
        "\u6e05\u660e\u573a"
    ],
    "wof:name":"Qingmingchang",
    "wof:placetype":"locality"
},
  "geometry": {"coordinates":[99.29089999999999,26.1911],"type":"Point"}
}