{
  "type": "Feature",
  "properties": {
    "gn:admin1_code":"11.0",
    "gn:asciiname":"Dapoli",
    "gn:country_code":"CN",
    "gn:dem":317,
    "gn:feature_class":"P",
    "gn:feature_code":"PPL",
    "gn:name":"Dapoli",
    "gn:population":0,
    "gn:timezone":"Asia/Shanghai",
    "iso:country":"CN",
    "name:hin_x_preferred":[
        "\u0926\u093e\u092a\u094b\u0932\u0940"
    ],
    "name:zho_x_preferred":[
        "\u5927\u5761\u91cc"
    ],
    "wof:name":"Dapoli",
    "wof:placetype":"locality"
},
  "geometry": {"coordinates":[113.18599,28.52491],"type":"Point"}
}