{
  "type": "Feature",
  "properties": {
    "gn:admin1_code":"26.0",
    "gn:asciiname":"Shangshiwenggou",
    "gn:country_code":"CN",
    "gn:dem":886,
    "gn:feature_class":"P",
    "gn:feature_code":"PPL",
    "gn:name":"Shangshiwenggou",
    "gn:population":0,
    "gn:timezone":"Asia/Shanghai",
    "iso:country":"CN",
    "name:zho_x_preferred":[
        "\u4e0a\u5341\u74ee\u6c9f"
    ],
    "wof:name":"Shangshiwenggou",
    "wof:placetype":"locality"
},
  "geometry": {"coordinates":[109.43309000000001,33.46122],"type":"Point"}
}