{
  "type": "Feature",
  "properties": {
    "gn:admin1_code":"32.0",
    "gn:asciiname":"Wangduo",
    "gn:country_code":"CN",
    "gn:dem":3816,
    "gn:feature_class":"P",
    "gn:feature_code":"PPL",
    "gn:name":"Wangduo",
    "gn:population":0,
    "gn:timezone":"Asia/Shanghai",
    "iso:country":"CN",
    "name:zho_x_preferred":[
        "\u65fa\u591a"
    ],
    "wof:name":"Wangduo",
    "wof:placetype":"locality"
},
  "geometry": {"coordinates":[99.8694,29.6772],"type":"Point"}
}