{
  "type": "Feature",
  "properties": {
    "gn:admin1_code":"31.0",
    "gn:asciiname":"Datianxi",
    "gn:country_code":"CN",
    "gn:dem":73,
    "gn:feature_class":"P",
    "gn:feature_code":"PPL",
    "gn:name":"Datianxi",
    "gn:population":0,
    "gn:timezone":"Asia/Shanghai",
    "iso:country":"CN",
    "name:zho_x_preferred":[
        "\u6253\u7530\u6eaa"
    ],
    "wof:name":"Datianxi",
    "wof:placetype":"locality"
},
  "geometry": {"coordinates":[109.96381,19.5446],"type":"Point"}
}