{
  "type": "Feature",
  "properties": {
    "gn:country":"CN",
    "gn:fcode":"PPL",
    "gn:pop":2300,
    "iso:country":"CN",
    "name:unk_x_variant":[
        "Chu-ch\u2019i"
    ],
    "name:zho_x_preferred":[
        "\u7af9\u5c90"
    ],
    "name:zho_x_variant":[
        "\u7af9\u5c90\u4e61"
    ],
    "qs:name":"Zhuqi",
    "qs:photos_9r":0,
    "qs:photos_sr":0,
    "qs:pop_sr":"4",
    "wd:wordcount":188,
    "wof:name":"Zhuqi",
    "wof:placetype":"locality",
    "wof:population":2300
},
  "geometry": {"coordinates":[119.10194,26.14611],"type":"Point"}
}