{
  "type": "Feature",
  "properties": {
    "gn:country":"CN",
    "gn:fcode":"PPL",
    "gn:pop":2300,
    "iso:country":"CN",
    "name:hak_x_preferred":[
        "Tsuk-kh\u00ec-hi\u00f4ng"
    ],
    "name:jpn_x_preferred":[
        "\u7af9\u5d0e\u90f7"
    ],
    "name:kor_x_preferred":[
        "\uc8fc\uce58\ud5a5"
    ],
    "name:pol_x_preferred":[
        "Zhuqi"
    ],
    "name:unk_x_variant":[
        "Chu-ch\u2019i"
    ],
    "name:vie_x_preferred":[
        "Tr\u00fac Khi"
    ],
    "name:zho_x_preferred":[
        "\u7af9\u5c90"
    ],
    "name:zho_x_variant":[
        "\u7af9\u5c90\u4e61",
        "\u7af9\u5d0e\u9109"
    ],
    "qs:name":"Zhuqi",
    "qs:photos_9r":0,
    "qs:photos_sr":0,
    "qs:pop_sr":"4",
    "wd:wordcount":188,
    "wof:name":"Zhuqi",
    "wof:placetype":"locality",
    "wof:population":2300
},
  "geometry": {"coordinates":[119.10194,26.14611],"type":"Point"}
}