{
  "type": "Feature",
  "properties": {
    "gn:admin1_code":"4.0",
    "gn:asciiname":"Bianhe",
    "gn:country_code":"CN",
    "gn:dem":17,
    "gn:feature_class":"P",
    "gn:feature_code":"PPL",
    "gn:name":"Bianhe",
    "gn:population":0,
    "gn:timezone":"Asia/Shanghai",
    "iso:country":"CN",
    "name:zho_x_preferred":[
        "\u6c74\u6cb3"
    ],
    "wof:name":"Bianhe",
    "wof:placetype":"locality"
},
  "geometry": {"coordinates":[118.23529000000001,33.4281],"type":"Point"}
}