{
  "type": "Feature",
  "properties": {
    "gn:admin1_code":"11.0",
    "gn:asciiname":"Malao",
    "gn:country_code":"CN",
    "gn:dem":329,
    "gn:feature_class":"P",
    "gn:feature_code":"PPL",
    "gn:name":"Malao",
    "gn:population":0,
    "gn:timezone":"Asia/Shanghai",
    "iso:country":"CN",
    "name:cat_x_preferred":[
        "Malao"
    ],
    "name:fra_x_preferred":[
        "Malao"
    ],
    "name:som_x_preferred":[
        "Malao"
    ],
    "name:zho_x_preferred":[
        "\u9a6c\u8001"
    ],
    "wof:name":"Malao",
    "wof:placetype":"locality"
},
  "geometry": {"coordinates":[109.86183,28.76495],"type":"Point"}
}