{
  "type": "Feature",
  "properties": {
    "gn:admin1_code":"29",
    "gn:asciiname":"Shangfamen",
    "gn:country_code":"CN",
    "gn:dem":1497,
    "gn:feature_class":"P",
    "gn:feature_code":"PPL",
    "gn:name":"Shangfamen",
    "gn:population":0,
    "gn:timezone":"Asia/Shanghai",
    "iso:country":"CN",
    "name:zho_x_preferred":[
        "\u4e0a\u6cd5\u95e8"
    ],
    "wof:name":"Shangfamen",
    "wof:placetype":"locality"
},
  "geometry": {"coordinates":[103.40600000000001,24.1777],"type":"Point"}
}