{
  "type": "Feature",
  "properties": {
    "gn:admin1_code":"1.0",
    "gn:asciiname":"Baoyi Nongchang",
    "gn:country_code":"CN",
    "gn:dem":43,
    "gn:feature_class":"P",
    "gn:feature_code":"PPLF",
    "gn:name":"Baoyi Nongchang",
    "gn:population":0,
    "gn:timezone":"Asia/Shanghai",
    "iso:country":"CN",
    "name:zho_x_preferred":[
        "\u4fdd\u4e49\u519c\u573a"
    ],
    "wof:name":"Baoyi Nongchang",
    "wof:placetype":"locality"
},
  "geometry": {"coordinates":[116.73688,32.24152],"type":"Point"}
}