{
  "type": "Feature",
  "properties": {
    "gn:admin1_code":"15.0",
    "gn:asciiname":"Yuantou",
    "gn:country_code":"CN",
    "gn:dem":1892,
    "gn:feature_class":"P",
    "gn:feature_code":"PPL",
    "gn:name":"Yuantou",
    "gn:population":0,
    "gn:timezone":"Asia/Shanghai",
    "iso:country":"CN",
    "name:und_x_variant":[
        "\u539f\u5934"
    ],
    "wof:name":"Yuantou",
    "wof:placetype":"locality"
},
  "geometry": {"coordinates":[105.66007999999999,35.70553],"type":"Point"}
}