{
  "type": "Feature",
  "properties": {
    "gn:admin1_code":"11",
    "gn:asciiname":"Xuanxi",
    "gn:country_code":"CN",
    "gn:dem":619,
    "gn:feature_class":"P",
    "gn:feature_code":"PPL",
    "gn:name":"Xuanxi",
    "gn:population":0,
    "gn:timezone":"Asia/Shanghai",
    "iso:country":"CN",
    "wof:name":"Xuanxi",
    "wof:placetype":"locality"
},
  "geometry": {"coordinates":[110.74139,28.30278],"type":"Point"}
}