{
  "type": "Feature",
  "properties": {
    "gn:admin1_code":"30.0",
    "gn:asciiname":"Shangpingtian",
    "gn:country_code":"CN",
    "gn:dem":337,
    "gn:feature_class":"P",
    "gn:feature_code":"PPL",
    "gn:name":"Shangpingtian",
    "gn:population":0,
    "gn:timezone":"Asia/Shanghai",
    "iso:country":"CN",
    "name:zho_x_preferred":[
        "\u4e0a\u576a\u7530"
    ],
    "wof:name":"Shangpingtian",
    "wof:placetype":"locality"
},
  "geometry": {"coordinates":[115.16621000000001,23.81806],"type":"Point"}
}