{
  "type": "Feature",
  "properties": {
    "gn:admin1_code":"15.0",
    "gn:asciiname":"Qianshanzhengjia",
    "gn:country_code":"CN",
    "gn:dem":1805,
    "gn:feature_class":"P",
    "gn:feature_code":"PPL",
    "gn:name":"Qianshanzhengjia",
    "gn:population":0,
    "gn:timezone":"Asia/Shanghai",
    "iso:country":"CN",
    "name:und_x_variant":[
        "\u524d\u5c71\u90d1\u5bb6"
    ],
    "wof:name":"Qianshanzhengjia",
    "wof:placetype":"locality"
},
  "geometry": {"coordinates":[105.6268,35.14713],"type":"Point"}
}