{
  "type": "Feature",
  "properties": {
    "gn:admin1_code":"1.0",
    "gn:asciiname":"Wushitoucun",
    "gn:country_code":"CN",
    "gn:dem":61,
    "gn:feature_class":"P",
    "gn:feature_code":"PPL",
    "gn:name":"Wushitoucun",
    "gn:population":0,
    "gn:timezone":"Asia/Shanghai",
    "iso:country":"CN",
    "name:zho_x_preferred":[
        "\u4e94\u5341\u5934\u6751"
    ],
    "wof:name":"Wushitoucun",
    "wof:placetype":"locality"
},
  "geometry": {"coordinates":[117.36033,32.03944],"type":"Point"}
}