{
  "type": "Feature",
  "properties": {
    "gn:admin1_code":"32.0",
    "gn:asciiname":"Baidiaofang",
    "gn:country_code":"CN",
    "gn:dem":1033,
    "gn:feature_class":"P",
    "gn:feature_code":"PPL",
    "gn:name":"Baidiaofang",
    "gn:population":0,
    "gn:timezone":"Asia/Shanghai",
    "iso:country":"CN",
    "name:zho_x_preferred":[
        "\u767d\u7889\u623f"
    ],
    "wof:name":"Baidiaofang",
    "wof:placetype":"locality"
},
  "geometry": {"coordinates":[103.617,28.7615],"type":"Point"}
}