{
  "type": "Feature",
  "properties": {
    "gn:admin1_code":"22.0",
    "gn:asciiname":"Wangfu Shangying",
    "gn:country_code":"CN",
    "gn:dem":27,
    "gn:feature_class":"P",
    "gn:feature_code":"PPL",
    "gn:name":"Wangfu Shangying",
    "gn:population":0,
    "gn:timezone":"Asia/Shanghai",
    "iso:country":"CN",
    "name:zho_x_preferred":[
        "\u738b\u752b\u4e0a\u8425"
    ],
    "wof:name":"Wangfu Shangying",
    "wof:placetype":"locality"
},
  "geometry": {"coordinates":[116.65616,39.83164],"type":"Point"}
}