{
  "type": "Feature",
  "properties": {
    "gn:admin1_code":"3.0",
    "gn:asciiname":"Cenjia",
    "gn:country_code":"CN",
    "gn:dem":47,
    "gn:feature_class":"P",
    "gn:feature_code":"PPL",
    "gn:name":"Cenjia",
    "gn:population":0,
    "gn:timezone":"Asia/Shanghai",
    "iso:country":"CN",
    "name:und_x_variant":[
        "\u5c91\u5bb6"
    ],
    "wof:name":"Cenjia",
    "wof:placetype":"locality"
},
  "geometry": {"coordinates":[115.69638,29.27593],"type":"Point"}
}