{
  "type": "Feature",
  "properties": {
    "gn:admin1_code":"24.0",
    "gn:asciiname":"Guojiachacun",
    "gn:country_code":"CN",
    "gn:dem":1014,
    "gn:feature_class":"P",
    "gn:feature_code":"PPL",
    "gn:name":"Guojiachacun",
    "gn:population":0,
    "gn:timezone":"Asia/Shanghai",
    "iso:country":"CN",
    "name:zho_x_preferred":[
        "\u90ed\u5bb6\u5c94\u6751"
    ],
    "wof:name":"Guojiachacun",
    "wof:placetype":"locality"
},
  "geometry": {"coordinates":[110.95663999999999,37.97845],"type":"Point"}
}