{
  "type": "Feature",
  "properties": {
    "gn:admin1_code":"29.0",
    "gn:asciiname":"Xiaobazi",
    "gn:country_code":"CN",
    "gn:dem":1739,
    "gn:feature_class":"P",
    "gn:feature_code":"PPL",
    "gn:name":"Xiaobazi",
    "gn:population":0,
    "gn:timezone":"Asia/Shanghai",
    "iso:country":"CN",
    "name:zho_x_preferred":[
        "\u5c0f\u575d\u5b50"
    ],
    "wof:name":"Xiaobazi",
    "wof:placetype":"locality"
},
  "geometry": {"coordinates":[100.30800000000001,23.4775],"type":"Point"}
}