{
  "type": "Feature",
  "properties": {
    "gn:admin1_code":"05",
    "gn:asciiname":"Weizigoucun",
    "gn:country_code":"CN",
    "gn:dem":296,
    "gn:feature_class":"P",
    "gn:feature_code":"PPL",
    "gn:name":"Weizigoucun",
    "gn:population":0,
    "gn:timezone":"Asia/Shanghai",
    "iso:country":"CN",
    "name:und_x_variant":[
        "Weizigou"
    ],
    "name:zho_x_preferred":[
        "\u82c7\u5b50\u6c9f\u6751"
    ],
    "wof:name":"Weizigoucun",
    "wof:placetype":"locality"
},
  "geometry": {"coordinates":[126.11736999999999,43.5114],"type":"Point"}
}