{
  "type": "Feature",
  "properties": {
    "gn:admin1_code":"8.0",
    "gn:asciiname":"Yindong",
    "gn:country_code":"CN",
    "gn:dem":58,
    "gn:feature_class":"P",
    "gn:feature_code":"PPL",
    "gn:name":"Yindong",
    "gn:population":0,
    "gn:timezone":"Asia/Shanghai",
    "iso:country":"CN",
    "name:zho_x_preferred":[
        "\u97f3\u4e1c"
    ],
    "wof:name":"Yindong",
    "wof:placetype":"locality"
},
  "geometry": {"coordinates":[133.83413000000002,47.4433],"type":"Point"}
}