{
  "type": "Feature",
  "properties": {
    "gn:admin1_code":"32.0",
    "gn:asciiname":"Shufang",
    "gn:country_code":"CN",
    "gn:dem":287,
    "gn:feature_class":"P",
    "gn:feature_code":"PPL",
    "gn:name":"Shufang",
    "gn:population":0,
    "gn:timezone":"Asia/Shanghai",
    "iso:country":"CN",
    "name:zho_x_preferred":[
        "\u4e66\u623f"
    ],
    "wof:name":"Shufang",
    "wof:placetype":"locality"
},
  "geometry": {"coordinates":[107.137,31.1481],"type":"Point"}
}