{
  "type": "Feature",
  "properties": {
    "gn:admin1_code":"32.0",
    "gn:asciiname":"Ningyuan",
    "gn:country_code":"CN",
    "gn:dem":2064,
    "gn:feature_class":"P",
    "gn:feature_code":"PPL",
    "gn:name":"Ningyuan",
    "gn:population":0,
    "gn:timezone":"Asia/Shanghai",
    "iso:country":"CN",
    "name:zho_x_preferred":[
        "\u5b81\u6e90"
    ],
    "wof:name":"Ningyuan",
    "wof:placetype":"locality"
},
  "geometry": {"coordinates":[102.1485,28.75722],"type":"Point"}
}