{
  "type": "Feature",
  "properties": {
    "gn:admin1_code":"11",
    "gn:asciiname":"Niugudang",
    "gn:country_code":"CN",
    "gn:dem":260,
    "gn:feature_class":"P",
    "gn:feature_code":"PPL",
    "gn:name":"Niugudang",
    "gn:population":0,
    "gn:timezone":"Asia/Shanghai",
    "iso:country":"CN",
    "name:und_x_variant":[
        "\u725b\u53e4\u51fc",
        "Niugudang"
    ],
    "wof:name":"Niugudang",
    "wof:placetype":"locality"
},
  "geometry": {"coordinates":[111.75360999999999,25.64667],"type":"Point"}
}