{
  "type": "Feature",
  "properties": {
    "gn:admin1_code":"3.0",
    "gn:asciiname":"Baishui",
    "gn:country_code":"CN",
    "gn:dem":197,
    "gn:feature_class":"P",
    "gn:feature_code":"PPL",
    "gn:name":"Baishui",
    "gn:population":0,
    "gn:timezone":"Asia/Shanghai",
    "iso:country":"CN",
    "name:deu_x_preferred":[
        "Baishui"
    ],
    "name:kor_x_preferred":[
        "\ubc14\uc774\uc218\uc774"
    ],
    "name:und_x_variant":[
        "\u767d\u6c34"
    ],
    "wof:name":"Baishui",
    "wof:placetype":"locality"
},
  "geometry": {"coordinates":[114.69385,27.94152],"type":"Point"}
}