{
  "type": "Feature",
  "properties": {
    "gn:admin1_code":"8.0",
    "gn:asciiname":"Shisigongli",
    "gn:country_code":"CN",
    "gn:dem":245,
    "gn:feature_class":"P",
    "gn:feature_code":"PPL",
    "gn:name":"Shisigongli",
    "gn:population":0,
    "gn:timezone":"Asia/Shanghai",
    "iso:country":"CN",
    "name:zho_x_preferred":[
        "\u5341\u56db\u516c\u91cc"
    ],
    "wof:name":"Shisigongli",
    "wof:placetype":"locality"
},
  "geometry": {"coordinates":[128.23973000000001,46.8154],"type":"Point"}
}