{
  "type": "Feature",
  "properties": {
    "gn:admin1_code":"9.0",
    "gn:asciiname":"Nandingye",
    "gn:country_code":"CN",
    "gn:dem":381,
    "gn:feature_class":"P",
    "gn:feature_code":"PPL",
    "gn:name":"Nandingye",
    "gn:population":0,
    "gn:timezone":"Asia/Shanghai",
    "iso:country":"CN",
    "name:zho_x_preferred":[
        "\u5357\u4e01\u51b6"
    ],
    "wof:name":"Nandingye",
    "wof:placetype":"locality"
},
  "geometry": {"coordinates":[113.96415,36.25782],"type":"Point"}
}