{
  "type": "Feature",
  "properties": {
    "gn:admin1_code":"15.0",
    "gn:asciiname":"Xixiangxiang",
    "gn:country_code":"CN",
    "gn:dem":1700,
    "gn:feature_class":"P",
    "gn:feature_code":"PPL",
    "gn:name":"Xixiangxiang",
    "gn:population":0,
    "gn:timezone":"Asia/Shanghai",
    "iso:country":"CN",
    "name:und_x_variant":[
        "\u7ec6\u5df7\u4e61"
    ],
    "wof:name":"Xixiangxiang",
    "wof:placetype":"locality"
},
  "geometry": {"coordinates":[105.58411,35.49289],"type":"Point"}
}