{
  "type": "Feature",
  "properties": {
    "gn:admin1_code":"32.0",
    "gn:asciiname":"Xiasuoqiao",
    "gn:country_code":"CN",
    "gn:dem":1147,
    "gn:feature_class":"P",
    "gn:feature_code":"PPL",
    "gn:name":"Xiasuoqiao",
    "gn:population":0,
    "gn:timezone":"Asia/Shanghai",
    "iso:country":"CN",
    "name:zho_x_preferred":[
        "\u4e0b\u7d22\u6865"
    ],
    "wof:name":"Xiasuoqiao",
    "wof:placetype":"locality"
},
  "geometry": {"coordinates":[103.47022,31.27951],"type":"Point"}
}