{
  "type": "Feature",
  "properties": {
    "gn:admin1_code":"26.0",
    "gn:asciiname":"Qianjutai",
    "gn:country_code":"CN",
    "gn:dem":1234,
    "gn:feature_class":"P",
    "gn:feature_code":"PPL",
    "gn:name":"Qianjutai",
    "gn:population":0,
    "gn:timezone":"Asia/Shanghai",
    "iso:country":"CN",
    "name:zho_x_preferred":[
        "\u524d\u5177\u53f0"
    ],
    "wof:name":"Qianjutai",
    "wof:placetype":"locality"
},
  "geometry": {"coordinates":[109.68577000000001,35.95325],"type":"Point"}
}