{
  "type": "Feature",
  "properties": {
    "gn:admin1_code":"10.0",
    "gn:asciiname":"Fangzhong",
    "gn:country_code":"CN",
    "gn:dem":38,
    "gn:feature_class":"P",
    "gn:feature_code":"PPL",
    "gn:name":"Fangzhong",
    "gn:population":0,
    "gn:timezone":"Asia/Shanghai",
    "iso:country":"CN",
    "name:zho_x_preferred":[
        "\u65b9\u4e2d"
    ],
    "wof:name":"Fangzhong",
    "wof:placetype":"locality"
},
  "geometry": {"coordinates":[115.79586999999999,39.33589],"type":"Point"}
}