{
  "type": "Feature",
  "properties": {
    "gn:admin1_code":"19.0",
    "gn:asciiname":"Xitaigoucun",
    "gn:country_code":"CN",
    "gn:dem":209,
    "gn:feature_class":"P",
    "gn:feature_code":"PPL",
    "gn:name":"Xitaigoucun",
    "gn:population":0,
    "gn:timezone":"Asia/Shanghai",
    "iso:country":"CN",
    "name:zho_x_preferred":[
        "\u897f\u53f0\u6c9f\u6751"
    ],
    "wof:name":"Xitaigoucun",
    "wof:placetype":"locality"
},
  "geometry": {"coordinates":[123.84005999999999,41.59835],"type":"Point"}
}