{
  "type": "Feature",
  "properties": {
    "gn:admin1_code":"3",
    "gn:asciiname":"Zhongmenkeng",
    "gn:country_code":"CN",
    "gn:dem":221,
    "gn:feature_class":"P",
    "gn:feature_code":"PPL",
    "gn:name":"Zhongmenkeng",
    "gn:population":0,
    "gn:timezone":"Asia/Shanghai",
    "iso:country":"CN",
    "name:zho_x_preferred":[
        "\u4e2d\u95e8\u5751"
    ],
    "wof:name":"Zhongmenkeng",
    "wof:placetype":"locality"
},
  "geometry": {"coordinates":[114.52800000000001,25.679],"type":"Point"}
}