{
  "type": "Feature",
  "properties": {
    "gn:admin1_code":"2.0",
    "gn:asciiname":"Gulixiang",
    "gn:country_code":"CN",
    "gn:dem":12,
    "gn:feature_class":"P",
    "gn:feature_code":"PPL",
    "gn:name":"Gulixiang",
    "gn:population":0,
    "gn:timezone":"Asia/Shanghai",
    "iso:country":"CN",
    "name:zho_x_preferred":[
        "\u53e4\u91cc\u5df7"
    ],
    "wof:name":"Gulixiang",
    "wof:placetype":"locality"
},
  "geometry": {"coordinates":[120.87466999999999,29.97672],"type":"Point"}
}