{
  "type": "Feature",
  "properties": {
    "gn:admin1_code":"29.0",
    "gn:asciiname":"Hongpo",
    "gn:country_code":"CN",
    "gn:dem":2718,
    "gn:feature_class":"P",
    "gn:feature_code":"PPL",
    "gn:name":"Hongpo",
    "gn:population":0,
    "gn:timezone":"Asia/Shanghai",
    "iso:country":"CN",
    "name:zho_x_preferred":[
        "\u7ea2\u5761"
    ],
    "wof:name":"Hongpo",
    "wof:placetype":"locality"
},
  "geometry": {"coordinates":[98.9021,28.287],"type":"Point"}
}