{
  "type": "Feature",
  "properties": {
    "gn:admin1_code":"1.0",
    "gn:asciiname":"Dafancun",
    "gn:country_code":"CN",
    "gn:dem":13,
    "gn:feature_class":"P",
    "gn:feature_code":"PPL",
    "gn:name":"Dafancun",
    "gn:population":0,
    "gn:timezone":"Asia/Shanghai",
    "iso:country":"CN",
    "name:zho_x_preferred":[
        "\u5927\u8303\u6751"
    ],
    "wof:name":"Dafancun",
    "wof:placetype":"locality"
},
  "geometry": {"coordinates":[118.25669000000001,31.72178],"type":"Point"}
}