{
  "type": "Feature",
  "properties": {
    "gn:admin1_code":"26.0",
    "gn:asciiname":"Caishenmiao",
    "gn:country_code":"CN",
    "gn:dem":1007,
    "gn:feature_class":"P",
    "gn:feature_code":"PPL",
    "gn:name":"Caishenmiao",
    "gn:population":0,
    "gn:timezone":"Asia/Shanghai",
    "iso:country":"CN",
    "name:zho_x_preferred":[
        "\u8d22\u795e\u5e99"
    ],
    "wof:name":"Caishenmiao",
    "wof:placetype":"locality"
},
  "geometry": {"coordinates":[108.72333,33.44521],"type":"Point"}
}