{
  "type": "Feature",
  "properties": {
    "gn:admin1_code":"26.0",
    "gn:asciiname":"Xuzhuangzecun",
    "gn:country_code":"CN",
    "gn:dem":1272,
    "gn:feature_class":"P",
    "gn:feature_code":"PPL",
    "gn:name":"Xuzhuangzecun",
    "gn:population":0,
    "gn:timezone":"Asia/Shanghai",
    "iso:country":"CN",
    "name:zho_x_preferred":[
        "\u5f90\u5e84\u5219\u6751"
    ],
    "wof:name":"Xuzhuangzecun",
    "wof:placetype":"locality"
},
  "geometry": {"coordinates":[109.37154,37.39833],"type":"Point"}
}