{
  "type": "Feature",
  "properties": {
    "gn:admin1_code":"12.0",
    "gn:asciiname":"Jiugenshu",
    "gn:country_code":"CN",
    "gn:dem":818,
    "gn:feature_class":"P",
    "gn:feature_code":"PPL",
    "gn:name":"Jiugenshu",
    "gn:population":0,
    "gn:timezone":"Asia/Shanghai",
    "iso:country":"CN",
    "name:zho_x_preferred":[
        "\u4e5d\u6839\u6811"
    ],
    "wof:name":"Jiugenshu",
    "wof:placetype":"locality"
},
  "geometry": {"coordinates":[109.60285,30.53561],"type":"Point"}
}