{
  "type": "Feature",
  "properties": {
    "gn:admin1_code":"11.0",
    "gn:asciiname":"Shengtou",
    "gn:country_code":"CN",
    "gn:dem":708,
    "gn:feature_class":"P",
    "gn:feature_code":"PPL",
    "gn:name":"Shengtou",
    "gn:population":0,
    "gn:timezone":"Asia/Shanghai",
    "iso:country":"CN",
    "name:zho_x_preferred":[
        "\u5269\u5934"
    ],
    "wof:name":"Shengtou",
    "wof:placetype":"locality"
},
  "geometry": {"coordinates":[110.73626000000002,29.8672],"type":"Point"}
}