{
  "type": "Feature",
  "properties": {
    "gn:admin1_code":"19.0",
    "gn:asciiname":"Halagou",
    "gn:country_code":"CN",
    "gn:dem":96,
    "gn:feature_class":"P",
    "gn:feature_code":"PPL",
    "gn:name":"Halagou",
    "gn:population":0,
    "gn:timezone":"Asia/Shanghai",
    "iso:country":"CN",
    "name:zho_x_preferred":[
        "\u54c8\u62c9\u6c9f"
    ],
    "wof:name":"Halagou",
    "wof:placetype":"locality"
},
  "geometry": {"coordinates":[123.655,43.0165],"type":"Point"}
}