{
  "type": "Feature",
  "properties": {
    "gn:admin1_code":"7.0",
    "gn:asciiname":"Langqiao",
    "gn:country_code":"CN",
    "gn:dem":605,
    "gn:feature_class":"P",
    "gn:feature_code":"PPL",
    "gn:name":"Langqiao",
    "gn:population":0,
    "gn:timezone":"Asia/Shanghai",
    "iso:country":"CN",
    "name:zho_x_preferred":[
        "\u6717\u6865"
    ],
    "wof:name":"Langqiao",
    "wof:placetype":"locality"
},
  "geometry": {"coordinates":[118.81819,25.51892],"type":"Point"}
}