{
  "type": "Feature",
  "properties": {
    "gn:admin1_code":"12.0",
    "gn:asciiname":"Shihui'ao",
    "gn:country_code":"CN",
    "gn:dem":192,
    "gn:feature_class":"P",
    "gn:feature_code":"PPL",
    "gn:name":"Shihui\u2019ao",
    "gn:population":0,
    "gn:timezone":"Asia/Shanghai",
    "iso:country":"CN",
    "name:zho_x_preferred":[
        "Shihui\u2019ao"
    ],
    "name:zho_x_variant":[
        "\u77f3\u7070\u51f9"
    ],
    "wof:name":"Shihui'ao",
    "wof:placetype":"locality"
},
  "geometry": {"coordinates":[113.41072,31.54124],"type":"Point"}
}