{
  "type": "Feature",
  "properties": {
    "gn:admin1_code":"16.0",
    "gn:asciiname":"Datan",
    "gn:country_code":"CN",
    "gn:dem":39,
    "gn:feature_class":"P",
    "gn:feature_code":"PPL",
    "gn:name":"Datan",
    "gn:population":0,
    "gn:timezone":"Asia/Shanghai",
    "iso:country":"CN",
    "name:deu_x_preferred":[
        "Datan"
    ],
    "name:ita_x_preferred":[
        "Datan"
    ],
    "name:zho_x_preferred":[
        "\u5927\u6f6d"
    ],
    "wof:name":"Datan",
    "wof:placetype":"locality"
},
  "geometry": {"coordinates":[110.001,23.2953],"type":"Point"}
}