{
  "type": "Feature",
  "properties": {
    "gn:admin1_code":"30.0",
    "gn:asciiname":"Jingshuitang",
    "gn:country_code":"CN",
    "gn:dem":99,
    "gn:feature_class":"P",
    "gn:feature_code":"PPL",
    "gn:name":"Jingshuitang",
    "gn:population":0,
    "gn:timezone":"Asia/Shanghai",
    "iso:country":"CN",
    "name:zho_x_preferred":[
        "Jingshuitang"
    ],
    "name:zho_x_variant":[
        "\u4e95\u6c34\u5858"
    ],
    "wof:name":"Jingshuitang",
    "wof:placetype":"locality"
},
  "geometry": {"coordinates":[115.12444000000001,24.325],"type":"Point"}
}