{
  "type": "Feature",
  "properties": {
    "gn:admin1_code":"3.0",
    "gn:asciiname":"Nanlucun",
    "gn:country_code":"CN",
    "gn:dem":52,
    "gn:feature_class":"P",
    "gn:feature_code":"PPL",
    "gn:name":"Nanlucun",
    "gn:population":0,
    "gn:timezone":"Asia/Shanghai",
    "iso:country":"CN",
    "name:und_x_variant":[
        "\u5357\u8def\u6751"
    ],
    "wof:name":"Nanlucun",
    "wof:placetype":"locality"
},
  "geometry": {"coordinates":[115.78127000000001,28.55873],"type":"Point"}
}