{
  "type": "Feature",
  "properties": {
    "gn:admin1_code":"16",
    "gn:asciiname":"Longjiaoshang",
    "gn:country_code":"CN",
    "gn:dem":649,
    "gn:feature_class":"P",
    "gn:feature_code":"PPL",
    "gn:name":"Longjiaoshang",
    "gn:population":0,
    "gn:timezone":"Asia/Shanghai",
    "iso:country":"CN",
    "name:zho_x_preferred":[
        "\u9f99\u89d2\u4e0a"
    ],
    "wof:name":"Longjiaoshang",
    "wof:placetype":"locality"
},
  "geometry": {"coordinates":[110.239,24.8681],"type":"Point"}
}