{
  "type": "Feature",
  "properties": {
    "gn:admin1_code":"32.0",
    "gn:asciiname":"Lasaide",
    "gn:country_code":"CN",
    "gn:dem":2227,
    "gn:feature_class":"P",
    "gn:feature_code":"PPL",
    "gn:name":"Lasaide",
    "gn:population":0,
    "gn:timezone":"Asia/Shanghai",
    "iso:country":"CN",
    "name:zho_x_preferred":[
        "\u62c9\u585e\u5f97"
    ],
    "wof:name":"Lasaide",
    "wof:placetype":"locality"
},
  "geometry": {"coordinates":[102.9464,28.55231],"type":"Point"}
}