{
  "type": "Feature",
  "properties": {
    "gn:admin1_code":"4.0",
    "gn:asciiname":"Bajiaqiao",
    "gn:country_code":"CN",
    "gn:dem":7,
    "gn:feature_class":"P",
    "gn:feature_code":"PPL",
    "gn:name":"Bajiaqiao",
    "gn:population":0,
    "gn:timezone":"Asia/Shanghai",
    "iso:country":"CN",
    "name:und_x_variant":[
        "\u516b\u5bb6\u6865"
    ],
    "wof:name":"Bajiaqiao",
    "wof:placetype":"locality"
},
  "geometry": {"coordinates":[121.21276,31.93288],"type":"Point"}
}