{
  "type": "Feature",
  "properties": {
    "gn:admin1_code":"8.0",
    "gn:asciiname":"Babailiangtun",
    "gn:country_code":"CN",
    "gn:dem":243,
    "gn:feature_class":"P",
    "gn:feature_code":"PPL",
    "gn:name":"Babailiangtun",
    "gn:population":0,
    "gn:timezone":"Asia/Shanghai",
    "iso:country":"CN",
    "name:zho_x_preferred":[
        "\u516b\u767e\u4e24\u5c6f"
    ],
    "wof:name":"Babailiangtun",
    "wof:placetype":"locality"
},
  "geometry": {"coordinates":[126.55737000000001,48.19776],"type":"Point"}
}