{
  "type": "Feature",
  "properties": {
    "gn:admin1_code":"16.0",
    "gn:asciiname":"Qishicun",
    "gn:country_code":"CN",
    "gn:dem":234,
    "gn:feature_class":"P",
    "gn:feature_code":"PPL",
    "gn:name":"Qishicun",
    "gn:population":0,
    "gn:timezone":"Asia/Shanghai",
    "iso:country":"CN",
    "name:zho_x_preferred":[
        "\u4e03\u5341\u6751"
    ],
    "wof:name":"Qishicun",
    "wof:placetype":"locality"
},
  "geometry": {"coordinates":[108.078,23.455],"type":"Point"}
}