{
  "type": "Feature",
  "properties": {
    "gn:admin1_code":"19.0",
    "gn:asciiname":"Erdaoyang",
    "gn:country_code":"CN",
    "gn:dem":553,
    "gn:feature_class":"P",
    "gn:feature_code":"PPL",
    "gn:name":"Erdaoyang",
    "gn:population":0,
    "gn:timezone":"Asia/Shanghai",
    "iso:country":"CN",
    "name:und_x_variant":[
        "\u4e8c\u9053\u9633"
    ],
    "wof:name":"Erdaoyang",
    "wof:placetype":"locality"
},
  "geometry": {"coordinates":[124.81408999999999,41.25522],"type":"Point"}
}