{
  "type": "Feature",
  "properties": {
    "gn:admin1_code":"25",
    "gn:asciiname":"Hulingu",
    "gn:country_code":"CN",
    "gn:dem":533,
    "gn:feature_class":"P",
    "gn:feature_code":"PPL",
    "gn:name":"Hulingu",
    "gn:population":0,
    "gn:timezone":"Asia/Shanghai",
    "iso:country":"CN",
    "name:zho_x_preferred":[
        "\u80e1\u6797\u53e4"
    ],
    "wof:name":"Hulingu",
    "wof:placetype":"locality"
},
  "geometry": {"coordinates":[118.28700000000001,36.4954],"type":"Point"}
}