{
  "type": "Feature",
  "properties": {
    "gn:admin1_code":"26.0",
    "gn:asciiname":"Yangdaomaocun",
    "gn:country_code":"CN",
    "gn:dem":1359,
    "gn:feature_class":"P",
    "gn:feature_code":"PPL",
    "gn:name":"Yangdaomaocun",
    "gn:population":0,
    "gn:timezone":"Asia/Shanghai",
    "iso:country":"CN",
    "name:zho_x_preferred":[
        "\u9633\u9053\u5cc1\u6751"
    ],
    "wof:name":"Yangdaomaocun",
    "wof:placetype":"locality"
},
  "geometry": {"coordinates":[109.33074000000001,37.27101],"type":"Point"}
}