{
  "type": "Feature",
  "properties": {
    "gn:admin1_code":"9",
    "gn:asciiname":"Baitu",
    "gn:country_code":"CN",
    "gn:dem":1116,
    "gn:feature_class":"P",
    "gn:feature_code":"PPL",
    "gn:name":"Baitu",
    "gn:population":0,
    "gn:timezone":"Asia/Shanghai",
    "iso:country":"CN",
    "wof:name":"Baitu",
    "wof:placetype":"locality"
},
  "geometry": {"coordinates":[111.38611000000002,34.0125],"type":"Point"}
}