{
  "type": "Feature",
  "properties": {
    "gn:admin1_code":"12.0",
    "gn:asciiname":"Yanjiawan",
    "gn:country_code":"CN",
    "gn:dem":31,
    "gn:feature_class":"P",
    "gn:feature_code":"PPL",
    "gn:name":"Yanjiawan",
    "gn:population":0,
    "gn:timezone":"Asia/Shanghai",
    "iso:country":"CN",
    "name:und_x_variant":[
        "\u4e25\u5bb6\u5846"
    ],
    "wof:name":"Yanjiawan",
    "wof:placetype":"locality"
},
  "geometry": {"coordinates":[115.31659999999999,30.00502],"type":"Point"}
}