{
  "type": "Feature",
  "properties": {
    "gn:admin1_code":"12.0",
    "gn:asciiname":"Changwoxu",
    "gn:country_code":"CN",
    "gn:dem":280,
    "gn:feature_class":"P",
    "gn:feature_code":"PPL",
    "gn:name":"Changwoxu",
    "gn:population":0,
    "gn:timezone":"Asia/Shanghai",
    "iso:country":"CN",
    "name:zho_x_preferred":[
        "Changwoxu"
    ],
    "name:zho_x_variant":[
        "\u957f\u7a9d\u5f90"
    ],
    "wof:name":"Changwoxu",
    "wof:placetype":"locality"
},
  "geometry": {"coordinates":[114.46993000000001,29.69599],"type":"Point"}
}