{
  "type": "Feature",
  "properties": {
    "gn:admin1_code":"11.0",
    "gn:asciiname":"Shichong",
    "gn:country_code":"CN",
    "gn:dem":281,
    "gn:feature_class":"P",
    "gn:feature_code":"PPL",
    "gn:name":"Shichong",
    "gn:population":0,
    "gn:timezone":"Asia/Shanghai",
    "iso:country":"CN",
    "name:und_x_variant":[
        "Shichong Yangjia"
    ],
    "name:zho_x_preferred":[
        "\u77f3\u51b2"
    ],
    "wof:name":"Shichong",
    "wof:placetype":"locality"
},
  "geometry": {"coordinates":[111.15701,26.96395],"type":"Point"}
}