{
  "type": "Feature",
  "properties": {
    "gn:admin1_code":"18",
    "gn:asciiname":"Tuping",
    "gn:country_code":"CN",
    "gn:dem":702,
    "gn:feature_class":"P",
    "gn:feature_code":"PPL",
    "gn:name":"Tuping",
    "gn:population":0,
    "gn:timezone":"Asia/Shanghai",
    "iso:country":"CN",
    "name:zho_x_preferred":[
        "\u571f\u576a"
    ],
    "wof:name":"Tuping",
    "wof:placetype":"locality"
},
  "geometry": {"coordinates":[108.18300000000001,27.9307],"type":"Point"}
}