{
  "type": "Feature",
  "properties": {
    "gn:admin1_code":"11",
    "gn:asciiname":"Yijialing",
    "gn:country_code":"CN",
    "gn:dem":948,
    "gn:feature_class":"P",
    "gn:feature_code":"PPL",
    "gn:name":"Yijialing",
    "gn:population":0,
    "gn:timezone":"Asia/Shanghai",
    "iso:country":"CN",
    "name:und_x_variant":[
        "\u6613\u5bb6\u5cad",
        "Yijialing"
    ],
    "wof:name":"Yijialing",
    "wof:placetype":"locality"
},
  "geometry": {"coordinates":[111.515,25.775],"type":"Point"}
}