{
  "type": "Feature",
  "properties": {
    "gn:admin1_code":"11.0",
    "gn:asciiname":"Zhujia Dawu",
    "gn:country_code":"CN",
    "gn:dem":265,
    "gn:feature_class":"P",
    "gn:feature_code":"PPL",
    "gn:name":"Zhujia Dawu",
    "gn:population":0,
    "gn:timezone":"Asia/Shanghai",
    "iso:country":"CN",
    "name:zho_x_preferred":[
        "\u6731\u5bb6\u5927\u5c4b"
    ],
    "wof:name":"Zhujia Dawu",
    "wof:placetype":"locality"
},
  "geometry": {"coordinates":[113.78512000000001,27.32411],"type":"Point"}
}