{
  "type": "Feature",
  "properties": {
    "gn:admin1_code":"20.0",
    "gn:asciiname":"Huangyangcheng",
    "gn:country_code":"CN",
    "gn:dem":1459,
    "gn:feature_class":"P",
    "gn:feature_code":"PPL",
    "gn:name":"Huangyangcheng",
    "gn:population":0,
    "gn:timezone":"Asia/Shanghai",
    "iso:country":"CN",
    "name:und_x_variant":[
        "\u9ec4\u7f8a\u57ce"
    ],
    "wof:name":"Huangyangcheng",
    "wof:placetype":"locality"
},
  "geometry": {"coordinates":[112.56003,41.5975],"type":"Point"}
}