{
  "type": "Feature",
  "properties": {
    "gn:admin1_code":"9.0",
    "gn:asciiname":"Tongying",
    "gn:country_code":"CN",
    "gn:dem":31,
    "gn:feature_class":"P",
    "gn:feature_code":"PPL",
    "gn:name":"Tongying",
    "gn:population":0,
    "gn:timezone":"Asia/Shanghai",
    "iso:country":"CN",
    "name:zho_x_preferred":[
        "\u7ae5\u8425"
    ],
    "wof:name":"Tongying",
    "wof:placetype":"locality"
},
  "geometry": {"coordinates":[115.80208,32.40242],"type":"Point"}
}