{
  "type": "Feature",
  "properties": {
    "gn:admin1_code":"12.0",
    "gn:asciiname":"Yutangling",
    "gn:country_code":"CN",
    "gn:dem":40,
    "gn:feature_class":"P",
    "gn:feature_code":"PPL",
    "gn:name":"Yutangling",
    "gn:population":0,
    "gn:timezone":"Asia/Shanghai",
    "iso:country":"CN",
    "name:zho_x_preferred":[
        "\u4f59\u5858\u5cad"
    ],
    "wof:name":"Yutangling",
    "wof:placetype":"locality"
},
  "geometry": {"coordinates":[115.89214,30.11148],"type":"Point"}
}