{
  "type": "Feature",
  "properties": {
    "gn:admin1_code":"21.0",
    "gn:asciiname":"Jingxing Sidui",
    "gn:country_code":"CN",
    "gn:dem":1102,
    "gn:feature_class":"P",
    "gn:feature_code":"PPLF",
    "gn:name":"Jingxing Sidui",
    "gn:population":0,
    "gn:timezone":"Asia/Shanghai",
    "iso:country":"CN",
    "name:zho_x_preferred":[
        "\u4eac\u661f\u56db\u961f"
    ],
    "wof:name":"Jingxing Sidui",
    "wof:placetype":"locality"
},
  "geometry": {"coordinates":[106.53100000000001,38.6393],"type":"Point"}
}