{
  "type": "Feature",
  "properties": {
    "gn:admin1_code":"30",
    "gn:asciiname":"Koujia",
    "gn:country_code":"CN",
    "gn:dem":127,
    "gn:feature_class":"P",
    "gn:feature_code":"PPL",
    "gn:name":"Koujia",
    "gn:population":0,
    "gn:timezone":"Asia/Shanghai",
    "iso:country":"CN",
    "name:zho_x_preferred":[
        "\u53e3\u7532"
    ],
    "wof:name":"Koujia",
    "wof:placetype":"locality"
},
  "geometry": {"coordinates":[116.24250000000001,24.39283],"type":"Point"}
}