{
  "type": "Feature",
  "properties": {
    "gn:admin1_code":"13.0",
    "gn:asciiname":"Akdala",
    "gn:country_code":"CN",
    "gn:dem":1488,
    "gn:feature_class":"P",
    "gn:feature_code":"PPLA4",
    "gn:name":"Akdala",
    "gn:population":0,
    "gn:timezone":"Asia/Shanghai",
    "iso:country":"CN",
    "name:ceb_x_preferred":[
        "Akdala"
    ],
    "name:fas_x_preferred":[
        "\u0627\u06a9\u062f\u0627\u0644\u0627"
    ],
    "name:kaz_x_preferred":[
        "\u0410\u049b\u0434\u0430\u043b\u0430"
    ],
    "name:mkd_x_preferred":[
        "\u0410\u043a\u0434\u0430\u043b\u0430"
    ],
    "name:msa_x_preferred":[
        "Akdala"
    ],
    "name:por_x_preferred":[
        "Akdala"
    ],
    "name:rus_x_preferred":[
        "\u0410\u043a\u0434\u0430\u043b\u0430"
    ],
    "name:swe_x_preferred":[
        "Akdala"
    ],
    "name:uig_x_preferred":[
        "Aqdala"
    ],
    "name:uig_x_variant":[
        "\u0626\u0627\u0642\u062f\u0627\u0644\u0627",
        "\u0410\u049b\u0434\u0430\u043b\u0430"
    ],
    "name:ukr_x_preferred":[
        "\u0410\u043a\u0434\u0430\u043b\u0430"
    ],
    "name:und_x_variant":[
        "Akdala Xiang",
        "Akedala",
        "Akedala Xiang"
    ],
    "name:zho_x_preferred":[
        "\u963f\u514b\u8fbe\u62c9"
    ],
    "name:zho_x_variant":[
        "\u963f\u514b\u8fbe\u62c9\u4e61"
    ],
    "wof:name":"Akdala",
    "wof:placetype":"locality"
},
  "geometry": {"coordinates":[81.38,42.98861],"type":"Point"}
}