{
  "type": "Feature",
  "properties": {
    "gn:admin1_code":"7",
    "gn:asciiname":"Dongkengwei",
    "gn:country_code":"CN",
    "gn:dem":30,
    "gn:feature_class":"P",
    "gn:feature_code":"PPL",
    "gn:name":"Dongkengwei",
    "gn:population":0,
    "gn:timezone":"Asia/Shanghai",
    "iso:country":"CN",
    "name:zho_x_preferred":[
        "\u4e1c\u5751\u5c3e"
    ],
    "wof:name":"Dongkengwei",
    "wof:placetype":"locality"
},
  "geometry": {"coordinates":[117.21408,23.81703],"type":"Point"}
}