{
  "type": "Feature",
  "properties": {
    "gn:admin1_code":"7.0",
    "gn:asciiname":"Nanshan",
    "gn:country_code":"CN",
    "gn:dem":404,
    "gn:feature_class":"P",
    "gn:feature_code":"PPL",
    "gn:name":"Nanshan",
    "gn:population":0,
    "gn:timezone":"Asia/Shanghai",
    "iso:country":"CN",
    "name:cat_x_preferred":[
        "Nanshan"
    ],
    "name:ceb_x_preferred":[
        "Nanshan"
    ],
    "name:deu_x_preferred":[
        "Nanshan"
    ],
    "name:eus_x_preferred":[
        "Nanshan"
    ],
    "name:fra_x_preferred":[
        "Nanshan"
    ],
    "name:jpn_x_preferred":[
        "\u5357\u5c71\u533a"
    ],
    "name:kor_x_preferred":[
        "\ub09c\uc0b0\uad6c"
    ],
    "name:nld_x_preferred":[
        "Nanshan"
    ],
    "name:nor_x_preferred":[
        "Nanshan"
    ],
    "name:rus_x_preferred":[
        "\u041d\u0430\u043d\u044c\u0448\u0430\u043d\u044c"
    ],
    "name:swe_x_preferred":[
        "Nanshan"
    ],
    "name:zho_x_preferred":[
        "\u5357\u5c71"
    ],
    "name:zho_x_variant":[
        "\u5357\u5c71\u533a"
    ],
    "wof:name":"Nanshan",
    "wof:placetype":"locality"
},
  "geometry": {"coordinates":[119.82997,26.91152],"type":"Point"}
}