{
  "type": "Feature",
  "properties": {
    "gn:admin1_code":"30",
    "gn:asciiname":"Dayangtian",
    "gn:country_code":"CN",
    "gn:dem":621,
    "gn:feature_class":"P",
    "gn:feature_code":"PPL",
    "gn:name":"Dayangtian",
    "gn:population":0,
    "gn:timezone":"Asia/Shanghai",
    "iso:country":"CN",
    "name:und_x_variant":[
        "\u5927\u79e7\u7530",
        "Shanxi"
    ],
    "wof:name":"Dayangtian",
    "wof:placetype":"locality"
},
  "geometry": {"coordinates":[113.52321999999999,25.29427],"type":"Point"}
}