{
  "type": "Feature",
  "properties": {
    "gn:admin1_code":"30.0",
    "gn:asciiname":"Macheng",
    "gn:country_code":"CN",
    "gn:dem":25,
    "gn:feature_class":"P",
    "gn:feature_code":"PPL",
    "gn:name":"Macheng",
    "gn:population":0,
    "gn:timezone":"Asia/Urumqi",
    "iso:country":"CN",
    "name:zho_x_preferred":[
        "\u9ebb\u57ce"
    ],
    "wof:name":"Macheng",
    "wof:placetype":"locality"
},
  "geometry": {"coordinates":[110.18143000000001,20.27812],"type":"Point"}
}