{
  "type": "Feature",
  "properties": {
    "gn:admin1_code":"24.0",
    "gn:asciiname":"Haojiagou",
    "gn:country_code":"CN",
    "gn:dem":1329,
    "gn:feature_class":"P",
    "gn:feature_code":"PPL",
    "gn:name":"Haojiagou",
    "gn:population":0,
    "gn:timezone":"Asia/Shanghai",
    "iso:country":"CN",
    "name:und_x_variant":[
        "\u90dd\u5bb6\u6c9f"
    ],
    "name:zho_x_preferred":[
        "\u90dd\u5bb6\u6c9f"
    ],
    "wof:name":"Haojiagou",
    "wof:placetype":"locality"
},
  "geometry": {"coordinates":[112.45269,39.13481],"type":"Point"}
}