{
  "type": "Feature",
  "properties": {
    "gn:admin1_code":"26.0",
    "gn:asciiname":"Zuitou",
    "gn:country_code":"CN",
    "gn:dem":1542,
    "gn:feature_class":"P",
    "gn:feature_code":"PPLA3",
    "gn:name":"Zuitou",
    "gn:population":0,
    "gn:timezone":"Asia/Shanghai",
    "iso:country":"CN",
    "name:und_x_variant":[
        "T\u2019ai-pai",
        "Zuitou Zhen",
        "Taibai Xian",
        "Zuitoujie",
        "T\u2019ai-pai-ch\u2019\u00fc",
        "Ta-pai",
        "Tsui-t\u2019ou",
        "Tsui-t\u2019ou-chen",
        "Tszuytouchzhen\u2019",
        "Zuitou",
        "\u5634\u5934",
        "\u592a\u767d\u53bf"
    ],
    "name:zho_x_preferred":[
        "\u5480\u5934\u9547"
    ],
    "wof:name":"Zuitou",
    "wof:placetype":"locality"
},
  "geometry": {"coordinates":[107.31265999999999,34.06219],"type":"Point"}
}