{
  "type": "Feature",
  "properties": {
    "gn:admin1_code":"2.0",
    "gn:asciiname":"Huangliangchen",
    "gn:country_code":"CN",
    "gn:dem":33,
    "gn:feature_class":"P",
    "gn:feature_code":"PPL",
    "gn:name":"Huangliangchen",
    "gn:population":0,
    "gn:timezone":"Asia/Shanghai",
    "iso:country":"CN",
    "name:und_x_variant":[
        "Wang-liang-ch\u2019en-chen"
    ],
    "name:zho_x_preferred":[
        "\u9ec4\u6881\u9648"
    ],
    "wof:name":"Huangliangchen",
    "wof:placetype":"locality"
},
  "geometry": {"coordinates":[120.84134,28.87673],"type":"Point"}
}