{
  "type": "Feature",
  "properties": {
    "gn:admin1_code":"4.0",
    "gn:asciiname":"Jinkengxu",
    "gn:country_code":"CN",
    "gn:dem":17,
    "gn:feature_class":"P",
    "gn:feature_code":"PPL",
    "gn:name":"Jinkengxu",
    "gn:population":0,
    "gn:timezone":"Asia/Shanghai",
    "iso:country":"CN",
    "name:zho_x_preferred":[
        "\u91d1\u5751\u5729"
    ],
    "wof:name":"Jinkengxu",
    "wof:placetype":"locality"
},
  "geometry": {"coordinates":[118.97422,31.41277],"type":"Point"}
}