{
  "type": "Feature",
  "properties": {
    "gn:admin1_code":"11.0",
    "gn:asciiname":"Xijiaoyuan",
    "gn:country_code":"CN",
    "gn:dem":33,
    "gn:feature_class":"P",
    "gn:feature_code":"PPL",
    "gn:name":"Xijiaoyuan",
    "gn:population":0,
    "gn:timezone":"Asia/Shanghai",
    "iso:country":"CN",
    "name:zho_x_preferred":[
        "\u897f\u89d2\u57b8"
    ],
    "wof:name":"Xijiaoyuan",
    "wof:placetype":"locality"
},
  "geometry": {"coordinates":[112.38979999999999,29.5191],"type":"Point"}
}