{
  "type": "Feature",
  "properties": {
    "gn:admin1_code":"11.0",
    "gn:asciiname":"Lunan",
    "gn:country_code":"CN",
    "gn:dem":429,
    "gn:feature_class":"P",
    "gn:feature_code":"PPL",
    "gn:name":"Lunan",
    "gn:population":0,
    "gn:timezone":"Asia/Shanghai",
    "iso:country":"CN",
    "name:ceb_x_preferred":[
        "Lunan"
    ],
    "name:deu_x_preferred":[
        "Lunan"
    ],
    "name:nld_x_preferred":[
        "Lunan"
    ],
    "name:swe_x_preferred":[
        "Lunan"
    ],
    "name:zho_x_preferred":[
        "\u7089\u5357"
    ],
    "wof:name":"Lunan",
    "wof:placetype":"locality"
},
  "geometry": {"coordinates":[109.51764,26.5583],"type":"Point"}
}