{
  "type": "Feature",
  "properties": {
    "gn:admin1_code":"18",
    "gn:asciiname":"Zhuangfang",
    "gn:country_code":"CN",
    "gn:dem":1056,
    "gn:feature_class":"P",
    "gn:feature_code":"PPL",
    "gn:name":"Zhuangfang",
    "gn:population":0,
    "gn:timezone":"Asia/Shanghai",
    "iso:country":"CN",
    "name:zho_x_preferred":[
        "\u5e84\u623f"
    ],
    "wof:name":"Zhuangfang",
    "wof:placetype":"locality"
},
  "geometry": {"coordinates":[107.77,28.3705],"type":"Point"}
}