{
  "type": "Feature",
  "properties": {
    "gn:admin1_code":"18.0",
    "gn:asciiname":"Xiaoya",
    "gn:country_code":"CN",
    "gn:dem":651,
    "gn:feature_class":"P",
    "gn:feature_code":"PPLA4",
    "gn:name":"Xiaoya",
    "gn:population":0,
    "gn:timezone":"Asia/Shanghai",
    "iso:country":"CN",
    "name:und_x_variant":[
        "Xiaoya Zhen",
        "Luotongzhai"
    ],
    "name:zho_x_preferred":[
        "\u5c0f\u96c5"
    ],
    "name:zho_x_variant":[
        "\u5c0f\u96c5\u9547",
        "\u9a86\u901a\u5b85"
    ],
    "wof:name":"Xiaoya",
    "wof:placetype":"locality"
},
  "geometry": {"coordinates":[107.21754,28.48947],"type":"Point"}
}