{
  "type": "Feature",
  "properties": {
    "iso:country":"CN",
    "ne:ADM0CAP":0.0,
    "ne:ADM0NAME":"China",
    "ne:ADM0_A3":"CHN",
    "ne:ADM1NAME":"Gansu",
    "ne:ADMIN1_COD":0,
    "ne:CAPALT":0,
    "ne:CHANGED":0,
    "ne:CHECKME":0,
    "ne:COMPARE":0,
    "ne:DIFFASCII":0,
    "ne:ELEVATION":0.0,
    "ne:FEATURECLA":"Populated place",
    "ne:GEONAMEID":-1,
    "ne:GEONAMESNO":"No GeoNames match due to small population, not in GeoNames, or poor NEV placement.",
    "ne:GN_POP":0,
    "ne:GTOPO30":0.0,
    "ne:ISO_A2":"CN",
    "ne:LABELRANK":1,
    "ne:LATITUDE":34.436178,
    "ne:LONGITUDE":104.03059,
    "ne:LS_MATCH":1,
    "ne:LS_NAME":"Minxian",
    "ne:MAX_AREAKM":28.0,
    "ne:MAX_AREAMI":11.0,
    "ne:MAX_BBXMAX":104.058333,
    "ne:MAX_BBXMIN":103.908333,
    "ne:MAX_BBYMAX":34.45,
    "ne:MAX_BBYMIN":34.416667,
    "ne:MAX_NATSCA":20.0,
    "ne:MAX_PERKM":46.0,
    "ne:MAX_PERMI":28.0,
    "ne:MAX_POP10":67826,
    "ne:MAX_POP20":67826,
    "ne:MAX_POP300":0,
    "ne:MAX_POP310":0,
    "ne:MAX_POP50":0,
    "ne:MEAN_BBXC":103.988333,
    "ne:MEAN_BBYC":34.43125,
    "ne:MEGACITY":0,
    "ne:MIN_AREAKM":28.0,
    "ne:MIN_AREAMI":11.0,
    "ne:MIN_BBXMAX":104.058333,
    "ne:MIN_BBXMIN":103.908333,
    "ne:MIN_BBYMAX":34.45,
    "ne:MIN_BBYMIN":34.416667,
    "ne:MIN_PERKM":46.0,
    "ne:MIN_PERMI":28.0,
    "ne:NAME":"Minxian",
    "ne:NAMEASCII":"Minxian",
    "ne:NAMEDIFF":0,
    "ne:NATSCALE":20,
    "ne:POP1950":0,
    "ne:POP1955":0,
    "ne:POP1960":0,
    "ne:POP1965":0,
    "ne:POP1970":0,
    "ne:POP1975":0,
    "ne:POP1980":0,
    "ne:POP1985":0,
    "ne:POP1990":0,
    "ne:POP1995":0,
    "ne:POP2000":0,
    "ne:POP2005":0,
    "ne:POP2010":0,
    "ne:POP2015":0,
    "ne:POP2020":0,
    "ne:POP2025":0,
    "ne:POP2050":0,
    "ne:POP_MAX":67826,
    "ne:POP_MIN":67826,
    "ne:POP_OTHER":66820,
    "ne:RANK_MAX":8,
    "ne:RANK_MIN":8,
    "ne:SCALERANK":7,
    "ne:SOV0NAME":"China",
    "ne:SOV_A3":"CHN",
    "ne:UN_FID":0,
    "ne:UN_LAT":0.0,
    "ne:UN_LONG":0.0,
    "ne:WORLDCITY":0,
    "ne:min_zoom":6.7,
    "wof:name":"Minxian",
    "wof:placetype":"locality"
},
  "geometry": {"coordinates":[104.03059037172284,34.43617840477657],"type":"Point"}
}