{
  "type": "Feature",
  "properties": {
    "gn:admin1_code":"26.0",
    "gn:asciiname":"Jushengcun",
    "gn:country_code":"CN",
    "gn:dem":1033,
    "gn:feature_class":"P",
    "gn:feature_code":"PPL",
    "gn:name":"Jushengcun",
    "gn:population":0,
    "gn:timezone":"Asia/Shanghai",
    "iso:country":"CN",
    "name:zho_x_preferred":[
        "\u5c45\u751f\u6751"
    ],
    "wof:name":"Jushengcun",
    "wof:placetype":"locality"
},
  "geometry": {"coordinates":[109.40642,35.63831],"type":"Point"}
}