{
  "type": "Feature",
  "properties": {
    "gn:admin1_code":"26.0",
    "gn:asciiname":"Chajiaolou",
    "gn:country_code":"CN",
    "gn:dem":797,
    "gn:feature_class":"P",
    "gn:feature_code":"PPL",
    "gn:name":"Chajiaolou",
    "gn:population":0,
    "gn:timezone":"Asia/Shanghai",
    "iso:country":"CN",
    "name:und_x_variant":[
        "\u8336\u89d2\u697c"
    ],
    "wof:name":"Chajiaolou",
    "wof:placetype":"locality"
},
  "geometry": {"coordinates":[107.25785,33.35115],"type":"Point"}
}