{
  "type": "Feature",
  "properties": {
    "gn:admin1_code":"14.0",
    "gn:asciiname":"Suola",
    "gn:country_code":"CN",
    "gn:dem":4453,
    "gn:feature_class":"P",
    "gn:feature_code":"PPL",
    "gn:name":"Suola",
    "gn:population":0,
    "gn:timezone":"Asia/Urumqi",
    "iso:country":"CN",
    "name:zho_x_preferred":[
        "\u7d22\u62c9"
    ],
    "wof:name":"Suola",
    "wof:placetype":"locality"
},
  "geometry": {"coordinates":[96.12805,30.39282],"type":"Point"}
}