{
  "type": "Feature",
  "properties": {
    "gn:admin1_code":"15.0",
    "gn:asciiname":"Zhangjiagou",
    "gn:country_code":"CN",
    "gn:dem":1207,
    "gn:feature_class":"P",
    "gn:feature_code":"PPL",
    "gn:name":"Zhangjiagou",
    "gn:population":0,
    "gn:timezone":"Asia/Shanghai",
    "iso:country":"CN",
    "name:und_x_variant":[
        "\u5f20\u5bb6\u6c9f"
    ],
    "name:zho_x_preferred":[
        "\u5f20\u5bb6\u6c9f"
    ],
    "wof:name":"Zhangjiagou",
    "wof:placetype":"locality"
},
  "geometry": {"coordinates":[104.82644999999999,32.91121],"type":"Point"}
}