{
  "type": "Feature",
  "properties": {
    "gn:admin1_code":"30.0",
    "gn:asciiname":"Xiayunlong",
    "gn:country_code":"CN",
    "gn:dem":215,
    "gn:feature_class":"P",
    "gn:feature_code":"PPL",
    "gn:name":"Xiayunlong",
    "gn:population":0,
    "gn:timezone":"Asia/Urumqi",
    "iso:country":"CN",
    "name:zho_x_preferred":[
        "\u4e0b\u4e91\u9f99"
    ],
    "wof:name":"Xiayunlong",
    "wof:placetype":"locality"
},
  "geometry": {"coordinates":[111.02334999999999,22.47993],"type":"Point"}
}