{
  "type": "Feature",
  "properties": {
    "gn:admin1_code":"11",
    "gn:asciiname":"Changtangjie",
    "gn:country_code":"CN",
    "gn:dem":121,
    "gn:feature_class":"P",
    "gn:feature_code":"PPL",
    "gn:name":"Changtangjie",
    "gn:population":0,
    "gn:timezone":"Asia/Shanghai",
    "iso:country":"CN",
    "name:zho_x_preferred":[
        "\u957f\u5858\u8857"
    ],
    "wof:name":"Changtangjie",
    "wof:placetype":"locality"
},
  "geometry": {"coordinates":[112.04761999999999,26.69915],"type":"Point"}
}