{
  "type": "Feature",
  "properties": {
    "gn:admin1_code":"12.0",
    "gn:asciiname":"Yaochangping",
    "gn:country_code":"CN",
    "gn:dem":1214,
    "gn:feature_class":"P",
    "gn:feature_code":"PPL",
    "gn:name":"Yaochangping",
    "gn:population":0,
    "gn:timezone":"Asia/Shanghai",
    "iso:country":"CN",
    "name:zho_x_preferred":[
        "Yaochangping"
    ],
    "name:zho_x_variant":[
        "\u7a91\u5382\u576a"
    ],
    "wof:name":"Yaochangping",
    "wof:placetype":"locality"
},
  "geometry": {"coordinates":[109.77567000000001,29.77134],"type":"Point"}
}