{
  "type": "Feature",
  "properties": {
    "gn:admin1_code":"33.0",
    "gn:asciiname":"Dacaogou",
    "gn:country_code":"CN",
    "gn:dem":1339,
    "gn:feature_class":"P",
    "gn:feature_code":"PPL",
    "gn:name":"Dacaogou",
    "gn:population":0,
    "gn:timezone":"Asia/Shanghai",
    "iso:country":"CN",
    "name:zho_x_preferred":[
        "\u5927\u69fd\u6c9f"
    ],
    "wof:name":"Dacaogou",
    "wof:placetype":"locality"
},
  "geometry": {"coordinates":[108.62924,28.9748],"type":"Point"}
}