{
  "type": "Feature",
  "properties": {
    "gn:admin1_code":"14.0",
    "gn:asciiname":"Quekexiong",
    "gn:country_code":"CN",
    "gn:dem":3671,
    "gn:feature_class":"P",
    "gn:feature_code":"PPL",
    "gn:name":"Quekexiong",
    "gn:population":0,
    "gn:timezone":"Asia/Urumqi",
    "iso:country":"CN",
    "name:zho_x_preferred":[
        "\u96c0\u79d1\u96c4"
    ],
    "wof:name":"Quekexiong",
    "wof:placetype":"locality"
},
  "geometry": {"coordinates":[91.31471000000001,29.17014],"type":"Point"}
}