{
  "type": "Feature",
  "properties": {
    "gn:admin1_code":"12.0",
    "gn:asciiname":"Guanting",
    "gn:country_code":"CN",
    "gn:dem":28,
    "gn:feature_class":"P",
    "gn:feature_code":"PPL",
    "gn:name":"Guanting",
    "gn:population":0,
    "gn:timezone":"Asia/Shanghai",
    "iso:country":"CN",
    "name:deu_x_preferred":[
        "Guanting"
    ],
    "name:zho_x_preferred":[
        "\u5b98\u4ead"
    ],
    "wof:name":"Guanting",
    "wof:placetype":"locality"
},
  "geometry": {"coordinates":[113.77051000000002,30.85594],"type":"Point"}
}