{
  "type": "Feature",
  "properties": {
    "gn:admin1_code":"29",
    "gn:asciiname":"Fengdong",
    "gn:country_code":"CN",
    "gn:dem":248,
    "gn:feature_class":"P",
    "gn:feature_code":"PPL",
    "gn:name":"Fengdong",
    "gn:population":0,
    "gn:timezone":"Asia/Shanghai",
    "iso:country":"CN",
    "name:zho_x_preferred":[
        "\u98ce\u6d1e"
    ],
    "wof:name":"Fengdong",
    "wof:placetype":"locality"
},
  "geometry": {"coordinates":[106.047,23.9225],"type":"Point"}
}