{
  "type": "Feature",
  "properties": {
    "gn:admin1_code":"10.0",
    "gn:asciiname":"Zongjia Taiping",
    "gn:country_code":"CN",
    "gn:dem":900,
    "gn:feature_class":"P",
    "gn:feature_code":"PPL",
    "gn:name":"Zongjia Taiping",
    "gn:population":0,
    "gn:timezone":"Asia/Shanghai",
    "iso:country":"CN",
    "name:zho_x_preferred":[
        "\u5b97\u5bb6\u592a\u5e73"
    ],
    "wof:name":"Zongjia Taiping",
    "wof:placetype":"locality"
},
  "geometry": {"coordinates":[114.90608,40.00411],"type":"Point"}
}