{
  "type": "Feature",
  "properties": {
    "gn:admin1_code":"14.0",
    "gn:asciiname":"Shaxilong",
    "gn:country_code":"CN",
    "gn:dem":4271,
    "gn:feature_class":"P",
    "gn:feature_code":"PPL",
    "gn:name":"Shaxilong",
    "gn:population":0,
    "gn:timezone":"Asia/Urumqi",
    "iso:country":"CN",
    "name:zho_x_preferred":[
        "\u6749\u7a00\u9f99"
    ],
    "wof:name":"Shaxilong",
    "wof:placetype":"locality"
},
  "geometry": {"coordinates":[95.16687,31.01301],"type":"Point"}
}