{
  "type": "Feature",
  "properties": {
    "gn:admin1_code":"06",
    "gn:asciiname":"Daotanghe",
    "gn:country_code":"CN",
    "gn:dem":3290,
    "gn:feature_class":"P",
    "gn:feature_code":"PPLA4",
    "gn:name":"Daotanghe",
    "gn:population":0,
    "gn:timezone":"Asia/Shanghai",
    "iso:country":"CN",
    "name:und_x_variant":[
        "Tao-t\u2019ang-ho",
        "Daotanghe",
        "Daotanghe Zhen"
    ],
    "name:zho_x_preferred":[
        "\u5012\u6dcc\u6cb3"
    ],
    "name:zho_x_variant":[
        "\u5012\u6dcc\u6cb3\u9547"
    ],
    "wof:name":"Daotanghe",
    "wof:placetype":"locality"
},
  "geometry": {"coordinates":[100.96528000000001,36.39889],"type":"Point"}
}