{
  "type": "Feature",
  "properties": {
    "gn:admin1_code":"19.0",
    "gn:asciiname":"Zhangbuzi",
    "gn:country_code":"CN",
    "gn:dem":115,
    "gn:feature_class":"P",
    "gn:feature_code":"PPL",
    "gn:name":"Zhangbuzi",
    "gn:population":0,
    "gn:timezone":"Asia/Shanghai",
    "iso:country":"CN",
    "name:und_x_variant":[
        "Zhangpuzi",
        "Zhangbuzi"
    ],
    "name:zho_x_preferred":[
        "\u5f20\u5821\u5b50"
    ],
    "wof:name":"Zhangbuzi",
    "wof:placetype":"locality"
},
  "geometry": {"coordinates":[122.52099,40.31677],"type":"Point"}
}