{
  "type": "Feature",
  "properties": {
    "gn:admin1_code":"26.0",
    "gn:asciiname":"Liutuncun",
    "gn:country_code":"CN",
    "gn:dem":439,
    "gn:feature_class":"P",
    "gn:feature_code":"PPL",
    "gn:name":"Liutuncun",
    "gn:population":0,
    "gn:timezone":"Asia/Shanghai",
    "iso:country":"CN",
    "name:zho_x_preferred":[
        "\u516d\u5c6f\u6751"
    ],
    "wof:name":"Liutuncun",
    "wof:placetype":"locality"
},
  "geometry": {"coordinates":[108.10702999999999,34.18427],"type":"Point"}
}