{
  "type": "Feature",
  "properties": {
    "gn:admin1_code":"32.0",
    "gn:asciiname":"Baijiacun",
    "gn:country_code":"CN",
    "gn:dem":2311,
    "gn:feature_class":"P",
    "gn:feature_code":"PPL",
    "gn:name":"Baijiacun",
    "gn:population":0,
    "gn:timezone":"Asia/Shanghai",
    "iso:country":"CN",
    "name:zho_x_preferred":[
        "\u67cf\u5bb6\u6751"
    ],
    "wof:name":"Baijiacun",
    "wof:placetype":"locality"
},
  "geometry": {"coordinates":[102.84963,26.68213],"type":"Point"}
}