{
  "type": "Feature",
  "properties": {
    "gn:admin1_code":"3.0",
    "gn:asciiname":"Daozhuangtang",
    "gn:country_code":"CN",
    "gn:dem":152,
    "gn:feature_class":"P",
    "gn:feature_code":"PPL",
    "gn:name":"Daozhuangtang",
    "gn:population":0,
    "gn:timezone":"Asia/Shanghai",
    "iso:country":"CN",
    "name:und_x_variant":[
        "\u5230\u5e84\u5858"
    ],
    "wof:name":"Daozhuangtang",
    "wof:placetype":"locality"
},
  "geometry": {"coordinates":[116.38056,26.89146],"type":"Point"}
}