{
  "type": "Feature",
  "properties": {
    "gn:admin1_code":"9.0",
    "gn:asciiname":"Beilei",
    "gn:country_code":"CN",
    "gn:dem":67,
    "gn:feature_class":"P",
    "gn:feature_code":"PPL",
    "gn:name":"Beilei",
    "gn:population":0,
    "gn:timezone":"Asia/Shanghai",
    "iso:country":"CN",
    "name:zho_x_preferred":[
        "\u5317\u96f7"
    ],
    "wof:name":"Beilei",
    "wof:placetype":"locality"
},
  "geometry": {"coordinates":[114.18791,32.41990999999999],"type":"Point"}
}