{
  "type": "Feature",
  "properties": {
    "gn:admin1_code":"15.0",
    "gn:asciiname":"Damaidian",
    "gn:country_code":"CN",
    "gn:dem":2811,
    "gn:feature_class":"P",
    "gn:feature_code":"PPL",
    "gn:name":"Damaidian",
    "gn:population":0,
    "gn:timezone":"Asia/Shanghai",
    "iso:country":"CN",
    "name:zho_x_preferred":[
        "\u8fbe\u9ea6\u5e97"
    ],
    "wof:name":"Damaidian",
    "wof:placetype":"locality"
},
  "geometry": {"coordinates":[102.658,35.1896],"type":"Point"}
}