{
  "type": "Feature",
  "properties": {
    "gn:admin1_code":"32.0",
    "gn:asciiname":"Anshan",
    "gn:country_code":"CN",
    "gn:dem":627,
    "gn:feature_class":"P",
    "gn:feature_code":"PPL",
    "gn:name":"Anshan",
    "gn:population":0,
    "gn:timezone":"Asia/Shanghai",
    "iso:country":"CN",
    "name:afr_x_preferred":[
        "Anshan"
    ],
    "name:ara_x_preferred":[
        "\u0622\u0646\u0634\u0627\u0646"
    ],
    "name:aze_x_preferred":[
        "An\u015fan"
    ],
    "name:bul_x_preferred":[
        "\u0410\u043d\u0448\u0430\u043d"
    ],
    "name:cdo_x_preferred":[
        "\u0102ng-s\u0103ng"
    ],
    "name:ceb_x_preferred":[
        "Anshan"
    ],
    "name:ces_x_preferred":[
        "An-\u0161an"
    ],
    "name:che_x_preferred":[
        "\u0410\u043d\u044c\u0448\u0430\u043d\u044c"
    ],
    "name:dan_x_preferred":[
        "Anshan"
    ],
    "name:deu_x_preferred":[
        "Anshan"
    ],
    "name:epo_x_preferred":[
        "An\u015dano"
    ],
    "name:est_x_preferred":[
        "Anshan Shi"
    ],
    "name:eus_x_preferred":[
        "Anshan"
    ],
    "name:fas_x_preferred":[
        "\u0622\u0646\u0634\u0627\u0646"
    ],
    "name:fin_x_preferred":[
        "Anshan"
    ],
    "name:fra_x_preferred":[
        "Anshan"
    ],
    "name:glg_x_preferred":[
        "Anshan"
    ],
    "name:heb_x_preferred":[
        "\u05d0\u05e0\u05e9\u05d0\u05df"
    ],
    "name:hye_x_preferred":[
        "\u0531\u0576\u0577\u0561\u0576"
    ],
    "name:ind_x_preferred":[
        "Anshan"
    ],
    "name:ita_x_preferred":[
        "Anshan"
    ],
    "name:jpn_x_preferred":[
        "\u978d\u5c71\u5e02"
    ],
    "name:kaz_x_preferred":[
        "\u0410\u043d\u044c\u0448\u0430\u043d\u044c"
    ],
    "name:kik_x_preferred":[
        "Anshan"
    ],
    "name:kir_x_preferred":[
        "\u0410\u043d\u044c\u0448\u0430\u043d\u044c"
    ],
    "name:kor_x_preferred":[
        "\uc548\uc0b0\uc2dc"
    ],
    "name:lit_x_preferred":[
        "An\u0161anas"
    ],
    "name:mlg_x_preferred":[
        "Anshan"
    ],
    "name:nld_x_preferred":[
        "Anshan"
    ],
    "name:nno_x_preferred":[
        "Anshan"
    ],
    "name:nor_x_preferred":[
        "Anshan"
    ],
    "name:pan_x_preferred":[
        "\u0a05\u0a28\u0a38\u0a3c\u0a3e\u0a28"
    ],
    "name:pol_x_preferred":[
        "Anshan"
    ],
    "name:por_x_preferred":[
        "Anshan"
    ],
    "name:rus_x_preferred":[
        "\u0410\u043d\u044c\u0448\u0430\u043d\u044c"
    ],
    "name:sco_x_preferred":[
        "Anshan"
    ],
    "name:spa_x_preferred":[
        "Ansh\u00e1n"
    ],
    "name:srp_x_preferred":[
        "\u0410\u043d\u0448\u0430\u043d"
    ],
    "name:swe_x_preferred":[
        "Anshan"
    ],
    "name:tgl_x_preferred":[
        "Anshan"
    ],
    "name:tur_x_preferred":[
        "Anshan"
    ],
    "name:uig_x_preferred":[
        "\u0626\u06d5\u0646\u0634\u06d5\u0646 \u0634\u06d5\u06be\u0649\u0631\u0649"
    ],
    "name:ukr_x_preferred":[
        "\u0410\u043d\u044c\u0448\u0430\u043d\u044c"
    ],
    "name:urd_x_preferred":[
        "\u0627\u0646\u0634\u0627\u0646"
    ],
    "name:uzb_x_preferred":[
        "Anshan"
    ],
    "name:vie_x_preferred":[
        "An S\u01a1n"
    ],
    "name:war_x_preferred":[
        "Anshan"
    ],
    "name:wuu_x_preferred":[
        "\u978d\u5c71\u5e02"
    ],
    "name:zho_x_preferred":[
        "\u978d\u5c71"
    ],
    "name:zho_x_variant":[
        "\u978d\u5c71\u5e02"
    ],
    "wof:name":"Anshan",
    "wof:placetype":"locality"
},
  "geometry": {"coordinates":[106.78400000000001,31.6697],"type":"Point"}
}