{
  "type": "Feature",
  "properties": {
    "gn:admin1_code":"18",
    "gn:asciiname":"Xiayaoli",
    "gn:country_code":"CN",
    "gn:dem":780,
    "gn:feature_class":"P",
    "gn:feature_code":"PPL",
    "gn:name":"Xiayaoli",
    "gn:population":0,
    "gn:timezone":"Asia/Shanghai",
    "iso:country":"CN",
    "name:zho_x_preferred":[
        "\u4e0b\u7a91\u91cc"
    ],
    "wof:name":"Xiayaoli",
    "wof:placetype":"locality"
},
  "geometry": {"coordinates":[106.45,25.5037],"type":"Point"}
}