{
  "type": "Feature",
  "properties": {
    "gn:admin1_code":"26.0",
    "gn:asciiname":"Zhongyingheba",
    "gn:country_code":"CN",
    "gn:dem":1756,
    "gn:feature_class":"P",
    "gn:feature_code":"PPL",
    "gn:name":"Zhongyingheba",
    "gn:population":0,
    "gn:timezone":"Asia/Shanghai",
    "iso:country":"CN",
    "name:und_x_variant":[
        "\u4e2d\u8425\u6cb3\u575d"
    ],
    "wof:name":"Zhongyingheba",
    "wof:placetype":"locality"
},
  "geometry": {"coordinates":[107.63378,33.85736],"type":"Point"}
}