{
  "type": "Feature",
  "properties": {
    "gn:admin1_code":"29.0",
    "gn:asciiname":"Laobandeng",
    "gn:country_code":"CN",
    "gn:dem":1397,
    "gn:feature_class":"P",
    "gn:feature_code":"PPL",
    "gn:name":"Laobandeng",
    "gn:population":0,
    "gn:timezone":"Asia/Shanghai",
    "iso:country":"CN",
    "name:zho_x_preferred":[
        "\u8001\u677f\u51f3"
    ],
    "wof:name":"Laobandeng",
    "wof:placetype":"locality"
},
  "geometry": {"coordinates":[101.995,24.9732],"type":"Point"}
}