{
  "type": "Feature",
  "properties": {
    "gn:admin1_code":"11.0",
    "gn:asciiname":"Beichahu",
    "gn:country_code":"CN",
    "gn:dem":27,
    "gn:feature_class":"P",
    "gn:feature_code":"PPL",
    "gn:name":"Beichahu",
    "gn:population":0,
    "gn:timezone":"Asia/Shanghai",
    "iso:country":"CN",
    "name:zho_x_preferred":[
        "\u5317\u6c4a\u6e56"
    ],
    "wof:name":"Beichahu",
    "wof:placetype":"locality"
},
  "geometry": {"coordinates":[112.62542000000001,28.74407],"type":"Point"}
}