{
  "type": "Feature",
  "properties": {
    "gn:admin1_code":"26.0",
    "gn:asciiname":"Yaoguacun",
    "gn:country_code":"CN",
    "gn:dem":998,
    "gn:feature_class":"P",
    "gn:feature_code":"PPL",
    "gn:name":"Yaoguacun",
    "gn:population":0,
    "gn:timezone":"Asia/Shanghai",
    "iso:country":"CN",
    "name:zho_x_preferred":[
        "\u7a91\u576c\u6751"
    ],
    "wof:name":"Yaoguacun",
    "wof:placetype":"locality"
},
  "geometry": {"coordinates":[110.37003,38.23679],"type":"Point"}
}