{
  "type": "Feature",
  "properties": {
    "gn:admin1_code":"19.0",
    "gn:asciiname":"Caojiatai",
    "gn:country_code":"CN",
    "gn:dem":20,
    "gn:feature_class":"P",
    "gn:feature_code":"PPL",
    "gn:name":"Caojiatai",
    "gn:population":0,
    "gn:timezone":"Asia/Shanghai",
    "iso:country":"CN",
    "name:zho_x_preferred":[
        "\u66f9\u5bb6\u53f0"
    ],
    "wof:name":"Caojiatai",
    "wof:placetype":"locality"
},
  "geometry": {"coordinates":[122.68300000000001,41.6968],"type":"Point"}
}