{
  "type": "Feature",
  "properties": {
    "gn:admin1_code":"26.0",
    "gn:asciiname":"Dayangpo",
    "gn:country_code":"CN",
    "gn:dem":1114,
    "gn:feature_class":"P",
    "gn:feature_code":"PPL",
    "gn:name":"Dayangpo",
    "gn:population":0,
    "gn:timezone":"Asia/Shanghai",
    "iso:country":"CN",
    "name:zho_x_preferred":[
        "\u5927\u9633\u5761"
    ],
    "wof:name":"Dayangpo",
    "wof:placetype":"locality"
},
  "geometry": {"coordinates":[108.1024,32.51868],"type":"Point"}
}