{
  "type": "Feature",
  "properties": {
    "gn:admin1_code":"32.0",
    "gn:asciiname":"Kasha",
    "gn:country_code":"CN",
    "gn:dem":3825,
    "gn:feature_class":"P",
    "gn:feature_code":"PPL",
    "gn:name":"Kasha",
    "gn:population":0,
    "gn:timezone":"Asia/Shanghai",
    "iso:country":"CN",
    "name:zho_x_preferred":[
        "\u5361\u6c99"
    ],
    "wof:name":"Kasha",
    "wof:placetype":"locality"
},
  "geometry": {"coordinates":[98.9104,31.6997],"type":"Point"}
}