{
  "type": "Feature",
  "properties": {
    "gn:admin1_code":"5.0",
    "gn:asciiname":"Tuyandong",
    "gn:country_code":"CN",
    "gn:dem":27,
    "gn:feature_class":"P",
    "gn:feature_code":"PPL",
    "gn:name":"Tuyandong",
    "gn:population":0,
    "gn:timezone":"Asia/Shanghai",
    "iso:country":"CN",
    "name:und_x_variant":[
        "T\u2019u-yen-tung"
    ],
    "wof:name":"Tuyandong",
    "wof:placetype":"locality"
},
  "geometry": {"coordinates":[130.33938999999998,42.64764],"type":"Point"}
}