{
  "type": "Feature",
  "properties": {
    "gn:admin1_code":"29.0",
    "gn:asciiname":"Dujia",
    "gn:country_code":"CN",
    "gn:dem":1769,
    "gn:feature_class":"P",
    "gn:feature_code":"PPL",
    "gn:name":"Dujia",
    "gn:population":0,
    "gn:timezone":"Asia/Shanghai",
    "iso:country":"CN",
    "name:zho_x_preferred":[
        "\u72ec\u5bb6"
    ],
    "wof:name":"Dujia",
    "wof:placetype":"locality"
},
  "geometry": {"coordinates":[100.821,25.1625],"type":"Point"}
}