{
  "type": "Feature",
  "properties": {
    "gn:admin1_code":"5.0",
    "gn:asciiname":"Jiangdong",
    "gn:country_code":"CN",
    "gn:dem":738,
    "gn:feature_class":"P",
    "gn:feature_code":"PPL",
    "gn:name":"Jiangdong",
    "gn:population":0,
    "gn:timezone":"Asia/Shanghai",
    "iso:country":"CN",
    "name:deu_x_preferred":[
        "Jiangdong"
    ],
    "name:fra_x_preferred":[
        "Jiangdong"
    ],
    "name:und_x_variant":[
        "\u6c5f\u4e1c"
    ],
    "wof:name":"Jiangdong",
    "wof:placetype":"locality"
},
  "geometry": {"coordinates":[127.44328,42.29792],"type":"Point"}
}