{
  "type": "Feature",
  "properties": {
    "gn:admin1_code":"19.0",
    "gn:asciiname":"Miaojia Buzi",
    "gn:country_code":"CN",
    "gn:dem":21,
    "gn:feature_class":"P",
    "gn:feature_code":"PPL",
    "gn:name":"Miaojia Buzi",
    "gn:population":0,
    "gn:timezone":"Asia/Shanghai",
    "iso:country":"CN",
    "name:und_x_variant":[
        "Miaojiabaozi",
        "Miaojia Puzi",
        "Miaojia Buzi"
    ],
    "name:zho_x_preferred":[
        "\u82d7\u5bb6\u5821\u5b50"
    ],
    "wof:name":"Miaojia Buzi",
    "wof:placetype":"locality"
},
  "geometry": {"coordinates":[124.13473,40.00276],"type":"Point"}
}