{
  "type": "Feature",
  "properties": {
    "gn:admin1_code":"29.0",
    "gn:asciiname":"Yangla",
    "gn:country_code":"CN",
    "gn:dem":3051,
    "gn:feature_class":"P",
    "gn:feature_code":"PPL",
    "gn:name":"Yangla",
    "gn:population":0,
    "gn:timezone":"Asia/Shanghai",
    "iso:country":"CN",
    "name:zho_x_preferred":[
        "\u7f8a\u62c9"
    ],
    "wof:name":"Yangla",
    "wof:placetype":"locality"
},
  "geometry": {"coordinates":[99.03,29.1508],"type":"Point"}
}