{
  "type": "Feature",
  "properties": {
    "gn:admin1_code":"4.0",
    "gn:asciiname":"Zhaotali",
    "gn:country_code":"CN",
    "gn:dem":9,
    "gn:feature_class":"P",
    "gn:feature_code":"PPL",
    "gn:name":"Zhaotali",
    "gn:population":0,
    "gn:timezone":"Asia/Shanghai",
    "iso:country":"CN",
    "name:zho_x_preferred":[
        "\u8d75\u5854\u91cc"
    ],
    "wof:name":"Zhaotali",
    "wof:placetype":"locality"
},
  "geometry": {"coordinates":[119.82883,32.02271],"type":"Point"}
}