{
  "type": "Feature",
  "properties": {
    "gn:admin1_code":"7.0",
    "gn:asciiname":"Chongsancun",
    "gn:country_code":"CN",
    "gn:dem":182,
    "gn:feature_class":"P",
    "gn:feature_code":"PPL",
    "gn:name":"Chongsancun",
    "gn:population":0,
    "gn:timezone":"Asia/Shanghai",
    "iso:country":"CN",
    "name:zho_x_preferred":[
        "\u51b2\u4e09\u6751"
    ],
    "wof:name":"Chongsancun",
    "wof:placetype":"locality"
},
  "geometry": {"coordinates":[117.36488,26.11994],"type":"Point"}
}