{
  "type": "Feature",
  "properties": {
    "gn:admin1_code":"4.0",
    "gn:asciiname":"Dongguo",
    "gn:country_code":"CN",
    "gn:dem":4,
    "gn:feature_class":"P",
    "gn:feature_code":"PPL",
    "gn:name":"Dongguo",
    "gn:population":0,
    "gn:timezone":"Asia/Shanghai",
    "iso:country":"CN",
    "name:und_x_variant":[
        "\u4e1c\u90ed"
    ],
    "name:zho_x_preferred":[
        "\u4e1c\u90ed"
    ],
    "wof:name":"Dongguo",
    "wof:placetype":"locality"
},
  "geometry": {"coordinates":[119.85382,32.89315],"type":"Point"}
}