{
  "type": "Feature",
  "properties": {
    "gn:admin1_code":"15.0",
    "gn:asciiname":"Yongchang Chengguanzhen",
    "gn:country_code":"CN",
    "gn:dem":1919,
    "gn:feature_class":"P",
    "gn:feature_code":"PPLA3",
    "gn:name":"Yongchang Chengguanzhen",
    "gn:population":0,
    "gn:timezone":"Asia/Shanghai",
    "iso:country":"CN",
    "name:und_x_variant":[
        "Yunchan",
        "Yung-ch\u2019ang-hsien",
        "Yung-ch\u2019ang",
        "Yongchang",
        "Yongchang Chengguanzhen",
        "Yongchang Xian"
    ],
    "name:zho_x_preferred":[
        "\u6c38\u660c\u57ce\u5173\u9547"
    ],
    "name:zho_x_variant":[
        "\u6c38\u660c\u53bf"
    ],
    "wof:name":"Yongchang Chengguanzhen",
    "wof:placetype":"locality"
},
  "geometry": {"coordinates":[102.02016999999999,38.27053],"type":"Point"}
}