{
  "type": "Feature",
  "properties": {
    "gn:admin1_code":"19.0",
    "gn:asciiname":"Shangpozi",
    "gn:country_code":"CN",
    "gn:dem":30,
    "gn:feature_class":"P",
    "gn:feature_code":"PPL",
    "gn:name":"Shangpozi",
    "gn:population":0,
    "gn:timezone":"Asia/Shanghai",
    "iso:country":"CN",
    "name:zho_x_preferred":[
        "\u4e0a\u5761\u5b50"
    ],
    "wof:name":"Shangpozi",
    "wof:placetype":"locality"
},
  "geometry": {"coordinates":[120.84268,40.79096],"type":"Point"}
}