{
  "type": "Feature",
  "properties": {
    "gn:admin1_code":"30",
    "gn:asciiname":"Shaotanping",
    "gn:country_code":"CN",
    "gn:dem":381,
    "gn:feature_class":"P",
    "gn:feature_code":"PPL",
    "gn:name":"Shaotanping",
    "gn:population":0,
    "gn:timezone":"Asia/Shanghai",
    "iso:country":"CN",
    "name:und_x_variant":[
        "\u70e7\u70ad\u576a"
    ],
    "wof:name":"Shaotanping",
    "wof:placetype":"locality"
},
  "geometry": {"coordinates":[112.14534,25.01763],"type":"Point"}
}