{
  "type": "Feature",
  "properties": {
    "gn:admin1_code":"11.0",
    "gn:asciiname":"Hengguo'ao",
    "gn:country_code":"CN",
    "gn:dem":520,
    "gn:feature_class":"P",
    "gn:feature_code":"PPL",
    "gn:name":"Hengguo\u2019ao",
    "gn:population":0,
    "gn:timezone":"Asia/Shanghai",
    "iso:country":"CN",
    "name:und_x_variant":[
        "Hengguo\u2019ao"
    ],
    "name:zho_x_preferred":[
        "\u6a2a\u8fc7\u5773"
    ],
    "wof:name":"Hengguo'ao",
    "wof:placetype":"locality"
},
  "geometry": {"coordinates":[110.95695000000001,27.88502],"type":"Point"}
}