{
  "type": "Feature",
  "properties": {
    "gn:admin1_code":"26.0",
    "gn:asciiname":"Taiduocun",
    "gn:country_code":"CN",
    "gn:dem":967,
    "gn:feature_class":"P",
    "gn:feature_code":"PPL",
    "gn:name":"Taiduocun",
    "gn:population":0,
    "gn:timezone":"Asia/Shanghai",
    "iso:country":"CN",
    "name:zho_x_preferred":[
        "\u592a\u591a\u6751"
    ],
    "wof:name":"Taiduocun",
    "wof:placetype":"locality"
},
  "geometry": {"coordinates":[110.19584999999999,36.12351],"type":"Point"}
}