{
  "type": "Feature",
  "properties": {
    "gn:admin1_code":"14.0",
    "gn:asciiname":"Duosongba",
    "gn:country_code":"CN",
    "gn:dem":4367,
    "gn:feature_class":"P",
    "gn:feature_code":"PPL",
    "gn:name":"Duosongba",
    "gn:population":0,
    "gn:timezone":"Asia/Urumqi",
    "iso:country":"CN",
    "name:zho_x_preferred":[
        "\u593a\u677e\u5df4"
    ],
    "wof:name":"Duosongba",
    "wof:placetype":"locality"
},
  "geometry": {"coordinates":[94.24814000000001,29.60161],"type":"Point"}
}