{
  "type": "Feature",
  "properties": {
    "gn:admin1_code":"26.0",
    "gn:asciiname":"Daluorigou",
    "gn:country_code":"CN",
    "gn:dem":1423,
    "gn:feature_class":"P",
    "gn:feature_code":"PPL",
    "gn:name":"Daluorigou",
    "gn:population":0,
    "gn:timezone":"Asia/Shanghai",
    "iso:country":"CN",
    "name:zho_x_preferred":[
        "\u5927\u843d\u65e5\u6c9f"
    ],
    "wof:name":"Daluorigou",
    "wof:placetype":"locality"
},
  "geometry": {"coordinates":[110.36687000000001,33.81726],"type":"Point"}
}