{
  "type": "Feature",
  "properties": {
    "gn:admin1_code":"12.0",
    "gn:asciiname":"Yangping",
    "gn:country_code":"CN",
    "gn:dem":154,
    "gn:feature_class":"P",
    "gn:feature_code":"PPLA4",
    "gn:name":"Yangping",
    "gn:population":0,
    "gn:timezone":"Asia/Shanghai",
    "iso:country":"CN",
    "name:und_x_variant":[
        "Yangping Zhen"
    ],
    "name:zho_x_preferred":[
        "\u6d0b\u576a"
    ],
    "name:zho_x_variant":[
        "\u6d0b\u576a\u9547"
    ],
    "wof:name":"Yangping",
    "wof:placetype":"locality"
},
  "geometry": {"coordinates":[111.5536,31.22424],"type":"Point"}
}