{
  "type": "Feature",
  "properties": {
    "gn:admin1_code":"11.0",
    "gn:asciiname":"Ouyangjiadun",
    "gn:cc2":"CN",
    "gn:country_code":"CN",
    "gn:dem":24,
    "gn:feature_class":"P",
    "gn:feature_code":"PPL",
    "gn:name":"Ouyangjiadun",
    "gn:population":0,
    "gn:timezone":"Asia/Shanghai",
    "iso:country":"CN",
    "name:und_x_variant":[
        "Yangjiadun",
        "Ouyangjiadun"
    ],
    "wof:name":"Ouyangjiadun",
    "wof:placetype":"locality"
},
  "geometry": {"coordinates":[113.01888999999998,28.87806],"type":"Point"}
}