{
  "type": "Feature",
  "properties": {
    "gn:admin1_code":"15.0",
    "gn:asciiname":"Shangxiaocha",
    "gn:country_code":"CN",
    "gn:dem":2079,
    "gn:feature_class":"P",
    "gn:feature_code":"PPL",
    "gn:name":"Shangxiaocha",
    "gn:population":0,
    "gn:timezone":"Asia/Shanghai",
    "iso:country":"CN",
    "name:zho_x_preferred":[
        "\u4e0a\u5c0f\u5c94"
    ],
    "wof:name":"Shangxiaocha",
    "wof:placetype":"locality"
},
  "geometry": {"coordinates":[104.93899999999999,35.3646],"type":"Point"}
}