{
  "type": "Feature",
  "properties": {
    "gn:admin1_code":"30",
    "gn:asciiname":"Caiwu",
    "gn:country_code":"CN",
    "gn:dem":12,
    "gn:feature_class":"P",
    "gn:feature_code":"PPL",
    "gn:name":"Caiwu",
    "gn:population":0,
    "gn:timezone":"Asia/Urumqi",
    "iso:country":"CN",
    "name:zho_x_preferred":[
        "\u8521\u5c4b"
    ],
    "wof:name":"Caiwu",
    "wof:placetype":"locality"
},
  "geometry": {"coordinates":[110.88842,21.61675],"type":"Point"}
}