{
  "type": "Feature",
  "properties": {
    "gn:admin1_code":"26.0",
    "gn:asciiname":"Renjiagoucun",
    "gn:country_code":"CN",
    "gn:dem":1276,
    "gn:feature_class":"P",
    "gn:feature_code":"PPL",
    "gn:name":"Renjiagoucun",
    "gn:population":0,
    "gn:timezone":"Asia/Shanghai",
    "iso:country":"CN",
    "name:zho_x_preferred":[
        "\u4efb\u5bb6\u6c9f\u6751"
    ],
    "wof:name":"Renjiagoucun",
    "wof:placetype":"locality"
},
  "geometry": {"coordinates":[109.40788999999999,36.96153],"type":"Point"}
}