{
  "type": "Feature",
  "properties": {
    "gn:admin1_code":"3.0",
    "gn:asciiname":"Dongkengyuan",
    "gn:country_code":"CN",
    "gn:dem":623,
    "gn:feature_class":"P",
    "gn:feature_code":"PPL",
    "gn:name":"Dongkengyuan",
    "gn:population":0,
    "gn:timezone":"Asia/Shanghai",
    "iso:country":"CN",
    "name:und_x_variant":[
        "\u4e1c\u5751\u6e90"
    ],
    "wof:name":"Dongkengyuan",
    "wof:placetype":"locality"
},
  "geometry": {"coordinates":[114.50642999999999,29.24557],"type":"Point"}
}