{
  "type": "Feature",
  "properties": {
    "gn:admin1_code":"24.0",
    "gn:asciiname":"Lianjiagou",
    "gn:country_code":"CN",
    "gn:dem":1104,
    "gn:feature_class":"P",
    "gn:feature_code":"PPL",
    "gn:name":"Lianjiagou",
    "gn:population":0,
    "gn:timezone":"Asia/Shanghai",
    "iso:country":"CN",
    "name:zho_x_preferred":[
        "\u8fde\u5bb6\u6c9f"
    ],
    "wof:name":"Lianjiagou",
    "wof:placetype":"locality"
},
  "geometry": {"coordinates":[112.51987,36.57795],"type":"Point"}
}