{
  "type": "Feature",
  "properties": {
    "gn:admin1_code":"18",
    "gn:asciiname":"Tangshakan",
    "gn:country_code":"CN",
    "gn:dem":979,
    "gn:feature_class":"P",
    "gn:feature_code":"PPL",
    "gn:name":"Tangshakan",
    "gn:population":0,
    "gn:timezone":"Asia/Shanghai",
    "iso:country":"CN",
    "name:zho_x_preferred":[
        "\u5858\u7802\u574e"
    ],
    "wof:name":"Tangshakan",
    "wof:placetype":"locality"
},
  "geometry": {"coordinates":[107.55,28.1359],"type":"Point"}
}