{
  "type": "Feature",
  "properties": {
    "gn:admin1_code":"16.0",
    "gn:asciiname":"Nonglao",
    "gn:country_code":"CN",
    "gn:dem":632,
    "gn:feature_class":"P",
    "gn:feature_code":"PPL",
    "gn:name":"Nonglao",
    "gn:population":0,
    "gn:timezone":"Asia/Shanghai",
    "iso:country":"CN",
    "name:zho_x_preferred":[
        "\u5f04\u8001"
    ],
    "wof:name":"Nonglao",
    "wof:placetype":"locality"
},
  "geometry": {"coordinates":[107.575,24.1818],"type":"Point"}
}