{
  "type": "Feature",
  "properties": {
    "gn:admin1_code":"01",
    "gn:asciiname":"Zhelan",
    "gn:cc2":"CN",
    "gn:country_code":"CN",
    "gn:dem":35,
    "gn:feature_class":"P",
    "gn:feature_code":"PPL",
    "gn:name":"Zhelan",
    "gn:population":0,
    "gn:timezone":"Asia/Shanghai",
    "iso:country":"CN",
    "name:und_x_variant":[
        "Chulan",
        "Zhelan"
    ],
    "wof:name":"Zhelan",
    "wof:placetype":"locality"
},
  "geometry": {"coordinates":[117.33167,34.02917],"type":"Point"}
}