{
  "type": "Feature",
  "properties": {
    "gn:admin1_code":"15.0",
    "gn:asciiname":"Wubule",
    "gn:country_code":"CN",
    "gn:dem":3243,
    "gn:feature_class":"P",
    "gn:feature_code":"PPL",
    "gn:name":"Wubule",
    "gn:population":0,
    "gn:timezone":"Asia/Shanghai",
    "iso:country":"CN",
    "name:zho_x_preferred":[
        "\u4e4c\u5e03\u52d2"
    ],
    "wof:name":"Wubule",
    "wof:placetype":"locality"
},
  "geometry": {"coordinates":[103.857,33.7642],"type":"Point"}
}