{
  "type": "Feature",
  "properties": {
    "gn:admin1_code":"26",
    "gn:asciiname":"Mofanggou",
    "gn:cc2":"CN",
    "gn:country_code":"CN",
    "gn:dem":1606,
    "gn:feature_class":"P",
    "gn:feature_code":"PPL",
    "gn:name":"Mofanggou",
    "gn:population":0,
    "gn:timezone":"Asia/Shanghai",
    "iso:country":"CN",
    "name:und_x_variant":[
        "Mo-fang-kou",
        "Mofanggou"
    ],
    "wof:name":"Mofanggou",
    "wof:placetype":"locality"
},
  "geometry": {"coordinates":[107.30611,33.92389],"type":"Point"}
}