{
  "type": "Feature",
  "properties": {
    "gn:admin1_code":"32.0",
    "gn:asciiname":"Yazizui",
    "gn:country_code":"CN",
    "gn:dem":918,
    "gn:feature_class":"P",
    "gn:feature_code":"PPL",
    "gn:name":"Yazizui",
    "gn:population":0,
    "gn:timezone":"Asia/Shanghai",
    "iso:country":"CN",
    "name:zho_x_preferred":[
        "\u9e2d\u5b50\u5480"
    ],
    "wof:name":"Yazizui",
    "wof:placetype":"locality"
},
  "geometry": {"coordinates":[104.202,31.6012],"type":"Point"}
}