{
  "type": "Feature",
  "properties": {
    "gn:admin1_code":"5.0",
    "gn:asciiname":"Pengjia Wobucun",
    "gn:country_code":"CN",
    "gn:dem":129,
    "gn:feature_class":"P",
    "gn:feature_code":"PPL",
    "gn:name":"Pengjia Wobucun",
    "gn:population":0,
    "gn:timezone":"Asia/Shanghai",
    "iso:country":"CN",
    "name:zho_x_preferred":[
        "\u5f6d\u5bb6\u7a9d\u5821\u6751"
    ],
    "wof:name":"Pengjia Wobucun",
    "wof:placetype":"locality"
},
  "geometry": {"coordinates":[124.06366,43.2936],"type":"Point"}
}