{
  "type": "Feature",
  "properties": {
    "gn:admin1_code":"25.0",
    "gn:asciiname":"Yaocun",
    "gn:cc2":"CN",
    "gn:country_code":"CN",
    "gn:dem":66,
    "gn:feature_class":"P",
    "gn:feature_code":"PPL",
    "gn:name":"Yaocun",
    "gn:population":0,
    "gn:timezone":"Asia/Shanghai",
    "iso:country":"CN",
    "name:und_x_variant":[
        "Yao-ts\u2019un",
        "Yaocun"
    ],
    "wof:name":"Yaocun",
    "wof:placetype":"locality"
},
  "geometry": {"coordinates":[116.92306000000001,35.66611],"type":"Point"}
}