{
  "type": "Feature",
  "properties": {
    "gn:admin1_code":"13",
    "gn:asciiname":"Erer Tuanchang",
    "gn:country_code":"CN",
    "gn:dem":1056,
    "gn:feature_class":"P",
    "gn:feature_code":"PPLF",
    "gn:name":"Erer Tuanchang",
    "gn:population":0,
    "gn:timezone":"Asia/Urumqi",
    "iso:country":"CN",
    "name:und_x_variant":[
        "\u4e8c\u4e8c\u56e2\u573a"
    ],
    "wof:name":"Erer Tuanchang",
    "wof:placetype":"locality"
},
  "geometry": {"coordinates":[86.56495,42.17788],"type":"Point"}
}