{
  "type": "Feature",
  "properties": {
    "gn:admin1_code":"9.0",
    "gn:asciiname":"Xiaohuangqiao",
    "gn:country_code":"CN",
    "gn:dem":86,
    "gn:feature_class":"P",
    "gn:feature_code":"PPL",
    "gn:name":"Xiaohuangqiao",
    "gn:population":0,
    "gn:timezone":"Asia/Shanghai",
    "iso:country":"CN",
    "name:zho_x_preferred":[
        "\u5c0f\u9ec4\u6865"
    ],
    "wof:name":"Xiaohuangqiao",
    "wof:placetype":"locality"
},
  "geometry": {"coordinates":[113.79643,34.13179],"type":"Point"}
}