{
  "type": "Feature",
  "properties": {
    "gn:admin1_code":"4.0",
    "gn:asciiname":"Shanzuitou Wangjia",
    "gn:country_code":"CN",
    "gn:dem":10,
    "gn:feature_class":"P",
    "gn:feature_code":"PPL",
    "gn:name":"Shanzuitou Wangjia",
    "gn:population":0,
    "gn:timezone":"Asia/Shanghai",
    "iso:country":"CN",
    "name:zho_x_preferred":[
        "\u5c71\u5634\u5934\u738b\u5bb6"
    ],
    "wof:name":"Shanzuitou Wangjia",
    "wof:placetype":"locality"
},
  "geometry": {"coordinates":[119.74222,32.07031],"type":"Point"}
}