{
  "type": "Feature",
  "properties": {
    "gn:admin1_code":"10.0",
    "gn:asciiname":"Lujiayu",
    "gn:country_code":"CN",
    "gn:dem":313,
    "gn:feature_class":"P",
    "gn:feature_code":"PPL",
    "gn:name":"Lujiayu",
    "gn:population":0,
    "gn:timezone":"Asia/Shanghai",
    "iso:country":"CN",
    "name:und_x_variant":[
        "\u9c81\u5bb6\u5cea"
    ],
    "wof:name":"Lujiayu",
    "wof:placetype":"locality"
},
  "geometry": {"coordinates":[114.40045000000001,38.6854],"type":"Point"}
}