{
  "type": "Feature",
  "properties": {
    "gn:admin1_code":"11.0",
    "gn:asciiname":"Xikengzi",
    "gn:country_code":"CN",
    "gn:dem":636,
    "gn:feature_class":"P",
    "gn:feature_code":"PPL",
    "gn:name":"Xikengzi",
    "gn:population":0,
    "gn:timezone":"Asia/Shanghai",
    "iso:country":"CN",
    "name:zho_x_preferred":[
        "\u897f\u5751\u5b50"
    ],
    "wof:name":"Xikengzi",
    "wof:placetype":"locality"
},
  "geometry": {"coordinates":[114.10563,26.13023],"type":"Point"}
}