{
  "type": "Feature",
  "properties": {
    "gn:admin1_code":"32.0",
    "gn:asciiname":"Maqu",
    "gn:country_code":"CN",
    "gn:dem":4193,
    "gn:feature_class":"P",
    "gn:feature_code":"PPL",
    "gn:name":"Maqu",
    "gn:population":0,
    "gn:timezone":"Asia/Shanghai",
    "iso:country":"CN",
    "name:zho_x_preferred":[
        "\u9ebb\u66f2"
    ],
    "wof:name":"Maqu",
    "wof:placetype":"locality"
},
  "geometry": {"coordinates":[98.38249999999999,33.0137],"type":"Point"}
}