{
  "type": "Feature",
  "properties": {
    "gn:admin1_code":"26.0",
    "gn:asciiname":"Lincaogou",
    "gn:country_code":"CN",
    "gn:dem":1083,
    "gn:feature_class":"P",
    "gn:feature_code":"PPL",
    "gn:name":"Lincaogou",
    "gn:population":0,
    "gn:timezone":"Asia/Shanghai",
    "iso:country":"CN",
    "name:zho_x_preferred":[
        "\u6797\u66f9\u6c9f"
    ],
    "wof:name":"Lincaogou",
    "wof:placetype":"locality"
},
  "geometry": {"coordinates":[110.12867,33.67496],"type":"Point"}
}