{
  "type": "Feature",
  "properties": {
    "gn:admin1_code":"25",
    "gn:asciiname":"Beiyuezhuang",
    "gn:country_code":"CN",
    "gn:dem":73,
    "gn:feature_class":"P",
    "gn:feature_code":"PPL",
    "gn:name":"Beiyuezhuang",
    "gn:population":0,
    "gn:timezone":"Asia/Shanghai",
    "iso:country":"CN",
    "name:zho_x_preferred":[
        "\u5317\u6708\u5e84"
    ],
    "wof:name":"Beiyuezhuang",
    "wof:placetype":"locality"
},
  "geometry": {"coordinates":[118.741,34.9492],"type":"Point"}
}