{
  "type": "Feature",
  "properties": {
    "gn:admin1_code":"16.0",
    "gn:asciiname":"Bingtun",
    "gn:country_code":"CN",
    "gn:dem":478,
    "gn:feature_class":"P",
    "gn:feature_code":"PPL",
    "gn:name":"Bingtun",
    "gn:population":0,
    "gn:timezone":"Asia/Shanghai",
    "iso:country":"CN",
    "name:zho_x_preferred":[
        "\u5175\u5c6f"
    ],
    "wof:name":"Bingtun",
    "wof:placetype":"locality"
},
  "geometry": {"coordinates":[107.23999999999999,23.0507],"type":"Point"}
}