{
  "type": "Feature",
  "properties": {
    "gn:admin1_code":"29.0",
    "gn:asciiname":"Bangguo",
    "gn:country_code":"CN",
    "gn:dem":1748,
    "gn:feature_class":"P",
    "gn:feature_code":"PPL",
    "gn:name":"Bangguo",
    "gn:population":0,
    "gn:timezone":"Asia/Shanghai",
    "iso:country":"CN",
    "name:zho_x_preferred":[
        "\u90a6\u8fc7"
    ],
    "wof:name":"Bangguo",
    "wof:placetype":"locality"
},
  "geometry": {"coordinates":[99.676,23.0102],"type":"Point"}
}