{
  "type": "Feature",
  "properties": {
    "gn:admin1_code":"29.0",
    "gn:asciiname":"Tianweiba",
    "gn:country_code":"CN",
    "gn:dem":2268,
    "gn:feature_class":"P",
    "gn:feature_code":"PPL",
    "gn:name":"Tianweiba",
    "gn:population":0,
    "gn:timezone":"Asia/Shanghai",
    "iso:country":"CN",
    "name:und_x_variant":[
        "\u7530\u5c3e\u5df4"
    ],
    "wof:name":"Tianweiba",
    "wof:placetype":"locality"
},
  "geometry": {"coordinates":[103.20142,26.57967],"type":"Point"}
}