{
  "type": "Feature",
  "properties": {
    "gn:admin1_code":"26.0",
    "gn:asciiname":"Huaishutacun",
    "gn:country_code":"CN",
    "gn:dem":1183,
    "gn:feature_class":"P",
    "gn:feature_code":"PPL",
    "gn:name":"Huaishutacun",
    "gn:population":0,
    "gn:timezone":"Asia/Shanghai",
    "iso:country":"CN",
    "name:zho_x_preferred":[
        "\u69d0\u6811\u5854\u6751"
    ],
    "wof:name":"Huaishutacun",
    "wof:placetype":"locality"
},
  "geometry": {"coordinates":[110.51618000000001,38.55101],"type":"Point"}
}