{
  "type": "Feature",
  "properties": {
    "gn:admin1_code":"21.0",
    "gn:asciiname":"Xiaodundun",
    "gn:country_code":"CN",
    "gn:dem":1378,
    "gn:feature_class":"P",
    "gn:feature_code":"PPL",
    "gn:name":"Xiaodundun",
    "gn:population":0,
    "gn:timezone":"Asia/Shanghai",
    "iso:country":"CN",
    "name:zho_x_preferred":[
        "\u5c0f\u58a9\u58a9"
    ],
    "wof:name":"Xiaodundun",
    "wof:placetype":"locality"
},
  "geometry": {"coordinates":[105.886,38.3761],"type":"Point"}
}