{
  "type": "Feature",
  "properties": {
    "gn:admin1_code":"33.0",
    "gn:asciiname":"Huangling",
    "gn:country_code":"CN",
    "gn:dem":513,
    "gn:feature_class":"P",
    "gn:feature_code":"PPL",
    "gn:name":"Huangling",
    "gn:population":0,
    "gn:timezone":"Asia/Shanghai",
    "iso:country":"CN",
    "name:zho_x_preferred":[
        "\u9ec4\u5cad"
    ],
    "wof:name":"Huangling",
    "wof:placetype":"locality"
},
  "geometry": {"coordinates":[108.0355,30.89671],"type":"Point"}
}