{
  "type": "Feature",
  "properties": {
    "gn:admin1_code":"32.0",
    "gn:asciiname":"Wangjia Shangling",
    "gn:country_code":"CN",
    "gn:dem":552,
    "gn:feature_class":"P",
    "gn:feature_code":"PPL",
    "gn:name":"Wangjia Shangling",
    "gn:population":0,
    "gn:timezone":"Asia/Shanghai",
    "iso:country":"CN",
    "name:und_x_variant":[
        "\u738b\u5bb6\u4e0a\u5cad"
    ],
    "wof:name":"Wangjia Shangling",
    "wof:placetype":"locality"
},
  "geometry": {"coordinates":[106.0001,32.36507],"type":"Point"}
}