{
  "type": "Feature",
  "properties": {
    "gn:admin1_code":"29",
    "gn:asciiname":"Xiaoqingshu",
    "gn:country_code":"CN",
    "gn:dem":1604,
    "gn:feature_class":"P",
    "gn:feature_code":"PPL",
    "gn:name":"Xiaoqingshu",
    "gn:population":0,
    "gn:timezone":"Asia/Shanghai",
    "iso:country":"CN",
    "name:zho_x_preferred":[
        "\u5c0f\u9752\u6811"
    ],
    "wof:name":"Xiaoqingshu",
    "wof:placetype":"locality"
},
  "geometry": {"coordinates":[101.848,24.914],"type":"Point"}
}