{
  "type": "Feature",
  "properties": {
    "gn:admin1_code":"1.0",
    "gn:asciiname":"Yuechangcun",
    "gn:country_code":"CN",
    "gn:dem":21,
    "gn:feature_class":"P",
    "gn:feature_code":"PPL",
    "gn:name":"Yuechangcun",
    "gn:population":0,
    "gn:timezone":"Asia/Shanghai",
    "iso:country":"CN",
    "name:zho_x_preferred":[
        "\u5cb3\u573a\u6751"
    ],
    "wof:name":"Yuechangcun",
    "wof:placetype":"locality"
},
  "geometry": {"coordinates":[117.91088999999999,33.66913],"type":"Point"}
}