{
  "type": "Feature",
  "properties": {
    "gn:admin1_code":"25.0",
    "gn:asciiname":"Dongdingzhuangcun",
    "gn:country_code":"CN",
    "gn:dem":38,
    "gn:feature_class":"P",
    "gn:feature_code":"PPL",
    "gn:name":"Dongdingzhuangcun",
    "gn:population":0,
    "gn:timezone":"Asia/Shanghai",
    "iso:country":"CN",
    "name:zho_x_preferred":[
        "\u4e1c\u4e01\u5e84\u6751"
    ],
    "wof:name":"Dongdingzhuangcun",
    "wof:placetype":"locality"
},
  "geometry": {"coordinates":[115.91694,36.88226],"type":"Point"}
}