{
  "type": "Feature",
  "properties": {
    "gn:admin1_code":"29.0",
    "gn:asciiname":"Damangran",
    "gn:country_code":"CN",
    "gn:dem":845,
    "gn:feature_class":"P",
    "gn:feature_code":"PPL",
    "gn:name":"Damangran",
    "gn:population":0,
    "gn:timezone":"Asia/Shanghai",
    "iso:country":"CN",
    "name:zho_x_preferred":[
        "\u5927\u8292\u67d3"
    ],
    "wof:name":"Damangran",
    "wof:placetype":"locality"
},
  "geometry": {"coordinates":[97.9247,24.6321],"type":"Point"}
}