{
  "type": "Feature",
  "properties": {
    "gn:admin1_code":"11.0",
    "gn:asciiname":"Qianjiazui",
    "gn:country_code":"CN",
    "gn:dem":67,
    "gn:feature_class":"P",
    "gn:feature_code":"PPL",
    "gn:name":"Qianjiazui",
    "gn:population":0,
    "gn:timezone":"Asia/Shanghai",
    "iso:country":"CN",
    "name:zho_x_preferred":[
        "Qianjiazui"
    ],
    "name:zho_x_variant":[
        "\u94b1\u5bb6\u5480"
    ],
    "wof:name":"Qianjiazui",
    "wof:placetype":"locality"
},
  "geometry": {"coordinates":[111.82514999999999,29.37163],"type":"Point"}
}