{
  "type": "Feature",
  "properties": {
    "gn:admin1_code":"31",
    "gn:asciiname":"Shisuo",
    "gn:country_code":"CN",
    "gn:dem":16,
    "gn:feature_class":"P",
    "gn:feature_code":"PPL",
    "gn:name":"Shisuo",
    "gn:population":0,
    "gn:timezone":"Asia/Shanghai",
    "iso:country":"CN",
    "name:und_x_variant":[
        "Shih-so",
        "Shisuo",
        "\u5341\u6240"
    ],
    "wof:name":"Shisuo",
    "wof:placetype":"locality"
},
  "geometry": {"coordinates":[108.649,19.0545],"type":"Point"}
}