{
  "type": "Feature",
  "properties": {
    "gn:admin1_code":"15.0",
    "gn:asciiname":"Gejiazhai",
    "gn:country_code":"CN",
    "gn:dem":2516,
    "gn:feature_class":"P",
    "gn:feature_code":"PPL",
    "gn:name":"Gejiazhai",
    "gn:population":0,
    "gn:timezone":"Asia/Shanghai",
    "iso:country":"CN",
    "name:zho_x_preferred":[
        "\u845b\u5bb6\u5be8"
    ],
    "wof:name":"Gejiazhai",
    "wof:placetype":"locality"
},
  "geometry": {"coordinates":[104.33799999999999,35.4524],"type":"Point"}
}