{
  "type": "Feature",
  "properties": {
    "gn:admin1_code":"9",
    "gn:asciiname":"Panguningfu",
    "gn:country_code":"CN",
    "gn:dem":52,
    "gn:feature_class":"P",
    "gn:feature_code":"PPL",
    "gn:name":"Panguningfu",
    "gn:population":0,
    "gn:timezone":"Asia/Shanghai",
    "iso:country":"CN",
    "name:zho_x_preferred":[
        "\u6f58\u53e4\u5b81\u752b"
    ],
    "wof:name":"Panguningfu",
    "wof:placetype":"locality"
},
  "geometry": {"coordinates":[115.21476,36.12854],"type":"Point"}
}