{
  "type": "Feature",
  "properties": {
    "gn:admin1_code":"26",
    "gn:asciiname":"Dongchuan",
    "gn:cc2":"CN",
    "gn:country_code":"CN",
    "gn:dem":700,
    "gn:feature_class":"P",
    "gn:feature_code":"PPL",
    "gn:name":"Dongchuan",
    "gn:population":0,
    "gn:timezone":"Asia/Shanghai",
    "iso:country":"CN",
    "name:und_x_variant":[
        "Tung-ch\u2019uan-chen",
        "Dongchuanjie",
        "Tung-ch\u2019uan",
        "Tung-ch\u2019uan-chieh",
        "Dongchuan"
    ],
    "wof:name":"Dongchuan",
    "wof:placetype":"locality"
},
  "geometry": {"coordinates":[108.84721999999999,33.5425],"type":"Point"}
}