{
  "type": "Feature",
  "properties": {
    "gn:admin1_code":"7.0",
    "gn:asciiname":"Guchunyang",
    "gn:country_code":"CN",
    "gn:dem":619,
    "gn:feature_class":"P",
    "gn:feature_code":"PPL",
    "gn:name":"Guchunyang",
    "gn:population":0,
    "gn:timezone":"Asia/Shanghai",
    "iso:country":"CN",
    "name:zho_x_preferred":[
        "\u53e4\u6625\u6d0b"
    ],
    "wof:name":"Guchunyang",
    "wof:placetype":"locality"
},
  "geometry": {"coordinates":[118.00564,25.63547],"type":"Point"}
}