{
  "type": "Feature",
  "properties": {
    "gn:admin1_code":"3.0",
    "gn:asciiname":"Beitujia",
    "gn:country_code":"CN",
    "gn:dem":26,
    "gn:feature_class":"P",
    "gn:feature_code":"PPL",
    "gn:name":"Beitujia",
    "gn:population":0,
    "gn:timezone":"Asia/Shanghai",
    "iso:country":"CN",
    "name:und_x_variant":[
        "\u5317\u6d82\u5bb6"
    ],
    "wof:name":"Beitujia",
    "wof:placetype":"locality"
},
  "geometry": {"coordinates":[116.18673,28.57793],"type":"Point"}
}