{
  "type": "Feature",
  "properties": {
    "gn:admin1_code":"18",
    "gn:asciiname":"Sangzhai",
    "gn:country_code":"CN",
    "gn:dem":1245,
    "gn:feature_class":"P",
    "gn:feature_code":"PPL",
    "gn:name":"Sangzhai",
    "gn:population":0,
    "gn:timezone":"Asia/Shanghai",
    "iso:country":"CN",
    "name:zho_x_preferred":[
        "\u6851\u5be8"
    ],
    "wof:name":"Sangzhai",
    "wof:placetype":"locality"
},
  "geometry": {"coordinates":[105.66800000000001,26.1192],"type":"Point"}
}