{
  "type": "Feature",
  "properties": {
    "gn:admin1_code":"9.0",
    "gn:asciiname":"Chengjiao",
    "gn:country_code":"CN",
    "gn:dem":195,
    "gn:feature_class":"P",
    "gn:feature_code":"PPLA4",
    "gn:name":"Chengjiao",
    "gn:population":0,
    "gn:timezone":"Asia/Shanghai",
    "iso:country":"CN",
    "name:ceb_x_preferred":[
        "Chengjiao"
    ],
    "name:deu_x_preferred":[
        "Chengjiao"
    ],
    "name:swe_x_preferred":[
        "Chengjiao"
    ],
    "name:und_x_variant":[
        "\u57ce\u90ca",
        "Chengjiao"
    ],
    "wof:name":"Chengjiao",
    "wof:placetype":"locality"
},
  "geometry": {"coordinates":[112.44042,33.48755999999999],"type":"Point"}
}