{
  "type": "Feature",
  "properties": {
    "gn:admin1_code":"30",
    "gn:asciiname":"Shibei Chachang",
    "gn:country_code":"CN",
    "gn:dem":740,
    "gn:feature_class":"P",
    "gn:feature_code":"PPL",
    "gn:name":"Shibei Chachang",
    "gn:population":0,
    "gn:timezone":"Asia/Shanghai",
    "iso:country":"CN",
    "name:zho_x_preferred":[
        "\u77f3\u5317\u8336\u573a"
    ],
    "wof:name":"Shibei Chachang",
    "wof:placetype":"locality"
},
  "geometry": {"coordinates":[116.92349,24.10954],"type":"Point"}
}