{
  "type": "Feature",
  "properties": {
    "gn:admin1_code":"29",
    "gn:asciiname":"Mosha",
    "gn:country_code":"CN",
    "gn:dem":1347,
    "gn:feature_class":"P",
    "gn:feature_code":"PPL",
    "gn:name":"Mosha",
    "gn:population":0,
    "gn:timezone":"Asia/Shanghai",
    "iso:country":"CN",
    "name:fas_x_preferred":[
        "\u0645\u0634\u0627"
    ],
    "name:zho_x_preferred":[
        "\u78e8\u6c99"
    ],
    "wof:name":"Mosha",
    "wof:placetype":"locality"
},
  "geometry": {"coordinates":[103.087,24.2743],"type":"Point"}
}