{
  "type": "Feature",
  "properties": {
    "gn:admin1_code":"13",
    "gn:asciiname":"Talakuole",
    "gn:country_code":"CN",
    "gn:dem":1038,
    "gn:feature_class":"P",
    "gn:feature_code":"PPL",
    "gn:name":"Talakuole",
    "gn:population":0,
    "gn:timezone":"Asia/Shanghai",
    "iso:country":"CN",
    "name:und_x_variant":[
        "\u5854\u62c9\u9614\u52d2"
    ],
    "wof:name":"Talakuole",
    "wof:placetype":"locality"
},
  "geometry": {"coordinates":[80.52417,40.28644],"type":"Point"}
}