{
  "type": "Feature",
  "properties": {
    "gn:admin1_code":"8.0",
    "gn:asciiname":"Hongguang",
    "gn:country_code":"CN",
    "gn:dem":188,
    "gn:feature_class":"P",
    "gn:feature_code":"PPLA4",
    "gn:name":"Hongguang",
    "gn:population":0,
    "gn:timezone":"Asia/Shanghai",
    "iso:country":"CN",
    "name:und_x_variant":[
        "Hongguang Xiang"
    ],
    "name:zho_x_preferred":[
        "\u7ea2\u5149"
    ],
    "name:zho_x_variant":[
        "\u7ea2\u5149\u4e61"
    ],
    "wof:name":"Hongguang",
    "wof:placetype":"locality"
},
  "geometry": {"coordinates":[126.28695,46.34354],"type":"Point"}
}