{
  "type": "Feature",
  "properties": {
    "gn:admin1_code":"5.0",
    "gn:asciiname":"Xiaojilecun",
    "gn:country_code":"CN",
    "gn:dem":414,
    "gn:feature_class":"P",
    "gn:feature_code":"PPL",
    "gn:name":"Xiaojilecun",
    "gn:population":0,
    "gn:timezone":"Asia/Shanghai",
    "iso:country":"CN",
    "name:zho_x_preferred":[
        "\u5c0f\u5409\u4e50\u6751"
    ],
    "wof:name":"Xiaojilecun",
    "wof:placetype":"locality"
},
  "geometry": {"coordinates":[125.52024,42.25624000000001],"type":"Point"}
}