{
  "type": "Feature",
  "properties": {
    "gn:admin1_code":"12.0",
    "gn:asciiname":"Youda Citang",
    "gn:country_code":"CN",
    "gn:dem":216,
    "gn:feature_class":"P",
    "gn:feature_code":"PPL",
    "gn:name":"Youda Citang",
    "gn:population":0,
    "gn:timezone":"Asia/Shanghai",
    "iso:country":"CN",
    "name:zho_x_preferred":[
        "\u6e38\u5927\u7960\u5802"
    ],
    "wof:name":"Youda Citang",
    "wof:placetype":"locality"
},
  "geometry": {"coordinates":[115.32002,30.39812],"type":"Point"}
}