{
  "type": "Feature",
  "properties": {
    "gn:admin1_code":"16.0",
    "gn:asciiname":"Luojiu",
    "gn:country_code":"CN",
    "gn:dem":127,
    "gn:feature_class":"P",
    "gn:feature_code":"PPL",
    "gn:name":"Luojiu",
    "gn:population":0,
    "gn:timezone":"Asia/Shanghai",
    "iso:country":"CN",
    "name:zho_x_preferred":[
        "\u843d\u4e45"
    ],
    "wof:name":"Luojiu",
    "wof:placetype":"locality"
},
  "geometry": {"coordinates":[109.26600000000001,25.1491],"type":"Point"}
}