{
  "type": "Feature",
  "properties": {
    "gn:admin1_code":"16.0",
    "gn:asciiname":"Zuwang",
    "gn:country_code":"CN",
    "gn:dem":546,
    "gn:feature_class":"P",
    "gn:feature_code":"PPL",
    "gn:name":"Zuwang",
    "gn:population":0,
    "gn:timezone":"Asia/Shanghai",
    "iso:country":"CN",
    "name:zho_x_preferred":[
        "\u7956\u738b"
    ],
    "wof:name":"Zuwang",
    "wof:placetype":"locality"
},
  "geometry": {"coordinates":[107.505,24.1717],"type":"Point"}
}