{
  "type": "Feature",
  "properties": {
    "gn:admin1_code":"18",
    "gn:asciiname":"Shanggaoshan",
    "gn:country_code":"CN",
    "gn:dem":1274,
    "gn:feature_class":"P",
    "gn:feature_code":"PPL",
    "gn:name":"Shanggaoshan",
    "gn:population":0,
    "gn:timezone":"Asia/Shanghai",
    "iso:country":"CN",
    "name:zho_x_preferred":[
        "\u4e0a\u9ad8\u5c71"
    ],
    "wof:name":"Shanggaoshan",
    "wof:placetype":"locality"
},
  "geometry": {"coordinates":[106.642,26.7088],"type":"Point"}
}