{
  "type": "Feature",
  "properties": {
    "gn:admin1_code":"4.0",
    "gn:asciiname":"Yinji",
    "gn:cc2":"CN",
    "gn:country_code":"CN",
    "gn:dem":5,
    "gn:feature_class":"P",
    "gn:feature_code":"PPL",
    "gn:name":"Yinji",
    "gn:population":0,
    "gn:timezone":"Asia/Shanghai",
    "iso:country":"CN",
    "name:und_x_variant":[
        "Yin-chia-chi",
        "Yin-chi",
        "Yinji"
    ],
    "wof:name":"Yinji",
    "wof:placetype":"locality"
},
  "geometry": {"coordinates":[119.18333,33.03333],"type":"Point"}
}