{
  "type": "Feature",
  "properties": {
    "gn:admin1_code":"26.0",
    "gn:asciiname":"Fengpingcun",
    "gn:country_code":"CN",
    "gn:dem":666,
    "gn:feature_class":"P",
    "gn:feature_code":"PPL",
    "gn:name":"Fengpingcun",
    "gn:population":0,
    "gn:timezone":"Asia/Shanghai",
    "iso:country":"CN",
    "name:zho_x_preferred":[
        "\u67ab\u576a\u6751"
    ],
    "wof:name":"Fengpingcun",
    "wof:placetype":"locality"
},
  "geometry": {"coordinates":[108.86597,33.3161],"type":"Point"}
}