{
  "type": "Feature",
  "properties": {
    "gn:admin1_code":"18",
    "gn:asciiname":"Niuchang",
    "gn:cc2":"CN",
    "gn:country_code":"CN",
    "gn:dem":974,
    "gn:feature_class":"P",
    "gn:feature_code":"PPL",
    "gn:name":"Niuchang",
    "gn:population":0,
    "gn:timezone":"Asia/Shanghai",
    "iso:country":"CN",
    "name:und_x_variant":[
        "Niuchang Zhen",
        "Niuchang"
    ],
    "wof:name":"Niuchang",
    "wof:placetype":"locality"
},
  "geometry": {"coordinates":[107.58638999999999,26.23972],"type":"Point"}
}