{
  "type": "Feature",
  "properties": {
    "gn:admin1_code":"2.0",
    "gn:asciiname":"Wenkeng",
    "gn:country_code":"CN",
    "gn:dem":481,
    "gn:feature_class":"P",
    "gn:feature_code":"PPL",
    "gn:name":"Wenkeng",
    "gn:population":0,
    "gn:timezone":"Asia/Shanghai",
    "iso:country":"CN",
    "name:zho_x_preferred":[
        "\u6587\u5751"
    ],
    "wof:name":"Wenkeng",
    "wof:placetype":"locality"
},
  "geometry": {"coordinates":[119.16549999999999,28.24696],"type":"Point"}
}