{
  "type": "Feature",
  "properties": {
    "gn:admin1_code":"26",
    "gn:asciiname":"Heijiapu",
    "gn:cc2":"CN",
    "gn:country_code":"CN",
    "gn:dem":923,
    "gn:feature_class":"P",
    "gn:feature_code":"PPL",
    "gn:name":"Heijiapu",
    "gn:population":0,
    "gn:timezone":"Asia/Shanghai",
    "iso:country":"CN",
    "name:und_x_variant":[
        "Hei-chia-p\u2019u",
        "Heijiapu"
    ],
    "wof:name":"Heijiapu",
    "wof:placetype":"locality"
},
  "geometry": {"coordinates":[109.88333,36.66667],"type":"Point"}
}