{
  "type": "Feature",
  "properties": {
    "gn:admin1_code":"07",
    "gn:asciiname":"Bailin",
    "gn:country_code":"CN",
    "gn:dem":54,
    "gn:feature_class":"P",
    "gn:feature_code":"PPL",
    "gn:name":"Bailin",
    "gn:population":0,
    "gn:timezone":"Asia/Shanghai",
    "iso:country":"CN",
    "name:und_x_variant":[
        "Pai-lin",
        "Pai-tin",
        "Bailin"
    ],
    "wof:name":"Bailin",
    "wof:placetype":"locality"
},
  "geometry": {"coordinates":[120.16341,27.18132],"type":"Point"}
}