{
  "type": "Feature",
  "properties": {
    "gn:admin1_code":"8.0",
    "gn:asciiname":"Yanjun Shisidui",
    "gn:country_code":"CN",
    "gn:dem":126,
    "gn:feature_class":"P",
    "gn:feature_code":"PPLF",
    "gn:name":"Yanjun Shisidui",
    "gn:population":0,
    "gn:timezone":"Asia/Shanghai",
    "iso:country":"CN",
    "name:zho_x_preferred":[
        "\u5ef6\u519b\u5341\u56db\u961f"
    ],
    "wof:name":"Yanjun Shisidui",
    "wof:placetype":"locality"
},
  "geometry": {"coordinates":[130.82159999999999,47.7927],"type":"Point"}
}