{
  "type": "Feature",
  "properties": {
    "gn:admin1_code":"29.0",
    "gn:asciiname":"Lunacun",
    "gn:country_code":"CN",
    "gn:dem":1991,
    "gn:feature_class":"P",
    "gn:feature_code":"PPL",
    "gn:name":"Lunacun",
    "gn:population":0,
    "gn:timezone":"Asia/Shanghai",
    "iso:country":"CN",
    "name:und_x_variant":[
        "\u9c81\u7eb3\u6751"
    ],
    "wof:name":"Lunacun",
    "wof:placetype":"locality"
},
  "geometry": {"coordinates":[103.63592,26.2964],"type":"Point"}
}