{
  "type": "Feature",
  "properties": {
    "gn:admin1_code":"10",
    "gn:asciiname":"Erduigou",
    "gn:country_code":"CN",
    "gn:dem":1188,
    "gn:feature_class":"P",
    "gn:feature_code":"PPL",
    "gn:name":"Erduigou",
    "gn:population":0,
    "gn:timezone":"Asia/Shanghai",
    "iso:country":"CN",
    "name:zho_x_preferred":[
        "\u4e8c\u5bf9\u6c9f"
    ],
    "wof:name":"Erduigou",
    "wof:placetype":"locality"
},
  "geometry": {"coordinates":[115.61223,41.18802],"type":"Point"}
}