{
  "type": "Feature",
  "properties": {
    "gn:admin1_code":"11.0",
    "gn:asciiname":"Taozixi",
    "gn:country_code":"CN",
    "gn:dem":99,
    "gn:feature_class":"P",
    "gn:feature_code":"PPL",
    "gn:name":"Taozixi",
    "gn:population":0,
    "gn:timezone":"Asia/Shanghai",
    "iso:country":"CN",
    "name:zho_x_preferred":[
        "Taozixi"
    ],
    "name:zho_x_variant":[
        "\u6843\u5b50\u6eaa"
    ],
    "wof:name":"Taozixi",
    "wof:placetype":"locality"
},
  "geometry": {"coordinates":[111.31735,29.49437],"type":"Point"}
}