{
  "type": "Feature",
  "properties": {
    "gn:admin1_code":"13",
    "gn:asciiname":"Luotuo Shitou",
    "gn:country_code":"CN",
    "gn:dem":875,
    "gn:feature_class":"P",
    "gn:feature_code":"PPL",
    "gn:name":"Luotuo Shitou",
    "gn:population":0,
    "gn:timezone":"Asia/Urumqi",
    "iso:country":"CN",
    "name:und_x_variant":[
        "\u9a86\u9a7c\u77f3\u5934"
    ],
    "wof:name":"Luotuo Shitou",
    "wof:placetype":"locality"
},
  "geometry": {"coordinates":[95.18486,44.21549],"type":"Point"}
}