{
  "type": "Feature",
  "properties": {
    "gn:admin1_code":"5.0",
    "gn:asciiname":"Longshengbu",
    "gn:country_code":"CN",
    "gn:dem":319,
    "gn:feature_class":"P",
    "gn:feature_code":"PPL",
    "gn:name":"Longshengbu",
    "gn:population":0,
    "gn:timezone":"Asia/Shanghai",
    "iso:country":"CN",
    "name:zho_x_preferred":[
        "\u9686\u76db\u5821"
    ],
    "wof:name":"Longshengbu",
    "wof:placetype":"locality"
},
  "geometry": {"coordinates":[126.06876,42.58353],"type":"Point"}
}