{
  "type": "Feature",
  "properties": {
    "gn:admin1_code":"25",
    "gn:asciiname":"Fenshui",
    "gn:cc2":"CN",
    "gn:country_code":"CN",
    "gn:dem":10,
    "gn:feature_class":"P",
    "gn:feature_code":"PPL",
    "gn:name":"Fenshui",
    "gn:population":0,
    "gn:timezone":"Asia/Shanghai",
    "iso:country":"CN",
    "name:ceb_x_preferred":[
        "Fenshui"
    ],
    "name:swe_x_preferred":[
        "Fenshui"
    ],
    "name:und_x_variant":[
        "Fen-shui-chen"
    ],
    "name:zho_x_preferred":[
        "\u5206\u6c34\u4e61"
    ],
    "wof:name":"Fenshui",
    "wof:placetype":"locality"
},
  "geometry": {"coordinates":[119.27861,35.13028],"type":"Point"}
}