{
  "type": "Feature",
  "properties": {
    "gn:admin1_code":"08",
    "gn:asciiname":"Yong'an",
    "gn:country_code":"CN",
    "gn:dem":223,
    "gn:feature_class":"P",
    "gn:feature_code":"PPL",
    "gn:name":"Yong\u2019an",
    "gn:population":0,
    "gn:timezone":"Asia/Shanghai",
    "iso:country":"CN",
    "name:ara_x_preferred":[
        "\u064a\u0627\u0646\u063a\u0627\u0646"
    ],
    "name:cdo_x_preferred":[
        "\u012ang-\u0103ng"
    ],
    "name:deu_x_preferred":[
        "Yong\u2019an"
    ],
    "name:fas_x_preferred":[
        "\u06cc\u0627\u0646\u06af\u0627\u0646"
    ],
    "name:fra_x_preferred":[
        "Yong'an"
    ],
    "name:hak_x_preferred":[
        "Y\u00fan-\u00f4n-s\u1e73"
    ],
    "name:ita_x_preferred":[
        "Yong'an"
    ],
    "name:jpn_x_preferred":[
        "\u6c38\u5b89\u5e02"
    ],
    "name:kik_x_preferred":[
        "Yong'an"
    ],
    "name:kor_x_preferred":[
        "\uc735\uc548\uc2dc"
    ],
    "name:mlg_x_preferred":[
        "Yong'an"
    ],
    "name:nor_x_preferred":[
        "Yong'an"
    ],
    "name:pam_x_preferred":[
        "Yong'an"
    ],
    "name:pnb_x_preferred":[
        "\u06cc\u0648\u0646\u06af \u0622\u0646"
    ],
    "name:por_x_preferred":[
        "Yong'an"
    ],
    "name:spa_x_preferred":[
        "Y\u014fng'\u0101n Sh\u00ec"
    ],
    "name:swe_x_preferred":[
        "Yong'an"
    ],
    "name:urd_x_preferred":[
        "\u06cc\u0648\u0646\u06af\u0627\u0646"
    ],
    "name:vie_x_preferred":[
        "V\u0129nh An"
    ],
    "name:war_x_preferred":[
        "Yongan"
    ],
    "name:zho_x_preferred":[
        "\u6c38\u5b89\u5e02"
    ],
    "wof:name":"Yong'an",
    "wof:placetype":"locality"
},
  "geometry": {"coordinates":[130.15000000000001,46.75],"type":"Point"}
}