{
  "type": "Feature",
  "properties": {
    "gn:admin1_code":"16.0",
    "gn:asciiname":"Dalongyong",
    "gn:country_code":"CN",
    "gn:dem":931,
    "gn:feature_class":"P",
    "gn:feature_code":"PPL",
    "gn:name":"Dalongyong",
    "gn:population":0,
    "gn:timezone":"Asia/Shanghai",
    "iso:country":"CN",
    "name:zho_x_preferred":[
        "\u5927\u62e2\u62e5"
    ],
    "wof:name":"Dalongyong",
    "wof:placetype":"locality"
},
  "geometry": {"coordinates":[107.13800000000001,25.0588],"type":"Point"}
}