{
  "type": "Feature",
  "properties": {
    "gn:admin1_code":"8.0",
    "gn:asciiname":"Xinhongcun",
    "gn:country_code":"CN",
    "gn:dem":66,
    "gn:feature_class":"P",
    "gn:feature_code":"PPL",
    "gn:name":"Xinhongcun",
    "gn:population":0,
    "gn:timezone":"Asia/Shanghai",
    "iso:country":"CN",
    "name:zho_x_preferred":[
        "\u65b0\u7ea2\u6751"
    ],
    "wof:name":"Xinhongcun",
    "wof:placetype":"locality"
},
  "geometry": {"coordinates":[132.02321000000001,46.65155],"type":"Point"}
}