{
  "type": "Feature",
  "properties": {
    "gn:admin1_code":"2.0",
    "gn:asciiname":"Qianbanhu",
    "gn:country_code":"CN",
    "gn:dem":9,
    "gn:feature_class":"P",
    "gn:feature_code":"PPL",
    "gn:name":"Qianbanhu",
    "gn:population":0,
    "gn:timezone":"Asia/Shanghai",
    "iso:country":"CN",
    "name:zho_x_preferred":[
        "\u524d\u534a\u6e56"
    ],
    "wof:name":"Qianbanhu",
    "wof:placetype":"locality"
},
  "geometry": {"coordinates":[120.95851,29.94015],"type":"Point"}
}