{
  "type": "Feature",
  "properties": {
    "gn:admin1_code":"11",
    "gn:asciiname":"Xiwuji",
    "gn:country_code":"CN",
    "gn:dem":69,
    "gn:feature_class":"P",
    "gn:feature_code":"PPL",
    "gn:name":"Xiwuji",
    "gn:population":0,
    "gn:timezone":"Asia/Shanghai",
    "iso:country":"CN",
    "name:zho_x_preferred":[
        "\u7ec6\u5c4b\u5409"
    ],
    "wof:name":"Xiwuji",
    "wof:placetype":"locality"
},
  "geometry": {"coordinates":[112.46741000000002,26.8405],"type":"Point"}
}