{
  "type": "Feature",
  "properties": {
    "gn:admin1_code":"14",
    "gn:asciiname":"Xiamai",
    "gn:country_code":"CN",
    "gn:dem":4070,
    "gn:feature_class":"P",
    "gn:feature_code":"PPL",
    "gn:name":"Xiamai",
    "gn:population":0,
    "gn:timezone":"Asia/Urumqi",
    "iso:country":"CN",
    "name:zho_x_preferred":[
        "\u590f\u9ea6"
    ],
    "wof:name":"Xiamai",
    "wof:placetype":"locality"
},
  "geometry": {"coordinates":[89.2679,29.4572],"type":"Point"}
}