{
  "type": "Feature",
  "properties": {
    "gn:admin1_code":"19.0",
    "gn:asciiname":"Mamahuolang",
    "gn:country_code":"CN",
    "gn:dem":149,
    "gn:feature_class":"P",
    "gn:feature_code":"PPL",
    "gn:name":"Mamahuolang",
    "gn:population":0,
    "gn:timezone":"Asia/Shanghai",
    "iso:country":"CN",
    "name:und_x_variant":[
        "\u5988\u5988\u8d27\u90ce"
    ],
    "name:zho_x_preferred":[
        "\u5988\u5988\u8d27\u90ce"
    ],
    "wof:name":"Mamahuolang",
    "wof:placetype":"locality"
},
  "geometry": {"coordinates":[124.20099999999999,42.3883],"type":"Point"}
}