{
  "type": "Feature",
  "properties": {
    "gn:admin1_code":"18",
    "gn:asciiname":"Fengziwo",
    "gn:country_code":"CN",
    "gn:dem":970,
    "gn:feature_class":"P",
    "gn:feature_code":"PPL",
    "gn:name":"Fengziwo",
    "gn:population":0,
    "gn:timezone":"Asia/Shanghai",
    "iso:country":"CN",
    "name:zho_x_preferred":[
        "\u8702\u5b50\u7a9d"
    ],
    "wof:name":"Fengziwo",
    "wof:placetype":"locality"
},
  "geometry": {"coordinates":[107.81100000000001,28.3203],"type":"Point"}
}