{
  "type": "Feature",
  "properties": {
    "gn:admin1_code":"5.0",
    "gn:asciiname":"Fulucun",
    "gn:country_code":"CN",
    "gn:dem":349,
    "gn:feature_class":"P",
    "gn:feature_code":"PPL",
    "gn:name":"Fulucun",
    "gn:population":0,
    "gn:timezone":"Asia/Shanghai",
    "iso:country":"CN",
    "name:zho_x_preferred":[
        "\u798f\u5f55\u6751"
    ],
    "wof:name":"Fulucun",
    "wof:placetype":"locality"
},
  "geometry": {"coordinates":[125.25295,42.72237],"type":"Point"}
}