{
  "type": "Feature",
  "properties": {
    "gn:admin1_code":"16.0",
    "gn:asciiname":"Shuiyatang",
    "gn:country_code":"CN",
    "gn:dem":27,
    "gn:feature_class":"P",
    "gn:feature_code":"PPL",
    "gn:name":"Shuiyatang",
    "gn:population":0,
    "gn:timezone":"Asia/Shanghai",
    "iso:country":"CN",
    "name:zho_x_preferred":[
        "\u6c34\u9e2d\u5858"
    ],
    "wof:name":"Shuiyatang",
    "wof:placetype":"locality"
},
  "geometry": {"coordinates":[109.416,21.6031],"type":"Point"}
}