{
  "type": "Feature",
  "properties": {
    "gn:admin1_code":"11.0",
    "gn:asciiname":"Gufutang",
    "gn:country_code":"CN",
    "gn:dem":411,
    "gn:feature_class":"P",
    "gn:feature_code":"PPL",
    "gn:name":"Gufutang",
    "gn:population":0,
    "gn:timezone":"Asia/Shanghai",
    "iso:country":"CN",
    "name:zho_x_preferred":[
        "\u8c37\u5bcc\u5858"
    ],
    "wof:name":"Gufutang",
    "wof:placetype":"locality"
},
  "geometry": {"coordinates":[112.49299999999999,25.27212],"type":"Point"}
}