{
  "type": "Feature",
  "properties": {
    "gn:admin1_code":"9.0",
    "gn:asciiname":"Tanweizi",
    "gn:country_code":"CN",
    "gn:dem":45,
    "gn:feature_class":"P",
    "gn:feature_code":"PPL",
    "gn:name":"Tanweizi",
    "gn:population":0,
    "gn:timezone":"Asia/Shanghai",
    "iso:country":"CN",
    "name:zho_x_preferred":[
        "\u8c2d\u56f4\u5b50"
    ],
    "wof:name":"Tanweizi",
    "wof:placetype":"locality"
},
  "geometry": {"coordinates":[114.87657,32.62132],"type":"Point"}
}