{
  "type": "Feature",
  "properties": {
    "gn:admin1_code":"25.0",
    "gn:asciiname":"Tiekuang",
    "gn:country_code":"CN",
    "gn:dem":161,
    "gn:feature_class":"P",
    "gn:feature_code":"PPL",
    "gn:name":"Tiekuang",
    "gn:population":0,
    "gn:timezone":"Asia/Shanghai",
    "iso:country":"CN",
    "name:zho_x_preferred":[
        "\u94c1\u593c"
    ],
    "wof:name":"Tiekuang",
    "wof:placetype":"locality"
},
  "geometry": {"coordinates":[120.34963999999999,37.30043],"type":"Point"}
}