{
  "type": "Feature",
  "properties": {
    "gn:admin1_code":"2.0",
    "gn:asciiname":"Aohu",
    "gn:country_code":"CN",
    "gn:dem":70,
    "gn:feature_class":"P",
    "gn:feature_code":"PPL",
    "gn:name":"Aohu",
    "gn:population":0,
    "gn:timezone":"Asia/Shanghai",
    "iso:country":"CN",
    "name:zho_x_preferred":[
        "\u5c99\u80e1"
    ],
    "wof:name":"Aohu",
    "wof:placetype":"locality"
},
  "geometry": {"coordinates":[121.44828,28.83195],"type":"Point"}
}