{
  "type": "Feature",
  "properties": {
    "gn:admin1_code":"10",
    "gn:asciiname":"Caoyuan",
    "gn:country_code":"CN",
    "gn:dem":1395,
    "gn:feature_class":"P",
    "gn:feature_code":"PPL",
    "gn:name":"Caoyuan",
    "gn:population":0,
    "gn:timezone":"Asia/Shanghai",
    "iso:country":"CN",
    "wof:name":"Caoyuan",
    "wof:placetype":"locality"
},
  "geometry": {"coordinates":[116.35193999999998,41.95778],"type":"Point"}
}