{
  "type": "Feature",
  "properties": {
    "gn:admin1_code":"29.0",
    "gn:asciiname":"Linggangzhai",
    "gn:country_code":"CN",
    "gn:dem":1754,
    "gn:feature_class":"P",
    "gn:feature_code":"PPL",
    "gn:name":"Linggangzhai",
    "gn:population":0,
    "gn:timezone":"Asia/Shanghai",
    "iso:country":"CN",
    "name:zho_x_preferred":[
        "\u5cad\u5c97\u5be8"
    ],
    "wof:name":"Linggangzhai",
    "wof:placetype":"locality"
},
  "geometry": {"coordinates":[99.9062,24.3359],"type":"Point"}
}