{
  "type": "Feature",
  "properties": {
    "gn:admin1_code":"1.0",
    "gn:asciiname":"Wan'ancun",
    "gn:country_code":"CN",
    "gn:dem":35,
    "gn:feature_class":"P",
    "gn:feature_code":"PPL",
    "gn:name":"Wan\u2019ancun",
    "gn:population":0,
    "gn:timezone":"Asia/Shanghai",
    "iso:country":"CN",
    "name:und_x_variant":[
        "Wan\u2019ancun"
    ],
    "name:zho_x_preferred":[
        "\u4e07\u5b89\u6751"
    ],
    "wof:name":"Wan'ancun",
    "wof:placetype":"locality"
},
  "geometry": {"coordinates":[115.78877,33.20676],"type":"Point"}
}