{
  "type": "Feature",
  "properties": {
    "gn:admin1_code":"24.0",
    "gn:asciiname":"Daguzhuanggou",
    "gn:country_code":"CN",
    "gn:dem":1101,
    "gn:feature_class":"P",
    "gn:feature_code":"PPL",
    "gn:name":"Daguzhuanggou",
    "gn:population":0,
    "gn:timezone":"Asia/Shanghai",
    "iso:country":"CN",
    "name:zho_x_preferred":[
        "\u5927\u53e4\u5e84\u6c9f"
    ],
    "wof:name":"Daguzhuanggou",
    "wof:placetype":"locality"
},
  "geometry": {"coordinates":[112.58778999999998,36.28552],"type":"Point"}
}