{
  "type": "Feature",
  "properties": {
    "gn:admin1_code":"16.0",
    "gn:asciiname":"Bagao",
    "gn:country_code":"CN",
    "gn:dem":465,
    "gn:feature_class":"P",
    "gn:feature_code":"PPL",
    "gn:name":"Bagao",
    "gn:population":0,
    "gn:timezone":"Asia/Shanghai",
    "iso:country":"CN",
    "name:zho_x_preferred":[
        "\u516b\u9ad8"
    ],
    "wof:name":"Bagao",
    "wof:placetype":"locality"
},
  "geometry": {"coordinates":[106.15600000000001,24.2488],"type":"Point"}
}