{
  "type": "Feature",
  "properties": {
    "gn:admin1_code":"26.0",
    "gn:asciiname":"Juchigou",
    "gn:country_code":"CN",
    "gn:dem":1943,
    "gn:feature_class":"P",
    "gn:feature_code":"PPL",
    "gn:name":"Juchigou",
    "gn:population":0,
    "gn:timezone":"Asia/Shanghai",
    "iso:country":"CN",
    "name:und_x_variant":[
        "\u952f\u9f7f\u6c9f"
    ],
    "wof:name":"Juchigou",
    "wof:placetype":"locality"
},
  "geometry": {"coordinates":[107.6052,33.76444],"type":"Point"}
}