{
  "type": "Feature",
  "properties": {
    "gn:admin1_code":"8.0",
    "gn:asciiname":"Erdaowan",
    "gn:country_code":"CN",
    "gn:dem":195,
    "gn:feature_class":"P",
    "gn:feature_code":"PPLA4",
    "gn:name":"Erdaowan",
    "gn:population":0,
    "gn:timezone":"Asia/Shanghai",
    "iso:country":"CN",
    "name:und_x_variant":[
        "Erdaowan Zhen"
    ],
    "name:zho_x_preferred":[
        "\u4e8c\u9053\u6e7e"
    ],
    "name:zho_x_variant":[
        "\u4e8c\u9053\u6e7e\u9547"
    ],
    "wof:name":"Erdaowan",
    "wof:placetype":"locality"
},
  "geometry": {"coordinates":[124.53252999999999,47.95882],"type":"Point"}
}