{
  "type": "Feature",
  "properties": {
    "gn:admin1_code":"16.0",
    "gn:asciiname":"Shangpinglong",
    "gn:country_code":"CN",
    "gn:dem":91,
    "gn:feature_class":"P",
    "gn:feature_code":"PPL",
    "gn:name":"Shangpinglong",
    "gn:population":0,
    "gn:timezone":"Asia/Shanghai",
    "iso:country":"CN",
    "name:zho_x_preferred":[
        "\u4e0a\u5e73\u9f99"
    ],
    "wof:name":"Shangpinglong",
    "wof:placetype":"locality"
},
  "geometry": {"coordinates":[109.54900000000001,24.3798],"type":"Point"}
}