{
  "type": "Feature",
  "properties": {
    "gn:admin1_code":"26.0",
    "gn:asciiname":"Shaofangbian",
    "gn:country_code":"CN",
    "gn:dem":1404,
    "gn:feature_class":"P",
    "gn:feature_code":"PPL",
    "gn:name":"Shaofangbian",
    "gn:population":0,
    "gn:timezone":"Asia/Shanghai",
    "iso:country":"CN",
    "name:zho_x_preferred":[
        "\u70e7\u623f\u782d"
    ],
    "wof:name":"Shaofangbian",
    "wof:placetype":"locality"
},
  "geometry": {"coordinates":[109.14567,36.54488],"type":"Point"}
}