{
  "type": "Feature",
  "properties": {
    "gn:admin1_code":"19.0",
    "gn:asciiname":"Paifanggou",
    "gn:country_code":"CN",
    "gn:dem":73,
    "gn:feature_class":"P",
    "gn:feature_code":"PPL",
    "gn:name":"Paifanggou",
    "gn:population":0,
    "gn:timezone":"Asia/Shanghai",
    "iso:country":"CN",
    "name:zho_x_preferred":[
        "\u724c\u574a\u6c9f"
    ],
    "wof:name":"Paifanggou",
    "wof:placetype":"locality"
},
  "geometry": {"coordinates":[121.843,39.2985],"type":"Point"}
}