{
  "type": "Feature",
  "properties": {
    "gn:admin1_code":"13",
    "gn:asciiname":"Qiumake",
    "gn:country_code":"CN",
    "gn:dem":1043,
    "gn:feature_class":"P",
    "gn:feature_code":"PPL",
    "gn:name":"Qiumake",
    "gn:population":0,
    "gn:timezone":"Asia/Shanghai",
    "iso:country":"CN",
    "name:und_x_variant":[
        "\u79cb\u739b\u514b"
    ],
    "wof:name":"Qiumake",
    "wof:placetype":"locality"
},
  "geometry": {"coordinates":[80.25709000000001,40.53319000000001],"type":"Point"}
}