{
  "type": "Feature",
  "properties": {
    "gn:admin1_code":"8.0",
    "gn:asciiname":"Nanlidong",
    "gn:country_code":"CN",
    "gn:dem":125,
    "gn:feature_class":"P",
    "gn:feature_code":"PPL",
    "gn:name":"Nanlidong",
    "gn:population":0,
    "gn:timezone":"Asia/Shanghai",
    "iso:country":"CN",
    "name:zho_x_preferred":[
        "\u5357\u5229\u4e1c"
    ],
    "wof:name":"Nanlidong",
    "wof:placetype":"locality"
},
  "geometry": {"coordinates":[127.88035000000001,46.01799000000001],"type":"Point"}
}