{
  "type": "Feature",
  "properties": {
    "gn:admin1_code":"19",
    "gn:asciiname":"Xiayingzi",
    "gn:country_code":"CN",
    "gn:dem":339,
    "gn:feature_class":"P",
    "gn:feature_code":"PPLA4",
    "gn:name":"Xiayingzi",
    "gn:population":0,
    "gn:timezone":"Asia/Shanghai",
    "iso:country":"CN",
    "name:und_x_variant":[
        "\u4e0b\u8425\u5b50",
        "Xiayingzi Jiedao",
        "\u4e0b\u8425\u5b50\u8857\u9053"
    ],
    "wof:name":"Xiayingzi",
    "wof:placetype":"locality"
},
  "geometry": {"coordinates":[124.55213999999999,41.72318],"type":"Point"}
}