{
  "type": "Feature",
  "properties": {
    "gn:admin1_code":"33.0",
    "gn:asciiname":"Gongnong",
    "gn:country_code":"CN",
    "gn:dem":390,
    "gn:feature_class":"P",
    "gn:feature_code":"PPL",
    "gn:name":"Gongnong",
    "gn:population":0,
    "gn:timezone":"Asia/Shanghai",
    "iso:country":"CN",
    "name:ceb_x_preferred":[
        "Gongnong"
    ],
    "name:deu_x_preferred":[
        "Gongnong"
    ],
    "name:zho_x_preferred":[
        "\u5de5\u519c"
    ],
    "wof:name":"Gongnong",
    "wof:placetype":"locality"
},
  "geometry": {"coordinates":[107.11951000000001,29.55303],"type":"Point"}
}