{
  "type": "Feature",
  "properties": {
    "gn:admin1_code":"20",
    "gn:asciiname":"Tailiang",
    "gn:cc2":"CN",
    "gn:country_code":"CN",
    "gn:dem":1238,
    "gn:feature_class":"P",
    "gn:feature_code":"PPL",
    "gn:name":"Tailiang",
    "gn:population":0,
    "gn:timezone":"Asia/Shanghai",
    "iso:country":"CN",
    "name:und_x_variant":[
        "T\u2019ai-ling",
        "Tailiang"
    ],
    "wof:name":"Tailiang",
    "wof:placetype":"locality"
},
  "geometry": {"coordinates":[109.40361,40.88222],"type":"Point"}
}