{
  "type": "Feature",
  "properties": {
    "gn:admin1_code":"29.0",
    "gn:asciiname":"Yuanjiazhai",
    "gn:country_code":"CN",
    "gn:dem":1016,
    "gn:feature_class":"P",
    "gn:feature_code":"PPL",
    "gn:name":"Yuanjiazhai",
    "gn:population":0,
    "gn:timezone":"Asia/Shanghai",
    "iso:country":"CN",
    "name:zho_x_preferred":[
        "\u8881\u5bb6\u5be8"
    ],
    "wof:name":"Yuanjiazhai",
    "wof:placetype":"locality"
},
  "geometry": {"coordinates":[99.3802,24.7885],"type":"Point"}
}