{
  "type": "Feature",
  "properties": {
    "gn:admin1_code":"25",
    "gn:asciiname":"Shimencun",
    "gn:country_code":"CN",
    "gn:dem":121,
    "gn:feature_class":"P",
    "gn:feature_code":"PPL",
    "gn:name":"Shimencun",
    "gn:population":0,
    "gn:timezone":"Asia/Shanghai",
    "iso:country":"CN",
    "name:und_x_variant":[
        "Shih-men",
        "Shimen",
        "Shimencun"
    ],
    "name:zho_x_preferred":[
        "\u77f3\u95e8"
    ],
    "name:zho_x_variant":[
        "\u77f3\u95e8\u6751"
    ],
    "wof:name":"Shimencun",
    "wof:placetype":"locality"
},
  "geometry": {"coordinates":[119.57209,35.89135],"type":"Point"}
}