{
  "type": "Feature",
  "properties": {
    "gn:admin1_code":"9",
    "gn:asciiname":"Yanghutou",
    "gn:country_code":"CN",
    "gn:dem":50,
    "gn:feature_class":"P",
    "gn:feature_code":"PPL",
    "gn:name":"Yanghutou",
    "gn:population":0,
    "gn:timezone":"Asia/Shanghai",
    "iso:country":"CN",
    "name:zho_x_preferred":[
        "\u6768\u864e\u5934"
    ],
    "wof:name":"Yanghutou",
    "wof:placetype":"locality"
},
  "geometry": {"coordinates":[115.34699999999999,34.0092],"type":"Point"}
}