{
  "type": "Feature",
  "properties": {
    "gn:admin1_code":"8.0",
    "gn:asciiname":"Anshantun",
    "gn:country_code":"CN",
    "gn:dem":233,
    "gn:feature_class":"P",
    "gn:feature_code":"PPL",
    "gn:name":"Anshantun",
    "gn:population":0,
    "gn:timezone":"Asia/Shanghai",
    "iso:country":"CN",
    "name:zho_x_preferred":[
        "\u5b89\u5c71\u5c6f"
    ],
    "wof:name":"Anshantun",
    "wof:placetype":"locality"
},
  "geometry": {"coordinates":[127.83835999999999,45.25662],"type":"Point"}
}