{
  "type": "Feature",
  "properties": {
    "gn:admin1_code":"20",
    "gn:asciiname":"Hsin-wo-p'u",
    "gn:country_code":"CN",
    "gn:dem":491,
    "gn:feature_class":"P",
    "gn:feature_code":"PPL",
    "gn:name":"Hsin-wo-p\u2019u",
    "gn:population":0,
    "gn:timezone":"Asia/Shanghai",
    "iso:country":"CN",
    "wof:name":"Hsin-wo-p'u",
    "wof:placetype":"locality"
},
  "geometry": {"coordinates":[119.99917000000001,42.77778],"type":"Point"}
}