{
  "type": "Feature",
  "properties": {
    "gn:admin1_code":"8.0",
    "gn:asciiname":"Qinghuacun",
    "gn:country_code":"CN",
    "gn:dem":232,
    "gn:feature_class":"P",
    "gn:feature_code":"PPL",
    "gn:name":"Qinghuacun",
    "gn:population":0,
    "gn:timezone":"Asia/Shanghai",
    "iso:country":"CN",
    "name:zho_x_preferred":[
        "\u5e86\u534e\u6751"
    ],
    "wof:name":"Qinghuacun",
    "wof:placetype":"locality"
},
  "geometry": {"coordinates":[124.86274,49.09464000000001],"type":"Point"}
}