{
  "type": "Feature",
  "properties": {
    "gn:admin1_code":"29.0",
    "gn:asciiname":"Liangjiadi",
    "gn:country_code":"CN",
    "gn:dem":1806,
    "gn:feature_class":"P",
    "gn:feature_code":"PPL",
    "gn:name":"Liangjiadi",
    "gn:population":0,
    "gn:timezone":"Asia/Shanghai",
    "iso:country":"CN",
    "name:zho_x_preferred":[
        "\u6881\u5bb6\u5730"
    ],
    "wof:name":"Liangjiadi",
    "wof:placetype":"locality"
},
  "geometry": {"coordinates":[100.721,24.2681],"type":"Point"}
}