{
  "type": "Feature",
  "properties": {
    "gn:admin1_code":"29.0",
    "gn:asciiname":"Yongqing",
    "gn:country_code":"CN",
    "gn:dem":2362,
    "gn:feature_class":"P",
    "gn:feature_code":"PPL",
    "gn:name":"Yongqing",
    "gn:population":0,
    "gn:timezone":"Asia/Shanghai",
    "iso:country":"CN",
    "name:und_x_variant":[
        "\u62e5\u7b90"
    ],
    "wof:name":"Yongqing",
    "wof:placetype":"locality"
},
  "geometry": {"coordinates":[102.36827,25.92966],"type":"Point"}
}