{
  "type": "Feature",
  "properties": {
    "gn:admin1_code":"19.0",
    "gn:asciiname":"Jinjiatai",
    "gn:country_code":"CN",
    "gn:dem":29,
    "gn:feature_class":"P",
    "gn:feature_code":"PPL",
    "gn:name":"Jinjiatai",
    "gn:population":0,
    "gn:timezone":"Asia/Shanghai",
    "iso:country":"CN",
    "name:zho_x_preferred":[
        "\u91d1\u7532\u53f0"
    ],
    "wof:name":"Jinjiatai",
    "wof:placetype":"locality"
},
  "geometry": {"coordinates":[122.8267,41.02292],"type":"Point"}
}