{
  "type": "Feature",
  "properties": {
    "gn:admin1_code":"4.0",
    "gn:asciiname":"Dongbancun",
    "gn:country_code":"CN",
    "gn:dem":1,
    "gn:feature_class":"P",
    "gn:feature_code":"PPL",
    "gn:name":"Dongbancun",
    "gn:population":0,
    "gn:timezone":"Asia/Shanghai",
    "iso:country":"CN",
    "name:zho_x_preferred":[
        "\u4e1c\u962a\u6751"
    ],
    "wof:name":"Dongbancun",
    "wof:placetype":"locality"
},
  "geometry": {"coordinates":[119.93371999999999,32.68732],"type":"Point"}
}