{
  "type": "Feature",
  "properties": {
    "gn:admin1_code":"04",
    "gn:asciiname":"Beiwangcun",
    "gn:cc2":"CN",
    "gn:country_code":"CN",
    "gn:dem":6,
    "gn:feature_class":"P",
    "gn:feature_code":"PPL",
    "gn:name":"Beiwangcun",
    "gn:population":0,
    "gn:timezone":"Asia/Shanghai",
    "iso:country":"CN",
    "name:und_x_variant":[
        "Pei-hsiang-ts\u2019un",
        "Beiwangcun"
    ],
    "wof:name":"Beiwangcun",
    "wof:placetype":"locality"
},
  "geometry": {"coordinates":[120.745,31.34],"type":"Point"}
}