{
  "type": "Feature",
  "properties": {
    "gn:admin1_code":"13.0",
    "gn:asciiname":"Kostik",
    "gn:country_code":"CN",
    "gn:dem":513,
    "gn:feature_class":"P",
    "gn:feature_code":"PPLA4",
    "gn:name":"Kostik",
    "gn:population":0,
    "gn:timezone":"Asia/Urumqi",
    "iso:country":"CN",
    "name:uig_x_preferred":[
        "K\u0329ostik\u0329"
    ],
    "name:uig_x_variant":[
        "Qostiq",
        "\u0642\u0648\u0633\u062a\u0649\u0642",
        "\u049a\u043e\u0441\u0442\u044b\u049b"
    ],
    "name:und_x_variant":[
        "Kostik Xiang",
        "Kostik",
        "Kuositeke",
        "Kuositeke Xiang"
    ],
    "name:zho_x_preferred":[
        "\u9614\u65af\u7279\u514b"
    ],
    "name:zho_x_variant":[
        "\u9614\u65af\u7279\u514b\u4e61"
    ],
    "wof:name":"Kostik",
    "wof:placetype":"locality"
},
  "geometry": {"coordinates":[87.33078,47.78682],"type":"Point"}
}