{
  "type": "Feature",
  "properties": {
    "gn:admin1_code":"7",
    "gn:asciiname":"Zhuxi",
    "gn:country_code":"CN",
    "gn:dem":1025,
    "gn:feature_class":"P",
    "gn:feature_code":"PPL",
    "gn:name":"Zhuxi",
    "gn:population":0,
    "gn:timezone":"Asia/Shanghai",
    "iso:country":"CN",
    "name:ceb_x_preferred":[
        "Zhuxi"
    ],
    "name:nor_x_preferred":[
        "Zhuxi"
    ],
    "wof:name":"Zhuxi",
    "wof:placetype":"locality"
},
  "geometry": {"coordinates":[118.49889,26.05278],"type":"Point"}
}