{
  "type": "Feature",
  "properties": {
    "gn:admin1_code":"7",
    "gn:asciiname":"Shuangxikou",
    "gn:country_code":"CN",
    "gn:dem":747,
    "gn:feature_class":"P",
    "gn:feature_code":"PPL",
    "gn:name":"Shuangxikou",
    "gn:population":0,
    "gn:timezone":"Asia/Shanghai",
    "iso:country":"CN",
    "name:und_x_variant":[
        "\u53cc\u6eaa\u53e3"
    ],
    "wof:name":"Shuangxikou",
    "wof:placetype":"locality"
},
  "geometry": {"coordinates":[117.7925,27.79639],"type":"Point"}
}