{
  "type": "Feature",
  "properties": {
    "gn:admin1_code":"25",
    "gn:asciiname":"Da'an",
    "gn:country_code":"CN",
    "gn:dem":112,
    "gn:feature_class":"P",
    "gn:feature_code":"PPL",
    "gn:name":"Da\u2019an",
    "gn:population":0,
    "gn:timezone":"Asia/Shanghai",
    "iso:country":"CN",
    "name:und_x_variant":[
        "Da\u2019an"
    ],
    "name:zho_x_preferred":[
        "\u5927\u5b89"
    ],
    "wof:name":"Da'an",
    "wof:placetype":"locality"
},
  "geometry": {"coordinates":[118.544,35.6081],"type":"Point"}
}