{
  "type": "Feature",
  "properties": {
    "gn:admin1_code":"32.0",
    "gn:asciiname":"Shangbisha",
    "gn:country_code":"CN",
    "gn:dem":3486,
    "gn:feature_class":"P",
    "gn:feature_code":"PPL",
    "gn:name":"Shangbisha",
    "gn:population":0,
    "gn:timezone":"Asia/Shanghai",
    "iso:country":"CN",
    "name:zho_x_preferred":[
        "\u4e0a\u6bd4\u6c99"
    ],
    "wof:name":"Shangbisha",
    "wof:placetype":"locality"
},
  "geometry": {"coordinates":[99.3159,31.5064],"type":"Point"}
}