{
  "type": "Feature",
  "properties": {
    "gn:admin1_code":"3.0",
    "gn:asciiname":"Yuanjia",
    "gn:country_code":"CN",
    "gn:dem":69,
    "gn:feature_class":"P",
    "gn:feature_code":"PPL",
    "gn:name":"Yuanjia",
    "gn:population":0,
    "gn:timezone":"Asia/Shanghai",
    "iso:country":"CN",
    "name:und_x_variant":[
        "\u8881\u5bb6"
    ],
    "wof:name":"Yuanjia",
    "wof:placetype":"locality"
},
  "geometry": {"coordinates":[116.45441,29.73824],"type":"Point"}
}