{
  "type": "Feature",
  "properties": {
    "gn:admin1_code":"26",
    "gn:asciiname":"Aihaomao",
    "gn:cc2":"CN",
    "gn:country_code":"CN",
    "gn:dem":1316,
    "gn:feature_class":"P",
    "gn:feature_code":"PPL",
    "gn:name":"Aihaomao",
    "gn:population":0,
    "gn:timezone":"Asia/Shanghai",
    "iso:country":"CN",
    "name:und_x_variant":[
        "Ai-p\u2019in-mao",
        "Aihaomao"
    ],
    "wof:name":"Aihaomao",
    "wof:placetype":"locality"
},
  "geometry": {"coordinates":[109.34999999999999,37.68333],"type":"Point"}
}