{
  "type": "Feature",
  "properties": {
    "gn:admin1_code":"25",
    "gn:asciiname":"Huanjiayu",
    "gn:country_code":"CN",
    "gn:dem":161,
    "gn:feature_class":"P",
    "gn:feature_code":"PPL",
    "gn:name":"Huanjiayu",
    "gn:population":0,
    "gn:timezone":"Asia/Shanghai",
    "iso:country":"CN",
    "name:zho_x_preferred":[
        "\u5ba6\u5bb6\u5cea"
    ],
    "wof:name":"Huanjiayu",
    "wof:placetype":"locality"
},
  "geometry": {"coordinates":[117.217,36.2248],"type":"Point"}
}