{
  "type": "Feature",
  "properties": {
    "gn:admin1_code":"7",
    "gn:asciiname":"Changmen",
    "gn:country_code":"CN",
    "gn:dem":927,
    "gn:feature_class":"P",
    "gn:feature_code":"PPL",
    "gn:name":"Changmen",
    "gn:population":0,
    "gn:timezone":"Asia/Shanghai",
    "iso:country":"CN",
    "name:und_x_variant":[
        "\u957f\u95e8"
    ],
    "wof:name":"Changmen",
    "wof:placetype":"locality"
},
  "geometry": {"coordinates":[118.39369000000001,26.04809],"type":"Point"}
}