{
  "type": "Feature",
  "properties": {
    "gn:admin1_code":"30",
    "gn:asciiname":"Baifenpo",
    "gn:country_code":"CN",
    "gn:dem":42,
    "gn:feature_class":"P",
    "gn:feature_code":"PPL",
    "gn:name":"Baifenpo",
    "gn:population":0,
    "gn:timezone":"Asia/Shanghai",
    "iso:country":"CN",
    "name:zho_x_preferred":[
        "\u767d\u575f\u5761"
    ],
    "wof:name":"Baifenpo",
    "wof:placetype":"locality"
},
  "geometry": {"coordinates":[111.8981,22.30794],"type":"Point"}
}