{
  "type": "Feature",
  "properties": {
    "gn:admin1_code":"3.0",
    "gn:asciiname":"Yalu",
    "gn:country_code":"CN",
    "gn:dem":156,
    "gn:feature_class":"P",
    "gn:feature_code":"PPL",
    "gn:name":"Yalu",
    "gn:population":0,
    "gn:timezone":"Asia/Shanghai",
    "iso:country":"CN",
    "name:zho_x_preferred":[
        "\u9e2d\u8def"
    ],
    "wof:name":"Yalu",
    "wof:placetype":"locality"
},
  "geometry": {"coordinates":[113.68600000000001,27.4551],"type":"Point"}
}