{
  "type": "Feature",
  "properties": {
    "gn:admin1_code":"05",
    "gn:asciiname":"Baomacheng",
    "gn:country_code":"CN",
    "gn:dem":689,
    "gn:feature_class":"P",
    "gn:feature_code":"PPL",
    "gn:name":"Baomacheng",
    "gn:population":0,
    "gn:timezone":"Asia/Shanghai",
    "iso:country":"CN",
    "wof:name":"Baomacheng",
    "wof:placetype":"locality"
},
  "geometry": {"coordinates":[128.07832999999999,42.47611],"type":"Point"}
}