{
  "type": "Feature",
  "properties": {
    "gn:admin1_code":"4.0",
    "gn:asciiname":"Jiangjiaxia",
    "gn:country_code":"CN",
    "gn:dem":5,
    "gn:feature_class":"P",
    "gn:feature_code":"PPL",
    "gn:name":"Jiangjiaxia",
    "gn:population":0,
    "gn:timezone":"Asia/Shanghai",
    "iso:country":"CN",
    "name:zho_x_preferred":[
        "\u848b\u5bb6\u53a6"
    ],
    "wof:name":"Jiangjiaxia",
    "wof:placetype":"locality"
},
  "geometry": {"coordinates":[119.58857999999999,32.67073],"type":"Point"}
}