{
  "type": "Feature",
  "properties": {
    "gn:admin1_code":"10.0",
    "gn:asciiname":"Huaizhuang",
    "gn:country_code":"CN",
    "gn:dem":13,
    "gn:feature_class":"P",
    "gn:feature_code":"PPL",
    "gn:name":"Huaizhuang",
    "gn:population":0,
    "gn:timezone":"Asia/Shanghai",
    "iso:country":"CN",
    "name:zho_x_preferred":[
        "\u69d0\u5e84"
    ],
    "wof:name":"Huaizhuang",
    "wof:placetype":"locality"
},
  "geometry": {"coordinates":[116.22499999999999,38.4736],"type":"Point"}
}