{
  "type": "Feature",
  "properties": {
    "gn:admin1_code":"29.0",
    "gn:asciiname":"Languangzhai",
    "gn:country_code":"CN",
    "gn:dem":1543,
    "gn:feature_class":"P",
    "gn:feature_code":"PPL",
    "gn:name":"Languangzhai",
    "gn:population":0,
    "gn:timezone":"Asia/Shanghai",
    "iso:country":"CN",
    "name:zho_x_preferred":[
        "\u70c2\u5e7f\u5be8"
    ],
    "wof:name":"Languangzhai",
    "wof:placetype":"locality"
},
  "geometry": {"coordinates":[104.35599999999999,24.3381],"type":"Point"}
}