{
  "type": "Feature",
  "properties": {
    "gn:admin1_code":"14.0",
    "gn:asciiname":"Chima",
    "gn:country_code":"CN",
    "gn:dem":4636,
    "gn:feature_class":"P",
    "gn:feature_code":"PPL",
    "gn:name":"Chima",
    "gn:population":0,
    "gn:timezone":"Asia/Urumqi",
    "iso:country":"CN",
    "name:ceb_x_preferred":[
        "Chima"
    ],
    "name:deu_x_preferred":[
        "Chima"
    ],
    "name:ita_x_preferred":[
        "Chima"
    ],
    "name:nld_x_preferred":[
        "Chima"
    ],
    "name:swe_x_preferred":[
        "Chima"
    ],
    "name:zho_x_preferred":[
        "\u5c3a\u9ebb"
    ],
    "wof:name":"Chima",
    "wof:placetype":"locality"
},
  "geometry": {"coordinates":[97.18016,30.54008],"type":"Point"}
}