{
  "type": "Feature",
  "properties": {
    "gn:admin1_code":"8.0",
    "gn:asciiname":"Qinjiantun",
    "gn:country_code":"CN",
    "gn:dem":182,
    "gn:feature_class":"P",
    "gn:feature_code":"PPL",
    "gn:name":"Qinjiantun",
    "gn:population":0,
    "gn:timezone":"Asia/Shanghai",
    "iso:country":"CN",
    "name:zho_x_preferred":[
        "\u52e4\u4fed\u5c6f"
    ],
    "wof:name":"Qinjiantun",
    "wof:placetype":"locality"
},
  "geometry": {"coordinates":[127.03861000000001,45.37155],"type":"Point"}
}