{
  "type": "Feature",
  "properties": {
    "gn:admin1_code":"26.0",
    "gn:asciiname":"Liujiazhuangcun",
    "gn:country_code":"CN",
    "gn:dem":1029,
    "gn:feature_class":"P",
    "gn:feature_code":"PPL",
    "gn:name":"Liujiazhuangcun",
    "gn:population":0,
    "gn:timezone":"Asia/Shanghai",
    "iso:country":"CN",
    "name:zho_x_preferred":[
        "\u67f3\u5bb6\u5e84\u6751"
    ],
    "wof:name":"Liujiazhuangcun",
    "wof:placetype":"locality"
},
  "geometry": {"coordinates":[109.53438,35.54768],"type":"Point"}
}