{
  "type": "Feature",
  "properties": {
    "gn:admin1_code":"26.0",
    "gn:asciiname":"Sujiapocun",
    "gn:country_code":"CN",
    "gn:dem":433,
    "gn:feature_class":"P",
    "gn:feature_code":"PPL",
    "gn:name":"Sujiapocun",
    "gn:population":0,
    "gn:timezone":"Asia/Shanghai",
    "iso:country":"CN",
    "name:zho_x_preferred":[
        "\u82cf\u5bb6\u5761\u6751"
    ],
    "wof:name":"Sujiapocun",
    "wof:placetype":"locality"
},
  "geometry": {"coordinates":[109.01781,34.68821],"type":"Point"}
}