{
  "type": "Feature",
  "properties": {
    "gn:admin1_code":"9.0",
    "gn:asciiname":"Gangkou'an",
    "gn:country_code":"CN",
    "gn:dem":87,
    "gn:feature_class":"P",
    "gn:feature_code":"PPL",
    "gn:name":"Gangkou\u2019an",
    "gn:population":0,
    "gn:timezone":"Asia/Shanghai",
    "iso:country":"CN",
    "name:und_x_variant":[
        "Gangkou\u2019an"
    ],
    "name:zho_x_preferred":[
        "\u5c97\u53e3\u5cb8"
    ],
    "wof:name":"Gangkou'an",
    "wof:placetype":"locality"
},
  "geometry": {"coordinates":[112.58669999999999,32.54996],"type":"Point"}
}