{
  "type": "Feature",
  "properties": {
    "gn:admin1_code":"10",
    "gn:asciiname":"Liugangxi",
    "gn:country_code":"CN",
    "gn:dem":335,
    "gn:feature_class":"P",
    "gn:feature_code":"PPL",
    "gn:name":"Liugangxi",
    "gn:population":0,
    "gn:timezone":"Asia/Shanghai",
    "iso:country":"CN",
    "name:zho_x_preferred":[
        "\u5218\u5c97\u897f"
    ],
    "wof:name":"Liugangxi",
    "wof:placetype":"locality"
},
  "geometry": {"coordinates":[114.07599999999999,36.5175],"type":"Point"}
}