{
  "type": "Feature",
  "properties": {
    "gn:admin1_code":"14.0",
    "gn:asciiname":"Muchangangcun",
    "gn:country_code":"CN",
    "gn:dem":3984,
    "gn:feature_class":"P",
    "gn:feature_code":"PPL",
    "gn:name":"Muchangangcun",
    "gn:population":0,
    "gn:timezone":"Asia/Urumqi",
    "iso:country":"CN",
    "name:zho_x_preferred":[
        "\u7136\u660c\u6751"
    ],
    "wof:name":"Muchangangcun",
    "wof:placetype":"locality"
},
  "geometry": {"coordinates":[95.79470999999999,30.67922],"type":"Point"}
}