{
  "type": "Feature",
  "properties": {
    "gn:admin1_code":"24.0",
    "gn:asciiname":"Wangliaocun",
    "gn:country_code":"CN",
    "gn:dem":674,
    "gn:feature_class":"P",
    "gn:feature_code":"PPL",
    "gn:name":"Wangliaocun",
    "gn:population":0,
    "gn:timezone":"Asia/Shanghai",
    "iso:country":"CN",
    "name:zho_x_preferred":[
        "\u738b\u8fbd\u6751"
    ],
    "wof:name":"Wangliaocun",
    "wof:placetype":"locality"
},
  "geometry": {"coordinates":[110.31433,34.71988],"type":"Point"}
}