{
  "type": "Feature",
  "properties": {
    "gn:admin1_code":"7.0",
    "gn:asciiname":"Licuoyang",
    "gn:country_code":"CN",
    "gn:dem":938,
    "gn:feature_class":"P",
    "gn:feature_code":"PPL",
    "gn:name":"Licuoyang",
    "gn:population":0,
    "gn:timezone":"Asia/Shanghai",
    "iso:country":"CN",
    "name:zho_x_preferred":[
        "Licuoyang"
    ],
    "name:zho_x_variant":[
        "\u91cc\u539d\u6d0b"
    ],
    "wof:name":"Licuoyang",
    "wof:placetype":"locality"
},
  "geometry": {"coordinates":[118.89306000000001,26.54472],"type":"Point"}
}