{
  "type": "Feature",
  "properties": {
    "gn:admin1_code":"18.0",
    "gn:asciiname":"Laowangping",
    "gn:country_code":"CN",
    "gn:dem":438,
    "gn:feature_class":"P",
    "gn:feature_code":"PPL",
    "gn:name":"Laowangping",
    "gn:population":0,
    "gn:timezone":"Asia/Shanghai",
    "iso:country":"CN",
    "name:zho_x_preferred":[
        "\u8001\u738b\u576a"
    ],
    "wof:name":"Laowangping",
    "wof:placetype":"locality"
},
  "geometry": {"coordinates":[108.932,27.8559],"type":"Point"}
}