{
  "type": "Feature",
  "properties": {
    "gn:admin1_code":"15.0",
    "gn:asciiname":"Bajiacha",
    "gn:country_code":"CN",
    "gn:dem":2199,
    "gn:feature_class":"P",
    "gn:feature_code":"PPL",
    "gn:name":"Bajiacha",
    "gn:population":0,
    "gn:timezone":"Asia/Shanghai",
    "iso:country":"CN",
    "name:zho_x_preferred":[
        "\u516b\u5bb6\u5c94"
    ],
    "wof:name":"Bajiacha",
    "wof:placetype":"locality"
},
  "geometry": {"coordinates":[104.526,36.0285],"type":"Point"}
}