{
  "type": "Feature",
  "properties": {
    "gn:admin1_code":"24.0",
    "gn:asciiname":"Xisongjiachangcun",
    "gn:country_code":"CN",
    "gn:dem":1002,
    "gn:feature_class":"P",
    "gn:feature_code":"PPL",
    "gn:name":"Xisongjiachangcun",
    "gn:population":0,
    "gn:timezone":"Asia/Shanghai",
    "iso:country":"CN",
    "name:zho_x_preferred":[
        "\u897f\u5b8b\u5bb6\u5382\u6751"
    ],
    "wof:name":"Xisongjiachangcun",
    "wof:placetype":"locality"
},
  "geometry": {"coordinates":[114.02115000000001,40.40272],"type":"Point"}
}