{
  "type": "Feature",
  "properties": {
    "gn:admin1_code":"16",
    "gn:asciiname":"Liangjiang",
    "gn:cc2":"CN",
    "gn:country_code":"CN",
    "gn:dem":164,
    "gn:feature_class":"P",
    "gn:feature_code":"PPL",
    "gn:name":"Liangjiang",
    "gn:population":0,
    "gn:timezone":"Asia/Shanghai",
    "iso:country":"CN",
    "name:ceb_x_preferred":[
        "Liangjiang"
    ],
    "name:deu_x_preferred":[
        "Liangjiang"
    ],
    "name:und_x_variant":[
        "Liang-chiang-hs\u00fc",
        "Liang-chiang",
        "Liangkiang",
        "Liang-chiang-t\u2019ang",
        "Liangjiang"
    ],
    "wof:name":"Liangjiang",
    "wof:placetype":"locality"
},
  "geometry": {"coordinates":[110.02222,25.20278],"type":"Point"}
}