{
  "type": "Feature",
  "properties": {
    "gn:admin1_code":"25",
    "gn:asciiname":"Hongshaozi",
    "gn:country_code":"CN",
    "gn:dem":407,
    "gn:feature_class":"P",
    "gn:feature_code":"PPL",
    "gn:name":"Hongshaozi",
    "gn:population":0,
    "gn:timezone":"Asia/Shanghai",
    "iso:country":"CN",
    "name:zho_x_preferred":[
        "\u7ea2\u54e8\u5b50"
    ],
    "wof:name":"Hongshaozi",
    "wof:placetype":"locality"
},
  "geometry": {"coordinates":[117.408,36.4573],"type":"Point"}
}