{
  "type": "Feature",
  "properties": {
    "gn:admin1_code":"5.0",
    "gn:asciiname":"Qingshankoucun",
    "gn:country_code":"CN",
    "gn:dem":166,
    "gn:feature_class":"P",
    "gn:feature_code":"PPL",
    "gn:name":"Qingshankoucun",
    "gn:population":0,
    "gn:timezone":"Asia/Shanghai",
    "iso:country":"CN",
    "name:zho_x_preferred":[
        "\u9752\u5c71\u53e3\u6751"
    ],
    "wof:name":"Qingshankoucun",
    "wof:placetype":"locality"
},
  "geometry": {"coordinates":[125.65754,44.89419],"type":"Point"}
}