{
  "type": "Feature",
  "properties": {
    "gn:admin1_code":"9.0",
    "gn:asciiname":"Yaoqiaohe Nancun",
    "gn:country_code":"CN",
    "gn:dem":60,
    "gn:feature_class":"P",
    "gn:feature_code":"PPL",
    "gn:name":"Yaoqiaohe Nancun",
    "gn:population":0,
    "gn:timezone":"Asia/Shanghai",
    "iso:country":"CN",
    "name:zho_x_preferred":[
        "\u59da\u6865\u6cb3\u5357\u6751"
    ],
    "wof:name":"Yaoqiaohe Nancun",
    "wof:placetype":"locality"
},
  "geometry": {"coordinates":[114.09469,33.72150999999999],"type":"Point"}
}