{
  "type": "Feature",
  "properties": {
    "gn:admin1_code":"16.0",
    "gn:asciiname":"Genglao",
    "gn:country_code":"CN",
    "gn:dem":383,
    "gn:feature_class":"P",
    "gn:feature_code":"PPL",
    "gn:name":"Genglao",
    "gn:population":0,
    "gn:timezone":"Asia/Shanghai",
    "iso:country":"CN",
    "name:zho_x_preferred":[
        "\u66f4\u52b3"
    ],
    "wof:name":"Genglao",
    "wof:placetype":"locality"
},
  "geometry": {"coordinates":[106.709,23.684],"type":"Point"}
}