{
  "type": "Feature",
  "properties": {
    "gn:admin1_code":"7.0",
    "gn:asciiname":"Shenyang",
    "gn:country_code":"CN",
    "gn:dem":253,
    "gn:feature_class":"P",
    "gn:feature_code":"PPL",
    "gn:name":"Shenyang",
    "gn:population":0,
    "gn:timezone":"Asia/Shanghai",
    "iso:country":"CN",
    "name:zho_x_preferred":[
        "\u6df1\u6d0b"
    ],
    "wof:name":"Shenyang",
    "wof:placetype":"locality"
},
  "geometry": {"coordinates":[118.12973999999998,25.26645],"type":"Point"}
}