{
  "type": "Feature",
  "properties": {
    "gn:admin1_code":"9.0",
    "gn:asciiname":"Xiaojie",
    "gn:country_code":"CN",
    "gn:dem":405,
    "gn:feature_class":"P",
    "gn:feature_code":"PPL",
    "gn:name":"Xiaojie",
    "gn:population":0,
    "gn:timezone":"Asia/Shanghai",
    "iso:country":"CN",
    "name:und_x_variant":[
        "\u5c0f\u8857",
        "Xiaojie"
    ],
    "wof:name":"Xiaojie",
    "wof:placetype":"locality"
},
  "geometry": {"coordinates":[112.13951000000002,33.36762],"type":"Point"}
}