{
  "type": "Feature",
  "properties": {
    "gn:admin1_code":"9.0",
    "gn:asciiname":"Yuhuangmiao",
    "gn:country_code":"CN",
    "gn:dem":87,
    "gn:feature_class":"P",
    "gn:feature_code":"PPL",
    "gn:name":"Yuhuangmiao",
    "gn:population":0,
    "gn:timezone":"Asia/Shanghai",
    "iso:country":"CN",
    "name:und_x_variant":[
        "\u7389\u7687\u5e99"
    ],
    "name:zho_x_preferred":[
        "\u7389\u7687\u5e99"
    ],
    "wof:name":"Yuhuangmiao",
    "wof:placetype":"locality"
},
  "geometry": {"coordinates":[113.67541,33.3272],"type":"Point"}
}