{
  "type": "Feature",
  "properties": {
    "gn:admin1_code":"18",
    "gn:asciiname":"Qimashan",
    "gn:country_code":"CN",
    "gn:dem":2086,
    "gn:feature_class":"P",
    "gn:feature_code":"PPL",
    "gn:name":"Qimashan",
    "gn:population":0,
    "gn:timezone":"Asia/Shanghai",
    "iso:country":"CN",
    "name:zho_x_preferred":[
        "\u9a91\u9a6c\u5c71"
    ],
    "wof:name":"Qimashan",
    "wof:placetype":"locality"
},
  "geometry": {"coordinates":[104.657,26.6648],"type":"Point"}
}