{
  "type": "Feature",
  "properties": {
    "gn:admin1_code":"2.0",
    "gn:asciiname":"Xiaoxi",
    "gn:country_code":"CN",
    "gn:dem":40,
    "gn:feature_class":"P",
    "gn:feature_code":"PPL",
    "gn:name":"Xiaoxi",
    "gn:population":0,
    "gn:timezone":"Asia/Shanghai",
    "iso:country":"CN",
    "name:zho_x_preferred":[
        "\u7b71\u6eaa"
    ],
    "wof:name":"Xiaoxi",
    "wof:placetype":"locality"
},
  "geometry": {"coordinates":[119.56990999999999,29.1052],"type":"Point"}
}