{
  "type": "Feature",
  "properties": {
    "gn:admin1_code":"9.0",
    "gn:asciiname":"Zhuyuanbian",
    "gn:country_code":"CN",
    "gn:dem":1158,
    "gn:feature_class":"P",
    "gn:feature_code":"PPL",
    "gn:name":"Zhuyuanbian",
    "gn:population":0,
    "gn:timezone":"Asia/Shanghai",
    "iso:country":"CN",
    "name:und_x_variant":[
        "\u7af9\u56ed\u8fb9",
        "Zhuyuanbian"
    ],
    "wof:name":"Zhuyuanbian",
    "wof:placetype":"locality"
},
  "geometry": {"coordinates":[112.37427,33.83305],"type":"Point"}
}