{
  "type": "Feature",
  "properties": {
    "gn:admin1_code":"18",
    "gn:asciiname":"Huamiaozhai",
    "gn:country_code":"CN",
    "gn:dem":1631,
    "gn:feature_class":"P",
    "gn:feature_code":"PPL",
    "gn:name":"Huamiaozhai",
    "gn:population":0,
    "gn:timezone":"Asia/Shanghai",
    "iso:country":"CN",
    "name:zho_x_preferred":[
        "\u82b1\u82d7\u5be8"
    ],
    "wof:name":"Huamiaozhai",
    "wof:placetype":"locality"
},
  "geometry": {"coordinates":[105.38,27.1117],"type":"Point"}
}