{
  "type": "Feature",
  "properties": {
    "gn:admin1_code":"29",
    "gn:asciiname":"Huangjiazhuang",
    "gn:country_code":"CN",
    "gn:dem":1487,
    "gn:feature_class":"P",
    "gn:feature_code":"PPL",
    "gn:name":"Huangjiazhuang",
    "gn:population":0,
    "gn:timezone":"Asia/Shanghai",
    "iso:country":"CN",
    "name:zho_x_preferred":[
        "\u9ec4\u5bb6\u5e84"
    ],
    "wof:name":"Huangjiazhuang",
    "wof:placetype":"locality"
},
  "geometry": {"coordinates":[103.343,24.1153],"type":"Point"}
}