{
  "type": "Feature",
  "properties": {
    "gn:admin1_code":"19.0",
    "gn:asciiname":"Wangjia Wazi",
    "gn:country_code":"CN",
    "gn:dem":58,
    "gn:feature_class":"P",
    "gn:feature_code":"PPL",
    "gn:name":"Wangjia Wazi",
    "gn:population":0,
    "gn:timezone":"Asia/Shanghai",
    "iso:country":"CN",
    "name:zho_x_preferred":[
        "\u738b\u5bb6\u6d3c\u5b50"
    ],
    "wof:name":"Wangjia Wazi",
    "wof:placetype":"locality"
},
  "geometry": {"coordinates":[122.178,42.0393],"type":"Point"}
}