{
  "type": "Feature",
  "properties": {
    "gn:admin1_code":"26.0",
    "gn:asciiname":"Xiwangjia Maocun",
    "gn:country_code":"CN",
    "gn:dem":1017,
    "gn:feature_class":"P",
    "gn:feature_code":"PPL",
    "gn:name":"Xiwangjia Maocun",
    "gn:population":0,
    "gn:timezone":"Asia/Shanghai",
    "iso:country":"CN",
    "name:zho_x_preferred":[
        "\u897f\u738b\u5bb6\u5cc1\u6751"
    ],
    "wof:name":"Xiwangjia Maocun",
    "wof:placetype":"locality"
},
  "geometry": {"coordinates":[110.657,38.7149],"type":"Point"}
}