{
  "type": "Feature",
  "properties": {
    "gn:admin1_code":"29.0",
    "gn:asciiname":"Dingxiangzhai",
    "gn:country_code":"CN",
    "gn:dem":1987,
    "gn:feature_class":"P",
    "gn:feature_code":"PPL",
    "gn:name":"Dingxiangzhai",
    "gn:population":0,
    "gn:timezone":"Asia/Shanghai",
    "iso:country":"CN",
    "name:zho_x_preferred":[
        "\u4e01\u9999\u5be8"
    ],
    "wof:name":"Dingxiangzhai",
    "wof:placetype":"locality"
},
  "geometry": {"coordinates":[99.4308,25.1331],"type":"Point"}
}