{
  "type": "Feature",
  "properties": {
    "gn:admin1_code":"11",
    "gn:asciiname":"Zhexi Linchang",
    "gn:country_code":"CN",
    "gn:dem":183,
    "gn:feature_class":"P",
    "gn:feature_code":"PPLF",
    "gn:name":"Zhexi Linchang",
    "gn:population":0,
    "gn:timezone":"Asia/Shanghai",
    "iso:country":"CN",
    "wof:name":"Zhexi Linchang",
    "wof:placetype":"locality"
},
  "geometry": {"coordinates":[111.01139000000001,28.12722],"type":"Point"}
}