{
  "type": "Feature",
  "properties": {
    "gn:admin1_code":"1.0",
    "gn:asciiname":"Shenggangcun",
    "gn:country_code":"CN",
    "gn:dem":76,
    "gn:feature_class":"P",
    "gn:feature_code":"PPL",
    "gn:name":"Shenggangcun",
    "gn:population":0,
    "gn:timezone":"Asia/Shanghai",
    "iso:country":"CN",
    "name:zho_x_preferred":[
        "\u76db\u5c97\u6751"
    ],
    "wof:name":"Shenggangcun",
    "wof:placetype":"locality"
},
  "geometry": {"coordinates":[117.51103999999999,32.16107],"type":"Point"}
}