{
  "type": "Feature",
  "properties": {
    "gn:admin1_code":"19.0",
    "gn:asciiname":"Zhaojia Wobu",
    "gn:country_code":"CN",
    "gn:dem":109,
    "gn:feature_class":"P",
    "gn:feature_code":"PPL",
    "gn:name":"Zhaojia Wobu",
    "gn:population":0,
    "gn:timezone":"Asia/Shanghai",
    "iso:country":"CN",
    "name:und_x_variant":[
        "Zhaojiawobao",
        "Zhaojia Wobu"
    ],
    "name:zho_x_preferred":[
        "\u8d75\u5bb6\u7a9d\u5821"
    ],
    "wof:name":"Zhaojia Wobu",
    "wof:placetype":"locality"
},
  "geometry": {"coordinates":[123.73063,42.80283],"type":"Point"}
}