{
  "type": "Feature",
  "properties": {
    "gn:admin1_code":"20.0",
    "gn:asciiname":"Guoxianyao",
    "gn:country_code":"CN",
    "gn:dem":1877,
    "gn:feature_class":"P",
    "gn:feature_code":"PPL",
    "gn:name":"Guoxianyao",
    "gn:population":0,
    "gn:timezone":"Asia/Shanghai",
    "iso:country":"CN",
    "name:und_x_variant":[
        "\u5d1e\u53bf\u7a91"
    ],
    "wof:name":"Guoxianyao",
    "wof:placetype":"locality"
},
  "geometry": {"coordinates":[111.63726,40.95527],"type":"Point"}
}