{
  "type": "Feature",
  "properties": {
    "gn:admin1_code":"14.0",
    "gn:asciiname":"Sangbo",
    "gn:country_code":"CN",
    "gn:dem":4020,
    "gn:feature_class":"P",
    "gn:feature_code":"PPL",
    "gn:name":"Sangbo",
    "gn:population":0,
    "gn:timezone":"Asia/Urumqi",
    "iso:country":"CN",
    "name:zho_x_preferred":[
        "\u6851\u6ce2"
    ],
    "wof:name":"Sangbo",
    "wof:placetype":"locality"
},
  "geometry": {"coordinates":[87.7777,29.0709],"type":"Point"}
}