{
  "type": "Feature",
  "properties": {
    "gn:admin1_code":"13",
    "gn:asciiname":"Kazihu",
    "gn:country_code":"CN",
    "gn:dem":1646,
    "gn:feature_class":"P",
    "gn:feature_code":"PPL",
    "gn:name":"Kazihu",
    "gn:population":0,
    "gn:timezone":"Asia/Urumqi",
    "iso:country":"CN",
    "name:und_x_variant":[
        "\u5361\u5b50\u6e56"
    ],
    "wof:name":"Kazihu",
    "wof:placetype":"locality"
},
  "geometry": {"coordinates":[92.82290999999999,43.57938],"type":"Point"}
}