{
  "type": "Feature",
  "properties": {
    "gn:admin1_code":"15.0",
    "gn:asciiname":"Kangjiazhuang",
    "gn:country_code":"CN",
    "gn:dem":1334,
    "gn:feature_class":"P",
    "gn:feature_code":"PPL",
    "gn:name":"Kangjiazhuang",
    "gn:population":0,
    "gn:timezone":"Asia/Shanghai",
    "iso:country":"CN",
    "name:zho_x_preferred":[
        "\u5eb7\u5bb6\u5e84"
    ],
    "wof:name":"Kangjiazhuang",
    "wof:placetype":"locality"
},
  "geometry": {"coordinates":[107.37,35.4096],"type":"Point"}
}