{
  "type": "Feature",
  "properties": {
    "gn:admin1_code":"30.0",
    "gn:asciiname":"Chushuiguo",
    "gn:country_code":"CN",
    "gn:dem":660,
    "gn:feature_class":"P",
    "gn:feature_code":"PPL",
    "gn:name":"Chushuiguo",
    "gn:population":0,
    "gn:timezone":"Asia/Urumqi",
    "iso:country":"CN",
    "name:zho_x_preferred":[
        "\u51fa\u6c34\u57da"
    ],
    "wof:name":"Chushuiguo",
    "wof:placetype":"locality"
},
  "geometry": {"coordinates":[111.13120000000001,22.2757],"type":"Point"}
}