{
  "type": "Feature",
  "properties": {
    "gn:admin1_code":"24.0",
    "gn:asciiname":"Gubeiling",
    "gn:country_code":"CN",
    "gn:dem":1882,
    "gn:feature_class":"P",
    "gn:feature_code":"PPL",
    "gn:name":"Gubeiling",
    "gn:population":0,
    "gn:timezone":"Asia/Shanghai",
    "iso:country":"CN",
    "name:und_x_variant":[
        "\u987e\u5317\u5cad"
    ],
    "name:zho_x_preferred":[
        "\u987e\u5317\u5cad"
    ],
    "wof:name":"Gubeiling",
    "wof:placetype":"locality"
},
  "geometry": {"coordinates":[112.20399999999999,39.46938],"type":"Point"}
}