{
  "type": "Feature",
  "properties": {
    "gn:admin1_code":"4.0",
    "gn:asciiname":"Rongmeima",
    "gn:country_code":"CN",
    "gn:dem":13,
    "gn:feature_class":"P",
    "gn:feature_code":"PPL",
    "gn:name":"Rongmeima",
    "gn:population":0,
    "gn:timezone":"Asia/Shanghai",
    "iso:country":"CN",
    "name:zho_x_preferred":[
        "\u620e\u6885\u9a6c"
    ],
    "wof:name":"Rongmeima",
    "wof:placetype":"locality"
},
  "geometry": {"coordinates":[119.73491,32.03763],"type":"Point"}
}