{
  "type": "Feature",
  "properties": {
    "gn:admin1_code":"4.0",
    "gn:asciiname":"Zhangjing",
    "gn:cc2":"CN",
    "gn:country_code":"CN",
    "gn:dem":6,
    "gn:feature_class":"P",
    "gn:feature_code":"PPL",
    "gn:name":"Zhangjing",
    "gn:population":0,
    "gn:timezone":"Asia/Shanghai",
    "iso:country":"CN",
    "name:und_x_variant":[
        "Chang-ching-ch\u2019iao",
        "Zhangjing Zhen",
        "Zhangjingqiao",
        "Zhangjing"
    ],
    "wof:name":"Zhangjing",
    "wof:placetype":"locality"
},
  "geometry": {"coordinates":[120.435,31.65667],"type":"Point"}
}