{
  "type": "Feature",
  "properties": {
    "gn:admin1_code":"20.0",
    "gn:asciiname":"Bagongli",
    "gn:country_code":"CN",
    "gn:dem":890,
    "gn:feature_class":"P",
    "gn:feature_code":"PPL",
    "gn:name":"Bagongli",
    "gn:population":0,
    "gn:timezone":"Asia/Shanghai",
    "iso:country":"CN",
    "name:zho_x_preferred":[
        "\u516b\u516c\u91cc"
    ],
    "wof:name":"Bagongli",
    "wof:placetype":"locality"
},
  "geometry": {"coordinates":[121.00697,48.66067],"type":"Point"}
}