{
  "type": "Feature",
  "properties": {
    "gn:admin1_code":"33.0",
    "gn:asciiname":"Tanzhong",
    "gn:country_code":"CN",
    "gn:dem":559,
    "gn:feature_class":"P",
    "gn:feature_code":"PPL",
    "gn:name":"Tanzhong",
    "gn:population":0,
    "gn:timezone":"Asia/Shanghai",
    "iso:country":"CN",
    "name:zho_x_preferred":[
        "\u8c2d\u4e2d"
    ],
    "wof:name":"Tanzhong",
    "wof:placetype":"locality"
},
  "geometry": {"coordinates":[107.57317999999999,29.6694],"type":"Point"}
}