{
  "type": "Feature",
  "properties": {
    "gn:admin1_code":"29.0",
    "gn:asciiname":"Guangbie Laozhai",
    "gn:country_code":"CN",
    "gn:dem":1430,
    "gn:feature_class":"P",
    "gn:feature_code":"PPL",
    "gn:name":"Guangbie Laozhai",
    "gn:population":0,
    "gn:timezone":"Asia/Shanghai",
    "iso:country":"CN",
    "name:zho_x_preferred":[
        "\u5e7f\u522b\u8001\u5be8"
    ],
    "wof:name":"Guangbie Laozhai",
    "wof:placetype":"locality"
},
  "geometry": {"coordinates":[99.54940000000001,22.2891],"type":"Point"}
}