{
  "type": "Feature",
  "properties": {
    "gn:admin1_code":"25",
    "gn:asciiname":"Shangnali",
    "gn:country_code":"CN",
    "gn:dem":48,
    "gn:feature_class":"P",
    "gn:feature_code":"PPL",
    "gn:name":"Shangnali",
    "gn:population":0,
    "gn:timezone":"Asia/Shanghai",
    "iso:country":"CN",
    "name:zho_x_preferred":[
        "\u5c1a\u90a3\u91cc"
    ],
    "wof:name":"Shangnali",
    "wof:placetype":"locality"
},
  "geometry": {"coordinates":[115.88,35.8282],"type":"Point"}
}