{
  "type": "Feature",
  "properties": {
    "gn:admin1_code":"12.0",
    "gn:asciiname":"Xinhe",
    "gn:country_code":"CN",
    "gn:dem":27,
    "gn:feature_class":"P",
    "gn:feature_code":"PPLA4",
    "gn:name":"Xinhe",
    "gn:population":0,
    "gn:timezone":"Asia/Shanghai",
    "iso:country":"CN",
    "name:ceb_x_preferred":[
        "Xinhe"
    ],
    "name:deu_x_preferred":[
        "Xinhe"
    ],
    "name:fra_x_preferred":[
        "Xinhe"
    ],
    "name:kor_x_preferred":[
        "\uc2e0\ud5c8\ud604"
    ],
    "name:und_x_variant":[
        "Xinhe Zhen"
    ],
    "name:zho_x_preferred":[
        "\u65b0\u6cb3"
    ],
    "name:zho_x_variant":[
        "\u65b0\u6cb3\u9547"
    ],
    "wof:name":"Xinhe",
    "wof:placetype":"locality"
},
  "geometry": {"coordinates":[113.93326,30.68919],"type":"Point"}
}