{
  "type": "Feature",
  "properties": {
    "gn:admin1_code":"8.0",
    "gn:asciiname":"Jiangjunlingtun",
    "gn:country_code":"CN",
    "gn:dem":135,
    "gn:feature_class":"P",
    "gn:feature_code":"PPL",
    "gn:name":"Jiangjunlingtun",
    "gn:population":0,
    "gn:timezone":"Asia/Shanghai",
    "iso:country":"CN",
    "name:zho_x_preferred":[
        "\u5c06\u519b\u5cad\u5c6f"
    ],
    "wof:name":"Jiangjunlingtun",
    "wof:placetype":"locality"
},
  "geometry": {"coordinates":[132.87062,46.12438],"type":"Point"}
}