{
  "type": "Feature",
  "properties": {
    "gn:admin1_code":"25",
    "gn:asciiname":"Heishibu",
    "gn:country_code":"CN",
    "gn:dem":130,
    "gn:feature_class":"P",
    "gn:feature_code":"PPL",
    "gn:name":"Heishibu",
    "gn:population":0,
    "gn:timezone":"Asia/Shanghai",
    "iso:country":"CN",
    "name:zho_x_preferred":[
        "\u9ed1\u77f3\u57e0"
    ],
    "wof:name":"Heishibu",
    "wof:placetype":"locality"
},
  "geometry": {"coordinates":[117.217,36.0277],"type":"Point"}
}