{
  "type": "Feature",
  "properties": {
    "gn:admin1_code":"19.0",
    "gn:asciiname":"Wangjia Buzi",
    "gn:country_code":"CN",
    "gn:dem":3,
    "gn:feature_class":"P",
    "gn:feature_code":"PPL",
    "gn:name":"Wangjia Buzi",
    "gn:population":0,
    "gn:timezone":"Asia/Shanghai",
    "iso:country":"CN",
    "name:und_x_variant":[
        "Wangjia Puzi",
        "\u738b\u5bb6\u5821\u5b50",
        "Wangjia Buzi"
    ],
    "wof:name":"Wangjia Buzi",
    "wof:placetype":"locality"
},
  "geometry": {"coordinates":[122.22403,40.64817],"type":"Point"}
}