{
  "type": "Feature",
  "properties": {
    "gn:admin1_code":"25",
    "gn:asciiname":"Xigaojiagou",
    "gn:country_code":"CN",
    "gn:dem":106,
    "gn:feature_class":"P",
    "gn:feature_code":"PPL",
    "gn:name":"Xigaojiagou",
    "gn:population":0,
    "gn:timezone":"Asia/Shanghai",
    "iso:country":"CN",
    "name:zho_x_preferred":[
        "\u897f\u9ad8\u5bb6\u6c9f"
    ],
    "wof:name":"Xigaojiagou",
    "wof:placetype":"locality"
},
  "geometry": {"coordinates":[119.11,35.4742],"type":"Point"}
}