{
  "type": "Feature",
  "properties": {
    "gn:admin1_code":"12.0",
    "gn:asciiname":"Houziguai",
    "gn:country_code":"CN",
    "gn:dem":37,
    "gn:feature_class":"P",
    "gn:feature_code":"PPL",
    "gn:name":"Houziguai",
    "gn:population":0,
    "gn:timezone":"Asia/Shanghai",
    "iso:country":"CN",
    "name:zho_x_preferred":[
        "Houziguai"
    ],
    "name:zho_x_variant":[
        "\u7334\u5b50\u62d0"
    ],
    "wof:name":"Houziguai",
    "wof:placetype":"locality"
},
  "geometry": {"coordinates":[111.99048000000001,30.17399],"type":"Point"}
}