{
  "type": "Feature",
  "properties": {
    "gn:admin1_code":"4.0",
    "gn:asciiname":"Gechengcun",
    "gn:country_code":"CN",
    "gn:dem":26,
    "gn:feature_class":"P",
    "gn:feature_code":"PPL",
    "gn:name":"Gechengcun",
    "gn:population":0,
    "gn:timezone":"Asia/Shanghai",
    "iso:country":"CN",
    "name:und_x_variant":[
        "Gechang"
    ],
    "name:zho_x_preferred":[
        "\u845b\u7a0b\u6751"
    ],
    "wof:name":"Gechengcun",
    "wof:placetype":"locality"
},
  "geometry": {"coordinates":[118.00708,34.29352],"type":"Point"}
}