{
  "type": "Feature",
  "properties": {
    "gn:admin1_code":"32.0",
    "gn:asciiname":"Jin'anhuizhu",
    "gn:country_code":"CN",
    "gn:dem":2858,
    "gn:feature_class":"P",
    "gn:feature_code":"PPL",
    "gn:name":"Jin\u2019anhuizhu",
    "gn:population":0,
    "gn:timezone":"Asia/Shanghai",
    "iso:country":"CN",
    "name:zho_x_preferred":[
        "\u8fdb\u5b89\u56de\u65cf"
    ],
    "wof:name":"Jin'anhuizhu",
    "wof:placetype":"locality"
},
  "geometry": {"coordinates":[103.59898,32.64813],"type":"Point"}
}