{
  "type": "Feature",
  "properties": {
    "gn:admin1_code":"18",
    "gn:asciiname":"Lugoutang",
    "gn:country_code":"CN",
    "gn:dem":1230,
    "gn:feature_class":"P",
    "gn:feature_code":"PPL",
    "gn:name":"Lugoutang",
    "gn:population":0,
    "gn:timezone":"Asia/Shanghai",
    "iso:country":"CN",
    "name:zho_x_preferred":[
        "\u9c81\u6c9f\u5858"
    ],
    "wof:name":"Lugoutang",
    "wof:placetype":"locality"
},
  "geometry": {"coordinates":[105.371,25.2824],"type":"Point"}
}