{
  "type": "Feature",
  "properties": {
    "gn:admin1_code":"11",
    "gn:asciiname":"Zhatian",
    "gn:country_code":"CN",
    "gn:dem":319,
    "gn:feature_class":"P",
    "gn:feature_code":"PPL",
    "gn:name":"Zhatian",
    "gn:population":0,
    "gn:timezone":"Asia/Shanghai",
    "iso:country":"CN",
    "wof:name":"Zhatian",
    "wof:placetype":"locality"
},
  "geometry": {"coordinates":[111.19110999999999,26.67806],"type":"Point"}
}