{
  "type": "Feature",
  "properties": {
    "gn:admin1_code":"19.0",
    "gn:asciiname":"Zhazigou",
    "gn:country_code":"CN",
    "gn:dem":227,
    "gn:feature_class":"P",
    "gn:feature_code":"PPL",
    "gn:name":"Zhazigou",
    "gn:population":0,
    "gn:timezone":"Asia/Shanghai",
    "iso:country":"CN",
    "name:zho_x_preferred":[
        "\u781f\u5b50\u6c9f"
    ],
    "wof:name":"Zhazigou",
    "wof:placetype":"locality"
},
  "geometry": {"coordinates":[123.45999999999999,41.0727],"type":"Point"}
}