{
  "type": "Feature",
  "properties": {
    "gn:admin1_code":"29.0",
    "gn:asciiname":"Xiaoganhe",
    "gn:country_code":"CN",
    "gn:dem":1999,
    "gn:feature_class":"P",
    "gn:feature_code":"PPL",
    "gn:name":"Xiaoganhe",
    "gn:population":0,
    "gn:timezone":"Asia/Shanghai",
    "iso:country":"CN",
    "name:zho_x_preferred":[
        "\u5c0f\u5e72\u6cb3"
    ],
    "wof:name":"Xiaoganhe",
    "wof:placetype":"locality"
},
  "geometry": {"coordinates":[102.011,25.2807],"type":"Point"}
}