{
  "type": "Feature",
  "properties": {
    "gn:admin1_code":"24.0",
    "gn:asciiname":"Xiamizhuang",
    "gn:country_code":"CN",
    "gn:dem":1004,
    "gn:feature_class":"P",
    "gn:feature_code":"PPL",
    "gn:name":"Xiamizhuang",
    "gn:population":0,
    "gn:timezone":"Asia/Shanghai",
    "iso:country":"CN",
    "name:zho_x_preferred":[
        "\u4e0b\u7c73\u5e84"
    ],
    "wof:name":"Xiamizhuang",
    "wof:placetype":"locality"
},
  "geometry": {"coordinates":[113.23357,39.86603],"type":"Point"}
}