{
  "type": "Feature",
  "properties": {
    "gn:admin1_code":"26.0",
    "gn:asciiname":"Duanjia",
    "gn:country_code":"CN",
    "gn:dem":562,
    "gn:feature_class":"P",
    "gn:feature_code":"PPLA4",
    "gn:name":"Duanjia",
    "gn:population":0,
    "gn:timezone":"Asia/Shanghai",
    "iso:country":"CN",
    "name:und_x_variant":[
        "\u6bb5\u5bb6",
        "Duanjia Zhen",
        "\u6bb5\u5bb6\u9547"
    ],
    "wof:name":"Duanjia",
    "wof:placetype":"locality"
},
  "geometry": {"coordinates":[107.90621000000002,34.30994],"type":"Point"}
}