{
  "type": "Feature",
  "properties": {
    "gn:admin1_code":"11.0",
    "gn:asciiname":"Jiulongchong",
    "gn:country_code":"CN",
    "gn:dem":85,
    "gn:feature_class":"P",
    "gn:feature_code":"PPL",
    "gn:name":"Jiulongchong",
    "gn:population":0,
    "gn:timezone":"Asia/Shanghai",
    "iso:country":"CN",
    "name:zho_x_preferred":[
        "\u4e5d\u9f99\u51b2"
    ],
    "wof:name":"Jiulongchong",
    "wof:placetype":"locality"
},
  "geometry": {"coordinates":[112.18068999999998,28.73833],"type":"Point"}
}