{
  "type": "Feature",
  "properties": {
    "gn:admin1_code":"26",
    "gn:asciiname":"Caotang",
    "gn:country_code":"CN",
    "gn:dem":429,
    "gn:feature_class":"P",
    "gn:feature_code":"PPLA4",
    "gn:name":"Caotang",
    "gn:population":0,
    "gn:timezone":"Asia/Shanghai",
    "iso:country":"CN",
    "name:und_x_variant":[
        "Caotang Zhen",
        "Caotang"
    ],
    "name:zho_x_preferred":[
        "\u8349\u5802"
    ],
    "name:zho_x_variant":[
        "\u8349\u5802\u9547"
    ],
    "wof:name":"Caotang",
    "wof:placetype":"locality"
},
  "geometry": {"coordinates":[108.71083,34.04389],"type":"Point"}
}