{
  "type": "Feature",
  "properties": {
    "gn:admin1_code":"16.0",
    "gn:asciiname":"Waichaohuai",
    "gn:country_code":"CN",
    "gn:dem":270,
    "gn:feature_class":"P",
    "gn:feature_code":"PPL",
    "gn:name":"Waichaohuai",
    "gn:population":0,
    "gn:timezone":"Asia/Shanghai",
    "iso:country":"CN",
    "name:zho_x_preferred":[
        "\u5916\u671d\u6000"
    ],
    "wof:name":"Waichaohuai",
    "wof:placetype":"locality"
},
  "geometry": {"coordinates":[108.751,23.9109],"type":"Point"}
}