{
  "type": "Feature",
  "properties": {
    "gn:admin1_code":"3.0",
    "gn:asciiname":"Luojie",
    "gn:country_code":"CN",
    "gn:dem":43,
    "gn:feature_class":"P",
    "gn:feature_code":"PPL",
    "gn:name":"Luojie",
    "gn:population":0,
    "gn:timezone":"Asia/Shanghai",
    "iso:country":"CN",
    "name:und_x_variant":[
        "\u7f57\u7ed3"
    ],
    "wof:name":"Luojie",
    "wof:placetype":"locality"
},
  "geometry": {"coordinates":[117.26036999999999,29.38717],"type":"Point"}
}