{
  "type": "Feature",
  "properties": {
    "gn:admin1_code":"1.0",
    "gn:asciiname":"Zhuxicun",
    "gn:country_code":"CN",
    "gn:dem":245,
    "gn:feature_class":"P",
    "gn:feature_code":"PPL",
    "gn:name":"Zhuxicun",
    "gn:population":0,
    "gn:timezone":"Asia/Shanghai",
    "iso:country":"CN",
    "name:und_x_variant":[
        "Zhuxi"
    ],
    "name:zho_x_preferred":[
        "\u7af9\u6eaa\u6751"
    ],
    "wof:name":"Zhuxicun",
    "wof:placetype":"locality"
},
  "geometry": {"coordinates":[117.89935,30.09906],"type":"Point"}
}