{
  "type": "Feature",
  "properties": {
    "gn:admin1_code":"11.0",
    "gn:asciiname":"Guyoukou",
    "gn:country_code":"CN",
    "gn:dem":427,
    "gn:feature_class":"P",
    "gn:feature_code":"PPL",
    "gn:name":"Guyoukou",
    "gn:population":0,
    "gn:timezone":"Asia/Shanghai",
    "iso:country":"CN",
    "name:zho_x_preferred":[
        "\u53e4\u53cb\u53e3"
    ],
    "wof:name":"Guyoukou",
    "wof:placetype":"locality"
},
  "geometry": {"coordinates":[109.81077999999999,26.35162],"type":"Point"}
}