{
  "type": "Feature",
  "properties": {
    "gn:admin1_code":"19.0",
    "gn:asciiname":"Tongxing",
    "gn:country_code":"CN",
    "gn:dem":15,
    "gn:feature_class":"P",
    "gn:feature_code":"PPL",
    "gn:name":"Tongxing",
    "gn:population":0,
    "gn:timezone":"Asia/Shanghai",
    "iso:country":"CN",
    "name:und_x_variant":[
        "\u540c\u5174"
    ],
    "name:zho_x_preferred":[
        "\u540c\u5174"
    ],
    "wof:name":"Tongxing",
    "wof:placetype":"locality"
},
  "geometry": {"coordinates":[124.00232,39.90116],"type":"Point"}
}