{
  "type": "Feature",
  "properties": {
    "gn:admin1_code":"14.0",
    "gn:asciiname":"Jinai",
    "gn:country_code":"CN",
    "gn:dem":3170,
    "gn:feature_class":"P",
    "gn:feature_code":"PPL",
    "gn:name":"Jinai",
    "gn:population":0,
    "gn:timezone":"Asia/Urumqi",
    "iso:country":"CN",
    "name:zho_x_preferred":[
        "\u53ca\u4e43"
    ],
    "wof:name":"Jinai",
    "wof:placetype":"locality"
},
  "geometry": {"coordinates":[96.74630000000001,30.25053],"type":"Point"}
}