{
  "type": "Feature",
  "properties": {
    "gn:admin1_code":"15.0",
    "gn:asciiname":"Gakou Gongma",
    "gn:country_code":"CN",
    "gn:dem":3175,
    "gn:feature_class":"P",
    "gn:feature_code":"PPL",
    "gn:name":"Gakou Gongma",
    "gn:population":0,
    "gn:timezone":"Asia/Shanghai",
    "iso:country":"CN",
    "name:zho_x_preferred":[
        "\u5c15\u53e3\u8d21\u739b"
    ],
    "wof:name":"Gakou Gongma",
    "wof:placetype":"locality"
},
  "geometry": {"coordinates":[102.827,34.9778],"type":"Point"}
}