{
  "type": "Feature",
  "properties": {
    "gn:admin1_code":"26",
    "gn:asciiname":"Wanliucun",
    "gn:country_code":"CN",
    "gn:dem":359,
    "gn:feature_class":"P",
    "gn:feature_code":"PPL",
    "gn:name":"Wanliucun",
    "gn:population":0,
    "gn:timezone":"Asia/Shanghai",
    "iso:country":"CN",
    "name:zho_x_preferred":[
        "\u6e7e\u5218\u6751"
    ],
    "wof:name":"Wanliucun",
    "wof:placetype":"locality"
},
  "geometry": {"coordinates":[109.41958,34.60327],"type":"Point"}
}