{
  "type": "Feature",
  "properties": {
    "gn:admin1_code":"4.0",
    "gn:asciiname":"Dajinxu",
    "gn:country_code":"CN",
    "gn:dem":5,
    "gn:feature_class":"P",
    "gn:feature_code":"PPL",
    "gn:name":"Dajinxu",
    "gn:population":0,
    "gn:timezone":"Asia/Shanghai",
    "iso:country":"CN",
    "name:zho_x_preferred":[
        "Dajinxu"
    ],
    "name:zho_x_variant":[
        "\u5927\u91d1\u5729"
    ],
    "wof:name":"Dajinxu",
    "wof:placetype":"locality"
},
  "geometry": {"coordinates":[119.29805,33.95776],"type":"Point"}
}