{
  "type": "Feature",
  "properties": {
    "gn:admin1_code":"5.0",
    "gn:asciiname":"Lazi Menli",
    "gn:country_code":"CN",
    "gn:dem":572,
    "gn:feature_class":"P",
    "gn:feature_code":"PPL",
    "gn:name":"Lazi Menli",
    "gn:population":0,
    "gn:timezone":"Asia/Shanghai",
    "iso:country":"CN",
    "name:zho_x_preferred":[
        "\u782c\u5b50\u95e8\u91cc"
    ],
    "wof:name":"Lazi Menli",
    "wof:placetype":"locality"
},
  "geometry": {"coordinates":[126.05323,41.84182],"type":"Point"}
}