{
  "type": "Feature",
  "properties": {
    "gn:admin1_code":"25.0",
    "gn:asciiname":"Yujiahe",
    "gn:country_code":"CN",
    "gn:dem":175,
    "gn:feature_class":"P",
    "gn:feature_code":"PPL",
    "gn:name":"Yujiahe",
    "gn:population":0,
    "gn:timezone":"Asia/Shanghai",
    "iso:country":"CN",
    "name:zho_x_preferred":[
        "\u4e8e\u5bb6\u6cb3"
    ],
    "wof:name":"Yujiahe",
    "wof:placetype":"locality"
},
  "geometry": {"coordinates":[120.13623,37.13829000000001],"type":"Point"}
}