{
  "type": "Feature",
  "properties": {
    "gn:admin1_code":"24.0",
    "gn:asciiname":"Heishiling",
    "gn:country_code":"CN",
    "gn:dem":927,
    "gn:feature_class":"P",
    "gn:feature_code":"PPL",
    "gn:name":"Heishiling",
    "gn:population":0,
    "gn:timezone":"Asia/Shanghai",
    "iso:country":"CN",
    "name:zho_x_preferred":[
        "\u9ed1\u77f3\u5cad"
    ],
    "wof:name":"Heishiling",
    "wof:placetype":"locality"
},
  "geometry": {"coordinates":[112.85634,35.29104],"type":"Point"}
}