{
  "type": "Feature",
  "properties": {
    "gn:admin1_code":"28",
    "gn:asciiname":"Xinkou",
    "gn:country_code":"CN",
    "gn:dem":7,
    "gn:feature_class":"P",
    "gn:feature_code":"PPLA4",
    "gn:name":"Xinkou",
    "gn:population":0,
    "gn:timezone":"Asia/Shanghai",
    "iso:country":"CN",
    "name:und_x_variant":[
        "Shangxinkou"
    ],
    "name:zho_x_preferred":[
        "\u8f9b\u53e3"
    ],
    "wof:name":"Xinkou",
    "wof:placetype":"locality"
},
  "geometry": {"coordinates":[116.98005999999999,39.10304],"type":"Point"}
}