{
  "type": "Feature",
  "properties": {
    "gn:admin1_code":"30.0",
    "gn:asciiname":"Guantianxin",
    "gn:country_code":"CN",
    "gn:dem":4,
    "gn:feature_class":"P",
    "gn:feature_code":"PPL",
    "gn:name":"Guantianxin",
    "gn:population":0,
    "gn:timezone":"Asia/Shanghai",
    "iso:country":"CN",
    "name:zho_x_preferred":[
        "\u704c\u7530\u65b0"
    ],
    "wof:name":"Guantianxin",
    "wof:placetype":"locality"
},
  "geometry": {"coordinates":[112.76335,22.33788],"type":"Point"}
}