{
  "type": "Feature",
  "properties": {
    "gn:admin1_code":"9",
    "gn:asciiname":"Xizhaozi",
    "gn:country_code":"CN",
    "gn:dem":895,
    "gn:feature_class":"P",
    "gn:feature_code":"PPL",
    "gn:name":"Xizhaozi",
    "gn:population":0,
    "gn:timezone":"Asia/Shanghai",
    "iso:country":"CN",
    "wof:name":"Xizhaozi",
    "wof:placetype":"locality"
},
  "geometry": {"coordinates":[111.26528,34.15861],"type":"Point"}
}