{
  "type": "Feature",
  "properties": {
    "gn:admin1_code":"19.0",
    "gn:asciiname":"Jianchanggou",
    "gn:country_code":"CN",
    "gn:dem":390,
    "gn:feature_class":"P",
    "gn:feature_code":"PPL",
    "gn:name":"Jianchanggou",
    "gn:population":0,
    "gn:timezone":"Asia/Shanghai",
    "iso:country":"CN",
    "name:zho_x_preferred":[
        "\u78b1\u5382\u6c9f"
    ],
    "wof:name":"Jianchanggou",
    "wof:placetype":"locality"
},
  "geometry": {"coordinates":[124.99007,41.40713],"type":"Point"}
}