{
  "type": "Feature",
  "properties": {
    "gn:admin1_code":"26.0",
    "gn:asciiname":"Dajinggou",
    "gn:country_code":"CN",
    "gn:dem":539,
    "gn:feature_class":"P",
    "gn:feature_code":"PPL",
    "gn:name":"Dajinggou",
    "gn:population":0,
    "gn:timezone":"Asia/Shanghai",
    "iso:country":"CN",
    "name:und_x_variant":[
        "\u5927\u4e95\u6c9f"
    ],
    "wof:name":"Dajinggou",
    "wof:placetype":"locality"
},
  "geometry": {"coordinates":[107.55507,33.14781],"type":"Point"}
}