{
  "type": "Feature",
  "properties": {
    "gn:admin1_code":"24.0",
    "gn:asciiname":"Dongnanyu",
    "gn:country_code":"CN",
    "gn:dem":945,
    "gn:feature_class":"P",
    "gn:feature_code":"PPL",
    "gn:name":"Dongnanyu",
    "gn:population":0,
    "gn:timezone":"Asia/Shanghai",
    "iso:country":"CN",
    "name:zho_x_preferred":[
        "\u4e1c\u5357\u8201"
    ],
    "wof:name":"Dongnanyu",
    "wof:placetype":"locality"
},
  "geometry": {"coordinates":[113.64073999999999,38.02078],"type":"Point"}
}