{
  "type": "Feature",
  "properties": {
    "gn:admin1_code":"5.0",
    "gn:asciiname":"Liujiayuan",
    "gn:country_code":"CN",
    "gn:dem":703,
    "gn:feature_class":"P",
    "gn:feature_code":"PPL",
    "gn:name":"Liujiayuan",
    "gn:population":0,
    "gn:timezone":"Asia/Shanghai",
    "iso:country":"CN",
    "name:und_x_variant":[
        "\u5218\u5bb6\u9662"
    ],
    "wof:name":"Liujiayuan",
    "wof:placetype":"locality"
},
  "geometry": {"coordinates":[126.11563999999998,41.34057],"type":"Point"}
}