{
  "type": "Feature",
  "properties": {
    "gn:admin1_code":"3.0",
    "gn:asciiname":"Yunting",
    "gn:country_code":"CN",
    "gn:dem":109,
    "gn:feature_class":"P",
    "gn:feature_code":"PPL",
    "gn:name":"Yunting",
    "gn:population":0,
    "gn:timezone":"Asia/Shanghai",
    "iso:country":"CN",
    "name:und_x_variant":[
        "\u4e91\u4ead"
    ],
    "wof:name":"Yunting",
    "wof:placetype":"locality"
},
  "geometry": {"coordinates":[115.96510000000001,27.85897000000001],"type":"Point"}
}