{
  "type": "Feature",
  "properties": {
    "gn:admin1_code":"29.0",
    "gn:asciiname":"Jiupanpo",
    "gn:country_code":"CN",
    "gn:dem":804,
    "gn:feature_class":"P",
    "gn:feature_code":"PPL",
    "gn:name":"Jiupanpo",
    "gn:population":0,
    "gn:timezone":"Asia/Shanghai",
    "iso:country":"CN",
    "name:zho_x_preferred":[
        "\u4e5d\u76d8\u5761"
    ],
    "wof:name":"Jiupanpo",
    "wof:placetype":"locality"
},
  "geometry": {"coordinates":[104.357,28.312],"type":"Point"}
}