{
  "type": "Feature",
  "properties": {
    "gn:admin1_code":"29",
    "gn:asciiname":"Longhudian",
    "gn:country_code":"CN",
    "gn:dem":1627,
    "gn:feature_class":"P",
    "gn:feature_code":"PPL",
    "gn:name":"Longhudian",
    "gn:population":0,
    "gn:timezone":"Asia/Shanghai",
    "iso:country":"CN",
    "name:zho_x_preferred":[
        "\u9f99\u547c\u7538"
    ],
    "wof:name":"Longhudian",
    "wof:placetype":"locality"
},
  "geometry": {"coordinates":[101.898,24.4614],"type":"Point"}
}