{
  "type": "Feature",
  "properties": {
    "gn:admin1_code":"15.0",
    "gn:asciiname":"Shagouquan",
    "gn:country_code":"CN",
    "gn:dem":2240,
    "gn:feature_class":"P",
    "gn:feature_code":"PPL",
    "gn:name":"Shagouquan",
    "gn:population":0,
    "gn:timezone":"Asia/Shanghai",
    "iso:country":"CN",
    "name:zho_x_preferred":[
        "\u6c99\u6c9f\u5708"
    ],
    "wof:name":"Shagouquan",
    "wof:placetype":"locality"
},
  "geometry": {"coordinates":[101.536,38.5293],"type":"Point"}
}