{
  "type": "Feature",
  "properties": {
    "gn:admin1_code":"14.0",
    "gn:asciiname":"Gyungcang",
    "gn:country_code":"CN",
    "gn:dem":4413,
    "gn:feature_class":"P",
    "gn:feature_code":"PPL",
    "gn:name":"Gyungcang",
    "gn:population":0,
    "gn:timezone":"Asia/Shanghai",
    "iso:country":"CN",
    "name:bod_x_preferred":[
        "Gyungcang"
    ],
    "name:msa_x_preferred":[
        "Gyungcang"
    ],
    "name:und_x_variant":[
        "Zhongcang",
        "Gyungcang"
    ],
    "name:zho_x_preferred":[
        "\u4ef2\u4ed3"
    ],
    "name:zho_x_variant":[
        "Juncang",
        "\u5747\u4ed3",
        "Qieqin",
        "\u4e14\u94a6"
    ],
    "wof:name":"Gyungcang",
    "wof:placetype":"locality"
},
  "geometry": {"coordinates":[79.58794,32.86962],"type":"Point"}
}