{
  "type": "Feature",
  "properties": {
    "gn:admin1_code":"11.0",
    "gn:asciiname":"Dayuanzhuang",
    "gn:country_code":"CN",
    "gn:dem":219,
    "gn:feature_class":"P",
    "gn:feature_code":"PPL",
    "gn:name":"Dayuanzhuang",
    "gn:population":0,
    "gn:timezone":"Asia/Shanghai",
    "iso:country":"CN",
    "name:zho_x_preferred":[
        "\u5927\u6c85\u5e84"
    ],
    "wof:name":"Dayuanzhuang",
    "wof:placetype":"locality"
},
  "geometry": {"coordinates":[113.73475999999999,28.10424],"type":"Point"}
}