{
  "type": "Feature",
  "properties": {
    "gn:admin1_code":"24.0",
    "gn:asciiname":"Zaoling",
    "gn:cc2":"CN",
    "gn:country_code":"CN",
    "gn:dem":771,
    "gn:feature_class":"P",
    "gn:feature_code":"PPL",
    "gn:name":"Zaoling",
    "gn:population":0,
    "gn:timezone":"Asia/Shanghai",
    "iso:country":"CN",
    "name:und_x_variant":[
        "Tsao-ling",
        "Zaoling"
    ],
    "wof:name":"Zaoling",
    "wof:placetype":"locality"
},
  "geometry": {"coordinates":[110.64917,35.80167],"type":"Point"}
}