{
  "type": "Feature",
  "properties": {
    "gn:admin1_code":"30.0",
    "gn:asciiname":"Chelongcun",
    "gn:country_code":"CN",
    "gn:dem":75,
    "gn:feature_class":"P",
    "gn:feature_code":"PPL",
    "gn:name":"Chelongcun",
    "gn:population":0,
    "gn:timezone":"Asia/Shanghai",
    "iso:country":"CN",
    "name:zho_x_preferred":[
        "\u8f66\u9f99\u6751"
    ],
    "wof:name":"Chelongcun",
    "wof:placetype":"locality"
},
  "geometry": {"coordinates":[116.72811000000002,24.4652],"type":"Point"}
}