{
  "type": "Feature",
  "properties": {
    "gn:admin1_code":"8.0",
    "gn:asciiname":"Xiangbaicun",
    "gn:country_code":"CN",
    "gn:dem":197,
    "gn:feature_class":"P",
    "gn:feature_code":"PPL",
    "gn:name":"Xiangbaicun",
    "gn:population":0,
    "gn:timezone":"Asia/Shanghai",
    "iso:country":"CN",
    "name:zho_x_preferred":[
        "\u53a2\u767d\u6751"
    ],
    "wof:name":"Xiangbaicun",
    "wof:placetype":"locality"
},
  "geometry": {"coordinates":[126.54031999999999,46.98748],"type":"Point"}
}