{
  "type": "Feature",
  "properties": {
    "gn:admin1_code":"8.0",
    "gn:asciiname":"Donghuicun",
    "gn:country_code":"CN",
    "gn:dem":143,
    "gn:feature_class":"P",
    "gn:feature_code":"PPL",
    "gn:name":"Donghuicun",
    "gn:population":0,
    "gn:timezone":"Asia/Shanghai",
    "iso:country":"CN",
    "name:zho_x_preferred":[
        "\u4e1c\u8f89\u6751"
    ],
    "wof:name":"Donghuicun",
    "wof:placetype":"locality"
},
  "geometry": {"coordinates":[129.95116000000002,46.18985],"type":"Point"}
}