{
  "type": "Feature",
  "properties": {
    "gn:admin1_code":"30",
    "gn:asciiname":"Datang",
    "gn:country_code":"CN",
    "gn:dem":187,
    "gn:feature_class":"P",
    "gn:feature_code":"PPLA4",
    "gn:name":"Datang",
    "gn:population":0,
    "gn:timezone":"Asia/Shanghai",
    "iso:country":"CN",
    "name:und_x_variant":[
        "Datang Zhen"
    ],
    "name:zho_x_preferred":[
        "\u5927\u5858"
    ],
    "name:zho_x_variant":[
        "\u5927\u5858\u9547"
    ],
    "wof:name":"Datang",
    "wof:placetype":"locality"
},
  "geometry": {"coordinates":[114.52473999999999,25.28102],"type":"Point"}
}