{
  "type": "Feature",
  "properties": {
    "gn:admin1_code":"19.0",
    "gn:asciiname":"Beicha",
    "gn:country_code":"CN",
    "gn:dem":306,
    "gn:feature_class":"P",
    "gn:feature_code":"PPL",
    "gn:name":"Beicha",
    "gn:population":0,
    "gn:timezone":"Asia/Shanghai",
    "iso:country":"CN",
    "name:und_x_variant":[
        "\u5317\u5c94"
    ],
    "wof:name":"Beicha",
    "wof:placetype":"locality"
},
  "geometry": {"coordinates":[123.5699,40.75068],"type":"Point"}
}