{
  "type": "Feature",
  "properties": {
    "gn:admin1_code":"22.0",
    "gn:asciiname":"Wofosicun",
    "gn:country_code":"CN",
    "gn:dem":119,
    "gn:feature_class":"P",
    "gn:feature_code":"PPL",
    "gn:name":"Wofosicun",
    "gn:population":0,
    "gn:timezone":"Asia/Shanghai",
    "iso:country":"CN",
    "name:zho_x_preferred":[
        "\u5367\u4f5b\u5bfa\u6751"
    ],
    "wof:name":"Wofosicun",
    "wof:placetype":"locality"
},
  "geometry": {"coordinates":[116.1974,40.0076],"type":"Point"}
}