{
  "type": "Feature",
  "properties": {
    "gn:admin1_code":"18",
    "gn:asciiname":"Dousun",
    "gn:country_code":"CN",
    "gn:dem":1101,
    "gn:feature_class":"P",
    "gn:feature_code":"PPL",
    "gn:name":"Dousun",
    "gn:population":0,
    "gn:timezone":"Asia/Shanghai",
    "iso:country":"CN",
    "name:zho_x_preferred":[
        "\u6597\u7b0b"
    ],
    "wof:name":"Dousun",
    "wof:placetype":"locality"
},
  "geometry": {"coordinates":[106.35599999999999,25.6954],"type":"Point"}
}