{
  "type": "Feature",
  "properties": {
    "gn:admin1_code":"7",
    "gn:asciiname":"Xiamei",
    "gn:country_code":"CN",
    "gn:dem":22,
    "gn:feature_class":"P",
    "gn:feature_code":"PPL",
    "gn:name":"Xiamei",
    "gn:population":0,
    "gn:timezone":"Asia/Shanghai",
    "iso:country":"CN",
    "name:zho_x_preferred":[
        "\u971e\u7f8e"
    ],
    "wof:name":"Xiamei",
    "wof:placetype":"locality"
},
  "geometry": {"coordinates":[118.55916999999999,24.9672],"type":"Point"}
}