{
  "type": "Feature",
  "properties": {
    "gn:admin1_code":"1.0",
    "gn:asciiname":"Taojicun",
    "gn:country_code":"CN",
    "gn:dem":30,
    "gn:feature_class":"P",
    "gn:feature_code":"PPL",
    "gn:name":"Taojicun",
    "gn:population":0,
    "gn:timezone":"Asia/Shanghai",
    "iso:country":"CN",
    "name:zho_x_preferred":[
        "\u9676\u96c6\u6751"
    ],
    "wof:name":"Taojicun",
    "wof:placetype":"locality"
},
  "geometry": {"coordinates":[116.26288,32.92262],"type":"Point"}
}