{
  "type": "Feature",
  "properties": {
    "gn:admin1_code":"26.0",
    "gn:asciiname":"Mengyayao",
    "gn:country_code":"CN",
    "gn:dem":1074,
    "gn:feature_class":"P",
    "gn:feature_code":"PPL",
    "gn:name":"Mengyayao",
    "gn:population":0,
    "gn:timezone":"Asia/Shanghai",
    "iso:country":"CN",
    "name:zho_x_preferred":[
        "\u5b5f\u5d16\u7a91"
    ],
    "wof:name":"Mengyayao",
    "wof:placetype":"locality"
},
  "geometry": {"coordinates":[110.46595000000001,38.69794],"type":"Point"}
}