{
  "type": "Feature",
  "properties": {
    "gn:admin1_code":"3.0",
    "gn:asciiname":"Tangyuan",
    "gn:country_code":"CN",
    "gn:dem":92,
    "gn:feature_class":"P",
    "gn:feature_code":"PPL",
    "gn:name":"Tangyuan",
    "gn:population":0,
    "gn:timezone":"Asia/Shanghai",
    "iso:country":"CN",
    "name:ceb_x_preferred":[
        "Tangyuan"
    ],
    "name:deu_x_preferred":[
        "Tangyuan"
    ],
    "name:fra_x_preferred":[
        "Tangyuan"
    ],
    "name:rus_x_preferred":[
        "\u0422\u0430\u043d\u044a\u044e\u0430\u043d\u044c"
    ],
    "name:und_x_variant":[
        "\u5858\u6e90"
    ],
    "wof:name":"Tangyuan",
    "wof:placetype":"locality"
},
  "geometry": {"coordinates":[114.97753,27.28039],"type":"Point"}
}