{
  "type": "Feature",
  "properties": {
    "gn:admin1_code":"07",
    "gn:asciiname":"Laiwu",
    "gn:country_code":"CN",
    "gn:dem":476,
    "gn:feature_class":"P",
    "gn:feature_code":"PPL",
    "gn:name":"Laiwu",
    "gn:population":0,
    "gn:timezone":"Asia/Shanghai",
    "iso:country":"CN",
    "name:zho_x_preferred":[
        "\u8d56\u5c4b"
    ],
    "wof:name":"Laiwu",
    "wof:placetype":"locality"
},
  "geometry": {"coordinates":[116.33879,24.89821],"type":"Point"}
}