{
  "type": "Feature",
  "properties": {
    "gn:admin1_code":"07",
    "gn:asciiname":"Laiwu",
    "gn:country_code":"CN",
    "gn:dem":476,
    "gn:feature_class":"P",
    "gn:feature_code":"PPL",
    "gn:name":"Laiwu",
    "gn:population":0,
    "gn:timezone":"Asia/Shanghai",
    "iso:country":"CN",
    "name:afr_x_preferred":[
        "Laiwu"
    ],
    "name:ara_x_preferred":[
        "\u0644\u0627\u064a\u0648\u0648"
    ],
    "name:cdo_x_preferred":[
        "L\u00e0i-\u00f9"
    ],
    "name:ceb_x_preferred":[
        "Laiwu"
    ],
    "name:ces_x_preferred":[
        "Laj-wu"
    ],
    "name:dan_x_preferred":[
        "Laiwu"
    ],
    "name:deu_x_preferred":[
        "Laiwu"
    ],
    "name:eus_x_preferred":[
        "Laiwu"
    ],
    "name:fas_x_preferred":[
        "\u0644\u0627\u06cc\u0648\u0648"
    ],
    "name:fin_x_preferred":[
        "Laiwu"
    ],
    "name:fra_x_preferred":[
        "Laiwu"
    ],
    "name:ita_x_preferred":[
        "Laiwu"
    ],
    "name:jpn_x_preferred":[
        "\u83b1\u856a\u5e02"
    ],
    "name:kik_x_preferred":[
        "Laiwu"
    ],
    "name:kor_x_preferred":[
        "\ub77c\uc774\uc6b0\uc2dc"
    ],
    "name:mlg_x_preferred":[
        "Laiwu"
    ],
    "name:nld_x_preferred":[
        "Laiwu"
    ],
    "name:nno_x_preferred":[
        "Laiwu"
    ],
    "name:nor_x_preferred":[
        "Laiwu"
    ],
    "name:pol_x_preferred":[
        "Laiwu"
    ],
    "name:rus_x_preferred":[
        "\u041b\u0430\u0439\u0443"
    ],
    "name:spa_x_preferred":[
        "Laiwu"
    ],
    "name:swe_x_preferred":[
        "Laiwu"
    ],
    "name:tgl_x_preferred":[
        "Laiwu"
    ],
    "name:tha_x_preferred":[
        "\u0e44\u0e2b\u0e25\u0e2d\u0e39\u0e4b"
    ],
    "name:tur_x_preferred":[
        "Laiwu"
    ],
    "name:urd_x_preferred":[
        "\u0644\u0627\u0626\u0648\u0648"
    ],
    "name:vie_x_preferred":[
        "Lai Vu"
    ],
    "name:war_x_preferred":[
        "Laiwu"
    ],
    "name:wuu_x_preferred":[
        "\u83b1\u829c\u5e02"
    ],
    "name:zho_x_preferred":[
        "\u8d56\u5c4b"
    ],
    "name:zho_x_variant":[
        "\u83b1\u829c\u5e02"
    ],
    "wof:name":"Laiwu",
    "wof:placetype":"locality"
},
  "geometry": {"coordinates":[116.33879,24.89821],"type":"Point"}
}