{
  "type": "Feature",
  "properties": {
    "gn:admin1_code":"9.0",
    "gn:asciiname":"Lilouying",
    "gn:country_code":"CN",
    "gn:dem":41,
    "gn:feature_class":"P",
    "gn:feature_code":"PPL",
    "gn:name":"Lilouying",
    "gn:population":0,
    "gn:timezone":"Asia/Shanghai",
    "iso:country":"CN",
    "name:zho_x_preferred":[
        "\u674e\u697c\u8425"
    ],
    "wof:name":"Lilouying",
    "wof:placetype":"locality"
},
  "geometry": {"coordinates":[115.20075,33.29512],"type":"Point"}
}