{
  "type": "Feature",
  "properties": {
    "gn:admin1_code":"3.0",
    "gn:asciiname":"Shanxia",
    "gn:country_code":"CN",
    "gn:dem":70,
    "gn:feature_class":"P",
    "gn:feature_code":"PPL",
    "gn:name":"Shanxia",
    "gn:population":0,
    "gn:timezone":"Asia/Shanghai",
    "iso:country":"CN",
    "name:und_x_variant":[
        "\u5c71\u4e0b"
    ],
    "wof:name":"Shanxia",
    "wof:placetype":"locality"
},
  "geometry": {"coordinates":[114.95368999999999,29.22449000000001],"type":"Point"}
}