{
  "type": "Feature",
  "properties": {
    "gn:admin1_code":"15.0",
    "gn:asciiname":"Shibao",
    "gn:country_code":"CN",
    "gn:dem":1621,
    "gn:feature_class":"P",
    "gn:feature_code":"PPLA4",
    "gn:name":"Shibao",
    "gn:population":0,
    "gn:timezone":"Asia/Shanghai",
    "iso:country":"CN",
    "name:und_x_variant":[
        "\u77f3\u5821"
    ],
    "wof:name":"Shibao",
    "wof:placetype":"locality"
},
  "geometry": {"coordinates":[105.29771,34.09167],"type":"Point"}
}