{
  "type": "Feature",
  "properties": {
    "gn:admin1_code":"2",
    "gn:asciiname":"Shuangjiangxi",
    "gn:country_code":"CN",
    "gn:dem":38,
    "gn:feature_class":"P",
    "gn:feature_code":"PPL",
    "gn:name":"Shuangjiangxi",
    "gn:population":0,
    "gn:timezone":"Asia/Shanghai",
    "iso:country":"CN",
    "wof:name":"Shuangjiangxi",
    "wof:placetype":"locality"
},
  "geometry": {"coordinates":[120.69972,29.79083],"type":"Point"}
}