{
  "type": "Feature",
  "properties": {
    "gn:admin1_code":"29.0",
    "gn:asciiname":"Zhehong",
    "gn:country_code":"CN",
    "gn:dem":1956,
    "gn:feature_class":"P",
    "gn:feature_code":"PPL",
    "gn:name":"Zhehong",
    "gn:population":0,
    "gn:timezone":"Asia/Shanghai",
    "iso:country":"CN",
    "name:zho_x_preferred":[
        "\u8005\u6d2a"
    ],
    "wof:name":"Zhehong",
    "wof:placetype":"locality"
},
  "geometry": {"coordinates":[104.56999999999999,25.1871],"type":"Point"}
}