{
  "type": "Feature",
  "properties": {
    "gn:admin1_code":"04",
    "gn:asciiname":"Gaoqiao",
    "gn:country_code":"CN",
    "gn:dem":8,
    "gn:feature_class":"P",
    "gn:feature_code":"PPLA4",
    "gn:name":"Gaoqiao",
    "gn:population":0,
    "gn:timezone":"Asia/Shanghai",
    "iso:country":"CN",
    "name:ceb_x_preferred":[
        "Gaoqiao"
    ],
    "name:deu_x_preferred":[
        "Gaoqiao"
    ],
    "name:swe_x_preferred":[
        "Gaoqiao"
    ],
    "name:und_x_variant":[
        "Kao-ch\u2019iao-chen",
        "Kao-ch\u2019iao",
        "Gaoqiao",
        "Gaoqiao Zhen"
    ],
    "name:zho_x_preferred":[
        "\u9ad8\u6865"
    ],
    "wof:name":"Gaoqiao",
    "wof:placetype":"locality"
},
  "geometry": {"coordinates":[119.64919999999999,32.22907],"type":"Point"}
}