{
  "type": "Feature",
  "properties": {
    "gn:admin1_code":"12.0",
    "gn:asciiname":"Tangjia Laowu",
    "gn:country_code":"CN",
    "gn:dem":35,
    "gn:feature_class":"P",
    "gn:feature_code":"PPL",
    "gn:name":"Tangjia Laowu",
    "gn:population":0,
    "gn:timezone":"Asia/Shanghai",
    "iso:country":"CN",
    "name:zho_x_preferred":[
        "\u6c64\u5bb6\u8001\u5c4b"
    ],
    "wof:name":"Tangjia Laowu",
    "wof:placetype":"locality"
},
  "geometry": {"coordinates":[113.97008,30.91002000000001],"type":"Point"}
}