{
  "type": "Feature",
  "properties": {
    "gn:admin1_code":"05",
    "gn:asciiname":"Sanhonghuzi",
    "gn:country_code":"CN",
    "gn:dem":515,
    "gn:feature_class":"P",
    "gn:feature_code":"PPL",
    "gn:name":"Sanhonghuzi",
    "gn:population":0,
    "gn:timezone":"Asia/Shanghai",
    "iso:country":"CN",
    "name:und_x_variant":[
        "\u4e09\u5f18\u6e56\u5b50",
        "San-hung-hu-tzu"
    ],
    "wof:name":"Sanhonghuzi",
    "wof:placetype":"locality"
},
  "geometry": {"coordinates":[125.71321,40.88542],"type":"Point"}
}