{
  "type": "Feature",
  "properties": {
    "gn:admin1_code":"1.0",
    "gn:asciiname":"Qiushancun",
    "gn:country_code":"CN",
    "gn:dem":655,
    "gn:feature_class":"P",
    "gn:feature_code":"PPL",
    "gn:name":"Qiushancun",
    "gn:population":0,
    "gn:timezone":"Asia/Shanghai",
    "iso:country":"CN",
    "name:zho_x_preferred":[
        "\u90b1\u5c71\u6751"
    ],
    "wof:name":"Qiushancun",
    "wof:placetype":"locality"
},
  "geometry": {"coordinates":[116.50736999999999,31.116],"type":"Point"}
}