{
  "type": "Feature",
  "properties": {
    "gn:admin1_code":"1.0",
    "gn:asciiname":"Sankoutangcun",
    "gn:country_code":"CN",
    "gn:dem":35,
    "gn:feature_class":"P",
    "gn:feature_code":"PPL",
    "gn:name":"Sankoutangcun",
    "gn:population":0,
    "gn:timezone":"Asia/Shanghai",
    "iso:country":"CN",
    "name:zho_x_preferred":[
        "\u4e09\u53e3\u5858\u6751"
    ],
    "wof:name":"Sankoutangcun",
    "wof:placetype":"locality"
},
  "geometry": {"coordinates":[116.27649,32.04754000000001],"type":"Point"}
}