{
  "type": "Feature",
  "properties": {
    "gn:admin1_code":"12.0",
    "gn:asciiname":"Wuyeguo",
    "gn:country_code":"CN",
    "gn:dem":153,
    "gn:feature_class":"P",
    "gn:feature_code":"PPL",
    "gn:name":"Wuyeguo",
    "gn:population":0,
    "gn:timezone":"Asia/Shanghai",
    "iso:country":"CN",
    "name:zho_x_preferred":[
        "Wuyeguo"
    ],
    "name:zho_x_variant":[
        "\u4e94\u53f6\u57da"
    ],
    "wof:name":"Wuyeguo",
    "wof:placetype":"locality"
},
  "geometry": {"coordinates":[114.00912,29.37698],"type":"Point"}
}