{
  "type": "Feature",
  "properties": {
    "gn:admin1_code":"10",
    "gn:asciiname":"Wangxuezhuang",
    "gn:country_code":"CN",
    "gn:dem":20,
    "gn:feature_class":"P",
    "gn:feature_code":"PPL",
    "gn:name":"Wangxuezhuang",
    "gn:population":0,
    "gn:timezone":"Asia/Shanghai",
    "iso:country":"CN",
    "name:zho_x_preferred":[
        "\u738b\u859b\u5e84"
    ],
    "wof:name":"Wangxuezhuang",
    "wof:placetype":"locality"
},
  "geometry": {"coordinates":[115.81999999999999,37.9042],"type":"Point"}
}