{
  "type": "Feature",
  "properties": {
    "gn:admin1_code":"30.0",
    "gn:asciiname":"Liangdong",
    "gn:country_code":"CN",
    "gn:dem":407,
    "gn:feature_class":"P",
    "gn:feature_code":"PPL",
    "gn:name":"Liangdong",
    "gn:population":0,
    "gn:timezone":"Asia/Shanghai",
    "iso:country":"CN",
    "name:zho_x_preferred":[
        "Liangdong"
    ],
    "name:zho_x_variant":[
        "\u826f\u6d1e"
    ],
    "wof:name":"Liangdong",
    "wof:placetype":"locality"
},
  "geometry": {"coordinates":[112.13916999999999,24.40222],"type":"Point"}
}