{
  "type": "Feature",
  "properties": {
    "gn:admin1_code":"15.0",
    "gn:asciiname":"Yayi",
    "gn:country_code":"CN",
    "gn:dem":2433,
    "gn:feature_class":"P",
    "gn:feature_code":"PPL",
    "gn:name":"Yayi",
    "gn:population":0,
    "gn:timezone":"Asia/Shanghai",
    "iso:country":"CN",
    "name:und_x_variant":[
        "\u7259\u76ca"
    ],
    "name:zho_x_preferred":[
        "\u7259\u76ca"
    ],
    "wof:name":"Yayi",
    "wof:placetype":"locality"
},
  "geometry": {"coordinates":[104.22851,33.74999],"type":"Point"}
}