{
  "type": "Feature",
  "properties": {
    "gn:admin1_code":"32.0",
    "gn:asciiname":"Maguishi",
    "gn:country_code":"CN",
    "gn:dem":687,
    "gn:feature_class":"P",
    "gn:feature_code":"PPL",
    "gn:name":"Maguishi",
    "gn:population":0,
    "gn:timezone":"Asia/Shanghai",
    "iso:country":"CN",
    "name:zho_x_preferred":[
        "\u9a6c\u8dea\u77f3"
    ],
    "wof:name":"Maguishi",
    "wof:placetype":"locality"
},
  "geometry": {"coordinates":[106.842,31.4162],"type":"Point"}
}