{
  "type": "Feature",
  "properties": {
    "gn:admin1_code":"12.0",
    "gn:asciiname":"Baimenlou",
    "gn:country_code":"CN",
    "gn:dem":26,
    "gn:feature_class":"P",
    "gn:feature_code":"PPL",
    "gn:name":"Baimenlou",
    "gn:population":0,
    "gn:timezone":"Asia/Shanghai",
    "iso:country":"CN",
    "name:zho_x_preferred":[
        "Baimenlou"
    ],
    "name:zho_x_variant":[
        "\u767d\u95e8\u697c"
    ],
    "wof:name":"Baimenlou",
    "wof:placetype":"locality"
},
  "geometry": {"coordinates":[115.05492,29.81459000000001],"type":"Point"}
}