{
  "type": "Feature",
  "properties": {
    "gn:admin1_code":"29.0",
    "gn:asciiname":"Zhashi",
    "gn:country_code":"CN",
    "gn:dem":2718,
    "gn:feature_class":"P",
    "gn:feature_code":"PPL",
    "gn:name":"Zhashi",
    "gn:population":0,
    "gn:timezone":"Asia/Shanghai",
    "iso:country":"CN",
    "name:zho_x_preferred":[
        "\u624e\u5b9e"
    ],
    "wof:name":"Zhashi",
    "wof:placetype":"locality"
},
  "geometry": {"coordinates":[100.68600000000001,27.7282],"type":"Point"}
}