{
  "type": "Feature",
  "properties": {
    "gn:admin1_code":"25",
    "gn:asciiname":"Buliu",
    "gn:country_code":"CN",
    "gn:dem":47,
    "gn:feature_class":"P",
    "gn:feature_code":"PPLA4",
    "gn:name":"Buliu",
    "gn:population":0,
    "gn:timezone":"Asia/Shanghai",
    "iso:country":"CN",
    "name:und_x_variant":[
        "Pu-liu-ts\u2019un",
        "Buliucun",
        "Buliu",
        "Buliu Zhen"
    ],
    "name:zho_x_preferred":[
        "\u57e0\u67f3"
    ],
    "name:zho_x_variant":[
        "\u57e0\u67f3\u9547"
    ],
    "wof:name":"Buliu",
    "wof:placetype":"locality"
},
  "geometry": {"coordinates":[122.43068999999998,37.33689],"type":"Point"}
}