{
  "type": "Feature",
  "properties": {
    "gn:admin1_code":"3.0",
    "gn:asciiname":"Longju Lijia",
    "gn:country_code":"CN",
    "gn:dem":94,
    "gn:feature_class":"P",
    "gn:feature_code":"PPL",
    "gn:name":"Longju Lijia",
    "gn:population":0,
    "gn:timezone":"Asia/Shanghai",
    "iso:country":"CN",
    "name:und_x_variant":[
        "\u9f99\u5c45\u674e\u5bb6"
    ],
    "wof:name":"Longju Lijia",
    "wof:placetype":"locality"
},
  "geometry": {"coordinates":[117.71814999999999,29.22493],"type":"Point"}
}