{
  "type": "Feature",
  "properties": {
    "gn:admin1_code":"30.0",
    "gn:asciiname":"Kengwei",
    "gn:country_code":"CN",
    "gn:dem":56,
    "gn:feature_class":"P",
    "gn:feature_code":"PPL",
    "gn:name":"Kengwei",
    "gn:population":0,
    "gn:timezone":"Asia/Shanghai",
    "iso:country":"CN",
    "name:zho_x_preferred":[
        "\u5751\u5c3e"
    ],
    "wof:name":"Kengwei",
    "wof:placetype":"locality"
},
  "geometry": {"coordinates":[112.08378999999999,22.9758],"type":"Point"}
}