{
  "type": "Feature",
  "properties": {
    "gn:admin1_code":"19.0",
    "gn:asciiname":"Chetouyingzi",
    "gn:country_code":"CN",
    "gn:dem":142,
    "gn:feature_class":"P",
    "gn:feature_code":"PPL",
    "gn:name":"Chetouyingzi",
    "gn:population":0,
    "gn:timezone":"Asia/Shanghai",
    "iso:country":"CN",
    "name:und_x_variant":[
        "\u8f66\u5934\u8425\u5b50"
    ],
    "name:zho_x_preferred":[
        "\u8f66\u5934\u8425\u5b50"
    ],
    "wof:name":"Chetouyingzi",
    "wof:placetype":"locality"
},
  "geometry": {"coordinates":[120.70547000000001,41.64343],"type":"Point"}
}