{
  "type": "Feature",
  "properties": {
    "gn:admin1_code":"33.0",
    "gn:asciiname":"Qianjiang",
    "gn:country_code":"CN",
    "gn:dem":582,
    "gn:feature_class":"P",
    "gn:feature_code":"PPLA3",
    "gn:name":"Qianjiang",
    "gn:population":0,
    "gn:timezone":"Asia/Shanghai",
    "iso:country":"CN",
    "name:deu_x_preferred":[
        "Qianjiang"
    ],
    "name:eng_x_preferred":[
        "Qianjiang"
    ],
    "name:eus_x_preferred":[
        "Qianjiang Barrutia"
    ],
    "name:fas_x_preferred":[
        "\u06a9\u06cc\u0627\u0646\u0698\u06cc\u0627\u0646\u06af"
    ],
    "name:jpn_x_preferred":[
        "\u9ed4\u6c5f\u533a"
    ],
    "name:kor_x_preferred":[
        "\uccb8\uc7a5\uad6c"
    ],
    "name:mwl_x_preferred":[
        "Qianjiang"
    ],
    "name:nld_x_preferred":[
        "Qianjiang"
    ],
    "name:nor_x_preferred":[
        "Qianjiang"
    ],
    "name:rus_x_preferred":[
        "\u0426\u044f\u043d\u044c\u0446\u0437\u044f\u043d"
    ],
    "name:swe_x_preferred":[
        "Qianjiang"
    ],
    "name:tur_x_preferred":[
        "Qianjiang"
    ],
    "name:und_x_variant":[
        "Chengxi",
        "Chengxi Jiedao",
        "Qianjiang"
    ],
    "name:urd_x_preferred":[
        "\u0686\u06cc\u0627\u0646\u062c\u06cc\u0627\u0646\u06af \u0636\u0644\u0639"
    ],
    "name:vie_x_preferred":[
        "Ki\u1ec1m Giang"
    ],
    "name:zho_x_preferred":[
        "\u57ce\u897f"
    ],
    "name:zho_x_variant":[
        "\u57ce\u897f\u8857\u9053",
        "\u9ed4\u6c5f\u533a"
    ],
    "wof:name":"Qianjiang",
    "wof:placetype":"locality"
},
  "geometry": {"coordinates":[108.77478000000001,29.53284],"type":"Point"}
}