{
  "type": "Feature",
  "properties": {
    "gn:admin1_code":"7",
    "gn:asciiname":"Lujiayang",
    "gn:country_code":"CN",
    "gn:dem":949,
    "gn:feature_class":"P",
    "gn:feature_code":"PPL",
    "gn:name":"L\u00fcjiayang",
    "gn:population":0,
    "gn:timezone":"Asia/Shanghai",
    "iso:country":"CN",
    "name:und_x_variant":[
        "L\u00fcjiayang",
        "\u5415\u5bb6\u6d0b"
    ],
    "wof:name":"Lujiayang",
    "wof:placetype":"locality"
},
  "geometry": {"coordinates":[119.07722,27.1725],"type":"Point"}
}