{
  "type": "Feature",
  "properties": {
    "gn:admin1_code":"02",
    "gn:asciiname":"Daodiao'ertou",
    "gn:country_code":"CN",
    "gn:dem":230,
    "gn:feature_class":"P",
    "gn:feature_code":"PPL",
    "gn:name":"Daodiao\u2019ertou",
    "gn:population":0,
    "gn:timezone":"Asia/Shanghai",
    "iso:country":"CN",
    "name:zho_x_preferred":[
        "Daodiao\u2019ertou"
    ],
    "wof:name":"Daodiao'ertou",
    "wof:placetype":"locality"
},
  "geometry": {"coordinates":[120.53943999999998,27.92806],"type":"Point"}
}