{
  "type": "Feature",
  "properties": {
    "gn:admin1_code":"25.0",
    "gn:asciiname":"Xiaolian",
    "gn:country_code":"CN",
    "gn:dem":19,
    "gn:feature_class":"P",
    "gn:feature_code":"PPL",
    "gn:name":"Xiaolian",
    "gn:population":0,
    "gn:timezone":"Asia/Shanghai",
    "iso:country":"CN",
    "name:fra_x_preferred":[
        "Xiaolian"
    ],
    "name:zho_x_preferred":[
        "\u5c0f\u83b2"
    ],
    "wof:name":"Xiaolian",
    "wof:placetype":"locality"
},
  "geometry": {"coordinates":[119.46825,35.46697],"type":"Point"}
}