{
  "type": "Feature",
  "properties": {
    "gn:admin1_code":"19.0",
    "gn:asciiname":"Daniugou",
    "gn:country_code":"CN",
    "gn:dem":161,
    "gn:feature_class":"P",
    "gn:feature_code":"PPL",
    "gn:name":"Daniugou",
    "gn:population":0,
    "gn:timezone":"Asia/Shanghai",
    "iso:country":"CN",
    "name:zho_x_preferred":[
        "\u5927\u725b\u6c9f"
    ],
    "wof:name":"Daniugou",
    "wof:placetype":"locality"
},
  "geometry": {"coordinates":[125.01600000000001,40.6351],"type":"Point"}
}