{
  "type": "Feature",
  "properties": {
    "gn:admin1_code":"2",
    "gn:asciiname":"Baozhulong",
    "gn:country_code":"CN",
    "gn:dem":312,
    "gn:feature_class":"P",
    "gn:feature_code":"PPL",
    "gn:name":"Baozhulong",
    "gn:population":0,
    "gn:timezone":"Asia/Shanghai",
    "iso:country":"CN",
    "name:zho_x_preferred":[
        "\u62b1\u73e0\u5784"
    ],
    "wof:name":"Baozhulong",
    "wof:placetype":"locality"
},
  "geometry": {"coordinates":[118.84407,28.64297],"type":"Point"}
}