{
  "type": "Feature",
  "properties": {
    "gn:admin1_code":"16.0",
    "gn:asciiname":"Jiziling",
    "gn:country_code":"CN",
    "gn:dem":141,
    "gn:feature_class":"P",
    "gn:feature_code":"PPL",
    "gn:name":"Jiziling",
    "gn:population":0,
    "gn:timezone":"Asia/Shanghai",
    "iso:country":"CN",
    "name:zho_x_preferred":[
        "\u9e21\u4ed4\u5cad"
    ],
    "wof:name":"Jiziling",
    "wof:placetype":"locality"
},
  "geometry": {"coordinates":[110.86,24.6091],"type":"Point"}
}