{
  "type": "Feature",
  "properties": {
    "gn:admin1_code":"11.0",
    "gn:asciiname":"Masixi",
    "gn:country_code":"CN",
    "gn:dem":516,
    "gn:feature_class":"P",
    "gn:feature_code":"PPL",
    "gn:name":"Masixi",
    "gn:population":0,
    "gn:timezone":"Asia/Shanghai",
    "iso:country":"CN",
    "name:zho_x_preferred":[
        "\u9a6c\u5636\u6eaa"
    ],
    "wof:name":"Masixi",
    "wof:placetype":"locality"
},
  "geometry": {"coordinates":[110.04236000000002,29.21453],"type":"Point"}
}