{
  "type": "Feature",
  "properties": {
    "gn:admin1_code":"16.0",
    "gn:asciiname":"Guansheping",
    "gn:country_code":"CN",
    "gn:dem":220,
    "gn:feature_class":"P",
    "gn:feature_code":"PPL",
    "gn:name":"Guansheping",
    "gn:population":0,
    "gn:timezone":"Asia/Shanghai",
    "iso:country":"CN",
    "name:zho_x_preferred":[
        "\u5b98\u793e\u576a"
    ],
    "wof:name":"Guansheping",
    "wof:placetype":"locality"
},
  "geometry": {"coordinates":[110.459,24.1679],"type":"Point"}
}