{
  "type": "Feature",
  "properties": {
    "gn:admin1_code":"12.0",
    "gn:asciiname":"Wodangping",
    "gn:country_code":"CN",
    "gn:dem":989,
    "gn:feature_class":"P",
    "gn:feature_code":"PPL",
    "gn:name":"Wodangping",
    "gn:population":0,
    "gn:timezone":"Asia/Shanghai",
    "iso:country":"CN",
    "name:zho_x_preferred":[
        "\u7a9d\u51fc\u576a"
    ],
    "wof:name":"Wodangping",
    "wof:placetype":"locality"
},
  "geometry": {"coordinates":[108.98457000000001,29.87997],"type":"Point"}
}