{
  "type": "Feature",
  "properties": {
    "gn:admin1_code":"29",
    "gn:asciiname":"Benlong",
    "gn:country_code":"CN",
    "gn:dem":1569,
    "gn:feature_class":"P",
    "gn:feature_code":"PPL",
    "gn:name":"Benlong",
    "gn:population":0,
    "gn:timezone":"Asia/Shanghai",
    "iso:country":"CN",
    "name:zho_x_preferred":[
        "\u672c\u9f99"
    ],
    "wof:name":"Benlong",
    "wof:placetype":"locality"
},
  "geometry": {"coordinates":[103.25018,24.97574],"type":"Point"}
}