{
  "type": "Feature",
  "properties": {
    "gn:admin1_code":"25.0",
    "gn:asciiname":"Beiliushuicun",
    "gn:country_code":"CN",
    "gn:dem":56,
    "gn:feature_class":"P",
    "gn:feature_code":"PPL",
    "gn:name":"Beiliushuicun",
    "gn:population":0,
    "gn:timezone":"Asia/Shanghai",
    "iso:country":"CN",
    "name:zho_x_preferred":[
        "\u5317\u6d41\u6c34\u6751"
    ],
    "wof:name":"Beiliushuicun",
    "wof:placetype":"locality"
},
  "geometry": {"coordinates":[122.33019,37.20189],"type":"Point"}
}