{
  "type": "Feature",
  "properties": {
    "gn:admin1_code":"7.0",
    "gn:asciiname":"Fozigao",
    "gn:country_code":"CN",
    "gn:dem":269,
    "gn:feature_class":"P",
    "gn:feature_code":"PPL",
    "gn:name":"Fozigao",
    "gn:population":0,
    "gn:timezone":"Asia/Shanghai",
    "iso:country":"CN",
    "name:zho_x_preferred":[
        "\u4f5b\u5b50\u9ad8"
    ],
    "wof:name":"Fozigao",
    "wof:placetype":"locality"
},
  "geometry": {"coordinates":[116.08058,25.08023],"type":"Point"}
}