{
  "type": "Feature",
  "properties": {
    "gn:admin1_code":"18",
    "gn:asciiname":"Daloujiao",
    "gn:country_code":"CN",
    "gn:dem":1384,
    "gn:feature_class":"P",
    "gn:feature_code":"PPL",
    "gn:name":"Daloujiao",
    "gn:population":0,
    "gn:timezone":"Asia/Shanghai",
    "iso:country":"CN",
    "name:zho_x_preferred":[
        "\u5927\u697c\u811a"
    ],
    "wof:name":"Daloujiao",
    "wof:placetype":"locality"
},
  "geometry": {"coordinates":[106.218,26.5337],"type":"Point"}
}