{
  "type": "Feature",
  "properties": {
    "gn:admin1_code":"31",
    "gn:asciiname":"Renxincun",
    "gn:country_code":"CN",
    "gn:dem":36,
    "gn:feature_class":"P",
    "gn:feature_code":"PPL",
    "gn:name":"Renxincun",
    "gn:population":0,
    "gn:timezone":"Asia/Shanghai",
    "iso:country":"CN",
    "name:zho_x_preferred":[
        "\u4ec1\u65b0\u6751"
    ],
    "wof:name":"Renxincun",
    "wof:placetype":"locality"
},
  "geometry": {"coordinates":[110.351,19.7972],"type":"Point"}
}