{
  "type": "Feature",
  "properties": {
    "gn:admin1_code":"33.0",
    "gn:asciiname":"Dawa",
    "gn:country_code":"CN",
    "gn:dem":302,
    "gn:feature_class":"P",
    "gn:feature_code":"PPL",
    "gn:name":"Dawa",
    "gn:population":0,
    "gn:timezone":"Asia/Shanghai",
    "iso:country":"CN",
    "name:ceb_x_preferred":[
        "Dawa"
    ],
    "name:deu_x_preferred":[
        "Dawa"
    ],
    "name:fra_x_preferred":[
        "Dawa"
    ],
    "name:nor_x_preferred":[
        "Dawa"
    ],
    "name:por_x_preferred":[
        "Dawa"
    ],
    "name:swe_x_preferred":[
        "Dawa"
    ],
    "name:zho_x_preferred":[
        "\u5927\u74e6"
    ],
    "wof:name":"Dawa",
    "wof:placetype":"locality"
},
  "geometry": {"coordinates":[109.36664,31.01834],"type":"Point"}
}