{
  "type": "Feature",
  "properties": {
    "gn:admin1_code":"25.0",
    "gn:asciiname":"Dadiji",
    "gn:cc2":"CN",
    "gn:country_code":"CN",
    "gn:dem":64,
    "gn:feature_class":"P",
    "gn:feature_code":"PPL",
    "gn:name":"Dadiji",
    "gn:population":0,
    "gn:timezone":"Asia/Shanghai",
    "iso:country":"CN",
    "name:zho_x_preferred":[
        "\u5927\u8fea\u5409"
    ],
    "wof:name":"Dadiji",
    "wof:placetype":"locality"
},
  "geometry": {"coordinates":[119.4397,35.7118],"type":"Point"}
}