{
  "type": "Feature",
  "properties": {
    "gn:admin1_code":"24.0",
    "gn:asciiname":"Qianyaoshang",
    "gn:country_code":"CN",
    "gn:dem":824,
    "gn:feature_class":"P",
    "gn:feature_code":"PPL",
    "gn:name":"Qianyaoshang",
    "gn:population":0,
    "gn:timezone":"Asia/Shanghai",
    "iso:country":"CN",
    "name:zho_x_preferred":[
        "\u524d\u7a91\u4e0a"
    ],
    "wof:name":"Qianyaoshang",
    "wof:placetype":"locality"
},
  "geometry": {"coordinates":[110.61628,36.62814],"type":"Point"}
}