{
  "type": "Feature",
  "properties": {
    "gn:admin1_code":"9.0",
    "gn:asciiname":"Nanzhuang",
    "gn:country_code":"CN",
    "gn:dem":623,
    "gn:feature_class":"P",
    "gn:feature_code":"PPL",
    "gn:name":"Nanzhuang",
    "gn:population":0,
    "gn:timezone":"Asia/Shanghai",
    "iso:country":"CN",
    "name:und_x_variant":[
        "\u5357\u5e84",
        "Nanzhuang"
    ],
    "wof:name":"Nanzhuang",
    "wof:placetype":"locality"
},
  "geometry": {"coordinates":[112.23222,33.38324],"type":"Point"}
}