{
  "type": "Feature",
  "properties": {
    "gn:admin1_code":"14.0",
    "gn:asciiname":"Kambudoi",
    "gn:country_code":"CN",
    "gn:dem":4164,
    "gn:feature_class":"P",
    "gn:feature_code":"PPLF",
    "gn:name":"Kambudoi",
    "gn:population":0,
    "gn:timezone":"Asia/Urumqi",
    "iso:country":"CN",
    "name:bod_x_preferred":[
        "Kambudoi"
    ],
    "name:zho_x_preferred":[
        "Kangbudui"
    ],
    "name:zho_x_variant":[
        "\u5eb7\u5e03\u5806",
        "Xiongmo",
        "\u96c4\u6a21"
    ],
    "wof:name":"Kambudoi",
    "wof:placetype":"locality"
},
  "geometry": {"coordinates":[88.90100000000002,27.701],"type":"Point"}
}