{
  "type": "Feature",
  "properties": {
    "gn:admin1_code":"4.0",
    "gn:asciiname":"Rongzhongcun",
    "gn:country_code":"CN",
    "gn:dem":4,
    "gn:feature_class":"P",
    "gn:feature_code":"PPL",
    "gn:name":"Rongzhongcun",
    "gn:population":0,
    "gn:timezone":"Asia/Shanghai",
    "iso:country":"CN",
    "name:und_x_variant":[
        "\u84c9\u4e2d\u6751"
    ],
    "name:zho_x_preferred":[
        "\u84c9\u4e2d\u6751"
    ],
    "wof:name":"Rongzhongcun",
    "wof:placetype":"locality"
},
  "geometry": {"coordinates":[120.16685,31.73663],"type":"Point"}
}