{
  "type": "Feature",
  "properties": {
    "gn:admin1_code":"30",
    "gn:asciiname":"Wushan",
    "gn:country_code":"CN",
    "gn:dem":355,
    "gn:feature_class":"P",
    "gn:feature_code":"PPLA4",
    "gn:name":"Wushan",
    "gn:population":0,
    "gn:timezone":"Asia/Shanghai",
    "iso:country":"CN",
    "name:und_x_variant":[
        "\u4e94\u5c71",
        "Wushan Zhen",
        "\u4e94\u5c71\u9547"
    ],
    "wof:name":"Wushan",
    "wof:placetype":"locality"
},
  "geometry": {"coordinates":[113.48014999999999,25.25104],"type":"Point"}
}