{
  "type": "Feature",
  "properties": {
    "gn:admin1_code":"11",
    "gn:asciiname":"Qijiaping",
    "gn:country_code":"CN",
    "gn:dem":196,
    "gn:feature_class":"P",
    "gn:feature_code":"PPLA4",
    "gn:name":"Qijiaping",
    "gn:population":0,
    "gn:timezone":"Asia/Shanghai",
    "iso:country":"CN",
    "name:und_x_variant":[
        "Ch\u2019i-chia-p\u2019ing",
        "Qijiaping",
        "\u4e03\u7532\u576a",
        "Qijiaping Zhen",
        "\u4e03\u7532\u576a\u9547"
    ],
    "wof:name":"Qijiaping",
    "wof:placetype":"locality"
},
  "geometry": {"coordinates":[110.85363999999998,28.88485],"type":"Point"}
}