{
  "type": "Feature",
  "properties": {
    "gn:admin1_code":"8.0",
    "gn:asciiname":"Qulianyoutun",
    "gn:country_code":"CN",
    "gn:dem":218,
    "gn:feature_class":"P",
    "gn:feature_code":"PPL",
    "gn:name":"Qulianyoutun",
    "gn:population":0,
    "gn:timezone":"Asia/Shanghai",
    "iso:country":"CN",
    "name:zho_x_preferred":[
        "\u66f2\u8fde\u6709\u5c6f"
    ],
    "wof:name":"Qulianyoutun",
    "wof:placetype":"locality"
},
  "geometry": {"coordinates":[125.33112,47.59571],"type":"Point"}
}