{
  "type": "Feature",
  "properties": {
    "gn:admin1_code":"09",
    "gn:asciiname":"Xiaoying",
    "gn:country_code":"CN",
    "gn:dem":83,
    "gn:feature_class":"P",
    "gn:feature_code":"PPL",
    "gn:name":"Xiaoying",
    "gn:population":0,
    "gn:timezone":"Asia/Shanghai",
    "iso:country":"CN",
    "name:und_x_variant":[
        "\u5c0f\u8425",
        "Daying",
        "Xiaoying"
    ],
    "wof:name":"Xiaoying",
    "wof:placetype":"locality"
},
  "geometry": {"coordinates":[113.3604,33.72087],"type":"Point"}
}