{
  "type": "Feature",
  "properties": {
    "gn:admin1_code":"33",
    "gn:asciiname":"Shihui",
    "gn:country_code":"CN",
    "gn:dem":464,
    "gn:feature_class":"P",
    "gn:feature_code":"PPLA4",
    "gn:name":"Shihui",
    "gn:population":0,
    "gn:timezone":"Asia/Shanghai",
    "iso:country":"CN",
    "name:und_x_variant":[
        "Shih-hui",
        "Shihui",
        "Shihui Zhen"
    ],
    "name:zho_x_preferred":[
        "\u77f3\u4f1a"
    ],
    "name:zho_x_variant":[
        "\u77f3\u4f1a\u9547"
    ],
    "wof:name":"Shihui",
    "wof:placetype":"locality"
},
  "geometry": {"coordinates":[108.61017,29.57177],"type":"Point"}
}