{
  "type": "Feature",
  "properties": {
    "gn:admin1_code":"29",
    "gn:asciiname":"Matuo",
    "gn:country_code":"CN",
    "gn:dem":1447,
    "gn:feature_class":"P",
    "gn:feature_code":"PPL",
    "gn:name":"Matuo",
    "gn:population":0,
    "gn:timezone":"Asia/Shanghai",
    "iso:country":"CN",
    "name:zho_x_preferred":[
        "\u9a6c\u9a6e"
    ],
    "wof:name":"Matuo",
    "wof:placetype":"locality"
},
  "geometry": {"coordinates":[105.059,23.8322],"type":"Point"}
}