{
  "type": "Feature",
  "properties": {
    "gn:admin1_code":"10",
    "gn:asciiname":"Xiyanggao",
    "gn:country_code":"CN",
    "gn:dem":63,
    "gn:feature_class":"P",
    "gn:feature_code":"PPL",
    "gn:name":"Xiyanggao",
    "gn:population":0,
    "gn:timezone":"Asia/Shanghai",
    "iso:country":"CN",
    "wof:name":"Xiyanggao",
    "wof:placetype":"locality"
},
  "geometry": {"coordinates":[114.66694,36.33917],"type":"Point"}
}