{
  "type": "Feature",
  "properties": {
    "gn:admin1_code":"8.0",
    "gn:asciiname":"Minfacun",
    "gn:country_code":"CN",
    "gn:dem":141,
    "gn:feature_class":"P",
    "gn:feature_code":"PPL",
    "gn:name":"Minfacun",
    "gn:population":0,
    "gn:timezone":"Asia/Shanghai",
    "iso:country":"CN",
    "name:zho_x_preferred":[
        "\u6c11\u53d1\u6751"
    ],
    "wof:name":"Minfacun",
    "wof:placetype":"locality"
},
  "geometry": {"coordinates":[126.32135,45.60632],"type":"Point"}
}