{
  "type": "Feature",
  "properties": {
    "gn:admin1_code":"18",
    "gn:asciiname":"Gaoshan",
    "gn:country_code":"CN",
    "gn:dem":1008,
    "gn:feature_class":"P",
    "gn:feature_code":"PPL",
    "gn:name":"Gaoshan",
    "gn:population":0,
    "gn:timezone":"Asia/Shanghai",
    "iso:country":"CN",
    "wof:name":"Gaoshan",
    "wof:placetype":"locality"
},
  "geometry": {"coordinates":[107.73333,26.58333],"type":"Point"}
}