{
  "type": "Feature",
  "properties": {
    "gn:admin1_code":"19.0",
    "gn:asciiname":"Xiamajiazi",
    "gn:country_code":"CN",
    "gn:dem":538,
    "gn:feature_class":"P",
    "gn:feature_code":"PPL",
    "gn:name":"Xiamajiazi",
    "gn:population":0,
    "gn:timezone":"Asia/Shanghai",
    "iso:country":"CN",
    "name:zho_x_preferred":[
        "\u4e0b\u9a6c\u5bb6\u5b50"
    ],
    "wof:name":"Xiamajiazi",
    "wof:placetype":"locality"
},
  "geometry": {"coordinates":[119.547,40.8533],"type":"Point"}
}