{
  "type": "Feature",
  "properties": {
    "gn:admin1_code":"12.0",
    "gn:asciiname":"Nianpanya",
    "gn:country_code":"CN",
    "gn:dem":578,
    "gn:feature_class":"P",
    "gn:feature_code":"PPL",
    "gn:name":"Nianpanya",
    "gn:population":0,
    "gn:timezone":"Asia/Shanghai",
    "iso:country":"CN",
    "name:zho_x_preferred":[
        "\u78be\u76d8\u57ad"
    ],
    "wof:name":"Nianpanya",
    "wof:placetype":"locality"
},
  "geometry": {"coordinates":[110.22423999999999,31.05372],"type":"Point"}
}