{
  "type": "Feature",
  "properties": {
    "gn:admin1_code":"26.0",
    "gn:asciiname":"Huawuji",
    "gn:country_code":"CN",
    "gn:dem":891,
    "gn:feature_class":"P",
    "gn:feature_code":"PPL",
    "gn:name":"Huawuji",
    "gn:population":0,
    "gn:timezone":"Asia/Shanghai",
    "iso:country":"CN",
    "name:zho_x_preferred":[
        "\u82b1\u5c4b\u57fa"
    ],
    "wof:name":"Huawuji",
    "wof:placetype":"locality"
},
  "geometry": {"coordinates":[107.45010000000001,32.58494],"type":"Point"}
}