{
  "type": "Feature",
  "properties": {
    "gn:admin1_code":"11.0",
    "gn:asciiname":"Bairuo",
    "gn:country_code":"CN",
    "gn:dem":273,
    "gn:feature_class":"P",
    "gn:feature_code":"PPL",
    "gn:name":"Bairuo",
    "gn:population":0,
    "gn:timezone":"Asia/Shanghai",
    "iso:country":"CN",
    "name:zho_x_preferred":[
        "\u767d\u7bac"
    ],
    "wof:name":"Bairuo",
    "wof:placetype":"locality"
},
  "geometry": {"coordinates":[113.66603000000001,29.2208],"type":"Point"}
}