{
  "type": "Feature",
  "properties": {
    "gn:admin1_code":"2.0",
    "gn:asciiname":"Bicong",
    "gn:country_code":"CN",
    "gn:dem":132,
    "gn:feature_class":"P",
    "gn:feature_code":"PPL",
    "gn:name":"Bicong",
    "gn:population":0,
    "gn:timezone":"Asia/Shanghai",
    "iso:country":"CN",
    "name:und_x_variant":[
        "\u78a7\u6dd9"
    ],
    "wof:name":"Bicong",
    "wof:placetype":"locality"
},
  "geometry": {"coordinates":[119.55329999999999,30.25536],"type":"Point"}
}