{
  "type": "Feature",
  "properties": {
    "gn:admin1_code":"15.0",
    "gn:asciiname":"Xiaozhuang",
    "gn:country_code":"CN",
    "gn:dem":1894,
    "gn:feature_class":"P",
    "gn:feature_code":"PPL",
    "gn:name":"Xiaozhuang",
    "gn:population":0,
    "gn:timezone":"Asia/Shanghai",
    "iso:country":"CN",
    "name:ceb_x_preferred":[
        "Xiaozhuang"
    ],
    "name:und_x_variant":[
        "\u5c0f\u5e84"
    ],
    "wof:name":"Xiaozhuang",
    "wof:placetype":"locality"
},
  "geometry": {"coordinates":[105.12307,33.52314000000001],"type":"Point"}
}