{
  "type": "Feature",
  "properties": {
    "gn:admin1_code":"4.0",
    "gn:asciiname":"Jinjiadun",
    "gn:country_code":"CN",
    "gn:dem":3,
    "gn:feature_class":"P",
    "gn:feature_code":"PPL",
    "gn:name":"Jinjiadun",
    "gn:population":0,
    "gn:timezone":"Asia/Shanghai",
    "iso:country":"CN",
    "name:und_x_variant":[
        "\u91d1\u5bb6\u58a9"
    ],
    "wof:name":"Jinjiadun",
    "wof:placetype":"locality"
},
  "geometry": {"coordinates":[120.6567,32.96609],"type":"Point"}
}