{
  "type": "Feature",
  "properties": {
    "gn:admin1_code":"16.0",
    "gn:asciiname":"Sanli",
    "gn:country_code":"CN",
    "gn:dem":105,
    "gn:feature_class":"P",
    "gn:feature_code":"PPL",
    "gn:name":"Sanli",
    "gn:population":0,
    "gn:timezone":"Asia/Shanghai",
    "iso:country":"CN",
    "name:deu_x_preferred":[
        "Sanli"
    ],
    "name:zho_x_preferred":[
        "\u4e09\u91cc"
    ],
    "wof:name":"Sanli",
    "wof:placetype":"locality"
},
  "geometry": {"coordinates":[109.607,24.2742],"type":"Point"}
}