{
  "type": "Feature",
  "properties": {
    "gn:admin1_code":"20.0",
    "gn:asciiname":"Xinlin",
    "gn:country_code":"CN",
    "gn:dem":348,
    "gn:feature_class":"P",
    "gn:feature_code":"PPLA4",
    "gn:name":"Xinlin",
    "gn:population":0,
    "gn:timezone":"Asia/Shanghai",
    "iso:country":"CN",
    "name:und_x_variant":[
        "Xinlin Zhen"
    ],
    "name:zho_x_preferred":[
        "\u65b0\u6797"
    ],
    "name:zho_x_variant":[
        "\u65b0\u6797\u9547"
    ],
    "wof:name":"Xinlin",
    "wof:placetype":"locality"
},
  "geometry": {"coordinates":[122.44069,47.25545],"type":"Point"}
}