{
  "type": "Feature",
  "properties": {
    "gn:admin1_code":"13.0",
    "gn:asciiname":"Haramgai",
    "gn:country_code":"CN",
    "gn:dem":577,
    "gn:feature_class":"P",
    "gn:feature_code":"PPLA4",
    "gn:name":"Haramgai",
    "gn:population":0,
    "gn:timezone":"Asia/Urumqi",
    "iso:country":"CN",
    "name:und_x_variant":[
        "Halamagai",
        "Halamagai Xiang"
    ],
    "name:zho_x_preferred":[
        "\u54c8\u62c9\u739b\u76d6"
    ],
    "name:zho_x_variant":[
        "\u54c8\u62c9\u739b\u76d6\u4e61"
    ],
    "wof:name":"Haramgai",
    "wof:placetype":"locality"
},
  "geometry": {"coordinates":[87.77417,46.65684],"type":"Point"}
}