{
  "type": "Feature",
  "properties": {
    "gn:admin1_code":"29.0",
    "gn:asciiname":"Xianing'an",
    "gn:country_code":"CN",
    "gn:dem":1685,
    "gn:feature_class":"P",
    "gn:feature_code":"PPL",
    "gn:name":"Xianing\u2019an",
    "gn:population":0,
    "gn:timezone":"Asia/Shanghai",
    "iso:country":"CN",
    "name:und_x_variant":[
        "Xianing\u2019an"
    ],
    "name:zho_x_preferred":[
        "\u4e0b\u5b81\u5b89"
    ],
    "wof:name":"Xianing'an",
    "wof:placetype":"locality"
},
  "geometry": {"coordinates":[100.077,23.5628],"type":"Point"}
}