{
  "type": "Feature",
  "properties": {
    "gn:admin1_code":"3.0",
    "gn:asciiname":"Xiejiawu",
    "gn:country_code":"CN",
    "gn:dem":43,
    "gn:feature_class":"P",
    "gn:feature_code":"PPL",
    "gn:name":"Xiejiawu",
    "gn:population":0,
    "gn:timezone":"Asia/Shanghai",
    "iso:country":"CN",
    "name:und_x_variant":[
        "\u87f9\u5bb6\u575e"
    ],
    "wof:name":"Xiejiawu",
    "wof:placetype":"locality"
},
  "geometry": {"coordinates":[116.99213,29.39069000000001],"type":"Point"}
}