{
  "type": "Feature",
  "properties": {
    "gn:admin1_code":"19.0",
    "gn:asciiname":"Dayushuxia",
    "gn:country_code":"CN",
    "gn:dem":292,
    "gn:feature_class":"P",
    "gn:feature_code":"PPL",
    "gn:name":"Dayushuxia",
    "gn:population":0,
    "gn:timezone":"Asia/Shanghai",
    "iso:country":"CN",
    "name:und_x_variant":[
        "\u5927\u6986\u6811\u4e0b"
    ],
    "wof:name":"Dayushuxia",
    "wof:placetype":"locality"
},
  "geometry": {"coordinates":[123.477,40.9565],"type":"Point"}
}