{
  "type": "Feature",
  "properties": {
    "gn:admin1_code":"08",
    "gn:asciiname":"Hongfeng Linchang",
    "gn:country_code":"CN",
    "gn:dem":704,
    "gn:feature_class":"P",
    "gn:feature_code":"PPLF",
    "gn:name":"Hongfeng Linchang",
    "gn:population":0,
    "gn:timezone":"Asia/Shanghai",
    "iso:country":"CN",
    "wof:name":"Hongfeng Linchang",
    "wof:placetype":"locality"
},
  "geometry": {"coordinates":[123.46056000000002,51.48833],"type":"Point"}
}