{
  "type": "Feature",
  "properties": {
    "gn:admin1_code":"4.0",
    "gn:asciiname":"Daxudai",
    "gn:country_code":"CN",
    "gn:dem":4,
    "gn:feature_class":"P",
    "gn:feature_code":"PPL",
    "gn:name":"Daxudai",
    "gn:population":0,
    "gn:timezone":"Asia/Shanghai",
    "iso:country":"CN",
    "name:zho_x_preferred":[
        "\u5927\u5729\u5788"
    ],
    "wof:name":"Daxudai",
    "wof:placetype":"locality"
},
  "geometry": {"coordinates":[120.07729999999999,32.042],"type":"Point"}
}