{
  "type": "Feature",
  "properties": {
    "gn:admin1_code":"18",
    "gn:asciiname":"Xiabeigu",
    "gn:country_code":"CN",
    "gn:dem":2088,
    "gn:feature_class":"P",
    "gn:feature_code":"PPL",
    "gn:name":"Xiabeigu",
    "gn:population":0,
    "gn:timezone":"Asia/Shanghai",
    "iso:country":"CN",
    "name:zho_x_preferred":[
        "\u4e0b\u8d1d\u53e4"
    ],
    "wof:name":"Xiabeigu",
    "wof:placetype":"locality"
},
  "geometry": {"coordinates":[103.91200000000001,26.7609],"type":"Point"}
}