{
  "type": "Feature",
  "properties": {
    "gn:admin1_code":"19.0",
    "gn:asciiname":"Liufenggou",
    "gn:country_code":"CN",
    "gn:dem":85,
    "gn:feature_class":"P",
    "gn:feature_code":"PPL",
    "gn:name":"Liufenggou",
    "gn:population":0,
    "gn:timezone":"Asia/Shanghai",
    "iso:country":"CN",
    "name:und_x_variant":[
        "\u5218\u51af\u6c9f"
    ],
    "wof:name":"Liufenggou",
    "wof:placetype":"locality"
},
  "geometry": {"coordinates":[122.96299999999999,40.9366],"type":"Point"}
}