{
  "type": "Feature",
  "properties": {
    "gn:admin1_code":"32.0",
    "gn:asciiname":"Shichihaofu",
    "gn:country_code":"CN",
    "gn:dem":2360,
    "gn:feature_class":"P",
    "gn:feature_code":"PPL",
    "gn:name":"Shichihaofu",
    "gn:population":0,
    "gn:timezone":"Asia/Shanghai",
    "iso:country":"CN",
    "name:zho_x_preferred":[
        "\u662f\u5403\u597d\u752b"
    ],
    "wof:name":"Shichihaofu",
    "wof:placetype":"locality"
},
  "geometry": {"coordinates":[102.53695,27.49696],"type":"Point"}
}