{
  "type": "Feature",
  "properties": {
    "gn:admin1_code":"8.0",
    "gn:asciiname":"Laolujia",
    "gn:country_code":"CN",
    "gn:dem":173,
    "gn:feature_class":"P",
    "gn:feature_code":"PPL",
    "gn:name":"Laolujia",
    "gn:population":0,
    "gn:timezone":"Asia/Shanghai",
    "iso:country":"CN",
    "name:zho_x_preferred":[
        "\u8001\u82a6\u5bb6"
    ],
    "wof:name":"Laolujia",
    "wof:placetype":"locality"
},
  "geometry": {"coordinates":[127.46383,46.97824],"type":"Point"}
}