{
  "type": "Feature",
  "properties": {
    "gn:admin1_code":"30.0",
    "gn:asciiname":"Lianba",
    "gn:country_code":"CN",
    "gn:dem":112,
    "gn:feature_class":"P",
    "gn:feature_code":"PPL",
    "gn:name":"Lianba",
    "gn:population":0,
    "gn:timezone":"Asia/Shanghai",
    "iso:country":"CN",
    "name:zho_x_preferred":[
        "Lianba"
    ],
    "name:zho_x_variant":[
        "\u8054\u575d"
    ],
    "wof:name":"Lianba",
    "wof:placetype":"locality"
},
  "geometry": {"coordinates":[112.40889,24.56028],"type":"Point"}
}