{
  "type": "Feature",
  "properties": {
    "gn:admin1_code":"11.0",
    "gn:asciiname":"Gaojiapu",
    "gn:country_code":"CN",
    "gn:dem":33,
    "gn:feature_class":"P",
    "gn:feature_code":"PPL",
    "gn:name":"Gaojiapu",
    "gn:population":0,
    "gn:timezone":"Asia/Shanghai",
    "iso:country":"CN",
    "name:zho_x_preferred":[
        "Gaojiapu"
    ],
    "name:zho_x_variant":[
        "\u9ad8\u5bb6\u94fa"
    ],
    "wof:name":"Gaojiapu",
    "wof:placetype":"locality"
},
  "geometry": {"coordinates":[111.91973,29.13302],"type":"Point"}
}