{
  "type": "Feature",
  "properties": {
    "gn:admin1_code":"26.0",
    "gn:asciiname":"Baitangtangcun",
    "gn:country_code":"CN",
    "gn:dem":1639,
    "gn:feature_class":"P",
    "gn:feature_code":"PPL",
    "gn:name":"Baitangtangcun",
    "gn:population":0,
    "gn:timezone":"Asia/Shanghai",
    "iso:country":"CN",
    "name:zho_x_preferred":[
        "\u767d\u5858\u5858\u6751"
    ],
    "wof:name":"Baitangtangcun",
    "wof:placetype":"locality"
},
  "geometry": {"coordinates":[107.33905,37.22963],"type":"Point"}
}