{
  "type": "Feature",
  "properties": {
    "gn:admin1_code":"5.0",
    "gn:asciiname":"Xiasiping",
    "gn:country_code":"CN",
    "gn:dem":463,
    "gn:feature_class":"P",
    "gn:feature_code":"PPL",
    "gn:name":"Xiasiping",
    "gn:population":0,
    "gn:timezone":"Asia/Shanghai",
    "iso:country":"CN",
    "name:und_x_variant":[
        "\u4e0b\u56db\u5e73"
    ],
    "wof:name":"Xiasiping",
    "wof:placetype":"locality"
},
  "geometry": {"coordinates":[126.18307,41.82142],"type":"Point"}
}