{
  "type": "Feature",
  "properties": {
    "gn:admin1_code":"11.0",
    "gn:asciiname":"Yejia",
    "gn:country_code":"CN",
    "gn:dem":60,
    "gn:feature_class":"P",
    "gn:feature_code":"PPL",
    "gn:name":"Yejia",
    "gn:population":0,
    "gn:timezone":"Asia/Shanghai",
    "iso:country":"CN",
    "name:zho_x_preferred":[
        "\u53f6\u5bb6"
    ],
    "wof:name":"Yejia",
    "wof:placetype":"locality"
},
  "geometry": {"coordinates":[111.95050000000001,28.61612],"type":"Point"}
}