{
  "type": "Feature",
  "properties": {
    "gn:admin1_code":"25",
    "gn:asciiname":"Houhujiabu",
    "gn:country_code":"CN",
    "gn:dem":109,
    "gn:feature_class":"P",
    "gn:feature_code":"PPL",
    "gn:name":"Houhujiabu",
    "gn:population":0,
    "gn:timezone":"Asia/Shanghai",
    "iso:country":"CN",
    "name:zho_x_preferred":[
        "\u540e\u80e1\u5bb6\u57e0"
    ],
    "wof:name":"Houhujiabu",
    "wof:placetype":"locality"
},
  "geometry": {"coordinates":[118.503,35.5412],"type":"Point"}
}