{
  "type": "Feature",
  "properties": {
    "gn:admin1_code":"11.0",
    "gn:asciiname":"Sanlong",
    "gn:country_code":"CN",
    "gn:dem":446,
    "gn:feature_class":"P",
    "gn:feature_code":"PPL",
    "gn:name":"Sanlong",
    "gn:population":0,
    "gn:timezone":"Asia/Shanghai",
    "iso:country":"CN",
    "name:zho_x_preferred":[
        "\u4e09\u9f99"
    ],
    "wof:name":"Sanlong",
    "wof:placetype":"locality"
},
  "geometry": {"coordinates":[111.06489000000001,28.24883],"type":"Point"}
}