{
  "type": "Feature",
  "properties": {
    "gn:admin1_code":"29.0",
    "gn:asciiname":"Yongmaocun",
    "gn:country_code":"CN",
    "gn:dem":2327,
    "gn:feature_class":"P",
    "gn:feature_code":"PPL",
    "gn:name":"Yongmaocun",
    "gn:population":0,
    "gn:timezone":"Asia/Shanghai",
    "iso:country":"CN",
    "name:zho_x_preferred":[
        "\u6c38\u8302\u6751"
    ],
    "wof:name":"Yongmaocun",
    "wof:placetype":"locality"
},
  "geometry": {"coordinates":[102.43600000000001,26.1465],"type":"Point"}
}