{
  "type": "Feature",
  "properties": {
    "gn:admin1_code":"1.0",
    "gn:asciiname":"Tieshan",
    "gn:country_code":"CN",
    "gn:dem":254,
    "gn:feature_class":"P",
    "gn:feature_code":"PPL",
    "gn:name":"Tieshan",
    "gn:population":0,
    "gn:timezone":"Asia/Shanghai",
    "iso:country":"CN",
    "name:zho_x_preferred":[
        "\u94c1\u5c71"
    ],
    "wof:name":"Tieshan",
    "wof:placetype":"locality"
},
  "geometry": {"coordinates":[118.04412000000001,30.86079],"type":"Point"}
}