{
  "type": "Feature",
  "properties": {
    "gn:admin1_code":"21.0",
    "gn:asciiname":"Lijia Xinzhuang",
    "gn:country_code":"CN",
    "gn:dem":1587,
    "gn:feature_class":"P",
    "gn:feature_code":"PPL",
    "gn:name":"Lijia Xinzhuang",
    "gn:population":0,
    "gn:timezone":"Asia/Shanghai",
    "iso:country":"CN",
    "name:zho_x_preferred":[
        "\u674e\u5bb6\u65b0\u5e84"
    ],
    "wof:name":"Lijia Xinzhuang",
    "wof:placetype":"locality"
},
  "geometry": {"coordinates":[106.60899999999999,37.255],"type":"Point"}
}