{
  "type": "Feature",
  "properties": {
    "gn:admin1_code":"13.0",
    "gn:asciiname":"Tiekelike",
    "gn:country_code":"CN",
    "gn:dem":1337,
    "gn:feature_class":"P",
    "gn:feature_code":"PPL",
    "gn:name":"Tiekelike",
    "gn:population":0,
    "gn:timezone":"Asia/Shanghai",
    "iso:country":"CN",
    "name:zho_x_preferred":[
        "\u94c1\u514b\u91cc\u514b"
    ],
    "wof:name":"Tiekelike",
    "wof:placetype":"locality"
},
  "geometry": {"coordinates":[79.15567,37.35275],"type":"Point"}
}