{
  "type": "Feature",
  "properties": {
    "gn:admin1_code":"32.0",
    "gn:asciiname":"Mingzhi Xicun",
    "gn:country_code":"CN",
    "gn:dem":3478,
    "gn:feature_class":"P",
    "gn:feature_code":"PPL",
    "gn:name":"Mingzhi Xicun",
    "gn:population":0,
    "gn:timezone":"Asia/Shanghai",
    "iso:country":"CN",
    "name:zho_x_preferred":[
        "\u660e\u4e4b\u897f\u6751"
    ],
    "wof:name":"Mingzhi Xicun",
    "wof:placetype":"locality"
},
  "geometry": {"coordinates":[101.494,30.106],"type":"Point"}
}