{
  "type": "Feature",
  "properties": {
    "gn:admin1_code":"14",
    "gn:asciiname":"Chuxi",
    "gn:country_code":"CN",
    "gn:dem":3978,
    "gn:feature_class":"P",
    "gn:feature_code":"PPL",
    "gn:name":"Chuxi",
    "gn:population":0,
    "gn:timezone":"Asia/Urumqi",
    "iso:country":"CN",
    "name:zho_x_preferred":[
        "\u9664\u897f"
    ],
    "wof:name":"Chuxi",
    "wof:placetype":"locality"
},
  "geometry": {"coordinates":[89.54799999999999,29.2884],"type":"Point"}
}