{
  "type": "Feature",
  "properties": {
    "gn:admin1_code":"2",
    "gn:asciiname":"Xiayang",
    "gn:country_code":"CN",
    "gn:dem":638,
    "gn:feature_class":"P",
    "gn:feature_code":"PPL",
    "gn:name":"Xiayang",
    "gn:population":0,
    "gn:timezone":"Asia/Shanghai",
    "iso:country":"CN",
    "name:zho_x_preferred":[
        "\u4e0b\u579f"
    ],
    "wof:name":"Xiayang",
    "wof:placetype":"locality"
},
  "geometry": {"coordinates":[119.98778,27.41139],"type":"Point"}
}