{
  "type": "Feature",
  "properties": {
    "gn:admin1_code":"33.0",
    "gn:asciiname":"Renhemen",
    "gn:country_code":"CN",
    "gn:dem":308,
    "gn:feature_class":"P",
    "gn:feature_code":"PPL",
    "gn:name":"Renhemen",
    "gn:population":0,
    "gn:timezone":"Asia/Shanghai",
    "iso:country":"CN",
    "name:zho_x_preferred":[
        "\u4eba\u548c\u95e8"
    ],
    "wof:name":"Renhemen",
    "wof:placetype":"locality"
},
  "geometry": {"coordinates":[106.31999999999999,29.6331],"type":"Point"}
}