{
  "type": "Feature",
  "properties": {
    "gn:admin1_code":"29",
    "gn:asciiname":"Yangjie",
    "gn:country_code":"CN",
    "gn:dem":1368,
    "gn:feature_class":"P",
    "gn:feature_code":"PPL",
    "gn:name":"Yangjie",
    "gn:population":0,
    "gn:timezone":"Asia/Shanghai",
    "iso:country":"CN",
    "name:zho_x_preferred":[
        "\u7f8a\u8857"
    ],
    "wof:name":"Yangjie",
    "wof:placetype":"locality"
},
  "geometry": {"coordinates":[103.44929999999999,24.22563],"type":"Point"}
}