{
  "type": "Feature",
  "properties": {
    "gn:admin1_code":"29.0",
    "gn:asciiname":"Xiahuyu",
    "gn:country_code":"CN",
    "gn:dem":1133,
    "gn:feature_class":"P",
    "gn:feature_code":"PPL",
    "gn:name":"Xiahuyu",
    "gn:population":0,
    "gn:timezone":"Asia/Shanghai",
    "iso:country":"CN",
    "name:zho_x_preferred":[
        "\u4e0b\u6237\u80b2"
    ],
    "wof:name":"Xiahuyu",
    "wof:placetype":"locality"
},
  "geometry": {"coordinates":[98.8672,23.8292],"type":"Point"}
}