{
  "type": "Feature",
  "properties": {
    "gn:admin1_code":"4.0",
    "gn:asciiname":"Zhuxu",
    "gn:country_code":"CN",
    "gn:dem":9,
    "gn:feature_class":"P",
    "gn:feature_code":"PPL",
    "gn:name":"Zhuxu",
    "gn:population":0,
    "gn:timezone":"Asia/Shanghai",
    "iso:country":"CN",
    "name:zho_x_preferred":[
        "Zhuxu"
    ],
    "name:zho_x_variant":[
        "\u6731\u5729"
    ],
    "wof:name":"Zhuxu",
    "wof:placetype":"locality"
},
  "geometry": {"coordinates":[119.12904,33.58136],"type":"Point"}
}