{
  "type": "Feature",
  "properties": {
    "gn:admin1_code":"30.0",
    "gn:asciiname":"Zhongdong",
    "gn:country_code":"CN",
    "gn:dem":384,
    "gn:feature_class":"P",
    "gn:feature_code":"PPL",
    "gn:name":"Zhongdong",
    "gn:population":0,
    "gn:timezone":"Asia/Shanghai",
    "iso:country":"CN",
    "name:zho_x_preferred":[
        "Zhongdong"
    ],
    "name:zho_x_variant":[
        "\u4e2d\u6d1e"
    ],
    "wof:name":"Zhongdong",
    "wof:placetype":"locality"
},
  "geometry": {"coordinates":[114.22481999999999,24.60639],"type":"Point"}
}