{
  "type": "Feature",
  "properties": {
    "iso:country":"CN",
    "name:ceb_x_preferred":[
        "Minfeng Xian"
    ],
    "name:deu_x_preferred":[
        "Niya"
    ],
    "name:eng_x_preferred":[
        "Minfeng County"
    ],
    "name:fas_x_preferred":[
        "\u0634\u0647\u0631\u0633\u062a\u0627\u0646 \u0645\u06cc\u0646\u0641\u0646\u06af"
    ],
    "name:gan_x_preferred":[
        "\u6c11\u4e30\u53bf"
    ],
    "name:jpn_x_preferred":[
        "\u30cb\u30e4\u770c"
    ],
    "name:kor_x_preferred":[
        "\ubbfc\ud391\ud604"
    ],
    "name:nan_x_preferred":[
        "Niya-ko\u0101n"
    ],
    "name:nld_x_preferred":[
        "Niya"
    ],
    "name:nob_x_preferred":[
        "Minfeng"
    ],
    "name:rus_x_preferred":[
        "\u041d\u0438\u044f"
    ],
    "name:swe_x_preferred":[
        "Niye"
    ],
    "name:tur_x_preferred":[
        "Niya \u0130l\u00e7esi"
    ],
    "name:uig_x_preferred":[
        "\u0646\u0649\u064a\u06d5 \u0646\u0627\u06be\u0649\u064a\u0649\u0633\u0649"
    ],
    "name:ukr_x_preferred":[
        "\u041c\u0456\u043d\u044c\u0444\u0438\u043d"
    ],
    "name:urd_x_preferred":[
        "\u0645\u0646\u0641\u06cc\u0646\u06af \u06a9\u0627\u0624\u0646\u0679\u06cc"
    ],
    "name:vie_x_preferred":[
        "D\u00e2n Phong"
    ],
    "name:wuu_x_preferred":[
        "\u6c11\u4e30\u53bf"
    ],
    "name:zho_x_preferred":[
        "\u6c11\u4e30\u53bf"
    ],
    "qs:name":"\u6c11\u4e30\u53bf",
    "qs:name_adm0":"\u4e2d\u570b",
    "qs:name_adm1":"\u65b0\u7586\u7ef4\u543e\u5c14\u81ea\u6cbb\u533a",
    "qs:photos":568,
    "qs:photos_1k":115,
    "qs:photos_9k":3,
    "qs:photos_9r":5,
    "qs:photos_all":568,
    "qs:photos_sr":8,
    "qs:placetype":"LocalAdmin",
    "qs:pop_sr":"0",
    "wd:wordcount":91,
    "wof:name":"\u6c11\u4e30\u53bf",
    "wof:placetype":"localadmin"
},
  "geometry": {"coordinates":[82.688169,37.067848],"type":"Point"}
}