{
  "type": "Feature",
  "properties": {
    "iso:country":"CN",
    "qs:name":"\u6c11\u4e30\u53bf",
    "qs:name_adm0":"\u4e2d\u570b",
    "qs:name_adm1":"\u65b0\u7586\u7ef4\u543e\u5c14\u81ea\u6cbb\u533a",
    "qs:photos":568,
    "qs:photos_1k":115,
    "qs:photos_9k":3,
    "qs:photos_9r":5,
    "qs:photos_all":568,
    "qs:photos_sr":8,
    "qs:placetype":"LocalAdmin",
    "qs:pop_sr":"0",
    "wd:wordcount":91,
    "wof:name":"\u6c11\u4e30\u53bf",
    "wof:placetype":"localadmin"
},
  "geometry": {"coordinates":[82.688169,37.067848],"type":"Point"}
}