{
  "type": "Feature",
  "properties": {
    "gn:admin1_code":"7.0",
    "gn:asciiname":"Xianglin",
    "gn:country_code":"CN",
    "gn:dem":588,
    "gn:feature_class":"P",
    "gn:feature_code":"PPL",
    "gn:name":"Xianglin",
    "gn:population":0,
    "gn:timezone":"Asia/Shanghai",
    "iso:country":"CN",
    "name:zho_x_preferred":[
        "\u9999\u6797"
    ],
    "wof:name":"Xianglin",
    "wof:placetype":"locality"
},
  "geometry": {"coordinates":[119.16544,26.64107000000001],"type":"Point"}
}