{
  "type": "Feature",
  "properties": {
    "gn:admin1_code":"8.0",
    "gn:asciiname":"Huashuzhangzi",
    "gn:country_code":"CN",
    "gn:dem":676,
    "gn:feature_class":"P",
    "gn:feature_code":"PPL",
    "gn:name":"Huashuzhangzi",
    "gn:population":0,
    "gn:timezone":"Asia/Shanghai",
    "iso:country":"CN",
    "name:und_x_variant":[
        "\u6866\u6811\u6756\u5b50"
    ],
    "wof:name":"Huashuzhangzi",
    "wof:placetype":"locality"
},
  "geometry": {"coordinates":[131.12045000000001,43.45495],"type":"Point"}
}