{
  "type": "Feature",
  "properties": {
    "gn:admin1_code":"32.0",
    "gn:asciiname":"Dahuanglianshu",
    "gn:country_code":"CN",
    "gn:dem":478,
    "gn:feature_class":"P",
    "gn:feature_code":"PPL",
    "gn:name":"Dahuanglianshu",
    "gn:population":0,
    "gn:timezone":"Asia/Shanghai",
    "iso:country":"CN",
    "name:zho_x_preferred":[
        "\u5927\u9ec4\u83b2\u6811"
    ],
    "wof:name":"Dahuanglianshu",
    "wof:placetype":"locality"
},
  "geometry": {"coordinates":[104.459,30.5676],"type":"Point"}
}