{
  "type": "Feature",
  "properties": {
    "gn:admin1_code":"09",
    "gn:asciiname":"Qinghua",
    "gn:cc2":"CN",
    "gn:country_code":"CN",
    "gn:dem":123,
    "gn:feature_class":"P",
    "gn:feature_code":"PPL",
    "gn:name":"Qinghua",
    "gn:population":0,
    "gn:timezone":"Asia/Shanghai",
    "iso:country":"CN",
    "name:und_x_variant":[
        "Ch\u2019ing-hua-chen",
        "Ch\u2019ing-hua",
        "Qinghua"
    ],
    "wof:name":"Qinghua",
    "wof:placetype":"locality"
},
  "geometry": {"coordinates":[112.3175,32.88472],"type":"Point"}
}