{
  "type": "Feature",
  "properties": {
    "gn:admin1_code":"33.0",
    "gn:asciiname":"Nanjiang",
    "gn:country_code":"CN",
    "gn:dem":698,
    "gn:feature_class":"P",
    "gn:feature_code":"PPL",
    "gn:name":"Nanjiang",
    "gn:population":0,
    "gn:timezone":"Asia/Shanghai",
    "iso:country":"CN",
    "name:zho_x_preferred":[
        "\u5357\u6c5f"
    ],
    "wof:name":"Nanjiang",
    "wof:placetype":"locality"
},
  "geometry": {"coordinates":[107.90694000000001,29.84084],"type":"Point"}
}