{
  "type": "Feature",
  "properties": {
    "gn:admin1_code":"8.0",
    "gn:asciiname":"Gaojia Weizi",
    "gn:country_code":"CN",
    "gn:dem":298,
    "gn:feature_class":"P",
    "gn:feature_code":"PPLF",
    "gn:name":"Gaojia Weizi",
    "gn:population":0,
    "gn:timezone":"Asia/Shanghai",
    "iso:country":"CN",
    "name:zho_x_preferred":[
        "\u9ad8\u5bb6\u56f4\u5b50"
    ],
    "wof:name":"Gaojia Weizi",
    "wof:placetype":"locality"
},
  "geometry": {"coordinates":[126.40675,48.03872],"type":"Point"}
}