{
  "type": "Feature",
  "properties": {
    "gn:admin1_code":"10",
    "gn:asciiname":"Xiangluzhai",
    "gn:country_code":"CN",
    "gn:dem":418,
    "gn:feature_class":"P",
    "gn:feature_code":"PPL",
    "gn:name":"Xiangluzhai",
    "gn:population":0,
    "gn:timezone":"Asia/Shanghai",
    "iso:country":"CN",
    "name:zho_x_preferred":[
        "\u9999\u7089\u5be8"
    ],
    "wof:name":"Xiangluzhai",
    "wof:placetype":"locality"
},
  "geometry": {"coordinates":[114.017,37.1321],"type":"Point"}
}