{
  "type": "Feature",
  "properties": {
    "gn:admin1_code":"2.0",
    "gn:asciiname":"Zhijiang",
    "gn:country_code":"CN",
    "gn:dem":422,
    "gn:feature_class":"P",
    "gn:feature_code":"PPL",
    "gn:name":"Zhijiang",
    "gn:population":0,
    "gn:timezone":"Asia/Shanghai",
    "iso:country":"CN",
    "name:ceb_x_preferred":[
        "Zhijiang"
    ],
    "name:deu_x_preferred":[
        "Zhijiang"
    ],
    "name:eus_x_preferred":[
        "Zhijiang"
    ],
    "name:fra_x_preferred":[
        "Zhijiang"
    ],
    "name:nor_x_preferred":[
        "Zhijiang"
    ],
    "name:swe_x_preferred":[
        "Zhijiang"
    ],
    "name:zho_x_preferred":[
        "\u76f4\u6c5f"
    ],
    "wof:name":"Zhijiang",
    "wof:placetype":"locality"
},
  "geometry": {"coordinates":[120.89181000000001,28.55884],"type":"Point"}
}