{
  "type": "Feature",
  "properties": {
    "gn:admin1_code":"2.0",
    "gn:asciiname":"Zhijiang",
    "gn:country_code":"CN",
    "gn:dem":422,
    "gn:feature_class":"P",
    "gn:feature_code":"PPL",
    "gn:name":"Zhijiang",
    "gn:population":0,
    "gn:timezone":"Asia/Shanghai",
    "iso:country":"CN",
    "name:ara_x_preferred":[
        "\u062a\u0634\u064a\u062c\u064a\u0627\u0646\u063a"
    ],
    "name:ben_x_preferred":[
        "\u099d\u09bf\u099c\u09bf\u09df\u09be\u0982"
    ],
    "name:ceb_x_preferred":[
        "Zhijiang"
    ],
    "name:deu_x_preferred":[
        "Zhijiang"
    ],
    "name:ell_x_preferred":[
        "\u0396\u03b9\u03c4\u03b6\u03b9\u03ac\u03bd\u03b3\u03ba"
    ],
    "name:eus_x_preferred":[
        "Zhijiang"
    ],
    "name:fas_x_preferred":[
        "\u0698\u06cc\u062c\u06cc\u0627\u0646\u06af"
    ],
    "name:fra_x_preferred":[
        "Zhejiang"
    ],
    "name:fra_x_variant":[
        "Zhijiang"
    ],
    "name:heb_x_preferred":[
        "\u05d6'\u05d9\u05d6'\u05d9\u05d0\u05e0\u05d2"
    ],
    "name:hin_x_preferred":[
        "\u091c\u093f\u091c\u093c\u093f\u092f\u093e\u0902\u0917"
    ],
    "name:hun_x_preferred":[
        "Zhijiang"
    ],
    "name:ind_x_preferred":[
        "Zhijiang"
    ],
    "name:ita_x_preferred":[
        "Zhijiang"
    ],
    "name:kor_x_preferred":[
        "\uc9c0\uc7a5"
    ],
    "name:nld_x_preferred":[
        "Zhijiang"
    ],
    "name:nor_x_preferred":[
        "Zhijiang"
    ],
    "name:pol_x_preferred":[
        "Zhijiang"
    ],
    "name:por_x_preferred":[
        "Zhijiang"
    ],
    "name:rus_x_preferred":[
        "\u0427\u0436\u044d\u0446\u0437\u044f\u043d"
    ],
    "name:spa_x_preferred":[
        "Zhijiang"
    ],
    "name:swe_x_preferred":[
        "Zhijiang"
    ],
    "name:tur_x_preferred":[
        "Zhijiang"
    ],
    "name:ukr_x_preferred":[
        "\u0427\u0436\u0438\u0446\u0437\u044f\u043d"
    ],
    "name:urd_x_preferred":[
        "\u0632\u06cc\u062c\u06cc\u0627\u0646\u06af"
    ],
    "name:vie_x_preferred":[
        "Chi Giang"
    ],
    "name:zho_x_preferred":[
        "\u76f4\u6c5f"
    ],
    "wof:name":"Zhijiang",
    "wof:placetype":"locality"
},
  "geometry": {"coordinates":[120.89181000000001,28.55884],"type":"Point"}
}