{
  "type": "Feature",
  "properties": {
    "gn:admin1_code":"9.0",
    "gn:asciiname":"Xudazhuang",
    "gn:country_code":"CN",
    "gn:dem":43,
    "gn:feature_class":"P",
    "gn:feature_code":"PPL",
    "gn:name":"Xudazhuang",
    "gn:population":0,
    "gn:timezone":"Asia/Shanghai",
    "iso:country":"CN",
    "name:zho_x_preferred":[
        "\u5f90\u5927\u5e84"
    ],
    "wof:name":"Xudazhuang",
    "wof:placetype":"locality"
},
  "geometry": {"coordinates":[114.91723,32.63664],"type":"Point"}
}