{
  "type": "Feature",
  "properties": {
    "gn:admin1_code":"5.0",
    "gn:asciiname":"Dingjia Wopeng",
    "gn:country_code":"CN",
    "gn:dem":292,
    "gn:feature_class":"P",
    "gn:feature_code":"PPL",
    "gn:name":"Dingjia Wopeng",
    "gn:population":0,
    "gn:timezone":"Asia/Shanghai",
    "iso:country":"CN",
    "name:zho_x_preferred":[
        "\u4e01\u5bb6\u7a9d\u68da"
    ],
    "wof:name":"Dingjia Wopeng",
    "wof:placetype":"locality"
},
  "geometry": {"coordinates":[121.84547999999999,45.73343],"type":"Point"}
}