{
  "type": "Feature",
  "properties": {
    "gn:admin1_code":"15.0",
    "gn:asciiname":"Zhabaliang",
    "gn:country_code":"CN",
    "gn:dem":1097,
    "gn:feature_class":"P",
    "gn:feature_code":"PPL",
    "gn:name":"Zhabaliang",
    "gn:population":0,
    "gn:timezone":"Asia/Urumqi",
    "iso:country":"CN",
    "name:zho_x_preferred":[
        "\u95f8\u575d\u6881"
    ],
    "wof:name":"Zhabaliang",
    "wof:placetype":"locality"
},
  "geometry": {"coordinates":[94.7255,40.2813],"type":"Point"}
}