{
  "type": "Feature",
  "properties": {
    "gn:admin1_code":"10",
    "gn:asciiname":"Liugu",
    "gn:country_code":"CN",
    "gn:dem":59,
    "gn:feature_class":"P",
    "gn:feature_code":"PPL",
    "gn:name":"Liugu",
    "gn:population":0,
    "gn:timezone":"Asia/Shanghai",
    "iso:country":"CN",
    "name:und_x_variant":[
        "Liu-ku",
        "Liugu"
    ],
    "name:zho_x_preferred":[
        "\u5218\u56fa"
    ],
    "wof:name":"Liugu",
    "wof:placetype":"locality"
},
  "geometry": {"coordinates":[114.569,36.8707],"type":"Point"}
}