{
  "type": "Feature",
  "properties": {
    "gn:admin1_code":"11.0",
    "gn:asciiname":"Shentonggang",
    "gn:country_code":"CN",
    "gn:dem":30,
    "gn:feature_class":"P",
    "gn:feature_code":"PPL",
    "gn:name":"Shentonggang",
    "gn:population":0,
    "gn:timezone":"Asia/Shanghai",
    "iso:country":"CN",
    "name:zho_x_preferred":[
        "\u795e\u7ae5\u6e2f"
    ],
    "wof:name":"Shentonggang",
    "wof:placetype":"locality"
},
  "geometry": {"coordinates":[112.42928999999999,29.31859],"type":"Point"}
}