{
  "type": "Feature",
  "properties": {
    "gn:admin1_code":"8.0",
    "gn:asciiname":"Hulin Badui",
    "gn:country_code":"CN",
    "gn:dem":330,
    "gn:feature_class":"P",
    "gn:feature_code":"PPLF",
    "gn:name":"Hulin Badui",
    "gn:population":0,
    "gn:timezone":"Asia/Shanghai",
    "iso:country":"CN",
    "name:zho_x_preferred":[
        "\u62a4\u6797\u516b\u961f"
    ],
    "wof:name":"Hulin Badui",
    "wof:placetype":"locality"
},
  "geometry": {"coordinates":[122.61959,47.25817],"type":"Point"}
}