{
  "type": "Feature",
  "properties": {
    "gn:admin1_code":"11",
    "gn:asciiname":"Shiyangxu",
    "gn:country_code":"CN",
    "gn:dem":252,
    "gn:feature_class":"P",
    "gn:feature_code":"PPL",
    "gn:name":"Shiyangxu",
    "gn:population":0,
    "gn:timezone":"Asia/Shanghai",
    "iso:country":"CN",
    "name:und_x_variant":[
        "Shiyang",
        "Shiyangxu"
    ],
    "name:zho_x_preferred":[
        "\u77f3\u7f8a\u5729"
    ],
    "wof:name":"Shiyangxu",
    "wof:placetype":"locality"
},
  "geometry": {"coordinates":[112.23472,25.74861],"type":"Point"}
}