{
  "type": "Feature",
  "properties": {
    "gn:admin1_code":"29.0",
    "gn:asciiname":"Mimao",
    "gn:country_code":"CN",
    "gn:dem":1812,
    "gn:feature_class":"P",
    "gn:feature_code":"PPL",
    "gn:name":"Mimao",
    "gn:population":0,
    "gn:timezone":"Asia/Shanghai",
    "iso:country":"CN",
    "name:und_x_variant":[
        "\u7c73\u8302"
    ],
    "wof:name":"Mimao",
    "wof:placetype":"locality"
},
  "geometry": {"coordinates":[104.45273,26.41247000000001],"type":"Point"}
}