{
  "type": "Feature",
  "properties": {
    "gn:admin1_code":"24.0",
    "gn:asciiname":"Xinsheke",
    "gn:country_code":"CN",
    "gn:dem":1230,
    "gn:feature_class":"P",
    "gn:feature_code":"PPL",
    "gn:name":"Xinsheke",
    "gn:population":0,
    "gn:timezone":"Asia/Shanghai",
    "iso:country":"CN",
    "name:zho_x_preferred":[
        "\u65b0\u820d\u7aa0"
    ],
    "wof:name":"Xinsheke",
    "wof:placetype":"locality"
},
  "geometry": {"coordinates":[111.27347,38.44796],"type":"Point"}
}