{
  "type": "Feature",
  "properties": {
    "gn:admin1_code":"26.0",
    "gn:asciiname":"Niujiayinpo",
    "gn:country_code":"CN",
    "gn:dem":711,
    "gn:feature_class":"P",
    "gn:feature_code":"PPL",
    "gn:name":"Niujiayinpo",
    "gn:population":0,
    "gn:timezone":"Asia/Shanghai",
    "iso:country":"CN",
    "name:zho_x_preferred":[
        "\u725b\u5bb6\u9634\u5761"
    ],
    "wof:name":"Niujiayinpo",
    "wof:placetype":"locality"
},
  "geometry": {"coordinates":[109.77453,32.9882],"type":"Point"}
}