{
  "type": "Feature",
  "properties": {
    "gn:admin1_code":"20.0",
    "gn:asciiname":"Donggong",
    "gn:country_code":"CN",
    "gn:dem":605,
    "gn:feature_class":"P",
    "gn:feature_code":"PPL",
    "gn:name":"Donggong",
    "gn:population":0,
    "gn:timezone":"Asia/Shanghai",
    "iso:country":"CN",
    "name:zho_x_preferred":[
        "\u4e1c\u5bab"
    ],
    "wof:name":"Donggong",
    "wof:placetype":"locality"
},
  "geometry": {"coordinates":[119.03659,49.16443],"type":"Point"}
}