{
  "type": "Feature",
  "properties": {
    "gn:admin1_code":"33.0",
    "gn:asciiname":"Lantian'ao",
    "gn:country_code":"CN",
    "gn:dem":504,
    "gn:feature_class":"P",
    "gn:feature_code":"PPL",
    "gn:name":"Lantian\u2019ao",
    "gn:population":0,
    "gn:timezone":"Asia/Shanghai",
    "iso:country":"CN",
    "name:und_x_variant":[
        "Lantian\u2019ao"
    ],
    "name:zho_x_preferred":[
        "\u6ee5\u7530\u5773"
    ],
    "wof:name":"Lantian'ao",
    "wof:placetype":"locality"
},
  "geometry": {"coordinates":[107.43767,30.01435],"type":"Point"}
}