{
  "type": "Feature",
  "properties": {
    "gn:admin1_code":"16",
    "gn:asciiname":"Lengzhaichong",
    "gn:country_code":"CN",
    "gn:dem":274,
    "gn:feature_class":"P",
    "gn:feature_code":"PPL",
    "gn:name":"Lengzhaichong",
    "gn:population":0,
    "gn:timezone":"Asia/Shanghai",
    "iso:country":"CN",
    "name:zho_x_preferred":[
        "\u51b7\u5be8\u51b2"
    ],
    "wof:name":"Lengzhaichong",
    "wof:placetype":"locality"
},
  "geometry": {"coordinates":[110.334,24.6959],"type":"Point"}
}