{
  "type": "Feature",
  "properties": {
    "gn:admin1_code":"1.0",
    "gn:asciiname":"Taochi",
    "gn:country_code":"CN",
    "gn:dem":27,
    "gn:feature_class":"P",
    "gn:feature_code":"PPL",
    "gn:name":"Taochi",
    "gn:population":0,
    "gn:timezone":"Asia/Shanghai",
    "iso:country":"CN",
    "name:ell_x_preferred":[
        "\u03a4\u03ac\u03bf\u03c7\u03bf\u03b9"
    ],
    "name:kat_x_preferred":[
        "\u10e2\u10d0\u10dd\u10ee\u10d4\u10d1\u10d8"
    ],
    "wof:name":"Taochi",
    "wof:placetype":"locality"
},
  "geometry": {"coordinates":[118.76331999999999,31.58172],"type":"Point"}
}