{
  "type": "Feature",
  "properties": {
    "gn:admin1_code":"11",
    "gn:asciiname":"Lijia",
    "gn:country_code":"CN",
    "gn:dem":293,
    "gn:feature_class":"P",
    "gn:feature_code":"PPL",
    "gn:name":"Lijia",
    "gn:population":0,
    "gn:timezone":"Asia/Shanghai",
    "iso:country":"CN",
    "name:deu_x_preferred":[
        "Lijia"
    ],
    "name:und_x_variant":[
        "\u674e\u5bb6",
        "Lijia"
    ],
    "wof:name":"Lijia",
    "wof:placetype":"locality"
},
  "geometry": {"coordinates":[111.36306,25.67056],"type":"Point"}
}