{
  "type": "Feature",
  "properties": {
    "gn:admin1_code":"15.0",
    "gn:asciiname":"Kaba",
    "gn:country_code":"CN",
    "gn:dem":2198,
    "gn:feature_class":"P",
    "gn:feature_code":"PPLA4",
    "gn:name":"Kaba",
    "gn:population":0,
    "gn:timezone":"Asia/Shanghai",
    "iso:country":"CN",
    "name:ceb_x_preferred":[
        "Kaba"
    ],
    "name:deu_x_preferred":[
        "Kaba"
    ],
    "name:fin_x_preferred":[
        "Kaba"
    ],
    "name:fra_x_preferred":[
        "Kaba"
    ],
    "name:hrv_x_preferred":[
        "Kaba"
    ],
    "name:swe_x_preferred":[
        "Kaba"
    ],
    "name:und_x_variant":[
        "\u5361\u575d"
    ],
    "wof:name":"Kaba",
    "wof:placetype":"locality"
},
  "geometry": {"coordinates":[103.49484,33.98035],"type":"Point"}
}