{
  "type": "Feature",
  "properties": {
    "gn:admin1_code":"14",
    "gn:asciiname":"Zhakang",
    "gn:country_code":"CN",
    "gn:dem":4721,
    "gn:feature_class":"P",
    "gn:feature_code":"PPL",
    "gn:name":"Zhakang",
    "gn:population":0,
    "gn:timezone":"Asia/Urumqi",
    "iso:country":"CN",
    "name:zho_x_preferred":[
        "\u624e\u625b"
    ],
    "wof:name":"Zhakang",
    "wof:placetype":"locality"
},
  "geometry": {"coordinates":[89.2971,30.875],"type":"Point"}
}