{
  "type": "Feature",
  "properties": {
    "gn:admin1_code":"7.0",
    "gn:asciiname":"Shan'ao",
    "gn:country_code":"CN",
    "gn:dem":399,
    "gn:feature_class":"P",
    "gn:feature_code":"PPL",
    "gn:name":"Shan\u2019ao",
    "gn:population":0,
    "gn:timezone":"Asia/Shanghai",
    "iso:country":"CN",
    "name:zho_x_preferred":[
        "\u5c71\u5773"
    ],
    "name:zho_x_variant":[
        "Shan\u2019ao"
    ],
    "wof:name":"Shan'ao",
    "wof:placetype":"locality"
},
  "geometry": {"coordinates":[118.18107000000001,27.9837],"type":"Point"}
}