{
  "type": "Feature",
  "properties": {
    "gn:admin1_code":"6.0",
    "gn:asciiname":"Xigeduo",
    "gn:country_code":"CN",
    "gn:dem":3293,
    "gn:feature_class":"P",
    "gn:feature_code":"PPL",
    "gn:name":"Xigeduo",
    "gn:population":0,
    "gn:timezone":"Asia/Shanghai",
    "iso:country":"CN",
    "name:und_x_variant":[
        "\u897f\u683c\u591a"
    ],
    "wof:name":"Xigeduo",
    "wof:placetype":"locality"
},
  "geometry": {"coordinates":[100.46296,35.59196],"type":"Point"}
}