{
  "type": "Feature",
  "properties": {
    "gn:admin1_code":"18",
    "gn:asciiname":"Xiaoqiaohe",
    "gn:country_code":"CN",
    "gn:dem":1453,
    "gn:feature_class":"P",
    "gn:feature_code":"PPL",
    "gn:name":"Xiaoqiaohe",
    "gn:population":0,
    "gn:timezone":"Asia/Shanghai",
    "iso:country":"CN",
    "name:zho_x_preferred":[
        "\u5c0f\u6865\u6cb3"
    ],
    "wof:name":"Xiaoqiaohe",
    "wof:placetype":"locality"
},
  "geometry": {"coordinates":[105.051,25.3581],"type":"Point"}
}