{
  "type": "Feature",
  "properties": {
    "gn:admin1_code":"29.0",
    "gn:asciiname":"Luohanba",
    "gn:country_code":"CN",
    "gn:dem":1466,
    "gn:feature_class":"P",
    "gn:feature_code":"PPL",
    "gn:name":"Luohanba",
    "gn:population":0,
    "gn:timezone":"Asia/Shanghai",
    "iso:country":"CN",
    "name:zho_x_preferred":[
        "\u7f57\u6c49\u575d"
    ],
    "wof:name":"Luohanba",
    "wof:placetype":"locality"
},
  "geometry": {"coordinates":[104.006,28.0864],"type":"Point"}
}