{
  "type": "Feature",
  "properties": {
    "gn:admin1_code":"19.0",
    "gn:asciiname":"Dishuilazicun",
    "gn:country_code":"CN",
    "gn:dem":329,
    "gn:feature_class":"P",
    "gn:feature_code":"PPL",
    "gn:name":"Dishuilazicun",
    "gn:population":0,
    "gn:timezone":"Asia/Shanghai",
    "iso:country":"CN",
    "name:zho_x_preferred":[
        "\u6ef4\u6c34\u782c\u5b50\u6751"
    ],
    "wof:name":"Dishuilazicun",
    "wof:placetype":"locality"
},
  "geometry": {"coordinates":[125.202,41.0674],"type":"Point"}
}