{
  "type": "Feature",
  "properties": {
    "gn:admin1_code":"16.0",
    "gn:asciiname":"Lecai",
    "gn:country_code":"CN",
    "gn:dem":92,
    "gn:feature_class":"P",
    "gn:feature_code":"PPL",
    "gn:name":"Lecai",
    "gn:population":0,
    "gn:timezone":"Asia/Shanghai",
    "iso:country":"CN",
    "name:zho_x_preferred":[
        "\u52d2\u83dc"
    ],
    "wof:name":"Lecai",
    "wof:placetype":"locality"
},
  "geometry": {"coordinates":[108.94,22.7145],"type":"Point"}
}