{
  "type": "Feature",
  "properties": {
    "gn:admin1_code":"7.0",
    "gn:asciiname":"Tianxibu",
    "gn:country_code":"CN",
    "gn:dem":251,
    "gn:feature_class":"P",
    "gn:feature_code":"PPL",
    "gn:name":"Tianxibu",
    "gn:population":0,
    "gn:timezone":"Asia/Shanghai",
    "iso:country":"CN",
    "name:zho_x_preferred":[
        "\u7530\u6eaa\u5e03"
    ],
    "wof:name":"Tianxibu",
    "wof:placetype":"locality"
},
  "geometry": {"coordinates":[117.92915000000001,27.08796],"type":"Point"}
}