{
  "type": "Feature",
  "properties": {
    "gn:admin1_code":"15.0",
    "gn:asciiname":"Gaolingdun",
    "gn:country_code":"CN",
    "gn:dem":2660,
    "gn:feature_class":"P",
    "gn:feature_code":"PPL",
    "gn:name":"Gaolingdun",
    "gn:population":0,
    "gn:timezone":"Asia/Shanghai",
    "iso:country":"CN",
    "name:zho_x_preferred":[
        "\u9ad8\u5cad\u58a9"
    ],
    "wof:name":"Gaolingdun",
    "wof:placetype":"locality"
},
  "geometry": {"coordinates":[103.55800000000001,37.1551],"type":"Point"}
}