{
  "type": "Feature",
  "properties": {
    "gn:admin1_code":"12.0",
    "gn:asciiname":"Shentuo",
    "gn:country_code":"CN",
    "gn:dem":894,
    "gn:feature_class":"P",
    "gn:feature_code":"PPL",
    "gn:name":"Shentuo",
    "gn:population":0,
    "gn:timezone":"Asia/Shanghai",
    "iso:country":"CN",
    "name:zho_x_preferred":[
        "Shentuo"
    ],
    "name:zho_x_variant":[
        "\u6df1\u5768"
    ],
    "wof:name":"Shentuo",
    "wof:placetype":"locality"
},
  "geometry": {"coordinates":[109.21525,29.5943],"type":"Point"}
}