{
  "type": "Feature",
  "properties": {
    "gn:admin1_code":"7.0",
    "gn:asciiname":"Luoyang",
    "gn:country_code":"CN",
    "gn:dem":936,
    "gn:feature_class":"P",
    "gn:feature_code":"PPL",
    "gn:name":"Luoyang",
    "gn:population":0,
    "gn:timezone":"Asia/Shanghai",
    "iso:country":"CN",
    "name:zho_x_preferred":[
        "Luoyang"
    ],
    "name:zho_x_variant":[
        "\u7f57\u6d0b"
    ],
    "wof:name":"Luoyang",
    "wof:placetype":"locality"
},
  "geometry": {"coordinates":[118.83523999999998,26.44538],"type":"Point"}
}