{
  "type": "Feature",
  "properties": {
    "gn:admin1_code":"12.0",
    "gn:asciiname":"Zhongfeng",
    "gn:country_code":"CN",
    "gn:dem":491,
    "gn:feature_class":"P",
    "gn:feature_code":"PPLA4",
    "gn:name":"Zhongfeng",
    "gn:population":0,
    "gn:timezone":"Asia/Shanghai",
    "iso:country":"CN",
    "name:und_x_variant":[
        "Chung-feng",
        "Zhongfeng",
        "Zhongfeng Zhen",
        "\u4e2d\u5cf0\u9547"
    ],
    "name:zho_x_preferred":[
        "\u4e2d\u5cf0"
    ],
    "wof:name":"Zhongfeng",
    "wof:placetype":"locality"
},
  "geometry": {"coordinates":[109.64027,32.32358],"type":"Point"}
}