{
  "type": "Feature",
  "properties": {
    "gn:admin1_code":"19.0",
    "gn:asciiname":"Louzishancun",
    "gn:country_code":"CN",
    "gn:dem":268,
    "gn:feature_class":"P",
    "gn:feature_code":"PPL",
    "gn:name":"Louzishancun",
    "gn:population":0,
    "gn:timezone":"Asia/Shanghai",
    "iso:country":"CN",
    "name:zho_x_preferred":[
        "\u697c\u5b50\u5c71\u6751"
    ],
    "wof:name":"Louzishancun",
    "wof:placetype":"locality"
},
  "geometry": {"coordinates":[124.279,40.8303],"type":"Point"}
}