{
  "type": "Feature",
  "properties": {
    "gn:admin1_code":"32.0",
    "gn:asciiname":"Yejiuda",
    "gn:country_code":"CN",
    "gn:dem":3956,
    "gn:feature_class":"P",
    "gn:feature_code":"PPL",
    "gn:name":"Yejiuda",
    "gn:population":0,
    "gn:timezone":"Asia/Shanghai",
    "iso:country":"CN",
    "name:zho_x_preferred":[
        "\u91ce\u7a76\u8fbe"
    ],
    "wof:name":"Yejiuda",
    "wof:placetype":"locality"
},
  "geometry": {"coordinates":[98.53740000000001,32.1498],"type":"Point"}
}