{
  "type": "Feature",
  "properties": {
    "gn:admin1_code":"19.0",
    "gn:asciiname":"Yaogaojiacun",
    "gn:country_code":"CN",
    "gn:dem":92,
    "gn:feature_class":"P",
    "gn:feature_code":"PPL",
    "gn:name":"Yaogaojiacun",
    "gn:population":0,
    "gn:timezone":"Asia/Shanghai",
    "iso:country":"CN",
    "name:zho_x_preferred":[
        "\u8170\u9ad8\u5bb6\u6751"
    ],
    "wof:name":"Yaogaojiacun",
    "wof:placetype":"locality"
},
  "geometry": {"coordinates":[122.48999999999999,42.4264],"type":"Point"}
}