{
  "type": "Feature",
  "properties": {
    "gn:admin1_code":"4.0",
    "gn:asciiname":"Yangweicun",
    "gn:country_code":"CN",
    "gn:dem":2,
    "gn:feature_class":"P",
    "gn:feature_code":"PPL",
    "gn:name":"Yangweicun",
    "gn:population":0,
    "gn:timezone":"Asia/Shanghai",
    "iso:country":"CN",
    "name:zho_x_preferred":[
        "\u6768\u97e6\u6751"
    ],
    "wof:name":"Yangweicun",
    "wof:placetype":"locality"
},
  "geometry": {"coordinates":[120.14364999999999,33.27509000000001],"type":"Point"}
}