{
  "type": "Feature",
  "properties": {
    "gn:admin1_code":"6.0",
    "gn:asciiname":"Amen Zhangsang",
    "gn:country_code":"CN",
    "gn:dem":3446,
    "gn:feature_class":"P",
    "gn:feature_code":"PPL",
    "gn:name":"Amen Zhangsang",
    "gn:population":0,
    "gn:timezone":"Asia/Shanghai",
    "iso:country":"CN",
    "name:zho_x_preferred":[
        "\u963f\u95e8\u7ae0\u6851"
    ],
    "wof:name":"Amen Zhangsang",
    "wof:placetype":"locality"
},
  "geometry": {"coordinates":[100.98577,32.66842],"type":"Point"}
}