{
  "type": "Feature",
  "properties": {
    "gn:admin1_code":"26.0",
    "gn:asciiname":"Lugoutan",
    "gn:country_code":"CN",
    "gn:dem":1049,
    "gn:feature_class":"P",
    "gn:feature_code":"PPL",
    "gn:name":"Lugoutan",
    "gn:population":0,
    "gn:timezone":"Asia/Shanghai",
    "iso:country":"CN",
    "name:zho_x_preferred":[
        "\u82a6\u6c9f\u6ee9"
    ],
    "wof:name":"Lugoutan",
    "wof:placetype":"locality"
},
  "geometry": {"coordinates":[110.21338,38.59902],"type":"Point"}
}