{
  "type": "Feature",
  "properties": {
    "gn:admin1_code":"7.0",
    "gn:asciiname":"Heshangpu",
    "gn:country_code":"CN",
    "gn:dem":17,
    "gn:feature_class":"P",
    "gn:feature_code":"PPL",
    "gn:name":"Heshangpu",
    "gn:population":0,
    "gn:timezone":"Asia/Shanghai",
    "iso:country":"CN",
    "name:zho_x_preferred":[
        "\u548c\u5c1a\u57d4"
    ],
    "wof:name":"Heshangpu",
    "wof:placetype":"locality"
},
  "geometry": {"coordinates":[117.86539,24.30751],"type":"Point"}
}