{
  "type": "Feature",
  "properties": {
    "gn:admin1_code":"26.0",
    "gn:asciiname":"Jinyaping",
    "gn:country_code":"CN",
    "gn:dem":600,
    "gn:feature_class":"P",
    "gn:feature_code":"PPL",
    "gn:name":"Jinyaping",
    "gn:population":0,
    "gn:timezone":"Asia/Shanghai",
    "iso:country":"CN",
    "name:zho_x_preferred":[
        "\u91d1\u9e2d\u576a"
    ],
    "wof:name":"Jinyaping",
    "wof:placetype":"locality"
},
  "geometry": {"coordinates":[108.29065,32.74802],"type":"Point"}
}