{
  "type": "Feature",
  "properties": {
    "gn:admin1_code":"29.0",
    "gn:asciiname":"Qingfeng",
    "gn:country_code":"CN",
    "gn:dem":805,
    "gn:feature_class":"P",
    "gn:feature_code":"PPL",
    "gn:name":"Qingfeng",
    "gn:population":0,
    "gn:timezone":"Asia/Shanghai",
    "iso:country":"CN",
    "name:und_x_variant":[
        "\u9752\u67ab"
    ],
    "wof:name":"Qingfeng",
    "wof:placetype":"locality"
},
  "geometry": {"coordinates":[104.01585,27.80557],"type":"Point"}
}