{
  "type": "Feature",
  "properties": {
    "gn:admin1_code":"9",
    "gn:asciiname":"Yuecunji",
    "gn:country_code":"CN",
    "gn:dem":54,
    "gn:feature_class":"P",
    "gn:feature_code":"PPL",
    "gn:name":"Yuecunji",
    "gn:population":0,
    "gn:timezone":"Asia/Shanghai",
    "iso:country":"CN",
    "name:zho_x_preferred":[
        "\u5cb3\u6751\u96c6"
    ],
    "wof:name":"Yuecunji",
    "wof:placetype":"locality"
},
  "geometry": {"coordinates":[115.18935999999999,36.12463],"type":"Point"}
}