{
  "type": "Feature",
  "properties": {
    "gn:admin1_code":"15.0",
    "gn:asciiname":"Jieguanting",
    "gn:country_code":"CN",
    "gn:dem":2094,
    "gn:feature_class":"P",
    "gn:feature_code":"PPL",
    "gn:name":"Jieguanting",
    "gn:population":0,
    "gn:timezone":"Asia/Shanghai",
    "iso:country":"CN",
    "name:und_x_variant":[
        "\u63a5\u5b98\u4ead"
    ],
    "wof:name":"Jieguanting",
    "wof:placetype":"locality"
},
  "geometry": {"coordinates":[105.26064,33.33056],"type":"Point"}
}