{
  "type": "Feature",
  "properties": {
    "gn:admin1_code":"6.0",
    "gn:asciiname":"Ya'er Gaite",
    "gn:country_code":"CN",
    "gn:dem":3183,
    "gn:feature_class":"P",
    "gn:feature_code":"PPL",
    "gn:name":"Ya\u2019er Gaite",
    "gn:population":0,
    "gn:timezone":"Asia/Urumqi",
    "iso:country":"CN",
    "name:und_x_variant":[
        "Ya\u2019er Gaite"
    ],
    "name:zho_x_preferred":[
        "\u4e9a\u5c14\u76d6\u7279"
    ],
    "wof:name":"Ya'er Gaite",
    "wof:placetype":"locality"
},
  "geometry": {"coordinates":[97.40366,35.9676],"type":"Point"}
}