{
  "type": "Feature",
  "properties": {
    "gn:admin1_code":"21.0",
    "gn:asciiname":"Cuiqukou",
    "gn:country_code":"CN",
    "gn:dem":1126,
    "gn:feature_class":"P",
    "gn:feature_code":"PPL",
    "gn:name":"Cuiqukou",
    "gn:population":0,
    "gn:timezone":"Asia/Shanghai",
    "iso:country":"CN",
    "name:zho_x_preferred":[
        "\u5d14\u6e20\u53e3"
    ],
    "wof:name":"Cuiqukou",
    "wof:placetype":"locality"
},
  "geometry": {"coordinates":[106.282,38.0102],"type":"Point"}
}