{
  "type": "Feature",
  "properties": {
    "gn:admin1_code":"32",
    "gn:asciiname":"Jianxing",
    "gn:country_code":"CN",
    "gn:dem":384,
    "gn:feature_class":"P",
    "gn:feature_code":"PPL",
    "gn:name":"Jianxing",
    "gn:population":0,
    "gn:timezone":"Asia/Shanghai",
    "iso:country":"CN",
    "name:deu_x_preferred":[
        "Jianxing"
    ],
    "name:und_x_variant":[
        "Chien-hsing"
    ],
    "wof:name":"Jianxing",
    "wof:placetype":"locality"
},
  "geometry": {"coordinates":[105.85105,31.23855],"type":"Point"}
}