{
  "type": "Feature",
  "properties": {
    "gn:admin1_code":"24.0",
    "gn:asciiname":"Baiziyuancun",
    "gn:country_code":"CN",
    "gn:dem":983,
    "gn:feature_class":"P",
    "gn:feature_code":"PPL",
    "gn:name":"Baiziyuancun",
    "gn:population":0,
    "gn:timezone":"Asia/Shanghai",
    "iso:country":"CN",
    "name:zho_x_preferred":[
        "\u767d\u5b50\u539f\u6751"
    ],
    "wof:name":"Baiziyuancun",
    "wof:placetype":"locality"
},
  "geometry": {"coordinates":[110.56574000000001,36.0044],"type":"Point"}
}