{
  "type": "Feature",
  "properties": {
    "gn:admin1_code":"14.0",
    "gn:asciiname":"Mongda",
    "gn:country_code":"CN",
    "gn:dem":4149,
    "gn:feature_class":"P",
    "gn:feature_code":"PPLF",
    "gn:name":"Mongda",
    "gn:population":0,
    "gn:timezone":"Asia/Urumqi",
    "iso:country":"CN",
    "name:bod_x_preferred":[
        "Mongda"
    ],
    "name:zho_x_preferred":[
        "Mangda"
    ],
    "name:zho_x_variant":[
        "\u832b\u8fbe",
        "Zongzha",
        "\u5b97\u624e"
    ],
    "wof:name":"Mongda",
    "wof:placetype":"locality"
},
  "geometry": {"coordinates":[98.001,31.401],"type":"Point"}
}