{
  "type": "Feature",
  "properties": {
    "gn:admin1_code":"18.0",
    "gn:asciiname":"Dajingbian",
    "gn:country_code":"CN",
    "gn:dem":992,
    "gn:feature_class":"P",
    "gn:feature_code":"PPL",
    "gn:name":"Dajingbian",
    "gn:population":0,
    "gn:timezone":"Asia/Shanghai",
    "iso:country":"CN",
    "name:zho_x_preferred":[
        "\u5927\u4e95\u8fb9"
    ],
    "wof:name":"Dajingbian",
    "wof:placetype":"locality"
},
  "geometry": {"coordinates":[107.494,26.7522],"type":"Point"}
}