{
  "type": "Feature",
  "properties": {
    "gn:admin1_code":"2.0",
    "gn:asciiname":"Wangzibang",
    "gn:country_code":"CN",
    "gn:dem":62,
    "gn:feature_class":"P",
    "gn:feature_code":"PPL",
    "gn:name":"Wangzibang",
    "gn:population":0,
    "gn:timezone":"Asia/Shanghai",
    "iso:country":"CN",
    "name:zho_x_preferred":[
        "\u738b\u5b57\u6d5c"
    ],
    "wof:name":"Wangzibang",
    "wof:placetype":"locality"
},
  "geometry": {"coordinates":[121.31774,29.9452],"type":"Point"}
}