{
  "type": "Feature",
  "properties": {
    "gn:admin1_code":"25.0",
    "gn:asciiname":"Zhangcunwang",
    "gn:country_code":"CN",
    "gn:dem":18,
    "gn:feature_class":"P",
    "gn:feature_code":"PPL",
    "gn:name":"Zhangcunwang",
    "gn:population":0,
    "gn:timezone":"Asia/Shanghai",
    "iso:country":"CN",
    "name:zho_x_preferred":[
        "\u4ec9\u6751\u738b"
    ],
    "wof:name":"Zhangcunwang",
    "wof:placetype":"locality"
},
  "geometry": {"coordinates":[121.23555,37.4551],"type":"Point"}
}