{
  "type": "Feature",
  "properties": {
    "gn:admin1_code":"2.0",
    "gn:asciiname":"Tanlizheng",
    "gn:country_code":"CN",
    "gn:dem":39,
    "gn:feature_class":"P",
    "gn:feature_code":"PPL",
    "gn:name":"Tanlizheng",
    "gn:population":0,
    "gn:timezone":"Asia/Shanghai",
    "iso:country":"CN",
    "name:zho_x_preferred":[
        "\u575b\u91cc\u90d1"
    ],
    "wof:name":"Tanlizheng",
    "wof:placetype":"locality"
},
  "geometry": {"coordinates":[119.56793,29.11883],"type":"Point"}
}