{
  "type": "Feature",
  "properties": {
    "gn:admin1_code":"8.0",
    "gn:asciiname":"Fenglecun",
    "gn:country_code":"CN",
    "gn:dem":54,
    "gn:feature_class":"P",
    "gn:feature_code":"PPL",
    "gn:name":"Fenglecun",
    "gn:population":0,
    "gn:timezone":"Asia/Shanghai",
    "iso:country":"CN",
    "name:zho_x_preferred":[
        "\u4e30\u4e50\u6751"
    ],
    "wof:name":"Fenglecun",
    "wof:placetype":"locality"
},
  "geometry": {"coordinates":[132.57946000000001,47.67769000000001],"type":"Point"}
}