{
  "type": "Feature",
  "properties": {
    "gn:admin1_code":"1.0",
    "gn:asciiname":"Xiangshan",
    "gn:country_code":"CN",
    "gn:dem":38,
    "gn:feature_class":"P",
    "gn:feature_code":"PPLA4",
    "gn:name":"Xiangshan",
    "gn:population":0,
    "gn:timezone":"Asia/Shanghai",
    "iso:country":"CN",
    "name:ceb_x_preferred":[
        "Xiangshan"
    ],
    "name:deu_x_preferred":[
        "Xiangshan"
    ],
    "name:eus_x_preferred":[
        "Xiangshan"
    ],
    "name:fra_x_preferred":[
        "Xiangshan"
    ],
    "name:kor_x_preferred":[
        "\uc0f9\uc0b0\uad6c"
    ],
    "name:nor_x_preferred":[
        "Xiangshan"
    ],
    "name:pol_x_preferred":[
        "Xiangshan"
    ],
    "name:swe_x_preferred":[
        "Xiangshan"
    ],
    "name:und_x_variant":[
        "Hsiang-shan",
        "Xiangshan Zhen",
        "\u5411\u5c71\u9547",
        "Xiangshan"
    ],
    "name:zho_x_preferred":[
        "\u5411\u5c71"
    ],
    "wof:name":"Xiangshan",
    "wof:placetype":"locality"
},
  "geometry": {"coordinates":[118.58682,31.66055],"type":"Point"}
}