{
  "type": "Feature",
  "properties": {
    "gn:admin1_code":"29",
    "gn:asciiname":"Dahuangchuan",
    "gn:country_code":"CN",
    "gn:dem":2013,
    "gn:feature_class":"P",
    "gn:feature_code":"PPL",
    "gn:name":"Dahuangchuan",
    "gn:population":0,
    "gn:timezone":"Asia/Shanghai",
    "iso:country":"CN",
    "name:zho_x_preferred":[
        "\u5927\u8352\u5ddd"
    ],
    "wof:name":"Dahuangchuan",
    "wof:placetype":"locality"
},
  "geometry": {"coordinates":[102.45399999999999,24.5751],"type":"Point"}
}