{
  "type": "Feature",
  "properties": {
    "gn:admin1_code":"15.0",
    "gn:asciiname":"Niba",
    "gn:country_code":"CN",
    "gn:dem":2939,
    "gn:feature_class":"P",
    "gn:feature_code":"PPLA4",
    "gn:name":"Niba",
    "gn:population":0,
    "gn:timezone":"Asia/Shanghai",
    "iso:country":"CN",
    "name:und_x_variant":[
        "\u5c3c\u5df4",
        "Nibaxiang",
        "Niba Xiang",
        "\u5c3c\u5df4\u4e61"
    ],
    "wof:name":"Niba",
    "wof:placetype":"locality"
},
  "geometry": {"coordinates":[103.08458,34.45774],"type":"Point"}
}