{
  "type": "Feature",
  "properties": {
    "gn:admin1_code":"19.0",
    "gn:asciiname":"Xiaokuang Donggou",
    "gn:country_code":"CN",
    "gn:dem":347,
    "gn:feature_class":"P",
    "gn:feature_code":"PPL",
    "gn:name":"Xiaokuang Donggou",
    "gn:population":0,
    "gn:timezone":"Asia/Shanghai",
    "iso:country":"CN",
    "name:und_x_variant":[
        "\u5c0f\u77ff\u6d1e\u6c9f"
    ],
    "wof:name":"Xiaokuang Donggou",
    "wof:placetype":"locality"
},
  "geometry": {"coordinates":[124.23938,41.23018],"type":"Point"}
}