{
  "type": "Feature",
  "properties": {
    "gn:admin1_code":"30",
    "gn:asciiname":"Shanghongshe",
    "gn:country_code":"CN",
    "gn:dem":377,
    "gn:feature_class":"P",
    "gn:feature_code":"PPL",
    "gn:name":"Shanghongshe",
    "gn:population":0,
    "gn:timezone":"Asia/Shanghai",
    "iso:country":"CN",
    "name:zho_x_preferred":[
        "\u4e0a\u6d2a\u756c"
    ],
    "wof:name":"Shanghongshe",
    "wof:placetype":"locality"
},
  "geometry": {"coordinates":[116.11833,24.84119],"type":"Point"}
}