{
  "type": "Feature",
  "properties": {
    "gn:admin1_code":"24",
    "gn:asciiname":"Tansuo",
    "gn:country_code":"CN",
    "gn:dem":1123,
    "gn:feature_class":"P",
    "gn:feature_code":"PPL",
    "gn:name":"Tansuo",
    "gn:population":0,
    "gn:timezone":"Asia/Shanghai",
    "iso:country":"CN",
    "name:und_x_variant":[
        "T\u2019an-su-ts\u2019un",
        "Tansu",
        "Tansuo"
    ],
    "name:zho_x_preferred":[
        "\u575b\u7d22"
    ],
    "wof:name":"Tansuo",
    "wof:placetype":"locality"
},
  "geometry": {"coordinates":[111.41865,36.97769],"type":"Point"}
}