{
  "type": "Feature",
  "properties": {
    "gn:admin1_code":"26.0",
    "gn:asciiname":"Guanyingou",
    "gn:country_code":"CN",
    "gn:dem":1902,
    "gn:feature_class":"P",
    "gn:feature_code":"PPL",
    "gn:name":"Guanyingou",
    "gn:population":0,
    "gn:timezone":"Asia/Shanghai",
    "iso:country":"CN",
    "name:und_x_variant":[
        "\u8d2f\u94f6\u6c9f"
    ],
    "wof:name":"Guanyingou",
    "wof:placetype":"locality"
},
  "geometry": {"coordinates":[106.62801,33.65849],"type":"Point"}
}