{
  "type": "Feature",
  "properties": {
    "gn:admin1_code":"29.0",
    "gn:asciiname":"Rizui",
    "gn:country_code":"CN",
    "gn:dem":2106,
    "gn:feature_class":"P",
    "gn:feature_code":"PPL",
    "gn:name":"Rizui",
    "gn:population":0,
    "gn:timezone":"Asia/Shanghai",
    "iso:country":"CN",
    "name:zho_x_preferred":[
        "\u65e5\u5480"
    ],
    "wof:name":"Rizui",
    "wof:placetype":"locality"
},
  "geometry": {"coordinates":[98.8634,28.2875],"type":"Point"}
}