{
  "type": "Feature",
  "properties": {
    "gn:admin1_code":"29.0",
    "gn:asciiname":"Dashunzhai",
    "gn:country_code":"CN",
    "gn:dem":1052,
    "gn:feature_class":"P",
    "gn:feature_code":"PPL",
    "gn:name":"Dashunzhai",
    "gn:population":0,
    "gn:timezone":"Asia/Shanghai",
    "iso:country":"CN",
    "name:zho_x_preferred":[
        "\u5927\u987a\u5be8"
    ],
    "wof:name":"Dashunzhai",
    "wof:placetype":"locality"
},
  "geometry": {"coordinates":[102.685,23.144],"type":"Point"}
}