{
  "type": "Feature",
  "properties": {
    "gn:admin1_code":"3.0",
    "gn:asciiname":"Dachun",
    "gn:country_code":"CN",
    "gn:dem":169,
    "gn:feature_class":"P",
    "gn:feature_code":"PPLA4",
    "gn:name":"Dachun",
    "gn:population":0,
    "gn:timezone":"Asia/Shanghai",
    "iso:country":"CN",
    "name:und_x_variant":[
        "\u5927\u693f",
        "Dachun Xiang",
        "\u5927\u693f\u4e61"
    ],
    "wof:name":"Dachun",
    "wof:placetype":"locality"
},
  "geometry": {"coordinates":[114.25042999999999,29.11867],"type":"Point"}
}