{
  "type": "Feature",
  "properties": {
    "gn:admin1_code":"29",
    "gn:asciiname":"Bajiaowan",
    "gn:country_code":"CN",
    "gn:dem":1397,
    "gn:feature_class":"P",
    "gn:feature_code":"PPL",
    "gn:name":"Bajiaowan",
    "gn:population":0,
    "gn:timezone":"Asia/Shanghai",
    "iso:country":"CN",
    "name:zho_x_preferred":[
        "\u516b\u89d2\u5f2f"
    ],
    "wof:name":"Bajiaowan",
    "wof:placetype":"locality"
},
  "geometry": {"coordinates":[105.474,23.5436],"type":"Point"}
}