{
  "type": "Feature",
  "properties": {
    "gn:admin1_code":"10",
    "gn:asciiname":"Lianggang",
    "gn:country_code":"CN",
    "gn:dem":278,
    "gn:feature_class":"P",
    "gn:feature_code":"PPL",
    "gn:name":"Lianggang",
    "gn:population":0,
    "gn:timezone":"Asia/Shanghai",
    "iso:country":"CN",
    "wof:name":"Lianggang",
    "wof:placetype":"locality"
},
  "geometry": {"coordinates":[115.04861,39.22389],"type":"Point"}
}