{
  "type": "Feature",
  "properties": {
    "gn:admin1_code":"11.0",
    "gn:asciiname":"Wuxi",
    "gn:country_code":"CN",
    "gn:dem":187,
    "gn:feature_class":"P",
    "gn:feature_code":"PPL",
    "gn:name":"Wuxi",
    "gn:population":0,
    "gn:timezone":"Asia/Shanghai",
    "iso:country":"CN",
    "name:zho_x_preferred":[
        "Wuxi"
    ],
    "name:zho_x_variant":[
        "\u90ac\u6eaa"
    ],
    "wof:name":"Wuxi",
    "wof:placetype":"locality"
},
  "geometry": {"coordinates":[111.13033,29.32091],"type":"Point"}
}