{
  "type": "Feature",
  "properties": {
    "gn:admin1_code":"26.0",
    "gn:asciiname":"Longwancun",
    "gn:country_code":"CN",
    "gn:dem":823,
    "gn:feature_class":"P",
    "gn:feature_code":"PPL",
    "gn:name":"Longwancun",
    "gn:population":0,
    "gn:timezone":"Asia/Shanghai",
    "iso:country":"CN",
    "name:zho_x_preferred":[
        "\u9f99\u6e7e\u6751"
    ],
    "wof:name":"Longwancun",
    "wof:placetype":"locality"
},
  "geometry": {"coordinates":[110.26654000000001,37.51245],"type":"Point"}
}