{
  "type": "Feature",
  "properties": {
    "gn:admin1_code":"24.0",
    "gn:asciiname":"Xia'aocun",
    "gn:country_code":"CN",
    "gn:dem":1452,
    "gn:feature_class":"P",
    "gn:feature_code":"PPL",
    "gn:name":"Xia\u2019aocun",
    "gn:population":0,
    "gn:timezone":"Asia/Shanghai",
    "iso:country":"CN",
    "name:und_x_variant":[
        "Xia\u2019aocun"
    ],
    "name:zho_x_preferred":[
        "\u4e0b\u51f9\u6751"
    ],
    "wof:name":"Xia'aocun",
    "wof:placetype":"locality"
},
  "geometry": {"coordinates":[113.39561999999999,37.21157],"type":"Point"}
}