{
  "type": "Feature",
  "properties": {
    "gn:admin1_code":"05",
    "gn:asciiname":"Madidacun",
    "gn:country_code":"CN",
    "gn:dem":121,
    "gn:feature_class":"P",
    "gn:feature_code":"PPL",
    "gn:name":"Madidacun",
    "gn:population":0,
    "gn:timezone":"Asia/Shanghai",
    "iso:country":"CN",
    "name:und_x_variant":[
        "Ma-ti",
        "Ma-ti-ta",
        "Madida",
        "\u9a6c\u6ef4\u8fbe",
        "Madidacun"
    ],
    "name:zho_x_preferred":[
        "\u9a6c\u6ef4\u8fbe\u6751"
    ],
    "wof:name":"Madidacun",
    "wof:placetype":"locality"
},
  "geometry": {"coordinates":[130.80477999999999,42.92846],"type":"Point"}
}