{
  "type": "Feature",
  "properties": {
    "gn:admin1_code":"8.0",
    "gn:asciiname":"Huolidi",
    "gn:country_code":"CN",
    "gn:dem":255,
    "gn:feature_class":"P",
    "gn:feature_code":"PPL",
    "gn:name":"Huolidi",
    "gn:population":0,
    "gn:timezone":"Asia/Shanghai",
    "iso:country":"CN",
    "name:zho_x_preferred":[
        "\u706b\u7281\u5730"
    ],
    "wof:name":"Huolidi",
    "wof:placetype":"locality"
},
  "geometry": {"coordinates":[126.57964,48.16382],"type":"Point"}
}