{
  "type": "Feature",
  "properties": {
    "gn:admin1_code":"14.0",
    "gn:asciiname":"Lieding",
    "gn:country_code":"CN",
    "gn:dem":4367,
    "gn:feature_class":"P",
    "gn:feature_code":"PPL",
    "gn:name":"Lieding",
    "gn:population":0,
    "gn:timezone":"Asia/Urumqi",
    "iso:country":"CN",
    "name:zho_x_preferred":[
        "\u5217\u5b9a"
    ],
    "wof:name":"Lieding",
    "wof:placetype":"locality"
},
  "geometry": {"coordinates":[86.8702,29.2333],"type":"Point"}
}