{
  "type": "Feature",
  "properties": {
    "gn:admin1_code":"3.0",
    "gn:asciiname":"Chengwenming",
    "gn:country_code":"CN",
    "gn:dem":90,
    "gn:feature_class":"P",
    "gn:feature_code":"PPL",
    "gn:name":"Chengwenming",
    "gn:population":0,
    "gn:timezone":"Asia/Shanghai",
    "iso:country":"CN",
    "name:zho_x_preferred":[
        "\u7a0b\u6587\u660e"
    ],
    "wof:name":"Chengwenming",
    "wof:placetype":"locality"
},
  "geometry": {"coordinates":[117.20132,28.53597],"type":"Point"}
}