{
  "type": "Feature",
  "properties": {
    "gn:admin1_code":"7.0",
    "gn:asciiname":"Jiazhuang",
    "gn:country_code":"CN",
    "gn:dem":244,
    "gn:feature_class":"P",
    "gn:feature_code":"PPL",
    "gn:name":"Jiazhuang",
    "gn:population":0,
    "gn:timezone":"Asia/Shanghai",
    "iso:country":"CN",
    "name:zho_x_preferred":[
        "\u52a0\u5e84"
    ],
    "wof:name":"Jiazhuang",
    "wof:placetype":"locality"
},
  "geometry": {"coordinates":[116.31887999999999,25.10443],"type":"Point"}
}