{
  "type": "Feature",
  "properties": {
    "gn:admin1_code":"25.0",
    "gn:asciiname":"Taoyuanzhuang",
    "gn:country_code":"CN",
    "gn:dem":68,
    "gn:feature_class":"P",
    "gn:feature_code":"PPL",
    "gn:name":"Taoyuanzhuang",
    "gn:population":0,
    "gn:timezone":"Asia/Shanghai",
    "iso:country":"CN",
    "name:zho_x_preferred":[
        "\u6843\u56ed\u5e84"
    ],
    "wof:name":"Taoyuanzhuang",
    "wof:placetype":"locality"
},
  "geometry": {"coordinates":[121.24056000000002,37.20029],"type":"Point"}
}