{
  "type": "Feature",
  "properties": {
    "gn:admin1_code":"18.0",
    "gn:asciiname":"Lengbao",
    "gn:country_code":"CN",
    "gn:dem":439,
    "gn:feature_class":"P",
    "gn:feature_code":"PPL",
    "gn:name":"Lengbao",
    "gn:population":0,
    "gn:timezone":"Asia/Shanghai",
    "iso:country":"CN",
    "name:zho_x_preferred":[
        "\u51b7\u62a5"
    ],
    "wof:name":"Lengbao",
    "wof:placetype":"locality"
},
  "geometry": {"coordinates":[108.24299999999999,26.0407],"type":"Point"}
}