{
  "type": "Feature",
  "properties": {
    "gn:admin1_code":"24.0",
    "gn:asciiname":"Chejiapocun",
    "gn:country_code":"CN",
    "gn:dem":964,
    "gn:feature_class":"P",
    "gn:feature_code":"PPL",
    "gn:name":"Chejiapocun",
    "gn:population":0,
    "gn:timezone":"Asia/Shanghai",
    "iso:country":"CN",
    "name:zho_x_preferred":[
        "\u8f66\u5bb6\u5761\u6751"
    ],
    "wof:name":"Chejiapocun",
    "wof:placetype":"locality"
},
  "geometry": {"coordinates":[110.91941,36.66461],"type":"Point"}
}