{
  "type": "Feature",
  "properties": {
    "gn:admin1_code":"26.0",
    "gn:asciiname":"Dashamao",
    "gn:country_code":"CN",
    "gn:dem":1499,
    "gn:feature_class":"P",
    "gn:feature_code":"PPL",
    "gn:name":"Dashamao",
    "gn:population":0,
    "gn:timezone":"Asia/Shanghai",
    "iso:country":"CN",
    "name:zho_x_preferred":[
        "\u5927\u6c99\u5cc1"
    ],
    "wof:name":"Dashamao",
    "wof:placetype":"locality"
},
  "geometry": {"coordinates":[108.43258,37.3507],"type":"Point"}
}