{
  "type": "Feature",
  "properties": {
    "gn:admin1_code":"10",
    "gn:asciiname":"Dashangguan",
    "gn:country_code":"CN",
    "gn:dem":22,
    "gn:feature_class":"P",
    "gn:feature_code":"PPL",
    "gn:name":"Dashangguan",
    "gn:population":0,
    "gn:timezone":"Asia/Shanghai",
    "iso:country":"CN",
    "name:zho_x_preferred":[
        "\u5927\u4e0a\u5b98"
    ],
    "wof:name":"Dashangguan",
    "wof:placetype":"locality"
},
  "geometry": {"coordinates":[116.11623,37.678],"type":"Point"}
}