{
  "type": "Feature",
  "properties": {
    "gn:admin1_code":"20.0",
    "gn:asciiname":"Yangmushan Wudui",
    "gn:country_code":"CN",
    "gn:dem":331,
    "gn:feature_class":"P",
    "gn:feature_code":"PPLF",
    "gn:name":"Yangmushan Wudui",
    "gn:population":0,
    "gn:timezone":"Asia/Shanghai",
    "iso:country":"CN",
    "name:zho_x_preferred":[
        "\u6768\u6728\u5c71\u4e94\u961f"
    ],
    "wof:name":"Yangmushan Wudui",
    "wof:placetype":"locality"
},
  "geometry": {"coordinates":[124.96256,49.57221],"type":"Point"}
}