{
  "type": "Feature",
  "properties": {
    "gn:admin1_code":"26.0",
    "gn:asciiname":"Leihuayu",
    "gn:country_code":"CN",
    "gn:dem":1069,
    "gn:feature_class":"P",
    "gn:feature_code":"PPL",
    "gn:name":"Leihuayu",
    "gn:population":0,
    "gn:timezone":"Asia/Shanghai",
    "iso:country":"CN",
    "name:zho_x_preferred":[
        "\u96f7\u82b1\u5cea"
    ],
    "wof:name":"Leihuayu",
    "wof:placetype":"locality"
},
  "geometry": {"coordinates":[109.17522,36.38127],"type":"Point"}
}