{
  "type": "Feature",
  "properties": {
    "gn:admin1_code":"16.0",
    "gn:asciiname":"Yangdipo",
    "gn:country_code":"CN",
    "gn:dem":41,
    "gn:feature_class":"P",
    "gn:feature_code":"PPL",
    "gn:name":"Yangdipo",
    "gn:population":0,
    "gn:timezone":"Asia/Shanghai",
    "iso:country":"CN",
    "name:zho_x_preferred":[
        "\u79e7\u5730\u5761"
    ],
    "wof:name":"Yangdipo",
    "wof:placetype":"locality"
},
  "geometry": {"coordinates":[109.52800000000001,21.9348],"type":"Point"}
}