{
  "type": "Feature",
  "properties": {
    "gn:admin1_code":"29.0",
    "gn:asciiname":"Xiawengsan",
    "gn:country_code":"CN",
    "gn:dem":1688,
    "gn:feature_class":"P",
    "gn:feature_code":"PPL",
    "gn:name":"Xiawengsan",
    "gn:population":0,
    "gn:timezone":"Asia/Shanghai",
    "iso:country":"CN",
    "name:zho_x_preferred":[
        "\u4e0b\u7fc1\u6563"
    ],
    "wof:name":"Xiawengsan",
    "wof:placetype":"locality"
},
  "geometry": {"coordinates":[99.696,23.207],"type":"Point"}
}