{
  "type": "Feature",
  "properties": {
    "gn:admin1_code":"4.0",
    "gn:asciiname":"Houyangjia",
    "gn:country_code":"CN",
    "gn:dem":28,
    "gn:feature_class":"P",
    "gn:feature_code":"PPL",
    "gn:name":"Houyangjia",
    "gn:population":0,
    "gn:timezone":"Asia/Shanghai",
    "iso:country":"CN",
    "name:zho_x_preferred":[
        "\u540e\u6768\u5bb6"
    ],
    "wof:name":"Houyangjia",
    "wof:placetype":"locality"
},
  "geometry": {"coordinates":[118.01000000000001,34.4091],"type":"Point"}
}