{
  "type": "Feature",
  "properties": {
    "gn:admin1_code":"29.0",
    "gn:asciiname":"Anaicun",
    "gn:country_code":"CN",
    "gn:dem":2091,
    "gn:feature_class":"P",
    "gn:feature_code":"PPL",
    "gn:name":"Anaicun",
    "gn:population":0,
    "gn:timezone":"Asia/Shanghai",
    "iso:country":"CN",
    "name:zho_x_preferred":[
        "\u963f\u4e43\u6751"
    ],
    "wof:name":"Anaicun",
    "wof:placetype":"locality"
},
  "geometry": {"coordinates":[103.054,25.0576],"type":"Point"}
}