{
  "type": "Feature",
  "properties": {
    "gn:admin1_code":"26.0",
    "gn:asciiname":"Anpo",
    "gn:country_code":"CN",
    "gn:dem":724,
    "gn:feature_class":"P",
    "gn:feature_code":"PPL",
    "gn:name":"Anpo",
    "gn:population":0,
    "gn:timezone":"Asia/Shanghai",
    "iso:country":"CN",
    "name:und_x_variant":[
        "\u5b89\u5761"
    ],
    "wof:name":"Anpo",
    "wof:placetype":"locality"
},
  "geometry": {"coordinates":[107.16401999999999,34.63667],"type":"Point"}
}